{
  "type": "Feature",
  "properties": {
    "addr:full":"Zi Les Aubreaux 16440 Roullet St Estephe Poitou-Charentes 16440",
    "addr:postcode":"16440;16440",
    "addr:street":"Zi Les Aubreaux;St Estephe",
    "iso:country":"FR",
    "sg:address":"Zi Les Aubreaux 16440 Roullet St Estephe",
    "sg:classifiers":[
        {
            "category":"Professional",
            "subcategory":"Engineering",
            "type":"Services"
        }
    ],
    "sg:phone":"+33 5 45 67 94 18",
    "sg:postcode":"16440",
    "sg:province":"Poitou-Charentes",
    "sg:tags":[
        "machine",
        "-",
        "mechanical"
    ],
    "wof:name":"Caravi",
    "wof:placetype":"venue"
},
  "geometry": {"coordinates":[0.046818,45.582775],"type":"Point"}
}