{
  "type": "Feature",
  "properties": {
    "addr:full":"Ccal Leclerc 31120 Roques Midi Pyr\u00e9n\u00e9es 31120",
    "addr:postcode":"31120;31120",
    "iso:country":"FR",
    "sg:address":"Ccal Leclerc 31120 Roques",
    "sg:classifiers":[
        {
            "category":"Health Services",
            "subcategory":"Optometrist",
            "type":"Services"
        }
    ],
    "sg:phone":"+33 5 62 87 64 50",
    "sg:postcode":"31120",
    "sg:province":"Midi Pyr\u00e9n\u00e9es",
    "sg:tags":[
        "instrument",
        "optical",
        "-",
        "precision",
        "equipment"
    ],
    "wof:name":"Tati Optique",
    "wof:placetype":"venue"
},
  "geometry": {"coordinates":[1.398561,43.52187],"type":"Point"}
}