{
  "type": "Feature",
  "properties": {
    "addr:full":"B.P. 267, 01202 Bellegarde sur Valserine C\u00e9dex^^1, Av. Paul Langevin, 01200 Bellegarde sur Valserine Rhone-Alpes 01200",
    "addr:housenumber":"b.p. 267",
    "addr:postcode":"01202;01200;01200",
    "addr:street":"Av. Paul Langevin;Rhone-Alpes",
    "iso:country":"FR",
    "sg:address":"B.P. 267, 01202 Bellegarde sur Valserine C\u00e9dex^^1, Av. Paul Langevin, 01200 Bellegarde sur Valserine",
    "sg:orig_category":"Non-Classified Establishments",
    "sg:phone":"+33 4 50 48 68 08",
    "sg:postcode":"01200",
    "sg:province":"Rhone-Alpes",
    "wof:name":"Etablissements Mouches Devaux S.a.r.l.",
    "wof:placetype":"venue"
},
  "geometry": {"coordinates":[5.80849,46.110901],"type":"Point"}
}