{
  "type": "Feature",
  "properties": {
    "iso:country":"FR",
    "sg:address":"Rue Des Marguerites 92000 Nanterre",
    "sg:classifiers":[
        {
            "category":"Manufacturing",
            "subcategory":"Chemicals & Compounds",
            "type":"Manufacturing & Wholesale Goods"
        }
    ],
    "sg:phone":"+33 1 41 30 10 10",
    "sg:postcode":"92000",
    "sg:province":"Ile de France",
    "sg:tags":[
        "pharmaceutical",
        "chemistry",
        "-",
        "by-product"
    ],
    "wof:name":"L'air Liquide Sa",
    "wof:placetype":"venue"
},
  "geometry": {"coordinates":[2.21981,48.9161],"type":"Point"}
}