{
  "type": "Feature",
  "properties": {
    "iso:country":"FR",
    "sg:address":"18 Rue Auguste Lumi\u00e8re 22000 St Brieuc",
    "sg:city":"Saint-Brieuc",
    "sg:classifiers":[
        {
            "category":"Utilities",
            "subcategory":"Telephone",
            "type":"Services"
        }
    ],
    "sg:phone":"+33 2 96 62 25 25",
    "sg:postcode":"22000",
    "sg:province":"Bretagne",
    "sg:tags":[
        "telecommunication"
    ],
    "wof:name":"L'ete",
    "wof:placetype":"venue"
},
  "geometry": {"coordinates":[-2.731812,48.509361],"type":"Point"}
}