{
  "type": "Feature",
  "properties": {
    "addr:full":"16, av. Jean Jaur\u00e8s, 94607 Choisy le Roi C\u00e9dex Ile-de-France",
    "addr:postcode":"94607",
    "addr:street":"16 Av. Jean Jaure\u0300S",
    "iso:country":"FR",
    "sg:address":"16, av. Jean Jaur\u00e8s, 94607 Choisy le Roi C\u00e9dex",
    "sg:orig_category":"Unclassifiable Establishments",
    "sg:phone":"+33 1 49 78 56 00",
    "sg:province":"Ile-de-France",
    "wof:name":"Lactalis International S.a.",
    "wof:placetype":"venue"
},
  "geometry": {"coordinates":[2.40909,48.762264],"type":"Point"}
}