{
  "type": "Feature",
  "properties": {
    "iso:country":"FR",
    "sg:address":"27, Rue du Four \u00e0 Chaux, 13007 Marseille",
    "sg:orig_category":"Non-Classified Establishments",
    "sg:phone":"+33 4 95 09 38 00",
    "sg:province":"Provence-Alpes-C\u00f4te d'Azur",
    "wof:name":"M.c.o. S.a.r.l. - Marc Crousillat Organisation",
    "wof:placetype":"venue"
},
  "geometry": {"coordinates":[5.355848,43.287926],"type":"Point"}
}