{
  "type": "Feature",
  "properties": {
    "addr:full":"7, Rue de la For\u00eat, 37600 Sennevi\u00e8res Sennevi\u00e8res Centre 37600",
    "addr:housenumber":"7",
    "addr:postcode":"37600;37600",
    "addr:street":"Rue De La Fore\u0302T",
    "iso:country":"FR",
    "sg:address":"7, Rue de la For\u00eat, 37600 Sennevi\u00e8res",
    "sg:city":"Sennevi\u00e8res",
    "sg:orig_category":"Non-Classified Establishments",
    "sg:phone":"+33 2 47 94 72 42",
    "sg:postcode":"37600",
    "sg:province":"Centre",
    "wof:name":"Zajewski E.u.r.l.",
    "wof:placetype":"venue"
},
  "geometry": {"coordinates":[1.102565,47.106815],"type":"Point"}
}