{
  "type": "Feature",
  "properties": {
    "addr:full":"B.P. 79, 78314 Maurepas C\u00e9dex^^8, Rue Amp\u00e8re, 78310 Coigni\u00e8res Ile de France",
    "addr:postcode":"78314;78310;ile",
    "addr:street":"B.P. 79;Rue Ampe\u0300Re",
    "iso:country":"FR",
    "sg:address":"B.P. 79, 78314 Maurepas C\u00e9dex^^8, Rue Amp\u00e8re, 78310 Coigni\u00e8res",
    "sg:orig_category":"Non-Classified Establishments",
    "sg:phone":"+33 1 30 49 40 51",
    "sg:province":"Ile de France",
    "wof:name":"Samsic Ile De France S.a.",
    "wof:placetype":"venue"
},
  "geometry": {"coordinates":[1.944855,48.761749],"type":"Point"}
}