{
  "type": "Feature",
  "properties": {
    "iso:country":"FR",
    "sg:address":"122, Rue Damremont, 75018 Paris",
    "sg:orig_category":"Unclassifiable Establishments",
    "sg:phone":"+33 1 42 55 66 49",
    "sg:province":"Ile de France",
    "wof:name":"Soci\u00e9t\u00e9 D'assistance Technique D'exploitation Et De Maintenance S.a.r.l.",
    "wof:placetype":"venue"
},
  "geometry": {"coordinates":[2.337391,48.89476],"type":"Point"}
}