{
  "type": "Feature",
  "properties": {
    "iso:country":"FR",
    "sg:address":"58, Bd de l'Industrie, 53940 Saint Berthevin",
    "sg:orig_category":"Non-Classified Establishments",
    "sg:phone":"+33 2 43 68 71 63",
    "sg:province":"Pays de Loire",
    "wof:name":"Iss Abilis S.a.s.",
    "wof:placetype":"venue"
},
  "geometry": {"coordinates":[-0.81588,48.06382],"type":"Point"}
}