{
  "type": "Feature",
  "properties": {
    "addr:full":"Rue Marcel Tadur 72140 Sill\u00e9 Le Guillaume Pays de Loire 72140",
    "addr:postcode":"72140;72140",
    "addr:street":"Rue Marcel Tadur;Guillaume Pays;Loire",
    "iso:country":"FR",
    "sg:address":"Rue Marcel Tadur 72140 Sill\u00e9 Le Guillaume",
    "sg:classifiers":[
        {
            "category":"Farming",
            "subcategory":"Farm & Veterinary Services",
            "type":"Manufacturing & Wholesale Goods"
        }
    ],
    "sg:phone":"+33 2 43 20 12 63",
    "sg:postcode":"72140",
    "sg:province":"Pays de Loire",
    "sg:tags":[
        "food",
        "product",
        "breeding",
        "animal",
        "related"
    ],
    "wof:name":"Ouest Nutrition Animale",
    "wof:placetype":"venue"
},
  "geometry": {"coordinates":[-0.210974,48.093803],"type":"Point"}
}