{
  "type": "Feature",
  "properties": {
    "addr:full":"2 rue des Alpes 68390 Sausheim Sausheim Alsace 68390",
    "addr:housenumber":"2",
    "addr:postcode":"68390;68390",
    "addr:street":"Rue Des Alpes;Sausheim",
    "iso:country":"FR",
    "sg:address":"2 rue des Alpes 68390 Sausheim",
    "sg:city":"Sausheim",
    "sg:orig_category":"Sharpening And Setting Machines For Wood Saw Blades",
    "sg:phone":"+33 3 89 61 51 55",
    "sg:postcode":"68390",
    "sg:province":"Alsace",
    "wof:name":"Interholz Raimann Sarl",
    "wof:placetype":"venue"
},
  "geometry": {"coordinates":[7.387655,47.778542],"type":"Point"}
}