{
  "type": "Feature",
  "properties": {
    "addr:full":"Av. Amiral Melchior Lorient Bretagne 56100",
    "addr:postcode":"56100",
    "addr:street":"Av. Amiral Melchior Lorient",
    "iso:country":"FR",
    "sg:address":"Av. Amiral Melchior",
    "sg:city":"Lorient",
    "sg:orig_category":"Unclassifiable Establishments",
    "sg:phone":"+33 2 97 37 30 66",
    "sg:postcode":"56100",
    "sg:province":"Bretagne",
    "wof:name":"Etablissement Le Touze S.a.",
    "wof:placetype":"venue"
},
  "geometry": {"coordinates":[-3.359474,47.737289],"type":"Point"}
}