{
  "type": "Feature",
  "properties": {
    "addr:full":"17, Bd Plombi\u00e8res, 13003 Marseille Provence-Alpes-C\u00f4te d'Azur",
    "addr:housenumber":"17",
    "addr:postcode":"13003",
    "addr:street":"Bd Plombie\u0300Res",
    "iso:country":"FR",
    "sg:address":"17, Bd Plombi\u00e8res, 13003 Marseille",
    "sg:orig_category":"Unclassifiable Establishments",
    "sg:phone":"+33 4 91 62 07 81",
    "sg:province":"Provence-Alpes-C\u00f4te d'Azur",
    "wof:name":"Lenfant S.a.r.l.",
    "wof:placetype":"venue"
},
  "geometry": {"coordinates":[5.387224,43.314999],"type":"Point"}
}