{
  "type": "Feature",
  "properties": {
    "addr:full":"25 Voie Romaine 51450 Betheny Champagne 51450",
    "addr:housenumber":"25",
    "addr:postcode":"51450;51450",
    "addr:street":"Voie Romaine;Champagne",
    "iso:country":"FR",
    "sg:address":"25 Voie Romaine 51450 Betheny",
    "sg:classifiers":[
        {
            "category":"Farming",
            "subcategory":"Livestock Farm",
            "type":"Manufacturing & Wholesale Goods"
        }
    ],
    "sg:phone":"+33 3 26 77 89 89",
    "sg:postcode":"51450",
    "sg:province":"Champagne",
    "sg:tags":[
        "breeding",
        "agriculture",
        "animal"
    ],
    "wof:name":"Les Serres Aquatiques",
    "wof:placetype":"venue"
},
  "geometry": {"coordinates":[4.056661,49.277855],"type":"Point"}
}