{
  "type": "Feature",
  "properties": {
    "addr:full":"ZI de Pommenauque Carentan Basse Normandie 50500",
    "addr:postcode":"50500",
    "addr:street":"Zi De Pommenauque",
    "iso:country":"FR",
    "sg:address":"ZI de Pommenauque",
    "sg:city":"Carentan",
    "sg:orig_category":"Unclassifiable Establishments",
    "sg:phone":"+33 2 33 71 62 70",
    "sg:postcode":"50500",
    "sg:province":"Basse Normandie",
    "wof:name":"Mermonde S.a.",
    "wof:placetype":"venue"
},
  "geometry": {"coordinates":[-1.247078,49.30291],"type":"Point"}
}