{
  "type": "Feature",
  "properties": {
    "addr:full":"72 av Drapeau; Dijon Bourgogne",
    "addr:street":"72 Av Drapeau",
    "iso:country":"FR",
    "sg:address":"72 av Drapeau; Dijon",
    "sg:classifiers":[
        {
            "category":"Banks & Credit Unions",
            "subcategory":"Bank",
            "type":"Services"
        }
    ],
    "sg:phone":"+33 3380713354",
    "sg:province":"Bourgogne",
    "wof:name":"Cr\u00e9dit Agricole",
    "wof:placetype":"venue"
},
  "geometry": {"coordinates":[5.044766,47.339314],"type":"Point"}
}