{
  "type": "Feature",
  "properties": {
    "addr:full":"1242 Route De Norroy Za Ile De France 54700 Pont A Mousson Lorraine 54700",
    "addr:housenumber":"1242",
    "addr:postcode":"54700;54700",
    "addr:street":"Route De Norroy Za Ile De France",
    "iso:country":"FR",
    "sg:address":"1242 Route De Norroy Za Ile De France 54700 Pont A Mousson",
    "sg:classifiers":[
        {
            "category":"Manufacturing",
            "subcategory":"Glass & Minerals",
            "type":"Manufacturing & Wholesale Goods"
        }
    ],
    "sg:phone":"+33 3 83 81 03 77",
    "sg:postcode":"54700",
    "sg:province":"Lorraine",
    "sg:tags":[
        "building",
        "material"
    ],
    "wof:name":"Bati Verre (groupe Alu Girard)",
    "wof:placetype":"venue"
},
  "geometry": {"coordinates":[6.054945,48.902954],"type":"Point"}
}