{
  "type": "Feature",
  "properties": {
    "addr:full":"7, Rue Emile Roux - ZI des Gailletrous, 41260 La Chauss\u00e9e Saint Victor La Chauss\u00e9e-Saint-Victor Centre 41260",
    "addr:housenumber":"7;chausse\u0301e-saint-victor",
    "addr:postcode":"41260;41260",
    "addr:street":"Rue Emile Roux Zi Des Gailletrous;Chausse\u0301E Saint Victor La",
    "iso:country":"FR",
    "sg:address":"7, Rue Emile Roux - ZI des Gailletrous, 41260 La Chauss\u00e9e Saint Victor",
    "sg:city":"La Chauss\u00e9e-Saint-Victor",
    "sg:orig_category":"Non-Classified Establishments",
    "sg:phone":"+33 2 54 56 37 41",
    "sg:postcode":"41260",
    "sg:province":"Centre",
    "wof:name":"Tbr S.a. - Transports Bruno Robert",
    "wof:placetype":"venue"
},
  "geometry": {"coordinates":[1.354592,47.615322],"type":"Point"}
}