{
  "type": "Feature",
  "properties": {
    "iso:country":"FR",
    "sg:address":"Rue Fran\u00e7ois Rochaix 01100 Oyonnax",
    "sg:classifiers":[
        {
            "category":"Manufacturing",
            "subcategory":"Rubber & Plastics",
            "type":"Manufacturing & Wholesale Goods"
        }
    ],
    "sg:phone":"+33 4 74 73 45 13",
    "sg:postcode":"01100",
    "sg:province":"Rhone-Alpes",
    "sg:tags":[
        "metallurgy",
        "finished",
        "-",
        "metalworking",
        "metallic"
    ],
    "wof:name":"Atm Sa",
    "wof:placetype":"venue"
},
  "geometry": {"coordinates":[5.65492,46.270882],"type":"Point"}
}