{
  "type": "Feature",
  "properties": {
    "addr:full":"9 Rue De Saint-Senoch 75017 Paris Ile de France 75017",
    "addr:housenumber":"9",
    "addr:postcode":"75017;75017",
    "addr:street":"Rue De Saint-Senoch",
    "iso:country":"FR",
    "sg:address":"9 Rue De Saint-Senoch 75017 Paris",
    "sg:classifiers":[
        {
            "category":"Manufacturing",
            "subcategory":"Tools & Machinery",
            "type":"Manufacturing & Wholesale Goods"
        }
    ],
    "sg:phone":"+33 1 47 64 40 91",
    "sg:postcode":"75017",
    "sg:province":"Ile de France",
    "sg:tags":[
        "metallurgy",
        "metalworking"
    ],
    "wof:name":"Fran\u00c7ais Importation Representation Et Exportation Sa",
    "wof:placetype":"venue"
},
  "geometry": {"coordinates":[2.293367,48.881702],"type":"Point"}
}