{
  "type": "Feature",
  "properties": {
    "addr:full":"Zone A\u00e9ron Louis Br\u00e9guet 78140 Velizy Villacoublay Ile de France 78140",
    "addr:postcode":"78140;78140",
    "addr:street":"Zone;Louis Bre\u0301Guet",
    "iso:country":"FR",
    "sg:address":"Zone A\u00e9ron Louis Br\u00e9guet 78140 Velizy Villacoublay",
    "sg:classifiers":[
        {
            "category":"Military Area",
            "subcategory":"Air Force Base",
            "type":"Public Place"
        }
    ],
    "sg:phone":"+33 1 46 29 70 00",
    "sg:postcode":"78140",
    "sg:province":"Ile de France",
    "sg:tags":[
        "control",
        "flight",
        "monitoring",
        "equipment"
    ],
    "wof:name":"Sextant Avionique Sa",
    "wof:placetype":"venue"
},
  "geometry": {"coordinates":[2.18246,48.78503],"type":"Point"}
}