{
  "type": "Feature",
  "properties": {
    "iso:country":"FR",
    "sg:address":"995, Rue Beno\u00eet Frachon - ZI de la Motte, 26800 Portes l\u00e8s Valence",
    "sg:orig_category":"Non-Classified Establishments",
    "sg:phone":"+33 4 75 57 92 00",
    "sg:postcode":"26800",
    "sg:province":"Rhone-Alpes",
    "wof:name":"Cubic Industrie Valence S.a.s.",
    "wof:placetype":"venue"
},
  "geometry": {"coordinates":[4.872865,44.893608],"type":"Point"}
}