{
  "type": "Feature",
  "properties": {
    "addr:full":"B.P. 66, 59640 Dunkerque^^14, Rue de la Perche, 59640 Dunkerque Midi Pyr\u00e9n\u00e9es",
    "addr:postcode":"59640;59640",
    "addr:street":"B.P. 66;Rue De La Perche",
    "iso:country":"FR",
    "sg:address":"B.P. 66, 59640 Dunkerque^^14, Rue de la Perche, 59640 Dunkerque",
    "sg:orig_category":"Non-Classified Establishments",
    "sg:phone":"+33 3 28 24 91 91",
    "sg:province":"Midi Pyr\u00e9n\u00e9es",
    "wof:name":"Billiet S.a.r.l.",
    "wof:placetype":"venue"
},
  "geometry": {"coordinates":[2.33656,51.01675],"type":"Point"}
}