{
  "type": "Feature",
  "properties": {
    "addr:full":"R De St Quentin 02110 Bohain En Vermandois Picardie 02110",
    "addr:postcode":"02110;02110",
    "addr:street":"Bohain En Vermandois Picardie",
    "iso:country":"FR",
    "sg:address":"R De St Quentin 02110 Bohain En Vermandois",
    "sg:classifiers":[
        {
            "category":"Shopping",
            "subcategory":"Crafts & Fabrics",
            "type":"Retail Goods"
        }
    ],
    "sg:phone":"+33 3 23 07 51 30",
    "sg:postcode":"02110",
    "sg:province":"Picardie",
    "sg:tags":[
        "textile",
        "clothing"
    ],
    "wof:name":"Noiret Bohain Sa",
    "wof:placetype":"venue"
},
  "geometry": {"coordinates":[3.451367,49.981113],"type":"Point"}
}