{
  "type": "Feature",
  "properties": {
    "addr:full":"Aeroport Charles De Gaulle Batiment 3414b 93290 Tremblay En France Ile de France",
    "addr:housenumber":"3414b",
    "addr:postcode":"93290",
    "addr:street":"Aeroport Charles De Gaulle",
    "iso:country":"FR",
    "sg:address":"Aeroport Charles De Gaulle Batiment 3414b 93290 Tremblay En France",
    "sg:classifiers":[
        {
            "category":"Home & Garden",
            "subcategory":"Furniture",
            "type":"Retail Goods"
        }
    ],
    "sg:phone":"+33 1 48 62 20 20",
    "sg:province":"Ile de France",
    "sg:tags":[
        "wood"
    ],
    "wof:name":"Emballage Sfe",
    "wof:placetype":"venue"
},
  "geometry": {"coordinates":[2.56727,48.951214],"type":"Point"}
}