{
  "type": "Feature",
  "properties": {
    "addr:full":"6, Bd Gambetta, 11100 Narbonne Languedoc-Roussillon",
    "addr:housenumber":"6",
    "addr:postcode":"11100",
    "addr:street":"Bd Gambetta",
    "iso:country":"FR",
    "sg:address":"6, Bd Gambetta, 11100 Narbonne",
    "sg:orig_category":"Unclassifiable Establishments",
    "sg:phone":"+33 4 68 32 15 02",
    "sg:province":"Languedoc-Roussillon",
    "wof:name":"Groupe Sabe S.a.r.l.",
    "wof:placetype":"venue"
},
  "geometry": {"coordinates":[3.007398,43.182159],"type":"Point"}
}