{
  "type": "Feature",
  "properties": {
    "addr:full":"12 rue du Chateau 74950 Scionzier Rhone-Alpes",
    "addr:housenumber":"12",
    "addr:postcode":"74950",
    "addr:street":"Rue Du Chateau",
    "iso:country":"FR",
    "sg:address":"12 rue du Chateau 74950 Scionzier",
    "sg:classifiers":[
        {
            "category":"Wholesale",
            "subcategory":"Auto Parts",
            "type":"Manufacturing & Wholesale Goods"
        }
    ],
    "sg:phone":"+33 4 50 98 34 32",
    "sg:province":"Rhone-Alpes",
    "sg:tags":[
        "machine",
        "screw"
    ],
    "wof:name":"P\u00e9rillat G\u00e9rard Sa",
    "wof:placetype":"venue"
},
  "geometry": {"coordinates":[6.551171,46.060089],"type":"Point"}
}