{
  "type": "Feature",
  "properties": {
    "iso:country":"FR",
    "sg:address":"27, Rue Egalit\u00e9, 95250 Beauchamp",
    "sg:orig_category":"Unclassifiable Establishments",
    "sg:phone":"+33 1 39 95 11 52",
    "sg:province":"Ile de France",
    "wof:name":"Etablissements Olivier S.a.r.l.",
    "wof:placetype":"venue"
},
  "geometry": {"coordinates":[2.186,49.017414],"type":"Point"}
}