{
  "type": "Feature",
  "properties": {
    "addr:full":"8 quai Papacino 06300 Nice",
    "addr:housenumber":"8",
    "addr:postcode":"06300",
    "addr:street":"Quai Papacino",
    "iso:country":"FR",
    "sg:address":"8 quai Papacino 06300 Nice",
    "sg:classifiers":[
        {
            "category":"Government",
            "subcategory":"Department Of Motor Vehicles",
            "type":"Public Place"
        }
    ],
    "sg:phone":"+33 4 92 00 24 36",
    "sg:tags":[
        "image",
        "treatment",
        "digital"
    ],
    "wof:name":"Laboratoire D'imagerie Prof Augerot S.a.",
    "wof:placetype":"venue"
},
  "geometry": {"coordinates":[7.283718,43.697777],"type":"Point"}
}