{
  "type": "Feature",
  "properties": {
    "addr:full":"55 Rue Ludovic Trarieux 59220 Denain Nord Pas-de-Calais 59220",
    "addr:housenumber":"55",
    "addr:postcode":"59220;59220",
    "addr:street":"Rue Ludovic Trarieux",
    "iso:country":"FR",
    "sg:address":"55 Rue Ludovic Trarieux 59220 Denain",
    "sg:classifiers":[
        {
            "category":"Home & Garden",
            "subcategory":"Furniture",
            "type":"Retail Goods"
        }
    ],
    "sg:phone":"+33 3 27 43 30 00",
    "sg:postcode":"59220",
    "sg:province":"Nord Pas-de-Calais",
    "sg:tags":[
        "household",
        "wood"
    ],
    "wof:name":"59 Service Cuisines",
    "wof:placetype":"venue"
},
  "geometry": {"coordinates":[3.398167,50.328709],"type":"Point"}
}