{
  "type": "Feature",
  "properties": {
    "iso:country":"FR",
    "sg:address":"93 Avenue Henri Barbusse 92140 Clamart",
    "sg:classifiers":[
        {
            "category":"Shopping",
            "subcategory":"Clothing, Apparel, & Fashions",
            "type":"Retail Goods"
        }
    ],
    "sg:phone":"+33 1 45 29 07 96",
    "sg:postcode":"92140",
    "sg:province":"Ile de France",
    "sg:tags":[
        "textile",
        "clothing",
        "clothes"
    ],
    "wof:name":"Lea",
    "wof:placetype":"venue"
},
  "geometry": {"coordinates":[2.257972,48.81234],"type":"Point"}
}