{
  "type": "Feature",
  "properties": {
    "iso:country":"FR",
    "sg:address":"La Sauni\u00e8re 89600 Saint Florentin",
    "sg:city":"Ch\u00e9u",
    "sg:orig_category":"Non-Classified Establishments",
    "sg:phone":"+33 3 86 35 02 60",
    "sg:postcode":"89600",
    "sg:province":"Bourgogne",
    "wof:name":"Vulcanic S.a.",
    "wof:placetype":"venue"
},
  "geometry": {"coordinates":[3.72972,48.002575],"type":"Point"}
}