{
  "type": "Feature",
  "properties": {
    "iso:country":"FR",
    "sg:address":"20 Rue Georges Clemenceau 80200 Peronne",
    "sg:classifiers":[
        {
            "category":"Wholesale",
            "subcategory":"Medical Equipment & Supplies",
            "type":"Manufacturing & Wholesale Goods"
        }
    ],
    "sg:phone":"+33 3 22 83 14 22",
    "sg:postcode":"80200",
    "sg:province":"Picardie",
    "sg:tags":[
        "instrument",
        "health",
        "-",
        "precision"
    ],
    "wof:name":"Peronne Protheses",
    "wof:placetype":"venue"
},
  "geometry": {"coordinates":[2.934197,49.930511],"type":"Point"}
}