{
  "type": "Feature",
  "properties": {
    "addr:full":"B.P. 4, 62970 Courcelles l\u00e8s Lens^^85, Rue des Fusill\u00e9s, 62970 Courcelles l\u00e8s Lens Nord Pas-de-Calais",
    "addr:housenumber":"4",
    "addr:postcode":"62970;62970",
    "addr:street":"B.P.;Rue Des Fusille\u0301S",
    "iso:country":"FR",
    "sg:address":"B.P. 4, 62970 Courcelles l\u00e8s Lens^^85, Rue des Fusill\u00e9s, 62970 Courcelles l\u00e8s Lens",
    "sg:orig_category":"Non-Classified Establishments",
    "sg:phone":"+33 3 21 77 10 00",
    "sg:province":"Nord Pas-de-Calais",
    "wof:name":"Sapiso S.a.",
    "wof:placetype":"venue"
},
  "geometry": {"coordinates":[3.012464,50.409458],"type":"Point"}
}