{
  "type": "Feature",
  "properties": {
    "iso:country":"FR",
    "sg:address":"34430 ST JEAN DE VEDAS",
    "sg:orig_category":"Shaped Components Made Of Gypsum Panels",
    "sg:phone":"+33 4 67 17 90 60",
    "sg:province":"Languedoc-Roussillon",
    "wof:name":"Novovis S.a.",
    "wof:placetype":"venue"
},
  "geometry": {"coordinates":[3.83252,43.573292],"type":"Point"}
}