{
  "type": "Feature",
  "properties": {
    "iso:country":"FR",
    "sg:address":"172 Boulevard De La Villette, Vvf J Vermot, 75019 Paris",
    "sg:classifiers":[
        {
            "category":"Banks & Credit Unions",
            "subcategory":"Financial Services",
            "type":"Services"
        }
    ],
    "sg:phone":"+33 1 44 52 46 12",
    "sg:postcode":"75019",
    "sg:province":"Ile de France",
    "sg:tags":[
        "banking",
        "finance",
        "insurance"
    ],
    "wof:name":"Vvl Vacances",
    "wof:placetype":"venue"
},
  "geometry": {"coordinates":[2.38225,48.88237],"type":"Point"}
}