{
  "type": "Feature",
  "properties": {
    "addr:full":"336 Rue Saint-Honor\u00e9 Paris Ile de France 75001",
    "addr:housenumber":"336",
    "addr:postcode":"75001",
    "addr:street":"Rue Saint-Honore\u0301",
    "iso:country":"FR",
    "sg:address":"336 Rue Saint-Honor\u00e9",
    "sg:city":"Paris",
    "sg:classifiers":[
        {
            "category":"Banks & Credit Unions",
            "subcategory":"Financial Services",
            "type":"Services"
        }
    ],
    "sg:phone":"+33 1 55 04 12 12",
    "sg:postcode":"75001",
    "sg:province":"Ile de France",
    "sg:tags":[
        "banking",
        "finance",
        "insurance"
    ],
    "wof:name":"Groupement Interprofessionnel De Participation Effort Constr",
    "wof:placetype":"venue"
},
  "geometry": {"coordinates":[2.330544,48.865818],"type":"Point"}
}