{
  "type": "Feature",
  "properties": {
    "addr:full":"36, Rue Aristide Hurbiez, 62400 B\u00e9thune Nord Pas-de-Calais",
    "addr:housenumber":"36",
    "addr:postcode":"62400",
    "addr:street":"Rue Aristide Hurbiez",
    "iso:country":"FR",
    "sg:address":"36, Rue Aristide Hurbiez, 62400 B\u00e9thune",
    "sg:orig_category":"Non-Classified Establishments",
    "sg:phone":"+33 3 21 56 97 44",
    "sg:province":"Nord Pas-de-Calais",
    "wof:name":"Otessa C'clean S.a.r.l.",
    "wof:placetype":"venue"
},
  "geometry": {"coordinates":[2.639592,50.523781],"type":"Point"}
}