{
  "type": "Feature",
  "properties": {
    "addr:full":"Rue Charles Nungesser Mas Des Cavaliers 34130 Mauguio Languedoc-Roussillon 34130",
    "addr:postcode":"34130;34130",
    "addr:street":"Rue Charles Nungesser Mas Des Cavaliers",
    "iso:country":"FR",
    "sg:address":"Rue Charles Nungesser Mas Des Cavaliers 34130 Mauguio",
    "sg:classifiers":[
        {
            "category":"Wholesale",
            "subcategory":"Machinery & Supplies",
            "type":"Manufacturing & Wholesale Goods"
        }
    ],
    "sg:phone":"+33 4 67 20 08 06",
    "sg:postcode":"34130",
    "sg:province":"Languedoc-Roussillon",
    "sg:tags":[
        "handling",
        "material",
        "-",
        "machine",
        "equipment",
        "engineering",
        "mechanical"
    ],
    "wof:name":"Otis",
    "wof:placetype":"venue"
},
  "geometry": {"coordinates":[3.93489,43.58704],"type":"Point"}
}