{
  "type": "Feature",
  "properties": {
    "addr:full":"8, Rue du G\u00e9n\u00e9ral Leclerc, 27000 Evreux Haute Normandie 27000",
    "addr:housenumber":"8",
    "addr:postcode":"27000;27000",
    "addr:street":"Rue Du Ge\u0301Ne\u0301Ral Leclerc;Haute Normandie",
    "iso:country":"FR",
    "sg:address":"8, Rue du G\u00e9n\u00e9ral Leclerc, 27000 Evreux",
    "sg:orig_category":"Non-Classified Establishments",
    "sg:phone":"+33 2 32 31 12 12",
    "sg:postcode":"27000",
    "sg:province":"Haute Normandie",
    "wof:name":"Copy M\u00e9dia S.a.",
    "wof:placetype":"venue"
},
  "geometry": {"coordinates":[1.147225,49.027657],"type":"Point"}
}