{
  "type": "Feature",
  "properties": {
    "iso:country":"FR",
    "sg:address":"8, Rue du G\u00e9n\u00e9ral Leclerc, 27000 Evreux",
    "sg:orig_category":"Non-Classified Establishments",
    "sg:phone":"+33 2 32 31 12 12",
    "sg:postcode":"27000",
    "sg:province":"Haute Normandie",
    "wof:name":"Copy M\u00e9dia S.a.",
    "wof:placetype":"venue"
},
  "geometry": {"coordinates":[1.147225,49.027657],"type":"Point"}
}