{
  "type": "Feature",
  "properties": {
    "iso:country":"FR",
    "sg:address":"28, Place du March\u00e9, 57400 Sarrebourg",
    "sg:orig_category":"Unclassifiable Establishments",
    "sg:phone":"+33 3 87 03 24 34",
    "sg:province":"Lorraine",
    "wof:name":"Herrmann S.a.",
    "wof:placetype":"venue"
},
  "geometry": {"coordinates":[7.052024,48.735184],"type":"Point"}
}