{
  "type": "Feature",
  "properties": {
    "addr:full":"259, Av. des Caniers - ZI des Paluds, 13400 Aubagne",
    "addr:postcode":"13400",
    "addr:street":"259 Av. Des Caniers Zi Des Paluds",
    "iso:country":"FR",
    "sg:address":"259, Av. des Caniers - ZI des Paluds, 13400 Aubagne",
    "sg:orig_category":"Non-Classified Establishments",
    "sg:phone":"+33 4 42 84 41 71",
    "wof:name":"Optimadata S.a.r.l.",
    "wof:placetype":"venue"
},
  "geometry": {"coordinates":[5.5687,43.292141],"type":"Point"}
}