{
  "type": "Feature",
  "properties": {
    "iso:country":"FR",
    "sg:address":"Av. de la Dev\u00e8ze - Z.I. du Capiscol",
    "sg:city":"B\u00e9ziers",
    "sg:orig_category":"Unclassifiable Establishments",
    "sg:phone":"+33 4 67 76 74 19",
    "sg:postcode":"34500",
    "sg:province":"Languedoc-Roussillon",
    "wof:name":"Innova S.a.",
    "wof:placetype":"venue"
},
  "geometry": {"coordinates":[3.216105,43.344234],"type":"Point"}
}