{
  "type": "Feature",
  "properties": {
    "addr:full":"Zone Industrielle Sousbiscain Villers sous Saint Leu Picardie 60340",
    "addr:postcode":"60340",
    "addr:street":"Zone Industrielle Sousbiscain Villers Sous Saint;Picardie",
    "iso:country":"FR",
    "sg:address":"Zone Industrielle Sousbiscain",
    "sg:city":"Villers sous Saint Leu",
    "sg:orig_category":"Non-Classified Establishments",
    "sg:phone":"+33 3 44 56 85 70",
    "sg:postcode":"60340",
    "sg:province":"Picardie",
    "wof:name":"S.s.m.i. S.a. - Soci\u00e9t\u00e9 Sp\u00e9cialis\u00e9e Dans Le Mat\u00e9riel D'imprimerie",
    "wof:placetype":"venue"
},
  "geometry": {"coordinates":[2.398079,49.210522],"type":"Point"}
}