{
  "type": "Feature",
  "properties": {
    "addr:full":"8 Rue Jacques Coeur 03400 Yzeure Yzeure Auvergne 03400",
    "addr:housenumber":"8",
    "addr:postcode":"03400;03400",
    "addr:street":"Rue Jacques Coeur",
    "iso:country":"FR",
    "sg:address":"8 Rue Jacques Coeur 03400 Yzeure",
    "sg:city":"Yzeure",
    "sg:classifiers":[
        {
            "category":"Food & Beverages",
            "subcategory":"Fruits & Vegetables",
            "type":"Retail Goods"
        }
    ],
    "sg:phone":"+33 4 70 44 90 30",
    "sg:postcode":"03400",
    "sg:province":"Auvergne",
    "sg:tags":[
        "preserve",
        "cake",
        "product",
        "related",
        "bread"
    ],
    "wof:name":"Cba Sa",
    "wof:placetype":"venue"
},
  "geometry": {"coordinates":[3.351116,46.574207],"type":"Point"}
}