{
  "type": "Feature",
  "properties": {
    "iso:country":"FR",
    "sg:address":"6, Rue Jean Bart - Technoparc, 31670 Lab\u00e8ge",
    "sg:orig_category":"Unclassifiable Establishments",
    "sg:phone":"+33 5 61 00 15 00",
    "sg:province":"Midi Pyr\u00e9n\u00e9es",
    "wof:name":"B.p.i. Leroy Consultants S.a.",
    "wof:placetype":"venue"
},
  "geometry": {"coordinates":[1.527111,43.529713],"type":"Point"}
}