{
  "type": "Feature",
  "properties": {
    "addr:full":"96 R Louis Lumi\u00e8re 54230 Neuves Maisons Lorraine 54230",
    "addr:housenumber":"96",
    "addr:postcode":"54230;54230",
    "addr:street":"R Louis Lumie\u0300Re",
    "iso:country":"FR",
    "sg:address":"96 R Louis Lumi\u00e8re 54230 Neuves Maisons",
    "sg:classifiers":[
        {
            "category":"Shopping",
            "subcategory":"Clothing, Apparel, & Fashions",
            "type":"Retail Goods"
        }
    ],
    "sg:phone":"+33 3 83 26 44 40",
    "sg:postcode":"54230",
    "sg:province":"Lorraine",
    "sg:tags":[
        "textile",
        "clothing",
        "clothes"
    ],
    "wof:name":"Sarl Marion Productions",
    "wof:placetype":"venue"
},
  "geometry": {"coordinates":[6.090888,48.616741],"type":"Point"}
}