{
  "type": "Feature",
  "properties": {
    "addr:full":"10, Rue Jean Monnet, 94270 Le Kremlin Bic\u00eatre Ile de France",
    "addr:housenumber":"10",
    "addr:postcode":"94270",
    "addr:street":"Rue Jean Monnet",
    "iso:country":"FR",
    "sg:address":"10, Rue Jean Monnet, 94270 Le Kremlin Bic\u00eatre",
    "sg:orig_category":"Non-Classified Establishments",
    "sg:phone":"+33 6 72 80 47 83",
    "sg:province":"Ile de France",
    "wof:name":"Information Document S.a.r.l.",
    "wof:placetype":"venue"
},
  "geometry": {"coordinates":[2.359713,48.808887],"type":"Point"}
}