{
  "type": "Feature",
  "properties": {
    "addr:full":"141 bis de Saussure; Paris; 75017 Ile de France",
    "addr:housenumber":"141 bis",
    "addr:postcode":"75017 ile",
    "addr:street":"De Saussure",
    "iso:country":"FR",
    "sg:address":"141 bis",
    "sg:city":"de Saussure; Paris; 75017",
    "sg:classifiers":[
        {
            "category":"Industrial Area",
            "type":"Public Place"
        }
    ],
    "sg:phone":"+33 1 47 64 33 45",
    "sg:province":"Ile de France",
    "sg:tags":[
        "large",
        "private"
    ],
    "wof:name":"Groupe Partouche Sa",
    "wof:placetype":"venue"
},
  "geometry": {"coordinates":[2.306718,48.889324],"type":"Point"}
}