{
  "type": "Feature",
  "properties": {
    "addr:full":"17 Bis Rue Jean Xxiii 80000 Amiens Picardie 80000",
    "addr:housenumber":"17 bis",
    "addr:postcode":"rue;80000;80000",
    "addr:street":"Jean Xxiii",
    "iso:country":"FR",
    "sg:address":"17 Bis Rue Jean Xxiii 80000 Amiens",
    "sg:classifiers":[
        {
            "category":"Manufacturing",
            "subcategory":"Metals",
            "type":"Manufacturing & Wholesale Goods"
        }
    ],
    "sg:phone":"+33 3 22 91 72 53",
    "sg:postcode":"80000",
    "sg:province":"Picardie",
    "sg:tags":[
        "-",
        "machine",
        "equipment",
        "engineering",
        "machinery",
        "mechanical"
    ],
    "wof:name":"Entreprise Generale De Peinture Bouchez",
    "wof:placetype":"venue"
},
  "geometry": {"coordinates":[2.306972,49.894402],"type":"Point"}
}