{
  "type": "Feature",
  "properties": {
    "iso:country":"FR",
    "sg:address":"56, Rue Pfastatt, 68110 Illzach",
    "sg:city":"Illzach",
    "sg:orig_category":"Unclassifiable Establishments",
    "sg:phone":"+33 3 89 53 34 69",
    "sg:postcode":"68110",
    "sg:province":"Alsace",
    "wof:name":"Brumer S.a.r.l.",
    "wof:placetype":"venue"
},
  "geometry": {"coordinates":[7.339858,47.780636],"type":"Point"}
}