{
  "type": "Feature",
  "properties": {
    "iso:country":"FR",
    "sg:address":"Rue du Bompas - ZI du Bompas",
    "sg:city":"Chemill\u00e9",
    "sg:orig_category":"Non-Classified Establishments",
    "sg:phone":"+33 2 41 30 55 08",
    "sg:postcode":"49120",
    "sg:province":"Pays de Loire",
    "wof:name":"Les Ateliers Alla S.a.r.l.",
    "wof:placetype":"venue"
},
  "geometry": {"coordinates":[-0.697404,47.144993],"type":"Point"}
}