{
  "type": "Feature",
  "properties": {
    "iso:country":"FR",
    "sg:address":"81, Bd Carnot - Immeuble Cap Wilson, 31000 Toulouse",
    "sg:orig_category":"Unclassifiable Establishments",
    "sg:phone":"+33 5 61 23 98 99",
    "sg:province":"Midi Pyr\u00e9n\u00e9es",
    "wof:name":"Euro R.s.c.g. Futurs S.a.",
    "wof:placetype":"venue"
},
  "geometry": {"coordinates":[1.44955,43.604889],"type":"Point"}
}