{
  "type": "Feature",
  "properties": {
    "iso:country":"FR",
    "sg:address":"2, Rue Coudraies, 17250 Saint Porchaire",
    "sg:orig_category":"Unclassifiable Establishments",
    "sg:phone":"+33 5 46 95 60 07",
    "sg:province":"Poitou-Charentes",
    "wof:name":"Etablissements Bouquet Fr\u00e8res S.a.",
    "wof:placetype":"venue"
},
  "geometry": {"coordinates":[-0.780819,45.822266],"type":"Point"}
}