{
  "type": "Feature",
  "properties": {
    "iso:country":"FR",
    "sg:address":"RN 193",
    "sg:city":"Furiani",
    "sg:orig_category":"Non-Classified Establishments",
    "sg:phone":"+33 4 95 59 20 90",
    "sg:postcode":"20600",
    "sg:province":"Corse",
    "wof:name":"Canazzi Et Fils S.a.",
    "wof:placetype":"venue"
},
  "geometry": {"coordinates":[9.415856,42.658413],"type":"Point"}
}