{
  "type": "Feature",
  "properties": {
    "addr:full":"12 rue de Bruxelles 69100 Villeurbanne Rhone-Alpes 69100",
    "addr:housenumber":"12",
    "addr:postcode":"69100;69100",
    "addr:street":"Rue De Bruxelles",
    "iso:country":"FR",
    "sg:address":"12 rue de Bruxelles 69100 Villeurbanne",
    "sg:classifiers":[
        {
            "category":"Manufacturing",
            "subcategory":"Textiles",
            "type":"Manufacturing & Wholesale Goods"
        }
    ],
    "sg:phone":"+33 4 78 89 86 35",
    "sg:postcode":"69100",
    "sg:province":"Rhone-Alpes",
    "sg:tags":[
        "cloth",
        "fleece",
        "made"
    ],
    "wof:name":"Ets Henri Revillet Et Succ Pierre Leger S.a.",
    "wof:placetype":"venue"
},
  "geometry": {"coordinates":[4.868252,45.77729],"type":"Point"}
}