{
  "type": "Feature",
  "properties": {
    "addr:full":"39, Rte de Rouen, 80132 Mareuil Caubert Picardie",
    "addr:housenumber":"39",
    "addr:postcode":"80132",
    "addr:street":"Rte De Rouen",
    "iso:country":"FR",
    "sg:address":"39, Rte de Rouen, 80132 Mareuil Caubert",
    "sg:orig_category":"Unclassifiable Establishments",
    "sg:phone":"+33 3 22 20 16 20",
    "sg:province":"Picardie",
    "wof:name":"E.a.m. S.a. - Entreprise Abbevilloise De Miroiterie",
    "wof:placetype":"venue"
},
  "geometry": {"coordinates":[1.814671,50.084667],"type":"Point"}
}