{
  "type": "Feature",
  "properties": {
    "iso:country":"FR",
    "sg:address":"Rue Charles Laveran 11401 CASTELNAUDARY CEDEX",
    "sg:classifiers":[
        {
            "category":"Farming",
            "subcategory":"Fish & Marine Products",
            "type":"Manufacturing & Wholesale Goods"
        }
    ],
    "sg:phone":"+33 4 68 94 52 10",
    "sg:province":"Languedoc-Roussillon",
    "sg:tags":[
        "organic"
    ],
    "wof:name":"Brugier Sillon Sa",
    "wof:placetype":"venue"
},
  "geometry": {"coordinates":[1.95976,43.303886],"type":"Point"}
}