{
  "type": "Feature",
  "properties": {
    "iso:country":"FR",
    "sg:address":"3, Rue de Bitburg, 08300 Rethel",
    "sg:city":"Bergnicourt",
    "sg:orig_category":"Non-Classified Establishments",
    "sg:phone":"+33 3 24 38 04 48",
    "sg:postcode":"08300",
    "sg:province":"Champagne",
    "wof:name":"Eclair S\u00e9curit\u00e9 S.a.s.",
    "wof:placetype":"venue"
},
  "geometry": {"coordinates":[4.384465,49.506027],"type":"Point"}
}