{
  "type": "Feature",
  "properties": {
    "iso:country":"FR",
    "sg:address":"Rte du Barrage",
    "sg:city":"La Richardais",
    "sg:orig_category":"Unclassifiable Establishments",
    "sg:phone":"+33 2 99 88 55 90",
    "sg:postcode":"35780",
    "sg:province":"Bretagne",
    "wof:name":"Emeraude Jardins S.a.r.l.",
    "wof:placetype":"venue"
},
  "geometry": {"coordinates":[-2.038343,48.61375],"type":"Point"}
}