{
  "type": "Feature",
  "properties": {
    "iso:country":"FR",
    "sg:address":"Rue Francois Jacob Zi 62800 Li\u00e9vin",
    "sg:classifiers":[
        {
            "category":"Structure",
            "subcategory":"Public Building",
            "type":"Public Place"
        }
    ],
    "sg:phone":"+33 3 21 29 15 15",
    "sg:postcode":"62800",
    "sg:province":"Nord Pas-de-Calais",
    "sg:tags":[
        "telecommunicat",
        "household",
        "work",
        "appliance",
        "construction",
        "audio-visual"
    ],
    "wof:name":"Entreprise Hejnal",
    "wof:placetype":"venue"
},
  "geometry": {"coordinates":[2.779565,50.4216],"type":"Point"}
}