{
  "type": "Feature",
  "properties": {
    "iso:country":"FR",
    "sg:address":"B.P. 305, 64103 Bayonne C\u00e9dex^^36, All\u00e9e Marines, 64100 Bayonne",
    "sg:city":"Bayonne",
    "sg:orig_category":"Non-Classified Establishments",
    "sg:phone":"+33 5 59 25 32 60",
    "sg:postcode":"64100",
    "sg:province":"Aquitaine",
    "wof:name":"B.f.c.c. - Banque Fran\u00e7aise De Cr\u00e9dit Coop\u00e9ratif",
    "wof:placetype":"venue"
},
  "geometry": {"coordinates":[-1.476364,43.492741],"type":"Point"}
}