{
  "type": "Feature",
  "properties": {
    "addr:full":"Za De Fareins 01480 Fareins Rhone-Alpes 01480",
    "addr:postcode":"01480;01480",
    "addr:street":"Za De Fareins",
    "iso:country":"FR",
    "sg:address":"Za De Fareins 01480 Fareins",
    "sg:classifiers":[
        {
            "category":"Utilities",
            "subcategory":"Electric",
            "type":"Services"
        }
    ],
    "sg:phone":"+33 4 74 09 57 82",
    "sg:postcode":"01480",
    "sg:province":"Rhone-Alpes",
    "sg:tags":[
        "electricity",
        "electronic",
        "electrical",
        "equipment"
    ],
    "wof:name":"Adte",
    "wof:placetype":"venue"
},
  "geometry": {"coordinates":[4.76135,46.018681],"type":"Point"}
}