{
  "type": "Feature",
  "properties": {
    "iso:country":"FR",
    "sg:address":"20, Rue d'Isly, 35000 Rennes",
    "sg:city":"Rennes",
    "sg:orig_category":"Unclassifiable Establishments",
    "sg:phone":"+33 2 99 85 87 87",
    "sg:postcode":"35000",
    "sg:province":"Bretagne",
    "wof:name":"National Tours S.a.",
    "wof:placetype":"venue"
},
  "geometry": {"coordinates":[-1.67774,48.106911],"type":"Point"}
}