{
  "type": "Feature",
  "properties": {
    "addr:full":"2 Rue De La Pierre Large 67004 Strasbourg Strasbourg Alsace 67000",
    "addr:housenumber":"2",
    "addr:postcode":"67004;67000",
    "addr:street":"Rue De La Pierre Large",
    "iso:country":"FR",
    "sg:address":"2 Rue De La Pierre Large 67004 Strasbourg",
    "sg:city":"Strasbourg",
    "sg:classifiers":[
        {
            "category":"Professional",
            "subcategory":"Business Services",
            "type":"Services"
        }
    ],
    "sg:phone":"+33 3 88 76 75 88",
    "sg:postcode":"67000",
    "sg:province":"Alsace",
    "sg:tags":[
        "training",
        "advice"
    ],
    "wof:name":"College Episc St Etienne Petit Seminaire",
    "wof:placetype":"venue"
},
  "geometry": {"coordinates":[7.755989,48.582741],"type":"Point"}
}