{
  "type": "Feature",
  "properties": {
    "iso:country":"FR",
    "sg:address":"56, Av. Avogadro - ZI des Cadesteaux, 13340 Rognac",
    "sg:orig_category":"Non-Classified Establishments",
    "sg:phone":"+33 4 42 34 70 25",
    "sg:province":"Provence-Alpes-C\u00f4te d'Azur",
    "wof:name":"P.m.p. S.a.r.l. - Pr\u00e9cision M\u00e9canique Phoc\u00e9enne",
    "wof:placetype":"venue"
},
  "geometry": {"coordinates":[5.229803,43.48933],"type":"Point"}
}