{
  "type": "Feature",
  "properties": {
    "addr:full":"10 Rue De Stockholm 75008 Paris Ile de France 75008",
    "addr:housenumber":"10",
    "addr:postcode":"75008;75008",
    "addr:street":"Rue De Stockholm",
    "iso:country":"FR",
    "sg:address":"10 Rue De Stockholm 75008 Paris",
    "sg:classifiers":[
        {
            "category":"Professional",
            "subcategory":"Engineering",
            "type":"Services"
        }
    ],
    "sg:phone":"+33 1 45 22 04 12",
    "sg:postcode":"75008",
    "sg:province":"Ile de France",
    "sg:tags":[
        "machine",
        "-",
        "mechanical"
    ],
    "wof:name":"Equipage Sarl",
    "wof:placetype":"venue"
},
  "geometry": {"coordinates":[2.321986,48.877171],"type":"Point"}
}