{
  "type": "Feature",
  "properties": {
    "addr:full":"50, Rue de Picpus, 75012 Paris Ile de France",
    "addr:housenumber":"50",
    "addr:postcode":"75012",
    "addr:street":"Rue De Picpus",
    "iso:country":"FR",
    "sg:address":"50, Rue de Picpus, 75012 Paris",
    "sg:orig_category":"Unclassifiable Establishments",
    "sg:phone":"+33 1 43 43 90 00",
    "sg:province":"Ile de France",
    "wof:name":"B.m. Et Associ\u00e9s S.a.",
    "wof:placetype":"venue"
},
  "geometry": {"coordinates":[2.396271,48.84388],"type":"Point"}
}