{
  "type": "Feature",
  "properties": {
    "addr:full":"ZI la Rochette Josselin Bretagne 56120",
    "addr:postcode":"56120",
    "addr:street":"Zi La Rochette Josselin Bretagne",
    "iso:country":"FR",
    "sg:address":"ZI la Rochette",
    "sg:city":"Josselin",
    "sg:orig_category":"Non-Classified Establishments",
    "sg:phone":"+33 2 97 22 30 30",
    "sg:postcode":"56120",
    "sg:province":"Bretagne",
    "wof:name":"Etablissements Boucicaud S.a.r.l.",
    "wof:placetype":"venue"
},
  "geometry": {"coordinates":[-2.545454,47.961281],"type":"Point"}
}