{
  "type": "Feature",
  "properties": {
    "addr:full":"252, Rue du Flocon - ZA les Peupliers, 59200 Tourcoing Nord Pas-de-Calais",
    "addr:housenumber":"252",
    "addr:postcode":"59200",
    "addr:street":"Rue Du Flocon Za Les Peupliers",
    "iso:country":"FR",
    "sg:address":"252, Rue du Flocon - ZA les Peupliers, 59200 Tourcoing",
    "sg:orig_category":"Non-Classified Establishments",
    "sg:phone":"+33 3 20 26 46 98",
    "sg:province":"Nord Pas-de-Calais",
    "wof:name":"Studio Set S.a.r.l.",
    "wof:placetype":"venue"
},
  "geometry": {"coordinates":[3.159375,50.722389],"type":"Point"}
}