{
  "type": "Feature",
  "properties": {
    "addr:full":"40 Rue Laurent Cavalier 02230 Fresnoy Le Grand Picardie 02230",
    "addr:housenumber":"40",
    "addr:postcode":"02230;02230",
    "addr:street":"Rue Laurent Cavalier;Picardie",
    "iso:country":"FR",
    "sg:address":"40 Rue Laurent Cavalier 02230 Fresnoy Le Grand",
    "sg:classifiers":[
        {
            "category":"Manufacturing",
            "subcategory":"Textiles",
            "type":"Manufacturing & Wholesale Goods"
        }
    ],
    "sg:phone":"+33 3 23 09 84 42",
    "sg:postcode":"02230",
    "sg:province":"Picardie",
    "sg:tags":[
        "linen",
        "clothing",
        "fabric"
    ],
    "wof:name":"Theatuft",
    "wof:placetype":"venue"
},
  "geometry": {"coordinates":[3.41765,49.946415],"type":"Point"}
}