{
  "type": "Feature",
  "properties": {
    "iso:country":"FR",
    "sg:address":"B.P. CE 2914, 91029 Evry C\u00e9dex^^2, Rue du Bois Chaland, 91090 Lisses",
    "sg:orig_category":"Non-Classified Establishments",
    "sg:phone":"+33 1 69 11 38 21",
    "sg:postcode":"91090",
    "sg:province":"Ile de France",
    "wof:name":"Buhrs France S.n.c.",
    "wof:placetype":"venue"
},
  "geometry": {"coordinates":[2.423843,48.597694],"type":"Point"}
}