{
  "type": "Feature",
  "properties": {
    "addr:full":"Lieu Dit Les Auberges 69770 Longessaigne Rhone-Alpes 69770",
    "addr:postcode":"69770;69770",
    "addr:street":"Lieu Dit Les Auberges;Rhone-Alpes",
    "iso:country":"FR",
    "sg:address":"Lieu Dit Les Auberges 69770 Longessaigne",
    "sg:classifiers":[
        {
            "category":"Home & Garden",
            "subcategory":"Furniture",
            "type":"Retail Goods"
        }
    ],
    "sg:phone":"+33 4 74 70 13 51",
    "sg:postcode":"69770",
    "sg:province":"Rhone-Alpes",
    "sg:tags":[
        "wood"
    ],
    "wof:name":"Service Menuiserie Charpente Journet (s.m.c Journet)",
    "wof:placetype":"venue"
},
  "geometry": {"coordinates":[4.4413,45.793495],"type":"Point"}
}