{
  "type": "Feature",
  "properties": {
    "iso:country":"FR",
    "sg:address":"96 Bd Montparnasse 75680 Paris Cedex 14",
    "sg:classifiers":[
        {
            "category":"Professional",
            "subcategory":"Printing & Photocopies",
            "type":"Services"
        }
    ],
    "sg:phone":"+33 1 44 10 75 75",
    "sg:province":"\u00cele-de-France",
    "sg:tags":[
        "publishing"
    ],
    "wof:name":"Diff Edit Sa",
    "wof:placetype":"venue"
},
  "geometry": {"coordinates":[2.327554,48.842476],"type":"Point"}
}