{
  "type": "Feature",
  "properties": {
    "iso:country":"FR",
    "sg:address":"Rive Droite De La Somme BP 37 80101 Abbeville Cedex",
    "sg:city":"Vill\u00e9",
    "sg:classifiers":[
        {
            "category":"Manufacturing",
            "subcategory":"Tools & Machinery",
            "type":"Manufacturing & Wholesale Goods"
        }
    ],
    "sg:phone":"+33 810 10 88 01",
    "sg:postcode":"67220",
    "sg:province":"Alsace",
    "sg:tags":[
        "environment",
        "equipment",
        "-"
    ],
    "wof:name":"Generale Des Eaux",
    "wof:placetype":"venue"
},
  "geometry": {"coordinates":[1.811973,50.111095],"type":"Point"}
}