{
  "type": "Feature",
  "properties": {
    "addr:full":"3 Rue Gustave Madiot 91070 Bondoufle Ile de France 91070",
    "addr:housenumber":"3",
    "addr:postcode":"91070;ile;91070",
    "addr:street":"Rue Gustave Madiot;France",
    "iso:country":"FR",
    "sg:address":"3 Rue Gustave Madiot 91070 Bondoufle",
    "sg:classifiers":[
        {
            "category":"Manufacturing",
            "subcategory":"Tools & Machinery",
            "type":"Manufacturing & Wholesale Goods"
        }
    ],
    "sg:phone":"+33 1 60 86 41 58",
    "sg:postcode":"91070",
    "sg:province":"Ile de France",
    "sg:tags":[
        "metallurgy",
        "metalworking"
    ],
    "wof:name":"Ets Grincourt Sarl",
    "wof:placetype":"venue"
},
  "geometry": {"coordinates":[2.366611,48.603138],"type":"Point"}
}