{
  "type": "Feature",
  "properties": {
    "addr:full":"246 Chem Des Pommi\u00e8res 69400 Villefranche Sur S\u00e2one Rhone-Alpes 69400",
    "addr:housenumber":"246;sa\u0302one",
    "addr:postcode":"69400;69400",
    "addr:street":"Chem Des Pommie\u0300Res;Rhone-Alpes",
    "iso:country":"FR",
    "sg:address":"246 Chem Des Pommi\u00e8res 69400 Villefranche Sur S\u00e2one",
    "sg:orig_category":"Miscellaneous Products",
    "sg:phone":"+33 4 74 09 40 20",
    "sg:postcode":"69400",
    "sg:province":"Rhone-Alpes",
    "wof:name":"Sefama Sa",
    "wof:placetype":"venue"
},
  "geometry": {"coordinates":[4.749014,45.97649],"type":"Point"}
}