{
  "type": "Feature",
  "properties": {
    "addr:full":"B.P. 3, 57560 Abreschviller^^Rue de la Gare, 57560 Abreschviller Lorraine",
    "addr:housenumber":"3",
    "addr:postcode":"57560;57560",
    "addr:street":"B.P.;La Gare",
    "iso:country":"FR",
    "sg:address":"B.P. 3, 57560 Abreschviller^^Rue de la Gare, 57560 Abreschviller",
    "sg:orig_category":"Non-Classified Establishments",
    "sg:phone":"+33 3 87 03 70 04",
    "sg:province":"Lorraine",
    "wof:name":"Scieries R\u00e9unies D'abreschviller S.a.",
    "wof:placetype":"venue"
},
  "geometry": {"coordinates":[7.095787,48.637177],"type":"Point"}
}