{
  "type": "Feature",
  "properties": {
    "addr:full":"Za Les Bosquets 76210 St Eustache La For\u00eat Haute Normandie 76210",
    "addr:postcode":"76210;76210",
    "addr:street":"Za Les Bosquets;Haute Normandie",
    "iso:country":"FR",
    "sg:address":"Za Les Bosquets 76210 St Eustache La For\u00eat",
    "sg:classifiers":[
        {
            "category":"Wholesale",
            "subcategory":"Medical Equipment & Supplies",
            "type":"Manufacturing & Wholesale Goods"
        }
    ],
    "sg:phone":"+33 2 35 38 10 23",
    "sg:postcode":"76210",
    "sg:province":"Haute Normandie",
    "sg:tags":[
        "instrument",
        "health",
        "-",
        "precision"
    ],
    "wof:name":"Normalab Analis Sa",
    "wof:placetype":"venue"
},
  "geometry": {"coordinates":[0.455309,49.562023],"type":"Point"}
}