{
  "type": "Feature",
  "properties": {
    "iso:country":"FR",
    "sg:address":"B.P. 41",
    "sg:city":"Equeurdreville Hainneville^^La Belle Jardini\u00e8re 50120 Equeurdreville Hainneville",
    "sg:orig_category":"Non-Classified Establishments",
    "sg:phone":"+33 2 33 01 52 52",
    "sg:postcode":"50120",
    "sg:province":"Basse Normandie",
    "wof:name":"O.t.e.c.m.i. S.a. - Omnium Technique D'etudes Et De Contr\u00f4les De Montages Industriels",
    "wof:placetype":"venue"
},
  "geometry": {"coordinates":[-1.674594,49.656322],"type":"Point"}
}