{
  "type": "Feature",
  "properties": {
    "iso:country":"FR",
    "sg:address":"B.P. 70616, 72025 Le Mans C\u00e9dex^^79, Av. Pierre Piffault - ZI Sud, 72000 Le Mans",
    "sg:orig_category":"Non-Classified Establishments",
    "sg:phone":"+33 2 43 75 55 88",
    "sg:province":"Pays de Loire",
    "wof:name":"Maine Soudage S.a.",
    "wof:placetype":"venue"
},
  "geometry": {"coordinates":[0.197813,48.008095],"type":"Point"}
}