{
  "type": "Feature",
  "properties": {
    "iso:country":"FR",
    "sg:address":"6 Rue L\u00e9on Patoux 51688 Reims",
    "sg:classifiers":[
        {
            "category":"Utilities",
            "subcategory":"Telephone",
            "type":"Services"
        }
    ],
    "sg:phone":"+33 3 26 48 48 48",
    "sg:province":"Aquitaine",
    "sg:tags":[
        "telecommunication"
    ],
    "wof:name":"Ste Alcatel Reseaux D'entreprise",
    "wof:placetype":"venue"
},
  "geometry": {"coordinates":[4.03384,49.25415],"type":"Point"}
}