{
  "type": "Feature",
  "properties": {
    "addr:full":"197, Av. Jean Cordier, 33600 Pessac Pessac Aquitaine 33600",
    "addr:postcode":"33600;33600",
    "addr:street":"197 Av. Jean Cordier",
    "iso:country":"FR",
    "sg:address":"197, Av. Jean Cordier, 33600 Pessac",
    "sg:city":"Pessac",
    "sg:orig_category":"Non-Classified Establishments",
    "sg:phone":"+33 5 56 93 23 40",
    "sg:postcode":"33600",
    "sg:province":"Aquitaine",
    "wof:name":"Ch\u00e2teau Les Carmes Haut Brion S.c.e.a.",
    "wof:placetype":"venue"
},
  "geometry": {"coordinates":[-0.610739,44.82019],"type":"Point"}
}