{
  "type": "Feature",
  "properties": {
    "addr:full":"8 rue Alexander Fl\u00e9ming 93360 Neuilly Plaisance Ile de France",
    "addr:housenumber":"8",
    "addr:postcode":"93360",
    "addr:street":"Rue Alexander Fle\u0301Ming;Ile De France",
    "iso:country":"FR",
    "sg:address":"8 rue Alexander Fl\u00e9ming 93360 Neuilly Plaisance",
    "sg:classifiers":[
        {
            "category":"Retail",
            "subcategory":"Auto Repair",
            "type":"Services"
        }
    ],
    "sg:phone":"+33 1 43 00 13 64",
    "sg:province":"Ile de France",
    "sg:tags":[
        "shop",
        "car",
        "tool"
    ],
    "wof:name":"Ets S.e.c.m.o.d. S.a.",
    "wof:placetype":"venue"
},
  "geometry": {"coordinates":[2.516327,48.866169],"type":"Point"}
}