{
  "type": "Feature",
  "properties": {
    "iso:country":"FR",
    "sg:address":"Zi Pras",
    "sg:city":"Industriel 65260 Pierrefitte Nestalas",
    "sg:classifiers":[
        {
            "category":"Manufacturing",
            "subcategory":"Metals",
            "type":"Manufacturing & Wholesale Goods"
        }
    ],
    "sg:phone":"+33 5 62 92 13 95",
    "sg:postcode":"65260",
    "sg:province":"Midi Pyr\u00e9n\u00e9es",
    "sg:tags":[
        "-",
        "machine",
        "equipment",
        "engineering",
        "machinery",
        "mechanical"
    ],
    "wof:name":"Mitjavila",
    "wof:placetype":"venue"
},
  "geometry": {"coordinates":[-0.074489,42.959557],"type":"Point"}
}