{
  "type": "Feature",
  "properties": {
    "iso:country":"FR",
    "sg:address":"Pizancon Canard Et Riousse 26300 Chatuzange le Goubet",
    "sg:classifiers":[
        {
            "category":"Manufacturing",
            "subcategory":"Furniture",
            "type":"Manufacturing & Wholesale Goods"
        }
    ],
    "sg:phone":"+33 4 75 70 55 80",
    "sg:postcode":"26300",
    "sg:province":"Rhone-Alpes",
    "sg:tags":[
        "wicker"
    ],
    "wof:name":"Sarl Patrick Labeaume Sarl",
    "wof:placetype":"venue"
},
  "geometry": {"coordinates":[5.09157,44.938511],"type":"Point"}
}