{
  "type": "Feature",
  "properties": {
    "iso:country":"FR",
    "sg:address":"Ld Florigny 44470 Carquefou",
    "sg:classifiers":[
        {
            "category":"Professional",
            "type":"Services"
        }
    ],
    "sg:phone":"+33 2 40 93 70 79",
    "sg:province":"Pays de Loire",
    "sg:tags":[
        "transport",
        "road"
    ],
    "wof:name":"Transports Bonnet Et Fils",
    "wof:placetype":"venue"
},
  "geometry": {"coordinates":[-1.480153,47.296024],"type":"Point"}
}