{
  "type": "Feature",
  "properties": {
    "addr:full":"55 Quai De Paludate 33800 Bordeaux Bordeaux Aquitaine 33800",
    "addr:housenumber":"55",
    "addr:postcode":"33800;33800",
    "addr:street":"Quai De Paludate",
    "iso:country":"FR",
    "sg:address":"55 Quai De Paludate 33800 Bordeaux",
    "sg:city":"Bordeaux",
    "sg:classifiers":[
        {
            "category":"Food & Beverages",
            "subcategory":"Groceries & Convenience Stores",
            "type":"Retail Goods"
        }
    ],
    "sg:phone":"+33 5 56 85 67 32",
    "sg:postcode":"33800",
    "sg:province":"Aquitaine",
    "sg:tags":[
        "product",
        "related"
    ],
    "wof:name":"La Bovida",
    "wof:placetype":"venue"
},
  "geometry": {"coordinates":[-0.552394,44.827911],"type":"Point"}
}