{
  "type": "Feature",
  "properties": {
    "addr:full":"B.P. 533, 13681 Aubagne C\u00e9dex^^Chemin de la Vall\u00e9e - ZI Saint Mitre, 13680 Aubagne Provence-Alpes-C\u00f4te d'Azur",
    "addr:housenumber":"b.p. 533",
    "addr:postcode":"13681;13680",
    "addr:street":"Valle\u0301E",
    "iso:country":"FR",
    "sg:address":"B.P. 533, 13681 Aubagne C\u00e9dex^^Chemin de la Vall\u00e9e - ZI Saint Mitre, 13680 Aubagne",
    "sg:orig_category":"Non-Classified Establishments",
    "sg:phone":"+33 4 42 18 70 60",
    "sg:province":"Provence-Alpes-C\u00f4te d'Azur",
    "wof:name":"L.c.m. S.a.r.l. - La Commerciale Des M\u00e9taux",
    "wof:placetype":"venue"
},
  "geometry": {"coordinates":[5.12418,43.590092],"type":"Point"}
}