{
  "type": "Feature",
  "properties": {
    "addr:full":"10, Rue Duvergnier, 75019 Paris Ile de France 75019",
    "addr:housenumber":"10",
    "addr:postcode":"75019;75019",
    "addr:street":"Rue Duvergnier",
    "iso:country":"FR",
    "sg:address":"10, Rue Duvergnier, 75019 Paris",
    "sg:orig_category":"Non-Classified Establishments",
    "sg:phone":"+33 1 55 26 95 95",
    "sg:postcode":"75019",
    "sg:province":"Ile de France",
    "wof:name":"Adress Company S.a.r.l.",
    "wof:placetype":"venue"
},
  "geometry": {"coordinates":[2.377195,48.889385],"type":"Point"}
}