{
  "type": "Feature",
  "properties": {
    "iso:country":"FR",
    "sg:address":"La Belle Etoile 25770 Franois",
    "sg:orig_category":"Non-Classified Establishments",
    "sg:phone":"+33 3 81 52 24 28",
    "sg:province":"Franche Comt\u00e9",
    "wof:name":"Poitrey",
    "wof:placetype":"venue"
},
  "geometry": {"coordinates":[5.92544,47.211956],"type":"Point"}
}