{
  "type": "Feature",
  "properties": {
    "addr:full":"46, Rue de la T\u00e9l\u00e9matique - Technop\u00f4le le Polyg\u00f4ne, 42000 Saint Etienne Rhone-Alpes",
    "addr:housenumber":"46",
    "addr:postcode":"42000",
    "addr:street":"Rue De La Te\u0301Le\u0301Matique Technopo\u0302Le Le Polygo\u0302Ne",
    "iso:country":"FR",
    "sg:address":"46, Rue de la T\u00e9l\u00e9matique - Technop\u00f4le le Polyg\u00f4ne, 42000 Saint Etienne",
    "sg:orig_category":"Unclassifiable Establishments",
    "sg:phone":"+33 4 77 79 52 80",
    "sg:province":"Rhone-Alpes",
    "wof:name":"Prysm Laboratoire Algade S.a.",
    "wof:placetype":"venue"
},
  "geometry": {"coordinates":[4.387921,45.439053],"type":"Point"}
}