{
  "type": "Feature",
  "properties": {
    "iso:country":"FR",
    "sg:address":"15, Bd Gabriel Guist'hau, 44000 Nantes",
    "sg:orig_category":"Unclassifiable Establishments",
    "sg:phone":"+33 2 40 48 90 40",
    "sg:province":"Pays de Loire",
    "wof:name":"B.h.e.",
    "wof:placetype":"venue"
},
  "geometry": {"coordinates":[-1.569529,47.217999],"type":"Point"}
}