{
  "type": "Feature",
  "properties": {
    "addr:full":"B.P. 291, 68316 Illzach C\u00e9dex^^9, Avenue de Hollande, 68110 Illzach Illzach Alsace 68110",
    "addr:housenumber":"b.p. 291",
    "addr:postcode":"68316;68110;68110",
    "addr:street":"Ce\u0301Dex^^9 Avenue De Hollande",
    "iso:country":"FR",
    "sg:address":"B.P. 291, 68316 Illzach C\u00e9dex^^9, Avenue de Hollande, 68110 Illzach",
    "sg:city":"Illzach",
    "sg:orig_category":"Non-Classified Establishments",
    "sg:phone":"+33 3 89 61 78 22",
    "sg:postcode":"68110",
    "sg:province":"Alsace",
    "wof:name":"Alsace Mat\u00e9riaux S.a.r.l.",
    "wof:placetype":"venue"
},
  "geometry": {"coordinates":[7.348394,47.782181],"type":"Point"}
}