{
  "type": "Feature",
  "properties": {
    "addr:full":"15, Bd du Mar\u00e9chal Juin, 78200 Mantes la Jolie Ile de France",
    "addr:housenumber":"15",
    "addr:postcode":"78200",
    "addr:street":"Bd Du Mare\u0301Chal Juin",
    "iso:country":"FR",
    "sg:address":"15, Bd du Mar\u00e9chal Juin, 78200 Mantes la Jolie",
    "sg:orig_category":"Unclassifiable Establishments",
    "sg:phone":"+33 1 30 33 51 51",
    "sg:province":"Ile de France",
    "wof:name":"Adia France",
    "wof:placetype":"venue"
},
  "geometry": {"coordinates":[1.709738,48.990437],"type":"Point"}
}