{
  "type": "Feature",
  "properties": {
    "iso:country":"FR",
    "sg:address":"30, Rue Gaston de Flotte - ZA Saint Jean du D\u00e9sert, 13012 Marseille",
    "sg:orig_category":"Unclassifiable Establishments",
    "sg:phone":"+33 4 91 19 91 99",
    "sg:province":"Poitou-Charentes",
    "wof:name":"L.p. France S.a.",
    "wof:placetype":"venue"
},
  "geometry": {"coordinates":[5.44175,43.30703],"type":"Point"}
}