{
  "type": "Feature",
  "properties": {
    "addr:full":"30, Rue Gaston de Flotte - ZA Saint Jean du D\u00e9sert, 13012 Marseille Poitou-Charentes",
    "addr:housenumber":"30",
    "addr:postcode":"13012",
    "addr:street":"Rue Gaston De Flotte Za Saint Jean Du De\u0301Sert",
    "iso:country":"FR",
    "sg:address":"30, Rue Gaston de Flotte - ZA Saint Jean du D\u00e9sert, 13012 Marseille",
    "sg:orig_category":"Unclassifiable Establishments",
    "sg:phone":"+33 4 91 19 91 99",
    "sg:province":"Poitou-Charentes",
    "wof:name":"L.p. France S.a.",
    "wof:placetype":"venue"
},
  "geometry": {"coordinates":[5.44175,43.30703],"type":"Point"}
}