{
  "type": "Feature",
  "properties": {
    "addr:full":"Rue Serge Barranx 40150 Soorts Hossegor Angresse Aquitaine 40150",
    "addr:postcode":"40150;40150",
    "addr:street":"Rue Serge",
    "iso:country":"FR",
    "sg:address":"Rue Serge Barranx 40150 Soorts Hossegor",
    "sg:city":"Angresse",
    "sg:classifiers":[
        {
            "category":"Utilities",
            "type":"Services"
        }
    ],
    "sg:phone":"+33 810 35 73 57",
    "sg:postcode":"40150",
    "sg:province":"Aquitaine",
    "sg:tags":[
        "raw",
        "energy",
        "material"
    ],
    "wof:name":"Lyonnaise Des Eaux France",
    "wof:placetype":"venue"
},
  "geometry": {"coordinates":[-1.426819,43.658119],"type":"Point"}
}