{
  "type": "Feature",
  "properties": {
    "addr:full":"Le Bourg 01560 Curciat Dongalon Rhone-Alpes 01560",
    "addr:postcode":"01560;01560",
    "addr:street":"Le Bourg;Rhone-Alpes",
    "iso:country":"FR",
    "sg:address":"Le Bourg 01560 Curciat Dongalon",
    "sg:orig_category":"Non-Classified Establishments",
    "sg:phone":"+33 4 74 52 90 56",
    "sg:postcode":"01560",
    "sg:province":"Rhone-Alpes",
    "wof:name":"Entreprise Prabel Et Fils S.a.r.l.",
    "wof:placetype":"venue"
},
  "geometry": {"coordinates":[5.116601,46.439442],"type":"Point"}
}