{
  "type": "Feature",
  "properties": {
    "addr:full":"1 Avenue Des Industries 33440 Ambares Et Lagrave Ambar\u00e8s-et-Lagrave Aquitaine 33440",
    "addr:housenumber":"1",
    "addr:postcode":"33440;33440",
    "addr:street":"Avenue Des Industries",
    "iso:country":"FR",
    "sg:address":"1 Avenue Des Industries 33440 Ambares Et Lagrave",
    "sg:city":"Ambar\u00e8s-et-Lagrave",
    "sg:classifiers":[
        {
            "category":"Manufacturing",
            "subcategory":"Chemicals & Compounds",
            "type":"Manufacturing & Wholesale Goods"
        }
    ],
    "sg:phone":"+33 5 56 77 82 30",
    "sg:postcode":"33440",
    "sg:province":"Aquitaine",
    "sg:tags":[
        "pharmaceutical",
        "energy",
        "chemistry",
        "-",
        "by-product"
    ],
    "wof:name":"Picoty Sa",
    "wof:placetype":"venue"
},
  "geometry": {"coordinates":[-0.522774,44.925705],"type":"Point"}
}