{
  "type": "Feature",
  "properties": {
    "addr:full":"28d Rue Jean Perrin 59500 Douai Nord Pas-de-Calais 59500",
    "addr:housenumber":"28d",
    "addr:postcode":"59500;59500",
    "addr:street":"Rue Jean Perrin",
    "iso:country":"FR",
    "sg:address":"28d Rue Jean Perrin 59500 Douai",
    "sg:classifiers":[
        {
            "category":"Shopping",
            "subcategory":"Hobbies, Toys, & Games",
            "type":"Retail Goods"
        }
    ],
    "sg:phone":"+33 3 27 99 77 11",
    "sg:postcode":"59500",
    "sg:province":"Nord Pas-de-Calais",
    "sg:tags":[
        "product",
        "miscellaneous",
        "entertainment"
    ],
    "wof:name":"Degand Marquage Sa",
    "wof:placetype":"venue"
},
  "geometry": {"coordinates":[3.095974,50.392803],"type":"Point"}
}