{
  "type": "Feature",
  "properties": {
    "addr:full":"Rue Buisson du Roi - ZI Le Meux Picardie 60880",
    "addr:postcode":"60880",
    "addr:street":"Rue Buisson Du Roi Zi;Meux Picardie",
    "iso:country":"FR",
    "sg:address":"Rue Buisson du Roi - ZI",
    "sg:city":"Le Meux",
    "sg:orig_category":"Non-Classified Establishments",
    "sg:phone":"+33 3 44 91 41 41",
    "sg:postcode":"60880",
    "sg:province":"Picardie",
    "wof:name":"Jet Services",
    "wof:placetype":"venue"
},
  "geometry": {"coordinates":[2.776811,49.389362],"type":"Point"}
}