{
  "type": "Feature",
  "properties": {
    "iso:country":"FR",
    "sg:address":"12",
    "sg:city":"Petit Hameau 45110 Ch\u00e2teauneuf sur Loire",
    "sg:classifiers":[
        {
            "category":"Home & Garden",
            "subcategory":"Furniture",
            "type":"Retail Goods"
        }
    ],
    "sg:phone":"+33 2 38 58 43 37",
    "sg:province":"Centre",
    "sg:tags":[
        "wood"
    ],
    "wof:name":"Barillet",
    "wof:placetype":"venue"
},
  "geometry": {"coordinates":[2.21668,47.876678],"type":"Point"}
}