{
  "type": "Feature",
  "properties": {
    "addr:full":"Route De Beaumont 43100 Paulhac Paulhac Auvergne 43100",
    "addr:postcode":"43100;paulhac;43100",
    "addr:street":"Route De Beaumont",
    "iso:country":"FR",
    "sg:address":"Route De Beaumont 43100 Paulhac",
    "sg:city":"Paulhac",
    "sg:classifiers":[
        {
            "category":"Manufacturing",
            "subcategory":"Paper Products",
            "type":"Manufacturing & Wholesale Goods"
        }
    ],
    "sg:phone":"+33 4 71 74 91 13",
    "sg:postcode":"43100",
    "sg:province":"Auvergne",
    "sg:tags":[
        "packaging",
        "material",
        "-",
        "cardboard"
    ],
    "wof:name":"Compagnie Industrielle De Paulhac (cip)",
    "wof:placetype":"venue"
},
  "geometry": {"coordinates":[3.359585,45.305145],"type":"Point"}
}