{
  "type": "Feature",
  "properties": {
    "addr:full":"84, Rte Nationale - Lieu dit Enneti\u00e8res des Avelins , 59710 Avelin Nord Pas-de-Calais",
    "addr:housenumber":"84",
    "addr:postcode":"59710",
    "addr:street":"Rte Nationale Lieu Dit Ennetie\u0300Res Des Avelins",
    "iso:country":"FR",
    "sg:address":"84, Rte Nationale - Lieu dit Enneti\u00e8res des Avelins , 59710 Avelin",
    "sg:orig_category":"Unclassifiable Establishments",
    "sg:phone":"+33 3 20 64 67 25",
    "sg:province":"Nord Pas-de-Calais",
    "wof:name":"S.t.r. Huys S.a.",
    "wof:placetype":"venue"
},
  "geometry": {"coordinates":[3.080295,50.53793],"type":"Point"}
}