{
  "type": "Feature",
  "properties": {
    "addr:full":"259, Rue Saint Honor\u00e9, 75001 Paris Ile de France",
    "addr:housenumber":"259",
    "addr:postcode":"75001",
    "addr:street":"Rue Saint Honore\u0301",
    "iso:country":"FR",
    "sg:address":"259, Rue Saint Honor\u00e9, 75001 Paris",
    "sg:orig_category":"Unclassifiable Establishments",
    "sg:phone":"+33 1 47 03 44 28",
    "sg:province":"Ile de France",
    "wof:name":"Label Communication E.u.r.l.",
    "wof:placetype":"venue"
},
  "geometry": {"coordinates":[2.326461,48.867226],"type":"Point"}
}