{
  "type": "Feature",
  "properties": {
    "addr:full":"B.P. 64, 67130 Schirmeck^^28, Rue des Forges, 67130 Schirmeck Schirmeck Alsace 67130",
    "addr:postcode":"67130;67130;67130",
    "addr:street":"B.P. 64;Rue Des Forges",
    "iso:country":"FR",
    "sg:address":"B.P. 64, 67130 Schirmeck^^28, Rue des Forges, 67130 Schirmeck",
    "sg:city":"Schirmeck",
    "sg:orig_category":"Non-Classified Establishments",
    "sg:phone":"+33 3 88 49 64 80",
    "sg:postcode":"67130",
    "sg:province":"Alsace",
    "wof:name":"Fonderie De La Bruche S.a.",
    "wof:placetype":"venue"
},
  "geometry": {"coordinates":[7.288189,48.519802],"type":"Point"}
}