{
  "type": "Feature",
  "properties": {
    "addr:full":"B.P. 5, 28111 Luc\u00e9 C\u00e9dex^^59, Rue du Mar\u00e9chal Leclerc, 28110 Luc\u00e9 Luc\u00e9 Centre 28110",
    "addr:housenumber":"5",
    "addr:postcode":"28111;28110;28110",
    "addr:street":"B.P.;Rue Du Mare\u0301Chal Leclerc",
    "iso:country":"FR",
    "sg:address":"B.P. 5, 28111 Luc\u00e9 C\u00e9dex^^59, Rue du Mar\u00e9chal Leclerc, 28110 Luc\u00e9",
    "sg:city":"Luc\u00e9",
    "sg:orig_category":"Non-Classified Establishments",
    "sg:phone":"+33 2 37 35 41 48",
    "sg:postcode":"28110",
    "sg:province":"Centre",
    "wof:name":"M.p.o.s. S.a.r.l. - M\u00e9canique De Pr\u00e9cision Et D'outillages Sp\u00e9ciaux",
    "wof:placetype":"venue"
},
  "geometry": {"coordinates":[1.467334,48.440228],"type":"Point"}
}