{
  "type": "Feature",
  "properties": {
    "addr:full":"1 Avenue Du Bois 69500 Bron Rhone-Alpes 69500",
    "addr:housenumber":"1",
    "addr:postcode":"69500;69500",
    "addr:street":"Avenue Du Bois",
    "iso:country":"FR",
    "sg:address":"1 Avenue Du Bois 69500 Bron",
    "sg:classifiers":[
        {
            "category":"Building & Trades",
            "subcategory":"Construction",
            "type":"Services"
        }
    ],
    "sg:phone":"+33 4 78 26 30 44",
    "sg:postcode":"69500",
    "sg:province":"Rhone-Alpes",
    "sg:tags":[
        "work",
        "public"
    ],
    "wof:name":"Etablissements Chazal Sa",
    "wof:placetype":"venue"
},
  "geometry": {"coordinates":[4.905809,45.734241],"type":"Point"}
}