{
  "type": "Feature",
  "properties": {
    "addr:full":"52, Av du G\u00e9n\u00e9ral Sarrail, 52115 Saint Dizier C\u00e9dex Champagne-Ardenne",
    "addr:postcode":"52115",
    "addr:street":"52 Av Du Ge\u0301Ne\u0301Ral Sarrail",
    "iso:country":"FR",
    "sg:address":"52, Av du G\u00e9n\u00e9ral Sarrail, 52115 Saint Dizier C\u00e9dex",
    "sg:orig_category":"Non-Classified Establishments",
    "sg:phone":"+33 3 25 55 68 00",
    "sg:province":"Champagne-Ardenne",
    "wof:name":"Etilam S.a.",
    "wof:placetype":"venue"
},
  "geometry": {"coordinates":[4.953652,48.644764],"type":"Point"}
}