{
  "type": "Feature",
  "properties": {
    "addr:full":"20, rue de Savoye, 51100 Reims Champagne",
    "addr:housenumber":"20",
    "addr:postcode":"51100",
    "addr:street":"Rue De Savoye",
    "iso:country":"FR",
    "sg:address":"20, rue de Savoye, 51100 Reims",
    "sg:orig_category":"Non-Classified Establishments",
    "sg:phone":"+33 3 26 47 71 02",
    "sg:province":"Champagne",
    "wof:name":"Lambert S.a.",
    "wof:placetype":"venue"
},
  "geometry": {"coordinates":[4.039692,49.26075],"type":"Point"}
}