{
  "type": "Feature",
  "properties": {
    "addr:full":"B.P. 09, 59710 Avelin C\u00e9dex^^ZA Les Marli\u00e8res, 59710 Avelin Nord Pas-de-Calais",
    "addr:postcode":"59710;59710",
    "addr:street":"B.P. 09;Ce\u0301Dex^^Za;Marlie\u0300Res",
    "iso:country":"FR",
    "sg:address":"B.P. 09, 59710 Avelin C\u00e9dex^^ZA Les Marli\u00e8res, 59710 Avelin",
    "sg:orig_category":"Non-Classified Establishments",
    "sg:phone":"+33 3 20 16 28 00",
    "sg:province":"Nord Pas-de-Calais",
    "wof:name":"Imprimerie Tillie S.a.",
    "wof:placetype":"venue"
},
  "geometry": {"coordinates":[3.080295,50.53793],"type":"Point"}
}