{
  "type": "Feature",
  "properties": {
    "addr:full":"3 Rue De La Marne 76410 St Aubin Les Elbeuf Haute Normandie",
    "addr:housenumber":"3",
    "addr:postcode":"76410",
    "addr:street":"Rue De La Marne;St Aubin Les;Haute Normandie",
    "iso:country":"FR",
    "sg:address":"3 Rue De La Marne 76410 St Aubin Les Elbeuf",
    "sg:classifiers":[
        {
            "category":"Professional",
            "type":"Services"
        }
    ],
    "sg:phone":"+33 2 35 78 91 09",
    "sg:province":"Haute Normandie",
    "sg:tags":[
        "transport",
        "road"
    ],
    "wof:name":"Abx Sa",
    "wof:placetype":"venue"
},
  "geometry": {"coordinates":[1.015976,49.304047],"type":"Point"}
}