{
  "type": "Feature",
  "properties": {
    "iso:country":"FR",
    "sg:address":"c\u00f4te du Monast\u00e8re 12000 Rodez",
    "sg:classifiers":[
        {
            "category":"Personal",
            "subcategory":"Tanning Parlor",
            "type":"Services"
        }
    ],
    "sg:phone":"+33 5 65 67 00 66",
    "sg:postcode":"12000",
    "sg:province":"Midi Pyr\u00e9n\u00e9es",
    "sg:tags":[
        "hide"
    ],
    "wof:name":"Tannerie Arnal F. S.a.",
    "wof:placetype":"venue"
},
  "geometry": {"coordinates":[2.575621,44.345528],"type":"Point"}
}