{
  "type": "Feature",
  "properties": {
    "addr:full":"B.P. 229, 73102 Aix les Bains C\u00e9dex^^ZI les Bougnard Mouxy, 73100 Aix les Bains Rhone-Alpes 73100",
    "addr:housenumber":"b.p. 229",
    "addr:postcode":"73102;73100;73100",
    "iso:country":"FR",
    "sg:address":"B.P. 229, 73102 Aix les Bains C\u00e9dex^^ZI les Bougnard Mouxy, 73100 Aix les Bains",
    "sg:orig_category":"Non-Classified Establishments",
    "sg:phone":"+33 4 79 61 60 11",
    "sg:postcode":"73100",
    "sg:province":"Rhone-Alpes",
    "wof:name":"Entreprise Barel Et Pelletier S.a.",
    "wof:placetype":"venue"
},
  "geometry": {"coordinates":[5.899685,45.672455],"type":"Point"}
}