{
  "type": "Feature",
  "properties": {
    "addr:full":"7, Rue Victor Flamant, 80130 Friville Escarbotin Picardie",
    "addr:housenumber":"7",
    "addr:postcode":"80130",
    "addr:street":"Rue Victor Flamant",
    "iso:country":"FR",
    "sg:address":"7, Rue Victor Flamant, 80130 Friville Escarbotin",
    "sg:orig_category":"Unclassifiable Establishments",
    "sg:phone":"+33 3 22 30 63 95",
    "sg:province":"Picardie",
    "wof:name":"Vimeu Emballages S.a. - Groupe Paxor",
    "wof:placetype":"venue"
},
  "geometry": {"coordinates":[1.545398,50.08213],"type":"Point"}
}