{
  "type": "Feature",
  "properties": {
    "addr:full":"40 rue des Cordeli\u00e8res 75013 Paris Ile de France 75013",
    "addr:housenumber":"40",
    "addr:postcode":"75013;75013",
    "addr:street":"Rue Des Cordelie\u0300Res",
    "iso:country":"FR",
    "sg:address":"40 rue des Cordeli\u00e8res 75013 Paris",
    "sg:classifiers":[
        {
            "category":"Shopping",
            "subcategory":"Clothing, Apparel, & Fashions",
            "type":"Retail Goods"
        }
    ],
    "sg:phone":"+33 1 55 43 24 24",
    "sg:postcode":"75013",
    "sg:province":"Ile de France",
    "sg:tags":[
        "blouse",
        "ladies'",
        "dress"
    ],
    "wof:name":"Ste D Exploitation Etablissement C Marty Sa",
    "wof:placetype":"venue"
},
  "geometry": {"coordinates":[2.348485,48.833687],"type":"Point"}
}