{
  "type": "Feature",
  "properties": {
    "addr:full":"Chem Des Silos 31100 Toulouse Midi Pyr\u00e9n\u00e9es",
    "addr:postcode":"31100",
    "iso:country":"FR",
    "sg:address":"Chem Des Silos 31100 Toulouse",
    "sg:classifiers":[
        {
            "category":"Banks & Credit Unions",
            "subcategory":"Investment Brokerage",
            "type":"Services"
        }
    ],
    "sg:phone":"+33 5 62 20 05 00",
    "sg:province":"Midi Pyr\u00e9n\u00e9es",
    "sg:tags":[
        "-",
        "transport",
        "related"
    ],
    "wof:name":"Toulouse Offset Presse Sa",
    "wof:placetype":"venue"
},
  "geometry": {"coordinates":[1.416683,43.558121],"type":"Point"}
}