{
  "type": "Feature",
  "properties": {
    "addr:full":"16 Rue Du Vernay 42100 St Etienne Rhone-Alpes 42100",
    "addr:housenumber":"16",
    "addr:postcode":"42100;42100",
    "addr:street":"Rue Du Vernay",
    "iso:country":"FR",
    "sg:address":"16 Rue Du Vernay 42100 St Etienne",
    "sg:classifiers":[
        {
            "category":"Professional",
            "subcategory":"Engineering",
            "type":"Services"
        }
    ],
    "sg:phone":"+33 4 77 41 43 99",
    "sg:postcode":"42100",
    "sg:province":"Rhone-Alpes",
    "sg:tags":[
        "machine",
        "-",
        "mechanical"
    ],
    "wof:name":"Entreprise Regionale D'ascenseurs (era)",
    "wof:placetype":"venue"
},
  "geometry": {"coordinates":[4.392085,45.431427],"type":"Point"}
}