{
  "type": "Feature",
  "properties": {
    "addr:full":"44 Rue Jean Baptiste Clement Rethel Champagne 08300",
    "addr:housenumber":"44",
    "addr:postcode":"08300",
    "addr:street":"Rue Jean Baptiste Clement;Champagne",
    "iso:country":"FR",
    "sg:address":"44 Rue Jean Baptiste Clement",
    "sg:city":"Rethel",
    "sg:classifiers":[
        {
            "category":"Banks & Credit Unions",
            "subcategory":"Financial Services",
            "type":"Services"
        }
    ],
    "sg:phone":"+33 3 24 38 51 56",
    "sg:postcode":"08300",
    "sg:province":"Champagne",
    "sg:tags":[
        "banking",
        "finance",
        "insurance"
    ],
    "wof:name":"Fcn Societe Francaise De Revision",
    "wof:placetype":"venue"
},
  "geometry": {"coordinates":[4.370711,49.507732],"type":"Point"}
}