{
  "type": "Feature",
  "properties": {
    "iso:country":"FR",
    "sg:address":"Rue des Etangs - ZI",
    "sg:city":"Blangy sur Bresle",
    "sg:orig_category":"Unclassifiable Establishments",
    "sg:phone":"+33 2 32 97 43 43",
    "sg:postcode":"76340",
    "sg:province":"Haute Normandie",
    "wof:name":"Plastiques De Haute Normandie S.a.",
    "wof:placetype":"venue"
},
  "geometry": {"coordinates":[1.593718,49.821468],"type":"Point"}
}