{
  "type": "Feature",
  "properties": {
    "addr:full":"415, Rte Nationale, 68600 Algolsheim Algolsheim Alsace 68600",
    "addr:housenumber":"415",
    "addr:postcode":"68600;68600",
    "addr:street":"Rte Nationale",
    "iso:country":"FR",
    "sg:address":"415, Rte Nationale, 68600 Algolsheim",
    "sg:city":"Algolsheim",
    "sg:orig_category":"Unclassifiable Establishments",
    "sg:phone":"+33 3 89 72 05 35",
    "sg:postcode":"68600",
    "sg:province":"Alsace",
    "wof:name":"Magnetek France S.a.r.l.",
    "wof:placetype":"venue"
},
  "geometry": {"coordinates":[7.54467,48.040482],"type":"Point"}
}