{
  "type": "Feature",
  "properties": {
    "addr:full":"B.P. 10032, 57056 Metz C\u00e9dex 02^^Z.I. Talange Hauconcourt, 57280 Hauconcourt Lorraine",
    "addr:housenumber":"10032",
    "addr:postcode":"57056;57280",
    "iso:country":"FR",
    "sg:address":"B.P. 10032, 57056 Metz C\u00e9dex 02^^Z.I. Talange Hauconcourt, 57280 Hauconcourt",
    "sg:orig_category":"Non-Classified Establishments",
    "sg:phone":"+33 3 87 51 80 53",
    "sg:province":"Lorraine",
    "wof:name":"S.l.p.c. - Soci\u00e9t\u00e9 Lorraine De Produits Chimiques S.a.",
    "wof:placetype":"venue"
},
  "geometry": {"coordinates":[6.160855,49.209999],"type":"Point"}
}