{
  "type": "Feature",
  "properties": {
    "addr:full":"Rte St Nicolas BP 8 54110 Rosi\u00e8res Aux Salines Lorraine",
    "addr:housenumber":"8",
    "addr:postcode":"54110",
    "addr:street":"Rte St Nicolas Bp;Salines",
    "iso:country":"FR",
    "sg:address":"Rte St Nicolas BP 8 54110 Rosi\u00e8res Aux Salines",
    "sg:classifiers":[
        {
            "category":"Professional",
            "type":"Services"
        }
    ],
    "sg:phone":"+33 3 83 48 10 40",
    "sg:province":"Lorraine",
    "sg:tags":[
        "transport",
        "road"
    ],
    "wof:name":"Transports Henn Sarl",
    "wof:placetype":"venue"
},
  "geometry": {"coordinates":[6.329566,48.601257],"type":"Point"}
}