{
  "type": "Feature",
  "properties": {
    "iso:country":"FR",
    "sg:address":"B.P. 3",
    "sg:city":"Masseret C\u00e9dex^^Lescurat 19510 Masseret",
    "sg:orig_category":"Non-Classified Establishments",
    "sg:phone":"+33 5 55 73 41 58",
    "sg:postcode":"19510",
    "sg:province":"Limousin",
    "wof:name":"Juanico S.a.r.l.",
    "wof:placetype":"venue"
},
  "geometry": {"coordinates":[1.538284,45.504665],"type":"Point"}
}