{
  "type": "Feature",
  "properties": {
    "addr:full":"B.P. 3 Masseret C\u00e9dex^^Lescurat 19510 Masseret Limousin 19510",
    "addr:postcode":"19510;19510",
    "addr:street":"B.P. 3 Masseret Ce\u0301Dex^^Lescurat",
    "iso:country":"FR",
    "sg:address":"B.P. 3",
    "sg:city":"Masseret C\u00e9dex^^Lescurat 19510 Masseret",
    "sg:orig_category":"Non-Classified Establishments",
    "sg:phone":"+33 5 55 73 41 58",
    "sg:postcode":"19510",
    "sg:province":"Limousin",
    "wof:name":"Juanico S.a.r.l.",
    "wof:placetype":"venue"
},
  "geometry": {"coordinates":[1.538284,45.504665],"type":"Point"}
}