{
  "type": "Feature",
  "properties": {
    "iso:country":"FR",
    "sg:address":"28, Rue Jean Jaur\u00e8s, 92800 Puteaux",
    "sg:orig_category":"Non-Classified Establishments",
    "sg:phone":"+33 1 47 62 60 03",
    "sg:postcode":"92800",
    "sg:province":"Ile de France",
    "wof:name":"Editions 83 S.a.",
    "wof:placetype":"venue"
},
  "geometry": {"coordinates":[2.247547,48.884762],"type":"Point"}
}