{
  "type": "Feature",
  "properties": {
    "addr:full":"12, Av. des Tropiquest, 91940 Les Ulis Ile de France",
    "addr:postcode":"91940",
    "addr:street":"12 Av. Des Tropiquest",
    "iso:country":"FR",
    "sg:address":"12, Av. des Tropiquest, 91940 Les Ulis",
    "sg:orig_category":"Unclassifiable Establishments",
    "sg:phone":"+33 1 69 18 88 10",
    "sg:province":"Ile de France",
    "wof:name":"Thermoquest S.a.",
    "wof:placetype":"venue"
},
  "geometry": {"coordinates":[2.202092,48.684059],"type":"Point"}
}