{
  "type": "Feature",
  "properties": {
    "iso:country":"FR",
    "sg:address":"44, All\u00e9e de Cumi\u00e8res, 51202 Epernay C\u00e9dex",
    "sg:orig_category":"Unclassifiable Establishments",
    "sg:phone":"+33 3 26 59 86 00",
    "sg:province":"Champagne",
    "wof:name":"C.s.g.v. - Coop\u00e9rative Du Syndicat G\u00e9n\u00e9ral Des Vignerons",
    "wof:placetype":"venue"
},
  "geometry": {"coordinates":[3.951278,49.056892],"type":"Point"}
}