{
  "type": "Feature",
  "properties": {
    "addr:full":"Rue Antoine De St Exup\u00e9ry 44860 St Aignan De Gd Lieu Pays de Loire",
    "addr:postcode":"44860",
    "addr:street":"Rue Antoine De St Exupe\u0301Ry;Lieu",
    "iso:country":"FR",
    "sg:address":"Rue Antoine De St Exup\u00e9ry 44860 St Aignan De Gd Lieu",
    "sg:classifiers":[
        {
            "category":"Manufacturing",
            "subcategory":"Printing",
            "type":"Manufacturing & Wholesale Goods"
        }
    ],
    "sg:phone":"+33 2 40 75 22 77",
    "sg:province":"Pays de Loire",
    "sg:tags":[
        "publishing"
    ],
    "wof:name":"Scann Ouest Sarl",
    "wof:placetype":"venue"
},
  "geometry": {"coordinates":[-1.639081,47.121914],"type":"Point"}
}