{
  "type": "Feature",
  "properties": {
    "addr:full":"211, Av. Francis de Pressens\u00e9, 69200 V\u00e9nissieux Rhone-Alpes",
    "addr:postcode":"69200",
    "addr:street":"211 Av. Francis De Pressense\u0301",
    "iso:country":"FR",
    "sg:address":"211, Av. Francis de Pressens\u00e9, 69200 V\u00e9nissieux",
    "sg:orig_category":"Unclassifiable Establishments",
    "sg:phone":"+33 4 72 78 21 70",
    "sg:province":"Rhone-Alpes",
    "wof:name":"Agintis S.a.",
    "wof:placetype":"venue"
},
  "geometry": {"coordinates":[4.873895,45.713245],"type":"Point"}
}