{
  "type": "Feature",
  "properties": {
    "iso:country":"FR",
    "sg:address":"Rue Gerard Desargue Za Salvaza 11000 Carcassonne",
    "sg:classifiers":[
        {
            "category":"Professional",
            "subcategory":"Engineering",
            "type":"Services"
        }
    ],
    "sg:phone":"+33 4 68 47 94 94",
    "sg:postcode":"11000",
    "sg:province":"Languedoc-Roussillon",
    "sg:tags":[
        "machine",
        "-",
        "mechanical"
    ],
    "wof:name":"Developpement Industriel Realisation Etude (dire)",
    "wof:placetype":"venue"
},
  "geometry": {"coordinates":[2.306378,43.188465],"type":"Point"}
}