{
  "type": "Feature",
  "properties": {
    "addr:full":"94 Rue Pasteur 94120 Fontenay Sous Bois Ile de France 94120",
    "addr:housenumber":"94",
    "addr:postcode":"94120;94120",
    "addr:street":"Rue Pasteur;Bois Ile De France",
    "iso:country":"FR",
    "sg:address":"94 Rue Pasteur 94120 Fontenay Sous Bois",
    "sg:classifiers":[
        {
            "category":"Bakery",
            "type":"Food & Drink"
        }
    ],
    "sg:phone":"+33 1 41 95 10 60",
    "sg:postcode":"94120",
    "sg:province":"Ile de France",
    "sg:tags":[
        "cake",
        "product",
        "related",
        "bread"
    ],
    "wof:name":"Etoile Du Liban",
    "wof:placetype":"venue"
},
  "geometry": {"coordinates":[2.458133,48.848534],"type":"Point"}
}