{
  "type": "Feature",
  "properties": {
    "addr:full":"75, Av. Pierre Corneille, 91420 Morangis Ile de France 91420",
    "addr:postcode":"91420;ile;91420",
    "addr:street":"75 Av. Pierre Corneille;France",
    "iso:country":"FR",
    "sg:address":"75, Av. Pierre Corneille, 91420 Morangis",
    "sg:orig_category":"Non-Classified Establishments",
    "sg:phone":"+33 1 69 09 47 41",
    "sg:postcode":"91420",
    "sg:province":"Ile de France",
    "wof:name":"Action V.p.c. S.a.",
    "wof:placetype":"venue"
},
  "geometry": {"coordinates":[2.327784,48.703587],"type":"Point"}
}