{
  "type": "Feature",
  "properties": {
    "addr:full":"11, Rue Brossolette, 59148 Flines lez R\u00e2ches Nord Pas-de-Calais",
    "addr:housenumber":"11",
    "addr:postcode":"59148",
    "addr:street":"Rue Brossolette",
    "iso:country":"FR",
    "sg:address":"11, Rue Brossolette, 59148 Flines lez R\u00e2ches",
    "sg:orig_category":"Unclassifiable Establishments",
    "sg:phone":"+33 3 27 92 21 21",
    "sg:province":"Nord Pas-de-Calais",
    "wof:name":"M.p.d. S.a.r.l. - Menuiserie Pvc Du Douaisis",
    "wof:placetype":"venue"
},
  "geometry": {"coordinates":[3.18883,50.420738],"type":"Point"}
}