{
  "type": "Feature",
  "properties": {
    "addr:full":"Rte de la Prairie - ZI Alex Groissiat Groissiat Rhone-Alpes 01110",
    "addr:postcode":"01110",
    "addr:street":"Rte De La Prairie Zi Alex Groissiat;Rhone-Alpes",
    "iso:country":"FR",
    "sg:address":"Rte de la Prairie - ZI Alex Groissiat",
    "sg:city":"Groissiat",
    "sg:orig_category":"Unclassifiable Establishments",
    "sg:phone":"+33 4 74 73 43 37",
    "sg:postcode":"01110",
    "sg:province":"Rhone-Alpes",
    "wof:name":"D.p.h. Moules M\u00e9talliques S.a.",
    "wof:placetype":"venue"
},
  "geometry": {"coordinates":[5.580183,45.980537],"type":"Point"}
}