{
  "type": "Feature",
  "properties": {
    "addr:full":"48 bis, rue Fabert, 75340 Paris CEDEX 07, Dept 75 Auvergne",
    "addr:housenumber":"48 bis",
    "addr:postcode":"75340;75",
    "addr:street":"Rue Fabert",
    "iso:country":"FR",
    "sg:address":"48 bis, rue Fabert, 75340 Paris CEDEX 07, Dept 75",
    "sg:classifiers":[
        {
            "category":"Banks & Credit Unions",
            "subcategory":"Bank",
            "type":"Services"
        }
    ],
    "sg:phone":"+33 5 49 55 70 00",
    "sg:province":"Auvergne",
    "wof:name":"Financi\u00e8re Saint Dominique (private Equity)",
    "wof:placetype":"venue"
},
  "geometry": {"coordinates":[2.311108,48.858143],"type":"Point"}
}