{
  "type": "Feature",
  "properties": {
    "addr:full":"Zi Sud 42160 Andr\u00e9zieux Bouth\u00e9on Rhone-Alpes 42160",
    "addr:postcode":"42160;42160",
    "addr:street":"Rhone-Alpes",
    "iso:country":"FR",
    "sg:address":"Zi Sud 42160 Andr\u00e9zieux Bouth\u00e9on",
    "sg:classifiers":[
        {
            "category":"Manufacturing",
            "subcategory":"Metals",
            "type":"Manufacturing & Wholesale Goods"
        }
    ],
    "sg:phone":"+33 4 77 55 52 30",
    "sg:postcode":"42160",
    "sg:province":"Rhone-Alpes",
    "sg:tags":[
        "metallurgy",
        "metalworking",
        "processing"
    ],
    "wof:name":"Thermi Loire Sas",
    "wof:placetype":"venue"
},
  "geometry": {"coordinates":[4.25674,45.52943],"type":"Point"}
}