{
  "type": "Feature",
  "properties": {
    "addr:full":"Rte Tranzault Ardentes Centre 36120",
    "addr:housenumber":"ardentes",
    "addr:postcode":"36120",
    "addr:street":"Rte Tranzault",
    "iso:country":"FR",
    "sg:address":"Rte Tranzault",
    "sg:city":"Ardentes",
    "sg:orig_category":"Non-Classified Establishments",
    "sg:phone":"+33 2 54 08 12 80",
    "sg:postcode":"36120",
    "sg:province":"Centre",
    "wof:name":"Etablissements Pierre Robert Et Compagnie S.a.",
    "wof:placetype":"venue"
},
  "geometry": {"coordinates":[1.795385,46.673389],"type":"Point"}
}