{
  "type": "Feature",
  "properties": {
    "addr:full":"Lieu Dit De La Chausseraie Route De Thouars 79250 Nueil Les Aubiers Poitou-Charentes",
    "addr:postcode":"79250",
    "addr:street":"Lieu Dit De La;Route De Thouars;Les Aubiers",
    "iso:country":"FR",
    "sg:address":"Lieu Dit De La Chausseraie Route De Thouars 79250 Nueil Les Aubiers",
    "sg:classifiers":[
        {
            "category":"Home & Garden",
            "subcategory":"Furniture",
            "type":"Retail Goods"
        }
    ],
    "sg:phone":"+33 5 49 65 60 03",
    "sg:province":"Poitou-Charentes",
    "sg:tags":[
        "wood"
    ],
    "wof:name":"Caisserie Aubraise Moderne (cam)",
    "wof:placetype":"venue"
},
  "geometry": {"coordinates":[-0.590424,46.95528],"type":"Point"}
}