{
  "type": "Feature",
  "properties": {
    "iso:country":"FR",
    "sg:address":"74, Rue Chateauvert, 26000 Valence",
    "sg:orig_category":"Unclassifiable Establishments",
    "sg:phone":"+33 4 75 44 04 30",
    "sg:postcode":"26000",
    "sg:province":"Rhone-Alpes",
    "wof:name":"Bourguignon Et Fils S.a.r.l.",
    "wof:placetype":"venue"
},
  "geometry": {"coordinates":[4.897876,44.922634],"type":"Point"}
}