{
  "type": "Feature",
  "properties": {
    "iso:country":"FR",
    "sg:address":"13, Cours Ruffin, 76210 Bolbec",
    "sg:orig_category":"Non-Classified Establishments",
    "sg:phone":"+33 2 35 31 06 85",
    "sg:postcode":"76210",
    "sg:province":"Haute Normandie",
    "wof:name":"D\u00e9pard\u00e9 S.a.r.l.",
    "wof:placetype":"venue"
},
  "geometry": {"coordinates":[0.476521,49.570541],"type":"Point"}
}