{
  "type": "Feature",
  "properties": {
    "iso:country":"FR",
    "sg:address":"10, Rue de la Longeraie, 35760 Saint Gr\u00e9goire",
    "sg:city":"Montgermont",
    "sg:orig_category":"Unclassifiable Establishments",
    "sg:phone":"+33 2 99 87 48 10",
    "sg:postcode":"35760",
    "sg:province":"Bretagne",
    "wof:name":"Elyo Centre Ouest S.a.",
    "wof:placetype":"venue"
},
  "geometry": {"coordinates":[-1.689307,48.134773],"type":"Point"}
}