{
  "type": "Feature",
  "properties": {
    "addr:full":"5, Rue des Fr\u00e8res Lumi\u00e8re - Parc d'Activit\u00e9s d'Eckbolsheim, 67087 Strasbourg Eckbolsheim Alsace 67201",
    "addr:housenumber":"5",
    "addr:postcode":"67087;67201",
    "addr:street":"Rue Des Fre\u0300Res Lumie\u0300Re Parc D'Activite \u0301S D'Eckbolsheim",
    "iso:country":"FR",
    "sg:address":"5, Rue des Fr\u00e8res Lumi\u00e8re - Parc d'Activit\u00e9s d'Eckbolsheim, 67087 Strasbourg",
    "sg:city":"Eckbolsheim",
    "sg:orig_category":"Non-Classified Establishments",
    "sg:phone":"+33 3 88 78 96 69",
    "sg:postcode":"67201",
    "sg:province":"Alsace",
    "wof:name":"Cabinet Magar Soci\u00e9t\u00e9 D'expertise Comptable S.a.",
    "wof:placetype":"venue"
},
  "geometry": {"coordinates":[7.703519,48.566338],"type":"Point"}
}