{
  "type": "Feature",
  "properties": {
    "addr:full":"17 Boulevard Monge 69330 Meyzieu Rhone-Alpes",
    "addr:housenumber":"17",
    "addr:postcode":"69330",
    "addr:street":"Boulevard Monge",
    "iso:country":"FR",
    "sg:address":"17 Boulevard Monge 69330 Meyzieu",
    "sg:classifiers":[
        {
            "category":"Professional",
            "subcategory":"Engineering",
            "type":"Services"
        }
    ],
    "sg:phone":"+33 4 78 31 40 58",
    "sg:province":"Rhone-Alpes",
    "sg:tags":[
        "machine",
        "-",
        "mechanical"
    ],
    "wof:name":"Polyprofils Sa",
    "wof:placetype":"venue"
},
  "geometry": {"coordinates":[5.017095,45.767887],"type":"Point"}
}