{
  "type": "Feature",
  "properties": {
    "addr:full":"62, Rte du Hazay, 78520 Limay Ile de France",
    "addr:housenumber":"62",
    "addr:postcode":"78520",
    "addr:street":"Rte Du Hazay;Ile De France",
    "iso:country":"FR",
    "sg:address":"62, Rte du Hazay, 78520 Limay",
    "sg:orig_category":"Non-Classified Establishments",
    "sg:phone":"+33 1 30 92 56 00",
    "sg:province":"Ile de France",
    "wof:name":"Port Autonome De Paris",
    "wof:placetype":"venue"
},
  "geometry": {"coordinates":[1.747118,48.97366],"type":"Point"}
}