{
  "type": "Feature",
  "properties": {
    "iso:country":"FR",
    "sg:address":"37 Bd Pierre Lefaucheux 72100 Le Mans",
    "sg:classifiers":[
        {
            "category":"Manufacturing",
            "subcategory":"Glass & Minerals",
            "type":"Manufacturing & Wholesale Goods"
        }
    ],
    "sg:phone":"+33 2 43 85 29 13",
    "sg:postcode":"72100",
    "sg:province":"Pays de Loire",
    "sg:tags":[
        "building",
        "material"
    ],
    "wof:name":"Sotraver",
    "wof:placetype":"venue"
},
  "geometry": {"coordinates":[0.175462,47.969276],"type":"Point"}
}