{
  "type": "Feature",
  "properties": {
    "iso:country":"FR",
    "sg:address":"70 Avenue Emile Zola 75015 Paris",
    "sg:classifiers":[
        {
            "category":"Home & Garden",
            "subcategory":"Furniture",
            "type":"Retail Goods"
        }
    ],
    "sg:phone":"+33 1 43 92 43 92",
    "sg:postcode":"75015",
    "sg:province":"Ile de France",
    "sg:tags":[
        "household",
        "wood"
    ],
    "wof:name":"Zola Color",
    "wof:placetype":"venue"
},
  "geometry": {"coordinates":[2.284874,48.846352],"type":"Point"}
}