{
  "type": "Feature",
  "properties": {
    "iso:country":"FR",
    "sg:address":"16, Av. Charles de Gaulle - B\u00e2t. 14, 31130 Balma",
    "sg:orig_category":"Unclassifiable Establishments",
    "sg:phone":"+33 5 62 57 72 80",
    "sg:province":"Midi Pyr\u00e9n\u00e9es",
    "wof:name":"Midi-pyr\u00e9n\u00e9es Expertise S.a.",
    "wof:placetype":"venue"
},
  "geometry": {"coordinates":[1.499115,43.596333],"type":"Point"}
}