{
  "type": "Feature",
  "properties": {
    "iso:country":"FR",
    "sg:address":"135",
    "sg:city":"de Periole; Toulouse Cedex; 31079",
    "sg:classifiers":[
        {
            "category":"Industrial Area",
            "type":"Public Place"
        }
    ],
    "sg:phone":"+33 5 61 58 77 00",
    "sg:province":"Corse",
    "sg:tags":[
        "large",
        "private"
    ],
    "wof:name":"Soci\u00e9t\u00e9 Industrielle D'aviation Lat\u00e9co\u00e8re, Sa",
    "wof:placetype":"venue"
},
  "geometry": {"coordinates":[1.44301,43.604359],"type":"Point"}
}