{
  "type": "Feature",
  "properties": {
    "addr:full":"360 avenue Victor Hugo 26000 Valence Rhone-Alpes 26000",
    "addr:housenumber":"360",
    "addr:postcode":"26000;26000",
    "addr:street":"Avenue Victor Hugo",
    "iso:country":"FR",
    "sg:address":"360 avenue Victor Hugo 26000 Valence",
    "sg:classifiers":[
        {
            "category":"Food & Beverages",
            "subcategory":"Fruits & Vegetables",
            "type":"Retail Goods"
        }
    ],
    "sg:phone":"+33 4 75 41 22 47",
    "sg:postcode":"26000",
    "sg:province":"Rhone-Alpes",
    "wof:name":"Les Vergers De Valence Sica",
    "wof:placetype":"venue"
},
  "geometry": {"coordinates":[4.884601,44.914379],"type":"Point"}
}