{
  "type": "Feature",
  "properties": {
    "addr:full":"44610 Indre Pays de Loire",
    "addr:postcode":"44610",
    "addr:street":"Indre",
    "iso:country":"FR",
    "sg:address":"44610 Indre",
    "sg:orig_category":"Unclassifiable Establishments",
    "sg:phone":"+33 2 40 38 19 71",
    "sg:province":"Pays de Loire",
    "wof:name":"Usinor Packaging S.a.",
    "wof:placetype":"venue"
},
  "geometry": {"coordinates":[-1.67039,47.199379],"type":"Point"}
}