{
  "type": "Feature",
  "properties": {
    "addr:full":"B.P. 119 Aniche Nord Pas-de-Calais 59580",
    "addr:housenumber":"b.p. 119",
    "addr:postcode":"59580",
    "addr:street":"Aniche Nord",
    "iso:country":"FR",
    "sg:address":"B.P. 119",
    "sg:city":"Aniche",
    "sg:orig_category":"Non-Classified Establishments",
    "sg:phone":"+33 3 27 93 62 35",
    "sg:postcode":"59580",
    "sg:province":"Nord Pas-de-Calais",
    "wof:name":"Glaverbel S.a.",
    "wof:placetype":"venue"
},
  "geometry": {"coordinates":[3.249528,50.331013],"type":"Point"}
}