{
  "type": "Feature",
  "properties": {
    "iso:country":"FR",
    "sg:address":"Les Meuni\u00e8res 38260 La C\u00f4te Saint Andr\u00e9",
    "sg:orig_category":"Unclassifiable Establishments",
    "sg:phone":"+33 4 74 20 51 10",
    "sg:province":"Rhone-Alpes",
    "wof:name":"Imprimerie Rochat S.a",
    "wof:placetype":"venue"
},
  "geometry": {"coordinates":[5.25326,45.389923],"type":"Point"}
}