{
  "type": "Feature",
  "properties": {
    "addr:full":"2, Rue du Moulin \u00e0 Vapeur, 62200 Boulogne sur Mer Nord Pas-de-Calais",
    "addr:housenumber":"2",
    "addr:postcode":"62200",
    "addr:street":"Rue Du Moulin A\u0300 Vapeur;Sur Mer Nord",
    "iso:country":"FR",
    "sg:address":"2, Rue du Moulin \u00e0 Vapeur, 62200 Boulogne sur Mer",
    "sg:orig_category":"Unclassifiable Establishments",
    "sg:phone":"+33 3 21 10 20 20",
    "sg:province":"Nord Pas-de-Calais",
    "wof:name":"Habart S.a.",
    "wof:placetype":"venue"
},
  "geometry": {"coordinates":[1.596962,50.721516],"type":"Point"}
}