{
  "type": "Feature",
  "properties": {
    "addr:full":"8 Rue Andr\u00e9 Ch\u00e9nier Amiens Picardie 80000",
    "addr:housenumber":"8",
    "addr:postcode":"80000",
    "addr:street":"Rue Andre\u0301 Che\u0301Nier",
    "iso:country":"FR",
    "sg:address":"8 Rue Andr\u00e9 Ch\u00e9nier",
    "sg:city":"Amiens",
    "sg:classifiers":[
        {
            "category":"Banks & Credit Unions",
            "subcategory":"Financial Services",
            "type":"Services"
        }
    ],
    "sg:phone":"+33 3 22 33 83 38",
    "sg:postcode":"80000",
    "sg:province":"Picardie",
    "sg:tags":[
        "banking",
        "finance",
        "insurance"
    ],
    "wof:name":"Lisiecki Casimir",
    "wof:placetype":"venue"
},
  "geometry": {"coordinates":[2.285207,49.877308],"type":"Point"}
}