{
  "type": "Feature",
  "properties": {
    "iso:country":"FR",
    "sg:address":"Zone d'Activit\u00e9 Cit\u00e9 Bompertuis",
    "sg:city":"Gardanne",
    "sg:orig_category":"Non-Classified Establishments",
    "sg:phone":"+33 4 42 65 43 43",
    "sg:postcode":"13120",
    "wof:name":"Microm\u00e9ga S.a.r.l.",
    "wof:placetype":"venue"
},
  "geometry": {"coordinates":[5.48555,43.458542],"type":"Point"}
}