{
  "type": "Feature",
  "properties": {
    "iso:country":"FR",
    "sg:address":"21, Rue Roger Salengro - Parc d'Activit\u00e9 Pau-Pyr\u00e9n\u00e9es, 64000 Pau",
    "sg:city":"Pau",
    "sg:orig_category":"Unclassifiable Establishments",
    "sg:phone":"+33 5 59 14 50 00",
    "sg:postcode":"64000",
    "sg:province":"Aquitaine",
    "wof:name":"C\u00e9g\u00e9lec S.a.",
    "wof:placetype":"venue"
},
  "geometry": {"coordinates":[-0.327924,43.315941],"type":"Point"}
}