{
  "type": "Feature",
  "properties": {
    "iso:country":"FR",
    "sg:address":"B.P. 11, 14502 Vire C\u00e9dex^^ZI Est, 14500 Vire",
    "sg:city":"Vire",
    "sg:orig_category":"Non-Classified Establishments",
    "sg:phone":"+33 2 31 68 06 42",
    "sg:postcode":"14500",
    "sg:province":"Basse Normandie",
    "wof:name":"Teim S.a.",
    "wof:placetype":"venue"
},
  "geometry": {"coordinates":[-0.815379,48.772549],"type":"Point"}
}