{
  "type": "Feature",
  "properties": {
    "addr:full":"2, Rue Charles de Gaulle, 02340 Chaourse Picardie 02340",
    "addr:housenumber":"2",
    "addr:postcode":"02340;02340",
    "addr:street":"Rue Charles De Gaulle;Picardie",
    "iso:country":"FR",
    "sg:address":"2, Rue Charles de Gaulle, 02340 Chaourse",
    "sg:orig_category":"Non-Classified Establishments",
    "sg:phone":"+33 3 23 21 28 12",
    "sg:postcode":"02340",
    "sg:province":"Picardie",
    "wof:name":"Boucher S.a.r.l.",
    "wof:placetype":"venue"
},
  "geometry": {"coordinates":[4.002152,49.692692],"type":"Point"}
}