{
  "type": "Feature",
  "properties": {
    "iso:country":"FR",
    "sg:address":"44, Av. des Ch\u00e2taigniers, 95150 Taverny",
    "sg:orig_category":"Non-Classified Establishments",
    "sg:phone":"+33 1 39 32 90 90",
    "sg:postcode":"95150",
    "sg:province":"Ile de France",
    "wof:name":"C.r.p. S.a. - Construction R\u00e9parations P\u00e9troliers",
    "wof:placetype":"venue"
},
  "geometry": {"coordinates":[2.18835,49.02533],"type":"Point"}
}