{
  "type": "Feature",
  "properties": {
    "iso:country":"FR",
    "sg:address":"rue Messager 59175 Templemars",
    "sg:classifiers":[
        {
            "category":"Manufacturing",
            "subcategory":"Paper Products",
            "type":"Manufacturing & Wholesale Goods"
        }
    ],
    "sg:phone":"+33 3 20 62 96 40",
    "sg:postcode":"59175",
    "sg:province":"Nord Pas-de-Calais",
    "sg:tags":[
        "adhesive",
        "self-adhesive",
        "labels",
        "label"
    ],
    "wof:name":"Etiquetage Rationnel Sa",
    "wof:placetype":"venue"
},
  "geometry": {"coordinates":[3.06248,50.566944],"type":"Point"}
}