{
  "type": "Feature",
  "properties": {
    "iso:country":"FR",
    "sg:address":"14 boulevard Poissonni\u00e8re 75009 Paris",
    "sg:classifiers":[
        {
            "category":"Professional",
            "subcategory":"Business Services",
            "type":"Services"
        }
    ],
    "sg:phone":"+33 1 44 83 65 65",
    "sg:postcode":"75009",
    "sg:province":"Ile de France",
    "sg:tags":[
        "agency",
        "export"
    ],
    "wof:name":"Segealon The Best Export Bureau Sarl",
    "wof:placetype":"venue"
},
  "geometry": {"coordinates":[2.34628,48.871059],"type":"Point"}
}