{
  "type": "Feature",
  "properties": {
    "addr:full":"155, Rue Jean Morin - Z.I. des Dragiez, 74800 La Roche sur Foron Rhone-Alpes 74800",
    "addr:housenumber":"155",
    "addr:postcode":"74800;74800",
    "addr:street":"Rue Jean Morin;Des Dragiez",
    "iso:country":"FR",
    "sg:address":"155, Rue Jean Morin - Z.I. des Dragiez, 74800 La Roche sur Foron",
    "sg:orig_category":"Unclassifiable Establishments",
    "sg:phone":"+33 4 50 03 17 52",
    "sg:postcode":"74800",
    "sg:province":"Rhone-Alpes",
    "wof:name":"S.a.m.o. S.a. - Savoie Alpes Machines Outils",
    "wof:placetype":"venue"
},
  "geometry": {"coordinates":[6.357741,46.047504],"type":"Point"}
}