{
  "type": "Feature",
  "properties": {
    "iso:country":"FR",
    "sg:address":"10 rue Vandrezanne 75013 Paris",
    "sg:orig_category":"Applied Hydrogeology",
    "sg:phone":"+33 1 45 80 51 61",
    "sg:postcode":"75013",
    "sg:province":"Ile de France",
    "wof:name":"Rock View International Sarl",
    "wof:placetype":"venue"
},
  "geometry": {"coordinates":[2.355793,48.82822],"type":"Point"}
}