{
  "type": "Feature",
  "properties": {
    "addr:full":"30 Quai Du Dr Gailleton 69002 Lyon Rhone-Alpes 69002",
    "addr:housenumber":"30",
    "addr:postcode":"69002;69002",
    "addr:street":"Quai Du Dr Gailleton",
    "iso:country":"FR",
    "sg:address":"30 Quai Du Dr Gailleton 69002 Lyon",
    "sg:classifiers":[
        {
            "category":"Manufacturing",
            "subcategory":"Leather Goods",
            "type":"Manufacturing & Wholesale Goods"
        }
    ],
    "sg:phone":"+33 4 78 42 12 14",
    "sg:postcode":"69002",
    "sg:province":"Rhone-Alpes",
    "sg:tags":[
        "shoe"
    ],
    "wof:name":"Manufacture Lyonnaise De Courroies Et Cuirs Industrie Sa",
    "wof:placetype":"venue"
},
  "geometry": {"coordinates":[4.83295,45.752338],"type":"Point"}
}