{
  "type": "Feature",
  "properties": {
    "addr:full":"Les Blanches 53410 Port Brillet Pays de Loire",
    "addr:postcode":"53410",
    "addr:street":"Blanches;Brillet",
    "iso:country":"FR",
    "sg:address":"Les Blanches 53410 Port Brillet",
    "sg:orig_category":"Unclassifiable Establishments",
    "sg:phone":"+33 2 43 02 02 44",
    "sg:province":"Pays de Loire",
    "wof:name":"Contr\u00f4le Lavallois S.a.r.l.",
    "wof:placetype":"venue"
},
  "geometry": {"coordinates":[-0.953193,48.11837],"type":"Point"}
}