{
  "type": "Feature",
  "properties": {
    "addr:full":"Rte d'Eymet Saint Laurent des Vignes Aquitaine 24100",
    "addr:postcode":"24100",
    "addr:street":"Rte D'Eymet",
    "iso:country":"FR",
    "sg:address":"Rte d'Eymet",
    "sg:city":"Saint Laurent des Vignes",
    "sg:orig_category":"Non-Classified Establishments",
    "sg:phone":"+33 5 53 63 71 00",
    "sg:postcode":"24100",
    "sg:province":"Aquitaine",
    "wof:name":"Interactifs France S.a.r.l.",
    "wof:placetype":"venue"
},
  "geometry": {"coordinates":[0.474934,44.813194],"type":"Point"}
}