{
  "type": "Feature",
  "properties": {
    "addr:full":"Alpes Espace Montm\u00e9lian Rhone-Alpes 73800",
    "addr:postcode":"73800",
    "iso:country":"FR",
    "sg:address":"Alpes Espace",
    "sg:city":"Montm\u00e9lian",
    "sg:orig_category":"Unclassifiable Establishments",
    "sg:phone":"+33 4 79 84 21 45",
    "sg:postcode":"73800",
    "sg:province":"Rhone-Alpes",
    "wof:name":"C.m.s.-braillon S.a.",
    "wof:placetype":"venue"
},
  "geometry": {"coordinates":[6.038695,45.448456],"type":"Point"}
}