{
  "type": "Feature",
  "properties": {
    "addr:full":"B.P. 4, 80400 Eppeville^^90, Rue du Mal Leclerc, 80400 Eppeville Picardie",
    "addr:housenumber":"4",
    "addr:postcode":"80400;80400",
    "addr:street":"B.P.;Rue Du Mal Leclerc",
    "iso:country":"FR",
    "sg:address":"B.P. 4, 80400 Eppeville^^90, Rue du Mal Leclerc, 80400 Eppeville",
    "sg:orig_category":"Non-Classified Establishments",
    "sg:phone":"+33 3 22 88 40 00",
    "sg:province":"Picardie",
    "wof:name":"Saint Louis Sucre S.n.c.",
    "wof:placetype":"venue"
},
  "geometry": {"coordinates":[3.074485,49.748417],"type":"Point"}
}