{
  "type": "Feature",
  "properties": {
    "addr:full":"Zone D'Activit\u00e9 Pr\u00e9 Roux 38190 Froges Rhone-Alpes 38190",
    "addr:postcode":"38190;38190",
    "addr:street":"Zone;\u0301 Pre\u0301 Roux;Rhone-Alpes",
    "iso:country":"FR",
    "sg:address":"Zone D'Activit\u00e9 Pr\u00e9 Roux 38190 Froges",
    "sg:classifiers":[
        {
            "category":"Manufacturing",
            "subcategory":"Paper Products",
            "type":"Manufacturing & Wholesale Goods"
        }
    ],
    "sg:phone":"+33 4 76 45 73 27",
    "sg:postcode":"38190",
    "sg:province":"Rhone-Alpes",
    "sg:tags":[
        "finished",
        "cardboard",
        "-"
    ],
    "wof:name":"Etiqsystems Sa",
    "wof:placetype":"venue"
},
  "geometry": {"coordinates":[5.92435,45.27322],"type":"Point"}
}