{
  "type": "Feature",
  "properties": {
    "iso:country":"FR",
    "sg:address":"4, Rue Gustave Eiffel, 71530 Crissey",
    "sg:city":"Crissey",
    "sg:orig_category":"Unclassifiable Establishments",
    "sg:phone":"+33 3 85 41 50 22",
    "sg:postcode":"71530",
    "sg:province":"Bourgogne",
    "wof:name":"Tremeau Industrie S.a.",
    "wof:placetype":"venue"
},
  "geometry": {"coordinates":[4.86856,46.823559],"type":"Point"}
}