{
  "type": "Feature",
  "properties": {
    "iso:country":"FR",
    "sg:address":"24 rue Borgnis Desbordes 78000 Versailles",
    "sg:classifiers":[
        {
            "category":"Farming",
            "subcategory":"Fish & Marine Products",
            "type":"Manufacturing & Wholesale Goods"
        }
    ],
    "sg:phone":"+33 1 39 50 49 23",
    "sg:province":"Ile de France",
    "sg:tags":[
        "metallurgy",
        "iron"
    ],
    "wof:name":"Metalliages Sa",
    "wof:placetype":"venue"
},
  "geometry": {"coordinates":[2.127934,48.793476],"type":"Point"}
}