{
  "type": "Feature",
  "properties": {
    "addr:full":"ZI du Monge Lourdes Midi Pyr\u00e9n\u00e9es 65100",
    "addr:postcode":"pyre\u0301ne\u0301es 65100",
    "addr:street":"Zi Du Monge",
    "iso:country":"FR",
    "sg:address":"ZI du Monge",
    "sg:city":"Lourdes",
    "sg:orig_category":"Unclassifiable Establishments",
    "sg:phone":"+33 5 62 42 73 42",
    "sg:postcode":"65100",
    "sg:province":"Midi Pyr\u00e9n\u00e9es",
    "wof:name":"Sewe Color S.a.",
    "wof:placetype":"venue"
},
  "geometry": {"coordinates":[-0.045999,43.096745],"type":"Point"}
}