{
  "type": "Feature",
  "properties": {
    "addr:full":"Rue Charles Nungesser - Mas des Cavaliers Mauguio Languedoc-Roussillon 34130",
    "addr:postcode":"34130",
    "addr:street":"Rue Charles Nungesser Mas Des Cavaliers",
    "iso:country":"FR",
    "sg:address":"Rue Charles Nungesser - Mas des Cavaliers",
    "sg:city":"Mauguio",
    "sg:orig_category":"Non-Classified Establishments",
    "sg:phone":"+33 4 67 99 49 00",
    "sg:postcode":"34130",
    "sg:province":"Languedoc-Roussillon",
    "wof:name":"Horanet Services Et Diffusion S.a.",
    "wof:placetype":"venue"
},
  "geometry": {"coordinates":[3.93489,43.58704],"type":"Point"}
}