{
  "type": "Feature",
  "properties": {
    "iso:country":"FR",
    "sg:address":"B.P. 159, 80203 P\u00e9ronne C\u00e9dex^^Rte Barleux, 80200 P\u00e9ronne",
    "sg:orig_category":"Non-Classified Establishments",
    "sg:phone":"+33 3 22 73 32 88",
    "sg:province":"Picardie",
    "wof:name":"Flodor Industrie S.a.",
    "wof:placetype":"venue"
},
  "geometry": {"coordinates":[2.935345,49.929661],"type":"Point"}
}