{
  "type": "Feature",
  "properties": {
    "addr:full":"Av. Rhin et Danube - P.A.E. Marenton Annonay Rhone-Alpes 07100",
    "addr:postcode":"07100",
    "addr:street":"Av. Rhin Et Danube P.A.E. Marenton;Rhone-Alpes",
    "iso:country":"FR",
    "sg:address":"Av. Rhin et Danube - P.A.E. Marenton",
    "sg:city":"Annonay",
    "sg:orig_category":"Unclassifiable Establishments",
    "sg:phone":"+33 4 75 67 07 00",
    "sg:postcode":"07100",
    "sg:province":"Rhone-Alpes",
    "wof:name":"Tissages De Quintenas S.a.",
    "wof:placetype":"venue"
},
  "geometry": {"coordinates":[4.68985,45.240707],"type":"Point"}
}