{
  "type": "Feature",
  "properties": {
    "addr:full":"place Narcisse Pavos 59271 Viesly Nord Pas-de-Calais",
    "addr:postcode":"59271",
    "addr:street":"Place Narcisse Pavos",
    "iso:country":"FR",
    "sg:address":"place Narcisse Pavos 59271 Viesly",
    "sg:classifiers":[
        {
            "category":"Manufacturing",
            "subcategory":"Building Materials",
            "type":"Manufacturing & Wholesale Goods"
        }
    ],
    "sg:phone":"+33 3 27 76 55 55",
    "sg:province":"Nord Pas-de-Calais",
    "sg:tags":[
        "textile",
        "industry",
        "carrier",
        "yarn"
    ],
    "wof:name":"Viesly Industries Textiles Sa",
    "wof:placetype":"venue"
},
  "geometry": {"coordinates":[3.46196,50.152382],"type":"Point"}
}