{
  "type": "Feature",
  "properties": {
    "addr:full":"B.P. 112 Nyons C\u00e9dex^^26110 Condorcet Rhone-Alpes 26110",
    "addr:housenumber":"b.p. 112",
    "addr:postcode":"26110",
    "addr:street":"Ce\u0301Dex^^26110",
    "iso:country":"FR",
    "sg:address":"B.P. 112",
    "sg:city":"Nyons C\u00e9dex^^26110 Condorcet",
    "sg:orig_category":"Non-Classified Establishments",
    "sg:phone":"+33 4 75 26 59 59",
    "sg:postcode":"26110",
    "sg:province":"Rhone-Alpes",
    "wof:name":"C.v.p. S.a. - Carlier Vermorelle Piers",
    "wof:placetype":"venue"
},
  "geometry": {"coordinates":[5.010615,44.29884],"type":"Point"}
}