{
  "type": "Feature",
  "properties": {
    "addr:full":"41, Rue Roland Garros, 78530 Buc Ile de France",
    "addr:housenumber":"41",
    "addr:postcode":"78530;ile",
    "addr:street":"Rue Roland Garros",
    "iso:country":"FR",
    "sg:address":"41, Rue Roland Garros, 78530 Buc",
    "sg:orig_category":"Unclassifiable Establishments",
    "sg:phone":"+33 1 39 56 03 27",
    "sg:province":"Ile de France",
    "wof:name":"Transports G. Moraud S.a.",
    "wof:placetype":"venue"
},
  "geometry": {"coordinates":[2.114842,48.764511],"type":"Point"}
}