{
  "type": "Feature",
  "properties": {
    "addr:full":"231 Rue De Lille 59650 Villeneuve D'Ascq Vill\u00e9 Alsace 67220",
    "addr:housenumber":"231",
    "addr:postcode":"59650;67220",
    "addr:street":"Rue De Lille",
    "iso:country":"FR",
    "sg:address":"231 Rue De Lille 59650 Villeneuve D'Ascq",
    "sg:city":"Vill\u00e9",
    "sg:classifiers":[
        {
            "category":"Shopping",
            "subcategory":"Clothing, Apparel, & Fashions",
            "type":"Retail Goods"
        }
    ],
    "sg:phone":"+33 3 20 05 54 26",
    "sg:postcode":"67220",
    "sg:province":"Alsace",
    "sg:tags":[
        "textile",
        "clothing",
        "clothes"
    ],
    "wof:name":"Petit Faune (grain De Lune)",
    "wof:placetype":"venue"
},
  "geometry": {"coordinates":[3.131357,50.647236],"type":"Point"}
}