{
  "type": "Feature",
  "properties": {
    "addr:full":"Za Aux Queches 71380 Alleriot All\u00e9riot Bourgogne 71380",
    "addr:postcode":"71380;71380",
    "addr:street":"Za Aux Queches",
    "iso:country":"FR",
    "sg:address":"Za Aux Queches 71380 Alleriot",
    "sg:city":"All\u00e9riot",
    "sg:classifiers":[
        {
            "category":"Farming",
            "subcategory":"Livestock Farm",
            "type":"Manufacturing & Wholesale Goods"
        }
    ],
    "sg:phone":"+33 3 85 47 50 11",
    "sg:postcode":"71380",
    "sg:province":"Bourgogne",
    "sg:tags":[
        "breeding",
        "agriculture",
        "animal"
    ],
    "wof:name":"Euro Dispal",
    "wof:placetype":"venue"
},
  "geometry": {"coordinates":[4.94511,46.815193],"type":"Point"}
}