{
  "type": "Feature",
  "properties": {
    "iso:country":"FR",
    "sg:address":"Zi Les M\u00fbres 26190 St Jean En Royans",
    "sg:classifiers":[
        {
            "category":"Shopping",
            "subcategory":"Crafts & Fabrics",
            "type":"Retail Goods"
        }
    ],
    "sg:phone":"+33 4 75 47 75 11",
    "sg:postcode":"26190",
    "sg:province":"Rhone-Alpes",
    "sg:tags":[
        "textile",
        "clothing"
    ],
    "wof:name":"Tissages Des Mures Sarl",
    "wof:placetype":"venue"
},
  "geometry": {"coordinates":[5.292025,45.016861],"type":"Point"}
}