{
  "type": "Feature",
  "properties": {
    "iso:country":"FR",
    "sg:address":"131, Rue Anatole France, 01100 Oyonnax",
    "sg:orig_category":"Non-Classified Establishments",
    "sg:phone":"+33 4 74 81 81 25",
    "sg:postcode":"01100",
    "sg:province":"Rhone-Alpes",
    "wof:name":"C.r.i.t. Int\u00e9rim S.a.",
    "wof:placetype":"venue"
},
  "geometry": {"coordinates":[5.654691,46.255936],"type":"Point"}
}