{
  "type": "Feature",
  "properties": {
    "iso:country":"FR",
    "sg:address":"ZI de Rib\u00e9court",
    "sg:city":"Pimprez",
    "sg:orig_category":"Unclassifiable Establishments",
    "sg:phone":"+33 3 44 75 03 03",
    "sg:postcode":"60170",
    "sg:province":"Picardie",
    "wof:name":"G.m.g. S.a.r.l.",
    "wof:placetype":"venue"
},
  "geometry": {"coordinates":[2.952331,49.514751],"type":"Point"}
}