{
  "type": "Feature",
  "properties": {
    "addr:full":"15, Bd Stalingrad, 44000 Nantes Pays de Loire",
    "addr:housenumber":"15",
    "addr:postcode":"44000",
    "addr:street":"Bd Stalingrad",
    "iso:country":"FR",
    "sg:address":"15, Bd Stalingrad, 44000 Nantes",
    "sg:orig_category":"Unclassifiable Establishments",
    "sg:phone":"+33 2 51 86 84 84",
    "sg:province":"Pays de Loire",
    "wof:name":"Auto Pi\u00e8ces Nantais S.a.",
    "wof:placetype":"venue"
},
  "geometry": {"coordinates":[-1.538466,47.218761],"type":"Point"}
}