{
  "type": "Feature",
  "properties": {
    "iso:country":"FR",
    "sg:address":"Le Moulin D Herbault Villedomer 37110 Auzouer En Touraine",
    "sg:city":"Villed\u00f4mer",
    "sg:classifiers":[
        {
            "category":"Manufacturing",
            "subcategory":"Chemicals & Compounds",
            "type":"Manufacturing & Wholesale Goods"
        }
    ],
    "sg:phone":"+33 2 47 56 90 46",
    "sg:postcode":"37110",
    "sg:province":"Centre",
    "sg:tags":[
        "pharmaceutical",
        "chemistry",
        "-",
        "by-product"
    ],
    "wof:name":"Synthron",
    "wof:placetype":"venue"
},
  "geometry": {"coordinates":[0.903285,47.585526],"type":"Point"}
}