{
  "type": "Feature",
  "properties": {
    "iso:country":"FR",
    "sg:address":"3 Pl De Saverne Les Renardi\u00e8res 92400 Courbevoie",
    "sg:classifiers":[
        {
            "category":"Wholesale",
            "subcategory":"Chemicals & Plastics",
            "type":"Manufacturing & Wholesale Goods"
        }
    ],
    "sg:phone":"+33 1 41 88 70 00",
    "sg:postcode":"92400",
    "sg:province":"Ile de France",
    "sg:tags":[
        "pharmaceutical",
        "energy"
    ],
    "wof:name":"Antargaz",
    "wof:placetype":"venue"
},
  "geometry": {"coordinates":[2.25645,48.895908],"type":"Point"}
}