{
  "type": "Feature",
  "properties": {
    "addr:full":"112, Chemin de la Noue, 74380 Cranves Sales Rhone-Alpes 74380",
    "addr:housenumber":"112",
    "addr:postcode":"74380;74380",
    "addr:street":"Chemin De La Noue",
    "iso:country":"FR",
    "sg:address":"112, Chemin de la Noue, 74380 Cranves Sales",
    "sg:orig_category":"Unclassifiable Establishments",
    "sg:phone":"+33 4 50 36 76 45",
    "sg:postcode":"74380",
    "sg:province":"Rhone-Alpes",
    "wof:name":"M\u00e9talhermet S.a.",
    "wof:placetype":"venue"
},
  "geometry": {"coordinates":[6.282525,46.181599],"type":"Point"}
}