{
  "type": "Feature",
  "properties": {
    "addr:full":"77316 Marne la Vall\u00e9e C\u00e9dex 02^^28, Rue des Vieilles Vignes, 77183 Croissy Beaubourg Ile de France",
    "addr:housenumber":"02 ^ ^ 28",
    "addr:postcode":"77316;77183",
    "addr:street":"Ce\u0301Dex;Rue Des Vieilles Vignes",
    "iso:country":"FR",
    "sg:address":"77316 Marne la Vall\u00e9e C\u00e9dex 02^^28, Rue des Vieilles Vignes, 77183 Croissy Beaubourg",
    "sg:orig_category":"Non-Classified Establishments",
    "sg:phone":"+33 1 69 67 10 00",
    "sg:province":"Ile de France",
    "wof:name":"Op\u00e9ra S.a.s.",
    "wof:placetype":"venue"
},
  "geometry": {"coordinates":[2.659334,48.828526],"type":"Point"}
}