{
  "type": "Feature",
  "properties": {
    "iso:country":"FR",
    "sg:address":"12 Pl De La R\u00e9publique 71100 Chalon Sur Sa\u00f4ne",
    "sg:city":"Chalon-sur-Sa\u00f4ne",
    "sg:classifiers":[
        {
            "category":"Autos & Motor Vehicles",
            "subcategory":"Automobile Sales",
            "type":"Retail Goods"
        }
    ],
    "sg:phone":"+33 3 85 48 12 14",
    "sg:postcode":"71100",
    "sg:province":"Bourgogne",
    "sg:tags":[
        "equipment",
        "motor-cars",
        "transport"
    ],
    "wof:name":"Sas",
    "wof:placetype":"venue"
},
  "geometry": {"coordinates":[4.847733,46.783497],"type":"Point"}
}