{
  "type": "Feature",
  "properties": {
    "addr:full":"1 Monc\u00e9 41100 Saint Firmin des Pr\u00e9s Centre 41100",
    "addr:housenumber":"1",
    "addr:postcode":"41100;41100",
    "addr:street":"Monce\u0301;Firmin Des Pre\u0301S",
    "iso:country":"FR",
    "sg:address":"1",
    "sg:city":"Monc\u00e9 41100 Saint Firmin des Pr\u00e9s",
    "sg:classifiers":[
        {
            "category":"Manufacturing",
            "subcategory":"Metals",
            "type":"Manufacturing & Wholesale Goods"
        }
    ],
    "sg:phone":"+33 2 54 23 40 74",
    "sg:postcode":"41100",
    "sg:province":"Centre",
    "sg:tags":[
        "metallurgy",
        "steel",
        "metalworking"
    ],
    "wof:name":"Lajoinie Fonderie",
    "wof:placetype":"venue"
},
  "geometry": {"coordinates":[1.0947,47.842274],"type":"Point"}
}