{
  "type": "Feature",
  "properties": {
    "addr:full":"13 Rue Saint Salomon 56000 Vannes Vannes Bretagne 56000",
    "addr:housenumber":"13",
    "addr:postcode":"56000;56000",
    "addr:street":"Rue Saint Salomon",
    "iso:country":"FR",
    "sg:address":"13 Rue Saint Salomon 56000 Vannes",
    "sg:city":"Vannes",
    "sg:classifiers":[
        {
            "category":"Shopping",
            "subcategory":"Clothing, Apparel, & Fashions",
            "type":"Retail Goods"
        }
    ],
    "sg:phone":"+33 2 97 42 50 03",
    "sg:postcode":"56000",
    "sg:province":"Bretagne",
    "sg:tags":[
        "textile",
        "clothing",
        "clothes"
    ],
    "wof:name":"Creation Et Production Sa Jean Bourget",
    "wof:placetype":"venue"
},
  "geometry": {"coordinates":[-2.758618,47.657143],"type":"Point"}
}