{
  "type": "Feature",
  "properties": {
    "addr:full":"17, Rue de la R\u00e9publique, 69002 Lyon Rhone-Alpes 69002",
    "addr:housenumber":"17",
    "addr:postcode":"69002;69002",
    "addr:street":"Rue De La Re\u0301Publique",
    "iso:country":"FR",
    "sg:address":"17, Rue de la R\u00e9publique, 69002 Lyon",
    "sg:orig_category":"Non-Classified Establishments",
    "sg:phone":"+33 4 78 28 17 77",
    "sg:postcode":"69002",
    "sg:province":"Rhone-Alpes",
    "wof:name":"Beaumont S.a.",
    "wof:placetype":"venue"
},
  "geometry": {"coordinates":[4.836093,45.76511],"type":"Point"}
}