{
  "type": "Feature",
  "properties": {
    "addr:full":"503 Route Des Rutys 77310 PRINGY Ile de France",
    "addr:housenumber":"503",
    "addr:postcode":"77310;ile",
    "addr:street":"Route Des Rutys",
    "iso:country":"FR",
    "sg:address":"503 Route Des Rutys 77310 PRINGY",
    "sg:classifiers":[
        {
            "category":"Manufacturing",
            "subcategory":"Lumber",
            "type":"Manufacturing & Wholesale Goods"
        }
    ],
    "sg:phone":"+33 4 50 27 19 94",
    "sg:province":"Ile de France",
    "sg:tags":[
        "overseas",
        "timber"
    ],
    "wof:name":"Socarit S.a.",
    "wof:placetype":"venue"
},
  "geometry": {"coordinates":[6.123919,45.941994],"type":"Point"}
}