{
  "type": "Feature",
  "properties": {
    "iso:country":"FR",
    "sg:address":"B.P. 23324, 44003 Nantes C\u00e9dex 01^^1, All\u00e9e Turenne, 44000 Nantes",
    "sg:orig_category":"Non-Classified Establishments",
    "sg:phone":"+33 2 40 47 93 25",
    "sg:province":"Pays de Loire",
    "wof:name":"Voyages Errien S.a.",
    "wof:placetype":"venue"
},
  "geometry": {"coordinates":[-1.553059,47.218117],"type":"Point"}
}