{
  "type": "Feature",
  "properties": {
    "iso:country":"FR",
    "sg:address":"4 Quai Kl\u00e9ber 67080 Strasbourg Cedex",
    "sg:city":"Strasbourg",
    "sg:classifiers":[
        {
            "category":"Professional",
            "subcategory":"Advertising",
            "type":"Services"
        }
    ],
    "sg:phone":"+33 3 88 76 42 35",
    "sg:postcode":"67000",
    "sg:province":"Alsace",
    "sg:tags":[
        "information",
        "medium",
        "communication"
    ],
    "wof:name":"Eic Mcis",
    "wof:placetype":"venue"
},
  "geometry": {"coordinates":[7.74202,48.585426],"type":"Point"}
}