{
  "type": "Feature",
  "properties": {
    "addr:full":"11 Impasse Du Rajol 12100 Millau Midi Pyr\u00e9n\u00e9es",
    "addr:housenumber":"11",
    "addr:postcode":"12100",
    "addr:street":"Impasse Du Rajol",
    "iso:country":"FR",
    "sg:address":"11 Impasse Du Rajol 12100 Millau",
    "sg:classifiers":[
        {
            "category":"Professional",
            "subcategory":"Printing & Photocopies",
            "type":"Services"
        }
    ],
    "sg:phone":"+33 5 65 61 15 08",
    "sg:province":"Midi Pyr\u00e9n\u00e9es",
    "sg:tags":[
        "publishing"
    ],
    "wof:name":"Vo2 Diffusion",
    "wof:placetype":"venue"
},
  "geometry": {"coordinates":[3.082494,44.099991],"type":"Point"}
}