{
  "type": "Feature",
  "properties": {
    "addr:full":"325 Route Du Cammas Zone Artisanale 46110 Vayrac Midi Pyr\u00e9n\u00e9es",
    "addr:housenumber":"325",
    "addr:postcode":"46110",
    "addr:street":"Route Du Cammas Zone Artisanale",
    "iso:country":"FR",
    "sg:address":"325 Route Du Cammas Zone Artisanale 46110 Vayrac",
    "sg:classifiers":[
        {
            "category":"Manufacturing",
            "subcategory":"Rubber & Plastics",
            "type":"Manufacturing & Wholesale Goods"
        }
    ],
    "sg:phone":"+33 5 65 32 44 47",
    "sg:province":"Midi Pyr\u00e9n\u00e9es",
    "wof:name":"Societe Des Industries Mecaniques Et Du Caoutchouc (simeca)",
    "wof:placetype":"venue"
},
  "geometry": {"coordinates":[1.740226,44.900391],"type":"Point"}
}