{
  "type": "Feature",
  "properties": {
    "iso:country":"FR",
    "sg:address":"11, Place Honor\u00e9 de Balzac, 77160 Provins",
    "sg:orig_category":"Unclassifiable Establishments",
    "sg:phone":"+33 1 60 67 60 67",
    "sg:province":"Ile de France",
    "wof:name":"Microtherm France S.a.r.l.",
    "wof:placetype":"venue"
},
  "geometry": {"coordinates":[3.298066,48.559341],"type":"Point"}
}