{
  "type": "Feature",
  "properties": {
    "addr:full":"B.P. 2 Landivy C\u00e9dex^^53190 Landivy Pays de Loire 53190",
    "addr:postcode":"53190",
    "addr:street":"B.P. 2;Ce\u0301Dex^^53190",
    "iso:country":"FR",
    "sg:address":"B.P. 2",
    "sg:city":"Landivy C\u00e9dex^^53190 Landivy",
    "sg:orig_category":"Non-Classified Establishments",
    "sg:phone":"+33 2 43 05 41 35",
    "sg:postcode":"53190",
    "sg:province":"Pays de Loire",
    "wof:name":"Etablissements Gontier S.a.",
    "wof:placetype":"venue"
},
  "geometry": {"coordinates":[-0.964924,48.448681],"type":"Point"}
}