{
  "type": "Feature",
  "properties": {
    "addr:full":"Zi Des Argiles Zi 84405 Apt",
    "addr:postcode":"84405",
    "addr:street":"Des Argiles Zi",
    "iso:country":"FR",
    "sg:address":"Zi Des Argiles Zi 84405 Apt",
    "sg:classifiers":[
        {
            "category":"Building & Trades",
            "subcategory":"Construction",
            "type":"Services"
        }
    ],
    "sg:phone":"+33 4 90 04 82 22",
    "sg:tags":[
        "work",
        "public"
    ],
    "wof:name":"Miditra\u00c7age",
    "wof:placetype":"venue"
},
  "geometry": {"coordinates":[5.395111,43.875885],"type":"Point"}
}