{
  "type": "Feature",
  "properties": {
    "iso:country":"FR",
    "sg:address":"48, Bd L\u00e9on Gambetta, 46000 Cahors",
    "sg:orig_category":"Unclassifiable Establishments",
    "sg:phone":"+33 5 65 23 28 28",
    "sg:province":"Midi Pyr\u00e9n\u00e9es",
    "wof:name":"Raynal Voyages S.a.r.l.",
    "wof:placetype":"venue"
},
  "geometry": {"coordinates":[1.441589,44.444122],"type":"Point"}
}