{
  "type": "Feature",
  "properties": {
    "addr:full":"55 Route Orbais 51210 Le Breuil Champagne 51210",
    "addr:housenumber":"55",
    "addr:postcode":"51210;51210",
    "addr:street":"Route Orbais",
    "iso:country":"FR",
    "sg:address":"55 Route Orbais 51210 Le Breuil",
    "sg:classifiers":[
        {
            "category":"Food Court",
            "type":"Food & Drink"
        }
    ],
    "sg:phone":"+33 3 26 59 21 09",
    "sg:postcode":"51210",
    "sg:province":"Champagne",
    "sg:tags":[
        "product",
        "related"
    ],
    "wof:name":"Champagne Jean Moutardier",
    "wof:placetype":"venue"
},
  "geometry": {"coordinates":[3.50046,48.78986],"type":"Point"}
}