{
  "type": "Feature",
  "properties": {
    "iso:country":"FR",
    "sg:address":"av Pierre et Marie Curie 06700 ST LAURENT DU VAR",
    "sg:classifiers":[
        {
            "category":"Manufacturing",
            "subcategory":"Printing",
            "type":"Manufacturing & Wholesale Goods"
        }
    ],
    "sg:phone":"+33 4 93 19 40 50",
    "sg:province":"Champagne",
    "sg:tags":[
        "house",
        "book"
    ],
    "wof:name":"Baud Sa",
    "wof:placetype":"venue"
},
  "geometry": {"coordinates":[7.184003,43.699554],"type":"Point"}
}