{
  "type": "Feature",
  "properties": {
    "addr:full":"7, Rue Charles Fourier, 75013 Paris Ile de France",
    "addr:housenumber":"7",
    "addr:postcode":"75013",
    "addr:street":"Rue Charles Fourier",
    "iso:country":"FR",
    "sg:address":"7, Rue Charles Fourier, 75013 Paris",
    "sg:orig_category":"Unclassifiable Establishments",
    "sg:phone":"+33 1 53 80 90 40",
    "sg:province":"Ile de France",
    "wof:name":"La Fourmi Informatique S.a.r.l.",
    "wof:placetype":"venue"
},
  "geometry": {"coordinates":[2.352296,48.824276],"type":"Point"}
}