{
  "type": "Feature",
  "properties": {
    "iso:country":"FR",
    "sg:address":"4 Bis Rue Anatole France 37300 Jou\u00e9 Les Tours",
    "sg:city":"Jou\u00e9-l\u00e8s-Tours",
    "sg:orig_category":"Miscellaneous Products",
    "sg:phone":"+33 2 47 67 00 39",
    "sg:postcode":"37300",
    "sg:province":"Centre",
    "wof:name":"Sa Du Roc Etablissement",
    "wof:placetype":"venue"
},
  "geometry": {"coordinates":[0.660512,47.354012],"type":"Point"}
}