{
  "type": "Feature",
  "properties": {
    "addr:full":"Rte de Mont sur Monnet Ney Franche Comt\u00e9 39300",
    "addr:postcode":"39300",
    "addr:street":"Rte De Mont Sur Monnet Ney Franche Comte\u0301",
    "iso:country":"FR",
    "sg:address":"Rte de Mont sur Monnet",
    "sg:city":"Ney",
    "sg:orig_category":"Unclassifiable Establishments",
    "sg:phone":"+33 3 84 52 04 30",
    "sg:postcode":"39300",
    "sg:province":"Franche Comt\u00e9",
    "wof:name":"Grandvuinet - Cattenoz S.a.",
    "wof:placetype":"venue"
},
  "geometry": {"coordinates":[5.907597,46.747177],"type":"Point"}
}