{
  "type": "Feature",
  "properties": {
    "iso:country":"FR",
    "sg:address":"7, Av. du March\u00e9 Commun, 44000 Nantes",
    "sg:orig_category":"Unclassifiable Establishments",
    "sg:phone":"+33 2 51 89 27 00",
    "sg:province":"Pays de Loire",
    "wof:name":"Fichet S\u00e9curit\u00e9 Electronique S.a.",
    "wof:placetype":"venue"
},
  "geometry": {"coordinates":[-1.499233,47.253822],"type":"Point"}
}