{
  "type": "Feature",
  "properties": {
    "addr:full":"Av. des Taillis - ZI Impasse du Rh\u00f4ne Corbas Rhone-Alpes 69960",
    "addr:postcode":"69960",
    "addr:street":"Av. Des Taillis Zi Impasse Du Rho\u0302Ne;Rhone-Alpes",
    "iso:country":"FR",
    "sg:address":"Av. des Taillis - ZI Impasse du Rh\u00f4ne",
    "sg:city":"Corbas",
    "sg:orig_category":"Non-Classified Establishments",
    "sg:phone":"+33 4 72 90 93 93",
    "sg:postcode":"69960",
    "sg:province":"Rhone-Alpes",
    "wof:name":"Flex Minute S.a.r.l.",
    "wof:placetype":"venue"
},
  "geometry": {"coordinates":[4.898495,45.670914],"type":"Point"}
}