{
  "type": "Feature",
  "properties": {
    "iso:country":"FR",
    "sg:address":"46 Rue Des Capucins 28100 Dreux",
    "sg:city":"Dreux",
    "sg:classifiers":[
        {
            "category":"Professional",
            "subcategory":"Business Services",
            "type":"Services"
        }
    ],
    "sg:phone":"+33 2 37 46 12 81",
    "sg:postcode":"28100",
    "sg:province":"Centre",
    "sg:tags":[
        "travel",
        "transport",
        "road"
    ],
    "wof:name":"Autocars Bon Voyage Sarl",
    "wof:placetype":"venue"
},
  "geometry": {"coordinates":[1.372593,48.739128],"type":"Point"}
}