{
  "type": "Feature",
  "properties": {
    "iso:country":"FR",
    "sg:address":"Immeuble Antinea; Montpellier",
    "sg:classifiers":[
        {
            "category":"Banks & Credit Unions",
            "subcategory":"Bank",
            "type":"Services"
        }
    ],
    "sg:phone":"+33 4 67 15 72 00",
    "sg:province":"Midi Pyr\u00e9n\u00e9es",
    "wof:name":"Societe Marseillaise, De Cr\u00e9dit Sa",
    "wof:placetype":"venue"
},
  "geometry": {"coordinates":[3.87609,43.610855],"type":"Point"}
}