{
  "type": "Feature",
  "properties": {
    "addr:full":"RN 4 - Le Corbier Jouy le Chatel Ile de France 77970",
    "addr:postcode":"77970",
    "addr:street":"Rn 4 Le Corbier;Le Chatel",
    "iso:country":"FR",
    "sg:address":"RN 4 - Le Corbier",
    "sg:city":"Jouy le Chatel",
    "sg:orig_category":"Non-Classified Establishments",
    "sg:phone":"+33 1 60 67 05 50",
    "sg:postcode":"77970",
    "sg:province":"Ile de France",
    "wof:name":"Europfil Traitement De Surfaces S.a.",
    "wof:placetype":"venue"
},
  "geometry": {"coordinates":[3.12582,48.668755],"type":"Point"}
}