{
  "type": "Feature",
  "properties": {
    "addr:full":"2 Place Becquet 52100 St Dizier Champagne 52100",
    "addr:housenumber":"2",
    "addr:postcode":"52100;52100",
    "addr:street":"Place Becquet;Champagne",
    "iso:country":"FR",
    "sg:address":"2 Place Becquet 52100 St Dizier",
    "sg:classifiers":[
        {
            "category":"Home & Garden",
            "subcategory":"Furniture",
            "type":"Retail Goods"
        }
    ],
    "sg:phone":"+33 3 25 04 18 00",
    "sg:postcode":"52100",
    "sg:province":"Champagne",
    "sg:tags":[
        "professional",
        "household",
        "wood"
    ],
    "wof:name":"Manathan Sarl",
    "wof:placetype":"venue"
},
  "geometry": {"coordinates":[4.992962,48.626171],"type":"Point"}
}