{
  "type": "Feature",
  "properties": {
    "addr:full":"Route Des Pernes Les Fontaines 84450 Saint Saturnin Les Avignon Aquitaine",
    "addr:postcode":"84450",
    "addr:street":"Route Des Pernes Les Fontaines;Saturnin",
    "iso:country":"FR",
    "sg:address":"Route Des Pernes Les Fontaines 84450 Saint Saturnin Les Avignon",
    "sg:classifiers":[
        {
            "category":"Home & Garden",
            "subcategory":"Furniture",
            "type":"Retail Goods"
        }
    ],
    "sg:phone":"+33 4 90 22 42 97",
    "sg:province":"Aquitaine",
    "sg:tags":[
        "wood"
    ],
    "wof:name":"Art Emballage",
    "wof:placetype":"venue"
},
  "geometry": {"coordinates":[4.93846,43.959003],"type":"Point"}
}