{
  "type": "Feature",
  "properties": {
    "addr:full":"Rue Amiral Favereau 56100 Lorient Lorient Bretagne 56100",
    "addr:postcode":"56100;56100",
    "addr:street":"Rue Amiral Favereau",
    "iso:country":"FR",
    "sg:address":"Rue Amiral Favereau 56100 Lorient",
    "sg:city":"Lorient",
    "sg:classifiers":[
        {
            "category":"Wholesale",
            "subcategory":"Meat",
            "type":"Manufacturing & Wholesale Goods"
        }
    ],
    "sg:phone":"+33 2 97 21 03 05",
    "sg:postcode":"56100",
    "sg:province":"Bretagne",
    "sg:tags":[
        "food",
        "cooked",
        "product",
        "related"
    ],
    "wof:name":"Loriviande Sarl",
    "wof:placetype":"venue"
},
  "geometry": {"coordinates":[-3.367729,47.766132],"type":"Point"}
}