{
  "type": "Feature",
  "properties": {
    "iso:country":"FR",
    "sg:address":"12 Av Condorcet 91240 St Michel Sur Orge",
    "sg:classifiers":[
        {
            "category":"Professional",
            "subcategory":"Engineering",
            "type":"Services"
        }
    ],
    "sg:phone":"+33 1 69 46 56 46",
    "sg:postcode":"91240",
    "sg:province":"Ile de France",
    "sg:tags":[
        "machine",
        "-",
        "mechanical"
    ],
    "wof:name":"Ferroli France Sarl",
    "wof:placetype":"venue"
},
  "geometry": {"coordinates":[2.32123,48.622459],"type":"Point"}
}