{
  "type": "Feature",
  "properties": {
    "addr:full":"40, Bd de Courcerin, 77185 Lognes Ile de France",
    "addr:housenumber":"40",
    "addr:postcode":"77185;ile",
    "addr:street":"Bd De Courcerin",
    "iso:country":"FR",
    "sg:address":"40, Bd de Courcerin, 77185 Lognes",
    "sg:orig_category":"Unclassifiable Establishments",
    "sg:phone":"+33 1 64 80 79 87",
    "sg:province":"Ile de France",
    "wof:name":"V.d. Sytelec S.n.c.",
    "wof:placetype":"venue"
},
  "geometry": {"coordinates":[2.617126,48.823563],"type":"Point"}
}