{
  "type": "Feature",
  "properties": {
    "iso:country":"FR",
    "sg:address":"10, R de la Gare aux Marchandises, 67380 Lingolsheim",
    "sg:city":"Lingolsheim",
    "sg:orig_category":"Non-Classified Establishments",
    "sg:phone":"+33 3 88 76 11 72",
    "sg:postcode":"67380",
    "sg:province":"Alsace",
    "wof:name":"Atelier La Boiserie S.a.r.l.",
    "wof:placetype":"venue"
},
  "geometry": {"coordinates":[7.6771,48.558392],"type":"Point"}
}