{
  "type": "Feature",
  "properties": {
    "iso:country":"FR",
    "sg:address":"Ld Basse Indre 44610 Indre",
    "sg:classifiers":[
        {
            "category":"Farming",
            "subcategory":"Farm",
            "type":"Manufacturing & Wholesale Goods"
        }
    ],
    "sg:phone":"+33 2 40 38 67 25",
    "sg:postcode":"44610",
    "sg:province":"Pays de Loire",
    "sg:tags":[
        "horticulture",
        "agriculture",
        "livestock"
    ],
    "wof:name":"Soferti Snc",
    "wof:placetype":"venue"
},
  "geometry": {"coordinates":[-1.671124,47.19857],"type":"Point"}
}