{
  "type": "Feature",
  "properties": {
    "addr:full":"Chemin de la Vall\u00e9e - ZI Saint Mitre Aubagne Franche Comt\u00e9 13400",
    "addr:postcode":"13400",
    "addr:street":"Chemin De La Valle\u0301E Zi Saint Mitre;Franche Comte\u0301",
    "iso:country":"FR",
    "sg:address":"Chemin de la Vall\u00e9e - ZI Saint Mitre",
    "sg:city":"Aubagne",
    "sg:orig_category":"Unclassifiable Establishments",
    "sg:phone":"+33 4 42 18 54 10",
    "sg:postcode":"13400",
    "sg:province":"Franche Comt\u00e9",
    "wof:name":"Dupont Vaffier S.a.r.l.",
    "wof:placetype":"venue"
},
  "geometry": {"coordinates":[5.5687,43.292141],"type":"Point"}
}