{
  "type": "Feature",
  "properties": {
    "iso:country":"FR",
    "sg:address":"B.P. 92, 74803 La Roche sur Foron C\u00e9dex^^50, Rue Ing\u00e9nieur Sansoule - ZI les Alfor\u00eats, 74800 La Roch",
    "sg:orig_category":"Non-Classified Establishments",
    "sg:phone":"+33 4 50 03 19 96",
    "sg:postcode":"74800",
    "sg:province":"Rhone-Alpes",
    "wof:name":"Electro Pr\u00e9cision S.a.",
    "wof:placetype":"venue"
},
  "geometry": {"coordinates":[-95.585648,46.868126],"type":"Point"}
}