{
  "type": "Feature",
  "properties": {
    "iso:country":"FR",
    "sg:address":"160 avenue du G\u00e9n\u00e9ral de Gaulle 02260 La Capelle",
    "sg:classifiers":[
        {
            "category":"Shopping",
            "subcategory":"Stationery & Office Supplies",
            "type":"Retail Goods"
        }
    ],
    "sg:phone":"+33 3 23 97 55 70",
    "sg:province":"Picardie",
    "sg:tags":[
        "paint",
        "brush"
    ],
    "wof:name":"Le H\u00e9risson Sa",
    "wof:placetype":"venue"
},
  "geometry": {"coordinates":[3.91766,49.984421],"type":"Point"}
}