{
  "type": "Feature",
  "properties": {
    "addr:full":"10, Rue du Havre, 75009 Paris Ile de France",
    "addr:housenumber":"10",
    "addr:postcode":"75009",
    "addr:street":"Rue Du Havre",
    "iso:country":"FR",
    "sg:address":"10, Rue du Havre, 75009 Paris",
    "sg:orig_category":"Unclassifiable Establishments",
    "sg:phone":"+33 1 53 20 46 90",
    "sg:province":"Ile de France",
    "wof:name":"Europe Technique 3000 S.a.",
    "wof:placetype":"venue"
},
  "geometry": {"coordinates":[2.326942,48.874985],"type":"Point"}
}