{
  "type": "Feature",
  "properties": {
    "addr:full":"73, Rue Claude Bernard, 75005 Paris Ile de France",
    "addr:housenumber":"73",
    "addr:postcode":"75005",
    "addr:street":"Rue Claude Bernard",
    "iso:country":"FR",
    "sg:address":"73, Rue Claude Bernard, 75005 Paris",
    "sg:orig_category":"Non-Classified Establishments",
    "sg:phone":"+33 1 58 52 15 21",
    "sg:province":"Ile de France",
    "wof:name":"Machination S.a.",
    "wof:placetype":"venue"
},
  "geometry": {"coordinates":[2.343993,48.840897],"type":"Point"}
}