{
  "type": "Feature",
  "properties": {
    "iso:country":"FR",
    "sg:address":"10 B, Rue Marc Urtin, 26500 Bourg l\u00e8s Valence",
    "sg:orig_category":"Unclassifiable Establishments",
    "sg:phone":"+33 4 75 42 47 76",
    "sg:province":"Rhone-Alpes",
    "wof:name":"Canon France",
    "wof:placetype":"venue"
},
  "geometry": {"coordinates":[4.894031,44.945126],"type":"Point"}
}