{
  "type": "Feature",
  "properties": {
    "addr:full":"42, Rue des Jardins, 68000 Colmar Colmar Alsace 68000",
    "addr:housenumber":"42",
    "addr:postcode":"68000;68000",
    "addr:street":"Rue Des Jardins",
    "iso:country":"FR",
    "sg:address":"42, Rue des Jardins, 68000 Colmar",
    "sg:city":"Colmar",
    "sg:orig_category":"Unclassifiable Establishments",
    "sg:phone":"+33 3 89 24 65 50",
    "sg:postcode":"68000",
    "sg:province":"Alsace",
    "wof:name":"L.k. Tours S.a.",
    "wof:placetype":"venue"
},
  "geometry": {"coordinates":[7.373206,48.076305],"type":"Point"}
}