{
  "type": "Feature",
  "properties": {
    "iso:country":"FR",
    "sg:address":"895 rue des Fr\u00e8res Lumi\u00e8re 71000 MACON",
    "sg:city":"Sanc\u00e9",
    "sg:classifiers":[
        {
            "category":"Food & Beverages",
            "subcategory":"Fruits & Vegetables",
            "type":"Retail Goods"
        }
    ],
    "sg:phone":"+33 3 85 20 47 00",
    "sg:postcode":"71000",
    "sg:province":"Bourgogne",
    "sg:tags":[
        "juice",
        "nectar"
    ],
    "wof:name":"Joker Sa",
    "wof:placetype":"venue"
},
  "geometry": {"coordinates":[4.816699,46.288372],"type":"Point"}
}