{
  "type": "Feature",
  "properties": {
    "iso:country":"FR",
    "sg:address":"3, Rue du B\u00e9n\u00e9lux - Zone Euronord, 31150 Lespinasse",
    "sg:orig_category":"Non-Classified Establishments",
    "sg:phone":"+33 5 61 35 05 00",
    "sg:province":"Midi Pyr\u00e9n\u00e9es",
    "wof:name":"P\u00e2tes Fra\u00eeches Luison S.a.r.l.",
    "wof:placetype":"venue"
},
  "geometry": {"coordinates":[1.411975,43.726673],"type":"Point"}
}