{
  "type": "Feature",
  "properties": {
    "iso:country":"FR",
    "sg:address":"746, Av. du G\u00e9n\u00e9ral Cartier, 73000 Chamb\u00e9ry",
    "sg:orig_category":"Unclassifiable Establishments",
    "sg:phone":"+33 4 79 69 18 81",
    "sg:postcode":"73000",
    "sg:province":"Rhone-Alpes",
    "wof:name":"Etablissements Descours & Cabaud Produits M\u00e9tallurgiques S.a.",
    "wof:placetype":"venue"
},
  "geometry": {"coordinates":[5.89722,45.577141],"type":"Point"}
}