{
  "type": "Feature",
  "properties": {
    "iso:country":"FR",
    "sg:address":"5, Rue de Bellevue, 91400 Orsay",
    "sg:orig_category":"Unclassifiable Establishments",
    "sg:phone":"+33 1 69 07 38 44",
    "sg:province":"Ile de France",
    "wof:name":"Supradis Automatismes S.a.",
    "wof:placetype":"venue"
},
  "geometry": {"coordinates":[2.184018,48.685951],"type":"Point"}
}