{
  "type": "Feature",
  "properties": {
    "iso:country":"FR",
    "sg:address":"31c Rue Des Landelles 35510 Cesson S\u00e9vign\u00e9",
    "sg:city":"Cesson-S\u00e9vign\u00e9",
    "sg:classifiers":[
        {
            "category":"Professional",
            "type":"Services"
        }
    ],
    "sg:phone":"+33 2 99 53 87 53",
    "sg:postcode":"35510",
    "sg:province":"Bretagne",
    "sg:tags":[
        "-",
        "related",
        "road",
        "transport"
    ],
    "wof:name":"Bama Courses",
    "wof:placetype":"venue"
},
  "geometry": {"coordinates":[-1.622268,48.100014],"type":"Point"}
}