{
  "type": "Feature",
  "properties": {
    "addr:full":"28 ave du G\u00e9n\u00e9ral de Gaulle; Strasbourg; 67000 Strasbourg Alsace 67000",
    "addr:postcode":"67000;67000",
    "addr:street":"28 Ave Du Ge\u0301Ne\u0301Ral De Gaulle",
    "iso:country":"FR",
    "sg:address":"28 ave du G\u00e9n\u00e9ral de Gaulle; Strasbourg; 67000",
    "sg:city":"Strasbourg",
    "sg:classifiers":[
        {
            "category":"Banks & Credit Unions",
            "subcategory":"Bank",
            "type":"Services"
        }
    ],
    "sg:phone":"+33 3 88 45 97 40",
    "sg:postcode":"67000",
    "sg:province":"Alsace",
    "wof:name":"Cr\u00e9dit Industriel D'alsace, De Lorraine Sa",
    "wof:placetype":"venue"
},
  "geometry": {"coordinates":[7.76897,48.577595],"type":"Point"}
}