{
  "type": "Feature",
  "properties": {
    "addr:full":"2, Chemin Passe aux Fresnes, 02450 La Neuville l\u00e8s Dorengt Picardie",
    "addr:housenumber":"2",
    "addr:postcode":"02450",
    "addr:street":"Chemin Passe Aux Fresnes;Picardie",
    "iso:country":"FR",
    "sg:address":"2, Chemin Passe aux Fresnes, 02450 La Neuville l\u00e8s Dorengt",
    "sg:orig_category":"Unclassifiable Establishments",
    "sg:phone":"+33 3 23 60 67 26",
    "sg:province":"Picardie",
    "wof:name":"Porembski Transports S.a.",
    "wof:placetype":"venue"
},
  "geometry": {"coordinates":[3.672077,49.977772],"type":"Point"}
}