{
  "type": "Feature",
  "properties": {
    "iso:country":"FR",
    "sg:address":"Rte du Rialet - Le Mazet",
    "sg:city":"Payrin Augmontel",
    "sg:orig_category":"Non-Classified Establishments",
    "sg:phone":"+33 5 63 61 66 48",
    "sg:postcode":"81660",
    "sg:province":"Midi Pyr\u00e9n\u00e9es",
    "wof:name":"Soci\u00e9t\u00e9 Martineau P. S.a.r.l.",
    "wof:placetype":"venue"
},
  "geometry": {"coordinates":[2.405188,43.503761],"type":"Point"}
}