{
  "type": "Feature",
  "properties": {
    "addr:full":"211av Des Gr\u00e9sillons Gennevilliers Ile de France 92231",
    "addr:postcode":"92231",
    "iso:country":"FR",
    "sg:address":"211av Des Gr\u00e9sillons",
    "sg:city":"Gennevilliers",
    "sg:classifiers":[
        {
            "category":"Banks & Credit Unions",
            "subcategory":"Financial Services",
            "type":"Services"
        }
    ],
    "sg:phone":"+33 1 41 32 12 12",
    "sg:postcode":"92231",
    "sg:province":"Ile de France",
    "sg:tags":[
        "banking",
        "finance",
        "insurance"
    ],
    "wof:name":"Alliance Sante",
    "wof:placetype":"venue"
},
  "geometry": {"coordinates":[2.315334,48.920288],"type":"Point"}
}