{
  "type": "Feature",
  "properties": {
    "addr:full":"B.P. 37, 42001 Saint Etienne C\u00e9dex 1^^20, Rue Victor Grignard, 42000 Saint Etienne Rhone-Alpes 42000",
    "addr:housenumber":"1 ^ ^ 20",
    "addr:postcode":"42001;42000;42000",
    "addr:street":"B.P. 37;Ce\u0301Dex;Rue Victor Grignard",
    "iso:country":"FR",
    "sg:address":"B.P. 37, 42001 Saint Etienne C\u00e9dex 1^^20, Rue Victor Grignard, 42000 Saint Etienne",
    "sg:orig_category":"Non-Classified Establishments",
    "sg:phone":"+33 4 77 74 24 22",
    "sg:postcode":"42000",
    "sg:province":"Rhone-Alpes",
    "wof:name":"Soci\u00e9t\u00e9 Chomienne E.g.i.e. S.a.r.l.",
    "wof:placetype":"venue"
},
  "geometry": {"coordinates":[4.401943,45.45929],"type":"Point"}
}