{
  "type": "Feature",
  "properties": {
    "addr:full":"6, Chemin des Alpilles, 04000 Digne les Bains Provence-Alpes-C\u00f4te d'Azur",
    "addr:housenumber":"6",
    "addr:postcode":"04000",
    "addr:street":"Chemin Des Alpilles;Les Bains",
    "iso:country":"FR",
    "sg:address":"6, Chemin des Alpilles, 04000 Digne les Bains",
    "sg:orig_category":"Unclassifiable Establishments",
    "sg:phone":"+33 4 92 36 61 70",
    "sg:province":"Provence-Alpes-C\u00f4te d'Azur",
    "wof:name":"Razel Pico Sud S.a.",
    "wof:placetype":"venue"
},
  "geometry": {"coordinates":[6.206119,44.082474],"type":"Point"}
}