{
  "type": "Feature",
  "properties": {
    "addr:full":"65, Rue Emile Hauviller, 70500 Corre Franche Comt\u00e9",
    "addr:housenumber":"65",
    "addr:postcode":"70500",
    "addr:street":"Rue Emile Hauviller;Franche Comte\u0301",
    "iso:country":"FR",
    "sg:address":"65, Rue Emile Hauviller, 70500 Corre",
    "sg:orig_category":"Unclassifiable Establishments",
    "sg:phone":"+33 3 84 92 52 52",
    "sg:province":"Franche Comt\u00e9",
    "wof:name":"Detroye S.a.",
    "wof:placetype":"venue"
},
  "geometry": {"coordinates":[5.995035,47.918896],"type":"Point"}
}