{
  "type": "Feature",
  "properties": {
    "addr:full":"85 rue Sebastien Choulette 54200 Toul Lorraine",
    "addr:housenumber":"85",
    "addr:postcode":"54200",
    "addr:street":"Rue Sebastien Choulette",
    "iso:country":"FR",
    "sg:address":"85 rue Sebastien Choulette 54200 Toul",
    "sg:orig_category":"Sweepers, Industrial",
    "sg:phone":"+33 3 83 65 22 22",
    "sg:province":"Lorraine",
    "wof:name":"Mathieu Yno S.a.",
    "wof:placetype":"venue"
},
  "geometry": {"coordinates":[5.887047,48.670372],"type":"Point"}
}