{
  "type": "Feature",
  "properties": {
    "addr:full":"122, Rue du Temple, 62000 Arras Nord Pas-de-Calais 62000",
    "addr:housenumber":"122",
    "addr:postcode":"62000;62000",
    "addr:street":"Rue Du Temple",
    "iso:country":"FR",
    "sg:address":"122, Rue du Temple, 62000 Arras",
    "sg:orig_category":"Non-Classified Establishments",
    "sg:phone":"+33 3 21 55 54 22",
    "sg:postcode":"62000",
    "sg:province":"Nord Pas-de-Calais",
    "wof:name":"C.e.r. S.a.r.l. - Constructions Electrom\u00e9caniques Reaumur",
    "wof:placetype":"venue"
},
  "geometry": {"coordinates":[2.78661,50.280998],"type":"Point"}
}