{
  "type": "Feature",
  "properties": {
    "addr:full":"zi Luceau 72500 Ch\u00e2teau du Loir Pays de Loire 72500",
    "addr:postcode":"72500;72500",
    "addr:street":"Loir",
    "iso:country":"FR",
    "sg:address":"zi Luceau 72500 Ch\u00e2teau du Loir",
    "sg:classifiers":[
        {
            "category":"Professional",
            "subcategory":"Engineering",
            "type":"Services"
        }
    ],
    "sg:phone":"+33 2 43 38 10 10",
    "sg:postcode":"72500",
    "sg:province":"Pays de Loire",
    "sg:tags":[
        "machine",
        "-",
        "mechanical"
    ],
    "wof:name":"Thermo-refrigeration (sa)",
    "wof:placetype":"venue"
},
  "geometry": {"coordinates":[0.41794,47.695484],"type":"Point"}
}