{
  "type": "Feature",
  "properties": {
    "iso:country":"FR",
    "sg:address":"10, Rue Ettore Bugatti, 67000 Eckbolsheim",
    "sg:city":"Strasbourg",
    "sg:orig_category":"Unclassifiable Establishments",
    "sg:phone":"+33 3 88 78 80 81",
    "sg:postcode":"67000",
    "sg:province":"Alsace",
    "wof:name":"Dectra Pharm S.a.",
    "wof:placetype":"venue"
},
  "geometry": {"coordinates":[7.73643,48.585079],"type":"Point"}
}