{
  "type": "Feature",
  "properties": {
    "addr:full":"pl Mairie; Labouheyre Centre",
    "addr:street":"Pl",
    "iso:country":"FR",
    "sg:address":"pl Mairie; Labouheyre",
    "sg:classifiers":[
        {
            "category":"Banks & Credit Unions",
            "subcategory":"Bank",
            "type":"Services"
        }
    ],
    "sg:phone":"+33 3358070079",
    "sg:province":"Centre",
    "wof:name":"Cr\u00e9dit Agricole Du Sud Ouest",
    "wof:placetype":"venue"
},
  "geometry": {"coordinates":[-0.919579,44.212688],"type":"Point"}
}