{
  "type": "Feature",
  "properties": {
    "iso:country":"FR",
    "sg:address":"Rue des Voeux Saint Georges",
    "sg:city":"Villeneuve le Roi",
    "sg:orig_category":"Unclassifiable Establishments",
    "sg:phone":"+33 1 41 65 91 00",
    "sg:postcode":"94290",
    "sg:province":"Ile de France",
    "wof:name":"B.s.a. S.a. - Blemding Et Services Associ\u00e9s",
    "wof:placetype":"venue"
},
  "geometry": {"coordinates":[2.438956,48.731197],"type":"Point"}
}