{
  "type": "Feature",
  "properties": {
    "iso:country":"FR",
    "sg:address":"B.P. 8, 77411 Claye Souilly C\u00e9dex^^Rue de la Gabrielle Prolong\u00e9e, 77410 Claye Souilly",
    "sg:orig_category":"Non-Classified Establishments",
    "sg:phone":"+33 1 60 26 18 84",
    "sg:province":"Ile de France",
    "wof:name":"Somifra S.a. - Soci\u00e9t\u00e9 Outillage Et M\u00e9canique Ile-de-france",
    "wof:placetype":"venue"
},
  "geometry": {"coordinates":[2.68843,48.945576],"type":"Point"}
}