{
  "type": "Feature",
  "properties": {
    "addr:full":"B.P. 128, 78148 V\u00e9lizy Villacoublay C\u00e9dex^^18, Rue Grange Dame Rose - B\u00e2t Avenir, 78140 V\u00e9lizy Villa Ile de France 78140",
    "addr:housenumber":"b.p. 128;ba\u0302t",
    "addr:postcode":"78148;78140;78140",
    "addr:street":"Rue Grange Dame Rose",
    "iso:country":"FR",
    "sg:address":"B.P. 128, 78148 V\u00e9lizy Villacoublay C\u00e9dex^^18, Rue Grange Dame Rose - B\u00e2t Avenir, 78140 V\u00e9lizy Villa",
    "sg:orig_category":"Non-Classified Establishments",
    "sg:phone":"+33 1 34 88 53 00",
    "sg:postcode":"78140",
    "sg:province":"Ile de France",
    "wof:name":"Cadence Design Systems S.a.s.",
    "wof:placetype":"venue"
},
  "geometry": {"coordinates":[2.18246,48.78503],"type":"Point"}
}