{
  "type": "Feature",
  "properties": {
    "addr:full":"1666, Chemin de la Gaude, 06140 Vence Franche Comt\u00e9",
    "addr:housenumber":"1666",
    "addr:postcode":"06140",
    "addr:street":"Chemin De La Gaude;Franche Comte\u0301",
    "iso:country":"FR",
    "sg:address":"1666, Chemin de la Gaude, 06140 Vence",
    "sg:orig_category":"Unclassifiable Establishments",
    "sg:phone":"+33 4 93 58 06 58",
    "sg:province":"Franche Comt\u00e9",
    "wof:name":"Photogravure Offset Azur S.a.r.l.",
    "wof:placetype":"venue"
},
  "geometry": {"coordinates":[7.136965,43.717209],"type":"Point"}
}