{
  "type": "Feature",
  "properties": {
    "iso:country":"FR",
    "sg:address":"P\u00e9ricentre de la C\u00e9pi\u00e8re",
    "sg:city":"Toulouse C\u00e9dex",
    "sg:orig_category":"Non-Classified Establishments",
    "sg:phone":"+33 5 62 14 82 02",
    "sg:postcode":"31081",
    "sg:province":"Languedoc-Roussillon",
    "wof:name":"Coface",
    "wof:placetype":"venue"
},
  "geometry": {"coordinates":[1.44301,43.604359],"type":"Point"}
}