{
  "type": "Feature",
  "properties": {
    "iso:country":"FR",
    "sg:address":"9, Rue Robert Schumann, 76000 Rouen",
    "sg:orig_category":"Unclassifiable Establishments",
    "sg:phone":"+33 2 35 88 44 42",
    "sg:province":"Haute Normandie",
    "wof:name":"C.r.c.i. De Haute Normandie - Chambre R\u00e9gionale De Commerce Et D'industrie De Haute Normandie",
    "wof:placetype":"venue"
},
  "geometry": {"coordinates":[1.103276,49.437958],"type":"Point"}
}