{
  "type": "Feature",
  "properties": {
    "addr:full":"Rue Celestin Linder 42780 VIOLAY Rhone-Alpes 42780",
    "addr:postcode":"42780;42780",
    "addr:street":"Rue Celestin Linder;Rhone-Alpes",
    "iso:country":"FR",
    "sg:address":"Rue Celestin Linder 42780 VIOLAY",
    "sg:classifiers":[
        {
            "category":"Manufacturing",
            "subcategory":"Textiles",
            "type":"Manufacturing & Wholesale Goods"
        }
    ],
    "sg:phone":"+33 4 74 63 99 90",
    "sg:postcode":"42780",
    "sg:province":"Rhone-Alpes",
    "sg:tags":[
        "curtain",
        "fabric"
    ],
    "wof:name":"France Voiles Sa",
    "wof:placetype":"venue"
},
  "geometry": {"coordinates":[4.357001,45.852264],"type":"Point"}
}