{
  "type": "Feature",
  "properties": {
    "iso:country":"FR",
    "sg:address":"B.P. 11, 60590 Trie Ch\u00e2teau^^30, Av des Tamaris, 60590 Trie Ch\u00e2teau",
    "sg:orig_category":"Non-Classified Establishments",
    "sg:phone":"+33 3 44 49 77 99",
    "sg:postcode":"60590",
    "sg:province":"Picardie",
    "wof:name":"C.b.m. Informatique S.a.r.l.",
    "wof:placetype":"venue"
},
  "geometry": {"coordinates":[1.820488,49.285877],"type":"Point"}
}