{
  "type": "Feature",
  "properties": {
    "addr:full":"19 ave Jules Ferry; Les Clayes sous Bois; 78340 Ile de France 78340",
    "addr:postcode":"78340;78340",
    "addr:street":"19 Ave Jules Ferry;Ile De France",
    "iso:country":"FR",
    "sg:address":"19 ave Jules Ferry; Les Clayes sous Bois; 78340",
    "sg:classifiers":[
        {
            "category":"Banks & Credit Unions",
            "subcategory":"Bank",
            "type":"Services"
        }
    ],
    "sg:phone":"+33 30553591",
    "sg:postcode":"78340",
    "sg:province":"Ile de France",
    "wof:name":"Banque Nationale De Paris",
    "wof:placetype":"venue"
},
  "geometry": {"coordinates":[1.986528,48.822765],"type":"Point"}
}