{
  "type": "Feature",
  "properties": {
    "iso:country":"FR",
    "sg:address":"ZI de Chesnaie - Actipole 35",
    "sg:city":"Miniac Morvan",
    "sg:orig_category":"Non-Classified Establishments",
    "sg:phone":"+33 2 99 58 00 02",
    "sg:postcode":"35540",
    "sg:province":"Bretagne",
    "wof:name":"Rototec S.a.",
    "wof:placetype":"venue"
},
  "geometry": {"coordinates":[-1.836639,48.486481],"type":"Point"}
}