{
  "type": "Feature",
  "properties": {
    "iso:country":"FR",
    "sg:address":"B.P. 512, 50305 Avranches C\u00e9dex^^21, Bd Amiral Gauchet, 50300 Avranches",
    "sg:city":"Avranches",
    "sg:orig_category":"Non-Classified Establishments",
    "sg:phone":"+33 2 33 79 09 09",
    "sg:postcode":"50300",
    "sg:province":"Basse Normandie",
    "wof:name":"De Kerpel-day Associates S.a.r.l.",
    "wof:placetype":"venue"
},
  "geometry": {"coordinates":[-1.377784,48.663998],"type":"Point"}
}