{
  "type": "Feature",
  "properties": {
    "addr:full":"Route Nationale 414 Rehainviller Lorraine 54300",
    "addr:postcode":"414;54300",
    "addr:street":"Route Nationale;Rehainviller Lorraine",
    "iso:country":"FR",
    "sg:address":"Route Nationale 414",
    "sg:city":"Rehainviller",
    "sg:orig_category":"Non-Classified Establishments",
    "sg:phone":"+33 3 83 74 00 38",
    "sg:postcode":"54300",
    "sg:province":"Lorraine",
    "wof:name":"Socomec S.a.r.l. - Soci\u00e9t\u00e9 Constructions M\u00e9caniques De Chaufontaine",
    "wof:placetype":"venue"
},
  "geometry": {"coordinates":[6.49027,48.59306],"type":"Point"}
}