{
  "type": "Feature",
  "properties": {
    "iso:country":"FR",
    "sg:address":"13, Rue de la Violaie, 49500 Chaz\u00e9 sur Argos",
    "sg:orig_category":"Non-Classified Establishments",
    "sg:phone":"+33 2 41 61 44 46",
    "sg:province":"Pays de Loire",
    "wof:name":"Lesurtel J.c. S.a.r.l.",
    "wof:placetype":"venue"
},
  "geometry": {"coordinates":[-0.895299,47.613922],"type":"Point"}
}