{
  "type": "Feature",
  "properties": {
    "addr:full":"16 Rue Du Docteur Paul Chevallier 49504 Segr\u00e9 Cedex Allier Midi Pyr\u00e9n\u00e9es 65360",
    "addr:housenumber":"16",
    "addr:postcode":"49504;65360",
    "addr:street":"Rue Du Docteur Paul Chevallier",
    "iso:country":"FR",
    "sg:address":"16 Rue Du Docteur Paul Chevallier 49504 Segr\u00e9 Cedex",
    "sg:city":"Allier",
    "sg:classifiers":[
        {
            "category":"Shopping",
            "subcategory":"Computers & Home Electronics",
            "type":"Retail Goods"
        }
    ],
    "sg:phone":"+33 2 41 94 71 71",
    "sg:postcode":"65360",
    "sg:province":"Midi Pyr\u00e9n\u00e9es",
    "sg:tags":[
        "electric",
        "electricity",
        "component",
        "equipment",
        "electrical",
        "electronic"
    ],
    "wof:name":"Juret Sa",
    "wof:placetype":"venue"
},
  "geometry": {"coordinates":[-0.869269,47.683037],"type":"Point"}
}