{
  "type": "Feature",
  "properties": {
    "addr:full":"36, Av de la Lib\u00e9ration, 54600 Villers l\u00e8s Nancy Lorraine",
    "addr:postcode":"54600",
    "addr:street":"36 Av De La Libe\u0301Ration",
    "iso:country":"FR",
    "sg:address":"36, Av de la Lib\u00e9ration, 54600 Villers l\u00e8s Nancy",
    "sg:orig_category":"Unclassifiable Establishments",
    "sg:phone":"+33 3 83 27 32 65",
    "sg:province":"Lorraine",
    "wof:name":"Nadess S.a.",
    "wof:placetype":"venue"
},
  "geometry": {"coordinates":[6.159007,48.677738],"type":"Point"}
}