{
  "type": "Feature",
  "properties": {
    "iso:country":"FR",
    "sg:address":"2, Rue Gambetta, 38490 Saint Andr\u00e9 le Gaz",
    "sg:orig_category":"Unclassifiable Establishments",
    "sg:phone":"+33 4 74 88 74 66",
    "sg:province":"Rhone-Alpes",
    "wof:name":"Acrylics Technics S.a.r.l.",
    "wof:placetype":"venue"
},
  "geometry": {"coordinates":[5.532633,45.544247],"type":"Point"}
}