{
  "type": "Feature",
  "properties": {
    "iso:country":"FR",
    "sg:address":"rue des Artisans 64500 St Jean de Luz",
    "sg:city":"Ciboure",
    "sg:classifiers":[
        {
            "category":"Manufacturing",
            "subcategory":"Rubber & Plastics",
            "type":"Manufacturing & Wholesale Goods"
        }
    ],
    "sg:phone":"+33 5 59 26 71 58",
    "sg:postcode":"64500",
    "sg:province":"Aquitaine",
    "sg:tags":[
        "profile"
    ],
    "wof:name":"Logotext C.g.a. Sa",
    "wof:placetype":"venue"
},
  "geometry": {"coordinates":[-1.626493,43.403362],"type":"Point"}
}