{
  "type": "Feature",
  "properties": {
    "addr:full":"6/8, Rue Devallois, 78290 Croissy sur Seine Ile de France",
    "addr:housenumber":"6 / 8",
    "addr:postcode":"78290",
    "addr:street":"Rue Devallois",
    "iso:country":"FR",
    "sg:address":"6/8, Rue Devallois, 78290 Croissy sur Seine",
    "sg:orig_category":"Non-Classified Establishments",
    "sg:phone":"+33 1 39 76 55 02",
    "sg:province":"Ile de France",
    "wof:name":"Sintco S.a.",
    "wof:placetype":"venue"
},
  "geometry": {"coordinates":[2.13582,48.872635],"type":"Point"}
}