{
  "type": "Feature",
  "properties": {
    "addr:full":"Rue de Saint Alban les Vignes Vienne Rhone-Alpes 38200",
    "addr:postcode":"38200",
    "addr:street":"Rue De Saint Alban Les",
    "iso:country":"FR",
    "sg:address":"Rue de Saint Alban les Vignes",
    "sg:city":"Vienne",
    "sg:orig_category":"Unclassifiable Establishments",
    "sg:phone":"+33 4 74 31 69 52",
    "sg:postcode":"38200",
    "sg:province":"Rhone-Alpes",
    "wof:name":"I.p.r. Distribution S.a.r.l. - Is\u00e8re Plastique R\u00e9alisation Distribution",
    "wof:placetype":"venue"
},
  "geometry": {"coordinates":[4.852434,45.500721],"type":"Point"}
}