{
  "type": "Feature",
  "properties": {
    "iso:country":"FR",
    "sg:address":"1 Rue Du Coll\u00e8ge 53190 Landivy",
    "sg:classifiers":[
        {
            "category":"Real Estate",
            "subcategory":"Surveying",
            "type":"Services"
        }
    ],
    "sg:phone":"+33 2 43 05 40 92",
    "sg:postcode":"53190",
    "sg:province":"Pays de Loire",
    "sg:tags":[
        "leather",
        "raw",
        "material",
        "-",
        "shoe"
    ],
    "wof:name":"Socopa Cuirs Gie",
    "wof:placetype":"venue"
},
  "geometry": {"coordinates":[-1.024028,48.478882],"type":"Point"}
}