{
  "type": "Feature",
  "properties": {
    "iso:country":"FR",
    "sg:address":"1, Rue des Fr\u00e8res Rannou, 29140 Rosporden",
    "sg:city":"Rosporden",
    "sg:orig_category":"Non-Classified Establishments",
    "sg:phone":"+33 2 98 59 89 46",
    "sg:postcode":"29140",
    "sg:province":"Bretagne",
    "wof:name":"Etablissements Georgelin S.a.r.l.",
    "wof:placetype":"venue"
},
  "geometry": {"coordinates":[-3.829559,47.958031],"type":"Point"}
}