{
  "type": "Feature",
  "properties": {
    "iso:country":"FR",
    "sg:address":"165 Rue Louis Mallet 18000 Bourges",
    "sg:city":"Bourges",
    "sg:classifiers":[
        {
            "category":"Professional",
            "type":"Services"
        }
    ],
    "sg:phone":"+33 2 48 21 87 10",
    "sg:postcode":"18000",
    "sg:province":"Centre",
    "sg:tags":[
        "transport"
    ],
    "wof:name":"Transports Heles",
    "wof:placetype":"venue"
},
  "geometry": {"coordinates":[2.36268,47.081825],"type":"Point"}
}