{
  "type": "Feature",
  "properties": {
    "addr:full":"8, Rue Jules Py, 88210 Moussey Lorraine",
    "addr:housenumber":"8",
    "addr:postcode":"88210",
    "addr:street":"Rue Jules Py",
    "iso:country":"FR",
    "sg:address":"8, Rue Jules Py, 88210 Moussey",
    "sg:orig_category":"Unclassifiable Establishments",
    "sg:phone":"+33 3 29 42 50 05",
    "sg:province":"Lorraine",
    "wof:name":"T.s.a Plastiques S.a.r.l. - Techniques De Soudure Appliqu\u00e9es",
    "wof:placetype":"venue"
},
  "geometry": {"coordinates":[7.026682,48.432308],"type":"Point"}
}