{
  "type": "Feature",
  "properties": {
    "iso:country":"FR",
    "sg:address":"33, Rue des Trois Fronti\u00e8res, 68110 Illzach",
    "sg:city":"Illzach",
    "sg:orig_category":"Unclassifiable Establishments",
    "sg:phone":"+33 3 89 61 82 88",
    "sg:postcode":"68110",
    "sg:province":"Alsace",
    "wof:name":"Hengstenberg S.a.r.l.",
    "wof:placetype":"venue"
},
  "geometry": {"coordinates":[7.392493,47.773304],"type":"Point"}
}