{
  "type": "Feature",
  "properties": {
    "addr:full":"23, Rue Bugatti, 37000 Tours Tours Centre 37000",
    "addr:housenumber":"23",
    "addr:postcode":"37000;37000",
    "addr:street":"Rue Bugatti",
    "iso:country":"FR",
    "sg:address":"23, Rue Bugatti, 37000 Tours",
    "sg:city":"Tours",
    "sg:orig_category":"Unclassifiable Establishments",
    "sg:phone":"+33 2 47 77 13 00",
    "sg:postcode":"37000",
    "sg:province":"Centre",
    "wof:name":"C.a.t. S.a. - Compagnie Des Autocars De Tourraine",
    "wof:placetype":"venue"
},
  "geometry": {"coordinates":[0.665576,47.377018],"type":"Point"}
}