{
  "type": "Feature",
  "properties": {
    "addr:full":"3 Av Jean Bonnefont 36100 Issoudun Issoudun Centre 36100",
    "addr:postcode":"36100;36100",
    "addr:street":"Av Jean Bonnefont",
    "iso:country":"FR",
    "sg:address":"3 Av Jean Bonnefont 36100 Issoudun",
    "sg:city":"Issoudun",
    "sg:classifiers":[
        {
            "category":"Farming",
            "subcategory":"Farm",
            "type":"Manufacturing & Wholesale Goods"
        }
    ],
    "sg:phone":"+33 2 54 03 38 38",
    "sg:postcode":"36100",
    "sg:province":"Centre",
    "sg:tags":[
        "horticulture",
        "agriculture",
        "livestock"
    ],
    "wof:name":"Socofer Sa",
    "wof:placetype":"venue"
},
  "geometry": {"coordinates":[1.998108,46.95911],"type":"Point"}
}