{
  "type": "Feature",
  "properties": {
    "iso:country":"FR",
    "sg:address":"Rte d'Apchat",
    "sg:city":"Ardes",
    "sg:orig_category":"Unclassifiable Establishments",
    "sg:phone":"+33 5 57 26 14 70",
    "sg:postcode":"63420",
    "sg:province":"Auvergne",
    "wof:name":"Elsi S.a.",
    "wof:placetype":"venue"
},
  "geometry": {"coordinates":[3.12702,45.404419],"type":"Point"}
}