{
  "type": "Feature",
  "properties": {
    "addr:full":"B.P. 4356, 69242 Lyon C\u00e9dex 04^^51, Rue Deleuvre, 69004 Lyon Rhone-Alpes 69004",
    "addr:housenumber":"04 ^ ^ 51",
    "addr:postcode":"69242;69004;69004",
    "addr:street":"B.P. 4356;Ce\u0301Dex;Rue Deleuvre",
    "iso:country":"FR",
    "sg:address":"B.P. 4356, 69242 Lyon C\u00e9dex 04^^51, Rue Deleuvre, 69004 Lyon",
    "sg:orig_category":"Non-Classified Establishments",
    "sg:phone":"+33 4 72 10 62 62",
    "sg:postcode":"69004",
    "sg:province":"Rhone-Alpes",
    "wof:name":"Savarez S.a.",
    "wof:placetype":"venue"
},
  "geometry": {"coordinates":[4.82979,45.775742],"type":"Point"}
}