{
  "type": "Feature",
  "properties": {
    "addr:full":"9, Rue du Boulevard, 59290 Wasquehal Nord Pas-de-Calais",
    "addr:housenumber":"9",
    "addr:postcode":"59290",
    "addr:street":"Rue Du Boulevard",
    "iso:country":"FR",
    "sg:address":"9, Rue du Boulevard, 59290 Wasquehal",
    "sg:orig_category":"Unclassifiable Establishments",
    "sg:phone":"+33 3 20 72 41 60",
    "sg:province":"Nord Pas-de-Calais",
    "wof:name":"A.m.s. S.a. - Ateliers M\u00e9caniques Sp\u00e9cialis\u00e9s",
    "wof:placetype":"venue"
},
  "geometry": {"coordinates":[3.127438,50.664608],"type":"Point"}
}