{
  "type": "Feature",
  "properties": {
    "addr:full":"B.P. 59 Rivery^^La Haute Borne 80136 Rivery Picardie 80136",
    "addr:postcode":"80136;80136",
    "addr:street":"B.P. 59 Rivery^^La Haute",
    "iso:country":"FR",
    "sg:address":"B.P. 59",
    "sg:city":"Rivery^^La Haute Borne 80136 Rivery",
    "sg:orig_category":"Non-Classified Establishments",
    "sg:phone":"+33 3 22 70 70 70",
    "sg:postcode":"80136",
    "sg:province":"Picardie",
    "wof:name":"Courriers Automobiles Picards S.a.",
    "wof:placetype":"venue"
},
  "geometry": {"coordinates":[2.323065,49.902409],"type":"Point"}
}