{
  "type": "Feature",
  "properties": {
    "addr:full":"Rue Buisson Sarrazin 51450 Betheny Champagne",
    "addr:postcode":"51450",
    "addr:street":"Rue Buisson Sarrazin",
    "iso:country":"FR",
    "sg:address":"Rue Buisson Sarrazin 51450 Betheny",
    "sg:classifiers":[
        {
            "category":"Professional",
            "type":"Services"
        }
    ],
    "sg:phone":"+33 3 26 07 00 31",
    "sg:province":"Champagne",
    "sg:tags":[
        "transport",
        "road"
    ],
    "wof:name":"Transports Caillot Sarl",
    "wof:placetype":"venue"
},
  "geometry": {"coordinates":[4.055491,49.275414],"type":"Point"}
}