{
  "type": "Feature",
  "properties": {
    "addr:full":"Za 53170 Bazougers Pays de Loire 53170",
    "addr:postcode":"53170;53170",
    "addr:street":"Za",
    "iso:country":"FR",
    "sg:address":"Za 53170 Bazougers",
    "sg:classifiers":[
        {
            "category":"Manufacturing",
            "subcategory":"Metals",
            "type":"Manufacturing & Wholesale Goods"
        }
    ],
    "sg:phone":"+33 2 43 02 33 66",
    "sg:postcode":"53170",
    "sg:province":"Pays de Loire",
    "sg:tags":[
        "metallurgy",
        "metalworking",
        "processing"
    ],
    "wof:name":"Reametal Sa",
    "wof:placetype":"venue"
},
  "geometry": {"coordinates":[-0.642545,47.900532],"type":"Point"}
}