{
  "type": "Feature",
  "properties": {
    "addr:full":"Aux Gayris 32300 Lagarde Hachan Midi Pyr\u00e9n\u00e9es 32300",
    "addr:postcode":"32300;32300",
    "iso:country":"FR",
    "sg:address":"Aux Gayris 32300 Lagarde Hachan",
    "sg:classifiers":[
        {
            "category":"Autos & Motor Vehicles",
            "subcategory":"Automobile Sales",
            "type":"Retail Goods"
        }
    ],
    "sg:phone":"+33 5 62 66 05 57",
    "sg:postcode":"32300",
    "sg:province":"Midi Pyr\u00e9n\u00e9es",
    "sg:tags":[
        "equipment",
        "industrial",
        "transport"
    ],
    "wof:name":"Ets Lavigne Sarl",
    "wof:placetype":"venue"
},
  "geometry": {"coordinates":[0.50838,43.421738],"type":"Point"}
}