{
  "type": "Feature",
  "properties": {
    "iso:country":"FR",
    "sg:address":"Immeuble Jacques-Coeur; Neuville; 76370",
    "sg:classifiers":[
        {
            "category":"Banks & Credit Unions",
            "subcategory":"Bank",
            "type":"Services"
        }
    ],
    "sg:phone":"+33 3335842211",
    "sg:postcode":"76370",
    "sg:province":"Haute Normandie",
    "wof:name":"Soci\u00e9t\u00e9 G\u00e9n\u00e9rale",
    "wof:placetype":"venue"
},
  "geometry": {"coordinates":[1.093,49.904709],"type":"Point"}
}