{
  "type": "Feature",
  "properties": {
    "addr:full":"B.P. 210, 64602 Anglet C\u00e9dex^^8, All\u00e9e de Samadet, 64600 Anglet Anglet Aquitaine 64600",
    "addr:housenumber":"b.p. 210",
    "addr:postcode":"64602;64600;64600",
    "addr:street":"Alle\u0301E De Samadet",
    "iso:country":"FR",
    "sg:address":"B.P. 210, 64602 Anglet C\u00e9dex^^8, All\u00e9e de Samadet, 64600 Anglet",
    "sg:city":"Anglet",
    "sg:orig_category":"Non-Classified Establishments",
    "sg:phone":"+33 5 59 31 96 95",
    "sg:postcode":"64600",
    "sg:province":"Aquitaine",
    "wof:name":"Farmer Industrie Service S.a.r.l.",
    "wof:placetype":"venue"
},
  "geometry": {"coordinates":[-1.514707,43.481705],"type":"Point"}
}