{
  "type": "Feature",
  "properties": {
    "iso:country":"FR",
    "sg:address":"8, Bd du Recteur Jean Sarrailh, 64000 Pau",
    "sg:city":"Pau",
    "sg:orig_category":"Non-Classified Establishments",
    "sg:phone":"+33 5 59 14 21 00",
    "sg:postcode":"64000",
    "sg:province":"Aquitaine",
    "wof:name":"Banque Populaire Du Sud Ouest",
    "wof:placetype":"venue"
},
  "geometry": {"coordinates":[-0.366617,43.311214],"type":"Point"}
}