{
  "type": "Feature",
  "properties": {
    "iso:country":"FR",
    "sg:address":"28, Av. de Marseille, 93220 Gagny",
    "sg:orig_category":"Non-Classified Establishments",
    "sg:phone":"+33 1 43 88 27 36",
    "sg:postcode":"93220",
    "sg:province":"Ile de France",
    "wof:name":"Coupain Molina Et Associ\u00e9s S.a.r.l.",
    "wof:placetype":"venue"
},
  "geometry": {"coordinates":[2.548495,48.874699],"type":"Point"}
}