{
  "type": "Feature",
  "properties": {
    "addr:full":"13 Rte De Jeuxey 88000 Epinal Lorraine 88000",
    "addr:housenumber":"13",
    "addr:postcode":"88000;88000",
    "addr:street":"Rte De Jeuxey",
    "iso:country":"FR",
    "sg:address":"13 Rte De Jeuxey 88000 Epinal",
    "sg:classifiers":[
        {
            "category":"Shopping",
            "subcategory":"Stationery & Office Supplies",
            "type":"Retail Goods"
        }
    ],
    "sg:phone":"+33 3 29 34 25 25",
    "sg:postcode":"88000",
    "sg:province":"Lorraine",
    "sg:tags":[
        "information",
        "technology",
        "telecommunication",
        "equipment"
    ],
    "wof:name":"Efica Bureautique Sarl",
    "wof:placetype":"venue"
},
  "geometry": {"coordinates":[6.454096,48.193661],"type":"Point"}
}