{
  "type": "Feature",
  "properties": {
    "iso:country":"FR",
    "sg:address":"460, Rue Armand Japy - Technoland, 25460 Etupes",
    "sg:orig_category":"Unclassifiable Establishments",
    "sg:phone":"+33 3 81 99 10 99",
    "sg:province":"Franche Comt\u00e9",
    "wof:name":"M.a.p.e. S.a. - Mesure Analyse Process Environnement",
    "wof:placetype":"venue"
},
  "geometry": {"coordinates":[6.862814,47.506931],"type":"Point"}
}