{
  "type": "Feature",
  "properties": {
    "addr:full":"Rn De St Menet Campagne La Maussane 13396 Marseille Cedex 11 Poitou-Charentes",
    "addr:postcode":"13396;11",
    "addr:street":"De St;Campagne;Maussane",
    "iso:country":"FR",
    "sg:address":"Rn De St Menet Campagne La Maussane 13396 Marseille Cedex 11",
    "sg:classifiers":[
        {
            "category":"Building & Trades",
            "subcategory":"Construction",
            "type":"Services"
        }
    ],
    "sg:phone":"+33 4 91 43 03 34",
    "sg:province":"Poitou-Charentes",
    "sg:tags":[
        "advice",
        "work",
        "public",
        "business"
    ],
    "wof:name":"Marius Daniel Et Fils",
    "wof:placetype":"venue"
},
  "geometry": {"coordinates":[5.50389,43.292229],"type":"Point"}
}