{
  "type": "Feature",
  "properties": {
    "iso:country":"FR",
    "sg:address":"112, Rue R\u00e9aumur, 75002 Paris",
    "sg:orig_category":"Unclassifiable Establishments",
    "sg:phone":"+33 1 40 26 26 35",
    "sg:province":"Ile de France",
    "wof:name":"Lea Rome S.a.r.l.",
    "wof:placetype":"venue"
},
  "geometry": {"coordinates":[2.345915,48.867805],"type":"Point"}
}