{
  "type": "Feature",
  "properties": {
    "addr:full":"7, Place de Saverne - Immeuble les Renardi\u00e8res, 92415 Courbevoie C\u00e9dex Ile-de-France",
    "addr:housenumber":"7",
    "addr:postcode":"92415",
    "addr:street":"Place De Saverne",
    "iso:country":"FR",
    "sg:address":"7, Place de Saverne - Immeuble les Renardi\u00e8res, 92415 Courbevoie C\u00e9dex",
    "sg:orig_category":"Non-Classified Establishments",
    "sg:phone":"+33 1 56 37 02 51",
    "sg:province":"Ile-de-France",
    "wof:name":"Saint Gobain Eurocoustic S.a.",
    "wof:placetype":"venue"
},
  "geometry": {"coordinates":[2.25651,48.896809],"type":"Point"}
}