{
  "type": "Feature",
  "properties": {
    "addr:full":"18/20, Rue Saint Hilaire - ZI Vert Galant, 95370 Saint Ouen l'Aum\u00f4ne Ile de France",
    "addr:housenumber":"18 / 20",
    "addr:postcode":"95370",
    "addr:street":"Rue Saint Hilaire Zi Vert Galant",
    "iso:country":"FR",
    "sg:address":"18/20, Rue Saint Hilaire - ZI Vert Galant, 95370 Saint Ouen l'Aum\u00f4ne",
    "sg:orig_category":"Unclassifiable Establishments",
    "sg:phone":"+33 1 34 48 33 99",
    "sg:province":"Ile de France",
    "wof:name":"Blanc A\u00e9ro Technologies S.a.",
    "wof:placetype":"venue"
},
  "geometry": {"coordinates":[-120.38960299999999,37.983238],"type":"Point"}
}