{
  "type": "Feature",
  "properties": {
    "addr:full":"22 Rue De La Savonnerie Zone Artisanale 68460 Lutterbach Lutterbach Alsace 68460",
    "addr:housenumber":"22",
    "addr:postcode":"68460;68460",
    "addr:street":"Rue De La Savonnerie Zone Artisanale",
    "iso:country":"FR",
    "sg:address":"22 Rue De La Savonnerie Zone Artisanale 68460 Lutterbach",
    "sg:city":"Lutterbach",
    "sg:classifiers":[
        {
            "category":"Manufacturing",
            "subcategory":"Metals",
            "type":"Manufacturing & Wholesale Goods"
        }
    ],
    "sg:phone":"+33 3 89 57 99 98",
    "sg:postcode":"68460",
    "sg:province":"Alsace",
    "sg:tags":[
        "metallurgy",
        "metalworking",
        "processing"
    ],
    "wof:name":"Alsameca",
    "wof:placetype":"venue"
},
  "geometry": {"coordinates":[7.28171,47.76054],"type":"Point"}
}