{
  "type": "Feature",
  "properties": {
    "addr:full":"44 Pr\u00e9sident Kennedy 75016 PARIS Ile de France 75016",
    "addr:housenumber":"44",
    "addr:postcode":"75016;75016",
    "addr:street":"Pre\u0301Sident Kennedy",
    "iso:country":"FR",
    "sg:address":"44",
    "sg:city":"Pr\u00e9sident Kennedy 75016 PARIS",
    "sg:orig_category":"Advertising Communication, advertising and the media Professional goods Wood and Furniture",
    "sg:phone":"+33 1 40 99 98 88",
    "sg:postcode":"75016",
    "sg:province":"Ile de France",
    "wof:name":"Promobus France",
    "wof:placetype":"venue"
},
  "geometry": {"coordinates":[2.283851,48.854969],"type":"Point"}
}