{
  "type": "Feature",
  "properties": {
    "addr:full":"280 avenue de Colmar 67100 Strasbourg Strasbourg Alsace 67100",
    "addr:housenumber":"280",
    "addr:postcode":"67100;67100",
    "addr:street":"Avenue De Colmar",
    "iso:country":"FR",
    "sg:address":"280 avenue de Colmar 67100 Strasbourg",
    "sg:city":"Strasbourg",
    "sg:classifiers":[
        {
            "category":"Autos & Motor Vehicles",
            "subcategory":"Auto Supplies",
            "type":"Retail Goods"
        }
    ],
    "sg:phone":"+33 3 88 65 70 20",
    "sg:postcode":"67100",
    "sg:province":"Alsace",
    "sg:tags":[
        "automobile",
        "accessory"
    ],
    "wof:name":"Kautzmann Sa",
    "wof:placetype":"venue"
},
  "geometry": {"coordinates":[7.743013,48.551868],"type":"Point"}
}