{
  "type": "Feature",
  "properties": {
    "addr:full":"11, Av. Dubonnet, 92407 Courbevoie C\u00e9dex \u00cele-de-France",
    "addr:postcode":"92407",
    "addr:street":"11 Av. Dubonnet;Ce\u0301Dex",
    "iso:country":"FR",
    "sg:address":"11, Av. Dubonnet, 92407 Courbevoie C\u00e9dex",
    "sg:orig_category":"Non-Classified Establishments",
    "sg:phone":"+33 1 49 04 43 33",
    "sg:province":"\u00cele-de-France",
    "wof:name":"Novaction S.a.",
    "wof:placetype":"venue"
},
  "geometry": {"coordinates":[2.260373,48.901592],"type":"Point"}
}