{
  "type": "Feature",
  "properties": {
    "addr:full":"Quartier les Meuniers Saint Julien en Saint Alban Rhone-Alpes 07000",
    "addr:postcode":"07000",
    "addr:street":"Quartier;Saint",
    "iso:country":"FR",
    "sg:address":"Quartier les Meuniers",
    "sg:city":"Saint Julien en Saint Alban",
    "sg:orig_category":"Non-Classified Establishments",
    "sg:phone":"+33 4 75 65 72 35",
    "sg:postcode":"07000",
    "sg:province":"Rhone-Alpes",
    "wof:name":"Proud S.a.",
    "wof:placetype":"venue"
},
  "geometry": {"coordinates":[4.69842,44.754501],"type":"Point"}
}