{
  "type": "Feature",
  "properties": {
    "addr:full":"B.P. 148, 54003 Nancy C\u00e9dex^^4, All\u00e9e des Aub\u00e9pines - ZAC du Parc de Haye, 54840 Velaine en Haye Lorraine",
    "addr:housenumber":"b.p. 148",
    "addr:postcode":"54003;54840",
    "addr:street":"Alle\u0301E Des Aube\u0301Pines Zac Du Parc De Haye",
    "iso:country":"FR",
    "sg:address":"B.P. 148, 54003 Nancy C\u00e9dex^^4, All\u00e9e des Aub\u00e9pines - ZAC du Parc de Haye, 54840 Velaine en Haye",
    "sg:orig_category":"Non-Classified Establishments",
    "sg:phone":"+33 3 83 23 26 66",
    "sg:province":"Lorraine",
    "wof:name":"Publi Nancy S.a.",
    "wof:placetype":"venue"
},
  "geometry": {"coordinates":[5.96087,48.690689],"type":"Point"}
}