{
  "type": "Feature",
  "properties": {
    "addr:full":"ZI de la Butte Nozay Ile de France 91620",
    "addr:postcode":"91620",
    "addr:street":"Zi De La Butte;Ile De France",
    "iso:country":"FR",
    "sg:address":"ZI de la Butte",
    "sg:city":"Nozay",
    "sg:orig_category":"Unclassifiable Establishments",
    "sg:phone":"+33 1 69 80 71 33",
    "sg:postcode":"91620",
    "sg:province":"Ile de France",
    "wof:name":"C.e.l.t.i. S.n.c.",
    "wof:placetype":"venue"
},
  "geometry": {"coordinates":[2.242235,48.66037],"type":"Point"}
}