{
  "type": "Feature",
  "properties": {
    "iso:country":"FR",
    "sg:address":"129 avenue Roger Salengro 94500 Champigny sur Marne",
    "sg:classifiers":[
        {
            "category":"Building & Trades",
            "subcategory":"Construction",
            "type":"Services"
        }
    ],
    "sg:phone":"+33 1 48 81 30 10",
    "sg:postcode":"94500",
    "sg:province":"Ile de France",
    "sg:tags":[
        "machine",
        "services",
        "drawing-based"
    ],
    "wof:name":"C.m.s. Sa",
    "wof:placetype":"venue"
},
  "geometry": {"coordinates":[2.495797,48.817657],"type":"Point"}
}