{
  "type": "Feature",
  "properties": {
    "addr:full":"La Perroli\u00e8re 42350 La Talaudi\u00e8re Rhone-Alpes",
    "addr:postcode":"42350",
    "addr:street":"La Talaudie\u0300Re Rhone-Alpes",
    "iso:country":"FR",
    "sg:address":"La Perroli\u00e8re 42350 La Talaudi\u00e8re",
    "sg:orig_category":"Non-Classified Establishments",
    "sg:phone":"+33 4 77 53 32 39",
    "sg:province":"Rhone-Alpes",
    "wof:name":"S.t.p.c. S.a. - Soci\u00e9t\u00e9 Travaux Publics Et Canalisation",
    "wof:placetype":"venue"
},
  "geometry": {"coordinates":[4.442902,45.473743],"type":"Point"}
}