{
  "type": "Feature",
  "properties": {
    "addr:full":"11, Rue d'Outre Furar - Le Soleil, 42000 Saint Etienne Rhone-Alpes",
    "addr:housenumber":"11",
    "addr:postcode":"42000",
    "addr:street":"Rue D'Outre Furar Le",
    "iso:country":"FR",
    "sg:address":"11, Rue d'Outre Furar - Le Soleil, 42000 Saint Etienne",
    "sg:orig_category":"Unclassifiable Establishments",
    "sg:phone":"+33 4 77 32 63 79",
    "sg:province":"Rhone-Alpes",
    "wof:name":"S.r.t. S.a. - Soci\u00e9t\u00e8 R\u00e9gionale De Transports.",
    "wof:placetype":"venue"
},
  "geometry": {"coordinates":[4.38924,45.451859],"type":"Point"}
}