{
  "type": "Feature",
  "properties": {
    "addr:full":"16 Rue Du Champ Moyen Industrielle Sud 54710 Fleville Devant Nancy Lorraine",
    "addr:housenumber":"16",
    "addr:postcode":"54710",
    "addr:street":"Rue Du Champ Moyen Industrielle Sud",
    "iso:country":"FR",
    "sg:address":"16 Rue Du Champ Moyen",
    "sg:city":"Industrielle Sud 54710 Fleville Devant Nancy",
    "sg:classifiers":[
        {
            "category":"Professional",
            "type":"Services"
        }
    ],
    "sg:phone":"+33 3 83 15 20 15",
    "sg:province":"Lorraine",
    "sg:tags":[
        "transport",
        "road"
    ],
    "wof:name":"Michel Et Mayer Distribution",
    "wof:placetype":"venue"
},
  "geometry": {"coordinates":[6.161059,48.621563],"type":"Point"}
}