{
  "type": "Feature",
  "properties": {
    "addr:full":"42 Rue De Vaucanson 69150 D\u00e9cines Charpieu Rhone-Alpes 69150",
    "addr:housenumber":"42",
    "addr:postcode":"69150;69150",
    "addr:street":"Rue De Vaucanson;Rhone-Alpes",
    "iso:country":"FR",
    "sg:address":"42 Rue De Vaucanson 69150 D\u00e9cines Charpieu",
    "sg:classifiers":[
        {
            "category":"Shopping",
            "subcategory":"Crafts & Fabrics",
            "type":"Retail Goods"
        }
    ],
    "sg:phone":"+33 4 72 14 18 20",
    "sg:postcode":"69150",
    "sg:province":"Rhone-Alpes",
    "sg:tags":[
        "textile",
        "clothing"
    ],
    "wof:name":"Medaxe Sa",
    "wof:placetype":"venue"
},
  "geometry": {"coordinates":[4.940136,45.753487],"type":"Point"}
}