{
  "type": "Feature",
  "properties": {
    "iso:country":"FR",
    "sg:address":"Rue Jean-Pierre Clause 67300 Schiltigheim",
    "sg:city":"Schiltigheim",
    "sg:classifiers":[
        {
            "category":"Food & Beverages",
            "subcategory":"Meat & Fish",
            "type":"Retail Goods"
        }
    ],
    "sg:phone":"+33 3 88 19 20 00",
    "sg:postcode":"67300",
    "sg:province":"Alsace",
    "sg:tags":[
        "preserve",
        "cooked",
        "product",
        "related"
    ],
    "wof:name":"Feyel Artzner Sa",
    "wof:placetype":"venue"
},
  "geometry": {"coordinates":[7.724075,48.602612],"type":"Point"}
}