{
  "type": "Feature",
  "properties": {
    "addr:full":"B.P. 126, 62054 Saint Laurent Blangy C\u00e9dex^^ZAL du 14 Juillet, 62223 Saint Laurent Blangy Nord Pas-de-Calais 62223",
    "addr:housenumber":"b.p. 126",
    "addr:postcode":"62054;62223;62223",
    "addr:street":"Du 14 Juillet;Laurent Blangy Nord",
    "iso:country":"FR",
    "sg:address":"B.P. 126, 62054 Saint Laurent Blangy C\u00e9dex^^ZAL du 14 Juillet, 62223 Saint Laurent Blangy",
    "sg:orig_category":"Non-Classified Establishments",
    "sg:phone":"+33 3 21 55 80 99",
    "sg:postcode":"62223",
    "sg:province":"Nord Pas-de-Calais",
    "wof:name":"C.m.b.h. S.a. - Constructions M\u00e9talliques B\u00e2timents Hangars",
    "wof:placetype":"venue"
},
  "geometry": {"coordinates":[2.803693,50.303818],"type":"Point"}
}