{
  "type": "Feature",
  "properties": {
    "addr:full":"B.P. 10 Sainte M\u00e8re Eglise Basse Normandie 50480",
    "addr:postcode":"50480",
    "addr:street":"B.P. 10 Sainte Me\u0300Re Eglise Basse",
    "iso:country":"FR",
    "sg:address":"B.P. 10",
    "sg:city":"Sainte M\u00e8re Eglise",
    "sg:orig_category":"Non-Classified Establishments",
    "sg:phone":"+33 2 33 21 69 00",
    "sg:postcode":"50480",
    "sg:province":"Basse Normandie",
    "wof:name":"Dimat 50 S.a.s.",
    "wof:placetype":"venue"
},
  "geometry": {"coordinates":[-1.317429,49.408295],"type":"Point"}
}