{
  "type": "Feature",
  "properties": {
    "addr:full":"6, All\u00e9e de Londres - Centre de Vie de Courtaboeuf, 91969 Les Ulis C\u00e9dex Aquitaine",
    "addr:housenumber":"6",
    "addr:postcode":"91969",
    "addr:street":"Alle\u0301E De Londres",
    "iso:country":"FR",
    "sg:address":"6, All\u00e9e de Londres - Centre de Vie de Courtaboeuf, 91969 Les Ulis C\u00e9dex",
    "sg:orig_category":"Non-Classified Establishments",
    "sg:phone":"+33 1 69 07 13 14",
    "sg:province":"Aquitaine",
    "wof:name":"J.k. S.a.",
    "wof:placetype":"venue"
},
  "geometry": {"coordinates":[-0.12714,51.506321],"type":"Point"}
}