{
  "type": "Feature",
  "properties": {
    "iso:country":"FR",
    "sg:address":"Le Grand Moutet Zac De L Echangeur Ilot 2 18000 Bourges",
    "sg:city":"Bourges",
    "sg:classifiers":[
        {
            "category":"Professional",
            "subcategory":"Engineering",
            "type":"Services"
        }
    ],
    "sg:phone":"+33 2 48 67 50 30",
    "sg:postcode":"18000",
    "sg:province":"Centre",
    "sg:tags":[
        "machine",
        "-",
        "mechanical"
    ],
    "wof:name":"Fadis",
    "wof:placetype":"venue"
},
  "geometry": {"coordinates":[2.39293,47.085854],"type":"Point"}
}