{
  "type": "Feature",
  "properties": {
    "iso:country":"FR",
    "sg:address":"2203 Chemin De Saint Claude 06600 Antibes",
    "sg:classifiers":[
        {
            "category":"Professional",
            "subcategory":"Engineering",
            "type":"Services"
        }
    ],
    "sg:phone":"+33 4 93 74 10 10",
    "sg:province":"Franche Comt\u00e9",
    "sg:tags":[
        "machine",
        "-",
        "environment",
        "equipment",
        "machinery",
        "mechanical"
    ],
    "wof:name":"Chubb",
    "wof:placetype":"venue"
},
  "geometry": {"coordinates":[7.093091,43.601631],"type":"Point"}
}