{
  "type": "Feature",
  "properties": {
    "iso:country":"FR",
    "sg:address":"24 rue Ballu 75009 Paris",
    "sg:orig_category":"Ladies' Trousers Suits, Suits, Jackets, Skirts, And Trousers",
    "sg:phone":"+33 1 49 70 15 15",
    "sg:postcode":"75009",
    "sg:province":"Ile de France",
    "wof:name":"Escada D\u00e9velopment Sarl",
    "wof:placetype":"venue"
},
  "geometry": {"coordinates":[2.330187,48.881989],"type":"Point"}
}