{
  "type": "Feature",
  "properties": {
    "addr:full":"8 Rue Forges 60112 Milly Sur Th\u00e9rain Picardie",
    "addr:housenumber":"8",
    "addr:postcode":"60112",
    "addr:street":"Rue Forges",
    "iso:country":"FR",
    "sg:address":"8 Rue Forges 60112 Milly Sur Th\u00e9rain",
    "sg:classifiers":[
        {
            "category":"Manufacturing",
            "subcategory":"Rubber & Plastics",
            "type":"Manufacturing & Wholesale Goods"
        }
    ],
    "sg:phone":"+33 3 44 81 32 60",
    "sg:province":"Picardie",
    "wof:name":"Ets Louis Besse",
    "wof:placetype":"venue"
},
  "geometry": {"coordinates":[1.993067,49.493999],"type":"Point"}
}