{
  "type": "Feature",
  "properties": {
    "addr:full":"10 Bis, Rue de Paris, 95350 Piscop Ile de France 95350",
    "addr:housenumber":"10 bis",
    "addr:postcode":"95350;95350",
    "addr:street":"Rue De Paris;Ile De France",
    "iso:country":"FR",
    "sg:address":"10 Bis, Rue de Paris, 95350 Piscop",
    "sg:orig_category":"Non-Classified Establishments",
    "sg:phone":"+33 1 34 19 56 87",
    "sg:postcode":"95350",
    "sg:province":"Ile de France",
    "wof:name":"Entreprise Barreau",
    "wof:placetype":"venue"
},
  "geometry": {"coordinates":[2.348712,49.019547],"type":"Point"}
}