{
  "type": "Feature",
  "properties": {
    "iso:country":"FR",
    "sg:address":"B.P. 32, 31701 Blagnac C\u00e9dex^^5, Rue Dieudonn\u00e9 Costes, 31700 Blagnac",
    "sg:orig_category":"Non-Classified Establishments",
    "sg:phone":"+33 5 62 74 20 00",
    "sg:postcode":"31700",
    "sg:province":"Midi Pyr\u00e9n\u00e9es",
    "wof:name":"C.r.c.i. Midi Pyr\u00e9n\u00e9es - Chambre R\u00e9gionale Commerce Et Industrie",
    "wof:placetype":"venue"
},
  "geometry": {"coordinates":[1.39684,43.634586],"type":"Point"}
}