{
  "type": "Feature",
  "properties": {
    "addr:full":"B.P. 56, 73410 Albens^^ZA les Pr\u00e9s Roses, 73410 Albens Rhone-Alpes 73410",
    "addr:postcode":"73410;73410;73410",
    "addr:street":"B.P. 56",
    "iso:country":"FR",
    "sg:address":"B.P. 56, 73410 Albens^^ZA les Pr\u00e9s Roses, 73410 Albens",
    "sg:orig_category":"Non-Classified Establishments",
    "sg:phone":"+33 4 79 63 07 14",
    "sg:postcode":"73410",
    "sg:province":"Rhone-Alpes",
    "wof:name":"Delgado Fr\u00e8res S.a.r.l.",
    "wof:placetype":"venue"
},
  "geometry": {"coordinates":[5.960386,45.739845],"type":"Point"}
}