{
  "type": "Feature",
  "properties": {
    "addr:full":"18 Rue Bara 92130 Issy Les Moulineaux Ile de France 92130",
    "addr:housenumber":"18",
    "addr:postcode":"92130;92130",
    "addr:street":"Rue Bara",
    "iso:country":"FR",
    "sg:address":"18 Rue Bara 92130 Issy Les Moulineaux",
    "sg:classifiers":[
        {
            "category":"Professional",
            "subcategory":"Engineering",
            "type":"Services"
        }
    ],
    "sg:phone":"+33 1 46 48 70 00",
    "sg:postcode":"92130",
    "sg:province":"Ile de France",
    "sg:tags":[
        "machine",
        "-",
        "mechanical"
    ],
    "wof:name":"Ciac Sa",
    "wof:placetype":"venue"
},
  "geometry": {"coordinates":[2.2675,48.83316],"type":"Point"}
}