{
  "type": "Feature",
  "properties": {
    "iso:country":"FR",
    "sg:address":"Les Blanch\u00e8res 01500 Ambronay",
    "sg:orig_category":"Unclassifiable Establishments",
    "sg:phone":"+33 4 74 38 20 10",
    "sg:province":"Rhone-Alpes",
    "wof:name":"Fournier Rondot S.a.",
    "wof:placetype":"venue"
},
  "geometry": {"coordinates":[5.355265,45.996475],"type":"Point"}
}