{
  "type": "Feature",
  "properties": {
    "addr:full":"24A, Rte Nationale - Ile Napol\u00e9on - Centre d'Activit\u00e9 Actipolis, 68390 Sausheim Sausheim Alsace 68390",
    "addr:housenumber":"24a",
    "addr:postcode":"68390;68390",
    "addr:street":"Rte Nationale Ile Napole\u0301On Centre;Actipolis;Sausheim",
    "iso:country":"FR",
    "sg:address":"24A, Rte Nationale - Ile Napol\u00e9on - Centre d'Activit\u00e9 Actipolis, 68390 Sausheim",
    "sg:city":"Sausheim",
    "sg:orig_category":"Unclassifiable Establishments",
    "sg:phone":"+33 3 89 61 85 52",
    "sg:postcode":"68390",
    "sg:province":"Alsace",
    "wof:name":"Dubich Mobilier S.a.",
    "wof:placetype":"venue"
},
  "geometry": {"coordinates":[7.40721,47.802368],"type":"Point"}
}