{
  "type": "Feature",
  "properties": {
    "addr:full":"52-62 Av D'Enghien 93806 \u00c9pinay Sur Seine Champagne",
    "addr:housenumber":"52-62",
    "addr:postcode":"93806",
    "addr:street":"Av D'Enghien",
    "iso:country":"FR",
    "sg:address":"52-62 Av D'Enghien 93806 \u00c9pinay Sur Seine",
    "sg:classifiers":[
        {
            "category":"Professional",
            "subcategory":"Engineering",
            "type":"Services"
        }
    ],
    "sg:phone":"+33 1 49 33 89 33",
    "sg:province":"Champagne",
    "sg:tags":[
        "machine",
        "-",
        "mechanical"
    ],
    "wof:name":"Le Calibre Sa",
    "wof:placetype":"venue"
},
  "geometry": {"coordinates":[2.307356,48.959862],"type":"Point"}
}