{
  "type": "Feature",
  "properties": {
    "iso:country":"FR",
    "sg:address":"Rue Gutenberg 82004 Montauban Cedex",
    "sg:city":"Berg",
    "sg:classifiers":[
        {
            "category":"Utilities",
            "subcategory":"Electric",
            "type":"Services"
        }
    ],
    "sg:phone":"+33 5 63 03 50 05",
    "sg:postcode":"67320",
    "sg:province":"Alsace",
    "sg:tags":[
        "electricity",
        "electronic",
        "electrical",
        "equipment"
    ],
    "wof:name":"Seardi Pompage Sa",
    "wof:placetype":"venue"
},
  "geometry": {"coordinates":[1.364208,44.039169],"type":"Point"}
}