{
  "type": "Feature",
  "properties": {
    "iso:country":"FR",
    "sg:address":"B.P. 26, 42360 Panissi\u00e8res C\u00e9dex^^Rue Joanny Chirat, 42360 Panissi\u00e8res",
    "sg:orig_category":"Non-Classified Establishments",
    "sg:phone":"+33 4 77 28 65 33",
    "sg:postcode":"42360",
    "sg:province":"Rhone-Alpes",
    "wof:name":"Etablissements Jaubert Gayet S.a.",
    "wof:placetype":"venue"
},
  "geometry": {"coordinates":[4.345204,45.753693],"type":"Point"}
}