{
  "type": "Feature",
  "properties": {
    "addr:full":"3 pl de l'Eglise; Digoin; 71160 Digoin Bourgogne 71160",
    "addr:housenumber":"3",
    "addr:postcode":"71160;71160",
    "addr:street":"Pl De L'Eglise;Bourgogne",
    "iso:country":"FR",
    "sg:address":"3 pl de l'Eglise; Digoin; 71160",
    "sg:city":"Digoin",
    "sg:classifiers":[
        {
            "category":"Banks & Credit Unions",
            "subcategory":"Bank",
            "type":"Services"
        }
    ],
    "sg:phone":"+33 3385530941",
    "sg:postcode":"71160",
    "sg:province":"Bourgogne",
    "wof:name":"Soci\u00e9t\u00e9 G\u00e9n\u00e9rale",
    "wof:placetype":"venue"
},
  "geometry": {"coordinates":[3.977778,46.480415],"type":"Point"}
}