{
  "type": "Feature",
  "properties": {
    "addr:full":"31 Route Santenay 21190 Chassagne Montrachet Auxey-Duresses Bourgogne 21190",
    "addr:housenumber":"31",
    "addr:postcode":"21190;21190",
    "addr:street":"Route Santenay",
    "iso:country":"FR",
    "sg:address":"31 Route Santenay 21190 Chassagne Montrachet",
    "sg:city":"Auxey-Duresses",
    "sg:classifiers":[
        {
            "category":"Food Court",
            "type":"Food & Drink"
        }
    ],
    "sg:phone":"+33 3 80 21 30 52",
    "sg:postcode":"21190",
    "sg:province":"Bourgogne",
    "sg:tags":[
        "product",
        "related"
    ],
    "wof:name":"Rene Lamy Sarl",
    "wof:placetype":"venue"
},
  "geometry": {"coordinates":[4.732189,46.936508],"type":"Point"}
}