{
  "type": "Feature",
  "properties": {
    "iso:country":"FR",
    "sg:address":"rue de l'Embarcad\u00e8re 03600 COMMENTRY",
    "sg:city":"Commentry",
    "sg:orig_category":"Steam Turbines",
    "sg:phone":"+33 4 70 64 32 33",
    "sg:postcode":"03600",
    "sg:province":"Auvergne",
    "wof:name":"Turbolub Sa",
    "wof:placetype":"venue"
},
  "geometry": {"coordinates":[2.741254,46.296265],"type":"Point"}
}