{
  "type": "Feature",
  "properties": {
    "iso:country":"FR",
    "sg:address":"Rte de Chanvres",
    "sg:city":"Joigny",
    "sg:orig_category":"Unclassifiable Establishments",
    "sg:phone":"+33 3 86 92 00 10",
    "sg:postcode":"89300",
    "sg:province":"Bourgogne",
    "wof:name":"Ateliers De Joigny S.a.",
    "wof:placetype":"venue"
},
  "geometry": {"coordinates":[3.377049,47.967709],"type":"Point"}
}