{
  "type": "Feature",
  "properties": {
    "addr:full":"Pa Des Trois Noyers 77164 Ferri\u00e8res En Brie Ile de France",
    "addr:postcode":"77164",
    "iso:country":"FR",
    "sg:address":"Pa Des Trois Noyers 77164 Ferri\u00e8res En Brie",
    "sg:classifiers":[
        {
            "category":"Professional",
            "type":"Services"
        }
    ],
    "sg:phone":"+33 1 64 76 61 80",
    "sg:province":"Ile de France",
    "sg:tags":[
        "transport",
        "road"
    ],
    "wof:name":"Jet Paris- Jet Services",
    "wof:placetype":"venue"
},
  "geometry": {"coordinates":[2.704695,48.821323],"type":"Point"}
}