{
  "type": "Feature",
  "properties": {
    "addr:full":"83460 Les Arcs",
    "addr:postcode":"83460",
    "iso:country":"FR",
    "sg:address":"83460 Les Arcs",
    "sg:orig_category":"Unclassifiable Establishments",
    "sg:phone":"+33 4 94 99 50 30",
    "wof:name":"Ch\u00e2teau De Sainte Roseline S.c.e.a.",
    "wof:placetype":"venue"
},
  "geometry": {"coordinates":[6.480395,43.461021],"type":"Point"}
}