{
  "type": "Feature",
  "properties": {
    "iso:country":"FR",
    "sg:address":"17 Rue De Precy 60820 Boran Sur Oise",
    "sg:classifiers":[
        {
            "category":"Shopping",
            "subcategory":"Bicycles & Sporting Goods",
            "type":"Retail Goods"
        }
    ],
    "sg:phone":"+33 3 44 21 90 40",
    "sg:postcode":"60820",
    "sg:province":"Picardie",
    "sg:tags":[
        "product",
        "sport",
        "miscellaneous"
    ],
    "wof:name":"Sport France Sa",
    "wof:placetype":"venue"
},
  "geometry": {"coordinates":[2.356688,49.168858],"type":"Point"}
}