{
  "type": "Feature",
  "properties": {
    "addr:full":"131, Av. des Maronniers, 38300 Bourgoin Jallieu Rhone-Alpes 38300",
    "addr:postcode":"38300;38300",
    "addr:street":"131 Av. Des Maronniers;Rhone-Alpes",
    "iso:country":"FR",
    "sg:address":"131, Av. des Maronniers, 38300 Bourgoin Jallieu",
    "sg:orig_category":"Non-Classified Establishments",
    "sg:phone":"+33 4 74 28 51 58",
    "sg:postcode":"38300",
    "sg:province":"Rhone-Alpes",
    "wof:name":"Embunic S.a.r.l. - Emballage Et Usinage Unique",
    "wof:placetype":"venue"
},
  "geometry": {"coordinates":[5.26401,45.593094],"type":"Point"}
}