{
  "type": "Feature",
  "properties": {
    "addr:full":"1, Place Boildieu, 75002 Paris Ile de France",
    "addr:housenumber":"1",
    "addr:postcode":"75002",
    "addr:street":"Place Boildieu",
    "iso:country":"FR",
    "sg:address":"1, Place Boildieu, 75002 Paris",
    "sg:orig_category":"Unclassifiable Establishments",
    "sg:phone":"+33 1 42 97 55 22",
    "sg:province":"Ile de France",
    "wof:name":"Transcomint S.a.",
    "wof:placetype":"venue"
},
  "geometry": {"coordinates":[2.337647,48.870682],"type":"Point"}
}