{
  "type": "Feature",
  "properties": {
    "iso:country":"FR",
    "sg:address":"B.P. 55, 10302 Sainte Savine C\u00e9dex^^Parc d'Activit\u00e9s Savipol, 10300 Sainte Savine",
    "sg:orig_category":"Non-Classified Establishments",
    "sg:phone":"+33 3 25 71 31 50",
    "sg:postcode":"10300",
    "sg:province":"Champagne",
    "wof:name":"D3e Electronique S.a. - Distribution Est Equipements Etudes Electronique",
    "wof:placetype":"venue"
},
  "geometry": {"coordinates":[3.92846,48.304249],"type":"Point"}
}