{
  "type": "Feature",
  "properties": {
    "addr:full":"B.P. 684, 62030 Arras C\u00e9dex^^130, Rue de Cambrai, 62000 Arras Nord Pas-de-Calais",
    "addr:housenumber":"b.p. 684",
    "addr:postcode":"62030;62000",
    "addr:street":"Rue De Cambrai",
    "iso:country":"FR",
    "sg:address":"B.P. 684, 62030 Arras C\u00e9dex^^130, Rue de Cambrai, 62000 Arras",
    "sg:orig_category":"Non-Classified Establishments",
    "sg:phone":"+33 3 21 60 61 00",
    "sg:province":"Nord Pas-de-Calais",
    "wof:name":"Satca S.a.",
    "wof:placetype":"venue"
},
  "geometry": {"coordinates":[2.77891,50.290989],"type":"Point"}
}