{
  "type": "Feature",
  "properties": {
    "addr:full":"4 ave Jean Calvet; Gaillac; 81600 Midi Pyr\u00e9n\u00e9es 81600",
    "addr:postcode":"81600;81600",
    "addr:street":"4 Ave Jean Calvet",
    "iso:country":"FR",
    "sg:address":"4 ave Jean Calvet; Gaillac; 81600",
    "sg:classifiers":[
        {
            "category":"Banks & Credit Unions",
            "subcategory":"Bank",
            "type":"Services"
        }
    ],
    "sg:phone":"+33 3363572062",
    "sg:postcode":"81600",
    "sg:province":"Midi Pyr\u00e9n\u00e9es",
    "wof:name":"Banque Nationale De Paris",
    "wof:placetype":"venue"
},
  "geometry": {"coordinates":[1.899024,43.899643],"type":"Point"}
}