{
  "type": "Feature",
  "properties": {
    "addr:full":"101, Av. Yves Farge - ZI des Yvaudi\u00e8res, 37700 Saint Pierre des Corps La Ville-aux-Dames Centre 37700",
    "addr:housenumber":"101",
    "addr:postcode":"37700;37700",
    "addr:street":"Av. Yves Farge Zi Des Yvaudie\u0300Res;Des Corps La",
    "iso:country":"FR",
    "sg:address":"101, Av. Yves Farge - ZI des Yvaudi\u00e8res, 37700 Saint Pierre des Corps",
    "sg:city":"La Ville-aux-Dames",
    "sg:orig_category":"Unclassifiable Establishments",
    "sg:phone":"+33 2 47 32 45 45",
    "sg:postcode":"37700",
    "sg:province":"Centre",
    "wof:name":"Vitamotor S.a.",
    "wof:placetype":"venue"
},
  "geometry": {"coordinates":[0.745803,47.3853],"type":"Point"}
}