{
  "type": "Feature",
  "properties": {
    "addr:full":"Route De Sarrebruck Za La Planchette 57645 Montoy Flanville Vill\u00e9 Alsace 67220",
    "addr:postcode":"57645;67220",
    "addr:street":"Route De Sarrebruck Za La Planchette",
    "iso:country":"FR",
    "sg:address":"Route De Sarrebruck Za La Planchette 57645 Montoy Flanville",
    "sg:city":"Vill\u00e9",
    "sg:classifiers":[
        {
            "category":"Building & Trades",
            "subcategory":"Construction",
            "type":"Services"
        }
    ],
    "sg:phone":"+33 3 87 76 87 90",
    "sg:postcode":"67220",
    "sg:province":"Alsace",
    "sg:tags":[
        "work",
        "public"
    ],
    "wof:name":"Cnh France Sa",
    "wof:placetype":"venue"
},
  "geometry": {"coordinates":[6.277843,49.119083],"type":"Point"}
}