{
  "type": "Feature",
  "properties": {
    "addr:full":"Quartier de l'Aum\u00f4ne Vieille - Techniparc de la Bastidonne Aubagne Nord Pas-de-Calais 13400",
    "addr:postcode":"13400",
    "addr:street":"Quartier;Vieille;De La Bastidonne Aubagne Nord",
    "iso:country":"FR",
    "sg:address":"Quartier de l'Aum\u00f4ne Vieille - Techniparc de la Bastidonne",
    "sg:city":"Aubagne",
    "sg:orig_category":"Unclassifiable Establishments",
    "sg:phone":"+33 4 91 19 12 30",
    "sg:postcode":"13400",
    "sg:province":"Nord Pas-de-Calais",
    "wof:name":"Laurent Bouillet Entreprise S.a.",
    "wof:placetype":"venue"
},
  "geometry": {"coordinates":[5.529231,43.287045],"type":"Point"}
}