{
  "type": "Feature",
  "properties": {
    "iso:country":"FR",
    "sg:address":"15, Rue Ch\u00e2teau des Rentiers, 75013 Paris",
    "sg:orig_category":"Unclassifiable Establishments",
    "sg:phone":"+33 1 44 24 98 02",
    "sg:province":"Ile de France",
    "wof:name":"Extendos S.a.",
    "wof:placetype":"venue"
},
  "geometry": {"coordinates":[2.370691,48.823441],"type":"Point"}
}