{
  "type": "Feature",
  "properties": {
    "addr:full":"15, Rue Guibal, 13003 Marseille Provence-Alpes-C\u00f4te d'Azur",
    "addr:housenumber":"15",
    "addr:postcode":"13003",
    "addr:street":"Rue Guibal",
    "iso:country":"FR",
    "sg:address":"15, Rue Guibal, 13003 Marseille",
    "sg:orig_category":"Unclassifiable Establishments",
    "sg:phone":"+33 4 91 95 90 39",
    "sg:province":"Provence-Alpes-C\u00f4te d'Azur",
    "wof:name":"Joseph Gazan S.a.",
    "wof:placetype":"venue"
},
  "geometry": {"coordinates":[5.388035,43.30817],"type":"Point"}
}