{
  "type": "Feature",
  "properties": {
    "addr:full":"ZI du Clos Marquet 42400 ST CHAMOND Rhone-Alpes 42400",
    "addr:postcode":"42400;42400",
    "addr:street":"Zi Du Clos Marquet;Rhone-Alpes",
    "iso:country":"FR",
    "sg:address":"ZI du Clos Marquet 42400 ST CHAMOND",
    "sg:classifiers":[
        {
            "category":"Shopping",
            "subcategory":"Crafts & Fabrics",
            "type":"Retail Goods"
        }
    ],
    "sg:phone":"+33 4 77 31 00 60",
    "sg:postcode":"42400",
    "sg:province":"Rhone-Alpes",
    "sg:tags":[
        "knitted",
        "technical",
        "purpose"
    ],
    "wof:name":"Tricotage Saint Chamonais Sa",
    "wof:placetype":"venue"
},
  "geometry": {"coordinates":[4.512304,45.473969],"type":"Point"}
}