{
  "type": "Feature",
  "properties": {
    "addr:full":"Cht Cissac 33250 Cissac M\u00e9doc Cissac-M\u00e9doc Aquitaine 33250",
    "addr:postcode":"33250;33250",
    "addr:street":"Cissac",
    "iso:country":"FR",
    "sg:address":"Cht Cissac 33250 Cissac M\u00e9doc",
    "sg:city":"Cissac-M\u00e9doc",
    "sg:classifiers":[
        {
            "category":"Food Court",
            "type":"Food & Drink"
        }
    ],
    "sg:phone":"+33 5 56 59 58 39",
    "sg:postcode":"33250",
    "sg:province":"Aquitaine",
    "sg:tags":[
        "product",
        "related"
    ],
    "wof:name":"Louis Vialard Sa",
    "wof:placetype":"venue"
},
  "geometry": {"coordinates":[-0.828098,45.227722],"type":"Point"}
}