{
  "type": "Feature",
  "properties": {
    "addr:full":"B.P. 43127, 14103 Lisieux C\u00e9dex^^3, Rue Saint Ursin, 14100 Lisieux Lisieux Basse Normandie 14100",
    "addr:housenumber":"14103",
    "addr:postcode":"14100;14100",
    "addr:street":"Rue Saint Ursin",
    "iso:country":"FR",
    "sg:address":"B.P. 43127, 14103 Lisieux C\u00e9dex^^3, Rue Saint Ursin, 14100 Lisieux",
    "sg:city":"Lisieux",
    "sg:orig_category":"Non-Classified Establishments",
    "sg:phone":"+33 2 31 31 34 55",
    "sg:postcode":"14100",
    "sg:province":"Basse Normandie",
    "wof:name":"Unibois P.m.s. Recyclage S.a.r.l. - Palette Manutention Services",
    "wof:placetype":"venue"
},
  "geometry": {"coordinates":[0.189525,49.074329],"type":"Point"}
}