{
  "type": "Feature",
  "properties": {
    "iso:country":"FR",
    "sg:address":"ZA",
    "sg:city":"Aix les Bains",
    "sg:orig_category":"Unclassifiable Establishments",
    "sg:phone":"+33 4 79 35 33 47",
    "sg:postcode":"73100",
    "sg:province":"Rhone-Alpes",
    "wof:name":"Sated S.a.r.l.",
    "wof:placetype":"venue"
},
  "geometry": {"coordinates":[5.899685,45.672455],"type":"Point"}
}