{
  "type": "Feature",
  "properties": {
    "iso:country":"FR",
    "sg:address":"Aire Des R\u00e9compenses Autoroute A 5 77130 Forges",
    "sg:classifiers":[
        {
            "category":"Manufacturing",
            "subcategory":"Chemicals & Compounds",
            "type":"Manufacturing & Wholesale Goods"
        }
    ],
    "sg:phone":"+33 1 64 70 08 30",
    "sg:postcode":"77130",
    "sg:province":"Ile de France",
    "sg:tags":[
        "pharmaceutical",
        "energy",
        "chemistry",
        "-",
        "by-product"
    ],
    "wof:name":"Station Service Carrefour",
    "wof:placetype":"venue"
},
  "geometry": {"coordinates":[2.891333,48.303902],"type":"Point"}
}