{
  "type": "Feature",
  "properties": {
    "iso:country":"FR",
    "sg:address":"B.P. 22, 49401 Saumur C\u00e9dex^^Rte de Montsoreau, 49400 Saumur",
    "sg:orig_category":"Non-Classified Establishments",
    "sg:phone":"+33 2 41 83 13 30",
    "sg:province":"Pays de Loire",
    "wof:name":"Gratien Meyer Seydoux Holding S.a.",
    "wof:placetype":"venue"
},
  "geometry": {"coordinates":[-0.068679,47.2145],"type":"Point"}
}