{
  "type": "Feature",
  "properties": {
    "addr:full":"B\u00e2t. Module Air Le Bourget du Lac Rhone-Alpes 73370",
    "addr:housenumber":"ba\u0302t",
    "addr:postcode":"73370",
    "addr:street":"Air Le Bourget Du Lac Rhone-Alpes",
    "iso:country":"FR",
    "sg:address":"B\u00e2t. Module Air",
    "sg:city":"Le Bourget du Lac",
    "sg:orig_category":"Unclassifiable Establishments",
    "sg:phone":"+33 4 79 25 39 75",
    "sg:postcode":"73370",
    "sg:province":"Rhone-Alpes",
    "wof:name":"Applied Utech S.a.",
    "wof:placetype":"venue"
},
  "geometry": {"coordinates":[5.86225,45.643875],"type":"Point"}
}