{
  "type": "Feature",
  "properties": {
    "iso:country":"FR",
    "sg:address":"Quai Auguste Th\u00e9phany; Camaret sur Mer; 29570",
    "sg:city":"Camaret-sur-Mer",
    "sg:classifiers":[
        {
            "category":"Banks & Credit Unions",
            "subcategory":"Bank",
            "type":"Services"
        }
    ],
    "sg:phone":"+33 2 98 27 94 20",
    "sg:postcode":"29570",
    "sg:province":"Bretagne",
    "wof:name":"Caisse Regionale De Cr\u00e9dit, Maritime Mutuel Du Finist\u00e8re",
    "wof:placetype":"venue"
},
  "geometry": {"coordinates":[-4.592309,48.274998],"type":"Point"}
}