{
  "type": "Feature",
  "properties": {
    "iso:country":"FR",
    "sg:address":"B.P. 31, 72083 Le Mans C\u00e9dex 9^^40, Rue Pr\u00e9martine, 72000 Le Mans",
    "sg:orig_category":"Non-Classified Establishments",
    "sg:phone":"+33 2 43 76 33 33",
    "sg:postcode":"72000",
    "sg:province":"Pays de Loire",
    "wof:name":"Cr\u00e9dit Agricole De L'anjou Et Du Maine",
    "wof:placetype":"venue"
},
  "geometry": {"coordinates":[0.197813,48.008095],"type":"Point"}
}