{
  "type": "Feature",
  "properties": {
    "iso:country":"FR",
    "sg:address":"231, Rue Marcel Dassault - ZI, 33260 La Teste de Buch",
    "sg:city":"Teste-de-Buch",
    "sg:orig_category":"Non-Classified Establishments",
    "sg:phone":"+33 5 56 54 32 33",
    "sg:postcode":"33260",
    "sg:province":"Aquitaine",
    "wof:name":"Bardo Paysage S.a.r.l.",
    "wof:placetype":"venue"
},
  "geometry": {"coordinates":[-1.122885,44.612183],"type":"Point"}
}