{
  "type": "Feature",
  "properties": {
    "iso:country":"FR",
    "sg:address":"40 Av De La D\u00e9portation 26100 Romans Sur Is\u00e8re",
    "sg:classifiers":[
        {
            "category":"Professional",
            "type":"Services"
        }
    ],
    "sg:phone":"+33 4 75 71 17 51",
    "sg:province":"Rhone-Alpes",
    "sg:tags":[
        "transport",
        "road"
    ],
    "wof:name":"Sntv Perrenot Sa",
    "wof:placetype":"venue"
},
  "geometry": {"coordinates":[5.088481,45.050938],"type":"Point"}
}