{
  "type": "Feature",
  "properties": {
    "addr:full":"34, Av du Stade, 43600 Sainte Sigol\u00e8ne Les Villettes Auvergne 43600",
    "addr:postcode":"43600;43600",
    "addr:street":"34 Av Du Stade;Sigole\u0300Ne;Villettes",
    "iso:country":"FR",
    "sg:address":"34, Av du Stade, 43600 Sainte Sigol\u00e8ne",
    "sg:city":"Les Villettes",
    "sg:orig_category":"Unclassifiable Establishments",
    "sg:phone":"+33 4 71 66 15 54",
    "sg:postcode":"43600",
    "sg:province":"Auvergne",
    "wof:name":"Tissage Reviron S.a.r.l.",
    "wof:placetype":"venue"
},
  "geometry": {"coordinates":[4.234041,45.238773],"type":"Point"}
}