{
  "type": "Feature",
  "properties": {
    "addr:full":"26 R\u00e9sidence Parc Dromel 13009 Marseille Poitou-Charentes",
    "addr:housenumber":"26",
    "addr:postcode":"13009",
    "addr:street":"Re\u0301Sidence Parc Dromel",
    "iso:country":"FR",
    "sg:address":"26 R\u00e9sidence Parc Dromel 13009 Marseille",
    "sg:classifiers":[
        {
            "category":"Banks & Credit Unions",
            "subcategory":"Financial Services",
            "type":"Services"
        }
    ],
    "sg:phone":"+33 4 91 17 23 91",
    "sg:province":"Poitou-Charentes",
    "sg:tags":[
        "banking",
        "insurance",
        "institution",
        "finance"
    ],
    "wof:name":"Credit Lyonnais",
    "wof:placetype":"venue"
},
  "geometry": {"coordinates":[5.401315,43.248466],"type":"Point"}
}