{
  "type": "Feature",
  "properties": {
    "addr:full":"Bonnefond 43600 Sainte Sigol\u00e8ne Les Villettes Auvergne 43600",
    "addr:postcode":"43600;43600",
    "addr:street":"Sigole\u0300Ne;Villettes",
    "iso:country":"FR",
    "sg:address":"Bonnefond 43600 Sainte Sigol\u00e8ne",
    "sg:city":"Les Villettes",
    "sg:orig_category":"Unclassifiable Establishments",
    "sg:phone":"+33 4 71 66 44 69",
    "sg:postcode":"43600",
    "sg:province":"Auvergne",
    "wof:name":"Latour S.a.r.l.",
    "wof:placetype":"venue"
},
  "geometry": {"coordinates":[4.23542,45.243401],"type":"Point"}
}