{
  "type": "Feature",
  "properties": {
    "iso:country":"FR",
    "sg:address":"8 Av Mal De Lattre De Tassigny 25200 Montb\u00e9liard",
    "sg:classifiers":[
        {
            "category":"Professional",
            "subcategory":"Business Services",
            "type":"Services"
        }
    ],
    "sg:phone":"+33 3 81 99 31 00",
    "sg:postcode":"25200",
    "sg:province":"Franche Comt\u00e9",
    "sg:tags":[
        "training",
        "advice"
    ],
    "wof:name":"Lycee Professionnel",
    "wof:placetype":"venue"
},
  "geometry": {"coordinates":[6.796277,47.511639],"type":"Point"}
}