{
  "type": "Feature",
  "properties": {
    "iso:country":"FR",
    "sg:address":"B.P. 2",
    "sg:city":"Eclaron Braucourt Sainte Livi\u00e8re^^52290 Eclaron Braucourt Sainte Livi\u00e8re",
    "sg:orig_category":"Non-Classified Establishments",
    "sg:phone":"+33 3 25 04 10 06",
    "sg:postcode":"52290",
    "sg:province":"Champagne",
    "wof:name":"Briffoteaux Fils S.a.",
    "wof:placetype":"venue"
},
  "geometry": {"coordinates":[4.865826,48.590858],"type":"Point"}
}