{
  "type": "Feature",
  "properties": {
    "addr:full":"Grossereix 87280 Limoges Limousin",
    "addr:postcode":"87280",
    "addr:street":"Grossereix",
    "iso:country":"FR",
    "sg:address":"Grossereix 87280 Limoges",
    "sg:orig_category":"Unclassifiable Establishments",
    "sg:phone":"+33 5 55 36 84 34",
    "sg:province":"Limousin",
    "wof:name":"S.t.f. S.a. - Soci\u00e9t\u00e9 Des Transports Faurie",
    "wof:placetype":"venue"
},
  "geometry": {"coordinates":[1.277526,45.892975],"type":"Point"}
}