{
  "type": "Feature",
  "properties": {
    "iso:country":"FR",
    "sg:address":"ZAC Saint Martin Nord",
    "sg:city":"Mougins",
    "sg:orig_category":"Unclassifiable Establishments",
    "sg:phone":"+33 4 92 28 21 10",
    "sg:postcode":"06250",
    "sg:province":"Provence-Alpes-C\u00f4te d'Azur",
    "wof:name":"Seed S.a. - Soci\u00e9t\u00e9 D'exploitation Electro-diesel",
    "wof:placetype":"venue"
},
  "geometry": {"coordinates":[6.99596,43.599918],"type":"Point"}
}