{
  "type": "Feature",
  "properties": {
    "addr:full":"B.P. 277, 78147 V\u00e9lizy Villacoublay C\u00e9dex^^1, Rue du Petit Clamart, 78140 V\u00e9lizy Villacoublay Ile de France",
    "addr:housenumber":"b.p. 277",
    "addr:postcode":"78147;78140",
    "addr:street":"Rue Du Petit Clamart",
    "iso:country":"FR",
    "sg:address":"B.P. 277, 78147 V\u00e9lizy Villacoublay C\u00e9dex^^1, Rue du Petit Clamart, 78140 V\u00e9lizy Villacoublay",
    "sg:orig_category":"Non-Classified Establishments",
    "sg:phone":"+33 1 40 83 68 68",
    "sg:province":"Ile de France",
    "wof:name":"Mercury Int\u00e9ractive France S.a.r.l.",
    "wof:placetype":"venue"
},
  "geometry": {"coordinates":[2.18246,48.78503],"type":"Point"}
}