{
  "type": "Feature",
  "properties": {
    "addr:full":"100 Bd Beaumarchais 75011 Paris Ile de France",
    "addr:housenumber":"100",
    "addr:postcode":"75011",
    "addr:street":"Bd Beaumarchais",
    "iso:country":"FR",
    "sg:address":"100 Bd Beaumarchais 75011 Paris",
    "sg:classifiers":[
        {
            "category":"Professional",
            "type":"Services"
        }
    ],
    "sg:phone":"+33 1 43 55 32 20",
    "sg:province":"Ile de France",
    "sg:tags":[
        "transport",
        "road"
    ],
    "wof:name":"Alfred Morin Demenagements Sarl",
    "wof:placetype":"venue"
},
  "geometry": {"coordinates":[2.367551,48.860424],"type":"Point"}
}