{
  "type": "Feature",
  "properties": {
    "iso:country":"FR",
    "sg:address":"39 Bis Quai Richelieu 33000 Bordeaux",
    "sg:city":"Bordeaux",
    "sg:classifiers":[
        {
            "category":"Professional",
            "subcategory":"Business Services",
            "type":"Services"
        }
    ],
    "sg:phone":"+33 5 56 79 35 71",
    "sg:postcode":"33000",
    "sg:province":"Aquitaine",
    "sg:tags":[
        "body",
        "advice"
    ],
    "wof:name":"Ass Sociale Travail Temps Pluriels Sa",
    "wof:placetype":"venue"
},
  "geometry": {"coordinates":[-0.567368,44.837952],"type":"Point"}
}