{
  "type": "Feature",
  "properties": {
    "addr:full":"126, Rue M. Joffre, 76600 Le Havre Haute Normandie",
    "addr:housenumber":"126",
    "addr:postcode":"76600",
    "addr:street":"Rue M. Joffre",
    "iso:country":"FR",
    "sg:address":"126, Rue M. Joffre, 76600 Le Havre",
    "sg:orig_category":"Unclassifiable Establishments",
    "sg:phone":"+33 2 35 22 86 06",
    "sg:province":"Haute Normandie",
    "wof:name":"Huis Clos S.a.",
    "wof:placetype":"venue"
},
  "geometry": {"coordinates":[0.125357,49.499855],"type":"Point"}
}