{
  "type": "Feature",
  "properties": {
    "iso:country":"FR",
    "sg:address":"Rue Gabriel De Mortillet 77503 Chelles Cedex",
    "sg:classifiers":[
        {
            "category":"Transit Center",
            "subcategory":"Freight",
            "type":"Transportation"
        }
    ],
    "sg:phone":"+33 1 64 72 45 85",
    "sg:province":"Bretagne",
    "sg:tags":[
        "metallurgy",
        "pipe",
        "metalworking",
        "sheet"
    ],
    "wof:name":"Fischer Service Acier Sa",
    "wof:placetype":"venue"
},
  "geometry": {"coordinates":[2.60689,48.877739],"type":"Point"}
}