{
  "type": "Feature",
  "properties": {
    "iso:country":"FR",
    "sg:address":"1 Rue Ferdinand De Lesseps 36600 Valen\u00e7ay",
    "sg:city":"Valen\u00e7ay",
    "sg:classifiers":[
        {
            "category":"Professional",
            "subcategory":"Business Services",
            "type":"Services"
        }
    ],
    "sg:phone":"+33 2 54 00 12 33",
    "sg:postcode":"36600",
    "sg:province":"Centre",
    "sg:tags":[
        "training",
        "advice"
    ],
    "wof:name":"College Alain Fournier",
    "wof:placetype":"venue"
},
  "geometry": {"coordinates":[1.564605,47.164074],"type":"Point"}
}