{
  "type": "Feature",
  "properties": {
    "addr:full":"2, Hameau d'Allevren, 45480 Greneville en Beauce Andonville Centre 45480",
    "addr:housenumber":"2",
    "addr:postcode":"45480;45480",
    "addr:street":"Hameau D'Allevren",
    "iso:country":"FR",
    "sg:address":"2, Hameau d'Allevren, 45480 Greneville en Beauce",
    "sg:city":"Andonville",
    "sg:orig_category":"Non-Classified Establishments",
    "sg:phone":"+33 2 38 39 32 73",
    "sg:postcode":"45480",
    "sg:province":"Centre",
    "wof:name":"S.p.p.i. S.a.r.l. - Soci\u00e9t\u00e9 Production Diffusion Produits Industriels",
    "wof:placetype":"venue"
},
  "geometry": {"coordinates":[2.077222,48.177765],"type":"Point"}
}