{
  "type": "Feature",
  "properties": {
    "addr:full":"Marsa 38460 Panossas Rhone-Alpes",
    "addr:postcode":"38460",
    "addr:street":"Marsa",
    "iso:country":"FR",
    "sg:address":"Marsa 38460 Panossas",
    "sg:orig_category":"Unclassifiable Establishments",
    "sg:phone":"+33 4 74 90 21 22",
    "sg:province":"Rhone-Alpes",
    "wof:name":"Soci\u00e9t\u00e9 Des Engrais Manon Michut S.a.",
    "wof:placetype":"venue"
},
  "geometry": {"coordinates":[5.206662,45.667885],"type":"Point"}
}