{
  "type": "Feature",
  "properties": {
    "addr:full":"3 route de Chevigny 21130 AUXONNE Auxonne Bourgogne 21130",
    "addr:housenumber":"3",
    "addr:postcode":"21130;21130",
    "addr:street":"Route De Chevigny",
    "iso:country":"FR",
    "sg:address":"3 route de Chevigny 21130 AUXONNE",
    "sg:city":"Auxonne",
    "sg:classifiers":[
        {
            "category":"Food & Beverages",
            "subcategory":"Fruits & Vegetables",
            "type":"Retail Goods"
        }
    ],
    "sg:phone":"+33 3 80 77 47 57",
    "sg:postcode":"21130",
    "sg:province":"Bourgogne",
    "sg:tags":[
        "dried"
    ],
    "wof:name":"S.t.l. S.a.",
    "wof:placetype":"venue"
},
  "geometry": {"coordinates":[5.394947,47.193642],"type":"Point"}
}