{
  "type": "Feature",
  "properties": {
    "iso:country":"FR",
    "sg:address":"Zi",
    "sg:city":"De Sure 01390 St Andr\u00e9 De Corcy",
    "sg:classifiers":[
        {
            "category":"Professional",
            "subcategory":"Engineering",
            "type":"Services"
        }
    ],
    "sg:phone":"+33 4 72 26 81 00",
    "sg:postcode":"01390",
    "sg:province":"Rhone-Alpes",
    "sg:tags":[
        "machine",
        "-",
        "mechanical"
    ],
    "wof:name":"Unical France Sa",
    "wof:placetype":"venue"
},
  "geometry": {"coordinates":[4.950757,45.925713],"type":"Point"}
}