{
  "type": "Feature",
  "properties": {
    "addr:full":"B.P. 17, 62420 Billy Montigny^^Rue H\u00e9l\u00e8ne Boucher - Zone Euro Billy - B\u00e2timent K, 62420 Billy Montig Nord Pas-de-Calais",
    "addr:housenumber":"62420;62420",
    "addr:street":"B.P. 17;Billy Montigny^^Rue He\u0301Le\u0300Ne Boucher;Billy",
    "iso:country":"FR",
    "sg:address":"B.P. 17, 62420 Billy Montigny^^Rue H\u00e9l\u00e8ne Boucher - Zone Euro Billy - B\u00e2timent K, 62420 Billy Montig",
    "sg:orig_category":"Non-Classified Establishments",
    "sg:phone":"+33 3 21 76 37 68",
    "sg:province":"Nord Pas-de-Calais",
    "wof:name":"P\u00e9cora Fr\u00e8res, S.a.r.l.",
    "wof:placetype":"venue"
},
  "geometry": {"coordinates":[-87.98107899999999,39.29789],"type":"Point"}
}