{
  "type": "Feature",
  "properties": {
    "addr:full":"B.P. 31, 87300 Bellac^^17, Av. Denfert Rochereau, 87300 Bellac Limousin 87300",
    "addr:postcode":"87300;87300;87300",
    "addr:street":"B.P. 31;Av. Denfert Rochereau",
    "iso:country":"FR",
    "sg:address":"B.P. 31, 87300 Bellac^^17, Av. Denfert Rochereau, 87300 Bellac",
    "sg:orig_category":"Non-Classified Establishments",
    "sg:phone":"+33 5 55 60 91 80",
    "sg:postcode":"87300",
    "sg:province":"Limousin",
    "wof:name":"B.p.c. - Banque Populaire Du Centre",
    "wof:placetype":"venue"
},
  "geometry": {"coordinates":[1.103486,46.04298],"type":"Point"}
}