{
  "type": "Feature",
  "properties": {
    "iso:country":"FR",
    "sg:address":"31, Av. Favre d'Eglantine, 11300 Limoux",
    "sg:orig_category":"Non-Classified Establishments",
    "sg:phone":"+33 4 68 31 09 70",
    "sg:province":"Languedoc-Roussillon",
    "wof:name":"Peintures Reca S.a.",
    "wof:placetype":"venue"
},
  "geometry": {"coordinates":[2.218833,43.050323],"type":"Point"}
}