{
  "type": "Feature",
  "properties": {
    "iso:country":"FR",
    "sg:address":"26, Av. Foch, 57000 Metz",
    "sg:orig_category":"Non-Classified Establishments",
    "sg:phone":"+33 3 87 36 03 94",
    "sg:postcode":"57000",
    "sg:province":"Lorraine",
    "wof:name":"D.s.k. France S.a.r.l.",
    "wof:placetype":"venue"
},
  "geometry": {"coordinates":[6.176146,49.111809],"type":"Point"}
}