{
  "type": "Feature",
  "properties": {
    "addr:full":"15 Rue Du Ruisseau 75018 Paris Ile de France 75018",
    "addr:housenumber":"15",
    "addr:postcode":"75018;75018",
    "addr:street":"Rue Du Ruisseau",
    "iso:country":"FR",
    "sg:address":"15 Rue Du Ruisseau 75018 Paris",
    "sg:classifiers":[
        {
            "category":"Shopping",
            "subcategory":"Clothing, Apparel, & Fashions",
            "type":"Retail Goods"
        }
    ],
    "sg:phone":"+33 1 46 06 30 00",
    "sg:postcode":"75018",
    "sg:province":"Ile de France",
    "sg:tags":[
        "textile",
        "clothing",
        "clothes"
    ],
    "wof:name":"Michel Colin Creations",
    "wof:placetype":"venue"
},
  "geometry": {"coordinates":[2.339658,48.891895],"type":"Point"}
}