{
  "type": "Feature",
  "properties": {
    "addr:full":"53, Av. de la R\u00e9publique - ZI de l'Arsenal, 69200 V\u00e9nissieux Rhone-Alpes",
    "addr:postcode":"69200",
    "addr:street":"53 Av. De La Re\u0301Publique;De L'Arsenal",
    "iso:country":"FR",
    "sg:address":"53, Av. de la R\u00e9publique - ZI de l'Arsenal, 69200 V\u00e9nissieux",
    "sg:orig_category":"Non-Classified Establishments",
    "sg:phone":"+33 4 72 50 76 10",
    "sg:province":"Rhone-Alpes",
    "wof:name":"Socabel S.a.",
    "wof:placetype":"venue"
},
  "geometry": {"coordinates":[4.87795,45.70546],"type":"Point"}
}