{
  "type": "Feature",
  "properties": {
    "iso:country":"FR",
    "sg:address":"71, Rue Rambuteau, 75004 Paris",
    "sg:orig_category":"Non-Classified Establishments",
    "sg:phone":"+33 1 48 04 32 32",
    "sg:province":"Ile de France",
    "wof:name":"Mission Int\u00e9rim S.a.r.l.",
    "wof:placetype":"venue"
},
  "geometry": {"coordinates":[2.350257,48.861858],"type":"Point"}
}