{
  "type": "Feature",
  "properties": {
    "addr:full":"6 Av R\u00e9publique 14800 Deauville Deauville Basse Normandie 14800",
    "addr:postcode":"14800;14800",
    "addr:street":"Av Re\u0301Publique",
    "iso:country":"FR",
    "sg:address":"6 Av R\u00e9publique 14800 Deauville",
    "sg:city":"Deauville",
    "sg:classifiers":[
        {
            "category":"Professional",
            "type":"Services"
        }
    ],
    "sg:phone":"+33 2 31 88 35 10",
    "sg:postcode":"14800",
    "sg:province":"Basse Normandie",
    "sg:tags":[
        "transport",
        "road"
    ],
    "wof:name":"Collen Demenagements",
    "wof:placetype":"venue"
},
  "geometry": {"coordinates":[0.080424,49.359509],"type":"Point"}
}