{
  "type": "Feature",
  "properties": {
    "iso:country":"FR",
    "sg:address":"Av. Pierre et Marie Curie - ZI - Secteur C",
    "sg:city":"Saint Laurent du Var",
    "sg:orig_category":"Non-Classified Establishments",
    "sg:phone":"+33 4 93 14 26 60",
    "sg:postcode":"06700",
    "sg:province":"Champagne",
    "wof:name":"Docks Et Entrep\u00f4ts Sazias S.a.",
    "wof:placetype":"venue"
},
  "geometry": {"coordinates":[7.18693,43.687363],"type":"Point"}
}