{
  "type": "Feature",
  "properties": {
    "addr:full":"19, Rue de l'Abbaye, 88480 Etival Clairefontaine Lorraine",
    "addr:housenumber":"19",
    "addr:postcode":"88480",
    "addr:street":"Rue De L'Abbaye",
    "iso:country":"FR",
    "sg:address":"19, Rue de l'Abbaye, 88480 Etival Clairefontaine",
    "sg:orig_category":"Unclassifiable Establishments",
    "sg:phone":"+33 3 29 52 22 11",
    "sg:province":"Lorraine",
    "wof:name":"Papeteries De Clairefontaine S.a.",
    "wof:placetype":"venue"
},
  "geometry": {"coordinates":[6.865177,48.364559],"type":"Point"}
}