{
  "type": "Feature",
  "properties": {
    "addr:full":"Rue Des Celtes 68510 Sierentz Sierentz Alsace 68510",
    "addr:postcode":"68510;68510",
    "addr:street":"Rue Des Celtes",
    "iso:country":"FR",
    "sg:address":"Rue Des Celtes 68510 Sierentz",
    "sg:city":"Sierentz",
    "sg:classifiers":[
        {
            "category":"Manufacturing",
            "subcategory":"Rubber & Plastics",
            "type":"Manufacturing & Wholesale Goods"
        }
    ],
    "sg:phone":"+33 3 89 83 98 21",
    "sg:postcode":"68510",
    "sg:province":"Alsace",
    "wof:name":"Cs Plasturgie",
    "wof:placetype":"venue"
},
  "geometry": {"coordinates":[7.44823,47.664837],"type":"Point"}
}