{
  "type": "Feature",
  "properties": {
    "iso:country":"FR",
    "sg:address":"B.P. 503, 08003 Charleville M\u00e9zi\u00e8res C\u00e9dex^^8, Rue Camille Didier - ZI de Mohon, 08000 Charleville M",
    "sg:city":"Charleville-M\u00e9zi\u00e8res",
    "sg:orig_category":"Fermetures du b\u00e2timent Fermetures industrielles Menuiserie PVC",
    "sg:phone":"+33 3 24 57 65 00",
    "sg:postcode":"08000",
    "sg:province":"Champagne",
    "wof:name":"Jeantils Gillet S.a.",
    "wof:placetype":"venue"
},
  "geometry": {"coordinates":[4.7174,49.758801],"type":"Point"}
}