{
  "type": "Feature",
  "properties": {
    "iso:country":"FR",
    "sg:address":"B.P. 15, 02110 Bohain en Vermandois^^47, Rue Sauret Robert, 02110 Bohain en Vermandois",
    "sg:orig_category":"Non-Classified Establishments",
    "sg:phone":"+33 3 23 07 11 24",
    "sg:province":"Picardie",
    "wof:name":"Tissage Vermandere S.a.r.l.",
    "wof:placetype":"venue"
},
  "geometry": {"coordinates":[3.43535,49.973919],"type":"Point"}
}