{
  "type": "Feature",
  "properties": {
    "addr:full":"6 Rue Joffre Bruy\u00e8res Lorraine 88600",
    "addr:housenumber":"6",
    "addr:postcode":"88600",
    "addr:street":"Rue Joffre",
    "iso:country":"FR",
    "sg:address":"6 Rue Joffre",
    "sg:city":"Bruy\u00e8res",
    "sg:classifiers":[
        {
            "category":"Banks & Credit Unions",
            "subcategory":"Financial Services",
            "type":"Services"
        }
    ],
    "sg:phone":"+33 3 29 50 12 42",
    "sg:postcode":"88600",
    "sg:province":"Lorraine",
    "sg:tags":[
        "banking",
        "finance",
        "insurance"
    ],
    "wof:name":"Cabinet Michel Et Spittler Sa Exp Comptables",
    "wof:placetype":"venue"
},
  "geometry": {"coordinates":[6.681395,48.143887],"type":"Point"}
}