{
  "type": "Feature",
  "properties": {
    "addr:full":"209, Rte de Schirmeck, 67200 Strasbourg Strasbourg Alsace 67200",
    "addr:housenumber":"209",
    "addr:postcode":"67200;67200",
    "addr:street":"Rte De Schirmeck",
    "iso:country":"FR",
    "sg:address":"209, Rte de Schirmeck, 67200 Strasbourg",
    "sg:city":"Strasbourg",
    "sg:orig_category":"Unclassifiable Establishments",
    "sg:phone":"+33 3 88 29 77 10",
    "sg:postcode":"67200",
    "sg:province":"Alsace",
    "wof:name":"Laboratoire Wieger S.a.r.l.",
    "wof:placetype":"venue"
},
  "geometry": {"coordinates":[7.707724,48.566261],"type":"Point"}
}