{
  "type": "Feature",
  "properties": {
    "iso:country":"FR",
    "sg:address":"36 ave de la R\u00e9publique; Champagnole; 39300",
    "sg:classifiers":[
        {
            "category":"Banks & Credit Unions",
            "subcategory":"Bank",
            "type":"Services"
        }
    ],
    "sg:phone":"+33 3384523033",
    "sg:postcode":"39300",
    "sg:province":"Franche Comt\u00e9",
    "wof:name":"Banque Nationale De Paris",
    "wof:placetype":"venue"
},
  "geometry": {"coordinates":[5.908686,46.744865],"type":"Point"}
}