{
  "type": "Feature",
  "properties": {
    "iso:country":"FR",
    "sg:address":"4 Rue Des Salins 63000 Clermont Ferrand",
    "sg:city":"Clermont-Ferrand",
    "sg:classifiers":[
        {
            "category":"Manufacturing",
            "subcategory":"Glass & Minerals",
            "type":"Manufacturing & Wholesale Goods"
        }
    ],
    "sg:phone":"+33 4 73 93 45 21",
    "sg:postcode":"63000",
    "sg:province":"Auvergne",
    "sg:tags":[
        "building",
        "material"
    ],
    "wof:name":"Sarl Constant Perret",
    "wof:placetype":"venue"
},
  "geometry": {"coordinates":[3.080343,45.771854],"type":"Point"}
}