{
  "type": "Feature",
  "properties": {
    "addr:full":"26 R du Cdt Ren\u00e9 Mouchotte 75014 Paris Ile de France 75014",
    "addr:housenumber":"26",
    "addr:postcode":"75014;75014",
    "addr:street":"R Du Cdt Rene\u0301 Mouchotte",
    "iso:country":"FR",
    "sg:address":"26 R du Cdt Ren\u00e9 Mouchotte 75014 Paris",
    "sg:orig_category":"Didactical Toys",
    "sg:phone":"+33 1 45 38 73 62",
    "sg:postcode":"75014",
    "sg:province":"Ile de France",
    "wof:name":"Multimedia Diffusion S.a.r.l.",
    "wof:placetype":"venue"
},
  "geometry": {"coordinates":[2.319597,48.838634],"type":"Point"}
}