{
  "type": "Feature",
  "properties": {
    "addr:full":"26 rue Victor Lagrange 69007 Lyon Rhone-Alpes 69007",
    "addr:housenumber":"26",
    "addr:postcode":"69007;69007",
    "addr:street":"Rue Victor Lagrange",
    "iso:country":"FR",
    "sg:address":"26 rue Victor Lagrange 69007 Lyon",
    "sg:classifiers":[
        {
            "category":"Structure",
            "subcategory":"Building",
            "type":"Public Place"
        }
    ],
    "sg:phone":"+33 4 72 72 23 00",
    "sg:postcode":"69007",
    "sg:province":"Rhone-Alpes",
    "sg:tags":[
        "air-conditioning",
        "system",
        "maintenance",
        "servicing"
    ],
    "wof:name":"Cofatex Services Sa",
    "wof:placetype":"venue"
},
  "geometry": {"coordinates":[4.834428,45.744331],"type":"Point"}
}