{
  "type": "Feature",
  "properties": {
    "addr:full":"34, Rue de la Digue, 54000 Nancy Lorraine",
    "addr:housenumber":"34",
    "addr:postcode":"54000",
    "addr:street":"Rue De La Digue",
    "iso:country":"FR",
    "sg:address":"34, Rue de la Digue, 54000 Nancy",
    "sg:orig_category":"Unclassifiable Establishments",
    "sg:phone":"+33 3 83 39 09 09",
    "sg:province":"Lorraine",
    "wof:name":"Viltz S.a.",
    "wof:placetype":"venue"
},
  "geometry": {"coordinates":[6.204161,48.69698],"type":"Point"}
}