{
  "type": "Feature",
  "properties": {
    "iso:country":"FR",
    "sg:address":"rue Guillemet Desvignes 71570 La Chapelle De Guinchay",
    "sg:city":"Chaintr\u00e9",
    "sg:classifiers":[
        {
            "category":"Wholesale",
            "subcategory":"Wine & Distilled Alcoholic Beverages",
            "type":"Manufacturing & Wholesale Goods"
        }
    ],
    "sg:phone":"+33 3 85 33 83 21",
    "sg:postcode":"71570",
    "sg:province":"Bourgogne",
    "sg:tags":[
        "french"
    ],
    "wof:name":"Desvignes Aine & Fils Sa",
    "wof:placetype":"venue"
},
  "geometry": {"coordinates":[4.77334,46.212032],"type":"Point"}
}