{
  "type": "Feature",
  "properties": {
    "iso:country":"FR",
    "sg:address":"18, Rue Carnot, 39200 Saint Claude",
    "sg:orig_category":"Unclassifiable Establishments",
    "sg:phone":"+33 3 84 45 02 07",
    "sg:province":"Franche Comt\u00e9",
    "wof:name":"Pignon F. Et Fils S.a.r.l.",
    "wof:placetype":"venue"
},
  "geometry": {"coordinates":[5.85972,46.381569],"type":"Point"}
}