{
  "type": "Feature",
  "properties": {
    "iso:country":"FR",
    "sg:address":"64 Bis Bd Jean Jaur\u00e9s 93400 St Ouen",
    "sg:classifiers":[
        {
            "category":"Utilities",
            "subcategory":"Mobile Phone",
            "type":"Services"
        }
    ],
    "sg:phone":"+33 1 40 10 55 55",
    "sg:postcode":"93400",
    "sg:province":"Ile de France",
    "sg:tags":[
        "telecommunication",
        "audio-visual"
    ],
    "wof:name":"Techni-cine-phot",
    "wof:placetype":"venue"
},
  "geometry": {"coordinates":[2.335117,48.913216],"type":"Point"}
}