{
  "type": "Feature",
  "properties": {
    "iso:country":"FR",
    "sg:address":"3 rue Rouget de Lisle 01100 Bellignat",
    "sg:classifiers":[
        {
            "category":"Personal",
            "subcategory":"Hair Removal",
            "type":"Services"
        }
    ],
    "sg:phone":"+33 4 74 77 24 21",
    "sg:postcode":"01100",
    "sg:province":"Rhone-Alpes",
    "sg:tags":[
        "comb"
    ],
    "wof:name":"Gaudet-guillet Sa",
    "wof:placetype":"venue"
},
  "geometry": {"coordinates":[5.637915,46.252338],"type":"Point"}
}