{
  "type": "Feature",
  "properties": {
    "addr:full":"75 d'Orsay; Paris Cedex; 75321 \u00cele-de-France",
    "addr:housenumber":"75",
    "addr:postcode":"paris;75321",
    "addr:street":"D'Orsay",
    "iso:country":"FR",
    "sg:address":"75",
    "sg:city":"d'Orsay; Paris Cedex; 75321",
    "sg:classifiers":[
        {
            "category":"Industrial Area",
            "type":"Public Place"
        }
    ],
    "sg:phone":"+33 1 40 62 55 55",
    "sg:province":"\u00cele-de-France",
    "sg:tags":[
        "large",
        "private"
    ],
    "wof:name":"Soci\u00e9t\u00e9 D'oxyg\u00e8ne Et D'acetyl\u00e8ne D'extr\u00eame-orient",
    "wof:placetype":"venue"
},
  "geometry": {"coordinates":[2.316123,48.862724],"type":"Point"}
}