{
  "type": "Feature",
  "properties": {
    "addr:full":"21, Rue des Etats Unis, 44110 Ch\u00e2teaubriant Pays de Loire",
    "addr:housenumber":"21",
    "addr:postcode":"44110",
    "addr:street":"Rue Des Etats Unis",
    "iso:country":"FR",
    "sg:address":"21, Rue des Etats Unis, 44110 Ch\u00e2teaubriant",
    "sg:orig_category":"Unclassifiable Establishments",
    "sg:phone":"+33 2 40 81 10 67",
    "sg:province":"Pays de Loire",
    "wof:name":"Corbin Et Fils Etablissement S.a.r.l.",
    "wof:placetype":"venue"
},
  "geometry": {"coordinates":[-1.388873,47.702358],"type":"Point"}
}