{
  "type": "Feature",
  "properties": {
    "iso:country":"FR",
    "sg:address":"B.P. 316, 92143 Clamart C\u00e9dex^^185, Av. du G\u00e9n\u00e9ral de Gaulle, 92140 Clamart",
    "sg:orig_category":"Non-Classified Establishments",
    "sg:phone":"+33 1 41 28 87 87",
    "sg:postcode":"92140",
    "sg:province":"Ile de France",
    "wof:name":"Enertec S.a.",
    "wof:placetype":"venue"
},
  "geometry": {"coordinates":[2.262025,48.80027],"type":"Point"}
}