{
  "type": "Feature",
  "properties": {
    "addr:full":"43, Rue Antoine Condorcet - Parc Technologique de l'Isle d'Abeau, 38090 Vaulx Milieu Rhone-Alpes",
    "addr:housenumber":"43",
    "addr:postcode":"38090",
    "addr:street":"Rue Antoine Condorcet;Technologique;D'Abeau;Rhone-Alpes",
    "iso:country":"FR",
    "sg:address":"43, Rue Antoine Condorcet - Parc Technologique de l'Isle d'Abeau, 38090 Vaulx Milieu",
    "sg:orig_category":"Unclassifiable Establishments",
    "sg:phone":"+33 4 74 95 95 95",
    "sg:province":"Rhone-Alpes",
    "wof:name":"Avantec S.a.r.l.",
    "wof:placetype":"venue"
},
  "geometry": {"coordinates":[5.17867,45.612461],"type":"Point"}
}