{
  "type": "Feature",
  "properties": {
    "iso:country":"FR",
    "sg:address":"8, Rue Sainte Claire Deville, 77185 Lognes",
    "sg:orig_category":"Non-Classified Establishments",
    "sg:phone":"+33 1 60 95 43 00",
    "sg:postcode":"77185",
    "sg:province":"Ile de France",
    "wof:name":"Cyklop France",
    "wof:placetype":"venue"
},
  "geometry": {"coordinates":[2.631778,48.84021],"type":"Point"}
}