{
  "type": "Feature",
  "properties": {
    "iso:country":"FR",
    "sg:address":"6, Rue du 8 mai 1945, 78000 Versailles",
    "sg:orig_category":"Non-Classified Establishments",
    "sg:phone":"+33 1 39 24 17 17",
    "sg:province":"Ile de France",
    "wof:name":"Marbrerie Des Yvelines S.a.",
    "wof:placetype":"venue"
},
  "geometry": {"coordinates":[2.13926,48.795528],"type":"Point"}
}