{
  "type": "Feature",
  "properties": {
    "addr:full":"2 R du G\u00e9n Legrand Girarde 02100 ST QUENTIN Picardie",
    "addr:housenumber":"2",
    "addr:postcode":"02100",
    "addr:street":"R Du Ge\u0301N Legrand Girarde",
    "iso:country":"FR",
    "sg:address":"2 R du G\u00e9n Legrand Girarde 02100 ST QUENTIN",
    "sg:classifiers":[
        {
            "category":"Manufacturing",
            "subcategory":"Textiles",
            "type":"Manufacturing & Wholesale Goods"
        }
    ],
    "sg:phone":"+33 3 23 08 17 84",
    "sg:province":"Picardie",
    "sg:tags":[
        "plain",
        "fabric"
    ],
    "wof:name":"Textiles Bochard Sarl",
    "wof:placetype":"venue"
},
  "geometry": {"coordinates":[3.2924,49.853355],"type":"Point"}
}