{
  "type": "Feature",
  "properties": {
    "addr:full":"28 Rue De Rouen 67000 Strasbourg Strasbourg Alsace 67000",
    "addr:housenumber":"28",
    "addr:postcode":"67000;67000",
    "addr:street":"Rue De Rouen",
    "iso:country":"FR",
    "sg:address":"28 Rue De Rouen 67000 Strasbourg",
    "sg:city":"Strasbourg",
    "sg:classifiers":[
        {
            "category":"Banks & Credit Unions",
            "subcategory":"Investment Brokerage",
            "type":"Services"
        }
    ],
    "sg:phone":"+33 3 88 61 85 78",
    "sg:postcode":"67000",
    "sg:province":"Alsace",
    "sg:tags":[
        "-",
        "transport",
        "related"
    ],
    "wof:name":"Ste Europeenne De Stockage",
    "wof:placetype":"venue"
},
  "geometry": {"coordinates":[7.80022,48.598396],"type":"Point"}
}