{
  "type": "Feature",
  "properties": {
    "iso:country":"FR",
    "sg:address":"98, Rte de Gen\u00e8ve, 69140 Rillieux la Pape",
    "sg:orig_category":"Unclassifiable Establishments",
    "sg:phone":"+33 4 78 88 11 80",
    "sg:province":"Rhone-Alpes",
    "wof:name":"Sold'in S.a.r.l.",
    "wof:placetype":"venue"
},
  "geometry": {"coordinates":[4.898469,45.807838],"type":"Point"}
}