{
  "type": "Feature",
  "properties": {
    "addr:full":"B.P. 15, 47160 Damazan C\u00e9dex^^Rte des Landes, 47160 Damazan Damazan Aquitaine 47160",
    "addr:postcode":"47160;47160;47160",
    "addr:street":"B.P. 15",
    "iso:country":"FR",
    "sg:address":"B.P. 15, 47160 Damazan C\u00e9dex^^Rte des Landes, 47160 Damazan",
    "sg:city":"Damazan",
    "sg:orig_category":"Non-Classified Establishments",
    "sg:phone":"+33 5 53 79 40 33",
    "sg:postcode":"47160",
    "sg:province":"Aquitaine",
    "wof:name":"Etablissements Lamarque S.a.r.l.",
    "wof:placetype":"venue"
},
  "geometry": {"coordinates":[0.243943,44.227581],"type":"Point"}
}