{
  "type": "Feature",
  "properties": {
    "iso:country":"FR",
    "sg:address":"1, Rue d'Alger, 67000 Strasbourg",
    "sg:city":"Strasbourg",
    "sg:orig_category":"Unclassifiable Establishments",
    "sg:phone":"+33 3 88 61 01 06",
    "sg:postcode":"67000",
    "sg:province":"Alsace",
    "wof:name":"Locapharm S.a.",
    "wof:placetype":"venue"
},
  "geometry": {"coordinates":[7.790074,48.588287],"type":"Point"}
}