{
  "type": "Feature",
  "properties": {
    "iso:country":"FR",
    "sg:address":"Avenue de la gare 32100 CONDOM",
    "sg:classifiers":[
        {
            "category":"Food & Beverages",
            "subcategory":"Fruits & Vegetables",
            "type":"Retail Goods"
        }
    ],
    "sg:phone":"+33 5 62 28 24 77",
    "sg:postcode":"32100",
    "sg:province":"Midi Pyr\u00e9n\u00e9es",
    "sg:tags":[
        "noble",
        "brandy"
    ],
    "wof:name":"Janneau S.a.",
    "wof:placetype":"venue"
},
  "geometry": {"coordinates":[0.365515,43.960217],"type":"Point"}
}