{
  "type": "Feature",
  "properties": {
    "addr:full":"B.P. 685, 29553 Quimper C\u00e9dex^^Rte du Stangala, 29500 Ergu\u00e9 Gab\u00e9ric Ergu\u00e9-Gab\u00e9ric Bretagne 29500",
    "addr:housenumber":"b.p. 685",
    "addr:postcode":"29553;29500;29500",
    "addr:street":"Stangala",
    "iso:country":"FR",
    "sg:address":"B.P. 685, 29553 Quimper C\u00e9dex^^Rte du Stangala, 29500 Ergu\u00e9 Gab\u00e9ric",
    "sg:city":"Ergu\u00e9-Gab\u00e9ric",
    "sg:orig_category":"Non-Classified Establishments",
    "sg:phone":"+33 2 98 52 16 44",
    "sg:postcode":"29500",
    "sg:province":"Bretagne",
    "wof:name":"Marin\u00e9lec S.a.r.l.",
    "wof:placetype":"venue"
},
  "geometry": {"coordinates":[-4.028125,47.996159],"type":"Point"}
}