{
  "type": "Feature",
  "properties": {
    "addr:full":"17, Rue Louis Gu\u00e9rin, 69100 Villeurbanne Rhone-Alpes",
    "addr:housenumber":"17",
    "addr:postcode":"69100",
    "addr:street":"Rue Louis Gue\u0301Rin",
    "iso:country":"FR",
    "sg:address":"17, Rue Louis Gu\u00e9rin, 69100 Villeurbanne",
    "sg:orig_category":"Unclassifiable Establishments",
    "sg:phone":"+33 4 72 69 28 00",
    "sg:province":"Rhone-Alpes",
    "wof:name":"Sechaud & Metz S.a.",
    "wof:placetype":"venue"
},
  "geometry": {"coordinates":[4.860878,45.778236],"type":"Point"}
}