{
  "type": "Feature",
  "properties": {
    "addr:full":"Zi De Gron 89100 Gron Gron Bourgogne 89100",
    "addr:postcode":"89100;89100",
    "addr:street":"Zi De Gron",
    "iso:country":"FR",
    "sg:address":"Zi De Gron 89100 Gron",
    "sg:city":"Gron",
    "sg:classifiers":[
        {
            "category":"Manufacturing",
            "subcategory":"Rubber & Plastics",
            "type":"Manufacturing & Wholesale Goods"
        }
    ],
    "sg:phone":"+33 3 86 65 06 90",
    "sg:postcode":"89100",
    "sg:province":"Bourgogne",
    "wof:name":"Plastikpack Gmbh Et Cie France",
    "wof:placetype":"venue"
},
  "geometry": {"coordinates":[3.263471,48.160458],"type":"Point"}
}