{
  "type": "Feature",
  "properties": {
    "iso:country":"FR",
    "sg:address":"9 Rue Marcelin Berthelot 92160 Antony",
    "sg:classifiers":[
        {
            "category":"Shopping",
            "subcategory":"Computers & Home Electronics",
            "type":"Retail Goods"
        }
    ],
    "sg:phone":"+33 1 46 74 47 47",
    "sg:postcode":"92160",
    "sg:province":"Ile de France",
    "sg:tags":[
        "equipment",
        "electrical",
        "component",
        "electric",
        "electronic"
    ],
    "wof:name":"Cci Eurolam Sa",
    "wof:placetype":"venue"
},
  "geometry": {"coordinates":[2.314957,48.735813],"type":"Point"}
}