{
  "type": "Feature",
  "properties": {
    "addr:full":"97 Av De Verdun 93230 Romainville Ile de France 93230",
    "addr:postcode":"93230;ile;93230",
    "addr:street":"97 Av De Verdun;France",
    "iso:country":"FR",
    "sg:address":"97 Av De Verdun 93230 Romainville",
    "sg:classifiers":[
        {
            "category":"Utilities",
            "subcategory":"Mobile Phone",
            "type":"Services"
        }
    ],
    "sg:phone":"+33 1 49 15 15 15",
    "sg:postcode":"93230",
    "sg:province":"Ile de France",
    "sg:tags":[
        "telecommunication",
        "audio-visual"
    ],
    "wof:name":"Nokia France Sa",
    "wof:placetype":"venue"
},
  "geometry": {"coordinates":[2.429522,48.881519],"type":"Point"}
}