{
  "type": "Feature",
  "properties": {
    "iso:country":"FR",
    "sg:address":"Rue d'Arponlieu",
    "sg:city":"Dourges",
    "sg:orig_category":"Unclassifiable Establishments",
    "sg:phone":"+33 3 21 49 45 80",
    "sg:postcode":"62119",
    "sg:province":"Nord Pas-de-Calais",
    "wof:name":"Menuiserie Pont \u00e0 Sault S.a.r.l.",
    "wof:placetype":"venue"
},
  "geometry": {"coordinates":[1.664881,50.237923],"type":"Point"}
}