{
  "type": "Feature",
  "properties": {
    "addr:full":"B.P. 3 Ch\u00e2tenois Lorraine 88170",
    "addr:postcode":"88170",
    "addr:street":"B.P. 3",
    "iso:country":"FR",
    "sg:address":"B.P. 3",
    "sg:city":"Ch\u00e2tenois",
    "sg:orig_category":"Non-Classified Establishments",
    "sg:phone":"+33 3 29 94 50 54",
    "sg:postcode":"88170",
    "sg:province":"Lorraine",
    "wof:name":"So.vo.co S.a. - Soci\u00e9t\u00e9 Vosgienne De Conserves",
    "wof:placetype":"venue"
},
  "geometry": {"coordinates":[5.832454,48.302082],"type":"Point"}
}