{
  "type": "Feature",
  "properties": {
    "iso:country":"FR",
    "sg:address":"1, Rue Augereau, 37100 Tours",
    "sg:city":"Tours",
    "sg:orig_category":"Non-Classified Establishments",
    "sg:phone":"+33 2 47 88 27 00",
    "sg:postcode":"37100",
    "sg:province":"Centre",
    "wof:name":"Gr\u00e9ta Touraine",
    "wof:placetype":"venue"
},
  "geometry": {"coordinates":[0.674,47.42255],"type":"Point"}
}