{
  "type": "Feature",
  "properties": {
    "addr:full":"1, All\u00e9e des Entrepreneurs, 10100 Romilly sur Seine Champagne",
    "addr:housenumber":"1",
    "addr:postcode":"10100",
    "addr:street":"Alle\u0301E Des Entrepreneurs",
    "iso:country":"FR",
    "sg:address":"1, All\u00e9e des Entrepreneurs, 10100 Romilly sur Seine",
    "sg:orig_category":"Unclassifiable Establishments",
    "sg:phone":"+33 3 25 39 56 00",
    "sg:province":"Champagne",
    "wof:name":"Poup\u00e9e Mat\u00e9riaux S.a.",
    "wof:placetype":"venue"
},
  "geometry": {"coordinates":[3.713707,48.509781],"type":"Point"}
}