{
  "type": "Feature",
  "properties": {
    "iso:country":"FR",
    "sg:address":"14 Av Des Tilleuls 71500 Louhans",
    "sg:city":"Louhans",
    "sg:classifiers":[
        {
            "category":"Shopping",
            "type":"Retail Goods"
        }
    ],
    "sg:phone":"+33 3 85 75 72 72",
    "sg:postcode":"71500",
    "sg:province":"Bourgogne",
    "sg:tags":[
        "metallurgy",
        "finished",
        "-",
        "metalworking",
        "metallic"
    ],
    "wof:name":"Societe Mecanique Tolerie Louhannaise Sa",
    "wof:placetype":"venue"
},
  "geometry": {"coordinates":[5.211139,46.628887],"type":"Point"}
}