{
  "type": "Feature",
  "properties": {
    "addr:full":"11, Rue des Selliers - Actip\u00f4le, 57070 Metz Lorraine",
    "addr:housenumber":"11",
    "addr:postcode":"57070",
    "addr:street":"Rue Des Selliers Actipo\u0302Le",
    "iso:country":"FR",
    "sg:address":"11, Rue des Selliers - Actip\u00f4le, 57070 Metz",
    "sg:orig_category":"Non-Classified Establishments",
    "sg:phone":"+33 3 87 76 02 79",
    "sg:province":"Lorraine",
    "wof:name":"M.a.e.c. S.a. - Manufacture Appareillage Electrique De Cahors",
    "wof:placetype":"venue"
},
  "geometry": {"coordinates":[6.25025,49.115391],"type":"Point"}
}