{
  "type": "Feature",
  "properties": {
    "addr:full":"53, Rue de la Chapelle, 49000 Angers Pays de Loire",
    "addr:housenumber":"53",
    "addr:postcode":"49000",
    "addr:street":"Rue De La Chapelle",
    "iso:country":"FR",
    "sg:address":"53, Rue de la Chapelle, 49000 Angers",
    "sg:orig_category":"Unclassifiable Establishments",
    "sg:phone":"+33 2 41 68 08 18",
    "sg:province":"Pays de Loire",
    "wof:name":"Jean-louis Di Scala S.a.",
    "wof:placetype":"venue"
},
  "geometry": {"coordinates":[-0.540249,47.45829],"type":"Point"}
}