{
  "type": "Feature",
  "properties": {
    "addr:full":"15, Rue de la Haye, 52220 Droyes Champagne",
    "addr:housenumber":"15",
    "addr:postcode":"52220",
    "addr:street":"Rue De La Haye",
    "iso:country":"FR",
    "sg:address":"15, Rue de la Haye, 52220 Droyes",
    "sg:orig_category":"Non-Classified Establishments",
    "sg:phone":"+33 3 25 04 23 28",
    "sg:province":"Champagne",
    "wof:name":"Le Canard Du Bocage S.a.r.l.",
    "wof:placetype":"venue"
},
  "geometry": {"coordinates":[4.845838,48.4095],"type":"Point"}
}