{
  "type": "Feature",
  "properties": {
    "addr:full":"Rte de la Charit\u00e9 Saint Germain du Puy Centre 18390",
    "addr:postcode":"18390",
    "addr:street":"Rte De La Charite\u0301",
    "iso:country":"FR",
    "sg:address":"Rte de la Charit\u00e9",
    "sg:city":"Saint Germain du Puy",
    "sg:orig_category":"Unclassifiable Establishments",
    "sg:phone":"+33 2 48 67 70 00",
    "sg:postcode":"18390",
    "sg:province":"Centre",
    "wof:name":"C.m.m.u. - Comptoirs Modernes Major-unidis",
    "wof:placetype":"venue"
},
  "geometry": {"coordinates":[2.441085,47.096161],"type":"Point"}
}