{
  "type": "Feature",
  "properties": {
    "addr:full":"Martinet du Haut 39110 Salins les Bains Franche Comt\u00e9 39110",
    "addr:postcode":"39110;39110",
    "addr:street":"Martinet;Haut;Franche Comte\u0301",
    "iso:country":"FR",
    "sg:address":"Martinet du Haut 39110 Salins les Bains",
    "sg:orig_category":"Cryogenic Seals",
    "sg:phone":"+33 3 84 37 97 70",
    "sg:postcode":"39110",
    "sg:province":"Franche Comt\u00e9",
    "wof:name":"Cryonic Medical Sa",
    "wof:placetype":"venue"
},
  "geometry": {"coordinates":[5.935865,46.852779],"type":"Point"}
}