{
  "type": "Feature",
  "properties": {
    "addr:full":"Rte de Ham les Moines Cliron Champagne 08090",
    "addr:postcode":"08090",
    "addr:street":"Rte De Ham;Champagne",
    "iso:country":"FR",
    "sg:address":"Rte de Ham les Moines",
    "sg:city":"Cliron",
    "sg:orig_category":"Non-Classified Establishments",
    "sg:phone":"+33 3 24 52 94 34",
    "sg:postcode":"08090",
    "sg:province":"Champagne",
    "wof:name":"Atom - Sodery S.a.",
    "wof:placetype":"venue"
},
  "geometry": {"coordinates":[4.667313,49.792923],"type":"Point"}
}