{
  "type": "Feature",
  "properties": {
    "iso:country":"FR",
    "sg:address":"22 rue Georges Clemenceau 03200 Vichy",
    "sg:city":"Vichy",
    "sg:orig_category":"Magnification Loupes",
    "sg:phone":"+33 4 70 30 19 30",
    "sg:postcode":"03200",
    "sg:province":"Auvergne",
    "wof:name":"Ste Jean Et Pierre Medas Sa",
    "wof:placetype":"venue"
},
  "geometry": {"coordinates":[3.422729,46.124969],"type":"Point"}
}