{
  "type": "Feature",
  "properties": {
    "addr:full":"2BIS rue Mercoeur 75011 Paris Ile de France 75011",
    "addr:housenumber":"2bis",
    "addr:postcode":"75011;75011",
    "addr:street":"Rue Mercoeur",
    "iso:country":"FR",
    "sg:address":"2BIS rue Mercoeur 75011 Paris",
    "sg:classifiers":[
        {
            "category":"Wholesale",
            "subcategory":"Medical Equipment & Supplies",
            "type":"Manufacturing & Wholesale Goods"
        }
    ],
    "sg:phone":"+33 1 43 48 67 27",
    "sg:postcode":"75011",
    "sg:province":"Ile de France",
    "sg:tags":[
        "dental",
        "used"
    ],
    "wof:name":"Evident Sa",
    "wof:placetype":"venue"
},
  "geometry": {"coordinates":[2.382523,48.856544],"type":"Point"}
}