{
  "type": "Feature",
  "properties": {
    "iso:country":"FR",
    "sg:address":"18 rue de Cherbourg 68260 Kingersheim",
    "sg:city":"Kingersheim",
    "sg:classifiers":[
        {
            "category":"Manufacturing",
            "subcategory":"Wood Products",
            "type":"Manufacturing & Wholesale Goods"
        }
    ],
    "sg:phone":"+33 3 89 52 21 15",
    "sg:postcode":"68260",
    "sg:province":"Alsace",
    "sg:tags":[
        "treating"
    ],
    "wof:name":"Produits Mauler Sa",
    "wof:placetype":"venue"
},
  "geometry": {"coordinates":[7.312773,47.776814],"type":"Point"}
}