{
  "type": "Feature",
  "properties": {
    "addr:full":"23 B Cours Carnot Elbeuf Haute Normandie 76500",
    "addr:housenumber":"23 b",
    "addr:postcode":"76500",
    "addr:street":"Cours Carnot;Haute Normandie",
    "iso:country":"FR",
    "sg:address":"23 B Cours Carnot",
    "sg:city":"Elbeuf",
    "sg:classifiers":[
        {
            "category":"Banks & Credit Unions",
            "subcategory":"Financial Services",
            "type":"Services"
        }
    ],
    "sg:phone":"+33 2 35 77 20 50",
    "sg:postcode":"76500",
    "sg:province":"Haute Normandie",
    "sg:tags":[
        "banking",
        "finance",
        "insurance"
    ],
    "wof:name":"Fiduciaire De France Societe D'expertise Comptable Commissai (fidex)",
    "wof:placetype":"venue"
},
  "geometry": {"coordinates":[1.013173,49.287197],"type":"Point"}
}