{
  "type": "Feature",
  "properties": {
    "addr:full":"5 Rue Schumann Zac Du Breuil 54850 Messein Lorraine 54850",
    "addr:housenumber":"5",
    "addr:postcode":"54850;54850",
    "addr:street":"Rue Schumann Zac Du Breuil",
    "iso:country":"FR",
    "sg:address":"5 Rue Schumann Zac Du Breuil 54850 Messein",
    "sg:classifiers":[
        {
            "category":"Professional",
            "subcategory":"Engineering",
            "type":"Services"
        }
    ],
    "sg:phone":"+33 3 83 54 87 40",
    "sg:postcode":"54850",
    "sg:province":"Lorraine",
    "sg:tags":[
        "machine",
        "-",
        "mechanical"
    ],
    "wof:name":"Air Eco Concept (aec)",
    "wof:placetype":"venue"
},
  "geometry": {"coordinates":[6.145854,48.609951],"type":"Point"}
}