{
  "type": "Feature",
  "properties": {
    "addr:full":"Ch\u00e2teau de Belle Rose - lieu dit Gardat Montagne Aquitaine 33570",
    "addr:postcode":"33570",
    "addr:street":"Dit Gardat Montagne",
    "iso:country":"FR",
    "sg:address":"Ch\u00e2teau de Belle Rose - lieu dit Gardat",
    "sg:city":"Montagne",
    "sg:orig_category":"Unclassifiable Establishments",
    "sg:phone":"+33 5 57 74 61 16",
    "sg:postcode":"33570",
    "sg:province":"Aquitaine",
    "wof:name":"Vignobles Lacour S.c.e.a.",
    "wof:placetype":"venue"
},
  "geometry": {"coordinates":[-0.073954,44.924324],"type":"Point"}
}