{
  "type": "Feature",
  "properties": {
    "iso:country":"FR",
    "sg:address":"Lieu Dit Laugerie 87220 Feytiat",
    "sg:classifiers":[
        {
            "category":"Professional",
            "type":"Services"
        }
    ],
    "sg:phone":"+33 5 55 31 33 03",
    "sg:province":"Limousin",
    "sg:tags":[
        "transport",
        "road"
    ],
    "wof:name":"Transports Demenagements Reunis Sa",
    "wof:placetype":"venue"
},
  "geometry": {"coordinates":[1.323045,45.736263],"type":"Point"}
}