{
  "type": "Feature",
  "properties": {
    "iso:country":"FR",
    "sg:address":"129, Av. Galli\u00e9ni, 93140 Bondy",
    "sg:orig_category":"Unclassifiable Establishments",
    "sg:phone":"+33 1 48 02 32 32",
    "sg:province":"Ile de France",
    "wof:name":"Darty S.a.",
    "wof:placetype":"venue"
},
  "geometry": {"coordinates":[2.482653,48.906467],"type":"Point"}
}