{
  "type": "Feature",
  "properties": {
    "iso:country":"FR",
    "sg:address":"ZI Le Sourn",
    "sg:city":"Pontivy",
    "sg:orig_category":"Unclassifiable Establishments",
    "sg:phone":"+33 2 97 25 20 20",
    "sg:postcode":"56300",
    "sg:province":"Bretagne",
    "wof:name":"Gallais N\u00e9goce S.a.",
    "wof:placetype":"venue"
},
  "geometry": {"coordinates":[-2.966129,48.064919],"type":"Point"}
}