{
  "type": "Feature",
  "properties": {
    "addr:full":"33460 Cussac Fort M\u00e9doc Macau Aquitaine 33460",
    "addr:postcode":"33460;33460",
    "addr:street":"Cussac Fort",
    "iso:country":"FR",
    "sg:address":"33460 Cussac Fort M\u00e9doc",
    "sg:city":"Macau",
    "sg:orig_category":"Non-Classified Establishments",
    "sg:phone":"+33 5 56 58 91 10",
    "sg:postcode":"33460",
    "sg:province":"Aquitaine",
    "wof:name":"Ch\u00e2teau Tour Du Haut Moulin S.c.e.a.",
    "wof:placetype":"venue"
},
  "geometry": {"coordinates":[-0.730719,45.11945],"type":"Point"}
}