{
  "type": "Feature",
  "properties": {
    "addr:full":"Za Des Dolines 25500 Le B\u00e9lieu Franche Comt\u00e9",
    "addr:postcode":"25500",
    "addr:street":"Za Des Dolines;Franche Comte\u0301",
    "iso:country":"FR",
    "sg:address":"Za Des Dolines 25500 Le B\u00e9lieu",
    "sg:classifiers":[
        {
            "category":"Manufacturing",
            "subcategory":"Paper Products",
            "type":"Manufacturing & Wholesale Goods"
        }
    ],
    "sg:phone":"+33 3 81 67 14 63",
    "sg:province":"Franche Comt\u00e9",
    "sg:tags":[
        "packaging",
        "material",
        "-",
        "cardboard"
    ],
    "wof:name":"Cartonnages Pfahrer",
    "wof:placetype":"venue"
},
  "geometry": {"coordinates":[6.633296,47.119316],"type":"Point"}
}