{
  "type": "Feature",
  "properties": {
    "addr:full":"11, Bd d'Eylau - ZI Nord, 85000 La Roche sur Yon Pays de Loire",
    "addr:housenumber":"11",
    "addr:postcode":"85000",
    "addr:street":"Bd D'Eylau Zi Nord;Roche;Yon",
    "iso:country":"FR",
    "sg:address":"11, Bd d'Eylau - ZI Nord, 85000 La Roche sur Yon",
    "sg:orig_category":"Unclassifiable Establishments",
    "sg:phone":"+33 2 51 05 48 52",
    "sg:province":"Pays de Loire",
    "wof:name":"Caillaud Tamo S.a.r.l.",
    "wof:placetype":"venue"
},
  "geometry": {"coordinates":[-1.427244,46.683128],"type":"Point"}
}