{
  "type": "Feature",
  "properties": {
    "addr:full":"8 rue de la Richonne 16100 ST LAURENT DE COGNAC Poitou-Charentes 16100",
    "addr:housenumber":"8",
    "addr:postcode":"16100;cognac;16100",
    "addr:street":"Rue De La Richonne",
    "iso:country":"FR",
    "sg:address":"8 rue de la Richonne 16100 ST LAURENT DE COGNAC",
    "sg:classifiers":[
        {
            "category":"Food & Beverages",
            "subcategory":"Fruits & Vegetables",
            "type":"Retail Goods"
        }
    ],
    "sg:phone":"+33 5 45 35 79 79",
    "sg:postcode":"16100",
    "sg:province":"Poitou-Charentes",
    "sg:tags":[
        "noble",
        "brandy"
    ],
    "wof:name":"Jas Hennessy Et Compagnie S.a.",
    "wof:placetype":"venue"
},
  "geometry": {"coordinates":[-0.331223,45.6964],"type":"Point"}
}