{
  "type": "Feature",
  "properties": {
    "iso:country":"FR",
    "sg:address":"51 All Gluck 68069 Mulhouse",
    "sg:classifiers":[
        {
            "category":"Shopping",
            "subcategory":"Stationery & Office Supplies",
            "type":"Retail Goods"
        }
    ],
    "sg:phone":"+33 3 89 32 64 00",
    "sg:province":"Midi Pyr\u00e9n\u00e9es",
    "sg:tags":[
        "information",
        "technology",
        "telecommunication",
        "equipment"
    ],
    "wof:name":"Clemessy Telecommunication",
    "wof:placetype":"venue"
},
  "geometry": {"coordinates":[7.32026,47.756001],"type":"Point"}
}