{
  "type": "Feature",
  "properties": {
    "addr:full":"B.P. 23 Petite Rosselle^^Puits Gargan 57540 Petite Rosselle Lorraine 57540",
    "addr:postcode":"57540;57540",
    "addr:street":"B.P. 23 Petite Rosselle^^Puits Gargan;Rosselle",
    "iso:country":"FR",
    "sg:address":"B.P. 23",
    "sg:city":"Petite Rosselle^^Puits Gargan 57540 Petite Rosselle",
    "sg:orig_category":"Non-Classified Establishments",
    "sg:phone":"+33 3 87 85 46 89",
    "sg:postcode":"57540",
    "sg:province":"Lorraine",
    "wof:name":"Soci\u00e9t\u00e9 G\u00e9n\u00e9rale Du B\u00e2timent S.a.r.l.",
    "wof:placetype":"venue"
},
  "geometry": {"coordinates":[6.845923,49.207031],"type":"Point"}
}