{
  "type": "Feature",
  "properties": {
    "addr:full":"11, Rue de la Boissi\u00e8re, 76170 La Frenaye Haute Normandie 76170",
    "addr:housenumber":"11",
    "addr:postcode":"76170;76170",
    "addr:street":"Rue De La Boissie\u0300Re;Frenaye Haute Normandie",
    "iso:country":"FR",
    "sg:address":"11, Rue de la Boissi\u00e8re, 76170 La Frenaye",
    "sg:orig_category":"Non-Classified Establishments",
    "sg:phone":"+33 2 35 38 01 15",
    "sg:postcode":"76170",
    "sg:province":"Haute Normandie",
    "wof:name":"Chriralsep S.a.",
    "wof:placetype":"venue"
},
  "geometry": {"coordinates":[0.580671,49.527309],"type":"Point"}
}