{
  "type": "Feature",
  "properties": {
    "iso:country":"FR",
    "sg:address":"42, Av. du Progr\u00e8s, 69680 Chassieu",
    "sg:orig_category":"Non-Classified Establishments",
    "sg:phone":"+33 4 72 47 42 00",
    "sg:postcode":"69680",
    "sg:province":"Rhone-Alpes",
    "wof:name":"Sgb S.a.s.",
    "wof:placetype":"venue"
},
  "geometry": {"coordinates":[4.965242,45.733856],"type":"Point"}
}