{
  "type": "Feature",
  "properties": {
    "iso:country":"FR",
    "sg:address":"182 Rue De Saint Prix 95157 Taverny",
    "sg:classifiers":[
        {
            "category":"Manufacturing",
            "subcategory":"Rubber & Plastics",
            "type":"Manufacturing & Wholesale Goods"
        }
    ],
    "sg:phone":"+33 1 34 18 39 90",
    "sg:province":"Basse Normandie",
    "sg:tags":[
        "packaging",
        "material",
        "-"
    ],
    "wof:name":"Pivaudran Sa",
    "wof:placetype":"venue"
},
  "geometry": {"coordinates":[2.18955,49.021858],"type":"Point"}
}