{
  "type": "Feature",
  "properties": {
    "addr:full":"10 Cloitre Saint Aignan 45000 Orleans Orl\u00e9ans Centre 45000",
    "addr:housenumber":"10",
    "addr:postcode":"45000;45000",
    "addr:street":"Cloitre Saint Aignan",
    "iso:country":"FR",
    "sg:address":"10 Cloitre Saint Aignan 45000 Orleans",
    "sg:city":"Orl\u00e9ans",
    "sg:classifiers":[
        {
            "category":"Shopping",
            "subcategory":"Clothing, Apparel, & Fashions",
            "type":"Retail Goods"
        }
    ],
    "sg:phone":"+33 2 38 53 74 15",
    "sg:postcode":"45000",
    "sg:province":"Centre",
    "sg:tags":[
        "textile",
        "clothing",
        "clothes"
    ],
    "wof:name":"Saprim Diffusion",
    "wof:placetype":"venue"
},
  "geometry": {"coordinates":[1.916384,47.899525],"type":"Point"}
}