{
  "type": "Feature",
  "properties": {
    "iso:country":"FR",
    "sg:address":"24, Bd Poissonni\u00e8re, 75009 Paris",
    "sg:orig_category":"Non-Classified Establishments",
    "sg:phone":"+33 1 44 79 97 05",
    "sg:postcode":"75009",
    "sg:province":"Ile de France",
    "wof:name":"B.i.m. Sifram Group Sarl - Business International Merchant",
    "wof:placetype":"venue"
},
  "geometry": {"coordinates":[2.344561,48.871365],"type":"Point"}
}