{
  "type": "Feature",
  "properties": {
    "iso:country":"FR",
    "sg:address":"R Des Cressoni\u00e8res 95500 Gonesse",
    "sg:classifiers":[
        {
            "category":"Professional",
            "subcategory":"Engineering",
            "type":"Services"
        }
    ],
    "sg:phone":"+33 1 39 87 52 66",
    "sg:postcode":"95500",
    "sg:province":"Ile de France",
    "sg:tags":[
        "machine",
        "-",
        "mechanical"
    ],
    "wof:name":"Maruani J R",
    "wof:placetype":"venue"
},
  "geometry": {"coordinates":[2.458405,48.988464],"type":"Point"}
}