{
  "type": "Feature",
  "properties": {
    "iso:country":"FR",
    "sg:address":"13, Rue Henri Brion, 78300 Poissy",
    "sg:orig_category":"Unclassifiable Establishments",
    "sg:phone":"+33 1 39 11 50 39",
    "sg:province":"Ile de France",
    "wof:name":"Sodep - Soci\u00e9t\u00e9 Outillage D\u00e9coupage Emboutissage Pr\u00e9cision S.a.r.l.",
    "wof:placetype":"venue"
},
  "geometry": {"coordinates":[2.061279,48.934837],"type":"Point"}
}