{
  "type": "Feature",
  "properties": {
    "addr:full":"Rue L\u00e9o Lagrange - ZA la Bargette Saint Priest en Jarez Rhone-Alpes 42270",
    "addr:postcode":"42270",
    "addr:street":"Rue Le\u0301O Lagrange Za La Bargette Saint;Rhone-Alpes",
    "iso:country":"FR",
    "sg:address":"Rue L\u00e9o Lagrange - ZA la Bargette",
    "sg:city":"Saint Priest en Jarez",
    "sg:orig_category":"Non-Classified Establishments",
    "sg:phone":"+33 4 77 92 54 92",
    "sg:postcode":"42270",
    "sg:province":"Rhone-Alpes",
    "wof:name":"Locapharm S.a.",
    "wof:placetype":"venue"
},
  "geometry": {"coordinates":[4.379601,45.473232],"type":"Point"}
}