{
  "type": "Feature",
  "properties": {
    "iso:country":"FR",
    "sg:address":"9, Rue Saboterie, 87700 Aixe sur Vienne",
    "sg:orig_category":"Unclassifiable Establishments",
    "sg:phone":"+33 5 55 30 90 50",
    "sg:province":"Limousin",
    "wof:name":"B.p.c. - Banque Populaire Du Centre",
    "wof:placetype":"venue"
},
  "geometry": {"coordinates":[1.135605,45.79554],"type":"Point"}
}