{
  "type": "Feature",
  "properties": {
    "addr:full":"Z.I. de Bellevue Secondigny Poitou-Charentes 79130",
    "addr:postcode":"79130",
    "addr:street":"Z.I. De Bellevue Secondigny",
    "iso:country":"FR",
    "sg:address":"Z.I. de Bellevue",
    "sg:city":"Secondigny",
    "sg:orig_category":"Unclassifiable Establishments",
    "sg:phone":"+33 5 49 63 70 90",
    "sg:postcode":"79130",
    "sg:province":"Poitou-Charentes",
    "wof:name":"Hangarter",
    "wof:placetype":"venue"
},
  "geometry": {"coordinates":[-0.443124,46.563416],"type":"Point"}
}