{
  "type": "Feature",
  "properties": {
    "iso:country":"FR",
    "sg:address":"Rue Andr\u00e9 Maginot - ZA",
    "sg:city":"Marckolsheim",
    "sg:orig_category":"Unclassifiable Establishments",
    "sg:phone":"+33 3 88 58 64 70",
    "sg:postcode":"67390",
    "sg:province":"Alsace",
    "wof:name":"Ad\u00e9fo Chimie S.a.",
    "wof:placetype":"venue"
},
  "geometry": {"coordinates":[7.545834,48.167503],"type":"Point"}
}