{
  "type": "Feature",
  "properties": {
    "addr:full":"Rue des Lavandi\u00e8res - Domaine le Vieux Moulin Tavel Languedoc-Roussillon 30126",
    "addr:postcode":"30126",
    "addr:street":"Rue Des Lavandie\u0300Res;Le",
    "iso:country":"FR",
    "sg:address":"Rue des Lavandi\u00e8res - Domaine le Vieux Moulin",
    "sg:city":"Tavel",
    "sg:orig_category":"Unclassifiable Establishments",
    "sg:phone":"+33 4 66 50 07 79",
    "sg:postcode":"30126",
    "sg:province":"Languedoc-Roussillon",
    "wof:name":"Caves Roudil Henri Dominique S.a.r.l.",
    "wof:placetype":"venue"
},
  "geometry": {"coordinates":[4.698181,44.05442],"type":"Point"}
}