{
  "type": "Feature",
  "properties": {
    "iso:country":"FR",
    "sg:address":"2, Rue Chevremont, 57000 Metz",
    "sg:orig_category":"Unclassifiable Establishments",
    "sg:phone":"+33 3 87 76 28 11",
    "sg:province":"Lorraine",
    "wof:name":"Tinus Bernard",
    "wof:placetype":"venue"
},
  "geometry": {"coordinates":[6.177789,49.121197],"type":"Point"}
}