{
  "type": "Feature",
  "properties": {
    "addr:full":"3 Ram Sainte Melaine 29600 Morlaix Morlaix Bretagne 29600",
    "addr:housenumber":"3",
    "addr:postcode":"29600;29600",
    "addr:street":"Ram Sainte Melaine",
    "iso:country":"FR",
    "sg:address":"3 Ram Sainte Melaine 29600 Morlaix",
    "sg:city":"Morlaix",
    "sg:classifiers":[
        {
            "category":"Professional",
            "subcategory":"Printing & Photocopies",
            "type":"Services"
        }
    ],
    "sg:phone":"+33 2 98 63 88 20",
    "sg:postcode":"29600",
    "sg:province":"Bretagne",
    "sg:tags":[
        "publishing"
    ],
    "wof:name":"Societe Ouest France",
    "wof:placetype":"venue"
},
  "geometry": {"coordinates":[-3.828595,48.578407],"type":"Point"}
}