{
  "type": "Feature",
  "properties": {
    "iso:country":"FR",
    "sg:address":"64 rue La Fayette 75009 Paris",
    "sg:classifiers":[
        {
            "category":"Shopping",
            "subcategory":"Jewelry",
            "type":"Retail Goods"
        }
    ],
    "sg:phone":"+33 1 45 23 41 41",
    "sg:postcode":"75009",
    "sg:province":"Ile de France",
    "sg:tags":[
        "gemstone",
        "jewellery"
    ],
    "wof:name":"Lully S.a.r.l.",
    "wof:placetype":"venue"
},
  "geometry": {"coordinates":[2.343515,48.875679],"type":"Point"}
}