{
  "type": "Feature",
  "properties": {
    "iso:country":"FR",
    "sg:address":"132 Grand Rue 67500 Haguenau",
    "sg:city":"Haguenau",
    "sg:classifiers":[
        {
            "category":"Professional",
            "subcategory":"Printing & Photocopies",
            "type":"Services"
        }
    ],
    "sg:phone":"+33 3 88 73 59 59",
    "sg:postcode":"67500",
    "sg:province":"Alsace",
    "sg:tags":[
        "publishing"
    ],
    "wof:name":"Comareg Sa",
    "wof:placetype":"venue"
},
  "geometry": {"coordinates":[7.788681,48.814358],"type":"Point"}
}