{
  "type": "Feature",
  "properties": {
    "addr:full":"12 Quimper Bretagne 29000",
    "addr:housenumber":"12",
    "addr:postcode":"29000",
    "addr:street":"Quimper Bretagne",
    "iso:country":"FR",
    "sg:address":"12",
    "sg:city":"Quimper",
    "sg:classifiers":[
        {
            "category":"Social Services",
            "subcategory":"Retirement Home",
            "type":"Services"
        }
    ],
    "sg:phone":"+33 2 98 95 39 24",
    "sg:postcode":"29000",
    "sg:province":"Bretagne",
    "sg:tags":[
        "ceramic",
        "wood",
        "household",
        "good",
        "furniture"
    ],
    "wof:name":"Art De Cornouaille",
    "wof:placetype":"venue"
},
  "geometry": {"coordinates":[-4.103299,47.995583],"type":"Point"}
}