{
  "type": "Feature",
  "properties": {
    "addr:full":"10, Rue des Gardes - ZA Les Gardes, 91370 Verri\u00e8res le Buisson Ile de France",
    "addr:housenumber":"10",
    "addr:postcode":"91370",
    "addr:street":"Rue Des Gardes Za Les Gardes",
    "iso:country":"FR",
    "sg:address":"10, Rue des Gardes - ZA Les Gardes, 91370 Verri\u00e8res le Buisson",
    "sg:orig_category":"Unclassifiable Establishments",
    "sg:phone":"+33 1 69 93 80 80",
    "sg:province":"Ile de France",
    "wof:name":"Labelvage S.a.r.l.",
    "wof:placetype":"venue"
},
  "geometry": {"coordinates":[2.266935,48.746086],"type":"Point"}
}