{
  "type": "Feature",
  "properties": {
    "iso:country":"FR",
    "sg:address":"94 R Beno\u00eet Malon 94270 Le Kremlin Bic\u00eatre",
    "sg:classifiers":[
        {
            "category":"Shopping",
            "subcategory":"Bicycles & Sporting Goods",
            "type":"Retail Goods"
        }
    ],
    "sg:phone":"+33 1 46 72 36 57",
    "sg:postcode":"94270",
    "sg:province":"Ile de France",
    "sg:tags":[
        "product",
        "sport",
        "miscellaneous"
    ],
    "wof:name":"Tap Ball 2000 Sarl",
    "wof:placetype":"venue"
},
  "geometry": {"coordinates":[2.34898,48.804066],"type":"Point"}
}