{
  "type": "Feature",
  "properties": {
    "iso:country":"FR",
    "sg:address":"2a R Du Mar\u00e9chal Koenig 67210 Obernai",
    "sg:city":"Obernai",
    "sg:classifiers":[
        {
            "category":"Wholesale",
            "subcategory":"Medical Equipment & Supplies",
            "type":"Manufacturing & Wholesale Goods"
        }
    ],
    "sg:phone":"+33 3 88 95 19 75",
    "sg:postcode":"67210",
    "sg:province":"Alsace",
    "sg:tags":[
        "instrument",
        "health",
        "-",
        "precision"
    ],
    "wof:name":"Laboratoire Bannwarth",
    "wof:placetype":"venue"
},
  "geometry": {"coordinates":[7.493755,48.459824],"type":"Point"}
}