{
  "type": "Feature",
  "properties": {
    "addr:full":"Rue du Carreau Entrange Lorraine 57330",
    "addr:postcode":"57330",
    "addr:street":"Rue Du Carreau Entrange Lorraine",
    "iso:country":"FR",
    "sg:address":"Rue du Carreau",
    "sg:city":"Entrange",
    "sg:orig_category":"Non-Classified Establishments",
    "sg:phone":"+33 3 82 55 14 55",
    "sg:postcode":"57330",
    "sg:province":"Lorraine",
    "wof:name":"Sertisol S.a. - Soci\u00e9t\u00e9 D'etudes Et R\u00e9alisation De Travaux D'isolation",
    "wof:placetype":"venue"
},
  "geometry": {"coordinates":[6.119025,49.418701],"type":"Point"}
}