{
  "type": "Feature",
  "properties": {
    "addr:full":"1 Rue Graverot 25260 COLOMBIER FONTAINE Franche Comt\u00e9 25260",
    "addr:housenumber":"1",
    "addr:postcode":"25260;25260",
    "addr:street":"Rue Graverot;Franche Comte\u0301",
    "iso:country":"FR",
    "sg:address":"1 Rue Graverot 25260 COLOMBIER FONTAINE",
    "sg:classifiers":[
        {
            "category":"Manufacturing",
            "subcategory":"Wood Products",
            "type":"Manufacturing & Wholesale Goods"
        }
    ],
    "sg:phone":"+33 3 81 93 70 82",
    "sg:postcode":"25260",
    "sg:province":"Franche Comt\u00e9",
    "sg:tags":[
        "lumber"
    ],
    "wof:name":"Bourlier Demont S.a.r.l.",
    "wof:placetype":"venue"
},
  "geometry": {"coordinates":[6.689657,47.450146],"type":"Point"}
}