{
  "type": "Feature",
  "properties": {
    "addr:full":"B.P. 9006, 95070 Cergy Pontoise C\u00e9dex^^14, Rue du Bois de Pont, 95310 Saint Ouen l'Aum\u00f4ne Ile de France",
    "addr:postcode":"95070;95310",
    "addr:street":"B.P. 9006;Rue Du Bois De Pont",
    "iso:country":"FR",
    "sg:address":"B.P. 9006, 95070 Cergy Pontoise C\u00e9dex^^14, Rue du Bois de Pont, 95310 Saint Ouen l'Aum\u00f4ne",
    "sg:orig_category":"Non-Classified Establishments",
    "sg:phone":"+33 1 34 48 36 36",
    "sg:province":"Ile de France",
    "wof:name":"La Cornue S.a.",
    "wof:placetype":"venue"
},
  "geometry": {"coordinates":[-1.227549,46.528107],"type":"Point"}
}