{
  "type": "Feature",
  "properties": {
    "addr:full":"Chez Rochard 16300 Lagarde sur le N\u00e9 Poitou-Charentes",
    "addr:postcode":"16300",
    "addr:street":"Chez Rochard",
    "iso:country":"FR",
    "sg:address":"Chez Rochard 16300 Lagarde sur le N\u00e9",
    "sg:orig_category":"Non-Classified Establishments",
    "sg:phone":"+33 5 45 78 72 56",
    "sg:province":"Poitou-Charentes",
    "wof:name":"Transports Bernard Chauvin S.a.",
    "wof:placetype":"venue"
},
  "geometry": {"coordinates":[-0.21097,45.508732],"type":"Point"}
}