{
  "type": "Feature",
  "properties": {
    "iso:country":"FR",
    "sg:address":"13, Rue des Bouleaux, 88120 Saint Am\u00e9",
    "sg:orig_category":"Non-Classified Establishments",
    "sg:phone":"+33 3 29 61 20 84",
    "sg:province":"Lorraine",
    "wof:name":"Fran\u00e7ois Graniterie S.a.r.l.",
    "wof:placetype":"venue"
},
  "geometry": {"coordinates":[6.652149,48.01915],"type":"Point"}
}