{
  "type": "Feature",
  "properties": {
    "addr:full":"Rue Ambroise Par\u00e9 - TP Lippmann - ZI La Guernerie Bois Grenier Nord Pas-de-Calais 59280",
    "addr:postcode":"59280",
    "addr:street":"Rue Ambroise Pare\u0301;Lippmann Zi La Guernerie Bois Grenier Nord",
    "iso:country":"FR",
    "sg:address":"Rue Ambroise Par\u00e9 - TP Lippmann - ZI La Guernerie",
    "sg:city":"Bois Grenier",
    "sg:orig_category":"Unclassifiable Establishments",
    "sg:phone":"+33 3 20 35 25 34",
    "sg:postcode":"59280",
    "sg:province":"Nord Pas-de-Calais",
    "wof:name":"S.2c. S.a.r.l.",
    "wof:placetype":"venue"
},
  "geometry": {"coordinates":[2.881701,50.686623],"type":"Point"}
}