{
  "type": "Feature",
  "properties": {
    "addr:full":"15, Rue Jean Rostand - ZI des Clergous, 81600 Gaillac Midi Pyr\u00e9n\u00e9es",
    "addr:housenumber":"15",
    "addr:postcode":"81600",
    "addr:street":"Rue Jean Rostand Zi Des Clergous",
    "iso:country":"FR",
    "sg:address":"15, Rue Jean Rostand - ZI des Clergous, 81600 Gaillac",
    "sg:orig_category":"Non-Classified Establishments",
    "sg:phone":"+33 5 63 57 17 78",
    "sg:province":"Midi Pyr\u00e9n\u00e9es",
    "wof:name":"Manufacture De Confection De Gaillac S.a.r.l.",
    "wof:placetype":"venue"
},
  "geometry": {"coordinates":[1.94877,43.843327],"type":"Point"}
}