{
  "type": "Feature",
  "properties": {
    "iso:country":"FR",
    "sg:address":"84, Rue Isa\u00efe Sellier, 80130 Friville Escarbotin",
    "sg:orig_category":"Unclassifiable Establishments",
    "sg:phone":"+33 3 22 30 05 13",
    "sg:province":"Picardie",
    "wof:name":"Grandsire S.a.",
    "wof:placetype":"venue"
},
  "geometry": {"coordinates":[1.55762,50.092628],"type":"Point"}
}