{
  "type": "Feature",
  "properties": {
    "addr:full":"34, Rue Casimir P\u00e9rier, 69297 Lyon C\u00e9dex 2 Rhone-Alpes",
    "addr:housenumber":"34;2",
    "addr:postcode":"69297",
    "addr:street":"Rue Casimir Pe\u0301Rier;Ce\u0301Dex",
    "iso:country":"FR",
    "sg:address":"34, Rue Casimir P\u00e9rier, 69297 Lyon C\u00e9dex 2",
    "sg:orig_category":"Non-Classified Establishments",
    "sg:phone":"+33 4 78 42 44 25",
    "sg:province":"Rhone-Alpes",
    "wof:name":"Cl\u00e9dor La Provence S.a.",
    "wof:placetype":"venue"
},
  "geometry": {"coordinates":[4.82645,45.74638],"type":"Point"}
}