{
  "type": "Feature",
  "properties": {
    "addr:full":"B.P. 1 Villeneuve de Marsan C\u00e9dex^^Les Tablettes 40190 Villeneuve de Marsan Aquitaine 40190",
    "addr:postcode":"40190;40190",
    "addr:street":"B.P. 1;Tablettes",
    "iso:country":"FR",
    "sg:address":"B.P. 1",
    "sg:city":"Villeneuve de Marsan C\u00e9dex^^Les Tablettes 40190 Villeneuve de Marsan",
    "sg:orig_category":"Non-Classified Establishments",
    "sg:phone":"+33 5 58 45 22 12",
    "sg:postcode":"40190",
    "sg:province":"Aquitaine",
    "wof:name":"R\u00e9gert Et Compagnie S.a.",
    "wof:placetype":"venue"
},
  "geometry": {"coordinates":[-0.325716,43.8876],"type":"Point"}
}