{
  "type": "Feature",
  "properties": {
    "addr:full":"B.P. 3033, 10012 Troyes C\u00e9dex^^27, Rue Roger Salengro, 10150 Pont Sainte Marie Champagne",
    "addr:postcode":"10012;10150",
    "addr:street":"B.P. 3033;Rue Roger Salengro",
    "iso:country":"FR",
    "sg:address":"B.P. 3033, 10012 Troyes C\u00e9dex^^27, Rue Roger Salengro, 10150 Pont Sainte Marie",
    "sg:orig_category":"Non-Classified Establishments",
    "sg:phone":"+33 3 25 78 22 44",
    "sg:province":"Champagne",
    "wof:name":"S.a.b. S.a. - Soci\u00e9t\u00e9 Auboise De Bureautique",
    "wof:placetype":"venue"
},
  "geometry": {"coordinates":[4.09298,48.317806],"type":"Point"}
}