{
  "type": "Feature",
  "properties": {
    "iso:country":"FR",
    "sg:address":"332 rue de la Lys 59250 Halluin",
    "sg:orig_category":"Non-Classified Establishments",
    "sg:phone":"+33 3 20 11 58 88",
    "sg:province":"Nord Pas-de-Calais",
    "wof:name":"S.f.l. Sa",
    "wof:placetype":"venue"
},
  "geometry": {"coordinates":[3.11203,50.78418],"type":"Point"}
}