{
  "type": "Feature",
  "properties": {
    "iso:country":"FR",
    "sg:address":"3, Rue A. Marsaud, 87160 Saint Sulpice les Feuilles",
    "sg:orig_category":"Non-Classified Establishments",
    "sg:phone":"+33 5 55 76 28 63",
    "sg:postcode":"87160",
    "sg:province":"Limousin",
    "wof:name":"Conserverie P.pallard",
    "wof:placetype":"venue"
},
  "geometry": {"coordinates":[1.371821,46.266094],"type":"Point"}
}