{
  "type": "Feature",
  "properties": {
    "addr:full":"154 Rue De Vaugirard Paris Ile de France 75015",
    "addr:housenumber":"154",
    "addr:postcode":"75015",
    "addr:street":"Rue De Vaugirard",
    "iso:country":"FR",
    "sg:address":"154 Rue De Vaugirard",
    "sg:city":"Paris",
    "sg:classifiers":[
        {
            "category":"Banks & Credit Unions",
            "subcategory":"Financial Services",
            "type":"Services"
        }
    ],
    "sg:phone":"+33 1 46 14 76 86",
    "sg:postcode":"75015",
    "sg:province":"Ile de France",
    "sg:tags":[
        "banking",
        "finance",
        "insurance"
    ],
    "wof:name":"Ge Capital Equipement Finance",
    "wof:placetype":"venue"
},
  "geometry": {"coordinates":[2.31415,48.843533],"type":"Point"}
}