{
  "type": "Feature",
  "properties": {
    "iso:country":"FR",
    "sg:address":"B.P. 15, 68960 Oberdorf^^20, Rue Principale, 68960 Oberdorf",
    "sg:city":"Oberdorf",
    "sg:orig_category":"Non-Classified Establishments",
    "sg:phone":"+33 3 89 07 98 93",
    "sg:postcode":"68960",
    "sg:province":"Alsace",
    "wof:name":"Rauscher France S.a.r.l.",
    "wof:placetype":"venue"
},
  "geometry": {"coordinates":[7.30068,47.563545],"type":"Point"}
}