{
  "type": "Feature",
  "properties": {
    "addr:full":"11, Cours Gambetta, 13100 Aix en Provence Nord Pas-de-Calais",
    "addr:housenumber":"11",
    "addr:postcode":"13100",
    "addr:street":"Cours Gambetta;En Provence Nord",
    "iso:country":"FR",
    "sg:address":"11, Cours Gambetta, 13100 Aix en Provence",
    "sg:orig_category":"Unclassifiable Establishments",
    "sg:phone":"+33 4 42 21 71 20",
    "sg:province":"Nord Pas-de-Calais",
    "wof:name":"Ucabail",
    "wof:placetype":"venue"
},
  "geometry": {"coordinates":[5.454417,43.524788],"type":"Point"}
}