{
  "type": "Feature",
  "properties": {
    "iso:country":"FR",
    "sg:address":"5 rue Jean Perrin 66000 Perpignan",
    "sg:classifiers":[
        {
            "category":"Recreation",
            "subcategory":"Water Park",
            "type":"Entertainment"
        }
    ],
    "sg:phone":"+33 4 68 61 40 11",
    "sg:province":"Languedoc-Roussillon",
    "sg:tags":[
        "humidifiers",
        "treatment",
        "air"
    ],
    "wof:name":"Tecnofil Industries Sa",
    "wof:placetype":"venue"
},
  "geometry": {"coordinates":[2.888169,42.733879],"type":"Point"}
}