{
  "type": "Feature",
  "properties": {
    "addr:full":"3307, Av. de Prades, 66000 Perpignan Languedoc-Roussillon",
    "addr:housenumber":"3307",
    "addr:postcode":"66000",
    "addr:street":"Av. De Prades",
    "iso:country":"FR",
    "sg:address":"3307, Av. de Prades, 66000 Perpignan",
    "sg:orig_category":"Unclassifiable Establishments",
    "sg:phone":"+33 4 68 56 75 02",
    "sg:province":"Languedoc-Roussillon",
    "wof:name":"Alliance Sant\u00e9 S.a.s.",
    "wof:placetype":"venue"
},
  "geometry": {"coordinates":[2.82877,42.688938],"type":"Point"}
}