{
  "type": "Feature",
  "properties": {
    "addr:full":"Domaine de la Truy\u00e8re 23230 LA CELLE SOUS GOUZON Limousin 23230",
    "addr:housenumber":"23230",
    "addr:postcode":"23230",
    "iso:country":"FR",
    "sg:address":"Domaine de la Truy\u00e8re 23230 LA CELLE SOUS GOUZON",
    "sg:classifiers":[
        {
            "category":"Food & Beverages",
            "subcategory":"Meat & Fish",
            "type":"Retail Goods"
        }
    ],
    "sg:phone":"+33 5 55 62 20 62",
    "sg:postcode":"23230",
    "sg:province":"Limousin",
    "sg:tags":[
        "sausage"
    ],
    "wof:name":"Ets Champeval S.a.e.",
    "wof:placetype":"venue"
},
  "geometry": {"coordinates":[2.185872,46.162186],"type":"Point"}
}