{
  "type": "Feature",
  "properties": {
    "iso:country":"FR",
    "sg:address":"B.P. 28, 45700 Villemandeur C\u00e9dex^^9, Rue Pierre Nobel, 45700 Villemandeur",
    "sg:city":"Villemandeur",
    "sg:orig_category":"Non-Classified Establishments",
    "sg:phone":"+33 2 38 93 20 90",
    "sg:postcode":"45700",
    "sg:province":"Centre",
    "wof:name":"Dactyl Buro Du Centre S.a.",
    "wof:placetype":"venue"
},
  "geometry": {"coordinates":[2.765315,47.896927],"type":"Point"}
}