{
  "type": "Feature",
  "properties": {
    "iso:country":"FR",
    "sg:address":"54 rue Moli\u00e8re 81100 Castres",
    "sg:classifiers":[
        {
            "category":"Professional",
            "type":"Services"
        }
    ],
    "sg:phone":"+33 5 63 62 14 14",
    "sg:province":"Midi Pyr\u00e9n\u00e9es",
    "sg:tags":[
        "transport"
    ],
    "wof:name":"Transeuro Sarl",
    "wof:placetype":"venue"
},
  "geometry": {"coordinates":[2.251777,43.59388],"type":"Point"}
}