{
  "type": "Feature",
  "properties": {
    "addr:full":"16, Rue Andr\u00e9 Amp\u00e8re - Parc d'Activit\u00e9 de la M\u00e9nardi\u00e8re, 37540 Saint Cyr sur Loire Saint-Cyr-sur-Loire Centre 37540",
    "addr:housenumber":"16",
    "addr:postcode":"37540;37540",
    "addr:street":"Rue Andre\u0301 Ampe\u0300Re Parc D'Activite \u0301 De La Me\u0301Nardie\u0300Re;Cyr",
    "iso:country":"FR",
    "sg:address":"16, Rue Andr\u00e9 Amp\u00e8re - Parc d'Activit\u00e9 de la M\u00e9nardi\u00e8re, 37540 Saint Cyr sur Loire",
    "sg:city":"Saint-Cyr-sur-Loire",
    "sg:orig_category":"Unclassifiable Establishments",
    "sg:phone":"+33 2 47 40 47 00",
    "sg:postcode":"37540",
    "sg:province":"Centre",
    "wof:name":"Materlignes S.a.",
    "wof:placetype":"venue"
},
  "geometry": {"coordinates":[0.664188,47.419899],"type":"Point"}
}