{
  "type": "Feature",
  "properties": {
    "addr:full":"B.P. 80305, 60723 Pont Sainte Maxence C\u00e9dex^^24, Rue d'Halatte, 60700 Pont Sainte Maxence Picardie",
    "addr:postcode":"60723;60700",
    "addr:street":"Rue D'Halatte",
    "iso:country":"FR",
    "sg:address":"B.P. 80305, 60723 Pont Sainte Maxence C\u00e9dex^^24, Rue d'Halatte, 60700 Pont Sainte Maxence",
    "sg:orig_category":"Non-Classified Establishments",
    "sg:phone":"+33 3 44 72 21 46",
    "sg:province":"Picardie",
    "wof:name":"Votat S.a.",
    "wof:placetype":"venue"
},
  "geometry": {"coordinates":[2.605964,49.295685],"type":"Point"}
}