{
  "type": "Feature",
  "properties": {
    "addr:full":"578 Avenue Charles De Gaulle 42153 Riorges Rhone-Alpes 42153",
    "addr:housenumber":"578",
    "addr:postcode":"42153;42153",
    "addr:street":"Avenue Charles De Gaulle;Rhone-Alpes",
    "iso:country":"FR",
    "sg:address":"578 Avenue Charles De Gaulle 42153 Riorges",
    "sg:classifiers":[
        {
            "category":"Shopping",
            "subcategory":"Clothing, Apparel, & Fashions",
            "type":"Retail Goods"
        }
    ],
    "sg:phone":"+33 4 77 68 45 11",
    "sg:postcode":"42153",
    "sg:province":"Rhone-Alpes",
    "sg:tags":[
        "textile",
        "clothing",
        "clothes"
    ],
    "wof:name":"Ipe Confection",
    "wof:placetype":"venue"
},
  "geometry": {"coordinates":[4.063583,46.055382],"type":"Point"}
}