{
  "type": "Feature",
  "properties": {
    "addr:full":"10 Rue Volney, 75002 Paris, Dept 75 Ile de France 75002",
    "addr:housenumber":"10;75",
    "addr:postcode":"75002;75002",
    "addr:street":"Rue Volney;Ile De France",
    "iso:country":"FR",
    "sg:address":"10 Rue Volney, 75002 Paris, Dept 75",
    "sg:classifiers":[
        {
            "category":"Banks & Credit Unions",
            "subcategory":"Bank",
            "type":"Services"
        }
    ],
    "sg:postcode":"75002",
    "sg:province":"Ile de France",
    "wof:name":"Via Bail",
    "wof:placetype":"venue"
},
  "geometry": {"coordinates":[2.330131,48.8694],"type":"Point"}
}