{
  "type": "Feature",
  "properties": {
    "iso:country":"FR",
    "sg:address":"2 Rue Archim\u00e8de 10600 La Chapelle St Luc",
    "sg:classifiers":[
        {
            "category":"Shopping",
            "subcategory":"Computers & Home Electronics",
            "type":"Retail Goods"
        }
    ],
    "sg:phone":"+33 3 25 78 35 03",
    "sg:postcode":"10600",
    "sg:province":"Champagne",
    "sg:tags":[
        "equipment",
        "electrical",
        "component",
        "electric",
        "electronic"
    ],
    "wof:name":"Prog-elec Sarl",
    "wof:placetype":"venue"
},
  "geometry": {"coordinates":[4.04113,48.317238],"type":"Point"}
}