{
  "type": "Feature",
  "properties": {
    "iso:country":"FR",
    "sg:address":"Grande Rue Basse",
    "sg:city":"Tanlay",
    "sg:orig_category":"Non-Classified Establishments",
    "sg:phone":"+33 3 86 75 89 89",
    "sg:postcode":"89430",
    "sg:province":"Bourgogne",
    "wof:name":"Delprat S.a.",
    "wof:placetype":"venue"
},
  "geometry": {"coordinates":[4.082309,47.849026],"type":"Point"}
}