{
  "type": "Feature",
  "properties": {
    "addr:full":"4, Place des Allobroges - Le Cristal , 74300 Cluses Rhone-Alpes",
    "addr:housenumber":"4",
    "addr:postcode":"74300",
    "addr:street":"Place Des Allobroges Le Cristal",
    "iso:country":"FR",
    "sg:address":"4, Place des Allobroges - Le Cristal , 74300 Cluses",
    "sg:orig_category":"Non-Classified Establishments",
    "sg:phone":"+33 4 50 98 82 06",
    "sg:province":"Rhone-Alpes",
    "wof:name":"Savoies Audit Gestion S.a.",
    "wof:placetype":"venue"
},
  "geometry": {"coordinates":[6.580518,46.05748],"type":"Point"}
}