{
  "type": "Feature",
  "properties": {
    "iso:country":"FR",
    "sg:address":"24 Rue Dauphine 75006 Paris",
    "sg:classifiers":[
        {
            "category":"Shopping",
            "subcategory":"Hobbies, Toys, & Games",
            "type":"Retail Goods"
        }
    ],
    "sg:phone":"+33 1 43 26 56 21",
    "sg:postcode":"75006",
    "sg:province":"Ile de France",
    "sg:tags":[
        "product",
        "miscellaneous",
        "entertainment"
    ],
    "wof:name":"Art Cadre Dauphine Sarl",
    "wof:placetype":"venue"
},
  "geometry": {"coordinates":[2.3394,48.854992],"type":"Point"}
}