{
  "type": "Feature",
  "properties": {
    "addr:full":"Avenue Du Gros Chene Parc D Acti Des Bellevues 95610 Eragny Sur Oise Ile de France 95610",
    "addr:postcode":"95610;95610",
    "addr:street":"Avenue Du Gros Chene Parc D Acti Des Bellevues",
    "iso:country":"FR",
    "sg:address":"Avenue Du Gros Chene Parc D Acti Des Bellevues 95610 Eragny Sur Oise",
    "sg:classifiers":[
        {
            "category":"Government",
            "subcategory":"Department Of Motor Vehicles",
            "type":"Public Place"
        }
    ],
    "sg:phone":"+33 1 34 33 63 63",
    "sg:postcode":"95610",
    "sg:province":"Ile de France",
    "sg:tags":[
        "equipment",
        "industrial",
        "transport",
        "motor-cars"
    ],
    "wof:name":"Renault Pieces Et Accessoires",
    "wof:placetype":"venue"
},
  "geometry": {"coordinates":[2.107264,49.027889],"type":"Point"}
}