{
  "type": "Feature",
  "properties": {
    "iso:country":"FR",
    "sg:address":"4 rue du G\u00e9n\u00e9ral Leclerc; Benfeld; 67230",
    "sg:city":"Benfeld",
    "sg:classifiers":[
        {
            "category":"Banks & Credit Unions",
            "subcategory":"Bank",
            "type":"Services"
        }
    ],
    "sg:phone":"+33 3 88 58 71 88",
    "sg:postcode":"67230",
    "sg:province":"Alsace",
    "wof:name":"Cr\u00e9dit Industriel D'alsace, Et De Lorraine Sa",
    "wof:placetype":"venue"
},
  "geometry": {"coordinates":[7.592055,48.371105],"type":"Point"}
}