{
  "type": "Feature",
  "properties": {
    "addr:full":"127 rue de Flandres; Paris; 75019 Ile de France 75019",
    "addr:housenumber":"127",
    "addr:postcode":"75019;75019",
    "addr:street":"Rue De Flandres Paris;France",
    "iso:country":"FR",
    "sg:address":"127 rue de Flandres; Paris; 75019",
    "sg:classifiers":[
        {
            "category":"Banks & Credit Unions",
            "subcategory":"Bank",
            "type":"Services"
        }
    ],
    "sg:phone":"+33 1 40 36 58 00",
    "sg:postcode":"75019",
    "sg:province":"Ile de France",
    "wof:name":"Cr\u00e9dit Commercial De France",
    "wof:placetype":"venue"
},
  "geometry": {"coordinates":[2.378036,48.891975],"type":"Point"}
}