{
  "type": "Feature",
  "properties": {
    "addr:full":"2, Rue de la Garboti\u00e8re - Villebarou , 41000 Blois Villebarou Centre 41000",
    "addr:housenumber":"2;villebarou",
    "addr:postcode":"41000;41000",
    "addr:street":"Rue De La Garbotie\u0300Re",
    "iso:country":"FR",
    "sg:address":"2, Rue de la Garboti\u00e8re - Villebarou , 41000 Blois",
    "sg:city":"Villebarou",
    "sg:orig_category":"Unclassifiable Establishments",
    "sg:phone":"+33 2 54 44 47 00",
    "sg:postcode":"41000",
    "sg:province":"Centre",
    "wof:name":"Cadbury France S.a.",
    "wof:placetype":"venue"
},
  "geometry": {"coordinates":[1.331433,47.586849],"type":"Point"}
}