{
  "type": "Feature",
  "properties": {
    "iso:country":"FR",
    "sg:address":"2, Rue Missak Manouchian, 38130 Echirolles",
    "sg:orig_category":"Non-Classified Establishments",
    "sg:phone":"+33 4 76 09 07 35",
    "sg:province":"Rhone-Alpes",
    "wof:name":"P\u00e9rona S.a.",
    "wof:placetype":"venue"
},
  "geometry": {"coordinates":[5.711367,45.144161],"type":"Point"}
}