{
  "type": "Feature",
  "properties": {
    "iso:country":"FR",
    "sg:address":"6, Rue Mar\u00e9chal Foch, 77400 Thorigny sur Marne",
    "sg:orig_category":"Non-Classified Establishments",
    "sg:phone":"+33 1 60 07 13 79",
    "sg:province":"Ile de France",
    "wof:name":"S.i.p.m.e. S.a.r.l. - Soci\u00e9t\u00e9 D'installation De Protection M\u00e9canique Et Electronique",
    "wof:placetype":"venue"
},
  "geometry": {"coordinates":[2.717328,48.884914],"type":"Point"}
}