{
  "type": "Feature",
  "properties": {
    "addr:full":"79, Av. de Saint Aisaille, 74200 Thonon les Bains Rhone-Alpes",
    "addr:postcode":"74200",
    "addr:street":"79 Av. De Saint Aisaille",
    "iso:country":"FR",
    "sg:address":"79, Av. de Saint Aisaille, 74200 Thonon les Bains",
    "sg:orig_category":"Non-Classified Establishments",
    "sg:phone":"+33 4 50 26 35 35",
    "sg:province":"Rhone-Alpes",
    "wof:name":"S.t.a.t. S.a.r.l. - Soci\u00e9t\u00e9 De Transports Agglom\u00e9ration Thononaise",
    "wof:placetype":"venue"
},
  "geometry": {"coordinates":[6.501934,46.387066],"type":"Point"}
}