{
  "type": "Feature",
  "properties": {
    "iso:country":"FR",
    "sg:address":"445 Bd Gambetta 59200 Tourcoing",
    "sg:classifiers":[
        {
            "category":"Banks & Credit Unions",
            "subcategory":"Financial Services",
            "type":"Services"
        }
    ],
    "sg:phone":"+33 3 20 24 97 87",
    "sg:postcode":"59200",
    "sg:province":"Nord Pas-de-Calais",
    "sg:tags":[
        "banking",
        "insurance",
        "institution",
        "finance"
    ],
    "wof:name":"Fonds D'investissement Rtvl Nord Creation Sa",
    "wof:placetype":"venue"
},
  "geometry": {"coordinates":[3.16043,50.704361],"type":"Point"}
}