{
  "type": "Feature",
  "properties": {
    "iso:country":"FR",
    "sg:address":"12 Rue Du 8 33200 Bordeaux Caud\u00e9ran",
    "sg:city":"Bordeaux",
    "sg:classifiers":[
        {
            "category":"Manufacturing",
            "subcategory":"Metals",
            "type":"Manufacturing & Wholesale Goods"
        }
    ],
    "sg:phone":"+33 5 56 47 44 51",
    "sg:postcode":"33200",
    "sg:province":"Aquitaine",
    "sg:tags":[
        "-",
        "machine",
        "equipment",
        "engineering",
        "machinery",
        "mechanical"
    ],
    "wof:name":"Kennametal France",
    "wof:placetype":"venue"
},
  "geometry": {"coordinates":[-0.61632,44.854031],"type":"Point"}
}