{
  "type": "Feature",
  "properties": {
    "iso:country":"FR",
    "sg:address":"8, All\u00e9e Didier Daurat - ZAC de Maignon, 64600 Anglet",
    "sg:city":"Anglet",
    "sg:orig_category":"Non-Classified Establishments",
    "sg:phone":"+33 5 59 31 49 48",
    "sg:postcode":"64600",
    "sg:province":"Aquitaine",
    "wof:name":"E.t.d.e. S.a. - Entreprise De Transport Et Distribution D'energies",
    "wof:placetype":"venue"
},
  "geometry": {"coordinates":[-1.514707,43.481705],"type":"Point"}
}