{
  "type": "Feature",
  "properties": {
    "addr:full":"47 rue du Pr\u00e9 Didier 38520 ST Egreve Rhone-Alpes",
    "addr:housenumber":"47",
    "addr:postcode":"38520",
    "addr:street":"Rue Du Pre\u0301 Didier",
    "iso:country":"FR",
    "sg:address":"47 rue du Pr\u00e9 Didier 38520 ST Egreve",
    "sg:classifiers":[
        {
            "category":"Professional",
            "type":"Services"
        }
    ],
    "sg:phone":"+33 4 76 75 51 36",
    "sg:province":"Rhone-Alpes",
    "sg:tags":[
        "transport"
    ],
    "wof:name":"Transports Coing Andr\u00e9 Sarl",
    "wof:placetype":"venue"
},
  "geometry": {"coordinates":[6.030423,45.054955],"type":"Point"}
}