{
  "type": "Feature",
  "properties": {
    "iso:country":"FR",
    "sg:address":"Rue Blaise Pascal - Zone de Chalembert",
    "sg:city":"Jaunay Clan",
    "sg:orig_category":"Non-Classified Establishments",
    "sg:phone":"+33 5 49 38 59 59",
    "sg:postcode":"86130",
    "sg:province":"Poitou-Charentes",
    "wof:name":"Alliane Sant\u00e9 S.a.s.",
    "wof:placetype":"venue"
},
  "geometry": {"coordinates":[0.36604,46.681557],"type":"Point"}
}