{
  "type": "Feature",
  "properties": {
    "addr:full":"1 chemin Weingarten 67140 Mittelbergheim Mittelbergheim Alsace 67140",
    "addr:housenumber":"1",
    "addr:postcode":"67140;67140",
    "addr:street":"Chemin Weingarten;Mittelbergheim",
    "iso:country":"FR",
    "sg:address":"1 chemin Weingarten 67140 Mittelbergheim",
    "sg:city":"Mittelbergheim",
    "sg:orig_category":"Furniture, General",
    "sg:phone":"+33 3 88 58 59 60",
    "sg:postcode":"67140",
    "sg:province":"Alsace",
    "wof:name":"Ebenisterie Seltz Et Fils S.a.",
    "wof:placetype":"venue"
},
  "geometry": {"coordinates":[7.439092,48.393234],"type":"Point"}
}