{
  "type": "Feature",
  "properties": {
    "iso:country":"FR",
    "sg:address":"Zone Industrielle",
    "sg:city":"Villers Saint Paul",
    "sg:orig_category":"Unclassifiable Establishments",
    "sg:phone":"+33 3 44 29 63 00",
    "sg:postcode":"60870",
    "sg:province":"Picardie",
    "wof:name":"Lyondell S.a.",
    "wof:placetype":"venue"
},
  "geometry": {"coordinates":[2.487537,49.288544],"type":"Point"}
}