{
  "type": "Feature",
  "properties": {
    "iso:country":"FR",
    "sg:address":"4 rue Esprit des Lois; Bordeaux; 33005",
    "sg:city":"Bordeaux",
    "sg:classifiers":[
        {
            "category":"Banks & Credit Unions",
            "subcategory":"Bank",
            "type":"Services"
        }
    ],
    "sg:phone":"+33 5 56 01 91 00",
    "sg:postcode":"33100",
    "sg:province":"Aquitaine",
    "wof:name":"Barclays Bank Plc",
    "wof:placetype":"venue"
},
  "geometry": {"coordinates":[-0.571405,44.843067],"type":"Point"}
}