{
  "type": "Feature",
  "properties": {
    "iso:country":"FR",
    "sg:address":"15 Rue De Vanves 92100 Boulogne Billancourt",
    "sg:classifiers":[
        {
            "category":"Professional",
            "subcategory":"Advertising",
            "type":"Services"
        }
    ],
    "sg:phone":"+33 1 47 61 87 10",
    "sg:postcode":"92100",
    "sg:province":"Ile de France",
    "sg:tags":[
        "marketing",
        "medium",
        "communication"
    ],
    "wof:name":"Telog Sa",
    "wof:placetype":"venue"
},
  "geometry": {"coordinates":[2.252737,48.833935],"type":"Point"}
}