{
  "type": "Feature",
  "properties": {
    "addr:full":"B.P. 89, 80534 Friville Escarbotin C\u00e9dex^^18, Rue du Mar\u00e9chal Foch, 80130 Friville Escarbotin Picardie 80130",
    "addr:postcode":"80534;80130;80130",
    "addr:street":"B.P. 89;Rue Du Mare\u0301Chal Foch",
    "iso:country":"FR",
    "sg:address":"B.P. 89, 80534 Friville Escarbotin C\u00e9dex^^18, Rue du Mar\u00e9chal Foch, 80130 Friville Escarbotin",
    "sg:orig_category":"Non-Classified Establishments",
    "sg:phone":"+33 3 22 60 22 70",
    "sg:postcode":"80130",
    "sg:province":"Picardie",
    "wof:name":"Delabie S.a.",
    "wof:placetype":"venue"
},
  "geometry": {"coordinates":[1.542147,50.080269],"type":"Point"}
}