{
  "type": "Feature",
  "properties": {
    "iso:country":"FR",
    "sg:address":"Le Haut Coin 44140 Aigrefeuille Sur Maine",
    "sg:classifiers":[
        {
            "category":"Autos & Motor Vehicles",
            "subcategory":"Automobile Sales",
            "type":"Retail Goods"
        }
    ],
    "sg:phone":"+33 2 40 06 61 23",
    "sg:postcode":"44140",
    "sg:province":"Pays de Loire",
    "sg:tags":[
        "equipment",
        "motor-cars",
        "transport"
    ],
    "wof:name":"Carrosserie Leroy Sarl",
    "wof:placetype":"venue"
},
  "geometry": {"coordinates":[-1.415674,47.082657],"type":"Point"}
}