{
  "type": "Feature",
  "properties": {
    "addr:full":"52 Bd 1er Chasseurs; Alen\u00e7on; 61000 Alen\u00e7on Basse Normandie 61000",
    "addr:housenumber":"52",
    "addr:postcode":"61000;61000",
    "addr:street":"Bd 1Er Chasseurs",
    "iso:country":"FR",
    "sg:address":"52 Bd 1er Chasseurs; Alen\u00e7on; 61000",
    "sg:city":"Alen\u00e7on",
    "sg:classifiers":[
        {
            "category":"Banks & Credit Unions",
            "subcategory":"Bank",
            "type":"Services"
        }
    ],
    "sg:phone":"+33 3333313030",
    "sg:postcode":"61000",
    "sg:province":"Basse Normandie",
    "wof:name":"Cr\u00e9dit Agricole Mutuel, De L'orne",
    "wof:placetype":"venue"
},
  "geometry": {"coordinates":[0.08355,48.438904],"type":"Point"}
}