{
  "type": "Feature",
  "properties": {
    "iso:country":"FR",
    "sg:address":"42, Bd Emile G\u00e9nevoix, 93230 Romainville",
    "sg:orig_category":"Non-Classified Establishments",
    "sg:phone":"+33 1 48 44 28 15",
    "sg:province":"Ile de France",
    "wof:name":"Europe Hydro S.a.",
    "wof:placetype":"venue"
},
  "geometry": {"coordinates":[2.43535,48.881706],"type":"Point"}
}