{
  "type": "Feature",
  "properties": {
    "addr:full":"9, Rue Jean Dollfus, 90000 Belfort Franche Comt\u00e9",
    "addr:housenumber":"9",
    "addr:postcode":"90000",
    "addr:street":"Rue Jean Dollfus;Franche Comte\u0301",
    "iso:country":"FR",
    "sg:address":"9, Rue Jean Dollfus, 90000 Belfort",
    "sg:orig_category":"Unclassifiable Establishments",
    "sg:phone":"+33 3 84 28 12 27",
    "sg:province":"Franche Comt\u00e9",
    "wof:name":"B\u00e2tiloisirs S.a.",
    "wof:placetype":"venue"
},
  "geometry": {"coordinates":[6.84248,47.637791],"type":"Point"}
}