{
  "type": "Feature",
  "properties": {
    "iso:country":"FR",
    "sg:address":"46 Rue Nationale 25220 Roche Lez Beaupre",
    "sg:classifiers":[
        {
            "category":"Manufacturing",
            "subcategory":"Printing",
            "type":"Manufacturing & Wholesale Goods"
        }
    ],
    "sg:phone":"+33 3 81 57 03 16",
    "sg:province":"Franche Comt\u00e9",
    "sg:tags":[
        "publishing"
    ],
    "wof:name":"Sprint Faconnage",
    "wof:placetype":"venue"
},
  "geometry": {"coordinates":[6.11691,47.276928],"type":"Point"}
}