{
  "type": "Feature",
  "properties": {
    "iso:country":"FR",
    "sg:address":"20, Rue Royale, 75008 Paris",
    "sg:orig_category":"Unclassifiable Establishments",
    "sg:phone":"+33 1 42 61 29 84",
    "sg:province":"Ile de France",
    "wof:name":"Depreux France S.a.r.l.",
    "wof:placetype":"venue"
},
  "geometry": {"coordinates":[2.323619,48.868706],"type":"Point"}
}