{
  "type": "Feature",
  "properties": {
    "addr:full":"route d'Etampes 91410 St Cyr sous Dourdan Ile de France",
    "addr:postcode":"91410",
    "addr:street":"Route D'Etampes",
    "iso:country":"FR",
    "sg:address":"route d'Etampes 91410 St Cyr sous Dourdan",
    "sg:classifiers":[
        {
            "category":"Retail",
            "subcategory":"Event Space",
            "type":"Services"
        }
    ],
    "sg:phone":"+33 1 64 55 10 95",
    "sg:province":"Ile de France",
    "sg:tags":[
        "developing",
        "photo",
        "self-service",
        "booth",
        "passport",
        "automatic"
    ],
    "wof:name":"Ste Construction Electromecanique-scem S.a.r.l.",
    "wof:placetype":"venue"
},
  "geometry": {"coordinates":[2.01379,48.527512],"type":"Point"}
}