{
  "type": "Feature",
  "properties": {
    "iso:country":"FR",
    "sg:address":"2 All Du Verger 95700 Roissy En France",
    "sg:classifiers":[
        {
            "category":"Travel",
            "subcategory":"Hotels & Motels",
            "type":"Entertainment"
        }
    ],
    "sg:phone":"+33 1 34 29 33 33",
    "sg:postcode":"95700",
    "sg:province":"Ile de France",
    "sg:tags":[
        "hotels",
        "business",
        "restaurant"
    ],
    "wof:name":"Copthorne Hotel Roissy Sa",
    "wof:placetype":"venue"
},
  "geometry": {"coordinates":[2.517005,49.003883],"type":"Point"}
}