{
  "type": "Feature",
  "properties": {
    "iso:country":"FR",
    "sg:address":"39, Av. Jean Becker R\u00e9my, 27940 Aubevoye",
    "sg:orig_category":"Unclassifiable Establishments",
    "sg:phone":"+33 2 32 52 11 71",
    "sg:province":"Haute Normandie",
    "wof:name":"S.t.p.n. S.a.r.l. - Soci\u00e9t\u00e9 De Transformation De Papier Normande",
    "wof:placetype":"venue"
},
  "geometry": {"coordinates":[1.35993,49.173119],"type":"Point"}
}