{
  "type": "Feature",
  "properties": {
    "addr:full":"22, Rue Jeanne d'Arc, 60000 Beauvais Picardie",
    "addr:housenumber":"22",
    "addr:postcode":"60000",
    "addr:street":"Rue Jeanne D'Arc",
    "iso:country":"FR",
    "sg:address":"22, Rue Jeanne d'Arc, 60000 Beauvais",
    "sg:orig_category":"Unclassifiable Establishments",
    "sg:phone":"+33 3 44 45 06 45",
    "sg:province":"Picardie",
    "wof:name":"Beaudart D\u00e9m\u00e9co S.a.r.l.",
    "wof:placetype":"venue"
},
  "geometry": {"coordinates":[2.087872,49.432049],"type":"Point"}
}