{
  "type": "Feature",
  "properties": {
    "iso:country":"FR",
    "sg:address":"11, Rue Pierre Ma\u00eetre, 51100 Reims",
    "sg:orig_category":"Unclassifiable Establishments",
    "sg:phone":"+33 3 26 84 69 40",
    "sg:province":"Champagne",
    "wof:name":"Transport De Bagneux S.a.",
    "wof:placetype":"venue"
},
  "geometry": {"coordinates":[4.008761,49.262295],"type":"Point"}
}