{
  "type": "Feature",
  "properties": {
    "iso:country":"FR",
    "sg:address":"ZI de la Plaine de l'Ain",
    "sg:city":"Saint Vulbas",
    "sg:orig_category":"Unclassifiable Establishments",
    "sg:phone":"+33 4 74 46 21 00",
    "sg:postcode":"01150",
    "sg:province":"Rhone-Alpes",
    "wof:name":"Easydis S.a.",
    "wof:placetype":"venue"
},
  "geometry": {"coordinates":[5.391374,45.868443],"type":"Point"}
}