{
  "type": "Feature",
  "properties": {
    "addr:full":"21 rue de la R\u00e9publique; Loches; 37600 Loches Centre 37600",
    "addr:housenumber":"21",
    "addr:postcode":"37600;37600",
    "addr:street":"Rue De La Re\u0301Publique",
    "iso:country":"FR",
    "sg:address":"21 rue de la R\u00e9publique; Loches; 37600",
    "sg:city":"Loches",
    "sg:classifiers":[
        {
            "category":"Banks & Credit Unions",
            "subcategory":"Bank",
            "type":"Services"
        }
    ],
    "sg:phone":"+33 3347590626",
    "sg:postcode":"37600",
    "sg:province":"Centre",
    "wof:name":"Soci\u00e9t\u00e9 G\u00e9n\u00e9rale",
    "wof:placetype":"venue"
},
  "geometry": {"coordinates":[0.998185,47.129192],"type":"Point"}
}