{
  "type": "Feature",
  "properties": {
    "addr:full":"41, Av. de la Grande Arm\u00e9e, 75116 Paris \u00cele-de-France",
    "addr:postcode":"75116",
    "addr:street":"41 Av. De La Grande Arme\u0301E",
    "iso:country":"FR",
    "sg:address":"41, Av. de la Grande Arm\u00e9e, 75116 Paris",
    "sg:orig_category":"Non-Classified Establishments",
    "sg:phone":"+33 1 45 00 19 85",
    "sg:province":"\u00cele-de-France",
    "wof:name":"Eti S.a.",
    "wof:placetype":"venue"
},
  "geometry": {"coordinates":[2.288285,48.875511],"type":"Point"}
}