{
  "type": "Feature",
  "properties": {
    "iso:country":"FR",
    "sg:address":"8 rue Parmentier 60290 Rantigny",
    "sg:classifiers":[
        {
            "category":"Building & Trades",
            "subcategory":"Cleaning & Sanitation",
            "type":"Services"
        }
    ],
    "sg:phone":"+33 3 44 73 31 22",
    "sg:postcode":"60290",
    "sg:province":"Picardie",
    "sg:tags":[
        "pharmaceutical",
        "plant",
        "technical",
        "industry",
        "sterilizing",
        "chemical"
    ],
    "wof:name":"Griffith Micro Sciences Sa",
    "wof:placetype":"venue"
},
  "geometry": {"coordinates":[2.446561,49.32526],"type":"Point"}
}