{
  "type": "Feature",
  "properties": {
    "addr:full":"27, Rue Jean Mermoz, 74300 Cluses Rhone-Alpes 74300",
    "addr:housenumber":"27",
    "addr:postcode":"74300;74300",
    "addr:street":"Rue Jean Mermoz",
    "iso:country":"FR",
    "sg:address":"27, Rue Jean Mermoz, 74300 Cluses",
    "sg:orig_category":"Non-Classified Establishments",
    "sg:phone":"+33 4 50 98 25 20",
    "sg:postcode":"74300",
    "sg:province":"Rhone-Alpes",
    "wof:name":"Etablissement Baudeco S.a.r.l.",
    "wof:placetype":"venue"
},
  "geometry": {"coordinates":[6.563162,46.072151],"type":"Point"}
}