{
  "type": "Feature",
  "properties": {
    "addr:full":"Z I Artois Flandre 62138 Douvrin Nord Pas-de-Calais",
    "addr:postcode":"62138",
    "addr:street":"Z I Artois Flandre",
    "iso:country":"FR",
    "sg:address":"Z I Artois Flandre 62138 Douvrin",
    "sg:classifiers":[
        {
            "category":"Utilities",
            "subcategory":"Natural Gas",
            "type":"Services"
        }
    ],
    "sg:phone":"+33 3 21 79 49 90",
    "sg:province":"Nord Pas-de-Calais",
    "sg:tags":[
        "plant"
    ],
    "wof:name":"Lbcc Systemes Et Productique S.a.",
    "wof:placetype":"venue"
},
  "geometry": {"coordinates":[2.831475,50.508141],"type":"Point"}
}