{
  "type": "Feature",
  "properties": {
    "addr:full":"9 rue Bichat; Oyonnax; 01100 Rhone-Alpes 01100",
    "addr:housenumber":"9",
    "addr:postcode":"01100;01100",
    "addr:street":"Rue Bichat",
    "iso:country":"FR",
    "sg:address":"9 rue Bichat; Oyonnax; 01100",
    "sg:classifiers":[
        {
            "category":"Banks & Credit Unions",
            "subcategory":"Bank",
            "type":"Services"
        }
    ],
    "sg:phone":"+33 4 74 73 80 02",
    "sg:postcode":"01100",
    "sg:province":"Rhone-Alpes",
    "wof:name":"Banque Rh\u00f4ne-alpes",
    "wof:placetype":"venue"
},
  "geometry": {"coordinates":[5.65573,46.258259],"type":"Point"}
}