{
  "type": "Feature",
  "properties": {
    "iso:country":"FR",
    "sg:address":"1 Chemin Barat Neou 33114 Le Barp",
    "sg:city":"Le Barp",
    "sg:classifiers":[
        {
            "category":"Professional",
            "type":"Services"
        }
    ],
    "sg:phone":"+33 5 56 88 67 56",
    "sg:postcode":"33114",
    "sg:province":"Aquitaine",
    "sg:tags":[
        "transport",
        "road"
    ],
    "wof:name":"Vierge Christian",
    "wof:placetype":"venue"
},
  "geometry": {"coordinates":[-0.720099,44.56929],"type":"Point"}
}