{
  "type": "Feature",
  "properties": {
    "iso:country":"FR",
    "sg:address":"75, Chemin de Sainte Marthe, 13014 Marseille",
    "sg:orig_category":"Unclassifiable Establishments",
    "sg:phone":"+33 4 91 10 35 50",
    "sg:province":"Poitou-Charentes",
    "wof:name":"Pharmatel S.a.",
    "wof:placetype":"venue"
},
  "geometry": {"coordinates":[5.389234,43.322559],"type":"Point"}
}