{
  "type": "Feature",
  "properties": {
    "addr:full":"8 Descartes; Le Plessis; 92350 Ile de France 92350",
    "addr:housenumber":"8",
    "addr:postcode":"92350;92350",
    "addr:street":"Descartes Le Plessis;France",
    "iso:country":"FR",
    "sg:address":"8",
    "sg:city":"Descartes; Le Plessis; 92350",
    "sg:classifiers":[
        {
            "category":"Banks & Credit Unions",
            "subcategory":"Bank",
            "type":"Services"
        }
    ],
    "sg:phone":"+33 16302235",
    "sg:postcode":"92350",
    "sg:province":"Ile de France",
    "wof:name":"Banque Nationale De Paris",
    "wof:placetype":"venue"
},
  "geometry": {"coordinates":[-117.26155900000001,34.05238],"type":"Point"}
}