{
  "type": "Feature",
  "properties": {
    "addr:full":"B.P. 28, 59510 Hem^^279, Rue Jules Guesde, 59510 Hem Nord Pas-de-Calais 59510",
    "addr:postcode":"59510;59510;59510",
    "addr:street":"B.P. 28;Rue Jules Guesde",
    "iso:country":"FR",
    "sg:address":"B.P. 28, 59510 Hem^^279, Rue Jules Guesde, 59510 Hem",
    "sg:orig_category":"Non-Classified Establishments",
    "sg:phone":"+33 3 20 81 80 40",
    "sg:postcode":"59510",
    "sg:province":"Nord Pas-de-Calais",
    "wof:name":"Dendievel Eug\u00e8ne Et Fils Imprimerie S.a.",
    "wof:placetype":"venue"
},
  "geometry": {"coordinates":[3.184105,50.653839],"type":"Point"}
}