{
  "type": "Feature",
  "properties": {
    "addr:full":"Le Cherbois 87890 Jouac Limousin 87890",
    "addr:postcode":"87890;87890",
    "iso:country":"FR",
    "sg:address":"Le Cherbois 87890 Jouac",
    "sg:classifiers":[
        {
            "category":"Utilities",
            "type":"Services"
        }
    ],
    "sg:phone":"+33 5 55 68 21 09",
    "sg:postcode":"87890",
    "sg:province":"Limousin",
    "sg:tags":[
        "raw",
        "energy",
        "material"
    ],
    "wof:name":"Ste Des Mines De Jouac",
    "wof:placetype":"venue"
},
  "geometry": {"coordinates":[1.255655,46.32394],"type":"Point"}
}