{
  "type": "Feature",
  "properties": {
    "addr:full":"Rte Nationale Mazingarbe Nord Pas-de-Calais 62670",
    "addr:postcode":"62670",
    "addr:street":"Rte Nationale Mazingarbe Nord",
    "iso:country":"FR",
    "sg:address":"Rte Nationale",
    "sg:city":"Mazingarbe",
    "sg:orig_category":"Unclassifiable Establishments",
    "sg:phone":"+33 3 21 44 86 85",
    "sg:postcode":"62670",
    "sg:province":"Nord Pas-de-Calais",
    "wof:name":"Nord H\u00e9lio Service S.a.",
    "wof:placetype":"venue"
},
  "geometry": {"coordinates":[2.7474,50.472546],"type":"Point"}
}