{
  "type": "Feature",
  "properties": {
    "addr:full":"Biberacker N\u00b0 10 Colmar Alsace 68000",
    "addr:postcode":"68000",
    "addr:street":"Colmar",
    "iso:country":"FR",
    "sg:address":"Biberacker N\u00b0 10",
    "sg:city":"Colmar",
    "sg:orig_category":"Unclassifiable Establishments",
    "sg:phone":"+33 3 89 23 02 05",
    "sg:postcode":"68000",
    "sg:province":"Alsace",
    "wof:name":"Les Floralies E.a.r.l.",
    "wof:placetype":"venue"
},
  "geometry": {"coordinates":[7.363583,48.081985],"type":"Point"}
}