{
  "type": "Feature",
  "properties": {
    "iso:country":"FR",
    "sg:address":"79 cours Jean Jaur\u00e8s; Grenoble; 38000",
    "sg:classifiers":[
        {
            "category":"Banks & Credit Unions",
            "subcategory":"Bank",
            "type":"Services"
        }
    ],
    "sg:phone":"+33 3376463887",
    "sg:postcode":"38000",
    "sg:province":"Rhone-Alpes",
    "wof:name":"Sovac",
    "wof:placetype":"venue"
},
  "geometry": {"coordinates":[5.718281,45.184597],"type":"Point"}
}