{
  "type": "Feature",
  "properties": {
    "iso:country":"FR",
    "sg:address":"ZI de Gr\u00e2ces",
    "sg:city":"Guingamp",
    "sg:orig_category":"Unclassifiable Establishments",
    "sg:phone":"+33 2 96 40 63 80",
    "sg:postcode":"22200",
    "sg:province":"Bretagne",
    "wof:name":"Kdi Rou\u00ebnel S.a.s.",
    "wof:placetype":"venue"
},
  "geometry": {"coordinates":[-3.149486,48.562763],"type":"Point"}
}