{
  "type": "Feature",
  "properties": {
    "iso:country":"FR",
    "sg:address":"36 Av Philippe De Volvire 35490 Sens De Bretagne",
    "sg:city":"Chauvign\u00e9",
    "sg:classifiers":[
        {
            "category":"Professional",
            "type":"Services"
        }
    ],
    "sg:phone":"+33 2 99 39 53 53",
    "sg:postcode":"35490",
    "sg:province":"Bretagne",
    "sg:tags":[
        "transport",
        "road"
    ],
    "wof:name":"Ferron Amand Sarl Transport",
    "wof:placetype":"venue"
},
  "geometry": {"coordinates":[-1.531643,48.331982],"type":"Point"}
}