{
  "type": "Feature",
  "properties": {
    "addr:full":"984, Rte de la Vall\u00e9e, 69380 Ch\u00e2tillon Rhone-Alpes",
    "addr:housenumber":"984",
    "addr:postcode":"69380",
    "addr:street":"Rte De La Valle\u0301E",
    "iso:country":"FR",
    "sg:address":"984, Rte de la Vall\u00e9e, 69380 Ch\u00e2tillon",
    "sg:orig_category":"Unclassifiable Establishments",
    "sg:phone":"+33 4 78 47 99 44",
    "sg:province":"Rhone-Alpes",
    "wof:name":"Etablissements Neutragel S.a.",
    "wof:placetype":"venue"
},
  "geometry": {"coordinates":[4.641668,45.879021],"type":"Point"}
}