{
  "type": "Feature",
  "properties": {
    "addr:full":"rue Merigonde 81100 Castres Midi Pyr\u00e9n\u00e9es 81100",
    "addr:postcode":"81100;81100",
    "addr:street":"Rue Merigonde",
    "iso:country":"FR",
    "sg:address":"rue Merigonde 81100 Castres",
    "sg:classifiers":[
        {
            "category":"Government",
            "subcategory":"Post Office",
            "type":"Public Place"
        }
    ],
    "sg:phone":"+33 5 63 35 78 52",
    "sg:postcode":"81100",
    "sg:province":"Midi Pyr\u00e9n\u00e9es",
    "sg:tags":[
        "protective",
        "clothing",
        "special"
    ],
    "wof:name":"Bastie S.a.r.l.",
    "wof:placetype":"venue"
},
  "geometry": {"coordinates":[2.25311,43.602398],"type":"Point"}
}