{
  "type": "Feature",
  "properties": {
    "addr:full":"B.P. 54 V\u00e9zelise^^La Croisette 54330 V\u00e9zelise Lorraine 54330",
    "addr:postcode":"54330;54330",
    "addr:street":"B.P. 54 Ve\u0301Zelise^^La Croisette",
    "iso:country":"FR",
    "sg:address":"B.P. 54",
    "sg:city":"V\u00e9zelise^^La Croisette 54330 V\u00e9zelise",
    "sg:orig_category":"Compresseurs \u00e0 air comprim\u00e9 Graissage centralis\u00e9, Appareils de Graissage pneumatiques, Pistolets de ",
    "sg:phone":"+33 3 83 26 92 88",
    "sg:postcode":"54330",
    "sg:province":"Lorraine",
    "wof:name":"Sogit S.a.",
    "wof:placetype":"venue"
},
  "geometry": {"coordinates":[6.08866,48.487446],"type":"Point"}
}