{
  "type": "Feature",
  "properties": {
    "addr:full":"1, Rte du Saut de la Cuve, 88125 Le Syndicat C\u00e9dex Franche Comt\u00e9",
    "addr:housenumber":"1",
    "addr:postcode":"88125",
    "addr:street":"Rte Du Saut De La Cuve;Franche Comte\u0301",
    "iso:country":"FR",
    "sg:address":"1, Rte du Saut de la Cuve, 88125 Le Syndicat C\u00e9dex",
    "sg:orig_category":"Non-Classified Establishments",
    "sg:phone":"+33 3 29 61 20 86",
    "sg:province":"Franche Comt\u00e9",
    "wof:name":"Fertil S.a.",
    "wof:placetype":"venue"
},
  "geometry": {"coordinates":[-103.231667,33.61462],"type":"Point"}
}