{
  "type": "Feature",
  "properties": {
    "iso:country":"FR",
    "sg:address":"21, Rue Championnet, 75018 Paris",
    "sg:orig_category":"Unclassifiable Establishments",
    "sg:phone":"+33 1 42 54 85 93",
    "sg:province":"Ile de France",
    "wof:name":"Offsec 27 S.a.",
    "wof:placetype":"venue"
},
  "geometry": {"coordinates":[2.350546,48.895241],"type":"Point"}
}