{
  "type": "Feature",
  "properties": {
    "iso:country":"FR",
    "sg:address":"2, Rue des Menuisiers, 67460 Souffelweyersheim",
    "sg:city":"Souffelweyersheim",
    "sg:orig_category":"Unclassifiable Establishments",
    "sg:phone":"+33 3 88 20 91 91",
    "sg:postcode":"67460",
    "sg:province":"Alsace",
    "wof:name":"Menuiserie D'alsace S.a.r.l.",
    "wof:placetype":"venue"
},
  "geometry": {"coordinates":[7.727713,48.629219],"type":"Point"}
}