{
  "type": "Feature",
  "properties": {
    "addr:full":"9, Rue des Perri\u00e8res, 39200 Saint Claude Franche Comt\u00e9",
    "addr:housenumber":"9",
    "addr:postcode":"39200",
    "addr:street":"Rue Des Perrie\u0300Res;Franche Comte\u0301",
    "iso:country":"FR",
    "sg:address":"9, Rue des Perri\u00e8res, 39200 Saint Claude",
    "sg:orig_category":"Unclassifiable Establishments",
    "sg:phone":"+33 3 84 45 15 85",
    "sg:province":"Franche Comt\u00e9",
    "wof:name":"Etablissements Jean Goujon Et Fils S.a.r.l.",
    "wof:placetype":"venue"
},
  "geometry": {"coordinates":[5.86014,46.392361],"type":"Point"}
}