{
  "type": "Feature",
  "properties": {
    "iso:country":"FR",
    "sg:address":"63000 Clermont Ferrand",
    "sg:city":"Clermont-Ferrand",
    "sg:orig_category":"Non-Classified Establishments",
    "sg:phone":"+33 4 73 28 76 20",
    "sg:postcode":"63000",
    "sg:province":"Auvergne",
    "wof:name":"Gestetner S.a.",
    "wof:placetype":"venue"
},
  "geometry": {"coordinates":[3.12125,45.77145],"type":"Point"}
}