{
  "type": "Feature",
  "properties": {
    "addr:full":"48 Boulevard Des Coquibus 91025 \u00c9vry Cedex Centre",
    "addr:housenumber":"48",
    "addr:postcode":"91025;cedex",
    "addr:street":"Boulevard Des Coquibus",
    "iso:country":"FR",
    "sg:address":"48 Boulevard Des Coquibus 91025 \u00c9vry Cedex",
    "sg:classifiers":[
        {
            "category":"Farming",
            "subcategory":"Livestock Farm",
            "type":"Manufacturing & Wholesale Goods"
        }
    ],
    "sg:phone":"+33 1 69 47 11 00",
    "sg:province":"Centre",
    "sg:tags":[
        "breeding",
        "agriculture",
        "animal"
    ],
    "wof:name":"Icelandic Freezing Plants",
    "wof:placetype":"venue"
},
  "geometry": {"coordinates":[2.43037,48.624821],"type":"Point"}
}