{
  "type": "Feature",
  "properties": {
    "iso:country":"FR",
    "sg:address":"16, Rue Jacques Monod, 76130 Mont Saint Aignan",
    "sg:orig_category":"Unclassifiable Establishments",
    "sg:phone":"+33 2 35 59 45 45",
    "sg:province":"Haute Normandie",
    "wof:name":"Adp - Gsi - Auto Data Processing - G\u00e9n\u00e9rale Services Informatiques S.a.",
    "wof:placetype":"venue"
},
  "geometry": {"coordinates":[1.09612,49.476833],"type":"Point"}
}