{
  "type": "Feature",
  "properties": {
    "addr:full":"57 Tavaux Chevigny St Sauveur BP 61 cedex 21802 Quetigny Bourgogne",
    "addr:housenumber":"57",
    "addr:postcode":"21802",
    "addr:street":"Tavaux Chevigny St;Bp 61 Cedex",
    "iso:country":"FR",
    "sg:address":"57",
    "sg:city":"Tavaux Chevigny St Sauveur BP 61 cedex 21802 Quetigny",
    "sg:classifiers":[
        {
            "category":"Manufacturing",
            "subcategory":"Rubber & Plastics",
            "type":"Manufacturing & Wholesale Goods"
        }
    ],
    "sg:phone":"+33 3 80 46 80 00",
    "sg:province":"Bourgogne",
    "wof:name":"Ondex (sas)",
    "wof:placetype":"venue"
},
  "geometry": {"coordinates":[5.115562,47.309772],"type":"Point"}
}