{
  "type": "Feature",
  "properties": {
    "addr:full":"5 Bis Rue De Seignelay 56100 Lorient Lorient Bretagne 56100",
    "addr:housenumber":"5 bis",
    "addr:postcode":"56100;56100",
    "addr:street":"Rue De Seignelay",
    "iso:country":"FR",
    "sg:address":"5 Bis Rue De Seignelay 56100 Lorient",
    "sg:city":"Lorient",
    "sg:classifiers":[
        {
            "category":"Manufacturing",
            "subcategory":"Chemicals & Compounds",
            "type":"Manufacturing & Wholesale Goods"
        }
    ],
    "sg:phone":"+33 2 97 37 16 44",
    "sg:postcode":"56100",
    "sg:province":"Bretagne",
    "sg:tags":[
        "pharmaceutical",
        "chemistry",
        "-",
        "by-product"
    ],
    "wof:name":"Worex Snc",
    "wof:placetype":"venue"
},
  "geometry": {"coordinates":[-3.362222,47.731747],"type":"Point"}
}