{
  "type": "Feature",
  "properties": {
    "addr:full":"3, Chemin Pav\u00e9, 95340 Bernes sur Oise Ile de France",
    "addr:housenumber":"3",
    "addr:postcode":"95340",
    "addr:street":"Chemin Pave\u0301",
    "iso:country":"FR",
    "sg:address":"3, Chemin Pav\u00e9, 95340 Bernes sur Oise",
    "sg:orig_category":"Unclassifiable Establishments",
    "sg:phone":"+33 1 30 34 26 50",
    "sg:province":"Ile de France",
    "wof:name":"Cariane Val D'oise S.n.c.",
    "wof:placetype":"venue"
},
  "geometry": {"coordinates":[2.299627,49.152271],"type":"Point"}
}