{
  "type": "Feature",
  "properties": {
    "iso:country":"FR",
    "sg:address":"3, Av du 106\u00e8me RI, 51000 Ch\u00e2lons en Champagne",
    "sg:orig_category":"Unclassifiable Establishments",
    "sg:phone":"+33 3 26 66 78 00",
    "sg:province":"Champagne",
    "wof:name":"F.r.e.s.a. S.a. - Fabriques R\u00e9unies D'electrodes De Soudure \u00e0 L'arc",
    "wof:placetype":"venue"
},
  "geometry": {"coordinates":[4.354734,48.970455],"type":"Point"}
}