{
  "type": "Feature",
  "properties": {
    "iso:country":"FR",
    "sg:address":"1, Rue de Bourgogne, 91220 Br\u00e9tigny sur Orge",
    "sg:orig_category":"Non-Classified Establishments",
    "sg:phone":"+33 1 60 85 24 24",
    "sg:province":"Ile de France",
    "wof:name":"Perrichon S.a.r.l",
    "wof:placetype":"venue"
},
  "geometry": {"coordinates":[2.304789,48.590099],"type":"Point"}
}