{
  "type": "Feature",
  "properties": {
    "addr:full":"B.P. 38, 59721 Denain C\u00e9dex^^108, Rue Jean Jaur\u00e8s, 59220 Denain Nord Pas-de-Calais 59220",
    "addr:postcode":"59721;59220;59220",
    "addr:street":"B.P. 38;Rue Jean Jaure\u0300S",
    "iso:country":"FR",
    "sg:address":"B.P. 38, 59721 Denain C\u00e9dex^^108, Rue Jean Jaur\u00e8s, 59220 Denain",
    "sg:orig_category":"Non-Classified Establishments",
    "sg:phone":"+33 3 27 21 40 00",
    "sg:postcode":"59220",
    "sg:province":"Nord Pas-de-Calais",
    "wof:name":"Andr\u00e9 S.a.",
    "wof:placetype":"venue"
},
  "geometry": {"coordinates":[3.39305,50.326897],"type":"Point"}
}