{
  "type": "Feature",
  "properties": {
    "addr:full":"82 Av Leon Blum 09300 Lavelanet Midi Pyr\u00e9n\u00e9es 09300",
    "addr:postcode":"09300;09300",
    "addr:street":"82 Av Leon Blum",
    "iso:country":"FR",
    "sg:address":"82 Av Leon Blum 09300 Lavelanet",
    "sg:classifiers":[
        {
            "category":"Professional",
            "subcategory":"Engineering",
            "type":"Services"
        }
    ],
    "sg:phone":"+33 5 61 01 13 71",
    "sg:postcode":"09300",
    "sg:province":"Midi Pyr\u00e9n\u00e9es",
    "sg:tags":[
        "machine",
        "-",
        "mechanical"
    ],
    "wof:name":"M. Palacios Patrick",
    "wof:placetype":"venue"
},
  "geometry": {"coordinates":[1.842019,42.92836],"type":"Point"}
}