{
  "type": "Feature",
  "properties": {
    "iso:country":"FR",
    "sg:address":"Rue Bellitourne 53204 Ch\u00e2teau Gontier",
    "sg:city":"Ch\u00e2teau",
    "sg:classifiers":[
        {
            "category":"Food & Beverages",
            "subcategory":"Dairy",
            "type":"Retail Goods"
        }
    ],
    "sg:phone":"+33 2 43 09 53 00",
    "sg:postcode":"71250",
    "sg:province":"Bourgogne",
    "sg:tags":[
        "product",
        "related"
    ],
    "wof:name":"Fromageries Perreault",
    "wof:placetype":"venue"
},
  "geometry": {"coordinates":[-0.707919,47.825954],"type":"Point"}
}