{
  "type": "Feature",
  "properties": {
    "addr:full":"Pl Jean Hameau; La Teste; 33260 Teste-de-Buch Aquitaine 33260",
    "addr:postcode":"33260;33260",
    "addr:street":"Pl Jean Hameau La Teste",
    "iso:country":"FR",
    "sg:address":"Pl Jean Hameau; La Teste; 33260",
    "sg:city":"Teste-de-Buch",
    "sg:classifiers":[
        {
            "category":"Banks & Credit Unions",
            "subcategory":"Bank",
            "type":"Services"
        }
    ],
    "sg:phone":"+33 3356664470",
    "sg:postcode":"33260",
    "sg:province":"Aquitaine",
    "wof:name":"Soci\u00e9t\u00e9 G\u00e9n\u00e9rale",
    "wof:placetype":"venue"
},
  "geometry": {"coordinates":[-1.145227,44.632915],"type":"Point"}
}