{
  "type": "Feature",
  "properties": {
    "iso:country":"FR",
    "sg:address":"1, Chemin Lat\u00e9ral, 94140 Alfortville",
    "sg:orig_category":"Unclassifiable Establishments",
    "sg:phone":"+33 1 43 75 47 66",
    "sg:province":"Ile de France",
    "wof:name":"Propack S.a.",
    "wof:placetype":"venue"
},
  "geometry": {"coordinates":[2.416624,48.814487],"type":"Point"}
}