{
  "type": "Feature",
  "properties": {
    "iso:country":"FR",
    "sg:address":"49, Bd Descat, 59200 Tourcoing",
    "sg:orig_category":"Non-Classified Establishments",
    "sg:phone":"+33 3 20 26 90 80",
    "sg:postcode":"59200",
    "sg:province":"Nord Pas-de-Calais",
    "wof:name":"Com'plus S.a.",
    "wof:placetype":"venue"
},
  "geometry": {"coordinates":[3.159375,50.722389],"type":"Point"}
}