{
  "type": "Feature",
  "properties": {
    "iso:country":"FR",
    "sg:address":"5, Rue de la Rochelle, 94150 Rungis",
    "sg:orig_category":"Unclassifiable Establishments",
    "sg:phone":"+33 1 45 60 42 66",
    "sg:province":"Ile de France",
    "wof:name":"Le Moussaillon S.a.",
    "wof:placetype":"venue"
},
  "geometry": {"coordinates":[2.35548,48.754841],"type":"Point"}
}