{
  "type": "Feature",
  "properties": {
    "addr:full":"35 Ch Du Vouldy 10000 Troyes Champagne 10000",
    "addr:housenumber":"35",
    "addr:postcode":"10000;10000",
    "addr:street":"Ch Du Vouldy",
    "iso:country":"FR",
    "sg:address":"35 Ch Du Vouldy 10000 Troyes",
    "sg:classifiers":[
        {
            "category":"Professional",
            "subcategory":"Engineering",
            "type":"Services"
        }
    ],
    "sg:phone":"+33 3 25 80 07 71",
    "sg:postcode":"10000",
    "sg:province":"Champagne",
    "sg:tags":[
        "machine",
        "-",
        "mechanical"
    ],
    "wof:name":"Boeglin Sarl",
    "wof:placetype":"venue"
},
  "geometry": {"coordinates":[4.088681,48.29097],"type":"Point"}
}