{
  "type": "Feature",
  "properties": {
    "iso:country":"FR",
    "sg:address":"RN2",
    "sg:city":"Saint Maixent l'Ecole",
    "sg:orig_category":"Unclassifiable Establishments",
    "sg:phone":"+33 5 49 76 11 05",
    "sg:postcode":"79400",
    "sg:province":"Poitou-Charentes",
    "wof:name":"Laroche Peltier Et Compagnie S.a.",
    "wof:placetype":"venue"
},
  "geometry": {"coordinates":[-0.22462,46.44009],"type":"Point"}
}