{
  "type": "Feature",
  "properties": {
    "iso:country":"FR",
    "sg:address":"29 ter, Rue Croix de Fer, 78100 Saint Germain en Laye",
    "sg:orig_category":"Non-Classified Establishments",
    "sg:phone":"+33 1 34 66 42 06",
    "sg:province":"Ile de France",
    "wof:name":"S.e.p.e.m. S.a.r.l. - Soci\u00e9t\u00e9 Exploitation Produit \u00e9lectronique M\u00e9canique",
    "wof:placetype":"venue"
},
  "geometry": {"coordinates":[2.064664,48.898399],"type":"Point"}
}