{
  "type": "Feature",
  "properties": {
    "addr:full":"69 Rue Henri Vezouet BP 471 22604 Loudeac Loud\u00e9ac Bretagne 22600",
    "addr:housenumber":"69;471",
    "addr:postcode":"22604;22600",
    "addr:street":"Rue Henri Vezouet Bp",
    "iso:country":"FR",
    "sg:address":"69 Rue Henri Vezouet BP 471 22604 Loudeac",
    "sg:city":"Loud\u00e9ac",
    "sg:classifiers":[
        {
            "category":"Professional",
            "subcategory":"Business Services",
            "type":"Services"
        }
    ],
    "sg:phone":"+33 2 96 66 82 66",
    "sg:postcode":"22600",
    "sg:province":"Bretagne",
    "sg:tags":[
        "body",
        "advice"
    ],
    "wof:name":"Dynamique Agro Alimentaire Loudeac Soc",
    "wof:placetype":"venue"
},
  "geometry": {"coordinates":[-2.754195,48.1754],"type":"Point"}
}