{
  "type": "Feature",
  "properties": {
    "addr:full":"Rte De Richelieu 37120 Braslou Richelieu Centre 37120",
    "addr:postcode":"37120;37120",
    "addr:street":"Rte De Richelieu",
    "iso:country":"FR",
    "sg:address":"Rte De Richelieu 37120 Braslou",
    "sg:city":"Richelieu",
    "sg:classifiers":[
        {
            "category":"Home & Garden",
            "subcategory":"Household Appliances",
            "type":"Retail Goods"
        }
    ],
    "sg:phone":"+33 2 47 95 60 00",
    "sg:postcode":"37120",
    "sg:province":"Centre",
    "sg:tags":[
        "product",
        "miscellaneous"
    ],
    "wof:name":"Olc De Bournais",
    "wof:placetype":"venue"
},
  "geometry": {"coordinates":[0.413795,46.948654],"type":"Point"}
}