{
  "type": "Feature",
  "properties": {
    "addr:full":"2, Rue de Marclan, 31600 Muret Midi Pyr\u00e9n\u00e9es",
    "addr:housenumber":"2",
    "addr:postcode":"31600",
    "addr:street":"Rue De Marclan",
    "iso:country":"FR",
    "sg:address":"2, Rue de Marclan, 31600 Muret",
    "sg:orig_category":"Non-Classified Establishments",
    "sg:phone":"+33 5 61 51 00 39",
    "sg:province":"Midi Pyr\u00e9n\u00e9es",
    "wof:name":"M\u00e9gisserie Moisand S.a.r.l.",
    "wof:placetype":"venue"
},
  "geometry": {"coordinates":[1.33799,43.485413],"type":"Point"}
}