{
  "type": "Feature",
  "properties": {
    "addr:full":"19 Rue Jules Ferry Zi Du Bas Pontet 69360 St Symphorien D'Ozon Rhone-Alpes 69360",
    "addr:housenumber":"19",
    "addr:postcode":"69360;69360",
    "addr:street":"Rue Jules Ferry Zi Du Bas;Rhone-Alpes",
    "iso:country":"FR",
    "sg:address":"19 Rue Jules Ferry Zi Du Bas Pontet 69360 St Symphorien D'Ozon",
    "sg:classifiers":[
        {
            "category":"Professional",
            "subcategory":"Engineering",
            "type":"Services"
        }
    ],
    "sg:phone":"+33 4 78 02 84 93",
    "sg:postcode":"69360",
    "sg:province":"Rhone-Alpes",
    "sg:tags":[
        "machine",
        "-",
        "mechanical"
    ],
    "wof:name":"L M Realisations Sa",
    "wof:placetype":"venue"
},
  "geometry": {"coordinates":[-101.20152299999999,30.710594],"type":"Point"}
}