{
  "type": "Feature",
  "properties": {
    "iso:country":"FR",
    "sg:address":"72 Rue Reignier 33100 Bordeaux",
    "sg:city":"Bordeaux",
    "sg:classifiers":[
        {
            "category":"Food Court",
            "type":"Food & Drink"
        }
    ],
    "sg:phone":"+33 5 57 77 11 50",
    "sg:postcode":"33100",
    "sg:province":"Aquitaine",
    "sg:tags":[
        "product",
        "related"
    ],
    "wof:name":"Cuvelier Et Fils Sarl",
    "wof:placetype":"venue"
},
  "geometry": {"coordinates":[-0.559904,44.846859],"type":"Point"}
}