{
  "type": "Feature",
  "properties": {
    "iso:country":"FR",
    "sg:address":"Rd 939 17160 Matha",
    "sg:classifiers":[
        {
            "category":"Wholesale",
            "subcategory":"Farm Supplies",
            "type":"Manufacturing & Wholesale Goods"
        }
    ],
    "sg:phone":"+33 5 46 58 77 07",
    "sg:postcode":"17160",
    "sg:province":"Poitou-Charentes",
    "sg:tags":[
        "-",
        "machine",
        "equipment",
        "engineering",
        "machinery",
        "mechanical",
        "agriculture"
    ],
    "wof:name":"Agroma",
    "wof:placetype":"venue"
},
  "geometry": {"coordinates":[-0.326821,45.802044],"type":"Point"}
}