{
  "type": "Feature",
  "properties": {
    "iso:country":"FR",
    "sg:address":"18, Place Tolozan, 69001 Lyon",
    "sg:orig_category":"Non-Classified Establishments",
    "sg:phone":"+33 4 72 98 58 58",
    "sg:postcode":"69001",
    "sg:province":"Rhone-Alpes",
    "wof:name":"Transit Communication S.a.s.",
    "wof:placetype":"venue"
},
  "geometry": {"coordinates":[4.83185,45.768505],"type":"Point"}
}