{
  "type": "Feature",
  "properties": {
    "addr:full":"Rue Henri Potez - Z.I. Nord Albert Picardie 80300",
    "addr:postcode":"80300",
    "addr:street":"Rue Henri Potez Z.I. Nord Albert Picardie",
    "iso:country":"FR",
    "sg:address":"Rue Henri Potez - Z.I. Nord",
    "sg:city":"Albert",
    "sg:orig_category":"Unclassifiable Establishments",
    "sg:phone":"+33 3 22 74 43 00",
    "sg:postcode":"80300",
    "sg:province":"Picardie",
    "wof:name":"Forest Lin\u00e9 Albert S.a.",
    "wof:placetype":"venue"
},
  "geometry": {"coordinates":[2.646825,50.00407],"type":"Point"}
}