{
  "type": "Feature",
  "properties": {
    "iso:country":"FR",
    "sg:address":"19, Av. Industrielle, 59520 Marquette lez Lille",
    "sg:orig_category":"Non-Classified Establishments",
    "sg:phone":"+33 3 28 04 00 06",
    "sg:postcode":"59520",
    "sg:province":"Nord Pas-de-Calais",
    "wof:name":"A.m.h. S.a.r.l. - Ateliers De M\u00e9canique D'hellemmes",
    "wof:placetype":"venue"
},
  "geometry": {"coordinates":[3.054847,50.678043],"type":"Point"}
}