{
  "type": "Feature",
  "properties": {
    "addr:full":"42, Rue Ile Napol\u00e9on - Z.I. Ile Napol\u00e9on, 68170 Rixheim Rixheim Alsace 68170",
    "addr:housenumber":"42",
    "addr:postcode":"68170;alsace 68170",
    "addr:street":"Rue Ile Napole\u0301On Z.I. Ile Napole\u0301On;Rixheim",
    "iso:country":"FR",
    "sg:address":"42, Rue Ile Napol\u00e9on - Z.I. Ile Napol\u00e9on, 68170 Rixheim",
    "sg:city":"Rixheim",
    "sg:orig_category":"Unclassifiable Establishments",
    "sg:phone":"+33 3 89 64 54 54",
    "sg:postcode":"68170",
    "sg:province":"Alsace",
    "wof:name":"Alsatel S.a.",
    "wof:placetype":"venue"
},
  "geometry": {"coordinates":[7.397395,47.744122],"type":"Point"}
}