{
  "type": "Feature",
  "properties": {
    "iso:country":"FR",
    "sg:address":"75, Chemin de Sommiers, 30310 Verg\u00e8ze",
    "sg:orig_category":"Non-Classified Establishments",
    "sg:phone":"+33 4 66 73 17 73",
    "sg:postcode":"30310",
    "sg:province":"Languedoc-Roussillon",
    "wof:name":"A.d.m.e. Bioanalyses S.a.",
    "wof:placetype":"venue"
},
  "geometry": {"coordinates":[4.221424,43.743683],"type":"Point"}
}