{
  "type": "Feature",
  "properties": {
    "iso:country":"FR",
    "sg:address":"8 place Th\u00e9odore P\u00e2que 57500 St Avold",
    "sg:classifiers":[
        {
            "category":"Professional",
            "subcategory":"Employment Agencies",
            "type":"Services"
        }
    ],
    "sg:phone":"+33 3 87 29 02 03",
    "sg:province":"Lorraine",
    "sg:tags":[
        "personnel",
        "temporary"
    ],
    "wof:name":"Mc Interim Sarl",
    "wof:placetype":"venue"
},
  "geometry": {"coordinates":[6.701294,49.1036],"type":"Point"}
}