{
  "type": "Feature",
  "properties": {
    "addr:full":"1, Mail Clouseau, 41000 Blois Blois Centre 41000",
    "addr:housenumber":"1",
    "addr:postcode":"41000;41000",
    "addr:street":"Mail Clouseau",
    "iso:country":"FR",
    "sg:address":"1, Mail Clouseau, 41000 Blois",
    "sg:city":"Blois",
    "sg:orig_category":"Unclassifiable Establishments",
    "sg:phone":"+33 2 54 90 45 00",
    "sg:postcode":"41000",
    "sg:province":"Centre",
    "wof:name":"Manpower Tertiaire S.a.s.",
    "wof:placetype":"venue"
},
  "geometry": {"coordinates":[1.33704,47.58923],"type":"Point"}
}