{
  "type": "Feature",
  "properties": {
    "addr:full":"3/5, Rue Bayard, 75393 Paris C\u00e9dex 8 Champagne",
    "addr:housenumber":"3 / 5;8",
    "addr:postcode":"75393",
    "addr:street":"Rue Bayard",
    "iso:country":"FR",
    "sg:address":"3/5, Rue Bayard, 75393 Paris C\u00e9dex 8",
    "sg:orig_category":"Non-Classified Establishments",
    "sg:phone":"+33 1 44 35 60 60",
    "sg:province":"Champagne",
    "wof:name":"Bayard Presse S.a.",
    "wof:placetype":"venue"
},
  "geometry": {"coordinates":[2.307609,48.865162],"type":"Point"}
}