{
  "type": "Feature",
  "properties": {
    "iso:country":"FR",
    "sg:address":"24, Rue de Fauville, 27000 Evreux",
    "sg:orig_category":"Non-Classified Establishments",
    "sg:phone":"+33 2 32 39 15 49",
    "sg:province":"Haute Normandie",
    "wof:name":"Italic Compo S.a.r.l.",
    "wof:placetype":"venue"
},
  "geometry": {"coordinates":[1.17565,49.025009],"type":"Point"}
}