{
  "type": "Feature",
  "properties": {
    "addr:full":"24, Rue de Fauville, 27000 Evreux Haute Normandie",
    "addr:housenumber":"24",
    "addr:postcode":"27000",
    "addr:street":"Rue De Fauville;Haute Normandie",
    "iso:country":"FR",
    "sg:address":"24, Rue de Fauville, 27000 Evreux",
    "sg:orig_category":"Non-Classified Establishments",
    "sg:phone":"+33 2 32 39 15 49",
    "sg:province":"Haute Normandie",
    "wof:name":"Italic Compo S.a.r.l.",
    "wof:placetype":"venue"
},
  "geometry": {"coordinates":[1.17565,49.025009],"type":"Point"}
}