{
  "type": "Feature",
  "properties": {
    "addr:full":"29 rue Fran\u00e7ois de Tessan 77330 OZOIR LA FERRIERE Ile de France 77330",
    "addr:housenumber":"29",
    "addr:postcode":"77330;77330",
    "addr:street":"Rue Franc\u0327Ois De Tessan",
    "iso:country":"FR",
    "sg:address":"29 rue Fran\u00e7ois de Tessan 77330 OZOIR LA FERRIERE",
    "sg:classifiers":[
        {
            "category":"Retail",
            "subcategory":"Event Space",
            "type":"Services"
        }
    ],
    "sg:phone":"+33 1 64 40 33 54",
    "sg:postcode":"77330",
    "sg:province":"Ile de France",
    "sg:tags":[
        "case",
        "display"
    ],
    "wof:name":"Cr\u00e9ations Oph\u00e9lia Sarl",
    "wof:placetype":"venue"
},
  "geometry": {"coordinates":[2.698672,48.76038],"type":"Point"}
}