{
  "type": "Feature",
  "properties": {
    "addr:full":"11, Rue des Pontrits, 64603 Anglet C\u00e9dex Anglet Aquitaine 64600",
    "addr:housenumber":"11",
    "addr:postcode":"64603;64600",
    "addr:street":"Rue Des Pontrits",
    "iso:country":"FR",
    "sg:address":"11, Rue des Pontrits, 64603 Anglet C\u00e9dex",
    "sg:city":"Anglet",
    "sg:orig_category":"Non-Classified Establishments",
    "sg:phone":"+33 5 59 31 41 76",
    "sg:postcode":"64600",
    "sg:province":"Aquitaine",
    "wof:name":"Soci\u00e9t\u00e9 D'exploitation Des Etablissements Bouney S.a.",
    "wof:placetype":"venue"
},
  "geometry": {"coordinates":[-1.530436,43.492085],"type":"Point"}
}