{
  "type": "Feature",
  "properties": {
    "addr:full":"276 Rue Du Coloney 74700 Sallanches Rhone-Alpes 74700",
    "addr:housenumber":"276",
    "addr:postcode":"74700;74700",
    "addr:street":"Rue Du Coloney",
    "iso:country":"FR",
    "sg:address":"276 Rue Du Coloney 74700 Sallanches",
    "sg:classifiers":[
        {
            "category":"Manufacturing",
            "subcategory":"Chemicals & Compounds",
            "type":"Manufacturing & Wholesale Goods"
        }
    ],
    "sg:phone":"+33 4 50 58 46 35",
    "sg:postcode":"74700",
    "sg:province":"Rhone-Alpes",
    "sg:tags":[
        "pharmaceutical",
        "energy",
        "chemistry",
        "-",
        "by-product"
    ],
    "wof:name":"La Mure Bianco Prodits Prtrolier",
    "wof:placetype":"venue"
},
  "geometry": {"coordinates":[6.63587,45.944607],"type":"Point"}
}