{
  "type": "Feature",
  "properties": {
    "addr:full":"3, All\u00e9e de la Seine - Immeuble Paryseine, 94854 Ivry sur Seine C\u00e9dex Haute Normandie",
    "addr:housenumber":"3",
    "addr:postcode":"94854",
    "addr:street":"Alle\u0301E De La Seine;Paryseine;Haute Normandie",
    "iso:country":"FR",
    "sg:address":"3, All\u00e9e de la Seine - Immeuble Paryseine, 94854 Ivry sur Seine C\u00e9dex",
    "sg:orig_category":"Non-Classified Establishments",
    "sg:phone":"+33 1 56 20 50 00",
    "sg:province":"Haute Normandie",
    "wof:name":"Wanadoo E. Marchand S.a.",
    "wof:placetype":"venue"
},
  "geometry": {"coordinates":[2.399564,48.818554],"type":"Point"}
}