{
  "type": "Feature",
  "properties": {
    "addr:full":"Zi Nord 43 Chemin De Chiradie 69530 Brignais Rhone-Alpes",
    "addr:housenumber":"43",
    "addr:postcode":"69530",
    "addr:street":"Zi Nord;Chemin De Chiradie",
    "iso:country":"FR",
    "sg:address":"Zi Nord 43 Chemin De Chiradie 69530 Brignais",
    "sg:classifiers":[
        {
            "category":"Professional",
            "subcategory":"Engineering",
            "type":"Services"
        }
    ],
    "sg:phone":"+33 4 78 05 07 55",
    "sg:province":"Rhone-Alpes",
    "sg:tags":[
        "machine",
        "-",
        "mechanical"
    ],
    "wof:name":"Sobergrand Industrie",
    "wof:placetype":"venue"
},
  "geometry": {"coordinates":[4.76228,45.670528],"type":"Point"}
}