{
  "type": "Feature",
  "properties": {
    "addr:full":"23, Rue Anatole France, 78400 Chatou Ile de France 78400",
    "addr:housenumber":"23",
    "addr:postcode":"78400;78400",
    "addr:street":"Rue Anatole France;Ile De France",
    "iso:country":"FR",
    "sg:address":"23, Rue Anatole France, 78400 Chatou",
    "sg:orig_category":"Non-Classified Establishments",
    "sg:phone":"+33 1 34 80 68 45",
    "sg:postcode":"78400",
    "sg:province":"Ile de France",
    "wof:name":"Diouron Jean Pierre",
    "wof:placetype":"venue"
},
  "geometry": {"coordinates":[2.148824,48.8894],"type":"Point"}
}