{
  "type": "Feature",
  "properties": {
    "iso:country":"FR",
    "sg:address":"65, Av. Jules Cantini - Tour M\u00e9diterran\u00e9e, 13006 Marseille",
    "sg:orig_category":"Unclassifiable Establishments",
    "sg:phone":"+33 4 91 80 60 50",
    "sg:province":"Provence-Alpes-C\u00f4te d'Azur",
    "wof:name":"Banque Sanpaolo",
    "wof:placetype":"venue"
},
  "geometry": {"coordinates":[5.388277,43.283756],"type":"Point"}
}