{
  "type": "Feature",
  "properties": {
    "iso:country":"FR",
    "sg:address":"33, Quai de Bacalan, 33300 Bordeaux",
    "sg:city":"Bordeaux",
    "sg:orig_category":"Unclassifiable Establishments",
    "sg:phone":"+33 5 56 39 18 49",
    "sg:postcode":"33300",
    "sg:province":"Aquitaine",
    "wof:name":"Samazeuilh S.a.",
    "wof:placetype":"venue"
},
  "geometry": {"coordinates":[-0.559071,44.858089],"type":"Point"}
}