{
  "type": "Feature",
  "properties": {
    "iso:country":"FR",
    "sg:address":"CD 49",
    "sg:city":"Saclas",
    "sg:orig_category":"Unclassifiable Establishments",
    "sg:phone":"+33 1 64 95 67 92",
    "sg:postcode":"91690",
    "sg:province":"Ile de France",
    "wof:name":"Climel S.a.",
    "wof:placetype":"venue"
},
  "geometry": {"coordinates":[2.12557,48.360584],"type":"Point"}
}