{
  "type": "Feature",
  "properties": {
    "iso:country":"FR",
    "sg:address":"114 Chemin Oratoire Bouc",
    "sg:city":"Gardanne",
    "sg:classifiers":[
        {
            "category":"Banks & Credit Unions",
            "subcategory":"Financial Services",
            "type":"Services"
        }
    ],
    "sg:phone":"+33 4 42 65 88 21",
    "sg:postcode":"13120",
    "sg:province":"Centre",
    "sg:tags":[
        "banking",
        "finance",
        "insurance"
    ],
    "wof:name":"Hydro Geo Mediterranee Zi Avon Sa",
    "wof:placetype":"venue"
},
  "geometry": {"coordinates":[5.45076,43.445824],"type":"Point"}
}