{
  "type": "Feature",
  "properties": {
    "iso:country":"FR",
    "sg:address":"58, Av. Adolphe Schneider, 92140 Clamart",
    "sg:orig_category":"Non-Classified Establishments",
    "sg:phone":"+33 1 46 38 83 26",
    "sg:province":"Ile de France",
    "wof:name":"S.c.d. S.a.r.l.",
    "wof:placetype":"venue"
},
  "geometry": {"coordinates":[2.253653,48.807213],"type":"Point"}
}