{
  "type": "Feature",
  "properties": {
    "iso:country":"FR",
    "sg:address":"7, Av. des Cit\u00e9s Unies, 56300 Pontivy",
    "sg:city":"Pontivy",
    "sg:orig_category":"Non-Classified Establishments",
    "sg:phone":"+33 2 97 25 06 79",
    "sg:postcode":"56300",
    "sg:province":"Bretagne",
    "wof:name":"Etablissements Pierre Le Forrestier S.a.",
    "wof:placetype":"venue"
},
  "geometry": {"coordinates":[-2.958774,48.053493],"type":"Point"}
}