{
  "type": "Feature",
  "properties": {
    "addr:full":"Rte De La Baronne Zac St Est\u00e8ve 06640 St Jeannet Pays de Loire",
    "addr:postcode":"06640",
    "addr:street":"Rte De La Baronne Zac St Este\u0300Ve;Jeannet",
    "iso:country":"FR",
    "sg:address":"Rte De La Baronne Zac St Est\u00e8ve 06640 St Jeannet",
    "sg:classifiers":[
        {
            "category":"Park",
            "type":"Public Place"
        }
    ],
    "sg:phone":"+33 4 92 12 05 05",
    "sg:province":"Pays de Loire",
    "sg:tags":[
        "work",
        "construction",
        "sport"
    ],
    "wof:name":"Piscines Et Filtrations Sarl",
    "wof:placetype":"venue"
},
  "geometry": {"coordinates":[7.14787,43.746399],"type":"Point"}
}