{
  "type": "Feature",
  "properties": {
    "iso:country":"FR",
    "sg:address":"9001 Rue Casimir Perrier 59490 Somain",
    "sg:classifiers":[
        {
            "category":"Manufacturing",
            "subcategory":"Wood Products",
            "type":"Manufacturing & Wholesale Goods"
        }
    ],
    "sg:phone":"+33 3 27 86 11 08",
    "sg:postcode":"59490",
    "sg:province":"Nord Pas-de-Calais",
    "sg:tags":[
        "professional",
        "miscellaneous",
        "furniture"
    ],
    "wof:name":"Etablissment Hellin",
    "wof:placetype":"venue"
},
  "geometry": {"coordinates":[3.29539,50.343899],"type":"Point"}
}