{
  "type": "Feature",
  "properties": {
    "addr:full":"57, Grande Rue, 78630 Morainvilliers Ile de France",
    "addr:housenumber":"57",
    "addr:postcode":"78630",
    "addr:street":"Grande Rue;Ile De France",
    "iso:country":"FR",
    "sg:address":"57, Grande Rue, 78630 Morainvilliers",
    "sg:orig_category":"Unclassifiable Establishments",
    "sg:phone":"+33 1 30 80 06 23",
    "sg:province":"Ile de France",
    "wof:name":"Ing\u00e9pro S.a.r.l.",
    "wof:placetype":"venue"
},
  "geometry": {"coordinates":[1.935578,48.929039],"type":"Point"}
}