{
  "type": "Feature",
  "properties": {
    "iso:country":"FR",
    "sg:address":"Rue Cl\u00e9ment Ader - ZAE du Pr\u00e9-Clos",
    "sg:city":"Buc",
    "sg:orig_category":"Unclassifiable Establishments",
    "sg:phone":"+33 1 39 20 68 00",
    "sg:postcode":"78530",
    "sg:province":"Ile de France",
    "wof:name":"Descours Et Cabaud S.a.",
    "wof:placetype":"venue"
},
  "geometry": {"coordinates":[2.126343,48.774464],"type":"Point"}
}