{
  "type": "Feature",
  "properties": {
    "addr:full":"La Mezerine 69220 Charentay Rhone-Alpes",
    "addr:postcode":"69220",
    "iso:country":"FR",
    "sg:address":"La Mezerine 69220 Charentay",
    "sg:orig_category":"Unclassifiable Establishments",
    "sg:phone":"+33 4 74 06 15 15",
    "sg:province":"Rhone-Alpes",
    "wof:name":"Distillerie Du Beaujolais S.a.",
    "wof:placetype":"venue"
},
  "geometry": {"coordinates":[4.709428,46.095013],"type":"Point"}
}