{
  "type": "Feature",
  "properties": {
    "addr:full":"Av Des Censives 60000 Till\u00e9 Picardie",
    "addr:postcode":"60000",
    "addr:street":"Av Des Censives",
    "iso:country":"FR",
    "sg:address":"Av Des Censives 60000 Till\u00e9",
    "sg:classifiers":[
        {
            "category":"Manufacturing",
            "subcategory":"Printing",
            "type":"Manufacturing & Wholesale Goods"
        }
    ],
    "sg:phone":"+33 3 44 45 00 81",
    "sg:province":"Picardie",
    "sg:tags":[
        "publishing"
    ],
    "wof:name":"Imprimerie Commerciale De L'oise Sa",
    "wof:placetype":"venue"
},
  "geometry": {"coordinates":[2.09564,49.457077],"type":"Point"}
}