{
  "type": "Feature",
  "properties": {
    "iso:country":"FR",
    "sg:address":"B.P. 443, 76806 Saint Etienne du Rouvray C\u00e9dex^^Rue de l'Etang Delpech, 76800 Saint Etienne du Rouvr",
    "sg:orig_category":"Non-Classified Establishments",
    "sg:phone":"+33 2 32 95 94 00",
    "sg:postcode":"76800",
    "sg:province":"Haute Normandie",
    "wof:name":"Calberson Normandie S.a.",
    "wof:placetype":"venue"
},
  "geometry": {"coordinates":[1.113204,49.387844],"type":"Point"}
}