{
  "type": "Feature",
  "properties": {
    "addr:full":"25 R Des Usines 31150 Fenouillet Midi Pyr\u00e9n\u00e9es 31150",
    "addr:housenumber":"25",
    "addr:postcode":"31150;31150",
    "addr:street":"R Des Usines",
    "iso:country":"FR",
    "sg:address":"25 R Des Usines 31150 Fenouillet",
    "sg:classifiers":[
        {
            "category":"Manufacturing",
            "subcategory":"Chemicals & Compounds",
            "type":"Manufacturing & Wholesale Goods"
        }
    ],
    "sg:phone":"+33 5 61 37 58 00",
    "sg:postcode":"31150",
    "sg:province":"Midi Pyr\u00e9n\u00e9es",
    "sg:tags":[
        "pharmaceutical",
        "energy",
        "chemistry",
        "-",
        "by-product"
    ],
    "wof:name":"Totalgaz Snc",
    "wof:placetype":"venue"
},
  "geometry": {"coordinates":[1.403669,43.686707],"type":"Point"}
}