{
  "type": "Feature",
  "properties": {
    "addr:full":"3, Rte de Morlaix, 29520 Ch\u00e2teauneuf du Faou Ch\u00e2teauneuf-du-Faou Bretagne 29520",
    "addr:housenumber":"3",
    "addr:postcode":"29520;29520",
    "addr:street":"Rte De Morlaix;Faou Cha\u0302Teauneuf-Du-Faou Bretagne",
    "iso:country":"FR",
    "sg:address":"3, Rte de Morlaix, 29520 Ch\u00e2teauneuf du Faou",
    "sg:city":"Ch\u00e2teauneuf-du-Faou",
    "sg:orig_category":"Non-Classified Establishments",
    "sg:phone":"+33 2 98 81 76 49",
    "sg:postcode":"29520",
    "sg:province":"Bretagne",
    "wof:name":"G\u00e9dimat Jacq Poron S.a.",
    "wof:placetype":"venue"
},
  "geometry": {"coordinates":[-3.821067,48.196209],"type":"Point"}
}