{
  "type": "Feature",
  "properties": {
    "addr:full":"13 pl Saint Pierre; Carquefou Carquefou Pays de Loire 44470",
    "addr:housenumber":"13",
    "addr:postcode":"44470",
    "addr:street":"Pl",
    "iso:country":"FR",
    "sg:address":"13 pl Saint Pierre; Carquefou",
    "sg:city":"Carquefou",
    "sg:classifiers":[
        {
            "category":"Banks & Credit Unions",
            "subcategory":"Bank",
            "type":"Services"
        }
    ],
    "sg:phone":"+33 3340508309",
    "sg:postcode":"44470",
    "sg:province":"Pays de Loire",
    "wof:name":"Cr\u00e9dit Mutuel",
    "wof:placetype":"venue"
},
  "geometry": {"coordinates":[-1.491927,47.296581],"type":"Point"}
}