{
  "type": "Feature",
  "properties": {
    "iso:country":"FR",
    "sg:address":"91, Bd Deodat de Severac, 31300 Toulouse",
    "sg:orig_category":"Non-Classified Establishments",
    "sg:phone":"+33 5 61 42 53 30",
    "sg:postcode":"31300",
    "sg:province":"Midi Pyr\u00e9n\u00e9es",
    "wof:name":"Cabinet Pazio Barthas S.a.",
    "wof:placetype":"venue"
},
  "geometry": {"coordinates":[1.422322,43.588947],"type":"Point"}
}