{
  "type": "Feature",
  "properties": {
    "iso:country":"FR",
    "sg:address":"Moulin Badet",
    "sg:city":"Levernois",
    "sg:orig_category":"Unclassifiable Establishments",
    "sg:phone":"+33 3 80 26 21 00",
    "sg:postcode":"21200",
    "sg:province":"Bourgogne",
    "wof:name":"Roualet Imprimeur S.a.",
    "wof:placetype":"venue"
},
  "geometry": {"coordinates":[4.874019,46.990608],"type":"Point"}
}