{
  "type": "Feature",
  "properties": {
    "addr:full":"305 All De Craponne 13300 Salon De Provence Outre-Mer",
    "addr:housenumber":"305",
    "addr:postcode":"13300",
    "addr:street":"All De Craponne",
    "iso:country":"FR",
    "sg:address":"305 All De Craponne 13300 Salon De Provence",
    "sg:classifiers":[
        {
            "category":"Wholesale",
            "subcategory":"Medical Equipment & Supplies",
            "type":"Manufacturing & Wholesale Goods"
        }
    ],
    "sg:phone":"+33 4 90 44 60 60",
    "sg:province":"Outre-Mer",
    "sg:tags":[
        "instrument",
        "health",
        "-",
        "precision"
    ],
    "wof:name":"Biotech International Sarl",
    "wof:placetype":"venue"
},
  "geometry": {"coordinates":[5.099575,43.635853],"type":"Point"}
}