{
  "type": "Feature",
  "properties": {
    "addr:full":"29, Rue Legrand, 94120 Fontenay sous Bois Ile de France",
    "addr:housenumber":"29",
    "addr:postcode":"94120",
    "addr:street":"Rue Legrand;Bois Ile De France",
    "iso:country":"FR",
    "sg:address":"29, Rue Legrand, 94120 Fontenay sous Bois",
    "sg:orig_category":"Non-Classified Establishments",
    "sg:phone":"+33 1 48 75 38 07",
    "sg:province":"Ile de France",
    "wof:name":"Fish Eye Technologies S.a.",
    "wof:placetype":"venue"
},
  "geometry": {"coordinates":[2.473244,48.842743],"type":"Point"}
}