{
  "type": "Feature",
  "properties": {
    "addr:full":"B.P. 12, 67170 Brumath^^180, Av de Strasbourg, 67170 Brumath Brumath Alsace 67170",
    "addr:postcode":"67170;67170;67170",
    "addr:street":"B.P. 12;Av De Strasbourg",
    "iso:country":"FR",
    "sg:address":"B.P. 12, 67170 Brumath^^180, Av de Strasbourg, 67170 Brumath",
    "sg:city":"Brumath",
    "sg:orig_category":"Non-Classified Establishments",
    "sg:phone":"+33 3 88 51 83 11",
    "sg:postcode":"67170",
    "sg:province":"Alsace",
    "wof:name":"Beil Nicolas S.a.",
    "wof:placetype":"venue"
},
  "geometry": {"coordinates":[7.710455,48.730267],"type":"Point"}
}