{
  "type": "Feature",
  "properties": {
    "addr:full":"355, Rue Victor Hugo - Parc Bertel n\u00b017, 76300 Sotteville Les Rouen Haute Normandie",
    "addr:housenumber":"355",
    "addr:postcode":"76300",
    "addr:street":"Rue Victor Hugo Parc Bertel N\u00b017;Haute Normandie",
    "iso:country":"FR",
    "sg:address":"355, Rue Victor Hugo - Parc Bertel n\u00b017, 76300 Sotteville Les Rouen",
    "sg:orig_category":"Unclassifiable Establishments",
    "sg:phone":"+33 2 35 03 22 60",
    "sg:province":"Haute Normandie",
    "wof:name":"S. N. I. F. S. S.a.r.l. - Soci\u00e9t\u00e9 Normande D'impression De Flocage Et S\u00e9rigraphie",
    "wof:placetype":"venue"
},
  "geometry": {"coordinates":[1.09781,49.408909],"type":"Point"}
}