{
  "type": "Feature",
  "properties": {
    "addr:full":"Lieu Dit Le Villard 38380 Miribel Les Echelles Rhone-Alpes 38380",
    "addr:postcode":"38380;38380",
    "addr:street":"Lieu Dit Le Villard;Rhone-Alpes",
    "iso:country":"FR",
    "sg:address":"Lieu Dit Le Villard 38380 Miribel Les Echelles",
    "sg:classifiers":[
        {
            "category":"Home & Garden",
            "subcategory":"Furniture",
            "type":"Retail Goods"
        }
    ],
    "sg:phone":"+33 4 76 55 41 61",
    "sg:postcode":"38380",
    "sg:province":"Rhone-Alpes",
    "sg:tags":[
        "household",
        "wood"
    ],
    "wof:name":"Eugene De Guiers",
    "wof:placetype":"venue"
},
  "geometry": {"coordinates":[5.710903,45.433544],"type":"Point"}
}