{
  "type": "Feature",
  "properties": {
    "addr:full":"37 av F Delano Roosevelt 75008 Paris Ile de France",
    "addr:postcode":"75008",
    "addr:street":"37 Av F Delano Roosevelt",
    "iso:country":"FR",
    "sg:address":"37 av F Delano Roosevelt 75008 Paris",
    "sg:classifiers":[
        {
            "category":"Real Estate",
            "subcategory":"Real Estate Services",
            "type":"Services"
        }
    ],
    "sg:phone":"+33 1 53 93 99 53",
    "sg:province":"Ile de France",
    "sg:tags":[
        "patent"
    ],
    "wof:name":"Cabinet De Boisse Et Colas Sc",
    "wof:placetype":"venue"
},
  "geometry": {"coordinates":[2.30973,48.86776],"type":"Point"}
}