{
  "type": "Feature",
  "properties": {
    "addr:full":"Chemin de Taffignon Chaponost Rhone-Alpes 69630",
    "addr:postcode":"69630",
    "addr:street":"Chemin De Taffignon;Rhone-Alpes",
    "iso:country":"FR",
    "sg:address":"Chemin de Taffignon",
    "sg:city":"Chaponost",
    "sg:orig_category":"Unclassifiable Establishments",
    "sg:phone":"+33 4 78 51 93 88",
    "sg:postcode":"69630",
    "sg:province":"Rhone-Alpes",
    "wof:name":"Soberco Environnement S.a.r.l.",
    "wof:placetype":"venue"
},
  "geometry": {"coordinates":[4.775475,45.72575],"type":"Point"}
}