{
  "type": "Feature",
  "properties": {
    "addr:full":"Morlaix 29204 Morlaix Nord Pas-de-Calais",
    "addr:postcode":"29204",
    "iso:country":"FR",
    "sg:address":"Morlaix 29204 Morlaix",
    "sg:classifiers":[
        {
            "category":"Taxi",
            "type":"Transportation"
        }
    ],
    "sg:phone":"+33 2 98 62 10 22",
    "sg:province":"Nord Pas-de-Calais",
    "sg:tags":[
        "air"
    ],
    "wof:name":"Brit Air S.a.",
    "wof:placetype":"venue"
},
  "geometry": {"coordinates":[-3.82755,48.576969],"type":"Point"}
}