{
  "type": "Feature",
  "properties": {
    "iso:country":"FR",
    "sg:address":"6, Av. de Louisiane - ZI du Fontanil, 38120 Saint Egr\u00e8ve",
    "sg:orig_category":"Unclassifiable Establishments",
    "sg:phone":"+33 4 76 75 68 68",
    "sg:province":"Rhone-Alpes",
    "wof:name":"M\u00e9tallogravure Dauphinoise S.a.",
    "wof:placetype":"venue"
},
  "geometry": {"coordinates":[5.68088,45.232937],"type":"Point"}
}