{
  "type": "Feature",
  "properties": {
    "addr:full":"B.P. 238, 74942 Annecy le Vieux C\u00e9dex^^PAE Les Glaisins, 74940 Annecy le Vieux Rhone-Alpes",
    "addr:housenumber":"b.p. 238",
    "addr:postcode":"74942;74940",
    "iso:country":"FR",
    "sg:address":"B.P. 238, 74942 Annecy le Vieux C\u00e9dex^^PAE Les Glaisins, 74940 Annecy le Vieux",
    "sg:orig_category":"Non-Classified Establishments",
    "sg:phone":"+33 4 50 33 30 30",
    "sg:province":"Rhone-Alpes",
    "wof:name":"Sopra S.a.",
    "wof:placetype":"venue"
},
  "geometry": {"coordinates":[6.142605,45.919136],"type":"Point"}
}