{
  "type": "Feature",
  "properties": {
    "addr:full":"29, Rue Cl\u00e9menceau, 57440 Algrange Lorraine",
    "addr:housenumber":"29",
    "addr:postcode":"57440",
    "addr:street":"Rue Cle\u0301Menceau",
    "iso:country":"FR",
    "sg:address":"29, Rue Cl\u00e9menceau, 57440 Algrange",
    "sg:orig_category":"TRANSFORMATION DE MATI\u00c8RES PLASTIQUES AUTOMOBILE, \u00c9LECTRO-M\u00c9NAGER, CONNECTIQUE",
    "sg:phone":"+33 3 82 84 19 58",
    "sg:province":"Lorraine",
    "wof:name":"Afialor S.a.r.l.",
    "wof:placetype":"venue"
},
  "geometry": {"coordinates":[6.042466,49.353275],"type":"Point"}
}