{
  "type": "Feature",
  "properties": {
    "addr:full":"Chemin de l'Avenue Bi\u00e9ville Beuville Basse Normandie 14112",
    "addr:postcode":"14112",
    "addr:street":"Chemin De L'Avenue",
    "iso:country":"FR",
    "sg:address":"Chemin de l'Avenue",
    "sg:city":"Bi\u00e9ville Beuville",
    "sg:orig_category":"Unclassifiable Establishments",
    "sg:phone":"+33 2 31 43 73 93",
    "sg:postcode":"14112",
    "sg:province":"Basse Normandie",
    "wof:name":"Technir\u00e9al 14 S.a.",
    "wof:placetype":"venue"
},
  "geometry": {"coordinates":[-0.32683,49.23885],"type":"Point"}
}