{
  "type": "Feature",
  "properties": {
    "iso:country":"FR",
    "sg:address":"26, Quai Saint Vincent, 69001 Lyon",
    "sg:orig_category":"Non-Classified Establishments",
    "sg:phone":"+33 4 78 39 40 40",
    "sg:province":"Rhone-Alpes",
    "wof:name":"Pierre Baccara S.a.",
    "wof:placetype":"venue"
},
  "geometry": {"coordinates":[4.822492,45.768513],"type":"Point"}
}