{
  "type": "Feature",
  "properties": {
    "iso:country":"FR",
    "sg:address":"44, Rue Constant Ragot, 41110 Saint Aignan",
    "sg:city":"Ch\u00e2teauvieux",
    "sg:orig_category":"Non-Classified Establishments",
    "sg:phone":"+33 2 54 75 22 08",
    "sg:postcode":"41110",
    "sg:province":"Centre",
    "wof:name":"Marbrerie Moderne S.a.r.l.",
    "wof:placetype":"venue"
},
  "geometry": {"coordinates":[1.37298,47.268978],"type":"Point"}
}