{
  "type": "Feature",
  "properties": {
    "iso:country":"FR",
    "sg:address":"25, Rue Mably, 33000 Bordeaux",
    "sg:city":"Bordeaux",
    "sg:orig_category":"Non-Classified Establishments",
    "sg:phone":"+33 5 56 81 76 03",
    "sg:postcode":"33000",
    "sg:province":"Aquitaine",
    "wof:name":"Garon Bonvalot S.a.",
    "wof:placetype":"venue"
},
  "geometry": {"coordinates":[-0.577582,44.8438],"type":"Point"}
}