{
  "type": "Feature",
  "properties": {
    "iso:country":"FR",
    "sg:address":"Route D\u00e9partementale 155 - CAER",
    "sg:city":"Normanville",
    "sg:orig_category":"Unclassifiable Establishments",
    "sg:phone":"+33 2 32 62 21 20",
    "sg:postcode":"27930",
    "sg:province":"Haute Normandie",
    "wof:name":"Vecteur Scan S.a.r.l.",
    "wof:placetype":"venue"
},
  "geometry": {"coordinates":[1.17113,48.963875],"type":"Point"}
}