{
  "type": "Feature",
  "properties": {
    "addr:full":"73 Avenue Du Douard Zi Les Paluds 13685 Aubagne Cedex",
    "addr:housenumber":"73",
    "addr:postcode":"13685",
    "addr:street":"Avenue Du Douard Zi Les Paluds",
    "iso:country":"FR",
    "sg:address":"73 Avenue Du Douard Zi Les Paluds 13685 Aubagne Cedex",
    "sg:classifiers":[
        {
            "category":"Wholesale",
            "subcategory":"Drugs",
            "type":"Manufacturing & Wholesale Goods"
        }
    ],
    "sg:phone":"+33 4 42 82 16 95",
    "sg:tags":[
        "chemical",
        "pharmaceutical"
    ],
    "wof:name":"Arcane Industries",
    "wof:placetype":"venue"
},
  "geometry": {"coordinates":[5.57028,43.293251],"type":"Point"}
}