{
  "type": "Feature",
  "properties": {
    "addr:full":"70 rue Lemercier Paris 75017",
    "addr:housenumber":"70",
    "addr:postcode":"75017",
    "addr:street":"Rue Lemercier",
    "iso:country":"FR",
    "sg:address":"70 rue Lemercier",
    "sg:city":"Paris",
    "sg:classifiers":[
        {
            "category":"Professional",
            "subcategory":"Computer Services",
            "type":"Services"
        }
    ],
    "sg:postcode":"75017",
    "sg:tags":[
        "forecasting",
        "statistics",
        "forecasts",
        "cloud-computing",
        "analytics",
        "demand",
        "sales",
        "safety-stock",
        "inventory",
        "optimization"
    ],
    "sg:website":"http://www.lokad.com",
    "wof:name":"Lokad",
    "wof:placetype":"venue"
},
  "geometry": {"coordinates":[2.321084,48.888086],"type":"Point"}
}