{
  "type": "Feature",
  "properties": {
    "addr:full":"36, Rue Laurent Troutet, 25560 Bannans Franche Comt\u00e9",
    "addr:housenumber":"36",
    "addr:postcode":"25560",
    "addr:street":"Rue Laurent Troutet;Franche Comte\u0301",
    "iso:country":"FR",
    "sg:address":"36, Rue Laurent Troutet, 25560 Bannans",
    "sg:orig_category":"Non-Classified Establishments",
    "sg:phone":"+33 3 81 89 81 00",
    "sg:province":"Franche Comt\u00e9",
    "wof:name":"Les Monts De Joux",
    "wof:placetype":"venue"
},
  "geometry": {"coordinates":[6.237483,46.885082],"type":"Point"}
}