{
  "type": "Feature",
  "properties": {
    "addr:full":"69 Boulevard Victor Hugo 93400 St Ouen Ile de France 93400",
    "addr:housenumber":"69",
    "addr:postcode":"93400;93400",
    "addr:street":"Boulevard Victor Hugo;St;Ile De France",
    "iso:country":"FR",
    "sg:address":"69 Boulevard Victor Hugo 93400 St Ouen",
    "sg:classifiers":[
        {
            "category":"Manufacturing",
            "subcategory":"Chemicals & Compounds",
            "type":"Manufacturing & Wholesale Goods"
        }
    ],
    "sg:phone":"+33 1 49 18 14 30",
    "sg:postcode":"93400",
    "sg:province":"Ile de France",
    "sg:tags":[
        "pharmaceutical",
        "chemistry",
        "-",
        "by-product"
    ],
    "wof:name":"Laboratoires Roche Nicholas Sa (lrn)",
    "wof:placetype":"venue"
},
  "geometry": {"coordinates":[2.329164,48.908897],"type":"Point"}
}