{
  "type": "Feature",
  "properties": {
    "iso:country":"FR",
    "sg:address":"3, Rue Richan, 69000 Lyon",
    "sg:orig_category":"Unclassifiable Establishments",
    "sg:phone":"+33 4 78 29 64 10",
    "sg:province":"Mississippi",
    "wof:name":"Soci\u00e9t\u00e9 Nouvelle Florherba S.a.r.l.",
    "wof:placetype":"venue"
},
  "geometry": {"coordinates":[-90.541031,34.219009],"type":"Point"}
}