{
  "type": "Feature",
  "properties": {
    "iso:country":"FR",
    "sg:address":"Chemin De Loretto Imm Pozzo Di Borgo 20090 Ajaccio",
    "sg:classifiers":[
        {
            "category":"Farming",
            "subcategory":"Livestock Farm",
            "type":"Manufacturing & Wholesale Goods"
        }
    ],
    "sg:phone":"+33 4 95 10 04 44",
    "sg:postcode":"20090",
    "sg:province":"Corse",
    "sg:tags":[
        "breeding",
        "agriculture",
        "animal"
    ],
    "wof:name":"L'insulaire De Distribution Express Alimentaire Frais (l'ideal Frais)",
    "wof:placetype":"venue"
},
  "geometry": {"coordinates":[8.730585,41.930866],"type":"Point"}
}