{
  "type": "Feature",
  "properties": {
    "addr:full":"B.P. 3, 52290 Eclaron Braucourt Sainte Livi\u00e8re^^Rue d'Humbecourt, 52290 Eclaron Braucourt Sainte Liv Champagne 52290",
    "addr:housenumber":"3",
    "addr:postcode":"52290;52290;52290",
    "addr:street":"B.P.;D'Humbecourt;Champagne",
    "iso:country":"FR",
    "sg:address":"B.P. 3, 52290 Eclaron Braucourt Sainte Livi\u00e8re^^Rue d'Humbecourt, 52290 Eclaron Braucourt Sainte Liv",
    "sg:orig_category":"Non-Classified Establishments",
    "sg:phone":"+33 3 25 04 10 03",
    "sg:postcode":"52290",
    "sg:province":"Champagne",
    "wof:name":"Coop\u00e9rative Agricole De Distillerie Et De D\u00e9shydratation D'eclaron",
    "wof:placetype":"venue"
},
  "geometry": {"coordinates":[4.880656,48.585522],"type":"Point"}
}