{
  "type": "Feature",
  "properties": {
    "addr:full":"Le Vieux Bourg 69460 Odenas Rhone-Alpes 69460",
    "addr:postcode":"69460;69460",
    "addr:street":"Le Vieux Bourg;Rhone-Alpes",
    "iso:country":"FR",
    "sg:address":"Le Vieux Bourg 69460 Odenas",
    "sg:classifiers":[
        {
            "category":"Food Court",
            "type":"Food & Drink"
        }
    ],
    "sg:phone":"+33 4 74 03 40 87",
    "sg:postcode":"69460",
    "sg:province":"Rhone-Alpes",
    "sg:tags":[
        "product",
        "related"
    ],
    "wof:name":"Domaine Benoit Trichard Earl",
    "wof:placetype":"venue"
},
  "geometry": {"coordinates":[4.642184,46.088158],"type":"Point"}
}