{
  "type": "Feature",
  "properties": {
    "addr:full":"B.P. 5211, 31079 Toulouse C\u00e9dex 5^^135, Rue de P\u00e9riole, 31500 Toulouse Midi Pyr\u00e9n\u00e9es",
    "addr:housenumber":"5;^ 135",
    "addr:postcode":"31079;31500",
    "addr:street":"B.P. 5211;^;Rue De Pe\u0301Riole",
    "iso:country":"FR",
    "sg:address":"B.P. 5211, 31079 Toulouse C\u00e9dex 5^^135, Rue de P\u00e9riole, 31500 Toulouse",
    "sg:orig_category":"Non-Classified Establishments",
    "sg:phone":"+33 5 61 58 77 00",
    "sg:province":"Midi Pyr\u00e9n\u00e9es",
    "wof:name":"Soci\u00e9t\u00e9 Lat\u00e9co\u00e8re S.a.",
    "wof:placetype":"venue"
},
  "geometry": {"coordinates":[1.47517,43.60207],"type":"Point"}
}