{
  "type": "Feature",
  "properties": {
    "addr:full":"Le Village 34980 Combaillaux Languedoc-Roussillon",
    "addr:postcode":"34980",
    "addr:street":"Le Village",
    "iso:country":"FR",
    "sg:address":"Le Village 34980 Combaillaux",
    "sg:orig_category":"Unclassifiable Establishments",
    "sg:phone":"+33 4 67 84 19 00",
    "sg:province":"Languedoc-Roussillon",
    "wof:name":"Carri\u00e8res De La Madeleine S.a.",
    "wof:placetype":"venue"
},
  "geometry": {"coordinates":[3.806955,43.69313],"type":"Point"}
}