{
  "type": "Feature",
  "properties": {
    "iso:country":"FR",
    "sg:address":"8 rue du Caire 75002 Paris",
    "sg:classifiers":[
        {
            "category":"Shopping",
            "subcategory":"Clothing, Apparel, & Fashions",
            "type":"Retail Goods"
        }
    ],
    "sg:phone":"+33 1 42 33 55 45",
    "sg:postcode":"75002",
    "sg:province":"Ile de France",
    "sg:tags":[
        "blouse",
        "ladies'",
        "dress"
    ],
    "wof:name":"Loumy Diffusion S.a.r.l.",
    "wof:placetype":"venue"
},
  "geometry": {"coordinates":[2.352358,48.867317],"type":"Point"}
}