{
  "type": "Feature",
  "properties": {
    "iso:country":"FR",
    "sg:address":"39, Av. des 3 Peuples, 78180 Montigny le Bretonneux",
    "sg:orig_category":"Non-Classified Establishments",
    "sg:phone":"+33 1 30 64 81 00",
    "sg:province":"Ile de France",
    "wof:name":"Timeplex S.a.",
    "wof:placetype":"venue"
},
  "geometry": {"coordinates":[2.024615,48.778194],"type":"Point"}
}