{
  "type": "Feature",
  "properties": {
    "iso:country":"FR",
    "sg:address":"5, All\u00e9e des Magnolias, 72000 Le Mans",
    "sg:orig_category":"Non-Classified Establishments",
    "sg:phone":"+33 2 43 86 05 47",
    "sg:province":"Pays de Loire",
    "wof:name":"S\u00e9curitas S.a.r.l.",
    "wof:placetype":"venue"
},
  "geometry": {"coordinates":[0.19882,47.989437],"type":"Point"}
}