{
  "type": "Feature",
  "properties": {
    "addr:full":"B.P. 161, 63204 Riom C\u00e9dex^^Rue de l'Amb\u00e8ne, 63200 Riom Riom Auvergne 63200",
    "addr:housenumber":"b.p. 161",
    "addr:postcode":"63204;63200;63200",
    "addr:street":"\u0300Ne",
    "iso:country":"FR",
    "sg:address":"B.P. 161, 63204 Riom C\u00e9dex^^Rue de l'Amb\u00e8ne, 63200 Riom",
    "sg:city":"Riom",
    "sg:orig_category":"Non-Classified Establishments",
    "sg:phone":"+33 4 73 64 44 32",
    "sg:postcode":"63200",
    "sg:province":"Auvergne",
    "wof:name":"M\u00e9catronic S.a.",
    "wof:placetype":"venue"
},
  "geometry": {"coordinates":[3.12598,45.889454],"type":"Point"}
}