{
  "type": "Feature",
  "properties": {
    "iso:country":"FR",
    "sg:address":"Rue Pierre et Marie Curie - ZI du Haut Coudray",
    "sg:city":"Montreuil Juign\u00e9",
    "sg:orig_category":"Unclassifiable Establishments",
    "sg:phone":"+33 2 41 31 13 00",
    "sg:postcode":"49460",
    "sg:province":"Pays de Loire",
    "wof:name":"Etablissements Adrien S.a.",
    "wof:placetype":"venue"
},
  "geometry": {"coordinates":[-0.611961,47.52935],"type":"Point"}
}