{
  "type": "Feature",
  "properties": {
    "addr:full":"route de Saint Sauveur 60410 Verberie Picardie 60410",
    "addr:postcode":"60410;60410",
    "addr:street":"Route De Saint Sauveur;Picardie",
    "iso:country":"FR",
    "sg:address":"route de Saint Sauveur 60410 Verberie",
    "sg:classifiers":[
        {
            "category":"Building & Trades",
            "subcategory":"Construction",
            "type":"Services"
        }
    ],
    "sg:phone":"+33 3 44 38 50 50",
    "sg:postcode":"60410",
    "sg:province":"Picardie",
    "sg:tags":[
        "machine",
        "hiring"
    ],
    "wof:name":"I.c.e. France S.a.r.l.",
    "wof:placetype":"venue"
},
  "geometry": {"coordinates":[2.749547,49.320465],"type":"Point"}
}