{
  "type": "Feature",
  "properties": {
    "addr:full":"68, Av Antoine de Saint Exup\u00e9ry, 62100 Calais Nord Pas-de-Calais",
    "addr:postcode":"62100",
    "addr:street":"68 Av Antoine De Saint Exupe\u0301Ry;Calais;Pas-De-Calais",
    "iso:country":"FR",
    "sg:address":"68, Av Antoine de Saint Exup\u00e9ry, 62100 Calais",
    "sg:orig_category":"Unclassifiable Establishments",
    "sg:phone":"+33 3 21 97 32 99",
    "sg:province":"Nord Pas-de-Calais",
    "wof:name":"Gilbert S.a.r.l.",
    "wof:placetype":"venue"
},
  "geometry": {"coordinates":[1.892404,50.946136],"type":"Point"}
}