{
  "type": "Feature",
  "properties": {
    "addr:full":"15 All De La Fosse Maussoin 93390 Clichy Sous Bois Ile de France 93390",
    "addr:housenumber":"15",
    "addr:postcode":"93390;93390",
    "addr:street":"All De La Fosse Maussoin;Bois Ile De France",
    "iso:country":"FR",
    "sg:address":"15 All De La Fosse Maussoin 93390 Clichy Sous Bois",
    "sg:classifiers":[
        {
            "category":"Food & Beverages",
            "subcategory":"Fruits & Vegetables",
            "type":"Retail Goods"
        }
    ],
    "sg:phone":"+33 1 43 01 00 19",
    "sg:postcode":"93390",
    "sg:province":"Ile de France",
    "sg:tags":[
        "frozen",
        "product",
        "related"
    ],
    "wof:name":"Singly Sarl",
    "wof:placetype":"venue"
},
  "geometry": {"coordinates":[2.532131,48.906441],"type":"Point"}
}