{
  "type": "Feature",
  "properties": {
    "iso:country":"FR",
    "sg:address":"10, Rue Amp\u00e9re, 45800 Saint Jean de Braye",
    "sg:city":"Combleux",
    "sg:orig_category":"Unclassifiable Establishments",
    "sg:phone":"+33 2 38 61 50 78",
    "sg:postcode":"45800",
    "sg:province":"Centre",
    "wof:name":"Ctc Industrie S.a.r.l.",
    "wof:placetype":"venue"
},
  "geometry": {"coordinates":[1.948341,47.916752],"type":"Point"}
}