{
  "type": "Feature",
  "properties": {
    "addr:full":"B.P. 154, 59303 Valenciennes C\u00e9dex^^166, Av de Denain, 59300 Valenciennes Nord Pas-de-Calais",
    "addr:housenumber":"b.p. 154",
    "addr:postcode":"59303;59300",
    "addr:street":"Av De Denain",
    "iso:country":"FR",
    "sg:address":"B.P. 154, 59303 Valenciennes C\u00e9dex^^166, Av de Denain, 59300 Valenciennes",
    "sg:orig_category":"Non-Classified Establishments",
    "sg:phone":"+33 3 27 46 40 00",
    "sg:province":"Nord Pas-de-Calais",
    "wof:name":"Sergeant 59 S.a.",
    "wof:placetype":"venue"
},
  "geometry": {"coordinates":[3.524105,50.358494],"type":"Point"}
}