{
  "type": "Feature",
  "properties": {
    "addr:full":"10, Av Albert Raimond, 42270 Saint Priest en Jarez Rhone-Alpes",
    "addr:postcode":"42270",
    "addr:street":"10 Av Albert Raimond;Priest",
    "iso:country":"FR",
    "sg:address":"10, Av Albert Raimond, 42270 Saint Priest en Jarez",
    "sg:orig_category":"Unclassifiable Establishments",
    "sg:phone":"+33 4 77 74 48 01",
    "sg:province":"Rhone-Alpes",
    "wof:name":"Pacte S\u00e9curit\u00e9 S.a.",
    "wof:placetype":"venue"
},
  "geometry": {"coordinates":[4.377378,45.468517],"type":"Point"}
}