{
  "type": "Feature",
  "properties": {
    "iso:country":"FR",
    "sg:address":"87380 Meuzac",
    "sg:orig_category":"Unclassifiable Establishments",
    "sg:phone":"+33 5 55 09 97 03",
    "sg:province":"Limousin",
    "wof:name":"Minerva Oil S.a.r.l.",
    "wof:placetype":"venue"
},
  "geometry": {"coordinates":[1.4396,45.552769],"type":"Point"}
}