{
  "type": "Feature",
  "properties": {
    "addr:full":"Le Chatard 42370 Saint Alban les Eaux Rhone-Alpes",
    "addr:postcode":"42370",
    "iso:country":"FR",
    "sg:address":"Le Chatard 42370 Saint Alban les Eaux",
    "sg:orig_category":"Non-Classified Establishments",
    "sg:phone":"+33 4 77 66 42 50",
    "sg:province":"Rhone-Alpes",
    "wof:name":"Saint Alban Boissons S.a.",
    "wof:placetype":"venue"
},
  "geometry": {"coordinates":[3.950901,46.018482],"type":"Point"}
}