{
  "type": "Feature",
  "properties": {
    "addr:full":"24 Rue Danton 59160 Lomme Nord Pas-de-Calais 59160",
    "addr:housenumber":"24",
    "addr:postcode":"59160;59160",
    "addr:street":"Rue Danton",
    "iso:country":"FR",
    "sg:address":"24 Rue Danton 59160 Lomme",
    "sg:classifiers":[
        {
            "category":"Manufacturing",
            "subcategory":"Metals",
            "type":"Manufacturing & Wholesale Goods"
        }
    ],
    "sg:phone":"+33 3 20 93 06 60",
    "sg:postcode":"59160",
    "sg:province":"Nord Pas-de-Calais",
    "sg:tags":[
        "-",
        "machine",
        "equipment",
        "engineering",
        "machinery",
        "mechanical"
    ],
    "wof:name":"Aluconfort",
    "wof:placetype":"venue"
},
  "geometry": {"coordinates":[3.005442,50.648048],"type":"Point"}
}