{
  "type": "Feature",
  "properties": {
    "iso:country":"FR",
    "sg:address":"B.P. 20627, 60206 Compi\u00e8gne C\u00e9dex^^18, Rue de la Glaci\u00e8re, 60200 Compi\u00e8gne",
    "sg:orig_category":"Non-Classified Establishments",
    "sg:phone":"+33 3 44 02 89 89",
    "sg:postcode":"60200",
    "sg:province":"Picardie",
    "wof:name":"A.f.p.a. Oise - Site De Compi\u00e8gne",
    "wof:placetype":"venue"
},
  "geometry": {"coordinates":[2.825,49.417671],"type":"Point"}
}