{
  "type": "Feature",
  "properties": {
    "iso:country":"FR",
    "sg:address":"15 rue St Maurice 54850 MESSEIN",
    "sg:classifiers":[
        {
            "category":"Real Estate",
            "subcategory":"Real Estate Services",
            "type":"Services"
        }
    ],
    "sg:phone":"+33 3 83 47 28 24",
    "sg:province":"Lorraine",
    "sg:tags":[
        "crustacean",
        "shellfish"
    ],
    "wof:name":"Schaller P\u00e8re Et Fils Sarl",
    "wof:placetype":"venue"
},
  "geometry": {"coordinates":[6.159235,48.609276],"type":"Point"}
}