{
  "type": "Feature",
  "properties": {
    "addr:full":"37, All\u00e9e des Erables, 33140 Cadaujac Cadaujac Aquitaine 33140",
    "addr:housenumber":"37",
    "addr:postcode":"33140;33140",
    "addr:street":"Alle\u0301E Des Erables",
    "iso:country":"FR",
    "sg:address":"37, All\u00e9e des Erables, 33140 Cadaujac",
    "sg:city":"Cadaujac",
    "sg:orig_category":"Non-Classified Establishments",
    "sg:phone":"+33 5 56 30 02 44",
    "sg:postcode":"33140",
    "sg:province":"Aquitaine",
    "wof:name":"Etablissement Lagrave S.a.",
    "wof:placetype":"venue"
},
  "geometry": {"coordinates":[-0.537702,44.739399],"type":"Point"}
}