{
  "type": "Feature",
  "properties": {
    "addr:full":"Zone Industrielle Est Rogerville Le Havre Haute Normandie 76600",
    "addr:postcode":"76600",
    "addr:street":"Zone Industrielle Est",
    "iso:country":"FR",
    "sg:address":"Zone Industrielle Est Rogerville",
    "sg:city":"Le Havre",
    "sg:orig_category":"Unclassifiable Establishments",
    "sg:phone":"+33 2 35 47 69 07",
    "sg:postcode":"76600",
    "sg:province":"Haute Normandie",
    "wof:name":"S.e.i. S.a. - Soci\u00e9t\u00e9 D'etudes Industrielles",
    "wof:placetype":"venue"
},
  "geometry": {"coordinates":[0.101405,49.493511],"type":"Point"}
}