{
  "type": "Feature",
  "properties": {
    "addr:full":"B.P. 11, 89144 Ligny le Ch\u00e2tel^^Av Noue Marou - ZA, 89144 Ligny le Ch\u00e2tel Ligny-le-Ch\u00e2tel Bourgogne 89144",
    "addr:postcode":"89144;89144;89144",
    "addr:street":"B.P. 11;Za;Bourgogne",
    "iso:country":"FR",
    "sg:address":"B.P. 11, 89144 Ligny le Ch\u00e2tel^^Av Noue Marou - ZA, 89144 Ligny le Ch\u00e2tel",
    "sg:city":"Ligny-le-Ch\u00e2tel",
    "sg:orig_category":"Non-Classified Establishments",
    "sg:phone":"+33 3 86 47 50 51",
    "sg:postcode":"89144",
    "sg:province":"Bourgogne",
    "wof:name":"A.m.p.l. S.a.r.l. - Atelier M\u00e9canique De Pr\u00e9cision De Ligny",
    "wof:placetype":"venue"
},
  "geometry": {"coordinates":[3.743643,47.895241],"type":"Point"}
}