{
  "type": "Feature",
  "properties": {
    "iso:country":"FR",
    "sg:address":"63, Av. Jean-Baptiste Lebas, 59100 Roubaix",
    "sg:orig_category":"Unclassifiable Establishments",
    "sg:phone":"+33 3 20 01 01 01",
    "sg:province":"Nord Pas-de-Calais",
    "wof:name":"Delplanque M. Et L. S.a.r.l.",
    "wof:placetype":"venue"
},
  "geometry": {"coordinates":[3.16941,50.693066],"type":"Point"}
}