{
  "type": "Feature",
  "properties": {
    "addr:full":"4, Av. du Mar\u00e9chal de Lattre de Tassigny, 25290 Ornans Franche Comt\u00e9",
    "addr:postcode":"25290",
    "addr:street":"Av. Du Mare\u0301Chal De Lattre De Tassigny;Franche Comte\u0301",
    "iso:country":"FR",
    "sg:address":"4, Av. du Mar\u00e9chal de Lattre de Tassigny, 25290 Ornans",
    "sg:orig_category":"Unclassifiable Establishments",
    "sg:phone":"+33 3 81 62 25 05",
    "sg:province":"Franche Comt\u00e9",
    "wof:name":"Doras Bouvet Ponsar S.a.",
    "wof:placetype":"venue"
},
  "geometry": {"coordinates":[6.129475,47.106297],"type":"Point"}
}