{
  "type": "Feature",
  "properties": {
    "addr:full":"30 Rue Boussingault 92726 Paris \u00cele-de-France",
    "addr:housenumber":"30",
    "addr:postcode":"92726",
    "addr:street":"Rue Boussingault",
    "iso:country":"FR",
    "sg:address":"30 Rue Boussingault 92726 Paris",
    "sg:classifiers":[
        {
            "category":"Manufacturing",
            "subcategory":"Printing",
            "type":"Manufacturing & Wholesale Goods"
        }
    ],
    "sg:phone":"+33 1 53 62 51 00",
    "sg:province":"\u00cele-de-France",
    "sg:tags":[
        "publishing"
    ],
    "wof:name":"Oberthur Card Systems",
    "wof:placetype":"venue"
},
  "geometry": {"coordinates":[2.344336,48.824471],"type":"Point"}
}