{
  "type": "Feature",
  "properties": {
    "addr:full":"9 Rue Edouard Devaux BP 190 62504 St Omer Centre",
    "addr:housenumber":"9;190",
    "addr:postcode":"62504",
    "addr:street":"Rue Edouard Devaux Bp",
    "iso:country":"FR",
    "sg:address":"9 Rue Edouard Devaux BP 190 62504 St Omer",
    "sg:classifiers":[
        {
            "category":"Food Court",
            "type":"Food & Drink"
        }
    ],
    "sg:phone":"+33 3 21 98 76 00",
    "sg:province":"Centre",
    "sg:tags":[
        "product",
        "related"
    ],
    "wof:name":"Brasserie De Saint Omer",
    "wof:placetype":"venue"
},
  "geometry": {"coordinates":[2.252753,50.753876],"type":"Point"}
}