{
  "type": "Feature",
  "properties": {
    "addr:full":"26 R De Meru 60730 Sainte Genevieve Picardie",
    "addr:housenumber":"26",
    "addr:postcode":"60730",
    "addr:street":"R De Meru;Genevieve",
    "iso:country":"FR",
    "sg:address":"26 R De Meru 60730 Sainte Genevieve",
    "sg:classifiers":[
        {
            "category":"Manufacturing",
            "subcategory":"Printing",
            "type":"Manufacturing & Wholesale Goods"
        }
    ],
    "sg:phone":"+33 3 44 08 60 01",
    "sg:province":"Picardie",
    "sg:tags":[
        "publishing"
    ],
    "wof:name":"M. Wagner Jean-pierre",
    "wof:placetype":"venue"
},
  "geometry": {"coordinates":[2.179429,49.290691],"type":"Point"}
}