{
  "type": "Feature",
  "properties": {
    "addr:full":"B.P. 3, 67215 Obernai C\u00e9dex^^132, Bd d'Europe - ZI, 67215 Obernai Obernai Alsace 67210",
    "addr:housenumber":"3",
    "addr:postcode":"67215;ce\u0301dex^^132;67215;67210",
    "addr:street":"B.P.;D'Europe Zi",
    "iso:country":"FR",
    "sg:address":"B.P. 3, 67215 Obernai C\u00e9dex^^132, Bd d'Europe - ZI, 67215 Obernai",
    "sg:city":"Obernai",
    "sg:orig_category":"Non-Classified Establishments",
    "sg:phone":"+33 3 88 49 50 50",
    "sg:postcode":"67210",
    "sg:province":"Alsace",
    "wof:name":"Hager Electro S.a.",
    "wof:placetype":"venue"
},
  "geometry": {"coordinates":[7.4547,48.476841],"type":"Point"}
}