{
  "type": "Feature",
  "properties": {
    "addr:full":"25 Rue Josue Hofer 68200 Mulhouse Mulhouse Alsace 68200",
    "addr:housenumber":"25",
    "addr:postcode":"68200;68200",
    "addr:street":"Rue Josue Hofer",
    "iso:country":"FR",
    "sg:address":"25 Rue Josue Hofer 68200 Mulhouse",
    "sg:city":"Mulhouse",
    "sg:classifiers":[
        {
            "category":"Utilities",
            "subcategory":"Telephone",
            "type":"Services"
        }
    ],
    "sg:phone":"+33 3 89 32 11 11",
    "sg:postcode":"68200",
    "sg:province":"Alsace",
    "sg:tags":[
        "electricity",
        "equipment",
        "electrical",
        "telecommunication",
        "electronic"
    ],
    "wof:name":"Spie Communication Est Sa",
    "wof:placetype":"venue"
},
  "geometry": {"coordinates":[7.313625,47.75634],"type":"Point"}
}