{
  "type": "Feature",
  "properties": {
    "addr:full":"La Colmini\u00e8re 45240 Sennely Sennely Centre 45240",
    "addr:housenumber":"sennely",
    "addr:postcode":"45240;45240",
    "iso:country":"FR",
    "sg:address":"La Colmini\u00e8re 45240 Sennely",
    "sg:city":"Sennely",
    "sg:classifiers":[
        {
            "category":"Home & Garden",
            "subcategory":"Furniture",
            "type":"Retail Goods"
        }
    ],
    "sg:phone":"+33 2 38 76 96 60",
    "sg:postcode":"45240",
    "sg:province":"Centre",
    "sg:tags":[
        "wood"
    ],
    "wof:name":"Cochain Mecabois Sa",
    "wof:placetype":"venue"
},
  "geometry": {"coordinates":[1.78052,47.683125],"type":"Point"}
}