{
  "type": "Feature",
  "properties": {
    "addr:full":"22 Rue Adrien R\u00e9gent 56370 Sarzeau Sarzeau Bretagne 56370",
    "addr:housenumber":"22",
    "addr:postcode":"56370;sarzeau;56370",
    "addr:street":"Rue Adrien Re\u0301Gent",
    "iso:country":"FR",
    "sg:address":"22 Rue Adrien R\u00e9gent 56370 Sarzeau",
    "sg:city":"Sarzeau",
    "sg:classifiers":[
        {
            "category":"Professional",
            "subcategory":"Business Services",
            "type":"Services"
        }
    ],
    "sg:phone":"+33 2 97 41 81 84",
    "sg:postcode":"56370",
    "sg:province":"Bretagne",
    "sg:tags":[
        "training",
        "advice"
    ],
    "wof:name":"College De Rhuys",
    "wof:placetype":"venue"
},
  "geometry": {"coordinates":[-2.764444,47.527416],"type":"Point"}
}