{
  "type": "Feature",
  "properties": {
    "iso:country":"FR",
    "sg:address":"2, Grande Rue, 90800 Bavilliers",
    "sg:orig_category":"Unclassifiable Establishments",
    "sg:phone":"+33 3 84 21 24 31",
    "sg:province":"Franche Comt\u00e9",
    "wof:name":"Chaudey Fr\u00e8res S.a.r.l.",
    "wof:placetype":"venue"
},
  "geometry": {"coordinates":[6.833895,47.620541],"type":"Point"}
}