{
  "type": "Feature",
  "properties": {
    "iso:country":"FR",
    "sg:address":"rue Clement Ader 57970 Yutz",
    "sg:classifiers":[
        {
            "category":"Ferry Terminal",
            "type":"Transportation"
        }
    ],
    "sg:phone":"+33 3 82 59 36 66",
    "sg:province":"Midi Pyr\u00e9n\u00e9es",
    "sg:tags":[
        "coil",
        "drawing"
    ],
    "wof:name":"Prosimo Sa",
    "wof:placetype":"venue"
},
  "geometry": {"coordinates":[6.215571,49.358986],"type":"Point"}
}