{
  "type": "Feature",
  "properties": {
    "addr:full":"17, Rue des Granges Galand, 37550 Saint Avertin Saint-Avertin Centre 37550",
    "addr:housenumber":"17;saint-avertin",
    "addr:postcode":"37550;37550",
    "addr:street":"Rue Des Granges Galand",
    "iso:country":"FR",
    "sg:address":"17, Rue des Granges Galand, 37550 Saint Avertin",
    "sg:city":"Saint-Avertin",
    "sg:orig_category":"Unclassifiable Establishments",
    "sg:phone":"+33 2 47 28 90 90",
    "sg:postcode":"37550",
    "sg:province":"Centre",
    "wof:name":"Espace B.d.l S.a.r.l.",
    "wof:placetype":"venue"
},
  "geometry": {"coordinates":[0.719918,47.368088],"type":"Point"}
}