{
  "type": "Feature",
  "properties": {
    "iso:country":"FR",
    "sg:address":"RD 12",
    "sg:city":"Ternay",
    "sg:orig_category":"Non-Classified Establishments",
    "sg:phone":"+33 4 37 20 13 01",
    "sg:postcode":"69360",
    "sg:province":"Rhone-Alpes",
    "wof:name":"Batinet S.a.r.l.",
    "wof:placetype":"venue"
},
  "geometry": {"coordinates":[4.856095,45.634987],"type":"Point"}
}