{
  "type": "Feature",
  "properties": {
    "iso:country":"FR",
    "sg:address":"50 Rue Du Gal De Gaulle 95880 Enghien Les Bains",
    "sg:classifiers":[
        {
            "category":"Manufacturing",
            "subcategory":"Jewelry",
            "type":"Manufacturing & Wholesale Goods"
        }
    ],
    "sg:phone":"+33 1 39 64 04 04",
    "sg:postcode":"95880",
    "sg:province":"Ile de France",
    "sg:tags":[
        "product",
        "miscellaneous",
        "jewellery"
    ],
    "wof:name":"Mb Creations Michel Barrial Creations",
    "wof:placetype":"venue"
},
  "geometry": {"coordinates":[2.305214,48.96946],"type":"Point"}
}