{
  "type": "Feature",
  "properties": {
    "addr:full":"Le Clapay 01250 Chavannes sur Suran Rhone-Alpes 01250",
    "addr:postcode":"01250;sur;01250",
    "addr:street":"Chavannes;Suran Rhone-Alpes",
    "iso:country":"FR",
    "sg:address":"Le Clapay 01250 Chavannes sur Suran",
    "sg:orig_category":"Non-Classified Establishments",
    "sg:phone":"+33 4 74 51 75 67",
    "sg:postcode":"01250",
    "sg:province":"Rhone-Alpes",
    "wof:name":"Entreprise Sommier Jean-luc",
    "wof:placetype":"venue"
},
  "geometry": {"coordinates":[5.36418,46.190819],"type":"Point"}
}