{
  "type": "Feature",
  "properties": {
    "iso:country":"FR",
    "sg:address":"rue Gaston Chevrolet 21200 Vignoles",
    "sg:city":"Vignoles",
    "sg:classifiers":[
        {
            "category":"Professional",
            "type":"Services"
        }
    ],
    "sg:phone":"+33 3 80 24 43 00",
    "sg:postcode":"21200",
    "sg:province":"Bourgogne",
    "sg:tags":[
        "transport"
    ],
    "wof:name":"Jf Hillebrand France S.a.",
    "wof:placetype":"venue"
},
  "geometry": {"coordinates":[4.865356,47.021843],"type":"Point"}
}