{
  "type": "Feature",
  "properties": {
    "iso:country":"FR",
    "sg:address":"9 R Curie 69006 Lyon",
    "sg:classifiers":[
        {
            "category":"Professional",
            "subcategory":"Engineering",
            "type":"Services"
        }
    ],
    "sg:phone":"+33 4 37 24 59 59",
    "sg:province":"Rhone-Alpes",
    "sg:tags":[
        "machine",
        "-",
        "environment",
        "equipment",
        "machinery",
        "mechanical"
    ],
    "wof:name":"Confort General Europeen",
    "wof:placetype":"venue"
},
  "geometry": {"coordinates":[4.859211,45.769516],"type":"Point"}
}