{
  "type": "Feature",
  "properties": {
    "addr:full":"route de Fort Mardyck 59640 Dunkerque Midi Pyr\u00e9n\u00e9es",
    "addr:postcode":"59640",
    "addr:street":"Route De Fort",
    "iso:country":"FR",
    "sg:address":"route de Fort Mardyck 59640 Dunkerque",
    "sg:orig_category":"Cements, Plastic",
    "sg:phone":"+33 3 28 62 74 00",
    "sg:province":"Midi Pyr\u00e9n\u00e9es",
    "wof:name":"Polimeri Europa France Sa",
    "wof:placetype":"venue"
},
  "geometry": {"coordinates":[2.30427,51.026711],"type":"Point"}
}