{
  "type": "Feature",
  "properties": {
    "addr:full":"16/18, Place de la Chapelle, 75018 Paris Ile de France",
    "addr:housenumber":"16 / 18",
    "addr:postcode":"75018",
    "addr:street":"Place De La Chapelle",
    "iso:country":"FR",
    "sg:address":"16/18, Place de la Chapelle, 75018 Paris",
    "sg:orig_category":"Non-Classified Establishments",
    "sg:phone":"+33 1 53 35 98 98",
    "sg:province":"Ile de France",
    "wof:name":"S.e.p.e Int\u00e9rim S.a.",
    "wof:placetype":"venue"
},
  "geometry": {"coordinates":[2.359713,48.884953],"type":"Point"}
}