{
  "type": "Feature",
  "properties": {
    "addr:full":"55, Av Charles de Gaulle, 08013 Charleville M\u00e9zi\u00e8res C\u00e9dex Champagne-Ardenne",
    "addr:postcode":"08013",
    "addr:street":"55 Av Charles De Gaulle",
    "iso:country":"FR",
    "sg:address":"55, Av Charles de Gaulle, 08013 Charleville M\u00e9zi\u00e8res C\u00e9dex",
    "sg:orig_category":"Unclassifiable Establishments",
    "sg:phone":"+33 3 24 33 42 89",
    "sg:province":"Champagne-Ardenne",
    "wof:name":"C.t.i.f. - Centre Technique Des Industries De La Fonderie",
    "wof:placetype":"venue"
},
  "geometry": {"coordinates":[4.715933,49.768002],"type":"Point"}
}