{
  "type": "Feature",
  "properties": {
    "iso:country":"FR",
    "sg:address":"16, Rte des forges, 55000 Haironville",
    "sg:orig_category":"Unclassifiable Establishments",
    "sg:phone":"+33 3 29 79 85 85",
    "sg:province":"Lorraine",
    "wof:name":"Haironville S.a.",
    "wof:placetype":"venue"
},
  "geometry": {"coordinates":[5.084741,48.685223],"type":"Point"}
}