{
  "type": "Feature",
  "properties": {
    "addr:full":"B.P. 3019, 59703 Marcq en Baroeul C\u00e9dex^^274, Bd Cl\u00e9menceau, 59700 Marcq en Baroeul Nord Pas-de-Calais",
    "addr:postcode":"59703;59700",
    "addr:street":"B.P. 3019;Bd Cle\u0301Menceau;En Baroeul Nord",
    "iso:country":"FR",
    "sg:address":"B.P. 3019, 59703 Marcq en Baroeul C\u00e9dex^^274, Bd Cl\u00e9menceau, 59700 Marcq en Baroeul",
    "sg:orig_category":"Non-Classified Establishments",
    "sg:phone":"+33 3 20 99 25 50",
    "sg:province":"Nord Pas-de-Calais",
    "wof:name":"Sogea Nord Ouest S.n.c.",
    "wof:placetype":"venue"
},
  "geometry": {"coordinates":[3.09404,50.673965],"type":"Point"}
}