{
  "type": "Feature",
  "properties": {
    "addr:full":"B.P. 83, 69682 Chassieu C\u00e9dex^^25, Rue des Fr\u00e8res Lumi\u00e8re, 69680 Chassieu Rhone-Alpes 69680",
    "addr:postcode":"69682;69680;69680",
    "addr:street":"B.P. 83;Rue Des Fre\u0300Res Lumie\u0300Re",
    "iso:country":"FR",
    "sg:address":"B.P. 83, 69682 Chassieu C\u00e9dex^^25, Rue des Fr\u00e8res Lumi\u00e8re, 69680 Chassieu",
    "sg:orig_category":"Non-Classified Establishments",
    "sg:phone":"+33 4 72 47 61 10",
    "sg:postcode":"69680",
    "sg:province":"Rhone-Alpes",
    "wof:name":"Bodycote Hit S.a.",
    "wof:placetype":"venue"
},
  "geometry": {"coordinates":[4.972185,45.743477],"type":"Point"}
}