{
  "type": "Feature",
  "properties": {
    "addr:full":"Zi De Chasnais 85407 Lu\u00e7on Auvergne",
    "addr:postcode":"85407",
    "addr:street":"Zi De Chasnais",
    "iso:country":"FR",
    "sg:address":"Zi De Chasnais 85407 Lu\u00e7on",
    "sg:classifiers":[
        {
            "category":"Home & Garden",
            "subcategory":"Furniture",
            "type":"Retail Goods"
        }
    ],
    "sg:phone":"+33 2 51 28 51 28",
    "sg:province":"Auvergne",
    "sg:tags":[
        "household",
        "wood"
    ],
    "wof:name":"Moderna France",
    "wof:placetype":"venue"
},
  "geometry": {"coordinates":[-1.166538,46.454948],"type":"Point"}
}