{
  "type": "Feature",
  "properties": {
    "addr:full":"Rue Jules Rozi\u00e8res 46270 BAGNAC SUR CELE Midi Pyr\u00e9n\u00e9es 46270",
    "addr:postcode":"46270;46270",
    "addr:street":"Rue Jules Rozie\u0300Res",
    "iso:country":"FR",
    "sg:address":"Rue Jules Rozi\u00e8res 46270 BAGNAC SUR CELE",
    "sg:orig_category":"Deep-Drawing, Hydromechanical",
    "sg:phone":"+33 5 65 34 95 50",
    "sg:postcode":"46270",
    "sg:province":"Midi Pyr\u00e9n\u00e9es",
    "wof:name":"Bourrel Jean Marie Sarl",
    "wof:placetype":"venue"
},
  "geometry": {"coordinates":[2.159808,44.666264],"type":"Point"}
}