{
  "type": "Feature",
  "properties": {
    "iso:country":"FR",
    "sg:address":"42, Rue Legendre, 75017 Paris",
    "sg:orig_category":"Non-Classified Establishments",
    "sg:phone":"+33 1 47 54 08 08",
    "sg:province":"Ile de France",
    "wof:name":"M\u00e9diasite S.a.r.l.",
    "wof:placetype":"venue"
},
  "geometry": {"coordinates":[2.31525,48.884567],"type":"Point"}
}