{
  "type": "Feature",
  "properties": {
    "addr:full":"270, Rte de Blanzy, 74460 Marnaz Rhone-Alpes",
    "addr:housenumber":"270",
    "addr:postcode":"74460",
    "addr:street":"Rte De Blanzy",
    "iso:country":"FR",
    "sg:address":"270, Rte de Blanzy, 74460 Marnaz",
    "sg:orig_category":"Non-Classified Establishments",
    "sg:phone":"+33 4 50 96 34 64",
    "sg:province":"Rhone-Alpes",
    "wof:name":"Peroem S.a.",
    "wof:placetype":"venue"
},
  "geometry": {"coordinates":[6.525887,46.056084],"type":"Point"}
}