{
  "type": "Feature",
  "properties": {
    "addr:full":"13 rue le Sueur 75116 Paris Haute Normandie",
    "addr:housenumber":"13",
    "addr:postcode":"75116",
    "addr:street":"Rue Le Sueur",
    "iso:country":"FR",
    "sg:address":"13 rue le Sueur 75116 Paris",
    "sg:classifiers":[
        {
            "category":"Social Services",
            "subcategory":"Job Training",
            "type":"Services"
        }
    ],
    "sg:phone":"+33 1 46 69 60 00",
    "sg:province":"Haute Normandie",
    "sg:tags":[
        "civil",
        "engineering",
        "laying",
        "cable"
    ],
    "wof:name":"Seco-dg Sa",
    "wof:placetype":"venue"
},
  "geometry": {"coordinates":[2.287274,48.87479],"type":"Point"}
}