{
  "type": "Feature",
  "properties": {
    "addr:full":"ZAC de Charm\u00e9 Ern\u00e9e Pays de Loire 53500",
    "addr:postcode":"53500",
    "addr:street":"Zac De Charme\u0301 Erne\u0301E Pays",
    "iso:country":"FR",
    "sg:address":"ZAC de Charm\u00e9",
    "sg:city":"Ern\u00e9e",
    "sg:orig_category":"Unclassifiable Establishments",
    "sg:phone":"+33 2 43 05 81 53",
    "sg:postcode":"53500",
    "sg:province":"Pays de Loire",
    "wof:name":"U.n.m. S.a. - Usinage Num\u00e9rique De La Mayenne",
    "wof:placetype":"venue"
},
  "geometry": {"coordinates":[-0.933511,48.296383],"type":"Point"}
}