{
  "type": "Feature",
  "properties": {
    "iso:country":"FR",
    "sg:address":"49 Bd Preuilly 37000 Tours",
    "sg:city":"Tours",
    "sg:classifiers":[
        {
            "category":"Manufacturing",
            "subcategory":"Printing",
            "type":"Manufacturing & Wholesale Goods"
        }
    ],
    "sg:phone":"+33 2 47 76 15 01",
    "sg:postcode":"37000",
    "sg:province":"Centre",
    "sg:tags":[
        "publishing"
    ],
    "wof:name":"Touraine Compo Ste Sarl",
    "wof:placetype":"venue"
},
  "geometry": {"coordinates":[0.66844,47.3922],"type":"Point"}
}