{
  "type": "Feature",
  "properties": {
    "addr:full":"5, Av. des Paquerettes, 06300 Nice",
    "addr:postcode":"06300",
    "addr:street":"Av. Des Paquerettes",
    "iso:country":"FR",
    "sg:address":"5, Av. des Paquerettes, 06300 Nice",
    "sg:orig_category":"Unclassifiable Establishments",
    "sg:phone":"+33 4 93 27 27 47",
    "wof:name":"L'eclat S.a.r.l.",
    "wof:placetype":"venue"
},
  "geometry": {"coordinates":[7.30535,43.737129],"type":"Point"}
}