{
  "type": "Feature",
  "properties": {
    "addr:full":"Verdoyer Za Du Verdoyer 87430 Verneuil Sur Vienne Limousin 87430",
    "addr:postcode":"87430;87430",
    "addr:street":"Za Du Verdoyer",
    "iso:country":"FR",
    "sg:address":"Verdoyer Za Du Verdoyer 87430 Verneuil Sur Vienne",
    "sg:classifiers":[
        {
            "category":"Wholesale",
            "subcategory":"Farm Supplies",
            "type":"Manufacturing & Wholesale Goods"
        }
    ],
    "sg:phone":"+33 5 55 48 48 00",
    "sg:postcode":"87430",
    "sg:province":"Limousin",
    "sg:tags":[
        "-",
        "machine",
        "equipment",
        "engineering",
        "machinery",
        "mechanical",
        "agriculture"
    ],
    "wof:name":"Renault Agriculture",
    "wof:placetype":"venue"
},
  "geometry": {"coordinates":[1.127005,45.848839],"type":"Point"}
}