{
  "type": "Feature",
  "properties": {
    "iso:country":"FR",
    "sg:address":"6 Bd De Verdun 02200 Soissons",
    "sg:classifiers":[
        {
            "category":"Social Services",
            "subcategory":"Job Training",
            "type":"Services"
        }
    ],
    "sg:phone":"+33 3 23 59 55 96",
    "sg:postcode":"02200",
    "sg:province":"Picardie",
    "sg:tags":[
        "good",
        "business",
        "advice",
        "-",
        "metalworking",
        "metallic",
        "metallurgy",
        "finished"
    ],
    "wof:name":"Brd Services",
    "wof:placetype":"venue"
},
  "geometry": {"coordinates":[3.336419,49.380894],"type":"Point"}
}