{
  "type": "Feature",
  "properties": {
    "addr:full":"7 Rue Du Bordelais BP 61 69802 St Priest Basse Normandie",
    "addr:housenumber":"7;61",
    "addr:postcode":"69802",
    "addr:street":"Rue Du Bordelais Bp",
    "iso:country":"FR",
    "sg:address":"7 Rue Du Bordelais BP 61 69802 St Priest",
    "sg:classifiers":[
        {
            "category":"Manufacturing",
            "subcategory":"Metals",
            "type":"Manufacturing & Wholesale Goods"
        }
    ],
    "sg:phone":"+33 4 72 23 23 23",
    "sg:province":"Basse Normandie",
    "sg:tags":[
        "metallurgy",
        "metalworking",
        "processing"
    ],
    "wof:name":"Jacquet Sa",
    "wof:placetype":"venue"
},
  "geometry": {"coordinates":[4.91891,45.697617],"type":"Point"}
}