{
  "type": "Feature",
  "properties": {
    "addr:full":"Rn 31 02290 Montigny Lengrain Picardie 02290",
    "addr:postcode":"02290;02290",
    "addr:street":"Rn 31",
    "iso:country":"FR",
    "sg:address":"Rn 31 02290 Montigny Lengrain",
    "sg:classifiers":[
        {
            "category":"Food & Beverages",
            "subcategory":"Groceries & Convenience Stores",
            "type":"Retail Goods"
        }
    ],
    "sg:phone":"+33 3 23 55 43 43",
    "sg:postcode":"02290",
    "sg:province":"Picardie",
    "sg:tags":[
        "product",
        "related"
    ],
    "wof:name":"Beau Marais Fraicheur D'europe",
    "wof:placetype":"venue"
},
  "geometry": {"coordinates":[3.16768,49.407619],"type":"Point"}
}