{
  "type": "Feature",
  "properties": {
    "addr:full":"Lieu-Dit La Friche Aux Moi Route De Pelinuc 35290 Le Crouais Le Crouais Bretagne 35290",
    "addr:housenumber":"crouais",
    "addr:postcode":"35290;35290",
    "addr:street":"Lieu-Dit La Friche Aux Moi Route De Pelinuc;Le Crouais Bretagne",
    "iso:country":"FR",
    "sg:address":"Lieu-Dit La Friche Aux Moi Route De Pelinuc 35290 Le Crouais",
    "sg:city":"Le Crouais",
    "sg:classifiers":[
        {
            "category":"Wholesale",
            "subcategory":"Machinery & Supplies",
            "type":"Manufacturing & Wholesale Goods"
        }
    ],
    "sg:phone":"+33 2 99 09 65 00",
    "sg:postcode":"35290",
    "sg:province":"Bretagne",
    "sg:tags":[
        "-",
        "machine",
        "equipment",
        "engineering",
        "animal",
        "mechanical",
        "breeding",
        "agriculture"
    ],
    "wof:name":"Piers Industries",
    "wof:placetype":"venue"
},
  "geometry": {"coordinates":[-2.157423,48.127377],"type":"Point"}
}