{
  "type": "Feature",
  "properties": {
    "addr:full":"B.P. 4, 59249 Aubers^^29, Rte du Mailly, 59249 Aubers Nord Pas-de-Calais",
    "addr:housenumber":"4",
    "addr:postcode":"59249;59249",
    "addr:street":"B.P.;Rte Du Mailly",
    "iso:country":"FR",
    "sg:address":"B.P. 4, 59249 Aubers^^29, Rte du Mailly, 59249 Aubers",
    "sg:orig_category":"Non-Classified Establishments",
    "sg:phone":"+33 3 20 50 21 60",
    "sg:province":"Nord Pas-de-Calais",
    "wof:name":"Leclercq Jean-marie S.a.",
    "wof:placetype":"venue"
},
  "geometry": {"coordinates":[2.824945,50.595493],"type":"Point"}
}