{
  "type": "Feature",
  "properties": {
    "iso:country":"FR",
    "sg:address":"Place Bayard",
    "sg:city":"Pontcharra",
    "sg:orig_category":"Unclassifiable Establishments",
    "sg:phone":"+33 4 76 97 64 64",
    "sg:postcode":"38530",
    "sg:province":"Rhone-Alpes",
    "wof:name":"Banque De Savoie",
    "wof:placetype":"venue"
},
  "geometry": {"coordinates":[6.02432,45.433128],"type":"Point"}
}