{
  "type": "Feature",
  "properties": {
    "addr:full":"Chauss\u00e9e de la Moselle Le Havre Haute Normandie 76600",
    "addr:postcode":"76600",
    "addr:street":"Chausse\u0301E De La Moselle",
    "iso:country":"FR",
    "sg:address":"Chauss\u00e9e de la Moselle",
    "sg:city":"Le Havre",
    "sg:orig_category":"Non-Classified Establishments",
    "sg:phone":"+33 2 35 25 78 78",
    "sg:postcode":"76600",
    "sg:province":"Haute Normandie",
    "wof:name":"G.s.l. S.a. - G\u00e9n\u00e9rale De Services Et De Logistique",
    "wof:placetype":"venue"
},
  "geometry": {"coordinates":[0.18113,49.491241],"type":"Point"}
}