{
  "type": "Feature",
  "properties": {
    "addr:full":"1029, Av de la Gironde, 59640 Dunkerque Midi Pyr\u00e9n\u00e9es",
    "addr:housenumber":"1029",
    "addr:postcode":"59640",
    "addr:street":"Av De La Gironde",
    "iso:country":"FR",
    "sg:address":"1029, Av de la Gironde, 59640 Dunkerque",
    "sg:orig_category":"Unclassifiable Establishments",
    "sg:phone":"+33 3 28 29 28 29",
    "sg:province":"Midi Pyr\u00e9n\u00e9es",
    "wof:name":"S.a.t.m. S.a. - Soci\u00e9t\u00e9 Auxiliaire De Transports Et Manutention",
    "wof:placetype":"venue"
},
  "geometry": {"coordinates":[2.344989,51.006371],"type":"Point"}
}