{
  "type": "Feature",
  "properties": {
    "addr:full":"18 Rue Des Bas Rogers 92800 Puteaux Ile de France 92800",
    "addr:housenumber":"18",
    "addr:postcode":"92800;92800",
    "addr:street":"Rue Des Bas Rogers",
    "iso:country":"FR",
    "sg:address":"18 Rue Des Bas Rogers 92800 Puteaux",
    "sg:classifiers":[
        {
            "category":"Professional",
            "subcategory":"Engineering",
            "type":"Services"
        }
    ],
    "sg:phone":"+33 1 41 38 89 00",
    "sg:postcode":"92800",
    "sg:province":"Ile de France",
    "sg:tags":[
        "machine",
        "-",
        "environment",
        "equipment",
        "machinery",
        "mechanical"
    ],
    "wof:name":"La Detection Electronique Francaise (def)",
    "wof:placetype":"venue"
},
  "geometry": {"coordinates":[2.234206,48.879902],"type":"Point"}
}