{
  "type": "Feature",
  "properties": {
    "iso:country":"FR",
    "sg:address":"8, Rue du B\u00e2timent d'Argent, 69001 Lyon",
    "sg:orig_category":"Unclassifiable Establishments",
    "sg:phone":"+33 4 72 19 22 23",
    "sg:province":"Rhone-Alpes",
    "wof:name":"Cirra S.a.",
    "wof:placetype":"venue"
},
  "geometry": {"coordinates":[4.83779,45.766296],"type":"Point"}
}