{
  "type": "Feature",
  "properties": {
    "addr:full":"23, Bd Poissonni\u00e8re, 75002 Paris Ile de France",
    "addr:housenumber":"23",
    "addr:postcode":"75002",
    "addr:street":"Bd Poissonnie\u0300Re",
    "iso:country":"FR",
    "sg:address":"23, Bd Poissonni\u00e8re, 75002 Paris",
    "sg:orig_category":"Unclassifiable Establishments",
    "sg:phone":"+33 1 42 21 49 66",
    "sg:province":"Ile de France",
    "wof:name":"America Center S.a.r.l.",
    "wof:placetype":"venue"
},
  "geometry": {"coordinates":[2.344098,48.871166],"type":"Point"}
}