{
  "type": "Feature",
  "properties": {
    "iso:country":"FR",
    "sg:address":"25, Av. L\u00e9onard de Vinci - Europarc, 33600 Pessac",
    "sg:city":"Pessac",
    "sg:orig_category":"Non-Classified Establishments",
    "sg:phone":"+33 5 57 89 17 40",
    "sg:postcode":"33600",
    "sg:province":"Aquitaine",
    "wof:name":"E.b.c. Informatique S.a.",
    "wof:placetype":"venue"
},
  "geometry": {"coordinates":[-0.630989,44.80616],"type":"Point"}
}