{
  "type": "Feature",
  "properties": {
    "iso:country":"FR",
    "sg:address":"5, Rue DMC - ZI du Pont d'Aspach, 68520 Burnhaupt le Haut",
    "sg:city":"Burnhaupt-le-Bas",
    "sg:orig_category":"Unclassifiable Establishments",
    "sg:phone":"+33 3 89 83 11 12",
    "sg:postcode":"68520",
    "sg:province":"Alsace",
    "wof:name":"Sopemod S.a.r.l.",
    "wof:placetype":"venue"
},
  "geometry": {"coordinates":[7.147247,47.740509],"type":"Point"}
}