{
  "type": "Feature",
  "properties": {
    "iso:country":"FR",
    "sg:address":"Rue Basly - Zone Industrielle",
    "sg:city":"Beuvry",
    "sg:orig_category":"Non-Classified Establishments",
    "sg:phone":"+33 3 21 65 13 66",
    "sg:postcode":"62660",
    "sg:province":"Nord Pas-de-Calais",
    "wof:name":"P.f.b. S.a. - Plastiques Fa\u00e7onn\u00e9s Du B\u00e9thunois",
    "wof:placetype":"venue"
},
  "geometry": {"coordinates":[2.682003,50.522648],"type":"Point"}
}