{
  "type": "Feature",
  "properties": {
    "iso:country":"FR",
    "sg:address":"Rue Edouard Branly Zi La Bouriette 11000 Carcassonne",
    "sg:classifiers":[
        {
            "category":"Food & Beverages",
            "subcategory":"Dairy",
            "type":"Retail Goods"
        }
    ],
    "sg:phone":"+33 4 68 11 46 50",
    "sg:postcode":"11000",
    "sg:province":"Languedoc-Roussillon",
    "sg:tags":[
        "product",
        "related"
    ],
    "wof:name":"Boncolac Sa",
    "wof:placetype":"venue"
},
  "geometry": {"coordinates":[2.306378,43.188465],"type":"Point"}
}