{
  "type": "Feature",
  "properties": {
    "iso:country":"FR",
    "sg:address":"2, Rue Pierrefitte, 41600 Chaon",
    "sg:city":"Chaon",
    "sg:orig_category":"Non-Classified Establishments",
    "sg:phone":"+33 2 54 88 44 26",
    "sg:postcode":"41600",
    "sg:province":"Centre",
    "wof:name":"Entreprise Foltier Et Fils S.a.r.l.",
    "wof:placetype":"venue"
},
  "geometry": {"coordinates":[2.171351,47.606846],"type":"Point"}
}