{
  "type": "Feature",
  "properties": {
    "iso:country":"FR",
    "sg:address":"Cit\u00e9 Moulin \u00e0 Papier",
    "sg:city":"Rugles",
    "sg:orig_category":"Unclassifiable Establishments",
    "sg:phone":"+33 2 32 35 63 00",
    "sg:postcode":"27250",
    "sg:province":"Haute Normandie",
    "wof:name":"Compagnie Europ\u00e9enne Du Zirconium C\u00e9zus S.a.",
    "wof:placetype":"venue"
},
  "geometry": {"coordinates":[0.71065,48.815563],"type":"Point"}
}