{
  "type": "Feature",
  "properties": {
    "addr:full":"Rte de Chasselay - ZI de Braille Lissieu Rhone-Alpes 69380",
    "addr:postcode":"69380",
    "addr:street":"Rte De Chasselay Zi De Braille;Rhone-Alpes",
    "iso:country":"FR",
    "sg:address":"Rte de Chasselay - ZI de Braille",
    "sg:city":"Lissieu",
    "sg:orig_category":"Unclassifiable Establishments",
    "sg:phone":"+33 4 78 47 61 20",
    "sg:postcode":"69380",
    "sg:province":"Rhone-Alpes",
    "wof:name":"Carly S.a.",
    "wof:placetype":"venue"
},
  "geometry": {"coordinates":[4.71535,45.835541],"type":"Point"}
}