{
  "type": "Feature",
  "properties": {
    "addr:full":"B.P. 99,^^11, Bd de la R\u00e9publique, 59580 Emerchicourt Nord Pas-de-Calais",
    "addr:housenumber":"^ 11",
    "addr:postcode":"59580",
    "addr:street":"B.P. 99 ^;Bd De La Re\u0301Publique;Emerchicourt Nord",
    "iso:country":"FR",
    "sg:address":"B.P. 99,^^11, Bd de la R\u00e9publique, 59580 Emerchicourt",
    "sg:orig_category":"Non-Classified Establishments",
    "sg:phone":"+33 3 27 93 43 30",
    "sg:province":"Nord Pas-de-Calais",
    "wof:name":"Saint Gobain Glass S.a.",
    "wof:placetype":"venue"
},
  "geometry": {"coordinates":[3.249528,50.331013],"type":"Point"}
}