{
  "type": "Feature",
  "properties": {
    "iso:country":"FR",
    "sg:address":"Rue de Tritteling - Parc Industriel",
    "sg:city":"Faulquemont",
    "sg:orig_category":"Unclassifiable Establishments",
    "sg:phone":"+33 3 87 90 71 01",
    "sg:postcode":"57380",
    "sg:province":"Lorraine",
    "wof:name":"C.a.s.e. / D.u.f. - Centre D'accueil Et De Services Aux Entreprises",
    "wof:placetype":"venue"
},
  "geometry": {"coordinates":[6.5989,49.045826],"type":"Point"}
}