{
  "type": "Feature",
  "properties": {
    "iso:country":"FR",
    "sg:address":"11 Avenue Du General Sarrail 52101 St Dizier Cedex",
    "sg:classifiers":[
        {
            "category":"Manufacturing",
            "subcategory":"Metals",
            "type":"Manufacturing & Wholesale Goods"
        }
    ],
    "sg:phone":"+33 3 25 56 75 00",
    "sg:province":"Pays de Loire",
    "sg:tags":[
        "metallurgy",
        "steel",
        "metalworking"
    ],
    "wof:name":"Acieries Hachette Et Driout (ahd)",
    "wof:placetype":"venue"
},
  "geometry": {"coordinates":[4.951627,48.643559],"type":"Point"}
}