{
  "type": "Feature",
  "properties": {
    "addr:full":"10, Rue de l'Eglise, 27150 Le Thil en Vexin Haute Normandie 27150",
    "addr:housenumber":"10",
    "addr:postcode":"27150;27150",
    "addr:street":"Rue De L'Eglise;Thil En Vexin Haute Normandie",
    "iso:country":"FR",
    "sg:address":"10, Rue de l'Eglise, 27150 Le Thil en Vexin",
    "sg:orig_category":"Non-Classified Establishments",
    "sg:phone":"+33 2 32 55 54 15",
    "sg:postcode":"27150",
    "sg:province":"Haute Normandie",
    "wof:name":"Cossin Pierre-yves",
    "wof:placetype":"venue"
},
  "geometry": {"coordinates":[1.555474,49.311092],"type":"Point"}
}