{
  "type": "Feature",
  "properties": {
    "addr:full":"12, Rue de la Baume, 75411 Paris C\u00e9dex 8 \u00cele-de-France",
    "addr:housenumber":"12",
    "addr:postcode":"75411",
    "addr:street":"Rue De La Baume",
    "iso:country":"FR",
    "sg:address":"12, Rue de la Baume, 75411 Paris C\u00e9dex 8",
    "sg:orig_category":"Non-Classified Establishments",
    "sg:phone":"+33 1 40 76 25 00",
    "sg:province":"\u00cele-de-France",
    "wof:name":"Soci\u00e9t\u00e9 Electro Banque S.a.",
    "wof:placetype":"venue"
},
  "geometry": {"coordinates":[2.311866,48.874378],"type":"Point"}
}