{
  "type": "Feature",
  "properties": {
    "addr:full":"RD 929 Neuilly en Thelle Picardie 60530",
    "addr:postcode":"60530",
    "addr:street":"Rd 929 Neuilly En Thelle Picardie",
    "iso:country":"FR",
    "sg:address":"RD 929",
    "sg:city":"Neuilly en Thelle",
    "sg:orig_category":"Unclassifiable Establishments",
    "sg:phone":"+33 3 44 26 85 85",
    "sg:postcode":"60530",
    "sg:province":"Picardie",
    "wof:name":"Somico S.a.",
    "wof:placetype":"venue"
},
  "geometry": {"coordinates":[2.28527,49.224705],"type":"Point"}
}