{
  "type": "Feature",
  "properties": {
    "addr:full":"15 Rue Leonard De Vinci 92160 Antony Ile de France 92160",
    "addr:housenumber":"15",
    "addr:postcode":"92160;92160",
    "addr:street":"Rue Leonard De Vinci",
    "iso:country":"FR",
    "sg:address":"15 Rue Leonard De Vinci 92160 Antony",
    "sg:classifiers":[
        {
            "category":"Professional",
            "subcategory":"Engineering",
            "type":"Services"
        }
    ],
    "sg:phone":"+33 1 46 74 66 55",
    "sg:postcode":"92160",
    "sg:province":"Ile de France",
    "sg:tags":[
        "machine",
        "-",
        "jewellery",
        "mechanical"
    ],
    "wof:name":"Benitah Andre",
    "wof:placetype":"venue"
},
  "geometry": {"coordinates":[2.315391,48.740902],"type":"Point"}
}