{
  "type": "Feature",
  "properties": {
    "iso:country":"FR",
    "sg:address":"8 R De La Gare 59225 Clary",
    "sg:classifiers":[
        {
            "category":"Shopping",
            "subcategory":"Crafts & Fabrics",
            "type":"Retail Goods"
        }
    ],
    "sg:phone":"+33 3 27 85 08 60",
    "sg:postcode":"59225",
    "sg:province":"Nord Pas-de-Calais",
    "sg:tags":[
        "textile",
        "clothing"
    ],
    "wof:name":"Ets Baudchon Sa",
    "wof:placetype":"venue"
},
  "geometry": {"coordinates":[3.391704,50.078197],"type":"Point"}
}