{
  "type": "Feature",
  "properties": {
    "iso:country":"FR",
    "sg:address":"ZI la Sucrerie",
    "sg:city":"Laneuvilleroy",
    "sg:orig_category":"Non-Classified Establishments",
    "sg:phone":"+33 3 44 51 73 01",
    "sg:postcode":"60190",
    "sg:province":"Picardie",
    "wof:name":"J.p. Arbez S.a.",
    "wof:placetype":"venue"
},
  "geometry": {"coordinates":[2.578056,49.480976],"type":"Point"}
}