{
  "type": "Feature",
  "properties": {
    "addr:full":"5, Rue de la Pr\u00e9v\u00f4t\u00e9, 78550 Houdan Ile de France",
    "addr:housenumber":"5",
    "addr:postcode":"78550;ile",
    "addr:street":"Rue De La Pre\u0301Vo\u0302Te\u0301",
    "iso:country":"FR",
    "sg:address":"5, Rue de la Pr\u00e9v\u00f4t\u00e9, 78550 Houdan",
    "sg:orig_category":"Unclassifiable Establishments",
    "sg:phone":"+33 1 30 88 10 25",
    "sg:province":"Ile de France",
    "wof:name":"D.m.i.b. S.a.r.l. - Diffusion De Mat\u00e9riel Industriel De Bureau",
    "wof:placetype":"venue"
},
  "geometry": {"coordinates":[1.60191,48.788956],"type":"Point"}
}