{
  "type": "Feature",
  "properties": {
    "addr:full":"49 Bis Rue Ste Anne 75002 Paris Ile de France 75002",
    "addr:housenumber":"49 bis",
    "addr:postcode":"75002;75002",
    "addr:street":"Rue Ste Anne",
    "iso:country":"FR",
    "sg:address":"49 Bis Rue Ste Anne 75002 Paris",
    "sg:classifiers":[
        {
            "category":"Manufacturing",
            "subcategory":"Textiles",
            "type":"Manufacturing & Wholesale Goods"
        }
    ],
    "sg:phone":"+33 1 47 03 44 77",
    "sg:postcode":"75002",
    "sg:province":"Ile de France",
    "sg:tags":[
        "linen",
        "clothing",
        "fabric"
    ],
    "wof:name":"Jules Flipo Ets",
    "wof:placetype":"venue"
},
  "geometry": {"coordinates":[2.335746,48.867172],"type":"Point"}
}