{
  "type": "Feature",
  "properties": {
    "addr:full":"Zi Le Palun Emanuelle Vitria 13120 Gardanne Basse Normandie",
    "addr:postcode":"13120",
    "addr:street":"Zi Le;Emanuelle Vitria",
    "iso:country":"FR",
    "sg:address":"Zi Le Palun",
    "sg:city":"Emanuelle Vitria 13120 Gardanne",
    "sg:classifiers":[
        {
            "category":"Manufacturing",
            "subcategory":"Metals",
            "type":"Manufacturing & Wholesale Goods"
        }
    ],
    "sg:phone":"+33 4 42 58 31 47",
    "sg:province":"Basse Normandie",
    "sg:tags":[
        "pipe",
        "sheet",
        "-",
        "metalworking",
        "metallic",
        "metallurgy",
        "finished"
    ],
    "wof:name":"Ets Grimaud Et Cie Sarl",
    "wof:placetype":"venue"
},
  "geometry": {"coordinates":[5.47062,43.454971],"type":"Point"}
}