{
  "type": "Feature",
  "properties": {
    "addr:full":"89, Rte de Chateauneuf, 26200 Mont\u00e9limar Rhone-Alpes",
    "addr:housenumber":"89",
    "addr:postcode":"26200",
    "addr:street":"Rte De Chateauneuf",
    "iso:country":"FR",
    "sg:address":"89, Rte de Chateauneuf, 26200 Mont\u00e9limar",
    "sg:orig_category":"Unclassifiable Establishments",
    "sg:phone":"+33 4 75 01 05 93",
    "sg:province":"Rhone-Alpes",
    "wof:name":"Abram Et Fils S.a.",
    "wof:placetype":"venue"
},
  "geometry": {"coordinates":[4.738539,44.533489],"type":"Point"}
}