{
  "type": "Feature",
  "properties": {
    "addr:full":"Zi Occitania 87250 Bessines Sur Gartempe Limousin 87250",
    "addr:postcode":"87250;87250",
    "addr:street":"Occitania",
    "iso:country":"FR",
    "sg:address":"Zi Occitania 87250 Bessines Sur Gartempe",
    "sg:classifiers":[
        {
            "category":"Manufacturing",
            "subcategory":"Glass & Minerals",
            "type":"Manufacturing & Wholesale Goods"
        }
    ],
    "sg:phone":"+33 5 55 76 12 81",
    "sg:postcode":"87250",
    "sg:province":"Limousin",
    "sg:tags":[
        "building",
        "material"
    ],
    "wof:name":"M. Crespin Patrick Le Nouhaud",
    "wof:placetype":"venue"
},
  "geometry": {"coordinates":[1.36853,46.10907],"type":"Point"}
}