{
  "type": "Feature",
  "properties": {
    "addr:full":"B.P. 22, 89390 Cry^^9, rue du Moulin, 89390 Cry Cry Bourgogne 89390",
    "addr:postcode":"89390;89390;89390",
    "addr:street":"B.P. 22;Rue Du Moulin",
    "iso:country":"FR",
    "sg:address":"B.P. 22, 89390 Cry^^9, rue du Moulin, 89390 Cry",
    "sg:city":"Cry",
    "sg:orig_category":"Non-Classified Establishments",
    "sg:phone":"+33 3 86 55 71 23",
    "sg:postcode":"89390",
    "sg:province":"Bourgogne",
    "wof:name":"S.i.b. S.a. - Scieries Industrielles De Bourgogne",
    "wof:placetype":"venue"
},
  "geometry": {"coordinates":[4.228455,47.734425],"type":"Point"}
}