{
  "type": "Feature",
  "properties": {
    "iso:country":"FR",
    "sg:address":"39, Rte de Toul, 54840 Velaine en Haye",
    "sg:orig_category":"Non-Classified Establishments",
    "sg:phone":"+33 3 83 23 20 57",
    "sg:province":"Lorraine",
    "wof:name":"Transports Schlichting S.a.",
    "wof:placetype":"venue"
},
  "geometry": {"coordinates":[6.037742,48.691788],"type":"Point"}
}