{
  "type": "Feature",
  "properties": {
    "addr:full":"12, Place de la Tourbie, 29000 Quimper Quimper Bretagne 29000",
    "addr:housenumber":"12",
    "addr:postcode":"29000;29000",
    "addr:street":"Place De La Tourbie",
    "iso:country":"FR",
    "sg:address":"12, Place de la Tourbie, 29000 Quimper",
    "sg:city":"Quimper",
    "sg:orig_category":"Non-Classified Establishments",
    "sg:phone":"+33 2 98 95 30 31",
    "sg:postcode":"29000",
    "sg:province":"Bretagne",
    "wof:name":"C.r.i.t. Int\u00e9rim S.a.",
    "wof:placetype":"venue"
},
  "geometry": {"coordinates":[-4.10234,47.999435],"type":"Point"}
}