{
  "type": "Feature",
  "properties": {
    "addr:full":"ZA des Planchettes Feurs Rhone-Alpes 42110",
    "addr:postcode":"42110",
    "addr:street":"Za Des Planchettes;Rhone-Alpes",
    "iso:country":"FR",
    "sg:address":"ZA des Planchettes",
    "sg:city":"Feurs",
    "sg:orig_category":"Unclassifiable Establishments",
    "sg:phone":"+33 4 77 27 01 70",
    "sg:postcode":"42110",
    "sg:province":"Rhone-Alpes",
    "wof:name":"Damon Fr\u00e9n\u00e9at S.a.r.l.",
    "wof:placetype":"venue"
},
  "geometry": {"coordinates":[4.2255,45.743793],"type":"Point"}
}