{
  "type": "Feature",
  "properties": {
    "addr:full":"Rte de Montbrison Saint Romain le Puy Rhone-Alpes 42610",
    "addr:postcode":"42610",
    "addr:street":"Rte De Montbrison Saint Romain Le",
    "iso:country":"FR",
    "sg:address":"Rte de Montbrison",
    "sg:city":"Saint Romain le Puy",
    "sg:orig_category":"Non-Classified Establishments",
    "sg:phone":"+33 4 77 76 61 53",
    "sg:postcode":"42610",
    "sg:province":"Rhone-Alpes",
    "wof:name":"Etablissements Louisvial S.a.r.l.",
    "wof:placetype":"venue"
},
  "geometry": {"coordinates":[4.12494,45.560547],"type":"Point"}
}