{
  "type": "Feature",
  "properties": {
    "addr:full":"34, Rue Henri Chevreau, 75020 Paris Ile de France",
    "addr:housenumber":"34",
    "addr:postcode":"75020",
    "addr:street":"Rue Henri Chevreau",
    "iso:country":"FR",
    "sg:address":"34, Rue Henri Chevreau, 75020 Paris",
    "sg:orig_category":"Unclassifiable Establishments",
    "sg:phone":"+33 1 46 36 64 24",
    "sg:province":"Ile de France",
    "wof:name":"Imprimerie La Productrice S.a.",
    "wof:placetype":"venue"
},
  "geometry": {"coordinates":[2.389396,48.870323],"type":"Point"}
}