{
  "type": "Feature",
  "properties": {
    "addr:full":"2 Rue De La Chaussee 18190 Chateauneuf Sur Cher Chambon Centre 18190",
    "addr:housenumber":"2",
    "addr:postcode":"18190;18190",
    "addr:street":"Rue De La Chaussee",
    "iso:country":"FR",
    "sg:address":"2 Rue De La Chaussee 18190 Chateauneuf Sur Cher",
    "sg:city":"Chambon",
    "sg:classifiers":[
        {
            "category":"Manufacturing",
            "subcategory":"Jewelry",
            "type":"Manufacturing & Wholesale Goods"
        }
    ],
    "sg:phone":"+33 2 48 60 64 00",
    "sg:postcode":"18190",
    "sg:province":"Centre",
    "sg:tags":[
        "product",
        "miscellaneous",
        "jewellery"
    ],
    "wof:name":"L'atelier Ja Naffre",
    "wof:placetype":"venue"
},
  "geometry": {"coordinates":[2.316079,46.857265],"type":"Point"}
}