{
  "type": "Feature",
  "properties": {
    "addr:full":"Rte des Landes Damazan Aquitaine 47160",
    "addr:postcode":"47160",
    "addr:street":"Rte Des Landes",
    "iso:country":"FR",
    "sg:address":"Rte des Landes",
    "sg:city":"Damazan",
    "sg:orig_category":"Unclassifiable Establishments",
    "sg:phone":"+33 5 53 79 40 33",
    "sg:postcode":"47160",
    "sg:province":"Aquitaine",
    "wof:name":"Etablissements Lamarque S.a.r.l.",
    "wof:placetype":"venue"
},
  "geometry": {"coordinates":[0.27146,44.287365],"type":"Point"}
}