{
  "type": "Feature",
  "properties": {
    "addr:full":"5 Rue Bellini Tourarago 92806 Puteaux Defense Cedex Midi Pyr\u00e9n\u00e9es",
    "addr:housenumber":"5",
    "addr:postcode":"92806;defense cedex midi",
    "addr:street":"Rue Bellini Tourarago",
    "iso:country":"FR",
    "sg:address":"5 Rue Bellini Tourarago 92806 Puteaux Defense Cedex",
    "sg:classifiers":[
        {
            "category":"Marine",
            "type":"Transportation"
        }
    ],
    "sg:phone":"+33 1 46 96 18 00",
    "sg:province":"Midi Pyr\u00e9n\u00e9es",
    "sg:tags":[
        "transport",
        "sea"
    ],
    "wof:name":"Touax Sa",
    "wof:placetype":"venue"
},
  "geometry": {"coordinates":[2.23768,48.883331],"type":"Point"}
}