{
  "type": "Feature",
  "properties": {
    "iso:country":"FR",
    "sg:address":"34a, Rue Principale, 67480 Roppenheim",
    "sg:city":"Roppenheim",
    "sg:orig_category":"Unclassifiable Establishments",
    "sg:phone":"+33 3 88 86 41 53",
    "sg:postcode":"67480",
    "sg:province":"Alsace",
    "wof:name":"Ruffenach Machines Agricoles S.a.",
    "wof:placetype":"venue"
},
  "geometry": {"coordinates":[8.054354,48.842583],"type":"Point"}
}