{
  "type": "Feature",
  "properties": {
    "addr:full":"14 R G\u00e9n\u00e9ral Leclerc 67250 Lampertsloch Lampertsloch Alsace 67250",
    "addr:housenumber":"14",
    "addr:postcode":"67250;67250",
    "addr:street":"R Ge\u0301Ne\u0301Ral Leclerc;Lampertsloch",
    "iso:country":"FR",
    "sg:address":"14 R G\u00e9n\u00e9ral Leclerc 67250 Lampertsloch",
    "sg:city":"Lampertsloch",
    "sg:classifiers":[
        {
            "category":"Building & Trades",
            "subcategory":"Construction",
            "type":"Services"
        }
    ],
    "sg:phone":"+33 3 88 80 73 13",
    "sg:postcode":"67250",
    "sg:province":"Alsace",
    "sg:tags":[
        "work",
        "public"
    ],
    "wof:name":"Herrmann Sa",
    "wof:placetype":"venue"
},
  "geometry": {"coordinates":[7.88268,48.937824],"type":"Point"}
}