{
  "type": "Feature",
  "properties": {
    "iso:country":"FR",
    "sg:address":"7 rue de l'Uranium 67800 Bischheim",
    "sg:city":"Bischheim",
    "sg:classifiers":[
        {
            "category":"Banks & Credit Unions",
            "subcategory":"Bureau De Change",
            "type":"Services"
        }
    ],
    "sg:phone":"+33 3 88 83 44 10",
    "sg:postcode":"67800",
    "sg:province":"Alsace",
    "sg:tags":[
        "demolition"
    ],
    "wof:name":"Cardem D\u00e9molition Sa",
    "wof:placetype":"venue"
},
  "geometry": {"coordinates":[7.76478,48.626995],"type":"Point"}
}