{
  "type": "Feature",
  "properties": {
    "addr:full":"30, Rue L'Hermitte, 59140 Dunkerque Nord Pas-de-Calais",
    "addr:housenumber":"30",
    "addr:postcode":"59140",
    "addr:street":"Rue L'Hermitte",
    "iso:country":"FR",
    "sg:address":"30, Rue L'Hermitte, 59140 Dunkerque",
    "sg:orig_category":"Unclassifiable Establishments",
    "sg:phone":"+33 3 28 66 47 61",
    "sg:province":"Nord Pas-de-Calais",
    "wof:name":"Dunkerque Expansion S.a.r.l.",
    "wof:placetype":"venue"
},
  "geometry": {"coordinates":[2.383795,51.037178],"type":"Point"}
}