{
  "type": "Feature",
  "properties": {
    "iso:country":"FR",
    "sg:address":"50, Av. Maurice Thorez, 94200 Ivry sur Seine",
    "sg:orig_category":"Non-Classified Establishments",
    "sg:phone":"+33 1 46 70 14 20",
    "sg:province":"Ile de France",
    "wof:name":"Garex S.a.r.l.",
    "wof:placetype":"venue"
},
  "geometry": {"coordinates":[2.375495,48.817474],"type":"Point"}
}