{
  "type": "Feature",
  "properties": {
    "iso:country":"FR",
    "sg:address":"B.P. 249, 89004 Auxerre C\u00e9dex^^Rue de Caillotes - Z.I. Plaine des Isles, 89000 Auxerre",
    "sg:city":"Auxerre",
    "sg:orig_category":"Non-Classified Establishments",
    "sg:phone":"+33 3 86 94 23 50",
    "sg:postcode":"89000",
    "sg:province":"Bourgogne",
    "wof:name":"H.p.l. S.a. - Hamel Poids Lourds",
    "wof:placetype":"venue"
},
  "geometry": {"coordinates":[3.569305,47.796051],"type":"Point"}
}