{
  "type": "Feature",
  "properties": {
    "iso:country":"FR",
    "sg:address":"20, Av. de la Gare, 76340 Blangy sur Bresle",
    "sg:orig_category":"Non-Classified Establishments",
    "sg:phone":"+33 2 35 93 87 05",
    "sg:province":"Haute Normandie",
    "wof:name":"Le Polygone",
    "wof:placetype":"venue"
},
  "geometry": {"coordinates":[1.627227,49.931759],"type":"Point"}
}