{
  "type": "Feature",
  "properties": {
    "addr:full":"Route D Angers 44670 La Chapelle Glain Pays de Loire 44670",
    "addr:postcode":"44670;44670",
    "addr:street":"Route D Angers",
    "iso:country":"FR",
    "sg:address":"Route D Angers 44670 La Chapelle Glain",
    "sg:classifiers":[
        {
            "category":"Wholesale",
            "subcategory":"Machinery & Supplies",
            "type":"Manufacturing & Wholesale Goods"
        }
    ],
    "sg:phone":"+33 2 40 55 54 88",
    "sg:postcode":"44670",
    "sg:province":"Pays de Loire",
    "sg:tags":[
        "-",
        "machine",
        "equipment",
        "engineering",
        "animal",
        "mechanical",
        "breeding",
        "agriculture"
    ],
    "wof:name":"Couvoir Du Pin Gauguet Sa",
    "wof:placetype":"venue"
},
  "geometry": {"coordinates":[-1.291049,47.611065],"type":"Point"}
}