{
  "type": "Feature",
  "properties": {
    "addr:full":"191 Rte Des Docks 76120 Le Grand Quevilly Haute Normandie 76120",
    "addr:housenumber":"191",
    "addr:postcode":"76120;76120",
    "addr:street":"Rte Des Docks;Haute Normandie",
    "iso:country":"FR",
    "sg:address":"191 Rte Des Docks 76120 Le Grand Quevilly",
    "sg:classifiers":[
        {
            "category":"Shopping",
            "type":"Retail Goods"
        }
    ],
    "sg:phone":"+33 2 35 18 26 26",
    "sg:postcode":"76120",
    "sg:province":"Haute Normandie",
    "sg:tags":[
        "metallurgy",
        "finished",
        "-",
        "metalworking",
        "metallic"
    ],
    "wof:name":"Crown Cork Company France",
    "wof:placetype":"venue"
},
  "geometry": {"coordinates":[1.021958,49.400032],"type":"Point"}
}