{
  "type": "Feature",
  "properties": {
    "iso:country":"FR",
    "sg:address":"56, Rue du Tilloy, 60000 Beauvais",
    "sg:orig_category":"Unclassifiable Establishments",
    "sg:phone":"+33 3 44 10 52 00",
    "sg:province":"Picardie",
    "wof:name":"Scherdel Herckelbart Dawson S.a.",
    "wof:placetype":"venue"
},
  "geometry": {"coordinates":[2.102447,49.443497],"type":"Point"}
}