{
  "type": "Feature",
  "properties": {
    "addr:full":"B.P. 119, 13267 Marseille C\u00e9dex 08^^1, Rue Daumier - Immeuble le V\u00e9lasquez, 13000 Marseille Poitou-Charentes",
    "addr:housenumber":"b.p. 119;08 ^ ^ 1;immeuble",
    "addr:postcode":"13267;13000",
    "addr:street":"Ce\u0301Dex;Rue Daumier",
    "iso:country":"FR",
    "sg:address":"B.P. 119, 13267 Marseille C\u00e9dex 08^^1, Rue Daumier - Immeuble le V\u00e9lasquez, 13000 Marseille",
    "sg:orig_category":"Non-Classified Establishments",
    "sg:phone":"+33 4 91 15 75 00",
    "sg:province":"Poitou-Charentes",
    "wof:name":"Solendi",
    "wof:placetype":"venue"
},
  "geometry": {"coordinates":[5.37249,43.293686],"type":"Point"}
}