{
  "type": "Feature",
  "properties": {
    "iso:country":"FR",
    "sg:address":"Rte de l'Herm",
    "sg:city":"B\u00e9rat",
    "sg:orig_category":"Unclassifiable Establishments",
    "sg:phone":"+33 5 62 14 70 30",
    "sg:postcode":"31370",
    "sg:province":"Midi Pyr\u00e9n\u00e9es",
    "wof:name":"Languedoc Emballages S.a.r.l.",
    "wof:placetype":"venue"
},
  "geometry": {"coordinates":[1.217976,43.460266],"type":"Point"}
}