{
  "type": "Feature",
  "properties": {
    "addr:full":"17 Rue Des Clos 77100 Meaux Ile de France",
    "addr:housenumber":"17",
    "addr:postcode":"77100;ile",
    "addr:street":"Rue Des Clos",
    "iso:country":"FR",
    "sg:address":"17 Rue Des Clos 77100 Meaux",
    "sg:classifiers":[
        {
            "category":"Manufacturing",
            "subcategory":"Rubber & Plastics",
            "type":"Manufacturing & Wholesale Goods"
        }
    ],
    "sg:phone":"+33 1 64 34 72 45",
    "sg:province":"Ile de France",
    "sg:tags":[
        "packaging",
        "material",
        "-"
    ],
    "wof:name":"Sorel Sa",
    "wof:placetype":"venue"
},
  "geometry": {"coordinates":[2.913958,48.965309],"type":"Point"}
}