{
  "type": "Feature",
  "properties": {
    "addr:full":"83 avenue Andr\u00e9 Morizet 92100 Boulogne Billancourt Ile de France 92100",
    "addr:housenumber":"83",
    "addr:postcode":"92100;92100",
    "addr:street":"Avenue Andre\u0301 Morizet",
    "iso:country":"FR",
    "sg:address":"83 avenue Andr\u00e9 Morizet 92100 Boulogne Billancourt",
    "sg:classifiers":[
        {
            "category":"Banks & Credit Unions",
            "subcategory":"Bureau De Change",
            "type":"Services"
        }
    ],
    "sg:phone":"+33 1 46 05 88 08",
    "sg:postcode":"92100",
    "sg:province":"Ile de France",
    "sg:tags":[
        "decoration",
        "accessory"
    ],
    "wof:name":"Edi France Eurl",
    "wof:placetype":"venue"
},
  "geometry": {"coordinates":[2.233209,48.838177],"type":"Point"}
}