{
  "type": "Feature",
  "properties": {
    "iso:country":"FR",
    "sg:address":"41 rue du Vieux Pont; Chalonnes; 49290",
    "sg:classifiers":[
        {
            "category":"Banks & Credit Unions",
            "subcategory":"Bank",
            "type":"Services"
        }
    ],
    "sg:phone":"+33 3341410158",
    "sg:postcode":"49290",
    "sg:province":"Pays de Loire",
    "wof:name":"Banque Nationale De Paris",
    "wof:placetype":"venue"
},
  "geometry": {"coordinates":[-0.75942,47.3512],"type":"Point"}
}