{
  "type": "Feature",
  "properties": {
    "addr:full":"41 rue du Vieux Pont; Chalonnes; 49290 Pays de Loire 49290",
    "addr:housenumber":"41",
    "addr:postcode":"49290;49290",
    "addr:street":"Rue Du Vieux Pont Chalonnes",
    "iso:country":"FR",
    "sg:address":"41 rue du Vieux Pont; Chalonnes; 49290",
    "sg:classifiers":[
        {
            "category":"Banks & Credit Unions",
            "subcategory":"Bank",
            "type":"Services"
        }
    ],
    "sg:phone":"+33 3341410158",
    "sg:postcode":"49290",
    "sg:province":"Pays de Loire",
    "wof:name":"Banque Nationale De Paris",
    "wof:placetype":"venue"
},
  "geometry": {"coordinates":[-0.75942,47.3512],"type":"Point"}
}