{
  "type": "Feature",
  "properties": {
    "addr:full":"18, Rue Godefroy, 69006 Lyon Rhone-Alpes 69006",
    "addr:housenumber":"18",
    "addr:postcode":"69006;69006",
    "addr:street":"Rue Godefroy",
    "iso:country":"FR",
    "sg:address":"18, Rue Godefroy, 69006 Lyon",
    "sg:orig_category":"Non-Classified Establishments",
    "sg:phone":"+33 4 78 89 11 64",
    "sg:postcode":"69006",
    "sg:province":"Rhone-Alpes",
    "wof:name":"Mezcal Edition",
    "wof:placetype":"venue"
},
  "geometry": {"coordinates":[4.841533,45.770252],"type":"Point"}
}