{
  "type": "Feature",
  "properties": {
    "iso:country":"FR",
    "sg:address":"112 Chemin Des Moulins 06670 Castagniers",
    "sg:classifiers":[
        {
            "category":"Manufacturing",
            "subcategory":"Paper Products",
            "type":"Manufacturing & Wholesale Goods"
        }
    ],
    "sg:phone":"+33 4 93 29 29 03",
    "sg:province":"Provence-Alpes-C\u00f4te d'Azur",
    "sg:tags":[
        "raw",
        "material",
        "-",
        "cardboard"
    ],
    "wof:name":"Sarl Meditec",
    "wof:placetype":"venue"
},
  "geometry": {"coordinates":[7.215368,43.791496],"type":"Point"}
}