{
  "type": "Feature",
  "properties": {
    "addr:full":"1, Rue de l'Arquebuse, 51000 Ch\u00e2lons en Champagne Champagne",
    "addr:housenumber":"1",
    "addr:postcode":"51000",
    "addr:street":"Rue De L'Arquebuse",
    "iso:country":"FR",
    "sg:address":"1, Rue de l'Arquebuse, 51000 Ch\u00e2lons en Champagne",
    "sg:orig_category":"Non-Classified Establishments",
    "sg:phone":"+33 3 26 70 44 68",
    "sg:province":"Champagne",
    "wof:name":"Repro And Co S.a.r.l.",
    "wof:placetype":"venue"
},
  "geometry": {"coordinates":[4.36804,48.959686],"type":"Point"}
}