{
  "type": "Feature",
  "properties": {
    "addr:full":"53, Rue Roosevelt, 57970 Yutz Lorraine",
    "addr:housenumber":"53",
    "addr:postcode":"57970",
    "addr:street":"Rue Roosevelt",
    "iso:country":"FR",
    "sg:address":"53, Rue Roosevelt, 57970 Yutz",
    "sg:orig_category":"Non-Classified Establishments",
    "sg:phone":"+33 3 82 56 74 29",
    "sg:province":"Lorraine",
    "wof:name":"Euro - Vitrail",
    "wof:placetype":"venue"
},
  "geometry": {"coordinates":[6.185512,49.351372],"type":"Point"}
}