{
  "type": "Feature",
  "properties": {
    "iso:country":"FR",
    "sg:address":"Rte de Lu\u00e7on - ZI",
    "sg:city":"Mareuil sur Lay Dissais",
    "sg:orig_category":"Unclassifiable Establishments",
    "sg:phone":"+33 2 51 30 55 75",
    "sg:postcode":"85320",
    "sg:province":"Pays de Loire",
    "wof:name":"Soci\u00e9t\u00e9 D'exploitation Des Etablissements Gr\u00e9au S.a.",
    "wof:placetype":"venue"
},
  "geometry": {"coordinates":[-1.284115,46.478207],"type":"Point"}
}