{
  "type": "Feature",
  "properties": {
    "addr:full":"30, Rue Fran\u00e7ois Hardouin, 37100 Tours Tours Centre 37100",
    "addr:housenumber":"30",
    "addr:postcode":"37100;37100",
    "addr:street":"Rue Franc\u0327Ois Hardouin",
    "iso:country":"FR",
    "sg:address":"30, Rue Fran\u00e7ois Hardouin, 37100 Tours",
    "sg:city":"Tours",
    "sg:orig_category":"Unclassifiable Establishments",
    "sg:phone":"+33 2 47 42 84 90",
    "sg:postcode":"37100",
    "sg:province":"Centre",
    "wof:name":"C.e.b.t.p S.a. - Centre D'expertise Du B\u00e2timent Et Des Travaux Publics",
    "wof:placetype":"venue"
},
  "geometry": {"coordinates":[0.6886,47.41745],"type":"Point"}
}