{
  "type": "Feature",
  "properties": {
    "iso:country":"FR",
    "sg:address":"B.P. 75, 76700 Harfleur^^Zone Industrielle D'Gudalle, 76700 Harfleur",
    "sg:orig_category":"Non-Classified Establishments",
    "sg:phone":"+33 2 35 13 03 03",
    "sg:postcode":"76700",
    "sg:province":"Haute Normandie",
    "wof:name":"Andr\u00e9 Alfred S.a.",
    "wof:placetype":"venue"
},
  "geometry": {"coordinates":[0.1989,49.504921],"type":"Point"}
}