{
  "type": "Feature",
  "properties": {
    "addr:full":"25, Rue Georges Sand, 94400 Vitry sur Seine Ile de France",
    "addr:housenumber":"25",
    "addr:postcode":"94400",
    "addr:street":"Rue Georges Sand",
    "iso:country":"FR",
    "sg:address":"25, Rue Georges Sand, 94400 Vitry sur Seine",
    "sg:orig_category":"Unclassifiable Establishments",
    "sg:phone":"+33 1 46 80 20 71",
    "sg:province":"Ile de France",
    "wof:name":"Isolmat S.a.",
    "wof:placetype":"venue"
},
  "geometry": {"coordinates":[2.407559,48.797775],"type":"Point"}
}