{
  "type": "Feature",
  "properties": {
    "addr:full":"2, Rue Bateli\u00e8re, 56100 Lorient Lorient Bretagne 56100",
    "addr:housenumber":"2",
    "addr:postcode":"56100;56100",
    "addr:street":"Rue Batelie\u0300Re",
    "iso:country":"FR",
    "sg:address":"2, Rue Bateli\u00e8re, 56100 Lorient",
    "sg:city":"Lorient",
    "sg:orig_category":"Non-Classified Establishments",
    "sg:phone":"+33 2 97 83 86 83",
    "sg:postcode":"56100",
    "sg:province":"Bretagne",
    "wof:name":"I.d.mer - Institut Technique De D\u00e9veloppement De Produits De Mer",
    "wof:placetype":"venue"
},
  "geometry": {"coordinates":[-3.376984,47.733925],"type":"Point"}
}