{
  "type": "Feature",
  "properties": {
    "iso:country":"FR",
    "sg:address":"188, Rue Gabriel P\u00e9ri, 92700 Colombes",
    "sg:orig_category":"Unclassifiable Establishments",
    "sg:phone":"+33 1 42 42 60 76",
    "sg:province":"Ile de France",
    "wof:name":"Cristal Fr\u00e8res S.a.r.l.",
    "wof:placetype":"venue"
},
  "geometry": {"coordinates":[2.24035,48.918953],"type":"Point"}
}