{
  "type": "Feature",
  "properties": {
    "addr:full":"March\u00e9 de Saumaty Marseille Provence-Alpes-C\u00f4te d'Azur 13016",
    "addr:postcode":"13016",
    "iso:country":"FR",
    "sg:address":"March\u00e9 de Saumaty",
    "sg:city":"Marseille",
    "sg:orig_category":"Unclassifiable Establishments",
    "sg:phone":"+33 4 91 46 28 28",
    "sg:postcode":"13016",
    "sg:province":"Provence-Alpes-C\u00f4te d'Azur",
    "wof:name":"Orcel D'jamico S.a.r.l.",
    "wof:placetype":"venue"
},
  "geometry": {"coordinates":[5.31744,43.360481],"type":"Point"}
}