{
  "type": "Feature",
  "properties": {
    "iso:country":"FR",
    "sg:address":"10, Rue de la Libert\u00e9, 49070 Saint Jean de Lini\u00e8res",
    "sg:orig_category":"Non-Classified Establishments",
    "sg:phone":"+33 2 41 36 81 41",
    "sg:province":"Pays de Loire",
    "wof:name":"Logosapience S.a.r.l.",
    "wof:placetype":"venue"
},
  "geometry": {"coordinates":[-0.654163,47.459251],"type":"Point"}
}