{
  "type": "Feature",
  "properties": {
    "addr:full":"Z.A. Amboise Saint Martin de Seignanx Aquitaine 40390",
    "addr:postcode":"40390",
    "addr:street":"Z.A. Amboise",
    "iso:country":"FR",
    "sg:address":"Z.A. Amboise",
    "sg:city":"Saint Martin de Seignanx",
    "sg:orig_category":"Unclassifiable Establishments",
    "sg:phone":"+33 5 59 56 53 67",
    "sg:postcode":"40390",
    "sg:province":"Aquitaine",
    "wof:name":"H.p. Fermetures S.a. - Henri Peyrichou Fermetures",
    "wof:placetype":"venue"
},
  "geometry": {"coordinates":[-1.331188,43.515244],"type":"Point"}
}