{
  "type": "Feature",
  "properties": {
    "iso:country":"FR",
    "sg:address":"La Touche 56800 Plo\u00ebrmel",
    "sg:city":"Plo\u00ebrmel",
    "sg:orig_category":"Unclassifiable Establishments",
    "sg:phone":"+33 2 97 73 32 90",
    "sg:postcode":"56800",
    "sg:province":"Bretagne",
    "wof:name":"A.r.e.p. Pl\u00f6ermel - Association R\u00e9gionale D'education Permanente",
    "wof:placetype":"venue"
},
  "geometry": {"coordinates":[-2.404024,47.948505],"type":"Point"}
}