{
  "type": "Feature",
  "properties": {
    "addr:full":"B.P. 12, 67831 Lingolsheim^^230, Rue de la Faisanderie - Parc Club des Tanneries, 67380 Lingolsheim Lingolsheim Alsace 67380",
    "addr:postcode":"67831;67380;67380",
    "addr:street":"B.P. 12;Rue De La Faisanderie Parc Club Des Tanneries",
    "iso:country":"FR",
    "sg:address":"B.P. 12, 67831 Lingolsheim^^230, Rue de la Faisanderie - Parc Club des Tanneries, 67380 Lingolsheim",
    "sg:city":"Lingolsheim",
    "sg:orig_category":"Non-Classified Establishments",
    "sg:phone":"+33 3 90 20 21 05",
    "sg:postcode":"67380",
    "sg:province":"Alsace",
    "wof:name":"Intrum Justitia France S.a.",
    "wof:placetype":"venue"
},
  "geometry": {"coordinates":[7.68126,48.554295],"type":"Point"}
}