{
  "type": "Feature",
  "properties": {
    "iso:country":"FR",
    "sg:address":"ZA les Renandi\u00e8res",
    "sg:city":"Arc sur Tille",
    "sg:orig_category":"Unclassifiable Establishments",
    "sg:phone":"+33 3 80 37 21 41",
    "sg:postcode":"21560",
    "sg:province":"Bourgogne",
    "wof:name":"Javaux Lev\u00e8que S.a.",
    "wof:placetype":"venue"
},
  "geometry": {"coordinates":[5.190315,47.34478],"type":"Point"}
}