{
  "type": "Feature",
  "properties": {
    "addr:full":"1130, Rte de Provence, 06140 Tourrettes sur Loup Provence-Alpes-C\u00f4te d'Azur",
    "addr:housenumber":"1130",
    "addr:postcode":"06140",
    "addr:street":"Rte De Provence;Loup",
    "iso:country":"FR",
    "sg:address":"1130, Rte de Provence, 06140 Tourrettes sur Loup",
    "sg:orig_category":"Unclassifiable Establishments",
    "sg:phone":"+33 4 93 24 14 62",
    "sg:province":"Provence-Alpes-C\u00f4te d'Azur",
    "wof:name":"Logg\u00e8re France S.a.r.l.",
    "wof:placetype":"venue"
},
  "geometry": {"coordinates":[7.073538,43.714626],"type":"Point"}
}