{
  "type": "Feature",
  "properties": {
    "iso:country":"FR",
    "sg:address":"9, Rue Gambetta, 59260 Lezennes",
    "sg:orig_category":"Non-Classified Establishments",
    "sg:phone":"+33 3 20 34 03 27",
    "sg:postcode":"59260",
    "sg:province":"Nord Pas-de-Calais",
    "wof:name":"Alvig Multim\u00e9dia S.a.r.l.",
    "wof:placetype":"venue"
},
  "geometry": {"coordinates":[3.11554,50.614391],"type":"Point"}
}