{
  "type": "Feature",
  "properties": {
    "iso:country":"FR",
    "sg:address":"Bois",
    "sg:city":"Brugheas",
    "sg:classifiers":[
        {
            "category":"Professional",
            "subcategory":"Engineering",
            "type":"Services"
        }
    ],
    "sg:phone":"+33 4 70 58 82 22",
    "sg:postcode":"03700",
    "sg:province":"Auvergne",
    "sg:tags":[
        "machine",
        "-",
        "mechanical"
    ],
    "wof:name":"Appli-chau",
    "wof:placetype":"venue"
},
  "geometry": {"coordinates":[3.38527,46.108341],"type":"Point"}
}