{
  "type": "Feature",
  "properties": {
    "addr:full":"42114 Chirassimont Rhone-Alpes 42114",
    "addr:postcode":"42114;42114",
    "addr:street":"Rhone-Alpes",
    "iso:country":"FR",
    "sg:address":"42114 Chirassimont",
    "sg:orig_category":"Non-Classified Establishments",
    "sg:phone":"+33 4 77 62 41 94",
    "sg:postcode":"42114",
    "sg:province":"Rhone-Alpes",
    "wof:name":"Collangette Fils S.a.r.l.",
    "wof:placetype":"venue"
},
  "geometry": {"coordinates":[4.28431,45.914215],"type":"Point"}
}