{
  "type": "Feature",
  "properties": {
    "iso:country":"FR",
    "sg:address":"18, Rue du Gal de Maud-huy, 57710 Tressange",
    "sg:orig_category":"Non-Classified Establishments",
    "sg:phone":"+33 3 82 91 89 89",
    "sg:province":"Lorraine",
    "wof:name":"Stal S.c.a.",
    "wof:placetype":"venue"
},
  "geometry": {"coordinates":[5.982425,49.401764],"type":"Point"}
}