{
  "type": "Feature",
  "properties": {
    "addr:full":"Zone Industrielle 24700 MONTPON MENESTEROL Moulin-Neuf Aquitaine 24700",
    "addr:postcode":"24700;24700",
    "addr:street":"Zone Industrielle",
    "iso:country":"FR",
    "sg:address":"Zone Industrielle 24700 MONTPON MENESTEROL",
    "sg:city":"Moulin-Neuf",
    "sg:classifiers":[
        {
            "category":"Retail",
            "subcategory":"Event Space",
            "type":"Services"
        }
    ],
    "sg:phone":"+33 5 53 80 85 00",
    "sg:postcode":"24700",
    "sg:province":"Aquitaine",
    "sg:tags":[
        "measuring",
        "device",
        "electronic"
    ],
    "wof:name":"Kimo S.a.",
    "wof:placetype":"venue"
},
  "geometry": {"coordinates":[0.167606,45.009319],"type":"Point"}
}