{
  "type": "Feature",
  "properties": {
    "addr:full":"Savoir Hexapole Mery Rhone-Alpes 73420",
    "addr:postcode":"73420",
    "iso:country":"FR",
    "sg:address":"Savoir Hexapole",
    "sg:city":"Mery",
    "sg:orig_category":"Unclassifiable Establishments",
    "sg:phone":"+33 4 79 88 50 61",
    "sg:postcode":"73420",
    "sg:province":"Rhone-Alpes",
    "wof:name":"S.n.t. S.a.",
    "wof:placetype":"venue"
},
  "geometry": {"coordinates":[5.919765,45.659649],"type":"Point"}
}