{
  "type": "Feature",
  "properties": {
    "addr:full":"163, Rue Dejean, 80000 Amiens Picardie 80000",
    "addr:housenumber":"163",
    "addr:postcode":"80000;80000",
    "addr:street":"Rue Dejean",
    "iso:country":"FR",
    "sg:address":"163, Rue Dejean, 80000 Amiens",
    "sg:orig_category":"Non-Classified Establishments",
    "sg:phone":"+33 3 22 91 09 27",
    "sg:postcode":"80000",
    "sg:province":"Picardie",
    "wof:name":"Comptoir Distribution Vente S.a.",
    "wof:placetype":"venue"
},
  "geometry": {"coordinates":[2.319378,49.890781],"type":"Point"}
}