{
  "type": "Feature",
  "properties": {
    "iso:country":"FR",
    "sg:address":"Ch\u00e2teau du Roc 11700 Montbrun des Corbi\u00e8res",
    "sg:orig_category":"Non-Classified Establishments",
    "sg:phone":"+33 4 68 32 84 84",
    "sg:province":"Languedoc-Roussillon",
    "wof:name":"Vignobles Jacques Bacou S.a.r.l.",
    "wof:placetype":"venue"
},
  "geometry": {"coordinates":[2.65799,43.277916],"type":"Point"}
}