{
  "type": "Feature",
  "properties": {
    "iso:country":"FR",
    "sg:address":"ZI Henri Potez",
    "sg:city":"Albert",
    "sg:orig_category":"MONTE-CHARGES ET ASCENSEURS MODULE H., ASCENSEURS DE CHARGE SOUS-TRAITANCE A\u00c9RONAUTIQUE",
    "sg:phone":"+33 3 22 74 00 22",
    "sg:postcode":"80300",
    "sg:province":"Picardie",
    "wof:name":"G\u00e9n\u00e9rale M\u00e9canique Hydraulique (hydronord) S.a.",
    "wof:placetype":"venue"
},
  "geometry": {"coordinates":[2.646825,50.00407],"type":"Point"}
}