{
  "type": "Feature",
  "properties": {
    "iso:country":"FR",
    "sg:address":"2 all\u00e9e de la Clairi\u00e8re 59536 WAVRIN CEDEX",
    "sg:city":"Lairi\u00e8re",
    "sg:classifiers":[
        {
            "category":"Banks & Credit Unions",
            "subcategory":"Investment Brokerage",
            "type":"Services"
        }
    ],
    "sg:phone":"+33 3 20 58 88 04",
    "sg:postcode":"11330",
    "sg:province":"Languedoc-Roussillon",
    "sg:tags":[
        "article",
        "production",
        "metal",
        "mass"
    ],
    "wof:name":"Ets Bouillet Sarl",
    "wof:placetype":"venue"
},
  "geometry": {"coordinates":[2.922963,50.555107],"type":"Point"}
}