{
  "type": "Feature",
  "properties": {
    "iso:country":"FR",
    "sg:address":"Av. Emmanuel Pontremoli - Nice La Plaine 1 - B\u00e2t. A3",
    "sg:city":"Nice",
    "sg:orig_category":"Unclassifiable Establishments",
    "sg:phone":"+33 4 93 18 74 70",
    "sg:postcode":"06200",
    "sg:province":"Provence-Alpes-C\u00f4te d'Azur",
    "wof:name":"Bureau V\u00e9ritas C.e.p. S.a.",
    "wof:placetype":"venue"
},
  "geometry": {"coordinates":[7.215093,43.745003],"type":"Point"}
}