{
  "type": "Feature",
  "properties": {
    "addr:full":"ZA Les Teppes Saint Cyr sur Menthon Rhone-Alpes 01380",
    "addr:postcode":"01380",
    "addr:street":"Za Les Teppes Saint Cyr Sur Menthon Rhone-Alpes",
    "iso:country":"FR",
    "sg:address":"ZA Les Teppes",
    "sg:city":"Saint Cyr sur Menthon",
    "sg:orig_category":"Non-Classified Establishments",
    "sg:phone":"+33 4 74 30 26 31",
    "sg:postcode":"01380",
    "sg:province":"Rhone-Alpes",
    "wof:name":"Serge Vardas",
    "wof:placetype":"venue"
},
  "geometry": {"coordinates":[4.97583,46.275414],"type":"Point"}
}