{
  "type": "Feature",
  "properties": {
    "iso:country":"FR",
    "sg:address":"B.P. 234, 22105 Dinan C\u00e9dex^^Rue Auguste Pavie, 22100 Dinan",
    "sg:city":"Dinan",
    "sg:orig_category":"Non-Classified Establishments",
    "sg:phone":"+33 2 96 39 59 70",
    "sg:postcode":"22100",
    "sg:province":"Bretagne",
    "wof:name":"C.c.i. De Dinan",
    "wof:placetype":"venue"
},
  "geometry": {"coordinates":[-2.064859,48.390835],"type":"Point"}
}