{
  "type": "Feature",
  "properties": {
    "addr:full":"Ld Pompignat 40 Ancienne Route De Riom Ancienne Rte De Riom 63119 Chateaugay Ch\u00e2teaugay Auvergne 63119",
    "addr:housenumber":"40",
    "addr:postcode":"63119;63119",
    "addr:street":"Ld;Ancienne Route De Riom Ancienne Rte De Riom",
    "iso:country":"FR",
    "sg:address":"Ld Pompignat 40 Ancienne Route De Riom Ancienne Rte De Riom 63119 Chateaugay",
    "sg:city":"Ch\u00e2teaugay",
    "sg:classifiers":[
        {
            "category":"Building & Trades",
            "subcategory":"Construction",
            "type":"Services"
        }
    ],
    "sg:phone":"+33 4 73 23 07 78",
    "sg:postcode":"63119",
    "sg:province":"Auvergne",
    "sg:tags":[
        "work",
        "public"
    ],
    "wof:name":"Entreprise Renon",
    "wof:placetype":"venue"
},
  "geometry": {"coordinates":[3.085175,45.850052],"type":"Point"}
}