{
  "type": "Feature",
  "properties": {
    "iso:country":"FR",
    "sg:address":"8 avenue de Coubertin 38170 Seyssinet Pariset",
    "sg:classifiers":[
        {
            "category":"Utilities",
            "subcategory":"Electric",
            "type":"Services"
        }
    ],
    "sg:phone":"+33 4 76 70 19 60",
    "sg:postcode":"38170",
    "sg:province":"Rhone-Alpes",
    "sg:tags":[
        "clock"
    ],
    "wof:name":"Gorgy Timing S.a.",
    "wof:placetype":"venue"
},
  "geometry": {"coordinates":[5.689797,45.1688],"type":"Point"}
}