{
  "type": "Feature",
  "properties": {
    "iso:country":"FR",
    "sg:address":"39 bis, Rue Eug\u00e8ne Chaulet, 40100 Dax",
    "sg:city":"Dax",
    "sg:orig_category":"Non-Classified Establishments",
    "sg:phone":"+33 5 58 90 15 44",
    "sg:postcode":"40100",
    "sg:province":"Aquitaine",
    "wof:name":"D\u00e9rivados Forestales France S.a.s.",
    "wof:placetype":"venue"
},
  "geometry": {"coordinates":[-1.051499,43.717213],"type":"Point"}
}