{
  "type": "Feature",
  "properties": {
    "addr:full":"32 Route D Ebange 57270 Uckange Lorraine 57270",
    "addr:housenumber":"32",
    "addr:postcode":"57270;57270",
    "addr:street":"Route D Ebange",
    "iso:country":"FR",
    "sg:address":"32 Route D Ebange 57270 Uckange",
    "sg:classifiers":[
        {
            "category":"Manufacturing",
            "subcategory":"Metals",
            "type":"Manufacturing & Wholesale Goods"
        }
    ],
    "sg:phone":"+33 3 82 59 81 00",
    "sg:postcode":"57270",
    "sg:province":"Lorraine",
    "sg:tags":[
        "metallurgy",
        "metalworking",
        "processing"
    ],
    "wof:name":"Solblank France",
    "wof:placetype":"venue"
},
  "geometry": {"coordinates":[6.14673,49.31152],"type":"Point"}
}