{
  "type": "Feature",
  "properties": {
    "iso:country":"FR",
    "sg:address":"249 Rue Du Fbg De Roubaix 59010 Lille Cedex",
    "sg:classifiers":[
        {
            "category":"Shopping",
            "subcategory":"Crafts & Fabrics",
            "type":"Retail Goods"
        }
    ],
    "sg:phone":"+33 3 20 12 11 80",
    "sg:province":"Nord Pas-de-Calais",
    "sg:tags":[
        "textile",
        "clothing"
    ],
    "wof:name":"Etablissements Vrau",
    "wof:placetype":"venue"
},
  "geometry": {"coordinates":[3.06344,50.63718],"type":"Point"}
}