{
  "type": "Feature",
  "properties": {
    "addr:full":"22, Rue de la Roquette, 75011 Paris Ile de France",
    "addr:housenumber":"22",
    "addr:postcode":"75011",
    "addr:street":"Rue De La Roquette",
    "iso:country":"FR",
    "sg:address":"22, Rue de la Roquette, 75011 Paris",
    "sg:orig_category":"Non-Classified Establishments",
    "sg:phone":"+33 1 47 00 85 95",
    "sg:province":"Ile de France",
    "wof:name":"Sv Jud S.a.r.l.",
    "wof:placetype":"venue"
},
  "geometry": {"coordinates":[2.370941,48.853779],"type":"Point"}
}