{
  "type": "Feature",
  "properties": {
    "addr:full":"Clapot 71740 CHATEAUNEUF Ch\u00e2teauneuf Bourgogne 71740",
    "addr:postcode":"71740;71740",
    "addr:street":"Clapot;Bourgogne",
    "iso:country":"FR",
    "sg:address":"Clapot 71740 CHATEAUNEUF",
    "sg:city":"Ch\u00e2teauneuf",
    "sg:classifiers":[
        {
            "category":"Structure",
            "subcategory":"Building",
            "type":"Public Place"
        }
    ],
    "sg:phone":"+33 3 85 26 24 08",
    "sg:postcode":"71740",
    "sg:province":"Bourgogne",
    "sg:tags":[
        "attic",
        "addition",
        "finishing",
        "roof",
        "trusses"
    ],
    "wof:name":"Clapot Sa",
    "wof:placetype":"venue"
},
  "geometry": {"coordinates":[4.262239,46.201317],"type":"Point"}
}