{
  "type": "Feature",
  "properties": {
    "addr:full":"18 rue Chardanne 93310 LE PRE ST GERVAIS Ile de France",
    "addr:housenumber":"18",
    "addr:postcode":"93310",
    "addr:street":"Rue Chardanne;Pre St",
    "iso:country":"FR",
    "sg:address":"18 rue Chardanne 93310 LE PRE ST GERVAIS",
    "sg:orig_category":"Wire Rope Cutters",
    "sg:phone":"+33 1 48 40 84 60",
    "sg:province":"Ile de France",
    "wof:name":"D\u00e9coup S.a.",
    "wof:placetype":"venue"
},
  "geometry": {"coordinates":[2.40072,48.885368],"type":"Point"}
}