{
  "type": "Feature",
  "properties": {
    "addr:full":"2, Rue Maryse Basti\u00e9, 69500 Bron Rhone-Alpes 69500",
    "addr:housenumber":"2",
    "addr:postcode":"69500;69500",
    "addr:street":"Rue Maryse Bastie\u0301",
    "iso:country":"FR",
    "sg:address":"2, Rue Maryse Basti\u00e9, 69500 Bron",
    "sg:orig_category":"Unclassifiable Establishments",
    "sg:phone":"+33 4 72 15 82 10",
    "sg:postcode":"69500",
    "sg:province":"Rhone-Alpes",
    "wof:name":"Baudin Ch\u00e2teauneuf S.a.",
    "wof:placetype":"venue"
},
  "geometry": {"coordinates":[4.921267,45.726749],"type":"Point"}
}