{
  "type": "Feature",
  "properties": {
    "iso:country":"FR",
    "sg:address":"B.P. 13, 10500 Brienne le Ch\u00e2teau^^Av de Verdun, 10500 Brienne le Ch\u00e2teau",
    "sg:orig_category":"Non-Classified Establishments",
    "sg:phone":"+33 3 25 92 88 06",
    "sg:province":"Champagne",
    "wof:name":"France Case S.a.",
    "wof:placetype":"venue"
},
  "geometry": {"coordinates":[4.530473,48.391685],"type":"Point"}
}