{
  "type": "Feature",
  "properties": {
    "addr:full":"161, Av. de Ch\u00e2teaudun, 41000 Blois Blois Centre 41000",
    "addr:postcode":"41000;41000",
    "addr:street":"161 Av. De Cha\u0302Teaudun",
    "iso:country":"FR",
    "sg:address":"161, Av. de Ch\u00e2teaudun, 41000 Blois",
    "sg:city":"Blois",
    "sg:orig_category":"Non-Classified Establishments",
    "sg:phone":"+33 2 54 90 54 54",
    "sg:postcode":"41000",
    "sg:province":"Centre",
    "wof:name":"Arcante S.n.c.",
    "wof:placetype":"venue"
},
  "geometry": {"coordinates":[1.328035,47.611279],"type":"Point"}
}