{
  "type": "Feature",
  "properties": {
    "addr:full":"64, Av du 8\u00e8me Rgt des Hussards, 68130 Carspach Carspach Alsace 68130",
    "addr:postcode":"68130;68130",
    "addr:street":"64 Av Du 8E\u0300Me Rgt Des Hussards;Carspach",
    "iso:country":"FR",
    "sg:address":"64, Av du 8\u00e8me Rgt des Hussards, 68130 Carspach",
    "sg:city":"Carspach",
    "sg:orig_category":"Unclassifiable Establishments",
    "sg:phone":"+33 3 89 40 01 56",
    "sg:postcode":"68130",
    "sg:province":"Alsace",
    "wof:name":"Brogle Btp S.a.r.l.",
    "wof:placetype":"venue"
},
  "geometry": {"coordinates":[7.226746,47.625538],"type":"Point"}
}