{
  "type": "Feature",
  "properties": {
    "iso:country":"FR",
    "sg:address":"1 Rue Henri Jarry",
    "sg:city":"Les Ponts De C\u00e9",
    "sg:classifiers":[
        {
            "category":"Banks & Credit Unions",
            "subcategory":"Financial Services",
            "type":"Services"
        }
    ],
    "sg:phone":"+33 2 41 96 67 40",
    "sg:postcode":"49130",
    "sg:province":"Pays de Loire",
    "sg:tags":[
        "banking",
        "finance",
        "insurance"
    ],
    "wof:name":"Fiducial Expertise",
    "wof:placetype":"venue"
},
  "geometry": {"coordinates":[-0.504227,47.435925],"type":"Point"}
}