{
  "type": "Feature",
  "properties": {
    "iso:country":"FR",
    "sg:address":"50-52 R Louveau 92320 Chatillon",
    "sg:classifiers":[
        {
            "category":"Wholesale",
            "subcategory":"Machinery & Supplies",
            "type":"Manufacturing & Wholesale Goods"
        }
    ],
    "sg:phone":"+33 1 58 07 14 00",
    "sg:postcode":"92320",
    "sg:province":"Ile de France",
    "sg:tags":[
        "food",
        "processing",
        "-",
        "machine",
        "equipment",
        "engineering",
        "mechanical"
    ],
    "wof:name":"Elecrem Sa",
    "wof:placetype":"venue"
},
  "geometry": {"coordinates":[2.29465,48.802879],"type":"Point"}
}