{
  "type": "Feature",
  "properties": {
    "addr:full":"B.P. 8, 08370 Margut^^Rue de la Prairie, 08370 Margut Champagne 08370",
    "addr:housenumber":"8",
    "addr:postcode":"08370;08370;08370",
    "addr:street":"B.P.;La Prairie;Champagne",
    "iso:country":"FR",
    "sg:address":"B.P. 8, 08370 Margut^^Rue de la Prairie, 08370 Margut",
    "sg:orig_category":"Non-Classified Establishments",
    "sg:phone":"+33 3 24 22 61 51",
    "sg:postcode":"08370",
    "sg:province":"Champagne",
    "wof:name":"Au Confort Electrique S.a.r.l.",
    "wof:placetype":"venue"
},
  "geometry": {"coordinates":[5.275851,49.597698],"type":"Point"}
}