{
  "type": "Feature",
  "properties": {
    "addr:full":"1 Rue Ren\u00e9 Cassin 95220 Herblay Ile de France 95220",
    "addr:housenumber":"1",
    "addr:postcode":"95220;ile;95220",
    "addr:street":"Rue Rene\u0301 Cassin;France",
    "iso:country":"FR",
    "sg:address":"1 Rue Ren\u00e9 Cassin 95220 Herblay",
    "sg:classifiers":[
        {
            "category":"Building & Trades",
            "subcategory":"Construction",
            "type":"Services"
        }
    ],
    "sg:phone":"+33 1 39 31 60 00",
    "sg:postcode":"95220",
    "sg:province":"Ile de France",
    "sg:tags":[
        "work",
        "public"
    ],
    "wof:name":"Sobea Environnement",
    "wof:placetype":"venue"
},
  "geometry": {"coordinates":[2.185134,48.996941],"type":"Point"}
}