{
  "type": "Feature",
  "properties": {
    "addr:full":"Zac Des 60 Jours 57685 Augny Lorraine",
    "addr:housenumber":"zac",
    "addr:postcode":"57685",
    "addr:street":"Des 60 Jours",
    "iso:country":"FR",
    "sg:address":"Zac Des 60 Jours 57685 Augny",
    "sg:classifiers":[
        {
            "category":"Travel",
            "subcategory":"Hotels & Motels",
            "type":"Entertainment"
        }
    ],
    "sg:phone":"+33 3 87 56 05 48",
    "sg:province":"Lorraine",
    "sg:tags":[
        "hotels",
        "business",
        "restaurant"
    ],
    "wof:name":"Serare Courte Paille",
    "wof:placetype":"venue"
},
  "geometry": {"coordinates":[6.122042,49.058556],"type":"Point"}
}