{
  "type": "Feature",
  "properties": {
    "addr:full":"232 Rue Paul Bert 69003 Lyon Rhone-Alpes 69003",
    "addr:housenumber":"232",
    "addr:postcode":"69003;69003",
    "addr:street":"Rue Paul Bert",
    "iso:country":"FR",
    "sg:address":"232 Rue Paul Bert 69003 Lyon",
    "sg:classifiers":[
        {
            "category":"Professional",
            "subcategory":"Business Services",
            "type":"Services"
        }
    ],
    "sg:phone":"+33 4 72 12 01 01",
    "sg:postcode":"69003",
    "sg:province":"Rhone-Alpes",
    "sg:tags":[
        "training",
        "advice"
    ],
    "wof:name":"Ecole Emile Cohl",
    "wof:placetype":"venue"
},
  "geometry": {"coordinates":[4.865814,45.75668],"type":"Point"}
}