{
  "type": "Feature",
  "properties": {
    "iso:country":"FR",
    "sg:address":"Z.I. du Jalday",
    "sg:city":"Saint Jean de Luz",
    "sg:orig_category":"Unclassifiable Establishments",
    "sg:phone":"+33 5 59 51 92 00",
    "sg:postcode":"64500",
    "sg:province":"Aquitaine",
    "wof:name":"Olano Logistique Du Froid S.a.r.l.",
    "wof:placetype":"venue"
},
  "geometry": {"coordinates":[-1.660884,43.38773],"type":"Point"}
}