{
  "type": "Feature",
  "properties": {
    "iso:country":"FR",
    "sg:address":"B.P. 22, 88290 Saulxures sur Moselotte^^Rue les Amias, 88290 Saulxures sur Moselotte",
    "sg:orig_category":"Non-Classified Establishments",
    "sg:phone":"+33 3 29 24 60 55",
    "sg:province":"Lorraine",
    "wof:name":"Gerbois S.a.",
    "wof:placetype":"venue"
},
  "geometry": {"coordinates":[6.772985,47.949284],"type":"Point"}
}