{
  "type": "Feature",
  "properties": {
    "iso:country":"FR",
    "sg:address":"18, Rue Blanqui, 10100 Romilly sur Seine",
    "sg:orig_category":"Unclassifiable Establishments",
    "sg:phone":"+33 3 25 24 83 12",
    "sg:province":"Champagne",
    "wof:name":"Morizot S.a.r.l.",
    "wof:placetype":"venue"
},
  "geometry": {"coordinates":[3.733108,48.515373],"type":"Point"}
}