{
  "type": "Feature",
  "properties": {
    "addr:full":"18, Rue Blanqui, 10100 Romilly sur Seine Champagne",
    "addr:housenumber":"18",
    "addr:postcode":"10100",
    "addr:street":"Rue Blanqui",
    "iso:country":"FR",
    "sg:address":"18, Rue Blanqui, 10100 Romilly sur Seine",
    "sg:orig_category":"Unclassifiable Establishments",
    "sg:phone":"+33 3 25 24 83 12",
    "sg:province":"Champagne",
    "wof:name":"Morizot S.a.r.l.",
    "wof:placetype":"venue"
},
  "geometry": {"coordinates":[3.733108,48.515373],"type":"Point"}
}