{
  "type": "Feature",
  "properties": {
    "iso:country":"FR",
    "sg:address":"92 Rue Reaumur 75002 Paris",
    "sg:classifiers":[
        {
            "category":"Banks & Credit Unions",
            "subcategory":"Financial Services",
            "type":"Services"
        }
    ],
    "sg:phone":"+33 1 42 68 22 68",
    "sg:postcode":"75002",
    "sg:province":"Ile de France",
    "sg:tags":[
        "banking",
        "insurance",
        "institution",
        "finance"
    ],
    "wof:name":"Indreco",
    "wof:placetype":"venue"
},
  "geometry": {"coordinates":[2.349833,48.866928],"type":"Point"}
}