{
  "type": "Feature",
  "properties": {
    "addr:full":"6 all\u00e9e de la Garenne 28100 Dreux Dreux Centre 28100",
    "addr:housenumber":"6;dreux",
    "addr:postcode":"28100;28100",
    "addr:street":"Alle\u0301E De La Garenne",
    "iso:country":"FR",
    "sg:address":"6 all\u00e9e de la Garenne 28100 Dreux",
    "sg:city":"Dreux",
    "sg:orig_category":"Deep-Drawing, Hydromechanical",
    "sg:phone":"+33 2 37 42 51 00",
    "sg:postcode":"28100",
    "sg:province":"Centre",
    "wof:name":"Aginco S.a.",
    "wof:placetype":"venue"
},
  "geometry": {"coordinates":[1.360018,48.750362],"type":"Point"}
}