{
  "type": "Feature",
  "properties": {
    "addr:full":"RN 31 Rte de Clermont Beauvais Picardie 60000",
    "addr:postcode":"60000",
    "addr:street":"Rn 31 Rte De Clermont;Picardie",
    "iso:country":"FR",
    "sg:address":"RN 31 Rte de Clermont",
    "sg:city":"Beauvais",
    "sg:orig_category":"Unclassifiable Establishments",
    "sg:phone":"+33 802 08 44 44",
    "sg:postcode":"60000",
    "sg:province":"Picardie",
    "wof:name":"Lefevre Manutention",
    "wof:placetype":"venue"
},
  "geometry": {"coordinates":[2.10356,49.431934],"type":"Point"}
}