{
  "type": "Feature",
  "properties": {
    "addr:full":"12, Rue Mara\u00eechers, 10120 Saint Andr\u00e9 les Vergers Champagne",
    "addr:housenumber":"12",
    "addr:postcode":"10120",
    "addr:street":"Rue Marai\u0302Chers;Andre\u0301 Les",
    "iso:country":"FR",
    "sg:address":"12, Rue Mara\u00eechers, 10120 Saint Andr\u00e9 les Vergers",
    "sg:orig_category":"Unclassifiable Establishments",
    "sg:phone":"+33 3 25 82 14 01",
    "sg:province":"Champagne",
    "wof:name":"Distrilab Industrie",
    "wof:placetype":"venue"
},
  "geometry": {"coordinates":[4.042673,48.267574],"type":"Point"}
}