{
  "type": "Feature",
  "properties": {
    "addr:full":"69, Bd Bessi\u00e8res, 75017 Paris Ile de France",
    "addr:housenumber":"69",
    "addr:postcode":"75017",
    "addr:street":"Bd Bessie\u0300Res",
    "iso:country":"FR",
    "sg:address":"69, Bd Bessi\u00e8res, 75017 Paris",
    "sg:orig_category":"Unclassifiable Establishments",
    "sg:phone":"+33 1 53 06 16 16",
    "sg:province":"Ile de France",
    "wof:name":"Elucyd\u00e9e S.a.",
    "wof:placetype":"venue"
},
  "geometry": {"coordinates":[2.321264,48.897072],"type":"Point"}
}