{
  "type": "Feature",
  "properties": {
    "iso:country":"FR",
    "sg:address":"B.P. 55, 45520 Chevilly C\u00e9dex^^6, Rue de l'Hermitage, 45520 Chevilly",
    "sg:city":"Chevilly",
    "sg:orig_category":"Non-Classified Establishments",
    "sg:phone":"+33 2 38 80 10 57",
    "sg:postcode":"45520",
    "sg:province":"Centre",
    "wof:name":"S.n.u.p. S.a.",
    "wof:placetype":"venue"
},
  "geometry": {"coordinates":[1.851472,48.022999],"type":"Point"}
}