{
  "type": "Feature",
  "properties": {
    "iso:country":"FR",
    "sg:address":"9 Chemin Des Silos 31100 Toulouse",
    "sg:classifiers":[
        {
            "category":"Shopping",
            "subcategory":"Computers & Home Electronics",
            "type":"Retail Goods"
        }
    ],
    "sg:phone":"+33 5 62 20 09 20",
    "sg:postcode":"31100",
    "sg:province":"Midi Pyr\u00e9n\u00e9es",
    "sg:tags":[
        "equipment",
        "electrical",
        "component",
        "electric",
        "electronic"
    ],
    "wof:name":"Jenitranes",
    "wof:placetype":"venue"
},
  "geometry": {"coordinates":[1.420081,43.556759],"type":"Point"}
}