{
  "type": "Feature",
  "properties": {
    "addr:full":"30 Wettolsheim Alsace 68920",
    "addr:housenumber":"30",
    "addr:postcode":"68920",
    "addr:street":"Wettolsheim Alsace",
    "iso:country":"FR",
    "sg:address":"30",
    "sg:city":"Wettolsheim",
    "sg:classifiers":[
        {
            "category":"Food Court",
            "type":"Food & Drink"
        }
    ],
    "sg:phone":"+33 3 89 80 62 92",
    "sg:postcode":"68920",
    "sg:province":"Alsace",
    "sg:tags":[
        "product",
        "related"
    ],
    "wof:name":"Barmes Buecher",
    "wof:placetype":"venue"
},
  "geometry": {"coordinates":[7.298829,48.06015],"type":"Point"}
}