{
  "type": "Feature",
  "properties": {
    "addr:full":"15, Chemin de la Crabe, 31300 Toulouse Midi Pyr\u00e9n\u00e9es 31300",
    "addr:housenumber":"15",
    "addr:postcode":"31300;31300",
    "addr:street":"Chemin De La Crabe",
    "iso:country":"FR",
    "sg:address":"15, Chemin de la Crabe, 31300 Toulouse",
    "sg:orig_category":"Non-Classified Establishments",
    "sg:phone":"+33 5 61 15 88 48",
    "sg:postcode":"31300",
    "sg:province":"Midi Pyr\u00e9n\u00e9es",
    "wof:name":"A.r. Consultants S.a.r.l.",
    "wof:placetype":"venue"
},
  "geometry": {"coordinates":[1.375407,43.610676],"type":"Point"}
}