{
  "type": "Feature",
  "properties": {
    "addr:full":"1/3, Quai de Grenelle, 75015 Paris Ile de France",
    "addr:housenumber":"1 / 3",
    "addr:postcode":"75015",
    "addr:street":"Quai De Grenelle",
    "iso:country":"FR",
    "sg:address":"1/3, Quai de Grenelle, 75015 Paris",
    "sg:orig_category":"Unclassifiable Establishments",
    "sg:phone":"+33 1 44 37 75 00",
    "sg:province":"Ile de France",
    "wof:name":"Pharma-lab S.a.",
    "wof:placetype":"venue"
},
  "geometry": {"coordinates":[2.288623,48.854328],"type":"Point"}
}