{
  "type": "Feature",
  "properties": {
    "addr:full":"Av Franklin Roosevelt - ZI du Grand Launay Le Grand Quevilly Haute Normandie 76120",
    "addr:postcode":"76120",
    "addr:street":"Av Franklin Roosevelt Zi Du Grand Launay;Haute Normandie",
    "iso:country":"FR",
    "sg:address":"Av Franklin Roosevelt - ZI du Grand Launay",
    "sg:city":"Le Grand Quevilly",
    "sg:orig_category":"Non-Classified Establishments",
    "sg:phone":"+33 2 32 11 45 45",
    "sg:postcode":"76120",
    "sg:province":"Haute Normandie",
    "wof:name":"Normandie Accessoires S.a.",
    "wof:placetype":"venue"
},
  "geometry": {"coordinates":[1.05078,49.408234],"type":"Point"}
}