{
  "type": "Feature",
  "properties": {
    "addr:full":"B.P. 59 Saint Loub\u00e8s C\u00e9dex^^Domaine du Ribet 33450 Saint Loub\u00e8s Aquitaine 33451",
    "addr:housenumber":"59",
    "addr:postcode":"33450;33451",
    "addr:street":"B.P.;Saint Loube\u0300S Ce\u0301Dex^^Domaine Du Ribet",
    "iso:country":"FR",
    "sg:address":"B.P. 59",
    "sg:city":"Saint Loub\u00e8s C\u00e9dex^^Domaine du Ribet 33450 Saint Loub\u00e8s",
    "sg:orig_category":"Non-Classified Establishments",
    "sg:phone":"+33 5 57 97 07 20",
    "sg:postcode":"33451",
    "sg:province":"Aquitaine",
    "wof:name":"G.v.g. S.a. - Grands Vins De Gironde",
    "wof:placetype":"venue"
},
  "geometry": {"coordinates":[-0.428015,44.881542],"type":"Point"}
}