{
  "type": "Feature",
  "properties": {
    "addr:full":"16, Rue Emile Chautemps, 74300 Cluses Rhone-Alpes 74300",
    "addr:housenumber":"16",
    "addr:postcode":"74300;74300",
    "addr:street":"Rue Emile Chautemps",
    "iso:country":"FR",
    "sg:address":"16, Rue Emile Chautemps, 74300 Cluses",
    "sg:orig_category":"Non-Classified Establishments",
    "sg:phone":"+33 4 50 98 57 52",
    "sg:postcode":"74300",
    "sg:province":"Rhone-Alpes",
    "wof:name":"I.b.s. S.a. - Informatique Bureautique Service",
    "wof:placetype":"venue"
},
  "geometry": {"coordinates":[6.575664,46.060822],"type":"Point"}
}