{
  "type": "Feature",
  "properties": {
    "addr:full":"Rue de Balme Cerdon Rhone-Alpes 01450",
    "addr:postcode":"01450",
    "addr:street":"Rue De Balme;Rhone-Alpes",
    "iso:country":"FR",
    "sg:address":"Rue de Balme",
    "sg:city":"Cerdon",
    "sg:orig_category":"Non-Classified Establishments",
    "sg:phone":"+33 4 74 39 97 77",
    "sg:postcode":"01450",
    "sg:province":"Rhone-Alpes",
    "wof:name":"Champagne Mailly Grand Cru G.a.e.c.",
    "wof:placetype":"venue"
},
  "geometry": {"coordinates":[5.447391,46.108112],"type":"Point"}
}