{
  "type": "Feature",
  "properties": {
    "addr:full":"Pont Chevalier 07100 Annonay Rhone-Alpes 07100",
    "addr:postcode":"07100;07100",
    "addr:street":"Pont Chevalier",
    "iso:country":"FR",
    "sg:address":"Pont Chevalier 07100 Annonay",
    "sg:classifiers":[
        {
            "category":"Government",
            "subcategory":"Department Of Motor Vehicles",
            "type":"Public Place"
        }
    ],
    "sg:phone":"+33 4 75 67 67 53",
    "sg:postcode":"07100",
    "sg:province":"Rhone-Alpes",
    "sg:tags":[
        "equipment",
        "industrial",
        "transport",
        "motor-cars"
    ],
    "wof:name":"Realisation Chaudronne Construction Metallique Sarl (rccm)",
    "wof:placetype":"venue"
},
  "geometry": {"coordinates":[4.671922,45.235989],"type":"Point"}
}