{
  "type": "Feature",
  "properties": {
    "addr:full":"Parc d'Activit\u00e9s de la Fringalle Val de Reuil Haute Normandie 27100",
    "addr:postcode":"27100",
    "iso:country":"FR",
    "sg:address":"Parc d'Activit\u00e9s de la Fringalle",
    "sg:city":"Val de Reuil",
    "sg:orig_category":"Unclassifiable Establishments",
    "sg:phone":"+33 2 32 09 44 55",
    "sg:postcode":"27100",
    "sg:province":"Haute Normandie",
    "wof:name":"Trouw Nutrition France S.a.",
    "wof:placetype":"venue"
},
  "geometry": {"coordinates":[1.21381,49.257622],"type":"Point"}
}