{
  "type": "Feature",
  "properties": {
    "iso:country":"FR",
    "sg:address":"Zone Commerciale Reneac H 56400 Plougoumelen",
    "sg:city":"Plougoumelen",
    "sg:classifiers":[
        {
            "category":"Utilities",
            "subcategory":"Mobile Phone",
            "type":"Services"
        }
    ],
    "sg:phone":"+33 2 97 24 34 34",
    "sg:postcode":"56400",
    "sg:province":"Bretagne",
    "sg:tags":[
        "telecommunication",
        "audio-visual"
    ],
    "wof:name":"Innova Son",
    "wof:placetype":"venue"
},
  "geometry": {"coordinates":[-2.916154,47.654373],"type":"Point"}
}