{
  "type": "Feature",
  "properties": {
    "addr:full":"ZI Rive Gauche Langogne Languedoc-Roussillon 48300",
    "addr:postcode":"48300",
    "iso:country":"FR",
    "sg:address":"ZI Rive Gauche",
    "sg:city":"Langogne",
    "sg:orig_category":"Non-Classified Establishments",
    "sg:phone":"+33 4 66 69 30 88",
    "sg:postcode":"48300",
    "sg:province":"Languedoc-Roussillon",
    "wof:name":"Le Jardin D'hitena S.a.r.l.",
    "wof:placetype":"venue"
},
  "geometry": {"coordinates":[3.856037,44.72657],"type":"Point"}
}