{
  "type": "Feature",
  "properties": {
    "addr:full":"32, Rue de Barbieux, 59100 Roubaix Nord Pas-de-Calais",
    "addr:housenumber":"32",
    "addr:postcode":"59100",
    "addr:street":"Rue De Barbieux",
    "iso:country":"FR",
    "sg:address":"32, Rue de Barbieux, 59100 Roubaix",
    "sg:orig_category":"Unclassifiable Establishments",
    "sg:phone":"+33 3 20 20 62 62",
    "sg:province":"Nord Pas-de-Calais",
    "wof:name":"C.p.i. S.a.",
    "wof:placetype":"venue"
},
  "geometry": {"coordinates":[3.17169,50.68148],"type":"Point"}
}