{
  "type": "Feature",
  "properties": {
    "addr:full":"34 R De La R\u00e9publique 01202 Bellegarde Sur Valserine Cedex Bellegarde Languedoc-Roussillon 30127",
    "addr:housenumber":"34",
    "addr:postcode":"01202;valserine cedex bellegarde;30127",
    "addr:street":"R De La Re\u0301Publique",
    "iso:country":"FR",
    "sg:address":"34 R De La R\u00e9publique 01202 Bellegarde Sur Valserine Cedex",
    "sg:city":"Bellegarde",
    "sg:classifiers":[
        {
            "category":"Professional",
            "subcategory":"Business Services",
            "type":"Services"
        }
    ],
    "sg:phone":"+33 4 50 56 60 60",
    "sg:postcode":"30127",
    "sg:province":"Languedoc-Roussillon",
    "sg:tags":[
        "body",
        "advice"
    ],
    "wof:name":"Commune De Bellegarde Sur Valserine",
    "wof:placetype":"venue"
},
  "geometry": {"coordinates":[5.826209,46.107601],"type":"Point"}
}