{
  "type": "Feature",
  "properties": {
    "iso:country":"FR",
    "sg:address":"19/21, Rue du Bois Rochefort - ZA des Perriers, 78500 Sartrouville",
    "sg:orig_category":"Unclassifiable Establishments",
    "sg:phone":"+33 1 39 15 21 77",
    "sg:province":"Ile de France",
    "wof:name":"Protostyle S.a.r.l.",
    "wof:placetype":"venue"
},
  "geometry": {"coordinates":[2.16183,48.941525],"type":"Point"}
}