{
  "type": "Feature",
  "properties": {
    "addr:full":"19, Fbg de Gien, 45260 Lorris Lorris Centre 45260",
    "addr:housenumber":"19",
    "addr:postcode":"45260;45260",
    "addr:street":"Fbg De Gien",
    "iso:country":"FR",
    "sg:address":"19, Fbg de Gien, 45260 Lorris",
    "sg:city":"Lorris",
    "sg:orig_category":"Non-Classified Establishments",
    "sg:phone":"+33 2 38 92 40 28",
    "sg:postcode":"45260",
    "sg:province":"Centre",
    "wof:name":"Duchesne Constructions M\u00e9caniques S.a.",
    "wof:placetype":"venue"
},
  "geometry": {"coordinates":[2.531105,47.85067],"type":"Point"}
}