{
  "type": "Feature",
  "properties": {
    "addr:full":"55 Avenue Stade 74952 Scionzier Cedex Midi Pyr\u00e9n\u00e9es",
    "addr:housenumber":"55",
    "addr:postcode":"74952 scionzier cedex midi",
    "addr:street":"Avenue Stade",
    "iso:country":"FR",
    "sg:address":"55 Avenue Stade 74952 Scionzier Cedex",
    "sg:orig_category":"Mechanical Engineering - machines Metallurgy and Metalworking Metals - machinery and equipment Profe",
    "sg:phone":"+33 4 50 98 34 44",
    "sg:province":"Midi Pyr\u00e9n\u00e9es",
    "wof:name":"Modern Industrie Sa",
    "wof:placetype":"venue"
},
  "geometry": {"coordinates":[6.551157,46.063725],"type":"Point"}
}