{
  "type": "Feature",
  "properties": {
    "iso:country":"FR",
    "sg:address":"9 route du Menil 88160 Le Thillot",
    "sg:classifiers":[
        {
            "category":"Government",
            "subcategory":"City Hall",
            "type":"Public Place"
        }
    ],
    "sg:phone":"+33 3 29 25 29 29",
    "sg:postcode":"88160",
    "sg:province":"Lorraine",
    "sg:tags":[
        "interior",
        "painting"
    ],
    "wof:name":"N\u00e9otec-france Sa",
    "wof:placetype":"venue"
},
  "geometry": {"coordinates":[6.775623,47.891876],"type":"Point"}
}