{
  "type": "Feature",
  "properties": {
    "addr:full":"2 Rue Lobstein Strasbourg Cedex Alsace 67004",
    "addr:housenumber":"2",
    "addr:postcode":"cedex;67004",
    "addr:street":"Rue Lobstein",
    "iso:country":"FR",
    "sg:address":"2 Rue Lobstein",
    "sg:city":"Strasbourg Cedex",
    "sg:classifiers":[
        {
            "category":"Banks & Credit Unions",
            "subcategory":"Financial Services",
            "type":"Services"
        }
    ],
    "sg:phone":"+33 3 88 25 25 25",
    "sg:postcode":"67004",
    "sg:province":"Alsace",
    "sg:tags":[
        "banking",
        "finance",
        "insurance"
    ],
    "wof:name":"Caisse Regionale D Assurance Maladie",
    "wof:placetype":"venue"
},
  "geometry": {"coordinates":[7.765508,48.582809],"type":"Point"}
}