{
  "type": "Feature",
  "properties": {
    "iso:country":"FR",
    "sg:address":"13, Rue Tannmuhle, 67310 Romanswiller",
    "sg:city":"Romanswiller",
    "sg:orig_category":"LUBRIFIANTS SP\u00c9CIAUX, GRAISSES, HUILES, P\u00c2TES, M\u00c9LANGES DE POUDRES ET A\u00c9ROSOLS",
    "sg:phone":"+33 3 88 59 11 59",
    "sg:postcode":"67310",
    "sg:province":"Alsace",
    "wof:name":"S.e.t.r.a.l. S.a.r.l. - Soci\u00e9t\u00e9 D'etudes Techniques Recherches Applications Lubrification",
    "wof:placetype":"venue"
},
  "geometry": {"coordinates":[7.39288,48.644081],"type":"Point"}
}