{
  "type": "Feature",
  "properties": {
    "iso:country":"FR",
    "sg:address":"Usine De Saint Jean Route Minervoise 11000 Carcassonne",
    "sg:classifiers":[
        {
            "category":"Manufacturing",
            "subcategory":"Rubber & Plastics",
            "type":"Manufacturing & Wholesale Goods"
        }
    ],
    "sg:phone":"+33 4 68 79 58 00",
    "sg:province":"Languedoc-Roussillon",
    "wof:name":"Polynauve",
    "wof:placetype":"venue"
},
  "geometry": {"coordinates":[2.306378,43.188465],"type":"Point"}
}