{
  "type": "Feature",
  "properties": {
    "addr:full":"18 Avenue Montaigne 75008 Paris Ile de France 75008",
    "addr:housenumber":"18",
    "addr:postcode":"75008;75008",
    "addr:street":"Avenue Montaigne",
    "iso:country":"FR",
    "sg:address":"18 Avenue Montaigne 75008 Paris",
    "sg:classifiers":[
        {
            "category":"Shopping",
            "subcategory":"Crafts & Fabrics",
            "type":"Retail Goods"
        }
    ],
    "sg:phone":"+33 1 47 20 75 25",
    "sg:postcode":"75008",
    "sg:province":"Ile de France",
    "sg:tags":[
        "textile",
        "linen",
        "clothing"
    ],
    "wof:name":"Porthault Sa",
    "wof:placetype":"venue"
},
  "geometry": {"coordinates":[2.304721,48.86594],"type":"Point"}
}