{
  "type": "Feature",
  "properties": {
    "iso:country":"FR",
    "sg:address":"150 Boulevard De L'Ariane R\u00e9sidence Le Paillon B\u00e2t 4 06359 Cedex 4",
    "sg:classifiers":[
        {
            "category":"Building & Trades",
            "subcategory":"Construction",
            "type":"Services"
        }
    ],
    "sg:phone":"+33 4 97 00 05 80",
    "sg:province":"Centre",
    "sg:tags":[
        "work",
        "public"
    ],
    "wof:name":"Sn Vigna A M",
    "wof:placetype":"venue"
},
  "geometry": {"coordinates":[-71.879608,41.4659],"type":"Point"}
}