{
  "type": "Feature",
  "properties": {
    "addr:full":"15-19, Rue Etienne Dolet, 76140 Le Petit Quevilly Haute Normandie",
    "addr:housenumber":"15-19",
    "addr:postcode":"76140",
    "addr:street":"Rue Etienne Dolet;Le Petit Quevilly Haute Normandie",
    "iso:country":"FR",
    "sg:address":"15-19, Rue Etienne Dolet, 76140 Le Petit Quevilly",
    "sg:orig_category":"Unclassifiable Establishments",
    "sg:phone":"+33 2 32 81 63 30",
    "sg:province":"Haute Normandie",
    "wof:name":"Saproden D\u00e9veloppement S.a.",
    "wof:placetype":"venue"
},
  "geometry": {"coordinates":[1.046492,49.431934],"type":"Point"}
}