{
  "type": "Feature",
  "properties": {
    "addr:full":"11, Rue Raymond Lefevre, 93891 Livry Gargan C\u00e9dex Champagne",
    "addr:housenumber":"11",
    "addr:postcode":"93891",
    "addr:street":"Rue Raymond Lefevre",
    "iso:country":"FR",
    "sg:address":"11, Rue Raymond Lefevre, 93891 Livry Gargan C\u00e9dex",
    "sg:orig_category":"Non-Classified Establishments",
    "sg:phone":"+33 1 43 83 56 21",
    "sg:province":"Champagne",
    "wof:name":"Emroll S.a.",
    "wof:placetype":"venue"
},
  "geometry": {"coordinates":[2.553678,48.930897],"type":"Point"}
}