{
  "type": "Feature",
  "properties": {
    "addr:full":"39 Avenue J Baptiste Lebas 59100 Roubaix Nord Pas-de-Calais 59100",
    "addr:housenumber":"39",
    "addr:postcode":"59100;59100",
    "addr:street":"Avenue J Baptiste Lebas",
    "iso:country":"FR",
    "sg:address":"39 Avenue J Baptiste Lebas 59100 Roubaix",
    "sg:classifiers":[
        {
            "category":"Food Court",
            "type":"Food & Drink"
        }
    ],
    "sg:phone":"+33 3 20 36 21 17",
    "sg:postcode":"59100",
    "sg:province":"Nord Pas-de-Calais",
    "sg:tags":[
        "product",
        "related"
    ],
    "wof:name":"Kalys Sa",
    "wof:placetype":"venue"
},
  "geometry": {"coordinates":[3.170452,50.6926],"type":"Point"}
}