{
  "type": "Feature",
  "properties": {
    "addr:full":"28/30, Bd Roger Salengro, 78200 Mantes la Ville Ile de France",
    "addr:housenumber":"28 / 30",
    "addr:postcode":"78200",
    "addr:street":"Bd Roger Salengro",
    "iso:country":"FR",
    "sg:address":"28/30, Bd Roger Salengro, 78200 Mantes la Ville",
    "sg:orig_category":"Unclassifiable Establishments",
    "sg:phone":"+33 1 34 78 89 46",
    "sg:province":"Ile de France",
    "wof:name":"Wartsila N.s.d. France S.a.",
    "wof:placetype":"venue"
},
  "geometry": {"coordinates":[-97.928825,26.298334],"type":"Point"}
}