{
  "type": "Feature",
  "properties": {
    "iso:country":"FR",
    "sg:address":"Rte D'Arthez De B\u00e9arn BP 17 64300 Mont",
    "sg:city":"Mont",
    "sg:classifiers":[
        {
            "category":"Shopping",
            "type":"Retail Goods"
        }
    ],
    "sg:phone":"+33 5 59 38 77 77",
    "sg:postcode":"64300",
    "sg:province":"Aquitaine",
    "sg:tags":[
        "metallurgy",
        "finished",
        "-",
        "metalworking",
        "metallic"
    ],
    "wof:name":"Rexam Sas",
    "wof:placetype":"venue"
},
  "geometry": {"coordinates":[-0.775408,43.501228],"type":"Point"}
}