{
  "type": "Feature",
  "properties": {
    "iso:country":"FR",
    "sg:address":"3 rue du Rouy 27950 ST MARCEL",
    "sg:classifiers":[
        {
            "category":"Wholesale",
            "subcategory":"Metals & Minerals",
            "type":"Manufacturing & Wholesale Goods"
        }
    ],
    "sg:phone":"+33 2 32 64 51 51",
    "sg:postcode":"27950",
    "sg:province":"Haute Normandie",
    "sg:tags":[
        "packaging"
    ],
    "wof:name":"Tapon-france S.a.",
    "wof:placetype":"venue"
},
  "geometry": {"coordinates":[1.445772,49.098995],"type":"Point"}
}