{
  "type": "Feature",
  "properties": {
    "addr:full":"79, Rue de la R\u00e9publique, 93000 Bobigny Ile de France",
    "addr:housenumber":"79",
    "addr:postcode":"93000;ile",
    "addr:street":"Rue De La Re\u0301Publique",
    "iso:country":"FR",
    "sg:address":"79, Rue de la R\u00e9publique, 93000 Bobigny",
    "sg:orig_category":"Unclassifiable Establishments",
    "sg:phone":"+33 1 48 30 36 36",
    "sg:province":"Ile de France",
    "wof:name":"Dursapt S.a.",
    "wof:placetype":"venue"
},
  "geometry": {"coordinates":[2.433459,48.906582],"type":"Point"}
}