{
  "type": "Feature",
  "properties": {
    "addr:full":"2, Rue Rosset, 39200 Saint Claude Franche Comt\u00e9",
    "addr:housenumber":"2",
    "addr:postcode":"39200",
    "addr:street":"Rue Rosset;Franche Comte\u0301",
    "iso:country":"FR",
    "sg:address":"2, Rue Rosset, 39200 Saint Claude",
    "sg:orig_category":"Unclassifiable Establishments",
    "sg:phone":"+33 3 84 45 15 08",
    "sg:province":"Franche Comt\u00e9",
    "wof:name":"Farlac S.a.",
    "wof:placetype":"venue"
},
  "geometry": {"coordinates":[5.865537,46.389118],"type":"Point"}
}