{
  "type": "Feature",
  "properties": {
    "addr:full":"B.P. 14, 79301 Bressuire C\u00e9dex^^79, Bd du Mar\u00e9chal Foch, 79300 Bressuire Poitou-Charentes",
    "addr:postcode":"79301;ce\u0301dex^^79;79300",
    "addr:street":"B.P. 14;Bd Du Mare\u0301Chal Foch",
    "iso:country":"FR",
    "sg:address":"B.P. 14, 79301 Bressuire C\u00e9dex^^79, Bd du Mar\u00e9chal Foch, 79300 Bressuire",
    "sg:orig_category":"Non-Classified Establishments",
    "sg:phone":"+33 5 49 65 02 40",
    "sg:province":"Poitou-Charentes",
    "wof:name":"Grimaud Mat\u00e9riel S.a.",
    "wof:placetype":"venue"
},
  "geometry": {"coordinates":[-0.434544,46.774929],"type":"Point"}
}