{
  "type": "Feature",
  "properties": {
    "addr:full":"15, Av. de Fontcouverte, 84000 Avignon Fontcouverte Poitou-Charentes 17100",
    "addr:postcode":"84000;17100",
    "addr:street":"15 Av. De Fontcouverte",
    "iso:country":"FR",
    "sg:address":"15, Av. de Fontcouverte, 84000 Avignon",
    "sg:city":"Fontcouverte",
    "sg:orig_category":"Unclassifiable Establishments",
    "sg:phone":"+33 4 90 88 54 67",
    "sg:postcode":"17100",
    "sg:province":"Poitou-Charentes",
    "wof:name":"Etablissements Bouzon S.a.",
    "wof:placetype":"venue"
},
  "geometry": {"coordinates":[4.843,43.937695],"type":"Point"}
}