{
  "type": "Feature",
  "properties": {
    "addr:full":"92/98, Rue de Tours, 41400 Montrichard Montrichard Centre 41400",
    "addr:housenumber":"92 / 98",
    "addr:postcode":"41400;41400",
    "addr:street":"Rue De Tours;Montrichard",
    "iso:country":"FR",
    "sg:address":"92/98, Rue de Tours, 41400 Montrichard",
    "sg:city":"Montrichard",
    "sg:orig_category":"Unclassifiable Establishments",
    "sg:phone":"+33 2 54 32 00 60",
    "sg:postcode":"41400",
    "sg:province":"Centre",
    "wof:name":"Ch\u00e9ry-dion S.a.r.l.",
    "wof:placetype":"venue"
},
  "geometry": {"coordinates":[1.179398,47.342117],"type":"Point"}
}