{
  "type": "Feature",
  "properties": {
    "iso:country":"FR",
    "sg:address":"9, Rue Froment, 75009 Paris",
    "sg:orig_category":"Non-Classified Establishments",
    "sg:phone":"+33 1 45 26 79 89",
    "sg:province":"Ile de France",
    "wof:name":"Harden S.a.",
    "wof:placetype":"venue"
},
  "geometry": {"coordinates":[2.334543,48.882706],"type":"Point"}
}