{
  "type": "Feature",
  "properties": {
    "iso:country":"FR",
    "sg:address":"95 Rue De Neuf Mesnil Cite De L Entreprise 59750 Feignies",
    "sg:classifiers":[
        {
            "category":"Manufacturing",
            "subcategory":"Metals",
            "type":"Manufacturing & Wholesale Goods"
        }
    ],
    "sg:phone":"+33 3 27 63 98 12",
    "sg:postcode":"59750",
    "sg:province":"Nord Pas-de-Calais",
    "sg:tags":[
        "-",
        "machine",
        "equipment",
        "engineering",
        "machinery",
        "mechanical"
    ],
    "wof:name":"Rectidiam",
    "wof:placetype":"venue"
},
  "geometry": {"coordinates":[3.90869,50.277302],"type":"Point"}
}