{
  "type": "Feature",
  "properties": {
    "addr:full":"Rte d'Angers Saint Fort Pays de Loire 53200",
    "addr:postcode":"53200",
    "addr:street":"Rte D'Angers Saint Fort Pays",
    "iso:country":"FR",
    "sg:address":"Rte d'Angers",
    "sg:city":"Saint Fort",
    "sg:orig_category":"Unclassifiable Establishments",
    "sg:phone":"+33 2 43 70 63 04",
    "sg:postcode":"53200",
    "sg:province":"Pays de Loire",
    "wof:name":"Chocolaterie Biscuiterie Roland R\u00e9aut\u00e9 S.a.r.l.",
    "wof:placetype":"venue"
},
  "geometry": {"coordinates":[-0.504927,45.52898],"type":"Point"}
}