{
  "type": "Feature",
  "properties": {
    "addr:full":"16 Av Des Entrepreneurs 95400 Villiers Le Bel Ile de France 95400",
    "addr:postcode":"95400;95400",
    "addr:street":"16 Av Des Entrepreneurs",
    "iso:country":"FR",
    "sg:address":"16 Av Des Entrepreneurs 95400 Villiers Le Bel",
    "sg:classifiers":[
        {
            "category":"Professional",
            "subcategory":"Engineering",
            "type":"Services"
        }
    ],
    "sg:phone":"+33 1 34 04 18 00",
    "sg:postcode":"95400",
    "sg:province":"Ile de France",
    "sg:tags":[
        "machine",
        "-",
        "mechanical"
    ],
    "wof:name":"Flo Pak",
    "wof:placetype":"venue"
},
  "geometry": {"coordinates":[2.394263,48.998428],"type":"Point"}
}