{
  "type": "Feature",
  "properties": {
    "iso:country":"FR",
    "sg:address":"Avenue Andre Roussin Quartier Saint Andre Btf90 13016 Marseille",
    "sg:classifiers":[
        {
            "category":"Shopping",
            "subcategory":"Computers & Home Electronics",
            "type":"Retail Goods"
        }
    ],
    "sg:phone":"+33 4 91 09 13 70",
    "sg:province":"Poitou-Charentes",
    "sg:tags":[
        "household",
        "appliance",
        "telecommunication",
        "audio-visual"
    ],
    "wof:name":"Mosquito",
    "wof:placetype":"venue"
},
  "geometry": {"coordinates":[5.321475,43.362785],"type":"Point"}
}