{
  "type": "Feature",
  "properties": {
    "addr:full":"22 Rue Du Moulin Villelouvette 91520 Egly Ile de France",
    "addr:housenumber":"22",
    "addr:postcode":"91520",
    "addr:street":"Rue Du Moulin Villelouvette;Ile De France",
    "iso:country":"FR",
    "sg:address":"22 Rue Du Moulin Villelouvette 91520 Egly",
    "sg:classifiers":[
        {
            "category":"Wholesale",
            "subcategory":"Machinery & Supplies",
            "type":"Manufacturing & Wholesale Goods"
        }
    ],
    "sg:phone":"+33 1 69 17 12 00",
    "sg:province":"Ile de France",
    "sg:tags":[
        "equipment",
        "precision"
    ],
    "wof:name":"Imaintel",
    "wof:placetype":"venue"
},
  "geometry": {"coordinates":[2.22171,48.57999],"type":"Point"}
}