{
  "type": "Feature",
  "properties": {
    "addr:full":"2, All\u00e9e Albert Camus, 63000 Clermont Ferrand Clermont-Ferrand Auvergne 63000",
    "addr:housenumber":"2",
    "addr:postcode":"63000;63000",
    "addr:street":"Alle\u0301E Albert Camus",
    "iso:country":"FR",
    "sg:address":"2, All\u00e9e Albert Camus, 63000 Clermont Ferrand",
    "sg:city":"Clermont-Ferrand",
    "sg:orig_category":"Non-Classified Establishments",
    "sg:phone":"+33 4 73 27 76 14",
    "sg:postcode":"63000",
    "sg:province":"Auvergne",
    "wof:name":"Denise Brachet",
    "wof:placetype":"venue"
},
  "geometry": {"coordinates":[3.113257,45.768631],"type":"Point"}
}