{
  "type": "Feature",
  "properties": {
    "addr:full":"Zone De Limay 78440 Porcheville Ile de France 78440",
    "addr:postcode":"78440;78440",
    "addr:street":"De Limay;Ile De France",
    "iso:country":"FR",
    "sg:address":"Zone De Limay 78440 Porcheville",
    "sg:classifiers":[
        {
            "category":"Manufacturing",
            "subcategory":"Chemicals & Compounds",
            "type":"Manufacturing & Wholesale Goods"
        }
    ],
    "sg:phone":"+33 1 30 98 26 26",
    "sg:postcode":"78440",
    "sg:province":"Ile de France",
    "sg:tags":[
        "pharmaceutical",
        "chemistry",
        "-",
        "by-product"
    ],
    "wof:name":"Linde Gas Sa",
    "wof:placetype":"venue"
},
  "geometry": {"coordinates":[1.77809,48.970123],"type":"Point"}
}