{
  "type": "Feature",
  "properties": {
    "iso:country":"FR",
    "sg:address":"20 Parc Du Beauvallon 57970 Illange",
    "sg:classifiers":[
        {
            "category":"Utilities",
            "subcategory":"Telephone",
            "type":"Services"
        }
    ],
    "sg:phone":"+33 3 82 82 24 00",
    "sg:province":"Centre",
    "sg:tags":[
        "telecommunication"
    ],
    "wof:name":"Zenitel Sa",
    "wof:placetype":"venue"
},
  "geometry": {"coordinates":[6.1873,49.35741],"type":"Point"}
}