{
  "type": "Feature",
  "properties": {
    "iso:country":"FR",
    "sg:address":"B.P. 36, 09190 Lorp Sentaraille C\u00e9dex^^Rte de Toulouse, 09190 Lorp Sentaraille",
    "sg:orig_category":"Non-Classified Establishments",
    "sg:phone":"+33 5 61 66 29 55",
    "sg:postcode":"09190",
    "sg:province":"Midi Pyr\u00e9n\u00e9es",
    "wof:name":"Com\u00e9ter S.a.",
    "wof:placetype":"venue"
},
  "geometry": {"coordinates":[1.121569,43.014156],"type":"Point"}
}