{
  "type": "Feature",
  "properties": {
    "addr:full":"55, Av. Pierre Piffault, 72026 le Mans C\u00e9dex R\u00e9gion Pays de la Loire",
    "addr:postcode":"72026",
    "addr:street":"55 Av. Pierre Piffault",
    "iso:country":"FR",
    "sg:address":"55, Av. Pierre Piffault, 72026 le Mans C\u00e9dex",
    "sg:orig_category":"Non-Classified Establishments",
    "sg:phone":"+33 2 43 41 33 33",
    "sg:province":"R\u00e9gion Pays de la Loire",
    "wof:name":"Partenia S.a.r.l.",
    "wof:placetype":"venue"
},
  "geometry": {"coordinates":[0.186106,47.963634],"type":"Point"}
}