{
  "type": "Feature",
  "properties": {
    "iso:country":"FR",
    "sg:address":"Rte de F\u00e9rolles - Parc d'Activit\u00e9s de Chevry",
    "sg:city":"Chevry Cossigny",
    "sg:orig_category":"Non-Classified Establishments",
    "sg:phone":"+33 1 60 62 06 06",
    "sg:postcode":"77173",
    "sg:province":"Ile de France",
    "wof:name":"Sauermann Industrie S.a.",
    "wof:placetype":"venue"
},
  "geometry": {"coordinates":[2.67479,48.72086],"type":"Point"}
}