{
  "type": "Feature",
  "properties": {
    "iso:country":"FR",
    "sg:address":"B.P. 14, 57150 Creutzwald^^ZI Lourde, 57150 Creutzwald",
    "sg:orig_category":"Non-Classified Establishments",
    "sg:phone":"+33 3 87 82 83 82",
    "sg:postcode":"57150",
    "sg:province":"Lorraine",
    "wof:name":"Creutzwald Injection S.a.",
    "wof:placetype":"venue"
},
  "geometry": {"coordinates":[6.694479,49.204865],"type":"Point"}
}