{
  "type": "Feature",
  "properties": {
    "iso:country":"FR",
    "sg:address":"Ld",
    "sg:city":"Des Vernais 74130 Vougy",
    "sg:classifiers":[
        {
            "category":"Banks & Credit Unions",
            "subcategory":"Investment Brokerage",
            "type":"Services"
        }
    ],
    "sg:phone":"+33 4 50 34 58 07",
    "sg:postcode":"74130",
    "sg:province":"Rhone-Alpes",
    "sg:tags":[
        "-",
        "transport",
        "related"
    ],
    "wof:name":"Societe Metallurgique De Revigny Smr",
    "wof:placetype":"venue"
},
  "geometry": {"coordinates":[6.388322,45.95652],"type":"Point"}
}