{
  "type": "Feature",
  "properties": {
    "addr:full":"16 rue de la Banque 75002 Paris Ile de France 75002",
    "addr:housenumber":"16",
    "addr:postcode":"75002;75002",
    "addr:street":"Rue De La Banque",
    "iso:country":"FR",
    "sg:address":"16 rue de la Banque 75002 Paris",
    "sg:classifiers":[
        {
            "category":"Manufacturing",
            "subcategory":"Paper Products",
            "type":"Manufacturing & Wholesale Goods"
        }
    ],
    "sg:phone":"+33 1 53 45 20 00",
    "sg:postcode":"75002",
    "sg:province":"Ile de France",
    "sg:tags":[
        "lining",
        "base"
    ],
    "wof:name":"Brunswick Et Fils S.a.r.l",
    "wof:placetype":"venue"
},
  "geometry": {"coordinates":[2.341114,48.867832],"type":"Point"}
}