{
  "type": "Feature",
  "properties": {
    "addr:full":"B.P. 95, 70303 Luxeuil les Bains C\u00e9dex^^ZI Guillaume Hory, 70300 Luxeuil les Bains Franche Comt\u00e9 70300",
    "addr:postcode":"70303;70300;70300",
    "addr:street":"B.P. 95;Ce\u0301Dex^^Zi Guillaume Hory;Franche Comte\u0301",
    "iso:country":"FR",
    "sg:address":"B.P. 95, 70303 Luxeuil les Bains C\u00e9dex^^ZI Guillaume Hory, 70300 Luxeuil les Bains",
    "sg:orig_category":"Non-Classified Establishments",
    "sg:phone":"+33 3 84 93 94 95",
    "sg:postcode":"70300",
    "sg:province":"Franche Comt\u00e9",
    "wof:name":"Carpenter S.a.s.",
    "wof:placetype":"venue"
},
  "geometry": {"coordinates":[6.3795,47.819172],"type":"Point"}
}