{
  "type": "Feature",
  "properties": {
    "addr:full":"Rte de Tranchepie Verneuil sur Vienne Limousin 87430",
    "addr:postcode":"87430",
    "addr:street":"Rte De Tranchepie Verneuil Sur Vienne Limousin",
    "iso:country":"FR",
    "sg:address":"Rte de Tranchepie",
    "sg:city":"Verneuil sur Vienne",
    "sg:orig_category":"Non-Classified Establishments",
    "sg:phone":"+33 5 55 00 10 08",
    "sg:postcode":"87430",
    "sg:province":"Limousin",
    "wof:name":"Campal - Coop\u00e9rative Agricole Eleveurs Moutons Plein Air",
    "wof:placetype":"venue"
},
  "geometry": {"coordinates":[1.148841,45.865746],"type":"Point"}
}