{
  "type": "Feature",
  "properties": {
    "iso:country":"FR",
    "sg:address":"12 Avenue Du 20e Corps 54000 Nancy",
    "sg:classifiers":[
        {
            "category":"Professional",
            "subcategory":"Advertising",
            "type":"Services"
        }
    ],
    "sg:phone":"+33 3 83 19 05 10",
    "sg:postcode":"54000",
    "sg:province":"Lorraine",
    "sg:tags":[
        "communication",
        "medium"
    ],
    "wof:name":"Lorpro Sarl",
    "wof:placetype":"venue"
},
  "geometry": {"coordinates":[6.190596,48.693249],"type":"Point"}
}