{
  "type": "Feature",
  "properties": {
    "iso:country":"FR",
    "sg:address":"51, Rue de la Garenne, 41600 Lamotte Beuvron",
    "sg:city":"Chaon",
    "sg:orig_category":"Non-Classified Establishments",
    "sg:phone":"+33 2 54 88 09 11",
    "sg:postcode":"41600",
    "sg:province":"Centre",
    "wof:name":"Chantier Bernard",
    "wof:placetype":"venue"
},
  "geometry": {"coordinates":[2.02112,47.602779],"type":"Point"}
}