{
  "type": "Feature",
  "properties": {
    "addr:full":"21, rue Montlaurent, 51000 Reims Champagne",
    "addr:housenumber":"21",
    "addr:postcode":"51000",
    "addr:street":"Rue Montlaurent",
    "iso:country":"FR",
    "sg:address":"21, rue Montlaurent, 51000 Reims",
    "sg:orig_category":"Non-Classified Establishments",
    "sg:phone":"+33 3 26 49 04 76",
    "sg:province":"Champagne",
    "wof:name":"S\u00e9curit\u00e9 Et Services S.a.",
    "wof:placetype":"venue"
},
  "geometry": {"coordinates":[4.04256,49.248077],"type":"Point"}
}