{
  "type": "Feature",
  "properties": {
    "addr:full":"B.P. 144, 62520 Le Touquet Paris Plage^^Av. Georges Besse, 62520 Le Touquet Paris Plage Nord Pas-de-Calais",
    "addr:housenumber":"b.p. 144",
    "addr:postcode":"62520;62520",
    "addr:street":"Touquet;Georges Besse;Touquet Paris Plage Nord",
    "iso:country":"FR",
    "sg:address":"B.P. 144, 62520 Le Touquet Paris Plage^^Av. Georges Besse, 62520 Le Touquet Paris Plage",
    "sg:orig_category":"Non-Classified Establishments",
    "sg:phone":"+33 3 21 89 04 00",
    "sg:province":"Nord Pas-de-Calais",
    "wof:name":"Sedef M. Store - Etablissement Faidherbe S.a.",
    "wof:placetype":"venue"
},
  "geometry": {"coordinates":[1.594005,50.519402],"type":"Point"}
}