{
  "type": "Feature",
  "properties": {
    "iso:country":"FR",
    "sg:address":"2 place Louis Pradel 69001 Lyon",
    "sg:classifiers":[
        {
            "category":"Shopping",
            "subcategory":"Jewelry",
            "type":"Retail Goods"
        }
    ],
    "sg:phone":"+33 4 78 28 62 60",
    "sg:province":"Rhone-Alpes",
    "sg:tags":[
        "stone",
        "setting",
        "jewellery"
    ],
    "wof:name":"Lyon Serti Sa",
    "wof:placetype":"venue"
},
  "geometry": {"coordinates":[4.837469,45.767956],"type":"Point"}
}