{
  "type": "Feature",
  "properties": {
    "addr:full":"6 rue de Ventadour; Paris; 75001 Ile de France 75001",
    "addr:housenumber":"6",
    "addr:postcode":"75001 ile;france 75001",
    "addr:street":"Rue De Ventadour",
    "iso:country":"FR",
    "sg:address":"6 rue de Ventadour; Paris; 75001",
    "sg:classifiers":[
        {
            "category":"Banks & Credit Unions",
            "subcategory":"Bank",
            "type":"Services"
        }
    ],
    "sg:phone":"+33 1 44 58 41 02",
    "sg:postcode":"75001",
    "sg:province":"Ile de France",
    "wof:name":"Banque F\u00e9d\u00e9rative, Du Cr\u00e9dit Mutuel",
    "wof:placetype":"venue"
},
  "geometry": {"coordinates":[2.334569,48.866863],"type":"Point"}
}