{
  "type": "Feature",
  "properties": {
    "iso:country":"FR",
    "sg:address":"B.P. 35",
    "sg:city":"Saint Andr\u00e9 d'Huiriat^^01290 Saint Andr\u00e9 d'Huiriat",
    "sg:orig_category":"Non-Classified Establishments",
    "sg:phone":"+33 4 74 50 19 94",
    "sg:postcode":"01290",
    "sg:province":"Rhone-Alpes",
    "wof:name":"Laboratoires N.p.c. S.a.",
    "wof:placetype":"venue"
},
  "geometry": {"coordinates":[4.91219,46.212502],"type":"Point"}
}