{
  "type": "Feature",
  "properties": {
    "addr:full":"Rue Ir\u00e8ne Fr\u00e9d\u00e9ric Joliot Curie Zi De Malitorne 18230 St Doulchard Saint-Doulchard Centre 18230",
    "addr:postcode":"18230;18230",
    "addr:street":"Rue Ire\u0300Ne Fre\u0301De\u0301Ric Joliot Curie Zi De Malitorne",
    "iso:country":"FR",
    "sg:address":"Rue Ir\u00e8ne Fr\u00e9d\u00e9ric Joliot Curie Zi De Malitorne 18230 St Doulchard",
    "sg:city":"Saint-Doulchard",
    "sg:classifiers":[
        {
            "category":"Professional",
            "subcategory":"Printing & Photocopies",
            "type":"Services"
        }
    ],
    "sg:phone":"+33 2 48 70 58 48",
    "sg:postcode":"18230",
    "sg:province":"Centre",
    "sg:tags":[
        "publishing"
    ],
    "wof:name":"Presse Portage (someco)",
    "wof:placetype":"venue"
},
  "geometry": {"coordinates":[2.35792,47.104084],"type":"Point"}
}