{
  "type": "Feature",
  "properties": {
    "addr:full":"B.P. 705, 83030 Toulon C\u00e9dex 9^^All\u00e9e d'Ath\u00e9nes - Parc d'activit\u00e9 du Plateau, 83870 Signes Aquitaine",
    "addr:housenumber":"b.p. 705",
    "addr:postcode":"83030;83870",
    "iso:country":"FR",
    "sg:address":"B.P. 705, 83030 Toulon C\u00e9dex 9^^All\u00e9e d'Ath\u00e9nes - Parc d'activit\u00e9 du Plateau, 83870 Signes",
    "sg:orig_category":"Non-Classified Establishments",
    "sg:phone":"+33 4 94 88 55 00",
    "sg:province":"Aquitaine",
    "wof:name":"International Microbio S.a.",
    "wof:placetype":"venue"
},
  "geometry": {"coordinates":[5.84984,43.275612],"type":"Point"}
}