{
  "type": "Feature",
  "properties": {
    "addr:full":"Zi Du Vazzio 20090 Ajaccio Corse 20090",
    "addr:postcode":"20090;20090",
    "addr:street":"Zi Du Vazzio",
    "iso:country":"FR",
    "sg:address":"Zi Du Vazzio 20090 Ajaccio",
    "sg:classifiers":[
        {
            "category":"Shopping",
            "subcategory":"Computers & Home Electronics",
            "type":"Retail Goods"
        }
    ],
    "sg:phone":"+33 4 95 23 79 23",
    "sg:postcode":"20090",
    "sg:province":"Corse",
    "sg:tags":[
        "electronic",
        "electrical",
        "equipment"
    ],
    "wof:name":"Sagem Ajaccio",
    "wof:placetype":"venue"
},
  "geometry": {"coordinates":[8.789329,41.934601],"type":"Point"}
}