{
  "type": "Feature",
  "properties": {
    "addr:full":"2, Rue Amp\u00e8re, 62000 Arras Nord Pas-de-Calais",
    "addr:housenumber":"2",
    "addr:postcode":"62000",
    "addr:street":"Rue Ampe\u0300Re",
    "iso:country":"FR",
    "sg:address":"2, Rue Amp\u00e8re, 62000 Arras",
    "sg:orig_category":"Non-Classified Establishments",
    "sg:phone":"+33 3 21 21 31 80",
    "sg:province":"Nord Pas-de-Calais",
    "wof:name":"Pinault Nord Est, S.a.",
    "wof:placetype":"venue"
},
  "geometry": {"coordinates":[2.739042,50.299343],"type":"Point"}
}