{
  "type": "Feature",
  "properties": {
    "iso:country":"FR",
    "sg:address":"126 Quai De La Souys 33100 Bordeaux",
    "sg:city":"Bordeaux",
    "sg:orig_category":"Drinks Food and Related Products Food processing - machinery and equipment Mechanical Engineering - ",
    "sg:phone":"+33 5 57 77 92 92",
    "sg:postcode":"33100",
    "sg:province":"Aquitaine",
    "wof:name":"Groupe Oenologique Lamothe Abiet Pinosa",
    "wof:placetype":"venue"
},
  "geometry": {"coordinates":[-0.539273,44.827904],"type":"Point"}
}