{
  "type": "Feature",
  "properties": {
    "addr:full":"26 A Rue De Gen\u00eatre 90600 Grandvillars Franche Comt\u00e9 90600",
    "addr:housenumber":"26 a",
    "addr:postcode":"90600;90600",
    "addr:street":"Rue De Gene\u0302Tre;Franche Comte\u0301",
    "iso:country":"FR",
    "sg:address":"26 A Rue De Gen\u00eatre 90600 Grandvillars",
    "sg:classifiers":[
        {
            "category":"Professional",
            "subcategory":"Engineering",
            "type":"Services"
        }
    ],
    "sg:phone":"+33 3 84 27 81 12",
    "sg:postcode":"90600",
    "sg:province":"Franche Comt\u00e9",
    "sg:tags":[
        "machine",
        "-",
        "mechanical"
    ],
    "wof:name":"Ets Kremer Sarl",
    "wof:placetype":"venue"
},
  "geometry": {"coordinates":[6.971102,47.542511],"type":"Point"}
}