{
  "type": "Feature",
  "properties": {
    "addr:full":"Zone Industrielle - Carreau de la Mine Sainte Marie aux Ch\u00eanes Languedoc-Roussillon 57255",
    "addr:postcode":"57255",
    "addr:street":"Zone Industrielle Carreau De La Mine;Aux Che\u0302Nes",
    "iso:country":"FR",
    "sg:address":"Zone Industrielle - Carreau de la Mine",
    "sg:city":"Sainte Marie aux Ch\u00eanes",
    "sg:orig_category":"Non-Classified Establishments",
    "sg:phone":"+33 3 87 61 92 21",
    "sg:postcode":"57255",
    "sg:province":"Languedoc-Roussillon",
    "wof:name":"S.i.m\u00e9ca S.a.r.l.",
    "wof:placetype":"venue"
},
  "geometry": {"coordinates":[6.00664,49.190941],"type":"Point"}
}