{
  "type": "Feature",
  "properties": {
    "iso:country":"FR",
    "sg:address":"33, Rue de laChauss\u00e9e du Port - Espace d'Activit\u00e9 la Ch du Port, 51000 Ch\u00e2lons en Champagne",
    "sg:orig_category":"Unclassifiable Establishments",
    "sg:phone":"+33 3 26 21 64 65",
    "sg:province":"Champagne",
    "wof:name":"Institut De Soudure",
    "wof:placetype":"venue"
},
  "geometry": {"coordinates":[4.356582,48.958801],"type":"Point"}
}