{
  "type": "Feature",
  "properties": {
    "addr:full":"2 rue March\u00e9; Machecoul Pays de Loire",
    "addr:housenumber":"2",
    "addr:street":"Rue Marche\u0301 Machecoul",
    "iso:country":"FR",
    "sg:address":"2 rue March\u00e9; Machecoul",
    "sg:classifiers":[
        {
            "category":"Banks & Credit Unions",
            "subcategory":"Bank",
            "type":"Services"
        }
    ],
    "sg:phone":"+33 3340314425",
    "sg:province":"Pays de Loire",
    "wof:name":"Banque Cio",
    "wof:placetype":"venue"
},
  "geometry": {"coordinates":[-1.821824,46.992874],"type":"Point"}
}