{
  "type": "Feature",
  "properties": {
    "addr:full":"Rte de Vitr\u00e9 - Beauvais La Guerche de Bretagne Bretagne 35130",
    "addr:postcode":"35130",
    "addr:street":"Rte De Vitre\u0301;La;De Bretagne",
    "iso:country":"FR",
    "sg:address":"Rte de Vitr\u00e9 - Beauvais",
    "sg:city":"La Guerche de Bretagne",
    "sg:orig_category":"Unclassifiable Establishments",
    "sg:phone":"+33 2 99 96 42 29",
    "sg:postcode":"35130",
    "sg:province":"Bretagne",
    "wof:name":"B.m.f. S.a.r.l. - Bertron Menuiserie Fermetures",
    "wof:placetype":"venue"
},
  "geometry": {"coordinates":[-1.265248,47.901817],"type":"Point"}
}