{
  "type": "Feature",
  "properties": {
    "addr:full":"18 Boulevard General Leclerc Cogl\u00e8s Bretagne 35460",
    "addr:housenumber":"18",
    "addr:postcode":"35460",
    "addr:street":"Boulevard General Leclerc",
    "iso:country":"FR",
    "sg:address":"18 Boulevard General Leclerc",
    "sg:city":"Cogl\u00e8s",
    "sg:classifiers":[
        {
            "category":"Banks & Credit Unions",
            "subcategory":"Financial Services",
            "type":"Services"
        }
    ],
    "sg:phone":"+33 2 99 98 62 76",
    "sg:postcode":"35460",
    "sg:province":"Bretagne",
    "sg:tags":[
        "banking",
        "finance",
        "insurance"
    ],
    "wof:name":"Caisse Regionale Credit Agricole Mutuel Ille Et Vilaine (crcam)",
    "wof:placetype":"venue"
},
  "geometry": {"coordinates":[-1.481703,48.458721],"type":"Point"}
}