{
  "type": "Feature",
  "properties": {
    "addr:full":"38 Bd Raymond Poincar\u00e9 55000 Bar Le Duc Lorraine",
    "addr:housenumber":"38",
    "addr:postcode":"55000",
    "addr:street":"Bd Raymond Poincare\u0301;Le Duc",
    "iso:country":"FR",
    "sg:address":"38 Bd Raymond Poincar\u00e9 55000 Bar Le Duc",
    "sg:classifiers":[
        {
            "category":"Manufacturing",
            "subcategory":"Printing",
            "type":"Manufacturing & Wholesale Goods"
        }
    ],
    "sg:phone":"+33 3 29 45 08 78",
    "sg:province":"Lorraine",
    "sg:tags":[
        "publishing"
    ],
    "wof:name":"Saint Paul Imprimeur Editeur Sa",
    "wof:placetype":"venue"
},
  "geometry": {"coordinates":[5.155729,48.776569],"type":"Point"}
}