{
  "type": "Feature",
  "properties": {
    "addr:full":"2, Rue Alphonse Baudin, 01100 Oyonnax Rhone-Alpes",
    "addr:housenumber":"2",
    "addr:postcode":"01100",
    "addr:street":"Rue Alphonse Baudin",
    "iso:country":"FR",
    "sg:address":"2, Rue Alphonse Baudin, 01100 Oyonnax",
    "sg:orig_category":"Unclassifiable Establishments",
    "sg:phone":"+33 4 74 12 02 85",
    "sg:province":"Rhone-Alpes",
    "wof:name":"Bavoux Industries S.a.s.",
    "wof:placetype":"venue"
},
  "geometry": {"coordinates":[5.65885,46.264664],"type":"Point"}
}