{
  "type": "Feature",
  "properties": {
    "addr:full":"8/10, Rue du Gast, 78100 Saint Germain en Laye Ile de France",
    "addr:housenumber":"8 / 10",
    "addr:postcode":"78100",
    "addr:street":"Rue Du Gast",
    "iso:country":"FR",
    "sg:address":"8/10, Rue du Gast, 78100 Saint Germain en Laye",
    "sg:orig_category":"Non-Classified Establishments",
    "sg:phone":"+33 1 34 51 27 19",
    "sg:province":"Ile de France",
    "wof:name":"S\u00e9piolsa France S.a.r.l.",
    "wof:placetype":"venue"
},
  "geometry": {"coordinates":[2.091349,48.895309],"type":"Point"}
}