{
  "type": "Feature",
  "properties": {
    "addr:full":"49 Rue Geo Chavez 69150 Decines Charpieu Rhone-Alpes 69150",
    "addr:housenumber":"49",
    "addr:postcode":"69150;69150",
    "addr:street":"Rue Geo Chavez;Rhone-Alpes",
    "iso:country":"FR",
    "sg:address":"49 Rue Geo Chavez 69150 Decines Charpieu",
    "sg:classifiers":[
        {
            "category":"Shopping",
            "subcategory":"Clothing, Apparel, & Fashions",
            "type":"Retail Goods"
        }
    ],
    "sg:phone":"+33 4 78 49 76 17",
    "sg:postcode":"69150",
    "sg:province":"Rhone-Alpes",
    "sg:tags":[
        "textile",
        "clothing",
        "clothes"
    ],
    "wof:name":"Avedison",
    "wof:placetype":"venue"
},
  "geometry": {"coordinates":[4.953058,45.774323],"type":"Point"}
}