{
  "type": "Feature",
  "properties": {
    "addr:full":"74 Avenue Du Maine 75014 Paris Ile de France",
    "addr:housenumber":"74",
    "addr:postcode":"75014",
    "addr:street":"Avenue Du Maine",
    "iso:country":"FR",
    "sg:address":"74 Avenue Du Maine 75014 Paris",
    "sg:classifiers":[
        {
            "category":"Professional",
            "subcategory":"Printing & Photocopies",
            "type":"Services"
        }
    ],
    "sg:phone":"+33 1 44 10 12 90",
    "sg:province":"Ile de France",
    "sg:tags":[
        "publishing"
    ],
    "wof:name":"Editions Tallandier",
    "wof:placetype":"venue"
},
  "geometry": {"coordinates":[2.321852,48.839054],"type":"Point"}
}