{
  "type": "Feature",
  "properties": {
    "addr:full":"6, Rue de l'Hermitage, 45520 Chevilly Chevilly Centre 45520",
    "addr:housenumber":"6",
    "addr:postcode":"45520;45520",
    "addr:street":"Rue De L'Hermitage",
    "iso:country":"FR",
    "sg:address":"6, Rue de l'Hermitage, 45520 Chevilly",
    "sg:city":"Chevilly",
    "sg:orig_category":"Unclassifiable Establishments",
    "sg:phone":"+33 2 38 80 10 57",
    "sg:postcode":"45520",
    "sg:province":"Centre",
    "wof:name":"S.n.u.p. S.a.",
    "wof:placetype":"venue"
},
  "geometry": {"coordinates":[3.005625,49.644062],"type":"Point"}
}