{
  "type": "Feature",
  "properties": {
    "addr:full":"Rue de l'Ing\u00e9nieur Bertin Longvic Bourgogne 21600",
    "addr:postcode":"21600",
    "addr:street":"Rue De L'Inge \u0301Nieur Bertin",
    "iso:country":"FR",
    "sg:address":"Rue de l'Ing\u00e9nieur Bertin",
    "sg:city":"Longvic",
    "sg:orig_category":"Unclassifiable Establishments",
    "sg:phone":"+33 3 80 31 64 28",
    "sg:postcode":"21600",
    "sg:province":"Bourgogne",
    "wof:name":"Locapharm S.a.",
    "wof:placetype":"venue"
},
  "geometry": {"coordinates":[5.032022,47.295349],"type":"Point"}
}