{
  "type": "Feature",
  "properties": {
    "iso:country":"FR",
    "sg:address":"B.P. 192, 36254 Ch\u00e2teauroux C\u00e9dex^^Rte de Limoges, 36250 Saint Maur",
    "sg:city":"Niherne",
    "sg:orig_category":"Non-Classified Establishments",
    "sg:phone":"+33 2 54 60 22 20",
    "sg:postcode":"36250",
    "sg:province":"Centre",
    "wof:name":"Etablissement Th\u00e9ret S.a.",
    "wof:placetype":"venue"
},
  "geometry": {"coordinates":[1.637739,46.80542],"type":"Point"}
}