{
  "type": "Feature",
  "properties": {
    "addr:full":"B.P. 8, 31601 Muret C\u00e9dex^^27 bis, Av. des Pyr\u00e9n\u00e9es, 31600 Muret Midi Pyr\u00e9n\u00e9es",
    "addr:housenumber":"8",
    "addr:postcode":"31601;31600",
    "addr:street":"B.P.;Av. Des Pyre\u0301Ne\u0301Es",
    "iso:country":"FR",
    "sg:address":"B.P. 8, 31601 Muret C\u00e9dex^^27 bis, Av. des Pyr\u00e9n\u00e9es, 31600 Muret",
    "sg:orig_category":"Non-Classified Establishments",
    "sg:phone":"+33 5 61 51 15 88",
    "sg:province":"Midi Pyr\u00e9n\u00e9es",
    "wof:name":"Imprimerie Cazaux S.a.r.l.",
    "wof:placetype":"venue"
},
  "geometry": {"coordinates":[1.313195,43.413681],"type":"Point"}
}