{
  "type": "Feature",
  "properties": {
    "addr:full":"A\u00e9roport De Paris Le Bourget Zone Aviation D Affaires 93350 Le Bourget Ile de France 93350",
    "addr:postcode":"93350;93350",
    "iso:country":"FR",
    "sg:address":"A\u00e9roport De Paris Le Bourget Zone Aviation D Affaires 93350 Le Bourget",
    "sg:classifiers":[
        {
            "category":"Manufacturing",
            "subcategory":"Aerospace",
            "type":"Manufacturing & Wholesale Goods"
        }
    ],
    "sg:phone":"+33 1 48 35 92 90",
    "sg:postcode":"93350",
    "sg:province":"Ile de France",
    "sg:tags":[
        "equipment",
        "aeronautic",
        "transport",
        "vehicle"
    ],
    "wof:name":"Aircraft Interior Products",
    "wof:placetype":"venue"
},
  "geometry": {"coordinates":[2.423501,48.93335],"type":"Point"}
}