{
  "type": "Feature",
  "properties": {
    "iso:country":"FR",
    "sg:address":"12600 Brommat",
    "sg:classifiers":[
        {
            "category":"Shopping",
            "subcategory":"Computers & Home Electronics",
            "type":"Retail Goods"
        }
    ],
    "sg:phone":"+33 5 65 66 61 50",
    "sg:postcode":"12600",
    "sg:province":"Midi Pyr\u00e9n\u00e9es",
    "sg:tags":[
        "electronic",
        "electrical",
        "equipment"
    ],
    "wof:name":"Rte Resaux Transport Electricite",
    "wof:placetype":"venue"
},
  "geometry": {"coordinates":[2.684997,44.828465],"type":"Point"}
}