{
  "type": "Feature",
  "properties": {
    "iso:country":"FR",
    "sg:address":"250, Rue Saint Denis, 75002 Paris",
    "sg:orig_category":"Unclassifiable Establishments",
    "sg:phone":"+33 1 42 33 01 07",
    "sg:province":"Ile de France",
    "wof:name":"Actuel Oremont S.a.r.l.",
    "wof:placetype":"venue"
},
  "geometry": {"coordinates":[2.352618,48.86935],"type":"Point"}
}