{
  "type": "Feature",
  "properties": {
    "iso:country":"FR",
    "sg:address":"28 Quai Surcouf 35600 Redon",
    "sg:city":"Redon",
    "sg:orig_category":"Miscellaneous Products",
    "sg:phone":"+33 2 99 71 01 76",
    "sg:postcode":"35600",
    "sg:province":"Bretagne",
    "wof:name":"Sep Redon Ploerel",
    "wof:placetype":"venue"
},
  "geometry": {"coordinates":[-2.090245,47.645164],"type":"Point"}
}