{
  "type": "Feature",
  "properties": {
    "addr:full":"10 Av Des Fr\u00e8res Lumi\u00e8re 64140 Lons Lons Aquitaine 64140",
    "addr:postcode":"64140;64140",
    "addr:street":"10 Av Des Fre\u0300Res Lumie\u0300Re",
    "iso:country":"FR",
    "sg:address":"10 Av Des Fr\u00e8res Lumi\u00e8re 64140 Lons",
    "sg:city":"Lons",
    "sg:classifiers":[
        {
            "category":"Farming",
            "subcategory":"Farm & Veterinary Services",
            "type":"Manufacturing & Wholesale Goods"
        }
    ],
    "sg:phone":"+33 5 59 40 10 00",
    "sg:postcode":"64140",
    "sg:province":"Aquitaine",
    "sg:tags":[
        "food",
        "product",
        "breeding",
        "animal",
        "related"
    ],
    "wof:name":"Sanders Adour (societe De Participations)",
    "wof:placetype":"venue"
},
  "geometry": {"coordinates":[-0.418088,43.311306],"type":"Point"}
}