{
  "type": "Feature",
  "properties": {
    "addr:full":"19 Pl Jean Bart 59140 Dunkerque Nord Pas-de-Calais 59140",
    "addr:housenumber":"19",
    "addr:postcode":"59140;59140",
    "addr:street":"Pl Jean Bart",
    "iso:country":"FR",
    "sg:address":"19 Pl Jean Bart 59140 Dunkerque",
    "sg:classifiers":[
        {
            "category":"Bakery",
            "type":"Food & Drink"
        }
    ],
    "sg:phone":"+33 3 28 66 71 81",
    "sg:postcode":"59140",
    "sg:province":"Nord Pas-de-Calais",
    "sg:tags":[
        "cake",
        "product",
        "related",
        "bread"
    ],
    "wof:name":"Patisserie Jean Bart",
    "wof:placetype":"venue"
},
  "geometry": {"coordinates":[2.376697,51.034981],"type":"Point"}
}