{
  "type": "Feature",
  "properties": {
    "iso:country":"FR",
    "sg:address":"ZI du Carr\u00e9",
    "sg:city":"Grasse",
    "sg:orig_category":"Unclassifiable Establishments",
    "sg:phone":"+33 4 93 70 22 33",
    "sg:postcode":"06130",
    "sg:province":"Provence-Alpes-C\u00f4te d'Azur",
    "wof:name":"O.c.m. S.a.r.l. - Omnium De Construction M\u00e9tallique",
    "wof:placetype":"venue"
},
  "geometry": {"coordinates":[6.922461,43.660435],"type":"Point"}
}