{
  "type": "Feature",
  "properties": {
    "iso:country":"FR",
    "sg:address":"42 bis, Rue des Jardins, 52130 Wassy",
    "sg:orig_category":"Unclassifiable Establishments",
    "sg:phone":"+33 3 25 55 89 94",
    "sg:province":"Champagne",
    "wof:name":"Modelage De La Blaise",
    "wof:placetype":"venue"
},
  "geometry": {"coordinates":[4.944588,48.501045],"type":"Point"}
}