{
  "type": "Feature",
  "properties": {
    "addr:full":"42 bis, Rue des Jardins, 52130 Wassy Champagne",
    "addr:housenumber":"42 bis",
    "addr:postcode":"52130",
    "addr:street":"Rue Des Jardins",
    "iso:country":"FR",
    "sg:address":"42 bis, Rue des Jardins, 52130 Wassy",
    "sg:orig_category":"Unclassifiable Establishments",
    "sg:phone":"+33 3 25 55 89 94",
    "sg:province":"Champagne",
    "wof:name":"Modelage De La Blaise",
    "wof:placetype":"venue"
},
  "geometry": {"coordinates":[4.944588,48.501045],"type":"Point"}
}