{
  "type": "Feature",
  "properties": {
    "iso:country":"FR",
    "sg:address":"Rue Paul Ramadier",
    "sg:city":"Pau",
    "sg:orig_category":"Non-Classified Establishments",
    "sg:phone":"+33 5 59 02 32 99",
    "sg:postcode":"64000",
    "sg:province":"Aquitaine",
    "wof:name":"Mory Team S.a.",
    "wof:placetype":"venue"
},
  "geometry": {"coordinates":[-0.31667,43.316704],"type":"Point"}
}