{
  "type": "Feature",
  "properties": {
    "addr:full":"10 bis, Bd de la Marne, 77120 Coulommiers Ile de France 77120",
    "addr:housenumber":"10 bis",
    "addr:postcode":"77120;ile;77120",
    "addr:street":"Bd De La Marne;France",
    "iso:country":"FR",
    "sg:address":"10 bis, Bd de la Marne, 77120 Coulommiers",
    "sg:orig_category":"Non-Classified Establishments",
    "sg:phone":"+33 1 64 20 73 91",
    "sg:postcode":"77120",
    "sg:province":"Ile de France",
    "wof:name":"Automatismes Services S.a.",
    "wof:placetype":"venue"
},
  "geometry": {"coordinates":[3.090988,48.80378],"type":"Point"}
}