{
  "type": "Feature",
  "properties": {
    "addr:full":"Les Viauds 16210 Bellon Poitou-Charentes 16210",
    "addr:postcode":"16210;16210",
    "addr:street":"Bellon",
    "iso:country":"FR",
    "sg:address":"Les Viauds 16210 Bellon",
    "sg:orig_category":"Non-Classified Establishments",
    "sg:phone":"+33 5 45 98 17 05",
    "sg:postcode":"16210",
    "sg:province":"Poitou-Charentes",
    "wof:name":"Beno\u00eet E.a.r.l.",
    "wof:placetype":"venue"
},
  "geometry": {"coordinates":[0.113484,45.311012],"type":"Point"}
}