{
  "type": "Feature",
  "properties": {
    "addr:full":"Zac Du Champ De Perrier Pte Du Grand Lyon 01700 Neyron Rhone-Alpes 01700",
    "addr:postcode":"01700;01700",
    "addr:street":"Zac Du Champ De Perrier Pte Du Grand",
    "iso:country":"FR",
    "sg:address":"Zac Du Champ De Perrier Pte Du Grand Lyon 01700 Neyron",
    "sg:classifiers":[
        {
            "category":"Professional",
            "subcategory":"Printing & Photocopies",
            "type":"Services"
        }
    ],
    "sg:phone":"+33 4 72 01 58 68",
    "sg:postcode":"01700",
    "sg:province":"Rhone-Alpes",
    "sg:tags":[
        "publishing"
    ],
    "wof:name":"Les Editions Du Plaisancier",
    "wof:placetype":"venue"
},
  "geometry": {"coordinates":[4.93177,45.81464],"type":"Point"}
}