{
  "type": "Feature",
  "properties": {
    "iso:country":"FR",
    "sg:address":"Rte de Saint Gilles",
    "sg:city":"Aizenay",
    "sg:orig_category":"Unclassifiable Establishments",
    "sg:phone":"+33 2 51 48 36 36",
    "sg:postcode":"85190",
    "sg:province":"Pays de Loire",
    "wof:name":"Sedep S.a.",
    "wof:placetype":"venue"
},
  "geometry": {"coordinates":[-1.610729,46.676075],"type":"Point"}
}