{
  "type": "Feature",
  "properties": {
    "addr:full":"396 av G\u00e9n Leclerc; S. Laurent Champagne",
    "addr:street":"396 Av Ge\u0301N Leclerc S. Laurent",
    "iso:country":"FR",
    "sg:address":"396 av G\u00e9n Leclerc; S. Laurent",
    "sg:classifiers":[
        {
            "category":"Banks & Credit Unions",
            "subcategory":"Bank",
            "type":"Services"
        }
    ],
    "sg:phone":"+33 3393315530",
    "sg:province":"Champagne",
    "wof:name":"Soci\u00e9t\u00e9 G\u00e9n\u00e9rale, Agence Village",
    "wof:placetype":"venue"
},
  "geometry": {"coordinates":[-76.851433,39.070282],"type":"Point"}
}