{
  "type": "Feature",
  "properties": {
    "addr:full":"21, Rue du Port, 92000 Nanterre Ile de France",
    "addr:housenumber":"21",
    "addr:postcode":"92000",
    "addr:street":"Rue Du Port",
    "iso:country":"FR",
    "sg:address":"21, Rue du Port, 92000 Nanterre",
    "sg:orig_category":"Unclassifiable Establishments",
    "sg:phone":"+33 1 41 91 19 70",
    "sg:province":"Ile de France",
    "wof:name":"G.p.a. S.a.r.l.",
    "wof:placetype":"venue"
},
  "geometry": {"coordinates":[2.178582,48.893303],"type":"Point"}
}