{
  "type": "Feature",
  "properties": {
    "iso:country":"FR",
    "sg:address":"9 All De L'Industrie BP 406 64700 Hendaye",
    "sg:city":"Hendaye",
    "sg:classifiers":[
        {
            "category":"Shopping",
            "subcategory":"Computers & Home Electronics",
            "type":"Retail Goods"
        }
    ],
    "sg:phone":"+33 5 59 51 62 62",
    "sg:postcode":"64700",
    "sg:province":"Aquitaine",
    "sg:tags":[
        "equipment",
        "household",
        "electrical",
        "appliance",
        "electronic"
    ],
    "wof:name":"Bonnet Neve",
    "wof:placetype":"venue"
},
  "geometry": {"coordinates":[-1.770666,43.343575],"type":"Point"}
}