{
  "type": "Feature",
  "properties": {
    "addr:full":"B.P. 9, 45141 Saint Jean de la Ruelle C\u00e9dex^^5, Rue Henri Dunant - ZI de Ingr\u00e9, 45140 Ingr\u00e9 Ingr\u00e9 Centre 45140",
    "addr:housenumber":"9",
    "addr:postcode":"45141;45140;45140",
    "addr:street":"B.P.;La Ruelle Ce\u0301Dex^^5 Rue Henri Dunant Zi De Ingre\u0301",
    "iso:country":"FR",
    "sg:address":"B.P. 9, 45141 Saint Jean de la Ruelle C\u00e9dex^^5, Rue Henri Dunant - ZI de Ingr\u00e9, 45140 Ingr\u00e9",
    "sg:city":"Ingr\u00e9",
    "sg:orig_category":"Non-Classified Establishments",
    "sg:phone":"+33 2 38 79 55 34",
    "sg:postcode":"45140",
    "sg:province":"Centre",
    "wof:name":"B.r.c. S.a. - Business Repro Centre",
    "wof:placetype":"venue"
},
  "geometry": {"coordinates":[1.8745,47.912949],"type":"Point"}
}