{
  "type": "Feature",
  "properties": {
    "iso:country":"FR",
    "sg:address":"1 Rue De La Fromagerie 77930 Chailly En Biere",
    "sg:classifiers":[
        {
            "category":"Shopping",
            "type":"Retail Goods"
        }
    ],
    "sg:phone":"+33 1 60 66 29 18",
    "sg:postcode":"77930",
    "sg:province":"Ile de France",
    "sg:tags":[
        "metallurgy",
        "finished",
        "-",
        "metalworking",
        "metallic"
    ],
    "wof:name":"Techneed",
    "wof:placetype":"venue"
},
  "geometry": {"coordinates":[2.596596,48.465523],"type":"Point"}
}