{
  "type": "Feature",
  "properties": {
    "addr:full":"Rue du Trieu du Quesnoy - Z.A. Roubaix-Est Toufflers Nord Pas-de-Calais 59390",
    "addr:postcode":"59390",
    "addr:street":"Rue Du Trieu Du Quesnoy Z.A. Roubaix-Est Toufflers Nord",
    "iso:country":"FR",
    "sg:address":"Rue du Trieu du Quesnoy - Z.A. Roubaix-Est",
    "sg:city":"Toufflers",
    "sg:orig_category":"Non-Classified Establishments",
    "sg:phone":"+33 3 20 75 74 44",
    "sg:postcode":"59390",
    "sg:province":"Nord Pas-de-Calais",
    "wof:name":"Batimpro - Charrier S.a.",
    "wof:placetype":"venue"
},
  "geometry": {"coordinates":[3.234615,50.669254],"type":"Point"}
}