{
  "type": "Feature",
  "properties": {
    "addr:full":"6 Rue Daru 75008 Paris Ile de France",
    "addr:housenumber":"6",
    "addr:postcode":"75008",
    "addr:street":"Rue Daru",
    "iso:country":"FR",
    "sg:address":"6 Rue Daru 75008 Paris",
    "sg:classifiers":[
        {
            "category":"Banks & Credit Unions",
            "subcategory":"Investment Brokerage",
            "type":"Services"
        }
    ],
    "sg:phone":"+33 1 44 15 33 50",
    "sg:province":"Ile de France",
    "sg:tags":[
        "-",
        "transport",
        "related"
    ],
    "wof:name":"Femme",
    "wof:placetype":"venue"
},
  "geometry": {"coordinates":[2.301017,48.877342],"type":"Point"}
}