{
  "type": "Feature",
  "properties": {
    "addr:full":"4 Mont\u00e9e St Barth\u00e9l\u00e9my 69005 Lyon Rhone-Alpes",
    "addr:housenumber":"4",
    "addr:postcode":"69005",
    "addr:street":"Monte\u0301E St Barthe\u0301Le\u0301My",
    "iso:country":"FR",
    "sg:address":"4 Mont\u00e9e St Barth\u00e9l\u00e9my 69005 Lyon",
    "sg:classifiers":[
        {
            "category":"Professional",
            "subcategory":"Business Services",
            "type":"Services"
        }
    ],
    "sg:phone":"+33 4 78 28 38 34",
    "sg:province":"Rhone-Alpes",
    "sg:tags":[
        "training",
        "advice"
    ],
    "wof:name":"Association Familiale Externat Ste Marie",
    "wof:placetype":"venue"
},
  "geometry": {"coordinates":[4.826571,45.76564],"type":"Point"}
}