{
  "type": "Feature",
  "properties": {
    "addr:full":"28 Rue G\u00e9rot 89000 Auxerre Auxerre Bourgogne 89000",
    "addr:housenumber":"28",
    "addr:postcode":"89000;89000",
    "addr:street":"Rue Ge\u0301Rot",
    "iso:country":"FR",
    "sg:address":"28 Rue G\u00e9rot 89000 Auxerre",
    "sg:city":"Auxerre",
    "sg:classifiers":[
        {
            "category":"Manufacturing",
            "subcategory":"Metals",
            "type":"Manufacturing & Wholesale Goods"
        }
    ],
    "sg:phone":"+33 3 86 72 06 05",
    "sg:postcode":"89000",
    "sg:province":"Bourgogne",
    "sg:tags":[
        "metallurgy",
        "steel",
        "metalworking"
    ],
    "wof:name":"Fonderie D'auxerre Sa",
    "wof:placetype":"venue"
},
  "geometry": {"coordinates":[3.578496,47.792603],"type":"Point"}
}