{
  "type": "Feature",
  "properties": {
    "iso:country":"FR",
    "sg:address":"21 rue Joannes Carret 69009 Lyon",
    "sg:classifiers":[
        {
            "category":"Professional",
            "subcategory":"Advertising",
            "type":"Services"
        }
    ],
    "sg:phone":"+33 4 78 47 72 72",
    "sg:postcode":"69009",
    "sg:province":"Rhone-Alpes",
    "sg:tags":[
        "glass",
        "made",
        "gift",
        "crystal"
    ],
    "wof:name":"Concept & Impression Conseil S.a.",
    "wof:placetype":"venue"
},
  "geometry": {"coordinates":[4.815564,45.790813],"type":"Point"}
}