{
  "type": "Feature",
  "properties": {
    "addr:full":"7, Av. du 24 Ao\u00fbt 1944, 69630 V\u00e9nissieux Rhone-Alpes",
    "addr:postcode":"69630",
    "addr:street":"Av. Du 24 Aou\u0302T 1944",
    "iso:country":"FR",
    "sg:address":"7, Av. du 24 Ao\u00fbt 1944, 69630 V\u00e9nissieux",
    "sg:orig_category":"Unclassifiable Establishments",
    "sg:phone":"+33 4 72 50 86 58",
    "sg:province":"Rhone-Alpes",
    "wof:name":"Fraikin Location S.a.",
    "wof:placetype":"venue"
},
  "geometry": {"coordinates":[4.74319,45.710232],"type":"Point"}
}