{
  "type": "Feature",
  "properties": {
    "addr:full":"Avenue Provence Departementale 432 26320 St Marcel Les Valence Rhone-Alpes",
    "addr:housenumber":"432",
    "addr:postcode":"26320",
    "addr:street":"Avenue;Departementale;Marcel Les",
    "iso:country":"FR",
    "sg:address":"Avenue Provence Departementale 432 26320 St Marcel Les Valence",
    "sg:classifiers":[
        {
            "category":"Manufacturing",
            "subcategory":"Motor Vehicles & Parts",
            "type":"Manufacturing & Wholesale Goods"
        }
    ],
    "sg:phone":"+33 4 75 58 84 28",
    "sg:province":"Rhone-Alpes",
    "sg:tags":[
        "engine",
        "machine",
        "engineering",
        "-",
        "mechanical"
    ],
    "wof:name":"Lem",
    "wof:placetype":"venue"
},
  "geometry": {"coordinates":[4.953553,44.969872],"type":"Point"}
}