{
  "type": "Feature",
  "properties": {
    "iso:country":"FR",
    "sg:address":"14/16, Place Mendes France, 49100 Angers",
    "sg:orig_category":"Unclassifiable Establishments",
    "sg:phone":"+33 2 41 23 52 52",
    "sg:province":"Pays de Loire",
    "wof:name":"C.i.p.a. Immobilier G.i.e.",
    "wof:placetype":"venue"
},
  "geometry": {"coordinates":[-0.546221,47.472664],"type":"Point"}
}