{
  "type": "Feature",
  "properties": {
    "addr:full":"92, Rue Baudin, 92307 Levallois Perret C\u00e9dex \u00cele-de-France",
    "addr:housenumber":"92",
    "addr:postcode":"92307",
    "addr:street":"Rue Baudin;Ce\u0301Dex",
    "iso:country":"FR",
    "sg:address":"92, Rue Baudin, 92307 Levallois Perret C\u00e9dex",
    "sg:orig_category":"Non-Classified Establishments",
    "sg:phone":"+33 1 41 06 35 00",
    "sg:province":"\u00cele-de-France",
    "wof:name":"Schering Plough S.a.",
    "wof:placetype":"venue"
},
  "geometry": {"coordinates":[2.288552,48.899048],"type":"Point"}
}