{
  "type": "Feature",
  "properties": {
    "iso:country":"FR",
    "sg:address":"Rue Charles le Tellier - ZI",
    "sg:city":"Pontivy",
    "sg:orig_category":"Unclassifiable Establishments",
    "sg:phone":"+33 2 97 25 01 10",
    "sg:postcode":"56300",
    "sg:province":"Bretagne",
    "wof:name":"Kdi Rou\u00ebnel S.a.s.",
    "wof:placetype":"venue"
},
  "geometry": {"coordinates":[-2.964889,48.053471],"type":"Point"}
}