{
  "type": "Feature",
  "properties": {
    "addr:full":"10, Rue Perr\u00e9e, 75003 Paris Ile de France",
    "addr:housenumber":"10",
    "addr:postcode":"75003",
    "addr:street":"Rue Perre\u0301E",
    "iso:country":"FR",
    "sg:address":"10, Rue Perr\u00e9e, 75003 Paris",
    "sg:orig_category":"Unclassifiable Establishments",
    "sg:phone":"+33 1 42 77 76 41",
    "sg:province":"Ile de France",
    "wof:name":"I.n.c.o.s. S.a.r.l. - International Consult System",
    "wof:placetype":"venue"
},
  "geometry": {"coordinates":[2.361758,48.864521],"type":"Point"}
}