{
  "type": "Feature",
  "properties": {
    "addr:full":"64 Rue Du Dolmen 44600 St Nazaire Pays de Loire 44600",
    "addr:housenumber":"64",
    "addr:postcode":"44600 st nazaire;44600",
    "addr:street":"Rue Du Dolmen",
    "iso:country":"FR",
    "sg:address":"64 Rue Du Dolmen 44600 St Nazaire",
    "sg:classifiers":[
        {
            "category":"Government",
            "subcategory":"Department Of Motor Vehicles",
            "type":"Public Place"
        }
    ],
    "sg:phone":"+33 2 40 22 06 55",
    "sg:postcode":"44600",
    "sg:province":"Pays de Loire",
    "sg:tags":[
        "equipment",
        "industrial",
        "transport",
        "motor-cars"
    ],
    "wof:name":"Eurl Bruno Lievre",
    "wof:placetype":"venue"
},
  "geometry": {"coordinates":[-2.205484,47.281464],"type":"Point"}
}