{
  "type": "Feature",
  "properties": {
    "addr:full":"Fermes De La Picardie 89190 Courgenay Courgenay Bourgogne 89190",
    "addr:postcode":"89190;89190",
    "iso:country":"FR",
    "sg:address":"Fermes De La Picardie 89190 Courgenay",
    "sg:city":"Courgenay",
    "sg:classifiers":[
        {
            "category":"Farming",
            "subcategory":"Livestock Farm",
            "type":"Manufacturing & Wholesale Goods"
        }
    ],
    "sg:phone":"+33 3 86 86 70 79",
    "sg:postcode":"89190",
    "sg:province":"Bourgogne",
    "sg:tags":[
        "grain",
        "agriculture",
        "cereal"
    ],
    "wof:name":"Fermes De La Picardie Sa",
    "wof:placetype":"venue"
},
  "geometry": {"coordinates":[3.55753,48.233505],"type":"Point"}
}