{
  "type": "Feature",
  "properties": {
    "addr:full":"B.P. 23, 78141 V\u00e9lizy Villacoublay C\u00e9dex^^2, Rue Lat\u00e9co\u00e8re, 78140 V\u00e9lizy Villacoublay Ile de France",
    "addr:postcode":"78141;78140",
    "addr:street":"B.P. 23;Rue Late\u0301Coe\u0300Re",
    "iso:country":"FR",
    "sg:address":"B.P. 23, 78141 V\u00e9lizy Villacoublay C\u00e9dex^^2, Rue Lat\u00e9co\u00e8re, 78140 V\u00e9lizy Villacoublay",
    "sg:orig_category":"Non-Classified Establishments",
    "sg:phone":"+33 1 30 70 35 00",
    "sg:province":"Ile de France",
    "wof:name":"Thal\u00e8s Electron Devices S.a.",
    "wof:placetype":"venue"
},
  "geometry": {"coordinates":[2.18246,48.78503],"type":"Point"}
}