{
  "type": "Feature",
  "properties": {
    "addr:full":"Zone de Soriech n\u00b0 5 Lattes Languedoc-Roussillon 34970",
    "addr:postcode":"34970",
    "iso:country":"FR",
    "sg:address":"Zone de Soriech n\u00b0 5",
    "sg:city":"Lattes",
    "sg:orig_category":"Unclassifiable Establishments",
    "sg:phone":"+33 4 67 64 36 65",
    "sg:postcode":"34970",
    "sg:province":"Languedoc-Roussillon",
    "wof:name":"Eurolot S.a.r.l.",
    "wof:placetype":"venue"
},
  "geometry": {"coordinates":[3.90524,43.570381],"type":"Point"}
}