{
  "type": "Feature",
  "properties": {
    "addr:full":"Fromentel 61210 La Fresnaye Au Sauvage Lande-de-Loug\u00e9 Basse Normandie 61210",
    "addr:postcode":"61210;61210",
    "addr:street":"Fromentel;Fresnaye Au Sauvage Lande-De-Louge\u0301 Basse",
    "iso:country":"FR",
    "sg:address":"Fromentel 61210 La Fresnaye Au Sauvage",
    "sg:city":"Lande-de-Loug\u00e9",
    "sg:classifiers":[
        {
            "category":"Professional",
            "type":"Services"
        }
    ],
    "sg:phone":"+33 2 33 35 00 01",
    "sg:postcode":"61210",
    "sg:province":"Basse Normandie",
    "sg:tags":[
        "transport",
        "road"
    ],
    "wof:name":"Quince Transports Sa",
    "wof:placetype":"venue"
},
  "geometry": {"coordinates":[-0.26751,48.719082],"type":"Point"}
}