{
  "type": "Feature",
  "properties": {
    "addr:full":"ZA de Bassilour Bidart Aquitaine 64210",
    "addr:postcode":"64210",
    "addr:street":"Za De Bassilour",
    "iso:country":"FR",
    "sg:address":"ZA de Bassilour",
    "sg:city":"Bidart",
    "sg:orig_category":"Unclassifiable Establishments",
    "sg:phone":"+33 5 59 47 77 01",
    "sg:postcode":"64210",
    "sg:province":"Aquitaine",
    "wof:name":"Digital Graffic S.a.r.l.",
    "wof:placetype":"venue"
},
  "geometry": {"coordinates":[-1.591007,43.439095],"type":"Point"}
}