{
  "type": "Feature",
  "properties": {
    "iso:country":"FR",
    "sg:address":"26, Mont\u00e9e Lucien Magnat, 38780 Pont Ev\u00eaque",
    "sg:orig_category":"Unclassifiable Establishments",
    "sg:phone":"+33 4 74 57 26 55",
    "sg:postcode":"38780",
    "sg:province":"Rhone-Alpes",
    "wof:name":"Etablissements Girard Andr\u00e9 S.a.r.l.",
    "wof:placetype":"venue"
},
  "geometry": {"coordinates":[4.905646,45.53056],"type":"Point"}
}