{
  "type": "Feature",
  "properties": {
    "addr:full":"B.P. 116, 08002 Charleville M\u00e9zi\u00e8res C\u00e9dex^^9, Rue Pierre Curie, 08002 Charleville M\u00e9zi\u00e8res Vill\u00e9 Alsace 67220",
    "addr:housenumber":"b.p. 116",
    "addr:postcode":"08002;08002;67220",
    "addr:street":"Rue Pierre Curie",
    "iso:country":"FR",
    "sg:address":"B.P. 116, 08002 Charleville M\u00e9zi\u00e8res C\u00e9dex^^9, Rue Pierre Curie, 08002 Charleville M\u00e9zi\u00e8res",
    "sg:city":"Vill\u00e9",
    "sg:orig_category":"Non-Classified Establishments",
    "sg:phone":"+33 3 24 37 84 28",
    "sg:postcode":"67220",
    "sg:province":"Alsace",
    "wof:name":"Ardennes Vulcanisation S.a.",
    "wof:placetype":"venue"
},
  "geometry": {"coordinates":[3.911801,48.001587],"type":"Point"}
}