{
  "type": "Feature",
  "properties": {
    "addr:full":"19 Rue Cognac Jay 75007 Paris Ile de France 75007",
    "addr:housenumber":"19",
    "addr:postcode":"75007;75007",
    "addr:street":"Rue Cognac",
    "iso:country":"FR",
    "sg:address":"19 Rue Cognac Jay 75007 Paris",
    "sg:classifiers":[
        {
            "category":"Professional",
            "subcategory":"Advertising",
            "type":"Services"
        }
    ],
    "sg:phone":"+33 1 40 62 32 32",
    "sg:postcode":"75007",
    "sg:province":"Ile de France",
    "sg:tags":[
        "information",
        "medium",
        "communication"
    ],
    "wof:name":"Transtele - Canal France International",
    "wof:placetype":"venue"
},
  "geometry": {"coordinates":[2.302953,48.861645],"type":"Point"}
}