{
  "type": "Feature",
  "properties": {
    "iso:country":"FR",
    "sg:address":"Rte d'Hirson",
    "sg:city":"Saint Michel",
    "sg:orig_category":"Unclassifiable Establishments",
    "sg:phone":"+33 3 23 58 29 33",
    "sg:postcode":"02830",
    "sg:province":"Picardie",
    "wof:name":"B.p.l. S.a.r.l. - B\u00e9ton Pr\u00e9fabrication Location",
    "wof:placetype":"venue"
},
  "geometry": {"coordinates":[4.116945,49.914856],"type":"Point"}
}