{
  "type": "Feature",
  "properties": {
    "iso:country":"FR",
    "sg:address":"Immeuble Aliz\u00e9 la Rigourdi\u00e8re",
    "sg:city":"Cesson S\u00e9vign\u00e9",
    "sg:orig_category":"Non-Classified Establishments",
    "sg:phone":"+33 2 99 67 63 12",
    "sg:postcode":"35210",
    "sg:province":"Bretagne",
    "wof:name":"Avis Fleet Services S.a.s.",
    "wof:placetype":"venue"
},
  "geometry": {"coordinates":[-87.38722199999999,44.726311],"type":"Point"}
}