{
  "type": "Feature",
  "properties": {
    "iso:country":"FR",
    "sg:address":"B.P. 8",
    "sg:city":"Lapalisse",
    "sg:orig_category":"Non-Classified Establishments",
    "sg:phone":"+33 4 70 99 10 52",
    "sg:postcode":"03120",
    "sg:province":"Auvergne",
    "wof:name":"Huileries De Lapalisse S.a.",
    "wof:placetype":"venue"
},
  "geometry": {"coordinates":[3.654424,46.215527],"type":"Point"}
}