{
  "type": "Feature",
  "properties": {
    "addr:full":"5, Rue de Rambouillet, 59400 Cambrai Nord Pas-de-Calais",
    "addr:housenumber":"5",
    "addr:postcode":"59400",
    "addr:street":"Rue De Rambouillet",
    "iso:country":"FR",
    "sg:address":"5, Rue de Rambouillet, 59400 Cambrai",
    "sg:orig_category":"Non-Classified Establishments",
    "sg:phone":"+33 3 27 82 98 98",
    "sg:province":"Nord Pas-de-Calais",
    "wof:name":"Quennesson F\u00e9\u00e9rie S.a.",
    "wof:placetype":"venue"
},
  "geometry": {"coordinates":[3.244183,50.188431],"type":"Point"}
}