{
  "type": "Feature",
  "properties": {
    "addr:full":"8 rue Ferdinand de Lesseps 26000 Valence Rhone-Alpes 26000",
    "addr:housenumber":"8",
    "addr:postcode":"26000;26000",
    "addr:street":"Rue Ferdinand De Lesseps",
    "iso:country":"FR",
    "sg:address":"8 rue Ferdinand de Lesseps 26000 Valence",
    "sg:classifiers":[
        {
            "category":"Shopping",
            "subcategory":"Stationery & Office Supplies",
            "type":"Retail Goods"
        }
    ],
    "sg:phone":"+33 4 75 78 17 45",
    "sg:postcode":"26000",
    "sg:province":"Rhone-Alpes",
    "wof:name":"Sa Roll Adriatic",
    "wof:placetype":"venue"
},
  "geometry": {"coordinates":[4.92336,44.923592],"type":"Point"}
}