{
  "type": "Feature",
  "properties": {
    "iso:country":"FR",
    "sg:address":"Z.I. Le Coquet 03260 ST GERMAIN DES FOSSES",
    "sg:city":"Marcenat",
    "sg:classifiers":[
        {
            "category":"Home & Garden",
            "subcategory":"Home Furnishings",
            "type":"Retail Goods"
        }
    ],
    "sg:phone":"+33 4 70 59 60 19",
    "sg:postcode":"03260",
    "sg:province":"Auvergne",
    "sg:tags":[
        "premise"
    ],
    "wof:name":"Simobi Sa",
    "wof:placetype":"venue"
},
  "geometry": {"coordinates":[3.449902,46.223774],"type":"Point"}
}