{
  "type": "Feature",
  "properties": {
    "addr:full":"39, Rue du Puits Mauger, 35000 Rennes Rennes Bretagne 35000",
    "addr:housenumber":"39",
    "addr:postcode":"35000;35000",
    "addr:street":"Rue Du Puits Mauger",
    "iso:country":"FR",
    "sg:address":"39, Rue du Puits Mauger, 35000 Rennes",
    "sg:city":"Rennes",
    "sg:orig_category":"Unclassifiable Establishments",
    "sg:phone":"+33 2 99 65 57 58",
    "sg:postcode":"35000",
    "sg:province":"Bretagne",
    "wof:name":"C.r.i.t. Int\u00e9rim S.a.",
    "wof:placetype":"venue"
},
  "geometry": {"coordinates":[-1.682627,48.105595],"type":"Point"}
}