{
  "type": "Feature",
  "properties": {
    "iso:country":"FR",
    "sg:address":"B.P. 84, 13752 Les Pennes Mirabeau^^19, Av. Lamartine - ZA de l'Agavon, 13170 Les Pennes Mirabeau",
    "sg:orig_category":"Non-Classified Establishments",
    "sg:phone":"+33 4 42 02 50 55",
    "sg:province":"Poitou-Charentes",
    "wof:name":"Caserta Salvi S.a.",
    "wof:placetype":"venue"
},
  "geometry": {"coordinates":[5.282638,43.417511],"type":"Point"}
}