{
  "type": "Feature",
  "properties": {
    "addr:full":"39, Av des Fusill\u00e9s, 80150 Cr\u00e9cy en Ponthieu Picardie",
    "addr:postcode":"80150",
    "addr:street":"39 Av Des Fusille\u0301S",
    "iso:country":"FR",
    "sg:address":"39, Av des Fusill\u00e9s, 80150 Cr\u00e9cy en Ponthieu",
    "sg:orig_category":"Unclassifiable Establishments",
    "sg:phone":"+33 3 22 23 77 77",
    "sg:province":"Picardie",
    "wof:name":"Fromentin S.a.",
    "wof:placetype":"venue"
},
  "geometry": {"coordinates":[1.89931,50.251156],"type":"Point"}
}