{
  "type": "Feature",
  "properties": {
    "addr:full":"Route de Montagny 74650 CHAVANOD Rhone-Alpes 74650",
    "addr:postcode":"74650;74650",
    "addr:street":"Route De Montagny",
    "iso:country":"FR",
    "sg:address":"Route de Montagny 74650 CHAVANOD",
    "sg:classifiers":[
        {
            "category":"Banks & Credit Unions",
            "subcategory":"Investment Brokerage",
            "type":"Services"
        }
    ],
    "sg:phone":"+33 4 50 69 39 39",
    "sg:postcode":"74650",
    "sg:province":"Rhone-Alpes",
    "sg:tags":[
        "development",
        "electronics"
    ],
    "wof:name":"Ve + Ka Si",
    "wof:placetype":"venue"
},
  "geometry": {"coordinates":[6.035073,45.875027],"type":"Point"}
}