{
  "type": "Feature",
  "properties": {
    "iso:country":"FR",
    "sg:address":"B.P. 222, 60202 Compi\u00e8gne C\u00e9dex^^33, Rue d'Amiens, 60200 Compi\u00e8gne",
    "sg:orig_category":"Non-Classified Establishments",
    "sg:phone":"+33 3 44 83 32 31",
    "sg:province":"Picardie",
    "wof:name":"Prodeco - Produits D'entretien Et De D\u00e9coration",
    "wof:placetype":"venue"
},
  "geometry": {"coordinates":[2.836988,49.426956],"type":"Point"}
}