{
  "type": "Feature",
  "properties": {
    "iso:country":"FR",
    "sg:address":"104 A Rue Des Bains 68390 Sausheim",
    "sg:city":"Sausheim",
    "sg:classifiers":[
        {
            "category":"Wholesale",
            "subcategory":"Machinery & Supplies",
            "type":"Manufacturing & Wholesale Goods"
        }
    ],
    "sg:phone":"+33 3 89 31 02 78",
    "sg:postcode":"68390",
    "sg:province":"Alsace",
    "sg:tags":[
        "handling",
        "material",
        "-",
        "machine",
        "equipment",
        "engineering",
        "mechanical"
    ],
    "wof:name":"Schindler Ascenseurs",
    "wof:placetype":"venue"
},
  "geometry": {"coordinates":[7.387061,47.786175],"type":"Point"}
}