{
  "type": "Feature",
  "properties": {
    "addr:full":"Rue Fernand Forest - ZA de Mozac Riom Auvergne 63202",
    "addr:postcode":"63202",
    "addr:street":"Rue Fernand Forest Za De Mozac",
    "iso:country":"FR",
    "sg:address":"Rue Fernand Forest - ZA de Mozac",
    "sg:city":"Riom",
    "sg:orig_category":"Unclassifiable Establishments",
    "sg:phone":"+33 4 73 98 02 22",
    "sg:postcode":"63202",
    "sg:province":"Auvergne",
    "wof:name":"Ikon Office Solutions",
    "wof:placetype":"venue"
},
  "geometry": {"coordinates":[3.115165,45.893814],"type":"Point"}
}