{
  "type": "Feature",
  "properties": {
    "iso:country":"FR",
    "sg:address":"4 All De La Girardi\u00e8re Z I Molina La Chazotte 42000 St Etienne",
    "sg:classifiers":[
        {
            "category":"Manufacturing",
            "subcategory":"Metals",
            "type":"Manufacturing & Wholesale Goods"
        }
    ],
    "sg:phone":"+33 4 77 79 51 00",
    "sg:postcode":"42000",
    "sg:province":"Rhone-Alpes",
    "sg:tags":[
        "metallurgy",
        "steel",
        "metalworking"
    ],
    "wof:name":"Mecacier",
    "wof:placetype":"venue"
},
  "geometry": {"coordinates":[4.387921,45.439053],"type":"Point"}
}