{
  "type": "Feature",
  "properties": {
    "iso:country":"FR",
    "sg:address":"3, Place du Sanitat, 44105 Nantes",
    "sg:orig_category":"Non-Classified Establishments",
    "sg:phone":"+33 2 40 44 27 00",
    "sg:province":"Midi Pyr\u00e9n\u00e9es",
    "wof:name":"E.t.p.o. - S.a. - Entreprise De Travaux Public De L'ouest",
    "wof:placetype":"venue"
},
  "geometry": {"coordinates":[-1.568262,47.20985],"type":"Point"}
}