{
  "type": "Feature",
  "properties": {
    "iso:country":"FR",
    "sg:address":"B.P. 611, 01706 Miribel C\u00e9dex^^ZAC de Rosarge - Les Echets , 01700 Miribel",
    "sg:orig_category":"Non-Classified Establishments",
    "sg:phone":"+33 4 72 26 20 00",
    "sg:postcode":"01700",
    "sg:province":"Rhone-Alpes",
    "wof:name":"S.i.p. S.a. - S\u00e9rigraphie Industrielle Et Publicitaire",
    "wof:placetype":"venue"
},
  "geometry": {"coordinates":[4.96153,45.828629],"type":"Point"}
}