{
  "type": "Feature",
  "properties": {
    "iso:country":"FR",
    "sg:address":"B.P. 90185, 86962 Futuroscope C\u00e9dex^^16, Bd des Fr\u00e8res Lumi\u00e8res - T\u00e9l\u00e9port 2, 86360 Chasseneuil du P",
    "sg:orig_category":"Non-Classified Establishments",
    "sg:phone":"+33 5 49 49 45 10",
    "sg:postcode":"86360",
    "sg:province":"Poitou-Charentes",
    "wof:name":"Ant\u00e9a S.a.",
    "wof:placetype":"venue"
},
  "geometry": {"coordinates":[0.37477,46.650494],"type":"Point"}
}