{
  "type": "Feature",
  "properties": {
    "iso:country":"FR",
    "sg:address":"14, Esplanade Paul C\u00e9zanne, 51100 Reims",
    "sg:orig_category":"Cart\u00e9risation de machines Chaudronnerie alimentaire Chaudronnerie aluminium Chaudronnerie en acier i",
    "sg:phone":"+33 3 26 87 84 75",
    "sg:postcode":"51100",
    "sg:province":"Champagne",
    "wof:name":"Mica S.a.r.l. - Maintenance Industrielle Champ Ardennaise",
    "wof:placetype":"venue"
},
  "geometry": {"coordinates":[4.01144,49.226509],"type":"Point"}
}