{
  "type": "Feature",
  "properties": {
    "iso:country":"FR",
    "sg:address":"18, Rue de Stenbach, 57200 Sarreguemines",
    "sg:orig_category":"Unclassifiable Establishments",
    "sg:phone":"+33 3 87 95 63 92",
    "sg:province":"Lorraine",
    "wof:name":"Sodiva Kihl Vins Et Spiritueux S.a.r.l.",
    "wof:placetype":"venue"
},
  "geometry": {"coordinates":[7.078103,49.10062],"type":"Point"}
}