{
  "type": "Feature",
  "properties": {
    "addr:full":"Chemin Des Sablieres Zone Artisanale 86210 Bonneuil Matours Poitou-Charentes 86210",
    "addr:postcode":"86210;86210",
    "addr:street":"Chemin Des Sablieres Zone Artisanale;Matours",
    "iso:country":"FR",
    "sg:address":"Chemin Des Sablieres Zone Artisanale 86210 Bonneuil Matours",
    "sg:classifiers":[
        {
            "category":"Manufacturing",
            "subcategory":"Wood Products",
            "type":"Manufacturing & Wholesale Goods"
        }
    ],
    "sg:phone":"+33 5 49 21 03 70",
    "sg:postcode":"86210",
    "sg:province":"Poitou-Charentes",
    "sg:tags":[
        "professional",
        "furniture"
    ],
    "wof:name":"Sarl Mcd (arform)",
    "wof:placetype":"venue"
},
  "geometry": {"coordinates":[0.591585,46.646172],"type":"Point"}
}