{
  "type": "Feature",
  "properties": {
    "iso:country":"FR",
    "sg:address":"13, Rue Etienne Richerand, 69003 Lyon",
    "sg:orig_category":"Unclassifiable Establishments",
    "sg:phone":"+33 4 72 35 12 25",
    "sg:postcode":"69003",
    "sg:province":"Rhone-Alpes",
    "wof:name":"Angst + Pfister S.a.",
    "wof:placetype":"venue"
},
  "geometry": {"coordinates":[4.866922,45.762707],"type":"Point"}
}