{
  "type": "Feature",
  "properties": {
    "iso:country":"FR",
    "sg:address":"13, Chemin du Levant, 01210 Fernay Voltaire",
    "sg:orig_category":"Unclassifiable Establishments",
    "sg:phone":"+33 4 50 40 54 35",
    "sg:province":"North Dakota",
    "wof:name":"Cabinet Michel Moinas",
    "wof:placetype":"venue"
},
  "geometry": {"coordinates":[-100.843224,48.020119],"type":"Point"}
}