{
  "type": "Feature",
  "properties": {
    "addr:full":"40 Rue Des Perrins 49130 Les Ponts De C\u00e9 Pays de Loire",
    "addr:housenumber":"40",
    "addr:postcode":"49130",
    "addr:street":"Rue Des Perrins;Ponts De Ce\u0301",
    "iso:country":"FR",
    "sg:address":"40 Rue Des Perrins 49130 Les Ponts De C\u00e9",
    "sg:classifiers":[
        {
            "category":"Manufacturing",
            "subcategory":"Paper Products",
            "type":"Manufacturing & Wholesale Goods"
        }
    ],
    "sg:phone":"+33 2 41 44 91 00",
    "sg:province":"Pays de Loire",
    "sg:tags":[
        "packaging",
        "material",
        "-",
        "cardboard"
    ],
    "wof:name":"Ste Huteau Sa",
    "wof:placetype":"venue"
},
  "geometry": {"coordinates":[-0.523464,47.44265],"type":"Point"}
}