{
  "type": "Feature",
  "properties": {
    "iso:country":"FR",
    "sg:address":"Rte de Mezzavia",
    "sg:city":"Ajaccio",
    "sg:orig_category":"Unclassifiable Establishments",
    "sg:phone":"+33 4 95 22 19 44",
    "sg:postcode":"20090",
    "sg:province":"Corse",
    "wof:name":"Ollandini Transports De Marchandises",
    "wof:placetype":"venue"
},
  "geometry": {"coordinates":[8.762596,41.94722],"type":"Point"}
}