{
  "type": "Feature",
  "properties": {
    "addr:full":"408, Av. du Prado, 13008 Marseille Poitou-Charentes",
    "addr:postcode":"13008",
    "addr:street":"408 Av. Du Prado",
    "iso:country":"FR",
    "sg:address":"408, Av. du Prado, 13008 Marseille",
    "sg:orig_category":"Non-Classified Establishments",
    "sg:phone":"+33 4 91 23 09 60",
    "sg:province":"Poitou-Charentes",
    "wof:name":"N.s.m.d - Neuflize Schlumberger Mallet Demachy",
    "wof:placetype":"venue"
},
  "geometry": {"coordinates":[5.3854,43.269012],"type":"Point"}
}