{
  "type": "Feature",
  "properties": {
    "addr:full":"B.P. 1039, 59701 Marcq en Baroeul C\u00e9dex^^395, Rue du G\u00e9n\u00e9ral de Gaulle, 59700 Marcq en Baroeul Nord Pas-de-Calais 59700",
    "addr:postcode":"59701;59700;59700",
    "addr:street":"B.P. 1039;Rue Du Ge\u0301Ne\u0301Ral De Gaulle;En Baroeul Nord",
    "iso:country":"FR",
    "sg:address":"B.P. 1039, 59701 Marcq en Baroeul C\u00e9dex^^395, Rue du G\u00e9n\u00e9ral de Gaulle, 59700 Marcq en Baroeul",
    "sg:orig_category":"Non-Classified Establishments",
    "sg:phone":"+33 3 20 43 93 20",
    "sg:postcode":"59700",
    "sg:province":"Nord Pas-de-Calais",
    "wof:name":"Cartotec S.a.",
    "wof:placetype":"venue"
},
  "geometry": {"coordinates":[3.09404,50.673965],"type":"Point"}
}