{
  "type": "Feature",
  "properties": {
    "addr:full":"Zone Industrielle de Bavilliers Argi\u00e9sans Franche Comt\u00e9 90800",
    "addr:postcode":"90800",
    "addr:street":"Zone Industrielle De Bavilliers;Franche Comte\u0301",
    "iso:country":"FR",
    "sg:address":"Zone Industrielle de Bavilliers",
    "sg:city":"Argi\u00e9sans",
    "sg:orig_category":"Unclassifiable Establishments",
    "sg:phone":"+33 3 84 90 16 90",
    "sg:postcode":"90800",
    "sg:province":"Franche Comt\u00e9",
    "wof:name":"Sogycobois S.a.",
    "wof:placetype":"venue"
},
  "geometry": {"coordinates":[6.821717,47.603027],"type":"Point"}
}