{
  "type": "Feature",
  "properties": {
    "addr:full":"34 Rue Gustave Lennier 76600 Le Havre Haute Normandie 76600",
    "addr:housenumber":"34",
    "addr:postcode":"76600;76600",
    "addr:street":"Rue Gustave Lennier",
    "iso:country":"FR",
    "sg:address":"34 Rue Gustave Lennier 76600 Le Havre",
    "sg:classifiers":[
        {
            "category":"Professional",
            "subcategory":"Business Services",
            "type":"Services"
        }
    ],
    "sg:phone":"+33 2 35 42 49 95",
    "sg:postcode":"76600",
    "sg:province":"Haute Normandie",
    "sg:tags":[
        "body",
        "advice"
    ],
    "wof:name":"Ligue Havraise Pour L'aide Aux Personnes Handicap\u00c9s",
    "wof:placetype":"venue"
},
  "geometry": {"coordinates":[0.108299,49.489223],"type":"Point"}
}