{
  "type": "Feature",
  "properties": {
    "addr:full":"263 boulevard Louise Michel 42153 Riorges Rhone-Alpes 42153",
    "addr:housenumber":"263",
    "addr:postcode":"42153;42153",
    "addr:street":"Boulevard Louise Michel;Rhone-Alpes",
    "iso:country":"FR",
    "sg:address":"263 boulevard Louise Michel 42153 Riorges",
    "sg:orig_category":"Caps Headwear",
    "sg:phone":"+33 4 77 71 29 39",
    "sg:postcode":"42153",
    "sg:province":"Rhone-Alpes",
    "wof:name":"Les Ateliers Tyral S.a.",
    "wof:placetype":"venue"
},
  "geometry": {"coordinates":[4.05182,46.051666],"type":"Point"}
}