{
  "type": "Feature",
  "properties": {
    "addr:full":"5 Pl Carnot 69002 Lyon Rhone-Alpes 69002",
    "addr:housenumber":"5",
    "addr:postcode":"69002;69002",
    "addr:street":"Pl Carnot",
    "iso:country":"FR",
    "sg:address":"5 Pl Carnot 69002 Lyon",
    "sg:classifiers":[
        {
            "category":"Shopping",
            "subcategory":"Clothing, Apparel, & Fashions",
            "type":"Retail Goods"
        }
    ],
    "sg:phone":"+33 4 72 77 02 45",
    "sg:postcode":"69002",
    "sg:province":"Rhone-Alpes",
    "sg:tags":[
        "textile",
        "clothing",
        "clothes"
    ],
    "wof:name":"Ste Expl Ets Sibarita",
    "wof:placetype":"venue"
},
  "geometry": {"coordinates":[4.82871,45.751644],"type":"Point"}
}