{
  "type": "Feature",
  "properties": {
    "addr:full":"ZAC de Valgora - Centre Herm\u00e8s Ilot 7 La Valette du Var Provence-Alpes-C\u00f4te d'Azur 83160",
    "addr:housenumber":"7",
    "addr:postcode":"83160",
    "addr:street":"Zac De Valgora;La Valette Du Var",
    "iso:country":"FR",
    "sg:address":"ZAC de Valgora - Centre Herm\u00e8s Ilot 7",
    "sg:city":"La Valette du Var",
    "sg:orig_category":"Non-Classified Establishments",
    "sg:phone":"+33 4 98 01 37 60",
    "sg:postcode":"83160",
    "sg:province":"Provence-Alpes-C\u00f4te d'Azur",
    "wof:name":"Teuchos Provence Alpes C\u00f4te D'azur S.a.r.l.",
    "wof:placetype":"venue"
},
  "geometry": {"coordinates":[5.980705,43.136925],"type":"Point"}
}