{
  "type": "Feature",
  "properties": {
    "addr:full":"13, Place Paul Soult, 81100 Castres Midi Pyr\u00e9n\u00e9es",
    "addr:housenumber":"13",
    "addr:postcode":"81100",
    "addr:street":"Place Paul Soult",
    "iso:country":"FR",
    "sg:address":"13, Place Paul Soult, 81100 Castres",
    "sg:orig_category":"Unclassifiable Establishments",
    "sg:phone":"+33 5 63 71 30 30",
    "sg:province":"Midi Pyr\u00e9n\u00e9es",
    "wof:name":"B.p.t.a. - Banque Populaire Du Tarn Et De L'aveyron",
    "wof:placetype":"venue"
},
  "geometry": {"coordinates":[2.246029,43.604347],"type":"Point"}
}