{
  "type": "Feature",
  "properties": {
    "iso:country":"FR",
    "sg:address":"10 Rue Malbec 33000 Bordeaux",
    "sg:city":"Bordeaux",
    "sg:classifiers":[
        {
            "category":"Food Court",
            "type":"Food & Drink"
        }
    ],
    "sg:phone":"+33 5 56 91 44 96",
    "sg:postcode":"33000",
    "sg:province":"Aquitaine",
    "sg:tags":[
        "product",
        "related"
    ],
    "wof:name":"Montagne Et Compagnie",
    "wof:placetype":"venue"
},
  "geometry": {"coordinates":[-0.561126,44.827305],"type":"Point"}
}