{
  "type": "Feature",
  "properties": {
    "addr:full":"B.P. 17, 60280 Clairoix^^Impasse des Etangs, 60280 Clairoix Picardie",
    "addr:postcode":"60280;60280",
    "addr:street":"B.P. 17;Des Etangs",
    "iso:country":"FR",
    "sg:address":"B.P. 17, 60280 Clairoix^^Impasse des Etangs, 60280 Clairoix",
    "sg:orig_category":"Non-Classified Establishments",
    "sg:phone":"+33 3 44 83 26 36",
    "sg:province":"Picardie",
    "wof:name":"Gantois S.a.",
    "wof:placetype":"venue"
},
  "geometry": {"coordinates":[2.817685,49.426105],"type":"Point"}
}