{
  "type": "Feature",
  "properties": {
    "addr:full":"3 Avenue Des Coudriers 78180 Montigny Le Bretonneux Ile de France 78180",
    "addr:housenumber":"3",
    "addr:postcode":"78180;78180",
    "addr:street":"Avenue Des Coudriers",
    "iso:country":"FR",
    "sg:address":"3 Avenue Des Coudriers 78180 Montigny Le Bretonneux",
    "sg:classifiers":[
        {
            "category":"Manufacturing",
            "subcategory":"Tools & Machinery",
            "type":"Manufacturing & Wholesale Goods"
        }
    ],
    "sg:phone":"+33 1 30 57 47 74",
    "sg:postcode":"78180",
    "sg:province":"Ile de France",
    "sg:tags":[
        "equipment",
        "measurement",
        "-",
        "precision",
        "instrument"
    ],
    "wof:name":"Lloyd Instruments Sa",
    "wof:placetype":"venue"
},
  "geometry": {"coordinates":[2.020509,48.776863],"type":"Point"}
}