{
  "type": "Feature",
  "properties": {
    "addr:full":"5, Rue d'Antin, 59800 Lille Nord Pas-de-Calais",
    "addr:housenumber":"5",
    "addr:postcode":"59800",
    "addr:street":"Rue D'Antin",
    "iso:country":"FR",
    "sg:address":"5, Rue d'Antin, 59800 Lille",
    "sg:orig_category":"Unclassifiable Establishments",
    "sg:phone":"+33 3 20 12 88 91",
    "sg:province":"Nord Pas-de-Calais",
    "wof:name":"Conrad Electronic S.a.",
    "wof:placetype":"venue"
},
  "geometry": {"coordinates":[3.046304,50.627968],"type":"Point"}
}