{
  "type": "Feature",
  "properties": {
    "addr:full":"ZA de la Halleraie Vern sur Seiche Bretagne 35770",
    "addr:postcode":"35770",
    "addr:street":"Za De La Halleraie Vern Sur Seiche Bretagne",
    "iso:country":"FR",
    "sg:address":"ZA de la Halleraie",
    "sg:city":"Vern sur Seiche",
    "sg:orig_category":"Unclassifiable Establishments",
    "sg:phone":"+33 2 99 53 02 78",
    "sg:postcode":"35770",
    "sg:province":"Bretagne",
    "wof:name":"P.r.b. S.a. - Produits De Rev\u00eatement Du B\u00e2timent",
    "wof:placetype":"venue"
},
  "geometry": {"coordinates":[-1.604871,48.050728],"type":"Point"}
}