{
  "type": "Feature",
  "properties": {
    "addr:full":"B.P. 317, 92156 Suresnes C\u00e9dex^^51, Rue Carnot, 92150 Suresnes Ile de France",
    "addr:housenumber":"b.p. 317",
    "addr:postcode":"92156;92150;ile",
    "addr:street":"Rue Carnot",
    "iso:country":"FR",
    "sg:address":"B.P. 317, 92156 Suresnes C\u00e9dex^^51, Rue Carnot, 92150 Suresnes",
    "sg:orig_category":"Non-Classified Establishments",
    "sg:phone":"+33 1 40 99 61 61",
    "sg:province":"Ile de France",
    "wof:name":"Philips Composants Et Semi-conducteurs S.a.",
    "wof:placetype":"venue"
},
  "geometry": {"coordinates":[2.22677,48.867504],"type":"Point"}
}