{
  "type": "Feature",
  "properties": {
    "iso:country":"FR",
    "sg:address":"Lotissement Artisanal Male 47480 Pont Du Casse",
    "sg:city":"Bajamont",
    "sg:classifiers":[
        {
            "category":"Manufacturing",
            "subcategory":"Wood Products",
            "type":"Manufacturing & Wholesale Goods"
        }
    ],
    "sg:phone":"+33 5 53 66 83 55",
    "sg:postcode":"47480",
    "sg:province":"Aquitaine",
    "sg:tags":[
        "professional",
        "furniture"
    ],
    "wof:name":"Societe D'exploitation Des Etablissements Suire",
    "wof:placetype":"venue"
},
  "geometry": {"coordinates":[0.680915,44.231335],"type":"Point"}
}