{
  "type": "Feature",
  "properties": {
    "addr:full":"35, Rue de la Commune de Paris, 59760 Grande Synthe Nord Pas-de-Calais",
    "addr:housenumber":"35",
    "addr:postcode":"59760",
    "addr:street":"Rue De La Commune De Paris",
    "iso:country":"FR",
    "sg:address":"35, Rue de la Commune de Paris, 59760 Grande Synthe",
    "sg:orig_category":"Unclassifiable Establishments",
    "sg:phone":"+33 3 28 28 90 50",
    "sg:province":"Nord Pas-de-Calais",
    "wof:name":"A.n.p.e.",
    "wof:placetype":"venue"
},
  "geometry": {"coordinates":[2.30457,51.012772],"type":"Point"}
}