{
  "type": "Feature",
  "properties": {
    "iso:country":"FR",
    "sg:address":"9, Rue Alfred Kastler, 44300 Nantes",
    "sg:orig_category":"Unclassifiable Establishments",
    "sg:phone":"+33 2 51 85 26 66",
    "sg:province":"Pays de Loire",
    "wof:name":"Prios Soft Ware S.a.",
    "wof:placetype":"venue"
},
  "geometry": {"coordinates":[-1.520547,47.281116],"type":"Point"}
}