{
  "type": "Feature",
  "properties": {
    "addr:full":"B.P. 919, 45209 Montargis C\u00e9dex^^206, Rue Saint Gabriel - ZI Amilly, 45200 Amilly Montargis Centre 45200",
    "addr:housenumber":"b.p. 919",
    "addr:postcode":"45209;45200;45200",
    "addr:street":"Rue Saint Gabriel Zi",
    "iso:country":"FR",
    "sg:address":"B.P. 919, 45209 Montargis C\u00e9dex^^206, Rue Saint Gabriel - ZI Amilly, 45200 Amilly",
    "sg:city":"Montargis",
    "sg:orig_category":"Non-Classified Establishments",
    "sg:phone":"+33 2 38 95 08 08",
    "sg:postcode":"45200",
    "sg:province":"Centre",
    "wof:name":"Transports Tendron S.a.",
    "wof:placetype":"venue"
},
  "geometry": {"coordinates":[2.767561,47.974705],"type":"Point"}
}