{
  "type": "Feature",
  "properties": {
    "addr:full":"Lieu Dit Bramfan 16240 Paizay Naudouin Embourie Poitou-Charentes 16240",
    "addr:postcode":"16240;16240",
    "addr:street":"Lieu Dit Bramfan;Embourie",
    "iso:country":"FR",
    "sg:address":"Lieu Dit Bramfan 16240 Paizay Naudouin Embourie",
    "sg:classifiers":[
        {
            "category":"Home & Garden",
            "subcategory":"Furniture",
            "type":"Retail Goods"
        }
    ],
    "sg:phone":"+33 5 45 71 18 35",
    "sg:postcode":"16240",
    "sg:province":"Poitou-Charentes",
    "sg:tags":[
        "household",
        "wood"
    ],
    "wof:name":"Etablissements Michaud",
    "wof:placetype":"venue"
},
  "geometry": {"coordinates":[0.007295,46.044548],"type":"Point"}
}