{
  "type": "Feature",
  "properties": {
    "addr:full":"13 rue de la Brot 21000 Dijon Dijon Bourgogne 21000",
    "addr:housenumber":"13",
    "addr:postcode":"21000;21000",
    "addr:street":"Rue De La Brot",
    "iso:country":"FR",
    "sg:address":"13 rue de la Brot 21000 Dijon",
    "sg:city":"Dijon",
    "sg:classifiers":[
        {
            "category":"Manufacturing",
            "subcategory":"Rubber & Plastics",
            "type":"Manufacturing & Wholesale Goods"
        }
    ],
    "sg:phone":"+33 3 80 73 21 63",
    "sg:postcode":"21000",
    "sg:province":"Bourgogne",
    "sg:tags":[
        "processing"
    ],
    "wof:name":"Vernet Behringer S.a.",
    "wof:placetype":"venue"
},
  "geometry": {"coordinates":[5.071758,47.345451],"type":"Point"}
}