{
  "type": "Feature",
  "properties": {
    "addr:full":"58300 Decize Decize Bourgogne 58300",
    "addr:postcode":"58300;58300",
    "iso:country":"FR",
    "sg:address":"58300 Decize",
    "sg:city":"Decize",
    "sg:orig_category":"Unclassifiable Establishments",
    "sg:phone":"+33 3 86 77 32 32",
    "sg:postcode":"58300",
    "sg:province":"Bourgogne",
    "wof:name":"Michelin A.v.s. - Usine De Caillots S.a.",
    "wof:placetype":"venue"
},
  "geometry": {"coordinates":[3.4639,46.80706],"type":"Point"}
}