{
  "type": "Feature",
  "properties": {
    "addr:full":"La Croix Des Cinq Chemins 35460 Baill\u00e9 Baill\u00e9 Bretagne 35460",
    "addr:postcode":"35460;35460",
    "addr:street":"La Croix Des Cinq Chemins;Baille\u0301",
    "iso:country":"FR",
    "sg:address":"La Croix Des Cinq Chemins 35460 Baill\u00e9",
    "sg:city":"Baill\u00e9",
    "sg:classifiers":[
        {
            "category":"Shopping",
            "type":"Retail Goods"
        }
    ],
    "sg:phone":"+33 2 99 18 57 18",
    "sg:postcode":"35460",
    "sg:province":"Bretagne",
    "sg:tags":[
        "metallurgy",
        "finished",
        "-",
        "metalworking",
        "metallic"
    ],
    "wof:name":"Legris Sa",
    "wof:placetype":"venue"
},
  "geometry": {"coordinates":[-1.372909,48.377628],"type":"Point"}
}