{
  "type": "Feature",
  "properties": {
    "addr:full":"Rue Giesmard Carentan Basse Normandie 50500",
    "addr:postcode":"50500",
    "addr:street":"Rue Giesmard",
    "iso:country":"FR",
    "sg:address":"Rue Giesmard",
    "sg:city":"Carentan",
    "sg:orig_category":"Non-Classified Establishments",
    "sg:phone":"+33 2 33 71 01 01",
    "sg:postcode":"50500",
    "sg:province":"Basse Normandie",
    "wof:name":"Serpico",
    "wof:placetype":"venue"
},
  "geometry": {"coordinates":[-1.234689,49.303123],"type":"Point"}
}