{
  "type": "Feature",
  "properties": {
    "iso:country":"FR",
    "sg:address":"Route D Apremont Zi De L Albanne 73490 La Ravoire",
    "sg:classifiers":[
        {
            "category":"Professional",
            "subcategory":"Engineering",
            "type":"Services"
        }
    ],
    "sg:phone":"+33 4 79 28 28 67",
    "sg:postcode":"73490",
    "sg:province":"Rhone-Alpes",
    "sg:tags":[
        "instrument",
        "measurement",
        "-",
        "precision",
        "machine",
        "equipment",
        "mechanical"
    ],
    "wof:name":"Etudes De Lignes De Pesage Et D'ensachage (elpe)",
    "wof:placetype":"venue"
},
  "geometry": {"coordinates":[5.961922,45.55677],"type":"Point"}
}