{
  "type": "Feature",
  "properties": {
    "addr:full":"ZI le Terrdeau 84971 Carpentras Languedoc-Roussillon",
    "addr:postcode":"84971",
    "addr:street":"Zi Le Terrdeau",
    "iso:country":"FR",
    "sg:address":"ZI le Terrdeau 84971 Carpentras",
    "sg:classifiers":[
        {
            "category":"Professional",
            "subcategory":"Accounting & Tax Preparation",
            "type":"Services"
        }
    ],
    "sg:phone":"+33 4 90 63 89 89",
    "sg:province":"Languedoc-Roussillon",
    "sg:tags":[
        "additive",
        "baking"
    ],
    "wof:name":"Ducros Sa",
    "wof:placetype":"venue"
},
  "geometry": {"coordinates":[5.04769,44.052078],"type":"Point"}
}