{
  "type": "Feature",
  "properties": {
    "addr:full":"6, Rue de la Garenne, 95310 Saint Ouen l'Aum\u00f4ne Ile de France",
    "addr:housenumber":"6",
    "addr:postcode":"95310",
    "addr:street":"Rue De La Garenne",
    "iso:country":"FR",
    "sg:address":"6, Rue de la Garenne, 95310 Saint Ouen l'Aum\u00f4ne",
    "sg:orig_category":"Unclassifiable Establishments",
    "sg:phone":"+33 1 34 32 50 50",
    "sg:province":"Ile de France",
    "wof:name":"Straub S.a.",
    "wof:placetype":"venue"
},
  "geometry": {"coordinates":[2.828237,48.578621],"type":"Point"}
}