{
  "type": "Feature",
  "properties": {
    "addr:full":"5 R De Copenhague 13127 Vitrolles Centre",
    "addr:housenumber":"5",
    "addr:postcode":"13127",
    "addr:street":"R De Copenhague",
    "iso:country":"FR",
    "sg:address":"5 R De Copenhague 13127 Vitrolles",
    "sg:classifiers":[
        {
            "category":"Building & Trades",
            "subcategory":"Construction",
            "type":"Services"
        }
    ],
    "sg:phone":"+33 4 42 10 11 12",
    "sg:province":"Centre",
    "sg:tags":[
        "work",
        "public"
    ],
    "wof:name":"Appia",
    "wof:placetype":"venue"
},
  "geometry": {"coordinates":[5.242514,43.427128],"type":"Point"}
}