{
  "type": "Feature",
  "properties": {
    "iso:country":"FR",
    "sg:address":"116 Bd St Marcel 13011 Marseille Cedex 11",
    "sg:classifiers":[
        {
            "category":"Manufacturing",
            "subcategory":"Tools & Machinery",
            "type":"Manufacturing & Wholesale Goods"
        }
    ],
    "sg:phone":"+33 4 91 44 56 19",
    "sg:province":"Poitou-Charentes",
    "sg:tags":[
        "metallurgy",
        "metalworking"
    ],
    "wof:name":"Ste Denyfontaine Sa",
    "wof:placetype":"venue"
},
  "geometry": {"coordinates":[5.462679,43.288269],"type":"Point"}
}