{
  "type": "Feature",
  "properties": {
    "addr:full":"12-14 rue Fran\u00e7ois Barbini 13003 Marseille Rhone-Alpes",
    "addr:housenumber":"12-14",
    "addr:postcode":"13003",
    "addr:street":"Rue Franc\u0327Ois Barbini",
    "iso:country":"FR",
    "sg:address":"12-14 rue Fran\u00e7ois Barbini 13003 Marseille",
    "sg:orig_category":"Girls' Clothing",
    "sg:phone":"+33 4 91 50 24 00",
    "sg:province":"Rhone-Alpes",
    "wof:name":"Am Trak S.a.r.l.",
    "wof:placetype":"venue"
},
  "geometry": {"coordinates":[5.382427,43.31332],"type":"Point"}
}