{
  "type": "Feature",
  "properties": {
    "addr:full":"5, Traverse du Chemin de Fer, 13400 Aubagne Franche Comt\u00e9",
    "addr:housenumber":"5",
    "addr:postcode":"13400",
    "addr:street":"Traverse Du Chemin De Fer;Franche Comte\u0301",
    "iso:country":"FR",
    "sg:address":"5, Traverse du Chemin de Fer, 13400 Aubagne",
    "sg:orig_category":"Non-Classified Establishments",
    "sg:phone":"+33 4 42 03 26 55",
    "sg:province":"Franche Comt\u00e9",
    "wof:name":"E.g.p. S.a.r.l. - Electroplastie G\u00e9n\u00e9rale Phoc\u00e9enne",
    "wof:placetype":"venue"
},
  "geometry": {"coordinates":[5.546165,43.287506],"type":"Point"}
}