{
  "type": "Feature",
  "properties": {
    "addr:full":"84110 Sablet Provence-Alpes-C\u00f4te d'Azur",
    "addr:postcode":"84110",
    "iso:country":"FR",
    "sg:address":"84110 Sablet",
    "sg:orig_category":"Non-Classified Establishments",
    "sg:phone":"+33 4 90 28 28 80",
    "sg:province":"Provence-Alpes-C\u00f4te d'Azur",
    "wof:name":"Lavau Mouret Et Compagnie S.a.",
    "wof:placetype":"venue"
},
  "geometry": {"coordinates":[5.008068,44.190483],"type":"Point"}
}