{
  "type": "Feature",
  "properties": {
    "iso:country":"FR",
    "sg:address":"Ile de Saulcy 57045 Metz",
    "sg:orig_category":"Unclassifiable Establishments",
    "sg:phone":"+33 3 87 34 69 00",
    "sg:province":"Lorraine",
    "wof:name":"E.n.i.m. - Ecole Nationale D'ing\u00e9nieurs De Metz",
    "wof:placetype":"venue"
},
  "geometry": {"coordinates":[6.168035,49.120346],"type":"Point"}
}