{
  "type": "Feature",
  "properties": {
    "iso:country":"FR",
    "sg:address":"43, Rue des Ponts de Comines, 59800 Lille",
    "sg:orig_category":"Unclassifiable Establishments",
    "sg:phone":"+33 3 20 74 37 63",
    "sg:province":"Nord Pas-de-Calais",
    "wof:name":"Askell Promotion Nord S.a.",
    "wof:placetype":"venue"
},
  "geometry": {"coordinates":[3.067775,50.637768],"type":"Point"}
}