{
  "type": "Feature",
  "properties": {
    "iso:country":"FR",
    "sg:address":"1, All\u00e9e du Verger, 95700 Roissy en France",
    "sg:orig_category":"Non-Classified Establishments",
    "sg:phone":"+33 1 34 29 30 00",
    "sg:province":"Ile de France",
    "wof:name":"Holiday Inn Paris Charles De Gaulle S.a.r.l.",
    "wof:placetype":"venue"
},
  "geometry": {"coordinates":[2.521274,49.005383],"type":"Point"}
}