{
  "type": "Feature",
  "properties": {
    "iso:country":"FR",
    "sg:address":"110, Av. Marcellin Berthelot, 69520 Grigny",
    "sg:orig_category":"Non-Classified Establishments",
    "sg:phone":"+33 4 72 24 17 03",
    "sg:province":"Rhone-Alpes",
    "wof:name":"Matec S.a.r.l.",
    "wof:placetype":"venue"
},
  "geometry": {"coordinates":[4.776915,45.595551],"type":"Point"}
}