{
  "type": "Feature",
  "properties": {
    "addr:full":"Rond Point Maurice le Lannou - ZAC Atalante Rennes Bretagne 35000",
    "addr:postcode":"35000",
    "addr:street":"Rond Point Maurice Le Lannou Zac Atalante Rennes",
    "iso:country":"FR",
    "sg:address":"Rond Point Maurice le Lannou - ZAC Atalante",
    "sg:city":"Rennes",
    "sg:orig_category":"Unclassifiable Establishments",
    "sg:phone":"+33 2 23 48 28 80",
    "sg:postcode":"35000",
    "sg:province":"Bretagne",
    "wof:name":"Space G.i.e.",
    "wof:placetype":"venue"
},
  "geometry": {"coordinates":[-1.712938,48.114822],"type":"Point"}
}