{
  "type": "Feature",
  "properties": {
    "iso:country":"FR",
    "sg:address":"283 Rue Auguste Marchal 59571 Jeumont Cedex",
    "sg:classifiers":[
        {
            "category":"Professional",
            "subcategory":"Engineering",
            "type":"Services"
        }
    ],
    "sg:phone":"+33 3 27 39 44 88",
    "sg:province":"Haute Normandie",
    "sg:tags":[
        "machine",
        "-",
        "mechanical"
    ],
    "wof:name":"Cercleurop Sa",
    "wof:placetype":"venue"
},
  "geometry": {"coordinates":[4.088899,50.29306],"type":"Point"}
}