{
  "type": "Feature",
  "properties": {
    "iso:country":"FR",
    "sg:address":"B.P. 2, 67901 Strasbourg C\u00e9dex 9^^12, Rue du March\u00e9 Gare, 67200 Strasbourg",
    "sg:city":"Strasbourg",
    "sg:orig_category":"Non-Classified Establishments",
    "sg:phone":"+33 3 88 77 78 78",
    "sg:postcode":"67200",
    "sg:province":"Alsace",
    "wof:name":"S.a.p.a.m. S.a. - Soci\u00e9t\u00e9 Approvisionnement Produits Afrique M\u00e9tropole",
    "wof:placetype":"venue"
},
  "geometry": {"coordinates":[7.71425,48.578671],"type":"Point"}
}