{
  "type": "Feature",
  "properties": {
    "iso:country":"FR",
    "sg:address":"4, Chemin du Malacher, 38240 Meylan",
    "sg:orig_category":"Non-Classified Establishments",
    "sg:phone":"+33 4 76 18 04 34",
    "sg:postcode":"38240",
    "sg:province":"Rhone-Alpes",
    "wof:name":"Astria D\u00e9veloppement S.a.",
    "wof:placetype":"venue"
},
  "geometry": {"coordinates":[5.786745,45.210472],"type":"Point"}
}