{
  "type": "Feature",
  "properties": {
    "addr:full":"19, Rue Jacquemart Templeux, 08000 Charleville M\u00e9zi\u00e8res Charleville-M\u00e9zi\u00e8res Champagne 08000",
    "addr:housenumber":"19",
    "addr:postcode":"08000;08000",
    "addr:street":"Rue Jacquemart",
    "iso:country":"FR",
    "sg:address":"19, Rue Jacquemart Templeux, 08000 Charleville M\u00e9zi\u00e8res",
    "sg:city":"Charleville-M\u00e9zi\u00e8res",
    "sg:orig_category":"Non-Classified Establishments",
    "sg:phone":"+33 3 24 59 35 76",
    "sg:postcode":"08000",
    "sg:province":"Champagne",
    "wof:name":"R.e.a. S.a.r.l. - Rev\u00eatements Electrolytiques Ardennais",
    "wof:placetype":"venue"
},
  "geometry": {"coordinates":[4.727926,49.771385],"type":"Point"}
}