{
  "type": "Feature",
  "properties": {
    "iso:country":"FR",
    "sg:address":"Rue Danton",
    "sg:city":"Cormeilles en Parisis",
    "sg:orig_category":"Unclassifiable Establishments",
    "sg:phone":"+33 1 39 31 31 31",
    "sg:postcode":"95240",
    "sg:province":"Ile de France",
    "wof:name":"Georges Borca Et Fils S.a.",
    "wof:placetype":"venue"
},
  "geometry": {"coordinates":[2.200907,48.961903],"type":"Point"}
}