{
  "type": "Feature",
  "properties": {
    "addr:full":"Le Bourg 01480 Villeneuve Rhone-Alpes 01480",
    "addr:postcode":"01480;01480",
    "addr:street":"Le Bourg",
    "iso:country":"FR",
    "sg:address":"Le Bourg 01480 Villeneuve",
    "sg:classifiers":[
        {
            "category":"Farming",
            "subcategory":"Livestock Farm",
            "type":"Manufacturing & Wholesale Goods"
        }
    ],
    "sg:phone":"+33 4 74 00 75 85",
    "sg:postcode":"01480",
    "sg:province":"Rhone-Alpes",
    "sg:tags":[
        "breeding",
        "agriculture",
        "animal"
    ],
    "wof:name":"Perraud Jean Paul",
    "wof:placetype":"venue"
},
  "geometry": {"coordinates":[4.78928,46.00367],"type":"Point"}
}