{
  "type": "Feature",
  "properties": {
    "iso:country":"FR",
    "sg:address":"8, Chemin du Grand Pas - Zone Auguste 1, 33610 Cestas",
    "sg:city":"Cestas",
    "sg:orig_category":"Non-Classified Establishments",
    "sg:phone":"+33 5 56 07 01 34",
    "sg:postcode":"33610",
    "sg:province":"Aquitaine",
    "wof:name":"A.m.g. S.a.r.l. - Atelier M\u00e9tallerie Girondine",
    "wof:placetype":"venue"
},
  "geometry": {"coordinates":[-0.685714,44.741707],"type":"Point"}
}