{
  "type": "Feature",
  "properties": {
    "iso:country":"FR",
    "sg:address":"Hameau de Bezuet 02400 B\u00e9zu Saint Germain",
    "sg:orig_category":"Unclassifiable Establishments",
    "sg:phone":"+33 3 23 70 80 39",
    "sg:province":"Picardie",
    "wof:name":"M\u00e9tal Alu S.a.r.l.",
    "wof:placetype":"venue"
},
  "geometry": {"coordinates":[3.39314,49.05019],"type":"Point"}
}