{
  "type": "Feature",
  "properties": {
    "iso:country":"FR",
    "sg:address":"17, Rue des Fr\u00e8res Lumi\u00e8re, 67201 Eckbolsheim",
    "sg:city":"Eckbolsheim",
    "sg:orig_category":"Unclassifiable Establishments",
    "sg:phone":"+33 3 90 20 25 25",
    "sg:postcode":"67201",
    "sg:province":"Alsace",
    "wof:name":"Iss Abilis S.a.s.",
    "wof:placetype":"venue"
},
  "geometry": {"coordinates":[7.686251,48.587257],"type":"Point"}
}