{
  "type": "Feature",
  "properties": {
    "addr:full":"7, Rue de l' Egalit\u00e9, 65200 Bagn\u00e8res de Bigorre Midi Pyr\u00e9n\u00e9es",
    "addr:housenumber":"7",
    "addr:postcode":"65200",
    "addr:street":"Rue De L ' Egalite\u0301",
    "iso:country":"FR",
    "sg:address":"7, Rue de l' Egalit\u00e9, 65200 Bagn\u00e8res de Bigorre",
    "sg:orig_category":"Unclassifiable Establishments",
    "sg:phone":"+33 5 62 91 00 38",
    "sg:province":"Midi Pyr\u00e9n\u00e9es",
    "wof:name":"M.c.i. S.a. - Moteurs Et C\u00e2blages Industriels",
    "wof:placetype":"venue"
},
  "geometry": {"coordinates":[0.151085,43.070175],"type":"Point"}
}