{
  "type": "Feature",
  "properties": {
    "iso:country":"FR",
    "sg:address":"7 R L\u00e9on Berthault 35064 Rennes Cedex",
    "sg:classifiers":[
        {
            "category":"Shopping",
            "type":"Retail Goods"
        }
    ],
    "sg:phone":"+33 2 99 59 23 68",
    "sg:province":"Picardie",
    "sg:tags":[
        "metallurgy",
        "finished",
        "-",
        "metalworking",
        "metallic"
    ],
    "wof:name":"Abriom",
    "wof:placetype":"venue"
},
  "geometry": {"coordinates":[-1.730974,48.10899],"type":"Point"}
}