{
  "type": "Feature",
  "properties": {
    "addr:full":"19, Av. de Fontcouverte, 84000 Avignon Provence-Alpes-C\u00f4te d'Azur",
    "addr:postcode":"84000",
    "addr:street":"19 Av. De Fontcouverte",
    "iso:country":"FR",
    "sg:address":"19, Av. de Fontcouverte, 84000 Avignon",
    "sg:orig_category":"Unclassifiable Establishments",
    "sg:phone":"+33 4 90 89 35 00",
    "sg:province":"Provence-Alpes-C\u00f4te d'Azur",
    "wof:name":"S.p.b. S.a.r.l. - Soci\u00e9t\u00e9 Proven\u00e7ale De Boulonnerie",
    "wof:placetype":"venue"
},
  "geometry": {"coordinates":[4.843807,43.937382],"type":"Point"}
}