{
  "type": "Feature",
  "properties": {
    "iso:country":"FR",
    "sg:address":"8 R L\u00e9onard De Vinci Zac De La Haie Passart 77170 Brie Comte Robert",
    "sg:classifiers":[
        {
            "category":"Professional",
            "subcategory":"Engineering",
            "type":"Services"
        }
    ],
    "sg:phone":"+33 1 60 62 48 90",
    "sg:postcode":"77170",
    "sg:province":"Ile de France",
    "sg:tags":[
        "machine",
        "-",
        "mechanical"
    ],
    "wof:name":"Senabra-isotherm Sarl",
    "wof:placetype":"venue"
},
  "geometry": {"coordinates":[2.612735,48.691845],"type":"Point"}
}