{
  "type": "Feature",
  "properties": {
    "iso:country":"FR",
    "sg:address":"32, Av. de la R\u00e9publique, 78640 Neauphle le Ch\u00e2teau",
    "sg:orig_category":"Unclassifiable Establishments",
    "sg:phone":"+33 1 34 89 61 62",
    "sg:province":"Ile de France",
    "wof:name":"Henri Blanc S.a.",
    "wof:placetype":"venue"
},
  "geometry": {"coordinates":[1.905759,48.81152],"type":"Point"}
}