{
  "type": "Feature",
  "properties": {
    "addr:full":"B.P. 705, 84033 Avignon C\u00e9dex^^Av. l'Amandier, 84000 Avignon Rhone-Alpes",
    "addr:housenumber":"b.p. 705",
    "addr:postcode":"84033;l'amandier 84000",
    "iso:country":"FR",
    "sg:address":"B.P. 705, 84033 Avignon C\u00e9dex^^Av. l'Amandier, 84000 Avignon",
    "sg:orig_category":"Non-Classified Establishments",
    "sg:phone":"+33 4 90 13 46 60",
    "sg:province":"Rhone-Alpes",
    "wof:name":"L'appovisionnement Electrique",
    "wof:placetype":"venue"
},
  "geometry": {"coordinates":[4.856467,43.950359],"type":"Point"}
}