{
  "type": "Feature",
  "properties": {
    "iso:country":"FR",
    "sg:address":"Rue Fran\u00e7ois-No\u00ebl Baboeuf - Quartier Camp Laurent",
    "sg:city":"La Seyne sur Mer",
    "sg:orig_category":"Unclassifiable Establishments",
    "sg:phone":"+33 4 94 10 99 00",
    "sg:postcode":"83500",
    "sg:province":"Champagne",
    "wof:name":"Axima S.a.",
    "wof:placetype":"venue"
},
  "geometry": {"coordinates":[5.85831,43.11478],"type":"Point"}
}