{
  "type": "Feature",
  "properties": {
    "iso:country":"FR",
    "sg:address":"19 Av Du Grand Verger 44105 Nantes Cedex 04",
    "sg:classifiers":[
        {
            "category":"Professional",
            "subcategory":"Business Services",
            "type":"Services"
        }
    ],
    "sg:phone":"+33 2 40 43 43 44",
    "sg:province":"Basse Normandie",
    "sg:tags":[
        "instrument",
        "advice",
        "-",
        "precision",
        "equipment",
        "health"
    ],
    "wof:name":"Siemens Sas",
    "wof:placetype":"venue"
},
  "geometry": {"coordinates":[-1.602253,47.207546],"type":"Point"}
}