{
  "type": "Feature",
  "properties": {
    "addr:full":"120, Rte du M\u00e9doc, 33110 Le Bouscat Le Bouscat Aquitaine 33110",
    "addr:housenumber":"120",
    "addr:postcode":"33110;33110",
    "addr:street":"Rte Du Me\u0301Doc",
    "iso:country":"FR",
    "sg:address":"120, Rte du M\u00e9doc, 33110 Le Bouscat",
    "sg:city":"Le Bouscat",
    "sg:orig_category":"Unclassifiable Establishments",
    "sg:phone":"+33 5 56 28 25 91",
    "sg:postcode":"33110",
    "sg:province":"Aquitaine",
    "wof:name":"Cemonet Aquitaine S.a.r.l.",
    "wof:placetype":"venue"
},
  "geometry": {"coordinates":[-0.622164,44.876743],"type":"Point"}
}