{
  "type": "Feature",
  "properties": {
    "iso:country":"FR",
    "sg:address":"120, Rte du M\u00e9doc, 33110 Le Bouscat",
    "sg:city":"Le Bouscat",
    "sg:orig_category":"Unclassifiable Establishments",
    "sg:phone":"+33 5 56 28 25 91",
    "sg:postcode":"33110",
    "sg:province":"Aquitaine",
    "wof:name":"Cemonet Aquitaine S.a.r.l.",
    "wof:placetype":"venue"
},
  "geometry": {"coordinates":[-0.622164,44.876743],"type":"Point"}
}