{
  "type": "Feature",
  "properties": {
    "addr:full":"ZI Saint Maurice Manosque Provence-Alpes-C\u00f4te d'Azur 04100",
    "addr:postcode":"04100",
    "iso:country":"FR",
    "sg:address":"ZI Saint Maurice",
    "sg:city":"Manosque",
    "sg:orig_category":"Unclassifiable Establishments",
    "sg:phone":"+33 4 92 70 19 00",
    "sg:postcode":"04100",
    "sg:province":"Provence-Alpes-C\u00f4te d'Azur",
    "wof:name":"L'occitane S.a.",
    "wof:placetype":"venue"
},
  "geometry": {"coordinates":[5.784205,43.831474],"type":"Point"}
}