{
  "type": "Feature",
  "properties": {
    "iso:country":"FR",
    "sg:address":"Rte de Cambrai",
    "sg:city":"Marcoing",
    "sg:orig_category":"Unclassifiable Establishments",
    "sg:phone":"+33 3 27 37 52 56",
    "sg:postcode":"59159",
    "sg:province":"Nord Pas-de-Calais",
    "wof:name":"Electro B\u00e9ton S.a.r.l.",
    "wof:placetype":"venue"
},
  "geometry": {"coordinates":[3.183746,50.122772],"type":"Point"}
}