{
  "type": "Feature",
  "properties": {
    "addr:full":"Portes De La For\u00eat Du Clos Parc D'Activit\u00e9s 77090 Collegien Ile de France",
    "addr:postcode":"77090",
    "addr:street":"La Fore\u0302T Du Clos Parc D'Activite \u0301S;Ile De France",
    "iso:country":"FR",
    "sg:address":"Portes De La For\u00eat",
    "sg:city":"Du Clos Parc D'Activit\u00e9s 77090 Collegien",
    "sg:classifiers":[
        {
            "category":"Manufacturing",
            "subcategory":"Rubber & Plastics",
            "type":"Manufacturing & Wholesale Goods"
        }
    ],
    "sg:phone":"+33 1 60 06 05 10",
    "sg:province":"Ile de France",
    "wof:name":"Transfoplak",
    "wof:placetype":"venue"
},
  "geometry": {"coordinates":[2.67576,48.82486],"type":"Point"}
}