{
  "type": "Feature",
  "properties": {
    "addr:full":"B.P. 206, 61306 L'Aigle C\u00e9dex^^Rte de Crulai - ZI n\u00b0 1 - Fr\u00e9mondi\u00e8re , 61300 L'Aigle Crulai Basse Normandie 61300",
    "addr:housenumber":"b.p. 206",
    "addr:postcode":"61306;61300;61300",
    "addr:street":"Fre\u0301Mondie\u0300Re",
    "iso:country":"FR",
    "sg:address":"B.P. 206, 61306 L'Aigle C\u00e9dex^^Rte de Crulai - ZI n\u00b0 1 - Fr\u00e9mondi\u00e8re , 61300 L'Aigle",
    "sg:city":"Crulai",
    "sg:orig_category":"Non-Classified Establishments",
    "sg:phone":"+33 2 33 84 50 50",
    "sg:postcode":"61300",
    "sg:province":"Basse Normandie",
    "wof:name":"Pelletier Et Jaminet S.a.r.l.",
    "wof:placetype":"venue"
},
  "geometry": {"coordinates":[0.64151,48.73592],"type":"Point"}
}