{
  "type": "Feature",
  "properties": {
    "addr:full":"18, Rue de Paris, 60420 Tricot Picardie",
    "addr:housenumber":"18",
    "addr:postcode":"60420",
    "addr:street":"Rue De Paris",
    "iso:country":"FR",
    "sg:address":"18, Rue de Paris, 60420 Tricot",
    "sg:orig_category":"Unclassifiable Establishments",
    "sg:phone":"+33 3 44 51 30 87",
    "sg:province":"Picardie",
    "wof:name":"Excelsior Fonderie S.a.",
    "wof:placetype":"venue"
},
  "geometry": {"coordinates":[2.596533,49.55529],"type":"Point"}
}