{
  "type": "Feature",
  "properties": {
    "addr:full":"6, Av d'Alsace, 90160 Denney Franche Comt\u00e9",
    "addr:postcode":"90160",
    "addr:street":"Av D'Alsace;Franche Comte\u0301",
    "iso:country":"FR",
    "sg:address":"6, Av d'Alsace, 90160 Denney",
    "sg:orig_category":"Unclassifiable Establishments",
    "sg:phone":"+33 3 84 29 87 55",
    "sg:province":"Franche Comt\u00e9",
    "wof:name":"O.p.s.d. S.a.r.l.",
    "wof:placetype":"venue"
},
  "geometry": {"coordinates":[6.896544,47.653202],"type":"Point"}
}