{
  "type": "Feature",
  "properties": {
    "iso:country":"FR",
    "sg:address":"Zi Rue Du Ried BP 7 67610 Wantzenau (La)",
    "sg:city":"La Wantzenau",
    "sg:orig_category":"Miscellaneous Products",
    "sg:phone":"+33 3 88 59 20 00",
    "sg:postcode":"67610",
    "sg:province":"Alsace",
    "wof:name":"Bayer Elastomere",
    "wof:placetype":"venue"
},
  "geometry": {"coordinates":[7.802724,48.651554],"type":"Point"}
}