{
  "type": "Feature",
  "properties": {
    "iso:country":"FR",
    "sg:address":"1 Avenue De Dallas 21000 Dijon",
    "sg:city":"Dijon",
    "sg:classifiers":[
        {
            "category":"Food & Beverages",
            "subcategory":"Fruits & Vegetables",
            "type":"Retail Goods"
        }
    ],
    "sg:phone":"+33 3 80 73 04 00",
    "sg:postcode":"21000",
    "sg:province":"Bourgogne",
    "sg:tags":[
        "frozen",
        "product",
        "related"
    ],
    "wof:name":"Davigel Sa",
    "wof:placetype":"venue"
},
  "geometry": {"coordinates":[5.061019,47.337357],"type":"Point"}
}