{
  "type": "Feature",
  "properties": {
    "addr:full":"26, Rue EmileCombes, 33000 Bordeaux Bordeaux Aquitaine 33000",
    "addr:housenumber":"26",
    "addr:postcode":"33000;33000",
    "addr:street":"Rue Emilecombes",
    "iso:country":"FR",
    "sg:address":"26, Rue EmileCombes, 33000 Bordeaux",
    "sg:city":"Bordeaux",
    "sg:orig_category":"Unclassifiable Establishments",
    "sg:phone":"+33 5 56 92 41 57",
    "sg:postcode":"33000",
    "sg:province":"Aquitaine",
    "wof:name":"A.i.a. - Atelier Industriel A\u00e9ronautique",
    "wof:placetype":"venue"
},
  "geometry": {"coordinates":[-0.609019,44.836399],"type":"Point"}
}