{
  "type": "Feature",
  "properties": {
    "iso:country":"FR",
    "sg:address":"Ch\u00e2teau 37150 Chenonceaux",
    "sg:city":"Chenonceaux",
    "sg:orig_category":"Business travel Construction and Public Works Professional fairs Public works",
    "sg:phone":"+33 2 47 23 90 07",
    "sg:postcode":"37150",
    "sg:province":"Centre",
    "wof:name":"Chenonceau Expansion Sa",
    "wof:placetype":"venue"
},
  "geometry": {"coordinates":[1.049415,47.247349],"type":"Point"}
}