{
  "type": "Feature",
  "properties": {
    "addr:full":"Rte de Villeneuve Sainte Livrade sur Lot Aquitaine 47110",
    "addr:postcode":"47110",
    "addr:street":"Rte De Villeneuve Sainte Livrade",
    "iso:country":"FR",
    "sg:address":"Rte de Villeneuve",
    "sg:city":"Sainte Livrade sur Lot",
    "sg:orig_category":"Non-Classified Establishments",
    "sg:phone":"+33 5 53 01 02 12",
    "sg:postcode":"47110",
    "sg:province":"Aquitaine",
    "wof:name":"Antoine Espaces Verts S.a.r.l.",
    "wof:placetype":"venue"
},
  "geometry": {"coordinates":[0.612425,44.399807],"type":"Point"}
}