{
  "type": "Feature",
  "properties": {
    "addr:full":"14, Rue de Gatines, 41110 Seigy Seigy Centre 41110",
    "addr:housenumber":"14",
    "addr:postcode":"41110;41110",
    "addr:street":"Rue De Gatines",
    "iso:country":"FR",
    "sg:address":"14, Rue de Gatines, 41110 Seigy",
    "sg:city":"Seigy",
    "sg:orig_category":"Non-Classified Establishments",
    "sg:phone":"+33 2 54 75 26 01",
    "sg:postcode":"41110",
    "sg:province":"Centre",
    "wof:name":"Cl\u00e9ment Guy-d\u00e9cos",
    "wof:placetype":"venue"
},
  "geometry": {"coordinates":[1.389954,47.262455],"type":"Point"}
}