{
  "type": "Feature",
  "properties": {
    "addr:full":"69 Rue Georges Cl\u00e9menceau 41200 Romorantin Lanthenay Villefranche-sur-Cher Centre 41200",
    "addr:housenumber":"69",
    "addr:postcode":"41200;41200",
    "addr:street":"Rue Georges Cle\u0301Menceau",
    "iso:country":"FR",
    "sg:address":"69 Rue Georges Cl\u00e9menceau 41200 Romorantin Lanthenay",
    "sg:city":"Villefranche-sur-Cher",
    "sg:classifiers":[
        {
            "category":"Travel",
            "subcategory":"Hotels & Motels",
            "type":"Entertainment"
        }
    ],
    "sg:phone":"+33 2 54 94 15 15",
    "sg:postcode":"41200",
    "sg:province":"Centre",
    "sg:tags":[
        "hotels",
        "business",
        "restaurant"
    ],
    "wof:name":"Grand Hotel De Lion D'or Abcd Sarl",
    "wof:placetype":"venue"
},
  "geometry": {"coordinates":[1.74446,47.35955],"type":"Point"}
}