{
  "type": "Feature",
  "properties": {
    "addr:full":"113 Avenue Du Danemark 37100 Tours Tours Centre 37100",
    "addr:housenumber":"113",
    "addr:postcode":"37100;37100",
    "addr:street":"Avenue Du Danemark",
    "iso:country":"FR",
    "sg:address":"113 Avenue Du Danemark 37100 Tours",
    "sg:city":"Tours",
    "sg:classifiers":[
        {
            "category":"Shopping",
            "subcategory":"Computers & Home Electronics",
            "type":"Retail Goods"
        }
    ],
    "sg:phone":"+33 2 47 88 50 60",
    "sg:postcode":"37100",
    "sg:province":"Centre",
    "sg:tags":[
        "electric",
        "electricity",
        "component",
        "equipment",
        "electrical",
        "electronic"
    ],
    "wof:name":"Etudes Et Realisations Electriques De Touraine Eret (eret)",
    "wof:placetype":"venue"
},
  "geometry": {"coordinates":[0.67914,47.42981],"type":"Point"}
}