{
  "type": "Feature",
  "properties": {
    "addr:full":"23, Bd Am\u00e9lie Gex, 73100 Aix les Bains Rhone-Alpes 73100",
    "addr:housenumber":"23",
    "addr:postcode":"73100;73100",
    "addr:street":"Bd Ame\u0301Lie Gex",
    "iso:country":"FR",
    "sg:address":"23, Bd Am\u00e9lie Gex, 73100 Aix les Bains",
    "sg:orig_category":"Unclassifiable Establishments",
    "sg:phone":"+33 4 79 35 08 45",
    "sg:postcode":"73100",
    "sg:province":"Rhone-Alpes",
    "wof:name":"Datem",
    "wof:placetype":"venue"
},
  "geometry": {"coordinates":[5.902002,45.695518],"type":"Point"}
}