{
  "type": "Feature",
  "properties": {
    "addr:full":"56, Rue Amp\u00e8re, 13340 Rognac Poitou-Charentes",
    "addr:housenumber":"56",
    "addr:postcode":"13340",
    "addr:street":"Rue Ampe\u0300Re",
    "iso:country":"FR",
    "sg:address":"56, Rue Amp\u00e8re, 13340 Rognac",
    "sg:orig_category":"Non-Classified Establishments",
    "sg:phone":"+33 4 42 78 73 11",
    "sg:province":"Poitou-Charentes",
    "wof:name":"P.r.b. S.a. - Produits De Rev\u00eatement Du B\u00e2timent",
    "wof:placetype":"venue"
},
  "geometry": {"coordinates":[5.211924,43.499901],"type":"Point"}
}