{
  "type": "Feature",
  "properties": {
    "addr:full":"RUE DU VERT BOIS 59960 Neuville en Ferrain Nord Pas-de-Calais 59960",
    "addr:postcode":"59960;59960",
    "addr:street":"Rue Du Vert Bois",
    "iso:country":"FR",
    "sg:address":"RUE DU VERT BOIS 59960 Neuville en Ferrain",
    "sg:orig_category":"Advertising Articles, Magnetic",
    "sg:phone":"+33 3 20 28 40 00",
    "sg:postcode":"59960",
    "sg:province":"Nord Pas-de-Calais",
    "wof:name":"Aimants Goudsmit France Sarl",
    "wof:placetype":"venue"
},
  "geometry": {"coordinates":[3.169745,50.754875],"type":"Point"}
}