{
  "type": "Feature",
  "properties": {
    "addr:full":"Av Marcel Dassault Zone Induspal 64140 Lons Lons Aquitaine 64140",
    "addr:postcode":"64140;64140",
    "addr:street":"Av Marcel Dassault Zone Induspal",
    "iso:country":"FR",
    "sg:address":"Av Marcel Dassault Zone Induspal 64140 Lons",
    "sg:city":"Lons",
    "sg:classifiers":[
        {
            "category":"Food & Beverages",
            "subcategory":"Dairy",
            "type":"Retail Goods"
        }
    ],
    "sg:phone":"+33 5 59 72 19 19",
    "sg:postcode":"64140",
    "sg:province":"Aquitaine",
    "sg:tags":[
        "product",
        "related"
    ],
    "wof:name":"3a Sa",
    "wof:placetype":"venue"
},
  "geometry": {"coordinates":[-0.410374,43.301151],"type":"Point"}
}