{
  "type": "Feature",
  "properties": {
    "iso:country":"FR",
    "sg:address":"L'Etoile - Almont Les Juntes 12300 Almont Les Juntes",
    "sg:classifiers":[
        {
            "category":"Autos & Motor Vehicles",
            "subcategory":"Automobile Sales",
            "type":"Retail Goods"
        }
    ],
    "sg:phone":"+33 5 65 64 09 22",
    "sg:postcode":"12300",
    "sg:province":"Midi Pyr\u00e9n\u00e9es",
    "sg:tags":[
        "equipment",
        "industrial",
        "transport"
    ],
    "wof:name":"Rouergue Carrosserie Industrielle",
    "wof:placetype":"venue"
},
  "geometry": {"coordinates":[-85.08200100000001,38.088203],"type":"Point"}
}