{
  "type": "Feature",
  "properties": {
    "iso:country":"FR",
    "sg:address":"Zone Artisanale Pont Nord 61450 La Ferriere Aux Etangs",
    "sg:city":"Banvou",
    "sg:classifiers":[
        {
            "category":"Manufacturing",
            "subcategory":"Tools & Machinery",
            "type":"Manufacturing & Wholesale Goods"
        }
    ],
    "sg:phone":"+33 2 33 66 93 30",
    "sg:postcode":"61450",
    "sg:province":"Basse Normandie",
    "sg:tags":[
        "environment",
        "equipment",
        "-"
    ],
    "wof:name":"Etablissements Julien",
    "wof:placetype":"venue"
},
  "geometry": {"coordinates":[-0.519624,48.662193],"type":"Point"}
}