{
  "type": "Feature",
  "properties": {
    "addr:full":"Za De Troyalac Carte Postale 19 29563 Quimper Cedex 9 Quimper Bretagne 29000",
    "addr:housenumber":"19",
    "addr:postcode":"29563;29000",
    "addr:street":"Za De Troyalac;Postale",
    "iso:country":"FR",
    "sg:address":"Za De Troyalac Carte Postale 19 29563 Quimper Cedex 9",
    "sg:city":"Quimper",
    "sg:classifiers":[
        {
            "category":"Professional",
            "subcategory":"Engineering",
            "type":"Services"
        }
    ],
    "sg:phone":"+33 2 98 94 69 99",
    "sg:postcode":"29000",
    "sg:province":"Bretagne",
    "sg:tags":[
        "machine",
        "-",
        "mechanical"
    ],
    "wof:name":"Emballages Technologies",
    "wof:placetype":"venue"
},
  "geometry": {"coordinates":[-4.110034,47.988216],"type":"Point"}
}