{
  "type": "Feature",
  "properties": {
    "iso:country":"FR",
    "sg:address":"3, Rue Chapelle du Bel Air, 69340 Francheville",
    "sg:orig_category":"Unclassifiable Establishments",
    "sg:phone":"+33 4 72 40 03 20",
    "sg:province":"Rhone-Alpes",
    "wof:name":"H.t.f. Industrie S.a.r.l. - Hitech France",
    "wof:placetype":"venue"
},
  "geometry": {"coordinates":[4.756724,45.746559],"type":"Point"}
}