{
  "type": "Feature",
  "properties": {
    "addr:full":"B.P. 80, 38353 La Tour du Pin C\u00e9dex^^ZI Saint Jean de Soudain, 38110 La Tour du Pin Rhone-Alpes 38110",
    "addr:housenumber":"38353;38110",
    "addr:postcode":"38110",
    "addr:street":"B.P. 80;Saint",
    "iso:country":"FR",
    "sg:address":"B.P. 80, 38353 La Tour du Pin C\u00e9dex^^ZI Saint Jean de Soudain, 38110 La Tour du Pin",
    "sg:orig_category":"Non-Classified Establishments",
    "sg:phone":"+33 4 74 97 23 55",
    "sg:postcode":"38110",
    "sg:province":"Rhone-Alpes",
    "wof:name":"S\u00e9far Fyltis S.a.",
    "wof:placetype":"venue"
},
  "geometry": {"coordinates":[5.454585,45.52478],"type":"Point"}
}