{
  "type": "Feature",
  "properties": {
    "addr:full":"Rue Des Famards Centre De Gros 59810 Lesquin Nord Pas-de-Calais 59810",
    "addr:postcode":"59810;59810",
    "addr:street":"Rue Des Famards",
    "iso:country":"FR",
    "sg:address":"Rue Des Famards Centre De Gros 59810 Lesquin",
    "sg:classifiers":[
        {
            "category":"Manufacturing",
            "subcategory":"Textiles",
            "type":"Manufacturing & Wholesale Goods"
        }
    ],
    "sg:phone":"+33 3 20 96 58 70",
    "sg:postcode":"59810",
    "sg:province":"Nord Pas-de-Calais",
    "sg:tags":[
        "linen",
        "clothing",
        "fabric"
    ],
    "wof:name":"Ftm",
    "wof:placetype":"venue"
},
  "geometry": {"coordinates":[3.11003,50.588009],"type":"Point"}
}