{
  "type": "Feature",
  "properties": {
    "addr:full":"42, Rue de la Gare, 62300 Lens Nord Pas-de-Calais 62300",
    "addr:housenumber":"42",
    "addr:postcode":"62300;62300",
    "addr:street":"Rue De La Gare",
    "iso:country":"FR",
    "sg:address":"42, Rue de la Gare, 62300 Lens",
    "sg:orig_category":"Non-Classified Establishments",
    "sg:phone":"+33 3 21 67 65 65",
    "sg:postcode":"62300",
    "sg:province":"Nord Pas-de-Calais",
    "wof:name":"C.r.i.t. Int\u00e9rim, S.a.",
    "wof:placetype":"venue"
},
  "geometry": {"coordinates":[2.830912,50.427601],"type":"Point"}
}