{
  "type": "Feature",
  "properties": {
    "addr:full":"99, Rue Louis Poterat, 76100 Rouen Haute Normandie",
    "addr:housenumber":"99",
    "addr:postcode":"76100",
    "addr:street":"Rue Louis Poterat;Haute Normandie",
    "iso:country":"FR",
    "sg:address":"99, Rue Louis Poterat, 76100 Rouen",
    "sg:orig_category":"Unclassifiable Establishments",
    "sg:phone":"+33 2 35 58 46 46",
    "sg:province":"Haute Normandie",
    "wof:name":"Groupe Normand D'electricite S.a.",
    "wof:placetype":"venue"
},
  "geometry": {"coordinates":[1.071334,49.428268],"type":"Point"}
}