{
  "type": "Feature",
  "properties": {
    "addr:full":"3, Rue du Vert Bois - Zone Industrielle, 59535 Neuville en Ferrain C\u00e9dex Vill\u00e9 Alsace 67220",
    "addr:housenumber":"3",
    "addr:postcode":"59535;67220",
    "addr:street":"Rue Du Vert Bois Zone Industrielle",
    "iso:country":"FR",
    "sg:address":"3, Rue du Vert Bois - Zone Industrielle, 59535 Neuville en Ferrain C\u00e9dex",
    "sg:city":"Vill\u00e9",
    "sg:orig_category":"Non-Classified Establishments",
    "sg:phone":"+33 3 20 28 40 00",
    "sg:postcode":"67220",
    "sg:province":"Alsace",
    "wof:name":"Aimants Goudsmit France S.a.r.l.",
    "wof:placetype":"venue"
},
  "geometry": {"coordinates":[-109.21843,48.033401],"type":"Point"}
}