{
  "type": "Feature",
  "properties": {
    "iso:country":"FR",
    "sg:address":"13 Avenue Victor Hugo Espace Victor Hugo 69160 Tassin La Demi Lune",
    "sg:classifiers":[
        {
            "category":"Utilities",
            "type":"Services"
        }
    ],
    "sg:phone":"+33 4 72 53 28 00",
    "sg:postcode":"69160",
    "sg:province":"Rhone-Alpes",
    "sg:tags":[
        "raw",
        "energy",
        "material"
    ],
    "wof:name":"Societe D'amenagement Urbain Et Rural (saur)",
    "wof:placetype":"venue"
},
  "geometry": {"coordinates":[4.78198,45.76403],"type":"Point"}
}