{
  "type": "Feature",
  "properties": {
    "addr:full":"25 Av Colbert 89250 Seignelay Seignelay Bourgogne 89250",
    "addr:postcode":"89250;89250",
    "addr:street":"25 Av Colbert",
    "iso:country":"FR",
    "sg:address":"25 Av Colbert 89250 Seignelay",
    "sg:city":"Seignelay",
    "sg:classifiers":[
        {
            "category":"Manufacturing",
            "subcategory":"Metals",
            "type":"Manufacturing & Wholesale Goods"
        }
    ],
    "sg:phone":"+33 3 86 47 90 74",
    "sg:postcode":"89250",
    "sg:province":"Bourgogne",
    "sg:tags":[
        "-",
        "machine",
        "equipment",
        "engineering",
        "machinery",
        "mechanical"
    ],
    "wof:name":"Laureseb",
    "wof:placetype":"venue"
},
  "geometry": {"coordinates":[3.600786,47.907486],"type":"Point"}
}