{
  "type": "Feature",
  "properties": {
    "addr:full":"R Jean Etienne Montgolfier 11000 Carcassonne Languedoc-Roussillon 11000",
    "addr:postcode":"11000;11000",
    "addr:street":"R;Montgolfier",
    "iso:country":"FR",
    "sg:address":"R Jean Etienne Montgolfier 11000 Carcassonne",
    "sg:classifiers":[
        {
            "category":"Wholesale",
            "subcategory":"Farm Supplies",
            "type":"Manufacturing & Wholesale Goods"
        }
    ],
    "sg:phone":"+33 4 68 11 74 00",
    "sg:postcode":"11000",
    "sg:province":"Languedoc-Roussillon",
    "sg:tags":[
        "-",
        "machine",
        "equipment",
        "engineering",
        "machinery",
        "mechanical",
        "agriculture"
    ],
    "wof:name":"Jean De Bru Sa",
    "wof:placetype":"venue"
},
  "geometry": {"coordinates":[2.331775,43.214378],"type":"Point"}
}