{
  "type": "Feature",
  "properties": {
    "addr:full":"27 Boulevard Des Alpes Meylan Rhone-Alpes 38240",
    "addr:housenumber":"27",
    "addr:postcode":"38240",
    "addr:street":"Boulevard Des Alpes;Rhone-Alpes",
    "iso:country":"FR",
    "sg:address":"27 Boulevard Des Alpes",
    "sg:city":"Meylan",
    "sg:classifiers":[
        {
            "category":"Banks & Credit Unions",
            "subcategory":"Financial Services",
            "type":"Services"
        }
    ],
    "sg:phone":"+33 4 76 90 14 27",
    "sg:postcode":"38240",
    "sg:province":"Rhone-Alpes",
    "sg:tags":[
        "banking",
        "finance",
        "insurance"
    ],
    "wof:name":"Scp Louvat Torre Vincent Cach Chevalier",
    "wof:placetype":"venue"
},
  "geometry": {"coordinates":[5.770948,45.203781],"type":"Point"}
}