{
  "type": "Feature",
  "properties": {
    "iso:country":"FR",
    "sg:address":"Les N\u00e9gadis",
    "sg:city":"Draguignan",
    "sg:classifiers":[
        {
            "category":"Banks & Credit Unions",
            "subcategory":"Financial Services",
            "type":"Services"
        }
    ],
    "sg:phone":"+33 4 94 84 40 40",
    "sg:postcode":"83000",
    "sg:province":"Provence-Alpes-C\u00f4te d'Azur",
    "sg:tags":[
        "banking",
        "finance",
        "insurance"
    ],
    "wof:name":"Credit Agricole",
    "wof:placetype":"venue"
},
  "geometry": {"coordinates":[6.480915,43.529552],"type":"Point"}
}