{
  "type": "Feature",
  "properties": {
    "addr:full":"25 Bd De L'Industrie 85000 La Roche Sur Yon Pays de Loire 85000",
    "addr:housenumber":"25",
    "addr:postcode":"85000;85000",
    "addr:street":"Bd De L'Industrie;Roche;Yon",
    "iso:country":"FR",
    "sg:address":"25 Bd De L'Industrie 85000 La Roche Sur Yon",
    "sg:classifiers":[
        {
            "category":"Food Court",
            "type":"Food & Drink"
        }
    ],
    "sg:phone":"+33 2 51 62 03 73",
    "sg:postcode":"85000",
    "sg:province":"Pays de Loire",
    "sg:tags":[
        "product",
        "related"
    ],
    "wof:name":"Sofabo (ste De Fabrication De Boissons)",
    "wof:placetype":"venue"
},
  "geometry": {"coordinates":[-1.439341,46.655621],"type":"Point"}
}