{
  "type": "Feature",
  "properties": {
    "addr:full":"Rue du Vertuquet - ZI Neuville en Ferrain Nord Pas-de-Calais 59960",
    "addr:postcode":"59960",
    "addr:street":"Rue Du Vertuquet Zi Neuville En Ferrain Nord",
    "iso:country":"FR",
    "sg:address":"Rue du Vertuquet - ZI",
    "sg:city":"Neuville en Ferrain",
    "sg:orig_category":"Unclassifiable Establishments",
    "sg:phone":"+33 3 20 94 10 32",
    "sg:postcode":"59960",
    "sg:province":"Nord Pas-de-Calais",
    "wof:name":"Soliver France S.a.",
    "wof:placetype":"venue"
},
  "geometry": {"coordinates":[3.15239,50.750355],"type":"Point"}
}