{
  "type": "Feature",
  "properties": {
    "iso:country":"FR",
    "sg:address":"76, Rue de Stalingrad, 38000 Grenoble",
    "sg:orig_category":"Unclassifiable Establishments",
    "sg:phone":"+33 4 76 47 92 54",
    "sg:postcode":"38000",
    "sg:province":"Rhone-Alpes",
    "wof:name":"Grenoble Entretien S.a.",
    "wof:placetype":"venue"
},
  "geometry": {"coordinates":[5.725803,45.175533],"type":"Point"}
}