{
  "type": "Feature",
  "properties": {
    "addr:full":"76, Rue de Stalingrad, 38000 Grenoble Rhone-Alpes 38000",
    "addr:housenumber":"76",
    "addr:postcode":"38000;38000",
    "addr:street":"Rue De Stalingrad",
    "iso:country":"FR",
    "sg:address":"76, Rue de Stalingrad, 38000 Grenoble",
    "sg:orig_category":"Unclassifiable Establishments",
    "sg:phone":"+33 4 76 47 92 54",
    "sg:postcode":"38000",
    "sg:province":"Rhone-Alpes",
    "wof:name":"Grenoble Entretien S.a.",
    "wof:placetype":"venue"
},
  "geometry": {"coordinates":[5.725803,45.175533],"type":"Point"}
}