{
  "type": "Feature",
  "properties": {
    "addr:full":"46 Rue Pierre Charron 75008 Paris Ile de France 75008",
    "addr:housenumber":"46",
    "addr:postcode":"75008;75008",
    "addr:street":"Rue Pierre Charron",
    "iso:country":"FR",
    "sg:address":"46 Rue Pierre Charron 75008 Paris",
    "sg:classifiers":[
        {
            "category":"Professional",
            "subcategory":"Business Services",
            "type":"Services"
        }
    ],
    "sg:phone":"+33 1 56 62 22 00",
    "sg:postcode":"75008",
    "sg:province":"Ile de France",
    "sg:tags":[
        "body",
        "advice"
    ],
    "wof:name":"Ambassade D'estonie",
    "wof:placetype":"venue"
},
  "geometry": {"coordinates":[2.301668,48.868568],"type":"Point"}
}