{
  "type": "Feature",
  "properties": {
    "addr:full":"Zone Industrielle Chemaudin Franche Comt\u00e9 25320",
    "addr:postcode":"25320",
    "addr:street":"Zone Industrielle;Franche Comte\u0301",
    "iso:country":"FR",
    "sg:address":"Zone Industrielle",
    "sg:city":"Chemaudin",
    "sg:orig_category":"Non-Classified Establishments",
    "sg:phone":"+33 3 81 58 45 45",
    "sg:postcode":"25320",
    "sg:province":"Franche Comt\u00e9",
    "wof:name":"Perez S.a.r.l.",
    "wof:placetype":"venue"
},
  "geometry": {"coordinates":[5.891367,47.223965],"type":"Point"}
}