{
  "type": "Feature",
  "properties": {
    "addr:full":"22 rue du Canal 30800 ST GILLES Languedoc-Roussillon 30800",
    "addr:housenumber":"22",
    "addr:postcode":"30800;30800",
    "addr:street":"Rue Du Canal;St Gilles",
    "iso:country":"FR",
    "sg:address":"22 rue du Canal 30800 ST GILLES",
    "sg:orig_category":"Non-Classified Establishments",
    "sg:phone":"+33 4 66 87 31 15",
    "sg:postcode":"30800",
    "sg:province":"Languedoc-Roussillon",
    "wof:name":"Et. Perret Et Fils Sarl",
    "wof:placetype":"venue"
},
  "geometry": {"coordinates":[4.433972,43.672829],"type":"Point"}
}