{
  "type": "Feature",
  "properties": {
    "iso:country":"FR",
    "sg:address":"Zi Du Terra 53100 Mayenne",
    "sg:classifiers":[
        {
            "category":"Bars & Pubs",
            "subcategory":"Gay Bar",
            "type":"Food & Drink"
        }
    ],
    "sg:phone":"+33 2 43 04 12 25",
    "sg:postcode":"53100",
    "sg:province":"Pays de Loire",
    "sg:tags":[
        "product",
        "livestock",
        "cereal",
        "related",
        "grain",
        "animal",
        "breeding",
        "agriculture"
    ],
    "wof:name":"Agrial Cooperative",
    "wof:placetype":"venue"
},
  "geometry": {"coordinates":[-0.617214,48.305771],"type":"Point"}
}