{
  "type": "Feature",
  "properties": {
    "addr:full":"520 Rue Robert Amy 49400 Saumur Pays de Loire",
    "addr:housenumber":"520",
    "addr:postcode":"49400",
    "addr:street":"Rue Robert Amy",
    "iso:country":"FR",
    "sg:address":"520 Rue Robert Amy 49400 Saumur",
    "sg:classifiers":[
        {
            "category":"Professional",
            "type":"Services"
        }
    ],
    "sg:phone":"+33 2 41 67 83 94",
    "sg:province":"Pays de Loire",
    "sg:tags":[
        "transport",
        "road"
    ],
    "wof:name":"Ogf",
    "wof:placetype":"venue"
},
  "geometry": {"coordinates":[-0.075454,47.245846],"type":"Point"}
}