{
  "type": "Feature",
  "properties": {
    "addr:full":"B.P. 245, 69515 Vaulx en Velin C\u00e9dex^^15, Rue L\u00e9onard de Vinci - ZI Est, 69120 Vaulx en Velin Rhone-Alpes 69120",
    "addr:housenumber":"b.p. 245",
    "addr:postcode":"69515;69120;69120",
    "addr:street":"Rue Le\u0301Onard De Vinci Zi Est",
    "iso:country":"FR",
    "sg:address":"B.P. 245, 69515 Vaulx en Velin C\u00e9dex^^15, Rue L\u00e9onard de Vinci - ZI Est, 69120 Vaulx en Velin",
    "sg:orig_category":"Non-Classified Establishments",
    "sg:phone":"+33 4 78 79 57 40",
    "sg:postcode":"69120",
    "sg:province":"Rhone-Alpes",
    "wof:name":"Etablissement R. Prat S.a.",
    "wof:placetype":"venue"
},
  "geometry": {"coordinates":[4.916895,45.779022],"type":"Point"}
}