{
  "type": "Feature",
  "properties": {
    "iso:country":"FR",
    "sg:address":"B.P. 84, 83003 Draguignan C\u00e9dex^^743, Bd Saint Exup\u00e9ry - ZA Saint Hermentaire, 83300 Draguignan",
    "sg:orig_category":"Non-Classified Establishments",
    "sg:phone":"+33 4 94 50 99 10",
    "sg:province":"Champagne",
    "wof:name":"Elie Laugier S.a.",
    "wof:placetype":"venue"
},
  "geometry": {"coordinates":[6.463645,43.539795],"type":"Point"}
}