{
  "type": "Feature",
  "properties": {
    "addr:full":"Village D'Entreprises, Bat Q, Parc Tertiaire De Valgora 83160 La Valette Provence-Alpes-C\u00f4te d'Azur",
    "addr:postcode":"83160",
    "addr:street":"Valette",
    "iso:country":"FR",
    "sg:address":"Village D'Entreprises, Bat Q, Parc Tertiaire De Valgora 83160 La Valette",
    "sg:classifiers":[
        {
            "category":"Wholesale",
            "subcategory":"Machinery & Supplies",
            "type":"Manufacturing & Wholesale Goods"
        }
    ],
    "sg:phone":"+33 4 98 01 37 10",
    "sg:province":"Provence-Alpes-C\u00f4te d'Azur",
    "sg:tags":[
        "equipment",
        "precision"
    ],
    "wof:name":"Axians",
    "wof:placetype":"venue"
},
  "geometry": {"coordinates":[5.98935,43.148201],"type":"Point"}
}