{
  "type": "Feature",
  "properties": {
    "addr:full":"Rue des Puits Semmadon Franche Comt\u00e9 70120",
    "addr:postcode":"70120",
    "addr:street":"Rue Des Puits Semmadon Franche Comte\u0301",
    "iso:country":"FR",
    "sg:address":"Rue des Puits",
    "sg:city":"Semmadon",
    "sg:orig_category":"Unclassifiable Establishments",
    "sg:phone":"+33 3 84 92 10 92",
    "sg:postcode":"70120",
    "sg:province":"Franche Comt\u00e9",
    "wof:name":"Chapoy S.a.",
    "wof:placetype":"venue"
},
  "geometry": {"coordinates":[5.873532,47.741344],"type":"Point"}
}