{
  "type": "Feature",
  "properties": {
    "addr:full":"99, Rte du Ch\u00eane, 72230 Arnage Pays de Loire",
    "addr:housenumber":"99",
    "addr:postcode":"72230",
    "addr:street":"Rte Du Che\u0302Ne",
    "iso:country":"FR",
    "sg:address":"99, Rte du Ch\u00eane, 72230 Arnage",
    "sg:orig_category":"Non-Classified Establishments",
    "sg:phone":"+33 2 43 21 65 45",
    "sg:province":"Pays de Loire",
    "wof:name":"F.b.s. S.a. - Fa\u00e7onnage Brossage De La Sarthe",
    "wof:placetype":"venue"
},
  "geometry": {"coordinates":[0.190877,47.940201],"type":"Point"}
}