{
  "type": "Feature",
  "properties": {
    "addr:full":"2 ave Gabriel Peri; Paris; 75382 Bretagne",
    "addr:postcode":"75382",
    "addr:street":"2 Ave Gabriel Peri Paris",
    "iso:country":"FR",
    "sg:address":"2 ave Gabriel Peri; Paris; 75382",
    "sg:classifiers":[
        {
            "category":"Banks & Credit Unions",
            "subcategory":"Bank",
            "type":"Services"
        }
    ],
    "sg:phone":"+33 1 47 42 37 22",
    "sg:province":"Bretagne",
    "wof:name":"The Riggs National, Bank (europe) Sa",
    "wof:placetype":"venue"
},
  "geometry": {"coordinates":[2.3111,48.873241],"type":"Point"}
}