{
  "type": "Feature",
  "properties": {
    "addr:full":"76, All\u00e9e Jean Jaur\u00e8s, 31071 Toulouse C\u00e9dex 7 Champagne",
    "addr:housenumber":"76;7",
    "addr:postcode":"31071",
    "addr:street":"Alle\u0301E Jean Jaure\u0300S",
    "iso:country":"FR",
    "sg:address":"76, All\u00e9e Jean Jaur\u00e8s, 31071 Toulouse C\u00e9dex 7",
    "sg:orig_category":"Non-Classified Establishments",
    "sg:phone":"+33 5 61 62 04 36",
    "sg:province":"Champagne",
    "wof:name":"Auditek S.a.r.l.",
    "wof:placetype":"venue"
},
  "geometry": {"coordinates":[1.452848,43.60812],"type":"Point"}
}