{
  "type": "Feature",
  "properties": {
    "iso:country":"FR",
    "sg:address":"Rte de Pierrefonds",
    "sg:city":"Cr\u00e9py en Valois",
    "sg:orig_category":"Unclassifiable Establishments",
    "sg:phone":"+33 3 44 59 14 86",
    "sg:postcode":"60800",
    "sg:province":"Picardie",
    "wof:name":"Alliance Environnement S.a.",
    "wof:placetype":"venue"
},
  "geometry": {"coordinates":[2.89532,49.241051],"type":"Point"}
}