{
  "type": "Feature",
  "properties": {
    "addr:full":"ZAC des Moulineaux Virazeil Aquitaine 47200",
    "addr:housenumber":"zac",
    "addr:postcode":"47200",
    "addr:street":"Des Moulineaux",
    "iso:country":"FR",
    "sg:address":"ZAC des Moulineaux",
    "sg:city":"Virazeil",
    "sg:orig_category":"Unclassifiable Establishments",
    "sg:phone":"+33 5 53 20 12 42",
    "sg:postcode":"47200",
    "sg:province":"Aquitaine",
    "wof:name":"D.d.s. Distribution S.a.r.l.",
    "wof:placetype":"venue"
},
  "geometry": {"coordinates":[0.217694,44.505688],"type":"Point"}
}