{
  "type": "Feature",
  "properties": {
    "iso:country":"FR",
    "sg:address":"6 Rue Prosper Faugere",
    "sg:city":"Bergerac",
    "sg:classifiers":[
        {
            "category":"Banks & Credit Unions",
            "subcategory":"Financial Services",
            "type":"Services"
        }
    ],
    "sg:phone":"+33 5 53 74 52 74",
    "sg:postcode":"24100",
    "sg:province":"Aquitaine",
    "sg:tags":[
        "banking",
        "finance",
        "insurance"
    ],
    "wof:name":"Ardial Fiduciaire Sa",
    "wof:placetype":"venue"
},
  "geometry": {"coordinates":[0.487838,44.850643],"type":"Point"}
}