{
  "type": "Feature",
  "properties": {
    "iso:country":"FR",
    "sg:address":"14 Rue B\u00e9ranger 11100 Narbonne",
    "sg:classifiers":[
        {
            "category":"Utilities",
            "type":"Services"
        }
    ],
    "sg:phone":"+33 4 68 32 87 10",
    "sg:postcode":"11100",
    "sg:province":"Languedoc-Roussillon",
    "sg:tags":[
        "raw",
        "energy",
        "material"
    ],
    "wof:name":"Generale Des Eaux",
    "wof:placetype":"venue"
},
  "geometry": {"coordinates":[3.01061,43.189499],"type":"Point"}
}