{
  "type": "Feature",
  "properties": {
    "iso:country":"FR",
    "sg:address":"Rte Chalbatenia 64250 Soura\u00eede",
    "sg:city":"Soura\u00efde",
    "sg:classifiers":[
        {
            "category":"Food & Beverages",
            "subcategory":"Meat & Fish",
            "type":"Retail Goods"
        }
    ],
    "sg:phone":"+33 5 59 93 90 30",
    "sg:postcode":"64250",
    "sg:province":"Aquitaine",
    "sg:tags":[
        "preserve",
        "cooked",
        "product",
        "related"
    ],
    "wof:name":"Ste D'exploitation Pascal Massonde",
    "wof:placetype":"venue"
},
  "geometry": {"coordinates":[-1.503206,43.293476],"type":"Point"}
}