{
  "type": "Feature",
  "properties": {
    "iso:country":"FR",
    "sg:address":"33, Rue des Morillons - ZAC des Doucettes, 95140 Garges l\u00e8s Gonesse",
    "sg:orig_category":"Unclassifiable Establishments",
    "sg:phone":"+33 1 39 93 15 55",
    "sg:province":"Ile de France",
    "wof:name":"Matransaf S.a.",
    "wof:placetype":"venue"
},
  "geometry": {"coordinates":[2.39924,48.970955],"type":"Point"}
}