{
  "type": "Feature",
  "properties": {
    "iso:country":"FR",
    "sg:address":"Ccal Bretagnia 29600 St Martin Des Champs",
    "sg:city":"Morlaix",
    "sg:classifiers":[
        {
            "category":"Travel",
            "subcategory":"Hotels & Motels",
            "type":"Entertainment"
        }
    ],
    "sg:phone":"+33 2 98 63 27 99",
    "sg:postcode":"29600",
    "sg:province":"Bretagne",
    "sg:tags":[
        "hotels",
        "business",
        "restaurant"
    ],
    "wof:name":"Ste D'exploitation Commerciale Le Moulin",
    "wof:placetype":"venue"
},
  "geometry": {"coordinates":[-3.790329,48.535446],"type":"Point"}
}