{
  "type": "Feature",
  "properties": {
    "iso:country":"FR",
    "sg:address":"Rte Du Mans 53960 Bonchamp Les Laval",
    "sg:classifiers":[
        {
            "category":"Professional",
            "type":"Services"
        }
    ],
    "sg:phone":"+33 2 43 59 71 20",
    "sg:province":"Pays de Loire",
    "sg:tags":[
        "transport",
        "road"
    ],
    "wof:name":"Deniau Transports Sa",
    "wof:placetype":"venue"
},
  "geometry": {"coordinates":[-0.698759,48.070309],"type":"Point"}
}