{
  "type": "Feature",
  "properties": {
    "addr:full":"1 Pl Du Ch\u00e2teau 16200 Jarnac Poitou-Charentes 16200",
    "addr:housenumber":"1",
    "addr:postcode":"16200;16200",
    "addr:street":"Pl Du Cha\u0302Teau",
    "iso:country":"FR",
    "sg:address":"1 Pl Du Ch\u00e2teau 16200 Jarnac",
    "sg:classifiers":[
        {
            "category":"Banks & Credit Unions",
            "subcategory":"Financial Services",
            "type":"Services"
        }
    ],
    "sg:phone":"+33 5 45 81 16 61",
    "sg:postcode":"16200",
    "sg:province":"Poitou-Charentes",
    "sg:tags":[
        "banking",
        "insurance",
        "institution",
        "finance"
    ],
    "wof:name":"Credit Lyonnais",
    "wof:placetype":"venue"
},
  "geometry": {"coordinates":[-0.17431,45.679321],"type":"Point"}
}