{
  "type": "Feature",
  "properties": {
    "iso:country":"FR",
    "sg:address":"52 blvd Ren\u00e9 Cassin; Nice",
    "sg:classifiers":[
        {
            "category":"Banks & Credit Unions",
            "subcategory":"Bank",
            "type":"Services"
        }
    ],
    "sg:phone":"+33 3393831827",
    "sg:province":"Pays de Loire",
    "wof:name":"Soci\u00e9t\u00e9 G\u00e9n\u00e9rale, Agence Nice St Augustin",
    "wof:placetype":"venue"
},
  "geometry": {"coordinates":[-122.8386,39.121292],"type":"Point"}
}