{
  "type": "Feature",
  "properties": {
    "addr:full":"B.P. 70304, 22203 Guingamp C\u00e9dex^^20, Rte de Kerbost - Z.I. de Gr\u00e2ces, 22200 Guingamp Guingamp Bretagne 22200",
    "addr:postcode":"22203;22200;guingamp;22200",
    "addr:street":"Rte De Kerbost Z.I. De Gra\u0302Ces",
    "iso:country":"FR",
    "sg:address":"B.P. 70304, 22203 Guingamp C\u00e9dex^^20, Rte de Kerbost - Z.I. de Gr\u00e2ces, 22200 Guingamp",
    "sg:city":"Guingamp",
    "sg:orig_category":"Non-Classified Establishments",
    "sg:phone":"+33 2 96 43 81 93",
    "sg:postcode":"22200",
    "sg:province":"Bretagne",
    "wof:name":"Unicopa - Union R\u00e9gionale De Coop\u00e9rative Agricole",
    "wof:placetype":"venue"
},
  "geometry": {"coordinates":[-3.240289,48.517059],"type":"Point"}
}