{
  "type": "Feature",
  "properties": {
    "addr:full":"4 Place De La Republique St Leonard De Noblat Limousin 87400",
    "addr:housenumber":"4",
    "addr:postcode":"87400",
    "addr:street":"Place De La Republique St",
    "iso:country":"FR",
    "sg:address":"4 Place De La Republique",
    "sg:city":"St Leonard De Noblat",
    "sg:classifiers":[
        {
            "category":"Banks & Credit Unions",
            "subcategory":"Financial Services",
            "type":"Services"
        }
    ],
    "sg:phone":"+33 5 55 56 14 98",
    "sg:postcode":"87400",
    "sg:province":"Limousin",
    "sg:tags":[
        "banking",
        "finance",
        "insurance"
    ],
    "wof:name":"Societe Fiduciaire Nationale D'expertise Comptable Fidexpert (fid)",
    "wof:placetype":"venue"
},
  "geometry": {"coordinates":[1.49033,45.83799],"type":"Point"}
}