{
  "type": "Feature",
  "properties": {
    "addr:full":"53bis, Rue Marcel Henaux, 59700 Marcq en Baroeul Nord Pas-de-Calais",
    "addr:housenumber":"53bis",
    "addr:postcode":"59700",
    "addr:street":"Rue Marcel Henaux;En Baroeul Nord",
    "iso:country":"FR",
    "sg:address":"53bis, Rue Marcel Henaux, 59700 Marcq en Baroeul",
    "sg:orig_category":"Unclassifiable Establishments",
    "sg:phone":"+33 3 20 06 92 93",
    "sg:province":"Nord Pas-de-Calais",
    "wof:name":"Devred Gayet S.a.r.l.",
    "wof:placetype":"venue"
},
  "geometry": {"coordinates":[3.092797,50.651054],"type":"Point"}
}