{
  "type": "Feature",
  "properties": {
    "iso:country":"FR",
    "sg:address":"Le Moulin Neuf 23700 Rougnat",
    "sg:orig_category":"Non-Classified Establishments",
    "sg:phone":"+33 5 55 67 06 04",
    "sg:province":"Limousin",
    "wof:name":"Filature Fonty S.a.r.l.",
    "wof:placetype":"venue"
},
  "geometry": {"coordinates":[2.517765,46.041912],"type":"Point"}
}