{
  "type": "Feature",
  "properties": {
    "addr:full":"Rue D'Hesdin 62270 Fr\u00e9vent Nord Pas-de-Calais",
    "addr:postcode":"62270",
    "addr:street":"Rue D'Hesdin",
    "iso:country":"FR",
    "sg:address":"Rue D'Hesdin 62270 Fr\u00e9vent",
    "sg:classifiers":[
        {
            "category":"Manufacturing",
            "subcategory":"Rubber & Plastics",
            "type":"Manufacturing & Wholesale Goods"
        }
    ],
    "sg:phone":"+33 3 21 41 20 98",
    "sg:province":"Nord Pas-de-Calais",
    "wof:name":"Artea",
    "wof:placetype":"venue"
},
  "geometry": {"coordinates":[2.200542,50.301666],"type":"Point"}
}