{
  "type": "Feature",
  "properties": {
    "addr:full":"Za De La Croix Des Hormes 69250 Montanay Rhone-Alpes 69250",
    "addr:postcode":"69250;69250",
    "addr:street":"Za De La Croix Des Hormes;Rhone-Alpes",
    "iso:country":"FR",
    "sg:address":"Za De La Croix Des Hormes 69250 Montanay",
    "sg:classifiers":[
        {
            "category":"Shopping",
            "type":"Retail Goods"
        }
    ],
    "sg:phone":"+33 4 72 08 23 40",
    "sg:postcode":"69250",
    "sg:province":"Rhone-Alpes",
    "sg:tags":[
        "metallurgy",
        "finished",
        "-",
        "metalworking",
        "metallic"
    ],
    "wof:name":"Eurosanit Sa",
    "wof:placetype":"venue"
},
  "geometry": {"coordinates":[4.85812,45.879227],"type":"Point"}
}