{
  "type": "Feature",
  "properties": {
    "addr:full":"25-27 R De Clichy 93584 St Ouen Ile de France",
    "addr:housenumber":"25-27",
    "addr:postcode":"93584",
    "addr:street":"R De Clichy;St;Ile De France",
    "iso:country":"FR",
    "sg:address":"25-27 R De Clichy 93584 St Ouen",
    "sg:classifiers":[
        {
            "category":"Food & Beverages",
            "subcategory":"Dairy",
            "type":"Retail Goods"
        }
    ],
    "sg:phone":"+33 1 49 48 19 48",
    "sg:province":"Ile de France",
    "sg:tags":[
        "product",
        "related"
    ],
    "wof:name":"Sadipal Distribution Sa",
    "wof:placetype":"venue"
},
  "geometry": {"coordinates":[1.63802,48.607769],"type":"Point"}
}