{
  "type": "Feature",
  "properties": {
    "addr:full":"27-31 Rue Auguste Comte 87020 Limoges Limoges Limousin 87280",
    "addr:housenumber":"27-31",
    "addr:postcode":"87020;87280",
    "addr:street":"Rue Auguste Comte",
    "iso:country":"FR",
    "sg:address":"27-31 Rue Auguste Comte 87020 Limoges",
    "sg:city":"Limoges",
    "sg:orig_category":"Engines and parts Mechanical Engineering - machines Metallurgy and Metalworking Plastics Rubber and ",
    "sg:phone":"+33 5 55 38 95 70",
    "sg:postcode":"87280",
    "sg:province":"Limousin",
    "wof:name":"Kdi Beraud Sudreau",
    "wof:placetype":"venue"
},
  "geometry": {"coordinates":[1.27309,45.876759],"type":"Point"}
}