{
  "type": "Feature",
  "properties": {
    "iso:country":"FR",
    "sg:address":"17, Cours Alsace Lorraine, 31460 Caraman",
    "sg:orig_category":"Non-Classified Establishments",
    "sg:phone":"+33 5 62 18 81 18",
    "sg:postcode":"31460",
    "sg:province":"Midi Pyr\u00e9n\u00e9es",
    "wof:name":"Catac",
    "wof:placetype":"venue"
},
  "geometry": {"coordinates":[1.757103,43.53075],"type":"Point"}
}