{
  "type": "Feature",
  "properties": {
    "addr:full":"14 Rue Henri Chalamet 26000 Valence Rhone-Alpes 26000",
    "addr:housenumber":"14",
    "addr:postcode":"26000;26000",
    "addr:street":"Rue Henri Chalamet",
    "iso:country":"FR",
    "sg:address":"14 Rue Henri Chalamet 26000 Valence",
    "sg:classifiers":[
        {
            "category":"Professional",
            "subcategory":"Business Services",
            "type":"Services"
        }
    ],
    "sg:phone":"+33 4 75 78 15 60",
    "sg:postcode":"26000",
    "sg:province":"Rhone-Alpes",
    "sg:tags":[
        "training",
        "advice"
    ],
    "wof:name":"College Prive Sainte Anne",
    "wof:placetype":"venue"
},
  "geometry": {"coordinates":[4.89346,44.929653],"type":"Point"}
}