{
  "type": "Feature",
  "properties": {
    "addr:full":"La Maladiere Pole 2000 Pole 2000 07130 St Peray Rhone-Alpes",
    "addr:housenumber":"2000;2000",
    "addr:postcode":"07130",
    "addr:street":"Pole;Pole",
    "iso:country":"FR",
    "sg:address":"La Maladiere Pole 2000 Pole 2000 07130 St Peray",
    "sg:classifiers":[
        {
            "category":"Manufacturing",
            "subcategory":"Wood Products",
            "type":"Manufacturing & Wholesale Goods"
        }
    ],
    "sg:phone":"+33 4 75 81 85 10",
    "sg:province":"Rhone-Alpes",
    "sg:tags":[
        "furniture"
    ],
    "wof:name":"Sarl Traversier Maurice",
    "wof:placetype":"venue"
},
  "geometry": {"coordinates":[4.857873,44.942963],"type":"Point"}
}