{
  "type": "Feature",
  "properties": {
    "addr:full":"2, Place Fran\u00e7ois II, 44200 Nantes Pays de Loire",
    "addr:housenumber":"2",
    "addr:postcode":"44200",
    "addr:street":"Place Franc\u0327Ois Ii",
    "iso:country":"FR",
    "sg:address":"2, Place Fran\u00e7ois II, 44200 Nantes",
    "sg:orig_category":"Non-Classified Establishments",
    "sg:phone":"+33 2 40 35 02 40",
    "sg:province":"Pays de Loire",
    "wof:name":"R.d.s. S.a. - Repro Dactyl Services",
    "wof:placetype":"venue"
},
  "geometry": {"coordinates":[-1.556894,47.206367],"type":"Point"}
}