{
  "type": "Feature",
  "properties": {
    "iso:country":"FR",
    "sg:address":"4 Rue De La Collegiale 75005 Paris",
    "sg:classifiers":[
        {
            "category":"Manufacturing",
            "subcategory":"Printing",
            "type":"Manufacturing & Wholesale Goods"
        }
    ],
    "sg:phone":"+33 1 43 37 80 30",
    "sg:province":"Ile de France",
    "sg:tags":[
        "publishing"
    ],
    "wof:name":"Flash Image'in Sarl",
    "wof:placetype":"venue"
},
  "geometry": {"coordinates":[2.35268,48.837406],"type":"Point"}
}