{
  "type": "Feature",
  "properties": {
    "addr:full":"178, Bd Haussman, 75008 Paris Ile de France",
    "addr:housenumber":"178",
    "addr:postcode":"75008",
    "addr:street":"Bd Haussman",
    "iso:country":"FR",
    "sg:address":"178, Bd Haussman, 75008 Paris",
    "sg:orig_category":"Non-Classified Establishments",
    "sg:phone":"+33 1 53 96 50 40",
    "sg:province":"Ile de France",
    "wof:name":"O.n.s. S.a. - On Net Services",
    "wof:placetype":"venue"
},
  "geometry": {"coordinates":[2.307217,48.875126],"type":"Point"}
}