{
  "type": "Feature",
  "properties": {
    "iso:country":"FR",
    "sg:address":"Moulin de Villeroy 80150 Vitz sur Authie",
    "sg:orig_category":"Unclassifiable Establishments",
    "sg:phone":"+33 3 22 29 21 61",
    "sg:province":"Picardie",
    "wof:name":"Huilerie Coache S.a.r.l.",
    "wof:placetype":"venue"
},
  "geometry": {"coordinates":[1.880765,50.25227],"type":"Point"}
}