{
  "type": "Feature",
  "properties": {
    "iso:country":"FR",
    "sg:address":"1919, Rte de Mende, 34293 Montpellier",
    "sg:orig_category":"Non-Classified Establishments",
    "sg:phone":"+33 4 67 61 34 34",
    "sg:province":"Languedoc-Roussillon",
    "wof:name":"C.n.r.s. - Centre National De Recherches Scientifiques",
    "wof:placetype":"venue"
},
  "geometry": {"coordinates":[3.865399,43.638695],"type":"Point"}
}