{
  "type": "Feature",
  "properties": {
    "addr:full":"645, Av. Mayor de Montricher - ZI les Milles - B\u00e2t C, 13851 Aix en Provence C\u00e9dex 02 Nord Pas-de-Calais",
    "addr:housenumber":"645;02",
    "addr:postcode":"13851",
    "addr:street":"Av. Mayor De Montricher Zi Les;Ce\u0301Dex",
    "iso:country":"FR",
    "sg:address":"645, Av. Mayor de Montricher - ZI les Milles - B\u00e2t C, 13851 Aix en Provence C\u00e9dex 02",
    "sg:orig_category":"Non-Classified Establishments",
    "sg:phone":"+33 4 42 16 30 00",
    "sg:province":"Nord Pas-de-Calais",
    "wof:name":"Cofathec Services S.a.",
    "wof:placetype":"venue"
},
  "geometry": {"coordinates":[5.38935,43.50206],"type":"Point"}
}