{
  "type": "Feature",
  "properties": {
    "addr:full":"6, Rue de la Croisette, 54210 Saint Nicolas de Port Lorraine",
    "addr:housenumber":"6",
    "addr:postcode":"54210",
    "addr:street":"Rue De La Croisette;Port",
    "iso:country":"FR",
    "sg:address":"6, Rue de la Croisette, 54210 Saint Nicolas de Port",
    "sg:orig_category":"Unclassifiable Establishments",
    "sg:phone":"+33 3 83 46 93 09",
    "sg:province":"Lorraine",
    "wof:name":"C.a.t. - Saint Nicolas - Centre D'aide Par Le Travail",
    "wof:placetype":"venue"
},
  "geometry": {"coordinates":[6.283165,48.620926],"type":"Point"}
}