{
  "type": "Feature",
  "properties": {
    "iso:country":"FR",
    "sg:address":"92523 Neuilly sur Seine C\u00e9dex^^88, Av. Charles de Gaulle, 92200 Neuilly sur Seine",
    "sg:orig_category":"Non-Classified Establishments",
    "sg:phone":"+33 1 46 41 48 00",
    "sg:province":"Ile de France",
    "wof:name":"Setimeg S.a.",
    "wof:placetype":"venue"
},
  "geometry": {"coordinates":[2.26934,48.884377],"type":"Point"}
}