{
  "type": "Feature",
  "properties": {
    "addr:full":"4 Pl Prieurs Evrunes 85290 Mortagne Sur S\u00e8vre Pays de Loire 85290",
    "addr:housenumber":"4",
    "addr:postcode":"85290;85290",
    "addr:street":"Pl Prieurs Evrunes;Se\u0300Vre",
    "iso:country":"FR",
    "sg:address":"4 Pl Prieurs Evrunes 85290 Mortagne Sur S\u00e8vre",
    "sg:classifiers":[
        {
            "category":"Professional",
            "subcategory":"Engineering",
            "type":"Services"
        }
    ],
    "sg:phone":"+33 2 51 66 77 77",
    "sg:postcode":"85290",
    "sg:province":"Pays de Loire",
    "sg:tags":[
        "machine",
        "-",
        "mechanical"
    ],
    "wof:name":"Ix Manu Sa",
    "wof:placetype":"venue"
},
  "geometry": {"coordinates":[-0.940346,46.975887],"type":"Point"}
}