{
  "type": "Feature",
  "properties": {
    "addr:full":"29 Av Jules Uhry 60100 Creil Picardie",
    "addr:postcode":"60100",
    "addr:street":"29 Av Jules Uhry",
    "iso:country":"FR",
    "sg:address":"29 Av Jules Uhry 60100 Creil",
    "sg:classifiers":[
        {
            "category":"Professional",
            "subcategory":"Printing & Photocopies",
            "type":"Services"
        }
    ],
    "sg:phone":"+33 3 44 65 63 21",
    "sg:province":"Picardie",
    "sg:tags":[
        "publishing"
    ],
    "wof:name":"Manchette Publicite",
    "wof:placetype":"venue"
},
  "geometry": {"coordinates":[2.471405,49.264153],"type":"Point"}
}