{
  "type": "Feature",
  "properties": {
    "addr:full":"1240 Rte Des Dolines Buropolis 06904 Sophia Antipolis Cedex Centre",
    "addr:housenumber":"1240",
    "addr:postcode":"06904",
    "addr:street":"Rte Des Dolines Buropolis;Antipolis Cedex",
    "iso:country":"FR",
    "sg:address":"1240 Rte Des Dolines Buropolis 06904 Sophia Antipolis Cedex",
    "sg:classifiers":[
        {
            "category":"Manufacturing",
            "subcategory":"Chemicals & Compounds",
            "type":"Manufacturing & Wholesale Goods"
        }
    ],
    "sg:phone":"+33 4 93 95 60 00",
    "sg:province":"Centre",
    "sg:tags":[
        "pharmaceutical",
        "chemistry",
        "-",
        "by-product"
    ],
    "wof:name":"Dow Agrosciences",
    "wof:placetype":"venue"
},
  "geometry": {"coordinates":[-73.542252,41.05164],"type":"Point"}
}