{
  "type": "Feature",
  "properties": {
    "iso:country":"FR",
    "sg:address":"309 cours Lib\u00e9ration; Talence",
    "sg:classifiers":[
        {
            "category":"Banks & Credit Unions",
            "subcategory":"Bank",
            "type":"Services"
        }
    ],
    "sg:phone":"+33 3356803520",
    "sg:province":"Midi Pyr\u00e9n\u00e9es",
    "wof:name":"Banque Populair Du Sud Ouest",
    "wof:placetype":"venue"
},
  "geometry": {"coordinates":[-0.591434,44.811043],"type":"Point"}
}