{
  "type": "Feature",
  "properties": {
    "iso:country":"FR",
    "sg:address":"Coulaud Sud Rue Firmin Bouvier 24750 Boulazac",
    "sg:city":"Boulazac",
    "sg:classifiers":[
        {
            "category":"Farming",
            "subcategory":"Livestock Farm",
            "type":"Manufacturing & Wholesale Goods"
        }
    ],
    "sg:phone":"+33 5 53 04 64 69",
    "sg:postcode":"24750",
    "sg:province":"Aquitaine",
    "sg:tags":[
        "breeding",
        "agriculture",
        "animal"
    ],
    "wof:name":"Espinet Sa",
    "wof:placetype":"venue"
},
  "geometry": {"coordinates":[0.789735,45.09977],"type":"Point"}
}