{
  "type": "Feature",
  "properties": {
    "iso:country":"FR",
    "sg:address":"Le Mont Rouge 50700 Valognes",
    "sg:city":"Valognes",
    "sg:orig_category":"Non-Classified Establishments",
    "sg:phone":"+33 2 33 40 11 24",
    "sg:postcode":"50700",
    "sg:province":"Basse Normandie",
    "wof:name":"Motin Fr\u00e8res S.a.",
    "wof:placetype":"venue"
},
  "geometry": {"coordinates":[-1.43503,49.451469],"type":"Point"}
}