{
  "type": "Feature",
  "properties": {
    "addr:full":"Rue De La For\u00eat Vau De Chaume 41110 St Aignan Ch\u00e2teauvieux Centre 41110",
    "addr:postcode":"41110;41110",
    "addr:street":"Rue De La Fore\u0302T;De Chaume",
    "iso:country":"FR",
    "sg:address":"Rue De La For\u00eat Vau De Chaume 41110 St Aignan",
    "sg:city":"Ch\u00e2teauvieux",
    "sg:classifiers":[
        {
            "category":"Home & Garden",
            "subcategory":"Furniture",
            "type":"Retail Goods"
        }
    ],
    "sg:phone":"+33 2 54 71 65 65",
    "sg:postcode":"41110",
    "sg:province":"Centre",
    "sg:tags":[
        "wood"
    ],
    "wof:name":"Ste Megnien Distrubution Bois Materiaux Carrelages",
    "wof:placetype":"venue"
},
  "geometry": {"coordinates":[1.34709,47.260868],"type":"Point"}
}