{
  "type": "Feature",
  "properties": {
    "addr:full":"Ccal Auchan 59760 Grande Synthe Nord Pas-de-Calais 59760",
    "addr:postcode":"59760;59760",
    "addr:street":"Grande Synthe Nord",
    "iso:country":"FR",
    "sg:address":"Ccal Auchan 59760 Grande Synthe",
    "sg:classifiers":[
        {
            "category":"Travel",
            "subcategory":"Hotels & Motels",
            "type":"Entertainment"
        }
    ],
    "sg:phone":"+33 3 28 27 97 27",
    "sg:postcode":"59760",
    "sg:province":"Nord Pas-de-Calais",
    "sg:tags":[
        "hotels",
        "business",
        "restaurant"
    ],
    "wof:name":"Pizza Pai",
    "wof:placetype":"venue"
},
  "geometry": {"coordinates":[2.30272,51.013069],"type":"Point"}
}