{
  "type": "Feature",
  "properties": {
    "iso:country":"FR",
    "sg:address":"33049 Bruges C\u00e9dex^^1, Rue Pierre et Marie Curie, 33520 Bruges",
    "sg:city":"Bruges",
    "sg:orig_category":"Non-Classified Establishments",
    "sg:phone":"+33 5 56 39 44 44",
    "sg:postcode":"33520",
    "sg:province":"Aquitaine",
    "wof:name":"Dolisos Laboratoires",
    "wof:placetype":"venue"
},
  "geometry": {"coordinates":[-0.610265,44.887768],"type":"Point"}
}