{
  "type": "Feature",
  "properties": {
    "iso:country":"FR",
    "sg:address":"63, Rue Principale, 68700 Michelbach",
    "sg:city":"Michelbach",
    "sg:orig_category":"Non-Classified Establishments",
    "sg:phone":"+33 3 89 82 55 97",
    "sg:postcode":"68700",
    "sg:province":"Alsace",
    "wof:name":"Monnier Jo\u00ebl",
    "wof:placetype":"venue"
},
  "geometry": {"coordinates":[7.111998,47.761543],"type":"Point"}
}