{
  "type": "Feature",
  "properties": {
    "addr:full":"63, Rue Principale, 68700 Michelbach Michelbach Alsace 68700",
    "addr:housenumber":"63",
    "addr:postcode":"68700;68700",
    "addr:street":"Rue Principale",
    "iso:country":"FR",
    "sg:address":"63, Rue Principale, 68700 Michelbach",
    "sg:city":"Michelbach",
    "sg:orig_category":"Non-Classified Establishments",
    "sg:phone":"+33 3 89 82 55 97",
    "sg:postcode":"68700",
    "sg:province":"Alsace",
    "wof:name":"Monnier Jo\u00ebl",
    "wof:placetype":"venue"
},
  "geometry": {"coordinates":[7.111998,47.761543],"type":"Point"}
}