{
  "type": "Feature",
  "properties": {
    "addr:full":"Route De St Gilles Zone De Legrin 30132 Caissargues Languedoc-Roussillon 30132",
    "addr:postcode":"30132;30132",
    "addr:street":"Route De St;Caissargues",
    "iso:country":"FR",
    "sg:address":"Route De St Gilles Zone De Legrin 30132 Caissargues",
    "sg:classifiers":[
        {
            "category":"Manufacturing",
            "subcategory":"Metals",
            "type":"Manufacturing & Wholesale Goods"
        }
    ],
    "sg:phone":"+33 4 66 38 61 61",
    "sg:postcode":"30132",
    "sg:province":"Languedoc-Roussillon",
    "sg:tags":[
        "metallurgy",
        "metalworking",
        "processing"
    ],
    "wof:name":"Peinture Antico Diffusion (pad)",
    "wof:placetype":"venue"
},
  "geometry": {"coordinates":[4.377945,43.796341],"type":"Point"}
}