{
  "type": "Feature",
  "properties": {
    "iso:country":"FR",
    "sg:address":"4 A Rue Contades 67300 Schiltigheim",
    "sg:city":"Schiltigheim",
    "sg:classifiers":[
        {
            "category":"Health Services",
            "subcategory":"Medical Lab",
            "type":"Services"
        }
    ],
    "sg:phone":"+33 3 88 81 20 20",
    "sg:postcode":"67300",
    "sg:province":"Alsace",
    "sg:tags":[
        "chemical",
        "pharmaceutical",
        "pharmacy"
    ],
    "wof:name":"Laboratoires Dolisos",
    "wof:placetype":"venue"
},
  "geometry": {"coordinates":[7.754609,48.601578],"type":"Point"}
}