{
  "type": "Feature",
  "properties": {
    "addr:full":"Les Touches 16560 Anais Poitou-Charentes 16560",
    "addr:postcode":"16560;16560",
    "iso:country":"FR",
    "sg:address":"Les Touches 16560 Anais",
    "sg:classifiers":[
        {
            "category":"Professional",
            "subcategory":"Engineering",
            "type":"Services"
        }
    ],
    "sg:phone":"+33 5 45 20 68 62",
    "sg:postcode":"16560",
    "sg:province":"Poitou-Charentes",
    "sg:tags":[
        "machine",
        "-",
        "mechanical"
    ],
    "wof:name":"Innomould",
    "wof:placetype":"venue"
},
  "geometry": {"coordinates":[0.25703,45.784691],"type":"Point"}
}