{
  "type": "Feature",
  "properties": {
    "addr:full":"Ecart Buxerulles 55300 Buxerulles Lorraine",
    "addr:postcode":"55300",
    "addr:street":"Buxerulles",
    "iso:country":"FR",
    "sg:address":"Ecart Buxerulles 55300 Buxerulles",
    "sg:classifiers":[
        {
            "category":"Utilities",
            "subcategory":"Water",
            "type":"Services"
        }
    ],
    "sg:phone":"+33 3 29 89 36 14",
    "sg:province":"Lorraine",
    "sg:tags":[
        "sew-on",
        "badge"
    ],
    "wof:name":"Robatech S.a.",
    "wof:placetype":"venue"
},
  "geometry": {"coordinates":[5.541056,48.891834],"type":"Point"}
}