{
  "type": "Feature",
  "properties": {
    "iso:country":"FR",
    "sg:address":"Route De Nyons 84110 St Romain En Viennois",
    "sg:classifiers":[
        {
            "category":"Home & Garden",
            "subcategory":"Furniture",
            "type":"Retail Goods"
        }
    ],
    "sg:phone":"+33 4 90 46 46 87",
    "sg:province":"Rhone-Alpes",
    "sg:tags":[
        "household",
        "wood"
    ],
    "wof:name":"L'estagnie Meubles Arnaud",
    "wof:placetype":"venue"
},
  "geometry": {"coordinates":[5.008068,44.190483],"type":"Point"}
}