{
  "type": "Feature",
  "properties": {
    "iso:country":"FR",
    "sg:address":"ZI Les Plaines",
    "sg:city":"Courlaoux",
    "sg:orig_category":"INSTALLATEUR: FROID INDUSTRIEL ET COMMERCIAL, CLIMATISATION FROID INDUSTRIEL ET COMMERCIAL, CLIMATIS",
    "sg:phone":"+33 3 84 35 38 44",
    "sg:postcode":"39570",
    "sg:province":"Franche Comt\u00e9",
    "wof:name":"Boost' Air R\u00e9frig\u00e9ration S.a.r.l.",
    "wof:placetype":"venue"
},
  "geometry": {"coordinates":[5.46095,46.66806],"type":"Point"}
}