{
  "type": "Feature",
  "properties": {
    "addr:full":"Av. de Saint Nazaire Canet en Roussillon Languedoc-Roussillon 66140",
    "addr:postcode":"66140",
    "addr:street":"Av. De Saint Nazaire;Roussillon",
    "iso:country":"FR",
    "sg:address":"Av. de Saint Nazaire",
    "sg:city":"Canet en Roussillon",
    "sg:orig_category":"Non-Classified Establishments",
    "sg:phone":"+33 4 68 80 36 96",
    "sg:postcode":"66140",
    "sg:province":"Languedoc-Roussillon",
    "wof:name":"P\u00e9pini\u00e8res Peyret Jacques",
    "wof:placetype":"venue"
},
  "geometry": {"coordinates":[3.00464,42.704426],"type":"Point"}
}