{
  "type": "Feature",
  "properties": {
    "addr:full":"36, Rue Solf\u00e9rino, 51100 Reims Champagne",
    "addr:housenumber":"36",
    "addr:postcode":"51100",
    "addr:street":"Rue Solfe\u0301Rino",
    "iso:country":"FR",
    "sg:address":"36, Rue Solf\u00e9rino, 51100 Reims",
    "sg:orig_category":"Unclassifiable Establishments",
    "sg:phone":"+33 3 26 40 12 54",
    "sg:province":"Champagne",
    "wof:name":"L'atelier Graphique S.a.r.l.",
    "wof:placetype":"venue"
},
  "geometry": {"coordinates":[4.049447,49.266869],"type":"Point"}
}