{
  "type": "Feature",
  "properties": {
    "addr:full":"10 rue du Centre 01100 Bellignat Rhone-Alpes 01100",
    "addr:housenumber":"10",
    "addr:postcode":"01100;01100",
    "addr:street":"Rue Du Centre;Rhone-Alpes",
    "iso:country":"FR",
    "sg:address":"10 rue du Centre 01100 Bellignat",
    "sg:classifiers":[
        {
            "category":"Manufacturing",
            "subcategory":"Rubber & Plastics",
            "type":"Manufacturing & Wholesale Goods"
        }
    ],
    "sg:phone":"+33 4 74 77 51 21",
    "sg:postcode":"01100",
    "sg:province":"Rhone-Alpes",
    "sg:tags":[
        "injection",
        "moulding",
        "dy"
    ],
    "wof:name":"Grosfilley J.p. Sarl",
    "wof:placetype":"venue"
},
  "geometry": {"coordinates":[5.630096,46.243649],"type":"Point"}
}