{
  "type": "Feature",
  "properties": {
    "addr:full":"373 Rue Des Pyrenees 75020 Paris Ile de France 75020",
    "addr:housenumber":"373",
    "addr:postcode":"75020;75020",
    "addr:street":"Rue Des Pyrenees",
    "iso:country":"FR",
    "sg:address":"373 Rue Des Pyrenees 75020 Paris",
    "sg:classifiers":[
        {
            "category":"Shopping",
            "subcategory":"Clothing, Apparel, & Fashions",
            "type":"Retail Goods"
        }
    ],
    "sg:phone":"+33 1 46 36 38 34",
    "sg:postcode":"75020",
    "sg:province":"Ile de France",
    "sg:tags":[
        "textile",
        "clothing",
        "clothes"
    ],
    "wof:name":"Croatia",
    "wof:placetype":"venue"
},
  "geometry": {"coordinates":[2.389808,48.87339],"type":"Point"}
}