{
  "type": "Feature",
  "properties": {
    "iso:country":"FR",
    "sg:address":"77 Route St Alban De Roche 38080 Four",
    "sg:classifiers":[
        {
            "category":"Home & Garden",
            "subcategory":"Furniture",
            "type":"Retail Goods"
        }
    ],
    "sg:phone":"+33 4 74 93 44 43",
    "sg:postcode":"38080",
    "sg:province":"Rhone-Alpes",
    "sg:tags":[
        "household",
        "wood"
    ],
    "wof:name":"Berlioz Creations Sa",
    "wof:placetype":"venue"
},
  "geometry": {"coordinates":[5.210363,45.591843],"type":"Point"}
}