{
  "type": "Feature",
  "properties": {
    "iso:country":"FR",
    "sg:address":"34967 Montpellier C\u00e9dex 2^^168, Rue de la Vieille Poste - Nexwave Bulding - Parc du Mill\u00e9naire, 3400",
    "sg:orig_category":"Non-Classified Establishments",
    "sg:phone":"+33 4 99 52 89 89",
    "sg:province":"Auvergne",
    "wof:name":"Nexwave Solutions S.a.",
    "wof:placetype":"venue"
},
  "geometry": {"coordinates":[3.37215,46.573559],"type":"Point"}
}