{
  "type": "Feature",
  "properties": {
    "addr:full":"Residence du Centre; Anglet; 64600 Anglet Aquitaine 64600",
    "addr:postcode":"64600;64600",
    "iso:country":"FR",
    "sg:address":"Residence du Centre; Anglet; 64600",
    "sg:city":"Anglet",
    "sg:classifiers":[
        {
            "category":"Banks & Credit Unions",
            "subcategory":"Bank",
            "type":"Services"
        }
    ],
    "sg:phone":"+33 3359638675",
    "sg:postcode":"64600",
    "sg:province":"Aquitaine",
    "wof:name":"Soci\u00e9t\u00e9 G\u00e9n\u00e9rale",
    "wof:placetype":"venue"
},
  "geometry": {"coordinates":[-1.514707,43.481705],"type":"Point"}
}