{
  "type": "Feature",
  "properties": {
    "addr:full":"21, Rue des Sports, 74600 Seynod Rhone-Alpes",
    "addr:housenumber":"21",
    "addr:postcode":"74600",
    "addr:street":"Rue Des Sports",
    "iso:country":"FR",
    "sg:address":"21, Rue des Sports, 74600 Seynod",
    "sg:orig_category":"Unclassifiable Establishments",
    "sg:phone":"+33 4 50 69 54 24",
    "sg:province":"Rhone-Alpes",
    "wof:name":"Domo Conseil Electricit\u00e9",
    "wof:placetype":"venue"
},
  "geometry": {"coordinates":[6.084318,45.883392],"type":"Point"}
}