{
  "type": "Feature",
  "properties": {
    "addr:full":"3, Rue Hubert Pennevert - ZI des Soeurs, 17300 Rochefort Poitou-Charentes",
    "addr:housenumber":"3",
    "addr:postcode":"17300 rochefort",
    "addr:street":"Rue Hubert Pennevert Zi Des Soeurs",
    "iso:country":"FR",
    "sg:address":"3, Rue Hubert Pennevert - ZI des Soeurs, 17300 Rochefort",
    "sg:orig_category":"Unclassifiable Establishments",
    "sg:phone":"+33 5 46 87 30 00",
    "sg:province":"Poitou-Charentes",
    "wof:name":"Lecuiller S.a.",
    "wof:placetype":"venue"
},
  "geometry": {"coordinates":[-0.958704,45.934818],"type":"Point"}
}