{
  "type": "Feature",
  "properties": {
    "addr:full":"22, Rue des Cerisiers - ZI de l'Eglantier, 91090 Lisses Ile de France",
    "addr:housenumber":"22",
    "addr:postcode":"91090;ile",
    "addr:street":"Rue Des Cerisiers Zi De L'Eglantier",
    "iso:country":"FR",
    "sg:address":"22, Rue des Cerisiers - ZI de l'Eglantier, 91090 Lisses",
    "sg:orig_category":"Unclassifiable Establishments",
    "sg:phone":"+33 1 69 47 49 49",
    "sg:province":"Ile de France",
    "wof:name":"Hitachi Power Tools France S.a.",
    "wof:placetype":"venue"
},
  "geometry": {"coordinates":[2.432151,48.598194],"type":"Point"}
}