{
  "type": "Feature",
  "properties": {
    "iso:country":"FR",
    "sg:address":"5 Rue De La Broche 21800 Quetigny",
    "sg:city":"Quetigny",
    "sg:classifiers":[
        {
            "category":"Shopping",
            "subcategory":"Computers & Home Electronics",
            "type":"Retail Goods"
        }
    ],
    "sg:phone":"+33 3 80 48 90 10",
    "sg:postcode":"21800",
    "sg:province":"Bourgogne",
    "sg:tags":[
        "electronic",
        "electrical",
        "equipment"
    ],
    "wof:name":"Roulement Service",
    "wof:placetype":"venue"
},
  "geometry": {"coordinates":[5.103691,47.306877],"type":"Point"}
}