{
  "type": "Feature",
  "properties": {
    "addr:full":"8, Rue de Greffuhles, 75008 Paris Ile de France",
    "addr:housenumber":"8",
    "addr:postcode":"75008",
    "addr:street":"Rue De Greffuhles",
    "iso:country":"FR",
    "sg:address":"8, Rue de Greffuhles, 75008 Paris",
    "sg:orig_category":"Unclassifiable Establishments",
    "sg:phone":"+33 1 47 42 20 05",
    "sg:province":"Ile de France",
    "wof:name":"Duo Industrie S.a.s.",
    "wof:placetype":"venue"
},
  "geometry": {"coordinates":[2.325356,48.872723],"type":"Point"}
}