{
  "type": "Feature",
  "properties": {
    "addr:full":"260 Route Des Creuses 74600 Seynod Rhone-Alpes 74600",
    "addr:housenumber":"260",
    "addr:postcode":"74600;74600",
    "addr:street":"Route Des Creuses",
    "iso:country":"FR",
    "sg:address":"260 Route Des Creuses 74600 Seynod",
    "sg:classifiers":[
        {
            "category":"Wholesale",
            "subcategory":"Machinery & Supplies",
            "type":"Manufacturing & Wholesale Goods"
        }
    ],
    "sg:phone":"+33 4 50 69 05 45",
    "sg:postcode":"74600",
    "sg:province":"Rhone-Alpes",
    "sg:tags":[
        "handling",
        "material",
        "-",
        "machine",
        "equipment",
        "engineering",
        "mechanical"
    ],
    "wof:name":"Mstm Sa",
    "wof:placetype":"venue"
},
  "geometry": {"coordinates":[6.078552,45.88932],"type":"Point"}
}