{
  "type": "Feature",
  "properties": {
    "iso:country":"FR",
    "sg:address":"16 pl Eglise; Avessac",
    "sg:city":"Avessac",
    "sg:classifiers":[
        {
            "category":"Banks & Credit Unions",
            "subcategory":"Bank",
            "type":"Services"
        }
    ],
    "sg:phone":"+33 3399919965",
    "sg:postcode":"44460",
    "sg:province":"Pays de Loire",
    "wof:name":"Cr\u00e9dit Agricole Mutuel",
    "wof:placetype":"venue"
},
  "geometry": {"coordinates":[-1.989339,47.653721],"type":"Point"}
}