{
  "type": "Feature",
  "properties": {
    "iso:country":"FR",
    "sg:address":"15 Bis Rue Jean Charcot 22102 Dinan Cedex",
    "sg:classifiers":[
        {
            "category":"Professional",
            "subcategory":"Business Services",
            "type":"Services"
        }
    ],
    "sg:phone":"+33 2 96 87 60 00",
    "sg:province":"Bretagne",
    "sg:tags":[
        "training",
        "advice"
    ],
    "wof:name":"Lycee Professionel Ker Siam",
    "wof:placetype":"venue"
},
  "geometry": {"coordinates":[-2.05246,48.448559],"type":"Point"}
}