{
  "type": "Feature",
  "properties": {
    "addr:full":"53 Av Victor Hugo 75116 Paris Ile-de-France",
    "addr:postcode":"75116",
    "addr:street":"53 Av Victor Hugo",
    "iso:country":"FR",
    "sg:address":"53 Av Victor Hugo 75116 Paris",
    "sg:classifiers":[
        {
            "category":"Professional",
            "subcategory":"Printing & Photocopies",
            "type":"Services"
        }
    ],
    "sg:phone":"+33 1 44 17 83 00",
    "sg:province":"Ile-de-France",
    "sg:tags":[
        "paper",
        "raw",
        "material",
        "-",
        "cardboard"
    ],
    "wof:name":"Norske Skog France Sarl",
    "wof:placetype":"venue"
},
  "geometry": {"coordinates":[2.288805,48.870991],"type":"Point"}
}