{
  "type": "Feature",
  "properties": {
    "addr:full":"13, Av. du G\u00e9n\u00e9ral Leclerc, 94700 Maisons Alfort Ile de France",
    "addr:postcode":"94700",
    "addr:street":"13 Av. Du Ge\u0301Ne\u0301Ral Leclerc",
    "iso:country":"FR",
    "sg:address":"13, Av. du G\u00e9n\u00e9ral Leclerc, 94700 Maisons Alfort",
    "sg:orig_category":"Unclassifiable Establishments",
    "sg:phone":"+33 1 58 73 89 99",
    "sg:province":"Ile de France",
    "wof:name":"Pastelle S.a.r.l.",
    "wof:placetype":"venue"
},
  "geometry": {"coordinates":[2.421782,48.815174],"type":"Point"}
}