{
  "type": "Feature",
  "properties": {
    "iso:country":"FR",
    "sg:address":"Rd 561 13350 Charleval",
    "sg:city":"Charleval",
    "sg:classifiers":[
        {
            "category":"Wholesale",
            "subcategory":"Farm Supplies",
            "type":"Manufacturing & Wholesale Goods"
        }
    ],
    "sg:phone":"+33 4 42 28 41 39",
    "sg:postcode":"27380",
    "sg:province":"Haute Normandie",
    "sg:tags":[
        "-",
        "machine",
        "equipment",
        "engineering",
        "machinery",
        "mechanical",
        "agriculture"
    ],
    "wof:name":"Arborop",
    "wof:placetype":"venue"
},
  "geometry": {"coordinates":[5.24475,43.719589],"type":"Point"}
}