{
  "type": "Feature",
  "properties": {
    "iso:country":"FR",
    "sg:address":"10, Rue Antoine Lavoisier, 81000 Albi",
    "sg:orig_category":"Non-Classified Establishments",
    "sg:phone":"+33 5 63 45 18 44",
    "sg:postcode":"81000",
    "sg:province":"Midi Pyr\u00e9n\u00e9es",
    "wof:name":"Divina Claude S.a.r.l.",
    "wof:placetype":"venue"
},
  "geometry": {"coordinates":[2.200408,43.931892],"type":"Point"}
}