{
  "type": "Feature",
  "properties": {
    "addr:full":"114 Rue Jules Barni 80090 Amiens Amiens Picardie 80000",
    "addr:housenumber":"114",
    "addr:postcode":"80090 amiens;80000",
    "addr:street":"Rue Jules Barni",
    "iso:country":"FR",
    "sg:address":"114 Rue Jules Barni 80090 Amiens",
    "sg:city":"Amiens",
    "sg:classifiers":[
        {
            "category":"Food Court",
            "type":"Food & Drink"
        }
    ],
    "sg:phone":"+33 3 22 91 66 62",
    "sg:postcode":"80000",
    "sg:province":"Picardie",
    "sg:tags":[
        "product",
        "related"
    ],
    "wof:name":"Roussel Et Fils",
    "wof:placetype":"venue"
},
  "geometry": {"coordinates":[2.316436,49.886684],"type":"Point"}
}