{
  "type": "Feature",
  "properties": {
    "iso:country":"FR",
    "sg:address":"8, Rue de Franche Comt\u00e9 - Valparc, 25480 Ecole Valentin",
    "sg:orig_category":"Unclassifiable Establishments",
    "sg:phone":"+33 3 81 53 65 62",
    "sg:province":"Franche Comt\u00e9",
    "wof:name":"C.t.s. S.a.r.l. - Chaudronnerie T\u00f4lerie Serrurerie",
    "wof:placetype":"venue"
},
  "geometry": {"coordinates":[5.982078,47.27187],"type":"Point"}
}