{
  "type": "Feature",
  "properties": {
    "addr:full":"20 Impasse Edgar Quinet 93120 La Courneuve Ile de France 93120",
    "addr:housenumber":"20",
    "addr:postcode":"93120;93120",
    "addr:street":"Impasse Edgar Quinet",
    "iso:country":"FR",
    "sg:address":"20 Impasse Edgar Quinet 93120 La Courneuve",
    "sg:classifiers":[
        {
            "category":"Shopping",
            "subcategory":"Clothing, Apparel, & Fashions",
            "type":"Retail Goods"
        }
    ],
    "sg:phone":"+33 1 48 37 60 13",
    "sg:postcode":"93120",
    "sg:province":"Ile de France",
    "sg:tags":[
        "textile",
        "clothing",
        "clothes"
    ],
    "wof:name":"Stela",
    "wof:placetype":"venue"
},
  "geometry": {"coordinates":[2.393547,48.929703],"type":"Point"}
}