{
  "type": "Feature",
  "properties": {
    "addr:full":"31, Rue du Canal, 59400 Cambrai Nord Pas-de-Calais",
    "addr:housenumber":"31",
    "addr:postcode":"59400",
    "addr:street":"Rue Du Canal",
    "iso:country":"FR",
    "sg:address":"31, Rue du Canal, 59400 Cambrai",
    "sg:orig_category":"Non-Classified Establishments",
    "sg:phone":"+33 3 27 83 89 29",
    "sg:province":"Nord Pas-de-Calais",
    "wof:name":"Oubry Electronic S.a.r.l.",
    "wof:placetype":"venue"
},
  "geometry": {"coordinates":[3.21865,50.175842],"type":"Point"}
}