{
  "type": "Feature",
  "properties": {
    "addr:full":"Av Du Mas Argelliers Ld Les 3 Pointes 34000 Montpellier Languedoc-Roussillon 34000",
    "addr:housenumber":"3",
    "addr:postcode":"34000;34000",
    "addr:street":"Av Du Mas Argelliers Ld Les;Pointes",
    "iso:country":"FR",
    "sg:address":"Av Du Mas Argelliers Ld Les 3 Pointes 34000 Montpellier",
    "sg:classifiers":[
        {
            "category":"Building & Trades",
            "subcategory":"Construction",
            "type":"Services"
        }
    ],
    "sg:phone":"+33 4 67 58 78 78",
    "sg:postcode":"34000",
    "sg:province":"Languedoc-Roussillon",
    "sg:tags":[
        "work",
        "public"
    ],
    "wof:name":"Snc Des Maisons Individuelles Mediterannee",
    "wof:placetype":"venue"
},
  "geometry": {"coordinates":[3.87609,43.610855],"type":"Point"}
}