{
  "type": "Feature",
  "properties": {
    "addr:full":"Le Musset 61110 Cond\u00e9 Sur Huisne Saint-Maurice-sur-Huisne Basse Normandie 61110",
    "addr:postcode":"61110;61110",
    "addr:street":"Conde\u0301;Huisne Saint-Maurice-Sur-Huisne Basse",
    "iso:country":"FR",
    "sg:address":"Le Musset 61110 Cond\u00e9 Sur Huisne",
    "sg:city":"Saint-Maurice-sur-Huisne",
    "sg:orig_category":"Games and entertainment Horticulture Miscellaneous Products",
    "sg:phone":"+33 2 33 73 30 11",
    "sg:postcode":"61110",
    "sg:province":"Basse Normandie",
    "wof:name":"Soparco Sa",
    "wof:placetype":"venue"
},
  "geometry": {"coordinates":[0.85473,48.380863],"type":"Point"}
}