{
  "type": "Feature",
  "properties": {
    "iso:country":"FR",
    "sg:address":"7, Rue Clovis Ch\u00e9zel, 51100 Reims",
    "sg:orig_category":"Unclassifiable Establishments",
    "sg:phone":"+33 3 26 82 19 59",
    "sg:province":"Champagne",
    "wof:name":"Alpem S.a.",
    "wof:placetype":"venue"
},
  "geometry": {"coordinates":[4.0329,49.240471],"type":"Point"}
}