{
  "type": "Feature",
  "properties": {
    "addr:full":"1 Rue Division Leclerc 67290 Petersbach Petersbach Alsace 67290",
    "addr:housenumber":"1",
    "addr:postcode":"67290;67290",
    "addr:street":"Rue Division Leclerc",
    "iso:country":"FR",
    "sg:address":"1 Rue Division Leclerc 67290 Petersbach",
    "sg:city":"Petersbach",
    "sg:classifiers":[
        {
            "category":"Food Court",
            "type":"Food & Drink"
        }
    ],
    "sg:phone":"+33 3 88 71 79 79",
    "sg:postcode":"67290",
    "sg:province":"Alsace",
    "sg:tags":[
        "product",
        "related"
    ],
    "wof:name":"Les Grands Chais De France",
    "wof:placetype":"venue"
},
  "geometry": {"coordinates":[7.271104,48.869183],"type":"Point"}
}