{
  "type": "Feature",
  "properties": {
    "iso:country":"FR",
    "sg:address":"38- 40 Cs Artisid Briand 08000 Charleville Mezi\u00e8res",
    "sg:city":"Charleville-M\u00e9zi\u00e8res",
    "sg:classifiers":[
        {
            "category":"Professional",
            "subcategory":"Printing & Photocopies",
            "type":"Services"
        }
    ],
    "sg:phone":"+33 3 24 33 78 78",
    "sg:postcode":"08000",
    "sg:province":"Champagne",
    "sg:tags":[
        "publishing"
    ],
    "wof:name":"L'ardennais L'union",
    "wof:placetype":"venue"
},
  "geometry": {"coordinates":[4.719185,49.768421],"type":"Point"}
}