{
  "type": "Feature",
  "properties": {
    "iso:country":"FR",
    "sg:address":"Rue du Mar\u00e9chal Leclerc; Pont Audemer; 27500",
    "sg:classifiers":[
        {
            "category":"Banks & Credit Unions",
            "subcategory":"Bank",
            "type":"Services"
        }
    ],
    "sg:phone":"+33 32416014",
    "sg:postcode":"27500",
    "sg:province":"Haute Normandie",
    "wof:name":"Cr\u00e9dit Agricole De L'eure",
    "wof:placetype":"venue"
},
  "geometry": {"coordinates":[0.512965,49.35466],"type":"Point"}
}