{
  "type": "Feature",
  "properties": {
    "iso:country":"FR",
    "sg:address":"5 bis, Rue Lucien Edouard Geber, 92240 Malakoff",
    "sg:orig_category":"Unclassifiable Establishments",
    "sg:phone":"+33 1 46 54 24 13",
    "sg:province":"Ile de France",
    "wof:name":"Jpb Electro Acoustique S.a.r.l.",
    "wof:placetype":"venue"
},
  "geometry": {"coordinates":[2.310573,48.821426],"type":"Point"}
}