{
  "type": "Feature",
  "properties": {
    "iso:country":"FR",
    "sg:address":"34, Rue Malmaison, 95500 Gonesse",
    "sg:orig_category":"Non-Classified Establishments",
    "sg:phone":"+33 1 34 45 19 50",
    "sg:province":"Ile de France",
    "wof:name":"S.t.a.f.i. S.a. - Soci\u00e9t\u00e9 De Transports Et D'affr\u00eatements Fran\u00e7ais",
    "wof:placetype":"venue"
},
  "geometry": {"coordinates":[2.45493,48.982056],"type":"Point"}
}