{
  "type": "Feature",
  "properties": {
    "addr:full":"Zi de berleane 64160 Morlaas Morla\u00e0s Aquitaine 64160",
    "addr:postcode":"64160;64160",
    "addr:street":"Zi De Berleane",
    "iso:country":"FR",
    "sg:address":"Zi de berleane 64160 Morlaas",
    "sg:city":"Morla\u00e0s",
    "sg:classifiers":[
        {
            "category":"Industrial Area",
            "type":"Public Place"
        }
    ],
    "sg:phone":"+33 5 59 80 66 00",
    "sg:postcode":"64160",
    "sg:province":"Aquitaine",
    "sg:tags":[
        "box",
        "cardboard"
    ],
    "wof:name":"Embadac Sa",
    "wof:placetype":"venue"
},
  "geometry": {"coordinates":[-0.263594,43.344894],"type":"Point"}
}