{
  "type": "Feature",
  "properties": {
    "addr:full":"4 Chapeliers; Aix en Provence; 13100 Nord Pas-de-Calais",
    "addr:housenumber":"4;13100",
    "addr:street":"Chapeliers Aix",
    "iso:country":"FR",
    "sg:address":"4",
    "sg:city":"Chapeliers; Aix en Provence; 13100",
    "sg:classifiers":[
        {
            "category":"Banks & Credit Unions",
            "subcategory":"Bank",
            "type":"Services"
        }
    ],
    "sg:phone":"+33 3342266980",
    "sg:province":"Nord Pas-de-Calais",
    "wof:name":"Cr\u00e9dit Mutuel Aix En Provence",
    "wof:placetype":"venue"
},
  "geometry": {"coordinates":[5.448981,43.528416],"type":"Point"}
}