{
  "type": "Feature",
  "properties": {
    "iso:country":"FR",
    "sg:address":"B.P. 04, 67114 Eschau^^23, Rue du G\u00e9n\u00e9ral de Gaulle, 67114 Eschau",
    "sg:city":"Eschau",
    "sg:orig_category":"Non-Classified Establishments",
    "sg:phone":"+33 3 88 59 04 90",
    "sg:postcode":"67114",
    "sg:province":"Alsace",
    "wof:name":"Entreprise Lucien Speyser Et Compagnie S.a.",
    "wof:placetype":"venue"
},
  "geometry": {"coordinates":[7.715565,48.487968],"type":"Point"}
}