{
  "type": "Feature",
  "properties": {
    "addr:full":"Fort des Rousses 39220 Les Rousses Franche Comt\u00e9",
    "addr:postcode":"39220",
    "addr:street":"Fort Des Rousses;Franche Comte\u0301",
    "iso:country":"FR",
    "sg:address":"Fort des Rousses 39220 Les Rousses",
    "sg:orig_category":"Unclassifiable Establishments",
    "sg:phone":"+33 3 84 60 56 01",
    "sg:province":"Franche Comt\u00e9",
    "wof:name":"Forsym S.a.",
    "wof:placetype":"venue"
},
  "geometry": {"coordinates":[6.09632,46.512825],"type":"Point"}
}