{
  "type": "Feature",
  "properties": {
    "addr:full":"7 Av William Ponty 17300 Rochefort Poitou-Charentes 17300",
    "addr:postcode":"17300 rochefort;17300",
    "addr:street":"Av William Ponty",
    "iso:country":"FR",
    "sg:address":"7 Av William Ponty 17300 Rochefort",
    "sg:classifiers":[
        {
            "category":"Wholesale",
            "subcategory":"Metals & Minerals",
            "type":"Manufacturing & Wholesale Goods"
        }
    ],
    "sg:phone":"+33 5 46 82 13 90",
    "sg:postcode":"17300",
    "sg:province":"Poitou-Charentes",
    "sg:tags":[
        "steel",
        "metallurgy",
        "tool",
        "metalworking"
    ],
    "wof:name":"Berton Sa",
    "wof:placetype":"venue"
},
  "geometry": {"coordinates":[-0.956334,45.945236],"type":"Point"}
}