{
  "type": "Feature",
  "properties": {
    "iso:country":"FR",
    "sg:address":"27, Rue Gutenberg, 91070 Bondoufle",
    "sg:orig_category":"Unclassifiable Establishments",
    "sg:phone":"+33 1 60 86 47 00",
    "sg:province":"Ile de France",
    "wof:name":"Somiplast S.a.",
    "wof:placetype":"venue"
},
  "geometry": {"coordinates":[2.377104,48.62035],"type":"Point"}
}