{
  "type": "Feature",
  "properties": {
    "addr:full":"5, Place du Champ de Foire, 71150 Rully Rully Bourgogne 71150",
    "addr:housenumber":"5",
    "addr:postcode":"71150;71150",
    "addr:street":"Place Du Champ De Foire",
    "iso:country":"FR",
    "sg:address":"5, Place du Champ de Foire, 71150 Rully",
    "sg:city":"Rully",
    "sg:orig_category":"Non-Classified Establishments",
    "sg:phone":"+33 3 85 87 20 71",
    "sg:postcode":"71150",
    "sg:province":"Bourgogne",
    "wof:name":"Maison Albert Sounit S.a.r.l.",
    "wof:placetype":"venue"
},
  "geometry": {"coordinates":[4.742191,46.871616],"type":"Point"}
}