{
  "type": "Feature",
  "properties": {
    "addr:full":"31, Quai de Beauvais, 59280 Armenti\u00e8res Nord Pas-de-Calais",
    "addr:housenumber":"31",
    "addr:postcode":"59280",
    "addr:street":"Quai De Beauvais",
    "iso:country":"FR",
    "sg:address":"31, Quai de Beauvais, 59280 Armenti\u00e8res",
    "sg:orig_category":"Unclassifiable Establishments",
    "sg:phone":"+33 3 20 35 45 00",
    "sg:province":"Nord Pas-de-Calais",
    "wof:name":"C.a.t. Les Ateliers De La Lys - Centre D'aide Par Le Travail",
    "wof:placetype":"venue"
},
  "geometry": {"coordinates":[2.884687,50.688286],"type":"Point"}
}