{
  "type": "Feature",
  "properties": {
    "addr:full":"299, Rue Aristide Briand, 76600 Le Havre Haute Normandie",
    "addr:housenumber":"299",
    "addr:postcode":"76600",
    "addr:street":"Rue Aristide Briand",
    "iso:country":"FR",
    "sg:address":"299, Rue Aristide Briand, 76600 Le Havre",
    "sg:orig_category":"Non-Classified Establishments",
    "sg:phone":"+33 2 35 26 72 22",
    "sg:province":"Haute Normandie",
    "wof:name":"Sonatec S.a.",
    "wof:placetype":"venue"
},
  "geometry": {"coordinates":[0.137629,49.500484],"type":"Point"}
}