{
  "type": "Feature",
  "properties": {
    "iso:country":"FR",
    "sg:address":"B.P. 21, 55300 Saint Mihiel^^26, Av de la 40\u00e8me Division, 55300 Saint Mihiel",
    "sg:orig_category":"Non-Classified Establishments",
    "sg:phone":"+33 3 29 89 06 88",
    "sg:province":"Lorraine",
    "wof:name":"Kostka France S.a.",
    "wof:placetype":"venue"
},
  "geometry": {"coordinates":[5.541056,48.891834],"type":"Point"}
}