{
  "type": "Feature",
  "properties": {
    "iso:country":"FR",
    "sg:address":"Chemin Du Cordon",
    "sg:city":"De Montebello 78350 Jouy En Josas",
    "sg:classifiers":[
        {
            "category":"Professional",
            "subcategory":"Computer Services",
            "type":"Services"
        }
    ],
    "sg:phone":"+33 1 46 11 70 00",
    "sg:postcode":"78350",
    "sg:province":"Ile de France",
    "sg:tags":[
        "information",
        "technology",
        "software"
    ],
    "wof:name":"Line Data Service Equipe Sarl",
    "wof:placetype":"venue"
},
  "geometry": {"coordinates":[2.162675,48.770805],"type":"Point"}
}