{
  "type": "Feature",
  "properties": {
    "iso:country":"FR",
    "sg:address":"B.P. 807, 27138 Verneuil sur Avre C\u00e9dex^^ZI, 27130 Verneuil sur Avre",
    "sg:orig_category":"Non-Classified Establishments",
    "sg:phone":"+33 2 32 32 84 40",
    "sg:province":"Haute Normandie",
    "wof:name":"Lorin Syst\u00e8mes S.a.",
    "wof:placetype":"venue"
},
  "geometry": {"coordinates":[0.85463,48.701855],"type":"Point"}
}