{
  "type": "Feature",
  "properties": {
    "addr:full":"B.P. 8264, 95801 Cergy Pontoise C\u00e9dex^^5, Rue de la Grande Ourse, 95800 Cergy Ile de France",
    "addr:postcode":"95801;95800;ile",
    "addr:street":"B.P. 8264;Rue De La Grande Ourse",
    "iso:country":"FR",
    "sg:address":"B.P. 8264, 95801 Cergy Pontoise C\u00e9dex^^5, Rue de la Grande Ourse, 95800 Cergy",
    "sg:orig_category":"Non-Classified Establishments",
    "sg:phone":"+33 1 34 41 60 00",
    "sg:province":"Ile de France",
    "wof:name":"Great Lakes Chemical France S.a.s.",
    "wof:placetype":"venue"
},
  "geometry": {"coordinates":[2.000455,49.035156],"type":"Point"}
}