{
  "type": "Feature",
  "properties": {
    "addr:full":"11, Parc Ariane - Immeuble le Triton, 78284 Guyancourt C\u00e9dex Ancourt Haute Normandie 76370",
    "addr:housenumber":"11",
    "addr:postcode":"78284;76370",
    "addr:street":"Parc Ariane Immeuble Le Triton;Haute Normandie",
    "iso:country":"FR",
    "sg:address":"11, Parc Ariane - Immeuble le Triton, 78284 Guyancourt C\u00e9dex",
    "sg:city":"Ancourt",
    "sg:orig_category":"Non-Classified Establishments",
    "sg:phone":"+33 1 61 08 48 60",
    "sg:postcode":"76370",
    "sg:province":"Haute Normandie",
    "wof:name":"Allshare S.a.",
    "wof:placetype":"venue"
},
  "geometry": {"coordinates":[2.058947,48.78717],"type":"Point"}
}