{
  "type": "Feature",
  "properties": {
    "iso:country":"FR",
    "sg:address":"Rue Haussmann Zi Du Pradas 09190 Lorp Sentaraille",
    "sg:classifiers":[
        {
            "category":"Health Services",
            "subcategory":"Medical Lab",
            "type":"Services"
        }
    ],
    "sg:phone":"+33 5 61 04 81 42",
    "sg:postcode":"09190",
    "sg:province":"Midi Pyr\u00e9n\u00e9es",
    "sg:tags":[
        "chemical",
        "pharmaceutical",
        "pharmacy"
    ],
    "wof:name":"Bioeurope Industries",
    "wof:placetype":"venue"
},
  "geometry": {"coordinates":[1.121569,43.014156],"type":"Point"}
}