{
  "type": "Feature",
  "properties": {
    "iso:country":"FR",
    "sg:address":"6 Avenue Montaigne 75008 Paris",
    "sg:classifiers":[
        {
            "category":"Travel",
            "subcategory":"Hotels & Motels",
            "type":"Entertainment"
        }
    ],
    "sg:phone":"+33 1 47 20 30 50",
    "sg:postcode":"75008",
    "sg:province":"Ile de France",
    "sg:tags":[
        "hotels",
        "business",
        "restaurant"
    ],
    "wof:name":"Montaigne Hotel",
    "wof:placetype":"venue"
},
  "geometry": {"coordinates":[2.303569,48.865311],"type":"Point"}
}