{
  "type": "Feature",
  "properties": {
    "addr:full":"Rue de l'Industrie - ZAC des Mont\u00e9es Orl\u00e9ans C\u00e9dex 2 Aquitaine 45073",
    "addr:housenumber":"2",
    "addr:postcode":"45073",
    "addr:street":"Rue De L'Industrie Zac Des Monte\u0301Es",
    "iso:country":"FR",
    "sg:address":"Rue de l'Industrie - ZAC des Mont\u00e9es",
    "sg:city":"Orl\u00e9ans C\u00e9dex 2",
    "sg:orig_category":"Non-Classified Establishments",
    "sg:phone":"+33 2 38 56 02 38",
    "sg:postcode":"45073",
    "sg:province":"Aquitaine",
    "wof:name":"E.r.g.b. S.a. - Etude R\u00e9alisation G\u00e9n\u00e9rale B\u00e2timent",
    "wof:placetype":"venue"
},
  "geometry": {"coordinates":[1.910307,47.879581],"type":"Point"}
}