{
  "type": "Feature",
  "properties": {
    "iso:country":"FR",
    "sg:address":"B.P. 2089, 69616 Villeurbanne C\u00e9dex^^2, Bd du 11 Novembre, 69100 Villeurbanne",
    "sg:orig_category":"Non-Classified Establishments",
    "sg:phone":"+33 4 78 17 37 50",
    "sg:postcode":"69100",
    "sg:province":"Rhone-Alpes",
    "wof:name":"Adetec S.a.",
    "wof:placetype":"venue"
},
  "geometry": {"coordinates":[4.87905,45.769596],"type":"Point"}
}