{
  "type": "Feature",
  "properties": {
    "iso:country":"FR",
    "sg:address":"Za Les Terreaux 25620 Mamirolle",
    "sg:classifiers":[
        {
            "category":"Wholesale",
            "subcategory":"Machinery & Supplies",
            "type":"Manufacturing & Wholesale Goods"
        }
    ],
    "sg:phone":"+33 3 81 55 78 79",
    "sg:province":"Franche Comt\u00e9",
    "sg:tags":[
        "equipment",
        "equipement",
        "precision",
        "timekeeping"
    ],
    "wof:name":"Pretre Et Fils",
    "wof:placetype":"venue"
},
  "geometry": {"coordinates":[6.162851,47.19738],"type":"Point"}
}