{
  "type": "Feature",
  "properties": {
    "iso:country":"FR",
    "sg:address":"18 -20 R De La Retardais BP 32063 35920 Rennes",
    "sg:classifiers":[
        {
            "category":"Manufacturing",
            "subcategory":"Printing",
            "type":"Manufacturing & Wholesale Goods"
        }
    ],
    "sg:phone":"+33 2 99 59 35 26",
    "sg:province":"Brittany",
    "sg:tags":[
        "publishing"
    ],
    "wof:name":"Imprimerie Technique Moderne",
    "wof:placetype":"venue"
},
  "geometry": {"coordinates":[-1.728785,48.105396],"type":"Point"}
}