{
  "type": "Feature",
  "properties": {
    "addr:full":"1 Rue Gay Lussac 25007 Besan\u00e7on Cedex Champagne",
    "addr:housenumber":"1",
    "addr:postcode":"25007",
    "addr:street":"Rue Gay Lussac",
    "iso:country":"FR",
    "sg:address":"1 Rue Gay Lussac 25007 Besan\u00e7on Cedex",
    "sg:classifiers":[
        {
            "category":"Banks & Credit Unions",
            "subcategory":"Investment Brokerage",
            "type":"Services"
        }
    ],
    "sg:phone":"+33 3 81 50 34 23",
    "sg:province":"Champagne",
    "sg:tags":[
        "business",
        "equipement",
        "advice",
        "precision",
        "timekeeping",
        "equipment"
    ],
    "wof:name":"Reparalux",
    "wof:placetype":"venue"
},
  "geometry": {"coordinates":[5.989174,47.237965],"type":"Point"}
}