{
  "type": "Feature",
  "properties": {
    "iso:country":"FR",
    "sg:address":"B.P. 168, 06510 Carros C\u00e9dex^^LID 1\u00e8re Avenue, 06510 Carros",
    "sg:orig_category":"Non-Classified Establishments",
    "sg:phone":"+33 4 93 29 20 01",
    "sg:province":"Corse",
    "wof:name":"F.j. Belmonte S.a.r.l.",
    "wof:placetype":"venue"
},
  "geometry": {"coordinates":[7.17573,43.785782],"type":"Point"}
}