{
  "type": "Feature",
  "properties": {
    "iso:country":"FR",
    "sg:address":"48, Chemin de la Guay\u00e8re, 91310 Longpont sur Orge",
    "sg:orig_category":"Non-Classified Establishments",
    "sg:phone":"+33 1 69 01 29 43",
    "sg:postcode":"91310",
    "sg:province":"Ile de France",
    "wof:name":"Bonnal S.a.r.l.",
    "wof:placetype":"venue"
},
  "geometry": {"coordinates":[2.283739,48.634041],"type":"Point"}
}