{
  "type": "Feature",
  "properties": {
    "iso:country":"FR",
    "sg:address":"1022 Rue F\u00e9lix Faure 76320 Caudebec Les Elbeuf",
    "sg:classifiers":[
        {
            "category":"Professional",
            "subcategory":"Computer Services",
            "type":"Services"
        }
    ],
    "sg:phone":"+33 2 35 81 80 00",
    "sg:postcode":"76320",
    "sg:province":"Haute Normandie",
    "sg:tags":[
        "information",
        "technology",
        "software"
    ],
    "wof:name":"A D D S Concept Sa",
    "wof:placetype":"venue"
},
  "geometry": {"coordinates":[1.02362,49.287342],"type":"Point"}
}