{
  "type": "Feature",
  "properties": {
    "addr:full":"ZI Ancy le Franc Bourgogne 89160",
    "addr:housenumber":"ancy",
    "addr:postcode":"89160",
    "addr:street":"Le Franc Bourgogne",
    "iso:country":"FR",
    "sg:address":"ZI",
    "sg:city":"Ancy le Franc",
    "sg:orig_category":"Unclassifiable Establishments",
    "sg:phone":"+33 3 86 75 14 42",
    "sg:postcode":"89160",
    "sg:province":"Bourgogne",
    "wof:name":"T\u00f4lerie M\u00e9canique Service S.a.r.l.",
    "wof:placetype":"venue"
},
  "geometry": {"coordinates":[4.16385,47.775414],"type":"Point"}
}