{
  "type": "Feature",
  "properties": {
    "iso:country":"FR",
    "sg:address":"Zone Artisanale 01340 Attignat",
    "sg:classifiers":[
        {
            "category":"Professional",
            "type":"Services"
        }
    ],
    "sg:phone":"+33 4 74 25 11 11",
    "sg:province":"Rhone-Alpes",
    "sg:tags":[
        "transport",
        "road"
    ],
    "wof:name":"Transports Georges Chenaux Sa",
    "wof:placetype":"venue"
},
  "geometry": {"coordinates":[5.16116,46.284721],"type":"Point"}
}