{
  "type": "Feature",
  "properties": {
    "addr:full":"13, Rue Andr\u00e9 Theuriet, 55000 Bar le Duc Lorraine",
    "addr:housenumber":"13",
    "addr:postcode":"55000",
    "addr:street":"Rue Andre\u0301 Theuriet;Le Duc",
    "iso:country":"FR",
    "sg:address":"13, Rue Andr\u00e9 Theuriet, 55000 Bar le Duc",
    "sg:orig_category":"Unclassifiable Establishments",
    "sg:phone":"+33 3 29 79 15 30",
    "sg:province":"Lorraine",
    "wof:name":"Menuiserie Barroise S.a.r.l.",
    "wof:placetype":"venue"
},
  "geometry": {"coordinates":[5.163376,48.77425],"type":"Point"}
}