{
  "type": "Feature",
  "properties": {
    "addr:full":"68/70, Rue des Ronzi\u00e8res, 63037 Clermont Ferrand C\u00e9dex 1 Clermont Rhone-Alpes 74270",
    "addr:housenumber":"68 / 70;1",
    "addr:postcode":"63037;74270",
    "addr:street":"Rue Des Ronzie\u0300Res;Ce\u0301Dex",
    "iso:country":"FR",
    "sg:address":"68/70, Rue des Ronzi\u00e8res, 63037 Clermont Ferrand C\u00e9dex 1",
    "sg:city":"Clermont",
    "sg:orig_category":"Non-Classified Establishments",
    "sg:phone":"+33 4 73 98 32 50",
    "sg:postcode":"74270",
    "sg:province":"Rhone-Alpes",
    "wof:name":"Entreprise Mazet Et Compagnie S.a.",
    "wof:placetype":"venue"
},
  "geometry": {"coordinates":[3.129311,45.775578],"type":"Point"}
}