{
  "type": "Feature",
  "properties": {
    "iso:country":"FR",
    "sg:address":"340, Av de la Marne, 59700 Marcq en Baroeul",
    "sg:orig_category":"Unclassifiable Establishments",
    "sg:phone":"+33 3 20 99 79 79",
    "sg:province":"Nord Pas-de-Calais",
    "wof:name":"D.m.v. S.a.",
    "wof:placetype":"venue"
},
  "geometry": {"coordinates":[3.115158,50.679897],"type":"Point"}
}