{
  "type": "Feature",
  "properties": {
    "addr:full":"65/71, Rue Henri Gautier - ZI les Vignes, 93012 Bobigny C\u00e9dex Bobigny Ile de France 93000",
    "addr:housenumber":"65 / 71",
    "addr:postcode":"93012;93000",
    "addr:street":"Rue Henri Gautier Zi Les Vignes",
    "iso:country":"FR",
    "sg:address":"65/71, Rue Henri Gautier - ZI les Vignes, 93012 Bobigny C\u00e9dex",
    "sg:city":"Bobigny",
    "sg:orig_category":"Non-Classified Establishments",
    "sg:phone":"+33 1 48 10 26 10",
    "sg:postcode":"93000",
    "sg:province":"Ile de France",
    "wof:name":"La G\u00e9n\u00e9rale Industrie S.a.",
    "wof:placetype":"venue"
},
  "geometry": {"coordinates":[2.44049,48.906429],"type":"Point"}
}