{
  "type": "Feature",
  "properties": {
    "addr:full":"Z I num\u00e9ro 2 37110 CHATEAU RENAULT Autr\u00e8che Centre 37110",
    "addr:housenumber":"2;autre\u0300che",
    "addr:postcode":"37110",
    "addr:street":"Z I Nume\u0301Ro",
    "iso:country":"FR",
    "sg:address":"Z I num\u00e9ro 2 37110 CHATEAU RENAULT",
    "sg:city":"Autr\u00e8che",
    "sg:classifiers":[
        {
            "category":"Manufacturing",
            "subcategory":"Motor Vehicles & Parts",
            "type":"Manufacturing & Wholesale Goods"
        }
    ],
    "sg:phone":"+33 2 47 29 51 42",
    "sg:postcode":"37110",
    "sg:province":"Centre",
    "sg:tags":[
        "precision",
        "mechanic"
    ],
    "wof:name":"Ste Industrielle M\u00e9canique Appliqu\u00e9e S.a.",
    "wof:placetype":"venue"
},
  "geometry": {"coordinates":[0.99705,47.524975],"type":"Point"}
}