{
  "type": "Feature",
  "properties": {
    "addr:full":"64160 Monassut Audiracq Cosl\u00e9da\u00e0-Lube-Boast Aquitaine 64160",
    "addr:housenumber":"cosle\u0301daa\u0300-lube-boast",
    "addr:postcode":"64160;64160",
    "iso:country":"FR",
    "sg:address":"64160 Monassut Audiracq",
    "sg:city":"Cosl\u00e9da\u00e0-Lube-Boast",
    "sg:classifiers":[
        {
            "category":"Shopping",
            "subcategory":"Crafts & Fabrics",
            "type":"Retail Goods"
        }
    ],
    "sg:phone":"+33 5 59 77 41 38",
    "sg:postcode":"64160",
    "sg:province":"Aquitaine",
    "sg:tags":[
        "textile",
        "clothing"
    ],
    "wof:name":"J Moura Et Fils",
    "wof:placetype":"venue"
},
  "geometry": {"coordinates":[-0.19567,43.419563],"type":"Point"}
}