{
  "type": "Feature",
  "properties": {
    "addr:full":"R Lavosier Zi Sud BP 33 37130 Langeais Langeais Centre 37130",
    "addr:postcode":"37130;37130",
    "addr:street":"Zi;Bp 33",
    "iso:country":"FR",
    "sg:address":"R Lavosier Zi Sud BP 33 37130 Langeais",
    "sg:city":"Langeais",
    "sg:classifiers":[
        {
            "category":"Shopping",
            "subcategory":"Hobbies, Toys, & Games",
            "type":"Retail Goods"
        }
    ],
    "sg:phone":"+33 2 47 96 18 00",
    "sg:postcode":"37130",
    "sg:province":"Centre",
    "sg:tags":[
        "product",
        "miscellaneous",
        "entertainment"
    ],
    "wof:name":"Corolle Sa",
    "wof:placetype":"venue"
},
  "geometry": {"coordinates":[0.302169,47.285252],"type":"Point"}
}