{
  "type": "Feature",
  "properties": {
    "addr:full":"10 Rue Gutenberg Zi Du Brezet 63100 Clermont Ferrand Clermont-Ferrand Auvergne 63100",
    "addr:housenumber":"10",
    "addr:postcode":"63100;63100",
    "addr:street":"Rue Gutenberg Zi Du Brezet",
    "iso:country":"FR",
    "sg:address":"10 Rue Gutenberg Zi Du Brezet 63100 Clermont Ferrand",
    "sg:city":"Clermont-Ferrand",
    "sg:classifiers":[
        {
            "category":"Manufacturing",
            "subcategory":"Tools & Machinery",
            "type":"Manufacturing & Wholesale Goods"
        }
    ],
    "sg:phone":"+33 4 73 98 98 89",
    "sg:postcode":"63100",
    "sg:province":"Auvergne",
    "sg:tags":[
        "metallurgy",
        "metalworking"
    ],
    "wof:name":"Lba",
    "wof:placetype":"venue"
},
  "geometry": {"coordinates":[2.09017,43.151814],"type":"Point"}
}