{
  "type": "Feature",
  "properties": {
    "iso:country":"FR",
    "sg:address":"Route De Saint Pons 34600 Bedarieux",
    "sg:classifiers":[
        {
            "category":"Manufacturing",
            "subcategory":"Glass & Minerals",
            "type":"Manufacturing & Wholesale Goods"
        }
    ],
    "sg:phone":"+33 4 67 95 00 32",
    "sg:postcode":"34600",
    "sg:province":"Languedoc-Roussillon",
    "sg:tags":[
        "building",
        "material"
    ],
    "wof:name":"Bdi Societe Par Actions Simplifiee",
    "wof:placetype":"venue"
},
  "geometry": {"coordinates":[3.159445,43.61549],"type":"Point"}
}