{
  "type": "Feature",
  "properties": {
    "iso:country":"FR",
    "sg:address":"Le Grand Moulin 37510 Ballan Mir\u00e9",
    "sg:city":"Ballan-Mir\u00e9",
    "sg:classifiers":[
        {
            "category":"Food & Beverages",
            "subcategory":"Groceries & Convenience Stores",
            "type":"Retail Goods"
        }
    ],
    "sg:phone":"+33 2 47 53 00 15",
    "sg:postcode":"37510",
    "sg:province":"Centre",
    "sg:tags":[
        "product",
        "grain",
        "cereal",
        "related"
    ],
    "wof:name":"Grand Moulin De Ballan",
    "wof:placetype":"venue"
},
  "geometry": {"coordinates":[0.605976,47.361446],"type":"Point"}
}