{
  "type": "Feature",
  "properties": {
    "iso:country":"FR",
    "sg:address":"Le Village 01800 Rignieux Le Franc",
    "sg:classifiers":[
        {
            "category":"Shopping",
            "type":"Retail Goods"
        }
    ],
    "sg:phone":"+33 4 74 46 08 70",
    "sg:postcode":"01800",
    "sg:province":"Rhone-Alpes",
    "sg:tags":[
        "metallurgy",
        "finished",
        "-",
        "metalworking",
        "metallic"
    ],
    "wof:name":"Thimeca Sa",
    "wof:placetype":"venue"
},
  "geometry": {"coordinates":[5.18087,45.897339],"type":"Point"}
}