{
  "type": "Feature",
  "properties": {
    "iso:country":"FR",
    "sg:address":"60, Rue du Commandant Gustave Gat\u00e9, 44600 Saint Nazaire",
    "sg:orig_category":"Unclassifiable Establishments",
    "sg:phone":"+33 2 40 70 52 24",
    "sg:province":"Pays de Loire",
    "wof:name":"C.s.o. S.a. - Comptoir Du Sud Ouest",
    "wof:placetype":"venue"
},
  "geometry": {"coordinates":[-2.222445,47.27626],"type":"Point"}
}