{
  "type": "Feature",
  "properties": {
    "iso:country":"FR",
    "sg:address":"B.P. 2, 59178 Hasnon^^5, Rue Olivier de Guise, 59178 Hasnon",
    "sg:orig_category":"Non-Classified Establishments",
    "sg:phone":"+33 3 27 48 30 00",
    "sg:province":"Nord Pas-de-Calais",
    "wof:name":"Lauwers Emballages S.a.r.l.",
    "wof:placetype":"venue"
},
  "geometry": {"coordinates":[3.387112,50.416573],"type":"Point"}
}