{
  "type": "Feature",
  "properties": {
    "addr:full":"21, Av. Michel Cr\u00e9peau, 17000 La Rochelle Poitou-Charentes",
    "addr:postcode":"17000",
    "addr:street":"21 Av. Michel Cre\u0301Peau",
    "iso:country":"FR",
    "sg:address":"21, Av. Michel Cr\u00e9peau, 17000 La Rochelle",
    "sg:orig_category":"Non-Classified Establishments",
    "sg:phone":"+33 5 46 07 76 60",
    "sg:province":"Poitou-Charentes",
    "wof:name":"S.e.c.d.a. S.a. - Soci\u00e9t\u00e9 D'expertise Comptable Atlantique",
    "wof:placetype":"venue"
},
  "geometry": {"coordinates":[-1.155333,46.153385],"type":"Point"}
}