{
  "type": "Feature",
  "properties": {
    "iso:country":"FR",
    "sg:address":"11/13, Cours Valmy, 92070 Paris la D\u00e9fence C\u00e9dex",
    "sg:orig_category":"Non-Classified Establishments",
    "sg:phone":"+33 1 41 25 58 00",
    "sg:province":"Midi Pyr\u00e9n\u00e9es",
    "wof:name":"Sersid S.a.r.l.",
    "wof:placetype":"venue"
},
  "geometry": {"coordinates":[2.208,48.896141],"type":"Point"}
}