{
  "type": "Feature",
  "properties": {
    "iso:country":"FR",
    "sg:address":"rue de la Corne d'Abondance 74100 Ville la Grand",
    "sg:classifiers":[
        {
            "category":"Home & Garden",
            "subcategory":"Building Materials",
            "type":"Retail Goods"
        }
    ],
    "sg:phone":"+33 4 50 95 52 48",
    "sg:postcode":"74100",
    "sg:province":"Rhone-Alpes",
    "sg:tags":[
        "ready-mixed",
        "fresh",
        "concrete"
    ],
    "wof:name":"Kristo Sa",
    "wof:placetype":"venue"
},
  "geometry": {"coordinates":[6.264246,46.201553],"type":"Point"}
}