{
  "type": "Feature",
  "properties": {
    "iso:country":"FR",
    "sg:address":"5, Av. Marcel Cerdan, 69100 Villeurbanne",
    "sg:orig_category":"Unclassifiable Establishments",
    "sg:phone":"+33 4 78 84 29 60",
    "sg:postcode":"69100",
    "sg:province":"Rhone-Alpes",
    "wof:name":"Acfal - Foramtion",
    "wof:placetype":"venue"
},
  "geometry": {"coordinates":[4.903841,45.766506],"type":"Point"}
}