{
  "type": "Feature",
  "properties": {
    "iso:country":"FR",
    "sg:address":"6 Route De Neaux 53600 Evron",
    "sg:classifiers":[
        {
            "category":"Farming",
            "subcategory":"Farm",
            "type":"Manufacturing & Wholesale Goods"
        }
    ],
    "sg:phone":"+33 2 43 01 33 26",
    "sg:postcode":"53600",
    "sg:province":"Pays de Loire",
    "sg:tags":[
        "horticulture",
        "agriculture",
        "livestock"
    ],
    "wof:name":"Etablissements Horticoles Choupeaux",
    "wof:placetype":"venue"
},
  "geometry": {"coordinates":[-0.432901,48.132961],"type":"Point"}
}