{
  "type": "Feature",
  "properties": {
    "iso:country":"FR",
    "sg:address":"20, Roc Lacroix Saint Georges, 77600 Bussy Saint Georges",
    "sg:orig_category":"Non-Classified Establishments",
    "sg:phone":"+33 1 64 66 18 23",
    "sg:province":"Ile de France",
    "wof:name":"L.g.f. S.a.r.l. - La Gravure Ferri\u00e9roise",
    "wof:placetype":"venue"
},
  "geometry": {"coordinates":[2.702625,48.840481],"type":"Point"}
}