{
  "type": "Feature",
  "properties": {
    "addr:full":"Zi 26205 Mont\u00e9limar Aquitaine",
    "addr:postcode":"26205",
    "addr:street":"Zi",
    "iso:country":"FR",
    "sg:address":"Zi 26205 Mont\u00e9limar",
    "sg:classifiers":[
        {
            "category":"Professional",
            "type":"Services"
        }
    ],
    "sg:phone":"+33 4 75 00 72 26",
    "sg:province":"Aquitaine",
    "sg:tags":[
        "transport",
        "road"
    ],
    "wof:name":"Mazet",
    "wof:placetype":"venue"
},
  "geometry": {"coordinates":[4.74916,44.555592],"type":"Point"}
}