{
  "type": "Feature",
  "properties": {
    "addr:full":"Route De L'Ecluse Watier 59140 Dunkerque Nord Pas-de-Calais 59140",
    "addr:postcode":"59140;59140",
    "addr:street":"Route De L'Ecluse Watier",
    "iso:country":"FR",
    "sg:address":"Route De L'Ecluse Watier 59140 Dunkerque",
    "sg:classifiers":[
        {
            "category":"Shopping",
            "type":"Retail Goods"
        }
    ],
    "sg:phone":"+33 3 28 65 90 00",
    "sg:postcode":"59140",
    "sg:province":"Nord Pas-de-Calais",
    "sg:tags":[
        "metallurgy",
        "finished",
        "-",
        "metalworking",
        "metallic"
    ],
    "wof:name":"Societe De Constructions De Reparations Navales Et De Mecani (socarenam)",
    "wof:placetype":"venue"
},
  "geometry": {"coordinates":[2.354474,51.051697],"type":"Point"}
}