{
  "type": "Feature",
  "properties": {
    "iso:country":"FR",
    "sg:address":"12100 St Georges De Luzencon",
    "sg:classifiers":[
        {
            "category":"Professional",
            "subcategory":"Business Services",
            "type":"Services"
        }
    ],
    "sg:phone":"+33 5 65 61 19 02",
    "sg:postcode":"12100",
    "sg:province":"Midi Pyr\u00e9n\u00e9es",
    "sg:tags":[
        "travel",
        "transport",
        "road"
    ],
    "wof:name":"Autocars Causse",
    "wof:placetype":"venue"
},
  "geometry": {"coordinates":[2.98414,44.063969],"type":"Point"}
}