{
  "type": "Feature",
  "properties": {
    "addr:full":"162, Rte de Strasbourg, 69140 Rillieux la Pape Rhone-Alpes 69140",
    "addr:housenumber":"162",
    "addr:postcode":"69140;69140",
    "addr:street":"Rte De Strasbourg",
    "iso:country":"FR",
    "sg:address":"162, Rte de Strasbourg, 69140 Rillieux la Pape",
    "sg:orig_category":"Non-Classified Establishments",
    "sg:phone":"+33 4 78 08 38 22",
    "sg:postcode":"69140",
    "sg:province":"Rhone-Alpes",
    "wof:name":"A1 Pack S.a.r.l.",
    "wof:placetype":"venue"
},
  "geometry": {"coordinates":[4.878572,45.80106],"type":"Point"}
}