{
  "type": "Feature",
  "properties": {
    "addr:full":"77, Rue Corbier Thi\u00e9baut, 60270 Gouvieux Picardie",
    "addr:housenumber":"77",
    "addr:postcode":"60270",
    "addr:street":"Rue Corbier Thie\u0301Baut",
    "iso:country":"FR",
    "sg:address":"77, Rue Corbier Thi\u00e9baut, 60270 Gouvieux",
    "sg:orig_category":"Unclassifiable Establishments",
    "sg:phone":"+33 3 44 67 13 30",
    "sg:province":"Picardie",
    "wof:name":"Atelier M\u00e9canique De Gouvieux S.a.r.l.",
    "wof:placetype":"venue"
},
  "geometry": {"coordinates":[2.41743,49.197266],"type":"Point"}
}