{
  "type": "Feature",
  "properties": {
    "iso:country":"FR",
    "sg:address":"3, Rue du Palais de Justice, 59800 Lille",
    "sg:orig_category":"Non-Classified Establishments",
    "sg:phone":"+33 3 20 12 16 40",
    "sg:province":"Nord Pas-de-Calais",
    "wof:name":"Interleasing France S.a.r.l.",
    "wof:placetype":"venue"
},
  "geometry": {"coordinates":[3.06218,50.64175],"type":"Point"}
}