{
  "type": "Feature",
  "properties": {
    "addr:full":"18 Rue Andr\u00e9 Marie Amp\u00e8re 33560 Carbon Blanc Carbon-Blanc Aquitaine 33560",
    "addr:housenumber":"18",
    "addr:postcode":"33560;33560",
    "addr:street":"Rue Andre\u0301 Marie Ampe\u0300Re;Blanc",
    "iso:country":"FR",
    "sg:address":"18 Rue Andr\u00e9 Marie Amp\u00e8re 33560 Carbon Blanc",
    "sg:city":"Carbon-Blanc",
    "sg:classifiers":[
        {
            "category":"Food Court",
            "type":"Food & Drink"
        }
    ],
    "sg:phone":"+33 5 56 77 81 00",
    "sg:postcode":"33560",
    "sg:province":"Aquitaine",
    "sg:tags":[
        "product",
        "related"
    ],
    "wof:name":"Sovex Grands Chateaux Sa",
    "wof:placetype":"venue"
},
  "geometry": {"coordinates":[-0.489143,44.911911],"type":"Point"}
}