{
  "type": "Feature",
  "properties": {
    "addr:full":"59, Rue des Quatre Termes - ZI les Paluds, 13400 Aubagne Picardie",
    "addr:housenumber":"59",
    "addr:postcode":"13400",
    "addr:street":"Rue Des Quatre Termes Zi Les Paluds",
    "iso:country":"FR",
    "sg:address":"59, Rue des Quatre Termes - ZI les Paluds, 13400 Aubagne",
    "sg:orig_category":"Unclassifiable Establishments",
    "sg:phone":"+33 4 42 82 03 68",
    "sg:province":"Picardie",
    "wof:name":"Vercor S.a.",
    "wof:placetype":"venue"
},
  "geometry": {"coordinates":[5.598311,43.288445],"type":"Point"}
}