{
  "type": "Feature",
  "properties": {
    "addr:full":"RN 7 Saint Andiol Provence-Alpes-C\u00f4te d'Azur 13670",
    "addr:postcode":"13670",
    "addr:street":"Rn 7 Saint Andiol",
    "iso:country":"FR",
    "sg:address":"RN 7",
    "sg:city":"Saint Andiol",
    "sg:orig_category":"Unclassifiable Establishments",
    "sg:phone":"+33 4 90 95 02 44",
    "sg:postcode":"13670",
    "sg:province":"Provence-Alpes-C\u00f4te d'Azur",
    "wof:name":"Provence Mat\u00e9riaux S.a.",
    "wof:placetype":"venue"
},
  "geometry": {"coordinates":[4.94301,43.836479],"type":"Point"}
}