{
  "type": "Feature",
  "properties": {
    "addr:full":"13, Rte de Brumath, 67550 Vendenheim Vendenheim Alsace 67550",
    "addr:housenumber":"13",
    "addr:postcode":"67550;67550",
    "addr:street":"Rte De Brumath",
    "iso:country":"FR",
    "sg:address":"13, Rte de Brumath, 67550 Vendenheim",
    "sg:city":"Vendenheim",
    "sg:orig_category":"Non-Classified Establishments",
    "sg:phone":"+33 3 88 69 42 97",
    "sg:postcode":"67550",
    "sg:province":"Alsace",
    "wof:name":"Schoni S.a.r.l.",
    "wof:placetype":"venue"
},
  "geometry": {"coordinates":[7.71787,48.672459],"type":"Point"}
}