{
  "type": "Feature",
  "properties": {
    "iso:country":"FR",
    "sg:address":"128, Rue Pasteur, 59370 Mons en Baroeul",
    "sg:orig_category":"Unclassifiable Establishments",
    "sg:phone":"+33 3 20 33 02 05",
    "sg:province":"Nord Pas-de-Calais",
    "wof:name":"Typon Grafic S.a.r.l.",
    "wof:placetype":"venue"
},
  "geometry": {"coordinates":[3.10327,50.649769],"type":"Point"}
}