{
  "type": "Feature",
  "properties": {
    "addr:full":"157 Rue Du Temple 75003 Paris Ile de France 75003",
    "addr:housenumber":"157",
    "addr:postcode":"75003;75003",
    "addr:street":"Rue Du Temple",
    "iso:country":"FR",
    "sg:address":"157 Rue Du Temple 75003 Paris",
    "sg:classifiers":[
        {
            "category":"Manufacturing",
            "subcategory":"Jewelry",
            "type":"Manufacturing & Wholesale Goods"
        }
    ],
    "sg:phone":"+33 1 42 72 60 28",
    "sg:postcode":"75003",
    "sg:province":"Ile de France",
    "sg:tags":[
        "product",
        "miscellaneous",
        "jewellery"
    ],
    "wof:name":"Poggi Sa",
    "wof:placetype":"venue"
},
  "geometry": {"coordinates":[2.359145,48.864487],"type":"Point"}
}