{
  "type": "Feature",
  "properties": {
    "addr:full":"B.P. 12, 69290 Gr\u00e9zieu la Varenne^^ZA les Ferri\u00e8res, 69290 Gr\u00e9zieu la Varenne Rhone-Alpes 69290",
    "addr:postcode":"69290;69290;69290",
    "addr:street":"B.P. 12;Varenne^^Za",
    "iso:country":"FR",
    "sg:address":"B.P. 12, 69290 Gr\u00e9zieu la Varenne^^ZA les Ferri\u00e8res, 69290 Gr\u00e9zieu la Varenne",
    "sg:orig_category":"Non-Classified Establishments",
    "sg:phone":"+33 4 78 44 70 80",
    "sg:postcode":"69290",
    "sg:province":"Rhone-Alpes",
    "wof:name":"Guiflex S.a.r.l.",
    "wof:placetype":"venue"
},
  "geometry": {"coordinates":[4.72283,45.747356],"type":"Point"}
}