{
  "type": "Feature",
  "properties": {
    "addr:full":"9, Rue Andr\u00e9 Fruchard, 54320 Max\u00e9ville Lorraine 54320",
    "addr:housenumber":"9",
    "addr:postcode":"54320;54320",
    "addr:street":"Rue Andre\u0301 Fruchard",
    "iso:country":"FR",
    "sg:address":"9, Rue Andr\u00e9 Fruchard, 54320 Max\u00e9ville",
    "sg:orig_category":"Non-Classified Establishments",
    "sg:phone":"+33 3 83 35 92 92",
    "sg:postcode":"54320",
    "sg:province":"Lorraine",
    "wof:name":"C.a.d. S.a.r.l.",
    "wof:placetype":"venue"
},
  "geometry": {"coordinates":[6.169984,48.71492],"type":"Point"}
}