{
  "type": "Feature",
  "properties": {
    "addr:full":"Rn 13 9 78240 Chambourcy Ile de France 78240",
    "addr:housenumber":"9",
    "addr:postcode":"78240;ile;78240",
    "addr:street":"Rn 13;France",
    "iso:country":"FR",
    "sg:address":"Rn 13",
    "sg:city":"9 78240 Chambourcy",
    "sg:classifiers":[
        {
            "category":"Autos & Motor Vehicles",
            "subcategory":"Automobile Sales",
            "type":"Retail Goods"
        }
    ],
    "sg:phone":"+33 1 39 22 31 11",
    "sg:postcode":"78240",
    "sg:province":"Ile de France",
    "sg:tags":[
        "equipment",
        "motor-cars",
        "transport"
    ],
    "wof:name":"Automobiles Peugeot Sa",
    "wof:placetype":"venue"
},
  "geometry": {"coordinates":[2.038427,48.907097],"type":"Point"}
}