{
  "type": "Feature",
  "properties": {
    "addr:full":"42, Rue des 7 Serpents, 93500 Pantin Ile de France",
    "addr:housenumber":"42",
    "addr:postcode":"93500;ile",
    "addr:street":"Rue Des 7 Serpents",
    "iso:country":"FR",
    "sg:address":"42, Rue des 7 Serpents, 93500 Pantin",
    "sg:orig_category":"Non-Classified Establishments",
    "sg:phone":"+33 1 48 44 05 88",
    "sg:province":"Ile de France",
    "wof:name":"Euroscam S.a.r.l.",
    "wof:placetype":"venue"
},
  "geometry": {"coordinates":[2.40168,48.89658],"type":"Point"}
}