{
  "type": "Feature",
  "properties": {
    "iso:country":"FR",
    "sg:address":"ZA d'Hellieule",
    "sg:city":"Saint Di\u00e9",
    "sg:orig_category":"Unclassifiable Establishments",
    "sg:phone":"+33 3 29 55 01 01",
    "sg:postcode":"88100",
    "sg:province":"Lorraine",
    "wof:name":"Claudel Miroiterie S.a.r.l.",
    "wof:placetype":"venue"
},
  "geometry": {"coordinates":[6.942892,48.285076],"type":"Point"}
}