{
  "type": "Feature",
  "properties": {
    "addr:full":"B.P. 48, 69513 Vaulx en Velin C\u00e9dex^^13, Av. Bataillon C Libert\u00e9 - Immeuble la Soie, 69120 Vaulx en  Rhone-Alpes 69120",
    "addr:postcode":"69513;69120;69120",
    "addr:street":"B.P. 48;Av. Bataillon C Liberte\u0301 Immeuble La Soie",
    "iso:country":"FR",
    "sg:address":"B.P. 48, 69513 Vaulx en Velin C\u00e9dex^^13, Av. Bataillon C Libert\u00e9 - Immeuble la Soie, 69120 Vaulx en ",
    "sg:orig_category":"Non-Classified Establishments",
    "sg:phone":"+33 4 72 15 21 40",
    "sg:postcode":"69120",
    "sg:province":"Rhone-Alpes",
    "wof:name":"Citex S.a.",
    "wof:placetype":"venue"
},
  "geometry": {"coordinates":[4.916895,45.779022],"type":"Point"}
}