{
  "type": "Feature",
  "properties": {
    "addr:full":"BP 26 29240 Brest Naval Bretagne",
    "addr:housenumber":"bp 26",
    "addr:postcode":"29240",
    "addr:street":"Naval",
    "iso:country":"FR",
    "sg:address":"BP 26 29240 Brest Naval",
    "sg:classifiers":[
        {
            "category":"Autos & Motor Vehicles",
            "subcategory":"Boat Sales",
            "type":"Retail Goods"
        }
    ],
    "sg:phone":"+33 2 98 22 55 54",
    "sg:province":"Bretagne",
    "sg:tags":[
        "equipment",
        "transport"
    ],
    "wof:name":"Dcn Brest",
    "wof:placetype":"venue"
},
  "geometry": {"coordinates":[-4.4869,48.390598],"type":"Point"}
}