{
  "type": "Feature",
  "properties": {
    "addr:full":"B.P. 84218, 06131 Grasse C\u00e9dex^^ZI du Carr\u00e9, 06130 Grasse Provence-Alpes-C\u00f4te d'Azur",
    "addr:postcode":"06131;06130",
    "addr:street":"Grasse",
    "iso:country":"FR",
    "sg:address":"B.P. 84218, 06131 Grasse C\u00e9dex^^ZI du Carr\u00e9, 06130 Grasse",
    "sg:orig_category":"Non-Classified Establishments",
    "sg:phone":"+33 4 93 70 01 69",
    "sg:province":"Provence-Alpes-C\u00f4te d'Azur",
    "wof:name":"Saccof Packaging S.a.",
    "wof:placetype":"venue"
},
  "geometry": {"coordinates":[6.931647,43.649738],"type":"Point"}
}