{
  "type": "Feature",
  "properties": {
    "iso:country":"FR",
    "sg:address":"avenue de l'Industrie 16470 ST MICHEL",
    "sg:classifiers":[
        {
            "category":"Manufacturing",
            "subcategory":"Paper Products",
            "type":"Manufacturing & Wholesale Goods"
        }
    ],
    "sg:phone":"+33 5 45 25 17 20",
    "sg:postcode":"16470",
    "sg:province":"Poitou-Charentes",
    "sg:tags":[
        "cardboard",
        "package"
    ],
    "wof:name":"Otor Papeterie Saint Michel S.a.r.l.",
    "wof:placetype":"venue"
},
  "geometry": {"coordinates":[0.107095,45.649818],"type":"Point"}
}