{
  "type": "Feature",
  "properties": {
    "addr:full":"121, Rue H. de Chardonnet - ZI Technisud, 38029 Grenoble C\u00e9dex 2 Franche Comt\u00e9",
    "addr:housenumber":"121;2",
    "addr:postcode":"38029",
    "addr:street":"Rue H. De Chardonnet Zi Technisud;Franche Comte\u0301",
    "iso:country":"FR",
    "sg:address":"121, Rue H. de Chardonnet - ZI Technisud, 38029 Grenoble C\u00e9dex 2",
    "sg:orig_category":"Non-Classified Establishments",
    "sg:phone":"+33 4 38 49 92 92",
    "sg:province":"Franche Comt\u00e9",
    "wof:name":"Ademis S.a.r.l.",
    "wof:placetype":"venue"
},
  "geometry": {"coordinates":[5.72557,45.189621],"type":"Point"}
}