{
  "type": "Feature",
  "properties": {
    "addr:full":"18 rue de Sarreguemines; Bitche; 57232 Languedoc-Roussillon",
    "addr:housenumber":"18",
    "addr:postcode":"57232",
    "addr:street":"Rue De Sarreguemines",
    "iso:country":"FR",
    "sg:address":"18 rue de Sarreguemines; Bitche; 57232",
    "sg:classifiers":[
        {
            "category":"Banks & Credit Unions",
            "subcategory":"Bank",
            "type":"Services"
        }
    ],
    "sg:phone":"+33 3 87 96 00 47",
    "sg:province":"Languedoc-Roussillon",
    "wof:name":"Cr\u00e9dit Industriel D'alsace, Et De Lorraine Sa",
    "wof:placetype":"venue"
},
  "geometry": {"coordinates":[7.42021,49.05394],"type":"Point"}
}