{
  "type": "Feature",
  "properties": {
    "iso:country":"FR",
    "sg:address":"avenue de Layats 64500 ST JEAN DE LUZ",
    "sg:city":"Ciboure",
    "sg:classifiers":[
        {
            "category":"Wholesale",
            "subcategory":"Medical Equipment & Supplies",
            "type":"Manufacturing & Wholesale Goods"
        }
    ],
    "sg:phone":"+33 5 59 51 90 90",
    "sg:postcode":"64500",
    "sg:province":"Aquitaine",
    "sg:tags":[
        "instrument",
        "surgical"
    ],
    "wof:name":"B. Braun Medical Sa",
    "wof:placetype":"venue"
},
  "geometry": {"coordinates":[-1.638014,43.399326],"type":"Point"}
}