{
  "type": "Feature",
  "properties": {
    "iso:country":"FR",
    "sg:address":"Ld Les Saurondes 49400 St Hilaire St Florent",
    "sg:classifiers":[
        {
            "category":"Manufacturing",
            "subcategory":"Leather Goods",
            "type":"Manufacturing & Wholesale Goods"
        }
    ],
    "sg:phone":"+33 2 41 67 12 45",
    "sg:postcode":"49400",
    "sg:province":"Pays de Loire",
    "sg:tags":[
        "shoe"
    ],
    "wof:name":"Butet Frederic Sa",
    "wof:placetype":"venue"
},
  "geometry": {"coordinates":[-92.474236,47.611626],"type":"Point"}
}