{
  "type": "Feature",
  "properties": {
    "iso:country":"FR",
    "sg:address":"20, Bd du Parc, 92521 Neuilly sur Seine C\u00e9dex",
    "sg:orig_category":"Non-Classified Establishments",
    "sg:phone":"+33 1 41 43 32 00",
    "sg:province":"\u00cele-de-France",
    "wof:name":"Parfums Van Cleef Et Arpels S.a.",
    "wof:placetype":"venue"
},
  "geometry": {"coordinates":[2.265143,48.893681],"type":"Point"}
}