{
  "type": "Feature",
  "properties": {
    "iso:country":"FR",
    "sg:address":"Quartier des Iles, 07370 Sarras C\u00e9dex^^Quartier des Iles, 07370 Sarras",
    "sg:orig_category":"Non-Classified Establishments",
    "sg:phone":"+33 4 75 23 27 11",
    "sg:postcode":"07370",
    "sg:province":"Rhone-Alpes",
    "wof:name":"Vuitton Atelier Sud Est",
    "wof:placetype":"venue"
},
  "geometry": {"coordinates":[4.78432,45.169788],"type":"Point"}
}