{
  "type": "Feature",
  "properties": {
    "addr:full":"quartier de la Grave 84210 Althen des Paluds",
    "addr:postcode":"84210",
    "addr:street":"Quartier;La Grave;Des Paluds",
    "iso:country":"FR",
    "sg:address":"quartier de la Grave 84210 Althen des Paluds",
    "sg:orig_category":"Apples, Fresh",
    "sg:phone":"+33 4 90 62 01 54",
    "wof:name":"Etablissements Pidoux S.a.r.l.",
    "wof:placetype":"venue"
},
  "geometry": {"coordinates":[4.95905,43.996609],"type":"Point"}
}