{
  "type": "Feature",
  "properties": {
    "addr:full":"6, Rue Lemercier, 76320 Caudebec les Elbeuf Haute Normandie",
    "addr:housenumber":"6",
    "addr:postcode":"76320",
    "addr:street":"Rue Lemercier;Haute Normandie",
    "iso:country":"FR",
    "sg:address":"6, Rue Lemercier, 76320 Caudebec les Elbeuf",
    "sg:orig_category":"Unclassifiable Establishments",
    "sg:phone":"+33 2 35 78 22 22",
    "sg:province":"Haute Normandie",
    "wof:name":"Seine Impressions S.a.r.l.",
    "wof:placetype":"venue"
},
  "geometry": {"coordinates":[1.01608,49.283875],"type":"Point"}
}