{
  "type": "Feature",
  "properties": {
    "iso:country":"FR",
    "sg:address":"Zi Du District 85600 St Georges De Montaigu",
    "sg:classifiers":[
        {
            "category":"Manufacturing",
            "subcategory":"Metals",
            "type":"Manufacturing & Wholesale Goods"
        }
    ],
    "sg:phone":"+33 2 51 09 25 25",
    "sg:postcode":"85600",
    "sg:province":"Pays de Loire",
    "sg:tags":[
        "-",
        "machine",
        "equipment",
        "engineering",
        "machinery",
        "mechanical"
    ],
    "wof:name":"Societe De Materiaux Et Techniques Composites Smtc",
    "wof:placetype":"venue"
},
  "geometry": {"coordinates":[-1.29668,46.947796],"type":"Point"}
}