{
  "type": "Feature",
  "properties": {
    "iso:country":"FR",
    "sg:address":"1bis, Ancienne Route de Paris, 60000 Allonne",
    "sg:orig_category":"Unclassifiable Establishments",
    "sg:phone":"+33 3 44 02 86 00",
    "sg:province":"Picardie",
    "wof:name":"Brocard S.a.s.",
    "wof:placetype":"venue"
},
  "geometry": {"coordinates":[2.111895,49.407219],"type":"Point"}
}