{
  "type": "Feature",
  "properties": {
    "iso:country":"FR",
    "sg:address":"Za Les Rosaies Zi 35550 Sixt Sur Aff",
    "sg:city":"Bruc-sur-Aff",
    "sg:classifiers":[
        {
            "category":"Manufacturing",
            "subcategory":"Paper Products",
            "type":"Manufacturing & Wholesale Goods"
        }
    ],
    "sg:phone":"+33 2 99 70 08 70",
    "sg:postcode":"35550",
    "sg:province":"Bretagne",
    "sg:tags":[
        "finished",
        "cardboard",
        "-"
    ],
    "wof:name":"Fa\u00c7onnage Bretagne",
    "wof:placetype":"venue"
},
  "geometry": {"coordinates":[-2.077669,47.776226],"type":"Point"}
}