{
  "type": "Feature",
  "properties": {
    "addr:full":"B.P. 63 Loon Plage Nord Pas-de-Calais 59279",
    "addr:postcode":"59279",
    "addr:street":"B.P. 63;Pas-De-Calais",
    "iso:country":"FR",
    "sg:address":"B.P. 63",
    "sg:city":"Loon Plage",
    "sg:orig_category":"Non-Classified Establishments",
    "sg:phone":"+33 3 28 28 01 01",
    "sg:postcode":"59279",
    "sg:province":"Nord Pas-de-Calais",
    "wof:name":"S.i.m.e.p. S.a.r.l. - Soci\u00e9t\u00e9 D'installation Et De Maintenance D'equipement De Pompage",
    "wof:placetype":"venue"
},
  "geometry": {"coordinates":[2.21998,50.994347],"type":"Point"}
}