{
  "type": "Feature",
  "properties": {
    "iso:country":"FR",
    "sg:address":"B.P. 76, 21802 Quetigny C\u00e9dex^^59, Av de Tavaux, 21800 Chevigny Saint Sauveur",
    "sg:city":"Quetigny",
    "sg:orig_category":"Non-Classified Establishments",
    "sg:phone":"+33 3 80 46 73 00",
    "sg:postcode":"21800",
    "sg:province":"Bourgogne",
    "wof:name":"Soplachim S.a.",
    "wof:placetype":"venue"
},
  "geometry": {"coordinates":[5.135262,47.301807],"type":"Point"}
}