{
  "type": "Feature",
  "properties": {
    "addr:full":"330, Rue Valvire, 50000 Saint L\u00f4 Saint-L\u00f4 Basse Normandie 50000",
    "addr:housenumber":"330",
    "addr:postcode":"50000;50000",
    "addr:street":"Rue Valvire",
    "iso:country":"FR",
    "sg:address":"330, Rue Valvire, 50000 Saint L\u00f4",
    "sg:city":"Saint-L\u00f4",
    "sg:orig_category":"Unclassifiable Establishments",
    "sg:phone":"+33 2 33 77 32 70",
    "sg:postcode":"50000",
    "sg:province":"Basse Normandie",
    "wof:name":"Normandie Magazine S.a.r.l.",
    "wof:placetype":"venue"
},
  "geometry": {"coordinates":[-1.096699,49.119469],"type":"Point"}
}