{
  "type": "Feature",
  "properties": {
    "iso:country":"FR",
    "sg:address":"62, Rue Benjamin Baillaud - B\u00e2t. 5 Carr\u00e9 Wilson, 31500 Toulouse",
    "sg:orig_category":"Non-Classified Establishments",
    "sg:phone":"+33 5 34 25 03 53",
    "sg:province":"Midi Pyr\u00e9n\u00e9es",
    "wof:name":"Osmose Photogravure S.a.r.l.",
    "wof:placetype":"venue"
},
  "geometry": {"coordinates":[1.465286,43.617462],"type":"Point"}
}