{
  "type": "Feature",
  "properties": {
    "iso:country":"FR",
    "sg:address":"B.P. 29, 62129 Th\u00e9rouanne^^Grande Rue, 62129 Th\u00e9rouanne",
    "sg:orig_category":"Non-Classified Establishments",
    "sg:phone":"+33 3 21 12 62 90",
    "sg:postcode":"62129",
    "sg:province":"Nord Pas-de-Calais",
    "wof:name":"Etablissements Jacques Millamon Compagnie S.a.",
    "wof:placetype":"venue"
},
  "geometry": {"coordinates":[2.286715,50.669773],"type":"Point"}
}