{
  "type": "Feature",
  "properties": {
    "iso:country":"FR",
    "sg:address":"Voie Romaine Pont De Semecourt 10140 Maizi\u00e8res Les Metz",
    "sg:classifiers":[
        {
            "category":"Shopping",
            "subcategory":"Computers & Home Electronics",
            "type":"Retail Goods"
        }
    ],
    "sg:phone":"+33 3 87 70 57 57",
    "sg:postcode":"10140",
    "sg:province":"Champagne",
    "sg:tags":[
        "equipment",
        "electrical",
        "component",
        "electric",
        "electronic"
    ],
    "wof:name":"France Transf Voie Romaine",
    "wof:placetype":"venue"
},
  "geometry": {"coordinates":[4.4667,48.238022],"type":"Point"}
}