{
  "type": "Feature",
  "properties": {
    "addr:full":"Rue Condorcet - Parc Technologie 5 Villefontaine Rhone-Alpes 38090",
    "addr:housenumber":"5",
    "addr:postcode":"38090",
    "addr:street":"Rue Condorcet;Technologie;Rhone-Alpes",
    "iso:country":"FR",
    "sg:address":"Rue Condorcet - Parc Technologie 5",
    "sg:city":"Villefontaine",
    "sg:orig_category":"Unclassifiable Establishments",
    "sg:phone":"+33 4 74 95 24 00",
    "sg:postcode":"38090",
    "sg:province":"Rhone-Alpes",
    "wof:name":"C.c.i. Nord Is\u00e8re",
    "wof:placetype":"venue"
},
  "geometry": {"coordinates":[5.16649,45.62727],"type":"Point"}
}