{
  "type": "Feature",
  "properties": {
    "iso:country":"FR",
    "sg:address":"Kerliguet 29900 Concarneau",
    "sg:city":"Concarneau",
    "sg:classifiers":[
        {
            "category":"Wholesale",
            "subcategory":"Machinery & Supplies",
            "type":"Manufacturing & Wholesale Goods"
        }
    ],
    "sg:phone":"+33 2 98 50 61 95",
    "sg:postcode":"29900",
    "sg:province":"Bretagne",
    "sg:tags":[
        "food",
        "processing",
        "-",
        "machine",
        "equipment",
        "engineering",
        "mechanical"
    ],
    "wof:name":"Blys",
    "wof:placetype":"venue"
},
  "geometry": {"coordinates":[-3.903727,47.908024],"type":"Point"}
}