{
  "type": "Feature",
  "properties": {
    "addr:full":"176, Rue de Loisne, 62136 Vieille Chapelle Nord Pas-de-Calais",
    "addr:housenumber":"176",
    "addr:postcode":"62136",
    "addr:street":"Rue De Loisne;Vieille Chapelle Nord",
    "iso:country":"FR",
    "sg:address":"176, Rue de Loisne, 62136 Vieille Chapelle",
    "sg:orig_category":"Non-Classified Establishments",
    "sg:phone":"+33 3 21 27 86 82",
    "sg:province":"Nord Pas-de-Calais",
    "wof:name":"Ribeiro E.u.r.l.",
    "wof:placetype":"venue"
},
  "geometry": {"coordinates":[2.71157,50.585331],"type":"Point"}
}