{
  "type": "Feature",
  "properties": {
    "iso:country":"FR",
    "sg:address":"160 rue de la R\u00e9publique 39400 MORBIER",
    "sg:classifiers":[
        {
            "category":"Manufacturing",
            "subcategory":"Glass & Minerals",
            "type":"Manufacturing & Wholesale Goods"
        }
    ],
    "sg:phone":"+33 3 84 33 04 31",
    "sg:postcode":"39400",
    "sg:province":"Franche Comt\u00e9",
    "sg:tags":[
        "frame"
    ],
    "wof:name":"Ets Maurice Vuillet Et Fils S.a.",
    "wof:placetype":"venue"
},
  "geometry": {"coordinates":[6.015896,46.535824],"type":"Point"}
}