{
  "type": "Feature",
  "properties": {
    "iso:country":"FR",
    "sg:address":"3, Rue de la Garenne, 27950 Saint Marcel",
    "sg:orig_category":"Non-Classified Establishments",
    "sg:phone":"+33 2 32 51 47 16",
    "sg:postcode":"27950",
    "sg:province":"Haute Normandie",
    "wof:name":"A.m.i. S.a.r.l. - Automatisme Micro-informatique Industriel",
    "wof:placetype":"venue"
},
  "geometry": {"coordinates":[1.458286,49.102978],"type":"Point"}
}