{
  "type": "Feature",
  "properties": {
    "addr:full":"ZI K\u00e9rivin Saint Martin des Champs Bretagne 29600",
    "addr:postcode":"29600",
    "iso:country":"FR",
    "sg:address":"ZI K\u00e9rivin",
    "sg:city":"Saint Martin des Champs",
    "sg:orig_category":"Unclassifiable Establishments",
    "sg:phone":"+33 2 98 62 18 94",
    "sg:postcode":"29600",
    "sg:province":"Bretagne",
    "wof:name":"G\u00e9o",
    "wof:placetype":"venue"
},
  "geometry": {"coordinates":[-3.844494,48.574829],"type":"Point"}
}