{
  "type": "Feature",
  "properties": {
    "iso:country":"FR",
    "sg:address":"Rue Nicolas Appert - ZI du Moulin de l'Ecaille",
    "sg:city":"Tinqueux",
    "sg:orig_category":"Unclassifiable Establishments",
    "sg:phone":"+33 3 26 08 12 06",
    "sg:postcode":"51430",
    "sg:province":"Champagne",
    "wof:name":"Soremat S.a.",
    "wof:placetype":"venue"
},
  "geometry": {"coordinates":[3.993903,49.247528],"type":"Point"}
}