{
  "type": "Feature",
  "properties": {
    "addr:full":"rue du Rec de Veyret 11100 Narbonne Languedoc-Roussillon",
    "addr:postcode":"11100",
    "addr:street":"Rue Du Rec De Veyret",
    "iso:country":"FR",
    "sg:address":"rue du Rec de Veyret 11100 Narbonne",
    "sg:classifiers":[
        {
            "category":"Bakery",
            "type":"Food & Drink"
        }
    ],
    "sg:phone":"+33 4 68 41 38 35",
    "sg:province":"Languedoc-Roussillon",
    "sg:tags":[
        "pastry"
    ],
    "wof:name":"Pedrero Sa",
    "wof:placetype":"venue"
},
  "geometry": {"coordinates":[2.988067,43.175446],"type":"Point"}
}