{
  "type": "Feature",
  "properties": {
    "iso:country":"FR",
    "sg:address":"Av des Petis Pr\u00e9s - ZI de l'Oison",
    "sg:city":"Saint Pierre les Elbeuf",
    "sg:orig_category":"Chocolat et/ou produits chocolat\u00e9s Chocolats personnalis\u00e9s Confiserie",
    "sg:phone":"+33 2 35 77 61 77",
    "sg:postcode":"76320",
    "sg:province":"Haute Normandie",
    "wof:name":"Lormier P\u00e8re Et Fils S.a.r.l.",
    "wof:placetype":"venue"
},
  "geometry": {"coordinates":[1.036363,49.289288],"type":"Point"}
}