{
  "type": "Feature",
  "properties": {
    "iso:country":"FR",
    "sg:address":"28 rue Emile Menier 75116 Paris",
    "sg:classifiers":[
        {
            "category":"Tea Room",
            "subcategory":"None",
            "type":"Food & Drink"
        }
    ],
    "sg:phone":"+33 1 53 70 37 00",
    "sg:province":"\u00cele-de-France",
    "sg:tags":[
        "plaster"
    ],
    "wof:name":"Lafarge Aluminates S.a.r.l.",
    "wof:placetype":"venue"
},
  "geometry": {"coordinates":[2.279242,48.869095],"type":"Point"}
}