{
  "type": "Feature",
  "properties": {
    "iso:country":"FR",
    "sg:address":"RN 532 - ZI les Iles Cord\u00e9es",
    "sg:city":"Veurey Voroize",
    "sg:orig_category":"Non-Classified Establishments",
    "sg:phone":"+33 4 76 53 94 63",
    "sg:postcode":"38113",
    "sg:province":"Rhone-Alpes",
    "wof:name":"Alu Stores G. Bazet S.a.r.l.",
    "wof:placetype":"venue"
},
  "geometry": {"coordinates":[5.613688,45.271927],"type":"Point"}
}