{
  "type": "Feature",
  "properties": {
    "addr:full":"39, Rue des Postes, 93300 Aubervilliers Ile de France 93300",
    "addr:housenumber":"39",
    "addr:postcode":"93300;93300",
    "addr:street":"Rue Des Postes",
    "iso:country":"FR",
    "sg:address":"39, Rue des Postes, 93300 Aubervilliers",
    "sg:orig_category":"Non-Classified Establishments",
    "sg:phone":"+33 1 43 52 93 40",
    "sg:postcode":"93300",
    "sg:province":"Ile de France",
    "wof:name":"A.b.s. S.a.r.l. - Assistance Balance Services",
    "wof:placetype":"venue"
},
  "geometry": {"coordinates":[2.390266,48.904285],"type":"Point"}
}