{
  "type": "Feature",
  "properties": {
    "addr:full":"55 Avenue Marceau Paris Ile de France 75116",
    "addr:housenumber":"55",
    "addr:postcode":"75116",
    "addr:street":"Avenue Marceau",
    "iso:country":"FR",
    "sg:address":"55 Avenue Marceau",
    "sg:city":"Paris",
    "sg:classifiers":[
        {
            "category":"Banks & Credit Unions",
            "subcategory":"Financial Services",
            "type":"Services"
        }
    ],
    "sg:phone":"+33 1 53 57 47 95",
    "sg:postcode":"75116",
    "sg:province":"Ile de France",
    "sg:tags":[
        "banking",
        "finance",
        "insurance"
    ],
    "wof:name":"Coutrelis & Associ\u00c9s",
    "wof:placetype":"venue"
},
  "geometry": {"coordinates":[2.297737,48.869846],"type":"Point"}
}