{
  "type": "Feature",
  "properties": {
    "addr:full":"Zi Du Fossal 47500 Montayral Montayral Aquitaine 47500",
    "addr:postcode":"47500;47500",
    "addr:street":"Zi Du Fossal",
    "iso:country":"FR",
    "sg:address":"Zi Du Fossal 47500 Montayral",
    "sg:city":"Montayral",
    "sg:classifiers":[
        {
            "category":"Food & Beverages",
            "subcategory":"Dairy",
            "type":"Retail Goods"
        }
    ],
    "sg:phone":"+33 5 53 36 17 00",
    "sg:postcode":"47500",
    "sg:province":"Aquitaine",
    "sg:tags":[
        "product",
        "related"
    ],
    "wof:name":"Laiterie De Ladhuie",
    "wof:placetype":"venue"
},
  "geometry": {"coordinates":[0.985055,44.480976],"type":"Point"}
}