{
  "type": "Feature",
  "properties": {
    "addr:full":"2, Rue de Selles, 51490 Pontfaverger Moronvilliers Champagne",
    "addr:housenumber":"2",
    "addr:postcode":"51490",
    "addr:street":"Rue De Selles",
    "iso:country":"FR",
    "sg:address":"2, Rue de Selles, 51490 Pontfaverger Moronvilliers",
    "sg:orig_category":"Non-Classified Establishments",
    "sg:phone":"+33 3 26 48 72 73",
    "sg:province":"Champagne",
    "wof:name":"Promel Brunella Technologies S.a.",
    "wof:placetype":"venue"
},
  "geometry": {"coordinates":[4.31106,49.29821],"type":"Point"}
}