{
  "type": "Feature",
  "properties": {
    "iso:country":"FR",
    "sg:address":"8 bis, Rue de la Source, 92000 Nanterre",
    "sg:orig_category":"Non-Classified Establishments",
    "sg:phone":"+33 1 47 21 82 82",
    "sg:province":"Ile de France",
    "wof:name":"Grafelt S.a.r.l.",
    "wof:placetype":"venue"
},
  "geometry": {"coordinates":[2.20516,48.886368],"type":"Point"}
}