{
  "type": "Feature",
  "properties": {
    "addr:full":"72, Rue de la Gare, 62470 Calonne Ricouart Nord Pas-de-Calais",
    "addr:housenumber":"72",
    "addr:postcode":"62470",
    "addr:street":"Rue De La Gare",
    "iso:country":"FR",
    "sg:address":"72, Rue de la Gare, 62470 Calonne Ricouart",
    "sg:orig_category":"Unclassifiable Establishments",
    "sg:phone":"+33 3 21 65 50 48",
    "sg:province":"Nord Pas-de-Calais",
    "wof:name":"Lansel S.a.",
    "wof:placetype":"venue"
},
  "geometry": {"coordinates":[2.478421,50.48196],"type":"Point"}
}