{
  "type": "Feature",
  "properties": {
    "addr:full":"La Caussade 47150 Lacaussade Lacaussade Aquitaine 47150",
    "addr:postcode":"47150;47150",
    "iso:country":"FR",
    "sg:address":"La Caussade 47150 Lacaussade",
    "sg:city":"Lacaussade",
    "sg:classifiers":[
        {
            "category":"Home & Garden",
            "subcategory":"Furniture",
            "type":"Retail Goods"
        }
    ],
    "sg:phone":"+33 5 53 36 42 30",
    "sg:postcode":"47150",
    "sg:province":"Aquitaine",
    "sg:tags":[
        "wood"
    ],
    "wof:name":"Ste Du Charbon De Bois De L Agenais (socba)",
    "wof:placetype":"venue"
},
  "geometry": {"coordinates":[0.730768,44.470425],"type":"Point"}
}