{
  "type": "Feature",
  "properties": {
    "addr:full":"Marmont 01540 Vonnas Rhone-Alpes",
    "addr:postcode":"01540",
    "addr:street":"Marmont",
    "iso:country":"FR",
    "sg:address":"Marmont 01540 Vonnas",
    "sg:orig_category":"Unclassifiable Establishments",
    "sg:phone":"+33 4 74 50 07 41",
    "sg:province":"Rhone-Alpes",
    "wof:name":"Entreprise Sani Dombes",
    "wof:placetype":"venue"
},
  "geometry": {"coordinates":[4.978343,46.203285],"type":"Point"}
}