{
  "type": "Feature",
  "properties": {
    "iso:country":"FR",
    "sg:address":"Rue Jules Horwitz",
    "sg:city":"Grenoble",
    "sg:orig_category":"Unclassifiable Establishments",
    "sg:phone":"+33 4 76 88 20 00",
    "sg:postcode":"38000",
    "sg:province":"Rhone-Alpes",
    "wof:name":"E.s.r.f. - European Synchroton Radiation Facility",
    "wof:placetype":"venue"
},
  "geometry": {"coordinates":[5.70152,45.206444],"type":"Point"}
}