{
  "type": "Feature",
  "properties": {
    "addr:full":"Route Des Gorges 83560 Vinon Sur Verdon Nord Pas-de-Calais",
    "addr:postcode":"83560",
    "addr:street":"Route Des Gorges;Verdon Nord",
    "iso:country":"FR",
    "sg:address":"Route Des Gorges 83560 Vinon Sur Verdon",
    "sg:classifiers":[
        {
            "category":"Food & Beverages",
            "subcategory":"Groceries & Convenience Stores",
            "type":"Retail Goods"
        }
    ],
    "sg:phone":"+33 4 92 78 83 78",
    "sg:province":"Nord Pas-de-Calais",
    "sg:tags":[
        "product",
        "grain",
        "cereal",
        "related"
    ],
    "wof:name":"Sarl Verdon Farine",
    "wof:placetype":"venue"
},
  "geometry": {"coordinates":[5.840002,43.736553],"type":"Point"}
}