{
  "type": "Feature",
  "properties": {
    "iso:country":"FR",
    "sg:address":"74, Av. de Lorraine, 94150 Rungis",
    "sg:orig_category":"Unclassifiable Establishments",
    "sg:phone":"+33 1 46 86 06 75",
    "sg:province":"Ile de France",
    "wof:name":"P\u00e9rez Lemeunier S.a.",
    "wof:placetype":"venue"
},
  "geometry": {"coordinates":[2.35142,48.74918],"type":"Point"}
}