{
  "type": "Feature",
  "properties": {
    "iso:country":"FR",
    "sg:address":"26 ave du Commandant; Aytre; 17440",
    "sg:classifiers":[
        {
            "category":"Banks & Credit Unions",
            "subcategory":"Bank",
            "type":"Services"
        }
    ],
    "sg:phone":"+33 3346441818",
    "sg:postcode":"17440",
    "sg:province":"Poitou-Charentes",
    "wof:name":"Soci\u00e9t\u00e9 G\u00e9n\u00e9rale",
    "wof:placetype":"venue"
},
  "geometry": {"coordinates":[-1.126244,46.136833],"type":"Point"}
}