{
  "type": "Feature",
  "properties": {
    "addr:full":"4, Bd Bernard Vos - Plateforme Logistique Grand Lyon, 69780 Mions Rhone-Alpes",
    "addr:housenumber":"4",
    "addr:postcode":"69780",
    "addr:street":"Bd Bernard Vos",
    "iso:country":"FR",
    "sg:address":"4, Bd Bernard Vos - Plateforme Logistique Grand Lyon, 69780 Mions",
    "sg:orig_category":"Unclassifiable Establishments",
    "sg:phone":"+33 4 37 25 21 21",
    "sg:province":"Rhone-Alpes",
    "wof:name":"Transports Graveleau S.a.",
    "wof:placetype":"venue"
},
  "geometry": {"coordinates":[4.954582,45.662968],"type":"Point"}
}