{
  "type": "Feature",
  "properties": {
    "addr:full":"ZI du Moros - Port de P\u00eache Concarneau Bretagne 29900",
    "addr:postcode":"29900",
    "addr:street":"Zi Du Moros Port De Pe\u0302Che;Bretagne",
    "iso:country":"FR",
    "sg:address":"ZI du Moros - Port de P\u00eache",
    "sg:city":"Concarneau",
    "sg:orig_category":"Unclassifiable Establishments",
    "sg:phone":"+33 2 98 97 09 65",
    "sg:postcode":"29900",
    "sg:province":"Bretagne",
    "wof:name":"C.r.m. S.a. - Compagnie Radio Maritime",
    "wof:placetype":"venue"
},
  "geometry": {"coordinates":[-3.917344,47.871864],"type":"Point"}
}