{
  "type": "Feature",
  "properties": {
    "iso:country":"FR",
    "sg:address":"Rue Roger Dumoulin - ZI",
    "sg:city":"Amiens",
    "sg:orig_category":"Unclassifiable Establishments",
    "sg:phone":"+33 3 22 54 55 00",
    "sg:postcode":"80000",
    "sg:province":"Picardie",
    "wof:name":"Dunlop France S.a.",
    "wof:placetype":"venue"
},
  "geometry": {"coordinates":[2.293165,49.894733],"type":"Point"}
}