{
  "type": "Feature",
  "properties": {
    "iso:country":"FR",
    "sg:address":"1",
    "sg:city":"des Chataigniers; La Chapelle sur Erdre; 44240",
    "sg:classifiers":[
        {
            "category":"Banks & Credit Unions",
            "subcategory":"Bank",
            "type":"Services"
        }
    ],
    "sg:phone":"+33 3340297555",
    "sg:postcode":"44240",
    "sg:province":"Pays de Loire",
    "wof:name":"Caisse R\u00e9gionale, De Cr\u00e9dit Agricole",
    "wof:placetype":"venue"
},
  "geometry": {"coordinates":[-1.552183,47.299114],"type":"Point"}
}