{
  "type": "Feature",
  "properties": {
    "iso:country":"FR",
    "sg:address":"Route De Chantereine 78200 Mantes La Ville",
    "sg:classifiers":[
        {
            "category":"Manufacturing",
            "subcategory":"Rubber & Plastics",
            "type":"Manufacturing & Wholesale Goods"
        }
    ],
    "sg:phone":"+33 1 30 98 56 00",
    "sg:province":"Ile de France",
    "sg:tags":[
        "packaging",
        "material",
        "-"
    ],
    "wof:name":"Du Pont De Nemours Sas",
    "wof:placetype":"venue"
},
  "geometry": {"coordinates":[-97.928825,26.298334],"type":"Point"}
}