{
  "type": "Feature",
  "properties": {
    "iso:country":"FR",
    "sg:address":"B.P. 90, 84503 Boll\u00e8ne C\u00e9dex^^192, Chemin du Fournillier, 84500 Boll\u00e8ne",
    "sg:orig_category":"Non-Classified Establishments",
    "sg:phone":"+33 4 90 30 97 51",
    "sg:province":"Provence-Alpes-C\u00f4te d'Azur",
    "wof:name":"S.o.d.e.c. S.a. - Soci\u00e9t\u00e9 Organisation De Documentations Et D'exper",
    "wof:placetype":"venue"
},
  "geometry": {"coordinates":[4.748432,44.282192],"type":"Point"}
}