{
  "type": "Feature",
  "properties": {
    "addr:full":"11 rue Commines 75003 Paris Ile de France",
    "addr:housenumber":"11",
    "addr:postcode":"75003",
    "addr:street":"Rue Commines",
    "iso:country":"FR",
    "sg:address":"11 rue Commines 75003 Paris",
    "sg:classifiers":[
        {
            "category":"Shopping",
            "subcategory":"Clothing, Apparel, & Fashions",
            "type":"Retail Goods"
        }
    ],
    "sg:phone":"+33 1 48 04 04 07",
    "sg:province":"Ile de France",
    "sg:tags":[
        "shirt"
    ],
    "wof:name":"Caf Sa",
    "wof:placetype":"venue"
},
  "geometry": {"coordinates":[2.365877,48.862198],"type":"Point"}
}