{
  "type": "Feature",
  "properties": {
    "addr:full":"46, Av du Commandant de Neuch\u00e8ze, 71400 Autun Autun Bourgogne 71400",
    "addr:postcode":"71400;71400",
    "addr:street":"46 Av Du Commandant De Neuche\u0300Ze",
    "iso:country":"FR",
    "sg:address":"46, Av du Commandant de Neuch\u00e8ze, 71400 Autun",
    "sg:city":"Autun",
    "sg:orig_category":"Unclassifiable Establishments",
    "sg:phone":"+33 3 85 52 21 63",
    "sg:postcode":"71400",
    "sg:province":"Bourgogne",
    "wof:name":"Dufraigne S.a.r.l.",
    "wof:placetype":"venue"
},
  "geometry": {"coordinates":[4.277597,46.957924],"type":"Point"}
}