{
  "type": "Feature",
  "properties": {
    "iso:country":"FR",
    "sg:address":"Le Grand Boissay 28310 Toury",
    "sg:city":"Allaines-Mervilliers",
    "sg:classifiers":[
        {
            "category":"Farming",
            "subcategory":"Farm",
            "type":"Manufacturing & Wholesale Goods"
        }
    ],
    "sg:phone":"+33 2 37 91 27 27",
    "sg:postcode":"28310",
    "sg:province":"Centre",
    "sg:tags":[
        "horticulture",
        "agriculture",
        "livestock"
    ],
    "wof:name":"Cooperative Agricole De Toury",
    "wof:placetype":"venue"
},
  "geometry": {"coordinates":[1.92104,48.188595],"type":"Point"}
}