{
  "type": "Feature",
  "properties": {
    "iso:country":"FR",
    "sg:address":"19 Rue De L'Industrie 67400 Illkirch Graffenstaden",
    "sg:city":"Geispolsheim",
    "sg:classifiers":[
        {
            "category":"Professional",
            "subcategory":"Advertising",
            "type":"Services"
        }
    ],
    "sg:phone":"+33 3 88 66 32 34",
    "sg:postcode":"67400",
    "sg:province":"Alsace",
    "sg:tags":[
        "marketing",
        "medium",
        "communication"
    ],
    "wof:name":"Distri Press Sarl",
    "wof:placetype":"venue"
},
  "geometry": {"coordinates":[7.731668,48.530483],"type":"Point"}
}