{
  "type": "Feature",
  "properties": {
    "addr:full":"209, Rue Georges Guynemer - ZA de l'A\u00e9ropole, 44150 Ancenis Pays de Loire 44150",
    "addr:housenumber":"209",
    "addr:postcode":"44150;44150",
    "addr:street":"Rue Georges Guynemer Za De L'Ae \u0301Ropole",
    "iso:country":"FR",
    "sg:address":"209, Rue Georges Guynemer - ZA de l'A\u00e9ropole, 44150 Ancenis",
    "sg:orig_category":"Non-Classified Establishments",
    "sg:phone":"+33 2 51 14 15 50",
    "sg:postcode":"44150",
    "sg:province":"Pays de Loire",
    "wof:name":"Carrard S.a.",
    "wof:placetype":"venue"
},
  "geometry": {"coordinates":[-1.188412,47.408371],"type":"Point"}
}