{
  "type": "Feature",
  "properties": {
    "iso:country":"FR",
    "sg:address":"B.P. 215, 13308 Marseille C\u00e9dex 14^^12, Bd Fr\u00e9d\u00e9ric Sauvage, 13014 Marseille",
    "sg:orig_category":"Non-Classified Establishments",
    "sg:phone":"+33 4 95 05 55 00",
    "sg:province":"Poitou-Charentes",
    "wof:name":"Schenker S.a.",
    "wof:placetype":"venue"
},
  "geometry": {"coordinates":[5.382571,43.334103],"type":"Point"}
}