{
  "type": "Feature",
  "properties": {
    "iso:country":"FR",
    "sg:address":"2, Rue Edmond Besse, 33083 Bordeaux C\u00e9dex",
    "sg:orig_category":"Non-Classified Establishments",
    "sg:phone":"+33 5 56 50 15 50",
    "sg:province":"Auvergne",
    "wof:name":"Indrago S.a.r.l.",
    "wof:placetype":"venue"
},
  "geometry": {"coordinates":[-0.548719,44.88736],"type":"Point"}
}