{
  "type": "Feature",
  "properties": {
    "iso:country":"FR",
    "sg:address":"Z I Pyrene Aeropole 65290 JUILLAN",
    "sg:classifiers":[
        {
            "category":"Manufacturing",
            "subcategory":"Metals",
            "type":"Manufacturing & Wholesale Goods"
        }
    ],
    "sg:phone":"+33 5 62 32 69 00",
    "sg:postcode":"65290",
    "sg:province":"Midi Pyr\u00e9n\u00e9es",
    "sg:tags":[
        "aluminium"
    ],
    "wof:name":"Aluminium Systeme De Tarbes Sa",
    "wof:placetype":"venue"
},
  "geometry": {"coordinates":[0.028535,43.200371],"type":"Point"}
}