{
  "type": "Feature",
  "properties": {
    "addr:full":"B.P. 94, 16103 Cognac C\u00e9dex^^ZI de Merpins, 16100 Cognac Poitou-Charentes",
    "addr:postcode":"16103;16100 cognac",
    "addr:street":"B.P. 94",
    "iso:country":"FR",
    "sg:address":"B.P. 94, 16103 Cognac C\u00e9dex^^ZI de Merpins, 16100 Cognac",
    "sg:orig_category":"Non-Classified Establishments",
    "sg:phone":"+33 5 45 82 62 22",
    "sg:province":"Poitou-Charentes",
    "wof:name":"Seguin Moreau Et Compagnie S.a.",
    "wof:placetype":"venue"
},
  "geometry": {"coordinates":[-0.313384,45.67149],"type":"Point"}
}