{
  "type": "Feature",
  "properties": {
    "iso:country":"FR",
    "sg:address":"7, Rue des Boucheries, 60200 Compi\u00e8gne",
    "sg:orig_category":"Non-Classified Establishments",
    "sg:phone":"+33 3 44 23 09 30",
    "sg:province":"Picardie",
    "wof:name":"Pinel D\u00e9m\u00e9nagements S.a.",
    "wof:placetype":"venue"
},
  "geometry": {"coordinates":[2.824456,49.416256],"type":"Point"}
}