{
  "type": "Feature",
  "properties": {
    "iso:country":"FR",
    "sg:address":"11 Quai De La Souys 33100 Bordeaux",
    "sg:city":"Bordeaux",
    "sg:classifiers":[
        {
            "category":"Home & Garden",
            "subcategory":"Furniture",
            "type":"Retail Goods"
        }
    ],
    "sg:phone":"+33 5 56 40 50 51",
    "sg:postcode":"33100",
    "sg:province":"Aquitaine",
    "sg:tags":[
        "wood"
    ],
    "wof:name":"Gedimat Labenne Rougier",
    "wof:placetype":"venue"
},
  "geometry": {"coordinates":[-0.54863,44.832664],"type":"Point"}
}