{
  "type": "Feature",
  "properties": {
    "addr:full":"4 Rue Bernardswiller 67210 Obernai Obernai Alsace 67210",
    "addr:housenumber":"4",
    "addr:postcode":"67210;67210",
    "addr:street":"Rue Bernardswiller",
    "iso:country":"FR",
    "sg:address":"4 Rue Bernardswiller 67210 Obernai",
    "sg:city":"Obernai",
    "sg:orig_category":"Miscellaneous Products",
    "sg:phone":"+33 3 88 95 61 08",
    "sg:postcode":"67210",
    "sg:province":"Alsace",
    "wof:name":"Klein Freres Sa",
    "wof:placetype":"venue"
},
  "geometry": {"coordinates":[7.473456,48.460236],"type":"Point"}
}