{
  "type": "Feature",
  "properties": {
    "iso:country":"FR",
    "sg:address":"Rue Archicamts 80015 Amiens",
    "sg:city":"Amiens",
    "sg:orig_category":"Air transport Business travel Business travel - Transport Road transport Sea transport Transport - r",
    "sg:phone":"+33 3 22 54 31 90",
    "sg:postcode":"80000",
    "sg:province":"Picardie",
    "wof:name":"Abx Logistique France",
    "wof:placetype":"venue"
},
  "geometry": {"coordinates":[2.26419,49.929359],"type":"Point"}
}