{
  "type": "Feature",
  "properties": {
    "addr:full":"18, Bd des Martyrs de Ch\u00e2teaubriand, 95100 Argenteuil Ile de France",
    "addr:housenumber":"18",
    "addr:postcode":"95100;ile",
    "addr:street":"Bd Des Martyrs De Cha\u0302Teaubriand",
    "iso:country":"FR",
    "sg:address":"18, Bd des Martyrs de Ch\u00e2teaubriand, 95100 Argenteuil",
    "sg:orig_category":"Non-Classified Establishments",
    "sg:phone":"+33 1 39 81 13 38",
    "sg:province":"Ile de France",
    "wof:name":"Onderbeke Ateliers S.a.r.l.",
    "wof:placetype":"venue"
},
  "geometry": {"coordinates":[2.20943,48.951126],"type":"Point"}
}