{
  "type": "Feature",
  "properties": {
    "addr:full":"233 Boulevard Amiral Mouchez 76600 Le Havre Haute Normandie 76600",
    "addr:housenumber":"233",
    "addr:postcode":"76600;76600",
    "addr:street":"Boulevard Amiral Mouchez",
    "iso:country":"FR",
    "sg:address":"233 Boulevard Amiral Mouchez 76600 Le Havre",
    "sg:classifiers":[
        {
            "category":"Professional",
            "subcategory":"Engineering",
            "type":"Services"
        }
    ],
    "sg:phone":"+33 2 35 24 64 00",
    "sg:postcode":"76600",
    "sg:province":"Haute Normandie",
    "sg:tags":[
        "machine",
        "-",
        "mechanical"
    ],
    "wof:name":"Maugars (ateliers L) Sa",
    "wof:placetype":"venue"
},
  "geometry": {"coordinates":[0.149179,49.48827],"type":"Point"}
}