{
  "type": "Feature",
  "properties": {
    "addr:full":"9 rue de Tlemcen; Gien; 45500 Gien Centre 45500",
    "addr:housenumber":"9",
    "addr:postcode":"45500;45500",
    "addr:street":"Rue De Tlemcen",
    "iso:country":"FR",
    "sg:address":"9 rue de Tlemcen; Gien; 45500",
    "sg:city":"Gien",
    "sg:classifiers":[
        {
            "category":"Banks & Credit Unions",
            "subcategory":"Bank",
            "type":"Services"
        }
    ],
    "sg:phone":"+33 3338671567",
    "sg:postcode":"45500",
    "sg:province":"Centre",
    "wof:name":"Banque Nationale De Paris",
    "wof:placetype":"venue"
},
  "geometry": {"coordinates":[2.632756,47.684059],"type":"Point"}
}