{
  "type": "Feature",
  "properties": {
    "addr:full":"40 Rue Denis Papin Zi Jean Mal\u00e8ze 47240 Bon Encontre Bon-Encontre Aquitaine 47240",
    "addr:housenumber":"40",
    "addr:postcode":"47240;47240",
    "addr:street":"Rue Denis Papin Zi Jean Male\u0300Ze",
    "iso:country":"FR",
    "sg:address":"40 Rue Denis Papin Zi Jean Mal\u00e8ze 47240 Bon Encontre",
    "sg:city":"Bon-Encontre",
    "sg:classifiers":[
        {
            "category":"Airport",
            "type":"Transportation"
        }
    ],
    "sg:phone":"+33 5 53 68 59 92",
    "sg:postcode":"47240",
    "sg:province":"Aquitaine",
    "sg:tags":[
        "transport",
        "air"
    ],
    "wof:name":"Francaise De Transports Gondrand Freres",
    "wof:placetype":"venue"
},
  "geometry": {"coordinates":[0.698695,44.16959],"type":"Point"}
}