{
  "type": "Feature",
  "properties": {
    "iso:country":"FR",
    "sg:address":"32 - 3, Rue du Ballon - Z.I. les Richardets, 93165 Noisy le Grand C\u00e9dex",
    "sg:orig_category":"Unclassifiable Establishments",
    "sg:phone":"+33 1 48 15 88 00",
    "sg:province":"Poitou-Charentes",
    "wof:name":"Chesapeake Display Et Packaging Europe S.a.",
    "wof:placetype":"venue"
},
  "geometry": {"coordinates":[2.553644,48.848892],"type":"Point"}
}