{
  "type": "Feature",
  "properties": {
    "iso:country":"FR",
    "sg:address":"Av. Marie Amp\u00e8re - Zone Induspal",
    "sg:city":"Lons",
    "sg:orig_category":"Non-Classified Establishments",
    "sg:phone":"+33 5 59 32 32 72",
    "sg:postcode":"64140",
    "sg:province":"Aquitaine",
    "wof:name":"T.t.c. S.a. - Tricotage Traitement Confection",
    "wof:placetype":"venue"
},
  "geometry": {"coordinates":[-0.428331,43.313919],"type":"Point"}
}