{
  "type": "Feature",
  "properties": {
    "addr:full":"60, Rue Maurice Sarraut, 59200 Tourcoing Nord Pas-de-Calais",
    "addr:housenumber":"60",
    "addr:postcode":"59200",
    "addr:street":"Rue Maurice Sarraut",
    "iso:country":"FR",
    "sg:address":"60, Rue Maurice Sarraut, 59200 Tourcoing",
    "sg:orig_category":"Non-Classified Establishments",
    "sg:phone":"+33 3 20 76 70 79",
    "sg:province":"Nord Pas-de-Calais",
    "wof:name":"Gipsy S.a.",
    "wof:placetype":"venue"
},
  "geometry": {"coordinates":[3.159661,50.735676],"type":"Point"}
}