{
  "type": "Feature",
  "properties": {
    "addr:full":"36/40, Rue Babeuf, 93380 Pierrefitte sur Seine Ile de France",
    "addr:housenumber":"36 / 40",
    "addr:postcode":"93380",
    "addr:street":"Rue Babeuf",
    "iso:country":"FR",
    "sg:address":"36/40, Rue Babeuf, 93380 Pierrefitte sur Seine",
    "sg:orig_category":"Unclassifiable Establishments",
    "sg:phone":"+33 1 49 40 10 80",
    "sg:province":"Ile de France",
    "wof:name":"A\u00e9rotechnique S.a.",
    "wof:placetype":"venue"
},
  "geometry": {"coordinates":[2.372132,48.960739],"type":"Point"}
}