{
  "type": "Feature",
  "properties": {
    "iso:country":"FR",
    "sg:address":"26 Rue De La Godde 45802 St Jean De Braye Cedex",
    "sg:classifiers":[
        {
            "category":"Banks & Credit Unions",
            "subcategory":"Financial Services",
            "type":"Services"
        }
    ],
    "sg:phone":"+33 2 38 60 27 27",
    "sg:province":"Champagne",
    "sg:tags":[
        "banking",
        "insurance",
        "institution",
        "finance"
    ],
    "wof:name":"Caisse Regionale De Ca Mutuel Centre Loire",
    "wof:placetype":"venue"
},
  "geometry": {"coordinates":[1.978739,47.919048],"type":"Point"}
}