{
  "type": "Feature",
  "properties": {
    "iso:country":"FR",
    "sg:address":"51, Rue de la Malacombe - ZI de Chesnes, 38070 Saint Quentin Fallavier",
    "sg:orig_category":"Unclassifiable Establishments",
    "sg:phone":"+33 4 74 94 31 80",
    "sg:province":"Rhone-Alpes",
    "wof:name":"Phil Trans S.a.r.l.",
    "wof:placetype":"venue"
},
  "geometry": {"coordinates":[5.11081,45.632595],"type":"Point"}
}