{
  "type": "Feature",
  "properties": {
    "iso:country":"FR",
    "sg:address":"9, Rue des Peupliers, 31820 Pibrac",
    "sg:orig_category":"Non-Classified Establishments",
    "sg:phone":"+33 5 61 86 83 76",
    "sg:postcode":"31820",
    "sg:province":"Midi Pyr\u00e9n\u00e9es",
    "wof:name":"Barry Controls Limited",
    "wof:placetype":"venue"
},
  "geometry": {"coordinates":[1.281574,43.613075],"type":"Point"}
}