{
  "type": "Feature",
  "properties": {
    "iso:country":"FR",
    "sg:address":"36, Rue Devosge, 21000 Dijon",
    "sg:city":"Dijon",
    "sg:orig_category":"Unclassifiable Establishments",
    "sg:phone":"+33 3 80 44 11 75",
    "sg:postcode":"21000",
    "sg:province":"Bourgogne",
    "wof:name":"Temps R\u00e9el S.a.r.l.",
    "wof:placetype":"venue"
},
  "geometry": {"coordinates":[5.036896,47.325829],"type":"Point"}
}