{
  "type": "Feature",
  "properties": {
    "iso:country":"FR",
    "sg:address":"384 Rue Des Mousquetaires Zi Saint Justin 40260 Castets",
    "sg:city":"Castets",
    "sg:classifiers":[
        {
            "category":"Home & Garden",
            "subcategory":"Furniture",
            "type":"Retail Goods"
        }
    ],
    "sg:phone":"+33 5 58 55 05 10",
    "sg:postcode":"40260",
    "sg:province":"Aquitaine",
    "sg:tags":[
        "household",
        "wood"
    ],
    "wof:name":"Saint Palais",
    "wof:placetype":"venue"
},
  "geometry": {"coordinates":[-1.068398,43.872623],"type":"Point"}
}