{
  "type": "Feature",
  "properties": {
    "iso:country":"FR",
    "sg:address":"B.P. 5, 43600 Sainte Sigol\u00e8ne C\u00e9dex^^Rte d'Yssingeaux, 43600 Sainte Sigol\u00e8ne",
    "sg:city":"Les Villettes",
    "sg:orig_category":"Non-Classified Establishments",
    "sg:phone":"+33 4 71 66 62 88",
    "sg:postcode":"43600",
    "sg:province":"Auvergne",
    "wof:name":"Eurofoulard Diffusion S.a.r.l",
    "wof:placetype":"venue"
},
  "geometry": {"coordinates":[4.230585,45.235588],"type":"Point"}
}