{
  "type": "Feature",
  "properties": {
    "addr:full":"Kervihan 56580 Br\u00e9han Br\u00e9han Bretagne 56580",
    "addr:postcode":"56580;56580",
    "addr:street":"Kervihan;Bre\u0301Han",
    "iso:country":"FR",
    "sg:address":"Kervihan 56580 Br\u00e9han",
    "sg:city":"Br\u00e9han",
    "sg:classifiers":[
        {
            "category":"Professional",
            "subcategory":"Business Services",
            "type":"Services"
        }
    ],
    "sg:phone":"+33 2 97 38 85 16",
    "sg:postcode":"56580",
    "sg:province":"Bretagne",
    "sg:tags":[
        "body",
        "advice"
    ],
    "wof:name":"Ass Les Enfants De Kervihan",
    "wof:placetype":"venue"
},
  "geometry": {"coordinates":[-2.766409,48.037312],"type":"Point"}
}