{
  "type": "Feature",
  "properties": {
    "iso:country":"FR",
    "sg:address":"107 Rue Raspail 94700 Maisons Alfort",
    "sg:classifiers":[
        {
            "category":"Shopping",
            "subcategory":"Luggage & Leather Goods",
            "type":"Retail Goods"
        }
    ],
    "sg:phone":"+33 1 48 93 74 44",
    "sg:postcode":"94700",
    "sg:province":"Ile de France",
    "sg:tags":[
        "shoe"
    ],
    "wof:name":"Sebagh Raphael",
    "wof:placetype":"venue"
},
  "geometry": {"coordinates":[2.44794,48.808151],"type":"Point"}
}