{
  "type": "Feature",
  "properties": {
    "addr:full":"B.P. 44 Mourenx Aquitaine 64150",
    "addr:postcode":"64150",
    "addr:street":"B.P. 44",
    "iso:country":"FR",
    "sg:address":"B.P. 44",
    "sg:city":"Mourenx",
    "sg:orig_category":"Non-Classified Establishments",
    "sg:phone":"+33 5 59 71 59 07",
    "sg:postcode":"64150",
    "sg:province":"Aquitaine",
    "wof:name":"S.e. Technim\u00e9tal S.a.r.l.",
    "wof:placetype":"venue"
},
  "geometry": {"coordinates":[-0.61819,43.354855],"type":"Point"}
}