{
  "type": "Feature",
  "properties": {
    "iso:country":"FR",
    "sg:address":"r Embreville 80770 Beauchamps",
    "sg:classifiers":[
        {
            "category":"Professional",
            "subcategory":"Engineering",
            "type":"Services"
        }
    ],
    "sg:phone":"+33 3 22 61 28 28",
    "sg:postcode":"80770",
    "sg:province":"Picardie",
    "sg:tags":[
        "machine",
        "-",
        "mechanical"
    ],
    "wof:name":"Deme",
    "wof:placetype":"venue"
},
  "geometry": {"coordinates":[1.510787,50.017857],"type":"Point"}
}