{
  "type": "Feature",
  "properties": {
    "addr:full":"49 Rue De Boult 51110 Isles Sur Suippe Champagne 51110",
    "addr:housenumber":"49",
    "addr:postcode":"51110;51110",
    "addr:street":"Rue De Boult;Isles;Suippe Champagne",
    "iso:country":"FR",
    "sg:address":"49 Rue De Boult 51110 Isles Sur Suippe",
    "sg:classifiers":[
        {
            "category":"Wholesale",
            "subcategory":"Machinery & Supplies",
            "type":"Manufacturing & Wholesale Goods"
        }
    ],
    "sg:phone":"+33 3 26 03 89 89",
    "sg:postcode":"51110",
    "sg:province":"Champagne",
    "sg:tags":[
        "handling",
        "material",
        "-",
        "machine",
        "equipment",
        "engineering",
        "mechanical"
    ],
    "wof:name":"Hymeca Manutention",
    "wof:placetype":"venue"
},
  "geometry": {"coordinates":[4.200098,49.359936],"type":"Point"}
}