{
  "type": "Feature",
  "properties": {
    "addr:full":"Rue Du 11 Novembre 17281 Puilboreau Midi Pyr\u00e9n\u00e9es",
    "addr:postcode":"17281",
    "addr:street":"Rue Du 11 Novembre",
    "iso:country":"FR",
    "sg:address":"Rue Du 11 Novembre 17281 Puilboreau",
    "sg:classifiers":[
        {
            "category":"Manufacturing",
            "subcategory":"Tools & Machinery",
            "type":"Manufacturing & Wholesale Goods"
        }
    ],
    "sg:phone":"+33 5 46 67 57 55",
    "sg:province":"Midi Pyr\u00e9n\u00e9es",
    "sg:tags":[
        "metallurgy",
        "metalworking"
    ],
    "wof:name":"Grassin",
    "wof:placetype":"venue"
},
  "geometry": {"coordinates":[-1.119705,46.173767],"type":"Point"}
}