{
  "type": "Feature",
  "properties": {
    "addr:full":"41, Bd du Parc - Parc d'Affaires Eurotunnet, 62231 Coquelles Nord Pas-de-Calais",
    "addr:housenumber":"41",
    "addr:postcode":"62231",
    "addr:street":"Bd Du Parc Parc",
    "iso:country":"FR",
    "sg:address":"41, Bd du Parc - Parc d'Affaires Eurotunnet, 62231 Coquelles",
    "sg:orig_category":"Non-Classified Establishments",
    "sg:phone":"+33 3 21 46 86 00",
    "sg:province":"Nord Pas-de-Calais",
    "wof:name":"Schneider Electric S.a.",
    "wof:placetype":"venue"
},
  "geometry": {"coordinates":[1.806112,50.929459],"type":"Point"}
}