{
  "type": "Feature",
  "properties": {
    "addr:full":"7BIS rue Blanqui 42400 ST CHAMOND Rhone-Alpes",
    "addr:housenumber":"7bis",
    "addr:postcode":"42400",
    "addr:street":"Rue Blanqui",
    "iso:country":"FR",
    "sg:address":"7BIS rue Blanqui 42400 ST CHAMOND",
    "sg:classifiers":[
        {
            "category":"Manufacturing",
            "subcategory":"Motor Vehicles & Parts",
            "type":"Manufacturing & Wholesale Goods"
        }
    ],
    "sg:phone":"+33 4 77 22 60 60",
    "sg:province":"Rhone-Alpes",
    "sg:tags":[
        "precision",
        "mechanic"
    ],
    "wof:name":"Forginove S.a.r.l.",
    "wof:placetype":"venue"
},
  "geometry": {"coordinates":[4.505804,45.458763],"type":"Point"}
}