{
  "type": "Feature",
  "properties": {
    "iso:country":"FR",
    "sg:address":"1, Promenade du Rhin, 21000 Dijon",
    "sg:city":"Dijon",
    "sg:orig_category":"Unclassifiable Establishments",
    "sg:phone":"+33 3 80 59 61 15",
    "sg:postcode":"21000",
    "sg:province":"Bourgogne",
    "wof:name":"A.n.p.e. Direction D\u00e9l\u00e9gu\u00e9e De C\u00f4te D'or",
    "wof:placetype":"venue"
},
  "geometry": {"coordinates":[5.025309,47.314144],"type":"Point"}
}