{
  "type": "Feature",
  "properties": {
    "addr:full":"115 Av Des Faxes 69427 Lyon Cedex 03 Languedoc-Roussillon",
    "addr:postcode":"69427;cedex 03",
    "addr:street":"115 Av Des Faxes",
    "iso:country":"FR",
    "sg:address":"115 Av Des Faxes 69427 Lyon Cedex 03",
    "sg:classifiers":[
        {
            "category":"Building & Trades",
            "subcategory":"Construction",
            "type":"Services"
        }
    ],
    "sg:phone":"+33 4 26 68 25 00",
    "sg:province":"Languedoc-Roussillon",
    "sg:tags":[
        "work",
        "public"
    ],
    "wof:name":"Maia Sonnier Genie Civil - T.p. Sa",
    "wof:placetype":"venue"
},
  "geometry": {"coordinates":[4.86843,45.751369],"type":"Point"}
}