{
  "type": "Feature",
  "properties": {
    "addr:full":"B.P. 02, 58209 Cosne Cours sur Loire C\u00e9dex^^Rue des Fr\u00e8res Gambon, 58200 Cosne Cours sur Loire Cosne-Cours-sur-Loire Bourgogne 58200",
    "addr:postcode":"58209;58200;58200",
    "addr:street":"B.P. 02;Cours;Des Fre\u0300Res Gambon",
    "iso:country":"FR",
    "sg:address":"B.P. 02, 58209 Cosne Cours sur Loire C\u00e9dex^^Rue des Fr\u00e8res Gambon, 58200 Cosne Cours sur Loire",
    "sg:city":"Cosne-Cours-sur-Loire",
    "sg:orig_category":"Non-Classified Establishments",
    "sg:phone":"+33 3 86 28 54 92",
    "sg:postcode":"58200",
    "sg:province":"Bourgogne",
    "wof:name":"E.d.f. - G.d.f. Services",
    "wof:placetype":"venue"
},
  "geometry": {"coordinates":[2.943994,47.415398],"type":"Point"}
}