{
  "type": "Feature",
  "properties": {
    "iso:country":"FR",
    "sg:address":"ZI chemin Grenouill\u00e8re BP 60109 Cedex 60251 Mouy",
    "sg:classifiers":[
        {
            "category":"Shopping",
            "subcategory":"Computers & Home Electronics",
            "type":"Retail Goods"
        }
    ],
    "sg:phone":"+33 3 44 26 83 92",
    "sg:province":"Franche Comt\u00e9",
    "sg:tags":[
        "electronic",
        "electrical",
        "equipment"
    ],
    "wof:name":"Seicer",
    "wof:placetype":"venue"
},
  "geometry": {"coordinates":[-88.54782899999999,42.051609],"type":"Point"}
}