{
  "type": "Feature",
  "properties": {
    "iso:country":"FR",
    "sg:address":"Rue Nungesser Et Coli 44860 St Aignan Grandlieu",
    "sg:orig_category":"Business advice and other services Environment - machinery and equipment Training",
    "sg:phone":"+33 2 40 13 12 00",
    "sg:postcode":"44860",
    "sg:province":"Pays de Loire",
    "wof:name":"Atos Environnement Sa",
    "wof:placetype":"venue"
},
  "geometry": {"coordinates":[-1.591549,47.155186],"type":"Point"}
}