{
  "type": "Feature",
  "properties": {
    "addr:full":"47 Rue Du Fbg St Honor\u00e9 75401 Paris Cedex 08 Midi Pyr\u00e9n\u00e9es",
    "addr:housenumber":"47",
    "addr:postcode":"75401",
    "addr:street":"Rue Du Fbg St Honore\u0301",
    "iso:country":"FR",
    "sg:address":"47 Rue Du Fbg St Honor\u00e9 75401 Paris Cedex 08",
    "sg:classifiers":[
        {
            "category":"Banks & Credit Unions",
            "subcategory":"Financial Services",
            "type":"Services"
        }
    ],
    "sg:phone":"+33 1 40 17 25 25",
    "sg:province":"Midi Pyr\u00e9n\u00e9es",
    "sg:tags":[
        "banking",
        "insurance",
        "institution",
        "finance"
    ],
    "wof:name":"Rothschild Banque (la Compagnie Financiere Edmond De)",
    "wof:placetype":"venue"
},
  "geometry": {"coordinates":[2.3111,48.873241],"type":"Point"}
}