{
  "type": "Feature",
  "properties": {
    "addr:full":"RN 330 - La Croix Gillet Monthyon Ile de France 77122",
    "addr:postcode":"77122",
    "addr:street":"Rn 330 La Croix Gillet Monthyon Ile De France",
    "iso:country":"FR",
    "sg:address":"RN 330 - La Croix Gillet",
    "sg:city":"Monthyon",
    "sg:orig_category":"Unclassifiable Establishments",
    "sg:phone":"+33 1 64 36 24 08",
    "sg:postcode":"77122",
    "sg:province":"Ile de France",
    "wof:name":"Pr\u00e9fall S.a.",
    "wof:placetype":"venue"
},
  "geometry": {"coordinates":[2.833215,49.006104],"type":"Point"}
}