{
  "type": "Feature",
  "properties": {
    "addr:full":"Ld Les Promenades 26220 Dieulefit Rhone-Alpes 26220",
    "addr:postcode":"26220;26220",
    "addr:street":"Ld;Promenades",
    "iso:country":"FR",
    "sg:address":"Ld Les Promenades 26220 Dieulefit",
    "sg:classifiers":[
        {
            "category":"Manufacturing",
            "subcategory":"Motor Vehicles & Parts",
            "type":"Manufacturing & Wholesale Goods"
        }
    ],
    "sg:phone":"+33 4 75 46 88 11",
    "sg:postcode":"26220",
    "sg:province":"Rhone-Alpes",
    "sg:tags":[
        "engine",
        "machine",
        "engineering",
        "-",
        "mechanical"
    ],
    "wof:name":"Lufra",
    "wof:placetype":"venue"
},
  "geometry": {"coordinates":[5.1476,44.461697],"type":"Point"}
}