{
  "type": "Feature",
  "properties": {
    "iso:country":"FR",
    "sg:address":"31, Av. de Saint Roch - Immeuble le Delta, 13740 Le Rove",
    "sg:orig_category":"Non-Classified Establishments",
    "sg:phone":"+33 4 91 46 80 60",
    "sg:province":"Haute Normandie",
    "wof:name":"I.e.m.s. S.a.r.l. - Information Europ\u00e9enne Management Syst\u00e8me",
    "wof:placetype":"venue"
},
  "geometry": {"coordinates":[5.24777,43.367294],"type":"Point"}
}