{
  "type": "Feature",
  "properties": {
    "addr:full":"8 Rue De Bel Air 85590 TREIZE VENTS Pays de Loire",
    "addr:housenumber":"8",
    "addr:postcode":"85590",
    "addr:street":"Rue De Bel Air;Vents",
    "iso:country":"FR",
    "sg:address":"8 Rue De Bel Air 85590 TREIZE VENTS",
    "sg:classifiers":[
        {
            "category":"Shopping",
            "subcategory":"Clothing, Apparel, & Fashions",
            "type":"Retail Goods"
        }
    ],
    "sg:phone":"+33 2 51 57 60 12",
    "sg:province":"Pays de Loire",
    "sg:tags":[
        "sportswear"
    ],
    "wof:name":"Mbs Compagnie S.a.r.l.",
    "wof:placetype":"venue"
},
  "geometry": {"coordinates":[-0.850329,46.920269],"type":"Point"}
}