{
  "type": "Feature",
  "properties": {
    "addr:full":"Rte de Carhaix - Guerneac'h Gourin Bretagne 56110",
    "addr:postcode":"56110",
    "addr:street":"Rte De Carhaix Guerneac'H Gourin Bretagne",
    "iso:country":"FR",
    "sg:address":"Rte de Carhaix - Guerneac'h",
    "sg:city":"Gourin",
    "sg:orig_category":"Non-Classified Establishments",
    "sg:phone":"+33 2 97 23 48 76",
    "sg:postcode":"56110",
    "sg:province":"Bretagne",
    "wof:name":"A.r.d.o.t. S.a. - Soci\u00e9t\u00e9 Industrielle Armoricaine De L\u00e9gumes",
    "wof:placetype":"venue"
},
  "geometry": {"coordinates":[-3.581424,48.273029],"type":"Point"}
}