{
  "type": "Feature",
  "properties": {
    "addr:full":"184 Rue Du Ladhof 68000 Colmar Colmar Alsace 68000",
    "addr:housenumber":"184",
    "addr:postcode":"68000;68000",
    "addr:street":"Rue Du Ladhof",
    "iso:country":"FR",
    "sg:address":"184 Rue Du Ladhof 68000 Colmar",
    "sg:city":"Colmar",
    "sg:classifiers":[
        {
            "category":"Professional",
            "type":"Services"
        }
    ],
    "sg:phone":"+33 3 89 21 06 20",
    "sg:postcode":"68000",
    "sg:province":"Alsace",
    "sg:tags":[
        "transport",
        "road"
    ],
    "wof:name":"Smat",
    "wof:placetype":"venue"
},
  "geometry": {"coordinates":[7.379298,48.106663],"type":"Point"}
}