{
  "type": "Feature",
  "properties": {
    "addr:full":"ZA La Tissoni\u00e8re Garnay Centre 28500",
    "addr:housenumber":"garnay",
    "addr:postcode":"28500",
    "addr:street":"Za La Tissonie\u0300Re",
    "iso:country":"FR",
    "sg:address":"ZA La Tissoni\u00e8re",
    "sg:city":"Garnay",
    "sg:orig_category":"Non-Classified Establishments",
    "sg:phone":"+33 2 37 38 88 88",
    "sg:postcode":"28500",
    "sg:province":"Centre",
    "wof:name":"C.p.r.o. S.a.",
    "wof:placetype":"venue"
},
  "geometry": {"coordinates":[1.338395,48.705914],"type":"Point"}
}