{
  "type": "Feature",
  "properties": {
    "addr:full":"Za La Butte 53500 Vautorte Pays de Loire 53500",
    "addr:postcode":"53500;53500",
    "addr:street":"Za La Butte",
    "iso:country":"FR",
    "sg:address":"Za La Butte 53500 Vautorte",
    "sg:classifiers":[
        {
            "category":"Home & Garden",
            "subcategory":"Furniture",
            "type":"Retail Goods"
        }
    ],
    "sg:phone":"+33 2 43 00 58 76",
    "sg:postcode":"53500",
    "sg:province":"Pays de Loire",
    "sg:tags":[
        "household",
        "wood"
    ],
    "wof:name":"Meubles Bernard Boittin",
    "wof:placetype":"venue"
},
  "geometry": {"coordinates":[-0.832105,48.301311],"type":"Point"}
}