{
  "type": "Feature",
  "properties": {
    "addr:full":"48, Rue Auger, 93698 Pantin C\u00e9dex Midi Pyr\u00e9n\u00e9es",
    "addr:housenumber":"48",
    "addr:postcode":"93698",
    "addr:street":"Rue Auger",
    "iso:country":"FR",
    "sg:address":"48, Rue Auger, 93698 Pantin C\u00e9dex",
    "sg:orig_category":"Non-Classified Establishments",
    "sg:phone":"+33 1 41 83 23 23",
    "sg:province":"Midi Pyr\u00e9n\u00e9es",
    "wof:name":"Rizerie Franco Am\u00e9ricaine Et Coloniale S.a.",
    "wof:placetype":"venue"
},
  "geometry": {"coordinates":[2.398987,48.894058],"type":"Point"}
}