{
  "type": "Feature",
  "properties": {
    "iso:country":"FR",
    "sg:address":"B.P. 24, 13610 Le Puy Sainte R\u00e9parade C\u00e9dex^^Quartier des Six Doigts, 13610 Le Puy Sainte R\u00e9parade",
    "sg:orig_category":"Non-Classified Establishments",
    "sg:phone":"+33 4 42 61 82 40",
    "sg:province":"Midi Pyr\u00e9n\u00e9es",
    "wof:name":"Provence Ingr\u00e9dients E.u.r.l.",
    "wof:placetype":"venue"
},
  "geometry": {"coordinates":[5.434375,43.662586],"type":"Point"}
}