{
  "type": "Feature",
  "properties": {
    "addr:full":"21 Rue Stanislas Colmar Alsace 68000",
    "addr:housenumber":"21",
    "addr:postcode":"68000",
    "addr:street":"Rue Stanislas Colmar",
    "iso:country":"FR",
    "sg:address":"21 Rue Stanislas",
    "sg:city":"Colmar",
    "sg:classifiers":[
        {
            "category":"Banks & Credit Unions",
            "subcategory":"Financial Services",
            "type":"Services"
        }
    ],
    "sg:phone":"+33 3 89 41 07 50",
    "sg:postcode":"68000",
    "sg:province":"Alsace",
    "sg:tags":[
        "banking",
        "finance",
        "insurance"
    ],
    "wof:name":"La Mondiale",
    "wof:placetype":"venue"
},
  "geometry": {"coordinates":[7.35285,48.080589],"type":"Point"}
}