{
  "type": "Feature",
  "properties": {
    "iso:country":"FR",
    "sg:address":"9-13 Rue Salvador Allende 95870 Bezons",
    "sg:classifiers":[
        {
            "category":"Bakery",
            "type":"Food & Drink"
        }
    ],
    "sg:phone":"+33 1 39 96 55 55",
    "sg:postcode":"95870",
    "sg:province":"Ile de France",
    "sg:tags":[
        "cake",
        "product",
        "related",
        "bread"
    ],
    "wof:name":"Lemonnier Freres Sa",
    "wof:placetype":"venue"
},
  "geometry": {"coordinates":[2.213741,48.918831],"type":"Point"}
}