{
  "type": "Feature",
  "properties": {
    "iso:country":"FR",
    "sg:address":"ZAC Saint Antoine - Lot. 35",
    "sg:city":"Saint Aun\u00e8s",
    "sg:orig_category":"Non-Classified Establishments",
    "sg:phone":"+33 4 67 70 04 44",
    "sg:postcode":"34130",
    "sg:province":"Languedoc-Roussillon",
    "wof:name":"A.g.e.i. S.a. - Approvisionnement G\u00e9n\u00e9ral Electrique Industriel",
    "wof:placetype":"venue"
},
  "geometry": {"coordinates":[4.0079,43.617867],"type":"Point"}
}