{
  "type": "Feature",
  "properties": {
    "addr:full":"Espace Economique 7 Quartiers Des Marrons 26140 Albon Rhone-Alpes 26140",
    "addr:housenumber":"7",
    "addr:postcode":"26140;26140",
    "addr:street":"Quartiers Des Marrons;Rhone-Alpes",
    "iso:country":"FR",
    "sg:address":"Espace Economique",
    "sg:city":"7 Quartiers Des Marrons 26140 Albon",
    "sg:classifiers":[
        {
            "category":"Banks & Credit Unions",
            "subcategory":"Investment Brokerage",
            "type":"Services"
        }
    ],
    "sg:phone":"+33 4 75 03 75 03",
    "sg:postcode":"26140",
    "sg:province":"Rhone-Alpes",
    "sg:tags":[
        "-",
        "transport",
        "related"
    ],
    "wof:name":"Base D'albon Sa",
    "wof:placetype":"venue"
},
  "geometry": {"coordinates":[4.818085,45.230911],"type":"Point"}
}