{
  "type": "Feature",
  "properties": {
    "addr:full":"B.P. 38, 67122 Molsheim C\u00e9dex^^38, Rte de la Hardt - Zone Industrielle, 67120 Molsheim Molsheim Alsace 67120",
    "addr:postcode":"67122;67120;67120",
    "addr:street":"B.P. 38;Rte De La Hardt Zone Industrielle",
    "iso:country":"FR",
    "sg:address":"B.P. 38, 67122 Molsheim C\u00e9dex^^38, Rte de la Hardt - Zone Industrielle, 67120 Molsheim",
    "sg:city":"Molsheim",
    "sg:orig_category":"Non-Classified Establishments",
    "sg:phone":"+33 3 88 38 24 88",
    "sg:postcode":"67120",
    "sg:province":"Alsace",
    "wof:name":"S.o.g.e.c. S.a.r.l. - Soci\u00e9t\u00e9 De G\u00e9rance Exploitation De Commerce",
    "wof:placetype":"venue"
},
  "geometry": {"coordinates":[7.490672,48.540382],"type":"Point"}
}