{
  "type": "Feature",
  "properties": {
    "iso:country":"FR",
    "sg:address":"9 Rue De Paris 35513 Cesson S\u00e9vign\u00e9 Cedex",
    "sg:classifiers":[
        {
            "category":"Autos & Motor Vehicles",
            "subcategory":"Automobile Sales",
            "type":"Retail Goods"
        }
    ],
    "sg:phone":"+33 2 99 83 40 00",
    "sg:province":"Ile de France",
    "sg:tags":[
        "equipment",
        "motor-cars",
        "transport"
    ],
    "wof:name":"Sobredia",
    "wof:placetype":"venue"
},
  "geometry": {"coordinates":[-1.599856,48.114235],"type":"Point"}
}