{
  "type": "Feature",
  "properties": {
    "iso:country":"FR",
    "sg:address":"62, Rue Nicolas Appert, 87000 Limoges",
    "sg:orig_category":"Non-Classified Establishments",
    "sg:phone":"+33 5 55 38 86 86",
    "sg:province":"Limousin",
    "wof:name":"Sanufic Couleur S.a.",
    "wof:placetype":"venue"
},
  "geometry": {"coordinates":[1.278098,45.877819],"type":"Point"}
}