{
  "type": "Feature",
  "properties": {
    "addr:full":"73, Av. Joseph Louis Lambot - ZI Toulon Est, 83078 Toulon C\u00e9dex Bourgogne",
    "addr:postcode":"83078",
    "addr:street":"73 Av. Joseph Louis Lambot Zi;Est",
    "iso:country":"FR",
    "sg:address":"73, Av. Joseph Louis Lambot - ZI Toulon Est, 83078 Toulon C\u00e9dex",
    "sg:orig_category":"Non-Classified Establishments",
    "sg:phone":"+33 4 94 08 00 21",
    "sg:province":"Bourgogne",
    "wof:name":"Griesser S.a.",
    "wof:placetype":"venue"
},
  "geometry": {"coordinates":[5.9052,43.13773],"type":"Point"}
}