{
  "type": "Feature",
  "properties": {
    "iso:country":"FR",
    "sg:address":"251, Bd P\u00e9reire, 75017 Paris",
    "sg:orig_category":"Unclassifiable Establishments",
    "sg:phone":"+33 1 53 81 82 53",
    "sg:province":"Ile de France",
    "wof:name":"Bsgl-cort Consultants S.a.",
    "wof:placetype":"venue"
},
  "geometry": {"coordinates":[2.286443,48.87878],"type":"Point"}
}