{
  "type": "Feature",
  "properties": {
    "iso:country":"FR",
    "sg:address":"44, Bd Lyautey, 41200 Romorantin Lanthenay",
    "sg:city":"Villefranche-sur-Cher",
    "sg:orig_category":"Unclassifiable Establishments",
    "sg:phone":"+33 2 54 76 15 38",
    "sg:postcode":"41200",
    "sg:province":"Centre",
    "wof:name":"Sologne Informatique S.a.",
    "wof:placetype":"venue"
},
  "geometry": {"coordinates":[1.738978,47.364437],"type":"Point"}
}