{
  "type": "Feature",
  "properties": {
    "iso:country":"FR",
    "sg:address":"Route de Feurs 42360 PANISSIERES",
    "sg:classifiers":[
        {
            "category":"Shopping",
            "subcategory":"Clothing, Apparel, & Fashions",
            "type":"Retail Goods"
        }
    ],
    "sg:phone":"+33 4 77 28 68 68",
    "sg:province":"Rhone-Alpes",
    "sg:tags":[
        "work",
        "clothes"
    ],
    "wof:name":"Granjard Et Fils Sa",
    "wof:placetype":"venue"
},
  "geometry": {"coordinates":[4.341532,45.787418],"type":"Point"}
}