{
  "type": "Feature",
  "properties": {
    "addr:full":"7 Rue De L'Esp\u00e9rance 49120 La Chapelle Rousselin Pays de Loire 49120",
    "addr:housenumber":"7",
    "addr:postcode":"49120;49120",
    "addr:street":"Rue De L'Espe \u0301Rance;Rousselin",
    "iso:country":"FR",
    "sg:address":"7 Rue De L'Esp\u00e9rance 49120 La Chapelle Rousselin",
    "sg:classifiers":[
        {
            "category":"Personal",
            "subcategory":"Shoe Repair & Shine",
            "type":"Services"
        }
    ],
    "sg:phone":"+33 2 41 30 70 11",
    "sg:postcode":"49120",
    "sg:province":"Pays de Loire",
    "sg:tags":[
        "leather",
        "textile",
        "clothing",
        "clothes"
    ],
    "wof:name":"Rouchette Sas",
    "wof:placetype":"venue"
},
  "geometry": {"coordinates":[-0.79467,47.21357],"type":"Point"}
}