{
  "type": "Feature",
  "properties": {
    "iso:country":"FR",
    "sg:address":"ZI du Val de l'Orne",
    "sg:city":"Conflans en Jarnisy",
    "sg:orig_category":"Non-Classified Establishments",
    "sg:phone":"+33 3 82 33 15 01",
    "sg:postcode":"54800",
    "sg:province":"Lorraine",
    "wof:name":"Wahu Bigmat S.a.",
    "wof:placetype":"venue"
},
  "geometry": {"coordinates":[5.909523,49.190132],"type":"Point"}
}