{
  "type": "Feature",
  "properties": {
    "addr:full":"Rue de la Gatine - ZI du Cormier - Le Tremplin Cholet Pays de Loire 49300",
    "addr:postcode":"49300",
    "addr:street":"Rue De La Gatine Zi Du Cormier Le",
    "iso:country":"FR",
    "sg:address":"Rue de la Gatine - ZI du Cormier - Le Tremplin",
    "sg:city":"Cholet",
    "sg:orig_category":"Unclassifiable Establishments",
    "sg:phone":"+33 2 41 70 05 12",
    "sg:postcode":"49300",
    "sg:province":"Pays de Loire",
    "wof:name":"Copylote S.a.r.l.",
    "wof:placetype":"venue"
},
  "geometry": {"coordinates":[-0.892689,46.99659],"type":"Point"}
}