{
  "type": "Feature",
  "properties": {
    "iso:country":"FR",
    "sg:address":"avenue du Mar\u00e9chal Lyautey 06210 Mandelieu la Napoule",
    "sg:classifiers":[
        {
            "category":"Manufacturing",
            "subcategory":"Food",
            "type":"Manufacturing & Wholesale Goods"
        }
    ],
    "sg:phone":"+33 4 93 48 16 16",
    "sg:province":"Haute Normandie",
    "sg:tags":[
        "frozen"
    ],
    "wof:name":"Angelini Sa",
    "wof:placetype":"venue"
},
  "geometry": {"coordinates":[6.948601,43.556732],"type":"Point"}
}