{
  "type": "Feature",
  "properties": {
    "addr:full":"10, Rue Lionel Terray, 92500 Rueil Malmaison Ile de France",
    "addr:housenumber":"10",
    "addr:postcode":"92500",
    "addr:street":"Rue Lionel Terray",
    "iso:country":"FR",
    "sg:address":"10, Rue Lionel Terray, 92500 Rueil Malmaison",
    "sg:orig_category":"Non-Classified Establishments",
    "sg:phone":"+33 1 55 47 59 59",
    "sg:province":"Ile de France",
    "wof:name":"Iteis S.a.s.",
    "wof:placetype":"venue"
},
  "geometry": {"coordinates":[2.180591,48.861134],"type":"Point"}
}