{
  "type": "Feature",
  "properties": {
    "iso:country":"FR",
    "sg:address":"Parc d'Activit\u00e9s du Coudrier - ZA des Quatre vents n\u00b011",
    "sg:city":"Boissy l'Aillerie",
    "sg:orig_category":"Non-Classified Establishments",
    "sg:phone":"+33 1 34 42 10 79",
    "sg:postcode":"95650",
    "sg:province":"Ile de France",
    "wof:name":"Eur'office S.a.r.l.",
    "wof:placetype":"venue"
},
  "geometry": {"coordinates":[-0.773337,47.787292],"type":"Point"}
}