{
  "type": "Feature",
  "properties": {
    "iso:country":"FR",
    "sg:address":"23, Rue Cl\u00e9ment Ader - ZI les Gloriets, 85340 Olonne sur Mer",
    "sg:orig_category":"Non-Classified Establishments",
    "sg:phone":"+33 2 51 21 05 60",
    "sg:province":"Pays de Loire",
    "wof:name":"M.a.p.o. S.a. - Moules Aviation Prototypes Outillages",
    "wof:placetype":"venue"
},
  "geometry": {"coordinates":[-1.773149,46.536518],"type":"Point"}
}