{
  "type": "Feature",
  "properties": {
    "addr:full":"ZA en Roche Chevagny les Chevri\u00e8res Bourgogne 71960",
    "addr:postcode":"71960",
    "addr:street":"Za En Roche Chevagny Les",
    "iso:country":"FR",
    "sg:address":"ZA en Roche",
    "sg:city":"Chevagny les Chevri\u00e8res",
    "sg:orig_category":"Unclassifiable Establishments",
    "sg:phone":"+33 3 85 20 55 40",
    "sg:postcode":"71960",
    "sg:province":"Bourgogne",
    "wof:name":"Perroux S.a.",
    "wof:placetype":"venue"
},
  "geometry": {"coordinates":[4.771036,46.331085],"type":"Point"}
}