{
  "type": "Feature",
  "properties": {
    "addr:full":"27, Rue de la Ribeyre, 15500 Massiac Massiac Auvergne 15500",
    "addr:housenumber":"27",
    "addr:postcode":"15500;massiac;15500",
    "addr:street":"Rue De La Ribeyre",
    "iso:country":"FR",
    "sg:address":"27, Rue de la Ribeyre, 15500 Massiac",
    "sg:city":"Massiac",
    "sg:orig_category":"Unclassifiable Establishments",
    "sg:phone":"+33 4 71 23 02 35",
    "sg:postcode":"15500",
    "sg:province":"Auvergne",
    "wof:name":"Saga M\u00e9dical S.a.",
    "wof:placetype":"venue"
},
  "geometry": {"coordinates":[3.195223,45.257847],"type":"Point"}
}