{
  "type": "Feature",
  "properties": {
    "addr:full":"RUE HENRI BESSEMER 19360 COSNAC Limousin",
    "addr:postcode":"19360",
    "addr:street":"Rue Henri Bessemer",
    "iso:country":"FR",
    "sg:address":"RUE HENRI BESSEMER 19360 COSNAC",
    "sg:classifiers":[
        {
            "category":"Manufacturing",
            "subcategory":"Metals",
            "type":"Manufacturing & Wholesale Goods"
        }
    ],
    "sg:phone":"+33 5 55 74 28 58",
    "sg:province":"Limousin",
    "sg:tags":[
        "sheet",
        "thin",
        "working"
    ],
    "wof:name":"Hycamep Floirat S.a.",
    "wof:placetype":"venue"
},
  "geometry": {"coordinates":[1.585306,45.135616],"type":"Point"}
}