{
  "type": "Feature",
  "properties": {
    "addr:full":"1, Rue du 14 Juillet - Zone Emploi, 62223 Saint Laurent Blangy Nord Pas-de-Calais",
    "addr:housenumber":"1",
    "addr:postcode":"62223",
    "addr:street":"Rue Du 14 Juillet Zone Emploi;Laurent Blangy Nord",
    "iso:country":"FR",
    "sg:address":"1, Rue du 14 Juillet - Zone Emploi, 62223 Saint Laurent Blangy",
    "sg:orig_category":"Unclassifiable Establishments",
    "sg:phone":"+33 3 21 50 41 00",
    "sg:province":"Nord Pas-de-Calais",
    "wof:name":"Setrem S.a.",
    "wof:placetype":"venue"
},
  "geometry": {"coordinates":[2.803593,50.303928],"type":"Point"}
}