{
  "type": "Feature",
  "properties": {
    "iso:country":"FR",
    "sg:address":"13 Av Albert Sorel 14000 Caen",
    "sg:city":"Caen",
    "sg:classifiers":[
        {
            "category":"Professional",
            "subcategory":"Business Services",
            "type":"Services"
        }
    ],
    "sg:phone":"+33 2 31 85 10 20",
    "sg:postcode":"14000",
    "sg:province":"Basse Normandie",
    "sg:tags":[
        "travel",
        "fair"
    ],
    "wof:name":"Caen Expo Congres",
    "wof:placetype":"venue"
},
  "geometry": {"coordinates":[-0.370867,49.177406],"type":"Point"}
}