{
  "type": "Feature",
  "properties": {
    "addr:full":"Rte De S\u00e9rignan 84100 Orange Centre",
    "addr:postcode":"84100",
    "addr:street":"Rte De Se\u0301Rignan",
    "iso:country":"FR",
    "sg:address":"Rte De S\u00e9rignan 84100 Orange",
    "sg:classifiers":[
        {
            "category":"Food Court",
            "type":"Food & Drink"
        }
    ],
    "sg:phone":"+33 4 90 11 86 86",
    "sg:province":"Centre",
    "sg:tags":[
        "product",
        "related"
    ],
    "wof:name":"Salavert Les Domaines Bernard Sldb",
    "wof:placetype":"venue"
},
  "geometry": {"coordinates":[4.830534,44.163425],"type":"Point"}
}