{
  "type": "Feature",
  "properties": {
    "addr:full":"Av d'Aurillac Figeac Midi Pyr\u00e9n\u00e9es 46000",
    "addr:postcode":"46000",
    "addr:street":"Av D'Aurillac",
    "iso:country":"FR",
    "sg:address":"Av d'Aurillac",
    "sg:city":"Figeac",
    "sg:orig_category":"Unclassifiable Establishments",
    "sg:phone":"+33 5 65 50 01 78",
    "sg:postcode":"46000",
    "sg:province":"Midi Pyr\u00e9n\u00e9es",
    "wof:name":"Pesage Midi Pyr\u00e9n\u00e9es S.a.r.l.",
    "wof:placetype":"venue"
},
  "geometry": {"coordinates":[2.042692,44.608234],"type":"Point"}
}