{
  "type": "Feature",
  "properties": {
    "addr:full":"Za En Grain 39360 Molinges Franche Comt\u00e9",
    "addr:postcode":"39360",
    "addr:street":"Za En Grain;Franche Comte\u0301",
    "iso:country":"FR",
    "sg:address":"Za En Grain 39360 Molinges",
    "sg:classifiers":[
        {
            "category":"Manufacturing",
            "subcategory":"Rubber & Plastics",
            "type":"Manufacturing & Wholesale Goods"
        }
    ],
    "sg:phone":"+33 3 84 41 42 00",
    "sg:province":"Franche Comt\u00e9",
    "wof:name":"Jb Technics Sa",
    "wof:placetype":"venue"
},
  "geometry": {"coordinates":[5.765685,46.356995],"type":"Point"}
}