{
  "type": "Feature",
  "properties": {
    "iso:country":"FR",
    "sg:address":"105-107 Rue Du Fbg St Honor\u00e9 75008 Paris",
    "sg:classifiers":[
        {
            "category":"Professional",
            "subcategory":"Advertising",
            "type":"Services"
        }
    ],
    "sg:phone":"+33 1 44 13 50 50",
    "sg:postcode":"75008",
    "sg:province":"Ile de France",
    "sg:tags":[
        "information",
        "medium",
        "communication"
    ],
    "wof:name":"Media Labtechnologie",
    "wof:placetype":"venue"
},
  "geometry": {"coordinates":[2.311516,48.872391],"type":"Point"}
}