{
  "type": "Feature",
  "properties": {
    "addr:full":"09800 Bethmale Midi Pyr\u00e9n\u00e9es 09800",
    "addr:postcode":"09800;09800",
    "iso:country":"FR",
    "sg:address":"09800 Bethmale",
    "sg:classifiers":[
        {
            "category":"Wholesale",
            "subcategory":"Machinery & Supplies",
            "type":"Manufacturing & Wholesale Goods"
        }
    ],
    "sg:phone":"+33 5 61 04 05 55",
    "sg:postcode":"09800",
    "sg:province":"Midi Pyr\u00e9n\u00e9es",
    "sg:tags":[
        "food",
        "processing",
        "-",
        "machine",
        "equipment",
        "engineering",
        "mechanical"
    ],
    "wof:name":"Fromagerie De La Core",
    "wof:placetype":"venue"
},
  "geometry": {"coordinates":[1.059858,42.886879],"type":"Point"}
}