{
  "type": "Feature",
  "properties": {
    "iso:country":"FR",
    "sg:address":"27, Rue du Dirigeable - ZI des Paluds, 13400 Aubagne",
    "sg:orig_category":"Non-Classified Establishments",
    "sg:phone":"+33 4 42 82 12 82",
    "sg:province":"Basse Normandie",
    "wof:name":"Mp S.n.c. - M\u00e9diterran\u00e9e Pr\u00e9fabrication",
    "wof:placetype":"venue"
},
  "geometry": {"coordinates":[5.5687,43.292141],"type":"Point"}
}