{
  "type": "Feature",
  "properties": {
    "iso:country":"FR",
    "sg:address":"Rue Des Augustins 33160 St M\u00e9dard En Jalles",
    "sg:city":"Salaunes",
    "sg:classifiers":[
        {
            "category":"Professional",
            "subcategory":"Engineering",
            "type":"Services"
        }
    ],
    "sg:phone":"+33 5 56 70 16 20",
    "sg:postcode":"33160",
    "sg:province":"Aquitaine",
    "sg:tags":[
        "machine",
        "-",
        "mechanical"
    ],
    "wof:name":"Polymeca Sa",
    "wof:placetype":"venue"
},
  "geometry": {"coordinates":[-0.688906,44.877518],"type":"Point"}
}