{
  "type": "Feature",
  "properties": {
    "iso:country":"FR",
    "sg:address":"Zone Industrielle 43700 Brives Charensac",
    "sg:city":"Blavozy",
    "sg:classifiers":[
        {
            "category":"Food & Beverages",
            "subcategory":"Fruits & Vegetables",
            "type":"Retail Goods"
        }
    ],
    "sg:phone":"+33 4 71 04 81 00",
    "sg:postcode":"43700",
    "sg:province":"Auvergne",
    "sg:tags":[
        "frozen",
        "product",
        "related"
    ],
    "wof:name":"Valette Sa",
    "wof:placetype":"venue"
},
  "geometry": {"coordinates":[3.924806,45.047512],"type":"Point"}
}