{
  "type": "Feature",
  "properties": {
    "addr:full":"Rte de Martel Souillac Midi Pyr\u00e9n\u00e9es 46200",
    "addr:postcode":"46200",
    "addr:street":"Rte De Martel",
    "iso:country":"FR",
    "sg:address":"Rte de Martel",
    "sg:city":"Souillac",
    "sg:orig_category":"Unclassifiable Establishments",
    "sg:phone":"+33 5 65 32 75 92",
    "sg:postcode":"46200",
    "sg:province":"Midi Pyr\u00e9n\u00e9es",
    "wof:name":"B.m.i. - B\u00e9ton Moul\u00e9 Industriel",
    "wof:placetype":"venue"
},
  "geometry": {"coordinates":[1.492953,44.907581],"type":"Point"}
}