{
  "type": "Feature",
  "properties": {
    "addr:full":"12, Rue Edouard Branly - Parc de la Madeleine, 44980 Sainte Luce sur Loire Pays de Loire",
    "addr:housenumber":"12",
    "addr:postcode":"44980",
    "addr:street":"Rue Edouard Branly Parc De La Madeleine;Luce;Loire",
    "iso:country":"FR",
    "sg:address":"12, Rue Edouard Branly - Parc de la Madeleine, 44980 Sainte Luce sur Loire",
    "sg:orig_category":"Non-Classified Establishments",
    "sg:phone":"+33 2 40 25 99 53",
    "sg:province":"Pays de Loire",
    "wof:name":"Horo Quartz Atlantique S.a.",
    "wof:placetype":"venue"
},
  "geometry": {"coordinates":[-1.479029,47.263371],"type":"Point"}
}