{
  "type": "Feature",
  "properties": {
    "addr:full":"22, Av de l'Abb\u00e9 Jean de B\u00e9co, 59720 Louvroil Nord Pas-de-Calais",
    "addr:postcode":"59720",
    "addr:street":"22 Av De L'Abbe \u0301 Jean De Be\u0301Co",
    "iso:country":"FR",
    "sg:address":"22, Av de l'Abb\u00e9 Jean de B\u00e9co, 59720 Louvroil",
    "sg:orig_category":"Unclassifiable Establishments",
    "sg:phone":"+33 3 27 53 05 30",
    "sg:province":"Nord Pas-de-Calais",
    "wof:name":"Hoogovens Myriad S.a.",
    "wof:placetype":"venue"
},
  "geometry": {"coordinates":[3.96214,50.263851],"type":"Point"}
}