{
  "type": "Feature",
  "properties": {
    "iso:country":"FR",
    "sg:address":"Rue des Framards - Acticentre B\u00e2t M",
    "sg:city":"Lesquin",
    "sg:orig_category":"Unclassifiable Establishments",
    "sg:phone":"+33 3 20 62 28 38",
    "sg:postcode":"59818",
    "sg:province":"Nord-Pas-de-Calais",
    "wof:name":"Cofatech Services S.a.",
    "wof:placetype":"venue"
},
  "geometry": {"coordinates":[3.11003,50.588009],"type":"Point"}
}