{
  "type": "Feature",
  "properties": {
    "addr:full":"59, Chemin Neuf - Parc d'Ativit\u00e9s Logis Neuf, 69780 Toussieu Rhone-Alpes 69780",
    "addr:housenumber":"59",
    "addr:postcode":"69780;69780",
    "addr:street":"Chemin Neuf Parc D'Ativite \u0301S Logis Neuf;Rhone-Alpes",
    "iso:country":"FR",
    "sg:address":"59, Chemin Neuf - Parc d'Ativit\u00e9s Logis Neuf, 69780 Toussieu",
    "sg:orig_category":"Unclassifiable Establishments",
    "sg:phone":"+33 4 72 48 10 04",
    "sg:postcode":"69780",
    "sg:province":"Rhone-Alpes",
    "wof:name":"Deltafroid E.u.r.l.",
    "wof:placetype":"venue"
},
  "geometry": {"coordinates":[4.99177,45.65134],"type":"Point"}
}