{
  "type": "Feature",
  "properties": {
    "addr:full":"Route Chatillon Coligny 45230 Montbouy Montbouy Centre 45230",
    "addr:housenumber":"montbouy",
    "addr:postcode":"45230;45230",
    "addr:street":"Route Chatillon Coligny",
    "iso:country":"FR",
    "sg:address":"Route Chatillon Coligny 45230 Montbouy",
    "sg:city":"Montbouy",
    "sg:classifiers":[
        {
            "category":"Shopping",
            "type":"Retail Goods"
        }
    ],
    "sg:phone":"+33 2 38 97 53 24",
    "sg:postcode":"45230",
    "sg:province":"Centre",
    "sg:tags":[
        "metallurgy",
        "finished",
        "-",
        "metalworking",
        "metallic"
    ],
    "wof:name":"Sa Gauvin",
    "wof:placetype":"venue"
},
  "geometry": {"coordinates":[2.822896,47.860512],"type":"Point"}
}