{
  "type": "Feature",
  "properties": {
    "iso:country":"FR",
    "sg:address":"49, Chemin de la Justice, 92290 Ch\u00e2tenay Malabry",
    "sg:orig_category":"Unclassifiable Establishments",
    "sg:phone":"+33 1 46 01 74 10",
    "sg:province":"Ile de France",
    "wof:name":"Trace Ing\u00e9nierie S.a.",
    "wof:placetype":"venue"
},
  "geometry": {"coordinates":[2.2573,48.766556],"type":"Point"}
}