{
  "type": "Feature",
  "properties": {
    "iso:country":"FR",
    "sg:address":"6 Rue Paul Vaillant Couturier 76120 Le Grand Quevilly",
    "sg:classifiers":[
        {
            "category":"Professional",
            "subcategory":"Business Services",
            "type":"Services"
        }
    ],
    "sg:phone":"+33 2 32 11 14 10",
    "sg:postcode":"76120",
    "sg:province":"Haute Normandie",
    "sg:tags":[
        "industrial",
        "advice",
        "motor-cars",
        "equipment",
        "vehicle",
        "transport"
    ],
    "wof:name":"Atelier Regional De Bobinage Sarl",
    "wof:placetype":"venue"
},
  "geometry": {"coordinates":[1.039639,49.417336],"type":"Point"}
}