{
  "type": "Feature",
  "properties": {
    "iso:country":"FR",
    "sg:address":"ZI",
    "sg:city":"Guipry",
    "sg:orig_category":"Non-Classified Establishments",
    "sg:phone":"+33 2 99 92 33 33",
    "sg:postcode":"35480",
    "sg:province":"Bretagne",
    "wof:name":"Placopl\u00e2tre Lambert",
    "wof:placetype":"venue"
},
  "geometry": {"coordinates":[-1.846595,47.825855],"type":"Point"}
}