{
  "type": "Feature",
  "properties": {
    "addr:full":"Rue de Napont Neufmanil Champagne 08700",
    "addr:postcode":"08700",
    "addr:street":"Rue De Napont;Champagne",
    "iso:country":"FR",
    "sg:address":"Rue de Napont",
    "sg:city":"Neufmanil",
    "sg:orig_category":"Unclassifiable Establishments",
    "sg:phone":"+33 3 24 53 67 67",
    "sg:postcode":"08700",
    "sg:province":"Champagne",
    "wof:name":"Pommier - Form\u00e9tal S.a.r.l.",
    "wof:placetype":"venue"
},
  "geometry": {"coordinates":[4.795734,49.811756],"type":"Point"}
}