{
  "type": "Feature",
  "properties": {
    "addr:full":"10 Rue De Perignat 63800 Cournon D Auvergne P\u00e9rignat-sur-Allier Auvergne 63800",
    "addr:housenumber":"10",
    "addr:postcode":"63800;63800",
    "addr:street":"Rue De Perignat;D",
    "iso:country":"FR",
    "sg:address":"10 Rue De Perignat 63800 Cournon D Auvergne",
    "sg:city":"P\u00e9rignat-sur-Allier",
    "sg:classifiers":[
        {
            "category":"Manufacturing",
            "subcategory":"Leather Goods",
            "type":"Manufacturing & Wholesale Goods"
        }
    ],
    "sg:phone":"+33 4 73 84 81 81",
    "sg:postcode":"63800",
    "sg:province":"Auvergne",
    "sg:tags":[
        "shoe"
    ],
    "wof:name":"Bagages Et Cuirs",
    "wof:placetype":"venue"
},
  "geometry": {"coordinates":[3.16549,45.742329],"type":"Point"}
}