{
  "type": "Feature",
  "properties": {
    "addr:full":"65 Av Antoine De Saint Exupery 62100 Calais Nord Pas-de-Calais",
    "addr:postcode":"62100",
    "addr:street":"65 Av Antoine De Saint Exupery;Calais;Pas-De-Calais",
    "iso:country":"FR",
    "sg:address":"65 Av Antoine De Saint Exupery 62100 Calais",
    "sg:classifiers":[
        {
            "category":"Professional",
            "type":"Services"
        }
    ],
    "sg:phone":"+33 3 21 97 55 55",
    "sg:province":"Nord Pas-de-Calais",
    "sg:tags":[
        "transport",
        "road"
    ],
    "wof:name":"Societe Nouvelle Zup Ambulances",
    "wof:placetype":"venue"
},
  "geometry": {"coordinates":[1.885904,50.946236],"type":"Point"}
}