{
  "type": "Feature",
  "properties": {
    "iso:country":"FR",
    "sg:address":"B.P. 603, 85015 La Roche sur Yon C\u00e9dex^^Rte de Lu\u00e7on - Les Coux , 85000 La Roche sur Yon",
    "sg:orig_category":"Non-Classified Establishments",
    "sg:phone":"+33 2 51 37 30 37",
    "sg:province":"Pays de Loire",
    "wof:name":"Soci\u00e9t\u00e9 Naullet S.a.",
    "wof:placetype":"venue"
},
  "geometry": {"coordinates":[-1.427199,46.67157],"type":"Point"}
}