{
  "type": "Feature",
  "properties": {
    "addr:full":"92 Chem De P\u00e9m\u00e9gnan Zi Du Conte 40000 Mont De Marsan Mont-de-Marsan Aquitaine 40000",
    "addr:housenumber":"92",
    "addr:postcode":"40000;40000",
    "addr:street":"Chem De Pe\u0301Me\u0301Gnan Zi Du Conte",
    "iso:country":"FR",
    "sg:address":"92 Chem De P\u00e9m\u00e9gnan Zi Du Conte 40000 Mont De Marsan",
    "sg:city":"Mont-de-Marsan",
    "sg:classifiers":[
        {
            "category":"Professional",
            "type":"Services"
        }
    ],
    "sg:phone":"+33 5 58 75 75 76",
    "sg:postcode":"40000",
    "sg:province":"Aquitaine",
    "sg:tags":[
        "transport",
        "road"
    ],
    "wof:name":"Demenagements Alain Masse Sa",
    "wof:placetype":"venue"
},
  "geometry": {"coordinates":[-0.498939,43.889503],"type":"Point"}
}