{
  "type": "Feature",
  "properties": {
    "iso:country":"FR",
    "sg:address":"17, Rue Mathias - Ch\u00e2teau Millet, 33640 Portets",
    "sg:city":"Portets",
    "sg:orig_category":"Non-Classified Establishments",
    "sg:phone":"+33 5 56 67 27 13",
    "sg:postcode":"33640",
    "sg:province":"Aquitaine",
    "wof:name":"Domaine De La Mette E.a.r.l.",
    "wof:placetype":"venue"
},
  "geometry": {"coordinates":[-0.402069,44.679958],"type":"Point"}
}