{
  "type": "Feature",
  "properties": {
    "addr:full":"23 Avenue Du Bois Vert 31120 Portet Sur Garonne Midi Pyr\u00e9n\u00e9es 31120",
    "addr:housenumber":"23",
    "addr:postcode":"31120;31120",
    "addr:street":"Avenue Du Bois Vert",
    "iso:country":"FR",
    "sg:address":"23 Avenue Du Bois Vert 31120 Portet Sur Garonne",
    "sg:classifiers":[
        {
            "category":"Shopping",
            "type":"Retail Goods"
        }
    ],
    "sg:phone":"+33 5 62 87 68 80",
    "sg:postcode":"31120",
    "sg:province":"Midi Pyr\u00e9n\u00e9es",
    "sg:tags":[
        "metallurgy",
        "finished",
        "-",
        "metalworking",
        "metallic"
    ],
    "wof:name":"Societe Europeene De Fabrication Et D Importation (sefi Europ Felix)",
    "wof:placetype":"venue"
},
  "geometry": {"coordinates":[1.380941,43.528709],"type":"Point"}
}