{
  "type": "Feature",
  "properties": {
    "addr:full":"ZI 85120 Antigny Pays de Loire 85120",
    "addr:postcode":"85120;85120",
    "addr:street":"Zi",
    "iso:country":"FR",
    "sg:address":"ZI 85120 Antigny",
    "sg:classifiers":[
        {
            "category":"Wholesale",
            "subcategory":"Furniture",
            "type":"Manufacturing & Wholesale Goods"
        }
    ],
    "sg:phone":"+33 2 51 51 65 09",
    "sg:postcode":"85120",
    "sg:province":"Pays de Loire",
    "sg:tags":[
        "cash-and-carry"
    ],
    "wof:name":"Couture Sa",
    "wof:placetype":"venue"
},
  "geometry": {"coordinates":[-0.771784,46.573956],"type":"Point"}
}