{
  "type": "Feature",
  "properties": {
    "iso:country":"FR",
    "sg:address":"B.P. 41058, 67382 Lingolsheim^^Rue Forlen, 67118 Geispolsheim",
    "sg:city":"Geispolsheim",
    "sg:orig_category":"Non-Classified Establishments",
    "sg:phone":"+33 3 88 55 12 12",
    "sg:postcode":"67400",
    "sg:province":"Alsace",
    "wof:name":"Mercure Prest Services S.a.r.l.",
    "wof:placetype":"venue"
},
  "geometry": {"coordinates":[7.643295,48.515163],"type":"Point"}
}