{
  "type": "Feature",
  "properties": {
    "addr:full":"2 rue De La Briqueterie 95380 LOUVRES Ile de France 95380",
    "addr:housenumber":"2",
    "addr:postcode":"95380;95380",
    "addr:street":"Rue De La Briqueterie;Ile De France",
    "iso:country":"FR",
    "sg:address":"2 rue De La Briqueterie 95380 LOUVRES",
    "sg:classifiers":[
        {
            "category":"Manufacturing",
            "subcategory":"Rubber & Plastics",
            "type":"Manufacturing & Wholesale Goods"
        }
    ],
    "sg:phone":"+33 1 34 47 41 41",
    "sg:postcode":"95380",
    "sg:province":"Ile de France",
    "sg:tags":[
        "made",
        "drive",
        "belt"
    ],
    "wof:name":"Gates S.a.r.l.",
    "wof:placetype":"venue"
},
  "geometry": {"coordinates":[2.494178,49.05093],"type":"Point"}
}