{
  "type": "Feature",
  "properties": {
    "addr:full":"route de Laumont 31450 Pompertuzat Midi Pyr\u00e9n\u00e9es",
    "addr:postcode":"31450",
    "addr:street":"Route De Laumont",
    "iso:country":"FR",
    "sg:address":"route de Laumont 31450 Pompertuzat",
    "sg:orig_category":"Reverse Osmosis Equipment, Hand-Operated, For Drinking Water Production On Liferafts",
    "sg:phone":"+33 5 61 27 80 27",
    "sg:province":"Midi Pyr\u00e9n\u00e9es",
    "wof:name":"C.2.r. Sarl",
    "wof:placetype":"venue"
},
  "geometry": {"coordinates":[1.50154,43.486065],"type":"Point"}
}