{
  "type": "Feature",
  "properties": {
    "iso:country":"FR",
    "sg:address":"99 Rue Du General De Gaulle 17139 Dompierre Sur Mer",
    "sg:orig_category":"Games and entertainment Horticulture Miscellaneous Products",
    "sg:phone":"+33 5 46 35 30 14",
    "sg:postcode":"17139",
    "sg:province":"Poitou-Charentes",
    "wof:name":"Societe Robin Et Cie",
    "wof:placetype":"venue"
},
  "geometry": {"coordinates":[-1.072668,46.185764],"type":"Point"}
}