{
  "type": "Feature",
  "properties": {
    "iso:country":"FR",
    "sg:address":"110 avenue du G\u00e9n\u00e9ral Leclerc 69300 Caluire et Cuire",
    "sg:orig_category":"Special Beverage Delivery Vans, Beverage Transporting Bodies, Mobile Counters",
    "sg:phone":"+33 4 78 23 63 00",
    "sg:province":"Rhone-Alpes",
    "wof:name":"Barraud Feniou Vax Rvm Industrie Sa",
    "wof:placetype":"venue"
},
  "geometry": {"coordinates":[4.868844,45.807053],"type":"Point"}
}