{
  "type": "Feature",
  "properties": {
    "iso:country":"FR",
    "sg:address":"Zac De St Martin Sud 34120 Pezenas",
    "sg:classifiers":[
        {
            "category":"Banks & Credit Unions",
            "subcategory":"Investment Brokerage",
            "type":"Services"
        }
    ],
    "sg:phone":"+33 4 67 35 48 48",
    "sg:province":"Languedoc-Roussillon",
    "sg:tags":[
        "-",
        "transport",
        "related"
    ],
    "wof:name":"Intermarche",
    "wof:placetype":"venue"
},
  "geometry": {"coordinates":[3.424247,43.461823],"type":"Point"}
}