{
  "type": "Feature",
  "properties": {
    "iso:country":"FR",
    "sg:address":"68, Av. de Paris, 91790 Boissy Sous Saint Yon",
    "sg:orig_category":"Non-Classified Establishments",
    "sg:phone":"+33 1 60 82 02 80",
    "sg:province":"Ile de France",
    "wof:name":"S.o.c.r.a.t.e.c.h. S.a. - Soci\u00e9t\u00e9 De Conceptions Et R\u00e9alisations D'automatisme De Production",
    "wof:placetype":"venue"
},
  "geometry": {"coordinates":[2.215218,48.546551],"type":"Point"}
}