{
  "type": "Feature",
  "properties": {
    "addr:full":"21 Avenue Bordeaux 86490 Beaumont Poitou-Charentes",
    "addr:housenumber":"21",
    "addr:postcode":"86490",
    "addr:street":"Avenue",
    "iso:country":"FR",
    "sg:address":"21 Avenue Bordeaux 86490 Beaumont",
    "sg:classifiers":[
        {
            "category":"Manufacturing",
            "subcategory":"Paper Products",
            "type":"Manufacturing & Wholesale Goods"
        }
    ],
    "sg:phone":"+33 5 49 19 13 10",
    "sg:province":"Poitou-Charentes",
    "sg:tags":[
        "packaging",
        "material",
        "-",
        "cardboard"
    ],
    "wof:name":"Papeterie Du Poitou Sa",
    "wof:placetype":"venue"
},
  "geometry": {"coordinates":[0.440061,46.731144],"type":"Point"}
}