{
  "type": "Feature",
  "properties": {
    "iso:country":"FR",
    "sg:address":"B.P. 19, 28231 Epernon C\u00e9dex^^16, Rue du Docteur Gilles, 28230 Epernon",
    "sg:city":"\u00c9pernon",
    "sg:orig_category":"Non-Classified Establishments",
    "sg:phone":"+33 2 37 23 51 00",
    "sg:postcode":"28230",
    "sg:province":"Centre",
    "wof:name":"B.m.s. S.a. - Bristol Mayers Squibb",
    "wof:placetype":"venue"
},
  "geometry": {"coordinates":[1.67713,48.609051],"type":"Point"}
}