{
  "type": "Feature",
  "properties": {
    "iso:country":"FR",
    "sg:address":"10 Rue Jean Moulin 74150 Rumilly",
    "sg:classifiers":[
        {
            "category":"Wholesale",
            "subcategory":"Machinery & Supplies",
            "type":"Manufacturing & Wholesale Goods"
        }
    ],
    "sg:phone":"+33 4 50 88 53 00",
    "sg:province":"Rhone-Alpes",
    "sg:tags":[
        "equipment",
        "precision"
    ],
    "wof:name":"Domis Sa",
    "wof:placetype":"venue"
},
  "geometry": {"coordinates":[5.955786,45.847469],"type":"Point"}
}