{
  "type": "Feature",
  "properties": {
    "addr:full":"Rte de la Gare - Zone Industrielle Muizon Champagne 51140",
    "addr:postcode":"51140",
    "addr:street":"Rte De La Gare;Industrielle;Champagne",
    "iso:country":"FR",
    "sg:address":"Rte de la Gare - Zone Industrielle",
    "sg:city":"Muizon",
    "sg:orig_category":"Unclassifiable Establishments",
    "sg:phone":"+33 3 26 02 91 25",
    "sg:postcode":"51140",
    "sg:province":"Champagne",
    "wof:name":"A.c.o.r.b.o.i.s. S.a.r.l.",
    "wof:placetype":"venue"
},
  "geometry": {"coordinates":[3.889085,49.275993],"type":"Point"}
}