{
  "type": "Feature",
  "properties": {
    "addr:full":"6, All\u00e9e des Nielles - ZI des C\u00e9sardes, 74600 Seynod Rhone-Alpes 74600",
    "addr:housenumber":"6",
    "addr:postcode":"74600;74600",
    "addr:street":"Alle\u0301E Des Nielles Zi Des Ce\u0301Sardes",
    "iso:country":"FR",
    "sg:address":"6, All\u00e9e des Nielles - ZI des C\u00e9sardes, 74600 Seynod",
    "sg:orig_category":"Unclassifiable Establishments",
    "sg:phone":"+33 4 50 69 19 72",
    "sg:postcode":"74600",
    "sg:province":"Rhone-Alpes",
    "wof:name":"Far S.a.",
    "wof:placetype":"venue"
},
  "geometry": {"coordinates":[6.100926,45.888924],"type":"Point"}
}