{
  "type": "Feature",
  "properties": {
    "iso:country":"FR",
    "sg:address":"13A, Rue de l'Energie - ZA Sud, 67210 Obernai",
    "sg:city":"Obernai",
    "sg:orig_category":"Unclassifiable Establishments",
    "sg:phone":"+33 825 28 05 80",
    "sg:postcode":"67210",
    "sg:province":"Alsace",
    "wof:name":"Nacel + S.a.r.l.",
    "wof:placetype":"venue"
},
  "geometry": {"coordinates":[7.494401,48.453373],"type":"Point"}
}