{
  "type": "Feature",
  "properties": {
    "addr:full":"18 Rue Guynemer 32000 Auch Midi Pyr\u00e9n\u00e9es 32000",
    "addr:housenumber":"18",
    "addr:postcode":"32000;32000",
    "addr:street":"Rue Guynemer",
    "iso:country":"FR",
    "sg:address":"18 Rue Guynemer 32000 Auch",
    "sg:classifiers":[
        {
            "category":"Banks & Credit Unions",
            "subcategory":"Financial Services",
            "type":"Services"
        }
    ],
    "sg:phone":"+33 5 62 63 31 98",
    "sg:postcode":"32000",
    "sg:province":"Midi Pyr\u00e9n\u00e9es",
    "sg:tags":[
        "banking",
        "insurance",
        "institution",
        "finance"
    ],
    "wof:name":"Caisse D'epargne Et De Prevoyance De Midi Pyrenees",
    "wof:placetype":"venue"
},
  "geometry": {"coordinates":[0.582477,43.647213],"type":"Point"}
}