{
  "type": "Feature",
  "properties": {
    "addr:full":"Av. d'Uriage Saint Pierre d'Allevard Rhone-Alpes 38830",
    "addr:postcode":"38830",
    "addr:street":"Av. D'Uriage;Rhone-Alpes",
    "iso:country":"FR",
    "sg:address":"Av. d'Uriage",
    "sg:city":"Saint Pierre d'Allevard",
    "sg:orig_category":"Non-Classified Establishments",
    "sg:phone":"+33 4 76 45 38 45",
    "sg:postcode":"38830",
    "sg:province":"Rhone-Alpes",
    "wof:name":"Ugimag S.a.",
    "wof:placetype":"venue"
},
  "geometry": {"coordinates":[6.045957,45.373383],"type":"Point"}
}