{
  "type": "Feature",
  "properties": {
    "addr:full":"2, Route de Rehon, 54135 Mexy Lorraine",
    "addr:housenumber":"2",
    "addr:postcode":"54135",
    "addr:street":"Route De Rehon",
    "iso:country":"FR",
    "sg:address":"2, Route de Rehon, 54135 Mexy",
    "sg:orig_category":"Unclassifiable Establishments",
    "sg:phone":"+33 3 82 24 53 74",
    "sg:province":"Lorraine",
    "wof:name":"Pagnoncelli Fr\u00e8res S.a.r.l.",
    "wof:placetype":"venue"
},
  "geometry": {"coordinates":[5.778489,49.501949],"type":"Point"}
}