{
  "type": "Feature",
  "properties": {
    "iso:country":"FR",
    "sg:address":"Lieu-Dit Za D Eculaz Champ Tissot 74930 REIGNIER",
    "sg:classifiers":[
        {
            "category":"Professional",
            "subcategory":"Printing & Photocopies",
            "type":"Services"
        }
    ],
    "sg:phone":"+33 4 50 43 81 00",
    "sg:province":"Rhone-Alpes",
    "sg:tags":[
        "offset"
    ],
    "wof:name":"Icg Sa",
    "wof:placetype":"venue"
},
  "geometry": {"coordinates":[6.218197,46.091667],"type":"Point"}
}