{
  "type": "Feature",
  "properties": {
    "addr:full":"B.P. 2, 77860 Quincy Voisins^^262, Av. Mar\u00e9chal Foch, 77860 Quincy Voisins Ile de France 77860",
    "addr:housenumber":"2",
    "addr:postcode":"77860;77860;77860",
    "addr:street":"B.P.;Av. Mare\u0301Chal Foch",
    "iso:country":"FR",
    "sg:address":"B.P. 2, 77860 Quincy Voisins^^262, Av. Mar\u00e9chal Foch, 77860 Quincy Voisins",
    "sg:orig_category":"Non-Classified Establishments",
    "sg:phone":"+33 1 64 63 41 70",
    "sg:postcode":"77860",
    "sg:province":"Ile de France",
    "wof:name":"Docks De Quincy Voisins S.a.",
    "wof:placetype":"venue"
},
  "geometry": {"coordinates":[2.862415,48.897308],"type":"Point"}
}