{
  "type": "Feature",
  "properties": {
    "iso:country":"FR",
    "sg:address":"B.P. 426, 78055 Montigny le Bretonneux C\u00e9dex^^1, Av. du Parc, 78180 Montigny le Bretonneux",
    "sg:orig_category":"Non-Classified Establishments",
    "sg:phone":"+33 1 30 12 85 00",
    "sg:province":"Ile de France",
    "wof:name":"Socotec Industrie S.a.",
    "wof:placetype":"venue"
},
  "geometry": {"coordinates":[2.04549,48.785019],"type":"Point"}
}