{
  "type": "Feature",
  "properties": {
    "addr:full":"Haute Limoug\u00e8re 37230 Fondettes Fondettes Centre 37230",
    "addr:postcode":"37230;37230",
    "iso:country":"FR",
    "sg:address":"Haute Limoug\u00e8re 37230 Fondettes",
    "sg:city":"Fondettes",
    "sg:classifiers":[
        {
            "category":"Professional",
            "subcategory":"Engineering",
            "type":"Services"
        }
    ],
    "sg:phone":"+33 2 47 42 18 03",
    "sg:postcode":"37230",
    "sg:province":"Centre",
    "sg:tags":[
        "machine",
        "-",
        "mechanical"
    ],
    "wof:name":"Ets Dumas Sarl",
    "wof:placetype":"venue"
},
  "geometry": {"coordinates":[0.622701,47.409626],"type":"Point"}
}