{
  "type": "Feature",
  "properties": {
    "addr:full":"Les Planes Nord 30560 St Hilaire De Brethmas Languedoc-Roussillon",
    "addr:postcode":"30560",
    "addr:street":"Brethmas",
    "iso:country":"FR",
    "sg:address":"Les Planes Nord 30560 St Hilaire De Brethmas",
    "sg:classifiers":[
        {
            "category":"Professional",
            "type":"Services"
        }
    ],
    "sg:phone":"+33 4 66 61 31 14",
    "sg:province":"Languedoc-Roussillon",
    "sg:tags":[
        "transport",
        "road"
    ],
    "wof:name":"Capelle (transports) Sa",
    "wof:placetype":"venue"
},
  "geometry": {"coordinates":[4.104405,44.100056],"type":"Point"}
}