{
  "type": "Feature",
  "properties": {
    "iso:country":"FR",
    "sg:address":"3 Rue Pi\u00e8rre Emmanuel 95330 Domont",
    "sg:classifiers":[
        {
            "category":"Home & Garden",
            "subcategory":"Furniture",
            "type":"Retail Goods"
        }
    ],
    "sg:phone":"+33 1 39 91 04 76",
    "sg:postcode":"95330",
    "sg:province":"Ile de France",
    "sg:tags":[
        "household",
        "wood"
    ],
    "wof:name":"Quadro Sarl",
    "wof:placetype":"venue"
},
  "geometry": {"coordinates":[2.346122,49.026119],"type":"Point"}
}