{
  "type": "Feature",
  "properties": {
    "addr:full":"B.P. 98, 54250 Champigneulles^^Rue du Canal - ZI, 54250 Champigneulles Lorraine",
    "addr:postcode":"54250;54250",
    "addr:street":"B.P. 98;Du Canal Zi",
    "iso:country":"FR",
    "sg:address":"B.P. 98, 54250 Champigneulles^^Rue du Canal - ZI, 54250 Champigneulles",
    "sg:orig_category":"Non-Classified Establishments",
    "sg:phone":"+33 3 83 31 26 82",
    "sg:province":"Lorraine",
    "wof:name":"Technoram S.a.r.l.",
    "wof:placetype":"venue"
},
  "geometry": {"coordinates":[6.16533,48.73391],"type":"Point"}
}