{
  "type": "Feature",
  "properties": {
    "iso:country":"FR",
    "sg:address":"755 Av Ambroise Croizat 38920 Crolles",
    "sg:city":"Crolles",
    "sg:classifiers":[
        {
            "category":"Transit Center",
            "subcategory":"Freight",
            "type":"Transportation"
        }
    ],
    "sg:phone":"+33 4 76 08 19 37",
    "sg:postcode":"38190",
    "sg:province":"Rhone-Alpes",
    "sg:tags":[
        "metallurgy",
        "pipe",
        "metalworking",
        "sheet"
    ],
    "wof:name":"Defi Services",
    "wof:placetype":"venue"
},
  "geometry": {"coordinates":[5.889093,45.271774],"type":"Point"}
}