{
  "type": "Feature",
  "properties": {
    "addr:full":"2 Place Grimaldi 06000 Nice Pays de Loire",
    "addr:housenumber":"2",
    "addr:postcode":"06000",
    "addr:street":"Place Grimaldi",
    "iso:country":"FR",
    "sg:address":"2 Place Grimaldi 06000 Nice",
    "sg:classifiers":[
        {
            "category":"Shopping",
            "type":"Retail Goods"
        }
    ],
    "sg:phone":"+33 4 93 87 89 48",
    "sg:province":"Pays de Loire",
    "sg:tags":[
        "metallurgy",
        "finished",
        "-",
        "metalworking",
        "metallic"
    ],
    "wof:name":"Clerapid",
    "wof:placetype":"venue"
},
  "geometry": {"coordinates":[7.265166,43.697826],"type":"Point"}
}