{
  "type": "Feature",
  "properties": {
    "addr:full":"Za Aux Morands 71210 Montchanin Montchanin Bourgogne 71210",
    "addr:postcode":"71210;71210",
    "addr:street":"Za Aux Morands",
    "iso:country":"FR",
    "sg:address":"Za Aux Morands 71210 Montchanin",
    "sg:city":"Montchanin",
    "sg:classifiers":[
        {
            "category":"Home & Garden",
            "subcategory":"Furniture",
            "type":"Retail Goods"
        }
    ],
    "sg:phone":"+33 3 85 78 52 00",
    "sg:postcode":"71210",
    "sg:province":"Bourgogne",
    "sg:tags":[
        "household",
        "wood"
    ],
    "wof:name":"Matrex Industries",
    "wof:placetype":"venue"
},
  "geometry": {"coordinates":[4.46917,46.748814],"type":"Point"}
}