{
  "type": "Feature",
  "properties": {
    "iso:country":"FR",
    "sg:address":"Rue des Petites Combes - ZAC des Baterses Nord",
    "sg:city":"Beynost",
    "sg:orig_category":"Unclassifiable Establishments",
    "sg:phone":"+33 4 78 55 87 87",
    "sg:postcode":"01700",
    "sg:province":"Rhone-Alpes",
    "wof:name":"St\u00e9phanoise Des Tissus Et Rubans S.a.",
    "wof:placetype":"venue"
},
  "geometry": {"coordinates":[4.96153,45.828629],"type":"Point"}
}