{
  "type": "Feature",
  "properties": {
    "addr:full":"Rte d'Angoul\u00eame Villebois Lavalette Poitou-Charentes 16320",
    "addr:postcode":"16320",
    "addr:street":"Rte D'Angoule \u0302Me Villebois Lavalette",
    "iso:country":"FR",
    "sg:address":"Rte d'Angoul\u00eame",
    "sg:city":"Villebois Lavalette",
    "sg:orig_category":"Unclassifiable Establishments",
    "sg:phone":"+33 5 45 64 92 10",
    "sg:postcode":"16320",
    "sg:province":"Poitou-Charentes",
    "wof:name":"Etablissements Ferrand S.a.",
    "wof:placetype":"venue"
},
  "geometry": {"coordinates":[0.27803,45.48233],"type":"Point"}
}