{
  "type": "Feature",
  "properties": {
    "iso:country":"FR",
    "sg:address":"B.P. 74, 31322 Castanet Tolosan C\u00e9dex^^All\u00e9e Camille Soula, 31320 Vigoulet Auzil",
    "sg:orig_category":"Non-Classified Establishments",
    "sg:phone":"+33 5 61 75 52 00",
    "sg:province":"Midi Pyr\u00e9n\u00e9es",
    "wof:name":"Laboratoires Pierre Fabre Dermo-cosm\u00e9tique S.a.",
    "wof:placetype":"venue"
},
  "geometry": {"coordinates":[1.452547,43.482239],"type":"Point"}
}