{
  "type": "Feature",
  "properties": {
    "iso:country":"FR",
    "sg:address":"42, Rue des Bardines - ZI, 63370 Lempdes",
    "sg:city":"Lempdes",
    "sg:orig_category":"Non-Classified Establishments",
    "sg:phone":"+33 4 73 61 67 98",
    "sg:postcode":"63370",
    "sg:province":"Auvergne",
    "wof:name":"A.a.c.d. E.u.r.l. - Auvergne Assistance Chimie Distribution",
    "wof:placetype":"venue"
},
  "geometry": {"coordinates":[3.197355,45.768345],"type":"Point"}
}