{
  "type": "Feature",
  "properties": {
    "iso:country":"FR",
    "sg:address":"17 Rue R Et Y Noutary 33130 Begles",
    "sg:city":"B\u00e8gles",
    "sg:classifiers":[
        {
            "category":"Wholesale",
            "subcategory":"Machinery & Supplies",
            "type":"Manufacturing & Wholesale Goods"
        }
    ],
    "sg:phone":"+33 5 56 49 51 39",
    "sg:postcode":"33130",
    "sg:province":"Aquitaine",
    "sg:tags":[
        "handling",
        "material",
        "-",
        "machine",
        "equipment",
        "engineering",
        "mechanical"
    ],
    "wof:name":"Potain",
    "wof:placetype":"venue"
},
  "geometry": {"coordinates":[-0.553904,44.808079],"type":"Point"}
}