{
  "type": "Feature",
  "properties": {
    "iso:country":"FR",
    "sg:address":"B.P. 1, 67110 Reichshoffen^^Rue des Forges, 67110 Reichshoffen",
    "sg:city":"Reichshoffen",
    "sg:orig_category":"Non-Classified Establishments",
    "sg:phone":"+33 3 88 80 86 80",
    "sg:postcode":"67110",
    "sg:province":"Alsace",
    "wof:name":"Cogifer Industries S.a.",
    "wof:placetype":"venue"
},
  "geometry": {"coordinates":[7.663385,48.932232],"type":"Point"}
}