{
  "type": "Feature",
  "properties": {
    "iso:country":"FR",
    "sg:address":"17, Rte de Sedan, 08450 Haraucourt",
    "sg:city":"Omicourt",
    "sg:orig_category":"Unclassifiable Establishments",
    "sg:phone":"+33 3 24 26 71 11",
    "sg:postcode":"08450",
    "sg:province":"Champagne",
    "wof:name":"S.3.a. S.a.r.l. - Alexandre Et Antoine",
    "wof:placetype":"venue"
},
  "geometry": {"coordinates":[4.96365,49.626091],"type":"Point"}
}