{
  "type": "Feature",
  "properties": {
    "addr:full":"6 Rue Rouget De Lisle 39000 Lons Le Saunier Franche Comt\u00e9 39000",
    "addr:housenumber":"6",
    "addr:postcode":"39000;39000",
    "addr:street":"Rue Rouget De Lisle;Franche Comte\u0301",
    "iso:country":"FR",
    "sg:address":"6 Rue Rouget De Lisle 39000 Lons Le Saunier",
    "sg:classifiers":[
        {
            "category":"Banks & Credit Unions",
            "subcategory":"Financial Services",
            "type":"Services"
        }
    ],
    "sg:phone":"+33 3 84 85 63 63",
    "sg:postcode":"39000",
    "sg:province":"Franche Comt\u00e9",
    "sg:tags":[
        "banking",
        "insurance",
        "institution",
        "finance"
    ],
    "wof:name":"Credit Lyonnais",
    "wof:placetype":"venue"
},
  "geometry": {"coordinates":[5.554407,46.67244],"type":"Point"}
}