{
  "type": "Feature",
  "properties": {
    "addr:full":"1 R De Cit\u00e9s 71405 Autun Cedex Bourgogne",
    "addr:housenumber":"1",
    "addr:postcode":"71405",
    "addr:street":"R De Cite\u0301S",
    "iso:country":"FR",
    "sg:address":"1 R De Cit\u00e9s 71405 Autun Cedex",
    "sg:classifiers":[
        {
            "category":"Banks & Credit Unions",
            "subcategory":"Financial Services",
            "type":"Services"
        }
    ],
    "sg:phone":"+33 810 81 10 23",
    "sg:province":"Bourgogne",
    "sg:tags":[
        "banking",
        "insurance",
        "institution",
        "finance"
    ],
    "wof:name":"Caisse D'epargne De Bourgogne",
    "wof:placetype":"venue"
},
  "geometry": {"coordinates":[4.298893,46.95332],"type":"Point"}
}