{
  "type": "Feature",
  "properties": {
    "addr:full":"Av. Charles Moulet - ZAC de Croix Sainte Martigues Midi Pyr\u00e9n\u00e9es 13500",
    "addr:postcode":"13500",
    "addr:street":"Av. Charles Moulet Zac De Croix",
    "iso:country":"FR",
    "sg:address":"Av. Charles Moulet - ZAC de Croix Sainte",
    "sg:city":"Martigues",
    "sg:orig_category":"Unclassifiable Establishments",
    "sg:phone":"+33 4 42 49 35 49",
    "sg:postcode":"13500",
    "sg:province":"Midi Pyr\u00e9n\u00e9es",
    "wof:name":"S.m.g.f. S.a.r.l. - Soci\u00e9t\u00e9 De M\u00e9canique G\u00e9n\u00e9rale Fontsarade",
    "wof:placetype":"venue"
},
  "geometry": {"coordinates":[5.055235,43.406536],"type":"Point"}
}