{
  "type": "Feature",
  "properties": {
    "addr:full":"2 Rue Du Dr. Pascal Za Du Rondeau 38434 Echirolles Cedex \u00c9chirolles Rhone-Alpes 38130",
    "addr:housenumber":"2",
    "addr:postcode":"38434;38130",
    "addr:street":"Rue Du Dr. Pascal Za Du Rondeau",
    "iso:country":"FR",
    "sg:address":"2 Rue Du Dr. Pascal Za Du Rondeau 38434 Echirolles Cedex",
    "sg:city":"\u00c9chirolles",
    "sg:classifiers":[
        {
            "category":"Utilities",
            "subcategory":"Electric",
            "type":"Services"
        }
    ],
    "sg:phone":"+33 4 76 09 14 51",
    "sg:postcode":"38130",
    "sg:province":"Rhone-Alpes",
    "sg:tags":[
        "electricity",
        "electronic",
        "electrical",
        "equipment"
    ],
    "wof:name":"Ets Dervieux Sa",
    "wof:placetype":"venue"
},
  "geometry": {"coordinates":[5.71924,45.139801],"type":"Point"}
}