{
  "type": "Feature",
  "properties": {
    "iso:country":"FR",
    "sg:address":"815 Av Joliot Cuerie 83130 La Garde",
    "sg:city":"La Garde",
    "sg:classifiers":[
        {
            "category":"Manufacturing",
            "subcategory":"Jewelry",
            "type":"Manufacturing & Wholesale Goods"
        }
    ],
    "sg:phone":"+33 4 94 14 90 02",
    "sg:postcode":"38520",
    "sg:province":"Rhone-Alpes",
    "sg:tags":[
        "product",
        "miscellaneous",
        "jewellery"
    ],
    "wof:name":"Etablissements Moucheront",
    "wof:placetype":"venue"
},
  "geometry": {"coordinates":[6.009775,43.124866],"type":"Point"}
}