{
  "type": "Feature",
  "properties": {
    "iso:country":"FR",
    "sg:address":"Rte d'Avignon",
    "sg:city":"Cabannes",
    "sg:orig_category":"Non-Classified Establishments",
    "sg:phone":"+33 4 90 95 32 61",
    "sg:postcode":"13440",
    "sg:province":"Provence-Alpes-C\u00f4te d'Azur",
    "wof:name":"Nature Bois Emballages S.a.",
    "wof:placetype":"venue"
},
  "geometry": {"coordinates":[4.985917,43.872082],"type":"Point"}
}