{
  "type": "Feature",
  "properties": {
    "iso:country":"FR",
    "sg:address":"8, Rue Danton, 78800 Houilles",
    "sg:orig_category":"Unclassifiable Establishments",
    "sg:phone":"+33 1 39 14 53 96",
    "sg:province":"Ile de France",
    "wof:name":"Gravoplex S.a.r.l.",
    "wof:placetype":"venue"
},
  "geometry": {"coordinates":[2.1828,48.920784],"type":"Point"}
}