{
  "type": "Feature",
  "properties": {
    "addr:full":"B.P. 24, 59175 Templemars^^Rue de l'Epinoy - Parc d'Activit\u00e9s, 59175 Templemars Nord Pas-de-Calais 59175",
    "addr:postcode":"59175;59175;59175",
    "addr:street":"B.P. 24;L'Epinoy;\u0301S",
    "iso:country":"FR",
    "sg:address":"B.P. 24, 59175 Templemars^^Rue de l'Epinoy - Parc d'Activit\u00e9s, 59175 Templemars",
    "sg:orig_category":"Non-Classified Establishments",
    "sg:phone":"+33 3 20 16 75 75",
    "sg:postcode":"59175",
    "sg:province":"Nord Pas-de-Calais",
    "wof:name":"Castorama France S.a.",
    "wof:placetype":"venue"
},
  "geometry": {"coordinates":[3.068528,50.567921],"type":"Point"}
}