{
  "type": "Feature",
  "properties": {
    "addr:full":"Bas De Domelin 73270 Beaufort Sur Doron Rhone-Alpes 73270",
    "addr:postcode":"73270;73270",
    "addr:street":"Bas;Rhone-Alpes",
    "iso:country":"FR",
    "sg:address":"Bas De Domelin 73270 Beaufort Sur Doron",
    "sg:classifiers":[
        {
            "category":"Manufacturing",
            "subcategory":"Metals",
            "type":"Manufacturing & Wholesale Goods"
        }
    ],
    "sg:phone":"+33 4 79 38 34 11",
    "sg:postcode":"73270",
    "sg:province":"Rhone-Alpes",
    "sg:tags":[
        "metallurgy",
        "metalworking"
    ],
    "wof:name":"Transrol",
    "wof:placetype":"venue"
},
  "geometry": {"coordinates":[6.56886,45.686649],"type":"Point"}
}