{
  "type": "Feature",
  "properties": {
    "addr:full":"15 rue Georges Pitard 75015 Paris Ile de France 75015",
    "addr:housenumber":"15",
    "addr:postcode":"75015;75015",
    "addr:street":"Rue Georges Pitard",
    "iso:country":"FR",
    "sg:address":"15 rue Georges Pitard 75015 Paris",
    "sg:classifiers":[
        {
            "category":"Professional",
            "subcategory":"Business Services",
            "type":"Services"
        }
    ],
    "sg:phone":"+33 1 55 76 17 55",
    "sg:postcode":"75015",
    "sg:province":"Ile de France",
    "sg:tags":[
        "agency",
        "export"
    ],
    "wof:name":"Via Europe Pour Le Commerce International Sa",
    "wof:placetype":"venue"
},
  "geometry": {"coordinates":[2.310541,48.834698],"type":"Point"}
}