{
  "type": "Feature",
  "properties": {
    "addr:full":"RN 151 Neuvy Pailloux Centre 36100",
    "addr:postcode":"36100",
    "addr:street":"Rn 151 Neuvy Pailloux",
    "iso:country":"FR",
    "sg:address":"RN 151",
    "sg:city":"Neuvy Pailloux",
    "sg:orig_category":"Unclassifiable Establishments",
    "sg:phone":"+33 2 54 49 52 66",
    "sg:postcode":"36100",
    "sg:province":"Centre",
    "wof:name":"Tisserand S.a.",
    "wof:placetype":"venue"
},
  "geometry": {"coordinates":[1.927415,46.825329],"type":"Point"}
}