{
  "type": "Feature",
  "properties": {
    "addr:full":"Rue Villiers De L'Isle Adam Zac De Plerin Pl\u00e9rin Bretagne 22190",
    "addr:postcode":"22190",
    "addr:street":"Rue Villiers De L'Isle Adam Zac De Plerin Ple\u0301Rin",
    "iso:country":"FR",
    "sg:address":"Rue Villiers De L'Isle Adam Zac De Plerin",
    "sg:city":"Pl\u00e9rin",
    "sg:classifiers":[
        {
            "category":"Banks & Credit Unions",
            "subcategory":"Financial Services",
            "type":"Services"
        }
    ],
    "sg:phone":"+33 2 96 79 82 82",
    "sg:postcode":"22190",
    "sg:province":"Bretagne",
    "sg:tags":[
        "banking",
        "finance",
        "insurance"
    ],
    "wof:name":"Fiduciaire Juridique Et Fiscale De France Fidal (fjff) Fidal",
    "wof:placetype":"venue"
},
  "geometry": {"coordinates":[-2.78152,48.546719],"type":"Point"}
}