{
  "type": "Feature",
  "properties": {
    "addr:full":"1 bis, Passage Duhesme, 75018 Paris Ile de France",
    "addr:housenumber":"1 bis",
    "addr:postcode":"75018",
    "addr:street":"Passage Duhesme",
    "iso:country":"FR",
    "sg:address":"1 bis, Passage Duhesme, 75018 Paris",
    "sg:orig_category":"Non-Classified Establishments",
    "sg:phone":"+33 1 42 64 96 45",
    "sg:province":"Ile de France",
    "wof:name":"Sopanet S.a.r.l.",
    "wof:placetype":"venue"
},
  "geometry": {"coordinates":[2.346655,48.896317],"type":"Point"}
}