{
  "type": "Feature",
  "properties": {
    "iso:country":"FR",
    "sg:address":"45 Avenue Charles De Gaulle 71400 Autun",
    "sg:city":"Autun",
    "sg:classifiers":[
        {
            "category":"Manufacturing",
            "subcategory":"Wood Products",
            "type":"Manufacturing & Wholesale Goods"
        }
    ],
    "sg:phone":"+33 3 85 86 98 76",
    "sg:postcode":"71400",
    "sg:province":"Bourgogne",
    "sg:tags":[
        "professional",
        "furniture"
    ],
    "wof:name":"Ste Hotellerie Restauration Services",
    "wof:placetype":"venue"
},
  "geometry": {"coordinates":[4.294942,46.954029],"type":"Point"}
}