{
  "type": "Feature",
  "properties": {
    "addr:full":"51- 57 Rue Henri Gautier 93000 Bobigny Ile de France 93000",
    "addr:housenumber":"57",
    "addr:postcode":"93000;ile;93000",
    "addr:street":"Rue Henri Gautier;France",
    "iso:country":"FR",
    "sg:address":"51- 57 Rue Henri Gautier 93000 Bobigny",
    "sg:orig_category":"Clothing accessories Paper and Cardboard Paper and cardboard - Packaging materials Textiles and Clot",
    "sg:phone":"+33 1 48 45 48 48",
    "sg:postcode":"93000",
    "sg:province":"Ile de France",
    "wof:name":"Carton Flash Sa",
    "wof:placetype":"venue"
},
  "geometry": {"coordinates":[2.427078,48.904652],"type":"Point"}
}