{
  "type": "Feature",
  "properties": {
    "addr:full":"La Croix Leigne 42190 Chandon Rhone-Alpes 42190",
    "addr:postcode":"42190;42190",
    "addr:street":"La Croix Leigne",
    "iso:country":"FR",
    "sg:address":"La Croix Leigne 42190 Chandon",
    "sg:classifiers":[
        {
            "category":"Professional",
            "subcategory":"Engineering",
            "type":"Services"
        }
    ],
    "sg:phone":"+33 4 77 60 01 55",
    "sg:postcode":"42190",
    "sg:province":"Rhone-Alpes",
    "sg:tags":[
        "machine",
        "-",
        "mechanical"
    ],
    "wof:name":"Poyet Sarl",
    "wof:placetype":"venue"
},
  "geometry": {"coordinates":[4.189885,46.148838],"type":"Point"}
}