{
  "type": "Feature",
  "properties": {
    "iso:country":"FR",
    "sg:address":"520, Rte de Pringy, 74370 Argonay",
    "sg:orig_category":"Unclassifiable Establishments",
    "sg:phone":"+33 4 50 27 29 15",
    "sg:postcode":"74370",
    "sg:province":"Rhone-Alpes",
    "wof:name":"Figel S.a.",
    "wof:placetype":"venue"
},
  "geometry": {"coordinates":[6.131106,45.943893],"type":"Point"}
}