{
  "type": "Feature",
  "properties": {
    "iso:country":"FR",
    "sg:address":"ZA de l'Alouette",
    "sg:city":"Saint Michel",
    "sg:orig_category":"Unclassifiable Establishments",
    "sg:phone":"+33 3 23 58 57 57",
    "sg:postcode":"02830",
    "sg:province":"Picardie",
    "wof:name":"Profil'n S.a.r.l.",
    "wof:placetype":"venue"
},
  "geometry": {"coordinates":[4.112969,49.914646],"type":"Point"}
}