{
  "type": "Feature",
  "properties": {
    "iso:country":"FR",
    "sg:address":"5 rue du Canal 67204 Achenheim",
    "sg:city":"Achenheim",
    "sg:classifiers":[
        {
            "category":"Professional",
            "type":"Services"
        }
    ],
    "sg:phone":"+33 3 90 29 34 24",
    "sg:postcode":"67204",
    "sg:province":"Alsace",
    "sg:tags":[
        "transport"
    ],
    "wof:name":"Transports Maurer S.a.r.l.",
    "wof:placetype":"venue"
},
  "geometry": {"coordinates":[7.630975,48.581093],"type":"Point"}
}