{
  "type": "Feature",
  "properties": {
    "addr:full":"58 Rue Raphael Ponson 13001 Marseille Poitou-Charentes",
    "addr:housenumber":"58",
    "addr:postcode":"13001",
    "addr:street":"Rue Raphael Ponson",
    "iso:country":"FR",
    "sg:address":"58 Rue Raphael Ponson 13001 Marseille",
    "sg:classifiers":[
        {
            "category":"Professional",
            "subcategory":"Advertising",
            "type":"Services"
        }
    ],
    "sg:phone":"+33 4 91 84 00 30",
    "sg:province":"Poitou-Charentes",
    "sg:tags":[
        "information",
        "medium",
        "communication"
    ],
    "wof:name":"Laboratoires Et Services Picto Sa",
    "wof:placetype":"venue"
},
  "geometry": {"coordinates":[5.37249,43.293686],"type":"Point"}
}