{
  "type": "Feature",
  "properties": {
    "iso:country":"FR",
    "sg:address":"677, Rue du Faubourg Esquerchin, 59553 Cuincy",
    "sg:orig_category":"Unclassifiable Establishments",
    "sg:phone":"+33 3 27 71 57 57",
    "sg:province":"Nord Pas-de-Calais",
    "wof:name":"Fabrique Alu S.a.",
    "wof:placetype":"venue"
},
  "geometry": {"coordinates":[3.040484,50.371578],"type":"Point"}
}