{
  "type": "Feature",
  "properties": {
    "addr:full":"104, Rue de Miromesnil, 75008 Paris Ile de France",
    "addr:housenumber":"104",
    "addr:postcode":"75008",
    "addr:street":"Rue De Miromesnil",
    "iso:country":"FR",
    "sg:address":"104, Rue de Miromesnil, 75008 Paris",
    "sg:orig_category":"Unclassifiable Establishments",
    "sg:phone":"+33 1 53 83 01 01",
    "sg:province":"Ile de France",
    "wof:name":"Eurytmic Cloiselec S.a.",
    "wof:placetype":"venue"
},
  "geometry": {"coordinates":[2.315593,48.880386],"type":"Point"}
}