{
  "type": "Feature",
  "properties": {
    "iso:country":"FR",
    "sg:address":"RN 100 - ZI la Grande Marine",
    "sg:city":"L'Isle sur la Sorgue",
    "sg:orig_category":"Unclassifiable Establishments",
    "sg:phone":"+33 4 90 38 14 75",
    "sg:postcode":"84800",
    "sg:province":"Provence-Alpes-C\u00f4te d'Azur",
    "wof:name":"Berger S.a.",
    "wof:placetype":"venue"
},
  "geometry": {"coordinates":[5.030911,43.922688],"type":"Point"}
}