{
  "type": "Feature",
  "properties": {
    "iso:country":"FR",
    "sg:address":"Les Iscles ZI Secteur D 06700 ST LAURENT DU VAR",
    "sg:classifiers":[
        {
            "category":"Cinema",
            "subcategory":"Movie Theater",
            "type":"Entertainment"
        }
    ],
    "sg:phone":"+33 4 92 12 57 57",
    "sg:province":"Champagne",
    "sg:tags":[
        "volume",
        "picture"
    ],
    "wof:name":"Panini France Sa",
    "wof:placetype":"venue"
},
  "geometry": {"coordinates":[7.18804,43.678242],"type":"Point"}
}