{
  "type": "Feature",
  "properties": {
    "addr:full":"Batiment 22 Garonor 93600 Aulnay Sous Bois Ile de France",
    "addr:postcode":"93600",
    "addr:street":"Garonor",
    "iso:country":"FR",
    "sg:address":"Batiment 22 Garonor 93600 Aulnay Sous Bois",
    "sg:classifiers":[
        {
            "category":"Shopping",
            "subcategory":"Pharmacy",
            "type":"Retail Goods"
        }
    ],
    "sg:phone":"+33 1 48 65 43 43",
    "sg:province":"Ile de France",
    "sg:tags":[
        "preparation",
        "pharmaceutical"
    ],
    "wof:name":"Depots Generaux Pharma Sa",
    "wof:placetype":"venue"
},
  "geometry": {"coordinates":[2.472009,48.962227],"type":"Point"}
}