{
  "type": "Feature",
  "properties": {
    "addr:full":"8 Place Du Square Aurillac Auvergne 15000",
    "addr:housenumber":"8",
    "addr:postcode":"15000",
    "addr:street":"Place Du Square",
    "iso:country":"FR",
    "sg:address":"8 Place Du Square",
    "sg:city":"Aurillac",
    "sg:classifiers":[
        {
            "category":"Banks & Credit Unions",
            "subcategory":"Financial Services",
            "type":"Services"
        }
    ],
    "sg:phone":"+33 4 71 45 50 00",
    "sg:postcode":"15000",
    "sg:province":"Auvergne",
    "sg:tags":[
        "banking",
        "finance",
        "insurance"
    ],
    "wof:name":"Caisse Regionale De Credit Agricole Mutuel Du Cantal (crcam) Agence St Eloy",
    "wof:placetype":"venue"
},
  "geometry": {"coordinates":[2.444282,44.927898],"type":"Point"}
}