{
  "type": "Feature",
  "properties": {
    "iso:country":"FR",
    "sg:address":"3 Rue De La Buhoti\u00e8re 35136 St Jacques De La Lande",
    "sg:city":"Saint-Jacques-de-la-Lande",
    "sg:classifiers":[
        {
            "category":"Manufacturing",
            "subcategory":"Chemicals & Compounds",
            "type":"Manufacturing & Wholesale Goods"
        }
    ],
    "sg:phone":"+33 2 99 29 46 00",
    "sg:postcode":"35136",
    "sg:province":"Bretagne",
    "sg:tags":[
        "pharmaceutical",
        "chemistry"
    ],
    "wof:name":"Solvadis France",
    "wof:placetype":"venue"
},
  "geometry": {"coordinates":[-1.729372,48.079674],"type":"Point"}
}