{
  "type": "Feature",
  "properties": {
    "addr:full":"07310 Arcens Rhone-Alpes",
    "addr:postcode":"07310",
    "iso:country":"FR",
    "sg:address":"07310 Arcens",
    "sg:orig_category":"Unclassifiable Establishments",
    "sg:phone":"+33 4 75 30 42 00",
    "sg:province":"Rhone-Alpes",
    "wof:name":"Exploitation Des Sources S.a.",
    "wof:placetype":"venue"
},
  "geometry": {"coordinates":[4.32322,44.899429],"type":"Point"}
}