{
  "type": "Feature",
  "properties": {
    "addr:full":"37, Bd Beaurepaire, 59100 Roubaix Nord Pas-de-Calais",
    "addr:housenumber":"37",
    "addr:postcode":"59100",
    "addr:street":"Bd Beaurepaire",
    "iso:country":"FR",
    "sg:address":"37, Bd Beaurepaire, 59100 Roubaix",
    "sg:orig_category":"Non-Classified Establishments",
    "sg:phone":"+33 3 20 75 58 11",
    "sg:province":"Nord Pas-de-Calais",
    "wof:name":"Lehoucq G. Et Fils Anciens Etablissements S.a.",
    "wof:placetype":"venue"
},
  "geometry": {"coordinates":[3.19505,50.691158],"type":"Point"}
}