{
  "type": "Feature",
  "properties": {
    "iso:country":"FR",
    "sg:address":"Rue de l'Aussonnelle",
    "sg:city":"Cornebarrieu",
    "sg:orig_category":"Non-Classified Establishments",
    "sg:phone":"+33 5 62 13 16 01",
    "sg:postcode":"31700",
    "sg:province":"Midi Pyr\u00e9n\u00e9es",
    "wof:name":"S.t.e.a. S.a.r.l. - Soci\u00e9t\u00e9 Toulousaine D'electronique Appliqu\u00e9e",
    "wof:placetype":"venue"
},
  "geometry": {"coordinates":[1.3257,43.649891],"type":"Point"}
}