{
  "type": "Feature",
  "properties": {
    "iso:country":"FR",
    "sg:address":"19 pl Eglise; Porspoder; 29840",
    "sg:city":"Porspoder",
    "sg:classifiers":[
        {
            "category":"Banks & Credit Unions",
            "subcategory":"Bank",
            "type":"Services"
        }
    ],
    "sg:phone":"+33 2 98 89 90 46",
    "sg:postcode":"29840",
    "sg:province":"Bretagne",
    "wof:name":"Cr\u00e9dit Agricole Mutuel",
    "wof:placetype":"venue"
},
  "geometry": {"coordinates":[-4.765374,48.509563],"type":"Point"}
}