{
  "type": "Feature",
  "properties": {
    "iso:country":"FR",
    "sg:address":"45, Rue Victor Hugo, 93500 Pantin",
    "sg:orig_category":"Non-Classified Establishments",
    "sg:phone":"+33 1 41 83 52 52",
    "sg:province":"Ile de France",
    "wof:name":"Publications Fiduciaires S.a.",
    "wof:placetype":"venue"
},
  "geometry": {"coordinates":[2.407453,48.894142],"type":"Point"}
}