{
  "type": "Feature",
  "properties": {
    "addr:full":"89 Bd De Strasbourg 76600 Le Havre Haute Normandie 76600",
    "addr:housenumber":"89",
    "addr:postcode":"76600;76600",
    "addr:street":"Bd De Strasbourg",
    "iso:country":"FR",
    "sg:address":"89 Bd De Strasbourg 76600 Le Havre",
    "sg:classifiers":[
        {
            "category":"Banks & Credit Unions",
            "subcategory":"Financial Services",
            "type":"Services"
        }
    ],
    "sg:phone":"+33 2 35 22 07 60",
    "sg:postcode":"76600",
    "sg:province":"Haute Normandie",
    "sg:tags":[
        "banking",
        "finance",
        "insurance"
    ],
    "wof:name":"Louvel Et Naem Scm",
    "wof:placetype":"venue"
},
  "geometry": {"coordinates":[0.111068,49.493378],"type":"Point"}
}