{
  "type": "Feature",
  "properties": {
    "iso:country":"FR",
    "sg:address":"1, Place Hector Berlioz, 38260 La C\u00f4te Saint Andr\u00e9",
    "sg:orig_category":"Non-Classified Establishments",
    "sg:phone":"+33 4 74 20 30 42",
    "sg:province":"Rhone-Alpes",
    "wof:name":"Normand Paysagiste S.a.r.l.",
    "wof:placetype":"venue"
},
  "geometry": {"coordinates":[5.261574,45.390141],"type":"Point"}
}