{
  "type": "Feature",
  "properties": {
    "addr:full":"25, Quai F\u00e9lix Faure, 49000 Angers Pays de Loire",
    "addr:housenumber":"25",
    "addr:postcode":"49000",
    "addr:street":"Quai Fe\u0301Lix Faure",
    "iso:country":"FR",
    "sg:address":"25, Quai F\u00e9lix Faure, 49000 Angers",
    "sg:orig_category":"Unclassifiable Establishments",
    "sg:phone":"+33 2 41 93 24 31",
    "sg:province":"Pays de Loire",
    "wof:name":"E.d.f. Et G.d.f.",
    "wof:placetype":"venue"
},
  "geometry": {"coordinates":[-0.549707,47.481945],"type":"Point"}
}