{
  "type": "Feature",
  "properties": {
    "addr:full":"52800 Foulain Champagne",
    "addr:postcode":"52800",
    "iso:country":"FR",
    "sg:address":"52800 Foulain",
    "sg:orig_category":"Unclassifiable Establishments",
    "sg:phone":"+33 3 25 31 13 64",
    "sg:province":"Champagne",
    "wof:name":"Cobevim - Coop\u00e9rative B\u00e9tail Et Viande Du Mouton",
    "wof:placetype":"venue"
},
  "geometry": {"coordinates":[5.21165,48.039299],"type":"Point"}
}