{
  "type": "Feature",
  "properties": {
    "iso:country":"FR",
    "sg:address":"16, Rue Amp\u00e8re, 95307 Cergy C\u00e9dex",
    "sg:orig_category":"Non-Classified Establishments",
    "sg:phone":"+33 1 30 30 57 16",
    "sg:province":"Ile de France",
    "wof:name":"Applybox S.a.r.l.",
    "wof:placetype":"venue"
},
  "geometry": {"coordinates":[2.0412,49.061352],"type":"Point"}
}