{
  "type": "Feature",
  "properties": {
    "addr:full":"2 Rue St. Exup\u00e9ry 31140 Launaguet Midi Pyr\u00e9n\u00e9es 31140",
    "addr:housenumber":"2",
    "addr:postcode":"31140;31140",
    "addr:street":"Rue St. Exupe\u0301Ry",
    "iso:country":"FR",
    "sg:address":"2 Rue St. Exup\u00e9ry 31140 Launaguet",
    "sg:classifiers":[
        {
            "category":"Professional",
            "subcategory":"Engineering",
            "type":"Services"
        }
    ],
    "sg:phone":"+33 5 62 79 87 87",
    "sg:postcode":"31140",
    "sg:province":"Midi Pyr\u00e9n\u00e9es",
    "sg:tags":[
        "machine",
        "-",
        "mechanical"
    ],
    "wof:name":"Mecahers Sa",
    "wof:placetype":"venue"
},
  "geometry": {"coordinates":[1.44122,43.674313],"type":"Point"}
}