{
  "type": "Feature",
  "properties": {
    "addr:full":"All\u00e9e du Clos des Charmes Coll\u00e9gien Ile de France 77090",
    "addr:postcode":"77090",
    "addr:street":"Alle\u0301E Du Clos Des Charmes",
    "iso:country":"FR",
    "sg:address":"All\u00e9e du Clos des Charmes",
    "sg:city":"Coll\u00e9gien",
    "sg:orig_category":"Unclassifiable Establishments",
    "sg:phone":"+33 1 64 80 53 53",
    "sg:postcode":"77090",
    "sg:province":"Ile de France",
    "wof:name":"Novotel Marne La Vall\u00e9e",
    "wof:placetype":"venue"
},
  "geometry": {"coordinates":[2.674529,48.830166],"type":"Point"}
}