{
  "type": "Feature",
  "properties": {
    "addr:full":"ZA de Rechimas Craponne sur Arzon Auvergne 43500",
    "addr:postcode":"43500",
    "addr:street":"Za De Rechimas",
    "iso:country":"FR",
    "sg:address":"ZA de Rechimas",
    "sg:city":"Craponne sur Arzon",
    "sg:orig_category":"Non-Classified Establishments",
    "sg:phone":"+33 4 71 03 21 07",
    "sg:postcode":"43500",
    "sg:province":"Auvergne",
    "wof:name":"Le Dessert Du Velay S.a.",
    "wof:placetype":"venue"
},
  "geometry": {"coordinates":[3.84552,45.330261],"type":"Point"}
}