{
  "type": "Feature",
  "properties": {
    "iso:country":"FR",
    "sg:address":"ZAC de la Donni\u00e8re 69970 Marennes",
    "sg:orig_category":"Sintering Plastics",
    "sg:phone":"+33 4 78 02 40 05",
    "sg:province":"Rhone-Alpes",
    "wof:name":"Moditec S.a.r.l.",
    "wof:placetype":"venue"
},
  "geometry": {"coordinates":[4.912591,45.619339],"type":"Point"}
}