{
  "type": "Feature",
  "properties": {
    "iso:country":"FR",
    "sg:address":"30, Rue des Scieries - Petite synthe , 59640 Dunkerque",
    "sg:orig_category":"Unclassifiable Establishments",
    "sg:phone":"+33 3 28 64 64 04",
    "sg:province":"Nord-Pas-de-Calais",
    "wof:name":"Menuiserie Dunkerquoise S.a.r.l.",
    "wof:placetype":"venue"
},
  "geometry": {"coordinates":[2.32694,51.01915],"type":"Point"}
}