{
  "type": "Feature",
  "properties": {
    "addr:full":"11, Rue du March\u00e9 Commun, 44300 Nantes Pays de Loire",
    "addr:housenumber":"11",
    "addr:postcode":"44300",
    "addr:street":"Rue Du Marche\u0301 Commun",
    "iso:country":"FR",
    "sg:address":"11, Rue du March\u00e9 Commun, 44300 Nantes",
    "sg:orig_category":"Unclassifiable Establishments",
    "sg:phone":"+33 2 40 52 30 63",
    "sg:province":"Pays de Loire",
    "wof:name":"A.s.i. S.a. - Avenir Service Industrie",
    "wof:placetype":"venue"
},
  "geometry": {"coordinates":[-1.499731,47.255726],"type":"Point"}
}