{
  "type": "Feature",
  "properties": {
    "addr:full":"17, Av. Marcelin Berthelot, 92167 Antony C\u00e9dex Ile de France",
    "addr:postcode":"92167",
    "addr:street":"17 Av. Marcelin Berthelot",
    "iso:country":"FR",
    "sg:address":"17, Av. Marcelin Berthelot, 92167 Antony C\u00e9dex",
    "sg:orig_category":"Non-Classified Establishments",
    "sg:phone":"+33 1 46 11 45 00",
    "sg:province":"Ile de France",
    "wof:name":"Aldes A\u00e9raulique S.a.",
    "wof:placetype":"venue"
},
  "geometry": {"coordinates":[2.302653,48.752647],"type":"Point"}
}