{
  "type": "Feature",
  "properties": {
    "iso:country":"FR",
    "sg:address":"B.P. 70, 33041 Bordeaux C\u00e9dex^^6, Rue Lucien Faure - Hangar 29 Porte 6, 33000 Bordeaux",
    "sg:city":"Bordeaux",
    "sg:orig_category":"Non-Classified Establishments",
    "sg:phone":"+33 5 56 43 06 41",
    "sg:postcode":"33000",
    "sg:province":"Aquitaine",
    "wof:name":"Aquitimbre S.a.r.l.",
    "wof:placetype":"venue"
},
  "geometry": {"coordinates":[-0.581039,44.836636],"type":"Point"}
}