{
  "type": "Feature",
  "properties": {
    "addr:full":"Avenue Pierre Et Marie Curie Zone Industrielle Secteur B 06700 St Laurent Du Var Champagne",
    "addr:housenumber":"06700",
    "addr:street":"Avenue Pierre Et Marie Curie Zone Industrielle Secteur B;St Laurent Du Var",
    "iso:country":"FR",
    "sg:address":"Avenue Pierre Et Marie Curie Zone Industrielle Secteur B 06700 St Laurent Du Var",
    "sg:classifiers":[
        {
            "category":"Manufacturing",
            "subcategory":"Metals",
            "type":"Manufacturing & Wholesale Goods"
        }
    ],
    "sg:phone":"+33 4 93 31 81 30",
    "sg:province":"Champagne",
    "sg:tags":[
        "-",
        "machine",
        "equipment",
        "engineering",
        "machinery",
        "mechanical"
    ],
    "wof:name":"Sud Est Affutage",
    "wof:placetype":"venue"
},
  "geometry": {"coordinates":[7.18693,43.687363],"type":"Point"}
}