{
  "type": "Feature",
  "properties": {
    "iso:country":"FR",
    "sg:address":"58, Bd Paul Vaillant Couturier, 94246 L'Ha\u00ff les Roses C\u00e9dex",
    "sg:orig_category":"Non-Classified Establishments",
    "sg:phone":"+33 1 46 65 18 34",
    "sg:province":"\u00cele-de-France",
    "wof:name":"Idexpo S.a.",
    "wof:placetype":"venue"
},
  "geometry": {"coordinates":[2.34076,48.7784],"type":"Point"}
}