{
  "type": "Feature",
  "properties": {
    "addr:full":"1 All\u00e9e De Mortarieu 82000 Montauban Midi Pyr\u00e9n\u00e9es 82000",
    "addr:housenumber":"1",
    "addr:postcode":"82000;82000",
    "addr:street":"Alle\u0301E De Mortarieu",
    "iso:country":"FR",
    "sg:address":"1 All\u00e9e De Mortarieu 82000 Montauban",
    "sg:classifiers":[
        {
            "category":"Professional",
            "subcategory":"Business Services",
            "type":"Services"
        }
    ],
    "sg:phone":"+33 5 63 63 12 61",
    "sg:postcode":"82000",
    "sg:province":"Midi Pyr\u00e9n\u00e9es",
    "sg:tags":[
        "training",
        "advice"
    ],
    "wof:name":"Institut Familial",
    "wof:placetype":"venue"
},
  "geometry": {"coordinates":[1.35567,44.014679],"type":"Point"}
}