{
  "type": "Feature",
  "properties": {
    "addr:full":"Passage Sophie Trebuchet 44110 Chateaubriant Pays de Loire 44110",
    "addr:postcode":"44110;44110",
    "addr:street":"Passage Sophie Trebuchet;Chateaubriant",
    "iso:country":"FR",
    "sg:address":"Passage Sophie Trebuchet 44110 Chateaubriant",
    "sg:classifiers":[
        {
            "category":"Manufacturing",
            "subcategory":"Jewelry",
            "type":"Manufacturing & Wholesale Goods"
        }
    ],
    "sg:phone":"+33 2 40 81 30 24",
    "sg:postcode":"44110",
    "sg:province":"Pays de Loire",
    "sg:tags":[
        "product",
        "miscellaneous",
        "jewellery"
    ],
    "wof:name":"Biche De Bere",
    "wof:placetype":"venue"
},
  "geometry": {"coordinates":[-1.37793,47.719429],"type":"Point"}
}