{
  "type": "Feature",
  "properties": {
    "addr:full":"2 Pl De Verdun 32000 Auch Midi Pyr\u00e9n\u00e9es 32000",
    "addr:housenumber":"2",
    "addr:postcode":"32000;32000",
    "addr:street":"Pl De Verdun",
    "iso:country":"FR",
    "sg:address":"2 Pl De Verdun 32000 Auch",
    "sg:classifiers":[
        {
            "category":"Shopping",
            "subcategory":"Clothing, Apparel, & Fashions",
            "type":"Retail Goods"
        }
    ],
    "sg:phone":"+33 5 62 05 11 88",
    "sg:postcode":"32000",
    "sg:province":"Midi Pyr\u00e9n\u00e9es",
    "sg:tags":[
        "textile",
        "clothing",
        "clothes"
    ],
    "wof:name":"Salam Freres Sa",
    "wof:placetype":"venue"
},
  "geometry": {"coordinates":[0.592622,43.648323],"type":"Point"}
}