{
  "type": "Feature",
  "properties": {
    "addr:full":"80, Rue de Menilmontant, 75020 Paris Ile de France 75020",
    "addr:housenumber":"80",
    "addr:postcode":"75020;75020",
    "addr:street":"Rue De Menilmontant",
    "iso:country":"FR",
    "sg:address":"80, Rue de Menilmontant, 75020 Paris",
    "sg:orig_category":"Non-Classified Establishments",
    "sg:phone":"+33 1 46 36 07 02",
    "sg:postcode":"75020",
    "sg:province":"Ile de France",
    "wof:name":"Editions Parsia S.a.r.l.",
    "wof:placetype":"venue"
},
  "geometry": {"coordinates":[2.390758,48.868813],"type":"Point"}
}