{
  "type": "Feature",
  "properties": {
    "addr:full":"Le Pavillon BP 64 Zi Du Pavillon 87202 St Junien Languedoc-Roussillon",
    "addr:housenumber":"64",
    "addr:postcode":"87202",
    "addr:street":"Zi Du Pavillon",
    "iso:country":"FR",
    "sg:address":"Le Pavillon BP 64 Zi Du Pavillon 87202 St Junien",
    "sg:classifiers":[
        {
            "category":"Manufacturing",
            "subcategory":"Building Materials",
            "type":"Manufacturing & Wholesale Goods"
        }
    ],
    "sg:phone":"+33 5 55 43 05 55",
    "sg:province":"Languedoc-Roussillon",
    "sg:tags":[
        "-",
        "machine",
        "raw",
        "engineering",
        "paper",
        "mechanical",
        "cardboard"
    ],
    "wof:name":"Atelier De Faconnage Et De Conditionnement Afc",
    "wof:placetype":"venue"
},
  "geometry": {"coordinates":[0.901046,45.887379],"type":"Point"}
}