{
  "type": "Feature",
  "properties": {
    "addr:full":"Rn 147 86420 VERRUE Poitou-Charentes 86420",
    "addr:postcode":"86420;86420",
    "addr:street":"Rn 147",
    "iso:country":"FR",
    "sg:address":"Rn 147 86420 VERRUE",
    "sg:classifiers":[
        {
            "category":"Home & Garden",
            "subcategory":"Building Materials",
            "type":"Retail Goods"
        }
    ],
    "sg:phone":"+33 5 49 22 31 00",
    "sg:postcode":"86420",
    "sg:province":"Poitou-Charentes",
    "sg:tags":[
        "stone",
        "ceramic"
    ],
    "wof:name":"Etablissements Madej Sarl",
    "wof:placetype":"venue"
},
  "geometry": {"coordinates":[0.174415,46.863613],"type":"Point"}
}