{
  "type": "Feature",
  "properties": {
    "iso:country":"FR",
    "sg:address":"Rue Dolmen 22730 Tregastel",
    "sg:city":"Tr\u00e9gastel",
    "sg:classifiers":[
        {
            "category":"Utilities",
            "subcategory":"Electric",
            "type":"Services"
        }
    ],
    "sg:phone":"+33 2 96 15 65 00",
    "sg:postcode":"22730",
    "sg:province":"Bretagne",
    "sg:tags":[
        "electricity",
        "electronic",
        "electrical",
        "equipment"
    ],
    "wof:name":"Cables Pirelli Sa",
    "wof:placetype":"venue"
},
  "geometry": {"coordinates":[-3.513319,48.817009],"type":"Point"}
}