{
  "type": "Feature",
  "properties": {
    "addr:full":"Zae Les Gagnards 16350 Champagne Mouton Poitou-Charentes 16350",
    "addr:housenumber":"16350",
    "addr:postcode":"16350",
    "addr:street":"Zae;Champagne Mouton",
    "iso:country":"FR",
    "sg:address":"Zae Les Gagnards 16350 Champagne Mouton",
    "sg:classifiers":[
        {
            "category":"Shopping",
            "type":"Retail Goods"
        }
    ],
    "sg:phone":"+33 5 45 31 86 81",
    "sg:postcode":"16350",
    "sg:province":"Poitou-Charentes",
    "sg:tags":[
        "metallurgy",
        "finished",
        "-",
        "metalworking",
        "metallic"
    ],
    "wof:name":"La Croisee Ds Sa",
    "wof:placetype":"venue"
},
  "geometry": {"coordinates":[0.400056,45.949234],"type":"Point"}
}