{
  "type": "Feature",
  "properties": {
    "addr:full":"1 rue des Montagnes de Lans 38130 Echirolles Rhone-Alpes 38130",
    "addr:housenumber":"1",
    "addr:postcode":"38130;38130",
    "addr:street":"Rue Des Montagnes De Lans;Rhone-Alpes",
    "iso:country":"FR",
    "sg:address":"1 rue des Montagnes de Lans 38130 Echirolles",
    "sg:classifiers":[
        {
            "category":"Manufacturing",
            "subcategory":"Printing",
            "type":"Manufacturing & Wholesale Goods"
        }
    ],
    "sg:phone":"+33 4 76 09 96 97",
    "sg:postcode":"38130",
    "sg:province":"Rhone-Alpes",
    "sg:tags":[
        "house",
        "book"
    ],
    "wof:name":"Riondet-malbert Sa",
    "wof:placetype":"venue"
},
  "geometry": {"coordinates":[5.696743,45.152718],"type":"Point"}
}