{
  "type": "Feature",
  "properties": {
    "addr:full":"2 Rue De La Lib\u00e9ration 54150 Avril Lorraine",
    "addr:housenumber":"2",
    "addr:postcode":"54150",
    "addr:street":"Rue De La Libe\u0301Ration",
    "iso:country":"FR",
    "sg:address":"2 Rue De La Lib\u00e9ration 54150 Avril",
    "sg:classifiers":[
        {
            "category":"Professional",
            "subcategory":"Business Services",
            "type":"Services"
        }
    ],
    "sg:phone":"+33 3 82 46 28 59",
    "sg:province":"Lorraine",
    "sg:tags":[
        "chilled",
        "transport",
        "refrigerated"
    ],
    "wof:name":"Transports E. Savard Sarl",
    "wof:placetype":"venue"
},
  "geometry": {"coordinates":[5.961805,49.285595],"type":"Point"}
}