{
  "type": "Feature",
  "properties": {
    "addr:full":"222 Rue De Rosny 93100 Montreuil Ile de France 93100",
    "addr:housenumber":"222",
    "addr:postcode":"93100;93100",
    "addr:street":"Rue De Rosny",
    "iso:country":"FR",
    "sg:address":"222 Rue De Rosny 93100 Montreuil",
    "sg:classifiers":[
        {
            "category":"Shopping",
            "subcategory":"Computers & Home Electronics",
            "type":"Retail Goods"
        }
    ],
    "sg:phone":"+33 1 55 86 87 80",
    "sg:postcode":"93100",
    "sg:province":"Ile de France",
    "sg:tags":[
        "equipment",
        "electrical",
        "component",
        "electric",
        "electronic"
    ],
    "wof:name":"Miranda Europe",
    "wof:placetype":"venue"
},
  "geometry": {"coordinates":[2.46135,48.868668],"type":"Point"}
}