{
  "type": "Feature",
  "properties": {
    "addr:full":"12 R Des Fr\u00e8res Lumi\u00e8re Sae Du Pas De St Jacques 86180 Buxerolles Poitou-Charentes 86180",
    "addr:housenumber":"12",
    "addr:postcode":"86180;86180",
    "addr:street":"R Des Fre\u0300Res Lumie\u0300Re",
    "iso:country":"FR",
    "sg:address":"12 R Des Fr\u00e8res Lumi\u00e8re Sae Du Pas De St Jacques 86180 Buxerolles",
    "sg:classifiers":[
        {
            "category":"Government",
            "subcategory":"Department Of Motor Vehicles",
            "type":"Public Place"
        }
    ],
    "sg:phone":"+33 5 49 47 56 91",
    "sg:postcode":"86180",
    "sg:province":"Poitou-Charentes",
    "sg:tags":[
        "equipment",
        "industrial",
        "transport",
        "motor-cars"
    ],
    "wof:name":"Fournitures Industrielles Auto Poitevines Sarl",
    "wof:placetype":"venue"
},
  "geometry": {"coordinates":[0.35252,46.598751],"type":"Point"}
}