{
  "type": "Feature",
  "properties": {
    "addr:full":"Route Rochelle; Les Sorini\u00e8res Les Sorini\u00e8res Pays de Loire 44840",
    "addr:postcode":"44840",
    "addr:street":"Route Rochelle;Sorinie\u0300Res Les Sorinie\u0300Res Pays",
    "iso:country":"FR",
    "sg:address":"Route Rochelle; Les Sorini\u00e8res",
    "sg:city":"Les Sorini\u00e8res",
    "sg:classifiers":[
        {
            "category":"Banks & Credit Unions",
            "subcategory":"Bank",
            "type":"Services"
        }
    ],
    "sg:phone":"+33 3340044692",
    "sg:postcode":"44840",
    "sg:province":"Pays de Loire",
    "wof:name":"Cr\u00e9dit Agricole Mutuel",
    "wof:placetype":"venue"
},
  "geometry": {"coordinates":[-1.531499,47.148575],"type":"Point"}
}