{
  "type": "Feature",
  "properties": {
    "addr:full":"Av Jean Pandolfi 20110 Propriano Corse 20110",
    "addr:postcode":"20110;20110",
    "addr:street":"Av Jean Pandolfi",
    "iso:country":"FR",
    "sg:address":"Av Jean Pandolfi 20110 Propriano",
    "sg:classifiers":[
        {
            "category":"Professional",
            "subcategory":"Business Services",
            "type":"Services"
        }
    ],
    "sg:phone":"+33 4 95 76 01 27",
    "sg:postcode":"20110",
    "sg:province":"Corse",
    "sg:tags":[
        "training",
        "advice"
    ],
    "wof:name":"C E S Jean Nicoli College Enseignement Secondaire",
    "wof:placetype":"venue"
},
  "geometry": {"coordinates":[8.901212,41.674603],"type":"Point"}
}