{
  "type": "Feature",
  "properties": {
    "iso:country":"FR",
    "sg:address":"29 bis, Cours Mirabeau, 13700 Marignane",
    "sg:orig_category":"Non-Classified Establishments",
    "sg:phone":"+33 4 42 88 80 84",
    "sg:province":"Midi Pyr\u00e9n\u00e9es",
    "wof:name":"Force Gardiennage S.a.r.l.",
    "wof:placetype":"venue"
},
  "geometry": {"coordinates":[5.216408,43.416351],"type":"Point"}
}