{
  "type": "Feature",
  "properties": {
    "iso:country":"FR",
    "sg:address":"31 Av De Paris 45000 Orl\u00e9ans",
    "sg:city":"Orl\u00e9ans",
    "sg:classifiers":[
        {
            "category":"Professional",
            "subcategory":"Computer Services",
            "type":"Services"
        }
    ],
    "sg:phone":"+33 2 38 52 36 60",
    "sg:postcode":"45000",
    "sg:province":"Centre",
    "sg:tags":[
        "information",
        "technology",
        "software"
    ],
    "wof:name":"Sopra Group Sa",
    "wof:placetype":"venue"
},
  "geometry": {"coordinates":[1.90388,47.909508],"type":"Point"}
}