{
  "type": "Feature",
  "properties": {
    "addr:full":"52, Rte de Choisy, 60200 Compi\u00e8gne Picardie",
    "addr:housenumber":"52",
    "addr:postcode":"60200",
    "addr:street":"Rte De Choisy",
    "iso:country":"FR",
    "sg:address":"52, Rte de Choisy, 60200 Compi\u00e8gne",
    "sg:orig_category":"Non-Classified Establishments",
    "sg:phone":"+33 3 44 38 03 04",
    "sg:province":"Picardie",
    "wof:name":"Soci\u00e9t\u00e9 G\u00e9n\u00e9rale Electrique Entreprise S.a.r.l.",
    "wof:placetype":"venue"
},
  "geometry": {"coordinates":[2.855335,49.429077],"type":"Point"}
}