{
  "type": "Feature",
  "properties": {
    "addr:full":"Rue Alo\u00efs Senefelder - ZI Sud-Est Reims Champagne 51100",
    "addr:postcode":"51100",
    "addr:street":"Rue Aloi\u0308S Senefelder Zi Sud-Est;Champagne",
    "iso:country":"FR",
    "sg:address":"Rue Alo\u00efs Senefelder - ZI Sud-Est",
    "sg:city":"Reims",
    "sg:orig_category":"Unclassifiable Establishments",
    "sg:phone":"+33 3 26 50 68 38",
    "sg:postcode":"51100",
    "sg:province":"Champagne",
    "wof:name":"Cadillac Plastic S.a.",
    "wof:placetype":"venue"
},
  "geometry": {"coordinates":[4.028445,49.26284],"type":"Point"}
}