{
  "type": "Feature",
  "properties": {
    "iso:country":"FR",
    "sg:address":"1 Rue De La Robotique",
    "sg:city":"Productique 42000 St Etienne",
    "sg:classifiers":[
        {
            "category":"Manufacturing",
            "subcategory":"Printing",
            "type":"Manufacturing & Wholesale Goods"
        }
    ],
    "sg:phone":"+33 4 77 93 38 38",
    "sg:postcode":"42000",
    "sg:province":"Rhone-Alpes",
    "sg:tags":[
        "publishing"
    ],
    "wof:name":"A F G",
    "wof:placetype":"venue"
},
  "geometry": {"coordinates":[4.387921,45.439053],"type":"Point"}
}