{
  "type": "Feature",
  "properties": {
    "addr:full":"B.P. 18 Beaujeu^^69430 Beaujeu Rhone-Alpes 69430",
    "addr:postcode":"69430",
    "addr:street":"B.P. 18 Beaujeu^^69430 Beaujeu Rhone-Alpes",
    "iso:country":"FR",
    "sg:address":"B.P. 18",
    "sg:city":"Beaujeu^^69430 Beaujeu",
    "sg:orig_category":"Non-Classified Establishments",
    "sg:phone":"+33 4 74 69 29 29",
    "sg:postcode":"69430",
    "sg:province":"Rhone-Alpes",
    "wof:name":"Entreprise Revillon S.a.s.",
    "wof:placetype":"venue"
},
  "geometry": {"coordinates":[4.571452,46.113628],"type":"Point"}
}