{
  "type": "Feature",
  "properties": {
    "iso:country":"FR",
    "sg:address":"ZA Chambaret Sud",
    "sg:city":"Langeac",
    "sg:orig_category":"Unclassifiable Establishments",
    "sg:phone":"+33 4 71 77 15 15",
    "sg:postcode":"43300",
    "sg:province":"Auvergne",
    "wof:name":"T.m.u.a. S.a.",
    "wof:placetype":"venue"
},
  "geometry": {"coordinates":[3.497535,45.100426],"type":"Point"}
}