{
  "type": "Feature",
  "properties": {
    "addr:full":"B.P. 505, 81107 Castres C\u00e9dex^^17, rue des M\u00e9tiers - ZI de M\u00e9lou, 81100 Castres Midi Pyr\u00e9n\u00e9es 81100",
    "addr:housenumber":"b.p. 505",
    "addr:postcode":"81107;81100;81100",
    "addr:street":"Rue Des Me\u0301Tiers Zi De Me\u0301Lou",
    "iso:country":"FR",
    "sg:address":"B.P. 505, 81107 Castres C\u00e9dex^^17, rue des M\u00e9tiers - ZI de M\u00e9lou, 81100 Castres",
    "sg:orig_category":"Non-Classified Establishments",
    "sg:phone":"+33 5 63 59 35 95",
    "sg:postcode":"81100",
    "sg:province":"Midi Pyr\u00e9n\u00e9es",
    "wof:name":"De Cathalo S.a.",
    "wof:placetype":"venue"
},
  "geometry": {"coordinates":[2.257356,43.56094],"type":"Point"}
}