{
  "type": "Feature",
  "properties": {
    "iso:country":"FR",
    "sg:address":"Rue des Ateliers - ZAC de Beaubaton",
    "sg:city":"Mignaloux Beauvoir",
    "sg:orig_category":"Unclassifiable Establishments",
    "sg:phone":"+33 5 49 46 84 12",
    "sg:postcode":"86550",
    "sg:province":"Poitou-Charentes",
    "wof:name":"P.m.p. S.a.s. - Pr\u00e9cision M\u00e9canique Poitevine",
    "wof:placetype":"venue"
},
  "geometry": {"coordinates":[0.415481,46.541206],"type":"Point"}
}