{
  "type": "Feature",
  "properties": {
    "addr:full":"2 Rue Rabelais 75008 Paris Ile de France 75008",
    "addr:housenumber":"2",
    "addr:postcode":"75008;75008",
    "addr:street":"Rue Rabelais",
    "iso:country":"FR",
    "sg:address":"2 Rue Rabelais 75008 Paris",
    "sg:classifiers":[
        {
            "category":"Sports & Exercise",
            "subcategory":"Sports Center",
            "type":"Entertainment"
        }
    ],
    "sg:phone":"+33 1 56 59 15 50",
    "sg:postcode":"75008",
    "sg:province":"Ile de France",
    "sg:tags":[
        "game"
    ],
    "wof:name":"Cercle Du Jockey Club",
    "wof:placetype":"venue"
},
  "geometry": {"coordinates":[2.312838,48.870682],"type":"Point"}
}