{
  "type": "Feature",
  "properties": {
    "iso:country":"FR",
    "sg:address":"66 Rue De Clairie 75002 Paris",
    "sg:classifiers":[
        {
            "category":"Shopping",
            "subcategory":"Clothing, Apparel, & Fashions",
            "type":"Retail Goods"
        }
    ],
    "sg:phone":"+33 1 43 11 28 30",
    "sg:postcode":"75002",
    "sg:province":"Ile de France",
    "sg:tags":[
        "textile",
        "clothing",
        "clothes"
    ],
    "wof:name":"Dary S Expansion",
    "wof:placetype":"venue"
},
  "geometry": {"coordinates":[2.34069,48.866241],"type":"Point"}
}