{
  "type": "Feature",
  "properties": {
    "addr:full":"ZI du Vern 29400 Landivisiau Landivisiau Bretagne 29400",
    "addr:postcode":"29400;29400",
    "addr:street":"Zi Du Vern",
    "iso:country":"FR",
    "sg:address":"ZI du Vern 29400 Landivisiau",
    "sg:city":"Landivisiau",
    "sg:orig_category":"Salmon, Smoked",
    "sg:phone":"+33 2 98 68 44 45",
    "sg:postcode":"29400",
    "sg:province":"Bretagne",
    "wof:name":"Narvik S.a",
    "wof:placetype":"venue"
},
  "geometry": {"coordinates":[-4.068729,48.510777],"type":"Point"}
}