{
  "type": "Feature",
  "properties": {
    "addr:full":"52, Rue Centrale, 38070 Saint Quentin Fallavier Rhone-Alpes",
    "addr:housenumber":"52",
    "addr:postcode":"38070",
    "addr:street":"Rue Centrale",
    "iso:country":"FR",
    "sg:address":"52, Rue Centrale, 38070 Saint Quentin Fallavier",
    "sg:orig_category":"Non-Classified Establishments",
    "sg:phone":"+33 4 74 94 24 09",
    "sg:province":"Rhone-Alpes",
    "wof:name":"Maximaille S.a.",
    "wof:placetype":"venue"
},
  "geometry": {"coordinates":[5.106949,45.634415],"type":"Point"}
}