{
  "type": "Feature",
  "properties": {
    "addr:full":"5 Rue De La Butte BP 50 94268 Fresnes Cedex Centre",
    "addr:housenumber":"5;50",
    "addr:postcode":"94268;cedex",
    "addr:street":"Rue De La Butte Bp",
    "iso:country":"FR",
    "sg:address":"5 Rue De La Butte BP 50 94268 Fresnes Cedex",
    "sg:classifiers":[
        {
            "category":"Professional",
            "subcategory":"Engineering",
            "type":"Services"
        }
    ],
    "sg:phone":"+33 1 46 15 50 60",
    "sg:province":"Centre",
    "sg:tags":[
        "machine",
        "-",
        "mechanical"
    ],
    "wof:name":"Acsim",
    "wof:placetype":"venue"
},
  "geometry": {"coordinates":[2.333309,48.75914],"type":"Point"}
}