{
  "type": "Feature",
  "properties": {
    "addr:full":"Av. du Ch\u00e2teau - L'Orangerie Cheverny Centre 41700",
    "addr:postcode":"41700",
    "addr:street":"Av. Du Cha\u0302Teau L'Orangerie",
    "iso:country":"FR",
    "sg:address":"Av. du Ch\u00e2teau - L'Orangerie",
    "sg:city":"Cheverny",
    "sg:orig_category":"Unclassifiable Establishments",
    "sg:phone":"+33 2 54 79 91 28",
    "sg:postcode":"41700",
    "sg:province":"Centre",
    "wof:name":"L'orangerie Du Ch\u00e2teau De Cheverny S.a.r.l.",
    "wof:placetype":"venue"
},
  "geometry": {"coordinates":[1.4801,47.345631],"type":"Point"}
}