{
  "type": "Feature",
  "properties": {
    "addr:full":"Zi Zae Des Tannes Basse 34800 Clermont L'Herault Languedoc-Roussillon 34800",
    "addr:postcode":"34800;l'herault;34800",
    "addr:street":"Basse",
    "iso:country":"FR",
    "sg:address":"Zi Zae Des Tannes Basse 34800 Clermont L'Herault",
    "sg:classifiers":[
        {
            "category":"Professional",
            "subcategory":"Engineering",
            "type":"Services"
        }
    ],
    "sg:phone":"+33 4 67 88 49 70",
    "sg:postcode":"34800",
    "sg:province":"Languedoc-Roussillon",
    "sg:tags":[
        "machine",
        "-",
        "mechanical"
    ],
    "wof:name":"Groupe Uccoar Sa",
    "wof:placetype":"venue"
},
  "geometry": {"coordinates":[3.43383,43.626781],"type":"Point"}
}