{
  "type": "Feature",
  "properties": {
    "addr:full":"Chem De La Cav\u00e9e St Lazare 02430 Gauchy Picardie",
    "addr:postcode":"02430",
    "addr:street":"Chem De La Cave\u0301E St Lazare",
    "iso:country":"FR",
    "sg:address":"Chem De La Cav\u00e9e St Lazare 02430 Gauchy",
    "sg:classifiers":[
        {
            "category":"Manufacturing",
            "subcategory":"Printing",
            "type":"Manufacturing & Wholesale Goods"
        }
    ],
    "sg:phone":"+33 3 23 50 64 40",
    "sg:province":"Picardie",
    "sg:tags":[
        "publishing"
    ],
    "wof:name":"Roto Aisne",
    "wof:placetype":"venue"
},
  "geometry": {"coordinates":[3.28569,49.825809],"type":"Point"}
}