{
  "type": "Feature",
  "properties": {
    "addr:full":"Rue Saint Roch Gresy sur Is\u00e8re Rhone-Alpes 73460",
    "addr:postcode":"73460",
    "addr:street":"Rue Saint Roch Gresy",
    "iso:country":"FR",
    "sg:address":"Rue Saint Roch",
    "sg:city":"Gresy sur Is\u00e8re",
    "sg:orig_category":"Non-Classified Establishments",
    "sg:phone":"+33 4 79 37 92 03",
    "sg:postcode":"73460",
    "sg:province":"Rhone-Alpes",
    "wof:name":"Sallettaz S.a.r.l.",
    "wof:placetype":"venue"
},
  "geometry": {"coordinates":[6.237405,45.594669],"type":"Point"}
}