{
  "type": "Feature",
  "properties": {
    "addr:full":"26/28, Passage Ponsard, 93260 Les Lilas Ile de France",
    "addr:housenumber":"26 / 28",
    "addr:postcode":"93260",
    "addr:street":"Passage Ponsard",
    "iso:country":"FR",
    "sg:address":"26/28, Passage Ponsard, 93260 Les Lilas",
    "sg:orig_category":"Unclassifiable Establishments",
    "sg:phone":"+33 1 43 60 66 93",
    "sg:province":"Ile de France",
    "wof:name":"Modern' Chrome S.a.r.l.",
    "wof:placetype":"venue"
},
  "geometry": {"coordinates":[2.416648,48.876312],"type":"Point"}
}