{
  "type": "Feature",
  "properties": {
    "addr:full":"Les Forges 26530 Le Grand Serre Rhone-Alpes 26530",
    "addr:postcode":"26530;26530",
    "addr:street":"Les Forges",
    "iso:country":"FR",
    "sg:address":"Les Forges 26530 Le Grand Serre",
    "sg:orig_category":"Unclassifiable Establishments",
    "sg:phone":"+33 4 75 68 90 23",
    "sg:postcode":"26530",
    "sg:province":"Rhone-Alpes",
    "wof:name":"Moulinage De La Galaure S.a.",
    "wof:placetype":"venue"
},
  "geometry": {"coordinates":[5.103265,45.269756],"type":"Point"}
}