{
  "type": "Feature",
  "properties": {
    "iso:country":"FR",
    "sg:address":"57, Av. Raymond Aron, 92160 Antony",
    "sg:orig_category":"Unclassifiable Establishments",
    "sg:phone":"+33 1 49 73 25 60",
    "sg:province":"Ile de France",
    "wof:name":"T.v.a. Engineering S.a.",
    "wof:placetype":"venue"
},
  "geometry": {"coordinates":[2.30935,48.764408],"type":"Point"}
}