{
  "type": "Feature",
  "properties": {
    "iso:country":"FR",
    "sg:address":"B.P. 7",
    "sg:city":"Neuvic",
    "sg:orig_category":"Non-Classified Establishments",
    "sg:phone":"+33 5 53 80 83 30",
    "sg:postcode":"24190",
    "sg:province":"Aquitaine",
    "wof:name":"Marbot Et Compagnie S.a.",
    "wof:placetype":"venue"
},
  "geometry": {"coordinates":[0.47692,45.051495],"type":"Point"}
}