{
  "type": "Feature",
  "properties": {
    "addr:full":"Av. du Mourre de Luc Entraigues sur la Sorgue Provence-Alpes-C\u00f4te d'Azur 84320",
    "addr:postcode":"84320",
    "addr:street":"Av. Du Mourre De Luc Entraigues;La Sorgue",
    "iso:country":"FR",
    "sg:address":"Av. du Mourre de Luc",
    "sg:city":"Entraigues sur la Sorgue",
    "sg:orig_category":"Non-Classified Establishments",
    "sg:phone":"+33 4 90 83 17 75",
    "sg:postcode":"84320",
    "sg:province":"Provence-Alpes-C\u00f4te d'Azur",
    "wof:name":"Cartonnerie Moderne S.a.",
    "wof:placetype":"venue"
},
  "geometry": {"coordinates":[4.922313,43.992504],"type":"Point"}
}