{
  "type": "Feature",
  "properties": {
    "addr:full":"Zi Rue Des Brionnais Zi 42190 Charlieu Rhone-Alpes 42190",
    "addr:postcode":"42190;42190",
    "addr:street":"Rue Des Brionnais Zi",
    "iso:country":"FR",
    "sg:address":"Zi Rue Des Brionnais Zi 42190 Charlieu",
    "sg:classifiers":[
        {
            "category":"Professional",
            "subcategory":"Engineering",
            "type":"Services"
        }
    ],
    "sg:phone":"+33 4 77 69 34 00",
    "sg:postcode":"42190",
    "sg:province":"Rhone-Alpes",
    "sg:tags":[
        "machine",
        "-",
        "mechanical"
    ],
    "wof:name":"Mgo Mecanique Generale Odin",
    "wof:placetype":"venue"
},
  "geometry": {"coordinates":[4.173226,46.157578],"type":"Point"}
}