{
  "type": "Feature",
  "properties": {
    "addr:full":"36 bis, Rue Kleber, 54110 Dombasle sur Meurthe Lorraine",
    "addr:housenumber":"36 bis",
    "addr:postcode":"54110",
    "addr:street":"Rue Kleber",
    "iso:country":"FR",
    "sg:address":"36 bis, Rue Kleber, 54110 Dombasle sur Meurthe",
    "sg:orig_category":"Unclassifiable Establishments",
    "sg:phone":"+33 3 83 48 11 67",
    "sg:province":"Lorraine",
    "wof:name":"Aff\u00fbtage Marchal S.a.r.l.",
    "wof:placetype":"venue"
},
  "geometry": {"coordinates":[6.355365,48.615013],"type":"Point"}
}