{
  "type": "Feature",
  "properties": {
    "iso:country":"FR",
    "sg:address":"B.P. 13, 78270 Bonni\u00e8res sur Seine^^Quai de Seine, 78270 Bonni\u00e8res sur Seine",
    "sg:orig_category":"Non-Classified Establishments",
    "sg:phone":"+33 1 30 98 20 80",
    "sg:province":"Ile de France",
    "wof:name":"Iton Seine S.a.",
    "wof:placetype":"venue"
},
  "geometry": {"coordinates":[1.579122,49.037071],"type":"Point"}
}