{
  "type": "Feature",
  "properties": {
    "addr:full":"B.P. 90172, 57104 Thionville C\u00e9dex^^ZI Cormontaigne, 57100 Thionville Lorraine",
    "addr:postcode":"57104;57100",
    "addr:street":"Cormontaigne",
    "iso:country":"FR",
    "sg:address":"B.P. 90172, 57104 Thionville C\u00e9dex^^ZI Cormontaigne, 57100 Thionville",
    "sg:orig_category":"Non-Classified Establishments",
    "sg:phone":"+33 3 82 82 20 70",
    "sg:province":"Lorraine",
    "wof:name":"Soci\u00e9t\u00e9 Nouvelle Charthi Verdegem S.a.",
    "wof:placetype":"venue"
},
  "geometry": {"coordinates":[6.16909,49.357601],"type":"Point"}
}