{
  "type": "Feature",
  "properties": {
    "iso:country":"FR",
    "sg:address":"11, Rue du Lieutenant Colonel Lesur, 02720 Marcy",
    "sg:orig_category":"Unclassifiable Establishments",
    "sg:phone":"+33 3 23 08 80 77",
    "sg:province":"Picardie",
    "wof:name":"Leriche S.a.",
    "wof:placetype":"venue"
},
  "geometry": {"coordinates":[3.399427,49.848221],"type":"Point"}
}