{
  "type": "Feature",
  "properties": {
    "iso:country":"FR",
    "sg:address":"Zi Grd Fontaine 38490 Chimilin",
    "sg:classifiers":[
        {
            "category":"Professional",
            "type":"Services"
        }
    ],
    "sg:phone":"+33 4 76 31 67 93",
    "sg:province":"Rhone-Alpes",
    "sg:tags":[
        "transport",
        "road"
    ],
    "wof:name":"Transports Guillaud",
    "wof:placetype":"venue"
},
  "geometry": {"coordinates":[5.600455,45.57695],"type":"Point"}
}