{
  "type": "Feature",
  "properties": {
    "addr:full":"2, Chemin des Granges - ZI - Hameau des Reys , 26270 Saulce sur Rh\u00f4ne Rhone-Alpes 26270",
    "addr:housenumber":"2",
    "addr:postcode":"26270;26270",
    "addr:street":"Chemin Des Granges Zi Hameau Des Reys",
    "iso:country":"FR",
    "sg:address":"2, Chemin des Granges - ZI - Hameau des Reys , 26270 Saulce sur Rh\u00f4ne",
    "sg:orig_category":"Non-Classified Establishments",
    "sg:phone":"+33 4 75 63 03 59",
    "sg:postcode":"26270",
    "sg:province":"Rhone-Alpes",
    "wof:name":"Ergica S.a.",
    "wof:placetype":"venue"
},
  "geometry": {"coordinates":[4.797704,44.692307],"type":"Point"}
}