{
  "type": "Feature",
  "properties": {
    "addr:full":"34, Rue de la Mine, 62250 Ferques Nord Pas-de-Calais",
    "addr:housenumber":"34",
    "addr:postcode":"62250",
    "addr:street":"Rue De La Mine",
    "iso:country":"FR",
    "sg:address":"34, Rue de la Mine, 62250 Ferques",
    "sg:orig_category":"Unclassifiable Establishments",
    "sg:phone":"+33 3 21 92 89 06",
    "sg:province":"Nord Pas-de-Calais",
    "wof:name":"Levis Bouly",
    "wof:placetype":"venue"
},
  "geometry": {"coordinates":[1.773191,50.820835],"type":"Point"}
}