{
  "type": "Feature",
  "properties": {
    "addr:full":"44, Av. Jean Jaur\u00e8s, 38270 Beaurepaire Rhone-Alpes",
    "addr:postcode":"38270",
    "addr:street":"44 Av. Jean Jaure\u0300S",
    "iso:country":"FR",
    "sg:address":"44, Av. Jean Jaur\u00e8s, 38270 Beaurepaire",
    "sg:orig_category":"Non-Classified Establishments",
    "sg:phone":"+33 4 74 79 24 24",
    "sg:province":"Rhone-Alpes",
    "wof:name":"Michal Mat\u00e9riaux S.a.",
    "wof:placetype":"venue"
},
  "geometry": {"coordinates":[5.056368,45.333008],"type":"Point"}
}