{
  "type": "Feature",
  "properties": {
    "iso:country":"FR",
    "sg:address":"boulevard du Grand Castaing 31120 Roques",
    "sg:classifiers":[
        {
            "category":"Professional",
            "subcategory":"Engineering",
            "type":"Services"
        }
    ],
    "sg:phone":"+33 5 61 51 82 30",
    "sg:province":"Midi Pyr\u00e9n\u00e9es",
    "sg:tags":[
        "screw",
        "aircraft",
        "bolt"
    ],
    "wof:name":"Fairchild M\u00e9caero Snc",
    "wof:placetype":"venue"
},
  "geometry": {"coordinates":[1.342415,43.491493],"type":"Point"}
}