{
  "type": "Feature",
  "properties": {
    "addr:full":"77 Rue De La Maire Zi Les Paluds 13781 Aubagne Cedex Champagne",
    "addr:housenumber":"77",
    "addr:postcode":"13781",
    "addr:street":"Rue De La Maire Zi Les Paluds",
    "iso:country":"FR",
    "sg:address":"77 Rue De La Maire Zi Les Paluds 13781 Aubagne Cedex",
    "sg:classifiers":[
        {
            "category":"Professional",
            "subcategory":"Engineering",
            "type":"Services"
        }
    ],
    "sg:phone":"+33 4 42 18 60 60",
    "sg:province":"Champagne",
    "sg:tags":[
        "machine",
        "-",
        "mechanical"
    ],
    "wof:name":"Fp Soudage",
    "wof:placetype":"venue"
},
  "geometry": {"coordinates":[5.57028,43.293251],"type":"Point"}
}