{
  "type": "Feature",
  "properties": {
    "addr:full":"107, Av. de la R\u00e9publique, 92325 Ch\u00e2tillon C\u00e9dex Ch\u00e2tillon Ile de France 92320",
    "addr:postcode":"92325;92320",
    "addr:street":"107 Av. De La Re\u0301Publique",
    "iso:country":"FR",
    "sg:address":"107, Av. de la R\u00e9publique, 92325 Ch\u00e2tillon C\u00e9dex",
    "sg:city":"Ch\u00e2tillon",
    "sg:orig_category":"Non-Classified Establishments",
    "sg:phone":"+33 1 47 35 73 50",
    "sg:postcode":"92320",
    "sg:province":"Ile de France",
    "wof:name":"Etablissement F. Morin Et Compagnie S.a.",
    "wof:placetype":"venue"
},
  "geometry": {"coordinates":[2.297711,48.80489],"type":"Point"}
}