{
  "type": "Feature",
  "properties": {
    "iso:country":"FR",
    "sg:address":"1, Village de la Pijude, 50180 Saint Gilles",
    "sg:city":"H\u00e9b\u00e9crevon",
    "sg:orig_category":"Non-Classified Establishments",
    "sg:phone":"+33 2 33 77 44 44",
    "sg:postcode":"50180",
    "sg:province":"Basse Normandie",
    "wof:name":"S.m.3 S.a.",
    "wof:placetype":"venue"
},
  "geometry": {"coordinates":[-1.112378,49.116535],"type":"Point"}
}