{
  "type": "Feature",
  "properties": {
    "addr:full":"8, Rue Jean Momet - Z.I. Parc 3, 68870 Bartenheim Bartenheim Alsace 68870",
    "addr:housenumber":"8;3",
    "addr:postcode":"68870;68870",
    "addr:street":"Rue Jean Momet Z.I. Parc",
    "iso:country":"FR",
    "sg:address":"8, Rue Jean Momet - Z.I. Parc 3, 68870 Bartenheim",
    "sg:city":"Bartenheim",
    "sg:orig_category":"Unclassifiable Establishments",
    "sg:phone":"+33 3 89 70 75 20",
    "sg:postcode":"68870",
    "sg:province":"Alsace",
    "wof:name":"France 3b Scientific S.a.r.l.",
    "wof:placetype":"venue"
},
  "geometry": {"coordinates":[7.494668,47.636616],"type":"Point"}
}