{
  "type": "Feature",
  "properties": {
    "iso:country":"FR",
    "sg:address":"21 bis, Rue Camille Didier - ZI de Mohon, 08000 Charleville M\u00e9zi\u00e8res",
    "sg:city":"Charleville-M\u00e9zi\u00e8res",
    "sg:orig_category":"Non-Classified Establishments",
    "sg:phone":"+33 3 24 37 24 61",
    "sg:postcode":"08000",
    "sg:province":"Champagne",
    "wof:name":"Transports Chezy S.a.r.l.",
    "wof:placetype":"venue"
},
  "geometry": {"coordinates":[4.7174,49.758801],"type":"Point"}
}