{
  "type": "Feature",
  "properties": {
    "addr:full":"Station les Karellis Montricher Albanne Rhone-Alpes 73870",
    "addr:postcode":"73870",
    "addr:street":"Rhone-Alpes",
    "iso:country":"FR",
    "sg:address":"Station les Karellis",
    "sg:city":"Montricher Albanne",
    "sg:orig_category":"Unclassifiable Establishments",
    "sg:phone":"+33 4 79 59 50 30",
    "sg:postcode":"73870",
    "sg:province":"Rhone-Alpes",
    "wof:name":"R\u00e9gie Des Remont\u00e9es M\u00e9caniques",
    "wof:placetype":"venue"
},
  "geometry": {"coordinates":[6.408205,45.255169],"type":"Point"}
}