{
  "type": "Feature",
  "properties": {
    "addr:full":"51, Rue de la R\u00e9publique, 73000 Barberaz Rhone-Alpes 73000",
    "addr:housenumber":"51",
    "addr:postcode":"73000;73000",
    "addr:street":"Rue De La Re\u0301Publique;Rhone-Alpes",
    "iso:country":"FR",
    "sg:address":"51, Rue de la R\u00e9publique, 73000 Barberaz",
    "sg:orig_category":"Unclassifiable Establishments",
    "sg:phone":"+33 825 08 02 01",
    "sg:postcode":"73000",
    "sg:province":"Rhone-Alpes",
    "wof:name":"Daxel S.a.",
    "wof:placetype":"venue"
},
  "geometry": {"coordinates":[5.950135,45.560238],"type":"Point"}
}