{
  "type": "Feature",
  "properties": {
    "addr:full":"49 blvd des Martyrs; Gourdon; 46300 Midi Pyr\u00e9n\u00e9es 46300",
    "addr:postcode":"46300;46300",
    "addr:street":"49 Blvd Des Martyrs Gourdon",
    "iso:country":"FR",
    "sg:address":"49 blvd des Martyrs; Gourdon; 46300",
    "sg:classifiers":[
        {
            "category":"Banks & Credit Unions",
            "subcategory":"Bank",
            "type":"Services"
        }
    ],
    "sg:phone":"+33 3365411274",
    "sg:postcode":"46300",
    "sg:province":"Midi Pyr\u00e9n\u00e9es",
    "wof:name":"Banque Nationale De Paris",
    "wof:placetype":"venue"
},
  "geometry": {"coordinates":[1.41163,44.69997],"type":"Point"}
}