{
  "type": "Feature",
  "properties": {
    "addr:full":"19 rue Poliveau 75005 Paris Ile de France",
    "addr:housenumber":"19",
    "addr:postcode":"75005",
    "addr:street":"Rue Poliveau",
    "iso:country":"FR",
    "sg:address":"19 rue Poliveau 75005 Paris",
    "sg:classifiers":[
        {
            "category":"Shopping",
            "subcategory":"Pharmacy",
            "type":"Retail Goods"
        }
    ],
    "sg:phone":"+33 1 55 43 34 00",
    "sg:province":"Ile de France",
    "sg:tags":[
        "preparation",
        "pharmaceutical"
    ],
    "wof:name":"Laboratoires Grimberg S.a.",
    "wof:placetype":"venue"
},
  "geometry": {"coordinates":[2.359961,48.840145],"type":"Point"}
}