{
  "type": "Feature",
  "properties": {
    "addr:full":"11, Av Marcel Dassault, 37200 Tours Tours Centre 37200",
    "addr:postcode":"37200;37200",
    "addr:street":"11 Av Marcel Dassault",
    "iso:country":"FR",
    "sg:address":"11, Av Marcel Dassault, 37200 Tours",
    "sg:city":"Tours",
    "sg:orig_category":"Non-Classified Establishments",
    "sg:phone":"+33 2 47 28 29 30",
    "sg:postcode":"37200",
    "sg:province":"Centre",
    "wof:name":"Contact S\u00e9curit\u00e9 S.a.",
    "wof:placetype":"venue"
},
  "geometry": {"coordinates":[0.688072,47.363895],"type":"Point"}
}