{
  "type": "Feature",
  "properties": {
    "iso:country":"FR",
    "sg:address":"6 blvd Victor Hugo; Troyes; 10014",
    "sg:classifiers":[
        {
            "category":"Banks & Credit Unions",
            "subcategory":"Bank",
            "type":"Services"
        }
    ],
    "sg:phone":"+33 3 25 42 44 44",
    "sg:province":"Bourgogne",
    "wof:name":"Banque De France",
    "wof:placetype":"venue"
},
  "geometry": {"coordinates":[4.07529,48.301182],"type":"Point"}
}