{
  "type": "Feature",
  "properties": {
    "addr:full":"3-5 Rue Jacquard 93310 Le Pr\u00e9 St Gervais Ile de France 93310",
    "addr:housenumber":"3-5",
    "addr:postcode":"93310;93310",
    "addr:street":"Rue Jacquard;Le Pre\u0301 St",
    "iso:country":"FR",
    "sg:address":"3-5 Rue Jacquard 93310 Le Pr\u00e9 St Gervais",
    "sg:classifiers":[
        {
            "category":"Utilities",
            "subcategory":"Electric",
            "type":"Services"
        }
    ],
    "sg:phone":"+33 1 48 45 20 98",
    "sg:postcode":"93310",
    "sg:province":"Ile de France",
    "sg:tags":[
        "electricity",
        "electronic",
        "electrical",
        "equipment"
    ],
    "wof:name":"Krendel Sa",
    "wof:placetype":"venue"
},
  "geometry": {"coordinates":[2.405929,48.886772],"type":"Point"}
}