{
  "type": "Feature",
  "properties": {
    "iso:country":"FR",
    "sg:address":"9, Rue de la Fonderie, 35000 Rennes",
    "sg:city":"Rennes",
    "sg:orig_category":"Unclassifiable Establishments",
    "sg:phone":"+33 2 99 67 70 70",
    "sg:postcode":"35000",
    "sg:province":"Bretagne",
    "wof:name":"Sog\u00e9a Bretagne S.n.c.",
    "wof:placetype":"venue"
},
  "geometry": {"coordinates":[-1.688964,48.106571],"type":"Point"}
}