{
  "type": "Feature",
  "properties": {
    "addr:full":"1, Av. de la R\u00e9publique, 74100 Annemasse Rhone-Alpes",
    "addr:postcode":"74100",
    "addr:street":"Av. De La Re\u0301Publique",
    "iso:country":"FR",
    "sg:address":"1, Av. de la R\u00e9publique, 74100 Annemasse",
    "sg:orig_category":"Unclassifiable Establishments",
    "sg:phone":"+33 4 50 92 54 83",
    "sg:province":"Rhone-Alpes",
    "wof:name":"Sovec",
    "wof:placetype":"venue"
},
  "geometry": {"coordinates":[6.234778,46.193008],"type":"Point"}
}