{
  "type": "Feature",
  "properties": {
    "addr:full":"rue du Trou aux Serpents 57050 Metz Lorraine 57050",
    "addr:postcode":"57050;57050",
    "addr:street":"Rue Du Trou Aux Serpents",
    "iso:country":"FR",
    "sg:address":"rue du Trou aux Serpents 57050 Metz",
    "sg:classifiers":[
        {
            "category":"Food & Beverages",
            "subcategory":"Meat & Fish",
            "type":"Retail Goods"
        }
    ],
    "sg:phone":"+33 3 87 32 53 08",
    "sg:postcode":"57050",
    "sg:province":"Lorraine",
    "sg:tags":[
        "product"
    ],
    "wof:name":"Charal Sarl",
    "wof:placetype":"venue"
},
  "geometry": {"coordinates":[6.187808,49.141178],"type":"Point"}
}