{
  "type": "Feature",
  "properties": {
    "iso:country":"FR",
    "sg:address":"1, Rue de la Fosse Cochard, 51370 Saint Brice Courcelles",
    "sg:orig_category":"TRANSFERT ET MONTAGE DE LIGNES DE PROCESS maintenance industrielle mise en conformit\u00e9 de machines",
    "sg:phone":"+33 3 26 09 09 52",
    "sg:province":"Champagne",
    "wof:name":"D.t.v. S.a.r.l.",
    "wof:placetype":"venue"
},
  "geometry": {"coordinates":[3.993921,49.268761],"type":"Point"}
}