{
  "type": "Feature",
  "properties": {
    "iso:country":"FR",
    "sg:address":"B.P. 4301, 38943 Meylan C\u00e9dex^^4, Chemin du Pr\u00e9 Carr\u00e9, 38240 Meylan",
    "sg:orig_category":"Non-Classified Establishments",
    "sg:phone":"+33 4 76 61 63 63",
    "sg:postcode":"38240",
    "sg:province":"Rhone-Alpes",
    "wof:name":"A.f.p.i. Is\u00e8re S.a.r.l.",
    "wof:placetype":"venue"
},
  "geometry": {"coordinates":[5.77846,45.209316],"type":"Point"}
}