{
  "type": "Feature",
  "properties": {
    "addr:full":"2, Rue des Sablons, 45140 Ormes Ingr\u00e9 Centre 45140",
    "addr:housenumber":"2",
    "addr:postcode":"45140;45140",
    "addr:street":"Rue Des Sablons",
    "iso:country":"FR",
    "sg:address":"2, Rue des Sablons, 45140 Ormes",
    "sg:city":"Ingr\u00e9",
    "sg:orig_category":"Non-Classified Establishments",
    "sg:phone":"+33 2 38 74 90 90",
    "sg:postcode":"45140",
    "sg:province":"Centre",
    "wof:name":"Nexia Froid S.a.",
    "wof:placetype":"venue"
},
  "geometry": {"coordinates":[1.836009,47.948521],"type":"Point"}
}