{
  "type": "Feature",
  "properties": {
    "iso:country":"FR",
    "sg:address":"2 Rue Du Patis",
    "sg:city":"Montargis",
    "sg:classifiers":[
        {
            "category":"Banks & Credit Unions",
            "subcategory":"Financial Services",
            "type":"Services"
        }
    ],
    "sg:phone":"+33 2 38 28 30 80",
    "sg:postcode":"45200",
    "sg:province":"Centre",
    "sg:tags":[
        "banking",
        "finance",
        "insurance"
    ],
    "wof:name":"Expertise Et Technique Comptables (etc)",
    "wof:placetype":"venue"
},
  "geometry": {"coordinates":[2.732921,47.998783],"type":"Point"}
}