{
  "type": "Feature",
  "properties": {
    "addr:full":"1 rue du G\u00e9n\u00e9ral Rapp 67450 Mundolsheim Mundolsheim Alsace 67450",
    "addr:housenumber":"1",
    "addr:postcode":"67450;67450",
    "addr:street":"Rue Du Ge\u0301Ne\u0301Ral Rapp",
    "iso:country":"FR",
    "sg:address":"1 rue du G\u00e9n\u00e9ral Rapp 67450 Mundolsheim",
    "sg:city":"Mundolsheim",
    "sg:classifiers":[
        {
            "category":"Sports & Exercise",
            "subcategory":"Athletic Track",
            "type":"Entertainment"
        }
    ],
    "sg:phone":"+33 3 90 20 30 40",
    "sg:postcode":"67450",
    "sg:province":"Alsace",
    "sg:tags":[
        "record"
    ],
    "wof:name":"Mce France Sarl",
    "wof:placetype":"venue"
},
  "geometry": {"coordinates":[7.717458,48.631771],"type":"Point"}
}