{
  "type": "Feature",
  "properties": {
    "iso:country":"FR",
    "sg:address":"19, Rue Louis Gr\u00e9guet - Parc d'Activit\u00e9s Cl\u00e9ment Ader, 34830 Jacou",
    "sg:orig_category":"Unclassifiable Establishments",
    "sg:phone":"+33 4 67 59 40 10",
    "sg:province":"Languedoc-Roussillon",
    "wof:name":"Sicsol S.a.",
    "wof:placetype":"venue"
},
  "geometry": {"coordinates":[3.91264,43.659279],"type":"Point"}
}