{
  "type": "Feature",
  "properties": {
    "addr:full":"Rte de Montpellier - ZI des Fournels Lunel Languedoc-Roussillon 34400",
    "addr:postcode":"34400",
    "addr:street":"Rte De Montpellier Zi Des Fournels Lunel",
    "iso:country":"FR",
    "sg:address":"Rte de Montpellier - ZI des Fournels",
    "sg:city":"Lunel",
    "sg:orig_category":"Unclassifiable Establishments",
    "sg:phone":"+33 4 67 71 12 33",
    "sg:postcode":"34400",
    "sg:province":"Languedoc-Roussillon",
    "wof:name":"Copal",
    "wof:placetype":"venue"
},
  "geometry": {"coordinates":[4.108795,43.679749],"type":"Point"}
}