{
  "type": "Feature",
  "properties": {
    "addr:full":"Herbage Hurvani\u00e8re 14290 St Cyr Du Ronceray Cernay Basse Normandie 14290",
    "addr:housenumber":"14290",
    "addr:postcode":"14290",
    "addr:street":"St Cyr Du Ronceray;Basse",
    "iso:country":"FR",
    "sg:address":"Herbage Hurvani\u00e8re 14290 St Cyr Du Ronceray",
    "sg:city":"Cernay",
    "sg:classifiers":[
        {
            "category":"Food Court",
            "type":"Food & Drink"
        }
    ],
    "sg:phone":"+33 2 31 63 71 53",
    "sg:postcode":"14290",
    "sg:province":"Basse Normandie",
    "sg:tags":[
        "product",
        "related"
    ],
    "wof:name":"Calvados Groult Roger Sa",
    "wof:placetype":"venue"
},
  "geometry": {"coordinates":[0.291775,49.046101],"type":"Point"}
}