{
  "type": "Feature",
  "properties": {
    "addr:full":"237 Route De Paris Ou Route Nati 86000 Poitiers Poitou-Charentes 86000",
    "addr:housenumber":"237",
    "addr:postcode":"86000;86000",
    "addr:street":"Route De Paris;Route Nati",
    "iso:country":"FR",
    "sg:address":"237 Route De Paris Ou Route Nati 86000 Poitiers",
    "sg:orig_category":"Mobile Concrete Mixers, Ready-Mixed Concrete Trucks",
    "sg:phone":"+33 5 49 88 16 66",
    "sg:postcode":"86000",
    "sg:province":"Poitou-Charentes",
    "wof:name":"Etablissement Touillet Sa",
    "wof:placetype":"venue"
},
  "geometry": {"coordinates":[0.34169,46.58057],"type":"Point"}
}