{
  "type": "Feature",
  "properties": {
    "addr:full":"33 Pl Reine Mathilde 14000 Caen Caen Basse Normandie 14000",
    "addr:housenumber":"33",
    "addr:postcode":"14000;14000",
    "addr:street":"Pl Reine Mathilde",
    "iso:country":"FR",
    "sg:address":"33 Pl Reine Mathilde 14000 Caen",
    "sg:city":"Caen",
    "sg:classifiers":[
        {
            "category":"Professional",
            "subcategory":"Business Services",
            "type":"Services"
        }
    ],
    "sg:phone":"+33 2 31 94 72 00",
    "sg:postcode":"14000",
    "sg:province":"Basse Normandie",
    "sg:tags":[
        "body",
        "advice"
    ],
    "wof:name":"Union Regionalede L'enseignement Catholique",
    "wof:placetype":"venue"
},
  "geometry": {"coordinates":[-0.353679,49.186901],"type":"Point"}
}