{
  "type": "Feature",
  "properties": {
    "addr:full":"66, Rue Bechevelin, 69007 Lyon Rhone-Alpes",
    "addr:housenumber":"66",
    "addr:postcode":"69007",
    "addr:street":"Rue Bechevelin",
    "iso:country":"FR",
    "sg:address":"66, Rue Bechevelin, 69007 Lyon",
    "sg:orig_category":"Unclassifiable Establishments",
    "sg:phone":"+33 4 78 69 16 47",
    "sg:province":"Rhone-Alpes",
    "wof:name":"Prestige Sanitaire S.a.r.l.",
    "wof:placetype":"venue"
},
  "geometry": {"coordinates":[4.83978,45.750099],"type":"Point"}
}