{
  "type": "Feature",
  "properties": {
    "addr:full":"93 avenue de Paris 51000 Chalons en Champagne Champagne 51000",
    "addr:housenumber":"93",
    "addr:postcode":"51000;51000",
    "addr:street":"Avenue De Paris",
    "iso:country":"FR",
    "sg:address":"93 avenue de Paris 51000 Chalons en Champagne",
    "sg:classifiers":[
        {
            "category":"Food & Beverages",
            "subcategory":"Liquor & Beverages",
            "type":"Retail Goods"
        }
    ],
    "sg:phone":"+33 3 26 68 18 68",
    "sg:postcode":"51000",
    "sg:province":"Champagne",
    "sg:tags":[
        "champagne"
    ],
    "wof:name":"S.c.e.v. Sa",
    "wof:placetype":"venue"
},
  "geometry": {"coordinates":[4.342512,48.953159],"type":"Point"}
}