{
  "type": "Feature",
  "properties": {
    "addr:full":"2, Place de la D\u00e9fense - Le Enit Center 1, 92053 Paris la D\u00e9fense C\u00e9dex \u00cele-de-France",
    "addr:housenumber":"2;1",
    "addr:postcode":"92053",
    "addr:street":"Place De La De\u0301Fense Le;Ce\u0301Dex",
    "iso:country":"FR",
    "sg:address":"2, Place de la D\u00e9fense - Le Enit Center 1, 92053 Paris la D\u00e9fense C\u00e9dex",
    "sg:orig_category":"Non-Classified Establishments",
    "sg:phone":"+33 1 41 45 27 27",
    "sg:province":"\u00cele-de-France",
    "wof:name":"Steelcase Strafor S.a.",
    "wof:placetype":"venue"
},
  "geometry": {"coordinates":[2.24119,48.888939],"type":"Point"}
}