{
  "type": "Feature",
  "properties": {
    "addr:full":"37 rue Louis Rameau 95870 Bezons Ile de France 95870",
    "addr:housenumber":"37",
    "addr:postcode":"95870;ile;95870",
    "addr:street":"Rue Louis Rameau;France",
    "iso:country":"FR",
    "sg:address":"37 rue Louis Rameau 95870 Bezons",
    "sg:classifiers":[
        {
            "category":"Manufacturing",
            "subcategory":"Tools & Machinery",
            "type":"Manufacturing & Wholesale Goods"
        }
    ],
    "sg:phone":"+33 1 34 26 20 00",
    "sg:postcode":"95870",
    "sg:province":"Ile de France",
    "sg:tags":[
        "machine"
    ],
    "wof:name":"Ste Generale Machines Sa",
    "wof:placetype":"venue"
},
  "geometry": {"coordinates":[2.212237,48.921188],"type":"Point"}
}