{
  "type": "Feature",
  "properties": {
    "addr:full":"12 Boulevard Malesherbes 75008 Paris Ile de France 75008",
    "addr:housenumber":"12",
    "addr:postcode":"75008;75008",
    "addr:street":"Boulevard Malesherbes",
    "iso:country":"FR",
    "sg:address":"12 Boulevard Malesherbes 75008 Paris",
    "sg:classifiers":[
        {
            "category":"Travel",
            "subcategory":"Hotels & Motels",
            "type":"Entertainment"
        }
    ],
    "sg:phone":"+33 1 42 65 72 06",
    "sg:postcode":"75008",
    "sg:province":"Ile de France",
    "sg:tags":[
        "hotels",
        "business",
        "restaurant"
    ],
    "wof:name":"Hotel Waldorf Madeleine Sa",
    "wof:placetype":"venue"
},
  "geometry": {"coordinates":[2.322349,48.871651],"type":"Point"}
}