{
  "type": "Feature",
  "properties": {
    "addr:full":"Imp Gutenberg Zi Du Fournalet 84706 Sorgues Cedex Berg Alsace 67320",
    "addr:postcode":"84706;cedex;67320",
    "addr:street":"Imp Gutenberg Zi Du Fournalet;Berg",
    "iso:country":"FR",
    "sg:address":"Imp Gutenberg Zi Du Fournalet 84706 Sorgues Cedex",
    "sg:city":"Berg",
    "sg:classifiers":[
        {
            "category":"Manufacturing",
            "subcategory":"Paper Products",
            "type":"Manufacturing & Wholesale Goods"
        }
    ],
    "sg:phone":"+33 4 90 83 32 11",
    "sg:postcode":"67320",
    "sg:province":"Alsace",
    "sg:tags":[
        "raw",
        "material",
        "-",
        "cardboard"
    ],
    "wof:name":"Seyfert Provence",
    "wof:placetype":"venue"
},
  "geometry": {"coordinates":[4.873481,44.00827],"type":"Point"}
}