{
  "type": "Feature",
  "properties": {
    "addr:full":"3 place du March\u00e9; Faulquemont; 57380 Lorraine 57380",
    "addr:housenumber":"3",
    "addr:postcode":"57380;57380",
    "addr:street":"Place Du Marche\u0301",
    "iso:country":"FR",
    "sg:address":"3 place du March\u00e9; Faulquemont; 57380",
    "sg:classifiers":[
        {
            "category":"Banks & Credit Unions",
            "subcategory":"Bank",
            "type":"Services"
        }
    ],
    "sg:phone":"+33 3 87 94 40 55",
    "sg:postcode":"57380",
    "sg:province":"Lorraine",
    "wof:name":"Cr\u00e9dit Industriel D'alsace, Et De Lorraine Sa",
    "wof:placetype":"venue"
},
  "geometry": {"coordinates":[6.599706,49.044048],"type":"Point"}
}