{
  "type": "Feature",
  "properties": {
    "addr:full":"48 B Av De Chateau Thierry 02200 Soissons Picardie 02200",
    "addr:housenumber":"48",
    "addr:postcode":"02200;02200",
    "addr:street":"B Av De Chateau Thierry",
    "iso:country":"FR",
    "sg:address":"48 B Av De Chateau Thierry 02200 Soissons",
    "sg:classifiers":[
        {
            "category":"Farming",
            "subcategory":"Livestock Farm",
            "type":"Manufacturing & Wholesale Goods"
        }
    ],
    "sg:phone":"+33 3 23 73 21 69",
    "sg:postcode":"02200",
    "sg:province":"Picardie",
    "sg:tags":[
        "agriculture"
    ],
    "wof:name":"M. Maillard Jean-pierre Pepinieres Maillard",
    "wof:placetype":"venue"
},
  "geometry": {"coordinates":[3.329634,49.370106],"type":"Point"}
}