{
  "type": "Feature",
  "properties": {
    "addr:full":"135 Rue De Douai 59000 Lille Nord Pas-de-Calais 59000",
    "addr:housenumber":"135",
    "addr:postcode":"59000;59000",
    "addr:street":"Rue De Douai",
    "iso:country":"FR",
    "sg:address":"135 Rue De Douai 59000 Lille",
    "sg:classifiers":[
        {
            "category":"Shopping",
            "type":"Retail Goods"
        }
    ],
    "sg:phone":"+33 3 20 18 05 18",
    "sg:postcode":"59000",
    "sg:province":"Nord Pas-de-Calais",
    "sg:tags":[
        "metallurgy",
        "finished",
        "-",
        "metalworking",
        "metallic"
    ],
    "wof:name":"Chaumeca International Sa",
    "wof:placetype":"venue"
},
  "geometry": {"coordinates":[3.073239,50.6199],"type":"Point"}
}