{
  "type": "Feature",
  "properties": {
    "iso:country":"FR",
    "sg:address":"1457, Rue Vilaine, 76850 Bosc le Hard",
    "sg:orig_category":"Unclassifiable Establishments",
    "sg:phone":"+33 2 32 93 92 12",
    "sg:province":"Haute Normandie",
    "wof:name":"Seccom S.a.r.l.",
    "wof:placetype":"venue"
},
  "geometry": {"coordinates":[1.137861,49.651474],"type":"Point"}
}