{
  "type": "Feature",
  "properties": {
    "iso:country":"FR",
    "sg:address":"89770 Chailley",
    "sg:city":"Chailley",
    "sg:orig_category":"Non-Classified Establishments",
    "sg:phone":"+33 3 86 43 55 00",
    "sg:postcode":"89770",
    "sg:province":"Bourgogne",
    "wof:name":"Bsa S.a.",
    "wof:placetype":"venue"
},
  "geometry": {"coordinates":[3.701761,48.083473],"type":"Point"}
}