{
  "type": "Feature",
  "properties": {
    "addr:full":"B.P. 318, 17013 La Rochelle C\u00e9dex^^19-21, Rue Planquette, 17000 La Rochelle Poitou-Charentes 17000",
    "addr:housenumber":"b.p. 318;-21",
    "addr:postcode":"17013;17000;17000",
    "addr:street":"Ce\u0301Dex^^19;Rue Planquette",
    "iso:country":"FR",
    "sg:address":"B.P. 318, 17013 La Rochelle C\u00e9dex^^19-21, Rue Planquette, 17000 La Rochelle",
    "sg:orig_category":"Non-Classified Establishments",
    "sg:phone":"+33 5 46 27 13 13",
    "sg:postcode":"17000",
    "sg:province":"Poitou-Charentes",
    "wof:name":"Aunis-entretien S.a.r.l.",
    "wof:placetype":"venue"
},
  "geometry": {"coordinates":[-1.151639,46.159435],"type":"Point"}
}