{
  "type": "Feature",
  "properties": {
    "addr:full":"2, Villa de Lourcine, 75014 Paris Ile de France",
    "addr:housenumber":"2",
    "addr:postcode":"75014",
    "addr:street":"Villa De Lourcine",
    "iso:country":"FR",
    "sg:address":"2, Villa de Lourcine, 75014 Paris",
    "sg:orig_category":"Non-Classified Establishments",
    "sg:phone":"+33 1 53 80 99 99",
    "sg:province":"Ile de France",
    "wof:name":"Orpi Agences N\u00b0 1 E.u.r.l.",
    "wof:placetype":"venue"
},
  "geometry": {"coordinates":[2.338338,48.83144],"type":"Point"}
}