{
  "type": "Feature",
  "properties": {
    "iso:country":"FR",
    "sg:address":"16, Rue de l'Industrie, 41310 Saint Amand Longpr\u00e9",
    "sg:city":"Ambloy",
    "sg:orig_category":"Unclassifiable Establishments",
    "sg:phone":"+33 2 54 82 90 69",
    "sg:postcode":"41310",
    "sg:province":"Centre",
    "wof:name":"Materlignes S.a.",
    "wof:placetype":"venue"
},
  "geometry": {"coordinates":[1.011952,47.693935],"type":"Point"}
}