{
  "type": "Feature",
  "properties": {
    "addr:full":"16, Rue de l'Industrie, 41310 Saint Amand Longpr\u00e9 Ambloy Centre 41310",
    "addr:housenumber":"16",
    "addr:postcode":"41310;41310",
    "addr:street":"Rue De L'Industrie",
    "iso:country":"FR",
    "sg:address":"16, Rue de l'Industrie, 41310 Saint Amand Longpr\u00e9",
    "sg:city":"Ambloy",
    "sg:orig_category":"Unclassifiable Establishments",
    "sg:phone":"+33 2 54 82 90 69",
    "sg:postcode":"41310",
    "sg:province":"Centre",
    "wof:name":"Materlignes S.a.",
    "wof:placetype":"venue"
},
  "geometry": {"coordinates":[1.011952,47.693935],"type":"Point"}
}