{
  "type": "Feature",
  "properties": {
    "iso:country":"FR",
    "sg:address":"5, Rue du Launay, 44800 Saint Herblain",
    "sg:orig_category":"Unclassifiable Establishments",
    "sg:phone":"+33 2 40 95 29 00",
    "sg:province":"Pays de Loire",
    "wof:name":"Herv\u00e9 Thermique S.a.",
    "wof:placetype":"venue"
},
  "geometry": {"coordinates":[-1.630569,47.201046],"type":"Point"}
}