{
  "type": "Feature",
  "properties": {
    "addr:full":"42, Rue Ferdinand Buisson, 02300 Chauny Picardie",
    "addr:housenumber":"42",
    "addr:postcode":"02300",
    "addr:street":"Rue Ferdinand Buisson",
    "iso:country":"FR",
    "sg:address":"42, Rue Ferdinand Buisson, 02300 Chauny",
    "sg:orig_category":"Unclassifiable Establishments",
    "sg:phone":"+33 3 23 38 41 00",
    "sg:province":"Picardie",
    "wof:name":"S.c.c.c. S.a. - Soci\u00e9t\u00e9 De Coul\u00e9e Continue De Cuivre",
    "wof:placetype":"venue"
},
  "geometry": {"coordinates":[3.227598,49.615894],"type":"Point"}
}