{
  "type": "Feature",
  "properties": {
    "iso:country":"FR",
    "sg:address":"Chaudoux 18300 VERDIGNY",
    "sg:city":"Verdigny",
    "sg:classifiers":[
        {
            "category":"Wholesale",
            "subcategory":"Wine & Distilled Alcoholic Beverages",
            "type":"Manufacturing & Wholesale Goods"
        }
    ],
    "sg:phone":"+33 2 48 79 38 54",
    "sg:postcode":"18300",
    "sg:province":"Centre",
    "sg:tags":[
        "french"
    ],
    "wof:name":"Earl Reverdy-cadet",
    "wof:placetype":"venue"
},
  "geometry": {"coordinates":[2.81307,47.352901],"type":"Point"}
}