{
  "type": "Feature",
  "properties": {
    "addr:full":"La Cartonnerie 37320 Truyes Truyes Centre 37320",
    "addr:housenumber":"truyes",
    "addr:postcode":"37320;37320",
    "iso:country":"FR",
    "sg:address":"La Cartonnerie 37320 Truyes",
    "sg:city":"Truyes",
    "sg:classifiers":[
        {
            "category":"Manufacturing",
            "subcategory":"Paper Products",
            "type":"Manufacturing & Wholesale Goods"
        }
    ],
    "sg:phone":"+33 2 47 73 40 00",
    "sg:postcode":"37320",
    "sg:province":"Centre",
    "sg:tags":[
        "raw",
        "material",
        "-",
        "cardboard"
    ],
    "wof:name":"La Cartonnerie Oudin",
    "wof:placetype":"venue"
},
  "geometry": {"coordinates":[0.850077,47.271618],"type":"Point"}
}