{
  "type": "Feature",
  "properties": {
    "addr:full":"Rue Vaucanson Saint Bonnet de Mure Rhone-Alpes 69720",
    "addr:postcode":"69720",
    "addr:street":"Rue Vaucanson Saint;Rhone-Alpes",
    "iso:country":"FR",
    "sg:address":"Rue Vaucanson",
    "sg:city":"Saint Bonnet de Mure",
    "sg:orig_category":"Unclassifiable Establishments",
    "sg:phone":"+33 4 72 22 66 11",
    "sg:postcode":"69720",
    "sg:province":"Rhone-Alpes",
    "wof:name":"Ferraz Chawmut S.a.",
    "wof:placetype":"venue"
},
  "geometry": {"coordinates":[5.015004,45.698658],"type":"Point"}
}