{
  "type": "Feature",
  "properties": {
    "iso:country":"FR",
    "sg:address":"14 pl Clemenceau; Biarritz; 64202",
    "sg:city":"Biarritz",
    "sg:classifiers":[
        {
            "category":"Banks & Credit Unions",
            "subcategory":"Bank",
            "type":"Services"
        }
    ],
    "sg:phone":"+33 3359242400",
    "sg:postcode":"64200",
    "sg:province":"Aquitaine",
    "wof:name":"Soci\u00e9t\u00e9 G\u00e9n\u00e9rale",
    "wof:placetype":"venue"
},
  "geometry": {"coordinates":[-1.560257,43.48204],"type":"Point"}
}