{
  "type": "Feature",
  "properties": {
    "addr:full":"Chemin d'Orles Perpignan Languedoc-Roussillon 66000",
    "addr:postcode":"66000",
    "addr:street":"Chemin D'Orles",
    "iso:country":"FR",
    "sg:address":"Chemin d'Orles",
    "sg:city":"Perpignan",
    "sg:orig_category":"Non-Classified Establishments",
    "sg:phone":"+33 4 68 68 15 60",
    "sg:postcode":"66000",
    "sg:province":"Languedoc-Roussillon",
    "wof:name":"Novatrans S.a.",
    "wof:placetype":"venue"
},
  "geometry": {"coordinates":[2.855665,42.678585],"type":"Point"}
}