{
  "type": "Feature",
  "properties": {
    "iso:country":"FR",
    "sg:address":"2 quai Carnot; Mayenne; 53100",
    "sg:classifiers":[
        {
            "category":"Banks & Credit Unions",
            "subcategory":"Bank",
            "type":"Services"
        }
    ],
    "sg:phone":"+33 3343043432",
    "sg:postcode":"53100",
    "sg:province":"Pays de Loire",
    "wof:name":"Soci\u00e9t\u00e9 G\u00e9n\u00e9rale",
    "wof:placetype":"venue"
},
  "geometry": {"coordinates":[-0.617111,48.303635],"type":"Point"}
}