{
  "type": "Feature",
  "properties": {
    "iso:country":"FR",
    "sg:address":"ZA le Maupas",
    "sg:city":"Saint Meen le Grand",
    "sg:orig_category":"Non-Classified Establishments",
    "sg:phone":"+33 2 99 09 52 73",
    "sg:postcode":"35290",
    "sg:province":"Bretagne",
    "wof:name":"Hillion S.a.r.l.",
    "wof:placetype":"venue"
},
  "geometry": {"coordinates":[-2.192364,48.18948],"type":"Point"}
}