{
  "type": "Feature",
  "properties": {
    "iso:country":"FR",
    "sg:address":"Chemin des Planches",
    "sg:city":"Lonrai",
    "sg:orig_category":"Unclassifiable Establishments",
    "sg:phone":"+33 2 33 26 43 53",
    "sg:postcode":"61250",
    "sg:province":"Basse Normandie",
    "wof:name":"Cattirolo & Le Page",
    "wof:placetype":"venue"
},
  "geometry": {"coordinates":[-0.052958,48.380058],"type":"Point"}
}