{
  "type": "Feature",
  "properties": {
    "addr:full":"Rte De Lavaur BP 171 81304 Graulhet Midi-Pyr\u00e9n\u00e9es",
    "addr:housenumber":"171",
    "addr:postcode":"81304",
    "addr:street":"Rte De Lavaur Bp",
    "iso:country":"FR",
    "sg:address":"Rte De Lavaur BP 171 81304 Graulhet",
    "sg:classifiers":[
        {
            "category":"Manufacturing",
            "subcategory":"Printing",
            "type":"Manufacturing & Wholesale Goods"
        }
    ],
    "sg:phone":"+33 5 63 42 84 00",
    "sg:province":"Midi-Pyr\u00e9n\u00e9es",
    "sg:tags":[
        "publishing"
    ],
    "wof:name":"Escourbiac Sa",
    "wof:placetype":"venue"
},
  "geometry": {"coordinates":[1.948225,43.754921],"type":"Point"}
}