{
  "type": "Feature",
  "properties": {
    "iso:country":"FR",
    "sg:address":"27, Rue Zamenhof, 57300 Hagondange",
    "sg:orig_category":"Non-Classified Establishments",
    "sg:phone":"+33 3 87 72 03 77",
    "sg:postcode":"57300",
    "sg:province":"Lorraine",
    "wof:name":"Capricorne S.a.",
    "wof:placetype":"venue"
},
  "geometry": {"coordinates":[6.168885,49.254585],"type":"Point"}
}