{
  "type": "Feature",
  "properties": {
    "addr:full":"146, Rue Charles le Goffic, 29000 Quimper Quimper Bretagne 29000",
    "addr:housenumber":"146",
    "addr:postcode":"29000;29000",
    "addr:street":"Rue Charles Le Goffic",
    "iso:country":"FR",
    "sg:address":"146, Rue Charles le Goffic, 29000 Quimper",
    "sg:city":"Quimper",
    "sg:orig_category":"Unclassifiable Establishments",
    "sg:phone":"+33 2 98 90 19 12",
    "sg:postcode":"29000",
    "sg:province":"Bretagne",
    "wof:name":"B\u00e9r\u00e9houc Andr\u00e9",
    "wof:placetype":"venue"
},
  "geometry": {"coordinates":[-4.056738,47.98407],"type":"Point"}
}