{
  "type": "Feature",
  "properties": {
    "iso:country":"FR",
    "sg:address":"B.P. 112, 45200 Montargis C\u00e9dex^^6, Rue Chatouillat, 45200 Montargis",
    "sg:city":"Montargis",
    "sg:orig_category":"Non-Classified Establishments",
    "sg:phone":"+33 2 38 89 88 88",
    "sg:postcode":"45200",
    "sg:province":"Centre",
    "wof:name":"Sicrie",
    "wof:placetype":"venue"
},
  "geometry": {"coordinates":[2.767561,47.974705],"type":"Point"}
}