{
  "type": "Feature",
  "properties": {
    "addr:full":"33, Rue des Vanesses, 93420 Villepinte Ile de France",
    "addr:housenumber":"33",
    "addr:postcode":"93420",
    "addr:street":"Rue Des Vanesses;Ile De France",
    "iso:country":"FR",
    "sg:address":"33, Rue des Vanesses, 93420 Villepinte",
    "sg:orig_category":"Unclassifiable Establishments",
    "sg:phone":"+33 1 48 63 80 20",
    "sg:province":"Ile de France",
    "wof:name":"Willett France S.a.r.l.",
    "wof:placetype":"venue"
},
  "geometry": {"coordinates":[2.505738,48.974586],"type":"Point"}
}