{
  "type": "Feature",
  "properties": {
    "addr:full":"B.P. 86 Naveil Centre 41100",
    "addr:postcode":"41100",
    "addr:street":"B.P. 86",
    "iso:country":"FR",
    "sg:address":"B.P. 86",
    "sg:city":"Naveil",
    "sg:orig_category":"Non-Classified Establishments",
    "sg:phone":"+33 2 54 73 40 41",
    "sg:postcode":"41100",
    "sg:province":"Centre",
    "wof:name":"Entreprises Minier S.a.",
    "wof:placetype":"venue"
},
  "geometry": {"coordinates":[1.17829,47.712414],"type":"Point"}
}