{
  "type": "Feature",
  "properties": {
    "iso:country":"FR",
    "sg:address":"Ferme de Vauluceau 78870 Bailly",
    "sg:orig_category":"Unclassifiable Establishments",
    "sg:phone":"+33 1 39 63 48 00",
    "sg:province":"Ile de France",
    "wof:name":"Gally Cr\u00e9ation S.a.r.l.",
    "wof:placetype":"venue"
},
  "geometry": {"coordinates":[2.079645,48.839886],"type":"Point"}
}