{
  "type": "Feature",
  "properties": {
    "iso:country":"FR",
    "sg:address":"11 bis, Rue Andr\u00e9 Theuriet, 74000 Annecy",
    "sg:orig_category":"Unclassifiable Establishments",
    "sg:phone":"+33 4 50 27 85 07",
    "sg:postcode":"74000",
    "sg:province":"Rhone-Alpes",
    "wof:name":"Lhomme Jean Louis",
    "wof:placetype":"venue"
},
  "geometry": {"coordinates":[6.136891,45.9063],"type":"Point"}
}