{
  "type": "Feature",
  "properties": {
    "iso:country":"FR",
    "sg:address":"12, Chemin du professeur Duperet - Les Bureaux Verts, 69160 Tassin la Demi Lune",
    "sg:orig_category":"Non-Classified Establishments",
    "sg:phone":"+33 4 78 34 50 50",
    "sg:postcode":"69160",
    "sg:province":"Rhone-Alpes",
    "wof:name":"Lambert Alcyon S.a.",
    "wof:placetype":"venue"
},
  "geometry": {"coordinates":[4.78198,45.76403],"type":"Point"}
}