{
  "type": "Feature",
  "properties": {
    "addr:full":"10500 Blignicourt Champagne",
    "addr:housenumber":"10500",
    "addr:street":"Blignicourt Champagne",
    "iso:country":"FR",
    "sg:address":"10500 Blignicourt",
    "sg:classifiers":[
        {
            "category":"Food & Beverages",
            "subcategory":"Ethnic Foods",
            "type":"Retail Goods"
        }
    ],
    "sg:phone":"+33 3 25 92 16 06",
    "sg:province":"Champagne",
    "sg:tags":[
        "sauerkraut"
    ],
    "wof:name":"Andr\u00e9 Laurent Sa",
    "wof:placetype":"venue"
},
  "geometry": {"coordinates":[4.534059,48.462906],"type":"Point"}
}