{
  "type": "Feature",
  "properties": {
    "iso:country":"FR",
    "sg:address":"41, Bd Montparnasse, 75006 Paris",
    "sg:orig_category":"Non-Classified Establishments",
    "sg:phone":"+33 1 53 63 39 33",
    "sg:province":"Ile de France",
    "wof:name":"Voyages Sol Y Son S.a.r.l.",
    "wof:placetype":"venue"
},
  "geometry": {"coordinates":[2.321595,48.844753],"type":"Point"}
}