{
  "type": "Feature",
  "properties": {
    "iso:country":"FR",
    "sg:address":"26, Rue de Meaux, 75019 Paris",
    "sg:orig_category":"Unclassifiable Establishments",
    "sg:phone":"+33 1 42 03 64 32",
    "sg:province":"Ile de France",
    "wof:name":"Unipag S.a.",
    "wof:placetype":"venue"
},
  "geometry": {"coordinates":[2.372133,48.879662],"type":"Point"}
}