{
  "type": "Feature",
  "properties": {
    "addr:full":"Rte de Beaupr\u00e9au La Regrippi\u00e8re Pays de Loire 44330",
    "addr:postcode":"44330",
    "addr:street":"Rte De Beaupre\u0301Au La",
    "iso:country":"FR",
    "sg:address":"Rte de Beaupr\u00e9au",
    "sg:city":"La Regrippi\u00e8re",
    "sg:orig_category":"Unclassifiable Establishments",
    "sg:phone":"+33 2 40 33 63 65",
    "sg:postcode":"44330",
    "sg:province":"Pays de Loire",
    "wof:name":"Royal Mer Bretagne S.a.",
    "wof:placetype":"venue"
},
  "geometry": {"coordinates":[-1.282404,47.140255],"type":"Point"}
}