{
  "type": "Feature",
  "properties": {
    "iso:country":"FR",
    "sg:address":"La Ventouzerie 22350 Plumaudan",
    "sg:city":"Plumaudan",
    "sg:orig_category":"Non-Classified Establishments",
    "sg:phone":"+33 2 96 86 00 65",
    "sg:postcode":"22350",
    "sg:province":"Bretagne",
    "wof:name":"Craquelins Christian Margely S.a.r.l.",
    "wof:placetype":"venue"
},
  "geometry": {"coordinates":[-2.123188,48.361378],"type":"Point"}
}