{
  "type": "Feature",
  "properties": {
    "addr:full":"Rue Des Charmilles 35510 Cesson S\u00e9vign\u00e9 Cesson-S\u00e9vign\u00e9 Bretagne 35510",
    "addr:postcode":"35510;se\u0301vigne\u0301 cesson-se\u0301vigne\u0301;35510",
    "addr:street":"Rue Des Charmilles",
    "iso:country":"FR",
    "sg:address":"Rue Des Charmilles 35510 Cesson S\u00e9vign\u00e9",
    "sg:city":"Cesson-S\u00e9vign\u00e9",
    "sg:classifiers":[
        {
            "category":"Government",
            "subcategory":"Department Of Motor Vehicles",
            "type":"Public Place"
        }
    ],
    "sg:phone":"+33 2 99 86 11 11",
    "sg:postcode":"35510",
    "sg:province":"Bretagne",
    "sg:tags":[
        "equipment",
        "industrial",
        "transport",
        "motor-cars"
    ],
    "wof:name":"Ets Carmoine Monvoisin Sa",
    "wof:placetype":"venue"
},
  "geometry": {"coordinates":[-1.621855,48.103146],"type":"Point"}
}