{
  "type": "Feature",
  "properties": {
    "addr:full":"11 Rue Amp\u00e8re Zi La Bruche 67120 Duttlenheim Duttlenheim Alsace 67120",
    "addr:housenumber":"11",
    "addr:postcode":"67120;67120",
    "addr:street":"Rue Ampe\u0300Re Zi La Bruche;Duttlenheim",
    "iso:country":"FR",
    "sg:address":"11 Rue Amp\u00e8re Zi La Bruche 67120 Duttlenheim",
    "sg:city":"Duttlenheim",
    "sg:classifiers":[
        {
            "category":"Wholesale",
            "subcategory":"Machinery & Supplies",
            "type":"Manufacturing & Wholesale Goods"
        }
    ],
    "sg:phone":"+33 3 88 49 78 78",
    "sg:postcode":"67120",
    "sg:province":"Alsace",
    "sg:tags":[
        "handling",
        "material",
        "-",
        "machine",
        "equipment",
        "engineering",
        "mechanical"
    ],
    "wof:name":"Manuest Concept Sa",
    "wof:placetype":"venue"
},
  "geometry": {"coordinates":[7.490672,48.540382],"type":"Point"}
}