{
  "type": "Feature",
  "properties": {
    "iso:country":"FR",
    "sg:address":"Pont Carral 81490 Noailhac",
    "sg:classifiers":[
        {
            "category":"Home & Garden",
            "subcategory":"Furniture",
            "type":"Retail Goods"
        }
    ],
    "sg:phone":"+33 5 63 50 50 28",
    "sg:postcode":"81490",
    "sg:province":"Midi Pyr\u00e9n\u00e9es",
    "sg:tags":[
        "household",
        "wood"
    ],
    "wof:name":"Siguier Sa",
    "wof:placetype":"venue"
},
  "geometry": {"coordinates":[2.33555,43.568668],"type":"Point"}
}