{
  "type": "Feature",
  "properties": {
    "addr:full":"7 Avenue Jean Jaures Castelnau Le Lez Languedoc-Roussillon 34170",
    "addr:housenumber":"7",
    "addr:postcode":"34170",
    "addr:street":"Avenue Jean Jaures",
    "iso:country":"FR",
    "sg:address":"7 Avenue Jean Jaures",
    "sg:city":"Castelnau Le Lez",
    "sg:classifiers":[
        {
            "category":"Banks & Credit Unions",
            "subcategory":"Financial Services",
            "type":"Services"
        }
    ],
    "sg:phone":"+33 4 67 02 20 40",
    "sg:postcode":"34170",
    "sg:province":"Languedoc-Roussillon",
    "sg:tags":[
        "banking",
        "finance",
        "insurance"
    ],
    "wof:name":"Caisse D'epargne Et De Prevoyance Du Languedoc Roussill (cep)",
    "wof:placetype":"venue"
},
  "geometry": {"coordinates":[3.895245,43.633682],"type":"Point"}
}