{
  "type": "Feature",
  "properties": {
    "iso:country":"FR",
    "sg:address":"15 Rue Verte 76000 Rouen",
    "sg:classifiers":[
        {
            "category":"Professional",
            "subcategory":"Business Services",
            "type":"Services"
        }
    ],
    "sg:phone":"+33 2 35 71 40 63",
    "sg:postcode":"76000",
    "sg:province":"Haute Normandie",
    "sg:tags":[
        "training",
        "advice"
    ],
    "wof:name":"Institution Rey Lycee Prive Mixte",
    "wof:placetype":"venue"
},
  "geometry": {"coordinates":[1.093306,49.447826],"type":"Point"}
}