{
  "type": "Feature",
  "properties": {
    "addr:full":"5 Rue De La Pompadour 94470 Boissy St L\u00e9ger Ile de France 94470",
    "addr:housenumber":"5",
    "addr:postcode":"94470;94470",
    "addr:street":"Rue De La Pompadour;Boissy St;Ile De France",
    "iso:country":"FR",
    "sg:address":"5 Rue De La Pompadour 94470 Boissy St L\u00e9ger",
    "sg:classifiers":[
        {
            "category":"Manufacturing",
            "subcategory":"Building Materials",
            "type":"Manufacturing & Wholesale Goods"
        }
    ],
    "sg:phone":"+33 1 45 69 22 11",
    "sg:postcode":"94470",
    "sg:province":"Ile de France",
    "sg:tags":[
        "glass",
        "ceramic"
    ],
    "wof:name":"Forms Sarl (ste)",
    "wof:placetype":"venue"
},
  "geometry": {"coordinates":[2.49886,48.761196],"type":"Point"}
}