{
  "type": "Feature",
  "properties": {
    "addr:full":"1 Rue Jules Renard 52100 St Dizier Champagne 52100",
    "addr:housenumber":"1",
    "addr:postcode":"52100;52100",
    "addr:street":"Rue Jules Renard;Champagne",
    "iso:country":"FR",
    "sg:address":"1 Rue Jules Renard 52100 St Dizier",
    "sg:classifiers":[
        {
            "category":"Professional",
            "subcategory":"Engineering",
            "type":"Services"
        }
    ],
    "sg:phone":"+33 3 25 05 80 40",
    "sg:postcode":"52100",
    "sg:province":"Champagne",
    "sg:tags":[
        "machine",
        "-",
        "mechanical"
    ],
    "wof:name":"Dalkia",
    "wof:placetype":"venue"
},
  "geometry": {"coordinates":[4.976983,48.645424],"type":"Point"}
}