{
  "type": "Feature",
  "properties": {
    "addr:full":"21, Bd Lamartine, 22000 Saint Brieuc Saint-Brieuc Bretagne 22000",
    "addr:housenumber":"21",
    "addr:postcode":"22000;22000",
    "addr:street":"Bd Lamartine;Brieuc;Bretagne",
    "iso:country":"FR",
    "sg:address":"21, Bd Lamartine, 22000 Saint Brieuc",
    "sg:city":"Saint-Brieuc",
    "sg:orig_category":"Non-Classified Establishments",
    "sg:phone":"+33 2 96 60 87 87",
    "sg:postcode":"22000",
    "sg:province":"Bretagne",
    "wof:name":"Civitas S.a.",
    "wof:placetype":"venue"
},
  "geometry": {"coordinates":[-2.761336,48.51926],"type":"Point"}
}