{
  "type": "Feature",
  "properties": {
    "iso:country":"FR",
    "sg:address":"Zi Des Gu\u00e9rins 42126 Le C\u00f4teau",
    "sg:classifiers":[
        {
            "category":"Shopping",
            "subcategory":"Crafts & Fabrics",
            "type":"Retail Goods"
        }
    ],
    "sg:phone":"+33 4 77 23 77 23",
    "sg:province":"Nord Pas-de-Calais",
    "sg:tags":[
        "textile",
        "clothing"
    ],
    "wof:name":"Henitex International Sa",
    "wof:placetype":"venue"
},
  "geometry": {"coordinates":[4.10162,46.009499],"type":"Point"}
}