{
  "type": "Feature",
  "properties": {
    "iso:country":"FR",
    "sg:address":"13B rue Martini 16300 BARBEZIEUX ST HILAIRE",
    "sg:classifiers":[
        {
            "category":"Food & Beverages",
            "subcategory":"Supermarket",
            "type":"Retail Goods"
        }
    ],
    "sg:phone":"+33 5 45 78 14 70",
    "sg:province":"Poitou-Charentes",
    "sg:tags":[
        "cask",
        "wine"
    ],
    "wof:name":"Tonnellerie Mercier S.a.",
    "wof:placetype":"venue"
},
  "geometry": {"coordinates":[-0.161591,45.47121],"type":"Point"}
}