{
  "type": "Feature",
  "properties": {
    "addr:full":"27 ave de la Gare; Quimper Quimper Bretagne 29000",
    "addr:postcode":"29000",
    "addr:street":"27 Ave De La Gare",
    "iso:country":"FR",
    "sg:address":"27 ave de la Gare; Quimper",
    "sg:city":"Quimper",
    "sg:classifiers":[
        {
            "category":"Banks & Credit Unions",
            "subcategory":"Bank",
            "type":"Services"
        }
    ],
    "sg:phone":"+33 3398902034",
    "sg:postcode":"29000",
    "sg:province":"Bretagne",
    "wof:name":"Banque Populaire Bretange, Atlantique",
    "wof:placetype":"venue"
},
  "geometry": {"coordinates":[-4.09402,47.994167],"type":"Point"}
}