{
  "type": "Feature",
  "properties": {
    "addr:full":"Zi Des Epinettes 73230 Barby Rhone-Alpes 73230",
    "addr:postcode":"73230;73230",
    "addr:street":"Des Epinettes",
    "iso:country":"FR",
    "sg:address":"Zi Des Epinettes 73230 Barby",
    "sg:classifiers":[
        {
            "category":"Professional",
            "subcategory":"Engineering",
            "type":"Services"
        }
    ],
    "sg:phone":"+33 4 79 72 75 41",
    "sg:postcode":"73230",
    "sg:province":"Rhone-Alpes",
    "sg:tags":[
        "machine",
        "-",
        "mechanical"
    ],
    "wof:name":"Thermic Froid Sa",
    "wof:placetype":"venue"
},
  "geometry": {"coordinates":[5.977465,45.571201],"type":"Point"}
}