{
  "type": "Feature",
  "properties": {
    "addr:full":"9, Rue du Novembre - Chanteloup , 41100 Villerable Villerable Centre 41100",
    "addr:housenumber":"9;villerable",
    "addr:postcode":"41100;41100",
    "addr:street":"Rue Du Novembre Chanteloup",
    "iso:country":"FR",
    "sg:address":"9, Rue du Novembre - Chanteloup , 41100 Villerable",
    "sg:city":"Villerable",
    "sg:orig_category":"Unclassifiable Establishments",
    "sg:phone":"+33 2 54 77 47 63",
    "sg:postcode":"41100",
    "sg:province":"Centre",
    "wof:name":"R.i.v.l. - Restauration Immobili\u00e8re Du Val De Loire",
    "wof:placetype":"venue"
},
  "geometry": {"coordinates":[1.17829,47.712414],"type":"Point"}
}