{
  "type": "Feature",
  "properties": {
    "addr:full":"Av Lavoisier BP 37 Zi Nord Bat Moutte 13340 Rognac Provence-Alpes-C\u00f4te d'Azur",
    "addr:housenumber":"bp 37",
    "addr:postcode":"13340",
    "addr:street":"Av Lavoisier;Zi Nord;Moutte",
    "iso:country":"FR",
    "sg:address":"Av Lavoisier BP 37 Zi Nord Bat Moutte 13340 Rognac",
    "sg:classifiers":[
        {
            "category":"Banks & Credit Unions",
            "subcategory":"Investment Brokerage",
            "type":"Services"
        }
    ],
    "sg:phone":"+33 4 42 87 61 20",
    "sg:province":"Provence-Alpes-C\u00f4te d'Azur",
    "sg:tags":[
        "-",
        "transport",
        "related"
    ],
    "wof:name":"Les Fils De A Doumenge",
    "wof:placetype":"venue"
},
  "geometry": {"coordinates":[5.229803,43.48933],"type":"Point"}
}