{
  "type": "Feature",
  "properties": {
    "iso:country":"FR",
    "sg:address":"Chemin des Docks",
    "sg:city":"Cr\u00e9py en Valois",
    "sg:orig_category":"Unclassifiable Establishments",
    "sg:phone":"+33 3 44 59 14 44",
    "sg:postcode":"60800",
    "sg:province":"Picardie",
    "wof:name":"Mantel Andr\u00e9 S.a.",
    "wof:placetype":"venue"
},
  "geometry": {"coordinates":[2.888205,49.229561],"type":"Point"}
}