{
  "type": "Feature",
  "properties": {
    "iso:country":"FR",
    "sg:address":"14, Rue Alexandre Volta, 39300 Champagnole",
    "sg:orig_category":"Non-Classified Establishments",
    "sg:phone":"+33 3 84 53 07 50",
    "sg:province":"Franche Comt\u00e9",
    "wof:name":"Rusthul Roland S.a.r.l. - Sotrabat",
    "wof:placetype":"venue"
},
  "geometry": {"coordinates":[5.926165,46.742199],"type":"Point"}
}