{
  "type": "Feature",
  "properties": {
    "iso:country":"FR",
    "sg:address":"20, Rue Lanterne, 69001 Lyon",
    "sg:orig_category":"Non-Classified Establishments",
    "sg:phone":"+33 4 78 28 30 17",
    "sg:province":"Rhone-Alpes",
    "wof:name":"Semmel Berthe S.e.m.",
    "wof:placetype":"venue"
},
  "geometry": {"coordinates":[4.83176,45.766094],"type":"Point"}
}