{
  "type": "Feature",
  "properties": {
    "iso:country":"FR",
    "sg:address":"40, Rue du Bignon - Immeuble Alpha, 35135 Chantepie",
    "sg:city":"Chantepie",
    "sg:orig_category":"Unclassifiable Establishments",
    "sg:phone":"+33 2 99 22 66 66",
    "sg:postcode":"35135",
    "sg:province":"Bretagne",
    "wof:name":"Tulip S.a.",
    "wof:placetype":"venue"
},
  "geometry": {"coordinates":[-1.621307,48.099197],"type":"Point"}
}