{
  "type": "Feature",
  "properties": {
    "addr:full":"Marche Gare 47000 Agen Agen Aquitaine 47000",
    "addr:postcode":"47000;47000",
    "iso:country":"FR",
    "sg:address":"Marche Gare 47000 Agen",
    "sg:city":"Agen",
    "sg:classifiers":[
        {
            "category":"Wholesale",
            "subcategory":"Machinery & Supplies",
            "type":"Manufacturing & Wholesale Goods"
        }
    ],
    "sg:phone":"+33 5 53 96 47 88",
    "sg:postcode":"47000",
    "sg:province":"Aquitaine",
    "sg:tags":[
        "equipment",
        "precision"
    ],
    "wof:name":"Pesage 47",
    "wof:placetype":"venue"
},
  "geometry": {"coordinates":[0.617495,44.203964],"type":"Point"}
}