{
  "type": "Feature",
  "properties": {
    "iso:country":"FR",
    "sg:address":"20, Rue Gaillefontaine, 60220 Formerie",
    "sg:orig_category":"Non-Classified Establishments",
    "sg:phone":"+33 3 44 04 54 00",
    "sg:province":"Picardie",
    "wof:name":"Gamma Industries S.a.",
    "wof:placetype":"venue"
},
  "geometry": {"coordinates":[1.72239,49.651665],"type":"Point"}
}