{
  "type": "Feature",
  "properties": {
    "addr:full":"B.P. 334 Lyon C\u00e9dex^^69120 Lyon Rhone-Alpes 69125",
    "addr:housenumber":"b.p. 334",
    "addr:postcode":"69125",
    "iso:country":"FR",
    "sg:address":"B.P. 334",
    "sg:city":"Lyon C\u00e9dex^^69120 Lyon",
    "sg:orig_category":"Non-Classified Establishments",
    "sg:phone":"+33 4 72 22 78 20",
    "sg:postcode":"69125",
    "sg:province":"Rhone-Alpes",
    "wof:name":"Rivoire S.a.",
    "wof:placetype":"venue"
},
  "geometry": {"coordinates":[4.916895,45.779022],"type":"Point"}
}