{
  "type": "Feature",
  "properties": {
    "addr:full":"98, Bd des Champs Elys\u00e9es - Immeuble Europ\u00e9en, 91080 Courcouronnes Ile de France",
    "addr:housenumber":"98",
    "addr:postcode":"91080",
    "addr:street":"Bd Des Champs Elyse\u0301Es;Europe\u0301En",
    "iso:country":"FR",
    "sg:address":"98, Bd des Champs Elys\u00e9es - Immeuble Europ\u00e9en, 91080 Courcouronnes",
    "sg:orig_category":"Unclassifiable Establishments",
    "sg:phone":"+33 1 60 79 92 00",
    "sg:province":"Ile de France",
    "wof:name":"Bureau V\u00e9ritas",
    "wof:placetype":"venue"
},
  "geometry": {"coordinates":[2.424111,48.630028],"type":"Point"}
}