{
  "type": "Feature",
  "properties": {
    "addr:full":"Rue Guillaume Schoettke 57200 Sarreguemines Lorraine",
    "addr:postcode":"57200",
    "addr:street":"Rue Guillaume Schoettke",
    "iso:country":"FR",
    "sg:address":"Rue Guillaume Schoettke 57200 Sarreguemines",
    "sg:classifiers":[
        {
            "category":"Manufacturing",
            "subcategory":"Printing",
            "type":"Manufacturing & Wholesale Goods"
        }
    ],
    "sg:phone":"+33 3 87 27 65 50",
    "sg:province":"Lorraine",
    "sg:tags":[
        "publishing"
    ],
    "wof:name":"Diehl France Sarl",
    "wof:placetype":"venue"
},
  "geometry": {"coordinates":[7.105895,49.106556],"type":"Point"}
}