{
  "type": "Feature",
  "properties": {
    "iso:country":"FR",
    "sg:address":"ZAC Tabernottes",
    "sg:city":"Yvrac",
    "sg:orig_category":"Unclassifiable Establishments",
    "sg:phone":"+33 5 57 80 74 80",
    "sg:postcode":"33370",
    "sg:province":"Aquitaine",
    "wof:name":"Iss Abilis S.a.",
    "wof:placetype":"venue"
},
  "geometry": {"coordinates":[-0.461917,44.880695],"type":"Point"}
}