{
  "type": "Feature",
  "properties": {
    "addr:full":"Zi De L'Allier 42220 Bourg Argental Rhone-Alpes 42220",
    "addr:postcode":"42220;42220",
    "addr:street":"Zi De L'Allier;Rhone-Alpes",
    "iso:country":"FR",
    "sg:address":"Zi De L'Allier 42220 Bourg Argental",
    "sg:classifiers":[
        {
            "category":"Professional",
            "subcategory":"Engineering",
            "type":"Services"
        }
    ],
    "sg:phone":"+33 4 77 40 21 50",
    "sg:postcode":"42220",
    "sg:province":"Rhone-Alpes",
    "sg:tags":[
        "machine",
        "-",
        "mechanical"
    ],
    "wof:name":"Martin Plastiques Innovations Sa",
    "wof:placetype":"venue"
},
  "geometry": {"coordinates":[3.435126,46.127289],"type":"Point"}
}