{
  "type": "Feature",
  "properties": {
    "iso:country":"FR",
    "sg:address":"8 Rue Insurrection Parisien 94600 Choisy Le Roi",
    "sg:classifiers":[
        {
            "category":"Professional",
            "subcategory":"Engineering",
            "type":"Services"
        }
    ],
    "sg:phone":"+33 1 46 80 03 92",
    "sg:postcode":"94600",
    "sg:province":"Ile de France",
    "sg:tags":[
        "machine",
        "-",
        "mechanical"
    ],
    "wof:name":"Repex",
    "wof:placetype":"venue"
},
  "geometry": {"coordinates":[2.403846,48.770218],"type":"Point"}
}