{
  "type": "Feature",
  "properties": {
    "iso:country":"FR",
    "sg:address":"14270 Bieville Quetieville",
    "sg:city":"Cesny-aux-Vignes-Ou\u00e9zy",
    "sg:orig_category":"Miscellaneous Products",
    "sg:phone":"+33 2 31 20 78 08",
    "sg:postcode":"14270",
    "sg:province":"Basse Normandie",
    "wof:name":"Modling Sas",
    "wof:placetype":"venue"
},
  "geometry": {"coordinates":[-0.040903,49.103233],"type":"Point"}
}