{
  "type": "Feature",
  "properties": {
    "addr:full":"ZI Coupat Bo\u00e9 Aquitaine 47550",
    "addr:housenumber":"boe\u0301",
    "addr:postcode":"47550",
    "iso:country":"FR",
    "sg:address":"ZI Coupat",
    "sg:city":"Bo\u00e9",
    "sg:orig_category":"Unclassifiable Establishments",
    "sg:phone":"+33 5 53 69 24 00",
    "sg:postcode":"47550",
    "sg:province":"Aquitaine",
    "wof:name":"Dubouil S.a.",
    "wof:placetype":"venue"
},
  "geometry": {"coordinates":[0.626876,44.160385],"type":"Point"}
}