{
  "type": "Feature",
  "properties": {
    "iso:country":"FR",
    "sg:address":"710 Av Des March\u00e9s 84200 Carpentras",
    "sg:classifiers":[
        {
            "category":"Professional",
            "type":"Services"
        }
    ],
    "sg:phone":"+33 4 90 63 39 76",
    "sg:province":"Lorraine",
    "sg:tags":[
        "transport",
        "road"
    ],
    "wof:name":"Transports Berthaud Provence",
    "wof:placetype":"venue"
},
  "geometry": {"coordinates":[5.040558,44.039558],"type":"Point"}
}