{
  "type": "Feature",
  "properties": {
    "iso:country":"FR",
    "sg:address":"56, Bd de la Portelette, 80100 Abbeville",
    "sg:orig_category":"Non-Classified Establishments",
    "sg:phone":"+33 3 22 24 31 57",
    "sg:province":"Picardie",
    "wof:name":"S.g.p. S.a.r.l. - Sogeprove",
    "wof:placetype":"venue"
},
  "geometry": {"coordinates":[1.827485,50.101479],"type":"Point"}
}