{
  "type": "Feature",
  "properties": {
    "addr:full":"Voie Testelet 27100 Val De Reuil Haute Normandie 27100",
    "addr:postcode":"27100;27100",
    "addr:street":"Voie Testelet;Haute Normandie",
    "iso:country":"FR",
    "sg:address":"Voie Testelet 27100 Val De Reuil",
    "sg:classifiers":[
        {
            "category":"Professional",
            "subcategory":"Engineering",
            "type":"Services"
        }
    ],
    "sg:phone":"+33 2 32 61 24 11",
    "sg:postcode":"27100",
    "sg:province":"Haute Normandie",
    "sg:tags":[
        "machine",
        "-",
        "mechanical"
    ],
    "wof:name":"Hmg Sa",
    "wof:placetype":"venue"
},
  "geometry": {"coordinates":[1.178405,49.249973],"type":"Point"}
}