{
  "type": "Feature",
  "properties": {
    "addr:full":"14 Boulevard De La Madeleine 75008 Paris Ile de France 75008",
    "addr:housenumber":"14",
    "addr:postcode":"75008;75008",
    "addr:street":"Boulevard De La Madeleine",
    "iso:country":"FR",
    "sg:address":"14 Boulevard De La Madeleine 75008 Paris",
    "sg:classifiers":[
        {
            "category":"Shopping",
            "subcategory":"Clothing, Apparel, & Fashions",
            "type":"Retail Goods"
        }
    ],
    "sg:phone":"+33 1 43 12 55 20",
    "sg:postcode":"75008",
    "sg:province":"Ile de France",
    "sg:tags":[
        "textile",
        "clothing",
        "clothes"
    ],
    "wof:name":"Herve Leger Societe Anonyme",
    "wof:placetype":"venue"
},
  "geometry": {"coordinates":[2.325667,48.869602],"type":"Point"}
}