{
  "type": "Feature",
  "properties": {
    "addr:full":"95, Rue Nicolas Vauquelin, 31100 Toulouse Midi Pyr\u00e9n\u00e9es",
    "addr:housenumber":"95",
    "addr:postcode":"31100",
    "addr:street":"Rue Nicolas Vauquelin",
    "iso:country":"FR",
    "sg:address":"95, Rue Nicolas Vauquelin, 31100 Toulouse",
    "sg:orig_category":"Unclassifiable Establishments",
    "sg:phone":"+33 5 61 43 06 44",
    "sg:province":"Midi Pyr\u00e9n\u00e9es",
    "wof:name":"Sud-ouest Aff\u00fbtage",
    "wof:placetype":"venue"
},
  "geometry": {"coordinates":[1.404324,43.58144],"type":"Point"}
}