{
  "type": "Feature",
  "properties": {
    "addr:full":"Rte de Lyons la For\u00eat - ZAC des Deux Rivi\u00e8res Rouen Haute Normandie 76000",
    "addr:postcode":"76000",
    "addr:street":"Rte De Lyons La;Zac Des Deux Rivie\u0300Res;Haute Normandie",
    "iso:country":"FR",
    "sg:address":"Rte de Lyons la For\u00eat - ZAC des Deux Rivi\u00e8res",
    "sg:city":"Rouen",
    "sg:orig_category":"Non-Classified Establishments",
    "sg:phone":"+33 2 35 15 70 00",
    "sg:postcode":"76000",
    "sg:province":"Haute Normandie",
    "wof:name":"Ma\u00ebs Et Compagnie S.a.",
    "wof:placetype":"venue"
},
  "geometry": {"coordinates":[1.08933,49.44038],"type":"Point"}
}