{
  "type": "Feature",
  "properties": {
    "iso:country":"FR",
    "sg:address":"Les Ailes Centre Travaux Vichy 03200 Vichy",
    "sg:city":"Vichy",
    "sg:orig_category":"Miscellaneous Products",
    "sg:phone":"+33 4 70 96 54 54",
    "sg:postcode":"03200",
    "sg:province":"Auvergne",
    "wof:name":"Saur France (cise)",
    "wof:placetype":"venue"
},
  "geometry": {"coordinates":[3.433,46.122379],"type":"Point"}
}