{
  "type": "Feature",
  "properties": {
    "addr:full":"B.P. 3, 59680 Ferri\u00e8re la Petite^^Route de S Ch\u00e2teau, 59680 Ferri\u00e8re la Petite Nord Pas-de-Calais",
    "addr:housenumber":"3",
    "addr:postcode":"59680;59680",
    "addr:street":"B.P.;Cha\u0302Teau",
    "iso:country":"FR",
    "sg:address":"B.P. 3, 59680 Ferri\u00e8re la Petite^^Route de S Ch\u00e2teau, 59680 Ferri\u00e8re la Petite",
    "sg:orig_category":"Non-Classified Establishments",
    "sg:phone":"+33 3 27 62 03 18",
    "sg:province":"Nord Pas-de-Calais",
    "wof:name":"Jeu S.a.r.l.",
    "wof:placetype":"venue"
},
  "geometry": {"coordinates":[4.076595,50.253876],"type":"Point"}
}