{
  "type": "Feature",
  "properties": {
    "addr:full":"3, Rue Gustave Eiffel - ZI, 77220 Tournan en Brie Ile de France",
    "addr:housenumber":"3",
    "addr:postcode":"77220",
    "addr:street":"Rue Gustave Eiffel Zi",
    "iso:country":"FR",
    "sg:address":"3, Rue Gustave Eiffel - ZI, 77220 Tournan en Brie",
    "sg:orig_category":"Unclassifiable Establishments",
    "sg:phone":"+33 1 64 07 96 79",
    "sg:province":"Ile de France",
    "wof:name":"Cabsys T\u00e9l\u00e9broke S.a.r.l.",
    "wof:placetype":"venue"
},
  "geometry": {"coordinates":[2.76256,48.739803],"type":"Point"}
}