{
  "type": "Feature",
  "properties": {
    "addr:full":"37 bis, Rue Favard Guillaumond - ZI Taillas, 43600 Sainte Sigol\u00e8ne Les Villettes Auvergne 43600",
    "addr:housenumber":"37 bis",
    "addr:postcode":"43600;43600",
    "addr:street":"Rue Favard;Zi Taillas;Sigole\u0300Ne;Villettes",
    "iso:country":"FR",
    "sg:address":"37 bis, Rue Favard Guillaumond - ZI Taillas, 43600 Sainte Sigol\u00e8ne",
    "sg:city":"Les Villettes",
    "sg:orig_category":"Non-Classified Establishments",
    "sg:phone":"+33 4 71 61 59 49",
    "sg:postcode":"43600",
    "sg:province":"Auvergne",
    "wof:name":"Plastigol\u00e8ne S.a.r.l.",
    "wof:placetype":"venue"
},
  "geometry": {"coordinates":[4.23542,45.243401],"type":"Point"}
}