{
  "type": "Feature",
  "properties": {
    "iso:country":"FR",
    "sg:address":"Ch\u00e2teau de Pourcieux 83470 Pourcieux",
    "sg:city":"Ch\u00e2teau",
    "sg:orig_category":"Unclassifiable Establishments",
    "sg:phone":"+33 4 94 59 78 90",
    "sg:postcode":"71250",
    "sg:province":"Bourgogne",
    "wof:name":"D'espagnet Michel",
    "wof:placetype":"venue"
},
  "geometry": {"coordinates":[5.86024,43.452847],"type":"Point"}
}