{
  "type": "Feature",
  "properties": {
    "addr:full":"12 Rue Ecoles 38860 Les Deux Alpes Rhone-Alpes 38860",
    "addr:housenumber":"12",
    "addr:postcode":"38860;38860",
    "addr:street":"Rue Ecoles",
    "iso:country":"FR",
    "sg:address":"12 Rue Ecoles 38860 Les Deux Alpes",
    "sg:classifiers":[
        {
            "category":"Travel",
            "subcategory":"Hotels & Motels",
            "type":"Entertainment"
        }
    ],
    "sg:phone":"+33 4 76 80 50 60",
    "sg:postcode":"38860",
    "sg:province":"Rhone-Alpes",
    "sg:tags":[
        "hotels",
        "business",
        "restaurant"
    ],
    "wof:name":"La Mariande Sarl",
    "wof:placetype":"venue"
},
  "geometry": {"coordinates":[6.121058,45.004669],"type":"Point"}
}