{
  "type": "Feature",
  "properties": {
    "iso:country":"FR",
    "sg:address":"14, Rue des Forges, 51200 Epernay",
    "sg:orig_category":"Unclassifiable Establishments",
    "sg:phone":"+33 3 26 59 58 70",
    "sg:province":"Champagne",
    "wof:name":"Distransport S.a.e.m.",
    "wof:placetype":"venue"
},
  "geometry": {"coordinates":[3.950584,49.029461],"type":"Point"}
}