{
  "type": "Feature",
  "properties": {
    "addr:full":"154 all\u00e9e des Erables 93420 Villepinte Ile de France 93420",
    "addr:housenumber":"154",
    "addr:postcode":"93420;93420",
    "addr:street":"Alle\u0301E Des Erables;Ile De France",
    "iso:country":"FR",
    "sg:address":"154 all\u00e9e des Erables 93420 Villepinte",
    "sg:classifiers":[
        {
            "category":"Banks & Credit Unions",
            "subcategory":"Investment Brokerage",
            "type":"Services"
        }
    ],
    "sg:phone":"+33 1 60 61 62 62",
    "sg:postcode":"93420",
    "sg:province":"Ile de France",
    "sg:tags":[
        "product",
        "hair-care"
    ],
    "wof:name":"Miss Antilles International Sarl",
    "wof:placetype":"venue"
},
  "geometry": {"coordinates":[2.501765,48.973576],"type":"Point"}
}