{
  "type": "Feature",
  "properties": {
    "addr:full":"B.P. 266, 69659 Villefranche C\u00e9dex^^29, Rue des Deux Ruisseaux - ZI de la Collonge, 69400 Gleiz\u00e9 Rhone-Alpes 69400",
    "addr:housenumber":"b.p. 266",
    "addr:postcode":"69659;69400;69400",
    "addr:street":"Rue Des Deux Ruisseaux Zi De La Collonge",
    "iso:country":"FR",
    "sg:address":"B.P. 266, 69659 Villefranche C\u00e9dex^^29, Rue des Deux Ruisseaux - ZI de la Collonge, 69400 Gleiz\u00e9",
    "sg:orig_category":"Non-Classified Establishments",
    "sg:phone":"+33 4 74 02 28 58",
    "sg:postcode":"69400",
    "sg:province":"Rhone-Alpes",
    "wof:name":"Rgm Industries S.a.",
    "wof:placetype":"venue"
},
  "geometry": {"coordinates":[4.64756,45.957378],"type":"Point"}
}