{
  "type": "Feature",
  "properties": {
    "iso:country":"FR",
    "sg:address":"18, Rue de l'Arquebuse, 21000 Dijon",
    "sg:city":"Dijon",
    "sg:orig_category":"Non-Classified Establishments",
    "sg:phone":"+33 3 80 41 64 64",
    "sg:postcode":"21000",
    "sg:province":"Bourgogne",
    "wof:name":"Droz S.a.",
    "wof:placetype":"venue"
},
  "geometry": {"coordinates":[5.029389,47.321522],"type":"Point"}
}