{
  "type": "Feature",
  "properties": {
    "addr:full":"2 Rue Haute Saint Martin Sable Sur Sarthe Pays de Loire 72300",
    "addr:housenumber":"2",
    "addr:postcode":"72300",
    "addr:street":"Rue Haute Saint Martin Sable;Loire",
    "iso:country":"FR",
    "sg:address":"2 Rue Haute Saint Martin",
    "sg:city":"Sable Sur Sarthe",
    "sg:classifiers":[
        {
            "category":"Banks & Credit Unions",
            "subcategory":"Financial Services",
            "type":"Services"
        }
    ],
    "sg:phone":"+33 2 43 62 16 60",
    "sg:postcode":"72300",
    "sg:province":"Pays de Loire",
    "sg:tags":[
        "banking",
        "finance",
        "insurance"
    ],
    "wof:name":"Fiduciaire Technique Et Comptable De L'ouest (fiteco)",
    "wof:placetype":"venue"
},
  "geometry": {"coordinates":[-0.334995,47.840271],"type":"Point"}
}