{
  "type": "Feature",
  "properties": {
    "addr:full":"3621, Rte d'Alberville, 74320 Sevrier Rhone-Alpes 74320",
    "addr:housenumber":"3621",
    "addr:postcode":"74320;74320",
    "addr:street":"Rte D'Alberville",
    "iso:country":"FR",
    "sg:address":"3621, Rte d'Alberville, 74320 Sevrier",
    "sg:orig_category":"Unclassifiable Establishments",
    "sg:phone":"+33 4 50 19 00 19",
    "sg:postcode":"74320",
    "sg:province":"Rhone-Alpes",
    "wof:name":"Sporttrade France S.a.r.l.",
    "wof:placetype":"venue"
},
  "geometry": {"coordinates":[6.142122,45.882881],"type":"Point"}
}