{
  "type": "Feature",
  "properties": {
    "addr:full":"25 Av Des Arts 69100 Villeurbanne Rhone-Alpes 69100",
    "addr:postcode":"69100;69100",
    "addr:street":"25 Av Des Arts",
    "iso:country":"FR",
    "sg:address":"25 Av Des Arts 69100 Villeurbanne",
    "sg:classifiers":[
        {
            "category":"Health Services",
            "subcategory":"Podiatrist",
            "type":"Services"
        }
    ],
    "sg:phone":"+33 4 72 44 49 00",
    "sg:postcode":"69100",
    "sg:province":"Rhone-Alpes",
    "sg:tags":[
        "instrument",
        "measurement",
        "-",
        "precision",
        "equipment"
    ],
    "wof:name":"Cetiat",
    "wof:placetype":"venue"
},
  "geometry": {"coordinates":[4.87704,45.784889],"type":"Point"}
}