{
  "type": "Feature",
  "properties": {
    "addr:full":"B.P. 405, 31314 Lab\u00e8ge C\u00e9dex^^Innopolis B\u00e2t. B, 31670 Lab\u00e8ge Midi Pyr\u00e9n\u00e9es",
    "addr:housenumber":"b.p. 405",
    "addr:postcode":"31314;ba\u0302t;31670",
    "iso:country":"FR",
    "sg:address":"B.P. 405, 31314 Lab\u00e8ge C\u00e9dex^^Innopolis B\u00e2t. B, 31670 Lab\u00e8ge",
    "sg:orig_category":"Non-Classified Establishments",
    "sg:phone":"+33 5 61 39 21 92",
    "sg:province":"Midi Pyr\u00e9n\u00e9es",
    "wof:name":"Mach 3 Informatique S.a.r.l.",
    "wof:placetype":"venue"
},
  "geometry": {"coordinates":[1.527111,43.529713],"type":"Point"}
}