{
  "type": "Feature",
  "properties": {
    "addr:full":"34 blvd de Sebastopol; Paris; 750041 Ile de France 75004",
    "addr:postcode":"750041;75004",
    "addr:street":"34 Blvd De Sebastopol;De France",
    "iso:country":"FR",
    "sg:address":"34 blvd de Sebastopol; Paris; 750041",
    "sg:classifiers":[
        {
            "category":"Banks & Credit Unions",
            "subcategory":"Bank",
            "type":"Services"
        }
    ],
    "sg:phone":"+33 1 44 54 26 80",
    "sg:postcode":"75004",
    "sg:province":"Ile de France",
    "wof:name":"Soci\u00e9t\u00e9 G\u00e9n\u00e9rale",
    "wof:placetype":"venue"
},
  "geometry": {"coordinates":[2.349971,48.861336],"type":"Point"}
}