{
  "type": "Feature",
  "properties": {
    "iso:country":"FR",
    "sg:address":"15, Rue des Sablons, 75016 Paris",
    "sg:orig_category":"Unclassifiable Establishments",
    "sg:phone":"+33 1 47 55 76 00",
    "sg:province":"Ile de France",
    "wof:name":"Le Grand Livre Du Mois S.a.",
    "wof:placetype":"venue"
},
  "geometry": {"coordinates":[2.283762,48.865814],"type":"Point"}
}