{
  "type": "Feature",
  "properties": {
    "addr:full":"6, Rue Pierre M\u00e9tairie - ZA du Bel Air, 78120 Rambouillet Ile de France",
    "addr:housenumber":"6",
    "addr:postcode":"78120;ile",
    "addr:street":"Rue Pierre Me\u0301Tairie Za Du Bel Air",
    "iso:country":"FR",
    "sg:address":"6, Rue Pierre M\u00e9tairie - ZA du Bel Air, 78120 Rambouillet",
    "sg:orig_category":"Non-Classified Establishments",
    "sg:phone":"+33 1 30 46 52 52",
    "sg:province":"Ile de France",
    "wof:name":"Kiloutou S.a.",
    "wof:placetype":"venue"
},
  "geometry": {"coordinates":[1.826199,48.643406],"type":"Point"}
}