{
  "type": "Feature",
  "properties": {
    "addr:full":"Rue Des Embruns 29760 Penmarch Penmarch Bretagne 29760",
    "addr:postcode":"29760;29760",
    "addr:street":"Rue Des Embruns;Penmarch Bretagne",
    "iso:country":"FR",
    "sg:address":"Rue Des Embruns 29760 Penmarch",
    "sg:city":"Penmarch",
    "sg:classifiers":[
        {
            "category":"Farming",
            "subcategory":"Livestock Farm",
            "type":"Manufacturing & Wholesale Goods"
        }
    ],
    "sg:phone":"+33 2 98 58 52 44",
    "sg:postcode":"29760",
    "sg:province":"Bretagne",
    "sg:tags":[
        "breeding",
        "agriculture",
        "animal"
    ],
    "wof:name":"Art Mer",
    "wof:placetype":"venue"
},
  "geometry": {"coordinates":[-4.379969,47.81995],"type":"Point"}
}