{
  "type": "Feature",
  "properties": {
    "addr:full":"330 Rue Du Mourelet Zi Courtine 84000 Avignon Franche Comt\u00e9",
    "addr:housenumber":"330",
    "addr:postcode":"84000",
    "addr:street":"Rue Du Mourelet Zi Courtine;Franche Comte\u0301",
    "iso:country":"FR",
    "sg:address":"330 Rue Du Mourelet Zi Courtine 84000 Avignon",
    "sg:classifiers":[
        {
            "category":"Wholesale",
            "subcategory":"Vending Machines",
            "type":"Manufacturing & Wholesale Goods"
        }
    ],
    "sg:phone":"+33 4 32 76 03 00",
    "sg:province":"Franche Comt\u00e9",
    "sg:tags":[
        "energy",
        "-",
        "environment",
        "equipment",
        "engineering",
        "machinery",
        "mechanical"
    ],
    "wof:name":"Eole Res",
    "wof:placetype":"venue"
},
  "geometry": {"coordinates":[4.806015,43.948753],"type":"Point"}
}