{
  "type": "Feature",
  "properties": {
    "iso:country":"FR",
    "sg:address":"B.P. 130, 91944 Courtaboeuf C\u00e9dex^^7, Av. des Andes - ZI de Courtaboeuf, 91900 Les Ulis",
    "sg:orig_category":"Non-Classified Establishments",
    "sg:phone":"+33 1 69 29 88 68",
    "sg:province":"\u00cele-de-France",
    "wof:name":"Pelikan Hardcopy France S.a.",
    "wof:placetype":"venue"
},
  "geometry": {"coordinates":[2.16947,48.68161],"type":"Point"}
}