{
  "type": "Feature",
  "properties": {
    "addr:full":"30, Rue Commandant Lenoir, 38600 Fontaine Rhone-Alpes",
    "addr:housenumber":"30",
    "addr:postcode":"38600",
    "addr:street":"Rue Commandant Lenoir",
    "iso:country":"FR",
    "sg:address":"30, Rue Commandant Lenoir, 38600 Fontaine",
    "sg:orig_category":"Non-Classified Establishments",
    "sg:phone":"+33 4 76 26 02 89",
    "sg:province":"Rhone-Alpes",
    "wof:name":"Fontaine Insertion",
    "wof:placetype":"venue"
},
  "geometry": {"coordinates":[5.674567,45.191063],"type":"Point"}
}