{
  "type": "Feature",
  "properties": {
    "addr:full":"Zi Technoparc Futura Rue De L'Universit\u00e9 B\u00e9thune Nord Pas-de-Calais 62400",
    "addr:postcode":"62400",
    "addr:street":"Rue De L'Universite \u0301 Be\u0301Thune Nord",
    "iso:country":"FR",
    "sg:address":"Zi Technoparc Futura Rue De L'Universit\u00e9",
    "sg:city":"B\u00e9thune",
    "sg:classifiers":[
        {
            "category":"Banks & Credit Unions",
            "subcategory":"Financial Services",
            "type":"Services"
        }
    ],
    "sg:phone":"+33 3 21 63 14 20",
    "sg:postcode":"62400",
    "sg:province":"Nord Pas-de-Calais",
    "sg:tags":[
        "banking",
        "finance",
        "insurance"
    ],
    "wof:name":"Secob Porquet Beve Et Associes Sa",
    "wof:placetype":"venue"
},
  "geometry": {"coordinates":[2.653541,50.521114],"type":"Point"}
}