{
  "type": "Feature",
  "properties": {
    "iso:country":"FR",
    "sg:address":"Rue Barth\u00e9l\u00e9my Thimonnier - ZI",
    "sg:city":"Elne",
    "sg:orig_category":"Unclassifiable Establishments",
    "sg:phone":"+33 4 68 22 20 05",
    "sg:postcode":"66200",
    "sg:province":"Languedoc-Roussillon",
    "wof:name":"Gali France S.a.",
    "wof:placetype":"venue"
},
  "geometry": {"coordinates":[2.982696,42.606895],"type":"Point"}
}