{
  "type": "Feature",
  "properties": {
    "iso:country":"FR",
    "sg:address":"1 bis, Rue de Verdun, 34000 Montpellier",
    "sg:orig_category":"Non-Classified Establishments",
    "sg:phone":"+33 4 67 58 10 11",
    "sg:postcode":"34000",
    "sg:province":"Languedoc-Roussillon",
    "wof:name":"Coface S.a. - Compagnie Fran\u00e7aise D'assurance Pour Le Commerce",
    "wof:placetype":"venue"
},
  "geometry": {"coordinates":[3.880158,43.608215],"type":"Point"}
}