{
  "type": "Feature",
  "properties": {
    "addr:full":"Ch\u00e2teau la Fontaine Fronsac Aquitaine 33126",
    "addr:postcode":"33126",
    "addr:street":"Fronsac",
    "iso:country":"FR",
    "sg:address":"Ch\u00e2teau la Fontaine",
    "sg:city":"Fronsac",
    "sg:orig_category":"Non-Classified Establishments",
    "sg:phone":"+33 5 57 51 01 43",
    "sg:postcode":"33126",
    "sg:province":"Aquitaine",
    "wof:name":"Ch\u00e2teau La Fontaine",
    "wof:placetype":"venue"
},
  "geometry": {"coordinates":[-0.272819,44.924126],"type":"Point"}
}