{
  "type": "Feature",
  "properties": {
    "addr:full":"7, Esplanade Compans Caffarelli, 31000 Toulouse Midi Pyr\u00e9n\u00e9es 31000",
    "addr:housenumber":"7",
    "addr:postcode":"31000;31000",
    "addr:street":"Esplanade Compans Caffarelli",
    "iso:country":"FR",
    "sg:address":"7, Esplanade Compans Caffarelli, 31000 Toulouse",
    "sg:orig_category":"Non-Classified Establishments",
    "sg:phone":"+33 5 62 30 37 37",
    "sg:postcode":"31000",
    "sg:province":"Midi Pyr\u00e9n\u00e9es",
    "wof:name":"Chronopost International",
    "wof:placetype":"venue"
},
  "geometry": {"coordinates":[1.435147,43.61084],"type":"Point"}
}