{
  "type": "Feature",
  "properties": {
    "addr:full":"Rue Juiverie 72560 Chang\u00e9 Pays de Loire 72560",
    "addr:postcode":"72560;72560",
    "addr:street":"Rue Juiverie",
    "iso:country":"FR",
    "sg:address":"Rue Juiverie 72560 Chang\u00e9",
    "sg:classifiers":[
        {
            "category":"Wholesale",
            "subcategory":"Meat",
            "type":"Manufacturing & Wholesale Goods"
        }
    ],
    "sg:phone":"+33 2 43 61 57 57",
    "sg:postcode":"72560",
    "sg:province":"Pays de Loire",
    "sg:tags":[
        "food",
        "cooked",
        "product",
        "related"
    ],
    "wof:name":"Luissier Bordeau Chesnel",
    "wof:placetype":"venue"
},
  "geometry": {"coordinates":[0.280595,47.986206],"type":"Point"}
}