{
  "type": "Feature",
  "properties": {
    "iso:country":"FR",
    "sg:address":"50 blvd de Courtais; Montlu\u00e7on",
    "sg:classifiers":[
        {
            "category":"Banks & Credit Unions",
            "subcategory":"Bank",
            "type":"Services"
        }
    ],
    "sg:phone":"+33 3370039493",
    "sg:province":"Midi Pyr\u00e9n\u00e9es",
    "wof:name":"Banque Populaire Du, Massif Central",
    "wof:placetype":"venue"
},
  "geometry": {"coordinates":[2.602068,46.338787],"type":"Point"}
}