{
  "type": "Feature",
  "properties": {
    "iso:country":"FR",
    "sg:address":"B.P. 68, 77615 Marne la Vall\u00e9e C\u00e9dex 3^^1, All\u00e9e du Clos des Charmes - Les Portes de la For\u00eat, 77615",
    "sg:orig_category":"Non-Classified Establishments",
    "sg:phone":"+33 1 60 06 52 34",
    "sg:province":"Bourgogne",
    "wof:name":"Hama S.a.r.l.",
    "wof:placetype":"venue"
},
  "geometry": {"coordinates":[-94.071724,30.353951],"type":"Point"}
}