{
  "type": "Feature",
  "properties": {
    "iso:country":"FR",
    "sg:address":"40 Rue Du Cherche Midi 75006 Paris",
    "sg:classifiers":[
        {
            "category":"Professional",
            "subcategory":"Advertising",
            "type":"Services"
        }
    ],
    "sg:phone":"+33 1 45 49 22 56",
    "sg:postcode":"75006",
    "sg:province":"Ile de France",
    "sg:tags":[
        "communication",
        "medium"
    ],
    "wof:name":"Business Sa",
    "wof:placetype":"venue"
},
  "geometry": {"coordinates":[2.326389,48.849617],"type":"Point"}
}