{
  "type": "Feature",
  "properties": {
    "addr:full":"3 rue Pierre Corneille 69006 Lyon Rhone-Alpes",
    "addr:housenumber":"3",
    "addr:postcode":"69006",
    "addr:street":"Rue Pierre Corneille",
    "iso:country":"FR",
    "sg:address":"3 rue Pierre Corneille 69006 Lyon",
    "sg:classifiers":[
        {
            "category":"Manufacturing",
            "subcategory":"Textiles",
            "type":"Manufacturing & Wholesale Goods"
        }
    ],
    "sg:phone":"+33 4 72 75 97 11",
    "sg:province":"Rhone-Alpes",
    "sg:tags":[
        "import"
    ],
    "wof:name":"Bnj Creations Eurl",
    "wof:placetype":"venue"
},
  "geometry": {"coordinates":[4.843293,45.767689],"type":"Point"}
}