{
  "type": "Feature",
  "properties": {
    "iso:country":"FR",
    "sg:address":"B.P. 19, 54510 Tomblaine^^60, Rue Salvador Allende, 54510 Tomblaine",
    "sg:orig_category":"Non-Classified Establishments",
    "sg:phone":"+33 3 83 18 28 38",
    "sg:province":"Lorraine",
    "wof:name":"Rulquin Distribution S.a.",
    "wof:placetype":"venue"
},
  "geometry": {"coordinates":[6.209848,48.687271],"type":"Point"}
}