{
  "type": "Feature",
  "properties": {
    "addr:full":"Av Mar\u00e9chal Leclerc 71300 Montceau Les Mines Saint-Berain-sous-Sanvignes Bourgogne 71300",
    "addr:postcode":"71300;71300",
    "addr:street":"Av Mare\u0301Chal Leclerc;Bourgogne",
    "iso:country":"FR",
    "sg:address":"Av Mar\u00e9chal Leclerc 71300 Montceau Les Mines",
    "sg:city":"Saint-Berain-sous-Sanvignes",
    "sg:classifiers":[
        {
            "category":"Manufacturing",
            "subcategory":"Tools & Machinery",
            "type":"Manufacturing & Wholesale Goods"
        }
    ],
    "sg:phone":"+33 3 85 67 90 20",
    "sg:postcode":"71300",
    "sg:province":"Bourgogne",
    "sg:tags":[
        "metallurgy",
        "metalworking"
    ],
    "wof:name":"Comptoir General De Fers Et Quincaillerie Sa",
    "wof:placetype":"venue"
},
  "geometry": {"coordinates":[4.377323,46.685753],"type":"Point"}
}