{
  "type": "Feature",
  "properties": {
    "addr:full":"4, Rue de Verdun, 76410 Saint Aubin les Elbeuf Haute Normandie",
    "addr:housenumber":"4",
    "addr:postcode":"76410",
    "addr:street":"Rue De Verdun;Haute Normandie",
    "iso:country":"FR",
    "sg:address":"4, Rue de Verdun, 76410 Saint Aubin les Elbeuf",
    "sg:orig_category":"Unclassifiable Establishments",
    "sg:phone":"+33 2 35 81 92 92",
    "sg:province":"Haute Normandie",
    "wof:name":"Mcpi S.a.r.l. - Manutention Caoutchouc Pvc Industriel",
    "wof:placetype":"venue"
},
  "geometry": {"coordinates":[1.011849,49.303017],"type":"Point"}
}