{
  "type": "Feature",
  "properties": {
    "addr:full":"36, Rue Jules Vernes - Forum d'Orvault, 44700 Orvault Pays de Loire",
    "addr:housenumber":"36",
    "addr:postcode":"44700",
    "addr:street":"Rue Jules Vernes;D'Orvault",
    "iso:country":"FR",
    "sg:address":"36, Rue Jules Vernes - Forum d'Orvault, 44700 Orvault",
    "sg:orig_category":"Unclassifiable Establishments",
    "sg:phone":"+33 2 40 63 68 68",
    "sg:province":"Pays de Loire",
    "wof:name":"Generix S.a.",
    "wof:placetype":"venue"
},
  "geometry": {"coordinates":[-1.61973,47.274349],"type":"Point"}
}