{
  "type": "Feature",
  "properties": {
    "addr:full":"Z I 2 73460 Tournon Rhone-Alpes",
    "addr:housenumber":"2",
    "addr:postcode":"73460",
    "addr:street":"Z I",
    "iso:country":"FR",
    "sg:address":"Z I 2 73460 Tournon",
    "sg:orig_category":"Plaquettes",
    "sg:phone":"+33 4 79 38 58 04",
    "sg:province":"Rhone-Alpes",
    "wof:name":"Savoie Pan Sa",
    "wof:placetype":"venue"
},
  "geometry": {"coordinates":[6.306249,45.587067],"type":"Point"}
}