{
  "type": "Feature",
  "properties": {
    "addr:full":"Route De La Chapelle Trono 29120 Plomeur Plomeur Bretagne 29120",
    "addr:postcode":"29120;29120",
    "addr:street":"Route De La Chapelle Trono",
    "iso:country":"FR",
    "sg:address":"Route De La Chapelle Trono 29120 Plomeur",
    "sg:city":"Plomeur",
    "sg:classifiers":[
        {
            "category":"Farming",
            "subcategory":"Farm",
            "type":"Manufacturing & Wholesale Goods"
        }
    ],
    "sg:phone":"+33 2 98 58 65 01",
    "sg:postcode":"29120",
    "sg:province":"Bretagne",
    "sg:tags":[
        "horticulture",
        "agriculture",
        "livestock"
    ],
    "wof:name":"Florimer",
    "wof:placetype":"venue"
},
  "geometry": {"coordinates":[-4.281714,47.80986],"type":"Point"}
}