{
  "type": "Feature",
  "properties": {
    "addr:full":"B.P. 161, 71204 Le Creusot C\u00e9dex^^Av. de l'Europe - ZI Plaine des Riaux, 71200 Le Creusot Le Creusot Bourgogne 71200",
    "addr:housenumber":"b.p. 161",
    "addr:postcode":"71204;71200;71200",
    "addr:street":"Zi Plaine Des Riaux",
    "iso:country":"FR",
    "sg:address":"B.P. 161, 71204 Le Creusot C\u00e9dex^^Av. de l'Europe - ZI Plaine des Riaux, 71200 Le Creusot",
    "sg:city":"Le Creusot",
    "sg:orig_category":"Non-Classified Establishments",
    "sg:phone":"+33 3 85 77 01 00",
    "sg:postcode":"71200",
    "sg:province":"Bourgogne",
    "wof:name":"Adept T\u00e9l\u00e9com S.a.",
    "wof:placetype":"venue"
},
  "geometry": {"coordinates":[4.410755,46.807476],"type":"Point"}
}