{
  "type": "Feature",
  "properties": {
    "iso:country":"FR",
    "sg:address":"ZONE INDUSTRIELLE DE FELET 63300 THIERS",
    "sg:city":"Thiers",
    "sg:orig_category":"Finished goods - metallic Metal processing Metallurgy and Metalworking Sheets and pipes Tools",
    "sg:phone":"+33 4 73 80 21 09",
    "sg:postcode":"63300",
    "sg:province":"Auvergne",
    "wof:name":"Sepp (societe Ets Pironin Pauze)",
    "wof:placetype":"venue"
},
  "geometry": {"coordinates":[3.548272,45.855244],"type":"Point"}
}