{
  "type": "Feature",
  "properties": {
    "addr:full":"8, Rue Rambure, 60800 Auger Saint Vincent Picardie",
    "addr:housenumber":"8",
    "addr:postcode":"60800",
    "addr:street":"Rue Rambure",
    "iso:country":"FR",
    "sg:address":"8, Rue Rambure, 60800 Auger Saint Vincent",
    "sg:orig_category":"Unclassifiable Establishments",
    "sg:phone":"+33 3 44 59 00 10",
    "sg:province":"Picardie",
    "wof:name":"Win Europe S.a.",
    "wof:placetype":"venue"
},
  "geometry": {"coordinates":[2.8112,49.220356],"type":"Point"}
}