{
  "type": "Feature",
  "properties": {
    "iso:country":"FR",
    "sg:address":"R De L'Eglise 70500 Chauvirey Le Ch\u00e2tel",
    "sg:classifiers":[
        {
            "category":"Farming",
            "subcategory":"Farm & Veterinary Services",
            "type":"Manufacturing & Wholesale Goods"
        }
    ],
    "sg:phone":"+33 3 84 68 59 37",
    "sg:postcode":"70500",
    "sg:province":"Franche Comt\u00e9",
    "sg:tags":[
        "food",
        "product",
        "breeding",
        "animal",
        "related"
    ],
    "wof:name":"Sarl Dumont Et Guillaume",
    "wof:placetype":"venue"
},
  "geometry": {"coordinates":[5.810945,47.798187],"type":"Point"}
}