{
  "type": "Feature",
  "properties": {
    "iso:country":"FR",
    "sg:address":"9 Bd L\u00e9on Jouhaux; Istres",
    "sg:classifiers":[
        {
            "category":"Banks & Credit Unions",
            "subcategory":"Bank",
            "type":"Services"
        }
    ],
    "sg:phone":"+33 3342564040",
    "sg:province":"Aquitaine",
    "wof:name":"Banque Populaire, Proven\u00e7ale Corse",
    "wof:placetype":"venue"
},
  "geometry": {"coordinates":[4.986208,43.515144],"type":"Point"}
}