{
  "type": "Feature",
  "properties": {
    "addr:full":"B.P. 7, 54250 Champigneulles^^1, Impasse du Bal, 54250 Champigneulles Lorraine",
    "addr:housenumber":"7",
    "addr:postcode":"54250;54250",
    "addr:street":"B.P.;Impasse Du Bal",
    "iso:country":"FR",
    "sg:address":"B.P. 7, 54250 Champigneulles^^1, Impasse du Bal, 54250 Champigneulles",
    "sg:orig_category":"Non-Classified Establishments",
    "sg:phone":"+33 3 83 38 02 59",
    "sg:province":"Lorraine",
    "wof:name":"Imprimerie Hilt S.a.",
    "wof:placetype":"venue"
},
  "geometry": {"coordinates":[6.16533,48.73391],"type":"Point"}
}