{
  "type": "Feature",
  "properties": {
    "addr:full":"ZI les Vauvettes Vernouillet Centre 28500",
    "addr:postcode":"28500",
    "addr:street":"Zi Les Vauvettes Vernouillet",
    "iso:country":"FR",
    "sg:address":"ZI les Vauvettes",
    "sg:city":"Vernouillet",
    "sg:orig_category":"Non-Classified Establishments",
    "sg:phone":"+33 2 37 38 95 60",
    "sg:postcode":"28500",
    "sg:province":"Centre",
    "wof:name":"U.n.e.p.a.l. S.a.r.l.",
    "wof:placetype":"venue"
},
  "geometry": {"coordinates":[1.356785,48.719952],"type":"Point"}
}