{
  "type": "Feature",
  "properties": {
    "addr:full":"22, Av de Chamboland, 21700 Nuits Saint Georges Agencourt Bourgogne 21700",
    "addr:postcode":"21700;21700",
    "addr:street":"22 Av De Chamboland;Bourgogne",
    "iso:country":"FR",
    "sg:address":"22, Av de Chamboland, 21700 Nuits Saint Georges",
    "sg:city":"Agencourt",
    "sg:orig_category":"Unclassifiable Establishments",
    "sg:phone":"+33 3 80 62 60 00",
    "sg:postcode":"21700",
    "sg:province":"Bourgogne",
    "wof:name":"Filiber Imprimerie S.a.",
    "wof:placetype":"venue"
},
  "geometry": {"coordinates":[4.947515,47.131413],"type":"Point"}
}