{
  "type": "Feature",
  "properties": {
    "addr:full":"Lieu-Dit Pen Mane 56570 LOCMIQUELIC Locmiqu\u00e9lic Bretagne 56570",
    "addr:postcode":"56570;locmique\u0301lic;56570",
    "addr:street":"Lieu-Dit Pen Mane",
    "iso:country":"FR",
    "sg:address":"Lieu-Dit Pen Mane 56570 LOCMIQUELIC",
    "sg:city":"Locmiqu\u00e9lic",
    "sg:classifiers":[
        {
            "category":"Science Facility",
            "type":"Public Place"
        }
    ],
    "sg:phone":"+33 2 97 33 48 41",
    "sg:postcode":"56570",
    "sg:province":"Bretagne",
    "sg:tags":[
        "engineering",
        "naval"
    ],
    "wof:name":"Chantiers Navals Bernard Sa",
    "wof:placetype":"venue"
},
  "geometry": {"coordinates":[-3.346497,47.732319],"type":"Point"}
}