{
  "type": "Feature",
  "properties": {
    "addr:full":"Quartier Moutte - La Lebrati\u00e8re Simiane la Rotonde Provence-Alpes-C\u00f4te d'Azur 04150",
    "addr:postcode":"04150",
    "addr:street":"Quartier Moutte La Lebratie\u0300Re Simiane La Rotonde",
    "iso:country":"FR",
    "sg:address":"Quartier Moutte - La Lebrati\u00e8re",
    "sg:city":"Simiane la Rotonde",
    "sg:orig_category":"Unclassifiable Establishments",
    "sg:phone":"+33 4 92 75 93 67",
    "sg:postcode":"04150",
    "sg:province":"Provence-Alpes-C\u00f4te d'Azur",
    "wof:name":"Dauw Invest",
    "wof:placetype":"venue"
},
  "geometry": {"coordinates":[5.60995,44.03553],"type":"Point"}
}