{
  "type": "Feature",
  "properties": {
    "addr:full":"20 Rue Des Freres Lumiere 020 022 Zi Des Chanoux 93330 Neuilly Sur Marne Ile de France 93330",
    "addr:housenumber":"20;020 022",
    "addr:postcode":"93330;93330",
    "addr:street":"Rue Des Freres Lumiere;Zi Des Chanoux",
    "iso:country":"FR",
    "sg:address":"20 Rue Des Freres Lumiere 020 022 Zi Des Chanoux 93330 Neuilly Sur Marne",
    "sg:classifiers":[
        {
            "category":"Manufacturing",
            "subcategory":"Metals",
            "type":"Manufacturing & Wholesale Goods"
        }
    ],
    "sg:phone":"+33 1 43 00 43 00",
    "sg:postcode":"93330",
    "sg:province":"Ile de France",
    "sg:tags":[
        "metallurgy",
        "steel",
        "metalworking"
    ],
    "wof:name":"Etablissements Maurice Dries Et Compagnie",
    "wof:placetype":"venue"
},
  "geometry": {"coordinates":[2.52871,48.857376],"type":"Point"}
}