{
  "type": "Feature",
  "properties": {
    "addr:full":"81 R Joliot Curie 93170 Bagnolet Ile de France 93170",
    "addr:housenumber":"81",
    "addr:postcode":"93170;ile;93170",
    "addr:street":"R Joliot Curie;France",
    "iso:country":"FR",
    "sg:address":"81 R Joliot Curie 93170 Bagnolet",
    "sg:classifiers":[
        {
            "category":"Manufacturing",
            "subcategory":"Glass & Minerals",
            "type":"Manufacturing & Wholesale Goods"
        }
    ],
    "sg:phone":"+33 1 49 20 37 34",
    "sg:postcode":"93170",
    "sg:province":"Ile de France",
    "sg:tags":[
        "building",
        "material"
    ],
    "wof:name":"Macocco Ile De France Sa",
    "wof:placetype":"venue"
},
  "geometry": {"coordinates":[2.41767,48.868626],"type":"Point"}
}