{
  "type": "Feature",
  "properties": {
    "addr:full":"B.P. 32, 95270 Chaumontel C\u00e9dex^^62, Rue de la R\u00e9publique, 95270 Chaumontel Ile de France",
    "addr:postcode":"95270;95270;ile",
    "addr:street":"B.P. 32;Rue De La Re\u0301Publique",
    "iso:country":"FR",
    "sg:address":"B.P. 32, 95270 Chaumontel C\u00e9dex^^62, Rue de la R\u00e9publique, 95270 Chaumontel",
    "sg:orig_category":"Non-Classified Establishments",
    "sg:phone":"+33 1 34 71 92 80",
    "sg:province":"Ile de France",
    "wof:name":"Self Inox Aluminium S.a.",
    "wof:placetype":"venue"
},
  "geometry": {"coordinates":[2.369864,49.125587],"type":"Point"}
}