{
  "type": "Feature",
  "properties": {
    "addr:full":"213 Cours Victor Hugo 33323 B\u00e9gles Cedex B\u00e8gles Aquitaine 33130",
    "addr:housenumber":"213",
    "addr:postcode":"33323;33130",
    "addr:street":"Cours Victor Hugo",
    "iso:country":"FR",
    "sg:address":"213 Cours Victor Hugo 33323 B\u00e9gles Cedex",
    "sg:city":"B\u00e8gles",
    "sg:classifiers":[
        {
            "category":"Utilities",
            "type":"Services"
        }
    ],
    "sg:phone":"+33 5 56 49 82 00",
    "sg:postcode":"33130",
    "sg:province":"Aquitaine",
    "sg:tags":[
        "raw",
        "energy",
        "material"
    ],
    "wof:name":"Esso Rep",
    "wof:placetype":"venue"
},
  "geometry": {"coordinates":[-0.559276,44.806469],"type":"Point"}
}