{
  "type": "Feature",
  "properties": {
    "addr:full":"62 Rue Du Faubourg Saint-Honor\u00e9 Paris Ile de France 75008",
    "addr:housenumber":"62",
    "addr:postcode":"75008",
    "addr:street":"Rue Du Faubourg Saint-Honore\u0301",
    "iso:country":"FR",
    "sg:address":"62 Rue Du Faubourg Saint-Honor\u00e9",
    "sg:city":"Paris",
    "sg:classifiers":[
        {
            "category":"Banks & Credit Unions",
            "subcategory":"Financial Services",
            "type":"Services"
        }
    ],
    "sg:phone":"+33 1 53 43 14 14",
    "sg:postcode":"75008",
    "sg:province":"Ile de France",
    "sg:tags":[
        "banking",
        "finance",
        "insurance"
    ],
    "wof:name":"Paul Weiss Rifkind Wharton & Garrison",
    "wof:placetype":"venue"
},
  "geometry": {"coordinates":[2.318885,48.869823],"type":"Point"}
}