{
  "type": "Feature",
  "properties": {
    "addr:full":"B.P. 257, 51208 Epernay C\u00e9dex^^Place L\u00e9on Bourgeois, 51200 Epernay Champagne",
    "addr:housenumber":"b.p. 257",
    "addr:postcode":"51208;51200",
    "addr:street":"Le\u0301On Bourgeois",
    "iso:country":"FR",
    "sg:address":"B.P. 257, 51208 Epernay C\u00e9dex^^Place L\u00e9on Bourgeois, 51200 Epernay",
    "sg:orig_category":"Non-Classified Establishments",
    "sg:phone":"+33 3 26 51 61 48",
    "sg:province":"Champagne",
    "wof:name":"Renaudin S.a.",
    "wof:placetype":"venue"
},
  "geometry": {"coordinates":[3.95475,49.045197],"type":"Point"}
}