{
  "type": "Feature",
  "properties": {
    "iso:country":"FR",
    "sg:address":"6 Fbg De Bethl\u00e9em 58500 Clamecy",
    "sg:city":"Clamecy",
    "sg:classifiers":[
        {
            "category":"Social Services",
            "subcategory":"Retirement Home",
            "type":"Services"
        }
    ],
    "sg:phone":"+33 3 86 27 11 77",
    "sg:postcode":"58500",
    "sg:province":"Bourgogne",
    "sg:tags":[
        "ceramic",
        "wood",
        "household",
        "good",
        "furniture"
    ],
    "wof:name":"Faiences D'art Et Creations Roger Colas",
    "wof:placetype":"venue"
},
  "geometry": {"coordinates":[3.523495,47.459888],"type":"Point"}
}