{
  "type": "Feature",
  "properties": {
    "addr:full":"21 Rue Trousseau 37000 Tours Tours Centre 37000",
    "addr:housenumber":"21",
    "addr:postcode":"37000;37000",
    "addr:street":"Rue Trousseau",
    "iso:country":"FR",
    "sg:address":"21 Rue Trousseau 37000 Tours",
    "sg:city":"Tours",
    "sg:classifiers":[
        {
            "category":"Home & Garden",
            "subcategory":"Furniture",
            "type":"Retail Goods"
        }
    ],
    "sg:phone":"+33 2 47 46 03 24",
    "sg:postcode":"37000",
    "sg:province":"Centre",
    "sg:tags":[
        "professional",
        "household",
        "wood"
    ],
    "wof:name":"Societe Amenagement En Ferronnerie Et Metallerie (samferme)",
    "wof:placetype":"venue"
},
  "geometry": {"coordinates":[0.702344,47.385857],"type":"Point"}
}