{
  "type": "Feature",
  "properties": {
    "addr:full":"19bis, Rue Emile Ecuyer, 01100 Oyonnax Rhone-Alpes 01100",
    "addr:housenumber":"19bis",
    "addr:postcode":"01100;01100",
    "addr:street":"Rue Emile Ecuyer",
    "iso:country":"FR",
    "sg:address":"19bis, Rue Emile Ecuyer, 01100 Oyonnax",
    "sg:orig_category":"Unclassifiable Establishments",
    "sg:phone":"+33 4 74 77 35 95",
    "sg:postcode":"01100",
    "sg:province":"Rhone-Alpes",
    "wof:name":"Agostini-durafour S.a.r.l.",
    "wof:placetype":"venue"
},
  "geometry": {"coordinates":[5.646158,46.254566],"type":"Point"}
}