{
  "type": "Feature",
  "properties": {
    "addr:full":"B.P. 849, 49311 Cholet C\u00e9dex^^Rte de Pouzauges, 49300 Cholet Pays de Loire 49300",
    "addr:housenumber":"b.p. 849",
    "addr:postcode":"49311;49300;49300",
    "iso:country":"FR",
    "sg:address":"B.P. 849, 49311 Cholet C\u00e9dex^^Rte de Pouzauges, 49300 Cholet",
    "sg:orig_category":"Non-Classified Establishments",
    "sg:phone":"+33 1 41 65 27 33",
    "sg:postcode":"49300",
    "sg:province":"Pays de Loire",
    "wof:name":"C.d.s. S.a. - Choletaise De Distribution Et De Services",
    "wof:placetype":"venue"
},
  "geometry": {"coordinates":[-0.892689,46.99659],"type":"Point"}
}