{
  "type": "Feature",
  "properties": {
    "addr:full":"18 Rue De La Chartreuse 21200 Beaune Beaune Bourgogne 21200",
    "addr:housenumber":"18",
    "addr:postcode":"21200;21200",
    "addr:street":"Rue De La Chartreuse",
    "iso:country":"FR",
    "sg:address":"18 Rue De La Chartreuse 21200 Beaune",
    "sg:city":"Beaune",
    "sg:classifiers":[
        {
            "category":"Manufacturing",
            "subcategory":"Wood Products",
            "type":"Manufacturing & Wholesale Goods"
        }
    ],
    "sg:phone":"+33 3 80 24 66 66",
    "sg:postcode":"21200",
    "sg:province":"Bourgogne",
    "sg:tags":[
        "professional",
        "furniture"
    ],
    "wof:name":"Stand'in",
    "wof:placetype":"venue"
},
  "geometry": {"coordinates":[4.848608,47.015549],"type":"Point"}
}