{
  "type": "Feature",
  "properties": {
    "addr:full":"22 Brot ZAE Cap Nord BP 57505 Cedex 21075 Dijon Bourgogne",
    "addr:postcode":"cedex 21075",
    "addr:street":"Bp 57505",
    "iso:country":"FR",
    "sg:address":"22",
    "sg:city":"Brot ZAE Cap Nord BP 57505 Cedex 21075 Dijon",
    "sg:classifiers":[
        {
            "category":"Professional",
            "type":"Services"
        }
    ],
    "sg:phone":"+33 3 80 77 59 77",
    "sg:province":"Bourgogne",
    "sg:tags":[
        "transport",
        "road"
    ],
    "wof:name":"Regis Martelet",
    "wof:placetype":"venue"
},
  "geometry": {"coordinates":[5.04399,47.327209],"type":"Point"}
}