{
  "type": "Feature",
  "properties": {
    "addr:full":"ZAC de Haute Bedoule Actimart Sept\u00e8mes les Vallons Aquitaine 13240",
    "addr:postcode":"13240",
    "addr:street":"Zac De Haute Bedoule Actimart Septe\u0300Mes Les Vallons",
    "iso:country":"FR",
    "sg:address":"ZAC de Haute Bedoule Actimart",
    "sg:city":"Sept\u00e8mes les Vallons",
    "sg:orig_category":"Unclassifiable Establishments",
    "sg:phone":"+33 4 91 65 84 84",
    "sg:postcode":"13240",
    "sg:province":"Aquitaine",
    "wof:name":"H.t.s. S.a. - High Tech Services",
    "wof:placetype":"venue"
},
  "geometry": {"coordinates":[5.366162,43.398479],"type":"Point"}
}