{
  "type": "Feature",
  "properties": {
    "iso:country":"FR",
    "sg:address":"1 pl Aristide Briand; Villeneuve d'Ornon",
    "sg:city":"Vill\u00e9",
    "sg:classifiers":[
        {
            "category":"Banks & Credit Unions",
            "subcategory":"Bank",
            "type":"Services"
        }
    ],
    "sg:phone":"+33 3356871201",
    "sg:postcode":"67220",
    "sg:province":"Alsace",
    "wof:name":"Banque National Paris",
    "wof:placetype":"venue"
},
  "geometry": {"coordinates":[3.338643,45.852139],"type":"Point"}
}