{
  "type": "Feature",
  "properties": {
    "iso:country":"FR",
    "sg:address":"Rte De Nassandres 27800 Brionne",
    "sg:classifiers":[
        {
            "category":"Utilities",
            "type":"Services"
        }
    ],
    "sg:phone":"+33 2 32 45 72 44",
    "sg:postcode":"27800",
    "sg:province":"Haute Normandie",
    "sg:tags":[
        "raw",
        "energy",
        "material"
    ],
    "wof:name":"Sa Lesens Electricite",
    "wof:placetype":"venue"
},
  "geometry": {"coordinates":[0.740215,49.149632],"type":"Point"}
}