{
  "type": "Feature",
  "properties": {
    "addr:full":"Route D'Allanche 15170 Neussargues Moissac Joursac Auvergne 15170",
    "addr:postcode":"15170;15170",
    "addr:street":"Route D'Allanche",
    "iso:country":"FR",
    "sg:address":"Route D'Allanche 15170 Neussargues Moissac",
    "sg:city":"Joursac",
    "sg:classifiers":[
        {
            "category":"Home & Garden",
            "subcategory":"Furniture",
            "type":"Retail Goods"
        }
    ],
    "sg:phone":"+33 4 71 20 33 00",
    "sg:postcode":"15170",
    "sg:province":"Auvergne",
    "sg:tags":[
        "wood"
    ],
    "wof:name":"G B M F Sas",
    "wof:placetype":"venue"
},
  "geometry": {"coordinates":[2.97472,45.12756],"type":"Point"}
}