{
  "type": "Feature",
  "properties": {
    "addr:full":"31, Rue de la Coursme, 45300 Pithiviers Pithiviers Centre 45300",
    "addr:housenumber":"31",
    "addr:postcode":"45300;45300",
    "addr:street":"Rue De La Coursme",
    "iso:country":"FR",
    "sg:address":"31, Rue de la Coursme, 45300 Pithiviers",
    "sg:city":"Pithiviers",
    "sg:orig_category":"Unclassifiable Establishments",
    "sg:phone":"+33 2 38 30 03 97",
    "sg:postcode":"45300",
    "sg:province":"Centre",
    "wof:name":"Alliance M\u00e9dia S.a.",
    "wof:placetype":"venue"
},
  "geometry": {"coordinates":[2.21384,48.064007],"type":"Point"}
}