{
  "type": "Feature",
  "properties": {
    "addr:full":"Chemin Bolonieres 01500 Ambutrix Rhone-Alpes 01500",
    "addr:postcode":"01500;01500",
    "addr:street":"Chemin Bolonieres;Rhone-Alpes",
    "iso:country":"FR",
    "sg:address":"Chemin Bolonieres 01500 Ambutrix",
    "sg:classifiers":[
        {
            "category":"Professional",
            "type":"Services"
        }
    ],
    "sg:phone":"+33 4 74 46 83 33",
    "sg:postcode":"01500",
    "sg:province":"Rhone-Alpes",
    "sg:tags":[
        "transport",
        "road"
    ],
    "wof:name":"Transports Vachet Et Compagnie Sa",
    "wof:placetype":"venue"
},
  "geometry": {"coordinates":[5.334119,45.939957],"type":"Point"}
}