{
  "type": "Feature",
  "properties": {
    "addr:full":"7BIS Route De Seysses 31470 Fonsorbes Midi Pyr\u00e9n\u00e9es 31470",
    "addr:housenumber":"7bis",
    "addr:postcode":"31470;31470",
    "addr:street":"Route De Seysses",
    "iso:country":"FR",
    "sg:address":"7BIS Route De Seysses 31470 Fonsorbes",
    "sg:classifiers":[
        {
            "category":"Manufacturing",
            "subcategory":"Wood Products",
            "type":"Manufacturing & Wholesale Goods"
        }
    ],
    "sg:phone":"+33 5 61 91 31 44",
    "sg:postcode":"31470",
    "sg:province":"Midi Pyr\u00e9n\u00e9es",
    "sg:tags":[
        "solid",
        "furniture",
        "kitchen"
    ],
    "wof:name":"Ste Gh Sales Meubles Finitions Cuisines Sarl",
    "wof:placetype":"venue"
},
  "geometry": {"coordinates":[1.277713,43.522938],"type":"Point"}
}