{
  "type": "Feature",
  "properties": {
    "iso:country":"FR",
    "sg:address":"57 Rue Berlioz 06000 Nice",
    "sg:classifiers":[
        {
            "category":"Government",
            "subcategory":"Department Of Motor Vehicles",
            "type":"Public Place"
        }
    ],
    "sg:phone":"+33 4 93 87 40 41",
    "sg:province":"Rhone-Alpes",
    "sg:tags":[
        "equipment",
        "industrial",
        "transport",
        "motor-cars"
    ],
    "wof:name":"Ets Genevet Sarl",
    "wof:placetype":"venue"
},
  "geometry": {"coordinates":[7.259677,43.703064],"type":"Point"}
}