{
  "type": "Feature",
  "properties": {
    "addr:full":"Chem St Paul 02880 Crouy Picardie 02880",
    "addr:postcode":"02880;02880",
    "addr:street":"Chem St",
    "iso:country":"FR",
    "sg:address":"Chem St Paul 02880 Crouy",
    "sg:classifiers":[
        {
            "category":"Transit Center",
            "subcategory":"Freight",
            "type":"Transportation"
        }
    ],
    "sg:phone":"+33 3 23 59 82 00",
    "sg:postcode":"02880",
    "sg:province":"Picardie",
    "sg:tags":[
        "metallurgy",
        "pipe",
        "metalworking",
        "sheet"
    ],
    "wof:name":"Arichtechtural Systeme As",
    "wof:placetype":"venue"
},
  "geometry": {"coordinates":[3.37811,49.41016],"type":"Point"}
}