{
  "type": "Feature",
  "properties": {
    "addr:full":"Centre Commercial Malmed.; Maurepas; 78310 Ile de France 78310",
    "addr:postcode":"78310;78310",
    "addr:street":"Ile De France",
    "iso:country":"FR",
    "sg:address":"Centre Commercial Malmed.; Maurepas; 78310",
    "sg:classifiers":[
        {
            "category":"Banks & Credit Unions",
            "subcategory":"Bank",
            "type":"Services"
        }
    ],
    "sg:phone":"+33 30621025",
    "sg:postcode":"78310",
    "sg:province":"Ile de France",
    "wof:name":"Soci\u00e9t\u00e9 G\u00e9n\u00e9rale",
    "wof:placetype":"venue"
},
  "geometry": {"coordinates":[1.944855,48.761749],"type":"Point"}
}