{
  "type": "Feature",
  "properties": {
    "addr:full":"17, Rue des Cristalleries, 54000 Nancy Lorraine",
    "addr:housenumber":"17",
    "addr:postcode":"54000",
    "addr:street":"Rue Des Cristalleries",
    "iso:country":"FR",
    "sg:address":"17, Rue des Cristalleries, 54000 Nancy",
    "sg:orig_category":"Unclassifiable Establishments",
    "sg:phone":"+33 3 83 30 80 20",
    "sg:province":"Lorraine",
    "wof:name":"F.c. Daumes",
    "wof:placetype":"venue"
},
  "geometry": {"coordinates":[6.197871,48.697773],"type":"Point"}
}