{
  "type": "Feature",
  "properties": {
    "addr:full":"23, Rue la Bo\u00e9tie, 75008 Paris Ile de France",
    "addr:housenumber":"23",
    "addr:postcode":"75008",
    "addr:street":"Rue La Boe\u0301Tie",
    "iso:country":"FR",
    "sg:address":"23, Rue la Bo\u00e9tie, 75008 Paris",
    "sg:orig_category":"Non-Classified Establishments",
    "sg:phone":"+33 1 45 25 11 00",
    "sg:province":"Ile de France",
    "wof:name":"La Bo\u00e9tie Sa",
    "wof:placetype":"venue"
},
  "geometry": {"coordinates":[2.316642,48.873905],"type":"Point"}
}