{
  "type": "Feature",
  "properties": {
    "iso:country":"FR",
    "sg:address":"1 rue de la Gare 95110 Sannois",
    "sg:classifiers":[
        {
            "category":"Military Area",
            "subcategory":"Air Force Base",
            "type":"Public Place"
        }
    ],
    "sg:phone":"+33 1 30 25 77 00",
    "sg:postcode":"95110",
    "sg:province":"Ile de France",
    "sg:tags":[
        "carbon",
        "activated"
    ],
    "wof:name":"Union Des Combustibles Sa",
    "wof:placetype":"venue"
},
  "geometry": {"coordinates":[2.263243,48.969906],"type":"Point"}
}