{
  "type": "Feature",
  "properties": {
    "addr:full":"213, Rue Anatole France, 29200 Brest Brest Bretagne 29200",
    "addr:housenumber":"213",
    "addr:postcode":"29200;29200",
    "addr:street":"Rue Anatole France",
    "iso:country":"FR",
    "sg:address":"213, Rue Anatole France, 29200 Brest",
    "sg:city":"Brest",
    "sg:orig_category":"Unclassifiable Establishments",
    "sg:phone":"+33 2 98 49 42 33",
    "sg:postcode":"29200",
    "sg:province":"Bretagne",
    "wof:name":"Cr\u00e9pins Distributions S.a.r.l.",
    "wof:placetype":"venue"
},
  "geometry": {"coordinates":[-4.515112,48.382652],"type":"Point"}
}