{
  "type": "Feature",
  "properties": {
    "addr:full":"1, Rue Les Paquis, 57590 Donjeux Lorraine",
    "addr:housenumber":"1",
    "addr:postcode":"57590",
    "addr:street":"Rue Les Paquis",
    "iso:country":"FR",
    "sg:address":"1, Rue Les Paquis, 57590 Donjeux",
    "sg:orig_category":"Unclassifiable Establishments",
    "sg:phone":"+33 3 87 01 38 04",
    "sg:province":"Lorraine",
    "wof:name":"T.d.n. S.a.r.l. - Technique Distribution N\u00e9goce",
    "wof:placetype":"venue"
},
  "geometry": {"coordinates":[6.402274,48.880203],"type":"Point"}
}