{
  "type": "Feature",
  "properties": {
    "addr:full":"76 R Mar\u00e9chal De Lattre De Tassigny 79380 La For\u00eat Sur S\u00e8vre Poitou-Charentes 79380",
    "addr:housenumber":"76",
    "addr:postcode":"79380;79380",
    "addr:street":"R Mare\u0301Chal De Lattre De Tassigny;Fore\u0302T;Se\u0300Vre",
    "iso:country":"FR",
    "sg:address":"76 R Mar\u00e9chal De Lattre De Tassigny 79380 La For\u00eat Sur S\u00e8vre",
    "sg:classifiers":[
        {
            "category":"Shopping",
            "subcategory":"Clothing, Apparel, & Fashions",
            "type":"Retail Goods"
        }
    ],
    "sg:phone":"+33 5 49 80 86 11",
    "sg:postcode":"79380",
    "sg:province":"Poitou-Charentes",
    "sg:tags":[
        "textile",
        "clothing",
        "clothes"
    ],
    "wof:name":"Bocage Confection Sa",
    "wof:placetype":"venue"
},
  "geometry": {"coordinates":[-0.651124,46.766796],"type":"Point"}
}