{
  "type": "Feature",
  "properties": {
    "iso:country":"FR",
    "sg:address":"Zi Euro Val De Loire 41330 Foss\u00e9",
    "sg:city":"Foss\u00e9",
    "sg:classifiers":[
        {
            "category":"Banks & Credit Unions",
            "subcategory":"Investment Brokerage",
            "type":"Services"
        }
    ],
    "sg:phone":"+33 2 54 50 44 44",
    "sg:postcode":"41330",
    "sg:province":"Centre",
    "sg:tags":[
        "-",
        "transport",
        "related"
    ],
    "wof:name":"Calderson 41 Express Agence De Blois",
    "wof:placetype":"venue"
},
  "geometry": {"coordinates":[1.285515,47.632736],"type":"Point"}
}