{
  "type": "Feature",
  "properties": {
    "addr:full":"372, Av. Jean Guiton, 17000 La Rochelle Poitou-Charentes",
    "addr:postcode":"17000",
    "addr:street":"372 Av. Jean Guiton",
    "iso:country":"FR",
    "sg:address":"372, Av. Jean Guiton, 17000 La Rochelle",
    "sg:orig_category":"Unclassifiable Establishments",
    "sg:phone":"+33 5 46 00 39 00",
    "sg:province":"Poitou-Charentes",
    "wof:name":"Vama",
    "wof:placetype":"venue"
},
  "geometry": {"coordinates":[-1.194827,46.160225],"type":"Point"}
}