{
  "type": "Feature",
  "properties": {
    "iso:country":"FR",
    "sg:address":"19, Rue Petits Ruisseaux - ZA des Godets, 91370 Verri\u00e8res le Buisson",
    "sg:orig_category":"Unclassifiable Establishments",
    "sg:phone":"+33 1 64 47 16 16",
    "sg:province":"Ile de France",
    "wof:name":"Dipan France S.a.",
    "wof:placetype":"venue"
},
  "geometry": {"coordinates":[2.266935,48.746086],"type":"Point"}
}