{
  "type": "Feature",
  "properties": {
    "iso:country":"FR",
    "sg:address":"15 Rue Paul Lang 68560 Hirsingue",
    "sg:city":"Hirsingue",
    "sg:classifiers":[
        {
            "category":"Shopping",
            "subcategory":"Crafts & Fabrics",
            "type":"Retail Goods"
        }
    ],
    "sg:phone":"+33 3 89 07 52 07",
    "sg:postcode":"68560",
    "sg:province":"Alsace",
    "sg:tags":[
        "textile",
        "clothing"
    ],
    "wof:name":"Lang Textiles (emmanuel)",
    "wof:placetype":"venue"
},
  "geometry": {"coordinates":[7.250403,47.589638],"type":"Point"}
}