{
  "type": "Feature",
  "properties": {
    "addr:full":"375 Rue Champ Moyen 54710 Fl\u00e9ville Devant Nancy Lorraine",
    "addr:housenumber":"375",
    "addr:postcode":"54710",
    "addr:street":"Rue Champ Moyen",
    "iso:country":"FR",
    "sg:address":"375 Rue Champ Moyen 54710 Fl\u00e9ville Devant Nancy",
    "sg:classifiers":[
        {
            "category":"Professional",
            "type":"Services"
        }
    ],
    "sg:phone":"+33 3 83 25 86 61",
    "sg:province":"Lorraine",
    "sg:tags":[
        "transport",
        "road"
    ],
    "wof:name":"Iml2 Sarl",
    "wof:placetype":"venue"
},
  "geometry": {"coordinates":[6.209206,48.616947],"type":"Point"}
}