{
  "type": "Feature",
  "properties": {
    "iso:country":"FR",
    "sg:address":"51, Rue Chiers, 92100 Boulogne Billancourt",
    "sg:orig_category":"Non-Classified Establishments",
    "sg:phone":"+33 1 46 08 20 27",
    "sg:postcode":"92100",
    "sg:province":"Ile de France",
    "wof:name":"Artisan St\u00e9phanois Nettoyage R\u00e9unis S.a.r.l.",
    "wof:placetype":"venue"
},
  "geometry": {"coordinates":[2.24102,48.835155],"type":"Point"}
}