{
  "type": "Feature",
  "properties": {
    "addr:full":"Zi De L Appentiere 49280 Mazieres En Mauges Pays de Loire 49280",
    "addr:postcode":"49280;49280",
    "addr:street":"Zi De L Appentiere;Mauges",
    "iso:country":"FR",
    "sg:address":"Zi De L Appentiere 49280 Mazieres En Mauges",
    "sg:classifiers":[
        {
            "category":"Building & Trades",
            "subcategory":"Construction",
            "type":"Services"
        }
    ],
    "sg:phone":"+33 2 41 58 57 13",
    "sg:postcode":"49280",
    "sg:province":"Pays de Loire",
    "sg:tags":[
        "work",
        "public"
    ],
    "wof:name":"Avance Technologique Choletaise (atech)",
    "wof:placetype":"venue"
},
  "geometry": {"coordinates":[-0.816274,47.046146],"type":"Point"}
}