{
  "type": "Feature",
  "properties": {
    "iso:country":"FR",
    "sg:address":"r Kennedy; Miramas",
    "sg:classifiers":[
        {
            "category":"Banks & Credit Unions",
            "subcategory":"Bank",
            "type":"Services"
        }
    ],
    "sg:phone":"+33 3390580031",
    "sg:province":"Picardie",
    "wof:name":"Banque Chaix",
    "wof:placetype":"venue"
},
  "geometry": {"coordinates":[5.00306,43.584637],"type":"Point"}
}