{
  "type": "Feature",
  "properties": {
    "addr:full":"13, Rue Georges Cl\u00e9menceau, 69500 Bron Rhone-Alpes 69500",
    "addr:housenumber":"13",
    "addr:postcode":"69500;69500",
    "addr:street":"Rue Georges Cle\u0301Menceau",
    "iso:country":"FR",
    "sg:address":"13, Rue Georges Cl\u00e9menceau, 69500 Bron",
    "sg:orig_category":"Unclassifiable Establishments",
    "sg:phone":"+33 4 78 54 01 22",
    "sg:postcode":"69500",
    "sg:province":"Rhone-Alpes",
    "wof:name":"Rh\u00f4ne Alpes Photogravure S.a.r.l.",
    "wof:placetype":"venue"
},
  "geometry": {"coordinates":[4.899983,45.751457],"type":"Point"}
}