{
  "type": "Feature",
  "properties": {
    "iso:country":"FR",
    "sg:address":"Rte D'Avignon BP 140 84304 Cavaillon",
    "sg:classifiers":[
        {
            "category":"Professional",
            "type":"Services"
        }
    ],
    "sg:phone":"+33 4 90 78 45 00",
    "sg:province":"Provence-Alpes-C\u00f4te d'Azur",
    "sg:tags":[
        "transport",
        "road"
    ],
    "wof:name":"Transports Chabas Sa",
    "wof:placetype":"venue"
},
  "geometry": {"coordinates":[5.03407,43.829971],"type":"Point"}
}