{
  "type": "Feature",
  "properties": {
    "iso:country":"FR",
    "sg:address":"1 Rue Des Jacobins 27620 Ste Genevieve Les Gasny",
    "sg:classifiers":[
        {
            "category":"Shopping",
            "subcategory":"Clothing, Apparel, & Fashions",
            "type":"Retail Goods"
        }
    ],
    "sg:phone":"+33 2 32 52 66 24",
    "sg:postcode":"27620",
    "sg:province":"Haute Normandie",
    "sg:tags":[
        "textile",
        "clothing",
        "clothes"
    ],
    "wof:name":"Beny D Creations",
    "wof:placetype":"venue"
},
  "geometry": {"coordinates":[1.577729,49.07951],"type":"Point"}
}