{
  "type": "Feature",
  "properties": {
    "addr:full":"route de Boutoir 89210 Brienon Sur Armancon Bellechaume Bourgogne 89210",
    "addr:postcode":"89210;89210",
    "addr:street":"Route De Boutoir",
    "iso:country":"FR",
    "sg:address":"route de Boutoir 89210 Brienon Sur Armancon",
    "sg:city":"Bellechaume",
    "sg:classifiers":[
        {
            "category":"Manufacturing",
            "subcategory":"Lumber",
            "type":"Manufacturing & Wholesale Goods"
        }
    ],
    "sg:phone":"+33 3 86 56 10 60",
    "sg:postcode":"89210",
    "sg:province":"Bourgogne",
    "sg:tags":[
        "hardwood",
        "sawmill"
    ],
    "wof:name":"Duffard Sa",
    "wof:placetype":"venue"
},
  "geometry": {"coordinates":[3.624553,47.983913],"type":"Point"}
}