{
  "type": "Feature",
  "properties": {
    "addr:full":"ZI de Conneuil Montlouis sur Loire Centre 37270",
    "addr:postcode":"37270",
    "addr:street":"Zi De Conneuil",
    "iso:country":"FR",
    "sg:address":"ZI de Conneuil",
    "sg:city":"Montlouis sur Loire",
    "sg:orig_category":"Non-Classified Establishments",
    "sg:phone":"+33 2 47 50 92 92",
    "sg:postcode":"37270",
    "sg:province":"Centre",
    "wof:name":"C.e.a.l S.a.r.l. - Centre D'etudes D'animation Lumineuse",
    "wof:placetype":"venue"
},
  "geometry": {"coordinates":[0.827175,47.388725],"type":"Point"}
}