{
  "type": "Feature",
  "properties": {
    "iso:country":"FR",
    "sg:address":"951, Rue Aristide Briand, 76650 Petit Couronne",
    "sg:orig_category":"Unclassifiable Establishments",
    "sg:phone":"+33 2 35 68 02 44",
    "sg:province":"Haute Normandie",
    "wof:name":"A L'organisation S.a.r.l.",
    "wof:placetype":"venue"
},
  "geometry": {"coordinates":[1.023328,49.390171],"type":"Point"}
}