{
  "type": "Feature",
  "properties": {
    "iso:country":"FR",
    "sg:address":"Rue Denis Papin - ZA Mittelfeld",
    "sg:city":"Schiltigheim",
    "sg:orig_category":"Unclassifiable Establishments",
    "sg:phone":"+33 3 88 62 22 46",
    "sg:postcode":"67300",
    "sg:province":"Alsace",
    "wof:name":"Lebas System S.a.",
    "wof:placetype":"venue"
},
  "geometry": {"coordinates":[7.748565,48.605949],"type":"Point"}
}