{
  "type": "Feature",
  "properties": {
    "iso:country":"FR",
    "sg:address":"99 Rte De La Charit\u00e9 18000 Bourges",
    "sg:city":"Bourges",
    "sg:classifiers":[
        {
            "category":"Autos & Motor Vehicles",
            "subcategory":"Automobile Sales",
            "type":"Retail Goods"
        }
    ],
    "sg:phone":"+33 2 48 70 78 14",
    "sg:postcode":"18000",
    "sg:province":"Centre",
    "sg:tags":[
        "equipment",
        "motor-cars",
        "transport"
    ],
    "wof:name":"Sa Laudat",
    "wof:placetype":"venue"
},
  "geometry": {"coordinates":[2.416009,47.094658],"type":"Point"}
}