{
  "type": "Feature",
  "properties": {
    "iso:country":"FR",
    "sg:address":"58270 Cizely",
    "sg:city":"Cizely",
    "sg:classifiers":[
        {
            "category":"Manufacturing",
            "subcategory":"Metals",
            "type":"Manufacturing & Wholesale Goods"
        }
    ],
    "sg:phone":"+33 3 86 58 39 90",
    "sg:postcode":"58270",
    "sg:province":"Bourgogne",
    "sg:tags":[
        "metallurgy",
        "metalworking",
        "processing"
    ],
    "wof:name":"Ste D'applications Electriques Et Mecaniques (sapem)",
    "wof:placetype":"venue"
},
  "geometry": {"coordinates":[3.485399,46.989323],"type":"Point"}
}