{
  "type": "Feature",
  "properties": {
    "iso:country":"FR",
    "sg:address":"380 Rue L\u00e9on Gambetta 59000 Lille",
    "sg:classifiers":[
        {
            "category":"Farming",
            "subcategory":"Crops",
            "type":"Manufacturing & Wholesale Goods"
        }
    ],
    "sg:phone":"+33 3 20 30 79 73",
    "sg:postcode":"59000",
    "sg:province":"Nord Pas-de-Calais",
    "sg:tags":[
        "vegetable",
        "fruit",
        "agriculture",
        "livestock"
    ],
    "wof:name":"Parent Primeur",
    "wof:placetype":"venue"
},
  "geometry": {"coordinates":[3.047903,50.626778],"type":"Point"}
}