{
  "type": "Feature",
  "properties": {
    "iso:country":"FR",
    "sg:address":"ZAC La Croix Rouge - La Gaudi\u00e8re",
    "sg:city":"Ch\u00e2teaubourg",
    "sg:orig_category":"Non-Classified Establishments",
    "sg:phone":"+33 2 99 62 33 16",
    "sg:postcode":"35220",
    "sg:province":"Bretagne",
    "wof:name":"Jubert S.a.r.l.",
    "wof:placetype":"venue"
},
  "geometry": {"coordinates":[-1.392459,48.111],"type":"Point"}
}