{
  "type": "Feature",
  "properties": {
    "addr:full":"Rue James Joule 14120 Mondeville Mondeville Basse Normandie 14120",
    "addr:postcode":"14120;14120",
    "addr:street":"Rue James Joule;Basse",
    "iso:country":"FR",
    "sg:address":"Rue James Joule 14120 Mondeville",
    "sg:city":"Mondeville",
    "sg:classifiers":[
        {
            "category":"Manufacturing",
            "subcategory":"Metals",
            "type":"Manufacturing & Wholesale Goods"
        }
    ],
    "sg:phone":"+33 2 31 83 41 16",
    "sg:postcode":"14120",
    "sg:province":"Basse Normandie",
    "sg:tags":[
        "pipe",
        "sheet",
        "-",
        "metalworking",
        "metallic",
        "metallurgy",
        "finished"
    ],
    "wof:name":"Normandie Tuyauterie Sas",
    "wof:placetype":"venue"
},
  "geometry": {"coordinates":[-0.321222,49.166992],"type":"Point"}
}