{
  "type": "Feature",
  "properties": {
    "iso:country":"FR",
    "sg:address":"Biopole Clermont Limagne",
    "sg:city":"Saint Beauzire",
    "sg:orig_category":"Unclassifiable Establishments",
    "sg:phone":"+33 4 73 33 99 00",
    "sg:postcode":"63360",
    "sg:province":"Auvergne",
    "wof:name":"Greentech S.a.",
    "wof:placetype":"venue"
},
  "geometry": {"coordinates":[3.168779,45.848587],"type":"Point"}
}