{
  "type": "Feature",
  "properties": {
    "addr:full":"19, Rue de Mommenheim, 67670 Wittersheim Wittersheim Alsace 67670",
    "addr:housenumber":"19",
    "addr:postcode":"67670;67670",
    "addr:street":"Rue De Mommenheim",
    "iso:country":"FR",
    "sg:address":"19, Rue de Mommenheim, 67670 Wittersheim",
    "sg:city":"Wittersheim",
    "sg:orig_category":"Unclassifiable Establishments",
    "sg:phone":"+33 3 88 51 54 68",
    "sg:postcode":"67670",
    "sg:province":"Alsace",
    "wof:name":"B\u00f6rger France S.a.r.l.",
    "wof:placetype":"venue"
},
  "geometry": {"coordinates":[7.646921,48.770096],"type":"Point"}
}