{
  "type": "Feature",
  "properties": {
    "addr:full":"ZA Les Bouvreuils Saint Hilaire des Landes Bretagne 35140",
    "addr:postcode":"35140",
    "addr:street":"Za Les;Saint",
    "iso:country":"FR",
    "sg:address":"ZA Les Bouvreuils",
    "sg:city":"Saint Hilaire des Landes",
    "sg:orig_category":"Unclassifiable Establishments",
    "sg:phone":"+33 2 99 98 89 49",
    "sg:postcode":"35140",
    "sg:province":"Bretagne",
    "wof:name":"Soci\u00e9t\u00e9 D'exploitation Etablissements Dehaies S.a.r.l.",
    "wof:placetype":"venue"
},
  "geometry": {"coordinates":[-1.356884,48.351265],"type":"Point"}
}