{
  "type": "Feature",
  "properties": {
    "addr:full":"1176 avenue de Montpellier le Verme 30380 St Christol Les Ales Languedoc-Roussillon",
    "addr:housenumber":"1176",
    "addr:postcode":"30380",
    "addr:street":"Avenue De Montpellier Le Verme",
    "iso:country":"FR",
    "sg:address":"1176 avenue de Montpellier le Verme 30380 St Christol Les Ales",
    "sg:classifiers":[
        {
            "category":"Restaurant",
            "type":"Food & Drink"
        }
    ],
    "sg:phone":"+33 4 66 60 83 84",
    "sg:province":"Languedoc-Roussillon",
    "sg:tags":[
        "pasta"
    ],
    "wof:name":"St\u00e9 Exploit Des Huiles Benoit Sarl",
    "wof:placetype":"venue"
},
  "geometry": {"coordinates":[4.077045,44.084621],"type":"Point"}
}