{
  "type": "Feature",
  "properties": {
    "addr:full":"2, Rte de Dieppe, 76230 Quincampoix Haute Normandie",
    "addr:housenumber":"2",
    "addr:postcode":"76230",
    "addr:street":"Rte De Dieppe;Haute Normandie",
    "iso:country":"FR",
    "sg:address":"2, Rte de Dieppe, 76230 Quincampoix",
    "sg:orig_category":"Unclassifiable Establishments",
    "sg:phone":"+33 2 35 33 77 48",
    "sg:province":"Haute Normandie",
    "wof:name":"Norma Frais S.a.",
    "wof:placetype":"venue"
},
  "geometry": {"coordinates":[1.142708,49.514675],"type":"Point"}
}