{
  "type": "Feature",
  "properties": {
    "addr:full":"Basleville 16140 Villejesus Poitou-Charentes 16140",
    "addr:postcode":"16140;16140",
    "addr:street":"Basleville;Villejesus",
    "iso:country":"FR",
    "sg:address":"Basleville 16140 Villejesus",
    "sg:classifiers":[
        {
            "category":"Farming",
            "subcategory":"Livestock Farm",
            "type":"Manufacturing & Wholesale Goods"
        }
    ],
    "sg:phone":"+33 5 45 21 31 27",
    "sg:postcode":"16140",
    "sg:province":"Poitou-Charentes",
    "sg:tags":[
        "grain",
        "agriculture",
        "cereal"
    ],
    "wof:name":"Humal",
    "wof:placetype":"venue"
},
  "geometry": {"coordinates":[0.059531,45.830051],"type":"Point"}
}