{
  "type": "Feature",
  "properties": {
    "addr:full":"43 Rue Serpenoise 57000 Metz Lorraine 57000",
    "addr:housenumber":"43",
    "addr:postcode":"57000;57000",
    "addr:street":"Rue Serpenoise",
    "iso:country":"FR",
    "sg:address":"43 Rue Serpenoise 57000 Metz",
    "sg:classifiers":[
        {
            "category":"Professional",
            "subcategory":"Advertising",
            "type":"Services"
        }
    ],
    "sg:phone":"+33 3 87 75 18 70",
    "sg:postcode":"57000",
    "sg:province":"Lorraine",
    "sg:tags":[
        "information",
        "medium",
        "communication"
    ],
    "wof:name":"Photo Palace Sarl",
    "wof:placetype":"venue"
},
  "geometry": {"coordinates":[6.174719,49.116627],"type":"Point"}
}