{
  "type": "Feature",
  "properties": {
    "addr:full":"22, Chemin d'Empir\u00e9, 49130 Sainte Gemmes sur Loire Pays de Loire",
    "addr:housenumber":"22",
    "addr:postcode":"49130",
    "addr:street":"Chemin D'Empire \u0301;Gemmes;Loire",
    "iso:country":"FR",
    "sg:address":"22, Chemin d'Empir\u00e9, 49130 Sainte Gemmes sur Loire",
    "sg:orig_category":"Non-Classified Establishments",
    "sg:phone":"+33 2 41 66 04 60",
    "sg:province":"Pays de Loire",
    "wof:name":"P\u00e9pini\u00e8res Delaunay F. E.u.r.l.",
    "wof:placetype":"venue"
},
  "geometry": {"coordinates":[-0.58274,47.420322],"type":"Point"}
}