{
  "type": "Feature",
  "properties": {
    "addr:full":"Rue Levassor 78130 Les Mureaux Ile de France 78130",
    "addr:postcode":"78130;78130",
    "addr:street":"Rue Levassor",
    "iso:country":"FR",
    "sg:address":"Rue Levassor 78130 Les Mureaux",
    "sg:classifiers":[
        {
            "category":"Manufacturing",
            "subcategory":"Textiles",
            "type":"Manufacturing & Wholesale Goods"
        }
    ],
    "sg:phone":"+33 1 34 92 93 94",
    "sg:postcode":"78130",
    "sg:province":"Ile de France",
    "sg:tags":[
        "linen",
        "clothing",
        "fabric"
    ],
    "wof:name":"Paris Centre Sarl",
    "wof:placetype":"venue"
},
  "geometry": {"coordinates":[1.892745,48.98201],"type":"Point"}
}