{
  "type": "Feature",
  "properties": {
    "iso:country":"FR",
    "sg:address":"7 Grande Rue 25560 Frasne",
    "sg:classifiers":[
        {
            "category":"Home & Garden",
            "subcategory":"Furniture",
            "type":"Retail Goods"
        }
    ],
    "sg:phone":"+33 3 81 49 81 58",
    "sg:province":"Franche Comt\u00e9",
    "sg:tags":[
        "wood"
    ],
    "wof:name":"Spps",
    "wof:placetype":"venue"
},
  "geometry": {"coordinates":[6.15162,46.851952],"type":"Point"}
}