{
  "type": "Feature",
  "properties": {
    "iso:country":"FR",
    "sg:address":"68 Rue Du Faubourg Saint-Honor\u00e9",
    "sg:city":"Paris",
    "sg:classifiers":[
        {
            "category":"Banks & Credit Unions",
            "subcategory":"Financial Services",
            "type":"Services"
        }
    ],
    "sg:phone":"+33 1 55 27 11 00",
    "sg:postcode":"75008",
    "sg:province":"Ile de France",
    "sg:tags":[
        "banking",
        "finance",
        "insurance"
    ],
    "wof:name":"Skadeen Arps Slate Meagher Et Flom Llp",
    "wof:placetype":"venue"
},
  "geometry": {"coordinates":[2.318437,48.870064],"type":"Point"}
}