{
  "type": "Feature",
  "properties": {
    "addr:full":"Rte d'Epaignes Beuzeville Haute Normandie 27210",
    "addr:postcode":"27210",
    "addr:street":"Rte D'Epaignes;Haute Normandie",
    "iso:country":"FR",
    "sg:address":"Rte d'Epaignes",
    "sg:city":"Beuzeville",
    "sg:orig_category":"Unclassifiable Establishments",
    "sg:phone":"+33 2 32 57 76 96",
    "sg:postcode":"27210",
    "sg:province":"Haute Normandie",
    "wof:name":"Bric Auto S.a.r.l.",
    "wof:placetype":"venue"
},
  "geometry": {"coordinates":[0.427659,49.590885],"type":"Point"}
}