{
  "type": "Feature",
  "properties": {
    "iso:country":"FR",
    "sg:address":"25, Impase Maillol, 78160 Marly le Roi",
    "sg:orig_category":"Non-Classified Establishments",
    "sg:phone":"+33 1 39 58 20 18",
    "sg:province":"Ile de France",
    "wof:name":"Octant Diffusion S.a.r.l",
    "wof:placetype":"venue"
},
  "geometry": {"coordinates":[2.100093,48.876717],"type":"Point"}
}