{
  "type": "Feature",
  "properties": {
    "addr:full":"Av. Gaston Phoebus - Bois du Marmajou Lescar Aquitaine 64230",
    "addr:postcode":"64230",
    "addr:street":"Av. Gaston Phoebus Bois Du Marmajou",
    "iso:country":"FR",
    "sg:address":"Av. Gaston Phoebus - Bois du Marmajou",
    "sg:city":"Lescar",
    "sg:orig_category":"Non-Classified Establishments",
    "sg:phone":"+33 5 59 92 38 38",
    "sg:postcode":"64230",
    "sg:province":"Aquitaine",
    "wof:name":"Euroma S.a.r.l.",
    "wof:placetype":"venue"
},
  "geometry": {"coordinates":[-0.469177,43.319443],"type":"Point"}
}