{
  "type": "Feature",
  "properties": {
    "iso:country":"FR",
    "sg:address":"ZI de Drou\u00e9 sur Drouette",
    "sg:city":"\u00c9pernon",
    "sg:orig_category":"Unclassifiable Establishments",
    "sg:phone":"+33 2 37 18 02 80",
    "sg:postcode":"28230",
    "sg:province":"Centre",
    "wof:name":"U.p.m. Pack S.a.",
    "wof:placetype":"venue"
},
  "geometry": {"coordinates":[1.67713,48.609051],"type":"Point"}
}