{
  "type": "Feature",
  "properties": {
    "iso:country":"FR",
    "sg:address":"23 Zi Du Teinchurier 19100 Brive",
    "sg:classifiers":[
        {
            "category":"Food & Beverages",
            "subcategory":"Meat & Fish",
            "type":"Retail Goods"
        }
    ],
    "sg:phone":"+33 5 55 86 42 86",
    "sg:postcode":"19100",
    "sg:province":"Limousin",
    "sg:tags":[
        "preserve",
        "cooked",
        "product",
        "related"
    ],
    "wof:name":"Sa Rougie Bizac International",
    "wof:placetype":"venue"
},
  "geometry": {"coordinates":[1.53587,45.157036],"type":"Point"}
}