{
  "type": "Feature",
  "properties": {
    "addr:full":"86, Rue du G\u00e9n\u00e9ral Ebou\u00e9, 92136 Issy les Moulineaux C\u00e9dex Centre",
    "addr:housenumber":"86",
    "addr:postcode":"92136",
    "addr:street":"Rue Du Ge\u0301Ne\u0301Ral Eboue\u0301",
    "iso:country":"FR",
    "sg:address":"86, Rue du G\u00e9n\u00e9ral Ebou\u00e9, 92136 Issy les Moulineaux C\u00e9dex",
    "sg:orig_category":"Non-Classified Establishments",
    "sg:phone":"+33 1 45 29 92 00",
    "sg:province":"Centre",
    "wof:name":"R.n.p. S.a. - R\u00e9seau National De Promotion",
    "wof:placetype":"venue"
},
  "geometry": {"coordinates":[2.251248,48.821148],"type":"Point"}
}