{
  "type": "Feature",
  "properties": {
    "addr:full":"3 Rue Des Archives 29200 Brest Brest Bretagne 29200",
    "addr:housenumber":"3",
    "addr:postcode":"29200;29200",
    "addr:street":"Rue Des Archives",
    "iso:country":"FR",
    "sg:address":"3 Rue Des Archives 29200 Brest",
    "sg:city":"Brest",
    "sg:classifiers":[
        {
            "category":"Professional",
            "subcategory":"Business Services",
            "type":"Services"
        }
    ],
    "sg:phone":"+33 2 98 01 60 03",
    "sg:postcode":"29200",
    "sg:province":"Bretagne",
    "sg:tags":[
        "training",
        "advice"
    ],
    "wof:name":"Universite Bretagne Occidentale",
    "wof:placetype":"venue"
},
  "geometry": {"coordinates":[-4.508865,48.398277],"type":"Point"}
}