{
  "type": "Feature",
  "properties": {
    "iso:country":"FR",
    "sg:address":"Ld Keryann 29190 Gou\u00e9zec",
    "sg:city":"Gou\u00e9zec",
    "sg:classifiers":[
        {
            "category":"Professional",
            "type":"Services"
        }
    ],
    "sg:phone":"+33 2 98 73 30 57",
    "sg:postcode":"29190",
    "sg:province":"Bretagne",
    "sg:tags":[
        "transport",
        "road"
    ],
    "wof:name":"Societe Des Transports Adam De Villiers",
    "wof:placetype":"venue"
},
  "geometry": {"coordinates":[-3.981613,48.170166],"type":"Point"}
}