{
  "type": "Feature",
  "properties": {
    "addr:full":"34 Rue Guynemer 92130 Issy Les Moulineaux Ile de France",
    "addr:housenumber":"34",
    "addr:postcode":"92130",
    "addr:street":"Rue Guynemer",
    "iso:country":"FR",
    "sg:address":"34 Rue Guynemer 92130 Issy Les Moulineaux",
    "sg:classifiers":[
        {
            "category":"Manufacturing",
            "subcategory":"Printing",
            "type":"Manufacturing & Wholesale Goods"
        }
    ],
    "sg:phone":"+33 1 46 48 20 00",
    "sg:province":"Ile de France",
    "sg:tags":[
        "publishing"
    ],
    "wof:name":"Gemplus (gem)",
    "wof:placetype":"venue"
},
  "geometry": {"coordinates":[2.277123,48.830063],"type":"Point"}
}