{
  "type": "Feature",
  "properties": {
    "addr:full":"Zi Portes du Nord Libercourt Nord Pas-de-Calais 62820",
    "addr:postcode":"62820",
    "iso:country":"FR",
    "sg:address":"Zi Portes du Nord",
    "sg:city":"Libercourt",
    "sg:orig_category":"Non-Classified Establishments",
    "sg:phone":"+33 3 21 79 76 00",
    "sg:postcode":"62820",
    "sg:province":"Nord Pas-de-Calais",
    "wof:name":"Ducros Euro Express S.a.",
    "wof:placetype":"venue"
},
  "geometry": {"coordinates":[3.009885,50.480518],"type":"Point"}
}