{
  "type": "Feature",
  "properties": {
    "iso:country":"FR",
    "sg:address":"59, Rue Raymond Poincar\u00e9, 54000 Nancy",
    "sg:orig_category":"Unclassifiable Establishments",
    "sg:phone":"+33 3 83 41 37 65",
    "sg:province":"Lorraine",
    "wof:name":"Microfun S.a.r.l.",
    "wof:placetype":"venue"
},
  "geometry": {"coordinates":[6.169354,48.689072],"type":"Point"}
}