{
  "type": "Feature",
  "properties": {
    "iso:country":"FR",
    "sg:address":"85, Bd Gustave Flaubert, 63000 Clermont Ferrand",
    "sg:city":"Clermont-Ferrand",
    "sg:orig_category":"Unclassifiable Establishments",
    "sg:phone":"+33 4 73 98 39 70",
    "sg:postcode":"63000",
    "sg:province":"Auvergne",
    "wof:name":"Anconetti",
    "wof:placetype":"venue"
},
  "geometry": {"coordinates":[3.125445,45.766533],"type":"Point"}
}