{
  "type": "Feature",
  "properties": {
    "addr:full":"Rue Yves Prigent - ZA de la Boissi\u00e8re Morlaix Bretagne 29600",
    "addr:postcode":"29600",
    "addr:street":"Rue Yves Prigent Za De La Boissie\u0300Re;Bretagne",
    "iso:country":"FR",
    "sg:address":"Rue Yves Prigent - ZA de la Boissi\u00e8re",
    "sg:city":"Morlaix",
    "sg:orig_category":"Unclassifiable Establishments",
    "sg:phone":"+33 2 98 62 11 00",
    "sg:postcode":"29600",
    "sg:province":"Bretagne",
    "wof:name":"Espas",
    "wof:placetype":"venue"
},
  "geometry": {"coordinates":[-3.826259,48.577026],"type":"Point"}
}