{
  "type": "Feature",
  "properties": {
    "addr:full":"69125 Lyon Saint-Exup\u00e9ry A\u00e9roport Rhone-Alpes",
    "addr:postcode":"69125",
    "iso:country":"FR",
    "sg:address":"69125 Lyon Saint-Exup\u00e9ry A\u00e9roport",
    "sg:classifiers":[
        {
            "category":"Professional",
            "subcategory":"Business Services",
            "type":"Services"
        }
    ],
    "sg:phone":"+33 4 72 22 72 21",
    "sg:province":"Rhone-Alpes",
    "sg:tags":[
        "travel",
        "-",
        "transport",
        "air"
    ],
    "wof:name":"Aeroport International De Lyon",
    "wof:placetype":"venue"
},
  "geometry": {"coordinates":[5.08245,45.71981],"type":"Point"}
}