{
  "type": "Feature",
  "properties": {
    "addr:full":"69 rue de la Belle Etoile 95948 Roissy Charles De Gaulle Picardie",
    "addr:housenumber":"69",
    "addr:postcode":"95948",
    "addr:street":"Rue De La Belle Etoile",
    "iso:country":"FR",
    "sg:address":"69 rue de la Belle Etoile 95948 Roissy Charles De Gaulle",
    "sg:classifiers":[
        {
            "category":"Professional",
            "subcategory":"Management & Consulting",
            "type":"Services"
        }
    ],
    "sg:phone":"+33 1 49 90 53 70",
    "sg:province":"Picardie",
    "sg:tags":[
        "logistics"
    ],
    "wof:name":"Exel Freight S.a.",
    "wof:placetype":"venue"
},
  "geometry": {"coordinates":[0.15853,47.900101],"type":"Point"}
}