{
  "type": "Feature",
  "properties": {
    "iso:country":"FR",
    "sg:address":"6, Bd de la Muette - Z.A.C. de la Muette, 95140 Garges l\u00e8s Gonesse",
    "sg:orig_category":"Non-Classified Establishments",
    "sg:phone":"+33 1 34 53 67 00",
    "sg:province":"Ile de France",
    "wof:name":"P.l.t. Services S.a.r.l.",
    "wof:placetype":"venue"
},
  "geometry": {"coordinates":[2.39924,48.970955],"type":"Point"}
}