{
  "type": "Feature",
  "properties": {
    "iso:country":"FR",
    "sg:address":"4 Rue Louis Pasteur",
    "sg:city":"Des Gailletrous 41260 La Chaus\u00e9e St Victor",
    "sg:classifiers":[
        {
            "category":"Utilities",
            "subcategory":"Telephone",
            "type":"Services"
        }
    ],
    "sg:phone":"+33 2 54 57 52 52",
    "sg:province":"Centre",
    "sg:tags":[
        "telecommunication"
    ],
    "wof:name":"Mercura",
    "wof:placetype":"venue"
},
  "geometry": {"coordinates":[-121.20555899999999,38.137932],"type":"Point"}
}