{
  "type": "Feature",
  "properties": {
    "addr:full":"1, All\u00e9e Odilon Redon, 41100 Vend\u00f4me Vend\u00f4me Centre 41100",
    "addr:housenumber":"1",
    "addr:postcode":"41100;41100",
    "addr:street":"Alle\u0301E Odilon Redon",
    "iso:country":"FR",
    "sg:address":"1, All\u00e9e Odilon Redon, 41100 Vend\u00f4me",
    "sg:city":"Vend\u00f4me",
    "sg:orig_category":"Non-Classified Establishments",
    "sg:phone":"+33 2 54 77 97 80",
    "sg:postcode":"41100",
    "sg:province":"Centre",
    "wof:name":"Chonoski Jean-michel",
    "wof:placetype":"venue"
},
  "geometry": {"coordinates":[1.048484,47.815044],"type":"Point"}
}