{
  "type": "Feature",
  "properties": {
    "iso:country":"FR",
    "sg:address":"Zi Ouest 01700 St Maurice De Beynost",
    "sg:classifiers":[
        {
            "category":"Manufacturing",
            "subcategory":"Rubber & Plastics",
            "type":"Manufacturing & Wholesale Goods"
        }
    ],
    "sg:phone":"+33 4 78 55 39 29",
    "sg:province":"Rhone-Alpes",
    "sg:tags":[
        "packaging",
        "material",
        "-"
    ],
    "wof:name":"Dorlon Sa",
    "wof:placetype":"venue"
},
  "geometry": {"coordinates":[4.97759,45.829281],"type":"Point"}
}