{
  "type": "Feature",
  "properties": {
    "addr:full":"Laqueille Gare 63820 ST JULIEN PUY LAVEZE Briffons Auvergne 63820",
    "addr:postcode":"63820 st;63820",
    "addr:street":"Gare;Briffons",
    "iso:country":"FR",
    "sg:address":"Laqueille Gare 63820 ST JULIEN PUY LAVEZE",
    "sg:city":"Briffons",
    "sg:classifiers":[
        {
            "category":"Food & Beverages",
            "subcategory":"Cheese",
            "type":"Retail Goods"
        }
    ],
    "sg:phone":"+33 4 73 22 18 00",
    "sg:postcode":"63820",
    "sg:province":"Auvergne",
    "wof:name":"Soci\u00e9t\u00e9 Laiti\u00e8re Laqueuille Coop",
    "wof:placetype":"venue"
},
  "geometry": {"coordinates":[2.704592,45.645046],"type":"Point"}
}