{
  "type": "Feature",
  "properties": {
    "addr:full":"2BIS rue Neuve 59149 Cousolre Nord Pas-de-Calais 59149",
    "addr:housenumber":"2bis",
    "addr:postcode":"59149;59149",
    "addr:street":"Rue Neuve",
    "iso:country":"FR",
    "sg:address":"2BIS rue Neuve 59149 Cousolre",
    "sg:classifiers":[
        {
            "category":"Autos & Motor Vehicles",
            "subcategory":"Fuel & Gas Station",
            "type":"Retail Goods"
        }
    ],
    "sg:phone":"+33 3 27 63 20 77",
    "sg:postcode":"59149",
    "sg:province":"Nord Pas-de-Calais",
    "sg:tags":[
        "machine",
        "stone",
        "natural",
        "cnc",
        "working"
    ],
    "wof:name":"Decamps D\u00e9sir\u00e9 Sarl",
    "wof:placetype":"venue"
},
  "geometry": {"coordinates":[4.145037,50.253139],"type":"Point"}
}