{
  "type": "Feature",
  "properties": {
    "iso:country":"FR",
    "sg:address":"58, Av. Charles de Gaulle, 92200 Neuilly sur Seine",
    "sg:orig_category":"Unclassifiable Establishments",
    "sg:phone":"+33 1 55 62 15 55",
    "sg:province":"Ile de France",
    "wof:name":"Matis S.a.",
    "wof:placetype":"venue"
},
  "geometry": {"coordinates":[2.272868,48.881233],"type":"Point"}
}