{
  "type": "Feature",
  "properties": {
    "addr:full":"8, Rue des Grands Moulins, 88200 Saint Etienne l\u00e8s Remiremont Lorraine",
    "addr:housenumber":"8",
    "addr:postcode":"88200",
    "addr:street":"Rue Des Grands Moulins",
    "iso:country":"FR",
    "sg:address":"8, Rue des Grands Moulins, 88200 Saint Etienne l\u00e8s Remiremont",
    "sg:orig_category":"Unclassifiable Establishments",
    "sg:phone":"+33 3 29 23 91 26",
    "sg:province":"Lorraine",
    "wof:name":"M.p.l. S.a.r.l. - M\u00e9canique De Pr\u00e9cision Luc Petitjean",
    "wof:placetype":"venue"
},
  "geometry": {"coordinates":[6.602994,48.02166],"type":"Point"}
}