{
  "type": "Feature",
  "properties": {
    "iso:country":"FR",
    "sg:address":"1, Av Jeanne d'Arc, 62440 Harnes",
    "sg:orig_category":"Unclassifiable Establishments",
    "sg:phone":"+33 3 21 20 03 00",
    "sg:province":"Nord Pas-de-Calais",
    "wof:name":"E.b.t.m. S.a. - Entreprise De B\u00e2timent De Transformation Et Modernisation",
    "wof:placetype":"venue"
},
  "geometry": {"coordinates":[2.906035,50.448971],"type":"Point"}
}