{
  "type": "Feature",
  "properties": {
    "addr:full":"90, Rue d'Alsace - ZAC des Provinces, 45160 Olivet Ardon Centre 45160",
    "addr:housenumber":"90",
    "addr:postcode":"45160;45160",
    "addr:street":"Rue D'Alsace Zac Des Provinces",
    "iso:country":"FR",
    "sg:address":"90, Rue d'Alsace - ZAC des Provinces, 45160 Olivet",
    "sg:city":"Ardon",
    "sg:orig_category":"Non-Classified Establishments",
    "sg:phone":"+33 2 38 76 03 07",
    "sg:postcode":"45160",
    "sg:province":"Centre",
    "wof:name":"Soci\u00e9t\u00e9 Trane",
    "wof:placetype":"venue"
},
  "geometry": {"coordinates":[1.892303,47.869198],"type":"Point"}
}