{
  "type": "Feature",
  "properties": {
    "iso:country":"FR",
    "sg:address":"B.P. 137, 31676 Lab\u00e8ge C\u00e9dex^^Voie No 1, 31670 Lab\u00e8ge",
    "sg:orig_category":"Non-Classified Establishments",
    "sg:phone":"+33 5 61 00 40 00",
    "sg:province":"Midi Pyr\u00e9n\u00e9es",
    "wof:name":"Sanofi Recherche",
    "wof:placetype":"venue"
},
  "geometry": {"coordinates":[1.527111,43.529713],"type":"Point"}
}