{
  "type": "Feature",
  "properties": {
    "addr:full":"12 boulevard Abb\u00e9 Louis le Cam 56100 Lorient Lorient Bretagne 56100",
    "addr:housenumber":"12",
    "addr:postcode":"56100;56100",
    "addr:street":"Boulevard Abbe\u0301 Louis Le Cam",
    "iso:country":"FR",
    "sg:address":"12 boulevard Abb\u00e9 Louis le Cam 56100 Lorient",
    "sg:city":"Lorient",
    "sg:classifiers":[
        {
            "category":"Banks & Credit Unions",
            "subcategory":"Atm",
            "type":"Services"
        }
    ],
    "sg:phone":"+33 2 97 87 14 00",
    "sg:postcode":"56100",
    "sg:province":"Bretagne",
    "sg:tags":[
        "anchor",
        "chain"
    ],
    "wof:name":"Docks Et Entrep\u00f4ts Maritimes De Keroman Sarl",
    "wof:placetype":"venue"
},
  "geometry": {"coordinates":[-3.361513,47.729877],"type":"Point"}
}