{
  "type": "Feature",
  "properties": {
    "addr:full":"25 Rue Ch\u00e2teaubriand Paris Ile de France 75008",
    "addr:housenumber":"25",
    "addr:postcode":"75008",
    "addr:street":"Rue Cha\u0302Teaubriand",
    "iso:country":"FR",
    "sg:address":"25 Rue Ch\u00e2teaubriand",
    "sg:city":"Paris",
    "sg:classifiers":[
        {
            "category":"Banks & Credit Unions",
            "subcategory":"Financial Services",
            "type":"Services"
        }
    ],
    "sg:phone":"+33 1 42 56 29 30",
    "sg:postcode":"75008",
    "sg:province":"Ile de France",
    "sg:tags":[
        "banking",
        "finance",
        "insurance"
    ],
    "wof:name":"Fiduciaires Associes De France Sa",
    "wof:placetype":"venue"
},
  "geometry": {"coordinates":[2.299993,48.873817],"type":"Point"}
}