{
  "type": "Feature",
  "properties": {
    "addr:full":"116, Rue Edouard Vaillant, 94807 Villejuif C\u00e9dex Vill\u00e9 Alsace 67220",
    "addr:housenumber":"116",
    "addr:postcode":"94807;67220",
    "addr:street":"Rue Edouard Vaillant",
    "iso:country":"FR",
    "sg:address":"116, Rue Edouard Vaillant, 94807 Villejuif C\u00e9dex",
    "sg:city":"Vill\u00e9",
    "sg:orig_category":"Non-Classified Establishments",
    "sg:phone":"+33 1 53 14 50 50",
    "sg:postcode":"67220",
    "sg:province":"Alsace",
    "wof:name":"Timming S.a.",
    "wof:placetype":"venue"
},
  "geometry": {"coordinates":[2.351951,48.79327],"type":"Point"}
}