{
  "type": "Feature",
  "properties": {
    "addr:full":"Zac Des Combottes 25700 Valentigney Franche Comt\u00e9 25700",
    "addr:housenumber":"zac",
    "addr:postcode":"25700;25700",
    "addr:street":"Des Combottes;Franche Comte\u0301",
    "iso:country":"FR",
    "sg:address":"Zac Des Combottes 25700 Valentigney",
    "sg:classifiers":[
        {
            "category":"Autos & Motor Vehicles",
            "subcategory":"Automobile Sales",
            "type":"Retail Goods"
        }
    ],
    "sg:phone":"+33 3 81 36 20 20",
    "sg:postcode":"25700",
    "sg:province":"Franche Comt\u00e9",
    "sg:tags":[
        "equipment",
        "motor-cars",
        "transport"
    ],
    "wof:name":"Eak Composant Pour L'automobile Snc",
    "wof:placetype":"venue"
},
  "geometry": {"coordinates":[6.837825,47.464218],"type":"Point"}
}