{
  "type": "Feature",
  "properties": {
    "addr:full":"58 A, Rue du Dessous des Berges, 75013 Paris Ile de France",
    "addr:housenumber":"58 a",
    "addr:postcode":"75013",
    "addr:street":"Rue Du Dessous Des Berges",
    "iso:country":"FR",
    "sg:address":"58 A, Rue du Dessous des Berges, 75013 Paris",
    "sg:orig_category":"Unclassifiable Establishments",
    "sg:phone":"+33 1 53 94 65 90",
    "sg:province":"Ile de France",
    "wof:name":"Adine Sa",
    "wof:placetype":"venue"
},
  "geometry": {"coordinates":[2.373996,48.827557],"type":"Point"}
}