{
  "type": "Feature",
  "properties": {
    "iso:country":"FR",
    "sg:address":"758, Av du Tremblay - Zone Industrielle de Vaux, 60100 Creil",
    "sg:orig_category":"Unclassifiable Establishments",
    "sg:phone":"+33 3 44 25 59 66",
    "sg:province":"Picardie",
    "wof:name":"A.d.i. S.a.r.l.",
    "wof:placetype":"venue"
},
  "geometry": {"coordinates":[2.47547,49.259537],"type":"Point"}
}