{
  "type": "Feature",
  "properties": {
    "addr:full":"Rue Comtesse S\u00e9gur 26700 Pierrelatte Rhone-Alpes",
    "addr:postcode":"26700",
    "addr:street":"Rue Comtesse",
    "iso:country":"FR",
    "sg:address":"Rue Comtesse S\u00e9gur 26700 Pierrelatte",
    "sg:classifiers":[
        {
            "category":"Manufacturing",
            "subcategory":"Paper Products",
            "type":"Manufacturing & Wholesale Goods"
        }
    ],
    "sg:phone":"+33 4 75 04 05 68",
    "sg:province":"Rhone-Alpes",
    "sg:tags":[
        "packaging",
        "material",
        "-",
        "cardboard"
    ],
    "wof:name":"Spinnler (cartonnages)",
    "wof:placetype":"venue"
},
  "geometry": {"coordinates":[4.703764,44.38522],"type":"Point"}
}