{
  "type": "Feature",
  "properties": {
    "iso:country":"FR",
    "sg:address":"ZA du Champs de Mars",
    "sg:city":"Richemont",
    "sg:orig_category":"Non-Classified Establishments",
    "sg:phone":"+33 3 87 71 74 93",
    "sg:postcode":"57270",
    "sg:province":"Lorraine",
    "wof:name":"Covino S.a.r.l.",
    "wof:placetype":"venue"
},
  "geometry": {"coordinates":[6.166242,49.279499],"type":"Point"}
}