{
  "type": "Feature",
  "properties": {
    "iso:country":"FR",
    "sg:address":"49 All Des Pommiers 93190 Livry Gargan",
    "sg:classifiers":[
        {
            "category":"Manufacturing",
            "subcategory":"Metals",
            "type":"Manufacturing & Wholesale Goods"
        }
    ],
    "sg:phone":"+33 1 43 81 35 96",
    "sg:postcode":"93190",
    "sg:province":"Ile de France",
    "sg:tags":[
        "metallurgy",
        "steel",
        "metalworking"
    ],
    "wof:name":"Mecanique Generale Duthoit Germain Sarl",
    "wof:placetype":"venue"
},
  "geometry": {"coordinates":[2.536856,48.909286],"type":"Point"}
}