{
  "type": "Feature",
  "properties": {
    "iso:country":"FR",
    "sg:address":"Quartier Saint Michel",
    "sg:city":"Cabannes",
    "sg:orig_category":"Unclassifiable Establishments",
    "sg:phone":"+33 4 90 95 23 37",
    "sg:postcode":"13440",
    "sg:province":"Provence-Alpes-C\u00f4te d'Azur",
    "wof:name":"E.f.c. S.a. - Entrep\u00f4ts Frigorifiques Cabannes",
    "wof:placetype":"venue"
},
  "geometry": {"coordinates":[4.948805,43.858936],"type":"Point"}
}