{
  "type": "Feature",
  "properties": {
    "addr:full":"Place de l'Eglise - H\u00f4tel de Ville Saint Hilaire de Riez Pays de Loire 85270",
    "addr:postcode":"85270",
    "addr:street":"Place De L'Eglise Ho\u0302Tel;Saint;De Riez",
    "iso:country":"FR",
    "sg:address":"Place de l'Eglise - H\u00f4tel de Ville",
    "sg:city":"Saint Hilaire de Riez",
    "sg:orig_category":"Unclassifiable Establishments",
    "sg:phone":"+33 2 51 60 03 77",
    "sg:postcode":"85270",
    "sg:province":"Pays de Loire",
    "wof:name":"S.a.e.m. Saint Hilaire D\u00e9veloppement S.a.",
    "wof:placetype":"venue"
},
  "geometry": {"coordinates":[-1.94669,46.722641],"type":"Point"}
}