{
  "type": "Feature",
  "properties": {
    "addr:full":"Rue Garance - Voie n\u00b0 3 - B\u00e2t. E Lab\u00e8ge C\u00e9dex Aquitaine 31677",
    "addr:housenumber":"3 ba\u0302t e",
    "addr:postcode":"31677",
    "addr:street":"Rue Garance Voie N\u00b0",
    "iso:country":"FR",
    "sg:address":"Rue Garance - Voie n\u00b0 3 - B\u00e2t. E",
    "sg:city":"Lab\u00e8ge C\u00e9dex",
    "sg:orig_category":"Non-Classified Establishments",
    "sg:phone":"+33 5 61 00 96 00",
    "sg:postcode":"31677",
    "sg:province":"Aquitaine",
    "wof:name":"D.v. Construction S.a.",
    "wof:placetype":"venue"
},
  "geometry": {"coordinates":[1.527111,43.529713],"type":"Point"}
}