{
  "type": "Feature",
  "properties": {
    "iso:country":"FR",
    "sg:address":"Rue De Jamard 77390 Ozouer Le Voulgis",
    "sg:classifiers":[
        {
            "category":"Professional",
            "subcategory":"Engineering",
            "type":"Services"
        }
    ],
    "sg:phone":"+33 1 64 51 34 20",
    "sg:postcode":"77390",
    "sg:province":"Ile de France",
    "sg:tags":[
        "machine",
        "-",
        "mechanical"
    ],
    "wof:name":"Dow Automotive France Sa",
    "wof:placetype":"venue"
},
  "geometry": {"coordinates":[2.776661,48.663692],"type":"Point"}
}