{
  "type": "Feature",
  "properties": {
    "addr:full":"45, Bd Aragot, 79180 Chauray Poitou-Charentes 79180",
    "addr:housenumber":"45",
    "addr:postcode":"79180;79180",
    "addr:street":"Bd Aragot",
    "iso:country":"FR",
    "sg:address":"45, Bd Aragot, 79180 Chauray",
    "sg:orig_category":"Non-Classified Establishments",
    "sg:phone":"+33 5 49 33 71 71",
    "sg:postcode":"79180",
    "sg:province":"Poitou-Charentes",
    "wof:name":"Boiron S.a.",
    "wof:placetype":"venue"
},
  "geometry": {"coordinates":[-0.372754,46.361385],"type":"Point"}
}