{
  "type": "Feature",
  "properties": {
    "addr:full":"chemin des Meurins 59250 Halluin Nord Pas-de-Calais",
    "addr:postcode":"59250",
    "addr:street":"Chemin Des Meurins",
    "iso:country":"FR",
    "sg:address":"chemin des Meurins 59250 Halluin",
    "sg:orig_category":"Transport Services For Concert And Starring Tours",
    "sg:phone":"+33 3 20 25 95 25",
    "sg:province":"Nord Pas-de-Calais",
    "wof:name":"Militzer Et M\u00fcnch France Sa",
    "wof:placetype":"venue"
},
  "geometry": {"coordinates":[3.141969,50.783958],"type":"Point"}
}