{
  "type": "Feature",
  "properties": {
    "iso:country":"FR",
    "sg:address":"PAC des Ch\u00e2telets",
    "sg:city":"Tr\u00e9gueux",
    "sg:orig_category":"Unclassifiable Establishments",
    "sg:phone":"+33 2 96 76 63 63",
    "sg:postcode":"22950",
    "sg:province":"Bretagne",
    "wof:name":"C.i.e. S.a. - Cr\u00e9ation Innovation Entreprise",
    "wof:placetype":"venue"
},
  "geometry": {"coordinates":[-2.785505,48.462337],"type":"Point"}
}