{
  "type": "Feature",
  "properties": {
    "addr:full":"44 Rue Maurice Berthaux 95500 Le Thillay Ile de France 95500",
    "addr:housenumber":"44",
    "addr:postcode":"95500;95500",
    "addr:street":"Rue Maurice Berthaux",
    "iso:country":"FR",
    "sg:address":"44 Rue Maurice Berthaux 95500 Le Thillay",
    "sg:classifiers":[
        {
            "category":"Manufacturing",
            "subcategory":"Metals",
            "type":"Manufacturing & Wholesale Goods"
        }
    ],
    "sg:phone":"+33 1 39 88 35 22",
    "sg:postcode":"95500",
    "sg:province":"Ile de France",
    "sg:tags":[
        "metallurgy",
        "metalworking"
    ],
    "wof:name":"Transformation Industriel Des M\u00c9taux",
    "wof:placetype":"venue"
},
  "geometry": {"coordinates":[2.47996,49.00132],"type":"Point"}
}