{
  "type": "Feature",
  "properties": {
    "addr:full":"B.P. 32, 13751 Les Pennes Mirabeau C\u00e9dex^^27, Synergiparc - ZA l'Agavon - Synergie Parc, 13170 Les P Poitou-Charentes",
    "addr:postcode":"13751;13170",
    "addr:street":"B.P. 32;Za L'Agavon Synergie Parc;P",
    "iso:country":"FR",
    "sg:address":"B.P. 32, 13751 Les Pennes Mirabeau C\u00e9dex^^27, Synergiparc - ZA l'Agavon - Synergie Parc, 13170 Les P",
    "sg:orig_category":"Non-Classified Establishments",
    "sg:phone":"+33 4 42 02 60 00",
    "sg:province":"Poitou-Charentes",
    "wof:name":"It\u00e9ca Socadei S.a.",
    "wof:placetype":"venue"
},
  "geometry": {"coordinates":[5.282638,43.417511],"type":"Point"}
}