{
  "type": "Feature",
  "properties": {
    "iso:country":"FR",
    "sg:address":"Ch\u00e2teau Guibeau 33570 Puisseguin",
    "sg:city":"Puisseguin",
    "sg:orig_category":"Unclassifiable Establishments",
    "sg:phone":"+33 5 57 55 22 75",
    "sg:postcode":"33570",
    "sg:province":"Aquitaine",
    "wof:name":"Henri Bourlon S.c.e.a.",
    "wof:placetype":"venue"
},
  "geometry": {"coordinates":[-0.058452,44.94268],"type":"Point"}
}