{
  "type": "Feature",
  "properties": {
    "iso:country":"FR",
    "sg:address":"39 Rue Du Heron",
    "sg:city":"Lisieux",
    "sg:classifiers":[
        {
            "category":"Banks & Credit Unions",
            "subcategory":"Financial Services",
            "type":"Services"
        }
    ],
    "sg:phone":"+33 2 31 62 26 69",
    "sg:postcode":"14100",
    "sg:province":"Basse Normandie",
    "sg:tags":[
        "banking",
        "finance",
        "insurance"
    ],
    "wof:name":"Fiduciaire De France Societe D'expertise Comptable Commissai (fidex)",
    "wof:placetype":"venue"
},
  "geometry": {"coordinates":[0.220823,49.142097],"type":"Point"}
}