{
  "type": "Feature",
  "properties": {
    "iso:country":"FR",
    "sg:address":"Rue Plaine Basse 94290 Villeneuve Le Roi",
    "sg:classifiers":[
        {
            "category":"Manufacturing",
            "subcategory":"Metals",
            "type":"Manufacturing & Wholesale Goods"
        }
    ],
    "sg:phone":"+33 1 45 97 53 37",
    "sg:postcode":"94290",
    "sg:province":"Ile de France",
    "sg:tags":[
        "-",
        "machine",
        "equipment",
        "engineering",
        "machinery",
        "mechanical"
    ],
    "wof:name":"Stam",
    "wof:placetype":"venue"
},
  "geometry": {"coordinates":[2.4387,48.735184],"type":"Point"}
}