{
  "type": "Feature",
  "properties": {
    "addr:full":"143, Rue Jean Jaur\u00e8s, 59162 Ostricourt Nord Pas-de-Calais",
    "addr:housenumber":"143",
    "addr:postcode":"59162",
    "addr:street":"Rue Jean Jaure\u0300S",
    "iso:country":"FR",
    "sg:address":"143, Rue Jean Jaur\u00e8s, 59162 Ostricourt",
    "sg:orig_category":"Non-Classified Establishments",
    "sg:phone":"+33 3 27 87 05 19",
    "sg:province":"Nord Pas-de-Calais",
    "wof:name":"Lorthois Julien S.a.",
    "wof:placetype":"venue"
},
  "geometry": {"coordinates":[3.032988,50.453129],"type":"Point"}
}