{
  "type": "Feature",
  "properties": {
    "iso:country":"FR",
    "sg:address":"143, Rue Jean Jaur\u00e8s, 59162 Ostricourt",
    "sg:orig_category":"Non-Classified Establishments",
    "sg:phone":"+33 3 27 87 05 19",
    "sg:province":"Nord Pas-de-Calais",
    "wof:name":"Lorthois Julien S.a.",
    "wof:placetype":"venue"
},
  "geometry": {"coordinates":[3.032988,50.453129],"type":"Point"}
}