{
  "type": "Feature",
  "properties": {
    "addr:full":"68, Rue Anatole France, 92594 Levallois Perret C\u00e9dex Aquitaine",
    "addr:housenumber":"68",
    "addr:postcode":"92594",
    "addr:street":"Rue Anatole France",
    "iso:country":"FR",
    "sg:address":"68, Rue Anatole France, 92594 Levallois Perret C\u00e9dex",
    "sg:orig_category":"Non-Classified Establishments",
    "sg:phone":"+33 1 41 34 18 20",
    "sg:province":"Aquitaine",
    "wof:name":"Sagarmatha S.a.s.",
    "wof:placetype":"venue"
},
  "geometry": {"coordinates":[2.285616,48.891724],"type":"Point"}
}