{
  "type": "Feature",
  "properties": {
    "iso:country":"FR",
    "sg:address":"B.P. 36, 43001 Le Puy en Velay C\u00e9dex^^Rte des Estreys, 43000 Le Puy en Velay",
    "sg:city":"Le Puy-en-Velay",
    "sg:orig_category":"Non-Classified Establishments",
    "sg:phone":"+33 4 71 09 93 40",
    "sg:postcode":"43000",
    "sg:province":"Auvergne",
    "wof:name":"Pag\u00e8s S.a.",
    "wof:placetype":"venue"
},
  "geometry": {"coordinates":[3.895839,45.017532],"type":"Point"}
}