{
  "type": "Feature",
  "properties": {
    "addr:full":"Quartier Champarlaud Peipin Picardie 04200",
    "addr:postcode":"04200",
    "addr:street":"Picardie",
    "iso:country":"FR",
    "sg:address":"Quartier Champarlaud",
    "sg:city":"Peipin",
    "sg:orig_category":"Unclassifiable Establishments",
    "sg:phone":"+33 4 92 62 49 25",
    "sg:postcode":"04200",
    "sg:province":"Picardie",
    "wof:name":"Comptoir Alpin Des Bois S.a.",
    "wof:placetype":"venue"
},
  "geometry": {"coordinates":[5.969041,44.137764],"type":"Point"}
}