{
  "type": "Feature",
  "properties": {
    "addr:full":"2, Rue du Petit Pr\u00e9 - ZI de Qu\u00e9vert, 22100 Dinan Qu\u00e9vert Bretagne 22100",
    "addr:housenumber":"2",
    "addr:postcode":"22100;22100",
    "addr:street":"Rue Du Petit Pre\u0301 Zi De Que\u0301Vert;Que\u0301Vert",
    "iso:country":"FR",
    "sg:address":"2, Rue du Petit Pr\u00e9 - ZI de Qu\u00e9vert, 22100 Dinan",
    "sg:city":"Qu\u00e9vert",
    "sg:orig_category":"Unclassifiable Establishments",
    "sg:phone":"+33 2 96 39 50 91",
    "sg:postcode":"22100",
    "sg:province":"Bretagne",
    "wof:name":"C.c.e. S.a. - Constructions De La C\u00f4te D'emeraude",
    "wof:placetype":"venue"
},
  "geometry": {"coordinates":[-2.064859,48.390835],"type":"Point"}
}