{
  "type": "Feature",
  "properties": {
    "addr:full":"Rte de Colmar Uffholtz Alsace 68700",
    "addr:postcode":"68700",
    "addr:street":"Rte De Colmar",
    "iso:country":"FR",
    "sg:address":"Rte de Colmar",
    "sg:city":"Uffholtz",
    "sg:orig_category":"Unclassifiable Establishments",
    "sg:phone":"+33 3 89 75 50 31",
    "sg:postcode":"68700",
    "sg:province":"Alsace",
    "wof:name":"F\u00e9ral Industrie S.a.r.l.",
    "wof:placetype":"venue"
},
  "geometry": {"coordinates":[7.178375,47.809181],"type":"Point"}
}