{
  "type": "Feature",
  "properties": {
    "iso:country":"FR",
    "sg:address":"32, Rue Belle Paule, 31500 Toulouse",
    "sg:orig_category":"Unclassifiable Establishments",
    "sg:phone":"+33 5 62 71 64 71",
    "sg:province":"Midi Pyr\u00e9n\u00e9es",
    "wof:name":"S.i.c. S.a.r.l. - Structures Ing\u00e9nierie Construction",
    "wof:placetype":"venue"
},
  "geometry": {"coordinates":[1.465529,43.596325],"type":"Point"}
}