{
  "type": "Feature",
  "properties": {
    "iso:country":"FR",
    "sg:address":"9, Rue L\u00e9on Blum, 91124 Palaiseau C\u00e9dex",
    "sg:orig_category":"Non-Classified Establishments",
    "sg:phone":"+33 1 69 19 72 01",
    "sg:province":"\u00cele-de-France",
    "wof:name":"P\u00e9ridata S.a.",
    "wof:placetype":"venue"
},
  "geometry": {"coordinates":[2.253666,48.711678],"type":"Point"}
}