{
  "type": "Feature",
  "properties": {
    "addr:full":"Chem Classe 3 02315 St Quentin Cedex Nord Pas-de-Calais",
    "addr:housenumber":"3",
    "addr:postcode":"02315;cedex nord",
    "iso:country":"FR",
    "sg:address":"Chem Classe 3 02315 St Quentin Cedex",
    "sg:classifiers":[
        {
            "category":"Wholesale",
            "subcategory":"Machinery & Supplies",
            "type":"Manufacturing & Wholesale Goods"
        }
    ],
    "sg:phone":"+33 3 23 62 56 48",
    "sg:province":"Nord Pas-de-Calais",
    "sg:tags":[
        "handling",
        "material",
        "-",
        "machine",
        "equipment",
        "engineering",
        "mechanical"
    ],
    "wof:name":"Geodia Sas",
    "wof:placetype":"venue"
},
  "geometry": {"coordinates":[3.26385,49.84222],"type":"Point"}
}