{
  "type": "Feature",
  "properties": {
    "addr:full":"31 Rue Chomettes 77160 St Brice Ile de France",
    "addr:housenumber":"31",
    "addr:postcode":"77160",
    "addr:street":"Rue Chomettes",
    "iso:country":"FR",
    "sg:address":"31 Rue Chomettes 77160 St Brice",
    "sg:classifiers":[
        {
            "category":"Professional",
            "type":"Services"
        }
    ],
    "sg:phone":"+33 1 64 00 06 34",
    "sg:province":"Ile de France",
    "sg:tags":[
        "transport",
        "road"
    ],
    "wof:name":"Transports Clb Sa",
    "wof:placetype":"venue"
},
  "geometry": {"coordinates":[3.321573,48.571983],"type":"Point"}
}