{
  "type": "Feature",
  "properties": {
    "addr:full":"Rue Fran\u00e7ois Slakta Corbenay Franche Comt\u00e9 70320",
    "addr:postcode":"70320",
    "addr:street":"Rue Franc\u0327Ois Slakta;Franche Comte\u0301",
    "iso:country":"FR",
    "sg:address":"Rue Fran\u00e7ois Slakta",
    "sg:city":"Corbenay",
    "sg:orig_category":"Unclassifiable Establishments",
    "sg:phone":"+33 3 84 93 31 19",
    "sg:postcode":"70320",
    "sg:province":"Franche Comt\u00e9",
    "wof:name":"Voith Esac Hydro S.a.",
    "wof:placetype":"venue"
},
  "geometry": {"coordinates":[6.296375,47.882114],"type":"Point"}
}