{
  "type": "Feature",
  "properties": {
    "iso:country":"FR",
    "sg:address":"19 Rue De L'Industrie Zi Les R\u00eapes 70000 Vesoul",
    "sg:classifiers":[
        {
            "category":"Building & Trades",
            "subcategory":"Construction",
            "type":"Services"
        }
    ],
    "sg:phone":"+33 3 84 97 11 30",
    "sg:postcode":"70000",
    "sg:province":"Franche Comt\u00e9",
    "sg:tags":[
        "work",
        "public"
    ],
    "wof:name":"Sacer Paris Nord Est",
    "wof:placetype":"venue"
},
  "geometry": {"coordinates":[6.161116,47.639606],"type":"Point"}
}