{
  "type": "Feature",
  "properties": {
    "addr:full":"Pl Victor Hugo; Vichy; 03200 Vichy Auvergne 03200",
    "addr:postcode":"03200;03200",
    "addr:street":"Pl Victor Hugo",
    "iso:country":"FR",
    "sg:address":"Pl Victor Hugo; Vichy; 03200",
    "sg:city":"Vichy",
    "sg:classifiers":[
        {
            "category":"Banks & Credit Unions",
            "subcategory":"Bank",
            "type":"Services"
        }
    ],
    "sg:phone":"+33 3370301128",
    "sg:postcode":"03200",
    "sg:province":"Auvergne",
    "wof:name":"Cr\u00e9dit Lyonnais",
    "wof:placetype":"venue"
},
  "geometry": {"coordinates":[3.424061,46.121468],"type":"Point"}
}