{
  "type": "Feature",
  "properties": {
    "iso:country":"FR",
    "sg:address":"608, Rue du Mar\u00e9chal Juin - ZI Vaux le Penil, 77000 Melun",
    "sg:orig_category":"Unclassifiable Establishments",
    "sg:phone":"+33 1 64 37 05 59",
    "sg:province":"Ile de France",
    "wof:name":"S.n.a.v.e.b. S.a. - Soci\u00e9t\u00e9 Nouvelle Assainissement Vidange Ego\u00fbt Billard",
    "wof:placetype":"venue"
},
  "geometry": {"coordinates":[2.664085,48.539577],"type":"Point"}
}