{
  "type": "Feature",
  "properties": {
    "addr:full":"B.P. 28, 69631 V\u00e9nissieux C\u00e9dex^^203, Av. Francis de Pressens\u00e9, 69200 V\u00e9nissieux Rhone-Alpes",
    "addr:postcode":"69631;69200",
    "addr:street":"B.P. 28;Av. Francis De Pressense\u0301",
    "iso:country":"FR",
    "sg:address":"B.P. 28, 69631 V\u00e9nissieux C\u00e9dex^^203, Av. Francis de Pressens\u00e9, 69200 V\u00e9nissieux",
    "sg:orig_category":"Non-Classified Establishments",
    "sg:phone":"+33 4 78 77 55 00",
    "sg:province":"Rhone-Alpes",
    "wof:name":"Gb 2000 International S.a.",
    "wof:placetype":"venue"
},
  "geometry": {"coordinates":[4.885109,45.696575],"type":"Point"}
}