{
  "type": "Feature",
  "properties": {
    "iso:country":"FR",
    "sg:address":"8, Rue Gorde, 13010 Marseille",
    "sg:orig_category":"Non-Classified Establishments",
    "sg:phone":"+33 4 91 29 63 10",
    "sg:province":"Provence-Alpes-C\u00f4te d'Azur",
    "wof:name":"Net 2000 S.a.r.l.",
    "wof:placetype":"venue"
},
  "geometry": {"coordinates":[5.399478,43.285706],"type":"Point"}
}