{
  "type": "Feature",
  "properties": {
    "addr:full":"15 Rue Robert Schuman 44800 St Herblain Pays de Loire 44800",
    "addr:housenumber":"15",
    "addr:postcode":"44800;44800",
    "addr:street":"Rue Robert Schuman;Herblain",
    "iso:country":"FR",
    "sg:address":"15 Rue Robert Schuman 44800 St Herblain",
    "sg:classifiers":[
        {
            "category":"Manufacturing",
            "subcategory":"Metals",
            "type":"Manufacturing & Wholesale Goods"
        }
    ],
    "sg:phone":"+33 2 51 80 67 00",
    "sg:postcode":"44800",
    "sg:province":"Pays de Loire",
    "sg:tags":[
        "processing",
        "-",
        "metalworking",
        "metallic",
        "metallurgy",
        "finished"
    ],
    "wof:name":"Chaudronnerie Mecanique Tuyauterie Montage Sfcmm",
    "wof:placetype":"venue"
},
  "geometry": {"coordinates":[-1.631087,47.203831],"type":"Point"}
}