{
  "type": "Feature",
  "properties": {
    "addr:full":"21 Rue Voltaire 92250 La Garenne Colombes Ile de France 92250",
    "addr:housenumber":"21",
    "addr:postcode":"92250;92250",
    "addr:street":"Rue Voltaire",
    "iso:country":"FR",
    "sg:address":"21 Rue Voltaire 92250 La Garenne Colombes",
    "sg:classifiers":[
        {
            "category":"Shopping",
            "subcategory":"Crafts & Fabrics",
            "type":"Retail Goods"
        }
    ],
    "sg:phone":"+33 1 47 69 11 53",
    "sg:postcode":"92250",
    "sg:province":"Ile de France",
    "sg:tags":[
        "textile",
        "linen",
        "clothing"
    ],
    "wof:name":"Domeau Peres Sarl",
    "wof:placetype":"venue"
},
  "geometry": {"coordinates":[2.248049,48.907253],"type":"Point"}
}