{
  "type": "Feature",
  "properties": {
    "addr:full":"19, Rue Anatole France, 70300 Luxeuil les Bains Franche Comt\u00e9 70300",
    "addr:housenumber":"19",
    "addr:postcode":"70300;70300",
    "addr:street":"Rue Anatole France;Franche Comte\u0301",
    "iso:country":"FR",
    "sg:address":"19, Rue Anatole France, 70300 Luxeuil les Bains",
    "sg:orig_category":"Non-Classified Establishments",
    "sg:phone":"+33 3 84 40 21 13",
    "sg:postcode":"70300",
    "sg:province":"Franche Comt\u00e9",
    "wof:name":"Abattoir De Luxeuil Les Bains S.a.v.s.",
    "wof:placetype":"venue"
},
  "geometry": {"coordinates":[6.359074,47.816364],"type":"Point"}
}