{
  "type": "Feature",
  "properties": {
    "iso:country":"FR",
    "sg:address":"86100 Senille",
    "sg:classifiers":[
        {
            "category":"Farming",
            "subcategory":"Crops",
            "type":"Manufacturing & Wholesale Goods"
        }
    ],
    "sg:phone":"+33 5 49 93 65 05",
    "sg:postcode":"86100",
    "sg:province":"Poitou-Charentes",
    "sg:tags":[
        "vegetable",
        "fruit",
        "agriculture",
        "livestock"
    ],
    "wof:name":"Etablissements Boiry",
    "wof:placetype":"venue"
},
  "geometry": {"coordinates":[0.614296,46.778336],"type":"Point"}
}