{
  "type": "Feature",
  "properties": {
    "addr:full":"B.P. 22, 58028 Nevers C\u00e9dex^^ZI de Saint Eloi, 58000 Nevers Nevers Bourgogne 58000",
    "addr:postcode":"58028;58000;58000",
    "addr:street":"B.P. 22;Saint Eloi",
    "iso:country":"FR",
    "sg:address":"B.P. 22, 58028 Nevers C\u00e9dex^^ZI de Saint Eloi, 58000 Nevers",
    "sg:city":"Nevers",
    "sg:orig_category":"Non-Classified Establishments",
    "sg:phone":"+33 3 86 71 65 90",
    "sg:postcode":"58000",
    "sg:province":"Bourgogne",
    "wof:name":"Autodistribution Vast S.a.",
    "wof:placetype":"venue"
},
  "geometry": {"coordinates":[3.12953,46.920444],"type":"Point"}
}