{
  "type": "Feature",
  "properties": {
    "iso:country":"FR",
    "sg:address":"Vall\u00e9e des Vaux",
    "sg:city":"Cagnes sur Mer",
    "sg:orig_category":"Unclassifiable Establishments",
    "sg:phone":"+33 4 93 31 05 48",
    "sg:postcode":"06800",
    "sg:province":"Provence-Alpes-C\u00f4te d'Azur",
    "wof:name":"Ragni S.a.",
    "wof:placetype":"venue"
},
  "geometry": {"coordinates":[7.1533,43.664429],"type":"Point"}
}