{
  "type": "Feature",
  "properties": {
    "iso:country":"FR",
    "sg:address":"13, Chemin de Collex, 01210 Ferney Voltaire",
    "sg:orig_category":"Non-Classified Establishments",
    "sg:phone":"+33 4 50 40 69 53",
    "sg:postcode":"01210",
    "sg:province":"Rhone-Alpes",
    "wof:name":"Entreprise Reveillon Alain S.a.r.l.",
    "wof:placetype":"venue"
},
  "geometry": {"coordinates":[6.113345,46.258461],"type":"Point"}
}