{
  "type": "Feature",
  "properties": {
    "iso:country":"FR",
    "sg:address":"7 Boulevard Paul Emile Victor 92200 Neuilly Sur Seine",
    "sg:classifiers":[
        {
            "category":"Professional",
            "subcategory":"Printing & Photocopies",
            "type":"Services"
        }
    ],
    "sg:phone":"+33 1 41 43 85 85",
    "sg:province":"Ile de France",
    "sg:tags":[
        "publishing"
    ],
    "wof:name":"Michel Lafon Publishing Sa",
    "wof:placetype":"venue"
},
  "geometry": {"coordinates":[2.26259,48.89328],"type":"Point"}
}