{
  "type": "Feature",
  "properties": {
    "iso:country":"FR",
    "sg:address":"Rue St. Dominique 51006 Chalons En Champagne",
    "sg:classifiers":[
        {
            "category":"Professional",
            "subcategory":"Business Services",
            "type":"Services"
        }
    ],
    "sg:phone":"+33 3 26 69 26 89",
    "sg:province":"Outre-Mer",
    "sg:tags":[
        "training",
        "advice"
    ],
    "wof:name":"Ecole Nationale Sup Des Arts Et Metiers",
    "wof:placetype":"venue"
},
  "geometry": {"coordinates":[4.358846,48.956688],"type":"Point"}
}