{
  "type": "Feature",
  "properties": {
    "iso:country":"FR",
    "sg:address":"20, Rue Albert Romain, 69140 Rillieux la Pape",
    "sg:orig_category":"Non-Classified Establishments",
    "sg:phone":"+33 4 78 88 33 75",
    "sg:postcode":"69140",
    "sg:province":"Rhone-Alpes",
    "wof:name":"Alphaplast S.a.",
    "wof:placetype":"venue"
},
  "geometry": {"coordinates":[4.88432,45.806992],"type":"Point"}
}