{
  "type": "Feature",
  "properties": {
    "addr:full":"14, Rue Anatole de Monzie, 06300 Nice Picardie",
    "addr:housenumber":"14",
    "addr:postcode":"06300",
    "addr:street":"Rue Anatole De Monzie",
    "iso:country":"FR",
    "sg:address":"14, Rue Anatole de Monzie, 06300 Nice",
    "sg:orig_category":"Non-Classified Establishments",
    "sg:phone":"+33 4 93 54 35 32",
    "sg:province":"Picardie",
    "wof:name":"Interskill S.a.r.l.",
    "wof:placetype":"venue"
},
  "geometry": {"coordinates":[7.297729,43.736546],"type":"Point"}
}