{
  "type": "Feature",
  "properties": {
    "iso:country":"FR",
    "sg:address":"34 Avenue de la V\u00e8me R\u00e9publique 33460 CANTENAC",
    "sg:city":"Cantenac",
    "sg:classifiers":[
        {
            "category":"Wholesale",
            "subcategory":"Wine & Distilled Alcoholic Beverages",
            "type":"Manufacturing & Wholesale Goods"
        }
    ],
    "sg:phone":"+33 5 57 88 36 28",
    "sg:postcode":"33460",
    "sg:province":"Aquitaine",
    "sg:tags":[
        "french"
    ],
    "wof:name":"Ch\u00e2teau Priereur\u00e9 Lichine S.a.",
    "wof:placetype":"venue"
},
  "geometry": {"coordinates":[-0.654609,45.028728],"type":"Point"}
}