{
  "type": "Feature",
  "properties": {
    "addr:full":"6, Rue Victor Grignard, 42000 Saint Etienne Rhone-Alpes 42000",
    "addr:housenumber":"6",
    "addr:postcode":"42000;42000",
    "addr:street":"Rue Victor Grignard",
    "iso:country":"FR",
    "sg:address":"6, Rue Victor Grignard, 42000 Saint Etienne",
    "sg:orig_category":"Non-Classified Establishments",
    "sg:phone":"+33 4 77 92 51 54",
    "sg:postcode":"42000",
    "sg:province":"Rhone-Alpes",
    "wof:name":"Pum Plastiques S.a.",
    "wof:placetype":"venue"
},
  "geometry": {"coordinates":[4.398302,45.462353],"type":"Point"}
}