{
  "type": "Feature",
  "properties": {
    "iso:country":"FR",
    "sg:address":"26/30, Rue du Docteur Schweitzer, 51100 Reims",
    "sg:orig_category":"Unclassifiable Establishments",
    "sg:phone":"+33 3 26 50 65 64",
    "sg:province":"Champagne",
    "wof:name":"Impressions Technologies S.a.",
    "wof:placetype":"venue"
},
  "geometry": {"coordinates":[4.022051,49.278694],"type":"Point"}
}