{
  "type": "Feature",
  "properties": {
    "iso:country":"FR",
    "sg:address":"Bousbecque 59166 Bousbecque",
    "sg:classifiers":[
        {
            "category":"Communications",
            "subcategory":"Film & Video Production",
            "type":"Services"
        }
    ],
    "sg:phone":"+33 3 20 11 56 56",
    "sg:postcode":"59166",
    "sg:province":"Nord Pas-de-Calais",
    "sg:tags":[
        "packaging",
        "export",
        "cover"
    ],
    "wof:name":"Wipak Gryspeert Sa",
    "wof:placetype":"venue"
},
  "geometry": {"coordinates":[3.07805,50.764549],"type":"Point"}
}