{
  "type": "Feature",
  "properties": {
    "addr:full":"3, Rue de la Potence, 59235 Bers\u00e9e Nord Pas-de-Calais",
    "addr:housenumber":"3",
    "addr:postcode":"59235",
    "addr:street":"Rue De La Potence",
    "iso:country":"FR",
    "sg:address":"3, Rue de la Potence, 59235 Bers\u00e9e",
    "sg:orig_category":"Unclassifiable Establishments",
    "sg:phone":"+33 3 20 84 90 57",
    "sg:province":"Nord Pas-de-Calais",
    "wof:name":"Longu\u00e9p\u00e9 Et Compagnie S.a.r.l.",
    "wof:placetype":"venue"
},
  "geometry": {"coordinates":[3.143559,50.468735],"type":"Point"}
}