{
  "type": "Feature",
  "properties": {
    "iso:country":"FR",
    "sg:address":"9 Bd Louis Blanc 83990 Saint Tropez",
    "sg:classifiers":[
        {
            "category":"Utilities",
            "subcategory":"Telephone",
            "type":"Services"
        }
    ],
    "sg:phone":"+33 4 94 97 06 15",
    "sg:province":"Midi Pyr\u00e9n\u00e9es",
    "sg:tags":[
        "telecommunication"
    ],
    "wof:name":"Duquesne Telecom",
    "wof:placetype":"venue"
},
  "geometry": {"coordinates":[6.636025,43.269466],"type":"Point"}
}