{
  "type": "Feature",
  "properties": {
    "addr:full":"B.P. 3817, 87038 Limoges C\u00e9dex^^Bd des Arcades, 87100 .Limoges Limousin 87100",
    "addr:housenumber":"3817",
    "addr:postcode":"87038;87100;87100",
    "addr:street":"B.P.",
    "iso:country":"FR",
    "sg:address":"B.P. 3817, 87038 Limoges C\u00e9dex^^Bd des Arcades, 87100 .Limoges",
    "sg:orig_category":"Non-Classified Establishments",
    "sg:phone":"+33 5 55 04 40 00",
    "sg:postcode":"87100",
    "sg:province":"Limousin",
    "wof:name":"C.r.c.i. Limousin-poitou-charente - Chambre R\u00e9gionale De Commerce Et D'industrie Limoges",
    "wof:placetype":"venue"
},
  "geometry": {"coordinates":[1.193255,45.843124],"type":"Point"}
}