{
  "type": "Feature",
  "properties": {
    "iso:country":"FR",
    "sg:address":"49 Bd St Michel 75005 Paris",
    "sg:classifiers":[
        {
            "category":"Professional",
            "subcategory":"Printing & Photocopies",
            "type":"Services"
        }
    ],
    "sg:phone":"+33 1 44 41 81 20",
    "sg:province":"Ile de France",
    "sg:tags":[
        "publishing"
    ],
    "wof:name":"Presses Universitaires De France (puf)",
    "wof:placetype":"venue"
},
  "geometry": {"coordinates":[2.341793,48.84848],"type":"Point"}
}