{
  "type": "Feature",
  "properties": {
    "addr:full":"Au Bourg 42940 St Bonnet Le Courreau Rhone-Alpes 42940",
    "addr:postcode":"42940;42940",
    "iso:country":"FR",
    "sg:address":"Au Bourg 42940 St Bonnet Le Courreau",
    "sg:classifiers":[
        {
            "category":"Home & Garden",
            "subcategory":"Furniture",
            "type":"Retail Goods"
        }
    ],
    "sg:phone":"+33 4 77 76 82 87",
    "sg:postcode":"42940",
    "sg:province":"Rhone-Alpes",
    "sg:tags":[
        "professional",
        "household",
        "wood"
    ],
    "wof:name":"Etablissements F Chambon",
    "wof:placetype":"venue"
},
  "geometry": {"coordinates":[3.9442,45.660267],"type":"Point"}
}