{
  "type": "Feature",
  "properties": {
    "addr:full":"5, Rue des Erables, 88160 Fresse sur Moselle Lorraine",
    "addr:housenumber":"5",
    "addr:postcode":"88160",
    "addr:street":"Rue Des Erables",
    "iso:country":"FR",
    "sg:address":"5, Rue des Erables, 88160 Fresse sur Moselle",
    "sg:orig_category":"Unclassifiable Establishments",
    "sg:phone":"+33 3 29 25 27 16",
    "sg:province":"Lorraine",
    "wof:name":"Aubert S.a.r.l.",
    "wof:placetype":"venue"
},
  "geometry": {"coordinates":[6.775885,47.875164],"type":"Point"}
}