{
  "type": "Feature",
  "properties": {
    "iso:country":"FR",
    "sg:address":"9 Rue De Sailly 59554 Raillencourt Ste Olle",
    "sg:classifiers":[
        {
            "category":"Farming",
            "subcategory":"Farm",
            "type":"Manufacturing & Wholesale Goods"
        }
    ],
    "sg:phone":"+33 3 27 81 58 72",
    "sg:postcode":"59554",
    "sg:province":"Nord Pas-de-Calais",
    "sg:tags":[
        "horticulture",
        "agriculture",
        "livestock"
    ],
    "wof:name":"Endinor Hoquet Graines Ste Sa",
    "wof:placetype":"venue"
},
  "geometry": {"coordinates":[3.170648,50.192226],"type":"Point"}
}