{
  "type": "Feature",
  "properties": {
    "addr:full":"146, Rue du Paradis, 13294 Marseille C\u00e9dex 06 Poitou-Charentes",
    "addr:housenumber":"146;06",
    "addr:postcode":"13294",
    "addr:street":"Rue Du Paradis;Ce\u0301Dex",
    "iso:country":"FR",
    "sg:address":"146, Rue du Paradis, 13294 Marseille C\u00e9dex 06",
    "sg:orig_category":"Non-Classified Establishments",
    "sg:phone":"+33 4 91 57 05 57",
    "sg:province":"Poitou-Charentes",
    "wof:name":"Karapharm S.a.r.l.",
    "wof:placetype":"venue"
},
  "geometry": {"coordinates":[5.379575,43.286366],"type":"Point"}
}