{
  "type": "Feature",
  "properties": {
    "iso:country":"FR",
    "sg:address":"Rue H\u00e9l\u00e8ne Boucher 58501 Clamecy Cedex",
    "sg:classifiers":[
        {
            "category":"Manufacturing",
            "subcategory":"Metals",
            "type":"Manufacturing & Wholesale Goods"
        }
    ],
    "sg:phone":"+33 3 86 24 47 69",
    "sg:province":"Centre",
    "sg:tags":[
        "metallurgy",
        "metalworking",
        "processing"
    ],
    "wof:name":"Jmp Diffusion",
    "wof:placetype":"venue"
},
  "geometry": {"coordinates":[3.519736,47.467159],"type":"Point"}
}