{
  "type": "Feature",
  "properties": {
    "iso:country":"FR",
    "sg:address":"B.P. 4157, 58641 Varennes Vauzelles C\u00e9dex^^39, Rue de Verdun, 58640 Varennes Vauzelles",
    "sg:city":"Varennes-Vauzelles",
    "sg:orig_category":"Non-Classified Establishments",
    "sg:phone":"+33 3 86 38 24 24",
    "sg:postcode":"58640",
    "sg:province":"Bourgogne",
    "wof:name":"Time Sport International S.a.",
    "wof:placetype":"venue"
},
  "geometry": {"coordinates":[3.14957,47.015034],"type":"Point"}
}