{
  "type": "Feature",
  "properties": {
    "iso:country":"FR",
    "sg:address":"ZAC les Pr\u00e9s de V\u00e8vre",
    "sg:city":"Demigny",
    "sg:orig_category":"Unclassifiable Establishments",
    "sg:phone":"+33 3 85 49 99 50",
    "sg:postcode":"71150",
    "sg:province":"Bourgogne",
    "wof:name":"Nattier",
    "wof:placetype":"venue"
},
  "geometry": {"coordinates":[4.83284,46.931881],"type":"Point"}
}