{
  "type": "Feature",
  "properties": {
    "iso:country":"FR",
    "sg:address":"17, Rue d'Arsonval, 01000 Bourg en Bresse",
    "sg:orig_category":"Non-Classified Establishments",
    "sg:phone":"+33 4 74 23 82 10",
    "sg:province":"Rhone-Alpes",
    "wof:name":"Optimis S.a.",
    "wof:placetype":"venue"
},
  "geometry": {"coordinates":[5.2201,46.223568],"type":"Point"}
}