{
  "type": "Feature",
  "properties": {
    "addr:full":"C\u00e9zille 01340 Jayat Rhone-Alpes",
    "addr:postcode":"01340",
    "addr:street":"Ce\u0301Zille",
    "iso:country":"FR",
    "sg:address":"C\u00e9zille 01340 Jayat",
    "sg:orig_category":"Unclassifiable Establishments",
    "sg:phone":"+33 4 74 30 80 38",
    "sg:province":"Rhone-Alpes",
    "wof:name":"Entreprise Vitte Didier",
    "wof:placetype":"venue"
},
  "geometry": {"coordinates":[5.12586,46.34758],"type":"Point"}
}