{
  "type": "Feature",
  "properties": {
    "iso:country":"FR",
    "sg:address":"Chem De Pau 64121 Serres Castet",
    "sg:city":"Montardon",
    "sg:classifiers":[
        {
            "category":"Transit Center",
            "subcategory":"Freight",
            "type":"Transportation"
        }
    ],
    "sg:phone":"+33 5 59 33 38 64",
    "sg:postcode":"64121",
    "sg:province":"Aquitaine",
    "sg:tags":[
        "metallurgy",
        "pipe",
        "metalworking",
        "sheet"
    ],
    "wof:name":"Aeroquip Vickers Sa",
    "wof:placetype":"venue"
},
  "geometry": {"coordinates":[-0.357417,43.382252],"type":"Point"}
}