{
  "type": "Feature",
  "properties": {
    "addr:full":"11, Rue des B\u00e9casses, 67860 Rhinau Rhinau Alsace 67860",
    "addr:housenumber":"11",
    "addr:postcode":"67860;67860",
    "addr:street":"Rue Des Be\u0301Casses",
    "iso:country":"FR",
    "sg:address":"11, Rue des B\u00e9casses, 67860 Rhinau",
    "sg:city":"Rhinau",
    "sg:orig_category":"Unclassifiable Establishments",
    "sg:phone":"+33 3 88 58 76 10",
    "sg:postcode":"67860",
    "sg:province":"Alsace",
    "wof:name":"Chaudronnerie Rudinger S.a.r.l.",
    "wof:placetype":"venue"
},
  "geometry": {"coordinates":[7.713028,48.317493],"type":"Point"}
}