{
  "type": "Feature",
  "properties": {
    "addr:full":"B.P. 5, 83951 La Garde C\u00e9dex^^93, Av. du Mar\u00e9chal Delattre de Tassigny - Le Pouverel , 83130 La Gard Illinois",
    "addr:housenumber":"5",
    "addr:postcode":"83951;83130",
    "addr:street":"B.P.;Av. Du Mare\u0301Chal Delattre De Tassigny Le Pouverel",
    "iso:country":"FR",
    "sg:address":"B.P. 5, 83951 La Garde C\u00e9dex^^93, Av. du Mar\u00e9chal Delattre de Tassigny - Le Pouverel , 83130 La Gard",
    "sg:orig_category":"Non-Classified Establishments",
    "sg:phone":"+33 4 94 75 96 10",
    "sg:province":"Illinois",
    "wof:name":"Pianelli S. A.",
    "wof:placetype":"venue"
},
  "geometry": {"coordinates":[-89.95967899999999,38.861092],"type":"Point"}
}