{
  "type": "Feature",
  "properties": {
    "iso:country":"FR",
    "sg:address":"B.P. 5, 83951 La Garde C\u00e9dex^^93, Av. du Mar\u00e9chal Delattre de Tassigny - Le Pouverel , 83130 La Gard",
    "sg:orig_category":"Non-Classified Establishments",
    "sg:phone":"+33 4 94 75 96 10",
    "sg:province":"Illinois",
    "wof:name":"Pianelli S. A.",
    "wof:placetype":"venue"
},
  "geometry": {"coordinates":[-89.959679,38.861092],"type":"Point"}
}