{
  "type": "Feature",
  "properties": {
    "iso:country":"FR",
    "sg:address":"15 Av Du Pr\u00e9 De Challes 74940 Annecy Le Vieux",
    "sg:classifiers":[
        {
            "category":"Wholesale",
            "subcategory":"Machinery & Supplies",
            "type":"Manufacturing & Wholesale Goods"
        }
    ],
    "sg:phone":"+33 4 50 64 00 57",
    "sg:postcode":"74940",
    "sg:province":"Rhone-Alpes",
    "sg:tags":[
        "handling",
        "material",
        "-",
        "machine",
        "equipment",
        "engineering",
        "mechanical"
    ],
    "wof:name":"Oleodyne Sa",
    "wof:placetype":"venue"
},
  "geometry": {"coordinates":[6.168192,45.930992],"type":"Point"}
}