{
  "type": "Feature",
  "properties": {
    "addr:full":"B.P. 1127, 45001 Orl\u00e9ans C\u00e9dex 1^^16, Rue de la R\u00e9publique, 45000 Orl\u00e9ans Orl\u00e9ans Centre 45000",
    "addr:housenumber":"1127;^ 16",
    "addr:postcode":"45001;45000;45000",
    "addr:street":"B.P.;Rue De La Re\u0301Publique",
    "iso:country":"FR",
    "sg:address":"B.P. 1127, 45001 Orl\u00e9ans C\u00e9dex 1^^16, Rue de la R\u00e9publique, 45000 Orl\u00e9ans",
    "sg:city":"Orl\u00e9ans",
    "sg:orig_category":"Non-Classified Establishments",
    "sg:phone":"+33 2 38 54 01 00",
    "sg:postcode":"45000",
    "sg:province":"Centre",
    "wof:name":"La Nouvelle R\u00e9publique Du Centre Ouest",
    "wof:placetype":"venue"
},
  "geometry": {"coordinates":[1.904965,47.901428],"type":"Point"}
}