{
  "type": "Feature",
  "properties": {
    "iso:country":"FR",
    "sg:address":"Z.I. de Lavalotte 29490 GUIPAVAS",
    "sg:city":"Guipavas",
    "sg:orig_category":"Liquid Manure Bins",
    "sg:phone":"+33 2 98 34 41 00",
    "sg:postcode":"29490",
    "sg:province":"Bretagne",
    "wof:name":"Etablissement Michel Pichon S.a.",
    "wof:placetype":"venue"
},
  "geometry": {"coordinates":[-4.431994,48.40044],"type":"Point"}
}