{
  "type": "Feature",
  "properties": {
    "addr:full":"L'Aubriais 35133 Saint Germain en Cogl\u00e8s Beauc\u00e9 Bretagne 35133",
    "addr:postcode":"35133;35133",
    "addr:street":"L'Aubriais;Beauce\u0301 Bretagne",
    "iso:country":"FR",
    "sg:address":"L'Aubriais 35133 Saint Germain en Cogl\u00e8s",
    "sg:city":"Beauc\u00e9",
    "sg:orig_category":"Non-Classified Establishments",
    "sg:phone":"+33 2 99 95 48 48",
    "sg:postcode":"35133",
    "sg:province":"Bretagne",
    "wof:name":"Scorolec S.a.r.l.",
    "wof:placetype":"venue"
},
  "geometry": {"coordinates":[-1.272117,48.390324],"type":"Point"}
}