{
  "type": "Feature",
  "properties": {
    "iso:country":"FR",
    "sg:address":"ZA la Pichati\u00e8re",
    "sg:city":"Moirans",
    "sg:orig_category":"Unclassifiable Establishments",
    "sg:phone":"+33 4 76 35 57 30",
    "sg:postcode":"38430",
    "sg:province":"Rhone-Alpes",
    "wof:name":"Etablissement Martin Robert",
    "wof:placetype":"venue"
},
  "geometry": {"coordinates":[5.554805,45.327175],"type":"Point"}
}