{
  "type": "Feature",
  "properties": {
    "addr:full":"B.P. 4037, 10014 Troyes C\u00e9dex^^35, Rue Paul Dubois, 10000 Troyes Champagne",
    "addr:postcode":"10014;10000",
    "addr:street":"B.P. 4037;Rue Paul Dubois",
    "iso:country":"FR",
    "sg:address":"B.P. 4037, 10014 Troyes C\u00e9dex^^35, Rue Paul Dubois, 10000 Troyes",
    "sg:orig_category":"Non-Classified Establishments",
    "sg:phone":"+33 3 25 73 27 43",
    "sg:province":"Champagne",
    "wof:name":"Groupe D.c.c. S.a.r.l. - Groupe Des Consultants Compl\u00e9mentaires",
    "wof:placetype":"venue"
},
  "geometry": {"coordinates":[4.074345,48.297874],"type":"Point"}
}