{
  "type": "Feature",
  "properties": {
    "iso:country":"FR",
    "sg:address":"81, RN 7, 69570 Dardilly",
    "sg:orig_category":"Unclassifiable Establishments",
    "sg:phone":"+33 4 78 44 21 12",
    "sg:postcode":"69570",
    "sg:province":"Rhone-Alpes",
    "wof:name":"Papeteries E.r.c.e. S.a.",
    "wof:placetype":"venue"
},
  "geometry": {"coordinates":[4.753535,45.805908],"type":"Point"}
}