{
  "type": "Feature",
  "properties": {
    "addr:full":"3, Rue Claude Chappe, 69771 Saint Didier au Mont d'Or C\u00e9dex Rhone-Alpes",
    "addr:housenumber":"3",
    "addr:postcode":"69771",
    "addr:street":"Rue Claude Chappe;Didier Au Mont D'Or Ce\u0301Dex Rhone-Alpes",
    "iso:country":"FR",
    "sg:address":"3, Rue Claude Chappe, 69771 Saint Didier au Mont d'Or C\u00e9dex",
    "sg:orig_category":"Non-Classified Establishments",
    "sg:phone":"+33 4 72 53 17 53",
    "sg:province":"Rhone-Alpes",
    "wof:name":"Garon Bonvalot S.a.",
    "wof:placetype":"venue"
},
  "geometry": {"coordinates":[4.80792,45.799847],"type":"Point"}
}