{
  "type": "Feature",
  "properties": {
    "addr:full":"Chemin Du Cordat 81350 Valderies Midi Pyr\u00e9n\u00e9es 81350",
    "addr:postcode":"81350;81350",
    "addr:street":"Chemin Du Cordat",
    "iso:country":"FR",
    "sg:address":"Chemin Du Cordat 81350 Valderies",
    "sg:classifiers":[
        {
            "category":"Wholesale",
            "subcategory":"Farm Supplies",
            "type":"Manufacturing & Wholesale Goods"
        }
    ],
    "sg:phone":"+33 5 63 56 51 47",
    "sg:postcode":"81350",
    "sg:province":"Midi Pyr\u00e9n\u00e9es",
    "sg:tags":[
        "-",
        "machine",
        "equipment",
        "engineering",
        "machinery",
        "mechanical",
        "agriculture"
    ],
    "wof:name":"Societe Nouvelle Berthier (snb)",
    "wof:placetype":"venue"
},
  "geometry": {"coordinates":[2.232397,44.011471],"type":"Point"}
}