{
  "type": "Feature",
  "properties": {
    "iso:country":"FR",
    "sg:address":"ZI de la poudrerie",
    "sg:city":"Oissel",
    "sg:orig_category":"Unclassifiable Establishments",
    "sg:phone":"+33 2 35 64 69 15",
    "sg:postcode":"76350",
    "sg:province":"Haute Normandie",
    "wof:name":"Alliance Sant\u00e9 S.a.s.",
    "wof:placetype":"venue"
},
  "geometry": {"coordinates":[1.095915,49.341049],"type":"Point"}
}