{
  "type": "Feature",
  "properties": {
    "iso:country":"FR",
    "sg:address":"B.P. 39, 67300 Schiltigheim^^26, Rue Saint Charles, 67300 Schiltigheim",
    "sg:city":"Schiltigheim",
    "sg:orig_category":"Non-Classified Establishments",
    "sg:phone":"+33 3 88 18 66 18",
    "sg:postcode":"67300",
    "sg:province":"Alsace",
    "wof:name":"Astoria Diffusion S.a.",
    "wof:placetype":"venue"
},
  "geometry": {"coordinates":[7.748565,48.605949],"type":"Point"}
}