{
  "type": "Feature",
  "properties": {
    "iso:country":"FR",
    "sg:address":"60 72 rue Robert Moinon 95400 Goussin Ville",
    "sg:orig_category":"Vulkollan\u00ae Wheels, Rollers And Castors",
    "sg:phone":"+33 1 39 33 28 28",
    "sg:province":"Ile de France",
    "wof:name":"M.p.r. Groupe",
    "wof:placetype":"venue"
},
  "geometry": {"coordinates":[-79.13501,42.370567],"type":"Point"}
}