{
  "type": "Feature",
  "properties": {
    "iso:country":"FR",
    "sg:address":"33710 Lansac",
    "sg:city":"Lansac",
    "sg:orig_category":"Unclassifiable Establishments",
    "sg:phone":"+33 5 57 68 42 17",
    "sg:postcode":"33710",
    "sg:province":"Aquitaine",
    "wof:name":"Ch\u00e2teau Guionne S.c.e.a.",
    "wof:placetype":"venue"
},
  "geometry": {"coordinates":[-0.541519,45.061016],"type":"Point"}
}