{
  "type": "Feature",
  "properties": {
    "iso:country":"FR",
    "sg:address":"19, Rue de l'Enfer, 59980 Reumont",
    "sg:orig_category":"Unclassifiable Establishments",
    "sg:phone":"+33 3 27 75 17 29",
    "sg:province":"Nord Pas-de-Calais",
    "wof:name":"Etablissements Dumez S.a.r.l.",
    "wof:placetype":"venue"
},
  "geometry": {"coordinates":[3.487023,50.080635],"type":"Point"}
}