{
  "type": "Feature",
  "properties": {
    "iso:country":"FR",
    "sg:address":"1, Rue Maurice Robin, 03390 Montmarault",
    "sg:city":"Montmarault",
    "sg:orig_category":"Unclassifiable Establishments",
    "sg:phone":"+33 4 70 07 62 95",
    "sg:postcode":"03390",
    "sg:province":"Auvergne",
    "wof:name":"A.b.m. S.a. - Ateliers M\u00e9tallurgiques Du Bourbonnais",
    "wof:placetype":"venue"
},
  "geometry": {"coordinates":[2.954234,46.314892],"type":"Point"}
}