{
  "type": "Feature",
  "properties": {
    "addr:full":"3, Rue Joseph Sauveur - Saint James , 56130 Nivillac Nivillac Bretagne 56130",
    "addr:housenumber":"3",
    "addr:postcode":"56130;56130",
    "addr:street":"Rue Joseph Sauveur;Nivillac",
    "iso:country":"FR",
    "sg:address":"3, Rue Joseph Sauveur - Saint James , 56130 Nivillac",
    "sg:city":"Nivillac",
    "sg:orig_category":"Unclassifiable Establishments",
    "sg:phone":"+33 2 99 90 63 23",
    "sg:postcode":"56130",
    "sg:province":"Bretagne",
    "wof:name":"Bodiguel Ren\u00e9 Joseph",
    "wof:placetype":"venue"
},
  "geometry": {"coordinates":[-2.353767,47.478352],"type":"Point"}
}