{
  "type": "Feature",
  "properties": {
    "iso:country":"FR",
    "sg:address":"B.P. 209, 91007 Evry C\u00e9dex^^14, Rue du Bois Sauvage, 91000 Evry",
    "sg:orig_category":"Non-Classified Establishments",
    "sg:phone":"+33 1 69 36 69 69",
    "sg:province":"Ile de France",
    "wof:name":"K.l.a. Tencor S.a.r.l.",
    "wof:placetype":"venue"
},
  "geometry": {"coordinates":[2.4293,48.624664],"type":"Point"}
}