{
  "type": "Feature",
  "properties": {
    "addr:full":"36, Av. Beauregard, 74960 Cran Gevrier Rhone-Alpes 74960",
    "addr:postcode":"74960;74960",
    "addr:street":"36 Av. Beauregard;Rhone-Alpes",
    "iso:country":"FR",
    "sg:address":"36, Av. Beauregard, 74960 Cran Gevrier",
    "sg:orig_category":"Non-Classified Establishments",
    "sg:phone":"+33 4 50 57 13 90",
    "sg:postcode":"74960",
    "sg:province":"Rhone-Alpes",
    "wof:name":"Gerin Sapra S.a.r.l.",
    "wof:placetype":"venue"
},
  "geometry": {"coordinates":[6.10313,45.90379],"type":"Point"}
}