{
  "type": "Feature",
  "properties": {
    "iso:country":"FR",
    "sg:address":"B.P. 11",
    "sg:city":"Coullons",
    "sg:orig_category":"Non-Classified Establishments",
    "sg:phone":"+33 2 38 36 10 01",
    "sg:postcode":"45720",
    "sg:province":"Centre",
    "wof:name":"Suplisson S.a.",
    "wof:placetype":"venue"
},
  "geometry": {"coordinates":[2.492695,47.621101],"type":"Point"}
}