{
  "type": "Feature",
  "properties": {
    "addr:full":"38, Av d'Azur, 40140 Soustons Soustons Aquitaine 40140",
    "addr:postcode":"40140;40140",
    "addr:street":"38 Av D'Azur",
    "iso:country":"FR",
    "sg:address":"38, Av d'Azur, 40140 Soustons",
    "sg:city":"Soustons",
    "sg:orig_category":"Unclassifiable Establishments",
    "sg:phone":"+33 5 58 41 41 60",
    "sg:postcode":"40140",
    "sg:province":"Aquitaine",
    "wof:name":"H.t.t. Traitement Thermique E.u.r.l.",
    "wof:placetype":"venue"
},
  "geometry": {"coordinates":[-1.319392,43.760334],"type":"Point"}
}