{
  "type": "Feature",
  "properties": {
    "addr:full":"1, All\u00e9e du Wacken, 67978 Strasbourg c\u00e9dex Strasbourg Alsace 67000",
    "addr:housenumber":"1",
    "addr:postcode":"67978;ce\u0301dex;67000",
    "addr:street":"Alle\u0301E Du Wacken",
    "iso:country":"FR",
    "sg:address":"1, All\u00e9e du Wacken, 67978 Strasbourg c\u00e9dex",
    "sg:city":"Strasbourg",
    "sg:orig_category":"Non-Classified Establishments",
    "sg:phone":"+33 3 88 11 74 72",
    "sg:postcode":"67000",
    "sg:province":"Alsace",
    "wof:name":"Azur Patrimoine",
    "wof:placetype":"venue"
},
  "geometry": {"coordinates":[7.73609,48.585232],"type":"Point"}
}