{
  "type": "Feature",
  "properties": {
    "addr:full":"B.P. 17 Plabennec Bretagne 29860",
    "addr:postcode":"29860",
    "addr:street":"B.P. 17 Plabennec Bretagne",
    "iso:country":"FR",
    "sg:address":"B.P. 17",
    "sg:city":"Plabennec",
    "sg:orig_category":"Non-Classified Establishments",
    "sg:phone":"+33 2 98 40 42 54",
    "sg:postcode":"29860",
    "sg:province":"Bretagne",
    "wof:name":"Soci\u00e9t\u00e9 Avicole De Croas Prenn S.a.",
    "wof:placetype":"venue"
},
  "geometry": {"coordinates":[-4.426449,48.502136],"type":"Point"}
}