{
  "type": "Feature",
  "properties": {
    "iso:country":"FR",
    "sg:address":"16 Rue Du Maquis 39200 Coyriere",
    "sg:classifiers":[
        {
            "category":"Manufacturing",
            "subcategory":"Rubber & Plastics",
            "type":"Manufacturing & Wholesale Goods"
        }
    ],
    "sg:phone":"+33 3 84 45 06 17",
    "sg:province":"Franche Comt\u00e9",
    "wof:name":"Techniplast",
    "wof:placetype":"venue"
},
  "geometry": {"coordinates":[5.845646,46.344742],"type":"Point"}
}