{
  "type": "Feature",
  "properties": {
    "iso:country":"FR",
    "sg:address":"39 rue Montmartre 75002 Paris",
    "sg:classifiers":[
        {
            "category":"Retail",
            "subcategory":"Event Space",
            "type":"Services"
        }
    ],
    "sg:phone":"+33 1 42 36 20 10",
    "sg:province":"Ile de France",
    "sg:tags":[
        "small",
        "leather",
        "good"
    ],
    "wof:name":"Diffusion Illona S.a.r.l.",
    "wof:placetype":"venue"
},
  "geometry": {"coordinates":[2.344695,48.865433],"type":"Point"}
}