{
  "type": "Feature",
  "properties": {
    "iso:country":"FR",
    "sg:address":"Ouilly 71520 Montagny sur Grosne",
    "sg:city":"Curtil-sous-Buffi\u00e8res",
    "sg:classifiers":[
        {
            "category":"Shopping",
            "subcategory":"Hobbies, Toys, & Games",
            "type":"Retail Goods"
        }
    ],
    "sg:phone":"+33 3 85 50 43 80",
    "sg:postcode":"71520",
    "sg:province":"Bourgogne",
    "sg:tags":[
        "product",
        "miscellaneous",
        "entertainment"
    ],
    "wof:name":"Sauvageot Patrice",
    "wof:placetype":"venue"
},
  "geometry": {"coordinates":[4.53555,46.2855],"type":"Point"}
}