{
  "type": "Feature",
  "properties": {
    "addr:full":"18, Impasse du Colombier, 41300 Salbris Salbris Centre 41300",
    "addr:housenumber":"18;salbris",
    "addr:postcode":"41300;41300",
    "addr:street":"Impasse Du Colombier",
    "iso:country":"FR",
    "sg:address":"18, Impasse du Colombier, 41300 Salbris",
    "sg:city":"Salbris",
    "sg:orig_category":"Unclassifiable Establishments",
    "sg:phone":"+33 2 54 97 31 57",
    "sg:postcode":"41300",
    "sg:province":"Centre",
    "wof:name":"Elec Service Centre S.a.r.l.",
    "wof:placetype":"venue"
},
  "geometry": {"coordinates":[2.04998,47.420536],"type":"Point"}
}