{
  "type": "Feature",
  "properties": {
    "addr:full":"15 Rue Immeub Industriels 75011 Paris Ile de France 75011",
    "addr:housenumber":"15",
    "addr:postcode":"75011;75011",
    "addr:street":"Rue Immeub Industriels",
    "iso:country":"FR",
    "sg:address":"15 Rue Immeub Industriels 75011 Paris",
    "sg:classifiers":[
        {
            "category":"Home & Garden",
            "subcategory":"Furniture",
            "type":"Retail Goods"
        }
    ],
    "sg:phone":"+33 1 43 72 03 13",
    "sg:postcode":"75011",
    "sg:province":"Ile de France",
    "sg:tags":[
        "household",
        "wood"
    ],
    "wof:name":"Le Texier",
    "wof:placetype":"venue"
},
  "geometry": {"coordinates":[2.392385,48.850006],"type":"Point"}
}