{
  "type": "Feature",
  "properties": {
    "iso:country":"FR",
    "sg:address":"22, Rue Berg\u00e8re, 75009 Paris",
    "sg:orig_category":"Unclassifiable Establishments",
    "sg:phone":"+33 1 47 70 16 93",
    "sg:province":"Ile de France",
    "wof:name":"C.t.i.f.l. - Centre Technique Interprofessionnel Des Fruits Et L\u00e9gumes",
    "wof:placetype":"venue"
},
  "geometry": {"coordinates":[2.34518,48.872547],"type":"Point"}
}