{
  "type": "Feature",
  "properties": {
    "iso:country":"FR",
    "sg:address":"3 Rue Monge Zae De Chalembert 86130 Jaunay Clan",
    "sg:classifiers":[
        {
            "category":"Professional",
            "subcategory":"Engineering",
            "type":"Services"
        }
    ],
    "sg:phone":"+33 5 49 52 53 09",
    "sg:postcode":"86130",
    "sg:province":"Poitou-Charentes",
    "sg:tags":[
        "machine",
        "-",
        "environment",
        "equipment",
        "machinery",
        "mechanical"
    ],
    "wof:name":"Atse",
    "wof:placetype":"venue"
},
  "geometry": {"coordinates":[0.366834,46.681679],"type":"Point"}
}