{
  "type": "Feature",
  "properties": {
    "addr:full":"All\u00e9es des Peupliers - ZI Heillecourt Heillecourt Lorraine 54180",
    "addr:postcode":"54180",
    "addr:street":"Alle\u0301Es Des Peupliers Zi",
    "iso:country":"FR",
    "sg:address":"All\u00e9es des Peupliers - ZI Heillecourt",
    "sg:city":"Heillecourt",
    "sg:orig_category":"Non-Classified Establishments",
    "sg:phone":"+33 3 83 56 03 21",
    "sg:postcode":"54180",
    "sg:province":"Lorraine",
    "wof:name":"Lery Bouvier S.a.",
    "wof:placetype":"venue"
},
  "geometry": {"coordinates":[6.194192,48.653137],"type":"Point"}
}