{
  "type": "Feature",
  "properties": {
    "iso:country":"FR",
    "sg:address":"35, Rue du Bac, 94480 Ablon sur Seine",
    "sg:orig_category":"Unclassifiable Establishments",
    "sg:phone":"+33 1 49 61 05 67",
    "sg:province":"Ile de France",
    "wof:name":"Safi S.a.",
    "wof:placetype":"venue"
},
  "geometry": {"coordinates":[2.418348,48.723915],"type":"Point"}
}