{
  "type": "Feature",
  "properties": {
    "iso:country":"FR",
    "sg:address":"43 Bd Du 11 Novembre 1918 69100 Villeurbanne",
    "sg:classifiers":[
        {
            "category":"Professional",
            "subcategory":"Business Services",
            "type":"Services"
        }
    ],
    "sg:phone":"+33 4 72 69 76 00",
    "sg:province":"Rhone-Alpes",
    "sg:tags":[
        "body",
        "advice"
    ],
    "wof:name":"Ezus Lyon I",
    "wof:placetype":"venue"
},
  "geometry": {"coordinates":[4.863726,45.77906],"type":"Point"}
}