{
  "type": "Feature",
  "properties": {
    "iso:country":"FR",
    "sg:address":"Zac Du Min Impasse Du Pont Des Sommiers 84300 Cavaillon",
    "sg:classifiers":[
        {
            "category":"Professional",
            "subcategory":"Engineering",
            "type":"Services"
        }
    ],
    "sg:phone":"+33 4 90 78 38 68",
    "sg:province":"Languedoc-Roussillon",
    "sg:tags":[
        "machine",
        "-",
        "mechanical"
    ],
    "wof:name":"Manip'fruits",
    "wof:placetype":"venue"
},
  "geometry": {"coordinates":[5.041765,43.819195],"type":"Point"}
}