{
  "type": "Feature",
  "properties": {
    "iso:country":"FR",
    "sg:address":"129, Rue des Sagnes - Saint Andr\u00e9 Lepuy , 42210 Montrond les Bains",
    "sg:orig_category":"Non-Classified Establishments",
    "sg:phone":"+33 4 77 36 26 50",
    "sg:province":"Rhone-Alpes",
    "wof:name":"Freudenberg",
    "wof:placetype":"venue"
},
  "geometry": {"coordinates":[4.247863,45.642754],"type":"Point"}
}