{
  "type": "Feature",
  "properties": {
    "iso:country":"FR",
    "sg:address":"B.P. 504, 83041 Toulon C\u00e9dex 9^^48, Bd de Strasbourg, 83000 Toulon",
    "sg:orig_category":"Non-Classified Establishments",
    "sg:phone":"+33 4 94 09 83 77",
    "sg:province":"Provence-Alpes-C\u00f4te d'Azur",
    "wof:name":"L.b. - Lyonnaise De Banque",
    "wof:placetype":"venue"
},
  "geometry": {"coordinates":[5.930305,43.125324],"type":"Point"}
}