{
  "type": "Feature",
  "properties": {
    "addr:full":"B.P. 8, 31620 Fronton^^Rte de Montauban, 31620 Fronton Midi Pyr\u00e9n\u00e9es 31620",
    "addr:housenumber":"8",
    "addr:postcode":"31620;31620;31620",
    "addr:street":"B.P.",
    "iso:country":"FR",
    "sg:address":"B.P. 8, 31620 Fronton^^Rte de Montauban, 31620 Fronton",
    "sg:orig_category":"Non-Classified Establishments",
    "sg:phone":"+33 5 62 79 97 79",
    "sg:postcode":"31620",
    "sg:province":"Midi Pyr\u00e9n\u00e9es",
    "wof:name":"Comte De N\u00e9gret Cave De Fronton",
    "wof:placetype":"venue"
},
  "geometry": {"coordinates":[1.470783,43.738724],"type":"Point"}
}