{
  "type": "Feature",
  "properties": {
    "iso:country":"FR",
    "sg:address":"4 place de la Libert\u00e9 83000 Toulon",
    "sg:classifiers":[
        {
            "category":"Cinema",
            "subcategory":"Movie Theater",
            "type":"Entertainment"
        }
    ],
    "sg:phone":"+33 4 94 18 51 85",
    "sg:province":"Auvergne",
    "sg:tags":[
        "volume",
        "picture"
    ],
    "wof:name":"Mc Productions Sarl",
    "wof:placetype":"venue"
},
  "geometry": {"coordinates":[5.930772,43.12645],"type":"Point"}
}