{
  "type": "Feature",
  "properties": {
    "addr:full":"Place de l'Eglise le Tremblay sur Mauldre Ile de France 78490",
    "addr:postcode":"78490",
    "addr:street":"Place De L'Eglise Le Tremblay;Mauldre",
    "iso:country":"FR",
    "sg:address":"Place de l'Eglise",
    "sg:city":"le Tremblay sur Mauldre",
    "sg:orig_category":"Unclassifiable Establishments",
    "sg:phone":"+33 1 34 87 92 92",
    "sg:postcode":"78490",
    "sg:province":"Ile de France",
    "wof:name":"Ch\u00e2teau Du Tremblay",
    "wof:placetype":"venue"
},
  "geometry": {"coordinates":[1.876086,48.777752],"type":"Point"}
}