{
  "type": "Feature",
  "properties": {
    "addr:full":"Zi Kerannou 29250 St Pol De L\u00e9on Plougoulm Bretagne 29250",
    "addr:postcode":"29250;29250",
    "addr:street":"Plougoulm Bretagne",
    "iso:country":"FR",
    "sg:address":"Zi Kerannou 29250 St Pol De L\u00e9on",
    "sg:city":"Plougoulm",
    "sg:classifiers":[
        {
            "category":"Shopping",
            "type":"Retail Goods"
        }
    ],
    "sg:phone":"+33 2 98 69 10 66",
    "sg:postcode":"29250",
    "sg:province":"Bretagne",
    "sg:tags":[
        "metallurgy",
        "finished",
        "-",
        "metalworking",
        "metallic"
    ],
    "wof:name":"Quemener Chaudronnerie Soudure Maintenance Sa",
    "wof:placetype":"venue"
},
  "geometry": {"coordinates":[-3.986806,48.684654],"type":"Point"}
}