{
  "type": "Feature",
  "properties": {
    "addr:full":"22, Bd J.F. Kennedy, 28600 Luisant Luisant Centre 28600",
    "addr:housenumber":"22",
    "addr:postcode":"28600;28600",
    "addr:street":"Bd J.F. Kennedy",
    "iso:country":"FR",
    "sg:address":"22, Bd J.F. Kennedy, 28600 Luisant",
    "sg:city":"Luisant",
    "sg:orig_category":"Unclassifiable Establishments",
    "sg:phone":"+33 2 37 91 75 75",
    "sg:postcode":"28600",
    "sg:province":"Centre",
    "wof:name":"Etablissement Lorillard S.a.",
    "wof:placetype":"venue"
},
  "geometry": {"coordinates":[1.464979,48.430054],"type":"Point"}
}