{
  "type": "Feature",
  "properties": {
    "addr:full":"57, Bd Gaston Serpette, 44000 Nantes Pays de Loire",
    "addr:housenumber":"57",
    "addr:postcode":"44000",
    "addr:street":"Bd Gaston Serpette",
    "iso:country":"FR",
    "sg:address":"57, Bd Gaston Serpette, 44000 Nantes",
    "sg:orig_category":"Unclassifiable Establishments",
    "sg:phone":"+33 2 40 16 03 16",
    "sg:province":"Pays de Loire",
    "wof:name":"Photogravure De L'atlantique S.a.r.l.",
    "wof:placetype":"venue"
},
  "geometry": {"coordinates":[-1.575671,47.227936],"type":"Point"}
}