{
  "type": "Feature",
  "properties": {
    "addr:full":"5 avenue des Mondaults 33270 Floirac Floirac Aquitaine 33270",
    "addr:housenumber":"5",
    "addr:postcode":"33270;33270",
    "addr:street":"Avenue Des Mondaults",
    "iso:country":"FR",
    "sg:address":"5 avenue des Mondaults 33270 Floirac",
    "sg:city":"Floirac",
    "sg:classifiers":[
        {
            "category":"Wholesale",
            "subcategory":"Wine & Distilled Alcoholic Beverages",
            "type":"Manufacturing & Wholesale Goods"
        }
    ],
    "sg:phone":"+33 5 57 77 25 00",
    "sg:postcode":"33270",
    "sg:province":"Aquitaine",
    "sg:tags":[
        "french"
    ],
    "wof:name":"Le Marrec Vins Sa",
    "wof:placetype":"venue"
},
  "geometry": {"coordinates":[-0.504464,44.8423],"type":"Point"}
}