{
  "type": "Feature",
  "properties": {
    "addr:full":"Zone Artisanale de Bains sur Oust 35600 Redon Redon Bretagne 35600",
    "addr:postcode":"35600;35600",
    "addr:street":"Zone Artisanale De Bains Sur;Redon",
    "iso:country":"FR",
    "sg:address":"Zone Artisanale de Bains sur Oust 35600 Redon",
    "sg:city":"Redon",
    "sg:classifiers":[
        {
            "category":"Banks & Credit Unions",
            "subcategory":"Investment Brokerage",
            "type":"Services"
        }
    ],
    "sg:phone":"+33 2 99 91 76 56",
    "sg:postcode":"35600",
    "sg:province":"Bretagne",
    "sg:tags":[
        "table",
        "all-purpose",
        "roller"
    ],
    "wof:name":"S.c.m. S.a.r.l.",
    "wof:placetype":"venue"
},
  "geometry": {"coordinates":[-2.085934,47.651035],"type":"Point"}
}