{
  "type": "Feature",
  "properties": {
    "iso:country":"FR",
    "sg:address":"B.P. 9102, 95310 Saint Ouen l'Aum\u00f4ne^^8, Av. de Bourgogne - ZAC B\u00e9thunes, 95310 Saint Ouen l'Aum\u00f4ne",
    "sg:orig_category":"Non-Classified Establishments",
    "sg:phone":"+33 1 34 64 22 83",
    "sg:postcode":"95310",
    "sg:province":"Ile de France",
    "wof:name":"C.e.p. Industrie S.a.",
    "wof:placetype":"venue"
},
  "geometry": {"coordinates":[5.09797,43.781441],"type":"Point"}
}