{
  "type": "Feature",
  "properties": {
    "addr:full":"231, Rue Centre Arco, 21160 Marsannay la C\u00f4te Marsannay-la-C\u00f4te Bourgogne 21160",
    "addr:housenumber":"231",
    "addr:postcode":"21160;21160",
    "addr:street":"Rue Centre Arco",
    "iso:country":"FR",
    "sg:address":"231, Rue Centre Arco, 21160 Marsannay la C\u00f4te",
    "sg:city":"Marsannay-la-C\u00f4te",
    "sg:orig_category":"Non-Classified Establishments",
    "sg:phone":"+33 3 80 51 07 46",
    "sg:postcode":"21160",
    "sg:province":"Bourgogne",
    "wof:name":"Editions Et Communication",
    "wof:placetype":"venue"
},
  "geometry": {"coordinates":[5.009467,47.275497],"type":"Point"}
}