{
  "type": "Feature",
  "properties": {
    "addr:full":"ZI DE LA CHENOIS 54150 Briey Lorraine 54150",
    "addr:postcode":"54150;54150",
    "addr:street":"Zi De La Chenois",
    "iso:country":"FR",
    "sg:address":"ZI DE LA CHENOIS 54150 Briey",
    "sg:classifiers":[
        {
            "category":"Manufacturing",
            "subcategory":"Wood Products",
            "type":"Manufacturing & Wholesale Goods"
        }
    ],
    "sg:phone":"+33 3 82 46 28 90",
    "sg:postcode":"54150",
    "sg:province":"Lorraine",
    "sg:tags":[
        "lumber"
    ],
    "wof:name":"Briey Bois Sarl",
    "wof:placetype":"venue"
},
  "geometry": {"coordinates":[5.93833,49.24958],"type":"Point"}
}