{
  "type": "Feature",
  "properties": {
    "iso:country":"FR",
    "sg:address":"20, Rue Jean Jaur\u00e9s, 59117 Wervicq Sud",
    "sg:orig_category":"Unclassifiable Establishments",
    "sg:phone":"+33 3 20 63 14 14",
    "sg:province":"Nord Pas-de-Calais",
    "wof:name":"Dalle Hygi\u00e8ne S.a.",
    "wof:placetype":"venue"
},
  "geometry": {"coordinates":[3.043268,50.769268],"type":"Point"}
}