{
  "type": "Feature",
  "properties": {
    "iso:country":"FR",
    "sg:address":"B.P. 9",
    "sg:city":"Persan C\u00e9dex^^Hameau de la Croix Madelon 95340 Persan",
    "sg:orig_category":"Non-Classified Establishments",
    "sg:phone":"+33 1 39 37 40 40",
    "sg:postcode":"95340",
    "sg:province":"Ile de France",
    "wof:name":"Victor Martinet Et Compagnie S.a.",
    "wof:placetype":"venue"
},
  "geometry": {"coordinates":[2.276365,49.151005],"type":"Point"}
}