{
  "type": "Feature",
  "properties": {
    "iso:country":"FR",
    "sg:address":"B.P. 33, 01460 Montr\u00e9al la Cluse^^ZI du Musinet, 01460 Montr\u00e9al la Cluse",
    "sg:orig_category":"Non-Classified Establishments",
    "sg:phone":"+33 4 74 76 29 67",
    "sg:postcode":"01460",
    "sg:province":"Rhone-Alpes",
    "wof:name":"Zedes S.a.",
    "wof:placetype":"venue"
},
  "geometry": {"coordinates":[5.55338,46.177399],"type":"Point"}
}