{
  "type": "Feature",
  "properties": {
    "iso:country":"FR",
    "sg:address":"B.P. 177, 62220 Carvin^^CD 160 - Parc d'Activit\u00e9s, 62220 Carvin",
    "sg:orig_category":"Non-Classified Establishments",
    "sg:phone":"+33 3 21 74 85 00",
    "sg:postcode":"62220",
    "sg:province":"Nord Pas-de-Calais",
    "wof:name":"Citernord S.a.",
    "wof:placetype":"venue"
},
  "geometry": {"coordinates":[2.957716,50.501862],"type":"Point"}
}