{
  "type": "Feature",
  "properties": {
    "addr:full":"46330 Saint G\u00e9ry Midi Pyr\u00e9n\u00e9es 46330",
    "addr:housenumber":"46330",
    "addr:postcode":"46330",
    "addr:street":"Saint Ge\u0301Ry Midi Pyre\u0301Ne\u0301Es",
    "iso:country":"FR",
    "sg:address":"46330 Saint G\u00e9ry",
    "sg:orig_category":"Non-Classified Establishments",
    "sg:phone":"+33 5 65 31 40 03",
    "sg:postcode":"46330",
    "sg:province":"Midi Pyr\u00e9n\u00e9es",
    "wof:name":"Etablissements Decremps S.a.",
    "wof:placetype":"venue"
},
  "geometry": {"coordinates":[1.577568,44.478458],"type":"Point"}
}