{
  "type": "Feature",
  "properties": {
    "addr:full":"20 Rue Gauthey 75017 Paris Ile de France 75017",
    "addr:housenumber":"20",
    "addr:postcode":"75017;75017",
    "addr:street":"Rue Gauthey",
    "iso:country":"FR",
    "sg:address":"20 Rue Gauthey 75017 Paris",
    "sg:classifiers":[
        {
            "category":"Wholesale",
            "subcategory":"Medical Equipment & Supplies",
            "type":"Manufacturing & Wholesale Goods"
        }
    ],
    "sg:phone":"+33 1 42 29 89 69",
    "sg:postcode":"75017",
    "sg:province":"Ile de France",
    "sg:tags":[
        "instrument",
        "health",
        "-",
        "precision"
    ],
    "wof:name":"Bgm",
    "wof:placetype":"venue"
},
  "geometry": {"coordinates":[2.320879,48.891895],"type":"Point"}
}