{
  "type": "Feature",
  "properties": {
    "addr:full":"81, Rue Roger Salengro, 59112 Annoeullin Nord Pas-de-Calais",
    "addr:housenumber":"81",
    "addr:postcode":"59112",
    "addr:street":"Rue Roger Salengro",
    "iso:country":"FR",
    "sg:address":"81, Rue Roger Salengro, 59112 Annoeullin",
    "sg:orig_category":"Unclassifiable Establishments",
    "sg:phone":"+33 3 20 85 58 92",
    "sg:province":"Nord Pas-de-Calais",
    "wof:name":"Dufrasne Bruno S.a.",
    "wof:placetype":"venue"
},
  "geometry": {"coordinates":[2.940752,50.531258],"type":"Point"}
}