{
  "type": "Feature",
  "properties": {
    "iso:country":"FR",
    "sg:address":"Route De Marcilly Jardin D'Entreprises 41300 Selles Saint Denis",
    "sg:city":"La Fert\u00e9-Imbault",
    "sg:classifiers":[
        {
            "category":"Manufacturing",
            "subcategory":"Wood Products",
            "type":"Manufacturing & Wholesale Goods"
        }
    ],
    "sg:phone":"+33 2 54 94 17 00",
    "sg:postcode":"41300",
    "sg:province":"Centre",
    "sg:tags":[
        "professional",
        "furniture"
    ],
    "wof:name":"Ateliers Hubert Taillibert Sa",
    "wof:placetype":"venue"
},
  "geometry": {"coordinates":[1.923864,47.393696],"type":"Point"}
}