{
  "type": "Feature",
  "properties": {
    "iso:country":"FR",
    "sg:address":"90, Rue de la Victoire, 75009 Paris",
    "sg:orig_category":"Non-Classified Establishments",
    "sg:phone":"+33 1 48 74 30 78",
    "sg:province":"Ile de France",
    "wof:name":"M.s. Victoire S.a.r.l.",
    "wof:placetype":"venue"
},
  "geometry": {"coordinates":[2.33112,48.875046],"type":"Point"}
}