{
  "type": "Feature",
  "properties": {
    "iso:country":"FR",
    "sg:address":"73, Rue Saint Antoine, 62370 Ruminghem",
    "sg:orig_category":"Non-Classified Establishments",
    "sg:phone":"+33 3 21 82 37 20",
    "sg:postcode":"62370",
    "sg:province":"Nord Pas-de-Calais",
    "wof:name":"Demoor Et Colin S.a.r.l.",
    "wof:placetype":"venue"
},
  "geometry": {"coordinates":[2.162907,50.854641],"type":"Point"}
}