{
  "type": "Feature",
  "properties": {
    "iso:country":"FR",
    "sg:address":"27 Rue Albert Et Paul Touvenin 18100 Vierzon",
    "sg:city":"Vierzon",
    "sg:classifiers":[
        {
            "category":"Shopping",
            "type":"Retail Goods"
        }
    ],
    "sg:phone":"+33 2 48 52 95 00",
    "sg:postcode":"18100",
    "sg:province":"Centre",
    "sg:tags":[
        "metallurgy",
        "finished",
        "-",
        "metalworking",
        "metallic"
    ],
    "wof:name":"Moules De Precision De Sologne",
    "wof:placetype":"venue"
},
  "geometry": {"coordinates":[2.108548,47.20805],"type":"Point"}
}