{
  "type": "Feature",
  "properties": {
    "iso:country":"FR",
    "sg:address":"B.P. 229, 85502 Les Herbiers C\u00e9dex^^5, Rue du Tramway, 85500 Les Herbiers",
    "sg:orig_category":"Non-Classified Establishments",
    "sg:phone":"+33 2 51 64 88 00",
    "sg:postcode":"85500",
    "sg:province":"Pays de Loire",
    "wof:name":"Chaussures Arvi S.a.",
    "wof:placetype":"venue"
},
  "geometry": {"coordinates":[-1.019829,46.815769],"type":"Point"}
}