{
  "type": "Feature",
  "properties": {
    "addr:full":"2 Rue Ambroise Par\u00e9 69800 St Priest Rhone-Alpes 69800",
    "addr:housenumber":"2",
    "addr:postcode":"69800;69800",
    "addr:street":"Rue Ambroise Pare\u0301",
    "iso:country":"FR",
    "sg:address":"2 Rue Ambroise Par\u00e9 69800 St Priest",
    "sg:classifiers":[
        {
            "category":"Manufacturing",
            "subcategory":"Tools & Machinery",
            "type":"Manufacturing & Wholesale Goods"
        }
    ],
    "sg:phone":"+33 4 72 22 29 50",
    "sg:postcode":"69800",
    "sg:province":"Rhone-Alpes",
    "sg:tags":[
        "metallurgy",
        "metalworking"
    ],
    "wof:name":"Obi Sa",
    "wof:placetype":"venue"
},
  "geometry": {"coordinates":[4.97419,45.718056],"type":"Point"}
}