{
  "type": "Feature",
  "properties": {
    "iso:country":"FR",
    "sg:address":"Rue du Fond des Roches - ZA les 4 Arbres",
    "sg:city":"Elancourt",
    "sg:orig_category":"Unclassifiable Establishments",
    "sg:phone":"+33 1 30 13 09 90",
    "sg:postcode":"78990",
    "sg:province":"Ile de France",
    "wof:name":"Inforquin S.a.",
    "wof:placetype":"venue"
},
  "geometry": {"coordinates":[1.949475,48.768543],"type":"Point"}
}