{
  "type": "Feature",
  "properties": {
    "addr:full":"80 Avenue De La Marne 92546 Montrouge Midi Pyr\u00e9n\u00e9es",
    "addr:housenumber":"80",
    "addr:postcode":"92546",
    "addr:street":"Avenue De La Marne",
    "iso:country":"FR",
    "sg:address":"80 Avenue De La Marne 92546 Montrouge",
    "sg:classifiers":[
        {
            "category":"Professional",
            "subcategory":"Printing & Photocopies",
            "type":"Services"
        }
    ],
    "sg:phone":"+33 1 40 92 68 68",
    "sg:province":"Midi Pyr\u00e9n\u00e9es",
    "sg:tags":[
        "publishing"
    ],
    "wof:name":"Editions Legislatives Sa",
    "wof:placetype":"venue"
},
  "geometry": {"coordinates":[2.31993,48.818401],"type":"Point"}
}