{
  "type": "Feature",
  "properties": {
    "addr:full":"3, Rue Ren\u00e9 Razel, 91400 Saclay Ile de France 91400",
    "addr:housenumber":"3",
    "addr:postcode":"91400;ile;91400",
    "addr:street":"Rue Rene\u0301 Razel;France",
    "iso:country":"FR",
    "sg:address":"3, Rue Ren\u00e9 Razel, 91400 Saclay",
    "sg:orig_category":"Non-Classified Establishments",
    "sg:phone":"+33 1 69 85 69 85",
    "sg:postcode":"91400",
    "sg:province":"Ile de France",
    "wof:name":"Entreprise Razel Fr\u00e8res S.a.",
    "wof:placetype":"venue"
},
  "geometry": {"coordinates":[2.168019,48.734299],"type":"Point"}
}