{
  "type": "Feature",
  "properties": {
    "addr:full":"702, Rue du Pont Rouge, 59236 Frelinghien Nord Pas-de-Calais",
    "addr:housenumber":"702",
    "addr:postcode":"59236",
    "addr:street":"Rue Du Pont Rouge",
    "iso:country":"FR",
    "sg:address":"702, Rue du Pont Rouge, 59236 Frelinghien",
    "sg:orig_category":"Unclassifiable Establishments",
    "sg:phone":"+33 3 20 48 81 78",
    "sg:province":"Nord Pas-de-Calais",
    "wof:name":"Socel Visionor S.a.",
    "wof:placetype":"venue"
},
  "geometry": {"coordinates":[2.936187,50.71785],"type":"Point"}
}