{
  "type": "Feature",
  "properties": {
    "iso:country":"FR",
    "sg:address":"2, Bd Georges Cl\u00e9menceau, 92400 Courbevoie",
    "sg:orig_category":"Unclassifiable Establishments",
    "sg:phone":"+33 1 41 16 20 00",
    "sg:province":"Ile de France",
    "wof:name":"Maritz S.a.",
    "wof:placetype":"venue"
},
  "geometry": {"coordinates":[2.274307,48.902859],"type":"Point"}
}