{
  "type": "Feature",
  "properties": {
    "addr:full":"Za 11 79800 Soudan Poitou-Charentes 79800",
    "addr:housenumber":"11",
    "addr:postcode":"79800;79800",
    "addr:street":"Za",
    "iso:country":"FR",
    "sg:address":"Za",
    "sg:city":"11 79800 Soudan",
    "sg:classifiers":[
        {
            "category":"Professional",
            "subcategory":"Engineering",
            "type":"Services"
        }
    ],
    "sg:phone":"+33 5 49 06 56 54",
    "sg:postcode":"79800",
    "sg:province":"Poitou-Charentes",
    "sg:tags":[
        "machine",
        "-",
        "mechanical"
    ],
    "wof:name":"Fubo (sarl)",
    "wof:placetype":"venue"
},
  "geometry": {"coordinates":[-0.160149,46.320221],"type":"Point"}
}