{
  "type": "Feature",
  "properties": {
    "addr:full":"144, Rue Paul Bellamy, 44000 Nantes Pays de Loire",
    "addr:housenumber":"144",
    "addr:postcode":"44000",
    "addr:street":"Rue Paul Bellamy",
    "iso:country":"FR",
    "sg:address":"144, Rue Paul Bellamy, 44000 Nantes",
    "sg:orig_category":"Unclassifiable Establishments",
    "sg:phone":"+33 2 40 14 30 00",
    "sg:province":"Pays de Loire",
    "wof:name":"Bureau S.a.r.l.",
    "wof:placetype":"venue"
},
  "geometry": {"coordinates":[-1.562187,47.229015],"type":"Point"}
}