{
  "type": "Feature",
  "properties": {
    "iso:country":"FR",
    "sg:address":"Traverse de la Bourgade",
    "sg:city":"Aubagne",
    "sg:orig_category":"Non-Classified Establishments",
    "sg:phone":"+33 4 91 87 70 00",
    "sg:postcode":"13400",
    "sg:province":"Provence-Alpes-C\u00f4te d'Azur",
    "wof:name":"Misa France S.a.r.l.",
    "wof:placetype":"venue"
},
  "geometry": {"coordinates":[5.523875,43.283257],"type":"Point"}
}