{
  "type": "Feature",
  "properties": {
    "addr:full":"Rue Jean Rostand Za De L Ormeau 77380 Combs La Ville Ile de France 77380",
    "addr:postcode":"77380;77380",
    "addr:street":"Rue Jean Rostand Za De L Ormeau",
    "iso:country":"FR",
    "sg:address":"Rue Jean Rostand Za De L Ormeau 77380 Combs La Ville",
    "sg:classifiers":[
        {
            "category":"Home & Garden",
            "subcategory":"Furniture",
            "type":"Retail Goods"
        }
    ],
    "sg:phone":"+33 1 60 60 00 33",
    "sg:postcode":"77380",
    "sg:province":"Ile de France",
    "sg:tags":[
        "household",
        "wood"
    ],
    "wof:name":"France Cadres Sa",
    "wof:placetype":"venue"
},
  "geometry": {"coordinates":[2.555598,48.665943],"type":"Point"}
}