{
  "type": "Feature",
  "properties": {
    "addr:full":"44, Mont\u00e9e des Acacias, 01700 Beynost Rhone-Alpes 01700",
    "addr:housenumber":"44",
    "addr:postcode":"01700;01700",
    "addr:street":"Monte\u0301E Des Acacias",
    "iso:country":"FR",
    "sg:address":"44, Mont\u00e9e des Acacias, 01700 Beynost",
    "sg:orig_category":"Non-Classified Establishments",
    "sg:phone":"+33 4 72 25 83 71",
    "sg:postcode":"01700",
    "sg:province":"Rhone-Alpes",
    "wof:name":"Entreprise Cortinovis S.a.",
    "wof:placetype":"venue"
},
  "geometry": {"coordinates":[5.007586,45.83786],"type":"Point"}
}