{
  "type": "Feature",
  "properties": {
    "addr:full":"40 Rue Lucette Et Ren\u00e9 Desgrand 69100 Villeurbanne Rhone-Alpes 69100",
    "addr:housenumber":"40",
    "addr:postcode":"69100;69100",
    "addr:street":"Rue Lucette Et Rene\u0301 Desgrand",
    "iso:country":"FR",
    "sg:address":"40 Rue Lucette Et Ren\u00e9 Desgrand 69100 Villeurbanne",
    "sg:classifiers":[
        {
            "category":"Building & Trades",
            "subcategory":"Construction",
            "type":"Services"
        }
    ],
    "sg:phone":"+33 4 78 79 49 00",
    "sg:postcode":"69100",
    "sg:province":"Rhone-Alpes",
    "sg:tags":[
        "work",
        "public"
    ],
    "wof:name":"Gantelet Galaberthier",
    "wof:placetype":"venue"
},
  "geometry": {"coordinates":[4.900907,45.785324],"type":"Point"}
}