{
  "type": "Feature",
  "properties": {
    "addr:full":"All\u00e9e du Plateau - ZI Nord de Torcy Torcy Ile de France 77200",
    "addr:postcode":"77200",
    "addr:street":"Alle\u0301E Du Plateau Zi Nord De Torcy",
    "iso:country":"FR",
    "sg:address":"All\u00e9e du Plateau - ZI Nord de Torcy",
    "sg:city":"Torcy",
    "sg:orig_category":"Unclassifiable Establishments",
    "sg:phone":"+33 1 60 05 56 43",
    "sg:postcode":"77200",
    "sg:province":"Ile de France",
    "wof:name":"A.t.r. S.a.r.l. - Atelier Technique De Reprographie",
    "wof:placetype":"venue"
},
  "geometry": {"coordinates":[2.651845,48.849575],"type":"Point"}
}