{
  "type": "Feature",
  "properties": {
    "iso:country":"FR",
    "sg:address":"35 Av Marcel Dassault Zi La Plaine 31500 Toulouse",
    "sg:classifiers":[
        {
            "category":"Utilities",
            "subcategory":"Electric",
            "type":"Services"
        }
    ],
    "sg:phone":"+33 5 62 47 35 00",
    "sg:postcode":"31500",
    "sg:province":"Midi Pyr\u00e9n\u00e9es",
    "sg:tags":[
        "electricity",
        "electronic",
        "electrical",
        "equipment"
    ],
    "wof:name":"Sarel",
    "wof:placetype":"venue"
},
  "geometry": {"coordinates":[1.47517,43.60207],"type":"Point"}
}