{
  "type": "Feature",
  "properties": {
    "iso:country":"FR",
    "sg:address":"5 Rue Des Clouzeaux Pi De La Vertonne 44120 Vertou",
    "sg:orig_category":"Animals and breeding Games and entertainment Health - equipments and instruments Miscellaneous Produ",
    "sg:phone":"+33 2 40 03 24 17",
    "sg:postcode":"44120",
    "sg:province":"Pays de Loire",
    "wof:name":"Barbot Genia Sa",
    "wof:placetype":"venue"
},
  "geometry": {"coordinates":[-1.468059,47.137573],"type":"Point"}
}