{
  "type": "Feature",
  "properties": {
    "iso:country":"FR",
    "sg:address":"49 Avenue De L Europe 07100 Annonay",
    "sg:classifiers":[
        {
            "category":"Professional",
            "subcategory":"Printing & Photocopies",
            "type":"Services"
        }
    ],
    "sg:phone":"+33 4 75 69 25 80",
    "sg:postcode":"07100",
    "sg:province":"Rhone-Alpes",
    "sg:tags":[
        "publishing"
    ],
    "wof:name":"Societe D'edition Du Reveil Du Vivarais",
    "wof:placetype":"venue"
},
  "geometry": {"coordinates":[4.668495,45.245186],"type":"Point"}
}