{
  "type": "Feature",
  "properties": {
    "addr:full":"49 Avenue De L Europe 07100 Annonay Rhone-Alpes 07100",
    "addr:housenumber":"49",
    "addr:postcode":"07100;07100",
    "addr:street":"Avenue De L Europe",
    "iso:country":"FR",
    "sg:address":"49 Avenue De L Europe 07100 Annonay",
    "sg:classifiers":[
        {
            "category":"Professional",
            "subcategory":"Printing & Photocopies",
            "type":"Services"
        }
    ],
    "sg:phone":"+33 4 75 69 25 80",
    "sg:postcode":"07100",
    "sg:province":"Rhone-Alpes",
    "sg:tags":[
        "publishing"
    ],
    "wof:name":"Societe D'edition Du Reveil Du Vivarais",
    "wof:placetype":"venue"
},
  "geometry": {"coordinates":[4.668495,45.245186],"type":"Point"}
}