{
  "type": "Feature",
  "properties": {
    "addr:full":"Bd du Midi - Immeuble Rouen Oc\u00e9an Rouen Haute Normandie 76100",
    "addr:postcode":"76100",
    "addr:street":"Bd Du Midi",
    "iso:country":"FR",
    "sg:address":"Bd du Midi - Immeuble Rouen Oc\u00e9an",
    "sg:city":"Rouen",
    "sg:orig_category":"Unclassifiable Establishments",
    "sg:phone":"+33 2 35 58 40 40",
    "sg:postcode":"76100",
    "sg:province":"Haute Normandie",
    "wof:name":"Saga Trans S.a.",
    "wof:placetype":"venue"
},
  "geometry": {"coordinates":[1.036619,49.431416],"type":"Point"}
}