{
  "type": "Feature",
  "properties": {
    "addr:full":"1 Rue de l'Europe de Font Ratel 38640 CLAIX Rhone-Alpes 38640",
    "addr:housenumber":"1",
    "addr:postcode":"38640;38640",
    "addr:street":"Rue De L'Europe De Font Ratel",
    "iso:country":"FR",
    "sg:address":"1 Rue de l'Europe",
    "sg:city":"de Font Ratel 38640 CLAIX",
    "sg:classifiers":[
        {
            "category":"Professional",
            "subcategory":"Research",
            "type":"Services"
        }
    ],
    "sg:phone":"+33 4 76 98 68 31",
    "sg:postcode":"38640",
    "sg:province":"Rhone-Alpes",
    "sg:tags":[
        "recorder",
        "recorders",
        "chart",
        "measurement"
    ],
    "wof:name":"Bio-logic S.a",
    "wof:placetype":"venue"
},
  "geometry": {"coordinates":[5.681641,45.122978],"type":"Point"}
}