{
  "type": "Feature",
  "properties": {
    "addr:full":"B.P. 4, 71301 Montceau les Mines C\u00e9dex^^Zone Industrielle de la Saule, 71300 Montceau les Mines Saint-Berain-sous-Sanvignes Bourgogne 71300",
    "addr:housenumber":"4",
    "addr:postcode":"71301;71300;71300",
    "addr:street":"B.P.;Saule;Bourgogne",
    "iso:country":"FR",
    "sg:address":"B.P. 4, 71301 Montceau les Mines C\u00e9dex^^Zone Industrielle de la Saule, 71300 Montceau les Mines",
    "sg:city":"Saint-Berain-sous-Sanvignes",
    "sg:orig_category":"Non-Classified Establishments",
    "sg:phone":"+33 3 85 67 92 92",
    "sg:postcode":"71300",
    "sg:province":"Bourgogne",
    "wof:name":"C.m.c. Saudin S.a. - Construction M\u00e9canique Chaudronnerie",
    "wof:placetype":"venue"
},
  "geometry": {"coordinates":[4.498485,46.618446],"type":"Point"}
}