{
  "type": "Feature",
  "properties": {
    "addr:full":"8 rue Guicherie 41170 CHOUE Choue Centre 41170",
    "addr:housenumber":"8;choue",
    "addr:postcode":"41170;41170",
    "addr:street":"Rue Guicherie",
    "iso:country":"FR",
    "sg:address":"8 rue Guicherie 41170 CHOUE",
    "sg:city":"Choue",
    "sg:orig_category":"Poultry, Slaughtered",
    "sg:phone":"+33 2 54 80 86 06",
    "sg:postcode":"41170",
    "sg:province":"Centre",
    "wof:name":"Gauthier Sa",
    "wof:placetype":"venue"
},
  "geometry": {"coordinates":[0.924962,47.997513],"type":"Point"}
}