{
  "type": "Feature",
  "properties": {
    "addr:full":"ZA les Florelites - Les Grandes Ormes Saint Fargeau Ponthierry Ile de France 77310",
    "addr:postcode":"77310",
    "addr:street":"Za Les Florelites Les Grandes Ormes",
    "iso:country":"FR",
    "sg:address":"ZA les Florelites - Les Grandes Ormes",
    "sg:city":"Saint Fargeau Ponthierry",
    "sg:orig_category":"Non-Classified Establishments",
    "sg:phone":"+33 1 60 65 67 20",
    "sg:postcode":"77310",
    "sg:province":"Ile de France",
    "wof:name":"A.t.c. S.a.r.l. - Assistance Technique Commerciale",
    "wof:placetype":"venue"
},
  "geometry": {"coordinates":[2.545845,48.529476],"type":"Point"}
}