{
  "type": "Feature",
  "properties": {
    "iso:country":"FR",
    "sg:address":"12 rue Marquiset 70800 Fontaine les Luxeuil",
    "sg:classifiers":[
        {
            "category":"Shopping Center",
            "type":"Public Place"
        }
    ],
    "sg:phone":"+33 3 84 93 33 50",
    "sg:postcode":"70800",
    "sg:province":"Franche Comt\u00e9",
    "sg:tags":[
        "aluminium",
        "casting"
    ],
    "wof:name":"Nouvelle Fero Sa",
    "wof:placetype":"venue"
},
  "geometry": {"coordinates":[6.33043,47.861954],"type":"Point"}
}