{
  "type": "Feature",
  "properties": {
    "addr:full":"41 Grande Rue 51270 Etoges Champagne 51270",
    "addr:housenumber":"41",
    "addr:postcode":"51270;51270",
    "addr:street":"Grande Rue;Champagne",
    "iso:country":"FR",
    "sg:address":"41 Grande Rue 51270 Etoges",
    "sg:classifiers":[
        {
            "category":"Food Court",
            "type":"Food & Drink"
        }
    ],
    "sg:phone":"+33 3 26 59 30 50",
    "sg:postcode":"51270",
    "sg:province":"Champagne",
    "sg:tags":[
        "product",
        "related"
    ],
    "wof:name":"Grongnet Guy",
    "wof:placetype":"venue"
},
  "geometry": {"coordinates":[3.809183,48.924282],"type":"Point"}
}