{
  "type": "Feature",
  "properties": {
    "iso:country":"FR",
    "sg:address":"Za Kermarquer 56470 La Trinit\u00e9 Sur Mer",
    "sg:city":"Saint-Philibert",
    "sg:classifiers":[
        {
            "category":"Utilities",
            "subcategory":"Telephone",
            "type":"Services"
        }
    ],
    "sg:phone":"+33 2 97 55 88 39",
    "sg:postcode":"56470",
    "sg:province":"Bretagne",
    "sg:tags":[
        "telecommunication"
    ],
    "wof:name":"Sitel Services France",
    "wof:placetype":"venue"
},
  "geometry": {"coordinates":[-3.026583,47.585464],"type":"Point"}
}