{
  "type": "Feature",
  "properties": {
    "addr:full":"B.P. 73, 63405 Chamali\u00e8res C\u00e9dex^^12 bis, Av. Thermale, 63400 Chamali\u00e8res Chamali\u00e8res Auvergne 63400",
    "addr:postcode":"63405;63400;63400",
    "addr:street":"B.P. 73;Av. Thermale",
    "iso:country":"FR",
    "sg:address":"B.P. 73, 63405 Chamali\u00e8res C\u00e9dex^^12 bis, Av. Thermale, 63400 Chamali\u00e8res",
    "sg:city":"Chamali\u00e8res",
    "sg:orig_category":"Non-Classified Establishments",
    "sg:phone":"+33 4 73 19 23 23",
    "sg:postcode":"63400",
    "sg:province":"Auvergne",
    "wof:name":"Cr\u00e9ations Artistiques S.a.",
    "wof:placetype":"venue"
},
  "geometry": {"coordinates":[3.06912,45.77533],"type":"Point"}
}