{
  "type": "Feature",
  "properties": {
    "iso:country":"FR",
    "sg:address":"55 Av Edouard Herriot 82303 Caussade Cedex",
    "sg:classifiers":[
        {
            "category":"Utilities",
            "subcategory":"Electric",
            "type":"Services"
        }
    ],
    "sg:phone":"+33 5 63 93 14 98",
    "sg:province":"Midi Pyr\u00e9n\u00e9es",
    "sg:tags":[
        "electricity",
        "electronic",
        "electrical",
        "equipment"
    ],
    "wof:name":"Apem",
    "wof:placetype":"venue"
},
  "geometry": {"coordinates":[1.52453,44.150002],"type":"Point"}
}