{
  "type": "Feature",
  "properties": {
    "addr:full":"B.P. 11, 67127 Molsheim C\u00e9dex^^4, Rue Denis Papin - Zone Industrielle, 67120 Duttlenheim Molsheim Alsace 67120",
    "addr:postcode":"67127;67120;67120",
    "addr:street":"B.P. 11;Rue Denis Papin Zone Industrielle",
    "iso:country":"FR",
    "sg:address":"B.P. 11, 67127 Molsheim C\u00e9dex^^4, Rue Denis Papin - Zone Industrielle, 67120 Duttlenheim",
    "sg:city":"Molsheim",
    "sg:orig_category":"Non-Classified Establishments",
    "sg:phone":"+33 3 88 38 26 57",
    "sg:postcode":"67120",
    "sg:province":"Alsace",
    "wof:name":"Rustyle Heinzmann Et Compagnie S.a.r.l.",
    "wof:placetype":"venue"
},
  "geometry": {"coordinates":[7.490672,48.540382],"type":"Point"}
}