{
  "type": "Feature",
  "properties": {
    "iso:country":"FR",
    "sg:address":"63300 Escoutoux",
    "sg:city":"Escoutoux",
    "sg:orig_category":"Unclassifiable Establishments",
    "sg:phone":"+33 4 73 80 08 89",
    "sg:postcode":"63300",
    "sg:province":"Auvergne",
    "wof:name":"Soci\u00e9t\u00e9 D'exploitation - S.a.r.l. - Thuel Chassaigne",
    "wof:placetype":"venue"
},
  "geometry": {"coordinates":[3.563396,45.82058],"type":"Point"}
}