{
  "type": "Feature",
  "properties": {
    "addr:full":"5, Rue du Pr Georges Chabot, 21600 Longvic Longvic Bourgogne 21600",
    "addr:housenumber":"5",
    "addr:postcode":"21600;21600",
    "addr:street":"Rue Du Pr Georges Chabot",
    "iso:country":"FR",
    "sg:address":"5, Rue du Pr Georges Chabot, 21600 Longvic",
    "sg:city":"Longvic",
    "sg:orig_category":"Unclassifiable Establishments",
    "sg:phone":"+33 3 80 67 76 07",
    "sg:postcode":"21600",
    "sg:province":"Bourgogne",
    "wof:name":"Protomatisme S.a.",
    "wof:placetype":"venue"
},
  "geometry": {"coordinates":[5.038486,47.291164],"type":"Point"}
}