{
  "type": "Feature",
  "properties": {
    "iso:country":"FR",
    "sg:address":"Av D'Auvergne Zi Du Breuil 43100 Brioude",
    "sg:city":"Brioude",
    "sg:classifiers":[
        {
            "category":"Manufacturing",
            "subcategory":"Food",
            "type":"Manufacturing & Wholesale Goods"
        }
    ],
    "sg:phone":"+33 4 71 74 93 17",
    "sg:postcode":"43100",
    "sg:province":"Auvergne",
    "sg:tags":[
        "preserve",
        "product",
        "related"
    ],
    "wof:name":"Saumonerie St Ferreol Sarl",
    "wof:placetype":"venue"
},
  "geometry": {"coordinates":[3.373687,45.32209],"type":"Point"}
}