{
  "type": "Feature",
  "properties": {
    "iso:country":"FR",
    "sg:address":"2, En Bonne Ruelle, 57000 Metz",
    "sg:orig_category":"Non-Classified Establishments",
    "sg:phone":"+33 3 87 75 23 33",
    "sg:province":"Lorraine",
    "wof:name":"Pic Vert Communication S.a.r.l.",
    "wof:placetype":"venue"
},
  "geometry": {"coordinates":[6.173529,49.116753],"type":"Point"}
}