{
  "type": "Feature",
  "properties": {
    "addr:full":"1945 Av Du Mar\u00e9chal Juin 30900 N\u00eemes Languedoc-Roussillon 30900",
    "addr:housenumber":"1945",
    "addr:postcode":"30900;30900",
    "addr:street":"Av Du Mare\u0301Chal Juin",
    "iso:country":"FR",
    "sg:address":"1945 Av Du Mar\u00e9chal Juin 30900 N\u00eemes",
    "sg:classifiers":[
        {
            "category":"Banks & Credit Unions",
            "subcategory":"Financial Services",
            "type":"Services"
        }
    ],
    "sg:phone":"+33 4 66 29 06 15",
    "sg:postcode":"30900",
    "sg:province":"Languedoc-Roussillon",
    "sg:tags":[
        "banking",
        "finance",
        "insurance"
    ],
    "wof:name":"B.c.a Groupement D'interet Economique Sa",
    "wof:placetype":"venue"
},
  "geometry": {"coordinates":[4.335946,43.815109],"type":"Point"}
}