{
  "type": "Feature",
  "properties": {
    "addr:full":"65, Chemin de La Mouche - ZI la Mouche, 69230 Saint Genis Laval Rhone-Alpes 69230",
    "addr:housenumber":"65",
    "addr:postcode":"69230;69230",
    "addr:street":"Chemin De La;La;Genis;Rhone-Alpes",
    "iso:country":"FR",
    "sg:address":"65, Chemin de La Mouche - ZI la Mouche, 69230 Saint Genis Laval",
    "sg:orig_category":"Non-Classified Establishments",
    "sg:phone":"+33 4 72 39 20 66",
    "sg:postcode":"69230",
    "sg:province":"Rhone-Alpes",
    "wof:name":"Arc Rigollot S.a.r.l.",
    "wof:placetype":"venue"
},
  "geometry": {"coordinates":[4.79296,45.694736],"type":"Point"}
}