{
  "type": "Feature",
  "properties": {
    "addr:full":"218 rue Caponi\u00e8re 14000 Caen Caen Basse Normandie 14000",
    "addr:housenumber":"218",
    "addr:postcode":"14000;14000",
    "addr:street":"Rue Caponie\u0300Re",
    "iso:country":"FR",
    "sg:address":"218 rue Caponi\u00e8re 14000 Caen",
    "sg:city":"Caen",
    "sg:classifiers":[
        {
            "category":"Military Area",
            "subcategory":"Restricted Area",
            "type":"Public Place"
        }
    ],
    "sg:phone":"+33 2 31 74 41 35",
    "sg:postcode":"14000",
    "sg:province":"Basse Normandie",
    "sg:tags":[
        "rustic",
        "country",
        "style",
        "furniture"
    ],
    "wof:name":"Les Si\u00e8ges Bree France S.a.",
    "wof:placetype":"venue"
},
  "geometry": {"coordinates":[-0.387988,49.175053],"type":"Point"}
}