{
  "type": "Feature",
  "properties": {
    "iso:country":"FR",
    "sg:address":"ZA de Fiancey",
    "sg:city":"Livron sur Dr\u00f4me",
    "sg:orig_category":"Unclassifiable Establishments",
    "sg:phone":"+33 4 75 61 00 67",
    "sg:postcode":"26250",
    "sg:province":"Rhone-Alpes",
    "wof:name":"Frisomat S.a.",
    "wof:placetype":"venue"
},
  "geometry": {"coordinates":[4.84206,44.771477],"type":"Point"}
}