{
  "type": "Feature",
  "properties": {
    "addr:full":"19 Place Etienne Pernet, 75740 Paris Cedex 15, Dept 75 Ile de France",
    "addr:housenumber":"19",
    "addr:postcode":"75740",
    "addr:street":"Place Etienne Pernet;Ile De France",
    "iso:country":"FR",
    "sg:address":"19 Place Etienne Pernet, 75740 Paris Cedex 15, Dept 75",
    "sg:classifiers":[
        {
            "category":"Banks & Credit Unions",
            "subcategory":"Bank",
            "type":"Services"
        }
    ],
    "sg:phone":"+33 1 44 12 86 86",
    "sg:province":"Ile de France",
    "wof:name":"Loxxia Credit",
    "wof:placetype":"venue"
},
  "geometry": {"coordinates":[2.292608,48.842667],"type":"Point"}
}