{
  "type": "Feature",
  "properties": {
    "addr:full":"3, All\u00e9e d'Auteuil - Parc Club de Nancy-Brabois, 54500 Vandoeuvre l\u00e8s Nancy Lorraine",
    "addr:housenumber":"3",
    "addr:postcode":"54500",
    "addr:street":"Alle\u0301E D'Auteuil Parc Club",
    "iso:country":"FR",
    "sg:address":"3, All\u00e9e d'Auteuil - Parc Club de Nancy-Brabois, 54500 Vandoeuvre l\u00e8s Nancy",
    "sg:orig_category":"Non-Classified Establishments",
    "sg:phone":"+33 3 83 44 45 46",
    "sg:province":"Lorraine",
    "wof:name":"Missler Infoest S.a.r.l.",
    "wof:placetype":"venue"
},
  "geometry": {"coordinates":[6.13704,48.653759],"type":"Point"}
}