{
  "type": "Feature",
  "properties": {
    "addr:full":"4, Rue de l'Industrie - Z.I., 39270 Orgelet Franche Comt\u00e9 39270",
    "addr:housenumber":"4",
    "addr:postcode":"39270;39270",
    "addr:street":"Rue De L'Industrie;Franche Comte\u0301",
    "iso:country":"FR",
    "sg:address":"4, Rue de l'Industrie - Z.I., 39270 Orgelet",
    "sg:orig_category":"CAO et/ou FAO Fraisage CN M\u00e9canique de pr\u00e9cision M\u00e9canique de pr\u00e9cision par CN 2, 3 et 4 axes Tourna",
    "sg:phone":"+33 3 84 25 42 42",
    "sg:postcode":"39270",
    "sg:province":"Franche Comt\u00e9",
    "wof:name":"S.m.p. Firmain P\u00e8re Et Fils S.a.r.l.",
    "wof:placetype":"venue"
},
  "geometry": {"coordinates":[5.60633,46.530197],"type":"Point"}
}