{
  "type": "Feature",
  "properties": {
    "addr:full":"Rd Pt Duboys d'Angers; Cannes; 06150 Centre",
    "addr:housenumber":"06150",
    "addr:street":"Rd",
    "iso:country":"FR",
    "sg:address":"Rd Pt Duboys d'Angers; Cannes; 06150",
    "sg:classifiers":[
        {
            "category":"Banks & Credit Unions",
            "subcategory":"Bank",
            "type":"Services"
        }
    ],
    "sg:phone":"+33 3393383376",
    "sg:province":"Centre",
    "wof:name":"Barclays Bank Plc",
    "wof:placetype":"venue"
},
  "geometry": {"coordinates":[7.026036,43.551617],"type":"Point"}
}