{
  "type": "Feature",
  "properties": {
    "iso:country":"FR",
    "sg:address":"4 R Des Fr\u00e8res Montgolfier 95500 Gonesse",
    "sg:classifiers":[
        {
            "category":"Professional",
            "subcategory":"Engineering",
            "type":"Services"
        }
    ],
    "sg:phone":"+33 1 34 53 91 71",
    "sg:postcode":"95500",
    "sg:province":"Ile de France",
    "sg:tags":[
        "machine",
        "-",
        "mechanical"
    ],
    "wof:name":"Rossi Motoreducteur",
    "wof:placetype":"venue"
},
  "geometry": {"coordinates":[2.454625,48.988781],"type":"Point"}
}