{
  "type": "Feature",
  "properties": {
    "iso:country":"FR",
    "sg:address":"42, Rue de Laborde, 75008 Paris",
    "sg:orig_category":"Unclassifiable Establishments",
    "sg:phone":"+33 1 42 93 50 03",
    "sg:province":"Ile de France",
    "wof:name":"Charrette Service S.a.",
    "wof:placetype":"venue"
},
  "geometry": {"coordinates":[2.316879,48.875584],"type":"Point"}
}