{
  "type": "Feature",
  "properties": {
    "addr:full":"1 Rue Charles Cohardy 02590 Etreillers Picardie 02590",
    "addr:housenumber":"1",
    "addr:postcode":"02590;02590",
    "addr:street":"Rue Charles Cohardy;Picardie",
    "iso:country":"FR",
    "sg:address":"1 Rue Charles Cohardy 02590 Etreillers",
    "sg:classifiers":[
        {
            "category":"Professional",
            "subcategory":"Advertising",
            "type":"Services"
        }
    ],
    "sg:phone":"+33 3 23 68 67 00",
    "sg:postcode":"02590",
    "sg:province":"Picardie",
    "sg:tags":[
        "marketing",
        "printing",
        "medium",
        "publishing",
        "communication"
    ],
    "wof:name":"Lmd Sarl",
    "wof:placetype":"venue"
},
  "geometry": {"coordinates":[3.161634,49.829987],"type":"Point"}
}