{
  "type": "Feature",
  "properties": {
    "addr:full":"Rn 88 31380 Garidech Midi Pyr\u00e9n\u00e9es 31380",
    "addr:postcode":"31380;31380",
    "addr:street":"Rn 88",
    "iso:country":"FR",
    "sg:address":"Rn 88 31380 Garidech",
    "sg:classifiers":[
        {
            "category":"Building & Trades",
            "subcategory":"Construction",
            "type":"Services"
        }
    ],
    "sg:phone":"+33 5 61 84 21 91",
    "sg:postcode":"31380",
    "sg:province":"Midi Pyr\u00e9n\u00e9es",
    "sg:tags":[
        "work",
        "public"
    ],
    "wof:name":"Scam Tp",
    "wof:placetype":"venue"
},
  "geometry": {"coordinates":[1.58427,43.681675],"type":"Point"}
}