{
  "type": "Feature",
  "properties": {
    "addr:full":"102 Quimper Bretagne 29000",
    "addr:housenumber":"102",
    "addr:postcode":"29000",
    "addr:street":"Quimper Bretagne",
    "iso:country":"FR",
    "sg:address":"102",
    "sg:city":"Quimper",
    "sg:classifiers":[
        {
            "category":"Shopping",
            "subcategory":"Crafts & Fabrics",
            "type":"Retail Goods"
        }
    ],
    "sg:phone":"+33 2 98 90 73 10",
    "sg:postcode":"29000",
    "sg:province":"Bretagne",
    "sg:tags":[
        "textile",
        "clothing"
    ],
    "wof:name":"C.a.t. Ty Hent Glaz",
    "wof:placetype":"venue"
},
  "geometry": {"coordinates":[-4.083168,47.999596],"type":"Point"}
}