{
  "type": "Feature",
  "properties": {
    "addr:full":"4, Rue Paul Vaillant Couturier, 94140 Alfortville Ile de France",
    "addr:housenumber":"4",
    "addr:postcode":"94140;ile",
    "addr:street":"Rue Paul Vaillant Couturier",
    "iso:country":"FR",
    "sg:address":"4, Rue Paul Vaillant Couturier, 94140 Alfortville",
    "sg:orig_category":"Unclassifiable Establishments",
    "sg:phone":"+33 1 43 76 36 35",
    "sg:province":"Ile de France",
    "wof:name":"Compo Film Services S.a.r.l.",
    "wof:placetype":"venue"
},
  "geometry": {"coordinates":[2.414691,48.815571],"type":"Point"}
}