{
  "type": "Feature",
  "properties": {
    "addr:full":"11, Rue du M\u00e9nillet, 60541 M\u00e9ru C\u00e9dex Pays de Loire",
    "addr:housenumber":"11",
    "addr:postcode":"60541",
    "addr:street":"Rue Du Me\u0301Nillet;Ce\u0301Dex",
    "iso:country":"FR",
    "sg:address":"11, Rue du M\u00e9nillet, 60541 M\u00e9ru C\u00e9dex",
    "sg:orig_category":"Non-Classified Establishments",
    "sg:phone":"+33 3 44 08 25 25",
    "sg:province":"Pays de Loire",
    "wof:name":"C.l.a.l. - M.s.x - S.a.",
    "wof:placetype":"venue"
},
  "geometry": {"coordinates":[2.13391,49.235592],"type":"Point"}
}