{
  "type": "Feature",
  "properties": {
    "addr:full":"17 rue du Chemin Vert 77410 Claye Souilly Ile de France 77410",
    "addr:housenumber":"17",
    "addr:postcode":"77410;77410",
    "addr:street":"Rue Du Chemin Vert",
    "iso:country":"FR",
    "sg:address":"17 rue du Chemin Vert 77410 Claye Souilly",
    "sg:classifiers":[
        {
            "category":"Shopping",
            "subcategory":"Computers & Home Electronics",
            "type":"Retail Goods"
        }
    ],
    "sg:phone":"+33 1 60 26 16 42",
    "sg:postcode":"77410",
    "sg:province":"Ile de France",
    "sg:tags":[
        "instrument",
        "electronic",
        "measurement"
    ],
    "wof:name":"A.r.m. Technologie Sarl",
    "wof:placetype":"venue"
},
  "geometry": {"coordinates":[2.6723,48.951061],"type":"Point"}
}