{
  "type": "Feature",
  "properties": {
    "addr:full":"B.P. 1395, 51064 Reims C\u00e9dex^^2bis, Impasse de Merfy, 51100 Reims Champagne",
    "addr:postcode":"51064;51100",
    "addr:street":"B.P. 1395;Impasse De Merfy",
    "iso:country":"FR",
    "sg:address":"B.P. 1395, 51064 Reims C\u00e9dex^^2bis, Impasse de Merfy, 51100 Reims",
    "sg:orig_category":"Non-Classified Establishments",
    "sg:phone":"+33 3 26 88 47 57",
    "sg:province":"Champagne",
    "wof:name":"Safig - Mdp S.a.s.",
    "wof:placetype":"venue"
},
  "geometry": {"coordinates":[4.028445,49.26284],"type":"Point"}
}