{
  "type": "Feature",
  "properties": {
    "addr:full":"6, Rue Paul Langevin, 93274 Sevran C\u00e9dex Centre",
    "addr:housenumber":"6",
    "addr:postcode":"93274",
    "addr:street":"Rue Paul Langevin",
    "iso:country":"FR",
    "sg:address":"6, Rue Paul Langevin, 93274 Sevran C\u00e9dex",
    "sg:orig_category":"Non-Classified Establishments",
    "sg:phone":"+33 1 43 84 94 83",
    "sg:province":"Centre",
    "wof:name":"Novair S.a.",
    "wof:placetype":"venue"
},
  "geometry": {"coordinates":[2.530589,48.94706],"type":"Point"}
}