{
  "type": "Feature",
  "properties": {
    "iso:country":"FR",
    "sg:address":"Parc Activites Kennedy Bta1 Rue Rud 33700 MERIGNAC",
    "sg:city":"M\u00e9rignac",
    "sg:classifiers":[
        {
            "category":"Shopping",
            "subcategory":"Books",
            "type":"Retail Goods"
        }
    ],
    "sg:phone":"+33 5 57 92 50 60",
    "sg:postcode":"33700",
    "sg:province":"Aquitaine",
    "wof:name":"Les Editions Du Capitole Sarl",
    "wof:placetype":"venue"
},
  "geometry": {"coordinates":[-0.619299,44.82597],"type":"Point"}
}