{
  "type": "Feature",
  "properties": {
    "addr:full":"RN 3 Blesmes Picardie 02400",
    "addr:postcode":"02400",
    "addr:street":"Rn 3 Blesmes Picardie",
    "iso:country":"FR",
    "sg:address":"RN 3",
    "sg:city":"Blesmes",
    "sg:orig_category":"Unclassifiable Establishments",
    "sg:phone":"+33 3 23 83 12 16",
    "sg:postcode":"02400",
    "sg:province":"Picardie",
    "wof:name":"P\u00e9pini\u00e8re Parcs Jardins Carr\u00e9 S.a",
    "wof:placetype":"venue"
},
  "geometry": {"coordinates":[3.39314,49.05019],"type":"Point"}
}