{
  "type": "Feature",
  "properties": {
    "addr:full":"ZA Marc Seguin 15130 Arpajon sur C\u00e8re Auvergne 15130",
    "addr:postcode":"15130;15130",
    "addr:street":"Za Marc Seguin",
    "iso:country":"FR",
    "sg:address":"ZA",
    "sg:city":"Marc Seguin 15130 Arpajon sur C\u00e8re",
    "sg:classifiers":[
        {
            "category":"Government",
            "subcategory":"Department Of Motor Vehicles",
            "type":"Public Place"
        }
    ],
    "sg:phone":"+33 4 71 48 15 34",
    "sg:postcode":"15130",
    "sg:province":"Auvergne",
    "sg:tags":[
        "equipment",
        "industrial",
        "transport",
        "motor-cars"
    ],
    "wof:name":"Ohlins Pierre Faucher Production Importateur Exclusif",
    "wof:placetype":"venue"
},
  "geometry": {"coordinates":[2.45937,44.90139],"type":"Point"}
}