{
  "type": "Feature",
  "properties": {
    "iso:country":"FR",
    "sg:address":"Rn 10 16430 Champniers Cedex 9",
    "sg:classifiers":[
        {
            "category":"Professional",
            "subcategory":"Engineering",
            "type":"Services"
        }
    ],
    "sg:phone":"+33 5 45 68 03 44",
    "sg:postcode":"16430",
    "sg:province":"Poitou-Charentes",
    "sg:tags":[
        "machine",
        "-",
        "mechanical"
    ],
    "wof:name":"Ets Laporte Sa",
    "wof:placetype":"venue"
},
  "geometry": {"coordinates":[0.211168,45.691833],"type":"Point"}
}