{
  "type": "Feature",
  "properties": {
    "addr:full":"5, All\u00e9e des H\u00eatres, 69760 Limonest Rhone-Alpes 69760",
    "addr:housenumber":"5",
    "addr:postcode":"69760;69760",
    "addr:street":"Alle\u0301E Des He\u0302Tres",
    "iso:country":"FR",
    "sg:address":"5, All\u00e9e des H\u00eatres, 69760 Limonest",
    "sg:orig_category":"Unclassifiable Establishments",
    "sg:phone":"+33 4 78 66 38 00",
    "sg:postcode":"69760",
    "sg:province":"Rhone-Alpes",
    "wof:name":"Carigel S.a.",
    "wof:placetype":"venue"
},
  "geometry": {"coordinates":[4.77401,45.807289],"type":"Point"}
}