{
  "type": "Feature",
  "properties": {
    "addr:full":"ZA les Molletons Monistrol sur Loire Auvergne 43120",
    "addr:postcode":"43120",
    "addr:street":"Za Les;Monistrol;Loire",
    "iso:country":"FR",
    "sg:address":"ZA les Molletons",
    "sg:city":"Monistrol sur Loire",
    "sg:orig_category":"Unclassifiable Establishments",
    "sg:phone":"+33 4 71 66 06 65",
    "sg:postcode":"43120",
    "sg:province":"Auvergne",
    "wof:name":"Imprimerie Court",
    "wof:placetype":"venue"
},
  "geometry": {"coordinates":[4.172515,45.292206],"type":"Point"}
}