{
  "type": "Feature",
  "properties": {
    "addr:full":"379, Rue des Ecoles, 59194 R\u00e2ches Nord Pas-de-Calais",
    "addr:housenumber":"379",
    "addr:postcode":"59194",
    "addr:street":"Rue Des Ecoles",
    "iso:country":"FR",
    "sg:address":"379, Rue des Ecoles, 59194 R\u00e2ches",
    "sg:orig_category":"Unclassifiable Establishments",
    "sg:phone":"+33 3 27 89 19 79",
    "sg:province":"Nord Pas-de-Calais",
    "wof:name":"Bail S.a.",
    "wof:placetype":"venue"
},
  "geometry": {"coordinates":[3.132118,50.415115],"type":"Point"}
}