{
  "type": "Feature",
  "properties": {
    "iso:country":"FR",
    "sg:address":"15, Rue du Buisson aux Fraises - ZI de la Bonde, 91741 Massy C\u00e9dex",
    "sg:orig_category":"Non-Classified Establishments",
    "sg:phone":"+33 1 60 13 04 18",
    "sg:province":"\u00cele-de-France",
    "wof:name":"Partenair S.a.",
    "wof:placetype":"venue"
},
  "geometry": {"coordinates":[2.27287,48.730301],"type":"Point"}
}