{
  "type": "Feature",
  "properties": {
    "addr:full":"21, Bd Pasteur, 75015 Paris Ile de France",
    "addr:housenumber":"21",
    "addr:postcode":"75015",
    "addr:street":"Bd Pasteur",
    "iso:country":"FR",
    "sg:address":"21, Bd Pasteur, 75015 Paris",
    "sg:orig_category":"Unclassifiable Establishments",
    "sg:phone":"+33 1 56 58 63 60",
    "sg:province":"Ile de France",
    "wof:name":"Institut Du Verre-prover S.a.",
    "wof:placetype":"venue"
},
  "geometry": {"coordinates":[2.312273,48.843937],"type":"Point"}
}