{
  "type": "Feature",
  "properties": {
    "addr:full":"92, Av. de Wagram, 75017 Paris Ile de France",
    "addr:postcode":"75017",
    "addr:street":"92 Av. De Wagram",
    "iso:country":"FR",
    "sg:address":"92, Av. de Wagram, 75017 Paris",
    "sg:orig_category":"Unclassifiable Establishments",
    "sg:phone":"+33 1 55 65 17 17",
    "sg:province":"Ile de France",
    "wof:name":"Apg-direct S.a.",
    "wof:placetype":"venue"
},
  "geometry": {"coordinates":[2.301664,48.88258],"type":"Point"}
}