{
  "type": "Feature",
  "properties": {
    "addr:full":"ZAC Actinove Thil Rhone-Alpes 01120",
    "addr:postcode":"01120",
    "addr:street":"Zac Actinove;Rhone-Alpes",
    "iso:country":"FR",
    "sg:address":"ZAC Actinove",
    "sg:city":"Thil",
    "sg:orig_category":"Non-Classified Establishments",
    "sg:phone":"+33 4 78 55 45 51",
    "sg:postcode":"01120",
    "sg:province":"Rhone-Alpes",
    "wof:name":"Tribollet S.a.",
    "wof:placetype":"venue"
},
  "geometry": {"coordinates":[5.021158,45.81501],"type":"Point"}
}