{
  "type": "Feature",
  "properties": {
    "iso:country":"FR",
    "sg:address":"3 ave du Pr\u00e9sident Wilson; Lezignan Corbi\u00e8res; 11200",
    "sg:classifiers":[
        {
            "category":"Banks & Credit Unions",
            "subcategory":"Bank",
            "type":"Services"
        }
    ],
    "sg:phone":"+33 3368270045",
    "sg:postcode":"11200",
    "sg:province":"Languedoc-Roussillon",
    "wof:name":"Banque Nationale De Paris",
    "wof:placetype":"venue"
},
  "geometry": {"coordinates":[2.808569,43.103775],"type":"Point"}
}