{
  "type": "Feature",
  "properties": {
    "iso:country":"FR",
    "sg:address":"17 Rue Edouard Branly 44980 Ste Luce Sur Loire",
    "sg:classifiers":[
        {
            "category":"Building & Trades",
            "subcategory":"Construction",
            "type":"Services"
        }
    ],
    "sg:phone":"+33 2 51 13 30 50",
    "sg:postcode":"44980",
    "sg:province":"Pays de Loire",
    "sg:tags":[
        "work",
        "public"
    ],
    "wof:name":"Trapelec Sa",
    "wof:placetype":"venue"
},
  "geometry": {"coordinates":[-1.479029,47.263371],"type":"Point"}
}