{
  "type": "Feature",
  "properties": {
    "iso:country":"FR",
    "sg:address":"112 Rue Des Erables BP 50346 Zi Paris Nord 2 95941 Roissy Cdg Cedex",
    "sg:classifiers":[
        {
            "category":"Food Court",
            "type":"Food & Drink"
        }
    ],
    "sg:phone":"+33 1 49 38 01 64",
    "sg:province":"Picardie",
    "sg:tags":[
        "product",
        "related"
    ],
    "wof:name":"Dsm Ingredients De Boulangerie",
    "wof:placetype":"venue"
},
  "geometry": {"coordinates":[2.51524,49.004028],"type":"Point"}
}