{
  "type": "Feature",
  "properties": {
    "addr:full":"All Jules Milhau Triangle Cs 19026 34967 Montpellier Cedex 2 Languedoc-Roussillon",
    "addr:postcode":"34967;cedex 2",
    "addr:street":"Triangle Cs 19026",
    "iso:country":"FR",
    "sg:address":"All Jules Milhau",
    "sg:city":"Triangle Cs 19026 34967 Montpellier Cedex 2",
    "sg:classifiers":[
        {
            "category":"Professional",
            "subcategory":"Printing & Photocopies",
            "type":"Services"
        }
    ],
    "sg:phone":"+33 4 67 06 78 78",
    "sg:province":"Languedoc-Roussillon",
    "sg:tags":[
        "publishing"
    ],
    "wof:name":"Sauramps Et Compagnie",
    "wof:placetype":"venue"
},
  "geometry": {"coordinates":[3.87927,43.608528],"type":"Point"}
}