{
  "type": "Feature",
  "properties": {
    "addr:full":"16, Rue Jean Bart, 35340 Liffr\u00e9 Liffr\u00e9 Bretagne 35340",
    "addr:housenumber":"16",
    "addr:postcode":"35340;35340",
    "addr:street":"Rue Jean Bart",
    "iso:country":"FR",
    "sg:address":"16, Rue Jean Bart, 35340 Liffr\u00e9",
    "sg:city":"Liffr\u00e9",
    "sg:orig_category":"Non-Classified Establishments",
    "sg:phone":"+33 2 99 23 50 50",
    "sg:postcode":"35340",
    "sg:province":"Bretagne",
    "wof:name":"S.v.a. - Soci\u00e9t\u00e9 Vitr\u00e9enne D'abattage",
    "wof:placetype":"venue"
},
  "geometry": {"coordinates":[-1.513419,48.212601],"type":"Point"}
}