{
  "type": "Feature",
  "properties": {
    "addr:full":"17, Rue Robertine Dubois, 02110 Seboncourt Picardie",
    "addr:housenumber":"17",
    "addr:postcode":"02110",
    "addr:street":"Rue Robertine Dubois",
    "iso:country":"FR",
    "sg:address":"17, Rue Robertine Dubois, 02110 Seboncourt",
    "sg:orig_category":"Unclassifiable Establishments",
    "sg:phone":"+33 3 23 66 03 14",
    "sg:province":"Picardie",
    "wof:name":"Lemaire Et Fils S.a.r.l.",
    "wof:placetype":"venue"
},
  "geometry": {"coordinates":[3.476257,49.953896],"type":"Point"}
}