{
  "type": "Feature",
  "properties": {
    "iso:country":"FR",
    "sg:address":"ZA de Presle",
    "sg:city":"Polliat",
    "sg:orig_category":"Unclassifiable Establishments",
    "sg:phone":"+33 4 74 30 49 92",
    "sg:postcode":"01310",
    "sg:province":"Rhone-Alpes",
    "wof:name":"Sud Est Froid S.a.r.l.",
    "wof:placetype":"venue"
},
  "geometry": {"coordinates":[5.12448,46.2495],"type":"Point"}
}