{
  "type": "Feature",
  "properties": {
    "iso:country":"FR",
    "sg:address":"26, Rue du Bois de la Rose, 74100 Ville la Grand",
    "sg:orig_category":"Non-Classified Establishments",
    "sg:phone":"+33 4 50 38 32 66",
    "sg:postcode":"74100",
    "sg:province":"Rhone-Alpes",
    "wof:name":"Laboratoire Dolisos",
    "wof:placetype":"venue"
},
  "geometry": {"coordinates":[6.278847,46.206638],"type":"Point"}
}