{
  "type": "Feature",
  "properties": {
    "iso:country":"FR",
    "sg:address":"1 Imp Du Bourrelier 44800 St Herblain",
    "sg:classifiers":[
        {
            "category":"Government",
            "subcategory":"Department Of Motor Vehicles",
            "type":"Public Place"
        }
    ],
    "sg:phone":"+33 2 40 92 18 24",
    "sg:postcode":"44800",
    "sg:province":"Pays de Loire",
    "sg:tags":[
        "equipment",
        "industrial",
        "transport",
        "motor-cars"
    ],
    "wof:name":"Safir Distribution",
    "wof:placetype":"venue"
},
  "geometry": {"coordinates":[-1.642049,47.223019],"type":"Point"}
}