{
  "type": "Feature",
  "properties": {
    "addr:full":"15, Quai Ernest Renaud, 44100 Nantes Pays de Loire",
    "addr:housenumber":"15",
    "addr:postcode":"44100",
    "addr:street":"Quai Ernest Renaud",
    "iso:country":"FR",
    "sg:address":"15, Quai Ernest Renaud, 44100 Nantes",
    "sg:orig_category":"Unclassifiable Establishments",
    "sg:phone":"+33 2 40 73 18 08",
    "sg:province":"Pays de Loire",
    "wof:name":"Coface S.a.",
    "wof:placetype":"venue"
},
  "geometry": {"coordinates":[-1.574659,47.205158],"type":"Point"}
}