{
  "type": "Feature",
  "properties": {
    "addr:full":"B.P. 106, 90400 Danjoutin^^3, Rue de la Lib\u00e9ration, 90400 Danjoutin Franche Comt\u00e9",
    "addr:housenumber":"b.p. 106",
    "addr:postcode":"90400;90400",
    "addr:street":"Rue De La Libe\u0301Ration;Franche Comte\u0301",
    "iso:country":"FR",
    "sg:address":"B.P. 106, 90400 Danjoutin^^3, Rue de la Lib\u00e9ration, 90400 Danjoutin",
    "sg:orig_category":"Non-Classified Establishments",
    "sg:phone":"+33 3 84 57 35 20",
    "sg:province":"Franche Comt\u00e9",
    "wof:name":"Tellier Electricit\u00e9 S.a.",
    "wof:placetype":"venue"
},
  "geometry": {"coordinates":[6.862866,47.618031],"type":"Point"}
}