{
  "type": "Feature",
  "properties": {
    "iso:country":"FR",
    "sg:address":"Les Terres Douces 85210 STE HERMINE",
    "sg:orig_category":"Slaughter-Houses, Abattoirs",
    "sg:phone":"+33 2 51 97 89 90",
    "sg:province":"Pays de Loire",
    "wof:name":"Etablissements Bodin Et Fils S.a.",
    "wof:placetype":"venue"
},
  "geometry": {"coordinates":[-1.059321,46.508663],"type":"Point"}
}