{
  "type": "Feature",
  "properties": {
    "iso:country":"FR",
    "sg:address":"Rue Commerce 67640 Fegersheim",
    "sg:city":"Fegersheim",
    "sg:classifiers":[
        {
            "category":"Manufacturing",
            "subcategory":"Metals",
            "type":"Manufacturing & Wholesale Goods"
        }
    ],
    "sg:phone":"+33 3 88 64 02 00",
    "sg:postcode":"67640",
    "sg:province":"Alsace",
    "sg:tags":[
        "metallurgy",
        "metalworking"
    ],
    "wof:name":"Kernst Henri Sa",
    "wof:placetype":"venue"
},
  "geometry": {"coordinates":[7.690123,48.497955],"type":"Point"}
}