{
  "type": "Feature",
  "properties": {
    "addr:full":"ZAI du Petit parc Ecquevilly Ile de France 78920",
    "addr:postcode":"78920",
    "iso:country":"FR",
    "sg:address":"ZAI du Petit parc",
    "sg:city":"Ecquevilly",
    "sg:orig_category":"Non-Classified Establishments",
    "sg:phone":"+33 1 34 75 52 51",
    "sg:postcode":"78920",
    "sg:province":"Ile de France",
    "wof:name":"D.n.i. S.a.",
    "wof:placetype":"venue"
},
  "geometry": {"coordinates":[1.918925,48.949734],"type":"Point"}
}