{
  "type": "Feature",
  "properties": {
    "addr:full":"March\u00e9 Saint Charles 66000 Perpignan Languedoc-Roussillon",
    "addr:postcode":"66000",
    "iso:country":"FR",
    "sg:address":"March\u00e9 Saint Charles 66000 Perpignan",
    "sg:orig_category":"Unclassifiable Establishments",
    "sg:phone":"+33 4 68 55 35 35",
    "sg:province":"Languedoc-Roussillon",
    "wof:name":"Agri Commerce S.a.",
    "wof:placetype":"venue"
},
  "geometry": {"coordinates":[2.851745,42.691494],"type":"Point"}
}