{
  "type": "Feature",
  "properties": {
    "addr:full":"ZI Sables de Beauregard 36700 Ch\u00e2tillon sur Indre Arpheuilles Centre 36700",
    "addr:postcode":"36700;36700",
    "addr:street":"Sables;Beauregard",
    "iso:country":"FR",
    "sg:address":"ZI Sables de Beauregard 36700 Ch\u00e2tillon sur Indre",
    "sg:city":"Arpheuilles",
    "sg:classifiers":[
        {
            "category":"Professional",
            "subcategory":"Engineering",
            "type":"Services"
        }
    ],
    "sg:phone":"+33 2 54 02 36 37",
    "sg:postcode":"36700",
    "sg:province":"Centre",
    "sg:tags":[
        "machine",
        "-",
        "mechanical"
    ],
    "wof:name":"Meca Precis",
    "wof:placetype":"venue"
},
  "geometry": {"coordinates":[1.17353,46.984276],"type":"Point"}
}