{
  "type": "Feature",
  "properties": {
    "iso:country":"FR",
    "sg:address":"47 Avenue Des Prades 15013 Aurillac Cedex",
    "sg:classifiers":[
        {
            "category":"Professional",
            "subcategory":"Business Services",
            "type":"Services"
        }
    ],
    "sg:phone":"+33 4 71 63 42 72",
    "sg:province":"Midi Pyr\u00e9n\u00e9es",
    "sg:tags":[
        "training",
        "advice"
    ],
    "wof:name":"Lycee Polyvalent Privee & Ecole Gerbert",
    "wof:placetype":"venue"
},
  "geometry": {"coordinates":[2.44385,44.928799],"type":"Point"}
}