{
  "type": "Feature",
  "properties": {
    "iso:country":"FR",
    "sg:address":"2BIS rue des Fr\u00e8res Montgolfier 95500 Gonesse",
    "sg:classifiers":[
        {
            "category":"Banks & Credit Unions",
            "subcategory":"Bank",
            "type":"Services"
        }
    ],
    "sg:phone":"+33 1 39 85 41 60",
    "sg:postcode":"95500",
    "sg:province":"Ile de France",
    "sg:tags":[
        "rubber",
        "mattress",
        "made",
        "pad",
        "plastic"
    ],
    "wof:name":"Mbe Sa",
    "wof:placetype":"venue"
},
  "geometry": {"coordinates":[2.454791,48.988251],"type":"Point"}
}