{
  "type": "Feature",
  "properties": {
    "iso:country":"FR",
    "sg:address":"La Loire 44220 Cou\u00ebron",
    "sg:orig_category":"Non-Classified Establishments",
    "sg:phone":"+33 2 40 63 14 69",
    "sg:postcode":"44220",
    "sg:province":"Pays de Loire",
    "wof:name":"Ar\u00f4mates",
    "wof:placetype":"venue"
},
  "geometry": {"coordinates":[-1.67289,47.251846],"type":"Point"}
}