{
  "type": "Feature",
  "properties": {
    "addr:full":"B.P. 7 Marignane C\u00e9dex^^13700 Marignane Basse Normandie 13727",
    "addr:postcode":"13727",
    "addr:street":"B.P. 7;Ce\u0301Dex^^13700;Basse",
    "iso:country":"FR",
    "sg:address":"B.P. 7",
    "sg:city":"Marignane C\u00e9dex^^13700 Marignane",
    "sg:orig_category":"Non-Classified Establishments",
    "sg:phone":"+33 4 42 14 14 14",
    "sg:postcode":"13727",
    "sg:province":"Basse Normandie",
    "wof:name":"A\u00e9roport Marseille Provence",
    "wof:placetype":"venue"
},
  "geometry": {"coordinates":[5.21421,43.418041],"type":"Point"}
}