{
  "type": "Feature",
  "properties": {
    "iso:country":"FR",
    "sg:address":"21, Rue de Choiseul, 75002 Paris",
    "sg:orig_category":"Unclassifiable Establishments",
    "sg:phone":"+33 1 40 07 87 87",
    "sg:province":"Ile de France",
    "wof:name":"Montparnasse Multim\u00e9dia S.a.",
    "wof:placetype":"venue"
},
  "geometry": {"coordinates":[2.335759,48.870525],"type":"Point"}
}