{
  "type": "Feature",
  "properties": {
    "addr:full":"20, Chemin Louis Chirpaz, 69134 Ecully C\u00e9dex Franche Comt\u00e9",
    "addr:housenumber":"20",
    "addr:postcode":"69134",
    "addr:street":"Chemin Louis Chirpaz;Franche Comte\u0301",
    "iso:country":"FR",
    "sg:address":"20, Chemin Louis Chirpaz, 69134 Ecully C\u00e9dex",
    "sg:orig_category":"Non-Classified Establishments",
    "sg:phone":"+33 4 72 18 02 40",
    "sg:province":"Franche Comt\u00e9",
    "wof:name":"Agibat Ing\u00e9nierie S.a.",
    "wof:placetype":"venue"
},
  "geometry": {"coordinates":[4.783317,45.778454],"type":"Point"}
}