{
  "type": "Feature",
  "properties": {
    "iso:country":"FR",
    "sg:address":"ZI Jean Mal\u00e8ze",
    "sg:city":"Bon Encontre",
    "sg:orig_category":"Unclassifiable Establishments",
    "sg:phone":"+33 5 53 68 49 49",
    "sg:postcode":"47240",
    "sg:province":"Aquitaine",
    "wof:name":"Soverso S.n.c.",
    "wof:placetype":"venue"
},
  "geometry": {"coordinates":[0.668345,44.186184],"type":"Point"}
}