{
  "type": "Feature",
  "properties": {
    "iso:country":"FR",
    "sg:address":"chemin de la Saulaie 45500 Gien",
    "sg:city":"Gien",
    "sg:classifiers":[
        {
            "category":"Bus Stop",
            "subcategory":"None",
            "type":"Transportation"
        }
    ],
    "sg:phone":"+33 2 38 37 62 00",
    "sg:postcode":"45500",
    "sg:province":"Centre",
    "sg:tags":[
        "omnibus",
        "car",
        "seat"
    ],
    "wof:name":"Isri France Gien S.a.r.l.",
    "wof:placetype":"venue"
},
  "geometry": {"coordinates":[2.6306,47.707371],"type":"Point"}
}