{
  "type": "Feature",
  "properties": {
    "addr:full":"79/83, Rue des Fr\u00e8res Lumi\u00e8re, 93330 Neuilly sur Marne Ile de France",
    "addr:housenumber":"79 / 83",
    "addr:postcode":"93330",
    "addr:street":"Rue Des Fre\u0300Res Lumie\u0300Re",
    "iso:country":"FR",
    "sg:address":"79/83, Rue des Fr\u00e8res Lumi\u00e8re, 93330 Neuilly sur Marne",
    "sg:orig_category":"Non-Classified Establishments",
    "sg:phone":"+33 1 43 00 99 55",
    "sg:province":"Ile de France",
    "wof:name":"Ring ! S.a.r.l.",
    "wof:placetype":"venue"
},
  "geometry": {"coordinates":[2.521056,48.867249],"type":"Point"}
}