{
  "type": "Feature",
  "properties": {
    "iso:country":"FR",
    "sg:address":"79/83, Rue des Fr\u00e8res Lumi\u00e8re, 93330 Neuilly sur Marne",
    "sg:orig_category":"Non-Classified Establishments",
    "sg:phone":"+33 1 43 00 99 55",
    "sg:province":"Ile de France",
    "wof:name":"Ring ! S.a.r.l.",
    "wof:placetype":"venue"
},
  "geometry": {"coordinates":[2.521056,48.867249],"type":"Point"}
}