{
  "type": "Feature",
  "properties": {
    "addr:full":"Av. du Gros Ch\u00eane - ZAC des Bellevues - B\u00e2t C Saint Ouen l'Aum\u00f4ne Ile de France 95310",
    "addr:housenumber":"c",
    "addr:postcode":"ba\u0302t;95310",
    "addr:street":"Av. Du Gros;Zac Des Bellevues;Saint Ouen L'Aumo \u0302Ne Ile De France",
    "iso:country":"FR",
    "sg:address":"Av. du Gros Ch\u00eane - ZAC des Bellevues - B\u00e2t C",
    "sg:city":"Saint Ouen l'Aum\u00f4ne",
    "sg:orig_category":"Unclassifiable Establishments",
    "sg:phone":"+33 1 34 64 22 45",
    "sg:postcode":"95310",
    "sg:province":"Ile de France",
    "wof:name":"C.e.f.b. - Comptoir Electrique Franco Belges",
    "wof:placetype":"venue"
},
  "geometry": {"coordinates":[1.151225,47.715446],"type":"Point"}
}