{
  "type": "Feature",
  "properties": {
    "iso:country":"FR",
    "sg:address":"47170 Poudenas",
    "sg:city":"Poudenas",
    "sg:orig_category":"Unclassifiable Establishments",
    "sg:phone":"+33 5 53 65 73 55",
    "sg:postcode":"47170",
    "sg:province":"Aquitaine",
    "wof:name":"Electra S.a.",
    "wof:placetype":"venue"
},
  "geometry": {"coordinates":[0.20942,44.045078],"type":"Point"}
}