{
  "type": "Feature",
  "properties": {
    "addr:full":"B.P. 2 Guignicourt^^02190 Cond\u00e9 sur Suippe Picardie 02190",
    "addr:postcode":"02190",
    "addr:street":"B.P. 2 Guignicourt^^02190 Conde\u0301;Suippe Picardie",
    "iso:country":"FR",
    "sg:address":"B.P. 2",
    "sg:city":"Guignicourt^^02190 Cond\u00e9 sur Suippe",
    "sg:orig_category":"Non-Classified Establishments",
    "sg:phone":"+33 3 23 25 36 00",
    "sg:postcode":"02190",
    "sg:province":"Picardie",
    "wof:name":"Saint Louis Sucre S.n.c.",
    "wof:placetype":"venue"
},
  "geometry": {"coordinates":[3.96664,49.438881],"type":"Point"}
}