{
  "type": "Feature",
  "properties": {
    "iso:country":"FR",
    "sg:address":"19, Rue du Vercos, 69960 Corbas",
    "sg:orig_category":"Unclassifiable Establishments",
    "sg:phone":"+33 4 78 20 56 96",
    "sg:province":"Rhone-Alpes",
    "wof:name":"Bargel Torrel Et Compagnie S.a.",
    "wof:placetype":"venue"
},
  "geometry": {"coordinates":[4.914762,45.672031],"type":"Point"}
}