{
  "type": "Feature",
  "properties": {
    "iso:country":"FR",
    "sg:address":"4/16, Av. du G\u00e9n\u00e9ral Leclerc, 92260 Fontenay aux Roses",
    "sg:orig_category":"Non-Classified Establishments",
    "sg:phone":"+33 1 41 87 70 00",
    "sg:postcode":"92260",
    "sg:province":"Ile de France",
    "wof:name":"C.s. T\u00e9l\u00e9com S.a.",
    "wof:placetype":"venue"
},
  "geometry": {"coordinates":[2.283632,48.79356],"type":"Point"}
}