{
  "type": "Feature",
  "properties": {
    "addr:full":"25, Rue du 8 Mai 1945, 94470 Boissy Saint L\u00e9ger Ile de France",
    "addr:housenumber":"25",
    "addr:postcode":"94470",
    "addr:street":"Rue Du 8 Mai 1945",
    "iso:country":"FR",
    "sg:address":"25, Rue du 8 Mai 1945, 94470 Boissy Saint L\u00e9ger",
    "sg:orig_category":"Unclassifiable Establishments",
    "sg:phone":"+33 1 45 10 63 00",
    "sg:province":"Ile de France",
    "wof:name":"Cieme Informatique S.a.",
    "wof:placetype":"venue"
},
  "geometry": {"coordinates":[2.500331,48.761314],"type":"Point"}
}