{
  "type": "Feature",
  "properties": {
    "addr:full":"2 Rue Cernes 03430 Cosne D'Allier Sauvagny Auvergne 03430",
    "addr:housenumber":"2",
    "addr:postcode":"03430;03430",
    "addr:street":"Rue Cernes",
    "iso:country":"FR",
    "sg:address":"2 Rue Cernes 03430 Cosne D'Allier",
    "sg:city":"Sauvagny",
    "sg:classifiers":[
        {
            "category":"Professional",
            "type":"Services"
        }
    ],
    "sg:phone":"+33 4 70 07 53 67",
    "sg:postcode":"03430",
    "sg:province":"Auvergne",
    "sg:tags":[
        "transport",
        "road"
    ],
    "wof:name":"Larvaron Transports Sa",
    "wof:placetype":"venue"
},
  "geometry": {"coordinates":[2.835608,46.474697],"type":"Point"}
}