{
  "type": "Feature",
  "properties": {
    "iso:country":"FR",
    "sg:address":"21, Place Saint Denis, 37400 Amboise",
    "sg:city":"Amboise",
    "sg:orig_category":"Unclassifiable Establishments",
    "sg:phone":"+33 2 47 57 29 26",
    "sg:postcode":"37400",
    "sg:province":"Centre",
    "wof:name":"Gardel Et Cie S.a.r.l.",
    "wof:placetype":"venue"
},
  "geometry": {"coordinates":[0.979372,47.410381],"type":"Point"}
}