{
  "type": "Feature",
  "properties": {
    "addr:full":"B.P. 70804, 57208 Sarreguemines C\u00e9dex^^ZI de R\u00e9melfing, 57208 Sarreguemines C\u00e9dex Languedoc-Roussillon",
    "addr:postcode":"57208;57208;ce\u0301dex",
    "iso:country":"FR",
    "sg:address":"B.P. 70804, 57208 Sarreguemines C\u00e9dex^^ZI de R\u00e9melfing, 57208 Sarreguemines C\u00e9dex",
    "sg:orig_category":"Cintrage Cintrage de tubes Cintrage de tubes \u00e0 froid Fa\u00e7onnage de tubes Filetage Fluoper\u00e7age Peintur",
    "sg:phone":"+33 3 87 98 35 29",
    "sg:province":"Languedoc-Roussillon",
    "wof:name":"Fey Othon S.a.",
    "wof:placetype":"venue"
},
  "geometry": {"coordinates":[7.070569,49.108246],"type":"Point"}
}