{
  "type": "Feature",
  "properties": {
    "addr:full":"39, Rue du Levant, 35400 Saint Malo Saint-Malo Bretagne 35400",
    "addr:housenumber":"39",
    "addr:postcode":"35400;35400",
    "addr:street":"Rue Du Levant;Saint-Malo",
    "iso:country":"FR",
    "sg:address":"39, Rue du Levant, 35400 Saint Malo",
    "sg:city":"Saint-Malo",
    "sg:orig_category":"Unclassifiable Establishments",
    "sg:phone":"+33 2 99 82 82 22",
    "sg:postcode":"35400",
    "sg:province":"Bretagne",
    "wof:name":"Clair Emeraude S.a.r.l.",
    "wof:placetype":"venue"
},
  "geometry": {"coordinates":[-1.998234,48.638889],"type":"Point"}
}