{
  "type": "Feature",
  "properties": {
    "iso:country":"FR",
    "sg:address":"74 av Raspail",
    "sg:city":"Gentilly",
    "sg:classifiers":[
        {
            "category":"Banks & Credit Unions",
            "subcategory":"Financial Services",
            "type":"Services"
        }
    ],
    "sg:phone":"+33 1 41 24 70 00",
    "sg:postcode":"94250",
    "sg:province":"Ile de France",
    "sg:tags":[
        "banking",
        "finance",
        "insurance"
    ],
    "wof:name":"Sanofi-synthelabo",
    "wof:placetype":"venue"
},
  "geometry": {"coordinates":[2.345345,48.811302],"type":"Point"}
}