{
  "type": "Feature",
  "properties": {
    "iso:country":"FR",
    "sg:address":"107 Route De Briollay 49100 Angers",
    "sg:classifiers":[
        {
            "category":"Wholesale",
            "subcategory":"Machinery & Supplies",
            "type":"Manufacturing & Wholesale Goods"
        }
    ],
    "sg:phone":"+33 2 41 41 14 14",
    "sg:postcode":"49100",
    "sg:province":"Pays de Loire",
    "sg:tags":[
        "handling",
        "material",
        "-",
        "machine",
        "equipment",
        "engineering",
        "mechanical"
    ],
    "wof:name":"Angers Palette Recyclage Apr (apr)",
    "wof:placetype":"venue"
},
  "geometry": {"coordinates":[-0.528473,47.497021],"type":"Point"}
}