{
  "type": "Feature",
  "properties": {
    "iso:country":"FR",
    "sg:address":"45, Rue Sainte Genevi\u00e8ve, 69006 Lyon",
    "sg:orig_category":"Non-Classified Establishments",
    "sg:phone":"+33 4 37 24 69 73",
    "sg:postcode":"69006",
    "sg:province":"Rhone-Alpes",
    "wof:name":"Symphonie Voyages S.a.r.l.",
    "wof:placetype":"venue"
},
  "geometry": {"coordinates":[4.864911,45.765347],"type":"Point"}
}