{
  "type": "Feature",
  "properties": {
    "iso:country":"FR",
    "sg:address":"24, Rue Coriolis, 75012 Paris",
    "sg:orig_category":"Unclassifiable Establishments",
    "sg:phone":"+33 1 43 45 34 58",
    "sg:province":"Ile de France",
    "wof:name":"Forplast France Production S.a.",
    "wof:placetype":"venue"
},
  "geometry": {"coordinates":[2.391009,48.836277],"type":"Point"}
}