{
  "type": "Feature",
  "properties": {
    "iso:country":"FR",
    "sg:address":"42, Rue de la Bresse, 94150 Rungis",
    "sg:orig_category":"Unclassifiable Establishments",
    "sg:phone":"+33 1 46 86 21 51",
    "sg:province":"Ile de France",
    "wof:name":"Etablissements Jouhaud S.a.r.l.",
    "wof:placetype":"venue"
},
  "geometry": {"coordinates":[2.3612,48.757965],"type":"Point"}
}