{
  "type": "Feature",
  "properties": {
    "addr:full":"15 Av Armstrong 33700 M\u00e9rignac M\u00e9rignac Aquitaine 33700",
    "addr:postcode":"33700;33700",
    "addr:street":"15 Av Armstrong",
    "iso:country":"FR",
    "sg:address":"15 Av Armstrong 33700 M\u00e9rignac",
    "sg:city":"M\u00e9rignac",
    "sg:classifiers":[
        {
            "category":"Transit Center",
            "subcategory":"Freight",
            "type":"Transportation"
        }
    ],
    "sg:phone":"+33 5 56 47 89 59",
    "sg:postcode":"33700",
    "sg:province":"Aquitaine",
    "sg:tags":[
        "metallurgy",
        "pipe",
        "metalworking",
        "sheet"
    ],
    "wof:name":"Technofluides Sarl",
    "wof:placetype":"venue"
},
  "geometry": {"coordinates":[-0.692664,44.837475],"type":"Point"}
}