{
  "type": "Feature",
  "properties": {
    "addr:full":"4, All\u00e9e de la Combe Bois Dieu, 69380 Lissieu Rhone-Alpes 69380",
    "addr:housenumber":"4",
    "addr:postcode":"69380;69380",
    "addr:street":"Alle\u0301E De La Combe Bois Dieu",
    "iso:country":"FR",
    "sg:address":"4, All\u00e9e de la Combe Bois Dieu, 69380 Lissieu",
    "sg:orig_category":"Unclassifiable Establishments",
    "sg:phone":"+33 4 72 54 99 02",
    "sg:postcode":"69380",
    "sg:province":"Rhone-Alpes",
    "wof:name":"H\u00f6nle Uv France S.a.r.l.",
    "wof:placetype":"venue"
},
  "geometry": {"coordinates":[4.71535,45.835541],"type":"Point"}
}