{
  "type": "Feature",
  "properties": {
    "addr:full":"Perches 81600 Gaillac Midi Pyr\u00e9n\u00e9es",
    "addr:postcode":"81600",
    "iso:country":"FR",
    "sg:address":"Perches 81600 Gaillac",
    "sg:orig_category":"Unclassifiable Establishments",
    "sg:phone":"+33 5 63 33 19 15",
    "sg:province":"Midi Pyr\u00e9n\u00e9es",
    "wof:name":"Domaine Des Hourtets S.c.e.a.",
    "wof:placetype":"venue"
},
  "geometry": {"coordinates":[1.8649,43.94194],"type":"Point"}
}