{
  "type": "Feature",
  "properties": {
    "iso:country":"FR",
    "sg:address":"32 Rue Des Cayennes 78700 Conflans Ste Honorine",
    "sg:classifiers":[
        {
            "category":"Utilities",
            "subcategory":"Electric",
            "type":"Services"
        }
    ],
    "sg:phone":"+33 1 39 72 10 70",
    "sg:postcode":"78700",
    "sg:province":"Ile de France",
    "sg:tags":[
        "electricity",
        "electronic",
        "electrical",
        "equipment"
    ],
    "wof:name":"Ste De Cablages De Conflans Sa",
    "wof:placetype":"venue"
},
  "geometry": {"coordinates":[2.082998,49.008881],"type":"Point"}
}