{
  "type": "Feature",
  "properties": {
    "iso:country":"FR",
    "sg:address":"3, Impasse Jean Mermoz - ZI du Terroir, 31140 Saint Alban",
    "sg:orig_category":"Non-Classified Establishments",
    "sg:phone":"+33 5 34 27 23 90",
    "sg:province":"Midi Pyr\u00e9n\u00e9es",
    "wof:name":"S.a.r. Sud-ouest S.a.s.",
    "wof:placetype":"venue"
},
  "geometry": {"coordinates":[1.429025,43.668308],"type":"Point"}
}