{
  "type": "Feature",
  "properties": {
    "iso:country":"FR",
    "sg:address":"Zone Industrielle nord 37110 CHATEAU RENAULT",
    "sg:city":"Autr\u00e8che",
    "sg:classifiers":[
        {
            "category":"Utilities",
            "subcategory":"Natural Gas",
            "type":"Services"
        }
    ],
    "sg:phone":"+33 2 47 62 58 00",
    "sg:postcode":"37110",
    "sg:province":"Centre",
    "sg:tags":[
        "fertilizer",
        "nitrogen"
    ],
    "wof:name":"Algochimie Laboratoires S.a.",
    "wof:placetype":"venue"
},
  "geometry": {"coordinates":[0.91292,47.59214],"type":"Point"}
}