{
  "type": "Feature",
  "properties": {
    "addr:full":"91 Av De La Lib\u00e9ration 54000 Nancy Lorraine 54000",
    "addr:postcode":"54000;54000",
    "addr:street":"91 Av De La Libe\u0301Ration",
    "iso:country":"FR",
    "sg:address":"91 Av De La Lib\u00e9ration 54000 Nancy",
    "sg:classifiers":[
        {
            "category":"Manufacturing",
            "subcategory":"Metals",
            "type":"Manufacturing & Wholesale Goods"
        }
    ],
    "sg:phone":"+33 3 83 95 20 00",
    "sg:postcode":"54000",
    "sg:province":"Lorraine",
    "sg:tags":[
        "metallurgy",
        "metalworking"
    ],
    "wof:name":"Saint Gobain Pam",
    "wof:placetype":"venue"
},
  "geometry": {"coordinates":[6.165134,48.693718],"type":"Point"}
}