{
  "type": "Feature",
  "properties": {
    "addr:full":"72 Av Georges Clemenceau 92000 Nanterre Ile de France 92000",
    "addr:postcode":"92000;92000",
    "addr:street":"72 Av Georges Clemenceau",
    "iso:country":"FR",
    "sg:address":"72 Av Georges Clemenceau 92000 Nanterre",
    "sg:classifiers":[
        {
            "category":"Autos & Motor Vehicles",
            "subcategory":"Automobile Sales",
            "type":"Retail Goods"
        }
    ],
    "sg:phone":"+33 1 41 20 30 40",
    "sg:postcode":"92000",
    "sg:province":"Ile de France",
    "sg:tags":[
        "equipment",
        "motor-cars",
        "transport"
    ],
    "wof:name":"Speedy France Sa",
    "wof:placetype":"venue"
},
  "geometry": {"coordinates":[2.205707,48.886574],"type":"Point"}
}