{
  "type": "Feature",
  "properties": {
    "addr:full":"5, Impasse du Saule, 57140 Woippy Lorraine",
    "addr:housenumber":"5",
    "addr:postcode":"57140",
    "addr:street":"Impasse Du Saule",
    "iso:country":"FR",
    "sg:address":"5, Impasse du Saule, 57140 Woippy",
    "sg:orig_category":"Unclassifiable Establishments",
    "sg:phone":"+33 3 87 32 52 52",
    "sg:province":"Lorraine",
    "wof:name":"Moselec S.a.r.l. - Soci\u00e9t\u00e9 Mosellane D'electricit\u00e9",
    "wof:placetype":"venue"
},
  "geometry": {"coordinates":[6.153335,49.146935],"type":"Point"}
}