{
  "type": "Feature",
  "properties": {
    "iso:country":"FR",
    "sg:address":"103 avenue Parmentier 75011 Paris",
    "sg:classifiers":[
        {
            "category":"Professional",
            "subcategory":"Testing Lab",
            "type":"Services"
        }
    ],
    "sg:phone":"+33 1 43 14 88 11",
    "sg:province":"Ile de France",
    "sg:tags":[
        "large",
        "laboratory",
        "laboratories",
        "photographic"
    ],
    "wof:name":"Graphi Chrome S.a.",
    "wof:placetype":"venue"
},
  "geometry": {"coordinates":[2.372981,48.86702],"type":"Point"}
}