{
  "type": "Feature",
  "properties": {
    "iso:country":"FR",
    "sg:address":"ZAC des Gouchoux",
    "sg:city":"Saint Jean d'Ardi\u00e8res",
    "sg:orig_category":"Unclassifiable Establishments",
    "sg:phone":"+33 4 74 66 68 00",
    "sg:postcode":"69220",
    "sg:province":"Rhone-Alpes",
    "wof:name":"Saint Jean Industries S.a.",
    "wof:placetype":"venue"
},
  "geometry": {"coordinates":[4.73872,46.12669],"type":"Point"}
}