{
  "type": "Feature",
  "properties": {
    "iso:country":"FR",
    "sg:address":"5, Bd Gustave Eiffel, 21600 Longvic",
    "sg:city":"Longvic",
    "sg:orig_category":"Unclassifiable Establishments",
    "sg:phone":"+33 3 80 74 76 78",
    "sg:postcode":"21600",
    "sg:province":"Bourgogne",
    "wof:name":"Le Nigen N Industries S.a.",
    "wof:placetype":"venue"
},
  "geometry": {"coordinates":[5.055492,47.278259],"type":"Point"}
}