{
  "type": "Feature",
  "properties": {
    "iso:country":"FR",
    "sg:address":"42, Rue Gustave Eiffel, 95190 Goussainville",
    "sg:orig_category":"Unclassifiable Establishments",
    "sg:phone":"+33 1 39 33 95 33",
    "sg:province":"Ile de France",
    "wof:name":"Acushnet France S.a.",
    "wof:placetype":"venue"
},
  "geometry": {"coordinates":[2.466546,49.021935],"type":"Point"}
}