{
  "type": "Feature",
  "properties": {
    "addr:full":"4, Rue de Vaucanson - ZI des Fleurs, 38170 Seyssinet Pariset Rhone-Alpes 38170",
    "addr:housenumber":"4",
    "addr:postcode":"38170;38170",
    "addr:street":"Rue De Vaucanson Zi Des Fleurs;Rhone-Alpes",
    "iso:country":"FR",
    "sg:address":"4, Rue de Vaucanson - ZI des Fleurs, 38170 Seyssinet Pariset",
    "sg:orig_category":"Unclassifiable Establishments",
    "sg:phone":"+33 4 76 70 29 89",
    "sg:postcode":"38170",
    "sg:province":"Rhone-Alpes",
    "wof:name":"S.a.d. S.a. - Soci\u00e9t\u00e9 D'agences Et De Diffusion",
    "wof:placetype":"venue"
},
  "geometry": {"coordinates":[5.696125,45.180908],"type":"Point"}
}