{
  "type": "Feature",
  "properties": {
    "iso:country":"FR",
    "sg:address":"Rue Alphonse Daudet 91000 Evry",
    "sg:classifiers":[
        {
            "category":"Manufacturing",
            "subcategory":"Glass & Minerals",
            "type":"Manufacturing & Wholesale Goods"
        }
    ],
    "sg:phone":"+33 1 60 77 28 09",
    "sg:postcode":"91000",
    "sg:province":"Ile de France",
    "sg:tags":[
        "building",
        "material"
    ],
    "wof:name":"Beton De France Ile De France",
    "wof:placetype":"venue"
},
  "geometry": {"coordinates":[2.45349,48.627766],"type":"Point"}
}