{
  "type": "Feature",
  "properties": {
    "addr:full":"19, Rte de Blois, 28200 Ch\u00e2teaudun Ch\u00e2teaudun Centre 28200",
    "addr:housenumber":"19",
    "addr:postcode":"28200;28200",
    "addr:street":"Rte De Blois",
    "iso:country":"FR",
    "sg:address":"19, Rte de Blois, 28200 Ch\u00e2teaudun",
    "sg:city":"Ch\u00e2teaudun",
    "sg:orig_category":"Non-Classified Establishments",
    "sg:phone":"+33 2 37 44 91 02",
    "sg:postcode":"28200",
    "sg:province":"Centre",
    "wof:name":"Dunoise Irrigation S.a.r.l.",
    "wof:placetype":"venue"
},
  "geometry": {"coordinates":[1.33401,48.061562],"type":"Point"}
}