{
  "type": "Feature",
  "properties": {
    "addr:full":"lieu dit le Hullin 55300 Valbois Lorraine",
    "addr:postcode":"55300",
    "addr:street":"Lieu Dit Le Hullin",
    "iso:country":"FR",
    "sg:address":"lieu dit le Hullin 55300 Valbois",
    "sg:orig_category":"Non-Classified Establishments",
    "sg:phone":"+33 3 29 90 99 99",
    "sg:province":"Lorraine",
    "wof:name":"I.t.p. Drapier - Intervention Travaux Publics",
    "wof:placetype":"venue"
},
  "geometry": {"coordinates":[5.541056,48.891834],"type":"Point"}
}