{
  "type": "Feature",
  "properties": {
    "iso:country":"FR",
    "sg:address":"B.P. 15, 63306 Thiers C\u00e9dex^^ZI de Felet, 63300 Thiers",
    "sg:city":"Thiers",
    "sg:orig_category":"Non-Classified Establishments",
    "sg:phone":"+33 4 73 80 72 67",
    "sg:postcode":"63300",
    "sg:province":"Auvergne",
    "wof:name":"Parembal S.a.",
    "wof:placetype":"venue"
},
  "geometry": {"coordinates":[3.563396,45.82058],"type":"Point"}
}