{
  "type": "Feature",
  "properties": {
    "addr:full":"159 Rue Ampere 36000 Chateauroux Ch\u00e2teauroux Centre 36000",
    "addr:housenumber":"159",
    "addr:postcode":"36000;36000",
    "addr:street":"Rue Ampere;Cha\u0302Teauroux",
    "iso:country":"FR",
    "sg:address":"159 Rue Ampere 36000 Chateauroux",
    "sg:city":"Ch\u00e2teauroux",
    "sg:classifiers":[
        {
            "category":"Manufacturing",
            "subcategory":"Metals",
            "type":"Manufacturing & Wholesale Goods"
        }
    ],
    "sg:phone":"+33 2 54 34 44 48",
    "sg:postcode":"36000",
    "sg:province":"Centre",
    "sg:tags":[
        "metallurgy",
        "metalworking",
        "processing"
    ],
    "wof:name":"Affutage Industriel Du Centre",
    "wof:placetype":"venue"
},
  "geometry": {"coordinates":[1.723767,46.814022],"type":"Point"}
}