{
  "type": "Feature",
  "properties": {
    "iso:country":"FR",
    "sg:address":"11, Av. du G\u00e9n\u00e9ral Leclerc, 92100 Boulogne Billancourt",
    "sg:orig_category":"Unclassifiable Establishments",
    "sg:phone":"+33 1 46 10 02 10",
    "sg:province":"Ile de France",
    "wof:name":"K.d.g. France S.a.",
    "wof:placetype":"venue"
},
  "geometry": {"coordinates":[2.242222,48.832989],"type":"Point"}
}