{
  "type": "Feature",
  "properties": {
    "addr:full":"48ter, Rue du Pav\u00e9, 78490 Le Tremblay sur Mauldre Ile de France",
    "addr:housenumber":"48ter",
    "addr:postcode":"78490",
    "addr:street":"Rue Du Pave\u0301;Tremblay;Mauldre Ile De France",
    "iso:country":"FR",
    "sg:address":"48ter, Rue du Pav\u00e9, 78490 Le Tremblay sur Mauldre",
    "sg:orig_category":"Unclassifiable Establishments",
    "sg:phone":"+33 1 34 87 87 08",
    "sg:province":"Ile de France",
    "wof:name":"Prettre Espaces Verts S.a.",
    "wof:placetype":"venue"
},
  "geometry": {"coordinates":[1.879619,48.778011],"type":"Point"}
}