{
  "type": "Feature",
  "properties": {
    "iso:country":"FR",
    "sg:address":"992 Chem Des Plantades Zi Les Plantades 83130 La Garde",
    "sg:classifiers":[
        {
            "category":"Shopping",
            "subcategory":"Computers & Home Electronics",
            "type":"Retail Goods"
        }
    ],
    "sg:phone":"+33 4 94 08 81 50",
    "sg:province":"Midi Pyr\u00e9n\u00e9es",
    "sg:tags":[
        "electric",
        "electricity",
        "component",
        "equipment",
        "electrical",
        "electronic"
    ],
    "wof:name":"Ets Cabus Et Raulot",
    "wof:placetype":"venue"
},
  "geometry": {"coordinates":[6.009775,43.124866],"type":"Point"}
}