{
  "type": "Feature",
  "properties": {
    "addr:full":"20/22, Rue Labrouste, 75015 Paris Ile de France",
    "addr:housenumber":"20 / 22",
    "addr:postcode":"75015",
    "addr:street":"Rue Labrouste",
    "iso:country":"FR",
    "sg:address":"20/22, Rue Labrouste, 75015 Paris",
    "sg:orig_category":"Unclassifiable Establishments",
    "sg:phone":"+33 1 53 68 16 16",
    "sg:province":"Ile de France",
    "wof:name":"Poly Print S.a.r.l.",
    "wof:placetype":"venue"
},
  "geometry": {"coordinates":[2.309046,48.835365],"type":"Point"}
}