{
  "type": "Feature",
  "properties": {
    "addr:full":"2 Avenue Gordon Bennett 75016 Paris Ile de France 75016",
    "addr:housenumber":"2",
    "addr:postcode":"75016;75016",
    "addr:street":"Avenue Gordon Bennett",
    "iso:country":"FR",
    "sg:address":"2 Avenue Gordon Bennett 75016 Paris",
    "sg:classifiers":[
        {
            "category":"Professional",
            "subcategory":"Business Services",
            "type":"Services"
        }
    ],
    "sg:phone":"+33 1 47 43 48 00",
    "sg:postcode":"75016",
    "sg:province":"Ile de France",
    "sg:tags":[
        "body",
        "advice"
    ],
    "wof:name":"Federation Francaise De Tennis",
    "wof:placetype":"venue"
},
  "geometry": {"coordinates":[2.250919,48.847198],"type":"Point"}
}