{
  "type": "Feature",
  "properties": {
    "iso:country":"FR",
    "sg:address":"Rte de Verri\u00e8res - Zone Industrielle",
    "sg:city":"Buch\u00e8res",
    "sg:orig_category":"Unclassifiable Establishments",
    "sg:phone":"+33 3 25 41 81 69",
    "sg:postcode":"10800",
    "sg:province":"Champagne",
    "wof:name":"Verger Transports S.a.",
    "wof:placetype":"venue"
},
  "geometry": {"coordinates":[4.099213,48.273235],"type":"Point"}
}