{
  "type": "Feature",
  "properties": {
    "addr:full":"30, Rue d'Eguison, 13010 Marseille Provence-Alpes-C\u00f4te d'Azur",
    "addr:housenumber":"30",
    "addr:postcode":"13010",
    "addr:street":"Rue D'Eguison",
    "iso:country":"FR",
    "sg:address":"30, Rue d'Eguison, 13010 Marseille",
    "sg:orig_category":"Unclassifiable Establishments",
    "sg:phone":"+33 4 91 79 24 23",
    "sg:province":"Provence-Alpes-C\u00f4te d'Azur",
    "wof:name":"S.m.a.g. S.a.r.l. - Soci\u00e9t\u00e9 Marseillaise D'achats Et De Gestion",
    "wof:placetype":"venue"
},
  "geometry": {"coordinates":[5.397034,43.281883],"type":"Point"}
}