{
  "type": "Feature",
  "properties": {
    "iso:country":"FR",
    "sg:address":"B.P. 1-502, 59383 Dunkerque C\u00e9dex 1^^11, Rue des Arbres, 59140 Dunkerque",
    "sg:orig_category":"Non-Classified Establishments",
    "sg:phone":"+33 3 28 58 67 89",
    "sg:postcode":"59140",
    "sg:province":"Nord Pas-de-Calais",
    "wof:name":"Dewulf-cailleret S.a.",
    "wof:placetype":"venue"
},
  "geometry": {"coordinates":[2.37693,51.036995],"type":"Point"}
}