{
  "type": "Feature",
  "properties": {
    "iso:country":"FR",
    "sg:address":"89, Rue du Faubourg Saint Antoine, 75011 Paris",
    "sg:orig_category":"Unclassifiable Establishments",
    "sg:phone":"+33 1 53 02 15 00",
    "sg:province":"Ile de France",
    "wof:name":"Bernard Brunhes International S.a.",
    "wof:placetype":"venue"
},
  "geometry": {"coordinates":[2.374925,48.851654],"type":"Point"}
}