{
  "type": "Feature",
  "properties": {
    "iso:country":"FR",
    "sg:address":"52 Av De La R\u00e9publique 75011 Paris",
    "sg:classifiers":[
        {
            "category":"Manufacturing",
            "subcategory":"Tools & Machinery",
            "type":"Manufacturing & Wholesale Goods"
        }
    ],
    "sg:phone":"+33 1 49 23 74 55",
    "sg:postcode":"75011",
    "sg:province":"Ile de France",
    "sg:tags":[
        "metallurgy",
        "metalworking"
    ],
    "wof:name":"Seroc",
    "wof:placetype":"venue"
},
  "geometry": {"coordinates":[2.375699,48.864868],"type":"Point"}
}