{
  "type": "Feature",
  "properties": {
    "iso:country":"FR",
    "sg:address":"27",
    "sg:city":"Parc aux Biches 91000 Evry",
    "sg:orig_category":"Chemicals and Pharmaceuticals Chemistry - by-products Industrial vehicles Motor-cars Vehicles and Tr",
    "sg:phone":"+33 1 69 36 38 80",
    "sg:postcode":"91000",
    "sg:province":"Ile de France",
    "wof:name":"Itd",
    "wof:placetype":"venue"
},
  "geometry": {"coordinates":[2.438074,48.641914],"type":"Point"}
}