{
  "type": "Feature",
  "properties": {
    "addr:full":"Za Le Solier 43220 Dunieres Duni\u00e8res Auvergne 43220",
    "addr:postcode":"43220;dunie\u0300res;43220",
    "addr:street":"Za Le Solier",
    "iso:country":"FR",
    "sg:address":"Za Le Solier 43220 Dunieres",
    "sg:city":"Duni\u00e8res",
    "sg:classifiers":[
        {
            "category":"Manufacturing",
            "subcategory":"Rubber & Plastics",
            "type":"Manufacturing & Wholesale Goods"
        }
    ],
    "sg:phone":"+33 4 71 66 87 17",
    "sg:postcode":"43220",
    "sg:province":"Auvergne",
    "sg:tags":[
        "packaging",
        "material",
        "-"
    ],
    "wof:name":"Teyssier Emballages Services Sarl",
    "wof:placetype":"venue"
},
  "geometry": {"coordinates":[4.343615,45.216541],"type":"Point"}
}