{
  "type": "Feature",
  "properties": {
    "iso:country":"FR",
    "sg:address":"27 Av De Friedland 75008 Paris",
    "sg:classifiers":[
        {
            "category":"Professional",
            "subcategory":"Business Services",
            "type":"Services"
        }
    ],
    "sg:phone":"+33 1 55 65 70 80",
    "sg:postcode":"75008",
    "sg:province":"Ile de France",
    "sg:tags":[
        "body",
        "advice"
    ],
    "wof:name":"Centre Dobservation Economique",
    "wof:placetype":"venue"
},
  "geometry": {"coordinates":[2.30124,48.874317],"type":"Point"}
}