{
  "type": "Feature",
  "properties": {
    "iso:country":"FR",
    "sg:address":"51, Rue Jean Moulin, 80000 Amiens",
    "sg:orig_category":"Unclassifiable Establishments",
    "sg:phone":"+33 3 22 95 00 90",
    "sg:province":"Picardie",
    "wof:name":"Girard S.a.r.l.",
    "wof:placetype":"venue"
},
  "geometry": {"coordinates":[2.280346,49.882607],"type":"Point"}
}