{
  "type": "Feature",
  "properties": {
    "addr:full":"167, Rue Paradis, 13006 Marseille Provence-Alpes-C\u00f4te d'Azur",
    "addr:housenumber":"167",
    "addr:postcode":"13006",
    "addr:street":"Rue Paradis",
    "iso:country":"FR",
    "sg:address":"167, Rue Paradis, 13006 Marseille",
    "sg:orig_category":"Non-Classified Establishments",
    "sg:phone":"+33 4 96 10 03 16",
    "sg:province":"Provence-Alpes-C\u00f4te d'Azur",
    "wof:name":"Imprimerie Lamy E.u.r.l.",
    "wof:placetype":"venue"
},
  "geometry": {"coordinates":[5.38324,43.290806],"type":"Point"}
}