{
  "type": "Feature",
  "properties": {
    "addr:full":"Zi Maysonnabe All Latecoere 64205 Biarritz Cedex Champagne",
    "addr:postcode":"64205",
    "iso:country":"FR",
    "sg:address":"Zi Maysonnabe",
    "sg:city":"All Latecoere 64205 Biarritz Cedex",
    "sg:classifiers":[
        {
            "category":"Food & Beverages",
            "subcategory":"Groceries & Convenience Stores",
            "type":"Retail Goods"
        }
    ],
    "sg:phone":"+33 5 59 52 25 40",
    "sg:province":"Champagne",
    "sg:tags":[
        "product",
        "related"
    ],
    "wof:name":"Polar France",
    "wof:placetype":"venue"
},
  "geometry": {"coordinates":[-1.558793,43.482571],"type":"Point"}
}