{
  "type": "Feature",
  "properties": {
    "addr:full":"Rte Teinte - Zone Industrielle Sougy sur Loire Bourgogne 58300",
    "addr:postcode":"58300",
    "addr:street":"Rte Teinte Zone Industrielle Sougy Sur",
    "iso:country":"FR",
    "sg:address":"Rte Teinte - Zone Industrielle",
    "sg:city":"Sougy sur Loire",
    "sg:orig_category":"Unclassifiable Establishments",
    "sg:phone":"+33 3 86 50 11 44",
    "sg:postcode":"58300",
    "sg:province":"Bourgogne",
    "wof:name":"Mat\u00e9riaux Pr\u00e9fabriqu\u00e9s Du Morvan S.a.",
    "wof:placetype":"venue"
},
  "geometry": {"coordinates":[3.425596,46.738682],"type":"Point"}
}