{
  "type": "Feature",
  "properties": {
    "iso:country":"FR",
    "sg:address":"1, Place Mathieu Jaboulay, 69230 Saint Genis Laval",
    "sg:orig_category":"Non-Classified Establishments",
    "sg:phone":"+33 4 78 86 85 65",
    "sg:postcode":"69230",
    "sg:province":"Rhone-Alpes",
    "wof:name":"C.c.f. - Cr\u00e9dit Commercial De France",
    "wof:placetype":"venue"
},
  "geometry": {"coordinates":[4.79251,45.695389],"type":"Point"}
}