{
  "type": "Feature",
  "properties": {
    "iso:country":"FR",
    "sg:address":"68, Rue Bayen, 75017 Paris",
    "sg:orig_category":"Unclassifiable Establishments",
    "sg:phone":"+33 1 53 81 95 00",
    "sg:province":"Ile de France",
    "wof:name":"Evaflor S.a.",
    "wof:placetype":"venue"
},
  "geometry": {"coordinates":[2.28958,48.88409],"type":"Point"}
}