{
  "type": "Feature",
  "properties": {
    "iso:country":"FR",
    "sg:address":"7 rue du Moulin Neuf 93240 Stains",
    "sg:classifiers":[
        {
            "category":"Manufacturing",
            "subcategory":"Rubber & Plastics",
            "type":"Manufacturing & Wholesale Goods"
        }
    ],
    "sg:phone":"+33 1 48 26 32 80",
    "sg:province":"Ile de France",
    "sg:tags":[
        "processing"
    ],
    "wof:name":"Abaqueplast S.a.r.l.",
    "wof:placetype":"venue"
},
  "geometry": {"coordinates":[2.392474,48.951843],"type":"Point"}
}