{
  "type": "Feature",
  "properties": {
    "iso:country":"FR",
    "sg:address":"22 Rue Des Nations 89470 Mon\u00e9teau",
    "sg:city":"Mon\u00e9teau",
    "sg:classifiers":[
        {
            "category":"Food & Beverages",
            "subcategory":"Groceries & Convenience Stores",
            "type":"Retail Goods"
        }
    ],
    "sg:phone":"+33 3 86 53 48 00",
    "sg:postcode":"89470",
    "sg:province":"Bourgogne",
    "sg:tags":[
        "product",
        "related"
    ],
    "wof:name":"Yoplait Sa",
    "wof:placetype":"venue"
},
  "geometry": {"coordinates":[3.578575,47.85006],"type":"Point"}
}