{
  "type": "Feature",
  "properties": {
    "iso:country":"FR",
    "sg:address":"B.P. 18, 01480 Jassans Riottier C\u00e9dex^^Rue de l'Industrie, 01480 Jassans Riottier",
    "sg:orig_category":"Non-Classified Establishments",
    "sg:phone":"+33 4 74 60 94 78",
    "sg:province":"Rhone-Alpes",
    "wof:name":"Saive Industrie S.a.",
    "wof:placetype":"venue"
},
  "geometry": {"coordinates":[4.766054,45.981064],"type":"Point"}
}