{
  "type": "Feature",
  "properties": {
    "addr:full":"4 Rue Claude Chappe 76300 Sotteville Les Rouen Haute Normandie 76300",
    "addr:housenumber":"4",
    "addr:postcode":"76300;76300",
    "addr:street":"Rue Claude Chappe;Haute Normandie",
    "iso:country":"FR",
    "sg:address":"4 Rue Claude Chappe 76300 Sotteville Les Rouen",
    "sg:classifiers":[
        {
            "category":"Shopping",
            "subcategory":"Computers & Home Electronics",
            "type":"Retail Goods"
        }
    ],
    "sg:phone":"+33 2 32 91 95 95",
    "sg:postcode":"76300",
    "sg:province":"Haute Normandie",
    "sg:tags":[
        "equipment",
        "household",
        "electrical",
        "appliance",
        "electronic"
    ],
    "wof:name":"Ragot Distribution",
    "wof:placetype":"venue"
},
  "geometry": {"coordinates":[1.111848,49.411015],"type":"Point"}
}