{
  "type": "Feature",
  "properties": {
    "addr:full":"9 Rue Du Progres 69800 Saint Priest Rhone-Alpes 69800",
    "addr:housenumber":"9",
    "addr:postcode":"69800;69800",
    "addr:street":"Rue Du Progres;Priest Rhone-Alpes",
    "iso:country":"FR",
    "sg:address":"9 Rue Du Progres 69800 Saint Priest",
    "sg:classifiers":[
        {
            "category":"Transit Center",
            "subcategory":"Freight",
            "type":"Transportation"
        }
    ],
    "sg:phone":"+33 4 72 47 59 80",
    "sg:postcode":"69800",
    "sg:province":"Rhone-Alpes",
    "sg:tags":[
        "metallurgy",
        "pipe",
        "metalworking",
        "sheet"
    ],
    "wof:name":"Ims Abraservice",
    "wof:placetype":"venue"
},
  "geometry": {"coordinates":[4.959554,45.720055],"type":"Point"}
}