{
  "type": "Feature",
  "properties": {
    "addr:full":"29 Rue Bernard 93000 Bobigny Ile de France 93000",
    "addr:housenumber":"29",
    "addr:postcode":"93000;ile;93000",
    "addr:street":"Rue Bernard;France",
    "iso:country":"FR",
    "sg:address":"29 Rue Bernard 93000 Bobigny",
    "sg:classifiers":[
        {
            "category":"Shopping",
            "subcategory":"Computers & Home Electronics",
            "type":"Retail Goods"
        }
    ],
    "sg:phone":"+33 1 49 15 54 00",
    "sg:postcode":"93000",
    "sg:province":"Ile de France",
    "sg:tags":[
        "equipment",
        "household",
        "electrical",
        "appliance",
        "electronic"
    ],
    "wof:name":"Dacem Sa",
    "wof:placetype":"venue"
},
  "geometry": {"coordinates":[2.425064,48.903072],"type":"Point"}
}