{
  "type": "Feature",
  "properties": {
    "addr:full":"Rue Nicolas Cugniot - ZI de l'Estagnol Carcassonne Languedoc-Roussillon 11000",
    "addr:postcode":"11000",
    "addr:street":"Rue Nicolas Cugniot Zi De L'Estagnol",
    "iso:country":"FR",
    "sg:address":"Rue Nicolas Cugniot - ZI de l'Estagnol",
    "sg:city":"Carcassonne",
    "sg:orig_category":"Unclassifiable Establishments",
    "sg:phone":"+33 4 68 25 13 03",
    "sg:postcode":"11000",
    "sg:province":"Languedoc-Roussillon",
    "wof:name":"Soci\u00e9t\u00e9 Charpente S.a.",
    "wof:placetype":"venue"
},
  "geometry": {"coordinates":[2.34842,43.207748],"type":"Point"}
}