{
  "type": "Feature",
  "properties": {
    "iso:country":"FR",
    "sg:address":"171, Rue des Douets, 37075 Tours C\u00e9dex 02",
    "sg:orig_category":"Non-Classified Establishments",
    "sg:phone":"+33 2 47 54 31 43",
    "sg:province":"Ile de France",
    "wof:name":"Astor S.a.",
    "wof:placetype":"venue"
},
  "geometry": {"coordinates":[0.686272,47.432384],"type":"Point"}
}