{
  "type": "Feature",
  "properties": {
    "addr:full":"B.P. 105, 93162 Noisy le Grand C\u00e9dex^^47, Av. Montaigne, 93160 Noisy le Grand Ile de France",
    "addr:housenumber":"b.p. 105",
    "addr:postcode":"93162;93160",
    "addr:street":"Av. Montaigne",
    "iso:country":"FR",
    "sg:address":"B.P. 105, 93162 Noisy le Grand C\u00e9dex^^47, Av. Montaigne, 93160 Noisy le Grand",
    "sg:orig_category":"Non-Classified Establishments",
    "sg:phone":"+33 1 48 15 16 95",
    "sg:province":"Ile de France",
    "wof:name":"Ic\u00f4ne Graphic S.a.r.l.",
    "wof:placetype":"venue"
},
  "geometry": {"coordinates":[2.553644,48.848892],"type":"Point"}
}