{
  "type": "Feature",
  "properties": {
    "addr:full":"Av. du pr\u00e9sident Kennedy M\u00e9rignac Aquitaine 33700",
    "addr:postcode":"33700",
    "addr:street":"Av. Du Pre\u0301Sident Kennedy",
    "iso:country":"FR",
    "sg:address":"Av. du pr\u00e9sident Kennedy",
    "sg:city":"M\u00e9rignac",
    "sg:orig_category":"Unclassifiable Establishments",
    "sg:phone":"+33 5 56 47 99 99",
    "sg:postcode":"33700",
    "sg:province":"Aquitaine",
    "wof:name":"I.g.s. C.p. S.a.r.l. - Ing\u00e9nierie Graphisme Services Charente Photogravure",
    "wof:placetype":"venue"
},
  "geometry": {"coordinates":[-0.653634,44.840691],"type":"Point"}
}