{
  "type": "Feature",
  "properties": {
    "iso:country":"FR",
    "sg:address":"12, Rue Cugnot - ZI des Hautes Garennes, 78570 Chanteloup les Vignes",
    "sg:orig_category":"Non-Classified Establishments",
    "sg:phone":"+33 1 39 70 99 03",
    "sg:province":"Ile de France",
    "wof:name":"Tremo S.a.r.l.",
    "wof:placetype":"venue"
},
  "geometry": {"coordinates":[2.035261,48.967773],"type":"Point"}
}