{
  "type": "Feature",
  "properties": {
    "iso:country":"FR",
    "sg:address":"Lille",
    "sg:city":"59",
    "sg:classifiers":[
        {
            "category":"Banks & Credit Unions",
            "subcategory":"Bank",
            "type":"Services"
        }
    ],
    "sg:province":"Nord Pas-de-Calais",
    "wof:name":"Bsd Courtage",
    "wof:placetype":"venue"
},
  "geometry": {"coordinates":[3.0628,50.63718],"type":"Point"}
}