{
  "type": "Feature",
  "properties": {
    "iso:country":"FR",
    "sg:address":"95 Rue Reaumur 75002 Paris",
    "sg:classifiers":[
        {
            "category":"Shopping",
            "subcategory":"Crafts & Fabrics",
            "type":"Retail Goods"
        }
    ],
    "sg:phone":"+33 1 40 26 13 30",
    "sg:postcode":"75002",
    "sg:province":"Ile de France",
    "sg:tags":[
        "textile",
        "clothing"
    ],
    "wof:name":"Cosi",
    "wof:placetype":"venue"
},
  "geometry": {"coordinates":[2.34601,48.867523],"type":"Point"}
}