{
  "type": "Feature",
  "properties": {
    "iso:country":"FR",
    "sg:address":"4, Rue de Montpellaz, 74150 Rumilly",
    "sg:orig_category":"Unclassifiable Establishments",
    "sg:phone":"+33 4 50 01 23 63",
    "sg:province":"Rhone-Alpes",
    "wof:name":"Vg Voyage Grillet S.a.r.l.",
    "wof:placetype":"venue"
},
  "geometry": {"coordinates":[5.943888,45.865314],"type":"Point"}
}