{
  "type": "Feature",
  "properties": {
    "addr:full":"153, Rue de Douai, 59000 Lille Nord Pas-de-Calais",
    "addr:housenumber":"153",
    "addr:postcode":"59000",
    "addr:street":"Rue De Douai",
    "iso:country":"FR",
    "sg:address":"153, Rue de Douai, 59000 Lille",
    "sg:orig_category":"Unclassifiable Establishments",
    "sg:phone":"+33 3 20 52 69 13",
    "sg:province":"Nord Pas-de-Calais",
    "wof:name":"Agir S.a.r.l.",
    "wof:placetype":"venue"
},
  "geometry": {"coordinates":[3.073371,50.618469],"type":"Point"}
}