{
  "type": "Feature",
  "properties": {
    "iso:country":"FR",
    "sg:address":"ZA du Patis des Saules",
    "sg:city":"Vincey",
    "sg:orig_category":"Unclassifiable Establishments",
    "sg:phone":"+33 3 29 67 33 67",
    "sg:postcode":"88450",
    "sg:province":"Lorraine",
    "wof:name":"Vosges Charpentes S.a.r.l.",
    "wof:placetype":"venue"
},
  "geometry": {"coordinates":[6.328075,48.3447],"type":"Point"}
}