{
  "type": "Feature",
  "properties": {
    "addr:full":"9 Grande Rue 88630 Soulosse Sous St \u00c9lophe Lorraine 88630",
    "addr:housenumber":"9",
    "addr:postcode":"88630;88630",
    "addr:street":"Grande Rue;Sous St E\u0301Lophe Lorraine",
    "iso:country":"FR",
    "sg:address":"9 Grande Rue 88630 Soulosse Sous St \u00c9lophe",
    "sg:classifiers":[
        {
            "category":"Bakery",
            "type":"Food & Drink"
        }
    ],
    "sg:phone":"+33 3 29 06 91 92",
    "sg:postcode":"88630",
    "sg:province":"Lorraine",
    "sg:tags":[
        "cake",
        "product",
        "related",
        "bread"
    ],
    "wof:name":"Boulangerie Chane Sarl",
    "wof:placetype":"venue"
},
  "geometry": {"coordinates":[5.733325,48.402817],"type":"Point"}
}