{
  "type": "Feature",
  "properties": {
    "addr:full":"13, Rue Plantagenet, 49100 Angers Pays de Loire",
    "addr:housenumber":"13",
    "addr:postcode":"49100",
    "addr:street":"Rue Plantagenet",
    "iso:country":"FR",
    "sg:address":"13, Rue Plantagenet, 49100 Angers",
    "sg:orig_category":"Unclassifiable Establishments",
    "sg:phone":"+33 2 41 87 14 14",
    "sg:province":"Pays de Loire",
    "wof:name":"Crit Int\u00e9rim",
    "wof:placetype":"venue"
},
  "geometry": {"coordinates":[-0.554905,47.473034],"type":"Point"}
}