{
  "type": "Feature",
  "properties": {
    "iso:country":"FR",
    "sg:address":"Zi Portuaire Du Havre Parc Indus Fourni Usine 76430 Sandouville",
    "sg:classifiers":[
        {
            "category":"Autos & Motor Vehicles",
            "subcategory":"Automobile Sales",
            "type":"Retail Goods"
        }
    ],
    "sg:phone":"+33 2 35 13 38 14",
    "sg:postcode":"76430",
    "sg:province":"Haute Normandie",
    "sg:tags":[
        "equipment",
        "motor-cars",
        "transport"
    ],
    "wof:name":"Siemar",
    "wof:placetype":"venue"
},
  "geometry": {"coordinates":[0.321059,49.499043],"type":"Point"}
}