{
  "type": "Feature",
  "properties": {
    "addr:full":"66 Sadi Carnot; La Garde; 83130 Rhone-Alpes",
    "addr:housenumber":"66",
    "addr:postcode":"83130",
    "addr:street":"Sadi Carnot",
    "iso:country":"FR",
    "sg:address":"66",
    "sg:city":"Sadi Carnot; La Garde; 83130",
    "sg:classifiers":[
        {
            "category":"Banks & Credit Unions",
            "subcategory":"Bank",
            "type":"Services"
        }
    ],
    "sg:phone":"+33 3393218462",
    "sg:province":"Rhone-Alpes",
    "wof:name":"Banque Nationale De Paris",
    "wof:placetype":"venue"
},
  "geometry": {"coordinates":[6.007994,43.124542],"type":"Point"}
}