{
  "type": "Feature",
  "properties": {
    "addr:full":"80 Rte De La Bressandi\u00e8re 79200 Ch\u00e2tillon Sur Thouet Poitou-Charentes 79200",
    "addr:housenumber":"80",
    "addr:postcode":"79200;thouet;79200",
    "addr:street":"Rte De La Bressandie\u0300Re",
    "iso:country":"FR",
    "sg:address":"80 Rte De La Bressandi\u00e8re 79200 Ch\u00e2tillon Sur Thouet",
    "sg:classifiers":[
        {
            "category":"Manufacturing",
            "subcategory":"Metals",
            "type":"Manufacturing & Wholesale Goods"
        }
    ],
    "sg:phone":"+33 5 49 95 10 10",
    "sg:postcode":"79200",
    "sg:province":"Poitou-Charentes",
    "sg:tags":[
        "metallurgy",
        "metalworking",
        "processing"
    ],
    "wof:name":"Bts Industrie",
    "wof:placetype":"venue"
},
  "geometry": {"coordinates":[-0.255633,46.667229],"type":"Point"}
}