{
  "type": "Feature",
  "properties": {
    "addr:full":"B.P. 15, 49600 Gest\u00e9 C\u00e9dex^^Rte de Villedieu, 49600 Gest\u00e9 Pays de Loire",
    "addr:postcode":"49600;49600",
    "addr:street":"B.P. 15",
    "iso:country":"FR",
    "sg:address":"B.P. 15, 49600 Gest\u00e9 C\u00e9dex^^Rte de Villedieu, 49600 Gest\u00e9",
    "sg:orig_category":"Non-Classified Establishments",
    "sg:phone":"+33 2 41 56 66 20",
    "sg:province":"Pays de Loire",
    "wof:name":"P.a.g. S.a.r.l.",
    "wof:placetype":"venue"
},
  "geometry": {"coordinates":[-1.017466,47.151772],"type":"Point"}
}