{
  "type": "Feature",
  "properties": {
    "addr:full":"53101 MAYENNE Champagne",
    "addr:postcode":"53101",
    "iso:country":"FR",
    "sg:address":"53101 MAYENNE",
    "sg:classifiers":[
        {
            "category":"Food & Beverages",
            "subcategory":"Meat & Fish",
            "type":"Retail Goods"
        }
    ],
    "sg:phone":"+33 2 43 04 20 32",
    "sg:province":"Champagne",
    "sg:tags":[
        "processing"
    ],
    "wof:name":"Georges Thiol S.c.s.",
    "wof:placetype":"venue"
},
  "geometry": {"coordinates":[-0.62045,48.304741],"type":"Point"}
}