{
  "type": "Feature",
  "properties": {
    "addr:full":"B.P. 58, 31802 Saint Gaudens C\u00e9dex^^8, Rue Guynemer, 31800 Saint Gaudens Midi Pyr\u00e9n\u00e9es",
    "addr:postcode":"31802;31800",
    "addr:street":"B.P. 58;Rue Guynemer",
    "iso:country":"FR",
    "sg:address":"B.P. 58, 31802 Saint Gaudens C\u00e9dex^^8, Rue Guynemer, 31800 Saint Gaudens",
    "sg:orig_category":"Non-Classified Establishments",
    "sg:phone":"+33 5 61 89 74 77",
    "sg:province":"Midi Pyr\u00e9n\u00e9es",
    "wof:name":"Gestas",
    "wof:placetype":"venue"
},
  "geometry": {"coordinates":[0.723251,43.050159],"type":"Point"}
}