{
  "type": "Feature",
  "properties": {
    "addr:full":"10 Place Du Marche Lezay Poitou-Charentes 79120",
    "addr:housenumber":"10",
    "addr:postcode":"79120",
    "addr:street":"Place Du Marche Lezay",
    "iso:country":"FR",
    "sg:address":"10 Place Du Marche",
    "sg:city":"Lezay",
    "sg:classifiers":[
        {
            "category":"Banks & Credit Unions",
            "subcategory":"Financial Services",
            "type":"Services"
        }
    ],
    "sg:phone":"+33 5 49 29 57 65",
    "sg:postcode":"79120",
    "sg:province":"Poitou-Charentes",
    "sg:tags":[
        "banking",
        "finance",
        "insurance"
    ],
    "wof:name":"Societe De Revision D'expertise De Gestion Et D'organisation (soregor)",
    "wof:placetype":"venue"
},
  "geometry": {"coordinates":[-0.009004,46.265091],"type":"Point"}
}