{
  "type": "Feature",
  "properties": {
    "addr:full":"ZAC La Gr\u00e9rie Rib\u00e9court Dreslincourt Picardie 60170",
    "addr:postcode":"60170",
    "addr:street":"Zac La Gre\u0301Rie Ribe\u0301Court Dreslincourt Picardie",
    "iso:country":"FR",
    "sg:address":"ZAC La Gr\u00e9rie",
    "sg:city":"Rib\u00e9court Dreslincourt",
    "sg:orig_category":"Non-Classified Establishments",
    "sg:phone":"+33 3 44 75 00 93",
    "sg:postcode":"60170",
    "sg:province":"Picardie",
    "wof:name":"E.t.i. S.a.s. - Electricit\u00e9 Technique Industrielle",
    "wof:placetype":"venue"
},
  "geometry": {"coordinates":[2.92245,49.509705],"type":"Point"}
}