{
  "type": "Feature",
  "properties": {
    "addr:full":"9 rue Amp\u00e8re 15000 Aurillac Aurillac Auvergne 15000",
    "addr:housenumber":"9",
    "addr:postcode":"15000;15000",
    "addr:street":"Rue Ampe\u0300Re",
    "iso:country":"FR",
    "sg:address":"9 rue Amp\u00e8re 15000 Aurillac",
    "sg:city":"Aurillac",
    "sg:classifiers":[
        {
            "category":"Transit Center",
            "subcategory":"Passenger",
            "type":"Transportation"
        }
    ],
    "sg:phone":"+33 4 71 64 17 90",
    "sg:postcode":"15000",
    "sg:province":"Auvergne",
    "sg:tags":[
        "umbrella"
    ],
    "wof:name":"Piganiol S.a.",
    "wof:placetype":"venue"
},
  "geometry": {"coordinates":[2.424436,44.912899],"type":"Point"}
}