{
  "type": "Feature",
  "properties": {
    "iso:country":"FR",
    "sg:address":"51, Rue Pigouche, 59100 Roubaix",
    "sg:orig_category":"Unclassifiable Establishments",
    "sg:phone":"+33 3 20 89 45 20",
    "sg:province":"Nord Pas-de-Calais",
    "wof:name":"N.t.e. S.a. - Nord Technique Etiquetage",
    "wof:placetype":"venue"
},
  "geometry": {"coordinates":[3.177742,50.67522],"type":"Point"}
}