{
  "type": "Feature",
  "properties": {
    "addr:full":"Rte d'Aix en Provence - ZAC Terre du Fort Pertuis Nord Pas-de-Calais 84120",
    "addr:postcode":"84120",
    "addr:street":"Rte D'Aix En Provence Zac Terre Du Fort Pertuis Nord",
    "iso:country":"FR",
    "sg:address":"Rte d'Aix en Provence - ZAC Terre du Fort",
    "sg:city":"Pertuis",
    "sg:orig_category":"Non-Classified Establishments",
    "sg:phone":"+33 4 90 79 87 77",
    "sg:postcode":"84120",
    "sg:province":"Nord Pas-de-Calais",
    "wof:name":"C.i.j. S.a. - Constructions Isothermes Joseph",
    "wof:placetype":"venue"
},
  "geometry": {"coordinates":[5.501571,43.684769],"type":"Point"}
}