{
  "type": "Feature",
  "properties": {
    "iso:country":"FR",
    "sg:address":"zi Louisi\u00e8re 85290 Mortagne sur S\u00e8vre",
    "sg:classifiers":[
        {
            "category":"Manufacturing",
            "subcategory":"Metals",
            "type":"Manufacturing & Wholesale Goods"
        }
    ],
    "sg:phone":"+33 2 51 65 03 75",
    "sg:postcode":"85290",
    "sg:province":"Pays de Loire",
    "sg:tags":[
        "-",
        "machine",
        "equipment",
        "engineering",
        "machinery",
        "mechanical"
    ],
    "wof:name":"Aob (sa)",
    "wof:placetype":"venue"
},
  "geometry": {"coordinates":[-0.953982,46.994831],"type":"Point"}
}