{
  "type": "Feature",
  "properties": {
    "iso:country":"FR",
    "sg:address":"48 bis, Chemin de Barray, 69007 Lyon",
    "sg:orig_category":"Non-Classified Establishments",
    "sg:phone":"+33 4 78 58 90 28",
    "sg:province":"Rhone-Alpes",
    "wof:name":"Yacc S.a.r.l. - Yves Annie Cruz Consultant",
    "wof:placetype":"venue"
},
  "geometry": {"coordinates":[4.842415,45.746235],"type":"Point"}
}