{
  "type": "Feature",
  "properties": {
    "iso:country":"FR",
    "sg:address":"Rue Du 19 Mars 1962 95670 MARLY LA VILLE",
    "sg:classifiers":[
        {
            "category":"Travel",
            "subcategory":"Hotels & Motels",
            "type":"Entertainment"
        }
    ],
    "sg:phone":"+33 3 27 36 06 89",
    "sg:postcode":"95670",
    "sg:province":"Ile de France",
    "sg:tags":[
        "equipment",
        "hotels",
        "restaurant"
    ],
    "wof:name":"Solideal France S.a.r.l.",
    "wof:placetype":"venue"
},
  "geometry": {"coordinates":[2.502209,49.092518],"type":"Point"}
}