{
  "type": "Feature",
  "properties": {
    "iso:country":"FR",
    "sg:address":"Capitainerie du Nouveau Port Quai Napol\u00e9on",
    "sg:city":"Vallauris",
    "sg:orig_category":"Unclassifiable Establishments",
    "sg:phone":"+33 4 93 63 30 30",
    "sg:postcode":"06220",
    "sg:province":"Rhone-Alpes",
    "wof:name":"S.n.p.v.g.j. S.a. - Soci\u00e9t\u00e9 Du Nouveau Port Vallauris Golfe Juan",
    "wof:placetype":"venue"
},
  "geometry": {"coordinates":[7.06074,43.573238],"type":"Point"}
}