{
  "type": "Feature",
  "properties": {
    "addr:full":"Maison Meharon 64220 Ascarat Ascarat Aquitaine 64220",
    "addr:postcode":"64220;64220",
    "iso:country":"FR",
    "sg:address":"Maison Meharon 64220 Ascarat",
    "sg:city":"Ascarat",
    "sg:classifiers":[
        {
            "category":"Bakery",
            "type":"Food & Drink"
        }
    ],
    "sg:phone":"+33 5 59 37 08 81",
    "sg:postcode":"64220",
    "sg:province":"Aquitaine",
    "sg:tags":[
        "cake",
        "product",
        "related",
        "bread"
    ],
    "wof:name":"Boulangerie Des Pyrenees",
    "wof:placetype":"venue"
},
  "geometry": {"coordinates":[-1.19582,43.104042],"type":"Point"}
}