{
  "type": "Feature",
  "properties": {
    "iso:country":"FR",
    "sg:address":"16 Rte De Champigny 51430 Tinqueux",
    "sg:classifiers":[
        {
            "category":"Professional",
            "subcategory":"Advertising",
            "type":"Services"
        }
    ],
    "sg:phone":"+33 3 26 84 08 09",
    "sg:postcode":"51430",
    "sg:province":"Champagne",
    "sg:tags":[
        "communication",
        "printing",
        "medium",
        "publishing"
    ],
    "wof:name":"Dauphin Clear Chanel",
    "wof:placetype":"venue"
},
  "geometry": {"coordinates":[3.984544,49.254814],"type":"Point"}
}