{
  "type": "Feature",
  "properties": {
    "addr:full":"Rue du Flocon Mouvaux Nord Pas-de-Calais 59420",
    "addr:postcode":"59420",
    "addr:street":"Rue Du Flocon",
    "iso:country":"FR",
    "sg:address":"Rue du Flocon",
    "sg:city":"Mouvaux",
    "sg:orig_category":"Unclassifiable Establishments",
    "sg:phone":"+33 3 20 69 12 21",
    "sg:postcode":"59420",
    "sg:province":"Nord Pas-de-Calais",
    "wof:name":"Les Fa\u00e7onnables S.a.",
    "wof:placetype":"venue"
},
  "geometry": {"coordinates":[3.14165,50.702068],"type":"Point"}
}