{
  "type": "Feature",
  "properties": {
    "addr:full":"76590 Anneville Sur Scie Haute Normandie 76590",
    "addr:postcode":"76590;76590",
    "addr:street":"Anneville;Haute Normandie",
    "iso:country":"FR",
    "sg:address":"76590 Anneville Sur Scie",
    "sg:classifiers":[
        {
            "category":"Food Court",
            "type":"Food & Drink"
        }
    ],
    "sg:phone":"+33 2 35 04 63 70",
    "sg:postcode":"76590",
    "sg:province":"Haute Normandie",
    "sg:tags":[
        "product",
        "related"
    ],
    "wof:name":"Csr Sa",
    "wof:placetype":"venue"
},
  "geometry": {"coordinates":[1.08604,49.830765],"type":"Point"}
}