{
  "type": "Feature",
  "properties": {
    "addr:full":"all\u00e9e du Saosnois 72600 Mamers Pays de Loire",
    "addr:postcode":"72600",
    "addr:street":"Alle\u0301E Du Saosnois",
    "iso:country":"FR",
    "sg:address":"all\u00e9e du Saosnois 72600 Mamers",
    "sg:classifiers":[
        {
            "category":"Shopping",
            "subcategory":"Stationery & Office Supplies",
            "type":"Retail Goods"
        }
    ],
    "sg:phone":"+33 2 43 31 15 50",
    "sg:province":"Pays de Loire",
    "sg:tags":[
        "packaging"
    ],
    "wof:name":"Rey Emballages S.a.r.l.",
    "wof:placetype":"venue"
},
  "geometry": {"coordinates":[0.383005,48.349854],"type":"Point"}
}