{
  "type": "Feature",
  "properties": {
    "iso:country":"FR",
    "sg:address":"135 Rue Pierre Seghers 26800 Portes Les Valence",
    "sg:classifiers":[
        {
            "category":"Professional",
            "subcategory":"Engineering",
            "type":"Services"
        }
    ],
    "sg:phone":"+33 4 75 57 98 40",
    "sg:postcode":"26800",
    "sg:province":"Rhone-Alpes",
    "sg:tags":[
        "machine",
        "-",
        "mechanical"
    ],
    "wof:name":"Frimaval Sa",
    "wof:placetype":"venue"
},
  "geometry": {"coordinates":[4.866864,44.876194],"type":"Point"}
}