{
  "type": "Feature",
  "properties": {
    "addr:full":"ZI de Thuisseau Montlouis sur Loire Centre 37270",
    "addr:postcode":"37270",
    "addr:street":"Zi De Thuisseau",
    "iso:country":"FR",
    "sg:address":"ZI de Thuisseau",
    "sg:city":"Montlouis sur Loire",
    "sg:orig_category":"Unclassifiable Establishments",
    "sg:phone":"+33 2 47 45 05 84",
    "sg:postcode":"37270",
    "sg:province":"Centre",
    "wof:name":"Philocolor-prochinor S.a.",
    "wof:placetype":"venue"
},
  "geometry": {"coordinates":[0.827175,47.388725],"type":"Point"}
}