{
  "type": "Feature",
  "properties": {
    "addr:full":"B.P. 43, 55101 Verdun C\u00e9dex^^Rue Saint Exup\u00e9ry, 55100 Verdun Lorraine",
    "addr:postcode":"55101;exupe\u0301ry 55100",
    "addr:street":"B.P. 43",
    "iso:country":"FR",
    "sg:address":"B.P. 43, 55101 Verdun C\u00e9dex^^Rue Saint Exup\u00e9ry, 55100 Verdun",
    "sg:orig_category":"Non-Classified Establishments",
    "sg:phone":"+33 3 29 86 60 13",
    "sg:province":"Lorraine",
    "wof:name":"Herbemont A.d. S.a.",
    "wof:placetype":"venue"
},
  "geometry": {"coordinates":[5.383225,49.164806],"type":"Point"}
}