{
  "type": "Feature",
  "properties": {
    "addr:full":"25, Av. de la Lib\u00e9ration, 38370 Les Roches de Condrieu Rhone-Alpes 38370",
    "addr:postcode":"38370;38370",
    "addr:street":"25 Av. De La Libe\u0301Ration;Rhone-Alpes",
    "iso:country":"FR",
    "sg:address":"25, Av. de la Lib\u00e9ration, 38370 Les Roches de Condrieu",
    "sg:orig_category":"Unclassifiable Establishments",
    "sg:phone":"+33 4 74 56 40 76",
    "sg:postcode":"38370",
    "sg:province":"Rhone-Alpes",
    "wof:name":"Etablissements C\u00f4te S.a.",
    "wof:placetype":"venue"
},
  "geometry": {"coordinates":[4.76771,45.452499],"type":"Point"}
}