{
  "type": "Feature",
  "properties": {
    "addr:full":"La Verrerie 21370 VELARS SUR OUCHE Lantenay Bourgogne 21370",
    "addr:postcode":"21370;21370",
    "addr:street":"Bourgogne",
    "iso:country":"FR",
    "sg:address":"La Verrerie 21370 VELARS SUR OUCHE",
    "sg:city":"Lantenay",
    "sg:orig_category":"Igniter Mechanisms",
    "sg:phone":"+33 3 80 76 06 06",
    "sg:postcode":"21370",
    "sg:province":"Bourgogne",
    "wof:name":"Electro-centre S.a.",
    "wof:placetype":"venue"
},
  "geometry": {"coordinates":[4.908493,47.320831],"type":"Point"}
}