{
  "type": "Feature",
  "properties": {
    "iso:country":"FR",
    "sg:address":"6 Rue Gustave Eiffel BP 8206 44982 Ste Luce Sur Loire",
    "sg:classifiers":[
        {
            "category":"Professional",
            "subcategory":"Computer Services",
            "type":"Services"
        }
    ],
    "sg:phone":"+33 2 40 25 82 51",
    "sg:province":"Basse Normandie",
    "sg:tags":[
        "information",
        "technology",
        "software"
    ],
    "wof:name":"Mediane Informatique Sa",
    "wof:placetype":"venue"
},
  "geometry": {"coordinates":[-1.485641,47.26273],"type":"Point"}
}