{
  "type": "Feature",
  "properties": {
    "iso:country":"FR",
    "sg:address":"2, Rue A de Caulaincourt, 80240 Roisel",
    "sg:orig_category":"Unclassifiable Establishments",
    "sg:phone":"+33 3 22 86 73 59",
    "sg:province":"Picardie",
    "wof:name":"Roisel Mat\u00e9riaux S.a.r.l.",
    "wof:placetype":"venue"
},
  "geometry": {"coordinates":[3.097455,49.945225],"type":"Point"}
}