{
  "type": "Feature",
  "properties": {
    "iso:country":"FR",
    "sg:address":"Les Chatelliers 41500 Su\u00e8vres",
    "sg:city":"Su\u00e8vres",
    "sg:orig_category":"Unclassifiable Establishments",
    "sg:phone":"+33 2 54 87 80 62",
    "sg:postcode":"41500",
    "sg:province":"Centre",
    "wof:name":"Terrier Jardins S.a.r.l.",
    "wof:placetype":"venue"
},
  "geometry": {"coordinates":[1.470537,47.66563],"type":"Point"}
}