{
  "type": "Feature",
  "properties": {
    "addr:full":"27 Rue De L'Industrie 67400 Illkirch Geispolsheim Alsace 67400",
    "addr:housenumber":"27",
    "addr:postcode":"67400;67400",
    "addr:street":"Rue De L'Industrie",
    "iso:country":"FR",
    "sg:address":"27 Rue De L'Industrie 67400 Illkirch",
    "sg:city":"Geispolsheim",
    "sg:classifiers":[
        {
            "category":"Manufacturing",
            "subcategory":"Tools & Machinery",
            "type":"Manufacturing & Wholesale Goods"
        }
    ],
    "sg:phone":"+33 3 88 67 47 10",
    "sg:postcode":"67400",
    "sg:province":"Alsace",
    "sg:tags":[
        "metallurgy",
        "metalworking"
    ],
    "wof:name":"Ake France Sa",
    "wof:placetype":"venue"
},
  "geometry": {"coordinates":[7.731668,48.530483],"type":"Point"}
}