{
  "type": "Feature",
  "properties": {
    "iso:country":"FR",
    "sg:address":"15, Rue de la Vall\u00e9e, 67520 Kuttolsheim",
    "sg:city":"Kuttolsheim",
    "sg:orig_category":"Non-Classified Establishments",
    "sg:phone":"+33 3 88 87 66 37",
    "sg:postcode":"67520",
    "sg:province":"Alsace",
    "wof:name":"J.m.f. Bois De Chauffage S.a.r.l.",
    "wof:placetype":"venue"
},
  "geometry": {"coordinates":[7.520807,48.645542],"type":"Point"}
}