{
  "type": "Feature",
  "properties": {
    "addr:full":"25 Rue Nationale 62117 Brebi\u00e8res Nord Pas-de-Calais",
    "addr:housenumber":"25",
    "addr:postcode":"62117",
    "addr:street":"Rue Nationale",
    "iso:country":"FR",
    "sg:address":"25 Rue Nationale 62117 Brebi\u00e8res",
    "sg:classifiers":[
        {
            "category":"Professional",
            "type":"Services"
        }
    ],
    "sg:phone":"+33 3 21 50 11 65",
    "sg:province":"Nord Pas-de-Calais",
    "sg:tags":[
        "transport",
        "road"
    ],
    "wof:name":"Belval Lionel",
    "wof:placetype":"venue"
},
  "geometry": {"coordinates":[3.02663,50.340862],"type":"Point"}
}