{
  "type": "Feature",
  "properties": {
    "addr:full":"1, Rue Auguste Gauthier, 49000 Angers Pays de Loire",
    "addr:housenumber":"1",
    "addr:postcode":"49000",
    "addr:street":"Rue Auguste Gauthier",
    "iso:country":"FR",
    "sg:address":"1, Rue Auguste Gauthier, 49000 Angers",
    "sg:orig_category":"Non-Classified Establishments",
    "sg:phone":"+33 2 41 86 91 91",
    "sg:province":"Pays de Loire",
    "wof:name":"Sceta Transport",
    "wof:placetype":"venue"
},
  "geometry": {"coordinates":[-0.547697,47.449478],"type":"Point"}
}