{
  "type": "Feature",
  "properties": {
    "iso:country":"FR",
    "sg:address":"15, Place Simon Vollant, 59000 Lille",
    "sg:orig_category":"Non-Classified Establishments",
    "sg:phone":"+33 3 20 86 15 15",
    "sg:province":"Nord Pas-de-Calais",
    "wof:name":"V.i.c. S.a.r.l. - Vid\u00e9o Infographie Communication",
    "wof:placetype":"venue"
},
  "geometry": {"coordinates":[3.069199,50.629326],"type":"Point"}
}