{
  "type": "Feature",
  "properties": {
    "iso:country":"FR",
    "sg:address":"Quartier Orgouze",
    "sg:city":"La Tour d'Aigues",
    "sg:orig_category":"Non-Classified Establishments",
    "sg:phone":"+33 4 90 07 36 84",
    "sg:postcode":"84240",
    "sg:province":"Rhone-Alpes",
    "wof:name":"Doga",
    "wof:placetype":"venue"
},
  "geometry": {"coordinates":[5.437254,43.773575],"type":"Point"}
}