{
  "type": "Feature",
  "properties": {
    "iso:country":"FR",
    "sg:address":"25 rue Cuvier; Valentigney; 25700",
    "sg:classifiers":[
        {
            "category":"Banks & Credit Unions",
            "subcategory":"Bank",
            "type":"Services"
        }
    ],
    "sg:phone":"+33 3 81 37 92 72",
    "sg:postcode":"25700",
    "sg:province":"Franche Comt\u00e9",
    "wof:name":"Cr\u00e9dit Industriel D'alsace, Et De Lorraine Sa",
    "wof:placetype":"venue"
},
  "geometry": {"coordinates":[6.835595,47.46315],"type":"Point"}
}