{
  "type": "Feature",
  "properties": {
    "addr:full":"Route De Vannes 44802 St Herblain Pays de Loire",
    "addr:postcode":"44802",
    "addr:street":"Route De Vannes;Herblain",
    "iso:country":"FR",
    "sg:address":"Route De Vannes 44802 St Herblain",
    "sg:classifiers":[
        {
            "category":"Autos & Motor Vehicles",
            "subcategory":"Automobile Sales",
            "type":"Retail Goods"
        }
    ],
    "sg:phone":"+33 2 40 16 17 18",
    "sg:province":"Pays de Loire",
    "sg:tags":[
        "equipment",
        "industrial",
        "transport"
    ],
    "wof:name":"Lts Sa",
    "wof:placetype":"venue"
},
  "geometry": {"coordinates":[-1.617495,47.25032],"type":"Point"}
}