{
  "type": "Feature",
  "properties": {
    "addr:full":"Le RutoireLieu-Dit Le Bourg 61130 BELLEME Bell\u00eame Basse Normandie 61130",
    "addr:postcode":"61130;61130",
    "addr:street":"Le Bourg",
    "iso:country":"FR",
    "sg:address":"Le RutoireLieu-Dit Le Bourg 61130 BELLEME",
    "sg:city":"Bell\u00eame",
    "sg:classifiers":[
        {
            "category":"Home & Garden",
            "subcategory":"Carpets & Floor Coverings",
            "type":"Retail Goods"
        }
    ],
    "sg:phone":"+33 2 99 05 77 77",
    "sg:postcode":"61130",
    "sg:province":"Basse Normandie",
    "sg:tags":[
        "flooring",
        "parquet"
    ],
    "wof:name":"Chene De L Orne S.a.",
    "wof:placetype":"venue"
},
  "geometry": {"coordinates":[0.544102,48.268017],"type":"Point"}
}