{
  "type": "Feature",
  "properties": {
    "addr:full":"Le Grand Pont 83310 Grimaud Lorraine",
    "addr:postcode":"83310",
    "addr:street":"Pont",
    "iso:country":"FR",
    "sg:address":"Le Grand Pont 83310 Grimaud",
    "sg:classifiers":[
        {
            "category":"Autos & Motor Vehicles",
            "subcategory":"Boat Sales",
            "type":"Retail Goods"
        }
    ],
    "sg:phone":"+33 4 94 56 46 81",
    "sg:province":"Lorraine",
    "sg:tags":[
        "equipment",
        "transport"
    ],
    "wof:name":"Assistance Nautique Du Golfe",
    "wof:placetype":"venue"
},
  "geometry": {"coordinates":[6.465188,43.207832],"type":"Point"}
}