{
  "type": "Feature",
  "properties": {
    "iso:country":"FR",
    "sg:address":"Chemin de la Louvi\u00e8re - ZI",
    "sg:city":"Suippes",
    "sg:orig_category":"Non-Classified Establishments",
    "sg:phone":"+33 3 26 64 36 94",
    "sg:postcode":"51600",
    "sg:province":"Champagne",
    "wof:name":"Suippes Thermolaquage S.a.r.l.",
    "wof:placetype":"venue"
},
  "geometry": {"coordinates":[4.533916,49.132465],"type":"Point"}
}