{
  "type": "Feature",
  "properties": {
    "addr:full":"161 Route Sarves 74370 Metz Tessy Rhone-Alpes 74370",
    "addr:housenumber":"161",
    "addr:postcode":"74370;74370",
    "addr:street":"Route Sarves;Rhone-Alpes",
    "iso:country":"FR",
    "sg:address":"161 Route Sarves 74370 Metz Tessy",
    "sg:classifiers":[
        {
            "category":"Home & Garden",
            "subcategory":"Furniture",
            "type":"Retail Goods"
        }
    ],
    "sg:phone":"+33 4 50 09 18 00",
    "sg:postcode":"74370",
    "sg:province":"Rhone-Alpes",
    "sg:tags":[
        "household",
        "wood"
    ],
    "wof:name":"Societe Fournier",
    "wof:placetype":"venue"
},
  "geometry": {"coordinates":[6.114937,45.9277],"type":"Point"}
}