{
  "type": "Feature",
  "properties": {
    "iso:country":"FR",
    "sg:address":"B.P. 13, 50110 Tourlaville^^497, Rue Jean Moulin, 50110 Tourlaville",
    "sg:city":"Tourlaville",
    "sg:orig_category":"Non-Classified Establishments",
    "sg:phone":"+33 2 33 20 42 78",
    "sg:postcode":"50110",
    "sg:province":"Basse Normandie",
    "wof:name":"R.l.d. Cherbourg S.a.s. - R\u00e9gie Linge D\u00e9veloppement",
    "wof:placetype":"venue"
},
  "geometry": {"coordinates":[-1.524824,49.60664],"type":"Point"}
}