{
  "type": "Feature",
  "properties": {
    "iso:country":"FR",
    "sg:address":"ZI les Estroublancs - Lot. N\u00b08",
    "sg:city":"Vitrolles",
    "sg:orig_category":"Unclassifiable Establishments",
    "sg:phone":"+33 4 42 10 57 57",
    "sg:postcode":"13127",
    "sg:province":"Midi Pyr\u00e9n\u00e9es",
    "wof:name":"Via Location France Provinces",
    "wof:placetype":"venue"
},
  "geometry": {"coordinates":[5.253005,43.449944],"type":"Point"}
}