{
  "type": "Feature",
  "properties": {
    "addr:full":"ZI les Estroublancs - Lot. N\u00b08 Vitrolles Midi Pyr\u00e9n\u00e9es 13127",
    "addr:housenumber":"lot. n\u00b08",
    "addr:postcode":"13127",
    "addr:street":"Zi Les",
    "iso:country":"FR",
    "sg:address":"ZI les Estroublancs - Lot. N\u00b08",
    "sg:city":"Vitrolles",
    "sg:orig_category":"Unclassifiable Establishments",
    "sg:phone":"+33 4 42 10 57 57",
    "sg:postcode":"13127",
    "sg:province":"Midi Pyr\u00e9n\u00e9es",
    "wof:name":"Via Location France Provinces",
    "wof:placetype":"venue"
},
  "geometry": {"coordinates":[5.253005,43.449944],"type":"Point"}
}