{
  "type": "Feature",
  "properties": {
    "addr:full":"10 Pl De L'Abbaye 42030 St Etienne Cedex 2 Champagne",
    "addr:housenumber":"10",
    "addr:postcode":"42030;etienne cedex 2",
    "addr:street":"Pl De L'Abbaye",
    "iso:country":"FR",
    "sg:address":"10 Pl De L'Abbaye 42030 St Etienne Cedex 2",
    "sg:classifiers":[
        {
            "category":"Professional",
            "subcategory":"Business Services",
            "type":"Services"
        }
    ],
    "sg:phone":"+33 4 77 81 86 00",
    "sg:province":"Champagne",
    "sg:tags":[
        "training",
        "advice"
    ],
    "wof:name":"College Notre Dame De Valbenoite",
    "wof:placetype":"venue"
},
  "geometry": {"coordinates":[4.38545,45.44096],"type":"Point"}
}