{
  "type": "Feature",
  "properties": {
    "iso:country":"FR",
    "sg:address":"47 Av G\u00e9n\u00e9ral De Gaulle 59710 Pont Un Marcq",
    "sg:classifiers":[
        {
            "category":"Wholesale",
            "subcategory":"Machinery & Supplies",
            "type":"Manufacturing & Wholesale Goods"
        }
    ],
    "sg:phone":"+33 3 20 41 48 88",
    "sg:province":"Nord Pas-de-Calais",
    "sg:tags":[
        "equipment",
        "optical",
        "precision",
        "instrument"
    ],
    "wof:name":"Agfa Gevaert Sa",
    "wof:placetype":"venue"
},
  "geometry": {"coordinates":[-75.29162599999999,43.169456],"type":"Point"}
}