{
  "type": "Feature",
  "properties": {
    "iso:country":"FR",
    "sg:address":"753 Rue Pierre Et Marie Curie 54710 Ludres",
    "sg:classifiers":[
        {
            "category":"Food & Beverages",
            "subcategory":"Dairy",
            "type":"Retail Goods"
        }
    ],
    "sg:phone":"+33 3 83 26 35 75",
    "sg:postcode":"54710",
    "sg:province":"Lorraine",
    "sg:tags":[
        "product",
        "related"
    ],
    "wof:name":"Ewoco Lorraine",
    "wof:placetype":"venue"
},
  "geometry": {"coordinates":[6.193227,48.615688],"type":"Point"}
}