{
  "type": "Feature",
  "properties": {
    "iso:country":"FR",
    "sg:address":"348 rte de Dieppe; Deville les Rouen; 76250",
    "sg:classifiers":[
        {
            "category":"Banks & Credit Unions",
            "subcategory":"Bank",
            "type":"Services"
        }
    ],
    "sg:phone":"+33 3335756740",
    "sg:postcode":"76250",
    "sg:province":"Haute Normandie",
    "wof:name":"Banque Nationale De Paris",
    "wof:placetype":"venue"
},
  "geometry": {"coordinates":[1.050416,49.46965],"type":"Point"}
}