{
  "type": "Feature",
  "properties": {
    "addr:full":"21 av Mar de Saxe; Lyon Rhone-Alpes",
    "addr:street":"21 Av Mar De Saxe",
    "iso:country":"FR",
    "sg:address":"21 av Mar de Saxe; Lyon",
    "sg:classifiers":[
        {
            "category":"Banks & Credit Unions",
            "subcategory":"Bank",
            "type":"Services"
        }
    ],
    "sg:phone":"+33 3378249136",
    "sg:province":"Rhone-Alpes",
    "wof:name":"Banque De Savoie",
    "wof:placetype":"venue"
},
  "geometry": {"coordinates":[-90.541031,34.219009],"type":"Point"}
}