{
  "type": "Feature",
  "properties": {
    "addr:full":"9BIS rue Henri Martin 92100 Boulogne Billancourt Ile de France 92100",
    "addr:housenumber":"9bis",
    "addr:postcode":"92100;92100",
    "addr:street":"Rue Henri Martin",
    "iso:country":"FR",
    "sg:address":"9BIS rue Henri Martin 92100 Boulogne Billancourt",
    "sg:classifiers":[
        {
            "category":"Banks & Credit Unions",
            "subcategory":"Investment Brokerage",
            "type":"Services"
        }
    ],
    "sg:phone":"+33 1 46 10 08 80",
    "sg:postcode":"92100",
    "sg:province":"Ile de France",
    "sg:tags":[
        "development",
        "management"
    ],
    "wof:name":"Business Dynamic Sarl",
    "wof:placetype":"venue"
},
  "geometry": {"coordinates":[2.251484,48.837456],"type":"Point"}
}