{
  "type": "Feature",
  "properties": {
    "iso:country":"FR",
    "sg:address":"56 rue de Lille 59940 Estaires",
    "sg:classifiers":[
        {
            "category":"Utilities",
            "subcategory":"Cable",
            "type":"Services"
        }
    ],
    "sg:phone":"+33 3 28 48 80 66",
    "sg:province":"Nord Pas-de-Calais",
    "sg:tags":[
        "equipment",
        "ventilation"
    ],
    "wof:name":"Madeleine Sa",
    "wof:placetype":"venue"
},
  "geometry": {"coordinates":[2.733648,50.643497],"type":"Point"}
}