{
  "type": "Feature",
  "properties": {
    "addr:full":"70, Rue du Javelot - Tour Sapporo, 75645 Paris C\u00e9dex 13 \u00cele-de-France",
    "addr:housenumber":"70",
    "addr:postcode":"75645",
    "addr:street":"Rue Du Javelot Tour",
    "iso:country":"FR",
    "sg:address":"70, Rue du Javelot - Tour Sapporo, 75645 Paris C\u00e9dex 13",
    "sg:orig_category":"Non-Classified Establishments",
    "sg:phone":"+33 1 53 94 53 00",
    "sg:province":"\u00cele-de-France",
    "wof:name":"M.h. Conseils S.a.",
    "wof:placetype":"venue"
},
  "geometry": {"coordinates":[2.36448,48.82629],"type":"Point"}
}