{
  "type": "Feature",
  "properties": {
    "addr:full":"Chem De L' Ar\u00e9ous 40440 Ondres Ondres Aquitaine 40440",
    "addr:postcode":"40440;40440",
    "addr:street":"Chem De L ' Are\u0301Ous",
    "iso:country":"FR",
    "sg:address":"Chem De L' Ar\u00e9ous 40440 Ondres",
    "sg:city":"Ondres",
    "sg:classifiers":[
        {
            "category":"Farming",
            "subcategory":"Livestock Farm",
            "type":"Manufacturing & Wholesale Goods"
        }
    ],
    "sg:phone":"+33 5 59 45 30 74",
    "sg:postcode":"40440",
    "sg:province":"Aquitaine",
    "sg:tags":[
        "breeding",
        "agriculture",
        "animal"
    ],
    "wof:name":"Stevenot Ets Sarl",
    "wof:placetype":"venue"
},
  "geometry": {"coordinates":[-1.443808,43.556473],"type":"Point"}
}