{
  "type": "Feature",
  "properties": {
    "iso:country":"FR",
    "sg:address":"445 Bd De L'Europe Artoipole 62118 Monchy Le Preux",
    "sg:classifiers":[
        {
            "category":"Manufacturing",
            "subcategory":"Motor Vehicles & Parts",
            "type":"Manufacturing & Wholesale Goods"
        }
    ],
    "sg:phone":"+33 3 21 21 39 50",
    "sg:postcode":"62118",
    "sg:province":"Nord Pas-de-Calais",
    "sg:tags":[
        "engine",
        "machine",
        "engineering",
        "-",
        "mechanical"
    ],
    "wof:name":"Caterpillar Transmissions France Sarl",
    "wof:placetype":"venue"
},
  "geometry": {"coordinates":[2.89367,50.26997],"type":"Point"}
}