{
  "type": "Feature",
  "properties": {
    "iso:country":"FR",
    "sg:address":"6, Rue Saint Vincent, 44330 Vallet",
    "sg:orig_category":"Unclassifiable Establishments",
    "sg:phone":"+33 2 40 36 69 70",
    "sg:province":"Pays de Loire",
    "wof:name":"Subileau S.a.",
    "wof:placetype":"venue"
},
  "geometry": {"coordinates":[-1.269519,47.160934],"type":"Point"}
}