{
  "type": "Feature",
  "properties": {
    "addr:full":"ZA Rohrwiller Alsace 67410",
    "addr:postcode":"67410",
    "addr:street":"Za Rohrwiller",
    "iso:country":"FR",
    "sg:address":"ZA",
    "sg:city":"Rohrwiller",
    "sg:orig_category":"Unclassifiable Establishments",
    "sg:phone":"+33 3 88 63 60 48",
    "sg:postcode":"67410",
    "sg:province":"Alsace",
    "wof:name":"Sutter Et Compagnie S.a.r.l.",
    "wof:placetype":"venue"
},
  "geometry": {"coordinates":[7.952345,48.765106],"type":"Point"}
}