{
  "type": "Feature",
  "properties": {
    "iso:country":"FR",
    "sg:address":"B.P. 191, 70004 Vesoul C\u00e9dex^^17, Rue de l'Industrie, 70000 Vesoul",
    "sg:orig_category":"Non-Classified Establishments",
    "sg:phone":"+33 3 84 75 86 66",
    "sg:postcode":"70000",
    "sg:province":"Franche Comt\u00e9",
    "wof:name":"Durlumen S.a.",
    "wof:placetype":"venue"
},
  "geometry": {"coordinates":[6.161116,47.639606],"type":"Point"}
}