{
  "type": "Feature",
  "properties": {
    "addr:full":"105 Rue Du Faubourg Madeleine Bat I 3 Orl\u00e9ans Centre 45000",
    "addr:housenumber":"105;3",
    "addr:postcode":"45000",
    "addr:street":"Rue Du Faubourg Madeleine Bat I",
    "iso:country":"FR",
    "sg:address":"105 Rue Du Faubourg Madeleine Bat I 3",
    "sg:city":"Orl\u00e9ans",
    "sg:classifiers":[
        {
            "category":"Banks & Credit Unions",
            "subcategory":"Financial Services",
            "type":"Services"
        }
    ],
    "sg:phone":"+33 2 38 88 10 11",
    "sg:postcode":"45000",
    "sg:province":"Centre",
    "sg:tags":[
        "banking",
        "finance",
        "insurance"
    ],
    "wof:name":"La Mondiale",
    "wof:placetype":"venue"
},
  "geometry": {"coordinates":[1.879969,47.899624],"type":"Point"}
}