{
  "type": "Feature",
  "properties": {
    "addr:full":"15 Pl De La Porte De Paris 77000 Melun Ile de France 77000",
    "addr:housenumber":"15",
    "addr:postcode":"77000;ile;77000",
    "addr:street":"Pl De La Porte De Paris;France",
    "iso:country":"FR",
    "sg:address":"15 Pl De La Porte De Paris 77000 Melun",
    "sg:classifiers":[
        {
            "category":"Wholesale",
            "subcategory":"Medical Equipment & Supplies",
            "type":"Manufacturing & Wholesale Goods"
        }
    ],
    "sg:phone":"+33 1 64 37 01 58",
    "sg:postcode":"77000",
    "sg:province":"Ile de France",
    "sg:tags":[
        "instrument",
        "health",
        "-",
        "precision"
    ],
    "wof:name":"Institut De L'audition",
    "wof:placetype":"venue"
},
  "geometry": {"coordinates":[2.658258,48.540333],"type":"Point"}
}