{
  "type": "Feature",
  "properties": {
    "addr:full":"238 bis, Av du g\u00e9n\u00e9ral de gaulle, 37540 Saint Cyr sur Loire Saint-Cyr-sur-Loire Centre 37540",
    "addr:housenumber":"238 bis",
    "addr:postcode":"37540;37540",
    "addr:street":"Av Du Ge\u0301Ne\u0301Ral De Gaulle;Cyr",
    "iso:country":"FR",
    "sg:address":"238 bis, Av du g\u00e9n\u00e9ral de gaulle, 37540 Saint Cyr sur Loire",
    "sg:city":"Saint-Cyr-sur-Loire",
    "sg:orig_category":"Unclassifiable Establishments",
    "sg:phone":"+33 2 47 49 13 50",
    "sg:postcode":"37540",
    "sg:province":"Centre",
    "wof:name":"Desautel S.a.",
    "wof:placetype":"venue"
},
  "geometry": {"coordinates":[0.65554,47.418831],"type":"Point"}
}