{
  "type": "Feature",
  "properties": {
    "iso:country":"FR",
    "sg:address":"6 rue Marcel Dassault 93360 Neuilly Plaisance",
    "sg:orig_category":"Castors",
    "sg:phone":"+33 1 43 00 60 30",
    "sg:postcode":"93360",
    "sg:province":"Ile de France",
    "wof:name":"Cerdis S.a.",
    "wof:placetype":"venue"
},
  "geometry": {"coordinates":[2.516068,48.864792],"type":"Point"}
}