{
  "type": "Feature",
  "properties": {
    "addr:full":"9 Bis Rue Cl\u00e9ment Ader 60200 Compiegne Picardie 60200",
    "addr:housenumber":"9 bis",
    "addr:postcode":"60200;60200",
    "addr:street":"Rue Cle\u0301Ment Ader;Picardie",
    "iso:country":"FR",
    "sg:address":"9 Bis Rue Cl\u00e9ment Ader 60200 Compiegne",
    "sg:classifiers":[
        {
            "category":"Professional",
            "subcategory":"Engineering",
            "type":"Services"
        }
    ],
    "sg:phone":"+33 3 44 23 20 17",
    "sg:postcode":"60200",
    "sg:province":"Picardie",
    "sg:tags":[
        "machine",
        "-",
        "mechanical"
    ],
    "wof:name":"Proxiserve",
    "wof:placetype":"venue"
},
  "geometry": {"coordinates":[2.788226,49.394768],"type":"Point"}
}