{
  "type": "Feature",
  "properties": {
    "addr:full":"71 Avenue Franklin D Roosevelt 75008 Paris Ile de France",
    "addr:housenumber":"71",
    "addr:postcode":"d;75008",
    "addr:street":"Avenue Franklin",
    "iso:country":"FR",
    "sg:address":"71 Avenue Franklin D Roosevelt 75008 Paris",
    "sg:classifiers":[
        {
            "category":"Manufacturing",
            "subcategory":"Paper Products",
            "type":"Manufacturing & Wholesale Goods"
        }
    ],
    "sg:phone":"+33 1 53 93 61 70",
    "sg:province":"Ile de France",
    "sg:tags":[
        "packaging",
        "material",
        "-",
        "cardboard"
    ],
    "wof:name":"Sopal",
    "wof:placetype":"venue"
},
  "geometry": {"coordinates":[2.309857,48.872688],"type":"Point"}
}