{
  "type": "Feature",
  "properties": {
    "addr:full":"52 Rue J Baptiste Defernez 62800 Lievin Nord Pas-de-Calais 62800",
    "addr:housenumber":"52",
    "addr:postcode":"62800;62800",
    "addr:street":"Rue J Baptiste Defernez;Lievin Nord",
    "iso:country":"FR",
    "sg:address":"52 Rue J Baptiste Defernez 62800 Lievin",
    "sg:classifiers":[
        {
            "category":"Home & Garden",
            "subcategory":"Furniture",
            "type":"Retail Goods"
        }
    ],
    "sg:phone":"+33 3 21 44 40 93",
    "sg:postcode":"62800",
    "sg:province":"Nord Pas-de-Calais",
    "sg:tags":[
        "household",
        "wood"
    ],
    "wof:name":"Michel Lespinasse Atelier Du Siege Et De La Literie",
    "wof:placetype":"venue"
},
  "geometry": {"coordinates":[2.779565,50.4216],"type":"Point"}
}