{
  "type": "Feature",
  "properties": {
    "addr:full":"28, Rue de Mayence, 21000 Dijon Dijon Bourgogne 21000",
    "addr:housenumber":"28",
    "addr:postcode":"21000;21000",
    "addr:street":"Rue De Mayence",
    "iso:country":"FR",
    "sg:address":"28, Rue de Mayence, 21000 Dijon",
    "sg:city":"Dijon",
    "sg:orig_category":"Unclassifiable Establishments",
    "sg:phone":"+33 3 80 78 87 50",
    "sg:postcode":"21000",
    "sg:province":"Bourgogne",
    "wof:name":"Verney S.a.",
    "wof:placetype":"venue"
},
  "geometry": {"coordinates":[5.062915,47.350758],"type":"Point"}
}