{
  "type": "Feature",
  "properties": {
    "addr:full":"38, Rue Roux de Brignolles, 13006 Marseille Provence-Alpes-C\u00f4te d'Azur",
    "addr:housenumber":"38",
    "addr:postcode":"13006",
    "addr:street":"Rue Roux De Brignolles",
    "iso:country":"FR",
    "sg:address":"38, Rue Roux de Brignolles, 13006 Marseille",
    "sg:orig_category":"Non-Classified Establishments",
    "sg:phone":"+33 4 91 13 87 13",
    "sg:province":"Provence-Alpes-C\u00f4te d'Azur",
    "wof:name":"Tci S.a.r.l.",
    "wof:placetype":"venue"
},
  "geometry": {"coordinates":[5.37373,43.289764],"type":"Point"}
}