{
  "type": "Feature",
  "properties": {
    "iso:country":"FR",
    "sg:address":"ZI Nord",
    "sg:city":"Vibraye",
    "sg:orig_category":"Unclassifiable Establishments",
    "sg:phone":"+33 2 43 93 61 74",
    "sg:postcode":"72320",
    "sg:province":"Pays de Loire",
    "wof:name":"J.p.x. S.a.r.l.",
    "wof:placetype":"venue"
},
  "geometry": {"coordinates":[0.737352,48.059319],"type":"Point"}
}