{
  "type": "Feature",
  "properties": {
    "iso:country":"FR",
    "sg:address":"37 Rue De Longjumeau 91165 Champlan Cedex",
    "sg:city":"Champlan",
    "sg:classifiers":[
        {
            "category":"Shopping",
            "subcategory":"Computers & Home Electronics",
            "type":"Retail Goods"
        }
    ],
    "sg:phone":"+33 1 69 79 32 20",
    "sg:postcode":"91160",
    "sg:province":"Ile de France",
    "sg:tags":[
        "household",
        "appliance",
        "telecommunication",
        "audio-visual"
    ],
    "wof:name":"Graniou Idf",
    "wof:placetype":"venue"
},
  "geometry": {"coordinates":[2.279402,48.705414],"type":"Point"}
}