{
  "type": "Feature",
  "properties": {
    "addr:full":"B.P. 144 Mont\u00e9limar C\u00e9dex^^L'Homme d'Armes 26740 Savasse Rhone-Alpes 26204",
    "addr:housenumber":"b.p. 144",
    "addr:postcode":"26740;26204",
    "addr:street":"Rhone-Alpes",
    "iso:country":"FR",
    "sg:address":"B.P. 144",
    "sg:city":"Mont\u00e9limar C\u00e9dex^^L'Homme d'Armes 26740 Savasse",
    "sg:orig_category":"Non-Classified Establishments",
    "sg:phone":"+33 4 75 00 82 50",
    "sg:postcode":"26204",
    "sg:province":"Rhone-Alpes",
    "wof:name":"Smurfit Lembacel",
    "wof:placetype":"venue"
},
  "geometry": {"coordinates":[4.751075,44.588852],"type":"Point"}
}