{
  "type": "Feature",
  "properties": {
    "iso:country":"FR",
    "sg:address":"Gussiat 01160 Pont d'Ain",
    "sg:orig_category":"Non-Classified Establishments",
    "sg:phone":"+33 4 74 39 04 69",
    "sg:province":"Rhone-Alpes",
    "wof:name":"Entreprise Pass\u00e9 Serge & Gilbert Fr\u00e8res S.n.c.",
    "wof:placetype":"venue"
},
  "geometry": {"coordinates":[5.617957,46.126259],"type":"Point"}
}