{
  "type": "Feature",
  "properties": {
    "addr:full":"24 rue Marx Dormoy 75018 Paris Ile de France 75018",
    "addr:housenumber":"24",
    "addr:postcode":"75018;75018",
    "addr:street":"Rue Marx Dormoy",
    "iso:country":"FR",
    "sg:address":"24 rue Marx Dormoy 75018 Paris",
    "sg:classifiers":[
        {
            "category":"Professional",
            "subcategory":"Art Services",
            "type":"Services"
        }
    ],
    "sg:phone":"+33 1 44 72 49 59",
    "sg:postcode":"75018",
    "sg:province":"Ile de France",
    "sg:tags":[
        "homepage",
        "designing"
    ],
    "wof:name":"Cent Degres Design S.a.",
    "wof:placetype":"venue"
},
  "geometry": {"coordinates":[2.359672,48.886234],"type":"Point"}
}