{
  "type": "Feature",
  "properties": {
    "addr:full":"Le Pont Boeuf 35135 Chantepie Chantepie Bretagne 35135",
    "addr:postcode":"35135;35135",
    "addr:street":"Boeuf",
    "iso:country":"FR",
    "sg:address":"Le Pont Boeuf 35135 Chantepie",
    "sg:city":"Chantepie",
    "sg:classifiers":[
        {
            "category":"Building & Trades",
            "subcategory":"Construction",
            "type":"Services"
        }
    ],
    "sg:phone":"+33 2 99 41 65 70",
    "sg:postcode":"35135",
    "sg:province":"Bretagne",
    "sg:tags":[
        "work",
        "public"
    ],
    "wof:name":"Srtp",
    "wof:placetype":"venue"
},
  "geometry": {"coordinates":[-1.604424,48.082531],"type":"Point"}
}