{
  "type": "Feature",
  "properties": {
    "addr:full":"Ile De Lahonce 64990 Lahonce Lahonce Aquitaine 64990",
    "addr:postcode":"64990;64990",
    "iso:country":"FR",
    "sg:address":"Ile De Lahonce 64990 Lahonce",
    "sg:city":"Lahonce",
    "sg:classifiers":[
        {
            "category":"Manufacturing",
            "subcategory":"Wood Products",
            "type":"Manufacturing & Wholesale Goods"
        }
    ],
    "sg:phone":"+33 5 59 31 54 97",
    "sg:postcode":"64990",
    "sg:province":"Aquitaine",
    "sg:tags":[
        "professional",
        "furniture"
    ],
    "wof:name":"Etude Fabrication Mecanique (efm)",
    "wof:placetype":"venue"
},
  "geometry": {"coordinates":[-1.378063,43.49382],"type":"Point"}
}