{
  "type": "Feature",
  "properties": {
    "addr:full":"266 Avenue Daumesnil 75012 Paris Ile de France 75012",
    "addr:housenumber":"266",
    "addr:postcode":"75012;75012",
    "addr:street":"Avenue Daumesnil",
    "iso:country":"FR",
    "sg:address":"266 Avenue Daumesnil 75012 Paris",
    "sg:classifiers":[
        {
            "category":"Professional",
            "subcategory":"Advertising",
            "type":"Services"
        }
    ],
    "sg:phone":"+33 1 40 03 97 60",
    "sg:postcode":"75012",
    "sg:province":"Ile de France",
    "sg:tags":[
        "information",
        "medium",
        "communication"
    ],
    "wof:name":"Publiest",
    "wof:placetype":"venue"
},
  "geometry": {"coordinates":[2.404492,48.836155],"type":"Point"}
}