{
  "type": "Feature",
  "properties": {
    "addr:full":"Pont Cher 37300 Jou\u00e9 l\u00e8s Tours Jou\u00e9-l\u00e8s-Tours Centre 37300",
    "addr:postcode":"37300;37300",
    "addr:street":"Pont Cher",
    "iso:country":"FR",
    "sg:address":"Pont Cher 37300 Jou\u00e9 l\u00e8s Tours",
    "sg:city":"Jou\u00e9-l\u00e8s-Tours",
    "sg:orig_category":"Unclassifiable Establishments",
    "sg:phone":"+33 2 47 05 78 06",
    "sg:postcode":"37300",
    "sg:province":"Centre",
    "wof:name":"Les Successeurs D'alexandre Marlin S.a.",
    "wof:placetype":"venue"
},
  "geometry": {"coordinates":[0.674284,47.363781],"type":"Point"}
}