{
  "type": "Feature",
  "properties": {
    "iso:country":"FR",
    "sg:address":"9, Cours Andr\u00e9 Philip, 69100 Villeurbanne",
    "sg:orig_category":"Non-Classified Establishments",
    "sg:phone":"+33 4 72 82 30 40",
    "sg:postcode":"69100",
    "sg:province":"Rhone-Alpes",
    "wof:name":"Alpf",
    "wof:placetype":"venue"
},
  "geometry": {"coordinates":[4.86312,45.772621],"type":"Point"}
}