{
  "type": "Feature",
  "properties": {
    "iso:country":"FR",
    "sg:address":"190 Rue Robert Schumann 50720 Barenton",
    "sg:city":"Barenton",
    "sg:classifiers":[
        {
            "category":"Shopping",
            "subcategory":"Clothing, Apparel, & Fashions",
            "type":"Retail Goods"
        }
    ],
    "sg:phone":"+33 2 33 59 45 12",
    "sg:postcode":"50720",
    "sg:province":"Basse Normandie",
    "sg:tags":[
        "textile",
        "clothing",
        "clothes"
    ],
    "wof:name":"Solidur Sa",
    "wof:placetype":"venue"
},
  "geometry": {"coordinates":[-0.836006,48.599892],"type":"Point"}
}