{
  "type": "Feature",
  "properties": {
    "iso:country":"FR",
    "sg:address":"8 Rue Du Jura 68210 Chavannes Sur L Etang",
    "sg:city":"Ballersdorf",
    "sg:classifiers":[
        {
            "category":"Farming",
            "subcategory":"Livestock Farm",
            "type":"Manufacturing & Wholesale Goods"
        }
    ],
    "sg:phone":"+33 3 89 25 21 25",
    "sg:postcode":"68210",
    "sg:province":"Alsace",
    "sg:tags":[
        "breeding",
        "agriculture",
        "animal"
    ],
    "wof:name":"Jp Freyburger Et Fils",
    "wof:placetype":"venue"
},
  "geometry": {"coordinates":[7.022435,47.630241],"type":"Point"}
}