{
  "type": "Feature",
  "properties": {
    "iso:country":"FR",
    "sg:address":"25, Av. Joffre, 65000 Tarbes",
    "sg:orig_category":"Non-Classified Establishments",
    "sg:phone":"+33 5 62 34 73 79",
    "sg:postcode":"65000",
    "sg:province":"Midi Pyr\u00e9n\u00e9es",
    "wof:name":"Cariane Pyr\u00e9n\u00e9es S.a.",
    "wof:placetype":"venue"
},
  "geometry": {"coordinates":[0.068685,43.239658],"type":"Point"}
}