{
  "type": "Feature",
  "properties": {
    "iso:country":"FR",
    "sg:address":"19 Rue Jean Jaures",
    "sg:city":"Neuvy Sur Loire",
    "sg:classifiers":[
        {
            "category":"Banks & Credit Unions",
            "subcategory":"Financial Services",
            "type":"Services"
        }
    ],
    "sg:phone":"+33 3 86 39 25 90",
    "sg:postcode":"58450",
    "sg:province":"Bourgogne",
    "sg:tags":[
        "banking",
        "finance",
        "insurance"
    ],
    "wof:name":"Societe Fiduciaire D'expertise Comptable De Gestion Et De Re (socogere) Fiduciaire Socogere",
    "wof:placetype":"venue"
},
  "geometry": {"coordinates":[2.882075,47.522507],"type":"Point"}
}