{
  "type": "Feature",
  "properties": {
    "iso:country":"FR",
    "sg:address":"10, Av. James Clerk Maxwell, 31100 Toulouse",
    "sg:orig_category":"Unclassifiable Establishments",
    "sg:phone":"+33 5 61 77 30 00",
    "sg:province":"Midi Pyr\u00e9n\u00e9es",
    "wof:name":"C.t.r.c.e.m.p.l. - Centre Technique R\u00e9gional Caisses Epargne Midi-pyr\u00e9n\u00e9es",
    "wof:placetype":"venue"
},
  "geometry": {"coordinates":[1.368195,43.590981],"type":"Point"}
}