{
  "type": "Feature",
  "properties": {
    "addr:full":"2, Rue Fernand Forest, 78520 Limay Ile de France",
    "addr:housenumber":"2",
    "addr:postcode":"78520",
    "addr:street":"Rue Fernand Forest;Ile De France",
    "iso:country":"FR",
    "sg:address":"2, Rue Fernand Forest, 78520 Limay",
    "sg:orig_category":"Unclassifiable Establishments",
    "sg:phone":"+33 1 30 92 92 00",
    "sg:province":"Ile de France",
    "wof:name":"Valchim S.a.",
    "wof:placetype":"venue"
},
  "geometry": {"coordinates":[1.761239,48.989361],"type":"Point"}
}