{
  "type": "Feature",
  "properties": {
    "addr:full":"13 bis, Av. du 8 Mai, 49290 Chalonnes sur Loire Pays de Loire",
    "addr:housenumber":"13 bis",
    "addr:postcode":"49290",
    "addr:street":"Av. Du 8 Mai",
    "iso:country":"FR",
    "sg:address":"13 bis, Av. du 8 Mai, 49290 Chalonnes sur Loire",
    "sg:orig_category":"Unclassifiable Establishments",
    "sg:phone":"+33 2 41 72 35 25",
    "sg:province":"Pays de Loire",
    "wof:name":"Eram Industrie S.a.r.l.",
    "wof:placetype":"venue"
},
  "geometry": {"coordinates":[-0.770909,47.348316],"type":"Point"}
}