{
  "type": "Feature",
  "properties": {
    "iso:country":"FR",
    "sg:address":"Avenue Lib\u00e9ration 77650 Ste Colombe",
    "sg:classifiers":[
        {
            "category":"Farming",
            "subcategory":"Farm & Veterinary Services",
            "type":"Manufacturing & Wholesale Goods"
        }
    ],
    "sg:phone":"+33 1 64 00 08 15",
    "sg:postcode":"77650",
    "sg:province":"Ile de France",
    "sg:tags":[
        "food",
        "product",
        "breeding",
        "animal",
        "related"
    ],
    "wof:name":"Pietrement (etablissements)",
    "wof:placetype":"venue"
},
  "geometry": {"coordinates":[3.26414,48.53318],"type":"Point"}
}