{
  "type": "Feature",
  "properties": {
    "addr:full":"5 Rue Industrie 63730 Les Martres De Veyre Authezat Auvergne 63730",
    "addr:housenumber":"5",
    "addr:postcode":"63730;63730",
    "addr:street":"Rue Industrie",
    "iso:country":"FR",
    "sg:address":"5 Rue Industrie 63730 Les Martres De Veyre",
    "sg:city":"Authezat",
    "sg:classifiers":[
        {
            "category":"Professional",
            "type":"Services"
        }
    ],
    "sg:phone":"+33 4 73 39 93 36",
    "sg:postcode":"63730",
    "sg:province":"Auvergne",
    "sg:tags":[
        "transport",
        "road"
    ],
    "wof:name":"Ste Exploitation Transports Chanabaud Sarl",
    "wof:placetype":"venue"
},
  "geometry": {"coordinates":[3.196052,45.692982],"type":"Point"}
}