{
  "type": "Feature",
  "properties": {
    "iso:country":"FR",
    "sg:address":"35, Rue Anatole France, 34120 P\u00e9zenas",
    "sg:orig_category":"Unclassifiable Establishments",
    "sg:phone":"+33 4 67 98 30 06",
    "sg:province":"Languedoc-Roussillon",
    "wof:name":"M.c.m. Consult S.a.r.l.",
    "wof:placetype":"venue"
},
  "geometry": {"coordinates":[3.42276,43.459286],"type":"Point"}
}