{
  "type": "Feature",
  "properties": {
    "addr:full":"Gane Lachaud 19140 Uzerche Limousin",
    "addr:postcode":"19140",
    "addr:street":"Lachaud",
    "iso:country":"FR",
    "sg:address":"Gane Lachaud 19140 Uzerche",
    "sg:orig_category":"Unclassifiable Establishments",
    "sg:phone":"+33 5 55 73 21 59",
    "sg:province":"Limousin",
    "wof:name":"Soci\u00e9t\u00e9 Uzerchoise Salaisons Trarieux Fils S.a.",
    "wof:placetype":"venue"
},
  "geometry": {"coordinates":[1.573586,45.398273],"type":"Point"}
}