{
  "type": "Feature",
  "properties": {
    "iso:country":"FR",
    "sg:address":"40 bis, Rue Cugnet, 92700 Colombes",
    "sg:orig_category":"Non-Classified Establishments",
    "sg:phone":"+33 1 47 82 02 73",
    "sg:postcode":"92700",
    "sg:province":"Ile de France",
    "wof:name":"Color Service S.a.",
    "wof:placetype":"venue"
},
  "geometry": {"coordinates":[2.234285,48.911591],"type":"Point"}
}