{
  "type": "Feature",
  "properties": {
    "addr:full":"Rue L'Hotaud 25560 Frasne Franche Comt\u00e9 25560",
    "addr:postcode":"25560;25560",
    "addr:street":"Rue L'Hotaud;Franche Comte\u0301",
    "iso:country":"FR",
    "sg:address":"Rue L'Hotaud 25560 Frasne",
    "sg:classifiers":[
        {
            "category":"Health Services",
            "subcategory":"Optometrist",
            "type":"Services"
        }
    ],
    "sg:phone":"+33 3 81 49 81 35",
    "sg:postcode":"25560",
    "sg:province":"Franche Comt\u00e9",
    "sg:tags":[
        "instrument",
        "optical",
        "-",
        "precision",
        "equipment"
    ],
    "wof:name":"Cebe International Sa",
    "wof:placetype":"venue"
},
  "geometry": {"coordinates":[5.475125,47.176777],"type":"Point"}
}