{
  "type": "Feature",
  "properties": {
    "addr:full":"Zi Rte De Revies 14470 Courseulles Sur Mer Graye-sur-Mer Basse Normandie 14470",
    "addr:postcode":"14470;14470",
    "addr:street":"Rte De Revies",
    "iso:country":"FR",
    "sg:address":"Zi Rte De Revies 14470 Courseulles Sur Mer",
    "sg:city":"Graye-sur-Mer",
    "sg:classifiers":[
        {
            "category":"Manufacturing",
            "subcategory":"Printing",
            "type":"Manufacturing & Wholesale Goods"
        }
    ],
    "sg:phone":"+33 2 31 37 59 48",
    "sg:postcode":"14470",
    "sg:province":"Basse Normandie",
    "sg:tags":[
        "publishing"
    ],
    "wof:name":"Ste Nouvelle Ets Vitrenvel",
    "wof:placetype":"venue"
},
  "geometry": {"coordinates":[-0.457794,49.334351],"type":"Point"}
}