{
  "type": "Feature",
  "properties": {
    "iso:country":"FR",
    "sg:address":"17bis, Av du 8 Mai, 10100 Romilly sur Seine",
    "sg:orig_category":"Unclassifiable Establishments",
    "sg:phone":"+33 3 25 39 54 54",
    "sg:province":"Champagne",
    "wof:name":"A.f.p.a.-aube",
    "wof:placetype":"venue"
},
  "geometry": {"coordinates":[3.724084,48.507233],"type":"Point"}
}