{
  "type": "Feature",
  "properties": {
    "addr:full":"54, Chemin Badaffier, 84700 Sorgues Provence-Alpes-C\u00f4te d'Azur",
    "addr:housenumber":"54",
    "addr:postcode":"84700",
    "addr:street":"Chemin Badaffier",
    "iso:country":"FR",
    "sg:address":"54, Chemin Badaffier, 84700 Sorgues",
    "sg:orig_category":"Non-Classified Establishments",
    "sg:phone":"+33 4 90 88 43 41",
    "sg:province":"Provence-Alpes-C\u00f4te d'Azur",
    "wof:name":"Proviba S.a.",
    "wof:placetype":"venue"
},
  "geometry": {"coordinates":[4.879986,44.006844],"type":"Point"}
}