{
  "type": "Feature",
  "properties": {
    "iso:country":"FR",
    "sg:address":"77 rue Antoine Masson; Auxonne",
    "sg:classifiers":[
        {
            "category":"Banks & Credit Unions",
            "subcategory":"Bank",
            "type":"Services"
        }
    ],
    "sg:phone":"+33 3380311640",
    "sg:province":"Aquitaine",
    "wof:name":"Banque Populaire De, Bourgogne (b.p.b)",
    "wof:placetype":"venue"
},
  "geometry": {"coordinates":[5.387757,47.192699],"type":"Point"}
}