{
  "type": "Feature",
  "properties": {
    "addr:full":"Route De Bedarrides 84230 Chateauneuf Du Pape Ch\u00e2teau Bourgogne 71250",
    "addr:postcode":"84230;71250",
    "addr:street":"Route De Bedarrides",
    "iso:country":"FR",
    "sg:address":"Route De Bedarrides 84230 Chateauneuf Du Pape",
    "sg:city":"Ch\u00e2teau",
    "sg:classifiers":[
        {
            "category":"Food Court",
            "type":"Food & Drink"
        }
    ],
    "sg:phone":"+33 4 90 83 76 08",
    "sg:postcode":"71250",
    "sg:province":"Bourgogne",
    "sg:tags":[
        "product",
        "related"
    ],
    "wof:name":"Vignobles Elie Jeune",
    "wof:placetype":"venue"
},
  "geometry": {"coordinates":[4.835999,44.049744],"type":"Point"}
}