{
  "type": "Feature",
  "properties": {
    "iso:country":"FR",
    "sg:address":"Avenue Beno\u00eet Frachon Zi 24750 Boulazac",
    "sg:city":"Boulazac",
    "sg:orig_category":"Bread and cakes Drinks Food and Related Products Fruits and vegetables Meats and cooked meat Preserv",
    "sg:phone":"+33 5 53 08 38 11",
    "sg:postcode":"24750",
    "sg:province":"Aquitaine",
    "wof:name":"Eda Centre-ouest Le Kiosque Service",
    "wof:placetype":"venue"
},
  "geometry": {"coordinates":[0.789735,45.09977],"type":"Point"}
}