{
  "type": "Feature",
  "properties": {
    "iso:country":"FR",
    "sg:address":"19, Bd Fabert, 08200 Sedan",
    "sg:orig_category":"Unclassifiable Establishments",
    "sg:phone":"+33 3 24 27 31 11",
    "sg:province":"Champagne",
    "wof:name":"C.c.i. De Sedan - Chambre De Commerce, D'industrie Et De Services De Sedan",
    "wof:placetype":"venue"
},
  "geometry": {"coordinates":[4.938926,49.700489],"type":"Point"}
}