{
  "type": "Feature",
  "properties": {
    "addr:full":"12, Rue de Chamechaude - ZI de l'Argenti\u00e8re, 38360 Sassenage Rhone-Alpes 38360",
    "addr:housenumber":"12",
    "addr:postcode":"38360;38360",
    "addr:street":"Rue De Chamechaude Zi De L'Argentie \u0300Re",
    "iso:country":"FR",
    "sg:address":"12, Rue de Chamechaude - ZI de l'Argenti\u00e8re, 38360 Sassenage",
    "sg:orig_category":"Non-Classified Establishments",
    "sg:phone":"+33 4 76 26 79 47",
    "sg:postcode":"38360",
    "sg:province":"Rhone-Alpes",
    "wof:name":"A.c.m.f. S.a.r.l.",
    "wof:placetype":"venue"
},
  "geometry": {"coordinates":[5.6835,45.205505],"type":"Point"}
}