{
  "type": "Feature",
  "properties": {
    "iso:country":"FR",
    "sg:address":"B.P. 78, 62302 Lens C\u00e9dex^^Rue des Colibris - Parc d'Activit\u00e9s les Oiseaux, 62300 Lens",
    "sg:orig_category":"Non-Classified Establishments",
    "sg:phone":"+33 3 21 69 88 44",
    "sg:province":"Nord Pas-de-Calais",
    "wof:name":"Imprimerie De La Centrale S.a.",
    "wof:placetype":"venue"
},
  "geometry": {"coordinates":[2.81767,50.436279],"type":"Point"}
}