{
  "type": "Feature",
  "properties": {
    "iso:country":"FR",
    "sg:address":"2 ave de la Grande; Longwy; 54402",
    "sg:classifiers":[
        {
            "category":"Banks & Credit Unions",
            "subcategory":"Bank",
            "type":"Services"
        }
    ],
    "sg:phone":"+33 3 82 24 28 91",
    "sg:province":"Haute Normandie",
    "wof:name":"Banque De France",
    "wof:placetype":"venue"
},
  "geometry": {"coordinates":[5.769745,49.515018],"type":"Point"}
}