{
  "type": "Feature",
  "properties": {
    "addr:full":"25, Rue du Gros H\u00eatre, 57500 Saint Avold Lorraine",
    "addr:housenumber":"25",
    "addr:postcode":"57500",
    "addr:street":"Rue Du Gros He\u0302Tre;Avold",
    "iso:country":"FR",
    "sg:address":"25, Rue du Gros H\u00eatre, 57500 Saint Avold",
    "sg:orig_category":"Non-Classified Establishments",
    "sg:phone":"+33 3 87 93 93 73",
    "sg:province":"Lorraine",
    "wof:name":"Manka Cr\u00e9ations S.a.r.l.",
    "wof:placetype":"venue"
},
  "geometry": {"coordinates":[6.723658,49.1185],"type":"Point"}
}