{
  "type": "Feature",
  "properties": {
    "iso:country":"FR",
    "sg:address":"132, Av. de Villiers, 75017 Paris",
    "sg:orig_category":"Unclassifiable Establishments",
    "sg:phone":"+33 1 47 63 06 37",
    "sg:province":"Ile de France",
    "wof:name":"Nutrimarketing Innovation Alimentaire Et Communication S.a.",
    "wof:placetype":"venue"
},
  "geometry": {"coordinates":[2.294631,48.885391],"type":"Point"}
}