{
  "type": "Feature",
  "properties": {
    "addr:full":"Chemin en Padouent Panassac Midi Pyr\u00e9n\u00e9es 32140",
    "addr:postcode":"32140",
    "addr:street":"Chemin En;Panassac",
    "iso:country":"FR",
    "sg:address":"Chemin en Padouent",
    "sg:city":"Panassac",
    "sg:orig_category":"Non-Classified Establishments",
    "sg:phone":"+33 5 62 66 15 80",
    "sg:postcode":"32140",
    "sg:province":"Midi Pyr\u00e9n\u00e9es",
    "wof:name":"S.t.m.s. S.a.r.l. - Serrurerie T\u00f4lerie M\u00e9cano-soudure",
    "wof:placetype":"venue"
},
  "geometry": {"coordinates":[0.567985,43.328064],"type":"Point"}
}