{
  "type": "Feature",
  "properties": {
    "iso:country":"FR",
    "sg:address":"3 Rue St Claude 77348 Pontault - Combault",
    "sg:classifiers":[
        {
            "category":"Professional",
            "subcategory":"Engineering",
            "type":"Services"
        }
    ],
    "sg:phone":"+33 1 64 43 51 90",
    "sg:province":"Picardie",
    "sg:tags":[
        "machine",
        "-",
        "mechanical"
    ],
    "wof:name":"Emic Sas",
    "wof:placetype":"venue"
},
  "geometry": {"coordinates":[2.610773,48.778465],"type":"Point"}
}