{
  "type": "Feature",
  "properties": {
    "addr:full":"19 Bis Quai Victor Augagneur 69003 Lyon Rhone-Alpes 69003",
    "addr:housenumber":"19 bis",
    "addr:postcode":"69003;69003",
    "addr:street":"Quai Victor Augagneur",
    "iso:country":"FR",
    "sg:address":"19 Bis Quai Victor Augagneur 69003 Lyon",
    "sg:classifiers":[
        {
            "category":"Shopping",
            "subcategory":"Clothing, Apparel, & Fashions",
            "type":"Retail Goods"
        }
    ],
    "sg:phone":"+33 4 78 60 00 56",
    "sg:postcode":"69003",
    "sg:province":"Rhone-Alpes",
    "sg:tags":[
        "textile",
        "clothing",
        "clothes"
    ],
    "wof:name":"La Canadienne Sa",
    "wof:placetype":"venue"
},
  "geometry": {"coordinates":[4.841112,45.758884],"type":"Point"}
}