{
  "type": "Feature",
  "properties": {
    "iso:country":"FR",
    "sg:address":"9, Rue des Commerces - ZAE Marsac, 24430 Marsac sur l'Isle",
    "sg:city":"Annesse-et-Beaulieu",
    "sg:orig_category":"Unclassifiable Establishments",
    "sg:phone":"+33 5 53 04 80 60",
    "sg:postcode":"24430",
    "sg:province":"Aquitaine",
    "wof:name":"Chemin\u00e9es Turbo Fonte S.a.",
    "wof:placetype":"venue"
},
  "geometry": {"coordinates":[0.662757,45.193253],"type":"Point"}
}