{
  "type": "Feature",
  "properties": {
    "addr:full":"42 Rue Du General Giraud 76000 Rouen Haute Normandie 76000",
    "addr:housenumber":"42",
    "addr:postcode":"76000;76000",
    "addr:street":"Rue Du General Giraud;Haute Normandie",
    "iso:country":"FR",
    "sg:address":"42 Rue Du General Giraud 76000 Rouen",
    "sg:classifiers":[
        {
            "category":"Food Court",
            "type":"Food & Drink"
        }
    ],
    "sg:phone":"+33 2 35 89 99 54",
    "sg:postcode":"76000",
    "sg:province":"Haute Normandie",
    "sg:tags":[
        "product",
        "related"
    ],
    "wof:name":"Calvados Christian Drouin",
    "wof:placetype":"venue"
},
  "geometry": {"coordinates":[1.088303,49.441013],"type":"Point"}
}