{
  "type": "Feature",
  "properties": {
    "iso:country":"FR",
    "sg:address":"5 Rue Prof Maurice Sureau Palais Dany 06000 Nice",
    "sg:classifiers":[
        {
            "category":"Wholesale",
            "subcategory":"Medical Equipment & Supplies",
            "type":"Manufacturing & Wholesale Goods"
        }
    ],
    "sg:phone":"+33 4 93 53 69 00",
    "sg:province":"Aquitaine",
    "sg:tags":[
        "instrument",
        "health",
        "-",
        "precision"
    ],
    "wof:name":"Techniques De L'art Dentaire",
    "wof:placetype":"venue"
},
  "geometry": {"coordinates":[7.271525,43.715569],"type":"Point"}
}