{
  "type": "Feature",
  "properties": {
    "addr:full":"Av. Jean Philippe Rameau - ZI de Croupillac Al\u00e8s Languedoc-Roussillon 30100",
    "addr:postcode":"30100",
    "addr:street":"Av. Jean Philippe Rameau Zi De Croupillac Ale\u0300S",
    "iso:country":"FR",
    "sg:address":"Av. Jean Philippe Rameau - ZI de Croupillac",
    "sg:city":"Al\u00e8s",
    "sg:orig_category":"Unclassifiable Establishments",
    "sg:phone":"+33 4 66 54 21 90",
    "sg:postcode":"30100",
    "sg:province":"Languedoc-Roussillon",
    "wof:name":"C.c.b. S.a.r.l. - Comptoir Cevenol Du Bois",
    "wof:placetype":"venue"
},
  "geometry": {"coordinates":[4.082515,44.121254],"type":"Point"}
}