{
  "type": "Feature",
  "properties": {
    "addr:full":"28, Cours Washington, 47000 Agen Agen Aquitaine 47000",
    "addr:housenumber":"28",
    "addr:postcode":"47000;47000",
    "addr:street":"Cours",
    "iso:country":"FR",
    "sg:address":"28, Cours Washington, 47000 Agen",
    "sg:city":"Agen",
    "sg:orig_category":"Non-Classified Establishments",
    "sg:phone":"+33 5 53 77 37 76",
    "sg:postcode":"47000",
    "sg:province":"Aquitaine",
    "wof:name":"Caisse D'epargne Aquitaine Nord",
    "wof:placetype":"venue"
},
  "geometry": {"coordinates":[0.618643,44.201942],"type":"Point"}
}