{
  "type": "Feature",
  "properties": {
    "addr:full":"5, Rue de la Logistique, 42000 Saint Etienne Rhone-Alpes",
    "addr:housenumber":"5",
    "addr:postcode":"42000",
    "addr:street":"Rue De La Logistique",
    "iso:country":"FR",
    "sg:address":"5, Rue de la Logistique, 42000 Saint Etienne",
    "sg:orig_category":"Unclassifiable Establishments",
    "sg:phone":"+33 4 77 74 14 11",
    "sg:province":"Rhone-Alpes",
    "wof:name":"Soci\u00e9t\u00e9 D'exploitation Des Caf\u00e9s Chapuis S.a.",
    "wof:placetype":"venue"
},
  "geometry": {"coordinates":[4.391145,45.455544],"type":"Point"}
}