{
  "type": "Feature",
  "properties": {
    "iso:country":"FR",
    "sg:address":"1 Rue Jean Red\u00e9l\u00e9 Site Eurochannel 76370 Dieppe",
    "sg:classifiers":[
        {
            "category":"Manufacturing",
            "subcategory":"Printing",
            "type":"Manufacturing & Wholesale Goods"
        }
    ],
    "sg:phone":"+33 2 35 06 97 97",
    "sg:province":"Haute Normandie",
    "sg:tags":[
        "publishing"
    ],
    "wof:name":"Scribe",
    "wof:placetype":"venue"
},
  "geometry": {"coordinates":[1.093,49.904709],"type":"Point"}
}