{
  "type": "Feature",
  "properties": {
    "addr:full":"Rue des Moulins Sainte Euph\u00e9mie Rhone-Alpes 01600",
    "addr:postcode":"01600",
    "addr:street":"Rue Des Moulins",
    "iso:country":"FR",
    "sg:address":"Rue des Moulins",
    "sg:city":"Sainte Euph\u00e9mie",
    "sg:orig_category":"Unclassifiable Establishments",
    "sg:phone":"+33 4 74 00 25 96",
    "sg:postcode":"01600",
    "sg:province":"Rhone-Alpes",
    "wof:name":"Entreprise L\u00e9v\u00e8que Maurice S.a.r.l.",
    "wof:placetype":"venue"
},
  "geometry": {"coordinates":[4.7962,45.972141],"type":"Point"}
}