{
  "type": "Feature",
  "properties": {
    "addr:full":"B.P. 117, 58205 Cosne Cours sur Loire C\u00e9dex^^ZI du Tremblat, 58200 Cosne Cours sur Loire Cosne-Cours-sur-Loire Bourgogne 58200",
    "addr:housenumber":"b.p. 117",
    "addr:postcode":"58205;58200;58200",
    "addr:street":"Cours",
    "iso:country":"FR",
    "sg:address":"B.P. 117, 58205 Cosne Cours sur Loire C\u00e9dex^^ZI du Tremblat, 58200 Cosne Cours sur Loire",
    "sg:city":"Cosne-Cours-sur-Loire",
    "sg:orig_category":"Non-Classified Establishments",
    "sg:phone":"+33 3 86 26 65 51",
    "sg:postcode":"58200",
    "sg:province":"Bourgogne",
    "wof:name":"S.t.p. S.a.r.l. - S\u00e9rigraphie Technique Et Publicitaire",
    "wof:placetype":"venue"
},
  "geometry": {"coordinates":[2.901115,47.369862],"type":"Point"}
}