{
  "type": "Feature",
  "properties": {
    "addr:full":"1 Rue Du Chemin Neuf 95130 Franconville La Garenne Ile de France 95130",
    "addr:housenumber":"1",
    "addr:postcode":"95130;95130",
    "addr:street":"Rue Du Chemin Neuf;Ile;France",
    "iso:country":"FR",
    "sg:address":"1 Rue Du Chemin Neuf 95130 Franconville La Garenne",
    "sg:classifiers":[
        {
            "category":"Manufacturing",
            "subcategory":"Aerospace",
            "type":"Manufacturing & Wholesale Goods"
        }
    ],
    "sg:phone":"+33 1 34 44 11 00",
    "sg:postcode":"95130",
    "sg:province":"Ile de France",
    "sg:tags":[
        "equipment",
        "aeronautic",
        "transport",
        "vehicle"
    ],
    "wof:name":"Erriam (erriam)",
    "wof:placetype":"venue"
},
  "geometry": {"coordinates":[2.235405,49.001438],"type":"Point"}
}