{
  "type": "Feature",
  "properties": {
    "addr:full":"Quartier Beauregard La Mure Rhone-Alpes 38350",
    "addr:postcode":"38350",
    "addr:street":"Quartier Beauregard;Rhone-Alpes",
    "iso:country":"FR",
    "sg:address":"Quartier Beauregard",
    "sg:city":"La Mure",
    "sg:orig_category":"Non-Classified Establishments",
    "sg:phone":"+33 4 76 30 97 44",
    "sg:postcode":"38350",
    "sg:province":"Rhone-Alpes",
    "wof:name":"I.t.t.a.c. S.a.r.l. - Injections Thermoplastiques Techniques Assistance Conseil",
    "wof:placetype":"venue"
},
  "geometry": {"coordinates":[5.733722,44.872341],"type":"Point"}
}