{
  "type": "Feature",
  "properties": {
    "addr:full":"15 Chem Du Petit Bois 69130 Ecully Rhone-Alpes 69130",
    "addr:housenumber":"15",
    "addr:postcode":"69130;69130",
    "addr:street":"Chem Du Petit Bois;Rhone-Alpes",
    "iso:country":"FR",
    "sg:address":"15 Chem Du Petit Bois 69130 Ecully",
    "sg:classifiers":[
        {
            "category":"Professional",
            "subcategory":"Business Services",
            "type":"Services"
        }
    ],
    "sg:phone":"+33 4 78 33 09 66",
    "sg:postcode":"69130",
    "sg:province":"Rhone-Alpes",
    "sg:tags":[
        "training",
        "advice"
    ],
    "wof:name":"I S E O R Institut Socio Economie Des Organisations",
    "wof:placetype":"venue"
},
  "geometry": {"coordinates":[4.762082,45.782951],"type":"Point"}
}