{
  "type": "Feature",
  "properties": {
    "iso:country":"FR",
    "sg:address":"Rte Saint Marcelin - Les Plats",
    "sg:city":"Saint Romain le Puy",
    "sg:orig_category":"Non-Classified Establishments",
    "sg:phone":"+33 4 77 76 07 76",
    "sg:postcode":"42610",
    "sg:province":"Rhone-Alpes",
    "wof:name":"Solover S.a.",
    "wof:placetype":"venue"
},
  "geometry": {"coordinates":[4.12494,45.560539],"type":"Point"}
}