{
  "type": "Feature",
  "properties": {
    "iso:country":"FR",
    "sg:address":"B.P. 26, 67320 Drulingen^^3, Rte de Bettwiller, 67320 Drulingen",
    "sg:city":"Drulingen",
    "sg:orig_category":"Non-Classified Establishments",
    "sg:phone":"+33 3 88 01 69 00",
    "sg:postcode":"67320",
    "sg:province":"Alsace",
    "wof:name":"Sotralentz M\u00e9tal Industries S.a.s.",
    "wof:placetype":"venue"
},
  "geometry": {"coordinates":[7.189794,48.866207],"type":"Point"}
}