{
  "type": "Feature",
  "properties": {
    "iso:country":"FR",
    "sg:address":"15, Rue de Montr\u00e9al, 74100 Ville la Grand",
    "sg:orig_category":"Non-Classified Establishments",
    "sg:phone":"+33 4 50 37 06 97",
    "sg:postcode":"74100",
    "sg:province":"Rhone-Alpes",
    "wof:name":"Delta Diffusion",
    "wof:placetype":"venue"
},
  "geometry": {"coordinates":[6.279209,46.204285],"type":"Point"}
}