{
  "type": "Feature",
  "properties": {
    "iso:country":"FR",
    "sg:address":"127 rue Marc Sangnier 94700 Maisons Alfort",
    "sg:classifiers":[
        {
            "category":"Retail",
            "subcategory":"Event Space",
            "type":"Services"
        }
    ],
    "sg:phone":"+33 1 48 99 70 95",
    "sg:postcode":"94700",
    "sg:province":"Ile de France",
    "sg:tags":[
        "measuring",
        "device",
        "electronic"
    ],
    "wof:name":"Distrimesure S.a.r.l.",
    "wof:placetype":"venue"
},
  "geometry": {"coordinates":[2.454059,48.806141],"type":"Point"}
}