{
  "type": "Feature",
  "properties": {
    "addr:full":"B.P. 28, 26601 Mont\u00e9limar C\u00e9dex^^20, Av. du Gournier - ZI Sud, 26200 Mont\u00e9limar Rhone-Alpes",
    "addr:postcode":"26601;26200",
    "addr:street":"B.P. 28;Av. Du Gournier Zi Sud",
    "iso:country":"FR",
    "sg:address":"B.P. 28, 26601 Mont\u00e9limar C\u00e9dex^^20, Av. du Gournier - ZI Sud, 26200 Mont\u00e9limar",
    "sg:orig_category":"Non-Classified Establishments",
    "sg:phone":"+33 4 75 92 33 33",
    "sg:province":"Rhone-Alpes",
    "wof:name":"S.m.m.b.t.p. S.a.",
    "wof:placetype":"venue"
},
  "geometry": {"coordinates":[4.74916,44.555592],"type":"Point"}
}