{
  "type": "Feature",
  "properties": {
    "addr:full":"1 Rue Fran\u00e7ois Joffr\u00e9 78180 Montigny-Le-Bretonneux Ile de France",
    "addr:housenumber":"1",
    "addr:postcode":"78180;ile",
    "addr:street":"Rue Franc\u0327Ois Joffre\u0301",
    "iso:country":"FR",
    "sg:address":"1 Rue Fran\u00e7ois Joffr\u00e9 78180 Montigny-Le-Bretonneux",
    "sg:classifiers":[
        {
            "category":"Manufacturing",
            "subcategory":"Wood Products",
            "type":"Manufacturing & Wholesale Goods"
        }
    ],
    "sg:phone":"+33 1 30 48 18 00",
    "sg:province":"Ile de France",
    "sg:tags":[
        "professional",
        "furniture"
    ],
    "wof:name":"Kinnarps Sa",
    "wof:placetype":"venue"
},
  "geometry": {"coordinates":[2.041725,48.778778],"type":"Point"}
}