{
  "type": "Feature",
  "properties": {
    "iso:country":"FR",
    "sg:address":"11 Quai De Brienne 33081 Bordeaux",
    "sg:city":"Bordeaux",
    "sg:classifiers":[
        {
            "category":"Professional",
            "subcategory":"Engineering",
            "type":"Services"
        }
    ],
    "sg:phone":"+33 5 56 49 90 90",
    "sg:postcode":"33100",
    "sg:province":"Aquitaine",
    "sg:tags":[
        "machine",
        "-",
        "mechanical"
    ],
    "wof:name":"Brossette Bti",
    "wof:placetype":"venue"
},
  "geometry": {"coordinates":[-0.543134,44.82288],"type":"Point"}
}