{
  "type": "Feature",
  "properties": {
    "iso:country":"FR",
    "sg:address":"B.P. 134, 39304 Champagnole C\u00e9dex^^2, Av de la Gare, 39300 Champagnole",
    "sg:orig_category":"Non-Classified Establishments",
    "sg:phone":"+33 3 84 52 01 17",
    "sg:postcode":"39300",
    "sg:province":"Franche Comt\u00e9",
    "wof:name":"Colin S.a.r.l.",
    "wof:placetype":"venue"
},
  "geometry": {"coordinates":[5.907597,46.747177],"type":"Point"}
}