{
  "type": "Feature",
  "properties": {
    "iso:country":"FR",
    "sg:address":"B.P. 28, 76700 Harfleur^^ZI Rogerville-Oudalle, 76430 Oudalle",
    "sg:orig_category":"Non-Classified Establishments",
    "sg:phone":"+33 2 35 13 43 10",
    "sg:province":"Haute Normandie",
    "wof:name":"Quille S.a.",
    "wof:placetype":"venue"
},
  "geometry": {"coordinates":[0.46642,49.486343],"type":"Point"}
}