{
  "type": "Feature",
  "properties": {
    "addr:full":"26, Place de la R\u00e9publique, 21700 Nuits Saint Georges Agencourt Bourgogne 21700",
    "addr:housenumber":"26",
    "addr:postcode":"21700;21700",
    "addr:street":"Place De La Re\u0301Publique;Bourgogne",
    "iso:country":"FR",
    "sg:address":"26, Place de la R\u00e9publique, 21700 Nuits Saint Georges",
    "sg:city":"Agencourt",
    "sg:orig_category":"Unclassifiable Establishments",
    "sg:phone":"+33 3 80 62 01 00",
    "sg:postcode":"21700",
    "sg:province":"Bourgogne",
    "wof:name":"Caisse D'\u00e9pargne De Bourgogne, Agence Nuits Saint Georges",
    "wof:placetype":"venue"
},
  "geometry": {"coordinates":[4.94888,47.136707],"type":"Point"}
}