{
  "type": "Feature",
  "properties": {
    "iso:country":"FR",
    "sg:address":"B.P. 15, 39160 Saint Amour^^Rue de la Marbrerie, 39160 Saint Amour",
    "sg:orig_category":"Non-Classified Establishments",
    "sg:phone":"+33 3 84 48 73 58",
    "sg:province":"Franche Comt\u00e9",
    "wof:name":"Yelmini Artaud S.a.",
    "wof:placetype":"venue"
},
  "geometry": {"coordinates":[5.344974,46.4352],"type":"Point"}
}