{
  "type": "Feature",
  "properties": {
    "addr:full":"17 Rue Jeanne Braconnier 92366 Meudon La For\u00eat Cedex Haute Normandie",
    "addr:housenumber":"17",
    "addr:postcode":"92366",
    "addr:street":"Rue Jeanne Braconnier;Haute Normandie",
    "iso:country":"FR",
    "sg:address":"17 Rue Jeanne Braconnier 92366 Meudon La For\u00eat Cedex",
    "sg:classifiers":[
        {
            "category":"Wholesale",
            "subcategory":"Medical Equipment & Supplies",
            "type":"Manufacturing & Wholesale Goods"
        }
    ],
    "sg:phone":"+33 1 45 37 15 37",
    "sg:province":"Haute Normandie",
    "sg:tags":[
        "instrument",
        "health",
        "-",
        "precision"
    ],
    "wof:name":"Sulzer Cardiovascular Sa",
    "wof:placetype":"venue"
},
  "geometry": {"coordinates":[2.212079,48.790413],"type":"Point"}
}