{
  "type": "Feature",
  "properties": {
    "iso:country":"FR",
    "sg:address":"Av. des Templiers - ZA Napollon",
    "sg:city":"Aubagne",
    "sg:orig_category":"Unclassifiable Establishments",
    "sg:phone":"+33 4 42 18 71 07",
    "sg:postcode":"13400",
    "sg:province":"Provence-Alpes-C\u00f4te d'Azur",
    "wof:name":"Num\u00e9ripolis S.a.",
    "wof:placetype":"venue"
},
  "geometry": {"coordinates":[5.5687,43.292141],"type":"Point"}
}