{
  "type": "Feature",
  "properties": {
    "addr:full":"10 rue de l'Avenir 91140 Villebon sur Yvette Ile de France 91140",
    "addr:housenumber":"10",
    "addr:postcode":"91140;91140",
    "addr:street":"Rue De L'Avenir",
    "iso:country":"FR",
    "sg:address":"10 rue de l'Avenir 91140 Villebon sur Yvette",
    "sg:classifiers":[
        {
            "category":"Shopping",
            "subcategory":"Computers & Home Electronics",
            "type":"Retail Goods"
        }
    ],
    "sg:phone":"+33 1 69 07 01 45",
    "sg:postcode":"91140",
    "sg:province":"Ile de France",
    "sg:tags":[
        "client-server",
        "software"
    ],
    "wof:name":"Aura Equipements Sa",
    "wof:placetype":"venue"
},
  "geometry": {"coordinates":[2.203031,48.697914],"type":"Point"}
}