{
  "type": "Feature",
  "properties": {
    "iso:country":"FR",
    "sg:address":"B.P. 1363, 76179 Rouen C\u00e9dex^^21, Rue de la Mare du Parc, 76100 Rouen",
    "sg:orig_category":"Non-Classified Establishments",
    "sg:phone":"+33 2 32 81 85 60",
    "sg:postcode":"76100",
    "sg:province":"Haute Normandie",
    "wof:name":"C.e.s.i. Normandie - Centres D'etudes Sup\u00e9rieures Industrielles",
    "wof:placetype":"venue"
},
  "geometry": {"coordinates":[1.0879,49.433601],"type":"Point"}
}