{
  "type": "Feature",
  "properties": {
    "addr:full":"15, rue des Bruy\u00e8res, 25220 Thise Franche Comt\u00e9",
    "addr:housenumber":"15",
    "addr:postcode":"25220",
    "addr:street":"Rue Des Bruye\u0300Res;Franche Comte\u0301",
    "iso:country":"FR",
    "sg:address":"15, rue des Bruy\u00e8res, 25220 Thise",
    "sg:orig_category":"Non-Classified Establishments",
    "sg:phone":"+33 3 81 47 18 70",
    "sg:province":"Franche Comt\u00e9",
    "wof:name":"S\u00e9cife S.a.",
    "wof:placetype":"venue"
},
  "geometry": {"coordinates":[6.061692,47.27113],"type":"Point"}
}