{
  "type": "Feature",
  "properties": {
    "iso:country":"FR",
    "sg:address":"1, Rue Emile de Girardin, 23400 Bourganeuf",
    "sg:orig_category":"Unclassifiable Establishments",
    "sg:phone":"+33 5 55 64 27 30",
    "sg:province":"Limousin",
    "wof:name":"B.p.c. - Banque Populaire Du Centre",
    "wof:placetype":"venue"
},
  "geometry": {"coordinates":[1.757765,45.951607],"type":"Point"}
}