{
  "type": "Feature",
  "properties": {
    "iso:country":"FR",
    "sg:address":"81, Cours Saint Louis, 33000 Bordeaux",
    "sg:city":"Bordeaux",
    "sg:orig_category":"Non-Classified Establishments",
    "sg:phone":"+33 5 56 43 15 00",
    "sg:postcode":"33000",
    "sg:province":"Aquitaine",
    "wof:name":"Mercure - Ch\u00e2teau Chartrons",
    "wof:placetype":"venue"
},
  "geometry": {"coordinates":[-0.569194,44.859463],"type":"Point"}
}