{
  "type": "Feature",
  "properties": {
    "iso:country":"FR",
    "sg:address":"33 Av Amp\u00e8re 91320 Wissous",
    "sg:classifiers":[
        {
            "category":"Professional",
            "subcategory":"Engineering",
            "type":"Services"
        }
    ],
    "sg:phone":"+33 1 69 53 65 90",
    "sg:postcode":"91320",
    "sg:province":"Ile de France",
    "sg:tags":[
        "machine",
        "-",
        "mechanical"
    ],
    "wof:name":"Actem",
    "wof:placetype":"venue"
},
  "geometry": {"coordinates":[2.317623,48.727394],"type":"Point"}
}