{
  "type": "Feature",
  "properties": {
    "addr:full":"47 All Des Caroubiers 40000 Mont De Marsan Mont-de-Marsan Aquitaine 40000",
    "addr:housenumber":"47",
    "addr:postcode":"40000;40000",
    "addr:street":"All Des Caroubiers",
    "iso:country":"FR",
    "sg:address":"47 All Des Caroubiers 40000 Mont De Marsan",
    "sg:city":"Mont-de-Marsan",
    "sg:classifiers":[
        {
            "category":"Shopping",
            "subcategory":"Computers & Home Electronics",
            "type":"Retail Goods"
        }
    ],
    "sg:phone":"+33 5 58 75 11 32",
    "sg:postcode":"40000",
    "sg:province":"Aquitaine",
    "sg:tags":[
        "equipment",
        "household",
        "electrical",
        "appliance",
        "electronic"
    ],
    "wof:name":"Ets Guilbaud Sarl",
    "wof:placetype":"venue"
},
  "geometry": {"coordinates":[-0.494934,43.888645],"type":"Point"}
}