{
  "type": "Feature",
  "properties": {
    "iso:country":"FR",
    "sg:address":"Av. d'Oc\u00e9anie",
    "sg:city":"Les Ulis C\u00e9dex",
    "sg:orig_category":"Non-Classified Establishments",
    "sg:phone":"+33 1 69 18 85 00",
    "sg:postcode":"91968",
    "sg:province":"Ile de France",
    "wof:name":"22 Service S.a.",
    "wof:placetype":"venue"
},
  "geometry": {"coordinates":[2.194293,48.67635],"type":"Point"}
}