{
  "type": "Feature",
  "properties": {
    "iso:country":"FR",
    "sg:address":"R Des Acacias BP 2281 27950 St Marcel",
    "sg:classifiers":[
        {
            "category":"Shopping",
            "subcategory":"Luggage & Leather Goods",
            "type":"Retail Goods"
        }
    ],
    "sg:phone":"+33 2 32 21 54 14",
    "sg:postcode":"27950",
    "sg:province":"Haute Normandie",
    "sg:tags":[
        "shoe"
    ],
    "wof:name":"Atlex Sa",
    "wof:placetype":"venue"
},
  "geometry": {"coordinates":[1.458697,49.105801],"type":"Point"}
}