{
  "type": "Feature",
  "properties": {
    "addr:full":"Rte de Saint Jean du Gard Anduze Languedoc-Roussillon 30140",
    "addr:postcode":"30140",
    "addr:street":"Rte De Saint Jean Du Gard",
    "iso:country":"FR",
    "sg:address":"Rte de Saint Jean du Gard",
    "sg:city":"Anduze",
    "sg:orig_category":"Non-Classified Establishments",
    "sg:phone":"+33 4 66 61 80 86",
    "sg:postcode":"30140",
    "sg:province":"Languedoc-Roussillon",
    "wof:name":"La Poterie D'anduze",
    "wof:placetype":"venue"
},
  "geometry": {"coordinates":[3.98039,44.05978],"type":"Point"}
}