{
  "type": "Feature",
  "properties": {
    "addr:full":"24 Rue Du Rocher Paris Ile de France 75008",
    "addr:housenumber":"24",
    "addr:postcode":"75008",
    "addr:street":"Rue Du Rocher",
    "iso:country":"FR",
    "sg:address":"24 Rue Du Rocher",
    "sg:city":"Paris",
    "sg:classifiers":[
        {
            "category":"Banks & Credit Unions",
            "subcategory":"Financial Services",
            "type":"Services"
        }
    ],
    "sg:phone":"+33 1 53 42 47 00",
    "sg:postcode":"75008",
    "sg:province":"Ile de France",
    "sg:tags":[
        "banking",
        "finance",
        "insurance"
    ],
    "wof:name":"Credit Maritime Mutuel",
    "wof:placetype":"venue"
},
  "geometry": {"coordinates":[2.322173,48.876595],"type":"Point"}
}