{
  "type": "Feature",
  "properties": {
    "addr:full":"9 rue Gambetta; Caudry; 59540 Nord Pas-de-Calais 59540",
    "addr:housenumber":"9",
    "addr:postcode":"59540;59540",
    "addr:street":"Rue Gambetta",
    "iso:country":"FR",
    "sg:address":"9 rue Gambetta; Caudry; 59540",
    "sg:classifiers":[
        {
            "category":"Banks & Credit Unions",
            "subcategory":"Bank",
            "type":"Services"
        }
    ],
    "sg:phone":"+33 27856654",
    "sg:postcode":"59540",
    "sg:province":"Nord Pas-de-Calais",
    "wof:name":"Banque Nationale De Paris",
    "wof:placetype":"venue"
},
  "geometry": {"coordinates":[3.40792,50.122604],"type":"Point"}
}