{
  "type": "Feature",
  "properties": {
    "iso:country":"FR",
    "sg:address":"2, Rue Galien, 93587 Saint Ouen",
    "sg:orig_category":"Unclassifiable Establishments",
    "sg:phone":"+33 1 49 18 75 75",
    "sg:province":"Centre",
    "wof:name":"O.c.p. R\u00e9partition S.a.s",
    "wof:placetype":"venue"
},
  "geometry": {"coordinates":[1.63802,48.607769],"type":"Point"}
}