{
  "type": "Feature",
  "properties": {
    "addr:full":"36, Rue Fromanteau, 91260 Juvisy sur Orge Ile de France",
    "addr:housenumber":"36",
    "addr:postcode":"91260",
    "addr:street":"Rue Fromanteau",
    "iso:country":"FR",
    "sg:address":"36, Rue Fromanteau, 91260 Juvisy sur Orge",
    "sg:orig_category":"Non-Classified Establishments",
    "sg:phone":"+33 1 69 21 74 38",
    "sg:province":"Ile de France",
    "wof:name":"S.e.r.n. S.a.r.l. - Soci\u00e9t\u00e9 D' Etude Et R\u00e9alisation Nouvelle",
    "wof:placetype":"venue"
},
  "geometry": {"coordinates":[2.367594,48.696686],"type":"Point"}
}