{
  "type": "Feature",
  "properties": {
    "addr:full":"72 Bd De La Saussaye 92200 Neuilly Sur Seine Ile de France 92200",
    "addr:housenumber":"72",
    "addr:postcode":"92200;92200",
    "addr:street":"Bd De La Saussaye",
    "iso:country":"FR",
    "sg:address":"72 Bd De La Saussaye 92200 Neuilly Sur Seine",
    "sg:classifiers":[
        {
            "category":"Professional",
            "subcategory":"Business Services",
            "type":"Services"
        }
    ],
    "sg:phone":"+33 1 46 24 10 51",
    "sg:postcode":"92200",
    "sg:province":"Ile de France",
    "sg:tags":[
        "training",
        "advice"
    ],
    "wof:name":"Marymount Cours",
    "wof:placetype":"venue"
},
  "geometry": {"coordinates":[2.270071,48.892731],"type":"Point"}
}