{
  "type": "Feature",
  "properties": {
    "iso:country":"FR",
    "sg:address":"3 rue Peyerimhoff 57800 Freyming Merlebach",
    "sg:classifiers":[
        {
            "category":"Community Center",
            "subcategory":"Social",
            "type":"Public Place"
        }
    ],
    "sg:phone":"+33 3 87 00 21 40",
    "sg:postcode":"57800",
    "sg:province":"Lorraine",
    "sg:tags":[
        "slate",
        "cladding",
        "ground"
    ],
    "wof:name":"Solodet Sarl",
    "wof:placetype":"venue"
},
  "geometry": {"coordinates":[6.77286,49.159199],"type":"Point"}
}