{
  "type": "Feature",
  "properties": {
    "addr:full":"Boulevard Paul Raphel 13730 St Victoret Centre",
    "addr:postcode":"13730",
    "addr:street":"Boulevard Paul Raphel",
    "iso:country":"FR",
    "sg:address":"Boulevard Paul Raphel 13730 St Victoret",
    "sg:classifiers":[
        {
            "category":"Shopping",
            "type":"Retail Goods"
        }
    ],
    "sg:phone":"+33 4 42 46 80 69",
    "sg:province":"Centre",
    "sg:tags":[
        "metallurgy",
        "finished",
        "-",
        "metalworking",
        "metallic"
    ],
    "wof:name":"Panneaux Armatures Speciaux (pas)",
    "wof:placetype":"venue"
},
  "geometry": {"coordinates":[5.265574,43.414597],"type":"Point"}
}