{
  "type": "Feature",
  "properties": {
    "addr:full":"4, Rue du Professeur Langevin, 59000 Lille Nord Pas-de-Calais",
    "addr:housenumber":"4",
    "addr:postcode":"59000",
    "addr:street":"Rue Du Professeur Langevin",
    "iso:country":"FR",
    "sg:address":"4, Rue du Professeur Langevin, 59000 Lille",
    "sg:orig_category":"Unclassifiable Establishments",
    "sg:phone":"+33 3 20 16 22 00",
    "sg:province":"Nord Pas-de-Calais",
    "wof:name":"Altadis S.a.",
    "wof:placetype":"venue"
},
  "geometry": {"coordinates":[3.073636,50.627552],"type":"Point"}
}