{
  "type": "Feature",
  "properties": {
    "iso:country":"FR",
    "sg:address":"Rte De Grosrouvre Ch\u00e2teau De La Couharde 78940 La Queue Les Yvelines",
    "sg:classifiers":[
        {
            "category":"Sports & Exercise",
            "subcategory":"Sports Center",
            "type":"Entertainment"
        }
    ],
    "sg:phone":"+33 1 34 86 48 89",
    "sg:postcode":"78940",
    "sg:province":"Ile de France",
    "sg:tags":[
        "game"
    ],
    "wof:name":"Golf Des Yvelines",
    "wof:placetype":"venue"
},
  "geometry": {"coordinates":[1.773036,48.805157],"type":"Point"}
}