{
  "type": "Feature",
  "properties": {
    "addr:full":"9 Rue Du Commerce 67202 Wolfisheim Wolfisheim Alsace 67202",
    "addr:housenumber":"9",
    "addr:postcode":"67202;67202",
    "addr:street":"Rue Du Commerce",
    "iso:country":"FR",
    "sg:address":"9 Rue Du Commerce 67202 Wolfisheim",
    "sg:city":"Wolfisheim",
    "sg:classifiers":[
        {
            "category":"Manufacturing",
            "subcategory":"Tools & Machinery",
            "type":"Manufacturing & Wholesale Goods"
        }
    ],
    "sg:phone":"+33 3 88 77 14 57",
    "sg:postcode":"67202",
    "sg:province":"Alsace",
    "sg:tags":[
        "environment",
        "equipment",
        "-"
    ],
    "wof:name":"Lingenheld Environnement",
    "wof:placetype":"venue"
},
  "geometry": {"coordinates":[7.668426,48.591789],"type":"Point"}
}