{
  "type": "Feature",
  "properties": {
    "iso:country":"FR",
    "sg:address":"20 bis, rue Louis-Philippe",
    "sg:city":"Neuilly-sur-Seine",
    "sg:classifiers":[
        {
            "category":"Professional",
            "subcategory":"Computer Services",
            "type":"Services"
        }
    ],
    "sg:postcode":"92200",
    "sg:tags":[
        "cv",
        "resume",
        "web-application",
        "jobs",
        "hiring"
    ],
    "sg:website":"http://moncv.com",
    "wof:name":"MonCV.com",
    "wof:placetype":"venue"
},
  "geometry": {"coordinates":[2.271368,48.881361],"type":"Point"}
}