{
  "type": "Feature",
  "properties": {
    "addr:full":"76 Rue De La Mine Za Le Rouergas 34980 St Gely Du Fesc Languedoc-Roussillon 34980",
    "addr:housenumber":"76",
    "addr:postcode":"34980;34980",
    "addr:street":"Rue De La Mine Za Le Rouergas",
    "iso:country":"FR",
    "sg:address":"76 Rue De La Mine Za Le Rouergas 34980 St Gely Du Fesc",
    "sg:classifiers":[
        {
            "category":"Utilities",
            "subcategory":"Mobile Phone",
            "type":"Services"
        }
    ],
    "sg:phone":"+33 4 67 66 67 90",
    "sg:postcode":"34980",
    "sg:province":"Languedoc-Roussillon",
    "sg:tags":[
        "telecommunication",
        "audio-visual"
    ],
    "wof:name":"Master",
    "wof:placetype":"venue"
},
  "geometry": {"coordinates":[3.806955,43.69313],"type":"Point"}
}