{
  "type": "Feature",
  "properties": {
    "addr:full":"Rue Jean Rostand La Talaudi\u00e8re Rhone-Alpes 42350",
    "addr:postcode":"42350",
    "addr:street":"Rue Jean Rostand La;Rhone-Alpes",
    "iso:country":"FR",
    "sg:address":"Rue Jean Rostand",
    "sg:city":"La Talaudi\u00e8re",
    "sg:orig_category":"Unclassifiable Establishments",
    "sg:phone":"+33 4 77 47 56 14",
    "sg:postcode":"42350",
    "sg:province":"Rhone-Alpes",
    "wof:name":"Slic S.a.r.l.",
    "wof:placetype":"venue"
},
  "geometry": {"coordinates":[4.438196,45.471745],"type":"Point"}
}