{
  "type": "Feature",
  "properties": {
    "addr:full":"ZA la Bayette Le Pradet Provence-Alpes-C\u00f4te d'Azur 83220",
    "addr:postcode":"83220",
    "addr:street":"Za La Bayette Le Pradet",
    "iso:country":"FR",
    "sg:address":"ZA la Bayette",
    "sg:city":"Le Pradet",
    "sg:orig_category":"Unclassifiable Establishments",
    "sg:phone":"+33 4 94 08 02 60",
    "sg:postcode":"83220",
    "sg:province":"Provence-Alpes-C\u00f4te d'Azur",
    "wof:name":"Copas Syst\u00e8mes",
    "wof:placetype":"venue"
},
  "geometry": {"coordinates":[6.022305,43.106483],"type":"Point"}
}