{
  "type": "Feature",
  "properties": {
    "iso:country":"FR",
    "sg:address":"Alex Zi Le Marais 01810 Groissiat",
    "sg:classifiers":[
        {
            "category":"Manufacturing",
            "subcategory":"Metals",
            "type":"Manufacturing & Wholesale Goods"
        }
    ],
    "sg:phone":"+33 4 74 73 53 37",
    "sg:province":"Rhone-Alpes",
    "sg:tags":[
        "metallurgy",
        "metalworking",
        "processing"
    ],
    "wof:name":"C C M Sas",
    "wof:placetype":"venue"
},
  "geometry": {"coordinates":[-71.166031,42.649849],"type":"Point"}
}