{
  "type": "Feature",
  "properties": {
    "addr:full":"B.P. 22, 59138 Pont sur Sambre^^97, Rue du 8 Mai 1945, 59138 Pont sur Sambre Nord Pas-de-Calais",
    "addr:postcode":"59138;59138",
    "addr:street":"B.P. 22;Rue Du 8 Mai 1945;Sambre Nord",
    "iso:country":"FR",
    "sg:address":"B.P. 22, 59138 Pont sur Sambre^^97, Rue du 8 Mai 1945, 59138 Pont sur Sambre",
    "sg:orig_category":"Non-Classified Establishments",
    "sg:phone":"+33 3 27 67 33 62",
    "sg:province":"Nord Pas-de-Calais",
    "wof:name":"Ringer Chaudronnerie Et Emballages S.a.",
    "wof:placetype":"venue"
},
  "geometry": {"coordinates":[3.846925,50.221619],"type":"Point"}
}