{
  "type": "Feature",
  "properties": {
    "addr:full":"Moriette 26760 Beaumont Les Valence Rhone-Alpes 26760",
    "addr:postcode":"26760;26760",
    "addr:street":"Moriette;Les;Rhone-Alpes",
    "iso:country":"FR",
    "sg:address":"Moriette 26760 Beaumont Les Valence",
    "sg:classifiers":[
        {
            "category":"Building & Trades",
            "subcategory":"Equipment Rental",
            "type":"Services"
        }
    ],
    "sg:phone":"+33 4 75 59 72 00",
    "sg:postcode":"26760",
    "sg:province":"Rhone-Alpes",
    "sg:tags":[
        "motor-cars",
        "road",
        "transport",
        "vehicle"
    ],
    "wof:name":"Sporting Garage Sarl",
    "wof:placetype":"venue"
},
  "geometry": {"coordinates":[4.939775,44.872269],"type":"Point"}
}