{
  "type": "Feature",
  "properties": {
    "iso:country":"FR",
    "sg:address":"8, Rue Jules Ferry, 88200 Remiremont",
    "sg:orig_category":"Unclassifiable Establishments",
    "sg:phone":"+33 3 29 23 18 92",
    "sg:province":"Lorraine",
    "wof:name":"Covobois S.a.",
    "wof:placetype":"venue"
},
  "geometry": {"coordinates":[6.599273,48.014832],"type":"Point"}
}