{
  "type": "Feature",
  "properties": {
    "addr:full":"8, Rue Jules Ferry, 88200 Remiremont Lorraine",
    "addr:housenumber":"8",
    "addr:postcode":"88200",
    "addr:street":"Rue Jules Ferry",
    "iso:country":"FR",
    "sg:address":"8, Rue Jules Ferry, 88200 Remiremont",
    "sg:orig_category":"Unclassifiable Establishments",
    "sg:phone":"+33 3 29 23 18 92",
    "sg:province":"Lorraine",
    "wof:name":"Covobois S.a.",
    "wof:placetype":"venue"
},
  "geometry": {"coordinates":[6.599273,48.014832],"type":"Point"}
}