{
  "type": "Feature",
  "properties": {
    "iso:country":"FR",
    "sg:address":"3, Rue du Renouveau, 78700 Conflans Sainte Honorine",
    "sg:orig_category":"Unclassifiable Establishments",
    "sg:phone":"+33 1 34 90 11 67",
    "sg:province":"Ile de France",
    "wof:name":"Pr\u00e9cis Pr\u00e9vost S.a.r.l.",
    "wof:placetype":"venue"
},
  "geometry": {"coordinates":[2.10164,49.003841],"type":"Point"}
}