{
  "type": "Feature",
  "properties": {
    "addr:full":"22, Rue Albert Collinet, 94170 Le Perreux sur Marne Ile de France",
    "addr:housenumber":"22",
    "addr:postcode":"94170",
    "addr:street":"Rue Albert Collinet",
    "iso:country":"FR",
    "sg:address":"22, Rue Albert Collinet, 94170 Le Perreux sur Marne",
    "sg:orig_category":"Non-Classified Establishments",
    "sg:phone":"+33 1 43 24 06 95",
    "sg:province":"Ile de France",
    "wof:name":"Plastomenu S.a.r.l.",
    "wof:placetype":"venue"
},
  "geometry": {"coordinates":[2.504528,48.855782],"type":"Point"}
}