{
  "type": "Feature",
  "properties": {
    "addr:full":"Rte de Paris Golancourt Picardie 60640",
    "addr:postcode":"60640",
    "addr:street":"Rte De Paris;Picardie",
    "iso:country":"FR",
    "sg:address":"Rte de Paris",
    "sg:city":"Golancourt",
    "sg:orig_category":"Non-Classified Establishments",
    "sg:phone":"+33 3 44 43 20 26",
    "sg:postcode":"60640",
    "sg:province":"Picardie",
    "wof:name":"F.n.e.i.b. S.a.",
    "wof:placetype":"venue"
},
  "geometry": {"coordinates":[3.06262,49.701321],"type":"Point"}
}