{
  "type": "Feature",
  "properties": {
    "iso:country":"FR",
    "sg:address":"46, Rue Joseph Desaymard, 63000 Clermont Ferrand",
    "sg:city":"Clermont-Ferrand",
    "sg:orig_category":"Non-Classified Establishments",
    "sg:phone":"+33 4 73 28 93 17",
    "sg:postcode":"63000",
    "sg:province":"Auvergne",
    "wof:name":"Blanchet S.a.",
    "wof:placetype":"venue"
},
  "geometry": {"coordinates":[3.127775,45.767426],"type":"Point"}
}