{
  "type": "Feature",
  "properties": {
    "addr:full":"ZI de la Fresnais Bain de Bretagne Bretagne 35470",
    "addr:housenumber":"fresnais",
    "addr:postcode":"35470",
    "addr:street":"Zi De La",
    "iso:country":"FR",
    "sg:address":"ZI de la Fresnais",
    "sg:city":"Bain de Bretagne",
    "sg:orig_category":"Unclassifiable Establishments",
    "sg:phone":"+33 2 99 43 74 75",
    "sg:postcode":"35470",
    "sg:province":"Bretagne",
    "wof:name":"S.b.t.s. S.a.r.l. - Soci\u00e9t\u00e9 Bretonne De T\u00f4lerie Et Serrurerie",
    "wof:placetype":"venue"
},
  "geometry": {"coordinates":[-1.683356,47.84523],"type":"Point"}
}