{
  "type": "Feature",
  "properties": {
    "iso:country":"FR",
    "sg:address":"3, Rue de Lorraine, 62510 Arques",
    "sg:orig_category":"Unclassifiable Establishments",
    "sg:phone":"+33 3 21 98 21 21",
    "sg:province":"Nord Pas-de-Calais",
    "wof:name":"Biov\u00e9 Laboratoires S.a.",
    "wof:placetype":"venue"
},
  "geometry": {"coordinates":[2.296285,50.746029],"type":"Point"}
}