{
  "type": "Feature",
  "properties": {
    "iso:country":"FR",
    "sg:address":"20 R Napol\u00e9on Fauveau 95170 Deuil La Barre",
    "sg:classifiers":[
        {
            "category":"Wholesale",
            "subcategory":"Meat",
            "type":"Manufacturing & Wholesale Goods"
        }
    ],
    "sg:phone":"+33 1 39 83 36 66",
    "sg:postcode":"95170",
    "sg:province":"Ile de France",
    "sg:tags":[
        "food",
        "cooked",
        "product",
        "related"
    ],
    "wof:name":"Hgs Jamic Sa",
    "wof:placetype":"venue"
},
  "geometry": {"coordinates":[2.32473,48.973381],"type":"Point"}
}