{
  "type": "Feature",
  "properties": {
    "iso:country":"FR",
    "sg:address":"29, Rte de Haguenau, 67670 Mommenheim",
    "sg:city":"Mommenheim",
    "sg:orig_category":"Unclassifiable Establishments",
    "sg:phone":"+33 3 88 51 62 07",
    "sg:postcode":"67670",
    "sg:province":"Alsace",
    "wof:name":"Bas-rhin Motoculture S.a.r.l.",
    "wof:placetype":"venue"
},
  "geometry": {"coordinates":[7.64947,48.75758],"type":"Point"}
}