{
  "type": "Feature",
  "properties": {
    "addr:full":"Faubourg Vergaville 57260 Dieuze Lorraine 57260",
    "addr:postcode":"57260;57260",
    "addr:street":"Faubourg Vergaville",
    "iso:country":"FR",
    "sg:address":"Faubourg Vergaville 57260 Dieuze",
    "sg:classifiers":[
        {
            "category":"Manufacturing",
            "subcategory":"Metals",
            "type":"Manufacturing & Wholesale Goods"
        }
    ],
    "sg:phone":"+33 3 87 86 85 58",
    "sg:postcode":"57260",
    "sg:province":"Lorraine",
    "sg:tags":[
        "metallurgy",
        "metalworking"
    ],
    "wof:name":"Holdiam Ets Metaquartz Sa",
    "wof:placetype":"venue"
},
  "geometry": {"coordinates":[6.72642,48.823994],"type":"Point"}
}