{
  "type": "Feature",
  "properties": {
    "addr:full":"3, Rue Saint Isidore, 69003 Lyon Rhone-Alpes 69003",
    "addr:housenumber":"3",
    "addr:postcode":"69003;69003",
    "addr:street":"Rue Saint Isidore",
    "iso:country":"FR",
    "sg:address":"3, Rue Saint Isidore, 69003 Lyon",
    "sg:orig_category":"Unclassifiable Establishments",
    "sg:phone":"+33 4 72 12 00 63",
    "sg:postcode":"69003",
    "sg:province":"Rhone-Alpes",
    "wof:name":"Balas S.a.",
    "wof:placetype":"venue"
},
  "geometry": {"coordinates":[4.883824,45.753117],"type":"Point"}
}