{
  "type": "Feature",
  "properties": {
    "addr:full":"26 Boulevard Victor Hugo 06000 Nice Centre",
    "addr:housenumber":"26",
    "addr:postcode":"06000",
    "addr:street":"Boulevard Victor Hugo",
    "iso:country":"FR",
    "sg:address":"26 Boulevard Victor Hugo 06000 Nice",
    "sg:classifiers":[
        {
            "category":"Professional",
            "subcategory":"Advertising",
            "type":"Services"
        }
    ],
    "sg:phone":"+33 4 92 14 44 88",
    "sg:province":"Centre",
    "sg:tags":[
        "communication",
        "medium"
    ],
    "wof:name":"Gregoire Gardette Associes",
    "wof:placetype":"venue"
},
  "geometry": {"coordinates":[7.263589,43.699356],"type":"Point"}
}