{
  "type": "Feature",
  "properties": {
    "iso:country":"FR",
    "sg:address":"Lahumere Micaouhaou 40220 Tarnos",
    "sg:city":"Tarnos",
    "sg:classifiers":[
        {
            "category":"Farming",
            "subcategory":"Farm",
            "type":"Manufacturing & Wholesale Goods"
        }
    ],
    "sg:phone":"+33 5 59 64 25 94",
    "sg:postcode":"40220",
    "sg:province":"Aquitaine",
    "sg:tags":[
        "horticulture",
        "agriculture",
        "livestock"
    ],
    "wof:name":"Jardilys Jardinerie Dicharry",
    "wof:placetype":"venue"
},
  "geometry": {"coordinates":[-1.442075,43.530788],"type":"Point"}
}