{
  "type": "Feature",
  "properties": {
    "iso:country":"FR",
    "sg:address":"7 Traverse Trivier Bat E2 13004 Marseille",
    "sg:classifiers":[
        {
            "category":"Food Court",
            "type":"Food & Drink"
        }
    ],
    "sg:phone":"+33 4 91 66 01 38",
    "sg:province":"Poitou-Charentes",
    "sg:tags":[
        "product",
        "related"
    ],
    "wof:name":"Batiment Provencial Sarl",
    "wof:placetype":"venue"
},
  "geometry": {"coordinates":[5.405784,43.312382],"type":"Point"}
}