{
  "type": "Feature",
  "properties": {
    "addr:full":"4, Rue Galil\u00e9e - Quartier de l'Europe, 78285 Guyancourt C\u00e9dex Ancourt Haute Normandie 76370",
    "addr:housenumber":"4",
    "addr:postcode":"78285;76370",
    "addr:street":"Rue Galile\u0301E;Haute Normandie",
    "iso:country":"FR",
    "sg:address":"4, Rue Galil\u00e9e - Quartier de l'Europe, 78285 Guyancourt C\u00e9dex",
    "sg:city":"Ancourt",
    "sg:orig_category":"Non-Classified Establishments",
    "sg:phone":"+33 1 34 52 10 30",
    "sg:postcode":"76370",
    "sg:province":"Haute Normandie",
    "wof:name":"Fondis Electronic S.a.",
    "wof:placetype":"venue"
},
  "geometry": {"coordinates":[2.055575,48.76733],"type":"Point"}
}