{
  "type": "Feature",
  "properties": {
    "addr:full":"B.P. 600 Melun C\u00e9dex Ile de France 77006",
    "addr:housenumber":"b.p. 600",
    "addr:postcode":"77006",
    "iso:country":"FR",
    "sg:address":"B.P. 600",
    "sg:city":"Melun C\u00e9dex",
    "sg:orig_category":"Non-Classified Establishments",
    "sg:phone":"+33 1 64 10 44 44",
    "sg:postcode":"77006",
    "sg:province":"Ile de France",
    "wof:name":"S.b. Ballestero S.a.",
    "wof:placetype":"venue"
},
  "geometry": {"coordinates":[2.664085,48.539577],"type":"Point"}
}