{
  "type": "Feature",
  "properties": {
    "addr:full":"rte St Saturnin 84130 Pontet (Le) Aquitaine",
    "addr:postcode":"84130",
    "addr:street":"Rte St Saturnin",
    "iso:country":"FR",
    "sg:address":"rte St Saturnin 84130 Pontet (Le)",
    "sg:classifiers":[
        {
            "category":"Autos & Motor Vehicles",
            "subcategory":"Automobile Sales",
            "type":"Retail Goods"
        }
    ],
    "sg:phone":"+33 4 90 31 12 00",
    "sg:province":"Aquitaine",
    "sg:tags":[
        "equipment",
        "motor-cars",
        "transport"
    ],
    "wof:name":"Calvino",
    "wof:placetype":"venue"
},
  "geometry": {"coordinates":[-111.888184,40.759521],"type":"Point"}
}