{
  "type": "Feature",
  "properties": {
    "addr:full":"B.P. 20, 63600 Ambert C\u00e9dex^^ZI, 63600 Ambert Ambert Auvergne 63600",
    "addr:postcode":"63600;63600;63600",
    "addr:street":"B.P. 20",
    "iso:country":"FR",
    "sg:address":"B.P. 20, 63600 Ambert C\u00e9dex^^ZI, 63600 Ambert",
    "sg:city":"Ambert",
    "sg:orig_category":"Non-Classified Establishments",
    "sg:phone":"+33 4 73 82 41 41",
    "sg:postcode":"63600",
    "sg:province":"Auvergne",
    "wof:name":"Sautra S.a. - Soci\u00e9t\u00e9 Auvergnate Transport Rh\u00f4ne-alpes",
    "wof:placetype":"venue"
},
  "geometry": {"coordinates":[3.78864,45.467865],"type":"Point"}
}