{
  "type": "Feature",
  "properties": {
    "iso:country":"FR",
    "sg:address":"chemin Clastrois 02100 St Quentin",
    "sg:classifiers":[
        {
            "category":"Military Area",
            "subcategory":"Army Base",
            "type":"Public Place"
        }
    ],
    "sg:phone":"+33 3 23 50 69 69",
    "sg:postcode":"02100",
    "sg:province":"Picardie",
    "sg:tags":[
        "font"
    ],
    "wof:name":"S.i.f. Sa",
    "wof:placetype":"venue"
},
  "geometry": {"coordinates":[3.301,49.836185],"type":"Point"}
}