{
  "type": "Feature",
  "properties": {
    "iso:country":"FR",
    "sg:address":"Avenue Joseph Lazare 34500 Beziers",
    "sg:classifiers":[
        {
            "category":"Manufacturing",
            "subcategory":"Rubber & Plastics",
            "type":"Manufacturing & Wholesale Goods"
        }
    ],
    "sg:phone":"+33 4 67 35 60 00",
    "sg:province":"Languedoc-Roussillon",
    "wof:name":"Placoplatre",
    "wof:placetype":"venue"
},
  "geometry": {"coordinates":[3.222161,43.33453],"type":"Point"}
}