{
  "type": "Feature",
  "properties": {
    "addr:full":"48, Rue Saint-Augustin, 57230 Bitche Lorraine",
    "addr:housenumber":"48",
    "addr:postcode":"57230",
    "addr:street":"Rue Saint-Augustin",
    "iso:country":"FR",
    "sg:address":"48, Rue Saint-Augustin, 57230 Bitche",
    "sg:orig_category":"Unclassifiable Establishments",
    "sg:phone":"+33 3 87 96 22 31",
    "sg:province":"Lorraine",
    "wof:name":"I.e.e. S.a.r.l. - Installation D'equipements Electriques",
    "wof:placetype":"venue"
},
  "geometry": {"coordinates":[7.431894,49.055428],"type":"Point"}
}