{
  "type": "Feature",
  "properties": {
    "iso:country":"FR",
    "sg:address":"Rue Jacques Callot - ZI Marienau",
    "sg:city":"Forbach",
    "sg:orig_category":"GROSSISTE: M\u00c9TALLURGIQUES ET SID\u00c9RURGIQUES, POUTRELLES, LAMIN\u00c9ES, T\u00d4LES, TUBES, ACIERS SP\u00c9CIAUX",
    "sg:phone":"+33 3 87 84 24 25",
    "sg:postcode":"57600",
    "sg:province":"Lorraine",
    "wof:name":"Saarex S.a.r.l.",
    "wof:placetype":"venue"
},
  "geometry": {"coordinates":[6.895186,49.185646],"type":"Point"}
}