{
  "type": "Feature",
  "properties": {
    "iso:country":"FR",
    "sg:address":"6, Rue des Bretons, 93218 La Plaine saint Denis C\u00e9dex",
    "sg:city":"Plaine",
    "sg:orig_category":"Non-Classified Establishments",
    "sg:phone":"+33 1 49 46 24 70",
    "sg:postcode":"67420",
    "sg:province":"Alsace",
    "wof:name":"Sorice Distribution S.a.",
    "wof:placetype":"venue"
},
  "geometry": {"coordinates":[2.358176,48.920033],"type":"Point"}
}