{
  "type": "Feature",
  "properties": {
    "iso:country":"FR",
    "sg:address":"15 Avenue Des Trois Peuples Zi Observatoire 15 21 23 78180 Montigny Le Bretonneux",
    "sg:classifiers":[
        {
            "category":"Food & Beverages",
            "subcategory":"Dairy",
            "type":"Retail Goods"
        }
    ],
    "sg:phone":"+33 1 61 08 49 49",
    "sg:postcode":"78180",
    "sg:province":"Ile de France",
    "sg:tags":[
        "product",
        "related"
    ],
    "wof:name":"La Sorbetine",
    "wof:placetype":"venue"
},
  "geometry": {"coordinates":[2.018596,48.77562],"type":"Point"}
}