{
  "type": "Feature",
  "properties": {
    "addr:full":"128 Rue De Pfastatt 68260 Kingersheim Kingersheim Alsace 68260",
    "addr:housenumber":"128",
    "addr:postcode":"68260;68260",
    "addr:street":"Rue De Pfastatt",
    "iso:country":"FR",
    "sg:address":"128 Rue De Pfastatt 68260 Kingersheim",
    "sg:city":"Kingersheim",
    "sg:classifiers":[
        {
            "category":"Building & Trades",
            "subcategory":"Construction",
            "type":"Services"
        }
    ],
    "sg:phone":"+33 3 89 52 88 88",
    "sg:postcode":"68260",
    "sg:province":"Alsace",
    "sg:tags":[
        "work",
        "public"
    ],
    "wof:name":"Eurovia Alsace Franche Comte",
    "wof:placetype":"venue"
},
  "geometry": {"coordinates":[7.30946,47.784805],"type":"Point"}
}