{
  "type": "Feature",
  "properties": {
    "addr:full":"7 Place Du Marche Vend\u00f4me Centre 41100",
    "addr:housenumber":"7",
    "addr:postcode":"41100",
    "addr:street":"Place Du Marche Vendo\u0302Me",
    "iso:country":"FR",
    "sg:address":"7 Place Du Marche",
    "sg:city":"Vend\u00f4me",
    "sg:classifiers":[
        {
            "category":"Banks & Credit Unions",
            "subcategory":"Financial Services",
            "type":"Services"
        }
    ],
    "sg:phone":"+33 2 54 73 38 39",
    "sg:postcode":"41100",
    "sg:province":"Centre",
    "sg:tags":[
        "banking",
        "finance",
        "insurance"
    ],
    "wof:name":"Banque Regionale De L'ouest (bro)",
    "wof:placetype":"venue"
},
  "geometry": {"coordinates":[1.065628,47.791195],"type":"Point"}
}