{
  "type": "Feature",
  "properties": {
    "addr:full":"13 Ld La Forge 68160 Ste Marie Aux Mines Sainte-Croix-aux-Mines Alsace 68160",
    "addr:housenumber":"13",
    "addr:postcode":"68160;68160",
    "addr:street":"Ld La;Aux Mines",
    "iso:country":"FR",
    "sg:address":"13 Ld La Forge 68160 Ste Marie Aux Mines",
    "sg:city":"Sainte-Croix-aux-Mines",
    "sg:classifiers":[
        {
            "category":"Food & Beverages",
            "subcategory":"Meat & Fish",
            "type":"Retail Goods"
        }
    ],
    "sg:phone":"+33 3 89 58 62 70",
    "sg:postcode":"68160",
    "sg:province":"Alsace",
    "sg:tags":[
        "preserve",
        "cooked",
        "product",
        "related"
    ],
    "wof:name":"Eurl Produits De La Cigogne Herrbrech",
    "wof:placetype":"venue"
},
  "geometry": {"coordinates":[7.203152,48.254871],"type":"Point"}
}