{
  "type": "Feature",
  "properties": {
    "iso:country":"FR",
    "sg:address":"B.P. 19, 73401 Ugine Cedex^^500, Rue Henri Gruaz, 73400 Ugine",
    "sg:orig_category":"Non-Classified Establishments",
    "sg:phone":"+33 4 79 89 74 01",
    "sg:postcode":"73400",
    "sg:province":"Rhone-Alpes",
    "wof:name":"Transports Mottier Et Fils S.a.",
    "wof:placetype":"venue"
},
  "geometry": {"coordinates":[6.403278,45.72578],"type":"Point"}
}