{
  "type": "Feature",
  "properties": {
    "iso:country":"FR",
    "sg:address":"B.P. 29, 59009 Lille C\u00e9dex^^33, Rue N\u00e9grier, 59800 Lille",
    "sg:orig_category":"Non-Classified Establishments",
    "sg:phone":"+33 3 20 55 42 60",
    "sg:province":"Nord Pas-de-Calais",
    "wof:name":"La Croix Du Nord S.a.",
    "wof:placetype":"venue"
},
  "geometry": {"coordinates":[3.08024,50.636189],"type":"Point"}
}