{
  "type": "Feature",
  "properties": {
    "addr:full":"13 Rue Fenelon 56100 Lorient Lorient Bretagne 56100",
    "addr:housenumber":"13",
    "addr:postcode":"56100;56100",
    "addr:street":"Rue Fenelon",
    "iso:country":"FR",
    "sg:address":"13 Rue Fenelon 56100 Lorient",
    "sg:city":"Lorient",
    "sg:classifiers":[
        {
            "category":"Shopping",
            "subcategory":"Computers & Home Electronics",
            "type":"Retail Goods"
        }
    ],
    "sg:phone":"+33 2 97 21 31 99",
    "sg:postcode":"56100",
    "sg:province":"Bretagne",
    "sg:tags":[
        "electronic",
        "electrical",
        "equipment"
    ],
    "wof:name":"Nuance",
    "wof:placetype":"venue"
},
  "geometry": {"coordinates":[-3.360579,47.750248],"type":"Point"}
}