{
  "type": "Feature",
  "properties": {
    "addr:full":"ZI du Martray 14730 Giberville Giberville Basse Normandie 14730",
    "addr:postcode":"14730;14730",
    "addr:street":"Zi Du Martray",
    "iso:country":"FR",
    "sg:address":"ZI du Martray 14730 Giberville",
    "sg:city":"Giberville",
    "sg:classifiers":[
        {
            "category":"Professional",
            "type":"Services"
        }
    ],
    "sg:phone":"+33 2 31 35 60 60",
    "sg:postcode":"14730",
    "sg:province":"Basse Normandie",
    "sg:tags":[
        "transport"
    ],
    "wof:name":"Larbre Industrie S.a.",
    "wof:placetype":"venue"
},
  "geometry": {"coordinates":[-0.283609,49.182594],"type":"Point"}
}