{
  "type": "Feature",
  "properties": {
    "addr:full":"641, Bd de l'Industrie, 33260 La Teste de Buch Teste-de-Buch Aquitaine 33260",
    "addr:housenumber":"641",
    "addr:postcode":"33260;33260",
    "addr:street":"Bd De L'Industrie",
    "iso:country":"FR",
    "sg:address":"641, Bd de l'Industrie, 33260 La Teste de Buch",
    "sg:city":"Teste-de-Buch",
    "sg:orig_category":"Non-Classified Establishments",
    "sg:phone":"+33 5 56 54 16 54",
    "sg:postcode":"33260",
    "sg:province":"Aquitaine",
    "wof:name":"Labenne Rougier S.n.c.",
    "wof:placetype":"venue"
},
  "geometry": {"coordinates":[-1.130375,44.60799],"type":"Point"}
}