{
  "type": "Feature",
  "properties": {
    "iso:country":"FR",
    "sg:address":"65, Rue Claudio Arrau - ZI la Courtine, 84000 Avignon",
    "sg:orig_category":"Unclassifiable Establishments",
    "sg:phone":"+33 4 90 14 27 70",
    "sg:province":"Provence-Alpes-C\u00f4te d'Azur",
    "wof:name":"H.p.r. S.a. - Hydraulique Et Pneumatique Rubber",
    "wof:placetype":"venue"
},
  "geometry": {"coordinates":[4.806015,43.948753],"type":"Point"}
}