{
  "type": "Feature",
  "properties": {
    "addr:full":"Rue Du Bruscos 64230 Sauvagnon Sauvagnon Aquitaine 64230",
    "addr:postcode":"64230;64230",
    "addr:street":"Rue Du Bruscos",
    "iso:country":"FR",
    "sg:address":"Rue Du Bruscos 64230 Sauvagnon",
    "sg:city":"Sauvagnon",
    "sg:classifiers":[
        {
            "category":"Manufacturing",
            "subcategory":"Rubber & Plastics",
            "type":"Manufacturing & Wholesale Goods"
        }
    ],
    "sg:phone":"+33 5 59 33 77 01",
    "sg:postcode":"64230",
    "sg:province":"Aquitaine",
    "wof:name":"Axyal Sa",
    "wof:placetype":"venue"
},
  "geometry": {"coordinates":[-0.410669,43.383751],"type":"Point"}
}