{
  "type": "Feature",
  "properties": {
    "addr:full":"409, Rue des Fr\u00e8res Lumi\u00e8re, 71000 M\u00e2con Sanc\u00e9 Bourgogne 71000",
    "addr:housenumber":"409",
    "addr:postcode":"71000;71000",
    "addr:street":"Rue Des Fre\u0300Res Lumie\u0300Re",
    "iso:country":"FR",
    "sg:address":"409, Rue des Fr\u00e8res Lumi\u00e8re, 71000 M\u00e2con",
    "sg:city":"Sanc\u00e9",
    "sg:orig_category":"Non-Classified Establishments",
    "sg:phone":"+33 3 85 20 56 56",
    "sg:postcode":"71000",
    "sg:province":"Bourgogne",
    "wof:name":"Lefebvre S.a.",
    "wof:placetype":"venue"
},
  "geometry": {"coordinates":[4.821981,46.285843],"type":"Point"}
}