{
  "type": "Feature",
  "properties": {
    "iso:country":"FR",
    "sg:address":"42 Rue Gambetta 83990 St Tropez",
    "sg:classifiers":[
        {
            "category":"Professional",
            "subcategory":"Printing & Photocopies",
            "type":"Services"
        }
    ],
    "sg:phone":"+33 4 94 55 96 10",
    "sg:province":"Provence-Alpes-C\u00f4te d'Azur",
    "sg:tags":[
        "publishing"
    ],
    "wof:name":"Republique",
    "wof:placetype":"venue"
},
  "geometry": {"coordinates":[6.641125,43.270741],"type":"Point"}
}