{
  "type": "Feature",
  "properties": {
    "iso:country":"FR",
    "sg:address":"32, Rue Malet Stevens - B\u00e2t. K, 30972 N\u00eemes C\u00e9dex",
    "sg:orig_category":"Non-Classified Establishments",
    "sg:phone":"+33 4 66 29 74 26",
    "sg:province":"Languedoc-Roussillon",
    "wof:name":"I.f.c. Provence S.a. - Institut Pour La Formation Et Le Conseil",
    "wof:placetype":"venue"
},
  "geometry": {"coordinates":[4.3451,43.838039],"type":"Point"}
}