{
  "type": "Feature",
  "properties": {
    "addr:full":"2, Bd du Mar\u00e9chal Juin, 65000 Tarbes Midi Pyr\u00e9n\u00e9es",
    "addr:housenumber":"2",
    "addr:postcode":"65000",
    "addr:street":"Bd Du Mare\u0301Chal Juin",
    "iso:country":"FR",
    "sg:address":"2, Bd du Mar\u00e9chal Juin, 65000 Tarbes",
    "sg:orig_category":"Unclassifiable Establishments",
    "sg:phone":"+33 5 62 34 34 07",
    "sg:province":"Midi Pyr\u00e9n\u00e9es",
    "wof:name":"Exploitation Conseil Imprimerie S.a.",
    "wof:placetype":"venue"
},
  "geometry": {"coordinates":[0.061979,43.239567],"type":"Point"}
}