{
  "type": "Feature",
  "properties": {
    "addr:full":"2 rue Fran\u00e7ois Mignotte 21700 NUITS ST GEORGES Agencourt Bourgogne 21700",
    "addr:housenumber":"2",
    "addr:postcode":"21700;21700",
    "addr:street":"Rue Franc\u0327Ois Mignotte;Nuits St;Bourgogne",
    "iso:country":"FR",
    "sg:address":"2 rue Fran\u00e7ois Mignotte 21700 NUITS ST GEORGES",
    "sg:city":"Agencourt",
    "sg:classifiers":[
        {
            "category":"Wholesale",
            "subcategory":"Wine & Distilled Alcoholic Beverages",
            "type":"Manufacturing & Wholesale Goods"
        }
    ],
    "sg:phone":"+33 3 80 62 42 00",
    "sg:postcode":"21700",
    "sg:province":"Bourgogne",
    "sg:tags":[
        "french"
    ],
    "wof:name":"Soci\u00e9t\u00e9 Moillard S.a.",
    "wof:placetype":"venue"
},
  "geometry": {"coordinates":[4.95002,47.139481],"type":"Point"}
}