{
  "type": "Feature",
  "properties": {
    "iso:country":"FR",
    "sg:address":"1 Rue Chambrouill\u00e8re 53960 Bonchamp L\u00e8s Laval",
    "sg:classifiers":[
        {
            "category":"Professional",
            "subcategory":"Engineering",
            "type":"Services"
        }
    ],
    "sg:phone":"+33 2 43 53 13 81",
    "sg:postcode":"53960",
    "sg:province":"Pays de Loire",
    "sg:tags":[
        "machine",
        "-",
        "mechanical"
    ],
    "wof:name":"Maison Mene Sa",
    "wof:placetype":"venue"
},
  "geometry": {"coordinates":[-0.715479,48.076759],"type":"Point"}
}