{
  "type": "Feature",
  "properties": {
    "addr:full":"1 Rue Chambrouill\u00e8re 53960 Bonchamp L\u00e8s Laval Pays de Loire 53960",
    "addr:housenumber":"1",
    "addr:postcode":"53960;53960",
    "addr:street":"Rue Chambrouille\u0300Re;Le\u0300S Laval",
    "iso:country":"FR",
    "sg:address":"1 Rue Chambrouill\u00e8re 53960 Bonchamp L\u00e8s Laval",
    "sg:classifiers":[
        {
            "category":"Professional",
            "subcategory":"Engineering",
            "type":"Services"
        }
    ],
    "sg:phone":"+33 2 43 53 13 81",
    "sg:postcode":"53960",
    "sg:province":"Pays de Loire",
    "sg:tags":[
        "machine",
        "-",
        "mechanical"
    ],
    "wof:name":"Maison Mene Sa",
    "wof:placetype":"venue"
},
  "geometry": {"coordinates":[-0.715479,48.076759],"type":"Point"}
}