{
  "type": "Feature",
  "properties": {
    "iso:country":"FR",
    "sg:address":"4, Quai Bondu, 44450 La Chapelle Basse Mer",
    "sg:orig_category":"Non-Classified Establishments",
    "sg:phone":"+33 2 40 03 66 55",
    "sg:postcode":"44450",
    "sg:province":"Pays de Loire",
    "wof:name":"Bondu Services S.a.",
    "wof:placetype":"venue"
},
  "geometry": {"coordinates":[-1.368514,47.282291],"type":"Point"}
}