{
  "type": "Feature",
  "properties": {
    "iso:country":"FR",
    "sg:address":"194 Rue De Rivoli 75001 Paris",
    "sg:classifiers":[
        {
            "category":"Professional",
            "subcategory":"Business Services",
            "type":"Services"
        }
    ],
    "sg:phone":"+33 1 53 45 87 87",
    "sg:postcode":"75001",
    "sg:province":"Ile de France",
    "sg:tags":[
        "body",
        "advice"
    ],
    "wof:name":"Idace",
    "wof:placetype":"venue"
},
  "geometry": {"coordinates":[2.331716,48.864006],"type":"Point"}
}