{
  "type": "Feature",
  "properties": {
    "addr:full":"27 R De La Foret 91630 Avrainville Ile de France 91630",
    "addr:housenumber":"27",
    "addr:postcode":"91630;91630",
    "addr:street":"R De La Foret;Ile De France",
    "iso:country":"FR",
    "sg:address":"27 R De La Foret 91630 Avrainville",
    "sg:classifiers":[
        {
            "category":"Farming",
            "subcategory":"Livestock Farm",
            "type":"Manufacturing & Wholesale Goods"
        }
    ],
    "sg:phone":"+33 1 64 91 34 34",
    "sg:postcode":"91630",
    "sg:province":"Ile de France",
    "sg:tags":[
        "agriculture"
    ],
    "wof:name":"M. Lenoel Louis",
    "wof:placetype":"venue"
},
  "geometry": {"coordinates":[2.24464,48.557659],"type":"Point"}
}