{
  "type": "Feature",
  "properties": {
    "iso:country":"FR",
    "sg:address":"Z.I. Cantaranne",
    "sg:city":"Rodez",
    "sg:orig_category":"Non-Classified Establishments",
    "sg:phone":"+33 5 65 67 00 21",
    "sg:postcode":"12033",
    "sg:province":"Midi Pyr\u00e9n\u00e9es",
    "wof:name":"Drimmer S.a.",
    "wof:placetype":"venue"
},
  "geometry": {"coordinates":[2.57274,44.349819],"type":"Point"}
}