{
  "type": "Feature",
  "properties": {
    "addr:full":"4 Rue Coustou 69001 Lyon Rhone-Alpes 69001",
    "addr:housenumber":"4",
    "addr:postcode":"69001;69001",
    "addr:street":"Rue Coustou",
    "iso:country":"FR",
    "sg:address":"4 Rue Coustou 69001 Lyon",
    "sg:classifiers":[
        {
            "category":"Professional",
            "subcategory":"Business Services",
            "type":"Services"
        }
    ],
    "sg:phone":"+33 4 78 27 39 87",
    "sg:postcode":"69001",
    "sg:province":"Rhone-Alpes",
    "sg:tags":[
        "advice",
        "clothes"
    ],
    "wof:name":"Ste Ogier Pitaud Sarl",
    "wof:placetype":"venue"
},
  "geometry": {"coordinates":[4.834959,45.769375],"type":"Point"}
}