{
  "type": "Feature",
  "properties": {
    "addr:full":"5 Rue De Frappe 19100 Brive La Gaillarde Limousin 19100",
    "addr:housenumber":"5",
    "addr:postcode":"19100;19100",
    "addr:street":"Rue De Frappe",
    "iso:country":"FR",
    "sg:address":"5 Rue De Frappe 19100 Brive La Gaillarde",
    "sg:classifiers":[
        {
            "category":"Shopping",
            "subcategory":"Hobbies, Toys, & Games",
            "type":"Retail Goods"
        }
    ],
    "sg:phone":"+33 5 55 24 12 12",
    "sg:postcode":"19100",
    "sg:province":"Limousin",
    "sg:tags":[
        "product",
        "breeding",
        "miscellaneous",
        "animal",
        "entertainment"
    ],
    "wof:name":"Royal Canin Sa",
    "wof:placetype":"venue"
},
  "geometry": {"coordinates":[1.534558,45.16066],"type":"Point"}
}