{
  "type": "Feature",
  "properties": {
    "addr:full":"21 Rue Saint Jean 69550 CUBLIZE Rhone-Alpes",
    "addr:housenumber":"21",
    "addr:postcode":"69550",
    "addr:street":"Rue Saint Jean",
    "iso:country":"FR",
    "sg:address":"21 Rue Saint Jean 69550 CUBLIZE",
    "sg:classifiers":[
        {
            "category":"Manufacturing",
            "subcategory":"Rubber & Plastics",
            "type":"Manufacturing & Wholesale Goods"
        }
    ],
    "sg:phone":"+33 4 74 89 59 00",
    "sg:province":"Rhone-Alpes",
    "sg:tags":[
        "processing"
    ],
    "wof:name":"Borealis Compound Sa",
    "wof:placetype":"venue"
},
  "geometry": {"coordinates":[4.38088,46.01757],"type":"Point"}
}