{
  "type": "Feature",
  "properties": {
    "iso:country":"FR",
    "sg:address":"228, Rte Enco de Botte, 13190 Allauch",
    "sg:orig_category":"Non-Classified Establishments",
    "sg:phone":"+33 4 91 07 11 77",
    "sg:province":"Provence-Alpes-C\u00f4te d'Azur",
    "wof:name":"Laboratoire Cryomed France S.a.",
    "wof:placetype":"venue"
},
  "geometry": {"coordinates":[5.479548,43.323174],"type":"Point"}
}