{
  "type": "Feature",
  "properties": {
    "addr:full":"5 Rue Du Long Douet 14760 Bretteville Sur Odon Bretteville-sur-Odon Basse Normandie 14760",
    "addr:housenumber":"5",
    "addr:postcode":"14760;14760",
    "addr:street":"Rue Du Long Douet",
    "iso:country":"FR",
    "sg:address":"5 Rue Du Long Douet 14760 Bretteville Sur Odon",
    "sg:city":"Bretteville-sur-Odon",
    "sg:classifiers":[
        {
            "category":"Wholesale",
            "subcategory":"Medical Equipment & Supplies",
            "type":"Manufacturing & Wholesale Goods"
        }
    ],
    "sg:phone":"+33 2 31 74 51 79",
    "sg:postcode":"14760",
    "sg:province":"Basse Normandie",
    "sg:tags":[
        "instrument",
        "health",
        "-",
        "precision"
    ],
    "wof:name":"Sarl Jc Bisson",
    "wof:placetype":"venue"
},
  "geometry": {"coordinates":[-0.423844,49.167248],"type":"Point"}
}