{
  "type": "Feature",
  "properties": {
    "addr:full":"Quartier des Iles Sarras Rhone-Alpes 07370",
    "addr:postcode":"07370",
    "addr:street":"Quartier Des Iles Sarras Rhone-Alpes",
    "iso:country":"FR",
    "sg:address":"Quartier des Iles",
    "sg:city":"Sarras",
    "sg:orig_category":"Unclassifiable Establishments",
    "sg:phone":"+33 4 75 23 27 11",
    "sg:postcode":"07370",
    "sg:province":"Rhone-Alpes",
    "wof:name":"Vuitton Atelier Sud Est",
    "wof:placetype":"venue"
},
  "geometry": {"coordinates":[4.808804,45.183243],"type":"Point"}
}