{
  "type": "Feature",
  "properties": {
    "iso:country":"FR",
    "sg:address":"271 Boulevard Pinel 69200 V\u00e9nissieux",
    "sg:classifiers":[
        {
            "category":"Manufacturing",
            "subcategory":"Metals",
            "type":"Manufacturing & Wholesale Goods"
        }
    ],
    "sg:phone":"+33 4 78 76 85 99",
    "sg:postcode":"69200",
    "sg:province":"Rhone-Alpes",
    "sg:tags":[
        "metallurgy",
        "steel",
        "metalworking"
    ],
    "wof:name":"Guitton Sa",
    "wof:placetype":"venue"
},
  "geometry": {"coordinates":[4.887237,45.725254],"type":"Point"}
}