{
  "type": "Feature",
  "properties": {
    "iso:country":"FR",
    "sg:address":"6, All\u00e9e de Coubron, 93390 Clichy sous Bois",
    "sg:orig_category":"Unclassifiable Establishments",
    "sg:phone":"+33 1 43 30 94 40",
    "sg:province":"Ile de France",
    "wof:name":"M.n.s. S.a.r.l.",
    "wof:placetype":"venue"
},
  "geometry": {"coordinates":[2.552256,48.912598],"type":"Point"}
}