{
  "type": "Feature",
  "properties": {
    "addr:full":"6, All\u00e9e de Coubron, 93390 Clichy sous Bois Ile de France",
    "addr:housenumber":"6",
    "addr:postcode":"93390",
    "addr:street":"Alle\u0301E De Coubron;Bois Ile De France",
    "iso:country":"FR",
    "sg:address":"6, All\u00e9e de Coubron, 93390 Clichy sous Bois",
    "sg:orig_category":"Unclassifiable Establishments",
    "sg:phone":"+33 1 43 30 94 40",
    "sg:province":"Ile de France",
    "wof:name":"M.n.s. S.a.r.l.",
    "wof:placetype":"venue"
},
  "geometry": {"coordinates":[2.552256,48.912598],"type":"Point"}
}