{
  "type": "Feature",
  "properties": {
    "iso:country":"FR",
    "sg:address":"22bis, Av. Foch, 94100 Saint Maur des Foss\u00e9s",
    "sg:orig_category":"Non-Classified Establishments",
    "sg:phone":"+33 1 48 85 06 48",
    "sg:postcode":"94100",
    "sg:province":"Ile de France",
    "wof:name":"Eaton Service International S.a.r.l.",
    "wof:placetype":"venue"
},
  "geometry": {"coordinates":[2.487849,48.803638],"type":"Point"}
}