{
  "type": "Feature",
  "properties": {
    "addr:full":"ZI des Saligues 64300 Orthez Orthez Aquitaine 64300",
    "addr:postcode":"64300;64300",
    "addr:street":"Des Saligues",
    "iso:country":"FR",
    "sg:address":"ZI des Saligues 64300 Orthez",
    "sg:city":"Orthez",
    "sg:classifiers":[
        {
            "category":"Shopping",
            "subcategory":"Clothing, Apparel, & Fashions",
            "type":"Retail Goods"
        }
    ],
    "sg:phone":"+33 5 59 69 14 33",
    "sg:postcode":"64300",
    "sg:province":"Aquitaine",
    "sg:tags":[
        "table",
        "linen"
    ],
    "wof:name":"Tissage Moutet S.a.",
    "wof:placetype":"venue"
},
  "geometry": {"coordinates":[-0.773174,43.48735],"type":"Point"}
}