{
  "type": "Feature",
  "properties": {
    "addr:full":"rue des Chantiers 34300 Agde Languedoc-Roussillon 34300",
    "addr:postcode":"34300;34300",
    "addr:street":"Rue Des Chantiers",
    "iso:country":"FR",
    "sg:address":"rue des Chantiers 34300 Agde",
    "sg:classifiers":[
        {
            "category":"Science Facility",
            "type":"Public Place"
        }
    ],
    "sg:phone":"+33 4 67 94 24 19",
    "sg:postcode":"34300",
    "sg:province":"Languedoc-Roussillon",
    "sg:tags":[
        "engineering",
        "naval"
    ],
    "wof:name":"Chantier Naval Allemand H - Euro Marine Sarl",
    "wof:placetype":"venue"
},
  "geometry": {"coordinates":[3.446722,43.289124],"type":"Point"}
}