{
  "type": "Feature",
  "properties": {
    "addr:full":"3, All\u00e9e du Verger, 78114 Magny les Hameaux Ile de France",
    "addr:housenumber":"3",
    "addr:postcode":"78114",
    "addr:street":"Alle\u0301E Du Verger",
    "iso:country":"FR",
    "sg:address":"3, All\u00e9e du Verger, 78114 Magny les Hameaux",
    "sg:orig_category":"Unclassifiable Establishments",
    "sg:phone":"+33 1 30 43 25 48",
    "sg:province":"Ile de France",
    "wof:name":"Quentin S.a.r.l.",
    "wof:placetype":"venue"
},
  "geometry": {"coordinates":[2.03582,48.740047],"type":"Point"}
}