{
  "type": "Feature",
  "properties": {
    "iso:country":"FR",
    "sg:address":"31, Av. Roosevelt, 57800 Freyming Merlebach",
    "sg:orig_category":"Non-Classified Establishments",
    "sg:phone":"+33 3 87 81 16 30",
    "sg:province":"Lorraine",
    "wof:name":"Loralliance S.a.",
    "wof:placetype":"venue"
},
  "geometry": {"coordinates":[6.812485,49.146488],"type":"Point"}
}