{
  "type": "Feature",
  "properties": {
    "iso:country":"FR",
    "sg:address":"20 Rue Vinc\u00e9 35310 Mordelles",
    "sg:city":"Mordelles",
    "sg:classifiers":[
        {
            "category":"Professional",
            "type":"Services"
        }
    ],
    "sg:phone":"+33 2 99 60 57 44",
    "sg:postcode":"35310",
    "sg:province":"Bretagne",
    "sg:tags":[
        "transport",
        "road"
    ],
    "wof:name":"Transports Geffray Sa",
    "wof:placetype":"venue"
},
  "geometry": {"coordinates":[-1.829977,48.081623],"type":"Point"}
}