{
  "type": "Feature",
  "properties": {
    "addr:full":"B.P. 23 Tosse Aquitaine 40230",
    "addr:postcode":"40230",
    "addr:street":"B.P. 23",
    "iso:country":"FR",
    "sg:address":"B.P. 23",
    "sg:city":"Tosse",
    "sg:orig_category":"Non-Classified Establishments",
    "sg:phone":"+33 5 58 49 99 20",
    "sg:postcode":"40230",
    "sg:province":"Aquitaine",
    "wof:name":"Etablissements Bourrasse S.a.",
    "wof:placetype":"venue"
},
  "geometry": {"coordinates":[-1.368627,43.60276],"type":"Point"}
}