{
  "type": "Feature",
  "properties": {
    "addr:full":"171, Av. du Mar\u00e9chal Juin, 24000 P\u00e9rigueux P\u00e9rigueux Aquitaine 24000",
    "addr:postcode":"24000;24000",
    "addr:street":"171 Av. Du Mare\u0301Chal Juin",
    "iso:country":"FR",
    "sg:address":"171, Av. du Mar\u00e9chal Juin, 24000 P\u00e9rigueux",
    "sg:city":"P\u00e9rigueux",
    "sg:orig_category":"Unclassifiable Establishments",
    "sg:phone":"+33 5 53 35 74 50",
    "sg:postcode":"24000",
    "sg:province":"Aquitaine",
    "wof:name":"Crown Cork Compagny France S.a.",
    "wof:placetype":"venue"
},
  "geometry": {"coordinates":[0.703013,45.185802],"type":"Point"}
}