{
  "type": "Feature",
  "properties": {
    "addr:full":"2 Rue Du Marchois 02600 Villers Cotterets Picardie 02600",
    "addr:housenumber":"2",
    "addr:postcode":"02600;02600",
    "addr:street":"Rue Du Marchois",
    "iso:country":"FR",
    "sg:address":"2 Rue Du Marchois 02600 Villers Cotterets",
    "sg:classifiers":[
        {
            "category":"Building & Trades",
            "subcategory":"Construction",
            "type":"Services"
        }
    ],
    "sg:phone":"+33 3 23 96 50 00",
    "sg:postcode":"02600",
    "sg:province":"Picardie",
    "sg:tags":[
        "work",
        "public"
    ],
    "wof:name":"Endel Sa",
    "wof:placetype":"venue"
},
  "geometry": {"coordinates":[3.099894,49.249344],"type":"Point"}
}