{
  "type": "Feature",
  "properties": {
    "addr:full":"19 Rue Marechal Foch 27400 Louviers Haute Normandie 27400",
    "addr:housenumber":"19",
    "addr:postcode":"27400;27400",
    "addr:street":"Rue Marechal Foch;Haute Normandie",
    "iso:country":"FR",
    "sg:address":"19 Rue Marechal Foch 27400 Louviers",
    "sg:orig_category":"Miscellaneous Products",
    "sg:phone":"+33 2 32 25 25 80",
    "sg:postcode":"27400",
    "sg:province":"Haute Normandie",
    "wof:name":"Pompes Funebres Et Marbrerie Luinaud",
    "wof:placetype":"venue"
},
  "geometry": {"coordinates":[1.17037,49.211517],"type":"Point"}
}