{
  "type": "Feature",
  "properties": {
    "addr:full":"406 Bd National 13003 Marseille Poitou-Charentes",
    "addr:housenumber":"406",
    "addr:postcode":"13003",
    "addr:street":"Bd National",
    "iso:country":"FR",
    "sg:address":"406 Bd National 13003 Marseille",
    "sg:classifiers":[
        {
            "category":"Banks & Credit Unions",
            "subcategory":"Investment Brokerage",
            "type":"Services"
        }
    ],
    "sg:phone":"+33 4 91 62 14 57",
    "sg:province":"Poitou-Charentes",
    "sg:tags":[
        "-",
        "transport",
        "related"
    ],
    "wof:name":"Docks Libres Et Magasins Generaux Sa",
    "wof:placetype":"venue"
},
  "geometry": {"coordinates":[5.37217,43.314919],"type":"Point"}
}