{
  "type": "Feature",
  "properties": {
    "addr:full":"9, Rue Gambetta, 62450 Bapaume Nord Pas-de-Calais 62450",
    "addr:housenumber":"9",
    "addr:postcode":"62450;62450",
    "addr:street":"Rue Gambetta",
    "iso:country":"FR",
    "sg:address":"9, Rue Gambetta, 62450 Bapaume",
    "sg:orig_category":"Non-Classified Establishments",
    "sg:phone":"+33 3 21 07 13 30",
    "sg:postcode":"62450",
    "sg:province":"Nord Pas-de-Calais",
    "wof:name":"Defontaine Daniel S.a.r.l.",
    "wof:placetype":"venue"
},
  "geometry": {"coordinates":[2.852375,50.102516],"type":"Point"}
}