{
  "type": "Feature",
  "properties": {
    "addr:full":"ZA des Jeunes Grands Ch\u00eanes Wallers Nord Pas-de-Calais 59135",
    "addr:housenumber":"grands",
    "addr:postcode":"59135",
    "addr:street":"Za Des Jeunes;Wallers;Pas-De-Calais",
    "iso:country":"FR",
    "sg:address":"ZA des Jeunes Grands Ch\u00eanes",
    "sg:city":"Wallers",
    "sg:orig_category":"Unclassifiable Establishments",
    "sg:phone":"+33 3 27 35 64 73",
    "sg:postcode":"59135",
    "sg:province":"Nord Pas-de-Calais",
    "wof:name":"M\u00e9tralu",
    "wof:placetype":"venue"
},
  "geometry": {"coordinates":[3.39254,50.373344],"type":"Point"}
}