{
  "type": "Feature",
  "properties": {
    "iso:country":"FR",
    "sg:address":"70, Rue Isabey, 54000 Nancy",
    "sg:orig_category":"Non-Classified Establishments",
    "sg:phone":"+33 3 83 98 42 81",
    "sg:postcode":"54000",
    "sg:province":"Lorraine",
    "wof:name":"Atelier Jacques F\u00e8ve",
    "wof:placetype":"venue"
},
  "geometry": {"coordinates":[6.169453,48.697502],"type":"Point"}
}