{
  "type": "Feature",
  "properties": {
    "iso:country":"FR",
    "sg:address":"Quartier Saint Martin",
    "sg:city":"Trets",
    "sg:orig_category":"Unclassifiable Establishments",
    "sg:phone":"+33 4 42 61 45 74",
    "sg:postcode":"13530",
    "sg:province":"Basse Normandie",
    "wof:name":"C.m.s.e. S.a.r.l. - Construction M\u00e9tallique Du Sud-est",
    "wof:placetype":"venue"
},
  "geometry": {"coordinates":[5.66723,43.450203],"type":"Point"}
}