{
  "type": "Feature",
  "properties": {
    "addr:full":"60, Rte de la Paoute - Le Plan de Grasse, 06130 Grasse Rhone-Alpes",
    "addr:housenumber":"60",
    "addr:postcode":"06130",
    "addr:street":"Rte De La Paoute;Plan De Grasse",
    "iso:country":"FR",
    "sg:address":"60, Rte de la Paoute - Le Plan de Grasse, 06130 Grasse",
    "sg:orig_category":"Unclassifiable Establishments",
    "sg:phone":"+33 4 93 40 56 66",
    "sg:province":"Rhone-Alpes",
    "wof:name":"Admos S.a.",
    "wof:placetype":"venue"
},
  "geometry": {"coordinates":[6.931648,43.649738],"type":"Point"}
}