{
  "type": "Feature",
  "properties": {
    "iso:country":"FR",
    "sg:address":"Zone D'Activit\u00e9 Atlantheix 56450 Theix",
    "sg:city":"Theix",
    "sg:classifiers":[
        {
            "category":"Home & Garden",
            "subcategory":"Furniture",
            "type":"Retail Goods"
        }
    ],
    "sg:phone":"+33 2 97 42 62 55",
    "sg:postcode":"56450",
    "sg:province":"Bretagne",
    "sg:tags":[
        "household",
        "wood"
    ],
    "wof:name":"Comptoir Des Lustres Sa",
    "wof:placetype":"venue"
},
  "geometry": {"coordinates":[-2.65018,47.629311],"type":"Point"}
}