{
  "type": "Feature",
  "properties": {
    "addr:full":"8 rue des Fleurs 69100 Villeurbanne Rhone-Alpes 69100",
    "addr:housenumber":"8",
    "addr:postcode":"69100;69100",
    "addr:street":"Rue Des Fleurs",
    "iso:country":"FR",
    "sg:address":"8 rue des Fleurs 69100 Villeurbanne",
    "sg:classifiers":[
        {
            "category":"Banks & Credit Unions",
            "subcategory":"Investment Brokerage",
            "type":"Services"
        }
    ],
    "sg:phone":"+33 4 72 11 39 90",
    "sg:postcode":"69100",
    "sg:province":"Rhone-Alpes",
    "sg:tags":[
        "development",
        "electronics"
    ],
    "wof:name":"L'ebenoid S.a.",
    "wof:placetype":"venue"
},
  "geometry": {"coordinates":[4.895329,45.75528],"type":"Point"}
}