{
  "type": "Feature",
  "properties": {
    "iso:country":"FR",
    "sg:address":"3 rue du Te 93290 Tremblay en France",
    "sg:classifiers":[
        {
            "category":"Professional",
            "type":"Services"
        }
    ],
    "sg:phone":"+33 1 49 19 53 40",
    "sg:province":"Ile de France",
    "sg:tags":[
        "transport"
    ],
    "wof:name":"Partnair Freight International Sa",
    "wof:placetype":"venue"
},
  "geometry": {"coordinates":[2.524889,48.991737],"type":"Point"}
}