{
  "type": "Feature",
  "properties": {
    "iso:country":"FR",
    "sg:address":"17 Avenue Des Catelines 69720 St Laurent De Mure",
    "sg:orig_category":"Miscellaneous Products",
    "sg:phone":"+33 4 72 48 37 60",
    "sg:postcode":"69720",
    "sg:province":"Rhone-Alpes",
    "wof:name":"Societe Francaise D'exploitation Des Plastiques (sfep)",
    "wof:placetype":"venue"
},
  "geometry": {"coordinates":[5.049213,45.690567],"type":"Point"}
}