{
  "type": "Feature",
  "properties": {
    "addr:full":"Av. Edouard Michelin Vannes Bretagne 56000",
    "addr:postcode":"56000",
    "addr:street":"Av. Edouard Michelin;Bretagne",
    "iso:country":"FR",
    "sg:address":"Av. Edouard Michelin",
    "sg:city":"Vannes",
    "sg:orig_category":"Unclassifiable Establishments",
    "sg:phone":"+33 2 97 01 87 00",
    "sg:postcode":"56000",
    "sg:province":"Bretagne",
    "wof:name":"Manufacture Fran\u00e7aise Des Pneumatiques Michelin S.c.a.",
    "wof:placetype":"venue"
},
  "geometry": {"coordinates":[-2.711284,47.659466],"type":"Point"}
}