{
  "type": "Feature",
  "properties": {
    "addr:full":"rue Denis Papin 72230 Ruaudin Pays de Loire 72230",
    "addr:postcode":"72230;72230",
    "addr:street":"Rue Denis Papin",
    "iso:country":"FR",
    "sg:address":"rue Denis Papin 72230 Ruaudin",
    "sg:classifiers":[
        {
            "category":"Wholesale",
            "subcategory":"Construction Materials",
            "type":"Manufacturing & Wholesale Goods"
        }
    ],
    "sg:phone":"+33 2 43 40 53 53",
    "sg:postcode":"72230",
    "sg:province":"Pays de Loire",
    "sg:tags":[
        "mould",
        "injection"
    ],
    "wof:name":"Destremo S.a.",
    "wof:placetype":"venue"
},
  "geometry": {"coordinates":[0.257308,47.939137],"type":"Point"}
}