{
  "type": "Feature",
  "properties": {
    "iso:country":"FR",
    "sg:address":"27 Rue De La R\u00e9publique 29780 Plouhinec",
    "sg:city":"Plouhinec",
    "sg:classifiers":[
        {
            "category":"Professional",
            "subcategory":"Business Services",
            "type":"Services"
        }
    ],
    "sg:phone":"+33 2 98 70 77 12",
    "sg:postcode":"29780",
    "sg:province":"Bretagne",
    "sg:tags":[
        "training",
        "advice"
    ],
    "wof:name":"Lycee Professionnel Jean Moulin",
    "wof:placetype":"venue"
},
  "geometry": {"coordinates":[-4.528605,48.019997],"type":"Point"}
}