{
  "type": "Feature",
  "properties": {
    "addr:full":"Rte Principale Baissey Champagne 52250",
    "addr:postcode":"52250",
    "addr:street":"Rte Principale;Champagne",
    "iso:country":"FR",
    "sg:address":"Rte Principale",
    "sg:city":"Baissey",
    "sg:orig_category":"Unclassifiable Establishments",
    "sg:phone":"+33 3 25 88 01 29",
    "sg:postcode":"52250",
    "sg:province":"Champagne",
    "wof:name":"Etablissements Pinto - Tous Travaux Du B\u00e2timent",
    "wof:placetype":"venue"
},
  "geometry": {"coordinates":[5.309909,47.767506],"type":"Point"}
}