{
  "type": "Feature",
  "properties": {
    "iso:country":"FR",
    "sg:address":"1198 Av. Du Docteur Moritz Donat 06254 Mougins Cedex",
    "sg:orig_category":"Chemicals and Pharmaceuticals Glass Health - equipments and instruments Optical equipments and instr",
    "sg:phone":"+33 4 92 92 44 00",
    "sg:province":"Nord Pas-de-Calais",
    "wof:name":"Allergan France Sa",
    "wof:placetype":"venue"
},
  "geometry": {"coordinates":[6.99596,43.599918],"type":"Point"}
}