{
  "type": "Feature",
  "properties": {
    "iso:country":"FR",
    "sg:address":"Ch\u00e2teau Lavallade - Haut Lavallade",
    "sg:city":"Saint Christophe des Bardes",
    "sg:orig_category":"Unclassifiable Establishments",
    "sg:phone":"+33 5 57 24 77 47",
    "sg:postcode":"33330",
    "sg:province":"Aquitaine",
    "wof:name":"Chagneau J.p.m.d. S.a.r.l.",
    "wof:placetype":"venue"
},
  "geometry": {"coordinates":[-0.12328,44.896118],"type":"Point"}
}