{
  "type": "Feature",
  "properties": {
    "addr:full":"Rte Taulignan BP 32 Cedex 84601 Valr\u00e9as Taulignan Rhone-Alpes 26770",
    "addr:housenumber":"32",
    "addr:postcode":"cedex 84601;26770",
    "addr:street":"Rte Taulignan Bp;Rhone-Alpes",
    "iso:country":"FR",
    "sg:address":"Rte Taulignan BP 32 Cedex 84601 Valr\u00e9as",
    "sg:city":"Taulignan",
    "sg:classifiers":[
        {
            "category":"Food Court",
            "type":"Food & Drink"
        }
    ],
    "sg:phone":"+33 4 90 35 17 96",
    "sg:postcode":"26770",
    "sg:province":"Rhone-Alpes",
    "sg:tags":[
        "product",
        "related"
    ],
    "wof:name":"Enclave Vinotheque",
    "wof:placetype":"venue"
},
  "geometry": {"coordinates":[4.987676,44.383446],"type":"Point"}
}