{
  "type": "Feature",
  "properties": {
    "addr:full":"6 rue Louis Armand 77330 Ozoir La Ferri\u00e8re Ile de France 77330",
    "addr:housenumber":"6",
    "addr:postcode":"77330;77330",
    "addr:street":"Rue Louis Armand",
    "iso:country":"FR",
    "sg:address":"6 rue Louis Armand 77330 Ozoir La Ferri\u00e8re",
    "sg:classifiers":[
        {
            "category":"Shopping",
            "subcategory":"Beauty & Cosmetics",
            "type":"Retail Goods"
        }
    ],
    "sg:phone":"+33 1 64 43 66 66",
    "sg:postcode":"77330",
    "sg:province":"Ile de France",
    "sg:tags":[
        "eyelash"
    ],
    "wof:name":"Laboratoires Wilson Sarl",
    "wof:placetype":"venue"
},
  "geometry": {"coordinates":[2.688188,48.766579],"type":"Point"}
}