{
  "type": "Feature",
  "properties": {
    "addr:full":"67, Av Jean Mermoz, 89000 Auxerre Auxerre Bourgogne 89000",
    "addr:postcode":"89000;89000",
    "addr:street":"67 Av Jean Mermoz",
    "iso:country":"FR",
    "sg:address":"67, Av Jean Mermoz, 89000 Auxerre",
    "sg:city":"Auxerre",
    "sg:orig_category":"Unclassifiable Establishments",
    "sg:phone":"+33 3 86 46 90 73",
    "sg:postcode":"89000",
    "sg:province":"Bourgogne",
    "wof:name":"Congy Marc S.a.",
    "wof:placetype":"venue"
},
  "geometry": {"coordinates":[3.584419,47.818996],"type":"Point"}
}