{
  "type": "Feature",
  "properties": {
    "iso:country":"FR",
    "sg:address":"Route De Gommeville 10250 Mussy Sur Seine",
    "sg:classifiers":[
        {
            "category":"Home & Garden",
            "subcategory":"Furniture",
            "type":"Retail Goods"
        }
    ],
    "sg:phone":"+33 3 25 38 44 22",
    "sg:province":"Champagne",
    "sg:tags":[
        "wood"
    ],
    "wof:name":"Ggf Mussy",
    "wof:placetype":"venue"
},
  "geometry": {"coordinates":[4.49762,47.977242],"type":"Point"}
}