{
  "type": "Feature",
  "properties": {
    "iso:country":"FR",
    "sg:address":"13 Zac De L'Aigue 69780 St Pierre De Chandieu",
    "sg:classifiers":[
        {
            "category":"Manufacturing",
            "subcategory":"Chemicals & Compounds",
            "type":"Manufacturing & Wholesale Goods"
        }
    ],
    "sg:phone":"+33 4 72 22 01 24",
    "sg:postcode":"69780",
    "sg:province":"Rhone-Alpes",
    "sg:tags":[
        "pharmaceutical",
        "chemistry",
        "-",
        "by-product"
    ],
    "wof:name":"Rhone Peintures Industrie",
    "wof:placetype":"venue"
},
  "geometry": {"coordinates":[5.0234,45.646759],"type":"Point"}
}