{
  "type": "Feature",
  "properties": {
    "addr:full":"124 Rue De Rennes 75006 Paris Ile de France 75006",
    "addr:housenumber":"124",
    "addr:postcode":"75006;75006",
    "addr:street":"Rue De Rennes",
    "iso:country":"FR",
    "sg:address":"124 Rue De Rennes 75006 Paris",
    "sg:classifiers":[
        {
            "category":"Travel",
            "subcategory":"Hotels & Motels",
            "type":"Entertainment"
        }
    ],
    "sg:phone":"+33 1 45 48 03 75",
    "sg:postcode":"75006",
    "sg:province":"Ile de France",
    "sg:tags":[
        "hotels",
        "business",
        "restaurant"
    ],
    "wof:name":"H\u00d4tel Aramis Sa",
    "wof:placetype":"venue"
},
  "geometry": {"coordinates":[2.326398,48.846779],"type":"Point"}
}