{
  "type": "Feature",
  "properties": {
    "addr:full":"B.P. 156, 68304 Saint Louis C\u00e9dex^^14, Rue du Ballon, 68300 Saint Louis Saint-Louis Alsace 68300",
    "addr:housenumber":"b.p. 156",
    "addr:postcode":"68304;68300;68300",
    "addr:street":"Rue Du Ballon",
    "iso:country":"FR",
    "sg:address":"B.P. 156, 68304 Saint Louis C\u00e9dex^^14, Rue du Ballon, 68300 Saint Louis",
    "sg:city":"Saint-Louis",
    "sg:orig_category":"Non-Classified Establishments",
    "sg:phone":"+33 3 89 69 73 65",
    "sg:postcode":"68300",
    "sg:province":"Alsace",
    "wof:name":"M\u00e9tro Cars S.a.",
    "wof:placetype":"venue"
},
  "geometry": {"coordinates":[7.558883,47.585861],"type":"Point"}
}