{
  "type": "Feature",
  "properties": {
    "addr:full":"B.P. 19, 51005 Ch\u00e2lons en Champagne C\u00e9dex^^2, Rue Michel M\u00e9nard, 51000 Ch\u00e2lons en Champagne Champagne",
    "addr:postcode":"51005;51000",
    "addr:street":"B.P. 19;Rue Michel Me\u0301Nard",
    "iso:country":"FR",
    "sg:address":"B.P. 19, 51005 Ch\u00e2lons en Champagne C\u00e9dex^^2, Rue Michel M\u00e9nard, 51000 Ch\u00e2lons en Champagne",
    "sg:orig_category":"Non-Classified Establishments",
    "sg:phone":"+33 3 26 65 40 40",
    "sg:province":"Champagne",
    "wof:name":"Soci\u00e9t\u00e9 Nouvelle Conraux S.a.r.l.",
    "wof:placetype":"venue"
},
  "geometry": {"coordinates":[4.355399,48.955708],"type":"Point"}
}