{
  "type": "Feature",
  "properties": {
    "iso:country":"FR",
    "sg:address":"Rte des Vaux - ZA",
    "sg:city":"Jou\u00e9 l\u00e8s Tours",
    "sg:orig_category":"Non-Classified Establishments",
    "sg:phone":"+33 2 47 80 02 11",
    "sg:postcode":"37300",
    "sg:province":"Centre",
    "wof:name":"T.r.b. S.a.r.l.",
    "wof:placetype":"venue"
},
  "geometry": {"coordinates":[0.662555,47.350945],"type":"Point"}
}