{
  "type": "Feature",
  "properties": {
    "iso:country":"FR",
    "sg:address":"90 rue de la Haie Coq 93300 Aubervilliers",
    "sg:classifiers":[
        {
            "category":"Shopping",
            "subcategory":"Department Store",
            "type":"Retail Goods"
        }
    ],
    "sg:phone":"+33 1 48 39 05 05",
    "sg:postcode":"93300",
    "sg:province":"Ile de France",
    "sg:tags":[
        "linen",
        "bed"
    ],
    "wof:name":"Fm Diffusion Sarl",
    "wof:placetype":"venue"
},
  "geometry": {"coordinates":[2.372096,48.90419],"type":"Point"}
}