{
  "type": "Feature",
  "properties": {
    "iso:country":"FR",
    "sg:address":"3, Rue Jacques Coeur, 75004 Paris",
    "sg:orig_category":"Non-Classified Establishments",
    "sg:phone":"+33 1 44 78 60 30",
    "sg:postcode":"75004",
    "sg:province":"Ile de France",
    "wof:name":"Agence Meesters S.a.r.l.",
    "wof:placetype":"venue"
},
  "geometry": {"coordinates":[2.366994,48.85223],"type":"Point"}
}