{
  "type": "Feature",
  "properties": {
    "addr:full":"B.P. 4129, 06303 Nice C\u00e9dex 4^^17, Rue Guiglionda de Sainte Agathe, 06300 Nice Picardie",
    "addr:housenumber":"4 ^ ^ 17",
    "addr:postcode":"06303;06300",
    "addr:street":"B.P. 4129;Ce\u0301Dex;Rue Guiglionda De Sainte Agathe",
    "iso:country":"FR",
    "sg:address":"B.P. 4129, 06303 Nice C\u00e9dex 4^^17, Rue Guiglionda de Sainte Agathe, 06300 Nice",
    "sg:orig_category":"Non-Classified Establishments",
    "sg:phone":"+33 4 93 27 77 00",
    "sg:province":"Picardie",
    "wof:name":"Kon\u00e9 S.a.",
    "wof:placetype":"venue"
},
  "geometry": {"coordinates":[7.291057,43.709461],"type":"Point"}
}