{
  "type": "Feature",
  "properties": {
    "addr:full":"13, Rte d'Ungershaim - Zone Industrielle, 68190 Ensisheim Ensisheim Alsace 68190",
    "addr:housenumber":"13",
    "addr:postcode":"68190;68190",
    "addr:street":"Rte D'Ungershaim Zone Industrielle",
    "iso:country":"FR",
    "sg:address":"13, Rte d'Ungershaim - Zone Industrielle, 68190 Ensisheim",
    "sg:city":"Ensisheim",
    "sg:orig_category":"Unclassifiable Establishments",
    "sg:phone":"+33 3 89 81 01 41",
    "sg:postcode":"68190",
    "sg:province":"Alsace",
    "wof:name":"Kaiser S.a.",
    "wof:placetype":"venue"
},
  "geometry": {"coordinates":[7.35432,47.865219],"type":"Point"}
}