{
  "type": "Feature",
  "properties": {
    "addr:full":"Port De Richemont 57300 Mondelange Lorraine 57300",
    "addr:postcode":"57300;57300",
    "addr:street":"Port De Richemont",
    "iso:country":"FR",
    "sg:address":"Port De Richemont 57300 Mondelange",
    "sg:classifiers":[
        {
            "category":"Wholesale",
            "subcategory":"Machinery & Supplies",
            "type":"Manufacturing & Wholesale Goods"
        }
    ],
    "sg:phone":"+33 3 87 72 10 36",
    "sg:postcode":"57300",
    "sg:province":"Lorraine",
    "sg:tags":[
        "handling",
        "material",
        "-",
        "machine",
        "equipment",
        "engineering",
        "mechanical"
    ],
    "wof:name":"Ccl Societe En Nom Collectif",
    "wof:placetype":"venue"
},
  "geometry": {"coordinates":[6.176587,49.264099],"type":"Point"}
}