{
  "type": "Feature",
  "properties": {
    "addr:full":"14 Rue Laforest 92240 Malakoff Ile de France 92240",
    "addr:housenumber":"14",
    "addr:postcode":"92240;ile;92240",
    "addr:street":"Rue Laforest;France",
    "iso:country":"FR",
    "sg:address":"14 Rue Laforest 92240 Malakoff",
    "sg:classifiers":[
        {
            "category":"Travel",
            "subcategory":"Hotels & Motels",
            "type":"Entertainment"
        }
    ],
    "sg:phone":"+33 1 42 53 16 16",
    "sg:postcode":"92240",
    "sg:province":"Ile de France",
    "sg:tags":[
        "hotels",
        "business",
        "restaurant"
    ],
    "wof:name":"France Hotel Du Parc",
    "wof:placetype":"venue"
},
  "geometry": {"coordinates":[2.301572,48.822777],"type":"Point"}
}