{
  "type": "Feature",
  "properties": {
    "addr:full":"24, Rue Jean Jacques Rousseau, 76600 Le Havre Haute Normandie 76600",
    "addr:housenumber":"24",
    "addr:postcode":"76600;76600",
    "addr:street":"Rue Jean Jacques Rousseau",
    "iso:country":"FR",
    "sg:address":"24, Rue Jean Jacques Rousseau, 76600 Le Havre",
    "sg:orig_category":"Non-Classified Establishments",
    "sg:phone":"+33 2 32 72 70 70",
    "sg:postcode":"76600",
    "sg:province":"Haute Normandie",
    "wof:name":"Axymeca S.a.s.",
    "wof:placetype":"venue"
},
  "geometry": {"coordinates":[0.13174,49.496151],"type":"Point"}
}