{
  "type": "Feature",
  "properties": {
    "iso:country":"FR",
    "sg:address":"Rte de Janville",
    "sg:city":"Auneau",
    "sg:orig_category":"Unclassifiable Establishments",
    "sg:phone":"+33 2 37 91 23 59",
    "sg:postcode":"28700",
    "sg:province":"Centre",
    "wof:name":"Richard Le Droff S.a.",
    "wof:placetype":"venue"
},
  "geometry": {"coordinates":[1.910886,48.354084],"type":"Point"}
}