{
  "type": "Feature",
  "properties": {
    "iso:country":"FR",
    "sg:address":"57 Av De Tavaux 21800 Chevigny St Sauveur",
    "sg:city":"Neuilly-l\u00e8s-Dijon",
    "sg:classifiers":[
        {
            "category":"Manufacturing",
            "subcategory":"Rubber & Plastics",
            "type":"Manufacturing & Wholesale Goods"
        }
    ],
    "sg:phone":"+33 3 80 46 73 00",
    "sg:postcode":"21800",
    "sg:province":"Bourgogne",
    "wof:name":"Soplachim",
    "wof:placetype":"venue"
},
  "geometry": {"coordinates":[5.134167,47.28767],"type":"Point"}
}