{
  "type": "Feature",
  "properties": {
    "addr:full":"Cleherlan 56230 Questembert Questembert Bretagne 56230",
    "addr:postcode":"56230;56230",
    "addr:street":"Cleherlan",
    "iso:country":"FR",
    "sg:address":"Cleherlan 56230 Questembert",
    "sg:city":"Questembert",
    "sg:orig_category":"Non-Classified Establishments",
    "sg:phone":"+33 2 97 43 71 00",
    "sg:postcode":"56230",
    "sg:province":"Bretagne",
    "wof:name":"Guyomarch Bretagne S.a.",
    "wof:placetype":"venue"
},
  "geometry": {"coordinates":[-2.461974,47.680656],"type":"Point"}
}