{
  "type": "Feature",
  "properties": {
    "iso:country":"FR",
    "sg:address":"ZI de Saint Lambert des Lev\u00e9es",
    "sg:city":"Saumur",
    "sg:orig_category":"Unclassifiable Establishments",
    "sg:phone":"+33 2 41 40 41 40",
    "sg:postcode":"49400",
    "sg:province":"Pays de Loire",
    "wof:name":"Castel S.a.",
    "wof:placetype":"venue"
},
  "geometry": {"coordinates":[-0.079319,47.259766],"type":"Point"}
}