{
  "type": "Feature",
  "properties": {
    "addr:full":"Zi 40220 Tarnos Tarnos Aquitaine 40220",
    "addr:postcode":"40220;40220",
    "addr:street":"Zi",
    "iso:country":"FR",
    "sg:address":"Zi 40220 Tarnos",
    "sg:city":"Tarnos",
    "sg:classifiers":[
        {
            "category":"Building & Trades",
            "subcategory":"Construction",
            "type":"Services"
        }
    ],
    "sg:phone":"+33 5 59 64 62 64",
    "sg:postcode":"40220",
    "sg:province":"Aquitaine",
    "sg:tags":[
        "work",
        "public"
    ],
    "wof:name":"Jean Hiriart",
    "wof:placetype":"venue"
},
  "geometry": {"coordinates":[-1.501113,43.54092],"type":"Point"}
}