{
  "type": "Feature",
  "properties": {
    "addr:full":"Rue Claude Nicolas Ledoux Aix en Provence Nord Pas-de-Calais 13790",
    "addr:postcode":"13790",
    "addr:street":"Rue Claude Nicolas Ledoux Aix;Pas-De-Calais",
    "iso:country":"FR",
    "sg:address":"Rue Claude Nicolas Ledoux",
    "sg:city":"Aix en Provence",
    "sg:orig_category":"Unclassifiable Establishments",
    "sg:phone":"+33 4 42 25 15 15",
    "sg:postcode":"13790",
    "sg:province":"Nord Pas-de-Calais",
    "wof:name":"Exp\u00e9rian S.a.",
    "wof:placetype":"venue"
},
  "geometry": {"coordinates":[5.402223,43.47123],"type":"Point"}
}