{
  "type": "Feature",
  "properties": {
    "iso:country":"FR",
    "sg:address":"45, Rue Pothier, 28200 Lutz en Dunois",
    "sg:city":"Ch\u00e2teaudun",
    "sg:orig_category":"Unclassifiable Establishments",
    "sg:phone":"+33 2 37 45 05 11",
    "sg:postcode":"28200",
    "sg:province":"Centre",
    "wof:name":"Paysages Crespin S.a.r.l.",
    "wof:placetype":"venue"
},
  "geometry": {"coordinates":[1.41175,48.059532],"type":"Point"}
}