{
  "type": "Feature",
  "properties": {
    "iso:country":"FR",
    "sg:address":"45 Boulevard Du 14 Juillet",
    "sg:city":"Troyes",
    "sg:classifiers":[
        {
            "category":"Banks & Credit Unions",
            "subcategory":"Financial Services",
            "type":"Services"
        }
    ],
    "sg:phone":"+33 3 25 73 71 46",
    "sg:postcode":"10000",
    "sg:province":"Champagne",
    "sg:tags":[
        "banking",
        "finance",
        "insurance"
    ],
    "wof:name":"Thieblemont Brigitte",
    "wof:placetype":"venue"
},
  "geometry": {"coordinates":[4.07654,48.293293],"type":"Point"}
}