{
  "type": "Feature",
  "properties": {
    "addr:full":"69220 Lanci\u00e9 Rhone-Alpes",
    "addr:postcode":"69220",
    "iso:country":"FR",
    "sg:address":"69220 Lanci\u00e9",
    "sg:orig_category":"Non-Classified Establishments",
    "sg:phone":"+33 4 74 04 18 00",
    "sg:province":"Rhone-Alpes",
    "wof:name":"Sapin Et Brousseloux S.a.",
    "wof:placetype":"venue"
},
  "geometry": {"coordinates":[4.716185,46.170845],"type":"Point"}
}