{
  "type": "Feature",
  "properties": {
    "iso:country":"FR",
    "sg:address":"16",
    "sg:city":"Gustave FLAUBERT-CROISSET 76380 Canteleu",
    "sg:classifiers":[
        {
            "category":"Professional",
            "subcategory":"Engineering",
            "type":"Services"
        }
    ],
    "sg:phone":"+33 2 35 36 06 90",
    "sg:postcode":"76380",
    "sg:province":"Haute Normandie",
    "sg:tags":[
        "machine",
        "-",
        "mechanical"
    ],
    "wof:name":"Lemire (sarl)",
    "wof:placetype":"venue"
},
  "geometry": {"coordinates":[1.0343,49.436859],"type":"Point"}
}