{
  "type": "Feature",
  "properties": {
    "addr:full":"33 Av Du Pont De Tasset 74960 Meythet Rhone-Alpes 74960",
    "addr:postcode":"74960;74960",
    "addr:street":"33 Av Du Pont De Tasset",
    "iso:country":"FR",
    "sg:address":"33 Av Du Pont De Tasset 74960 Meythet",
    "sg:classifiers":[
        {
            "category":"Shopping",
            "type":"Retail Goods"
        }
    ],
    "sg:phone":"+33 4 50 57 00 45",
    "sg:postcode":"74960",
    "sg:province":"Rhone-Alpes",
    "sg:tags":[
        "metallurgy",
        "finished",
        "-",
        "metalworking",
        "metallic"
    ],
    "wof:name":"Zama (ste Nouvelle) Sa",
    "wof:placetype":"venue"
},
  "geometry": {"coordinates":[6.102276,45.915157],"type":"Point"}
}