{
  "type": "Feature",
  "properties": {
    "addr:full":"33330 Saint Emilion Saint-\u00c9tienne-de-Lisse Aquitaine 33330",
    "addr:postcode":"33330;33330",
    "addr:street":"Saint",
    "iso:country":"FR",
    "sg:address":"33330 Saint Emilion",
    "sg:city":"Saint-\u00c9tienne-de-Lisse",
    "sg:orig_category":"Non-Classified Establishments",
    "sg:phone":"+33 5 57 51 49 36",
    "sg:postcode":"33330",
    "sg:province":"Aquitaine",
    "wof:name":"Ch\u00e2teau Jean Faur\u00e9 S.a.r.l.",
    "wof:placetype":"venue"
},
  "geometry": {"coordinates":[-0.155229,44.894924],"type":"Point"}
}