{
  "type": "Feature",
  "properties": {
    "iso:country":"FR",
    "sg:address":"6",
    "sg:city":"Forum; Arles",
    "sg:classifiers":[
        {
            "category":"Banks & Credit Unions",
            "subcategory":"Bank",
            "type":"Services"
        }
    ],
    "sg:phone":"+33 3390936355",
    "sg:province":"Pays de Loire",
    "wof:name":"Lyonnaise De Banque",
    "wof:placetype":"venue"
},
  "geometry": {"coordinates":[-84.19813499999999,32.118336],"type":"Point"}
}