{
  "type": "Feature",
  "properties": {
    "addr:full":"68 rue Neuve d'Argenson; Bergerac; 24100 Bergerac Aquitaine 24100",
    "addr:housenumber":"68",
    "addr:postcode":"24100;24100",
    "addr:street":"Rue Neuve D'Argenson",
    "iso:country":"FR",
    "sg:address":"68 rue Neuve d'Argenson; Bergerac; 24100",
    "sg:city":"Bergerac",
    "sg:classifiers":[
        {
            "category":"Banks & Credit Unions",
            "subcategory":"Bank",
            "type":"Services"
        }
    ],
    "sg:phone":"+33 3353574233",
    "sg:postcode":"24100",
    "sg:province":"Aquitaine",
    "wof:name":"Banque Nationale De Paris",
    "wof:placetype":"venue"
},
  "geometry": {"coordinates":[0.485061,44.851009],"type":"Point"}
}