{
  "type": "Feature",
  "properties": {
    "iso:country":"FR",
    "sg:address":"402, Rue Jean-Baptiste Biot, 66000 Perpignan",
    "sg:orig_category":"Unclassifiable Establishments",
    "sg:phone":"+33 4 68 61 18 72",
    "sg:province":"Languedoc-Roussillon",
    "wof:name":"Editions Du Castillet S.a.r.l.",
    "wof:placetype":"venue"
},
  "geometry": {"coordinates":[2.895332,42.736042],"type":"Point"}
}