{
  "type": "Feature",
  "properties": {
    "addr:full":"63 rue du Breuil; La Mure d'Is\u00e8re; 38350 Rhone-Alpes 38350",
    "addr:housenumber":"63",
    "addr:postcode":"38350;38350",
    "addr:street":"Rue Du Breuil;D'Ise \u0300Re",
    "iso:country":"FR",
    "sg:address":"63 rue du Breuil; La Mure d'Is\u00e8re; 38350",
    "sg:classifiers":[
        {
            "category":"Banks & Credit Unions",
            "subcategory":"Bank",
            "type":"Services"
        }
    ],
    "sg:phone":"+33 3376810178",
    "sg:postcode":"38350",
    "sg:province":"Rhone-Alpes",
    "wof:name":"Banque Nationale De Paris",
    "wof:placetype":"venue"
},
  "geometry": {"coordinates":[5.786397,44.906792],"type":"Point"}
}