{
  "type": "Feature",
  "properties": {
    "iso:country":"FR",
    "sg:address":"19 lotissement le Sous-Bois 13170 Les Pennes Mirabeau",
    "sg:classifiers":[
        {
            "category":"Manufacturing",
            "subcategory":"Printing",
            "type":"Manufacturing & Wholesale Goods"
        }
    ],
    "sg:phone":"+33 4 91 51 68 17",
    "sg:province":"Poitou-Charentes",
    "sg:tags":[
        "house",
        "book"
    ],
    "wof:name":"Bonisud S.a.r.l.",
    "wof:placetype":"venue"
},
  "geometry": {"coordinates":[5.341098,43.385506],"type":"Point"}
}