{
  "type": "Feature",
  "properties": {
    "addr:full":"250 Rue Jean Baptiste Martenot 56850 Caudan Caudan Bretagne 56850",
    "addr:housenumber":"250",
    "addr:postcode":"56850;56850",
    "addr:street":"Rue Jean Baptiste Martenot;Caudan",
    "iso:country":"FR",
    "sg:address":"250 Rue Jean Baptiste Martenot 56850 Caudan",
    "sg:city":"Caudan",
    "sg:classifiers":[
        {
            "category":"Professional",
            "subcategory":"Advertising",
            "type":"Services"
        }
    ],
    "sg:phone":"+33 2 97 81 05 55",
    "sg:postcode":"56850",
    "sg:province":"Bretagne",
    "sg:tags":[
        "communication",
        "printing",
        "medium",
        "publishing"
    ],
    "wof:name":"Dauphin Affichage",
    "wof:placetype":"venue"
},
  "geometry": {"coordinates":[-3.341144,47.785999],"type":"Point"}
}