{
  "type": "Feature",
  "properties": {
    "iso:country":"FR",
    "sg:address":"Champloup 01400 Neuville les Dames",
    "sg:orig_category":"Non-Classified Establishments",
    "sg:phone":"+33 4 74 55 61 68",
    "sg:postcode":"01400",
    "sg:province":"Rhone-Alpes",
    "wof:name":"Cinier G\u00e9rard S.a.r.l.",
    "wof:placetype":"venue"
},
  "geometry": {"coordinates":[4.999505,46.178638],"type":"Point"}
}