{
  "type": "Feature",
  "properties": {
    "iso:country":"FR",
    "sg:address":"1191, Chemin du Mas de Sorbier - Rte de Beaucaire - ZI de Gr\u00e9zan, 30000 N\u00eemes",
    "sg:orig_category":"Unclassifiable Establishments",
    "sg:phone":"+33 4 66 02 77 00",
    "sg:province":"Languedoc-Roussillon",
    "wof:name":"Logidis S.a.s.",
    "wof:placetype":"venue"
},
  "geometry": {"coordinates":[4.36035,43.86256],"type":"Point"}
}