{
  "type": "Feature",
  "properties": {
    "addr:full":"31, Av. des Charentes, 94150 Rungis Ile de France",
    "addr:postcode":"94150",
    "addr:street":"31 Av. Des Charentes",
    "iso:country":"FR",
    "sg:address":"31, Av. des Charentes, 94150 Rungis",
    "sg:orig_category":"Non-Classified Establishments",
    "sg:phone":"+33 1 45 60 71 20",
    "sg:province":"Ile de France",
    "wof:name":"I.p. Viandes S.a.",
    "wof:placetype":"venue"
},
  "geometry": {"coordinates":[2.35999,48.758671],"type":"Point"}
}