{
  "type": "Feature",
  "properties": {
    "addr:full":"Rue Menez Caon Telgruc sur Mer Bretagne 29560",
    "addr:postcode":"29560",
    "addr:street":"Rue Menez Caon Telgruc;Mer Bretagne",
    "iso:country":"FR",
    "sg:address":"Rue Menez Caon",
    "sg:city":"Telgruc sur Mer",
    "sg:orig_category":"Unclassifiable Establishments",
    "sg:phone":"+33 2 98 44 66 02",
    "sg:postcode":"29560",
    "sg:province":"Bretagne",
    "wof:name":"Editions Fitamant S.n.c.",
    "wof:placetype":"venue"
},
  "geometry": {"coordinates":[-4.374297,48.224178],"type":"Point"}
}