{
  "type": "Feature",
  "properties": {
    "iso:country":"FR",
    "sg:address":"RasignaniRn 193 20290 BORGO",
    "sg:classifiers":[
        {
            "category":"Wholesale",
            "subcategory":"Wine & Distilled Alcoholic Beverages",
            "type":"Manufacturing & Wholesale Goods"
        }
    ],
    "sg:phone":"+33 4 95 58 44 00",
    "sg:postcode":"20290",
    "sg:province":"Corse",
    "sg:tags":[
        "french"
    ],
    "wof:name":"Sica Union Des Vignerons Associes Du Levant Sica",
    "wof:placetype":"venue"
},
  "geometry": {"coordinates":[9.344066,42.457439],"type":"Point"}
}