{
  "type": "Feature",
  "properties": {
    "addr:full":"Chemin d'Armancourt - Z.A.C. de Merci\u00e8res Compi\u00e8gne Picardie 60200",
    "addr:postcode":"60200",
    "addr:street":"Chemin D'Armancourt Z.A.C. De Mercie\u0300Res",
    "iso:country":"FR",
    "sg:address":"Chemin d'Armancourt - Z.A.C. de Merci\u00e8res",
    "sg:city":"Compi\u00e8gne",
    "sg:orig_category":"Unclassifiable Establishments",
    "sg:phone":"+33 3 44 86 82 28",
    "sg:postcode":"60200",
    "sg:province":"Picardie",
    "wof:name":"Biocodex S.a.",
    "wof:placetype":"venue"
},
  "geometry": {"coordinates":[2.85486,49.401451],"type":"Point"}
}