{
  "type": "Feature",
  "properties": {
    "addr:full":"1 Rue Jean De Berri Les Residences De Nohant Oizon Centre 18700",
    "addr:housenumber":"1",
    "addr:postcode":"18700",
    "addr:street":"Rue Jean De Berri Les",
    "iso:country":"FR",
    "sg:address":"1 Rue Jean De Berri Les Residences De Nohant",
    "sg:city":"Oizon",
    "sg:classifiers":[
        {
            "category":"Banks & Credit Unions",
            "subcategory":"Financial Services",
            "type":"Services"
        }
    ],
    "sg:phone":"+33 2 48 58 03 77",
    "sg:postcode":"18700",
    "sg:province":"Centre",
    "sg:tags":[
        "banking",
        "finance",
        "insurance"
    ],
    "wof:name":"Societe Fiduciaire D'expertise Comptable De Gestion Et De Re (socogere)",
    "wof:placetype":"venue"
},
  "geometry": {"coordinates":[2.50778,47.421684],"type":"Point"}
}