{
  "type": "Feature",
  "properties": {
    "addr:full":"B.P. 36, 59401 Cambrai C\u00e9dex^^1535, Av de Paris, 59400 Cambrai Nord Pas-de-Calais",
    "addr:postcode":"59401;59400",
    "addr:street":"B.P. 36;Av De Paris",
    "iso:country":"FR",
    "sg:address":"B.P. 36, 59401 Cambrai C\u00e9dex^^1535, Av de Paris, 59400 Cambrai",
    "sg:orig_category":"Non-Classified Establishments",
    "sg:phone":"+33 3 27 74 95 66",
    "sg:province":"Nord Pas-de-Calais",
    "wof:name":"Fival Elaus S.a.r.l.",
    "wof:placetype":"venue"
},
  "geometry": {"coordinates":[3.23419,50.175018],"type":"Point"}
}