{
  "type": "Feature",
  "properties": {
    "addr:full":"B.P. 17, 35120 Dol de Bretagne C\u00e9dex^^Rue du Docteur Gringoire, 35120 Dol de Bretagne Hirel Bretagne 35120",
    "addr:postcode":"35120;35120;35120",
    "addr:street":"B.P. 17;De;De Bretagne;Bretagne",
    "iso:country":"FR",
    "sg:address":"B.P. 17, 35120 Dol de Bretagne C\u00e9dex^^Rue du Docteur Gringoire, 35120 Dol de Bretagne",
    "sg:city":"Hirel",
    "sg:orig_category":"Non-Classified Establishments",
    "sg:phone":"+33 2 99 48 03 71",
    "sg:postcode":"35120",
    "sg:province":"Bretagne",
    "wof:name":"C\u00e9dro S.a.",
    "wof:placetype":"venue"
},
  "geometry": {"coordinates":[-1.649389,48.473736],"type":"Point"}
}