{
  "type": "Feature",
  "properties": {
    "addr:full":"179 Rte De Paris 78820 Juziers Ile de France",
    "addr:housenumber":"179",
    "addr:postcode":"78820",
    "addr:street":"Rte De Paris;Ile De France",
    "iso:country":"FR",
    "sg:address":"179 Rte De Paris 78820 Juziers",
    "sg:classifiers":[
        {
            "category":"Manufacturing",
            "subcategory":"Rubber & Plastics",
            "type":"Manufacturing & Wholesale Goods"
        }
    ],
    "sg:phone":"+33 1 34 75 60 91",
    "sg:province":"Ile de France",
    "wof:name":"Etablissements Gergonne Gpi",
    "wof:placetype":"venue"
},
  "geometry": {"coordinates":[1.83663,48.989651],"type":"Point"}
}