{
  "type": "Feature",
  "properties": {
    "addr:full":"14, Rue Mitlon, 75009 Paris Ile de France",
    "addr:housenumber":"14",
    "addr:postcode":"75009",
    "addr:street":"Rue Mitlon",
    "iso:country":"FR",
    "sg:address":"14, Rue Mitlon, 75009 Paris",
    "sg:orig_category":"Non-Classified Establishments",
    "sg:phone":"+33 1 44 53 71 30",
    "sg:province":"Ile de France",
    "wof:name":"Pias France S.a.r.l.",
    "wof:placetype":"venue"
},
  "geometry": {"coordinates":[2.341071,48.877796],"type":"Point"}
}