{
  "type": "Feature",
  "properties": {
    "addr:full":"40 rue Vaillant Couturier 59165 Auberchicourt Nord Pas-de-Calais 59165",
    "addr:housenumber":"40",
    "addr:postcode":"59165;59165",
    "addr:street":"Rue Vaillant Couturier",
    "iso:country":"FR",
    "sg:address":"40 rue Vaillant Couturier 59165 Auberchicourt",
    "sg:classifiers":[
        {
            "category":"Professional",
            "subcategory":"Business Services",
            "type":"Services"
        }
    ],
    "sg:phone":"+33 3 27 90 34 55",
    "sg:postcode":"59165",
    "sg:province":"Nord Pas-de-Calais",
    "sg:tags":[
        "high-precision",
        "mechanic"
    ],
    "wof:name":"S.e.e.b. Sa",
    "wof:placetype":"venue"
},
  "geometry": {"coordinates":[3.239393,50.331924],"type":"Point"}
}