{
  "type": "Feature",
  "properties": {
    "addr:full":"Rue du Ruisseau Saint-Pierre - ZA Peltre Lorraine 57245",
    "addr:postcode":"57245",
    "addr:street":"Rue Du Ruisseau",
    "iso:country":"FR",
    "sg:address":"Rue du Ruisseau Saint-Pierre - ZA",
    "sg:city":"Peltre",
    "sg:orig_category":"Cloisons amovibles Faux-plafonds Isolation, Travaux d' Planchers sur\u00e9lev\u00e9s pr\u00e9fabriqu\u00e9s",
    "sg:phone":"+33 3 87 38 21 60",
    "sg:postcode":"57245",
    "sg:province":"Lorraine",
    "wof:name":"S.m.c.p. Richard S.a.r.l.",
    "wof:placetype":"venue"
},
  "geometry": {"coordinates":[6.23244,49.069908],"type":"Point"}
}