{
  "type": "Feature",
  "properties": {
    "addr:full":"5, Rue de la Croix, 59242 Genech Nord Pas-de-Calais",
    "addr:housenumber":"5",
    "addr:postcode":"59242",
    "addr:street":"Rue De La Croix",
    "iso:country":"FR",
    "sg:address":"5, Rue de la Croix, 59242 Genech",
    "sg:orig_category":"Non-Classified Establishments",
    "sg:phone":"+33 3 20 84 57 47",
    "sg:province":"Nord Pas-de-Calais",
    "wof:name":"Grard L\u00e9on",
    "wof:placetype":"venue"
},
  "geometry": {"coordinates":[3.22871,50.531479],"type":"Point"}
}