{
  "type": "Feature",
  "properties": {
    "addr:full":"Rte de Mantes - La Fontaine des Bl\u00e9s Magny en Vexin Ile de France 95420",
    "addr:postcode":"95420",
    "addr:street":"Rte De Mantes;Des Ble\u0301S Magny En Vexin Ile De France",
    "iso:country":"FR",
    "sg:address":"Rte de Mantes - La Fontaine des Bl\u00e9s",
    "sg:city":"Magny en Vexin",
    "sg:orig_category":"Unclassifiable Establishments",
    "sg:phone":"+33 1 34 67 33 54",
    "sg:postcode":"95420",
    "sg:province":"Ile de France",
    "wof:name":"Vartp S.a.",
    "wof:placetype":"venue"
},
  "geometry": {"coordinates":[1.786815,49.155235],"type":"Point"}
}