{
  "type": "Feature",
  "properties": {
    "addr:full":"2 All De Kerlann 56000 Vannes Vannes Bretagne 56000",
    "addr:housenumber":"2",
    "addr:postcode":"56000;56000",
    "addr:street":"All De Kerlann",
    "iso:country":"FR",
    "sg:address":"2 All De Kerlann 56000 Vannes",
    "sg:city":"Vannes",
    "sg:classifiers":[
        {
            "category":"Professional",
            "subcategory":"Printing & Photocopies",
            "type":"Services"
        }
    ],
    "sg:phone":"+33 2 97 40 71 71",
    "sg:postcode":"56000",
    "sg:province":"Bretagne",
    "sg:tags":[
        "publishing"
    ],
    "wof:name":"Vannes Portage Sarl",
    "wof:placetype":"venue"
},
  "geometry": {"coordinates":[-2.783572,47.664608],"type":"Point"}
}