{
  "type": "Feature",
  "properties": {
    "iso:country":"FR",
    "sg:address":"B.P. 15, 57740 Long\u00e9ville l\u00e8s Saint Avold^^ZI, 57740 Long\u00e9ville l\u00e8s Saint Avold",
    "sg:orig_category":"Non-Classified Establishments",
    "sg:phone":"+33 3 87 92 00 19",
    "sg:province":"Lorraine",
    "wof:name":"Kaefer Wanner S.a.s. - Agence Est",
    "wof:placetype":"venue"
},
  "geometry": {"coordinates":[6.70548,49.104271],"type":"Point"}
}