{
  "type": "Feature",
  "properties": {
    "iso:country":"FR",
    "sg:address":"12 Rue Du 4 Septembre 75002 Paris",
    "sg:classifiers":[
        {
            "category":"Banks & Credit Unions",
            "subcategory":"Financial Services",
            "type":"Services"
        }
    ],
    "sg:phone":"+33 1 42 96 16 33",
    "sg:postcode":"75002",
    "sg:province":"Ile de France",
    "sg:tags":[
        "banking",
        "finance",
        "insurance"
    ],
    "wof:name":"Bournilhas-citron-mirande Scpa",
    "wof:placetype":"venue"
},
  "geometry": {"coordinates":[2.337097,48.869511],"type":"Point"}
}