{
  "type": "Feature",
  "properties": {
    "addr:full":"32 rue Mirabeau; Le Relecq Kerhuon; 29480 Le Relecq-Kerhuon Bretagne 29480",
    "addr:housenumber":"32",
    "addr:postcode":"29480;29480",
    "addr:street":"Rue Mirabeau",
    "iso:country":"FR",
    "sg:address":"32 rue Mirabeau; Le Relecq Kerhuon; 29480",
    "sg:city":"Le Relecq-Kerhuon",
    "sg:classifiers":[
        {
            "category":"Banks & Credit Unions",
            "subcategory":"Bank",
            "type":"Services"
        }
    ],
    "sg:phone":"+33 2 28 98 22 51",
    "sg:postcode":"29480",
    "sg:province":"Bretagne",
    "wof:name":"Banque Du Cr\u00e9dit Mutuel, Pour L'entreprise",
    "wof:placetype":"venue"
},
  "geometry": {"coordinates":[-4.418539,48.406116],"type":"Point"}
}