{
  "type": "Feature",
  "properties": {
    "addr:full":"25, Rue L\u00e9onard Jarraud, 16400 La Couronne Poitou-Charentes",
    "addr:housenumber":"25",
    "addr:postcode":"16400;couronne",
    "addr:street":"Rue Le\u0301Onard Jarraud",
    "iso:country":"FR",
    "sg:address":"25, Rue L\u00e9onard Jarraud, 16400 La Couronne",
    "sg:orig_category":"Unclassifiable Establishments",
    "sg:phone":"+33 5 45 67 10 32",
    "sg:province":"Poitou-Charentes",
    "wof:name":"Lafarge Ciments S.a.",
    "wof:placetype":"venue"
},
  "geometry": {"coordinates":[0.10237,45.609249],"type":"Point"}
}