{
  "type": "Feature",
  "properties": {
    "iso:country":"FR",
    "sg:address":"9, Rue Lavoisier, 25000 Besan\u00e7on",
    "sg:orig_category":"Unclassifiable Establishments",
    "sg:phone":"+33 3 81 48 60 60",
    "sg:province":"Franche Comt\u00e9",
    "wof:name":"D.s. Entreprises S.a.r.l.",
    "wof:placetype":"venue"
},
  "geometry": {"coordinates":[5.981319,47.236248],"type":"Point"}
}