{
  "type": "Feature",
  "properties": {
    "iso:country":"FR",
    "sg:address":"3, Rampes Saint Prix, 02100 Saint Quentin",
    "sg:orig_category":"Unclassifiable Establishments",
    "sg:phone":"+33 3 23 62 12 62",
    "sg:province":"Picardie",
    "wof:name":"Soci\u00e9t\u00e9 Nouvelle G\u00e9p\u00e9lec S.a.r.l. - G\u00e9n\u00e9rale Picarde D'equipements Lignes Electriques Et Canalisatio",
    "wof:placetype":"venue"
},
  "geometry": {"coordinates":[3.280338,49.839752],"type":"Point"}
}