{
  "type": "Feature",
  "properties": {
    "addr:full":"73270 Beaufort Rhone-Alpes 73270",
    "addr:postcode":"73270;rhone-alpes 73270",
    "iso:country":"FR",
    "sg:address":"73270 Beaufort",
    "sg:orig_category":"Unclassifiable Establishments",
    "sg:phone":"+33 4 79 38 33 62",
    "sg:postcode":"73270",
    "sg:province":"Rhone-Alpes",
    "wof:name":"Soci\u00e9t\u00e9 Coop\u00e9rative Laiti\u00e8re Du Beaufortain S.c.a.",
    "wof:placetype":"venue"
},
  "geometry": {"coordinates":[6.57542,45.717667],"type":"Point"}
}