{
  "type": "Feature",
  "properties": {
    "addr:full":"Zone Industrielle De Monti 85700 Pouzauges Pays de Loire 85700",
    "addr:postcode":"85700;85700",
    "addr:street":"Zone Industrielle De Monti",
    "iso:country":"FR",
    "sg:address":"Zone Industrielle De Monti 85700 Pouzauges",
    "sg:classifiers":[
        {
            "category":"Manufacturing",
            "subcategory":"Metals",
            "type":"Manufacturing & Wholesale Goods"
        }
    ],
    "sg:phone":"+33 2 51 91 33 82",
    "sg:postcode":"85700",
    "sg:province":"Pays de Loire",
    "sg:tags":[
        "-",
        "machine",
        "equipment",
        "engineering",
        "machinery",
        "mechanical"
    ],
    "wof:name":"Vendee Diamant (vedia)",
    "wof:placetype":"venue"
},
  "geometry": {"coordinates":[-0.836104,46.7822],"type":"Point"}
}