{
  "type": "Feature",
  "properties": {
    "iso:country":"FR",
    "sg:address":"669, Rue de Valmont, 34980 Saint G\u00e9ly du Fesc",
    "sg:orig_category":"Unclassifiable Establishments",
    "sg:phone":"+33 4 67 63 34 81",
    "sg:province":"Languedoc-Roussillon",
    "wof:name":"Calytherm S.a.",
    "wof:placetype":"venue"
},
  "geometry": {"coordinates":[3.805637,43.687622],"type":"Point"}
}