{
  "type": "Feature",
  "properties": {
    "addr:full":"B.P. 71, 93260 Les Lilas C\u00e9dex^^153, Rue Noisy le Sec, 93260 Les Lilas Ile de France 93260",
    "addr:postcode":"93260;93260;93260",
    "addr:street":"B.P. 71;Rue Noisy Le Sec;France",
    "iso:country":"FR",
    "sg:address":"B.P. 71, 93260 Les Lilas C\u00e9dex^^153, Rue Noisy le Sec, 93260 Les Lilas",
    "sg:orig_category":"Non-Classified Establishments",
    "sg:phone":"+33 1 49 93 77 88",
    "sg:postcode":"93260",
    "sg:province":"Ile de France",
    "wof:name":"Ascenseurs Drieux Combaluzier S.a.",
    "wof:placetype":"venue"
},
  "geometry": {"coordinates":[2.415765,48.879616],"type":"Point"}
}