{
  "type": "Feature",
  "properties": {
    "iso:country":"FR",
    "sg:address":"Zi Route De Cholet 49300 Maul\u00e9vrier",
    "sg:orig_category":"Fabrics Leather - raw materials Leather and Shoes Leather goods Mechanical Engineering - machines Pr",
    "sg:phone":"+33 2 41 55 56 26",
    "sg:postcode":"49300",
    "sg:province":"Pays de Loire",
    "wof:name":"Pact-europact Sa",
    "wof:placetype":"venue"
},
  "geometry": {"coordinates":[-0.892689,46.99659],"type":"Point"}
}