{
  "type": "Feature",
  "properties": {
    "iso:country":"FR",
    "sg:address":"B.P. 1",
    "sg:city":"Les Quatre Routes du Lot C\u00e9dex^^46110 Les Quatre Routes du Lot",
    "sg:orig_category":"Non-Classified Establishments",
    "sg:phone":"+33 5 65 32 10 06",
    "sg:postcode":"46110",
    "sg:province":"Midi Pyr\u00e9n\u00e9es",
    "wof:name":"Q.m. S.a.r.l. - Quercy Menuiserie",
    "wof:placetype":"venue"
},
  "geometry": {"coordinates":[1.740226,44.900391],"type":"Point"}
}