{
  "type": "Feature",
  "properties": {
    "iso:country":"FR",
    "sg:address":"380 Rue Du Vergerot 39210 Domblans",
    "sg:classifiers":[
        {
            "category":"Health Services",
            "subcategory":"Optometrist",
            "type":"Services"
        }
    ],
    "sg:phone":"+33 3 84 87 19 60",
    "sg:postcode":"39210",
    "sg:province":"Franche Comt\u00e9",
    "sg:tags":[
        "instrument",
        "optical",
        "-",
        "precision",
        "equipment"
    ],
    "wof:name":"Odo",
    "wof:placetype":"venue"
},
  "geometry": {"coordinates":[5.600246,46.762032],"type":"Point"}
}