{
  "type": "Feature",
  "properties": {
    "iso:country":"FR",
    "sg:address":"17 Boulevard Clemenceau",
    "sg:city":"St Brieuc",
    "sg:classifiers":[
        {
            "category":"Banks & Credit Unions",
            "subcategory":"Financial Services",
            "type":"Services"
        }
    ],
    "sg:phone":"+33 2 96 33 32 87",
    "sg:postcode":"22000",
    "sg:province":"Bretagne",
    "sg:tags":[
        "banking",
        "finance",
        "insurance"
    ],
    "wof:name":"Societe Fiduciaire D'expertise Comptable De Gestion Et De Re (socogere)",
    "wof:placetype":"venue"
},
  "geometry": {"coordinates":[-2.759553,48.509586],"type":"Point"}
}