{
  "type": "Feature",
  "properties": {
    "addr:full":"3 Boulevard De La Madeleine 75001 Paris Ile de France 75001",
    "addr:housenumber":"3",
    "addr:postcode":"75001;75001",
    "addr:street":"Boulevard De La Madeleine",
    "iso:country":"FR",
    "sg:address":"3 Boulevard De La Madeleine 75001 Paris",
    "sg:classifiers":[
        {
            "category":"Shopping",
            "subcategory":"Luggage & Leather Goods",
            "type":"Retail Goods"
        }
    ],
    "sg:phone":"+33 1 42 61 11 87",
    "sg:postcode":"75001",
    "sg:province":"Ile de France",
    "sg:tags":[
        "shoe"
    ],
    "wof:name":"Jm Weston",
    "wof:placetype":"venue"
},
  "geometry": {"coordinates":[2.327535,48.869728],"type":"Point"}
}