{
  "type": "Feature",
  "properties": {
    "addr:full":"Prat Menan 29880 Plouguerneau Plouguerneau Bretagne 29880",
    "addr:postcode":"29880;29880",
    "addr:street":"Prat",
    "iso:country":"FR",
    "sg:address":"Prat Menan 29880 Plouguerneau",
    "sg:city":"Plouguerneau",
    "sg:classifiers":[
        {
            "category":"Shopping",
            "subcategory":"Pharmacy",
            "type":"Retail Goods"
        }
    ],
    "sg:phone":"+33 2 98 04 54 11",
    "sg:postcode":"29880",
    "sg:province":"Bretagne",
    "sg:tags":[
        "chemical",
        "pharmaceutical",
        "chemistry"
    ],
    "wof:name":"Agrimer (ste Nouvelle) Sa",
    "wof:placetype":"venue"
},
  "geometry": {"coordinates":[-4.52889,48.621403],"type":"Point"}
}