{
  "type": "Feature",
  "properties": {
    "iso:country":"FR",
    "sg:address":"B.P. 553, 69637 V\u00e9nissieux C\u00e9dex^^12, Rue Pierre Timbaud - ZI V\u00e9nissieux-Corbas-Saint Priest, 69200 ",
    "sg:orig_category":"Non-Classified Establishments",
    "sg:phone":"+33 4 72 50 31 58",
    "sg:postcode":"69200",
    "sg:province":"Rhone-Alpes",
    "wof:name":"Public Imprim S.a.r.l.",
    "wof:placetype":"venue"
},
  "geometry": {"coordinates":[4.904151,45.69297],"type":"Point"}
}