{
  "type": "Feature",
  "properties": {
    "iso:country":"FR",
    "sg:address":"Mas St Pierre 66170 Millas",
    "sg:classifiers":[
        {
            "category":"Farming",
            "subcategory":"Farm & Veterinary Services",
            "type":"Manufacturing & Wholesale Goods"
        }
    ],
    "sg:phone":"+33 4 68 57 19 44",
    "sg:postcode":"66170",
    "sg:province":"Languedoc-Roussillon",
    "sg:tags":[
        "advice",
        "agriculture",
        "livestock",
        "business"
    ],
    "wof:name":"Sarl Mas Saint Pierre",
    "wof:placetype":"venue"
},
  "geometry": {"coordinates":[2.688325,42.692459],"type":"Point"}
}