{
  "type": "Feature",
  "properties": {
    "iso:country":"FR",
    "sg:address":"B.P. 69",
    "sg:city":"Saint Front sur Nizonne^^Le Bourg 24300 Saint Front sur Nizonne",
    "sg:orig_category":"Non-Classified Establishments",
    "sg:phone":"+33 5 53 56 36 41",
    "sg:postcode":"24300",
    "sg:province":"Aquitaine",
    "wof:name":"Onix S.a.r.l.",
    "wof:placetype":"venue"
},
  "geometry": {"coordinates":[0.83423,45.438919],"type":"Point"}
}