{
  "type": "Feature",
  "properties": {
    "addr:full":"9 Rue De La Paix 75002 Paris Ile de France 75002",
    "addr:housenumber":"9",
    "addr:postcode":"75002;75002",
    "addr:street":"Rue De La Paix",
    "iso:country":"FR",
    "sg:address":"9 Rue De La Paix 75002 Paris",
    "sg:classifiers":[
        {
            "category":"Manufacturing",
            "subcategory":"Jewelry",
            "type":"Manufacturing & Wholesale Goods"
        }
    ],
    "sg:phone":"+33 1 42 61 57 53",
    "sg:postcode":"75002",
    "sg:province":"Ile de France",
    "sg:tags":[
        "product",
        "miscellaneous",
        "jewellery"
    ],
    "wof:name":"Mellerio Sa",
    "wof:placetype":"venue"
},
  "geometry": {"coordinates":[2.330802,48.869091],"type":"Point"}
}