{
  "type": "Feature",
  "properties": {
    "addr:full":"21370 Plombi\u00e8res l\u00e8s Dijon Lantenay Bourgogne 21370",
    "addr:postcode":"21370;21370",
    "addr:street":"Bourgogne",
    "iso:country":"FR",
    "sg:address":"21370 Plombi\u00e8res l\u00e8s Dijon",
    "sg:city":"Lantenay",
    "sg:orig_category":"Unclassifiable Establishments",
    "sg:phone":"+33 3 80 76 97 10",
    "sg:postcode":"21370",
    "sg:province":"Bourgogne",
    "wof:name":"A.d.m.cocoa S.a.",
    "wof:placetype":"venue"
},
  "geometry": {"coordinates":[4.972715,47.339386],"type":"Point"}
}