{
  "type": "Feature",
  "properties": {
    "iso:country":"FR",
    "sg:address":"3 bis, Rue de la Salp\u00e9tri\u00e8re, 54000 Nancy",
    "sg:orig_category":"Unclassifiable Establishments",
    "sg:phone":"+33 3 83 36 52 95",
    "sg:province":"Lorraine",
    "wof:name":"S.s.t.b. S.a.",
    "wof:placetype":"venue"
},
  "geometry": {"coordinates":[6.185645,48.68552],"type":"Point"}
}