{
  "type": "Feature",
  "properties": {
    "iso:country":"FR",
    "sg:address":"13474 Marseille C\u00e9dex^^10, Place de la Joliette - Les Docks Atrium 103, 13000 Marseille",
    "sg:orig_category":"Non-Classified Establishments",
    "sg:phone":"+33 4 91 13 45 92",
    "sg:province":"Poitou-Charentes",
    "wof:name":"E.a.",
    "wof:placetype":"venue"
},
  "geometry": {"coordinates":[5.37249,43.293686],"type":"Point"}
}