{
  "type": "Feature",
  "properties": {
    "iso:country":"FR",
    "sg:address":"131 Pl Aristide Berg\u00e8s Usine De Chedde 74190 Passy",
    "sg:classifiers":[
        {
            "category":"Manufacturing",
            "subcategory":"Chemicals & Compounds",
            "type":"Manufacturing & Wholesale Goods"
        }
    ],
    "sg:phone":"+33 4 50 47 47 00",
    "sg:postcode":"74190",
    "sg:province":"Rhone-Alpes",
    "sg:tags":[
        "pharmaceutical",
        "chemistry"
    ],
    "wof:name":"Sgl Carbon Sa",
    "wof:placetype":"venue"
},
  "geometry": {"coordinates":[6.685855,45.923489],"type":"Point"}
}