{
  "type": "Feature",
  "properties": {
    "iso:country":"FR",
    "sg:address":"Paltanaggia 20146 Sotta",
    "sg:orig_category":"Unclassifiable Establishments",
    "sg:phone":"+33 4 95 71 24 64",
    "sg:province":"Corse",
    "wof:name":"Euro Corse Voyages S.a.r.l.",
    "wof:placetype":"venue"
},
  "geometry": {"coordinates":[9.191675,41.545044],"type":"Point"}
}