{
  "type": "Feature",
  "properties": {
    "iso:country":"FR",
    "sg:address":"Le Plan 84440 Robion",
    "sg:classifiers":[
        {
            "category":"Farming",
            "subcategory":"Farm",
            "type":"Manufacturing & Wholesale Goods"
        }
    ],
    "sg:phone":"+33 4 90 76 68 10",
    "sg:province":"Midi Pyr\u00e9n\u00e9es",
    "sg:tags":[
        "horticulture",
        "agriculture",
        "livestock"
    ],
    "wof:name":"Sodemm Societe Des Engrais Manon Michut",
    "wof:placetype":"venue"
},
  "geometry": {"coordinates":[5.107724,43.840427],"type":"Point"}
}