{
  "type": "Feature",
  "properties": {
    "iso:country":"FR",
    "sg:address":"15 Av Mal Foch 69006 Lyon",
    "sg:classifiers":[
        {
            "category":"Banks & Credit Unions",
            "subcategory":"Financial Services",
            "type":"Services"
        }
    ],
    "sg:phone":"+33 4 72 69 59 49",
    "sg:province":"Rhone-Alpes",
    "sg:tags":[
        "banking",
        "insurance",
        "institution",
        "finance"
    ],
    "wof:name":"Duquesne Finance Sa",
    "wof:placetype":"venue"
},
  "geometry": {"coordinates":[4.849785,45.769245],"type":"Point"}
}