{
  "type": "Feature",
  "properties": {
    "addr:full":"B.P. 303 Auxerre C\u00e9dex Bourgogne 89005",
    "addr:housenumber":"b.p. 303",
    "addr:postcode":"89005",
    "iso:country":"FR",
    "sg:address":"B.P. 303",
    "sg:city":"Auxerre C\u00e9dex",
    "sg:orig_category":"Non-Classified Establishments",
    "sg:phone":"+33 3 86 49 26 11",
    "sg:postcode":"89005",
    "sg:province":"Bourgogne",
    "wof:name":"Costep Centre Est",
    "wof:placetype":"venue"
},
  "geometry": {"coordinates":[3.569305,47.796051],"type":"Point"}
}