{
  "type": "Feature",
  "properties": {
    "iso:country":"FR",
    "sg:address":"31 ave F\u00e9lix Faure; Menton; 06501",
    "sg:classifiers":[
        {
            "category":"Banks & Credit Unions",
            "subcategory":"Bank",
            "type":"Services"
        }
    ],
    "sg:phone":"+33 4 93 57 02 02",
    "sg:province":"Champagne",
    "wof:name":"Banque Populaire, De La C\u00f4te D'azur",
    "wof:placetype":"venue"
},
  "geometry": {"coordinates":[7.501799,43.774712],"type":"Point"}
}