{
  "type": "Feature",
  "properties": {
    "addr:full":"Route Du Pontet Quartier Des Verguets 84270 Vedene Bourgogne",
    "addr:postcode":"84270",
    "addr:street":"Route Du Pontet",
    "iso:country":"FR",
    "sg:address":"Route Du Pontet Quartier Des Verguets 84270 Vedene",
    "sg:classifiers":[
        {
            "category":"Wholesale",
            "subcategory":"Machinery & Supplies",
            "type":"Manufacturing & Wholesale Goods"
        }
    ],
    "sg:phone":"+33 4 90 31 36 74",
    "sg:province":"Bourgogne",
    "sg:tags":[
        "handling",
        "material",
        "-",
        "machine",
        "equipment",
        "engineering",
        "mechanical"
    ],
    "wof:name":"Favier Chazal Sussi Palettes",
    "wof:placetype":"venue"
},
  "geometry": {"coordinates":[4.905397,43.977158],"type":"Point"}
}