{
  "type": "Feature",
  "properties": {
    "iso:country":"FR",
    "sg:address":"31 rue Marbeuf 75008 Paris",
    "sg:classifiers":[
        {
            "category":"Food & Beverages",
            "subcategory":"Candy",
            "type":"Retail Goods"
        }
    ],
    "sg:phone":"+33 1 44 21 69 00",
    "sg:postcode":"75008",
    "sg:province":"Ile de France",
    "sg:tags":[
        "plants",
        "turnkey"
    ],
    "wof:name":"Rwe Solutions France",
    "wof:placetype":"venue"
},
  "geometry": {"coordinates":[2.304839,48.869507],"type":"Point"}
}