{
  "type": "Feature",
  "properties": {
    "iso:country":"FR",
    "sg:address":"294, Chemin de Lavalette, 82000 Castelsarrasin",
    "sg:orig_category":"Unclassifiable Establishments",
    "sg:phone":"+33 5 63 32 80 00",
    "sg:province":"Midi Pyr\u00e9n\u00e9es",
    "wof:name":"Alcoa France S.a.",
    "wof:placetype":"venue"
},
  "geometry": {"coordinates":[-82.44725800000001,38.323029],"type":"Point"}
}