{
  "type": "Feature",
  "properties": {
    "iso:country":"FR",
    "sg:address":"10 Chemin De Fondeyre 31085 Toulouse Cedex 2",
    "sg:classifiers":[
        {
            "category":"Manufacturing",
            "subcategory":"Wood Products",
            "type":"Manufacturing & Wholesale Goods"
        }
    ],
    "sg:phone":"+33 5 61 13 53 23",
    "sg:province":"Midi-Pyr\u00e9n\u00e9es",
    "sg:tags":[
        "furniture"
    ],
    "wof:name":"Diffusion Industrielle D Articles Meublants Sa",
    "wof:placetype":"venue"
},
  "geometry": {"coordinates":[1.422395,43.63797],"type":"Point"}
}