{
  "type": "Feature",
  "properties": {
    "addr:full":"La Vall\u00e9e Ch\u00e2telaudren Bretagne 22170",
    "addr:postcode":"22170",
    "addr:street":"La;Cha\u0302Telaudren Bretagne",
    "iso:country":"FR",
    "sg:address":"La Vall\u00e9e",
    "sg:city":"Ch\u00e2telaudren",
    "sg:orig_category":"Non-Classified Establishments",
    "sg:phone":"+33 2 96 79 54 00",
    "sg:postcode":"22170",
    "sg:province":"Bretagne",
    "wof:name":"Le Du Industrie S.a.",
    "wof:placetype":"venue"
},
  "geometry": {"coordinates":[-2.972309,48.53595],"type":"Point"}
}