{
  "type": "Feature",
  "properties": {
    "iso:country":"FR",
    "sg:address":"1, Bd Industriel, 76300 Sotteville les Rouen",
    "sg:orig_category":"Unclassifiable Establishments",
    "sg:phone":"+33 2 32 18 20 50",
    "sg:province":"Haute Normandie",
    "wof:name":"Brenntag Normandie S.a.",
    "wof:placetype":"venue"
},
  "geometry": {"coordinates":[1.106534,49.423622],"type":"Point"}
}