{
  "type": "Feature",
  "properties": {
    "addr:full":"98 de Valenciennes BP 237 59540 Caudry Nord Pas-de-Calais 59540",
    "addr:housenumber":"237",
    "addr:postcode":"59540;59540",
    "addr:street":"98 De Valenciennes Bp",
    "iso:country":"FR",
    "sg:address":"98",
    "sg:city":"de Valenciennes BP 237 59540 Caudry",
    "sg:classifiers":[
        {
            "category":"Manufacturing",
            "subcategory":"Glass & Minerals",
            "type":"Manufacturing & Wholesale Goods"
        }
    ],
    "sg:phone":"+33 3 27 85 80 54",
    "sg:postcode":"59540",
    "sg:province":"Nord Pas-de-Calais",
    "sg:tags":[
        "building",
        "material"
    ],
    "wof:name":"Allard Sa",
    "wof:placetype":"venue"
},
  "geometry": {"coordinates":[3.414661,50.13031],"type":"Point"}
}