{
  "type": "Feature",
  "properties": {
    "addr:full":"23 Ren\u00e9 Laennec; Donges; 44480 Pays de Loire 44480",
    "addr:housenumber":"23",
    "addr:postcode":"44480;44480",
    "addr:street":"Rene\u0301 Laennec",
    "iso:country":"FR",
    "sg:address":"23",
    "sg:city":"Ren\u00e9 Laennec; Donges; 44480",
    "sg:classifiers":[
        {
            "category":"Banks & Credit Unions",
            "subcategory":"Bank",
            "type":"Services"
        }
    ],
    "sg:phone":"+33 3340910303",
    "sg:postcode":"44480",
    "sg:province":"Pays de Loire",
    "wof:name":"Caisse R\u00e9gionale De Cr\u00e9dit Agricole",
    "wof:placetype":"venue"
},
  "geometry": {"coordinates":[-2.074131,47.319229],"type":"Point"}
}