{
  "type": "Feature",
  "properties": {
    "iso:country":"FR",
    "sg:address":"8, Rue Saint Pierre, 59170 Croix",
    "sg:orig_category":"Unclassifiable Establishments",
    "sg:phone":"+33 3 20 70 05 65",
    "sg:province":"Nord Pas-de-Calais",
    "wof:name":"Frais Poulet S.a.r.l.",
    "wof:placetype":"venue"
},
  "geometry": {"coordinates":[3.153983,50.684853],"type":"Point"}
}