{
  "type": "Feature",
  "properties": {
    "addr:full":"2 bis, Rue du Pavillon, 49070 Beaucouz\u00e9 Pays de Loire",
    "addr:housenumber":"2 bis",
    "addr:postcode":"49070",
    "addr:street":"Rue Du Pavillon",
    "iso:country":"FR",
    "sg:address":"2 bis, Rue du Pavillon, 49070 Beaucouz\u00e9",
    "sg:orig_category":"Unclassifiable Establishments",
    "sg:phone":"+33 2 41 48 84 66",
    "sg:province":"Pays de Loire",
    "wof:name":"S.i.b.e. S.a.",
    "wof:placetype":"venue"
},
  "geometry": {"coordinates":[-0.622177,47.466331],"type":"Point"}
}