{
  "type": "Feature",
  "properties": {
    "addr:full":"B.P. 919, 50449 Beaumont Hague C\u00e9dex^^ZI Digulleville, 50440 Beaumont Hague Digulleville Basse Normandie 50440",
    "addr:housenumber":"b.p. 919",
    "addr:postcode":"50449;50440;50440",
    "iso:country":"FR",
    "sg:address":"B.P. 919, 50449 Beaumont Hague C\u00e9dex^^ZI Digulleville, 50440 Beaumont Hague",
    "sg:city":"Digulleville",
    "sg:orig_category":"Non-Classified Establishments",
    "sg:phone":"+33 2 33 52 71 14",
    "sg:postcode":"50440",
    "sg:province":"Basse Normandie",
    "wof:name":"Laho Equipement",
    "wof:placetype":"venue"
},
  "geometry": {"coordinates":[-1.779169,49.59861],"type":"Point"}
}