{
  "type": "Feature",
  "properties": {
    "iso:country":"FR",
    "sg:address":"Lieu Dit Charrieras 24750 Tr\u00e9lissac",
    "sg:city":"Tr\u00e9lissac",
    "sg:classifiers":[
        {
            "category":"Manufacturing",
            "subcategory":"Metals",
            "type":"Manufacturing & Wholesale Goods"
        }
    ],
    "sg:phone":"+33 5 53 03 90 98",
    "sg:postcode":"24750",
    "sg:province":"Aquitaine",
    "sg:tags":[
        "metallurgy",
        "metalworking",
        "processing"
    ],
    "wof:name":"Artisanat Du Perigord Sarl",
    "wof:placetype":"venue"
},
  "geometry": {"coordinates":[0.789735,45.09977],"type":"Point"}
}