{
  "type": "Feature",
  "properties": {
    "addr:full":"Vaudebrune 61440 Saint Andr\u00e9 de Messei Messei Basse Normandie 61440",
    "addr:postcode":"61440;61440",
    "addr:street":"Vaudebrune;Basse",
    "iso:country":"FR",
    "sg:address":"Vaudebrune 61440 Saint Andr\u00e9 de Messei",
    "sg:city":"Messei",
    "sg:orig_category":"Unclassifiable Establishments",
    "sg:phone":"+33 2 33 66 91 19",
    "sg:postcode":"61440",
    "sg:province":"Basse Normandie",
    "wof:name":"Technipal S.a.",
    "wof:placetype":"venue"
},
  "geometry": {"coordinates":[-0.519519,48.675285],"type":"Point"}
}