{
  "type": "Feature",
  "properties": {
    "addr:full":"Le Verdoyer 141 87430 Verneuil Sur Vienne Limousin",
    "addr:housenumber":"141",
    "addr:postcode":"87430",
    "iso:country":"FR",
    "sg:address":"Le Verdoyer",
    "sg:city":"141 87430 Verneuil Sur Vienne",
    "sg:classifiers":[
        {
            "category":"Professional",
            "type":"Services"
        }
    ],
    "sg:phone":"+33 5 55 00 18 00",
    "sg:province":"Limousin",
    "sg:tags":[
        "transport",
        "road"
    ],
    "wof:name":"Transports Delaumenie Sa",
    "wof:placetype":"venue"
},
  "geometry": {"coordinates":[1.127005,45.848839],"type":"Point"}
}