{
  "type": "Feature",
  "properties": {
    "addr:full":"1 ave de la Lib\u00e9ration; Laxou; 54520 Lorraine 54520",
    "addr:postcode":"54520;54520",
    "addr:street":"1 Ave De La Libe\u0301Ration",
    "iso:country":"FR",
    "sg:address":"1 ave de la Lib\u00e9ration; Laxou; 54520",
    "sg:classifiers":[
        {
            "category":"Banks & Credit Unions",
            "subcategory":"Bank",
            "type":"Services"
        }
    ],
    "sg:phone":"+33 3383272613",
    "sg:postcode":"54520",
    "sg:province":"Lorraine",
    "wof:name":"Banque Nationale De Paris",
    "wof:placetype":"venue"
},
  "geometry": {"coordinates":[6.15662,48.677437],"type":"Point"}
}