{
  "type": "Feature",
  "properties": {
    "iso:country":"FR",
    "sg:address":"32 Route Nationale 69330 Jonage",
    "sg:classifiers":[
        {
            "category":"Manufacturing",
            "subcategory":"Metals",
            "type":"Manufacturing & Wholesale Goods"
        }
    ],
    "sg:phone":"+33 4 78 04 25 61",
    "sg:province":"Rhone-Alpes",
    "sg:tags":[
        "metallurgy",
        "metalworking",
        "processing"
    ],
    "wof:name":"Sarl Chavancy",
    "wof:placetype":"venue"
},
  "geometry": {"coordinates":[5.037173,45.79274],"type":"Point"}
}