{
  "type": "Feature",
  "properties": {
    "iso:country":"FR",
    "sg:address":"674, Rue Jeanne La Lorraine, 76850 Bosc le Hard",
    "sg:orig_category":"Unclassifiable Establishments",
    "sg:phone":"+33 2 35 33 30 02",
    "sg:province":"Haute Normandie",
    "wof:name":"Gie Interf\u00fbts S.a.",
    "wof:placetype":"venue"
},
  "geometry": {"coordinates":[1.174005,49.628857],"type":"Point"}
}