{
  "type": "Feature",
  "properties": {
    "iso:country":"FR",
    "sg:address":"Parc Burospace 7 Bis Zone D'Activit\u00e9 91571 Bi\u00e8vres Cedex",
    "sg:city":"Bi\u00e8vres",
    "sg:classifiers":[
        {
            "category":"Professional",
            "subcategory":"Engineering",
            "type":"Services"
        }
    ],
    "sg:phone":"+33 1 69 33 21 00",
    "sg:postcode":"08370",
    "sg:province":"Champagne",
    "sg:tags":[
        "machine",
        "-",
        "mechanical"
    ],
    "wof:name":"Gerber Garment Technology Sarl",
    "wof:placetype":"venue"
},
  "geometry": {"coordinates":[2.218548,48.766361],"type":"Point"}
}