{
  "type": "Feature",
  "properties": {
    "iso:country":"FR",
    "sg:address":"B.P. 8, 67151 Erstein C\u00e9dex^^Rue Ettor\u00e9 Bugatti, 67150 Erstein",
    "sg:city":"Erstein",
    "sg:orig_category":"Non-Classified Establishments",
    "sg:phone":"+33 3 88 59 86 36",
    "sg:postcode":"67150",
    "sg:province":"Alsace",
    "wof:name":"Erstein S.a.",
    "wof:placetype":"venue"
},
  "geometry": {"coordinates":[7.66295,48.421101],"type":"Point"}
}