{
  "type": "Feature",
  "properties": {
    "addr:full":"41, Chemin du Camp Miaulaire, 34400 Lunel Viel Languedoc-Roussillon",
    "addr:housenumber":"41",
    "addr:postcode":"34400",
    "addr:street":"Chemin Du Camp Miaulaire;Viel",
    "iso:country":"FR",
    "sg:address":"41, Chemin du Camp Miaulaire, 34400 Lunel Viel",
    "sg:orig_category":"Non-Classified Establishments",
    "sg:phone":"+33 4 67 71 07 30",
    "sg:province":"Languedoc-Roussillon",
    "wof:name":"Fab'o'fil S.a.r.l.",
    "wof:placetype":"venue"
},
  "geometry": {"coordinates":[4.100281,43.676125],"type":"Point"}
}