{
  "type": "Feature",
  "properties": {
    "addr:full":"22 Rue Blondel 75002 Paris Ile de France 75002",
    "addr:housenumber":"22",
    "addr:postcode":"75002;75002",
    "addr:street":"Rue Blondel",
    "iso:country":"FR",
    "sg:address":"22 Rue Blondel 75002 Paris",
    "sg:classifiers":[
        {
            "category":"Shopping",
            "subcategory":"Clothing, Apparel, & Fashions",
            "type":"Retail Goods"
        }
    ],
    "sg:phone":"+33 1 48 44 63 23",
    "sg:postcode":"75002",
    "sg:province":"Ile de France",
    "sg:tags":[
        "textile",
        "clothing",
        "clothes"
    ],
    "wof:name":"Bosca",
    "wof:placetype":"venue"
},
  "geometry": {"coordinates":[2.353253,48.868931],"type":"Point"}
}