{
  "type": "Feature",
  "properties": {
    "iso:country":"FR",
    "sg:address":"19, Rte de Paray, 91320 Wissous",
    "sg:orig_category":"Unclassifiable Establishments",
    "sg:phone":"+33 1 69 20 87 49",
    "sg:province":"Ile de France",
    "wof:name":"Andreoli Robert Et Compagnie S.a.r.l.",
    "wof:placetype":"venue"
},
  "geometry": {"coordinates":[2.330095,48.728561],"type":"Point"}
}