{
  "type": "Feature",
  "properties": {
    "addr:full":"9, Rue Huysmans, 75006 Paris Ile de France",
    "addr:housenumber":"9",
    "addr:postcode":"75006",
    "addr:street":"Rue Huysmans",
    "iso:country":"FR",
    "sg:address":"9, Rue Huysmans, 75006 Paris",
    "sg:orig_category":"Non-Classified Establishments",
    "sg:phone":"+33 1 42 84 88 80",
    "sg:province":"Ile de France",
    "wof:name":"Saqqara Systems S.a.",
    "wof:placetype":"venue"
},
  "geometry": {"coordinates":[2.328984,48.845612],"type":"Point"}
}