{
  "type": "Feature",
  "properties": {
    "addr:full":"9 Rue Gare 80500 Hargicourt Picardie 80500",
    "addr:housenumber":"9",
    "addr:postcode":"80500;80500",
    "addr:street":"Rue Gare;Picardie",
    "iso:country":"FR",
    "sg:address":"9 Rue Gare 80500 Hargicourt",
    "sg:classifiers":[
        {
            "category":"Farming",
            "subcategory":"Crops",
            "type":"Manufacturing & Wholesale Goods"
        }
    ],
    "sg:phone":"+33 3 22 78 79 79",
    "sg:postcode":"80500",
    "sg:province":"Picardie",
    "sg:tags":[
        "vegetable",
        "fruit",
        "agriculture",
        "livestock"
    ],
    "wof:name":"S I C A Parmentier Societe D Interet Collectif Agricole Sa",
    "wof:placetype":"venue"
},
  "geometry": {"coordinates":[2.531155,49.714424],"type":"Point"}
}