{
  "type": "Feature",
  "properties": {
    "addr:full":"B.P. 77810, 21078 Dijon C\u00e9dex^^14, Rue Mayence, 21000 Dijon Dijon Ile de France 21000",
    "addr:postcode":"21078;21000;21000",
    "addr:street":"Rue Mayence",
    "iso:country":"FR",
    "sg:address":"B.P. 77810, 21078 Dijon C\u00e9dex^^14, Rue Mayence, 21000 Dijon",
    "sg:city":"Dijon",
    "sg:orig_category":"Non-Classified Establishments",
    "sg:phone":"+33 3 80 77 44 44",
    "sg:postcode":"21000",
    "sg:province":"Ile de France",
    "wof:name":"S.d.m.e. S.a.",
    "wof:placetype":"venue"
},
  "geometry": {"coordinates":[5.044195,47.326458],"type":"Point"}
}