{
  "type": "Feature",
  "properties": {
    "addr:full":"44 rue des Forges 13010 Marseille Poitou-Charentes",
    "addr:housenumber":"44",
    "addr:postcode":"13010",
    "addr:street":"Rue Des Forges",
    "iso:country":"FR",
    "sg:address":"44 rue des Forges 13010 Marseille",
    "sg:classifiers":[
        {
            "category":"Professional",
            "subcategory":"Business Services",
            "type":"Services"
        }
    ],
    "sg:phone":"+33 4 96 20 83 83",
    "sg:province":"Poitou-Charentes",
    "sg:tags":[
        "agency",
        "export"
    ],
    "wof:name":"Bleu Marine S.a.",
    "wof:placetype":"venue"
},
  "geometry": {"coordinates":[5.409647,43.278324],"type":"Point"}
}