{
  "type": "Feature",
  "properties": {
    "addr:full":"43/45, Av. de Clichy, 75017 Paris Ile de France",
    "addr:housenumber":"43 / 45",
    "addr:postcode":"75017",
    "addr:street":"Av. De Clichy",
    "iso:country":"FR",
    "sg:address":"43/45, Av. de Clichy, 75017 Paris",
    "sg:orig_category":"Non-Classified Establishments",
    "sg:phone":"+33 1 45 22 27 81",
    "sg:province":"Ile de France",
    "wof:name":"M\u00e9talexfrance S.a.",
    "wof:placetype":"venue"
},
  "geometry": {"coordinates":[2.325779,48.886837],"type":"Point"}
}