{
  "type": "Feature",
  "properties": {
    "addr:full":"38490 Chimilin Rhone-Alpes 38490",
    "addr:postcode":"38490;38490",
    "addr:street":"Rhone-Alpes",
    "iso:country":"FR",
    "sg:address":"38490 Chimilin",
    "sg:classifiers":[
        {
            "category":"Professional",
            "subcategory":"Engineering",
            "type":"Services"
        }
    ],
    "sg:phone":"+33 4 76 31 69 92",
    "sg:postcode":"38490",
    "sg:province":"Rhone-Alpes",
    "sg:tags":[
        "machine",
        "-",
        "mechanical"
    ],
    "wof:name":"Materiel Graphique Diffusion (mgd)",
    "wof:placetype":"venue"
},
  "geometry": {"coordinates":[5.600455,45.57695],"type":"Point"}
}