{
  "type": "Feature",
  "properties": {
    "addr:full":"54, Rue du Faude, 68370 Orbey Orbey Alsace 68370",
    "addr:housenumber":"54",
    "addr:postcode":"68370;68370",
    "addr:street":"Rue Du Faude",
    "iso:country":"FR",
    "sg:address":"54, Rue du Faude, 68370 Orbey",
    "sg:city":"Orbey",
    "sg:orig_category":"Non-Classified Establishments",
    "sg:phone":"+33 3 89 71 20 69",
    "sg:postcode":"68370",
    "sg:province":"Alsace",
    "wof:name":"Scandella Fr\u00e8res S.a.r.l.",
    "wof:placetype":"venue"
},
  "geometry": {"coordinates":[7.16087,48.128021],"type":"Point"}
}