{
  "type": "Feature",
  "properties": {
    "addr:full":"67, Rue Saint Georges, 54000 Nancy Lorraine",
    "addr:housenumber":"67",
    "addr:postcode":"54000",
    "addr:street":"Rue Saint Georges",
    "iso:country":"FR",
    "sg:address":"67, Rue Saint Georges, 54000 Nancy",
    "sg:orig_category":"Unclassifiable Establishments",
    "sg:phone":"+33 3 83 32 06 02",
    "sg:province":"Lorraine",
    "wof:name":"Imprimerie Papeterie Rigot S.a.r.l.",
    "wof:placetype":"venue"
},
  "geometry": {"coordinates":[6.185943,48.691982],"type":"Point"}
}