{
  "type": "Feature",
  "properties": {
    "iso:country":"FR",
    "sg:address":"67, Rue Saint Georges, 54000 Nancy",
    "sg:orig_category":"Unclassifiable Establishments",
    "sg:phone":"+33 3 83 32 06 02",
    "sg:province":"Lorraine",
    "wof:name":"Imprimerie Papeterie Rigot S.a.r.l.",
    "wof:placetype":"venue"
},
  "geometry": {"coordinates":[6.185943,48.691982],"type":"Point"}
}