{
  "type": "Feature",
  "properties": {
    "iso:country":"FR",
    "sg:address":"Le Petit Saclay 91400 Orsay",
    "sg:classifiers":[
        {
            "category":"Farming",
            "subcategory":"Livestock Farm",
            "type":"Manufacturing & Wholesale Goods"
        }
    ],
    "sg:phone":"+33 1 69 41 13 66",
    "sg:postcode":"91400",
    "sg:province":"Ile de France",
    "sg:tags":[
        "agriculture"
    ],
    "wof:name":"M. Bourgoin Lucien",
    "wof:placetype":"venue"
},
  "geometry": {"coordinates":[2.172856,48.714882],"type":"Point"}
}