{
  "type": "Feature",
  "properties": {
    "addr:full":"62 rue Fran\u00e7ois 1er 75008 Paris Ile de France 75008",
    "addr:housenumber":"62",
    "addr:postcode":"75008;75008",
    "addr:street":"Rue Franc\u0327Ois 1Er",
    "iso:country":"FR",
    "sg:address":"62 rue Fran\u00e7ois 1er 75008 Paris",
    "sg:classifiers":[
        {
            "category":"Professional",
            "subcategory":"Business Services",
            "type":"Services"
        }
    ],
    "sg:phone":"+33 1 40 75 08 02",
    "sg:postcode":"75008",
    "sg:province":"Ile de France",
    "sg:tags":[
        "industrial",
        "export"
    ],
    "wof:name":"Tasc Internat Trade Assistance Sce Const Sa",
    "wof:placetype":"venue"
},
  "geometry": {"coordinates":[2.302065,48.869843],"type":"Point"}
}