{
  "type": "Feature",
  "properties": {
    "iso:country":"FR",
    "sg:address":"62 rue Fran\u00e7ois 1er 75008 Paris",
    "sg:classifiers":[
        {
            "category":"Professional",
            "subcategory":"Business Services",
            "type":"Services"
        }
    ],
    "sg:phone":"+33 1 40 75 08 02",
    "sg:postcode":"75008",
    "sg:province":"Ile de France",
    "sg:tags":[
        "industrial",
        "export"
    ],
    "wof:name":"Tasc Internat Trade Assistance Sce Const Sa",
    "wof:placetype":"venue"
},
  "geometry": {"coordinates":[2.302065,48.869843],"type":"Point"}
}