{
  "type": "Feature",
  "properties": {
    "addr:full":"33, Rue du 49\u00e8me BCA, 80290 Cauli\u00e8res Picardie 80290",
    "addr:housenumber":"33",
    "addr:postcode":"80290;80290",
    "addr:street":"Rue Du 49E\u0300Me Bca;Picardie",
    "iso:country":"FR",
    "sg:address":"33, Rue du 49\u00e8me BCA, 80290 Cauli\u00e8res",
    "sg:orig_category":"Bennes agricoles Bennes travaux publics B\u00e9taill\u00e8res Epandeurs Epandeurs de fumier M\u00e9cano-soudure Pla",
    "sg:phone":"+33 3 22 38 01 77",
    "sg:postcode":"80290",
    "sg:province":"Picardie",
    "wof:name":"Dangreville S.a.",
    "wof:placetype":"venue"
},
  "geometry": {"coordinates":[1.884268,49.778179],"type":"Point"}
}