{
  "type": "Feature",
  "properties": {
    "addr:full":"Zac Alex 74290 Alex Rhone-Alpes",
    "addr:postcode":"74290",
    "addr:street":"Zac Alex",
    "iso:country":"FR",
    "sg:address":"Zac Alex 74290 Alex",
    "sg:classifiers":[
        {
            "category":"Home & Garden",
            "subcategory":"Furniture",
            "type":"Retail Goods"
        }
    ],
    "sg:phone":"+33 4 50 02 85 28",
    "sg:province":"Rhone-Alpes",
    "sg:tags":[
        "wood"
    ],
    "wof:name":"Ste Technique Impregnation Par Injection",
    "wof:placetype":"venue"
},
  "geometry": {"coordinates":[6.237596,45.889404],"type":"Point"}
}