{
  "type": "Feature",
  "properties": {
    "iso:country":"FR",
    "sg:address":"1, Rue Thomas Edison, 67450 Mundolsheim",
    "sg:city":"Mundolsheim",
    "sg:orig_category":"Unclassifiable Establishments",
    "sg:phone":"+33 3 88 18 28 38",
    "sg:postcode":"67450",
    "sg:province":"Alsace",
    "wof:name":"R.c.s.",
    "wof:placetype":"venue"
},
  "geometry": {"coordinates":[7.726815,48.64175],"type":"Point"}
}