{
  "type": "Feature",
  "properties": {
    "addr:full":"B.P. 75, 88210 Senones^^20, Rue de la D\u00e9portation, 88210 Senones Lorraine",
    "addr:postcode":"88210;88210",
    "addr:street":"B.P. 75;Rue De La De\u0301Portation",
    "iso:country":"FR",
    "sg:address":"B.P. 75, 88210 Senones^^20, Rue de la D\u00e9portation, 88210 Senones",
    "sg:orig_category":"Non-Classified Establishments",
    "sg:phone":"+33 3 29 57 63 20",
    "sg:province":"Lorraine",
    "wof:name":"S.m.i. S.a.r.l.",
    "wof:placetype":"venue"
},
  "geometry": {"coordinates":[6.979165,48.3946],"type":"Point"}
}