{
  "type": "Feature",
  "properties": {
    "iso:country":"FR",
    "sg:address":"33, Av. du G\u00e9n\u00e9ral Leclerc, 92260 Fontenay aux Roses",
    "sg:orig_category":"Unclassifiable Establishments",
    "sg:phone":"+33 1 40 95 63 54",
    "sg:province":"Ile de France",
    "wof:name":"G-med G.i.e. - Groupement Pour L'evaluation Des Dispositifs M\u00e9dicaux",
    "wof:placetype":"venue"
},
  "geometry": {"coordinates":[2.273684,48.793095],"type":"Point"}
}