{
  "type": "Feature",
  "properties": {
    "addr:full":"30, Rue de la Lib\u00e9ration, 54450 B\u00e9nam\u00e9nil Lorraine",
    "addr:housenumber":"30",
    "addr:postcode":"54450",
    "addr:street":"Rue De La Libe\u0301Ration",
    "iso:country":"FR",
    "sg:address":"30, Rue de la Lib\u00e9ration, 54450 B\u00e9nam\u00e9nil",
    "sg:orig_category":"Unclassifiable Establishments",
    "sg:phone":"+33 3 83 71 10 60",
    "sg:province":"Lorraine",
    "wof:name":"Claudin Fr\u00e8res S.a.r.l.",
    "wof:placetype":"venue"
},
  "geometry": {"coordinates":[6.667194,48.57132],"type":"Point"}
}