{
  "type": "Feature",
  "properties": {
    "addr:full":"Rue De L'Ambassadeur BP 8 78860 Conflans Ste Honorine Ile de France 78860",
    "addr:postcode":"78860;78860",
    "addr:street":"Rue De;Bp 8;Ste Honorine Ile De France",
    "iso:country":"FR",
    "sg:address":"Rue De L'Ambassadeur BP 8 78860 Conflans Ste Honorine",
    "sg:classifiers":[
        {
            "category":"Manufacturing",
            "subcategory":"Metals",
            "type":"Manufacturing & Wholesale Goods"
        }
    ],
    "sg:phone":"+33 1 34 90 40 54",
    "sg:postcode":"78860",
    "sg:province":"Ile de France",
    "sg:tags":[
        "-",
        "machine",
        "equipment",
        "engineering",
        "machinery",
        "mechanical"
    ],
    "wof:name":"Diamant Winter France Sa",
    "wof:placetype":"venue"
},
  "geometry": {"coordinates":[2.11216,49.008583],"type":"Point"}
}