{
  "type": "Feature",
  "properties": {
    "addr:full":"140, Bd F\u00e9lix Faure, 93301 Aubervilliers C\u00e9dex Basse Normandie",
    "addr:housenumber":"140",
    "addr:postcode":"93301",
    "addr:street":"Bd Fe\u0301Lix Faure",
    "iso:country":"FR",
    "sg:address":"140, Bd F\u00e9lix Faure, 93301 Aubervilliers C\u00e9dex",
    "sg:orig_category":"Non-Classified Establishments",
    "sg:phone":"+33 1 43 52 11 40",
    "sg:province":"Basse Normandie",
    "wof:name":"R\u00e9nov' Cuves S.a.",
    "wof:placetype":"venue"
},
  "geometry": {"coordinates":[2.377427,48.90947],"type":"Point"}
}