{
  "type": "Feature",
  "properties": {
    "addr:full":"Zone Activit\u00e9 L\u00e9g\u00e8re Bruay la Buissi\u00e8re Nord Pas-de-Calais 62700",
    "addr:postcode":"62700",
    "addr:street":"Zone Activite\u0301 Le\u0301Ge\u0300Re Bruay La",
    "iso:country":"FR",
    "sg:address":"Zone Activit\u00e9 L\u00e9g\u00e8re",
    "sg:city":"Bruay la Buissi\u00e8re",
    "sg:orig_category":"Unclassifiable Establishments",
    "sg:phone":"+33 3 21 61 47 73",
    "sg:postcode":"62700",
    "sg:province":"Nord Pas-de-Calais",
    "wof:name":"Dezelus S.a.",
    "wof:placetype":"venue"
},
  "geometry": {"coordinates":[2.545135,50.482071],"type":"Point"}
}