{
  "type": "Feature",
  "properties": {
    "addr:full":"Quartier Saint Romain Salernes Basse Normandie 83690",
    "addr:postcode":"83690",
    "addr:street":"Basse",
    "iso:country":"FR",
    "sg:address":"Quartier Saint Romain",
    "sg:city":"Salernes",
    "sg:orig_category":"Unclassifiable Establishments",
    "sg:phone":"+33 4 94 85 91 91",
    "sg:postcode":"83690",
    "sg:province":"Basse Normandie",
    "wof:name":"Mat\u00e9riaux Esberard S.a.r.l.",
    "wof:placetype":"venue"
},
  "geometry": {"coordinates":[6.25249,43.560066],"type":"Point"}
}