{
  "type": "Feature",
  "properties": {
    "iso:country":"FR",
    "sg:address":"Rue Paquette BP 80 62903 Coquelles Cedex",
    "sg:city":"Coquelles",
    "sg:classifiers":[
        {
            "category":"Shopping",
            "subcategory":"Crafts & Fabrics",
            "type":"Retail Goods"
        }
    ],
    "sg:phone":"+33 3 21 46 01 40",
    "sg:postcode":"62231",
    "sg:province":"Nord Pas-de-Calais",
    "sg:tags":[
        "textile",
        "clothing"
    ],
    "wof:name":"Ets Gustave Brunet Sa",
    "wof:placetype":"venue"
},
  "geometry": {"coordinates":[1.855281,50.926262],"type":"Point"}
}