{
  "type": "Feature",
  "properties": {
    "addr:full":"17, Rue Gutenberg - ZA, 67610 La Wantzenau La Wantzenau Alsace 67610",
    "addr:housenumber":"17",
    "addr:postcode":"67610;67610",
    "addr:street":"Rue Gutenberg Za;Wantzenau",
    "iso:country":"FR",
    "sg:address":"17, Rue Gutenberg - ZA, 67610 La Wantzenau",
    "sg:city":"La Wantzenau",
    "sg:orig_category":"Non-Classified Establishments",
    "sg:phone":"+33 3 88 96 66 77",
    "sg:postcode":"67610",
    "sg:province":"Alsace",
    "wof:name":"H.b.c. Radiomatic France S.a.r.l.",
    "wof:placetype":"venue"
},
  "geometry": {"coordinates":[7.825742,48.65926],"type":"Point"}
}