{
  "type": "Feature",
  "properties": {
    "addr:full":"3, Rue de Paris - Cesson S\u00e9vign\u00e9 , 35090 Rennes Brittany",
    "addr:housenumber":"3",
    "addr:postcode":"35090",
    "addr:street":"Rue De Paris",
    "iso:country":"FR",
    "sg:address":"3, Rue de Paris - Cesson S\u00e9vign\u00e9 , 35090 Rennes",
    "sg:orig_category":"Unclassifiable Establishments",
    "sg:phone":"+33 2 99 83 56 15",
    "sg:province":"Brittany",
    "wof:name":"Cr\u00e9dit Lyonnais",
    "wof:placetype":"venue"
},
  "geometry": {"coordinates":[-1.71851,48.067379],"type":"Point"}
}