{
  "type": "Feature",
  "properties": {
    "addr:full":"15, Av des Paraboles - Euroteleport, 59100 Roubaix Nord Pas-de-Calais",
    "addr:postcode":"59100",
    "addr:street":"15 Av Des Paraboles Euroteleport",
    "iso:country":"FR",
    "sg:address":"15, Av des Paraboles - Euroteleport, 59100 Roubaix",
    "sg:orig_category":"Unclassifiable Establishments",
    "sg:phone":"+33 3 20 99 60 60",
    "sg:province":"Nord Pas-de-Calais",
    "wof:name":"Les Fils De Louis Mulliez S.a.",
    "wof:placetype":"venue"
},
  "geometry": {"coordinates":[3.1752,50.691704],"type":"Point"}
}