{
  "type": "Feature",
  "properties": {
    "addr:full":"119 Rue Du Dauphine 69800 St Priest Rhone-Alpes 69800",
    "addr:housenumber":"119",
    "addr:postcode":"69800;69800",
    "addr:street":"Rue Du Dauphine",
    "iso:country":"FR",
    "sg:address":"119 Rue Du Dauphine 69800 St Priest",
    "sg:classifiers":[
        {
            "category":"Autos & Motor Vehicles",
            "subcategory":"Automobile Sales",
            "type":"Retail Goods"
        }
    ],
    "sg:phone":"+33 4 72 96 51 11",
    "sg:postcode":"69800",
    "sg:province":"Rhone-Alpes",
    "sg:tags":[
        "equipment",
        "industrial",
        "transport"
    ],
    "wof:name":"Renault Vi (rvi)",
    "wof:placetype":"venue"
},
  "geometry": {"coordinates":[4.90921,45.717789],"type":"Point"}
}