{
  "type": "Feature",
  "properties": {
    "addr:full":"Les Souchers 24400 St Laurent Des Hommes Les L\u00e8ches Aquitaine 24400",
    "addr:housenumber":"le\u0300ches",
    "addr:postcode":"24400;24400",
    "addr:street":"St Laurent Des Hommes Les",
    "iso:country":"FR",
    "sg:address":"Les Souchers 24400 St Laurent Des Hommes",
    "sg:city":"Les L\u00e8ches",
    "sg:classifiers":[
        {
            "category":"Wholesale",
            "subcategory":"Farm Supplies",
            "type":"Manufacturing & Wholesale Goods"
        }
    ],
    "sg:phone":"+33 5 53 81 71 89",
    "sg:postcode":"24400",
    "sg:province":"Aquitaine",
    "sg:tags":[
        "-",
        "machine",
        "equipment",
        "engineering",
        "machinery",
        "mechanical",
        "agriculture"
    ],
    "wof:name":"Chambon Sa",
    "wof:placetype":"venue"
},
  "geometry": {"coordinates":[0.282055,45.019958],"type":"Point"}
}