{
  "type": "Feature",
  "properties": {
    "iso:country":"FR",
    "sg:address":"Rougent 35430 Saint P\u00e8re",
    "sg:city":"La Ville-\u00e8s-Nonais",
    "sg:orig_category":"Non-Classified Establishments",
    "sg:phone":"+33 2 99 58 38 39",
    "sg:postcode":"35430",
    "sg:province":"Bretagne",
    "wof:name":"Rondin Yvette",
    "wof:placetype":"venue"
},
  "geometry": {"coordinates":[-1.937836,48.579105],"type":"Point"}
}