{
  "type": "Feature",
  "properties": {
    "addr:full":"17, Rue Champeau - Cap Nord, 21850 Saint Apollinaire Saint-Apollinaire Bourgogne 21850",
    "addr:housenumber":"17",
    "addr:postcode":"21850;21850",
    "addr:street":"Rue Champeau Cap Nord",
    "iso:country":"FR",
    "sg:address":"17, Rue Champeau - Cap Nord, 21850 Saint Apollinaire",
    "sg:city":"Saint-Apollinaire",
    "sg:orig_category":"Unclassifiable Establishments",
    "sg:phone":"+33 3 80 73 47 21",
    "sg:postcode":"21850",
    "sg:province":"Bourgogne",
    "wof:name":"Loxam S.a.",
    "wof:placetype":"venue"
},
  "geometry": {"coordinates":[5.070531,47.343452],"type":"Point"}
}