{
  "type": "Feature",
  "properties": {
    "addr:full":"Le Puymaret 19360 Malemort sur Corr\u00e8ze Limousin",
    "addr:postcode":"19360",
    "iso:country":"FR",
    "sg:address":"Le Puymaret 19360 Malemort sur Corr\u00e8ze",
    "sg:orig_category":"Unclassifiable Establishments",
    "sg:phone":"+33 5 55 92 90 90",
    "sg:province":"Limousin",
    "wof:name":"Dubois Et Associ\u00e9s S.a.",
    "wof:placetype":"venue"
},
  "geometry": {"coordinates":[1.586165,45.180634],"type":"Point"}
}