{
  "type": "Feature",
  "properties": {
    "iso:country":"FR",
    "sg:address":"35ter, Av des Alli\u00e9s, 51000 Ch\u00e2lons en Champagne",
    "sg:orig_category":"Unclassifiable Establishments",
    "sg:phone":"+33 3 26 68 56 11",
    "sg:province":"Champagne",
    "wof:name":"Op\u00e9 Ratio S.a.",
    "wof:placetype":"venue"
},
  "geometry": {"coordinates":[4.376576,48.944386],"type":"Point"}
}