{
  "type": "Feature",
  "properties": {
    "addr:full":"Rerafay 71580 Frontenaud Frontenaud Bourgogne 71580",
    "addr:postcode":"71580;71580",
    "addr:street":"Rerafay",
    "iso:country":"FR",
    "sg:address":"Rerafay 71580 Frontenaud",
    "sg:city":"Frontenaud",
    "sg:classifiers":[
        {
            "category":"Home & Garden",
            "subcategory":"Furniture",
            "type":"Retail Goods"
        }
    ],
    "sg:phone":"+33 3 85 60 40 20",
    "sg:postcode":"71580",
    "sg:province":"Bourgogne",
    "sg:tags":[
        "wood"
    ],
    "wof:name":"Ets Rene Lacroix Et Cie Sa",
    "wof:placetype":"venue"
},
  "geometry": {"coordinates":[5.29212,46.55772],"type":"Point"}
}