{
  "type": "Feature",
  "properties": {
    "iso:country":"FR",
    "sg:address":"Rue de Mouillepied - ZI Canal des Soeurs",
    "sg:city":"Rochefort",
    "sg:orig_category":"Unclassifiable Establishments",
    "sg:phone":"+33 5 46 82 15 00",
    "sg:postcode":"17300",
    "sg:province":"Poitou-Charentes",
    "wof:name":"Sotrap S.a.",
    "wof:placetype":"venue"
},
  "geometry": {"coordinates":[-0.958704,45.934818],"type":"Point"}
}