{
  "type": "Feature",
  "properties": {
    "iso:country":"FR",
    "sg:address":"6, Rue du Conservatoire, 75009 Paris",
    "sg:orig_category":"Non-Classified Establishments",
    "sg:phone":"+33 1 44 83 60 60",
    "sg:postcode":"75009",
    "sg:province":"Ile de France",
    "wof:name":"Charter Multim\u00e9dia S.a.r.l.",
    "wof:placetype":"venue"
},
  "geometry": {"coordinates":[2.34708,48.873463],"type":"Point"}
}