{
  "type": "Feature",
  "properties": {
    "addr:full":"14 rue Paul Mespl\u00e9 31100 Toulouse Midi Pyr\u00e9n\u00e9es 31100",
    "addr:housenumber":"14",
    "addr:postcode":"31100;31100",
    "addr:street":"Rue Paul Mesple\u0301",
    "iso:country":"FR",
    "sg:address":"14 rue Paul Mespl\u00e9 31100 Toulouse",
    "sg:classifiers":[
        {
            "category":"Shopping",
            "subcategory":"Computers & Home Electronics",
            "type":"Retail Goods"
        }
    ],
    "sg:phone":"+33 5 34 61 10 00",
    "sg:postcode":"31100",
    "sg:province":"Midi Pyr\u00e9n\u00e9es",
    "sg:tags":[
        "electronic",
        "module"
    ],
    "wof:name":"Scg France Sas",
    "wof:placetype":"venue"
},
  "geometry": {"coordinates":[1.386916,43.572044],"type":"Point"}
}