{
  "type": "Feature",
  "properties": {
    "addr:full":"120 Av Edouard Branly 89400 Migennes Migennes Bourgogne 89400",
    "addr:postcode":"89400;89400",
    "addr:street":"120 Av Edouard Branly",
    "iso:country":"FR",
    "sg:address":"120 Av Edouard Branly 89400 Migennes",
    "sg:city":"Migennes",
    "sg:classifiers":[
        {
            "category":"Building & Trades",
            "subcategory":"Construction",
            "type":"Services"
        }
    ],
    "sg:phone":"+33 3 86 80 17 23",
    "sg:postcode":"89400",
    "sg:province":"Bourgogne",
    "sg:tags":[
        "work",
        "public"
    ],
    "wof:name":"Scr Bourgogne",
    "wof:placetype":"venue"
},
  "geometry": {"coordinates":[3.535047,47.969158],"type":"Point"}
}