{
  "type": "Feature",
  "properties": {
    "addr:full":"Avenue Andre Maurois 24310 Brantome Brant\u00f4me Aquitaine 24310",
    "addr:postcode":"24310;24310",
    "addr:street":"Avenue Andre Maurois",
    "iso:country":"FR",
    "sg:address":"Avenue Andre Maurois 24310 Brantome",
    "sg:city":"Brant\u00f4me",
    "sg:classifiers":[
        {
            "category":"Manufacturing",
            "subcategory":"Printing",
            "type":"Manufacturing & Wholesale Goods"
        }
    ],
    "sg:phone":"+33 5 53 45 40 50",
    "sg:postcode":"24310",
    "sg:province":"Aquitaine",
    "sg:tags":[
        "publishing"
    ],
    "wof:name":"Euroflash Impression Sa",
    "wof:placetype":"venue"
},
  "geometry": {"coordinates":[0.66317,45.360561],"type":"Point"}
}