{
  "type": "Feature",
  "properties": {
    "iso:country":"FR",
    "sg:address":"126 boulevard Victor Hugo 92110 Clichy",
    "sg:orig_category":"Adhesives Glue For Plastics",
    "sg:phone":"+33 1 55 21 03 50",
    "sg:postcode":"92110",
    "sg:province":"Ile de France",
    "wof:name":"Eleco Produits Sa",
    "wof:placetype":"venue"
},
  "geometry": {"coordinates":[2.318873,48.902477],"type":"Point"}
}