{
  "type": "Feature",
  "properties": {
    "addr:full":"10 Place De La Bourse 75002 Paris Ile de France",
    "addr:housenumber":"10",
    "addr:postcode":"75002",
    "addr:street":"Place De La Bourse",
    "iso:country":"FR",
    "sg:address":"10 Place De La Bourse 75002 Paris",
    "sg:classifiers":[
        {
            "category":"Professional",
            "subcategory":"Printing & Photocopies",
            "type":"Services"
        }
    ],
    "sg:phone":"+33 1 44 88 35 00",
    "sg:province":"Ile de France",
    "sg:tags":[
        "publishing"
    ],
    "wof:name":"Photocomposition Herold",
    "wof:placetype":"venue"
},
  "geometry": {"coordinates":[2.341099,48.86982],"type":"Point"}
}