{
  "type": "Feature",
  "properties": {
    "addr:full":"La Beaurie 16210 Chalais Poitou-Charentes",
    "addr:postcode":"16210",
    "iso:country":"FR",
    "sg:address":"La Beaurie 16210 Chalais",
    "sg:orig_category":"Unclassifiable Establishments",
    "sg:phone":"+33 5 45 98 21 18",
    "sg:province":"Poitou-Charentes",
    "wof:name":"Etablissements Jean Chambon S.a.",
    "wof:placetype":"venue"
},
  "geometry": {"coordinates":[0.042746,45.293816],"type":"Point"}
}