{
  "type": "Feature",
  "properties": {
    "addr:full":"83, Rue Dulong, 75017 Paris Ile de France",
    "addr:housenumber":"83",
    "addr:postcode":"75017",
    "addr:street":"Rue Dulong",
    "iso:country":"FR",
    "sg:address":"83, Rue Dulong, 75017 Paris",
    "sg:orig_category":"Unclassifiable Establishments",
    "sg:phone":"+33 1 42 27 73 31",
    "sg:province":"Ile de France",
    "wof:name":"S.d.e. S.a.r.l.",
    "wof:placetype":"venue"
},
  "geometry": {"coordinates":[2.31423,48.886707],"type":"Point"}
}