{
  "type": "Feature",
  "properties": {
    "iso:country":"FR",
    "sg:address":"31, Av. Jean Fran\u00e7ois Champollion, 31100 Toulouse",
    "sg:orig_category":"Unclassifiable Establishments",
    "sg:phone":"+33 5 61 43 65 65",
    "sg:province":"Midi Pyr\u00e9n\u00e9es",
    "wof:name":"S.s.t.i. S.a.r.l. - Solutions Statistiques Travail Informatique",
    "wof:placetype":"venue"
},
  "geometry": {"coordinates":[1.395019,43.546959],"type":"Point"}
}