{
  "type": "Feature",
  "properties": {
    "addr:full":"Domaine Universitaire de Saint Martin d'H\u00e8res 38000 Grenoble Rhone-Alpes 38000",
    "addr:postcode":"38000;38000",
    "addr:street":"Martin D'He \u0300Res",
    "iso:country":"FR",
    "sg:address":"Domaine Universitaire de Saint Martin d'H\u00e8res 38000 Grenoble",
    "sg:orig_category":"Unclassifiable Establishments",
    "sg:phone":"+33 4 76 82 56 51",
    "sg:postcode":"38000",
    "sg:province":"Rhone-Alpes",
    "wof:name":"Presses Universitaires De Grenoble",
    "wof:placetype":"venue"
},
  "geometry": {"coordinates":[5.794381,45.221058],"type":"Point"}
}