{
  "type": "Feature",
  "properties": {
    "addr:full":"L'Embranchement 14490 Montfiquet Montfiquet Basse Normandie 14490",
    "addr:postcode":"14490;14490",
    "addr:street":"L'Embranchement",
    "iso:country":"FR",
    "sg:address":"L'Embranchement 14490 Montfiquet",
    "sg:city":"Montfiquet",
    "sg:classifiers":[
        {
            "category":"Professional",
            "subcategory":"Business Services",
            "type":"Services"
        }
    ],
    "sg:phone":"+33 2 31 21 39 78",
    "sg:postcode":"14490",
    "sg:province":"Basse Normandie",
    "sg:tags":[
        "travel",
        "fair"
    ],
    "wof:name":"Le Relais De La Foret (hotel Restaurant)",
    "wof:placetype":"venue"
},
  "geometry": {"coordinates":[-0.864508,49.192524],"type":"Point"}
}