{
  "type": "Feature",
  "properties": {
    "iso:country":"FR",
    "sg:address":"Chemin de Sury",
    "sg:city":"Warcq",
    "sg:orig_category":"Unclassifiable Establishments",
    "sg:phone":"+33 3 24 56 57 80",
    "sg:postcode":"08000",
    "sg:province":"Champagne",
    "wof:name":"Bemaco - B\u00e9ton Mat\u00e9riaux De Construction S.n.c.",
    "wof:placetype":"venue"
},
  "geometry": {"coordinates":[4.663647,49.768665],"type":"Point"}
}