{
  "type": "Feature",
  "properties": {
    "addr:full":"1 Rue De Surcouf 33300 Bordeaux Bordeaux Aquitaine 33300",
    "addr:housenumber":"1",
    "addr:postcode":"33300;33300",
    "addr:street":"Rue De Surcouf",
    "iso:country":"FR",
    "sg:address":"1 Rue De Surcouf 33300 Bordeaux",
    "sg:city":"Bordeaux",
    "sg:classifiers":[
        {
            "category":"Banks & Credit Unions",
            "subcategory":"Investment Brokerage",
            "type":"Services"
        }
    ],
    "sg:phone":"+33 5 56 11 84 00",
    "sg:postcode":"33300",
    "sg:province":"Aquitaine",
    "sg:tags":[
        "-",
        "transport",
        "related"
    ],
    "wof:name":"Mory Team",
    "wof:placetype":"venue"
},
  "geometry": {"coordinates":[-0.556684,44.877514],"type":"Point"}
}