{
  "type": "Feature",
  "properties": {
    "addr:full":"280, Av. de la Marne, 59700 Marcq en Baroeul Nord Pas-de-Calais",
    "addr:housenumber":"280",
    "addr:postcode":"59700",
    "addr:street":"Av. De La Marne;En Baroeul Nord",
    "iso:country":"FR",
    "sg:address":"280, Av. de la Marne, 59700 Marcq en Baroeul",
    "sg:orig_category":"Unclassifiable Establishments",
    "sg:phone":"+33 3 20 65 04 50",
    "sg:province":"Nord Pas-de-Calais",
    "wof:name":"Renson France S.a.",
    "wof:placetype":"venue"
},
  "geometry": {"coordinates":[3.111601,50.677078],"type":"Point"}
}