{
  "type": "Feature",
  "properties": {
    "iso:country":"FR",
    "sg:address":"9 R Du Couchant 51400 Mourmelon Le Grand",
    "sg:classifiers":[
        {
            "category":"Professional",
            "type":"Services"
        }
    ],
    "sg:phone":"+33 3 26 66 02 65",
    "sg:province":"Champagne",
    "sg:tags":[
        "transport",
        "road"
    ],
    "wof:name":"Tradeco Sa",
    "wof:placetype":"venue"
},
  "geometry": {"coordinates":[4.359985,49.135658],"type":"Point"}
}