{
  "type": "Feature",
  "properties": {
    "iso:country":"FR",
    "sg:address":"Domaine de Sansaric",
    "sg:city":"Castres Gironde",
    "sg:orig_category":"Unclassifiable Establishments",
    "sg:phone":"+33 5 56 67 03 17",
    "sg:postcode":"33640",
    "sg:province":"Aquitaine",
    "wof:name":"Abadie Dominique",
    "wof:placetype":"venue"
},
  "geometry": {"coordinates":[-0.402069,44.679958],"type":"Point"}
}