{
  "type": "Feature",
  "properties": {
    "addr:full":"47, Rue Jules Verne - ZI du Br\u00e9zet, 63000 Clermont Ferrand Clermont-Ferrand Auvergne 63000",
    "addr:housenumber":"47",
    "addr:postcode":"63000;63000",
    "addr:street":"Rue Jules Verne Zi Du Bre\u0301Zet",
    "iso:country":"FR",
    "sg:address":"47, Rue Jules Verne - ZI du Br\u00e9zet, 63000 Clermont Ferrand",
    "sg:city":"Clermont-Ferrand",
    "sg:orig_category":"Unclassifiable Establishments",
    "sg:phone":"+33 4 73 41 18 18",
    "sg:postcode":"63000",
    "sg:province":"Auvergne",
    "wof:name":"Soci\u00e9t\u00e9 R\u00e9gionale Des Prestations Du Sud Ouest S.a.",
    "wof:placetype":"venue"
},
  "geometry": {"coordinates":[3.08183,45.777618],"type":"Point"}
}