{
  "type": "Feature",
  "properties": {
    "addr:full":"48 Rue Gisors 60590 Flavacourt Picardie 60590",
    "addr:housenumber":"48",
    "addr:postcode":"60590;60590",
    "addr:street":"Rue Gisors",
    "iso:country":"FR",
    "sg:address":"48 Rue Gisors 60590 Flavacourt",
    "sg:classifiers":[
        {
            "category":"Wholesale",
            "subcategory":"Machinery & Supplies",
            "type":"Manufacturing & Wholesale Goods"
        }
    ],
    "sg:phone":"+33 3 44 84 85 67",
    "sg:postcode":"60590",
    "sg:province":"Picardie",
    "sg:tags":[
        "handling",
        "material",
        "-",
        "machine",
        "equipment",
        "engineering",
        "mechanical"
    ],
    "wof:name":"Sercap Sarl",
    "wof:placetype":"venue"
},
  "geometry": {"coordinates":[1.823212,49.336586],"type":"Point"}
}