{
  "type": "Feature",
  "properties": {
    "iso:country":"FR",
    "sg:address":"1 Pl De L'Energie 67580 Mertzwiller",
    "sg:city":"Mertzwiller",
    "sg:classifiers":[
        {
            "category":"Building & Trades",
            "subcategory":"Construction",
            "type":"Services"
        }
    ],
    "sg:phone":"+33 3 88 90 19 60",
    "sg:postcode":"67580",
    "sg:province":"Alsace",
    "sg:tags":[
        "work",
        "public"
    ],
    "wof:name":"Colas Est",
    "wof:placetype":"venue"
},
  "geometry": {"coordinates":[7.67936,48.862591],"type":"Point"}
}