{
  "type": "Feature",
  "properties": {
    "addr:full":"23, Rue Louis le Grand, 75002 Paris Ile de France",
    "addr:housenumber":"23",
    "addr:postcode":"75002",
    "addr:street":"Rue Louis",
    "iso:country":"FR",
    "sg:address":"23, Rue Louis le Grand, 75002 Paris",
    "sg:orig_category":"Unclassifiable Establishments",
    "sg:phone":"+33 1 47 42 41 89",
    "sg:province":"Ile de France",
    "wof:name":"Guigou S.a.",
    "wof:placetype":"venue"
},
  "geometry": {"coordinates":[2.333734,48.870373],"type":"Point"}
}