{
  "type": "Feature",
  "properties": {
    "addr:full":"14, Rue de Chez Dary, 16710 Saint Yrieix sur Charente Poitou-Charentes 16710",
    "addr:housenumber":"14",
    "addr:postcode":"16710;16710",
    "addr:street":"Rue De Chez Dary",
    "iso:country":"FR",
    "sg:address":"14, Rue de Chez Dary, 16710 Saint Yrieix sur Charente",
    "sg:orig_category":"Non-Classified Establishments",
    "sg:phone":"+33 5 45 92 68 35",
    "sg:postcode":"16710",
    "sg:province":"Poitou-Charentes",
    "wof:name":"Desbordes Et Fils G.a.e.c.",
    "wof:placetype":"venue"
},
  "geometry": {"coordinates":[0.139299,45.666195],"type":"Point"}
}