{
  "type": "Feature",
  "properties": {
    "addr:full":"Rte d'Entrecasteaux - Domaine de Camparnaud Carc\u00e8s Provence-Alpes-C\u00f4te d'Azur 83570",
    "addr:postcode":"83570",
    "addr:street":"Rte D'Entrecasteaux Domaine De Camparnaud Carce\u0300S",
    "iso:country":"FR",
    "sg:address":"Rte d'Entrecasteaux - Domaine de Camparnaud",
    "sg:city":"Carc\u00e8s",
    "sg:orig_category":"Unclassifiable Establishments",
    "sg:phone":"+33 4 94 04 59 46",
    "sg:postcode":"83570",
    "sg:province":"Provence-Alpes-C\u00f4te d'Azur",
    "wof:name":"Domaine De Camparnaud S.a.r.l.",
    "wof:placetype":"venue"
},
  "geometry": {"coordinates":[6.18201,43.475479],"type":"Point"}
}