{
  "type": "Feature",
  "properties": {
    "iso:country":"FR",
    "sg:address":"ZA Port Arthur",
    "sg:city":"Plum\u00e9liau",
    "sg:orig_category":"Unclassifiable Establishments",
    "sg:phone":"+33 2 97 51 80 12",
    "sg:postcode":"56930",
    "sg:province":"Bretagne",
    "wof:name":"S.b.c.e.a. S.a. - Soci\u00e9t\u00e9 Bretonne De Canalisations Eau Et Assainis",
    "wof:placetype":"venue"
},
  "geometry": {"coordinates":[-2.975894,47.959064],"type":"Point"}
}