{
  "type": "Feature",
  "properties": {
    "iso:country":"FR",
    "sg:address":"Le Moulin Trochard 77120 Mouroux",
    "sg:classifiers":[
        {
            "category":"Manufacturing",
            "subcategory":"Electronics",
            "type":"Manufacturing & Wholesale Goods"
        }
    ],
    "sg:phone":"+33 1 64 03 59 09",
    "sg:province":"Ile de France",
    "sg:tags":[
        "pcb",
        "printed",
        "circuit",
        "board"
    ],
    "wof:name":"Ste Technique Realisation Electronique S.a.r.l.",
    "wof:placetype":"venue"
},
  "geometry": {"coordinates":[3.074477,48.820889],"type":"Point"}
}