{
  "type": "Feature",
  "properties": {
    "addr:full":"Zone Industrielle 3 Avenue De La Deportation 26100 Romans Sur Is\u00e8re Rhone-Alpes 26100",
    "addr:housenumber":"3",
    "addr:postcode":"26100;26100",
    "addr:street":"Zone Industrielle;Avenue De La Deportation",
    "iso:country":"FR",
    "sg:address":"Zone Industrielle 3 Avenue De La Deportation 26100 Romans Sur Is\u00e8re",
    "sg:classifiers":[
        {
            "category":"Farming",
            "subcategory":"Farm & Veterinary Services",
            "type":"Manufacturing & Wholesale Goods"
        }
    ],
    "sg:phone":"+33 4 75 70 50 76",
    "sg:postcode":"26100",
    "sg:province":"Rhone-Alpes",
    "sg:tags":[
        "advice",
        "agriculture",
        "livestock",
        "business"
    ],
    "wof:name":"Scierie Exploitation Forestiere Blanc",
    "wof:placetype":"venue"
},
  "geometry": {"coordinates":[5.081882,45.050152],"type":"Point"}
}