{
  "type": "Feature",
  "properties": {
    "addr:full":"Rte d'Haussimont Mont\u00e9preux Champagne 51320",
    "addr:postcode":"51320",
    "addr:street":"Rte D'Haussimont;Champagne",
    "iso:country":"FR",
    "sg:address":"Rte d'Haussimont",
    "sg:city":"Mont\u00e9preux",
    "sg:orig_category":"Unclassifiable Establishments",
    "sg:phone":"+33 3 26 67 46 48",
    "sg:postcode":"51320",
    "sg:province":"Champagne",
    "wof:name":"A.p.m. D\u00e9shy - Union Coop\u00e9rative De D\u00e9shydratation",
    "wof:placetype":"venue"
},
  "geometry": {"coordinates":[4.452103,48.846039],"type":"Point"}
}