{
  "type": "Feature",
  "properties": {
    "iso:country":"FR",
    "sg:address":"ZA du Poteau",
    "sg:city":"Villiers Charlemagne",
    "sg:orig_category":"Non-Classified Establishments",
    "sg:phone":"+33 2 43 09 17 70",
    "sg:postcode":"53170",
    "sg:province":"Pays de Loire",
    "wof:name":"P\u00e9gaplast S.a.r.l.",
    "wof:placetype":"venue"
},
  "geometry": {"coordinates":[-0.676821,47.921799],"type":"Point"}
}