{
  "type": "Feature",
  "properties": {
    "addr:full":"3, Rue Saint Valentin, 59640 Dunkerque Nord-Pas-de-Calais",
    "addr:housenumber":"3",
    "addr:postcode":"59640",
    "addr:street":"Rue Saint Valentin",
    "iso:country":"FR",
    "sg:address":"3, Rue Saint Valentin, 59640 Dunkerque",
    "sg:orig_category":"Unclassifiable Establishments",
    "sg:phone":"+33 3 28 58 72 72",
    "sg:province":"Nord-Pas-de-Calais",
    "wof:name":"C\u00e9d\u00e9o Dunkerque D.s.c. S.a.",
    "wof:placetype":"venue"
},
  "geometry": {"coordinates":[2.354808,51.023426],"type":"Point"}
}