{
  "type": "Feature",
  "properties": {
    "addr:full":"48 rue G\u00e9n Delestraint 59580 Aniche Nord Pas-de-Calais",
    "addr:housenumber":"48",
    "addr:postcode":"59580",
    "addr:street":"Rue Ge\u0301N Delestraint",
    "iso:country":"FR",
    "sg:address":"48 rue G\u00e9n Delestraint 59580 Aniche",
    "sg:orig_category":"Optical Filters",
    "sg:phone":"+33 3 27 95 83 40",
    "sg:province":"Nord Pas-de-Calais",
    "wof:name":"Sicover Industries Sa",
    "wof:placetype":"venue"
},
  "geometry": {"coordinates":[3.253929,50.335594],"type":"Point"}
}