{
  "type": "Feature",
  "properties": {
    "addr:full":"7, Rue du Moulin Chevalier, 45490 Corbeilles Corbeilles Centre 45490",
    "addr:housenumber":"7;corbeilles",
    "addr:postcode":"45490;45490",
    "addr:street":"Rue Du Moulin Chevalier",
    "iso:country":"FR",
    "sg:address":"7, Rue du Moulin Chevalier, 45490 Corbeilles",
    "sg:city":"Corbeilles",
    "sg:orig_category":"Non-Classified Establishments",
    "sg:phone":"+33 2 38 96 42 98",
    "sg:postcode":"45490",
    "sg:province":"Centre",
    "wof:name":"L Et G Design Production S.a.r.l.",
    "wof:placetype":"venue"
},
  "geometry": {"coordinates":[2.541525,48.07777],"type":"Point"}
}