{
  "type": "Feature",
  "properties": {
    "addr:full":"Rte De Pommard 21200 Beaune Beaune Bourgogne 21200",
    "addr:postcode":"21200;21200",
    "addr:street":"Rte De Pommard",
    "iso:country":"FR",
    "sg:address":"Rte De Pommard 21200 Beaune",
    "sg:city":"Beaune",
    "sg:classifiers":[
        {
            "category":"Food Court",
            "type":"Food & Drink"
        }
    ],
    "sg:phone":"+33 3 80 25 01 00",
    "sg:postcode":"21200",
    "sg:province":"Bourgogne",
    "sg:tags":[
        "product",
        "related"
    ],
    "wof:name":"Caves Des Hautes Cotes",
    "wof:placetype":"venue"
},
  "geometry": {"coordinates":[4.820568,47.015862],"type":"Point"}
}