{
  "type": "Feature",
  "properties": {
    "iso:country":"FR",
    "sg:address":"rue de l'Alliere 14500 VIRE",
    "sg:city":"Vire",
    "sg:classifiers":[
        {
            "category":"Manufacturing",
            "subcategory":"Motor Vehicles & Parts",
            "type":"Manufacturing & Wholesale Goods"
        }
    ],
    "sg:phone":"+33 2 31 67 18 88",
    "sg:postcode":"14500",
    "sg:province":"Basse Normandie",
    "sg:tags":[
        "precision",
        "mechanic"
    ],
    "wof:name":"Mecanique Generale Anger S.a.r.l.",
    "wof:placetype":"venue"
},
  "geometry": {"coordinates":[-0.860282,48.854359],"type":"Point"}
}