{
  "type": "Feature",
  "properties": {
    "iso:country":"FR",
    "sg:address":"42 Av De Belgique 68110 Illzach",
    "sg:city":"Illzach",
    "sg:classifiers":[
        {
            "category":"Food Court",
            "type":"Food & Drink"
        }
    ],
    "sg:phone":"+33 3 89 61 77 74",
    "sg:postcode":"68110",
    "sg:province":"Alsace",
    "sg:tags":[
        "product",
        "related"
    ],
    "wof:name":"Musslin-tresch Sarl",
    "wof:placetype":"venue"
},
  "geometry": {"coordinates":[7.367216,47.767097],"type":"Point"}
}