{
  "type": "Feature",
  "properties": {
    "addr:full":"95 Rue De Cahors 59640 Dunkerque Midi Pyr\u00e9n\u00e9es",
    "addr:housenumber":"95",
    "addr:postcode":"59640",
    "addr:street":"Rue De Cahors",
    "iso:country":"FR",
    "sg:address":"95 Rue De Cahors 59640 Dunkerque",
    "sg:classifiers":[
        {
            "category":"Building & Trades",
            "subcategory":"Construction",
            "type":"Services"
        }
    ],
    "sg:phone":"+33 3 28 58 78 60",
    "sg:province":"Midi Pyr\u00e9n\u00e9es",
    "sg:tags":[
        "work",
        "public"
    ],
    "wof:name":"Tef",
    "wof:placetype":"venue"
},
  "geometry": {"coordinates":[2.356685,51.02174],"type":"Point"}
}