{
  "type": "Feature",
  "properties": {
    "iso:country":"FR",
    "sg:address":"20 chemin Boussey 27750 LA COUTURE BOUSSEY",
    "sg:classifiers":[
        {
            "category":"Manufacturing",
            "subcategory":"Motor Vehicles & Parts",
            "type":"Manufacturing & Wholesale Goods"
        }
    ],
    "sg:phone":"+33 2 32 36 75 40",
    "sg:province":"Haute Normandie",
    "sg:tags":[
        "precision",
        "mechanic"
    ],
    "wof:name":"Ets Martin-chanu S.a.",
    "wof:placetype":"venue"
},
  "geometry": {"coordinates":[1.397291,48.902763],"type":"Point"}
}