{
  "type": "Feature",
  "properties": {
    "addr:full":"Av. Michel Chevalier - ZI Bois de Grasse Grasse Poitou-Charentes 06130",
    "addr:postcode":"06130",
    "addr:street":"Av. Michel Chevalier Zi Bois De Grasse",
    "iso:country":"FR",
    "sg:address":"Av. Michel Chevalier - ZI Bois de Grasse",
    "sg:city":"Grasse",
    "sg:orig_category":"Non-Classified Establishments",
    "sg:phone":"+33 4 93 70 26 20",
    "sg:postcode":"06130",
    "sg:province":"Poitou-Charentes",
    "wof:name":"Oredui S.a.",
    "wof:placetype":"venue"
},
  "geometry": {"coordinates":[6.931647,43.649738],"type":"Point"}
}