{
  "type": "Feature",
  "properties": {
    "addr:full":"505 Rue Du Champ Moyen 54710 Fl\u00e9ville Devant Nancy Lorraine",
    "addr:housenumber":"505",
    "addr:postcode":"54710",
    "addr:street":"Rue Du Champ Moyen",
    "iso:country":"FR",
    "sg:address":"505 Rue Du Champ Moyen 54710 Fl\u00e9ville Devant Nancy",
    "sg:classifiers":[
        {
            "category":"Professional",
            "type":"Services"
        }
    ],
    "sg:phone":"+33 3 83 15 20 20",
    "sg:province":"Lorraine",
    "sg:tags":[
        "transport",
        "road"
    ],
    "wof:name":"Transports Georges Et Schmitt Sa",
    "wof:placetype":"venue"
},
  "geometry": {"coordinates":[6.210913,48.61689],"type":"Point"}
}