{
  "type": "Feature",
  "properties": {
    "addr:full":"1, Rue Victor Hugo - Immeuble Agora, 44400 R\u00e9z\u00e9 Pays de Loire",
    "addr:housenumber":"1",
    "addr:postcode":"44400",
    "addr:street":"Rue Victor Hugo Immeuble Agora;Re\u0301Ze\u0301",
    "iso:country":"FR",
    "sg:address":"1, Rue Victor Hugo - Immeuble Agora, 44400 R\u00e9z\u00e9",
    "sg:orig_category":"Unclassifiable Establishments",
    "sg:phone":"+33 2 28 00 00 18",
    "sg:province":"Pays de Loire",
    "wof:name":"Vid' Stock S.a.r.l.",
    "wof:placetype":"venue"
},
  "geometry": {"coordinates":[-1.561972,47.188759],"type":"Point"}
}