{
  "type": "Feature",
  "properties": {
    "iso:country":"FR",
    "sg:address":"17 Rue Fondary 75015 Paris",
    "sg:classifiers":[
        {
            "category":"Professional",
            "subcategory":"Advertising",
            "type":"Services"
        }
    ],
    "sg:phone":"+33 1 44 37 00 00",
    "sg:postcode":"75015",
    "sg:province":"Ile de France",
    "sg:tags":[
        "communication",
        "medium"
    ],
    "wof:name":"Quali Pige Sarl",
    "wof:placetype":"venue"
},
  "geometry": {"coordinates":[2.292388,48.848553],"type":"Point"}
}