{
  "type": "Feature",
  "properties": {
    "addr:full":"2500 Route De Jonquieres 30840 Meynes Languedoc-Roussillon 30840",
    "addr:housenumber":"2500",
    "addr:postcode":"30840;30840",
    "addr:street":"Route De Jonquieres",
    "iso:country":"FR",
    "sg:address":"2500 Route De Jonquieres 30840 Meynes",
    "sg:orig_category":"Miscellaneous Products",
    "sg:phone":"+33 4 66 57 24 57",
    "sg:postcode":"30840",
    "sg:province":"Languedoc-Roussillon",
    "wof:name":"Mc Racing",
    "wof:placetype":"venue"
},
  "geometry": {"coordinates":[4.55364,43.874989],"type":"Point"}
}