{
  "type": "Feature",
  "properties": {
    "iso:country":"FR",
    "sg:address":"2, Rue de l'Abattoir, 08700 Gespunsart",
    "sg:city":"Gespunsart",
    "sg:orig_category":"Non-Classified Establishments",
    "sg:phone":"+33 3 24 53 85 32",
    "sg:postcode":"08700",
    "sg:province":"Champagne",
    "wof:name":"Salle S.a.r.l.",
    "wof:placetype":"venue"
},
  "geometry": {"coordinates":[4.826826,49.817253],"type":"Point"}
}