{
  "type": "Feature",
  "properties": {
    "iso:country":"FR",
    "sg:address":"Rte de Chinon",
    "sg:city":"Jou\u00e9 l\u00e8s Tours",
    "sg:orig_category":"Non-Classified Establishments",
    "sg:phone":"+33 2 47 68 40 07",
    "sg:postcode":"37300",
    "sg:province":"Centre",
    "wof:name":"G\u00e9n\u00e9ral Incendie S.a.",
    "wof:placetype":"venue"
},
  "geometry": {"coordinates":[0.697725,47.355347],"type":"Point"}
}