{
  "type": "Feature",
  "properties": {
    "addr:full":"49, Av. Jean Zay, 93190 Livry Gargan Ile de France",
    "addr:postcode":"93190",
    "addr:street":"49 Av. Jean Zay",
    "iso:country":"FR",
    "sg:address":"49, Av. Jean Zay, 93190 Livry Gargan",
    "sg:orig_category":"Unclassifiable Establishments",
    "sg:phone":"+33 1 43 32 46 20",
    "sg:province":"Ile de France",
    "wof:name":"Jd Refendage S.a.r.l.",
    "wof:placetype":"venue"
},
  "geometry": {"coordinates":[2.537924,48.915211],"type":"Point"}
}