{
  "type": "Feature",
  "properties": {
    "iso:country":"FR",
    "sg:address":"10 Rue Des Raymonds 26220 Dieulefit",
    "sg:classifiers":[
        {
            "category":"Shopping",
            "subcategory":"Hobbies, Toys, & Games",
            "type":"Retail Goods"
        }
    ],
    "sg:phone":"+33 4 75 46 84 38",
    "sg:postcode":"26220",
    "sg:province":"Rhone-Alpes",
    "sg:tags":[
        "product",
        "miscellaneous",
        "entertainment"
    ],
    "wof:name":"Jff",
    "wof:placetype":"venue"
},
  "geometry": {"coordinates":[5.073505,44.519863],"type":"Point"}
}