{
  "type": "Feature",
  "properties": {
    "iso:country":"FR",
    "sg:address":"4-6 rue de Carriers 91350 Grigny",
    "sg:classifiers":[
        {
            "category":"Wholesale",
            "subcategory":"Metals & Minerals",
            "type":"Manufacturing & Wholesale Goods"
        }
    ],
    "sg:phone":"+33 1 69 02 44 00",
    "sg:postcode":"91350",
    "sg:province":"Ile de France",
    "sg:tags":[
        "ceiling"
    ],
    "wof:name":"Abcd Profils S.a.",
    "wof:placetype":"venue"
},
  "geometry": {"coordinates":[2.393095,48.653549],"type":"Point"}
}