{
  "type": "Feature",
  "properties": {
    "addr:full":"Rue Edmond Gosselin Parc Entreprises 62950 Noyelles Godault Nord Pas-de-Calais 62950",
    "addr:postcode":"62950;62950",
    "addr:street":"Rue Edmond Gosselin Parc Entreprises;Pas-De-Calais",
    "iso:country":"FR",
    "sg:address":"Rue Edmond Gosselin Parc Entreprises 62950 Noyelles Godault",
    "sg:classifiers":[
        {
            "category":"Autos & Motor Vehicles",
            "subcategory":"Automobile Sales",
            "type":"Retail Goods"
        }
    ],
    "sg:phone":"+33 3 91 83 02 20",
    "sg:postcode":"62950",
    "sg:province":"Nord Pas-de-Calais",
    "sg:tags":[
        "equipment",
        "motor-cars",
        "transport"
    ],
    "wof:name":"Seg",
    "wof:placetype":"venue"
},
  "geometry": {"coordinates":[2.99495,50.41996],"type":"Point"}
}