{
  "type": "Feature",
  "properties": {
    "addr:full":"19 Rue Du Bignon Zi Sud Est 35063 Rennes Cedex Bretagne",
    "addr:housenumber":"19",
    "addr:postcode":"35063",
    "addr:street":"Rue Du Bignon Zi Sud Est;Cedex",
    "iso:country":"FR",
    "sg:address":"19 Rue Du Bignon Zi Sud Est 35063 Rennes Cedex",
    "sg:classifiers":[
        {
            "category":"Utilities",
            "subcategory":"Telephone",
            "type":"Services"
        }
    ],
    "sg:phone":"+33 2 99 26 28 00",
    "sg:province":"Bretagne",
    "sg:tags":[
        "telecommunication"
    ],
    "wof:name":"Eads Telecom",
    "wof:placetype":"venue"
},
  "geometry": {"coordinates":[-1.67777,48.111721],"type":"Point"}
}