{
  "type": "Feature",
  "properties": {
    "addr:full":"4 Pl De Boston 14200 Herouville St. Clair H\u00e9rouville-Saint-Clair Basse Normandie 14200",
    "addr:housenumber":"4",
    "addr:postcode":"14200;14200",
    "addr:street":"Pl De Boston;Herouville",
    "iso:country":"FR",
    "sg:address":"4 Pl De Boston 14200 Herouville St. Clair",
    "sg:city":"H\u00e9rouville-Saint-Clair",
    "sg:classifiers":[
        {
            "category":"Wholesale",
            "subcategory":"Machinery & Supplies",
            "type":"Manufacturing & Wholesale Goods"
        }
    ],
    "sg:phone":"+33 2 31 06 13 31",
    "sg:postcode":"14200",
    "sg:province":"Basse Normandie",
    "sg:tags":[
        "handling",
        "material",
        "-",
        "machine",
        "equipment",
        "engineering",
        "mechanical"
    ],
    "wof:name":"Otis Sa",
    "wof:placetype":"venue"
},
  "geometry": {"coordinates":[-0.355925,49.212402],"type":"Point"}
}