{
  "type": "Feature",
  "properties": {
    "addr:full":"Domaine Chateau De Pechlatt 11220 LAGRASSE Languedoc-Roussillon 11220",
    "addr:postcode":"11220;11220",
    "addr:street":"Chateau",
    "iso:country":"FR",
    "sg:address":"Domaine Chateau De Pechlatt 11220 LAGRASSE",
    "sg:classifiers":[
        {
            "category":"Wholesale",
            "subcategory":"Wine & Distilled Alcoholic Beverages",
            "type":"Manufacturing & Wholesale Goods"
        }
    ],
    "sg:phone":"+33 4 68 58 11 40",
    "sg:postcode":"11220",
    "sg:province":"Languedoc-Roussillon",
    "sg:tags":[
        "french"
    ],
    "wof:name":"Ste Civile Chateau De Pechlatt Sc",
    "wof:placetype":"venue"
},
  "geometry": {"coordinates":[2.699812,43.084595],"type":"Point"}
}