{
  "type": "Feature",
  "properties": {
    "iso:country":"FR",
    "sg:address":"B.P. 84, 68260 Kingersheim^^58, Fbg de Mulhouse, 68260 Kingersheim",
    "sg:city":"Kingersheim",
    "sg:orig_category":"Non-Classified Establishments",
    "sg:phone":"+33 3 88 05 80 00",
    "sg:postcode":"68260",
    "sg:province":"Alsace",
    "wof:name":"Latuner S.a.",
    "wof:placetype":"venue"
},
  "geometry": {"coordinates":[7.335795,47.790257],"type":"Point"}
}