{
  "type": "Feature",
  "properties": {
    "addr:full":"386, Bd Henri Barnier, 13006 Marseille Poitou-Charentes",
    "addr:housenumber":"386",
    "addr:postcode":"13006",
    "addr:street":"Bd Henri Barnier",
    "iso:country":"FR",
    "sg:address":"386, Bd Henri Barnier, 13006 Marseille",
    "sg:orig_category":"Unclassifiable Establishments",
    "sg:phone":"+33 4 96 15 19 19",
    "sg:province":"Poitou-Charentes",
    "wof:name":"Ortec Environnement S.a.",
    "wof:placetype":"venue"
},
  "geometry": {"coordinates":[5.38324,43.290806],"type":"Point"}
}