{
  "type": "Feature",
  "properties": {
    "addr:full":"8, Rue de la Rose Rouge, 72320 Lamnay Pays de Loire",
    "addr:housenumber":"8",
    "addr:postcode":"72320",
    "addr:street":"Rue De La Rose Rouge",
    "iso:country":"FR",
    "sg:address":"8, Rue de la Rose Rouge, 72320 Lamnay",
    "sg:orig_category":"Unclassifiable Establishments",
    "sg:phone":"+33 2 43 93 23 09",
    "sg:province":"Pays de Loire",
    "wof:name":"Mat\u00e9riaux Pitois S.a.",
    "wof:placetype":"venue"
},
  "geometry": {"coordinates":[0.707385,48.116035],"type":"Point"}
}