{
  "type": "Feature",
  "properties": {
    "addr:full":"Za De La Plaine Du Caire Lotissement 16 13830 Roquefort La Bedoule Plaine Alsace 67420",
    "addr:housenumber":"16",
    "addr:postcode":"13830;67420",
    "addr:street":"Za De La Plaine Du Caire Lotissement",
    "iso:country":"FR",
    "sg:address":"Za De La Plaine Du Caire Lotissement 16 13830 Roquefort La Bedoule",
    "sg:city":"Plaine",
    "sg:classifiers":[
        {
            "category":"Professional",
            "subcategory":"Engineering",
            "type":"Services"
        }
    ],
    "sg:phone":"+33 4 42 73 12 56",
    "sg:postcode":"67420",
    "sg:province":"Alsace",
    "sg:tags":[
        "machine",
        "-",
        "mechanical"
    ],
    "wof:name":"Fadisferm",
    "wof:placetype":"venue"
},
  "geometry": {"coordinates":[5.589952,43.247658],"type":"Point"}
}