{
  "type": "Feature",
  "properties": {
    "addr:full":"12 av Henri Isnard; Vence Basse Normandie",
    "addr:street":"12 Av Henri Isnard;Basse Normandie",
    "iso:country":"FR",
    "sg:address":"12 av Henri Isnard; Vence",
    "sg:classifiers":[
        {
            "category":"Banks & Credit Unions",
            "subcategory":"Bank",
            "type":"Services"
        }
    ],
    "sg:phone":"+33 3393580819",
    "sg:province":"Basse Normandie",
    "wof:name":"Cr\u00e9dit Agricole Des Alpes Maritimes",
    "wof:placetype":"venue"
},
  "geometry": {"coordinates":[7.11077,43.72327],"type":"Point"}
}