{
  "type": "Feature",
  "properties": {
    "iso:country":"FR",
    "sg:address":"2 Rue Ste Marie 92400 Courbevoie",
    "sg:classifiers":[
        {
            "category":"Banks & Credit Unions",
            "subcategory":"Financial Services",
            "type":"Services"
        }
    ],
    "sg:phone":"+33 1 47 89 90 00",
    "sg:postcode":"92400",
    "sg:province":"Ile de France",
    "sg:tags":[
        "banking",
        "finance",
        "insurance"
    ],
    "wof:name":"Helvetia - Compagnie Suisse Dassurances",
    "wof:placetype":"venue"
},
  "geometry": {"coordinates":[2.259251,48.892776],"type":"Point"}
}