{
  "type": "Feature",
  "properties": {
    "addr:full":"15 Avenue Mirabeau 06600 Antibes",
    "addr:housenumber":"15",
    "addr:postcode":"06600",
    "addr:street":"Avenue Mirabeau",
    "iso:country":"FR",
    "sg:address":"15 Avenue Mirabeau 06600 Antibes",
    "sg:classifiers":[
        {
            "category":"Manufacturing",
            "subcategory":"Metals",
            "type":"Manufacturing & Wholesale Goods"
        }
    ],
    "sg:phone":"+33 4 93 34 90 50",
    "sg:tags":[
        "metallurgy",
        "metalworking"
    ],
    "wof:name":"Ste Antiboise Navigair Sa",
    "wof:placetype":"venue"
},
  "geometry": {"coordinates":[7.121875,43.583477],"type":"Point"}
}