{
  "type": "Feature",
  "properties": {
    "addr:full":"B.P. 10, 78680 Epone^^10, Rue du Pav\u00e9, 78680 Epone Ile de France",
    "addr:postcode":"78680;78680",
    "addr:street":"B.P. 10;Rue Du Pave\u0301;Ile De France",
    "iso:country":"FR",
    "sg:address":"B.P. 10, 78680 Epone^^10, Rue du Pav\u00e9, 78680 Epone",
    "sg:orig_category":"Non-Classified Establishments",
    "sg:phone":"+33 1 30 95 66 76",
    "sg:province":"Ile de France",
    "wof:name":"T.t.i. S.a.r.l. - Techniques Thermiques Et Informatiques",
    "wof:placetype":"venue"
},
  "geometry": {"coordinates":[1.812535,48.957199],"type":"Point"}
}