{
  "type": "Feature",
  "properties": {
    "addr:full":"3 Place St-Louis 45500 Gien Gien Centre 45500",
    "addr:housenumber":"3",
    "addr:postcode":"45500;45500",
    "addr:street":"Place St-Louis",
    "iso:country":"FR",
    "sg:address":"3 Place St-Louis 45500 Gien",
    "sg:city":"Gien",
    "sg:classifiers":[
        {
            "category":"Banks & Credit Unions",
            "subcategory":"Financial Services",
            "type":"Services"
        }
    ],
    "sg:phone":"+33 2 38 29 55 29",
    "sg:postcode":"45500",
    "sg:province":"Centre",
    "sg:tags":[
        "banking",
        "insurance",
        "institution",
        "finance"
    ],
    "wof:name":"Banque Regionale De L'ouest (bro)",
    "wof:placetype":"venue"
},
  "geometry": {"coordinates":[2.633036,47.683552],"type":"Point"}
}