{
  "type": "Feature",
  "properties": {
    "iso:country":"FR",
    "sg:address":"30210 Fourn\u00e8s",
    "sg:orig_category":"Non-Classified Establishments",
    "sg:phone":"+33 4 66 37 48 00",
    "sg:province":"Languedoc-Roussillon",
    "wof:name":"Parefeuille Provence S.a.",
    "wof:placetype":"venue"
},
  "geometry": {"coordinates":[4.60222,43.930756],"type":"Point"}
}