{
  "type": "Feature",
  "properties": {
    "iso:country":"FR",
    "sg:address":"22, Rue Jean de la Fontaine, 24200 Sarlat La Caneda",
    "sg:city":"Carsac-Aillac",
    "sg:orig_category":"Unclassifiable Establishments",
    "sg:phone":"+33 5 53 59 08 39",
    "sg:postcode":"24200",
    "sg:province":"Aquitaine",
    "wof:name":"Aquitaine Expertise Conseils S.a.",
    "wof:placetype":"venue"
},
  "geometry": {"coordinates":[1.218865,44.86784],"type":"Point"}
}