{
  "type": "Feature",
  "properties": {
    "iso:country":"FR",
    "sg:address":"53, Rte de Bourges, 36100 Issoudun",
    "sg:city":"Issoudun",
    "sg:orig_category":"Non-Classified Establishments",
    "sg:phone":"+33 2 54 21 83 84",
    "sg:postcode":"36100",
    "sg:province":"Centre",
    "wof:name":"Cresystem S.a.r.l.",
    "wof:placetype":"venue"
},
  "geometry": {"coordinates":[2.002353,46.951004],"type":"Point"}
}