{
  "type": "Feature",
  "properties": {
    "iso:country":"FR",
    "sg:address":"170, Rue Barb\u00e8s, 18000 Bourges",
    "sg:city":"Bourges",
    "sg:orig_category":"Non-Classified Establishments",
    "sg:phone":"+33 2 48 50 94 95",
    "sg:postcode":"18000",
    "sg:province":"Centre",
    "wof:name":"Telinfo S.a.r.l.",
    "wof:placetype":"venue"
},
  "geometry": {"coordinates":[2.388301,47.07156],"type":"Point"}
}