{
  "type": "Feature",
  "properties": {
    "addr:full":"B.P. 1379, 76066 Le Havre C\u00e9dex^^192, Rue de la Vall\u00e9e, 76600 Le Havre Haute Normandie",
    "addr:postcode":"76066;76600",
    "addr:street":"B.P. 1379;Rue De La Valle\u0301E",
    "iso:country":"FR",
    "sg:address":"B.P. 1379, 76066 Le Havre C\u00e9dex^^192, Rue de la Vall\u00e9e, 76600 Le Havre",
    "sg:orig_category":"Non-Classified Establishments",
    "sg:phone":"+33 2 35 11 34 00",
    "sg:province":"Haute Normandie",
    "wof:name":"S.c.a.c. S.a.",
    "wof:placetype":"venue"
},
  "geometry": {"coordinates":[0.101405,49.493511],"type":"Point"}
}