{
  "type": "Feature",
  "properties": {
    "addr:full":"Rue Maurice Caullery - ZI Dorignies Douai Nord Pas-de-Calais 59500",
    "addr:postcode":"59500",
    "addr:street":"Rue Maurice;Zi Dorignies Douai Nord",
    "iso:country":"FR",
    "sg:address":"Rue Maurice Caullery - ZI Dorignies",
    "sg:city":"Douai",
    "sg:orig_category":"Non-Classified Establishments",
    "sg:phone":"+33 3 27 71 31 80",
    "sg:postcode":"59500",
    "sg:province":"Nord Pas-de-Calais",
    "wof:name":"M.v.s. S.a. - Mondial Viande Service",
    "wof:placetype":"venue"
},
  "geometry": {"coordinates":[3.07836,50.368759],"type":"Point"}
}