{
  "type": "Feature",
  "properties": {
    "iso:country":"FR",
    "sg:address":"B.P. 5, 76260 Eu^^ZI des Pr\u00e9s Sal\u00e9s, 76260 Eu",
    "sg:orig_category":"Non-Classified Establishments",
    "sg:phone":"+33 2 35 50 17 44",
    "sg:province":"Haute Normandie",
    "wof:name":"Technic-elec S.a.",
    "wof:placetype":"venue"
},
  "geometry": {"coordinates":[1.42007,50.049061],"type":"Point"}
}