{
  "type": "Feature",
  "properties": {
    "iso:country":"FR",
    "sg:address":"24, Rue Centrale, 38300 Montceau",
    "sg:orig_category":"Unclassifiable Establishments",
    "sg:phone":"+33 4 74 97 27 33",
    "sg:postcode":"38300",
    "sg:province":"Rhone-Alpes",
    "wof:name":"Soci\u00e9t\u00e9 Omam S.a.r.l.",
    "wof:placetype":"venue"
},
  "geometry": {"coordinates":[5.374285,45.587498],"type":"Point"}
}