{
  "type": "Feature",
  "properties": {
    "iso:country":"FR",
    "sg:address":"7, Rue Louis Bl\u00e9riot, 44700 Orvault",
    "sg:orig_category":"Unclassifiable Establishments",
    "sg:phone":"+33 2 40 63 90 03",
    "sg:province":"Pays de Loire",
    "wof:name":"S.i.h.q. S.a.s. - Syst\u00e8me Informatique \u00a3houdmond Quellien",
    "wof:placetype":"venue"
},
  "geometry": {"coordinates":[-1.617599,47.253479],"type":"Point"}
}