{
  "type": "Feature",
  "properties": {
    "iso:country":"FR",
    "sg:address":"3 Bis R Principale 67600 Baldenheim",
    "sg:city":"Baldenheim",
    "sg:classifiers":[
        {
            "category":"Farming",
            "subcategory":"Farm",
            "type":"Manufacturing & Wholesale Goods"
        }
    ],
    "sg:phone":"+33 3 88 85 30 12",
    "sg:postcode":"67600",
    "sg:province":"Alsace",
    "sg:tags":[
        "horticulture",
        "agriculture",
        "livestock"
    ],
    "wof:name":"Sca Aux Cyclamens D' Alsace",
    "wof:placetype":"venue"
},
  "geometry": {"coordinates":[7.539293,48.235428],"type":"Point"}
}