{
  "type": "Feature",
  "properties": {
    "iso:country":"FR",
    "sg:address":"27, Rue Georges Besse, 63100 Clermont Ferrand",
    "sg:city":"Clermont-Ferrand",
    "sg:orig_category":"Unclassifiable Establishments",
    "sg:phone":"+33 4 73 98 12 12",
    "sg:postcode":"63100",
    "sg:province":"Auvergne",
    "wof:name":"Dalkia S.a.",
    "wof:placetype":"venue"
},
  "geometry": {"coordinates":[3.137861,45.783314],"type":"Point"}
}