{
  "type": "Feature",
  "properties": {
    "addr:full":"14 Place Marie Jeanne Bassot Levallois Perret Cedex 92593 ",
    "addr:housenumber":"14",
    "addr:postcode":"perret cedex 92593",
    "addr:street":"Place Marie Jeanne Bassot",
    "iso:country":"FR",
    "sg:address":"14 Place Marie Jeanne Bassot",
    "sg:city":"Levallois Perret Cedex",
    "sg:classifiers":[
        {
            "category":"Manufacturing",
            "subcategory":"Electronics",
            "type":"Manufacturing & Wholesale Goods"
        }
    ],
    "sg:postcode":"92593 ",
    "sg:website":"http://www.nvidia.com",
    "wof:name":"NVidia",
    "wof:placetype":"venue"
},
  "geometry": {"coordinates":[2.283542,48.897549],"type":"Point"}
}