{
  "type": "Feature",
  "properties": {
    "addr:full":"Route De Lyon 01460 Montreal La Cluse Rhone-Alpes",
    "addr:postcode":"01460",
    "addr:street":"Route De Lyon;La",
    "iso:country":"FR",
    "sg:address":"Route De Lyon 01460 Montreal La Cluse",
    "sg:classifiers":[
        {
            "category":"Manufacturing",
            "subcategory":"Rubber & Plastics",
            "type":"Manufacturing & Wholesale Goods"
        }
    ],
    "sg:phone":"+33 4 74 76 05 79",
    "sg:province":"Rhone-Alpes",
    "wof:name":"Plastic Mulotti",
    "wof:placetype":"venue"
},
  "geometry": {"coordinates":[5.55338,46.177399],"type":"Point"}
}