{
  "type": "Feature",
  "properties": {
    "iso:country":"FR",
    "sg:address":"2, Rue du Clos prieur - ZA, 78840 Freneuse",
    "sg:orig_category":"Non-Classified Establishments",
    "sg:phone":"+33 1 30 98 97 14",
    "sg:province":"Ile de France",
    "wof:name":"Sifem S.a.r.l.",
    "wof:placetype":"venue"
},
  "geometry": {"coordinates":[1.600769,49.048203],"type":"Point"}
}