{
  "type": "Feature",
  "properties": {
    "iso:country":"FR",
    "sg:address":"All Des \u00c9pinettes B\u00e2t 9 77200 Torcy",
    "sg:classifiers":[
        {
            "category":"Manufacturing",
            "subcategory":"Tools & Machinery",
            "type":"Manufacturing & Wholesale Goods"
        }
    ],
    "sg:phone":"+33 1 60 05 90 35",
    "sg:postcode":"77200",
    "sg:province":"Ile de France",
    "sg:tags":[
        "equipment",
        "measurement",
        "-",
        "precision",
        "instrument"
    ],
    "wof:name":"Balance Milliot Sa",
    "wof:placetype":"venue"
},
  "geometry": {"coordinates":[2.65896,48.84919],"type":"Point"}
}