{
  "type": "Feature",
  "properties": {
    "addr:full":"Za De Tarfume 12390 Rignac Midi Pyr\u00e9n\u00e9es 12390",
    "addr:postcode":"12390;12390",
    "addr:street":"Za De Tarfume",
    "iso:country":"FR",
    "sg:address":"Za De Tarfume 12390 Rignac",
    "sg:classifiers":[
        {
            "category":"Education",
            "subcategory":"Special Training",
            "type":"Public Place"
        }
    ],
    "sg:phone":"+33 5 65 64 50 44",
    "sg:postcode":"12390",
    "sg:province":"Midi Pyr\u00e9n\u00e9es",
    "sg:tags":[
        "pharmaceutical",
        "livestock",
        "animal",
        "chemical",
        "grain",
        "cereal",
        "breeding",
        "chem",
        "agriculture"
    ],
    "wof:name":"Societe Cooperative Agricole Unicorpoint Vert",
    "wof:placetype":"venue"
},
  "geometry": {"coordinates":[2.28822,44.409988],"type":"Point"}
}