{
  "type": "Feature",
  "properties": {
    "iso:country":"FR",
    "sg:address":"Z.I.",
    "sg:city":"Jarz\u00e9",
    "sg:orig_category":"Non-Classified Establishments",
    "sg:phone":"+33 2 41 18 81 21",
    "sg:postcode":"49140",
    "sg:province":"Pays de Loire",
    "wof:name":"Vyllar S.a.r.l.",
    "wof:placetype":"venue"
},
  "geometry": {"coordinates":[-0.317761,47.499454],"type":"Point"}
}