{
  "type": "Feature",
  "properties": {
    "addr:full":"6, All\u00e9e de la Champelle - Parc Technologique de Brabois, 54500 Vandoeuvre l\u00e8s Nancy Lorraine",
    "addr:housenumber":"6",
    "addr:postcode":"54500",
    "addr:street":"Alle\u0301E De La Champelle Parc Technologique De Brabois",
    "iso:country":"FR",
    "sg:address":"6, All\u00e9e de la Champelle - Parc Technologique de Brabois, 54500 Vandoeuvre l\u00e8s Nancy",
    "sg:orig_category":"Non-Classified Establishments",
    "sg:phone":"+33 3 83 22 77 45",
    "sg:province":"Lorraine",
    "wof:name":"S.l. Consultant Marketing",
    "wof:placetype":"venue"
},
  "geometry": {"coordinates":[6.172675,48.659737],"type":"Point"}
}