{
  "type": "Feature",
  "properties": {
    "addr:full":"1 R Rieg 51689 Reims Champagne",
    "addr:housenumber":"1",
    "addr:postcode":"51689",
    "addr:street":"R Rieg",
    "iso:country":"FR",
    "sg:address":"1 R Rieg 51689 Reims",
    "sg:classifiers":[
        {
            "category":"Utilities",
            "subcategory":"Electric",
            "type":"Services"
        }
    ],
    "sg:phone":"+33 3 26 36 39 26",
    "sg:province":"Champagne",
    "sg:tags":[
        "electricity",
        "electronic",
        "electrical",
        "equipment"
    ],
    "wof:name":"Santerne",
    "wof:placetype":"venue"
},
  "geometry": {"coordinates":[4.03384,49.25415],"type":"Point"}
}