{
  "type": "Feature",
  "properties": {
    "addr:full":"146 Bd De St Quentin 80094 Amiens Cedex 3 Amiens Picardie 80000",
    "addr:housenumber":"146",
    "addr:postcode":"80094 amiens;80000",
    "addr:street":"Bd De St",
    "iso:country":"FR",
    "sg:address":"146 Bd De St Quentin 80094 Amiens Cedex 3",
    "sg:city":"Amiens",
    "sg:classifiers":[
        {
            "category":"Professional",
            "subcategory":"Business Services",
            "type":"Services"
        }
    ],
    "sg:phone":"+33 3 22 33 77 77",
    "sg:postcode":"80000",
    "sg:province":"Picardie",
    "sg:tags":[
        "training",
        "advice"
    ],
    "wof:name":"Lycee Professionnel La Providence",
    "wof:placetype":"venue"
},
  "geometry": {"coordinates":[2.297008,49.87899],"type":"Point"}
}