{
  "type": "Feature",
  "properties": {
    "iso:country":"FR",
    "sg:address":"Rue de la Source - ZAC du Haut Vigneau",
    "sg:city":"Gradignan C\u00e9dex",
    "sg:orig_category":"Non-Classified Establishments",
    "sg:phone":"+33 5 56 75 57 57",
    "sg:postcode":"33174",
    "sg:province":"Franche Comt\u00e9",
    "wof:name":"Imprim'33 S.a.",
    "wof:placetype":"venue"
},
  "geometry": {"coordinates":[-0.614138,44.773132],"type":"Point"}
}