{
  "type": "Feature",
  "properties": {
    "addr:full":"Rue de la Source - ZAC du Haut Vigneau Gradignan C\u00e9dex Franche Comt\u00e9 33174",
    "addr:postcode":"33174",
    "addr:street":"Rue De La Source Zac Du Haut Vigneau;Franche Comte\u0301",
    "iso:country":"FR",
    "sg:address":"Rue de la Source - ZAC du Haut Vigneau",
    "sg:city":"Gradignan C\u00e9dex",
    "sg:orig_category":"Non-Classified Establishments",
    "sg:phone":"+33 5 56 75 57 57",
    "sg:postcode":"33174",
    "sg:province":"Franche Comt\u00e9",
    "wof:name":"Imprim'33 S.a.",
    "wof:placetype":"venue"
},
  "geometry": {"coordinates":[-0.614138,44.773132],"type":"Point"}
}