{
  "type": "Feature",
  "properties": {
    "addr:full":"2050, Rte des Ch\u00e8res, 69480 Morance Rhone-Alpes",
    "addr:housenumber":"2050",
    "addr:postcode":"69480",
    "addr:street":"Rte Des Che\u0300Res",
    "iso:country":"FR",
    "sg:address":"2050, Rte des Ch\u00e8res, 69480 Morance",
    "sg:orig_category":"Unclassifiable Establishments",
    "sg:phone":"+33 4 78 47 35 28",
    "sg:province":"Rhone-Alpes",
    "wof:name":"P\u00e9pini\u00e8res Rey S.a.",
    "wof:placetype":"venue"
},
  "geometry": {"coordinates":[4.720956,45.888313],"type":"Point"}
}