{
  "type": "Feature",
  "properties": {
    "addr:full":"B.P. 83, 39800 Poligny^^Rue de Corbusier, 39800 Poligny Franche Comt\u00e9",
    "addr:postcode":"39800;39800",
    "addr:street":"B.P. 83;Corbusier;Franche Comte\u0301",
    "iso:country":"FR",
    "sg:address":"B.P. 83, 39800 Poligny^^Rue de Corbusier, 39800 Poligny",
    "sg:orig_category":"Non-Classified Establishments",
    "sg:phone":"+33 3 84 37 37 37",
    "sg:province":"Franche Comt\u00e9",
    "wof:name":"Microbat S.a.r.l.",
    "wof:placetype":"venue"
},
  "geometry": {"coordinates":[5.708668,46.834393],"type":"Point"}
}