{
  "type": "Feature",
  "properties": {
    "addr:full":"18, Rte de la Souterraine, 23300 Saint Agnant de Versillat Limousin 23300",
    "addr:housenumber":"18",
    "addr:postcode":"23300;23300",
    "addr:street":"Rte De La Souterraine",
    "iso:country":"FR",
    "sg:address":"18, Rte de la Souterraine, 23300 Saint Agnant de Versillat",
    "sg:orig_category":"Non-Classified Establishments",
    "sg:phone":"+33 5 55 63 11 08",
    "sg:postcode":"23300",
    "sg:province":"Limousin",
    "wof:name":"Adam Raymond Et Fils S.a.",
    "wof:placetype":"venue"
},
  "geometry": {"coordinates":[1.509815,46.277401],"type":"Point"}
}