{
  "type": "Feature",
  "properties": {
    "addr:full":"Ch\u00e2teau Bellerive 49190 Rochefort sur Loire Pays de Loire 49190",
    "addr:postcode":"49190;49190",
    "iso:country":"FR",
    "sg:address":"Ch\u00e2teau Bellerive 49190 Rochefort sur Loire",
    "sg:classifiers":[
        {
            "category":"Wholesale",
            "subcategory":"Wine & Distilled Alcoholic Beverages",
            "type":"Manufacturing & Wholesale Goods"
        }
    ],
    "sg:phone":"+33 2 41 78 33 66",
    "sg:postcode":"49190",
    "sg:province":"Pays de Loire",
    "sg:tags":[
        "french"
    ],
    "wof:name":"Ch\u00e2teau Bellerive Sarl",
    "wof:placetype":"venue"
},
  "geometry": {"coordinates":[-0.661869,47.340076],"type":"Point"}
}