{
  "type": "Feature",
  "properties": {
    "addr:full":"rue Joseph Laniel 14100 Beuvillers Beuvillers Basse Normandie 14100",
    "addr:postcode":"14100;14100",
    "addr:street":"Rue Joseph Laniel",
    "iso:country":"FR",
    "sg:address":"rue Joseph Laniel 14100 Beuvillers",
    "sg:city":"Beuvillers",
    "sg:classifiers":[
        {
            "category":"Manufacturing",
            "subcategory":"Rubber & Plastics",
            "type":"Manufacturing & Wholesale Goods"
        }
    ],
    "sg:phone":"+33 2 31 48 57 57",
    "sg:postcode":"14100",
    "sg:province":"Basse Normandie",
    "sg:tags":[
        "packaging",
        "mean"
    ],
    "wof:name":"Exbanor S.a.",
    "wof:placetype":"venue"
},
  "geometry": {"coordinates":[0.252137,49.132896],"type":"Point"}
}