{
  "type": "Feature",
  "properties": {
    "iso:country":"FR",
    "sg:address":"19, Av. Charles de Gaulle - ZAC la Ceriseraie, 93240 Stains",
    "sg:orig_category":"Unclassifiable Establishments",
    "sg:phone":"+33 1 49 71 31 10",
    "sg:province":"Ile de France",
    "wof:name":"Phoenix Computer S.a.r.l.",
    "wof:placetype":"venue"
},
  "geometry": {"coordinates":[2.383285,48.95528],"type":"Point"}
}