{
  "type": "Feature",
  "properties": {
    "addr:full":"28 rue Emile Druart 51100 Reims Champagne",
    "addr:housenumber":"28",
    "addr:postcode":"51100",
    "addr:street":"Rue Emile Druart",
    "iso:country":"FR",
    "sg:address":"28 rue Emile Druart 51100 Reims",
    "sg:classifiers":[
        {
            "category":"Home & Garden",
            "subcategory":"Household Appliances",
            "type":"Retail Goods"
        }
    ],
    "sg:phone":"+33 3 26 09 23 16",
    "sg:province":"Champagne",
    "sg:tags":[
        "scented",
        "air-conditioning"
    ],
    "wof:name":"S.c.c.c. Sa",
    "wof:placetype":"venue"
},
  "geometry": {"coordinates":[4.001,49.274063],"type":"Point"}
}