{
  "type": "Feature",
  "properties": {
    "iso:country":"FR",
    "sg:address":"2, Av de Suisse, 68110 Illzach",
    "sg:city":"Illzach",
    "sg:orig_category":"Non-Classified Establishments",
    "sg:phone":"+33 3 89 31 24 24",
    "sg:postcode":"68110",
    "sg:province":"Alsace",
    "wof:name":"Euromoving S.a.r.l.",
    "wof:placetype":"venue"
},
  "geometry": {"coordinates":[7.37206,47.770489],"type":"Point"}
}