{
  "type": "Feature",
  "properties": {
    "iso:country":"FR",
    "sg:address":"36, Rue Henri Giffard, 87280 Limoges",
    "sg:orig_category":"Unclassifiable Establishments",
    "sg:phone":"+33 2 54 08 16 16",
    "sg:province":"Limousin",
    "wof:name":"Bernis S.a.",
    "wof:placetype":"venue"
},
  "geometry": {"coordinates":[1.265473,45.875706],"type":"Point"}
}