{
  "type": "Feature",
  "properties": {
    "iso:country":"FR",
    "sg:address":"47, Rue de la Bresse, 94550 Chevilly Larue",
    "sg:orig_category":"Unclassifiable Establishments",
    "sg:phone":"+33 1 46 86 61 80",
    "sg:province":"Ile de France",
    "wof:name":"Etablissements Seron Fr\u00e8res S.a.",
    "wof:placetype":"venue"
},
  "geometry": {"coordinates":[2.36433,48.758095],"type":"Point"}
}