{
  "type": "Feature",
  "properties": {
    "addr:full":"B.P. 69, 62510 Arques^^1, Rue de Lorraine, 62510 Arques Nord Pas-de-Calais",
    "addr:postcode":"62510;62510",
    "addr:street":"B.P. 69;Rue De Lorraine",
    "iso:country":"FR",
    "sg:address":"B.P. 69, 62510 Arques^^1, Rue de Lorraine, 62510 Arques",
    "sg:orig_category":"Non-Classified Establishments",
    "sg:phone":"+33 3 21 98 70 50",
    "sg:province":"Nord Pas-de-Calais",
    "wof:name":"Piky S.a.",
    "wof:placetype":"venue"
},
  "geometry": {"coordinates":[2.294459,50.735394],"type":"Point"}
}