{
  "type": "Feature",
  "properties": {
    "addr:full":"65, Av. Andr\u00e9 Morizet, 92100 Boulogne Billancourt Ile de France",
    "addr:postcode":"92100",
    "addr:street":"65 Av. Andre\u0301 Morizet",
    "iso:country":"FR",
    "sg:address":"65, Av. Andr\u00e9 Morizet, 92100 Boulogne Billancourt",
    "sg:orig_category":"Unclassifiable Establishments",
    "sg:phone":"+33 1 48 25 27 65",
    "sg:province":"Ile de France",
    "wof:name":"Le Crochet Celt S.a.r.l.",
    "wof:placetype":"venue"
},
  "geometry": {"coordinates":[2.234997,48.837456],"type":"Point"}
}