{
  "type": "Feature",
  "properties": {
    "addr:full":"B.P. 36, 58501 Clamecy C\u00e9dex^^6, Fbg de Bethleem, 58500 Clamecy Clamecy Bourgogne 58500",
    "addr:postcode":"58501;58500;58500",
    "addr:street":"B.P. 36;Bethleem",
    "iso:country":"FR",
    "sg:address":"B.P. 36, 58501 Clamecy C\u00e9dex^^6, Fbg de Bethleem, 58500 Clamecy",
    "sg:city":"Clamecy",
    "sg:orig_category":"Non-Classified Establishments",
    "sg:phone":"+33 3 86 27 11 77",
    "sg:postcode":"58500",
    "sg:province":"Bourgogne",
    "wof:name":"Fa\u00efencerie D'art Colas S.a.",
    "wof:placetype":"venue"
},
  "geometry": {"coordinates":[3.520745,47.459946],"type":"Point"}
}