{
  "type": "Feature",
  "properties": {
    "addr:full":"1, Rue de Montdidier, 60120 Breteuil Picardie",
    "addr:housenumber":"1",
    "addr:postcode":"60120",
    "addr:street":"Rue De Montdidier",
    "iso:country":"FR",
    "sg:address":"1, Rue de Montdidier, 60120 Breteuil",
    "sg:orig_category":"Non-Classified Establishments",
    "sg:phone":"+33 3 44 80 67 50",
    "sg:province":"Picardie",
    "wof:name":"Inoforges S.a.",
    "wof:placetype":"venue"
},
  "geometry": {"coordinates":[2.299982,49.629337],"type":"Point"}
}