{
  "type": "Feature",
  "properties": {
    "addr:full":"Rue du Pr\u00e9 aux Boeufs Saint Etienne du Rouvray Haute Normandie 76800",
    "addr:postcode":"76800",
    "addr:street":"Rue Du Pre\u0301 Aux Boeufs;Haute Normandie",
    "iso:country":"FR",
    "sg:address":"Rue du Pr\u00e9 aux Boeufs",
    "sg:city":"Saint Etienne du Rouvray",
    "sg:orig_category":"Unclassifiable Establishments",
    "sg:phone":"+33 2 35 66 96 96",
    "sg:postcode":"76800",
    "sg:province":"Haute Normandie",
    "wof:name":"Facen S.a.",
    "wof:placetype":"venue"
},
  "geometry": {"coordinates":[1.117875,49.393608],"type":"Point"}
}