{
  "type": "Feature",
  "properties": {
    "iso:country":"FR",
    "sg:address":"81 Rue Coquebert 51066 Reims Cedex",
    "sg:classifiers":[
        {
            "category":"Food Court",
            "type":"Food & Drink"
        }
    ],
    "sg:phone":"+33 3 26 89 53 00",
    "sg:province":"Auvergne",
    "sg:tags":[
        "product",
        "related"
    ],
    "wof:name":"Des Vignobles Henriot",
    "wof:placetype":"venue"
},
  "geometry": {"coordinates":[4.042267,49.263023],"type":"Point"}
}