{
  "type": "Feature",
  "properties": {
    "addr:full":"Av. Jean Monnet Colomiers Midi Pyr\u00e9n\u00e9es 31770",
    "addr:postcode":"31770",
    "addr:street":"Av. Jean Monnet",
    "iso:country":"FR",
    "sg:address":"Av. Jean Monnet",
    "sg:city":"Colomiers",
    "sg:orig_category":"Unclassifiable Establishments",
    "sg:phone":"+33 5 61 71 07 70",
    "sg:postcode":"31770",
    "sg:province":"Midi Pyr\u00e9n\u00e9es",
    "wof:name":"T.t.a. S.a. - Tous Transports A\u00e9riens",
    "wof:placetype":"venue"
},
  "geometry": {"coordinates":[1.345746,43.62212],"type":"Point"}
}