{
  "type": "Feature",
  "properties": {
    "iso:country":"FR",
    "sg:address":"3, Place de l'Eglise, 44410 Asserac",
    "sg:orig_category":"Unclassifiable Establishments",
    "sg:phone":"+33 2 40 01 70 89",
    "sg:province":"Pays de Loire",
    "wof:name":"Besluau Maurice",
    "wof:placetype":"venue"
},
  "geometry": {"coordinates":[-2.390257,47.429058],"type":"Point"}
}