{
  "type": "Feature",
  "properties": {
    "addr:full":"16, Av. Saures, 12140 Entraygues sur Truy\u00e8re Midi Pyr\u00e9n\u00e9es 12140",
    "addr:postcode":"12140;12140",
    "addr:street":"16 Av. Saures",
    "iso:country":"FR",
    "sg:address":"16, Av. Saures, 12140 Entraygues sur Truy\u00e8re",
    "sg:orig_category":"Non-Classified Establishments",
    "sg:phone":"+33 5 65 51 29 40",
    "sg:postcode":"12140",
    "sg:province":"Midi Pyr\u00e9n\u00e9es",
    "wof:name":"Combettes S.a.",
    "wof:placetype":"venue"
},
  "geometry": {"coordinates":[2.565083,44.641338],"type":"Point"}
}