{
  "type": "Feature",
  "properties": {
    "addr:full":"Rte de Verlans - Byans H\u00e9ricourt Franche Comt\u00e9 70400",
    "addr:postcode":"70400",
    "addr:street":"Rte De Verlans Byans;Franche Comte\u0301",
    "iso:country":"FR",
    "sg:address":"Rte de Verlans - Byans",
    "sg:city":"H\u00e9ricourt",
    "sg:orig_category":"Unclassifiable Establishments",
    "sg:phone":"+33 3 84 46 45 89",
    "sg:postcode":"70400",
    "sg:province":"Franche Comt\u00e9",
    "wof:name":"La Pierre D'h\u00e9ricourt S.a.r.l.",
    "wof:placetype":"venue"
},
  "geometry": {"coordinates":[6.754775,47.574718],"type":"Point"}
}