{
  "type": "Feature",
  "properties": {
    "iso:country":"FR",
    "sg:address":"Place de l'H\u00f4tel de Ville",
    "sg:city":"Montaigu",
    "sg:orig_category":"Unclassifiable Establishments",
    "sg:phone":"+33 2 51 94 90 90",
    "sg:postcode":"85600",
    "sg:province":"Pays de Loire",
    "wof:name":"R.e.e.l. - Relais Emploi Entraide Local",
    "wof:placetype":"venue"
},
  "geometry": {"coordinates":[-1.627147,49.475643],"type":"Point"}
}