{
  "type": "Feature",
  "properties": {
    "iso:country":"FR",
    "sg:address":"25 Av Bieckert 06000 Nice",
    "sg:classifiers":[
        {
            "category":"Professional",
            "subcategory":"Business Services",
            "type":"Services"
        }
    ],
    "sg:phone":"+33 4 93 81 53 36",
    "sg:tags":[
        "training",
        "advice"
    ],
    "wof:name":"Ogec Stanislas Sa",
    "wof:placetype":"venue"
},
  "geometry": {"coordinates":[7.272569,43.706512],"type":"Point"}
}