{
  "type": "Feature",
  "properties": {
    "iso:country":"FR",
    "sg:address":"B.P. 1, 31480 Cadours^^1, Av. Raymond Sommer, 31480 Cadours",
    "sg:orig_category":"Non-Classified Establishments",
    "sg:phone":"+33 5 61 85 62 27",
    "sg:province":"Midi Pyr\u00e9n\u00e9es",
    "wof:name":"Gabrielle S.a.",
    "wof:placetype":"venue"
},
  "geometry": {"coordinates":[1.0697,43.685211],"type":"Point"}
}