{
  "type": "Feature",
  "properties": {
    "addr:full":"2 Rue Eugene Marechal 69200 Venissieux Rhone-Alpes 69200",
    "addr:housenumber":"2",
    "addr:postcode":"69200;69200",
    "addr:street":"Rue Eugene Marechal;Rhone-Alpes",
    "iso:country":"FR",
    "sg:address":"2 Rue Eugene Marechal 69200 Venissieux",
    "sg:classifiers":[
        {
            "category":"Transit Center",
            "subcategory":"Freight",
            "type":"Transportation"
        }
    ],
    "sg:phone":"+33 4 72 21 10 10",
    "sg:postcode":"69200",
    "sg:province":"Rhone-Alpes",
    "sg:tags":[
        "metallurgy",
        "pipe",
        "metalworking",
        "sheet"
    ],
    "wof:name":"Veninov",
    "wof:placetype":"venue"
},
  "geometry": {"coordinates":[4.878419,45.706127],"type":"Point"}
}