{
  "type": "Feature",
  "properties": {
    "iso:country":"FR",
    "sg:address":"10, Rue L\u00e9onard de Vinci, 69120 Vaulx en Velin",
    "sg:orig_category":"Unclassifiable Establishments",
    "sg:phone":"+33 4 78 79 30 50",
    "sg:province":"Rhone-Alpes",
    "wof:name":"O.c.p. R\u00e9partition S.a. - Organisme Du Commerce Pharmaceutique",
    "wof:placetype":"venue"
},
  "geometry": {"coordinates":[4.93229,45.779041],"type":"Point"}
}