{
  "type": "Feature",
  "properties": {
    "iso:country":"FR",
    "sg:address":"9, Rue Chateaubriand, 57330 Hettange Grande",
    "sg:orig_category":"Unclassifiable Establishments",
    "sg:phone":"+33 3 82 51 33 26",
    "sg:province":"Lorraine",
    "wof:name":"D\u00e9coram S.a.r.l.",
    "wof:placetype":"venue"
},
  "geometry": {"coordinates":[6.16109,49.39827],"type":"Point"}
}