{
  "type": "Feature",
  "properties": {
    "iso:country":"FR",
    "sg:address":"Rue Jean Baptiste Perrin Za Jean Mermoz 33320 Eysines",
    "sg:city":"Eysines",
    "sg:classifiers":[
        {
            "category":"Wholesale",
            "subcategory":"Machinery & Supplies",
            "type":"Manufacturing & Wholesale Goods"
        }
    ],
    "sg:phone":"+33 5 56 28 87 72",
    "sg:postcode":"33320",
    "sg:province":"Aquitaine",
    "sg:tags":[
        "handling",
        "material",
        "-",
        "machine",
        "equipment",
        "engineering",
        "mechanical"
    ],
    "wof:name":"Jungheinrich France",
    "wof:placetype":"venue"
},
  "geometry": {"coordinates":[-0.669039,44.903831],"type":"Point"}
}