{
  "type": "Feature",
  "properties": {
    "addr:full":"B.P. 138, 35513 Cesson S\u00e9vign\u00e9 C\u00e9dex^^Av. des Peupliers - Technoparc 4D, 35510 Cesson S\u00e9vign\u00e9 Cesson-S\u00e9vign\u00e9 Bretagne 35510",
    "addr:housenumber":"b.p. 138;4d",
    "addr:postcode":"35513;35510;se\u0301vigne\u0301 cesson-se\u0301vigne\u0301;35510",
    "addr:street":"Technoparc",
    "iso:country":"FR",
    "sg:address":"B.P. 138, 35513 Cesson S\u00e9vign\u00e9 C\u00e9dex^^Av. des Peupliers - Technoparc 4D, 35510 Cesson S\u00e9vign\u00e9",
    "sg:city":"Cesson-S\u00e9vign\u00e9",
    "sg:orig_category":"Non-Classified Establishments",
    "sg:phone":"+33 2 99 83 47 00",
    "sg:postcode":"35510",
    "sg:province":"Bretagne",
    "wof:name":"Socotec S.a.",
    "wof:placetype":"venue"
},
  "geometry": {"coordinates":[-1.604404,48.117016],"type":"Point"}
}