{
  "type": "Feature",
  "properties": {
    "iso:country":"FR",
    "sg:address":"Av Louis Lumi\u00e8re Zone Industrielle 17180 P\u00e9rigny",
    "sg:classifiers":[
        {
            "category":"Utilities",
            "subcategory":"Electric",
            "type":"Services"
        }
    ],
    "sg:phone":"+33 5 46 45 47 47",
    "sg:postcode":"17180",
    "sg:province":"Poitou-Charentes",
    "sg:tags":[
        "electricity",
        "electronic",
        "electrical",
        "equipment"
    ],
    "wof:name":"Spie Trindel",
    "wof:placetype":"venue"
},
  "geometry": {"coordinates":[-1.096665,46.15501],"type":"Point"}
}