{
  "type": "Feature",
  "properties": {
    "addr:full":"50, Av. du Pr\u00e9sident Wilson, 93200 Saint Denis Ile de France",
    "addr:postcode":"93200",
    "addr:street":"50 Av. Du Pre\u0301Sident Wilson",
    "iso:country":"FR",
    "sg:address":"50, Av. du Pr\u00e9sident Wilson, 93200 Saint Denis",
    "sg:orig_category":"Unclassifiable Establishments",
    "sg:phone":"+33 1 49 46 77 00",
    "sg:province":"Ile de France",
    "wof:name":"Pronuptia Cr\u00e9ations S.a.",
    "wof:placetype":"venue"
},
  "geometry": {"coordinates":[2.35676,48.928185],"type":"Point"}
}