{
  "type": "Feature",
  "properties": {
    "addr:full":"199 avenue Pasteur 33600 Pessac Pessac Aquitaine 33600",
    "addr:housenumber":"199",
    "addr:postcode":"33600;33600",
    "addr:street":"Avenue Pasteur",
    "iso:country":"FR",
    "sg:address":"199 avenue Pasteur 33600 Pessac",
    "sg:city":"Pessac",
    "sg:classifiers":[
        {
            "category":"Professional",
            "type":"Services"
        }
    ],
    "sg:phone":"+33 5 56 36 19 19",
    "sg:postcode":"33600",
    "sg:province":"Aquitaine",
    "sg:tags":[
        "transport"
    ],
    "wof:name":"Auto Mat & Transport Sa",
    "wof:placetype":"venue"
},
  "geometry": {"coordinates":[-0.652636,44.801922],"type":"Point"}
}