{
  "type": "Feature",
  "properties": {
    "addr:full":"Fontans 48700 Serverette Languedoc-Roussillon 48700",
    "addr:postcode":"48700;48700",
    "addr:street":"Fontans",
    "iso:country":"FR",
    "sg:address":"Fontans 48700 Serverette",
    "sg:orig_category":"Non-Classified Establishments",
    "sg:phone":"+33 4 66 48 33 05",
    "sg:postcode":"48700",
    "sg:province":"Languedoc-Roussillon",
    "wof:name":"Bois Et D\u00e9riv\u00e9s Loz\u00e9riens S.a.r.l.",
    "wof:placetype":"venue"
},
  "geometry": {"coordinates":[3.38668,44.739208],"type":"Point"}
}