{
  "type": "Feature",
  "properties": {
    "addr:full":"25, Bd Victor Hugo, 31770 Colomiers Midi Pyr\u00e9n\u00e9es",
    "addr:housenumber":"25",
    "addr:postcode":"31770",
    "addr:street":"Bd Victor Hugo",
    "iso:country":"FR",
    "sg:address":"25, Bd Victor Hugo, 31770 Colomiers",
    "sg:orig_category":"Non-Classified Establishments",
    "sg:phone":"+33 5 61 15 18 45",
    "sg:province":"Midi Pyr\u00e9n\u00e9es",
    "wof:name":"Newron System S.a.",
    "wof:placetype":"venue"
},
  "geometry": {"coordinates":[1.31035,43.615005],"type":"Point"}
}