{
  "type": "Feature",
  "properties": {
    "iso:country":"FR",
    "sg:address":"8 Rue Du Platre 69001 Lyon",
    "sg:classifiers":[
        {
            "category":"Shopping",
            "subcategory":"Clothing, Apparel, & Fashions",
            "type":"Retail Goods"
        }
    ],
    "sg:phone":"+33 4 78 39 42 94",
    "sg:postcode":"69001",
    "sg:province":"Rhone-Alpes",
    "sg:tags":[
        "textile",
        "clothing",
        "clothes"
    ],
    "wof:name":"Fouchere Pinchinat Sarl",
    "wof:placetype":"venue"
},
  "geometry": {"coordinates":[4.834006,45.765965],"type":"Point"}
}