{
  "type": "Feature",
  "properties": {
    "iso:country":"FR",
    "sg:address":"Rte De Baillet En France 95560 Montsoult",
    "sg:classifiers":[
        {
            "category":"Banks & Credit Unions",
            "subcategory":"Investment Brokerage",
            "type":"Services"
        }
    ],
    "sg:phone":"+33 1 34 08 36 02",
    "sg:province":"Ile de France",
    "sg:tags":[
        "-",
        "transport",
        "related"
    ],
    "wof:name":"Frigoscandia Distribution",
    "wof:placetype":"venue"
},
  "geometry": {"coordinates":[2.309886,49.070625],"type":"Point"}
}