{
  "type": "Feature",
  "properties": {
    "iso:country":"FR",
    "sg:address":"B.P. 48",
    "sg:city":"Cesson S\u00e9vign\u00e9 C\u00e9dex^^La Garaudi\u00e8re 35510 Cesson S\u00e9vign\u00e9",
    "sg:orig_category":"Non-Classified Establishments",
    "sg:phone":"+33 2 99 83 50 20",
    "sg:postcode":"35511",
    "sg:province":"Bretagne",
    "wof:name":"Etablissements Primault S.a.",
    "wof:placetype":"venue"
},
  "geometry": {"coordinates":[-1.604404,48.117016],"type":"Point"}
}