{
  "type": "Feature",
  "properties": {
    "addr:full":"1 Rue Des Blancs Monts 51350 Cormontreuil Champagne 51350",
    "addr:housenumber":"1",
    "addr:postcode":"51350;51350",
    "addr:street":"Rue Des Blancs Monts;Champagne",
    "iso:country":"FR",
    "sg:address":"1 Rue Des Blancs Monts 51350 Cormontreuil",
    "sg:orig_category":"Agriculture and Livestock Animals and breeding Chemicals and Pharmaceuticals Food and Related Produc",
    "sg:phone":"+33 3 26 82 47 97",
    "sg:postcode":"51350",
    "sg:province":"Champagne",
    "wof:name":"Mille Amis",
    "wof:placetype":"venue"
},
  "geometry": {"coordinates":[4.057006,49.216423],"type":"Point"}
}