{
  "type": "Feature",
  "properties": {
    "addr:full":"B.P. 12, 80800 Villers Bretonneux^^13, Rue du S\u00e9maphore, 80800 Villers Bretonneux Picardie",
    "addr:postcode":"80800;80800",
    "addr:street":"B.P. 12;Rue Du Se\u0301Maphore",
    "iso:country":"FR",
    "sg:address":"B.P. 12, 80800 Villers Bretonneux^^13, Rue du S\u00e9maphore, 80800 Villers Bretonneux",
    "sg:orig_category":"Non-Classified Establishments",
    "sg:phone":"+33 3 22 96 44 50",
    "sg:province":"Picardie",
    "wof:name":"S.t.a.g. S.a. - Soci\u00e9t\u00e9 De Travaux Publics Alain Gasnier",
    "wof:placetype":"venue"
},
  "geometry": {"coordinates":[2.51246,49.909565],"type":"Point"}
}