{
  "type": "Feature",
  "properties": {
    "addr:full":"11, Rue Gustave Eiffel, 13010 Marseille Provence-Alpes-C\u00f4te d'Azur",
    "addr:housenumber":"11",
    "addr:postcode":"13010",
    "addr:street":"Rue Gustave Eiffel",
    "iso:country":"FR",
    "sg:address":"11, Rue Gustave Eiffel, 13010 Marseille",
    "sg:orig_category":"Unclassifiable Establishments",
    "sg:phone":"+33 4 91 32 80 20",
    "sg:province":"Provence-Alpes-C\u00f4te d'Azur",
    "wof:name":"C.g.e. Distribution S.a.",
    "wof:placetype":"venue"
},
  "geometry": {"coordinates":[5.405387,43.274673],"type":"Point"}
}