{
  "type": "Feature",
  "properties": {
    "iso:country":"FR",
    "sg:address":"40",
    "sg:city":"Bo\u00e9tie 75008 Paris",
    "sg:classifiers":[
        {
            "category":"Banks & Credit Unions",
            "subcategory":"Financial Services",
            "type":"Services"
        }
    ],
    "sg:phone":"+33 1 70 75 10 70",
    "sg:postcode":"75008",
    "sg:province":"Ile de France",
    "sg:tags":[
        "banking",
        "consulting",
        "finance",
        "insurance"
    ],
    "wof:name":"It Asset Management",
    "wof:placetype":"venue"
},
  "geometry": {"coordinates":[2.314021,48.873726],"type":"Point"}
}