{
  "type": "Feature",
  "properties": {
    "addr:full":"4, Rue Roc Clair, 25690 Avoudrey Franche Comt\u00e9",
    "addr:housenumber":"4",
    "addr:postcode":"25690",
    "addr:street":"Rue Roc Clair;Franche Comte\u0301",
    "iso:country":"FR",
    "sg:address":"4, Rue Roc Clair, 25690 Avoudrey",
    "sg:orig_category":"Unclassifiable Establishments",
    "sg:phone":"+33 3 81 43 22 46",
    "sg:province":"Franche Comt\u00e9",
    "wof:name":"Bourgeois Etienne S.a.r.l.",
    "wof:placetype":"venue"
},
  "geometry": {"coordinates":[6.4346,47.138119],"type":"Point"}
}