{
  "type": "Feature",
  "properties": {
    "addr:full":"7, Grand'Rue, 68190 Raedersheim Raedersheim Alsace 68190",
    "addr:housenumber":"7",
    "addr:postcode":"68190;68190",
    "addr:street":"Grand'Rue",
    "iso:country":"FR",
    "sg:address":"7, Grand'Rue, 68190 Raedersheim",
    "sg:city":"Raedersheim",
    "sg:orig_category":"Non-Classified Establishments",
    "sg:phone":"+33 3 89 48 12 05",
    "sg:postcode":"68190",
    "sg:province":"Alsace",
    "wof:name":"M.g.s. S.a.r.l. - M\u00e9canique G\u00e9n\u00e9rale Schuller",
    "wof:placetype":"venue"
},
  "geometry": {"coordinates":[7.27457,47.827858],"type":"Point"}
}