{
  "type": "Feature",
  "properties": {
    "addr:full":"Le Tanneur 40300 Orthevielle Orthevielle Aquitaine 40300",
    "addr:postcode":"40300;40300",
    "iso:country":"FR",
    "sg:address":"Le Tanneur 40300 Orthevielle",
    "sg:city":"Orthevielle",
    "sg:orig_category":"Non-Classified Establishments",
    "sg:phone":"+33 5 58 73 16 16",
    "sg:postcode":"40300",
    "sg:province":"Aquitaine",
    "wof:name":"Nogec S.a.",
    "wof:placetype":"venue"
},
  "geometry": {"coordinates":[-1.142374,43.567146],"type":"Point"}
}