{
  "type": "Feature",
  "properties": {
    "iso:country":"FR",
    "sg:address":"19 Rue Bel\u00e9bat 49300 Cholet",
    "sg:classifiers":[
        {
            "category":"Manufacturing",
            "subcategory":"Printing",
            "type":"Manufacturing & Wholesale Goods"
        }
    ],
    "sg:phone":"+33 2 41 58 15 31",
    "sg:province":"Pays de Loire",
    "sg:tags":[
        "publishing"
    ],
    "wof:name":"Amd Sa",
    "wof:placetype":"venue"
},
  "geometry": {"coordinates":[-0.886831,47.056061],"type":"Point"}
}