{
  "type": "Feature",
  "properties": {
    "addr:full":"206, Av. du Mar\u00e9chal de Lattre de Tassigny, 44500 La Baule Pays de Loire",
    "addr:postcode":"de;44500",
    "addr:street":"206 Av. Du Mare\u0301Chal;Lattre De Tassigny",
    "iso:country":"FR",
    "sg:address":"206, Av. du Mar\u00e9chal de Lattre de Tassigny, 44500 La Baule",
    "sg:orig_category":"Unclassifiable Establishments",
    "sg:phone":"+33 2 40 60 23 24",
    "sg:province":"Pays de Loire",
    "wof:name":"Dotta S.a.r.l.",
    "wof:placetype":"venue"
},
  "geometry": {"coordinates":[1.671607,47.811596],"type":"Point"}
}