{
  "type": "Feature",
  "properties": {
    "addr:full":"B.P. 655, 59506 Douai C\u00e9dex^^148, Rue Martin du Nord, 59500 Douai Nord Pas-de-Calais 59500",
    "addr:housenumber":"b.p. 655",
    "addr:postcode":"59506;59500;59500",
    "addr:street":"Rue Martin Du Nord",
    "iso:country":"FR",
    "sg:address":"B.P. 655, 59506 Douai C\u00e9dex^^148, Rue Martin du Nord, 59500 Douai",
    "sg:orig_category":"Non-Classified Establishments",
    "sg:phone":"+33 3 27 71 32 41",
    "sg:postcode":"59500",
    "sg:province":"Nord Pas-de-Calais",
    "wof:name":"Douaisienne De Transformateurs Electriques De Mesures S.a.",
    "wof:placetype":"venue"
},
  "geometry": {"coordinates":[3.07836,50.368759],"type":"Point"}
}