{
  "type": "Feature",
  "properties": {
    "iso:country":"FR",
    "sg:address":"71 Rue Etienne Dolet 94140 Alfortville",
    "sg:classifiers":[
        {
            "category":"Professional",
            "subcategory":"Printing & Photocopies",
            "type":"Services"
        }
    ],
    "sg:phone":"+33 1 45 18 33 75",
    "sg:postcode":"94140",
    "sg:province":"Ile de France",
    "sg:tags":[
        "information",
        "technology",
        "publishing",
        "software"
    ],
    "wof:name":"Evalutel",
    "wof:placetype":"venue"
},
  "geometry": {"coordinates":[2.425648,48.793118],"type":"Point"}
}