{
  "type": "Feature",
  "properties": {
    "addr:full":"31 Charles Moretti BP 43 13001 Marseille Poitou-Charentes",
    "addr:housenumber":"31;bp 43",
    "addr:postcode":"13001",
    "addr:street":"Charles Moretti",
    "iso:country":"FR",
    "sg:address":"31",
    "sg:city":"Charles Moretti BP 43 13001 Marseille",
    "sg:classifiers":[
        {
            "category":"Shopping",
            "subcategory":"Computers & Home Electronics",
            "type":"Retail Goods"
        }
    ],
    "sg:phone":"+33 4 91 67 30 01",
    "sg:province":"Poitou-Charentes",
    "sg:tags":[
        "equipment",
        "household",
        "electrical",
        "appliance",
        "electronic"
    ],
    "wof:name":"Coste",
    "wof:placetype":"venue"
},
  "geometry": {"coordinates":[5.37249,43.293686],"type":"Point"}
}