{
  "type": "Feature",
  "properties": {
    "iso:country":"FR",
    "sg:address":"9, Rte de l'Epinoy, 80220 Gamaches",
    "sg:orig_category":"Unclassifiable Establishments",
    "sg:phone":"+33 3 22 60 38 38",
    "sg:province":"Picardie",
    "wof:name":"Caoutchoucs Modernes S.a.s.",
    "wof:placetype":"venue"
},
  "geometry": {"coordinates":[1.567965,49.978691],"type":"Point"}
}