{
  "type": "Feature",
  "properties": {
    "addr:full":"7 Rue Bruat 68006 Colmar Cedex Lorraine",
    "addr:housenumber":"7",
    "addr:postcode":"68006",
    "addr:street":"Rue Bruat",
    "iso:country":"FR",
    "sg:address":"7 Rue Bruat 68006 Colmar Cedex",
    "sg:classifiers":[
        {
            "category":"Professional",
            "subcategory":"Business Services",
            "type":"Services"
        }
    ],
    "sg:phone":"+33 3 89 22 68 00",
    "sg:province":"Lorraine",
    "sg:tags":[
        "training",
        "advice"
    ],
    "wof:name":"Departement Du Haut Rhin",
    "wof:placetype":"venue"
},
  "geometry": {"coordinates":[7.363583,48.081985],"type":"Point"}
}