{
  "type": "Feature",
  "properties": {
    "iso:country":"FR",
    "sg:address":"80, Rue Aristide Briand, 77300 Fontainebleau",
    "sg:orig_category":"Unclassifiable Establishments",
    "sg:phone":"+33 1 64 22 10 86",
    "sg:province":"Ile de France",
    "wof:name":"Bernard Bruche France E.u.r.l.",
    "wof:placetype":"venue"
},
  "geometry": {"coordinates":[2.709222,48.411751],"type":"Point"}
}