{
  "type": "Feature",
  "properties": {
    "addr:full":"82, Rue Galli\u00e9ni, 92773 Boulogne Billancourt C\u00e9dex 1 Ancourt Haute Normandie 76370",
    "addr:housenumber":"82;1",
    "addr:postcode":"92773;76370",
    "addr:street":"Rue Gallie\u0301Ni;Ce\u0301Dex;Haute Normandie",
    "iso:country":"FR",
    "sg:address":"82, Rue Galli\u00e9ni, 92773 Boulogne Billancourt C\u00e9dex 1",
    "sg:city":"Ancourt",
    "sg:orig_category":"Non-Classified Establishments",
    "sg:phone":"+33 1 48 25 44 55",
    "sg:postcode":"76370",
    "sg:province":"Haute Normandie",
    "wof:name":"Spinnaker Communication S.a.",
    "wof:placetype":"venue"
},
  "geometry": {"coordinates":[2.24347,48.83382],"type":"Point"}
}