{
  "type": "Feature",
  "properties": {
    "addr:full":"76, Rue Blaise Pascal - ZI des Mardelles, 93600 Aulnay sous Bois Ile de France",
    "addr:housenumber":"76",
    "addr:postcode":"93600",
    "addr:street":"Rue Blaise Pascal Zi Des Mardelles",
    "iso:country":"FR",
    "sg:address":"76, Rue Blaise Pascal - ZI des Mardelles, 93600 Aulnay sous Bois",
    "sg:orig_category":"Non-Classified Establishments",
    "sg:phone":"+33 1 48 66 20 31",
    "sg:province":"Ile de France",
    "wof:name":"Suburbaine Canalisations S.n.c.",
    "wof:placetype":"venue"
},
  "geometry": {"coordinates":[2.49124,48.927509],"type":"Point"}
}