{
  "type": "Feature",
  "properties": {
    "addr:full":"Bd Jean Moulin Brive la Gaillarde Limousin 19100",
    "addr:postcode":"19100",
    "addr:street":"Bd Jean Moulin Brive La Gaillarde Limousin",
    "iso:country":"FR",
    "sg:address":"Bd Jean Moulin",
    "sg:city":"Brive la Gaillarde",
    "sg:orig_category":"Unclassifiable Establishments",
    "sg:phone":"+33 5 55 86 12 24",
    "sg:postcode":"19100",
    "sg:province":"Limousin",
    "wof:name":"Laboratoire Dentaire Michel Gourdy S.a.",
    "wof:placetype":"venue"
},
  "geometry": {"coordinates":[1.502865,45.162785],"type":"Point"}
}