{
  "type": "Feature",
  "properties": {
    "iso:country":"FR",
    "sg:address":"26, Rue Brauhauban, 65000 Tarbes",
    "sg:orig_category":"Unclassifiable Establishments",
    "sg:phone":"+33 5 62 93 35 01",
    "sg:province":"Midi Pyr\u00e9n\u00e9es",
    "wof:name":"Imprimerie Dulout S.a.r.l.",
    "wof:placetype":"venue"
},
  "geometry": {"coordinates":[0.076213,43.232872],"type":"Point"}
}