{
  "type": "Feature",
  "properties": {
    "addr:full":"22 route de la Demi-Lune 92800 Puteaux Ile de France 92800",
    "addr:housenumber":"22",
    "addr:postcode":"92800;92800",
    "addr:street":"Route De La Demi-Lune",
    "iso:country":"FR",
    "sg:address":"22 route de la Demi-Lune 92800 Puteaux",
    "sg:classifiers":[
        {
            "category":"Manufacturing",
            "subcategory":"Glass & Minerals",
            "type":"Manufacturing & Wholesale Goods"
        }
    ],
    "sg:phone":"+33 1 55 91 30 00",
    "sg:postcode":"92800",
    "sg:province":"Ile de France",
    "sg:tags":[
        "mirror"
    ],
    "wof:name":"Glaverbel France S.a.",
    "wof:placetype":"venue"
},
  "geometry": {"coordinates":[2.234619,48.892448],"type":"Point"}
}