{
  "type": "Feature",
  "properties": {
    "iso:country":"FR",
    "sg:address":"24 Rue De L'Abb\u00e9 Munier 54120 Baccarat",
    "sg:classifiers":[
        {
            "category":"Professional",
            "subcategory":"Business Services",
            "type":"Services"
        }
    ],
    "sg:phone":"+33 3 83 76 10 10",
    "sg:postcode":"54120",
    "sg:province":"Lorraine",
    "sg:tags":[
        "body",
        "advice"
    ],
    "wof:name":"Association Dames De La Charite",
    "wof:placetype":"venue"
},
  "geometry": {"coordinates":[6.737442,48.447815],"type":"Point"}
}