{
  "type": "Feature",
  "properties": {
    "addr:full":"Rue Alexandre Adam Boulogne sur Mer Nord Pas-de-Calais 62200",
    "addr:postcode":"62200",
    "addr:street":"Rue Alexandre Adam Boulogne;Mer;Pas-De-Calais",
    "iso:country":"FR",
    "sg:address":"Rue Alexandre Adam",
    "sg:city":"Boulogne sur Mer",
    "sg:orig_category":"Unclassifiable Establishments",
    "sg:phone":"+33 3 21 10 03 90",
    "sg:postcode":"62200",
    "sg:province":"Nord Pas-de-Calais",
    "wof:name":"La Mouette Transports, S.a.",
    "wof:placetype":"venue"
},
  "geometry": {"coordinates":[1.59094,50.722881],"type":"Point"}
}