{
  "type": "Feature",
  "properties": {
    "addr:full":"38 Quai De La Madeleine 45000 Orl\u00e9ans Orl\u00e9ans Centre 45000",
    "addr:housenumber":"38",
    "addr:postcode":"45000;45000",
    "addr:street":"Quai De La Madeleine",
    "iso:country":"FR",
    "sg:address":"38 Quai De La Madeleine 45000 Orl\u00e9ans",
    "sg:city":"Orl\u00e9ans",
    "sg:classifiers":[
        {
            "category":"Banks & Credit Unions",
            "subcategory":"Investment Brokerage",
            "type":"Services"
        }
    ],
    "sg:phone":"+33 2 38 43 78 38",
    "sg:postcode":"45000",
    "sg:province":"Centre",
    "sg:tags":[
        "finance",
        "institution",
        "banking",
        "road",
        "insurance",
        "transport"
    ],
    "wof:name":"Brink's Evolution",
    "wof:placetype":"venue"
},
  "geometry": {"coordinates":[1.882237,47.89817],"type":"Point"}
}