{
  "type": "Feature",
  "properties": {
    "addr:full":"3, Av. Saint M\u00e9dard d'Eyrans, 33140 Cadaujac Cadaujac Aquitaine 33140",
    "addr:postcode":"33140;33140",
    "addr:street":"Av. Saint Me\u0301Dard D'Eyrans",
    "iso:country":"FR",
    "sg:address":"3, Av. Saint M\u00e9dard d'Eyrans, 33140 Cadaujac",
    "sg:city":"Cadaujac",
    "sg:orig_category":"Non-Classified Establishments",
    "sg:phone":"+33 5 56 94 37 32",
    "sg:postcode":"33140",
    "sg:province":"Aquitaine",
    "wof:name":"C.s.s. S.a.r.l. - Compagnie Surveillance S\u00e9curit\u00e9",
    "wof:placetype":"venue"
},
  "geometry": {"coordinates":[-0.530376,44.752831],"type":"Point"}
}