{
  "type": "Feature",
  "properties": {
    "addr:full":"5, Rue du Domaine, 35137 B\u00e9d\u00e9e B\u00e9d\u00e9e Bretagne 35137",
    "addr:housenumber":"5",
    "addr:postcode":"35137;35137",
    "addr:street":"Rue Du Domaine",
    "iso:country":"FR",
    "sg:address":"5, Rue du Domaine, 35137 B\u00e9d\u00e9e",
    "sg:city":"B\u00e9d\u00e9e",
    "sg:orig_category":"Unclassifiable Establishments",
    "sg:phone":"+33 2 99 07 10 88",
    "sg:postcode":"35137",
    "sg:province":"Bretagne",
    "wof:name":"Avi - Clim Ultrasonics S.a.r.l.",
    "wof:placetype":"venue"
},
  "geometry": {"coordinates":[-1.935458,48.181351],"type":"Point"}
}