{
  "type": "Feature",
  "properties": {
    "addr:full":"8 Rue Du Bourgamon 38400 St Martin D'H\u00e8res Rhone-Alpes 38400",
    "addr:housenumber":"8",
    "addr:postcode":"38400;38400",
    "addr:street":"Rue Du Bourgamon;Rhone-Alpes",
    "iso:country":"FR",
    "sg:address":"8 Rue Du Bourgamon 38400 St Martin D'H\u00e8res",
    "sg:classifiers":[
        {
            "category":"Food & Beverages",
            "subcategory":"Groceries & Convenience Stores",
            "type":"Retail Goods"
        }
    ],
    "sg:phone":"+33 4 76 24 02 72",
    "sg:postcode":"38400",
    "sg:province":"Rhone-Alpes",
    "sg:tags":[
        "product",
        "related"
    ],
    "wof:name":"Comptoir France Italie Sa",
    "wof:placetype":"venue"
},
  "geometry": {"coordinates":[5.76039,45.16732],"type":"Point"}
}