{
  "type": "Feature",
  "properties": {
    "addr:full":"33 rue du G\u00e9n\u00e9ral; Maiche; 25120 Franche Comt\u00e9 25120",
    "addr:housenumber":"33",
    "addr:postcode":"25120;25120",
    "addr:street":"Rue Du Ge\u0301Ne\u0301Ral Maiche;Franche Comte\u0301",
    "iso:country":"FR",
    "sg:address":"33 rue du G\u00e9n\u00e9ral; Maiche; 25120",
    "sg:classifiers":[
        {
            "category":"Banks & Credit Unions",
            "subcategory":"Bank",
            "type":"Services"
        }
    ],
    "sg:phone":"+33 3 81 64 03 78",
    "sg:postcode":"25120",
    "sg:province":"Franche Comt\u00e9",
    "wof:name":"Cr\u00e9dit Industriel D'alsace, Et De Lorraine Sa",
    "wof:placetype":"venue"
},
  "geometry": {"coordinates":[6.798859,47.249786],"type":"Point"}
}