{
  "type": "Feature",
  "properties": {
    "addr:full":"11 B Rue Rene Char 21000 Dijon Dijon Bourgogne 21000",
    "addr:housenumber":"11 b",
    "addr:postcode":"21000;21000",
    "addr:street":"Rue Rene Char",
    "iso:country":"FR",
    "sg:address":"11 B Rue Rene Char 21000 Dijon",
    "sg:city":"Dijon",
    "sg:classifiers":[
        {
            "category":"Health Services",
            "subcategory":"Medical Lab",
            "type":"Services"
        }
    ],
    "sg:phone":"+33 3 80 78 74 00",
    "sg:postcode":"21000",
    "sg:province":"Bourgogne",
    "sg:tags":[
        "chemical",
        "pharmaceutical",
        "pharmacy"
    ],
    "wof:name":"Merck Monot",
    "wof:placetype":"venue"
},
  "geometry": {"coordinates":[5.05707,47.353336],"type":"Point"}
}