{
  "type": "Feature",
  "properties": {
    "addr:full":"153 rue des 3 Tilleuls 77000 Vaux Le Penil Ile de France 77000",
    "addr:housenumber":"153",
    "addr:postcode":"77000;77000",
    "addr:street":"Rue Des 3 Tilleuls",
    "iso:country":"FR",
    "sg:address":"153 rue des 3 Tilleuls 77000 Vaux Le Penil",
    "sg:classifiers":[
        {
            "category":"Food & Beverages",
            "subcategory":"Meat & Fish",
            "type":"Retail Goods"
        }
    ],
    "sg:phone":"+33 1 64 37 32 59",
    "sg:postcode":"77000",
    "sg:province":"Ile de France",
    "sg:tags":[
        "sausage"
    ],
    "wof:name":"Ste De Diffusion De Produits Regionaux Sa",
    "wof:placetype":"venue"
},
  "geometry": {"coordinates":[2.685986,48.535393],"type":"Point"}
}