{
  "type": "Feature",
  "properties": {
    "addr:full":"Marclaz Z Commerciale 74200 Thonon les Bains Rhone-Alpes 74200",
    "addr:postcode":"74200;74200",
    "addr:street":"Commerciale",
    "iso:country":"FR",
    "sg:address":"Marclaz Z Commerciale 74200 Thonon les Bains",
    "sg:classifiers":[
        {
            "category":"Sports & Exercise",
            "subcategory":"Ski Slope",
            "type":"Entertainment"
        }
    ],
    "sg:phone":"+33 4 50 71 71 38",
    "sg:postcode":"74200",
    "sg:province":"Rhone-Alpes",
    "sg:tags":[
        "accessory"
    ],
    "wof:name":"Loisiralp Sarl",
    "wof:placetype":"venue"
},
  "geometry": {"coordinates":[6.61462,46.305523],"type":"Point"}
}