{
  "type": "Feature",
  "properties": {
    "addr:full":"8, Rue de Saint Nazaire, 67100 Strasbourg Strasbourg Alsace 67100",
    "addr:housenumber":"8",
    "addr:postcode":"67100;67100",
    "addr:street":"Rue De Saint Nazaire",
    "iso:country":"FR",
    "sg:address":"8, Rue de Saint Nazaire, 67100 Strasbourg",
    "sg:city":"Strasbourg",
    "sg:orig_category":"Unclassifiable Establishments",
    "sg:phone":"+33 3 88 40 54 54",
    "sg:postcode":"67100",
    "sg:province":"Alsace",
    "wof:name":"S.i.l. Fala S.a.r.l. - Soci\u00e9t\u00e9 Industrielle De Levure Fala",
    "wof:placetype":"venue"
},
  "geometry": {"coordinates":[7.782149,48.532402],"type":"Point"}
}