{
  "type": "Feature",
  "properties": {
    "iso:country":"FR",
    "sg:address":"44 Rue Pasteur 80170 Rosieres En Santerre",
    "sg:orig_category":"Miscellaneous Products",
    "sg:phone":"+33 3 22 88 02 99",
    "sg:postcode":"80170",
    "sg:province":"Picardie",
    "wof:name":"Etablissements P Dubosqueille",
    "wof:placetype":"venue"
},
  "geometry": {"coordinates":[2.701015,49.816235],"type":"Point"}
}