{
  "type": "Feature",
  "properties": {
    "iso:country":"FR",
    "sg:address":"1 Bis Rue De La Sauvaie Zi Sud-Est 35000 Rennes",
    "sg:city":"Rennes",
    "sg:classifiers":[
        {
            "category":"Professional",
            "subcategory":"Engineering",
            "type":"Services"
        }
    ],
    "sg:phone":"+33 2 99 86 13 60",
    "sg:postcode":"35000",
    "sg:province":"Bretagne",
    "sg:tags":[
        "machine",
        "-",
        "mechanical"
    ],
    "wof:name":"Serifi Efm",
    "wof:placetype":"venue"
},
  "geometry": {"coordinates":[-1.684477,48.107521],"type":"Point"}
}