{
  "type": "Feature",
  "properties": {
    "addr:full":"11, Av. Guillemin, 92600 Asni\u00e8res sur Seine Ile de France",
    "addr:postcode":"92600",
    "addr:street":"11 Av. Guillemin",
    "iso:country":"FR",
    "sg:address":"11, Av. Guillemin, 92600 Asni\u00e8res sur Seine",
    "sg:orig_category":"Unclassifiable Establishments",
    "sg:phone":"+33 1 41 11 35 00",
    "sg:province":"Ile de France",
    "wof:name":"Hoiret Et Fils S.a.",
    "wof:placetype":"venue"
},
  "geometry": {"coordinates":[2.28337,48.91819],"type":"Point"}
}