{
  "type": "Feature",
  "properties": {
    "addr:full":"Chemin des Marais - ZI Saint Brice Courcelles Champagne 51370",
    "addr:postcode":"51370",
    "addr:street":"Chemin Des Marais Zi Saint Brice",
    "iso:country":"FR",
    "sg:address":"Chemin des Marais - ZI",
    "sg:city":"Saint Brice Courcelles",
    "sg:orig_category":"Non-Classified Establishments",
    "sg:phone":"+33 3 26 84 68 00",
    "sg:postcode":"51370",
    "sg:province":"Champagne",
    "wof:name":"Dectra S.a.",
    "wof:placetype":"venue"
},
  "geometry": {"coordinates":[3.985995,49.261791],"type":"Point"}
}