{
  "type": "Feature",
  "properties": {
    "iso:country":"FR",
    "sg:address":"B.P. 37",
    "sg:city":"Gray^^70100 Velet",
    "sg:orig_category":"Non-Classified Establishments",
    "sg:phone":"+33 3 84 65 46 66",
    "sg:postcode":"70100",
    "sg:province":"Franche Comt\u00e9",
    "wof:name":"Zancarini Fr\u00e8res S.a.",
    "wof:placetype":"venue"
},
  "geometry": {"coordinates":[5.514565,47.369511],"type":"Point"}
}