{
  "type": "Feature",
  "properties": {
    "addr:full":"14 Rue Des Martyrs Elbeuf Haute Normandie 76500",
    "addr:housenumber":"14",
    "addr:postcode":"76500",
    "addr:street":"Rue Des Martyrs;Haute Normandie",
    "iso:country":"FR",
    "sg:address":"14 Rue Des Martyrs",
    "sg:city":"Elbeuf",
    "sg:classifiers":[
        {
            "category":"Banks & Credit Unions",
            "subcategory":"Financial Services",
            "type":"Services"
        }
    ],
    "sg:phone":"+33 2 35 81 24 52",
    "sg:postcode":"76500",
    "sg:province":"Haute Normandie",
    "sg:tags":[
        "banking",
        "finance",
        "insurance"
    ],
    "wof:name":"Credit Du Nord",
    "wof:placetype":"venue"
},
  "geometry": {"coordinates":[1.007938,49.287827],"type":"Point"}
}