{
  "type": "Feature",
  "properties": {
    "addr:full":"17 Quai Du Pr\u00e9sident Paul Doumer 92400 Courbevoie Cedex Ile de France 92400",
    "addr:housenumber":"17",
    "addr:postcode":"92400;ile;92400",
    "addr:street":"Quai Du Pre\u0301Sident Paul Doumer;France",
    "iso:country":"FR",
    "sg:address":"17 Quai Du Pr\u00e9sident Paul Doumer 92400 Courbevoie Cedex",
    "sg:classifiers":[
        {
            "category":"Shopping",
            "subcategory":"Stationery & Office Supplies",
            "type":"Retail Goods"
        }
    ],
    "sg:phone":"+33 1 41 99 77 77",
    "sg:postcode":"92400",
    "sg:province":"Ile de France",
    "sg:tags":[
        "information",
        "technology",
        "telecommunication",
        "equipment"
    ],
    "wof:name":"Canon-france Sa",
    "wof:placetype":"venue"
},
  "geometry": {"coordinates":[2.256968,48.890877],"type":"Point"}
}