{
  "type": "Feature",
  "properties": {
    "iso:country":"FR",
    "sg:address":"18bis, Av. de la Motte Picquet, 75007 Paris",
    "sg:orig_category":"Unclassifiable Establishments",
    "sg:phone":"+33 1 44 18 45 15",
    "sg:province":"Ile de France",
    "wof:name":"D.g. Interactive S.a. - Desgrippes Gob\u00e9 Interactive",
    "wof:placetype":"venue"
},
  "geometry": {"coordinates":[2.308162,48.856365],"type":"Point"}
}