{
  "type": "Feature",
  "properties": {
    "iso:country":"FR",
    "sg:address":"82 Rue Jules Ferry 22000 St Brieuc",
    "sg:city":"Saint-Brieuc",
    "sg:classifiers":[
        {
            "category":"Manufacturing",
            "subcategory":"Metals",
            "type":"Manufacturing & Wholesale Goods"
        }
    ],
    "sg:phone":"+33 2 96 01 57 57",
    "sg:postcode":"22000",
    "sg:province":"Bretagne",
    "sg:tags":[
        "metallurgy",
        "steel",
        "metalworking"
    ],
    "wof:name":"Manoir Industries",
    "wof:placetype":"venue"
},
  "geometry": {"coordinates":[-2.769994,48.500706],"type":"Point"}
}