{
  "type": "Feature",
  "properties": {
    "iso:country":"FR",
    "sg:address":"75, Rue Nationale, 49770 La Membrolle sur Longuen\u00e9e",
    "sg:orig_category":"Non-Classified Establishments",
    "sg:phone":"+33 2 41 31 45 00",
    "sg:province":"Picardie",
    "wof:name":"Andr\u00e9 Bouvet S.a.",
    "wof:placetype":"venue"
},
  "geometry": {"coordinates":[-0.669794,47.519283],"type":"Point"}
}