{
  "type": "Feature",
  "properties": {
    "iso:country":"FR",
    "sg:address":"15 rue Victor Baltard 77410 Claye Souilly",
    "sg:classifiers":[
        {
            "category":"Home & Garden",
            "subcategory":"Furniture",
            "type":"Retail Goods"
        }
    ],
    "sg:phone":"+33 1 60 26 77 77",
    "sg:postcode":"77410",
    "sg:province":"Ile de France",
    "sg:tags":[
        "packaging",
        "contract",
        "basis"
    ],
    "wof:name":"Naf Sarl",
    "wof:placetype":"venue"
},
  "geometry": {"coordinates":[2.672314,48.944981],"type":"Point"}
}