{
  "type": "Feature",
  "properties": {
    "iso:country":"FR",
    "sg:address":"15, Chemin du Halage - Zone Industrielle, 76300 Sotteville l\u00e8s Rouen",
    "sg:orig_category":"Non-Classified Establishments",
    "sg:phone":"+33 2 35 03 81 33",
    "sg:province":"Haute Normandie",
    "wof:name":"Pum Plastiques S.a.",
    "wof:placetype":"venue"
},
  "geometry": {"coordinates":[1.089274,49.414249],"type":"Point"}
}