{
  "type": "Feature",
  "properties": {
    "iso:country":"FR",
    "sg:address":"Les Martingales 26120 Chabeuil",
    "sg:classifiers":[
        {
            "category":"Professional",
            "subcategory":"Engineering",
            "type":"Services"
        }
    ],
    "sg:phone":"+33 4 75 85 26 82",
    "sg:postcode":"26120",
    "sg:province":"Rhone-Alpes",
    "sg:tags":[
        "machine",
        "-",
        "environment",
        "equipment",
        "machinery",
        "mechanical"
    ],
    "wof:name":"Fargier Ets Sa",
    "wof:placetype":"venue"
},
  "geometry": {"coordinates":[4.942149,44.920265],"type":"Point"}
}