{
  "type": "Feature",
  "properties": {
    "iso:country":"FR",
    "sg:address":"147, RN 2 - ZI des Marais, 38510 Morestel",
    "sg:orig_category":"Non-Classified Establishments",
    "sg:phone":"+33 4 74 80 23 00",
    "sg:postcode":"38510",
    "sg:province":"Rhone-Alpes",
    "wof:name":"S.o.m.e.p. S.a. - Soci\u00e9t\u00e9 M\u00e9tallurgique De Pr\u00e9cision",
    "wof:placetype":"venue"
},
  "geometry": {"coordinates":[5.420305,45.650581],"type":"Point"}
}