{
  "type": "Feature",
  "properties": {
    "addr:full":"Chemin du Ch\u00eane Lorry l\u00e8s Metz Lorraine 57000",
    "addr:postcode":"57000",
    "addr:street":"Chemin Du Che\u0302Ne",
    "iso:country":"FR",
    "sg:address":"Chemin du Ch\u00eane",
    "sg:city":"Lorry l\u00e8s Metz",
    "sg:orig_category":"Unclassifiable Establishments",
    "sg:phone":"+33 3 87 30 22 00",
    "sg:postcode":"57000",
    "sg:province":"Lorraine",
    "wof:name":"R.t.c. S.a.r.l. - R\u00e9alisations Techniques Et Commerciales",
    "wof:placetype":"venue"
},
  "geometry": {"coordinates":[-94.44761699999999,37.995975],"type":"Point"}
}