{
  "type": "Feature",
  "properties": {
    "iso:country":"FR",
    "sg:address":"3, Av. du Canada - Parc Technopolis - B\u00e2timent B\u00eata, 91974 Courtaboeuf C\u00e9dex",
    "sg:orig_category":"Non-Classified Establishments",
    "sg:phone":"+33 1 60 92 88 00",
    "sg:province":"Aquitaine",
    "wof:name":"A.i.m.d.f. S.a.",
    "wof:placetype":"venue"
},
  "geometry": {"coordinates":[-96.582092,62.35873],"type":"Point"}
}