{
  "type": "Feature",
  "properties": {
    "iso:country":"FR",
    "sg:address":"54, Rue Alexandre Dumas, 02600 Villers Cotter\u00eats",
    "sg:orig_category":"Non-Classified Establishments",
    "sg:phone":"+33 3 23 96 45 45",
    "sg:province":"Picardie",
    "wof:name":"Tecame S.a.",
    "wof:placetype":"venue"
},
  "geometry": {"coordinates":[3.094625,49.251373],"type":"Point"}
}