{
  "type": "Feature",
  "properties": {
    "addr:full":"2 Georges Leygues; Villeneuve sur Lot; 47300 Aquitaine 47300",
    "addr:housenumber":"2",
    "addr:postcode":"47300;47300",
    "addr:street":"Georges Leygues",
    "iso:country":"FR",
    "sg:address":"2",
    "sg:city":"Georges Leygues; Villeneuve sur Lot; 47300",
    "sg:classifiers":[
        {
            "category":"Banks & Credit Unions",
            "subcategory":"Bank",
            "type":"Services"
        }
    ],
    "sg:phone":"+33 3353706003",
    "sg:postcode":"47300",
    "sg:province":"Aquitaine",
    "wof:name":"Banque Nationale De Paris",
    "wof:placetype":"venue"
},
  "geometry": {"coordinates":[0.707418,44.408619],"type":"Point"}
}