{
  "type": "Feature",
  "properties": {
    "iso:country":"FR",
    "sg:address":"5, Chemin des Fontaines, 74100 Vetraz Monthoux",
    "sg:orig_category":"Non-Classified Establishments",
    "sg:phone":"+33 4 50 37 26 07",
    "sg:postcode":"74100",
    "sg:province":"Rhone-Alpes",
    "wof:name":"O.t.s. S.a. - Outils Techniques Scientifiques",
    "wof:placetype":"venue"
},
  "geometry": {"coordinates":[6.27278,46.187519],"type":"Point"}
}