{
  "type": "Feature",
  "properties": {
    "iso:country":"FR",
    "sg:address":"Cidoux 512 14410 Vassy",
    "sg:city":"Vassy",
    "sg:classifiers":[
        {
            "category":"Farming",
            "subcategory":"Farm & Veterinary Services",
            "type":"Manufacturing & Wholesale Goods"
        }
    ],
    "sg:phone":"+33 2 31 67 78 14",
    "sg:postcode":"14410",
    "sg:province":"Basse Normandie",
    "sg:tags":[
        "food",
        "product",
        "breeding",
        "animal",
        "related"
    ],
    "wof:name":"Cooperative Agrial",
    "wof:placetype":"venue"
},
  "geometry": {"coordinates":[-0.735887,48.813183],"type":"Point"}
}