{
  "type": "Feature",
  "properties": {
    "iso:country":"FR",
    "sg:address":"43, All\u00e9e du 12 F\u00e9vrier 1934, 77186 Noisiel",
    "sg:orig_category":"Unclassifiable Establishments",
    "sg:phone":"+33 1 60 95 07 00",
    "sg:province":"Ile de France",
    "wof:name":"F.p.s. S.a. - France Prot\u00e9ines Services",
    "wof:placetype":"venue"
},
  "geometry": {"coordinates":[2.61964,48.84248],"type":"Point"}
}