{
  "type": "Feature",
  "properties": {
    "iso:country":"FR",
    "sg:address":"2",
    "sg:city":"Flourens 75017 Paris",
    "sg:classifiers":[
        {
            "category":"Professional",
            "type":"Services"
        }
    ],
    "sg:phone":"+33 1 58 59 14 79",
    "sg:province":"Ile de France",
    "sg:tags":[
        "transport",
        "road"
    ],
    "wof:name":"Tad",
    "wof:placetype":"venue"
},
  "geometry": {"coordinates":[2.32649,48.897335],"type":"Point"}
}