{
  "type": "Feature",
  "properties": {
    "iso:country":"FR",
    "sg:address":"Zi 77100 Meaux",
    "sg:classifiers":[
        {
            "category":"Wholesale",
            "subcategory":"Machinery & Supplies",
            "type":"Manufacturing & Wholesale Goods"
        }
    ],
    "sg:phone":"+33 1 60 25 25 25",
    "sg:postcode":"77100",
    "sg:province":"Ile de France",
    "sg:tags":[
        "handling",
        "material",
        "-",
        "machine",
        "equipment",
        "engineering",
        "mechanical"
    ],
    "wof:name":"Transports Bour Sarl",
    "wof:placetype":"venue"
},
  "geometry": {"coordinates":[2.883054,48.959351],"type":"Point"}
}