{
  "type": "Feature",
  "properties": {
    "addr:full":"3, Rue de Foubastard, 31000 Toulouse Midi Pyr\u00e9n\u00e9es 31000",
    "addr:housenumber":"3",
    "addr:postcode":"31000;31000",
    "addr:street":"Rue De Foubastard",
    "iso:country":"FR",
    "sg:address":"3, Rue de Foubastard, 31000 Toulouse",
    "sg:orig_category":"Non-Classified Establishments",
    "sg:phone":"+33 5 61 22 45 42",
    "sg:postcode":"31000",
    "sg:province":"Midi Pyr\u00e9n\u00e9es",
    "wof:name":"Etablissements Falconetti S.a.r.l.",
    "wof:placetype":"venue"
},
  "geometry": {"coordinates":[1.445291,43.602631],"type":"Point"}
}