{
  "type": "Feature",
  "properties": {
    "iso:country":"FR",
    "sg:address":"Parc Industriel",
    "sg:city":"La Br\u00fblatte",
    "sg:orig_category":"Unclassifiable Establishments",
    "sg:phone":"+33 2 43 68 86 62",
    "sg:postcode":"53410",
    "sg:province":"Pays de Loire",
    "wof:name":"Adalid S.a.",
    "wof:placetype":"venue"
},
  "geometry": {"coordinates":[-1.013198,48.072639],"type":"Point"}
}