{
  "type": "Feature",
  "properties": {
    "addr:full":"17 Avenue Jean M\u00e9decin, 06000 Nice, Dept 06",
    "addr:housenumber":"17;06",
    "addr:postcode":"06000",
    "addr:street":"Avenue Jean Me\u0301Decin",
    "iso:country":"FR",
    "sg:address":"17 Avenue Jean M\u00e9decin, 06000 Nice, Dept 06",
    "sg:classifiers":[
        {
            "category":"Banks & Credit Unions",
            "subcategory":"Bank",
            "type":"Services"
        }
    ],
    "wof:name":"Banque Ni\u00e7oise De Cr\u00e9dit",
    "wof:placetype":"venue"
},
  "geometry": {"coordinates":[7.268186,43.699867],"type":"Point"}
}