{
  "type": "Feature",
  "properties": {
    "addr:full":"9 J. Fontaine 77510 REBAIS Ile de France 77510",
    "addr:housenumber":"9",
    "addr:postcode":"77510;ile;77510",
    "addr:street":"J. Fontaine;France",
    "iso:country":"FR",
    "sg:address":"9",
    "sg:city":"J. Fontaine 77510 REBAIS",
    "sg:classifiers":[
        {
            "category":"Professional",
            "subcategory":"Engineering",
            "type":"Services"
        }
    ],
    "sg:phone":"+33 1 64 04 51 80",
    "sg:postcode":"77510",
    "sg:province":"Ile de France",
    "sg:tags":[
        "machine",
        "-",
        "mechanical"
    ],
    "wof:name":"Tecma Pack",
    "wof:placetype":"venue"
},
  "geometry": {"coordinates":[3.237409,48.850063],"type":"Point"}
}