{
  "type": "Feature",
  "properties": {
    "addr:full":"99, Bd Thiers, 37000 Tours Tours Centre 37000",
    "addr:housenumber":"99",
    "addr:postcode":"37000;37000",
    "addr:street":"Bd Thiers",
    "iso:country":"FR",
    "sg:address":"99, Bd Thiers, 37000 Tours",
    "sg:city":"Tours",
    "sg:orig_category":"Non-Classified Establishments",
    "sg:phone":"+33 2 47 38 32 20",
    "sg:postcode":"37000",
    "sg:province":"Centre",
    "wof:name":"Lamalle Ing\u00e9nierie S.a.r.l.",
    "wof:placetype":"venue"
},
  "geometry": {"coordinates":[0.685636,47.381142],"type":"Point"}
}