{
  "type": "Feature",
  "properties": {
    "addr:full":"107, Bd Antonio Vivaldi, 42000 Saint Etienne Rhone-Alpes",
    "addr:housenumber":"107",
    "addr:postcode":"42000",
    "addr:street":"Bd Antonio Vivaldi",
    "iso:country":"FR",
    "sg:address":"107, Bd Antonio Vivaldi, 42000 Saint Etienne",
    "sg:orig_category":"Non-Classified Establishments",
    "sg:phone":"+33 4 77 93 08 02",
    "sg:province":"Rhone-Alpes",
    "wof:name":"Unim\u00e9ca S.a.",
    "wof:placetype":"venue"
},
  "geometry": {"coordinates":[4.40538,45.471161],"type":"Point"}
}