{
  "type": "Feature",
  "properties": {
    "addr:full":"B.P. 1109, 08090 Tournes^^ZI de Tournes, 08090 Tournes Aiglemont Champagne 08090",
    "addr:housenumber":"1109",
    "addr:postcode":"08090;08090;08090",
    "addr:street":"B.P.;Tournes;Champagne",
    "iso:country":"FR",
    "sg:address":"B.P. 1109, 08090 Tournes^^ZI de Tournes, 08090 Tournes",
    "sg:city":"Aiglemont",
    "sg:orig_category":"Non-Classified Establishments",
    "sg:phone":"+33 3 24 52 91 21",
    "sg:postcode":"08090",
    "sg:province":"Champagne",
    "wof:name":"Smith & Nephew Kinetec S.a.",
    "wof:placetype":"venue"
},
  "geometry": {"coordinates":[4.667313,49.792923],"type":"Point"}
}