{
  "type": "Feature",
  "properties": {
    "addr:full":"Rue De Meyrin Immeuble Bois Candide 01210 Ferney Voltaire Rhone-Alpes 01210",
    "addr:postcode":"01210;01210",
    "addr:street":"Rue De Meyrin",
    "iso:country":"FR",
    "sg:address":"Rue De Meyrin Immeuble Bois Candide 01210 Ferney Voltaire",
    "sg:classifiers":[
        {
            "category":"Wholesale",
            "subcategory":"Medical Equipment & Supplies",
            "type":"Manufacturing & Wholesale Goods"
        }
    ],
    "sg:phone":"+33 4 50 40 16 75",
    "sg:postcode":"01210",
    "sg:province":"Rhone-Alpes",
    "sg:tags":[
        "instrument",
        "health",
        "-",
        "precision"
    ],
    "wof:name":"Sarl Procitec",
    "wof:placetype":"venue"
},
  "geometry": {"coordinates":[6.108815,46.25436],"type":"Point"}
}