{
  "type": "Feature",
  "properties": {
    "addr:full":"16 Bis Rue Bir-Hakeim 94480 Ablon Sur Seine Ile de France 94480",
    "addr:housenumber":"16 bis",
    "addr:postcode":"94480;94480",
    "addr:street":"Rue Bir-Hakeim;France",
    "iso:country":"FR",
    "sg:address":"16 Bis Rue Bir-Hakeim 94480 Ablon Sur Seine",
    "sg:classifiers":[
        {
            "category":"Wholesale",
            "subcategory":"Medical Equipment & Supplies",
            "type":"Manufacturing & Wholesale Goods"
        }
    ],
    "sg:phone":"+33 1 45 97 65 25",
    "sg:postcode":"94480",
    "sg:province":"Ile de France",
    "sg:tags":[
        "instrument",
        "health",
        "-",
        "precision"
    ],
    "wof:name":"Crimo France Sarl",
    "wof:placetype":"venue"
},
  "geometry": {"coordinates":[2.421426,48.727196],"type":"Point"}
}