{
  "type": "Feature",
  "properties": {
    "addr:full":"77, Rte de Luxeuil, 70220 Fougerolles Franche Comt\u00e9",
    "addr:housenumber":"77",
    "addr:postcode":"70220",
    "addr:street":"Rte De Luxeuil;Franche Comte\u0301",
    "iso:country":"FR",
    "sg:address":"77, Rte de Luxeuil, 70220 Fougerolles",
    "sg:orig_category":"Unclassifiable Establishments",
    "sg:phone":"+33 3 84 49 10 44",
    "sg:province":"Franche Comt\u00e9",
    "wof:name":"Ateliers D'impressions Pierre Buriot S.a.",
    "wof:placetype":"venue"
},
  "geometry": {"coordinates":[6.398006,47.883934],"type":"Point"}
}