{
  "type": "Feature",
  "properties": {
    "addr:full":"9 Pl Des Vosges Immeuble Newton 92400 Courbevoie Ile de France 92400",
    "addr:housenumber":"9",
    "addr:postcode":"92400;92400",
    "addr:street":"Pl Des Vosges",
    "iso:country":"FR",
    "sg:address":"9 Pl Des Vosges Immeuble Newton 92400 Courbevoie",
    "sg:classifiers":[
        {
            "category":"Shopping",
            "subcategory":"Computers & Home Electronics",
            "type":"Retail Goods"
        }
    ],
    "sg:phone":"+33 1 46 67 40 00",
    "sg:postcode":"92400",
    "sg:province":"Ile de France",
    "sg:tags":[
        "information",
        "peripheral",
        "-",
        "technology"
    ],
    "wof:name":"Lexmark International Services Gie",
    "wof:placetype":"venue"
},
  "geometry": {"coordinates":[2.247935,48.89275],"type":"Point"}
}