{
  "type": "Feature",
  "properties": {
    "addr:full":"Port Fluvial Zi Du Stand 71000 Macon Sanc\u00e9 Bourgogne 71000",
    "addr:postcode":"71000;71000",
    "addr:street":"Port;Zi Du Stand",
    "iso:country":"FR",
    "sg:address":"Port Fluvial Zi Du Stand 71000 Macon",
    "sg:city":"Sanc\u00e9",
    "sg:classifiers":[
        {
            "category":"Utilities",
            "subcategory":"Electric",
            "type":"Services"
        }
    ],
    "sg:phone":"+33 3 85 38 46 00",
    "sg:postcode":"71000",
    "sg:province":"Bourgogne",
    "sg:tags":[
        "electricity",
        "electronic",
        "electrical",
        "equipment"
    ],
    "wof:name":"Facen",
    "wof:placetype":"venue"
},
  "geometry": {"coordinates":[4.833055,46.303043],"type":"Point"}
}