{
  "type": "Feature",
  "properties": {
    "addr:full":"La Rougerie 35680 Louvign\u00e9 de Bais Bais Bretagne 35680",
    "addr:postcode":"35680;35680",
    "addr:street":"Rougerie",
    "iso:country":"FR",
    "sg:address":"La Rougerie 35680 Louvign\u00e9 de Bais",
    "sg:city":"Bais",
    "sg:orig_category":"Non-Classified Establishments",
    "sg:phone":"+33 2 99 49 00 32",
    "sg:postcode":"35680",
    "sg:province":"Bretagne",
    "wof:name":"Ch\u00e2taign\u00e8re",
    "wof:placetype":"venue"
},
  "geometry": {"coordinates":[-1.308189,48.058762],"type":"Point"}
}