{
  "type": "Feature",
  "properties": {
    "addr:full":"2 All Des Bouleaux 54840 Velaine En Haye Lorraine",
    "addr:housenumber":"2",
    "addr:postcode":"54840",
    "addr:street":"All Des Bouleaux",
    "iso:country":"FR",
    "sg:address":"2 All Des Bouleaux 54840 Velaine En Haye",
    "sg:classifiers":[
        {
            "category":"Manufacturing",
            "subcategory":"Printing",
            "type":"Manufacturing & Wholesale Goods"
        }
    ],
    "sg:phone":"+33 3 83 95 66 66",
    "sg:province":"Lorraine",
    "sg:tags":[
        "publishing"
    ],
    "wof:name":"Serica",
    "wof:placetype":"venue"
},
  "geometry": {"coordinates":[6.050055,48.69846],"type":"Point"}
}