{
  "type": "Feature",
  "properties": {
    "iso:country":"FR",
    "sg:address":"4 Rue De L'Industrie 91210 Draveil",
    "sg:classifiers":[
        {
            "category":"Manufacturing",
            "subcategory":"Rubber & Plastics",
            "type":"Manufacturing & Wholesale Goods"
        }
    ],
    "sg:phone":"+33 1 69 40 15 20",
    "sg:province":"Ile de France",
    "wof:name":"Ste De Thermoformage De L Ouest Parisien",
    "wof:placetype":"venue"
},
  "geometry": {"coordinates":[2.435812,48.68541],"type":"Point"}
}