{
  "type": "Feature",
  "properties": {
    "iso:country":"FR",
    "sg:address":"3, Grande Rue, 25790 Les Gras",
    "sg:orig_category":"Non-Classified Establishments",
    "sg:phone":"+33 3 81 68 80 80",
    "sg:province":"Franche Comt\u00e9",
    "wof:name":"M\u00e9canique G\u00e9n\u00e9rale Des Gras S.a.r.l.",
    "wof:placetype":"venue"
},
  "geometry": {"coordinates":[6.543885,46.995026],"type":"Point"}
}