{
  "type": "Feature",
  "properties": {
    "iso:country":"FR",
    "sg:address":"29/31, Rue Gabriel P\u00e9ri, 94220 Charenton le Pont",
    "sg:orig_category":"Unclassifiable Establishments",
    "sg:phone":"+33 1 41 79 42 42",
    "sg:province":"Ile de France",
    "wof:name":"La Documentation Directe S.a.",
    "wof:placetype":"venue"
},
  "geometry": {"coordinates":[2.419371,48.8204],"type":"Point"}
}