{
  "type": "Feature",
  "properties": {
    "iso:country":"FR",
    "sg:address":"29 Rue Descombes 75017 Paris",
    "sg:classifiers":[
        {
            "category":"Professional",
            "subcategory":"Advertising",
            "type":"Services"
        }
    ],
    "sg:phone":"+33 1 42 27 84 84",
    "sg:postcode":"75017",
    "sg:province":"Ile de France",
    "sg:tags":[
        "marketing",
        "medium",
        "communication"
    ],
    "wof:name":"Agence Te",
    "wof:placetype":"venue"
},
  "geometry": {"coordinates":[2.291761,48.885311],"type":"Point"}
}