{
  "type": "Feature",
  "properties": {
    "addr:full":"Gourette Villagium Lou Sarri 64440 Eaux Bonnes B\u00e9ost Aquitaine 64440",
    "addr:postcode":"64440;64440",
    "addr:street":"Eaux",
    "iso:country":"FR",
    "sg:address":"Gourette Villagium Lou Sarri 64440 Eaux Bonnes",
    "sg:city":"B\u00e9ost",
    "sg:classifiers":[
        {
            "category":"Sports & Exercise",
            "subcategory":"Sports Center",
            "type":"Entertainment"
        }
    ],
    "sg:phone":"+33 5 59 05 10 15",
    "sg:postcode":"64440",
    "sg:province":"Aquitaine",
    "sg:tags":[
        "game"
    ],
    "wof:name":"Vvf Vacances",
    "wof:placetype":"venue"
},
  "geometry": {"coordinates":[-0.424929,42.988121],"type":"Point"}
}