{
  "type": "Feature",
  "properties": {
    "iso:country":"FR",
    "sg:address":"16, Rue des Ecoles, 41210 La Marolle en Sologne",
    "sg:city":"La Fert\u00e9-Beauharnais",
    "sg:orig_category":"Unclassifiable Establishments",
    "sg:phone":"+33 2 54 83 76 36",
    "sg:postcode":"41210",
    "sg:province":"Centre",
    "wof:name":"Le Pays De L'andan S.a.r.l.",
    "wof:placetype":"venue"
},
  "geometry": {"coordinates":[1.78101,47.581139],"type":"Point"}
}