{
  "type": "Feature",
  "properties": {
    "iso:country":"FR",
    "sg:address":"Morains le Petit 51130 Vertus",
    "sg:classifiers":[
        {
            "category":"Recreation",
            "subcategory":"Water Park",
            "type":"Entertainment"
        }
    ],
    "sg:phone":"+33 3 26 52 25 31",
    "sg:postcode":"51130",
    "sg:province":"Champagne",
    "sg:tags":[
        "alcohol",
        "ethyl"
    ],
    "wof:name":"D.r.c. Sa",
    "wof:placetype":"venue"
},
  "geometry": {"coordinates":[3.99278,48.81279],"type":"Point"}
}