{
  "type": "Feature",
  "properties": {
    "addr:full":"13 Rue De Gen\u00e8ve 69740 Genas Rhone-Alpes 69740",
    "addr:housenumber":"13",
    "addr:postcode":"69740;69740",
    "addr:street":"Rue De Gene\u0300Ve",
    "iso:country":"FR",
    "sg:address":"13 Rue De Gen\u00e8ve 69740 Genas",
    "sg:classifiers":[
        {
            "category":"Professional",
            "subcategory":"Engineering",
            "type":"Services"
        }
    ],
    "sg:phone":"+33 4 72 47 09 50",
    "sg:postcode":"69740",
    "sg:province":"Rhone-Alpes",
    "sg:tags":[
        "machine",
        "-",
        "mechanical"
    ],
    "wof:name":"Mci Industrie",
    "wof:placetype":"venue"
},
  "geometry": {"coordinates":[4.993785,45.713703],"type":"Point"}
}