{
  "type": "Feature",
  "properties": {
    "iso:country":"FR",
    "sg:address":"Pont 1er Faubourg de Cambrai 59360 Cateau Cambr\u00e9sis (Le)",
    "sg:classifiers":[
        {
            "category":"Transit Center",
            "subcategory":"Freight",
            "type":"Transportation"
        }
    ],
    "sg:phone":"+33 3 27 84 14 72",
    "sg:postcode":"59360",
    "sg:province":"Nord Pas-de-Calais",
    "sg:tags":[
        "metallurgy",
        "pipe",
        "metalworking",
        "sheet"
    ],
    "wof:name":"Caffiaux Debatte Aciers (sas)",
    "wof:placetype":"venue"
},
  "geometry": {"coordinates":[-122.132996,48.125565],"type":"Point"}
}