{
  "type": "Feature",
  "properties": {
    "iso:country":"FR",
    "sg:address":"6, Rue de Rilly la Montagne, 51100 Reims",
    "sg:orig_category":"Non-Classified Establishments",
    "sg:phone":"+33 3 26 02 02 69",
    "sg:province":"Champagne",
    "wof:name":"Guyot-walser Informatique S.a.r.l.",
    "wof:placetype":"venue"
},
  "geometry": {"coordinates":[4.005152,49.234547],"type":"Point"}
}