{
  "type": "Feature",
  "properties": {
    "addr:full":"Z.I. de Pompey Pompey Lorraine 54340",
    "addr:postcode":"54340",
    "addr:street":"Z.I. De Pompey",
    "iso:country":"FR",
    "sg:address":"Z.I. de Pompey",
    "sg:city":"Pompey",
    "sg:orig_category":"Non-Classified Establishments",
    "sg:phone":"+33 3 83 49 45 00",
    "sg:postcode":"54340",
    "sg:province":"Lorraine",
    "wof:name":"Photom\u00e9ca European Grafic Group S.a.",
    "wof:placetype":"venue"
},
  "geometry": {"coordinates":[6.137955,48.782089],"type":"Point"}
}