{
  "type": "Feature",
  "properties": {
    "addr:full":"99, Rue Charles Van Wyng\u00e8ne, 77181 Courtry Ile de France",
    "addr:housenumber":"99",
    "addr:postcode":"77181;ile",
    "addr:street":"Rue Charles Van Wynge\u0300Ne",
    "iso:country":"FR",
    "sg:address":"99, Rue Charles Van Wyng\u00e8ne, 77181 Courtry",
    "sg:orig_category":"Unclassifiable Establishments",
    "sg:phone":"+33 1 60 20 28 48",
    "sg:province":"Ile de France",
    "wof:name":"Ebs S.a. - Europe Base Services",
    "wof:placetype":"venue"
},
  "geometry": {"coordinates":[2.603692,48.910397],"type":"Point"}
}