{
  "type": "Feature",
  "properties": {
    "addr:full":"Rue de l'Industrie Bitschwiller l\u00e8s Thann Alsace 68620",
    "addr:postcode":"68620",
    "addr:street":"Rue De L'Industrie",
    "iso:country":"FR",
    "sg:address":"Rue de l'Industrie",
    "sg:city":"Bitschwiller l\u00e8s Thann",
    "sg:orig_category":"Unclassifiable Establishments",
    "sg:phone":"+33 3 89 37 60 77",
    "sg:postcode":"68620",
    "sg:province":"Alsace",
    "wof:name":"Claerr Chaudronnerie S.a.r.l.",
    "wof:placetype":"venue"
},
  "geometry": {"coordinates":[7.082883,47.823277],"type":"Point"}
}