{
  "type": "Feature",
  "properties": {
    "addr:full":"Soveria 20250 Corte Corse",
    "addr:housenumber":"20250",
    "addr:street":"Corte Corse",
    "iso:country":"FR",
    "sg:address":"Soveria 20250 Corte",
    "sg:orig_category":"Unclassifiable Establishments",
    "sg:phone":"+33 4 95 47 42 27",
    "sg:province":"Corse",
    "wof:name":"Confiserie Saint-sylvestre S.a.r.l.",
    "wof:placetype":"venue"
},
  "geometry": {"coordinates":[9.16384,42.360088],"type":"Point"}
}