{
  "type": "Feature",
  "properties": {
    "addr:full":"Quartier la Mousseline RN 568 Gignac la Nerthe Languedoc-Roussillon 13180",
    "addr:housenumber":"568",
    "addr:postcode":"13180",
    "addr:street":"Quartier La Mousseline Rn;Nerthe",
    "iso:country":"FR",
    "sg:address":"Quartier la Mousseline RN 568",
    "sg:city":"Gignac la Nerthe",
    "sg:orig_category":"Unclassifiable Establishments",
    "sg:phone":"+33 4 42 88 49 12",
    "sg:postcode":"13180",
    "sg:province":"Languedoc-Roussillon",
    "wof:name":"A.t.i. S.a.r.l. - Accessoires Tuyauteries Industrielles",
    "wof:placetype":"venue"
},
  "geometry": {"coordinates":[5.23455,43.391861],"type":"Point"}
}