{
  "type": "Feature",
  "properties": {
    "addr:full":"1, Le Parvis de la D\u00e9fense, 92800 Puteaux Ile de France",
    "addr:housenumber":"1",
    "addr:postcode":"92800",
    "addr:street":"Le Parvis De La De\u0301Fense",
    "iso:country":"FR",
    "sg:address":"1, Le Parvis de la D\u00e9fense, 92800 Puteaux",
    "sg:orig_category":"Unclassifiable Establishments",
    "sg:phone":"+33 1 40 90 60 00",
    "sg:province":"Ile de France",
    "wof:name":"Laboratoire U.p.s.a. S.a.s.",
    "wof:placetype":"venue"
},
  "geometry": {"coordinates":[2.24123,48.89122],"type":"Point"}
}