{
  "type": "Feature",
  "properties": {
    "addr:full":"B.P. 103, 33293 Blanquefort C\u00e9dex^^Rue du Commandant Charcot - ZI, 33290 Blanquefort Blanquefort Aquitaine 33290",
    "addr:housenumber":"b.p. 103",
    "addr:postcode":"33293;33290;33290",
    "addr:street":"Commandant Charcot Zi",
    "iso:country":"FR",
    "sg:address":"B.P. 103, 33293 Blanquefort C\u00e9dex^^Rue du Commandant Charcot - ZI, 33290 Blanquefort",
    "sg:city":"Blanquefort",
    "sg:orig_category":"Non-Classified Establishments",
    "sg:phone":"+33 5 56 95 59 59",
    "sg:postcode":"33290",
    "sg:province":"Aquitaine",
    "wof:name":"L.p.f. S.a.",
    "wof:placetype":"venue"
},
  "geometry": {"coordinates":[-0.634838,44.914902],"type":"Point"}
}