{
  "type": "Feature",
  "properties": {
    "iso:country":"FR",
    "sg:address":"47, Chemin de la Citadelle, 69230 Saint Genis Laval",
    "sg:orig_category":"Unclassifiable Establishments",
    "sg:phone":"+33 4 78 56 12 20",
    "sg:postcode":"69230",
    "sg:province":"Rhone-Alpes",
    "wof:name":"M\u00e9ca Service Automation S.a.r.l.",
    "wof:placetype":"venue"
},
  "geometry": {"coordinates":[4.798356,45.683521],"type":"Point"}
}