{
  "type": "Feature",
  "properties": {
    "addr:full":"Bd Des Apprentis 44600 St Nazaire Pays de Loire 44600",
    "addr:postcode":"44600 st nazaire;44600",
    "addr:street":"Bd Des Apprentis",
    "iso:country":"FR",
    "sg:address":"Bd Des Apprentis 44600 St Nazaire",
    "sg:classifiers":[
        {
            "category":"Manufacturing",
            "subcategory":"Metals",
            "type":"Manufacturing & Wholesale Goods"
        }
    ],
    "sg:phone":"+33 2 40 45 91 93",
    "sg:postcode":"44600",
    "sg:province":"Pays de Loire",
    "sg:tags":[
        "pipe",
        "sheet",
        "-",
        "metalworking",
        "metallic",
        "metallurgy",
        "finished"
    ],
    "wof:name":"St\u00c9 De Montage Et De Construction Navale Sa",
    "wof:placetype":"venue"
},
  "geometry": {"coordinates":[-2.185554,47.294998],"type":"Point"}
}