{
  "type": "Feature",
  "properties": {
    "iso:country":"FR",
    "sg:address":"105 Grande Rue 89113 FLEURY LA VALLEE",
    "sg:city":"Branches",
    "sg:classifiers":[
        {
            "category":"Manufacturing",
            "subcategory":"Textiles",
            "type":"Manufacturing & Wholesale Goods"
        }
    ],
    "sg:phone":"+33 3 86 73 81 69",
    "sg:postcode":"89113",
    "sg:province":"Bourgogne",
    "sg:tags":[
        "fibre",
        "natural"
    ],
    "wof:name":"Moissonnier Sarl",
    "wof:placetype":"venue"
},
  "geometry": {"coordinates":[3.448245,47.866413],"type":"Point"}
}