{
  "type": "Feature",
  "properties": {
    "iso:country":"FR",
    "sg:address":"B.P. 443, 65004 Tarbes C\u00e9dex^^2, Bd du Mar\u00e9chal Juin, 65000 Tarbes",
    "sg:orig_category":"Non-Classified Establishments",
    "sg:phone":"+33 5 62 34 34 07",
    "sg:province":"Midi Pyr\u00e9n\u00e9es",
    "wof:name":"Exploitation Conseil Imprimerie S.a.",
    "wof:placetype":"venue"
},
  "geometry": {"coordinates":[0.073125,43.230011],"type":"Point"}
}