{
  "type": "Feature",
  "properties": {
    "addr:full":"Rte de Mouchan Vic Fezensac Midi Pyr\u00e9n\u00e9es 32190",
    "addr:postcode":"32190",
    "addr:street":"Rte De Mouchan",
    "iso:country":"FR",
    "sg:address":"Rte de Mouchan",
    "sg:city":"Vic Fezensac",
    "sg:orig_category":"Non-Classified Establishments",
    "sg:phone":"+33 5 62 58 05 05",
    "sg:postcode":"32190",
    "sg:province":"Midi Pyr\u00e9n\u00e9es",
    "wof:name":"Coop\u00e9rative Agricole Les Silos Vicois",
    "wof:placetype":"venue"
},
  "geometry": {"coordinates":[0.276931,43.629028],"type":"Point"}
}