{
  "type": "Feature",
  "properties": {
    "addr:full":"555, Rue Saint Pierre, 13427 Marseille C\u00e9dex 12 Provence-Alpes-C\u00f4te d'Azur",
    "addr:housenumber":"555",
    "addr:postcode":"13427;12",
    "addr:street":"Rue Saint Pierre;Ce\u0301Dex",
    "iso:country":"FR",
    "sg:address":"555, Rue Saint Pierre, 13427 Marseille C\u00e9dex 12",
    "sg:orig_category":"Non-Classified Establishments",
    "sg:phone":"+33 4 91 47 63 25",
    "sg:province":"Provence-Alpes-C\u00f4te d'Azur",
    "wof:name":"Sud Atal S.a.r.l.",
    "wof:placetype":"venue"
},
  "geometry": {"coordinates":[5.44175,43.30703],"type":"Point"}
}