{
  "type": "Feature",
  "properties": {
    "iso:country":"FR",
    "sg:address":"42803 Rive De Gier",
    "sg:classifiers":[
        {
            "category":"Manufacturing",
            "subcategory":"Metals",
            "type":"Manufacturing & Wholesale Goods"
        }
    ],
    "sg:phone":"+33 4 77 75 20 00",
    "sg:province":"Basse Normandie",
    "sg:tags":[
        "metallurgy",
        "metalworking"
    ],
    "wof:name":"Usinor Industylle",
    "wof:placetype":"venue"
},
  "geometry": {"coordinates":[4.61411,45.528622],"type":"Point"}
}