{
  "type": "Feature",
  "properties": {
    "addr:full":"145 Rte De Paris 16160 Gond Pontouvre Poitou-Charentes 16160",
    "addr:housenumber":"145",
    "addr:postcode":"16160;16160",
    "addr:street":"Rte De Paris;Pontouvre",
    "iso:country":"FR",
    "sg:address":"145 Rte De Paris 16160 Gond Pontouvre",
    "sg:classifiers":[
        {
            "category":"Manufacturing",
            "subcategory":"Building Materials",
            "type":"Manufacturing & Wholesale Goods"
        }
    ],
    "sg:phone":"+33 5 45 68 37 70",
    "sg:postcode":"16160",
    "sg:province":"Poitou-Charentes",
    "sg:tags":[
        "-",
        "machine",
        "raw",
        "engineering",
        "paper",
        "mechanical",
        "cardboard"
    ],
    "wof:name":"Ter Sarl",
    "wof:placetype":"venue"
},
  "geometry": {"coordinates":[0.173702,45.671478],"type":"Point"}
}