{
  "type": "Feature",
  "properties": {
    "addr:full":"44 rue Eug\u00e8ne Bourdon 66000 Perpignan Languedoc-Roussillon 66000",
    "addr:housenumber":"44",
    "addr:postcode":"66000;66000",
    "addr:street":"Rue Euge\u0300Ne Bourdon",
    "iso:country":"FR",
    "sg:address":"44 rue Eug\u00e8ne Bourdon 66000 Perpignan",
    "sg:classifiers":[
        {
            "category":"Home & Garden",
            "subcategory":"Household Appliances",
            "type":"Retail Goods"
        }
    ],
    "sg:phone":"+33 4 68 52 34 49",
    "sg:postcode":"66000",
    "sg:province":"Languedoc-Roussillon",
    "sg:tags":[
        "electric"
    ],
    "wof:name":"Chinarro Electro Diffusion Ele S.a.",
    "wof:placetype":"venue"
},
  "geometry": {"coordinates":[2.89812,42.7318],"type":"Point"}
}