{
  "type": "Feature",
  "properties": {
    "addr:full":"Zi Sabli\u00e8re 28630 Nogent Le Phaye Berch\u00e8res-les-Pierres Centre 28630",
    "addr:postcode":"28630;28630",
    "addr:street":"Zi Sablie\u0300Re",
    "iso:country":"FR",
    "sg:address":"Zi Sabli\u00e8re 28630 Nogent Le Phaye",
    "sg:city":"Berch\u00e8res-les-Pierres",
    "sg:classifiers":[
        {
            "category":"Professional",
            "type":"Services"
        }
    ],
    "sg:phone":"+33 2 37 31 66 00",
    "sg:postcode":"28630",
    "sg:province":"Centre",
    "sg:tags":[
        "transport",
        "road"
    ],
    "wof:name":"Transports Lahaye Sa",
    "wof:placetype":"venue"
},
  "geometry": {"coordinates":[1.577293,48.446495],"type":"Point"}
}