{
  "type": "Feature",
  "properties": {
    "addr:full":"13, Rue Adrien Nordet - ZAC la Vall\u00e9e, 02100 Saint Quentin Picardie",
    "addr:housenumber":"13",
    "addr:postcode":"02100",
    "addr:street":"Rue Adrien Nordet Zac La Valle\u0301E",
    "iso:country":"FR",
    "sg:address":"13, Rue Adrien Nordet - ZAC la Vall\u00e9e, 02100 Saint Quentin",
    "sg:orig_category":"Unclassifiable Establishments",
    "sg:phone":"+33 3 23 64 00 22",
    "sg:province":"Picardie",
    "wof:name":"Bijouterie Oraisne S.a.r.l.",
    "wof:placetype":"venue"
},
  "geometry": {"coordinates":[3.288225,49.847912],"type":"Point"}
}