{
  "type": "Feature",
  "properties": {
    "addr:full":"Le Port; La C\u00f4tini\u00e8re; 17310 Poitou-Charentes 17310",
    "addr:postcode":"17310;17310",
    "iso:country":"FR",
    "sg:address":"Le Port; La C\u00f4tini\u00e8re; 17310",
    "sg:classifiers":[
        {
            "category":"Banks & Credit Unions",
            "subcategory":"Bank",
            "type":"Services"
        }
    ],
    "sg:phone":"+33 5 46 47 18 24",
    "sg:postcode":"17310",
    "sg:province":"Poitou-Charentes",
    "wof:name":"Caisse Regionale De Cr\u00e9dit, Maritime Mutuel Du Finist\u00e8re",
    "wof:placetype":"venue"
},
  "geometry": {"coordinates":[-77.358566,39.883881],"type":"Point"}
}