{
  "type": "Feature",
  "properties": {
    "iso:country":"FR",
    "sg:address":"52 av Jean Jaur\u00e8s; Pessac",
    "sg:classifiers":[
        {
            "category":"Banks & Credit Unions",
            "subcategory":"Bank",
            "type":"Services"
        }
    ],
    "sg:phone":"+33 3356451811",
    "sg:province":"Champagne",
    "wof:name":"Cr\u00e9dit Du Nord",
    "wof:placetype":"venue"
},
  "geometry": {"coordinates":[-0.626493,44.807457],"type":"Point"}
}