{
  "type": "Feature",
  "properties": {
    "addr:full":"3, Place Paul Bec - Les Echelles de la Ville Antigone, 34000 Montpellier Languedoc-Roussillon",
    "addr:housenumber":"3",
    "addr:postcode":"34000",
    "addr:street":"Place Paul Bec Les;De La Ville Antigone",
    "iso:country":"FR",
    "sg:address":"3, Place Paul Bec - Les Echelles de la Ville Antigone, 34000 Montpellier",
    "sg:orig_category":"Non-Classified Establishments",
    "sg:phone":"+33 4 67 69 70 52",
    "sg:province":"Languedoc-Roussillon",
    "wof:name":"Novelec Languedoc Roussillon",
    "wof:placetype":"venue"
},
  "geometry": {"coordinates":[3.87609,43.610855],"type":"Point"}
}