{
  "type": "Feature",
  "properties": {
    "addr:full":"71 Rue Nationale Tours Centre 37000",
    "addr:housenumber":"71",
    "addr:postcode":"37000",
    "addr:street":"Rue Nationale Tours",
    "iso:country":"FR",
    "sg:address":"71 Rue Nationale",
    "sg:city":"Tours",
    "sg:classifiers":[
        {
            "category":"Banks & Credit Unions",
            "subcategory":"Financial Services",
            "type":"Services"
        }
    ],
    "sg:phone":"+33 2 47 31 34 56",
    "sg:postcode":"37000",
    "sg:province":"Centre",
    "sg:tags":[
        "banking",
        "finance",
        "insurance"
    ],
    "wof:name":"Credit Lyonnais",
    "wof:placetype":"venue"
},
  "geometry": {"coordinates":[0.688078,47.392494],"type":"Point"}
}