{
  "type": "Feature",
  "properties": {
    "iso:country":"FR",
    "sg:address":"Les Peireguins 83390 CUERS",
    "sg:orig_category":"Wax Roses",
    "sg:phone":"+33 4 94 48 55 27",
    "wof:name":"Nirp International Les Roses Du Succes Sa",
    "wof:placetype":"venue"
},
  "geometry": {"coordinates":[6.075937,43.232903],"type":"Point"}
}