{
  "type": "Feature",
  "properties": {
    "iso:country":"FR",
    "sg:address":"B.P. 344, 38435 Echirolles C\u00e9dex^^1, Rue des Tropiques, 38130 Echirolles",
    "sg:orig_category":"Non-Classified Establishments",
    "sg:phone":"+33 4 76 40 35 91",
    "sg:postcode":"38130",
    "sg:province":"Rhone-Alpes",
    "wof:name":"Cyberstar S.a.",
    "wof:placetype":"venue"
},
  "geometry": {"coordinates":[5.7194,45.149536],"type":"Point"}
}