{
  "type": "Feature",
  "properties": {
    "iso:country":"FR",
    "sg:address":"247 all\u00e9e de la Traversi\u00e8re 06250 Mougins",
    "sg:classifiers":[
        {
            "category":"Food & Beverages",
            "subcategory":"Fruits & Vegetables",
            "type":"Retail Goods"
        }
    ],
    "sg:phone":"+33 4 93 75 39 69",
    "sg:province":"Aquitaine",
    "sg:tags":[
        "processing",
        "machinery"
    ],
    "wof:name":"Dcf Aromaprocess Sarl",
    "wof:placetype":"venue"
},
  "geometry": {"coordinates":[6.995527,43.594955],"type":"Point"}
}