{
  "type": "Feature",
  "properties": {
    "iso:country":"FR",
    "sg:address":"La Ribotiere 85170 Le Poire Sur Vie",
    "sg:classifiers":[
        {
            "category":"Utilities",
            "subcategory":"Telephone",
            "type":"Services"
        }
    ],
    "sg:phone":"+33 2 51 36 25 00",
    "sg:province":"Pays de Loire",
    "sg:tags":[
        "telecommunication"
    ],
    "wof:name":"Vendecom",
    "wof:placetype":"venue"
},
  "geometry": {"coordinates":[-1.491202,46.781693],"type":"Point"}
}