{
  "type": "Feature",
  "properties": {
    "addr:full":"B.P. 19, 63650 La Monnerie le Montel^^ZA Racine, 63650 La Monnerie le Montel Monnerie-le-Montel Auvergne 63650",
    "addr:housenumber":"63650",
    "addr:postcode":"63650;63650",
    "addr:street":"B.P. 19;Monnerie Le Montel^^Za Racine",
    "iso:country":"FR",
    "sg:address":"B.P. 19, 63650 La Monnerie le Montel^^ZA Racine, 63650 La Monnerie le Montel",
    "sg:city":"Monnerie-le-Montel",
    "sg:orig_category":"Non-Classified Establishments",
    "sg:phone":"+33 4 73 51 41 06",
    "sg:postcode":"63650",
    "sg:province":"Auvergne",
    "wof:name":"Le Loup S.a.r.l.",
    "wof:placetype":"venue"
},
  "geometry": {"coordinates":[3.604876,45.869713],"type":"Point"}
}