{
  "type": "Feature",
  "properties": {
    "addr:full":"81, Rue Escudier, 92100 Boulogne Billancourt Ile de France",
    "addr:housenumber":"81",
    "addr:postcode":"92100",
    "addr:street":"Rue Escudier",
    "iso:country":"FR",
    "sg:address":"81, Rue Escudier, 92100 Boulogne Billancourt",
    "sg:orig_category":"Unclassifiable Establishments",
    "sg:phone":"+33 1 48 25 22 22",
    "sg:province":"Ile de France",
    "wof:name":"De Pape Conseils S.a.r.l.",
    "wof:placetype":"venue"
},
  "geometry": {"coordinates":[2.243112,48.844448],"type":"Point"}
}