{
  "type": "Feature",
  "properties": {
    "iso:country":"FR",
    "sg:address":"Min Saint Augustin",
    "sg:city":"Nice",
    "sg:orig_category":"Non-Classified Establishments",
    "sg:phone":"+33 4 92 29 81 00",
    "sg:postcode":"06000",
    "sg:province":"Provence-Alpes-C\u00f4te d'Azur",
    "wof:name":"Disprolait Europ S.a.r.l.",
    "wof:placetype":"venue"
},
  "geometry": {"coordinates":[7.205069,43.674545],"type":"Point"}
}