{
  "type": "Feature",
  "properties": {
    "addr:full":"Chem Du Champ Des Martyrs 49240 Avrill\u00e9 Pays de Loire 49240",
    "addr:postcode":"49240;49240",
    "addr:street":"Chem Du Champ Des Martyrs",
    "iso:country":"FR",
    "sg:address":"Chem Du Champ Des Martyrs 49240 Avrill\u00e9",
    "sg:classifiers":[
        {
            "category":"Shopping",
            "subcategory":"Computers & Home Electronics",
            "type":"Retail Goods"
        }
    ],
    "sg:phone":"+33 2 41 33 63 40",
    "sg:postcode":"49240",
    "sg:province":"Pays de Loire",
    "sg:tags":[
        "electronic",
        "electrical",
        "equipment"
    ],
    "wof:name":"Artus Pacific Scientific",
    "wof:placetype":"venue"
},
  "geometry": {"coordinates":[-0.578384,47.492336],"type":"Point"}
}