{
  "type": "Feature",
  "properties": {
    "iso:country":"FR",
    "sg:address":"B.P. 49, 13361 Marseille C\u00e9dex 10^^41, Bd des Aci\u00e9ries, 13010 Marseille",
    "sg:orig_category":"Non-Classified Establishments",
    "sg:phone":"+33 4 91 80 88 50",
    "sg:province":"Poitou-Charentes",
    "wof:name":"Etablissement Richaud S.a.",
    "wof:placetype":"venue"
},
  "geometry": {"coordinates":[5.39525,43.281929],"type":"Point"}
}