{
  "type": "Feature",
  "properties": {
    "addr:full":"Chemin des Fr\u00eanes Briennon Rhone-Alpes 42720",
    "addr:postcode":"42720",
    "addr:street":"Chemin Des Fre\u0302Nes;Rhone-Alpes",
    "iso:country":"FR",
    "sg:address":"Chemin des Fr\u00eanes",
    "sg:city":"Briennon",
    "sg:orig_category":"Unclassifiable Establishments",
    "sg:phone":"+33 4 77 60 74 74",
    "sg:postcode":"42720",
    "sg:province":"Rhone-Alpes",
    "wof:name":"Roanne Gastronomie International S.a.",
    "wof:placetype":"venue"
},
  "geometry": {"coordinates":[4.076474,46.150406],"type":"Point"}
}