{
  "type": "Feature",
  "properties": {
    "addr:full":"40/42, Rue de Cronstadt, 75015 Paris Ile de France",
    "addr:housenumber":"40 / 42",
    "addr:postcode":"75015",
    "addr:street":"Rue De Cronstadt",
    "iso:country":"FR",
    "sg:address":"40/42, Rue de Cronstadt, 75015 Paris",
    "sg:orig_category":"Unclassifiable Establishments",
    "sg:phone":"+33 1 45 32 75 47",
    "sg:province":"Ile de France",
    "wof:name":"Atelier Du Cadratin S.a.r.l.",
    "wof:placetype":"venue"
},
  "geometry": {"coordinates":[2.301025,48.833462],"type":"Point"}
}