{
  "type": "Feature",
  "properties": {
    "addr:full":"Le Claux 26700 Pierrelatte Rhone-Alpes 26700",
    "addr:postcode":"26700;26700",
    "iso:country":"FR",
    "sg:address":"Le Claux 26700 Pierrelatte",
    "sg:classifiers":[
        {
            "category":"Food & Beverages",
            "subcategory":"Groceries & Convenience Stores",
            "type":"Retail Goods"
        }
    ],
    "sg:phone":"+33 4 75 96 88 30",
    "sg:postcode":"26700",
    "sg:province":"Rhone-Alpes",
    "sg:tags":[
        "product",
        "related"
    ],
    "wof:name":"Gyma Surgele",
    "wof:placetype":"venue"
},
  "geometry": {"coordinates":[4.700653,44.366825],"type":"Point"}
}