{
  "type": "Feature",
  "properties": {
    "iso:country":"FR",
    "sg:address":"2, Chemin Bonneville, 44300 Nantes",
    "sg:orig_category":"Non-Classified Establishments",
    "sg:phone":"+33 2 51 89 25 25",
    "sg:province":"Pays de Loire",
    "wof:name":"Gestetner S.a.",
    "wof:placetype":"venue"
},
  "geometry": {"coordinates":[-1.53666,47.24435],"type":"Point"}
}