{
  "type": "Feature",
  "properties": {
    "iso:country":"FR",
    "sg:address":"15 Impasse Du Champ Blanc 69150 Decines Charpieu",
    "sg:classifiers":[
        {
            "category":"Professional",
            "subcategory":"Engineering",
            "type":"Services"
        }
    ],
    "sg:phone":"+33 4 78 49 84 85",
    "sg:postcode":"69150",
    "sg:province":"Rhone-Alpes",
    "sg:tags":[
        "machine",
        "-",
        "mechanical"
    ],
    "wof:name":"Pgc",
    "wof:placetype":"venue"
},
  "geometry": {"coordinates":[4.9479,45.762821],"type":"Point"}
}