{
  "type": "Feature",
  "properties": {
    "addr:full":"1 Rue Thiers 88000 Epinal Lorraine 88000",
    "addr:housenumber":"1",
    "addr:postcode":"88000;88000",
    "addr:street":"Rue Thiers",
    "iso:country":"FR",
    "sg:address":"1 Rue Thiers 88000 Epinal",
    "sg:classifiers":[
        {
            "category":"Wholesale",
            "subcategory":"Machinery & Supplies",
            "type":"Manufacturing & Wholesale Goods"
        }
    ],
    "sg:phone":"+33 3 29 69 27 20",
    "sg:postcode":"88000",
    "sg:province":"Lorraine",
    "sg:tags":[
        "food",
        "processing",
        "-",
        "machine",
        "equipment",
        "engineering",
        "mechanical"
    ],
    "wof:name":"Bg",
    "wof:placetype":"venue"
},
  "geometry": {"coordinates":[6.451272,48.172798],"type":"Point"}
}