{
  "type": "Feature",
  "properties": {
    "iso:country":"FR",
    "sg:address":"1, Rue de Guebviller, 68260 Kingersheim",
    "sg:city":"Kingersheim",
    "sg:orig_category":"Unclassifiable Establishments",
    "sg:phone":"+33 3 89 57 33 66",
    "sg:postcode":"68260",
    "sg:province":"Alsace",
    "wof:name":"Metinox S.a.r.l.",
    "wof:placetype":"venue"
},
  "geometry": {"coordinates":[7.335795,47.790257],"type":"Point"}
}