{
  "type": "Feature",
  "properties": {
    "iso:country":"FR",
    "sg:address":"170 Cs Du M\u00e9doc 33300 Bordeaux",
    "sg:city":"Bordeaux",
    "sg:classifiers":[
        {
            "category":"Manufacturing",
            "subcategory":"Rubber & Plastics",
            "type":"Manufacturing & Wholesale Goods"
        }
    ],
    "sg:phone":"+33 5 56 43 41 11",
    "sg:postcode":"33300",
    "sg:province":"Aquitaine",
    "sg:tags":[
        "fabric",
        "-",
        "linen",
        "finished",
        "paper",
        "plast",
        "cardboard"
    ],
    "wof:name":"Ste Commerciale Revetements Modernes",
    "wof:placetype":"venue"
},
  "geometry": {"coordinates":[-0.573017,44.863304],"type":"Point"}
}