{
  "type": "Feature",
  "properties": {
    "addr:full":"Avenue Auguste Bastide 04860 Pierrevert Languedoc-Roussillon",
    "addr:postcode":"04860",
    "addr:street":"Avenue Auguste Bastide",
    "iso:country":"FR",
    "sg:address":"Avenue Auguste Bastide 04860 Pierrevert",
    "sg:classifiers":[
        {
            "category":"Food Court",
            "type":"Food & Drink"
        }
    ],
    "sg:phone":"+33 4 92 72 19 06",
    "sg:province":"Languedoc-Roussillon",
    "sg:tags":[
        "product",
        "related"
    ],
    "wof:name":"Ste Coop Vinicole Et Agricole Des Coteaux De Pierrevert",
    "wof:placetype":"venue"
},
  "geometry": {"coordinates":[5.75083,43.809685],"type":"Point"}
}