{
  "type": "Feature",
  "properties": {
    "addr:full":"B.P. 1, 82403 Valence d'Agen C\u00e9dex^^Cours de Verdun, 82400 Valence d'Agen Midi Pyr\u00e9n\u00e9es 82400",
    "addr:housenumber":"1",
    "addr:postcode":"82403;82400;82400",
    "addr:street":"B.P.;Verdun",
    "iso:country":"FR",
    "sg:address":"B.P. 1, 82403 Valence d'Agen C\u00e9dex^^Cours de Verdun, 82400 Valence d'Agen",
    "sg:orig_category":"Non-Classified Establishments",
    "sg:phone":"+33 5 63 39 50 26",
    "sg:postcode":"82400",
    "sg:province":"Midi Pyr\u00e9n\u00e9es",
    "wof:name":"Brunet Et Caillive S.a.",
    "wof:placetype":"venue"
},
  "geometry": {"coordinates":[0.612557,44.196617],"type":"Point"}
}