{
  "type": "Feature",
  "properties": {
    "iso:country":"FR",
    "sg:address":"B.P. 158, 61205 Argentan C\u00e9dex^^Bd de l'Expansion - ZI Sud, 61200 Argentan",
    "sg:city":"Argentan",
    "sg:orig_category":"Non-Classified Establishments",
    "sg:phone":"+33 2 33 12 40 80",
    "sg:postcode":"61200",
    "sg:province":"Basse Normandie",
    "wof:name":"Rovip Industrie S.a.",
    "wof:placetype":"venue"
},
  "geometry": {"coordinates":[-0.024389,48.729664],"type":"Point"}
}