{
  "type": "Feature",
  "properties": {
    "addr:full":"66, Bd F\u00e9lix Faure, 93300 Aubervilliers Ile de France",
    "addr:housenumber":"66",
    "addr:postcode":"93300",
    "addr:street":"Bd Fe\u0301Lix Faure",
    "iso:country":"FR",
    "sg:address":"66, Bd F\u00e9lix Faure, 93300 Aubervilliers",
    "sg:orig_category":"Unclassifiable Establishments",
    "sg:phone":"+33 1 48 34 90 00",
    "sg:province":"Ile de France",
    "wof:name":"K Par K Sud S.a.",
    "wof:placetype":"venue"
},
  "geometry": {"coordinates":[2.382474,48.904369],"type":"Point"}
}