{
  "type": "Feature",
  "properties": {
    "iso:country":"FR",
    "sg:address":"ZI les Bonnes 43410 LEMPDES SUR ALLAGNON",
    "sg:city":"Lempdes-sur-Allagnon",
    "sg:classifiers":[
        {
            "category":"Train Station",
            "subcategory":"Light Rail",
            "type":"Transportation"
        }
    ],
    "sg:phone":"+33 4 71 76 53 16",
    "sg:postcode":"43410",
    "sg:province":"Auvergne",
    "sg:tags":[
        "lamp",
        "post"
    ],
    "wof:name":"Escom Sa",
    "wof:placetype":"venue"
},
  "geometry": {"coordinates":[3.269716,45.385189],"type":"Point"}
}