{
  "type": "Feature",
  "properties": {
    "iso:country":"FR",
    "sg:address":"56570 Locmiqu\u00e9lic",
    "sg:city":"Locmiqu\u00e9lic",
    "sg:orig_category":"Unclassifiable Establishments",
    "sg:phone":"+33 2 97 33 48 41",
    "sg:postcode":"56570",
    "sg:province":"Bretagne",
    "wof:name":"Chantiers Navals Bernard S.a.",
    "wof:placetype":"venue"
},
  "geometry": {"coordinates":[-3.348649,47.724628],"type":"Point"}
}