{
  "type": "Feature",
  "properties": {
    "addr:full":"22 Rue Maupertuis 29200 Brest Brest Bretagne 29200",
    "addr:housenumber":"22",
    "addr:postcode":"29200;29200",
    "addr:street":"Rue Maupertuis",
    "iso:country":"FR",
    "sg:address":"22 Rue Maupertuis 29200 Brest",
    "sg:city":"Brest",
    "sg:classifiers":[
        {
            "category":"Utilities",
            "subcategory":"Electric",
            "type":"Services"
        }
    ],
    "sg:phone":"+33 2 98 42 01 01",
    "sg:postcode":"29200",
    "sg:province":"Bretagne",
    "sg:tags":[
        "electricity",
        "electronic",
        "electrical",
        "equipment"
    ],
    "wof:name":"Societe Bretonne De Cablage Marzin (sbcm)",
    "wof:placetype":"venue"
},
  "geometry": {"coordinates":[-4.462293,48.413864],"type":"Point"}
}