{
  "type": "Feature",
  "properties": {
    "iso:country":"FR",
    "sg:address":"14 ave Thiers; Fumel; 47500",
    "sg:city":"Fumel",
    "sg:classifiers":[
        {
            "category":"Banks & Credit Unions",
            "subcategory":"Bank",
            "type":"Services"
        }
    ],
    "sg:phone":"+33 3353711111",
    "sg:postcode":"47500",
    "sg:province":"Aquitaine",
    "wof:name":"Banque Nationale De Paris",
    "wof:placetype":"venue"
},
  "geometry": {"coordinates":[0.967102,44.498375],"type":"Point"}
}