{
  "type": "Feature",
  "properties": {
    "addr:full":"ZA du Bois Simon Perrecy les Forges Bourgogne 71420",
    "addr:postcode":"71420",
    "addr:street":"Za Du Bois Simon Perrecy Les Forges Bourgogne",
    "iso:country":"FR",
    "sg:address":"ZA du Bois Simon",
    "sg:city":"Perrecy les Forges",
    "sg:orig_category":"Unclassifiable Establishments",
    "sg:phone":"+33 3 85 79 31 62",
    "sg:postcode":"71420",
    "sg:province":"Bourgogne",
    "wof:name":"Labaune Errard S.a.r.l.",
    "wof:placetype":"venue"
},
  "geometry": {"coordinates":[4.21618,46.614361],"type":"Point"}
}