{
  "type": "Feature",
  "properties": {
    "addr:full":"2 Rue Du Gal Dubreton 56801 Plo\u00ebrmel Lorraine",
    "addr:housenumber":"2",
    "addr:postcode":"56801",
    "addr:street":"Rue Du Gal Dubreton",
    "iso:country":"FR",
    "sg:address":"2 Rue Du Gal Dubreton 56801 Plo\u00ebrmel",
    "sg:classifiers":[
        {
            "category":"Professional",
            "subcategory":"Business Services",
            "type":"Services"
        }
    ],
    "sg:phone":"+33 2 97 73 25 00",
    "sg:province":"Lorraine",
    "sg:tags":[
        "training",
        "advice"
    ],
    "wof:name":"Ogec La Mennais - St Armel",
    "wof:placetype":"venue"
},
  "geometry": {"coordinates":[-2.398204,47.931625],"type":"Point"}
}