{
  "type": "Feature",
  "properties": {
    "addr:full":"5 rue Gabriel Marie 13010 Marseille Poitou-Charentes",
    "addr:housenumber":"5",
    "addr:postcode":"13010",
    "addr:street":"Rue Gabriel Marie",
    "iso:country":"FR",
    "sg:address":"5 rue Gabriel Marie 13010 Marseille",
    "sg:classifiers":[
        {
            "category":"Professional",
            "subcategory":"Business Services",
            "type":"Services"
        }
    ],
    "sg:phone":"+33 4 91 32 32 82",
    "sg:province":"Poitou-Charentes",
    "sg:tags":[
        "data"
    ],
    "wof:name":"Ste Nle Ctre Realisateur Informat Profes Sarl",
    "wof:placetype":"venue"
},
  "geometry": {"coordinates":[5.40182,43.283798],"type":"Point"}
}