{
  "type": "Feature",
  "properties": {
    "addr:full":"lieu dit Coron 01300 Belley Rhone-Alpes 01300",
    "addr:postcode":"01300;01300",
    "addr:street":"Lieu Dit",
    "iso:country":"FR",
    "sg:address":"lieu dit Coron 01300 Belley",
    "sg:classifiers":[
        {
            "category":"Autos & Motor Vehicles",
            "subcategory":"Auto Supplies",
            "type":"Retail Goods"
        }
    ],
    "sg:phone":"+33 4 79 81 43 14",
    "sg:postcode":"01300",
    "sg:province":"Rhone-Alpes",
    "sg:tags":[
        "automobile",
        "accessory"
    ],
    "wof:name":"Tramont Sa",
    "wof:placetype":"venue"
},
  "geometry": {"coordinates":[5.714084,45.752052],"type":"Point"}
}