{
  "type": "Feature",
  "properties": {
    "iso:country":"FR",
    "sg:address":"32300 Mouch\u00e9s",
    "sg:orig_category":"Unclassifiable Establishments",
    "sg:phone":"+33 5 62 64 17 88",
    "sg:province":"Midi Pyr\u00e9n\u00e9es",
    "wof:name":"Etablissements Libaros S.a.r.l.",
    "wof:placetype":"venue"
},
  "geometry": {"coordinates":[-78.129913,36.726742],"type":"Point"}
}