{
  "type": "Feature",
  "properties": {
    "iso:country":"FR",
    "sg:address":"ZI Port de Rech",
    "sg:city":"Sarralbe",
    "sg:orig_category":"Unclassifiable Establishments",
    "sg:phone":"+33 3 87 97 05 84",
    "sg:postcode":"57430",
    "sg:province":"Lorraine",
    "wof:name":"Klein S.a.r.l.",
    "wof:placetype":"venue"
},
  "geometry": {"coordinates":[7.03013,49.000999],"type":"Point"}
}