{
  "type": "Feature",
  "properties": {
    "addr:full":"Rue Ferred Pr\u00e9zelin Paimboeuf Pays de Loire 44560",
    "addr:postcode":"44560",
    "addr:street":"Rue Ferred Pre\u0301Zelin",
    "iso:country":"FR",
    "sg:address":"Rue Ferred Pr\u00e9zelin",
    "sg:city":"Paimboeuf",
    "sg:orig_category":"Non-Classified Establishments",
    "sg:phone":"+33 2 40 39 66 00",
    "sg:postcode":"44560",
    "sg:province":"Pays de Loire",
    "wof:name":"A.c.t.i. Plastiques S.a.r.l. - Atlantique Chaudronnerie Tuyauterie Industrielle",
    "wof:placetype":"venue"
},
  "geometry": {"coordinates":[-2.016017,47.283436],"type":"Point"}
}