{
  "type": "Feature",
  "properties": {
    "iso:country":"FR",
    "sg:address":"77325 Marne la Vall\u00e9e C\u00e9dex 2^^9, Rue Albert Einstein - Espace Descartes , 77420 Champs sur Marne",
    "sg:orig_category":"Non-Classified Establishments",
    "sg:phone":"+33 1 64 68 30 00",
    "sg:postcode":"77420",
    "sg:province":"Ile de France",
    "wof:name":"E.m.c. S.a. - Engineering Micro Computers",
    "wof:placetype":"venue"
},
  "geometry": {"coordinates":[2.602945,48.852322],"type":"Point"}
}