{
  "type": "Feature",
  "properties": {
    "addr:full":"6 Chem De Viesly 59214 Qui\u00e9vy Nord Pas-de-Calais 59214",
    "addr:housenumber":"6",
    "addr:postcode":"59214;59214",
    "addr:street":"Chem De Viesly",
    "iso:country":"FR",
    "sg:address":"6 Chem De Viesly 59214 Qui\u00e9vy",
    "sg:classifiers":[
        {
            "category":"Shopping",
            "subcategory":"Clothing, Apparel, & Fashions",
            "type":"Retail Goods"
        }
    ],
    "sg:phone":"+33 3 27 76 56 56",
    "sg:postcode":"59214",
    "sg:province":"Nord Pas-de-Calais",
    "sg:tags":[
        "textile",
        "clothing",
        "clothes"
    ],
    "wof:name":"Gabriel D'authie Sa",
    "wof:placetype":"venue"
},
  "geometry": {"coordinates":[3.431671,50.164742],"type":"Point"}
}