{
  "type": "Feature",
  "properties": {
    "addr:full":"77, Bd Malesherbes, 75008 Paris Ile de France",
    "addr:housenumber":"77",
    "addr:postcode":"75008",
    "addr:street":"Bd Malesherbes",
    "iso:country":"FR",
    "sg:address":"77, Bd Malesherbes, 75008 Paris",
    "sg:orig_category":"Non-Classified Establishments",
    "sg:phone":"+33 1 44 69 92 25",
    "sg:province":"Ile de France",
    "wof:name":"Valorey Transmissions S.a.r.l.",
    "wof:placetype":"venue"
},
  "geometry": {"coordinates":[2.316862,48.877117],"type":"Point"}
}