{
  "type": "Feature",
  "properties": {
    "iso:country":"FR",
    "sg:address":"Esplanade Europe",
    "sg:city":"Anglet",
    "sg:orig_category":"Unclassifiable Establishments",
    "sg:phone":"+33 5 59 23 56 16",
    "sg:postcode":"64600",
    "sg:province":"Aquitaine",
    "wof:name":"Exel Freight S.a.",
    "wof:placetype":"venue"
},
  "geometry": {"coordinates":[-1.532562,43.472275],"type":"Point"}
}