{
  "type": "Feature",
  "properties": {
    "addr:full":"24, Rue du Boucher, 21000 Dijon Dijon Bourgogne 21000",
    "addr:housenumber":"24",
    "addr:postcode":"21000;21000",
    "addr:street":"Rue Du Boucher",
    "iso:country":"FR",
    "sg:address":"24, Rue du Boucher, 21000 Dijon",
    "sg:city":"Dijon",
    "sg:orig_category":"Non-Classified Establishments",
    "sg:phone":"+33 3 80 74 19 06",
    "sg:postcode":"21000",
    "sg:province":"Bourgogne",
    "wof:name":"Plasti-light S.a.",
    "wof:placetype":"venue"
},
  "geometry": {"coordinates":[4.99785,47.312469],"type":"Point"}
}