{
  "type": "Feature",
  "properties": {
    "iso:country":"FR",
    "sg:address":"ZA",
    "sg:city":"Fr\u00e8res Lumi\u00e8re 69720 St Bonnet de Mure",
    "sg:classifiers":[
        {
            "category":"Autos & Motor Vehicles",
            "subcategory":"Automobile Sales",
            "type":"Retail Goods"
        }
    ],
    "sg:phone":"+33 4 72 48 81 82",
    "sg:postcode":"69720",
    "sg:province":"Rhone-Alpes",
    "sg:tags":[
        "equipment",
        "industrial",
        "transport"
    ],
    "wof:name":"Chapuis R.t.s.",
    "wof:placetype":"venue"
},
  "geometry": {"coordinates":[5.02467,45.694511],"type":"Point"}
}