{
  "type": "Feature",
  "properties": {
    "addr:full":"Rue Louis Armand Soufflenheim Alsace 67620",
    "addr:postcode":"67620",
    "addr:street":"Rue Louis Armand Soufflenheim",
    "iso:country":"FR",
    "sg:address":"Rue Louis Armand",
    "sg:city":"Soufflenheim",
    "sg:orig_category":"Unclassifiable Establishments",
    "sg:phone":"+33 3 88 05 75 05",
    "sg:postcode":"67620",
    "sg:province":"Alsace",
    "wof:name":"Jaeck Automatismes S.a.r.l.",
    "wof:placetype":"venue"
},
  "geometry": {"coordinates":[7.95625,48.815479],"type":"Point"}
}