{
  "type": "Feature",
  "properties": {
    "addr:full":"29 Quai De Marne \u00c9pernay Champagne 51200",
    "addr:housenumber":"29",
    "addr:postcode":"51200",
    "addr:street":"Quai De Marne;Champagne",
    "iso:country":"FR",
    "sg:address":"29 Quai De Marne",
    "sg:city":"\u00c9pernay",
    "sg:classifiers":[
        {
            "category":"Banks & Credit Unions",
            "subcategory":"Financial Services",
            "type":"Services"
        }
    ],
    "sg:phone":"+33 3 26 54 46 50",
    "sg:postcode":"51200",
    "sg:province":"Champagne",
    "sg:tags":[
        "banking",
        "finance",
        "insurance"
    ],
    "wof:name":"La Fidiciaire Comptable Des Bord De Marne Sa",
    "wof:placetype":"venue"
},
  "geometry": {"coordinates":[3.960925,49.051956],"type":"Point"}
}