{
  "type": "Feature",
  "properties": {
    "addr:full":"Premier Pont Rte De Cambrai 59360 Le Cateau Cambr\u00e9sis Nord Pas-de-Calais 59360",
    "addr:postcode":"59360;59360",
    "addr:street":"Rte De Cambrai;Cateau Cambre\u0301Sis Nord",
    "iso:country":"FR",
    "sg:address":"Premier Pont Rte De Cambrai 59360 Le Cateau Cambr\u00e9sis",
    "sg:classifiers":[
        {
            "category":"Home & Garden",
            "subcategory":"Furniture",
            "type":"Retail Goods"
        }
    ],
    "sg:phone":"+33 3 27 84 00 25",
    "sg:postcode":"59360",
    "sg:province":"Nord Pas-de-Calais",
    "sg:tags":[
        "household",
        "wood"
    ],
    "wof:name":"Caffiaux Et Debatte",
    "wof:placetype":"venue"
},
  "geometry": {"coordinates":[3.543052,50.105213],"type":"Point"}
}