{
  "type": "Feature",
  "properties": {
    "iso:country":"FR",
    "sg:address":"50, Chemin du Professeur Deperet, 69160 Tassin la Demi Lune",
    "sg:orig_category":"Non-Classified Establishments",
    "sg:phone":"+33 4 78 34 00 34",
    "sg:postcode":"69160",
    "sg:province":"Rhone-Alpes",
    "wof:name":"Meilland Richardier Roses Nouvelles S.a.",
    "wof:placetype":"venue"
},
  "geometry": {"coordinates":[4.765582,45.751854],"type":"Point"}
}