{
  "type": "Feature",
  "properties": {
    "addr:full":"Chemin des S\u00e9gonnaux - Zone Portuaire Arles Provence-Alpes-C\u00f4te d'Azur 13200",
    "addr:postcode":"13200",
    "addr:street":"Chemin Des Se\u0301Gonnaux;Portuaire Arles",
    "iso:country":"FR",
    "sg:address":"Chemin des S\u00e9gonnaux - Zone Portuaire",
    "sg:city":"Arles",
    "sg:orig_category":"Non-Classified Establishments",
    "sg:phone":"+33 4 90 96 76 33",
    "sg:postcode":"13200",
    "sg:province":"Provence-Alpes-C\u00f4te d'Azur",
    "wof:name":"Port Fluvial D'arles",
    "wof:placetype":"venue"
},
  "geometry": {"coordinates":[4.70633,43.523918],"type":"Point"}
}