{
  "type": "Feature",
  "properties": {
    "iso:country":"FR",
    "sg:address":"20 rue Lavoisier 01100 Oyonnax",
    "sg:classifiers":[
        {
            "category":"Manufacturing",
            "subcategory":"Rubber & Plastics",
            "type":"Manufacturing & Wholesale Goods"
        }
    ],
    "sg:phone":"+33 4 74 77 05 42",
    "sg:province":"Rhone-Alpes",
    "sg:tags":[
        "article"
    ],
    "wof:name":"Ets Chanel Sarl",
    "wof:placetype":"venue"
},
  "geometry": {"coordinates":[5.648087,46.267075],"type":"Point"}
}