{
  "type": "Feature",
  "properties": {
    "addr:full":"Pl De La Gare 14290 Orbec Orbec Basse Normandie 14290",
    "addr:postcode":"14290;14290",
    "addr:street":"Pl De La Gare",
    "iso:country":"FR",
    "sg:address":"Pl De La Gare 14290 Orbec",
    "sg:city":"Orbec",
    "sg:classifiers":[
        {
            "category":"Farming",
            "subcategory":"Fish & Marine Products",
            "type":"Manufacturing & Wholesale Goods"
        }
    ],
    "sg:phone":"+33 2 31 32 76 98",
    "sg:postcode":"14290",
    "sg:province":"Basse Normandie",
    "sg:tags":[
        "pharmaceutical",
        "food",
        "-",
        "related",
        "chemical",
        "animal",
        "breeding",
        "chemistry",
        "by-product"
    ],
    "wof:name":"Agrial Point Vert",
    "wof:placetype":"venue"
},
  "geometry": {"coordinates":[0.401607,49.02037],"type":"Point"}
}