{
  "type": "Feature",
  "properties": {
    "iso:country":"FR",
    "sg:address":"101 Avenue Du General De Gaulle 51130 Vertus",
    "sg:classifiers":[
        {
            "category":"Food Court",
            "type":"Food & Drink"
        }
    ],
    "sg:phone":"+33 3 26 58 86 32",
    "sg:postcode":"51130",
    "sg:province":"Champagne",
    "sg:tags":[
        "product",
        "related"
    ],
    "wof:name":"Champagne Colin",
    "wof:placetype":"venue"
},
  "geometry": {"coordinates":[4.012096,48.896976],"type":"Point"}
}