{
  "type": "Feature",
  "properties": {
    "iso:country":"FR",
    "sg:address":"94, Rue des Maraichers, 75020 Paris",
    "sg:orig_category":"Unclassifiable Establishments",
    "sg:phone":"+33 1 43 71 01 67",
    "sg:province":"Ile de France",
    "wof:name":"Soci\u00e9t\u00e9 Nouvelle Chevalier Et Compagnie",
    "wof:placetype":"venue"
},
  "geometry": {"coordinates":[2.406293,48.85524],"type":"Point"}
}