{
  "type": "Feature",
  "properties": {
    "iso:country":"FR",
    "sg:address":"2, Rue Coston, 26200 Mont\u00e9limar",
    "sg:orig_category":"Non-Classified Establishments",
    "sg:phone":"+33 4 75 51 81 50",
    "sg:province":"Rhone-Alpes",
    "wof:name":"Greta-dr\u00f4me-proven\u00e7al",
    "wof:placetype":"venue"
},
  "geometry": {"coordinates":[4.752033,44.55872],"type":"Point"}
}