{
  "type": "Feature",
  "properties": {
    "addr:full":"B.P. 7, 62119 Dourges^^Z.A. de Bourcheuil, 62119 Dourges Nord Pas-de-Calais",
    "addr:housenumber":"7",
    "addr:postcode":"62119;62119",
    "addr:street":"B.P.",
    "iso:country":"FR",
    "sg:address":"B.P. 7, 62119 Dourges^^Z.A. de Bourcheuil, 62119 Dourges",
    "sg:orig_category":"Non-Classified Establishments",
    "sg:phone":"+33 3 21 13 81 48",
    "sg:province":"Nord Pas-de-Calais",
    "wof:name":"Semit S.a.",
    "wof:placetype":"venue"
},
  "geometry": {"coordinates":[2.98454,50.43438],"type":"Point"}
}