{
  "type": "Feature",
  "properties": {
    "addr:full":"1 Rue De La Loire Nantes Cedex 2 Pays de Loire 44266",
    "addr:housenumber":"1",
    "addr:postcode":"2 pays;44266",
    "addr:street":"Rue De La Loire",
    "iso:country":"FR",
    "sg:address":"1 Rue De La Loire",
    "sg:city":"Nantes Cedex 2",
    "sg:classifiers":[
        {
            "category":"Banks & Credit Unions",
            "subcategory":"Financial Services",
            "type":"Services"
        }
    ],
    "sg:phone":"+33 2 40 41 41 41",
    "sg:postcode":"44266",
    "sg:province":"Pays de Loire",
    "sg:tags":[
        "banking",
        "finance",
        "insurance"
    ],
    "wof:name":"Region Des Pays De Loire",
    "wof:placetype":"venue"
},
  "geometry": {"coordinates":[-1.529009,47.258694],"type":"Point"}
}