{
  "type": "Feature",
  "properties": {
    "addr:full":"ZI les Iles Cord\u00e9es Veurey Voroize Rhone-Alpes 38113",
    "addr:postcode":"38113",
    "addr:street":"Zi Les Iles Corde\u0301Es Veurey Voroize Rhone-Alpes",
    "iso:country":"FR",
    "sg:address":"ZI les Iles Cord\u00e9es",
    "sg:city":"Veurey Voroize",
    "sg:orig_category":"Unclassifiable Establishments",
    "sg:phone":"+33 4 76 53 96 00",
    "sg:postcode":"38113",
    "sg:province":"Rhone-Alpes",
    "wof:name":"Fonderie Aluzinc S.a.r.l.",
    "wof:placetype":"venue"
},
  "geometry": {"coordinates":[5.613688,45.271927],"type":"Point"}
}