{
  "type": "Feature",
  "properties": {
    "addr:full":"4500, Av. de Grisolles, 31620 Fronton Midi Pyr\u00e9n\u00e9es 31620",
    "addr:housenumber":"4500",
    "addr:postcode":"31620;31620",
    "addr:street":"Av. De Grisolles",
    "iso:country":"FR",
    "sg:address":"4500, Av. de Grisolles, 31620 Fronton",
    "sg:orig_category":"Non-Classified Establishments",
    "sg:phone":"+33 5 34 27 91 91",
    "sg:postcode":"31620",
    "sg:province":"Midi Pyr\u00e9n\u00e9es",
    "wof:name":"Ch\u00e2teau Bellevue La For\u00eat S.c.e.a.",
    "wof:placetype":"venue"
},
  "geometry": {"coordinates":[1.38495,43.84132],"type":"Point"}
}