{
  "type": "Feature",
  "properties": {
    "addr:full":"Les Plantees 38160 St Marcellin Rhone-Alpes 38160",
    "addr:housenumber":"38160",
    "addr:postcode":"38160",
    "addr:street":"St Marcellin Rhone-Alpes",
    "iso:country":"FR",
    "sg:address":"Les Plantees 38160 St Marcellin",
    "sg:classifiers":[
        {
            "category":"Farming",
            "subcategory":"Livestock Farm",
            "type":"Manufacturing & Wholesale Goods"
        }
    ],
    "sg:phone":"+33 4 76 64 00 43",
    "sg:postcode":"38160",
    "sg:province":"Rhone-Alpes",
    "sg:tags":[
        "breeding",
        "agriculture",
        "animal"
    ],
    "wof:name":"Societe Francaise De Production Avicole (sfpa)",
    "wof:placetype":"venue"
},
  "geometry": {"coordinates":[5.314482,45.1366],"type":"Point"}
}