{
  "type": "Feature",
  "properties": {
    "addr:full":"96bis, Rue Henri Barbusse, 80130 Friville Escarbotin Picardie",
    "addr:housenumber":"96bis",
    "addr:postcode":"80130",
    "addr:street":"Rue Henri Barbusse",
    "iso:country":"FR",
    "sg:address":"96bis, Rue Henri Barbusse, 80130 Friville Escarbotin",
    "sg:orig_category":"Unclassifiable Establishments",
    "sg:phone":"+33 3 22 26 31 34",
    "sg:province":"Picardie",
    "wof:name":"Genifer M.b.a. S.a.",
    "wof:placetype":"venue"
},
  "geometry": {"coordinates":[1.543078,50.082966],"type":"Point"}
}