{
  "type": "Feature",
  "properties": {
    "iso:country":"FR",
    "sg:address":"21, Rue Marius Berliet - Espace Industriel, 69720 Saint Bonnet de Mure",
    "sg:orig_category":"Unclassifiable Establishments",
    "sg:phone":"+33 4 78 40 95 95",
    "sg:postcode":"69720",
    "sg:province":"Rhone-Alpes",
    "wof:name":"Doga S.a.",
    "wof:placetype":"venue"
},
  "geometry": {"coordinates":[5.02467,45.694511],"type":"Point"}
}