{
  "type": "Feature",
  "properties": {
    "addr:full":"Rue Billy sur Ourcq Rozet Saint Albin Picardie 02210",
    "addr:postcode":"02210",
    "addr:street":"Rue Billy;Ourcq;Saint;Picardie",
    "iso:country":"FR",
    "sg:address":"Rue Billy sur Ourcq",
    "sg:city":"Rozet Saint Albin",
    "sg:orig_category":"Unclassifiable Establishments",
    "sg:phone":"+33 3 23 71 51 51",
    "sg:postcode":"02210",
    "sg:province":"Picardie",
    "wof:name":"Samin S.a.",
    "wof:placetype":"venue"
},
  "geometry": {"coordinates":[3.35096,49.21339],"type":"Point"}
}