{
  "type": "Feature",
  "properties": {
    "iso:country":"FR",
    "sg:address":"B.P. 70426, 44104 Nantes C\u00e9dex 04^^36, Rue Paul Bert, 44100 Nantes",
    "sg:orig_category":"Non-Classified Establishments",
    "sg:phone":"+33 2 40 38 23 23",
    "sg:postcode":"44100",
    "sg:province":"Pays de Loire",
    "wof:name":"A.f.p.a. - Association Nationale Pour La Formation Professio",
    "wof:placetype":"venue"
},
  "geometry": {"coordinates":[-1.60436,47.211891],"type":"Point"}
}