{
  "type": "Feature",
  "properties": {
    "iso:country":"FR",
    "sg:address":"17, Rue Hamelin, 75116 Paris C\u00e9dex 16",
    "sg:orig_category":"Non-Classified Establishments",
    "sg:phone":"+33 1 47 27 51 49",
    "sg:province":"Picardie",
    "wof:name":"A.p.r.o.d.i. - Association Pour La Promotion Et Le D\u00e9veloppement Industriel",
    "wof:placetype":"venue"
},
  "geometry": {"coordinates":[2.291935,48.867069],"type":"Point"}
}