{
  "type": "Feature",
  "properties": {
    "addr:full":"B.P. 44, 18230 Saint Doulchard C\u00e9dex^^ZI de Malitorne, 18230 Saint Doulchard Saint-Doulchard Centre 18230",
    "addr:housenumber":"saint-doulchard",
    "addr:postcode":"18230;18230 saint doulchard;18230",
    "addr:street":"B.P. 44",
    "iso:country":"FR",
    "sg:address":"B.P. 44, 18230 Saint Doulchard C\u00e9dex^^ZI de Malitorne, 18230 Saint Doulchard",
    "sg:city":"Saint-Doulchard",
    "sg:orig_category":"Non-Classified Establishments",
    "sg:phone":"+33 2 48 27 63 40",
    "sg:postcode":"18230",
    "sg:province":"Centre",
    "wof:name":"Fimatec S.a.",
    "wof:placetype":"venue"
},
  "geometry": {"coordinates":[2.35792,47.104084],"type":"Point"}
}