{
  "type": "Feature",
  "properties": {
    "iso:country":"FR",
    "sg:address":"19, Bd Nomino\u00eb, 35740 Pac\u00e9",
    "sg:city":"Pac\u00e9",
    "sg:orig_category":"Unclassifiable Establishments",
    "sg:phone":"+33 2 99 60 10 11",
    "sg:postcode":"35740",
    "sg:province":"Bretagne",
    "wof:name":"Arsoe Bretagne",
    "wof:placetype":"venue"
},
  "geometry": {"coordinates":[-1.777939,48.145061],"type":"Point"}
}