{
  "type": "Feature",
  "properties": {
    "iso:country":"FR",
    "sg:address":"Rue Julien Neveu",
    "sg:city":"Noyal sur Vilaine",
    "sg:orig_category":"Unclassifiable Establishments",
    "sg:phone":"+33 2 99 04 12 49",
    "sg:postcode":"35530",
    "sg:province":"Bretagne",
    "wof:name":"Les Fromagers De Tradition S.a.",
    "wof:placetype":"venue"
},
  "geometry": {"coordinates":[-1.528671,48.110764],"type":"Point"}
}