{
  "type": "Feature",
  "properties": {
    "iso:country":"FR",
    "sg:address":"B.P. 1, 61700 Domfront^^Z.I., 61700 Domfront",
    "sg:city":"Domfront",
    "sg:orig_category":"Non-Classified Establishments",
    "sg:phone":"+33 2 33 37 57 00",
    "sg:postcode":"61700",
    "sg:province":"Basse Normandie",
    "wof:name":"Lurem S.a.",
    "wof:placetype":"venue"
},
  "geometry": {"coordinates":[-0.614971,48.539494],"type":"Point"}
}