{
  "type": "Feature",
  "properties": {
    "addr:full":"13, Place Etienne Fran\u00e7ois Choisel, 78180 Montigny le Bretonneux Ile de France",
    "addr:housenumber":"13",
    "addr:postcode":"78180",
    "addr:street":"Place Etienne Franc\u0327Ois Choisel",
    "iso:country":"FR",
    "sg:address":"13, Place Etienne Fran\u00e7ois Choisel, 78180 Montigny le Bretonneux",
    "sg:orig_category":"Non-Classified Establishments",
    "sg:phone":"+33 1 34 52 34 20",
    "sg:province":"Ile de France",
    "wof:name":"Randstad Int\u00e9rim S.a.",
    "wof:placetype":"venue"
},
  "geometry": {"coordinates":[2.04605,48.785301],"type":"Point"}
}