{
  "type": "Feature",
  "properties": {
    "iso:country":"FR",
    "sg:address":"360, Av du 7\u00e8me RI, 46000 Cahors",
    "sg:orig_category":"Unclassifiable Establishments",
    "sg:phone":"+33 5 65 20 48 20",
    "sg:province":"Midi Pyr\u00e9n\u00e9es",
    "wof:name":"Sofrec S.a.",
    "wof:placetype":"venue"
},
  "geometry": {"coordinates":[1.428511,44.464668],"type":"Point"}
}