{
  "type": "Feature",
  "properties": {
    "addr:full":"Rue Du Docteur Calmette 59410 Anzin Nord Pas-de-Calais 59410",
    "addr:postcode":"59410;59410",
    "addr:street":"Rue Du Docteur Calmette",
    "iso:country":"FR",
    "sg:address":"Rue Du Docteur Calmette 59410 Anzin",
    "sg:classifiers":[
        {
            "category":"Manufacturing",
            "subcategory":"Glass & Minerals",
            "type":"Manufacturing & Wholesale Goods"
        }
    ],
    "sg:phone":"+33 3 27 28 22 00",
    "sg:postcode":"59410",
    "sg:province":"Nord Pas-de-Calais",
    "sg:tags":[
        "building",
        "material"
    ],
    "wof:name":"Gravis Anzin Sa",
    "wof:placetype":"venue"
},
  "geometry": {"coordinates":[3.51047,50.369324],"type":"Point"}
}