{
  "type": "Feature",
  "properties": {
    "iso:country":"FR",
    "sg:address":"B.P. 28, 78290 Croissy sur Seine^^27, Av. de Wailly, 78290 Croissy sur Seine",
    "sg:orig_category":"Non-Classified Establishments",
    "sg:phone":"+33 1 39 76 11 92",
    "sg:province":"Ile de France",
    "wof:name":"Stora Ensotimber France S.a.",
    "wof:placetype":"venue"
},
  "geometry": {"coordinates":[2.142,48.877205],"type":"Point"}
}