{
  "type": "Feature",
  "properties": {
    "iso:country":"FR",
    "sg:address":"Rte Nationale 75 - La Chapelle",
    "sg:city":"Saint Martin du Mont",
    "sg:orig_category":"Non-Classified Establishments",
    "sg:phone":"+33 4 74 35 58 24",
    "sg:postcode":"01160",
    "sg:province":"Rhone-Alpes",
    "wof:name":"Dubois Isolation Industrie S.a.r.l.",
    "wof:placetype":"venue"
},
  "geometry": {"coordinates":[5.31877,46.082642],"type":"Point"}
}