{
  "type": "Feature",
  "properties": {
    "iso:country":"FR",
    "sg:address":"Place Jean Salusse",
    "sg:city":"Saint Maximin la Sainte Baume",
    "sg:orig_category":"Unclassifiable Establishments",
    "sg:phone":"+33 4 94 86 55 66",
    "sg:postcode":"83470",
    "sg:province":"Lorraine",
    "wof:name":"Hotellerie Du Couvent Royal",
    "wof:placetype":"venue"
},
  "geometry": {"coordinates":[5.862952,43.453381],"type":"Point"}
}