{
  "type": "Feature",
  "properties": {
    "addr:full":"17, Rue Nationale, 37000 Tours Tours Centre 37000",
    "addr:housenumber":"17",
    "addr:postcode":"37000;37000",
    "addr:street":"Rue Nationale",
    "iso:country":"FR",
    "sg:address":"17, Rue Nationale, 37000 Tours",
    "sg:city":"Tours",
    "sg:orig_category":"Non-Classified Establishments",
    "sg:phone":"+33 2 47 61 03 07",
    "sg:postcode":"37000",
    "sg:province":"Centre",
    "wof:name":"P.g Consultants",
    "wof:placetype":"venue"
},
  "geometry": {"coordinates":[0.686595,47.395271],"type":"Point"}
}