{
  "type": "Feature",
  "properties": {
    "iso:country":"FR",
    "sg:address":"ZI Puy Nardon",
    "sg:city":"Mortagne sur S\u00e8vre",
    "sg:orig_category":"Unclassifiable Establishments",
    "sg:phone":"+33 2 51 65 07 25",
    "sg:postcode":"85290",
    "sg:province":"Pays de Loire",
    "wof:name":"Manic S.a.r.l.",
    "wof:placetype":"venue"
},
  "geometry": {"coordinates":[-0.953982,46.994831],"type":"Point"}
}