{
  "type": "Feature",
  "properties": {
    "addr:full":"3, rue Consier - Zone Industrielle, 71530 Crissey Crissey Bourgogne 71530",
    "addr:housenumber":"3",
    "addr:postcode":"71530;71530",
    "addr:street":"Rue Consier Zone Industrielle",
    "iso:country":"FR",
    "sg:address":"3, rue Consier - Zone Industrielle, 71530 Crissey",
    "sg:city":"Crissey",
    "sg:orig_category":"Non-Classified Establishments",
    "sg:phone":"+33 3 85 43 52 01",
    "sg:postcode":"71530",
    "sg:province":"Bourgogne",
    "wof:name":"Setip S.a. - Soci\u00e9t\u00e9 D'etudes Et De Travaux Pour L'industrie Du P\u00e9trole",
    "wof:placetype":"venue"
},
  "geometry": {"coordinates":[4.88201,46.816959],"type":"Point"}
}