{
  "type": "Feature",
  "properties": {
    "addr:full":"16 Pl Jules Nadi 26100 Romans Sur Is\u00e8re Rhone-Alpes 26100",
    "addr:housenumber":"16",
    "addr:postcode":"26100;26100",
    "addr:street":"Pl Jules Nadi",
    "iso:country":"FR",
    "sg:address":"16 Pl Jules Nadi 26100 Romans Sur Is\u00e8re",
    "sg:classifiers":[
        {
            "category":"Banks & Credit Unions",
            "subcategory":"Financial Services",
            "type":"Services"
        }
    ],
    "sg:phone":"+33 4 75 72 82 00",
    "sg:postcode":"26100",
    "sg:province":"Rhone-Alpes",
    "sg:tags":[
        "banking",
        "insurance",
        "institution",
        "finance"
    ],
    "wof:name":"Banque Populaire Des Alpes",
    "wof:placetype":"venue"
},
  "geometry": {"coordinates":[5.051384,45.044571],"type":"Point"}
}