{
  "type": "Feature",
  "properties": {
    "iso:country":"FR",
    "sg:address":"2 Rue Mairie 79100 Ste Radegonde",
    "sg:classifiers":[
        {
            "category":"Shopping",
            "subcategory":"Clothing, Apparel, & Fashions",
            "type":"Retail Goods"
        }
    ],
    "sg:phone":"+33 5 49 68 12 00",
    "sg:postcode":"79100",
    "sg:province":"Poitou-Charentes",
    "sg:tags":[
        "textile",
        "clothing",
        "clothes"
    ],
    "wof:name":"Anett 1 Sarl",
    "wof:placetype":"venue"
},
  "geometry": {"coordinates":[-0.247634,46.996113],"type":"Point"}
}