{
  "type": "Feature",
  "properties": {
    "iso:country":"FR",
    "sg:address":"62 Rte D'Orl\u00e9ans 45190 Beaugency",
    "sg:city":"Beaugency",
    "sg:classifiers":[
        {
            "category":"Autos & Motor Vehicles",
            "subcategory":"Automobile Sales",
            "type":"Retail Goods"
        }
    ],
    "sg:phone":"+33 2 38 46 33 50",
    "sg:postcode":"45190",
    "sg:province":"Centre",
    "sg:tags":[
        "equipment",
        "motor-cars",
        "transport"
    ],
    "wof:name":"Faurecia Sieges D'automobile Sa",
    "wof:placetype":"venue"
},
  "geometry": {"coordinates":[1.632642,47.781315],"type":"Point"}
}