{
  "type": "Feature",
  "properties": {
    "addr:full":"6 Rue Du Palais De Justice 36000 Ch\u00e2teauroux Ch\u00e2teauroux Centre 36000",
    "addr:housenumber":"6",
    "addr:postcode":"36000;36000",
    "addr:street":"Rue Du Palais De Justice;Cha\u0302Teauroux",
    "iso:country":"FR",
    "sg:address":"6 Rue Du Palais De Justice 36000 Ch\u00e2teauroux",
    "sg:city":"Ch\u00e2teauroux",
    "sg:classifiers":[
        {
            "category":"Manufacturing",
            "subcategory":"Printing",
            "type":"Manufacturing & Wholesale Goods"
        }
    ],
    "sg:phone":"+33 2 54 34 42 24",
    "sg:postcode":"36000",
    "sg:province":"Centre",
    "sg:tags":[
        "publishing"
    ],
    "wof:name":"Technique Plan Sarl",
    "wof:placetype":"venue"
},
  "geometry": {"coordinates":[1.692851,46.808392],"type":"Point"}
}