{
  "type": "Feature",
  "properties": {
    "iso:country":"FR",
    "sg:address":"18, Av. de l'Europe, 31520 Ramonville Saint Agne",
    "sg:orig_category":"Non-Classified Establishments",
    "sg:phone":"+33 5 61 75 78 00",
    "sg:province":"Midi Pyr\u00e9n\u00e9es",
    "wof:name":"P.b. Consultant S.a.r.l.",
    "wof:placetype":"venue"
},
  "geometry": {"coordinates":[1.485891,43.552814],"type":"Point"}
}