{
  "type": "Feature",
  "properties": {
    "iso:country":"FR",
    "sg:address":"11 Rue Christophe Colomb 75008 Paris",
    "sg:classifiers":[
        {
            "category":"Professional",
            "subcategory":"Advertising",
            "type":"Services"
        }
    ],
    "sg:phone":"+33 1 47 20 30 33",
    "sg:postcode":"75008",
    "sg:province":"Ile de France",
    "sg:tags":[
        "marketing",
        "medium",
        "communication"
    ],
    "wof:name":"Instit Previs Conjonc Plus Conseil",
    "wof:placetype":"venue"
},
  "geometry": {"coordinates":[2.299134,48.869617],"type":"Point"}
}