{
  "type": "Feature",
  "properties": {
    "addr:full":"60, Av. jean Jaur\u00e8s, 26600 Tain l'Hermitage Rhone-Alpes 26600",
    "addr:postcode":"26600;26600",
    "addr:street":"60 Av. Jean Jaure\u0300S",
    "iso:country":"FR",
    "sg:address":"60, Av. jean Jaur\u00e8s, 26600 Tain l'Hermitage",
    "sg:orig_category":"Unclassifiable Establishments",
    "sg:phone":"+33 4 75 08 35 35",
    "sg:postcode":"26600",
    "sg:province":"Rhone-Alpes",
    "wof:name":"C.g.s.t. Save S.a.s. - Compagnie Gazi\u00e8re Service Technique Save",
    "wof:placetype":"venue"
},
  "geometry": {"coordinates":[4.837465,45.070194],"type":"Point"}
}