{
  "type": "Feature",
  "properties": {
    "addr:full":"Av. Georges Cl\u00e9menceau - TSA 5003 - Immeuble D\u00e9fense Berg\u00e8res Nanterre Ile de France 92000",
    "addr:postcode":"5003;92000",
    "addr:street":"Av. Georges Cle\u0301Menceau Tsa",
    "iso:country":"FR",
    "sg:address":"Av. Georges Cl\u00e9menceau - TSA 5003 - Immeuble D\u00e9fense Berg\u00e8res",
    "sg:city":"Nanterre",
    "sg:orig_category":"Unclassifiable Establishments",
    "sg:phone":"+33 1 41 35 17 00",
    "sg:postcode":"92000",
    "sg:province":"Ile de France",
    "wof:name":"Dun Et Bradstreet S.a.",
    "wof:placetype":"venue"
},
  "geometry": {"coordinates":[2.194875,48.888084],"type":"Point"}
}