{
  "type": "Feature",
  "properties": {
    "addr:full":"5 Rue Antoine Becquerel 72100 Le Mans Pays de Loire",
    "addr:housenumber":"5",
    "addr:postcode":"72100",
    "addr:street":"Rue Antoine Becquerel",
    "iso:country":"FR",
    "sg:address":"5 Rue Antoine Becquerel 72100 Le Mans",
    "sg:classifiers":[
        {
            "category":"Professional",
            "type":"Services"
        }
    ],
    "sg:phone":"+33 2 43 50 28 00",
    "sg:province":"Pays de Loire",
    "sg:tags":[
        "transport",
        "road"
    ],
    "wof:name":"Demenagements Loison Lebreton Sa",
    "wof:placetype":"venue"
},
  "geometry": {"coordinates":[0.18471,47.96516],"type":"Point"}
}