{
  "type": "Feature",
  "properties": {
    "addr:full":"30 Boulevard D'Estienne D'Orves 72100 Le Mans Cedex 1 Pays de Loire 72100",
    "addr:housenumber":"30",
    "addr:postcode":"72100;1 pays;72100",
    "addr:street":"Boulevard D'Estienne D'Orves",
    "iso:country":"FR",
    "sg:address":"30 Boulevard D'Estienne D'Orves 72100 Le Mans Cedex 1",
    "sg:classifiers":[
        {
            "category":"Health Services",
            "subcategory":"Medical Lab",
            "type":"Services"
        }
    ],
    "sg:phone":"+33 2 43 14 31 00",
    "sg:postcode":"72100",
    "sg:province":"Pays de Loire",
    "sg:tags":[
        "chemical",
        "pharmaceutical",
        "pharmacy"
    ],
    "wof:name":"Ocp Repartition",
    "wof:placetype":"venue"
},
  "geometry": {"coordinates":[0.199829,47.979561],"type":"Point"}
}