{
  "type": "Feature",
  "properties": {
    "iso:country":"FR",
    "sg:address":"Rue Jules Valles Zi De La Chevalerie",
    "sg:city":"St Lo",
    "sg:classifiers":[
        {
            "category":"Banks & Credit Unions",
            "subcategory":"Financial Services",
            "type":"Services"
        }
    ],
    "sg:phone":"+33 2 33 77 14 14",
    "sg:postcode":"50000",
    "sg:province":"Basse Normandie",
    "sg:tags":[
        "banking",
        "finance",
        "insurance"
    ],
    "wof:name":"Fiduciaire De France Societe D'expertise Comptable Commissai (fidex)",
    "wof:placetype":"venue"
},
  "geometry": {"coordinates":[-1.073094,49.09045],"type":"Point"}
}