{
  "type": "Feature",
  "properties": {
    "addr:full":"760, Av. du M\u00f4le - ZI de Champagnaux, 74460 Marnaz Rhone-Alpes 74460",
    "addr:housenumber":"760",
    "addr:postcode":"74460;74460",
    "addr:street":"Av. Du Mo\u0302Le Zi De Champagnaux;Rhone-Alpes",
    "iso:country":"FR",
    "sg:address":"760, Av. du M\u00f4le - ZI de Champagnaux, 74460 Marnaz",
    "sg:orig_category":"Non-Classified Establishments",
    "sg:phone":"+33 4 50 98 08 63",
    "sg:postcode":"74460",
    "sg:province":"Rhone-Alpes",
    "wof:name":"Etablissement Debray Bernard S.a.r.l.",
    "wof:placetype":"venue"
},
  "geometry": {"coordinates":[6.52688,46.06094],"type":"Point"}
}