{
  "type": "Feature",
  "properties": {
    "addr:full":"Rue Du G\u00e9n\u00e9ral De Gaulle 22100 Lanvallay Lanvallay Bretagne 22100",
    "addr:postcode":"22100;22100",
    "addr:street":"Rue Du Ge\u0301Ne\u0301Ral De Gaulle;Lanvallay",
    "iso:country":"FR",
    "sg:address":"Rue Du G\u00e9n\u00e9ral De Gaulle 22100 Lanvallay",
    "sg:city":"Lanvallay",
    "sg:classifiers":[
        {
            "category":"Food & Beverages",
            "subcategory":"Fruits & Vegetables",
            "type":"Retail Goods"
        }
    ],
    "sg:phone":"+33 2 96 39 93 03",
    "sg:postcode":"22100",
    "sg:province":"Bretagne",
    "sg:tags":[
        "frozen",
        "product",
        "related"
    ],
    "wof:name":"Argel Ouest",
    "wof:placetype":"venue"
},
  "geometry": {"coordinates":[-2.0182,48.45224],"type":"Point"}
}