{
  "type": "Feature",
  "properties": {
    "addr:full":"rue F\u00e9lix Daguerre 15000 Aurillac Aurillac Auvergne 15000",
    "addr:postcode":"15000;15000",
    "addr:street":"Rue Fe\u0301Lix Daguerre;Auvergne",
    "iso:country":"FR",
    "sg:address":"rue F\u00e9lix Daguerre 15000 Aurillac",
    "sg:city":"Aurillac",
    "sg:orig_category":"Bathrooms, Exclusive",
    "sg:phone":"+33 4 71 63 63 02",
    "sg:postcode":"15000",
    "sg:province":"Auvergne",
    "wof:name":"Gmv Ameublement S.a.",
    "wof:placetype":"venue"
},
  "geometry": {"coordinates":[2.452618,44.910641],"type":"Point"}
}