{
  "type": "Feature",
  "properties": {
    "addr:full":"3, Rue Jean-Jacques Rousseau, 81200 Mazamet Midi Pyr\u00e9n\u00e9es",
    "addr:housenumber":"3",
    "addr:postcode":"81200",
    "addr:street":"Rue Jean-Jacques Rousseau",
    "iso:country":"FR",
    "sg:address":"3, Rue Jean-Jacques Rousseau, 81200 Mazamet",
    "sg:orig_category":"Unclassifiable Establishments",
    "sg:phone":"+33 5 63 97 71 65",
    "sg:province":"Midi Pyr\u00e9n\u00e9es",
    "wof:name":"Sofic S.a. - Soci\u00e9t\u00e9 Fran\u00e7aise D'instruments De Chirurgie",
    "wof:placetype":"venue"
},
  "geometry": {"coordinates":[2.36605,43.460224],"type":"Point"}
}