{
  "type": "Feature",
  "properties": {
    "iso:country":"FR",
    "sg:address":"10bis, Rue Duguay Trouin, 76000 Rouen",
    "sg:orig_category":"Unclassifiable Establishments",
    "sg:phone":"+33 2 35 71 40 48",
    "sg:province":"Haute Normandie",
    "wof:name":"Fimec S.a.r.l.",
    "wof:placetype":"venue"
},
  "geometry": {"coordinates":[1.082023,49.442757],"type":"Point"}
}