{
  "type": "Feature",
  "properties": {
    "addr:full":"Domaine De Grangeneuve 26230 ROUSSAS Rhone-Alpes 26230",
    "addr:postcode":"26230;26230",
    "addr:street":"Rhone-Alpes",
    "iso:country":"FR",
    "sg:address":"Domaine De Grangeneuve 26230 ROUSSAS",
    "sg:classifiers":[
        {
            "category":"Wholesale",
            "subcategory":"Wine & Distilled Alcoholic Beverages",
            "type":"Manufacturing & Wholesale Goods"
        }
    ],
    "sg:phone":"+33 4 75 98 50 22",
    "sg:postcode":"26230",
    "sg:province":"Rhone-Alpes",
    "sg:tags":[
        "french"
    ],
    "wof:name":"Bour O Et H Sarl",
    "wof:placetype":"venue"
},
  "geometry": {"coordinates":[4.774515,44.431591],"type":"Point"}
}