{
  "type": "Feature",
  "properties": {
    "addr:full":"16 Rue Jules Guesde 69310 Pierre B\u00e9nite Rhone-Alpes 69310",
    "addr:housenumber":"16",
    "addr:postcode":"69310;69310",
    "addr:street":"Rue Jules Guesde;Pierre Be\u0301Nite Rhone-Alpes",
    "iso:country":"FR",
    "sg:address":"16 Rue Jules Guesde 69310 Pierre B\u00e9nite",
    "sg:classifiers":[
        {
            "category":"Food & Beverages",
            "subcategory":"Fruits & Vegetables",
            "type":"Retail Goods"
        }
    ],
    "sg:phone":"+33 4 78 51 84 18",
    "sg:postcode":"69310",
    "sg:province":"Rhone-Alpes",
    "sg:tags":[
        "frozen",
        "product",
        "related"
    ],
    "wof:name":"Frigel Lyon Sarl",
    "wof:placetype":"venue"
},
  "geometry": {"coordinates":[4.822565,45.697472],"type":"Point"}
}