{
  "type": "Feature",
  "properties": {
    "addr:full":"4, Bd Marcel Sembat, 93200 Saint Denis Ile de France",
    "addr:housenumber":"4",
    "addr:postcode":"93200",
    "addr:street":"Bd Marcel Sembat",
    "iso:country":"FR",
    "sg:address":"4, Bd Marcel Sembat, 93200 Saint Denis",
    "sg:orig_category":"Unclassifiable Establishments",
    "sg:phone":"+33 1 42 43 52 52",
    "sg:province":"Ile de France",
    "wof:name":"Bnp Lease Groupe",
    "wof:placetype":"venue"
},
  "geometry": {"coordinates":[2.355652,48.930252],"type":"Point"}
}