{
  "type": "Feature",
  "properties": {
    "addr:full":"1, Rue Curie - ZI, 81450 Le Garric Midi Pyr\u00e9n\u00e9es",
    "addr:housenumber":"1",
    "addr:postcode":"81450",
    "addr:street":"Rue Curie Zi",
    "iso:country":"FR",
    "sg:address":"1, Rue Curie - ZI, 81450 Le Garric",
    "sg:orig_category":"Unclassifiable Establishments",
    "sg:phone":"+33 5 63 36 91 40",
    "sg:province":"Midi Pyr\u00e9n\u00e9es",
    "wof:name":"Savour' Miel S.a.r.l.",
    "wof:placetype":"venue"
},
  "geometry": {"coordinates":[2.16579,44.01033],"type":"Point"}
}