{
  "type": "Feature",
  "properties": {
    "iso:country":"FR",
    "sg:address":"Rue Mal Foch",
    "sg:city":"Le Trait",
    "sg:orig_category":"Unclassifiable Establishments",
    "sg:phone":"+33 2 35 37 14 28",
    "sg:postcode":"76580",
    "sg:province":"Haute Normandie",
    "wof:name":"C.e.i. S.a.r.l. - Conception Etudes Ing\u00e9nierie",
    "wof:placetype":"venue"
},
  "geometry": {"coordinates":[0.817565,49.46838],"type":"Point"}
}