{
  "type": "Feature",
  "properties": {
    "iso:country":"FR",
    "sg:address":"9, Rue du Professeur Legendre, 29900 Concarneau",
    "sg:city":"Concarneau",
    "sg:orig_category":"Unclassifiable Establishments",
    "sg:phone":"+33 2 98 60 52 52",
    "sg:postcode":"29900",
    "sg:province":"Bretagne",
    "wof:name":"Chevannes - Merceron - Ballery S.a.",
    "wof:placetype":"venue"
},
  "geometry": {"coordinates":[-3.914458,47.876343],"type":"Point"}
}