{
  "type": "Feature",
  "properties": {
    "addr:full":"194, Rte de Vely, 74300 Magland Rhone-Alpes 74300",
    "addr:housenumber":"194",
    "addr:postcode":"74300;74300",
    "addr:street":"Rte De Vely",
    "iso:country":"FR",
    "sg:address":"194, Rte de Vely, 74300 Magland",
    "sg:orig_category":"Non-Classified Establishments",
    "sg:phone":"+33 4 50 34 70 25",
    "sg:postcode":"74300",
    "sg:province":"Rhone-Alpes",
    "wof:name":"Gilbert Cordier Et Fils S.a.r.l.",
    "wof:placetype":"venue"
},
  "geometry": {"coordinates":[6.618922,46.003586],"type":"Point"}
}