{
  "type": "Feature",
  "properties": {
    "iso:country":"FR",
    "sg:address":"2 pl de Miremont; Vienne; 38200",
    "sg:classifiers":[
        {
            "category":"Banks & Credit Unions",
            "subcategory":"Bank",
            "type":"Services"
        }
    ],
    "sg:phone":"+33 3374858671",
    "sg:postcode":"38200",
    "sg:province":"Rhone-Alpes",
    "wof:name":"Banque Nationale De Paris",
    "wof:placetype":"venue"
},
  "geometry": {"coordinates":[4.874984,45.524662],"type":"Point"}
}