{
  "type": "Feature",
  "properties": {
    "addr:full":"34, Rue de la Vri\u00e8re, 44240 La Chapelle sur Erdre Pays de Loire",
    "addr:housenumber":"34",
    "addr:postcode":"44240",
    "addr:street":"Rue De La Vrie\u0300Re;Chapelle;Erdre",
    "iso:country":"FR",
    "sg:address":"34, Rue de la Vri\u00e8re, 44240 La Chapelle sur Erdre",
    "sg:orig_category":"Non-Classified Establishments",
    "sg:phone":"+33 2 51 81 36 36",
    "sg:province":"Pays de Loire",
    "wof:name":"Westotel Nantes Atlantique",
    "wof:placetype":"venue"
},
  "geometry": {"coordinates":[-1.551,47.282745],"type":"Point"}
}