{
  "type": "Feature",
  "properties": {
    "addr:full":"9, Rue les Haies, 75020 Paris Ile de France",
    "addr:housenumber":"9",
    "addr:postcode":"75020",
    "addr:street":"Rue Les Haies",
    "iso:country":"FR",
    "sg:address":"9, Rue les Haies, 75020 Paris",
    "sg:orig_category":"Unclassifiable Establishments",
    "sg:phone":"+33 1 43 48 06 77",
    "sg:province":"Ile de France",
    "wof:name":"Anju Entreprises S.a.r.l.",
    "wof:placetype":"venue"
},
  "geometry": {"coordinates":[2.399765,48.852421],"type":"Point"}
}