{
  "type": "Feature",
  "properties": {
    "iso:country":"FR",
    "sg:address":"27, Rte du Cheval Blanc, 84300 Cavaillon",
    "sg:orig_category":"Non-Classified Establishments",
    "sg:phone":"+33 4 90 76 01 60",
    "sg:province":"Provence-Alpes-C\u00f4te d'Azur",
    "wof:name":"Provence Moteurs S.a.r.l.",
    "wof:placetype":"venue"
},
  "geometry": {"coordinates":[5.052628,43.832558],"type":"Point"}
}