{
  "type": "Feature",
  "properties": {
    "iso:country":"FR",
    "sg:address":"Le Villard 74130 Le Petit Bornand",
    "sg:classifiers":[
        {
            "category":"Farming",
            "subcategory":"Farm",
            "type":"Manufacturing & Wholesale Goods"
        }
    ],
    "sg:phone":"+33 4 50 03 50 31",
    "sg:postcode":"74130",
    "sg:province":"Rhone-Alpes",
    "sg:tags":[
        "horticulture",
        "agriculture",
        "livestock"
    ],
    "wof:name":"Les Pepinieres D'altitude Puthod Successeurs",
    "wof:placetype":"venue"
},
  "geometry": {"coordinates":[6.397296,46.00565],"type":"Point"}
}