{
  "type": "Feature",
  "properties": {
    "iso:country":"FR",
    "sg:address":"Comblette 71600 Paray le Monial",
    "sg:city":"Varenne-Saint-Germain",
    "sg:orig_category":"Unclassifiable Establishments",
    "sg:phone":"+33 3 85 88 80 10",
    "sg:postcode":"71600",
    "sg:province":"Bourgogne",
    "wof:name":"Imprimerie Pantone 71 S.a.r.l.",
    "wof:placetype":"venue"
},
  "geometry": {"coordinates":[4.11673,46.429741],"type":"Point"}
}