{
  "type": "Feature",
  "properties": {
    "iso:country":"FR",
    "sg:address":"145, Impasse des Rocailles, 34170 Castelnau le Lez",
    "sg:orig_category":"Unclassifiable Establishments",
    "sg:phone":"+33 1 30 98 36 80",
    "sg:province":"Languedoc-Roussillon",
    "wof:name":"B.d.i. S.a.s. - B\u00e9daricienne Doras Industries",
    "wof:placetype":"venue"
},
  "geometry": {"coordinates":[3.919331,43.639538],"type":"Point"}
}