{
  "type": "Feature",
  "properties": {
    "addr:full":"17 rue Jacquard 69730 Genay Rhone-Alpes 69730",
    "addr:housenumber":"17",
    "addr:postcode":"69730;69730",
    "addr:street":"Rue Jacquard",
    "iso:country":"FR",
    "sg:address":"17 rue Jacquard 69730 Genay",
    "sg:orig_category":"Mardi Gras And Carnival Decoration Articles",
    "sg:phone":"+33 4 72 08 11 80",
    "sg:postcode":"69730",
    "sg:province":"Rhone-Alpes",
    "wof:name":"Castiel Fr\u00e8res Import Sa",
    "wof:placetype":"venue"
},
  "geometry": {"coordinates":[4.818137,45.886269],"type":"Point"}
}