{
  "type": "Feature",
  "properties": {
    "iso:country":"FR",
    "sg:address":"Rue du Bois",
    "sg:city":"Nully Tr\u00e9milly",
    "sg:orig_category":"Unclassifiable Establishments",
    "sg:phone":"+33 3 25 55 46 67",
    "sg:postcode":"52110",
    "sg:province":"Champagne",
    "wof:name":"D.a.l. Caquas",
    "wof:placetype":"venue"
},
  "geometry": {"coordinates":[4.803893,48.37072],"type":"Point"}
}