{
  "type": "Feature",
  "properties": {
    "addr:full":"7, Rue Notre Dame d'Esp\u00e9rance, 34000 Montpellier Languedoc-Roussillon",
    "addr:housenumber":"7",
    "addr:postcode":"34000",
    "addr:street":"Rue Notre Dame;\u0301Rance",
    "iso:country":"FR",
    "sg:address":"7, Rue Notre Dame d'Esp\u00e9rance, 34000 Montpellier",
    "sg:orig_category":"Unclassifiable Establishments",
    "sg:phone":"+33 4 67 41 20 96",
    "sg:province":"Languedoc-Roussillon",
    "wof:name":"Citex Technologies S.a.r.l.",
    "wof:placetype":"venue"
},
  "geometry": {"coordinates":[3.827985,43.612274],"type":"Point"}
}