{
  "type": "Feature",
  "properties": {
    "addr:full":"Av. du Pont Rouge - ZAC de la Fraternit\u00e9 Tonnay Charente Poitou-Charentes 17430",
    "addr:postcode":"17430",
    "addr:street":"Av. Du Pont Rouge Zac De La Fraternite\u0301 Tonnay Charente",
    "iso:country":"FR",
    "sg:address":"Av. du Pont Rouge - ZAC de la Fraternit\u00e9",
    "sg:city":"Tonnay Charente",
    "sg:orig_category":"Unclassifiable Establishments",
    "sg:phone":"+33 5 46 88 78 23",
    "sg:postcode":"17430",
    "sg:province":"Poitou-Charentes",
    "wof:name":"C.g.s.t. Save S.a.s. - Compagnie Gazi\u00e8re Service Technique Save",
    "wof:placetype":"venue"
},
  "geometry": {"coordinates":[-0.760494,45.895634],"type":"Point"}
}