{
  "type": "Feature",
  "properties": {
    "addr:full":"45, Av. Victoria, 03200 Vichy Vichy Auvergne 03200",
    "addr:postcode":"03200;03200",
    "addr:street":"45 Av.",
    "iso:country":"FR",
    "sg:address":"45, Av. Victoria, 03200 Vichy",
    "sg:city":"Vichy",
    "sg:orig_category":"Non-Classified Establishments",
    "sg:phone":"+33 4 70 98 37 65",
    "sg:postcode":"03200",
    "sg:province":"Auvergne",
    "wof:name":"Lejeune Transport S.a.",
    "wof:placetype":"venue"
},
  "geometry": {"coordinates":[3.42527,46.128365],"type":"Point"}
}