{
  "type": "Feature",
  "properties": {
    "iso:country":"FR",
    "sg:address":"60 Rue Marcel Dassault Zae Marcel Dassault 93148 Bondy Cedex",
    "sg:classifiers":[
        {
            "category":"Manufacturing",
            "subcategory":"Printing",
            "type":"Manufacturing & Wholesale Goods"
        }
    ],
    "sg:phone":"+33 1 48 48 08 88",
    "sg:province":"\u00cele-de-France",
    "sg:tags":[
        "publishing"
    ],
    "wof:name":"Bso Bellettre Serigraphie Offset",
    "wof:placetype":"venue"
},
  "geometry": {"coordinates":[2.48014,48.902901],"type":"Point"}
}