{
  "type": "Feature",
  "properties": {
    "iso:country":"FR",
    "sg:address":"7, Rue Jacques Monod, 76130 Mont Saint Aignan",
    "sg:orig_category":"Unclassifiable Establishments",
    "sg:phone":"+33 2 35 12 22 88",
    "sg:province":"Haute Normandie",
    "wof:name":"O.c.i. S.a.",
    "wof:placetype":"venue"
},
  "geometry": {"coordinates":[1.095042,49.476776],"type":"Point"}
}