{
  "type": "Feature",
  "properties": {
    "iso:country":"FR",
    "sg:address":"5 T Rue Clement Ader 60200 Compiegne",
    "sg:classifiers":[
        {
            "category":"Wholesale",
            "subcategory":"Farm Supplies",
            "type":"Manufacturing & Wholesale Goods"
        }
    ],
    "sg:phone":"+33 3 44 30 75 00",
    "sg:postcode":"60200",
    "sg:province":"Picardie",
    "sg:tags":[
        "-",
        "machine",
        "equipment",
        "engineering",
        "machinery",
        "mechanical",
        "agriculture"
    ],
    "wof:name":"Basf Agro Sas",
    "wof:placetype":"venue"
},
  "geometry": {"coordinates":[2.787061,49.39529],"type":"Point"}
}