{
  "type": "Feature",
  "properties": {
    "addr:full":"144, Rue des Barillettes - ZI les Barillettes, 73230 Saint Alban Leysse Rhone-Alpes 73230",
    "addr:housenumber":"144",
    "addr:postcode":"73230;73230",
    "addr:street":"Rue Des Barillettes Zi Les Barillettes;Rhone-Alpes",
    "iso:country":"FR",
    "sg:address":"144, Rue des Barillettes - ZI les Barillettes, 73230 Saint Alban Leysse",
    "sg:orig_category":"Unclassifiable Establishments",
    "sg:phone":"+33 4 79 85 05 97",
    "sg:postcode":"73230",
    "sg:province":"Rhone-Alpes",
    "wof:name":"Poncet Sae Imprimerie S.a.",
    "wof:placetype":"venue"
},
  "geometry": {"coordinates":[5.977465,45.571201],"type":"Point"}
}