{
  "type": "Feature",
  "properties": {
    "addr:full":"14, Rue de Fontenay - ZA de Luc\u00e9, 28110 Luc\u00e9 Luc\u00e9 Centre 28110",
    "addr:housenumber":"14",
    "addr:postcode":"28110;28110",
    "addr:street":"Rue De Fontenay Za De Luce\u0301",
    "iso:country":"FR",
    "sg:address":"14, Rue de Fontenay - ZA de Luc\u00e9, 28110 Luc\u00e9",
    "sg:city":"Luc\u00e9",
    "sg:orig_category":"Unclassifiable Establishments",
    "sg:phone":"+33 825 84 50 00",
    "sg:postcode":"28110",
    "sg:province":"Centre",
    "wof:name":"Audas Distribution S.a.",
    "wof:placetype":"venue"
},
  "geometry": {"coordinates":[1.467334,48.440228],"type":"Point"}
}