{
  "type": "Feature",
  "properties": {
    "iso:country":"FR",
    "sg:address":"9, Rue des Moulins, 63400 Chamali\u00e8res",
    "sg:city":"Chamali\u00e8res",
    "sg:orig_category":"Unclassifiable Establishments",
    "sg:phone":"+33 4 73 36 24 95",
    "sg:postcode":"63400",
    "sg:province":"Auvergne",
    "wof:name":"Manumesure S.a.- Manufacture Fran\u00e7aises D'appareils Electroniques De Mesure",
    "wof:placetype":"venue"
},
  "geometry": {"coordinates":[3.068738,45.778778],"type":"Point"}
}