{
  "type": "Feature",
  "properties": {
    "addr:full":"15, Rue Gilles de Roberval, 87280 Limoges Limousin",
    "addr:housenumber":"15",
    "addr:postcode":"87280",
    "addr:street":"Rue Gilles De Roberval",
    "iso:country":"FR",
    "sg:address":"15, Rue Gilles de Roberval, 87280 Limoges",
    "sg:orig_category":"Unclassifiable Establishments",
    "sg:phone":"+33 5 55 38 47 66",
    "sg:province":"Limousin",
    "wof:name":"Vidanges Nouvelles S.a.r.l.",
    "wof:placetype":"venue"
},
  "geometry": {"coordinates":[1.271357,45.879574],"type":"Point"}
}