{
  "type": "Feature",
  "properties": {
    "iso:country":"FR",
    "sg:address":"9, Rue du Chevallier Bayard, 59200 Tourcoing",
    "sg:orig_category":"Non-Classified Establishments",
    "sg:phone":"+33 3 20 25 24 23",
    "sg:province":"Nord Pas-de-Calais",
    "wof:name":"Eurographie S.a.r.l.",
    "wof:placetype":"venue"
},
  "geometry": {"coordinates":[3.172877,50.724934],"type":"Point"}
}