{
  "type": "Feature",
  "properties": {
    "addr:full":"9, Rue du Chevallier Bayard, 59200 Tourcoing Nord Pas-de-Calais",
    "addr:housenumber":"9",
    "addr:postcode":"59200",
    "addr:street":"Rue Du Chevallier Bayard",
    "iso:country":"FR",
    "sg:address":"9, Rue du Chevallier Bayard, 59200 Tourcoing",
    "sg:orig_category":"Non-Classified Establishments",
    "sg:phone":"+33 3 20 25 24 23",
    "sg:province":"Nord Pas-de-Calais",
    "wof:name":"Eurographie S.a.r.l.",
    "wof:placetype":"venue"
},
  "geometry": {"coordinates":[3.172877,50.724934],"type":"Point"}
}