{
  "type": "Feature",
  "properties": {
    "addr:full":"La Croisiere 84500 BOLLENE Centre",
    "addr:postcode":"84500",
    "addr:street":"Bollene",
    "iso:country":"FR",
    "sg:address":"La Croisiere 84500 BOLLENE",
    "sg:classifiers":[
        {
            "category":"Farming",
            "subcategory":"Berry Farm",
            "type":"Manufacturing & Wholesale Goods"
        }
    ],
    "sg:phone":"+33 4 90 30 59 17",
    "sg:province":"Centre",
    "sg:tags":[
        "preserve"
    ],
    "wof:name":"Midi Conserves S.a.",
    "wof:placetype":"venue"
},
  "geometry": {"coordinates":[4.707905,44.272911],"type":"Point"}
}