{
  "type": "Feature",
  "properties": {
    "iso:country":"FR",
    "sg:address":"264 Rue Garibaldi 69488 Lyon Cedex 03",
    "sg:classifiers":[
        {
            "category":"Professional",
            "subcategory":"Engineering",
            "type":"Services"
        }
    ],
    "sg:phone":"+33 4 72 60 64 00",
    "sg:province":"Rhone-Alpes",
    "sg:tags":[
        "machine",
        "-",
        "mechanical"
    ],
    "wof:name":"Elyo Centre Est Mediterranee Sa",
    "wof:placetype":"venue"
},
  "geometry": {"coordinates":[4.852992,45.753838],"type":"Point"}
}