{
  "type": "Feature",
  "properties": {
    "addr:full":"B.P. 427, 18104 Vierzon C\u00e9dex^^35-37, Rue de la Bidauderie, 18100 Vierzon Vierzon Centre 18100",
    "addr:housenumber":"b.p. 427;-37;vierzon",
    "addr:postcode":"18104;18100;18100",
    "addr:street":"Ce\u0301Dex^^35;Rue De La Bidauderie",
    "iso:country":"FR",
    "sg:address":"B.P. 427, 18104 Vierzon C\u00e9dex^^35-37, Rue de la Bidauderie, 18100 Vierzon",
    "sg:city":"Vierzon",
    "sg:orig_category":"Non-Classified Establishments",
    "sg:phone":"+33 2 48 52 40 40",
    "sg:postcode":"18100",
    "sg:province":"Centre",
    "wof:name":"Dalloz Fall Protection S.a.",
    "wof:placetype":"venue"
},
  "geometry": {"coordinates":[2.020555,47.206581],"type":"Point"}
}