{
  "type": "Feature",
  "properties": {
    "addr:full":"Route D'Antisanti 20270 ALERIA Corse",
    "addr:postcode":"20270",
    "addr:street":"Route D'Antisanti",
    "iso:country":"FR",
    "sg:address":"Route D'Antisanti 20270 ALERIA",
    "sg:classifiers":[
        {
            "category":"Manufacturing",
            "subcategory":"Glass & Minerals",
            "type":"Manufacturing & Wholesale Goods"
        }
    ],
    "sg:phone":"+33 4 95 57 03 87",
    "sg:province":"Corse",
    "sg:tags":[
        "polystyrene"
    ],
    "wof:name":"Corstyrene Sa",
    "wof:placetype":"venue"
},
  "geometry": {"coordinates":[9.34438,42.16761],"type":"Point"}
}