{
  "type": "Feature",
  "properties": {
    "addr:full":"5 T Route De Marcoussis 91310 Montlhery Ile de France 91310",
    "addr:housenumber":"5 t",
    "addr:postcode":"91310;ile;91310",
    "addr:street":"Route De Marcoussis;France",
    "iso:country":"FR",
    "sg:address":"5 T Route De Marcoussis 91310 Montlhery",
    "sg:classifiers":[
        {
            "category":"Shopping",
            "subcategory":"Hobbies, Toys, & Games",
            "type":"Retail Goods"
        }
    ],
    "sg:phone":"+33 1 69 01 74 20",
    "sg:postcode":"91310",
    "sg:province":"Ile de France",
    "sg:tags":[
        "product",
        "breeding",
        "miscellaneous",
        "animal",
        "entertainment"
    ],
    "wof:name":"Etablissements Morin Maurice",
    "wof:placetype":"venue"
},
  "geometry": {"coordinates":[2.267109,48.639633],"type":"Point"}
}