{
  "type": "Feature",
  "properties": {
    "addr:full":"Village de Pontchardon Pontchardon Basse Normandie 61120",
    "addr:postcode":"61120",
    "addr:street":"Pontchardon Basse",
    "iso:country":"FR",
    "sg:address":"Village de Pontchardon",
    "sg:city":"Pontchardon",
    "sg:orig_category":"Non-Classified Establishments",
    "sg:phone":"+33 2 33 39 05 42",
    "sg:postcode":"61120",
    "sg:province":"Basse Normandie",
    "wof:name":"C.f.f.c. Pamco Industries S.a.",
    "wof:placetype":"venue"
},
  "geometry": {"coordinates":[0.232705,48.851215],"type":"Point"}
}