{
  "type": "Feature",
  "properties": {
    "addr:full":"15, Av. Descartes, 92350 Le Plessis Robinson Ile de France",
    "addr:postcode":"92350",
    "addr:street":"15 Av. Descartes",
    "iso:country":"FR",
    "sg:address":"15, Av. Descartes, 92350 Le Plessis Robinson",
    "sg:orig_category":"Non-Classified Establishments",
    "sg:phone":"+33 1 46 30 22 38",
    "sg:province":"Ile de France",
    "wof:name":"Metareg S.a.",
    "wof:placetype":"venue"
},
  "geometry": {"coordinates":[2.242295,48.777149],"type":"Point"}
}