{
  "type": "Feature",
  "properties": {
    "addr:full":"12 Boulevard Pierre Renaudet 65014 Tarbes Cedex 9 Centre",
    "addr:housenumber":"12;9",
    "addr:postcode":"65014",
    "addr:street":"Boulevard Pierre Renaudet",
    "iso:country":"FR",
    "sg:address":"12 Boulevard Pierre Renaudet 65014 Tarbes Cedex 9",
    "sg:classifiers":[
        {
            "category":"Shopping",
            "subcategory":"Hobbies, Toys, & Games",
            "type":"Retail Goods"
        }
    ],
    "sg:phone":"+33 5 62 38 61 44",
    "sg:province":"Centre",
    "sg:tags":[
        "product",
        "miscellaneous",
        "entertainment"
    ],
    "wof:name":"Giat Industries",
    "wof:placetype":"venue"
},
  "geometry": {"coordinates":[0.07412,43.232861],"type":"Point"}
}