{
  "type": "Feature",
  "properties": {
    "iso:country":"FR",
    "sg:address":"4, Rue des M\u00e9tiers, 49130 Sainte Gemmes sur Loire",
    "sg:orig_category":"Unclassifiable Establishments",
    "sg:phone":"+33 2 41 66 20 88",
    "sg:province":"Pays de Loire",
    "wof:name":"Cidelec S.a.",
    "wof:placetype":"venue"
},
  "geometry": {"coordinates":[-0.56494,47.424984],"type":"Point"}
}