{
  "type": "Feature",
  "properties": {
    "addr:full":"170, Av. des M\u00e9l\u00e8zes - ZI les Pochons, 74300 Thyez Rhone-Alpes 74300",
    "addr:housenumber":"170",
    "addr:postcode":"74300;74300",
    "addr:street":"Av. Des Me\u0301Le\u0300Zes Zi Les Pochons;Rhone-Alpes",
    "iso:country":"FR",
    "sg:address":"170, Av. des M\u00e9l\u00e8zes - ZI les Pochons, 74300 Thyez",
    "sg:orig_category":"Unclassifiable Establishments",
    "sg:phone":"+33 4 50 98 70 52",
    "sg:postcode":"74300",
    "sg:province":"Rhone-Alpes",
    "wof:name":"Lefaillet G\u00e9rald S.a.",
    "wof:placetype":"venue"
},
  "geometry": {"coordinates":[6.633185,45.987919],"type":"Point"}
}