{
  "type": "Feature",
  "properties": {
    "addr:full":"2 chemin du G\u00e9nie 69200 VENISSIEUX Rhone-Alpes",
    "addr:housenumber":"2",
    "addr:postcode":"69200",
    "addr:street":"Chemin Du Ge\u0301Nie",
    "iso:country":"FR",
    "sg:address":"2 chemin du G\u00e9nie 69200 VENISSIEUX",
    "sg:classifiers":[
        {
            "category":"Government",
            "subcategory":"Office",
            "type":"Public Place"
        }
    ],
    "sg:phone":"+33 4 72 89 84 84",
    "sg:province":"Rhone-Alpes",
    "sg:tags":[
        "planning",
        "engineering",
        "industrial"
    ],
    "wof:name":"Atecas Ing\u00e9nierie Sarl",
    "wof:placetype":"venue"
},
  "geometry": {"coordinates":[4.859597,45.715469],"type":"Point"}
}