{
  "type": "Feature",
  "properties": {
    "iso:country":"FR",
    "sg:address":"54 Rue De La Plant\u00e8re 65360 Mom\u00e8res",
    "sg:classifiers":[
        {
            "category":"Farming",
            "subcategory":"Farm & Veterinary Services",
            "type":"Manufacturing & Wholesale Goods"
        }
    ],
    "sg:phone":"+33 5 62 45 95 34",
    "sg:postcode":"65360",
    "sg:province":"Midi Pyr\u00e9n\u00e9es",
    "sg:tags":[
        "livestock",
        "business",
        "advice",
        "wood",
        "agriculture",
        "furniture"
    ],
    "wof:name":"Expl Forestiere C Bastie Sarl",
    "wof:placetype":"venue"
},
  "geometry": {"coordinates":[0.099951,43.158024],"type":"Point"}
}