{
  "type": "Feature",
  "properties": {
    "addr:full":"17 bis, Rue Anatole France, 01100 Oyonnax Rhone-Alpes 01100",
    "addr:housenumber":"17 bis",
    "addr:postcode":"01100;01100",
    "addr:street":"Rue Anatole France",
    "iso:country":"FR",
    "sg:address":"17 bis, Rue Anatole France, 01100 Oyonnax",
    "sg:orig_category":"Unclassifiable Establishments",
    "sg:phone":"+33 4 74 77 83 45",
    "sg:postcode":"01100",
    "sg:province":"Rhone-Alpes",
    "wof:name":"Laurencin Michel",
    "wof:placetype":"venue"
},
  "geometry": {"coordinates":[5.65959,46.262798],"type":"Point"}
}