{
  "type": "Feature",
  "properties": {
    "addr:full":"B.P. 6, 68540 Bollwiller^^Rte de Guebwiller, 68540 Bollwiller Bollwiller Alsace 68540",
    "addr:housenumber":"6",
    "addr:postcode":"68540;68540;68540",
    "addr:street":"B.P.;Bollwiller",
    "iso:country":"FR",
    "sg:address":"B.P. 6, 68540 Bollwiller^^Rte de Guebwiller, 68540 Bollwiller",
    "sg:city":"Bollwiller",
    "sg:orig_category":"Non-Classified Establishments",
    "sg:phone":"+33 3 89 48 11 65",
    "sg:postcode":"68540",
    "sg:province":"Alsace",
    "wof:name":"Bollwiller Bricolage S.a.",
    "wof:placetype":"venue"
},
  "geometry": {"coordinates":[7.25961,47.860062],"type":"Point"}
}