{
  "type": "Feature",
  "properties": {
    "iso:country":"FR",
    "sg:address":"42 Rte Beynes 78640 Villiers St Fr\u00e9deric",
    "sg:classifiers":[
        {
            "category":"Autos & Motor Vehicles",
            "subcategory":"Automobile Sales",
            "type":"Retail Goods"
        }
    ],
    "sg:phone":"+33 1 34 55 92 00",
    "sg:postcode":"78640",
    "sg:province":"Ile de France",
    "sg:tags":[
        "equipment",
        "motor-cars",
        "transport"
    ],
    "wof:name":"Idvu",
    "wof:placetype":"venue"
},
  "geometry": {"coordinates":[1.876526,48.816734],"type":"Point"}
}