{
  "type": "Feature",
  "properties": {
    "addr:full":"1 rue de la Roussillonnaise 66600 Rivesaltes Languedoc-Roussillon 66600",
    "addr:housenumber":"1",
    "addr:postcode":"66600;66600",
    "addr:street":"Rue De La Roussillonnaise",
    "iso:country":"FR",
    "sg:address":"1 rue de la Roussillonnaise 66600 Rivesaltes",
    "sg:classifiers":[
        {
            "category":"Wholesale",
            "subcategory":"Wine & Distilled Alcoholic Beverages",
            "type":"Manufacturing & Wholesale Goods"
        }
    ],
    "sg:phone":"+33 4 68 64 06 63",
    "sg:postcode":"66600",
    "sg:province":"Languedoc-Roussillon",
    "sg:tags":[
        "french"
    ],
    "wof:name":"Les Unions Et Vignobles Du Rivesaltai Sa",
    "wof:placetype":"venue"
},
  "geometry": {"coordinates":[2.867914,42.768772],"type":"Point"}
}