{
  "type": "Feature",
  "properties": {
    "addr:full":"B.P. 536, 27135 Verneuil sur Avre C\u00e9dex^^ZI, 27135 Verneuil sur Avre Haute Normandie",
    "addr:housenumber":"b.p. 536",
    "addr:postcode":"27135;27135",
    "addr:street":"Avre Ce\u0301Dex^^Zi;Haute Normandie",
    "iso:country":"FR",
    "sg:address":"B.P. 536, 27135 Verneuil sur Avre C\u00e9dex^^ZI, 27135 Verneuil sur Avre",
    "sg:orig_category":"Non-Classified Establishments",
    "sg:phone":"+33 2 32 32 01 54",
    "sg:province":"Haute Normandie",
    "wof:name":"Cooperative Agricole De La R\u00e9gion De Verneuil S.c.a.",
    "wof:placetype":"venue"
},
  "geometry": {"coordinates":[3.869515,46.818153],"type":"Point"}
}