{
  "type": "Feature",
  "properties": {
    "iso:country":"FR",
    "sg:address":"21, Place du Barlet, 59500 Douai",
    "sg:orig_category":"Unclassifiable Establishments",
    "sg:phone":"+33 3 27 87 39 15",
    "sg:province":"Nord Pas-de-Calais",
    "wof:name":"Cuisine 21 S.a.r.l.",
    "wof:placetype":"venue"
},
  "geometry": {"coordinates":[3.083588,50.36607],"type":"Point"}
}