{
  "type": "Feature",
  "properties": {
    "addr:full":"Rte Dep 950 Ste Cecile 84870 Loriol Du Comtat Picardie",
    "addr:housenumber":"950 ste",
    "addr:postcode":"84870",
    "addr:street":"Rte Dep;Cecile;Comtat",
    "iso:country":"FR",
    "sg:address":"Rte Dep 950",
    "sg:city":"Ste Cecile 84870 Loriol Du Comtat",
    "sg:classifiers":[
        {
            "category":"Farming",
            "subcategory":"Livestock Farm",
            "type":"Manufacturing & Wholesale Goods"
        }
    ],
    "sg:phone":"+33 4 90 65 72 46",
    "sg:province":"Picardie",
    "sg:tags":[
        "agriculture"
    ],
    "wof:name":"Pepinieres Clop Sarl",
    "wof:placetype":"venue"
},
  "geometry": {"coordinates":[5.000185,44.076481],"type":"Point"}
}