{
  "type": "Feature",
  "properties": {
    "addr:full":"53 Rue D Estrees 36500 St Genou Sainte-Gemme Centre 36500",
    "addr:housenumber":"53",
    "addr:postcode":"36500;36500",
    "addr:street":"Rue D Estrees",
    "iso:country":"FR",
    "sg:address":"53 Rue D Estrees 36500 St Genou",
    "sg:city":"Sainte-Gemme",
    "sg:classifiers":[
        {
            "category":"Professional",
            "subcategory":"Engineering",
            "type":"Services"
        }
    ],
    "sg:phone":"+33 2 54 38 22 22",
    "sg:postcode":"36500",
    "sg:province":"Centre",
    "sg:tags":[
        "machine",
        "-",
        "mechanical"
    ],
    "wof:name":"Beirens Sa",
    "wof:placetype":"venue"
},
  "geometry": {"coordinates":[1.339747,46.921112],"type":"Point"}
}