{
  "type": "Feature",
  "properties": {
    "addr:full":"ZI De St C\u00e9saire 30000 NIMES Languedoc-Roussillon 30000",
    "addr:postcode":"30000;30000",
    "addr:street":"Zi De St Ce\u0301Saire",
    "iso:country":"FR",
    "sg:address":"ZI De St C\u00e9saire 30000 NIMES",
    "sg:classifiers":[
        {
            "category":"Shopping",
            "subcategory":"Clothing, Apparel, & Fashions",
            "type":"Retail Goods"
        }
    ],
    "sg:phone":"+33 4 66 64 31 45",
    "sg:postcode":"30000",
    "sg:province":"Languedoc-Roussillon",
    "sg:tags":[
        "clothing",
        "motorcycle"
    ],
    "wof:name":"Gants Segura S.a.r.l.",
    "wof:placetype":"venue"
},
  "geometry": {"coordinates":[4.327705,43.817001],"type":"Point"}
}