{
  "type": "Feature",
  "properties": {
    "addr:full":"28, Av. Henri Pourat, 63120 Courpi\u00e8re Courpi\u00e8re Auvergne 63120",
    "addr:postcode":"63120;courpie\u0300re;63120",
    "addr:street":"28 Av. Henri Pourat",
    "iso:country":"FR",
    "sg:address":"28, Av. Henri Pourat, 63120 Courpi\u00e8re",
    "sg:city":"Courpi\u00e8re",
    "sg:orig_category":"Unclassifiable Establishments",
    "sg:phone":"+33 4 73 53 10 77",
    "sg:postcode":"63120",
    "sg:province":"Auvergne",
    "wof:name":"M\u00e9nadier Et Fils S.a.",
    "wof:placetype":"venue"
},
  "geometry": {"coordinates":[3.54477,45.750271],"type":"Point"}
}