{
  "type": "Feature",
  "properties": {
    "iso:country":"FR",
    "sg:address":"Pointe Er Vil 56740 Locmariaquer",
    "sg:city":"Locmariaquer",
    "sg:orig_category":"Unclassifiable Establishments",
    "sg:phone":"+33 2 97 57 30 02",
    "sg:postcode":"56740",
    "sg:province":"Bretagne",
    "wof:name":"Fran\u00e7ois Cadoret",
    "wof:placetype":"venue"
},
  "geometry": {"coordinates":[-2.947762,47.571342],"type":"Point"}
}