{
  "type": "Feature",
  "properties": {
    "addr:full":"18 Rue Guillaume Tell 75017 Paris Ile de France",
    "addr:housenumber":"18",
    "addr:postcode":"75017",
    "addr:street":"Rue Guillaume Tell",
    "iso:country":"FR",
    "sg:address":"18 Rue Guillaume Tell 75017 Paris",
    "sg:classifiers":[
        {
            "category":"Autos & Motor Vehicles",
            "subcategory":"Automobile Sales",
            "type":"Retail Goods"
        }
    ],
    "sg:phone":"+33 1 43 80 25 20",
    "sg:province":"Ile de France",
    "sg:tags":[
        "equipment",
        "transport"
    ],
    "wof:name":"Societe Lyonnaise Des Containers Souples Sarl",
    "wof:placetype":"venue"
},
  "geometry": {"coordinates":[2.294151,48.884129],"type":"Point"}
}