{
  "type": "Feature",
  "properties": {
    "iso:country":"FR",
    "sg:address":"49 Rue Clement Ader 78200 BUCHELAY",
    "sg:classifiers":[
        {
            "category":"Autos & Motor Vehicles",
            "subcategory":"Recreational Vehicle Sales",
            "type":"Retail Goods"
        }
    ],
    "sg:phone":"+33 1 39 24 85 85",
    "sg:postcode":"78200",
    "sg:province":"Ile de France",
    "sg:tags":[
        "car",
        "part"
    ],
    "wof:name":"Sofitec Sa",
    "wof:placetype":"venue"
},
  "geometry": {"coordinates":[1.714715,48.989491],"type":"Point"}
}