{
  "type": "Feature",
  "properties": {
    "addr:full":"27 R Mazagran 13001 Marseille Poitou-Charentes",
    "addr:housenumber":"27",
    "addr:postcode":"13001",
    "addr:street":"R Mazagran",
    "iso:country":"FR",
    "sg:address":"27 R Mazagran 13001 Marseille",
    "sg:classifiers":[
        {
            "category":"Professional",
            "subcategory":"Business Services",
            "type":"Services"
        }
    ],
    "sg:phone":"+33 4 91 24 31 60",
    "sg:province":"Poitou-Charentes",
    "sg:tags":[
        "body",
        "advice"
    ],
    "wof:name":"Feder Amis Instruction Laique",
    "wof:placetype":"venue"
},
  "geometry": {"coordinates":[5.37249,43.293686],"type":"Point"}
}