{
  "type": "Feature",
  "properties": {
    "addr:full":"7, Rue de l'Activit\u00e9 - ZI du Champ Gaillard, 78700 Conflans Sainte Honorine Ile de France 78700",
    "addr:housenumber":"7",
    "addr:postcode":"78700;78700",
    "addr:street":"Rue De L'Activite \u0301 Zi Du Champ Gaillard",
    "iso:country":"FR",
    "sg:address":"7, Rue de l'Activit\u00e9 - ZI du Champ Gaillard, 78700 Conflans Sainte Honorine",
    "sg:orig_category":"Non-Classified Establishments",
    "sg:phone":"+33 1 39 72 69 16",
    "sg:postcode":"78700",
    "sg:province":"Ile de France",
    "wof:name":"Diolot S.a.",
    "wof:placetype":"venue"
},
  "geometry": {"coordinates":[2.092883,49.006557],"type":"Point"}
}