{
  "type": "Feature",
  "properties": {
    "addr:full":"48, Rue du Bourgamon, 38400 Saint Martin d'H\u00e8res Rhone-Alpes",
    "addr:housenumber":"48",
    "addr:postcode":"38400",
    "addr:street":"Rue Du Bourgamon",
    "iso:country":"FR",
    "sg:address":"48, Rue du Bourgamon, 38400 Saint Martin d'H\u00e8res",
    "sg:orig_category":"Non-Classified Establishments",
    "sg:phone":"+33 4 76 62 96 05",
    "sg:province":"Rhone-Alpes",
    "wof:name":"Print'alp S.a.r.l.",
    "wof:placetype":"venue"
},
  "geometry": {"coordinates":[5.762153,45.164482],"type":"Point"}
}