{
  "type": "Feature",
  "properties": {
    "iso:country":"FR",
    "sg:address":"51 rue de I'Eglise; Desvres; 62240",
    "sg:classifiers":[
        {
            "category":"Banks & Credit Unions",
            "subcategory":"Bank",
            "type":"Services"
        }
    ],
    "sg:phone":"+33 21916935",
    "sg:postcode":"62240",
    "sg:province":"Nord Pas-de-Calais",
    "wof:name":"Banque Nationale De Paris",
    "wof:placetype":"venue"
},
  "geometry": {"coordinates":[1.83077,50.669048],"type":"Point"}
}