{
  "type": "Feature",
  "properties": {
    "iso:country":"FR",
    "sg:address":"19 rue de Vanves; Clamart; 92140",
    "sg:classifiers":[
        {
            "category":"Banks & Credit Unions",
            "subcategory":"Bank",
            "type":"Services"
        }
    ],
    "sg:phone":"+33 16442692",
    "sg:postcode":"92140",
    "sg:province":"Ile de France",
    "wof:name":"Banque Nationale De Paris",
    "wof:placetype":"venue"
},
  "geometry": {"coordinates":[2.272467,48.812611],"type":"Point"}
}