{
  "type": "Feature",
  "properties": {
    "addr:full":"Ecurey 55290 MONTIERS SUR SAULX Lorraine 55290",
    "addr:postcode":"55290;55290",
    "addr:street":"Ecurey",
    "iso:country":"FR",
    "sg:address":"Ecurey 55290 MONTIERS SUR SAULX",
    "sg:classifiers":[
        {
            "category":"Government",
            "subcategory":"Fire Station",
            "type":"Public Place"
        }
    ],
    "sg:phone":"+33 3 29 75 88 89",
    "sg:postcode":"55290",
    "sg:province":"Lorraine",
    "sg:tags":[
        "coal",
        "grilling",
        "charcoal"
    ],
    "wof:name":"Carbo France Eurl",
    "wof:placetype":"venue"
},
  "geometry": {"coordinates":[5.271424,48.558105],"type":"Point"}
}