{
  "type": "Feature",
  "properties": {
    "addr:full":"2 Rue Louis Ampere 67400 Illkirch Graffenstaden Geispolsheim Alsace 67400",
    "addr:housenumber":"2",
    "addr:postcode":"67400;67400",
    "addr:street":"Rue Louis Ampere",
    "iso:country":"FR",
    "sg:address":"2 Rue Louis Ampere 67400 Illkirch Graffenstaden",
    "sg:city":"Geispolsheim",
    "sg:classifiers":[
        {
            "category":"Professional",
            "subcategory":"Engineering",
            "type":"Services"
        }
    ],
    "sg:phone":"+33 3 88 65 14 04",
    "sg:postcode":"67400",
    "sg:province":"Alsace",
    "sg:tags":[
        "machine",
        "-",
        "mechanical"
    ],
    "wof:name":"Installations Frigorifiques Ch Gerber Et Compagnie",
    "wof:placetype":"venue"
},
  "geometry": {"coordinates":[7.71171,48.510441],"type":"Point"}
}