{
  "type": "Feature",
  "properties": {
    "addr:full":"31 Rue Sedaine 75011 Paris Ile de France 75011",
    "addr:housenumber":"31",
    "addr:postcode":"75011;75011",
    "addr:street":"Rue Sedaine",
    "iso:country":"FR",
    "sg:address":"31 Rue Sedaine 75011 Paris",
    "sg:classifiers":[
        {
            "category":"Shopping",
            "subcategory":"Clothing, Apparel, & Fashions",
            "type":"Retail Goods"
        }
    ],
    "sg:phone":"+33 1 48 05 10 08",
    "sg:postcode":"75011",
    "sg:province":"Ile de France",
    "sg:tags":[
        "textile",
        "clothing",
        "clothes"
    ],
    "wof:name":"Etablissements Eole",
    "wof:placetype":"venue"
},
  "geometry": {"coordinates":[2.37375,48.856705],"type":"Point"}
}