{
  "type": "Feature",
  "properties": {
    "addr:full":"6, Rue Cl\u00e9ment Ader - ZAC de la Maison Neuve, 44980 Sainte Luce sur Loire Pays de Loire 44980",
    "addr:housenumber":"6",
    "addr:postcode":"44980;sur;pays;44980",
    "addr:street":"Rue Cle\u0301Ment Ader Zac De La Maison Neuve;Luce;Loire",
    "iso:country":"FR",
    "sg:address":"6, Rue Cl\u00e9ment Ader - ZAC de la Maison Neuve, 44980 Sainte Luce sur Loire",
    "sg:orig_category":"Non-Classified Establishments",
    "sg:phone":"+33 2 51 85 09 90",
    "sg:postcode":"44980",
    "sg:province":"Pays de Loire",
    "wof:name":"Automatec S.a.r.l.",
    "wof:placetype":"venue"
},
  "geometry": {"coordinates":[-1.486689,47.249596],"type":"Point"}
}