{
  "type": "Feature",
  "properties": {
    "iso:country":"FR",
    "sg:address":"A Berdoulet 32500 Fleurance",
    "sg:classifiers":[
        {
            "category":"Food & Beverages",
            "subcategory":"Meat & Fish",
            "type":"Retail Goods"
        }
    ],
    "sg:phone":"+33 5 62 64 07 90",
    "sg:postcode":"32500",
    "sg:province":"Midi Pyr\u00e9n\u00e9es",
    "sg:tags":[
        "preserve",
        "cooked",
        "product",
        "related"
    ],
    "wof:name":"Sica Sa",
    "wof:placetype":"venue"
},
  "geometry": {"coordinates":[0.653363,43.861431],"type":"Point"}
}