{
  "type": "Feature",
  "properties": {
    "addr:full":"34, Rue du Canal de Monsieur, 49532 Saint Aubin de Luign\u00e9 Midi Pyr\u00e9n\u00e9es",
    "addr:housenumber":"34",
    "addr:postcode":"49532",
    "addr:street":"Rue Du Canal De Monsieur",
    "iso:country":"FR",
    "sg:address":"34, Rue du Canal de Monsieur, 49532 Saint Aubin de Luign\u00e9",
    "sg:orig_category":"Unclassifiable Establishments",
    "sg:phone":"+33 2 41 78 53 20",
    "sg:province":"Midi Pyr\u00e9n\u00e9es",
    "wof:name":"S.2.i.s. S.a.",
    "wof:placetype":"venue"
},
  "geometry": {"coordinates":[-0.670334,47.328915],"type":"Point"}
}