{
  "type": "Feature",
  "properties": {
    "addr:full":"162, Rue Ducassou - ZI de Lann S\u00e9velin, 56850 Caudan Caudan Bretagne 56850",
    "addr:housenumber":"162",
    "addr:postcode":"56850;56850",
    "addr:street":"Rue Ducassou Zi De Lann Se\u0301Velin;Caudan",
    "iso:country":"FR",
    "sg:address":"162, Rue Ducassou - ZI de Lann S\u00e9velin, 56850 Caudan",
    "sg:city":"Caudan",
    "sg:orig_category":"Unclassifiable Establishments",
    "sg:phone":"+33 2 97 76 00 72",
    "sg:postcode":"56850",
    "sg:province":"Bretagne",
    "wof:name":"Frequelin Electrolyse S.a.",
    "wof:placetype":"venue"
},
  "geometry": {"coordinates":[-3.340384,47.810596],"type":"Point"}
}