{
  "type": "Feature",
  "properties": {
    "iso:country":"FR",
    "sg:address":"5 r Nationale; Anse",
    "sg:classifiers":[
        {
            "category":"Banks & Credit Unions",
            "subcategory":"Bank",
            "type":"Services"
        }
    ],
    "sg:phone":"+33 3374671516",
    "sg:province":"Rhone-Alpes",
    "wof:name":"Banque Nationale De Paris",
    "wof:placetype":"venue"
},
  "geometry": {"coordinates":[-90.100647,32.117153],"type":"Point"}
}