{
  "type": "Feature",
  "properties": {
    "addr:full":"9, Rue de la Sabli\u00e8re, 25300 Pontarlier Franche Comt\u00e9 25300",
    "addr:housenumber":"9",
    "addr:postcode":"25300;25300",
    "addr:street":"Rue De La Sablie\u0300Re;Franche Comte\u0301",
    "iso:country":"FR",
    "sg:address":"9, Rue de la Sabli\u00e8re, 25300 Pontarlier",
    "sg:orig_category":"Non-Classified Establishments",
    "sg:phone":"+33 3 81 46 80 32",
    "sg:postcode":"25300",
    "sg:province":"Franche Comt\u00e9",
    "wof:name":"Bresch Et Fils S.a.",
    "wof:placetype":"venue"
},
  "geometry": {"coordinates":[6.348803,46.903385],"type":"Point"}
}