{
  "type": "Feature",
  "properties": {
    "addr:full":"Desforanges 43330 Pont Salomon Pont-Salomon Auvergne 43330",
    "addr:postcode":"43330;43330",
    "addr:street":"Desforanges;Salomon Pont-Salomon",
    "iso:country":"FR",
    "sg:address":"Desforanges 43330 Pont Salomon",
    "sg:city":"Pont-Salomon",
    "sg:classifiers":[
        {
            "category":"Home & Garden",
            "subcategory":"Furniture",
            "type":"Retail Goods"
        }
    ],
    "sg:phone":"+33 4 71 66 24 70",
    "sg:postcode":"43330",
    "sg:province":"Auvergne",
    "sg:tags":[
        "household",
        "wood"
    ],
    "wof:name":"Ets Fournel Pere Et Fils",
    "wof:placetype":"venue"
},
  "geometry": {"coordinates":[4.233213,45.315914],"type":"Point"}
}