{
  "type": "Feature",
  "properties": {
    "addr:full":"4 Rue Bernard Palissy 54500 Vandoeuvre Les Nancy Lorraine 54500",
    "addr:housenumber":"4",
    "addr:postcode":"54500;54500",
    "addr:street":"Rue Bernard Palissy",
    "iso:country":"FR",
    "sg:address":"4 Rue Bernard Palissy 54500 Vandoeuvre Les Nancy",
    "sg:orig_category":"Miscellaneous Products",
    "sg:phone":"+33 3 83 15 21 21",
    "sg:postcode":"54500",
    "sg:province":"Lorraine",
    "wof:name":"Seita Altadis Sa",
    "wof:placetype":"venue"
},
  "geometry": {"coordinates":[6.180971,48.655163],"type":"Point"}
}