{
  "type": "Feature",
  "properties": {
    "addr:full":"24, Premi\u00e8re Avenue - ZI des Estroublancs, 13127 Vitrolles Midi Pyr\u00e9n\u00e9es",
    "addr:housenumber":"24",
    "addr:postcode":"13127",
    "addr:street":"Premie\u0300Re Avenue Zi Des Estroublancs",
    "iso:country":"FR",
    "sg:address":"24, Premi\u00e8re Avenue - ZI des Estroublancs, 13127 Vitrolles",
    "sg:orig_category":"Unclassifiable Establishments",
    "sg:phone":"+33 4 42 79 44 10",
    "sg:province":"Midi Pyr\u00e9n\u00e9es",
    "wof:name":"Ram",
    "wof:placetype":"venue"
},
  "geometry": {"coordinates":[5.241552,43.437275],"type":"Point"}
}