{
  "type": "Feature",
  "properties": {
    "addr:full":"320 Av De La Biste Zi La Biste 2 34670 Baillargues Languedoc-Roussillon 34670",
    "addr:housenumber":"320;2",
    "addr:postcode":"34670;34670",
    "addr:street":"Av De La Biste Zi La Biste",
    "iso:country":"FR",
    "sg:address":"320 Av De La Biste Zi La Biste 2 34670 Baillargues",
    "sg:classifiers":[
        {
            "category":"Professional",
            "subcategory":"Engineering",
            "type":"Services"
        }
    ],
    "sg:phone":"+33 4 67 91 98 00",
    "sg:postcode":"34670",
    "sg:province":"Languedoc-Roussillon",
    "sg:tags":[
        "machine",
        "-",
        "mechanical"
    ],
    "wof:name":"Cid Plastiques",
    "wof:placetype":"venue"
},
  "geometry": {"coordinates":[4.013353,43.65834],"type":"Point"}
}