{
  "type": "Feature",
  "properties": {
    "addr:full":"43, Rue d' Yvours, 69540 Irigny Rhone-Alpes",
    "addr:housenumber":"43",
    "addr:postcode":"69540",
    "addr:street":"Rue D ' Yvours",
    "iso:country":"FR",
    "sg:address":"43, Rue d' Yvours, 69540 Irigny",
    "sg:orig_category":"Unclassifiable Establishments",
    "sg:phone":"+33 4 72 39 19 00",
    "sg:province":"Rhone-Alpes",
    "wof:name":"Etablissements Loisillon S.a.",
    "wof:placetype":"venue"
},
  "geometry": {"coordinates":[4.826474,45.688812],"type":"Point"}
}