{
  "type": "Feature",
  "properties": {
    "addr:full":"Av. du District - ZI Faulquemont Lorraine 57380",
    "addr:postcode":"57380",
    "addr:street":"Av. Du District",
    "iso:country":"FR",
    "sg:address":"Av. du District - ZI",
    "sg:city":"Faulquemont",
    "sg:orig_category":"Al\u00e9sage Brides sp\u00e9ciales Constructions m\u00e9caniques Fraisage Maintenance et/ou entretien de machines M",
    "sg:phone":"+33 3 87 29 38 50",
    "sg:postcode":"57380",
    "sg:province":"Lorraine",
    "wof:name":"Socomec Industrie S.a.r.l.",
    "wof:placetype":"venue"
},
  "geometry": {"coordinates":[6.599175,49.042831],"type":"Point"}
}