{
  "type": "Feature",
  "properties": {
    "iso:country":"FR",
    "sg:address":"9 Rue Du Capitaine Faure 25000 Besan\u00e7on",
    "sg:classifiers":[
        {
            "category":"Professional",
            "subcategory":"Advertising",
            "type":"Services"
        }
    ],
    "sg:phone":"+33 3 81 81 41 44",
    "sg:postcode":"25000",
    "sg:province":"Franche Comt\u00e9",
    "sg:tags":[
        "communication",
        "medium"
    ],
    "wof:name":"Serge Bastien Et Associes",
    "wof:placetype":"venue"
},
  "geometry": {"coordinates":[6.009348,47.235882],"type":"Point"}
}