{
  "type": "Feature",
  "properties": {
    "iso:country":"FR",
    "sg:address":"25, Rue des Fontaines, 78124 Mareil sur Mauldre",
    "sg:orig_category":"Unclassifiable Establishments",
    "sg:phone":"+33 1 30 90 48 50",
    "sg:province":"Ile de France",
    "wof:name":"A.y.g. Logistique Internationale",
    "wof:placetype":"venue"
},
  "geometry": {"coordinates":[1.870946,48.891895],"type":"Point"}
}