{
  "type": "Feature",
  "properties": {
    "addr:full":"La Tournerie 33420 Grezillac Gr\u00e9zillac Aquitaine 33420",
    "addr:postcode":"33420;33420",
    "iso:country":"FR",
    "sg:address":"La Tournerie 33420 Grezillac",
    "sg:city":"Gr\u00e9zillac",
    "sg:classifiers":[
        {
            "category":"Wholesale",
            "subcategory":"Wine & Distilled Alcoholic Beverages",
            "type":"Manufacturing & Wholesale Goods"
        }
    ],
    "sg:phone":"+33 5 57 25 58 58",
    "sg:postcode":"33420",
    "sg:province":"Aquitaine",
    "sg:tags":[
        "french"
    ],
    "wof:name":"Union De Chateaux Et Domaines Viticoles En Bordelais Sarl",
    "wof:placetype":"venue"
},
  "geometry": {"coordinates":[-0.227227,44.802444],"type":"Point"}
}