{
  "type": "Feature",
  "properties": {
    "addr:full":"90, Rte de Turin, 06300 Nice Basse Normandie",
    "addr:housenumber":"90",
    "addr:postcode":"06300",
    "addr:street":"Rte De Turin",
    "iso:country":"FR",
    "sg:address":"90, Rte de Turin, 06300 Nice",
    "sg:orig_category":"Non-Classified Establishments",
    "sg:phone":"+33 4 93 89 12 07",
    "sg:province":"Basse Normandie",
    "wof:name":"Alpha Equipement S.a.",
    "wof:placetype":"venue"
},
  "geometry": {"coordinates":[7.284792,43.717632],"type":"Point"}
}