{
  "type": "Feature",
  "properties": {
    "iso:country":"FR",
    "sg:address":"67, Bd Cote Blatin, 63000 Clermont Ferrand",
    "sg:city":"Clermont-Ferrand",
    "sg:orig_category":"Non-Classified Establishments",
    "sg:phone":"+33 4 73 93 02 74",
    "sg:postcode":"63000",
    "sg:province":"Auvergne",
    "wof:name":"R.v.b. Gravure S.a.r.l. - Rouge Vert Bleu Gravure",
    "wof:placetype":"venue"
},
  "geometry": {"coordinates":[3.087985,45.767925],"type":"Point"}
}