{
  "type": "Feature",
  "properties": {
    "addr:full":"5 Quai Des Anglais La Ferte Sous Jouarre Ile de France 77260",
    "addr:housenumber":"5",
    "addr:postcode":"77260",
    "addr:street":"Quai Des Anglais;Jouarre",
    "iso:country":"FR",
    "sg:address":"5 Quai Des Anglais",
    "sg:city":"La Ferte Sous Jouarre",
    "sg:classifiers":[
        {
            "category":"Banks & Credit Unions",
            "subcategory":"Financial Services",
            "type":"Services"
        }
    ],
    "sg:phone":"+33 1 60 22 42 09",
    "sg:postcode":"77260",
    "sg:province":"Ile de France",
    "sg:tags":[
        "banking",
        "finance",
        "insurance"
    ],
    "wof:name":"Societe Fiduciaire D'expertise Comptable De Gestion Et De Re (socogere)",
    "wof:placetype":"venue"
},
  "geometry": {"coordinates":[3.131778,48.948235],"type":"Point"}
}