{
  "type": "Feature",
  "properties": {
    "addr:full":"17 rue du Faubourg du Temple Paris 75010",
    "addr:housenumber":"17",
    "addr:postcode":"75010",
    "addr:street":"Rue Du Faubourg Du Temple",
    "iso:country":"FR",
    "sg:address":"17 rue du Faubourg du Temple",
    "sg:city":"Paris",
    "sg:classifiers":[
        {
            "category":"Professional",
            "subcategory":"Management & Consulting",
            "type":"Services"
        }
    ],
    "sg:postcode":"75010",
    "sg:website":"http://www.fabernovel.com",
    "wof:name":"faberNovel",
    "wof:placetype":"venue"
},
  "geometry": {"coordinates":[2.35022,48.862063],"type":"Point"}
}