{
  "type": "Feature",
  "properties": {
    "iso:country":"FR",
    "sg:address":"ZI des Dineux",
    "sg:city":"Tr\u00e9meur",
    "sg:orig_category":"Unclassifiable Establishments",
    "sg:phone":"+33 2 96 84 64 44",
    "sg:postcode":"22250",
    "sg:province":"Bretagne",
    "wof:name":"Motoculture Blanchard S.a.",
    "wof:placetype":"venue"
},
  "geometry": {"coordinates":[-2.263419,48.347321],"type":"Point"}
}