{
  "type": "Feature",
  "properties": {
    "addr:full":"32 r R\u00e9publique; D\u00e9cines Charpieu Haute Normandie",
    "addr:housenumber":"32",
    "addr:street":"R Re\u0301Publique;Charpieu Haute Normandie",
    "iso:country":"FR",
    "sg:address":"32 r R\u00e9publique; D\u00e9cines Charpieu",
    "sg:classifiers":[
        {
            "category":"Banks & Credit Unions",
            "subcategory":"Bank",
            "type":"Services"
        }
    ],
    "sg:phone":"+33 3378492407",
    "sg:province":"Haute Normandie",
    "wof:name":"Lyonnaise De Banque",
    "wof:placetype":"venue"
},
  "geometry": {"coordinates":[4.959704,45.768848],"type":"Point"}
}