{
  "type": "Feature",
  "properties": {
    "iso:country":"FR",
    "sg:address":"8 Pl De La Gare 49100 Angers",
    "sg:classifiers":[
        {
            "category":"Travel",
            "subcategory":"Hotels & Motels",
            "type":"Entertainment"
        }
    ],
    "sg:phone":"+33 2 41 88 49 42",
    "sg:postcode":"49100",
    "sg:province":"Pays de Loire",
    "sg:tags":[
        "hotels",
        "business",
        "restaurant"
    ],
    "wof:name":"Hotel De France",
    "wof:placetype":"venue"
},
  "geometry": {"coordinates":[-0.557051,47.465424],"type":"Point"}
}