{
  "type": "Feature",
  "properties": {
    "addr:full":"4 Rue Escadrille Lafayette 31700 Blagnac Midi Pyr\u00e9n\u00e9es 31700",
    "addr:housenumber":"4",
    "addr:postcode":"31700;31700",
    "addr:street":"Rue Escadrille",
    "iso:country":"FR",
    "sg:address":"4 Rue Escadrille Lafayette 31700 Blagnac",
    "sg:classifiers":[
        {
            "category":"Utilities",
            "subcategory":"Electric",
            "type":"Services"
        }
    ],
    "sg:phone":"+33 5 61 16 75 00",
    "sg:postcode":"31700",
    "sg:province":"Midi Pyr\u00e9n\u00e9es",
    "sg:tags":[
        "electricity",
        "electronic",
        "electrical",
        "equipment"
    ],
    "wof:name":"Compagnie Francaise De Telecommunication (cofratel)",
    "wof:placetype":"venue"
},
  "geometry": {"coordinates":[1.377267,43.634323],"type":"Point"}
}