{
  "type": "Feature",
  "properties": {
    "iso:country":"FR",
    "sg:address":"Rue Principale 64300 Maslacq",
    "sg:city":"Maslacq",
    "sg:classifiers":[
        {
            "category":"Professional",
            "type":"Services"
        }
    ],
    "sg:phone":"+33 5 59 67 61 04",
    "sg:postcode":"64300",
    "sg:province":"Aquitaine",
    "sg:tags":[
        "transport",
        "road"
    ],
    "wof:name":"Maugouber Transports Sarl",
    "wof:placetype":"venue"
},
  "geometry": {"coordinates":[-0.693564,43.440449],"type":"Point"}
}