{
  "type": "Feature",
  "properties": {
    "iso:country":"FR",
    "sg:address":"La Roussille 23140 Jarnages",
    "sg:orig_category":"Unclassifiable Establishments",
    "sg:phone":"+33 5 55 80 90 39",
    "sg:province":"Limousin",
    "wof:name":"Atulam S.a.r.l.",
    "wof:placetype":"venue"
},
  "geometry": {"coordinates":[2.07857,46.184155],"type":"Point"}
}