{
  "type": "Feature",
  "properties": {
    "iso:country":"FR",
    "sg:address":"27 Rue De La Rivaudi\u00e8re 44805 Saint Herblain Cedex",
    "sg:classifiers":[
        {
            "category":"Professional",
            "subcategory":"Business Services",
            "type":"Services"
        }
    ],
    "sg:phone":"+33 2 40 92 13 43",
    "sg:province":"Pays de Loire",
    "sg:tags":[
        "training",
        "advice"
    ],
    "wof:name":"Asso Format Profess Batim Travaux Public",
    "wof:placetype":"venue"
},
  "geometry": {"coordinates":[-1.65366,47.221886],"type":"Point"}
}