{
  "type": "Feature",
  "properties": {
    "iso:country":"FR",
    "sg:address":"109, Av. Victor Hugo, 92140 Clamart",
    "sg:orig_category":"Unclassifiable Establishments",
    "sg:phone":"+33 1 46 42 00 42",
    "sg:province":"Ile de France",
    "wof:name":"Cl\u00f4tures Peignon S.a.r.l.",
    "wof:placetype":"venue"
},
  "geometry": {"coordinates":[2.269702,48.806744],"type":"Point"}
}