{
  "type": "Feature",
  "properties": {
    "addr:full":"221 Av De Grasse 06400 Cannes Rhone-Alpes",
    "addr:housenumber":"221",
    "addr:postcode":"06400",
    "addr:street":"Av De Grasse",
    "iso:country":"FR",
    "sg:address":"221 Av De Grasse 06400 Cannes",
    "sg:orig_category":"Miscellaneous Products",
    "sg:phone":"+33 4 92 98 00 05",
    "sg:province":"Rhone-Alpes",
    "wof:name":"Ogf",
    "wof:placetype":"venue"
},
  "geometry": {"coordinates":[7.004155,43.561211],"type":"Point"}
}