{
  "type": "Feature",
  "properties": {
    "addr:full":"4, Rue M\u00e8ge Mouries - Z.A. Bel Air, 78120 Rambouillet Ile de France",
    "addr:housenumber":"4",
    "addr:postcode":"78120;ile",
    "addr:street":"Rue Me\u0300Ge Mouries;Air",
    "iso:country":"FR",
    "sg:address":"4, Rue M\u00e8ge Mouries - Z.A. Bel Air, 78120 Rambouillet",
    "sg:orig_category":"Unclassifiable Establishments",
    "sg:phone":"+33 1 30 41 82 07",
    "sg:province":"Ile de France",
    "wof:name":"Laboratoires Suppo Steril S.a.",
    "wof:placetype":"venue"
},
  "geometry": {"coordinates":[1.828402,48.622013],"type":"Point"}
}