{
  "type": "Feature",
  "properties": {
    "addr:full":"19, Rue Coriolis, 54000 Nancy Lorraine",
    "addr:housenumber":"19",
    "addr:postcode":"54000",
    "addr:street":"Rue Coriolis",
    "iso:country":"FR",
    "sg:address":"19, Rue Coriolis, 54000 Nancy",
    "sg:orig_category":"Unclassifiable Establishments",
    "sg:phone":"+33 3 83 40 10 44",
    "sg:province":"Lorraine",
    "wof:name":"Itin\u00e9raire Design",
    "wof:placetype":"venue"
},
  "geometry": {"coordinates":[6.161453,48.687737],"type":"Point"}
}