{
  "type": "Feature",
  "properties": {
    "iso:country":"FR",
    "sg:address":"66 Rue Emile Zola 62590 Oignies",
    "sg:classifiers":[
        {
            "category":"Food Court",
            "type":"Food & Drink"
        }
    ],
    "sg:phone":"+33 3 21 74 08 77",
    "sg:postcode":"62590",
    "sg:province":"Nord Pas-de-Calais",
    "sg:tags":[
        "product",
        "related"
    ],
    "wof:name":"Brayel Sa",
    "wof:placetype":"venue"
},
  "geometry": {"coordinates":[2.99866,50.471992],"type":"Point"}
}