{
  "type": "Feature",
  "properties": {
    "addr:full":"Rue Geo Lufbery 02300 Chauny Picardie 02300",
    "addr:postcode":"02300;02300",
    "addr:street":"Rue Geo Lufbery",
    "iso:country":"FR",
    "sg:address":"Rue Geo Lufbery 02300 Chauny",
    "sg:classifiers":[
        {
            "category":"Utilities",
            "subcategory":"Electric",
            "type":"Services"
        }
    ],
    "sg:phone":"+33 810 80 28 02",
    "sg:postcode":"02300",
    "sg:province":"Picardie",
    "sg:tags":[
        "electricity",
        "raw",
        "energy",
        "material"
    ],
    "wof:name":"Electricite De France (edf)",
    "wof:placetype":"venue"
},
  "geometry": {"coordinates":[3.225545,49.611183],"type":"Point"}
}