{
  "type": "Feature",
  "properties": {
    "iso:country":"FR",
    "sg:address":"2, Rue Voltaire, 02100 Gricourt",
    "sg:orig_category":"Unclassifiable Establishments",
    "sg:phone":"+33 3 23 62 70 56",
    "sg:province":"Picardie",
    "wof:name":"Carlier Matines S.a.",
    "wof:placetype":"venue"
},
  "geometry": {"coordinates":[3.232516,49.880421],"type":"Point"}
}