{
  "type": "Feature",
  "properties": {
    "iso:country":"FR",
    "sg:address":"1 Rue Du Burlat 68260 Kingersheim",
    "sg:city":"Kingersheim",
    "sg:classifiers":[
        {
            "category":"Professional",
            "subcategory":"Printing & Photocopies",
            "type":"Services"
        }
    ],
    "sg:phone":"+33 3 89 52 97 97",
    "sg:postcode":"68260",
    "sg:province":"Alsace",
    "sg:tags":[
        "publishing"
    ],
    "wof:name":"Editions Braun",
    "wof:placetype":"venue"
},
  "geometry": {"coordinates":[7.31008,47.792305],"type":"Point"}
}