{
  "type": "Feature",
  "properties": {
    "addr:full":"Rue des Fr\u00e8res Voisins Le Mans C\u00e9dex 2 Pays de Loire 72021",
    "addr:postcode":"72021",
    "addr:street":"Rue Des Fre\u0300Res Voisins",
    "iso:country":"FR",
    "sg:address":"Rue des Fr\u00e8res Voisins",
    "sg:city":"Le Mans C\u00e9dex 2",
    "sg:orig_category":"Non-Classified Establishments",
    "sg:phone":"+33 2 43 43 37 60",
    "sg:postcode":"72021",
    "sg:province":"Pays de Loire",
    "wof:name":"R\u00e9nosol De Nettoyage S.a.",
    "wof:placetype":"venue"
},
  "geometry": {"coordinates":[0.176385,48.031879],"type":"Point"}
}