{
  "type": "Feature",
  "properties": {
    "addr:full":"9 rue des Faisans 67380 Lingolsheim Lingolsheim Alsace 67380",
    "addr:housenumber":"9",
    "addr:postcode":"67380;67380",
    "addr:street":"Rue Des Faisans",
    "iso:country":"FR",
    "sg:address":"9 rue des Faisans 67380 Lingolsheim",
    "sg:city":"Lingolsheim",
    "sg:classifiers":[
        {
            "category":"Food & Beverages",
            "subcategory":"Groceries & Convenience Stores",
            "type":"Retail Goods"
        }
    ],
    "sg:phone":"+33 3 88 10 38 80",
    "sg:postcode":"67380",
    "sg:province":"Alsace",
    "sg:tags":[
        "dietetic",
        "foodstuff"
    ],
    "wof:name":"Herbalife International France Sa",
    "wof:placetype":"venue"
},
  "geometry": {"coordinates":[7.674358,48.551922],"type":"Point"}
}