{
  "type": "Feature",
  "properties": {
    "addr:full":"Les Chaboissi\u00e8res 44330 Vallet Pays de Loire",
    "addr:postcode":"44330",
    "addr:street":"Vallet",
    "iso:country":"FR",
    "sg:address":"Les Chaboissi\u00e8res 44330 Vallet",
    "sg:orig_category":"Non-Classified Establishments",
    "sg:phone":"+33 2 40 33 94 44",
    "sg:province":"Pays de Loire",
    "wof:name":"Patis Des Vignes E.a.r.l.",
    "wof:placetype":"venue"
},
  "geometry": {"coordinates":[-1.221827,47.173862],"type":"Point"}
}