{
  "type": "Feature",
  "properties": {
    "addr:full":"4, Rue des Potiers d'Etain, 57070 Metz Lorraine",
    "addr:housenumber":"4",
    "addr:postcode":"57070",
    "addr:street":"Rue Des Potiers D'Etain",
    "iso:country":"FR",
    "sg:address":"4, Rue des Potiers d'Etain, 57070 Metz",
    "sg:orig_category":"Unclassifiable Establishments",
    "sg:phone":"+33 3 87 76 43 43",
    "sg:province":"Lorraine",
    "wof:name":"Pilz Inter S.a.r.l.",
    "wof:placetype":"venue"
},
  "geometry": {"coordinates":[6.24366,49.116673],"type":"Point"}
}