{
  "type": "Feature",
  "properties": {
    "iso:country":"FR",
    "sg:address":"B.P. 245, 35514 Cesson S\u00e9vign\u00e9 C\u00e9dex^^11, Rue des Charmilles, 35510 Cesson S\u00e9vign\u00e9",
    "sg:city":"Cesson-S\u00e9vign\u00e9",
    "sg:orig_category":"Non-Classified Establishments",
    "sg:phone":"+33 2 99 53 54 88",
    "sg:postcode":"35510",
    "sg:province":"Bretagne",
    "wof:name":"Dauphin Communication",
    "wof:placetype":"venue"
},
  "geometry": {"coordinates":[-1.604404,48.117016],"type":"Point"}
}