{
  "type": "Feature",
  "properties": {
    "addr:full":"82 quai Claude le Lorrain 54000 Nancy Lorraine 54000",
    "addr:housenumber":"82",
    "addr:postcode":"54000;54000",
    "addr:street":"Quai Claude Le Lorrain",
    "iso:country":"FR",
    "sg:address":"82 quai Claude le Lorrain 54000 Nancy",
    "sg:classifiers":[
        {
            "category":"Professional",
            "subcategory":"Business Services",
            "type":"Services"
        }
    ],
    "sg:phone":"+33 3 83 36 65 81",
    "sg:postcode":"54000",
    "sg:province":"Lorraine",
    "sg:tags":[
        "observation",
        "market"
    ],
    "wof:name":"Icn Service Association",
    "wof:placetype":"venue"
},
  "geometry": {"coordinates":[6.170426,48.697933],"type":"Point"}
}