{
  "type": "Feature",
  "properties": {
    "iso:country":"FR",
    "sg:address":"25, Av. de la Lib\u00e9ration, 45000 Orl\u00e9ans",
    "sg:city":"Orl\u00e9ans",
    "sg:orig_category":"Unclassifiable Establishments",
    "sg:phone":"+33 2 38 43 22 96",
    "sg:postcode":"45000",
    "sg:province":"Centre",
    "wof:name":"E.d.n. S.a.r.l. - Europ\u00e9enne De Nettoyage",
    "wof:placetype":"venue"
},
  "geometry": {"coordinates":[1.902156,47.920048],"type":"Point"}
}