{
  "type": "Feature",
  "properties": {
    "iso:country":"FR",
    "sg:address":"41 rue des Iris 68000 Colmar",
    "sg:city":"Colmar",
    "sg:orig_category":"Steelworks, Turnkey",
    "sg:phone":"+33 3 89 23 72 50",
    "sg:postcode":"68000",
    "sg:province":"Alsace",
    "wof:name":"Est Siderurgie Sa",
    "wof:placetype":"venue"
},
  "geometry": {"coordinates":[7.350187,48.063316],"type":"Point"}
}