{
  "type": "Feature",
  "properties": {
    "addr:full":"Parking Tir 68300 St Louis Saint-Louis Alsace 68300",
    "addr:postcode":"68300;68300",
    "iso:country":"FR",
    "sg:address":"Parking Tir 68300 St Louis",
    "sg:city":"Saint-Louis",
    "sg:classifiers":[
        {
            "category":"Banks & Credit Unions",
            "subcategory":"Investment Brokerage",
            "type":"Services"
        }
    ],
    "sg:phone":"+33 3 89 69 14 83",
    "sg:postcode":"68300",
    "sg:province":"Alsace",
    "sg:tags":[
        "-",
        "transport",
        "related"
    ],
    "wof:name":"Sft Gondrand Freres",
    "wof:placetype":"venue"
},
  "geometry": {"coordinates":[7.56349,47.585796],"type":"Point"}
}