{
  "type": "Feature",
  "properties": {
    "iso:country":"FR",
    "sg:address":"33420 St Vincent De Pertignas",
    "sg:city":"Branne",
    "sg:classifiers":[
        {
            "category":"Food Court",
            "type":"Food & Drink"
        }
    ],
    "sg:phone":"+33 5 57 84 13 66",
    "sg:postcode":"33420",
    "sg:province":"Aquitaine",
    "sg:tags":[
        "product",
        "related"
    ],
    "wof:name":"Union Saint Vincent",
    "wof:placetype":"venue"
},
  "geometry": {"coordinates":[-0.111961,44.79845],"type":"Point"}
}