{
  "type": "Feature",
  "properties": {
    "iso:country":"FR",
    "sg:address":"Ferme D Hermeray 78113 Bourdonne",
    "sg:classifiers":[
        {
            "category":"Farming",
            "subcategory":"Livestock Farm",
            "type":"Manufacturing & Wholesale Goods"
        }
    ],
    "sg:phone":"+33 1 34 87 14 79",
    "sg:postcode":"78113",
    "sg:province":"Ile de France",
    "sg:tags":[
        "agriculture"
    ],
    "wof:name":"Ferme D'hermeray Sarl",
    "wof:placetype":"venue"
},
  "geometry": {"coordinates":[1.65252,48.74976],"type":"Point"}
}