{
  "type": "Feature",
  "properties": {
    "iso:country":"FR",
    "sg:address":"07000 St Julien En St Alban",
    "sg:classifiers":[
        {
            "category":"Shopping",
            "subcategory":"Crafts & Fabrics",
            "type":"Retail Goods"
        }
    ],
    "sg:phone":"+33 4 75 66 92 22",
    "sg:postcode":"07000",
    "sg:province":"Rhone-Alpes",
    "sg:tags":[
        "textile",
        "clothing"
    ],
    "wof:name":"Milliken France Sa",
    "wof:placetype":"venue"
},
  "geometry": {"coordinates":[4.698425,44.754501],"type":"Point"}
}