{
  "type": "Feature",
  "properties": {
    "iso:country":"FR",
    "sg:address":"B.P. 38",
    "sg:city":"Claye Souilly C\u00e9dex^^La Ros\u00e9e Gressy 77410 Claye Souilly",
    "sg:orig_category":"Non-Classified Establishments",
    "sg:phone":"+33 1 60 26 00 26",
    "sg:postcode":"77410",
    "sg:province":"Ile de France",
    "wof:name":"Mabillon P\u00e8re Et Fils S.a.",
    "wof:placetype":"venue"
},
  "geometry": {"coordinates":[2.68843,48.945576],"type":"Point"}
}