{
  "type": "Feature",
  "properties": {
    "iso:country":"FR",
    "sg:address":"B.P. 17, 56326 Lorient C\u00e9dex^^18, Av. de Kergroise, 56100 Lorient",
    "sg:city":"Lorient",
    "sg:orig_category":"Non-Classified Establishments",
    "sg:phone":"+33 2 97 37 37 11",
    "sg:postcode":"56100",
    "sg:province":"Bretagne",
    "wof:name":"Ateliers De Kergroise S.a.",
    "wof:placetype":"venue"
},
  "geometry": {"coordinates":[-3.365181,47.748108],"type":"Point"}
}