{
  "type": "Feature",
  "properties": {
    "iso:country":"FR",
    "sg:address":"1 Ter Rue De La Libert\u00e9 91600 Savigny Sur Orge",
    "sg:classifiers":[
        {
            "category":"Manufacturing",
            "subcategory":"Tools & Machinery",
            "type":"Manufacturing & Wholesale Goods"
        }
    ],
    "sg:phone":"+33 1 69 05 07 05",
    "sg:postcode":"91600",
    "sg:province":"Ile de France",
    "sg:tags":[
        "equipment",
        "measurement",
        "-",
        "precision",
        "instrument"
    ],
    "wof:name":"Abbsys France Sarl",
    "wof:placetype":"venue"
},
  "geometry": {"coordinates":[2.349755,48.677353],"type":"Point"}
}