{
  "type": "Feature",
  "properties": {
    "iso:country":"FR",
    "sg:address":"62, Rue Saint Maximin, 69003 Lyon",
    "sg:orig_category":"Unclassifiable Establishments",
    "sg:phone":"+33 4 78 53 51 01",
    "sg:province":"Rhone-Alpes",
    "wof:name":"S.i.r.r. S.a. - Soci\u00e9t\u00e9 D'ing\u00e9nierie De La R\u00e9gion Rh\u00e9nane",
    "wof:placetype":"venue"
},
  "geometry": {"coordinates":[4.87231,45.747799],"type":"Point"}
}