{
  "type": "Feature",
  "properties": {
    "addr:full":"1 Avenue Du Champ De Mars 45072 Orl\u00e9ans Poitou-Charentes",
    "addr:housenumber":"1",
    "addr:postcode":"45072",
    "addr:street":"Avenue Du Champ De Mars",
    "iso:country":"FR",
    "sg:address":"1 Avenue Du Champ De Mars 45072 Orl\u00e9ans",
    "sg:classifiers":[
        {
            "category":"Health Services",
            "subcategory":"Medical Lab",
            "type":"Services"
        }
    ],
    "sg:phone":"+33 2 38 51 58 65",
    "sg:province":"Poitou-Charentes",
    "sg:tags":[
        "chemical",
        "pharmaceutical",
        "pharmacy"
    ],
    "wof:name":"Marinopoulos Famar France",
    "wof:placetype":"venue"
},
  "geometry": {"coordinates":[1.894212,47.89399],"type":"Point"}
}