{
  "type": "Feature",
  "properties": {
    "addr:full":"Za La Boissi\u00e8re 29600 Morlaix Morlaix Bretagne 29600",
    "addr:postcode":"29600;29600",
    "addr:street":"Za La Boissie\u0300Re",
    "iso:country":"FR",
    "sg:address":"Za La Boissi\u00e8re 29600 Morlaix",
    "sg:city":"Morlaix",
    "sg:classifiers":[
        {
            "category":"Professional",
            "subcategory":"Engineering",
            "type":"Services"
        }
    ],
    "sg:phone":"+33 2 98 88 30 30",
    "sg:postcode":"29600",
    "sg:province":"Bretagne",
    "sg:tags":[
        "machine",
        "-",
        "mechanical"
    ],
    "wof:name":"Queguiner Materiaux",
    "wof:placetype":"venue"
},
  "geometry": {"coordinates":[-3.826259,48.577026],"type":"Point"}
}