{
  "type": "Feature",
  "properties": {
    "addr:full":"B.P. 8, 26800 Portes les Valence^^RD 7, 26800 Etoile sur Rhone Rhone-Alpes",
    "addr:housenumber":"8;7",
    "addr:postcode":"26800;26800",
    "addr:street":"B.P.;Valence^^Rd",
    "iso:country":"FR",
    "sg:address":"B.P. 8, 26800 Portes les Valence^^RD 7, 26800 Etoile sur Rhone",
    "sg:orig_category":"Non-Classified Establishments",
    "sg:phone":"+33 4 75 57 00 99",
    "sg:province":"Rhone-Alpes",
    "wof:name":"Irrigaronne S.a.",
    "wof:placetype":"venue"
},
  "geometry": {"coordinates":[4.907647,44.794395],"type":"Point"}
}