{
  "type": "Feature",
  "properties": {
    "addr:full":"6 Avenue Gustave Eiffel 33600 Pessac Pessac Aquitaine 33600",
    "addr:housenumber":"6",
    "addr:postcode":"33600;33600",
    "addr:street":"Avenue Gustave Eiffel",
    "iso:country":"FR",
    "sg:address":"6 Avenue Gustave Eiffel 33600 Pessac",
    "sg:city":"Pessac",
    "sg:classifiers":[
        {
            "category":"Manufacturing",
            "subcategory":"Paper Products",
            "type":"Manufacturing & Wholesale Goods"
        }
    ],
    "sg:phone":"+33 5 57 26 87 13",
    "sg:postcode":"33600",
    "sg:province":"Aquitaine",
    "sg:tags":[
        "packaging",
        "material",
        "-",
        "cardboard"
    ],
    "wof:name":"Radenen Emballages",
    "wof:placetype":"venue"
},
  "geometry": {"coordinates":[-0.639418,44.78632],"type":"Point"}
}