{
  "type": "Feature",
  "properties": {
    "iso:country":"FR",
    "sg:address":"8 RUE GUTENBERG 68800 VIEUX THANN",
    "sg:city":"Thann",
    "sg:classifiers":[
        {
            "category":"Banks & Credit Unions",
            "subcategory":"Bureau De Change",
            "type":"Services"
        }
    ],
    "sg:phone":"+33 3 89 37 98 60",
    "sg:postcode":"68800",
    "sg:province":"Alsace",
    "sg:tags":[
        "mast",
        "boat"
    ],
    "wof:name":"Alucarbon Sarl",
    "wof:placetype":"venue"
},
  "geometry": {"coordinates":[7.144223,47.801224],"type":"Point"}
}