{
  "type": "Feature",
  "properties": {
    "addr:full":"Zone Eurofret Craywick Bat Bur'Opal 59279 Loon Plage Nord Pas-de-Calais",
    "addr:postcode":"59279",
    "addr:street":"Zone Eurofret",
    "iso:country":"FR",
    "sg:address":"Zone Eurofret Craywick Bat Bur'Opal 59279 Loon Plage",
    "sg:classifiers":[
        {
            "category":"Marine",
            "type":"Transportation"
        }
    ],
    "sg:phone":"+33 3 28 22 65 00",
    "sg:province":"Nord Pas-de-Calais",
    "sg:tags":[
        "transport",
        "sea"
    ],
    "wof:name":"Transcap International",
    "wof:placetype":"venue"
},
  "geometry": {"coordinates":[2.189836,50.974831],"type":"Point"}
}