{
  "type": "Feature",
  "properties": {
    "iso:country":"FR",
    "sg:address":"3, Av des Marronniers - ZAC du Bois, 59840 P\u00e9renchies",
    "sg:orig_category":"Unclassifiable Establishments",
    "sg:phone":"+33 3 20 00 19 19",
    "sg:province":"Nord Pas-de-Calais",
    "wof:name":"Burie S.a.",
    "wof:placetype":"venue"
},
  "geometry": {"coordinates":[2.973282,50.668343],"type":"Point"}
}