{
  "type": "Feature",
  "properties": {
    "addr:full":"avenue L\u00e9onard de Vinci 33600 Pessac Pessac Aquitaine 33600",
    "addr:postcode":"33600;33600",
    "addr:street":"Avenue Le\u0301Onard De Vinci",
    "iso:country":"FR",
    "sg:address":"avenue L\u00e9onard de Vinci 33600 Pessac",
    "sg:city":"Pessac",
    "sg:classifiers":[
        {
            "category":"Building & Trades",
            "subcategory":"Locksmith",
            "type":"Services"
        }
    ],
    "sg:phone":"+33 5 56 07 97 07",
    "sg:postcode":"33600",
    "sg:province":"Aquitaine",
    "sg:tags":[
        "software"
    ],
    "wof:name":"Fingo S.a.",
    "wof:placetype":"venue"
},
  "geometry": {"coordinates":[-0.653511,44.783524],"type":"Point"}
}