{
  "type": "Feature",
  "properties": {
    "addr:full":"B.P. 7567, 37075 Tours C\u00e9dex^^12, All\u00e9e Colette Duval - Europarc - Tour Nord, 37000 Tours Tours Centre 37000",
    "addr:postcode":"37075;37000;37000",
    "addr:street":"B.P. 7567;Alle\u0301E Colette Duval Europarc Tour Nord",
    "iso:country":"FR",
    "sg:address":"B.P. 7567, 37075 Tours C\u00e9dex^^12, All\u00e9e Colette Duval - Europarc - Tour Nord, 37000 Tours",
    "sg:city":"Tours",
    "sg:orig_category":"Non-Classified Establishments",
    "sg:phone":"+33 2 47 62 84 84",
    "sg:postcode":"37000",
    "sg:province":"Centre",
    "wof:name":"Schneider Electric S.a.",
    "wof:placetype":"venue"
},
  "geometry": {"coordinates":[0.689715,47.390385],"type":"Point"}
}