{
  "type": "Feature",
  "properties": {
    "addr:full":"B.P. 163, 72303 Solesmes C\u00e9dex^^Rte du Mans, 72300 Solesmes Pays de Loire",
    "addr:housenumber":"b.p. 163",
    "addr:postcode":"72303;72300",
    "addr:street":"Mans",
    "iso:country":"FR",
    "sg:address":"B.P. 163, 72303 Solesmes C\u00e9dex^^Rte du Mans, 72300 Solesmes",
    "sg:orig_category":"Non-Classified Establishments",
    "sg:phone":"+33 2 43 92 27 56",
    "sg:province":"Pays de Loire",
    "wof:name":"Le Bobinage Sabolien Sarl",
    "wof:placetype":"venue"
},
  "geometry": {"coordinates":[-0.326529,47.731071],"type":"Point"}
}