{
  "type": "Feature",
  "properties": {
    "iso:country":"FR",
    "sg:address":"7, Le Pr\u00e9 du Lay, 95620 Parmain",
    "sg:orig_category":"Non-Classified Establishments",
    "sg:phone":"+33 1 34 73 12 73",
    "sg:postcode":"95620",
    "sg:province":"Ile de France",
    "wof:name":"Base X Mini Micro S.a.",
    "wof:placetype":"venue"
},
  "geometry": {"coordinates":[2.209495,49.11412],"type":"Point"}
}