{
  "type": "Feature",
  "properties": {
    "addr:full":"Parc d'Activit\u00e9s la Jos\u00e9phine Saint Christophe du Ligneron Pays de Loire 85670",
    "addr:postcode":"85670",
    "addr:street":"La Jose\u0301Phine Saint Christophe Du Ligneron Pays",
    "iso:country":"FR",
    "sg:address":"Parc d'Activit\u00e9s la Jos\u00e9phine",
    "sg:city":"Saint Christophe du Ligneron",
    "sg:orig_category":"Non-Classified Establishments",
    "sg:phone":"+33 2 51 93 11 88",
    "sg:postcode":"85670",
    "sg:province":"Pays de Loire",
    "wof:name":"Transports P\u00e9rocheau S.a.",
    "wof:placetype":"venue"
},
  "geometry": {"coordinates":[-1.76221,46.823921],"type":"Point"}
}