{
  "type": "Feature",
  "properties": {
    "iso:country":"FR",
    "sg:address":"B.P. 90, 69192 Saint Fons C\u00e9dex^^10, Chemin de Saint Gobain, 69160 Saint Fons",
    "sg:orig_category":"Non-Classified Establishments",
    "sg:phone":"+33 4 72 89 54 55",
    "sg:province":"Rhone-Alpes",
    "wof:name":"Laurylab S.a.r.l.",
    "wof:placetype":"venue"
},
  "geometry": {"coordinates":[4.851114,45.705524],"type":"Point"}
}