{
  "type": "Feature",
  "properties": {
    "addr:full":"55, Rue Marcel Brot, 54000 Nancy Lorraine",
    "addr:housenumber":"55",
    "addr:postcode":"54000",
    "addr:street":"Rue Marcel Brot",
    "iso:country":"FR",
    "sg:address":"55, Rue Marcel Brot, 54000 Nancy",
    "sg:orig_category":"Unclassifiable Establishments",
    "sg:phone":"+33 3 83 85 40 00",
    "sg:province":"Lorraine",
    "wof:name":"Quincaillerie Lorraine S.a.",
    "wof:placetype":"venue"
},
  "geometry": {"coordinates":[6.205403,48.678539],"type":"Point"}
}