{
  "type": "Feature",
  "properties": {
    "iso:country":"FR",
    "sg:address":"19, Rue Raspail, 35300 Foug\u00e8res",
    "sg:city":"Foug\u00e8res",
    "sg:orig_category":"Unclassifiable Establishments",
    "sg:phone":"+33 2 99 99 11 98",
    "sg:postcode":"35300",
    "sg:province":"Bretagne",
    "wof:name":"Galod\u00e9 G.d.n. S.a.r.l.",
    "wof:placetype":"venue"
},
  "geometry": {"coordinates":[-1.191356,48.356224],"type":"Point"}
}