{
  "type": "Feature",
  "properties": {
    "iso:country":"FR",
    "sg:address":"B.P. 9011, 74990 Annecy C\u00e9dex 9^^1, Rte de la Salle - ZAC des Romains, 74960 Cran Gevrier",
    "sg:orig_category":"Non-Classified Establishments",
    "sg:phone":"+33 4 50 67 21 77",
    "sg:postcode":"74960",
    "sg:province":"Rhone-Alpes",
    "wof:name":"S.c.e.e.m. Amad S.a. - Soci\u00e9t\u00e9 De Construction Electrique Et Electro-m\u00e9canique",
    "wof:placetype":"venue"
},
  "geometry": {"coordinates":[6.10647,45.907654],"type":"Point"}
}