{
  "type": "Feature",
  "properties": {
    "iso:country":"FR",
    "sg:address":"20 Rue De L Arc De Triomphe 75017 Paris",
    "sg:orig_category":"Miscellaneous Products",
    "sg:phone":"+33 1 53 04 93 60",
    "sg:postcode":"75017",
    "sg:province":"Ile de France",
    "wof:name":"Forest Line Capdenac",
    "wof:placetype":"venue"
},
  "geometry": {"coordinates":[2.293738,48.877151],"type":"Point"}
}