{
  "type": "Feature",
  "properties": {
    "iso:country":"FR",
    "sg:address":"B.P. 11, 43200 Saint Maurice de Lignon C\u00e9dex^^ZI l'Arjaller, 43200 Saint Maurice de Lignon",
    "sg:city":"Le Pertuis",
    "sg:orig_category":"Non-Classified Establishments",
    "sg:phone":"+33 4 71 65 30 15",
    "sg:postcode":"43200",
    "sg:province":"Auvergne",
    "wof:name":"Abrial Dmi S.a.r.l.",
    "wof:placetype":"venue"
},
  "geometry": {"coordinates":[4.036653,45.144875],"type":"Point"}
}