{
  "type": "Feature",
  "properties": {
    "iso:country":"FR",
    "sg:address":"16 Rue Des Champins 91150 Morigny Champigny",
    "sg:classifiers":[
        {
            "category":"Shopping",
            "subcategory":"Crafts & Fabrics",
            "type":"Retail Goods"
        }
    ],
    "sg:phone":"+33 1 64 94 07 88",
    "sg:postcode":"91150",
    "sg:province":"Ile de France",
    "sg:tags":[
        "textile",
        "clothing"
    ],
    "wof:name":"Baches Monard",
    "wof:placetype":"venue"
},
  "geometry": {"coordinates":[2.1782,48.445255],"type":"Point"}
}