{
  "type": "Feature",
  "properties": {
    "iso:country":"FR",
    "sg:address":"Zone Industrielle 77507 CHELLES CEDEX",
    "sg:city":"Chelles",
    "sg:classifiers":[
        {
            "category":"Shopping",
            "subcategory":"Stationery & Office Supplies",
            "type":"Retail Goods"
        }
    ],
    "sg:phone":"+33 1 60 93 01 10",
    "sg:postcode":"77500",
    "sg:province":"Ile de France",
    "wof:name":"Herbin Sueur Sa",
    "wof:placetype":"venue"
},
  "geometry": {"coordinates":[2.59116,48.87809],"type":"Point"}
}