{
  "type": "Feature",
  "properties": {
    "addr:full":"27 Place De Stockach 74800 La Roche Sur Foron Rhone-Alpes 74800",
    "addr:housenumber":"27",
    "addr:postcode":"74800;74800",
    "addr:street":"Place De Stockach",
    "iso:country":"FR",
    "sg:address":"27 Place De Stockach 74800 La Roche Sur Foron",
    "sg:classifiers":[
        {
            "category":"Professional",
            "subcategory":"Engineering",
            "type":"Services"
        }
    ],
    "sg:phone":"+33 4 50 03 02 39",
    "sg:postcode":"74800",
    "sg:province":"Rhone-Alpes",
    "sg:tags":[
        "machine",
        "-",
        "mechanical"
    ],
    "wof:name":"Societe Nouvelle Du Froid",
    "wof:placetype":"venue"
},
  "geometry": {"coordinates":[6.306582,46.071384],"type":"Point"}
}