{
  "type": "Feature",
  "properties": {
    "addr:full":"R\u00e9sidence des Arcades; Longjumeau; 91160 Ile de France 91160",
    "addr:postcode":"91160 ile;france 91160",
    "addr:street":"Re\u0301Sidence Des Arcades",
    "iso:country":"FR",
    "sg:address":"R\u00e9sidence des Arcades; Longjumeau; 91160",
    "sg:classifiers":[
        {
            "category":"Banks & Credit Unions",
            "subcategory":"Bank",
            "type":"Services"
        }
    ],
    "sg:phone":"+33 3369099101",
    "sg:postcode":"91160",
    "sg:province":"Ile de France",
    "wof:name":"Banque Nationale De Paris",
    "wof:placetype":"venue"
},
  "geometry": {"coordinates":[2.29005,48.691734],"type":"Point"}
}