{
  "type": "Feature",
  "properties": {
    "iso:country":"FR",
    "sg:address":"25, Av. Andr\u00e9 Descours - ., 07270 Lamastre",
    "sg:orig_category":"Non-Classified Establishments",
    "sg:phone":"+33 4 75 06 42 95",
    "sg:postcode":"07270",
    "sg:province":"Rhone-Alpes",
    "wof:name":"Leynier P\u00e8re Et Fils S.a.r.l.",
    "wof:placetype":"venue"
},
  "geometry": {"coordinates":[4.618367,44.990936],"type":"Point"}
}