{
  "type": "Feature",
  "properties": {
    "addr:full":"54 Rue Pierre Curie 78370 Plaisir Ile de France 78370",
    "addr:housenumber":"54",
    "addr:postcode":"78370;78370",
    "addr:street":"Rue Pierre Curie",
    "iso:country":"FR",
    "sg:address":"54 Rue Pierre Curie 78370 Plaisir",
    "sg:classifiers":[
        {
            "category":"Professional",
            "subcategory":"Engineering",
            "type":"Services"
        }
    ],
    "sg:phone":"+33 1 30 79 30 79",
    "sg:postcode":"78370",
    "sg:province":"Ile de France",
    "sg:tags":[
        "machine",
        "-",
        "environment",
        "equipment",
        "machinery",
        "mechanical"
    ],
    "wof:name":"Teris",
    "wof:placetype":"venue"
},
  "geometry": {"coordinates":[1.978857,48.801777],"type":"Point"}
}