{
  "type": "Feature",
  "properties": {
    "addr:full":"Chemin De La Cav\u00e9e 14120 Mondeville Mondeville Basse Normandie 14120",
    "addr:postcode":"14120;14120",
    "addr:street":"Chemin De La Cave\u0301E;Basse",
    "iso:country":"FR",
    "sg:address":"Chemin De La Cav\u00e9e 14120 Mondeville",
    "sg:city":"Mondeville",
    "sg:classifiers":[
        {
            "category":"Professional",
            "type":"Services"
        }
    ],
    "sg:phone":"+33 2 31 70 75 00",
    "sg:postcode":"14120",
    "sg:province":"Basse Normandie",
    "sg:tags":[
        "transport",
        "road"
    ],
    "wof:name":"Abx Logistique",
    "wof:placetype":"venue"
},
  "geometry": {"coordinates":[-0.321784,49.16959],"type":"Point"}
}