{
  "type": "Feature",
  "properties": {
    "addr:full":"L'Etang 78490 Bazoches sur Guyonne Ile de France",
    "addr:postcode":"78490",
    "addr:street":"L'Etang",
    "iso:country":"FR",
    "sg:address":"L'Etang 78490 Bazoches sur Guyonne",
    "sg:orig_category":"Non-Classified Establishments",
    "sg:phone":"+33 1 34 86 09 72",
    "sg:province":"Ile de France",
    "wof:name":"Soci\u00e9t\u00e9 Hanleco S.a.r.l.",
    "wof:placetype":"venue"
},
  "geometry": {"coordinates":[1.789361,48.771812],"type":"Point"}
}