{
  "type": "Feature",
  "properties": {
    "addr:full":"45 Rue Pierre Corneille 69006 Lyon Rhone-Alpes",
    "addr:housenumber":"45",
    "addr:postcode":"69006",
    "addr:street":"Rue Pierre Corneille",
    "iso:country":"FR",
    "sg:address":"45 Rue Pierre Corneille 69006 Lyon",
    "sg:classifiers":[
        {
            "category":"Shopping",
            "subcategory":"Clothing, Apparel, & Fashions",
            "type":"Retail Goods"
        }
    ],
    "sg:phone":"+33 4 78 65 94 03",
    "sg:province":"Rhone-Alpes",
    "sg:tags":[
        "textile",
        "clothing",
        "clothes"
    ],
    "wof:name":"Etablissements Fred",
    "wof:placetype":"venue"
},
  "geometry": {"coordinates":[4.843696,45.765423],"type":"Point"}
}