{
  "type": "Feature",
  "properties": {
    "iso:country":"FR",
    "sg:address":"34 Rue De Chenevieres 54450 BENAMENIL",
    "sg:classifiers":[
        {
            "category":"Utilities",
            "subcategory":"Natural Gas",
            "type":"Services"
        }
    ],
    "sg:phone":"+33 3 83 76 29 29",
    "sg:province":"Lorraine",
    "sg:tags":[
        "mechanics",
        "precision"
    ],
    "wof:name":"Chardin Et Kruum Sa",
    "wof:placetype":"venue"
},
  "geometry": {"coordinates":[6.666207,48.561321],"type":"Point"}
}