{
  "type": "Feature",
  "properties": {
    "addr:full":"3, Rue Amp\u00e8re, 93806 Epinay sur Seine C\u00e9dex \u00cele-de-France",
    "addr:housenumber":"3",
    "addr:postcode":"93806",
    "addr:street":"Rue Ampe\u0300Re",
    "iso:country":"FR",
    "sg:address":"3, Rue Amp\u00e8re, 93806 Epinay sur Seine C\u00e9dex",
    "sg:orig_category":"Non-Classified Establishments",
    "sg:phone":"+33 1 48 23 92 93",
    "sg:province":"\u00cele-de-France",
    "wof:name":"Laboratoires Den Mat France S.a.r.l.",
    "wof:placetype":"venue"
},
  "geometry": {"coordinates":[2.324539,48.950474],"type":"Point"}
}