{
  "type": "Feature",
  "properties": {
    "addr:full":"B.P. 6016, 57401 Sarrebourg C\u00e9dex^^4, Rue Napol\u00e9on 1er, 57400 Sarrebourg Lorraine 57400",
    "addr:postcode":"57401;57400;57400",
    "addr:street":"B.P. 6016;Rue Napole\u0301On 1Er",
    "iso:country":"FR",
    "sg:address":"B.P. 6016, 57401 Sarrebourg C\u00e9dex^^4, Rue Napol\u00e9on 1er, 57400 Sarrebourg",
    "sg:orig_category":"Non-Classified Establishments",
    "sg:phone":"+33 3 87 23 71 35",
    "sg:postcode":"57400",
    "sg:province":"Lorraine",
    "wof:name":"Ergste Westig France S.a.r.l.",
    "wof:placetype":"venue"
},
  "geometry": {"coordinates":[7.052015,48.73254],"type":"Point"}
}