{
  "type": "Feature",
  "properties": {
    "iso:country":"FR",
    "sg:address":"Espace du Bassin du Commerce",
    "sg:city":"Cherbourg",
    "sg:orig_category":"Non-Classified Establishments",
    "sg:phone":"+33 2 33 23 44 00",
    "sg:postcode":"50100",
    "sg:province":"Basse Normandie",
    "wof:name":"La Mar\u00e9e Cherbourgeoise S.a.",
    "wof:placetype":"venue"
},
  "geometry": {"coordinates":[-1.624039,49.6395],"type":"Point"}
}