{
  "type": "Feature",
  "properties": {
    "iso:country":"FR",
    "sg:address":"20 Rue De L'Eau Blanche Zi De Kergonan 29200 Brest",
    "sg:city":"Brest",
    "sg:classifiers":[
        {
            "category":"Professional",
            "type":"Services"
        }
    ],
    "sg:phone":"+33 2 98 41 37 70",
    "sg:postcode":"29200",
    "sg:province":"Bretagne",
    "sg:tags":[
        "transport",
        "road"
    ],
    "wof:name":"Drouin Europe",
    "wof:placetype":"venue"
},
  "geometry": {"coordinates":[-4.49955,48.408119],"type":"Point"}
}