{
  "type": "Feature",
  "properties": {
    "iso:country":"FR",
    "sg:address":"120 rue Bergson 42000 St Etienne",
    "sg:classifiers":[
        {
            "category":"Wholesale",
            "subcategory":"Medical Equipment & Supplies",
            "type":"Manufacturing & Wholesale Goods"
        }
    ],
    "sg:phone":"+33 4 77 74 51 11",
    "sg:postcode":"42000",
    "sg:province":"Rhone-Alpes",
    "wof:name":"La Diffusion Technique Francaise S.a.r.l.",
    "wof:placetype":"venue"
},
  "geometry": {"coordinates":[4.38137,45.461048],"type":"Point"}
}