{
  "type": "Feature",
  "properties": {
    "addr:full":"B.P. 534 Perpignan C\u00e9dex Midi Pyr\u00e9n\u00e9es 66005",
    "addr:housenumber":"b.p.",
    "addr:postcode":"66005",
    "addr:street":"534",
    "iso:country":"FR",
    "sg:address":"B.P. 534",
    "sg:city":"Perpignan C\u00e9dex",
    "sg:orig_category":"Non-Classified Establishments",
    "sg:phone":"+33 4 68 51 05 80",
    "sg:postcode":"66005",
    "sg:province":"Midi Pyr\u00e9n\u00e9es",
    "wof:name":"Frutag S.a.r.l.",
    "wof:placetype":"venue"
},
  "geometry": {"coordinates":[2.88743,42.69812],"type":"Point"}
}