{
  "type": "Feature",
  "properties": {
    "iso:country":"FR",
    "sg:address":"Rte de l'Industrie",
    "sg:city":"La B\u00e2thie",
    "sg:orig_category":"Unclassifiable Establishments",
    "sg:phone":"+33 4 79 89 64 09",
    "sg:postcode":"73540",
    "sg:province":"Rhone-Alpes",
    "wof:name":"Pouget Daniel",
    "wof:placetype":"venue"
},
  "geometry": {"coordinates":[6.437507,45.638634],"type":"Point"}
}