{
  "type": "Feature",
  "properties": {
    "addr:full":"5, Chemin du Moulin de la Rib\u00e8re, 32000 Auch Midi Pyr\u00e9n\u00e9es 32000",
    "addr:housenumber":"5",
    "addr:postcode":"32000;32000",
    "addr:street":"Chemin Du Moulin De La Ribe\u0300Re",
    "iso:country":"FR",
    "sg:address":"5, Chemin du Moulin de la Rib\u00e8re, 32000 Auch",
    "sg:orig_category":"Non-Classified Establishments",
    "sg:phone":"+33 5 62 60 64 64",
    "sg:postcode":"32000",
    "sg:province":"Midi Pyr\u00e9n\u00e9es",
    "wof:name":"Bureau Moderne S.a.",
    "wof:placetype":"venue"
},
  "geometry": {"coordinates":[0.582335,43.628014],"type":"Point"}
}