{
  "type": "Feature",
  "properties": {
    "addr:full":"27 avenue de Pezenas 34120 NEZIGNAN L EVEQUE Languedoc-Roussillon 34120",
    "addr:housenumber":"27",
    "addr:postcode":"34120;34120",
    "addr:street":"Avenue De Pezenas",
    "iso:country":"FR",
    "sg:address":"27 avenue de Pezenas 34120 NEZIGNAN L EVEQUE",
    "sg:classifiers":[
        {
            "category":"Food & Beverages",
            "subcategory":"Fruits & Vegetables",
            "type":"Retail Goods"
        }
    ],
    "sg:phone":"+33 4 67 90 45 40",
    "sg:postcode":"34120",
    "sg:province":"Languedoc-Roussillon",
    "sg:tags":[
        "paste"
    ],
    "wof:name":"Dumas S.a.",
    "wof:placetype":"venue"
},
  "geometry": {"coordinates":[3.407012,43.421234],"type":"Point"}
}