{
  "type": "Feature",
  "properties": {
    "iso:country":"FR",
    "sg:address":"17 Rue Des 2 Gares 92565 Rueil Malmaison",
    "sg:classifiers":[
        {
            "category":"Manufacturing",
            "subcategory":"Metals",
            "type":"Manufacturing & Wholesale Goods"
        }
    ],
    "sg:phone":"+33 1 47 14 55 55",
    "sg:province":"Aquitaine",
    "sg:tags":[
        "metallurgy",
        "steel",
        "metalworking"
    ],
    "wof:name":"Reynolds European Sas",
    "wof:placetype":"venue"
},
  "geometry": {"coordinates":[2.171548,48.887951],"type":"Point"}
}