{
  "type": "Feature",
  "properties": {
    "addr:full":"B.P. 435, 95005 Cergy C\u00e9dex^^Rue du Compas - ZI des B\u00e9thunes, 95310 Saint Ouen l'Aum\u00f4ne Ile de France",
    "addr:housenumber":"b.p. 435",
    "addr:postcode":"95005;95310",
    "addr:street":"Zi Des Be\u0301Thunes",
    "iso:country":"FR",
    "sg:address":"B.P. 435, 95005 Cergy C\u00e9dex^^Rue du Compas - ZI des B\u00e9thunes, 95310 Saint Ouen l'Aum\u00f4ne",
    "sg:orig_category":"Non-Classified Establishments",
    "sg:phone":"+33 1 34 48 38 38",
    "sg:province":"Ile de France",
    "wof:name":"Soci\u00e9t\u00e9 Gaffarel Musique S.a.",
    "wof:placetype":"venue"
},
  "geometry": {"coordinates":[2.12935,49.04504],"type":"Point"}
}