{
  "type": "Feature",
  "properties": {
    "iso:country":"FR",
    "sg:address":"63, Rue de B\u00e9arnais, 31000 Toulouse",
    "sg:orig_category":"Unclassifiable Establishments",
    "sg:phone":"+33 5 61 22 66 75",
    "sg:province":"Midi Pyr\u00e9n\u00e9es",
    "wof:name":"Les Chaudronniers Toulousains S.a.",
    "wof:placetype":"venue"
},
  "geometry": {"coordinates":[1.42534,43.61187],"type":"Point"}
}