{
  "type": "Feature",
  "properties": {
    "iso:country":"FR",
    "sg:address":"Zone Artisanale Errobi Larrondoko Eiherra 64250 Itxassou",
    "sg:city":"Itxassou",
    "sg:classifiers":[
        {
            "category":"Farming",
            "subcategory":"Livestock Farm",
            "type":"Manufacturing & Wholesale Goods"
        }
    ],
    "sg:phone":"+33 5 59 29 23 63",
    "sg:postcode":"64250",
    "sg:province":"Aquitaine",
    "sg:tags":[
        "agriculture"
    ],
    "wof:name":"Loreki",
    "wof:placetype":"venue"
},
  "geometry": {"coordinates":[-1.406502,43.332458],"type":"Point"}
}