{
  "type": "Feature",
  "properties": {
    "addr:full":"30 R Du Commerce 37140 Bourgueil Bourgueil Centre 37140",
    "addr:housenumber":"30",
    "addr:postcode":"37140;37140",
    "addr:street":"R Du Commerce",
    "iso:country":"FR",
    "sg:address":"30 R Du Commerce 37140 Bourgueil",
    "sg:city":"Bourgueil",
    "sg:classifiers":[
        {
            "category":"Professional",
            "subcategory":"Business Services",
            "type":"Services"
        }
    ],
    "sg:phone":"+33 2 47 97 73 45",
    "sg:postcode":"37140",
    "sg:province":"Centre",
    "sg:tags":[
        "body",
        "advice"
    ],
    "wof:name":"Assad",
    "wof:placetype":"venue"
},
  "geometry": {"coordinates":[0.170014,47.282776],"type":"Point"}
}