{
  "type": "Feature",
  "properties": {
    "addr:full":"74, Rte de Gen\u00e8ve, 89100 Malay le Petit Villeroy Bourgogne 89100",
    "addr:housenumber":"74",
    "addr:postcode":"89100;89100",
    "addr:street":"Rte De Gene\u0300Ve",
    "iso:country":"FR",
    "sg:address":"74, Rte de Gen\u00e8ve, 89100 Malay le Petit",
    "sg:city":"Villeroy",
    "sg:orig_category":"Unclassifiable Establishments",
    "sg:phone":"+33 3 86 88 24 61",
    "sg:postcode":"89100",
    "sg:province":"Bourgogne",
    "wof:name":"Gerbe S.a.r.l.",
    "wof:placetype":"venue"
},
  "geometry": {"coordinates":[3.390298,48.173275],"type":"Point"}
}