{
  "type": "Feature",
  "properties": {
    "addr:full":"Parc d'Activit\u00e9s du Gard Lens Nord Pas-de-Calais 62300",
    "addr:postcode":"62300",
    "addr:street":"Pas-De-Calais",
    "iso:country":"FR",
    "sg:address":"Parc d'Activit\u00e9s du Gard",
    "sg:city":"Lens",
    "sg:orig_category":"Non-Classified Establishments",
    "sg:phone":"+33 3 21 69 80 30",
    "sg:postcode":"62300",
    "sg:province":"Nord Pas-de-Calais",
    "wof:name":"C.g.s.t. Save S.a.s. - Compagnie Gazi\u00e8re Service Technique Save",
    "wof:placetype":"venue"
},
  "geometry": {"coordinates":[2.821852,50.421947],"type":"Point"}
}