{
  "type": "Feature",
  "properties": {
    "iso:country":"FR",
    "sg:address":"Chem De L'Escudie Za Plaine Nord 11100 Montredon Des Corbi\u00e8res",
    "sg:classifiers":[
        {
            "category":"Manufacturing",
            "subcategory":"Rubber & Plastics",
            "type":"Manufacturing & Wholesale Goods"
        }
    ],
    "sg:phone":"+33 4 68 41 08 00",
    "sg:province":"Languedoc-Roussillon",
    "wof:name":"Soditec",
    "wof:placetype":"venue"
},
  "geometry": {"coordinates":[2.938362,43.182644],"type":"Point"}
}