{
  "type": "Feature",
  "properties": {
    "addr:full":"176, Rue de Montmartre, 75002 Paris Ile de France",
    "addr:housenumber":"176",
    "addr:postcode":"75002",
    "addr:street":"Rue De Montmartre",
    "iso:country":"FR",
    "sg:address":"176, Rue de Montmartre, 75002 Paris",
    "sg:orig_category":"Unclassifiable Establishments",
    "sg:phone":"+33 1 55 80 43 00",
    "sg:province":"Ile de France",
    "wof:name":"Inter\u00e9pargne S.a.",
    "wof:placetype":"venue"
},
  "geometry": {"coordinates":[2.34321,48.871204],"type":"Point"}
}