{
  "type": "Feature",
  "properties": {
    "addr:full":"650 Avenue Montpellier 34970 Lattes Languedoc-Roussillon 34970",
    "addr:housenumber":"650",
    "addr:postcode":"34970;34970",
    "addr:street":"Avenue Montpellier",
    "iso:country":"FR",
    "sg:address":"650 Avenue Montpellier 34970 Lattes",
    "sg:classifiers":[
        {
            "category":"Professional",
            "subcategory":"Business Services",
            "type":"Services"
        }
    ],
    "sg:phone":"+33 4 67 99 80 00",
    "sg:postcode":"34970",
    "sg:province":"Languedoc-Roussillon",
    "sg:tags":[
        "information",
        "advice",
        "technology",
        "software"
    ],
    "wof:name":"Apogea Mediterranee Sa",
    "wof:placetype":"venue"
},
  "geometry": {"coordinates":[3.902079,43.567459],"type":"Point"}
}