{
  "type": "Feature",
  "properties": {
    "iso:country":"FR",
    "sg:address":"route de Soye 25340 SANTOCHE",
    "sg:classifiers":[
        {
            "category":"Professional",
            "subcategory":"Business Services",
            "type":"Services"
        }
    ],
    "sg:phone":"+33 3 81 90 74 00",
    "sg:postcode":"25340",
    "sg:province":"Franche Comt\u00e9",
    "sg:tags":[
        "high-precision",
        "mechanic"
    ],
    "wof:name":"Streit M\u00e9canique S.a.",
    "wof:placetype":"venue"
},
  "geometry": {"coordinates":[6.496715,47.393002],"type":"Point"}
}