{
  "type": "Feature",
  "properties": {
    "addr:full":"Ld Les Quatre Chem 19130 St Aulaire Limousin 19130",
    "addr:housenumber":"19130",
    "addr:postcode":"19130",
    "addr:street":"Ld;St Aulaire Limousin",
    "iso:country":"FR",
    "sg:address":"Ld Les Quatre Chem 19130 St Aulaire",
    "sg:classifiers":[
        {
            "category":"Farming",
            "subcategory":"Crops",
            "type":"Manufacturing & Wholesale Goods"
        }
    ],
    "sg:phone":"+33 5 55 25 29 60",
    "sg:postcode":"19130",
    "sg:province":"Limousin",
    "sg:tags":[
        "vegetable",
        "fruit",
        "agriculture",
        "livestock"
    ],
    "wof:name":"Gie Perlim",
    "wof:placetype":"venue"
},
  "geometry": {"coordinates":[1.37253,45.23074],"type":"Point"}
}