{
  "type": "Feature",
  "properties": {
    "iso:country":"FR",
    "sg:address":"8 rue Fran\u00e7ois Villon 75015 Paris",
    "sg:classifiers":[
        {
            "category":"Professional",
            "subcategory":"Advertising",
            "type":"Services"
        }
    ],
    "sg:phone":"+33 1 53 68 65 65",
    "sg:postcode":"75015",
    "sg:province":"Ile de France",
    "sg:tags":[
        "newspaper",
        "journal"
    ],
    "wof:name":"Ste Propublic Sa",
    "wof:placetype":"venue"
},
  "geometry": {"coordinates":[2.299667,48.838505],"type":"Point"}
}