{
  "type": "Feature",
  "properties": {
    "iso:country":"FR",
    "sg:address":"B.P. 19, 57303 Mondelange C\u00e9dex^^12, Rue de Boussange, 57300 Mondelange",
    "sg:orig_category":"Non-Classified Establishments",
    "sg:phone":"+33 3 87 71 48 32",
    "sg:province":"Lorraine",
    "wof:name":"Soled S.a.",
    "wof:placetype":"venue"
},
  "geometry": {"coordinates":[6.168165,49.261784],"type":"Point"}
}