{
  "type": "Feature",
  "properties": {
    "addr:full":"1 Izeure Bourgogne 21110",
    "addr:housenumber":"1",
    "addr:postcode":"21110",
    "addr:street":"Izeure Bourgogne",
    "iso:country":"FR",
    "sg:address":"1",
    "sg:city":"Izeure",
    "sg:classifiers":[
        {
            "category":"Wholesale",
            "subcategory":"Machinery & Supplies",
            "type":"Manufacturing & Wholesale Goods"
        }
    ],
    "sg:phone":"+33 3 80 29 74 01",
    "sg:postcode":"21110",
    "sg:province":"Bourgogne",
    "sg:tags":[
        "equipment",
        "precision"
    ],
    "wof:name":"Arplay Medical (sas)",
    "wof:placetype":"venue"
},
  "geometry": {"coordinates":[5.220228,47.241528],"type":"Point"}
}