{
  "type": "Feature",
  "properties": {
    "addr:full":"Avenue Gen De Gaulle Briancon Basse Normandie 05100",
    "addr:postcode":"05100",
    "addr:street":"Avenue Gen De Gaulle Briancon Basse",
    "iso:country":"FR",
    "sg:address":"Avenue Gen De Gaulle",
    "sg:city":"Briancon",
    "sg:classifiers":[
        {
            "category":"Banks & Credit Unions",
            "subcategory":"Financial Services",
            "type":"Services"
        }
    ],
    "sg:phone":"+33 4 92 25 49 00",
    "sg:postcode":"05100",
    "sg:province":"Basse Normandie",
    "sg:tags":[
        "banking",
        "finance",
        "insurance"
    ],
    "wof:name":"Credit Agricole Alpes Provence (cap) Agence De Briancon",
    "wof:placetype":"venue"
},
  "geometry": {"coordinates":[6.633317,44.889542],"type":"Point"}
}