{
  "type": "Feature",
  "properties": {
    "addr:full":"1 Rue Tony Ferret Bourg En Bresse Rhone-Alpes 01000",
    "addr:housenumber":"1",
    "addr:postcode":"01000",
    "addr:street":"Rue Tony Ferret",
    "iso:country":"FR",
    "sg:address":"1 Rue Tony Ferret",
    "sg:city":"Bourg En Bresse",
    "sg:classifiers":[
        {
            "category":"Banks & Credit Unions",
            "subcategory":"Financial Services",
            "type":"Services"
        }
    ],
    "sg:phone":"+33 4 74 50 31 80",
    "sg:postcode":"01000",
    "sg:province":"Rhone-Alpes",
    "sg:tags":[
        "banking",
        "finance",
        "insurance"
    ],
    "wof:name":"Fiduciaire De France Societe D'expertise Comptable Commissai (fidex)",
    "wof:placetype":"venue"
},
  "geometry": {"coordinates":[5.230291,46.195663],"type":"Point"}
}