{
  "type": "Feature",
  "properties": {
    "addr:full":"Chemin des Raveaux 63920 PESCHADOIRES Peschadoires Auvergne 63920",
    "addr:postcode":"63920;peschadoires;63920",
    "addr:street":"Chemin Des Raveaux",
    "iso:country":"FR",
    "sg:address":"Chemin des Raveaux 63920 PESCHADOIRES",
    "sg:city":"Peschadoires",
    "sg:classifiers":[
        {
            "category":"Professional",
            "subcategory":"Art Services",
            "type":"Services"
        }
    ],
    "sg:phone":"+33 4 73 80 35 22",
    "sg:postcode":"63920",
    "sg:province":"Auvergne",
    "sg:tags":[
        "metal",
        "drawing",
        "deep"
    ],
    "wof:name":"Forges Gorce Sas",
    "wof:placetype":"venue"
},
  "geometry": {"coordinates":[3.492746,45.827091],"type":"Point"}
}