{
  "type": "Feature",
  "properties": {
    "iso:country":"FR",
    "sg:address":"1 Bd Beaumarchais 75004 Paris",
    "sg:classifiers":[
        {
            "category":"Travel",
            "subcategory":"Hotels & Motels",
            "type":"Entertainment"
        }
    ],
    "sg:phone":"+33 1 44 61 90 40",
    "sg:postcode":"75004",
    "sg:province":"Ile de France",
    "sg:tags":[
        "hotels",
        "business",
        "restaurant"
    ],
    "wof:name":"Hippo Gestion Et Compagnie Hippopotamus Bastille",
    "wof:placetype":"venue"
},
  "geometry": {"coordinates":[2.368688,48.853893],"type":"Point"}
}