{
  "type": "Feature",
  "properties": {
    "addr:full":"4 R Gaston Montmousseau 38130 Echirolles Rhone-Alpes 38130",
    "addr:housenumber":"4",
    "addr:postcode":"38130;38130",
    "addr:street":"R Gaston Montmousseau;Rhone-Alpes",
    "iso:country":"FR",
    "sg:address":"4 R Gaston Montmousseau 38130 Echirolles",
    "sg:classifiers":[
        {
            "category":"Wholesale",
            "subcategory":"Machinery & Supplies",
            "type":"Manufacturing & Wholesale Goods"
        }
    ],
    "sg:phone":"+33 4 76 33 26 10",
    "sg:postcode":"38130",
    "sg:province":"Rhone-Alpes",
    "sg:tags":[
        "food",
        "processing",
        "-",
        "machine",
        "equipment",
        "engineering",
        "mechanical"
    ],
    "wof:name":"Dufieux Industrie Sa",
    "wof:placetype":"venue"
},
  "geometry": {"coordinates":[5.712046,45.155975],"type":"Point"}
}