{
  "type": "Feature",
  "properties": {
    "addr:full":"ROUTE DE MARIGNIER 74130 Ayse Rhone-Alpes",
    "addr:postcode":"74130",
    "addr:street":"Route De Marignier",
    "iso:country":"FR",
    "sg:address":"ROUTE DE MARIGNIER 74130 Ayse",
    "sg:classifiers":[
        {
            "category":"Building & Trades",
            "subcategory":"Construction",
            "type":"Services"
        }
    ],
    "sg:phone":"+33 4 50 97 22 92",
    "sg:province":"Rhone-Alpes",
    "sg:tags":[
        "turning",
        "vertical"
    ],
    "wof:name":"Precialp Sa",
    "wof:placetype":"venue"
},
  "geometry": {"coordinates":[6.388322,45.95652],"type":"Point"}
}