{
  "type": "Feature",
  "properties": {
    "iso:country":"FR",
    "sg:address":"24, Lotissement Le Bannet, 08200 Givonne",
    "sg:orig_category":"Unclassifiable Establishments",
    "sg:phone":"+33 3 24 29 70 40",
    "sg:province":"Champagne",
    "wof:name":"Botta Fr\u00e8res Et Fils S.a.r.l.",
    "wof:placetype":"venue"
},
  "geometry": {"coordinates":[4.988069,49.727551],"type":"Point"}
}