{
  "type": "Feature",
  "properties": {
    "iso:country":"FR",
    "sg:address":"Rte De Cambo 64100 Bayonne",
    "sg:city":"Bayonne",
    "sg:classifiers":[
        {
            "category":"Professional",
            "subcategory":"Printing & Photocopies",
            "type":"Services"
        }
    ],
    "sg:phone":"+33 5 59 58 05 05",
    "sg:postcode":"64100",
    "sg:province":"Aquitaine",
    "sg:tags":[
        "publishing"
    ],
    "wof:name":"Les Editions De La Semaine Sa",
    "wof:placetype":"venue"
},
  "geometry": {"coordinates":[-1.495834,43.466091],"type":"Point"}
}