{
  "type": "Feature",
  "properties": {
    "iso:country":"FR",
    "sg:address":"MIN Saint Augustin",
    "sg:city":"Nice",
    "sg:orig_category":"Non-Classified Establishments",
    "sg:phone":"+33 4 93 71 44 66",
    "sg:postcode":"06042",
    "sg:province":"Basse Normandie",
    "wof:name":"Frigorifique De L'union S.a.",
    "wof:placetype":"venue"
},
  "geometry": {"coordinates":[-122.8386,39.121292],"type":"Point"}
}