{
  "type": "Feature",
  "properties": {
    "addr:full":"B.P. 281, 10008 Troyes C\u00e9dex^^4, Rue Amand Poron, 10000 Troyes Champagne 10000",
    "addr:housenumber":"b.p. 281",
    "addr:postcode":"10008;10000;10000",
    "addr:street":"Rue Amand Poron",
    "iso:country":"FR",
    "sg:address":"B.P. 281, 10008 Troyes C\u00e9dex^^4, Rue Amand Poron, 10000 Troyes",
    "sg:orig_category":"Non-Classified Establishments",
    "sg:phone":"+33 3 25 70 48 88",
    "sg:postcode":"10000",
    "sg:province":"Champagne",
    "wof:name":"Cegelec Paris S.a.",
    "wof:placetype":"venue"
},
  "geometry": {"coordinates":[4.074345,48.297874],"type":"Point"}
}