{
  "type": "Feature",
  "properties": {
    "iso:country":"FR",
    "sg:address":"9, Rue Georges Picot, 69100 Villeurbanne",
    "sg:orig_category":"Non-Classified Establishments",
    "sg:phone":"+33 4 78 84 62 05",
    "sg:postcode":"69100",
    "sg:province":"Rhone-Alpes",
    "wof:name":"Outillages L.m. S.a.r.l.",
    "wof:placetype":"venue"
},
  "geometry": {"coordinates":[4.897261,45.775108],"type":"Point"}
}