{
  "type": "Feature",
  "properties": {
    "addr:full":"6, Rue du Vivier, 51160 Ay Champagne",
    "addr:housenumber":"6",
    "addr:postcode":"51160",
    "addr:street":"Rue Du Vivier",
    "iso:country":"FR",
    "sg:address":"6, Rue du Vivier, 51160 Ay",
    "sg:orig_category":"Unclassifiable Establishments",
    "sg:phone":"+33 3 26 58 77 30",
    "sg:province":"Champagne",
    "wof:name":"P.t.p.m. S.a. - Production De Textiles Et Plastiques De La Marne",
    "wof:placetype":"venue"
},
  "geometry": {"coordinates":[4.00336,49.049877],"type":"Point"}
}