{
  "type": "Feature",
  "properties": {
    "iso:country":"FR",
    "sg:address":"B.P. 274, 59405 Cambrai C\u00e9dex^^ZI Cantimpr\u00e9, 59400 Cambrai",
    "sg:orig_category":"Non-Classified Establishments",
    "sg:phone":"+33 3 27 82 96 00",
    "sg:postcode":"59400",
    "sg:province":"Nord Pas-de-Calais",
    "wof:name":"Bracq L\u00e9on Et Compagnie S.a.",
    "wof:placetype":"venue"
},
  "geometry": {"coordinates":[3.23419,50.175018],"type":"Point"}
}