{
  "type": "Feature",
  "properties": {
    "addr:full":"9 ter, Sentier de Neulimont, 93800 Epinay sur Seine Ile de France 93800",
    "addr:housenumber":"9 ter",
    "addr:postcode":"93800;93800",
    "addr:street":"Sentier De Neulimont;France",
    "iso:country":"FR",
    "sg:address":"9 ter, Sentier de Neulimont, 93800 Epinay sur Seine",
    "sg:orig_category":"Non-Classified Establishments",
    "sg:phone":"+33 1 48 41 44 22",
    "sg:postcode":"93800",
    "sg:province":"Ile de France",
    "wof:name":"Brulaire S.a.r.l.",
    "wof:placetype":"venue"
},
  "geometry": {"coordinates":[2.298384,48.964134],"type":"Point"}
}