{
  "type": "Feature",
  "properties": {
    "iso:country":"FR",
    "sg:address":"2931 Rue G\u00e9n\u00e9ral Leclerc 78380 Bougival",
    "sg:classifiers":[
        {
            "category":"Professional",
            "type":"Services"
        }
    ],
    "sg:phone":"+33 1 39 69 02 25",
    "sg:province":"Ile de France",
    "sg:tags":[
        "transport",
        "road"
    ],
    "wof:name":"Le Joncour Sarl",
    "wof:placetype":"venue"
},
  "geometry": {"coordinates":[2.140104,48.862968],"type":"Point"}
}