{
  "type": "Feature",
  "properties": {
    "addr:full":"4, Rue Denis Papin, 28500 Vernouillet Vernouillet Centre 28500",
    "addr:housenumber":"4",
    "addr:postcode":"28500;28500",
    "addr:street":"Rue Denis Papin;Vernouillet",
    "iso:country":"FR",
    "sg:address":"4, Rue Denis Papin, 28500 Vernouillet",
    "sg:city":"Vernouillet",
    "sg:orig_category":"Unclassifiable Establishments",
    "sg:phone":"+33 2 37 46 86 16",
    "sg:postcode":"28500",
    "sg:province":"Centre",
    "wof:name":"S.r.m. S.a.r.l. - Soci\u00e9t\u00e9 R\u00e9gnault M\u00e9canique",
    "wof:placetype":"venue"
},
  "geometry": {"coordinates":[1.378025,48.714069],"type":"Point"}
}