{
  "type": "Feature",
  "properties": {
    "addr:full":"18, Clos du Ch\u00e2teau, 02190 Guignicourt Picardie 02190",
    "addr:housenumber":"18",
    "addr:postcode":"02190;02190",
    "addr:street":"Clos Du Cha\u0302Teau",
    "iso:country":"FR",
    "sg:address":"18, Clos du Ch\u00e2teau, 02190 Guignicourt",
    "sg:orig_category":"Non-Classified Establishments",
    "sg:phone":"+33 3 23 79 94 42",
    "sg:postcode":"02190",
    "sg:province":"Picardie",
    "wof:name":"Aisne Montage S.a.r.l.",
    "wof:placetype":"venue"
},
  "geometry": {"coordinates":[3.959923,49.434414],"type":"Point"}
}