{
  "type": "Feature",
  "properties": {
    "addr:full":"B.P. 75, 69700 Givors C\u00e9dex^^1, Rue Edouard Prenat, 69700 Givors Rhone-Alpes 69700",
    "addr:postcode":"69700;69700;69700",
    "addr:street":"B.P. 75;Rue Edouard Prenat",
    "iso:country":"FR",
    "sg:address":"B.P. 75, 69700 Givors C\u00e9dex^^1, Rue Edouard Prenat, 69700 Givors",
    "sg:orig_category":"Non-Classified Establishments",
    "sg:phone":"+33 4 72 49 27 27",
    "sg:postcode":"69700",
    "sg:province":"Rhone-Alpes",
    "wof:name":"S.o.d.i.f. S.a. - Soci\u00e9t\u00e9 Diffusion Des Fontes",
    "wof:placetype":"venue"
},
  "geometry": {"coordinates":[4.715199,45.551682],"type":"Point"}
}