{
  "type": "Feature",
  "properties": {
    "iso:country":"FR",
    "sg:address":"Parc D'Affaires De Chapotin 69970 Chaponnay",
    "sg:classifiers":[
        {
            "category":"Manufacturing",
            "subcategory":"Metals",
            "type":"Manufacturing & Wholesale Goods"
        }
    ],
    "sg:phone":"+33 4 78 96 82 20",
    "sg:province":"Rhone-Alpes",
    "sg:tags":[
        "metallurgy",
        "steel",
        "metalworking"
    ],
    "wof:name":"Pellet A S C Sa",
    "wof:placetype":"venue"
},
  "geometry": {"coordinates":[4.92939,45.651409],"type":"Point"}
}