{
  "type": "Feature",
  "properties": {
    "addr:full":"B.P. 84, 42602 Montbrison C\u00e9dex^^Rte de Bo\u00ebn - ZI de Survaure, 42600 Montbrison Rhone-Alpes",
    "addr:postcode":"42602;42600",
    "addr:street":"B.P. 84;Zi;Survaure",
    "iso:country":"FR",
    "sg:address":"B.P. 84, 42602 Montbrison C\u00e9dex^^Rte de Bo\u00ebn - ZI de Survaure, 42600 Montbrison",
    "sg:orig_category":"Non-Classified Establishments",
    "sg:phone":"+33 4 77 58 17 18",
    "sg:province":"Rhone-Alpes",
    "wof:name":"Fairchild Produits S.n.e.p. S.a.",
    "wof:placetype":"venue"
},
  "geometry": {"coordinates":[3.996271,45.571075],"type":"Point"}
}