{
  "type": "Feature",
  "properties": {
    "iso:country":"FR",
    "sg:address":"199, Rue Championnet, 75018 Paris",
    "sg:orig_category":"Non-Classified Establishments",
    "sg:phone":"+33 1 44 85 88 88",
    "sg:province":"Ile de France",
    "wof:name":"G.f.i. Informatique S.a.",
    "wof:placetype":"venue"
},
  "geometry": {"coordinates":[2.331737,48.893829],"type":"Point"}
}