{
  "type": "Feature",
  "properties": {
    "addr:full":"20 rue Aristide Berges 31270 Cugnaux Midi Pyr\u00e9n\u00e9es 31270",
    "addr:housenumber":"20",
    "addr:postcode":"31270;31270",
    "addr:street":"Rue Aristide Berges",
    "iso:country":"FR",
    "sg:address":"20 rue Aristide Berges 31270 Cugnaux",
    "sg:orig_category":"Chemicals For Anodizing Workshops",
    "sg:phone":"+33 5 61 07 61 26",
    "sg:postcode":"31270",
    "sg:province":"Midi Pyr\u00e9n\u00e9es",
    "wof:name":"L.c. Syst\u00e8me S.a.",
    "wof:placetype":"venue"
},
  "geometry": {"coordinates":[1.368792,43.553905],"type":"Point"}
}