{
  "type": "Feature",
  "properties": {
    "iso:country":"FR",
    "sg:address":"Les Quatre Chemins",
    "sg:city":"Saint Aulaire",
    "sg:orig_category":"Unclassifiable Establishments",
    "sg:phone":"+33 5 55 25 94 00",
    "sg:postcode":"19130",
    "sg:province":"Limousin",
    "wof:name":"La Boissi\u00e8re S.a.r.l.",
    "wof:placetype":"venue"
},
  "geometry": {"coordinates":[1.39654,45.24889],"type":"Point"}
}