{
  "type": "Feature",
  "properties": {
    "iso:country":"FR",
    "sg:address":"215, Rte de Saint Omer, 62100 Calais",
    "sg:orig_category":"Unclassifiable Establishments",
    "sg:phone":"+33 3 21 34 44 10",
    "sg:province":"Nord Pas-de-Calais",
    "wof:name":"Magn\u00e9sia Socaltram S.a.",
    "wof:placetype":"venue"
},
  "geometry": {"coordinates":[1.881167,50.938805],"type":"Point"}
}