{
  "type": "Feature",
  "properties": {
    "addr:full":"Zone Artisanale 46600 MARTEL Midi Pyr\u00e9n\u00e9es 46600",
    "addr:postcode":"46600;46600",
    "addr:street":"Zone Artisanale",
    "iso:country":"FR",
    "sg:address":"Zone Artisanale 46600 MARTEL",
    "sg:classifiers":[
        {
            "category":"Professional",
            "subcategory":"Art Services",
            "type":"Services"
        }
    ],
    "sg:phone":"+33 5 65 37 38 41",
    "sg:postcode":"46600",
    "sg:province":"Midi Pyr\u00e9n\u00e9es",
    "sg:tags":[
        "varnishing",
        "design"
    ],
    "wof:name":"Solev Sa",
    "wof:placetype":"venue"
},
  "geometry": {"coordinates":[1.608561,44.937263],"type":"Point"}
}