{
  "type": "Feature",
  "properties": {
    "addr:full":"Zi De La Verrerie 54480 Cirey Sur Vezouze Lorraine 54480",
    "addr:postcode":"54480;54480",
    "addr:street":"Zi De La Verrerie;Vezouze Lorraine",
    "iso:country":"FR",
    "sg:address":"Zi De La Verrerie 54480 Cirey Sur Vezouze",
    "sg:classifiers":[
        {
            "category":"Manufacturing",
            "subcategory":"Glass & Minerals",
            "type":"Manufacturing & Wholesale Goods"
        }
    ],
    "sg:phone":"+33 3 83 42 50 03",
    "sg:postcode":"54480",
    "sg:province":"Lorraine",
    "sg:tags":[
        "building",
        "material"
    ],
    "wof:name":"L'huillier Seyer",
    "wof:placetype":"venue"
},
  "geometry": {"coordinates":[6.94305,48.583817],"type":"Point"}
}