{
  "type": "Feature",
  "properties": {
    "iso:country":"FR",
    "sg:address":"B.P. 2, 45401 Fleury les Aubrais C\u00e9dex^^4, Rue Andr\u00e9 Dessaux, 45400 Fleury les Aubrais",
    "sg:city":"Chanteau",
    "sg:orig_category":"Non-Classified Establishments",
    "sg:phone":"+33 2 38 72 38 72",
    "sg:postcode":"45400",
    "sg:province":"Centre",
    "wof:name":"S.o.d.i.m. S.a. - Soci\u00e9t\u00e9 De Diffusion D'appareils De Mesure",
    "wof:placetype":"venue"
},
  "geometry": {"coordinates":[1.920976,47.931038],"type":"Point"}
}