{
  "type": "Feature",
  "properties": {
    "iso:country":"FR",
    "sg:address":"Rte de Paris - RN 17",
    "sg:city":"La Chapelle en Serval",
    "sg:orig_category":"Unclassifiable Establishments",
    "sg:phone":"+33 3 44 54 95 95",
    "sg:postcode":"60520",
    "sg:province":"Picardie",
    "wof:name":"Roto Press Graphic S.a.",
    "wof:placetype":"venue"
},
  "geometry": {"coordinates":[2.5338,49.129875],"type":"Point"}
}