{
  "type": "Feature",
  "properties": {
    "iso:country":"FR",
    "sg:address":"Rue Julien Fayolle 43100 Brioude",
    "sg:city":"Brioude",
    "sg:classifiers":[
        {
            "category":"Shopping",
            "subcategory":"Clothing, Apparel, & Fashions",
            "type":"Retail Goods"
        }
    ],
    "sg:phone":"+33 4 71 50 08 41",
    "sg:postcode":"43100",
    "sg:province":"Auvergne",
    "sg:tags":[
        "textile",
        "clothing",
        "clothes"
    ],
    "wof:name":"Desi Mode Sas",
    "wof:placetype":"venue"
},
  "geometry": {"coordinates":[3.371429,45.313366],"type":"Point"}
}