{
  "type": "Feature",
  "properties": {
    "iso:country":"FR",
    "sg:address":"Usine de Roanne",
    "sg:city":"Saint Priest la Roche",
    "sg:orig_category":"Non-Classified Establishments",
    "sg:phone":"+33 4 77 64 91 58",
    "sg:postcode":"42590",
    "sg:province":"Rhone-Alpes",
    "wof:name":"Inv\u00e9ko France S.a.",
    "wof:placetype":"venue"
},
  "geometry": {"coordinates":[4.136859,45.873623],"type":"Point"}
}