{
  "type": "Feature",
  "properties": {
    "iso:country":"FR",
    "sg:address":"Lanine 64520 CAME",
    "sg:city":"Came",
    "sg:classifiers":[
        {
            "category":"Government",
            "subcategory":"Post Office",
            "type":"Public Place"
        }
    ],
    "sg:phone":"+33 5 59 56 02 65",
    "sg:postcode":"64520",
    "sg:province":"Aquitaine",
    "sg:tags":[
        "armchair",
        "chair",
        "period"
    ],
    "wof:name":"Jean Gestas S.a.",
    "wof:placetype":"venue"
},
  "geometry": {"coordinates":[-1.096813,43.490391],"type":"Point"}
}