{
  "type": "Feature",
  "properties": {
    "addr:full":"Lanine 64520 CAME Came Aquitaine 64520",
    "addr:postcode":"64520;64520",
    "addr:street":"Lanine",
    "iso:country":"FR",
    "sg:address":"Lanine 64520 CAME",
    "sg:city":"Came",
    "sg:classifiers":[
        {
            "category":"Government",
            "subcategory":"Post Office",
            "type":"Public Place"
        }
    ],
    "sg:phone":"+33 5 59 56 02 65",
    "sg:postcode":"64520",
    "sg:province":"Aquitaine",
    "sg:tags":[
        "armchair",
        "chair",
        "period"
    ],
    "wof:name":"Jean Gestas S.a.",
    "wof:placetype":"venue"
},
  "geometry": {"coordinates":[-1.096813,43.490391],"type":"Point"}
}