{
  "type": "Feature",
  "properties": {
    "iso:country":"FR",
    "sg:address":"23 Bd Sof\u00e9rino 35012 Rennes Cedex",
    "sg:classifiers":[
        {
            "category":"Banks & Credit Unions",
            "subcategory":"Financial Services",
            "type":"Services"
        }
    ],
    "sg:phone":"+33 2 99 29 57 57",
    "sg:province":"Nord Pas-de-Calais",
    "sg:tags":[
        "banking",
        "finance",
        "insurance"
    ],
    "wof:name":"Groupama Bretagne",
    "wof:placetype":"venue"
},
  "geometry": {"coordinates":[-1.668537,48.104549],"type":"Point"}
}