{
  "type": "Feature",
  "properties": {
    "iso:country":"FR",
    "sg:address":"1 bis, Villa Guizot, 75017 Paris",
    "sg:orig_category":"Non-Classified Establishments",
    "sg:phone":"+33 1 40 55 59 00",
    "sg:province":"Ile de France",
    "wof:name":"Mant\u00e9ro France S.a.r.l.",
    "wof:placetype":"venue"
},
  "geometry": {"coordinates":[2.29143,48.876934],"type":"Point"}
}