{
  "type": "Feature",
  "properties": {
    "iso:country":"FR",
    "sg:address":"14 Rue Waldeck Rousseau 59410 Anzin",
    "sg:classifiers":[
        {
            "category":"Manufacturing",
            "subcategory":"Metals",
            "type":"Manufacturing & Wholesale Goods"
        }
    ],
    "sg:phone":"+33 3 27 46 90 84",
    "sg:postcode":"59410",
    "sg:province":"Nord Pas-de-Calais",
    "sg:tags":[
        "metallurgy",
        "steel",
        "metalworking"
    ],
    "wof:name":"Etablissements Gorin",
    "wof:placetype":"venue"
},
  "geometry": {"coordinates":[3.50758,50.373234],"type":"Point"}
}