{
  "type": "Feature",
  "properties": {
    "addr:full":"Rue Mireille - Domaine de Corne-Loup Tavel Languedoc-Roussillon 30126",
    "addr:postcode":"30126",
    "addr:street":"Rue Mireille Domaine",
    "iso:country":"FR",
    "sg:address":"Rue Mireille - Domaine de Corne-Loup",
    "sg:city":"Tavel",
    "sg:orig_category":"Non-Classified Establishments",
    "sg:phone":"+33 4 66 50 34 37",
    "sg:postcode":"30126",
    "sg:province":"Languedoc-Roussillon",
    "wof:name":"Lafond Jacques",
    "wof:placetype":"venue"
},
  "geometry": {"coordinates":[4.698181,44.05442],"type":"Point"}
}