{
  "type": "Feature",
  "properties": {
    "iso:country":"FR",
    "sg:address":"2 R Henri Poincar\u00e9 93270 Sevran",
    "sg:classifiers":[
        {
            "category":"Shopping",
            "type":"Retail Goods"
        }
    ],
    "sg:phone":"+33 1 49 36 58 00",
    "sg:postcode":"93270",
    "sg:province":"Ile de France",
    "sg:tags":[
        "metallurgy",
        "finished",
        "-",
        "metalworking",
        "metallic"
    ],
    "wof:name":"Comptoir General Du Ressort Sa",
    "wof:placetype":"venue"
},
  "geometry": {"coordinates":[2.528747,48.94762],"type":"Point"}
}