{
  "type": "Feature",
  "properties": {
    "addr:full":"61 Rue Notre-Dame Des Champs 75006 Paris Ile de France 75006",
    "addr:housenumber":"61",
    "addr:postcode":"75006;75006",
    "addr:street":"Rue Notre-Dame Des Champs",
    "iso:country":"FR",
    "sg:address":"61 Rue Notre-Dame Des Champs 75006 Paris",
    "sg:classifiers":[
        {
            "category":"Professional",
            "subcategory":"Business Services",
            "type":"Services"
        }
    ],
    "sg:phone":"+33 1 44 32 06 70",
    "sg:postcode":"75006",
    "sg:province":"Ile de France",
    "sg:tags":[
        "training",
        "advice"
    ],
    "wof:name":"Ogec Notre Dame De Sion",
    "wof:placetype":"venue"
},
  "geometry": {"coordinates":[2.331108,48.843792],"type":"Point"}
}