{
  "type": "Feature",
  "properties": {
    "addr:full":"447, Rue de l'Indiennerie, 69400 Gleiz\u00e9 Rhone-Alpes 69400",
    "addr:housenumber":"447",
    "addr:postcode":"69400;69400",
    "addr:street":"Rue De L'Indiennerie",
    "iso:country":"FR",
    "sg:address":"447, Rue de l'Indiennerie, 69400 Gleiz\u00e9",
    "sg:orig_category":"Unclassifiable Establishments",
    "sg:phone":"+33 4 74 65 51 82",
    "sg:postcode":"69400",
    "sg:province":"Rhone-Alpes",
    "wof:name":"Rummler Auguste",
    "wof:placetype":"venue"
},
  "geometry": {"coordinates":[4.717579,45.991653],"type":"Point"}
}