{
  "type": "Feature",
  "properties": {
    "addr:full":"88 Rue De Provence 75008 Paris Ile de France 75008",
    "addr:housenumber":"88",
    "addr:postcode":"75008;75008",
    "addr:street":"Rue De Provence",
    "iso:country":"FR",
    "sg:address":"88 Rue De Provence 75008 Paris",
    "sg:classifiers":[
        {
            "category":"Shopping",
            "subcategory":"Clothing, Apparel, & Fashions",
            "type":"Retail Goods"
        }
    ],
    "sg:phone":"+33 1 42 80 30 93",
    "sg:postcode":"75008",
    "sg:province":"Ile de France",
    "sg:tags":[
        "textile",
        "clothing",
        "clothes"
    ],
    "wof:name":"Amd",
    "wof:placetype":"venue"
},
  "geometry": {"coordinates":[2.32695,48.874161],"type":"Point"}
}