{
  "type": "Feature",
  "properties": {
    "addr:full":"4, Rue Larrey, 49008 Angers C\u00e9dex 01 Centre",
    "addr:housenumber":"4;01",
    "addr:postcode":"49008",
    "addr:street":"Rue Larrey;Ce\u0301Dex;Centre",
    "iso:country":"FR",
    "sg:address":"4, Rue Larrey, 49008 Angers C\u00e9dex 01",
    "sg:orig_category":"Non-Classified Establishments",
    "sg:phone":"+33 2 41 35 41 47",
    "sg:province":"Centre",
    "wof:name":"Biovaleur S.a.",
    "wof:placetype":"venue"
},
  "geometry": {"coordinates":[-0.554782,47.480717],"type":"Point"}
}