{
  "type": "Feature",
  "properties": {
    "addr:full":"129, Rue Universit\u00e9, 75007 Paris Ile de France",
    "addr:housenumber":"129",
    "addr:postcode":"75007",
    "addr:street":"Rue Universite\u0301",
    "iso:country":"FR",
    "sg:address":"129, Rue Universit\u00e9, 75007 Paris",
    "sg:orig_category":"Non-Classified Establishments",
    "sg:phone":"+33 1 44 42 92 92",
    "sg:province":"Ile de France",
    "wof:name":"Satel Conseil G.i.e.",
    "wof:placetype":"venue"
},
  "geometry": {"coordinates":[2.308364,48.86108],"type":"Point"}
}