{
  "type": "Feature",
  "properties": {
    "iso:country":"FR",
    "sg:address":"22, Rue Marc S\u00e9guin - ZA La Savine, 07500 Guilherand Granges",
    "sg:orig_category":"Unclassifiable Establishments",
    "sg:phone":"+33 4 75 44 54 96",
    "sg:province":"Rhone-Alpes",
    "wof:name":"Impressions Modernes S.a.r.l.",
    "wof:placetype":"venue"
},
  "geometry": {"coordinates":[4.86969,44.93232],"type":"Point"}
}