{
  "type": "Feature",
  "properties": {
    "iso:country":"FR",
    "sg:address":"Le Jasmin 73240 St Genix Sur Guiers",
    "sg:classifiers":[
        {
            "category":"Shopping",
            "subcategory":"Crafts & Fabrics",
            "type":"Retail Goods"
        }
    ],
    "sg:phone":"+33 4 76 31 78 66",
    "sg:postcode":"73240",
    "sg:province":"Rhone-Alpes",
    "sg:tags":[
        "textile",
        "clothing"
    ],
    "wof:name":"Carret Tissage Sarl",
    "wof:placetype":"venue"
},
  "geometry": {"coordinates":[5.642171,45.589268],"type":"Point"}
}