{
  "type": "Feature",
  "properties": {
    "addr:full":"Rte Pointe du Hoc. Acign\u00e9 Bretagne 35690",
    "addr:postcode":"35690",
    "addr:street":"Rte Pointe Du Hoc. Acigne\u0301 Bretagne",
    "iso:country":"FR",
    "sg:address":"Rte Pointe du Hoc.",
    "sg:city":"Acign\u00e9",
    "sg:orig_category":"Unclassifiable Establishments",
    "sg:phone":"+33 2 99 62 58 79",
    "sg:postcode":"35690",
    "sg:province":"Bretagne",
    "wof:name":"Shessemans Valrep S.a.r.l.",
    "wof:placetype":"venue"
},
  "geometry": {"coordinates":[-1.534322,48.132721],"type":"Point"}
}