{
  "type": "Feature",
  "properties": {
    "iso:country":"FR",
    "sg:address":"Les Grandes Terres 26300 Barbi\u00e8res",
    "sg:classifiers":[
        {
            "category":"Professional",
            "subcategory":"Engineering",
            "type":"Services"
        }
    ],
    "sg:phone":"+33 4 75 47 41 34",
    "sg:postcode":"26300",
    "sg:province":"Rhone-Alpes",
    "sg:tags":[
        "machine",
        "-",
        "mechanical"
    ],
    "wof:name":"Sarl Multimeca",
    "wof:placetype":"venue"
},
  "geometry": {"coordinates":[5.13489,44.957893],"type":"Point"}
}