{
  "type": "Feature",
  "properties": {
    "iso:country":"FR",
    "sg:address":"Rte de la Guerche",
    "sg:city":"Vitr\u00e9",
    "sg:orig_category":"Unclassifiable Establishments",
    "sg:phone":"+33 2 99 74 55 94",
    "sg:postcode":"35500",
    "sg:province":"Bretagne",
    "wof:name":"A.c.f. S.a.r.l. - Ateliers De Clairfontaine",
    "wof:placetype":"venue"
},
  "geometry": {"coordinates":[-1.206069,48.096245],"type":"Point"}
}