{
  "type": "Feature",
  "properties": {
    "iso:country":"FR",
    "sg:address":"54, Grand'Rue, 57620 Lemberg",
    "sg:orig_category":"Unclassifiable Establishments",
    "sg:phone":"+33 3 87 06 48 20",
    "sg:province":"Lorraine",
    "wof:name":"Profilm\u00e9tal S.a.",
    "wof:placetype":"venue"
},
  "geometry": {"coordinates":[7.381371,48.977097],"type":"Point"}
}