{
  "type": "Feature",
  "properties": {
    "addr:full":"15 Rue De Spezet 56110 Gourin Gourin Bretagne 56110",
    "addr:housenumber":"15",
    "addr:postcode":"56110;56110",
    "addr:street":"Rue De Spezet;Gourin",
    "iso:country":"FR",
    "sg:address":"15 Rue De Spezet 56110 Gourin",
    "sg:city":"Gourin",
    "sg:classifiers":[
        {
            "category":"Professional",
            "subcategory":"Engineering",
            "type":"Services"
        }
    ],
    "sg:phone":"+33 2 97 23 42 02",
    "sg:postcode":"56110",
    "sg:province":"Bretagne",
    "sg:tags":[
        "machine",
        "-",
        "mechanical"
    ],
    "wof:name":"Renault Agriculture",
    "wof:placetype":"venue"
},
  "geometry": {"coordinates":[-3.616494,48.143654],"type":"Point"}
}