{
  "type": "Feature",
  "properties": {
    "addr:full":"B.P. 104 Malemort sur Corr\u00e8ze C\u00e9dex^^19360 Malemort sur Corr\u00e8ze Limousin 19360",
    "addr:housenumber":"b.p. 104",
    "addr:postcode":"19360",
    "iso:country":"FR",
    "sg:address":"B.P. 104",
    "sg:city":"Malemort sur Corr\u00e8ze C\u00e9dex^^19360 Malemort sur Corr\u00e8ze",
    "sg:orig_category":"Non-Classified Establishments",
    "sg:phone":"+33 5 55 92 17 13",
    "sg:postcode":"19360",
    "sg:province":"Limousin",
    "wof:name":"B.d.i. S.a.s. - B\u00e9daricienne Doras Industries",
    "wof:placetype":"venue"
},
  "geometry": {"coordinates":[1.585306,45.135616],"type":"Point"}
}