{
  "type": "Feature",
  "properties": {
    "addr:full":"route de Moulins 18004 Bourges Centre",
    "addr:postcode":"18004",
    "addr:street":"Route De Moulins",
    "iso:country":"FR",
    "sg:address":"route de Moulins 18004 Bourges",
    "sg:classifiers":[
        {
            "category":"Wholesale",
            "subcategory":"Chemicals & Plastics",
            "type":"Manufacturing & Wholesale Goods"
        }
    ],
    "sg:phone":"+33 2 48 20 15 38",
    "sg:province":"Centre",
    "sg:tags":[
        "industrial",
        "engineering",
        "parts",
        "vehicle",
        "injection",
        "moulded"
    ],
    "wof:name":"Standard Gum S.a.",
    "wof:placetype":"venue"
},
  "geometry": {"coordinates":[5.186265,45.901192],"type":"Point"}
}