{
  "type": "Feature",
  "properties": {
    "iso:country":"FR",
    "sg:address":"400, Rue Joseph L\u00e9on Jacquemare, 69400 Villefranche sur Sa\u00f4ne",
    "sg:orig_category":"Unclassifiable Establishments",
    "sg:phone":"+33 4 74 62 17 19",
    "sg:province":"Rhone-Alpes",
    "wof:name":"Lafont Chavent International S.a.",
    "wof:placetype":"venue"
},
  "geometry": {"coordinates":[4.743487,45.992931],"type":"Point"}
}