{
  "type": "Feature",
  "properties": {
    "iso:country":"FR",
    "sg:address":"1 rue Pont; Landerneau; 29800",
    "sg:city":"Landerneau",
    "sg:classifiers":[
        {
            "category":"Banks & Credit Unions",
            "subcategory":"Bank",
            "type":"Services"
        }
    ],
    "sg:phone":"+33 2 98 85 27 11",
    "sg:postcode":"29800",
    "sg:province":"Bretagne",
    "wof:name":"Cr\u00e9dit Lyonnais",
    "wof:placetype":"venue"
},
  "geometry": {"coordinates":[-4.249606,48.4505],"type":"Point"}
}