{
  "type": "Feature",
  "properties": {
    "addr:full":"B.P. 81, 62453 Bapaume C\u00e9dex^^9, Rue de Douai - R\u00e9sidence Les Remparts, 62450 Bapaume Nord Pas-de-Calais 62450",
    "addr:postcode":"62453;62450;62450",
    "addr:street":"B.P. 81;Rue De Douai Re\u0301Sidence Les Remparts",
    "iso:country":"FR",
    "sg:address":"B.P. 81, 62453 Bapaume C\u00e9dex^^9, Rue de Douai - R\u00e9sidence Les Remparts, 62450 Bapaume",
    "sg:orig_category":"Non-Classified Establishments",
    "sg:phone":"+33 3 21 51 97 30",
    "sg:postcode":"62450",
    "sg:province":"Nord Pas-de-Calais",
    "wof:name":"A.n.p.e.",
    "wof:placetype":"venue"
},
  "geometry": {"coordinates":[2.84946,50.10318],"type":"Point"}
}