{
  "type": "Feature",
  "properties": {
    "addr:full":"2, Rue Sainte Anne, 28400 Nogent le Rotrou Brunelles Centre 28400",
    "addr:housenumber":"2",
    "addr:postcode":"28400;28400",
    "addr:street":"Rue Sainte Anne",
    "iso:country":"FR",
    "sg:address":"2, Rue Sainte Anne, 28400 Nogent le Rotrou",
    "sg:city":"Brunelles",
    "sg:orig_category":"Unclassifiable Establishments",
    "sg:phone":"+33 2 37 52 27 66",
    "sg:postcode":"28400",
    "sg:province":"Centre",
    "wof:name":"M\u00e9thacryl S.a",
    "wof:placetype":"venue"
},
  "geometry": {"coordinates":[0.812249,48.324856],"type":"Point"}
}