{
  "type": "Feature",
  "properties": {
    "addr:full":"B.P. 230, 59563 La Madeleine C\u00e9dex^^2, Rue Lamartine, 59110 La Madeleine Nord Pas-de-Calais",
    "addr:housenumber":"b.p. 230",
    "addr:postcode":"59563;59110",
    "addr:street":"Rue Lamartine",
    "iso:country":"FR",
    "sg:address":"B.P. 230, 59563 La Madeleine C\u00e9dex^^2, Rue Lamartine, 59110 La Madeleine",
    "sg:orig_category":"Non-Classified Establishments",
    "sg:phone":"+33 3 20 55 33 06",
    "sg:province":"Nord Pas-de-Calais",
    "wof:name":"Sateb Travaux D'electricit\u00e9 S.a.",
    "wof:placetype":"venue"
},
  "geometry": {"coordinates":[3.073605,50.654518],"type":"Point"}
}