{
  "type": "Feature",
  "properties": {
    "addr:full":"Av. Pierre Troubat Montlu\u00e7on Auvergne 03100",
    "addr:postcode":"03100",
    "addr:street":"Av. Pierre Troubat",
    "iso:country":"FR",
    "sg:address":"Av. Pierre Troubat",
    "sg:city":"Montlu\u00e7on",
    "sg:orig_category":"Unclassifiable Establishments",
    "sg:phone":"+33 4 70 28 58 70",
    "sg:postcode":"03100",
    "sg:province":"Auvergne",
    "wof:name":"Isograd Entreprises S.a.s.",
    "wof:placetype":"venue"
},
  "geometry": {"coordinates":[2.61787,46.343281],"type":"Point"}
}