{
  "type": "Feature",
  "properties": {
    "addr:full":"Zi Sud 41100 Vend\u00f4me Vend\u00f4me Centre 41100",
    "addr:postcode":"41100;41100",
    "iso:country":"FR",
    "sg:address":"Zi Sud 41100 Vend\u00f4me",
    "sg:city":"Vend\u00f4me",
    "sg:classifiers":[
        {
            "category":"Manufacturing",
            "subcategory":"Metals",
            "type":"Manufacturing & Wholesale Goods"
        }
    ],
    "sg:phone":"+33 2 54 23 12 00",
    "sg:postcode":"41100",
    "sg:province":"Centre",
    "sg:tags":[
        "metallurgy",
        "metalworking",
        "processing"
    ],
    "wof:name":"Sofedit Vendome",
    "wof:placetype":"venue"
},
  "geometry": {"coordinates":[1.064763,47.792313],"type":"Point"}
}