{
  "type": "Feature",
  "properties": {
    "iso:country":"FR",
    "sg:address":"48, Av. du G\u00e9n\u00e9ral de Gaulle - Immeuble Wilson, 92800 Puteaux",
    "sg:orig_category":"Unclassifiable Establishments",
    "sg:phone":"+33 1 41 35 57 00",
    "sg:province":"Ile de France",
    "wof:name":"Totalgaz S.n.c.",
    "wof:placetype":"venue"
},
  "geometry": {"coordinates":[2.233915,48.888275],"type":"Point"}
}