{
  "type": "Feature",
  "properties": {
    "addr:full":"Z I Les Clottes 31360 ST MARTORY Midi Pyr\u00e9n\u00e9es 31360",
    "addr:postcode":"31360;31360",
    "addr:street":"Z I Les Clottes",
    "iso:country":"FR",
    "sg:address":"Z I Les Clottes 31360 ST MARTORY",
    "sg:classifiers":[
        {
            "category":"Structure",
            "subcategory":"Building",
            "type":"Public Place"
        }
    ],
    "sg:phone":"+33 5 61 97 11 11",
    "sg:postcode":"31360",
    "sg:province":"Midi Pyr\u00e9n\u00e9es",
    "sg:tags":[
        "delivery",
        "door",
        "inside",
        "installation"
    ],
    "wof:name":"Isodoc Sa",
    "wof:placetype":"venue"
},
  "geometry": {"coordinates":[0.866359,43.108395],"type":"Point"}
}