{
  "type": "Feature",
  "properties": {
    "addr:full":"1, Rue des Entrep\u00f4ts, 67116 Reichstett Reichstett Alsace 67116",
    "addr:housenumber":"1",
    "addr:postcode":"67116;67116",
    "addr:street":"Rue Des Entrepo\u0302Ts",
    "iso:country":"FR",
    "sg:address":"1, Rue des Entrep\u00f4ts, 67116 Reichstett",
    "sg:city":"Reichstett",
    "sg:orig_category":"Unclassifiable Establishments",
    "sg:phone":"+33 3 88 19 43 73",
    "sg:postcode":"67116",
    "sg:province":"Alsace",
    "wof:name":"Isolations Palusci S.a.",
    "wof:placetype":"venue"
},
  "geometry": {"coordinates":[7.784745,48.641224],"type":"Point"}
}