{
  "type": "Feature",
  "properties": {
    "iso:country":"FR",
    "sg:address":"16 bis, Bd Lamarck, 18000 Bourges",
    "sg:city":"Bourges",
    "sg:orig_category":"Non-Classified Establishments",
    "sg:phone":"+33 2 48 27 16 32",
    "sg:postcode":"18000",
    "sg:province":"Centre",
    "wof:name":"Enjeux Formation",
    "wof:placetype":"venue"
},
  "geometry": {"coordinates":[2.394337,47.079124],"type":"Point"}
}