{
  "type": "Feature",
  "properties": {
    "iso:country":"FR",
    "sg:address":"183 Rue Des Allies 42100 St Etienne",
    "sg:classifiers":[
        {
            "category":"Utilities",
            "subcategory":"Electric",
            "type":"Services"
        }
    ],
    "sg:phone":"+33 4 77 25 66 11",
    "sg:postcode":"42100",
    "sg:province":"Rhone-Alpes",
    "sg:tags":[
        "electricity",
        "electronic",
        "electrical",
        "equipment"
    ],
    "wof:name":"Goe Generale Operations Electriques",
    "wof:placetype":"venue"
},
  "geometry": {"coordinates":[4.421108,45.43914],"type":"Point"}
}