{
  "type": "Feature",
  "properties": {
    "addr:full":"Rue Alfred Kastler - Zone Saint Jacques 2 Max\u00e9ville Lorraine 54320",
    "addr:housenumber":"2",
    "addr:postcode":"54320",
    "addr:street":"Rue Alfred Kastler;Saint Jacques;Lorraine",
    "iso:country":"FR",
    "sg:address":"Rue Alfred Kastler - Zone Saint Jacques 2",
    "sg:city":"Max\u00e9ville",
    "sg:orig_category":"Unclassifiable Establishments",
    "sg:phone":"+33 3 83 93 28 28",
    "sg:postcode":"54320",
    "sg:province":"Lorraine",
    "wof:name":"Critel S.a.",
    "wof:placetype":"venue"
},
  "geometry": {"coordinates":[6.130915,48.704048],"type":"Point"}
}