{
  "type": "Feature",
  "properties": {
    "addr:full":"12, Rue Bleue, 75009 Paris Ile de France 75009",
    "addr:housenumber":"12",
    "addr:postcode":"75009;75009",
    "addr:street":"Rue Bleue",
    "iso:country":"FR",
    "sg:address":"12, Rue Bleue, 75009 Paris",
    "sg:orig_category":"Non-Classified Establishments",
    "sg:phone":"+33 1 48 24 47 44",
    "sg:postcode":"75009",
    "sg:province":"Ile de France",
    "wof:name":"Compofa\u00e7on S.a.r.l.",
    "wof:placetype":"venue"
},
  "geometry": {"coordinates":[2.346561,48.876003],"type":"Point"}
}