{
  "type": "Feature",
  "properties": {
    "addr:full":"69 Rue De Phalsbourg 57820 Lutzelbourg Lorraine 57820",
    "addr:housenumber":"69",
    "addr:postcode":"57820;57820",
    "addr:street":"Rue De Phalsbourg",
    "iso:country":"FR",
    "sg:address":"69 Rue De Phalsbourg 57820 Lutzelbourg",
    "sg:classifiers":[
        {
            "category":"Farming",
            "subcategory":"Farm & Veterinary Services",
            "type":"Manufacturing & Wholesale Goods"
        }
    ],
    "sg:phone":"+33 3 87 25 37 16",
    "sg:postcode":"57820",
    "sg:province":"Lorraine",
    "sg:tags":[
        "advice",
        "agriculture",
        "livestock",
        "business"
    ],
    "wof:name":"Etablissement Linck",
    "wof:placetype":"venue"
},
  "geometry": {"coordinates":[7.25145,48.736515],"type":"Point"}
}