{
  "type": "Feature",
  "properties": {
    "addr:full":"Rte de Sainte Alv\u00e8re - Creysse Creysse Aquitaine 24100",
    "addr:postcode":"24100",
    "addr:street":"Rte De Sainte Alve\u0300Re",
    "iso:country":"FR",
    "sg:address":"Rte de Sainte Alv\u00e8re - Creysse",
    "sg:city":"Creysse",
    "sg:orig_category":"Non-Classified Establishments",
    "sg:phone":"+33 5 33 23 25 80",
    "sg:postcode":"24100",
    "sg:province":"Aquitaine",
    "wof:name":"V\u00e9ronique S.a.r.l.",
    "wof:placetype":"venue"
},
  "geometry": {"coordinates":[0.45362,44.815235],"type":"Point"}
}