{
  "type": "Feature",
  "properties": {
    "addr:full":"31, Av. du G\u00e9n\u00e9ral Leclerc, 93500 Pantin Ile de France 93500",
    "addr:postcode":"93500;ile;93500",
    "addr:street":"31 Av. Du Ge\u0301Ne\u0301Ral Leclerc;France",
    "iso:country":"FR",
    "sg:address":"31, Av. du G\u00e9n\u00e9ral Leclerc, 93500 Pantin",
    "sg:orig_category":"Non-Classified Establishments",
    "sg:phone":"+33 1 48 91 01 02",
    "sg:postcode":"93500",
    "sg:province":"Ile de France",
    "wof:name":"C.d.v.i. S.a. - Construction Diffusion Vente International",
    "wof:placetype":"venue"
},
  "geometry": {"coordinates":[2.400013,48.895416],"type":"Point"}
}