{
  "type": "Feature",
  "properties": {
    "iso:country":"FR",
    "sg:address":"79 Rte De B\u00e9thune 62223 Ste Catherine",
    "sg:classifiers":[
        {
            "category":"Wholesale",
            "subcategory":"Farm Supplies",
            "type":"Manufacturing & Wholesale Goods"
        }
    ],
    "sg:phone":"+33 3 21 71 12 02",
    "sg:postcode":"62223",
    "sg:province":"Nord Pas-de-Calais",
    "sg:tags":[
        "-",
        "machine",
        "equipment",
        "engineering",
        "machinery",
        "mechanical",
        "agriculture"
    ],
    "wof:name":"Artois Motoculture Sa",
    "wof:placetype":"venue"
},
  "geometry": {"coordinates":[2.762008,50.312523],"type":"Point"}
}