{
  "type": "Feature",
  "properties": {
    "iso:country":"FR",
    "sg:address":"Av. Kennedy - ZI Saint C\u00e9saire",
    "sg:city":"N\u00eemes",
    "sg:orig_category":"Non-Classified Establishments",
    "sg:phone":"+33 4 66 64 73 37",
    "sg:postcode":"30900",
    "sg:province":"Languedoc-Roussillon",
    "wof:name":"S.e.c.a. S.a.r.l.",
    "wof:placetype":"venue"
},
  "geometry": {"coordinates":[4.356115,43.830025],"type":"Point"}
}