{
  "type": "Feature",
  "properties": {
    "iso:country":"FR",
    "sg:address":"Rte De Lourde 65270 St P\u00e9-De-Bigorre",
    "sg:classifiers":[
        {
            "category":"Professional",
            "type":"Services"
        }
    ],
    "sg:phone":"+33 5 62 41 81 46",
    "sg:province":"Midi Pyr\u00e9n\u00e9es",
    "sg:tags":[
        "transport",
        "road"
    ],
    "wof:name":"Ste Exploitation Tansports Barracou",
    "wof:placetype":"venue"
},
  "geometry": {"coordinates":[-0.160399,43.103664],"type":"Point"}
}