{
  "type": "Feature",
  "properties": {
    "iso:country":"FR",
    "sg:address":"10, Rue de la Porte, 68140 Munster",
    "sg:city":"Munster",
    "sg:orig_category":"Unclassifiable Establishments",
    "sg:phone":"+33 3 89 77 30 48",
    "sg:postcode":"68140",
    "sg:province":"Alsace",
    "wof:name":"Gehringer S.a.",
    "wof:placetype":"venue"
},
  "geometry": {"coordinates":[7.139811,48.038845],"type":"Point"}
}