{
  "type": "Feature",
  "properties": {
    "addr:full":"10, Rue de la Porte, 68140 Munster Munster Alsace 68140",
    "addr:housenumber":"10",
    "addr:postcode":"68140;68140",
    "addr:street":"Rue De La Porte;Munster",
    "iso:country":"FR",
    "sg:address":"10, Rue de la Porte, 68140 Munster",
    "sg:city":"Munster",
    "sg:orig_category":"Unclassifiable Establishments",
    "sg:phone":"+33 3 89 77 30 48",
    "sg:postcode":"68140",
    "sg:province":"Alsace",
    "wof:name":"Gehringer S.a.",
    "wof:placetype":"venue"
},
  "geometry": {"coordinates":[7.139811,48.038845],"type":"Point"}
}