{
  "type": "Feature",
  "properties": {
    "iso:country":"FR",
    "sg:address":"4 R Dunoir 69003 Lyon",
    "sg:classifiers":[
        {
            "category":"Shopping",
            "subcategory":"Luggage & Leather Goods",
            "type":"Retail Goods"
        }
    ],
    "sg:phone":"+33 4 78 60 13 59",
    "sg:postcode":"69003",
    "sg:province":"Rhone-Alpes",
    "sg:tags":[
        "shoe"
    ],
    "wof:name":"M. Breton Didier",
    "wof:placetype":"venue"
},
  "geometry": {"coordinates":[4.84978,45.760479],"type":"Point"}
}