{
  "type": "Feature",
  "properties": {
    "iso:country":"FR",
    "sg:address":"7 Sq Max Symans 75730 Paris Cedex 15",
    "sg:classifiers":[
        {
            "category":"Shopping",
            "subcategory":"Hobbies, Toys, & Games",
            "type":"Retail Goods"
        }
    ],
    "sg:phone":"+33 1 40 47 70 00",
    "sg:province":"Ile de France",
    "sg:tags":[
        "product",
        "miscellaneous",
        "entertainment"
    ],
    "wof:name":"L'autorite De Regulation Des Telecommunications A Paris",
    "wof:placetype":"venue"
},
  "geometry": {"coordinates":[2.29386,48.841679],"type":"Point"}
}