{
  "type": "Feature",
  "properties": {
    "addr:full":"Place Du Docteur Auvray Barneville Carteret Basse Normandie 50270",
    "addr:postcode":"50270",
    "addr:street":"Place Du Docteur Auvray",
    "iso:country":"FR",
    "sg:address":"Place Du Docteur Auvray",
    "sg:city":"Barneville Carteret",
    "sg:classifiers":[
        {
            "category":"Banks & Credit Unions",
            "subcategory":"Financial Services",
            "type":"Services"
        }
    ],
    "sg:phone":"+33 2 33 87 56 80",
    "sg:postcode":"50270",
    "sg:province":"Basse Normandie",
    "sg:tags":[
        "banking",
        "finance",
        "insurance"
    ],
    "wof:name":"Caisse Regional De Credit Agricole Mutuel Normandagence De Credit Agricolemutue L",
    "wof:placetype":"venue"
},
  "geometry": {"coordinates":[-1.752749,49.381626],"type":"Point"}
}