{
  "type": "Feature",
  "properties": {
    "addr:full":"2 rue Lavoisier 77400 Lagny sur Marne Ile de France 77400",
    "addr:housenumber":"2",
    "addr:postcode":"77400;77400",
    "addr:street":"Rue Lavoisier",
    "iso:country":"FR",
    "sg:address":"2 rue Lavoisier 77400 Lagny sur Marne",
    "sg:classifiers":[
        {
            "category":"Utilities",
            "subcategory":"Natural Gas",
            "type":"Services"
        }
    ],
    "sg:phone":"+33 1 64 12 46 05",
    "sg:postcode":"77400",
    "sg:province":"Ile de France",
    "sg:tags":[
        "liquefied"
    ],
    "wof:name":"Equip'fluides Sa",
    "wof:placetype":"venue"
},
  "geometry": {"coordinates":[2.680047,48.872883],"type":"Point"}
}