{
  "type": "Feature",
  "properties": {
    "addr:full":"5 Rue De L Avenir 14650 Carpiquet Carpiquet Basse Normandie 14650",
    "addr:housenumber":"5",
    "addr:postcode":"14650;14650",
    "addr:street":"Rue De L Avenir",
    "iso:country":"FR",
    "sg:address":"5 Rue De L Avenir 14650 Carpiquet",
    "sg:city":"Carpiquet",
    "sg:classifiers":[
        {
            "category":"Manufacturing",
            "subcategory":"Paper Products",
            "type":"Manufacturing & Wholesale Goods"
        }
    ],
    "sg:phone":"+33 2 31 71 11 11",
    "sg:postcode":"14650",
    "sg:province":"Basse Normandie",
    "sg:tags":[
        "finished",
        "cardboard",
        "-"
    ],
    "wof:name":"Coregraphic Jp Le Brun Impressions",
    "wof:placetype":"venue"
},
  "geometry": {"coordinates":[-0.43978,49.190559],"type":"Point"}
}