{
  "type": "Feature",
  "properties": {
    "iso:country":"FR",
    "sg:address":"1, Rue de Terre Neuve - Courtaboeuf , 91940 Les Ulis",
    "sg:orig_category":"Non-Classified Establishments",
    "sg:phone":"+33 1 69 07 52 41",
    "sg:province":"Ile de France",
    "wof:name":"Maine Plastiques S.a.",
    "wof:placetype":"venue"
},
  "geometry": {"coordinates":[2.169475,48.68161],"type":"Point"}
}