{
  "type": "Feature",
  "properties": {
    "addr:full":"pl de l'Eglise; Guiclan; 29410 Guiclan Bretagne 29410",
    "addr:postcode":"29410 guiclan;29410",
    "addr:street":"Pl De L'Eglise",
    "iso:country":"FR",
    "sg:address":"pl de l'Eglise; Guiclan; 29410",
    "sg:city":"Guiclan",
    "sg:classifiers":[
        {
            "category":"Banks & Credit Unions",
            "subcategory":"Bank",
            "type":"Services"
        }
    ],
    "sg:phone":"+33 2 98 79 42 57",
    "sg:postcode":"29410",
    "sg:province":"Bretagne",
    "wof:name":"Cr\u00e9dit Agricole Mutuel (c.a.m)",
    "wof:placetype":"venue"
},
  "geometry": {"coordinates":[-3.96233,48.550999],"type":"Point"}
}