{
  "type": "Feature",
  "properties": {
    "addr:full":"B.P. 17, 39502 Tavaux C\u00e9dex^^2, rue du Luxembourg, 39500 Tavaux Franche Comt\u00e9",
    "addr:postcode":"39502;39500",
    "addr:street":"B.P. 17;Rue Du Luxembourg;Franche Comte\u0301",
    "iso:country":"FR",
    "sg:address":"B.P. 17, 39502 Tavaux C\u00e9dex^^2, rue du Luxembourg, 39500 Tavaux",
    "sg:orig_category":"Non-Classified Establishments",
    "sg:phone":"+33 3 84 79 47 50",
    "sg:province":"Franche Comt\u00e9",
    "wof:name":"S.d.e.l. Bourgogne Franche Comt\u00e9 S.a.s - Saunier Duval Electricit\u00e9",
    "wof:placetype":"venue"
},
  "geometry": {"coordinates":[5.405445,47.034031],"type":"Point"}
}