{
  "type": "Feature",
  "properties": {
    "iso:country":"FR",
    "sg:address":"2, All\u00e9e des Tisserands - ZA des 4 Arbres, 78990 Elancourt",
    "sg:orig_category":"Unclassifiable Establishments",
    "sg:phone":"+33 1 30 50 49 98",
    "sg:province":"Ile de France",
    "wof:name":"Sodimatel S.a.",
    "wof:placetype":"venue"
},
  "geometry": {"coordinates":[1.949475,48.768543],"type":"Point"}
}