{
  "type": "Feature",
  "properties": {
    "iso:country":"FR",
    "sg:address":"5 R Charles Fran\u00e7ois Daubigny 95870 Bezons",
    "sg:classifiers":[
        {
            "category":"Manufacturing",
            "subcategory":"Food",
            "type":"Manufacturing & Wholesale Goods"
        }
    ],
    "sg:phone":"+33 1 30 76 83 83",
    "sg:province":"Ile de France",
    "sg:tags":[
        "packaging",
        "industry"
    ],
    "wof:name":"Omni Pac Sarl",
    "wof:placetype":"venue"
},
  "geometry": {"coordinates":[2.20385,48.914539],"type":"Point"}
}