{
  "type": "Feature",
  "properties": {
    "iso:country":"FR",
    "sg:address":"3, Rue Jean errin, 31100 Toulouse",
    "sg:orig_category":"Non-Classified Establishments",
    "sg:phone":"+33 5 34 50 26 26",
    "sg:province":"Midi Pyr\u00e9n\u00e9es",
    "wof:name":"Fayard Sud Machines Outils S.a.",
    "wof:placetype":"venue"
},
  "geometry": {"coordinates":[1.416251,43.552734],"type":"Point"}
}