{
  "type": "Feature",
  "properties": {
    "addr:full":"68 Rue Lille BP 99 59710 Avelin Nord Pas-de-Calais",
    "addr:housenumber":"68;99",
    "addr:postcode":"59710",
    "addr:street":"Rue Lille Bp",
    "iso:country":"FR",
    "sg:address":"68 Rue Lille BP 99 59710 Avelin",
    "sg:classifiers":[
        {
            "category":"Manufacturing",
            "subcategory":"Paper Products",
            "type":"Manufacturing & Wholesale Goods"
        }
    ],
    "sg:phone":"+33 3 20 62 01 22",
    "sg:province":"Nord Pas-de-Calais",
    "sg:tags":[
        "finished",
        "cardboard",
        "-"
    ],
    "wof:name":"Reynders",
    "wof:placetype":"venue"
},
  "geometry": {"coordinates":[3.08495,50.542309],"type":"Point"}
}