{
  "type": "Feature",
  "properties": {
    "iso:country":"FR",
    "sg:address":"58 R St Paul 29430 Plouescat",
    "sg:city":"Plouescat",
    "sg:classifiers":[
        {
            "category":"Professional",
            "type":"Services"
        }
    ],
    "sg:phone":"+33 2 98 69 89 40",
    "sg:postcode":"29430",
    "sg:province":"Bretagne",
    "sg:tags":[
        "transport",
        "road"
    ],
    "wof:name":"Herry Transports Sarl",
    "wof:placetype":"venue"
},
  "geometry": {"coordinates":[-4.166131,48.658249],"type":"Point"}
}