{
  "type": "Feature",
  "properties": {
    "addr:full":"B.P. 49, 17442 Aytr\u00e9 C\u00e9dex^^ZI Bel Aire, 17440 Aytr\u00e9 Poitou-Charentes",
    "addr:postcode":"17442;17440",
    "addr:street":"B.P. 49",
    "iso:country":"FR",
    "sg:address":"B.P. 49, 17442 Aytr\u00e9 C\u00e9dex^^ZI Bel Aire, 17440 Aytr\u00e9",
    "sg:orig_category":"Non-Classified Establishments",
    "sg:phone":"+33 5 46 45 22 11",
    "sg:province":"Poitou-Charentes",
    "wof:name":"Masters S.a.",
    "wof:placetype":"venue"
},
  "geometry": {"coordinates":[-1.113492,46.133381],"type":"Point"}
}