{
  "type": "Feature",
  "properties": {
    "addr:full":"Zi Laboulb\u00e8ne 47300 Villeneuve Sur Lot Villeneuve-sur-Lot Aquitaine 47300",
    "addr:postcode":"47300;47300",
    "addr:street":"Lot",
    "iso:country":"FR",
    "sg:address":"Zi Laboulb\u00e8ne 47300 Villeneuve Sur Lot",
    "sg:city":"Villeneuve-sur-Lot",
    "sg:classifiers":[
        {
            "category":"Professional",
            "subcategory":"Engineering",
            "type":"Services"
        }
    ],
    "sg:phone":"+33 5 53 70 93 72",
    "sg:postcode":"47300",
    "sg:province":"Aquitaine",
    "sg:tags":[
        "ma",
        "business",
        "advice",
        "-",
        "environment",
        "equipment",
        "machinery",
        "mechanical"
    ],
    "wof:name":"Soulard Et Fils (ets)",
    "wof:placetype":"venue"
},
  "geometry": {"coordinates":[0.70472,44.402969],"type":"Point"}
}