{
  "type": "Feature",
  "properties": {
    "iso:country":"FR",
    "sg:address":"2, Rue des Tennerolles, 92210 Saint Cloud",
    "sg:orig_category":"Unclassifiable Establishments",
    "sg:phone":"+33 1 46 02 00 33",
    "sg:province":"Ile de France",
    "wof:name":"Epsign S.a.",
    "wof:placetype":"venue"
},
  "geometry": {"coordinates":[2.213137,48.845661],"type":"Point"}
}