{
  "type": "Feature",
  "properties": {
    "iso:country":"FR",
    "sg:address":"B.P. 2047, 53020 Laval C\u00e9dex 9^^15, Rue Docteurs Calmette et Gu\u00e9rin, 53000 Laval",
    "sg:orig_category":"Non-Classified Establishments",
    "sg:phone":"+33 2 43 49 22 22",
    "sg:postcode":"53000",
    "sg:province":"Pays de Loire",
    "wof:name":"A.s.e.p.t. S.a.r.l. - Association Sur L'aseptie De La Production",
    "wof:placetype":"venue"
},
  "geometry": {"coordinates":[-0.756451,48.036293],"type":"Point"}
}