{
  "type": "Feature",
  "properties": {
    "addr:full":"B.P. 475, 34505 B\u00e9ziers C\u00e9dex^^Rue Ir\u00e8ne et Fr\u00e9d\u00e9ric Joliot Curie - ZI, 34500 B\u00e9ziers Languedoc-Roussillon",
    "addr:housenumber":"b.p. 475",
    "addr:postcode":"34505;34500",
    "addr:street":"Ire\u0300Ne Et Fre\u0301De\u0301Ric Joliot Curie Zi",
    "iso:country":"FR",
    "sg:address":"B.P. 475, 34505 B\u00e9ziers C\u00e9dex^^Rue Ir\u00e8ne et Fr\u00e9d\u00e9ric Joliot Curie - ZI, 34500 B\u00e9ziers",
    "sg:orig_category":"Non-Classified Establishments",
    "sg:phone":"+33 4 67 76 62 53",
    "sg:province":"Languedoc-Roussillon",
    "wof:name":"S.e.m. S.a.",
    "wof:placetype":"venue"
},
  "geometry": {"coordinates":[3.216105,43.344234],"type":"Point"}
}