{
  "type": "Feature",
  "properties": {
    "iso:country":"FR",
    "sg:address":"B.P. 273, 64702 Hendaye C\u00e9dex^^Rue de l'Industrie - ZI Les Joncaux, 64700 Hendaye",
    "sg:city":"Hendaye",
    "sg:orig_category":"Non-Classified Establishments",
    "sg:phone":"+33 5 59 20 18 56",
    "sg:postcode":"64700",
    "sg:province":"Aquitaine",
    "wof:name":"Traim\u00e9ca S.a.",
    "wof:placetype":"venue"
},
  "geometry": {"coordinates":[-1.770666,43.343575],"type":"Point"}
}