{
  "type": "Feature",
  "properties": {
    "addr:full":"15, Rue de la C\u00e9si\u00e8re, 74000 Annecy Rhone-Alpes",
    "addr:housenumber":"15",
    "addr:postcode":"74000",
    "addr:street":"Rue De La Ce\u0301Sie\u0300Re",
    "iso:country":"FR",
    "sg:address":"15, Rue de la C\u00e9si\u00e8re, 74000 Annecy",
    "sg:orig_category":"Unclassifiable Establishments",
    "sg:phone":"+33 4 50 10 05 50",
    "sg:province":"Rhone-Alpes",
    "wof:name":"Transports Alloin S.a.",
    "wof:placetype":"venue"
},
  "geometry": {"coordinates":[6.115529,45.881866],"type":"Point"}
}