{
  "type": "Feature",
  "properties": {
    "iso:country":"FR",
    "sg:address":"1 Rue Des Nonnetiers 57000 Metz",
    "sg:classifiers":[
        {
            "category":"Utilities",
            "type":"Services"
        }
    ],
    "sg:phone":"+33 3 87 74 26 69",
    "sg:postcode":"57000",
    "sg:province":"Lorraine",
    "sg:tags":[
        "raw",
        "energy",
        "material"
    ],
    "wof:name":"Dalkia (steb)",
    "wof:placetype":"venue"
},
  "geometry": {"coordinates":[6.236149,49.11694],"type":"Point"}
}