{
  "type": "Feature",
  "properties": {
    "addr:full":"Rue Principale Tr\u00e9zennes Lambres Nord Pas-de-Calais 62922",
    "addr:postcode":"62922",
    "addr:street":"Rue Principale Tre\u0301Zennes Lambres Nord",
    "iso:country":"FR",
    "sg:address":"Rue Principale Tr\u00e9zennes",
    "sg:city":"Lambres",
    "sg:orig_category":"Unclassifiable Establishments",
    "sg:phone":"+33 3 21 39 20 60",
    "sg:postcode":"62922",
    "sg:province":"Nord Pas-de-Calais",
    "wof:name":"Vaillant Et Fils Cartonnages S.a.",
    "wof:placetype":"venue"
},
  "geometry": {"coordinates":[2.42098,50.62635],"type":"Point"}
}