{
  "type": "Feature",
  "properties": {
    "addr:full":"90 Av De R\u00e9publique 91230 Montgeron Ile de France 91230",
    "addr:postcode":"91230;ile;91230",
    "addr:street":"90 Av De Re\u0301Publique;France",
    "iso:country":"FR",
    "sg:address":"90 Av De R\u00e9publique 91230 Montgeron",
    "sg:classifiers":[
        {
            "category":"Home & Garden",
            "subcategory":"Furniture",
            "type":"Retail Goods"
        }
    ],
    "sg:phone":"+33 1 69 03 53 02",
    "sg:postcode":"91230",
    "sg:province":"Ile de France",
    "sg:tags":[
        "household",
        "wood"
    ],
    "wof:name":"Etablissements Lescure Sa",
    "wof:placetype":"venue"
},
  "geometry": {"coordinates":[2.458111,48.705421],"type":"Point"}
}