{
  "type": "Feature",
  "properties": {
    "addr:full":"77 rue Henri Brisson 78500 Sartrouville Ile de France 78500",
    "addr:housenumber":"77",
    "addr:postcode":"78500;ile;78500",
    "addr:street":"Rue Henri Brisson;France",
    "iso:country":"FR",
    "sg:address":"77 rue Henri Brisson 78500 Sartrouville",
    "sg:classifiers":[
        {
            "category":"Manufacturing",
            "subcategory":"Tools & Machinery",
            "type":"Manufacturing & Wholesale Goods"
        }
    ],
    "sg:phone":"+33 1 30 86 55 55",
    "sg:postcode":"78500",
    "sg:province":"Ile de France",
    "sg:tags":[
        "device",
        "handling"
    ],
    "wof:name":"Sapem S.a.",
    "wof:placetype":"venue"
},
  "geometry": {"coordinates":[2.173875,48.934708],"type":"Point"}
}