{
  "type": "Feature",
  "properties": {
    "addr:full":"65, Rue de Cambrai, 59200 Tourcoing Nord Pas-de-Calais",
    "addr:housenumber":"65",
    "addr:postcode":"59200",
    "addr:street":"Rue De Cambrai",
    "iso:country":"FR",
    "sg:address":"65, Rue de Cambrai, 59200 Tourcoing",
    "sg:orig_category":"Non-Classified Establishments",
    "sg:phone":"+33 3 20 28 07 70",
    "sg:province":"Nord Pas-de-Calais",
    "wof:name":"S.g.t. S.a. - Soci\u00e9t\u00e9 G\u00e9n\u00e9rale De Travaux",
    "wof:placetype":"venue"
},
  "geometry": {"coordinates":[3.167338,50.726768],"type":"Point"}
}