{
  "type": "Feature",
  "properties": {
    "addr:full":"ZAC Savign\u00e9 Poitou-Charentes 86400",
    "addr:postcode":"86400",
    "addr:street":"Zac Savigne\u0301",
    "iso:country":"FR",
    "sg:address":"ZAC",
    "sg:city":"Savign\u00e9",
    "sg:orig_category":"Unclassifiable Establishments",
    "sg:phone":"+33 5 49 87 10 95",
    "sg:postcode":"86400",
    "sg:province":"Poitou-Charentes",
    "wof:name":"Bourloton S.a.",
    "wof:placetype":"venue"
},
  "geometry": {"coordinates":[0.27894,46.085754],"type":"Point"}
}