{
  "type": "Feature",
  "properties": {
    "addr:full":"B.P. 468, 69659 Villefranche sur S\u00e2one^^1220, Av. de l'Europe, 69400 Villefranche sur S\u00e2one Rhone-Alpes",
    "addr:housenumber":"b.p. 468",
    "addr:postcode":"69659;69400",
    "addr:street":"Av. De L'Europe",
    "iso:country":"FR",
    "sg:address":"B.P. 468, 69659 Villefranche sur S\u00e2one^^1220, Av. de l'Europe, 69400 Villefranche sur S\u00e2one",
    "sg:orig_category":"Non-Classified Establishments",
    "sg:phone":"+33 4 74 65 81 60",
    "sg:province":"Rhone-Alpes",
    "wof:name":"P\u00e9dia S.a.",
    "wof:placetype":"venue"
},
  "geometry": {"coordinates":[4.717711,45.991783],"type":"Point"}
}