{
  "type": "Feature",
  "properties": {
    "addr:full":"Lariant 50220 PRECEY Pr\u00e9cey Basse Normandie 50220",
    "addr:postcode":"50220;50220",
    "addr:street":"Lariant",
    "iso:country":"FR",
    "sg:address":"Lariant 50220 PRECEY",
    "sg:city":"Pr\u00e9cey",
    "sg:classifiers":[
        {
            "category":"Bus Stop",
            "subcategory":"None",
            "type":"Transportation"
        }
    ],
    "sg:phone":"+33 2 33 89 24 24",
    "sg:postcode":"50220",
    "sg:province":"Basse Normandie",
    "sg:tags":[
        "period",
        "furniture"
    ],
    "wof:name":"Omp Sas",
    "wof:placetype":"venue"
},
  "geometry": {"coordinates":[-1.384203,48.585514],"type":"Point"}
}