{
  "type": "Feature",
  "properties": {
    "iso:country":"FR",
    "sg:address":"37 C Cours Du Parc",
    "sg:city":"Dijon",
    "sg:classifiers":[
        {
            "category":"Banks & Credit Unions",
            "subcategory":"Financial Services",
            "type":"Services"
        }
    ],
    "sg:phone":"+33 3 80 65 45 23",
    "sg:postcode":"21000",
    "sg:province":"Bourgogne",
    "sg:tags":[
        "banking",
        "finance",
        "insurance"
    ],
    "wof:name":"Expertise Comptable Et Audit Sa",
    "wof:placetype":"venue"
},
  "geometry": {"coordinates":[5.04831,47.30407],"type":"Point"}
}