{
  "type": "Feature",
  "properties": {
    "addr:full":"7 Rue Kerelie Foyer Kerelie 29200 Brest Brest Bretagne 29200",
    "addr:housenumber":"7",
    "addr:postcode":"29200;29200",
    "addr:street":"Rue Kerelie",
    "iso:country":"FR",
    "sg:address":"7 Rue Kerelie Foyer Kerelie 29200 Brest",
    "sg:city":"Brest",
    "sg:classifiers":[
        {
            "category":"Shopping",
            "subcategory":"Computers & Home Electronics",
            "type":"Retail Goods"
        }
    ],
    "sg:phone":"+33 2 98 47 90 57",
    "sg:postcode":"29200",
    "sg:province":"Bretagne",
    "sg:tags":[
        "equipment",
        "electrical",
        "component",
        "electric",
        "electronic"
    ],
    "wof:name":"Sa Deti",
    "wof:placetype":"venue"
},
  "geometry": {"coordinates":[-4.486228,48.39024],"type":"Point"}
}