{
  "type": "Feature",
  "properties": {
    "addr:full":"Av Du 10 Ao\u00fbt Plateau Superieur 12300 Decazeville Midi Pyr\u00e9n\u00e9es 12300",
    "addr:postcode":"12300;12300",
    "addr:street":"Av Du 10 Aou\u0302T Plateau Superieur",
    "iso:country":"FR",
    "sg:address":"Av Du 10 Ao\u00fbt Plateau Superieur 12300 Decazeville",
    "sg:classifiers":[
        {
            "category":"Education",
            "subcategory":"Special Training",
            "type":"Public Place"
        }
    ],
    "sg:phone":"+33 5 65 43 10 66",
    "sg:postcode":"12300",
    "sg:province":"Midi Pyr\u00e9n\u00e9es",
    "sg:tags":[
        "pharmaceutical",
        "livestock",
        "animal",
        "chemical",
        "grain",
        "cereal",
        "breeding",
        "chem",
        "agriculture"
    ],
    "wof:name":"Ragt",
    "wof:placetype":"venue"
},
  "geometry": {"coordinates":[2.255207,44.558464],"type":"Point"}
}