{
  "type": "Feature",
  "properties": {
    "iso:country":"FR",
    "sg:address":"B.P. 59, 29403 Landivisiau C\u00e9dex^^31, Rue Charles le Goffic, 29400 Landivisiau",
    "sg:city":"Landivisiau",
    "sg:orig_category":"Non-Classified Establishments",
    "sg:phone":"+33 2 98 24 50 50",
    "sg:postcode":"29400",
    "sg:province":"Bretagne",
    "wof:name":"Entrep\u00f4t Easydis S.a.",
    "wof:placetype":"venue"
},
  "geometry": {"coordinates":[-4.004424,48.445419],"type":"Point"}
}