{
  "type": "Feature",
  "properties": {
    "iso:country":"FR",
    "sg:address":"Rue Du Pechier 42390 Villars",
    "sg:classifiers":[
        {
            "category":"Utilities",
            "type":"Services"
        }
    ],
    "sg:phone":"+33 810 44 54 45",
    "sg:province":"Rhone-Alpes",
    "sg:tags":[
        "raw",
        "energy",
        "material"
    ],
    "wof:name":"Lyonnaise Des Eaux France",
    "wof:placetype":"venue"
},
  "geometry": {"coordinates":[4.356755,45.476246],"type":"Point"}
}