{
  "type": "Feature",
  "properties": {
    "iso:country":"FR",
    "sg:address":"9, Bd Monge, 69330 Meyzieu",
    "sg:orig_category":"Unclassifiable Establishments",
    "sg:phone":"+33 4 37 44 30 00",
    "sg:province":"Rhone-Alpes",
    "wof:name":"S.p.a.c. S.a.",
    "wof:placetype":"venue"
},
  "geometry": {"coordinates":[5.023393,45.767109],"type":"Point"}
}