{
  "type": "Feature",
  "properties": {
    "addr:full":"9, Grande Rue, 78810 Feucherolles Ile de France",
    "addr:housenumber":"9",
    "addr:postcode":"78810;ile",
    "addr:street":"Grande Rue",
    "iso:country":"FR",
    "sg:address":"9, Grande Rue, 78810 Feucherolles",
    "sg:orig_category":"Unclassifiable Establishments",
    "sg:phone":"+33 1 30 79 91 00",
    "sg:province":"Ile de France",
    "wof:name":"Mill\u00e9naire 3 S.a.r.l.",
    "wof:placetype":"venue"
},
  "geometry": {"coordinates":[1.972219,48.872196],"type":"Point"}
}