{
  "type": "Feature",
  "properties": {
    "iso:country":"FR",
    "sg:address":"1780 route de Sappey 74300 Araches",
    "sg:orig_category":"Caps Headwear",
    "sg:phone":"+33 4 50 90 09 83",
    "sg:postcode":"74300",
    "sg:province":"Rhone-Alpes",
    "wof:name":"Chaud Devant Sarl",
    "wof:placetype":"venue"
},
  "geometry": {"coordinates":[6.632898,46.044212],"type":"Point"}
}