{
  "type": "Feature",
  "properties": {
    "addr:full":"136 rue de G\u00e9n\u00e9ral; Metz; 57050 Lorraine 57050",
    "addr:housenumber":"136",
    "addr:postcode":"57050;57050",
    "addr:street":"Rue De Ge\u0301Ne\u0301Ral Metz",
    "iso:country":"FR",
    "sg:address":"136 rue de G\u00e9n\u00e9ral; Metz; 57050",
    "sg:classifiers":[
        {
            "category":"Banks & Credit Unions",
            "subcategory":"Bank",
            "type":"Services"
        }
    ],
    "sg:phone":"+33 3 87 30 27 73",
    "sg:postcode":"57050",
    "sg:province":"Lorraine",
    "wof:name":"Cr\u00e9dit Industriel D'alsace, Et De Lorraine Sa",
    "wof:placetype":"venue"
},
  "geometry": {"coordinates":[6.1251,49.130074],"type":"Point"}
}