{
  "type": "Feature",
  "properties": {
    "addr:full":"208 bis, Rue la Fayette, 75010 Paris Ile de France",
    "addr:housenumber":"208 bis",
    "addr:postcode":"75010",
    "addr:street":"Rue La Fayette",
    "iso:country":"FR",
    "sg:address":"208 bis, Rue la Fayette, 75010 Paris",
    "sg:orig_category":"Unclassifiable Establishments",
    "sg:phone":"+33 1 44 89 90 89",
    "sg:province":"Ile de France",
    "wof:name":"Pro Scan 2000 S.a.",
    "wof:placetype":"venue"
},
  "geometry": {"coordinates":[2.365849,48.881577],"type":"Point"}
}