{
  "type": "Feature",
  "properties": {
    "addr:full":"ZA Bel Air Aucaleuc Bretagne 22100",
    "addr:postcode":"22100",
    "addr:street":"Za Bel;Bretagne",
    "iso:country":"FR",
    "sg:address":"ZA Bel Air",
    "sg:city":"Aucaleuc",
    "sg:orig_category":"Non-Classified Establishments",
    "sg:phone":"+33 2 96 39 45 64",
    "sg:postcode":"22100",
    "sg:province":"Bretagne",
    "wof:name":"Soci\u00e9t\u00e9 Lem\u00e9e S.a.",
    "wof:placetype":"venue"
},
  "geometry": {"coordinates":[-2.126184,48.456387],"type":"Point"}
}