{
  "type": "Feature",
  "properties": {
    "addr:full":"24 Rue Blaise Pascal 79000 Niort Poitou-Charentes 79000",
    "addr:housenumber":"24",
    "addr:postcode":"79000;79000",
    "addr:street":"Rue Blaise Pascal",
    "iso:country":"FR",
    "sg:address":"24 Rue Blaise Pascal 79000 Niort",
    "sg:classifiers":[
        {
            "category":"Shopping",
            "subcategory":"Bicycles & Sporting Goods",
            "type":"Retail Goods"
        }
    ],
    "sg:phone":"+33 5 49 09 04 50",
    "sg:postcode":"79000",
    "sg:province":"Poitou-Charentes",
    "sg:tags":[
        "product",
        "sport",
        "miscellaneous"
    ],
    "wof:name":"Dangil Sa",
    "wof:placetype":"venue"
},
  "geometry": {"coordinates":[-0.491706,46.313328],"type":"Point"}
}