{
  "type": "Feature",
  "properties": {
    "iso:country":"FR",
    "sg:address":"Av. d'Helmstedt",
    "sg:city":"Vitr\u00e9",
    "sg:orig_category":"Non-Classified Establishments",
    "sg:phone":"+33 2 99 74 42 66",
    "sg:postcode":"35500",
    "sg:province":"Bretagne",
    "wof:name":"Oberthur Card Systems S.a.",
    "wof:placetype":"venue"
},
  "geometry": {"coordinates":[-1.189443,48.116344],"type":"Point"}
}