{
  "type": "Feature",
  "properties": {
    "addr:full":"78 route de Branne; Cadillac; 33410 Cadillac Aquitaine 33410",
    "addr:housenumber":"78",
    "addr:postcode":"33410;33410",
    "addr:street":"Route De Branne",
    "iso:country":"FR",
    "sg:address":"78 route de Branne; Cadillac; 33410",
    "sg:city":"Cadillac",
    "sg:classifiers":[
        {
            "category":"Banks & Credit Unions",
            "subcategory":"Bank",
            "type":"Services"
        }
    ],
    "sg:phone":"+33 3356626548",
    "sg:postcode":"33410",
    "sg:province":"Aquitaine",
    "wof:name":"Cr\u00e9dit Agricole De La Gironde",
    "wof:placetype":"venue"
},
  "geometry": {"coordinates":[-0.317214,44.637028],"type":"Point"}
}