{
  "type": "Feature",
  "properties": {
    "addr:full":"Quartier Jeup 64190 Audaux Audaux Aquitaine 64190",
    "addr:postcode":"64190;64190",
    "iso:country":"FR",
    "sg:address":"Quartier Jeup 64190 Audaux",
    "sg:city":"Audaux",
    "sg:classifiers":[
        {
            "category":"Home & Garden",
            "subcategory":"Furniture",
            "type":"Retail Goods"
        }
    ],
    "sg:phone":"+33 5 59 66 55 41",
    "sg:postcode":"64190",
    "sg:province":"Aquitaine",
    "sg:tags":[
        "household",
        "wood"
    ],
    "wof:name":"Lacampagne Claude",
    "wof:placetype":"venue"
},
  "geometry": {"coordinates":[-0.711089,43.264034],"type":"Point"}
}