{
  "type": "Feature",
  "properties": {
    "addr:full":"B.P. 32, 74334 Poisy C\u00e9dex^^800, Rte d'Annecy, 74330 Poisy Rhone-Alpes 74330",
    "addr:postcode":"74334;74330;74330",
    "addr:street":"B.P. 32;Rte D'Annecy;Rhone-Alpes",
    "iso:country":"FR",
    "sg:address":"B.P. 32, 74334 Poisy C\u00e9dex^^800, Rte d'Annecy, 74330 Poisy",
    "sg:orig_category":"Non-Classified Establishments",
    "sg:phone":"+33 4 50 46 12 20",
    "sg:postcode":"74330",
    "sg:province":"Rhone-Alpes",
    "wof:name":"Fournier S.a.",
    "wof:placetype":"venue"
},
  "geometry": {"coordinates":[6.12883,45.898781],"type":"Point"}
}