{
  "type": "Feature",
  "properties": {
    "addr:full":"1 Cit\u00e9 De Paradis 75010 Paris Ile de France 75010",
    "addr:housenumber":"1",
    "addr:postcode":"75010;75010",
    "addr:street":"Cite\u0301 De Paradis",
    "iso:country":"FR",
    "sg:address":"1 Cit\u00e9 De Paradis 75010 Paris",
    "sg:classifiers":[
        {
            "category":"Shopping",
            "subcategory":"Clothing, Apparel, & Fashions",
            "type":"Retail Goods"
        }
    ],
    "sg:phone":"+33 1 47 70 88 27",
    "sg:postcode":"75010",
    "sg:province":"Ile de France",
    "sg:tags":[
        "textile",
        "clothing",
        "clothes"
    ],
    "wof:name":"Manufacture De Peausserie De Luxe Sa",
    "wof:placetype":"venue"
},
  "geometry": {"coordinates":[2.350077,48.875214],"type":"Point"}
}