{
  "type": "Feature",
  "properties": {
    "iso:country":"FR",
    "sg:address":"60, Rue Greneta, 75002 Paris",
    "sg:orig_category":"Non-Classified Establishments",
    "sg:phone":"+33 4 47 68 51 15",
    "sg:province":"Ile de France",
    "wof:name":"Team International S.a.r.l.",
    "wof:placetype":"venue"
},
  "geometry": {"coordinates":[2.347588,48.865715],"type":"Point"}
}