{
  "type": "Feature",
  "properties": {
    "iso:country":"FR",
    "sg:address":"4, Av. V\u00e9lasquez, 75008 Paris",
    "sg:orig_category":"Unclassifiable Establishments",
    "sg:phone":"+33 1 53 76 85 70",
    "sg:province":"Ile de France",
    "wof:name":"D.a.m. S.a. - Denain Anzin Min\u00e9raux",
    "wof:placetype":"venue"
},
  "geometry": {"coordinates":[2.31267,48.880035],"type":"Point"}
}