{
  "type": "Feature",
  "properties": {
    "addr:full":"Rte de Haguenau Soufflenheim Alsace 67620",
    "addr:postcode":"67620",
    "addr:street":"Rte De Haguenau",
    "iso:country":"FR",
    "sg:address":"Rte de Haguenau",
    "sg:city":"Soufflenheim",
    "sg:orig_category":"Unclassifiable Establishments",
    "sg:phone":"+33 3 88 86 62 09",
    "sg:postcode":"67620",
    "sg:province":"Alsace",
    "wof:name":"Friedrich S.a.r.l. - Sabli\u00e8res De Quartz",
    "wof:placetype":"venue"
},
  "geometry": {"coordinates":[7.952811,48.830742],"type":"Point"}
}