{
  "type": "Feature",
  "properties": {
    "iso:country":"FR",
    "sg:address":"529, Rue du March\u00e9 Rollay, 94506 Champigny sur Marne C\u00e9dex",
    "sg:orig_category":"Non-Classified Establishments",
    "sg:phone":"+33 1 45 16 16 20",
    "sg:province":"Midi Pyr\u00e9n\u00e9es",
    "wof:name":"Creaset S.a.",
    "wof:placetype":"venue"
},
  "geometry": {"coordinates":[2.528504,48.813648],"type":"Point"}
}