{
  "type": "Feature",
  "properties": {
    "addr:full":"Place du Terreau Manosque Aquitaine 04100",
    "addr:postcode":"04100",
    "addr:street":"Place Du Terreau",
    "iso:country":"FR",
    "sg:address":"Place du Terreau",
    "sg:city":"Manosque",
    "sg:orig_category":"Non-Classified Establishments",
    "sg:phone":"+33 4 92 72 00 44",
    "sg:postcode":"04100",
    "sg:province":"Aquitaine",
    "wof:name":"Imprimerie Mollet S.a.r.l.",
    "wof:placetype":"venue"
},
  "geometry": {"coordinates":[5.78225,43.832947],"type":"Point"}
}