{
  "type": "Feature",
  "properties": {
    "iso:country":"FR",
    "sg:address":"18, Rue Paul Bert - ZA, 89400 Charmoy",
    "sg:city":"Charmoy",
    "sg:orig_category":"Unclassifiable Establishments",
    "sg:phone":"+33 3 86 80 49 00",
    "sg:postcode":"89400",
    "sg:province":"Bourgogne",
    "wof:name":"Carnaby S.a.r.l.",
    "wof:placetype":"venue"
},
  "geometry": {"coordinates":[3.51162,47.963699],"type":"Point"}
}