{
  "type": "Feature",
  "properties": {
    "addr:full":"quartier Les Chassis 26600 La Roche de Glun Rhone-Alpes 26600",
    "addr:postcode":"26600;26600",
    "addr:street":"Quartier Les Chassis",
    "iso:country":"FR",
    "sg:address":"quartier Les Chassis 26600 La Roche de Glun",
    "sg:orig_category":"Identifications For Processing Plants",
    "sg:phone":"+33 4 75 84 64 78",
    "sg:postcode":"26600",
    "sg:province":"Rhone-Alpes",
    "wof:name":"Atlantic Zeiser Vision S.a.",
    "wof:placetype":"venue"
},
  "geometry": {"coordinates":[4.86822,45.025249],"type":"Point"}
}