{
  "type": "Feature",
  "properties": {
    "iso:country":"FR",
    "sg:address":"60 Quai Des Orf\u00e8vres 75001 Paris",
    "sg:classifiers":[
        {
            "category":"Professional",
            "subcategory":"Printing & Photocopies",
            "type":"Services"
        }
    ],
    "sg:phone":"+33 1 42 34 52 34",
    "sg:province":"Ile de France",
    "sg:tags":[
        "publishing"
    ],
    "wof:name":"Journal La Loi Gie",
    "wof:placetype":"venue"
},
  "geometry": {"coordinates":[2.341954,48.856361],"type":"Point"}
}