{
  "type": "Feature",
  "properties": {
    "iso:country":"FR",
    "sg:address":"71 Boulevard Brandenbourg 94200 Ivry Sur Seine",
    "sg:classifiers":[
        {
            "category":"Professional",
            "subcategory":"Printing & Photocopies",
            "type":"Services"
        }
    ],
    "sg:phone":"+33 1 49 59 30 00",
    "sg:province":"Ile de France",
    "sg:tags":[
        "publishing"
    ],
    "wof:name":"Nicaro Sarl",
    "wof:placetype":"venue"
},
  "geometry": {"coordinates":[2.392903,48.814415],"type":"Point"}
}