{
  "type": "Feature",
  "properties": {
    "iso:country":"FR",
    "sg:address":"Rue du Bois de la Dame",
    "sg:city":"Faye l'Abbesse",
    "sg:orig_category":"Non-Classified Establishments",
    "sg:phone":"+33 5 49 72 43 21",
    "sg:postcode":"79350",
    "sg:province":"Poitou-Charentes",
    "wof:name":"Cmsd S.a.r.l.",
    "wof:placetype":"venue"
},
  "geometry": {"coordinates":[-101.837173,33.737881],"type":"Point"}
}