{
  "type": "Feature",
  "properties": {
    "iso:country":"FR",
    "sg:address":"B.P. 20, 54650 Saulnes^^Zone Industrielle, 54650 Saulnes",
    "sg:orig_category":"Non-Classified Establishments",
    "sg:phone":"+33 3 82 25 37 38",
    "sg:province":"Lorraine",
    "wof:name":"L.m.i. Reconstruction S.a.r.l. - Le Mat\u00e9riel Industriel",
    "wof:placetype":"venue"
},
  "geometry": {"coordinates":[5.823113,49.531475],"type":"Point"}
}