{
  "type": "Feature",
  "properties": {
    "addr:full":"La Brande 17480 Le Ch\u00e2teau d'Ol\u00e9ron Poitou-Charentes",
    "addr:postcode":"17480",
    "addr:street":"La Brande;\u0301Ron",
    "iso:country":"FR",
    "sg:address":"La Brande 17480 Le Ch\u00e2teau d'Ol\u00e9ron",
    "sg:orig_category":"Unclassifiable Establishments",
    "sg:phone":"+33 5 46 47 65 94",
    "sg:province":"Poitou-Charentes",
    "wof:name":"Courdavault & L'huitri\u00e8re De L'ileau S.a.r.l.",
    "wof:placetype":"venue"
},
  "geometry": {"coordinates":[-0.497337,45.688507],"type":"Point"}
}