{
  "type": "Feature",
  "properties": {
    "addr:full":"3, Rue Saint Simon - ZA du Vert Galant, 95310 Saint Ouen l'Aumone Ile de France",
    "addr:housenumber":"3",
    "addr:postcode":"95310;l'aumone ile",
    "addr:street":"Rue Saint Simon Za Du Vert Galant",
    "iso:country":"FR",
    "sg:address":"3, Rue Saint Simon - ZA du Vert Galant, 95310 Saint Ouen l'Aumone",
    "sg:orig_category":"Unclassifiable Establishments",
    "sg:phone":"+33 1 34 40 74 00",
    "sg:province":"Ile de France",
    "wof:name":"Soci\u00e9t\u00e9 J. Daniel S.a.",
    "wof:placetype":"venue"
},
  "geometry": {"coordinates":[2.933116,48.55759],"type":"Point"}
}