{
  "type": "Feature",
  "properties": {
    "iso:country":"FR",
    "sg:address":"ZAC la Croisette",
    "sg:city":"Saint Nicolas de Port",
    "sg:orig_category":"Unclassifiable Establishments",
    "sg:phone":"+33 3 83 46 96 99",
    "sg:postcode":"54210",
    "sg:province":"Lorraine",
    "wof:name":"Jominet S.a.",
    "wof:placetype":"venue"
},
  "geometry": {"coordinates":[6.30159,48.631104],"type":"Point"}
}