{
  "type": "Feature",
  "properties": {
    "addr:full":"Av Ozanne 78440 Porcheville Ile de France 78440",
    "addr:postcode":"78440;78440",
    "addr:street":"Av Ozanne;Ile De France",
    "iso:country":"FR",
    "sg:address":"Av Ozanne 78440 Porcheville",
    "sg:classifiers":[
        {
            "category":"Manufacturing",
            "subcategory":"Metals",
            "type":"Manufacturing & Wholesale Goods"
        }
    ],
    "sg:phone":"+33 1 30 92 83 50",
    "sg:postcode":"78440",
    "sg:province":"Ile de France",
    "sg:tags":[
        "metallurgy",
        "steel",
        "metalworking"
    ],
    "wof:name":"Prosimo",
    "wof:placetype":"venue"
},
  "geometry": {"coordinates":[1.762414,48.984692],"type":"Point"}
}