{
  "type": "Feature",
  "properties": {
    "addr:full":"Quai des Agglom\u00e9r\u00e9s - Quai Anse d'Aubran - Anse d'Aubran Port de Bouc Provence-Alpes-C\u00f4te d'Azur 13110",
    "addr:postcode":"13110",
    "addr:street":"Quai Des Agglome\u0301Re\u0301S Quai Anse D'Aubran Anse D'Aubran Port De Bouc",
    "iso:country":"FR",
    "sg:address":"Quai des Agglom\u00e9r\u00e9s - Quai Anse d'Aubran - Anse d'Aubran",
    "sg:city":"Port de Bouc",
    "sg:orig_category":"Unclassifiable Establishments",
    "sg:phone":"+33 4 42 40 03 26",
    "sg:postcode":"13110",
    "sg:province":"Provence-Alpes-C\u00f4te d'Azur",
    "wof:name":"De C\u00e9sare Gastronomie S.a.r.l.",
    "wof:placetype":"venue"
},
  "geometry": {"coordinates":[4.976934,43.401684],"type":"Point"}
}