{
  "type": "Feature",
  "properties": {
    "addr:full":"B.P. 296, 44605 Saint Nazaire C\u00e9dex^^Bd des Apprentis, 44600 Saint Nazaire Pays de Loire",
    "addr:housenumber":"b.p. 296",
    "addr:postcode":"44605;44600",
    "addr:street":"Nazaire",
    "iso:country":"FR",
    "sg:address":"B.P. 296, 44605 Saint Nazaire C\u00e9dex^^Bd des Apprentis, 44600 Saint Nazaire",
    "sg:orig_category":"Non-Classified Establishments",
    "sg:phone":"+33 2 40 45 91 91",
    "sg:province":"Pays de Loire",
    "wof:name":"S.m.c.o. S.a.r.l. - Soci\u00e9t\u00e9 De Maintenance Et Construction De L'ouest",
    "wof:placetype":"venue"
},
  "geometry": {"coordinates":[-2.278494,47.240322],"type":"Point"}
}