{
  "type": "Feature",
  "properties": {
    "addr:full":"107 Rue Des Freres Lumiere Zi Sud 71000 Macon Sanc\u00e9 Bourgogne 71000",
    "addr:housenumber":"107",
    "addr:postcode":"71000;71000",
    "addr:street":"Rue Des Freres;Zi Sud",
    "iso:country":"FR",
    "sg:address":"107 Rue Des Freres Lumiere Zi Sud 71000 Macon",
    "sg:city":"Sanc\u00e9",
    "sg:classifiers":[
        {
            "category":"Farming",
            "subcategory":"Farm",
            "type":"Manufacturing & Wholesale Goods"
        }
    ],
    "sg:phone":"+33 3 85 34 97 00",
    "sg:postcode":"71000",
    "sg:province":"Bourgogne",
    "sg:tags":[
        "horticulture",
        "agriculture",
        "livestock"
    ],
    "wof:name":"Cedest",
    "wof:placetype":"venue"
},
  "geometry": {"coordinates":[4.833055,46.303043],"type":"Point"}
}