{
  "type": "Feature",
  "properties": {
    "addr:full":"389, Av. Jean Prouv\u00e9, 30900 N\u00eemes Languedoc-Roussillon",
    "addr:postcode":"30900",
    "addr:street":"389 Av. Jean Prouve\u0301",
    "iso:country":"FR",
    "sg:address":"389, Av. Jean Prouv\u00e9, 30900 N\u00eemes",
    "sg:orig_category":"Non-Classified Establishments",
    "sg:phone":"+33 4 66 38 60 20",
    "sg:province":"Languedoc-Roussillon",
    "wof:name":"Prodev S.a.r.l.",
    "wof:placetype":"venue"
},
  "geometry": {"coordinates":[4.351531,43.814194],"type":"Point"}
}