{
  "type": "Feature",
  "properties": {
    "addr:full":"5 ZAC d'Augny Augny Lorraine 57685",
    "addr:housenumber":"5",
    "addr:postcode":"57685",
    "addr:street":"Zac D'Augny Augny Lorraine",
    "iso:country":"FR",
    "sg:address":"5 ZAC d'Augny",
    "sg:city":"Augny",
    "sg:orig_category":"Unclassifiable Establishments",
    "sg:phone":"+33 3 87 38 44 02",
    "sg:postcode":"57685",
    "sg:province":"Lorraine",
    "wof:name":"Multi Process S.a.r.l.",
    "wof:placetype":"venue"
},
  "geometry": {"coordinates":[6.10956,49.053631],"type":"Point"}
}