{
  "type": "Feature",
  "properties": {
    "iso:country":"FR",
    "sg:address":"7, Rue du Cerf, 67400 Illkirch Graffenstaden",
    "sg:city":"Geispolsheim",
    "sg:orig_category":"Non-Classified Establishments",
    "sg:phone":"+33 3 88 67 10 00",
    "sg:postcode":"67400",
    "sg:province":"Alsace",
    "wof:name":"Haroche Communication S.a.r.l.",
    "wof:placetype":"venue"
},
  "geometry": {"coordinates":[7.736542,48.537968],"type":"Point"}
}