{
  "type": "Feature",
  "properties": {
    "addr:full":"r Commerce BP 137 59590 Raismes Nord Pas-de-Calais 59590",
    "addr:housenumber":"bp 137",
    "addr:postcode":"59590;59590",
    "iso:country":"FR",
    "sg:address":"r Commerce BP 137 59590 Raismes",
    "sg:classifiers":[
        {
            "category":"Government",
            "subcategory":"Department Of Motor Vehicles",
            "type":"Public Place"
        }
    ],
    "sg:phone":"+33 3 27 45 81 45",
    "sg:postcode":"59590",
    "sg:province":"Nord Pas-de-Calais",
    "sg:tags":[
        "equipment",
        "industrial",
        "transport",
        "motor-cars"
    ],
    "wof:name":"C.i.m.e. (sa)",
    "wof:placetype":"venue"
},
  "geometry": {"coordinates":[3.483345,50.388245],"type":"Point"}
}