{
  "type": "Feature",
  "properties": {
    "iso:country":"FR",
    "sg:address":"26 rue Fresnel 78310 Coignieres",
    "sg:classifiers":[
        {
            "category":"Manufacturing",
            "subcategory":"Metals",
            "type":"Manufacturing & Wholesale Goods"
        }
    ],
    "sg:phone":"+33 1 30 49 42 43",
    "sg:postcode":"78310",
    "sg:province":"Ile de France",
    "sg:tags":[
        "aluminium"
    ],
    "wof:name":"Apollo Metal S.a.",
    "wof:placetype":"venue"
},
  "geometry": {"coordinates":[1.925563,48.755211],"type":"Point"}
}