{
  "type": "Feature",
  "properties": {
    "addr:full":"6, Rue Michel Carr\u00e9, 66330 Cabestany Languedoc-Roussillon",
    "addr:housenumber":"6",
    "addr:postcode":"66330",
    "addr:street":"Rue Michel Carre\u0301",
    "iso:country":"FR",
    "sg:address":"6, Rue Michel Carr\u00e9, 66330 Cabestany",
    "sg:orig_category":"Unclassifiable Establishments",
    "sg:phone":"+33 4 68 66 54 38",
    "sg:province":"Languedoc-Roussillon",
    "wof:name":"Perez Carrelages S.a.r.l.",
    "wof:placetype":"venue"
},
  "geometry": {"coordinates":[2.920667,42.68856],"type":"Point"}
}