{
  "type": "Feature",
  "properties": {
    "iso:country":"FR",
    "sg:address":"B.P. 36, 69970 Chaponnay^^Parc d'Affaires de Chapotin, 69970 Chaponnay",
    "sg:orig_category":"Non-Classified Establishments",
    "sg:phone":"+33 4 78 96 00 37",
    "sg:province":"Rhone-Alpes",
    "wof:name":"F.p. 2 S.a.r.l.",
    "wof:placetype":"venue"
},
  "geometry": {"coordinates":[4.928624,45.64864],"type":"Point"}
}