{
  "type": "Feature",
  "properties": {
    "addr:full":"B.P. 2, 59780 Baisieux^^86, Rue de Tournai, 59780 Baisieux Nord Pas-de-Calais 59780",
    "addr:housenumber":"2",
    "addr:postcode":"59780;59780;59780",
    "addr:street":"B.P.;Rue De Tournai",
    "iso:country":"FR",
    "sg:address":"B.P. 2, 59780 Baisieux^^86, Rue de Tournai, 59780 Baisieux",
    "sg:orig_category":"Non-Classified Establishments",
    "sg:phone":"+33 3 20 41 90 00",
    "sg:postcode":"59780",
    "sg:province":"Nord Pas-de-Calais",
    "wof:name":"Comex S.a.",
    "wof:placetype":"venue"
},
  "geometry": {"coordinates":[3.240535,50.614738],"type":"Point"}
}