{
  "type": "Feature",
  "properties": {
    "addr:full":"B.P. 78, 64143 Lons Bill\u00e8re C\u00e9dex^^Av. Joliot Curie, 64140 Lons Lons Aquitaine 64140",
    "addr:postcode":"64143;64140;64140",
    "addr:street":"B.P. 78;Ce\u0301Dex^^Av Joliot Curie",
    "iso:country":"FR",
    "sg:address":"B.P. 78, 64143 Lons Bill\u00e8re C\u00e9dex^^Av. Joliot Curie, 64140 Lons",
    "sg:city":"Lons",
    "sg:orig_category":"Non-Classified Establishments",
    "sg:phone":"+33 5 59 92 11 62",
    "sg:postcode":"64140",
    "sg:province":"Aquitaine",
    "wof:name":"M.p.i. S.a.r.l. - Microm\u00e9canique De Pr\u00e9cision Industrielle",
    "wof:placetype":"venue"
},
  "geometry": {"coordinates":[-0.413078,43.317261],"type":"Point"}
}