{
  "type": "Feature",
  "properties": {
    "addr:full":"7 Av Vercors 38160 Chatte Rhone-Alpes 38160",
    "addr:postcode":"38160;38160",
    "addr:street":"Av Vercors",
    "iso:country":"FR",
    "sg:address":"7 Av Vercors 38160 Chatte",
    "sg:classifiers":[
        {
            "category":"Manufacturing",
            "subcategory":"Rubber & Plastics",
            "type":"Manufacturing & Wholesale Goods"
        }
    ],
    "sg:phone":"+33 4 76 64 07 73",
    "sg:postcode":"38160",
    "sg:province":"Rhone-Alpes",
    "wof:name":"Ivars France Sa",
    "wof:placetype":"venue"
},
  "geometry": {"coordinates":[5.282427,45.142246],"type":"Point"}
}