{
  "type": "Feature",
  "properties": {
    "iso:country":"FR",
    "sg:address":"Maisonneuve 74160 Vers",
    "sg:orig_category":"Non-Classified Establishments",
    "sg:phone":"+33 4 50 35 25 30",
    "sg:postcode":"74160",
    "sg:province":"Rhone-Alpes",
    "wof:name":"Dima S.a.",
    "wof:placetype":"venue"
},
  "geometry": {"coordinates":[6.025061,46.091328],"type":"Point"}
}