{
  "type": "Feature",
  "properties": {
    "addr:full":"96 ter, Av. Paul Doumer, 92500 Rueil Malmaison Ile de France",
    "addr:housenumber":"96",
    "addr:postcode":"92500",
    "addr:street":"Ter Av. Paul Doumer",
    "iso:country":"FR",
    "sg:address":"96 ter, Av. Paul Doumer, 92500 Rueil Malmaison",
    "sg:orig_category":"Non-Classified Establishments",
    "sg:phone":"+33 1 41 39 02 95",
    "sg:province":"Ile de France",
    "wof:name":"Plan\u00e8te Bleue S.a.r.l.",
    "wof:placetype":"venue"
},
  "geometry": {"coordinates":[2.180925,48.879871],"type":"Point"}
}