{
  "type": "Feature",
  "properties": {
    "addr:full":"ZI Spicheren Lorraine 57350",
    "addr:postcode":"57350",
    "addr:street":"Spicheren Lorraine",
    "iso:country":"FR",
    "sg:address":"ZI",
    "sg:city":"Spicheren",
    "sg:orig_category":"Unclassifiable Establishments",
    "sg:phone":"+33 3 87 85 03 40",
    "sg:postcode":"57350",
    "sg:province":"Lorraine",
    "wof:name":"S.l.e. S.a.r.l. - Fabrique De Baguettes Et De Galeries \u00e0 Rideaux",
    "wof:placetype":"venue"
},
  "geometry": {"coordinates":[6.928195,49.200981],"type":"Point"}
}