{
  "type": "Feature",
  "properties": {
    "addr:full":"183, Rue L\u00e9on Jouhaux, 78500 Sartrouville Ile de France",
    "addr:housenumber":"183",
    "addr:postcode":"78500;ile",
    "addr:street":"Rue Le\u0301On Jouhaux",
    "iso:country":"FR",
    "sg:address":"183, Rue L\u00e9on Jouhaux, 78500 Sartrouville",
    "sg:orig_category":"Unclassifiable Establishments",
    "sg:phone":"+33 1 61 04 22 22",
    "sg:province":"Ile de France",
    "wof:name":"Akora S.a.s.",
    "wof:placetype":"venue"
},
  "geometry": {"coordinates":[2.192567,48.948395],"type":"Point"}
}