{
  "type": "Feature",
  "properties": {
    "addr:full":"29, Rue des Moutons, 67870 Bischoffsheim Bischoffsheim Alsace 67870",
    "addr:housenumber":"29",
    "addr:postcode":"67870;67870",
    "addr:street":"Rue Des Moutons;Bischoffsheim",
    "iso:country":"FR",
    "sg:address":"29, Rue des Moutons, 67870 Bischoffsheim",
    "sg:city":"Bischoffsheim",
    "sg:orig_category":"Unclassifiable Establishments",
    "sg:phone":"+33 3 88 48 00 48",
    "sg:postcode":"67870",
    "sg:province":"Alsace",
    "wof:name":"Edelrid France S.a.r.l.",
    "wof:placetype":"venue"
},
  "geometry": {"coordinates":[7.496498,48.485107],"type":"Point"}
}