{
  "type": "Feature",
  "properties": {
    "iso:country":"FR",
    "sg:address":"1, Rue de l'Industrie, 76380 Bapeaume les Rouen",
    "sg:orig_category":"Non-Classified Establishments",
    "sg:phone":"+33 2 32 82 80 00",
    "sg:postcode":"76380",
    "sg:province":"Haute Normandie",
    "wof:name":"Ducros Euro Express S.a.",
    "wof:placetype":"venue"
},
  "geometry": {"coordinates":[1.039597,49.467541],"type":"Point"}
}