{
  "type": "Feature",
  "properties": {
    "iso:country":"FR",
    "sg:address":"B.P. 5326, 66033 Perpignan C\u00e9dex^^131, Rue de S\u00e9ville, 66000 Perpignan",
    "sg:orig_category":"Non-Classified Establishments",
    "sg:phone":"+33 4 68 68 19 33",
    "sg:province":"Languedoc-Roussillon",
    "wof:name":"Medina L.m. S.a.",
    "wof:placetype":"venue"
},
  "geometry": {"coordinates":[2.88743,42.69812],"type":"Point"}
}