{
  "type": "Feature",
  "properties": {
    "addr:full":"20 Rue Du Gal De Gaulle 58200 Cosne Cours Sur Loire Cosne-Cours-sur-Loire Bourgogne 58200",
    "addr:housenumber":"20",
    "addr:postcode":"58200;58200",
    "addr:street":"Rue Du Gal De Gaulle",
    "iso:country":"FR",
    "sg:address":"20 Rue Du Gal De Gaulle 58200 Cosne Cours Sur Loire",
    "sg:city":"Cosne-Cours-sur-Loire",
    "sg:classifiers":[
        {
            "category":"Banks & Credit Unions",
            "subcategory":"Financial Services",
            "type":"Services"
        }
    ],
    "sg:phone":"+33 3 86 28 84 60",
    "sg:postcode":"58200",
    "sg:province":"Bourgogne",
    "sg:tags":[
        "banking",
        "insurance",
        "institution",
        "finance"
    ],
    "wof:name":"Banque Populaire De Bourgogne (bpco)",
    "wof:placetype":"venue"
},
  "geometry": {"coordinates":[2.901115,47.369862],"type":"Point"}
}