{
  "type": "Feature",
  "properties": {
    "addr:full":"2 Rue Henri Iv 64800 Benejacq B\u00e9n\u00e9jacq Aquitaine 64800",
    "addr:housenumber":"2",
    "addr:postcode":"64800;64800",
    "addr:street":"Rue Henri Iv",
    "iso:country":"FR",
    "sg:address":"2 Rue Henri Iv 64800 Benejacq",
    "sg:city":"B\u00e9n\u00e9jacq",
    "sg:classifiers":[
        {
            "category":"Manufacturing",
            "subcategory":"Textiles",
            "type":"Manufacturing & Wholesale Goods"
        }
    ],
    "sg:phone":"+33 5 59 61 07 07",
    "sg:postcode":"64800",
    "sg:province":"Aquitaine",
    "sg:tags":[
        "linen",
        "clothing",
        "fabric"
    ],
    "wof:name":"Societe D'exploitation Des Tissages Valerien",
    "wof:placetype":"venue"
},
  "geometry": {"coordinates":[-0.212476,43.195053],"type":"Point"}
}