{
  "type": "Feature",
  "properties": {
    "addr:full":"5, Rue de la Planche aux Joncs, 57155 Marly Lorraine",
    "addr:housenumber":"5",
    "addr:postcode":"57155",
    "addr:street":"Rue De La Planche Aux Joncs",
    "iso:country":"FR",
    "sg:address":"5, Rue de la Planche aux Joncs, 57155 Marly",
    "sg:orig_category":"Unclassifiable Establishments",
    "sg:phone":"+33 3 87 56 11 11",
    "sg:province":"Lorraine",
    "wof:name":"Imprimerie Marchal S.a.r.l.",
    "wof:placetype":"venue"
},
  "geometry": {"coordinates":[6.14824,49.076191],"type":"Point"}
}