{
  "type": "Feature",
  "properties": {
    "iso:country":"FR",
    "sg:address":"ZI Roumagoua",
    "sg:city":"La Ciotat",
    "sg:orig_category":"Non-Classified Establishments",
    "sg:phone":"+33 4 42 83 31 88",
    "sg:postcode":"13600",
    "sg:province":"Provence-Alpes-C\u00f4te d'Azur",
    "wof:name":"C.t.i. S.a.r.l. - Chaudronnerie Tuyauterie Industrielle",
    "wof:placetype":"venue"
},
  "geometry": {"coordinates":[5.610365,43.174191],"type":"Point"}
}