{
  "type": "Feature",
  "properties": {
    "addr:full":"Parc d'Activit\u00e9 Gros Ch\u00eane S\u00e9rent Bretagne 56460",
    "addr:postcode":"56460",
    "addr:street":"Se\u0301Rent Bretagne",
    "iso:country":"FR",
    "sg:address":"Parc d'Activit\u00e9 Gros Ch\u00eane",
    "sg:city":"S\u00e9rent",
    "sg:orig_category":"Unclassifiable Establishments",
    "sg:phone":"+33 2 97 75 09 75",
    "sg:postcode":"56460",
    "sg:province":"Bretagne",
    "wof:name":"L.e.m. S.a. - Les Elastom\u00e8res Moul\u00e9s",
    "wof:placetype":"venue"
},
  "geometry": {"coordinates":[-2.515188,47.821888],"type":"Point"}
}