{
  "type": "Feature",
  "properties": {
    "iso:country":"FR",
    "sg:address":"17 Rue Emmaus 60000 Beauvais",
    "sg:classifiers":[
        {
            "category":"Professional",
            "subcategory":"Printing & Photocopies",
            "type":"Services"
        }
    ],
    "sg:phone":"+33 3 44 02 40 21",
    "sg:postcode":"60000",
    "sg:province":"Picardie",
    "sg:tags":[
        "machine",
        "engineering",
        "-",
        "mechanical"
    ],
    "wof:name":"Miller Graphics Beauvais",
    "wof:placetype":"venue"
},
  "geometry": {"coordinates":[2.08322,49.429558],"type":"Point"}
}