{
  "type": "Feature",
  "properties": {
    "addr:full":"Impasse Beno\u00eet Salbris Centre 41300",
    "addr:postcode":"41300",
    "addr:street":"Impasse Benoi\u0302T Salbris",
    "iso:country":"FR",
    "sg:address":"Impasse Beno\u00eet",
    "sg:city":"Salbris",
    "sg:orig_category":"Unclassifiable Establishments",
    "sg:phone":"+33 2 54 97 17 25",
    "sg:postcode":"41300",
    "sg:province":"Centre",
    "wof:name":"Electro Cab S.a.r.l.",
    "wof:placetype":"venue"
},
  "geometry": {"coordinates":[2.028337,47.418045],"type":"Point"}
}