{
  "type": "Feature",
  "properties": {
    "iso:country":"FR",
    "sg:address":"145, Rue Yves le Coz, 78000 Versailles",
    "sg:orig_category":"Unclassifiable Establishments",
    "sg:phone":"+33 1 39 24 39 24",
    "sg:province":"Ile de France",
    "wof:name":"S.e.v.s.c. S.a. - Soci\u00e9t\u00e9 Eaux Versailles Saint Cloud",
    "wof:placetype":"venue"
},
  "geometry": {"coordinates":[2.150475,48.791668],"type":"Point"}
}