{
  "type": "Feature",
  "properties": {
    "iso:country":"FR",
    "sg:address":"40 Bd De Dunkerque 13002 Marseille",
    "sg:classifiers":[
        {
            "category":"Marine",
            "type":"Transportation"
        }
    ],
    "sg:phone":"+33 4 91 13 18 00",
    "sg:province":"Poitou-Charentes",
    "sg:tags":[
        "transport",
        "sea"
    ],
    "wof:name":"Nedlloyd Lines France",
    "wof:placetype":"venue"
},
  "geometry": {"coordinates":[5.368016,43.307137],"type":"Point"}
}