{
  "type": "Feature",
  "properties": {
    "addr:full":"B.P. 43, 91412 Dourdan C\u00e9dex^^11, Rue Marie Poussepin - ZI de la Gaudr\u00e9e, 91410 Dourdan Ile de France",
    "addr:postcode":"91412;91410;ile",
    "addr:street":"B.P. 43;Rue Marie Poussepin Zi De La Gaudre\u0301E",
    "iso:country":"FR",
    "sg:address":"B.P. 43, 91412 Dourdan C\u00e9dex^^11, Rue Marie Poussepin - ZI de la Gaudr\u00e9e, 91410 Dourdan",
    "sg:orig_category":"Non-Classified Establishments",
    "sg:phone":"+33 1 64 59 35 20",
    "sg:province":"Ile de France",
    "wof:name":"Veeco Instruments S.a.",
    "wof:placetype":"venue"
},
  "geometry": {"coordinates":[2.01121,48.528149],"type":"Point"}
}