{
  "type": "Feature",
  "properties": {
    "iso:country":"FR",
    "sg:address":"25 bis, Av. Marcel Dassault, 31500 Toulouse",
    "sg:orig_category":"Unclassifiable Establishments",
    "sg:phone":"+33 5 61 17 47 17",
    "sg:province":"Midi Pyr\u00e9n\u00e9es",
    "wof:name":"K.h.i.2 S.a.",
    "wof:placetype":"venue"
},
  "geometry": {"coordinates":[1.496331,43.578594],"type":"Point"}
}