{
  "type": "Feature",
  "properties": {
    "addr:full":"65, R Mal de Lattre de Tassigny, 52115 Saint Dizier C\u00e9dex Assigny Centre 18260",
    "addr:housenumber":"65",
    "addr:postcode":"52115;18260",
    "addr:street":"R Mal De Lattre De Tassigny",
    "iso:country":"FR",
    "sg:address":"65, R Mal de Lattre de Tassigny, 52115 Saint Dizier C\u00e9dex",
    "sg:city":"Assigny",
    "sg:orig_category":"Non-Classified Establishments",
    "sg:phone":"+33 3 25 56 71 11",
    "sg:postcode":"18260",
    "sg:province":"Centre",
    "wof:name":"E.d.f. - G.d.f. Services",
    "wof:placetype":"venue"
},
  "geometry": {"coordinates":[4.954452,48.637424],"type":"Point"}
}