{
  "type": "Feature",
  "properties": {
    "iso:country":"FR",
    "sg:address":"avenue du Vermandois 60200 COMPIEGNE",
    "sg:classifiers":[
        {
            "category":"Manufacturing",
            "subcategory":"Chemicals & Compounds",
            "type":"Manufacturing & Wholesale Goods"
        }
    ],
    "sg:phone":"+33 3 44 40 75 75",
    "sg:province":"Picardie",
    "sg:tags":[
        "resin"
    ],
    "wof:name":"Dsm Composite Resins France Sas",
    "wof:placetype":"venue"
},
  "geometry": {"coordinates":[2.842907,49.432556],"type":"Point"}
}