{
  "type": "Feature",
  "properties": {
    "iso:country":"FR",
    "sg:address":"12, Rue Jean Perrin - ZI du Chapitre, 31100 Toulouse",
    "sg:orig_category":"Unclassifiable Establishments",
    "sg:phone":"+33 5 62 87 18 00",
    "sg:province":"Midi Pyr\u00e9n\u00e9es",
    "wof:name":"Domica S.a.r.l.",
    "wof:placetype":"venue"
},
  "geometry": {"coordinates":[1.39859,43.56786],"type":"Point"}
}