{
  "type": "Feature",
  "properties": {
    "addr:full":"Impasse de la Quintinie L'Isle d'Espagnac Poitou-Charentes 16340",
    "addr:postcode":"16340",
    "addr:street":"Impasse De La Quintinie;D'Espagnac",
    "iso:country":"FR",
    "sg:address":"Impasse de la Quintinie",
    "sg:city":"L'Isle d'Espagnac",
    "sg:orig_category":"Unclassifiable Establishments",
    "sg:phone":"+33 5 45 69 46 10",
    "sg:postcode":"16340",
    "sg:province":"Poitou-Charentes",
    "wof:name":"Agence Perriez Industrie S.a.",
    "wof:placetype":"venue"
},
  "geometry": {"coordinates":[-79.440071,41.82935],"type":"Point"}
}