{
  "type": "Feature",
  "properties": {
    "iso:country":"FR",
    "sg:address":"ZAC - Croix Sud",
    "sg:city":"Narbonne",
    "sg:orig_category":"Non-Classified Establishments",
    "sg:phone":"+33 4 68 42 06 60",
    "sg:postcode":"11100",
    "sg:province":"Languedoc-Roussillon",
    "wof:name":"Etablissement Robert Hortal Et Fils S.a.r.l.",
    "wof:placetype":"venue"
},
  "geometry": {"coordinates":[3.004325,43.188354],"type":"Point"}
}