{
  "type": "Feature",
  "properties": {
    "addr:full":"1002, RN, 74120 Meg\u00e8ve Rhone-Alpes 74120",
    "addr:housenumber":"1002",
    "addr:postcode":"rn 74120;74120",
    "iso:country":"FR",
    "sg:address":"1002, RN, 74120 Meg\u00e8ve",
    "sg:orig_category":"Unclassifiable Establishments",
    "sg:phone":"+33 4 50 21 10 52",
    "sg:postcode":"74120",
    "sg:province":"Rhone-Alpes",
    "wof:name":"Gaubicher S.a.",
    "wof:placetype":"venue"
},
  "geometry": {"coordinates":[6.61629,45.856449],"type":"Point"}
}