{
  "type": "Feature",
  "properties": {
    "iso:country":"FR",
    "sg:address":"B\u00e2timent 3-HLM El Viv\u00e8s",
    "sg:city":"Perpignan",
    "sg:orig_category":"Non-Classified Establishments",
    "sg:phone":"+33 4 68 61 27 40",
    "sg:postcode":"66000",
    "sg:province":"Languedoc-Roussillon",
    "wof:name":"Gescal International S.a.r.l.",
    "wof:placetype":"venue"
},
  "geometry": {"coordinates":[2.898027,42.710648],"type":"Point"}
}