{
  "type": "Feature",
  "properties": {
    "addr:full":"67, Rue Saint Jacques, 75005 Paris Ile de France",
    "addr:housenumber":"67",
    "addr:postcode":"75005",
    "addr:street":"Rue Saint Jacques",
    "iso:country":"FR",
    "sg:address":"67, Rue Saint Jacques, 75005 Paris",
    "sg:orig_category":"Non-Classified Establishments",
    "sg:phone":"+33 6 89 54 22 91",
    "sg:province":"Ile de France",
    "wof:name":"Monadis S.a.r.l.",
    "wof:placetype":"venue"
},
  "geometry": {"coordinates":[2.345296,48.850052],"type":"Point"}
}