{
  "type": "Feature",
  "properties": {
    "addr:full":"25 R De Verdun 57180 Terville Lorraine 57180",
    "addr:housenumber":"25",
    "addr:postcode":"57180;57180",
    "addr:street":"R De Verdun",
    "iso:country":"FR",
    "sg:address":"25 R De Verdun 57180 Terville",
    "sg:classifiers":[
        {
            "category":"Autos & Motor Vehicles",
            "subcategory":"Automobile Sales",
            "type":"Retail Goods"
        }
    ],
    "sg:phone":"+33 3 82 59 19 19",
    "sg:postcode":"57180",
    "sg:province":"Lorraine",
    "sg:tags":[
        "equipment",
        "motor-cars",
        "transport"
    ],
    "wof:name":"Ets A. Gardin",
    "wof:placetype":"venue"
},
  "geometry": {"coordinates":[6.147311,49.346504],"type":"Point"}
}