{
  "type": "Feature",
  "properties": {
    "addr:full":"B.P. 2092, 17010 La Rochelle C\u00e9dex 1^^Zone Portuaire de Chef de Baie - La Palisse , 17000 La Rochell Poitou-Charentes 17000",
    "addr:housenumber":"17010",
    "addr:postcode":"17000;17000",
    "addr:street":"B.P. 2092;La Palisse;Rochell",
    "iso:country":"FR",
    "sg:address":"B.P. 2092, 17010 La Rochelle C\u00e9dex 1^^Zone Portuaire de Chef de Baie - La Palisse , 17000 La Rochell",
    "sg:orig_category":"Non-Classified Establishments",
    "sg:phone":"+33 5 46 00 00 10",
    "sg:postcode":"17000",
    "sg:province":"Poitou-Charentes",
    "wof:name":"C.i.t. S.a. - Clergeau International Trading",
    "wof:placetype":"venue"
},
  "geometry": {"coordinates":[-1.151639,46.159435],"type":"Point"}
}