{
  "type": "Feature",
  "properties": {
    "addr:full":"35, Bd du Danemark - Parc d'Activit\u00e9s Albasud, 82000 Montauban Midi Pyr\u00e9n\u00e9es",
    "addr:housenumber":"35",
    "addr:postcode":"82000",
    "addr:street":"Bd Du Danemark Parc D'Activite \u0301S Albasud",
    "iso:country":"FR",
    "sg:address":"35, Bd du Danemark - Parc d'Activit\u00e9s Albasud, 82000 Montauban",
    "sg:orig_category":"Unclassifiable Establishments",
    "sg:phone":"+33 5 63 23 03 41",
    "sg:province":"Midi Pyr\u00e9n\u00e9es",
    "wof:name":"A.p.s. France Equipements S.a.r.l.",
    "wof:placetype":"venue"
},
  "geometry": {"coordinates":[1.32958,43.988613],"type":"Point"}
}