{
  "type": "Feature",
  "properties": {
    "addr:full":"81 Rue Waldeck Rousseau Ccial Sncf 83700 St Rapha\u00ebl Aquitaine",
    "addr:housenumber":"81",
    "addr:postcode":"83700",
    "addr:street":"Rue Waldeck Rousseau Ccial Sncf",
    "iso:country":"FR",
    "sg:address":"81 Rue Waldeck Rousseau Ccial Sncf 83700 St Rapha\u00ebl",
    "sg:classifiers":[
        {
            "category":"Utilities",
            "subcategory":"Telephone",
            "type":"Services"
        }
    ],
    "sg:phone":"+33 4 94 40 50 32",
    "sg:province":"Aquitaine",
    "sg:tags":[
        "telecommunication"
    ],
    "wof:name":"Duquesne Telecom",
    "wof:placetype":"venue"
},
  "geometry": {"coordinates":[6.768579,43.425011],"type":"Point"}
}