{
  "type": "Feature",
  "properties": {
    "iso:country":"FR",
    "sg:address":"Rue de la Manufacture",
    "sg:city":"Saint Gobain",
    "sg:orig_category":"EMBALLAGES A\u00c9RIENS OU MARITIMES, EMBALLAGES EN BOIS OU INDUSTRIEL, SUR MESURE PALETTES EN BOIS, CAIS",
    "sg:phone":"+33 3 23 52 60 08",
    "sg:postcode":"02410",
    "sg:province":"Picardie",
    "wof:name":"C.m.f. S.a.r.l. - Caisserie Menuiserie Fay",
    "wof:placetype":"venue"
},
  "geometry": {"coordinates":[3.370807,49.599213],"type":"Point"}
}