{
  "type": "Feature",
  "properties": {
    "addr:full":"1 Rue Maryse Basti\u00e9 59810 Lesquin Nord Pas-de-Calais 59810",
    "addr:housenumber":"1",
    "addr:postcode":"59810;59810",
    "addr:street":"Rue Maryse Bastie\u0301",
    "iso:country":"FR",
    "sg:address":"1 Rue Maryse Basti\u00e9 59810 Lesquin",
    "sg:classifiers":[
        {
            "category":"Banks & Credit Unions",
            "subcategory":"Investment Brokerage",
            "type":"Services"
        }
    ],
    "sg:phone":"+33 3 20 87 92 39",
    "sg:postcode":"59810",
    "sg:province":"Nord Pas-de-Calais",
    "sg:tags":[
        "-",
        "transport",
        "related",
        "air"
    ],
    "wof:name":"Airborne Express Sa",
    "wof:placetype":"venue"
},
  "geometry": {"coordinates":[3.11202,50.57666],"type":"Point"}
}