{
  "type": "Feature",
  "properties": {
    "iso:country":"FR",
    "sg:address":"Place De La Verrerie 03100 Montlucon",
    "sg:city":"Montlu\u00e7on",
    "sg:classifiers":[
        {
            "category":"Manufacturing",
            "subcategory":"Glass & Minerals",
            "type":"Manufacturing & Wholesale Goods"
        }
    ],
    "sg:phone":"+33 4 70 28 22 44",
    "sg:postcode":"03100",
    "sg:province":"Auvergne",
    "sg:tags":[
        "building",
        "material"
    ],
    "wof:name":"Verreries Du Centre",
    "wof:placetype":"venue"
},
  "geometry": {"coordinates":[2.599152,46.348354],"type":"Point"}
}