{
  "type": "Feature",
  "properties": {
    "iso:country":"FR",
    "sg:address":"3, Chemin du Buisson, 77760 Ury",
    "sg:orig_category":"Non-Classified Establishments",
    "sg:phone":"+33 1 64 24 42 66",
    "sg:province":"Ile de France",
    "wof:name":"Hein Lehmann S.a.r.l.",
    "wof:placetype":"venue"
},
  "geometry": {"coordinates":[2.606469,48.340168],"type":"Point"}
}