{
  "type": "Feature",
  "properties": {
    "addr:full":"1 bis rue Mercoeur; Nantes Haute Normandie",
    "addr:housenumber":"1 bis",
    "addr:street":"Rue Mercoeur",
    "iso:country":"FR",
    "sg:address":"1 bis rue Mercoeur; Nantes",
    "sg:classifiers":[
        {
            "category":"Banks & Credit Unions",
            "subcategory":"Bank",
            "type":"Services"
        }
    ],
    "sg:phone":"+33 3340487987",
    "sg:province":"Haute Normandie",
    "wof:name":"Banque Cio, Nantes Bretagne",
    "wof:placetype":"venue"
},
  "geometry": {"coordinates":[-1.560179,47.21743],"type":"Point"}
}