{
  "type": "Feature",
  "properties": {
    "iso:country":"FR",
    "sg:address":"B.P. 115, 69170 Tarare C\u00e9dex^^7, Av. Edouard Herriot, 69170 Tarare",
    "sg:orig_category":"Non-Classified Establishments",
    "sg:phone":"+33 4 74 05 35 00",
    "sg:postcode":"69170",
    "sg:province":"Rhone-Alpes",
    "wof:name":"Eutex Intermaille S.a.",
    "wof:placetype":"venue"
},
  "geometry": {"coordinates":[4.402325,45.84494],"type":"Point"}
}