{
  "type": "Feature",
  "properties": {
    "iso:country":"FR",
    "sg:address":"103 Avenue Mal De Saxe",
    "sg:city":"Lyon",
    "sg:classifiers":[
        {
            "category":"Banks & Credit Unions",
            "subcategory":"Financial Services",
            "type":"Services"
        }
    ],
    "sg:phone":"+33 4 72 84 46 00",
    "sg:postcode":"69003",
    "sg:province":"Rhone-Alpes",
    "sg:tags":[
        "banking",
        "finance",
        "insurance"
    ],
    "wof:name":"Banque Francaise Du Credit Cooperatif (credit Cooperatif Ou Bfcc)",
    "wof:placetype":"venue"
},
  "geometry": {"coordinates":[4.84978,45.760479],"type":"Point"}
}