{
  "type": "Feature",
  "properties": {
    "iso:country":"FR",
    "sg:address":"16BIS avenue Potier 93380 Pierrefitte sur Seine",
    "sg:classifiers":[
        {
            "category":"Manufacturing",
            "subcategory":"Motor Vehicles & Parts",
            "type":"Manufacturing & Wholesale Goods"
        }
    ],
    "sg:phone":"+33 1 48 26 42 67",
    "sg:province":"Ile de France",
    "sg:tags":[
        "precision",
        "mechanic"
    ],
    "wof:name":"M.o.p. S.a.r.l.",
    "wof:placetype":"venue"
},
  "geometry": {"coordinates":[2.359933,48.961365],"type":"Point"}
}