{
  "type": "Feature",
  "properties": {
    "addr:full":"B.P. 295, 02106 Saint Quentin C\u00e9dex^^Chemin Clastrois, 02100 Saint Quentin Picardie",
    "addr:housenumber":"b.p. 295",
    "addr:postcode":"02106;02100",
    "addr:street":"Clastrois",
    "iso:country":"FR",
    "sg:address":"B.P. 295, 02106 Saint Quentin C\u00e9dex^^Chemin Clastrois, 02100 Saint Quentin",
    "sg:orig_category":"Non-Classified Establishments",
    "sg:phone":"+33 3 23 50 69 69",
    "sg:province":"Picardie",
    "wof:name":"S.i.f. S.a. - Soci\u00e9t\u00e9 Industrielle Des Fontes",
    "wof:placetype":"venue"
},
  "geometry": {"coordinates":[3.291286,49.850952],"type":"Point"}
}