{
  "type": "Feature",
  "properties": {
    "addr:full":"377 Route De La Gare 83190 Ollioules",
    "addr:housenumber":"377",
    "addr:postcode":"83190",
    "addr:street":"Route De La Gare",
    "iso:country":"FR",
    "sg:address":"377 Route De La Gare 83190 Ollioules",
    "sg:classifiers":[
        {
            "category":"Shopping",
            "subcategory":"Clothing, Apparel, & Fashions",
            "type":"Retail Goods"
        }
    ],
    "sg:phone":"+33 4 94 63 74 33",
    "sg:tags":[
        "textile",
        "clothing",
        "clothes"
    ],
    "wof:name":"Game",
    "wof:placetype":"venue"
},
  "geometry": {"coordinates":[5.833336,43.124348],"type":"Point"}
}