{
  "type": "Feature",
  "properties": {
    "iso:country":"FR",
    "sg:address":"B.P. 7, 85250 Saint Fulgent C\u00e9dex^^Rue du Stade, 85250 Saint Fulgent",
    "sg:orig_category":"Non-Classified Establishments",
    "sg:phone":"+33 2 51 42 60 89",
    "sg:province":"Pays de Loire",
    "wof:name":"S.o.f.u.l.t.r.a.p S.a. - Soci\u00e9t\u00e9 Fulgentenaise De Travaux Publics Papin",
    "wof:placetype":"venue"
},
  "geometry": {"coordinates":[-1.174436,46.859283],"type":"Point"}
}