{
  "type": "Feature",
  "properties": {
    "addr:full":"24 Rue Charles Durand Pipact 18000 Bourges Bourges Centre 18000",
    "addr:housenumber":"24",
    "addr:postcode":"18000;18000",
    "addr:street":"Rue Charles Durand Pipact",
    "iso:country":"FR",
    "sg:address":"24 Rue Charles Durand Pipact 18000 Bourges",
    "sg:city":"Bourges",
    "sg:classifiers":[
        {
            "category":"Professional",
            "subcategory":"Business Services",
            "type":"Services"
        }
    ],
    "sg:phone":"+33 2 48 68 48 09",
    "sg:postcode":"18000",
    "sg:province":"Centre",
    "sg:tags":[
        "information",
        "advice",
        "technology",
        "software"
    ],
    "wof:name":"Sig Gie",
    "wof:placetype":"venue"
},
  "geometry": {"coordinates":[2.400801,47.101883],"type":"Point"}
}