{
  "type": "Feature",
  "properties": {
    "addr:full":"B.P. 04, 49380 Thouarc\u00e9 C\u00e9dex^^Rte de Dou\u00e9, 49380 Thouarc\u00e9 Pays de Loire 49380",
    "addr:postcode":"49380;49380;49380",
    "addr:street":"B.P. 04;Doue\u0301",
    "iso:country":"FR",
    "sg:address":"B.P. 04, 49380 Thouarc\u00e9 C\u00e9dex^^Rte de Dou\u00e9, 49380 Thouarc\u00e9",
    "sg:orig_category":"Non-Classified Establishments",
    "sg:phone":"+33 2 41 54 05 05",
    "sg:postcode":"49380",
    "sg:province":"Pays de Loire",
    "wof:name":"E.s.o. S.a. - Emballages Sp\u00e9ciaux De L'ouest",
    "wof:placetype":"venue"
},
  "geometry": {"coordinates":[-0.499644,47.238811],"type":"Point"}
}