{
  "type": "Feature",
  "properties": {
    "iso:country":"FR",
    "sg:address":"8, Rue M Dassault - Parc Technologique, 21000 Dijon",
    "sg:city":"Dijon",
    "sg:orig_category":"Non-Classified Establishments",
    "sg:phone":"+33 3 80 72 07 70",
    "sg:postcode":"21000",
    "sg:province":"Bourgogne",
    "wof:name":"Anvar Epic",
    "wof:placetype":"venue"
},
  "geometry": {"coordinates":[5.042608,47.357498],"type":"Point"}
}