{
  "type": "Feature",
  "properties": {
    "iso:country":"FR",
    "sg:address":"38, Rue du Chemin de Fer, 77400 Dampmart",
    "sg:orig_category":"Non-Classified Establishments",
    "sg:phone":"+33 1 60 07 67 17",
    "sg:postcode":"77400",
    "sg:province":"Ile de France",
    "wof:name":"C. P. I. S.a.r.l. - Contr\u00f4le De Processus Industriels",
    "wof:placetype":"venue"
},
  "geometry": {"coordinates":[2.731669,48.884094],"type":"Point"}
}