{
  "type": "Feature",
  "properties": {
    "iso:country":"FR",
    "sg:address":"52 Av Du Gal De Gaulle 94700 Maisons Alfort",
    "sg:classifiers":[
        {
            "category":"Manufacturing",
            "subcategory":"Leather Goods",
            "type":"Manufacturing & Wholesale Goods"
        }
    ],
    "sg:phone":"+33 1 48 93 31 00",
    "sg:postcode":"94700",
    "sg:province":"Ile de France",
    "sg:tags":[
        "shoe"
    ],
    "wof:name":"Bansse Et Cie",
    "wof:placetype":"venue"
},
  "geometry": {"coordinates":[2.421438,48.813213],"type":"Point"}
}