{
  "type": "Feature",
  "properties": {
    "iso:country":"FR",
    "sg:address":"av du Doct Mommont 46110 Quatre Routes (Les)",
    "sg:classifiers":[
        {
            "category":"Professional",
            "type":"Services"
        }
    ],
    "sg:phone":"+33 5 65 32 12 29",
    "sg:province":"Midi Pyr\u00e9n\u00e9es",
    "sg:tags":[
        "transport",
        "road"
    ],
    "wof:name":"Bernard Mangot",
    "wof:placetype":"venue"
},
  "geometry": {"coordinates":[1.640732,44.999187],"type":"Point"}
}