{
  "type": "Feature",
  "properties": {
    "iso:country":"FR",
    "sg:address":"Zone Industrielle d'Anglumeau 33450 Izon",
    "sg:city":"Izon",
    "sg:orig_category":"Recycling Of Screen Glass",
    "sg:phone":"+33 5 57 55 49 50",
    "sg:postcode":"33450",
    "sg:province":"Aquitaine",
    "wof:name":"Ipaq Sa",
    "wof:placetype":"venue"
},
  "geometry": {"coordinates":[-0.341814,44.913429],"type":"Point"}
}