{
  "type": "Feature",
  "properties": {
    "addr:full":"10, Rue de la Sabli\u00e8re, 92230 Gennevilliers Ile de France 92230",
    "addr:housenumber":"10",
    "addr:postcode":"92230;ile;92230",
    "addr:street":"Rue De La Sablie\u0300Re;France",
    "iso:country":"FR",
    "sg:address":"10, Rue de la Sabli\u00e8re, 92230 Gennevilliers",
    "sg:orig_category":"Non-Classified Establishments",
    "sg:phone":"+33 1 41 11 56 78",
    "sg:postcode":"92230",
    "sg:province":"Ile de France",
    "wof:name":"Apsim S.a.r.l.",
    "wof:placetype":"venue"
},
  "geometry": {"coordinates":[2.30617,48.917343],"type":"Point"}
}