{
  "type": "Feature",
  "properties": {
    "addr:full":"B.P. 15, 25490 Fesches le Ch\u00e2tel^^Parc d'Activit\u00e9s du Moulin, 25490 Fesches le Ch\u00e2tel Franche Comt\u00e9",
    "addr:housenumber":"cha\u0302tel",
    "addr:postcode":"25490;25490",
    "addr:street":"B.P. 15;Moulin;Franche Comte\u0301",
    "iso:country":"FR",
    "sg:address":"B.P. 15, 25490 Fesches le Ch\u00e2tel^^Parc d'Activit\u00e9s du Moulin, 25490 Fesches le Ch\u00e2tel",
    "sg:orig_category":"Non-Classified Establishments",
    "sg:phone":"+33 3 81 96 16 47",
    "sg:province":"Franche Comt\u00e9",
    "wof:name":"Pompes Japy S.a.",
    "wof:placetype":"venue"
},
  "geometry": {"coordinates":[6.942777,47.505238],"type":"Point"}
}