{
  "type": "Feature",
  "properties": {
    "addr:full":"24 Rue Des Huguenots 18700 Aubigny Sur N\u00e8re Aubigny-sur-N\u00e8re Centre 18700",
    "addr:housenumber":"24;aubigny-sur-ne\u0300re",
    "addr:postcode":"18700;18700",
    "addr:street":"Rue Des Huguenots",
    "iso:country":"FR",
    "sg:address":"24 Rue Des Huguenots 18700 Aubigny Sur N\u00e8re",
    "sg:city":"Aubigny-sur-N\u00e8re",
    "sg:classifiers":[
        {
            "category":"Manufacturing",
            "subcategory":"Metals",
            "type":"Manufacturing & Wholesale Goods"
        }
    ],
    "sg:phone":"+33 2 48 58 02 78",
    "sg:postcode":"18700",
    "sg:province":"Centre",
    "sg:tags":[
        "metallurgy",
        "steel",
        "metalworking"
    ],
    "wof:name":"Emaumetal Sa",
    "wof:placetype":"venue"
},
  "geometry": {"coordinates":[2.431825,47.47702],"type":"Point"}
}