{
  "type": "Feature",
  "properties": {
    "addr:full":"11 Rue Du Pont V 76600 Le Havre Haute Normandie",
    "addr:housenumber":"11",
    "addr:postcode":"76600",
    "addr:street":"Rue Du Pont V",
    "iso:country":"FR",
    "sg:address":"11 Rue Du Pont V 76600 Le Havre",
    "sg:classifiers":[
        {
            "category":"Marine",
            "type":"Transportation"
        }
    ],
    "sg:phone":"+33 2 35 53 50 47",
    "sg:province":"Haute Normandie",
    "sg:tags":[
        "transport",
        "sea"
    ],
    "wof:name":"Sogestran",
    "wof:placetype":"venue"
},
  "geometry": {"coordinates":[0.155586,49.482544],"type":"Point"}
}