{
  "type": "Feature",
  "properties": {
    "iso:country":"FR",
    "sg:address":"Av. de la Messesselle",
    "sg:city":"Nogent le Rotrou C\u00e9dex",
    "sg:orig_category":"Non-Classified Establishments",
    "sg:phone":"+33 2 37 52 63 84",
    "sg:postcode":"28402",
    "sg:province":"Poitou-Charentes",
    "wof:name":"Lacroix Sofrel Electronique S.a.",
    "wof:placetype":"venue"
},
  "geometry": {"coordinates":[-77.945953,34.23497],"type":"Point"}
}