{
  "type": "Feature",
  "properties": {
    "addr:full":"Cours Docteur Seigle Le Thor Midi Pyr\u00e9n\u00e9es 84250",
    "addr:postcode":"84250",
    "addr:street":"Cours Docteur Seigle;Midi",
    "iso:country":"FR",
    "sg:address":"Cours Docteur Seigle",
    "sg:city":"Le Thor",
    "sg:orig_category":"Unclassifiable Establishments",
    "sg:phone":"+33 4 90 33 93 81",
    "sg:postcode":"84250",
    "sg:province":"Midi Pyr\u00e9n\u00e9es",
    "wof:name":"Thiers Jean S.a.",
    "wof:placetype":"venue"
},
  "geometry": {"coordinates":[4.994055,43.931355],"type":"Point"}
}