{
  "type": "Feature",
  "properties": {
    "addr:full":"1 Avenue De Palarin 31120 Portet Sur Garonne Midi Pyr\u00e9n\u00e9es 31120",
    "addr:housenumber":"1",
    "addr:postcode":"31120;31120",
    "addr:street":"Avenue De Palarin",
    "iso:country":"FR",
    "sg:address":"1 Avenue De Palarin 31120 Portet Sur Garonne",
    "sg:classifiers":[
        {
            "category":"Autos & Motor Vehicles",
            "subcategory":"Automobile Sales",
            "type":"Retail Goods"
        }
    ],
    "sg:phone":"+33 5 61 72 80 90",
    "sg:postcode":"31120",
    "sg:province":"Midi Pyr\u00e9n\u00e9es",
    "sg:tags":[
        "equipment",
        "industrial",
        "transport"
    ],
    "wof:name":"Renault Vi (rvi)",
    "wof:placetype":"venue"
},
  "geometry": {"coordinates":[1.390644,43.524048],"type":"Point"}
}