{
  "type": "Feature",
  "properties": {
    "iso:country":"FR",
    "sg:address":"1, Rue du G\u00e9n\u00e9ral de Gaulle, 67520 Marlenheim",
    "sg:city":"Marlenheim",
    "sg:orig_category":"Unclassifiable Establishments",
    "sg:phone":"+33 3 88 87 69 79",
    "sg:postcode":"67520",
    "sg:province":"Alsace",
    "wof:name":"Alsa Remorques S.a.r.l.",
    "wof:placetype":"venue"
},
  "geometry": {"coordinates":[7.47717,48.621433],"type":"Point"}
}