{
  "type": "Feature",
  "properties": {
    "addr:full":"1, Rue du G\u00e9n\u00e9ral de Gaulle, 67520 Marlenheim Marlenheim Alsace 67520",
    "addr:housenumber":"1",
    "addr:postcode":"67520;67520",
    "addr:street":"Rue Du Ge\u0301Ne\u0301Ral De Gaulle",
    "iso:country":"FR",
    "sg:address":"1, Rue du G\u00e9n\u00e9ral de Gaulle, 67520 Marlenheim",
    "sg:city":"Marlenheim",
    "sg:orig_category":"Unclassifiable Establishments",
    "sg:phone":"+33 3 88 87 69 79",
    "sg:postcode":"67520",
    "sg:province":"Alsace",
    "wof:name":"Alsa Remorques S.a.r.l.",
    "wof:placetype":"venue"
},
  "geometry": {"coordinates":[7.47717,48.621433],"type":"Point"}
}