{
  "type": "Feature",
  "properties": {
    "iso:country":"FR",
    "sg:address":"rue Jean Rostand ZAL Foss\u00e9 10 62420 BILLY MONTIGNY",
    "sg:classifiers":[
        {
            "category":"Bus Stop",
            "subcategory":"None",
            "type":"Transportation"
        }
    ],
    "sg:phone":"+33 3 21 08 18 20",
    "sg:postcode":"62420",
    "sg:province":"Nord Pas-de-Calais",
    "sg:tags":[
        "omnibus",
        "car",
        "seat"
    ],
    "wof:name":"B.v. Productions Sa",
    "wof:placetype":"venue"
},
  "geometry": {"coordinates":[2.91168,50.413151],"type":"Point"}
}