{
  "type": "Feature",
  "properties": {
    "iso:country":"FR",
    "sg:address":"Les Noyers 41170 Souday",
    "sg:city":"Souday",
    "sg:orig_category":"Non-Classified Establishments",
    "sg:phone":"+33 2 54 80 74 17",
    "sg:postcode":"41170",
    "sg:province":"Centre",
    "wof:name":"Buschhoff Sylvie",
    "wof:placetype":"venue"
},
  "geometry": {"coordinates":[0.89086,48.04744],"type":"Point"}
}