{
  "type": "Feature",
  "properties": {
    "addr:full":"Za 35140 St Aubin Du Cormier Gosn\u00e9 Bretagne 35140",
    "addr:postcode":"35140;35140",
    "addr:street":"Za;St Aubin Du Cormier Gosne\u0301 Bretagne",
    "iso:country":"FR",
    "sg:address":"Za 35140 St Aubin Du Cormier",
    "sg:city":"Gosn\u00e9",
    "sg:classifiers":[
        {
            "category":"Shopping",
            "subcategory":"Clothing, Apparel, & Fashions",
            "type":"Retail Goods"
        }
    ],
    "sg:phone":"+33 2 99 39 10 94",
    "sg:postcode":"35140",
    "sg:province":"Bretagne",
    "sg:tags":[
        "textile",
        "clothing",
        "clothes"
    ],
    "wof:name":"Etablissements Michel Davenel",
    "wof:placetype":"venue"
},
  "geometry": {"coordinates":[-1.464616,48.246437],"type":"Point"}
}