{
  "type": "Feature",
  "properties": {
    "iso:country":"FR",
    "sg:address":"Ld Wirrenweg 68250 Pfaffenheim",
    "sg:city":"Pfaffenheim",
    "sg:classifiers":[
        {
            "category":"Shopping",
            "type":"Retail Goods"
        }
    ],
    "sg:phone":"+33 3 89 49 79 79",
    "sg:postcode":"68250",
    "sg:province":"Alsace",
    "sg:tags":[
        "metallurgy",
        "finished",
        "-",
        "metalworking",
        "metallic"
    ],
    "wof:name":"Atn Sarl",
    "wof:placetype":"venue"
},
  "geometry": {"coordinates":[7.296965,47.959679],"type":"Point"}
}