{
  "type": "Feature",
  "properties": {
    "addr:full":"136 Rue De La Republique 39400 Morez Franche Comt\u00e9 39400",
    "addr:housenumber":"136",
    "addr:postcode":"39400;39400",
    "addr:street":"Rue De La Republique;Franche Comte\u0301",
    "iso:country":"FR",
    "sg:address":"136 Rue De La Republique 39400 Morez",
    "sg:classifiers":[
        {
            "category":"Professional",
            "subcategory":"Engineering",
            "type":"Services"
        }
    ],
    "sg:phone":"+33 3 84 33 27 72",
    "sg:postcode":"39400",
    "sg:province":"Franche Comt\u00e9",
    "sg:tags":[
        "machine",
        "-",
        "jewellery",
        "mechanical"
    ],
    "wof:name":"Pesenti",
    "wof:placetype":"venue"
},
  "geometry": {"coordinates":[6.02158,46.523331],"type":"Point"}
}