{
  "type": "Feature",
  "properties": {
    "addr:full":"21, Rue de Clichy, 93584 Saint Ouen C\u00e9dex Ile de France",
    "addr:housenumber":"21",
    "addr:postcode":"93584;ce\u0301dex ile",
    "addr:street":"Rue De Clichy",
    "iso:country":"FR",
    "sg:address":"21, Rue de Clichy, 93584 Saint Ouen C\u00e9dex",
    "sg:orig_category":"Non-Classified Establishments",
    "sg:phone":"+33 1 49 45 44 55",
    "sg:province":"Ile de France",
    "wof:name":"His S.a.",
    "wof:placetype":"venue"
},
  "geometry": {"coordinates":[2.33167,48.90609],"type":"Point"}
}