{
  "type": "Feature",
  "properties": {
    "iso:country":"FR",
    "sg:address":"Av Du Tapis Vert 06220 Vallauris",
    "sg:classifiers":[
        {
            "category":"Manufacturing",
            "subcategory":"Building Materials",
            "type":"Manufacturing & Wholesale Goods"
        }
    ],
    "sg:phone":"+33 4 93 64 08 57",
    "sg:province":"Rhone-Alpes",
    "sg:tags":[
        "glass",
        "ceramic"
    ],
    "wof:name":"Mathieu Jean Marius Louis",
    "wof:placetype":"venue"
},
  "geometry": {"coordinates":[7.058306,43.578621],"type":"Point"}
}