{
  "type": "Feature",
  "properties": {
    "addr:full":"ZI de Prin Deyran\u00e7on Mauz\u00e9 sur le Mignon Poitou-Charentes 79210",
    "addr:postcode":"79210",
    "addr:street":"Zi De Prin Deyranc\u0327On Mauze\u0301 Sur Le Mignon",
    "iso:country":"FR",
    "sg:address":"ZI de Prin Deyran\u00e7on",
    "sg:city":"Mauz\u00e9 sur le Mignon",
    "sg:orig_category":"Unclassifiable Establishments",
    "sg:phone":"+33 5 49 26 77 33",
    "sg:postcode":"79210",
    "sg:province":"Poitou-Charentes",
    "wof:name":"G.c. Distribution S.a.r.l.",
    "wof:placetype":"venue"
},
  "geometry": {"coordinates":[-0.670804,46.195297],"type":"Point"}
}