{
  "type": "Feature",
  "properties": {
    "addr:full":"139 Av Du Promenoir 69400 Villefranche-Sur-Sa\u00f4ne Rhone-Alpes 69400",
    "addr:postcode":"69400;69400",
    "addr:street":"139 Av Du Promenoir",
    "iso:country":"FR",
    "sg:address":"139 Av Du Promenoir 69400 Villefranche-Sur-Sa\u00f4ne",
    "sg:classifiers":[
        {
            "category":"Professional",
            "subcategory":"Advertising",
            "type":"Services"
        }
    ],
    "sg:phone":"+33 4 74 62 89 89",
    "sg:postcode":"69400",
    "sg:province":"Rhone-Alpes",
    "sg:tags":[
        "information",
        "medium",
        "communication"
    ],
    "wof:name":"Regie Network Sa",
    "wof:placetype":"venue"
},
  "geometry": {"coordinates":[4.716636,45.98418],"type":"Point"}
}