{
  "type": "Feature",
  "properties": {
    "iso:country":"FR",
    "sg:address":"1327, Av. de la Houille Blanche, 73000 Chamb\u00e9ry",
    "sg:orig_category":"Unclassifiable Establishments",
    "sg:phone":"+33 4 74 27 59 00",
    "sg:postcode":"73000",
    "sg:province":"Rhone-Alpes",
    "wof:name":"S.a.t.m. S.a. - Soci\u00e9t\u00e9 Auxiliaire De Transport Et Manutention",
    "wof:placetype":"venue"
},
  "geometry": {"coordinates":[5.890109,45.587933],"type":"Point"}
}