{
  "type": "Feature",
  "properties": {
    "iso:country":"FR",
    "sg:address":"B.P. 1031, 69612 Villeurbanne C\u00e9dex^^199, Rte de Genas, 69100 Villeurbanne",
    "sg:orig_category":"Non-Classified Establishments",
    "sg:phone":"+33 4 72 34 08 08",
    "sg:province":"Rhone-Alpes",
    "wof:name":"S.e.r.g. S.a. - Soci\u00e9t\u00e9 D'etudes De R\u00e9alisations Et De Gestion S.a.",
    "wof:placetype":"venue"
},
  "geometry": {"coordinates":[4.87905,45.769596],"type":"Point"}
}