{
  "type": "Feature",
  "properties": {
    "addr:full":"21, Rue des Bintinais - ZA du Hill, 35230 Noyal Ch\u00e2tillon sur Seiche Bourgbarr\u00e9 Bretagne 35230",
    "addr:housenumber":"21",
    "addr:postcode":"35230;35230",
    "addr:street":"Rue Des Bintinais Za Du Hill",
    "iso:country":"FR",
    "sg:address":"21, Rue des Bintinais - ZA du Hill, 35230 Noyal Ch\u00e2tillon sur Seiche",
    "sg:city":"Bourgbarr\u00e9",
    "sg:orig_category":"Non-Classified Establishments",
    "sg:phone":"+33 2 99 32 06 31",
    "sg:postcode":"35230",
    "sg:province":"Bretagne",
    "wof:name":"Arm 2 S.a.r.l.",
    "wof:placetype":"venue"
},
  "geometry": {"coordinates":[-1.615554,47.99485],"type":"Point"}
}