{
  "type": "Feature",
  "properties": {
    "addr:full":"7, Rue des Canuts, 42390 Villars Rhone-Alpes",
    "addr:housenumber":"7",
    "addr:postcode":"42390",
    "addr:street":"Rue Des Canuts",
    "iso:country":"FR",
    "sg:address":"7, Rue des Canuts, 42390 Villars",
    "sg:orig_category":"Unclassifiable Establishments",
    "sg:phone":"+33 4 74 69 33 41",
    "sg:province":"Rhone-Alpes",
    "wof:name":"Sodipa S.a.",
    "wof:placetype":"venue"
},
  "geometry": {"coordinates":[4.369241,45.467319],"type":"Point"}
}