{
  "type": "Feature",
  "properties": {
    "iso:country":"FR",
    "sg:address":"113 Av Des Alli\u00e9s 62370 Audruicq",
    "sg:classifiers":[
        {
            "category":"Manufacturing",
            "subcategory":"Wood Products",
            "type":"Manufacturing & Wholesale Goods"
        }
    ],
    "sg:phone":"+33 3 21 35 78 24",
    "sg:province":"Nord Pas-de-Calais",
    "sg:tags":[
        "furniture"
    ],
    "wof:name":"Scierie Et Palettes Du Littoral",
    "wof:placetype":"venue"
},
  "geometry": {"coordinates":[2.0743,50.874378],"type":"Point"}
}