{
  "type": "Feature",
  "properties": {
    "iso:country":"FR",
    "sg:address":"6, Rue de la Grande Ourse, 95800 Cergy",
    "sg:orig_category":"Unclassifiable Establishments",
    "sg:phone":"+33 1 34 33 07 07",
    "sg:province":"Ile de France",
    "wof:name":"P.a. Technologies S.a.r.l.",
    "wof:placetype":"venue"
},
  "geometry": {"coordinates":[2.031225,49.053185],"type":"Point"}
}