{
  "type": "Feature",
  "properties": {
    "addr:full":"2, Av. du G\u00e9n\u00e9ral de Gaulle - Tour de Bureaux Rosny II, 93118 Rosny sous Bois C\u00e9dex Ile-de-France",
    "addr:postcode":"93118",
    "addr:street":"Av. Du Ge\u0301Ne\u0301Ral De Gaulle Tour De Bureaux",
    "iso:country":"FR",
    "sg:address":"2, Av. du G\u00e9n\u00e9ral de Gaulle - Tour de Bureaux Rosny II, 93118 Rosny sous Bois C\u00e9dex",
    "sg:orig_category":"Non-Classified Establishments",
    "sg:phone":"+33 1 48 54 90 00",
    "sg:province":"Ile-de-France",
    "wof:name":"R.i.i. Diffusion-liber S.a. - Relais Informatique International Diffusion",
    "wof:placetype":"venue"
},
  "geometry": {"coordinates":[2.482572,48.874428],"type":"Point"}
}