{
  "type": "Feature",
  "properties": {
    "iso:country":"FR",
    "sg:address":"283 Rue Guy Mocquet 59120 Loos",
    "sg:classifiers":[
        {
            "category":"Home & Garden",
            "subcategory":"Furniture",
            "type":"Retail Goods"
        }
    ],
    "sg:phone":"+33 3 20 07 73 67",
    "sg:postcode":"59120",
    "sg:province":"Nord Pas-de-Calais",
    "sg:tags":[
        "household",
        "wood"
    ],
    "wof:name":"Votre Maison Sa",
    "wof:placetype":"venue"
},
  "geometry": {"coordinates":[3.01704,50.606731],"type":"Point"}
}