{
  "type": "Feature",
  "properties": {
    "iso:country":"FR",
    "sg:address":"Cit\u00e9 Saint Lambin - ZI",
    "sg:city":"Maisonneuve",
    "sg:orig_category":"Unclassifiable Establishments",
    "sg:phone":"+33 5 49 51 00 33",
    "sg:postcode":"86170",
    "sg:province":"Poitou-Charentes",
    "wof:name":"G.i.t. S.a.",
    "wof:placetype":"venue"
},
  "geometry": {"coordinates":[0.267668,46.646358],"type":"Point"}
}