{
  "type": "Feature",
  "properties": {
    "iso:country":"FR",
    "sg:address":"17 rue de la T\u00e9l\u00e9matique 42000 ST ETIENNE",
    "sg:classifiers":[
        {
            "category":"Wholesale",
            "subcategory":"Hardware",
            "type":"Manufacturing & Wholesale Goods"
        }
    ],
    "sg:phone":"+33 4 77 74 10 75",
    "sg:postcode":"42000",
    "sg:province":"Rhone-Alpes",
    "sg:tags":[
        "anti-virus"
    ],
    "wof:name":"Ravial Sa",
    "wof:placetype":"venue"
},
  "geometry": {"coordinates":[4.393473,45.455849],"type":"Point"}
}