{
  "type": "Feature",
  "properties": {
    "iso:country":"FR",
    "sg:address":"34 Av Bois Baudran 13015 Marseille",
    "sg:classifiers":[
        {
            "category":"Shopping",
            "subcategory":"Bicycles & Sporting Goods",
            "type":"Retail Goods"
        }
    ],
    "sg:phone":"+33 4 91 09 44 63",
    "sg:province":"Poitou-Charentes",
    "sg:tags":[
        "product",
        "sport",
        "miscellaneous"
    ],
    "wof:name":"Beuchat International Sa",
    "wof:placetype":"venue"
},
  "geometry": {"coordinates":[5.366296,43.341312],"type":"Point"}
}