{
  "type": "Feature",
  "properties": {
    "iso:country":"FR",
    "sg:address":"B.P. 17, 89160 Ancy le Franc^^ZI, 89160 Ancy le Franc",
    "sg:city":"Ancy-le-Franc",
    "sg:orig_category":"Non-Classified Establishments",
    "sg:phone":"+33 3 86 75 14 42",
    "sg:postcode":"89160",
    "sg:province":"Bourgogne",
    "wof:name":"T\u00f4lerie M\u00e9canique Service S.a.r.l.",
    "wof:placetype":"venue"
},
  "geometry": {"coordinates":[4.17095,47.772911],"type":"Point"}
}