{
  "type": "Feature",
  "properties": {
    "iso:country":"FR",
    "sg:address":"73, Av. de la Perri\u00e8re, 56100 Lorient",
    "sg:city":"Lorient",
    "sg:orig_category":"Unclassifiable Establishments",
    "sg:phone":"+33 2 97 87 94 14",
    "sg:postcode":"56100",
    "sg:province":"Bretagne",
    "wof:name":"Seastem S.a.",
    "wof:placetype":"venue"
},
  "geometry": {"coordinates":[-3.363606,47.731842],"type":"Point"}
}