{
  "type": "Feature",
  "properties": {
    "iso:country":"FR",
    "sg:address":"45, Quai du Sablot, 40300 Peyrehorade",
    "sg:city":"Peyrehorade",
    "sg:orig_category":"Unclassifiable Establishments",
    "sg:phone":"+33 5 58 73 02 50",
    "sg:postcode":"40300",
    "sg:province":"Aquitaine",
    "wof:name":"Innodec E.u.r.l.",
    "wof:placetype":"venue"
},
  "geometry": {"coordinates":[-1.103969,43.543819],"type":"Point"}
}