{
  "type": "Feature",
  "properties": {
    "addr:full":"Route De St Etienne Les Vincents 42210 Montrond Les Bains Rhone-Alpes",
    "addr:postcode":"42210",
    "addr:street":"Route De St Etienne Les Vincents",
    "iso:country":"FR",
    "sg:address":"Route De St Etienne Les Vincents 42210 Montrond Les Bains",
    "sg:classifiers":[
        {
            "category":"Manufacturing",
            "subcategory":"Rubber & Plastics",
            "type":"Manufacturing & Wholesale Goods"
        }
    ],
    "sg:phone":"+33 4 77 94 54 71",
    "sg:province":"Rhone-Alpes",
    "wof:name":"Tout Production",
    "wof:placetype":"venue"
},
  "geometry": {"coordinates":[4.237527,45.636681],"type":"Point"}
}