{
  "type": "Feature",
  "properties": {
    "addr:full":"ZA Le clou \u00e0 crochet 91321 WISSOUS CEDEX Ile de France",
    "addr:postcode":"91321;ile",
    "addr:street":"Za Le;A\u0300 Crochet",
    "iso:country":"FR",
    "sg:address":"ZA Le clou \u00e0 crochet 91321 WISSOUS CEDEX",
    "sg:classifiers":[
        {
            "category":"Manufacturing",
            "subcategory":"Motor Vehicles & Parts",
            "type":"Manufacturing & Wholesale Goods"
        }
    ],
    "sg:phone":"+33 1 69 30 76 58",
    "sg:province":"Ile de France",
    "sg:tags":[
        "precision",
        "mechanic"
    ],
    "wof:name":"A.m.a. Sa",
    "wof:placetype":"venue"
},
  "geometry": {"coordinates":[2.32314,48.727646],"type":"Point"}
}