{
  "type": "Feature",
  "properties": {
    "addr:full":"Rte d'Escalquens - ZI de Vic Castanet Tolosan Midi Pyr\u00e9n\u00e9es 31320",
    "addr:postcode":"31320",
    "addr:street":"Rte D'Escalquens Zi De Vic",
    "iso:country":"FR",
    "sg:address":"Rte d'Escalquens - ZI de Vic",
    "sg:city":"Castanet Tolosan",
    "sg:orig_category":"Unclassifiable Establishments",
    "sg:phone":"+33 5 34 66 60 50",
    "sg:postcode":"31320",
    "sg:province":"Midi Pyr\u00e9n\u00e9es",
    "wof:name":"Station Diesel S.a.r.l.",
    "wof:placetype":"venue"
},
  "geometry": {"coordinates":[1.4773,43.502739],"type":"Point"}
}