{
  "type": "Feature",
  "properties": {
    "iso:country":"FR",
    "sg:address":"Rue Ren\u00e9 Cassin Zi Des Lauves 83340 Le Luc",
    "sg:classifiers":[
        {
            "category":"Transit Center",
            "subcategory":"Freight",
            "type":"Transportation"
        }
    ],
    "sg:phone":"+33 4 94 50 06 20",
    "sg:province":"Champagne",
    "sg:tags":[
        "metallurgy",
        "pipe",
        "metalworking",
        "sheet"
    ],
    "wof:name":"Armafor",
    "wof:placetype":"venue"
},
  "geometry": {"coordinates":[6.356552,43.315964],"type":"Point"}
}