{
  "type": "Feature",
  "properties": {
    "addr:full":"Rue de la Croix Ignon Mordelles Bretagne 35310",
    "addr:postcode":"35310",
    "addr:street":"Rue De La Croix Ignon Mordelles Bretagne",
    "iso:country":"FR",
    "sg:address":"Rue de la Croix Ignon",
    "sg:city":"Mordelles",
    "sg:orig_category":"Unclassifiable Establishments",
    "sg:phone":"+33 2 99 85 13 63",
    "sg:postcode":"35310",
    "sg:province":"Bretagne",
    "wof:name":"La Vaunoise S.a.",
    "wof:placetype":"venue"
},
  "geometry": {"coordinates":[-1.831834,48.08255],"type":"Point"}
}