{
  "type": "Feature",
  "properties": {
    "addr:full":"R Des Dunes 59820 Gravelines Nord Pas-de-Calais 59820",
    "addr:postcode":"59820;59820",
    "addr:street":"Gravelines Nord",
    "iso:country":"FR",
    "sg:address":"R Des Dunes 59820 Gravelines",
    "sg:classifiers":[
        {
            "category":"Shopping",
            "type":"Retail Goods"
        }
    ],
    "sg:phone":"+33 3 28 51 82 00",
    "sg:postcode":"59820",
    "sg:province":"Nord Pas-de-Calais",
    "sg:tags":[
        "metallurgy",
        "finished",
        "-",
        "metalworking",
        "metallic"
    ],
    "wof:name":"Tarlin Et Fils Sa",
    "wof:placetype":"venue"
},
  "geometry": {"coordinates":[2.153448,51.000195],"type":"Point"}
}