{
  "type": "Feature",
  "properties": {
    "addr:full":"B.P. 78, 33520 Bruges^^469, Rte du M\u00e9doc, 33520 Bruges Bruges Aquitaine 33520",
    "addr:postcode":"33520;33520;33520",
    "addr:street":"B.P. 78;Rte Du Me\u0301Doc",
    "iso:country":"FR",
    "sg:address":"B.P. 78, 33520 Bruges^^469, Rte du M\u00e9doc, 33520 Bruges",
    "sg:city":"Bruges",
    "sg:orig_category":"Non-Classified Establishments",
    "sg:phone":"+33 5 56 57 41 00",
    "sg:postcode":"33520",
    "sg:province":"Aquitaine",
    "wof:name":"Soci\u00e9t\u00e9 Pigeon A. S.a.",
    "wof:placetype":"venue"
},
  "geometry": {"coordinates":[-0.610265,44.887768],"type":"Point"}
}