{
  "type": "Feature",
  "properties": {
    "addr:full":"9 Rte De Paris 41100 St Ouen Lisle Centre 41100",
    "addr:housenumber":"9",
    "addr:postcode":"41100;41100",
    "addr:street":"Rte De Paris;St;Lisle",
    "iso:country":"FR",
    "sg:address":"9 Rte De Paris 41100 St Ouen",
    "sg:city":"Lisle",
    "sg:classifiers":[
        {
            "category":"Shopping",
            "subcategory":"Computers & Home Electronics",
            "type":"Retail Goods"
        }
    ],
    "sg:phone":"+33 2 54 73 30 00",
    "sg:postcode":"41100",
    "sg:province":"Centre",
    "sg:tags":[
        "equipment",
        "household",
        "electrical",
        "appliance",
        "electronic"
    ],
    "wof:name":"Bronte Industries Sa",
    "wof:placetype":"venue"
},
  "geometry": {"coordinates":[1.072066,47.805874],"type":"Point"}
}