{
  "type": "Feature",
  "properties": {
    "iso:country":"FR",
    "sg:address":"8 Rue De L'Industrie Zi Des Pontots 2 64600 Anglet",
    "sg:city":"Anglet",
    "sg:classifiers":[
        {
            "category":"Wholesale",
            "subcategory":"Chemicals & Plastics",
            "type":"Manufacturing & Wholesale Goods"
        }
    ],
    "sg:phone":"+33 5 59 63 01 44",
    "sg:postcode":"64600",
    "sg:province":"Aquitaine",
    "sg:tags":[
        "pharmaceutical",
        "cardboard",
        "-",
        "fini",
        "paper",
        "chemistry",
        "by-product"
    ],
    "wof:name":"Laplace Sa",
    "wof:placetype":"venue"
},
  "geometry": {"coordinates":[-1.500192,43.493908],"type":"Point"}
}