{
  "type": "Feature",
  "properties": {
    "iso:country":"FR",
    "sg:address":"4 Rte De L'Espace 44690 La Haie Fouassi\u00e8re",
    "sg:classifiers":[
        {
            "category":"Manufacturing",
            "subcategory":"Rubber & Plastics",
            "type":"Manufacturing & Wholesale Goods"
        }
    ],
    "sg:phone":"+33 2 40 54 86 90",
    "sg:province":"Pays de Loire",
    "wof:name":"La Vendeenne De Distribution",
    "wof:placetype":"venue"
},
  "geometry": {"coordinates":[-1.39343,47.166367],"type":"Point"}
}