{
  "type": "Feature",
  "properties": {
    "addr:full":"2, Rue de la Sauer, 67510 Lembach Lembach Alsace 67510",
    "addr:housenumber":"2",
    "addr:postcode":"67510;67510",
    "addr:street":"Rue De La Sauer",
    "iso:country":"FR",
    "sg:address":"2, Rue de la Sauer, 67510 Lembach",
    "sg:city":"Lembach",
    "sg:orig_category":"Unclassifiable Establishments",
    "sg:phone":"+33 3 88 94 42 97",
    "sg:postcode":"67510",
    "sg:province":"Alsace",
    "wof:name":"Ehrstein Ernest Scierie S.a.r.l.",
    "wof:placetype":"venue"
},
  "geometry": {"coordinates":[7.787109,49.00536],"type":"Point"}
}