{
  "type": "Feature",
  "properties": {
    "addr:full":"Espace Industriel les Muriers Digoin Bourgogne 71160",
    "addr:postcode":"71160",
    "addr:street":"Bourgogne",
    "iso:country":"FR",
    "sg:address":"Espace Industriel les Muriers",
    "sg:city":"Digoin",
    "sg:orig_category":"Non-Classified Establishments",
    "sg:phone":"+33 3 85 53 20 24",
    "sg:postcode":"71160",
    "sg:province":"Bourgogne",
    "wof:name":"Transports Digonnais S.a.r.l.",
    "wof:placetype":"venue"
},
  "geometry": {"coordinates":[3.977895,46.481796],"type":"Point"}
}