{
  "type": "Feature",
  "properties": {
    "iso:country":"FR",
    "sg:address":"ZI Les Carrieres Lieu Dit Le Champ 72400 Cherr\u00e9",
    "sg:classifiers":[
        {
            "category":"Manufacturing",
            "subcategory":"Motor Vehicles & Parts",
            "type":"Manufacturing & Wholesale Goods"
        }
    ],
    "sg:phone":"+33 2 43 93 62 39",
    "sg:province":"Pays de Loire",
    "sg:tags":[
        "precision",
        "mechanic"
    ],
    "wof:name":"Realisations Gallois Duguet Sa",
    "wof:placetype":"venue"
},
  "geometry": {"coordinates":[0.65629,48.173904],"type":"Point"}
}