{
  "type": "Feature",
  "properties": {
    "iso:country":"FR",
    "sg:address":"40 Rue Ernest Solvay 57430 Sarralbe",
    "sg:classifiers":[
        {
            "category":"Manufacturing",
            "subcategory":"Rubber & Plastics",
            "type":"Manufacturing & Wholesale Goods"
        }
    ],
    "sg:phone":"+33 3 87 87 70 00",
    "sg:province":"Lorraine",
    "wof:name":"Solvay Polyolefins Europe France Sa",
    "wof:placetype":"venue"
},
  "geometry": {"coordinates":[7.033955,49.011108],"type":"Point"}
}