{
  "type": "Feature",
  "properties": {
    "addr:full":"Rte De Clary 59225 Montigny En Cambr\u00e9sis Nord Pas-de-Calais 59225",
    "addr:postcode":"59225;59225",
    "addr:street":"Rte De Clary;Pas-De-Calais",
    "iso:country":"FR",
    "sg:address":"Rte De Clary 59225 Montigny En Cambr\u00e9sis",
    "sg:classifiers":[
        {
            "category":"Wholesale",
            "subcategory":"Machinery & Supplies",
            "type":"Manufacturing & Wholesale Goods"
        }
    ],
    "sg:phone":"+33 3 27 85 31 10",
    "sg:postcode":"59225",
    "sg:province":"Nord Pas-de-Calais",
    "sg:tags":[
        "food",
        "processing",
        "-",
        "machine",
        "equipment",
        "engineering",
        "mechanical"
    ],
    "wof:name":"Bodson Industrie Sa",
    "wof:placetype":"venue"
},
  "geometry": {"coordinates":[3.403578,50.095036],"type":"Point"}
}