{
  "type": "Feature",
  "properties": {
    "addr:full":"31, Av de Flandre, 59491 Villeneuve d'Ascq Nord Pas-de-Calais",
    "addr:postcode":"59491",
    "addr:street":"31 Av De Flandre",
    "iso:country":"FR",
    "sg:address":"31, Av de Flandre, 59491 Villeneuve d'Ascq",
    "sg:orig_category":"Unclassifiable Establishments",
    "sg:phone":"+33 3 20 72 32 12",
    "sg:province":"Nord Pas-de-Calais",
    "wof:name":"Diagoras Jean & Pierre S.a.",
    "wof:placetype":"venue"
},
  "geometry": {"coordinates":[2.361394,49.27264],"type":"Point"}
}