{
  "type": "Feature",
  "properties": {
    "iso:country":"FR",
    "sg:address":"Rue Eugene Chimont 59168 Boussois",
    "sg:classifiers":[
        {
            "category":"Manufacturing",
            "subcategory":"Glass & Minerals",
            "type":"Manufacturing & Wholesale Goods"
        }
    ],
    "sg:phone":"+33 3 27 69 39 40",
    "sg:postcode":"59168",
    "sg:province":"Nord Pas-de-Calais",
    "sg:tags":[
        "building",
        "material"
    ],
    "wof:name":"Glaverbel France Sa",
    "wof:placetype":"venue"
},
  "geometry": {"coordinates":[4.028315,50.289188],"type":"Point"}
}