{
  "type": "Feature",
  "properties": {
    "iso:country":"FR",
    "sg:address":"B.P. 3103, 17033 La Rochelle Cedex 1^^Rue de la Trinquette - Le Sextant , 17000 La Rochelle",
    "sg:orig_category":"Non-Classified Establishments",
    "sg:phone":"+33 5 46 50 50 30",
    "sg:province":"Poitou-Charentes",
    "wof:name":"Pharos S.a.",
    "wof:placetype":"venue"
},
  "geometry": {"coordinates":[-1.151639,46.159435],"type":"Point"}
}