{
  "type": "Feature",
  "properties": {
    "iso:country":"FR",
    "sg:address":"Vozerier Nord",
    "sg:city":"de Bonneville 74800 Amancy",
    "sg:classifiers":[
        {
            "category":"Manufacturing",
            "subcategory":"Metals",
            "type":"Manufacturing & Wholesale Goods"
        }
    ],
    "sg:phone":"+33 4 50 03 03 16",
    "sg:postcode":"74800",
    "sg:province":"Rhone-Alpes",
    "sg:tags":[
        "metallurgy",
        "metalworking",
        "processing"
    ],
    "wof:name":"Anselme Marmoux Et Fils",
    "wof:placetype":"venue"
},
  "geometry": {"coordinates":[6.357741,46.047504],"type":"Point"}
}