{
  "type": "Feature",
  "properties": {
    "iso:country":"FR",
    "sg:address":"Rte D'Eu 76340 Blangy Sur Bresle",
    "sg:classifiers":[
        {
            "category":"Shopping",
            "type":"Retail Goods"
        }
    ],
    "sg:phone":"+33 2 32 97 44 00",
    "sg:postcode":"76340",
    "sg:province":"Haute Normandie",
    "sg:tags":[
        "metallurgy",
        "finished",
        "-",
        "metalworking",
        "metallic"
    ],
    "wof:name":"Sas Metra Moules De Verrerie",
    "wof:placetype":"venue"
},
  "geometry": {"coordinates":[1.620914,49.933704],"type":"Point"}
}