{
  "type": "Feature",
  "properties": {
    "iso:country":"FR",
    "sg:address":"Zi Echarnasses 01200 Ch\u00e2tillon En Michaille",
    "sg:classifiers":[
        {
            "category":"Manufacturing",
            "subcategory":"Paper Products",
            "type":"Manufacturing & Wholesale Goods"
        }
    ],
    "sg:phone":"+33 4 50 56 64 04",
    "sg:province":"Rhone-Alpes",
    "sg:tags":[
        "raw",
        "material",
        "-",
        "cardboard"
    ],
    "wof:name":"Sas Cartonnages Cr",
    "wof:placetype":"venue"
},
  "geometry": {"coordinates":[5.79882,46.144123],"type":"Point"}
}