{
  "type": "Feature",
  "properties": {
    "addr:full":"19 Chemin De Ronde 74200 Thonon Les Bains Rhone-Alpes",
    "addr:housenumber":"19",
    "addr:postcode":"74200",
    "addr:street":"Chemin De Ronde",
    "iso:country":"FR",
    "sg:address":"19 Chemin De Ronde 74200 Thonon Les Bains",
    "sg:classifiers":[
        {
            "category":"Professional",
            "type":"Services"
        }
    ],
    "sg:phone":"+33 4 50 71 01 57",
    "sg:province":"Rhone-Alpes",
    "sg:tags":[
        "transport",
        "road"
    ],
    "wof:name":"Transports Morel Et Cie Sarl",
    "wof:placetype":"venue"
},
  "geometry": {"coordinates":[6.484684,46.36982],"type":"Point"}
}