{
  "type": "Feature",
  "properties": {
    "addr:full":"47, Av. de la Colombi\u00e8re, 74950 Scionzier Rhone-Alpes 74950",
    "addr:postcode":"74950;74950",
    "addr:street":"47 Av. De La Colombie\u0300Re;Rhone-Alpes",
    "iso:country":"FR",
    "sg:address":"47, Av. de la Colombi\u00e8re, 74950 Scionzier",
    "sg:orig_category":"Non-Classified Establishments",
    "sg:phone":"+33 4 50 98 09 22",
    "sg:postcode":"74950",
    "sg:province":"Rhone-Alpes",
    "wof:name":"A.d.i. S.a. - Arve D\u00e9colletage Ithier",
    "wof:placetype":"venue"
},
  "geometry": {"coordinates":[6.554605,46.052879],"type":"Point"}
}