{
  "type": "Feature",
  "properties": {
    "addr:full":"4 Rue Des Girondins 69007 Lyon Rhone-Alpes 69007",
    "addr:housenumber":"4",
    "addr:postcode":"69007;69007",
    "addr:street":"Rue Des Girondins",
    "iso:country":"FR",
    "sg:address":"4 Rue Des Girondins 69007 Lyon",
    "sg:classifiers":[
        {
            "category":"Professional",
            "subcategory":"Engineering",
            "type":"Services"
        }
    ],
    "sg:phone":"+33 4 72 71 51 10",
    "sg:postcode":"69007",
    "sg:province":"Rhone-Alpes",
    "sg:tags":[
        "machine",
        "-",
        "mechanical"
    ],
    "wof:name":"Lyfrig Sa",
    "wof:placetype":"venue"
},
  "geometry": {"coordinates":[4.82664,45.739529],"type":"Point"}
}