{
  "type": "Feature",
  "properties": {
    "iso:country":"FR",
    "sg:address":"2 Rte Moussey 88210 La Petite Raon",
    "sg:classifiers":[
        {
            "category":"Manufacturing",
            "subcategory":"Rubber & Plastics",
            "type":"Manufacturing & Wholesale Goods"
        }
    ],
    "sg:phone":"+33 3 29 52 60 60",
    "sg:province":"Lorraine",
    "wof:name":"Np Vosges",
    "wof:placetype":"venue"
},
  "geometry": {"coordinates":[6.999795,48.413376],"type":"Point"}
}