{
  "type": "Feature",
  "properties": {
    "iso:country":"FR",
    "sg:address":"10 R Du Puits Rochefort 42100 St Etienne",
    "sg:classifiers":[
        {
            "category":"Building & Trades",
            "subcategory":"Construction",
            "type":"Services"
        }
    ],
    "sg:phone":"+33 4 77 37 61 32",
    "sg:postcode":"42100",
    "sg:province":"Rhone-Alpes",
    "sg:tags":[
        "work",
        "public"
    ],
    "wof:name":"Assainissement Construction Bost Acb",
    "wof:placetype":"venue"
},
  "geometry": {"coordinates":[4.374002,45.427441],"type":"Point"}
}