{
  "type": "Feature",
  "properties": {
    "iso:country":"FR",
    "sg:address":"B.P. 1215, 13783 Aubagne C\u00e9dex^^75, Av. de la Roubine - ZI les Paluds, 13400 Aubagne",
    "sg:orig_category":"Non-Classified Establishments",
    "sg:phone":"+33 4 42 72 62 31",
    "sg:province":"Provence-Alpes-C\u00f4te d'Azur",
    "wof:name":"Rh\u00f4ne Elastom\u00e8res S.a.r.l.",
    "wof:placetype":"venue"
},
  "geometry": {"coordinates":[5.5687,43.292141],"type":"Point"}
}