{
  "type": "Feature",
  "properties": {
    "addr:full":"2 Rue Du Petit Albi Parc D'Activit\u00e9s De Cergy 95800 Cergy Ile de France 95800",
    "addr:housenumber":"2",
    "addr:postcode":"95800;ile;95800",
    "addr:street":"Rue Du Petit Albi Parc D'Activite \u0301S De Cergy;France",
    "iso:country":"FR",
    "sg:address":"2 Rue Du Petit Albi Parc D'Activit\u00e9s De Cergy 95800 Cergy",
    "sg:classifiers":[
        {
            "category":"Professional",
            "subcategory":"Computer Services",
            "type":"Services"
        }
    ],
    "sg:phone":"+33 1 30 73 70 70",
    "sg:postcode":"95800",
    "sg:province":"Ile de France",
    "sg:tags":[
        "information",
        "technology",
        "software"
    ],
    "wof:name":"Sagem Sa",
    "wof:placetype":"venue"
},
  "geometry": {"coordinates":[2.045561,49.053944],"type":"Point"}
}