{
  "type": "Feature",
  "properties": {
    "addr:full":"6 Rue De S\u00e9vign\u00e9 92120 Montrouge Ile de France 92120",
    "addr:housenumber":"6",
    "addr:postcode":"92120;92120",
    "addr:street":"Rue De Se\u0301Vigne\u0301",
    "iso:country":"FR",
    "sg:address":"6 Rue De S\u00e9vign\u00e9 92120 Montrouge",
    "sg:orig_category":"Gifts Miscellaneous Products Printing Printing and Publishing",
    "sg:phone":"+33 1 47 46 08 82",
    "sg:postcode":"92120",
    "sg:province":"Ile de France",
    "wof:name":"Collecti Livres Grossiste Sarl",
    "wof:placetype":"venue"
},
  "geometry": {"coordinates":[2.315339,48.812565],"type":"Point"}
}