{
  "type": "Feature",
  "properties": {
    "addr:full":"19, Rue des T\u00e2ches, 69800 Saint Priest Rhone-Alpes 69800",
    "addr:housenumber":"19",
    "addr:postcode":"69800;69800",
    "addr:street":"Rue Des Ta\u0302Ches;Priest Rhone-Alpes",
    "iso:country":"FR",
    "sg:address":"19, Rue des T\u00e2ches, 69800 Saint Priest",
    "sg:orig_category":"Non-Classified Establishments",
    "sg:phone":"+33 4 72 79 23 23",
    "sg:postcode":"69800",
    "sg:province":"Rhone-Alpes",
    "wof:name":"S.r.m.e. S.a.r.l.",
    "wof:placetype":"venue"
},
  "geometry": {"coordinates":[4.97224,45.716179],"type":"Point"}
}