{
  "type": "Feature",
  "properties": {
    "iso:country":"FR",
    "sg:address":"B.P. 31, 83088 La Garde C\u00e9dex^^1485, Av. de Draguignan - ZI Toulon Est, 83130 La Garde",
    "sg:city":"La Garde",
    "sg:orig_category":"Non-Classified Establishments",
    "sg:phone":"+33 4 94 75 94 64",
    "sg:postcode":"38520",
    "sg:province":"Rhone-Alpes",
    "wof:name":"Cedeo",
    "wof:placetype":"venue"
},
  "geometry": {"coordinates":[6.009775,43.124866],"type":"Point"}
}