{
  "type": "Feature",
  "properties": {
    "addr:full":"15 rue du Louvre, 75001 Paris, Dept 75 Ile de France 75001",
    "addr:housenumber":"15;75",
    "addr:postcode":"75001;75001",
    "addr:street":"Rue Du Louvre;Ile De France",
    "iso:country":"FR",
    "sg:address":"15 rue du Louvre, 75001 Paris, Dept 75",
    "sg:classifiers":[
        {
            "category":"Banks & Credit Unions",
            "subcategory":"Bank",
            "type":"Services"
        }
    ],
    "sg:phone":"+33 1 44 76 14 14",
    "sg:postcode":"75001",
    "sg:province":"Ile de France",
    "wof:name":"Alfi Gestion (securities House)",
    "wof:placetype":"venue"
},
  "geometry": {"coordinates":[2.497293,48.809368],"type":"Point"}
}