{
  "type": "Feature",
  "properties": {
    "addr:full":"9, Rue de la Durance, 67100 Strasbourg Strasbourg Alsace 67100",
    "addr:housenumber":"9",
    "addr:postcode":"67100;67100",
    "addr:street":"Rue De La Durance",
    "iso:country":"FR",
    "sg:address":"9, Rue de la Durance, 67100 Strasbourg",
    "sg:city":"Strasbourg",
    "sg:orig_category":"Unclassifiable Establishments",
    "sg:phone":"+33 3 88 65 79 30",
    "sg:postcode":"67100",
    "sg:province":"Alsace",
    "wof:name":"Etablissements Magnette Et Compagnie S.a.",
    "wof:placetype":"venue"
},
  "geometry": {"coordinates":[7.734442,48.553059],"type":"Point"}
}