{
  "type": "Feature",
  "properties": {
    "iso:country":"FR",
    "sg:address":"59, Rue des Ch\u00e2latres, 44000 Nantes",
    "sg:orig_category":"Non-Classified Establishments",
    "sg:phone":"+33 2 40 74 85 16",
    "sg:province":"Pays de Loire",
    "wof:name":"Office G\u00e9n\u00e9ral De Publications S.a.r.l.",
    "wof:placetype":"venue"
},
  "geometry": {"coordinates":[-1.53398,47.228836],"type":"Point"}
}