{
  "type": "Feature",
  "properties": {
    "addr:full":"13 rue Jacques Tati 69120 Vaulx en Velin Rhone-Alpes 69120",
    "addr:housenumber":"13",
    "addr:postcode":"69120;69120",
    "addr:street":"Rue Jacques Tati",
    "iso:country":"FR",
    "sg:address":"13 rue Jacques Tati 69120 Vaulx en Velin",
    "sg:classifiers":[
        {
            "category":"Wholesale",
            "subcategory":"Metals & Minerals",
            "type":"Manufacturing & Wholesale Goods"
        }
    ],
    "sg:phone":"+33 4 72 81 26 00",
    "sg:postcode":"69120",
    "sg:province":"Rhone-Alpes",
    "sg:tags":[
        "articles",
        "industrial"
    ],
    "wof:name":"Ste Indus Lyonnaise Articles Metalliques Sa",
    "wof:placetype":"venue"
},
  "geometry": {"coordinates":[4.930115,45.751122],"type":"Point"}
}