{
  "type": "Feature",
  "properties": {
    "iso:country":"FR",
    "sg:address":"70, Av. Kl\u00e9ber, 75784 Paris C\u00e9dex",
    "sg:orig_category":"Non-Classified Establishments",
    "sg:phone":"+33 1 47 55 02 02",
    "sg:province":"\u00cele-de-France",
    "wof:name":"T.h.e.d. International S.a. - Tourisme H\u00f4tellerie Engineering D\u00e9veloppement",
    "wof:placetype":"venue"
},
  "geometry": {"coordinates":[2.290169,48.867653],"type":"Point"}
}