{
  "type": "Feature",
  "properties": {
    "iso:country":"FR",
    "sg:address":"B.P. 213, 37702 Saint Pierre des Corps C\u00e9dex^^101, Av. Yves Farge - ZI des Yvaudi\u00e8res, 37700 Saint P",
    "sg:city":"La Ville-aux-Dames",
    "sg:orig_category":"Non-Classified Establishments",
    "sg:phone":"+33 2 47 32 45 45",
    "sg:postcode":"37700",
    "sg:province":"Centre",
    "wof:name":"Vitamotor S.a.",
    "wof:placetype":"venue"
},
  "geometry": {"coordinates":[0.7716,47.395424],"type":"Point"}
}