{
  "type": "Feature",
  "properties": {
    "addr:full":"Rte De Bailly BP 60209 60772 Ribecourt Cedex Haute Normandie",
    "addr:housenumber":"60772",
    "addr:postcode":"ribecourt cedex",
    "addr:street":"Rte De Bailly Bp 60209",
    "iso:country":"FR",
    "sg:address":"Rte De Bailly BP 60209 60772 Ribecourt Cedex",
    "sg:classifiers":[
        {
            "category":"Manufacturing",
            "subcategory":"Chemicals & Compounds",
            "type":"Manufacturing & Wholesale Goods"
        }
    ],
    "sg:phone":"+33 3 44 75 75 75",
    "sg:province":"Haute Normandie",
    "sg:tags":[
        "pharmaceutical",
        "chemistry",
        "-",
        "by-product"
    ],
    "wof:name":"Bostik Findley Sa",
    "wof:placetype":"venue"
},
  "geometry": {"coordinates":[2.92245,49.509701],"type":"Point"}
}