{
  "type": "Feature",
  "properties": {
    "addr:full":"Domaine De Ribonnet 31870 Beaumont Sur Leze Midi Pyr\u00e9n\u00e9es 31870",
    "addr:postcode":"31870;31870",
    "iso:country":"FR",
    "sg:address":"Domaine De Ribonnet 31870 Beaumont Sur Leze",
    "sg:classifiers":[
        {
            "category":"Food Court",
            "type":"Food & Drink"
        }
    ],
    "sg:phone":"+33 5 61 08 71 02",
    "sg:postcode":"31870",
    "sg:province":"Midi Pyr\u00e9n\u00e9es",
    "sg:tags":[
        "product",
        "related"
    ],
    "wof:name":"Societe A Responsabilite Limitee Vallees Et Terroirs (sarl Vallees Et Terroirs)",
    "wof:placetype":"venue"
},
  "geometry": {"coordinates":[1.320805,43.388115],"type":"Point"}
}