{
  "type": "Feature",
  "properties": {
    "iso:country":"FR",
    "sg:address":"51 rue Herv\u00e9 de Gu\u00e9briant 29800 Landerneau",
    "sg:city":"Landerneau",
    "sg:classifiers":[
        {
            "category":"Wholesale",
            "subcategory":"Machinery & Supplies",
            "type":"Manufacturing & Wholesale Goods"
        }
    ],
    "sg:phone":"+33 2 98 85 12 29",
    "sg:postcode":"29800",
    "sg:province":"Bretagne",
    "sg:tags":[
        "agricultural",
        "equipment"
    ],
    "wof:name":"Galvelpor S.a.",
    "wof:placetype":"venue"
},
  "geometry": {"coordinates":[-4.268845,48.448219],"type":"Point"}
}