{
  "type": "Feature",
  "properties": {
    "addr:full":"35Z I Lyon Nord 69727 GENAY CEDEX Champagne",
    "addr:housenumber":"35z",
    "addr:postcode":"69727",
    "addr:street":"I Lyon Nord",
    "iso:country":"FR",
    "sg:address":"35Z I Lyon Nord 69727 GENAY CEDEX",
    "sg:classifiers":[
        {
            "category":"Manufacturing",
            "subcategory":"Chemicals & Compounds",
            "type":"Manufacturing & Wholesale Goods"
        }
    ],
    "sg:phone":"+33 4 72 08 20 00",
    "sg:province":"Champagne",
    "sg:tags":[
        "industrial"
    ],
    "wof:name":"Ste Coatex S.a.",
    "wof:placetype":"venue"
},
  "geometry": {"coordinates":[4.84135,45.897861],"type":"Point"}
}