{
  "type": "Feature",
  "properties": {
    "iso:country":"FR",
    "sg:address":"18 Boulevard Paumont 13015 Marseille",
    "sg:classifiers":[
        {
            "category":"Professional",
            "subcategory":"Engineering",
            "type":"Services"
        }
    ],
    "sg:phone":"+33 4 91 60 93 58",
    "sg:province":"Poitou-Charentes",
    "sg:tags":[
        "machine",
        "-",
        "mechanical"
    ],
    "wof:name":"Atelier De Reparations Industrielles Et Maritimes (arim)",
    "wof:placetype":"venue"
},
  "geometry": {"coordinates":[5.37278,43.344948],"type":"Point"}
}