{
  "type": "Feature",
  "properties": {
    "iso:country":"FR",
    "sg:address":"Rte d'Issoudun",
    "sg:city":"Bourges",
    "sg:orig_category":"Unclassifiable Establishments",
    "sg:phone":"+33 2 48 67 80 80",
    "sg:postcode":"18000",
    "sg:province":"Centre",
    "wof:name":"C.c.i. Du Cher - Chambre De Commerce Et D'industrie Du Cher",
    "wof:placetype":"venue"
},
  "geometry": {"coordinates":[2.366722,47.062992],"type":"Point"}
}