{
  "type": "Feature",
  "properties": {
    "iso:country":"FR",
    "sg:address":"ZA de Quitigny",
    "sg:city":"Saint Germain l\u00e8s Arlay",
    "sg:orig_category":"Unclassifiable Establishments",
    "sg:phone":"+33 3 84 44 66 67",
    "sg:postcode":"39210",
    "sg:province":"Franche Comt\u00e9",
    "wof:name":"Eric Prost Diffusion S.a.s.",
    "wof:placetype":"venue"
},
  "geometry": {"coordinates":[5.55896,46.759144],"type":"Point"}
}