{
  "type": "Feature",
  "properties": {
    "iso:country":"FR",
    "sg:address":"Charmeil 03110 CHARMEIL",
    "sg:city":"Charmeil",
    "sg:orig_category":"Led Signalling Lamps",
    "sg:phone":"+33 4 70 58 86 86",
    "sg:postcode":"03110",
    "sg:province":"Auvergne",
    "wof:name":"S.e.r.m.e.t.o. Valmont Sa",
    "wof:placetype":"venue"
},
  "geometry": {"coordinates":[3.39307,46.160252],"type":"Point"}
}