{
  "type": "Feature",
  "properties": {
    "iso:country":"FR",
    "sg:address":"Chemin Lou Tribail Zi De Toctoucau 33610 Cestas",
    "sg:city":"Cestas",
    "sg:classifiers":[
        {
            "category":"Professional",
            "subcategory":"Engineering",
            "type":"Services"
        }
    ],
    "sg:phone":"+33 5 56 68 53 53",
    "sg:postcode":"33610",
    "sg:province":"Aquitaine",
    "sg:tags":[
        "machine",
        "-",
        "mechanical"
    ],
    "wof:name":"Perval",
    "wof:placetype":"venue"
},
  "geometry": {"coordinates":[-0.685714,44.741707],"type":"Point"}
}