{
  "type": "Feature",
  "properties": {
    "addr:full":"65/75 avenue Jean Mermoz 93120 La Courneuve Ile de France 93120",
    "addr:housenumber":"65 / 75",
    "addr:postcode":"93120;93120",
    "addr:street":"Avenue Jean Mermoz",
    "iso:country":"FR",
    "sg:address":"65/75 avenue Jean Mermoz 93120 La Courneuve",
    "sg:classifiers":[
        {
            "category":"Taxi",
            "type":"Transportation"
        }
    ],
    "sg:phone":"+33 1 49 92 94 94",
    "sg:postcode":"93120",
    "sg:province":"Ile de France",
    "sg:tags":[
        "geared",
        "electric",
        "motor"
    ],
    "wof:name":"Sm Cyclo France S.a.r.l.",
    "wof:placetype":"venue"
},
  "geometry": {"coordinates":[2.40415,48.932419],"type":"Point"}
}