{
  "type": "Feature",
  "properties": {
    "iso:country":"FR",
    "sg:address":"24 Rte De L'Isle Sur Sorgue 84300 Cavaillon",
    "sg:classifiers":[
        {
            "category":"Building & Trades",
            "subcategory":"Construction",
            "type":"Services"
        }
    ],
    "sg:phone":"+33 4 90 06 46 46",
    "sg:province":"Limousin",
    "sg:tags":[
        "work",
        "public"
    ],
    "wof:name":"Gerland Durance",
    "wof:placetype":"venue"
},
  "geometry": {"coordinates":[5.036776,43.853069],"type":"Point"}
}