{
  "type": "Feature",
  "properties": {
    "iso:country":"FR",
    "sg:address":"408 pl de la Madeleine; Verneuil; 27130",
    "sg:classifiers":[
        {
            "category":"Banks & Credit Unions",
            "subcategory":"Bank",
            "type":"Services"
        }
    ],
    "sg:phone":"+33 32606212",
    "sg:postcode":"27130",
    "sg:province":"Haute Normandie",
    "wof:name":"Cr\u00e9dit Agricole De L'eure",
    "wof:placetype":"venue"
},
  "geometry": {"coordinates":[0.85463,48.701855],"type":"Point"}
}