{
  "type": "Feature",
  "properties": {
    "iso:country":"FR",
    "sg:address":"20 Avenue Louison Bobet 06130 Grasse",
    "sg:classifiers":[
        {
            "category":"Manufacturing",
            "subcategory":"Chemicals & Compounds",
            "type":"Manufacturing & Wholesale Goods"
        }
    ],
    "sg:phone":"+33 4 92 42 43 44",
    "sg:province":"Rhone-Alpes",
    "sg:tags":[
        "pharmaceutical",
        "chemistry"
    ],
    "wof:name":"Remy Monique (laboratoire) Sa",
    "wof:placetype":"venue"
},
  "geometry": {"coordinates":[6.941587,43.626945],"type":"Point"}
}