{
  "type": "Feature",
  "properties": {
    "iso:country":"FR",
    "sg:address":"30, Rue Bernard Palissy, 45500 Gien",
    "sg:city":"Gien",
    "sg:orig_category":"Unclassifiable Establishments",
    "sg:phone":"+33 2 38 67 35 52",
    "sg:postcode":"45500",
    "sg:province":"Centre",
    "wof:name":"Protecnet S.a.r.l.",
    "wof:placetype":"venue"
},
  "geometry": {"coordinates":[2.626457,47.686005],"type":"Point"}
}