{
  "type": "Feature",
  "properties": {
    "iso:country":"FR",
    "sg:address":"5, Rue des Fontenelles - ZI du Petit Parc, 78920 Ecquevilly",
    "sg:orig_category":"Non-Classified Establishments",
    "sg:phone":"+33 1 34 75 96 96",
    "sg:province":"Ile de France",
    "wof:name":"Sterling Fluid Systems France S.a.",
    "wof:placetype":"venue"
},
  "geometry": {"coordinates":[1.918925,48.949734],"type":"Point"}
}