{
  "type": "Feature",
  "properties": {
    "addr:full":"48 cours L\u00e9on Bourgeois 51530 Pierry Centre",
    "addr:housenumber":"48",
    "addr:postcode":"51530",
    "addr:street":"Cours Le\u0301On Bourgeois",
    "iso:country":"FR",
    "sg:address":"48 cours L\u00e9on Bourgeois 51530 Pierry",
    "sg:classifiers":[
        {
            "category":"Food & Beverages",
            "subcategory":"Liquor & Beverages",
            "type":"Retail Goods"
        }
    ],
    "sg:phone":"+33 3 26 54 03 05",
    "sg:province":"Centre",
    "sg:tags":[
        "champagne"
    ],
    "wof:name":"Champagne Vollereaux Sa",
    "wof:placetype":"venue"
},
  "geometry": {"coordinates":[3.934279,49.01646],"type":"Point"}
}