{
  "type": "Feature",
  "properties": {
    "addr:full":"42, Av. de Bretagne, 94550 Chevilly Larue Ile de France",
    "addr:postcode":"94550",
    "addr:street":"42 Av. De Bretagne",
    "iso:country":"FR",
    "sg:address":"42, Av. de Bretagne, 94550 Chevilly Larue",
    "sg:orig_category":"Unclassifiable Establishments",
    "sg:phone":"+33 1 46 86 47 34",
    "sg:province":"Ile de France",
    "wof:name":"Lyonel Primeurs S.a.r.l.",
    "wof:placetype":"venue"
},
  "geometry": {"coordinates":[2.355175,48.763287],"type":"Point"}
}