{
  "type": "Feature",
  "properties": {
    "iso:country":"FR",
    "sg:address":"Chaumot 58800 Chaumot",
    "sg:city":"Chaumot",
    "sg:orig_category":"Unclassifiable Establishments",
    "sg:phone":"+33 3 86 20 00 76",
    "sg:postcode":"58800",
    "sg:province":"Bourgogne",
    "wof:name":"Riotte Prevotat S.d.f.",
    "wof:placetype":"venue"
},
  "geometry": {"coordinates":[3.64461,47.25843],"type":"Point"}
}