{
  "type": "Feature",
  "properties": {
    "addr:full":"02200 Chacrise Picardie",
    "addr:postcode":"02200",
    "iso:country":"FR",
    "sg:address":"02200 Chacrise",
    "sg:orig_category":"Unclassifiable Establishments",
    "sg:phone":"+33 3 23 55 18 18",
    "sg:province":"Picardie",
    "wof:name":"G\u00e9nard P\u00e8re Et Fils Transports S.a.",
    "wof:placetype":"venue"
},
  "geometry": {"coordinates":[3.404099,49.304855],"type":"Point"}
}