{
  "type": "Feature",
  "properties": {
    "addr:full":"3 rue de la Cotonni\u00e8re 14000 Caen Caen Basse Normandie 14000",
    "addr:housenumber":"3",
    "addr:postcode":"14000;14000",
    "addr:street":"Rue De La Cotonnie\u0300Re",
    "iso:country":"FR",
    "sg:address":"3 rue de la Cotonni\u00e8re 14000 Caen",
    "sg:city":"Caen",
    "sg:classifiers":[
        {
            "category":"Train Station",
            "subcategory":"Light Rail",
            "type":"Transportation"
        }
    ],
    "sg:phone":"+33 2 31 74 73 13",
    "sg:postcode":"14000",
    "sg:province":"Basse Normandie",
    "sg:tags":[
        "lighting"
    ],
    "wof:name":"Auteroche Industrie S.a.",
    "wof:placetype":"venue"
},
  "geometry": {"coordinates":[-0.40415,49.196915],"type":"Point"}
}