{
  "type": "Feature",
  "properties": {
    "addr:full":"72 Avenue De La Mer 14150 Ouistreham Ouistreham Basse Normandie 14150",
    "addr:housenumber":"72",
    "addr:postcode":"14150;14150",
    "addr:street":"Avenue De La Mer",
    "iso:country":"FR",
    "sg:address":"72 Avenue De La Mer 14150 Ouistreham",
    "sg:city":"Ouistreham",
    "sg:classifiers":[
        {
            "category":"Bakery",
            "type":"Food & Drink"
        }
    ],
    "sg:phone":"+33 2 31 97 18 10",
    "sg:postcode":"14150",
    "sg:province":"Basse Normandie",
    "sg:tags":[
        "cake",
        "product",
        "related",
        "bread"
    ],
    "wof:name":"Carlier Bruno Sarl",
    "wof:placetype":"venue"
},
  "geometry": {"coordinates":[-0.25889,49.286213],"type":"Point"}
}