{
  "type": "Feature",
  "properties": {
    "addr:full":"La Roche 38210 Poli\u00e9nas Rhone-Alpes 38210",
    "addr:postcode":"38210;38210",
    "addr:street":"La Roche;Rhone-Alpes",
    "iso:country":"FR",
    "sg:address":"La Roche 38210 Poli\u00e9nas",
    "sg:classifiers":[
        {
            "category":"Professional",
            "type":"Services"
        }
    ],
    "sg:phone":"+33 4 76 07 71 33",
    "sg:postcode":"38210",
    "sg:province":"Rhone-Alpes",
    "sg:tags":[
        "transport",
        "road"
    ],
    "wof:name":"Boulloud Gilles",
    "wof:placetype":"venue"
},
  "geometry": {"coordinates":[5.465564,45.251667],"type":"Point"}
}