{
  "type": "Feature",
  "properties": {
    "iso:country":"FR",
    "sg:address":"5 Av De L'Epi D'Or 94807 Cedex",
    "sg:classifiers":[
        {
            "category":"Manufacturing",
            "subcategory":"Metals",
            "type":"Manufacturing & Wholesale Goods"
        }
    ],
    "sg:phone":"+33 1 46 86 13 12",
    "sg:tags":[
        "metallurgy",
        "metalworking",
        "processing"
    ],
    "wof:name":"Billon Sa",
    "wof:placetype":"venue"
},
  "geometry": {"coordinates":[-122.34271200000001,37.937759],"type":"Point"}
}