{
  "type": "Feature",
  "properties": {
    "iso:country":"FR",
    "sg:address":"4 all\u00e9e Nic\u00e9phore Ni\u00e8pce 93360 Neuilly Plaisance",
    "sg:classifiers":[
        {
            "category":"Farming",
            "subcategory":"Orchard",
            "type":"Manufacturing & Wholesale Goods"
        }
    ],
    "sg:phone":"+33 1 43 00 92 72",
    "sg:province":"Ile de France",
    "sg:tags":[
        "switchgear"
    ],
    "wof:name":"Gounot S.a.",
    "wof:placetype":"venue"
},
  "geometry": {"coordinates":[2.495813,48.858234],"type":"Point"}
}