{
  "type": "Feature",
  "properties": {
    "addr:full":"Lieu Dit La Basse 88530 Le Tholy Lorraine",
    "addr:postcode":"88530",
    "addr:street":"Lieu Dit La Basse",
    "iso:country":"FR",
    "sg:address":"Lieu Dit La Basse 88530 Le Tholy",
    "sg:classifiers":[
        {
            "category":"Manufacturing",
            "subcategory":"Wood Products",
            "type":"Manufacturing & Wholesale Goods"
        }
    ],
    "sg:phone":"+33 3 29 61 82 66",
    "sg:province":"Lorraine",
    "sg:tags":[
        "professional",
        "furniture"
    ],
    "wof:name":"Ebenisterie Ferry",
    "wof:placetype":"venue"
},
  "geometry": {"coordinates":[6.758045,48.083878],"type":"Point"}
}