{
  "type": "Feature",
  "properties": {
    "iso:country":"FR",
    "sg:address":"175, Rte de Desvres, 62280 Saint Martin Boulogne",
    "sg:orig_category":"Non-Classified Establishments",
    "sg:phone":"+33 3 21 99 50 00",
    "sg:province":"Nord Pas-de-Calais",
    "wof:name":"Jms S.a.",
    "wof:placetype":"venue"
},
  "geometry": {"coordinates":[1.66062,50.71664],"type":"Point"}
}