{
  "type": "Feature",
  "properties": {
    "addr:full":"10 Rue De L'Ardoise 45170 Neuville Aux Bois Bougy-lez-Neuville Centre 45170",
    "addr:housenumber":"10",
    "addr:postcode":"45170;45170",
    "addr:street":"Rue De L'Ardoise;Bois Bougy-Lez-Neuville",
    "iso:country":"FR",
    "sg:address":"10 Rue De L'Ardoise 45170 Neuville Aux Bois",
    "sg:city":"Bougy-lez-Neuville",
    "sg:classifiers":[
        {
            "category":"Shopping",
            "subcategory":"Clothing, Apparel, & Fashions",
            "type":"Retail Goods"
        }
    ],
    "sg:phone":"+33 2 38 91 06 97",
    "sg:postcode":"45170",
    "sg:province":"Centre",
    "sg:tags":[
        "textile",
        "clothing",
        "clothes"
    ],
    "wof:name":"Au Renard Sa",
    "wof:placetype":"venue"
},
  "geometry": {"coordinates":[2.05268,48.068771],"type":"Point"}
}