{
  "type": "Feature",
  "properties": {
    "iso:country":"FR",
    "sg:address":"Rue Jean Lurcat 36700 CHATILLON SUR INDRE",
    "sg:city":"Arpheuilles",
    "sg:classifiers":[
        {
            "category":"Home & Garden",
            "subcategory":"Furniture",
            "type":"Retail Goods"
        }
    ],
    "sg:phone":"+33 2 54 38 70 87",
    "sg:postcode":"36700",
    "sg:province":"Centre",
    "sg:tags":[
        "designer"
    ],
    "wof:name":"Ste Guy Trochet S.a.r.l.",
    "wof:placetype":"venue"
},
  "geometry": {"coordinates":[1.168585,46.988071],"type":"Point"}
}