{
  "type": "Feature",
  "properties": {
    "addr:full":"Rue Du Cerou Zone Industrielle Du Cerou 81400 Carmaux Midi Pyr\u00e9n\u00e9es 81400",
    "addr:postcode":"81400;81400",
    "addr:street":"Rue Du Cerou Zone Industrielle Du Cerou",
    "iso:country":"FR",
    "sg:address":"Rue Du Cerou Zone Industrielle Du Cerou 81400 Carmaux",
    "sg:classifiers":[
        {
            "category":"Manufacturing",
            "subcategory":"Building Materials",
            "type":"Manufacturing & Wholesale Goods"
        }
    ],
    "sg:phone":"+33 5 63 80 10 80",
    "sg:postcode":"81400",
    "sg:province":"Midi Pyr\u00e9n\u00e9es",
    "sg:tags":[
        "glass",
        "ceramic"
    ],
    "wof:name":"Gres Cccitan Carrelage",
    "wof:placetype":"venue"
},
  "geometry": {"coordinates":[2.132425,44.032146],"type":"Point"}
}