{
  "type": "Feature",
  "properties": {
    "addr:full":"B.P. 3 Panissage^^38730 Panissage Rhone-Alpes 38730",
    "addr:postcode":"38730",
    "addr:street":"B.P. 3 Panissage^^38730;Rhone-Alpes",
    "iso:country":"FR",
    "sg:address":"B.P. 3",
    "sg:city":"Panissage^^38730 Panissage",
    "sg:orig_category":"Non-Classified Establishments",
    "sg:phone":"+33 4 74 88 25 13",
    "sg:postcode":"38730",
    "sg:province":"Rhone-Alpes",
    "wof:name":"Bigallet Et Jinot S.a.r.l.",
    "wof:placetype":"venue"
},
  "geometry": {"coordinates":[5.517865,45.45052],"type":"Point"}
}