{
  "type": "Feature",
  "properties": {
    "addr:full":"Rue Montainge - La Bagr\u00e9e Mondoubleau Centre 41170",
    "addr:housenumber":"mondoubleau",
    "addr:postcode":"41170",
    "addr:street":"Rue Montainge La Bagre\u0301E",
    "iso:country":"FR",
    "sg:address":"Rue Montainge - La Bagr\u00e9e",
    "sg:city":"Mondoubleau",
    "sg:orig_category":"Non-Classified Establishments",
    "sg:phone":"+33 2 54 80 81 67",
    "sg:postcode":"41170",
    "sg:province":"Centre",
    "wof:name":"Atelier Gaubert - Saradin Fran\u00e7ois",
    "wof:placetype":"venue"
},
  "geometry": {"coordinates":[0.85072,47.924099],"type":"Point"}
}