{
  "type": "Feature",
  "properties": {
    "addr:full":"Z.I. du Pigeon Blanc 56501 LOCMINE CEDEX Midi Pyr\u00e9n\u00e9es",
    "addr:postcode":"56501",
    "addr:street":"Z.I. Du Pigeon Blanc",
    "iso:country":"FR",
    "sg:address":"Z.I. du Pigeon Blanc 56501 LOCMINE CEDEX",
    "sg:classifiers":[
        {
            "category":"Food & Beverages",
            "subcategory":"Bakery",
            "type":"Retail Goods"
        }
    ],
    "sg:phone":"+33 2 97 26 78 00",
    "sg:province":"Midi Pyr\u00e9n\u00e9es",
    "sg:tags":[
        "biscuit"
    ],
    "wof:name":"Biscuiterie Le Ster Sa",
    "wof:placetype":"venue"
},
  "geometry": {"coordinates":[-2.834544,47.881954],"type":"Point"}
}