{
  "type": "Feature",
  "properties": {
    "addr:full":"11, Chemin du G\u00e9nie Militaire, 74940 Annecy le Vieux Rhone-Alpes 74940",
    "addr:housenumber":"11",
    "addr:postcode":"74940;74940",
    "addr:street":"Chemin Du Ge\u0301Nie Militaire",
    "iso:country":"FR",
    "sg:address":"11, Chemin du G\u00e9nie Militaire, 74940 Annecy le Vieux",
    "sg:orig_category":"Non-Classified Establishments",
    "sg:phone":"+33 4 50 67 42 65",
    "sg:postcode":"74940",
    "sg:province":"Rhone-Alpes",
    "wof:name":"Allegro S.a.",
    "wof:placetype":"venue"
},
  "geometry": {"coordinates":[6.121486,45.923294],"type":"Point"}
}