{
  "type": "Feature",
  "properties": {
    "iso:country":"FR",
    "sg:address":"Rue de Gutleutfeld",
    "sg:city":"Marmoutier",
    "sg:orig_category":"Unclassifiable Establishments",
    "sg:phone":"+33 3 88 71 42 94",
    "sg:postcode":"67440",
    "sg:province":"Alsace",
    "wof:name":"D'est Lingerie S.a.",
    "wof:placetype":"venue"
},
  "geometry": {"coordinates":[7.372071,48.701099],"type":"Point"}
}