{
  "type": "Feature",
  "properties": {
    "iso:country":"FR",
    "sg:address":"11 Bd Chateaubriand 95100 Argenteuil",
    "sg:classifiers":[
        {
            "category":"Professional",
            "subcategory":"Engineering",
            "type":"Services"
        }
    ],
    "sg:phone":"+33 1 34 11 76 00",
    "sg:postcode":"95100",
    "sg:province":"Ile de France",
    "sg:tags":[
        "machine",
        "-",
        "mechanical"
    ],
    "wof:name":"Etri",
    "wof:placetype":"venue"
},
  "geometry": {"coordinates":[2.209466,48.950836],"type":"Point"}
}