{
  "type": "Feature",
  "properties": {
    "iso:country":"FR",
    "sg:address":"Rte de Courth\u00e9zon",
    "sg:city":"Ch\u00e2teauneuf du Pape",
    "sg:orig_category":"Unclassifiable Establishments",
    "sg:phone":"+33 4 90 83 72 52",
    "sg:postcode":"84230",
    "sg:province":"Provence-Alpes-C\u00f4te d'Azur",
    "wof:name":"Domaine De Nalys",
    "wof:placetype":"venue"
},
  "geometry": {"coordinates":[4.83468,44.058636],"type":"Point"}
}