{
  "type": "Feature",
  "properties": {
    "addr:full":"19 Bis Rue De L'Etoile 72000 Le Mans Pays de Loire 72000",
    "addr:housenumber":"19 bis",
    "addr:postcode":"72000;72000",
    "addr:street":"Rue De L'Etoile",
    "iso:country":"FR",
    "sg:address":"19 Bis Rue De L'Etoile 72000 Le Mans",
    "sg:classifiers":[
        {
            "category":"Shopping",
            "subcategory":"Luggage & Leather Goods",
            "type":"Retail Goods"
        }
    ],
    "sg:phone":"+33 2 43 28 23 92",
    "sg:postcode":"72000",
    "sg:province":"Pays de Loire",
    "sg:tags":[
        "shoe"
    ],
    "wof:name":"Gobeaud Sa",
    "wof:placetype":"venue"
},
  "geometry": {"coordinates":[0.175055,48.00362],"type":"Point"}
}