{
  "type": "Feature",
  "properties": {
    "addr:full":"Zi Praye 55500 Velaines Lorraine 55500",
    "addr:postcode":"55500;55500",
    "iso:country":"FR",
    "sg:address":"Zi Praye 55500 Velaines",
    "sg:classifiers":[
        {
            "category":"Manufacturing",
            "subcategory":"Metals",
            "type":"Manufacturing & Wholesale Goods"
        }
    ],
    "sg:phone":"+33 3 29 78 81 43",
    "sg:postcode":"55500",
    "sg:province":"Lorraine",
    "sg:tags":[
        "metallurgy",
        "metalworking",
        "processing"
    ],
    "wof:name":"Lam Sa",
    "wof:placetype":"venue"
},
  "geometry": {"coordinates":[5.29731,48.704746],"type":"Point"}
}