{
  "type": "Feature",
  "properties": {
    "addr:full":"38 Reims 59100 Roubaix Nord Pas-de-Calais 59100",
    "addr:housenumber":"38",
    "addr:postcode":"59100;59100",
    "addr:street":"Reims",
    "iso:country":"FR",
    "sg:address":"38",
    "sg:city":"Reims 59100 Roubaix",
    "sg:classifiers":[
        {
            "category":"Professional",
            "subcategory":"Engineering",
            "type":"Services"
        }
    ],
    "sg:phone":"+33 3 20 45 39 39",
    "sg:postcode":"59100",
    "sg:province":"Nord Pas-de-Calais",
    "sg:tags":[
        "machine",
        "-",
        "mechanical"
    ],
    "wof:name":"Hibon (sas)",
    "wof:placetype":"venue"
},
  "geometry": {"coordinates":[3.190388,50.682587],"type":"Point"}
}