{
  "type": "Feature",
  "properties": {
    "addr:full":"1, Rue Joseph Cugnot - ZI de G\u00e9llainville, 28000 Chartres Chartres Centre 28000",
    "addr:housenumber":"1",
    "addr:postcode":"28000;28000",
    "addr:street":"Rue Joseph Cugnot Zi De Ge\u0301Llainville",
    "iso:country":"FR",
    "sg:address":"1, Rue Joseph Cugnot - ZI de G\u00e9llainville, 28000 Chartres",
    "sg:city":"Chartres",
    "sg:orig_category":"Non-Classified Establishments",
    "sg:phone":"+33 2 37 30 56 00",
    "sg:postcode":"28000",
    "sg:province":"Centre",
    "wof:name":"S.m.d. S.a.",
    "wof:placetype":"venue"
},
  "geometry": {"coordinates":[1.483419,48.444599],"type":"Point"}
}