{
  "type": "Feature",
  "properties": {
    "addr:full":"Rte de Vaison Malauc\u00e8ne Provence-Alpes-C\u00f4te d'Azur 84340",
    "addr:postcode":"84340",
    "addr:street":"Rte De Vaison",
    "iso:country":"FR",
    "sg:address":"Rte de Vaison",
    "sg:city":"Malauc\u00e8ne",
    "sg:orig_category":"Non-Classified Establishments",
    "sg:phone":"+33 4 90 36 19 21",
    "sg:postcode":"84340",
    "sg:province":"Provence-Alpes-C\u00f4te d'Azur",
    "wof:name":"Etablissements Clier S.a.r.l.",
    "wof:placetype":"venue"
},
  "geometry": {"coordinates":[5.131616,44.172165],"type":"Point"}
}