{
  "type": "Feature",
  "properties": {
    "iso:country":"FR",
    "sg:address":"B.P. 20, 38080 Saint Alban de Roche^^33, Rte de Lyon, 38080 Saint Alban de Roche",
    "sg:orig_category":"Non-Classified Establishments",
    "sg:phone":"+33 4 74 93 24 98",
    "sg:postcode":"38080",
    "sg:province":"Rhone-Alpes",
    "wof:name":"Soci\u00e9t\u00e9 D'exploitation Ciceron Henri S.a.s.",
    "wof:placetype":"venue"
},
  "geometry": {"coordinates":[5.233707,45.595795],"type":"Point"}
}