{
  "type": "Feature",
  "properties": {
    "addr:full":"Zi Marcel Dassault 64170 Artix Artix Aquitaine 64170",
    "addr:postcode":"64170;64170",
    "addr:street":"Dassault",
    "iso:country":"FR",
    "sg:address":"Zi Marcel Dassault 64170 Artix",
    "sg:city":"Artix",
    "sg:classifiers":[
        {
            "category":"Shopping",
            "type":"Retail Goods"
        }
    ],
    "sg:phone":"+33 5 59 83 36 29",
    "sg:postcode":"64170",
    "sg:province":"Aquitaine",
    "sg:tags":[
        "metallurgy",
        "finished",
        "-",
        "metalworking",
        "metallic"
    ],
    "wof:name":"Pyrenees Armatures",
    "wof:placetype":"venue"
},
  "geometry": {"coordinates":[-0.569274,43.399254],"type":"Point"}
}