{
  "type": "Feature",
  "properties": {
    "addr:full":"ZA du Monay Saint Eus\u00e8be Bourgogne 71210",
    "addr:postcode":"71210",
    "addr:street":"Za Du Monay Saint Euse\u0300Be Bourgogne",
    "iso:country":"FR",
    "sg:address":"ZA du Monay",
    "sg:city":"Saint Eus\u00e8be",
    "sg:orig_category":"Non-Classified Establishments",
    "sg:phone":"+33 3 85 77 73 00",
    "sg:postcode":"71210",
    "sg:province":"Bourgogne",
    "wof:name":"A.p.t.h. - Association De Pr\u00e9vention Dans Le Transport D'hydrocarbures",
    "wof:placetype":"venue"
},
  "geometry": {"coordinates":[4.463261,46.713284],"type":"Point"}
}