{
  "type": "Feature",
  "properties": {
    "addr:full":"Lieu Dit Fon De Pommier Za Du Lidon 47150 MONFLANQUIN Monflanquin Aquitaine 47150",
    "addr:postcode":"47150;47150",
    "addr:street":"Lieu Dit Fon De Pommier Za Du Lidon",
    "iso:country":"FR",
    "sg:address":"Lieu Dit Fon De Pommier Za Du Lidon 47150 MONFLANQUIN",
    "sg:city":"Monflanquin",
    "sg:classifiers":[
        {
            "category":"Food & Beverages",
            "subcategory":"Fruits & Vegetables",
            "type":"Retail Goods"
        }
    ],
    "sg:phone":"+33 5 53 36 50 63",
    "sg:postcode":"47150",
    "sg:province":"Aquitaine",
    "sg:tags":[
        "juice",
        "nectar"
    ],
    "wof:name":"Secopra Sa",
    "wof:placetype":"venue"
},
  "geometry": {"coordinates":[0.730768,44.470425],"type":"Point"}
}