{
  "type": "Feature",
  "properties": {
    "iso:country":"FR",
    "sg:address":"10 rue de Leicester 67000 Strasbourg",
    "sg:city":"Strasbourg",
    "sg:orig_category":"Claims Handling In Leasing Sector",
    "sg:phone":"+33 3 88 60 72 77",
    "sg:postcode":"67000",
    "sg:province":"Alsace",
    "wof:name":"Roux Sa",
    "wof:placetype":"venue"
},
  "geometry": {"coordinates":[7.771747,48.578159],"type":"Point"}
}