{
  "type": "Feature",
  "properties": {
    "iso:country":"FR",
    "sg:address":"21 Zi Barnier 34110 Frontignan",
    "sg:classifiers":[
        {
            "category":"Farming",
            "subcategory":"Livestock Farm",
            "type":"Manufacturing & Wholesale Goods"
        }
    ],
    "sg:phone":"+33 4 67 80 06 62",
    "sg:postcode":"34110",
    "sg:province":"Languedoc-Roussillon",
    "sg:tags":[
        "breeding",
        "agriculture",
        "animal"
    ],
    "wof:name":"Fiat Maree Sa",
    "wof:placetype":"venue"
},
  "geometry": {"coordinates":[3.75841,43.444561],"type":"Point"}
}