{
  "type": "Feature",
  "properties": {
    "addr:full":"Z.I. 49160 LONGUE JUMELLES Pays de Loire",
    "addr:postcode":"49160",
    "addr:street":"Z.I.;Jumelles",
    "iso:country":"FR",
    "sg:address":"Z.I. 49160 LONGUE JUMELLES",
    "sg:classifiers":[
        {
            "category":"Manufacturing",
            "subcategory":"Rubber & Plastics",
            "type":"Manufacturing & Wholesale Goods"
        }
    ],
    "sg:phone":"+33 2 41 52 61 82",
    "sg:province":"Pays de Loire",
    "sg:tags":[
        "material"
    ],
    "wof:name":"Carolex Sa",
    "wof:placetype":"venue"
},
  "geometry": {"coordinates":[-0.148994,47.315624],"type":"Point"}
}