{
  "type": "Feature",
  "properties": {
    "iso:country":"FR",
    "sg:address":"ZI N\u00b02 Valenciennes Rouvignies",
    "sg:city":"Valenciennes",
    "sg:orig_category":"Unclassifiable Establishments",
    "sg:phone":"+33 3 27 23 11 12",
    "sg:postcode":"59300",
    "sg:province":"Nord Pas-de-Calais",
    "wof:name":"Valoutil S.a.",
    "wof:placetype":"venue"
},
  "geometry": {"coordinates":[3.524105,50.358494],"type":"Point"}
}