{
  "type": "Feature",
  "properties": {
    "addr:full":"618, Rte Grignon, 78450 Chavenay Ile de France",
    "addr:housenumber":"618",
    "addr:postcode":"78450;ile",
    "addr:street":"Rte Grignon",
    "iso:country":"FR",
    "sg:address":"618, Rte Grignon, 78450 Chavenay",
    "sg:orig_category":"Unclassifiable Establishments",
    "sg:phone":"+33 1 30 54 58 13",
    "sg:province":"Ile de France",
    "wof:name":"Dolphy Distribution S.a.r.l.",
    "wof:placetype":"venue"
},
  "geometry": {"coordinates":[1.96834,48.85498],"type":"Point"}
}