{
  "type": "Feature",
  "properties": {
    "iso:country":"FR",
    "sg:address":"ZA Arnede 30252 SOMMIERES CEDEX",
    "sg:classifiers":[
        {
            "category":"Cinema",
            "subcategory":"Movie Theater",
            "type":"Entertainment"
        }
    ],
    "sg:phone":"+33 4 66 80 34 02",
    "sg:province":"Languedoc-Roussillon",
    "sg:tags":[
        "volume",
        "picture"
    ],
    "wof:name":"Romain Pages Editions Sarl",
    "wof:placetype":"venue"
},
  "geometry": {"coordinates":[4.089205,43.782681],"type":"Point"}
}