{
  "type": "Feature",
  "properties": {
    "addr:full":"175 rue de Massacan 34740 Vendargues Languedoc-Roussillon",
    "addr:housenumber":"175",
    "addr:postcode":"34740",
    "addr:street":"Rue De Massacan",
    "iso:country":"FR",
    "sg:address":"175 rue de Massacan 34740 Vendargues",
    "sg:classifiers":[
        {
            "category":"Communications",
            "subcategory":"Film & Video Production",
            "type":"Services"
        }
    ],
    "sg:phone":"+33 4 67 87 46 46",
    "sg:province":"Languedoc-Roussillon",
    "sg:tags":[
        "event-controlled",
        "systems",
        "surveillance"
    ],
    "wof:name":"Hymatom S.a.",
    "wof:placetype":"venue"
},
  "geometry": {"coordinates":[3.9488,43.654442],"type":"Point"}
}