{
  "type": "Feature",
  "properties": {
    "addr:full":"B.P. 133, 45143 Saint Jean de la Ruelle C\u00e9dex^^48 bis, Rue Charles Beauhaire, 45140 Saint Jean de la Ingr\u00e9 Centre 45140",
    "addr:housenumber":"b.p. 133;bis",
    "addr:postcode":"45143;45140;45140",
    "addr:street":"La Ruelle Ce\u0301Dex^^48;Rue Charles Beauhaire",
    "iso:country":"FR",
    "sg:address":"B.P. 133, 45143 Saint Jean de la Ruelle C\u00e9dex^^48 bis, Rue Charles Beauhaire, 45140 Saint Jean de la",
    "sg:city":"Ingr\u00e9",
    "sg:orig_category":"Non-Classified Establishments",
    "sg:phone":"+33 2 38 22 85 90",
    "sg:postcode":"45140",
    "sg:province":"Centre",
    "wof:name":"Riffault S.a.r.l.",
    "wof:placetype":"venue"
},
  "geometry": {"coordinates":[1.857649,47.919224],"type":"Point"}
}