{
  "type": "Feature",
  "properties": {
    "iso:country":"FR",
    "sg:address":"9 Passage Turquetil 75011 Paris",
    "sg:classifiers":[
        {
            "category":"Manufacturing",
            "subcategory":"Metals",
            "type":"Manufacturing & Wholesale Goods"
        }
    ],
    "sg:phone":"+33 1 43 70 13 80",
    "sg:postcode":"75011",
    "sg:province":"Ile de France",
    "sg:tags":[
        "-",
        "machine",
        "equipment",
        "engineering",
        "machinery",
        "mechanical"
    ],
    "wof:name":"Lebaron Freres (societe Des Chromographes) Sa",
    "wof:placetype":"venue"
},
  "geometry": {"coordinates":[2.379995,48.857594],"type":"Point"}
}