{
  "type": "Feature",
  "properties": {
    "addr:full":"72 avenue de la Lib\u00e9ration 01500 AMBERIEU EN BUGEY Rhone-Alpes 01500",
    "addr:housenumber":"72",
    "addr:postcode":"01500;01500",
    "addr:street":"Avenue De La Libe\u0301Ration;Rhone-Alpes",
    "iso:country":"FR",
    "sg:address":"72 avenue de la Lib\u00e9ration 01500 AMBERIEU EN BUGEY",
    "sg:classifiers":[
        {
            "category":"Manufacturing",
            "subcategory":"Motor Vehicles & Parts",
            "type":"Manufacturing & Wholesale Goods"
        }
    ],
    "sg:phone":"+33 4 74 46 14 00",
    "sg:postcode":"01500",
    "sg:province":"Rhone-Alpes",
    "sg:tags":[
        "precision",
        "mechanic"
    ],
    "wof:name":"A.m.b Sa",
    "wof:placetype":"venue"
},
  "geometry": {"coordinates":[5.33766,45.965603],"type":"Point"}
}