{
  "type": "Feature",
  "properties": {
    "iso:country":"FR",
    "sg:address":"47, Rue de la chauss\u00e9e d'Antin, 75009 Paris",
    "sg:orig_category":"Unclassifiable Establishments",
    "sg:phone":"+33 1 53 20 45 45",
    "sg:province":"Ile de France",
    "wof:name":"Dewco S.a.r.l.",
    "wof:placetype":"venue"
},
  "geometry": {"coordinates":[2.332278,48.874851],"type":"Point"}
}