{
  "type": "Feature",
  "properties": {
    "iso:country":"FR",
    "sg:address":"10 R Des Tilleuls 28120 Illiers Combray",
    "sg:city":"Bailleau-le-Pin",
    "sg:classifiers":[
        {
            "category":"Manufacturing",
            "subcategory":"Rubber & Plastics",
            "type":"Manufacturing & Wholesale Goods"
        }
    ],
    "sg:phone":"+33 2 37 24 01 12",
    "sg:postcode":"28120",
    "sg:province":"Centre",
    "wof:name":"Cabaplast Sa",
    "wof:placetype":"venue"
},
  "geometry": {"coordinates":[1.243628,48.307022],"type":"Point"}
}