{
  "type": "Feature",
  "properties": {
    "addr:full":"Autoport 66161 LE BOULOU CEDEX Centre",
    "addr:postcode":"66161",
    "addr:street":"Autoport",
    "iso:country":"FR",
    "sg:address":"Autoport 66161 LE BOULOU CEDEX",
    "sg:classifiers":[
        {
            "category":"Professional",
            "type":"Services"
        }
    ],
    "sg:phone":"+33 4 68 83 37 76",
    "sg:province":"Centre",
    "sg:tags":[
        "transport"
    ],
    "wof:name":"Tradifrance Sa",
    "wof:placetype":"venue"
},
  "geometry": {"coordinates":[2.830395,42.52483],"type":"Point"}
}