{
  "type": "Feature",
  "properties": {
    "iso:country":"FR",
    "sg:address":"Caves Du Gue D Argent 18300 Thauvenay",
    "sg:city":"Thauvenay",
    "sg:classifiers":[
        {
            "category":"Food Court",
            "type":"Food & Drink"
        }
    ],
    "sg:phone":"+33 2 48 79 94 10",
    "sg:postcode":"18300",
    "sg:province":"Centre",
    "sg:tags":[
        "product",
        "related"
    ],
    "wof:name":"Sas Serge Laloue",
    "wof:placetype":"venue"
},
  "geometry": {"coordinates":[2.868033,47.30529],"type":"Point"}
}