{
  "type": "Feature",
  "properties": {
    "addr:full":"35 blvd les Amphores; Cagnes sur Mer Centre",
    "addr:street":"35 Blvd Les Amphores Cagnes",
    "iso:country":"FR",
    "sg:address":"35 blvd les Amphores; Cagnes sur Mer",
    "sg:classifiers":[
        {
            "category":"Banks & Credit Unions",
            "subcategory":"Bank",
            "type":"Services"
        }
    ],
    "sg:phone":"+33 3393207520",
    "sg:province":"Centre",
    "wof:name":"Soci\u00e9t\u00e9 Marseillaise De Cr\u00e9dit",
    "wof:placetype":"venue"
},
  "geometry": {"coordinates":[7.150965,43.662418],"type":"Point"}
}