{
  "type": "Feature",
  "properties": {
    "iso:country":"FR",
    "sg:address":"B.P. 54, 68311 Illzach C\u00e9dex^^28, Rue de Kingersheim, 68110 Illzach",
    "sg:city":"Illzach",
    "sg:orig_category":"Non-Classified Establishments",
    "sg:phone":"+33 3 89 52 61 32",
    "sg:postcode":"68110",
    "sg:province":"Alsace",
    "wof:name":"Kleinhenny R S.a.r.l.",
    "wof:placetype":"venue"
},
  "geometry": {"coordinates":[7.348394,47.782181],"type":"Point"}
}