{
  "type": "Feature",
  "properties": {
    "iso:country":"FR",
    "sg:address":"10, All\u00e9e du Ch\u00e2teau Gassion, 57100 Thionville",
    "sg:orig_category":"Unclassifiable Establishments",
    "sg:phone":"+33 3 82 59 30 70",
    "sg:province":"Lorraine",
    "wof:name":"Cegelec S.a.",
    "wof:placetype":"venue"
},
  "geometry": {"coordinates":[6.15805,49.338509],"type":"Point"}
}