{
  "type": "Feature",
  "properties": {
    "iso:country":"FR",
    "sg:address":"53, Rte de Lourdes, 65310 Odos",
    "sg:orig_category":"Unclassifiable Establishments",
    "sg:phone":"+33 5 62 51 78 80",
    "sg:province":"Midi Pyr\u00e9n\u00e9es",
    "wof:name":"Adhetec S.a.",
    "wof:placetype":"venue"
},
  "geometry": {"coordinates":[0.04492,43.208519],"type":"Point"}
}