{
  "type": "Feature",
  "properties": {
    "addr:full":"21, Bd de la Maison Blanche, 13000 Marseille Provence-Alpes-C\u00f4te d'Azur",
    "addr:housenumber":"21",
    "addr:postcode":"13000",
    "addr:street":"Bd De La Maison Blanche",
    "iso:country":"FR",
    "sg:address":"21, Bd de la Maison Blanche, 13000 Marseille",
    "sg:orig_category":"Unclassifiable Establishments",
    "sg:phone":"+33 4 91 21 41 31",
    "sg:province":"Provence-Alpes-C\u00f4te d'Azur",
    "wof:name":"L'approvisionnement Electrique S.a.",
    "wof:placetype":"venue"
},
  "geometry": {"coordinates":[5.37249,43.293686],"type":"Point"}
}