{
  "type": "Feature",
  "properties": {
    "addr:full":"Rte Nationale 175 - Quetteville Quetteville Basse Normandie 14130",
    "addr:housenumber":"175",
    "addr:postcode":"14130",
    "addr:street":"Rte Nationale;Basse",
    "iso:country":"FR",
    "sg:address":"Rte Nationale 175 - Quetteville",
    "sg:city":"Quetteville",
    "sg:orig_category":"Non-Classified Establishments",
    "sg:phone":"+33 2 31 65 62 40",
    "sg:postcode":"14130",
    "sg:province":"Basse Normandie",
    "wof:name":"Chevotel De Lahauquerie S.a.r.l.",
    "wof:placetype":"venue"
},
  "geometry": {"coordinates":[0.31036,49.337238],"type":"Point"}
}