{
  "type": "Feature",
  "properties": {
    "iso:country":"FR",
    "sg:address":"49, Quai d'Embarquement, 65000 Tarbes",
    "sg:orig_category":"Unclassifiable Establishments",
    "sg:phone":"+33 5 62 36 00 44",
    "sg:province":"Midi Pyr\u00e9n\u00e9es",
    "wof:name":"Distri G.",
    "wof:placetype":"venue"
},
  "geometry": {"coordinates":[0.065049,43.241596],"type":"Point"}
}