{
  "type": "Feature",
  "properties": {
    "addr:full":"8, Rue Paul Gros - ZI Cap 10, 33270 Floirac Floirac Aquitaine 33270",
    "addr:housenumber":"8;10",
    "addr:postcode":"33270;33270",
    "addr:street":"Rue Paul Gros Zi Cap",
    "iso:country":"FR",
    "sg:address":"8, Rue Paul Gros - ZI Cap 10, 33270 Floirac",
    "sg:city":"Floirac",
    "sg:orig_category":"Unclassifiable Establishments",
    "sg:phone":"+33 5 56 40 49 89",
    "sg:postcode":"33270",
    "sg:province":"Aquitaine",
    "wof:name":"R.e.b. S.a.r.l.",
    "wof:placetype":"venue"
},
  "geometry": {"coordinates":[-0.516334,44.839329],"type":"Point"}
}