{
  "type": "Feature",
  "properties": {
    "addr:full":"chemin des Cotes Montbron 78350 Les Loges En Josas Ile de France 78350",
    "addr:postcode":"78350;france 78350",
    "addr:street":"Chemin Des Cotes",
    "iso:country":"FR",
    "sg:address":"chemin des Cotes Montbron 78350 Les Loges En Josas",
    "sg:classifiers":[
        {
            "category":"Professional",
            "subcategory":"Advertising",
            "type":"Services"
        }
    ],
    "sg:phone":"+33 1 39 20 19 60",
    "sg:postcode":"78350",
    "sg:province":"Ile de France",
    "sg:tags":[
        "direct-action"
    ],
    "wof:name":"Action D'eclat Archipel S.a.r.l.",
    "wof:placetype":"venue"
},
  "geometry": {"coordinates":[2.151074,48.760101],"type":"Point"}
}