{
  "type": "Feature",
  "properties": {
    "addr:full":"lieu dit le Grand Clos 49640 Daumeray Pays de Loire",
    "addr:postcode":"49640",
    "addr:street":"Lieu Dit Le Grand Clos",
    "iso:country":"FR",
    "sg:address":"lieu dit le Grand Clos 49640 Daumeray",
    "sg:classifiers":[
        {
            "category":"Farming",
            "subcategory":"Poultry Farm",
            "type":"Manufacturing & Wholesale Goods"
        }
    ],
    "sg:phone":"+33 2 41 32 56 65",
    "sg:province":"Pays de Loire",
    "sg:tags":[
        "stewed",
        "boned"
    ],
    "wof:name":"Guillet Sa Groupe Lbc",
    "wof:placetype":"venue"
},
  "geometry": {"coordinates":[-0.355179,47.702679],"type":"Point"}
}