{
  "type": "Feature",
  "properties": {
    "iso:country":"FR",
    "sg:address":"B.P. 1, 59820 Gravelines^^1, Rue de l'Industrie, 59820 Gravelines",
    "sg:orig_category":"Non-Classified Establishments",
    "sg:phone":"+33 3 28 23 25 85",
    "sg:province":"Nord Pas-de-Calais",
    "wof:name":"Instelec S.a.r.l",
    "wof:placetype":"venue"
},
  "geometry": {"coordinates":[2.121793,50.977947],"type":"Point"}
}