{
  "type": "Feature",
  "properties": {
    "addr:full":"Les Gibeaux 70600 Champlitte Franche Comt\u00e9 70600",
    "addr:postcode":"70600;70600",
    "addr:street":"Franche Comte\u0301",
    "iso:country":"FR",
    "sg:address":"Les Gibeaux 70600 Champlitte",
    "sg:orig_category":"D\u00c9COUPAGE, EMBOUTISSAGE POUR TOUTES INDUSTRIES JUSQU'\u00c0 250 T outillages de presse en tous genres pro",
    "sg:phone":"+33 3 84 67 64 51",
    "sg:postcode":"70600",
    "sg:province":"Franche Comt\u00e9",
    "wof:name":"Grognu Industries S.a.",
    "wof:placetype":"venue"
},
  "geometry": {"coordinates":[5.517495,47.610031],"type":"Point"}
}