{
  "type": "Feature",
  "properties": {
    "addr:full":"Le Petit Bois 42110 Epercieux St Paul Rhone-Alpes",
    "addr:postcode":"42110",
    "addr:street":"Le Petit Bois;Epercieux",
    "iso:country":"FR",
    "sg:address":"Le Petit Bois 42110 Epercieux St Paul",
    "sg:classifiers":[
        {
            "category":"Professional",
            "type":"Services"
        }
    ],
    "sg:phone":"+33 4 77 27 03 03",
    "sg:province":"Rhone-Alpes",
    "sg:tags":[
        "transport"
    ],
    "wof:name":"Transports Brulas Sarl",
    "wof:placetype":"venue"
},
  "geometry": {"coordinates":[4.271401,45.760094],"type":"Point"}
}