{
  "type": "Feature",
  "properties": {
    "addr:full":"30, Rue Carteron, 49300 Cholet Pays de Loire",
    "addr:housenumber":"30",
    "addr:postcode":"49300",
    "addr:street":"Rue Carteron",
    "iso:country":"FR",
    "sg:address":"30, Rue Carteron, 49300 Cholet",
    "sg:orig_category":"Unclassifiable Establishments",
    "sg:phone":"+33 2 41 62 58 18",
    "sg:province":"Pays de Loire",
    "wof:name":"First Engineering S.a.",
    "wof:placetype":"venue"
},
  "geometry": {"coordinates":[-0.868959,47.050289],"type":"Point"}
}