{
  "type": "Feature",
  "properties": {
    "addr:full":"ZI Les Gaillagues Saint R\u00e9my Midi Pyr\u00e9n\u00e9es 12200",
    "addr:postcode":"12200",
    "addr:street":"Zi Les Gaillagues Saint Re\u0301My Midi Pyre\u0301Ne\u0301Es",
    "iso:country":"FR",
    "sg:address":"ZI Les Gaillagues",
    "sg:city":"Saint R\u00e9my",
    "sg:orig_category":"Non-Classified Establishments",
    "sg:phone":"+33 5 65 65 01 11",
    "sg:postcode":"12200",
    "sg:province":"Midi Pyr\u00e9n\u00e9es",
    "wof:name":"Grapho 12 S.a.",
    "wof:placetype":"venue"
},
  "geometry": {"coordinates":[2.039621,44.39917],"type":"Point"}
}