{
  "type": "Feature",
  "properties": {
    "iso:country":"FR",
    "sg:address":"1 quai Colbert 76600 Le Havre",
    "sg:classifiers":[
        {
            "category":"Coffee & Tea",
            "type":"Food & Drink"
        }
    ],
    "sg:phone":"+33 2 35 22 71 22",
    "sg:province":"Haute Normandie",
    "sg:tags":[
        "roasted"
    ],
    "wof:name":"Soci\u00e9t\u00e9 Dafci Sa",
    "wof:placetype":"venue"
},
  "geometry": {"coordinates":[0.130015,49.492378],"type":"Point"}
}