{
  "type": "Feature",
  "properties": {
    "addr:full":"Rue Artisans 14670 Troarn Troarn Basse Normandie 14670",
    "addr:postcode":"14670;14670",
    "addr:street":"Rue Artisans",
    "iso:country":"FR",
    "sg:address":"Rue Artisans 14670 Troarn",
    "sg:city":"Troarn",
    "sg:classifiers":[
        {
            "category":"Food & Beverages",
            "subcategory":"Groceries & Convenience Stores",
            "type":"Retail Goods"
        }
    ],
    "sg:phone":"+33 2 31 39 23 78",
    "sg:postcode":"14670",
    "sg:province":"Basse Normandie",
    "sg:tags":[
        "preserve",
        "cake",
        "product",
        "related",
        "bread"
    ],
    "wof:name":"Blini Sa",
    "wof:placetype":"venue"
},
  "geometry": {"coordinates":[-0.186474,49.189915],"type":"Point"}
}