{
  "type": "Feature",
  "properties": {
    "addr:full":"avenue des Pins d'Alep 30100 ALES Languedoc-Roussillon 30100",
    "addr:housenumber":"d'alep",
    "addr:postcode":"30100;30100",
    "addr:street":"Avenue Des Pins",
    "iso:country":"FR",
    "sg:address":"avenue des Pins d'Alep 30100 ALES",
    "sg:classifiers":[
        {
            "category":"Autos & Motor Vehicles",
            "subcategory":"Recreational Vehicle Sales",
            "type":"Retail Goods"
        }
    ],
    "sg:phone":"+33 4 66 30 46 46",
    "sg:postcode":"30100",
    "sg:province":"Languedoc-Roussillon",
    "sg:tags":[
        "car",
        "part"
    ],
    "wof:name":"Ariette Production S.a.",
    "wof:placetype":"venue"
},
  "geometry": {"coordinates":[4.112405,44.117802],"type":"Point"}
}