{
  "type": "Feature",
  "properties": {
    "addr:full":"B.P. 85, 62210 Avion^^Bd Henri Martel, 62210 Avion Nord Pas-de-Calais",
    "addr:postcode":"62210;62210",
    "addr:street":"B.P. 85;Henri Martel",
    "iso:country":"FR",
    "sg:address":"B.P. 85, 62210 Avion^^Bd Henri Martel, 62210 Avion",
    "sg:orig_category":"Non-Classified Establishments",
    "sg:phone":"+33 3 21 79 16 40",
    "sg:province":"Nord Pas-de-Calais",
    "wof:name":"Routi\u00e8re Morin S.a.",
    "wof:placetype":"venue"
},
  "geometry": {"coordinates":[2.83327,50.413349],"type":"Point"}
}