{
  "type": "Feature",
  "properties": {
    "iso:country":"FR",
    "sg:address":"RN 33",
    "sg:city":"Saint Avold",
    "sg:orig_category":"Non-Classified Establishments",
    "sg:phone":"+33 3 87 91 09 09",
    "sg:postcode":"57500",
    "sg:province":"Lorraine",
    "wof:name":"Alpha Location S.a.",
    "wof:placetype":"venue"
},
  "geometry": {"coordinates":[6.705505,49.104275],"type":"Point"}
}