{
  "type": "Feature",
  "properties": {
    "iso:country":"FR",
    "sg:address":"15 F, Rue Paul Niclausse, 77515 Pommeuse",
    "sg:orig_category":"Non-Classified Establishments",
    "sg:phone":"+33 1 64 75 36 75",
    "sg:province":"Ile de France",
    "wof:name":"Soci\u00e9t\u00e9 Continentale Du Ressort S.a.r.l.",
    "wof:placetype":"venue"
},
  "geometry": {"coordinates":[3.017607,48.81509],"type":"Point"}
}