{
  "type": "Feature",
  "properties": {
    "addr:full":"8 Rue Cambon 75001 Paris Ile de France 75001",
    "addr:housenumber":"8",
    "addr:postcode":"75001;75001",
    "addr:street":"Rue Cambon",
    "iso:country":"FR",
    "sg:address":"8 Rue Cambon 75001 Paris",
    "sg:classifiers":[
        {
            "category":"Travel",
            "subcategory":"Hotels & Motels",
            "type":"Entertainment"
        }
    ],
    "sg:phone":"+33 1 44 77 54 00",
    "sg:postcode":"75001",
    "sg:province":"Ile de France",
    "sg:tags":[
        "hotels",
        "business",
        "restaurant"
    ],
    "wof:name":"Melia Vend\u00d4me",
    "wof:placetype":"venue"
},
  "geometry": {"coordinates":[2.325781,48.866753],"type":"Point"}
}