{
  "type": "Feature",
  "properties": {
    "addr:full":"Zone Artisanale 85110 St Germain De Princay Pays de Loire 85110",
    "addr:postcode":"85110;85110",
    "addr:street":"Zone Artisanale;Princay",
    "iso:country":"FR",
    "sg:address":"Zone Artisanale 85110 St Germain De Princay",
    "sg:classifiers":[
        {
            "category":"Autos & Motor Vehicles",
            "subcategory":"Automobile Sales",
            "type":"Retail Goods"
        }
    ],
    "sg:phone":"+33 2 51 94 37 20",
    "sg:postcode":"85110",
    "sg:province":"Pays de Loire",
    "sg:tags":[
        "equipment",
        "motor-cars",
        "transport"
    ],
    "wof:name":"Carrosserie Brondy",
    "wof:placetype":"venue"
},
  "geometry": {"coordinates":[-1.026532,46.723293],"type":"Point"}
}