{
  "type": "Feature",
  "properties": {
    "iso:country":"FR",
    "sg:address":"111, Chemin de Ronde, 78290 Croissy sur Seine",
    "sg:orig_category":"Non-Classified Establishments",
    "sg:phone":"+33 1 39 76 42 67",
    "sg:province":"Ile de France",
    "wof:name":"Lambert Moteurs S.a.",
    "wof:placetype":"venue"
},
  "geometry": {"coordinates":[2.118634,48.888718],"type":"Point"}
}