{
  "type": "Feature",
  "properties": {
    "iso:country":"FR",
    "sg:address":"14, Rue Contejean, 25200 Montb\u00e9liard",
    "sg:orig_category":"Non-Classified Establishments",
    "sg:phone":"+33 3 81 94 93 42",
    "sg:province":"Franche Comt\u00e9",
    "wof:name":"Loos S.a.",
    "wof:placetype":"venue"
},
  "geometry": {"coordinates":[6.795566,47.507668],"type":"Point"}
}