{
  "type": "Feature",
  "properties": {
    "addr:full":"15 Rue De Verdun 69170 Tarare Rhone-Alpes 69170",
    "addr:housenumber":"15",
    "addr:postcode":"69170;69170",
    "addr:street":"Rue De Verdun",
    "iso:country":"FR",
    "sg:address":"15 Rue De Verdun 69170 Tarare",
    "sg:classifiers":[
        {
            "category":"Shopping",
            "subcategory":"Crafts & Fabrics",
            "type":"Retail Goods"
        }
    ],
    "sg:phone":"+33 4 74 05 30 20",
    "sg:postcode":"69170",
    "sg:province":"Rhone-Alpes",
    "sg:tags":[
        "textile",
        "linen",
        "clothing"
    ],
    "wof:name":"Bel Air Industries",
    "wof:placetype":"venue"
},
  "geometry": {"coordinates":[4.436822,45.891212],"type":"Point"}
}