{
  "type": "Feature",
  "properties": {
    "addr:full":"9 rue Roger Salengro; Isbergues; 62330 Nord Pas-de-Calais 62330",
    "addr:housenumber":"9",
    "addr:postcode":"62330;62330",
    "addr:street":"Rue Roger Salengro",
    "iso:country":"FR",
    "sg:address":"9 rue Roger Salengro; Isbergues; 62330",
    "sg:classifiers":[
        {
            "category":"Banks & Credit Unions",
            "subcategory":"Bank",
            "type":"Services"
        }
    ],
    "sg:phone":"+33 21021665",
    "sg:postcode":"62330",
    "sg:province":"Nord Pas-de-Calais",
    "wof:name":"Banque Nationale De Paris",
    "wof:placetype":"venue"
},
  "geometry": {"coordinates":[2.466198,50.62077],"type":"Point"}
}