{
  "type": "Feature",
  "properties": {
    "iso:country":"FR",
    "sg:address":"ZA du Charbonnier",
    "sg:city":"Lamure sur Azergues",
    "sg:orig_category":"Non-Classified Establishments",
    "sg:phone":"+33 4 74 03 10 62",
    "sg:postcode":"69870",
    "sg:province":"Rhone-Alpes",
    "wof:name":"Mora E.r.m.i. S.a.r.l.",
    "wof:placetype":"venue"
},
  "geometry": {"coordinates":[4.49173,46.063274],"type":"Point"}
}