{
  "type": "Feature",
  "properties": {
    "addr:full":"2 Av Henri Barbusse 93000 Bobigny Ile de France 93000",
    "addr:postcode":"93000;ile;93000",
    "addr:street":"Av Henri Barbusse;France",
    "iso:country":"FR",
    "sg:address":"2 Av Henri Barbusse 93000 Bobigny",
    "sg:classifiers":[
        {
            "category":"Professional",
            "subcategory":"Advertising",
            "type":"Services"
        }
    ],
    "sg:phone":"+33 1 48 91 42 90",
    "sg:postcode":"93000",
    "sg:province":"Ile de France",
    "sg:tags":[
        "communication",
        "medium"
    ],
    "wof:name":"Jlc Conseils",
    "wof:placetype":"venue"
},
  "geometry": {"coordinates":[2.418025,48.903744],"type":"Point"}
}