{
  "type": "Feature",
  "properties": {
    "iso:country":"FR",
    "sg:address":"492 Route De Grenoble 06200 Nice",
    "sg:city":"Grenoble",
    "sg:classifiers":[
        {
            "category":"Manufacturing",
            "subcategory":"Rubber & Plastics",
            "type":"Manufacturing & Wholesale Goods"
        }
    ],
    "sg:phone":"+33 4 92 29 52 60",
    "sg:postcode":"38100",
    "sg:province":"Rhone-Alpes",
    "wof:name":"Euromaster France",
    "wof:placetype":"venue"
},
  "geometry": {"coordinates":[7.188504,43.712563],"type":"Point"}
}