{
  "type": "Feature",
  "properties": {
    "addr:full":"100, Av. du G\u00e9n\u00e9ral de Gaulle, 18500 Mehun sur Y\u00e8vre Marmagne Centre 18500",
    "addr:postcode":"18500;18500",
    "addr:street":"100 Av. Du Ge\u0301Ne\u0301Ral De Gaulle",
    "iso:country":"FR",
    "sg:address":"100, Av. du G\u00e9n\u00e9ral de Gaulle, 18500 Mehun sur Y\u00e8vre",
    "sg:city":"Marmagne",
    "sg:orig_category":"Non-Classified Establishments",
    "sg:phone":"+33 2 48 23 12 30",
    "sg:postcode":"18500",
    "sg:province":"Centre",
    "wof:name":"Etablissements Steiner Fr\u00e8res S.a.s.",
    "wof:placetype":"venue"
},
  "geometry": {"coordinates":[2.222105,47.143265],"type":"Point"}
}