{
  "type": "Feature",
  "properties": {
    "addr:full":"11 Pl Georges Cl\u00e9menceau 53100 Mayenne Pays de Loire 53100",
    "addr:housenumber":"11",
    "addr:postcode":"53100 mayenne;53100",
    "addr:street":"Pl Georges Cle\u0301Menceau",
    "iso:country":"FR",
    "sg:address":"11 Pl Georges Cl\u00e9menceau 53100 Mayenne",
    "sg:classifiers":[
        {
            "category":"Wholesale",
            "subcategory":"Meat",
            "type":"Manufacturing & Wholesale Goods"
        }
    ],
    "sg:phone":"+33 2 43 04 46 81",
    "sg:postcode":"53100",
    "sg:province":"Pays de Loire",
    "sg:tags":[
        "food",
        "cooked",
        "product",
        "related"
    ],
    "wof:name":"Thiol",
    "wof:placetype":"venue"
},
  "geometry": {"coordinates":[-0.619829,48.303268],"type":"Point"}
}