{
  "type": "Feature",
  "properties": {
    "addr:full":"Quartier des Blaches Peyrins Rhone-Alpes 26380",
    "addr:postcode":"26380",
    "addr:street":"Quartier Des Blaches;Rhone-Alpes",
    "iso:country":"FR",
    "sg:address":"Quartier des Blaches",
    "sg:city":"Peyrins",
    "sg:orig_category":"Non-Classified Establishments",
    "sg:phone":"+33 4 75 02 76 20",
    "sg:postcode":"26380",
    "sg:province":"Rhone-Alpes",
    "wof:name":"P\u00e9pini\u00e8res Pilaud S.c.e.a.",
    "wof:placetype":"venue"
},
  "geometry": {"coordinates":[5.063112,45.09156],"type":"Point"}
}