{
  "type": "Feature",
  "properties": {
    "addr:full":"B.P. 49, 44880 Sautron^^Rte de la Hubonni\u00e8re, 44880 Sautron Pays de Loire",
    "addr:postcode":"44880;44880",
    "addr:street":"B.P. 49;Hubonnie\u0300Re",
    "iso:country":"FR",
    "sg:address":"B.P. 49, 44880 Sautron^^Rte de la Hubonni\u00e8re, 44880 Sautron",
    "sg:orig_category":"Non-Classified Establishments",
    "sg:phone":"+33 2 40 63 85 80",
    "sg:province":"Pays de Loire",
    "wof:name":"Jourdain S.a.r.l.",
    "wof:placetype":"venue"
},
  "geometry": {"coordinates":[-1.672114,47.263714],"type":"Point"}
}