{
  "type": "Feature",
  "properties": {
    "addr:full":"8 ave du Pr\u00e9sident; Paris; 75016 Ile de France 75016",
    "addr:postcode":"75016;75016",
    "addr:street":"8 Ave Du Pre\u0301Sident Paris;France",
    "iso:country":"FR",
    "sg:address":"8 ave du Pr\u00e9sident; Paris; 75016",
    "sg:classifiers":[
        {
            "category":"Banks & Credit Unions",
            "subcategory":"Bank",
            "type":"Services"
        }
    ],
    "sg:phone":"+33 1 44 43 94 94",
    "sg:postcode":"75016",
    "sg:province":"Ile de France",
    "wof:name":"Soci\u00e9t\u00e9 G\u00e9n\u00e9rale",
    "wof:placetype":"venue"
},
  "geometry": {"coordinates":[2.25657,48.857079],"type":"Point"}
}