{
  "type": "Feature",
  "properties": {
    "addr:full":"72, Rue de la Chapelle, 74460 Marnaz Rhone-Alpes 74460",
    "addr:housenumber":"72",
    "addr:postcode":"74460;74460",
    "addr:street":"Rue De La Chapelle;Rhone-Alpes",
    "iso:country":"FR",
    "sg:address":"72, Rue de la Chapelle, 74460 Marnaz",
    "sg:orig_category":"Non-Classified Establishments",
    "sg:phone":"+33 4 50 98 49 71",
    "sg:postcode":"74460",
    "sg:province":"Rhone-Alpes",
    "wof:name":"Multidec S.a.r.l.",
    "wof:placetype":"venue"
},
  "geometry": {"coordinates":[6.525217,46.059326],"type":"Point"}
}