{
  "type": "Feature",
  "properties": {
    "addr:full":"B.P. 14, 18570 La Chapelle Saint Ursin^^Rte de Villeneuve, 18570 La Chapelle Saint Ursin Le Subdray Centre 18570",
    "addr:housenumber":"18570;18570;subdray",
    "addr:postcode":"18570",
    "addr:street":"B.P. 14;La",
    "iso:country":"FR",
    "sg:address":"B.P. 14, 18570 La Chapelle Saint Ursin^^Rte de Villeneuve, 18570 La Chapelle Saint Ursin",
    "sg:city":"Le Subdray",
    "sg:orig_category":"Non-Classified Establishments",
    "sg:phone":"+33 2 48 66 20 70",
    "sg:postcode":"18570",
    "sg:province":"Centre",
    "wof:name":"So.no.ma. S.a.",
    "wof:placetype":"venue"
},
  "geometry": {"coordinates":[2.276674,47.036385],"type":"Point"}
}