{
  "type": "Feature",
  "properties": {
    "iso:country":"FR",
    "sg:address":"Rue No\u00eblle Pons",
    "sg:city":"Nanterre",
    "sg:orig_category":"Non-Classified Establishments",
    "sg:phone":"+33 1 56 83 86 20",
    "sg:postcode":"92000",
    "sg:province":"Ile de France",
    "wof:name":"Esth\u00e9tique Actuelle S.a.r.l.",
    "wof:placetype":"venue"
},
  "geometry": {"coordinates":[2.228535,48.908085],"type":"Point"}
}