{
  "type": "Feature",
  "properties": {
    "addr:full":"27, Traverse Antoine Donaz, 13015 Marseille Poitou-Charentes",
    "addr:housenumber":"27",
    "addr:postcode":"13015",
    "addr:street":"Traverse Antoine Donaz",
    "iso:country":"FR",
    "sg:address":"27, Traverse Antoine Donaz, 13015 Marseille",
    "sg:orig_category":"Unclassifiable Establishments",
    "sg:phone":"+33 4 91 05 97 99",
    "sg:province":"Poitou-Charentes",
    "wof:name":"Tardy S.a.",
    "wof:placetype":"venue"
},
  "geometry": {"coordinates":[5.369787,43.323898],"type":"Point"}
}