{
  "type": "Feature",
  "properties": {
    "iso:country":"FR",
    "sg:address":"Bois Robert 49370 B\u00e9con Les Granits",
    "sg:classifiers":[
        {
            "category":"Professional",
            "subcategory":"Business Services",
            "type":"Services"
        }
    ],
    "sg:phone":"+33 2 41 77 90 14",
    "sg:postcode":"49370",
    "sg:province":"Pays de Loire",
    "sg:tags":[
        "training",
        "advice"
    ],
    "wof:name":"Institut Bois Robert",
    "wof:placetype":"venue"
},
  "geometry": {"coordinates":[-0.810879,47.506958],"type":"Point"}
}