{
  "type": "Feature",
  "properties": {
    "iso:country":"FR",
    "sg:address":"17 rue G\u00e9n\u00e9ral Leclerc; Chalon sur Sa\u00f4ne; 71100",
    "sg:city":"Chalon-sur-Sa\u00f4ne",
    "sg:classifiers":[
        {
            "category":"Banks & Credit Unions",
            "subcategory":"Bank",
            "type":"Services"
        }
    ],
    "sg:phone":"+33 3385483801",
    "sg:postcode":"71100",
    "sg:province":"Bourgogne",
    "wof:name":"Cr\u00e9dit Lyonnais",
    "wof:placetype":"venue"
},
  "geometry": {"coordinates":[4.853549,46.782398],"type":"Point"}
}