{
  "type": "Feature",
  "properties": {
    "addr:full":"B.P. 22, 36300 Le Blanc C\u00e9dex^^Z.I. des Groges, 36300 Le Blanc Le Blanc Centre 36300",
    "addr:housenumber":"le",
    "addr:postcode":"36300;36300;36300",
    "addr:street":"B.P. 22;Blanc;I.;Le Blanc",
    "iso:country":"FR",
    "sg:address":"B.P. 22, 36300 Le Blanc C\u00e9dex^^Z.I. des Groges, 36300 Le Blanc",
    "sg:city":"Le Blanc",
    "sg:orig_category":"Non-Classified Establishments",
    "sg:phone":"+33 2 54 28 30 30",
    "sg:postcode":"36300",
    "sg:province":"Centre",
    "wof:name":"Garnier S.a.",
    "wof:placetype":"venue"
},
  "geometry": {"coordinates":[1.059285,46.594685],"type":"Point"}
}