{
  "type": "Feature",
  "properties": {
    "addr:full":"37, Rte de Brumath, 67460 Souffelweyersheim Souffelweyersheim Alsace 67460",
    "addr:housenumber":"37",
    "addr:postcode":"67460;67460",
    "addr:street":"Rte De Brumath",
    "iso:country":"FR",
    "sg:address":"37, Rte de Brumath, 67460 Souffelweyersheim",
    "sg:city":"Souffelweyersheim",
    "sg:orig_category":"Unclassifiable Establishments",
    "sg:phone":"+33 3 88 20 01 24",
    "sg:postcode":"67460",
    "sg:province":"Alsace",
    "wof:name":"Cash Bureau 67 S.a.r.l.",
    "wof:placetype":"venue"
},
  "geometry": {"coordinates":[7.728537,48.632339],"type":"Point"}
}