{
  "type": "Feature",
  "properties": {
    "iso:country":"FR",
    "sg:address":"za",
    "sg:city":"Montmorillon 86300 Chauvigny",
    "sg:classifiers":[
        {
            "category":"Manufacturing",
            "subcategory":"Building Materials",
            "type":"Manufacturing & Wholesale Goods"
        }
    ],
    "sg:phone":"+33 5 49 61 50 00",
    "sg:postcode":"86300",
    "sg:province":"Poitou-Charentes",
    "sg:tags":[
        "glass",
        "ceramic"
    ],
    "wof:name":"Deshoulieres (sa)",
    "wof:placetype":"venue"
},
  "geometry": {"coordinates":[0.643404,46.569759],"type":"Point"}
}