{
  "type": "Feature",
  "properties": {
    "addr:full":"Ld Boudieu 15000 Aurillac Aurillac Auvergne 15000",
    "addr:postcode":"15000;15000",
    "addr:street":"Ld",
    "iso:country":"FR",
    "sg:address":"Ld Boudieu 15000 Aurillac",
    "sg:city":"Aurillac",
    "sg:classifiers":[
        {
            "category":"Home & Garden",
            "subcategory":"Furniture",
            "type":"Retail Goods"
        }
    ],
    "sg:phone":"+33 4 71 64 93 65",
    "sg:postcode":"15000",
    "sg:province":"Auvergne",
    "sg:tags":[
        "household",
        "wood"
    ],
    "wof:name":"La Varlope Sarl",
    "wof:placetype":"venue"
},
  "geometry": {"coordinates":[2.418721,44.907852],"type":"Point"}
}