{
  "type": "Feature",
  "properties": {
    "iso:country":"FR",
    "sg:address":"9, Chemin des Pierres, 25500 Morteau",
    "sg:orig_category":"Unclassifiable Establishments",
    "sg:phone":"+33 3 81 67 93 93",
    "sg:province":"Franche Comt\u00e9",
    "wof:name":"Soci\u00e9t\u00e9 Nouvelle A. Ruggeri S.a.r.l.",
    "wof:placetype":"venue"
},
  "geometry": {"coordinates":[6.613779,47.056931],"type":"Point"}
}