{
  "type": "Feature",
  "properties": {
    "addr:full":"Rue des Epinottes Montlebon Franche Comt\u00e9 25500",
    "addr:postcode":"25500",
    "addr:street":"Rue Des Epinottes;Franche Comte\u0301",
    "iso:country":"FR",
    "sg:address":"Rue des Epinottes",
    "sg:city":"Montlebon",
    "sg:orig_category":"Non-Classified Establishments",
    "sg:phone":"+33 3 81 67 01 26",
    "sg:postcode":"25500",
    "sg:province":"Franche Comt\u00e9",
    "wof:name":"Simonin S.a.r.l.",
    "wof:placetype":"venue"
},
  "geometry": {"coordinates":[6.602402,47.035225],"type":"Point"}
}