{
  "type": "Feature",
  "properties": {
    "addr:full":"B.P. 3075, 17035 La Rochelle C\u00e9dex^^35, Av. des Am\u00e9riques, 17000 La Rochelle Poitou-Charentes",
    "addr:housenumber":"17035",
    "addr:postcode":"17000",
    "addr:street":"B.P. 3075;Av. Des Ame\u0301Riques",
    "iso:country":"FR",
    "sg:address":"B.P. 3075, 17035 La Rochelle C\u00e9dex^^35, Av. des Am\u00e9riques, 17000 La Rochelle",
    "sg:orig_category":"Non-Classified Establishments",
    "sg:phone":"+33 5 46 07 66 88",
    "sg:province":"Poitou-Charentes",
    "wof:name":"Pr\u00e9pasia",
    "wof:placetype":"venue"
},
  "geometry": {"coordinates":[-1.151639,46.159435],"type":"Point"}
}