{
  "type": "Feature",
  "properties": {
    "addr:full":"2095, Av. de Paris, 59400 Cambrai Nord Pas-de-Calais",
    "addr:housenumber":"2095",
    "addr:postcode":"59400",
    "addr:street":"Av. De Paris",
    "iso:country":"FR",
    "sg:address":"2095, Av. de Paris, 59400 Cambrai",
    "sg:orig_category":"Unclassifiable Establishments",
    "sg:phone":"+33 3 27 37 71 49",
    "sg:province":"Nord Pas-de-Calais",
    "wof:name":"Miersman Pierre Et Fils S.a.",
    "wof:placetype":"venue"
},
  "geometry": {"coordinates":[3.221418,50.152714],"type":"Point"}
}