{
  "type": "Feature",
  "properties": {
    "addr:full":"16, Burospace, 91572 Bi\u00e8vres C\u00e9dex Bi\u00e8vres Champagne 08370",
    "addr:housenumber":"16",
    "addr:postcode":"91572;08370",
    "addr:street":"Burospace",
    "iso:country":"FR",
    "sg:address":"16, Burospace, 91572 Bi\u00e8vres C\u00e9dex",
    "sg:city":"Bi\u00e8vres",
    "sg:orig_category":"Non-Classified Establishments",
    "sg:phone":"+33 1 60 19 55 99",
    "sg:postcode":"08370",
    "sg:province":"Champagne",
    "wof:name":"Compagnie Fran\u00e7aise Woods S.a.",
    "wof:placetype":"venue"
},
  "geometry": {"coordinates":[2.215318,48.753994],"type":"Point"}
}