{
  "type": "Feature",
  "properties": {
    "iso:country":"FR",
    "sg:address":"La Varde 35400 Saint Malo",
    "sg:city":"Saint-Malo",
    "sg:orig_category":"Unclassifiable Establishments",
    "sg:phone":"+33 2 99 40 23 41",
    "sg:postcode":"35400",
    "sg:province":"Bretagne",
    "wof:name":"Shell Fish Viviers De Saint Malo S.a.",
    "wof:placetype":"venue"
},
  "geometry": {"coordinates":[-1.974209,48.682659],"type":"Point"}
}