{
  "type": "Feature",
  "properties": {
    "addr:full":"B.P. 8, 59465 Capinghem C\u00e9dex^^Rue de Zamin, 59160 Capinghem Nord Pas-de-Calais",
    "addr:housenumber":"8",
    "addr:postcode":"59465;59160",
    "addr:street":"B.P.;Zamin",
    "iso:country":"FR",
    "sg:address":"B.P. 8, 59465 Capinghem C\u00e9dex^^Rue de Zamin, 59160 Capinghem",
    "sg:orig_category":"Non-Classified Establishments",
    "sg:phone":"+33 3 20 17 63 17",
    "sg:province":"Nord Pas-de-Calais",
    "wof:name":"Mouille Michel S.a.",
    "wof:placetype":"venue"
},
  "geometry": {"coordinates":[2.961047,50.643799],"type":"Point"}
}