{
  "type": "Feature",
  "properties": {
    "iso:country":"FR",
    "sg:address":"71, Rue Albert Dhalenne, 93407 Saint Ouen C\u00e9dex",
    "sg:city":"Alb\u00e9",
    "sg:orig_category":"Non-Classified Establishments",
    "sg:phone":"+33 1 49 48 97 97",
    "sg:postcode":"67220",
    "sg:province":"Alsace",
    "wof:name":"Audit & Strat\u00e9gie S.a.",
    "wof:placetype":"venue"
},
  "geometry": {"coordinates":[2.333415,48.913906],"type":"Point"}
}