{
  "type": "Feature",
  "properties": {
    "addr:full":"25 Rue Du Mont Thabor 75001 Paris Ile de France 75001",
    "addr:housenumber":"25",
    "addr:postcode":"75001;75001",
    "addr:street":"Rue Du Mont Thabor",
    "iso:country":"FR",
    "sg:address":"25 Rue Du Mont Thabor 75001 Paris",
    "sg:classifiers":[
        {
            "category":"Manufacturing",
            "subcategory":"Textiles",
            "type":"Manufacturing & Wholesale Goods"
        }
    ],
    "sg:phone":"+33 1 42 60 11 18",
    "sg:postcode":"75001",
    "sg:province":"Ile de France",
    "sg:tags":[
        "clothing",
        "accessory"
    ],
    "wof:name":"Echapmode Sarl",
    "wof:placetype":"venue"
},
  "geometry": {"coordinates":[2.32523,48.866638],"type":"Point"}
}