{
  "type": "Feature",
  "properties": {
    "addr:full":"Z.A.E. 2 - Les Portes de l'Oise Chambly Picardie 60230",
    "addr:housenumber":"2",
    "addr:postcode":"60230",
    "addr:street":"Z.A.E.;Les Portes De L'Oise;Picardie",
    "iso:country":"FR",
    "sg:address":"Z.A.E. 2 - Les Portes de l'Oise",
    "sg:city":"Chambly",
    "sg:orig_category":"Non-Classified Establishments",
    "sg:phone":"+33 1 30 28 98 00",
    "sg:postcode":"60230",
    "sg:province":"Picardie",
    "wof:name":"Mecadrum S.a.",
    "wof:placetype":"venue"
},
  "geometry": {"coordinates":[2.236679,49.165916],"type":"Point"}
}