{
  "type": "Feature",
  "properties": {
    "iso:country":"FR",
    "sg:address":"Causse D Auge Zae Du Causse D Auge 48000 Mende",
    "sg:classifiers":[
        {
            "category":"Home & Garden",
            "subcategory":"Furniture",
            "type":"Retail Goods"
        }
    ],
    "sg:phone":"+33 4 66 49 29 06",
    "sg:postcode":"48000",
    "sg:province":"Languedoc-Roussillon",
    "sg:tags":[
        "household",
        "wood"
    ],
    "wof:name":"Techniligne",
    "wof:placetype":"venue"
},
  "geometry": {"coordinates":[3.559072,44.456753],"type":"Point"}
}