{
  "type": "Feature",
  "properties": {
    "addr:full":"931, Av. du Grand Arietaz, 73000 Chamb\u00e9ry Rhone-Alpes 73000",
    "addr:postcode":"73000;73000",
    "addr:street":"931 Av. Du Grand Arietaz",
    "iso:country":"FR",
    "sg:address":"931, Av. du Grand Arietaz, 73000 Chamb\u00e9ry",
    "sg:orig_category":"Unclassifiable Establishments",
    "sg:phone":"+33 4 79 62 24 73",
    "sg:postcode":"73000",
    "sg:province":"Rhone-Alpes",
    "wof:name":"Fonlupt Environnement S.a.",
    "wof:placetype":"venue"
},
  "geometry": {"coordinates":[5.900584,45.584984],"type":"Point"}
}