{
  "type": "Feature",
  "properties": {
    "addr:full":"Zac De Savine 44570 Trignac Pays de Loire 44570",
    "addr:postcode":"44570;44570",
    "addr:street":"Zac De Savine",
    "iso:country":"FR",
    "sg:address":"Zac De Savine 44570 Trignac",
    "sg:classifiers":[
        {
            "category":"Travel",
            "subcategory":"Hotels & Motels",
            "type":"Entertainment"
        }
    ],
    "sg:phone":"+33 2 40 90 35 80",
    "sg:postcode":"44570",
    "sg:province":"Pays de Loire",
    "sg:tags":[
        "hotels",
        "business",
        "restaurant"
    ],
    "wof:name":"Buffalo Grill",
    "wof:placetype":"venue"
},
  "geometry": {"coordinates":[-2.187869,47.317436],"type":"Point"}
}