{
  "type": "Feature",
  "properties": {
    "iso:country":"FR",
    "sg:address":"41, Rue Mercier - Z.I. de MItry Compans, 77290 Compans",
    "sg:orig_category":"Unclassifiable Establishments",
    "sg:phone":"+33 1 64 67 47 47",
    "sg:province":"Ile de France",
    "wof:name":"Viking Direct S.a.r.l.",
    "wof:placetype":"venue"
},
  "geometry": {"coordinates":[2.619585,48.984165],"type":"Point"}
}