{
  "type": "Feature",
  "properties": {
    "addr:full":"3 rue de Castellane 75008 Paris Ile de France 75008",
    "addr:housenumber":"3",
    "addr:postcode":"75008;75008",
    "addr:street":"Rue De Castellane",
    "iso:country":"FR",
    "sg:address":"3 rue de Castellane 75008 Paris",
    "sg:classifiers":[
        {
            "category":"Food & Beverages",
            "subcategory":"Ethnic Foods",
            "type":"Retail Goods"
        }
    ],
    "sg:phone":"+33 1 47 42 14 50",
    "sg:postcode":"75008",
    "sg:province":"Ile de France",
    "sg:tags":[
        "japanese"
    ],
    "wof:name":"Takashimaya France Sa",
    "wof:placetype":"venue"
},
  "geometry": {"coordinates":[2.32559,48.87199],"type":"Point"}
}