{
  "type": "Feature",
  "properties": {
    "iso:country":"FR",
    "sg:address":"3 av Robert Sol\u00e9au; Antibes",
    "sg:classifiers":[
        {
            "category":"Banks & Credit Unions",
            "subcategory":"Bank",
            "type":"Services"
        }
    ],
    "sg:phone":"+33 3393348612",
    "sg:province":"Auvergne",
    "wof:name":"Cr\u00e9dit Foncier De France",
    "wof:placetype":"venue"
},
  "geometry": {"coordinates":[7.120616,43.580986],"type":"Point"}
}