{
  "type": "Feature",
  "properties": {
    "addr:full":"7 Rue Des Fusill\u00e9s 77107 Meaux Cedex Ile de France",
    "addr:housenumber":"7",
    "addr:postcode":"77107;ile",
    "addr:street":"Rue Des Fusille\u0301S",
    "iso:country":"FR",
    "sg:address":"7 Rue Des Fusill\u00e9s 77107 Meaux Cedex",
    "sg:classifiers":[
        {
            "category":"Manufacturing",
            "subcategory":"Motor Vehicles & Parts",
            "type":"Manufacturing & Wholesale Goods"
        }
    ],
    "sg:phone":"+33 1 64 34 31 63",
    "sg:province":"Ile de France",
    "sg:tags":[
        "industrial",
        "tool",
        "motor-cars",
        "metallurgy",
        "equipment",
        "metalworking",
        "transport"
    ],
    "wof:name":"Meaux Specialites Autos",
    "wof:placetype":"venue"
},
  "geometry": {"coordinates":[2.880449,48.953293],"type":"Point"}
}