{
  "type": "Feature",
  "properties": {
    "addr:full":"D\u00e9p\u00f4t des Basses fermes Fublaines Ile de France 77470",
    "addr:postcode":"77470",
    "addr:street":"Fublaines",
    "iso:country":"FR",
    "sg:address":"D\u00e9p\u00f4t des Basses fermes",
    "sg:city":"Fublaines",
    "sg:orig_category":"Unclassifiable Establishments",
    "sg:phone":"+33 1 64 33 20 75",
    "sg:postcode":"77470",
    "sg:province":"Ile de France",
    "wof:name":"Soci\u00e9t\u00e9 P\u00e9trorep S.a.",
    "wof:placetype":"venue"
},
  "geometry": {"coordinates":[2.934528,48.943897],"type":"Point"}
}