{
  "type": "Feature",
  "properties": {
    "iso:country":"FR",
    "sg:address":"2 Rue Orne 55400 Etain",
    "sg:classifiers":[
        {
            "category":"Wholesale",
            "subcategory":"Medical Equipment & Supplies",
            "type":"Manufacturing & Wholesale Goods"
        }
    ],
    "sg:phone":"+33 3 29 87 86 22",
    "sg:postcode":"55400",
    "sg:province":"Lorraine",
    "sg:tags":[
        "instrument",
        "health",
        "-",
        "precision"
    ],
    "wof:name":"Scp",
    "wof:placetype":"venue"
},
  "geometry": {"coordinates":[5.633098,49.213963],"type":"Point"}
}