{
  "type": "Feature",
  "properties": {
    "addr:full":"B.P. 69, 84601 Valr\u00e9as C\u00e9dex^^Rte de Baume - ZI La Gr\u00e8ze, 84600 Valr\u00e9as Provence-Alpes-C\u00f4te d'Azur",
    "addr:postcode":"84601;84600",
    "addr:street":"B.P. 69;Zi La Gre\u0300Ze",
    "iso:country":"FR",
    "sg:address":"B.P. 69, 84601 Valr\u00e9as C\u00e9dex^^Rte de Baume - ZI La Gr\u00e8ze, 84600 Valr\u00e9as",
    "sg:orig_category":"Non-Classified Establishments",
    "sg:phone":"+33 4 90 28 56 90",
    "sg:province":"Provence-Alpes-C\u00f4te d'Azur",
    "wof:name":"S.i.c.a.f. S.a. - Soci\u00e9t\u00e9 Industrielle De Conditionnement \u00e0 Fa\u00e7on",
    "wof:placetype":"venue"
},
  "geometry": {"coordinates":[4.911945,44.359257],"type":"Point"}
}