{
  "type": "Feature",
  "properties": {
    "addr:full":"Voie n\u00b0 5 - B\u00e2t. 8 Lab\u00e8ge Midi Pyr\u00e9n\u00e9es 31670",
    "addr:housenumber":"5 ba\u0302t",
    "addr:postcode":"31670",
    "addr:street":"Voie N\u00b0",
    "iso:country":"FR",
    "sg:address":"Voie n\u00b0 5 - B\u00e2t. 8",
    "sg:city":"Lab\u00e8ge",
    "sg:orig_category":"Unclassifiable Establishments",
    "sg:phone":"+33 5 61 00 46 43",
    "sg:postcode":"31670",
    "sg:province":"Midi Pyr\u00e9n\u00e9es",
    "wof:name":"C.c.d. S.a.r.l. - Capitole Communication Digitale",
    "wof:placetype":"venue"
},
  "geometry": {"coordinates":[1.527111,43.529713],"type":"Point"}
}