{
  "type": "Feature",
  "properties": {
    "addr:full":"1 Av De L'Industrie BP 14 61200 Argentan Argentan Basse Normandie 61200",
    "addr:housenumber":"14",
    "addr:postcode":"61200;61200",
    "addr:street":"Av De L'Industrie Bp",
    "iso:country":"FR",
    "sg:address":"1 Av De L'Industrie BP 14 61200 Argentan",
    "sg:city":"Argentan",
    "sg:classifiers":[
        {
            "category":"Wholesale",
            "subcategory":"Machinery & Supplies",
            "type":"Manufacturing & Wholesale Goods"
        }
    ],
    "sg:phone":"+33 2 33 36 38 00",
    "sg:postcode":"61200",
    "sg:province":"Basse Normandie",
    "sg:tags":[
        "handling",
        "material",
        "-",
        "machine",
        "equipment",
        "engineering",
        "mechanical"
    ],
    "wof:name":"Mecanique Industrie Chimie (mic)",
    "wof:placetype":"venue"
},
  "geometry": {"coordinates":[-0.024769,48.731827],"type":"Point"}
}