{
  "type": "Feature",
  "properties": {
    "iso:country":"FR",
    "sg:address":"720 R D'Arras 62158 Saulty",
    "sg:classifiers":[
        {
            "category":"Professional",
            "type":"Services"
        }
    ],
    "sg:phone":"+33 3 21 48 23 57",
    "sg:province":"Nord Pas-de-Calais",
    "sg:tags":[
        "transport",
        "road"
    ],
    "wof:name":"Ste Exploitation Transports Dhot Sa",
    "wof:placetype":"venue"
},
  "geometry": {"coordinates":[2.533481,50.217243],"type":"Point"}
}