{
  "type": "Feature",
  "properties": {
    "addr:full":"720 R D'Arras 62158 Saulty Nord Pas-de-Calais",
    "addr:housenumber":"720",
    "addr:postcode":"62158",
    "addr:street":"R D'Arras",
    "iso:country":"FR",
    "sg:address":"720 R D'Arras 62158 Saulty",
    "sg:classifiers":[
        {
            "category":"Professional",
            "type":"Services"
        }
    ],
    "sg:phone":"+33 3 21 48 23 57",
    "sg:province":"Nord Pas-de-Calais",
    "sg:tags":[
        "transport",
        "road"
    ],
    "wof:name":"Ste Exploitation Transports Dhot Sa",
    "wof:placetype":"venue"
},
  "geometry": {"coordinates":[2.533481,50.217243],"type":"Point"}
}