{
  "type": "Feature",
  "properties": {
    "addr:full":"Parc d'Activit\u00e9s du Moulin ZI la Casserie Dampierre les Bois Franche Comt\u00e9 25490",
    "addr:postcode":"25490",
    "addr:street":"Zi La Casserie Dampierre Les;Franche Comte\u0301",
    "iso:country":"FR",
    "sg:address":"Parc d'Activit\u00e9s du Moulin ZI la Casserie",
    "sg:city":"Dampierre les Bois",
    "sg:orig_category":"Non-Classified Establishments",
    "sg:phone":"+33 3 81 93 00 50",
    "sg:postcode":"25490",
    "sg:province":"Franche Comt\u00e9",
    "wof:name":"Soci\u00e9t\u00e9 De D\u00e9capage Industriel Jolissaint S.a.",
    "wof:placetype":"venue"
},
  "geometry": {"coordinates":[6.91146,47.506489],"type":"Point"}
}