{
  "type": "Feature",
  "properties": {
    "iso:country":"FR",
    "sg:address":"ZA Bois de la Chocque - Espace Cr\u00e9atis",
    "sg:city":"Saint Quentin",
    "sg:orig_category":"Non-Classified Establishments",
    "sg:phone":"+33 3 23 67 74 40",
    "sg:postcode":"02100",
    "sg:province":"Picardie",
    "wof:name":"Groupe Frex S.a.r.l.",
    "wof:placetype":"venue"
},
  "geometry": {"coordinates":[3.288445,49.84795],"type":"Point"}
}