{
  "type": "Feature",
  "properties": {
    "iso:country":"FR",
    "sg:address":"494, Av. du Prado, 13008 Marseille",
    "sg:orig_category":"Unclassifiable Establishments",
    "sg:phone":"+33 4 91 23 70 70",
    "sg:province":"Provence-Alpes-C\u00f4te d'Azur",
    "wof:name":"C.f.c.m.m. - Caisse F\u00e9d\u00e9rale Cr\u00e9dit Mutuel M\u00e9diterran\u00e9e",
    "wof:placetype":"venue"
},
  "geometry": {"coordinates":[5.38086,43.266201],"type":"Point"}
}