{
  "type": "Feature",
  "properties": {
    "iso:country":"FR",
    "sg:address":"17 rue de la Gravelle 08800 LES HAUTES RIVIERES",
    "sg:city":"Deville",
    "sg:orig_category":"Car-Washing Devices",
    "sg:phone":"+33 3 24 53 49 48",
    "sg:postcode":"08800",
    "sg:province":"Champagne",
    "wof:name":"Usine Du Paquis S.a.",
    "wof:placetype":"venue"
},
  "geometry": {"coordinates":[4.848497,49.875061],"type":"Point"}
}