{
  "type": "Feature",
  "properties": {
    "addr:full":"928, Av. du Loiret, 45160 Olivet Olivet Centre 45160",
    "addr:housenumber":"928",
    "addr:postcode":"45160;45160",
    "addr:street":"Av. Du Loiret",
    "iso:country":"FR",
    "sg:address":"928, Av. du Loiret, 45160 Olivet",
    "sg:city":"Olivet",
    "sg:orig_category":"Unclassifiable Establishments",
    "sg:phone":"+33 2 38 66 34 48",
    "sg:postcode":"45160",
    "sg:province":"Centre",
    "wof:name":"Comptoir De Bois Daniel Sabbe S.a.",
    "wof:placetype":"venue"
},
  "geometry": {"coordinates":[1.902602,47.878128],"type":"Point"}
}