{
  "type": "Feature",
  "properties": {
    "addr:full":"8, Rue L\u00e9on Patou - P\u00f4le Technologique Henri Farman, 51100 Reims Champagne",
    "addr:housenumber":"8",
    "addr:postcode":"51100",
    "addr:street":"Rue Le\u0301On Patou Po\u0302Le;Farman",
    "iso:country":"FR",
    "sg:address":"8, Rue L\u00e9on Patou - P\u00f4le Technologique Henri Farman, 51100 Reims",
    "sg:orig_category":"Non-Classified Establishments",
    "sg:phone":"+33 3 26 47 20 71",
    "sg:province":"Champagne",
    "wof:name":"I.l.a.f. Fe - Institut De Logistique D'audit Et De Formation",
    "wof:placetype":"venue"
},
  "geometry": {"coordinates":[4.028445,49.26284],"type":"Point"}
}