{
  "type": "Feature",
  "properties": {
    "iso:country":"FR",
    "sg:address":"7 Chem Notre Dame De La Ronde 28100 Dreux",
    "sg:city":"Dreux",
    "sg:classifiers":[
        {
            "category":"Utilities",
            "subcategory":"Electric",
            "type":"Services"
        }
    ],
    "sg:phone":"+33 2 37 46 36 09",
    "sg:postcode":"28100",
    "sg:province":"Centre",
    "sg:tags":[
        "electricity",
        "electronic",
        "electrical",
        "equipment"
    ],
    "wof:name":"Forclum Val De L'eure",
    "wof:placetype":"venue"
},
  "geometry": {"coordinates":[1.364025,48.752125],"type":"Point"}
}