{
  "type": "Feature",
  "properties": {
    "addr:full":"95 rue du G\u00e9n\u00e9ral de Gaulle 68800 Thann Thann Alsace 68800",
    "addr:housenumber":"95",
    "addr:postcode":"68800;68800",
    "addr:street":"Rue Du Ge\u0301Ne\u0301Ral De Gaulle",
    "iso:country":"FR",
    "sg:address":"95 rue du G\u00e9n\u00e9ral de Gaulle 68800 Thann",
    "sg:city":"Thann",
    "sg:orig_category":"Hydrochloric Acid Hcl",
    "sg:phone":"+33 3 89 38 46 00",
    "sg:postcode":"68800",
    "sg:province":"Alsace",
    "wof:name":"Albemarle Ppc Sa",
    "wof:placetype":"venue"
},
  "geometry": {"coordinates":[7.10874,47.808071],"type":"Point"}
}