{
  "type": "Feature",
  "properties": {
    "iso:country":"FR",
    "sg:address":"Route de Saint Loup 70160 Saverney",
    "sg:classifiers":[
        {
            "category":"Manufacturing",
            "subcategory":"Chemicals & Compounds",
            "type":"Manufacturing & Wholesale Goods"
        }
    ],
    "sg:phone":"+33 3 84 96 33 00",
    "sg:province":"Franche Comt\u00e9",
    "sg:tags":[
        "granule",
        "pigment"
    ],
    "wof:name":"Orsa Granulats Franche-comt\u00e9 Sa",
    "wof:placetype":"venue"
},
  "geometry": {"coordinates":[-90.077759,29.95369],"type":"Point"}
}