{
  "type": "Feature",
  "properties": {
    "iso:country":"FR",
    "sg:address":"141/143, Rue du 1er Mai - ZA du Petit Nanterre 4, 92000 Nanterre",
    "sg:orig_category":"Unclassifiable Establishments",
    "sg:phone":"+33 1 47 86 74 40",
    "sg:province":"Ile de France",
    "wof:name":"Titanox A\u00e9rospace S.a.s",
    "wof:placetype":"venue"
},
  "geometry": {"coordinates":[2.194875,48.888084],"type":"Point"}
}