{
  "type": "Feature",
  "properties": {
    "addr:full":"B.P. 01, 13467 Marseille C\u00e9dex 16^^Usine de l'Estaque, 13016 Marseille Poitou-Charentes",
    "addr:postcode":"13467;13016",
    "addr:street":"B.P. 01",
    "iso:country":"FR",
    "sg:address":"B.P. 01, 13467 Marseille C\u00e9dex 16^^Usine de l'Estaque, 13016 Marseille",
    "sg:orig_category":"Non-Classified Establishments",
    "sg:phone":"+33 4 91 09 43 15",
    "sg:province":"Poitou-Charentes",
    "wof:name":"M\u00e9taleurop",
    "wof:placetype":"venue"
},
  "geometry": {"coordinates":[5.376415,43.308338],"type":"Point"}
}