{
  "type": "Feature",
  "properties": {
    "addr:full":"ZI du Pr\u00e9 Avrin Maul\u00e9vrier Pays de Loire 49360",
    "addr:postcode":"49360",
    "addr:street":"Zi Du Pre\u0301 Avrin",
    "iso:country":"FR",
    "sg:address":"ZI du Pr\u00e9 Avrin",
    "sg:city":"Maul\u00e9vrier",
    "sg:orig_category":"Non-Classified Establishments",
    "sg:phone":"+33 2 41 55 06 41",
    "sg:postcode":"49360",
    "sg:province":"Pays de Loire",
    "wof:name":"Anjou Composites S.a.r.l.",
    "wof:placetype":"venue"
},
  "geometry": {"coordinates":[-0.745819,47.007374],"type":"Point"}
}