{
  "type": "Feature",
  "properties": {
    "addr:full":"17 Rue Des Parachutistes 02110 Vaux Andigny Picardie 02110",
    "addr:housenumber":"17",
    "addr:postcode":"02110;02110",
    "addr:street":"Rue Des Parachutistes",
    "iso:country":"FR",
    "sg:address":"17 Rue Des Parachutistes 02110 Vaux Andigny",
    "sg:classifiers":[
        {
            "category":"Professional",
            "subcategory":"Engineering",
            "type":"Services"
        }
    ],
    "sg:phone":"+33 3 23 66 88 16",
    "sg:postcode":"02110",
    "sg:province":"Picardie",
    "sg:tags":[
        "machine",
        "-",
        "mechanical"
    ],
    "wof:name":"Zehnder Group - Vaux Andigny",
    "wof:placetype":"venue"
},
  "geometry": {"coordinates":[3.43535,49.973919],"type":"Point"}
}