{
  "type": "Feature",
  "properties": {
    "addr:full":"3, Bd Louis Nail, 56100 Lorient Lorient Bretagne 56100",
    "addr:housenumber":"3",
    "addr:postcode":"56100;56100",
    "addr:street":"Bd Louis Nail",
    "iso:country":"FR",
    "sg:address":"3, Bd Louis Nail, 56100 Lorient",
    "sg:city":"Lorient",
    "sg:orig_category":"Unclassifiable Establishments",
    "sg:phone":"+33 2 97 37 39 65",
    "sg:postcode":"56100",
    "sg:province":"Bretagne",
    "wof:name":"Etablissement Picaud J.f. E.u.r.l.",
    "wof:placetype":"venue"
},
  "geometry": {"coordinates":[-3.364272,47.732033],"type":"Point"}
}