{
  "type": "Feature",
  "properties": {
    "addr:full":"B.P. 17, 19101 Brive la Gaillarde C\u00e9dex^^Z.I. Teinchurier, 19100 Brive la Gaillarde Limousin 19100",
    "addr:postcode":"19101;19100;19100",
    "addr:street":"B.P. 17",
    "iso:country":"FR",
    "sg:address":"B.P. 17, 19101 Brive la Gaillarde C\u00e9dex^^Z.I. Teinchurier, 19100 Brive la Gaillarde",
    "sg:orig_category":"Non-Classified Establishments",
    "sg:phone":"+33 5 55 86 43 21",
    "sg:postcode":"19100",
    "sg:province":"Limousin",
    "wof:name":"Be.vi.cor. S.a. - B\u00e9tail Viande Corr\u00e8ze",
    "wof:placetype":"venue"
},
  "geometry": {"coordinates":[1.53587,45.157036],"type":"Point"}
}