{
  "type": "Feature",
  "properties": {
    "iso:country":"FR",
    "sg:address":"314, Rue du Marcelly, 74460 Marnaz",
    "sg:orig_category":"Non-Classified Establishments",
    "sg:phone":"+33 4 50 96 11 00",
    "sg:postcode":"74460",
    "sg:province":"Rhone-Alpes",
    "wof:name":"D\u00e9pann'elec S.a.",
    "wof:placetype":"venue"
},
  "geometry": {"coordinates":[6.532042,46.067219],"type":"Point"}
}