{
  "type": "Feature",
  "properties": {
    "iso:country":"FR",
    "sg:address":"2 Avenue Montboulon 77165 St Soupplets",
    "sg:classifiers":[
        {
            "category":"Wholesale",
            "subcategory":"Machinery & Supplies",
            "type":"Manufacturing & Wholesale Goods"
        }
    ],
    "sg:phone":"+33 1 60 61 56 00",
    "sg:province":"Ile de France",
    "sg:tags":[
        "equipment",
        "precision"
    ],
    "wof:name":"Electronique Techno Informatique Industr Sarl",
    "wof:placetype":"venue"
},
  "geometry": {"coordinates":[2.806565,49.031681],"type":"Point"}
}