{
  "type": "Feature",
  "properties": {
    "iso:country":"FR",
    "sg:address":"B.P. 74, 67402 Illkirch C\u00e9dex^^4, Rue de l'Industrie, 67400 Illkirch Graffenstaden",
    "sg:city":"Geispolsheim",
    "sg:orig_category":"Non-Classified Establishments",
    "sg:phone":"+33 3 88 66 07 10",
    "sg:postcode":"67400",
    "sg:province":"Alsace",
    "wof:name":"Ruch S.a.",
    "wof:placetype":"venue"
},
  "geometry": {"coordinates":[7.731668,48.530483],"type":"Point"}
}