{
  "type": "Feature",
  "properties": {
    "addr:full":"B.P. 16, 51160 Mareuil sur Ay^^44, rue Carnot, 51160 Mareuil sur Ay Champagne",
    "addr:postcode":"51160;51160",
    "addr:street":"B.P. 16;Mareuil;Rue Carnot;Mareuil",
    "iso:country":"FR",
    "sg:address":"B.P. 16, 51160 Mareuil sur Ay^^44, rue Carnot, 51160 Mareuil sur Ay",
    "sg:orig_category":"Non-Classified Establishments",
    "sg:phone":"+33 3 26 52 60 27",
    "sg:province":"Champagne",
    "wof:name":"Janin S.a.",
    "wof:placetype":"venue"
},
  "geometry": {"coordinates":[4.010445,49.052212],"type":"Point"}
}