{
  "type": "Feature",
  "properties": {
    "iso:country":"FR",
    "sg:address":"157, Av. Charles de Gaulle, 92200 Neuilly sur Seine",
    "sg:orig_category":"Non-Classified Establishments",
    "sg:phone":"+33 1 41 43 91 05",
    "sg:province":"Ile de France",
    "wof:name":"Eva Air",
    "wof:placetype":"venue"
},
  "geometry": {"coordinates":[2.263762,48.883278],"type":"Point"}
}