{
  "type": "Feature",
  "properties": {
    "iso:country":"FR",
    "sg:address":"Lux 09000 Serres sur Arget",
    "sg:orig_category":"Non-Classified Establishments",
    "sg:phone":"+33 5 61 65 38 28",
    "sg:postcode":"09000",
    "sg:province":"Midi Pyr\u00e9n\u00e9es",
    "wof:name":"Apys G.i.e.",
    "wof:placetype":"venue"
},
  "geometry": {"coordinates":[1.515324,42.980442],"type":"Point"}
}