{
  "type": "Feature",
  "properties": {
    "iso:country":"FR",
    "sg:address":"45, Rue Maurice Berteaux, 78600 Le Mesnil le Roi",
    "sg:orig_category":"Non-Classified Establishments",
    "sg:phone":"+33 1 34 93 93 94",
    "sg:province":"Ile de France",
    "wof:name":"Soci\u00e9t\u00e9 Hygi\u00e8ne Nettoyage Et Jardins S.a.r.l.",
    "wof:placetype":"venue"
},
  "geometry": {"coordinates":[2.119003,48.92469],"type":"Point"}
}