{
  "type": "Feature",
  "properties": {
    "iso:country":"FR",
    "sg:address":"B.P. 26, 66162 Le Boulou C\u00e9dex^^1, Rue des Vignes - Rte du Mas Linas - ZA Nord, 66160 Le Boulou",
    "sg:orig_category":"Non-Classified Establishments",
    "sg:phone":"+33 4 68 83 15 89",
    "sg:postcode":"66160",
    "sg:province":"Languedoc-Roussillon",
    "wof:name":"Bouchons Abel S.a.",
    "wof:placetype":"venue"
},
  "geometry": {"coordinates":[2.830395,42.52483],"type":"Point"}
}