{
  "type": "Feature",
  "properties": {
    "addr:full":"ZA chemin de Talmont le Christan Longeville sur Mer Pays de Loire 85560",
    "addr:postcode":"85560",
    "addr:street":"Za Chemin De Talmont Le Christan",
    "iso:country":"FR",
    "sg:address":"ZA chemin de Talmont le Christan",
    "sg:city":"Longeville sur Mer",
    "sg:orig_category":"Non-Classified Establishments",
    "sg:phone":"+33 2 51 20 40 00",
    "sg:postcode":"85560",
    "sg:province":"Pays de Loire",
    "wof:name":"Vend\u00e9e B\u00e9ton",
    "wof:placetype":"venue"
},
  "geometry": {"coordinates":[-1.48987,46.424656],"type":"Point"}
}