{
  "type": "Feature",
  "properties": {
    "iso:country":"FR",
    "sg:address":"21, Av. Paul Vaillant Couturier, 93120 La Courneuve",
    "sg:orig_category":"Non-Classified Establishments",
    "sg:phone":"+33 1 48 36 18 65",
    "sg:province":"Ile de France",
    "wof:name":"L.n.a. Conseils S.a.r.l.",
    "wof:placetype":"venue"
},
  "geometry": {"coordinates":[2.408559,48.919212],"type":"Point"}
}