{
  "type": "Feature",
  "properties": {
    "addr:full":"69, Av. Gaston Boissier, 78220 Viroflay Ile de France",
    "addr:postcode":"78220;ile",
    "addr:street":"69 Av. Gaston Boissier",
    "iso:country":"FR",
    "sg:address":"69, Av. Gaston Boissier, 78220 Viroflay",
    "sg:orig_category":"Non-Classified Establishments",
    "sg:phone":"+33 1 30 24 39 58",
    "sg:province":"Ile de France",
    "wof:name":"Matraform S.a.r.l.",
    "wof:placetype":"venue"
},
  "geometry": {"coordinates":[2.179185,48.800343],"type":"Point"}
}