{
  "type": "Feature",
  "properties": {
    "iso:country":"FR",
    "sg:address":"24 avenue Hoche 75008 Paris",
    "sg:classifiers":[
        {
            "category":"Home & Garden",
            "subcategory":"Carpets & Floor Coverings",
            "type":"Retail Goods"
        }
    ],
    "sg:phone":"+33 1 58 56 36 00",
    "sg:postcode":"75008",
    "sg:province":"Ile de France",
    "sg:tags":[
        "animal",
        "skin"
    ],
    "wof:name":"Tcim Sa",
    "wof:placetype":"venue"
},
  "geometry": {"coordinates":[2.300477,48.876289],"type":"Point"}
}