{
  "type": "Feature",
  "properties": {
    "addr:full":"8 Jean Rostand BP 223 81305 Graulhet Midi Pyr\u00e9n\u00e9es",
    "addr:housenumber":"8;223",
    "addr:postcode":"81305",
    "addr:street":"Jean Rostand Bp",
    "iso:country":"FR",
    "sg:address":"8",
    "sg:city":"Jean Rostand BP 223 81305 Graulhet",
    "sg:classifiers":[
        {
            "category":"Manufacturing",
            "subcategory":"Leather Goods",
            "type":"Manufacturing & Wholesale Goods"
        }
    ],
    "sg:phone":"+33 5 63 42 13 40",
    "sg:province":"Midi Pyr\u00e9n\u00e9es",
    "sg:tags":[
        "shoe"
    ],
    "wof:name":"Bernard Fabre Et Fils (sarl)",
    "wof:placetype":"venue"
},
  "geometry": {"coordinates":[1.990768,43.762951],"type":"Point"}
}