{
  "type": "Feature",
  "properties": {
    "addr:full":"65 rue Planchat 75020 Paris Ile de France 75020",
    "addr:housenumber":"65",
    "addr:postcode":"75020;75020",
    "addr:street":"Rue Planchat",
    "iso:country":"FR",
    "sg:address":"65 rue Planchat 75020 Paris",
    "sg:classifiers":[
        {
            "category":"Manufacturing",
            "subcategory":"Textiles",
            "type":"Manufacturing & Wholesale Goods"
        }
    ],
    "sg:phone":"+33 1 49 52 05 06",
    "sg:postcode":"75020",
    "sg:province":"Ile de France",
    "sg:tags":[
        "natural"
    ],
    "wof:name":"Lotes Sa",
    "wof:placetype":"venue"
},
  "geometry": {"coordinates":[2.395947,48.856403],"type":"Point"}
}