{
  "type": "Feature",
  "properties": {
    "addr:full":"160, Bd Haussman, 75008 Paris Ile de France 75008",
    "addr:housenumber":"160",
    "addr:postcode":"75008;75008",
    "addr:street":"Bd Haussman",
    "iso:country":"FR",
    "sg:address":"160, Bd Haussman, 75008 Paris",
    "sg:orig_category":"Non-Classified Establishments",
    "sg:phone":"+33 1 45 62 51 32",
    "sg:postcode":"75008",
    "sg:province":"Ile de France",
    "wof:name":"Bourdais S.a.",
    "wof:placetype":"venue"
},
  "geometry": {"coordinates":[2.310496,48.875225],"type":"Point"}
}