{
  "type": "Feature",
  "properties": {
    "addr:full":"21390 Normier Normier Bourgogne 21390",
    "addr:postcode":"21390;21390",
    "iso:country":"FR",
    "sg:address":"21390 Normier",
    "sg:city":"Normier",
    "sg:classifiers":[
        {
            "category":"Building & Trades",
            "subcategory":"Construction",
            "type":"Services"
        }
    ],
    "sg:phone":"+33 3 80 64 67 41",
    "sg:postcode":"21390",
    "sg:province":"Bourgogne",
    "sg:tags":[
        "work",
        "public"
    ],
    "wof:name":"M. Surceaux Eric",
    "wof:placetype":"venue"
},
  "geometry": {"coordinates":[4.433138,47.366043],"type":"Point"}
}