{
  "type": "Feature",
  "properties": {
    "addr:full":"22170 Plouagat Plouagat Bretagne 22170",
    "addr:postcode":"22170;22170",
    "addr:street":"Plouagat",
    "iso:country":"FR",
    "sg:address":"22170 Plouagat",
    "sg:city":"Plouagat",
    "sg:orig_category":"Unclassifiable Establishments",
    "sg:phone":"+33 2 96 79 51 51",
    "sg:postcode":"22170",
    "sg:province":"Bretagne",
    "wof:name":"Laboratoire Delta S.a.s.",
    "wof:placetype":"venue"
},
  "geometry": {"coordinates":[-2.999714,48.536285],"type":"Point"}
}