{
  "type": "Feature",
  "properties": {
    "iso:country":"FR",
    "sg:address":"1 Rue Du Duremont Zone Industrielle 59960 Neuville En Ferrain",
    "sg:classifiers":[
        {
            "category":"Manufacturing",
            "subcategory":"Motor Vehicles & Parts",
            "type":"Manufacturing & Wholesale Goods"
        }
    ],
    "sg:phone":"+33 3 20 94 75 19",
    "sg:postcode":"59960",
    "sg:province":"Nord Pas-de-Calais",
    "sg:tags":[
        "engine",
        "machine",
        "engineering",
        "-",
        "mechanical"
    ],
    "wof:name":"Etablissements Herbeaux Engrenages",
    "wof:placetype":"venue"
},
  "geometry": {"coordinates":[3.15239,50.750355],"type":"Point"}
}