{
  "type": "Feature",
  "properties": {
    "iso:country":"FR",
    "sg:address":"7, Rue des Vicaires, 59800 Lille",
    "sg:orig_category":"Unclassifiable Establishments",
    "sg:phone":"+33 3 20 21 82 22",
    "sg:province":"Nord Pas-de-Calais",
    "wof:name":"S.l.i.c.e. S.a.r.l.",
    "wof:placetype":"venue"
},
  "geometry": {"coordinates":[3.084962,50.644871],"type":"Point"}
}