{
  "type": "Feature",
  "properties": {
    "addr:full":"161, Bd Salvador Alliend\u00e9, 44812 Saint Herblain C\u00e9dex^^161, Bd Salvador Alliend\u00e9, 44800 Saint Herbla Pays de Loire",
    "addr:housenumber":"161;44812",
    "addr:postcode":"44800;herbla",
    "addr:street":"Bd Salvador Alliende\u0301;Bd Salvador Alliende\u0301",
    "iso:country":"FR",
    "sg:address":"161, Bd Salvador Alliend\u00e9, 44812 Saint Herblain C\u00e9dex^^161, Bd Salvador Alliend\u00e9, 44800 Saint Herbla",
    "sg:orig_category":"Non-Classified Establishments",
    "sg:phone":"+33 2 40 92 18 60",
    "sg:province":"Pays de Loire",
    "wof:name":"Sacer Atlantique S.a.",
    "wof:placetype":"venue"
},
  "geometry": {"coordinates":[-1.635174,47.221752],"type":"Point"}
}