{
  "type": "Feature",
  "properties": {
    "addr:full":"ZA des Lats Messimy Rhone-Alpes 69510",
    "addr:postcode":"69510",
    "addr:street":"Za Des Lats;Rhone-Alpes",
    "iso:country":"FR",
    "sg:address":"ZA des Lats",
    "sg:city":"Messimy",
    "sg:orig_category":"Unclassifiable Establishments",
    "sg:phone":"+33 4 78 45 01 62",
    "sg:postcode":"69510",
    "sg:province":"Rhone-Alpes",
    "wof:name":"Roger Gaurand S.a.",
    "wof:placetype":"venue"
},
  "geometry": {"coordinates":[4.674172,45.696644],"type":"Point"}
}