{
  "type": "Feature",
  "properties": {
    "addr:full":"8 Rue De L'Europe Zac De Font Ratel 38640 Claix Rhone-Alpes 38640",
    "addr:housenumber":"8",
    "addr:postcode":"38640;38640",
    "addr:street":"Rue De L'Europe Zac De Font Ratel",
    "iso:country":"FR",
    "sg:address":"8 Rue De L'Europe Zac De Font Ratel 38640 Claix",
    "sg:classifiers":[
        {
            "category":"Utilities",
            "subcategory":"Electric",
            "type":"Services"
        }
    ],
    "sg:phone":"+33 4 76 98 18 70",
    "sg:postcode":"38640",
    "sg:province":"Rhone-Alpes",
    "sg:tags":[
        "electricity",
        "electronic",
        "electrical",
        "equipment"
    ],
    "wof:name":"Spie Trindel",
    "wof:placetype":"venue"
},
  "geometry": {"coordinates":[5.681641,45.122978],"type":"Point"}
}