{
  "type": "Feature",
  "properties": {
    "iso:country":"FR",
    "sg:address":"30, Rue Louis Eudier, 76600 Le Havre",
    "sg:orig_category":"Unclassifiable Establishments",
    "sg:phone":"+33 2 35 24 59 80",
    "sg:province":"Haute Normandie",
    "wof:name":"Norelec Normandie Bretagne",
    "wof:placetype":"venue"
},
  "geometry": {"coordinates":[0.130143,49.48613],"type":"Point"}
}