{
  "type": "Feature",
  "properties": {
    "iso:country":"FR",
    "sg:address":"Zi Du Champ De Mars 42600 Savigneux",
    "sg:classifiers":[
        {
            "category":"Shopping",
            "type":"Retail Goods"
        }
    ],
    "sg:phone":"+33 4 77 58 71 30",
    "sg:postcode":"42600",
    "sg:province":"Rhone-Alpes",
    "sg:tags":[
        "metallurgy",
        "finished",
        "-",
        "metalworking",
        "metallic"
    ],
    "wof:name":"Martin Belaysoud M B Dumas",
    "wof:placetype":"venue"
},
  "geometry": {"coordinates":[4.080594,45.606167],"type":"Point"}
}