{
  "type": "Feature",
  "properties": {
    "iso:country":"FR",
    "sg:address":"1141 avenue Andr\u00e9 Lasquin 74700 Sallanches",
    "sg:classifiers":[
        {
            "category":"Manufacturing",
            "subcategory":"Motor Vehicles & Parts",
            "type":"Manufacturing & Wholesale Goods"
        }
    ],
    "sg:phone":"+33 4 50 58 45 03",
    "sg:province":"Rhone-Alpes",
    "sg:tags":[
        "precision",
        "mechanic"
    ],
    "wof:name":"Franck Et Sylvand Sarl",
    "wof:placetype":"venue"
},
  "geometry": {"coordinates":[6.635276,45.94894],"type":"Point"}
}