{
  "type": "Feature",
  "properties": {
    "addr:full":"7 av Lestonan; Ergu\u00e9 Gab\u00e9ric; 29500 Ergu\u00e9-Gab\u00e9ric Bretagne 29500",
    "addr:postcode":"29500;29500",
    "addr:street":"Av Lestonan;Bretagne",
    "iso:country":"FR",
    "sg:address":"7 av Lestonan; Ergu\u00e9 Gab\u00e9ric; 29500",
    "sg:city":"Ergu\u00e9-Gab\u00e9ric",
    "sg:classifiers":[
        {
            "category":"Banks & Credit Unions",
            "subcategory":"Bank",
            "type":"Services"
        }
    ],
    "sg:phone":"+33 2 98 59 62 22",
    "sg:postcode":"29500",
    "sg:province":"Bretagne",
    "wof:name":"Cr\u00e9dit Agricole",
    "wof:placetype":"venue"
},
  "geometry": {"coordinates":[-4.021429,48.019581],"type":"Point"}
}