{
  "type": "Feature",
  "properties": {
    "addr:full":"7 Rue Beau Soleil Zone Industrielle 22400 Lamballe Lamballe Bretagne 22400",
    "addr:housenumber":"7",
    "addr:postcode":"22400;22400",
    "addr:street":"Rue Beau Soleil Zone Industrielle",
    "iso:country":"FR",
    "sg:address":"7 Rue Beau Soleil Zone Industrielle 22400 Lamballe",
    "sg:city":"Lamballe",
    "sg:classifiers":[
        {
            "category":"Shopping",
            "type":"Retail Goods"
        }
    ],
    "sg:phone":"+33 2 96 31 18 55",
    "sg:postcode":"22400",
    "sg:province":"Bretagne",
    "sg:tags":[
        "metallurgy",
        "finished",
        "-",
        "metalworking",
        "metallic"
    ],
    "wof:name":"Tolerie Fine Electronique (tfe)",
    "wof:placetype":"venue"
},
  "geometry": {"coordinates":[-2.539697,48.428795],"type":"Point"}
}