{
  "type": "Feature",
  "properties": {
    "addr:full":"B.P. 42 Villefranche sur Sa\u00f4ne C\u00e9dex Rhone-Alpes 69652",
    "addr:postcode":"69652",
    "addr:street":"B.P. 42 Villefranche;Rhone-Alpes",
    "iso:country":"FR",
    "sg:address":"B.P. 42",
    "sg:city":"Villefranche sur Sa\u00f4ne C\u00e9dex",
    "sg:orig_category":"Non-Classified Establishments",
    "sg:phone":"+33 4 74 02 98 47",
    "sg:postcode":"69652",
    "sg:province":"Rhone-Alpes",
    "wof:name":"Groupe Bulteau S.a.",
    "wof:placetype":"venue"
},
  "geometry": {"coordinates":[4.71875,45.989868],"type":"Point"}
}