{
  "type": "Feature",
  "properties": {
    "addr:full":"Rte de Bayon - Zone Industrielle Charmes Lorraine 88130",
    "addr:postcode":"88130",
    "addr:street":"Rte De Bayon Zone Industrielle Charmes Lorraine",
    "iso:country":"FR",
    "sg:address":"Rte de Bayon - Zone Industrielle",
    "sg:city":"Charmes",
    "sg:orig_category":"Unclassifiable Establishments",
    "sg:phone":"+33 3 29 38 05 05",
    "sg:postcode":"88130",
    "sg:province":"Lorraine",
    "wof:name":"Patisfrance S.a.",
    "wof:placetype":"venue"
},
  "geometry": {"coordinates":[6.290925,48.372807],"type":"Point"}
}