{
  "type": "Feature",
  "properties": {
    "iso:country":"FR",
    "sg:address":"45, All\u00e9e du Mens, 69100 Villeurbanne",
    "sg:orig_category":"Non-Classified Establishments",
    "sg:phone":"+33 4 78 79 10 48",
    "sg:postcode":"69100",
    "sg:province":"Rhone-Alpes",
    "wof:name":"E.g.m.m. S.a.r.l. - Entreprise G\u00e9n\u00e9rale De Mesures M\u00e9caniques",
    "wof:placetype":"venue"
},
  "geometry": {"coordinates":[4.90622,45.780361],"type":"Point"}
}