{
  "type": "Feature",
  "properties": {
    "iso:country":"FR",
    "sg:address":"Domaine Ch\u00e2teau des Belles Eaux",
    "sg:city":"Caux",
    "sg:orig_category":"Non-Classified Establishments",
    "sg:phone":"+33 4 67 09 30 95",
    "sg:postcode":"34720",
    "sg:province":"Languedoc-Roussillon",
    "wof:name":"Ch\u00e2teau Des Belles Eaux",
    "wof:placetype":"venue"
},
  "geometry": {"coordinates":[3.366892,43.505764],"type":"Point"}
}