{
  "type": "Feature",
  "properties": {
    "addr:full":"Zae Des Cr\u00eats De Viry Sud 74540 Alby Sur Ch\u00e9ran Rhone-Alpes 74540",
    "addr:postcode":"74540;74540",
    "addr:street":"Des;Rhone-Alpes",
    "iso:country":"FR",
    "sg:address":"Zae Des Cr\u00eats De Viry Sud 74540 Alby Sur Ch\u00e9ran",
    "sg:classifiers":[
        {
            "category":"Shopping",
            "subcategory":"Bicycles & Sporting Goods",
            "type":"Retail Goods"
        }
    ],
    "sg:phone":"+33 4 50 68 30 06",
    "sg:postcode":"74540",
    "sg:province":"Rhone-Alpes",
    "sg:tags":[
        "product",
        "sport",
        "miscellaneous"
    ],
    "wof:name":"Fkf Sports Sa",
    "wof:placetype":"venue"
},
  "geometry": {"coordinates":[6.079054,45.751701],"type":"Point"}
}