{
  "type": "Feature",
  "properties": {
    "iso:country":"FR",
    "sg:address":"58 rue Cl\u00e9ment Marot 69007 Lyon",
    "sg:orig_category":"Car Roof Racks",
    "sg:phone":"+33 4 72 73 13 83",
    "sg:province":"Rhone-Alpes",
    "wof:name":"Ets Munier Sarl",
    "wof:placetype":"venue"
},
  "geometry": {"coordinates":[4.836844,45.73576],"type":"Point"}
}