{
  "type": "Feature",
  "properties": {
    "addr:full":"359 avenue des Etats-Unis 31200 Toulouse Midi Pyr\u00e9n\u00e9es",
    "addr:housenumber":"359",
    "addr:postcode":"31200",
    "addr:street":"Avenue Des Etats-Unis",
    "iso:country":"FR",
    "sg:address":"359 avenue des Etats-Unis 31200 Toulouse",
    "sg:classifiers":[
        {
            "category":"Shopping",
            "subcategory":"Stationery & Office Supplies",
            "type":"Retail Goods"
        }
    ],
    "sg:phone":"+33 5 61 70 18 00",
    "sg:province":"Midi Pyr\u00e9n\u00e9es",
    "sg:tags":[
        "furniture"
    ],
    "wof:name":"Aux Docks Du Bureau Sarl",
    "wof:placetype":"venue"
},
  "geometry": {"coordinates":[1.417899,43.659801],"type":"Point"}
}