{
  "type": "Feature",
  "properties": {
    "iso:country":"FR",
    "sg:address":"ZI",
    "sg:city":"des Grandes Combes 01700 BEYNOST",
    "sg:classifiers":[
        {
            "category":"Manufacturing",
            "subcategory":"Metals",
            "type":"Manufacturing & Wholesale Goods"
        }
    ],
    "sg:phone":"+33 4 78 55 17 19",
    "sg:postcode":"01700",
    "sg:province":"Rhone-Alpes",
    "sg:tags":[
        "metallurgy",
        "metalworking",
        "processing"
    ],
    "wof:name":"Chromeca",
    "wof:placetype":"venue"
},
  "geometry": {"coordinates":[5.002065,45.840061],"type":"Point"}
}