{
  "type": "Feature",
  "properties": {
    "addr:full":"570, Rte de Nice, 06600 Antibes Provence-Alpes-C\u00f4te d'Azur",
    "addr:housenumber":"570",
    "addr:postcode":"06600",
    "addr:street":"Rte De Nice",
    "iso:country":"FR",
    "sg:address":"570, Rte de Nice, 06600 Antibes",
    "sg:orig_category":"Non-Classified Establishments",
    "sg:phone":"+33 4 93 74 74 00",
    "sg:province":"Provence-Alpes-C\u00f4te d'Azur",
    "wof:name":"H.4.d. S.a.r.l. - Soci\u00e9t\u00e9 Hygi\u00e8ne 4d",
    "wof:placetype":"venue"
},
  "geometry": {"coordinates":[7.123414,43.605019],"type":"Point"}
}