{
  "type": "Feature",
  "properties": {
    "iso:country":"FR",
    "sg:address":"301 Boulevard Danielle Casanova 13014 Marseille",
    "sg:classifiers":[
        {
            "category":"Shopping",
            "type":"Retail Goods"
        }
    ],
    "sg:phone":"+33 4 95 05 50 50",
    "sg:province":"Poitou-Charentes",
    "sg:tags":[
        "metallurgy",
        "finished",
        "-",
        "metalworking",
        "metallic"
    ],
    "wof:name":"Sud Robinetterie Industrie Sri Robinet Et Valve (fabrication)",
    "wof:placetype":"venue"
},
  "geometry": {"coordinates":[5.378505,43.33485],"type":"Point"}
}