{
  "type": "Feature",
  "properties": {
    "addr:full":"La Lev\u00e9e de la Loire Cours les Barres Centre 18320",
    "addr:postcode":"18320",
    "addr:street":"La Leve\u0301E De La Loire Cours Les Barres",
    "iso:country":"FR",
    "sg:address":"La Lev\u00e9e de la Loire",
    "sg:city":"Cours les Barres",
    "sg:orig_category":"Unclassifiable Establishments",
    "sg:phone":"+33 3 86 38 74 99",
    "sg:postcode":"18320",
    "sg:province":"Centre",
    "wof:name":"Dugama S.a.r.l.",
    "wof:placetype":"venue"
},
  "geometry": {"coordinates":[3.067655,47.027119],"type":"Point"}
}