{
  "type": "Feature",
  "properties": {
    "iso:country":"FR",
    "sg:address":"14, Rue Saint Ferr\u00e9ol, 13001 Marseille",
    "sg:orig_category":"Non-Classified Establishments",
    "sg:phone":"+33 4 91 54 20 65",
    "sg:province":"Provence-Alpes-C\u00f4te d'Azur",
    "wof:name":"Universal Assurances S.a.r.l.",
    "wof:placetype":"venue"
},
  "geometry": {"coordinates":[5.376929,43.295582],"type":"Point"}
}