{
  "type": "Feature",
  "properties": {
    "addr:full":"B.P. 4, 59133 Phalempin^^1, Rue Winston Churchill, 59160 Lomme Nord Pas-de-Calais",
    "addr:housenumber":"4",
    "addr:postcode":"59133;59160;pas-de-calais",
    "addr:street":"B.P.;Rue Winston Churchill",
    "iso:country":"FR",
    "sg:address":"B.P. 4, 59133 Phalempin^^1, Rue Winston Churchill, 59160 Lomme",
    "sg:orig_category":"Non-Classified Establishments",
    "sg:phone":"+33 3 20 00 17 60",
    "sg:province":"Nord Pas-de-Calais",
    "wof:name":"Favier S.a.",
    "wof:placetype":"venue"
},
  "geometry": {"coordinates":[2.961047,50.643799],"type":"Point"}
}