{
  "type": "Feature",
  "properties": {
    "iso:country":"FR",
    "sg:address":"56 rue Emile Zola; Brest",
    "sg:classifiers":[
        {
            "category":"Banks & Credit Unions",
            "subcategory":"Bank",
            "type":"Services"
        }
    ],
    "sg:phone":"+33 3398806835",
    "sg:province":"Bretagne",
    "wof:name":"Banque Sofinco",
    "wof:placetype":"venue"
},
  "geometry": {"coordinates":[-4.487657,48.387421],"type":"Point"}
}