{
  "type": "Feature",
  "properties": {
    "addr:full":"Rte de l'Aviation Anglet Aquitaine 64600",
    "addr:postcode":"64600",
    "addr:street":"Rte De L'Aviation",
    "iso:country":"FR",
    "sg:address":"Rte de l'Aviation",
    "sg:city":"Anglet",
    "sg:orig_category":"Unclassifiable Establishments",
    "sg:phone":"+33 5 59 41 25 25",
    "sg:postcode":"64600",
    "sg:province":"Aquitaine",
    "wof:name":"Brigantine S.a.",
    "wof:placetype":"venue"
},
  "geometry": {"coordinates":[-1.523591,43.463451],"type":"Point"}
}