{
  "type": "Feature",
  "properties": {
    "iso:country":"FR",
    "sg:address":"Avenue De L Europe Zone Industrielle 49450 St Macaire En Mauges",
    "sg:classifiers":[
        {
            "category":"Shopping",
            "subcategory":"Luggage & Leather Goods",
            "type":"Retail Goods"
        }
    ],
    "sg:phone":"+33 2 41 49 77 02",
    "sg:postcode":"49450",
    "sg:province":"Pays de Loire",
    "sg:tags":[
        "shoe"
    ],
    "wof:name":"Pindiere",
    "wof:placetype":"venue"
},
  "geometry": {"coordinates":[-1.064815,47.091267],"type":"Point"}
}