{
  "type": "Feature",
  "properties": {
    "iso:country":"FR",
    "sg:address":"1903",
    "sg:city":"Jacques Cartier; S. Herblain",
    "sg:classifiers":[
        {
            "category":"Banks & Credit Unions",
            "subcategory":"Bank",
            "type":"Services"
        }
    ],
    "sg:phone":"+33 3340923290",
    "sg:province":"Nord Pas-de-Calais",
    "wof:name":"Cr\u00e9dit Mutuel Direction, De R\u00e9seau Rive Nord",
    "wof:placetype":"venue"
},
  "geometry": {"coordinates":[-71.943024,45.411949],"type":"Point"}
}