{
  "type": "Feature",
  "properties": {
    "iso:country":"FR",
    "sg:address":"9 R Fleury Neuvesel 69700 Givors",
    "sg:classifiers":[
        {
            "category":"Shopping",
            "subcategory":"Clothing, Apparel, & Fashions",
            "type":"Retail Goods"
        }
    ],
    "sg:phone":"+33 4 72 24 23 48",
    "sg:postcode":"69700",
    "sg:province":"Rhone-Alpes",
    "sg:tags":[
        "textile",
        "clothing",
        "clothes"
    ],
    "wof:name":"Mme Lorente Rousset Danielle",
    "wof:placetype":"venue"
},
  "geometry": {"coordinates":[4.762761,45.584751],"type":"Point"}
}