{
  "type": "Feature",
  "properties": {
    "addr:full":"Rue Ettore Bugatti 67038 Strasbourg Cedex 2 Strasbourg Alsace 67000",
    "addr:postcode":"67038;67000",
    "addr:street":"Rue Ettore Bugatti",
    "iso:country":"FR",
    "sg:address":"Rue Ettore Bugatti 67038 Strasbourg Cedex 2",
    "sg:city":"Strasbourg",
    "sg:classifiers":[
        {
            "category":"Shopping",
            "subcategory":"Gifts & Souvenirs",
            "type":"Retail Goods"
        }
    ],
    "sg:phone":"+33 3 88 77 00 88",
    "sg:postcode":"67000",
    "sg:province":"Alsace",
    "sg:tags":[
        "product",
        "miscellaneous"
    ],
    "wof:name":"Brigitte France Sarl",
    "wof:placetype":"venue"
},
  "geometry": {"coordinates":[7.790115,48.604111],"type":"Point"}
}