{
  "type": "Feature",
  "properties": {
    "addr:full":"55, Bd Dequevauvilliers, 92230 Gennevilliers Ile de France 92230",
    "addr:housenumber":"55",
    "addr:postcode":"92230;ile;92230",
    "addr:street":"Bd Dequevauvilliers;France",
    "iso:country":"FR",
    "sg:address":"55, Bd Dequevauvilliers, 92230 Gennevilliers",
    "sg:orig_category":"Non-Classified Establishments",
    "sg:phone":"+33 1 47 94 66 23",
    "sg:postcode":"92230",
    "sg:province":"Ile de France",
    "wof:name":"D.r.m. Machines Outils S.a.",
    "wof:placetype":"venue"
},
  "geometry": {"coordinates":[2.307173,48.945805],"type":"Point"}
}