{
  "type": "Feature",
  "properties": {
    "iso:country":"FR",
    "sg:address":"21, Rue Martin Luther King - ZI, 34500 B\u00e9ziers",
    "sg:orig_category":"Unclassifiable Establishments",
    "sg:phone":"+33 4 67 62 03 10",
    "sg:province":"Languedoc-Roussillon",
    "wof:name":"Glaces Antolin S.a.",
    "wof:placetype":"venue"
},
  "geometry": {"coordinates":[3.216105,43.344234],"type":"Point"}
}