{
  "type": "Feature",
  "properties": {
    "iso:country":"FR",
    "sg:address":"5, Rue du Parc, 93150 Le Blanc Mesnil",
    "sg:orig_category":"Unclassifiable Establishments",
    "sg:phone":"+33 1 48 14 34 80",
    "sg:province":"Ile de France",
    "wof:name":"Thyssen France S.a.",
    "wof:placetype":"venue"
},
  "geometry": {"coordinates":[2.43991,48.937679],"type":"Point"}
}