{
  "type": "Feature",
  "properties": {
    "iso:country":"FR",
    "sg:address":"225, Rue Centre Arco, 21160 Marsannay la C\u00f4te",
    "sg:city":"Marsannay-la-C\u00f4te",
    "sg:orig_category":"Unclassifiable Establishments",
    "sg:phone":"+33 3 80 52 41 00",
    "sg:postcode":"21160",
    "sg:province":"Bourgogne",
    "wof:name":"Thyssen Ascenseurs S.a.s.",
    "wof:placetype":"venue"
},
  "geometry": {"coordinates":[5.009467,47.275497],"type":"Point"}
}