{
  "type": "Feature",
  "properties": {
    "addr:full":"B.P. 48, 77370 Nangis^^ZI, 77370 Nangis Ile de France 77370",
    "addr:postcode":"77370;77370;77370",
    "addr:street":"B.P. 48;Ile De France",
    "iso:country":"FR",
    "sg:address":"B.P. 48, 77370 Nangis^^ZI, 77370 Nangis",
    "sg:orig_category":"Non-Classified Establishments",
    "sg:phone":"+33 1 64 60 44 00",
    "sg:postcode":"77370",
    "sg:province":"Ile de France",
    "wof:name":"Camom S.n.c.",
    "wof:placetype":"venue"
},
  "geometry": {"coordinates":[2.948903,48.507874],"type":"Point"}
}