{
  "type": "Feature",
  "properties": {
    "addr:full":"43, Rue de Caumartin, 75436 Paris Ile de France",
    "addr:housenumber":"43",
    "addr:postcode":"75436",
    "addr:street":"Rue De Caumartin",
    "iso:country":"FR",
    "sg:address":"43, Rue de Caumartin, 75436 Paris",
    "sg:orig_category":"Non-Classified Establishments",
    "sg:phone":"+33 1 40 17 83 00",
    "sg:province":"Ile de France",
    "wof:name":"Anvar E.p.i.c.",
    "wof:placetype":"venue"
},
  "geometry": {"coordinates":[2.328055,48.872822],"type":"Point"}
}