{
  "type": "Feature",
  "properties": {
    "iso:country":"FR",
    "sg:address":"Zone d'Activit\u00e9s",
    "sg:city":"Meauc\u00e9",
    "sg:orig_category":"Unclassifiable Establishments",
    "sg:phone":"+33 2 37 53 60 80",
    "sg:postcode":"28240",
    "sg:province":"Centre",
    "wof:name":"A.g.p.i. S.a. - Arts Graphiques Du Perche Imprimerie",
    "wof:placetype":"venue"
},
  "geometry": {"coordinates":[1.00241,48.48624],"type":"Point"}
}