{
  "type": "Feature",
  "properties": {
    "addr:full":"Rte De Montreuil 62630 Etaples Nord Pas-de-Calais 62630",
    "addr:postcode":"62630;62630",
    "addr:street":"Rte De Montreuil;Etaples Nord",
    "iso:country":"FR",
    "sg:address":"Rte De Montreuil 62630 Etaples",
    "sg:classifiers":[
        {
            "category":"Manufacturing",
            "subcategory":"Motor Vehicles & Parts",
            "type":"Manufacturing & Wholesale Goods"
        }
    ],
    "sg:phone":"+33 3 21 09 82 00",
    "sg:postcode":"62630",
    "sg:province":"Nord Pas-de-Calais",
    "sg:tags":[
        "engine",
        "machine",
        "engineering",
        "-",
        "mechanical"
    ],
    "wof:name":"Valeo Equipements Electriques Moteur",
    "wof:placetype":"venue"
},
  "geometry": {"coordinates":[1.642955,50.512535],"type":"Point"}
}