{
  "type": "Feature",
  "properties": {
    "iso:country":"FR",
    "sg:address":"Chemin de la Gueule de Bois",
    "sg:city":"Villevaud\u00e9",
    "sg:orig_category":"Unclassifiable Establishments",
    "sg:phone":"+33 1 60 26 21 19",
    "sg:postcode":"77410",
    "sg:province":"Ile de France",
    "wof:name":"Cartonneries De La Dhuys S.a.",
    "wof:placetype":"venue"
},
  "geometry": {"coordinates":[2.662545,48.901661],"type":"Point"}
}