{
  "type": "Feature",
  "properties": {
    "addr:full":"Z.I. Br\u00fblon Pays de Loire 72350",
    "addr:postcode":"72350",
    "addr:street":"Z.I. Bru\u0302Lon Pays",
    "iso:country":"FR",
    "sg:address":"Z.I.",
    "sg:city":"Br\u00fblon",
    "sg:orig_category":"Non-Classified Establishments",
    "sg:phone":"+33 2 43 62 15 15",
    "sg:postcode":"72350",
    "sg:province":"Pays de Loire",
    "wof:name":"F.p.e.e. S.a. - Fermetures Pour Economie D'energie",
    "wof:placetype":"venue"
},
  "geometry": {"coordinates":[-0.221174,47.904461],"type":"Point"}
}