{
  "type": "Feature",
  "properties": {
    "iso:country":"FR",
    "sg:address":"4 Rue Georges Sadoul 30900 Nimes",
    "sg:classifiers":[
        {
            "category":"Professional",
            "subcategory":"Advertising",
            "type":"Services"
        }
    ],
    "sg:phone":"+33 4 66 62 24 34",
    "sg:postcode":"30900",
    "sg:province":"Languedoc-Roussillon",
    "sg:tags":[
        "information",
        "medium",
        "communication"
    ],
    "wof:name":"Giraudy",
    "wof:placetype":"venue"
},
  "geometry": {"coordinates":[4.335507,43.818245],"type":"Point"}
}