{
  "type": "Feature",
  "properties": {
    "addr:full":"10 Chemin Des Barres Zi 71530 Crissey Crissey Bourgogne 71530",
    "addr:housenumber":"10",
    "addr:postcode":"71530;71530",
    "addr:street":"Chemin Des Barres Zi",
    "iso:country":"FR",
    "sg:address":"10 Chemin Des Barres Zi 71530 Crissey",
    "sg:city":"Crissey",
    "sg:classifiers":[
        {
            "category":"Manufacturing",
            "subcategory":"Rubber & Plastics",
            "type":"Manufacturing & Wholesale Goods"
        }
    ],
    "sg:phone":"+33 3 85 97 10 00",
    "sg:postcode":"71530",
    "sg:province":"Bourgogne",
    "wof:name":"Valmonld Sa",
    "wof:placetype":"venue"
},
  "geometry": {"coordinates":[4.88201,46.816959],"type":"Point"}
}