{
  "type": "Feature",
  "properties": {
    "iso:country":"FR",
    "sg:address":"1, Rue Marcel Langer - ZA la Piche, 31600 Seysses",
    "sg:orig_category":"Non-Classified Establishments",
    "sg:phone":"+33 5 61 56 16 16",
    "sg:postcode":"31600",
    "sg:province":"Midi Pyr\u00e9n\u00e9es",
    "wof:name":"D.l. Garonne S.a.",
    "wof:placetype":"venue"
},
  "geometry": {"coordinates":[1.313195,43.413681],"type":"Point"}
}