{
  "type": "Feature",
  "properties": {
    "iso:country":"FR",
    "sg:address":"Rte De Pau Le Mas 40805 Aire Sur L'Adour",
    "sg:classifiers":[
        {
            "category":"Banks & Credit Unions",
            "subcategory":"Financial Services",
            "type":"Services"
        }
    ],
    "sg:phone":"+33 5 58 71 43 43",
    "sg:province":"Champagne",
    "sg:tags":[
        "banking",
        "insurance",
        "institution",
        "finance"
    ],
    "wof:name":"Caisse Regionale De Credit Agricole D'aquitaine",
    "wof:placetype":"venue"
},
  "geometry": {"coordinates":[-0.272541,43.605255],"type":"Point"}
}