{
  "type": "Feature",
  "properties": {
    "addr:full":"ZA de Choisy Remiremont Lorraine 88200",
    "addr:postcode":"88200",
    "addr:street":"Za De Choisy",
    "iso:country":"FR",
    "sg:address":"ZA de Choisy",
    "sg:city":"Remiremont",
    "sg:orig_category":"Unclassifiable Establishments",
    "sg:phone":"+33 3 29 23 00 01",
    "sg:postcode":"88200",
    "sg:province":"Lorraine",
    "wof:name":"Althoffer Fonderie Et Construction M\u00e9canique S.a.",
    "wof:placetype":"venue"
},
  "geometry": {"coordinates":[6.589865,48.017303],"type":"Point"}
}