{
  "type": "Feature",
  "properties": {
    "addr:full":"8 Rue Manurhin 68120 Richwiller Richwiller Alsace 68120",
    "addr:housenumber":"8",
    "addr:postcode":"68120;68120",
    "addr:street":"Rue Manurhin",
    "iso:country":"FR",
    "sg:address":"8 Rue Manurhin 68120 Richwiller",
    "sg:city":"Richwiller",
    "sg:classifiers":[
        {
            "category":"Autos & Motor Vehicles",
            "subcategory":"Recreational Vehicle Sales",
            "type":"Retail Goods"
        }
    ],
    "sg:phone":"+33 3 89 50 78 78",
    "sg:postcode":"68120",
    "sg:province":"Alsace",
    "sg:tags":[
        "industrial",
        "tr",
        "motor-cars",
        "-",
        "metalworking",
        "metallic",
        "metallurgy",
        "finished"
    ],
    "wof:name":"Murrelectronik Sa",
    "wof:placetype":"venue"
},
  "geometry": {"coordinates":[7.303097,47.787121],"type":"Point"}
}