{
  "type": "Feature",
  "properties": {
    "iso:country":"FR",
    "sg:address":"7 Pl Monuments 38460 Cr\u00e9mieu",
    "sg:classifiers":[
        {
            "category":"Shopping",
            "subcategory":"Clothing, Apparel, & Fashions",
            "type":"Retail Goods"
        }
    ],
    "sg:phone":"+33 4 74 90 74 77",
    "sg:postcode":"38460",
    "sg:province":"Rhone-Alpes",
    "sg:tags":[
        "textile",
        "clothing",
        "clothes"
    ],
    "wof:name":"Equipement De Protection Industrielle Sarl",
    "wof:placetype":"venue"
},
  "geometry": {"coordinates":[5.27697,45.658482],"type":"Point"}
}