{
  "type": "Feature",
  "properties": {
    "addr:full":"Ch\u00e2teau Beychevelle 33250 ST JULIEN BEYCHEVELLE Cissac-M\u00e9doc Aquitaine 33250",
    "addr:housenumber":"33250",
    "addr:postcode":"33250",
    "addr:street":"St Julien Beychevelle",
    "iso:country":"FR",
    "sg:address":"Ch\u00e2teau Beychevelle 33250 ST JULIEN BEYCHEVELLE",
    "sg:city":"Cissac-M\u00e9doc",
    "sg:classifiers":[
        {
            "category":"Wholesale",
            "subcategory":"Wine & Distilled Alcoholic Beverages",
            "type":"Manufacturing & Wholesale Goods"
        }
    ],
    "sg:phone":"+33 5 56 73 20 70",
    "sg:postcode":"33250",
    "sg:province":"Aquitaine",
    "sg:tags":[
        "french"
    ],
    "wof:name":"Ch\u00e2teau Beychevelle S.c.",
    "wof:placetype":"venue"
},
  "geometry": {"coordinates":[-0.749246,45.173813],"type":"Point"}
}