{
  "type": "Feature",
  "properties": {
    "iso:country":"FR",
    "sg:address":"Le Village 26400 Aouste Sur Sye",
    "sg:classifiers":[
        {
            "category":"Manufacturing",
            "subcategory":"Paper Products",
            "type":"Manufacturing & Wholesale Goods"
        }
    ],
    "sg:phone":"+33 4 75 76 62 90",
    "sg:postcode":"26400",
    "sg:province":"Rhone-Alpes",
    "sg:tags":[
        "packaging",
        "material",
        "-",
        "cardboard"
    ],
    "wof:name":"Lembacel",
    "wof:placetype":"venue"
},
  "geometry": {"coordinates":[5.084799,44.623848],"type":"Point"}
}