{
  "type": "Feature",
  "properties": {
    "iso:country":"FR",
    "sg:address":"30 bd Marinoni; Beaulieu",
    "sg:city":"Beaulieu",
    "sg:classifiers":[
        {
            "category":"Banks & Credit Unions",
            "subcategory":"Bank",
            "type":"Services"
        }
    ],
    "sg:phone":"+33 3393010249",
    "sg:postcode":"15270",
    "sg:province":"Auvergne",
    "wof:name":"Banque Nationale, De Paris Bnp",
    "wof:placetype":"venue"
},
  "geometry": {"coordinates":[-95.80437499999999,47.342918],"type":"Point"}
}