{
  "type": "Feature",
  "properties": {
    "iso:country":"FR",
    "sg:address":"Route D Annonay 43290 Montfaucon En Velay",
    "sg:city":"Montfaucon-en-Velay",
    "sg:classifiers":[
        {
            "category":"Food & Beverages",
            "subcategory":"Groceries & Convenience Stores",
            "type":"Retail Goods"
        }
    ],
    "sg:phone":"+33 4 71 59 92 14",
    "sg:postcode":"43290",
    "sg:province":"Auvergne",
    "sg:tags":[
        "product",
        "grain",
        "cereal",
        "related"
    ],
    "wof:name":"Minoterie Lardon",
    "wof:placetype":"venue"
},
  "geometry": {"coordinates":[4.435895,45.142361],"type":"Point"}
}