{
  "type": "Feature",
  "properties": {
    "addr:full":"1 33350 Sainte Colombe Aquitaine 33350",
    "addr:housenumber":"1",
    "addr:postcode":"33350;33350",
    "iso:country":"FR",
    "sg:address":"1",
    "sg:city":"33350 Sainte Colombe",
    "sg:classifiers":[
        {
            "category":"Food Court",
            "type":"Food & Drink"
        }
    ],
    "sg:phone":"+33 5 57 40 34 99",
    "sg:postcode":"33350",
    "sg:province":"Aquitaine",
    "sg:tags":[
        "product",
        "related"
    ],
    "wof:name":"Chateau Faugeres",
    "wof:placetype":"venue"
},
  "geometry": {"coordinates":[-0.079372,44.879494],"type":"Point"}
}