{
  "type": "Feature",
  "properties": {
    "iso:country":"FR",
    "sg:address":"7 Rue Boileau",
    "sg:city":"Brest",
    "sg:classifiers":[
        {
            "category":"Banks & Credit Unions",
            "subcategory":"Financial Services",
            "type":"Services"
        }
    ],
    "sg:phone":"+33 2 98 80 50 46",
    "sg:postcode":"29200",
    "sg:province":"Bretagne",
    "sg:tags":[
        "banking",
        "finance",
        "insurance"
    ],
    "wof:name":"Brink Evolution",
    "wof:placetype":"venue"
},
  "geometry": {"coordinates":[-4.46287,48.398636],"type":"Point"}
}