{
  "type": "Feature",
  "properties": {
    "iso:country":"FR",
    "sg:address":"4 Av Des Elys\u00e9es 34350 Valras Plage",
    "sg:classifiers":[
        {
            "category":"Sports & Exercise",
            "subcategory":"Sports Center",
            "type":"Entertainment"
        }
    ],
    "sg:phone":"+33 4 67 32 60 60",
    "sg:postcode":"34350",
    "sg:province":"Languedoc-Roussillon",
    "sg:tags":[
        "game"
    ],
    "wof:name":"Valras Plage Loisirs",
    "wof:placetype":"venue"
},
  "geometry": {"coordinates":[3.28286,43.241634],"type":"Point"}
}