{
  "type": "Feature",
  "properties": {
    "addr:full":"2, Rue Jules Vercruysse, 02430 Gauchy Picardie",
    "addr:housenumber":"2",
    "addr:postcode":"02430",
    "addr:street":"Rue Jules Vercruysse",
    "iso:country":"FR",
    "sg:address":"2, Rue Jules Vercruysse, 02430 Gauchy",
    "sg:orig_category":"Unclassifiable Establishments",
    "sg:phone":"+33 3 23 64 64 20",
    "sg:province":"Picardie",
    "wof:name":"Fapagau Et Compagnie S.n.c.",
    "wof:placetype":"venue"
},
  "geometry": {"coordinates":[3.277563,49.829639],"type":"Point"}
}