{
  "type": "Feature",
  "properties": {
    "addr:full":"41 rue du Vieux Moulin 22190 PLERIN Pl\u00e9rin Bretagne 22190",
    "addr:housenumber":"41",
    "addr:postcode":"22190;22190",
    "addr:street":"Rue Du Vieux Moulin",
    "iso:country":"FR",
    "sg:address":"41 rue du Vieux Moulin 22190 PLERIN",
    "sg:city":"Pl\u00e9rin",
    "sg:classifiers":[
        {
            "category":"Retail",
            "subcategory":"Storage",
            "type":"Services"
        }
    ],
    "sg:phone":"+33 2 96 60 88 00",
    "sg:postcode":"22190",
    "sg:province":"Bretagne",
    "sg:tags":[
        "transport",
        "groupage"
    ],
    "wof:name":"Cars Rouillard S.a.",
    "wof:placetype":"venue"
},
  "geometry": {"coordinates":[-2.762481,48.523949],"type":"Point"}
}