{
  "type": "Feature",
  "properties": {
    "iso:country":"FR",
    "sg:address":"18/20, Rue Edouard Jacques, 75014 Paris",
    "sg:orig_category":"Non-Classified Establishments",
    "sg:phone":"+33 1 43 20 05 05",
    "sg:postcode":"75014",
    "sg:province":"Ile de France",
    "wof:name":"Cin\u00e9ma Computer Systems S.a.r.l.",
    "wof:placetype":"venue"
},
  "geometry": {"coordinates":[2.321609,48.834923],"type":"Point"}
}