{
  "type": "Feature",
  "properties": {
    "addr:full":"22 rue de Grenoble; Evreux; 27000 Haute Normandie 27000",
    "addr:housenumber":"22",
    "addr:postcode":"27000;27000",
    "addr:street":"Rue De Grenoble;Normandie",
    "iso:country":"FR",
    "sg:address":"22 rue de Grenoble; Evreux; 27000",
    "sg:classifiers":[
        {
            "category":"Banks & Credit Unions",
            "subcategory":"Bank",
            "type":"Services"
        }
    ],
    "sg:phone":"+33 32383502",
    "sg:postcode":"27000",
    "sg:province":"Haute Normandie",
    "wof:name":"Banque Nationale De Paris",
    "wof:placetype":"venue"
},
  "geometry": {"coordinates":[1.150141,49.026264],"type":"Point"}
}