{
  "type": "Feature",
  "properties": {
    "addr:full":"11 Quai Fecht 68040 Ingersheim Ingersheim Alsace 68040",
    "addr:housenumber":"11",
    "addr:postcode":"68040;68040",
    "addr:street":"Quai Fecht",
    "iso:country":"FR",
    "sg:address":"11 Quai Fecht 68040 Ingersheim",
    "sg:city":"Ingersheim",
    "sg:classifiers":[
        {
            "category":"Professional",
            "subcategory":"Engineering",
            "type":"Services"
        }
    ],
    "sg:phone":"+33 3 89 27 09 38",
    "sg:postcode":"68040",
    "sg:province":"Alsace",
    "sg:tags":[
        "machine",
        "-",
        "mechanical"
    ],
    "wof:name":"Geiger (atelier Mecanique R ) Sa",
    "wof:placetype":"venue"
},
  "geometry": {"coordinates":[7.30856,48.098156],"type":"Point"}
}