{
  "type": "Feature",
  "properties": {
    "addr:full":"10 Rue Saint Marc 89100 Maillot Maillot Bourgogne 89100",
    "addr:housenumber":"10",
    "addr:postcode":"89100;89100",
    "addr:street":"Rue Saint Marc",
    "iso:country":"FR",
    "sg:address":"10 Rue Saint Marc 89100 Maillot",
    "sg:city":"Maillot",
    "sg:classifiers":[
        {
            "category":"Manufacturing",
            "subcategory":"Printing",
            "type":"Manufacturing & Wholesale Goods"
        }
    ],
    "sg:phone":"+33 3 86 83 78 78",
    "sg:postcode":"89100",
    "sg:province":"Bourgogne",
    "sg:tags":[
        "publishing"
    ],
    "wof:name":"Sa Photogravure Eg",
    "wof:placetype":"venue"
},
  "geometry": {"coordinates":[3.308163,48.170597],"type":"Point"}
}