{
  "type": "Feature",
  "properties": {
    "addr:full":"Rte de Paris Cagny Basse Normandie 14630",
    "addr:postcode":"14630",
    "addr:street":"Rte De Paris",
    "iso:country":"FR",
    "sg:address":"Rte de Paris",
    "sg:city":"Cagny",
    "sg:orig_category":"Unclassifiable Establishments",
    "sg:phone":"+33 2 31 39 49 00",
    "sg:postcode":"14630",
    "sg:province":"Basse Normandie",
    "wof:name":"Saint Louis Sucre",
    "wof:placetype":"venue"
},
  "geometry": {"coordinates":[-0.250846,49.144386],"type":"Point"}
}