{
  "type": "Feature",
  "properties": {
    "addr:full":"B.P. 117, 62002 Arras C\u00e9dex^^Rue L\u00e9on Foucault, 62000 Arras Nord Pas-de-Calais 62000",
    "addr:housenumber":"b.p. 117",
    "addr:postcode":"62002;62000;62000",
    "addr:street":"Foucault",
    "iso:country":"FR",
    "sg:address":"B.P. 117, 62002 Arras C\u00e9dex^^Rue L\u00e9on Foucault, 62000 Arras",
    "sg:orig_category":"Non-Classified Establishments",
    "sg:phone":"+33 3 21 58 44 22",
    "sg:postcode":"62000",
    "sg:province":"Nord Pas-de-Calais",
    "wof:name":"Arrageoise De Conditionnement Et De Commercialisation D'oeufs S.a.",
    "wof:placetype":"venue"
},
  "geometry": {"coordinates":[2.77891,50.290989],"type":"Point"}
}