{
  "type": "Feature",
  "properties": {
    "addr:full":"32, Rue de Casablanca, 40230 Saint Vincent de Tyrosse B\u00e9nesse-Maremne Aquitaine 40230",
    "addr:housenumber":"32",
    "addr:postcode":"40230;40230",
    "addr:street":"Rue De Casablanca",
    "iso:country":"FR",
    "sg:address":"32, Rue de Casablanca, 40230 Saint Vincent de Tyrosse",
    "sg:city":"B\u00e9nesse-Maremne",
    "sg:orig_category":"Unclassifiable Establishments",
    "sg:phone":"+33 5 58 77 25 62",
    "sg:postcode":"40230",
    "sg:province":"Aquitaine",
    "wof:name":"T.m.c.g. S.a.r.l.",
    "wof:placetype":"venue"
},
  "geometry": {"coordinates":[-1.278067,43.668343],"type":"Point"}
}