{
  "type": "Feature",
  "properties": {
    "iso:country":"FR",
    "sg:address":"76 rue Victor Hugo 59160 Lomme",
    "sg:classifiers":[
        {
            "category":"Manufacturing",
            "subcategory":"Motor Vehicles & Parts",
            "type":"Manufacturing & Wholesale Goods"
        }
    ],
    "sg:phone":"+33 3 20 08 30 42",
    "sg:province":"Nord Pas-de-Calais",
    "sg:tags":[
        "precision",
        "mechanic"
    ],
    "wof:name":"R. Haesebrouck Et Fils Sas",
    "wof:placetype":"venue"
},
  "geometry": {"coordinates":[3.009807,50.629734],"type":"Point"}
}