{
  "type": "Feature",
  "properties": {
    "iso:country":"FR",
    "sg:address":"18, Place des Nymph\u00e9as, 93420 Villepinte",
    "sg:orig_category":"Unclassifiable Establishments",
    "sg:phone":"+33 1 49 90 23 00",
    "sg:province":"Ile de France",
    "wof:name":"Case Europe S.a.r.l.",
    "wof:placetype":"venue"
},
  "geometry": {"coordinates":[2.510661,48.973606],"type":"Point"}
}