{
  "type": "Feature",
  "properties": {
    "iso:country":"FR",
    "sg:address":"ZI du Visionis",
    "sg:city":"Gu\u00e9reins",
    "sg:orig_category":"Unclassifiable Establishments",
    "sg:phone":"+33 4 74 66 69 49",
    "sg:postcode":"01090",
    "sg:province":"Rhone-Alpes",
    "wof:name":"Soci\u00e9t\u00e9 Carina S.a.",
    "wof:placetype":"venue"
},
  "geometry": {"coordinates":[4.77624,46.104374],"type":"Point"}
}