{
  "type": "Feature",
  "properties": {
    "iso:country":"FR",
    "sg:address":"34, Rue des Pales - ZI, 63540 Romagnat",
    "sg:city":"Romagnat",
    "sg:orig_category":"Unclassifiable Establishments",
    "sg:phone":"+33 4 73 26 63 79",
    "sg:postcode":"63540",
    "sg:province":"Auvergne",
    "wof:name":"M\u00e9tallerie Roger Boisson S.a.",
    "wof:placetype":"venue"
},
  "geometry": {"coordinates":[3.102855,45.73061],"type":"Point"}
}