{
  "type": "Feature",
  "properties": {
    "addr:full":"La Croix Verte 22270 St Rieul M\u00e9grit Bretagne 22270",
    "addr:postcode":"22270;22270",
    "addr:street":"La Croix Verte;Me\u0301Grit",
    "iso:country":"FR",
    "sg:address":"La Croix Verte 22270 St Rieul",
    "sg:city":"M\u00e9grit",
    "sg:classifiers":[
        {
            "category":"Home & Garden",
            "subcategory":"Furniture",
            "type":"Retail Goods"
        }
    ],
    "sg:phone":"+33 2 96 34 14 05",
    "sg:postcode":"22270",
    "sg:province":"Bretagne",
    "sg:tags":[
        "wood"
    ],
    "wof:name":"Ets Alain Douard Sa",
    "wof:placetype":"venue"
},
  "geometry": {"coordinates":[-2.426294,48.436008],"type":"Point"}
}