{
  "type": "Feature",
  "properties": {
    "addr:full":"B.P. 27, 63120 Courpi\u00e8re^^ZI les Champs, 63120 Courpi\u00e8re Courpi\u00e8re Auvergne 63120",
    "addr:postcode":"63120;63120;courpie\u0300re;63120",
    "addr:street":"B.P. 27;Champs",
    "iso:country":"FR",
    "sg:address":"B.P. 27, 63120 Courpi\u00e8re^^ZI les Champs, 63120 Courpi\u00e8re",
    "sg:city":"Courpi\u00e8re",
    "sg:orig_category":"Non-Classified Establishments",
    "sg:phone":"+33 4 73 51 68 00",
    "sg:postcode":"63120",
    "sg:province":"Auvergne",
    "wof:name":"Celta S.a.",
    "wof:placetype":"venue"
},
  "geometry": {"coordinates":[3.535275,45.715576],"type":"Point"}
}