{
  "type": "Feature",
  "properties": {
    "addr:full":"21 bis, Rue du Bois du Tillet, 60800 Cr\u00e9py en Valois Picardie 60800",
    "addr:housenumber":"21 bis",
    "addr:postcode":"60800;60800",
    "addr:street":"Rue Du Bois Du Tillet;En;Picardie",
    "iso:country":"FR",
    "sg:address":"21 bis, Rue du Bois du Tillet, 60800 Cr\u00e9py en Valois",
    "sg:orig_category":"Non-Classified Establishments",
    "sg:phone":"+33 3 44 59 17 12",
    "sg:postcode":"60800",
    "sg:province":"Picardie",
    "wof:name":"Beta Syst\u00e8mes S.a.r.l.",
    "wof:placetype":"venue"
},
  "geometry": {"coordinates":[2.904874,49.227734],"type":"Point"}
}