{
  "type": "Feature",
  "properties": {
    "addr:full":"Rte Plessis Barbuise 10370 Villenauxe La Grande Champagne 10370",
    "addr:postcode":"10370;10370",
    "addr:street":"Rte Plessis",
    "iso:country":"FR",
    "sg:address":"Rte Plessis Barbuise 10370 Villenauxe La Grande",
    "sg:classifiers":[
        {
            "category":"Professional",
            "subcategory":"Printing & Photocopies",
            "type":"Services"
        }
    ],
    "sg:phone":"+33 3 25 21 00 95",
    "sg:postcode":"10370",
    "sg:province":"Champagne",
    "sg:tags":[
        "machine",
        "engineering",
        "-",
        "mechanical"
    ],
    "wof:name":"M\u00c9taplast Sa",
    "wof:placetype":"venue"
},
  "geometry": {"coordinates":[3.556114,48.589348],"type":"Point"}
}