{
  "type": "Feature",
  "properties": {
    "addr:full":"Rue Wilhelm Frank 57380 FAULQUEMONT Lorraine 57380",
    "addr:postcode":"57380;57380",
    "addr:street":"Rue Wilhelm Frank",
    "iso:country":"FR",
    "sg:address":"Rue Wilhelm Frank 57380 FAULQUEMONT",
    "sg:classifiers":[
        {
            "category":"Military Area",
            "subcategory":"Air Force Base",
            "type":"Public Place"
        }
    ],
    "sg:phone":"+33 3 87 29 24 30",
    "sg:postcode":"57380",
    "sg:province":"Lorraine",
    "sg:tags":[
        "window",
        "skylight",
        "dormer"
    ],
    "wof:name":"Roto Frank Sa",
    "wof:placetype":"venue"
},
  "geometry": {"coordinates":[6.599175,49.042831],"type":"Point"}
}