{
  "type": "Feature",
  "properties": {
    "addr:full":"Bd d'Abbadie - Espace Rossignol - B\u00e2t. 2 Saint Victoret Rhone-Alpes 13730",
    "addr:housenumber":"2",
    "addr:postcode":"13730",
    "addr:street":"Espace;Saint Victoret Rhone-Alpes",
    "iso:country":"FR",
    "sg:address":"Bd d'Abbadie - Espace Rossignol - B\u00e2t. 2",
    "sg:city":"Saint Victoret",
    "sg:orig_category":"Non-Classified Establishments",
    "sg:phone":"+33 4 42 10 49 03",
    "sg:postcode":"13730",
    "sg:province":"Rhone-Alpes",
    "wof:name":"Buyingpack S.a.",
    "wof:placetype":"venue"
},
  "geometry": {"coordinates":[5.249254,43.413101],"type":"Point"}
}