{
  "type": "Feature",
  "properties": {
    "iso:country":"FR",
    "sg:address":"25, Bd Armand Hayem, 95680 Montlignon",
    "sg:orig_category":"Non-Classified Establishments",
    "sg:phone":"+33 1 34 16 05 82",
    "sg:province":"Ile de France",
    "wof:name":"Expres Envelop' S.a.",
    "wof:placetype":"venue"
},
  "geometry": {"coordinates":[2.280526,49.010635],"type":"Point"}
}