{
  "type": "Feature",
  "properties": {
    "addr:full":"14, Rue Pierre de Coubertin - Parc Tertiaire de Mirande, 21000 Dijon Dijon Bourgogne 21000",
    "addr:housenumber":"14",
    "addr:postcode":"21000;21000",
    "addr:street":"Rue Pierre De Coubertin Parc Tertiaire De Mirande",
    "iso:country":"FR",
    "sg:address":"14, Rue Pierre de Coubertin - Parc Tertiaire de Mirande, 21000 Dijon",
    "sg:city":"Dijon",
    "sg:orig_category":"Unclassifiable Establishments",
    "sg:phone":"+33 3 80 68 23 53",
    "sg:postcode":"21000",
    "sg:province":"Bourgogne",
    "wof:name":"Appia France S.a.r.l. - Applications Informatiques Et Automobiles",
    "wof:placetype":"venue"
},
  "geometry": {"coordinates":[5.080666,47.311493],"type":"Point"}
}