{
  "type": "Feature",
  "properties": {
    "addr:full":"Z.I. La Fouillouse Rhone-Alpes 42480",
    "addr:postcode":"42480",
    "addr:street":"Z.I.;Rhone-Alpes",
    "iso:country":"FR",
    "sg:address":"Z.I.",
    "sg:city":"La Fouillouse",
    "sg:orig_category":"Unclassifiable Establishments",
    "sg:phone":"+33 4 77 36 12 12",
    "sg:postcode":"42480",
    "sg:province":"Rhone-Alpes",
    "wof:name":"Forez Piscines S.a.",
    "wof:placetype":"venue"
},
  "geometry": {"coordinates":[4.316932,45.501125],"type":"Point"}
}