{
  "type": "Feature",
  "properties": {
    "addr:full":"7 All Jean Jacques Rousseau 05400 Veynes Nord Pas-de-Calais",
    "addr:housenumber":"7",
    "addr:postcode":"05400",
    "addr:street":"All Jean;Rousseau",
    "iso:country":"FR",
    "sg:address":"7 All Jean Jacques Rousseau 05400 Veynes",
    "sg:classifiers":[
        {
            "category":"Shopping",
            "type":"Retail Goods"
        }
    ],
    "sg:phone":"+33 4 92 58 33 33",
    "sg:province":"Nord Pas-de-Calais",
    "sg:tags":[
        "metallurgy",
        "finished",
        "-",
        "metalworking",
        "metallic"
    ],
    "wof:name":"La Resistance Rd Sa",
    "wof:placetype":"venue"
},
  "geometry": {"coordinates":[5.829221,44.53109],"type":"Point"}
}