{
  "type": "Feature",
  "properties": {
    "addr:full":"ZI Madrazes Sarlat la Caneda Aquitaine 24200",
    "addr:postcode":"24200",
    "iso:country":"FR",
    "sg:address":"ZI Madrazes",
    "sg:city":"Sarlat la Caneda",
    "sg:orig_category":"Non-Classified Establishments",
    "sg:phone":"+33 5 53 59 40 24",
    "sg:postcode":"24200",
    "sg:province":"Aquitaine",
    "wof:name":"Comptoir Electrique Rexel S.a.",
    "wof:placetype":"venue"
},
  "geometry": {"coordinates":[1.21522,44.891651],"type":"Point"}
}