{
  "type": "Feature",
  "properties": {
    "addr:full":"2, Rue du Vicariat, 02570 Ch\u00e9zy sur Marne Picardie",
    "addr:housenumber":"2",
    "addr:postcode":"02570",
    "addr:street":"Rue Du Vicariat",
    "iso:country":"FR",
    "sg:address":"2, Rue du Vicariat, 02570 Ch\u00e9zy sur Marne",
    "sg:orig_category":"Unclassifiable Establishments",
    "sg:phone":"+33 3 23 82 81 26",
    "sg:province":"Picardie",
    "wof:name":"Voirin P\u00e8re Et Fils S.a.r.l.",
    "wof:placetype":"venue"
},
  "geometry": {"coordinates":[3.36712,48.988911],"type":"Point"}
}