{
  "type": "Feature",
  "properties": {
    "iso:country":"FR",
    "sg:address":"Zone D'Activit\u00e9s Vert Galant 64110 Juran\u00e7on",
    "sg:city":"Juran\u00e7on",
    "sg:classifiers":[
        {
            "category":"Professional",
            "subcategory":"Advertising",
            "type":"Services"
        }
    ],
    "sg:phone":"+33 5 59 06 67 17",
    "sg:postcode":"64110",
    "sg:province":"Aquitaine",
    "sg:tags":[
        "marketing",
        "medium",
        "communication"
    ],
    "wof:name":"Pau Diffusion Presse Sa",
    "wof:placetype":"venue"
},
  "geometry": {"coordinates":[-0.387838,43.277779],"type":"Point"}
}