{
  "type": "Feature",
  "properties": {
    "iso:country":"FR",
    "sg:address":"12, Rue de Villechien, 49000 Angers",
    "sg:orig_category":"Unclassifiable Establishments",
    "sg:phone":"+33 2 41 66 97 60",
    "sg:province":"Pays de Loire",
    "wof:name":"Gautier S.a.r.l.",
    "wof:placetype":"venue"
},
  "geometry": {"coordinates":[-0.519357,47.463535],"type":"Point"}
}