{
  "type": "Feature",
  "properties": {
    "addr:full":"1101 Rue L'Ange 01100 Bellignat Rhone-Alpes 01100",
    "addr:housenumber":"1101",
    "addr:postcode":"01100;01100",
    "addr:street":"Rue L'Ange;Rhone-Alpes",
    "iso:country":"FR",
    "sg:address":"1101 Rue L'Ange 01100 Bellignat",
    "sg:classifiers":[
        {
            "category":"Health Services",
            "subcategory":"Optometrist",
            "type":"Services"
        }
    ],
    "sg:phone":"+33 4 74 77 82 24",
    "sg:postcode":"01100",
    "sg:province":"Rhone-Alpes",
    "sg:tags":[
        "instrument",
        "optical",
        "-",
        "precision",
        "equipment"
    ],
    "wof:name":"Gem Lunetterie Sa",
    "wof:placetype":"venue"
},
  "geometry": {"coordinates":[5.630209,46.238998],"type":"Point"}
}