{
  "type": "Feature",
  "properties": {
    "iso:country":"FR",
    "sg:address":"77 c, Rue du G\u00e9n\u00e9ral de Gaulle, 68460 Lutterbach",
    "sg:city":"Lutterbach",
    "sg:orig_category":"Unclassifiable Establishments",
    "sg:phone":"+33 3 89 53 35 94",
    "sg:postcode":"68460",
    "sg:province":"Alsace",
    "wof:name":"Metolin S.a.r.l.",
    "wof:placetype":"venue"
},
  "geometry": {"coordinates":[7.288476,47.758755],"type":"Point"}
}