{
  "type": "Feature",
  "properties": {
    "addr:full":"26 Pl De Beaune 71100 Ch\u00e2lons Sur Sa\u00f4ne Chalon-sur-Sa\u00f4ne Bourgogne 71100",
    "addr:housenumber":"26",
    "addr:postcode":"71100;71100",
    "addr:street":"Pl De Beaune",
    "iso:country":"FR",
    "sg:address":"26 Pl De Beaune 71100 Ch\u00e2lons Sur Sa\u00f4ne",
    "sg:city":"Chalon-sur-Sa\u00f4ne",
    "sg:orig_category":"Mechanical Engineering - machines Paper and cardboard - raw materials Printing Printing and Publishi",
    "sg:phone":"+33 3 85 48 64 00",
    "sg:postcode":"71100",
    "sg:province":"Bourgogne",
    "wof:name":"Lips Reprographie Sa",
    "wof:placetype":"venue"
},
  "geometry": {"coordinates":[4.855409,46.784565],"type":"Point"}
}