{
  "type": "Feature",
  "properties": {
    "iso:country":"FR",
    "sg:address":"Av Gay- Lussac 64140 Lons",
    "sg:city":"Lons",
    "sg:classifiers":[
        {
            "category":"Manufacturing",
            "subcategory":"Tools & Machinery",
            "type":"Manufacturing & Wholesale Goods"
        }
    ],
    "sg:phone":"+33 5 59 32 85 91",
    "sg:postcode":"64140",
    "sg:province":"Aquitaine",
    "sg:tags":[
        "metallurgy",
        "metalworking"
    ],
    "wof:name":"Leitz Sarl Ste D'exploitation",
    "wof:placetype":"venue"
},
  "geometry": {"coordinates":[-0.418874,43.308918],"type":"Point"}
}