{
  "type": "Feature",
  "properties": {
    "iso:country":"FR",
    "sg:address":"ZA",
    "sg:city":"Franois",
    "sg:orig_category":"Non-Classified Establishments",
    "sg:phone":"+33 3 81 59 94 44",
    "sg:postcode":"25770",
    "sg:province":"Franche Comt\u00e9",
    "wof:name":"Transports Serge Chanez S.a.",
    "wof:placetype":"venue"
},
  "geometry": {"coordinates":[5.922374,47.231537],"type":"Point"}
}