{
  "type": "Feature",
  "properties": {
    "iso:country":"FR",
    "sg:address":"27 R De La Merbaudi\u00e8re 35760 Montgermont",
    "sg:city":"Montgermont",
    "sg:classifiers":[
        {
            "category":"Banks & Credit Unions",
            "subcategory":"Investment Brokerage",
            "type":"Services"
        }
    ],
    "sg:phone":"+33 2 99 68 70 55",
    "sg:postcode":"35760",
    "sg:province":"Bretagne",
    "sg:tags":[
        "-",
        "transport",
        "related"
    ],
    "wof:name":"Societe Cusenier",
    "wof:placetype":"venue"
},
  "geometry": {"coordinates":[-1.709588,48.15131],"type":"Point"}
}