{
  "type": "Feature",
  "properties": {
    "addr:full":"127, Rue Pasteur, 59370 Mons en Baroeul Nord Pas-de-Calais",
    "addr:housenumber":"127",
    "addr:postcode":"59370",
    "addr:street":"Rue Pasteur",
    "iso:country":"FR",
    "sg:address":"127, Rue Pasteur, 59370 Mons en Baroeul",
    "sg:orig_category":"Non-Classified Establishments",
    "sg:phone":"+33 3 20 56 94 11",
    "sg:province":"Nord Pas-de-Calais",
    "wof:name":"Graphiflex S.a.r.l.",
    "wof:placetype":"venue"
},
  "geometry": {"coordinates":[3.10327,50.649769],"type":"Point"}
}