{
  "type": "Feature",
  "properties": {
    "addr:full":"178 rue de Courcelles 75017 Paris Ile de France",
    "addr:housenumber":"178",
    "addr:postcode":"75017",
    "addr:street":"Rue De Courcelles",
    "iso:country":"FR",
    "sg:address":"178 rue de Courcelles 75017 Paris",
    "sg:classifiers":[
        {
            "category":"Professional",
            "subcategory":"Employment Agencies",
            "type":"Services"
        }
    ],
    "sg:phone":"+33 1 56 21 14 00",
    "sg:province":"Ile de France",
    "sg:tags":[
        "telephone",
        "marketing",
        "telemarketing",
        "agencies"
    ],
    "wof:name":"Ipj-haindl Sa",
    "wof:placetype":"venue"
},
  "geometry": {"coordinates":[2.298336,48.884132],"type":"Point"}
}