{
  "type": "Feature",
  "properties": {
    "iso:country":"FR",
    "sg:address":"26, Av. des Champs Elys\u00e9es, 75008 Paris",
    "sg:orig_category":"Unclassifiable Establishments",
    "sg:phone":"+33 1 53 75 70 00",
    "sg:province":"Ile de France",
    "wof:name":"D\u00e9l\u00e9gation Commerciale D'italie",
    "wof:placetype":"venue"
},
  "geometry": {"coordinates":[2.308701,48.869549],"type":"Point"}
}