{
  "type": "Feature",
  "properties": {
    "iso:country":"FR",
    "sg:address":"RN 20 - ZI Lavigne",
    "sg:city":"Auterive",
    "sg:orig_category":"Non-Classified Establishments",
    "sg:phone":"+33 5 61 50 53 71",
    "sg:postcode":"31190",
    "sg:province":"Midi Pyr\u00e9n\u00e9es",
    "wof:name":"M.i.s. Toulouse Sibe S.a.r.l. - Soci\u00e9t\u00e9 Industrielle De Bobinage Electrique",
    "wof:placetype":"venue"
},
  "geometry": {"coordinates":[1.40004,43.297123],"type":"Point"}
}