{
  "type": "Feature",
  "properties": {
    "addr:full":"52, Rue de Ponthieu, 75008 Paris Ile de France 75008",
    "addr:housenumber":"52",
    "addr:postcode":"75008;75008",
    "addr:street":"Rue De Ponthieu",
    "iso:country":"FR",
    "sg:address":"52, Rue de Ponthieu, 75008 Paris",
    "sg:orig_category":"Non-Classified Establishments",
    "sg:phone":"+33 1 45 63 14 08",
    "sg:postcode":"75008",
    "sg:province":"Ile de France",
    "wof:name":"Agence Dorian S.a.r.l.",
    "wof:placetype":"venue"
},
  "geometry": {"coordinates":[2.306869,48.871689],"type":"Point"}
}