{
  "type": "Feature",
  "properties": {
    "addr:full":"1, Rue de l'ancien ch\u00e2teau, 10130 Saint Phal Champagne",
    "addr:housenumber":"1",
    "addr:postcode":"10130",
    "addr:street":"Rue De L'Ancien Cha\u0302Teau",
    "iso:country":"FR",
    "sg:address":"1, Rue de l'ancien ch\u00e2teau, 10130 Saint Phal",
    "sg:orig_category":"Unclassifiable Establishments",
    "sg:phone":"+33 3 25 42 16 34",
    "sg:province":"Champagne",
    "wof:name":"Lambert Marcel Et Compagnie S.a.",
    "wof:placetype":"venue"
},
  "geometry": {"coordinates":[3.99633,48.120071],"type":"Point"}
}