{
  "type": "Feature",
  "properties": {
    "addr:full":"10 av de Bordeaux; Andernos les Bains; 33510 Andernos-les-Bains Aquitaine 33510",
    "addr:postcode":"33510;33510",
    "addr:street":"10 Av De Bordeaux",
    "iso:country":"FR",
    "sg:address":"10 av de Bordeaux; Andernos les Bains; 33510",
    "sg:city":"Andernos-les-Bains",
    "sg:classifiers":[
        {
            "category":"Banks & Credit Unions",
            "subcategory":"Bank",
            "type":"Services"
        }
    ],
    "sg:phone":"+33 3356824880",
    "sg:postcode":"33510",
    "sg:province":"Aquitaine",
    "wof:name":"Soci\u00e9t\u00e9 G\u00e9n\u00e9rale",
    "wof:placetype":"venue"
},
  "geometry": {"coordinates":[-1.096987,44.742859],"type":"Point"}
}