{
  "type": "Feature",
  "properties": {
    "iso:country":"FR",
    "sg:address":"24 Quai Deschamps 33100 Bordeaux",
    "sg:city":"Bordeaux",
    "sg:classifiers":[
        {
            "category":"Autos & Motor Vehicles",
            "subcategory":"Boat Sales",
            "type":"Retail Goods"
        }
    ],
    "sg:phone":"+33 5 56 86 56 22",
    "sg:postcode":"33100",
    "sg:province":"Aquitaine",
    "sg:tags":[
        "equipment",
        "transport"
    ],
    "wof:name":"Henri (constructions Mecaniques) Sa",
    "wof:placetype":"venue"
},
  "geometry": {"coordinates":[-0.557119,44.837521],"type":"Point"}
}