{
  "type": "Feature",
  "properties": {
    "addr:full":"42 Rue Noel Ballay Chartres Centre 28000",
    "addr:housenumber":"42",
    "addr:postcode":"28000",
    "addr:street":"Rue Noel Ballay Chartres",
    "iso:country":"FR",
    "sg:address":"42 Rue Noel Ballay",
    "sg:city":"Chartres",
    "sg:classifiers":[
        {
            "category":"Banks & Credit Unions",
            "subcategory":"Financial Services",
            "type":"Services"
        }
    ],
    "sg:phone":"+33 2 37 18 63 00",
    "sg:postcode":"28000",
    "sg:province":"Centre",
    "sg:tags":[
        "banking",
        "finance",
        "insurance"
    ],
    "wof:name":"Bp Rop Banque Populaire (bprop)",
    "wof:placetype":"venue"
},
  "geometry": {"coordinates":[1.484452,48.444916],"type":"Point"}
}