{
  "type": "Feature",
  "properties": {
    "iso:country":"FR",
    "sg:address":"3, Rue Gustave Fouillaron, 49300 Cholet",
    "sg:orig_category":"Unclassifiable Establishments",
    "sg:phone":"+33 2 41 58 41 65",
    "sg:province":"Pays de Loire",
    "wof:name":"Lefort Engineering S.a.r.l.",
    "wof:placetype":"venue"
},
  "geometry": {"coordinates":[-0.916,47.028934],"type":"Point"}
}