{
  "type": "Feature",
  "properties": {
    "addr:full":"Rue Du 11 Novembre 42750 St Denis De Cabanne Rhone-Alpes 42750",
    "addr:postcode":"42750;42750",
    "addr:street":"Rue Du 11 Novembre;Rhone-Alpes",
    "iso:country":"FR",
    "sg:address":"Rue Du 11 Novembre 42750 St Denis De Cabanne",
    "sg:classifiers":[
        {
            "category":"Shopping",
            "subcategory":"Computers & Home Electronics",
            "type":"Retail Goods"
        }
    ],
    "sg:phone":"+33 4 77 60 34 34",
    "sg:postcode":"42750",
    "sg:province":"Rhone-Alpes",
    "sg:tags":[
        "electronic",
        "electrical",
        "equipment"
    ],
    "wof:name":"Precloux Sarl",
    "wof:placetype":"venue"
},
  "geometry": {"coordinates":[4.211832,46.175262],"type":"Point"}
}