{
  "type": "Feature",
  "properties": {
    "iso:country":"FR",
    "sg:address":"72, Rue du Ch\u00e2teau d'Eau, 75010 Paris",
    "sg:orig_category":"Unclassifiable Establishments",
    "sg:phone":"+33 1 47 70 07 07",
    "sg:province":"Ile de France",
    "wof:name":"Soci\u00e9t\u00e9 Michon S.a.r.l.",
    "wof:placetype":"venue"
},
  "geometry": {"coordinates":[2.357819,48.871277],"type":"Point"}
}