{
  "type": "Feature",
  "properties": {
    "addr:full":"1, Chemin de la Rasse, 25120 Ma\u00eeche Franche Comt\u00e9",
    "addr:housenumber":"1",
    "addr:postcode":"25120",
    "addr:street":"Chemin De La Rasse;Franche Comte\u0301",
    "iso:country":"FR",
    "sg:address":"1, Chemin de la Rasse, 25120 Ma\u00eeche",
    "sg:orig_category":"Non-Classified Establishments",
    "sg:phone":"+33 3 81 64 09 45",
    "sg:province":"Franche Comt\u00e9",
    "wof:name":"Jeambrun Appareillages S.a.r.l.",
    "wof:placetype":"venue"
},
  "geometry": {"coordinates":[6.800144,47.254673],"type":"Point"}
}