{
  "type": "Feature",
  "properties": {
    "addr:full":"14 bis, Rue de Marbeuf, 75008 Paris Ile de France",
    "addr:housenumber":"14 bis",
    "addr:postcode":"75008",
    "addr:street":"Rue De Marbeuf",
    "iso:country":"FR",
    "sg:address":"14 bis, Rue de Marbeuf, 75008 Paris",
    "sg:orig_category":"Unclassifiable Establishments",
    "sg:phone":"+33 1 40 70 15 10",
    "sg:province":"Ile de France",
    "wof:name":"Plus Int\u00e9rim S.a.",
    "wof:placetype":"venue"
},
  "geometry": {"coordinates":[2.303145,48.868004],"type":"Point"}
}