{
  "type": "Feature",
  "properties": {
    "addr:full":"25, Rue Benoit Malon, 42800 Roanne Rhone-Alpes 42800",
    "addr:housenumber":"25",
    "addr:postcode":"42800;42800",
    "addr:street":"Rue Benoit Malon;Rhone-Alpes",
    "iso:country":"FR",
    "sg:address":"25, Rue Benoit Malon, 42800 Roanne",
    "sg:orig_category":"Unclassifiable Establishments",
    "sg:phone":"+33 4 77 70 14 66",
    "sg:postcode":"42800",
    "sg:province":"Rhone-Alpes",
    "wof:name":"Multi Process S.a.r.l.",
    "wof:placetype":"venue"
},
  "geometry": {"coordinates":[4.647085,45.478973],"type":"Point"}
}