{
  "type": "Feature",
  "properties": {
    "addr:full":"Rte De Sartrouville 78360 Montesson Ile de France",
    "addr:postcode":"78360;ile",
    "addr:street":"Rte De Sartrouville",
    "iso:country":"FR",
    "sg:address":"Rte De Sartrouville 78360 Montesson",
    "sg:classifiers":[
        {
            "category":"Professional",
            "type":"Services"
        }
    ],
    "sg:phone":"+33 1 39 52 14 14",
    "sg:province":"Ile de France",
    "sg:tags":[
        "transport",
        "road"
    ],
    "wof:name":"Societe Des Autoroutes Paris Normandie",
    "wof:placetype":"venue"
},
  "geometry": {"coordinates":[2.155935,48.923023],"type":"Point"}
}