{
  "type": "Feature",
  "properties": {
    "addr:full":"11 Rue Du R\u00e9verb\u00e8re Zae Des Fa\u00efenceries 54300 Lun\u00e9ville Lorraine",
    "addr:housenumber":"11",
    "addr:postcode":"54300",
    "addr:street":"Rue Du Re\u0301Verbe\u0300Re Zae Des Fai\u0308Enceries",
    "iso:country":"FR",
    "sg:address":"11 Rue Du R\u00e9verb\u00e8re Zae Des Fa\u00efenceries 54300 Lun\u00e9ville",
    "sg:classifiers":[
        {
            "category":"Manufacturing",
            "subcategory":"Printing",
            "type":"Manufacturing & Wholesale Goods"
        }
    ],
    "sg:phone":"+33 3 83 73 20 57",
    "sg:province":"Lorraine",
    "sg:tags":[
        "publishing"
    ],
    "wof:name":"Les Imprimeries Paradis Et Paracontinu",
    "wof:placetype":"venue"
},
  "geometry": {"coordinates":[6.49027,48.59306],"type":"Point"}
}