{
  "type": "Feature",
  "properties": {
    "addr:full":"75 quai Chartrons; Bordeaux Bordeaux Aquitaine 33100",
    "addr:housenumber":"75",
    "addr:postcode":"33100",
    "addr:street":"Quai Chartrons",
    "iso:country":"FR",
    "sg:address":"75 quai Chartrons; Bordeaux",
    "sg:city":"Bordeaux",
    "sg:classifiers":[
        {
            "category":"Banks & Credit Unions",
            "subcategory":"Bank",
            "type":"Services"
        }
    ],
    "sg:phone":"+33 3356814222",
    "sg:postcode":"33100",
    "sg:province":"Aquitaine",
    "wof:name":"Banque Nationale De Paris",
    "wof:placetype":"venue"
},
  "geometry": {"coordinates":[-0.567079,44.853592],"type":"Point"}
}