{
  "type": "Feature",
  "properties": {
    "addr:full":"La Bidaliere 01680 Lhuis Rhone-Alpes 01680",
    "addr:postcode":"01680;01680",
    "addr:street":"Rhone-Alpes",
    "iso:country":"FR",
    "sg:address":"La Bidaliere 01680 Lhuis",
    "sg:classifiers":[
        {
            "category":"Utilities",
            "subcategory":"Electric",
            "type":"Services"
        }
    ],
    "sg:phone":"+33 4 74 39 85 85",
    "sg:postcode":"01680",
    "sg:province":"Rhone-Alpes",
    "sg:tags":[
        "electricity",
        "electronic",
        "electrical",
        "equipment"
    ],
    "wof:name":"Agp",
    "wof:placetype":"venue"
},
  "geometry": {"coordinates":[5.55088,45.748596],"type":"Point"}
}