{
  "type": "Feature",
  "properties": {
    "iso:country":"FR",
    "sg:address":"2 rue de la Roquette 75011 Paris",
    "sg:classifiers":[
        {
            "category":"Banks & Credit Unions",
            "subcategory":"Bureau De Change",
            "type":"Services"
        }
    ],
    "sg:phone":"+33 1 64 10 31 00",
    "sg:postcode":"75011",
    "sg:province":"Ile de France",
    "sg:tags":[
        "living",
        "lamp",
        "room"
    ],
    "wof:name":"Etablissement Lucien Gau S.a.",
    "wof:placetype":"venue"
},
  "geometry": {"coordinates":[2.37021,48.853153],"type":"Point"}
}