{
  "type": "Feature",
  "properties": {
    "addr:full":"8, Av. F\u00e9lix Faure, 06000 Nice Provence-Alpes-C\u00f4te d'Azur",
    "addr:postcode":"06000",
    "addr:street":"Av. Fe\u0301Lix Faure",
    "iso:country":"FR",
    "sg:address":"8, Av. F\u00e9lix Faure, 06000 Nice",
    "sg:orig_category":"Unclassifiable Establishments",
    "sg:phone":"+33 4 93 62 26 22",
    "sg:province":"Provence-Alpes-C\u00f4te d'Azur",
    "wof:name":"Bleu Blanc Rouge S.a.r.l.",
    "wof:placetype":"venue"
},
  "geometry": {"coordinates":[7.274282,43.698528],"type":"Point"}
}