{
  "type": "Feature",
  "properties": {
    "addr:full":"15 Rue Louis Bl\u00e9riot 63800 Cournon D'Auvergne P\u00e9rignat-sur-Allier Auvergne 63800",
    "addr:housenumber":"15",
    "addr:postcode":"63800;pe\u0301rignat-sur-allier;63800",
    "addr:street":"Rue Louis Ble\u0301Riot",
    "iso:country":"FR",
    "sg:address":"15 Rue Louis Bl\u00e9riot 63800 Cournon D'Auvergne",
    "sg:city":"P\u00e9rignat-sur-Allier",
    "sg:classifiers":[
        {
            "category":"Professional",
            "subcategory":"Business Services",
            "type":"Services"
        }
    ],
    "sg:phone":"+33 4 73 84 24 81",
    "sg:postcode":"63800",
    "sg:province":"Auvergne",
    "sg:tags":[
        "body",
        "advice"
    ],
    "wof:name":"Restaurant Du Coeur",
    "wof:placetype":"venue"
},
  "geometry": {"coordinates":[3.165341,45.747829],"type":"Point"}
}