{
  "type": "Feature",
  "properties": {
    "addr:full":"9, Rue Lieutenant Naucourt, 01100 Oyonnax Rhone-Alpes",
    "addr:housenumber":"9",
    "addr:postcode":"01100",
    "addr:street":"Rue Lieutenant Naucourt",
    "iso:country":"FR",
    "sg:address":"9, Rue Lieutenant Naucourt, 01100 Oyonnax",
    "sg:orig_category":"Unclassifiable Establishments",
    "sg:phone":"+33 4 74 73 42 62",
    "sg:province":"Rhone-Alpes",
    "wof:name":"Optid\u00e9co S.a.r.l.",
    "wof:placetype":"venue"
},
  "geometry": {"coordinates":[5.662558,46.261368],"type":"Point"}
}