{
  "type": "Feature",
  "properties": {
    "iso:country":"FR",
    "sg:address":"576, Rue de la Lib\u00e9ration, 34130 Lansargues",
    "sg:orig_category":"Unclassifiable Establishments",
    "sg:phone":"+33 4 67 86 71 50",
    "sg:province":"Languedoc-Roussillon",
    "wof:name":"Delta Recyclage S.a.",
    "wof:placetype":"venue"
},
  "geometry": {"coordinates":[4.073972,43.648273],"type":"Point"}
}