{
  "type": "Feature",
  "properties": {
    "addr:full":"ZI Port Port Rhone-Alpes 01460",
    "addr:postcode":"01460",
    "addr:street":"Zi;Port Rhone-Alpes",
    "iso:country":"FR",
    "sg:address":"ZI Port",
    "sg:city":"Port",
    "sg:orig_category":"Unclassifiable Establishments",
    "sg:phone":"+33 4 74 76 14 53",
    "sg:postcode":"01460",
    "sg:province":"Rhone-Alpes",
    "wof:name":"Padije S.a.r.l.",
    "wof:placetype":"venue"
},
  "geometry": {"coordinates":[5.57107,46.163658],"type":"Point"}
}