{
  "type": "Feature",
  "properties": {
    "iso:country":"FR",
    "sg:address":"6, Bd Paul Langevin, 38600 Fontaine",
    "sg:orig_category":"Non-Classified Establishments",
    "sg:phone":"+33 4 76 26 10 00",
    "sg:province":"Rhone-Alpes",
    "wof:name":"J.p.f. Impression S.a.r.l.",
    "wof:placetype":"venue"
},
  "geometry": {"coordinates":[5.684748,45.188477],"type":"Point"}
}