{
  "type": "Feature",
  "properties": {
    "iso:country":"FR",
    "sg:address":"2 Route De Kirchheim 67520 Marlenheim",
    "sg:city":"Marlenheim",
    "sg:classifiers":[
        {
            "category":"Manufacturing",
            "subcategory":"Wood Products",
            "type":"Manufacturing & Wholesale Goods"
        }
    ],
    "sg:phone":"+33 3 88 59 28 20",
    "sg:postcode":"67520",
    "sg:province":"Alsace",
    "sg:tags":[
        "professional",
        "furniture"
    ],
    "wof:name":"Janser-france",
    "wof:placetype":"venue"
},
  "geometry": {"coordinates":[7.497799,48.613808],"type":"Point"}
}