{
  "type": "Feature",
  "properties": {
    "addr:full":"10, Rue Godefroy, 92821 Puteaux C\u00e9dex Ile-de-France",
    "addr:housenumber":"10",
    "addr:postcode":"92821",
    "addr:street":"Rue Godefroy",
    "iso:country":"FR",
    "sg:address":"10, Rue Godefroy, 92821 Puteaux C\u00e9dex",
    "sg:orig_category":"Unclassifiable Establishments",
    "sg:phone":"+33 1 55 23 72 00",
    "sg:province":"Ile-de-France",
    "wof:name":"Nec Computer S.a.s.",
    "wof:placetype":"venue"
},
  "geometry": {"coordinates":[2.243952,48.880478],"type":"Point"}
}