{
  "type": "Feature",
  "properties": {
    "addr:full":"1 Rue Roux De Brignoles 13286 Marseille Cedex 6 Poitou-Charentes",
    "addr:housenumber":"1",
    "addr:postcode":"13286",
    "addr:street":"Rue Roux De Brignoles",
    "iso:country":"FR",
    "sg:address":"1 Rue Roux De Brignoles 13286 Marseille Cedex 6",
    "sg:classifiers":[
        {
            "category":"Banks & Credit Unions",
            "subcategory":"Financial Services",
            "type":"Services"
        }
    ],
    "sg:phone":"+33 4 91 00 36 60",
    "sg:province":"Poitou-Charentes",
    "sg:tags":[
        "banking",
        "consulting",
        "finance",
        "insurance"
    ],
    "wof:name":"Ma\u00cetre Astier Michel",
    "wof:placetype":"venue"
},
  "geometry": {"coordinates":[5.375636,43.289738],"type":"Point"}
}