{
  "type": "Feature",
  "properties": {
    "iso:country":"FR",
    "sg:address":"6, Rue de Gu\u00e9 Maingot, 61370 Echauffour",
    "sg:city":"\u00c9chauffour",
    "sg:orig_category":"Non-Classified Establishments",
    "sg:phone":"+33 2 33 34 87 30",
    "sg:postcode":"61370",
    "sg:province":"Basse Normandie",
    "wof:name":"C.i.m. S.a.r.l. - Comptoir International Des M\u00e9tiers",
    "wof:placetype":"venue"
},
  "geometry": {"coordinates":[0.404094,48.739201],"type":"Point"}
}