{
  "type": "Feature",
  "properties": {
    "iso:country":"FR",
    "sg:address":"4, Rue de Marivaux, 75002 Paris",
    "sg:orig_category":"Unclassifiable Establishments",
    "sg:phone":"+33 1 42 61 12 11",
    "sg:province":"Ile de France",
    "wof:name":"Europe Gardiennage S\u00e9curit\u00e9 Priv\u00e9e S.a.r.l.",
    "wof:placetype":"venue"
},
  "geometry": {"coordinates":[2.337531,48.870651],"type":"Point"}
}