{
  "type": "Feature",
  "properties": {
    "addr:full":"Place d'Arm\u00e9nie Saint Maurice de Beynost Rhone-Alpes 01700",
    "addr:postcode":"01700",
    "addr:street":"Place D'Arme \u0301Nie Saint;De;Rhone-Alpes",
    "iso:country":"FR",
    "sg:address":"Place d'Arm\u00e9nie",
    "sg:city":"Saint Maurice de Beynost",
    "sg:orig_category":"Non-Classified Establishments",
    "sg:phone":"+33 4 78 30 30 00",
    "sg:postcode":"01700",
    "sg:province":"Rhone-Alpes",
    "wof:name":"Toray Plastics Europe S.a.",
    "wof:placetype":"venue"
},
  "geometry": {"coordinates":[4.981334,45.826115],"type":"Point"}
}