{
  "type": "Feature",
  "properties": {
    "iso:country":"FR",
    "sg:address":"6, Rue Isaac Newton - Parc La Fayette, 25075 Besan\u00e7on",
    "sg:orig_category":"Non-Classified Establishments",
    "sg:phone":"+33 3 81 54 56 00",
    "sg:province":"Franche-Comt\u00e9",
    "wof:name":"Schlumberger Tests Et Transactions S.a.",
    "wof:placetype":"venue"
},
  "geometry": {"coordinates":[5.968105,47.212769],"type":"Point"}
}