{
  "type": "Feature",
  "properties": {
    "addr:full":"50 rue de Paradis 75010 Paris Ile de France 75010",
    "addr:housenumber":"50",
    "addr:postcode":"75010;75010",
    "addr:street":"Rue De Paradis",
    "iso:country":"FR",
    "sg:address":"50 rue de Paradis 75010 Paris",
    "sg:classifiers":[
        {
            "category":"Shopping",
            "subcategory":"Department Store",
            "type":"Retail Goods"
        }
    ],
    "sg:phone":"+33 1 44 79 05 00",
    "sg:postcode":"75010",
    "sg:province":"Ile de France",
    "sg:tags":[
        "linen",
        "bed"
    ],
    "wof:name":"Tisselva Sa",
    "wof:placetype":"venue"
},
  "geometry": {"coordinates":[2.349393,48.875744],"type":"Point"}
}