{
  "type": "Feature",
  "properties": {
    "addr:full":"25 Rue De Fontenay 28110 Luc\u00e9 Luc\u00e9 Centre 28110",
    "addr:housenumber":"25",
    "addr:postcode":"28110;28110",
    "addr:street":"Rue De Fontenay",
    "iso:country":"FR",
    "sg:address":"25 Rue De Fontenay 28110 Luc\u00e9",
    "sg:city":"Luc\u00e9",
    "sg:classifiers":[
        {
            "category":"Professional",
            "subcategory":"Engineering",
            "type":"Services"
        }
    ],
    "sg:phone":"+33 2 37 35 32 11",
    "sg:postcode":"28110",
    "sg:province":"Centre",
    "sg:tags":[
        "machine",
        "-",
        "mechanical"
    ],
    "wof:name":"Et Co Vent Sa",
    "wof:placetype":"venue"
},
  "geometry": {"coordinates":[1.445334,48.426815],"type":"Point"}
}