{
  "type": "Feature",
  "properties": {
    "addr:full":"rue Des Fonds Saint Jacques 59750 FEIGNIES Nord Pas-de-Calais 59750",
    "addr:postcode":"59750;59750",
    "addr:street":"Rue Des Fonds Saint Jacques",
    "iso:country":"FR",
    "sg:address":"rue Des Fonds Saint Jacques 59750 FEIGNIES",
    "sg:classifiers":[
        {
            "category":"Manufacturing",
            "subcategory":"Tools & Machinery",
            "type":"Manufacturing & Wholesale Goods"
        }
    ],
    "sg:phone":"+33 3 27 53 10 60",
    "sg:postcode":"59750",
    "sg:province":"Nord Pas-de-Calais",
    "sg:tags":[
        "machine"
    ],
    "wof:name":"Sculfort Muller Et Pesant S.a.",
    "wof:placetype":"venue"
},
  "geometry": {"coordinates":[3.90946,50.281399],"type":"Point"}
}