{
  "type": "Feature",
  "properties": {
    "iso:country":"FR",
    "sg:address":"La Bourch\u00e8re 61110 Madeleine Bouvet (La)",
    "sg:city":"Saint-Maurice-sur-Huisne",
    "sg:classifiers":[
        {
            "category":"Food & Beverages",
            "subcategory":"Groceries & Convenience Stores",
            "type":"Retail Goods"
        }
    ],
    "sg:phone":"+33 2 33 73 90 22",
    "sg:postcode":"61110",
    "sg:province":"Basse Normandie",
    "sg:tags":[
        "product",
        "grain",
        "cereal",
        "related"
    ],
    "wof:name":"Minoteries Ornaises",
    "wof:placetype":"venue"
},
  "geometry": {"coordinates":[-89.078362,42.266899],"type":"Point"}
}