{
  "type": "Feature",
  "properties": {
    "iso:country":"FR",
    "sg:address":"57, Rue de la Parmenti\u00e8re, 37520 La Riche",
    "sg:city":"La Riche",
    "sg:orig_category":"Unclassifiable Establishments",
    "sg:phone":"+33 2 47 59 89 33",
    "sg:postcode":"37520",
    "sg:province":"Centre",
    "wof:name":"C.m.t. S.a. - Constructions M\u00e9talliques Tourangelles",
    "wof:placetype":"venue"
},
  "geometry": {"coordinates":[0.664532,47.381283],"type":"Point"}
}