{
  "type": "Feature",
  "properties": {
    "addr:full":"100, Rue du Calvaire, 59553 Esquerchin Nord Pas-de-Calais",
    "addr:housenumber":"100",
    "addr:postcode":"59553",
    "addr:street":"Rue Du Calvaire",
    "iso:country":"FR",
    "sg:address":"100, Rue du Calvaire, 59553 Esquerchin",
    "sg:orig_category":"Unclassifiable Establishments",
    "sg:phone":"+33 3 27 98 51 92",
    "sg:province":"Nord Pas-de-Calais",
    "wof:name":"Liaison Graphique S.a.r.l.",
    "wof:placetype":"venue"
},
  "geometry": {"coordinates":[3.013086,50.377567],"type":"Point"}
}