{
  "type": "Feature",
  "properties": {
    "iso:country":"FR",
    "sg:address":"191, Rue de la Ferme de Conte - ZI Mi Carri\u00e8re, 40000 Mont de Marsan",
    "sg:city":"Mont-de-Marsan",
    "sg:orig_category":"Non-Classified Establishments",
    "sg:phone":"+33 5 58 06 73 73",
    "sg:postcode":"40000",
    "sg:province":"Aquitaine",
    "wof:name":"Multinet S.a.",
    "wof:placetype":"venue"
},
  "geometry": {"coordinates":[-0.498939,43.889503],"type":"Point"}
}