{
  "type": "Feature",
  "properties": {
    "addr:full":"rue d'Attichy 24 60350 JAULZY Picardie 60350",
    "addr:housenumber":"24",
    "addr:postcode":"60350;60350",
    "addr:street":"Rue D'Attichy;Picardie",
    "iso:country":"FR",
    "sg:address":"rue d'Attichy 24 60350 JAULZY",
    "sg:classifiers":[
        {
            "category":"Government",
            "subcategory":"Department Of Motor Vehicles",
            "type":"Public Place"
        }
    ],
    "sg:phone":"+33 3 44 42 16 22",
    "sg:postcode":"60350",
    "sg:province":"Picardie",
    "sg:tags":[
        "bending",
        "steel",
        "aluminium",
        "section",
        "non-ferrous",
        "metal",
        "machine"
    ],
    "wof:name":"Cintreuses Mingori Sas",
    "wof:placetype":"venue"
},
  "geometry": {"coordinates":[3.005373,49.405163],"type":"Point"}
}