{
  "type": "Feature",
  "properties": {
    "addr:full":"4, Place de Brant, 67000 Strasbourg Strasbourg Alsace 67000",
    "addr:housenumber":"4",
    "addr:postcode":"67000;67000",
    "addr:street":"Place De Brant",
    "iso:country":"FR",
    "sg:address":"4, Place de Brant, 67000 Strasbourg",
    "sg:city":"Strasbourg",
    "sg:orig_category":"Non-Classified Establishments",
    "sg:phone":"+33 3 88 36 68 00",
    "sg:postcode":"67000",
    "sg:province":"Alsace",
    "wof:name":"Anstett S.a.r.l.",
    "wof:placetype":"venue"
},
  "geometry": {"coordinates":[7.762598,48.586311],"type":"Point"}
}