{
  "type": "Feature",
  "properties": {
    "addr:full":"10 Rue Du Petit Malbrande 74100 Annemasse Rhone-Alpes 74100",
    "addr:housenumber":"10",
    "addr:postcode":"74100;74100",
    "addr:street":"Rue Du Petit Malbrande",
    "iso:country":"FR",
    "sg:address":"10 Rue Du Petit Malbrande 74100 Annemasse",
    "sg:classifiers":[
        {
            "category":"Manufacturing",
            "subcategory":"Tools & Machinery",
            "type":"Manufacturing & Wholesale Goods"
        }
    ],
    "sg:phone":"+33 4 50 87 83 00",
    "sg:postcode":"74100",
    "sg:province":"Rhone-Alpes",
    "sg:tags":[
        "environment",
        "equipment",
        "-"
    ],
    "wof:name":"Cc2a",
    "wof:placetype":"venue"
},
  "geometry": {"coordinates":[6.238244,46.190121],"type":"Point"}
}