{
  "type": "Feature",
  "properties": {
    "addr:full":"Rue De Canteranne 33600 Pessac Pessac Aquitaine 33600",
    "addr:postcode":"33600;33600",
    "addr:street":"Rue De Canteranne",
    "iso:country":"FR",
    "sg:address":"Rue De Canteranne 33600 Pessac",
    "sg:city":"Pessac",
    "sg:classifiers":[
        {
            "category":"Autos & Motor Vehicles",
            "subcategory":"Automobile Sales",
            "type":"Retail Goods"
        }
    ],
    "sg:phone":"+33 5 57 89 15 15",
    "sg:postcode":"33600",
    "sg:province":"Aquitaine",
    "sg:tags":[
        "equipment",
        "motor-cars",
        "transport"
    ],
    "wof:name":"Renault Societe Par Actions Simplifiee",
    "wof:placetype":"venue"
},
  "geometry": {"coordinates":[-0.634564,44.784676],"type":"Point"}
}