{
  "type": "Feature",
  "properties": {
    "iso:country":"FR",
    "sg:address":"79 Rue Boissiere 75116 Paris",
    "sg:classifiers":[
        {
            "category":"Professional",
            "subcategory":"Business Services",
            "type":"Services"
        }
    ],
    "sg:phone":"+33 1 42 65 23 59",
    "sg:province":"Poitou-Charentes",
    "sg:tags":[
        "body",
        "advice"
    ],
    "wof:name":"Agia",
    "wof:placetype":"venue"
},
  "geometry": {"coordinates":[2.285776,48.869205],"type":"Point"}
}