{
  "type": "Feature",
  "properties": {
    "addr:full":"ZI de Lanrinou - Pencran Landerneau C\u00e9dex Brittany 29419",
    "addr:postcode":"29419",
    "addr:street":"Zi De Lanrinou Pencran;Ce\u0301Dex",
    "iso:country":"FR",
    "sg:address":"ZI de Lanrinou - Pencran",
    "sg:city":"Landerneau C\u00e9dex",
    "sg:orig_category":"Non-Classified Establishments",
    "sg:phone":"+33 2 98 85 43 43",
    "sg:postcode":"29419",
    "sg:province":"Brittany",
    "wof:name":"U.c.l.a.b. - Union De Coop\u00e9ratives Laiti\u00e8res Bretonnes",
    "wof:placetype":"venue"
},
  "geometry": {"coordinates":[-4.235216,48.449196],"type":"Point"}
}