{
  "type": "Feature",
  "properties": {
    "addr:full":"ZA Blum Decomberousse Villeurbanne Rhone-Alpes 69100",
    "addr:postcode":"69100",
    "addr:street":"Za;Decomberousse;Rhone-Alpes",
    "iso:country":"FR",
    "sg:address":"ZA Blum Decomberousse",
    "sg:city":"Villeurbanne",
    "sg:orig_category":"Unclassifiable Establishments",
    "sg:phone":"+33 4 72 37 33 33",
    "sg:postcode":"69100",
    "sg:province":"Rhone-Alpes",
    "wof:name":"Bonsieri Et Fils S.a.r.l.",
    "wof:placetype":"venue"
},
  "geometry": {"coordinates":[4.87905,45.769596],"type":"Point"}
}