{
  "type": "Feature",
  "properties": {
    "addr:full":"4, Rue du Chemin de Fer, 93800 Epinay sur Seine Ile de France",
    "addr:housenumber":"4",
    "addr:postcode":"93800",
    "addr:street":"Rue Du Chemin De Fer",
    "iso:country":"FR",
    "sg:address":"4, Rue du Chemin de Fer, 93800 Epinay sur Seine",
    "sg:orig_category":"Non-Classified Establishments",
    "sg:phone":"+33 1 48 27 39 92",
    "sg:province":"Ile de France",
    "wof:name":"Gelati Marsala S.a.r.l.",
    "wof:placetype":"venue"
},
  "geometry": {"coordinates":[2.327952,48.95937],"type":"Point"}
}