{
  "type": "Feature",
  "properties": {
    "iso:country":"FR",
    "sg:address":"Rue de la Plage - Usine de Gray",
    "sg:city":"Gray",
    "sg:orig_category":"Unclassifiable Establishments",
    "sg:phone":"+33 3 84 65 03 23",
    "sg:postcode":"70100",
    "sg:province":"Franche Comt\u00e9",
    "wof:name":"Etilam S.a.",
    "wof:placetype":"venue"
},
  "geometry": {"coordinates":[5.514565,47.369511],"type":"Point"}
}