{
  "type": "Feature",
  "properties": {
    "addr:full":"13, Rue de la Croix Boisseli\u00e8re, 91420 Morangis Ile de France",
    "addr:housenumber":"13",
    "addr:postcode":"91420;ile",
    "addr:street":"Rue De La Croix Boisselie\u0300Re",
    "iso:country":"FR",
    "sg:address":"13, Rue de la Croix Boisseli\u00e8re, 91420 Morangis",
    "sg:orig_category":"Non-Classified Establishments",
    "sg:phone":"+33 1 69 74 21 50",
    "sg:province":"Ile de France",
    "wof:name":"S.p.p.i. S.a. -soci\u00e9t\u00e9 Parisienne De Photogravure Et D'impression",
    "wof:placetype":"venue"
},
  "geometry": {"coordinates":[2.34151,48.706581],"type":"Point"}
}