{
  "type": "Feature",
  "properties": {
    "addr:full":"3, All\u00e9e des Saules, 78121 Crespi\u00e8res Ile de France 78121",
    "addr:housenumber":"3",
    "addr:postcode":"78121;ile;78121",
    "addr:street":"Alle\u0301E Des Saules;France",
    "iso:country":"FR",
    "sg:address":"3, All\u00e9e des Saules, 78121 Crespi\u00e8res",
    "sg:orig_category":"Non-Classified Establishments",
    "sg:phone":"+33 1 34 59 08 56",
    "sg:postcode":"78121",
    "sg:province":"Ile de France",
    "wof:name":"Africolor S.a.r.l.",
    "wof:placetype":"venue"
},
  "geometry": {"coordinates":[1.922405,48.884083],"type":"Point"}
}