{
  "type": "Feature",
  "properties": {
    "addr:full":"Autoroute A13 Sortie 17 Saint Aubin sur Gaillon Haute Normandie 27600",
    "addr:housenumber":"17",
    "addr:postcode":"27600",
    "addr:street":"Autoroute A13 Sortie;Saint Aubin Sur;Haute Normandie",
    "iso:country":"FR",
    "sg:address":"Autoroute A13 Sortie 17",
    "sg:city":"Saint Aubin sur Gaillon",
    "sg:orig_category":"Unclassifiable Establishments",
    "sg:phone":"+33 2 32 77 80 80",
    "sg:postcode":"27600",
    "sg:province":"Haute Normandie",
    "wof:name":"Din\u00e9xis Diffusion Plus S.a.",
    "wof:placetype":"venue"
},
  "geometry": {"coordinates":[1.334138,49.114738],"type":"Point"}
}