{
  "type": "Feature",
  "properties": {
    "addr:full":"109 Av Charles De Gaulle 62231 Coquelles Nord Pas-de-Calais 62231",
    "addr:postcode":"62231;62231",
    "addr:street":"109 Av Charles De Gaulle",
    "iso:country":"FR",
    "sg:address":"109 Av Charles De Gaulle 62231 Coquelles",
    "sg:classifiers":[
        {
            "category":"Building & Trades",
            "subcategory":"Construction",
            "type":"Services"
        }
    ],
    "sg:phone":"+33 3 21 46 37 10",
    "sg:postcode":"62231",
    "sg:province":"Nord Pas-de-Calais",
    "sg:tags":[
        "work",
        "public"
    ],
    "wof:name":"Appua Littoral",
    "wof:placetype":"venue"
},
  "geometry": {"coordinates":[1.806528,50.942005],"type":"Point"}
}