{
  "type": "Feature",
  "properties": {
    "addr:full":"che la Madeleine Inferieure 06130 Grasse Midi Pyr\u00e9n\u00e9es",
    "addr:postcode":"06130",
    "addr:street":"Inferieure",
    "iso:country":"FR",
    "sg:address":"che la Madeleine Inferieure 06130 Grasse",
    "sg:classifiers":[
        {
            "category":"Manufacturing",
            "subcategory":"Chemicals & Compounds",
            "type":"Manufacturing & Wholesale Goods"
        }
    ],
    "sg:phone":"+33 4 93 70 01 32",
    "sg:province":"Midi Pyr\u00e9n\u00e9es",
    "sg:tags":[
        "base"
    ],
    "wof:name":"Orgasynth Industrie Sa",
    "wof:placetype":"venue"
},
  "geometry": {"coordinates":[6.930387,43.658508],"type":"Point"}
}