{
  "type": "Feature",
  "properties": {
    "iso:country":"FR",
    "sg:address":"09190 Lorp Sentaraille",
    "sg:classifiers":[
        {
            "category":"Farming",
            "subcategory":"Farm",
            "type":"Manufacturing & Wholesale Goods"
        }
    ],
    "sg:phone":"+33 5 61 66 24 33",
    "sg:postcode":"09190",
    "sg:province":"Midi Pyr\u00e9n\u00e9es",
    "sg:tags":[
        "horticulture",
        "agriculture",
        "livestock"
    ],
    "wof:name":"Bugeia Noureau",
    "wof:placetype":"venue"
},
  "geometry": {"coordinates":[1.119653,43.009182],"type":"Point"}
}