{
  "type": "Feature",
  "properties": {
    "iso:country":"FR",
    "sg:address":"B.P. 160, 85104 Les Sables d'Olonne C\u00e9dex^^Bd de l'Ile Vertime, 85100 Les Sables d'Olonne",
    "sg:orig_category":"Non-Classified Establishments",
    "sg:phone":"+33 2 51 32 00 88",
    "sg:province":"Pays de Loire",
    "wof:name":"Soci\u00e9t\u00e9 Ruchaud S.a.",
    "wof:placetype":"venue"
},
  "geometry": {"coordinates":[-1.772772,46.536057],"type":"Point"}
}