{
  "type": "Feature",
  "properties": {
    "iso:country":"FR",
    "sg:address":"Rue Galil\u00e9e - Immeuble les Triades B",
    "sg:city":"Lab\u00e8ge",
    "sg:orig_category":"Unclassifiable Establishments",
    "sg:phone":"+33 5 62 24 48 12",
    "sg:postcode":"31670",
    "sg:province":"Midi Pyr\u00e9n\u00e9es",
    "wof:name":"2 S.i.s. S.a.",
    "wof:placetype":"venue"
},
  "geometry": {"coordinates":[1.503288,43.54908],"type":"Point"}
}