{
  "type": "Feature",
  "properties": {
    "iso:country":"FR",
    "sg:address":"Rue Krautwiller",
    "sg:city":"Krautwiller",
    "sg:orig_category":"Unclassifiable Establishments",
    "sg:phone":"+33 3 88 64 56 50",
    "sg:postcode":"67170",
    "sg:province":"Alsace",
    "wof:name":"F.m. Logistic S.a. - Faure Et Machet",
    "wof:placetype":"venue"
},
  "geometry": {"coordinates":[7.698501,48.735001],"type":"Point"}
}