{
  "type": "Feature",
  "properties": {
    "addr:full":"31 Rte De La Wantzenau Zi De Bischheim 67800 Hoenheim Hoenheim Alsace 67800",
    "addr:housenumber":"31",
    "addr:postcode":"67800;67800",
    "addr:street":"Rte De La Wantzenau Zi De Bischheim",
    "iso:country":"FR",
    "sg:address":"31 Rte De La Wantzenau Zi De Bischheim 67800 Hoenheim",
    "sg:city":"Hoenheim",
    "sg:classifiers":[
        {
            "category":"Retail",
            "subcategory":"Auto Rental",
            "type":"Services"
        }
    ],
    "sg:phone":"+33 3 88 18 69 20",
    "sg:postcode":"67800",
    "sg:province":"Alsace",
    "sg:tags":[
        "machine",
        "-",
        "precision",
        "environment",
        "equipment",
        "engineering",
        "machinery",
        "mechanical"
    ],
    "wof:name":"Adt France",
    "wof:placetype":"venue"
},
  "geometry": {"coordinates":[7.752544,48.61483],"type":"Point"}
}