{
  "type": "Feature",
  "properties": {
    "addr:full":"Mairie 31370 Rieumes Midi Pyr\u00e9n\u00e9es 31370",
    "addr:postcode":"31370;31370",
    "iso:country":"FR",
    "sg:address":"Mairie 31370 Rieumes",
    "sg:classifiers":[
        {
            "category":"Utilities",
            "type":"Services"
        }
    ],
    "sg:phone":"+33 5 61 91 80 82",
    "sg:postcode":"31370",
    "sg:province":"Midi Pyr\u00e9n\u00e9es",
    "sg:tags":[
        "raw",
        "energy",
        "material"
    ],
    "wof:name":"Synd Int Eaux Des Cote Du Touch",
    "wof:placetype":"venue"
},
  "geometry": {"coordinates":[1.121941,43.349316],"type":"Point"}
}