{
  "type": "Feature",
  "properties": {
    "addr:full":"30 Rue Des Ormeaux 35008 Rennes Cedex Ile de France",
    "addr:housenumber":"30",
    "addr:postcode":"35008;ile",
    "addr:street":"Rue Des Ormeaux",
    "iso:country":"FR",
    "sg:address":"30 Rue Des Ormeaux 35008 Rennes Cedex",
    "sg:classifiers":[
        {
            "category":"Professional",
            "subcategory":"Business Services",
            "type":"Services"
        }
    ],
    "sg:phone":"+33 2 99 50 51 14",
    "sg:province":"Ile de France",
    "sg:tags":[
        "training",
        "advice"
    ],
    "wof:name":"College Nationalise Les Ormeaux",
    "wof:placetype":"venue"
},
  "geometry": {"coordinates":[-1.684477,48.107521],"type":"Point"}
}