{
  "type": "Feature",
  "properties": {
    "iso:country":"FR",
    "sg:address":"1, Rue Panhard, 91830 Le Coudray Montceaux",
    "sg:orig_category":"Unclassifiable Establishments",
    "sg:phone":"+33 1 64 93 84 63",
    "sg:province":"Ile de France",
    "wof:name":"Constructions M\u00e9caniques Bondioli Et Pavesi France S.a.",
    "wof:placetype":"venue"
},
  "geometry": {"coordinates":[2.482005,48.564362],"type":"Point"}
}