{
  "type": "Feature",
  "properties": {
    "iso:country":"FR",
    "sg:address":"St Mihiel 55300 ST MIHIEL",
    "sg:classifiers":[
        {
            "category":"Home & Garden",
            "subcategory":"Furniture",
            "type":"Retail Goods"
        }
    ],
    "sg:phone":"+33 3 29 89 01 62",
    "sg:province":"Lorraine",
    "sg:tags":[
        "oak"
    ],
    "wof:name":"Pierson Diffusion Sa",
    "wof:placetype":"venue"
},
  "geometry": {"coordinates":[5.54105,48.89183],"type":"Point"}
}