{
  "type": "Feature",
  "properties": {
    "addr:full":"B.P. 19, 08460 Signy l'Abbaye^^Rue du Moulin de la Carole, 08460 Signy l'Abbaye Dommery Champagne 08460",
    "addr:postcode":"08460;08460;08460",
    "addr:street":"B.P. 19;Moulin De La Carole;Champagne",
    "iso:country":"FR",
    "sg:address":"B.P. 19, 08460 Signy l'Abbaye^^Rue du Moulin de la Carole, 08460 Signy l'Abbaye",
    "sg:city":"Dommery",
    "sg:orig_category":"Non-Classified Establishments",
    "sg:phone":"+33 3 24 52 81 03",
    "sg:postcode":"08460",
    "sg:province":"Champagne",
    "wof:name":"Collet Fr\u00e8res S.a.r.l.",
    "wof:placetype":"venue"
},
  "geometry": {"coordinates":[4.42079,49.697769],"type":"Point"}
}