{
  "type": "Feature",
  "properties": {
    "addr:full":"2 Rue Marcel Doret Immeuble Antares 31700 Blagnac Midi Pyr\u00e9n\u00e9es 31700",
    "addr:housenumber":"2",
    "addr:postcode":"31700;31700",
    "addr:street":"Rue Marcel Doret;Antares",
    "iso:country":"FR",
    "sg:address":"2 Rue Marcel Doret Immeuble Antares 31700 Blagnac",
    "sg:classifiers":[
        {
            "category":"Banks & Credit Unions",
            "subcategory":"Financial Services",
            "type":"Services"
        }
    ],
    "sg:phone":"+33 5 61 71 53 71",
    "sg:postcode":"31700",
    "sg:province":"Midi Pyr\u00e9n\u00e9es",
    "sg:tags":[
        "banking",
        "insurance",
        "institution",
        "finance"
    ],
    "wof:name":"Cich",
    "wof:placetype":"venue"
},
  "geometry": {"coordinates":[1.378557,43.63343],"type":"Point"}
}