{
  "type": "Feature",
  "properties": {
    "iso:country":"FR",
    "sg:address":"11, Rue Caraman, 31000 Toulouse",
    "sg:orig_category":"Non-Classified Establishments",
    "sg:phone":"+33 5 61 82 56 13",
    "sg:province":"Midi Pyr\u00e9n\u00e9es",
    "wof:name":"Si On En Parlait S.a.r.l.",
    "wof:placetype":"venue"
},
  "geometry": {"coordinates":[1.452674,43.602352],"type":"Point"}
}