{
  "type": "Feature",
  "properties": {
    "addr:full":"Zi R Des Archicamps 80080 Amiens Amiens Picardie 80000",
    "addr:postcode":"80080 amiens;80000",
    "addr:street":"R Des Archicamps",
    "iso:country":"FR",
    "sg:address":"Zi R Des Archicamps 80080 Amiens",
    "sg:city":"Amiens",
    "sg:classifiers":[
        {
            "category":"Professional",
            "subcategory":"Engineering",
            "type":"Services"
        }
    ],
    "sg:phone":"+33 3 22 52 45 49",
    "sg:postcode":"80000",
    "sg:province":"Picardie",
    "sg:tags":[
        "machine",
        "-",
        "mechanical"
    ],
    "wof:name":"M G P",
    "wof:placetype":"venue"
},
  "geometry": {"coordinates":[2.26419,49.929359],"type":"Point"}
}