{
  "type": "Feature",
  "properties": {
    "iso:country":"FR",
    "sg:address":"Zi Les Rochettes BP 115 91152 Etampes Cedex",
    "sg:city":"\u00c9tampes",
    "sg:classifiers":[
        {
            "category":"Manufacturing",
            "subcategory":"Tools & Machinery",
            "type":"Manufacturing & Wholesale Goods"
        }
    ],
    "sg:phone":"+33 1 64 94 80 08",
    "sg:postcode":"91150",
    "sg:province":"Ile de France",
    "sg:tags":[
        "metallurgy",
        "metalworking"
    ],
    "wof:name":"Cattiaux Rochettes Sa",
    "wof:placetype":"venue"
},
  "geometry": {"coordinates":[2.16208,48.434761],"type":"Point"}
}