{
  "type": "Feature",
  "properties": {
    "iso:country":"FR",
    "sg:address":"route Nationale 6 38290 La Verpilliere",
    "sg:classifiers":[
        {
            "category":"Manufacturing",
            "subcategory":"Motor Vehicles & Parts",
            "type":"Manufacturing & Wholesale Goods"
        }
    ],
    "sg:phone":"+33 4 74 82 24 00",
    "sg:postcode":"38290",
    "sg:province":"Rhone-Alpes",
    "sg:tags":[
        "current",
        "direct"
    ],
    "wof:name":"Tecumseh Europe S.a.",
    "wof:placetype":"venue"
},
  "geometry": {"coordinates":[5.147387,45.632999],"type":"Point"}
}