{
  "type": "Feature",
  "properties": {
    "iso:country":"FR",
    "sg:address":"12, Rue du Bois Gasseau, 77210 Samoreau",
    "sg:orig_category":"Unclassifiable Establishments",
    "sg:phone":"+33 1 64 23 91 20",
    "sg:province":"Ile de France",
    "wof:name":"Noyer S.a.",
    "wof:placetype":"venue"
},
  "geometry": {"coordinates":[2.764461,48.424995],"type":"Point"}
}