{
  "type": "Feature",
  "properties": {
    "addr:full":"12 bis, Rue de la Gr\u00e8ve, 28800 Bonneval Bonneval Centre 28800",
    "addr:housenumber":"12 bis",
    "addr:postcode":"28800;28800",
    "addr:street":"Rue De La Gre\u0300Ve;Bonneval",
    "iso:country":"FR",
    "sg:address":"12 bis, Rue de la Gr\u00e8ve, 28800 Bonneval",
    "sg:city":"Bonneval",
    "sg:orig_category":"Unclassifiable Establishments",
    "sg:phone":"+33 2 37 96 27 30",
    "sg:postcode":"28800",
    "sg:province":"Centre",
    "wof:name":"Synergie Hommes Entreprise S.a.r.l.",
    "wof:placetype":"venue"
},
  "geometry": {"coordinates":[1.386936,48.180283],"type":"Point"}
}