{
  "type": "Feature",
  "properties": {
    "addr:full":"1, Rue du Moulin \u00e0 Vent, 86000 Poitiers Poitou-Charentes 86000",
    "addr:housenumber":"1",
    "addr:postcode":"86000;86000",
    "addr:street":"Rue Du Moulin A\u0300 Vent",
    "iso:country":"FR",
    "sg:address":"1, Rue du Moulin \u00e0 Vent, 86000 Poitiers",
    "sg:orig_category":"Unclassifiable Establishments",
    "sg:phone":"+33 5 49 60 36 36",
    "sg:postcode":"86000",
    "sg:province":"Poitou-Charentes",
    "wof:name":"La Nouvelle R\u00e9publique Du Centre Ouest",
    "wof:placetype":"venue"
},
  "geometry": {"coordinates":[0.340001,46.585117],"type":"Point"}
}