{
  "type": "Feature",
  "properties": {
    "addr:full":"rue du Ch\u00e2teau 08160 Flize Balaives-et-Butz Champagne 08160",
    "addr:postcode":"08160;08160",
    "addr:street":"Rue Du Cha\u0302Teau;Champagne",
    "iso:country":"FR",
    "sg:address":"rue du Ch\u00e2teau 08160 Flize",
    "sg:city":"Balaives-et-Butz",
    "sg:classifiers":[
        {
            "category":"Bars & Pubs",
            "subcategory":"Nightclub",
            "type":"Food & Drink"
        }
    ],
    "sg:phone":"+33 3 24 54 04 92",
    "sg:postcode":"08160",
    "sg:province":"Champagne",
    "sg:tags":[
        "plants",
        "beverage",
        "turnkey"
    ],
    "wof:name":"Soci\u00e9t\u00e9 Arcomat Sa",
    "wof:placetype":"venue"
},
  "geometry": {"coordinates":[4.776803,49.699009],"type":"Point"}
}