{
  "type": "Feature",
  "properties": {
    "addr:full":"1 Bis Rue Sainte Marie 03100 Montlu\u00e7on Montlu\u00e7on Auvergne 03100",
    "addr:housenumber":"1 bis",
    "addr:postcode":"03100;03100",
    "addr:street":"Rue Sainte Marie",
    "iso:country":"FR",
    "sg:address":"1 Bis Rue Sainte Marie 03100 Montlu\u00e7on",
    "sg:city":"Montlu\u00e7on",
    "sg:classifiers":[
        {
            "category":"Professional",
            "subcategory":"Advertising",
            "type":"Services"
        }
    ],
    "sg:phone":"+33 4 70 02 53 53",
    "sg:postcode":"03100",
    "sg:province":"Auvergne",
    "sg:tags":[
        "communication",
        "medium"
    ],
    "wof:name":"Publicite Agri Centre Sarl",
    "wof:placetype":"venue"
},
  "geometry": {"coordinates":[2.605265,46.338802],"type":"Point"}
}