{
  "type": "Feature",
  "properties": {
    "addr:full":"764 R Claude Terrasse 69210 L'Arbresle Rhone-Alpes 69210",
    "addr:housenumber":"764",
    "addr:postcode":"69210;69210",
    "addr:street":"R Claude Terrasse",
    "iso:country":"FR",
    "sg:address":"764 R Claude Terrasse 69210 L'Arbresle",
    "sg:classifiers":[
        {
            "category":"Professional",
            "subcategory":"Engineering",
            "type":"Services"
        }
    ],
    "sg:phone":"+33 4 74 01 01 13",
    "sg:postcode":"69210",
    "sg:province":"Rhone-Alpes",
    "sg:tags":[
        "machine",
        "-",
        "mechanical"
    ],
    "wof:name":"Ets Joly Et Cie Sarl",
    "wof:placetype":"venue"
},
  "geometry": {"coordinates":[4.612185,45.829075],"type":"Point"}
}