{
  "type": "Feature",
  "properties": {
    "addr:full":"7, Bd Pierre Carle Noisiel, 77446 Marne la Vall\u00e9e Midi Pyr\u00e9n\u00e9es",
    "addr:housenumber":"7",
    "addr:postcode":"77446",
    "addr:street":"Bd Pierre Carle",
    "iso:country":"FR",
    "sg:address":"7, Bd Pierre Carle Noisiel, 77446 Marne la Vall\u00e9e",
    "sg:orig_category":"Unclassifiable Establishments",
    "sg:phone":"+33 1 60 53 21 00",
    "sg:province":"Midi Pyr\u00e9n\u00e9es",
    "wof:name":"Nestl\u00e9 France S.a.",
    "wof:placetype":"venue"
},
  "geometry": {"coordinates":[-0.840999,45.891319],"type":"Point"}
}