{
  "type": "Feature",
  "properties": {
    "iso:country":"FR",
    "sg:address":"B.P. 20, 12300 Decazeville C\u00e9dex^^9, Rue Cabrol, 12300 Decazeville",
    "sg:orig_category":"Non-Classified Establishments",
    "sg:phone":"+33 5 65 43 75 40",
    "sg:postcode":"12300",
    "sg:province":"Midi Pyr\u00e9n\u00e9es",
    "wof:name":"B.p.t.a.",
    "wof:placetype":"venue"
},
  "geometry": {"coordinates":[2.307615,44.541191],"type":"Point"}
}