{
  "type": "Feature",
  "properties": {
    "iso:country":"FR",
    "sg:address":"B.P. 408, 92141 Clamart C\u00e9dex^^1, Av. du G\u00e9n\u00e9ral de Gaulle, 92140 Clamart",
    "sg:orig_category":"Non-Classified Establishments",
    "sg:phone":"+33 1 47 65 43 21",
    "sg:postcode":"92140",
    "sg:province":"Ile de France",
    "wof:name":"E.d.f. Division Recherche Et D\u00e9veloppement Centre De Recherche",
    "wof:placetype":"venue"
},
  "geometry": {"coordinates":[2.262025,48.80027],"type":"Point"}
}