{
  "type": "Feature",
  "properties": {
    "addr:full":"594, Rue du 8 Mai 1945, 60290 Laigneville Picardie",
    "addr:housenumber":"594",
    "addr:postcode":"60290",
    "addr:street":"Rue Du 8 Mai 1945",
    "iso:country":"FR",
    "sg:address":"594, Rue du 8 Mai 1945, 60290 Laigneville",
    "sg:orig_category":"Unclassifiable Establishments",
    "sg:phone":"+33 3 44 71 05 40",
    "sg:province":"Picardie",
    "wof:name":"Hainault S.a.",
    "wof:placetype":"venue"
},
  "geometry": {"coordinates":[2.443714,49.302479],"type":"Point"}
}