{
  "type": "Feature",
  "properties": {
    "addr:full":"2 Rue General Leclerc Pont Audemer Haute Normandie 27500",
    "addr:housenumber":"2",
    "addr:postcode":"27500",
    "addr:street":"Rue General Leclerc Pont;Haute Normandie",
    "iso:country":"FR",
    "sg:address":"2 Rue General Leclerc",
    "sg:city":"Pont Audemer",
    "sg:classifiers":[
        {
            "category":"Banks & Credit Unions",
            "subcategory":"Financial Services",
            "type":"Services"
        }
    ],
    "sg:phone":"+33 2 32 41 60 14",
    "sg:postcode":"27500",
    "sg:province":"Haute Normandie",
    "sg:tags":[
        "banking",
        "finance",
        "insurance"
    ],
    "wof:name":"Caisse Regionale Du Credit Agricole Mutuel De L'eure (crca)",
    "wof:placetype":"venue"
},
  "geometry": {"coordinates":[0.513305,49.354401],"type":"Point"}
}