{
  "type": "Feature",
  "properties": {
    "iso:country":"FR",
    "sg:address":"Rue Marie Curie",
    "sg:city":"Saint S\u00e9bastien sur Loire",
    "sg:orig_category":"Non-Classified Establishments",
    "sg:phone":"+33 2 40 34 55 00",
    "sg:postcode":"44230",
    "sg:province":"Pays de Loire",
    "wof:name":"Jarnoux S.a.",
    "wof:placetype":"venue"
},
  "geometry": {"coordinates":[-1.483482,47.188084],"type":"Point"}
}