{
  "type": "Feature",
  "properties": {
    "iso:country":"FR",
    "sg:address":"B.P. 40",
    "sg:city":"Rabastens^^81630 Salvagnac",
    "sg:orig_category":"Non-Classified Establishments",
    "sg:phone":"+33 5 63 40 46 71",
    "sg:postcode":"81800",
    "sg:province":"Midi Pyr\u00e9n\u00e9es",
    "wof:name":"Micro Pointe S.a.r.l.",
    "wof:placetype":"venue"
},
  "geometry": {"coordinates":[1.58949,43.864319],"type":"Point"}
}