{
  "type": "Feature",
  "properties": {
    "iso:country":"FR",
    "sg:address":"March\u00e9 Internat Saint Charles 66000 Perpignan",
    "sg:classifiers":[
        {
            "category":"Food & Beverages",
            "subcategory":"Fruits & Vegetables",
            "type":"Retail Goods"
        }
    ],
    "sg:phone":"+33 4 68 55 36 00",
    "sg:postcode":"66000",
    "sg:province":"Languedoc-Roussillon",
    "wof:name":"Camilor France International Sa",
    "wof:placetype":"venue"
},
  "geometry": {"coordinates":[2.89991,42.704205],"type":"Point"}
}