{
  "type": "Feature",
  "properties": {
    "addr:full":"11 Rue Ferdinand Duval 75004 Paris Ile de France 75004",
    "addr:housenumber":"11",
    "addr:postcode":"75004;75004",
    "addr:street":"Rue Ferdinand Duval",
    "iso:country":"FR",
    "sg:address":"11 Rue Ferdinand Duval 75004 Paris",
    "sg:classifiers":[
        {
            "category":"Home & Garden",
            "subcategory":"Furniture",
            "type":"Retail Goods"
        }
    ],
    "sg:phone":"+33 1 42 78 99 99",
    "sg:postcode":"75004",
    "sg:province":"Ile de France",
    "sg:tags":[
        "household",
        "wood"
    ],
    "wof:name":"Vds",
    "wof:placetype":"venue"
},
  "geometry": {"coordinates":[2.35933,48.856579],"type":"Point"}
}