{
  "type": "Feature",
  "properties": {
    "addr:full":"Rue Fran\u00e7ois Boussus Wignehies Nord Pas-de-Calais 59212",
    "addr:postcode":"59212",
    "addr:street":"Rue Franc\u0327Ois Boussus",
    "iso:country":"FR",
    "sg:address":"Rue Fran\u00e7ois Boussus",
    "sg:city":"Wignehies",
    "sg:orig_category":"Unclassifiable Establishments",
    "sg:phone":"+33 3 27 60 22 22",
    "sg:postcode":"59212",
    "sg:province":"Nord Pas-de-Calais",
    "wof:name":"Filature Louis Hubinet S.a.",
    "wof:placetype":"venue"
},
  "geometry": {"coordinates":[3.996413,50.009663],"type":"Point"}
}