{
  "type": "Feature",
  "properties": {
    "addr:full":"2, Rue Emilie Path\u00e9 - Espace Lumi\u00e8re B\u00e2t. 3, 78400 Chatou Ile de France",
    "addr:housenumber":"2;3",
    "addr:postcode":"78400",
    "addr:street":"Rue Emilie Pathe\u0301;Ile De France",
    "iso:country":"FR",
    "sg:address":"2, Rue Emilie Path\u00e9 - Espace Lumi\u00e8re B\u00e2t. 3, 78400 Chatou",
    "sg:orig_category":"Unclassifiable Establishments",
    "sg:phone":"+33 1 30 09 60 30",
    "sg:province":"Ile de France",
    "wof:name":"Herrenknecht France S.a.r.l.",
    "wof:placetype":"venue"
},
  "geometry": {"coordinates":[2.1558,48.889992],"type":"Point"}
}