{
  "type": "Feature",
  "properties": {
    "iso:country":"FR",
    "sg:address":"ZI Corsac",
    "sg:city":"Brives Charensac",
    "sg:orig_category":"Non-Classified Establishments",
    "sg:phone":"+33 4 71 09 17 59",
    "sg:postcode":"43700",
    "sg:province":"Auvergne",
    "wof:name":"Rectification Du Velay S.a.r.l.",
    "wof:placetype":"venue"
},
  "geometry": {"coordinates":[3.924806,45.047512],"type":"Point"}
}