{
  "type": "Feature",
  "properties": {
    "addr:full":"passage de la Briante 61000 ALENCON Alen\u00e7on Basse Normandie 61000",
    "addr:postcode":"61000;61000",
    "addr:street":"Passage De La Briante",
    "iso:country":"FR",
    "sg:address":"passage de la Briante 61000 ALENCON",
    "sg:city":"Alen\u00e7on",
    "sg:orig_category":"Baling Presses, Manually Operated, Mechanical",
    "sg:phone":"+33 2 33 81 44 22",
    "sg:postcode":"61000",
    "sg:province":"Basse Normandie",
    "wof:name":"Lely France Sas",
    "wof:placetype":"venue"
},
  "geometry": {"coordinates":[0.086297,48.429993],"type":"Point"}
}