{
  "type": "Feature",
  "properties": {
    "addr:full":"2/4, Rue Raymond Tissot, 01100 Oyonnax Rhone-Alpes",
    "addr:housenumber":"2 / 4",
    "addr:postcode":"01100",
    "addr:street":"Rue Raymond Tissot",
    "iso:country":"FR",
    "sg:address":"2/4, Rue Raymond Tissot, 01100 Oyonnax",
    "sg:orig_category":"Unclassifiable Establishments",
    "sg:phone":"+33 4 74 81 72 90",
    "sg:province":"Rhone-Alpes",
    "wof:name":"Francia S.a.",
    "wof:placetype":"venue"
},
  "geometry": {"coordinates":[5.64399,46.24971],"type":"Point"}
}