{
  "type": "Feature",
  "properties": {
    "iso:country":"FR",
    "sg:address":"25, All\u00e9e Veuve Lindet Girard, 93390 Clichy sous Bois",
    "sg:orig_category":"Unclassifiable Establishments",
    "sg:phone":"+33 1 43 30 34 42",
    "sg:province":"Ile de France",
    "wof:name":"Scandella Et Fr\u00e8res S.a.",
    "wof:placetype":"venue"
},
  "geometry": {"coordinates":[2.553109,48.910973],"type":"Point"}
}