{
  "type": "Feature",
  "properties": {
    "addr:full":"1 Rue Hortensias 86460 Availles Limouzine Poitou-Charentes 86460",
    "addr:housenumber":"1",
    "addr:postcode":"86460;86460",
    "addr:street":"Rue Hortensias;Limouzine",
    "iso:country":"FR",
    "sg:address":"1 Rue Hortensias 86460 Availles Limouzine",
    "sg:classifiers":[
        {
            "category":"Shopping",
            "subcategory":"Crafts & Fabrics",
            "type":"Retail Goods"
        }
    ],
    "sg:phone":"+33 5 49 48 50 69",
    "sg:postcode":"86460",
    "sg:province":"Poitou-Charentes",
    "sg:tags":[
        "textile",
        "clothing"
    ],
    "wof:name":"Wauenzell Jean Claude",
    "wof:placetype":"venue"
},
  "geometry": {"coordinates":[0.658399,46.117687],"type":"Point"}
}