{
  "type": "Feature",
  "properties": {
    "addr:full":"10-12 ave Roquepine; Paris; 75008 Ile de France 75008",
    "addr:housenumber":"10-12",
    "addr:postcode":"75008 ile;france 75008",
    "addr:street":"Ave",
    "iso:country":"FR",
    "sg:address":"10-12 ave Roquepine; Paris; 75008",
    "sg:classifiers":[
        {
            "category":"Banks & Credit Unions",
            "subcategory":"Bank",
            "type":"Services"
        }
    ],
    "sg:phone":"+33 14343127500",
    "sg:postcode":"75008",
    "sg:province":"Ile de France",
    "wof:name":"Banque Du Cr\u00e9dit, Mutuel Ile De France Bcmi",
    "wof:placetype":"venue"
},
  "geometry": {"coordinates":[2.319128,48.873493],"type":"Point"}
}