{
  "type": "Feature",
  "properties": {
    "iso:country":"FR",
    "sg:address":"1, Rue Hippolyte Noiret, 08300 Rethel",
    "sg:city":"Bergnicourt",
    "sg:orig_category":"Unclassifiable Establishments",
    "sg:phone":"+33 3 24 39 61 61",
    "sg:postcode":"08300",
    "sg:province":"Champagne",
    "wof:name":"Martin Guillemin S.a.",
    "wof:placetype":"venue"
},
  "geometry": {"coordinates":[4.362531,49.507202],"type":"Point"}
}