{
  "type": "Feature",
  "properties": {
    "addr:full":"Av Victor Hugo 57450 Far\u00e9bersviller Lorraine 57450",
    "addr:postcode":"57450;57450",
    "addr:street":"Av Victor Hugo",
    "iso:country":"FR",
    "sg:address":"Av Victor Hugo 57450 Far\u00e9bersviller",
    "sg:classifiers":[
        {
            "category":"Professional",
            "subcategory":"Business Services",
            "type":"Services"
        }
    ],
    "sg:phone":"+33 3 87 29 81 50",
    "sg:postcode":"57450",
    "sg:province":"Lorraine",
    "sg:tags":[
        "training",
        "advice"
    ],
    "wof:name":"College Georges Holderith",
    "wof:placetype":"venue"
},
  "geometry": {"coordinates":[6.88145,49.119644],"type":"Point"}
}