{
  "type": "Feature",
  "properties": {
    "addr:full":"8, Rue Sainte Anne, 75001 Paris Ile de France",
    "addr:housenumber":"8",
    "addr:postcode":"75001",
    "addr:street":"Rue Sainte Anne",
    "iso:country":"FR",
    "sg:address":"8, Rue Sainte Anne, 75001 Paris",
    "sg:orig_category":"Unclassifiable Establishments",
    "sg:phone":"+33 1 49 26 49 65",
    "sg:province":"Ile de France",
    "wof:name":"Bank Of Tokyo Mitsubishi S.a.",
    "wof:placetype":"venue"
},
  "geometry": {"coordinates":[2.335302,48.865379],"type":"Point"}
}