{
  "type": "Feature",
  "properties": {
    "iso:country":"FR",
    "sg:address":"Place Bonaventure des Perriers",
    "sg:city":"Arnay le Duc",
    "sg:orig_category":"Non-Classified Establishments",
    "sg:phone":"+33 3 80 90 52 25",
    "sg:postcode":"21230",
    "sg:province":"Bourgogne",
    "wof:name":"Caisse D'epargne De Bourgogne - Agence Arnay Le Duc",
    "wof:placetype":"venue"
},
  "geometry": {"coordinates":[4.486046,47.130226],"type":"Point"}
}