{
  "type": "Feature",
  "properties": {
    "iso:country":"FR",
    "sg:address":"24",
    "sg:city":"Beauvais BP 90148 Cedex 35501 Vitr\u00e9",
    "sg:classifiers":[
        {
            "category":"Manufacturing",
            "subcategory":"Wood Products",
            "type":"Manufacturing & Wholesale Goods"
        }
    ],
    "sg:phone":"+33 2 99 75 04 50",
    "sg:province":"Brittany",
    "sg:tags":[
        "professional",
        "furniture"
    ],
    "wof:name":"M.m.o",
    "wof:placetype":"venue"
},
  "geometry": {"coordinates":[-1.211844,48.123085],"type":"Point"}
}