{
  "type": "Feature",
  "properties": {
    "addr:full":"4 pl Sebastian Brant; Strasbourg; 67000 Strasbourg Alsace 67000",
    "addr:housenumber":"4",
    "addr:postcode":"67000;67000",
    "addr:street":"Pl Sebastian Brant",
    "iso:country":"FR",
    "sg:address":"4 pl Sebastian Brant; Strasbourg; 67000",
    "sg:city":"Strasbourg",
    "sg:classifiers":[
        {
            "category":"Banks & Credit Unions",
            "subcategory":"Bank",
            "type":"Services"
        }
    ],
    "sg:phone":"+33 3 88 35 76 76",
    "sg:postcode":"67000",
    "sg:province":"Alsace",
    "wof:name":"Monte Paschi, Banque Sa",
    "wof:placetype":"venue"
},
  "geometry": {"coordinates":[7.762598,48.586311],"type":"Point"}
}