{
  "type": "Feature",
  "properties": {
    "addr:full":"Rue des P\u00e2querettes Luxeuil les Bains Franche Comt\u00e9 70300",
    "addr:postcode":"70300",
    "addr:street":"Rue Des Pa\u0302Querettes;Franche Comte\u0301",
    "iso:country":"FR",
    "sg:address":"Rue des P\u00e2querettes",
    "sg:city":"Luxeuil les Bains",
    "sg:orig_category":"Unclassifiable Establishments",
    "sg:phone":"+33 3 84 93 79 13",
    "sg:postcode":"70300",
    "sg:province":"Franche Comt\u00e9",
    "wof:name":"L.p.p.v. S.a. - Luxovienne De Pl\u00e2trerie Peinture Et Vitrerie",
    "wof:placetype":"venue"
},
  "geometry": {"coordinates":[6.37513,47.808426],"type":"Point"}
}