{
  "type": "Feature",
  "properties": {
    "addr:full":"66/68, Rue de la Folie Regnault, 75011 Paris Ile de France",
    "addr:housenumber":"66 / 68",
    "addr:postcode":"75011",
    "addr:street":"Rue De La Folie Regnault",
    "iso:country":"FR",
    "sg:address":"66/68, Rue de la Folie Regnault, 75011 Paris",
    "sg:orig_category":"Non-Classified Establishments",
    "sg:phone":"+33 1 43 71 77 50",
    "sg:province":"Ile de France",
    "wof:name":"Exprimo S.a.r.l.",
    "wof:placetype":"venue"
},
  "geometry": {"coordinates":[2.386228,48.860832],"type":"Point"}
}