{
  "type": "Feature",
  "properties": {
    "iso:country":"FR",
    "sg:address":"680 Rue De Peyrehitte Zone Industrielle 65300 Lannemezan",
    "sg:classifiers":[
        {
            "category":"Utilities",
            "subcategory":"Electric",
            "type":"Services"
        }
    ],
    "sg:phone":"+33 5 62 98 01 69",
    "sg:postcode":"65300",
    "sg:province":"Midi Pyr\u00e9n\u00e9es",
    "sg:tags":[
        "electricity",
        "raw",
        "energy",
        "material"
    ],
    "wof:name":"Energies Services Lannemezan",
    "wof:placetype":"venue"
},
  "geometry": {"coordinates":[0.434825,43.115124],"type":"Point"}
}