{
  "type": "Feature",
  "properties": {
    "addr:full":"2 Avenue Leon Jouhaux 33210 Langon Langon Aquitaine 33210",
    "addr:housenumber":"2",
    "addr:postcode":"33210;33210",
    "addr:street":"Avenue Leon Jouhaux",
    "iso:country":"FR",
    "sg:address":"2 Avenue Leon Jouhaux 33210 Langon",
    "sg:city":"Langon",
    "sg:classifiers":[
        {
            "category":"Professional",
            "subcategory":"Engineering",
            "type":"Services"
        }
    ],
    "sg:phone":"+33 5 57 98 08 80",
    "sg:postcode":"33210",
    "sg:province":"Aquitaine",
    "sg:tags":[
        "machine",
        "-",
        "mechanical"
    ],
    "wof:name":"Lucas Sa",
    "wof:placetype":"venue"
},
  "geometry": {"coordinates":[-0.264876,44.547108],"type":"Point"}
}