{
  "type": "Feature",
  "properties": {
    "addr:full":"3 Bis Rue Garnier 92200 Neuilly Sur Seine Ile de France 92200",
    "addr:housenumber":"3 bis",
    "addr:postcode":"92200;92200",
    "addr:street":"Rue Garnier",
    "iso:country":"FR",
    "sg:address":"3 Bis Rue Garnier 92200 Neuilly Sur Seine",
    "sg:classifiers":[
        {
            "category":"Professional",
            "subcategory":"Advertising",
            "type":"Services"
        }
    ],
    "sg:phone":"+33 1 47 47 13 50",
    "sg:postcode":"92200",
    "sg:province":"Ile de France",
    "sg:tags":[
        "information",
        "medium",
        "communication"
    ],
    "wof:name":"Son Et Lumiere Sa",
    "wof:placetype":"venue"
},
  "geometry": {"coordinates":[2.260412,48.885685],"type":"Point"}
}