{
  "type": "Feature",
  "properties": {
    "addr:full":"B.P. 34, 28111 Luc\u00e9 C\u00e9dex^^50, Rue Mar\u00e9chal Leclerc - Z.I., 28110 Luc\u00e9 Luc\u00e9 Centre 28110",
    "addr:postcode":"28111;28110;28110",
    "addr:street":"B.P. 34;Rue Mare\u0301Chal Leclerc",
    "iso:country":"FR",
    "sg:address":"B.P. 34, 28111 Luc\u00e9 C\u00e9dex^^50, Rue Mar\u00e9chal Leclerc - Z.I., 28110 Luc\u00e9",
    "sg:city":"Luc\u00e9",
    "sg:orig_category":"Non-Classified Establishments",
    "sg:phone":"+33 2 37 35 68 07",
    "sg:postcode":"28110",
    "sg:province":"Centre",
    "wof:name":"Stratline Industries S.a.",
    "wof:placetype":"venue"
},
  "geometry": {"coordinates":[1.467334,48.440228],"type":"Point"}
}