{
  "type": "Feature",
  "properties": {
    "addr:full":"Ltd Tourneuve 44700 Orvault Pays de Loire 44700",
    "addr:postcode":"44700;44700",
    "addr:street":"Tourneuve",
    "iso:country":"FR",
    "sg:address":"Ltd Tourneuve 44700 Orvault",
    "sg:classifiers":[
        {
            "category":"Farming",
            "subcategory":"Farm",
            "type":"Manufacturing & Wholesale Goods"
        }
    ],
    "sg:phone":"+33 2 40 63 92 93",
    "sg:postcode":"44700",
    "sg:province":"Pays de Loire",
    "sg:tags":[
        "horticulture",
        "agriculture",
        "livestock"
    ],
    "wof:name":"Val D'or Plants",
    "wof:placetype":"venue"
},
  "geometry": {"coordinates":[-1.597563,47.278759],"type":"Point"}
}