{
  "type": "Feature",
  "properties": {
    "iso:country":"FR",
    "sg:address":"Ld Zone Industrielle D Argon 74370 Argonay",
    "sg:classifiers":[
        {
            "category":"Manufacturing",
            "subcategory":"Metals",
            "type":"Manufacturing & Wholesale Goods"
        }
    ],
    "sg:phone":"+33 4 50 27 21 87",
    "sg:postcode":"74370",
    "sg:province":"Rhone-Alpes",
    "sg:tags":[
        "processing",
        "-",
        "metalworking",
        "metallic",
        "metallurgy",
        "finished"
    ],
    "wof:name":"Fmb",
    "wof:placetype":"venue"
},
  "geometry": {"coordinates":[6.109395,45.934166],"type":"Point"}
}