{
  "type": "Feature",
  "properties": {
    "iso:country":"FR",
    "sg:address":"41, Rue Michel Carr\u00e9, 95100 Argenteuil",
    "sg:orig_category":"Unclassifiable Establishments",
    "sg:phone":"+33 1 30 76 31 31",
    "sg:province":"Ile de France",
    "wof:name":"Capest S.a.",
    "wof:placetype":"venue"
},
  "geometry": {"coordinates":[2.23806,48.934895],"type":"Point"}
}