{
  "type": "Feature",
  "properties": {
    "iso:country":"FR",
    "sg:address":"B.P. 22",
    "sg:city":"Portes l\u00e8s Valence C\u00e9dex^^26800 Portes l\u00e8s Valence",
    "sg:orig_category":"Non-Classified Establishments",
    "sg:phone":"+33 4 75 57 07 33",
    "sg:postcode":"26800",
    "sg:province":"Rhone-Alpes",
    "wof:name":"Billon S.a.",
    "wof:placetype":"venue"
},
  "geometry": {"coordinates":[4.907647,44.794395],"type":"Point"}
}