{
  "type": "Feature",
  "properties": {
    "addr:full":"4, Rue de Salonique, 95100 Argenteuil Ile de France",
    "addr:housenumber":"4",
    "addr:postcode":"95100;ile",
    "addr:street":"Rue De Salonique",
    "iso:country":"FR",
    "sg:address":"4, Rue de Salonique, 95100 Argenteuil",
    "sg:orig_category":"Unclassifiable Establishments",
    "sg:phone":"+33 1 39 98 22 00",
    "sg:province":"Ile de France",
    "wof:name":"Vishay Composants Electroniques S.a.",
    "wof:placetype":"venue"
},
  "geometry": {"coordinates":[2.208293,48.948566],"type":"Point"}
}