{
  "type": "Feature",
  "properties": {
    "iso:country":"FR",
    "sg:address":"B.P. 8",
    "sg:city":"Eulmont",
    "sg:orig_category":"Non-Classified Establishments",
    "sg:phone":"+33 3 83 22 29 29",
    "sg:postcode":"54690",
    "sg:province":"Lorraine",
    "wof:name":"Altacom S.a.r.l.",
    "wof:placetype":"venue"
},
  "geometry": {"coordinates":[6.224874,48.750843],"type":"Point"}
}