{
  "type": "Feature",
  "properties": {
    "addr:full":"165 Route De Dieppe 76770 Le Houlme Haute Normandie 76770",
    "addr:housenumber":"165",
    "addr:postcode":"76770;76770",
    "addr:street":"Route De Dieppe;Haute Normandie",
    "iso:country":"FR",
    "sg:address":"165 Route De Dieppe 76770 Le Houlme",
    "sg:classifiers":[
        {
            "category":"Professional",
            "subcategory":"Engineering",
            "type":"Services"
        }
    ],
    "sg:phone":"+33 2 35 74 44 13",
    "sg:postcode":"76770",
    "sg:province":"Haute Normandie",
    "sg:tags":[
        "metallurgy",
        "good",
        "-",
        "metal",
        "mac",
        "metallic",
        "machine",
        "metalworking",
        "finished",
        "mechanical"
    ],
    "wof:name":"Ste D'etude Et De Commerce Setco",
    "wof:placetype":"venue"
},
  "geometry": {"coordinates":[1.043493,49.502438],"type":"Point"}
}