{
  "type": "Feature",
  "properties": {
    "addr:full":"584 Route De St Bernard Zi De Fetan 01600 Trevoux Rhone-Alpes 01600",
    "addr:housenumber":"584",
    "addr:postcode":"01600;01600",
    "addr:street":"Route De St;Zi;Fetan;Rhone-Alpes",
    "iso:country":"FR",
    "sg:address":"584 Route De St Bernard Zi De Fetan 01600 Trevoux",
    "sg:classifiers":[
        {
            "category":"Professional",
            "subcategory":"Engineering",
            "type":"Services"
        }
    ],
    "sg:phone":"+33 4 74 00 59 54",
    "sg:postcode":"01600",
    "sg:province":"Rhone-Alpes",
    "sg:tags":[
        "machine",
        "-",
        "mechanical"
    ],
    "wof:name":"Ora",
    "wof:placetype":"venue"
},
  "geometry": {"coordinates":[4.796472,45.94268],"type":"Point"}
}