{
  "type": "Feature",
  "properties": {
    "addr:full":"300, Rue Gustave Eiffel, 54710 Ludres Lorraine",
    "addr:housenumber":"300",
    "addr:postcode":"54710",
    "addr:street":"Rue Gustave Eiffel",
    "iso:country":"FR",
    "sg:address":"300, Rue Gustave Eiffel, 54710 Ludres",
    "sg:orig_category":"Non-Classified Establishments",
    "sg:phone":"+33 3 83 26 51 51",
    "sg:province":"Lorraine",
    "wof:name":"F.m. Logistic S.a. - Faure Et Machet",
    "wof:placetype":"venue"
},
  "geometry": {"coordinates":[6.192683,48.610264],"type":"Point"}
}