{
  "type": "Feature",
  "properties": {
    "addr:full":"Rte De Pacy BP 113 27400 Louviers Cedex Haute Normandie 27400",
    "addr:housenumber":"113",
    "addr:postcode":"27400;27400",
    "addr:street":"Rte De Pacy Bp",
    "iso:country":"FR",
    "sg:address":"Rte De Pacy BP 113 27400 Louviers Cedex",
    "sg:classifiers":[
        {
            "category":"Manufacturing",
            "subcategory":"Metals",
            "type":"Manufacturing & Wholesale Goods"
        }
    ],
    "sg:phone":"+33 2 32 50 23 12",
    "sg:postcode":"27400",
    "sg:province":"Haute Normandie",
    "sg:tags":[
        "metallurgy",
        "metalworking",
        "processing"
    ],
    "wof:name":"Smeh",
    "wof:placetype":"venue"
},
  "geometry": {"coordinates":[1.18579,49.201096],"type":"Point"}
}