{
  "type": "Feature",
  "properties": {
    "iso:country":"FR",
    "sg:address":"4, Bd Gueidon Malpass\u00e9, 13013 Marseille",
    "sg:orig_category":"Non-Classified Establishments",
    "sg:phone":"+33 4 91 66 66 36",
    "sg:province":"Provence-Alpes-C\u00f4te d'Azur",
    "wof:name":"Norelec Transport S.a.",
    "wof:placetype":"venue"
},
  "geometry": {"coordinates":[5.417715,43.322464],"type":"Point"}
}