{
  "type": "Feature",
  "properties": {
    "iso:country":"FR",
    "sg:address":"36 rue Marcel Dassault 59113 Seclin",
    "sg:classifiers":[
        {
            "category":"Real Estate",
            "subcategory":"Architect",
            "type":"Services"
        }
    ],
    "sg:phone":"+33 3 20 16 01 40",
    "sg:postcode":"59113",
    "sg:province":"Nord Pas-de-Calais",
    "sg:tags":[
        "work",
        "developing"
    ],
    "wof:name":"Ste Photographique Nord Labo S.a.",
    "wof:placetype":"venue"
},
  "geometry": {"coordinates":[3.034274,50.567371],"type":"Point"}
}