{
  "type": "Feature",
  "properties": {
    "addr:full":"La Primaube 12450 Luc Midi Pyr\u00e9n\u00e9es",
    "addr:postcode":"12450",
    "iso:country":"FR",
    "sg:address":"La Primaube 12450 Luc",
    "sg:orig_category":"Unclassifiable Establishments",
    "sg:phone":"+33 5 65 71 40 04",
    "sg:province":"Midi Pyr\u00e9n\u00e9es",
    "wof:name":"Transports Beteille S.a.",
    "wof:placetype":"venue"
},
  "geometry": {"coordinates":[2.55903,44.292271],"type":"Point"}
}