{
  "type": "Feature",
  "properties": {
    "iso:country":"FR",
    "sg:address":"37 rue du Saule Trapu 91300 Massy",
    "sg:orig_category":"Universal Cutting Machines",
    "sg:phone":"+33 1 69 53 63 63",
    "sg:province":"Ile de France",
    "wof:name":"Solartron France Sarl",
    "wof:placetype":"venue"
},
  "geometry": {"coordinates":[2.30347,48.730751],"type":"Point"}
}