{
  "type": "Feature",
  "properties": {
    "addr:full":"37 rue du Saule Trapu 91300 Massy Ile de France",
    "addr:housenumber":"37",
    "addr:postcode":"91300",
    "addr:street":"Rue Du Saule Trapu;Ile De France",
    "iso:country":"FR",
    "sg:address":"37 rue du Saule Trapu 91300 Massy",
    "sg:orig_category":"Universal Cutting Machines",
    "sg:phone":"+33 1 69 53 63 63",
    "sg:province":"Ile de France",
    "wof:name":"Solartron France Sarl",
    "wof:placetype":"venue"
},
  "geometry": {"coordinates":[2.30347,48.730751],"type":"Point"}
}