{
  "type": "Feature",
  "properties": {
    "iso:country":"FR",
    "sg:address":"42, Rue Lantiez, 75017 Paris",
    "sg:orig_category":"Non-Classified Establishments",
    "sg:phone":"+33 1 44 85 71 82",
    "sg:postcode":"75017",
    "sg:province":"Ile de France",
    "wof:name":"E - Mhotep S.a.r.l.",
    "wof:placetype":"venue"
},
  "geometry": {"coordinates":[2.324512,48.895626],"type":"Point"}
}