{
  "type": "Feature",
  "properties": {
    "addr:full":"40, Rte de Paris, 03000 Avermes Avermes Auvergne 03000",
    "addr:housenumber":"40",
    "addr:postcode":"03000;avermes;03000",
    "addr:street":"Rte De Paris",
    "iso:country":"FR",
    "sg:address":"40, Rte de Paris, 03000 Avermes",
    "sg:city":"Avermes",
    "sg:orig_category":"Unclassifiable Establishments",
    "sg:phone":"+33 4 70 48 40 00",
    "sg:postcode":"03000",
    "sg:province":"Auvergne",
    "wof:name":"J.p.m. Chauvat S.a.",
    "wof:placetype":"venue"
},
  "geometry": {"coordinates":[3.318716,46.583172],"type":"Point"}
}