{
  "type": "Feature",
  "properties": {
    "addr:full":"Rte De Troyes BP 89 Rn 19 52003 Chaumont Cedex Champagne-Ardenne",
    "addr:housenumber":"bp 89",
    "addr:postcode":"52003",
    "addr:street":"Rte De Troyes;Rn 19",
    "iso:country":"FR",
    "sg:address":"Rte De Troyes BP 89 Rn 19 52003 Chaumont Cedex",
    "sg:classifiers":[
        {
            "category":"Banks & Credit Unions",
            "subcategory":"Investment Brokerage",
            "type":"Services"
        }
    ],
    "sg:phone":"+33 3 25 35 31 10",
    "sg:province":"Champagne-Ardenne",
    "sg:tags":[
        "-",
        "transport",
        "related"
    ],
    "wof:name":"Gondrand Freres (societe Fr De Transport",
    "wof:placetype":"venue"
},
  "geometry": {"coordinates":[5.135536,48.110767],"type":"Point"}
}