{
  "type": "Feature",
  "properties": {
    "iso:country":"FR",
    "sg:address":"6",
    "sg:city":"Henri Chapay; Voreppe; 38340",
    "sg:classifiers":[
        {
            "category":"Banks & Credit Unions",
            "subcategory":"Bank",
            "type":"Services"
        }
    ],
    "sg:phone":"+33 3376502417",
    "sg:postcode":"38340",
    "sg:province":"Rhone-Alpes",
    "wof:name":"Banque Nationale De Paris",
    "wof:placetype":"venue"
},
  "geometry": {"coordinates":[5.635928,45.298191],"type":"Point"}
}