{
  "type": "Feature",
  "properties": {
    "addr:full":"8 Rue Fecht 68630 Bennwihr Mittelwihr Mittelwihr Alsace 68630",
    "addr:housenumber":"8",
    "addr:postcode":"68630;68630",
    "addr:street":"Rue Fecht",
    "iso:country":"FR",
    "sg:address":"8 Rue Fecht 68630 Bennwihr Mittelwihr",
    "sg:city":"Mittelwihr",
    "sg:classifiers":[
        {
            "category":"Professional",
            "subcategory":"Engineering",
            "type":"Services"
        }
    ],
    "sg:phone":"+33 3 89 24 22 22",
    "sg:postcode":"68630",
    "sg:province":"Alsace",
    "sg:tags":[
        "machine",
        "-",
        "mechanical"
    ],
    "wof:name":"Elevage Service Sarl",
    "wof:placetype":"venue"
},
  "geometry": {"coordinates":[7.32417,48.144958],"type":"Point"}
}