{
  "type": "Feature",
  "properties": {
    "addr:full":"7, Rue du moulin, 67110 Gundershoffen Gundershoffen Alsace 67110",
    "addr:housenumber":"7",
    "addr:postcode":"67110;67110",
    "addr:street":"Rue Du Moulin;Gundershoffen",
    "iso:country":"FR",
    "sg:address":"7, Rue du moulin, 67110 Gundershoffen",
    "sg:city":"Gundershoffen",
    "sg:orig_category":"Non-Classified Establishments",
    "sg:phone":"+33 3 21 60 47 47",
    "sg:postcode":"67110",
    "sg:province":"Alsace",
    "wof:name":"Location Wenger S.a.r.l.",
    "wof:placetype":"venue"
},
  "geometry": {"coordinates":[7.659925,48.903484],"type":"Point"}
}