{
  "type": "Feature",
  "properties": {
    "addr:full":"Chemin du Fort Virignin Rhone-Alpes 01300",
    "addr:postcode":"01300",
    "addr:street":"Chemin Du Fort Virignin Rhone-Alpes",
    "iso:country":"FR",
    "sg:address":"Chemin du Fort",
    "sg:city":"Virignin",
    "sg:orig_category":"Non-Classified Establishments",
    "sg:phone":"+33 4 79 81 92 22",
    "sg:postcode":"01300",
    "sg:province":"Rhone-Alpes",
    "wof:name":"Entreprise Studer Auguste",
    "wof:placetype":"venue"
},
  "geometry": {"coordinates":[5.718024,45.71257],"type":"Point"}
}