{
  "type": "Feature",
  "properties": {
    "addr:full":"Room 38 ave; Hy\u00e8res; 84301 Midi Pyr\u00e9n\u00e9es",
    "addr:postcode":"84301",
    "addr:street":"38 Ave",
    "iso:country":"FR",
    "sg:address":"Room 38",
    "sg:city":"ave; Hy\u00e8res; 84301",
    "sg:classifiers":[
        {
            "category":"Banks & Credit Unions",
            "subcategory":"Bank",
            "type":"Services"
        }
    ],
    "sg:phone":"+33 4 94 65 02 33",
    "sg:province":"Midi Pyr\u00e9n\u00e9es",
    "wof:name":"Banque De France",
    "wof:placetype":"venue"
},
  "geometry": {"coordinates":[-112.125603,41.614452],"type":"Point"}
}