{
  "type": "Feature",
  "properties": {
    "iso:country":"FR",
    "sg:address":"42 Avenue Henri Barbusse 92700 Colombes",
    "sg:classifiers":[
        {
            "category":"Utilities",
            "subcategory":"Electric",
            "type":"Services"
        }
    ],
    "sg:phone":"+33 810 42 01 40",
    "sg:postcode":"92700",
    "sg:province":"Ile de France",
    "sg:tags":[
        "electricity",
        "raw",
        "energy",
        "material"
    ],
    "wof:name":"Electricite De France (edf)",
    "wof:placetype":"venue"
},
  "geometry": {"coordinates":[2.252531,48.920055],"type":"Point"}
}