{
  "type": "Feature",
  "properties": {
    "iso:country":"FR",
    "sg:address":"2, Rue Jean Elys\u00e9e Dupuy - ZI du Tronchon, 69410 Champagne au Mont d'Or",
    "sg:orig_category":"Unclassifiable Establishments",
    "sg:phone":"+33 4 78 43 22 30",
    "sg:postcode":"69410",
    "sg:province":"Rhone-Alpes",
    "wof:name":"Forestyle Saint Ys S.a.",
    "wof:placetype":"venue"
},
  "geometry": {"coordinates":[5.717823,47.020477],"type":"Point"}
}