{
  "type": "Feature",
  "properties": {
    "addr:full":"B.P. 7, 80800 Villers Bretonneux^^Place du 14 Juillet, 80800 Villers Bretonneux Picardie",
    "addr:housenumber":"7",
    "addr:postcode":"80800;80800",
    "addr:street":"B.P.;Du 14 Juillet",
    "iso:country":"FR",
    "sg:address":"B.P. 7, 80800 Villers Bretonneux^^Place du 14 Juillet, 80800 Villers Bretonneux",
    "sg:orig_category":"Non-Classified Establishments",
    "sg:phone":"+33 3 22 48 00 33",
    "sg:province":"Picardie",
    "wof:name":"Top S.a.",
    "wof:placetype":"venue"
},
  "geometry": {"coordinates":[2.51246,49.909565],"type":"Point"}
}