{
  "type": "Feature",
  "properties": {
    "addr:full":"33 rue des Chardonnerets 95990 ROISSY EN FRANCE Aquitaine",
    "addr:housenumber":"33",
    "addr:postcode":"95990",
    "addr:street":"Rue Des Chardonnerets",
    "iso:country":"FR",
    "sg:address":"33 rue des Chardonnerets 95990 ROISSY EN FRANCE",
    "sg:classifiers":[
        {
            "category":"Autos & Motor Vehicles",
            "subcategory":"Auto Supplies",
            "type":"Retail Goods"
        }
    ],
    "sg:phone":"+33 1 49 89 31 70",
    "sg:province":"Aquitaine",
    "sg:tags":[
        "automobile",
        "accessory"
    ],
    "wof:name":"Morse Controls Sa",
    "wof:placetype":"venue"
},
  "geometry": {"coordinates":[2.51524,49.004028],"type":"Point"}
}