{
  "type": "Feature",
  "properties": {
    "addr:full":"za Blaise Pascal BP 60307 cedex 60026 Beauvais Picardie",
    "addr:postcode":"cedex 60026",
    "addr:street":"Za Blaise Pascal Bp 60307",
    "iso:country":"FR",
    "sg:address":"za",
    "sg:city":"Blaise Pascal BP 60307 cedex 60026 Beauvais",
    "sg:classifiers":[
        {
            "category":"Wholesale",
            "subcategory":"Farm Supplies",
            "type":"Manufacturing & Wholesale Goods"
        }
    ],
    "sg:phone":"+33 3 44 11 33 33",
    "sg:province":"Picardie",
    "sg:tags":[
        "-",
        "machine",
        "equipment",
        "engineering",
        "machinery",
        "mechanical",
        "agriculture"
    ],
    "wof:name":"Agco",
    "wof:placetype":"venue"
},
  "geometry": {"coordinates":[2.08652,49.43544],"type":"Point"}
}