{
  "type": "Feature",
  "properties": {
    "addr:full":"10 Rue Des Pyramides 75001 Paris Ile de France",
    "addr:housenumber":"10",
    "addr:postcode":"75001",
    "addr:street":"Rue Des Pyramides",
    "iso:country":"FR",
    "sg:address":"10 Rue Des Pyramides 75001 Paris",
    "sg:classifiers":[
        {
            "category":"Professional",
            "subcategory":"Printing & Photocopies",
            "type":"Services"
        }
    ],
    "sg:phone":"+33 1 40 40 13 40",
    "sg:province":"Ile de France",
    "sg:tags":[
        "publishing"
    ],
    "wof:name":"Economie Et Politique",
    "wof:placetype":"venue"
},
  "geometry": {"coordinates":[2.332987,48.864628],"type":"Point"}
}