{
  "type": "Feature",
  "properties": {
    "iso:country":"FR",
    "sg:address":"2 rue Andr\u00e9 Citro\u00ebn 95130 FRANCONVILLE LA GARENNE",
    "sg:classifiers":[
        {
            "category":"Landmark",
            "subcategory":"Fountain",
            "type":"Public Place"
        }
    ],
    "sg:phone":"+33 1 30 72 84 30",
    "sg:postcode":"95130",
    "sg:province":"Ile de France",
    "sg:tags":[
        "pen"
    ],
    "wof:name":"Cie Technologie De Luxe",
    "wof:placetype":"venue"
},
  "geometry": {"coordinates":[2.235405,49.001438],"type":"Point"}
}