{
  "type": "Feature",
  "properties": {
    "iso:country":"FR",
    "sg:address":"13, Bd Creach'Gwen, 29000 Quimper",
    "sg:city":"Quimper",
    "sg:orig_category":"Unclassifiable Establishments",
    "sg:phone":"+33 2 98 10 29 29",
    "sg:postcode":"29000",
    "sg:province":"Bretagne",
    "wof:name":"Somaintel Informatique S.a.s.",
    "wof:placetype":"venue"
},
  "geometry": {"coordinates":[-4.0977,47.998119],"type":"Point"}
}