{
  "type": "Feature",
  "properties": {
    "iso:country":"FR",
    "sg:address":"Bourg 58300 Verneuil",
    "sg:city":"Verneuil",
    "sg:classifiers":[
        {
            "category":"Wholesale",
            "subcategory":"Machinery & Supplies",
            "type":"Manufacturing & Wholesale Goods"
        }
    ],
    "sg:phone":"+33 3 86 50 54 00",
    "sg:postcode":"58300",
    "sg:province":"Bourgogne",
    "sg:tags":[
        "-",
        "machine",
        "equipment",
        "engineering",
        "animal",
        "mechanical",
        "breeding",
        "agriculture"
    ],
    "wof:name":"Bos Sarl",
    "wof:placetype":"venue"
},
  "geometry": {"coordinates":[3.557345,46.861324],"type":"Point"}
}