{
  "type": "Feature",
  "properties": {
    "addr:full":"89 boulevard de S\u00e9bastopol 75002 Paris Ile de France 75002",
    "addr:housenumber":"89",
    "addr:postcode":"75002;75002",
    "addr:street":"Boulevard De Se\u0301Bastopol",
    "iso:country":"FR",
    "sg:address":"89 boulevard de S\u00e9bastopol 75002 Paris",
    "sg:classifiers":[
        {
            "category":"Professional",
            "subcategory":"Business Services",
            "type":"Services"
        }
    ],
    "sg:phone":"+33 1 42 33 90 60",
    "sg:postcode":"75002",
    "sg:province":"Ile de France",
    "sg:tags":[
        "observation",
        "market"
    ],
    "wof:name":"Iddem S.a.r.l.",
    "wof:placetype":"venue"
},
  "geometry": {"coordinates":[2.351732,48.86515],"type":"Point"}
}