{
  "type": "Feature",
  "properties": {
    "iso:country":"FR",
    "sg:address":"6, Place Charles de Gaulle, 28290 Courtalain",
    "sg:city":"Courtalain",
    "sg:orig_category":"Non-Classified Establishments",
    "sg:phone":"+33 2 37 98 80 80",
    "sg:postcode":"28290",
    "sg:province":"Centre",
    "wof:name":"M.s. - 2.a. S.a.r.l. - Mobile Service All\u00e8gement Archives",
    "wof:placetype":"venue"
},
  "geometry": {"coordinates":[1.136234,48.078987],"type":"Point"}
}