{
  "type": "Feature",
  "properties": {
    "iso:country":"FR",
    "sg:address":"Zi D'Uvernet Fours 04400 Uvernet Fours",
    "sg:classifiers":[
        {
            "category":"Building & Trades",
            "subcategory":"Construction",
            "type":"Services"
        }
    ],
    "sg:phone":"+33 4 92 81 02 44",
    "sg:province":"Rhone-Alpes",
    "sg:tags":[
        "work",
        "public"
    ],
    "wof:name":"Entreprise Pierre Rossetto",
    "wof:placetype":"venue"
},
  "geometry": {"coordinates":[6.62523,44.36063],"type":"Point"}
}