{
  "type": "Feature",
  "properties": {
    "iso:country":"FR",
    "sg:address":"Za Ambroise 2 40390 St Martin De Seignanx",
    "sg:city":"Biarrotte",
    "sg:classifiers":[
        {
            "category":"Shopping",
            "type":"Retail Goods"
        }
    ],
    "sg:phone":"+33 5 59 56 51 15",
    "sg:postcode":"40390",
    "sg:province":"Aquitaine",
    "sg:tags":[
        "metallurgy",
        "finished",
        "-",
        "metalworking",
        "metallic"
    ],
    "wof:name":"Galvasteel Sa",
    "wof:placetype":"venue"
},
  "geometry": {"coordinates":[-1.416594,43.529083],"type":"Point"}
}