{
  "type": "Feature",
  "properties": {
    "iso:country":"FR",
    "sg:address":"11 R 35\u00e8me R\u00e9giment D'Aviation 69500 Bron",
    "sg:classifiers":[
        {
            "category":"Professional",
            "subcategory":"Printing & Photocopies",
            "type":"Services"
        }
    ],
    "sg:phone":"+33 4 72 14 28 50",
    "sg:province":"Rhone-Alpes",
    "sg:tags":[
        "publishing"
    ],
    "wof:name":"Imprimerie Sezanne",
    "wof:placetype":"venue"
},
  "geometry": {"coordinates":[4.930126,45.743935],"type":"Point"}
}