{
  "type": "Feature",
  "properties": {
    "addr:full":"Route De Saumur 49490 Noyant Pays de Loire 49490",
    "addr:postcode":"49490;49490",
    "addr:street":"Route De Saumur",
    "iso:country":"FR",
    "sg:address":"Route De Saumur 49490 Noyant",
    "sg:classifiers":[
        {
            "category":"Professional",
            "subcategory":"Engineering",
            "type":"Services"
        }
    ],
    "sg:phone":"+33 2 41 89 52 74",
    "sg:postcode":"49490",
    "sg:province":"Pays de Loire",
    "sg:tags":[
        "machine",
        "-",
        "mechanical"
    ],
    "wof:name":"Societe A B M Sarl",
    "wof:placetype":"venue"
},
  "geometry": {"coordinates":[0.114045,47.50835],"type":"Point"}
}