{
  "type": "Feature",
  "properties": {
    "addr:full":"Le Clot 38114 Allemond Rhone-Alpes 38114",
    "addr:postcode":"38114;38114",
    "addr:street":"Le Clot;Rhone-Alpes",
    "iso:country":"FR",
    "sg:address":"Le Clot 38114 Allemond",
    "sg:classifiers":[
        {
            "category":"Shopping",
            "subcategory":"Hobbies, Toys, & Games",
            "type":"Retail Goods"
        }
    ],
    "sg:phone":"+33 4 76 79 80 47",
    "sg:postcode":"38114",
    "sg:province":"Rhone-Alpes",
    "sg:tags":[
        "product",
        "miscellaneous",
        "entertainment"
    ],
    "wof:name":"Germain Bernard",
    "wof:placetype":"venue"
},
  "geometry": {"coordinates":[6.025946,45.130569],"type":"Point"}
}