{
  "type": "Feature",
  "properties": {
    "iso:country":"FR",
    "sg:address":"2 Rue Des 3 Tours 10200 Bar Sur Aube",
    "sg:classifiers":[
        {
            "category":"Home & Garden",
            "subcategory":"Building Materials",
            "type":"Retail Goods"
        }
    ],
    "sg:phone":"+33 3 25 27 10 71",
    "sg:postcode":"10200",
    "sg:province":"Champagne",
    "sg:tags":[
        "equipment",
        "energy",
        "-",
        "environment",
        "raw",
        "machinery"
    ],
    "wof:name":"Saur",
    "wof:placetype":"venue"
},
  "geometry": {"coordinates":[4.709934,48.23011],"type":"Point"}
}