{
  "type": "Feature",
  "properties": {
    "iso:country":"FR",
    "sg:address":"11, Av Schwabmunchen, 90200 Giromagny",
    "sg:orig_category":"Non-Classified Establishments",
    "sg:phone":"+33 3 84 29 32 46",
    "sg:postcode":"90200",
    "sg:province":"Franche Comt\u00e9",
    "wof:name":"Bixel Brasserie De Saint Louis S.a.r.l.",
    "wof:placetype":"venue"
},
  "geometry": {"coordinates":[6.830435,47.738152],"type":"Point"}
}