{
  "type": "Feature",
  "properties": {
    "iso:country":"FR",
    "sg:address":"RN 106 - Sainte Genevi\u00e8ve Malgoire",
    "sg:city":"Moussac",
    "sg:orig_category":"Unclassifiable Establishments",
    "sg:phone":"+33 4 66 83 30 52",
    "sg:postcode":"30190",
    "sg:province":"Languedoc-Roussillon",
    "wof:name":"Spring Water S.a.",
    "wof:placetype":"venue"
},
  "geometry": {"coordinates":[4.321909,43.935459],"type":"Point"}
}