{
  "type": "Feature",
  "properties": {
    "addr:full":"6 Rue Drogon 57970 Yutz Picardie",
    "addr:housenumber":"6",
    "addr:postcode":"57970",
    "addr:street":"Rue Drogon",
    "iso:country":"FR",
    "sg:address":"6 Rue Drogon 57970 Yutz",
    "sg:classifiers":[
        {
            "category":"Food Court",
            "type":"Food & Drink"
        }
    ],
    "sg:phone":"+33 3 82 56 09 24",
    "sg:province":"Picardie",
    "sg:tags":[
        "product",
        "related"
    ],
    "wof:name":"Les Vignobles Fran\u00c7ais Sarl",
    "wof:placetype":"venue"
},
  "geometry": {"coordinates":[6.191594,49.35701],"type":"Point"}
}