{
  "type": "Feature",
  "properties": {
    "addr:full":"4, Place Carnot, 58001 Nevers C\u00e9dex Picardie",
    "addr:housenumber":"4",
    "addr:postcode":"58001",
    "addr:street":"Place Carnot",
    "iso:country":"FR",
    "sg:address":"4, Place Carnot, 58001 Nevers C\u00e9dex",
    "sg:orig_category":"Non-Classified Establishments",
    "sg:phone":"+33 810 42 93 98",
    "sg:province":"Picardie",
    "wof:name":"Caisse D'epargne De Bourgogne S.a.",
    "wof:placetype":"venue"
},
  "geometry": {"coordinates":[3.157342,46.989269],"type":"Point"}
}