{
  "type": "Feature",
  "properties": {
    "iso:country":"FR",
    "sg:address":"108, Bd Haussmann, 75008 Paris",
    "sg:orig_category":"Unclassifiable Establishments",
    "sg:phone":"+33 1 44 70 80 80",
    "sg:province":"Ile de France",
    "wof:name":"Groupe Dresdner K.b. France",
    "wof:placetype":"venue"
},
  "geometry": {"coordinates":[2.321289,48.874702],"type":"Point"}
}