{
  "type": "Feature",
  "properties": {
    "addr:full":"27 Rue De L'Arquebuse 21000 Dijon Dijon Bourgogne 21000",
    "addr:housenumber":"27",
    "addr:postcode":"21000;21000",
    "addr:street":"Rue De L'Arquebuse",
    "iso:country":"FR",
    "sg:address":"27 Rue De L'Arquebuse 21000 Dijon",
    "sg:city":"Dijon",
    "sg:classifiers":[
        {
            "category":"Travel",
            "subcategory":"Hotels & Motels",
            "type":"Entertainment"
        }
    ],
    "sg:phone":"+33 3 80 76 94 94",
    "sg:postcode":"21000",
    "sg:province":"Bourgogne",
    "sg:tags":[
        "hotels",
        "business",
        "restaurant"
    ],
    "wof:name":"Us Food Pizza Hut",
    "wof:placetype":"venue"
},
  "geometry": {"coordinates":[5.029389,47.321522],"type":"Point"}
}