{
  "type": "Feature",
  "properties": {
    "addr:full":"B.P. 20, 13127 Vitrolles^^12, Rue de Berlin - ZI les Estroublancs, 13127 Vitrolles Provence-Alpes-C\u00f4te d'Azur",
    "addr:postcode":"13127;13127",
    "addr:street":"B.P. 20;Rue De Berlin Zi Les Estroublancs",
    "iso:country":"FR",
    "sg:address":"B.P. 20, 13127 Vitrolles^^12, Rue de Berlin - ZI les Estroublancs, 13127 Vitrolles",
    "sg:orig_category":"Non-Classified Establishments",
    "sg:phone":"+33 4 42 46 28 00",
    "sg:province":"Provence-Alpes-C\u00f4te d'Azur",
    "wof:name":"Transports Joyau",
    "wof:placetype":"venue"
},
  "geometry": {"coordinates":[5.232955,43.457664],"type":"Point"}
}