{
  "type": "Feature",
  "properties": {
    "addr:full":"15 Quai Gallieni 92150 Suresnes Ile de France 92150",
    "addr:housenumber":"15",
    "addr:postcode":"92150;ile;92150",
    "addr:street":"Quai Gallieni;France",
    "iso:country":"FR",
    "sg:address":"15 Quai Gallieni 92150 Suresnes",
    "sg:classifiers":[
        {
            "category":"Professional",
            "subcategory":"Advertising",
            "type":"Services"
        }
    ],
    "sg:phone":"+33 1 41 44 94 40",
    "sg:postcode":"92150",
    "sg:province":"Ile de France",
    "sg:tags":[
        "communication",
        "medium"
    ],
    "wof:name":"Benchmark Group",
    "wof:placetype":"venue"
},
  "geometry": {"coordinates":[2.22893,48.86784],"type":"Point"}
}