{
  "type": "Feature",
  "properties": {
    "addr:full":"79, Rue Fran\u00e7ois Mermet, 69160 Tassin la Demi Lune Rhone-Alpes",
    "addr:housenumber":"79",
    "addr:postcode":"69160",
    "addr:street":"Rue Franc\u0327Ois Mermet",
    "iso:country":"FR",
    "sg:address":"79, Rue Fran\u00e7ois Mermet, 69160 Tassin la Demi Lune",
    "sg:orig_category":"Unclassifiable Establishments",
    "sg:phone":"+33 4 78 34 19 54",
    "sg:province":"Rhone-Alpes",
    "wof:name":"Altendorf France S.a.r.l.",
    "wof:placetype":"venue"
},
  "geometry": {"coordinates":[4.76305,45.7584],"type":"Point"}
}