{
  "type": "Feature",
  "properties": {
    "iso:country":"FR",
    "sg:address":"79, Rue Fran\u00e7ois Mermet, 69160 Tassin la Demi Lune",
    "sg:orig_category":"Unclassifiable Establishments",
    "sg:phone":"+33 4 78 34 19 54",
    "sg:province":"Rhone-Alpes",
    "wof:name":"Altendorf France S.a.r.l.",
    "wof:placetype":"venue"
},
  "geometry": {"coordinates":[4.76305,45.7584],"type":"Point"}
}