{
  "type": "Feature",
  "properties": {
    "iso:country":"FR",
    "sg:address":"28, Rue du 35\u00e8me R\u00e9giment d'Aviation - ZAC du Ch\u00eane, 69500 Bron",
    "sg:orig_category":"Non-Classified Establishments",
    "sg:phone":"+33 4 72 14 62 22",
    "sg:postcode":"69500",
    "sg:province":"Rhone-Alpes",
    "wof:name":"A.r.s.a. S.a. - Atelier Reliures Spirales Artistiques",
    "wof:placetype":"venue"
},
  "geometry": {"coordinates":[4.91167,45.735451],"type":"Point"}
}