{
  "type": "Feature",
  "properties": {
    "iso:country":"FR",
    "sg:address":"110, Rue Foch, 57200 Sarreguemines",
    "sg:orig_category":"Unclassifiable Establishments",
    "sg:phone":"+33 3 87 95 19 25",
    "sg:province":"Lorraine",
    "wof:name":"Soci\u00e9t\u00e9 D'exploitation Des Etablissements Ulrich Antoine S.a.r.l.",
    "wof:placetype":"venue"
},
  "geometry": {"coordinates":[7.083406,49.117615],"type":"Point"}
}