{
  "type": "Feature",
  "properties": {
    "addr:full":"33, Rue des Ecoles, 25400 Exincourt Franche Comt\u00e9",
    "addr:housenumber":"33",
    "addr:postcode":"25400",
    "addr:street":"Rue Des Ecoles;Franche Comte\u0301",
    "iso:country":"FR",
    "sg:address":"33, Rue des Ecoles, 25400 Exincourt",
    "sg:orig_category":"Unclassifiable Establishments",
    "sg:phone":"+33 3 81 94 19 66",
    "sg:province":"Franche Comt\u00e9",
    "wof:name":"S.o.s. Froid Comtois S.a.",
    "wof:placetype":"venue"
},
  "geometry": {"coordinates":[6.832041,47.496777],"type":"Point"}
}