{
  "type": "Feature",
  "properties": {
    "iso:country":"FR",
    "sg:address":"34, Bd Milet, 02600 Villers Cotter\u00eats",
    "sg:orig_category":"Unclassifiable Establishments",
    "sg:phone":"+33 3 23 96 50 64",
    "sg:province":"Picardie",
    "wof:name":"Lefort F. Voyages S.a.",
    "wof:placetype":"venue"
},
  "geometry": {"coordinates":[3.0916,49.250263],"type":"Point"}
}