{
  "type": "Feature",
  "properties": {
    "iso:country":"FR",
    "sg:address":"B.P. 37, 49110 Saint Pierre Montlimart C\u00e9dex^^Rte Chaudron, 49110 Saint Pierre Montlimart",
    "sg:orig_category":"Non-Classified Establishments",
    "sg:phone":"+33 2 41 75 31 31",
    "sg:province":"Pays de Loire",
    "wof:name":"T.b.s. Industrie S.a.r.l.",
    "wof:placetype":"venue"
},
  "geometry": {"coordinates":[-1.02561,47.270817],"type":"Point"}
}