{
  "type": "Feature",
  "properties": {
    "addr:full":"B.P. 37, 49110 Saint Pierre Montlimart C\u00e9dex^^Rte Chaudron, 49110 Saint Pierre Montlimart Pays de Loire",
    "addr:postcode":"49110;49110",
    "addr:street":"B.P. 37;Ce\u0301Dex^^Rte Chaudron;Montlimart",
    "iso:country":"FR",
    "sg:address":"B.P. 37, 49110 Saint Pierre Montlimart C\u00e9dex^^Rte Chaudron, 49110 Saint Pierre Montlimart",
    "sg:orig_category":"Non-Classified Establishments",
    "sg:phone":"+33 2 41 75 31 31",
    "sg:province":"Pays de Loire",
    "wof:name":"T.b.s. Industrie S.a.r.l.",
    "wof:placetype":"venue"
},
  "geometry": {"coordinates":[-1.02561,47.270817],"type":"Point"}
}