{
  "type": "Feature",
  "properties": {
    "iso:country":"FR",
    "sg:address":"Rte d'Ambri\u00e8res",
    "sg:city":"Lassay les Ch\u00e2teaux",
    "sg:orig_category":"Unclassifiable Establishments",
    "sg:phone":"+33 2 43 04 73 42",
    "sg:postcode":"53110",
    "sg:province":"Pays de Loire",
    "wof:name":"Scierie De Lassay S.a.r.l.",
    "wof:placetype":"venue"
},
  "geometry": {"coordinates":[-0.421576,48.464886],"type":"Point"}
}