{
  "type": "Feature",
  "properties": {
    "iso:country":"FR",
    "sg:address":"1, All\u00e9e des Acacias, 07800 Charmes sur Rh\u00f4ne",
    "sg:orig_category":"Non-Classified Establishments",
    "sg:phone":"+33 4 75 60 98 16",
    "sg:postcode":"07800",
    "sg:province":"Rhone-Alpes",
    "wof:name":"Compo S.a.r.l.",
    "wof:placetype":"venue"
},
  "geometry": {"coordinates":[4.835345,44.862461],"type":"Point"}
}