{
  "type": "Feature",
  "properties": {
    "addr:full":"Rue Moulin S\u00e9n\u00e9court Bailleval Picardie 60140",
    "addr:postcode":"60140",
    "addr:street":"Rue Moulin Se\u0301Ne\u0301Court;Picardie",
    "iso:country":"FR",
    "sg:address":"Rue Moulin S\u00e9n\u00e9court",
    "sg:city":"Bailleval",
    "sg:orig_category":"Unclassifiable Establishments",
    "sg:phone":"+33 3 44 69 12 31",
    "sg:postcode":"60140",
    "sg:province":"Picardie",
    "wof:name":"Eckart - Poudmet S.a.",
    "wof:placetype":"venue"
},
  "geometry": {"coordinates":[2.46377,49.329456],"type":"Point"}
}