{
  "type": "Feature",
  "properties": {
    "iso:country":"FR",
    "sg:address":"B.P. 19",
    "sg:city":"Roman\u00e8che Thorins",
    "sg:orig_category":"Non-Classified Establishments",
    "sg:phone":"+33 3 85 35 22 67",
    "sg:postcode":"71570",
    "sg:province":"Bourgogne",
    "wof:name":"Vins Bertrand Pommier S.a.",
    "wof:placetype":"venue"
},
  "geometry": {"coordinates":[4.734236,46.189201],"type":"Point"}
}