{
  "type": "Feature",
  "properties": {
    "iso:country":"FR",
    "sg:address":"11, Bd des Recollets, 31078 Toulouse C\u00e9dex 4",
    "sg:orig_category":"Non-Classified Establishments",
    "sg:phone":"+33 5 62 26 62 42",
    "sg:province":"Centre",
    "wof:name":"A Propos S.a.r.l.",
    "wof:placetype":"venue"
},
  "geometry": {"coordinates":[1.443504,43.583809],"type":"Point"}
}