{
  "type": "Feature",
  "properties": {
    "addr:full":"225 Route Itsasuko Errebidea 64250 Espelette Espelette Aquitaine 64250",
    "addr:housenumber":"225",
    "addr:postcode":"64250;64250",
    "addr:street":"Route Itsasuko Errebidea",
    "iso:country":"FR",
    "sg:address":"225 Route Itsasuko Errebidea 64250 Espelette",
    "sg:city":"Espelette",
    "sg:classifiers":[
        {
            "category":"Real Estate",
            "subcategory":"Surveying",
            "type":"Services"
        }
    ],
    "sg:phone":"+33 5 59 93 90 88",
    "sg:postcode":"64250",
    "sg:province":"Aquitaine",
    "sg:tags":[
        "leather",
        "raw",
        "material",
        "-",
        "shoe"
    ],
    "wof:name":"Tannerie Remy Carriat Sa",
    "wof:placetype":"venue"
},
  "geometry": {"coordinates":[-1.449194,43.328335],"type":"Point"}
}