{
  "type": "Feature",
  "properties": {
    "addr:full":"29 avenue des Sources 69009 Lyon Rhone-Alpes 69009",
    "addr:housenumber":"29",
    "addr:postcode":"69009;69009",
    "addr:street":"Avenue Des Sources",
    "iso:country":"FR",
    "sg:address":"29 avenue des Sources 69009 Lyon",
    "sg:classifiers":[
        {
            "category":"Professional",
            "subcategory":"Management & Consulting",
            "type":"Services"
        }
    ],
    "sg:phone":"+33 4 72 52 94 20",
    "sg:postcode":"69009",
    "sg:province":"Rhone-Alpes",
    "sg:tags":[
        "software"
    ],
    "wof:name":"Diese Informatique Sa",
    "wof:placetype":"venue"
},
  "geometry": {"coordinates":[4.78523,45.788147],"type":"Point"}
}