{
  "type": "Feature",
  "properties": {
    "iso:country":"FR",
    "sg:address":"Rue De Chantemerle BP 64 49427 Saumur Cedex",
    "sg:classifiers":[
        {
            "category":"Farming",
            "subcategory":"Fish & Marine Products",
            "type":"Manufacturing & Wholesale Goods"
        }
    ],
    "sg:phone":"+33 2 41 40 44 44",
    "sg:province":"Franche Comt\u00e9",
    "sg:tags":[
        "preserve",
        "livestock",
        "food",
        "related",
        "frozen",
        "fruit",
        "vegetable",
        "agriculture"
    ],
    "wof:name":"Uca France Champignon",
    "wof:placetype":"venue"
},
  "geometry": {"coordinates":[-0.098571,47.234425],"type":"Point"}
}