{
  "type": "Feature",
  "properties": {
    "iso:country":"FR",
    "sg:address":"1, Av. du G\u00e9n\u00e9ral de Gaulle, 68390 Sausheim",
    "sg:city":"Sausheim",
    "sg:orig_category":"Unclassifiable Establishments",
    "sg:phone":"+33 3 89 31 04 70",
    "sg:postcode":"68390",
    "sg:province":"Alsace",
    "wof:name":"Schenker B.t.l. S.a.",
    "wof:placetype":"venue"
},
  "geometry": {"coordinates":[7.379007,47.77739],"type":"Point"}
}