{
  "type": "Feature",
  "properties": {
    "addr:full":"B.P. 7, 28170 Ch\u00e2teauneuf en Thymerais^^8, Rue Lemoult, 28170 Ch\u00e2teauneuf en Thymerais Ardelles Centre 28170",
    "addr:housenumber":"7;ardelles",
    "addr:postcode":"28170;28170;28170",
    "addr:street":"B.P.;Rue Lemoult",
    "iso:country":"FR",
    "sg:address":"B.P. 7, 28170 Ch\u00e2teauneuf en Thymerais^^8, Rue Lemoult, 28170 Ch\u00e2teauneuf en Thymerais",
    "sg:city":"Ardelles",
    "sg:orig_category":"Non-Classified Establishments",
    "sg:phone":"+33 2 37 51 69 75",
    "sg:postcode":"28170",
    "sg:province":"Centre",
    "wof:name":"Musci S.a.",
    "wof:placetype":"venue"
},
  "geometry": {"coordinates":[1.227045,48.52977],"type":"Point"}
}