{
  "type": "Feature",
  "properties": {
    "addr:full":"15 Avenue Paul Doumer Vandoeuvre Les Nancy Lorraine 54500",
    "addr:housenumber":"15",
    "addr:postcode":"54500",
    "addr:street":"Avenue Paul Doumer",
    "iso:country":"FR",
    "sg:address":"15 Avenue Paul Doumer",
    "sg:city":"Vandoeuvre Les Nancy",
    "sg:classifiers":[
        {
            "category":"Banks & Credit Unions",
            "subcategory":"Financial Services",
            "type":"Services"
        }
    ],
    "sg:phone":"+33 3 83 50 35 00",
    "sg:postcode":"54500",
    "sg:province":"Lorraine",
    "sg:tags":[
        "banking",
        "finance",
        "insurance"
    ],
    "wof:name":"Mutualite Sociale Agricole De Lorraine",
    "wof:placetype":"venue"
},
  "geometry": {"coordinates":[6.185942,48.674522],"type":"Point"}
}