{
  "type": "Feature",
  "properties": {
    "addr:full":"125, Rue des Charmettes, 69006 Lyon Rhone-Alpes",
    "addr:housenumber":"125",
    "addr:postcode":"69006",
    "addr:street":"Rue Des Charmettes",
    "iso:country":"FR",
    "sg:address":"125, Rue des Charmettes, 69006 Lyon",
    "sg:orig_category":"Unclassifiable Establishments",
    "sg:phone":"+33 4 37 24 19 28",
    "sg:province":"Rhone-Alpes",
    "wof:name":"Etablissement J. Chevrin",
    "wof:placetype":"venue"
},
  "geometry": {"coordinates":[4.867182,45.764671],"type":"Point"}
}