{
  "type": "Feature",
  "properties": {
    "iso:country":"FR",
    "sg:address":"Rue de Lompret - Village en Flandres",
    "sg:city":"Lambersart",
    "sg:orig_category":"Unclassifiable Establishments",
    "sg:phone":"+33 3 20 08 30 79",
    "sg:postcode":"59130",
    "sg:province":"Nord Pas-de-Calais",
    "wof:name":"Hemera S.a.r.l.",
    "wof:placetype":"venue"
},
  "geometry": {"coordinates":[3.02277,50.647751],"type":"Point"}
}