{
  "type": "Feature",
  "properties": {
    "addr:full":"Rue de Lompret - Village en Flandres Lambersart Nord Pas-de-Calais 59130",
    "addr:postcode":"59130",
    "addr:street":"Rue De Lompret Village En Flandres Lambersart Nord",
    "iso:country":"FR",
    "sg:address":"Rue de Lompret - Village en Flandres",
    "sg:city":"Lambersart",
    "sg:orig_category":"Unclassifiable Establishments",
    "sg:phone":"+33 3 20 08 30 79",
    "sg:postcode":"59130",
    "sg:province":"Nord Pas-de-Calais",
    "wof:name":"Hemera S.a.r.l.",
    "wof:placetype":"venue"
},
  "geometry": {"coordinates":[3.02277,50.647751],"type":"Point"}
}