{
  "type": "Feature",
  "properties": {
    "addr:full":"41, Rue Jules Guesde, 69230 Saint Genis Laval Rhone-Alpes",
    "addr:housenumber":"41",
    "addr:postcode":"69230",
    "addr:street":"Rue Jules Guesde;Genis;Rhone-Alpes",
    "iso:country":"FR",
    "sg:address":"41, Rue Jules Guesde, 69230 Saint Genis Laval",
    "sg:orig_category":"Unclassifiable Establishments",
    "sg:phone":"+33 4 72 39 03 17",
    "sg:province":"Rhone-Alpes",
    "wof:name":"Scebis S.a.",
    "wof:placetype":"venue"
},
  "geometry": {"coordinates":[4.813092,45.697151],"type":"Point"}
}