{
  "type": "Feature",
  "properties": {
    "addr:full":"460, Av. de la Quiera, 06370 Mouans Sartoux Midi Pyr\u00e9n\u00e9es",
    "addr:housenumber":"460",
    "addr:postcode":"06370",
    "addr:street":"Av. De La Quiera",
    "iso:country":"FR",
    "sg:address":"460, Av. de la Quiera, 06370 Mouans Sartoux",
    "sg:orig_category":"Non-Classified Establishments",
    "sg:phone":"+33 4 92 92 41 51",
    "sg:province":"Midi Pyr\u00e9n\u00e9es",
    "wof:name":"Brake France Service S.a.s.",
    "wof:placetype":"venue"
},
  "geometry": {"coordinates":[6.956253,43.606804],"type":"Point"}
}