{
  "type": "Feature",
  "properties": {
    "addr:full":"327, Rue du Banc Vert, 59640 Dunkerque Nord-Pas-de-Calais",
    "addr:housenumber":"327",
    "addr:postcode":"59640",
    "addr:street":"Rue Du Banc Vert",
    "iso:country":"FR",
    "sg:address":"327, Rue du Banc Vert, 59640 Dunkerque",
    "sg:orig_category":"Non-Classified Establishments",
    "sg:phone":"+33 3 28 24 21 50",
    "sg:province":"Nord-Pas-de-Calais",
    "wof:name":"Soci\u00e9t\u00e9 D'exploitation Debuyser S.a.r.l.",
    "wof:placetype":"venue"
},
  "geometry": {"coordinates":[2.35936,51.020432],"type":"Point"}
}