{
  "type": "Feature",
  "properties": {
    "iso:country":"FR",
    "sg:address":"La Grangette 24550 BESSE",
    "sg:city":"Besse",
    "sg:orig_category":"Safety Equipment For Forestry Operations",
    "sg:phone":"+33 5 53 29 92 03",
    "sg:postcode":"24550",
    "sg:province":"Aquitaine",
    "wof:name":"Jean Peuch Et Fils Sa",
    "wof:placetype":"venue"
},
  "geometry": {"coordinates":[1.108987,44.670162],"type":"Point"}
}