{
  "type": "Feature",
  "properties": {
    "iso:country":"FR",
    "sg:address":"20 quai du Lazaret 13002 Marseille",
    "sg:classifiers":[
        {
            "category":"Professional",
            "subcategory":"Business Services",
            "type":"Services"
        }
    ],
    "sg:phone":"+33 4 95 09 34 00",
    "sg:province":"Poitou-Charentes",
    "sg:tags":[
        "chilled",
        "transport",
        "refrigerated"
    ],
    "wof:name":"Heestership S.a.r.l.",
    "wof:placetype":"venue"
},
  "geometry": {"coordinates":[5.37001,43.296101],"type":"Point"}
}