{
  "type": "Feature",
  "properties": {
    "addr:full":"780 Rue Henri Fievet 59310 Orchies Nord Pas-de-Calais 59310",
    "addr:housenumber":"780",
    "addr:postcode":"59310;59310",
    "addr:street":"Rue Henri Fievet",
    "iso:country":"FR",
    "sg:address":"780 Rue Henri Fievet 59310 Orchies",
    "sg:classifiers":[
        {
            "category":"Farming",
            "subcategory":"Farm & Veterinary Services",
            "type":"Manufacturing & Wholesale Goods"
        }
    ],
    "sg:phone":"+33 3 20 71 81 62",
    "sg:postcode":"59310",
    "sg:province":"Nord Pas-de-Calais",
    "sg:tags":[
        "food",
        "product",
        "breeding",
        "animal",
        "related"
    ],
    "wof:name":"Proffinter",
    "wof:placetype":"venue"
},
  "geometry": {"coordinates":[3.24606,50.47398],"type":"Point"}
}