{
  "type": "Feature",
  "properties": {
    "iso:country":"FR",
    "sg:address":"2 Rue Salvador Allende 33400 Talence",
    "sg:city":"Talence",
    "sg:classifiers":[
        {
            "category":"Professional",
            "subcategory":"Engineering",
            "type":"Services"
        }
    ],
    "sg:phone":"+33 5 56 80 67 82",
    "sg:postcode":"33400",
    "sg:province":"Aquitaine",
    "sg:tags":[
        "machine",
        "-",
        "mechanical"
    ],
    "wof:name":"Ste Laygue Et Fils Sarl",
    "wof:placetype":"venue"
},
  "geometry": {"coordinates":[-0.587406,44.788845],"type":"Point"}
}