{
  "type": "Feature",
  "properties": {
    "addr:full":"7 Rue De L'Arcelle 38600 Fontaine Rhone-Alpes 38600",
    "addr:housenumber":"7",
    "addr:postcode":"38600;38600",
    "addr:street":"Rue De L'Arcelle",
    "iso:country":"FR",
    "sg:address":"7 Rue De L'Arcelle 38600 Fontaine",
    "sg:classifiers":[
        {
            "category":"Shopping",
            "subcategory":"Computers & Home Electronics",
            "type":"Retail Goods"
        }
    ],
    "sg:phone":"+33 4 76 26 07 42",
    "sg:postcode":"38600",
    "sg:province":"Rhone-Alpes",
    "sg:tags":[
        "electronic",
        "electrical",
        "equipment"
    ],
    "wof:name":"Portalp International Sa",
    "wof:placetype":"venue"
},
  "geometry": {"coordinates":[5.680465,45.202396],"type":"Point"}
}