{
  "type": "Feature",
  "properties": {
    "addr:full":"86, Rue de S\u00e8vres, 75007 Paris Ile de France 75007",
    "addr:housenumber":"86",
    "addr:postcode":"75007;75007",
    "addr:street":"Rue De Se\u0300Vres",
    "iso:country":"FR",
    "sg:address":"86, Rue de S\u00e8vres, 75007 Paris",
    "sg:orig_category":"Non-Classified Establishments",
    "sg:phone":"+33 1 45 66 51 31",
    "sg:postcode":"75007",
    "sg:province":"Ile de France",
    "wof:name":"B.i.c.s. - Banque Populaire Industrielle Et Commerciale De La R\u00e9gion Sud",
    "wof:placetype":"venue"
},
  "geometry": {"coordinates":[2.316731,48.846924],"type":"Point"}
}