{
  "type": "Feature",
  "properties": {
    "addr:full":"Pl Du Champ De Mars 50000 St L\u00f4 Saint-L\u00f4 Basse Normandie 50000",
    "addr:postcode":"50000;50000",
    "addr:street":"Pl Du Champ De Mars",
    "iso:country":"FR",
    "sg:address":"Pl Du Champ De Mars 50000 St L\u00f4",
    "sg:city":"Saint-L\u00f4",
    "sg:classifiers":[
        {
            "category":"Banks & Credit Unions",
            "subcategory":"Financial Services",
            "type":"Services"
        }
    ],
    "sg:phone":"+33 2 33 72 54 10",
    "sg:postcode":"50000",
    "sg:province":"Basse Normandie",
    "sg:tags":[
        "banking",
        "insurance",
        "institution",
        "finance"
    ],
    "wof:name":"Credit Agricole De St L\u00d4",
    "wof:placetype":"venue"
},
  "geometry": {"coordinates":[-1.087922,49.116245],"type":"Point"}
}