{
  "type": "Feature",
  "properties": {
    "addr:full":"136 Rue Gilbert De Voisins 78670 Villennes Sur Seine Ile de France 78670",
    "addr:housenumber":"136",
    "addr:postcode":"78670;78670",
    "addr:street":"Rue Gilbert De Voisins;France",
    "iso:country":"FR",
    "sg:address":"136 Rue Gilbert De Voisins 78670 Villennes Sur Seine",
    "sg:classifiers":[
        {
            "category":"Manufacturing",
            "subcategory":"Chemicals & Compounds",
            "type":"Manufacturing & Wholesale Goods"
        }
    ],
    "sg:phone":"+33 1 39 79 08 83",
    "sg:postcode":"78670",
    "sg:province":"Ile de France",
    "sg:tags":[
        "pharmaceutical",
        "chemistry"
    ],
    "wof:name":"Ashland Avebene Service Comptabilite Sa",
    "wof:placetype":"venue"
},
  "geometry": {"coordinates":[2.00453,48.928131],"type":"Point"}
}