{
  "type": "Feature",
  "properties": {
    "iso:country":"FR",
    "sg:address":"12 place du Bourg; Rodez",
    "sg:classifiers":[
        {
            "category":"Banks & Credit Unions",
            "subcategory":"Bank",
            "type":"Services"
        }
    ],
    "sg:phone":"+33 5 65 68 19 51",
    "sg:province":"Centre",
    "wof:name":"Soci\u00e9t\u00e9 Bordelaise, De Cic Sa",
    "wof:placetype":"venue"
},
  "geometry": {"coordinates":[2.575312,44.348648],"type":"Point"}
}