{
  "type": "Feature",
  "properties": {
    "iso:country":"FR",
    "sg:address":"Lieu Dit St Roc 72190 Sarge Les Le Mans",
    "sg:classifiers":[
        {
            "category":"Wholesale",
            "subcategory":"Farm Supplies",
            "type":"Manufacturing & Wholesale Goods"
        }
    ],
    "sg:phone":"+33 2 43 76 50 50",
    "sg:postcode":"72190",
    "sg:province":"Pays de Loire",
    "sg:tags":[
        "-",
        "machine",
        "equipment",
        "engineering",
        "machinery",
        "mechanical",
        "agriculture"
    ],
    "wof:name":"2 Ie Ingenierie Et Equipement Pour L'irrigation",
    "wof:placetype":"venue"
},
  "geometry": {"coordinates":[0.22683,48.03146],"type":"Point"}
}