{
  "type": "Feature",
  "properties": {
    "addr:full":"43, Rue du B\u00e9guin, 69007 Lyon Rhone-Alpes 69007",
    "addr:housenumber":"43",
    "addr:postcode":"69007;69007",
    "addr:street":"Rue Du Be\u0301Guin",
    "iso:country":"FR",
    "sg:address":"43, Rue du B\u00e9guin, 69007 Lyon",
    "sg:orig_category":"Unclassifiable Establishments",
    "sg:phone":"+33 4 78 72 94 11",
    "sg:postcode":"69007",
    "sg:province":"Rhone-Alpes",
    "wof:name":"Grivolat Et Matricon S.a.r.l.",
    "wof:placetype":"venue"
},
  "geometry": {"coordinates":[4.852097,45.74844],"type":"Point"}
}