{
  "type": "Feature",
  "properties": {
    "addr:full":"R De La Garenne Zi N 3 De La Chataigneraie 33210 Langon Langon Aquitaine 33210",
    "addr:housenumber":"3",
    "addr:postcode":"33210;33210",
    "addr:street":"La Garenne Zi N;De La Chataigneraie",
    "iso:country":"FR",
    "sg:address":"R De La Garenne Zi N 3 De La Chataigneraie 33210 Langon",
    "sg:city":"Langon",
    "sg:classifiers":[
        {
            "category":"Banks & Credit Unions",
            "subcategory":"Investment Brokerage",
            "type":"Services"
        }
    ],
    "sg:phone":"+33 5 56 76 52 22",
    "sg:postcode":"33210",
    "sg:province":"Aquitaine",
    "sg:tags":[
        "-",
        "transport",
        "related"
    ],
    "wof:name":"Christian Salvesen",
    "wof:placetype":"venue"
},
  "geometry": {"coordinates":[-0.260022,44.494415],"type":"Point"}
}