{
  "type": "Feature",
  "properties": {
    "addr:full":"Rte de Rouen Saint Aubin sur Scie Haute Normandie 76550",
    "addr:postcode":"76550",
    "addr:street":"Rte De Rouen Saint Aubin Sur Scie Haute Normandie",
    "iso:country":"FR",
    "sg:address":"Rte de Rouen",
    "sg:city":"Saint Aubin sur Scie",
    "sg:orig_category":"Unclassifiable Establishments",
    "sg:phone":"+33 2 35 85 23 56",
    "sg:postcode":"76550",
    "sg:province":"Haute Normandie",
    "wof:name":"Cerda S.a.r.l.",
    "wof:placetype":"venue"
},
  "geometry": {"coordinates":[1.06884,49.872936],"type":"Point"}
}