{
  "type": "Feature",
  "properties": {
    "addr:full":"20 Rue Nationale 85670 Falleron Pays de Loire 85670",
    "addr:housenumber":"20",
    "addr:postcode":"85670;85670",
    "addr:street":"Rue Nationale",
    "iso:country":"FR",
    "sg:address":"20 Rue Nationale 85670 Falleron",
    "sg:classifiers":[
        {
            "category":"Professional",
            "subcategory":"Engineering",
            "type":"Services"
        }
    ],
    "sg:phone":"+33 2 51 35 50 78",
    "sg:postcode":"85670",
    "sg:province":"Pays de Loire",
    "sg:tags":[
        "machine",
        "-",
        "mechanical"
    ],
    "wof:name":"Guillonneau Yvon Sarl",
    "wof:placetype":"venue"
},
  "geometry": {"coordinates":[-1.696847,46.882431],"type":"Point"}
}