{
  "type": "Feature",
  "properties": {
    "iso:country":"FR",
    "sg:address":"B.P. 418",
    "sg:city":"Hendaye C\u00e9dex",
    "sg:orig_category":"Non-Classified Establishments",
    "sg:phone":"+33 5 59 20 07 35",
    "sg:postcode":"64704",
    "sg:province":"Aquitaine",
    "wof:name":"Eurovia Aquitaine S.a.r.l.",
    "wof:placetype":"venue"
},
  "geometry": {"coordinates":[-1.776094,43.358524],"type":"Point"}
}