{
  "type": "Feature",
  "properties": {
    "addr:full":"480, Rue des Aviateurs, 25700 Mathay Franche Comt\u00e9",
    "addr:housenumber":"480",
    "addr:postcode":"25700",
    "addr:street":"Rue Des Aviateurs;Franche Comte\u0301",
    "iso:country":"FR",
    "sg:address":"480, Rue des Aviateurs, 25700 Mathay",
    "sg:orig_category":"Unclassifiable Establishments",
    "sg:phone":"+33 3 81 30 01 06",
    "sg:province":"Franche Comt\u00e9",
    "wof:name":"Exincourt B\u00e9ton S.a.",
    "wof:placetype":"venue"
},
  "geometry": {"coordinates":[6.78238,47.427711],"type":"Point"}
}