{
  "type": "Feature",
  "properties": {
    "addr:full":"153, Rte de Colmar, 68040 Ingersheim Ingersheim Alsace 68040",
    "addr:housenumber":"153",
    "addr:postcode":"68040;68040",
    "addr:street":"Rte De Colmar",
    "iso:country":"FR",
    "sg:address":"153, Rte de Colmar, 68040 Ingersheim",
    "sg:city":"Ingersheim",
    "sg:orig_category":"Non-Classified Establishments",
    "sg:phone":"+33 3 89 27 51 16",
    "sg:postcode":"68040",
    "sg:province":"Alsace",
    "wof:name":"Eurhode Service S.a.r.l.",
    "wof:placetype":"venue"
},
  "geometry": {"coordinates":[7.3214,48.088882],"type":"Point"}
}