{
  "type": "Feature",
  "properties": {
    "iso:country":"FR",
    "sg:address":"39 B, Grande Rue, 41370 Josnes",
    "sg:city":"Josnes",
    "sg:orig_category":"Non-Classified Establishments",
    "sg:phone":"+33 2 54 87 42 58",
    "sg:postcode":"41370",
    "sg:province":"Centre",
    "wof:name":"Etablissements Dupuis S.a.r.l.",
    "wof:placetype":"venue"
},
  "geometry": {"coordinates":[1.525504,47.79541],"type":"Point"}
}