{
  "type": "Feature",
  "properties": {
    "addr:full":"B.P. 26, 13680 Lan\u00e7on Provence C\u00e9dex^^ZI de Lan\u00e7on, 13680 Lan\u00e7on Provence Lan\u00e7on Champagne 08250",
    "addr:postcode":"13680;13680;08250",
    "addr:street":"B.P. 26;Lanc\u0327On",
    "iso:country":"FR",
    "sg:address":"B.P. 26, 13680 Lan\u00e7on Provence C\u00e9dex^^ZI de Lan\u00e7on, 13680 Lan\u00e7on Provence",
    "sg:city":"Lan\u00e7on",
    "sg:orig_category":"Non-Classified Establishments",
    "sg:phone":"+33 4 42 80 35 52",
    "sg:postcode":"08250",
    "sg:province":"Champagne",
    "wof:name":"A\u00e9roservice International S.a.r.l.",
    "wof:placetype":"venue"
},
  "geometry": {"coordinates":[5.12418,43.590092],"type":"Point"}
}