{
  "type": "Feature",
  "properties": {
    "iso:country":"FR",
    "sg:address":"Rue Jean Jaures 66260 St Laurent De Cerdans",
    "sg:classifiers":[
        {
            "category":"Professional",
            "subcategory":"Engineering",
            "type":"Services"
        }
    ],
    "sg:phone":"+33 4 68 39 50 02",
    "sg:postcode":"66260",
    "sg:province":"Languedoc-Roussillon",
    "sg:tags":[
        "machine",
        "-",
        "mechanical"
    ],
    "wof:name":"Les Toiles Du Soleil",
    "wof:placetype":"venue"
},
  "geometry": {"coordinates":[2.611893,42.386429],"type":"Point"}
}