{
  "type": "Feature",
  "properties": {
    "addr:full":"B.P. 14, 69641 Caluire et Cuire C\u00e9dex^^1422, Av. Barth\u00e9l\u00e9my Thimonnier, 69300 Caluire et Cuire Rhone-Alpes 69300",
    "addr:postcode":"69641;69300;69300",
    "addr:street":"B.P. 14;Av. Barthe\u0301Le\u0301My Thimonnier",
    "iso:country":"FR",
    "sg:address":"B.P. 14, 69641 Caluire et Cuire C\u00e9dex^^1422, Av. Barth\u00e9l\u00e9my Thimonnier, 69300 Caluire et Cuire",
    "sg:orig_category":"Non-Classified Establishments",
    "sg:phone":"+33 4 78 23 58 97",
    "sg:postcode":"69300",
    "sg:province":"Rhone-Alpes",
    "wof:name":"Mg Cr\u00e9ation S.a.",
    "wof:placetype":"venue"
},
  "geometry": {"coordinates":[4.845985,45.798859],"type":"Point"}
}