{
  "type": "Feature",
  "properties": {
    "addr:full":"29288 Brest CEDEX, Dept 29, France.^^32 rue Mirabeau, 29480 Le Relecq-Kerhuon Cedex 9, Dept 29 Le Relecq-Kerhuon Bretagne 29480",
    "addr:housenumber":"32;29",
    "addr:postcode":"29288;29480;relecq-kerhuon;29480",
    "addr:street":"Rue Mirabeau;Dept",
    "iso:country":"FR",
    "sg:address":"29288 Brest CEDEX, Dept 29, France.^^32 rue Mirabeau, 29480 Le Relecq-Kerhuon Cedex 9, Dept 29",
    "sg:city":"Le Relecq-Kerhuon",
    "sg:classifiers":[
        {
            "category":"Banks & Credit Unions",
            "subcategory":"Bank",
            "type":"Services"
        }
    ],
    "sg:phone":"+33 2 98 00 21 64",
    "sg:postcode":"29480",
    "sg:province":"Bretagne",
    "wof:name":"Banque Federal Finance",
    "wof:placetype":"venue"
},
  "geometry": {"coordinates":[-4.418551,48.406136],"type":"Point"}
}