{
  "type": "Feature",
  "properties": {
    "iso:country":"FR",
    "sg:address":"58 bis, Rue Saint Anne, 75002 Paris",
    "sg:orig_category":"Unclassifiable Establishments",
    "sg:phone":"+33 1 42 60 42 08",
    "sg:province":"Ile de France",
    "wof:name":"Fonderie Du Marais S.a.r.l.",
    "wof:placetype":"venue"
},
  "geometry": {"coordinates":[2.34114,48.867649],"type":"Point"}
}