{
  "type": "Feature",
  "properties": {
    "iso:country":"FR",
    "sg:address":"B.P. 9115, 64051 Pau C\u00e9dex 9^^Av. Larribau, 64000 Pau",
    "sg:city":"Pau",
    "sg:orig_category":"Non-Classified Establishments",
    "sg:phone":"+33 5 59 14 15 16",
    "sg:postcode":"64000",
    "sg:province":"Aquitaine",
    "wof:name":"S.t.a.p. S.a. - Soci\u00e9t\u00e9 De Transport De L'agglom\u00e9ration Paloise",
    "wof:placetype":"venue"
},
  "geometry": {"coordinates":[-0.374294,43.296558],"type":"Point"}
}