{
  "type": "Feature",
  "properties": {
    "addr:full":"B.P. 43, 33187 Le Haillan^^Av. Toussaint Catras, 33185 Le Haillan Le Haillan Aquitaine 33185",
    "addr:housenumber":"haillan;haillan",
    "addr:postcode":"33187;33185;33185",
    "addr:street":"B.P. 43;Catras",
    "iso:country":"FR",
    "sg:address":"B.P. 43, 33187 Le Haillan^^Av. Toussaint Catras, 33185 Le Haillan",
    "sg:city":"Le Haillan",
    "sg:orig_category":"Non-Classified Establishments",
    "sg:phone":"+33 5 56 34 56 00",
    "sg:postcode":"33185",
    "sg:province":"Aquitaine",
    "wof:name":"Schades S.a.",
    "wof:placetype":"venue"
},
  "geometry": {"coordinates":[-0.677844,44.872978],"type":"Point"}
}