{
  "type": "Feature",
  "properties": {
    "addr:full":"6, Rue Bachant, 59620 Aulnoye Aymeries Nord Pas-de-Calais 59620",
    "addr:housenumber":"6",
    "addr:postcode":"59620;59620",
    "addr:street":"Rue Bachant;Aymeries Nord",
    "iso:country":"FR",
    "sg:address":"6, Rue Bachant, 59620 Aulnoye Aymeries",
    "sg:orig_category":"M\u00c9CANIQUE G\u00c9N\u00c9RALE, TOURNAGE, FRAISAGE, RECTIFICATION, TAILLAGE, M\u00c9CANO-SOUDURE, MACHINES SP\u00c9CIALES ",
    "sg:phone":"+33 3 27 67 30 30",
    "sg:postcode":"59620",
    "sg:province":"Nord Pas-de-Calais",
    "wof:name":"Lantoine S.a.",
    "wof:placetype":"venue"
},
  "geometry": {"coordinates":[3.838014,50.209167],"type":"Point"}
}