{
  "type": "Feature",
  "properties": {
    "iso:country":"FR",
    "sg:address":"11 ZI d'Ensisheim 68190 Ensisheim",
    "sg:city":"Ensisheim",
    "sg:classifiers":[
        {
            "category":"Professional",
            "type":"Services"
        }
    ],
    "sg:phone":"+33 3 89 83 40 55",
    "sg:postcode":"68190",
    "sg:province":"Alsace",
    "sg:tags":[
        "transport"
    ],
    "wof:name":"Richert Transport S.a.r.l.",
    "wof:placetype":"venue"
},
  "geometry": {"coordinates":[7.35432,47.865219],"type":"Point"}
}