{
  "type": "Feature",
  "properties": {
    "iso:country":"FR",
    "sg:address":"Rte de Nauroy",
    "sg:city":"Beine Nauroy",
    "sg:orig_category":"Unclassifiable Establishments",
    "sg:phone":"+33 3 26 04 07 28",
    "sg:postcode":"51490",
    "sg:province":"Champagne",
    "wof:name":"M\u00e9canique 2 L S.a.r.l.",
    "wof:placetype":"venue"
},
  "geometry": {"coordinates":[4.265647,49.237225],"type":"Point"}
}