{
  "type": "Feature",
  "properties": {
    "addr:full":"5, Rue du ch\u00e2teau Trompette, 33000 Bordeaux Bordeaux Aquitaine 33000",
    "addr:housenumber":"5",
    "addr:postcode":"33000;33000",
    "addr:street":"Rue Du Cha\u0302Teau Trompette",
    "iso:country":"FR",
    "sg:address":"5, Rue du ch\u00e2teau Trompette, 33000 Bordeaux",
    "sg:city":"Bordeaux",
    "sg:orig_category":"Non-Classified Establishments",
    "sg:phone":"+33 5 56 52 04 51",
    "sg:postcode":"33000",
    "sg:province":"Aquitaine",
    "wof:name":"B.n.s.m.d. S.a. - Banque Neuflize Schlumberger Mallet Danachy",
    "wof:placetype":"venue"
},
  "geometry": {"coordinates":[-0.575774,44.844467],"type":"Point"}
}