{
  "type": "Feature",
  "properties": {
    "addr:full":"Parc De La Baie 50300 Le Val St Pere Avranches Basse Normandie 50300",
    "addr:postcode":"50300;50300",
    "addr:street":"Parc De La Baie;Val St",
    "iso:country":"FR",
    "sg:address":"Parc De La Baie 50300 Le Val St Pere",
    "sg:city":"Avranches",
    "sg:classifiers":[
        {
            "category":"Home & Garden",
            "subcategory":"Furniture",
            "type":"Retail Goods"
        }
    ],
    "sg:phone":"+33 2 33 89 02 55",
    "sg:postcode":"50300",
    "sg:province":"Basse Normandie",
    "sg:tags":[
        "household",
        "wood"
    ],
    "wof:name":"Ouest Placard",
    "wof:placetype":"venue"
},
  "geometry": {"coordinates":[-1.362701,48.669495],"type":"Point"}
}