{
  "type": "Feature",
  "properties": {
    "iso:country":"FR",
    "sg:address":"Zac Du Blavet 83520 Roquebrune Sur Argens",
    "sg:classifiers":[
        {
            "category":"Farming",
            "subcategory":"Farm",
            "type":"Manufacturing & Wholesale Goods"
        }
    ],
    "sg:phone":"+33 4 94 19 82 73",
    "sg:province":"Lorraine",
    "sg:tags":[
        "horticulture",
        "agriculture",
        "livestock"
    ],
    "wof:name":"Chabas Fleurs Sa",
    "wof:placetype":"venue"
},
  "geometry": {"coordinates":[6.64088,43.44437],"type":"Point"}
}