{
  "type": "Feature",
  "properties": {
    "addr:full":"12, Rue Saint Antoine du T, 31000 Toulouse Midi Pyr\u00e9n\u00e9es 31000",
    "addr:housenumber":"12",
    "addr:postcode":"31000;31000",
    "addr:street":"Rue Saint Antoine Du T",
    "iso:country":"FR",
    "sg:address":"12, Rue Saint Antoine du T, 31000 Toulouse",
    "sg:orig_category":"Non-Classified Establishments",
    "sg:phone":"+33 5 57 81 21 75",
    "sg:postcode":"31000",
    "sg:province":"Midi Pyr\u00e9n\u00e9es",
    "wof:name":"Banque Sofirec S.n.c.",
    "wof:placetype":"venue"
},
  "geometry": {"coordinates":[1.447445,43.603039],"type":"Point"}
}