{
  "type": "Feature",
  "properties": {
    "iso:country":"FR",
    "sg:address":"All Des Ch\u00eanes Zac Du Baconnet 69700 Montagny",
    "sg:classifiers":[
        {
            "category":"Manufacturing",
            "subcategory":"Tools & Machinery",
            "type":"Manufacturing & Wholesale Goods"
        }
    ],
    "sg:phone":"+33 4 72 49 27 72",
    "sg:postcode":"69700",
    "sg:province":"Rhone-Alpes",
    "sg:tags":[
        "equipment",
        "measurement",
        "-",
        "precision",
        "instrument"
    ],
    "wof:name":"Efs Sas",
    "wof:placetype":"venue"
},
  "geometry": {"coordinates":[4.715199,45.551682],"type":"Point"}
}