{
  "type": "Feature",
  "properties": {
    "iso:country":"FR",
    "sg:address":"5 Rue Vaucher 01117 Oyonnax Cedex",
    "sg:classifiers":[
        {
            "category":"Manufacturing",
            "subcategory":"Metals",
            "type":"Manufacturing & Wholesale Goods"
        }
    ],
    "sg:phone":"+33 4 74 77 35 04",
    "sg:province":"Midi Pyr\u00e9n\u00e9es",
    "sg:tags":[
        "metallurgy",
        "metalworking",
        "processing"
    ],
    "wof:name":"Codecor",
    "wof:placetype":"venue"
},
  "geometry": {"coordinates":[5.648746,46.259365],"type":"Point"}
}