{
  "type": "Feature",
  "properties": {
    "addr:full":"B.P. 109, 35501 Vitr\u00e9 C\u00e9dex^^Rte des Eaux, 35500 Vitr\u00e9 Vitr\u00e9 Bretagne 35500",
    "addr:housenumber":"b.p. 109",
    "addr:postcode":"35501;35500;35500",
    "addr:street":"Des Eaux;Bretagne",
    "iso:country":"FR",
    "sg:address":"B.P. 109, 35501 Vitr\u00e9 C\u00e9dex^^Rte des Eaux, 35500 Vitr\u00e9",
    "sg:city":"Vitr\u00e9",
    "sg:orig_category":"Non-Classified Establishments",
    "sg:phone":"+33 2 99 75 24 34",
    "sg:postcode":"35500",
    "sg:province":"Bretagne",
    "wof:name":"B.c.m. Cosm\u00e9tique S.a. - Boots Contract Manufacturing",
    "wof:placetype":"venue"
},
  "geometry": {"coordinates":[-1.30752,48.080273],"type":"Point"}
}