{
  "type": "Feature",
  "properties": {
    "addr:full":"3, Rue Amp\u00e8re, 69960 Corbas Rhone-Alpes",
    "addr:housenumber":"3",
    "addr:postcode":"69960",
    "addr:street":"Rue Ampe\u0300Re",
    "iso:country":"FR",
    "sg:address":"3, Rue Amp\u00e8re, 69960 Corbas",
    "sg:orig_category":"Unclassifiable Establishments",
    "sg:phone":"+33 4 72 50 50 33",
    "sg:province":"Rhone-Alpes",
    "wof:name":"Williams Silver Frost S.a.r.l.",
    "wof:placetype":"venue"
},
  "geometry": {"coordinates":[4.898495,45.670914],"type":"Point"}
}