{
  "type": "Feature",
  "properties": {
    "addr:full":"1135, Rue Lavoisier, 54710 Ludres Lorraine",
    "addr:housenumber":"1135",
    "addr:postcode":"54710",
    "addr:street":"Rue Lavoisier",
    "iso:country":"FR",
    "sg:address":"1135, Rue Lavoisier, 54710 Ludres",
    "sg:orig_category":"Non-Classified Establishments",
    "sg:phone":"+33 3 83 15 28 70",
    "sg:province":"Lorraine",
    "wof:name":"Thiebaut Transports S.a.r.l.",
    "wof:placetype":"venue"
},
  "geometry": {"coordinates":[6.191655,48.615311],"type":"Point"}
}