{
  "type": "Feature",
  "properties": {
    "iso:country":"FR",
    "sg:address":"9 Avenue I Et F Joliot Curie",
    "sg:city":"Ris Orangis",
    "sg:classifiers":[
        {
            "category":"Banks & Credit Unions",
            "subcategory":"Financial Services",
            "type":"Services"
        }
    ],
    "sg:phone":"+33 1 69 36 12 12",
    "sg:postcode":"91130",
    "sg:province":"Ile de France",
    "sg:tags":[
        "banking",
        "finance",
        "insurance"
    ],
    "wof:name":"Mutuelle Assurance Commercants Industriels De France Cadres (macif)",
    "wof:placetype":"venue"
},
  "geometry": {"coordinates":[2.409515,48.64957],"type":"Point"}
}