{
  "type": "Feature",
  "properties": {
    "iso:country":"FR",
    "sg:address":"200, Chemin des Ormeaux, 69578 Limonest C\u00e9dex",
    "sg:orig_category":"Non-Classified Establishments",
    "sg:phone":"+33 4 72 52 48 00",
    "sg:province":"Franche Comt\u00e9",
    "wof:name":"01 Db-stell S.a.",
    "wof:placetype":"venue"
},
  "geometry": {"coordinates":[4.772876,45.81007],"type":"Point"}
}