{
  "type": "Feature",
  "properties": {
    "addr:full":"12 rue des Pr\u00e9s 71300 Montceau les Mines Saint-Berain-sous-Sanvignes Bourgogne 71300",
    "addr:housenumber":"12",
    "addr:postcode":"71300;71300",
    "addr:street":"Rue Des Pre\u0301S;Bourgogne",
    "iso:country":"FR",
    "sg:address":"12 rue des Pr\u00e9s 71300 Montceau les Mines",
    "sg:city":"Saint-Berain-sous-Sanvignes",
    "sg:classifiers":[
        {
            "category":"Shopping",
            "subcategory":"Baby Store",
            "type":"Retail Goods"
        }
    ],
    "sg:phone":"+33 3 85 57 05 27",
    "sg:postcode":"71300",
    "sg:province":"Bourgogne",
    "sg:tags":[
        "children's",
        "sock"
    ],
    "wof:name":"Blanchard Sa",
    "wof:placetype":"venue"
},
  "geometry": {"coordinates":[4.357765,46.669659],"type":"Point"}
}