{
  "type": "Feature",
  "properties": {
    "iso:country":"FR",
    "sg:address":"138, Rue du G\u00e9n\u00e9ral de Gaulle, 10340 Les Riceys",
    "sg:orig_category":"Non-Classified Establishments",
    "sg:phone":"+33 3 25 29 30 93",
    "sg:province":"Champagne",
    "wof:name":"Maison Alexandre Bonnet S.a.",
    "wof:placetype":"venue"
},
  "geometry": {"coordinates":[4.36733,47.99155],"type":"Point"}
}