{
  "type": "Feature",
  "properties": {
    "iso:country":"FR",
    "sg:address":"20, Rue des Tr\u00e9zelots - La Porte Verte Essey , 54425 Pulnoy",
    "sg:orig_category":"Unclassifiable Establishments",
    "sg:phone":"+33 3 83 18 01 50",
    "sg:province":"Poitou-Charentes",
    "wof:name":"Bigmat C.i.a.b. S.a.",
    "wof:placetype":"venue"
},
  "geometry": {"coordinates":[6.251235,48.708633],"type":"Point"}
}