{
  "type": "Feature",
  "properties": {
    "addr:full":"33, Rue de la Poterne, 77620 Egreville Ile de France",
    "addr:housenumber":"33",
    "addr:postcode":"77620",
    "addr:street":"Rue De La Poterne;Ile De France",
    "iso:country":"FR",
    "sg:address":"33, Rue de la Poterne, 77620 Egreville",
    "sg:orig_category":"Unclassifiable Establishments",
    "sg:phone":"+33 1 64 78 58 40",
    "sg:province":"Ile de France",
    "wof:name":"Auxil S.a.",
    "wof:placetype":"venue"
},
  "geometry": {"coordinates":[2.875105,48.177063],"type":"Point"}
}