{
  "type": "Feature",
  "properties": {
    "addr:full":"Rue du Moulin Saint Hilaire le Grand Champagne 51600",
    "addr:postcode":"51600",
    "addr:street":"Rue Du Moulin Saint",
    "iso:country":"FR",
    "sg:address":"Rue du Moulin",
    "sg:city":"Saint Hilaire le Grand",
    "sg:orig_category":"Non-Classified Establishments",
    "sg:phone":"+33 3 26 70 00 02",
    "sg:postcode":"51600",
    "sg:province":"Champagne",
    "wof:name":"Bouvet N\u00e9goce S.a.",
    "wof:placetype":"venue"
},
  "geometry": {"coordinates":[4.468777,49.168602],"type":"Point"}
}