{
  "type": "Feature",
  "properties": {
    "addr:full":"B.P. 134, 51008 Ch\u00e2lons en Champagne C\u00e9dex^^42, Rue de Fagni\u00e8res, 51000 Ch\u00e2lons en Champagne Champagne 51000",
    "addr:housenumber":"b.p. 134",
    "addr:postcode":"51008;51000;51000",
    "addr:street":"Rue De Fagnie\u0300Res",
    "iso:country":"FR",
    "sg:address":"B.P. 134, 51008 Ch\u00e2lons en Champagne C\u00e9dex^^42, Rue de Fagni\u00e8res, 51000 Ch\u00e2lons en Champagne",
    "sg:orig_category":"Archives, Destruction d' Bennes, Location de Fers, mitrailles, r\u00e9cup\u00e9ration et/ou d\u00e9chets de Papier,",
    "sg:phone":"+33 3 26 68 17 61",
    "sg:postcode":"51000",
    "sg:province":"Champagne",
    "wof:name":"Roughol S.a.",
    "wof:placetype":"venue"
},
  "geometry": {"coordinates":[4.355399,48.955708],"type":"Point"}
}