{
  "type": "Feature",
  "properties": {
    "iso:country":"FR",
    "sg:address":"B.P. 50",
    "sg:city":"Villebon sur Yvette",
    "sg:orig_category":"Non-Classified Establishments",
    "sg:phone":"+33 1 64 48 27 37",
    "sg:postcode":"91140",
    "sg:province":"Ile de France",
    "wof:name":"D\u00e9co Ader S.a.",
    "wof:placetype":"venue"
},
  "geometry": {"coordinates":[2.227225,48.700069],"type":"Point"}
}