{
  "type": "Feature",
  "properties": {
    "addr:full":"56 rue du President; Lyon; 69001 Rhone-Alpes 69001",
    "addr:housenumber":"56",
    "addr:postcode":"69001;69001",
    "addr:street":"Rue Du President",
    "iso:country":"FR",
    "sg:address":"56 rue du President; Lyon; 69001",
    "sg:classifiers":[
        {
            "category":"Banks & Credit Unions",
            "subcategory":"Bank",
            "type":"Services"
        }
    ],
    "sg:phone":"+33 3372564600",
    "sg:postcode":"69001",
    "sg:province":"Rhone-Alpes",
    "wof:name":"Societe Marseillaise De Credit",
    "wof:placetype":"venue"
},
  "geometry": {"coordinates":[4.83185,45.768505],"type":"Point"}
}