{
  "type": "Feature",
  "properties": {
    "addr:full":"Avenue De Villarcher Zi Des Landiers Nord 73000 Chambery Rhone-Alpes 73000",
    "addr:postcode":"73000;73000",
    "addr:street":"Avenue De Villarcher Zi Des Landiers Nord",
    "iso:country":"FR",
    "sg:address":"Avenue De Villarcher Zi Des Landiers Nord 73000 Chambery",
    "sg:classifiers":[
        {
            "category":"Transit Center",
            "subcategory":"Freight",
            "type":"Transportation"
        }
    ],
    "sg:phone":"+33 4 79 68 65 50",
    "sg:postcode":"73000",
    "sg:province":"Rhone-Alpes",
    "sg:tags":[
        "metallurgy",
        "pipe",
        "metalworking",
        "sheet"
    ],
    "wof:name":"Etablissements Palmieri",
    "wof:placetype":"venue"
},
  "geometry": {"coordinates":[5.90839,45.538151],"type":"Point"}
}