{
  "type": "Feature",
  "properties": {
    "addr:full":"21 R Joann\u00e8s Carret 69009 Lyon Rhone-Alpes 69009",
    "addr:housenumber":"21",
    "addr:postcode":"69009;69009",
    "addr:street":"R Joanne\u0300S Carret",
    "iso:country":"FR",
    "sg:address":"21 R Joann\u00e8s Carret 69009 Lyon",
    "sg:classifiers":[
        {
            "category":"Wholesale",
            "subcategory":"Metals & Minerals",
            "type":"Manufacturing & Wholesale Goods"
        }
    ],
    "sg:phone":"+33 4 78 83 00 36",
    "sg:postcode":"69009",
    "sg:province":"Rhone-Alpes",
    "sg:tags":[
        "metallurgy",
        "pipe",
        "metalworking",
        "processing",
        "sheet"
    ],
    "wof:name":"Gabialex Sa",
    "wof:placetype":"venue"
},
  "geometry": {"coordinates":[4.815564,45.790813],"type":"Point"}
}