{
  "type": "Feature",
  "properties": {
    "addr:full":"21 Rue Du Boulanger 67430 Butten Butten Alsace 67430",
    "addr:housenumber":"21",
    "addr:postcode":"67430;67430",
    "addr:street":"Rue Du Boulanger",
    "iso:country":"FR",
    "sg:address":"21 Rue Du Boulanger 67430 Butten",
    "sg:city":"Butten",
    "sg:classifiers":[
        {
            "category":"Professional",
            "type":"Services"
        }
    ],
    "sg:phone":"+33 3 88 01 41 56",
    "sg:postcode":"67430",
    "sg:province":"Alsace",
    "sg:tags":[
        "transport",
        "road"
    ],
    "wof:name":"Eschenbrenner Freres",
    "wof:placetype":"venue"
},
  "geometry": {"coordinates":[7.223005,48.971127],"type":"Point"}
}