{
  "type": "Feature",
  "properties": {
    "addr:full":"12 Bd De La R\u00e9publique 42190 Charlieu Rhone-Alpes 42190",
    "addr:housenumber":"12",
    "addr:postcode":"42190;42190",
    "addr:street":"Bd De La Re\u0301Publique",
    "iso:country":"FR",
    "sg:address":"12 Bd De La R\u00e9publique 42190 Charlieu",
    "sg:classifiers":[
        {
            "category":"Manufacturing",
            "subcategory":"Rubber & Plastics",
            "type":"Manufacturing & Wholesale Goods"
        }
    ],
    "sg:phone":"+33 4 77 69 33 00",
    "sg:postcode":"42190",
    "sg:province":"Rhone-Alpes",
    "wof:name":"Plastohm Charlieu Sa",
    "wof:placetype":"venue"
},
  "geometry": {"coordinates":[4.166972,46.156765],"type":"Point"}
}