{
  "type": "Feature",
  "properties": {
    "addr:full":"46200 Saint Sozy Midi Pyr\u00e9n\u00e9es",
    "addr:housenumber":"46200",
    "addr:street":"Saint Sozy Midi",
    "iso:country":"FR",
    "sg:address":"46200 Saint Sozy",
    "sg:orig_category":"Non-Classified Establishments",
    "sg:phone":"+33 5 65 32 22 88",
    "sg:province":"Midi Pyr\u00e9n\u00e9es",
    "wof:name":"Quercy P\u00e9rigord Fermier S.c.a.",
    "wof:placetype":"venue"
},
  "geometry": {"coordinates":[1.56366,44.880402],"type":"Point"}
}