{
  "type": "Feature",
  "properties": {
    "iso:country":"FR",
    "sg:address":"72 all\u00e9e des Grands Journaux 74300 Cluses",
    "sg:classifiers":[
        {
            "category":"Manufacturing",
            "subcategory":"Motor Vehicles & Parts",
            "type":"Manufacturing & Wholesale Goods"
        }
    ],
    "sg:phone":"+33 4 50 98 31 37",
    "sg:province":"Rhone-Alpes",
    "sg:tags":[
        "precision",
        "mechanic"
    ],
    "wof:name":"Travaglini Sa",
    "wof:placetype":"venue"
},
  "geometry": {"coordinates":[6.581308,46.064743],"type":"Point"}
}