{
  "type": "Feature",
  "properties": {
    "addr:full":"RN 24 - ZI de Beausoleil Guillac Bretagne 56800",
    "addr:postcode":"56800",
    "addr:street":"Rn 24 Zi De Beausoleil",
    "iso:country":"FR",
    "sg:address":"RN 24 - ZI de Beausoleil",
    "sg:city":"Guillac",
    "sg:orig_category":"Unclassifiable Establishments",
    "sg:phone":"+33 2 97 73 91 91",
    "sg:postcode":"56800",
    "sg:province":"Bretagne",
    "wof:name":"Fermeture Du Porhoet S.a.r.l.",
    "wof:placetype":"venue"
},
  "geometry": {"coordinates":[-2.357955,47.879848],"type":"Point"}
}