{
  "type": "Feature",
  "properties": {
    "addr:full":"34 Bd Victor 75015 Paris Ile de France 75015",
    "addr:housenumber":"34",
    "addr:postcode":"75015;75015",
    "addr:street":"Bd Victor",
    "iso:country":"FR",
    "sg:address":"34 Bd Victor 75015 Paris",
    "sg:classifiers":[
        {
            "category":"Travel",
            "subcategory":"Hotels & Motels",
            "type":"Entertainment"
        }
    ],
    "sg:phone":"+33 1 45 33 01 91",
    "sg:postcode":"75015",
    "sg:province":"Ile de France",
    "sg:tags":[
        "hotels",
        "business",
        "restaurant"
    ],
    "wof:name":"Sappav Vinci Park",
    "wof:placetype":"venue"
},
  "geometry": {"coordinates":[2.284121,48.834038],"type":"Point"}
}