{
  "type": "Feature",
  "properties": {
    "addr:full":"139, Rue des Arts, 59100 Roubaix Nord Pas-de-Calais",
    "addr:housenumber":"139",
    "addr:postcode":"59100",
    "addr:street":"Rue Des Arts",
    "iso:country":"FR",
    "sg:address":"139, Rue des Arts, 59100 Roubaix",
    "sg:orig_category":"Unclassifiable Establishments",
    "sg:phone":"+33 3 20 28 48 68",
    "sg:province":"Nord Pas-de-Calais",
    "wof:name":"Insite S.a.r.l.",
    "wof:placetype":"venue"
},
  "geometry": {"coordinates":[3.162961,50.689423],"type":"Point"}
}