{
  "type": "Feature",
  "properties": {
    "addr:full":"17, Av. de Royan, 17130 Montendre Poitou-Charentes 17130",
    "addr:postcode":"17130;17130",
    "addr:street":"17 Av. De Royan",
    "iso:country":"FR",
    "sg:address":"17, Av. de Royan, 17130 Montendre",
    "sg:orig_category":"Non-Classified Establishments",
    "sg:phone":"+33 5 46 49 00 47",
    "sg:postcode":"17130",
    "sg:province":"Poitou-Charentes",
    "wof:name":"Bou\u00e9 Dominique Et Didier S.a.r.l.",
    "wof:placetype":"venue"
},
  "geometry": {"coordinates":[-0.40847,45.285606],"type":"Point"}
}