{
  "type": "Feature",
  "properties": {
    "addr:full":"Chem De F\u00e9ron 59212 Wignehies Nord Pas-de-Calais 59212",
    "addr:postcode":"59212;59212",
    "addr:street":"Chem De Fe\u0301Ron",
    "iso:country":"FR",
    "sg:address":"Chem De F\u00e9ron 59212 Wignehies",
    "sg:classifiers":[
        {
            "category":"Shopping",
            "type":"Retail Goods"
        }
    ],
    "sg:phone":"+33 3 27 60 13 78",
    "sg:postcode":"59212",
    "sg:province":"Nord Pas-de-Calais",
    "sg:tags":[
        "metallurgy",
        "finished",
        "-",
        "metalworking",
        "metallic"
    ],
    "wof:name":"Roth Sa",
    "wof:placetype":"venue"
},
  "geometry": {"coordinates":[4.009913,50.022907],"type":"Point"}
}