{
  "type": "Feature",
  "properties": {
    "iso:country":"FR",
    "sg:address":"8, Rue de Chalons sur Sa\u00f4ne, 69007 Lyon",
    "sg:orig_category":"Unclassifiable Establishments",
    "sg:phone":"+33 4 72 71 15 15",
    "sg:postcode":"69007",
    "sg:province":"Rhone-Alpes",
    "wof:name":"Profil Arbed Distribution France S.a.",
    "wof:placetype":"venue"
},
  "geometry": {"coordinates":[4.836365,45.719078],"type":"Point"}
}