{
  "type": "Feature",
  "properties": {
    "iso:country":"FR",
    "sg:address":"10, Av. Louis Aragon, 93000 Bobigny",
    "sg:orig_category":"Non-Classified Establishments",
    "sg:phone":"+33 1 48 31 90 71",
    "sg:postcode":"93000",
    "sg:province":"Ile de France",
    "wof:name":"Clemydro S.a.r.l.",
    "wof:placetype":"venue"
},
  "geometry": {"coordinates":[2.43983,48.914322],"type":"Point"}
}