{
  "type": "Feature",
  "properties": {
    "iso:country":"FR",
    "sg:address":"Beard 01460 GEOVREISSIAT",
    "sg:classifiers":[
        {
            "category":"Manufacturing",
            "subcategory":"Wood Products",
            "type":"Manufacturing & Wholesale Goods"
        }
    ],
    "sg:phone":"+33 4 74 76 27 38",
    "sg:province":"Rhone-Alpes",
    "sg:tags":[
        "pallet",
        "made"
    ],
    "wof:name":"Bab Entreprise Individuelle",
    "wof:placetype":"venue"
},
  "geometry": {"coordinates":[5.549845,46.179981],"type":"Point"}
}