{
  "type": "Feature",
  "properties": {
    "addr:full":"boulevard Georges Pompidou 06200 Nice Centre",
    "addr:postcode":"06200",
    "addr:street":"Boulevard Georges Pompidou",
    "iso:country":"FR",
    "sg:address":"boulevard Georges Pompidou 06200 Nice",
    "sg:classifiers":[
        {
            "category":"Food & Beverages",
            "subcategory":"Fruits & Vegetables",
            "type":"Retail Goods"
        }
    ],
    "sg:phone":"+33 4 93 72 07 70",
    "sg:province":"Centre",
    "wof:name":"Ste Ecofruits S.a.r.l.",
    "wof:placetype":"venue"
},
  "geometry": {"coordinates":[7.204165,43.668613],"type":"Point"}
}