{
  "type": "Feature",
  "properties": {
    "addr:full":"53 Av De La Lib\u00e9ration 42120 Le Coteau Rhone-Alpes 42120",
    "addr:postcode":"42120;42120",
    "addr:street":"53 Av De La Libe\u0301Ration;Rhone-Alpes",
    "iso:country":"FR",
    "sg:address":"53 Av De La Lib\u00e9ration 42120 Le Coteau",
    "sg:classifiers":[
        {
            "category":"Banks & Credit Unions",
            "subcategory":"Financial Services",
            "type":"Services"
        }
    ],
    "sg:phone":"+33 4 77 68 19 79",
    "sg:postcode":"42120",
    "sg:province":"Rhone-Alpes",
    "sg:tags":[
        "banking",
        "insurance",
        "institution",
        "finance"
    ],
    "wof:name":"Caisse D'epargne Loire Drome Ardeche Banque Cooperative",
    "wof:placetype":"venue"
},
  "geometry": {"coordinates":[4.084391,46.028942],"type":"Point"}
}