{
  "type": "Feature",
  "properties": {
    "iso:country":"FR",
    "sg:address":"392-470 Rue De Cocherel Zi 27000 Evreux",
    "sg:classifiers":[
        {
            "category":"Government",
            "subcategory":"Department Of Motor Vehicles",
            "type":"Public Place"
        }
    ],
    "sg:phone":"+33 2 32 39 80 00",
    "sg:postcode":"27000",
    "sg:province":"Haute Normandie",
    "sg:tags":[
        "equipment",
        "industrial",
        "transport",
        "motor-cars"
    ],
    "wof:name":"Fai Faurecia Snc",
    "wof:placetype":"venue"
},
  "geometry": {"coordinates":[1.150283,49.027546],"type":"Point"}
}