{
  "type": "Feature",
  "properties": {
    "addr:full":"B.P. 78, 92216 Saint Cloud C\u00e9dex^^13, Rue Henri R\u00e9gnault, 92210 Saint Cloud Ile de France",
    "addr:postcode":"92216;92210",
    "addr:street":"B.P. 78;Rue Henri Re\u0301Gnault",
    "iso:country":"FR",
    "sg:address":"B.P. 78, 92216 Saint Cloud C\u00e9dex^^13, Rue Henri R\u00e9gnault, 92210 Saint Cloud",
    "sg:orig_category":"Non-Classified Establishments",
    "sg:phone":"+33 1 47 71 79 68",
    "sg:province":"Ile de France",
    "wof:name":"Vassal Motor\u00e9ducteurs S.a.",
    "wof:placetype":"venue"
},
  "geometry": {"coordinates":[2.22036,48.84441],"type":"Point"}
}