{
  "type": "Feature",
  "properties": {
    "addr:full":"B.P. 7513, 44075 Nantes C\u00e9dex 03^^3, Rue de la Raini\u00e8re, 44000 Nantes Pays de Loire",
    "addr:housenumber":"03;^ 3",
    "addr:postcode":"44075;44000",
    "addr:street":"B.P. 7513;^;Rue De La Rainie\u0300Re",
    "iso:country":"FR",
    "sg:address":"B.P. 7513, 44075 Nantes C\u00e9dex 03^^3, Rue de la Raini\u00e8re, 44000 Nantes",
    "sg:orig_category":"Non-Classified Establishments",
    "sg:phone":"+33 2 40 68 35 80",
    "sg:province":"Pays de Loire",
    "wof:name":"Eurial Poitouraine S.a.s.",
    "wof:placetype":"venue"
},
  "geometry": {"coordinates":[-1.553059,47.218117],"type":"Point"}
}