{
  "type": "Feature",
  "properties": {
    "iso:country":"FR",
    "sg:address":"8 Bd De Bercy 75012 Paris",
    "sg:classifiers":[
        {
            "category":"Sports & Exercise",
            "subcategory":"Sports Center",
            "type":"Entertainment"
        }
    ],
    "sg:phone":"+33 1 40 02 60 60",
    "sg:postcode":"75012",
    "sg:province":"Ile de France",
    "sg:tags":[
        "game"
    ],
    "wof:name":"Ste Exploitation Palais Omnisport Bercy",
    "wof:placetype":"venue"
},
  "geometry": {"coordinates":[2.378037,48.839436],"type":"Point"}
}