{
  "type": "Feature",
  "properties": {
    "iso:country":"FR",
    "sg:address":"20, Chemin Louis Chirpaz - Immeuble les Bureau de Chalin, 69130 Ecully",
    "sg:orig_category":"Unclassifiable Establishments",
    "sg:phone":"+33 4 72 86 83 83",
    "sg:postcode":"69130",
    "sg:province":"Rhone-Alpes",
    "wof:name":"Neyrial Grand Est S.a.s.",
    "wof:placetype":"venue"
},
  "geometry": {"coordinates":[4.783317,45.778454],"type":"Point"}
}