{
  "type": "Feature",
  "properties": {
    "addr:full":"101, Rte de Tours, 72220 Ecommoy Pays de Loire",
    "addr:housenumber":"101",
    "addr:postcode":"72220",
    "addr:street":"Rte De Tours;Ecommoy",
    "iso:country":"FR",
    "sg:address":"101, Rte de Tours, 72220 Ecommoy",
    "sg:orig_category":"Unclassifiable Establishments",
    "sg:phone":"+33 2 43 47 02 90",
    "sg:province":"Pays de Loire",
    "wof:name":"B\u00e9lipa S.a.",
    "wof:placetype":"venue"
},
  "geometry": {"coordinates":[0.28698,47.824638],"type":"Point"}
}