{
  "type": "Feature",
  "properties": {
    "addr:full":"13 R Du Mar\u00e9chal Leclerc 25500 Morteau Franche Comt\u00e9 25500",
    "addr:housenumber":"13",
    "addr:postcode":"25500;25500",
    "addr:street":"R Du Mare\u0301Chal Leclerc;Franche Comte\u0301",
    "iso:country":"FR",
    "sg:address":"13 R Du Mar\u00e9chal Leclerc 25500 Morteau",
    "sg:classifiers":[
        {
            "category":"Manufacturing",
            "subcategory":"Metals",
            "type":"Manufacturing & Wholesale Goods"
        }
    ],
    "sg:phone":"+33 3 81 67 24 00",
    "sg:postcode":"25500",
    "sg:province":"Franche Comt\u00e9",
    "sg:tags":[
        "metallurgy",
        "steel",
        "metalworking"
    ],
    "wof:name":"Fabi Automobile",
    "wof:placetype":"venue"
},
  "geometry": {"coordinates":[6.604645,47.061562],"type":"Point"}
}