{
  "type": "Feature",
  "properties": {
    "addr:full":"110, Av. L\u00e9o Lagrange, 63300 Thiers Thiers Auvergne 63300",
    "addr:housenumber":"110",
    "addr:postcode":"63300;63300",
    "addr:street":"Av. Le\u0301O Lagrange",
    "iso:country":"FR",
    "sg:address":"110, Av. L\u00e9o Lagrange, 63300 Thiers",
    "sg:city":"Thiers",
    "sg:orig_category":"Unclassifiable Establishments",
    "sg:phone":"+33 4 73 80 20 69",
    "sg:postcode":"63300",
    "sg:province":"Auvergne",
    "wof:name":"Arno Industrie S.a.r.l.",
    "wof:placetype":"venue"
},
  "geometry": {"coordinates":[3.522632,45.845047],"type":"Point"}
}