{
  "type": "Feature",
  "properties": {
    "iso:country":"FR",
    "sg:address":"Campagne Trouchet 84220 Lioux",
    "sg:orig_category":"Non-Classified Establishments",
    "sg:phone":"+33 4 90 05 53 53",
    "sg:province":"Provence-Alpes-C\u00f4te d'Azur",
    "wof:name":"M.c.e.s. S.a.r.l. - Manufacture Caoutchouc Elastom\u00e8re Sp\u00e9ciaux",
    "wof:placetype":"venue"
},
  "geometry": {"coordinates":[5.201208,43.858566],"type":"Point"}
}