{
  "type": "Feature",
  "properties": {
    "iso:country":"FR",
    "sg:address":"27, Rue des Gros Gr\u00e8s, 92700 Colombes",
    "sg:orig_category":"Unclassifiable Establishments",
    "sg:phone":"+33 1 47 82 32 32",
    "sg:province":"Ile de France",
    "wof:name":"Imprimerie Indica S.a.r.l.",
    "wof:placetype":"venue"
},
  "geometry": {"coordinates":[2.241424,48.915974],"type":"Point"}
}