{
  "type": "Feature",
  "properties": {
    "iso:country":"FR",
    "sg:address":"B.P. 7318, 37073 Tours C\u00e9dex^^36, Rue de Su\u00e8de, 37000 Tours",
    "sg:city":"Tours",
    "sg:orig_category":"Non-Classified Establishments",
    "sg:phone":"+33 2 47 88 00 08",
    "sg:postcode":"37000",
    "sg:province":"Centre",
    "wof:name":"Hobart S.a.",
    "wof:placetype":"venue"
},
  "geometry": {"coordinates":[0.689715,47.390385],"type":"Point"}
}