{
  "type": "Feature",
  "properties": {
    "addr:full":"Av Danton - ZI Revin Champagne 08500",
    "addr:postcode":"zi;08500",
    "addr:street":"Av Danton;Champagne",
    "iso:country":"FR",
    "sg:address":"Av Danton - ZI",
    "sg:city":"Revin",
    "sg:orig_category":"Chaudronnerie, T\u00f4lerie Fraisage Maintenance industrielle M\u00e9canique de pr\u00e9cision M\u00e9canique g\u00e9n\u00e9rale M",
    "sg:phone":"+33 3 24 41 00 68",
    "sg:postcode":"08500",
    "sg:province":"Champagne",
    "wof:name":"Revitec S.a.r.l.",
    "wof:placetype":"venue"
},
  "geometry": {"coordinates":[4.64354,49.926094],"type":"Point"}
}