{
  "type": "Feature",
  "properties": {
    "addr:full":"2, Rue du Cours Fleury, 21000 Dijon Dijon Bourgogne 21000",
    "addr:housenumber":"2",
    "addr:postcode":"21000;21000",
    "addr:street":"Rue Du Cours Fleury",
    "iso:country":"FR",
    "sg:address":"2, Rue du Cours Fleury, 21000 Dijon",
    "sg:city":"Dijon",
    "sg:orig_category":"Unclassifiable Establishments",
    "sg:phone":"+33 3 80 47 77 25",
    "sg:postcode":"21000",
    "sg:province":"Bourgogne",
    "wof:name":"Nouvion Et Compagnie S.a.",
    "wof:placetype":"venue"
},
  "geometry": {"coordinates":[5.035964,47.351482],"type":"Point"}
}