{
  "type": "Feature",
  "properties": {
    "addr:full":"Rue Lavoisier Zi De La Sth\u00e8re 14200 H\u00e9rouville St Clair H\u00e9rouville-Saint-Clair Basse Normandie 14200",
    "addr:postcode":"14200;14200",
    "addr:street":"Rue Lavoisier Zi De La Sthe\u0300Re;He\u0301Rouville St",
    "iso:country":"FR",
    "sg:address":"Rue Lavoisier Zi De La Sth\u00e8re 14200 H\u00e9rouville St Clair",
    "sg:city":"H\u00e9rouville-Saint-Clair",
    "sg:classifiers":[
        {
            "category":"Manufacturing",
            "subcategory":"Rubber & Plastics",
            "type":"Manufacturing & Wholesale Goods"
        }
    ],
    "sg:phone":"+33 2 31 47 65 00",
    "sg:postcode":"14200",
    "sg:province":"Basse Normandie",
    "wof:name":"Laguerre Pere Et Fils Sarl",
    "wof:placetype":"venue"
},
  "geometry": {"coordinates":[-0.328299,49.203964],"type":"Point"}
}