{
  "type": "Feature",
  "properties": {
    "addr:full":"Lotissement 11 - ZA de la Grave Carros Provence-Alpes-C\u00f4te d'Azur 06510",
    "addr:postcode":"06510",
    "addr:street":"Lotissement 11 Za De La Grave Carros",
    "iso:country":"FR",
    "sg:address":"Lotissement 11 - ZA de la Grave",
    "sg:city":"Carros",
    "sg:orig_category":"Non-Classified Establishments",
    "sg:phone":"+33 4 93 29 06 22",
    "sg:postcode":"06510",
    "sg:province":"Provence-Alpes-C\u00f4te d'Azur",
    "wof:name":"Neige Azur S.a.",
    "wof:placetype":"venue"
},
  "geometry": {"coordinates":[7.17573,43.785782],"type":"Point"}
}