{
  "type": "Feature",
  "properties": {
    "iso:country":"FR",
    "sg:address":"2 Avenue De La Corse 13007 Marseille",
    "sg:classifiers":[
        {
            "category":"Bakery",
            "type":"Food & Drink"
        }
    ],
    "sg:phone":"+33 4 91 33 23 02",
    "sg:province":"Poitou-Charentes",
    "sg:tags":[
        "cake",
        "product",
        "related",
        "bread"
    ],
    "wof:name":"Boulangerie-patisserie Saint- Victor",
    "wof:placetype":"venue"
},
  "geometry": {"coordinates":[5.366158,43.289883],"type":"Point"}
}