{
  "type": "Feature",
  "properties": {
    "addr:full":"Bd Imp\u00e9ratrice 62630 \u00c9taples Nord Pas-de-Calais",
    "addr:postcode":"62630",
    "addr:street":"Bd Impe\u0301Ratrice",
    "iso:country":"FR",
    "sg:address":"Bd Imp\u00e9ratrice 62630 \u00c9taples",
    "sg:classifiers":[
        {
            "category":"Marine",
            "type":"Transportation"
        }
    ],
    "sg:phone":"+33 3 21 94 72 77",
    "sg:province":"Nord Pas-de-Calais",
    "sg:tags":[
        "transport",
        "sea"
    ],
    "wof:name":"Cooperative Maritime Etaploise Organisation De Producteurs",
    "wof:placetype":"venue"
},
  "geometry": {"coordinates":[1.632485,50.516705],"type":"Point"}
}