{
  "type": "Feature",
  "properties": {
    "addr:full":"La Bourie 69610 Haute Rivoire Rhone-Alpes",
    "addr:postcode":"69610",
    "addr:street":"Rivoire Rhone-Alpes",
    "iso:country":"FR",
    "sg:address":"La Bourie 69610 Haute Rivoire",
    "sg:classifiers":[
        {
            "category":"Professional",
            "subcategory":"Advertising",
            "type":"Services"
        }
    ],
    "sg:phone":"+33 4 74 70 68 00",
    "sg:province":"Rhone-Alpes",
    "sg:tags":[
        "sign"
    ],
    "wof:name":"Prismaflex International S.a.",
    "wof:placetype":"venue"
},
  "geometry": {"coordinates":[4.395622,45.719273],"type":"Point"}
}