{
  "type": "Feature",
  "properties": {
    "addr:full":"49 Avenue Vauban 49000 Angers Pays de Loire 49000",
    "addr:housenumber":"49",
    "addr:postcode":"49000;49000",
    "addr:street":"Avenue Vauban",
    "iso:country":"FR",
    "sg:address":"49 Avenue Vauban 49000 Angers",
    "sg:classifiers":[
        {
            "category":"Health Services",
            "subcategory":"Podiatrist",
            "type":"Services"
        }
    ],
    "sg:phone":"+33 2 41 35 03 03",
    "sg:postcode":"49000",
    "sg:province":"Pays de Loire",
    "sg:tags":[
        "instrument",
        "measurement",
        "-",
        "precision",
        "equipment"
    ],
    "wof:name":"Robin Sa",
    "wof:placetype":"venue"
},
  "geometry": {"coordinates":[-0.559354,47.4599],"type":"Point"}
}