{
  "type": "Feature",
  "properties": {
    "addr:full":"ZI du Buisson Sarrazin B\u00e9theny Champagne 51450",
    "addr:postcode":"51450",
    "addr:street":"Zi Du Buisson Sarrazin;Champagne",
    "iso:country":"FR",
    "sg:address":"ZI du Buisson Sarrazin",
    "sg:city":"B\u00e9theny",
    "sg:orig_category":"Unclassifiable Establishments",
    "sg:phone":"+33 3 26 07 00 31",
    "sg:postcode":"51450",
    "sg:province":"Champagne",
    "wof:name":"Caillot Transport S.a.",
    "wof:placetype":"venue"
},
  "geometry": {"coordinates":[4.058745,49.286026],"type":"Point"}
}