{
  "type": "Feature",
  "properties": {
    "addr:full":"6 Rue Fontaine 77700 Serris Ile de France",
    "addr:housenumber":"6",
    "addr:postcode":"77700;ile",
    "addr:street":"Rue Fontaine",
    "iso:country":"FR",
    "sg:address":"6 Rue Fontaine 77700 Serris",
    "sg:classifiers":[
        {
            "category":"Utilities",
            "subcategory":"Telephone",
            "type":"Services"
        }
    ],
    "sg:phone":"+33 1 64 63 32 00",
    "sg:province":"Ile de France",
    "sg:tags":[
        "telecommunication"
    ],
    "wof:name":"Nyssa Sarl",
    "wof:placetype":"venue"
},
  "geometry": {"coordinates":[2.795302,48.844296],"type":"Point"}
}