{
  "type": "Feature",
  "properties": {
    "addr:full":"25 rue Chartraine; Evreux Haute Normandie",
    "addr:housenumber":"25",
    "addr:street":"Rue Chartraine;Haute Normandie",
    "iso:country":"FR",
    "sg:address":"25 rue Chartraine; Evreux",
    "sg:classifiers":[
        {
            "category":"Banks & Credit Unions",
            "subcategory":"Bank",
            "type":"Services"
        }
    ],
    "sg:phone":"+33 32295252",
    "sg:province":"Haute Normandie",
    "wof:name":"Cr\u00e9dit Du Nord",
    "wof:placetype":"venue"
},
  "geometry": {"coordinates":[1.148533,49.025337],"type":"Point"}
}