{
  "type": "Feature",
  "properties": {
    "addr:full":"Av. Delattre de Tassigny Oloron Sainte Marie Aquitaine 64400",
    "addr:postcode":"64400",
    "addr:street":"Av. Delattre De Tassigny",
    "iso:country":"FR",
    "sg:address":"Av. Delattre de Tassigny",
    "sg:city":"Oloron Sainte Marie",
    "sg:orig_category":"Unclassifiable Establishments",
    "sg:phone":"+33 5 59 88 88 88",
    "sg:postcode":"64400",
    "sg:province":"Aquitaine",
    "wof:name":"Lindt Et Sprungli S.a.",
    "wof:placetype":"venue"
},
  "geometry": {"coordinates":[-0.623837,43.197208],"type":"Point"}
}