{
  "type": "Feature",
  "properties": {
    "iso:country":"FR",
    "sg:address":"112 Rue La Bo\u00e9tie 75008 Paris",
    "sg:classifiers":[
        {
            "category":"Travel",
            "subcategory":"Hotels & Motels",
            "type":"Entertainment"
        }
    ],
    "sg:phone":"+33 1 42 25 93 39",
    "sg:postcode":"75008",
    "sg:province":"Ile de France",
    "sg:tags":[
        "hotels",
        "business",
        "restaurant"
    ],
    "wof:name":"Medioni Champs Elysees Sa",
    "wof:placetype":"venue"
},
  "geometry": {"coordinates":[2.307657,48.871719],"type":"Point"}
}