{
  "type": "Feature",
  "properties": {
    "addr:full":"35, Rue Coquilli\u00e8re, 75001 Paris Ile de France",
    "addr:housenumber":"35",
    "addr:postcode":"75001",
    "addr:street":"Rue Coquillie\u0300Re",
    "iso:country":"FR",
    "sg:address":"35, Rue Coquilli\u00e8re, 75001 Paris",
    "sg:orig_category":"Unclassifiable Establishments",
    "sg:phone":"+33 1 41 73 76 19",
    "sg:province":"Ile de France",
    "wof:name":"Oz Impex S.a.r.l.",
    "wof:placetype":"venue"
},
  "geometry": {"coordinates":[2.341187,48.864223],"type":"Point"}
}