{
  "type": "Feature",
  "properties": {
    "addr:full":"Rte de Beaupuy - ZI Nord Beaupuy Aquitaine 47200",
    "addr:postcode":"47200",
    "addr:street":"Rte De Beaupuy Zi Nord",
    "iso:country":"FR",
    "sg:address":"Rte de Beaupuy - ZI Nord",
    "sg:city":"Beaupuy",
    "sg:orig_category":"Unclassifiable Establishments",
    "sg:phone":"+33 5 53 64 21 71",
    "sg:postcode":"47200",
    "sg:province":"Aquitaine",
    "wof:name":"S.i.m.m. S.a.r.l.",
    "wof:placetype":"venue"
},
  "geometry": {"coordinates":[0.20874,44.447285],"type":"Point"}
}