{
  "type": "Feature",
  "properties": {
    "addr:full":"2, Rue Paul Lamgevim, 93270 Sevran Ile de France",
    "addr:housenumber":"2",
    "addr:postcode":"93270",
    "addr:street":"Rue Paul Lamgevim",
    "iso:country":"FR",
    "sg:address":"2, Rue Paul Lamgevim, 93270 Sevran",
    "sg:orig_category":"Unclassifiable Establishments",
    "sg:phone":"+33 1 49 36 55 55",
    "sg:province":"Ile de France",
    "wof:name":"B.e.m.a. S.a.",
    "wof:placetype":"venue"
},
  "geometry": {"coordinates":[2.528383,48.946495],"type":"Point"}
}