{
  "type": "Feature",
  "properties": {
    "addr:full":"5 Rue De L'Houmaille Zi Du Chevir\u00e9 44340 Bouguenais Pays de Loire",
    "addr:housenumber":"5",
    "addr:postcode":"44340",
    "addr:street":"Rue De L'Houmaille Zi Du Chevire\u0301",
    "iso:country":"FR",
    "sg:address":"5 Rue De L'Houmaille Zi Du Chevir\u00e9 44340 Bouguenais",
    "sg:classifiers":[
        {
            "category":"Manufacturing",
            "subcategory":"Wood Products",
            "type":"Manufacturing & Wholesale Goods"
        }
    ],
    "sg:phone":"+33 2 51 11 20 00",
    "sg:province":"Pays de Loire",
    "sg:tags":[
        "furniture"
    ],
    "wof:name":"Pbm",
    "wof:placetype":"venue"
},
  "geometry": {"coordinates":[-1.613565,47.188347],"type":"Point"}
}