{
  "type": "Feature",
  "properties": {
    "iso:country":"FR",
    "sg:address":"4, Rue Pascal, 69680 Chassieu",
    "sg:orig_category":"Non-Classified Establishments",
    "sg:phone":"+33 4 72 47 82 22",
    "sg:postcode":"69680",
    "sg:province":"Rhone-Alpes",
    "wof:name":"Kleinhuis France S.a.r.l.",
    "wof:placetype":"venue"
},
  "geometry": {"coordinates":[4.972535,45.722713],"type":"Point"}
}