{
  "type": "Feature",
  "properties": {
    "iso:country":"FR",
    "sg:address":"6, Rue Jouye Rouve, 75020 Paris",
    "sg:orig_category":"Non-Classified Establishments",
    "sg:phone":"+33 1 44 62 06 45",
    "sg:province":"Ile de France",
    "wof:name":"U.c.p. S.a.r.l. - Union Cartonnages Et Peaux",
    "wof:placetype":"venue"
},
  "geometry": {"coordinates":[2.382536,48.87302],"type":"Point"}
}