{
  "type": "Feature",
  "properties": {
    "addr:full":"20/24, Rue Gombert, 59042 Lille C\u00e9dex Nord-Pas-de-Calais",
    "addr:housenumber":"20 / 24",
    "addr:postcode":"59042",
    "addr:street":"Rue Gombert;Ce\u0301Dex",
    "iso:country":"FR",
    "sg:address":"20/24, Rue Gombert, 59042 Lille C\u00e9dex",
    "sg:orig_category":"Non-Classified Establishments",
    "sg:phone":"+33 3 59 00 12 12",
    "sg:province":"Nord-Pas-de-Calais",
    "wof:name":"Sycomore",
    "wof:placetype":"venue"
},
  "geometry": {"coordinates":[3.060668,50.633492],"type":"Point"}
}