{
  "type": "Feature",
  "properties": {
    "iso:country":"FR",
    "sg:address":"Rouffiac Zone Artisanale 48000 St Bauzile",
    "sg:classifiers":[
        {
            "category":"Home & Garden",
            "subcategory":"Furniture",
            "type":"Retail Goods"
        }
    ],
    "sg:phone":"+33 4 66 47 10 73",
    "sg:postcode":"48000",
    "sg:province":"Languedoc-Roussillon",
    "sg:tags":[
        "household",
        "wood"
    ],
    "wof:name":"Sarl Lozere Cuisines",
    "wof:placetype":"venue"
},
  "geometry": {"coordinates":[3.559072,44.456753],"type":"Point"}
}