{
  "type": "Feature",
  "properties": {
    "addr:full":"Galette 58500 Clamecy Clamecy Bourgogne 58500",
    "addr:postcode":"58500;58500",
    "addr:street":"Galette",
    "iso:country":"FR",
    "sg:address":"Galette 58500 Clamecy",
    "sg:city":"Clamecy",
    "sg:orig_category":"Unclassifiable Establishments",
    "sg:phone":"+33 3 86 27 18 86",
    "sg:postcode":"58500",
    "sg:province":"Bourgogne",
    "wof:name":"Sodex Richoux",
    "wof:placetype":"venue"
},
  "geometry": {"coordinates":[3.505825,47.456051],"type":"Point"}
}