{
  "type": "Feature",
  "properties": {
    "addr:full":"Rte de Sable - ZI de la Promenade Grez en Bou\u00e8re Pays de Loire 53290",
    "addr:postcode":"53290",
    "addr:street":"Rte De Sable Zi De La Promenade Grez En Boue\u0300Re Pays",
    "iso:country":"FR",
    "sg:address":"Rte de Sable - ZI de la Promenade",
    "sg:city":"Grez en Bou\u00e8re",
    "sg:orig_category":"Non-Classified Establishments",
    "sg:phone":"+33 2 43 70 67 95",
    "sg:postcode":"53290",
    "sg:province":"Pays de Loire",
    "wof:name":"Nord - Ouest D\u00e9laquage S.a.r.l.",
    "wof:placetype":"venue"
},
  "geometry": {"coordinates":[-0.546889,47.772057],"type":"Point"}
}