{
  "type": "Feature",
  "properties": {
    "iso:country":"FR",
    "sg:address":"21 Avenue De Lattre De Tassigny 94120 Fontenay Sous Bois",
    "sg:classifiers":[
        {
            "category":"Manufacturing",
            "subcategory":"Tools & Machinery",
            "type":"Manufacturing & Wholesale Goods"
        }
    ],
    "sg:phone":"+33 1 45 14 72 00",
    "sg:postcode":"94120",
    "sg:province":"Ile de France",
    "sg:tags":[
        "metallurgy",
        "metalworking"
    ],
    "wof:name":"Bricorama",
    "wof:placetype":"venue"
},
  "geometry": {"coordinates":[2.493443,48.853497],"type":"Point"}
}