{
  "type": "Feature",
  "properties": {
    "iso:country":"FR",
    "sg:address":"Parc Le Kl\u00e9ber 55 Bis Rue De Rennes 35510 Cesson S\u00e9vign\u00e9",
    "sg:city":"Cesson-S\u00e9vign\u00e9",
    "sg:classifiers":[
        {
            "category":"Shopping",
            "subcategory":"Computers & Home Electronics",
            "type":"Retail Goods"
        }
    ],
    "sg:phone":"+33 2 99 83 01 01",
    "sg:postcode":"35510",
    "sg:province":"Bretagne",
    "sg:tags":[
        "electronic",
        "electrical",
        "equipment"
    ],
    "wof:name":"Aster Ingenierie",
    "wof:placetype":"venue"
},
  "geometry": {"coordinates":[-1.624029,48.113888],"type":"Point"}
}