{
  "type": "Feature",
  "properties": {
    "addr:full":"3, Place Gabriel - Palais de la Bourse, 33075 Bordeaux C\u00e9dex Aquitaine",
    "addr:housenumber":"3",
    "addr:postcode":"33075",
    "addr:street":"Place Gabriel Palais De La Bourse",
    "iso:country":"FR",
    "sg:address":"3, Place Gabriel - Palais de la Bourse, 33075 Bordeaux C\u00e9dex",
    "sg:orig_category":"Non-Classified Establishments",
    "sg:phone":"+33 5 56 90 58 00",
    "sg:province":"Aquitaine",
    "wof:name":"Port Autonome De Bordeaux",
    "wof:placetype":"venue"
},
  "geometry": {"coordinates":[-0.54581,44.8027],"type":"Point"}
}