{
  "type": "Feature",
  "properties": {
    "addr:full":"15 c, Rue de l'Ancienne, 28380 Saint R\u00e9my sur Avre Saint-R\u00e9my-sur-Avre Centre 28380",
    "addr:housenumber":"15 c",
    "addr:postcode":"28380;28380",
    "addr:street":"Rue De L'Ancienne;Avre",
    "iso:country":"FR",
    "sg:address":"15 c, Rue de l'Ancienne, 28380 Saint R\u00e9my sur Avre",
    "sg:city":"Saint-R\u00e9my-sur-Avre",
    "sg:orig_category":"Unclassifiable Establishments",
    "sg:phone":"+33 2 37 48 95 77",
    "sg:postcode":"28380",
    "sg:province":"Centre",
    "wof:name":"S.i.t.r. S.a.r.l. - Soci\u00e9t\u00e9 Interventions Techniques Remoise",
    "wof:placetype":"venue"
},
  "geometry": {"coordinates":[1.243644,48.764641],"type":"Point"}
}