{
  "type": "Feature",
  "properties": {
    "addr:full":"13, Rue Henri Farmam - ZAC Charles de Gaulle, 93290 Tremblay en France Ile de France 93290",
    "addr:housenumber":"13",
    "addr:postcode":"93290;93290",
    "addr:street":"Rue Henri Farmam Zac Charles De Gaulle",
    "iso:country":"FR",
    "sg:address":"13, Rue Henri Farmam - ZAC Charles de Gaulle, 93290 Tremblay en France",
    "sg:orig_category":"Non-Classified Establishments",
    "sg:phone":"+33 1 49 63 42 00",
    "sg:postcode":"93290",
    "sg:province":"Ile de France",
    "wof:name":"Cerel S.a.",
    "wof:placetype":"venue"
},
  "geometry": {"coordinates":[2.56727,48.951214],"type":"Point"}
}