{
  "type": "Feature",
  "properties": {
    "addr:full":"45 avenue Victor Hugo 93300 Aubervilliers Ile de France 93300",
    "addr:housenumber":"45",
    "addr:postcode":"93300;93300",
    "addr:street":"Avenue Victor Hugo",
    "iso:country":"FR",
    "sg:address":"45 avenue Victor Hugo 93300 Aubervilliers",
    "sg:classifiers":[
        {
            "category":"Shopping",
            "subcategory":"Department Store",
            "type":"Retail Goods"
        }
    ],
    "sg:phone":"+33 1 49 37 16 17",
    "sg:postcode":"93300",
    "sg:province":"Ile de France",
    "sg:tags":[
        "linen",
        "bed"
    ],
    "wof:name":"Etablissements Max Et Fils Sa",
    "wof:placetype":"venue"
},
  "geometry": {"coordinates":[2.371089,48.90266],"type":"Point"}
}