{
  "type": "Feature",
  "properties": {
    "iso:country":"FR",
    "sg:address":"13 rue Saint-Honor\u00e9 78000 Versailles",
    "sg:classifiers":[
        {
            "category":"Shopping",
            "subcategory":"Stationery & Office Supplies",
            "type":"Retail Goods"
        }
    ],
    "sg:phone":"+33 1 34 76 33 44",
    "sg:province":"Ile de France",
    "sg:tags":[
        "packaging"
    ],
    "wof:name":"Dominique Baehr Diffusion Eurl",
    "wof:placetype":"venue"
},
  "geometry": {"coordinates":[2.125218,48.798161],"type":"Point"}
}