{
  "type": "Feature",
  "properties": {
    "addr:full":"32 B Boulevard Haussmann 75009 Paris Ile de France 75009",
    "addr:housenumber":"32 b",
    "addr:postcode":"75009;75009",
    "addr:street":"Boulevard Haussmann",
    "iso:country":"FR",
    "sg:address":"32 B Boulevard Haussmann 75009 Paris",
    "sg:classifiers":[
        {
            "category":"Professional",
            "subcategory":"Engineering",
            "type":"Services"
        }
    ],
    "sg:phone":"+33 1 55 33 53 80",
    "sg:postcode":"75009",
    "sg:province":"Ile de France",
    "sg:tags":[
        "machine",
        "-",
        "mechanical"
    ],
    "wof:name":"Batignoles Technologies Thermiques (btt)",
    "wof:placetype":"venue"
},
  "geometry": {"coordinates":[2.334275,48.872974],"type":"Point"}
}