{
  "type": "Feature",
  "properties": {
    "iso:country":"FR",
    "sg:address":"B.P. 66, 13752 Les Pennes Mirabeau C\u00e9dex^^13, Av. Lamartine - ZI l'Agavon, 13170 Les Pennes Mirabeau",
    "sg:orig_category":"Non-Classified Establishments",
    "sg:phone":"+33 4 42 02 12 02",
    "sg:province":"Poitou-Charentes",
    "wof:name":"Equiptec S.a.",
    "wof:placetype":"venue"
},
  "geometry": {"coordinates":[5.282638,43.417511],"type":"Point"}
}