{
  "type": "Feature",
  "properties": {
    "addr:full":"7, Rte d'Elsenheim, 67390 Marckolsheim Marckolsheim Alsace 67390",
    "addr:housenumber":"7",
    "addr:postcode":"67390;67390",
    "addr:street":"Rte D'Elsenheim",
    "iso:country":"FR",
    "sg:address":"7, Rte d'Elsenheim, 67390 Marckolsheim",
    "sg:city":"Marckolsheim",
    "sg:orig_category":"Unclassifiable Establishments",
    "sg:phone":"+33 3 88 58 61 00",
    "sg:postcode":"67390",
    "sg:province":"Alsace",
    "wof:name":"Schwind Charles S.a.",
    "wof:placetype":"venue"
},
  "geometry": {"coordinates":[7.50131,48.161331],"type":"Point"}
}