{
  "type": "Feature",
  "properties": {
    "iso:country":"FR",
    "sg:address":"La Barbiere 47300 Villeneuve Sur Lot",
    "sg:city":"Villeneuve-sur-Lot",
    "sg:classifiers":[
        {
            "category":"Manufacturing",
            "subcategory":"Building Materials",
            "type":"Manufacturing & Wholesale Goods"
        }
    ],
    "sg:phone":"+33 5 53 40 54 54",
    "sg:postcode":"47300",
    "sg:province":"Aquitaine",
    "sg:tags":[
        "decoration"
    ],
    "wof:name":"Alexander S.a.r.l.",
    "wof:placetype":"venue"
},
  "geometry": {"coordinates":[0.65937,44.359684],"type":"Point"}
}