{
  "type": "Feature",
  "properties": {
    "iso:country":"FR",
    "sg:address":"1, Rue de la For\u00eat, 02600 Villers Cotter\u00eats",
    "sg:orig_category":"Unclassifiable Establishments",
    "sg:phone":"+33 3 23 96 00 41",
    "sg:province":"Picardie",
    "wof:name":"Pantz Ernest E.u.r.l.",
    "wof:placetype":"venue"
},
  "geometry": {"coordinates":[3.085534,49.241096],"type":"Point"}
}