{
  "type": "Feature",
  "properties": {
    "addr:full":"120, Rue Carnot, 59150 Wattrelos Nord Pas-de-Calais",
    "addr:housenumber":"120",
    "addr:postcode":"59150",
    "addr:street":"Rue Carnot",
    "iso:country":"FR",
    "sg:address":"120, Rue Carnot, 59150 Wattrelos",
    "sg:orig_category":"Unclassifiable Establishments",
    "sg:phone":"+33 3 20 75 74 09",
    "sg:province":"Nord Pas-de-Calais",
    "wof:name":"Moulin Chimie S.a.r.l.",
    "wof:placetype":"venue"
},
  "geometry": {"coordinates":[3.209579,50.699146],"type":"Point"}
}