{
  "type": "Feature",
  "properties": {
    "addr:full":"20 Rue De La Gare 42490 Fraisses Rhone-Alpes 42490",
    "addr:housenumber":"20",
    "addr:postcode":"42490;42490",
    "addr:street":"Rue De La Gare;Rhone-Alpes",
    "iso:country":"FR",
    "sg:address":"20 Rue De La Gare 42490 Fraisses",
    "sg:classifiers":[
        {
            "category":"Manufacturing",
            "subcategory":"Metals",
            "type":"Manufacturing & Wholesale Goods"
        }
    ],
    "sg:phone":"+33 4 77 40 49 00",
    "sg:postcode":"42490",
    "sg:province":"Rhone-Alpes",
    "sg:tags":[
        "-",
        "machine",
        "equipment",
        "engineering",
        "machinery",
        "mechanical"
    ],
    "wof:name":"Akers Sa",
    "wof:placetype":"venue"
},
  "geometry": {"coordinates":[4.26445,45.392059],"type":"Point"}
}