{
  "type": "Feature",
  "properties": {
    "addr:full":"12, Rue Aristide Briand, 10300 Sainte Savine Champagne 10300",
    "addr:housenumber":"12",
    "addr:postcode":"10300;10300",
    "addr:street":"Rue Aristide Briand",
    "iso:country":"FR",
    "sg:address":"12, Rue Aristide Briand, 10300 Sainte Savine",
    "sg:orig_category":"Non-Classified Establishments",
    "sg:phone":"+33 3 25 79 26 87",
    "sg:postcode":"10300",
    "sg:province":"Champagne",
    "wof:name":"Colbert S.a.",
    "wof:placetype":"venue"
},
  "geometry": {"coordinates":[4.054368,48.292824],"type":"Point"}
}