{
  "type": "Feature",
  "properties": {
    "addr:full":"Centre Espace Performance Alphasis - B\u00e2t. S Saint Gr\u00e9goire C\u00e9dex Brittany 35769",
    "addr:housenumber":"ba\u0302t",
    "addr:postcode":"35769",
    "addr:street":"Saint;Ce\u0301Dex",
    "iso:country":"FR",
    "sg:address":"Centre Espace Performance Alphasis - B\u00e2t. S",
    "sg:city":"Saint Gr\u00e9goire C\u00e9dex",
    "sg:orig_category":"Non-Classified Establishments",
    "sg:phone":"+33 2 99 23 72 20",
    "sg:postcode":"35769",
    "sg:province":"Brittany",
    "wof:name":"I.t.i.s. S.a.r.l. - Innovation T\u00e9l\u00e9communication Image Et Son",
    "wof:placetype":"venue"
},
  "geometry": {"coordinates":[-1.68273,48.153191],"type":"Point"}
}