{
  "type": "Feature",
  "properties": {
    "iso:country":"FR",
    "sg:address":"18, Place des Reflets - Tour Aurore, 92975 Paris la D\u00e9fence C\u00e9dex",
    "sg:orig_category":"Non-Classified Establishments",
    "sg:phone":"+33 1 47 78 53 79",
    "sg:province":"Midi Pyr\u00e9n\u00e9es",
    "wof:name":"Tankafrica S.a.",
    "wof:placetype":"venue"
},
  "geometry": {"coordinates":[2.208,48.896141],"type":"Point"}
}