{
  "type": "Feature",
  "properties": {
    "addr:full":"Av Fran\u00e7ois Mitterrand Zi Ouest 17700 Surg\u00e8res Poitou-Charentes 17700",
    "addr:postcode":"17700;17700",
    "addr:street":"Av Franc\u0327Ois Mitterrand Zi Ouest",
    "iso:country":"FR",
    "sg:address":"Av Fran\u00e7ois Mitterrand Zi Ouest 17700 Surg\u00e8res",
    "sg:classifiers":[
        {
            "category":"Farming",
            "subcategory":"Livestock Farm",
            "type":"Manufacturing & Wholesale Goods"
        }
    ],
    "sg:phone":"+33 5 46 27 60 20",
    "sg:postcode":"17700",
    "sg:province":"Poitou-Charentes",
    "sg:tags":[
        "breeding",
        "agriculture",
        "animal"
    ],
    "wof:name":"Sibcas",
    "wof:placetype":"venue"
},
  "geometry": {"coordinates":[-0.690955,46.052395],"type":"Point"}
}