{
  "type": "Feature",
  "properties": {
    "addr:full":"1, Rond Point de la Nation, 21000 Dijon Dijon Bourgogne 21000",
    "addr:housenumber":"1",
    "addr:postcode":"21000;21000",
    "addr:street":"Rond Point De La Nation",
    "iso:country":"FR",
    "sg:address":"1, Rond Point de la Nation, 21000 Dijon",
    "sg:city":"Dijon",
    "sg:orig_category":"Unclassifiable Establishments",
    "sg:phone":"+33 3 80 70 44 01",
    "sg:postcode":"21000",
    "sg:province":"Bourgogne",
    "wof:name":"Caisse D'epargne De Bourgogne S.a.",
    "wof:placetype":"venue"
},
  "geometry": {"coordinates":[5.046143,47.347168],"type":"Point"}
}