{
  "type": "Feature",
  "properties": {
    "iso:country":"FR",
    "sg:address":"71/75, Rte de Noisy, 93230 Romainville",
    "sg:orig_category":"Non-Classified Establishments",
    "sg:phone":"+33 1 41 83 15 30",
    "sg:postcode":"93230",
    "sg:province":"Ile de France",
    "wof:name":"Boucherie Bif Bovic",
    "wof:placetype":"venue"
},
  "geometry": {"coordinates":[2.430913,48.894714],"type":"Point"}
}