{
  "type": "Feature",
  "properties": {
    "addr:full":"ZI d'Ecouflant Angers Pays de Loire 49000",
    "addr:postcode":"49000",
    "addr:street":"Angers",
    "iso:country":"FR",
    "sg:address":"ZI d'Ecouflant",
    "sg:city":"Angers",
    "sg:orig_category":"Unclassifiable Establishments",
    "sg:phone":"+33 2 41 60 20 02",
    "sg:postcode":"49000",
    "sg:province":"Pays de Loire",
    "wof:name":"R.e.m. Ressorts S.a.r.l.",
    "wof:placetype":"venue"
},
  "geometry": {"coordinates":[-0.52998,47.528549],"type":"Point"}
}