{
  "type": "Feature",
  "properties": {
    "addr:full":"Rue Aim\u00e9 Dubost 62670 Mazingarbe Nord Pas-de-Calais 62670",
    "addr:postcode":"62670;62670",
    "addr:street":"Rue Aime\u0301 Dubost",
    "iso:country":"FR",
    "sg:address":"Rue Aim\u00e9 Dubost 62670 Mazingarbe",
    "sg:classifiers":[
        {
            "category":"Building & Trades",
            "subcategory":"Landfill",
            "type":"Services"
        }
    ],
    "sg:phone":"+33 3 21 72 84 94",
    "sg:postcode":"62670",
    "sg:province":"Nord Pas-de-Calais",
    "sg:tags":[
        "fa\u00e7ades",
        "metal"
    ],
    "wof:name":"Technochim-france Sa",
    "wof:placetype":"venue"
},
  "geometry": {"coordinates":[2.72745,50.456074],"type":"Point"}
}