{
  "type": "Feature",
  "properties": {
    "iso:country":"FR",
    "sg:address":"Rte Hardanges",
    "sg:city":"Le Ribay",
    "sg:orig_category":"Unclassifiable Establishments",
    "sg:phone":"+33 2 43 03 90 43",
    "sg:postcode":"53640",
    "sg:province":"Pays de Loire",
    "wof:name":"Desnos S.a.r.l.",
    "wof:placetype":"venue"
},
  "geometry": {"coordinates":[-0.40201,48.336792],"type":"Point"}
}