{
  "type": "Feature",
  "properties": {
    "addr:full":"20 avenue Andr\u00e9 Malraux 92300 Levallois Perret Ile de France 92300",
    "addr:housenumber":"20",
    "addr:postcode":"92300;ile;92300",
    "addr:street":"Avenue Andre\u0301 Malraux;France",
    "iso:country":"FR",
    "sg:address":"20 avenue Andr\u00e9 Malraux 92300 Levallois Perret",
    "sg:classifiers":[
        {
            "category":"Professional",
            "subcategory":"Management & Consulting",
            "type":"Services"
        }
    ],
    "sg:phone":"+33 1 47 59 39 39",
    "sg:postcode":"92300",
    "sg:province":"Ile de France",
    "sg:tags":[
        "consultancy"
    ],
    "wof:name":"Hewitt Associates Sarl",
    "wof:placetype":"venue"
},
  "geometry": {"coordinates":[2.276257,48.896618],"type":"Point"}
}