{
  "type": "Feature",
  "properties": {
    "iso:country":"FR",
    "sg:address":"1, Place G\u00e9n\u00e9ral Joseph Guillaut, 31300 Toulouse",
    "sg:orig_category":"Unclassifiable Establishments",
    "sg:phone":"+33 5 62 74 48 00",
    "sg:province":"Midi Pyr\u00e9n\u00e9es",
    "wof:name":"Jet Multi M\u00e9dia Hosting S.a.",
    "wof:placetype":"venue"
},
  "geometry": {"coordinates":[1.408716,43.608448],"type":"Point"}
}