{
  "type": "Feature",
  "properties": {
    "addr:full":"43, Chemin de la Corv\u00e9e, 57050 Metz Lorraine",
    "addr:housenumber":"43",
    "addr:postcode":"57050",
    "addr:street":"Chemin De La Corve\u0301E",
    "iso:country":"FR",
    "sg:address":"43, Chemin de la Corv\u00e9e, 57050 Metz",
    "sg:orig_category":"Non-Classified Establishments",
    "sg:phone":"+33 3 87 30 35 47",
    "sg:province":"Lorraine",
    "wof:name":"Weistroffer S.a.r.l.",
    "wof:placetype":"venue"
},
  "geometry": {"coordinates":[6.151065,49.138767],"type":"Point"}
}