{
  "type": "Feature",
  "properties": {
    "addr:full":"1, Rte d'Eschau, 67400 Illkirch Graffenstaden Geispolsheim Alsace 67400",
    "addr:housenumber":"1",
    "addr:postcode":"67400;67400",
    "addr:street":"Rte D'Eschau",
    "iso:country":"FR",
    "sg:address":"1, Rte d'Eschau, 67400 Illkirch Graffenstaden",
    "sg:city":"Geispolsheim",
    "sg:orig_category":"Unclassifiable Establishments",
    "sg:phone":"+33 3 90 40 05 50",
    "sg:postcode":"67400",
    "sg:province":"Alsace",
    "wof:name":"Ruiu G\u00e9rald S.a.",
    "wof:placetype":"venue"
},
  "geometry": {"coordinates":[7.714686,48.512234],"type":"Point"}
}