{
  "type": "Feature",
  "properties": {
    "iso:country":"FR",
    "sg:address":"B.P. 42015, 62060 Arras C\u00e9dex 9^^ZAC Artoipole, 62000 Arras",
    "sg:orig_category":"Abattoirs, Installations et/ou appareils pour Co-produits animaux, Machines et/ou appareils pour le ",
    "sg:phone":"+33 3 21 55 36 00",
    "sg:postcode":"62000",
    "sg:province":"Nord Pas-de-Calais",
    "wof:name":"La M\u00e9canique Moderne S.a.",
    "wof:placetype":"venue"
},
  "geometry": {"coordinates":[2.77891,50.290989],"type":"Point"}
}