{
  "type": "Feature",
  "properties": {
    "iso:country":"FR",
    "sg:address":"53, Rue Yves Farge, 69700 Givors",
    "sg:orig_category":"Unclassifiable Establishments",
    "sg:phone":"+33 4 72 24 03 83",
    "sg:postcode":"69700",
    "sg:province":"Rhone-Alpes",
    "wof:name":"Pividal S.a.r.l.",
    "wof:placetype":"venue"
},
  "geometry": {"coordinates":[4.764793,45.593063],"type":"Point"}
}