{
  "type": "Feature",
  "properties": {
    "addr:full":"Za Mondeville Basse Normandie 14120",
    "addr:postcode":"14120",
    "addr:street":"Za Mondeville Basse",
    "iso:country":"FR",
    "sg:address":"Za",
    "sg:city":"Mondeville",
    "sg:classifiers":[
        {
            "category":"Wholesale",
            "subcategory":"Farm Supplies",
            "type":"Manufacturing & Wholesale Goods"
        }
    ],
    "sg:phone":"+33 2 31 84 24 42",
    "sg:postcode":"14120",
    "sg:province":"Basse Normandie",
    "sg:tags":[
        "-",
        "machine",
        "equipment",
        "engineering",
        "machinery",
        "mechanical",
        "agriculture"
    ],
    "wof:name":"Etablissements Monrocq Sa",
    "wof:placetype":"venue"
},
  "geometry": {"coordinates":[-0.318344,49.178711],"type":"Point"}
}