{
  "type": "Feature",
  "properties": {
    "addr:full":"B.P. 8, 94440 Villecresnes^^52, Rue de Brunoy, 94440 Villecresnes Ile de France",
    "addr:housenumber":"8",
    "addr:postcode":"94440;94440;ile",
    "addr:street":"B.P.;Rue De Brunoy",
    "iso:country":"FR",
    "sg:address":"B.P. 8, 94440 Villecresnes^^52, Rue de Brunoy, 94440 Villecresnes",
    "sg:orig_category":"Non-Classified Establishments",
    "sg:phone":"+33 1 45 69 85 16",
    "sg:province":"Ile de France",
    "wof:name":"Modern Plastic S.a.r.l.",
    "wof:placetype":"venue"
},
  "geometry": {"coordinates":[2.53346,48.721809],"type":"Point"}
}