{
  "type": "Feature",
  "properties": {
    "iso:country":"FR",
    "sg:address":"Rte de Bastia - Porette",
    "sg:city":"Porto Vecchio",
    "sg:orig_category":"Non-Classified Establishments",
    "sg:phone":"+33 4 95 70 94 40",
    "sg:postcode":"20137",
    "sg:province":"Corse",
    "wof:name":"D Cash Corses S.n.c.",
    "wof:placetype":"venue"
},
  "geometry": {"coordinates":[9.27852,41.592529],"type":"Point"}
}