{
  "type": "Feature",
  "properties": {
    "iso:country":"FR",
    "sg:address":"Zone Juliette - 132 D Orly Fret 840",
    "sg:city":"Orly C\u00e9dex",
    "sg:orig_category":"Non-Classified Establishments",
    "sg:phone":"+33 1 49 75 31 06",
    "sg:postcode":"94549",
    "sg:province":"Ile de France",
    "wof:name":"Qualitair S.a.",
    "wof:placetype":"venue"
},
  "geometry": {"coordinates":[2.40116,48.742931],"type":"Point"}
}