{
  "type": "Feature",
  "properties": {
    "iso:country":"FR",
    "sg:address":"Zoo p\u00f4le",
    "sg:city":"Ploufragan",
    "sg:orig_category":"Non-Classified Establishments",
    "sg:phone":"+33 2 96 76 58 22",
    "sg:postcode":"22440",
    "sg:province":"Bretagne",
    "wof:name":"R.v. Biotech E.u.r.l.",
    "wof:placetype":"venue"
},
  "geometry": {"coordinates":[-2.793585,48.48938],"type":"Point"}
}