{
  "type": "Feature",
  "properties": {
    "addr:full":"545, Av de Lattre de Tassigny, 39300 Champagnole Franche Comt\u00e9",
    "addr:housenumber":"545",
    "addr:postcode":"39300",
    "addr:street":"Av De Lattre De Tassigny;Franche Comte\u0301",
    "iso:country":"FR",
    "sg:address":"545, Av de Lattre de Tassigny, 39300 Champagnole",
    "sg:orig_category":"Unclassifiable Establishments",
    "sg:phone":"+33 3 84 53 07 77",
    "sg:province":"Franche Comt\u00e9",
    "wof:name":"Jouef S.a.r.l.",
    "wof:placetype":"venue"
},
  "geometry": {"coordinates":[5.921138,46.74778],"type":"Point"}
}