{
  "type": "Feature",
  "properties": {
    "addr:full":"Zi 64130 Maul\u00e9on Soule Ainharp Aquitaine 64130",
    "addr:postcode":"64130;64130",
    "addr:street":"Zi",
    "iso:country":"FR",
    "sg:address":"Zi 64130 Maul\u00e9on Soule",
    "sg:city":"Ainharp",
    "sg:classifiers":[
        {
            "category":"Shopping",
            "subcategory":"Luggage & Leather Goods",
            "type":"Retail Goods"
        }
    ],
    "sg:phone":"+33 5 59 28 28 18",
    "sg:postcode":"64130",
    "sg:province":"Aquitaine",
    "sg:tags":[
        "shoe"
    ],
    "wof:name":"Don Quichosse Sarl",
    "wof:placetype":"venue"
},
  "geometry": {"coordinates":[-0.933393,43.148788],"type":"Point"}
}