{
  "type": "Feature",
  "properties": {
    "iso:country":"FR",
    "sg:address":"Rte de Villersexel",
    "sg:city":"Bart",
    "sg:orig_category":"Non-Classified Establishments",
    "sg:phone":"+33 3 81 90 35 43",
    "sg:postcode":"25420",
    "sg:province":"Franche Comt\u00e9",
    "wof:name":"Barbier S.a.",
    "wof:placetype":"venue"
},
  "geometry": {"coordinates":[6.765181,47.473015],"type":"Point"}
}