{
  "type": "Feature",
  "properties": {
    "addr:full":"19 rue Saint Jacques; Douai Nord Pas-de-Calais",
    "addr:housenumber":"19",
    "addr:street":"Rue Saint Jacques Douai Nord",
    "iso:country":"FR",
    "sg:address":"19 rue Saint Jacques; Douai",
    "sg:classifiers":[
        {
            "category":"Banks & Credit Unions",
            "subcategory":"Bank",
            "type":"Services"
        }
    ],
    "sg:phone":"+33 3 27 87 34 40",
    "sg:province":"Nord Pas-de-Calais",
    "wof:name":"Banque Scalbert, Dupont Sa",
    "wof:placetype":"venue"
},
  "geometry": {"coordinates":[3.083117,50.370529],"type":"Point"}
}