{
  "type": "Feature",
  "properties": {
    "addr:full":"CD 212 - ZAC Les Ribes Aubi\u00e8re Auvergne 63170",
    "addr:housenumber":"cd 212",
    "addr:postcode":"63170",
    "addr:street":"Zac Les",
    "iso:country":"FR",
    "sg:address":"CD 212 - ZAC Les Ribes",
    "sg:city":"Aubi\u00e8re",
    "sg:orig_category":"Unclassifiable Establishments",
    "sg:phone":"+33 4 73 27 23 25",
    "sg:postcode":"63170",
    "sg:province":"Auvergne",
    "wof:name":"Brendani S.a.",
    "wof:placetype":"venue"
},
  "geometry": {"coordinates":[3.110975,45.7509],"type":"Point"}
}