{
  "type": "Feature",
  "properties": {
    "addr:full":"13, Rue des Lanternniers, 57000 Metz Lorraine",
    "addr:housenumber":"13",
    "addr:postcode":"57000",
    "addr:street":"Rue Des Lanternniers",
    "iso:country":"FR",
    "sg:address":"13, Rue des Lanternniers, 57000 Metz",
    "sg:orig_category":"Unclassifiable Establishments",
    "sg:phone":"+33 3 87 75 20 05",
    "sg:province":"Lorraine",
    "wof:name":"Buro Prestations S.a.r.l.",
    "wof:placetype":"venue"
},
  "geometry": {"coordinates":[6.183995,49.07645],"type":"Point"}
}