{
  "type": "Feature",
  "properties": {
    "iso:country":"FR",
    "sg:address":"5 Rue Saint-Roch 75001 Paris",
    "sg:classifiers":[
        {
            "category":"Shopping",
            "subcategory":"Clothing, Apparel, & Fashions",
            "type":"Retail Goods"
        }
    ],
    "sg:phone":"+33 1 42 60 54 58",
    "sg:postcode":"75001",
    "sg:province":"Ile de France",
    "sg:tags":[
        "textile",
        "clothing",
        "clothes"
    ],
    "wof:name":"Fourrures Roger Gerko",
    "wof:placetype":"venue"
},
  "geometry": {"coordinates":[2.331428,48.864418],"type":"Point"}
}