{
  "type": "Feature",
  "properties": {
    "addr:full":"24, Rue Alfred Saury - ZAC de Francazal, 31270 Cugnaux Midi Pyr\u00e9n\u00e9es 31270",
    "addr:housenumber":"24",
    "addr:postcode":"31270;31270",
    "addr:street":"Rue Alfred Saury Zac De Francazal",
    "iso:country":"FR",
    "sg:address":"24, Rue Alfred Saury - ZAC de Francazal, 31270 Cugnaux",
    "sg:orig_category":"Non-Classified Establishments",
    "sg:phone":"+33 5 62 87 32 87",
    "sg:postcode":"31270",
    "sg:province":"Midi Pyr\u00e9n\u00e9es",
    "wof:name":"Danzas S.a.",
    "wof:placetype":"venue"
},
  "geometry": {"coordinates":[1.34424,43.536976],"type":"Point"}
}