{
  "type": "Feature",
  "properties": {
    "addr:full":"78 rue de Provence 75009 Paris Ile de France 75009",
    "addr:housenumber":"78",
    "addr:postcode":"75009;75009",
    "addr:street":"Rue De Provence",
    "iso:country":"FR",
    "sg:address":"78 rue de Provence 75009 Paris",
    "sg:classifiers":[
        {
            "category":"Building & Trades",
            "subcategory":"Equipment Rental",
            "type":"Services"
        }
    ],
    "sg:phone":"+33 1 44 53 83 83",
    "sg:postcode":"75009",
    "sg:province":"Ile de France",
    "sg:tags":[
        "industrial",
        "maintenance"
    ],
    "wof:name":"Eparco Sa",
    "wof:placetype":"venue"
},
  "geometry": {"coordinates":[2.331559,48.874378],"type":"Point"}
}