{
  "type": "Feature",
  "properties": {
    "addr:full":"Avenue Robert Schuman 78500 Sartrouville Ile de France 78500",
    "addr:postcode":"78500;ile;78500",
    "addr:street":"Avenue Robert Schuman;France",
    "iso:country":"FR",
    "sg:address":"Avenue Robert Schuman 78500 Sartrouville",
    "sg:classifiers":[
        {
            "category":"Home & Garden",
            "subcategory":"Furniture",
            "type":"Retail Goods"
        }
    ],
    "sg:phone":"+33 1 30 86 79 79",
    "sg:postcode":"78500",
    "sg:province":"Ile de France",
    "sg:tags":[
        "household",
        "wood"
    ],
    "wof:name":"Fly Meubles",
    "wof:placetype":"venue"
},
  "geometry": {"coordinates":[2.191525,48.947506],"type":"Point"}
}