{
  "type": "Feature",
  "properties": {
    "iso:country":"FR",
    "sg:address":"26 Rue De La Fontaine 68300 St Louis",
    "sg:city":"Saint-Louis",
    "sg:classifiers":[
        {
            "category":"Airport",
            "type":"Transportation"
        }
    ],
    "sg:phone":"+33 3 89 70 14 44",
    "sg:postcode":"68300",
    "sg:province":"Alsace",
    "sg:tags":[
        "transport",
        "air"
    ],
    "wof:name":"A M S Airlines Management Services Sa",
    "wof:placetype":"venue"
},
  "geometry": {"coordinates":[7.558276,47.579975],"type":"Point"}
}