{
  "type": "Feature",
  "properties": {
    "iso:country":"FR",
    "sg:address":"Place du 11 Novembre",
    "sg:city":"Dinan",
    "sg:orig_category":"Unclassifiable Establishments",
    "sg:phone":"+33 2 96 39 21 05",
    "sg:postcode":"22100",
    "sg:province":"Bretagne",
    "wof:name":"Tourisme Verney S.a.",
    "wof:placetype":"venue"
},
  "geometry": {"coordinates":[-2.052543,48.456905],"type":"Point"}
}