{
  "type": "Feature",
  "properties": {
    "addr:full":"7, Av. Raymond Feraud, 06200 Nice Champagne",
    "addr:postcode":"06200",
    "addr:street":"Av. Raymond Feraud",
    "iso:country":"FR",
    "sg:address":"7, Av. Raymond Feraud, 06200 Nice",
    "sg:orig_category":"Unclassifiable Establishments",
    "sg:phone":"+33 4 93 18 88 88",
    "sg:province":"Champagne",
    "wof:name":"Miraglia S.a.",
    "wof:placetype":"venue"
},
  "geometry": {"coordinates":[7.229295,43.682121],"type":"Point"}
}