{
  "type": "Feature",
  "properties": {
    "addr:full":"Ld La Fontenelle 71290 Cuisery Cuisery Bourgogne 71290",
    "addr:postcode":"71290;71290",
    "addr:street":"Ld La Fontenelle",
    "iso:country":"FR",
    "sg:address":"Ld La Fontenelle 71290 Cuisery",
    "sg:city":"Cuisery",
    "sg:classifiers":[
        {
            "category":"Professional",
            "type":"Services"
        }
    ],
    "sg:phone":"+33 3 85 27 01 50",
    "sg:postcode":"71290",
    "sg:province":"Bourgogne",
    "sg:tags":[
        "transport",
        "road"
    ],
    "wof:name":"Transports Cartier Sarl",
    "wof:placetype":"venue"
},
  "geometry": {"coordinates":[4.951675,46.516216],"type":"Point"}
}