{
  "type": "Feature",
  "properties": {
    "addr:full":"B.P. 2, 02000 Chavignon^^16, Rue L\u00e9on Paquin, 02000 Chavignon Picardie 02000",
    "addr:housenumber":"2",
    "addr:postcode":"02000;02000;02000",
    "addr:street":"B.P.;Rue Le\u0301On Paquin;Picardie",
    "iso:country":"FR",
    "sg:address":"B.P. 2, 02000 Chavignon^^16, Rue L\u00e9on Paquin, 02000 Chavignon",
    "sg:orig_category":"Non-Classified Establishments",
    "sg:phone":"+33 3 23 21 61 03",
    "sg:postcode":"02000",
    "sg:province":"Picardie",
    "wof:name":"C.m.l. S.a.r.l. - Constructions M\u00e9talliques Lefranc",
    "wof:placetype":"venue"
},
  "geometry": {"coordinates":[3.524935,49.479332],"type":"Point"}
}