{
  "type": "Feature",
  "properties": {
    "iso:country":"FR",
    "sg:address":"46, Rue des Gravilliers, 75003 Paris",
    "sg:orig_category":"Non-Classified Establishments",
    "sg:phone":"+33 1 42 72 37 35",
    "sg:postcode":"75003",
    "sg:province":"Ile de France",
    "wof:name":"B.j. Baranes Et Compagnie Sarl",
    "wof:placetype":"venue"
},
  "geometry": {"coordinates":[2.355914,48.864208],"type":"Point"}
}