{
  "type": "Feature",
  "properties": {
    "addr:full":"26 Avenue Vercors 26120 Malissard Rhone-Alpes 26120",
    "addr:housenumber":"26",
    "addr:postcode":"26120;26120",
    "addr:street":"Avenue Vercors;Rhone-Alpes",
    "iso:country":"FR",
    "sg:address":"26 Avenue Vercors 26120 Malissard",
    "sg:classifiers":[
        {
            "category":"Wholesale",
            "subcategory":"Medical Equipment & Supplies",
            "type":"Manufacturing & Wholesale Goods"
        }
    ],
    "sg:phone":"+33 4 75 85 27 05",
    "sg:postcode":"26120",
    "sg:province":"Rhone-Alpes",
    "sg:tags":[
        "instrument",
        "health",
        "-",
        "precision"
    ],
    "wof:name":"Vivares Sarl",
    "wof:placetype":"venue"
},
  "geometry": {"coordinates":[4.958481,44.901031],"type":"Point"}
}