{
  "type": "Feature",
  "properties": {
    "addr:full":"ZA des Cartelets Coullons Centre 45720",
    "addr:housenumber":"coullons",
    "addr:postcode":"45720",
    "addr:street":"Za Des Cartelets",
    "iso:country":"FR",
    "sg:address":"ZA des Cartelets",
    "sg:city":"Coullons",
    "sg:orig_category":"Unclassifiable Establishments",
    "sg:phone":"+33 2 38 29 20 22",
    "sg:postcode":"45720",
    "sg:province":"Centre",
    "wof:name":"C.e.g. Sologne S.a.",
    "wof:placetype":"venue"
},
  "geometry": {"coordinates":[2.492695,47.621101],"type":"Point"}
}