{
  "type": "Feature",
  "properties": {
    "addr:full":"16 Rue Romains 67110 Reichshoffen Reichshoffen Alsace 67110",
    "addr:housenumber":"16",
    "addr:postcode":"67110;67110",
    "addr:street":"Rue Romains",
    "iso:country":"FR",
    "sg:address":"16 Rue Romains 67110 Reichshoffen",
    "sg:city":"Reichshoffen",
    "sg:classifiers":[
        {
            "category":"Professional",
            "subcategory":"Engineering",
            "type":"Services"
        }
    ],
    "sg:phone":"+33 3 88 80 80 45",
    "sg:postcode":"67110",
    "sg:province":"Alsace",
    "sg:tags":[
        "machine",
        "-",
        "mechanical"
    ],
    "wof:name":"Tecline Sa",
    "wof:placetype":"venue"
},
  "geometry": {"coordinates":[7.670729,48.931217],"type":"Point"}
}