{
  "type": "Feature",
  "properties": {
    "addr:full":"17 boulevard Amp\u00e8re 13014 Marseille Provence-Alpes-C\u00f4te d'Azur",
    "addr:housenumber":"17",
    "addr:postcode":"13014",
    "addr:street":"Boulevard Ampe\u0300Re",
    "iso:country":"FR",
    "sg:address":"17 boulevard Amp\u00e8re 13014 Marseille",
    "sg:classifiers":[
        {
            "category":"Professional",
            "type":"Services"
        }
    ],
    "sg:phone":"+33 4 91 58 38 29",
    "sg:province":"Provence-Alpes-C\u00f4te d'Azur",
    "sg:tags":[
        "transport"
    ],
    "wof:name":"Sertransit Sa",
    "wof:placetype":"venue"
},
  "geometry": {"coordinates":[5.373127,43.338264],"type":"Point"}
}