{
  "type": "Feature",
  "properties": {
    "addr:full":"84, RN 37, 62450 Avesnes les Bapaume Nord Pas-de-Calais",
    "addr:housenumber":"84",
    "addr:postcode":"62450",
    "addr:street":"Rn 37",
    "iso:country":"FR",
    "sg:address":"84, RN 37, 62450 Avesnes les Bapaume",
    "sg:orig_category":"Unclassifiable Establishments",
    "sg:phone":"+33 3 21 59 55 36",
    "sg:province":"Nord Pas-de-Calais",
    "wof:name":"Larius France Coprom S.a.r.l.",
    "wof:placetype":"venue"
},
  "geometry": {"coordinates":[2.84946,50.10318],"type":"Point"}
}