{
  "type": "Feature",
  "properties": {
    "iso:country":"FR",
    "sg:address":"90",
    "sg:city":"Bertherigues; Barbentane",
    "sg:classifiers":[
        {
            "category":"Banks & Credit Unions",
            "subcategory":"Bank",
            "type":"Services"
        }
    ],
    "sg:phone":"+33 3390955003",
    "sg:province":"Rhone-Alpes",
    "wof:name":"Banque Chaix",
    "wof:placetype":"venue"
},
  "geometry": {"coordinates":[4.754439,43.900589],"type":"Point"}
}