{
  "type": "Feature",
  "properties": {
    "iso:country":"FR",
    "sg:address":"B.P. 63, 95612 Cergy Pontoise c\u00e9dex^^37, Av. du Gros Ch\u00eane - Parc Tech. d'Eragny, 95000 Cergy",
    "sg:orig_category":"Non-Classified Establishments",
    "sg:phone":"+33 1 34 21 85 85",
    "sg:province":"Ile de France",
    "wof:name":"Herv\u00e9 Thermique S.a.",
    "wof:placetype":"venue"
},
  "geometry": {"coordinates":[2.119302,49.023186],"type":"Point"}
}