{
  "type": "Feature",
  "properties": {
    "iso:country":"FR",
    "sg:address":"12, Rue Maubert, 41600 Nouan le Fuzelier",
    "sg:city":"Chaon",
    "sg:orig_category":"Non-Classified Establishments",
    "sg:phone":"+33 2 54 88 77 54",
    "sg:postcode":"41600",
    "sg:province":"Centre",
    "wof:name":"Vildy Bois S.a.r.l.",
    "wof:placetype":"venue"
},
  "geometry": {"coordinates":[2.036445,47.537266],"type":"Point"}
}