{
  "type": "Feature",
  "properties": {
    "addr:full":"B.P. 15, 54210 Ville en Vermois^^Rte de Saint Nicolas, 54210 Ville en Vermois Lorraine",
    "addr:postcode":"54210;54210",
    "addr:street":"B.P. 15;Ville En Vermois^^Rte De Saint Nicolas;Ville En Vermois",
    "iso:country":"FR",
    "sg:address":"B.P. 15, 54210 Ville en Vermois^^Rte de Saint Nicolas, 54210 Ville en Vermois",
    "sg:orig_category":"Non-Classified Establishments",
    "sg:phone":"+33 3 83 46 77 77",
    "sg:province":"Lorraine",
    "wof:name":"S.d.o. S.a. - S\u00e9lection Disc Organisation",
    "wof:placetype":"venue"
},
  "geometry": {"coordinates":[6.30159,48.631104],"type":"Point"}
}