{
  "type": "Feature",
  "properties": {
    "addr:full":"21 Av Jean Jaur\u00e8s 05000 Gap Champagne",
    "addr:postcode":"05000",
    "addr:street":"21 Av Jean Jaure\u0300S",
    "iso:country":"FR",
    "sg:address":"21 Av Jean Jaur\u00e8s 05000 Gap",
    "sg:classifiers":[
        {
            "category":"Professional",
            "type":"Services"
        }
    ],
    "sg:phone":"+33 4 92 53 93 13",
    "sg:province":"Champagne",
    "sg:tags":[
        "transport",
        "road"
    ],
    "wof:name":"Marcellin Et Cie Sarl",
    "wof:placetype":"venue"
},
  "geometry": {"coordinates":[6.073995,44.554134],"type":"Point"}
}