{
  "type": "Feature",
  "properties": {
    "addr:full":"2, Rue Saint Etienne, 42400 Saint Chamond Rhone-Alpes",
    "addr:housenumber":"2",
    "addr:postcode":"42400",
    "addr:street":"Rue Saint Etienne;Chamond Rhone-Alpes",
    "iso:country":"FR",
    "sg:address":"2, Rue Saint Etienne, 42400 Saint Chamond",
    "sg:orig_category":"Unclassifiable Establishments",
    "sg:phone":"+33 4 77 22 02 72",
    "sg:province":"Rhone-Alpes",
    "wof:name":"Etablissement Lathuilli\u00e8re S.a.r.l.",
    "wof:placetype":"venue"
},
  "geometry": {"coordinates":[4.506919,45.47208],"type":"Point"}
}