{
  "type": "Feature",
  "properties": {
    "iso:country":"FR",
    "sg:address":"B.P. 41535, 44315 Nantes C\u00e9dex 03^^17, Rue de la Petite Baratte, 44300 Nantes",
    "sg:orig_category":"Non-Classified Establishments",
    "sg:phone":"+33 2 40 68 10 10",
    "sg:province":"Pays de Loire",
    "wof:name":"S.d.e.c.c.i. S.a. - Saunier Duval Eau Chaude Chauffage Industrie",
    "wof:placetype":"venue"
},
  "geometry": {"coordinates":[-1.5359,47.25631],"type":"Point"}
}