{
  "type": "Feature",
  "properties": {
    "addr:full":"44, Av des Champs Elys\u00e9es, 02500 Hirson Picardie",
    "addr:postcode":"02500",
    "addr:street":"44 Av Des Champs Elyse\u0301Es",
    "iso:country":"FR",
    "sg:address":"44, Av des Champs Elys\u00e9es, 02500 Hirson",
    "sg:orig_category":"Unclassifiable Establishments",
    "sg:phone":"+33 3 23 58 16 13",
    "sg:province":"Picardie",
    "wof:name":"Modelage M\u00e9canique S.a.r.l.",
    "wof:placetype":"venue"
},
  "geometry": {"coordinates":[4.08786,49.913452],"type":"Point"}
}