{
  "type": "Feature",
  "properties": {
    "addr:full":"44, Rue Jacquard - ZI, 77400 Lagny sur Marne Ile de France",
    "addr:housenumber":"44",
    "addr:postcode":"77400",
    "addr:street":"Rue Jacquard Zi",
    "iso:country":"FR",
    "sg:address":"44, Rue Jacquard - ZI, 77400 Lagny sur Marne",
    "sg:orig_category":"Unclassifiable Establishments",
    "sg:phone":"+33 1 64 12 71 00",
    "sg:province":"Ile de France",
    "wof:name":"Bodycote Hit S.a.",
    "wof:placetype":"venue"
},
  "geometry": {"coordinates":[2.701485,48.87775],"type":"Point"}
}