{
  "type": "Feature",
  "properties": {
    "iso:country":"FR",
    "sg:address":"2, Rue Faisan Dor\u00e9, 94370 Sucy en Brie",
    "sg:orig_category":"Non-Classified Establishments",
    "sg:phone":"+33 1 45 90 67 22",
    "sg:province":"Ile de France",
    "wof:name":"Imag' In Photogravure S.a.r.l.",
    "wof:placetype":"venue"
},
  "geometry": {"coordinates":[2.550469,48.757915],"type":"Point"}
}