{
  "type": "Feature",
  "properties": {
    "addr:full":"B.P. 1, 88500 Mattaincourt^^65, Rue du G\u00e9n\u00e9ral Leclerc, 88500 Mattaincourt Lorraine 88500",
    "addr:housenumber":"1",
    "addr:postcode":"88500;88500;88500",
    "addr:street":"B.P.;Rue Du Ge\u0301Ne\u0301Ral Leclerc",
    "iso:country":"FR",
    "sg:address":"B.P. 1, 88500 Mattaincourt^^65, Rue du G\u00e9n\u00e9ral Leclerc, 88500 Mattaincourt",
    "sg:orig_category":"Non-Classified Establishments",
    "sg:phone":"+33 3 29 37 12 44",
    "sg:postcode":"88500",
    "sg:province":"Lorraine",
    "wof:name":"Ateliers Du Madon S.a.r.l.",
    "wof:placetype":"venue"
},
  "geometry": {"coordinates":[6.12538,48.318459],"type":"Point"}
}