{
  "type": "Feature",
  "properties": {
    "iso:country":"FR",
    "sg:address":"6 Rue Despourrins 64000 Pau",
    "sg:city":"Pau",
    "sg:classifiers":[
        {
            "category":"Professional",
            "subcategory":"Printing & Photocopies",
            "type":"Services"
        }
    ],
    "sg:phone":"+33 5 59 82 20 00",
    "sg:postcode":"64000",
    "sg:province":"Aquitaine",
    "sg:tags":[
        "publishing"
    ],
    "wof:name":"La R\u00c9publique Des Pyr\u00c9n\u00c9es",
    "wof:placetype":"venue"
},
  "geometry": {"coordinates":[-0.366646,43.299294],"type":"Point"}
}