{
  "type": "Feature",
  "properties": {
    "addr:full":"Av. du 11 Novembre Sainte Foy de Peyroli\u00e8res Midi Pyr\u00e9n\u00e9es 31470",
    "addr:postcode":"31470",
    "addr:street":"Av. Du 11 Novembre;Foy;Peyrolie\u0300Res",
    "iso:country":"FR",
    "sg:address":"Av. du 11 Novembre",
    "sg:city":"Sainte Foy de Peyroli\u00e8res",
    "sg:orig_category":"Unclassifiable Establishments",
    "sg:phone":"+33 5 34 47 01 17",
    "sg:postcode":"31470",
    "sg:province":"Midi Pyr\u00e9n\u00e9es",
    "wof:name":"Jabil Circuit Inc S.a.r.l.",
    "wof:placetype":"venue"
},
  "geometry": {"coordinates":[1.145995,43.493141],"type":"Point"}
}