{
  "type": "Feature",
  "properties": {
    "iso:country":"FR",
    "sg:address":"7 Rue Des Artisans 37300 Joue Les Tours",
    "sg:city":"Jou\u00e9-l\u00e8s-Tours",
    "sg:classifiers":[
        {
            "category":"Building & Trades",
            "subcategory":"Electrical",
            "type":"Services"
        }
    ],
    "sg:phone":"+33 2 47 67 80 25",
    "sg:postcode":"37300",
    "sg:province":"Centre",
    "sg:tags":[
        "electronic",
        "lighting",
        "equipment"
    ],
    "wof:name":"Citeos",
    "wof:placetype":"venue"
},
  "geometry": {"coordinates":[0.642345,47.34132],"type":"Point"}
}