{
  "type": "Feature",
  "properties": {
    "addr:full":"195 Rte De La Gare 40420 Labrit Labrit Aquitaine 40420",
    "addr:housenumber":"195",
    "addr:postcode":"40420;40420",
    "addr:street":"Rte De La Gare",
    "iso:country":"FR",
    "sg:address":"195 Rte De La Gare 40420 Labrit",
    "sg:city":"Labrit",
    "sg:classifiers":[
        {
            "category":"Shopping",
            "subcategory":"Luggage & Leather Goods",
            "type":"Retail Goods"
        }
    ],
    "sg:phone":"+33 5 58 51 05 57",
    "sg:postcode":"40420",
    "sg:province":"Aquitaine",
    "sg:tags":[
        "shoe"
    ],
    "wof:name":"Baby Love",
    "wof:placetype":"venue"
},
  "geometry": {"coordinates":[-0.548653,44.106647],"type":"Point"}
}