{
  "type": "Feature",
  "properties": {
    "iso:country":"FR",
    "sg:address":"Z.I. St Maurice 04101 MANOSQUE CEDEX",
    "sg:classifiers":[
        {
            "category":"Military Area",
            "subcategory":"Air Force Base",
            "type":"Public Place"
        }
    ],
    "sg:phone":"+33 4 92 72 66 48",
    "sg:province":"Aquitaine",
    "sg:tags":[
        "aviat",
        "rotor",
        "propellers",
        "blade",
        "variable-pitch"
    ],
    "wof:name":"Technic Aviation Sa",
    "wof:placetype":"venue"
},
  "geometry": {"coordinates":[5.784205,43.831474],"type":"Point"}
}