{
  "type": "Feature",
  "properties": {
    "iso:country":"FR",
    "sg:address":"57, Chemin du Vieux Ch\u00eane, 38240 Meylan",
    "sg:orig_category":"Non-Classified Establishments",
    "sg:phone":"+33 4 76 18 12 80",
    "sg:postcode":"38240",
    "sg:province":"Rhone-Alpes",
    "wof:name":"I.m.s. France S.a.r.l. - Integrated Measurement Systems",
    "wof:placetype":"venue"
},
  "geometry": {"coordinates":[5.795813,45.208771],"type":"Point"}
}