{
  "type": "Feature",
  "properties": {
    "iso:country":"FR",
    "sg:address":"Rte de Briac\u00e9 - ZA",
    "sg:city":"Le Landreau",
    "sg:orig_category":"Unclassifiable Establishments",
    "sg:phone":"+33 2 28 21 80 80",
    "sg:postcode":"44430",
    "sg:province":"Pays de Loire",
    "wof:name":"Butrot S.a.r.l.",
    "wof:placetype":"venue"
},
  "geometry": {"coordinates":[-1.343374,47.195854],"type":"Point"}
}