{
  "type": "Feature",
  "properties": {
    "iso:country":"FR",
    "sg:address":"47 rue de Feuchy 62223 Feuchy",
    "sg:classifiers":[
        {
            "category":"Manufacturing",
            "subcategory":"Motor Vehicles & Parts",
            "type":"Manufacturing & Wholesale Goods"
        }
    ],
    "sg:phone":"+33 3 21 55 36 00",
    "sg:province":"Nord Pas-de-Calais",
    "sg:tags":[
        "precision",
        "mechanic"
    ],
    "wof:name":"La Mecanique Moderne S.a.",
    "wof:placetype":"venue"
},
  "geometry": {"coordinates":[2.851609,50.281368],"type":"Point"}
}