{
  "type": "Feature",
  "properties": {
    "addr:full":"3 Rue La Bo\u00e9tie Paris Ile de France 75008",
    "addr:housenumber":"3",
    "addr:postcode":"75008",
    "addr:street":"Rue La Boe\u0301Tie",
    "iso:country":"FR",
    "sg:address":"3 Rue La Bo\u00e9tie",
    "sg:city":"Paris",
    "sg:classifiers":[
        {
            "category":"Banks & Credit Unions",
            "subcategory":"Financial Services",
            "type":"Services"
        }
    ],
    "sg:phone":"+33 1 44 94 24 24",
    "sg:postcode":"75008",
    "sg:province":"Ile de France",
    "sg:tags":[
        "banking",
        "finance",
        "insurance"
    ],
    "wof:name":"Credit Immobilier Europeen",
    "wof:placetype":"venue"
},
  "geometry": {"coordinates":[2.319078,48.874363],"type":"Point"}
}