{
  "type": "Feature",
  "properties": {
    "iso:country":"FR",
    "sg:address":"95, Bd d'Alsace Lorraine, 64000 Pau",
    "sg:city":"Pau",
    "sg:orig_category":"Unclassifiable Establishments",
    "sg:phone":"+33 5 59 32 48 39",
    "sg:postcode":"64000",
    "sg:province":"Aquitaine",
    "wof:name":"Domo Services Maintenance S.a.",
    "wof:placetype":"venue"
},
  "geometry": {"coordinates":[-0.34327,43.321529],"type":"Point"}
}