{
  "type": "Feature",
  "properties": {
    "addr:full":"91 Rue Tabuteau 78530 Buc Ile de France 78530",
    "addr:housenumber":"91",
    "addr:postcode":"78530;ile;78530",
    "addr:street":"Rue Tabuteau;France",
    "iso:country":"FR",
    "sg:address":"91 Rue Tabuteau 78530 Buc",
    "sg:classifiers":[
        {
            "category":"Shopping",
            "subcategory":"Hobbies, Toys, & Games",
            "type":"Retail Goods"
        }
    ],
    "sg:phone":"+33 1 39 56 06 07",
    "sg:postcode":"78530",
    "sg:province":"Ile de France",
    "sg:tags":[
        "product",
        "miscellaneous",
        "entertainment"
    ],
    "wof:name":"Asmodee Editions",
    "wof:placetype":"venue"
},
  "geometry": {"coordinates":[2.123375,48.763367],"type":"Point"}
}