{
  "type": "Feature",
  "properties": {
    "iso:country":"FR",
    "sg:address":"rue de la Grange aux Bois 57070 Metz",
    "sg:classifiers":[
        {
            "category":"Home & Garden",
            "subcategory":"Furniture",
            "type":"Retail Goods"
        }
    ],
    "sg:phone":"+33 3 87 75 13 16",
    "sg:postcode":"57070",
    "sg:province":"Lorraine",
    "sg:tags":[
        "living",
        "room"
    ],
    "wof:name":"Metz - Congr\u00e8s Association",
    "wof:placetype":"venue"
},
  "geometry": {"coordinates":[6.234319,49.085644],"type":"Point"}
}