{
  "type": "Feature",
  "properties": {
    "iso:country":"FR",
    "sg:address":"92603 Asni\u00e8res C\u00e9dex^^9/11, Rue Hector G. Fontaine, 92600 Asni\u00e8res sur Seine",
    "sg:orig_category":"Non-Classified Establishments",
    "sg:phone":"+33 1 41 32 17 32",
    "sg:postcode":"92600",
    "sg:province":"Ile de France",
    "wof:name":"Etablisements Charles Garnier S.a.",
    "wof:placetype":"venue"
},
  "geometry": {"coordinates":[2.289035,48.910294],"type":"Point"}
}