{
  "type": "Feature",
  "properties": {
    "addr:full":"117, Av. de Palavas, 34000 Montpellier Languedoc-Roussillon",
    "addr:postcode":"34000",
    "addr:street":"117 Av. De Palavas",
    "iso:country":"FR",
    "sg:address":"117, Av. de Palavas, 34000 Montpellier",
    "sg:orig_category":"Non-Classified Establishments",
    "sg:phone":"+33 4 67 22 15 45",
    "sg:province":"Languedoc-Roussillon",
    "wof:name":"S\u00e9curifrance S.a.",
    "wof:placetype":"venue"
},
  "geometry": {"coordinates":[3.890267,43.591103],"type":"Point"}
}