{
  "type": "Feature",
  "properties": {
    "addr:full":"Bd du Parc Villi\u00e9 Morgon Rhone-Alpes 69910",
    "addr:postcode":"69910",
    "addr:street":"Bd Du Parc;Rhone-Alpes",
    "iso:country":"FR",
    "sg:address":"Bd du Parc",
    "sg:city":"Villi\u00e9 Morgon",
    "sg:orig_category":"Non-Classified Establishments",
    "sg:phone":"+33 4 74 69 10 56",
    "sg:postcode":"69910",
    "sg:province":"Rhone-Alpes",
    "wof:name":"Laboratoire O\u00e9nologique Le Morgon S.a.r.l.",
    "wof:placetype":"venue"
},
  "geometry": {"coordinates":[4.678289,46.159992],"type":"Point"}
}