{
  "type": "Feature",
  "properties": {
    "addr:full":"59, Av. Cl\u00e9ment D\u00e9sormes, 01400 Ch\u00e2tillon sur Chalaronne Rhone-Alpes 01400",
    "addr:postcode":"01400;01400",
    "addr:street":"59 Av. Cle\u0301Ment De\u0301Sormes;Rhone-Alpes",
    "iso:country":"FR",
    "sg:address":"59, Av. Cl\u00e9ment D\u00e9sormes, 01400 Ch\u00e2tillon sur Chalaronne",
    "sg:orig_category":"Non-Classified Establishments",
    "sg:phone":"+33 4 74 55 10 91",
    "sg:postcode":"01400",
    "sg:province":"Rhone-Alpes",
    "wof:name":"Entreprise Dumay Bernard",
    "wof:placetype":"venue"
},
  "geometry": {"coordinates":[4.95964,46.117634],"type":"Point"}
}