{
  "type": "Feature",
  "properties": {
    "addr:full":"500, Rue Cl\u00e9ment Ader, 78530 Buc Ile de France",
    "addr:housenumber":"500",
    "addr:postcode":"78530;ile",
    "addr:street":"Rue Cle\u0301Ment Ader",
    "iso:country":"FR",
    "sg:address":"500, Rue Cl\u00e9ment Ader, 78530 Buc",
    "sg:orig_category":"Unclassifiable Establishments",
    "sg:phone":"+33 1 39 56 20 66",
    "sg:province":"Ile de France",
    "wof:name":"Prodif S.a.",
    "wof:placetype":"venue"
},
  "geometry": {"coordinates":[2.121226,48.761311],"type":"Point"}
}