{
  "type": "Feature",
  "properties": {
    "addr:full":"Lieu Dit Solerieux 18800 Baugy Baugy Centre 18800",
    "addr:housenumber":"baugy",
    "addr:postcode":"18800;18800",
    "addr:street":"Lieu Dit Solerieux",
    "iso:country":"FR",
    "sg:address":"Lieu Dit Solerieux 18800 Baugy",
    "sg:city":"Baugy",
    "sg:classifiers":[
        {
            "category":"Shopping",
            "subcategory":"Clothing, Apparel, & Fashions",
            "type":"Retail Goods"
        }
    ],
    "sg:phone":"+33 2 48 68 52 83",
    "sg:postcode":"18800",
    "sg:province":"Centre",
    "sg:tags":[
        "textile",
        "clothing",
        "clothes"
    ],
    "wof:name":"M 2c Confection",
    "wof:placetype":"venue"
},
  "geometry": {"coordinates":[2.798375,47.03038],"type":"Point"}
}