{
  "type": "Feature",
  "properties": {
    "addr:full":"7, Rue Emile Beley, 25460 Etupes Franche Comt\u00e9",
    "addr:housenumber":"7",
    "addr:postcode":"25460",
    "addr:street":"Rue Emile Beley;Franche Comte\u0301",
    "iso:country":"FR",
    "sg:address":"7, Rue Emile Beley, 25460 Etupes",
    "sg:orig_category":"Non-Classified Establishments",
    "sg:phone":"+33 3 81 94 11 22",
    "sg:province":"Franche Comt\u00e9",
    "wof:name":"Vauthier Et Compagnie S.a.",
    "wof:placetype":"venue"
},
  "geometry": {"coordinates":[6.86091,47.506245],"type":"Point"}
}