{
  "type": "Feature",
  "properties": {
    "addr:full":"164, Chemin de balme - Espace des Berthilliers, 71850 Charnay l\u00e8s M\u00e2con Charnay-l\u00e8s-M\u00e2con Bourgogne 71850",
    "addr:housenumber":"164",
    "addr:postcode":"71850;71850",
    "addr:street":"Chemin De Balme Espace Des Berthilliers",
    "iso:country":"FR",
    "sg:address":"164, Chemin de balme - Espace des Berthilliers, 71850 Charnay l\u00e8s M\u00e2con",
    "sg:city":"Charnay-l\u00e8s-M\u00e2con",
    "sg:orig_category":"Unclassifiable Establishments",
    "sg:phone":"+33 3 85 20 02 00",
    "sg:postcode":"71850",
    "sg:province":"Bourgogne",
    "wof:name":"Alg\u00e9co S.a.",
    "wof:placetype":"venue"
},
  "geometry": {"coordinates":[4.811808,46.308296],"type":"Point"}
}