{
  "type": "Feature",
  "properties": {
    "iso:country":"FR",
    "sg:address":"B.P. 10058, 57102 Thionville C\u00e9dex^^Rue du Donjon, 57100 Thionville",
    "sg:orig_category":"Non-Classified Establishments",
    "sg:phone":"+33 3 82 59 60 70",
    "sg:postcode":"57100",
    "sg:province":"Lorraine",
    "wof:name":"C.a.t. A.p.e.i. De Thionville",
    "wof:placetype":"venue"
},
  "geometry": {"coordinates":[6.16909,49.357601],"type":"Point"}
}