{
  "type": "Feature",
  "properties": {
    "addr:full":"32, Rue Godot de Mauroy, 75009 Paris Ile de France",
    "addr:housenumber":"32",
    "addr:postcode":"75009",
    "addr:street":"Rue Godot De Mauroy",
    "iso:country":"FR",
    "sg:address":"32, Rue Godot de Mauroy, 75009 Paris",
    "sg:orig_category":"Unclassifiable Establishments",
    "sg:phone":"+33 1 47 42 52 66",
    "sg:province":"Ile de France",
    "wof:name":"Pillet Hand Prostheses France S.a.r.l.",
    "wof:placetype":"venue"
},
  "geometry": {"coordinates":[2.327582,48.87215],"type":"Point"}
}