{
  "type": "Feature",
  "properties": {
    "addr:full":"2, Place Patton, 50300 Avranches Avranches Basse Normandie 50300",
    "addr:housenumber":"2",
    "addr:postcode":"50300;50300",
    "addr:street":"Place Patton",
    "iso:country":"FR",
    "sg:address":"2, Place Patton, 50300 Avranches",
    "sg:city":"Avranches",
    "sg:orig_category":"Unclassifiable Establishments",
    "sg:phone":"+33 2 33 58 53 08",
    "sg:postcode":"50300",
    "sg:province":"Basse Normandie",
    "wof:name":"Gr\u00e9ta Sud Manche",
    "wof:placetype":"venue"
},
  "geometry": {"coordinates":[-1.356966,48.682068],"type":"Point"}
}