{
  "type": "Feature",
  "properties": {
    "iso:country":"FR",
    "sg:address":"26 Rue Du Bois D Oly Zac D Augny Actisud Dunil 57685 Augny",
    "sg:classifiers":[
        {
            "category":"Shopping",
            "subcategory":"Hobbies, Toys, & Games",
            "type":"Retail Goods"
        }
    ],
    "sg:phone":"+33 3 87 38 39 99",
    "sg:province":"Lorraine",
    "sg:tags":[
        "product",
        "miscellaneous",
        "entertainment"
    ],
    "wof:name":"Sa La Kermesse",
    "wof:placetype":"venue"
},
  "geometry": {"coordinates":[6.122042,49.058556],"type":"Point"}
}