{
  "type": "Feature",
  "properties": {
    "addr:full":"6 Rue Marius Vivier Merle Zi 69200 Venissieux Rhone-Alpes",
    "addr:housenumber":"6",
    "addr:postcode":"69200",
    "addr:street":"Rue Marius Vivier",
    "iso:country":"FR",
    "sg:address":"6 Rue Marius Vivier Merle Zi 69200 Venissieux",
    "sg:classifiers":[
        {
            "category":"Wholesale",
            "subcategory":"Meat",
            "type":"Manufacturing & Wholesale Goods"
        }
    ],
    "sg:phone":"+33 4 72 90 05 50",
    "sg:province":"Rhone-Alpes",
    "sg:tags":[
        "food",
        "cooked",
        "product",
        "related"
    ],
    "wof:name":"Charcuterie Anselm Sarl",
    "wof:placetype":"venue"
},
  "geometry": {"coordinates":[4.90164,45.693451],"type":"Point"}
}