{
  "type": "Feature",
  "properties": {
    "iso:country":"FR",
    "sg:address":"7 Rue Henri Becquerel",
    "sg:city":"Rueil Malmaison",
    "sg:classifiers":[
        {
            "category":"Banks & Credit Unions",
            "subcategory":"Financial Services",
            "type":"Services"
        }
    ],
    "sg:phone":"+33 1 47 16 65 00",
    "sg:postcode":"92500",
    "sg:province":"Ile de France",
    "sg:tags":[
        "banking",
        "finance",
        "insurance"
    ],
    "wof:name":"Tem Groupe Brandt",
    "wof:placetype":"venue"
},
  "geometry": {"coordinates":[2.172986,48.889339],"type":"Point"}
}