{
  "type": "Feature",
  "properties": {
    "addr:full":"124, Bd du Mar\u00e9chal Leclerc, 33000 Bordeaux Bordeaux Aquitaine 33000",
    "addr:housenumber":"124",
    "addr:postcode":"33000;33000",
    "addr:street":"Bd Du Mare\u0301Chal Leclerc",
    "iso:country":"FR",
    "sg:address":"124, Bd du Mar\u00e9chal Leclerc, 33000 Bordeaux",
    "sg:city":"Bordeaux",
    "sg:orig_category":"Unclassifiable Establishments",
    "sg:phone":"+33 5 56 96 33 05",
    "sg:postcode":"33000",
    "sg:province":"Aquitaine",
    "wof:name":"Bricard S.a.",
    "wof:placetype":"venue"
},
  "geometry": {"coordinates":[-0.592619,44.827747],"type":"Point"}
}