{
  "type": "Feature",
  "properties": {
    "iso:country":"FR",
    "sg:address":"Rte des Avalloirs",
    "sg:city":"Saint L\u00e9onard des Bois",
    "sg:orig_category":"Unclassifiable Establishments",
    "sg:phone":"+33 2 43 31 44 44",
    "sg:postcode":"72590",
    "sg:province":"Pays de Loire",
    "wof:name":"Touring H\u00f4tel",
    "wof:placetype":"venue"
},
  "geometry": {"coordinates":[-98.206367,18.982199],"type":"Point"}
}