{
  "type": "Feature",
  "properties": {
    "addr:full":"Parc Europ\u00e9en d'Entreprises 63200 Riom Riom Auvergne 63200",
    "addr:postcode":"63200;63200",
    "iso:country":"FR",
    "sg:address":"Parc Europ\u00e9en d'Entreprises 63200 Riom",
    "sg:city":"Riom",
    "sg:classifiers":[
        {
            "category":"Real Estate",
            "subcategory":"Surveying",
            "type":"Services"
        }
    ],
    "sg:phone":"+33 4 73 64 53 33",
    "sg:postcode":"63200",
    "sg:province":"Auvergne",
    "sg:tags":[
        "material",
        "handling",
        "automation"
    ],
    "wof:name":"S.c.a.t.e. Sa",
    "wof:placetype":"venue"
},
  "geometry": {"coordinates":[3.12211,45.912579],"type":"Point"}
}