{
  "type": "Feature",
  "properties": {
    "addr:full":"2, Rue de l' Industrie - ZI, 45550 Saint Denis de l'H\u00f4tel Centre",
    "addr:housenumber":"2",
    "addr:postcode":"45550",
    "addr:street":"Rue De L ' Industrie Zi",
    "iso:country":"FR",
    "sg:address":"2, Rue de l' Industrie - ZI, 45550 Saint Denis de l'H\u00f4tel",
    "sg:orig_category":"Unclassifiable Establishments",
    "sg:phone":"+33 2 38 46 31 31",
    "sg:province":"Centre",
    "wof:name":"Caruelle Nicolas S.a.",
    "wof:placetype":"venue"
},
  "geometry": {"coordinates":[2.12803,47.874748],"type":"Point"}
}