{
  "type": "Feature",
  "properties": {
    "addr:full":"1 Rue Jean Veron 77500 Chelles Ile de France 77500",
    "addr:housenumber":"1",
    "addr:postcode":"77500;ile;77500",
    "addr:street":"Rue Jean Veron;France",
    "iso:country":"FR",
    "sg:address":"1 Rue Jean Veron 77500 Chelles",
    "sg:classifiers":[
        {
            "category":"Professional",
            "subcategory":"Business Services",
            "type":"Services"
        }
    ],
    "sg:phone":"+33 1 64 72 43 50",
    "sg:postcode":"77500",
    "sg:province":"Ile de France",
    "sg:tags":[
        "training",
        "advice"
    ],
    "wof:name":"Association Gasnier Guy",
    "wof:placetype":"venue"
},
  "geometry": {"coordinates":[2.594472,48.88047],"type":"Point"}
}