{
  "type": "Feature",
  "properties": {
    "iso:country":"FR",
    "sg:address":"12 Rue Luxembourg 51420 BERRU",
    "sg:classifiers":[
        {
            "category":"Food & Beverages",
            "subcategory":"Liquor & Beverages",
            "type":"Retail Goods"
        }
    ],
    "sg:phone":"+33 3 26 03 22 46",
    "sg:postcode":"51420",
    "sg:province":"Champagne",
    "sg:tags":[
        "champagne"
    ],
    "wof:name":"Champagne Picard Jacques Sarl",
    "wof:placetype":"venue"
},
  "geometry": {"coordinates":[4.154643,49.272293],"type":"Point"}
}