{
  "type": "Feature",
  "properties": {
    "addr:full":"Av Des D\u00e9port\u00e9s 60600 Clermont Picardie 60600",
    "addr:postcode":"60600;60600",
    "addr:street":"Av Des De\u0301Porte\u0301S",
    "iso:country":"FR",
    "sg:address":"Av Des D\u00e9port\u00e9s 60600 Clermont",
    "sg:classifiers":[
        {
            "category":"Building & Trades",
            "subcategory":"Construction",
            "type":"Services"
        }
    ],
    "sg:phone":"+33 3 44 78 45 51",
    "sg:postcode":"60600",
    "sg:province":"Picardie",
    "sg:tags":[
        "work",
        "public"
    ],
    "wof:name":"Appia Oise",
    "wof:placetype":"venue"
},
  "geometry": {"coordinates":[2.41947,49.384575],"type":"Point"}
}