{
  "type": "Feature",
  "properties": {
    "addr:full":"Rue Des Silos 62910 Moulle Nord Pas-de-Calais 62910",
    "addr:postcode":"62910;62910",
    "addr:street":"Rue Des Silos",
    "iso:country":"FR",
    "sg:address":"Rue Des Silos 62910 Moulle",
    "sg:classifiers":[
        {
            "category":"Utilities",
            "type":"Services"
        }
    ],
    "sg:phone":"+33 810 43 14 31",
    "sg:postcode":"62910",
    "sg:province":"Nord Pas-de-Calais",
    "sg:tags":[
        "raw",
        "energy",
        "material"
    ],
    "wof:name":"Lyonnaise Des Eaux France",
    "wof:placetype":"venue"
},
  "geometry": {"coordinates":[2.15271,50.8046],"type":"Point"}
}