{
  "type": "Feature",
  "properties": {
    "addr:full":"9, Rue Buffault, 75009 Paris Ile de France",
    "addr:housenumber":"9",
    "addr:postcode":"75009",
    "addr:street":"Rue Buffault",
    "iso:country":"FR",
    "sg:address":"9, Rue Buffault, 75009 Paris",
    "sg:orig_category":"Unclassifiable Establishments",
    "sg:phone":"+33 1 44 63 08 82",
    "sg:province":"Ile de France",
    "wof:name":"Nabousson S.a.r.l.",
    "wof:placetype":"venue"
},
  "geometry": {"coordinates":[2.341641,48.875584],"type":"Point"}
}