{
  "type": "Feature",
  "properties": {
    "addr:full":"4, Rue Sombreuse, 60800 Ormoy Villers Picardie",
    "addr:housenumber":"4",
    "addr:postcode":"60800",
    "addr:street":"Rue Sombreuse",
    "iso:country":"FR",
    "sg:address":"4, Rue Sombreuse, 60800 Ormoy Villers",
    "sg:orig_category":"Non-Classified Establishments",
    "sg:phone":"+33 3 44 21 22 31",
    "sg:province":"Picardie",
    "wof:name":"Senco Dosage S.a.r.l.",
    "wof:placetype":"venue"
},
  "geometry": {"coordinates":[2.838634,49.197323],"type":"Point"}
}