{
  "type": "Feature",
  "properties": {
    "addr:full":"72, Bd Aristide Briand, 77000 Melun Ile de France 77000",
    "addr:housenumber":"72",
    "addr:postcode":"77000;ile;77000",
    "addr:street":"Bd Aristide Briand;France",
    "iso:country":"FR",
    "sg:address":"72, Bd Aristide Briand, 77000 Melun",
    "sg:orig_category":"Non-Classified Establishments",
    "sg:phone":"+33 1 64 71 92 92",
    "sg:postcode":"77000",
    "sg:province":"Ile de France",
    "wof:name":"Creyf's S.g.s.",
    "wof:placetype":"venue"
},
  "geometry": {"coordinates":[2.651136,48.545368],"type":"Point"}
}