{
  "type": "Feature",
  "properties": {
    "iso:country":"FR",
    "sg:address":"Chemin de Cassel\u00e8vres - ZI de la Pointe",
    "sg:city":"Saint Jory",
    "sg:orig_category":"Unclassifiable Establishments",
    "sg:phone":"+33 5 62 22 99 22",
    "sg:postcode":"31790",
    "sg:province":"Midi Pyr\u00e9n\u00e9es",
    "wof:name":"C.m.t. S.a. - Compagnie Des Moteurs Et Transmissions",
    "wof:placetype":"venue"
},
  "geometry": {"coordinates":[1.37073,43.741692],"type":"Point"}
}