{
  "type": "Feature",
  "properties": {
    "addr:full":"BP 389; Charleville-Mezihres; 08106 CEDEX Vill\u00e9 Alsace 67220",
    "addr:housenumber":"389",
    "addr:postcode":"08106 cedex ville\u0301;67220",
    "addr:street":"Charleville-Mezihres",
    "iso:country":"FR",
    "sg:address":"BP 389; Charleville-Mezihres; 08106 CEDEX",
    "sg:city":"Vill\u00e9",
    "sg:classifiers":[
        {
            "category":"Shopping",
            "subcategory":"Computers & Home Electronics",
            "type":"Retail Goods"
        }
    ],
    "sg:phone":"+33 3 24 56 62 62",
    "sg:postcode":"67220",
    "sg:province":"Alsace",
    "sg:tags":[
        "chamber",
        "commerce"
    ],
    "wof:name":"Chambre De Commerce De Charleville-mezihres",
    "wof:placetype":"venue"
},
  "geometry": {"coordinates":[4.71944,49.77087],"type":"Point"}
}