{
  "type": "Feature",
  "properties": {
    "addr:full":"15, Rue des Pas Perdus, 95800 Cergy Ile de France",
    "addr:housenumber":"15",
    "addr:postcode":"95800;ile",
    "addr:street":"Rue Des Pas Perdus",
    "iso:country":"FR",
    "sg:address":"15, Rue des Pas Perdus, 95800 Cergy",
    "sg:orig_category":"Unclassifiable Establishments",
    "sg:phone":"+33 1 30 38 14 00",
    "sg:province":"Ile de France",
    "wof:name":"Phonactions S.a.r.l.",
    "wof:placetype":"venue"
},
  "geometry": {"coordinates":[2.033288,49.049698],"type":"Point"}
}