{
  "type": "Feature",
  "properties": {
    "iso:country":"FR",
    "sg:address":"Rue Aristide Berges 17180 P\u00e9rigny",
    "sg:classifiers":[
        {
            "category":"Wholesale",
            "subcategory":"Machinery & Supplies",
            "type":"Manufacturing & Wholesale Goods"
        }
    ],
    "sg:phone":"+33 5 46 44 31 33",
    "sg:postcode":"17180",
    "sg:province":"Poitou-Charentes",
    "sg:tags":[
        "handling",
        "material",
        "-",
        "machine",
        "equipment",
        "engineering",
        "mechanical"
    ],
    "wof:name":"Alpha Levage Sa",
    "wof:placetype":"venue"
},
  "geometry": {"coordinates":[-1.101595,46.164436],"type":"Point"}
}