{
  "type": "Feature",
  "properties": {
    "addr:full":"Bd Du Pr\u00e9sident Salvador Allende 30900 N\u00eemes Languedoc-Roussillon 30900",
    "addr:postcode":"30900;30900",
    "addr:street":"Bd Du Pre\u0301Sident Salvador Allende",
    "iso:country":"FR",
    "sg:address":"Bd Du Pr\u00e9sident Salvador Allende 30900 N\u00eemes",
    "sg:classifiers":[
        {
            "category":"Travel",
            "subcategory":"Hotels & Motels",
            "type":"Entertainment"
        }
    ],
    "sg:phone":"+33 4 66 38 13 84",
    "sg:postcode":"30900",
    "sg:province":"Languedoc-Roussillon",
    "sg:tags":[
        "hotels",
        "business",
        "restaurant"
    ],
    "wof:name":"Inter Hotel Nimotel",
    "wof:placetype":"venue"
},
  "geometry": {"coordinates":[4.386475,43.834061],"type":"Point"}
}