{
  "type": "Feature",
  "properties": {
    "addr:full":"A\u00e9rodrome D'Albertville 73460 Tournon Rhone-Alpes 73460",
    "addr:postcode":"73460;73460",
    "iso:country":"FR",
    "sg:address":"A\u00e9rodrome D'Albertville 73460 Tournon",
    "sg:classifiers":[
        {
            "category":"Professional",
            "subcategory":"Business Services",
            "type":"Services"
        }
    ],
    "sg:phone":"+33 4 79 38 47 47",
    "sg:postcode":"73460",
    "sg:province":"Rhone-Alpes",
    "sg:tags":[
        "travel",
        "-",
        "transport",
        "air"
    ],
    "wof:name":"Saf Industries",
    "wof:placetype":"venue"
},
  "geometry": {"coordinates":[6.31755,45.64423],"type":"Point"}
}