{
  "type": "Feature",
  "properties": {
    "iso:country":"FR",
    "sg:address":"43 chemin du Vieux Ch\u00eane 38240 Meylan",
    "sg:classifiers":[
        {
            "category":"Professional",
            "subcategory":"Computer Services",
            "type":"Services"
        }
    ],
    "sg:phone":"+33 4 76 41 73 33",
    "sg:province":"Rhone-Alpes",
    "sg:tags":[
        "engineering",
        "software"
    ],
    "wof:name":"Delta Consultants Sa",
    "wof:placetype":"venue"
},
  "geometry": {"coordinates":[5.79624,45.208054],"type":"Point"}
}