{
  "type": "Feature",
  "properties": {
    "iso:country":"FR",
    "sg:address":"Grand'Rue - Z.A.",
    "sg:city":"Walheim",
    "sg:orig_category":"Unclassifiable Establishments",
    "sg:phone":"+33 3 89 40 19 62",
    "sg:postcode":"68130",
    "sg:province":"Alsace",
    "wof:name":"Dover Doors",
    "wof:placetype":"venue"
},
  "geometry": {"coordinates":[7.264326,47.639767],"type":"Point"}
}