{
  "type": "Feature",
  "properties": {
    "iso:country":"FR",
    "sg:address":"163, Rue Pelleport, 75020 Paris",
    "sg:orig_category":"Unclassifiable Establishments",
    "sg:phone":"+33 1 44 62 70 10",
    "sg:province":"Ile de France",
    "wof:name":"C.2.m S.a - Marketing Communication Management",
    "wof:placetype":"venue"
},
  "geometry": {"coordinates":[2.397697,48.874607],"type":"Point"}
}