{
  "type": "Feature",
  "properties": {
    "addr:full":"15 rue des Halles 75001 Paris Ile de France",
    "addr:housenumber":"15",
    "addr:postcode":"75001",
    "addr:street":"Rue Des Halles",
    "iso:country":"FR",
    "sg:address":"15 rue des Halles 75001 Paris",
    "sg:classifiers":[
        {
            "category":"Science Facility",
            "type":"Public Place"
        }
    ],
    "sg:phone":"+33 1 42 33 41 41",
    "sg:province":"Ile de France",
    "sg:tags":[
        "transfer",
        "technology"
    ],
    "wof:name":"Novespace Sa",
    "wof:placetype":"venue"
},
  "geometry": {"coordinates":[2.346309,48.860085],"type":"Point"}
}