{
  "type": "Feature",
  "properties": {
    "iso:country":"FR",
    "sg:address":"151 Grande Rue 60530 Crouy En Thelle",
    "sg:classifiers":[
        {
            "category":"Shopping",
            "type":"Retail Goods"
        }
    ],
    "sg:phone":"+33 3 44 26 74 11",
    "sg:postcode":"60530",
    "sg:province":"Picardie",
    "sg:tags":[
        "metallurgy",
        "finished",
        "-",
        "metalworking",
        "metallic"
    ],
    "wof:name":"Musitelli Et Cie Sa",
    "wof:placetype":"venue"
},
  "geometry": {"coordinates":[2.320466,49.214462],"type":"Point"}
}