{
  "type": "Feature",
  "properties": {
    "iso:country":"FR",
    "sg:address":"15, Bd des Martyrs Nantais, 44000 Nantes",
    "sg:orig_category":"Unclassifiable Establishments",
    "sg:phone":"+33 2 40 47 87 40",
    "sg:province":"Pays de Loire",
    "wof:name":"Guillouard Nantes S.a.",
    "wof:placetype":"venue"
},
  "geometry": {"coordinates":[-1.553059,47.218117],"type":"Point"}
}