{
  "type": "Feature",
  "properties": {
    "iso:country":"FR",
    "sg:address":"B.P. 101, 59380 Bergues^^ZI de Bergues, 59380 Bergues",
    "sg:orig_category":"Non-Classified Establishments",
    "sg:phone":"+33 3 28 68 63 88",
    "sg:postcode":"59380",
    "sg:province":"Nord Pas-de-Calais",
    "wof:name":"Dekeister Fr\u00e8res S.a.",
    "wof:placetype":"venue"
},
  "geometry": {"coordinates":[2.493145,50.976814],"type":"Point"}
}