{
  "type": "Feature",
  "properties": {
    "iso:country":"FR",
    "sg:address":"16, Rue Henri Becquerel - ZAC de Kergaradec, 29850 Gouesnou",
    "sg:city":"Gouesnou",
    "sg:orig_category":"Non-Classified Establishments",
    "sg:phone":"+33 2 98 41 89 65",
    "sg:postcode":"29850",
    "sg:province":"Bretagne",
    "wof:name":"S.t.g. S.a. - Soci\u00e9t\u00e9 De Transport Gautier",
    "wof:placetype":"venue"
},
  "geometry": {"coordinates":[-4.465689,48.44989],"type":"Point"}
}