{
  "type": "Feature",
  "properties": {
    "iso:country":"FR",
    "sg:address":"35, Rue du Tapis Vert, 93260 Les Lilas",
    "sg:orig_category":"Unclassifiable Establishments",
    "sg:phone":"+33 1 48 40 45 82",
    "sg:province":"Ile de France",
    "wof:name":"H\u00e9dergen Cannes S.a.r.l.",
    "wof:placetype":"venue"
},
  "geometry": {"coordinates":[2.417876,48.882221],"type":"Point"}
}