{
  "type": "Feature",
  "properties": {
    "iso:country":"FR",
    "sg:address":"B.P. 75, 67212 Obernai C\u00e9dex^^4, Rue du Thal, 67210 Obernai",
    "sg:city":"Obernai",
    "sg:orig_category":"Non-Classified Establishments",
    "sg:phone":"+33 3 88 47 60 00",
    "sg:postcode":"67210",
    "sg:province":"Alsace",
    "wof:name":"Solo France S.a.r.l.",
    "wof:placetype":"venue"
},
  "geometry": {"coordinates":[7.485078,48.46225],"type":"Point"}
}