{
  "type": "Feature",
  "properties": {
    "addr:full":"82 Rue Curial 75019 Paris Ile de France",
    "addr:housenumber":"82",
    "addr:postcode":"75019",
    "addr:street":"Rue Curial",
    "iso:country":"FR",
    "sg:address":"82 Rue Curial 75019 Paris",
    "sg:classifiers":[
        {
            "category":"Professional",
            "subcategory":"Printing & Photocopies",
            "type":"Services"
        }
    ],
    "sg:phone":"+33 1 44 72 81 81",
    "sg:province":"Ile de France",
    "sg:tags":[
        "publishing"
    ],
    "wof:name":"Rigel Editions Sa",
    "wof:placetype":"venue"
},
  "geometry": {"coordinates":[2.374834,48.894997],"type":"Point"}
}