{
  "type": "Feature",
  "properties": {
    "addr:full":"23 rue Vincent Gonzales 33130 BEGLES B\u00e8gles Aquitaine 33130",
    "addr:housenumber":"23",
    "addr:postcode":"33130;33130",
    "addr:street":"Rue Vincent Gonzales",
    "iso:country":"FR",
    "sg:address":"23 rue Vincent Gonzales 33130 BEGLES",
    "sg:city":"B\u00e8gles",
    "sg:classifiers":[
        {
            "category":"Shopping",
            "subcategory":"Clothing, Apparel, & Fashions",
            "type":"Retail Goods"
        }
    ],
    "sg:phone":"+33 5 56 49 20 21",
    "sg:postcode":"33130",
    "sg:province":"Aquitaine",
    "sg:tags":[
        "blouse",
        "ladies'",
        "dress"
    ],
    "wof:name":"Un Certain Regard Sarl",
    "wof:placetype":"venue"
},
  "geometry": {"coordinates":[-0.566914,44.798817],"type":"Point"}
}