{
  "type": "Feature",
  "properties": {
    "addr:full":"56, Bd Voltaire, 75011 Paris Ile de France",
    "addr:housenumber":"56",
    "addr:postcode":"75011",
    "addr:street":"Bd Voltaire",
    "iso:country":"FR",
    "sg:address":"56, Bd Voltaire, 75011 Paris",
    "sg:orig_category":"Unclassifiable Establishments",
    "sg:phone":"+33 1 48 07 54 00",
    "sg:province":"Ile de France",
    "wof:name":"G.b.s. S.a.r.l.",
    "wof:placetype":"venue"
},
  "geometry": {"coordinates":[2.37135,48.862919],"type":"Point"}
}