{
  "type": "Feature",
  "properties": {
    "iso:country":"FR",
    "sg:address":"11 Av Gabriel P\u00e9ri 95500 Gonesse",
    "sg:classifiers":[
        {
            "category":"Bakery",
            "type":"Food & Drink"
        }
    ],
    "sg:phone":"+33 1 39 85 32 45",
    "sg:postcode":"95500",
    "sg:province":"Ile de France",
    "sg:tags":[
        "cake",
        "product",
        "related",
        "bread"
    ],
    "wof:name":"Simpa Sa",
    "wof:placetype":"venue"
},
  "geometry": {"coordinates":[2.422244,48.994972],"type":"Point"}
}