{
  "type": "Feature",
  "properties": {
    "addr:full":"1, Rue Lecouteux - Les Hauts Noirs , 41600 Lamotte Beuvron Chaon Centre 41600",
    "addr:housenumber":"1",
    "addr:postcode":"41600;41600",
    "addr:street":"Rue Lecouteux Les Hauts Noirs",
    "iso:country":"FR",
    "sg:address":"1, Rue Lecouteux - Les Hauts Noirs , 41600 Lamotte Beuvron",
    "sg:city":"Chaon",
    "sg:orig_category":"Unclassifiable Establishments",
    "sg:phone":"+33 2 54 88 21 06",
    "sg:postcode":"41600",
    "sg:province":"Centre",
    "wof:name":"A.m.s. S.a.r.l. - Auto Mat\u00e9riel De Sologne",
    "wof:placetype":"venue"
},
  "geometry": {"coordinates":[2.035673,47.536289],"type":"Point"}
}