{
  "type": "Feature",
  "properties": {
    "addr:full":"B.P. 511, 81107 Castres C\u00e9dex^^ZI de M\u00e9lou, 81100 Castres Midi Pyr\u00e9n\u00e9es",
    "addr:housenumber":"b.p. 511",
    "addr:postcode":"81107;81100",
    "addr:street":"Me\u0301Lou",
    "iso:country":"FR",
    "sg:address":"B.P. 511, 81107 Castres C\u00e9dex^^ZI de M\u00e9lou, 81100 Castres",
    "sg:orig_category":"Non-Classified Establishments",
    "sg:phone":"+33 5 63 71 80 88",
    "sg:province":"Midi Pyr\u00e9n\u00e9es",
    "wof:name":"S.c.i.m. S.a.r.l. - Soci\u00e9t\u00e9 Construction Industrielle M\u00e9tallique",
    "wof:placetype":"venue"
},
  "geometry": {"coordinates":[2.257356,43.56094],"type":"Point"}
}