{
  "type": "Feature",
  "properties": {
    "addr:full":"53bis, Rte d'Hirson, 02830 Saint Michel Picardie",
    "addr:housenumber":"53bis",
    "addr:postcode":"02830",
    "addr:street":"Rte D'Hirson",
    "iso:country":"FR",
    "sg:address":"53bis, Rte d'Hirson, 02830 Saint Michel",
    "sg:orig_category":"Non-Classified Establishments",
    "sg:phone":"+33 3 23 98 77 47",
    "sg:province":"Picardie",
    "wof:name":"Techno Moule S.a.",
    "wof:placetype":"venue"
},
  "geometry": {"coordinates":[4.116945,49.914856],"type":"Point"}
}