{
  "type": "Feature",
  "properties": {
    "addr:full":"491, Rue Pasteur, 59194 R\u00e2ches Nord Pas-de-Calais",
    "addr:housenumber":"491",
    "addr:postcode":"59194",
    "addr:street":"Rue Pasteur",
    "iso:country":"FR",
    "sg:address":"491, Rue Pasteur, 59194 R\u00e2ches",
    "sg:orig_category":"Non-Classified Establishments",
    "sg:phone":"+33 3 27 99 77 22",
    "sg:province":"Nord Pas-de-Calais",
    "wof:name":"S\u00e8de Et Compagnie S.a.r.l.",
    "wof:placetype":"venue"
},
  "geometry": {"coordinates":[3.13124,50.41404],"type":"Point"}
}