{
  "type": "Feature",
  "properties": {
    "addr:full":"2, Chemin de la M\u00e9nude - ZI en Jacca, 31770 Colomiers Midi Pyr\u00e9n\u00e9es 31770",
    "addr:housenumber":"2",
    "addr:postcode":"31770;31770",
    "addr:street":"Chemin De La Me\u0301Nude Zi En Jacca",
    "iso:country":"FR",
    "sg:address":"2, Chemin de la M\u00e9nude - ZI en Jacca, 31770 Colomiers",
    "sg:orig_category":"Non-Classified Establishments",
    "sg:phone":"+33 5 61 78 63 63",
    "sg:postcode":"31770",
    "sg:province":"Midi Pyr\u00e9n\u00e9es",
    "wof:name":"Aerem S.a. - Atelier D'etudes Et R\u00e9alisation Electrom\u00e9caniques",
    "wof:placetype":"venue"
},
  "geometry": {"coordinates":[1.33337,43.612431],"type":"Point"}
}