{
  "type": "Feature",
  "properties": {
    "addr:full":"Galm Auchan 59494 Petite For\u00eat Nord Pas-de-Calais 59494",
    "addr:postcode":"59494;59494",
    "addr:street":"Fore\u0302T Nord",
    "iso:country":"FR",
    "sg:address":"Galm Auchan 59494 Petite For\u00eat",
    "sg:classifiers":[
        {
            "category":"Professional",
            "subcategory":"Advertising",
            "type":"Services"
        }
    ],
    "sg:phone":"+33 3 27 29 53 28",
    "sg:postcode":"59494",
    "sg:province":"Nord Pas-de-Calais",
    "sg:tags":[
        "information",
        "medium",
        "communication"
    ],
    "wof:name":"Ste Pizza Pai",
    "wof:placetype":"venue"
},
  "geometry": {"coordinates":[3.472586,50.370441],"type":"Point"}
}