{
  "type": "Feature",
  "properties": {
    "addr:full":"14 Quai Fecht 68040 Ingersheim Ingersheim Alsace 68040",
    "addr:housenumber":"14",
    "addr:postcode":"68040;68040",
    "addr:street":"Quai Fecht",
    "iso:country":"FR",
    "sg:address":"14 Quai Fecht 68040 Ingersheim",
    "sg:city":"Ingersheim",
    "sg:classifiers":[
        {
            "category":"Manufacturing",
            "subcategory":"Paper Products",
            "type":"Manufacturing & Wholesale Goods"
        }
    ],
    "sg:phone":"+33 3 89 27 91 30",
    "sg:postcode":"68040",
    "sg:province":"Alsace",
    "sg:tags":[
        "raw",
        "material",
        "-",
        "cardboard"
    ],
    "wof:name":"Cartonnages Dine Sa",
    "wof:placetype":"venue"
},
  "geometry": {"coordinates":[7.30934,48.098324],"type":"Point"}
}