{
  "type": "Feature",
  "properties": {
    "addr:full":"17, Fbg de Bourgogne, 10110 Bar sur Seine Champagne",
    "addr:housenumber":"17",
    "addr:postcode":"10110",
    "addr:street":"Fbg De Bourgogne",
    "iso:country":"FR",
    "sg:address":"17, Fbg de Bourgogne, 10110 Bar sur Seine",
    "sg:orig_category":"Unclassifiable Establishments",
    "sg:phone":"+33 3 25 38 51 07",
    "sg:province":"Champagne",
    "wof:name":"Lacour Distribution S.a.r.l.",
    "wof:placetype":"venue"
},
  "geometry": {"coordinates":[4.376645,48.106174],"type":"Point"}
}