{
  "type": "Feature",
  "properties": {
    "iso:country":"FR",
    "sg:address":"Rte De Laon 02800 Charmes",
    "sg:classifiers":[
        {
            "category":"Professional",
            "subcategory":"Business Services",
            "type":"Services"
        }
    ],
    "sg:phone":"+33 3 23 56 22 11",
    "sg:postcode":"02800",
    "sg:province":"Picardie",
    "sg:tags":[
        "training",
        "advice"
    ],
    "wof:name":"Cours Prive Lacordaire",
    "wof:placetype":"venue"
},
  "geometry": {"coordinates":[3.386805,49.654289],"type":"Point"}
}