{
  "type": "Feature",
  "properties": {
    "iso:country":"FR",
    "sg:address":"R Des Maucourants 10400 Trainel",
    "sg:classifiers":[
        {
            "category":"Professional",
            "subcategory":"Engineering",
            "type":"Services"
        }
    ],
    "sg:phone":"+33 3 25 39 46 70",
    "sg:postcode":"10400",
    "sg:province":"Champagne",
    "sg:tags":[
        "machine",
        "-",
        "mechanical"
    ],
    "wof:name":"Spack System Sa",
    "wof:placetype":"venue"
},
  "geometry": {"coordinates":[3.43904,48.410347],"type":"Point"}
}