{
  "type": "Feature",
  "properties": {
    "iso:country":"FR",
    "sg:address":"Faury 42600 Essertines En Ch\u00e2telneuf",
    "sg:classifiers":[
        {
            "category":"Farming",
            "subcategory":"Livestock Farm",
            "type":"Manufacturing & Wholesale Goods"
        }
    ],
    "sg:phone":"+33 4 77 58 18 61",
    "sg:postcode":"42600",
    "sg:province":"Rhone-Alpes",
    "sg:tags":[
        "breeding",
        "agriculture",
        "animal"
    ],
    "wof:name":"Chazal Jean Yves",
    "wof:placetype":"venue"
},
  "geometry": {"coordinates":[3.996271,45.571075],"type":"Point"}
}