{
  "type": "Feature",
  "properties": {
    "iso:country":"FR",
    "sg:address":"5, Rue Eug\u00e8ne Chevreuil - ZI Plesses, 85180 Ch\u00e2teau d'Olonne",
    "sg:orig_category":"Non-Classified Establishments",
    "sg:phone":"+33 2 51 21 47 06",
    "sg:province":"Pays de Loire",
    "wof:name":"Mido Marquages S.a.r.l.",
    "wof:placetype":"venue"
},
  "geometry": {"coordinates":[-1.741401,46.505875],"type":"Point"}
}