{
  "type": "Feature",
  "properties": {
    "addr:full":"9 Square De Li\u00e8ge Vandoeuvre L\u00e8s Nancy Lorraine 54500",
    "addr:housenumber":"9",
    "addr:postcode":"54500",
    "addr:street":"Square De Lie\u0300Ge",
    "iso:country":"FR",
    "sg:address":"9 Square De Li\u00e8ge",
    "sg:city":"Vandoeuvre L\u00e8s Nancy",
    "sg:classifiers":[
        {
            "category":"Banks & Credit Unions",
            "subcategory":"Financial Services",
            "type":"Services"
        }
    ],
    "sg:phone":"+33 3 83 56 05 66",
    "sg:postcode":"54500",
    "sg:province":"Lorraine",
    "sg:tags":[
        "banking",
        "finance",
        "insurance"
    ],
    "wof:name":"Ste D Experts Comptables Lorrains",
    "wof:placetype":"venue"
},
  "geometry": {"coordinates":[6.170395,48.6684],"type":"Point"}
}