{
  "type": "Feature",
  "properties": {
    "addr:full":"12 Rue De Brest Resid 4 As 62217 Achicourt Nord Pas-de-Calais 62217",
    "addr:housenumber":"12;4 as",
    "addr:postcode":"62217;62217",
    "addr:street":"Rue De Brest Resid",
    "iso:country":"FR",
    "sg:address":"12 Rue De Brest Resid 4 As 62217 Achicourt",
    "sg:classifiers":[
        {
            "category":"Professional",
            "subcategory":"Engineering",
            "type":"Services"
        }
    ],
    "sg:phone":"+33 3 21 23 19 94",
    "sg:postcode":"62217",
    "sg:province":"Nord Pas-de-Calais",
    "sg:tags":[
        "machine",
        "-",
        "mechanical"
    ],
    "wof:name":"Entreprise Duval",
    "wof:placetype":"venue"
},
  "geometry": {"coordinates":[2.757345,50.273754],"type":"Point"}
}