{
  "type": "Feature",
  "properties": {
    "addr:full":"26, Rue Laurent Trouttet - Moulin de Bannans, 25560 Bannans Franche Comt\u00e9",
    "addr:housenumber":"26",
    "addr:postcode":"25560",
    "addr:street":"Rue Laurent Trouttet Moulin De Bannans;Franche Comte\u0301",
    "iso:country":"FR",
    "sg:address":"26, Rue Laurent Trouttet - Moulin de Bannans, 25560 Bannans",
    "sg:orig_category":"Non-Classified Establishments",
    "sg:phone":"+33 3 81 49 85 83",
    "sg:province":"Franche Comt\u00e9",
    "wof:name":"Girardet S.a.r.l. - Moulin De Bannans",
    "wof:placetype":"venue"
},
  "geometry": {"coordinates":[6.163377,46.857418],"type":"Point"}
}