{
  "type": "Feature",
  "properties": {
    "iso:country":"FR",
    "sg:address":"55/57, Av. Raymond Poincar\u00e9, 75116 Paris",
    "sg:orig_category":"Unclassifiable Establishments",
    "sg:phone":"+33 1 44 05 66 66",
    "sg:province":"\u00cele-de-France",
    "wof:name":"Le Parc Sofitel Demeure H\u00f4tels",
    "wof:placetype":"venue"
},
  "geometry": {"coordinates":[2.285816,48.866959],"type":"Point"}
}