{
  "type": "Feature",
  "properties": {
    "iso:country":"FR",
    "sg:address":"Zone Portuaire 44550 Montoir De Bretagne",
    "sg:classifiers":[
        {
            "category":"Banks & Credit Unions",
            "subcategory":"Investment Brokerage",
            "type":"Services"
        }
    ],
    "sg:phone":"+33 2 40 90 03 04",
    "sg:province":"Pays de Loire",
    "sg:tags":[
        "-",
        "transport",
        "related"
    ],
    "wof:name":"Euro Stockage",
    "wof:placetype":"venue"
},
  "geometry": {"coordinates":[-2.153179,47.327759],"type":"Point"}
}