{
  "type": "Feature",
  "properties": {
    "addr:full":"1 Rue Pierre Gilles De Gennes 72400 La Fert\u00e9 Bernard Pays de Loire 72400",
    "addr:housenumber":"1",
    "addr:postcode":"72400;72400",
    "addr:street":"Rue Pierre Gilles De Gennes;Bernard",
    "iso:country":"FR",
    "sg:address":"1 Rue Pierre Gilles De Gennes 72400 La Fert\u00e9 Bernard",
    "sg:classifiers":[
        {
            "category":"Shopping",
            "subcategory":"Computers & Home Electronics",
            "type":"Retail Goods"
        }
    ],
    "sg:phone":"+33 2 43 71 65 00",
    "sg:postcode":"72400",
    "sg:province":"Pays de Loire",
    "sg:tags":[
        "equipment",
        "electrical",
        "component",
        "electric",
        "electronic"
    ],
    "wof:name":"Delta Composants",
    "wof:placetype":"venue"
},
  "geometry": {"coordinates":[0.563782,48.134613],"type":"Point"}
}