{
  "type": "Feature",
  "properties": {
    "addr:full":"B.P. 68 Sainte Sigol\u00e8ne Auvergne 43600",
    "addr:postcode":"43600",
    "addr:street":"B.P. 68 Sainte Sigole\u0300Ne",
    "iso:country":"FR",
    "sg:address":"B.P. 68",
    "sg:city":"Sainte Sigol\u00e8ne",
    "sg:orig_category":"Non-Classified Establishments",
    "sg:phone":"+33 4 71 75 60 00",
    "sg:postcode":"43600",
    "sg:province":"Auvergne",
    "wof:name":"Soci\u00e9t\u00e9 Nouvelles Sigoplast S.a.s.",
    "wof:placetype":"venue"
},
  "geometry": {"coordinates":[4.23542,45.243401],"type":"Point"}
}