{
  "type": "Feature",
  "properties": {
    "addr:full":"3 Pl De Saverne Immeubles Renardi\u00e8res 92901 Paris La D\u00e9fense Saverne Alsace 67700",
    "addr:housenumber":"3",
    "addr:postcode":"92901;67700",
    "addr:street":"Pl De Saverne;Renardie\u0300Res",
    "iso:country":"FR",
    "sg:address":"3 Pl De Saverne Immeubles Renardi\u00e8res 92901 Paris La D\u00e9fense",
    "sg:city":"Saverne",
    "sg:classifiers":[
        {
            "category":"Professional",
            "subcategory":"Computer Services",
            "type":"Services"
        }
    ],
    "sg:phone":"+33 1 41 16 16 00",
    "sg:postcode":"67700",
    "sg:province":"Alsace",
    "sg:tags":[
        "information",
        "technology",
        "software"
    ],
    "wof:name":"Progress Software Sa",
    "wof:placetype":"venue"
},
  "geometry": {"coordinates":[2.24119,48.888939],"type":"Point"}
}