{
  "type": "Feature",
  "properties": {
    "addr:full":"ZIA du Barnier Frontignan Languedoc-Roussillon 34110",
    "addr:postcode":"34110",
    "iso:country":"FR",
    "sg:address":"ZIA du Barnier",
    "sg:city":"Frontignan",
    "sg:orig_category":"Unclassifiable Establishments",
    "sg:phone":"+33 4 67 51 62 30",
    "sg:postcode":"34110",
    "sg:province":"Languedoc-Roussillon",
    "wof:name":"E.e.i.a. S.a.r.l. - Entreprise D'electricit\u00e9 Industrielle Et Automati",
    "wof:placetype":"venue"
},
  "geometry": {"coordinates":[3.767678,43.462711],"type":"Point"}
}