{
  "type": "Feature",
  "properties": {
    "addr:full":"48, Rue des Vignes, 67202 Wolfisheim Wolfisheim Alsace 67202",
    "addr:housenumber":"48",
    "addr:postcode":"67202;67202",
    "addr:street":"Rue Des Vignes",
    "iso:country":"FR",
    "sg:address":"48, Rue des Vignes, 67202 Wolfisheim",
    "sg:city":"Wolfisheim",
    "sg:orig_category":"Unclassifiable Establishments",
    "sg:phone":"+33 3 88 76 55 80",
    "sg:postcode":"67202",
    "sg:province":"Alsace",
    "wof:name":"Sorelec S.a.r.l.",
    "wof:placetype":"venue"
},
  "geometry": {"coordinates":[7.666442,48.591267],"type":"Point"}
}