{
  "type": "Feature",
  "properties": {
    "addr:full":"17, Rue du Docteur Regad, 39400 Morez Franche Comt\u00e9",
    "addr:housenumber":"17",
    "addr:postcode":"39400",
    "addr:street":"Rue Du Docteur Regad;Franche Comte\u0301",
    "iso:country":"FR",
    "sg:address":"17, Rue du Docteur Regad, 39400 Morez",
    "sg:orig_category":"Unclassifiable Establishments",
    "sg:phone":"+33 3 84 33 23 13",
    "sg:province":"Franche Comt\u00e9",
    "wof:name":"Offner Fr\u00e8res S.a.r.l.",
    "wof:placetype":"venue"
},
  "geometry": {"coordinates":[6.025235,46.517227],"type":"Point"}
}