{
  "type": "Feature",
  "properties": {
    "addr:full":"2 Bis, Rue de Cannes, 59000 Lille Nord Pas-de-Calais 59000",
    "addr:housenumber":"2 bis",
    "addr:postcode":"59000;59000",
    "addr:street":"Rue De Cannes",
    "iso:country":"FR",
    "sg:address":"2 Bis, Rue de Cannes, 59000 Lille",
    "sg:orig_category":"Non-Classified Establishments",
    "sg:phone":"+33 3 28 16 01 60",
    "sg:postcode":"59000",
    "sg:province":"Nord Pas-de-Calais",
    "wof:name":"Centr.a.co. S.a.r.l. - Centre D'approvisionnement Des Collectivit\u00e9s",
    "wof:placetype":"venue"
},
  "geometry": {"coordinates":[3.04413,50.606705],"type":"Point"}
}