{
  "type": "Feature",
  "properties": {
    "iso:country":"FR",
    "sg:address":"12, Av. Charles de Gaulle - B\u00e2t. 12, 31130 Balma",
    "sg:orig_category":"Unclassifiable Establishments",
    "sg:phone":"+33 5 62 57 73 73",
    "sg:province":"Midi Pyr\u00e9n\u00e9es",
    "wof:name":"Batinix S.a.",
    "wof:placetype":"venue"
},
  "geometry": {"coordinates":[1.498258,43.596073],"type":"Point"}
}