{
  "type": "Feature",
  "properties": {
    "addr:full":"RN 15 Epretot Haute Normandie 76430",
    "addr:postcode":"76430",
    "addr:street":"Rn 15 Epretot Haute Normandie",
    "iso:country":"FR",
    "sg:address":"RN 15",
    "sg:city":"Epretot",
    "sg:orig_category":"Unclassifiable Establishments",
    "sg:phone":"+33 2 35 20 52 30",
    "sg:postcode":"76430",
    "sg:province":"Haute Normandie",
    "wof:name":"Paysages De L'estuaire S.a.",
    "wof:placetype":"venue"
},
  "geometry": {"coordinates":[0.46642,49.486343],"type":"Point"}
}