{
  "type": "Feature",
  "properties": {
    "addr:full":"30, Av. Karl Marx - ZI Est, 69120 Vaulx en Velin Rhone-Alpes",
    "addr:postcode":"69120",
    "addr:street":"30 Av. Karl Marx Zi Est",
    "iso:country":"FR",
    "sg:address":"30, Av. Karl Marx - ZI Est, 69120 Vaulx en Velin",
    "sg:orig_category":"Non-Classified Establishments",
    "sg:phone":"+33 4 72 04 92 00",
    "sg:province":"Rhone-Alpes",
    "wof:name":"Moeller S.a.",
    "wof:placetype":"venue"
},
  "geometry": {"coordinates":[4.916895,45.779022],"type":"Point"}
}