{
  "type": "Feature",
  "properties": {
    "addr:full":"B.P. 32, 77990 Le Mesnil Amelot^^1, Rue du Gu\u00e9 - Parc Strat\u00e9gic, 77990 Le Mesnil Amelot Ile de France",
    "addr:postcode":"77990;77990;ile",
    "addr:street":"B.P. 32;Rue Du Gue\u0301 Parc Strate\u0301Gic",
    "iso:country":"FR",
    "sg:address":"B.P. 32, 77990 Le Mesnil Amelot^^1, Rue du Gu\u00e9 - Parc Strat\u00e9gic, 77990 Le Mesnil Amelot",
    "sg:orig_category":"Non-Classified Establishments",
    "sg:phone":"+33 1 60 03 84 84",
    "sg:province":"Ile de France",
    "wof:name":"Moss Pi\u00e8ces Plastiques S.a.r.l.",
    "wof:placetype":"venue"
},
  "geometry": {"coordinates":[2.590909,49.017994],"type":"Point"}
}