{
  "type": "Feature",
  "properties": {
    "addr:full":"4, Rue Edmond Voisenet, 21000 Dijon Dijon Bourgogne 21000",
    "addr:housenumber":"4",
    "addr:postcode":"21000;21000",
    "addr:street":"Rue Edmond Voisenet",
    "iso:country":"FR",
    "sg:address":"4, Rue Edmond Voisenet, 21000 Dijon",
    "sg:city":"Dijon",
    "sg:orig_category":"Unclassifiable Establishments",
    "sg:phone":"+33 820 89 38 93",
    "sg:postcode":"21000",
    "sg:province":"Bourgogne",
    "wof:name":"La Maison De L'installeur S.a.",
    "wof:placetype":"venue"
},
  "geometry": {"coordinates":[5.024607,47.29903],"type":"Point"}
}