{
  "type": "Feature",
  "properties": {
    "iso:country":"FR",
    "sg:address":"Rue de la Croix Blanche",
    "sg:city":"Vaumoise",
    "sg:orig_category":"Unclassifiable Establishments",
    "sg:phone":"+33 3 44 88 40 63",
    "sg:postcode":"60117",
    "sg:province":"Picardie",
    "wof:name":"Velay Bernard Caisserie S.a.",
    "wof:placetype":"venue"
},
  "geometry": {"coordinates":[2.979749,49.233898],"type":"Point"}
}