{
  "type": "Feature",
  "properties": {
    "iso:country":"FR",
    "sg:address":"55, Bd de l'Embouchure - Central Parc - B\u00e2t. C, 31200 Toulouse",
    "sg:orig_category":"Non-Classified Establishments",
    "sg:phone":"+33 5 34 40 16 16",
    "sg:province":"Midi Pyr\u00e9n\u00e9es",
    "wof:name":"Garon Bonvalot S.a.",
    "wof:placetype":"venue"
},
  "geometry": {"coordinates":[1.432791,43.614876],"type":"Point"}
}