{
  "type": "Feature",
  "properties": {
    "iso:country":"FR",
    "sg:address":"Pl Du Colombier Cc Colombia Local 56 35000 Rennes",
    "sg:city":"Rennes",
    "sg:classifiers":[
        {
            "category":"Shopping",
            "subcategory":"Clothing, Apparel, & Fashions",
            "type":"Retail Goods"
        }
    ],
    "sg:phone":"+33 2 99 31 38 60",
    "sg:postcode":"35000",
    "sg:province":"Bretagne",
    "sg:tags":[
        "textile",
        "clothing",
        "clothes"
    ],
    "wof:name":"Devred Sa",
    "wof:placetype":"venue"
},
  "geometry": {"coordinates":[-1.684477,48.107521],"type":"Point"}
}