{
  "type": "Feature",
  "properties": {
    "addr:full":"1, Bd Ney, 75018 Paris Ile de France",
    "addr:housenumber":"1",
    "addr:postcode":"75018",
    "addr:street":"Bd Ney",
    "iso:country":"FR",
    "sg:address":"1, Bd Ney, 75018 Paris",
    "sg:orig_category":"Non-Classified Establishments",
    "sg:phone":"+33 1 44 89 83 33",
    "sg:province":"Ile de France",
    "wof:name":"Exel",
    "wof:placetype":"venue"
},
  "geometry": {"coordinates":[2.369058,48.898365],"type":"Point"}
}