{
  "type": "Feature",
  "properties": {
    "addr:full":"39, Grande Rue, 89320 Coulours Coulours Bourgogne 89320",
    "addr:housenumber":"39",
    "addr:postcode":"89320;89320",
    "addr:street":"Grande Rue",
    "iso:country":"FR",
    "sg:address":"39, Grande Rue, 89320 Coulours",
    "sg:city":"Coulours",
    "sg:orig_category":"Non-Classified Establishments",
    "sg:phone":"+33 3 86 96 23 59",
    "sg:postcode":"89320",
    "sg:province":"Bourgogne",
    "wof:name":"A.c.t.p. S.a. - Application Et Conseils Techniques De Plastiques",
    "wof:placetype":"venue"
},
  "geometry": {"coordinates":[3.587309,48.16486],"type":"Point"}
}