{
  "type": "Feature",
  "properties": {
    "iso:country":"FR",
    "sg:address":"31 rue Henri Rochefort 75017 Paris",
    "sg:classifiers":[
        {
            "category":"Military Area",
            "subcategory":"Army Base",
            "type":"Public Place"
        }
    ],
    "sg:phone":"+33 1 56 21 32 00",
    "sg:province":"Ile de France",
    "sg:tags":[
        "software",
        "program",
        "standard",
        "add-on"
    ],
    "wof:name":"Marketic Sa",
    "wof:placetype":"venue"
},
  "geometry": {"coordinates":[2.308359,48.882633],"type":"Point"}
}