{
  "type": "Feature",
  "properties": {
    "iso:country":"FR",
    "sg:address":"27, Rte de Wantzenau, 67800 Hoenheim",
    "sg:city":"Hoenheim",
    "sg:orig_category":"Unclassifiable Establishments",
    "sg:phone":"+33 3 90 22 29 29",
    "sg:postcode":"67800",
    "sg:province":"Alsace",
    "wof:name":"Gs Net S.a.r.l.",
    "wof:placetype":"venue"
},
  "geometry": {"coordinates":[7.766098,48.63221],"type":"Point"}
}