{
  "type": "Feature",
  "properties": {
    "addr:full":"Boulevard Du Pou Du Ciel Zone Industrielle 01600 Reyrieux Rhone-Alpes 01600",
    "addr:postcode":"01600;01600",
    "addr:street":"Boulevard Du Pou Du Ciel Zone Industrielle",
    "iso:country":"FR",
    "sg:address":"Boulevard Du Pou Du Ciel Zone Industrielle 01600 Reyrieux",
    "sg:classifiers":[
        {
            "category":"Transit Center",
            "subcategory":"Freight",
            "type":"Transportation"
        }
    ],
    "sg:phone":"+33 800 86 07 11",
    "sg:postcode":"01600",
    "sg:province":"Rhone-Alpes",
    "sg:tags":[
        "metallurgy",
        "pipe",
        "metalworking",
        "sheet"
    ],
    "wof:name":"Fabrication Generale Pour La Maintenance Fgpm (fgpm)",
    "wof:placetype":"venue"
},
  "geometry": {"coordinates":[4.79649,45.94265],"type":"Point"}
}