{
  "type": "Feature",
  "properties": {
    "addr:full":"4 Rue De La Monnaie 35000 Rennes Rennes Bretagne 35000",
    "addr:housenumber":"4",
    "addr:postcode":"35000;35000",
    "addr:street":"Rue De La Monnaie",
    "iso:country":"FR",
    "sg:address":"4 Rue De La Monnaie 35000 Rennes",
    "sg:city":"Rennes",
    "sg:classifiers":[
        {
            "category":"Banks & Credit Unions",
            "subcategory":"Financial Services",
            "type":"Services"
        }
    ],
    "sg:phone":"+33 2 99 78 54 00",
    "sg:postcode":"35000",
    "sg:province":"Bretagne",
    "sg:tags":[
        "banking",
        "insurance",
        "institution",
        "finance"
    ],
    "wof:name":"Credit Lyonnais",
    "wof:placetype":"venue"
},
  "geometry": {"coordinates":[-1.682038,48.11248],"type":"Point"}
}