{
  "type": "Feature",
  "properties": {
    "iso:country":"FR",
    "sg:address":"B.P. 75, 57155 Marly^^Rue des Garennes, 57155 Marly",
    "sg:orig_category":"Non-Classified Establishments",
    "sg:phone":"+33 3 87 56 02 31",
    "sg:province":"Aquitaine",
    "wof:name":"Colas Est",
    "wof:placetype":"venue"
},
  "geometry": {"coordinates":[6.154125,49.060066],"type":"Point"}
}