{
  "type": "Feature",
  "properties": {
    "addr:full":"Rte de Villers Maizy Picardie 02160",
    "addr:postcode":"02160",
    "addr:street":"Rte De Villers;Picardie",
    "iso:country":"FR",
    "sg:address":"Rte de Villers",
    "sg:city":"Maizy",
    "sg:orig_category":"Non-Classified Establishments",
    "sg:phone":"+33 3 23 25 37 90",
    "sg:postcode":"02160",
    "sg:province":"Picardie",
    "wof:name":"Capagri S.a.r.l.",
    "wof:placetype":"venue"
},
  "geometry": {"coordinates":[3.70976,49.392399],"type":"Point"}
}