{
  "type": "Feature",
  "properties": {
    "iso:country":"FR",
    "sg:address":"50 Rue Pascal 75013 Paris",
    "sg:classifiers":[
        {
            "category":"Professional",
            "subcategory":"Printing & Photocopies",
            "type":"Services"
        }
    ],
    "sg:phone":"+33 1 45 87 14 88",
    "sg:province":"Ile de France",
    "sg:tags":[
        "publishing"
    ],
    "wof:name":"L'amateur De Cigare (adc)",
    "wof:placetype":"venue"
},
  "geometry": {"coordinates":[2.348028,48.835434],"type":"Point"}
}