{
  "type": "Feature",
  "properties": {
    "addr:full":"RN 12 - ZI Pommeret Bretagne 22120",
    "addr:postcode":"22120",
    "addr:street":"Rn 12 Zi Pommeret Bretagne",
    "iso:country":"FR",
    "sg:address":"RN 12 - ZI",
    "sg:city":"Pommeret",
    "sg:orig_category":"Non-Classified Establishments",
    "sg:phone":"+33 2 96 34 33 06",
    "sg:postcode":"22120",
    "sg:province":"Bretagne",
    "wof:name":"S\u00e9ri Publi Intersignal S.a.r.l.",
    "wof:placetype":"venue"
},
  "geometry": {"coordinates":[-2.658644,48.421139],"type":"Point"}
}