{
  "type": "Feature",
  "properties": {
    "addr:full":"B.P. 13, 68650 Lapoutroie^^ZA d'Hachimette, 68650 Lapoutroie Lapoutroie Alsace 68650",
    "addr:postcode":"68650;68650;68650",
    "addr:street":"B.P. 13;D'Hachimette",
    "iso:country":"FR",
    "sg:address":"B.P. 13, 68650 Lapoutroie^^ZA d'Hachimette, 68650 Lapoutroie",
    "sg:city":"Lapoutroie",
    "sg:orig_category":"Non-Classified Establishments",
    "sg:phone":"+33 3 89 47 23 34",
    "sg:postcode":"68650",
    "sg:province":"Alsace",
    "wof:name":"Roda S.a.",
    "wof:placetype":"venue"
},
  "geometry": {"coordinates":[7.192601,48.150417],"type":"Point"}
}