{
  "type": "Feature",
  "properties": {
    "addr:full":"33, Av Jacques Duclos, 37700 Saint Pierre des Corps La Ville-aux-Dames Centre 37700",
    "addr:postcode":"37700;37700",
    "addr:street":"33 Av Jacques Duclos;Des Corps La",
    "iso:country":"FR",
    "sg:address":"33, Av Jacques Duclos, 37700 Saint Pierre des Corps",
    "sg:city":"La Ville-aux-Dames",
    "sg:orig_category":"Non-Classified Establishments",
    "sg:phone":"+33 2 47 32 28 20",
    "sg:postcode":"37700",
    "sg:province":"Centre",
    "wof:name":"Pinault Centre Ouest S.n.c.",
    "wof:placetype":"venue"
},
  "geometry": {"coordinates":[0.74504,47.381138],"type":"Point"}
}