{
  "type": "Feature",
  "properties": {
    "iso:country":"FR",
    "sg:address":"20 rue de l'Eperon 58000 Nevers",
    "sg:city":"Nevers",
    "sg:orig_category":"Cuvettes",
    "sg:phone":"+33 3 86 59 89 00",
    "sg:postcode":"58000",
    "sg:province":"Bourgogne",
    "wof:name":"Prominox Industrie S.a.r.l.",
    "wof:placetype":"venue"
},
  "geometry": {"coordinates":[3.178706,46.990532],"type":"Point"}
}