{
  "type": "Feature",
  "properties": {
    "addr:full":"Port du Noyer Arveyres Aquitaine 33500",
    "addr:postcode":"33500",
    "iso:country":"FR",
    "sg:address":"Port du Noyer",
    "sg:city":"Arveyres",
    "sg:orig_category":"Unclassifiable Establishments",
    "sg:phone":"+33 5 57 51 54 56",
    "sg:postcode":"33500",
    "sg:province":"Aquitaine",
    "wof:name":"Da Silva Pneus Libourne S.a.",
    "wof:placetype":"venue"
},
  "geometry": {"coordinates":[-0.258279,44.909698],"type":"Point"}
}