{
  "type": "Feature",
  "properties": {
    "iso:country":"FR",
    "sg:address":"13090 AIX EN PROVENCE",
    "sg:classifiers":[
        {
            "category":"Food & Beverages",
            "subcategory":"Specialty",
            "type":"Retail Goods"
        }
    ],
    "sg:phone":"+33 4 42 39 29 89",
    "sg:province":"Nord Pas-de-Calais",
    "sg:tags":[
        "almond",
        "speciality"
    ],
    "wof:name":"Confiserie Du Roy Ren\u00e9 S.a.r.l.",
    "wof:placetype":"venue"
},
  "geometry": {"coordinates":[5.43415,43.527222],"type":"Point"}
}