{
  "type": "Feature",
  "properties": {
    "addr:full":"Zac De Ma\u00e7on Est 01750 Replonges Haute Normandie",
    "addr:postcode":"01750",
    "addr:street":"Zac De Mac\u0327On Est;Haute Normandie",
    "iso:country":"FR",
    "sg:address":"Zac De Ma\u00e7on Est 01750 Replonges",
    "sg:classifiers":[
        {
            "category":"Manufacturing",
            "subcategory":"Food",
            "type":"Manufacturing & Wholesale Goods"
        }
    ],
    "sg:phone":"+33 3 85 31 02 55",
    "sg:province":"Haute Normandie",
    "sg:tags":[
        "preserve",
        "product",
        "related"
    ],
    "wof:name":"Ste Exploitation Conserves Grandjean Sarl",
    "wof:placetype":"venue"
},
  "geometry": {"coordinates":[4.872405,46.301384],"type":"Point"}
}