{
  "type": "Feature",
  "properties": {
    "addr:full":"15 Rue De La Paix 75002 Paris Ile de France 75002",
    "addr:housenumber":"15",
    "addr:postcode":"75002;75002",
    "addr:street":"Rue De La Paix",
    "iso:country":"FR",
    "sg:address":"15 Rue De La Paix 75002 Paris",
    "sg:classifiers":[
        {
            "category":"Personal",
            "subcategory":"Shoe Repair & Shine",
            "type":"Services"
        }
    ],
    "sg:phone":"+33 1 42 61 57 58",
    "sg:postcode":"75002",
    "sg:province":"Ile de France",
    "sg:tags":[
        "good",
        "equipement",
        "leather",
        "precision",
        "timekeeping",
        "equipment"
    ],
    "wof:name":"Boutique Alfred Dunhill",
    "wof:placetype":"venue"
},
  "geometry": {"coordinates":[2.331174,48.869461],"type":"Point"}
}