{
  "type": "Feature",
  "properties": {
    "iso:country":"FR",
    "sg:address":"1 Rue Du Bois Merrain 28000 Ch\u00e2rtres",
    "sg:city":"Chartres",
    "sg:classifiers":[
        {
            "category":"Bakery",
            "type":"Food & Drink"
        }
    ],
    "sg:phone":"+33 2 37 21 36 28",
    "sg:postcode":"28000",
    "sg:province":"Centre",
    "sg:tags":[
        "cake",
        "product",
        "related",
        "bread"
    ],
    "wof:name":"Au Bon Croissant Sarl",
    "wof:placetype":"venue"
},
  "geometry": {"coordinates":[1.485796,48.444473],"type":"Point"}
}