{
  "type": "Feature",
  "properties": {
    "addr:full":"25, Bd de S\u00e9bastopol, 75001 Paris Ile de France",
    "addr:housenumber":"25",
    "addr:postcode":"75001",
    "addr:street":"Bd De Se\u0301Bastopol",
    "iso:country":"FR",
    "sg:address":"25, Bd de S\u00e9bastopol, 75001 Paris",
    "sg:orig_category":"Unclassifiable Establishments",
    "sg:phone":"+33 1 40 41 66 70",
    "sg:province":"Ile de France",
    "wof:name":"Air Sud D\u00e9couvertes S.a.",
    "wof:placetype":"venue"
},
  "geometry": {"coordinates":[2.349063,48.860214],"type":"Point"}
}