{
  "type": "Feature",
  "properties": {
    "addr:full":"1 Marcillac Aquitaine 33860",
    "addr:housenumber":"1",
    "addr:postcode":"33860",
    "addr:street":"Marcillac Aquitaine",
    "iso:country":"FR",
    "sg:address":"1",
    "sg:city":"Marcillac",
    "sg:classifiers":[
        {
            "category":"Food Court",
            "type":"Food & Drink"
        }
    ],
    "sg:phone":"+33 5 57 32 48 33",
    "sg:postcode":"33860",
    "sg:province":"Aquitaine",
    "sg:tags":[
        "product",
        "related"
    ],
    "wof:name":"Cooperative Des Hauts De Gironde",
    "wof:placetype":"venue"
},
  "geometry": {"coordinates":[-0.513688,45.269753],"type":"Point"}
}