{
  "type": "Feature",
  "properties": {
    "addr:full":"67, Rue Pascal, 75013 Paris Ile de France 75013",
    "addr:housenumber":"67",
    "addr:postcode":"75013;75013",
    "addr:street":"Rue Pascal",
    "iso:country":"FR",
    "sg:address":"67, Rue Pascal, 75013 Paris",
    "sg:orig_category":"Non-Classified Establishments",
    "sg:phone":"+33 1 43 31 43 93",
    "sg:postcode":"75013",
    "sg:province":"Ile de France",
    "wof:name":"Ciporco Trading S.a.",
    "wof:placetype":"venue"
},
  "geometry": {"coordinates":[2.34788,48.834385],"type":"Point"}
}