{
  "type": "Feature",
  "properties": {
    "addr:full":"Les Bouquieres Zone Industrielle 25400 Exincourt Franche Comt\u00e9 25400",
    "addr:postcode":"25400;25400",
    "addr:street":"Zone Industrielle;Franche Comte\u0301",
    "iso:country":"FR",
    "sg:address":"Les Bouquieres Zone Industrielle 25400 Exincourt",
    "sg:classifiers":[
        {
            "category":"Shopping",
            "type":"Retail Goods"
        }
    ],
    "sg:phone":"+33 3 81 32 58 58",
    "sg:postcode":"25400",
    "sg:province":"Franche Comt\u00e9",
    "sg:tags":[
        "metallurgy",
        "finished",
        "-",
        "metalworking",
        "metallic"
    ],
    "wof:name":"Vuillemenot Thedis",
    "wof:placetype":"venue"
},
  "geometry": {"coordinates":[6.83359,47.49865],"type":"Point"}
}