{
  "type": "Feature",
  "properties": {
    "addr:full":"1, Rte de Genas, 69120 Vaulx en Velin Rhone-Alpes 69120",
    "addr:housenumber":"1",
    "addr:postcode":"69120;69120",
    "addr:street":"Rte De Genas",
    "iso:country":"FR",
    "sg:address":"1, Rte de Genas, 69120 Vaulx en Velin",
    "sg:orig_category":"Unclassifiable Establishments",
    "sg:phone":"+33 4 72 14 97 97",
    "sg:postcode":"69120",
    "sg:province":"Rhone-Alpes",
    "wof:name":"Soci\u00e9t\u00e9 Nouvelle Jeannallet S.a.",
    "wof:placetype":"venue"
},
  "geometry": {"coordinates":[4.918431,45.748592],"type":"Point"}
}