{
  "type": "Feature",
  "properties": {
    "addr:full":"1 Rue Ambroise Croizat Zi Des Glaises 91120 Palaiseau Ile de France 91120",
    "addr:housenumber":"1",
    "addr:postcode":"91120;ile;91120",
    "addr:street":"Rue Ambroise Croizat Zi Des Glaises;France",
    "iso:country":"FR",
    "sg:address":"1 Rue Ambroise Croizat Zi Des Glaises 91120 Palaiseau",
    "sg:classifiers":[
        {
            "category":"Home & Garden",
            "subcategory":"Furniture",
            "type":"Retail Goods"
        }
    ],
    "sg:phone":"+33 1 64 53 24 24",
    "sg:postcode":"91120",
    "sg:province":"Ile de France",
    "sg:tags":[
        "household",
        "wood"
    ],
    "wof:name":"Steel Ebene",
    "wof:placetype":"venue"
},
  "geometry": {"coordinates":[2.246296,48.713036],"type":"Point"}
}