{
  "type": "Feature",
  "properties": {
    "addr:full":"B.P. 10044 Saint Paul sur Ternoise C\u00e9dex^^62130 Siracourt Nord Pas-de-Calais 62130",
    "addr:housenumber":"10044",
    "addr:postcode":"62130",
    "iso:country":"FR",
    "sg:address":"B.P. 10044",
    "sg:city":"Saint Paul sur Ternoise C\u00e9dex^^62130 Siracourt",
    "sg:orig_category":"Non-Classified Establishments",
    "sg:phone":"+33 3 21 03 18 01",
    "sg:postcode":"62130",
    "sg:province":"Nord Pas-de-Calais",
    "wof:name":"A.b.s. Qualinord Coop\u00e9rative S.c.a.",
    "wof:placetype":"venue"
},
  "geometry": {"coordinates":[2.3353,50.380672],"type":"Point"}
}