{
  "type": "Feature",
  "properties": {
    "addr:full":"19 avenue du Ch\u00e2teau 91190 Gif sur Yvette Ile de France",
    "addr:housenumber":"19",
    "addr:postcode":"91190",
    "addr:street":"Avenue Du Cha\u0302Teau",
    "iso:country":"FR",
    "sg:address":"19 avenue du Ch\u00e2teau 91190 Gif sur Yvette",
    "sg:classifiers":[
        {
            "category":"Manufacturing",
            "subcategory":"Motor Vehicles & Parts",
            "type":"Manufacturing & Wholesale Goods"
        }
    ],
    "sg:phone":"+33 1 60 12 19 66",
    "sg:province":"Ile de France",
    "sg:tags":[
        "precision",
        "mechanic"
    ],
    "wof:name":"Activ Basse Temper Soc Realis Indus Meca Sarl",
    "wof:placetype":"venue"
},
  "geometry": {"coordinates":[2.110334,48.694656],"type":"Point"}
}