{
  "type": "Feature",
  "properties": {
    "addr:full":"Rue des Entrepreneurs - ZA Mirebeau Poitou-Charentes 86110",
    "addr:postcode":"86110",
    "addr:street":"Rue Des Entrepreneurs Za Mirebeau",
    "iso:country":"FR",
    "sg:address":"Rue des Entrepreneurs - ZA",
    "sg:city":"Mirebeau",
    "sg:orig_category":"Unclassifiable Establishments",
    "sg:phone":"+33 5 49 50 44 21",
    "sg:postcode":"86110",
    "sg:province":"Poitou-Charentes",
    "wof:name":"Girardeau Smacs S.a.r.l.",
    "wof:placetype":"venue"
},
  "geometry": {"coordinates":[0.206689,46.741806],"type":"Point"}
}