{
  "type": "Feature",
  "properties": {
    "addr:full":"1 Place Schneider 71200 Le Creusot Le Creusot Bourgogne 71200",
    "addr:housenumber":"1",
    "addr:postcode":"71200;71200",
    "addr:street":"Place Schneider",
    "iso:country":"FR",
    "sg:address":"1 Place Schneider 71200 Le Creusot",
    "sg:city":"Le Creusot",
    "sg:classifiers":[
        {
            "category":"Professional",
            "subcategory":"Printing & Photocopies",
            "type":"Services"
        }
    ],
    "sg:phone":"+33 3 85 80 34 34",
    "sg:postcode":"71200",
    "sg:province":"Bourgogne",
    "sg:tags":[
        "publishing"
    ],
    "wof:name":"Les Journaux De Saone Et Loire (jsl)",
    "wof:placetype":"venue"
},
  "geometry": {"coordinates":[4.420737,46.806065],"type":"Point"}
}