{
  "type": "Feature",
  "properties": {
    "iso:country":"FR",
    "sg:address":"41, Rue du G\u00e9n\u00e9ral de Gaulle, 59110 La Madeleine",
    "sg:orig_category":"Unclassifiable Establishments",
    "sg:phone":"+33 802 01 02 03",
    "sg:province":"Nord Pas-de-Calais",
    "wof:name":"N.c. Num\u00e9ric\u00e2ble S.n.c.",
    "wof:placetype":"venue"
},
  "geometry": {"coordinates":[3.070888,50.650116],"type":"Point"}
}