{
  "type": "Feature",
  "properties": {
    "addr:full":"Zac De L'Orme Rond 77170 Servon Ile de France 77170",
    "addr:postcode":"77170;ile;77170",
    "addr:street":"Zac De L'Orme Rond;France",
    "iso:country":"FR",
    "sg:address":"Zac De L'Orme Rond 77170 Servon",
    "sg:classifiers":[
        {
            "category":"Wholesale",
            "subcategory":"Farm Supplies",
            "type":"Manufacturing & Wholesale Goods"
        }
    ],
    "sg:phone":"+33 1 64 05 84 84",
    "sg:postcode":"77170",
    "sg:province":"Ile de France",
    "sg:tags":[
        "-",
        "machine",
        "equipment",
        "engineering",
        "machinery",
        "mechanical",
        "agriculture"
    ],
    "wof:name":"Jardins Loisirs",
    "wof:placetype":"venue"
},
  "geometry": {"coordinates":[2.58621,48.715858],"type":"Point"}
}