{
  "type": "Feature",
  "properties": {
    "addr:full":"B.P. 99, 92313 S\u00e8vres C\u00e9dex^^2, Rue Troyon, 92310 S\u00e8vres Ile de France 92310",
    "addr:postcode":"92313;92310;92310",
    "addr:street":"B.P. 99;Rue Troyon",
    "iso:country":"FR",
    "sg:address":"B.P. 99, 92313 S\u00e8vres C\u00e9dex^^2, Rue Troyon, 92310 S\u00e8vres",
    "sg:orig_category":"Non-Classified Establishments",
    "sg:phone":"+33 1 46 23 01 29",
    "sg:postcode":"92310",
    "sg:province":"Ile de France",
    "wof:name":"A.c.s.l. S.a.r.l.",
    "wof:placetype":"venue"
},
  "geometry": {"coordinates":[2.212127,48.824337],"type":"Point"}
}