{
  "type": "Feature",
  "properties": {
    "iso:country":"FR",
    "sg:address":"1 Bd De L'Industrie 28500 Vernouillet",
    "sg:city":"Vernouillet",
    "sg:classifiers":[
        {
            "category":"Banks & Credit Unions",
            "subcategory":"Investment Brokerage",
            "type":"Services"
        }
    ],
    "sg:phone":"+33 2 37 38 05 40",
    "sg:postcode":"28500",
    "sg:province":"Centre",
    "sg:tags":[
        "-",
        "transport",
        "related"
    ],
    "wof:name":"Danzas Dhl",
    "wof:placetype":"venue"
},
  "geometry": {"coordinates":[1.44802,48.719109],"type":"Point"}
}