{
  "type": "Feature",
  "properties": {
    "addr:full":"Chem Paul Madon Espace Frioul 83160 La Valette Du Var Centre",
    "addr:postcode":"83160",
    "addr:street":"La Valette Du Var Centre",
    "iso:country":"FR",
    "sg:address":"Chem Paul Madon Espace Frioul 83160 La Valette Du Var",
    "sg:classifiers":[
        {
            "category":"Professional",
            "subcategory":"Business Services",
            "type":"Services"
        }
    ],
    "sg:phone":"+33 4 94 08 31 98",
    "sg:province":"Centre",
    "sg:tags":[
        "information",
        "advice",
        "technology",
        "software"
    ],
    "wof:name":"Made Sa",
    "wof:placetype":"venue"
},
  "geometry": {"coordinates":[5.980705,43.136925],"type":"Point"}
}