{
  "type": "Feature",
  "properties": {
    "addr:full":"20 rue Am\u00e9d\u00e9e Guerard 89100 Sens Sens Bourgogne 89100",
    "addr:housenumber":"20",
    "addr:postcode":"89100;89100",
    "addr:street":"Rue Ame\u0301De\u0301E Guerard",
    "iso:country":"FR",
    "sg:address":"20 rue Am\u00e9d\u00e9e Guerard 89100 Sens",
    "sg:city":"Sens",
    "sg:classifiers":[
        {
            "category":"Food & Beverages",
            "subcategory":"Groceries & Convenience Stores",
            "type":"Retail Goods"
        }
    ],
    "sg:phone":"+33 3 86 83 96 40",
    "sg:postcode":"89100",
    "sg:province":"Bourgogne",
    "sg:tags":[
        "flour",
        "meal"
    ],
    "wof:name":"Moulins Dum\u00e9e Sa",
    "wof:placetype":"venue"
},
  "geometry": {"coordinates":[3.296384,48.195934],"type":"Point"}
}