{
  "type": "Feature",
  "properties": {
    "addr:full":"B.P. 22, 60220 Formerie^^Rte de Grusmenil, 60220 Formerie Picardie 60220",
    "addr:postcode":"60220;60220;60220",
    "addr:street":"B.P. 22",
    "iso:country":"FR",
    "sg:address":"B.P. 22, 60220 Formerie^^Rte de Grusmenil, 60220 Formerie",
    "sg:orig_category":"Non-Classified Establishments",
    "sg:phone":"+33 3 44 04 04 26",
    "sg:postcode":"60220",
    "sg:province":"Picardie",
    "wof:name":"Corro Olivier S.a.",
    "wof:placetype":"venue"
},
  "geometry": {"coordinates":[1.730822,49.650074],"type":"Point"}
}