{
  "type": "Feature",
  "properties": {
    "addr:full":"6, Rue Diderot, 38000 Grenoble Rhone-Alpes",
    "addr:housenumber":"6",
    "addr:postcode":"38000",
    "addr:street":"Rue Diderot",
    "iso:country":"FR",
    "sg:address":"6, Rue Diderot, 38000 Grenoble",
    "sg:orig_category":"Unclassifiable Establishments",
    "sg:phone":"+33 4 76 21 17 72",
    "sg:province":"Rhone-Alpes",
    "wof:name":"Techniplan S.a.",
    "wof:placetype":"venue"
},
  "geometry": {"coordinates":[5.705859,45.189251],"type":"Point"}
}