{
  "type": "Feature",
  "properties": {
    "iso:country":"FR",
    "sg:address":"Grangette 89520 Thury",
    "sg:city":"Thury",
    "sg:orig_category":"Unclassifiable Establishments",
    "sg:phone":"+33 3 86 45 25 85",
    "sg:postcode":"89520",
    "sg:province":"Bourgogne",
    "wof:name":"Mikadel S.a.r.l.",
    "wof:placetype":"venue"
},
  "geometry": {"coordinates":[3.31741,47.592484],"type":"Point"}
}