{
  "type": "Feature",
  "properties": {
    "addr:full":"272, Bd du Pr\u00e9sident Wilson, 33000 Bordeaux Bordeaux Aquitaine 33000",
    "addr:housenumber":"272",
    "addr:postcode":"33000;33000",
    "addr:street":"Bd Du Pre\u0301Sident Wilson",
    "iso:country":"FR",
    "sg:address":"272, Bd du Pr\u00e9sident Wilson, 33000 Bordeaux",
    "sg:city":"Bordeaux",
    "sg:orig_category":"Non-Classified Establishments",
    "sg:phone":"+33 5 56 01 42 90",
    "sg:postcode":"33000",
    "sg:province":"Aquitaine",
    "wof:name":"Apajh Atelier Du Site",
    "wof:placetype":"venue"
},
  "geometry": {"coordinates":[-0.596929,44.84885],"type":"Point"}
}