{
  "type": "Feature",
  "properties": {
    "iso:country":"FR",
    "sg:address":"Parc d'Activit\u00e9s Ayguette",
    "sg:city":"Vaison la Romaine",
    "sg:orig_category":"Unclassifiable Establishments",
    "sg:phone":"+33 4 90 36 39 39",
    "sg:postcode":"84110",
    "sg:province":"Champagne",
    "wof:name":"Sanz S.a.r.l.",
    "wof:placetype":"venue"
},
  "geometry": {"coordinates":[5.089168,44.24324],"type":"Point"}
}