{
  "type": "Feature",
  "properties": {
    "addr:full":"24, RN 10 - Maison Neuve , 78690 Les Essarts le Roi Ile de France 78690",
    "addr:housenumber":"24",
    "addr:postcode":"78690;78690",
    "addr:street":"Rn 10 Maison Neuve",
    "iso:country":"FR",
    "sg:address":"24, RN 10 - Maison Neuve , 78690 Les Essarts le Roi",
    "sg:orig_category":"Non-Classified Establishments",
    "sg:phone":"+33 1 30 41 68 68",
    "sg:postcode":"78690",
    "sg:province":"Ile de France",
    "wof:name":"Catecom S.a.",
    "wof:placetype":"venue"
},
  "geometry": {"coordinates":[1.880163,48.715771],"type":"Point"}
}