{
  "type": "Feature",
  "properties": {
    "iso:country":"FR",
    "sg:address":"1, Rue de l'Epau, 59230 Sars et Rosi\u00e8res",
    "sg:orig_category":"Unclassifiable Establishments",
    "sg:phone":"+33 3 27 48 35 00",
    "sg:province":"Nord Pas-de-Calais",
    "wof:name":"Math\u00e9na N\u00e9goce S.a.",
    "wof:placetype":"venue"
},
  "geometry": {"coordinates":[3.337271,50.442986],"type":"Point"}
}