{
  "type": "Feature",
  "properties": {
    "iso:country":"FR",
    "sg:address":"7 Rue De Lavoisier",
    "sg:city":"Blagnac",
    "sg:classifiers":[
        {
            "category":"Banks & Credit Unions",
            "subcategory":"Financial Services",
            "type":"Services"
        }
    ],
    "sg:phone":"+33 5 61 71 25 08",
    "sg:postcode":"31700",
    "sg:province":"Midi Pyr\u00e9n\u00e9es",
    "sg:tags":[
        "banking",
        "finance",
        "insurance"
    ],
    "wof:name":"Exco Fiduciaire Du Sud Ouest",
    "wof:placetype":"venue"
},
  "geometry": {"coordinates":[1.39684,43.634586],"type":"Point"}
}