{
  "type": "Feature",
  "properties": {
    "addr:full":"12 Place Saussure 74400 Chamonix Mont Blanc Rhone-Alpes 74400",
    "addr:housenumber":"12",
    "addr:postcode":"74400;74400",
    "addr:street":"Place Saussure;Mont;Rhone-Alpes",
    "iso:country":"FR",
    "sg:address":"12 Place Saussure 74400 Chamonix Mont Blanc",
    "sg:classifiers":[
        {
            "category":"Sports & Exercise",
            "subcategory":"Sports Center",
            "type":"Entertainment"
        }
    ],
    "sg:phone":"+33 4 50 53 07 65",
    "sg:postcode":"74400",
    "sg:province":"Rhone-Alpes",
    "sg:tags":[
        "game"
    ],
    "wof:name":"Participation Et Dinvestissement Du Casino De Sa",
    "wof:placetype":"venue"
},
  "geometry": {"coordinates":[6.870389,45.922829],"type":"Point"}
}