{
  "type": "Feature",
  "properties": {
    "addr:full":"Parc d'Activit\u00e9s de Sologne Lamotte Beuvron Centre 41600",
    "addr:postcode":"41600",
    "iso:country":"FR",
    "sg:address":"Parc d'Activit\u00e9s de Sologne",
    "sg:city":"Lamotte Beuvron",
    "sg:orig_category":"Unclassifiable Establishments",
    "sg:phone":"+33 2 54 88 05 31",
    "sg:postcode":"41600",
    "sg:province":"Centre",
    "wof:name":"Festins De Sologne E.u.r.l.",
    "wof:placetype":"venue"
},
  "geometry": {"coordinates":[2.039786,47.536007],"type":"Point"}
}