{
  "type": "Feature",
  "properties": {
    "addr:full":"6 R Rochambeau 75009 Paris Ile de France",
    "addr:housenumber":"6",
    "addr:postcode":"75009",
    "addr:street":"R Rochambeau",
    "iso:country":"FR",
    "sg:address":"6 R Rochambeau 75009 Paris",
    "sg:classifiers":[
        {
            "category":"Utilities",
            "subcategory":"Telephone",
            "type":"Services"
        }
    ],
    "sg:phone":"+33 1 48 78 93 64",
    "sg:province":"Ile de France",
    "sg:tags":[
        "telecommunication"
    ],
    "wof:name":"Ets Bailleux Balvay Sa",
    "wof:placetype":"venue"
},
  "geometry": {"coordinates":[2.346399,48.87738],"type":"Point"}
}