{
  "type": "Feature",
  "properties": {
    "iso:country":"FR",
    "sg:address":"B.P. 2056, 87070 Limoges C\u00e9dex^^Rue Nicolas Appert - ZI Nord, 87280 Limoges",
    "sg:orig_category":"Non-Classified Establishments",
    "sg:phone":"+33 5 55 37 27 40",
    "sg:province":"Limousin",
    "wof:name":"Sanicentre Assainissement S.a.",
    "wof:placetype":"venue"
},
  "geometry": {"coordinates":[1.299435,45.914837],"type":"Point"}
}