{
  "type": "Feature",
  "properties": {
    "iso:country":"FR",
    "sg:address":"52, Rue de Metz, 57470 Hombourg Haut",
    "sg:orig_category":"Hydrauliques, Accessoires Joints Joints pour hydraulique et pneumatique Pompes hydrauliques Raccords",
    "sg:phone":"+33 3 87 90 55 83",
    "sg:postcode":"57470",
    "sg:province":"Lorraine",
    "wof:name":"Circonflex Hydraulique S.a.r.l.",
    "wof:placetype":"venue"
},
  "geometry": {"coordinates":[6.783923,49.125362],"type":"Point"}
}