{
  "type": "Feature",
  "properties": {
    "iso:country":"FR",
    "sg:address":"13 R Ambroise Par\u00e9 BP 44 Le Forum 22360 Langueux",
    "sg:city":"Langueux",
    "sg:classifiers":[
        {
            "category":"Professional",
            "subcategory":"Advertising",
            "type":"Services"
        }
    ],
    "sg:phone":"+33 2 96 52 59 52",
    "sg:postcode":"22360",
    "sg:province":"Bretagne",
    "sg:tags":[
        "information",
        "medium",
        "communication"
    ],
    "wof:name":"Precom",
    "wof:placetype":"venue"
},
  "geometry": {"coordinates":[-2.715357,48.494778],"type":"Point"}
}