{
  "type": "Feature",
  "properties": {
    "iso:country":"FR",
    "sg:address":"B.P. 14, 45720 Coullons C\u00e9dex^^Rte Saint Gondon - La Tuilerie , 45720 Coullons",
    "sg:city":"Coullons",
    "sg:orig_category":"Non-Classified Establishments",
    "sg:phone":"+33 2 38 36 11 18",
    "sg:postcode":"45720",
    "sg:province":"Centre",
    "wof:name":"Saget S.n. S.a.",
    "wof:placetype":"venue"
},
  "geometry": {"coordinates":[2.492695,47.621101],"type":"Point"}
}