{
  "type": "Feature",
  "properties": {
    "addr:full":"B.P. 70 Saint Claude C\u00e9dex^^Village de Chaumont 39200 Saint Claude Franche Comt\u00e9 39202",
    "addr:housenumber":"70",
    "addr:postcode":"39200;39202",
    "addr:street":"B.P.;Saint Claude Ce\u0301Dex^^Village De Chaumont;Franche Comte\u0301",
    "iso:country":"FR",
    "sg:address":"B.P. 70",
    "sg:city":"Saint Claude C\u00e9dex^^Village de Chaumont 39200 Saint Claude",
    "sg:orig_category":"Non-Classified Establishments",
    "sg:phone":"+33 3 84 45 16 51",
    "sg:postcode":"39202",
    "sg:province":"Franche Comt\u00e9",
    "wof:name":"Etablissements Ulysse Poncet S.a.",
    "wof:placetype":"venue"
},
  "geometry": {"coordinates":[5.84194,46.34193],"type":"Point"}
}