{
  "type": "Feature",
  "properties": {
    "iso:country":"FR",
    "sg:address":"B.P. 70",
    "sg:city":"Saint Claude C\u00e9dex^^Village de Chaumont 39200 Saint Claude",
    "sg:orig_category":"Non-Classified Establishments",
    "sg:phone":"+33 3 84 45 16 51",
    "sg:postcode":"39202",
    "sg:province":"Franche Comt\u00e9",
    "wof:name":"Etablissements Ulysse Poncet S.a.",
    "wof:placetype":"venue"
},
  "geometry": {"coordinates":[5.84194,46.34193],"type":"Point"}
}