{
  "type": "Feature",
  "properties": {
    "iso:country":"FR",
    "sg:address":"64420 Espoey",
    "sg:city":"Espoey",
    "sg:orig_category":"Unclassifiable Establishments",
    "sg:phone":"+33 5 59 16 09 00",
    "sg:postcode":"64420",
    "sg:province":"Aquitaine",
    "wof:name":"Laiterie Pelissi\u00e9 S.a.",
    "wof:placetype":"venue"
},
  "geometry": {"coordinates":[-0.168639,43.245323],"type":"Point"}
}