{
  "type": "Feature",
  "properties": {
    "iso:country":"FR",
    "sg:address":"ZA Les Bosquets 4",
    "sg:city":"M\u00e9ry sur Oise",
    "sg:orig_category":"Unclassifiable Establishments",
    "sg:phone":"+33 1 30 36 24 24",
    "sg:postcode":"95540",
    "sg:province":"Ile de France",
    "wof:name":"Alliance Instruments S.a.",
    "wof:placetype":"venue"
},
  "geometry": {"coordinates":[2.166155,49.057209],"type":"Point"}
}