{
  "type": "Feature",
  "properties": {
    "addr:full":"1 Place De La Comedie C C Hotel De Ville 51000 Chalons En Champagne Champagne",
    "addr:housenumber":"1;de",
    "addr:postcode":"51000",
    "addr:street":"Place De La Comedie C;Ville",
    "iso:country":"FR",
    "sg:address":"1 Place De La Comedie C C Hotel De Ville 51000 Chalons En Champagne",
    "sg:classifiers":[
        {
            "category":"Professional",
            "subcategory":"Printing & Photocopies",
            "type":"Services"
        }
    ],
    "sg:phone":"+33 3 26 21 98 98",
    "sg:province":"Champagne",
    "sg:tags":[
        "publishing"
    ],
    "wof:name":"Societe De Presse Et D'edition De La Vallee De La Marne (spevm Sa)",
    "wof:placetype":"venue"
},
  "geometry": {"coordinates":[4.355399,48.955708],"type":"Point"}
}