{
  "type": "Feature",
  "properties": {
    "addr:full":"10 rue du G\u00e9n\u00e9ral Leclerc 67700 Monswiller Monswiller Alsace 67700",
    "addr:housenumber":"10",
    "addr:postcode":"67700;67700",
    "addr:street":"Rue Du Ge\u0301Ne\u0301Ral Leclerc;Monswiller",
    "iso:country":"FR",
    "sg:address":"10 rue du G\u00e9n\u00e9ral Leclerc 67700 Monswiller",
    "sg:city":"Monswiller",
    "sg:classifiers":[
        {
            "category":"Manufacturing",
            "subcategory":"Wood Products",
            "type":"Manufacturing & Wholesale Goods"
        }
    ],
    "sg:phone":"+33 3 88 02 15 15",
    "sg:postcode":"67700",
    "sg:province":"Alsace",
    "sg:tags":[
        "working",
        "drill"
    ],
    "wof:name":"Ets Charles Bonnet Et Fils Sarl",
    "wof:placetype":"venue"
},
  "geometry": {"coordinates":[7.376812,48.755451],"type":"Point"}
}