{
  "type": "Feature",
  "properties": {
    "iso:country":"FR",
    "sg:address":"Rue Ren\u00e9 Cassin",
    "sg:city":"Chartres",
    "sg:orig_category":"Non-Classified Establishments",
    "sg:phone":"+33 2 37 35 08 82",
    "sg:postcode":"28000",
    "sg:province":"Centre",
    "wof:name":"B.m.c.e. Point P S.a.",
    "wof:placetype":"venue"
},
  "geometry": {"coordinates":[1.52517,48.439884],"type":"Point"}
}