{
  "type": "Feature",
  "properties": {
    "addr:full":"1 Avenue Pierre De Coubertin 75013 Paris Ile de France 75013",
    "addr:housenumber":"1",
    "addr:postcode":"75013;75013",
    "addr:street":"Avenue Pierre De Coubertin",
    "iso:country":"FR",
    "sg:address":"1 Avenue Pierre De Coubertin 75013 Paris",
    "sg:classifiers":[
        {
            "category":"Professional",
            "subcategory":"Business Services",
            "type":"Services"
        }
    ],
    "sg:phone":"+33 1 40 78 28 00",
    "sg:postcode":"75013",
    "sg:province":"Ile de France",
    "sg:tags":[
        "body",
        "advice",
        "sport",
        "game",
        "entertainment"
    ],
    "wof:name":"Comite National Olympique Sportif Fran\u00c7ais",
    "wof:placetype":"venue"
},
  "geometry": {"coordinates":[2.344658,48.818954],"type":"Point"}
}