{
  "type": "Feature",
  "properties": {
    "addr:full":"Ccal 78140 V\u00e9lizy Villacoublay Ile de France 78140",
    "addr:postcode":"78140;78140",
    "addr:street":"Ccal",
    "iso:country":"FR",
    "sg:address":"Ccal 78140 V\u00e9lizy Villacoublay",
    "sg:classifiers":[
        {
            "category":"Health Services",
            "subcategory":"Optometrist",
            "type":"Services"
        }
    ],
    "sg:phone":"+33 1 34 65 16 79",
    "sg:postcode":"78140",
    "sg:province":"Ile de France",
    "sg:tags":[
        "instrument",
        "optical",
        "-",
        "precision",
        "equipment"
    ],
    "wof:name":"Les Opticiens Conseils Sa",
    "wof:placetype":"venue"
},
  "geometry": {"coordinates":[2.18246,48.78503],"type":"Point"}
}