{
  "type": "Feature",
  "properties": {
    "iso:country":"FR",
    "sg:address":"5 avenue Gabriel P\u00e9ri 93800 Epinay sur Seine",
    "sg:classifiers":[
        {
            "category":"Building & Trades",
            "subcategory":"Landscaping Services",
            "type":"Services"
        }
    ],
    "sg:phone":"+33 1 49 40 00 11",
    "sg:postcode":"93800",
    "sg:province":"Ile de France",
    "sg:tags":[
        "east-west"
    ],
    "wof:name":"Ww Sarl",
    "wof:placetype":"venue"
},
  "geometry": {"coordinates":[2.307158,48.954174],"type":"Point"}
}