{
  "type": "Feature",
  "properties": {
    "iso:country":"FR",
    "sg:address":"2 place du Maroc 75019 Paris",
    "sg:classifiers":[
        {
            "category":"Wholesale",
            "subcategory":"Machinery & Supplies",
            "type":"Manufacturing & Wholesale Goods"
        }
    ],
    "sg:phone":"+33 1 40 34 34 06",
    "sg:postcode":"75019",
    "sg:province":"Ile de France",
    "sg:tags":[
        "agricultural",
        "equipment"
    ],
    "wof:name":"Yamamira Sarl",
    "wof:placetype":"venue"
},
  "geometry": {"coordinates":[2.369344,48.886818],"type":"Point"}
}