{
  "type": "Feature",
  "properties": {
    "iso:country":"FR",
    "sg:address":"Zac La Baume 34290 Servian",
    "sg:classifiers":[
        {
            "category":"Food Court",
            "type":"Food & Drink"
        }
    ],
    "sg:phone":"+33 4 67 39 29 70",
    "sg:postcode":"34290",
    "sg:province":"Languedoc-Roussillon",
    "sg:tags":[
        "product",
        "related"
    ],
    "wof:name":"Dsm Food Specialities Sas",
    "wof:placetype":"venue"
},
  "geometry": {"coordinates":[3.307045,43.428188],"type":"Point"}
}