{
  "type": "Feature",
  "properties": {
    "addr:full":"Pech Mortier 24200 Marcillac St Quentin Carsac-Aillac Aquitaine 24200",
    "addr:postcode":"24200 marcillac st;24200",
    "addr:street":"Mortier",
    "iso:country":"FR",
    "sg:address":"Pech Mortier 24200 Marcillac St Quentin",
    "sg:city":"Carsac-Aillac",
    "sg:classifiers":[
        {
            "category":"Food & Beverages",
            "subcategory":"Meat & Fish",
            "type":"Retail Goods"
        }
    ],
    "sg:phone":"+33 5 53 29 67 98",
    "sg:postcode":"24200",
    "sg:province":"Aquitaine",
    "sg:tags":[
        "preserve",
        "cooked",
        "product",
        "related"
    ],
    "wof:name":"Sarl Lasserre",
    "wof:placetype":"venue"
},
  "geometry": {"coordinates":[1.174218,44.949116],"type":"Point"}
}