{
  "type": "Feature",
  "properties": {
    "iso:country":"FR",
    "sg:address":"5 avenue des Fr\u00e8res Lumi\u00e8re 94354 Villiers sur Marne",
    "sg:classifiers":[
        {
            "category":"Communications",
            "subcategory":"Television Station",
            "type":"Services"
        }
    ],
    "sg:phone":"+33 1 49 41 43 00",
    "sg:province":"Midi Pyr\u00e9n\u00e9es",
    "sg:tags":[
        "monitor"
    ],
    "wof:name":"Iiyama France Sarl",
    "wof:placetype":"venue"
},
  "geometry": {"coordinates":[2.536168,48.83828],"type":"Point"}
}