{
  "type": "Feature",
  "properties": {
    "addr:full":"Route Foix Pamiers Cedex Midi Pyr\u00e9n\u00e9es 09106",
    "addr:postcode":"pamiers;09106",
    "addr:street":"Route Foix",
    "iso:country":"FR",
    "sg:address":"Route Foix",
    "sg:city":"Pamiers Cedex",
    "sg:classifiers":[
        {
            "category":"Banks & Credit Unions",
            "subcategory":"Financial Services",
            "type":"Services"
        }
    ],
    "sg:phone":"+33 5 61 60 93 20",
    "sg:postcode":"09106",
    "sg:province":"Midi Pyr\u00e9n\u00e9es",
    "sg:tags":[
        "banking",
        "finance",
        "insurance"
    ],
    "wof:name":"Faure Et Cie (unimag) Sa",
    "wof:placetype":"venue"
},
  "geometry": {"coordinates":[1.620475,43.104019],"type":"Point"}
}