{
  "type": "Feature",
  "properties": {
    "iso:country":"FR",
    "sg:address":"1488 Route De Gravin",
    "sg:city":"Grands Clos 74300 Magland",
    "sg:classifiers":[
        {
            "category":"Manufacturing",
            "subcategory":"Tools & Machinery",
            "type":"Manufacturing & Wholesale Goods"
        }
    ],
    "sg:phone":"+33 4 50 90 20 36",
    "sg:postcode":"74300",
    "sg:province":"Rhone-Alpes",
    "sg:tags":[
        "metallurgy",
        "metalworking"
    ],
    "wof:name":"Decolletage Des Grands Clos",
    "wof:placetype":"venue"
},
  "geometry": {"coordinates":[6.633185,45.987919],"type":"Point"}
}