{
  "type": "Feature",
  "properties": {
    "addr:full":"Rue Des Sablons Za P\u00f4les 45 45140 Ormes Ormes Centre 45140",
    "addr:housenumber":"45",
    "addr:postcode":"45140;45140",
    "addr:street":"Rue Des Sablons Za Po\u0302Les",
    "iso:country":"FR",
    "sg:address":"Rue Des Sablons Za P\u00f4les 45 45140 Ormes",
    "sg:city":"Ormes",
    "sg:classifiers":[
        {
            "category":"Shopping",
            "subcategory":"Computers & Home Electronics",
            "type":"Retail Goods"
        }
    ],
    "sg:phone":"+33 2 38 70 88 88",
    "sg:postcode":"45140",
    "sg:province":"Centre",
    "sg:tags":[
        "equipment",
        "electrical",
        "component",
        "electric",
        "electronic"
    ],
    "wof:name":"Cidm",
    "wof:placetype":"venue"
},
  "geometry": {"coordinates":[1.8745,47.912949],"type":"Point"}
}