{
  "type": "Feature",
  "properties": {
    "addr:full":"245, Av. de l'Hermitage - ZA de Berret, 30200 Bagnols sur C\u00e8ze Languedoc-Roussillon 30200",
    "addr:housenumber":"245",
    "addr:postcode":"30200;30200",
    "addr:street":"Av. De L'Hermitage Za De Berret;Ce\u0300Ze",
    "iso:country":"FR",
    "sg:address":"245, Av. de l'Hermitage - ZA de Berret, 30200 Bagnols sur C\u00e8ze",
    "sg:orig_category":"Non-Classified Establishments",
    "sg:phone":"+33 4 66 90 50 82",
    "sg:postcode":"30200",
    "sg:province":"Languedoc-Roussillon",
    "wof:name":"A.d.e.m.a. G.i.e.",
    "wof:placetype":"venue"
},
  "geometry": {"coordinates":[4.632268,44.157818],"type":"Point"}
}