{
  "type": "Feature",
  "properties": {
    "iso:country":"FR",
    "sg:address":"B.P. 3, 29380 Bannalec^^Rte de Pont Aven, 29380 Bannalec",
    "sg:city":"Bannalec",
    "sg:orig_category":"Non-Classified Establishments",
    "sg:phone":"+33 2 98 39 85 39",
    "sg:postcode":"29380",
    "sg:province":"Bretagne",
    "wof:name":"Les Charcuterie De L'aven S.a.",
    "wof:placetype":"venue"
},
  "geometry": {"coordinates":[-3.689304,47.922436],"type":"Point"}
}