{
  "type": "Feature",
  "properties": {
    "addr:full":"Zone Industrielle de Bleriot Sangatte Nord Pas-de-Calais 62231",
    "addr:postcode":"62231",
    "addr:street":"Zone Industrielle De Bleriot Sangatte Nord",
    "iso:country":"FR",
    "sg:address":"Zone Industrielle de Bleriot",
    "sg:city":"Sangatte",
    "sg:orig_category":"Non-Classified Establishments",
    "sg:phone":"+33 3 21 97 09 08",
    "sg:postcode":"62231",
    "sg:province":"Nord Pas-de-Calais",
    "wof:name":"Brink's S.a.",
    "wof:placetype":"venue"
},
  "geometry": {"coordinates":[1.75819,50.947311],"type":"Point"}
}