{
  "type": "Feature",
  "properties": {
    "addr:full":"3, Rue des Lilas, 25250 Blussans Franche Comt\u00e9 25250",
    "addr:housenumber":"3",
    "addr:postcode":"25250;25250",
    "addr:street":"Rue Des Lilas;Franche Comte\u0301",
    "iso:country":"FR",
    "sg:address":"3, Rue des Lilas, 25250 Blussans",
    "sg:orig_category":"Non-Classified Establishments",
    "sg:phone":"+33 3 81 92 71 41",
    "sg:postcode":"25250",
    "sg:province":"Franche Comt\u00e9",
    "wof:name":"Dodivers S.a.",
    "wof:placetype":"venue"
},
  "geometry": {"coordinates":[6.607671,47.427345],"type":"Point"}
}