{
  "type": "Feature",
  "properties": {
    "iso:country":"FR",
    "sg:address":"30, Rte du Marillais, 49410 Saint Florent le Vieil",
    "sg:orig_category":"Non-Classified Establishments",
    "sg:phone":"+33 1 41 72 50 71",
    "sg:province":"Pays de Loire",
    "wof:name":"V.s.i. S.a.r.l.",
    "wof:placetype":"venue"
},
  "geometry": {"coordinates":[-0.927774,47.320755],"type":"Point"}
}