{
  "type": "Feature",
  "properties": {
    "addr:full":"B.P. 17, 92140 Clamart C\u00e9dex^^25, Rue de la Gaiet\u00e9, 92140 Clamart Ile de France",
    "addr:postcode":"92140;92140;ile",
    "addr:street":"B.P. 17;Rue De La Gaiete\u0301",
    "iso:country":"FR",
    "sg:address":"B.P. 17, 92140 Clamart C\u00e9dex^^25, Rue de la Gaiet\u00e9, 92140 Clamart",
    "sg:orig_category":"Non-Classified Establishments",
    "sg:phone":"+33 1 46 30 82 42",
    "sg:province":"Ile de France",
    "wof:name":"Sp\u00e9cialit\u00e9s T.a. S.a.",
    "wof:placetype":"venue"
},
  "geometry": {"coordinates":[2.262025,48.80027],"type":"Point"}
}