{
  "type": "Feature",
  "properties": {
    "addr:full":"La Jameti\u00e9re 49390 Vernoil Pays de Loire",
    "addr:postcode":"49390",
    "addr:street":"Vernoil",
    "iso:country":"FR",
    "sg:address":"La Jameti\u00e9re 49390 Vernoil",
    "sg:classifiers":[
        {
            "category":"Home & Garden",
            "subcategory":"Furniture",
            "type":"Retail Goods"
        }
    ],
    "sg:phone":"+33 2 41 51 51 20",
    "sg:province":"Pays de Loire",
    "sg:tags":[
        "wood"
    ],
    "wof:name":"Barthelemy Sa",
    "wof:placetype":"venue"
},
  "geometry": {"coordinates":[0.07644,47.340809],"type":"Point"}
}