{
  "type": "Feature",
  "properties": {
    "addr:full":"Z I 60420 MAIGNELAY MONTIGNY Picardie 60420",
    "addr:postcode":"60420;60420",
    "addr:street":"Z",
    "iso:country":"FR",
    "sg:address":"Z I 60420 MAIGNELAY MONTIGNY",
    "sg:classifiers":[
        {
            "category":"Shopping",
            "subcategory":"Pets & Pet Supplies",
            "type":"Retail Goods"
        }
    ],
    "sg:phone":"+33 3 44 51 15 09",
    "sg:postcode":"60420",
    "sg:province":"Picardie",
    "sg:tags":[
        "food",
        "dog",
        "cat"
    ],
    "wof:name":"M.b.v. Diffusion Sarl",
    "wof:placetype":"venue"
},
  "geometry": {"coordinates":[2.515835,49.55183],"type":"Point"}
}