{
  "type": "Feature",
  "properties": {
    "iso:country":"FR",
    "sg:address":"22 Pl Des Vosges La D\u00e9fense 5",
    "sg:city":"Monge 92979 Paris La D\u00e9fense Cedex",
    "sg:classifiers":[
        {
            "category":"Shopping",
            "subcategory":"Computers & Home Electronics",
            "type":"Retail Goods"
        }
    ],
    "sg:phone":"+33 1 41 99 41 99",
    "sg:province":"Midi Pyr\u00e9n\u00e9es",
    "sg:tags":[
        "equipment",
        "household",
        "electrical",
        "appliance",
        "electronic"
    ],
    "wof:name":"Moulinex",
    "wof:placetype":"venue"
},
  "geometry": {"coordinates":[2.24119,48.888939],"type":"Point"}
}