{
  "type": "Feature",
  "properties": {
    "iso:country":"FR",
    "sg:address":"Chemin du Moulin Neuf",
    "sg:city":"Manosque",
    "sg:orig_category":"Unclassifiable Establishments",
    "sg:phone":"+33 4 92 72 02 31",
    "sg:postcode":"04100",
    "sg:province":"Aquitaine",
    "wof:name":"S.e.e.a.p. S.a.r.l. - Entreprise Electrique Alpes Provence Imbert",
    "wof:placetype":"venue"
},
  "geometry": {"coordinates":[5.798105,43.827614],"type":"Point"}
}