{
  "type": "Feature",
  "properties": {
    "addr:full":"Rte de Rochepaule Lalouvesc Rhone-Alpes 07520",
    "addr:postcode":"07520",
    "addr:street":"Rte De Rochepaule;Rhone-Alpes",
    "iso:country":"FR",
    "sg:address":"Rte de Rochepaule",
    "sg:city":"Lalouvesc",
    "sg:orig_category":"Non-Classified Establishments",
    "sg:phone":"+33 4 75 67 88 00",
    "sg:postcode":"07520",
    "sg:province":"Rhone-Alpes",
    "wof:name":"S.a.m.o.v. S.a. - Soci\u00e9t\u00e9 Anonyme M\u00e9canique Outillage Vivarais",
    "wof:placetype":"venue"
},
  "geometry": {"coordinates":[4.507485,45.11409],"type":"Point"}
}