{
  "type": "Feature",
  "properties": {
    "iso:country":"FR",
    "sg:address":"4, Av. des Fr\u00e8res Montgolfier, 63170 Aubi\u00e8re",
    "sg:city":"Aubi\u00e8re",
    "sg:orig_category":"Unclassifiable Establishments",
    "sg:phone":"+33 4 73 26 34 94",
    "sg:postcode":"63170",
    "sg:province":"Auvergne",
    "wof:name":"A.v.p.s. S.a.r.l. - Audio-visuel Photo-syst\u00e8me",
    "wof:placetype":"venue"
},
  "geometry": {"coordinates":[3.110975,45.7509],"type":"Point"}
}