{
  "type": "Feature",
  "properties": {
    "addr:full":"Route St L\u00e9on la Couzenote 03220 JALIGNY SUR BESBRE Vaumas Auvergne 03220",
    "addr:postcode":"03220;03220",
    "addr:street":"Route St Le\u0301On La Couzenote",
    "iso:country":"FR",
    "sg:address":"Route St L\u00e9on la Couzenote 03220 JALIGNY SUR BESBRE",
    "sg:city":"Vaumas",
    "sg:classifiers":[
        {
            "category":"Education",
            "subcategory":"Dance Studio",
            "type":"Public Place"
        }
    ],
    "sg:phone":"+33 4 70 34 82 80",
    "sg:postcode":"03220",
    "sg:province":"Auvergne",
    "sg:tags":[
        "pallet"
    ],
    "wof:name":"Bois Et Scierie De La Besbre Sarl",
    "wof:placetype":"venue"
},
  "geometry": {"coordinates":[3.60482,46.377499],"type":"Point"}
}