{
  "type": "Feature",
  "properties": {
    "iso:country":"FR",
    "sg:address":"16, Rue de la C\u00f4te, 54000 Nancy",
    "sg:orig_category":"Unclassifiable Establishments",
    "sg:phone":"+33 3 83 96 59 59",
    "sg:province":"Lorraine",
    "wof:name":"Castor S.a.r.l.",
    "wof:placetype":"venue"
},
  "geometry": {"coordinates":[6.162653,48.691841],"type":"Point"}
}