{
  "type": "Feature",
  "properties": {
    "addr:full":"2, Rue de Lingolsheim, 67201 Eckbolsheim Eckbolsheim Alsace 67201",
    "addr:housenumber":"2",
    "addr:postcode":"67201;67201",
    "addr:street":"Rue De Lingolsheim",
    "iso:country":"FR",
    "sg:address":"2, Rue de Lingolsheim, 67201 Eckbolsheim",
    "sg:city":"Eckbolsheim",
    "sg:orig_category":"Non-Classified Establishments",
    "sg:phone":"+33 3 88 78 92 65",
    "sg:postcode":"67201",
    "sg:province":"Alsace",
    "wof:name":"Charles Etablissements S.a.",
    "wof:placetype":"venue"
},
  "geometry": {"coordinates":[7.687265,48.569473],"type":"Point"}
}