{
  "type": "Feature",
  "properties": {
    "addr:full":"37, Rue Fournet, 14100 Lisieux Lisieux Basse Normandie 14100",
    "addr:housenumber":"37",
    "addr:postcode":"14100;14100",
    "addr:street":"Rue Fournet",
    "iso:country":"FR",
    "sg:address":"37, Rue Fournet, 14100 Lisieux",
    "sg:city":"Lisieux",
    "sg:orig_category":"Unclassifiable Establishments",
    "sg:phone":"+33 2 31 62 08 24",
    "sg:postcode":"14100",
    "sg:province":"Basse Normandie",
    "wof:name":"Mosquet S.a.r.l.",
    "wof:placetype":"venue"
},
  "geometry": {"coordinates":[0.227292,49.136906],"type":"Point"}
}