{
  "type": "Feature",
  "properties": {
    "addr:full":"5, Rue Ir\u00e8ne Joliot Curie, 38320 Eybens Rhone-Alpes 38320",
    "addr:housenumber":"5",
    "addr:postcode":"38320;38320",
    "addr:street":"Rue Ire\u0300Ne Joliot Curie",
    "iso:country":"FR",
    "sg:address":"5, Rue Ir\u00e8ne Joliot Curie, 38320 Eybens",
    "sg:orig_category":"Unclassifiable Establishments",
    "sg:phone":"+33 4 76 25 34 73",
    "sg:postcode":"38320",
    "sg:province":"Rhone-Alpes",
    "wof:name":"Arkiane S.a.r.l.",
    "wof:placetype":"venue"
},
  "geometry": {"coordinates":[5.740476,45.150139],"type":"Point"}
}