{
  "type": "Feature",
  "properties": {
    "addr:full":"33 Rue Prudhomme 60690 La Neuville Sur Oudeuil Picardie 60690",
    "addr:housenumber":"33",
    "addr:postcode":"60690;60690",
    "addr:street":"Rue Prudhomme",
    "iso:country":"FR",
    "sg:address":"33 Rue Prudhomme 60690 La Neuville Sur Oudeuil",
    "sg:classifiers":[
        {
            "category":"Farming",
            "subcategory":"Farm & Veterinary Services",
            "type":"Manufacturing & Wholesale Goods"
        }
    ],
    "sg:phone":"+33 3 44 46 23 93",
    "sg:postcode":"60690",
    "sg:province":"Picardie",
    "sg:tags":[
        "advice",
        "agriculture",
        "livestock",
        "business"
    ],
    "wof:name":"Etablissement Laignier & Fils",
    "wof:placetype":"venue"
},
  "geometry": {"coordinates":[2.012019,49.573215],"type":"Point"}
}