{
  "type": "Feature",
  "properties": {
    "addr:full":"9 boulevard Jean Mermoz 84000 Avignon Centre",
    "addr:housenumber":"9",
    "addr:postcode":"84000",
    "addr:street":"Boulevard Jean Mermoz",
    "iso:country":"FR",
    "sg:address":"9 boulevard Jean Mermoz 84000 Avignon",
    "sg:classifiers":[
        {
            "category":"Shopping",
            "subcategory":"Department Store",
            "type":"Retail Goods"
        }
    ],
    "sg:phone":"+33 4 90 86 14 03",
    "sg:province":"Centre",
    "sg:tags":[
        "linen",
        "bed"
    ],
    "wof:name":"Marat Sa",
    "wof:placetype":"venue"
},
  "geometry": {"coordinates":[4.810849,43.931789],"type":"Point"}
}