{
  "type": "Feature",
  "properties": {
    "addr:full":"11, Porte du Grand Lyon - ZAC Champ du Perrier, 01700 Neyron Rhone-Alpes 01700",
    "addr:housenumber":"11",
    "addr:postcode":"01700;01700",
    "addr:street":"Porte Du Grand;Zac Champ Du Perrier",
    "iso:country":"FR",
    "sg:address":"11, Porte du Grand Lyon - ZAC Champ du Perrier, 01700 Neyron",
    "sg:orig_category":"Non-Classified Establishments",
    "sg:phone":"+33 4 72 01 02 03",
    "sg:postcode":"01700",
    "sg:province":"Rhone-Alpes",
    "wof:name":"S.l.e.t.i. S.a. - Soci\u00e9t\u00e9 Lyonnaise D'equipements Techniques Et Industriels",
    "wof:placetype":"venue"
},
  "geometry": {"coordinates":[4.96153,45.828629],"type":"Point"}
}