{
  "type": "Feature",
  "properties": {
    "iso:country":"FR",
    "sg:address":"Quai Jean Jaur\u00e8s",
    "sg:city":"La Voulte sur Rh\u00f4ne",
    "sg:orig_category":"Unclassifiable Establishments",
    "sg:phone":"+33 4 75 62 46 30",
    "sg:postcode":"07800",
    "sg:province":"Rhone-Alpes",
    "wof:name":"Le Moulin De La Chaume S.a.",
    "wof:placetype":"venue"
},
  "geometry": {"coordinates":[4.790153,44.807415],"type":"Point"}
}