{
  "type": "Feature",
  "properties": {
    "iso:country":"FR",
    "sg:address":"B.P. 303, 59056 Roubaix C\u00e9dex^^40, Rue Boucher de Perthes, 59100 Roubaix",
    "sg:orig_category":"Non-Classified Establishments",
    "sg:phone":"+33 3 20 24 80 51",
    "sg:province":"Nord Pas-de-Calais",
    "wof:name":"Eutex S.a.r.l.",
    "wof:placetype":"venue"
},
  "geometry": {"coordinates":[3.1752,50.691704],"type":"Point"}
}