{
  "type": "Feature",
  "properties": {
    "addr:full":"B.P. 375, 59020 Lille C\u00e9dex^^105, Rue Royale, 59800 Lille Nord Pas-de-Calais",
    "addr:housenumber":"b.p. 375",
    "addr:postcode":"59020;59800",
    "addr:street":"Rue Royale",
    "iso:country":"FR",
    "sg:address":"B.P. 375, 59020 Lille C\u00e9dex^^105, Rue Royale, 59800 Lille",
    "sg:orig_category":"Non-Classified Establishments",
    "sg:phone":"+33 3 20 42 49 00",
    "sg:province":"Nord Pas-de-Calais",
    "wof:name":"L'union G\u00e9n\u00e9rale Du Nord S.a.",
    "wof:placetype":"venue"
},
  "geometry": {"coordinates":[3.08024,50.636189],"type":"Point"}
}