{
  "type": "Feature",
  "properties": {
    "addr:full":"16 Rue Nicolai 69007 Lyon Rhone-Alpes",
    "addr:housenumber":"16",
    "addr:postcode":"69007",
    "addr:street":"Rue Nicolai",
    "iso:country":"FR",
    "sg:address":"16 Rue Nicolai 69007 Lyon",
    "sg:classifiers":[
        {
            "category":"Health Services",
            "subcategory":"Medical Lab",
            "type":"Services"
        }
    ],
    "sg:phone":"+33 4 72 47 86 86",
    "sg:province":"Rhone-Alpes",
    "sg:tags":[
        "chemical",
        "pharmaceutical",
        "pharmacy"
    ],
    "wof:name":"Laboratoires Dolisos",
    "wof:placetype":"venue"
},
  "geometry": {"coordinates":[4.856171,45.748882],"type":"Point"}
}