{
  "type": "Feature",
  "properties": {
    "addr:full":"53, Rue Carnot, 74000 Annecy Rhone-Alpes 74000",
    "addr:housenumber":"53",
    "addr:postcode":"74000;74000",
    "addr:street":"Rue Carnot",
    "iso:country":"FR",
    "sg:address":"53, Rue Carnot, 74000 Annecy",
    "sg:orig_category":"Unclassifiable Establishments",
    "sg:phone":"+33 4 50 52 33 00",
    "sg:postcode":"74000",
    "sg:province":"Rhone-Alpes",
    "wof:name":"Caisse D'epargne Des Alpes S.a.",
    "wof:placetype":"venue"
},
  "geometry": {"coordinates":[6.124558,45.9034],"type":"Point"}
}