{
  "type": "Feature",
  "properties": {
    "addr:full":"10, Rue des Deux C\u00e8dres, 93290 Tremblay en France Ile de France",
    "addr:housenumber":"10",
    "addr:postcode":"93290",
    "addr:street":"Rue Des Deux Ce\u0300Dres",
    "iso:country":"FR",
    "sg:address":"10, Rue des Deux C\u00e8dres, 93290 Tremblay en France",
    "sg:orig_category":"Unclassifiable Establishments",
    "sg:phone":"+33 1 48 62 09 99",
    "sg:province":"Ile de France",
    "wof:name":"V.o.t. S.a. - Van Ommeren Transport",
    "wof:placetype":"venue"
},
  "geometry": {"coordinates":[2.56727,48.951214],"type":"Point"}
}