{
  "type": "Feature",
  "properties": {
    "addr:full":"B.P. 241, 29272 Brest C\u00e9dex^^2, Rue R\u00e9aumur, 29200 Brest Brest Bretagne 29200",
    "addr:housenumber":"b.p. 241",
    "addr:postcode":"29272;29200;29200",
    "addr:street":"Rue Re\u0301Aumur",
    "iso:country":"FR",
    "sg:address":"B.P. 241, 29272 Brest C\u00e9dex^^2, Rue R\u00e9aumur, 29200 Brest",
    "sg:city":"Brest",
    "sg:orig_category":"Non-Classified Establishments",
    "sg:phone":"+33 2 98 41 12 32",
    "sg:postcode":"29200",
    "sg:province":"Bretagne",
    "wof:name":"Etablissements Fran\u00e7ois Meunier S.a.s.",
    "wof:placetype":"venue"
},
  "geometry": {"coordinates":[-4.486228,48.39024],"type":"Point"}
}