{
  "type": "Feature",
  "properties": {
    "addr:full":"21, Rue de Skopje, 21000 Dijon Dijon Bourgogne 21000",
    "addr:housenumber":"21",
    "addr:postcode":"21000;21000",
    "addr:street":"Rue De Skopje",
    "iso:country":"FR",
    "sg:address":"21, Rue de Skopje, 21000 Dijon",
    "sg:city":"Dijon",
    "sg:orig_category":"Unclassifiable Establishments",
    "sg:phone":"+33 3 80 78 41 00",
    "sg:postcode":"21000",
    "sg:province":"Bourgogne",
    "wof:name":"Pomona S.a.",
    "wof:placetype":"venue"
},
  "geometry": {"coordinates":[5.061501,47.342541],"type":"Point"}
}