{
  "type": "Feature",
  "properties": {
    "iso:country":"FR",
    "sg:address":"14 Rue Colbert Jean Baptiste 14000 Caen",
    "sg:city":"Caen",
    "sg:classifiers":[
        {
            "category":"Manufacturing",
            "subcategory":"Printing",
            "type":"Manufacturing & Wholesale Goods"
        }
    ],
    "sg:phone":"+33 2 31 43 21 00",
    "sg:postcode":"14000",
    "sg:province":"Basse Normandie",
    "sg:tags":[
        "publishing"
    ],
    "wof:name":"Oberthur Card Systems Sa",
    "wof:placetype":"venue"
},
  "geometry": {"coordinates":[-0.367116,49.207172],"type":"Point"}
}