{
  "type": "Feature",
  "properties": {
    "iso:country":"FR",
    "sg:address":"Rte de Bernay",
    "sg:city":"Conches en Ouche",
    "sg:orig_category":"Unclassifiable Establishments",
    "sg:phone":"+33 2 32 30 00 88",
    "sg:postcode":"27190",
    "sg:province":"Haute Normandie",
    "wof:name":"Usmeco S.a.r.l.",
    "wof:placetype":"venue"
},
  "geometry": {"coordinates":[0.91346,48.963825],"type":"Point"}
}