{
  "type": "Feature",
  "properties": {
    "iso:country":"FR",
    "sg:address":"146 Bis Av Louis Roche 92230 Gennevilliers",
    "sg:classifiers":[
        {
            "category":"Manufacturing",
            "subcategory":"Metals",
            "type":"Manufacturing & Wholesale Goods"
        }
    ],
    "sg:phone":"+33 1 47 99 98 50",
    "sg:postcode":"92230",
    "sg:province":"Ile de France",
    "sg:tags":[
        "metallurgy",
        "steel",
        "metalworking"
    ],
    "wof:name":"Pum Paris Normandie (ppn)",
    "wof:placetype":"venue"
},
  "geometry": {"coordinates":[2.310077,48.929047],"type":"Point"}
}