{
  "type": "Feature",
  "properties": {
    "addr:full":"B.P. 40, 64800 Nay C\u00e9dex^^Rue de la Gravi\u00e8re, 64800 Baudreix Baudreix Aquitaine 64800",
    "addr:postcode":"64800;64800;64800",
    "addr:street":"B.P. 40;Gravie\u0300Re",
    "iso:country":"FR",
    "sg:address":"B.P. 40, 64800 Nay C\u00e9dex^^Rue de la Gravi\u00e8re, 64800 Baudreix",
    "sg:city":"Baudreix",
    "sg:orig_category":"Non-Classified Establishments",
    "sg:phone":"+33 5 59 61 23 32",
    "sg:postcode":"64800",
    "sg:province":"Aquitaine",
    "wof:name":"Lacrouts Fr\u00e8res S.a.s.",
    "wof:placetype":"venue"
},
  "geometry": {"coordinates":[-0.252886,43.090973],"type":"Point"}
}