{
  "type": "Feature",
  "properties": {
    "iso:country":"FR",
    "sg:address":"3, Rue de l'Alma, 35000 Rennes",
    "sg:city":"Rennes",
    "sg:orig_category":"Unclassifiable Establishments",
    "sg:phone":"+33 2 99 31 77 44",
    "sg:postcode":"35000",
    "sg:province":"Bretagne",
    "wof:name":"B.s.21",
    "wof:placetype":"venue"
},
  "geometry": {"coordinates":[-1.675457,48.099178],"type":"Point"}
}