{
  "type": "Feature",
  "properties": {
    "addr:full":"7 Rue Europe 67230 Benfeld Benfeld Alsace 67230",
    "addr:housenumber":"7",
    "addr:postcode":"67230;67230",
    "addr:street":"Rue Europe",
    "iso:country":"FR",
    "sg:address":"7 Rue Europe 67230 Benfeld",
    "sg:city":"Benfeld",
    "sg:classifiers":[
        {
            "category":"Manufacturing",
            "subcategory":"Metals",
            "type":"Manufacturing & Wholesale Goods"
        }
    ],
    "sg:phone":"+33 3 88 58 71 00",
    "sg:postcode":"67230",
    "sg:province":"Alsace",
    "sg:tags":[
        "metallurgy",
        "metalworking",
        "processing"
    ],
    "wof:name":"Secome Sa",
    "wof:placetype":"venue"
},
  "geometry": {"coordinates":[7.59555,48.377342],"type":"Point"}
}