{
  "type": "Feature",
  "properties": {
    "iso:country":"FR",
    "sg:address":"La Croix Noury Z A 41100 Villiers Sur Loir",
    "sg:city":"Lisle",
    "sg:classifiers":[
        {
            "category":"Manufacturing",
            "subcategory":"Metals",
            "type":"Manufacturing & Wholesale Goods"
        }
    ],
    "sg:phone":"+33 2 54 80 21 35",
    "sg:postcode":"41100",
    "sg:province":"Centre",
    "sg:tags":[
        "-",
        "machine",
        "equipment",
        "engineering",
        "machinery",
        "mechanical"
    ],
    "wof:name":"Etablissements Guerineau Louis",
    "wof:placetype":"venue"
},
  "geometry": {"coordinates":[0.999022,47.801105],"type":"Point"}
}