{
  "type": "Feature",
  "properties": {
    "addr:full":"Lieu Dit La Saulniere 85280 La Ferriere Pays de Loire 85280",
    "addr:postcode":"85280;85280",
    "addr:street":"Lieu Dit La Saulniere;Ferriere",
    "iso:country":"FR",
    "sg:address":"Lieu Dit La Saulniere 85280 La Ferriere",
    "sg:classifiers":[
        {
            "category":"Home & Garden",
            "subcategory":"Furniture",
            "type":"Retail Goods"
        }
    ],
    "sg:phone":"+33 2 51 98 41 54",
    "sg:postcode":"85280",
    "sg:province":"Pays de Loire",
    "sg:tags":[
        "household",
        "wood"
    ],
    "wof:name":"Chaillou Hermouet Ebenistes Createurs",
    "wof:placetype":"venue"
},
  "geometry": {"coordinates":[-1.314795,46.712093],"type":"Point"}
}