{
  "type": "Feature",
  "properties": {
    "addr:full":"7, Rue Bachaumont, 75002 Paris Ile de France",
    "addr:housenumber":"7",
    "addr:postcode":"75002",
    "addr:street":"Rue Bachaumont",
    "iso:country":"FR",
    "sg:address":"7, Rue Bachaumont, 75002 Paris",
    "sg:orig_category":"Non-Classified Establishments",
    "sg:phone":"+33 1 42 21 13 68",
    "sg:province":"Ile de France",
    "wof:name":"S.e.b.h. S.a.s.",
    "wof:placetype":"venue"
},
  "geometry": {"coordinates":[2.346186,48.865837],"type":"Point"}
}