{
  "type": "Feature",
  "properties": {
    "iso:country":"FR",
    "sg:address":"6 Rue Troyon 92310 S\u00e8vres",
    "sg:classifiers":[
        {
            "category":"Banks & Credit Unions",
            "subcategory":"Financial Services",
            "type":"Services"
        }
    ],
    "sg:phone":"+33 1 46 23 65 00",
    "sg:postcode":"92310",
    "sg:province":"Ile de France",
    "sg:tags":[
        "banking",
        "insurance",
        "institution",
        "finance"
    ],
    "wof:name":"Alcan Packaging France Sa",
    "wof:placetype":"venue"
},
  "geometry": {"coordinates":[2.22672,48.826141],"type":"Point"}
}