{
  "type": "Feature",
  "properties": {
    "addr:full":"B\u00e2t Alexandre 92230 Gennevilliers Ile de France 92230",
    "addr:housenumber":"ba\u0302t",
    "addr:postcode":"92230;ile;92230",
    "addr:street":"France",
    "iso:country":"FR",
    "sg:address":"B\u00e2t",
    "sg:city":"Alexandre 92230 Gennevilliers",
    "sg:classifiers":[
        {
            "category":"Wholesale",
            "subcategory":"Machinery & Supplies",
            "type":"Manufacturing & Wholesale Goods"
        }
    ],
    "sg:phone":"+33 1 46 88 96 16",
    "sg:postcode":"92230",
    "sg:province":"Ile de France",
    "sg:tags":[
        "handling",
        "material",
        "-",
        "machine",
        "equipment",
        "engineering",
        "mechanical"
    ],
    "wof:name":"Sodica",
    "wof:placetype":"venue"
},
  "geometry": {"coordinates":[2.32228,48.921619],"type":"Point"}
}