{
  "type": "Feature",
  "properties": {
    "addr:full":"S/C Beaudu 16480 Oriolles Poitou-Charentes 16480",
    "addr:postcode":"16480;16480",
    "addr:street":"Oriolles",
    "iso:country":"FR",
    "sg:address":"S/C Beaudu 16480 Oriolles",
    "sg:classifiers":[
        {
            "category":"Wholesale",
            "subcategory":"Farm Supplies",
            "type":"Manufacturing & Wholesale Goods"
        }
    ],
    "sg:phone":"+33 5 45 98 74 33",
    "sg:postcode":"16480",
    "sg:province":"Poitou-Charentes",
    "sg:tags":[
        "-",
        "machine",
        "equipment",
        "engineering",
        "machinery",
        "mechanical",
        "agriculture"
    ],
    "wof:name":"Guenon Et Fils Sa",
    "wof:placetype":"venue"
},
  "geometry": {"coordinates":[-0.121064,45.347427],"type":"Point"}
}