{
  "type": "Feature",
  "properties": {
    "addr:full":"35ter Avenue Andr\u00e9 Morizet Boulogne 92100",
    "addr:housenumber":"35ter",
    "addr:postcode":"92100",
    "addr:street":"Avenue Andre\u0301 Morizet",
    "iso:country":"FR",
    "sg:address":"35ter Avenue Andr\u00e9 Morizet",
    "sg:city":"Boulogne",
    "sg:classifiers":[
        {
            "category":"Professional",
            "subcategory":"Computer Services",
            "type":"Services"
        }
    ],
    "sg:postcode":"92100",
    "sg:website":"http://www.talent-soft.com",
    "wof:name":"TalentSoft",
    "wof:placetype":"venue"
},
  "geometry": {"coordinates":[2.237852,48.836357],"type":"Point"}
}