{
  "type": "Feature",
  "properties": {
    "addr:full":"18 Avenue De La Gare 21400 Chatillon Sur Seine Aisey-sur-Seine Bourgogne 21400",
    "addr:housenumber":"18",
    "addr:postcode":"21400;21400",
    "addr:street":"Avenue De La Gare;Seine;Bourgogne",
    "iso:country":"FR",
    "sg:address":"18 Avenue De La Gare 21400 Chatillon Sur Seine",
    "sg:city":"Aisey-sur-Seine",
    "sg:classifiers":[
        {
            "category":"Shopping",
            "type":"Retail Goods"
        }
    ],
    "sg:phone":"+33 3 80 91 08 16",
    "sg:postcode":"21400",
    "sg:province":"Bourgogne",
    "sg:tags":[
        "metallurgy",
        "finished",
        "-",
        "metalworking",
        "metallic"
    ],
    "wof:name":"Arthur Dandelot",
    "wof:placetype":"venue"
},
  "geometry": {"coordinates":[4.572465,47.869335],"type":"Point"}
}