{
  "type": "Feature",
  "properties": {
    "addr:full":"B.P. 10, 77100 Meaux^^12, Rue Louis Courrier, 77100 Meaux Ile de France",
    "addr:postcode":"77100;77100;ile",
    "addr:street":"B.P. 10;Rue Louis Courrier",
    "iso:country":"FR",
    "sg:address":"B.P. 10, 77100 Meaux^^12, Rue Louis Courrier, 77100 Meaux",
    "sg:orig_category":"Non-Classified Establishments",
    "sg:phone":"+33 1 60 38 10 70",
    "sg:province":"Ile de France",
    "wof:name":"Henri Bieth Et Humber Industrie S.a.",
    "wof:placetype":"venue"
},
  "geometry": {"coordinates":[2.883054,48.959351],"type":"Point"}
}