{
  "type": "Feature",
  "properties": {
    "addr:full":"ZA les Deux Vall\u00e9es Vaugneray Rhone-Alpes 69670",
    "addr:postcode":"69670",
    "addr:street":"Za Les",
    "iso:country":"FR",
    "sg:address":"ZA les Deux Vall\u00e9es",
    "sg:city":"Vaugneray",
    "sg:orig_category":"Unclassifiable Establishments",
    "sg:phone":"+33 4 78 45 81 14",
    "sg:postcode":"69670",
    "sg:province":"Rhone-Alpes",
    "wof:name":"Diafoc S.a.",
    "wof:placetype":"venue"
},
  "geometry": {"coordinates":[4.65725,45.737991],"type":"Point"}
}