{
  "type": "Feature",
  "properties": {
    "addr:full":"Galerie Surcouf 93600 Aulnay Sous Bois Ile de France 93600",
    "addr:postcode":"93600;93600",
    "iso:country":"FR",
    "sg:address":"Galerie Surcouf 93600 Aulnay Sous Bois",
    "sg:classifiers":[
        {
            "category":"Bakery",
            "type":"Food & Drink"
        }
    ],
    "sg:phone":"+33 1 48 66 22 75",
    "sg:postcode":"93600",
    "sg:province":"Ile de France",
    "sg:tags":[
        "cake",
        "product",
        "related",
        "bread"
    ],
    "wof:name":"Boulangerie Aulnay 3ooo Sa",
    "wof:placetype":"venue"
},
  "geometry": {"coordinates":[2.50093,48.955711],"type":"Point"}
}