{
  "type": "Feature",
  "properties": {
    "iso:country":"FR",
    "sg:address":"859, Rte d'Aix les Bains, 73420 Viviers du Lac",
    "sg:orig_category":"Non-Classified Establishments",
    "sg:phone":"+33 4 79 88 87 76",
    "sg:postcode":"73420",
    "sg:province":"Rhone-Alpes",
    "wof:name":"Chaudronnerie Du Viviers S.a.r.l.",
    "wof:placetype":"venue"
},
  "geometry": {"coordinates":[5.91476,45.68808],"type":"Point"}
}