{
  "type": "Feature",
  "properties": {
    "addr:full":"19 Mar\u00e9chal Leclerc 60510 Therdonne Picardie 60510",
    "addr:housenumber":"19",
    "addr:postcode":"60510;60510",
    "addr:street":"Mare\u0301Chal Leclerc",
    "iso:country":"FR",
    "sg:address":"19",
    "sg:city":"Mar\u00e9chal Leclerc 60510 Therdonne",
    "sg:classifiers":[
        {
            "category":"Shopping",
            "type":"Retail Goods"
        }
    ],
    "sg:phone":"+33 3 44 07 34 34",
    "sg:postcode":"60510",
    "sg:province":"Picardie",
    "sg:tags":[
        "metallurgy",
        "finished",
        "-",
        "metalworking",
        "metallic"
    ],
    "wof:name":"Ressorts De L'oise",
    "wof:placetype":"venue"
},
  "geometry": {"coordinates":[2.158689,49.418468],"type":"Point"}
}