{
  "type": "Feature",
  "properties": {
    "addr:full":"4, Rue Jean Elys\u00e9e Dupuy - ZI du Tronchon, 69410 Champagne au Mont d'Or Rhone-Alpes 69410",
    "addr:housenumber":"4",
    "addr:postcode":"69410;69410",
    "addr:street":"Rue Jean Elyse\u0301E Dupuy Zi Du Tronchon;D'Or Rhone-Alpes",
    "iso:country":"FR",
    "sg:address":"4, Rue Jean Elys\u00e9e Dupuy - ZI du Tronchon, 69410 Champagne au Mont d'Or",
    "sg:orig_category":"Unclassifiable Establishments",
    "sg:phone":"+33 4 78 64 55 29",
    "sg:postcode":"69410",
    "sg:province":"Rhone-Alpes",
    "wof:name":"Relitech S.a.r.l.",
    "wof:placetype":"venue"
},
  "geometry": {"coordinates":[5.717823,47.020477],"type":"Point"}
}