{
  "type": "Feature",
  "properties": {
    "addr:full":"Zi Tulle Est Les Chabannes 19000 Tulle Limousin 19000",
    "addr:postcode":"19000;19000",
    "addr:street":"Tulle Est;Chabannes",
    "iso:country":"FR",
    "sg:address":"Zi Tulle Est Les Chabannes 19000 Tulle",
    "sg:classifiers":[
        {
            "category":"Building & Trades",
            "subcategory":"Construction",
            "type":"Services"
        }
    ],
    "sg:phone":"+33 5 55 26 98 98",
    "sg:postcode":"19000",
    "sg:province":"Limousin",
    "sg:tags":[
        "work",
        "public"
    ],
    "wof:name":"Eurovia Poitou Charentes Limousin",
    "wof:placetype":"venue"
},
  "geometry": {"coordinates":[1.756695,45.259048],"type":"Point"}
}