{
  "type": "Feature",
  "properties": {
    "addr:full":"106, Rte de Paris, 03000 Moulins Moulins Auvergne 03000",
    "addr:housenumber":"106",
    "addr:postcode":"03000;03000",
    "addr:street":"Rte De Paris",
    "iso:country":"FR",
    "sg:address":"106, Rte de Paris, 03000 Moulins",
    "sg:city":"Moulins",
    "sg:orig_category":"Unclassifiable Establishments",
    "sg:phone":"+33 4 70 48 17 02",
    "sg:postcode":"03000",
    "sg:province":"Auvergne",
    "wof:name":"Spic Armartures S.a.r.l.",
    "wof:placetype":"venue"
},
  "geometry": {"coordinates":[3.325611,46.57476],"type":"Point"}
}