{
  "type": "Feature",
  "properties": {
    "addr:full":"Av de l'Europe - Cit de Roncq Roncq Nord Pas-de-Calais 59960",
    "addr:postcode":"59960",
    "addr:street":"Av De L'Europe;Pas-De-Calais",
    "iso:country":"FR",
    "sg:address":"Av de l'Europe - Cit de Roncq",
    "sg:city":"Roncq",
    "sg:orig_category":"Unclassifiable Establishments",
    "sg:phone":"+33 3 20 11 51 80",
    "sg:postcode":"59960",
    "sg:province":"Nord Pas-de-Calais",
    "wof:name":"Schenker S.a.",
    "wof:placetype":"venue"
},
  "geometry": {"coordinates":[3.139279,50.740513],"type":"Point"}
}