{
  "type": "Feature",
  "properties": {
    "addr:full":"6, Rue de Dingolfing, 67170 Brumath Brumath Alsace 67170",
    "addr:housenumber":"6",
    "addr:postcode":"67170;67170",
    "addr:street":"Rue De Dingolfing",
    "iso:country":"FR",
    "sg:address":"6, Rue de Dingolfing, 67170 Brumath",
    "sg:city":"Brumath",
    "sg:orig_category":"Non-Classified Establishments",
    "sg:phone":"+33 3 88 14 47 55",
    "sg:postcode":"67170",
    "sg:province":"Alsace",
    "wof:name":"Fortex S.a.r.l.",
    "wof:placetype":"venue"
},
  "geometry": {"coordinates":[7.717022,48.734184],"type":"Point"}
}