{
  "type": "Feature",
  "properties": {
    "iso:country":"FR",
    "sg:address":"ZA les Arnajons",
    "sg:city":"Le Puy Sainte R\u00e9parade",
    "sg:orig_category":"Unclassifiable Establishments",
    "sg:phone":"+33 4 42 61 83 83",
    "sg:postcode":"13610",
    "sg:province":"Midi Pyr\u00e9n\u00e9es",
    "wof:name":"S.p.g.p. S.a.r.l.",
    "wof:placetype":"venue"
},
  "geometry": {"coordinates":[5.434375,43.662586],"type":"Point"}
}