{
  "type": "Feature",
  "properties": {
    "iso:country":"FR",
    "sg:address":"79270 Le Vanneau",
    "sg:orig_category":"Non-Classified Establishments",
    "sg:phone":"+33 5 49 35 00 03",
    "sg:postcode":"79270",
    "sg:province":"Poitou-Charentes",
    "wof:name":"Etablissements Allin S.a.",
    "wof:placetype":"venue"
},
  "geometry": {"coordinates":[-0.6368,46.295292],"type":"Point"}
}