{
  "type": "Feature",
  "properties": {
    "addr:full":"4, Rue du Four \u00e0 Chaux, 69009 Lyon Rhone-Alpes 69009",
    "addr:housenumber":"4",
    "addr:postcode":"69009;69009",
    "addr:street":"Rue Du Four A\u0300 Chaux",
    "iso:country":"FR",
    "sg:address":"4, Rue du Four \u00e0 Chaux, 69009 Lyon",
    "sg:orig_category":"Unclassifiable Establishments",
    "sg:phone":"+33 4 72 53 78 88",
    "sg:postcode":"69009",
    "sg:province":"Rhone-Alpes",
    "wof:name":"Varcity S.a.r.l.",
    "wof:placetype":"venue"
},
  "geometry": {"coordinates":[4.812367,45.785122],"type":"Point"}
}