{
  "type": "Feature",
  "properties": {
    "addr:full":"Rte de Villers la Faye Comblanchien Bourgogne 21700",
    "addr:postcode":"21700",
    "addr:street":"Rte De Villers La;Bourgogne",
    "iso:country":"FR",
    "sg:address":"Rte de Villers la Faye",
    "sg:city":"Comblanchien",
    "sg:orig_category":"Non-Classified Establishments",
    "sg:phone":"+33 3 80 62 94 25",
    "sg:postcode":"21700",
    "sg:province":"Bourgogne",
    "wof:name":"Les Pierres Bourguignonnes S.a.r.l.",
    "wof:placetype":"venue"
},
  "geometry": {"coordinates":[4.950248,47.137695],"type":"Point"}
}