{
  "type": "Feature",
  "properties": {
    "iso:country":"FR",
    "sg:address":"1 Za Migelane 33650 Saucats",
    "sg:city":"Saucats",
    "sg:classifiers":[
        {
            "category":"Manufacturing",
            "subcategory":"Tools & Machinery",
            "type":"Manufacturing & Wholesale Goods"
        }
    ],
    "sg:phone":"+33 5 57 97 17 97",
    "sg:postcode":"33650",
    "sg:province":"Aquitaine",
    "sg:tags":[
        "equipment",
        "measurement",
        "-",
        "precision",
        "instrument"
    ],
    "wof:name":"A Puissance 3 Sarl",
    "wof:placetype":"venue"
},
  "geometry": {"coordinates":[-0.594689,44.569355],"type":"Point"}
}