{
  "type": "Feature",
  "properties": {
    "iso:country":"FR",
    "sg:address":"Pa De La Vall\u00e9e De L'Escaut 59264 Onnaing",
    "sg:classifiers":[
        {
            "category":"Autos & Motor Vehicles",
            "subcategory":"Automobile Sales",
            "type":"Retail Goods"
        }
    ],
    "sg:phone":"+33 3 27 28 56 00",
    "sg:postcode":"59264",
    "sg:province":"Nord Pas-de-Calais",
    "sg:tags":[
        "equipment",
        "motor-cars",
        "transport"
    ],
    "wof:name":"Ogura",
    "wof:placetype":"venue"
},
  "geometry": {"coordinates":[3.59713,50.385681],"type":"Point"}
}