{
  "type": "Feature",
  "properties": {
    "addr:full":"28 Rue De La Redoute BP 86 92263 Fontenay Aux Roses Cedex Champagne",
    "addr:housenumber":"28;86",
    "addr:postcode":"92263;roses cedex",
    "addr:street":"Rue De La Redoute Bp",
    "iso:country":"FR",
    "sg:address":"28 Rue De La Redoute BP 86 92263 Fontenay Aux Roses Cedex",
    "sg:classifiers":[
        {
            "category":"Building & Trades",
            "subcategory":"Construction",
            "type":"Services"
        }
    ],
    "sg:phone":"+33 1 46 60 85 65",
    "sg:province":"Champagne",
    "sg:tags":[
        "work",
        "public"
    ],
    "wof:name":"Sechaud Et Metz Sa",
    "wof:placetype":"venue"
},
  "geometry": {"coordinates":[2.275423,48.794506],"type":"Point"}
}