{
  "type": "Feature",
  "properties": {
    "iso:country":"FR",
    "sg:address":"38, Rte Saint Omer, 59470 Zegerscappel",
    "sg:orig_category":"Non-Classified Establishments",
    "sg:phone":"+33 3 28 68 90 60",
    "sg:province":"Nord Pas-de-Calais",
    "wof:name":"Timmerman Maxime Et Compagnie S.a.",
    "wof:placetype":"venue"
},
  "geometry": {"coordinates":[2.375504,50.886066],"type":"Point"}
}