{
  "type": "Feature",
  "properties": {
    "addr:full":"Chemin des Croix Le Quesnoy Nord Pas-de-Calais 59530",
    "addr:postcode":"59530",
    "addr:street":"Chemin Des Croix Le;Nord",
    "iso:country":"FR",
    "sg:address":"Chemin des Croix",
    "sg:city":"Le Quesnoy",
    "sg:orig_category":"Unclassifiable Establishments",
    "sg:phone":"+33 3 27 20 54 54",
    "sg:postcode":"59530",
    "sg:province":"Nord Pas-de-Calais",
    "wof:name":"Cofradec S.a.",
    "wof:placetype":"venue"
},
  "geometry": {"coordinates":[3.64982,50.247562],"type":"Point"}
}