{
  "type": "Feature",
  "properties": {
    "addr:full":"B.P. 37, 60870 Villers Saint Paul^^Rue Albert Thomas - Z.A., 60870 Villers Saint Paul Picardie",
    "addr:postcode":"60870;60870",
    "addr:street":"B.P. 37;Z.A.",
    "iso:country":"FR",
    "sg:address":"B.P. 37, 60870 Villers Saint Paul^^Rue Albert Thomas - Z.A., 60870 Villers Saint Paul",
    "sg:orig_category":"Non-Classified Establishments",
    "sg:phone":"+33 3 44 66 33 91",
    "sg:province":"Picardie",
    "wof:name":"L.n.f. S.a.",
    "wof:placetype":"venue"
},
  "geometry": {"coordinates":[2.49983,49.291355],"type":"Point"}
}