{
  "type": "Feature",
  "properties": {
    "iso:country":"FR",
    "sg:address":"lieu dit le Vorgan 74150 VALLIERES",
    "sg:classifiers":[
        {
            "category":"Manufacturing",
            "subcategory":"Metals",
            "type":"Manufacturing & Wholesale Goods"
        }
    ],
    "sg:phone":"+33 4 50 62 12 84",
    "sg:province":"Rhone-Alpes",
    "sg:tags":[
        "blanking",
        "dy"
    ],
    "wof:name":"Ste Nouvelle Samag Sa",
    "wof:placetype":"venue"
},
  "geometry": {"coordinates":[5.943953,45.822372],"type":"Point"}
}