{
  "type": "Feature",
  "properties": {
    "iso:country":"FR",
    "sg:address":"12 Avenue Sommer 92160 Antony",
    "sg:classifiers":[
        {
            "category":"Shopping",
            "type":"Retail Goods"
        }
    ],
    "sg:phone":"+33 1 46 66 33 11",
    "sg:postcode":"92160",
    "sg:province":"Ile de France",
    "sg:tags":[
        "metallurgy",
        "finished",
        "-",
        "metalworking",
        "metallic"
    ],
    "wof:name":"Tardy Rollet Sa",
    "wof:placetype":"venue"
},
  "geometry": {"coordinates":[2.306623,48.73262],"type":"Point"}
}