{
  "type": "Feature",
  "properties": {
    "addr:full":"460, Rue de la Leysse, 73000 Chamb\u00e9ry Rhone-Alpes",
    "addr:housenumber":"460",
    "addr:postcode":"73000",
    "addr:street":"Rue De La Leysse",
    "iso:country":"FR",
    "sg:address":"460, Rue de la Leysse, 73000 Chamb\u00e9ry",
    "sg:orig_category":"Unclassifiable Establishments",
    "sg:phone":"+33 4 79 26 06 18",
    "sg:province":"Rhone-Alpes",
    "wof:name":"Jertex S.a.r.l.",
    "wof:placetype":"venue"
},
  "geometry": {"coordinates":[5.891591,45.596989],"type":"Point"}
}