{
  "type": "Feature",
  "properties": {
    "iso:country":"FR",
    "sg:address":"7 B, rte du P\u00e9age, 38370 Saint Clair du Rh\u00f4ne",
    "sg:orig_category":"Non-Classified Establishments",
    "sg:phone":"+33 4 74 56 56 30",
    "sg:province":"Rhone-Alpes",
    "wof:name":"Soci\u00e9t\u00e9 Nouvelle Charpente Saint Clair S.a.",
    "wof:placetype":"venue"
},
  "geometry": {"coordinates":[4.770464,45.435661],"type":"Point"}
}