{
  "type": "Feature",
  "properties": {
    "addr:full":"8, Rue de la Gare, 29340 Riec sur Belon Riec-sur-Belon Bretagne 29340",
    "addr:housenumber":"8",
    "addr:postcode":"29340;29340",
    "addr:street":"Rue De La Gare;Riec-Sur-Belon",
    "iso:country":"FR",
    "sg:address":"8, Rue de la Gare, 29340 Riec sur Belon",
    "sg:city":"Riec-sur-Belon",
    "sg:orig_category":"Unclassifiable Establishments",
    "sg:phone":"+33 2 98 06 90 67",
    "sg:postcode":"29340",
    "sg:province":"Bretagne",
    "wof:name":"A.c.m.g. Goalabr\u00e9 E.u.r.l.",
    "wof:placetype":"venue"
},
  "geometry": {"coordinates":[-3.689357,47.844891],"type":"Point"}
}