{
  "type": "Feature",
  "properties": {
    "addr:full":"8 Rue Jean Rostand 78194 Trappes Cedex \u00cele-de-France",
    "addr:housenumber":"8",
    "addr:postcode":"78194;cedex",
    "addr:street":"Rue Jean Rostand",
    "iso:country":"FR",
    "sg:address":"8 Rue Jean Rostand 78194 Trappes Cedex",
    "sg:classifiers":[
        {
            "category":"Manufacturing",
            "subcategory":"Rubber & Plastics",
            "type":"Manufacturing & Wholesale Goods"
        }
    ],
    "sg:phone":"+33 1 30 13 99 13",
    "sg:province":"\u00cele-de-France",
    "wof:name":"Rema Tip Top France Eurl",
    "wof:placetype":"venue"
},
  "geometry": {"coordinates":[1.999285,48.774651],"type":"Point"}
}