{
  "type": "Feature",
  "properties": {
    "addr:full":"54 Rue De Turbigo 75003 Paris Ile de France 75003",
    "addr:housenumber":"54",
    "addr:postcode":"75003;75003",
    "addr:street":"Rue De Turbigo",
    "iso:country":"FR",
    "sg:address":"54 Rue De Turbigo 75003 Paris",
    "sg:classifiers":[
        {
            "category":"Manufacturing",
            "subcategory":"Jewelry",
            "type":"Manufacturing & Wholesale Goods"
        }
    ],
    "sg:phone":"+33 1 42 78 09 22",
    "sg:postcode":"75003",
    "sg:province":"Ile de France",
    "sg:tags":[
        "product",
        "miscellaneous",
        "jewellery"
    ],
    "wof:name":"Vogler Sa",
    "wof:placetype":"venue"
},
  "geometry": {"coordinates":[2.357337,48.865601],"type":"Point"}
}