{
  "type": "Feature",
  "properties": {
    "addr:full":"1 Rue La Victoire De La Marne 34000 Montpellier Languedoc-Roussillon 34000",
    "addr:housenumber":"1",
    "addr:postcode":"34000;34000",
    "addr:street":"Rue La Victoire De La Marne",
    "iso:country":"FR",
    "sg:address":"1 Rue La Victoire De La Marne 34000 Montpellier",
    "sg:classifiers":[
        {
            "category":"Communications",
            "type":"Services"
        }
    ],
    "sg:phone":"+33 4 67 92 66 58",
    "sg:postcode":"34000",
    "sg:province":"Languedoc-Roussillon",
    "sg:tags":[
        "translation",
        "training",
        "interpretation",
        "advice",
        "business"
    ],
    "wof:name":"Ecole Klesse",
    "wof:placetype":"venue"
},
  "geometry": {"coordinates":[3.879423,43.606766],"type":"Point"}
}