{
  "type": "Feature",
  "properties": {
    "addr:full":"ZA les Vignes La Guierche Pays de Loire 72380",
    "addr:postcode":"72380",
    "addr:street":"Za Les Vignes La Guierche",
    "iso:country":"FR",
    "sg:address":"ZA les Vignes",
    "sg:city":"La Guierche",
    "sg:orig_category":"Non-Classified Establishments",
    "sg:phone":"+33 2 43 25 96 19",
    "sg:postcode":"72380",
    "sg:province":"Pays de Loire",
    "wof:name":"Vercor S.a.",
    "wof:placetype":"venue"
},
  "geometry": {"coordinates":[0.19414,48.11367],"type":"Point"}
}