{
  "type": "Feature",
  "properties": {
    "addr:full":"11/15, Rue Saint Andr\u00e9 - ZI des Vignes, 93000 Bobigny Ile de France",
    "addr:housenumber":"11 / 15",
    "addr:postcode":"93000;ile",
    "addr:street":"Rue Saint Andre\u0301 Zi Des Vignes",
    "iso:country":"FR",
    "sg:address":"11/15, Rue Saint Andr\u00e9 - ZI des Vignes, 93000 Bobigny",
    "sg:orig_category":"Non-Classified Establishments",
    "sg:phone":"+33 1 48 44 78 40",
    "sg:province":"Ile de France",
    "wof:name":"Vanherck S.a.",
    "wof:placetype":"venue"
},
  "geometry": {"coordinates":[2.445785,48.90477],"type":"Point"}
}