{
  "type": "Feature",
  "properties": {
    "addr:full":"33 Rue De La Petite Meilleraie Zac De La Foret 44840 Les Sorinieres Pays de Loire",
    "addr:housenumber":"33",
    "addr:postcode":"44840",
    "addr:street":"Rue De La Petite Meilleraie Zac De La Foret;Sorinieres",
    "iso:country":"FR",
    "sg:address":"33 Rue De La Petite Meilleraie Zac De La Foret 44840 Les Sorinieres",
    "sg:classifiers":[
        {
            "category":"Manufacturing",
            "subcategory":"Wood Products",
            "type":"Manufacturing & Wholesale Goods"
        }
    ],
    "sg:phone":"+33 2 40 05 71 71",
    "sg:province":"Pays de Loire",
    "sg:tags":[
        "professional",
        "furniture"
    ],
    "wof:name":"Societe Industrielle D'electricite De Loire (siela)",
    "wof:placetype":"venue"
},
  "geometry": {"coordinates":[-1.531499,47.148575],"type":"Point"}
}