{
  "type": "Feature",
  "properties": {
    "addr:full":"14c R Pierre De Couberten BP 27823 Parc De Merande 21078 Dijon Cedex Haute Normandie",
    "addr:housenumber":"14c",
    "addr:postcode":"27823;21078",
    "addr:street":"R Pierre De Couberten Bp",
    "iso:country":"FR",
    "sg:address":"14c R Pierre De Couberten BP 27823 Parc De Merande 21078 Dijon Cedex",
    "sg:classifiers":[
        {
            "category":"Social Services",
            "subcategory":"Job Training",
            "type":"Services"
        }
    ],
    "sg:phone":"+33 3 80 69 24 00",
    "sg:province":"Haute Normandie",
    "sg:tags":[
        "information",
        "peripheral",
        "-",
        "technology",
        "software"
    ],
    "wof:name":"Mediatec",
    "wof:placetype":"venue"
},
  "geometry": {"coordinates":[5.04399,47.327209],"type":"Point"}
}