{
  "type": "Feature",
  "properties": {
    "iso:country":"FR",
    "sg:address":"22 Rue Chauffour 10700 Torcy Le Grand",
    "sg:classifiers":[
        {
            "category":"Manufacturing",
            "subcategory":"Tools & Machinery",
            "type":"Manufacturing & Wholesale Goods"
        }
    ],
    "sg:phone":"+33 3 25 37 86 88",
    "sg:postcode":"10700",
    "sg:province":"Champagne",
    "sg:tags":[
        "metallurgy",
        "metalworking"
    ],
    "wof:name":"Ser-appro",
    "wof:placetype":"venue"
},
  "geometry": {"coordinates":[4.17431,48.533501],"type":"Point"}
}