{
  "type": "Feature",
  "properties": {
    "addr:full":"B.P. 13, 40350 Pouillon^^Rte de Dax, 40350 Pouillon Pouillon Aquitaine 40350",
    "addr:postcode":"40350;40350;40350",
    "addr:street":"B.P. 13",
    "iso:country":"FR",
    "sg:address":"B.P. 13, 40350 Pouillon^^Rte de Dax, 40350 Pouillon",
    "sg:city":"Pouillon",
    "sg:orig_category":"Non-Classified Establishments",
    "sg:phone":"+33 5 58 98 20 61",
    "sg:postcode":"40350",
    "sg:province":"Aquitaine",
    "wof:name":"S.e.f.t.i. S.a. - Soci\u00e9t\u00e9 Electrique Frigorifique Thermique Industrielle",
    "wof:placetype":"venue"
},
  "geometry": {"coordinates":[-0.99246,43.605968],"type":"Point"}
}