{
  "type": "Feature",
  "properties": {
    "iso:country":"FR",
    "sg:address":"6 Rue Du Clos Vert Zi Sud 35400 St Malo",
    "sg:city":"Saint-Malo",
    "sg:classifiers":[
        {
            "category":"Professional",
            "type":"Services"
        }
    ],
    "sg:phone":"+33 2 99 21 04 04",
    "sg:postcode":"35400",
    "sg:province":"Bretagne",
    "sg:tags":[
        "transport",
        "road"
    ],
    "wof:name":"Transports Leroux Sa",
    "wof:placetype":"venue"
},
  "geometry": {"coordinates":[-2.003669,48.604897],"type":"Point"}
}