{
  "type": "Feature",
  "properties": {
    "addr:full":"6, Impasse Edmond Audran - ZAC de la Glaci\u00e8re, 31200 Toulouse Midi Pyr\u00e9n\u00e9es",
    "addr:housenumber":"6",
    "addr:postcode":"31200",
    "addr:street":"Impasse Edmond Audran Zac De La Glacie\u0300Re",
    "iso:country":"FR",
    "sg:address":"6, Impasse Edmond Audran - ZAC de la Glaci\u00e8re, 31200 Toulouse",
    "sg:orig_category":"Unclassifiable Establishments",
    "sg:phone":"+33 5 34 40 77 40",
    "sg:province":"Midi Pyr\u00e9n\u00e9es",
    "wof:name":"Conservor S.a.",
    "wof:placetype":"venue"
},
  "geometry": {"coordinates":[1.44954,43.639011],"type":"Point"}
}