{
  "type": "Feature",
  "properties": {
    "iso:country":"FR",
    "sg:address":"1, Rue de la Terre Neuve, 91940 Les Ulis",
    "sg:orig_category":"Unclassifiable Establishments",
    "sg:phone":"+33 1 64 46 12 05",
    "sg:province":"Ile de France",
    "wof:name":"Arse S.a.r.l. - Assistance R\u00e9alisation Service Electronique",
    "wof:placetype":"venue"
},
  "geometry": {"coordinates":[2.204476,48.688854],"type":"Point"}
}