{
  "type": "Feature",
  "properties": {
    "addr:full":"32, Av. Mar\u00e9chal Delattre de Tassigny, 50100 Cherbourg Cherbourg-Octeville Basse Normandie 50100",
    "addr:postcode":"50100;50100",
    "addr:street":"32 Av. Mare\u0301Chal Delattre De Tassigny",
    "iso:country":"FR",
    "sg:address":"32, Av. Mar\u00e9chal Delattre de Tassigny, 50100 Cherbourg",
    "sg:city":"Cherbourg-Octeville",
    "sg:orig_category":"Unclassifiable Establishments",
    "sg:phone":"+33 2 33 20 04 26",
    "sg:postcode":"50100",
    "sg:province":"Basse Normandie",
    "wof:name":"Plvs E.u.r.l.",
    "wof:placetype":"venue"
},
  "geometry": {"coordinates":[-1.603833,49.635239],"type":"Point"}
}