{
  "type": "Feature",
  "properties": {
    "iso:country":"FR",
    "sg:address":"11, Rue de l'Egalerie, 42100 Saint Etienne",
    "sg:orig_category":"Unclassifiable Establishments",
    "sg:phone":"+33 4 77 80 10 37",
    "sg:postcode":"42100",
    "sg:province":"Rhone-Alpes",
    "wof:name":"Le Plissage Fran\u00e7ais S.a.",
    "wof:placetype":"venue"
},
  "geometry": {"coordinates":[4.391504,45.417648],"type":"Point"}
}