{
  "type": "Feature",
  "properties": {
    "iso:country":"FR",
    "sg:address":"7 Rue De Bretagne Erdre Active Ii Malabry 44240 La Chapelle Sur Erdre",
    "sg:orig_category":"Miscellaneous Products",
    "sg:phone":"+33 2 40 29 85 99",
    "sg:postcode":"44240",
    "sg:province":"Pays de Loire",
    "wof:name":"Etablissements Julio Fils",
    "wof:placetype":"venue"
},
  "geometry": {"coordinates":[-1.536342,47.28133],"type":"Point"}
}