{
  "type": "Feature",
  "properties": {
    "iso:country":"FR",
    "sg:address":"Parc La Breche Aux Loups 27340 Criquebeuf Sur Seine",
    "sg:classifiers":[
        {
            "category":"Shopping",
            "type":"Retail Goods"
        }
    ],
    "sg:phone":"+33 2 35 77 77 99",
    "sg:postcode":"27340",
    "sg:province":"Haute Normandie",
    "sg:tags":[
        "metallurgy",
        "finished",
        "-",
        "metalworking",
        "metallic"
    ],
    "wof:name":"Cia Pose",
    "wof:placetype":"venue"
},
  "geometry": {"coordinates":[1.110239,49.301323],"type":"Point"}
}