{
  "type": "Feature",
  "properties": {
    "addr:full":"Rte de Mussey - ZA Devarney Bar le Duc Lorraine 55000",
    "addr:postcode":"55000",
    "addr:street":"Rte De Mussey Za Devarney;Lorraine",
    "iso:country":"FR",
    "sg:address":"Rte de Mussey - ZA Devarney",
    "sg:city":"Bar le Duc",
    "sg:orig_category":"Non-Classified Establishments",
    "sg:phone":"+33 3 29 45 22 51",
    "sg:postcode":"55000",
    "sg:province":"Lorraine",
    "wof:name":"S.e.e.t.p. Robinet S.a.",
    "wof:placetype":"venue"
},
  "geometry": {"coordinates":[5.084741,48.685223],"type":"Point"}
}