{
  "type": "Feature",
  "properties": {
    "addr:full":"10 avenue de Friedland; 75008 Paris Ile de France",
    "addr:housenumber":"10",
    "addr:postcode":"75008",
    "addr:street":"Avenue De Friedland",
    "iso:country":"FR",
    "sg:address":"10 avenue de Friedland; 75008 Paris",
    "sg:classifiers":[
        {
            "category":"Industrial Area",
            "type":"Public Place"
        }
    ],
    "sg:phone":"+33 1 45 64 50 00",
    "sg:province":"Ile de France",
    "sg:tags":[
        "large",
        "private"
    ],
    "wof:name":"Soci\u00e9t\u00e9 Du Louvre",
    "wof:placetype":"venue"
},
  "geometry": {"coordinates":[2.303839,48.874924],"type":"Point"}
}