{
  "type": "Feature",
  "properties": {
    "iso:country":"FR",
    "sg:address":"32, Rte de Grenoble, 38430 Moirans",
    "sg:orig_category":"Unclassifiable Establishments",
    "sg:phone":"+33 4 76 35 33 00",
    "sg:province":"Rhone-Alpes",
    "wof:name":"Lomier Jean - Pierre",
    "wof:placetype":"venue"
},
  "geometry": {"coordinates":[5.580811,45.326138],"type":"Point"}
}