{
  "type": "Feature",
  "properties": {
    "iso:country":"FR",
    "sg:address":"B.P. 50",
    "sg:city":"Saint Cernin de Larche C\u00e9dex^^La Ferronnerie du Centre 19600 Saint Cernin de Larche",
    "sg:orig_category":"Non-Classified Establishments",
    "sg:phone":"+33 5 55 85 36 36",
    "sg:postcode":"19600",
    "sg:province":"Limousin",
    "wof:name":"Faure Et Fils S.a.",
    "wof:placetype":"venue"
},
  "geometry": {"coordinates":[1.41557,45.1026],"type":"Point"}
}