{
  "type": "Feature",
  "properties": {
    "addr:full":"1 Av Charcot 34240 Lamalou Les Bains Languedoc-Roussillon 34240",
    "addr:postcode":"34240;34240",
    "addr:street":"Av Charcot",
    "iso:country":"FR",
    "sg:address":"1 Av Charcot 34240 Lamalou Les Bains",
    "sg:classifiers":[
        {
            "category":"Travel",
            "subcategory":"Hotels & Motels",
            "type":"Entertainment"
        }
    ],
    "sg:phone":"+33 4 67 95 57 00",
    "sg:postcode":"34240",
    "sg:province":"Languedoc-Roussillon",
    "sg:tags":[
        "hotels",
        "business",
        "restaurant"
    ],
    "wof:name":"Belleville Sarl",
    "wof:placetype":"venue"
},
  "geometry": {"coordinates":[3.082405,43.594086],"type":"Point"}
}