{
  "type": "Feature",
  "properties": {
    "iso:country":"FR",
    "sg:address":"Centre Rouen Multimarchandises",
    "sg:city":"Saint Etienne du Rouvray",
    "sg:orig_category":"Unclassifiable Establishments",
    "sg:phone":"+33 2 35 64 19 20",
    "sg:postcode":"76800",
    "sg:province":"Haute Normandie",
    "wof:name":"T.t.a. S.a. - Tous Transports A\u00e9riens",
    "wof:placetype":"venue"
},
  "geometry": {"coordinates":[1.10721,49.379585],"type":"Point"}
}