{
  "type": "Feature",
  "properties": {
    "iso:country":"FR",
    "sg:address":"B.P. 20, 24120 Terrasson la Villedieu^^ZI Coutal, 24120 Terrasson la Villedieu",
    "sg:city":"Beauregard-de-Terrasson",
    "sg:orig_category":"Non-Classified Establishments",
    "sg:phone":"+33 5 53 50 22 88",
    "sg:postcode":"24120",
    "sg:province":"Aquitaine",
    "wof:name":"Biscuiterie Olibet S.a.r.l.",
    "wof:placetype":"venue"
},
  "geometry": {"coordinates":[1.31693,45.046028],"type":"Point"}
}