{
  "type": "Feature",
  "properties": {
    "iso:country":"FR",
    "sg:address":"49510 La Poitevini\u00e8re",
    "sg:orig_category":"Unclassifiable Establishments",
    "sg:phone":"+33 2 41 70 05 29",
    "sg:province":"Pays de Loire",
    "wof:name":"Breheret S.a.",
    "wof:placetype":"venue"
},
  "geometry": {"coordinates":[-0.896954,47.227261],"type":"Point"}
}