{
  "type": "Feature",
  "properties": {
    "addr:full":"9, All\u00e9e de l'Ile Gloriette, 44000 Nantes Pays de Loire",
    "addr:housenumber":"9",
    "addr:postcode":"44000",
    "addr:street":"Alle\u0301E De L'Ile Gloriette",
    "iso:country":"FR",
    "sg:address":"9, All\u00e9e de l'Ile Gloriette, 44000 Nantes",
    "sg:orig_category":"Unclassifiable Establishments",
    "sg:phone":"+33 2 40 89 50 57",
    "sg:province":"Pays de Loire",
    "wof:name":"Maxi Vid\u00e9o S.a.r.l.",
    "wof:placetype":"venue"
},
  "geometry": {"coordinates":[-1.557353,47.211159],"type":"Point"}
}