{
  "type": "Feature",
  "properties": {
    "addr:full":"B.P. 610 Furiani C\u00e9dex^^Basto-Chinchine 20600 Furiani Corse 20600",
    "addr:housenumber":"b.p. 610",
    "addr:postcode":"20600;20600",
    "addr:street":"Ce\u0301Dex^^Basto-Chinchine",
    "iso:country":"FR",
    "sg:address":"B.P. 610",
    "sg:city":"Furiani C\u00e9dex^^Basto-Chinchine 20600 Furiani",
    "sg:orig_category":"Non-Classified Establishments",
    "sg:phone":"+33 4 95 30 99 00",
    "sg:postcode":"20600",
    "sg:province":"Corse",
    "wof:name":"Enco Louis Raffalli S.a.r.l.",
    "wof:placetype":"venue"
},
  "geometry": {"coordinates":[9.415856,42.658413],"type":"Point"}
}