{
  "type": "Feature",
  "properties": {
    "addr:full":"23, Av. des Trois Peuples, 78180 Montigny le Bretonneux Ile de France 78180",
    "addr:postcode":"78180;78180",
    "addr:street":"23 Av. Des Trois Peuples",
    "iso:country":"FR",
    "sg:address":"23, Av. des Trois Peuples, 78180 Montigny le Bretonneux",
    "sg:orig_category":"Non-Classified Establishments",
    "sg:phone":"+33 1 30 43 11 17",
    "sg:postcode":"78180",
    "sg:province":"Ile de France",
    "wof:name":"Czmil S.a.",
    "wof:placetype":"venue"
},
  "geometry": {"coordinates":[2.019951,48.776394],"type":"Point"}
}