{
  "type": "Feature",
  "properties": {
    "addr:full":"1855, Rte d'Arras, 59554 Raillencourt Sainte Olle Nord Pas-de-Calais",
    "addr:housenumber":"1855",
    "addr:postcode":"59554",
    "addr:street":"Rte D'Arras;Sainte Olle Nord",
    "iso:country":"FR",
    "sg:address":"1855, Rte d'Arras, 59554 Raillencourt Sainte Olle",
    "sg:orig_category":"Non-Classified Establishments",
    "sg:phone":"+33 3 27 74 98 98",
    "sg:province":"Nord Pas-de-Calais",
    "wof:name":"France Pvc S.a.r.l.",
    "wof:placetype":"venue"
},
  "geometry": {"coordinates":[3.173692,50.188961],"type":"Point"}
}