{
  "type": "Feature",
  "properties": {
    "addr:full":"Rn 6 89200 Avallon Avallon Bourgogne 89200",
    "addr:postcode":"89200;89200",
    "addr:street":"Rn 6",
    "iso:country":"FR",
    "sg:address":"Rn 6 89200 Avallon",
    "sg:city":"Avallon",
    "sg:classifiers":[
        {
            "category":"Autos & Motor Vehicles",
            "subcategory":"Automobile Sales",
            "type":"Retail Goods"
        }
    ],
    "sg:phone":"+33 3 86 34 19 27",
    "sg:postcode":"89200",
    "sg:province":"Bourgogne",
    "sg:tags":[
        "equipment",
        "motor-cars",
        "transport"
    ],
    "wof:name":"Sodiva 2000",
    "wof:placetype":"venue"
},
  "geometry": {"coordinates":[3.907925,47.48978],"type":"Point"}
}