{
  "type": "Feature",
  "properties": {
    "addr:full":"Route de Janville 28700 AUNAY SOUS AUNEAU Auneau Centre 28700",
    "addr:postcode":"28700;28700",
    "addr:street":"Route De Janville",
    "iso:country":"FR",
    "sg:address":"Route de Janville 28700 AUNAY SOUS AUNEAU",
    "sg:city":"Auneau",
    "sg:classifiers":[
        {
            "category":"Building & Trades",
            "subcategory":"Locksmith",
            "type":"Services"
        }
    ],
    "sg:phone":"+33 2 37 91 23 59",
    "sg:postcode":"28700",
    "sg:province":"Centre",
    "sg:tags":[
        "chimney"
    ],
    "wof:name":"Soc. Supra Div. Richard Le Droff S.a.",
    "wof:placetype":"venue"
},
  "geometry": {"coordinates":[1.910886,48.354084],"type":"Point"}
}