{
  "type": "Feature",
  "properties": {
    "addr:full":"31, Rue des Fr\u00e8res Lumi\u00e8re, 69680 Chassieu Rhone-Alpes 69680",
    "addr:housenumber":"31",
    "addr:postcode":"69680;69680",
    "addr:street":"Rue Des Fre\u0300Res Lumie\u0300Re",
    "iso:country":"FR",
    "sg:address":"31, Rue des Fr\u00e8res Lumi\u00e8re, 69680 Chassieu",
    "sg:orig_category":"Unclassifiable Establishments",
    "sg:phone":"+33 4 72 47 39 39",
    "sg:postcode":"69680",
    "sg:province":"Rhone-Alpes",
    "wof:name":"Sta\u00fcbli Lyon S.a.",
    "wof:placetype":"venue"
},
  "geometry": {"coordinates":[4.961239,45.73431],"type":"Point"}
}