{
  "type": "Feature",
  "properties": {
    "addr:full":"5 Rue Jacques Monod 69320 Feyzin Rhone-Alpes 69320",
    "addr:housenumber":"5",
    "addr:postcode":"69320;69320",
    "addr:street":"Rue Jacques Monod",
    "iso:country":"FR",
    "sg:address":"5 Rue Jacques Monod 69320 Feyzin",
    "sg:classifiers":[
        {
            "category":"Home & Garden",
            "subcategory":"Furniture",
            "type":"Retail Goods"
        }
    ],
    "sg:phone":"+33 4 78 70 07 95",
    "sg:postcode":"69320",
    "sg:province":"Rhone-Alpes",
    "sg:tags":[
        "household",
        "wood"
    ],
    "wof:name":"Fournifleur",
    "wof:placetype":"venue"
},
  "geometry": {"coordinates":[4.849705,45.673664],"type":"Point"}
}