{
  "type": "Feature",
  "properties": {
    "addr:full":"6 Avenue Victoire 47230 Lavardac Lavardac Aquitaine 47230",
    "addr:housenumber":"6",
    "addr:postcode":"47230;47230",
    "addr:street":"Avenue Victoire",
    "iso:country":"FR",
    "sg:address":"6 Avenue Victoire 47230 Lavardac",
    "sg:city":"Lavardac",
    "sg:classifiers":[
        {
            "category":"Manufacturing",
            "subcategory":"Metals",
            "type":"Manufacturing & Wholesale Goods"
        }
    ],
    "sg:phone":"+33 5 53 65 53 61",
    "sg:postcode":"47230",
    "sg:province":"Aquitaine",
    "sg:tags":[
        "metallurgy",
        "metalworking",
        "processing"
    ],
    "wof:name":"Decolletage Et Mecanique Dalbret Sarl",
    "wof:placetype":"venue"
},
  "geometry": {"coordinates":[0.297485,44.176601],"type":"Point"}
}