{
  "type": "Feature",
  "properties": {
    "addr:full":"5 Square Saint Palais 81660 PAYRIN AUGMONTEL Midi Pyr\u00e9n\u00e9es 81660",
    "addr:housenumber":"5",
    "addr:postcode":"81660;81660",
    "addr:street":"Square Saint Palais",
    "iso:country":"FR",
    "sg:address":"5 Square Saint Palais 81660 PAYRIN AUGMONTEL",
    "sg:classifiers":[
        {
            "category":"Home & Garden",
            "subcategory":"Building Materials",
            "type":"Retail Goods"
        }
    ],
    "sg:phone":"+33 5 63 61 66 30",
    "sg:postcode":"81660",
    "sg:province":"Midi Pyr\u00e9n\u00e9es",
    "sg:tags":[
        "stone",
        "natural"
    ],
    "wof:name":"Export Stone France Sa",
    "wof:placetype":"venue"
},
  "geometry": {"coordinates":[2.344612,43.523014],"type":"Point"}
}