{
  "type": "Feature",
  "properties": {
    "addr:full":"8, All\u00e9e du Solier, 43220 Duni\u00e8res Duni\u00e8res Auvergne 43220",
    "addr:housenumber":"8",
    "addr:postcode":"43220;dunie\u0300res;43220",
    "addr:street":"Alle\u0301E Du Solier",
    "iso:country":"FR",
    "sg:address":"8, All\u00e9e du Solier, 43220 Duni\u00e8res",
    "sg:city":"Duni\u00e8res",
    "sg:orig_category":"Unclassifiable Establishments",
    "sg:phone":"+33 4 71 61 71 20",
    "sg:postcode":"43220",
    "sg:province":"Auvergne",
    "wof:name":"Pochon Tissage S.a.",
    "wof:placetype":"venue"
},
  "geometry": {"coordinates":[4.426631,45.186089],"type":"Point"}
}