{
  "type": "Feature",
  "properties": {
    "iso:country":"FR",
    "sg:address":"B.P. 104, 92164 Antony C\u00e9dex^^4, Av. Maurice Ravel, 92160 Antony",
    "sg:orig_category":"Non-Classified Establishments",
    "sg:phone":"+33 1 46 74 26 00",
    "sg:province":"Ile de France",
    "wof:name":"Universal Music S.a.",
    "wof:placetype":"venue"
},
  "geometry": {"coordinates":[2.302653,48.752647],"type":"Point"}
}