{
  "type": "Feature",
  "properties": {
    "addr:full":"26 Rue De Campilleau 33520 Bruges En France Bruges Aquitaine 33520",
    "addr:housenumber":"26",
    "addr:postcode":"33520;33520",
    "addr:street":"Rue De Campilleau",
    "iso:country":"FR",
    "sg:address":"26 Rue De Campilleau 33520 Bruges En France",
    "sg:city":"Bruges",
    "sg:classifiers":[
        {
            "category":"Marine",
            "type":"Transportation"
        }
    ],
    "sg:phone":"+33 5 56 16 15 14",
    "sg:postcode":"33520",
    "sg:province":"Aquitaine",
    "sg:tags":[
        "transport",
        "sea"
    ],
    "wof:name":"Petromarine Sa",
    "wof:placetype":"venue"
},
  "geometry": {"coordinates":[-0.615639,44.892632],"type":"Point"}
}