{
  "type": "Feature",
  "properties": {
    "iso:country":"FR",
    "sg:address":"B.P. 27, 88151 Thaon Les Vosges C\u00e9dex^^Z.I. Inova 3000, 88150 Thaon les Vosges",
    "sg:orig_category":"Non-Classified Establishments",
    "sg:phone":"+33 3 29 81 26 26",
    "sg:province":"Lorraine",
    "wof:name":"Sog\u00e9trel S.a. - Soci\u00e9t\u00e9 De Gestion D'ing\u00e9nierie Et De Travaux Electriques",
    "wof:placetype":"venue"
},
  "geometry": {"coordinates":[6.41948,48.250435],"type":"Point"}
}