{
  "type": "Feature",
  "properties": {
    "addr:full":"7, Rue de la Grosse Pierre, 78540 Vernouillet Ile de France",
    "addr:housenumber":"7",
    "addr:postcode":"78540;ile",
    "addr:street":"Rue De La Grosse Pierre",
    "iso:country":"FR",
    "sg:address":"7, Rue de la Grosse Pierre, 78540 Vernouillet",
    "sg:orig_category":"Unclassifiable Establishments",
    "sg:phone":"+33 1 39 65 69 09",
    "sg:province":"Ile de France",
    "wof:name":"Ouest-emballage 78 S.a.",
    "wof:placetype":"venue"
},
  "geometry": {"coordinates":[1.994875,48.976639],"type":"Point"}
}