{
  "type": "Feature",
  "properties": {
    "addr:full":"B.P. 1297, 31047 Toulouse C\u00e9dex^^150, Rue Nicolas Louis Vauguelin - Immeuble Buropolis, 31000 Toulou Midi Pyr\u00e9n\u00e9es 31000",
    "addr:housenumber":"1297",
    "addr:postcode":"31047;31000;31000",
    "addr:street":"B.P.;Rue Nicolas Louis Vauguelin",
    "iso:country":"FR",
    "sg:address":"B.P. 1297, 31047 Toulouse C\u00e9dex^^150, Rue Nicolas Louis Vauguelin - Immeuble Buropolis, 31000 Toulou",
    "sg:orig_category":"Non-Classified Establishments",
    "sg:phone":"+33 5 61 31 59 00",
    "sg:postcode":"31000",
    "sg:province":"Midi Pyr\u00e9n\u00e9es",
    "wof:name":"Bureau V\u00e9ritas S.a.",
    "wof:placetype":"venue"
},
  "geometry": {"coordinates":[1.44869,43.60574],"type":"Point"}
}