{
  "type": "Feature",
  "properties": {
    "iso:country":"FR",
    "sg:address":"B.P. 32, 56038 Vannes C\u00e9dex^^Rue du Commerce - Parc Innovation Bretagne Sud, 56000 Vannes",
    "sg:city":"Vannes",
    "sg:orig_category":"Non-Classified Establishments",
    "sg:phone":"+33 2 97 42 68 00",
    "sg:postcode":"56000",
    "sg:province":"Bretagne",
    "wof:name":"Wind River Systems S.a.r.l.",
    "wof:placetype":"venue"
},
  "geometry": {"coordinates":[-2.759959,47.658169],"type":"Point"}
}