{
  "type": "Feature",
  "properties": {
    "addr:full":"19, Av. Jules Carteret, 69007 Lyon Rhone-Alpes 69007",
    "addr:postcode":"69007;69007",
    "addr:street":"19 Av. Jules Carteret",
    "iso:country":"FR",
    "sg:address":"19, Av. Jules Carteret, 69007 Lyon",
    "sg:orig_category":"Unclassifiable Establishments",
    "sg:phone":"+33 4 74 94 06 54",
    "sg:postcode":"69007",
    "sg:province":"Rhone-Alpes",
    "wof:name":"Plastic Omnium M\u00e9dical S.a.",
    "wof:placetype":"venue"
},
  "geometry": {"coordinates":[4.84439,45.725941],"type":"Point"}
}