{
  "type": "Feature",
  "properties": {
    "iso:country":"FR",
    "sg:address":"21 rue de la Victoire 93150 Le Blanc Mesnil",
    "sg:classifiers":[
        {
            "category":"Banks & Credit Unions",
            "subcategory":"Bank",
            "type":"Services"
        }
    ],
    "sg:phone":"+33 1 48 65 20 74",
    "sg:postcode":"93150",
    "sg:province":"Ile de France",
    "sg:tags":[
        "equipment",
        "miscellaneous",
        "hydraulic",
        "accessory"
    ],
    "wof:name":"Decoflex S.a.",
    "wof:placetype":"venue"
},
  "geometry": {"coordinates":[2.445929,48.942928],"type":"Point"}
}