{
  "type": "Feature",
  "properties": {
    "iso:country":"FR",
    "sg:address":"262 avenue George Washington 62400 BETHUNE",
    "sg:classifiers":[
        {
            "category":"Manufacturing",
            "subcategory":"Building Materials",
            "type":"Manufacturing & Wholesale Goods"
        }
    ],
    "sg:phone":"+33 3 21 63 23 73",
    "sg:postcode":"62400",
    "sg:province":"Nord Pas-de-Calais",
    "sg:tags":[
        "fibre-reinforced",
        "composite"
    ],
    "wof:name":"Ste Transfor Indust Mat Orthop Plastique S.a.",
    "wof:placetype":"venue"
},
  "geometry": {"coordinates":[2.651483,50.540607],"type":"Point"}
}