{
  "type": "Feature",
  "properties": {
    "addr:full":"B.P. 1, 34660 Cournonterral^^Rue des Barrys, 34660 Cournonsec Languedoc-Roussillon 34660",
    "addr:housenumber":"1",
    "addr:postcode":"34660;34660;34660",
    "addr:street":"B.P.;Des Barrys",
    "iso:country":"FR",
    "sg:address":"B.P. 1, 34660 Cournonterral^^Rue des Barrys, 34660 Cournonsec",
    "sg:orig_category":"Non-Classified Establishments",
    "sg:phone":"+33 4 67 85 39 26",
    "sg:postcode":"34660",
    "sg:province":"Languedoc-Roussillon",
    "wof:name":"Entreprise Jouli\u00e9 T.p. S.n.c.",
    "wof:placetype":"venue"
},
  "geometry": {"coordinates":[3.707925,43.54879],"type":"Point"}
}