{
  "type": "Feature",
  "properties": {
    "iso:country":"FR",
    "sg:address":"6 Rue De La Jeannaie Zi 22400 Lamballe",
    "sg:city":"Lamballe",
    "sg:classifiers":[
        {
            "category":"Manufacturing",
            "subcategory":"Chemicals & Compounds",
            "type":"Manufacturing & Wholesale Goods"
        }
    ],
    "sg:phone":"+33 2 96 31 38 21",
    "sg:postcode":"22400",
    "sg:province":"Bretagne",
    "sg:tags":[
        "pharmaceutical",
        "energy",
        "chemistry",
        "-",
        "by-product"
    ],
    "wof:name":"Bollore Energie",
    "wof:placetype":"venue"
},
  "geometry": {"coordinates":[-2.539697,48.428795],"type":"Point"}
}