{
  "type": "Feature",
  "properties": {
    "iso:country":"FR",
    "sg:address":"98 Rue Paul Vaillant Couturier 92240 Malakoff",
    "sg:classifiers":[
        {
            "category":"Professional",
            "subcategory":"Engineering",
            "type":"Services"
        }
    ],
    "sg:phone":"+33 1 46 55 39 93",
    "sg:postcode":"92240",
    "sg:province":"Ile de France",
    "sg:tags":[
        "machine",
        "-",
        "mechanical"
    ],
    "wof:name":"Sidfrem",
    "wof:placetype":"venue"
},
  "geometry": {"coordinates":[2.294242,48.815464],"type":"Point"}
}