{
  "type": "Feature",
  "properties": {
    "addr:full":"B.P. 247, 54004 Nancy C\u00e9dex^^44, Cours L\u00e9opold, 54000 Nancy Lorraine",
    "addr:housenumber":"b.p. 247",
    "addr:postcode":"54004;54000",
    "addr:street":"Cours Le\u0301Opold",
    "iso:country":"FR",
    "sg:address":"B.P. 247, 54004 Nancy C\u00e9dex^^44, Cours L\u00e9opold, 54000 Nancy",
    "sg:orig_category":"Non-Classified Establishments",
    "sg:phone":"+33 3 83 37 34 46",
    "sg:province":"Lorraine",
    "wof:name":"Union Est Agro S.a.",
    "wof:placetype":"venue"
},
  "geometry": {"coordinates":[6.183405,48.689548],"type":"Point"}
}