{
  "type": "Feature",
  "properties": {
    "iso:country":"FR",
    "sg:address":"Rte de Castries",
    "sg:city":"Assas",
    "sg:orig_category":"Unclassifiable Establishments",
    "sg:phone":"+33 4 67 59 62 96",
    "sg:postcode":"34820",
    "sg:province":"Languedoc-Roussillon",
    "wof:name":"Lamb\u00e9 Ets E.u.r.l.",
    "wof:placetype":"venue"
},
  "geometry": {"coordinates":[3.90126,43.70208],"type":"Point"}
}