{
  "type": "Feature",
  "properties": {
    "iso:country":"FR",
    "sg:address":"B.P. 428, 19311 Brive la Gaillarde C\u00e9dex^^6, Rue Lieutenant Colonel Laporte, 19100 Brive la Gaillard",
    "sg:orig_category":"Non-Classified Establishments",
    "sg:phone":"+33 5 55 92 89 89",
    "sg:province":"Limousin",
    "wof:name":"Thomson Csf Communications",
    "wof:placetype":"venue"
},
  "geometry": {"coordinates":[1.53587,45.157036],"type":"Point"}
}