{
  "type": "Feature",
  "properties": {
    "addr:full":"Rte de la Touques Gac\u00e9 Basse Normandie 61230",
    "addr:postcode":"61230",
    "addr:street":"Rte De La Touques",
    "iso:country":"FR",
    "sg:address":"Rte de la Touques",
    "sg:city":"Gac\u00e9",
    "sg:orig_category":"Unclassifiable Establishments",
    "sg:phone":"+33 2 33 35 18 35",
    "sg:postcode":"61230",
    "sg:province":"Basse Normandie",
    "wof:name":"Tenpack S.a.",
    "wof:placetype":"venue"
},
  "geometry": {"coordinates":[0.292669,48.794426],"type":"Point"}
}