{
  "type": "Feature",
  "properties": {
    "iso:country":"FR",
    "sg:address":"31 Avenue Du Dix Huitieme Ri 64000 Pau",
    "sg:city":"Pau",
    "sg:classifiers":[
        {
            "category":"Wholesale",
            "subcategory":"Medical Equipment & Supplies",
            "type":"Manufacturing & Wholesale Goods"
        }
    ],
    "sg:phone":"+33 5 59 83 84 55",
    "sg:postcode":"64000",
    "sg:province":"Aquitaine",
    "sg:tags":[
        "instrument",
        "health",
        "-",
        "precision"
    ],
    "wof:name":"Delaire Bernatas",
    "wof:placetype":"venue"
},
  "geometry": {"coordinates":[-0.386438,43.29763],"type":"Point"}
}