{
  "type": "Feature",
  "properties": {
    "addr:full":"Le Village 26190 St Laurent En Royans Rhone-Alpes 26190",
    "addr:postcode":"26190;26190",
    "addr:street":"Le Village;St Laurent En;Rhone-Alpes",
    "iso:country":"FR",
    "sg:address":"Le Village 26190 St Laurent En Royans",
    "sg:classifiers":[
        {
            "category":"Shopping",
            "subcategory":"Crafts & Fabrics",
            "type":"Retail Goods"
        }
    ],
    "sg:phone":"+33 4 75 47 55 11",
    "sg:postcode":"26190",
    "sg:province":"Rhone-Alpes",
    "sg:tags":[
        "textile",
        "clothing"
    ],
    "wof:name":"Vercors Tissage Sa",
    "wof:placetype":"venue"
},
  "geometry": {"coordinates":[5.182355,44.886749],"type":"Point"}
}