{
  "type": "Feature",
  "properties": {
    "iso:country":"FR",
    "sg:address":"Le Bouchet 38230 Chavanoz",
    "sg:classifiers":[
        {
            "category":"Home & Garden",
            "subcategory":"Furniture",
            "type":"Retail Goods"
        }
    ],
    "sg:phone":"+33 4 78 32 10 23",
    "sg:province":"Rhone-Alpes",
    "sg:tags":[
        "wood"
    ],
    "wof:name":"Peinetti Emballages Sa",
    "wof:placetype":"venue"
},
  "geometry": {"coordinates":[5.18255,45.775944],"type":"Point"}
}