{
  "type": "Feature",
  "properties": {
    "addr:full":"Av Jean Precheur Duppigheim Alsace 67120",
    "addr:postcode":"67120",
    "addr:street":"Av Jean Precheur",
    "iso:country":"FR",
    "sg:address":"Av Jean Precheur",
    "sg:city":"Duppigheim",
    "sg:orig_category":"Unclassifiable Establishments",
    "sg:phone":"+33 3 88 49 16 55",
    "sg:postcode":"67120",
    "sg:province":"Alsace",
    "wof:name":"Euremo S.a.",
    "wof:placetype":"venue"
},
  "geometry": {"coordinates":[7.584512,48.543179],"type":"Point"}
}