{
  "type": "Feature",
  "properties": {
    "addr:full":"84 bis, Rue Garibaldi, 94100 Saint Maur des Foss\u00e9s Ile de France",
    "addr:housenumber":"84 bis",
    "addr:postcode":"94100",
    "addr:street":"Rue Garibaldi;Des Fosse\u0301S Ile De France",
    "iso:country":"FR",
    "sg:address":"84 bis, Rue Garibaldi, 94100 Saint Maur des Foss\u00e9s",
    "sg:orig_category":"Non-Classified Establishments",
    "sg:phone":"+33 1 48 89 85 00",
    "sg:province":"Ile de France",
    "wof:name":"P.i.c. T\u00e9l\u00e9matique S.a.r.l. - Picardie Informatique Communication",
    "wof:placetype":"venue"
},
  "geometry": {"coordinates":[2.485249,48.794514],"type":"Point"}
}