{
  "type": "Feature",
  "properties": {
    "iso:country":"FR",
    "sg:address":"B.P. 17, 81540 Durfort^^5, le Plo, 81540 Durfort",
    "sg:orig_category":"Non-Classified Establishments",
    "sg:phone":"+33 5 63 74 10 52",
    "sg:province":"Midi Pyr\u00e9n\u00e9es",
    "wof:name":"Etablissements Pierre Vergnes S.a.r.l.",
    "wof:placetype":"venue"
},
  "geometry": {"coordinates":[2.076339,43.41246],"type":"Point"}
}