{
  "type": "Feature",
  "properties": {
    "iso:country":"FR",
    "sg:address":"Rue Georges Eastman Pa Bord De Sa\u00f4ne 71100 Chalon Sur Saone",
    "sg:city":"Chalon-sur-Sa\u00f4ne",
    "sg:classifiers":[
        {
            "category":"Manufacturing",
            "subcategory":"Rubber & Plastics",
            "type":"Manufacturing & Wholesale Goods"
        }
    ],
    "sg:phone":"+33 3 85 48 95 26",
    "sg:postcode":"71100",
    "sg:province":"Bourgogne",
    "wof:name":"Mpib",
    "wof:placetype":"venue"
},
  "geometry": {"coordinates":[4.85501,46.779694],"type":"Point"}
}