{
  "type": "Feature",
  "properties": {
    "addr:full":"609 Rue Du Moulin 59190 Caestre Nord Pas-de-Calais",
    "addr:housenumber":"609",
    "addr:postcode":"59190",
    "addr:street":"Rue Du Moulin;Caestre Nord",
    "iso:country":"FR",
    "sg:address":"609 Rue Du Moulin 59190 Caestre",
    "sg:classifiers":[
        {
            "category":"Manufacturing",
            "subcategory":"Paper Products",
            "type":"Manufacturing & Wholesale Goods"
        }
    ],
    "sg:phone":"+33 3 28 43 82 82",
    "sg:province":"Nord Pas-de-Calais",
    "sg:tags":[
        "raw",
        "material",
        "-",
        "cardboard"
    ],
    "wof:name":"Dsa Emballage",
    "wof:placetype":"venue"
},
  "geometry": {"coordinates":[2.610778,50.761513],"type":"Point"}
}