{
  "type": "Feature",
  "properties": {
    "addr:full":"3, Bd de l'Europe - Tour de l'Europe, 68100 Mulhouse Mulhouse Alsace 68100",
    "addr:housenumber":"3",
    "addr:postcode":"68100;68100",
    "addr:street":"Bd De L'Europe Tour De L'Europe",
    "iso:country":"FR",
    "sg:address":"3, Bd de l'Europe - Tour de l'Europe, 68100 Mulhouse",
    "sg:city":"Mulhouse",
    "sg:orig_category":"Non-Classified Establishments",
    "sg:phone":"+33 3 89 66 08 60",
    "sg:postcode":"68100",
    "sg:province":"Alsace",
    "wof:name":"Beck Alain Consultants",
    "wof:placetype":"venue"
},
  "geometry": {"coordinates":[7.349008,47.746971],"type":"Point"}
}