{
  "type": "Feature",
  "properties": {
    "addr:full":"Zi Des Bois De Monts 49680 Vivy Pays de Loire",
    "addr:postcode":"49680",
    "addr:street":"Des Bois De Monts",
    "iso:country":"FR",
    "sg:address":"Zi Des Bois De Monts 49680 Vivy",
    "sg:classifiers":[
        {
            "category":"Home & Garden",
            "subcategory":"Furniture",
            "type":"Retail Goods"
        }
    ],
    "sg:phone":"+33 2 41 52 57 96",
    "sg:province":"Pays de Loire",
    "sg:tags":[
        "wood"
    ],
    "wof:name":"Chevrollier Sarl",
    "wof:placetype":"venue"
},
  "geometry": {"coordinates":[-0.057519,47.327534],"type":"Point"}
}