{
  "type": "Feature",
  "properties": {
    "addr:full":"44 Rue Marcel Grosmenil 94800 Villejuif Ile de France 94800",
    "addr:housenumber":"44",
    "addr:postcode":"94800;ile;94800",
    "addr:street":"Rue Marcel Grosmenil;France",
    "iso:country":"FR",
    "sg:address":"44 Rue Marcel Grosmenil 94800 Villejuif",
    "sg:classifiers":[
        {
            "category":"Professional",
            "subcategory":"Engineering",
            "type":"Services"
        }
    ],
    "sg:phone":"+33 1 43 90 14 20",
    "sg:postcode":"94800",
    "sg:province":"Ile de France",
    "sg:tags":[
        "machine",
        "-",
        "mechanical"
    ],
    "wof:name":"Sipc",
    "wof:placetype":"venue"
},
  "geometry": {"coordinates":[2.354609,48.797894],"type":"Point"}
}