{
  "type": "Feature",
  "properties": {
    "addr:full":"40 rue Condorcet 38090 VAULX MILIEU Rhone-Alpes 38090",
    "addr:housenumber":"40",
    "addr:postcode":"38090;38090",
    "addr:street":"Rue Condorcet;Rhone-Alpes",
    "iso:country":"FR",
    "sg:address":"40 rue Condorcet 38090 VAULX MILIEU",
    "sg:classifiers":[
        {
            "category":"Building & Trades",
            "subcategory":"Construction",
            "type":"Services"
        }
    ],
    "sg:phone":"+33 4 74 82 27 27",
    "sg:postcode":"38090",
    "sg:province":"Rhone-Alpes",
    "sg:tags":[
        "installation",
        "air-conditioning",
        "system"
    ],
    "wof:name":"Soprano Sas",
    "wof:placetype":"venue"
},
  "geometry": {"coordinates":[5.172664,45.625366],"type":"Point"}
}