{
  "type": "Feature",
  "properties": {
    "iso:country":"FR",
    "sg:address":"4",
    "sg:city":"Holtzheim",
    "sg:classifiers":[
        {
            "category":"Manufacturing",
            "subcategory":"Wood Products",
            "type":"Manufacturing & Wholesale Goods"
        }
    ],
    "sg:phone":"+33 3 88 10 18 60",
    "sg:postcode":"67810",
    "sg:province":"Alsace",
    "sg:tags":[
        "miscellaneous",
        "furniture"
    ],
    "wof:name":"Woodex",
    "wof:placetype":"venue"
},
  "geometry": {"coordinates":[7.652469,48.558952],"type":"Point"}
}