{
  "type": "Feature",
  "properties": {
    "iso:country":"FR",
    "sg:address":"43 Rue Damr\u00e9mont 75018 Paris",
    "sg:classifiers":[
        {
            "category":"Manufacturing",
            "subcategory":"Printing",
            "type":"Manufacturing & Wholesale Goods"
        }
    ],
    "sg:phone":"+33 1 53 41 14 14",
    "sg:province":"Ile de France",
    "sg:tags":[
        "publishing"
    ],
    "wof:name":"Imprimerie A. Capelle",
    "wof:placetype":"venue"
},
  "geometry": {"coordinates":[2.333743,48.88998],"type":"Point"}
}