{
  "type": "Feature",
  "properties": {
    "iso:country":"FR",
    "sg:address":"3 rue Maurice Leblanc 77124 Cregy les Meaux",
    "sg:classifiers":[
        {
            "category":"Manufacturing",
            "subcategory":"Glass & Minerals",
            "type":"Manufacturing & Wholesale Goods"
        }
    ],
    "sg:phone":"+33 1 64 33 95 00",
    "sg:postcode":"77124",
    "sg:province":"Ile de France",
    "sg:tags":[
        "frame"
    ],
    "wof:name":"Chamborelle Sa",
    "wof:placetype":"venue"
},
  "geometry": {"coordinates":[2.862771,48.970867],"type":"Point"}
}