{
  "type": "Feature",
  "properties": {
    "addr:full":"B.P. 37, 21301 Chen\u00f4ve C\u00e9dex^^18, Rue des Fr\u00e8res Montgolfier, 21300 Chen\u00f4ve Chen\u00f4ve Bourgogne 21300",
    "addr:postcode":"21301;21300;21300",
    "addr:street":"B.P. 37;Rue Des Fre\u0300Res Montgolfier",
    "iso:country":"FR",
    "sg:address":"B.P. 37, 21301 Chen\u00f4ve C\u00e9dex^^18, Rue des Fr\u00e8res Montgolfier, 21300 Chen\u00f4ve",
    "sg:city":"Chen\u00f4ve",
    "sg:orig_category":"Non-Classified Establishments",
    "sg:phone":"+33 3 80 52 05 25",
    "sg:postcode":"21300",
    "sg:province":"Bourgogne",
    "wof:name":"Sobomat Manudir S.a.r.l.",
    "wof:placetype":"venue"
},
  "geometry": {"coordinates":[5.004665,47.294296],"type":"Point"}
}