{
  "type": "Feature",
  "properties": {
    "iso:country":"FR",
    "sg:address":"Zi De Grand Fontaine 38490 Chimilin",
    "sg:classifiers":[
        {
            "category":"Professional",
            "subcategory":"Business Services",
            "type":"Services"
        }
    ],
    "sg:phone":"+33 4 76 32 50 17",
    "sg:postcode":"38490",
    "sg:province":"Rhone-Alpes",
    "sg:tags":[
        "advice",
        "fabric",
        "clothes"
    ],
    "wof:name":"Preparation Textile De Chimilin (ptc)",
    "wof:placetype":"venue"
},
  "geometry": {"coordinates":[5.600455,45.57695],"type":"Point"}
}