{
  "type": "Feature",
  "properties": {
    "iso:country":"FR",
    "sg:address":"64, Rue des Anguignis, 45100 Orl\u00e9ans",
    "sg:city":"Orl\u00e9ans",
    "sg:orig_category":"Unclassifiable Establishments",
    "sg:phone":"+33 2 38 66 80 80",
    "sg:postcode":"45100",
    "sg:province":"Centre",
    "wof:name":"Novator S.a.r.l.",
    "wof:placetype":"venue"
},
  "geometry": {"coordinates":[1.912563,47.888718],"type":"Point"}
}