{
  "type": "Feature",
  "properties": {
    "addr:full":"41, Rue Delizy - Immeuble les Diamants, 93500 Pantin Ile de France",
    "addr:housenumber":"41",
    "addr:postcode":"93500;ile",
    "addr:street":"Rue Delizy Immeuble Les Diamants",
    "iso:country":"FR",
    "sg:address":"41, Rue Delizy - Immeuble les Diamants, 93500 Pantin",
    "sg:orig_category":"Unclassifiable Establishments",
    "sg:phone":"+33 1 41 83 44 73",
    "sg:province":"Ile de France",
    "wof:name":"Bvrp Software S.a.",
    "wof:placetype":"venue"
},
  "geometry": {"coordinates":[2.407693,48.897297],"type":"Point"}
}