{
  "type": "Feature",
  "properties": {
    "iso:country":"FR",
    "sg:address":"ZI Sud",
    "sg:city":"Bellignat",
    "sg:orig_category":"Unclassifiable Establishments",
    "sg:phone":"+33 4 74 73 97 89",
    "sg:postcode":"01100",
    "sg:province":"Rhone-Alpes",
    "wof:name":"Battenfeld France S.a.",
    "wof:placetype":"venue"
},
  "geometry": {"coordinates":[5.62927,46.242184],"type":"Point"}
}