{
  "type": "Feature",
  "properties": {
    "iso:country":"FR",
    "sg:address":"32E rue V\u00e9nus 13127 Vitrolles",
    "sg:classifiers":[
        {
            "category":"Banks & Credit Unions",
            "subcategory":"Investment Brokerage",
            "type":"Services"
        }
    ],
    "sg:phone":"+33 4 42 46 10 60",
    "sg:province":"Provence-Alpes-C\u00f4te d'Azur",
    "sg:tags":[
        "pasta",
        "production",
        "semolina"
    ],
    "wof:name":"Ferico Sa",
    "wof:placetype":"venue"
},
  "geometry": {"coordinates":[5.27532,43.421406],"type":"Point"}
}