{
  "type": "Feature",
  "properties": {
    "addr:full":"35, Rte d'Arras, 59155 Faches Thumesnil Nord Pas-de-Calais",
    "addr:housenumber":"35",
    "addr:postcode":"59155",
    "addr:street":"Rte D'Arras;Thumesnil",
    "iso:country":"FR",
    "sg:address":"35, Rte d'Arras, 59155 Faches Thumesnil",
    "sg:orig_category":"Non-Classified Establishments",
    "sg:phone":"+33 3 20 88 15 20",
    "sg:province":"Nord Pas-de-Calais",
    "wof:name":"Fermetures Lilloises S.a.r.l.",
    "wof:placetype":"venue"
},
  "geometry": {"coordinates":[3.061501,50.611279],"type":"Point"}
}