{
  "type": "Feature",
  "properties": {
    "iso:country":"FR",
    "sg:address":"6 Rue Nicolas Copernic",
    "sg:city":"Trappes",
    "sg:classifiers":[
        {
            "category":"Banks & Credit Unions",
            "subcategory":"Financial Services",
            "type":"Services"
        }
    ],
    "sg:phone":"+33 1 30 66 80 00",
    "sg:postcode":"78190",
    "sg:province":"Ile de France",
    "sg:tags":[
        "banking",
        "finance",
        "insurance"
    ],
    "wof:name":"Iveco Unic Sa",
    "wof:placetype":"venue"
},
  "geometry": {"coordinates":[1.991885,48.765858],"type":"Point"}
}