{
  "type": "Feature",
  "properties": {
    "iso:country":"FR",
    "sg:address":"chemin des Romains 57140 Woippy",
    "sg:classifiers":[
        {
            "category":"Manufacturing",
            "subcategory":"Metals",
            "type":"Manufacturing & Wholesale Goods"
        }
    ],
    "sg:phone":"+33 3 87 51 11 00",
    "sg:postcode":"57140",
    "sg:province":"Lorraine",
    "sg:tags":[
        "alloy",
        "construction",
        "lightweight"
    ],
    "wof:name":"Prafer Snc",
    "wof:placetype":"venue"
},
  "geometry": {"coordinates":[6.151285,49.185024],"type":"Point"}
}