{
  "type": "Feature",
  "properties": {
    "iso:country":"FR",
    "sg:address":"510 avenue du G\u00e9n\u00e9ral de Gaulle 92140 Clamart",
    "sg:classifiers":[
        {
            "category":"Shopping",
            "subcategory":"Clothing, Apparel, & Fashions",
            "type":"Retail Goods"
        }
    ],
    "sg:phone":"+33 1 46 31 86 00",
    "sg:postcode":"92140",
    "sg:province":"Ile de France",
    "sg:tags":[
        "blouse",
        "ladies'",
        "dress"
    ],
    "wof:name":"Janlys Sa",
    "wof:placetype":"venue"
},
  "geometry": {"coordinates":[2.233774,48.778351],"type":"Point"}
}