{
  "type": "Feature",
  "properties": {
    "addr:full":"Av De La Vall\u00e9e 57870 Hartzviller Lorraine 57870",
    "addr:postcode":"57870;57870",
    "addr:street":"Av De La Valle\u0301E",
    "iso:country":"FR",
    "sg:address":"Av De La Vall\u00e9e 57870 Hartzviller",
    "sg:classifiers":[
        {
            "category":"Manufacturing",
            "subcategory":"Glass & Minerals",
            "type":"Manufacturing & Wholesale Goods"
        }
    ],
    "sg:phone":"+33 3 87 25 10 55",
    "sg:postcode":"57870",
    "sg:province":"Lorraine",
    "sg:tags":[
        "building",
        "material"
    ],
    "wof:name":"Cristalleries De Hartzviller Sarl",
    "wof:placetype":"venue"
},
  "geometry": {"coordinates":[7.083005,48.67239],"type":"Point"}
}