{
  "type": "Feature",
  "properties": {
    "iso:country":"FR",
    "sg:address":"120, Rte de Revel, 31400 Toulouse",
    "sg:orig_category":"Non-Classified Establishments",
    "sg:phone":"+33 5 61 20 80 76",
    "sg:province":"Midi Pyr\u00e9n\u00e9es",
    "wof:name":"Gau S.a.",
    "wof:placetype":"venue"
},
  "geometry": {"coordinates":[1.492332,43.57328],"type":"Point"}
}