{
  "type": "Feature",
  "properties": {
    "iso:country":"FR",
    "sg:address":"28, Rte du Bassin n\u00b06, 92230 Gennevilliers",
    "sg:orig_category":"Unclassifiable Establishments",
    "sg:phone":"+33 1 46 85 40 40",
    "sg:province":"Ile de France",
    "wof:name":"M.g.f. S.a. - Magasins G\u00e9n\u00e9raux De France",
    "wof:placetype":"venue"
},
  "geometry": {"coordinates":[2.294686,48.949123],"type":"Point"}
}