{
  "type": "Feature",
  "properties": {
    "iso:country":"FR",
    "sg:address":"4, Rue du G\u00e9n\u00e9ral Lanrezac, 75017 Paris",
    "sg:orig_category":"Unclassifiable Establishments",
    "sg:phone":"+33 1 44 09 01 01",
    "sg:province":"Ile de France",
    "wof:name":"Copyright Promotions",
    "wof:placetype":"venue"
},
  "geometry": {"coordinates":[2.293871,48.875854],"type":"Point"}
}