{
  "type": "Feature",
  "properties": {
    "iso:country":"FR",
    "sg:address":"104, Rue des Bains, 68390 Sausheim",
    "sg:city":"Sausheim",
    "sg:orig_category":"Unclassifiable Establishments",
    "sg:phone":"+33 3 89 31 06 20",
    "sg:postcode":"68390",
    "sg:province":"Alsace",
    "wof:name":"Edox S.a.r.l.",
    "wof:placetype":"venue"
},
  "geometry": {"coordinates":[7.387061,47.786175],"type":"Point"}
}