{
  "type": "Feature",
  "properties": {
    "addr:full":"3 Passage Gonin 69001 Lyon Rhone-Alpes 69001",
    "addr:housenumber":"3",
    "addr:postcode":"69001;69001",
    "addr:street":"Passage Gonin",
    "iso:country":"FR",
    "sg:address":"3 Passage Gonin 69001 Lyon",
    "sg:classifiers":[
        {
            "category":"Shopping",
            "subcategory":"Clothing, Apparel, & Fashions",
            "type":"Retail Goods"
        }
    ],
    "sg:phone":"+33 4 78 39 15 54",
    "sg:postcode":"69001",
    "sg:province":"Rhone-Alpes",
    "sg:tags":[
        "textile",
        "clothing",
        "clothes"
    ],
    "wof:name":"Anciens Ets Chatel Et Cie",
    "wof:placetype":"venue"
},
  "geometry": {"coordinates":[4.824418,45.768566],"type":"Point"}
}