{
  "type": "Feature",
  "properties": {
    "addr:full":"Rte Romeneau 21530 La Roche En Brenil La Roche-en-Brenil Bourgogne 21530",
    "addr:postcode":"21530;21530",
    "addr:street":"Rte Romeneau;Roche En Brenil La",
    "iso:country":"FR",
    "sg:address":"Rte Romeneau 21530 La Roche En Brenil",
    "sg:city":"La Roche-en-Brenil",
    "sg:classifiers":[
        {
            "category":"Professional",
            "type":"Services"
        }
    ],
    "sg:phone":"+33 3 80 64 71 67",
    "sg:postcode":"21530",
    "sg:province":"Bourgogne",
    "sg:tags":[
        "transport",
        "road"
    ],
    "wof:name":"Transports Seguin Sa",
    "wof:placetype":"venue"
},
  "geometry": {"coordinates":[4.192475,47.370403],"type":"Point"}
}