{
  "type": "Feature",
  "properties": {
    "addr:full":"2 rue de Carnac 56470 La Trinite Sur Mer Saint-Philibert Bretagne 56470",
    "addr:housenumber":"2",
    "addr:postcode":"56470",
    "addr:street":"Rue De Carnac;Trinite",
    "iso:country":"FR",
    "sg:address":"2 rue de Carnac 56470 La Trinite Sur Mer",
    "sg:city":"Saint-Philibert",
    "sg:classifiers":[
        {
            "category":"Recreation",
            "subcategory":"Sailing Club",
            "type":"Entertainment"
        }
    ],
    "sg:phone":"+33 2 97 55 80 77",
    "sg:postcode":"56470",
    "sg:province":"Bretagne",
    "sg:tags":[
        "sail"
    ],
    "wof:name":"Delta Voile Sarl",
    "wof:placetype":"venue"
},
  "geometry": {"coordinates":[-3.029609,47.589352],"type":"Point"}
}