{
  "type": "Feature",
  "properties": {
    "iso:country":"FR",
    "sg:address":"20 Rue De Paris",
    "sg:city":"Orsay",
    "sg:classifiers":[
        {
            "category":"Banks & Credit Unions",
            "subcategory":"Financial Services",
            "type":"Services"
        }
    ],
    "sg:phone":"+33 1 64 46 14 00",
    "sg:postcode":"91400",
    "sg:province":"Ile de France",
    "sg:tags":[
        "banking",
        "finance",
        "insurance"
    ],
    "wof:name":"Credit Du Nord",
    "wof:placetype":"venue"
},
  "geometry": {"coordinates":[2.187888,48.697578],"type":"Point"}
}