{
  "type": "Feature",
  "properties": {
    "addr:full":"2 Rue Pinsons 79200 Le Tallud Poitou-Charentes",
    "addr:housenumber":"2",
    "addr:postcode":"79200",
    "addr:street":"Rue Pinsons",
    "iso:country":"FR",
    "sg:address":"2 Rue Pinsons 79200 Le Tallud",
    "sg:classifiers":[
        {
            "category":"Manufacturing",
            "subcategory":"Chemicals & Compounds",
            "type":"Manufacturing & Wholesale Goods"
        }
    ],
    "sg:phone":"+33 5 49 64 04 55",
    "sg:province":"Poitou-Charentes",
    "sg:tags":[
        "pharmaceutical",
        "chemistry",
        "-",
        "by-product"
    ],
    "wof:name":"Worex Snc",
    "wof:placetype":"venue"
},
  "geometry": {"coordinates":[-0.288648,46.633389],"type":"Point"}
}