{
  "type": "Feature",
  "properties": {
    "iso:country":"FR",
    "sg:address":"13, Av. Jean Moulin - ZA du Pr\u00e9 Fus\u00e9, 77340 Pontault Combault",
    "sg:orig_category":"Unclassifiable Establishments",
    "sg:phone":"+33 1 64 43 60 50",
    "sg:province":"Ile de France",
    "wof:name":"M.d.m. Sa - Masse Diffusion Manutention",
    "wof:placetype":"venue"
},
  "geometry": {"coordinates":[2.60749,48.800526],"type":"Point"}
}