{
  "type": "Feature",
  "properties": {
    "iso:country":"FR",
    "sg:address":"20, Av. Fould, 65000 Tarbes",
    "sg:orig_category":"Unclassifiable Establishments",
    "sg:phone":"+33 5 62 93 20 06",
    "sg:province":"Midi Pyr\u00e9n\u00e9es",
    "wof:name":"Syndicat D\u00e9partemental Electricit\u00e9 Des Hautes Pyr\u00e9n\u00e9es",
    "wof:placetype":"venue"
},
  "geometry": {"coordinates":[0.071534,43.225368],"type":"Point"}
}