{
  "type": "Feature",
  "properties": {
    "addr:full":"10 Rue Saint-Marc 41200 Romorantin Lanthenay Villefranche-sur-Cher Centre 41200",
    "addr:housenumber":"10",
    "addr:postcode":"41200;41200",
    "addr:street":"Rue Saint-Marc",
    "iso:country":"FR",
    "sg:address":"10 Rue Saint-Marc 41200 Romorantin Lanthenay",
    "sg:city":"Villefranche-sur-Cher",
    "sg:classifiers":[
        {
            "category":"Professional",
            "subcategory":"Engineering",
            "type":"Services"
        }
    ],
    "sg:phone":"+33 2 54 76 00 51",
    "sg:postcode":"41200",
    "sg:province":"Centre",
    "sg:tags":[
        "machine",
        "-",
        "mechanical"
    ],
    "wof:name":"Dh Budemberg Sa",
    "wof:placetype":"venue"
},
  "geometry": {"coordinates":[1.737251,47.346718],"type":"Point"}
}