{
  "type": "Feature",
  "properties": {
    "addr:full":"Boulevard De La R\u00e9publique 62232 Annezin Nord Pas-de-Calais 62232",
    "addr:postcode":"62232;62232",
    "addr:street":"Boulevard De La Re\u0301Publique",
    "iso:country":"FR",
    "sg:address":"Boulevard De La R\u00e9publique 62232 Annezin",
    "sg:classifiers":[
        {
            "category":"Shopping",
            "type":"Retail Goods"
        }
    ],
    "sg:phone":"+33 3 21 57 10 54",
    "sg:postcode":"62232",
    "sg:province":"Nord Pas-de-Calais",
    "sg:tags":[
        "metallurgy",
        "finished",
        "-",
        "metalworking",
        "metallic"
    ],
    "wof:name":"N C I A Nouvelle Chaudronnerie Industrielle Annezinoise Sa",
    "wof:placetype":"venue"
},
  "geometry": {"coordinates":[2.600169,50.53038],"type":"Point"}
}