{
  "type": "Feature",
  "properties": {
    "addr:full":"Parc d'Activit\u00e9s Millau Ouest Saint Georges de Luzen\u00e7on Midi Pyr\u00e9n\u00e9es 12100",
    "addr:street":"\u0301S;Ouest Saint",
    "iso:country":"FR",
    "sg:address":"Parc d'Activit\u00e9s Millau Ouest",
    "sg:city":"Saint Georges de Luzen\u00e7on",
    "sg:orig_category":"Non-Classified Establishments",
    "sg:phone":"+33 5 65 58 41 41",
    "sg:postcode":"12100",
    "sg:province":"Midi Pyr\u00e9n\u00e9es",
    "wof:name":"Imprimerie Causses C\u00e9venne S.a.r.l.",
    "wof:placetype":"venue"
},
  "geometry": {"coordinates":[2.98414,44.063961],"type":"Point"}
}