{
  "type": "Feature",
  "properties": {
    "addr:full":"route du Moulin de Girardy 23170 CHAMBON SUR VOUEIZE Limousin 23170",
    "addr:postcode":"23170;23170",
    "addr:street":"Route Du Moulin De Girardy",
    "iso:country":"FR",
    "sg:address":"route du Moulin de Girardy 23170 CHAMBON SUR VOUEIZE",
    "sg:orig_category":"Material Pressure Vessels",
    "sg:phone":"+33 5 55 82 18 17",
    "sg:postcode":"23170",
    "sg:province":"Limousin",
    "wof:name":"Euro R\u00e9servoir S.a.",
    "wof:placetype":"venue"
},
  "geometry": {"coordinates":[2.346211,46.139374],"type":"Point"}
}