{
  "type": "Feature",
  "properties": {
    "addr:full":"1, Rue Abb\u00e9 Haustete, 88190 Golbey Lorraine",
    "addr:housenumber":"1",
    "addr:postcode":"88190",
    "addr:street":"Rue Abbe\u0301 Haustete",
    "iso:country":"FR",
    "sg:address":"1, Rue Abb\u00e9 Haustete, 88190 Golbey",
    "sg:orig_category":"Unclassifiable Establishments",
    "sg:phone":"+33 3 29 81 39 30",
    "sg:province":"Lorraine",
    "wof:name":"Interim 88 S.a.",
    "wof:placetype":"venue"
},
  "geometry": {"coordinates":[6.438338,48.197788],"type":"Point"}
}