{
  "type": "Feature",
  "properties": {
    "iso:country":"FR",
    "sg:address":"B.P. 50146, 57603 Forbach C\u00e9dex^^ZI Carrefour de l'Europe, 57600 Forbach",
    "sg:orig_category":"Non-Classified Establishments",
    "sg:phone":"+33 3 87 87 88 45",
    "sg:province":"Lorraine",
    "wof:name":"Optimol France S.a.r.l.",
    "wof:placetype":"venue"
},
  "geometry": {"coordinates":[6.89571,49.171749],"type":"Point"}
}