{
  "type": "Feature",
  "properties": {
    "addr:full":"Zi La Giraudi\u00e8re 35530 Noyal Sur Vilaine Br\u00e9c\u00e9 Bretagne 35530",
    "addr:postcode":"35530;bre\u0301ce\u0301;35530",
    "addr:street":"Zi La Giraudie\u0300Re",
    "iso:country":"FR",
    "sg:address":"Zi La Giraudi\u00e8re 35530 Noyal Sur Vilaine",
    "sg:city":"Br\u00e9c\u00e9",
    "sg:classifiers":[
        {
            "category":"Autos & Motor Vehicles",
            "subcategory":"Automobile Sales",
            "type":"Retail Goods"
        }
    ],
    "sg:phone":"+33 2 99 00 69 69",
    "sg:postcode":"35530",
    "sg:province":"Bretagne",
    "sg:tags":[
        "equipment",
        "industrial",
        "transport"
    ],
    "wof:name":"Ste Noyal Poids Lourds",
    "wof:placetype":"venue"
},
  "geometry": {"coordinates":[-1.521279,48.110287],"type":"Point"}
}