{
  "type": "Feature",
  "properties": {
    "addr:full":"12 bis, Rte du Perrolier - ZI le Tronchon, 69570 Dardilly Rhone-Alpes",
    "addr:housenumber":"12 bis",
    "addr:postcode":"69570",
    "addr:street":"Rte Du Perrolier Zi Le Tronchon",
    "iso:country":"FR",
    "sg:address":"12 bis, Rte du Perrolier - ZI le Tronchon, 69570 Dardilly",
    "sg:orig_category":"Unclassifiable Establishments",
    "sg:phone":"+33 4 78 35 60 70",
    "sg:province":"Rhone-Alpes",
    "wof:name":"Blanc Textiles S.a.r.l.",
    "wof:placetype":"venue"
},
  "geometry": {"coordinates":[4.753535,45.805908],"type":"Point"}
}