{
  "type": "Feature",
  "properties": {
    "iso:country":"FR",
    "sg:address":"53, Rue de Verdun, 62190 Lillers",
    "sg:orig_category":"Unclassifiable Establishments",
    "sg:phone":"+33 3 21 54 47 11",
    "sg:province":"Nord Pas-de-Calais",
    "wof:name":"A.n.p.e.",
    "wof:placetype":"venue"
},
  "geometry": {"coordinates":[2.48482,50.560577],"type":"Point"}
}