{
  "type": "Feature",
  "properties": {
    "addr:full":"B.P. 14, 59880 Saint Saulve^^53, Rue Henri Dure, 59880 Saint Saulve Nord Pas-de-Calais",
    "addr:postcode":"59880;59880;saulve",
    "addr:street":"B.P. 14;Rue Henri Dure;Pas-De-Calais",
    "iso:country":"FR",
    "sg:address":"B.P. 14, 59880 Saint Saulve^^53, Rue Henri Dure, 59880 Saint Saulve",
    "sg:orig_category":"Non-Classified Establishments",
    "sg:phone":"+33 3 27 30 15 62",
    "sg:province":"Nord Pas-de-Calais",
    "wof:name":"S.a.p. S.a. - Sant\u00e9 Assistance Promotion",
    "wof:placetype":"venue"
},
  "geometry": {"coordinates":[3.552555,50.369625],"type":"Point"}
}