{
  "type": "Feature",
  "properties": {
    "iso:country":"FR",
    "sg:address":"rd-pt Pierre Plant\u00e9e; Vitrolles",
    "sg:classifiers":[
        {
            "category":"Banks & Credit Unions",
            "subcategory":"Bank",
            "type":"Services"
        }
    ],
    "sg:phone":"+33 3342105720",
    "sg:province":"Languedoc-Roussillon",
    "wof:name":"Banque Nationale De Paris",
    "wof:placetype":"venue"
},
  "geometry": {"coordinates":[5.253827,43.448547],"type":"Point"}
}