{
  "type": "Feature",
  "properties": {
    "iso:country":"FR",
    "sg:address":"Av. Pierre Brossolette - ZA des Aur\u00e9ats",
    "sg:city":"Portes les Valence",
    "sg:orig_category":"Unclassifiable Establishments",
    "sg:phone":"+33 4 75 57 34 98",
    "sg:postcode":"26800",
    "sg:province":"Rhone-Alpes",
    "wof:name":"Emp System S.a.r.l.",
    "wof:placetype":"venue"
},
  "geometry": {"coordinates":[4.886351,44.879658],"type":"Point"}
}