{
  "type": "Feature",
  "properties": {
    "iso:country":"FR",
    "sg:address":"Quartier Pradines Rn7 84100 Orange",
    "sg:orig_category":"Miscellaneous Products",
    "sg:phone":"+33 4 90 11 87 00",
    "sg:province":"Centre",
    "wof:name":"Monitor Roulor Sa",
    "wof:placetype":"venue"
},
  "geometry": {"coordinates":[4.80867,44.136169],"type":"Point"}
}