{
  "type": "Feature",
  "properties": {
    "addr:full":"3, All\u00e9e des Bauches - ZA des Bauches, 38640 Claix Rhone-Alpes 38640",
    "addr:housenumber":"3",
    "addr:postcode":"38640;38640",
    "addr:street":"Alle\u0301E Des Bauches Za Des Bauches",
    "iso:country":"FR",
    "sg:address":"3, All\u00e9e des Bauches - ZA des Bauches, 38640 Claix",
    "sg:orig_category":"Non-Classified Establishments",
    "sg:phone":"+33 4 76 99 27 10",
    "sg:postcode":"38640",
    "sg:province":"Rhone-Alpes",
    "wof:name":"C.i.a.t. S.a. - Compagnie Industrielle D'applications Thermiques",
    "wof:placetype":"venue"
},
  "geometry": {"coordinates":[5.672615,45.120255],"type":"Point"}
}