{
  "type": "Feature",
  "properties": {
    "addr:full":"3 Rouge Le Grand 51100 Reims Champagne 51100",
    "addr:housenumber":"3",
    "addr:postcode":"51100;51100",
    "addr:street":"Rouge",
    "iso:country":"FR",
    "sg:address":"3 Rouge Le Grand 51100 Reims",
    "sg:classifiers":[
        {
            "category":"Social Services",
            "subcategory":"Job Training",
            "type":"Services"
        }
    ],
    "sg:phone":"+33 3 26 07 69 77",
    "sg:postcode":"51100",
    "sg:province":"Champagne",
    "sg:tags":[
        "good",
        "business",
        "advice",
        "-",
        "metalworking",
        "metallic",
        "metallurgy",
        "finished"
    ],
    "wof:name":"Gr Mecatech Grm Fermetures",
    "wof:placetype":"venue"
},
  "geometry": {"coordinates":[4.059882,49.247978],"type":"Point"}
}