{
  "type": "Feature",
  "properties": {
    "iso:country":"FR",
    "sg:address":"32 avenue Emile Zola",
    "sg:city":"Mons En Baroeul",
    "sg:classifiers":[
        {
            "category":"Banks & Credit Unions",
            "subcategory":"Financial Services",
            "type":"Services"
        }
    ],
    "sg:phone":"+33 3 20 67 37 37",
    "sg:postcode":"59370",
    "sg:province":"Nord Pas-de-Calais",
    "sg:tags":[
        "banking",
        "finance",
        "insurance"
    ],
    "wof:name":"La Mondiale Sa",
    "wof:placetype":"venue"
},
  "geometry": {"coordinates":[3.09427,50.642174],"type":"Point"}
}