{
  "type": "Feature",
  "properties": {
    "addr:full":"152, Rue de Picpus, 75012 Paris Ile de France 75012",
    "addr:housenumber":"152",
    "addr:postcode":"75012;75012",
    "addr:street":"Rue De Picpus",
    "iso:country":"FR",
    "sg:address":"152, Rue de Picpus, 75012 Paris",
    "sg:orig_category":"Non-Classified Establishments",
    "sg:phone":"+33 1 49 28 00 40",
    "sg:postcode":"75012",
    "sg:province":"Ile de France",
    "wof:name":"A.a.p. S.a. - Administration D'affiche Et De Publicit\u00e9",
    "wof:placetype":"venue"
},
  "geometry": {"coordinates":[2.403512,48.835114],"type":"Point"}
}