{
  "type": "Feature",
  "properties": {
    "iso:country":"FR",
    "sg:address":"92, Rue Boileau, 75016 Paris",
    "sg:orig_category":"Unclassifiable Establishments",
    "sg:phone":"+33 1 42 15 00 79",
    "sg:province":"Ile de France",
    "wof:name":"Push Tac S.a.r.l.",
    "wof:placetype":"venue"
},
  "geometry": {"coordinates":[2.261764,48.840237],"type":"Point"}
}