{
  "type": "Feature",
  "properties": {
    "iso:country":"FR",
    "sg:address":"Le Petit Tot 76190 Hautot Saint Sulpice",
    "sg:orig_category":"Non-Classified Establishments",
    "sg:phone":"+33 2 35 56 52 78",
    "sg:province":"Haute Normandie",
    "wof:name":"Yves Louis Parcs Et Jardins S.a.r.l.",
    "wof:placetype":"venue"
},
  "geometry": {"coordinates":[0.686241,49.602016],"type":"Point"}
}