{
  "type": "Feature",
  "properties": {
    "addr:full":"B.P. 8, 33886 Villenave d'Ornon C\u00e9dex^^Prairie de Courr\u00e8jean, 33140 Villenave d'Ornon Cadaujac Aquitaine 33140",
    "addr:housenumber":"8",
    "addr:postcode":"33886;33140;33140",
    "addr:street":"B.P.",
    "iso:country":"FR",
    "sg:address":"B.P. 8, 33886 Villenave d'Ornon C\u00e9dex^^Prairie de Courr\u00e8jean, 33140 Villenave d'Ornon",
    "sg:city":"Cadaujac",
    "sg:orig_category":"Non-Classified Establishments",
    "sg:phone":"+33 5 56 87 78 87",
    "sg:postcode":"33140",
    "sg:province":"Aquitaine",
    "wof:name":"A.f.m. Recyclage S.a.",
    "wof:placetype":"venue"
},
  "geometry": {"coordinates":[-0.568254,44.759846],"type":"Point"}
}