{
  "type": "Feature",
  "properties": {
    "addr:full":"31 Bd Anatole France 93200 St Denis Ile de France",
    "addr:housenumber":"31",
    "addr:postcode":"93200",
    "addr:street":"Bd Anatole France",
    "iso:country":"FR",
    "sg:address":"31 Bd Anatole France 93200 St Denis",
    "sg:classifiers":[
        {
            "category":"Manufacturing",
            "subcategory":"Printing",
            "type":"Manufacturing & Wholesale Goods"
        }
    ],
    "sg:phone":"+33 1 48 20 97 97",
    "sg:province":"Ile de France",
    "sg:tags":[
        "publishing"
    ],
    "wof:name":"Imprimerie Du Sceau",
    "wof:placetype":"venue"
},
  "geometry": {"coordinates":[2.352259,48.927074],"type":"Point"}
}