{
  "type": "Feature",
  "properties": {
    "addr:full":"72, Av. du Vercors, 38170 Seyssinet Pariset Rhone-Alpes 38170",
    "addr:postcode":"38170;38170",
    "addr:street":"72 Av. Du Vercors;Rhone-Alpes",
    "iso:country":"FR",
    "sg:address":"72, Av. du Vercors, 38170 Seyssinet Pariset",
    "sg:orig_category":"Unclassifiable Establishments",
    "sg:phone":"+33 4 76 96 63 90",
    "sg:postcode":"38170",
    "sg:province":"Rhone-Alpes",
    "wof:name":"Profil Et Pli S.a.r.l.",
    "wof:placetype":"venue"
},
  "geometry": {"coordinates":[5.68617,45.178551],"type":"Point"}
}