{
  "type": "Feature",
  "properties": {
    "addr:full":"2426 Route National 7 06272 VILLENEUVE LOUBET CEDEX Vill\u00e9 Alsace 67220",
    "addr:housenumber":"2426;7",
    "addr:postcode":"06272;loubet cedex ville\u0301;67220",
    "addr:street":"Route National",
    "iso:country":"FR",
    "sg:address":"2426 Route National 7 06272 VILLENEUVE LOUBET CEDEX",
    "sg:city":"Vill\u00e9",
    "sg:classifiers":[
        {
            "category":"Home & Garden",
            "subcategory":"Home Furnishings",
            "type":"Retail Goods"
        }
    ],
    "sg:phone":"+33 4 93 73 57 12",
    "sg:postcode":"67220",
    "sg:province":"Alsace",
    "sg:tags":[
        "interior",
        "decoration"
    ],
    "wof:name":"Enesco France Sa",
    "wof:placetype":"venue"
},
  "geometry": {"coordinates":[7.12296,43.657749],"type":"Point"}
}