{
  "type": "Feature",
  "properties": {
    "addr:full":"26, Andr\u00e9 Amp\u00e8re, 95310 Saint Ouen l' Aum\u00f4ne Ile de France",
    "addr:housenumber":"26",
    "addr:postcode":"95310",
    "addr:street":"Andre\u0301 Ampe\u0300Re;Ouen L ' Aumo\u0302Ne Ile De France",
    "iso:country":"FR",
    "sg:address":"26, Andr\u00e9 Amp\u00e8re, 95310 Saint Ouen l' Aum\u00f4ne",
    "sg:orig_category":"Unclassifiable Establishments",
    "sg:phone":"+33 1 34 64 46 29",
    "sg:province":"Ile de France",
    "wof:name":"Lumox S.a.r.l.",
    "wof:placetype":"venue"
},
  "geometry": {"coordinates":[-0.104016,48.298943],"type":"Point"}
}