{
  "type": "Feature",
  "properties": {
    "addr:full":"B.P. 84, 42125 Le Coteau C\u00e9dex^^55, Bd Charles de Gaulle - ZI, 42120 Le Coteau Rhone-Alpes 42120",
    "addr:postcode":"42125;zi 42120;42120",
    "addr:street":"B.P. 84;Ce\u0301Dex^^55 Bd Charles De Gaulle;Rhone-Alpes",
    "iso:country":"FR",
    "sg:address":"B.P. 84, 42125 Le Coteau C\u00e9dex^^55, Bd Charles de Gaulle - ZI, 42120 Le Coteau",
    "sg:orig_category":"Non-Classified Establishments",
    "sg:phone":"+33 4 77 23 66 66",
    "sg:postcode":"42120",
    "sg:province":"Rhone-Alpes",
    "wof:name":"Passot Innovation S.a.",
    "wof:placetype":"venue"
},
  "geometry": {"coordinates":[4.09834,45.991081],"type":"Point"}
}