{
  "type": "Feature",
  "properties": {
    "addr:full":"2 Rue Des Bains 73100 Aix Les Bains Rhone-Alpes 73100",
    "addr:housenumber":"2",
    "addr:postcode":"73100;73100",
    "addr:street":"Rue Des Bains",
    "iso:country":"FR",
    "sg:address":"2 Rue Des Bains 73100 Aix Les Bains",
    "sg:classifiers":[
        {
            "category":"Wholesale",
            "subcategory":"Medical Equipment & Supplies",
            "type":"Manufacturing & Wholesale Goods"
        }
    ],
    "sg:phone":"+33 4 79 35 16 29",
    "sg:postcode":"73100",
    "sg:province":"Rhone-Alpes",
    "sg:tags":[
        "instrument",
        "health",
        "-",
        "precision"
    ],
    "wof:name":"Beaupellet Orthopedie Sarl",
    "wof:placetype":"venue"
},
  "geometry": {"coordinates":[5.914947,45.689522],"type":"Point"}
}