{
  "type": "Feature",
  "properties": {
    "addr:full":"B.P. 5201, 78175^^32, Av. Carnot, 78100 Saint Germain en Laye Ile de France 78100",
    "addr:housenumber":"^ 32",
    "addr:postcode":"78175;78100;78100",
    "addr:street":"B.P. 5201;Av. Carnot",
    "iso:country":"FR",
    "sg:address":"B.P. 5201, 78175^^32, Av. Carnot, 78100 Saint Germain en Laye",
    "sg:orig_category":"Non-Classified Establishments",
    "sg:phone":"+33 1 39 10 51 00",
    "sg:postcode":"78100",
    "sg:province":"Ile de France",
    "wof:name":"Cogep S.a. - Compagnie G\u00e9n\u00e9rale Edition Publication",
    "wof:placetype":"venue"
},
  "geometry": {"coordinates":[2.091955,48.898411],"type":"Point"}
}