{
  "type": "Feature",
  "properties": {
    "iso:country":"FR",
    "sg:address":"Regourd Chem De La Sabli\u00e8re 46000 Cahors",
    "sg:classifiers":[
        {
            "category":"Manufacturing",
            "subcategory":"Rubber & Plastics",
            "type":"Manufacturing & Wholesale Goods"
        }
    ],
    "sg:phone":"+33 5 65 35 27 94",
    "sg:province":"Midi Pyr\u00e9n\u00e9es",
    "wof:name":"Frans Bonhomme",
    "wof:placetype":"venue"
},
  "geometry": {"coordinates":[1.440775,44.44659],"type":"Point"}
}