{
  "type": "Feature",
  "properties": {
    "iso:country":"FR",
    "sg:address":"2 Rue Du Gal De Gaulle 57140 Woippy",
    "sg:classifiers":[
        {
            "category":"Bakery",
            "type":"Food & Drink"
        }
    ],
    "sg:phone":"+33 3 87 31 34 68",
    "sg:postcode":"57140",
    "sg:province":"Lorraine",
    "sg:tags":[
        "cake",
        "product",
        "related",
        "bread"
    ],
    "wof:name":"Gerbe D'or Sa",
    "wof:placetype":"venue"
},
  "geometry": {"coordinates":[6.148585,49.151627],"type":"Point"}
}