{
  "type": "Feature",
  "properties": {
    "iso:country":"FR",
    "sg:address":"ZI de la Blanche T\u00e2che",
    "sg:city":"Camon",
    "sg:orig_category":"Unclassifiable Establishments",
    "sg:phone":"+33 3 22 70 72 72",
    "sg:postcode":"80450",
    "sg:province":"Picardie",
    "wof:name":"Innovam S.a",
    "wof:placetype":"venue"
},
  "geometry": {"coordinates":[2.34342,49.887493],"type":"Point"}
}