{
  "type": "Feature",
  "properties": {
    "iso:country":"FR",
    "sg:address":"ZI Louis Delaporte Zone Verte 76370 ROUXMESNIL BOUTEILLES",
    "sg:classifiers":[
        {
            "category":"Food & Beverages",
            "subcategory":"Groceries & Convenience Stores",
            "type":"Retail Goods"
        }
    ],
    "sg:phone":"+33 2 35 04 76 00",
    "sg:province":"Haute Normandie",
    "sg:tags":[
        "product",
        "industry",
        "system"
    ],
    "wof:name":"Davigel Sa",
    "wof:placetype":"venue"
},
  "geometry": {"coordinates":[1.093,49.904709],"type":"Point"}
}