{
  "type": "Feature",
  "properties": {
    "addr:full":"171 B Rue Championnet 75018 Paris Ile de France 75018",
    "addr:housenumber":"171 b",
    "addr:postcode":"75018;75018",
    "addr:street":"Rue Championnet",
    "iso:country":"FR",
    "sg:address":"171 B Rue Championnet 75018 Paris",
    "sg:classifiers":[
        {
            "category":"Wholesale",
            "subcategory":"Medical Equipment & Supplies",
            "type":"Manufacturing & Wholesale Goods"
        }
    ],
    "sg:phone":"+33 1 42 62 62 51",
    "sg:postcode":"75018",
    "sg:province":"Ile de France",
    "sg:tags":[
        "instrument",
        "health",
        "-",
        "precision"
    ],
    "wof:name":"Laboratoire Prothese Dentaire Dilca",
    "wof:placetype":"venue"
},
  "geometry": {"coordinates":[2.335222,48.894646],"type":"Point"}
}