{
  "type": "Feature",
  "properties": {
    "iso:country":"FR",
    "sg:address":"Rue Rosa Luxembourg - Le Wisconsin Eragny Parc",
    "sg:city":"Eragny",
    "sg:orig_category":"Unclassifiable Establishments",
    "sg:phone":"+33 1 34 30 22 33",
    "sg:postcode":"95610",
    "sg:province":"Ile de France",
    "wof:name":"Kieback Et Peter S.a.",
    "wof:placetype":"venue"
},
  "geometry": {"coordinates":[2.091,49.019009],"type":"Point"}
}