{
  "type": "Feature",
  "properties": {
    "addr:full":"157, Rue du Temple, 75003 Paris Ile de France",
    "addr:housenumber":"157",
    "addr:postcode":"75003",
    "addr:street":"Rue Du Temple",
    "iso:country":"FR",
    "sg:address":"157, Rue du Temple, 75003 Paris",
    "sg:orig_category":"Unclassifiable Establishments",
    "sg:phone":"+33 1 42 72 16 20",
    "sg:province":"Ile de France",
    "wof:name":"Souche Lappara Orf\u00e8vre Argentier S.a.",
    "wof:placetype":"venue"
},
  "geometry": {"coordinates":[2.359145,48.864487],"type":"Point"}
}