{
  "type": "Feature",
  "properties": {
    "addr:full":"115-117 avenue Raspail 94250 Gentilly Ile de France 94250",
    "addr:housenumber":"115-117",
    "addr:postcode":"94250;ile;94250",
    "addr:street":"Avenue Raspail;France",
    "iso:country":"FR",
    "sg:address":"115-117 avenue Raspail 94250 Gentilly",
    "sg:classifiers":[
        {
            "category":"Communications",
            "subcategory":"Film & Video Production",
            "type":"Services"
        }
    ],
    "sg:phone":"+33 1 49 08 59 69",
    "sg:postcode":"94250",
    "sg:province":"Ile de France",
    "sg:tags":[
        "workshop",
        "graphic"
    ],
    "wof:name":"Dba S.a.",
    "wof:placetype":"venue"
},
  "geometry": {"coordinates":[2.343661,48.809837],"type":"Point"}
}