{
  "type": "Feature",
  "properties": {
    "iso:country":"FR",
    "sg:address":"45, Rte de Saint Martin, 89120 Charny",
    "sg:city":"Charny",
    "sg:orig_category":"Unclassifiable Establishments",
    "sg:phone":"+33 3 86 63 62 37",
    "sg:postcode":"89120",
    "sg:province":"Bourgogne",
    "wof:name":"Ets A. Branger",
    "wof:placetype":"venue"
},
  "geometry": {"coordinates":[3.09604,47.883469],"type":"Point"}
}