{
  "type": "Feature",
  "properties": {
    "addr:full":"23, Rue de Brotterode, 38950 Saint Martin le Vinoux Rhone-Alpes 38950",
    "addr:housenumber":"23",
    "addr:postcode":"38950;38950",
    "addr:street":"Rue De Brotterode;Martin Le;Rhone-Alpes",
    "iso:country":"FR",
    "sg:address":"23, Rue de Brotterode, 38950 Saint Martin le Vinoux",
    "sg:orig_category":"Unclassifiable Establishments",
    "sg:phone":"+33 4 76 75 97 00",
    "sg:postcode":"38950",
    "sg:province":"Rhone-Alpes",
    "wof:name":"N.t.s. S.a.",
    "wof:placetype":"venue"
},
  "geometry": {"coordinates":[5.686815,45.214481],"type":"Point"}
}