{
  "type": "Feature",
  "properties": {
    "addr:full":"372 rue Saint-Honor\u00e9, 75001 Paris, Dept 75 Ile de France 75001",
    "addr:housenumber":"372;75",
    "addr:postcode":"75001;75001",
    "addr:street":"Rue Saint-Honore\u0301;Ile De France",
    "iso:country":"FR",
    "sg:address":"372 rue Saint-Honor\u00e9, 75001 Paris, Dept 75",
    "sg:classifiers":[
        {
            "category":"Banks & Credit Unions",
            "subcategory":"Bank",
            "type":"Services"
        }
    ],
    "sg:phone":"+33 1 55 35 84 00",
    "sg:postcode":"75001",
    "sg:province":"Ile de France",
    "wof:name":"Axa Banque",
    "wof:placetype":"venue"
},
  "geometry": {"coordinates":[2.327013,48.867336],"type":"Point"}
}