{
  "type": "Feature",
  "properties": {
    "iso:country":"FR",
    "sg:address":"Av Louis Joseph Gay Lussac 64140 Lons",
    "sg:city":"Lons",
    "sg:classifiers":[
        {
            "category":"Professional",
            "type":"Services"
        }
    ],
    "sg:phone":"+33 5 59 92 05 05",
    "sg:postcode":"64140",
    "sg:province":"Aquitaine",
    "sg:tags":[
        "transport",
        "road"
    ],
    "wof:name":"Transports Atp Brunet",
    "wof:placetype":"venue"
},
  "geometry": {"coordinates":[-0.418874,43.308918],"type":"Point"}
}