{
  "type": "Feature",
  "properties": {
    "addr:full":"7, Rue des 15 Arpents, 94577 Orly C\u00e9dex \u00cele-de-France",
    "addr:housenumber":"7",
    "addr:postcode":"94577",
    "addr:street":"Rue Des 15 Arpents;Ce\u0301Dex",
    "iso:country":"FR",
    "sg:address":"7, Rue des 15 Arpents, 94577 Orly C\u00e9dex",
    "sg:orig_category":"Non-Classified Establishments",
    "sg:phone":"+33 1 41 73 02 02",
    "sg:province":"\u00cele-de-France",
    "wof:name":"Eurotri S.a.",
    "wof:placetype":"venue"
},
  "geometry": {"coordinates":[2.40116,48.742931],"type":"Point"}
}