{
  "type": "Feature",
  "properties": {
    "addr:full":"15, Rue Danielle Casanova, 75001 Paris Ile de France",
    "addr:housenumber":"15",
    "addr:postcode":"75001",
    "addr:street":"Rue Danielle Casanova",
    "iso:country":"FR",
    "sg:address":"15, Rue Danielle Casanova, 75001 Paris",
    "sg:orig_category":"Unclassifiable Establishments",
    "sg:phone":"+33 1 47 03 62 80",
    "sg:province":"Ile de France",
    "wof:name":"Arjobex S.n.c.",
    "wof:placetype":"venue"
},
  "geometry": {"coordinates":[2.332432,48.867672],"type":"Point"}
}