{
  "type": "Feature",
  "properties": {
    "addr:full":"10 Av Paul Langevin 17180 P\u00e9rigny Poitou-Charentes 17180",
    "addr:postcode":"17180;17180",
    "addr:street":"10 Av Paul Langevin",
    "iso:country":"FR",
    "sg:address":"10 Av Paul Langevin 17180 P\u00e9rigny",
    "sg:classifiers":[
        {
            "category":"Wholesale",
            "subcategory":"Machinery & Supplies",
            "type":"Manufacturing & Wholesale Goods"
        }
    ],
    "sg:phone":"+33 5 46 44 85 50",
    "sg:postcode":"17180",
    "sg:province":"Poitou-Charentes",
    "sg:tags":[
        "equipment",
        "-",
        "precision",
        "glass",
        "optical",
        "health",
        "instrument"
    ],
    "wof:name":"Ioltech Sa",
    "wof:placetype":"venue"
},
  "geometry": {"coordinates":[-1.096899,46.161495],"type":"Point"}
}