{
  "type": "Feature",
  "properties": {
    "addr:full":"B.P. 97, 37397 Tours^^Rue Cassin - ZA l'Arche d'O\u00e9, 37390 Notre Dame d'O\u00e9 La Membrolle-sur-Choisille Centre 37390",
    "addr:housenumber":"membrolle-sur-choisille",
    "addr:postcode":"37397;37390;37390",
    "addr:street":"B.P. 97;\u0301",
    "iso:country":"FR",
    "sg:address":"B.P. 97, 37397 Tours^^Rue Cassin - ZA l'Arche d'O\u00e9, 37390 Notre Dame d'O\u00e9",
    "sg:city":"La Membrolle-sur-Choisille",
    "sg:orig_category":"Non-Classified Establishments",
    "sg:phone":"+33 2 47 51 19 00",
    "sg:postcode":"37390",
    "sg:province":"Centre",
    "wof:name":"Mag Process-dinagros S.a.",
    "wof:placetype":"venue"
},
  "geometry": {"coordinates":[-85.514313,35.173859],"type":"Point"}
}