{
  "type": "Feature",
  "properties": {
    "addr:full":"19 Avenue De L'Europe Zi 12100 Millau Midi Pyr\u00e9n\u00e9es 12100",
    "addr:housenumber":"19",
    "addr:postcode":"12100;12100",
    "addr:street":"Avenue De L'Europe Zi",
    "iso:country":"FR",
    "sg:address":"19 Avenue De L'Europe Zi 12100 Millau",
    "sg:classifiers":[
        {
            "category":"Government",
            "subcategory":"Fire Station",
            "type":"Public Place"
        }
    ],
    "sg:phone":"+33 5 65 61 90 30",
    "sg:postcode":"12100",
    "sg:province":"Midi Pyr\u00e9n\u00e9es",
    "sg:tags":[
        "electric",
        "electricity",
        "component",
        "equipment",
        "lighting",
        "electrical",
        "electronic"
    ],
    "wof:name":"Comptoir Electrique Du Midi",
    "wof:placetype":"venue"
},
  "geometry": {"coordinates":[3.12026,44.098042],"type":"Point"}
}