{
  "type": "Feature",
  "properties": {
    "iso:country":"FR",
    "sg:address":"Zi Des Clairances 86320 Lussac Les Ch\u00e2teaux",
    "sg:classifiers":[
        {
            "category":"Manufacturing",
            "subcategory":"Paper Products",
            "type":"Manufacturing & Wholesale Goods"
        }
    ],
    "sg:phone":"+33 5 49 84 58 58",
    "sg:postcode":"86320",
    "sg:province":"Poitou-Charentes",
    "sg:tags":[
        "raw",
        "material",
        "-",
        "cardboard"
    ],
    "wof:name":"Parisloire",
    "wof:placetype":"venue"
},
  "geometry": {"coordinates":[0.724003,46.40292],"type":"Point"}
}