{
  "type": "Feature",
  "properties": {
    "addr:full":"3 pl du G\u00e9n\u00e9ral de Gaulle; Aubenas Basse Normandie",
    "addr:housenumber":"3",
    "addr:street":"Pl Du Ge\u0301Ne\u0301Ral De Gaulle;Basse Normandie",
    "iso:country":"FR",
    "sg:address":"3 pl du G\u00e9n\u00e9ral de Gaulle; Aubenas",
    "sg:classifiers":[
        {
            "category":"Banks & Credit Unions",
            "subcategory":"Bank",
            "type":"Services"
        }
    ],
    "sg:phone":"+33 3375356022",
    "sg:province":"Basse Normandie",
    "wof:name":"Soci\u00e9t\u00e9 G\u00e9n\u00e9rale",
    "wof:placetype":"venue"
},
  "geometry": {"coordinates":[4.388429,44.619522],"type":"Point"}
}