{
  "type": "Feature",
  "properties": {
    "addr:full":"12/14, Rond-point des Champs Elys\u00e9es, 75008 Paris Ile de France",
    "addr:housenumber":"12 / 14",
    "addr:postcode":"75008",
    "addr:street":"Rond-Point Des Champs Elyse\u0301Es",
    "iso:country":"FR",
    "sg:address":"12/14, Rond-point des Champs Elys\u00e9es, 75008 Paris",
    "sg:orig_category":"Unclassifiable Establishments",
    "sg:phone":"+33 1 44 35 72 00",
    "sg:province":"Ile de France",
    "wof:name":"Orlane S.a.",
    "wof:placetype":"venue"
},
  "geometry": {"coordinates":[2.309389,48.869617],"type":"Point"}
}