{
  "type": "Feature",
  "properties": {
    "iso:country":"FR",
    "sg:address":"76 Rue Georges Clemenceau 77220 Tournan En Brie",
    "sg:classifiers":[
        {
            "category":"Professional",
            "subcategory":"Business Services",
            "type":"Services"
        }
    ],
    "sg:phone":"+33 1 64 07 20 18",
    "sg:postcode":"77220",
    "sg:province":"Ile de France",
    "sg:tags":[
        "training",
        "advice"
    ],
    "wof:name":"Lycee Denseignement Professionnel Cl\u00c9ment Ader",
    "wof:placetype":"venue"
},
  "geometry": {"coordinates":[2.75115,48.742271],"type":"Point"}
}