{
  "type": "Feature",
  "properties": {
    "addr:full":"Les Gauries 33220 Caplong Caplong Aquitaine 33220",
    "addr:postcode":"33220;33220",
    "iso:country":"FR",
    "sg:address":"Les Gauries 33220 Caplong",
    "sg:city":"Caplong",
    "sg:classifiers":[
        {
            "category":"Farming",
            "subcategory":"Farm & Veterinary Services",
            "type":"Manufacturing & Wholesale Goods"
        }
    ],
    "sg:phone":"+33 5 56 61 36 61",
    "sg:postcode":"33220",
    "sg:province":"Aquitaine",
    "sg:tags":[
        "advice",
        "agriculture",
        "livestock",
        "business"
    ],
    "wof:name":"Patrick Barriere Eurl",
    "wof:placetype":"venue"
},
  "geometry": {"coordinates":[0.162391,44.755672],"type":"Point"}
}