{
  "type": "Feature",
  "properties": {
    "addr:full":"16720 St Meme Les Carrieres Poitou-Charentes 16720",
    "addr:housenumber":"16720",
    "addr:postcode":"16720",
    "addr:street":"St Meme Les Carrieres",
    "iso:country":"FR",
    "sg:address":"16720 St Meme Les Carrieres",
    "sg:classifiers":[
        {
            "category":"Food Court",
            "type":"Food & Drink"
        }
    ],
    "sg:phone":"+33 5 45 81 90 35",
    "sg:postcode":"16720",
    "sg:province":"Poitou-Charentes",
    "sg:tags":[
        "product",
        "related"
    ],
    "wof:name":"Sa Distillerie De La Cure",
    "wof:placetype":"venue"
},
  "geometry": {"coordinates":[-0.143219,45.644394],"type":"Point"}
}