{
  "type": "Feature",
  "properties": {
    "addr:full":"105, Bd Haussmann, 75008 Paris Ile de France",
    "addr:housenumber":"105",
    "addr:postcode":"75008",
    "addr:street":"Bd Haussmann",
    "iso:country":"FR",
    "sg:address":"105, Bd Haussmann, 75008 Paris",
    "sg:orig_category":"Unclassifiable Establishments",
    "sg:phone":"+33 1 47 42 53 00",
    "sg:province":"Ile de France",
    "wof:name":"C. Et I. S.a. - Communication Et Institution",
    "wof:placetype":"venue"
},
  "geometry": {"coordinates":[2.317016,48.874996],"type":"Point"}
}