{
  "type": "Feature",
  "properties": {
    "iso:country":"FR",
    "sg:address":"77 Bis Rue Gravelines 59630 Bourbourg",
    "sg:classifiers":[
        {
            "category":"Food & Beverages",
            "subcategory":"Ethnic Foods",
            "type":"Retail Goods"
        }
    ],
    "sg:phone":"+33 3 28 22 30 22",
    "sg:postcode":"59630",
    "sg:province":"Nord Pas-de-Calais",
    "sg:tags":[
        "pharmaceutical",
        "product",
        "related",
        "pharmacy",
        "chemical",
        "animal",
        "breeding"
    ],
    "wof:name":"Duriez Et Fils Sa",
    "wof:placetype":"venue"
},
  "geometry": {"coordinates":[2.192442,50.949684],"type":"Point"}
}