{
  "type": "Feature",
  "properties": {
    "addr:full":"Imp Pont Des Sommiers 84300 Cavaillon Provence-Alpes-C\u00f4te d'Azur",
    "addr:postcode":"84300",
    "addr:street":"Imp Pont Des Sommiers",
    "iso:country":"FR",
    "sg:address":"Imp Pont Des Sommiers 84300 Cavaillon",
    "sg:classifiers":[
        {
            "category":"Manufacturing",
            "subcategory":"Rubber & Plastics",
            "type":"Manufacturing & Wholesale Goods"
        }
    ],
    "sg:phone":"+33 4 90 71 21 94",
    "sg:province":"Provence-Alpes-C\u00f4te d'Azur",
    "sg:tags":[
        "packaging",
        "material",
        "-"
    ],
    "wof:name":"Sormaf Sarl",
    "wof:placetype":"venue"
},
  "geometry": {"coordinates":[5.041765,43.819195],"type":"Point"}
}