{
  "type": "Feature",
  "properties": {
    "iso:country":"FR",
    "sg:address":"ZAC du Moulin Mayeux",
    "sg:city":"Bohain en Vermandois",
    "sg:orig_category":"Non-Classified Establishments",
    "sg:phone":"+33 3 23 07 12 35",
    "sg:postcode":"02110",
    "sg:province":"Picardie",
    "wof:name":"Dutoit Biscuits S.a.r.l.",
    "wof:placetype":"venue"
},
  "geometry": {"coordinates":[3.458471,49.985512],"type":"Point"}
}