{
  "type": "Feature",
  "properties": {
    "addr:full":"74420 Habere Lullin Rhone-Alpes 74420",
    "addr:postcode":"74420;74420",
    "iso:country":"FR",
    "sg:address":"74420 Habere Lullin",
    "sg:classifiers":[
        {
            "category":"Home & Garden",
            "subcategory":"Furniture",
            "type":"Retail Goods"
        }
    ],
    "sg:phone":"+33 4 50 39 50 64",
    "sg:postcode":"74420",
    "sg:province":"Rhone-Alpes",
    "sg:tags":[
        "household",
        "wood"
    ],
    "wof:name":"Mdf",
    "wof:placetype":"venue"
},
  "geometry": {"coordinates":[6.452188,46.233349],"type":"Point"}
}