{
  "type": "Feature",
  "properties": {
    "addr:full":"RN 117 Carbonne Midi Pyr\u00e9n\u00e9es 31390",
    "addr:postcode":"31390",
    "addr:street":"Rn 117",
    "iso:country":"FR",
    "sg:address":"RN 117",
    "sg:city":"Carbonne",
    "sg:orig_category":"Non-Classified Establishments",
    "sg:phone":"+33 5 61 87 88 88",
    "sg:postcode":"31390",
    "sg:province":"Midi Pyr\u00e9n\u00e9es",
    "wof:name":"Henri Pujade S.a.r.l.",
    "wof:placetype":"venue"
},
  "geometry": {"coordinates":[1.181165,43.273861],"type":"Point"}
}