{
  "type": "Feature",
  "properties": {
    "iso:country":"FR",
    "sg:address":"ZI du Bourgamon",
    "sg:city":"Saint Martin d'H\u00e8res",
    "sg:orig_category":"Unclassifiable Establishments",
    "sg:phone":"+33 4 76 25 88 73",
    "sg:postcode":"38400",
    "sg:province":"Rhone-Alpes",
    "wof:name":"S.i.t.e.l. S.a.r.l.",
    "wof:placetype":"venue"
},
  "geometry": {"coordinates":[5.760386,45.166779],"type":"Point"}
}