{
  "type": "Feature",
  "properties": {
    "addr:full":"38/42, Av. Pierre Brossolette, 94000 Cr\u00e9teil Ile de France 94000",
    "addr:housenumber":"38 / 42",
    "addr:postcode":"94000;94000",
    "addr:street":"Av. Pierre Brossolette",
    "iso:country":"FR",
    "sg:address":"38/42, Av. Pierre Brossolette, 94000 Cr\u00e9teil",
    "sg:orig_category":"Non-Classified Establishments",
    "sg:phone":"+33 1 45 17 25 90",
    "sg:postcode":"94000",
    "sg:province":"Ile de France",
    "wof:name":"B.f.c.c. S.a. - Banque Fran\u00e7aise Du Cr\u00e9dit Coop\u00e9ratif",
    "wof:placetype":"venue"
},
  "geometry": {"coordinates":[2.462955,48.790565],"type":"Point"}
}