{
  "type": "Feature",
  "properties": {
    "iso:country":"FR",
    "sg:address":"B.P. 114, 59290 Wasquehal^^108, Av de Flandres, 59290 Wasquehal",
    "sg:orig_category":"Non-Classified Establishments",
    "sg:phone":"+33 3 20 89 36 00",
    "sg:province":"Nord Pas-de-Calais",
    "wof:name":"Fac Simil\u00e9 Haut De France Bureautique S.a.",
    "wof:placetype":"venue"
},
  "geometry": {"coordinates":[3.132085,50.669395],"type":"Point"}
}