{
  "type": "Feature",
  "properties": {
    "iso:country":"FR",
    "sg:address":"RN 90",
    "sg:city":"Les Marches",
    "sg:orig_category":"Unclassifiable Establishments",
    "sg:phone":"+33 4 79 28 14 48",
    "sg:postcode":"73800",
    "sg:province":"Rhone-Alpes",
    "wof:name":"A.c.s. S.a.r.l. - Assemblage Connectique Services",
    "wof:placetype":"venue"
},
  "geometry": {"coordinates":[6.038695,45.448456],"type":"Point"}
}