{
  "type": "Feature",
  "properties": {
    "addr:full":"141, Rue Paul Tomoux, 93330 Neuilly sur Marne Ile de France",
    "addr:housenumber":"141",
    "addr:postcode":"93330",
    "addr:street":"Rue Paul Tomoux",
    "iso:country":"FR",
    "sg:address":"141, Rue Paul Tomoux, 93330 Neuilly sur Marne",
    "sg:orig_category":"Unclassifiable Establishments",
    "sg:phone":"+33 1 43 08 87 40",
    "sg:province":"Ile de France",
    "wof:name":"Borie",
    "wof:placetype":"venue"
},
  "geometry": {"coordinates":[2.528748,48.866302],"type":"Point"}
}