{
  "type": "Feature",
  "properties": {
    "iso:country":"FR",
    "sg:address":"13 Rue Antoine Balard 95310 St Ouen L'Aum\u00f4ne",
    "sg:classifiers":[
        {
            "category":"Manufacturing",
            "subcategory":"Building Materials",
            "type":"Manufacturing & Wholesale Goods"
        }
    ],
    "sg:phone":"+33 1 30 37 40 54",
    "sg:postcode":"95310",
    "sg:province":"Ile de France",
    "sg:tags":[
        "glass",
        "ceramic"
    ],
    "wof:name":"Filitro Electromagn\u00c9tisme",
    "wof:placetype":"venue"
},
  "geometry": {"coordinates":[-120.396912,38.051048],"type":"Point"}
}