{
  "type": "Feature",
  "properties": {
    "addr:full":"Rue de l'Europe Anzin Nord Pas-de-Calais 59410",
    "addr:postcode":"59410",
    "addr:street":"Rue De L'Europe Anzin Nord",
    "iso:country":"FR",
    "sg:address":"Rue de l'Europe",
    "sg:city":"Anzin",
    "sg:orig_category":"Unclassifiable Establishments",
    "sg:phone":"+33 3 27 28 17 28",
    "sg:postcode":"59410",
    "sg:province":"Nord Pas-de-Calais",
    "wof:name":"Norzinco S.a.",
    "wof:placetype":"venue"
},
  "geometry": {"coordinates":[3.509135,50.37669],"type":"Point"}
}