{
  "type": "Feature",
  "properties": {
    "iso:country":"FR",
    "sg:address":"Rue de Barcelone - ZI de la Roc de Fr\u00eate",
    "sg:city":"Bruges",
    "sg:orig_category":"Unclassifiable Establishments",
    "sg:phone":"+33 5 56 69 40 60",
    "sg:postcode":"33520",
    "sg:province":"Aquitaine",
    "wof:name":"Transports Graveleau S.a.",
    "wof:placetype":"venue"
},
  "geometry": {"coordinates":[-0.610265,44.887768],"type":"Point"}
}