{
  "type": "Feature",
  "properties": {
    "addr:full":"Rue Gay Lussac Gondecourt Nord Pas-de-Calais 59147",
    "addr:postcode":"59147",
    "addr:street":"Rue Gay Lussac Gondecourt Nord",
    "iso:country":"FR",
    "sg:address":"Rue Gay Lussac",
    "sg:city":"Gondecourt",
    "sg:orig_category":"Unclassifiable Establishments",
    "sg:phone":"+33 3 20 58 94 94",
    "sg:postcode":"59147",
    "sg:province":"Nord Pas-de-Calais",
    "wof:name":"Nord Asphalte S.a.r.l.",
    "wof:placetype":"venue"
},
  "geometry": {"coordinates":[2.965269,50.565319],"type":"Point"}
}