{
  "type": "Feature",
  "properties": {
    "addr:full":"All\u00e9e des Peupliers - B\u00e2t. G Cesson S\u00e9vign\u00e9 Ile de France 35570",
    "addr:postcode":"35570",
    "addr:street":"Alle\u0301E Des Peupliers Ba\u0302T",
    "iso:country":"FR",
    "sg:address":"All\u00e9e des Peupliers - B\u00e2t. G",
    "sg:city":"Cesson S\u00e9vign\u00e9",
    "sg:orig_category":"Unclassifiable Establishments",
    "sg:phone":"+33 2 99 83 86 88",
    "sg:postcode":"35570",
    "sg:province":"Ile de France",
    "wof:name":"Bayer S.a.",
    "wof:placetype":"venue"
},
  "geometry": {"coordinates":[-87.38722199999999,44.726311],"type":"Point"}
}