{
  "type": "Feature",
  "properties": {
    "addr:full":"175, Rue Jules Guesde, 59390 Lys lez Lannoy Nord Pas-de-Calais",
    "addr:housenumber":"175",
    "addr:postcode":"59390",
    "addr:street":"Rue Jules Guesde",
    "iso:country":"FR",
    "sg:address":"175, Rue Jules Guesde, 59390 Lys lez Lannoy",
    "sg:orig_category":"Unclassifiable Establishments",
    "sg:phone":"+33 3 20 75 28 59",
    "sg:province":"Nord Pas-de-Calais",
    "wof:name":"Henricart Pierre Et Fils S.a.",
    "wof:placetype":"venue"
},
  "geometry": {"coordinates":[3.203058,50.674107],"type":"Point"}
}