{
  "type": "Feature",
  "properties": {
    "addr:full":"Chez la Bondaz 74200 Reyvroz Rhone-Alpes 74200",
    "addr:postcode":"74200;74200",
    "addr:street":"Rhone-Alpes",
    "iso:country":"FR",
    "sg:address":"Chez la Bondaz 74200 Reyvroz",
    "sg:orig_category":"Unclassifiable Establishments",
    "sg:phone":"+33 4 50 73 80 44",
    "sg:postcode":"74200",
    "sg:province":"Rhone-Alpes",
    "wof:name":"Perrin Pierre S.a.",
    "wof:placetype":"venue"
},
  "geometry": {"coordinates":[6.567964,46.331108],"type":"Point"}
}