{
  "type": "Feature",
  "properties": {
    "addr:full":"56, Bd Courcerin - Espace Multiservices, 77183 Croissy Beaubourg Ile de France",
    "addr:housenumber":"56",
    "addr:postcode":"77183",
    "addr:street":"Bd Courcerin Espace",
    "iso:country":"FR",
    "sg:address":"56, Bd Courcerin - Espace Multiservices, 77183 Croissy Beaubourg",
    "sg:orig_category":"Unclassifiable Establishments",
    "sg:phone":"+33 1 60 17 28 48",
    "sg:province":"Ile de France",
    "wof:name":"S. E. I. N. E. M. S.a.s.",
    "wof:placetype":"venue"
},
  "geometry": {"coordinates":[2.659334,48.828526],"type":"Point"}
}