{
  "type": "Feature",
  "properties": {
    "addr:full":"13 Rue Bourg Mayou 64160 Morlaas Morla\u00e0s Aquitaine 64160",
    "addr:housenumber":"13",
    "addr:postcode":"64160;64160",
    "addr:street":"Rue Bourg Mayou",
    "iso:country":"FR",
    "sg:address":"13 Rue Bourg Mayou 64160 Morlaas",
    "sg:city":"Morla\u00e0s",
    "sg:classifiers":[
        {
            "category":"Wholesale",
            "subcategory":"Meat",
            "type":"Manufacturing & Wholesale Goods"
        }
    ],
    "sg:phone":"+33 5 59 33 04 17",
    "sg:postcode":"64160",
    "sg:province":"Aquitaine",
    "sg:tags":[
        "food",
        "cooked",
        "product",
        "related"
    ],
    "wof:name":"Maison Dalos Freres",
    "wof:placetype":"venue"
},
  "geometry": {"coordinates":[-0.262657,43.34613],"type":"Point"}
}