{
  "type": "Feature",
  "properties": {
    "addr:full":"Place Lucien Auvert Melun Ile de France 77000",
    "addr:postcode":"77000",
    "addr:street":"Place Lucien Auvert",
    "iso:country":"FR",
    "sg:address":"Place Lucien Auvert",
    "sg:city":"Melun",
    "sg:orig_category":"Non-Classified Establishments",
    "sg:phone":"+33 1 64 87 20 00",
    "sg:postcode":"77000",
    "sg:province":"Ile de France",
    "wof:name":"Coop\u00e9ration Pharmaceutique Fran\u00e7aise",
    "wof:placetype":"venue"
},
  "geometry": {"coordinates":[2.661889,48.529152],"type":"Point"}
}