{
  "type": "Feature",
  "properties": {
    "iso:country":"FR",
    "sg:address":"55 ter, Rue des Graviers, 78200 Magnanville",
    "sg:orig_category":"Non-Classified Establishments",
    "sg:phone":"+33 1 30 98 49 75",
    "sg:postcode":"78200",
    "sg:province":"Ile de France",
    "wof:name":"B\u00fchler Montec S.a.",
    "wof:placetype":"venue"
},
  "geometry": {"coordinates":[1.695081,48.975029],"type":"Point"}
}