{
  "type": "Feature",
  "properties": {
    "addr:full":"1 CHEMIN DES VERGERS 69760 Limonest Rhone-Alpes 69760",
    "addr:housenumber":"1",
    "addr:postcode":"69760;69760",
    "addr:street":"Chemin Des Vergers",
    "iso:country":"FR",
    "sg:address":"1 CHEMIN DES VERGERS 69760 Limonest",
    "sg:classifiers":[
        {
            "category":"Utilities",
            "subcategory":"Telephone",
            "type":"Services"
        }
    ],
    "sg:phone":"+33 4 72 52 97 97",
    "sg:postcode":"69760",
    "sg:province":"Rhone-Alpes",
    "sg:tags":[
        "modem"
    ],
    "wof:name":"West Modem Sa",
    "wof:placetype":"venue"
},
  "geometry": {"coordinates":[4.77387,45.807426],"type":"Point"}
}