{
  "type": "Feature",
  "properties": {
    "iso:country":"FR",
    "sg:address":"12, Rue Edouard Moss\u00e9, 13013 Marseille",
    "sg:orig_category":"Unclassifiable Establishments",
    "sg:phone":"+33 4 91 66 12 36",
    "sg:province":"Provence-Alpes-C\u00f4te d'Azur",
    "wof:name":"Bisogno Maurice",
    "wof:placetype":"venue"
},
  "geometry": {"coordinates":[5.45334,43.325657],"type":"Point"}
}