{
  "type": "Feature",
  "properties": {
    "iso:country":"FR",
    "sg:address":"100 Rue De Paris 91342 Massy Cedex",
    "sg:classifiers":[
        {
            "category":"Utilities",
            "subcategory":"Telephone",
            "type":"Services"
        }
    ],
    "sg:phone":"+33 1 64 47 20 00",
    "sg:province":"Bourgogne",
    "sg:tags":[
        "telecommunication"
    ],
    "wof:name":"Abb Automation",
    "wof:placetype":"venue"
},
  "geometry": {"coordinates":[2.267779,48.724373],"type":"Point"}
}