{
  "type": "Feature",
  "properties": {
    "addr:full":"5 Rue Louis Br\u00e9guet 44980 Ste Luce Sur Loire Pays de Loire 44980",
    "addr:housenumber":"5",
    "addr:postcode":"44980;44980",
    "addr:street":"Rue Louis Bre\u0301Guet;Luce;Loire",
    "iso:country":"FR",
    "sg:address":"5 Rue Louis Br\u00e9guet 44980 Ste Luce Sur Loire",
    "sg:classifiers":[
        {
            "category":"Professional",
            "subcategory":"Business Services",
            "type":"Services"
        }
    ],
    "sg:phone":"+33 2 40 68 37 00",
    "sg:postcode":"44980",
    "sg:province":"Pays de Loire",
    "sg:tags":[
        "textile",
        "linen",
        "advice",
        "clothing",
        "fabric"
    ],
    "wof:name":"Initial Services Textiles",
    "wof:placetype":"venue"
},
  "geometry": {"coordinates":[-1.468743,47.271519],"type":"Point"}
}