{
  "type": "Feature",
  "properties": {
    "addr:full":"14, Rue de Chenonceaux, 37150 Francueil Francueil Centre 37150",
    "addr:housenumber":"14;francueil",
    "addr:postcode":"37150;37150",
    "addr:street":"Rue De Chenonceaux",
    "iso:country":"FR",
    "sg:address":"14, Rue de Chenonceaux, 37150 Francueil",
    "sg:city":"Francueil",
    "sg:orig_category":"Unclassifiable Establishments",
    "sg:phone":"+33 2 47 23 91 22",
    "sg:postcode":"37150",
    "sg:province":"Centre",
    "wof:name":"Les Ma\u00eetres Vignerons De La Gourmandi\u00e8re S.c.a.",
    "wof:placetype":"venue"
},
  "geometry": {"coordinates":[1.07838,47.319775],"type":"Point"}
}