{
  "type": "Feature",
  "properties": {
    "iso:country":"FR",
    "sg:address":"Le Petit Lyon 12400 Montlaur",
    "sg:classifiers":[
        {
            "category":"Food & Beverages",
            "subcategory":"Dairy",
            "type":"Retail Goods"
        }
    ],
    "sg:phone":"+33 5 65 99 81 21",
    "sg:postcode":"12400",
    "sg:province":"Midi Pyr\u00e9n\u00e9es",
    "sg:tags":[
        "product",
        "related"
    ],
    "wof:name":"Les Fromageris Occitanes",
    "wof:placetype":"venue"
},
  "geometry": {"coordinates":[2.81365,43.889244],"type":"Point"}
}