{
  "type": "Feature",
  "properties": {
    "addr:full":"7, Rue des Grimettes, 92190 Meudon Ile de France",
    "addr:housenumber":"7",
    "addr:postcode":"92190",
    "addr:street":"Rue Des Grimettes",
    "iso:country":"FR",
    "sg:address":"7, Rue des Grimettes, 92190 Meudon",
    "sg:orig_category":"Non-Classified Establishments",
    "sg:phone":"+33 1 45 34 39 97",
    "sg:province":"Ile de France",
    "wof:name":"O.p.a. S.a.r.l. - Ordinateurs P\u00e9riph\u00e9riques Associ\u00e9s",
    "wof:placetype":"venue"
},
  "geometry": {"coordinates":[2.242209,48.808186],"type":"Point"}
}