{
  "type": "Feature",
  "properties": {
    "addr:full":"B.P. 46, 49430 Durtal C\u00e9dex^^Rte d'Angers - ZI les Touches, 49430 Durtal Pays de Loire 49430",
    "addr:postcode":"49430;d'angers zi;49430;49430",
    "addr:street":"B.P. 46",
    "iso:country":"FR",
    "sg:address":"B.P. 46, 49430 Durtal C\u00e9dex^^Rte d'Angers - ZI les Touches, 49430 Durtal",
    "sg:orig_category":"Non-Classified Establishments",
    "sg:phone":"+33 2 41 76 31 62",
    "sg:postcode":"49430",
    "sg:province":"Pays de Loire",
    "wof:name":"C.m.a.r. S.a.",
    "wof:placetype":"venue"
},
  "geometry": {"coordinates":[-0.2427,47.665771],"type":"Point"}
}