{
  "type": "Feature",
  "properties": {
    "addr:full":"B.P. 1 Plouvien Bretagne 29860",
    "addr:postcode":"29860",
    "addr:street":"B.P. 1 Plouvien Bretagne",
    "iso:country":"FR",
    "sg:address":"B.P. 1",
    "sg:city":"Plouvien",
    "sg:orig_category":"Non-Classified Establishments",
    "sg:phone":"+33 2 98 40 90 30",
    "sg:postcode":"29860",
    "sg:province":"Bretagne",
    "wof:name":"S.i.l.l. S.a. - Soci\u00e9t\u00e9 Industrielle Laiti\u00e8re Du L\u00e9on",
    "wof:placetype":"venue"
},
  "geometry": {"coordinates":[-4.373429,48.471745],"type":"Point"}
}