{
  "type": "Feature",
  "properties": {
    "addr:full":"18, Rue Fissot, 69009 Lyon Rhone-Alpes 69009",
    "addr:housenumber":"18",
    "addr:postcode":"69009;69009",
    "addr:street":"Rue Fissot",
    "iso:country":"FR",
    "sg:address":"18, Rue Fissot, 69009 Lyon",
    "sg:orig_category":"Unclassifiable Establishments",
    "sg:phone":"+33 4 78 64 83 24",
    "sg:postcode":"69009",
    "sg:province":"Rhone-Alpes",
    "wof:name":"S\u00e9ridium S.a.r.l.",
    "wof:placetype":"venue"
},
  "geometry": {"coordinates":[4.805335,45.774105],"type":"Point"}
}