{
  "type": "Feature",
  "properties": {
    "addr:full":"174 Av Des Minimes Immeuble Le Sirema 31200 Toulouse Midi Pyr\u00e9n\u00e9es 31200",
    "addr:housenumber":"immeuble",
    "addr:postcode":"31200;31200",
    "addr:street":"174 Av Des Minimes",
    "iso:country":"FR",
    "sg:address":"174 Av Des Minimes Immeuble Le Sirema 31200 Toulouse",
    "sg:classifiers":[
        {
            "category":"Banks & Credit Unions",
            "subcategory":"Financial Services",
            "type":"Services"
        }
    ],
    "sg:phone":"+33 5 62 72 93 13",
    "sg:postcode":"31200",
    "sg:province":"Midi Pyr\u00e9n\u00e9es",
    "sg:tags":[
        "banking",
        "insurance",
        "institution",
        "finance"
    ],
    "wof:name":"Bnp Paribas Lease Group",
    "wof:placetype":"venue"
},
  "geometry": {"coordinates":[1.43407,43.626053],"type":"Point"}
}