{
  "type": "Feature",
  "properties": {
    "addr:full":"B.P. 1015, 18025 Bourges C\u00e9dex^^36/38, Av. de la Prospective, 18000 Bourges Bourges Centre 18000",
    "addr:housenumber":"1015",
    "addr:postcode":"18025;18000;18000",
    "addr:street":"B.P.;38 Av. De La Prospective",
    "iso:country":"FR",
    "sg:address":"B.P. 1015, 18025 Bourges C\u00e9dex^^36/38, Av. de la Prospective, 18000 Bourges",
    "sg:city":"Bourges",
    "sg:orig_category":"Non-Classified Establishments",
    "sg:phone":"+33 2 48 70 01 18",
    "sg:postcode":"18000",
    "sg:province":"Centre",
    "wof:name":"Biscuits Dubois S.a.",
    "wof:placetype":"venue"
},
  "geometry": {"coordinates":[2.39293,47.085854],"type":"Point"}
}