{
  "type": "Feature",
  "properties": {
    "addr:full":"26bis, Av Pierre B\u00e9r\u00e9govoy, 58000 Nevers Nevers Bourgogne 58000",
    "addr:postcode":"58000;58000",
    "addr:street":"Av Pierre Be\u0301Re\u0301Govoy",
    "iso:country":"FR",
    "sg:address":"26bis, Av Pierre B\u00e9r\u00e9govoy, 58000 Nevers",
    "sg:city":"Nevers",
    "sg:orig_category":"Unclassifiable Establishments",
    "sg:phone":"+33 820 33 75 49",
    "sg:postcode":"58000",
    "sg:province":"Bourgogne",
    "wof:name":"B.p.b. - Banque Populaire De Bourgogne",
    "wof:placetype":"venue"
},
  "geometry": {"coordinates":[3.157822,46.989891],"type":"Point"}
}