{
  "type": "Feature",
  "properties": {
    "iso:country":"FR",
    "sg:address":"365, Le Clos Chemin de Maran, 83330 Le Beausset",
    "sg:city":"Beausse",
    "sg:orig_category":"Non-Classified Establishments",
    "sg:phone":"+33 4 94 90 20 78",
    "sg:postcode":"49410",
    "sg:province":"Pays de Loire",
    "wof:name":"Abs S\u00e9curit\u00e9 S.a.r.l.",
    "wof:placetype":"venue"
},
  "geometry": {"coordinates":[5.84586,43.164211],"type":"Point"}
}