{
  "type": "Feature",
  "properties": {
    "addr:full":"ZI Fief Girard Aigrefeuille d'Aunis Poitou-Charentes 17290",
    "addr:postcode":"17290",
    "addr:street":"Fief Girard;D'Aunis",
    "iso:country":"FR",
    "sg:address":"ZI Fief Girard",
    "sg:city":"Aigrefeuille d'Aunis",
    "sg:orig_category":"Unclassifiable Establishments",
    "sg:phone":"+33 5 46 35 70 40",
    "sg:postcode":"17290",
    "sg:province":"Poitou-Charentes",
    "wof:name":"Fountaine Pajot S.a.",
    "wof:placetype":"venue"
},
  "geometry": {"coordinates":[-0.93735,46.115749],"type":"Point"}
}