{
  "type": "Feature",
  "properties": {
    "addr:full":"71 Rue Racine 59100 Roubaix Nord Pas-de-Calais 59100",
    "addr:housenumber":"71",
    "addr:postcode":"59100;59100",
    "addr:street":"Rue Racine",
    "iso:country":"FR",
    "sg:address":"71 Rue Racine 59100 Roubaix",
    "sg:classifiers":[
        {
            "category":"Shopping",
            "subcategory":"Crafts & Fabrics",
            "type":"Retail Goods"
        }
    ],
    "sg:phone":"+33 3 20 68 50 10",
    "sg:postcode":"59100",
    "sg:province":"Nord Pas-de-Calais",
    "sg:tags":[
        "textile",
        "clothing"
    ],
    "wof:name":"Fantex Trading Sarl",
    "wof:placetype":"venue"
},
  "geometry": {"coordinates":[3.161608,50.702602],"type":"Point"}
}