{
  "type": "Feature",
  "properties": {
    "addr:full":"37, Rue de Valengelier, 77500 Chelles Ile de France",
    "addr:housenumber":"37",
    "addr:postcode":"77500;ile",
    "addr:street":"Rue De Valengelier",
    "iso:country":"FR",
    "sg:address":"37, Rue de Valengelier, 77500 Chelles",
    "sg:orig_category":"Unclassifiable Establishments",
    "sg:phone":"+33 1 64 26 69 69",
    "sg:province":"Ile de France",
    "wof:name":"S.e.r.i.a.l. S.a. - Soci\u00e9t\u00e9 Etude R\u00e9alisation Informatique Automatisme Logistique",
    "wof:placetype":"venue"
},
  "geometry": {"coordinates":[2.595365,48.891319],"type":"Point"}
}