{
  "type": "Feature",
  "properties": {
    "addr:full":"B.P. 2035, 13201 Marseille C\u00e9dex 01^^56, Rue de la Joliette, 1300 Marseille Rhone-Alpes",
    "addr:housenumber":"2035;01 ^ ^ 56;1300",
    "addr:postcode":"13201",
    "addr:street":"B.P.;Ce\u0301Dex;Rue De La Joliette",
    "iso:country":"FR",
    "sg:address":"B.P. 2035, 13201 Marseille C\u00e9dex 01^^56, Rue de la Joliette, 1300 Marseille",
    "sg:orig_category":"Non-Classified Establishments",
    "sg:phone":"+33 4 96 17 00 40",
    "sg:province":"Rhone-Alpes",
    "wof:name":"Nicolas Fr\u00e8res S.a.",
    "wof:placetype":"venue"
},
  "geometry": {"coordinates":[5.67735,45.734741],"type":"Point"}
}