{
  "type": "Feature",
  "properties": {
    "addr:full":"2 Avenue Georges Clemenceau Yssingeaux Auvergne 43200",
    "addr:housenumber":"2",
    "addr:postcode":"43200",
    "addr:street":"Avenue Georges Clemenceau",
    "iso:country":"FR",
    "sg:address":"2 Avenue Georges Clemenceau",
    "sg:city":"Yssingeaux",
    "sg:classifiers":[
        {
            "category":"Banks & Credit Unions",
            "subcategory":"Financial Services",
            "type":"Services"
        }
    ],
    "sg:phone":"+33 4 71 59 00 89",
    "sg:postcode":"43200",
    "sg:province":"Auvergne",
    "sg:tags":[
        "banking",
        "finance",
        "insurance"
    ],
    "wof:name":"Societe Fiduciaire Nationale D'expertise Comptable Fidexpert (fid)",
    "wof:placetype":"venue"
},
  "geometry": {"coordinates":[4.122541,45.143452],"type":"Point"}
}