{
  "type": "Feature",
  "properties": {
    "addr:full":"Zi Carrefour De L'Europe 57602 Forbach Lorraine",
    "addr:postcode":"57602",
    "addr:street":"Carrefour De L'Europe",
    "iso:country":"FR",
    "sg:address":"Zi Carrefour De L'Europe 57602 Forbach",
    "sg:classifiers":[
        {
            "category":"Manufacturing",
            "subcategory":"Printing",
            "type":"Manufacturing & Wholesale Goods"
        }
    ],
    "sg:phone":"+33 3 87 29 33 40",
    "sg:province":"Lorraine",
    "sg:tags":[
        "publishing"
    ],
    "wof:name":"Dhf",
    "wof:placetype":"venue"
},
  "geometry": {"coordinates":[6.89843,49.18594],"type":"Point"}
}