{
  "type": "Feature",
  "properties": {
    "addr:full":"43, Rue Louis David, 93170 Bagnolet Ile de France",
    "addr:housenumber":"43",
    "addr:postcode":"93170;ile",
    "addr:street":"Rue Louis David",
    "iso:country":"FR",
    "sg:address":"43, Rue Louis David, 93170 Bagnolet",
    "sg:orig_category":"Non-Classified Establishments",
    "sg:phone":"+33 1 43 62 63 63",
    "sg:province":"Ile de France",
    "wof:name":"Euroflex S.a.r.l.",
    "wof:placetype":"venue"
},
  "geometry": {"coordinates":[2.415377,48.873833],"type":"Point"}
}