{
  "type": "Feature",
  "properties": {
    "iso:country":"FR",
    "sg:address":"130-136 Av Joseph Kessel 78960 Voisins Le Bretonneux",
    "sg:classifiers":[
        {
            "category":"Wholesale",
            "subcategory":"Machinery & Supplies",
            "type":"Manufacturing & Wholesale Goods"
        }
    ],
    "sg:phone":"+33 1 34 52 38 50",
    "sg:postcode":"78960",
    "sg:province":"Ile de France",
    "sg:tags":[
        "handling",
        "material",
        "-",
        "machine",
        "equipment",
        "engineering",
        "mechanical"
    ],
    "wof:name":"Otis Sa",
    "wof:placetype":"venue"
},
  "geometry": {"coordinates":[2.054325,48.767178],"type":"Point"}
}