{
  "type": "Feature",
  "properties": {
    "addr:full":"B.P. 21, 38250 Villard de Lans^^Rte de Br\u00e9duire, 38250 Villard de Lans Rhone-Alpes 38250",
    "addr:postcode":"38250;38250;38250",
    "addr:street":"B.P. 21;Rhone-Alpes",
    "iso:country":"FR",
    "sg:address":"B.P. 21, 38250 Villard de Lans^^Rte de Br\u00e9duire, 38250 Villard de Lans",
    "sg:orig_category":"Non-Classified Establishments",
    "sg:phone":"+33 4 76 95 58 32",
    "sg:postcode":"38250",
    "sg:province":"Rhone-Alpes",
    "wof:name":"Entreprise Bonnard E.u.r.l.",
    "wof:placetype":"venue"
},
  "geometry": {"coordinates":[5.527228,45.03178],"type":"Point"}
}