{
  "type": "Feature",
  "properties": {
    "addr:full":"45 Rue Michel Cazaux Zi La Courtine La Sophie 84000 Avignon Provence-Alpes-C\u00f4te d'Azur",
    "addr:housenumber":"45",
    "addr:postcode":"84000",
    "addr:street":"Rue Michel Cazaux Zi La Courtine La Sophie",
    "iso:country":"FR",
    "sg:address":"45 Rue Michel Cazaux Zi La Courtine La Sophie 84000 Avignon",
    "sg:classifiers":[
        {
            "category":"Manufacturing",
            "subcategory":"Rubber & Plastics",
            "type":"Manufacturing & Wholesale Goods"
        }
    ],
    "sg:phone":"+33 4 90 86 47 42",
    "sg:province":"Provence-Alpes-C\u00f4te d'Azur",
    "wof:name":"Servi Provence Maintenance Systeme",
    "wof:placetype":"venue"
},
  "geometry": {"coordinates":[4.806015,43.948753],"type":"Point"}
}