{
  "type": "Feature",
  "properties": {
    "addr:full":"14, Rue Emile Grasset, 49300 Cholet Pays de Loire",
    "addr:housenumber":"14",
    "addr:postcode":"49300",
    "addr:street":"Rue Emile Grasset",
    "iso:country":"FR",
    "sg:address":"14, Rue Emile Grasset, 49300 Cholet",
    "sg:orig_category":"Unclassifiable Establishments",
    "sg:phone":"+33 2 41 62 31 77",
    "sg:province":"Pays de Loire",
    "wof:name":"C.g.s.t. Save S.a.s. - Compagnie Gazi\u00e8re Service Technique Save",
    "wof:placetype":"venue"
},
  "geometry": {"coordinates":[-0.872084,47.057713],"type":"Point"}
}