{
  "type": "Feature",
  "properties": {
    "addr:full":"B.P. 505, 51200 Epernay^^H\u00f4tel de Ville, 51200 Epernay Champagne",
    "addr:housenumber":"b.p. 505",
    "addr:postcode":"51200;51200",
    "addr:street":"Ville",
    "iso:country":"FR",
    "sg:address":"B.P. 505, 51200 Epernay^^H\u00f4tel de Ville, 51200 Epernay",
    "sg:orig_category":"Non-Classified Establishments",
    "sg:phone":"+33 3 26 53 36 00",
    "sg:province":"Champagne",
    "wof:name":"Mairie D'epernay",
    "wof:placetype":"venue"
},
  "geometry": {"coordinates":[3.95475,49.045197],"type":"Point"}
}