{
  "type": "Feature",
  "properties": {
    "iso:country":"FR",
    "sg:address":"4, Rue du Stade, 80800 Daours",
    "sg:orig_category":"Non-Classified Establishments",
    "sg:phone":"+33 3 22 96 37 37",
    "sg:province":"Picardie",
    "wof:name":"Sogidef S.a.",
    "wof:placetype":"venue"
},
  "geometry": {"coordinates":[2.457533,49.901855],"type":"Point"}
}