{
  "type": "Feature",
  "properties": {
    "iso:country":"FR",
    "sg:address":"30, Rue de Lattre de Tassigny, 67300 Schiltigheim",
    "sg:city":"Schiltigheim",
    "sg:orig_category":"Unclassifiable Establishments",
    "sg:phone":"+33 3 88 33 70 33",
    "sg:postcode":"67300",
    "sg:province":"Alsace",
    "wof:name":"Manufacture De V\u00eatements S.a.r.l.",
    "wof:placetype":"venue"
},
  "geometry": {"coordinates":[7.747283,48.60651],"type":"Point"}
}