{
  "type": "Feature",
  "properties": {
    "addr:full":"LID de Carros-le-Broc ave. 2079 M; Carros; 06511 Corse",
    "addr:housenumber":"2079 m",
    "addr:postcode":"06511",
    "addr:street":"Lid;Carros-Le-Broc Ave.;Carros",
    "iso:country":"FR",
    "sg:address":"LID de Carros-le-Broc",
    "sg:city":"ave. 2079 M; Carros; 06511",
    "sg:classifiers":[
        {
            "category":"Industrial Area",
            "type":"Public Place"
        }
    ],
    "sg:phone":"+33 4 93 29 11 28",
    "sg:province":"Corse",
    "sg:tags":[
        "large",
        "private"
    ],
    "wof:name":"Laboratoires Arkopharma Sa",
    "wof:placetype":"venue"
},
  "geometry": {"coordinates":[7.191765,43.766804],"type":"Point"}
}