{
  "type": "Feature",
  "properties": {
    "iso:country":"FR",
    "sg:address":"B.P. 99, 83003 Draguignan C\u00e9dex^^1, Bd Mar\u00e9chal Foch, 83300 Draguignan",
    "sg:orig_category":"Non-Classified Establishments",
    "sg:phone":"+33 4 94 50 55 50",
    "sg:province":"Outre-Mer",
    "wof:name":"C.d.t. - Comit\u00e9 D\u00e9partemental Du Tourisme",
    "wof:placetype":"venue"
},
  "geometry": {"coordinates":[6.463645,43.539795],"type":"Point"}
}