{
  "type": "Feature",
  "properties": {
    "iso:country":"FR",
    "sg:address":"1 Rue Saint Vincent 56000 Vannes",
    "sg:city":"Vannes",
    "sg:classifiers":[
        {
            "category":"Bakery",
            "type":"Food & Drink"
        }
    ],
    "sg:phone":"+33 2 97 47 16 51",
    "sg:postcode":"56000",
    "sg:province":"Bretagne",
    "sg:tags":[
        "cake",
        "product",
        "related",
        "bread"
    ],
    "wof:name":"Sarl Boulangerie Saint Vincent",
    "wof:placetype":"venue"
},
  "geometry": {"coordinates":[-2.758412,47.65419],"type":"Point"}
}