{
  "type": "Feature",
  "properties": {
    "iso:country":"FR",
    "sg:address":"Mas de Saint Louis",
    "sg:city":"Bellegarde",
    "sg:orig_category":"Non-Classified Establishments",
    "sg:phone":"+33 4 66 01 13 58",
    "sg:postcode":"30127",
    "sg:province":"Languedoc-Roussillon",
    "wof:name":"G.f.a. Lamour",
    "wof:placetype":"venue"
},
  "geometry": {"coordinates":[4.501595,43.777561],"type":"Point"}
}