{
  "type": "Feature",
  "properties": {
    "addr:full":"3, Rue Paul Langevin - ZI de la Croix Cadeau, 49240 Avrill\u00e9 Pays de Loire",
    "addr:housenumber":"3",
    "addr:postcode":"49240",
    "addr:street":"Rue Paul Langevin Zi De La Croix Cadeau",
    "iso:country":"FR",
    "sg:address":"3, Rue Paul Langevin - ZI de la Croix Cadeau, 49240 Avrill\u00e9",
    "sg:orig_category":"Unclassifiable Establishments",
    "sg:phone":"+33 2 41 42 95 00",
    "sg:province":"Pays de Loire",
    "wof:name":"Galvanotec S.a.",
    "wof:placetype":"venue"
},
  "geometry": {"coordinates":[-0.587263,47.504822],"type":"Point"}
}