{
  "type": "Feature",
  "properties": {
    "addr:full":"9, Rue Guhermont, 78730 Saint Arnoult en Yvelines Ile de France",
    "addr:housenumber":"9",
    "addr:postcode":"78730",
    "addr:street":"Rue Guhermont",
    "iso:country":"FR",
    "sg:address":"9, Rue Guhermont, 78730 Saint Arnoult en Yvelines",
    "sg:orig_category":"Unclassifiable Establishments",
    "sg:phone":"+33 1 30 41 26 82",
    "sg:province":"Ile de France",
    "wof:name":"Asam Automatismes S.a.r.l. - Assistance Services Automatisme M\u00e9canisation",
    "wof:placetype":"venue"
},
  "geometry": {"coordinates":[1.946038,48.575508],"type":"Point"}
}