{
  "type": "Feature",
  "properties": {
    "iso:country":"FR",
    "sg:address":"Le Bourg 63250 Celles Sur Durolle",
    "sg:city":"Arconsat",
    "sg:classifiers":[
        {
            "category":"Manufacturing",
            "subcategory":"Metals",
            "type":"Manufacturing & Wholesale Goods"
        }
    ],
    "sg:phone":"+33 4 73 51 50 11",
    "sg:postcode":"63250",
    "sg:province":"Auvergne",
    "sg:tags":[
        "metallurgy",
        "metalworking",
        "processing"
    ],
    "wof:name":"Ets Chambriard Et Fils Sarl",
    "wof:placetype":"venue"
},
  "geometry": {"coordinates":[3.704752,45.82304],"type":"Point"}
}