{
  "type": "Feature",
  "properties": {
    "iso:country":"FR",
    "sg:address":"Piparc 56400 Brech",
    "sg:city":"Brech",
    "sg:classifiers":[
        {
            "category":"Manufacturing",
            "subcategory":"Metals",
            "type":"Manufacturing & Wholesale Goods"
        }
    ],
    "sg:phone":"+33 2 97 24 08 38",
    "sg:postcode":"56400",
    "sg:province":"Bretagne",
    "sg:tags":[
        "metallurgy",
        "steel",
        "metalworking"
    ],
    "wof:name":"Afm Recycling",
    "wof:placetype":"venue"
},
  "geometry": {"coordinates":[-3.011294,47.682312],"type":"Point"}
}