{
  "type": "Feature",
  "properties": {
    "iso:country":"FR",
    "sg:address":"Chem D\u00e9partemental La Peyrade Site Ciment Lafarge Usine Sete 34110 Frontignan",
    "sg:classifiers":[
        {
            "category":"Professional",
            "subcategory":"Engineering",
            "type":"Services"
        }
    ],
    "sg:phone":"+33 4 67 46 66 90",
    "sg:postcode":"34110",
    "sg:province":"Languedoc-Roussillon",
    "sg:tags":[
        "machine",
        "-",
        "environment",
        "equipment",
        "machinery",
        "mechanical"
    ],
    "wof:name":"Scori Usine Lafarge",
    "wof:placetype":"venue"
},
  "geometry": {"coordinates":[3.75841,43.444561],"type":"Point"}
}