{
  "type": "Feature",
  "properties": {
    "addr:full":"Za De Bertheuil 40090 St Perdon Artassenx Aquitaine 40090",
    "addr:postcode":"40090;40090",
    "addr:street":"Za De Bertheuil",
    "iso:country":"FR",
    "sg:address":"Za De Bertheuil 40090 St Perdon",
    "sg:city":"Artassenx",
    "sg:classifiers":[
        {
            "category":"Home & Garden",
            "subcategory":"Furniture",
            "type":"Retail Goods"
        }
    ],
    "sg:phone":"+33 5 58 06 36 36",
    "sg:postcode":"40090",
    "sg:province":"Aquitaine",
    "sg:tags":[
        "wood"
    ],
    "wof:name":"Les Scieries D'aquitaine Sa",
    "wof:placetype":"venue"
},
  "geometry": {"coordinates":[-0.590879,43.863628],"type":"Point"}
}