{
  "type": "Feature",
  "properties": {
    "addr:full":"B.P. 80 Avoine Centre 37420",
    "addr:postcode":"37420",
    "addr:street":"B.P. 80 Avoine",
    "iso:country":"FR",
    "sg:address":"B.P. 80",
    "sg:city":"Avoine",
    "sg:orig_category":"Non-Classified Establishments",
    "sg:phone":"+33 2 47 98 60 60",
    "sg:postcode":"37420",
    "sg:province":"Centre",
    "wof:name":"C.p.n. De Production Nucl\u00e9aire De Chinon",
    "wof:placetype":"venue"
},
  "geometry": {"coordinates":[0.16497,47.188187],"type":"Point"}
}