{
  "type": "Feature",
  "properties": {
    "iso:country":"FR",
    "sg:address":"16, La Foug\u00e8re, 88150 Chavelot",
    "sg:orig_category":"Unclassifiable Establishments",
    "sg:phone":"+33 3 29 34 55 73",
    "sg:province":"Lorraine",
    "wof:name":"Fraikin Location S.a.",
    "wof:placetype":"venue"
},
  "geometry": {"coordinates":[6.431983,48.22863],"type":"Point"}
}