{
  "type": "Feature",
  "properties": {
    "iso:country":"FR",
    "sg:address":"1 Rue Desseaux 76100 Rouen",
    "sg:classifiers":[
        {
            "category":"Professional",
            "subcategory":"Engineering",
            "type":"Services"
        }
    ],
    "sg:phone":"+33 2 35 63 56 22",
    "sg:postcode":"76100",
    "sg:province":"Haute Normandie",
    "sg:tags":[
        "machine",
        "-",
        "mechanical"
    ],
    "wof:name":"La Corpo",
    "wof:placetype":"venue"
},
  "geometry": {"coordinates":[1.095354,49.429062],"type":"Point"}
}