{
  "type": "Feature",
  "properties": {
    "addr:full":"48 bis, Rue Gabriel Mouilleron, 54000 Nancy Lorraine",
    "addr:housenumber":"48 bis",
    "addr:postcode":"54000",
    "addr:street":"Rue Gabriel Mouilleron",
    "iso:country":"FR",
    "sg:address":"48 bis, Rue Gabriel Mouilleron, 54000 Nancy",
    "sg:orig_category":"Non-Classified Establishments",
    "sg:phone":"+33 3 83 41 10 20",
    "sg:province":"Lorraine",
    "wof:name":"Harmonie S.a.",
    "wof:placetype":"venue"
},
  "geometry": {"coordinates":[6.170857,48.684067],"type":"Point"}
}