{
  "type": "Feature",
  "properties": {
    "iso:country":"FR",
    "sg:address":"13, Rue de S\u00e8te, 67100 Strasbourg",
    "sg:city":"Strasbourg",
    "sg:orig_category":"Unclassifiable Establishments",
    "sg:phone":"+33 3 88 40 00 13",
    "sg:postcode":"67100",
    "sg:province":"Alsace",
    "wof:name":"S.m.l. S.a.r.l. - Soci\u00e9t\u00e9 De Manutention Et De Levage",
    "wof:placetype":"venue"
},
  "geometry": {"coordinates":[7.794154,48.542549],"type":"Point"}
}