{
  "type": "Feature",
  "properties": {
    "iso:country":"FR",
    "sg:address":"64 B Boulevard De La Republique 47000 Agen",
    "sg:city":"Agen",
    "sg:classifiers":[
        {
            "category":"Shopping",
            "subcategory":"Clothing, Apparel, & Fashions",
            "type":"Retail Goods"
        }
    ],
    "sg:phone":"+33 5 53 87 86 20",
    "sg:postcode":"47000",
    "sg:province":"Aquitaine",
    "sg:tags":[
        "textile",
        "clothing",
        "clothes"
    ],
    "wof:name":"Promod",
    "wof:placetype":"venue"
},
  "geometry": {"coordinates":[0.618797,44.204922],"type":"Point"}
}