{
  "type": "Feature",
  "properties": {
    "addr:full":"76 Avenue Andre Malraux 57000 Metz Lorraine 57000",
    "addr:housenumber":"76",
    "addr:postcode":"57000;57000",
    "addr:street":"Avenue Andre Malraux",
    "iso:country":"FR",
    "sg:address":"76 Avenue Andre Malraux 57000 Metz",
    "sg:classifiers":[
        {
            "category":"Professional",
            "subcategory":"Advertising",
            "type":"Services"
        }
    ],
    "sg:phone":"+33 3 87 63 95 30",
    "sg:postcode":"57000",
    "sg:province":"Lorraine",
    "sg:tags":[
        "information",
        "medium",
        "communication"
    ],
    "wof:name":"Mc Com",
    "wof:placetype":"venue"
},
  "geometry": {"coordinates":[6.180003,49.10276],"type":"Point"}
}