{
  "type": "Feature",
  "properties": {
    "iso:country":"FR",
    "sg:address":"B.P. 145, 49481 Saint Sylvain d'Anjou C\u00e9dex^^ZA des Fousseaux, 49480 Saint Sylvain d'Anjou",
    "sg:orig_category":"Non-Classified Establishments",
    "sg:phone":"+33 2 41 76 57 20",
    "sg:postcode":"49480",
    "sg:province":"Pays de Loire",
    "wof:name":"Avenir - M\u00e9ca S.a.r.l.",
    "wof:placetype":"venue"
},
  "geometry": {"coordinates":[-0.47588,47.512901],"type":"Point"}
}