{
  "type": "Feature",
  "properties": {
    "addr:full":"41/43, Rue Cr\u00e8vecoeur, 93120 La Courneuve Ile de France",
    "addr:housenumber":"41 / 43",
    "addr:postcode":"93120",
    "addr:street":"Rue Cre\u0300Vecoeur",
    "iso:country":"FR",
    "sg:address":"41/43, Rue Cr\u00e8vecoeur, 93120 La Courneuve",
    "sg:orig_category":"Unclassifiable Establishments",
    "sg:phone":"+33 1 48 11 39 50",
    "sg:province":"Ile de France",
    "wof:name":"Bati Formes S.a.",
    "wof:placetype":"venue"
},
  "geometry": {"coordinates":[2.384737,48.919498],"type":"Point"}
}