{
  "type": "Feature",
  "properties": {
    "iso:country":"FR",
    "sg:address":"16 Rue St Gilles 28800 Bonneval",
    "sg:city":"Bonneval",
    "sg:classifiers":[
        {
            "category":"Shopping",
            "subcategory":"Computers & Home Electronics",
            "type":"Retail Goods"
        }
    ],
    "sg:phone":"+33 2 37 44 67 67",
    "sg:postcode":"28800",
    "sg:province":"Centre",
    "sg:tags":[
        "equipment",
        "household",
        "electrical",
        "appliance",
        "electronic"
    ],
    "wof:name":"Roller Grill",
    "wof:placetype":"venue"
},
  "geometry": {"coordinates":[1.39976,48.199039],"type":"Point"}
}