{
  "type": "Feature",
  "properties": {
    "iso:country":"FR",
    "sg:address":"71, Av. Henri Barbusse, 87200 Saint Junien",
    "sg:orig_category":"Non-Classified Establishments",
    "sg:phone":"+33 5 55 02 15 79",
    "sg:province":"Limousin",
    "wof:name":"Vignaud Affuteuses S.a.r.l.",
    "wof:placetype":"venue"
},
  "geometry": {"coordinates":[0.908595,45.893696],"type":"Point"}
}