{
  "type": "Feature",
  "properties": {
    "addr:full":"ZA des Vall\u00e9es Pl\u00e9n\u00e9e Jugon Bretagne 22640",
    "addr:postcode":"22640",
    "addr:street":"Za Des Valle\u0301Es Ple\u0301Ne\u0301E Jugon Bretagne",
    "iso:country":"FR",
    "sg:address":"ZA des Vall\u00e9es",
    "sg:city":"Pl\u00e9n\u00e9e Jugon",
    "sg:orig_category":"Non-Classified Establishments",
    "sg:phone":"+33 2 96 51 70 10",
    "sg:postcode":"22640",
    "sg:province":"Bretagne",
    "wof:name":"Technolyse S.a.",
    "wof:placetype":"venue"
},
  "geometry": {"coordinates":[-2.400539,48.364731],"type":"Point"}
}