{
  "type": "Feature",
  "properties": {
    "iso:country":"FR",
    "sg:address":"2, Rte de Linselle, 59250 Halluin",
    "sg:orig_category":"Unclassifiable Establishments",
    "sg:phone":"+33 3 20 28 09 90",
    "sg:province":"Nord Pas-de-Calais",
    "wof:name":"Ducros Euro Express S.a.",
    "wof:placetype":"venue"
},
  "geometry": {"coordinates":[3.119158,50.78101],"type":"Point"}
}