{
  "type": "Feature",
  "properties": {
    "addr:full":"Le Monteil 24680 Lamonzie Saint Martin Gardonne Aquitaine 24680",
    "addr:postcode":"24680;24680",
    "iso:country":"FR",
    "sg:address":"Le Monteil 24680 Lamonzie Saint Martin",
    "sg:city":"Gardonne",
    "sg:orig_category":"Unclassifiable Establishments",
    "sg:phone":"+33 5 53 24 08 89",
    "sg:postcode":"24680",
    "sg:province":"Aquitaine",
    "wof:name":"D.s.d. S.a. - Diffusion Service Dordogne",
    "wof:placetype":"venue"
},
  "geometry": {"coordinates":[0.40479,44.826569],"type":"Point"}
}