{
  "type": "Feature",
  "properties": {
    "iso:country":"FR",
    "sg:address":"54 rue de la Garde 69360 Communay",
    "sg:classifiers":[
        {
            "category":"Shopping",
            "subcategory":"Baby Store",
            "type":"Retail Goods"
        }
    ],
    "sg:phone":"+33 4 74 78 44 30",
    "sg:province":"Rhone-Alpes",
    "sg:tags":[
        "babies'",
        "buggy",
        "pram"
    ],
    "wof:name":"Ets Jamic Sa",
    "wof:placetype":"venue"
},
  "geometry": {"coordinates":[4.833086,45.59853],"type":"Point"}
}