{
  "type": "Feature",
  "properties": {
    "addr:full":"B.P. 38, 64530 Pontacq C\u00e9dex^^34, Rue Mar\u00e9chal Foch, 64530 Pontacq Pontacq Aquitaine 64530",
    "addr:postcode":"64530;64530;64530",
    "addr:street":"B.P. 38;Rue Mare\u0301Chal Foch",
    "iso:country":"FR",
    "sg:address":"B.P. 38, 64530 Pontacq C\u00e9dex^^34, Rue Mar\u00e9chal Foch, 64530 Pontacq",
    "sg:city":"Pontacq",
    "sg:orig_category":"Non-Classified Establishments",
    "sg:phone":"+33 5 59 53 65 53",
    "sg:postcode":"64530",
    "sg:province":"Aquitaine",
    "wof:name":"Secma S.a.",
    "wof:placetype":"venue"
},
  "geometry": {"coordinates":[-0.155097,43.183056],"type":"Point"}
}