{
  "type": "Feature",
  "properties": {
    "addr:full":"9 Rue Mardors 21560 Couternon Couternon Bourgogne 21560",
    "addr:housenumber":"9",
    "addr:postcode":"21560;21560",
    "addr:street":"Rue Mardors",
    "iso:country":"FR",
    "sg:address":"9 Rue Mardors 21560 Couternon",
    "sg:city":"Couternon",
    "sg:classifiers":[
        {
            "category":"Professional",
            "subcategory":"Computer Services",
            "type":"Services"
        }
    ],
    "sg:phone":"+33 3 80 47 57 62",
    "sg:postcode":"21560",
    "sg:province":"Bourgogne",
    "sg:tags":[
        "information",
        "technology",
        "software"
    ],
    "wof:name":"Biosystemes Sarl",
    "wof:placetype":"venue"
},
  "geometry": {"coordinates":[5.143749,47.324841],"type":"Point"}
}