{
  "type": "Feature",
  "properties": {
    "iso:country":"FR",
    "sg:address":"Rue de l'Eglise",
    "sg:city":"Joze",
    "sg:orig_category":"Unclassifiable Establishments",
    "sg:phone":"+33 4 73 70 74 60",
    "sg:postcode":"63350",
    "sg:province":"Auvergne",
    "wof:name":"W.i.m. / I.r.i.p. S.a.r.l.",
    "wof:placetype":"venue"
},
  "geometry": {"coordinates":[3.30277,45.864372],"type":"Point"}
}