{
  "type": "Feature",
  "properties": {
    "iso:country":"FR",
    "sg:address":"Rue Jules Verne 74106 Vetraz Monthoux",
    "sg:classifiers":[
        {
            "category":"Autos & Motor Vehicles",
            "subcategory":"Automobile Sales",
            "type":"Retail Goods"
        }
    ],
    "sg:phone":"+33 4 50 95 40 00",
    "sg:province":"Centre",
    "sg:tags":[
        "equipment",
        "industrial",
        "transport"
    ],
    "wof:name":"Valeo",
    "wof:placetype":"venue"
},
  "geometry": {"coordinates":[-95.98101,36.190472],"type":"Point"}
}