{
  "type": "Feature",
  "properties": {
    "addr:full":"Za De Chanchany 43000 Espaly St Marcel Le Puy-en-Velay Auvergne 43000",
    "addr:postcode":"43000;43000",
    "addr:street":"Za De Chanchany;Espaly St Marcel;Puy-En-Velay",
    "iso:country":"FR",
    "sg:address":"Za De Chanchany 43000 Espaly St Marcel",
    "sg:city":"Le Puy-en-Velay",
    "sg:classifiers":[
        {
            "category":"Professional",
            "type":"Services"
        }
    ],
    "sg:phone":"+33 4 71 02 28 66",
    "sg:postcode":"43000",
    "sg:province":"Auvergne",
    "sg:tags":[
        "transport",
        "road"
    ],
    "wof:name":"Transports Visconte Sa",
    "wof:placetype":"venue"
},
  "geometry": {"coordinates":[3.863273,45.046825],"type":"Point"}
}