{
  "type": "Feature",
  "properties": {
    "addr:full":"1, Quai des Sablons, 89100 Sens Sens Bourgogne 89100",
    "addr:housenumber":"1",
    "addr:postcode":"89100;89100",
    "addr:street":"Quai Des Sablons",
    "iso:country":"FR",
    "sg:address":"1, Quai des Sablons, 89100 Sens",
    "sg:city":"Sens",
    "sg:orig_category":"Unclassifiable Establishments",
    "sg:phone":"+33 3 86 65 72 01",
    "sg:postcode":"89100",
    "sg:province":"Bourgogne",
    "wof:name":"B.m.c.e. Point P S.a.",
    "wof:placetype":"venue"
},
  "geometry": {"coordinates":[3.272553,48.199554],"type":"Point"}
}