{
  "type": "Feature",
  "properties": {
    "addr:full":"27 Courpi\u00e8re Auvergne 63120",
    "addr:housenumber":"27",
    "addr:postcode":"63120",
    "addr:street":"Courpie\u0300Re",
    "iso:country":"FR",
    "sg:address":"27",
    "sg:city":"Courpi\u00e8re",
    "sg:classifiers":[
        {
            "category":"Manufacturing",
            "subcategory":"Metals",
            "type":"Manufacturing & Wholesale Goods"
        }
    ],
    "sg:phone":"+33 4 73 53 07 87",
    "sg:postcode":"63120",
    "sg:province":"Auvergne",
    "sg:tags":[
        "-",
        "machine",
        "equipment",
        "engineering",
        "machinery",
        "mechanical"
    ],
    "wof:name":"Albert Reynard (ets)",
    "wof:placetype":"venue"
},
  "geometry": {"coordinates":[3.539555,45.765034],"type":"Point"}
}