{
  "type": "Feature",
  "properties": {
    "iso:country":"FR",
    "sg:address":"Chateau Mazerat 33330 ST EMILION",
    "sg:city":"Saint-\u00c9tienne-de-Lisse",
    "sg:classifiers":[
        {
            "category":"Wholesale",
            "subcategory":"Wine & Distilled Alcoholic Beverages",
            "type":"Manufacturing & Wholesale Goods"
        }
    ],
    "sg:phone":"+33 5 57 24 71 15",
    "sg:postcode":"33330",
    "sg:province":"Aquitaine",
    "sg:tags":[
        "french"
    ],
    "wof:name":"Earl Gouteyron Christian",
    "wof:placetype":"venue"
},
  "geometry": {"coordinates":[-0.156634,44.892399],"type":"Point"}
}