{
  "type": "Feature",
  "properties": {
    "iso:country":"FR",
    "sg:address":"88 Rue Lecocq 33000 Bordeaux",
    "sg:city":"Bordeaux",
    "sg:classifiers":[
        {
            "category":"Manufacturing",
            "subcategory":"Printing",
            "type":"Manufacturing & Wholesale Goods"
        }
    ],
    "sg:phone":"+33 5 56 96 63 02",
    "sg:postcode":"33000",
    "sg:province":"Aquitaine",
    "sg:tags":[
        "publishing"
    ],
    "wof:name":"Ets Jean Kossmann Sarl",
    "wof:placetype":"venue"
},
  "geometry": {"coordinates":[-0.587382,44.833611],"type":"Point"}
}