{
  "type": "Feature",
  "properties": {
    "iso:country":"FR",
    "sg:address":"6, Rue de la Montagne, 57600 Forbach",
    "sg:orig_category":"Unclassifiable Establishments",
    "sg:phone":"+33 3 87 84 37 21",
    "sg:province":"Lorraine",
    "wof:name":"Bosch Centre De Service S.a.s.",
    "wof:placetype":"venue"
},
  "geometry": {"coordinates":[6.89884,49.184841],"type":"Point"}
}