{
  "type": "Feature",
  "properties": {
    "addr:full":"B.P. 46, 57535 Marange Silvange^^Rond Point de Silvange, 57535 Marange Silvange Centre",
    "addr:postcode":"57535;57535",
    "addr:street":"B.P. 46;Silvange^^Rond",
    "iso:country":"FR",
    "sg:address":"B.P. 46, 57535 Marange Silvange^^Rond Point de Silvange, 57535 Marange Silvange",
    "sg:orig_category":"Non-Classified Establishments",
    "sg:phone":"+33 3 87 80 20 10",
    "sg:province":"Centre",
    "wof:name":"Demas S.a.",
    "wof:placetype":"venue"
},
  "geometry": {"coordinates":[6.11731,49.216114],"type":"Point"}
}