{
  "type": "Feature",
  "properties": {
    "iso:country":"FR",
    "sg:address":"10, Av. Mar\u00e9chal Leclerc, 01200 Bellegarde sur Valserine",
    "sg:orig_category":"Unclassifiable Establishments",
    "sg:phone":"+33 4 50 48 23 83",
    "sg:province":"Rhone-Alpes",
    "wof:name":"Soci\u00e9t\u00e9 Des Fournitures Industrielles Billet Et Founier S.a.",
    "wof:placetype":"venue"
},
  "geometry": {"coordinates":[5.810697,46.121063],"type":"Point"}
}