{
  "type": "Feature",
  "properties": {
    "addr:full":"Rue de la Pompe - Les Rubeaux Lubersac Limousin 19210",
    "addr:postcode":"19210",
    "addr:street":"Rue De La Pompe Les;Lubersac Limousin",
    "iso:country":"FR",
    "sg:address":"Rue de la Pompe - Les Rubeaux",
    "sg:city":"Lubersac",
    "sg:orig_category":"Non-Classified Establishments",
    "sg:phone":"+33 5 55 73 50 16",
    "sg:postcode":"19210",
    "sg:province":"Limousin",
    "wof:name":"Pompes Denis S.a.r.l.",
    "wof:placetype":"venue"
},
  "geometry": {"coordinates":[1.450631,45.431385],"type":"Point"}
}