{
  "type": "Feature",
  "properties": {
    "iso:country":"FR",
    "sg:address":"615 Route De Caudan Z.A. De Kergoussel 56850 Caudan",
    "sg:city":"Caudan",
    "sg:classifiers":[
        {
            "category":"Manufacturing",
            "subcategory":"Paper Products",
            "type":"Manufacturing & Wholesale Goods"
        }
    ],
    "sg:phone":"+33 2 97 76 96 76",
    "sg:postcode":"56850",
    "sg:province":"Bretagne",
    "sg:tags":[
        "finished",
        "cardboard",
        "-"
    ],
    "wof:name":"Bopack T.e.a. Ouest",
    "wof:placetype":"venue"
},
  "geometry": {"coordinates":[-3.340384,47.810596],"type":"Point"}
}