{
  "type": "Feature",
  "properties": {
    "iso:country":"FR",
    "sg:address":"28 rue d'Athenes 13127 Vitrolles",
    "sg:classifiers":[
        {
            "category":"Government",
            "subcategory":"Department Of Motor Vehicles",
            "type":"Public Place"
        }
    ],
    "sg:phone":"+33 4 42 89 03 89",
    "sg:province":"Centre",
    "sg:tags":[
        "brake"
    ],
    "wof:name":"Electro Moteur Cura Et Fils S.a.r.l.",
    "wof:placetype":"venue"
},
  "geometry": {"coordinates":[5.240835,43.441357],"type":"Point"}
}