{
  "type": "Feature",
  "properties": {
    "addr:full":"7, rue Anne-Marie Terri\u00e8re - Z.I., 51520 Saint Martin sur le Pr\u00e9 Champagne",
    "addr:housenumber":"7",
    "addr:postcode":"51520",
    "addr:street":"Rue Anne-Marie Terrie\u0300Re;Martin Sur Le Pre\u0301 Champagne",
    "iso:country":"FR",
    "sg:address":"7, rue Anne-Marie Terri\u00e8re - Z.I., 51520 Saint Martin sur le Pr\u00e9",
    "sg:orig_category":"Unclassifiable Establishments",
    "sg:phone":"+33 3 26 68 34 39",
    "sg:province":"Champagne",
    "wof:name":"France Rabotage S.a.",
    "wof:placetype":"venue"
},
  "geometry": {"coordinates":[4.345948,48.98521],"type":"Point"}
}