{
  "type": "Feature",
  "properties": {
    "iso:country":"FR",
    "sg:address":"Ch\u00e2teau le Grand Verdus 33670 Sadirac",
    "sg:city":"Sadirac",
    "sg:orig_category":"Unclassifiable Establishments",
    "sg:phone":"+33 5 56 30 50 90",
    "sg:postcode":"33670",
    "sg:province":"Aquitaine",
    "wof:name":"Philippe Et Antoine Legrix De La Salle S.c.e.a.",
    "wof:placetype":"venue"
},
  "geometry": {"coordinates":[-0.371374,44.751328],"type":"Point"}
}