{
  "type": "Feature",
  "properties": {
    "addr:full":"18, Rue de la Bo\u00e9tie, 75008 Paris Ile de France",
    "addr:housenumber":"18",
    "addr:postcode":"75008",
    "addr:street":"Rue De La Boe\u0301Tie",
    "iso:country":"FR",
    "sg:address":"18, Rue de la Bo\u00e9tie, 75008 Paris",
    "sg:orig_category":"Unclassifiable Establishments",
    "sg:phone":"+33 1 42 65 90 90",
    "sg:province":"Ile de France",
    "wof:name":"Iteam S.a.s.",
    "wof:placetype":"venue"
},
  "geometry": {"coordinates":[2.316909,48.874229],"type":"Point"}
}