{
  "type": "Feature",
  "properties": {
    "addr:full":"5, Rue Jacques Coeur - ZI, 03400 Yzeure Yzeure Auvergne 03400",
    "addr:housenumber":"5",
    "addr:postcode":"03400;03400",
    "addr:street":"Rue Jacques Coeur",
    "iso:country":"FR",
    "sg:address":"5, Rue Jacques Coeur - ZI, 03400 Yzeure",
    "sg:city":"Yzeure",
    "sg:orig_category":"Unclassifiable Establishments",
    "sg:phone":"+33 4 70 44 16 95",
    "sg:postcode":"03400",
    "sg:province":"Auvergne",
    "wof:name":"Tison S.a.r.l.",
    "wof:placetype":"venue"
},
  "geometry": {"coordinates":[3.37215,46.573559],"type":"Point"}
}