{
  "type": "Feature",
  "properties": {
    "addr:full":"9, Rue Robert, 69006 Lyon Rhone-Alpes 69006",
    "addr:housenumber":"9",
    "addr:postcode":"69006;69006",
    "addr:street":"Rue Robert",
    "iso:country":"FR",
    "sg:address":"9, Rue Robert, 69006 Lyon",
    "sg:orig_category":"Non-Classified Establishments",
    "sg:phone":"+33 4 72 75 94 94",
    "sg:postcode":"69006",
    "sg:province":"Rhone-Alpes",
    "wof:name":"C.d.r.a. - Centre Du D\u00e9sign Rh\u00f4ne Alpes",
    "wof:placetype":"venue"
},
  "geometry": {"coordinates":[4.85147,45.764339],"type":"Point"}
}