{
  "type": "Feature",
  "properties": {
    "iso:country":"FR",
    "sg:address":"15 place Notre Dame; Bressuire; 79303",
    "sg:city":"Bressuire",
    "sg:classifiers":[
        {
            "category":"Banks & Credit Unions",
            "subcategory":"Bank",
            "type":"Services"
        }
    ],
    "sg:phone":"+33 5 49 65 13 44",
    "sg:postcode":"79300",
    "sg:province":"Poitou-Charentes",
    "wof:name":"Cr\u00e9dit Industriel, De L'ouest Sa",
    "wof:placetype":"venue"
},
  "geometry": {"coordinates":[-0.492404,46.841946],"type":"Point"}
}