{
  "type": "Feature",
  "properties": {
    "iso:country":"FR",
    "sg:address":"Rte de Puy la Roque",
    "sg:city":"Monteils",
    "sg:orig_category":"Non-Classified Establishments",
    "sg:phone":"+33 5 63 26 00 12",
    "sg:postcode":"82300",
    "sg:province":"Midi Pyr\u00e9n\u00e9es",
    "wof:name":"Sematec S.a. - Soci\u00e9t\u00e9 D'entreprise Transports Et Carri\u00e8res",
    "wof:placetype":"venue"
},
  "geometry": {"coordinates":[1.605065,44.145657],"type":"Point"}
}