{
  "type": "Feature",
  "properties": {
    "iso:country":"FR",
    "sg:address":"123, Rte de Lorient, 35000 Rennes",
    "sg:city":"Rennes",
    "sg:orig_category":"Unclassifiable Establishments",
    "sg:phone":"+33 2 99 59 87 59",
    "sg:postcode":"35000",
    "sg:province":"Bretagne",
    "wof:name":"Auto Omnica Industrie S.a.",
    "wof:placetype":"venue"
},
  "geometry": {"coordinates":[-1.717592,48.109226],"type":"Point"}
}