{
  "type": "Feature",
  "properties": {
    "iso:country":"FR",
    "sg:address":"3, Rue Louis Bl\u00e9riot, 68127 Sainte Croix en Plaine",
    "sg:city":"Sainte-Croix-en-Plaine",
    "sg:orig_category":"Unclassifiable Establishments",
    "sg:phone":"+33 3 89 22 03 10",
    "sg:postcode":"68127",
    "sg:province":"Alsace",
    "wof:name":"Fermoba Alsace S.a.r.l.",
    "wof:placetype":"venue"
},
  "geometry": {"coordinates":[7.38494,48.01791],"type":"Point"}
}