{
  "type": "Feature",
  "properties": {
    "iso:country":"FR",
    "sg:address":"Rte de Saint Denis",
    "sg:city":"Saint Pierre d'Ol\u00e9ron",
    "sg:orig_category":"Unclassifiable Establishments",
    "sg:phone":"+33 5 46 47 23 08",
    "sg:postcode":"17310",
    "sg:province":"Poitou-Charentes",
    "wof:name":"Sumaca Vm Distribution",
    "wof:placetype":"venue"
},
  "geometry": {"coordinates":[-1.309137,45.945873],"type":"Point"}
}