{
  "type": "Feature",
  "properties": {
    "iso:country":"FR",
    "sg:address":"Rue des Peupliers",
    "sg:city":"La Fert\u00e9 Mac\u00e9",
    "sg:orig_category":"Non-Classified Establishments",
    "sg:phone":"+33 2 33 30 36 80",
    "sg:postcode":"61600",
    "sg:province":"Basse Normandie",
    "wof:name":"S.e.v.p. S.a.",
    "wof:placetype":"venue"
},
  "geometry": {"coordinates":[-0.300768,48.54089],"type":"Point"}
}