{
  "type": "Feature",
  "properties": {
    "addr:full":"67730 Ch\u00e2tenois Ch\u00e2tenois Alsace 67730",
    "addr:postcode":"67730;67730",
    "iso:country":"FR",
    "sg:address":"67730 Ch\u00e2tenois",
    "sg:city":"Ch\u00e2tenois",
    "sg:orig_category":"Unclassifiable Establishments",
    "sg:phone":"+33 3 88 89 05 73",
    "sg:postcode":"67730",
    "sg:province":"Alsace",
    "wof:name":"Usinage Centre Alsace S.a.r.l.",
    "wof:placetype":"venue"
},
  "geometry": {"coordinates":[7.399195,48.271835],"type":"Point"}
}