{
  "type": "Feature",
  "properties": {
    "iso:country":"FR",
    "sg:address":"3, Square Gambetta, 11000 Carcassonne",
    "sg:orig_category":"Non-Classified Establishments",
    "sg:phone":"+33 4 67 65 12 30",
    "sg:postcode":"11000",
    "sg:province":"Languedoc-Roussillon",
    "wof:name":"Coredimag S.a.",
    "wof:placetype":"venue"
},
  "geometry": {"coordinates":[2.357604,43.211964],"type":"Point"}
}