{
  "type": "Feature",
  "properties": {
    "iso:country":"FR",
    "sg:address":"Bd Salvador Alliend\u00e9",
    "sg:city":"St Herblain",
    "sg:orig_category":"Unclassifiable Establishments",
    "sg:phone":"+33 2 40 92 00 05",
    "sg:postcode":"44800",
    "sg:province":"Pays de Loire",
    "wof:name":"Euromaster France",
    "wof:placetype":"venue"
},
  "geometry": {"coordinates":[-1.610474,47.216225],"type":"Point"}
}