{
  "type": "Feature",
  "properties": {
    "addr:full":"Av. Chateaubriand - Zone de Conditionnement Paimpol Bretagne 22500",
    "addr:postcode":"22500",
    "addr:street":"Av. Chateaubriand;De Conditionnement Paimpol Bretagne",
    "iso:country":"FR",
    "sg:address":"Av. Chateaubriand - Zone de Conditionnement",
    "sg:city":"Paimpol",
    "sg:orig_category":"Unclassifiable Establishments",
    "sg:phone":"+33 2 96 20 80 40",
    "sg:postcode":"22500",
    "sg:province":"Bretagne",
    "wof:name":"Soci\u00e9t\u00e9 D'exploitation Des Etablissements Marcel Libouban S.a.r.l.",
    "wof:placetype":"venue"
},
  "geometry": {"coordinates":[-3.028369,48.737778],"type":"Point"}
}