{
  "type": "Feature",
  "properties": {
    "addr:full":"24 blvd Carnot; Gu\u00e9ret; 23001 Bretagne",
    "addr:postcode":"23001",
    "addr:street":"24 Blvd Carnot",
    "iso:country":"FR",
    "sg:address":"24 blvd Carnot; Gu\u00e9ret; 23001",
    "sg:classifiers":[
        {
            "category":"Banks & Credit Unions",
            "subcategory":"Bank",
            "type":"Services"
        }
    ],
    "sg:phone":"+33 5 55 52 46 89",
    "sg:province":"Bretagne",
    "wof:name":"Banque De France",
    "wof:placetype":"venue"
},
  "geometry": {"coordinates":[1.870045,46.170536],"type":"Point"}
}