{
  "type": "Feature",
  "properties": {
    "iso:country":"FR",
    "sg:address":"11, Av. Marc Sangnier, 92398 Villeneuve la Garenne C\u00e9dex",
    "sg:city":"Vill\u00e9",
    "sg:orig_category":"Non-Classified Establishments",
    "sg:phone":"+33 1 41 21 01 00",
    "sg:postcode":"67220",
    "sg:province":"Alsace",
    "wof:name":"Amarie.net S.a.",
    "wof:placetype":"venue"
},
  "geometry": {"coordinates":[2.326712,48.926884],"type":"Point"}
}