{
  "type": "Feature",
  "properties": {
    "iso:country":"FR",
    "sg:address":"53, Rue de la Thibaudi\u00e8re, 69007 Lyon",
    "sg:orig_category":"Unclassifiable Establishments",
    "sg:phone":"+33 4 72 72 95 49",
    "sg:postcode":"69007",
    "sg:province":"Rhone-Alpes",
    "wof:name":"Agence Maritime Du Grand Delta S.a.r.l.",
    "wof:placetype":"venue"
},
  "geometry": {"coordinates":[4.847426,45.749481],"type":"Point"}
}