{
  "type": "Feature",
  "properties": {
    "iso:country":"FR",
    "sg:address":"LD LES CONCHES 85560 LONGEVILLE SUR MER",
    "sg:classifiers":[
        {
            "category":"Shopping",
            "subcategory":"Hobbies, Toys, & Games",
            "type":"Retail Goods"
        }
    ],
    "sg:phone":"+33 2 51 33 32 93",
    "sg:postcode":"85560",
    "sg:province":"Pays de Loire",
    "sg:tags":[
        "product",
        "miscellaneous",
        "entertainment"
    ],
    "wof:name":"Camping Des Dunes",
    "wof:placetype":"venue"
},
  "geometry": {"coordinates":[-1.470079,46.38797],"type":"Point"}
}