{
  "type": "Feature",
  "properties": {
    "addr:full":"Hameau De Farges 07630 Le B\u00e9age Rhone-Alpes 07630",
    "addr:postcode":"07630;07630",
    "addr:street":"Hameau De Farges;Be\u0301Age Rhone-Alpes",
    "iso:country":"FR",
    "sg:address":"Hameau De Farges 07630 Le B\u00e9age",
    "sg:classifiers":[
        {
            "category":"Professional",
            "type":"Services"
        }
    ],
    "sg:phone":"+33 4 75 38 85 47",
    "sg:postcode":"07630",
    "sg:province":"Rhone-Alpes",
    "sg:tags":[
        "-",
        "related",
        "road",
        "transport"
    ],
    "wof:name":"Redon Freres Sarl",
    "wof:placetype":"venue"
},
  "geometry": {"coordinates":[4.121611,44.848396],"type":"Point"}
}