{
  "type": "Feature",
  "properties": {
    "addr:full":"61, Rue du Rivage - R\u00e9sidence Plein Sud, 59190 Hazebrouck Nord Pas-de-Calais",
    "addr:housenumber":"61",
    "addr:postcode":"59190",
    "addr:street":"Rue Du Rivage Re\u0301Sidence Plein Sud",
    "iso:country":"FR",
    "sg:address":"61, Rue du Rivage - R\u00e9sidence Plein Sud, 59190 Hazebrouck",
    "sg:orig_category":"Unclassifiable Establishments",
    "sg:phone":"+33 3 28 50 93 80",
    "sg:province":"Nord Pas-de-Calais",
    "wof:name":"A.n.p.e.",
    "wof:placetype":"venue"
},
  "geometry": {"coordinates":[2.540582,50.720726],"type":"Point"}
}