{
  "type": "Feature",
  "properties": {
    "addr:full":"16, Rue Auguereau, 75007 Paris Ile de France",
    "addr:housenumber":"16",
    "addr:postcode":"75007",
    "addr:street":"Rue Auguereau",
    "iso:country":"FR",
    "sg:address":"16, Rue Auguereau, 75007 Paris",
    "sg:orig_category":"Unclassifiable Establishments",
    "sg:phone":"+33 1 40 62 65 30",
    "sg:province":"Ile de France",
    "wof:name":"C.i.m.e.r. S.a.r.l. - Centrale D'importation D'exportation Et De Repr\u00e9sentation",
    "wof:placetype":"venue"
},
  "geometry": {"coordinates":[2.30202,48.856998],"type":"Point"}
}