{
  "type": "Feature",
  "properties": {
    "iso:country":"FR",
    "sg:address":"65 Rue Du Fond 74460 Marnaz",
    "sg:classifiers":[
        {
            "category":"Manufacturing",
            "subcategory":"Metals",
            "type":"Manufacturing & Wholesale Goods"
        }
    ],
    "sg:phone":"+33 4 50 98 35 74",
    "sg:postcode":"74460",
    "sg:province":"Rhone-Alpes",
    "sg:tags":[
        "metallurgy",
        "metalworking",
        "processing"
    ],
    "wof:name":"Parroche Et Dorioz (ets) Sa",
    "wof:placetype":"venue"
},
  "geometry": {"coordinates":[6.521463,46.060986],"type":"Point"}
}