{
  "type": "Feature",
  "properties": {
    "iso:country":"FR",
    "sg:address":"60 Av Des Gobelins 75013 Paris",
    "sg:classifiers":[
        {
            "category":"Professional",
            "subcategory":"Advertising",
            "type":"Services"
        }
    ],
    "sg:phone":"+33 1 45 35 10 10",
    "sg:postcode":"75013",
    "sg:province":"Ile de France",
    "sg:tags":[
        "information",
        "medium",
        "communication"
    ],
    "wof:name":"Megaphot Sarl",
    "wof:placetype":"venue"
},
  "geometry": {"coordinates":[2.35388,48.833538],"type":"Point"}
}