{
  "type": "Feature",
  "properties": {
    "iso:country":"FR",
    "sg:address":"88 Route D Auvers 95300 Pontoise",
    "sg:classifiers":[
        {
            "category":"Home & Garden",
            "subcategory":"Furniture",
            "type":"Retail Goods"
        }
    ],
    "sg:phone":"+33 1 30 38 58 23",
    "sg:postcode":"95300",
    "sg:province":"Ile de France",
    "sg:tags":[
        "household",
        "wood"
    ],
    "wof:name":"Mixit Creation",
    "wof:placetype":"venue"
},
  "geometry": {"coordinates":[2.124823,49.064194],"type":"Point"}
}