{
  "type": "Feature",
  "properties": {
    "iso:country":"FR",
    "sg:address":"16 Route Lazy 45730 ST BENOIT SUR LOIRE",
    "sg:city":"Saint-Beno\u00eet-sur-Loire",
    "sg:classifiers":[
        {
            "category":"Food & Beverages",
            "subcategory":"Groceries & Convenience Stores",
            "type":"Retail Goods"
        }
    ],
    "sg:phone":"+33 2 38 35 74 57",
    "sg:postcode":"45730",
    "sg:province":"Centre",
    "sg:tags":[
        "fresh"
    ],
    "wof:name":"B.t.g. Bouthegourd S.a.",
    "wof:placetype":"venue"
},
  "geometry": {"coordinates":[2.318738,47.793568],"type":"Point"}
}