{
  "type": "Feature",
  "properties": {
    "iso:country":"FR",
    "sg:address":"198 Avenue Victor Hugo",
    "sg:city":"Paris",
    "sg:classifiers":[
        {
            "category":"Banks & Credit Unions",
            "subcategory":"Financial Services",
            "type":"Services"
        }
    ],
    "sg:phone":"+33 1 45 04 61 73",
    "sg:postcode":"75116",
    "sg:province":"Ile de France",
    "sg:tags":[
        "banking",
        "finance",
        "insurance"
    ],
    "wof:name":"Funck-brentano & Partners",
    "wof:placetype":"venue"
},
  "geometry": {"coordinates":[2.273276,48.864716],"type":"Point"}
}