{
  "type": "Feature",
  "properties": {
    "addr:full":"41 Rue Du 11 Novembre 1918 51300 Vitry Le Fran\u00e7ois Champagne 51300",
    "addr:housenumber":"41",
    "addr:postcode":"51300;51300",
    "addr:street":"Rue Du 11 Novembre 1918;Franc\u0327Ois Champagne",
    "iso:country":"FR",
    "sg:address":"41 Rue Du 11 Novembre 1918 51300 Vitry Le Fran\u00e7ois",
    "sg:classifiers":[
        {
            "category":"Shopping",
            "subcategory":"Clothing, Apparel, & Fashions",
            "type":"Retail Goods"
        }
    ],
    "sg:phone":"+33 3 26 74 19 46",
    "sg:postcode":"51300",
    "sg:province":"Champagne",
    "sg:tags":[
        "textile",
        "clothing",
        "clothes"
    ],
    "wof:name":"Bonneterie Tran Sa",
    "wof:placetype":"venue"
},
  "geometry": {"coordinates":[4.58507,48.717106],"type":"Point"}
}