{
  "type": "Feature",
  "properties": {
    "iso:country":"FR",
    "sg:address":"31, Place Ronde - Espace 21, 92986 Paris la D\u00e9fense C\u00e9dex 7",
    "sg:orig_category":"Non-Classified Establishments",
    "sg:phone":"+33 1 49 00 31 31",
    "sg:province":"Midi Pyr\u00e9n\u00e9es",
    "wof:name":"Arinso France S.a.",
    "wof:placetype":"venue"
},
  "geometry": {"coordinates":[2.24119,48.888939],"type":"Point"}
}