{
  "type": "Feature",
  "properties": {
    "addr:full":"B.P. 129, 13321 Marseille C\u00e9dex 16^^36, Bd Emmanuel Eydoux - Gare de Marchandise de l'Estaque, 13016 Poitou-Charentes",
    "addr:housenumber":"b.p. 129;16 ^ ^ 36",
    "addr:postcode":"13321;13016",
    "addr:street":"Ce\u0301Dex;Bd Emmanuel Eydoux Gare De Marchandise De L'Estaque",
    "iso:country":"FR",
    "sg:address":"B.P. 129, 13321 Marseille C\u00e9dex 16^^36, Bd Emmanuel Eydoux - Gare de Marchandise de l'Estaque, 13016",
    "sg:orig_category":"Non-Classified Establishments",
    "sg:phone":"+33 4 91 46 67 67",
    "sg:province":"Poitou-Charentes",
    "wof:name":"Dehon Service S.a.",
    "wof:placetype":"venue"
},
  "geometry": {"coordinates":[5.30825,43.364422],"type":"Point"}
}