{
  "type": "Feature",
  "properties": {
    "iso:country":"FR",
    "sg:address":"B.P. 129, 13321 Marseille C\u00e9dex 16^^36, Bd Emmanuel Eydoux - Gare de Marchandise de l'Estaque, 13016",
    "sg:orig_category":"Non-Classified Establishments",
    "sg:phone":"+33 4 91 46 67 67",
    "sg:province":"Poitou-Charentes",
    "wof:name":"Dehon Service S.a.",
    "wof:placetype":"venue"
},
  "geometry": {"coordinates":[5.30825,43.364422],"type":"Point"}
}