{
  "type": "Feature",
  "properties": {
    "iso:country":"FR",
    "sg:address":"419 rue Guynemer 59680 Ferriere la Grande",
    "sg:classifiers":[
        {
            "category":"Manufacturing",
            "subcategory":"Motor Vehicles & Parts",
            "type":"Manufacturing & Wholesale Goods"
        }
    ],
    "sg:phone":"+33 3 27 62 05 59",
    "sg:province":"Nord Pas-de-Calais",
    "sg:tags":[
        "precision",
        "mechanic"
    ],
    "wof:name":"Allard Sarl",
    "wof:placetype":"venue"
},
  "geometry": {"coordinates":[3.994905,50.253494],"type":"Point"}
}