{
  "type": "Feature",
  "properties": {
    "iso:country":"FR",
    "sg:address":"B.P. 70, 23300 La Souterraine^^15, Rte de Limoges, 23300 La Souterraine",
    "sg:orig_category":"Non-Classified Establishments",
    "sg:phone":"+33 5 55 63 72 45",
    "sg:postcode":"23300",
    "sg:province":"Limousin",
    "wof:name":"Carrefour Du Bois Limousin S.a.r.l.",
    "wof:placetype":"venue"
},
  "geometry": {"coordinates":[1.53526,46.201057],"type":"Point"}
}