{
  "type": "Feature",
  "properties": {
    "iso:country":"FR",
    "sg:address":"av. de l'Europe",
    "sg:city":"Draveil",
    "sg:orig_category":"Non-Classified Establishments",
    "sg:phone":"+33 1 69 03 40 18",
    "sg:postcode":"91210",
    "sg:province":"Ile de France",
    "wof:name":"Marquant Pacholczyk S.a.",
    "wof:placetype":"venue"
},
  "geometry": {"coordinates":[2.428945,48.681461],"type":"Point"}
}