{
  "type": "Feature",
  "properties": {
    "iso:country":"FR",
    "sg:address":"15 Rue Du Docteur Roux 94600 Choisy Le Roi",
    "sg:classifiers":[
        {
            "category":"Professional",
            "subcategory":"Business Services",
            "type":"Services"
        }
    ],
    "sg:phone":"+33 1 46 81 75 00",
    "sg:postcode":"94600",
    "sg:province":"Ile de France",
    "sg:tags":[
        "travel",
        "fair"
    ],
    "wof:name":"Ades Organisation Sarl",
    "wof:placetype":"venue"
},
  "geometry": {"coordinates":[2.408183,48.771324],"type":"Point"}
}