{
  "type": "Feature",
  "properties": {
    "addr:full":"33 Rue Raymond Losserand; Paris Champagne",
    "addr:housenumber":"33",
    "addr:street":"Rue Raymond Losserand",
    "iso:country":"FR",
    "sg:address":"33 Rue Raymond Losserand; Paris",
    "sg:classifiers":[
        {
            "category":"Travel",
            "subcategory":"Travel Agent",
            "type":"Entertainment"
        }
    ],
    "sg:province":"Champagne",
    "wof:name":"Best Western Hotel Bretagne Montparnasse",
    "wof:placetype":"venue"
},
  "geometry": {"coordinates":[2.320842,48.83522],"type":"Point"}
}