{
  "type": "Feature",
  "properties": {
    "addr:full":"Rue Monge - ZI la Motte Portes l\u00e8s Valence Rhone-Alpes 26800",
    "addr:postcode":"26800",
    "addr:street":"Rue Monge Zi La Motte",
    "iso:country":"FR",
    "sg:address":"Rue Monge - ZI la Motte",
    "sg:city":"Portes l\u00e8s Valence",
    "sg:orig_category":"Unclassifiable Establishments",
    "sg:phone":"+33 4 75 57 44 99",
    "sg:postcode":"26800",
    "sg:province":"Rhone-Alpes",
    "wof:name":"Transports Graveleau S.a.",
    "wof:placetype":"venue"
},
  "geometry": {"coordinates":[4.871505,44.877972],"type":"Point"}
}