{
  "type": "Feature",
  "properties": {
    "addr:full":"9, Rue de la Fontaine Grill\u00e9e - ZI Nord, 44690 La Haie Fouassi\u00e8re Pays de Loire",
    "addr:housenumber":"9",
    "addr:postcode":"44690",
    "addr:street":"Rue De La Fontaine Grille\u0301E Zi Nord;Haie Fouassie\u0300Re",
    "iso:country":"FR",
    "sg:address":"9, Rue de la Fontaine Grill\u00e9e - ZI Nord, 44690 La Haie Fouassi\u00e8re",
    "sg:orig_category":"Non-Classified Establishments",
    "sg:phone":"+33 2 51 71 61 20",
    "sg:province":"Pays de Loire",
    "wof:name":"Kardex S.a.",
    "wof:placetype":"venue"
},
  "geometry": {"coordinates":[-1.384839,47.097115],"type":"Point"}
}