{
  "type": "Feature",
  "properties": {
    "iso:country":"FR",
    "sg:address":"49, Rue Francis Combe, 95000 Cergy",
    "sg:orig_category":"Non-Classified Establishments",
    "sg:phone":"+33 1 30 30 11 85",
    "sg:province":"Ile de France",
    "wof:name":"L.t.i. S.a.r.l. - Lef\u00e8bvre T\u00f4lerie Industrielle",
    "wof:placetype":"venue"
},
  "geometry": {"coordinates":[2.071726,49.045616],"type":"Point"}
}