{
  "type": "Feature",
  "properties": {
    "addr:full":"Zac De Calmont 12450 La Primaube Midi Pyr\u00e9n\u00e9es 12450",
    "addr:postcode":"12450;12450",
    "addr:street":"Zac De Calmont",
    "iso:country":"FR",
    "sg:address":"Zac De Calmont 12450 La Primaube",
    "sg:classifiers":[
        {
            "category":"Farming",
            "subcategory":"Livestock Farm",
            "type":"Manufacturing & Wholesale Goods"
        }
    ],
    "sg:phone":"+33 5 65 70 18 54",
    "sg:postcode":"12450",
    "sg:province":"Midi Pyr\u00e9n\u00e9es",
    "sg:tags":[
        "horticulture",
        "pharmaceutical",
        "-",
        "chemical",
        "chemistry",
        "agriculture",
        "by-product"
    ],
    "wof:name":"Ragt",
    "wof:placetype":"venue"
},
  "geometry": {"coordinates":[2.55903,44.292271],"type":"Point"}
}