{
  "type": "Feature",
  "properties": {
    "addr:full":"8, Rue Joffre, 62114 Sains en Gohelle Nord Pas-de-Calais",
    "addr:housenumber":"8",
    "addr:postcode":"62114;en",
    "addr:street":"Rue Joffre",
    "iso:country":"FR",
    "sg:address":"8, Rue Joffre, 62114 Sains en Gohelle",
    "sg:orig_category":"Unclassifiable Establishments",
    "sg:phone":"+33 3 21 29 79 30",
    "sg:province":"Nord Pas-de-Calais",
    "wof:name":"Sogemi S.a.r.l.",
    "wof:placetype":"venue"
},
  "geometry": {"coordinates":[2.686711,50.45002],"type":"Point"}
}