{
  "type": "Feature",
  "properties": {
    "iso:country":"FR",
    "sg:address":"B.P. 6, 72301 Sabl\u00e9 sur Sarthe C\u00e9dex^^Rte du Mans - ZI la Tuilerie, 72300 Sabl\u00e9 sur Sarthe",
    "sg:orig_category":"Non-Classified Establishments",
    "sg:phone":"+33 2 43 95 00 74",
    "sg:postcode":"72300",
    "sg:province":"Pays de Loire",
    "wof:name":"B.v.s. S.a. - Boulonneries Et Visseries De Sabl\u00e9",
    "wof:placetype":"venue"
},
  "geometry": {"coordinates":[-0.326529,47.731071],"type":"Point"}
}