{
  "type": "Feature",
  "properties": {
    "iso:country":"FR",
    "sg:address":"21, Av. Genottes, 95800 Cergy",
    "sg:orig_category":"Unclassifiable Establishments",
    "sg:phone":"+33 1 30 75 92 59",
    "sg:province":"Ile de France",
    "wof:name":"S.m.i.a.g. S.a.r.l. - Soci\u00e9t\u00e9 De Math\u00e9matique Informatique Appliqu\u00e9e \u00e0 La Gestion",
    "wof:placetype":"venue"
},
  "geometry": {"coordinates":[2.036415,49.046783],"type":"Point"}
}