{
  "type": "Feature",
  "properties": {
    "addr:full":"B.P. 1507, 38025 Grenoble C\u00e9dex 1^^3, Av. Doyen Louis Weil - Immeuble Grenat, 38000 Grenoble Rhone-Alpes",
    "addr:housenumber":"1507;1;^",
    "addr:postcode":"38025;38000",
    "addr:street":"B.P.;^;Av. Doyen Louis Weil;Grenat",
    "iso:country":"FR",
    "sg:address":"B.P. 1507, 38025 Grenoble C\u00e9dex 1^^3, Av. Doyen Louis Weil - Immeuble Grenat, 38000 Grenoble",
    "sg:orig_category":"Non-Classified Establishments",
    "sg:phone":"+33 4 76 84 27 40",
    "sg:province":"Rhone-Alpes",
    "wof:name":"I.d. 9 Prima S.a.",
    "wof:placetype":"venue"
},
  "geometry": {"coordinates":[5.732003,45.193989],"type":"Point"}
}