{
  "type": "Feature",
  "properties": {
    "addr:full":"Rue Jean Bovin Tourlaville Basse Normandie 50110",
    "addr:postcode":"50110",
    "addr:street":"Rue Jean Bovin",
    "iso:country":"FR",
    "sg:address":"Rue Jean Bovin",
    "sg:city":"Tourlaville",
    "sg:orig_category":"Unclassifiable Establishments",
    "sg:phone":"+33 2 33 88 51 00",
    "sg:postcode":"50110",
    "sg:province":"Basse Normandie",
    "wof:name":"S.t.n. S.a. - Soci\u00e9t\u00e9 De Transports De Normandie",
    "wof:placetype":"venue"
},
  "geometry": {"coordinates":[-1.586187,49.628098],"type":"Point"}
}