{
  "type": "Feature",
  "properties": {
    "iso:country":"FR",
    "sg:address":"187, Rue Edouard Branly, 93106 Montreuil C\u00e9dex",
    "sg:orig_category":"Non-Classified Establishments",
    "sg:phone":"+33 1 48 54 49 91",
    "sg:province":"Poitou-Charentes",
    "wof:name":"Safe S.a.",
    "wof:placetype":"venue"
},
  "geometry": {"coordinates":[2.464411,48.876163],"type":"Point"}
}