{
  "type": "Feature",
  "properties": {
    "iso:country":"FR",
    "sg:address":"Rue Democrite",
    "sg:city":"Le Mans",
    "sg:orig_category":"Non-Classified Establishments",
    "sg:phone":"+33 2 43 39 94 40",
    "sg:postcode":"72000",
    "sg:province":"Pays de Loire",
    "wof:name":"Soci\u00e9t\u00e9 Etude Recherche Ing\u00e9nierie Pharmaceutique S.a.",
    "wof:placetype":"venue"
},
  "geometry": {"coordinates":[0.154087,48.017494],"type":"Point"}
}