{
  "type": "Feature",
  "properties": {
    "iso:country":"FR",
    "sg:address":"Bizac 43370 Le Brignon",
    "sg:city":"Le Brignon",
    "sg:classifiers":[
        {
            "category":"Government",
            "subcategory":"Department Of Motor Vehicles",
            "type":"Public Place"
        }
    ],
    "sg:phone":"+33 4 71 03 96 71",
    "sg:postcode":"43370",
    "sg:province":"Auvergne",
    "sg:tags":[
        "equipment",
        "industrial",
        "transport",
        "motor-cars"
    ],
    "wof:name":"Auto Pieces 43",
    "wof:placetype":"venue"
},
  "geometry": {"coordinates":[3.84733,44.946484],"type":"Point"}
}