{
  "type": "Feature",
  "properties": {
    "addr:full":"B.P. 191, 17308 Rochefort C\u00e9dex^^2, Av. du Pont neuf, 17300 Rochefort Poitou-Charentes 17300",
    "addr:housenumber":"b.p. 191",
    "addr:postcode":"17308;17300 rochefort;17300",
    "addr:street":"Av. Du Pont Neuf",
    "iso:country":"FR",
    "sg:address":"B.P. 191, 17308 Rochefort C\u00e9dex^^2, Av. du Pont neuf, 17300 Rochefort",
    "sg:orig_category":"Non-Classified Establishments",
    "sg:phone":"+33 5 46 82 31 20",
    "sg:postcode":"17300",
    "sg:province":"Poitou-Charentes",
    "wof:name":"Cittram Littoral S.n.c.",
    "wof:placetype":"venue"
},
  "geometry": {"coordinates":[-0.958704,45.934818],"type":"Point"}
}