{
  "type": "Feature",
  "properties": {
    "addr:full":"B.P. 23, 71250 Cluny C\u00e9dex^^7, Av Charles de Gaulle, 71250 Cluny Cluny Bourgogne 71250",
    "addr:postcode":"71250;71250;71250",
    "addr:street":"B.P. 23;Av Charles De Gaulle",
    "iso:country":"FR",
    "sg:address":"B.P. 23, 71250 Cluny C\u00e9dex^^7, Av Charles de Gaulle, 71250 Cluny",
    "sg:city":"Cluny",
    "sg:orig_category":"Non-Classified Establishments",
    "sg:phone":"+33 3 85 59 55 66",
    "sg:postcode":"71250",
    "sg:province":"Bourgogne",
    "wof:name":"Oxxo S.a.",
    "wof:placetype":"venue"
},
  "geometry": {"coordinates":[4.618545,46.388313],"type":"Point"}
}