{
  "type": "Feature",
  "properties": {
    "addr:full":"1, Rue Robert Schuman, 13700 Marignane Provence-Alpes-C\u00f4te d'Azur",
    "addr:housenumber":"1",
    "addr:postcode":"13700",
    "addr:street":"Rue Robert Schuman",
    "iso:country":"FR",
    "sg:address":"1, Rue Robert Schuman, 13700 Marignane",
    "sg:orig_category":"Non-Classified Establishments",
    "sg:phone":"+33 4 42 88 78 67",
    "sg:province":"Provence-Alpes-C\u00f4te d'Azur",
    "wof:name":"Fontani S.a.r.l.",
    "wof:placetype":"venue"
},
  "geometry": {"coordinates":[5.210746,43.40633],"type":"Point"}
}