{
  "type": "Feature",
  "properties": {
    "addr:full":"239, Rue Saint Honor\u00e9, 75001 Paris Ile de France",
    "addr:housenumber":"239",
    "addr:postcode":"75001",
    "addr:street":"Rue Saint Honore\u0301",
    "iso:country":"FR",
    "sg:address":"239, Rue Saint Honor\u00e9, 75001 Paris",
    "sg:orig_category":"Non-Classified Establishments",
    "sg:phone":"+33 1 42 44 50 00",
    "sg:province":"Ile de France",
    "wof:name":"Saint Honor\u00e9 S.a.",
    "wof:placetype":"venue"
},
  "geometry": {"coordinates":[2.328071,48.866642],"type":"Point"}
}