{
  "type": "Feature",
  "properties": {
    "iso:country":"FR",
    "sg:address":"16, Rue de la D\u00e9fense, 92130 Issy les Moulineaux",
    "sg:orig_category":"Non-Classified Establishments",
    "sg:phone":"+33 1 46 62 90 11",
    "sg:province":"Ile de France",
    "wof:name":"Laboratoires Natt Fr\u00e8res S.a.r.l.",
    "wof:placetype":"venue"
},
  "geometry": {"coordinates":[2.260223,48.819149],"type":"Point"}
}