{
  "type": "Feature",
  "properties": {
    "addr:full":"4, Rue Faskrudfiord, 59430 Fort Mardyck Nord Pas-de-Calais",
    "addr:housenumber":"4",
    "addr:postcode":"59430",
    "addr:street":"Rue Faskrudfiord;Fort",
    "iso:country":"FR",
    "sg:address":"4, Rue Faskrudfiord, 59430 Fort Mardyck",
    "sg:orig_category":"Unclassifiable Establishments",
    "sg:phone":"+33 3 28 27 25 00",
    "sg:province":"Nord Pas-de-Calais",
    "wof:name":"T.s.c.t. S.a. - Travaux De Soudure Chaudronnerie Tuyauterie",
    "wof:placetype":"venue"
},
  "geometry": {"coordinates":[2.309159,51.032604],"type":"Point"}
}