{
  "type": "Feature",
  "properties": {
    "iso:country":"FR",
    "sg:address":"Kerroncou 29140 Saint Yvy",
    "sg:city":"Melgven",
    "sg:orig_category":"Non-Classified Establishments",
    "sg:phone":"+33 2 98 94 70 89",
    "sg:postcode":"29140",
    "sg:province":"Bretagne",
    "wof:name":"P\u00e9pini\u00e8res Le Meur S.a.r.l.",
    "wof:placetype":"venue"
},
  "geometry": {"coordinates":[-3.952024,47.965279],"type":"Point"}
}