{
  "type": "Feature",
  "properties": {
    "iso:country":"FR",
    "sg:address":"253, Bd du Mont Boron, 06300 Nice",
    "sg:orig_category":"Non-Classified Establishments",
    "sg:phone":"+33 4 92 00 82 92",
    "sg:province":"Franche Comt\u00e9",
    "wof:name":"Cera Technologies S.a.r.l.",
    "wof:placetype":"venue"
},
  "geometry": {"coordinates":[7.291881,43.7047],"type":"Point"}
}