{
  "type": "Feature",
  "properties": {
    "iso:country":"FR",
    "sg:address":"35, Rue des Usines, 44100 Nantes",
    "sg:orig_category":"Unclassifiable Establishments",
    "sg:phone":"+33 2 40 95 60 60",
    "sg:province":"Pays de Loire",
    "wof:name":"Sonastock S.a.",
    "wof:placetype":"venue"
},
  "geometry": {"coordinates":[-1.596671,47.196156],"type":"Point"}
}