{
  "type": "Feature",
  "properties": {
    "addr:full":"Zi St James 14290 St Cyr Du Ronceray Cernay Basse Normandie 14290",
    "addr:postcode":"14290;14290",
    "addr:street":"Zi St;Ronceray;Basse",
    "iso:country":"FR",
    "sg:address":"Zi St James 14290 St Cyr Du Ronceray",
    "sg:city":"Cernay",
    "sg:classifiers":[
        {
            "category":"Wholesale",
            "subcategory":"Machinery & Supplies",
            "type":"Manufacturing & Wholesale Goods"
        }
    ],
    "sg:phone":"+33 2 31 63 61 94",
    "sg:postcode":"14290",
    "sg:province":"Basse Normandie",
    "sg:tags":[
        "handling",
        "material",
        "-",
        "machine",
        "equipment",
        "engineering",
        "mechanical"
    ],
    "wof:name":"Sarl Multi Services Rolls (msr)",
    "wof:placetype":"venue"
},
  "geometry": {"coordinates":[0.296556,49.054707],"type":"Point"}
}