{
  "type": "Feature",
  "properties": {
    "iso:country":"FR",
    "sg:address":"1 Rue Saint Eloi 59200 Tourcoing",
    "sg:classifiers":[
        {
            "category":"Manufacturing",
            "subcategory":"Paper Products",
            "type":"Manufacturing & Wholesale Goods"
        }
    ],
    "sg:phone":"+33 3 20 12 80 80",
    "sg:province":"Nord Pas-de-Calais",
    "sg:tags":[
        "raw",
        "material",
        "-",
        "cardboard"
    ],
    "wof:name":"Etablissements G Petit",
    "wof:placetype":"venue"
},
  "geometry": {"coordinates":[3.164949,50.713024],"type":"Point"}
}