{
  "type": "Feature",
  "properties": {
    "iso:country":"FR",
    "sg:address":"14, Rue Beaus\u00e9jour, 49740 La Romagne",
    "sg:orig_category":"Non-Classified Establishments",
    "sg:phone":"+33 2 41 70 26 26",
    "sg:postcode":"49740",
    "sg:province":"Pays de Loire",
    "wof:name":"Brin Bertrand S.a.",
    "wof:placetype":"venue"
},
  "geometry": {"coordinates":[-1.025794,47.057892],"type":"Point"}
}