{
  "type": "Feature",
  "properties": {
    "addr:full":"36 Rue D'Alsace Lorraine 70000 Vesoul Franche Comt\u00e9 70000",
    "addr:housenumber":"36",
    "addr:postcode":"70000;70000",
    "addr:street":"Rue D'Alsace Lorraine;Franche Comte\u0301",
    "iso:country":"FR",
    "sg:address":"36 Rue D'Alsace Lorraine 70000 Vesoul",
    "sg:classifiers":[
        {
            "category":"Banks & Credit Unions",
            "subcategory":"Financial Services",
            "type":"Services"
        }
    ],
    "sg:phone":"+33 3 84 97 02 71",
    "sg:postcode":"70000",
    "sg:province":"Franche Comt\u00e9",
    "sg:tags":[
        "banking",
        "insurance",
        "institution",
        "finance"
    ],
    "wof:name":"Credit Lyonnais",
    "wof:placetype":"venue"
},
  "geometry": {"coordinates":[6.155829,47.622028],"type":"Point"}
}