{
  "type": "Feature",
  "properties": {
    "addr:full":"Cd 57 13530 Trets",
    "addr:postcode":"13530",
    "addr:street":"Cd 57",
    "iso:country":"FR",
    "sg:address":"Cd 57 13530 Trets",
    "sg:classifiers":[
        {
            "category":"Food Court",
            "type":"Food & Drink"
        }
    ],
    "sg:phone":"+33 4 42 29 21 59",
    "sg:tags":[
        "product",
        "related"
    ],
    "wof:name":"Mas De Cadenet Earl",
    "wof:placetype":"venue"
},
  "geometry": {"coordinates":[5.68379,43.447651],"type":"Point"}
}