{
  "type": "Feature",
  "properties": {
    "addr:full":"25 rue Edouard Delanglade 13006 Marseille Midi Pyr\u00e9n\u00e9es",
    "addr:housenumber":"25",
    "addr:postcode":"13006",
    "addr:street":"Rue Edouard Delanglade",
    "iso:country":"FR",
    "sg:address":"25 rue Edouard Delanglade 13006 Marseille",
    "sg:classifiers":[
        {
            "category":"Utilities",
            "subcategory":"Water",
            "type":"Services"
        }
    ],
    "sg:phone":"+33 4 91 57 60 60",
    "sg:province":"Midi Pyr\u00e9n\u00e9es",
    "sg:tags":[
        "waters",
        "natural",
        "mineral"
    ],
    "wof:name":"Eaux De Marseille Distribution S.a.",
    "wof:placetype":"venue"
},
  "geometry": {"coordinates":[5.374128,43.288784],"type":"Point"}
}