{
  "type": "Feature",
  "properties": {
    "addr:full":"74, Rue Paul Kimpe, 59260 Hellemmes Nord Pas-de-Calais 59260",
    "addr:housenumber":"74",
    "addr:postcode":"59260;59260",
    "addr:street":"Rue Paul Kimpe;Hellemmes Nord",
    "iso:country":"FR",
    "sg:address":"74, Rue Paul Kimpe, 59260 Hellemmes",
    "sg:orig_category":"Non-Classified Establishments",
    "sg:phone":"+33 6 86 86 43 43",
    "sg:postcode":"59260",
    "sg:province":"Nord Pas-de-Calais",
    "wof:name":"A.m.d. Conseil",
    "wof:placetype":"venue"
},
  "geometry": {"coordinates":[3.101946,50.618664],"type":"Point"}
}