{
  "type": "Feature",
  "properties": {
    "iso:country":"FR",
    "sg:address":"354, Av. Georges Cl\u00e9menceau, 92000 Nanterre",
    "sg:orig_category":"Non-Classified Establishments",
    "sg:phone":"+33 1 46 25 07 00",
    "sg:province":"Ile de France",
    "wof:name":"Stellimex S.a.",
    "wof:placetype":"venue"
},
  "geometry": {"coordinates":[2.223668,48.885208],"type":"Point"}
}