{
  "type": "Feature",
  "properties": {
    "addr:full":"B.P. 53, 78512 Rambouillet C\u00e9dex^^39, Rue Gustave Eiffel - ZI du Bel Air, 78120 Rambouillet Ile de France",
    "addr:postcode":"78512;78120;ile",
    "addr:street":"B.P. 53;Rue Gustave Eiffel Zi Du Bel Air",
    "iso:country":"FR",
    "sg:address":"B.P. 53, 78512 Rambouillet C\u00e9dex^^39, Rue Gustave Eiffel - ZI du Bel Air, 78120 Rambouillet",
    "sg:orig_category":"Non-Classified Establishments",
    "sg:phone":"+33 1 30 46 58 58",
    "sg:province":"Ile de France",
    "wof:name":"S.t.i. S.a.r.l. - Soci\u00e9t\u00e9 Des Techniques Innovantes",
    "wof:placetype":"venue"
},
  "geometry": {"coordinates":[1.826199,48.643406],"type":"Point"}
}