{
  "type": "Feature",
  "properties": {
    "iso:country":"FR",
    "sg:address":"168-170 Bd De Can\u00e9linat 92240 Malakoff",
    "sg:classifiers":[
        {
            "category":"Building & Trades",
            "subcategory":"Electrical",
            "type":"Services"
        }
    ],
    "sg:phone":"+33 1 41 17 48 50",
    "sg:postcode":"92240",
    "sg:province":"Ile de France",
    "sg:tags":[
        "electronic",
        "lighting",
        "equipment"
    ],
    "wof:name":"Adb Sas",
    "wof:placetype":"venue"
},
  "geometry": {"coordinates":[2.299999,48.811604],"type":"Point"}
}