{
  "type": "Feature",
  "properties": {
    "addr:full":"25, Rue de Vauzelles, 58000 Nevers Nevers Bourgogne 58000",
    "addr:housenumber":"25",
    "addr:postcode":"58000;58000",
    "addr:street":"Rue De Vauzelles",
    "iso:country":"FR",
    "sg:address":"25, Rue de Vauzelles, 58000 Nevers",
    "sg:city":"Nevers",
    "sg:orig_category":"Unclassifiable Establishments",
    "sg:phone":"+33 3 86 57 10 52",
    "sg:postcode":"58000",
    "sg:province":"Bourgogne",
    "wof:name":"Imprimerie Normalis\u00e9e S.a.r.l.",
    "wof:placetype":"venue"
},
  "geometry": {"coordinates":[3.153378,47.001755],"type":"Point"}
}