{
  "type": "Feature",
  "properties": {
    "iso:country":"FR",
    "sg:address":"39, Rue Centrale, 74940 Annecy le Vieux",
    "sg:orig_category":"Unclassifiable Establishments",
    "sg:phone":"+33 4 50 23 26 00",
    "sg:province":"Rhone-Alpes",
    "wof:name":"Carrier Sabli\u00e8res S.a.",
    "wof:placetype":"venue"
},
  "geometry": {"coordinates":[6.147569,45.906834],"type":"Point"}
}