{
  "type": "Feature",
  "properties": {
    "addr:full":"route de la Verrie 85290 St Laurent Sur Sevre Pays de Loire 85290",
    "addr:postcode":"85290;85290",
    "addr:street":"Route De La Verrie;St Laurent Sur Sevre Pays",
    "iso:country":"FR",
    "sg:address":"route de la Verrie 85290 St Laurent Sur Sevre",
    "sg:classifiers":[
        {
            "category":"Autos & Motor Vehicles",
            "subcategory":"Auto Supplies",
            "type":"Retail Goods"
        }
    ],
    "sg:phone":"+33 2 51 64 62 00",
    "sg:postcode":"85290",
    "sg:province":"Pays de Loire",
    "sg:tags":[
        "electric"
    ],
    "wof:name":"Jideco-equip Elect Electronique Europ\u00e9en Sa",
    "wof:placetype":"venue"
},
  "geometry": {"coordinates":[-0.882062,46.955406],"type":"Point"}
}