{
  "type": "Feature",
  "properties": {
    "addr:full":"Malmussou Bas 24260 Le Bugue Le Bugue Aquitaine 24260",
    "addr:housenumber":"bugue;bugue",
    "addr:postcode":"24260;24260",
    "addr:street":"Malmussou Bas",
    "iso:country":"FR",
    "sg:address":"Malmussou Bas 24260 Le Bugue",
    "sg:city":"Le Bugue",
    "sg:classifiers":[
        {
            "category":"Food & Beverages",
            "subcategory":"Meat & Fish",
            "type":"Retail Goods"
        }
    ],
    "sg:phone":"+33 5 53 07 22 64",
    "sg:postcode":"24260",
    "sg:province":"Aquitaine",
    "sg:tags":[
        "preserve",
        "cooked",
        "product",
        "related"
    ],
    "wof:name":"Etablissements Groliere Et Fils (ets Groliere Et Fils)",
    "wof:placetype":"venue"
},
  "geometry": {"coordinates":[0.948175,44.901176],"type":"Point"}
}