{
  "type": "Feature",
  "properties": {
    "addr:full":"25, Rue de la F\u00e9licit\u00e9, 75017 Paris Ile de France",
    "addr:housenumber":"25",
    "addr:postcode":"75017",
    "addr:street":"Rue De La Fe\u0301Licite\u0301",
    "iso:country":"FR",
    "sg:address":"25, Rue de la F\u00e9licit\u00e9, 75017 Paris",
    "sg:orig_category":"Unclassifiable Establishments",
    "sg:phone":"+33 1 42 27 52 36",
    "sg:province":"Ile de France",
    "wof:name":"Dartigues Jean",
    "wof:placetype":"venue"
},
  "geometry": {"coordinates":[2.31013,48.887112],"type":"Point"}
}