{
  "type": "Feature",
  "properties": {
    "addr:full":"7 Rue Edouard Branly Zac St Eloi 86000 Poitiers Poitou-Charentes",
    "addr:housenumber":"7",
    "addr:postcode":"86000",
    "addr:street":"Rue Edouard Branly Zac St",
    "iso:country":"FR",
    "sg:address":"7 Rue Edouard Branly Zac St Eloi 86000 Poitiers",
    "sg:classifiers":[
        {
            "category":"Manufacturing",
            "subcategory":"Glass & Minerals",
            "type":"Manufacturing & Wholesale Goods"
        }
    ],
    "sg:phone":"+33 5 49 01 94 03",
    "sg:province":"Poitou-Charentes",
    "sg:tags":[
        "building",
        "material"
    ],
    "wof:name":"Beton De France",
    "wof:placetype":"venue"
},
  "geometry": {"coordinates":[0.34169,46.58057],"type":"Point"}
}