{
  "type": "Feature",
  "properties": {
    "iso:country":"FR",
    "sg:address":"5, Rue Marie Poussepain, 91410 Dourdan",
    "sg:orig_category":"Unclassifiable Establishments",
    "sg:phone":"+33 1 64 59 77 27",
    "sg:province":"Ile de France",
    "wof:name":"Tulipia S.a.",
    "wof:placetype":"venue"
},
  "geometry": {"coordinates":[2.023409,48.523174],"type":"Point"}
}