{
  "type": "Feature",
  "properties": {
    "addr:full":"103 Chem M\u00fbriers 38260 Marcilloles Rhone-Alpes 38260",
    "addr:housenumber":"103",
    "addr:postcode":"38260;38260",
    "addr:street":"Chem Mu\u0302Riers;Rhone-Alpes",
    "iso:country":"FR",
    "sg:address":"103 Chem M\u00fbriers 38260 Marcilloles",
    "sg:classifiers":[
        {
            "category":"Manufacturing",
            "subcategory":"Chemicals & Compounds",
            "type":"Manufacturing & Wholesale Goods"
        }
    ],
    "sg:phone":"+33 4 74 54 08 49",
    "sg:postcode":"38260",
    "sg:province":"Rhone-Alpes",
    "sg:tags":[
        "pharmaceutical",
        "chemistry",
        "-",
        "by-product"
    ],
    "wof:name":"France Alu Color Fac Sa",
    "wof:placetype":"venue"
},
  "geometry": {"coordinates":[5.196824,45.342171],"type":"Point"}
}