{
  "type": "Feature",
  "properties": {
    "addr:full":"10, Place de la Joliette, 13002 Marseille Poitou-Charentes",
    "addr:housenumber":"10",
    "addr:postcode":"13002",
    "addr:street":"Place De La Joliette",
    "iso:country":"FR",
    "sg:address":"10, Place de la Joliette, 13002 Marseille",
    "sg:orig_category":"Unclassifiable Establishments",
    "sg:phone":"+33 4 91 99 83 10",
    "sg:province":"Poitou-Charentes",
    "wof:name":"Watson Brown S.a.",
    "wof:placetype":"venue"
},
  "geometry": {"coordinates":[5.365792,43.305336],"type":"Point"}
}