{
  "type": "Feature",
  "properties": {
    "iso:country":"FR",
    "sg:address":"191B, Rue Jean Jaur\u00e8s, 59880 Saint Saulve",
    "sg:orig_category":"Unclassifiable Establishments",
    "sg:phone":"+33 3 27 41 33 66",
    "sg:province":"Nord Pas-de-Calais",
    "wof:name":"Reliant S.a.r.l.",
    "wof:placetype":"venue"
},
  "geometry": {"coordinates":[3.556432,50.370903],"type":"Point"}
}