{
  "type": "Feature",
  "properties": {
    "iso:country":"FR",
    "sg:address":"Rue Paul Langevin - ZI la Croix Cadeau",
    "sg:city":"Avrill\u00e9",
    "sg:orig_category":"Unclassifiable Establishments",
    "sg:phone":"+33 2 41 31 13 60",
    "sg:postcode":"49240",
    "sg:province":"Pays de Loire",
    "wof:name":"Isotol S.a.",
    "wof:placetype":"venue"
},
  "geometry": {"coordinates":[-0.587263,47.504822],"type":"Point"}
}