{
  "type": "Feature",
  "properties": {
    "addr:full":"Route De Saint Renan 29810 Ploumoguer Ploumoguer Bretagne 29810",
    "addr:postcode":"29810;29810",
    "addr:street":"Route De Saint Renan;Ploumoguer",
    "iso:country":"FR",
    "sg:address":"Route De Saint Renan 29810 Ploumoguer",
    "sg:city":"Ploumoguer",
    "sg:classifiers":[
        {
            "category":"Farming",
            "subcategory":"Farm & Veterinary Services",
            "type":"Manufacturing & Wholesale Goods"
        }
    ],
    "sg:phone":"+33 2 98 89 62 01",
    "sg:postcode":"29810",
    "sg:province":"Bretagne",
    "sg:tags":[
        "advice",
        "agriculture",
        "livestock",
        "business"
    ],
    "wof:name":"Cooperative Des Agriculteurs De Bretagne",
    "wof:placetype":"venue"
},
  "geometry": {"coordinates":[-4.722997,48.402893],"type":"Point"}
}