{
  "type": "Feature",
  "properties": {
    "iso:country":"FR",
    "sg:address":"Zi Rue De La Thomasserie 49070 Beaucouz\u00e9",
    "sg:classifiers":[
        {
            "category":"Manufacturing",
            "subcategory":"Rubber & Plastics",
            "type":"Manufacturing & Wholesale Goods"
        }
    ],
    "sg:phone":"+33 2 41 73 10 40",
    "sg:province":"Pays de Loire",
    "sg:tags":[
        "packaging",
        "material",
        "-"
    ],
    "wof:name":"Styrpac",
    "wof:placetype":"venue"
},
  "geometry": {"coordinates":[-0.632213,47.474998],"type":"Point"}
}