{
  "type": "Feature",
  "properties": {
    "addr:full":"22, Bd Paul Vaillant Couturier, 59165 Auberchicourt Nord Pas-de-Calais 59165",
    "addr:housenumber":"22",
    "addr:postcode":"59165;59165",
    "addr:street":"Bd Paul Vaillant Couturier",
    "iso:country":"FR",
    "sg:address":"22, Bd Paul Vaillant Couturier, 59165 Auberchicourt",
    "sg:orig_category":"Non-Classified Establishments",
    "sg:phone":"+33 3 27 89 18 69",
    "sg:postcode":"59165",
    "sg:province":"Nord Pas-de-Calais",
    "wof:name":"Applimat Composites S.a.r.l.",
    "wof:placetype":"venue"
},
  "geometry": {"coordinates":[3.237516,50.333073],"type":"Point"}
}