{
  "type": "Feature",
  "properties": {
    "iso:country":"FR",
    "sg:address":"28, Rue du Bataillon Berthier, 69170 Tarare",
    "sg:orig_category":"Non-Classified Establishments",
    "sg:phone":"+33 4 74 63 12 80",
    "sg:province":"Rhone-Alpes",
    "wof:name":"Monot Damoune S.a.r.l.",
    "wof:placetype":"venue"
},
  "geometry": {"coordinates":[4.433006,45.899086],"type":"Point"}
}