{
  "type": "Feature",
  "properties": {
    "iso:country":"FR",
    "sg:address":"Zi L'Oseraie 84131 Le Pontet Cedex",
    "sg:city":"Le Pontet",
    "sg:classifiers":[
        {
            "category":"Shopping",
            "type":"Retail Goods"
        }
    ],
    "sg:phone":"+33 4 90 03 67 68",
    "sg:postcode":"73110",
    "sg:province":"Rhone-Alpes",
    "sg:tags":[
        "metallurgy",
        "finished",
        "-",
        "metalworking",
        "metallic"
    ],
    "wof:name":"Chaudronnerie & Tuyauterie Soudure",
    "wof:placetype":"venue"
},
  "geometry": {"coordinates":[12.309676,48.467957],"type":"Point"}
}