{
  "type": "Feature",
  "properties": {
    "addr:full":"2 Rue Gare Fourchaud 85200 Bourneau Pays de Loire",
    "addr:housenumber":"2",
    "addr:postcode":"85200",
    "addr:street":"Rue Gare Fourchaud",
    "iso:country":"FR",
    "sg:address":"2 Rue Gare Fourchaud 85200 Bourneau",
    "sg:classifiers":[
        {
            "category":"Professional",
            "type":"Services"
        }
    ],
    "sg:phone":"+33 2 51 00 22 07",
    "sg:province":"Pays de Loire",
    "sg:tags":[
        "transport",
        "road"
    ],
    "wof:name":"Ste D Expl Des Transports Fontan Sa",
    "wof:placetype":"venue"
},
  "geometry": {"coordinates":[-0.807965,46.392536],"type":"Point"}
}