{
  "type": "Feature",
  "properties": {
    "iso:country":"FR",
    "sg:address":"B.P. 70226, 35502 Vitr\u00e9 C\u00e9dex^^19, Av. de Helmstedt, 35500 Vitr\u00e9",
    "sg:city":"Vitr\u00e9",
    "sg:orig_category":"Non-Classified Establishments",
    "sg:phone":"+33 2 99 75 06 96",
    "sg:postcode":"35500",
    "sg:province":"Bretagne",
    "wof:name":"Cadieu Fr\u00e8res S.a.r.l.",
    "wof:placetype":"venue"
},
  "geometry": {"coordinates":[-1.30752,48.080273],"type":"Point"}
}