{
  "type": "Feature",
  "properties": {
    "addr:full":"9/11, Rue Georges Enesco, 94000 Cr\u00e9teil Ile de France",
    "addr:housenumber":"9 / 11",
    "addr:postcode":"94000",
    "addr:street":"Rue Georges Enesco",
    "iso:country":"FR",
    "sg:address":"9/11, Rue Georges Enesco, 94000 Cr\u00e9teil",
    "sg:orig_category":"Unclassifiable Establishments",
    "sg:phone":"+33 1 45 13 13 35",
    "sg:province":"Ile de France",
    "wof:name":"S.i.m.e.d. S.a.",
    "wof:placetype":"venue"
},
  "geometry": {"coordinates":[2.447267,48.796803],"type":"Point"}
}