{
  "type": "Feature",
  "properties": {
    "iso:country":"FR",
    "sg:address":"200 rue Serpentine 13510 Eguilles",
    "sg:city":"\u00c9guille",
    "sg:classifiers":[
        {
            "category":"Shopping",
            "subcategory":"Clothing, Apparel, & Fashions",
            "type":"Retail Goods"
        }
    ],
    "sg:phone":"+33 4 42 59 21 64",
    "sg:postcode":"17600",
    "sg:province":"Poitou-Charentes",
    "sg:tags":[
        "fur",
        "glove"
    ],
    "wof:name":"Ld S.a.",
    "wof:placetype":"venue"
},
  "geometry": {"coordinates":[5.364634,43.545967],"type":"Point"}
}