{
  "type": "Feature",
  "properties": {
    "iso:country":"FR",
    "sg:address":"4 Rue Goudier 63200 Riom",
    "sg:city":"Riom",
    "sg:classifiers":[
        {
            "category":"Professional",
            "subcategory":"Printing & Photocopies",
            "type":"Services"
        }
    ],
    "sg:phone":"+33 4 73 38 68 97",
    "sg:postcode":"63200",
    "sg:province":"Auvergne",
    "sg:tags":[
        "publishing"
    ],
    "wof:name":"Ste Floran Presse Sarl",
    "wof:placetype":"venue"
},
  "geometry": {"coordinates":[3.123469,45.883278],"type":"Point"}
}