{
  "type": "Feature",
  "properties": {
    "addr:full":"119, Rue des Chardonnerets - ZI Paris Nord II, 93290 Tremblay en France Ile de France",
    "addr:housenumber":"119",
    "addr:postcode":"93290",
    "addr:street":"Rue Des Chardonnerets Zi",
    "iso:country":"FR",
    "sg:address":"119, Rue des Chardonnerets - ZI Paris Nord II, 93290 Tremblay en France",
    "sg:orig_category":"Unclassifiable Establishments",
    "sg:phone":"+33 1 49 38 38 38",
    "sg:province":"Ile de France",
    "wof:name":"Topdeq S.a.s.",
    "wof:placetype":"venue"
},
  "geometry": {"coordinates":[2.56727,48.951214],"type":"Point"}
}