{
  "type": "Feature",
  "properties": {
    "addr:full":"B.P. 57, 33166 Saint M\u00e9dard en Jalles C\u00e9dex^^Av. Gay Lussac, 33160 Saint M\u00e9dard en Jalles Salaunes Aquitaine 33160",
    "addr:postcode":"33166;33160;33160",
    "addr:street":"B.P. 57;Me\u0301Dard;Gay Lussac;Me\u0301Dard",
    "iso:country":"FR",
    "sg:address":"B.P. 57, 33166 Saint M\u00e9dard en Jalles C\u00e9dex^^Av. Gay Lussac, 33160 Saint M\u00e9dard en Jalles",
    "sg:city":"Salaunes",
    "sg:orig_category":"Non-Classified Establishments",
    "sg:phone":"+33 5 56 70 50 50",
    "sg:postcode":"33160",
    "sg:province":"Aquitaine",
    "wof:name":"S.n.p.e. S.a. - Soci\u00e9t\u00e9 Nationale Des Poudres Et Explosifs",
    "wof:placetype":"venue"
},
  "geometry": {"coordinates":[-0.737203,44.880589],"type":"Point"}
}