{
  "type": "Feature",
  "properties": {
    "iso:country":"FR",
    "sg:address":"4, Rue de l'Industrie, 51350 Cormontreuil",
    "sg:orig_category":"Unclassifiable Establishments",
    "sg:phone":"+33 3 26 50 36 36",
    "sg:province":"Champagne",
    "wof:name":"Cofratel S.a.",
    "wof:placetype":"venue"
},
  "geometry": {"coordinates":[4.067365,49.216824],"type":"Point"}
}