{
  "type": "Feature",
  "properties": {
    "addr:full":"58 Boulevard Gustave Roch 44261 Nantes Cedex 2 Centre",
    "addr:housenumber":"58;2",
    "addr:postcode":"44261",
    "addr:street":"Boulevard Gustave Roch",
    "iso:country":"FR",
    "sg:address":"58 Boulevard Gustave Roch 44261 Nantes Cedex 2",
    "sg:classifiers":[
        {
            "category":"Farming",
            "subcategory":"Crops",
            "type":"Manufacturing & Wholesale Goods"
        }
    ],
    "sg:phone":"+33 2 51 25 09 00",
    "sg:province":"Centre",
    "sg:tags":[
        "vegetable",
        "fruit",
        "agriculture",
        "livestock"
    ],
    "wof:name":"Comptoir Fruitier Europeen Sa",
    "wof:placetype":"venue"
},
  "geometry": {"coordinates":[-1.555667,47.200958],"type":"Point"}
}