{
  "type": "Feature",
  "properties": {
    "addr:full":"8/10, Rue de la Chaussairie, 35170 Bruz Bruz Bretagne 35170",
    "addr:housenumber":"8 / 10",
    "addr:postcode":"35170;35170",
    "addr:street":"Rue De La Chaussairie",
    "iso:country":"FR",
    "sg:address":"8/10, Rue de la Chaussairie, 35170 Bruz",
    "sg:city":"Bruz",
    "sg:orig_category":"Unclassifiable Establishments",
    "sg:phone":"+33 2 99 41 21 63",
    "sg:postcode":"35170",
    "sg:province":"Bretagne",
    "wof:name":"Autocars Et Voyages Jollivet S.a.",
    "wof:placetype":"venue"
},
  "geometry": {"coordinates":[-1.718197,48.029526],"type":"Point"}
}