{
  "type": "Feature",
  "properties": {
    "iso:country":"FR",
    "sg:address":"B.P. 12, 59860 Bruay sur l'Escaut^^3, Bd Marcel Cachin, 59860 Bruay sur l'Escaut",
    "sg:orig_category":"Non-Classified Establishments",
    "sg:phone":"+33 3 27 33 11 33",
    "sg:province":"Nord Pas-de-Calais",
    "wof:name":"M. Et R. Hubert S.a.",
    "wof:placetype":"venue"
},
  "geometry": {"coordinates":[3.534409,50.394085],"type":"Point"}
}