{
  "type": "Feature",
  "properties": {
    "addr:full":"3, Rue Rosa Bonheur, 59290 Wasquehal Nord Pas-de-Calais",
    "addr:housenumber":"3",
    "addr:postcode":"59290",
    "addr:street":"Rue Rosa Bonheur",
    "iso:country":"FR",
    "sg:address":"3, Rue Rosa Bonheur, 59290 Wasquehal",
    "sg:orig_category":"Unclassifiable Establishments",
    "sg:phone":"+33 3 20 70 19 04",
    "sg:province":"Nord Pas-de-Calais",
    "wof:name":"Verbiese S.a.",
    "wof:placetype":"venue"
},
  "geometry": {"coordinates":[3.145448,50.692413],"type":"Point"}
}