{
  "type": "Feature",
  "properties": {
    "iso:country":"FR",
    "sg:address":"B.P. 7",
    "sg:city":"Valognes",
    "sg:orig_category":"Non-Classified Establishments",
    "sg:phone":"+33 2 33 40 38 40",
    "sg:postcode":"50700",
    "sg:province":"Basse Normandie",
    "wof:name":"Etablissements Leriche S.a.",
    "wof:placetype":"venue"
},
  "geometry": {"coordinates":[-1.468479,49.508766],"type":"Point"}
}