{
  "type": "Feature",
  "properties": {
    "iso:country":"FR",
    "sg:address":"Le Bac \u00e0 l'Aum\u00f4ne 60280 Clairoix",
    "sg:orig_category":"Non-Classified Establishments",
    "sg:phone":"+33 3 44 40 71 33",
    "sg:postcode":"60280",
    "sg:province":"Picardie",
    "wof:name":"Continental France S.n.c.",
    "wof:placetype":"venue"
},
  "geometry": {"coordinates":[2.84419,49.440411],"type":"Point"}
}