{
  "type": "Feature",
  "properties": {
    "iso:country":"FR",
    "sg:address":"54, Bd Gambetta, 30700 Uz\u00e8s",
    "sg:orig_category":"Non-Classified Establishments",
    "sg:phone":"+33 4 66 22 26 31",
    "sg:postcode":"30700",
    "sg:province":"Languedoc-Roussillon",
    "wof:name":"Biotech Diffusion S.a.r.l.",
    "wof:placetype":"venue"
},
  "geometry": {"coordinates":[4.41761,44.012474],"type":"Point"}
}