{
  "type": "Feature",
  "properties": {
    "addr:full":"16, Rue Friant, 75014 Paris Ile de France",
    "addr:housenumber":"16",
    "addr:postcode":"75014",
    "addr:street":"Rue Friant",
    "iso:country":"FR",
    "sg:address":"16, Rue Friant, 75014 Paris",
    "sg:orig_category":"Non-Classified Establishments",
    "sg:phone":"+33 1 56 53 65 65",
    "sg:province":"Ile de France",
    "wof:name":"Rexan S.a.",
    "wof:placetype":"venue"
},
  "geometry": {"coordinates":[2.324262,48.826031],"type":"Point"}
}