{
  "type": "Feature",
  "properties": {
    "addr:full":"20 avenue de Champagne 51200 Epernay Champagne 51200",
    "addr:housenumber":"20",
    "addr:postcode":"51200;51200",
    "addr:street":"Avenue De Champagne;Champagne",
    "iso:country":"FR",
    "sg:address":"20 avenue de Champagne 51200 Epernay",
    "sg:classifiers":[
        {
            "category":"Food & Beverages",
            "subcategory":"Liquor & Beverages",
            "type":"Retail Goods"
        }
    ],
    "sg:phone":"+33 3 26 51 22 00",
    "sg:postcode":"51200",
    "sg:province":"Champagne",
    "sg:tags":[
        "champagne"
    ],
    "wof:name":"Champagne Mercier Sa",
    "wof:placetype":"venue"
},
  "geometry": {"coordinates":[3.960489,49.04285],"type":"Point"}
}