{
  "type": "Feature",
  "properties": {
    "iso:country":"FR",
    "sg:address":"102 bis, Bd Saint Denis, 92400 Courbevoie",
    "sg:orig_category":"Unclassifiable Establishments",
    "sg:phone":"+33 1 41 16 88 55",
    "sg:province":"Ile de France",
    "wof:name":"Mecelec S.a.",
    "wof:placetype":"venue"
},
  "geometry": {"coordinates":[2.265436,48.898499],"type":"Point"}
}