{
  "type": "Feature",
  "properties": {
    "iso:country":"FR",
    "sg:address":"B.P. 14, 67038 Strasbourg C\u00e9dex 2^^Rue Alfred Kastler, 67200 Eckbolsheim",
    "sg:city":"Strasbourg",
    "sg:orig_category":"Non-Classified Establishments",
    "sg:phone":"+33 3 88 10 33 10",
    "sg:postcode":"67200",
    "sg:province":"Alsace",
    "wof:name":"Alusor S.a.",
    "wof:placetype":"venue"
},
  "geometry": {"coordinates":[7.687253,48.579323],"type":"Point"}
}