{
  "type": "Feature",
  "properties": {
    "addr:full":"9, Rue Charles Lucot, 52100 Saint Dizier Champagne",
    "addr:housenumber":"9",
    "addr:postcode":"52100",
    "addr:street":"Rue Charles Lucot;Dizier",
    "iso:country":"FR",
    "sg:address":"9, Rue Charles Lucot, 52100 Saint Dizier",
    "sg:orig_category":"Non-Classified Establishments",
    "sg:phone":"+33 3 25 05 88 55",
    "sg:province":"Champagne",
    "wof:name":"Induco S.a.r.l.",
    "wof:placetype":"venue"
},
  "geometry": {"coordinates":[4.93682,48.634853],"type":"Point"}
}