{
  "type": "Feature",
  "properties": {
    "addr:full":"19, Rue Edmond Michelet, 69490 Pontcharra sur Turdine Rhone-Alpes 69490",
    "addr:housenumber":"19",
    "addr:postcode":"69490;69490",
    "addr:street":"Rue Edmond Michelet;Rhone-Alpes",
    "iso:country":"FR",
    "sg:address":"19, Rue Edmond Michelet, 69490 Pontcharra sur Turdine",
    "sg:orig_category":"Unclassifiable Establishments",
    "sg:phone":"+33 4 74 05 60 07",
    "sg:postcode":"69490",
    "sg:province":"Rhone-Alpes",
    "wof:name":"Soci\u00e9t\u00e9 Girard S.a.r.l.",
    "wof:placetype":"venue"
},
  "geometry": {"coordinates":[4.498308,45.874966],"type":"Point"}
}