{
  "type": "Feature",
  "properties": {
    "addr:full":"17 route De Bourbourg 59380 SPYCKER Nord Pas-de-Calais 59380",
    "addr:housenumber":"17",
    "addr:postcode":"59380;59380",
    "addr:street":"Route De Bourbourg",
    "iso:country":"FR",
    "sg:address":"17 route De Bourbourg 59380 SPYCKER",
    "sg:classifiers":[
        {
            "category":"Home & Garden",
            "subcategory":"Building Materials",
            "type":"Retail Goods"
        }
    ],
    "sg:phone":"+33 3 28 29 03 67",
    "sg:postcode":"59380",
    "sg:province":"Nord Pas-de-Calais",
    "sg:tags":[
        "steel",
        "base"
    ],
    "wof:name":"Hexatechnic S.a.r.l.",
    "wof:placetype":"venue"
},
  "geometry": {"coordinates":[2.298578,50.986431],"type":"Point"}
}