{
  "type": "Feature",
  "properties": {
    "addr:full":"Rue Fontesse - Espace de la Motte Vesoul Franche Comt\u00e9 70000",
    "addr:postcode":"70000",
    "addr:street":"Rue Fontesse Espace De La Motte;Franche Comte\u0301",
    "iso:country":"FR",
    "sg:address":"Rue Fontesse - Espace de la Motte",
    "sg:city":"Vesoul",
    "sg:orig_category":"Unclassifiable Establishments",
    "sg:phone":"+33 3 84 75 41 55",
    "sg:postcode":"70000",
    "sg:province":"Franche Comt\u00e9",
    "wof:name":"Larr\u00e8re Philippe",
    "wof:placetype":"venue"
},
  "geometry": {"coordinates":[6.15293,47.636215],"type":"Point"}
}