{
  "type": "Feature",
  "properties": {
    "addr:full":"03360 Braize Braize Auvergne 03360",
    "addr:postcode":"03360;braize;03360",
    "iso:country":"FR",
    "sg:address":"03360 Braize",
    "sg:city":"Braize",
    "sg:orig_category":"Non-Classified Establishments",
    "sg:phone":"+33 4 70 06 12 29",
    "sg:postcode":"03360",
    "sg:province":"Auvergne",
    "wof:name":"Carbo Distribution S.a.",
    "wof:placetype":"venue"
},
  "geometry": {"coordinates":[2.64935,46.667496],"type":"Point"}
}