{
  "type": "Feature",
  "properties": {
    "iso:country":"FR",
    "sg:address":"580 Rue Du Champ Rouge 45770 Saran",
    "sg:city":"Saran",
    "sg:classifiers":[
        {
            "category":"Banks & Credit Unions",
            "subcategory":"Investment Brokerage",
            "type":"Services"
        }
    ],
    "sg:phone":"+33 2 38 70 82 00",
    "sg:postcode":"45770",
    "sg:province":"Centre",
    "sg:tags":[
        "-",
        "transport",
        "related"
    ],
    "wof:name":"Deret Logistique",
    "wof:placetype":"venue"
},
  "geometry": {"coordinates":[1.844823,47.955181],"type":"Point"}
}