{
  "type": "Feature",
  "properties": {
    "addr:full":"3/5, Rue des Gardes, 91370 Verri\u00e8res le Buisson Ile de France",
    "addr:housenumber":"3 / 5",
    "addr:postcode":"91370",
    "addr:street":"Rue Des Gardes",
    "iso:country":"FR",
    "sg:address":"3/5, Rue des Gardes, 91370 Verri\u00e8res le Buisson",
    "sg:orig_category":"Unclassifiable Establishments",
    "sg:phone":"+33 1 69 75 72 00",
    "sg:province":"Ile de France",
    "wof:name":"Message Plus S.a.r.l.",
    "wof:placetype":"venue"
},
  "geometry": {"coordinates":[2.281306,48.745178],"type":"Point"}
}