{
  "type": "Feature",
  "properties": {
    "addr:full":"9, Rue de Montagny, 42300 Villerest Rhone-Alpes 42300",
    "addr:housenumber":"9",
    "addr:postcode":"42300;42300",
    "addr:street":"Rue De Montagny",
    "iso:country":"FR",
    "sg:address":"9, Rue de Montagny, 42300 Villerest",
    "sg:orig_category":"Unclassifiable Establishments",
    "sg:phone":"+33 4 77 69 66 87",
    "sg:postcode":"42300",
    "sg:province":"Rhone-Alpes",
    "wof:name":"O.c.m.i. S.a.r.l. - Orty Consultant Marketing International",
    "wof:placetype":"venue"
},
  "geometry": {"coordinates":[4.040211,45.98912],"type":"Point"}
}