{
  "type": "Feature",
  "properties": {
    "iso:country":"FR",
    "sg:address":"rue des Pays-Bas 84100 Orange",
    "sg:orig_category":"Sport Toys, Athletic Toys",
    "sg:phone":"+33 4 90 34 59 06",
    "sg:province":"Centre",
    "wof:name":"Avio & Tiger Sa",
    "wof:placetype":"venue"
},
  "geometry": {"coordinates":[4.839371,44.124397],"type":"Point"}
}