{
  "type": "Feature",
  "properties": {
    "addr:full":"Ch\u00e2teau Fayan Puisseguin Aquitaine 33570",
    "addr:postcode":"33570",
    "iso:country":"FR",
    "sg:address":"Ch\u00e2teau Fayan",
    "sg:city":"Puisseguin",
    "sg:orig_category":"Unclassifiable Establishments",
    "sg:phone":"+33 5 57 74 63 49",
    "sg:postcode":"33570",
    "sg:province":"Aquitaine",
    "wof:name":"Mounet Philippe S.c.e.a.",
    "wof:placetype":"venue"
},
  "geometry": {"coordinates":[-0.058452,44.94268],"type":"Point"}
}