{
  "type": "Feature",
  "properties": {
    "addr:full":"5 Rue Sir Alexander Fleming Zi Des Renouilleres 93360 Neuilly Plaisance Ile de France 93360",
    "addr:housenumber":"5",
    "addr:postcode":"93360;93360",
    "addr:street":"Rue Sir Alexander Fleming Zi Des Renouilleres;Ile De France",
    "iso:country":"FR",
    "sg:address":"5 Rue Sir Alexander Fleming Zi Des Renouilleres 93360 Neuilly Plaisance",
    "sg:classifiers":[
        {
            "category":"Shopping",
            "subcategory":"Hobbies, Toys, & Games",
            "type":"Retail Goods"
        }
    ],
    "sg:phone":"+33 1 43 09 86 78",
    "sg:postcode":"93360",
    "sg:province":"Ile de France",
    "sg:tags":[
        "product",
        "miscellaneous",
        "entertainment"
    ],
    "wof:name":"Hobiform Cam",
    "wof:placetype":"venue"
},
  "geometry": {"coordinates":[2.502418,48.860184],"type":"Point"}
}