{
  "type": "Feature",
  "properties": {
    "addr:full":"64, Rue de la Moricerie, 49260 Saint Cyr en Bourg Pays de Loire",
    "addr:housenumber":"64",
    "addr:postcode":"49260",
    "addr:street":"Rue De La Moricerie;Cyr En Bourg Pays",
    "iso:country":"FR",
    "sg:address":"64, Rue de la Moricerie, 49260 Saint Cyr en Bourg",
    "sg:orig_category":"Non-Classified Establishments",
    "sg:phone":"+33 2 41 51 61 08",
    "sg:province":"Pays de Loire",
    "wof:name":"M.v.s. S.a.r.l.",
    "wof:placetype":"venue"
},
  "geometry": {"coordinates":[-0.057166,47.187027],"type":"Point"}
}