{
  "type": "Feature",
  "properties": {
    "addr:full":"Rte de Sainte Anne Pluvigner Bretagne 56330",
    "addr:postcode":"56330",
    "addr:street":"Rte De Sainte Anne Pluvigner Bretagne",
    "iso:country":"FR",
    "sg:address":"Rte de Sainte Anne",
    "sg:city":"Pluvigner",
    "sg:orig_category":"Non-Classified Establishments",
    "sg:phone":"+33 2 97 24 70 73",
    "sg:postcode":"56330",
    "sg:province":"Bretagne",
    "wof:name":"Bretagne Chrome S.a.",
    "wof:placetype":"venue"
},
  "geometry": {"coordinates":[-3.000514,47.766006],"type":"Point"}
}