{
  "type": "Feature",
  "properties": {
    "addr:full":"B.P. 134, 88304 Neufch\u00e2teau C\u00e9dex^^73, Rue du 12 Septembre 1944, 88300 Neufch\u00e2teau Lorraine",
    "addr:housenumber":"b.p. 134",
    "addr:postcode":"88304;88300",
    "addr:street":"Rue Du 12 Septembre 1944",
    "iso:country":"FR",
    "sg:address":"B.P. 134, 88304 Neufch\u00e2teau C\u00e9dex^^73, Rue du 12 Septembre 1944, 88300 Neufch\u00e2teau",
    "sg:orig_category":"Non-Classified Establishments",
    "sg:phone":"+33 3 29 94 29 90",
    "sg:province":"Lorraine",
    "wof:name":"Soci\u00e9t\u00e9 Nouvelle Alm\u00e9ca S.a.r.l.",
    "wof:placetype":"venue"
},
  "geometry": {"coordinates":[5.69254,48.358501],"type":"Point"}
}