{
  "type": "Feature",
  "properties": {
    "addr:full":"54 R Du Ch\u00e2teau D'Eau 28300 Mainvilliers Mainvilliers Centre 28300",
    "addr:housenumber":"54",
    "addr:postcode":"28300;28300",
    "addr:street":"R Du Cha\u0302Teau D'Eau",
    "iso:country":"FR",
    "sg:address":"54 R Du Ch\u00e2teau D'Eau 28300 Mainvilliers",
    "sg:city":"Mainvilliers",
    "sg:classifiers":[
        {
            "category":"Manufacturing",
            "subcategory":"Tools & Machinery",
            "type":"Manufacturing & Wholesale Goods"
        }
    ],
    "sg:phone":"+33 2 37 84 08 40",
    "sg:postcode":"28300",
    "sg:province":"Centre",
    "sg:tags":[
        "metallurgy",
        "metalworking"
    ],
    "wof:name":"Comptoir Metallurgique Chartrain Sa",
    "wof:placetype":"venue"
},
  "geometry": {"coordinates":[1.45283,48.450069],"type":"Point"}
}