{
  "type": "Feature",
  "properties": {
    "iso:country":"FR",
    "sg:address":"7 Rue Chappe BP 1011 78130 Les Mureaux",
    "sg:classifiers":[
        {
            "category":"Shopping",
            "subcategory":"Crafts & Fabrics",
            "type":"Retail Goods"
        }
    ],
    "sg:phone":"+33 1 30 22 08 08",
    "sg:postcode":"78130",
    "sg:province":"Ile de France",
    "sg:tags":[
        "textile",
        "clothing"
    ],
    "wof:name":"Thermopatch France Sa",
    "wof:placetype":"venue"
},
  "geometry": {"coordinates":[1.892065,48.978657],"type":"Point"}
}