{
  "type": "Feature",
  "properties": {
    "iso:country":"FR",
    "sg:address":"127, Av. Franklin Roosevelt, 69150 D\u00e9cines Charpieu",
    "sg:orig_category":"Unclassifiable Establishments",
    "sg:phone":"+33 4 72 05 64 10",
    "sg:postcode":"69150",
    "sg:province":"Rhone-Alpes",
    "wof:name":"Jallut Msa S.a.",
    "wof:placetype":"venue"
},
  "geometry": {"coordinates":[4.935641,45.755295],"type":"Point"}
}