{
  "type": "Feature",
  "properties": {
    "addr:full":"4, Av. Jean Rostand, 91400 Orsay Ile de France",
    "addr:postcode":"91400",
    "addr:street":"Av. Jean Rostand;Ile De France",
    "iso:country":"FR",
    "sg:address":"4, Av. Jean Rostand, 91400 Orsay",
    "sg:orig_category":"Unclassifiable Establishments",
    "sg:phone":"+33 1 69 35 33 40",
    "sg:province":"Ile de France",
    "wof:name":"Exabyte",
    "wof:placetype":"venue"
},
  "geometry": {"coordinates":[2.17625,48.7103],"type":"Point"}
}