{
  "type": "Feature",
  "properties": {
    "addr:full":"Le Rauly 24240 Monbazillac Monbazillac Aquitaine 24240",
    "addr:postcode":"24240;24240",
    "iso:country":"FR",
    "sg:address":"Le Rauly 24240 Monbazillac",
    "sg:city":"Monbazillac",
    "sg:orig_category":"Non-Classified Establishments",
    "sg:phone":"+33 5 53 24 55 91",
    "sg:postcode":"24240",
    "sg:province":"Aquitaine",
    "wof:name":"G.a.e.c. De La Barde",
    "wof:placetype":"venue"
},
  "geometry": {"coordinates":[0.442344,44.811241],"type":"Point"}
}