{
  "type": "Feature",
  "properties": {
    "addr:full":"6, Rue de l'Uranium, 67801 Hoenheim C\u00e9dex Kansas",
    "addr:housenumber":"6",
    "addr:postcode":"67801",
    "addr:street":"Rue De L'Uranium",
    "iso:country":"FR",
    "sg:address":"6, Rue de l'Uranium, 67801 Hoenheim C\u00e9dex",
    "sg:orig_category":"Non-Classified Establishments",
    "sg:phone":"+33 3 90 20 82 90",
    "sg:province":"Kansas",
    "wof:name":"Irion S.a.",
    "wof:placetype":"venue"
},
  "geometry": {"coordinates":[-100.012367,37.693378],"type":"Point"}
}