{
  "type": "Feature",
  "properties": {
    "addr:full":"1, Rue Delmas, 34000 Montpellier Languedoc-Roussillon",
    "addr:housenumber":"1",
    "addr:postcode":"34000",
    "addr:street":"Rue Delmas",
    "iso:country":"FR",
    "sg:address":"1, Rue Delmas, 34000 Montpellier",
    "sg:orig_category":"Non-Classified Establishments",
    "sg:phone":"+33 4 67 58 77 58",
    "sg:province":"Languedoc-Roussillon",
    "wof:name":"Studio B S.a.r.l.",
    "wof:placetype":"venue"
},
  "geometry": {"coordinates":[3.863567,43.609962],"type":"Point"}
}