{
  "type": "Feature",
  "properties": {
    "addr:full":"4, Rue de Fos sur Mer - Port Edouard Herriot, 69007 Lyon Rhone-Alpes 69007",
    "addr:housenumber":"4",
    "addr:postcode":"69007;69007",
    "addr:street":"Rue De Fos;Mer;Edouard Herriot",
    "iso:country":"FR",
    "sg:address":"4, Rue de Fos sur Mer - Port Edouard Herriot, 69007 Lyon",
    "sg:orig_category":"Non-Classified Establishments",
    "sg:phone":"+33 4 37 37 83 70",
    "sg:postcode":"69007",
    "sg:province":"Rhone-Alpes",
    "wof:name":"Eurovia B\u00e9ton S.n.c.",
    "wof:placetype":"venue"
},
  "geometry": {"coordinates":[4.842415,45.746235],"type":"Point"}
}