{
  "type": "Feature",
  "properties": {
    "iso:country":"FR",
    "sg:address":"Ld Le Pontet 33390 Eyrans",
    "sg:city":"Eyrans",
    "sg:classifiers":[
        {
            "category":"Home & Garden",
            "subcategory":"Building Materials",
            "type":"Retail Goods"
        }
    ],
    "sg:phone":"+33 5 57 42 62 30",
    "sg:postcode":"33390",
    "sg:province":"Aquitaine",
    "sg:tags":[
        "equipment",
        "energy",
        "-",
        "environment",
        "raw",
        "machinery"
    ],
    "wof:name":"Saur",
    "wof:placetype":"venue"
},
  "geometry": {"coordinates":[-0.642894,45.101875],"type":"Point"}
}