{
  "type": "Feature",
  "properties": {
    "addr:full":"Le Cluzeau 07690 VANOSC Rhone-Alpes",
    "addr:postcode":"07690",
    "addr:street":"Le Cluzeau",
    "iso:country":"FR",
    "sg:address":"Le Cluzeau 07690 VANOSC",
    "sg:classifiers":[
        {
            "category":"Sports & Exercise",
            "subcategory":"Sports Center",
            "type":"Entertainment"
        }
    ],
    "sg:phone":"+33 4 75 34 67 89",
    "sg:province":"Rhone-Alpes",
    "sg:tags":[
        "sporting",
        "good",
        "american"
    ],
    "wof:name":"Atan Sa",
    "wof:placetype":"venue"
},
  "geometry": {"coordinates":[4.547217,45.222057],"type":"Point"}
}