{
  "type": "Feature",
  "properties": {
    "iso:country":"FR",
    "sg:address":"Rue Florenne - ZI",
    "sg:city":"Blanquefort",
    "sg:orig_category":"Unclassifiable Establishments",
    "sg:phone":"+33 5 56 35 38 37",
    "sg:postcode":"33290",
    "sg:province":"Aquitaine",
    "wof:name":"Boueix Logistique S.a.r.l.",
    "wof:placetype":"venue"
},
  "geometry": {"coordinates":[-0.634838,44.914902],"type":"Point"}
}