{
  "type": "Feature",
  "properties": {
    "iso:country":"FR",
    "sg:address":"36",
    "sg:city":"de la Haye - Parc GVIO 38074 St. Quentin Fallavier",
    "sg:classifiers":[
        {
            "category":"Professional",
            "subcategory":"Testing Lab",
            "type":"Services"
        }
    ],
    "sg:phone":"+33 4 74 95 23 80",
    "sg:province":"Champagne",
    "sg:tags":[
        "laboratory",
        "furniture"
    ],
    "wof:name":"K\u00f6ttermann Sarl",
    "wof:placetype":"venue"
},
  "geometry": {"coordinates":[5.10321,45.658409],"type":"Point"}
}