{
  "type": "Feature",
  "properties": {
    "iso:country":"FR",
    "sg:address":"360 Avenue Du Medoc 33320 Eysines",
    "sg:city":"Eysines",
    "sg:classifiers":[
        {
            "category":"Home & Garden",
            "subcategory":"Furniture",
            "type":"Retail Goods"
        }
    ],
    "sg:phone":"+33 5 56 16 01 01",
    "sg:postcode":"33320",
    "sg:province":"Aquitaine",
    "sg:tags":[
        "wood"
    ],
    "wof:name":"Point P Materiaux",
    "wof:placetype":"venue"
},
  "geometry": {"coordinates":[-0.661621,44.891796],"type":"Point"}
}