{
  "type": "Feature",
  "properties": {
    "addr:full":"B.P. 9, 44360 Vigneux de Bretagne^^17, Rue de S\u00e9vign\u00e9, 44360 Vigneux de Bretagne Pays de Loire 44360",
    "addr:housenumber":"9",
    "addr:postcode":"44360;44360;44360",
    "addr:street":"B.P.;Rue De Se\u0301Vigne\u0301",
    "iso:country":"FR",
    "sg:address":"B.P. 9, 44360 Vigneux de Bretagne^^17, Rue de S\u00e9vign\u00e9, 44360 Vigneux de Bretagne",
    "sg:orig_category":"Non-Classified Establishments",
    "sg:phone":"+33 2 40 57 16 17",
    "sg:postcode":"44360",
    "sg:province":"Pays de Loire",
    "wof:name":"Ecofore S.a.",
    "wof:placetype":"venue"
},
  "geometry": {"coordinates":[-1.749463,47.240623],"type":"Point"}
}