{
  "type": "Feature",
  "properties": {
    "iso:country":"FR",
    "sg:address":"95707 Roissy Charles de Gaulle C\u00e9dex^^1, Rue du Pr\u00e9, 95700 Roissy en France",
    "sg:orig_category":"Non-Classified Establishments",
    "sg:phone":"+33 1 48 16 74 14",
    "sg:postcode":"95700",
    "sg:province":"Ile de France",
    "wof:name":"A.b.x. Logistics International France S.a.",
    "wof:placetype":"venue"
},
  "geometry": {"coordinates":[2.517005,49.003883],"type":"Point"}
}