{
  "type": "Feature",
  "properties": {
    "addr:full":"Port De Carhaix 29270 Motreff Motreff Bretagne 29270",
    "addr:postcode":"29270;29270",
    "addr:street":"Port;Carhaix;Motreff",
    "iso:country":"FR",
    "sg:address":"Port De Carhaix 29270 Motreff",
    "sg:city":"Motreff",
    "sg:classifiers":[
        {
            "category":"Farming",
            "subcategory":"Fish & Marine Products",
            "type":"Manufacturing & Wholesale Goods"
        }
    ],
    "sg:phone":"+33 2 98 99 54 54",
    "sg:postcode":"29270",
    "sg:province":"Bretagne",
    "sg:tags":[
        "animal",
        "food",
        "related",
        "grain",
        "cereal",
        "breeding"
    ],
    "wof:name":"Centralys Sa",
    "wof:placetype":"venue"
},
  "geometry": {"coordinates":[-3.60076,48.242069],"type":"Point"}
}