{
  "type": "Feature",
  "properties": {
    "addr:full":"359 Route De Sa 44300 Nantes Pays de Loire 44300",
    "addr:housenumber":"359",
    "addr:postcode":"44300;44300",
    "addr:street":"Route De Sa",
    "iso:country":"FR",
    "sg:address":"359 Route De Sa 44300 Nantes",
    "sg:classifiers":[
        {
            "category":"Shopping",
            "subcategory":"Books",
            "type":"Retail Goods"
        }
    ],
    "sg:phone":"+33 2 40 52 31 70",
    "sg:postcode":"44300",
    "sg:province":"Pays de Loire",
    "wof:name":"Marines Editions Sa",
    "wof:placetype":"venue"
},
  "geometry": {"coordinates":[-1.569279,47.245281],"type":"Point"}
}