{
  "type": "Feature",
  "properties": {
    "addr:full":"19, Rue Eug\u00e8ne de Ruelle - Immeuble Europ\u00e9en, 69003 Lyon Rhone-Alpes 69003",
    "addr:housenumber":"19",
    "addr:postcode":"69003;69003",
    "addr:street":"Rue Euge\u0300Ne De Ruelle Immeuble Europe\u0301En",
    "iso:country":"FR",
    "sg:address":"19, Rue Eug\u00e8ne de Ruelle - Immeuble Europ\u00e9en, 69003 Lyon",
    "sg:orig_category":"Non-Classified Establishments",
    "sg:phone":"+33 4 72 84 24 00",
    "sg:postcode":"69003",
    "sg:province":"Rhone-Alpes",
    "wof:name":"Easytech S.a.r.l.",
    "wof:placetype":"venue"
},
  "geometry": {"coordinates":[4.84978,45.760479],"type":"Point"}
}