{
  "type": "Feature",
  "properties": {
    "addr:full":"21, Rue Jean Beausire, 75004 Paris Ile de France",
    "addr:housenumber":"21",
    "addr:postcode":"75004",
    "addr:street":"Rue Jean Beausire",
    "iso:country":"FR",
    "sg:address":"21, Rue Jean Beausire, 75004 Paris",
    "sg:orig_category":"Non-Classified Establishments",
    "sg:phone":"+33 1 42 72 96 39",
    "sg:province":"Ile de France",
    "wof:name":"Katz Inter Lettres S.a.",
    "wof:placetype":"venue"
},
  "geometry": {"coordinates":[2.36841,48.85495],"type":"Point"}
}