{
  "type": "Feature",
  "properties": {
    "addr:full":"3 Route De Dun Sur Auron 18130 Bussy Bussy Centre 18130",
    "addr:housenumber":"3",
    "addr:postcode":"18130;18130",
    "addr:street":"Route De Dun Sur Auron",
    "iso:country":"FR",
    "sg:address":"3 Route De Dun Sur Auron 18130 Bussy",
    "sg:city":"Bussy",
    "sg:classifiers":[
        {
            "category":"Autos & Motor Vehicles",
            "subcategory":"Automobile Sales",
            "type":"Retail Goods"
        }
    ],
    "sg:phone":"+33 2 48 59 57 70",
    "sg:postcode":"18130",
    "sg:province":"Centre",
    "sg:tags":[
        "equipment",
        "motor-cars",
        "transport"
    ],
    "wof:name":"Carrosserie Industrielle Boutillon Cib",
    "wof:placetype":"venue"
},
  "geometry": {"coordinates":[2.56967,46.850601],"type":"Point"}
}