{
  "type": "Feature",
  "properties": {
    "iso:country":"FR",
    "sg:address":"Avenue monseigneur Rom\u00e9ro 37160 DESCARTES",
    "sg:city":"Descartes",
    "sg:classifiers":[
        {
            "category":"Shopping",
            "subcategory":"Stationery & Office Supplies",
            "type":"Retail Goods"
        }
    ],
    "sg:phone":"+33 2 47 59 76 05",
    "sg:postcode":"37160",
    "sg:province":"Centre",
    "sg:tags":[
        "cardboard"
    ],
    "wof:name":"Seysert Descartes Sa",
    "wof:placetype":"venue"
},
  "geometry": {"coordinates":[0.687555,46.979656],"type":"Point"}
}