{
  "type": "Feature",
  "properties": {
    "iso:country":"FR",
    "sg:address":"62, Rue du G\u00e9n\u00e9ral de Gaulle - Direction G\u00e9n\u00e9rale des Services Commerciaux, 78380 Bougival",
    "sg:orig_category":"Unclassifiable Establishments",
    "sg:phone":"+33 3 21 60 98 00",
    "sg:province":"Ile de France",
    "wof:name":"S.i.o. S.a. - Soci\u00e9t\u00e9 Industrielle Des Ol\u00e9agineux",
    "wof:placetype":"venue"
},
  "geometry": {"coordinates":[2.13922,48.86005],"type":"Point"}
}