{
  "type": "Feature",
  "properties": {
    "addr:full":"162, Rue de Paris, 92190 Meudon Ile de France",
    "addr:housenumber":"162",
    "addr:postcode":"92190",
    "addr:street":"Rue De Paris",
    "iso:country":"FR",
    "sg:address":"162, Rue de Paris, 92190 Meudon",
    "sg:orig_category":"Unclassifiable Establishments",
    "sg:phone":"+33 1 41 14 95 25",
    "sg:province":"Ile de France",
    "wof:name":"Expertam S.a.r.l.",
    "wof:placetype":"venue"
},
  "geometry": {"coordinates":[2.236382,48.807854],"type":"Point"}
}