{
  "type": "Feature",
  "properties": {
    "addr:full":"1225 Breenack Straete 59270 Merris Nord Pas-de-Calais 59270",
    "addr:housenumber":"1225",
    "addr:postcode":"59270;59270",
    "addr:street":"Breenack Straete",
    "iso:country":"FR",
    "sg:address":"1225 Breenack Straete 59270 Merris",
    "sg:classifiers":[
        {
            "category":"Shopping",
            "type":"Retail Goods"
        }
    ],
    "sg:phone":"+33 3 28 42 76 23",
    "sg:postcode":"59270",
    "sg:province":"Nord Pas-de-Calais",
    "sg:tags":[
        "metallurgy",
        "finished",
        "-",
        "metalworking",
        "metallic"
    ],
    "wof:name":"Debevre Sa",
    "wof:placetype":"venue"
},
  "geometry": {"coordinates":[2.659035,50.703396],"type":"Point"}
}