{
  "type": "Feature",
  "properties": {
    "iso:country":"FR",
    "sg:address":"1025 Rue Henri Becquerel Parc Club Du Mill\u00e9naire 34000 Montpellier",
    "sg:classifiers":[
        {
            "category":"Shopping",
            "subcategory":"Computers & Home Electronics",
            "type":"Retail Goods"
        }
    ],
    "sg:phone":"+33 4 67 15 45 45",
    "sg:postcode":"34000",
    "sg:province":"Languedoc-Roussillon",
    "sg:tags":[
        "equipment",
        "electrical",
        "component",
        "electric",
        "electronic"
    ],
    "wof:name":"Schneider Electric Industries Sa",
    "wof:placetype":"venue"
},
  "geometry": {"coordinates":[3.914558,43.609131],"type":"Point"}
}