{
  "type": "Feature",
  "properties": {
    "iso:country":"FR",
    "sg:address":"25, Rue Louis Amp\u00e8re - ZI des Chanoux, 93330 Neuilly sur Marne",
    "sg:orig_category":"Unclassifiable Establishments",
    "sg:phone":"+33 1 49 44 37 00",
    "sg:province":"Ile de France",
    "wof:name":"Bodycote Hit S.a.",
    "wof:placetype":"venue"
},
  "geometry": {"coordinates":[2.52871,48.857376],"type":"Point"}
}