{
  "type": "Feature",
  "properties": {
    "addr:full":"Bd La Fayette 62100 Calais Nord Pas-de-Calais 62100",
    "addr:postcode":"62100;62100",
    "addr:street":"Bd La Fayette;Calais;Pas-De-Calais",
    "iso:country":"FR",
    "sg:address":"Bd La Fayette 62100 Calais",
    "sg:classifiers":[
        {
            "category":"Professional",
            "subcategory":"Advertising",
            "type":"Services"
        }
    ],
    "sg:phone":"+33 3 21 85 97 97",
    "sg:postcode":"62100",
    "sg:province":"Nord Pas-de-Calais",
    "sg:tags":[
        "information",
        "medium",
        "communication"
    ],
    "wof:name":"Le Galibot",
    "wof:placetype":"venue"
},
  "geometry": {"coordinates":[1.855017,50.947495],"type":"Point"}
}