{
  "type": "Feature",
  "properties": {
    "iso:country":"FR",
    "sg:address":"17-21 All Du Dauphin\u00e9 91090 Lisses-Evry",
    "sg:classifiers":[
        {
            "category":"Shopping",
            "subcategory":"Computers & Home Electronics",
            "type":"Retail Goods"
        }
    ],
    "sg:phone":"+33 1 60 86 97 00",
    "sg:postcode":"91090",
    "sg:province":"Ile de France",
    "sg:tags":[
        "electric",
        "electricity",
        "component",
        "equipment",
        "electrical",
        "electronic"
    ],
    "wof:name":"Comptoir D'electricite Franco Belge (cefb)",
    "wof:placetype":"venue"
},
  "geometry": {"coordinates":[2.426028,48.611462],"type":"Point"}
}