{
  "type": "Feature",
  "properties": {
    "iso:country":"FR",
    "sg:address":"3, Rue de Granby - La Digonni\u00e8re , 42100 Saint Etienne",
    "sg:orig_category":"Non-Classified Establishments",
    "sg:phone":"+33 4 77 93 24 34",
    "sg:postcode":"42100",
    "sg:province":"Rhone-Alpes",
    "wof:name":"Entretiens Et Ramonages For\u00e9ziens S.a.r.l.",
    "wof:placetype":"venue"
},
  "geometry": {"coordinates":[4.387921,45.439053],"type":"Point"}
}