{
  "type": "Feature",
  "properties": {
    "addr:full":"39, Rue Pasteur, 57525 Talange Lorraine",
    "addr:housenumber":"39",
    "addr:postcode":"57525",
    "addr:street":"Rue Pasteur",
    "iso:country":"FR",
    "sg:address":"39, Rue Pasteur, 57525 Talange",
    "sg:orig_category":"Non-Classified Establishments",
    "sg:phone":"+33 3 87 71 35 06",
    "sg:province":"Lorraine",
    "wof:name":"Sporting France S.a.r.l.",
    "wof:placetype":"venue"
},
  "geometry": {"coordinates":[6.165458,49.239655],"type":"Point"}
}