{
  "type": "Feature",
  "properties": {
    "addr:full":"Za d'Arriet 40230 Benesse Maremne B\u00e9nesse-Maremne Aquitaine 40230",
    "addr:postcode":"40230;40230",
    "addr:street":"Za D'Arriet",
    "iso:country":"FR",
    "sg:address":"Za d'Arriet 40230 Benesse Maremne",
    "sg:city":"B\u00e9nesse-Maremne",
    "sg:classifiers":[
        {
            "category":"Professional",
            "type":"Services"
        }
    ],
    "sg:phone":"+33 5 58 41 85 40",
    "sg:postcode":"40230",
    "sg:province":"Aquitaine",
    "sg:tags":[
        "transport"
    ],
    "wof:name":"Mendy Developpement S.a.",
    "wof:placetype":"venue"
},
  "geometry": {"coordinates":[-1.396995,43.624634],"type":"Point"}
}