{
  "type": "Feature",
  "properties": {
    "addr:full":"5-7 Bd Tonnell\u00e9 37520 La Riche La Riche Centre 37520",
    "addr:housenumber":"5-7",
    "addr:postcode":"37520;37520",
    "addr:street":"Bd Tonnelle\u0301",
    "iso:country":"FR",
    "sg:address":"5-7 Bd Tonnell\u00e9 37520 La Riche",
    "sg:city":"La Riche",
    "sg:classifiers":[
        {
            "category":"Wholesale",
            "subcategory":"Medical Equipment & Supplies",
            "type":"Manufacturing & Wholesale Goods"
        }
    ],
    "sg:phone":"+33 2 47 37 01 87",
    "sg:postcode":"37520",
    "sg:province":"Centre",
    "sg:tags":[
        "instrument",
        "health",
        "-",
        "precision"
    ],
    "wof:name":"Jean Et Fils Ets Sarl",
    "wof:placetype":"venue"
},
  "geometry": {"coordinates":[0.668096,47.39151],"type":"Point"}
}