{
  "type": "Feature",
  "properties": {
    "iso:country":"FR",
    "sg:address":"ZI Egreteau",
    "sg:city":"Coutras",
    "sg:orig_category":"Unclassifiable Establishments",
    "sg:phone":"+33 5 57 69 34 93",
    "sg:postcode":"33230",
    "sg:province":"Aquitaine",
    "wof:name":"Artea S.a.",
    "wof:placetype":"venue"
},
  "geometry": {"coordinates":[-0.131489,45.038502],"type":"Point"}
}