{
  "type": "Feature",
  "properties": {
    "addr:full":"Zone Industrielle du canal Hochfelden Alsace 67270",
    "addr:postcode":"67270",
    "addr:street":"Zone Industrielle Du Canal Hochfelden",
    "iso:country":"FR",
    "sg:address":"Zone Industrielle du canal",
    "sg:city":"Hochfelden",
    "sg:orig_category":"Non-Classified Establishments",
    "sg:phone":"+33 3 88 91 56 77",
    "sg:postcode":"67270",
    "sg:province":"Alsace",
    "wof:name":"M\u00e9calec S.a.",
    "wof:placetype":"venue"
},
  "geometry": {"coordinates":[7.570045,48.757351],"type":"Point"}
}