{
  "type": "Feature",
  "properties": {
    "iso:country":"FR",
    "sg:address":"Route De Perpignan",
    "sg:city":"Crest 66380 Pia",
    "sg:classifiers":[
        {
            "category":"Home & Garden",
            "subcategory":"Furniture",
            "type":"Retail Goods"
        }
    ],
    "sg:phone":"+33 4 68 63 26 66",
    "sg:province":"Languedoc-Roussillon",
    "sg:tags":[
        "wood"
    ],
    "wof:name":"Ste Expl Etab Font Georges",
    "wof:placetype":"venue"
},
  "geometry": {"coordinates":[2.91039,42.741009],"type":"Point"}
}