{
  "type": "Feature",
  "properties": {
    "addr:full":"6, Rue Babonneau, 44100 Nantes Pays de Loire 44100",
    "addr:housenumber":"6",
    "addr:postcode":"44100;44100",
    "addr:street":"Rue Babonneau",
    "iso:country":"FR",
    "sg:address":"6, Rue Babonneau, 44100 Nantes",
    "sg:orig_category":"Non-Classified Establishments",
    "sg:phone":"+33 2 40 69 03 69",
    "sg:postcode":"44100",
    "sg:province":"Pays de Loire",
    "wof:name":"C.n.s.x. S.a.",
    "wof:placetype":"venue"
},
  "geometry": {"coordinates":[-1.57578,47.208046],"type":"Point"}
}