{
  "type": "Feature",
  "properties": {
    "addr:full":"3, Cami de Gabriac - ZI, 34560 Montbazin Languedoc-Roussillon",
    "addr:housenumber":"3",
    "addr:postcode":"34560",
    "addr:street":"Cami De Gabriac Zi",
    "iso:country":"FR",
    "sg:address":"3, Cami de Gabriac - ZI, 34560 Montbazin",
    "sg:orig_category":"Unclassifiable Establishments",
    "sg:phone":"+33 4 67 78 73 88",
    "sg:province":"Languedoc-Roussillon",
    "wof:name":"R\u00e9silac S.a.r.l.",
    "wof:placetype":"venue"
},
  "geometry": {"coordinates":[3.669425,43.489262],"type":"Point"}
}