{
  "type": "Feature",
  "properties": {
    "addr:full":"112, Bd Dalby, 44000 Nantes Pays de Loire",
    "addr:housenumber":"112",
    "addr:postcode":"44000",
    "addr:street":"Bd Dalby",
    "iso:country":"FR",
    "sg:address":"112, Bd Dalby, 44000 Nantes",
    "sg:orig_category":"Unclassifiable Establishments",
    "sg:phone":"+33 2 40 37 54 55",
    "sg:province":"Pays de Loire",
    "wof:name":"Fan S.a.r.l.",
    "wof:placetype":"venue"
},
  "geometry": {"coordinates":[-1.531416,47.221375],"type":"Point"}
}