{
  "type": "Feature",
  "properties": {
    "addr:full":"33 Espagne 31120 Portet sur Garonne Midi Pyr\u00e9n\u00e9es 31120",
    "addr:housenumber":"33",
    "addr:postcode":"31120;31120",
    "iso:country":"FR",
    "sg:address":"33",
    "sg:city":"Espagne 31120 Portet sur Garonne",
    "sg:classifiers":[
        {
            "category":"Home & Garden",
            "subcategory":"Furniture",
            "type":"Retail Goods"
        }
    ],
    "sg:phone":"+33 5 61 72 80 45",
    "sg:postcode":"31120",
    "sg:province":"Midi Pyr\u00e9n\u00e9es",
    "sg:tags":[
        "household",
        "wood"
    ],
    "wof:name":"Meubles Cerezo",
    "wof:placetype":"venue"
},
  "geometry": {"coordinates":[1.416566,43.543674],"type":"Point"}
}