{
  "type": "Feature",
  "properties": {
    "iso:country":"FR",
    "sg:address":"Rue Pierre Martin - Zone de l'Inqu\u00e9trie",
    "sg:city":"Saint Martin les Boulogne",
    "sg:orig_category":"Unclassifiable Establishments",
    "sg:phone":"+33 3 21 10 03 60",
    "sg:postcode":"62280",
    "sg:province":"Nord Pas-de-Calais",
    "wof:name":"Pharma Dom S.a.",
    "wof:placetype":"venue"
},
  "geometry": {"coordinates":[1.616011,50.724831],"type":"Point"}
}