{
  "type": "Feature",
  "properties": {
    "addr:full":"11, Rue Lacaze, 75014 Paris Ile de France",
    "addr:housenumber":"11",
    "addr:postcode":"75014",
    "addr:street":"Rue Lacaze",
    "iso:country":"FR",
    "sg:address":"11, Rue Lacaze, 75014 Paris",
    "sg:orig_category":"Unclassifiable Establishments",
    "sg:phone":"+33 1 40 52 01 20",
    "sg:province":"Ile de France",
    "wof:name":"Vigitel S.a.",
    "wof:placetype":"venue"
},
  "geometry": {"coordinates":[2.330402,48.824818],"type":"Point"}
}