{
  "type": "Feature",
  "properties": {
    "addr:full":"4, Rue du Commandant Leprieur, 56100 Lorient Lorient Bretagne 56100",
    "addr:housenumber":"4",
    "addr:postcode":"56100;56100",
    "addr:street":"Rue Du Commandant Leprieur",
    "iso:country":"FR",
    "sg:address":"4, Rue du Commandant Leprieur, 56100 Lorient",
    "sg:city":"Lorient",
    "sg:orig_category":"Non-Classified Establishments",
    "sg:phone":"+33 2 97 87 14 87",
    "sg:postcode":"56100",
    "sg:province":"Bretagne",
    "wof:name":"C.t.m. - Compagnie De Transports Du Morbihan",
    "wof:placetype":"venue"
},
  "geometry": {"coordinates":[-3.403054,47.765835],"type":"Point"}
}