{
  "type": "Feature",
  "properties": {
    "addr:full":"58 Avenue Des Terroirs De France 75012 Paris Ile de France 75012",
    "addr:housenumber":"58",
    "addr:postcode":"75012;75012",
    "addr:street":"Avenue Des Terroirs De France",
    "iso:country":"FR",
    "sg:address":"58 Avenue Des Terroirs De France 75012 Paris",
    "sg:classifiers":[
        {
            "category":"Food Court",
            "type":"Food & Drink"
        }
    ],
    "sg:phone":"+33 1 43 07 78 50",
    "sg:postcode":"75012",
    "sg:province":"Ile de France",
    "sg:tags":[
        "product",
        "related"
    ],
    "wof:name":"Ets Sardet Et Deribaucourt",
    "wof:placetype":"venue"
},
  "geometry": {"coordinates":[2.38681,48.830635],"type":"Point"}
}