{
  "type": "Feature",
  "properties": {
    "addr:full":"Ld La Vionni\u00e8re 53960 Bonchamp Les Laval Pays de Loire",
    "addr:postcode":"53960",
    "addr:street":"Ld;Bonchamp Les Laval",
    "iso:country":"FR",
    "sg:address":"Ld La Vionni\u00e8re 53960 Bonchamp Les Laval",
    "sg:classifiers":[
        {
            "category":"Home & Garden",
            "subcategory":"Furniture",
            "type":"Retail Goods"
        }
    ],
    "sg:phone":"+33 2 43 59 18 59",
    "sg:province":"Pays de Loire",
    "sg:tags":[
        "wood"
    ],
    "wof:name":"Pbm Ouest Agence Laval",
    "wof:placetype":"venue"
},
  "geometry": {"coordinates":[-0.722655,48.076714],"type":"Point"}
}