{
  "type": "Feature",
  "properties": {
    "addr:full":"18 Rue De Brest 67026 Strasbourg Strasbourg Alsace 67000",
    "addr:housenumber":"18",
    "addr:postcode":"67026;67000",
    "addr:street":"Rue De Brest",
    "iso:country":"FR",
    "sg:address":"18 Rue De Brest 67026 Strasbourg",
    "sg:city":"Strasbourg",
    "sg:classifiers":[
        {
            "category":"Building & Trades",
            "subcategory":"Construction",
            "type":"Services"
        }
    ],
    "sg:phone":"+33 3 88 39 41 78",
    "sg:postcode":"67000",
    "sg:province":"Alsace",
    "sg:tags":[
        "work",
        "public"
    ],
    "wof:name":"Cogifer Tf",
    "wof:placetype":"venue"
},
  "geometry": {"coordinates":[7.784684,48.535809],"type":"Point"}
}