{
  "type": "Feature",
  "properties": {
    "addr:full":"B.P. 221, 42800 Rive de Gier C\u00e9dex^^17, Rue Emile Zola, 42800 Rive de Gier Rhone-Alpes 42800",
    "addr:housenumber":"b.p. 221",
    "addr:postcode":"42800;42800;42800",
    "addr:street":"Rue Emile Zola;Rhone-Alpes",
    "iso:country":"FR",
    "sg:address":"B.P. 221, 42800 Rive de Gier C\u00e9dex^^17, Rue Emile Zola, 42800 Rive de Gier",
    "sg:orig_category":"Non-Classified Establishments",
    "sg:phone":"+33 4 77 75 00 42",
    "sg:postcode":"42800",
    "sg:province":"Rhone-Alpes",
    "wof:name":"C. M. S. S.a.r.l. - Chaudronnerie M\u00e9canique Service",
    "wof:placetype":"venue"
},
  "geometry": {"coordinates":[4.647085,45.478973],"type":"Point"}
}