{
  "type": "Feature",
  "properties": {
    "iso:country":"FR",
    "sg:address":"53, Rue Gambetta, 69740 Genas",
    "sg:orig_category":"Non-Classified Establishments",
    "sg:phone":"+33 4 74 90 72 83",
    "sg:postcode":"69740",
    "sg:province":"Rhone-Alpes",
    "wof:name":"Transports Allarousse S.a.r.l.",
    "wof:placetype":"venue"
},
  "geometry": {"coordinates":[5.02744,45.73291],"type":"Point"}
}