{
  "type": "Feature",
  "properties": {
    "addr:full":"Rue de la Garenne - Z.I. Vendargues C\u00e9dex Languedoc-Roussillon 34748",
    "addr:postcode":"ce\u0301dex;34748",
    "addr:street":"Rue De La Garenne Z.I.",
    "iso:country":"FR",
    "sg:address":"Rue de la Garenne - Z.I.",
    "sg:city":"Vendargues C\u00e9dex",
    "sg:orig_category":"Unclassifiable Establishments",
    "sg:phone":"+33 4 67 87 77 55",
    "sg:postcode":"34748",
    "sg:province":"Languedoc-Roussillon",
    "wof:name":"Kawneer France S.a.",
    "wof:placetype":"venue"
},
  "geometry": {"coordinates":[3.968675,43.655514],"type":"Point"}
}