{
  "type": "Feature",
  "properties": {
    "addr:full":"10A, Rue Kellermann, 67300 Schiltigheim Schiltigheim Alsace 67300",
    "addr:housenumber":"10a",
    "addr:postcode":"67300;67300",
    "addr:street":"Rue Kellermann",
    "iso:country":"FR",
    "sg:address":"10A, Rue Kellermann, 67300 Schiltigheim",
    "sg:city":"Schiltigheim",
    "sg:orig_category":"Unclassifiable Establishments",
    "sg:phone":"+33 3 88 19 99 96",
    "sg:postcode":"67300",
    "sg:province":"Alsace",
    "wof:name":"Data Tools Products S.a.r.l.",
    "wof:placetype":"venue"
},
  "geometry": {"coordinates":[7.732929,48.609276],"type":"Point"}
}