{
  "type": "Feature",
  "properties": {
    "addr:full":"92 rue de Courcelles 75008 Paris Ile de France",
    "addr:housenumber":"92",
    "addr:postcode":"75008",
    "addr:street":"Rue De Courcelles",
    "iso:country":"FR",
    "sg:address":"92 rue de Courcelles 75008 Paris",
    "sg:orig_category":"Properties For Films, Commercials, Advertising",
    "sg:phone":"+33 1 44 40 36 36",
    "sg:province":"Ile de France",
    "wof:name":"Prodimpor Sa",
    "wof:placetype":"venue"
},
  "geometry": {"coordinates":[2.303888,48.878841],"type":"Point"}
}