{
  "type": "Feature",
  "properties": {
    "addr:full":"Le Housset 35137 B\u00e9d\u00e9e B\u00e9d\u00e9e Bretagne 35137",
    "addr:postcode":"35137;35137",
    "iso:country":"FR",
    "sg:address":"Le Housset 35137 B\u00e9d\u00e9e",
    "sg:city":"B\u00e9d\u00e9e",
    "sg:orig_category":"Non-Classified Establishments",
    "sg:phone":"+33 2 99 07 04 59",
    "sg:postcode":"35137",
    "sg:province":"Bretagne",
    "wof:name":"Editions Folle Avoine",
    "wof:placetype":"venue"
},
  "geometry": {"coordinates":[-1.977464,48.162384],"type":"Point"}
}