{
  "type": "Feature",
  "properties": {
    "iso:country":"FR",
    "sg:address":"B.P. 11, 57620 Lemberg^^Rue de Sarreguemines - ZI, 57620 Lemberg",
    "sg:orig_category":"Non-Classified Establishments",
    "sg:phone":"+33 3 87 06 41 91",
    "sg:postcode":"57620",
    "sg:province":"Lorraine",
    "wof:name":"Cristyl S.a.r.l.",
    "wof:placetype":"venue"
},
  "geometry": {"coordinates":[7.379061,49.002766],"type":"Point"}
}