{
  "type": "Feature",
  "properties": {
    "iso:country":"FR",
    "sg:address":"40 bis, Rue Charles Mory, 91210 Draveil",
    "sg:orig_category":"Unclassifiable Establishments",
    "sg:phone":"+33 1 69 42 48 84",
    "sg:province":"Ile de France",
    "wof:name":"Lt Production S.a.r.l.",
    "wof:placetype":"venue"
},
  "geometry": {"coordinates":[2.432166,48.683205],"type":"Point"}
}