{
  "type": "Feature",
  "properties": {
    "addr:full":"18 avenue de Tourville 75007 Paris Ile de France",
    "addr:housenumber":"18",
    "addr:postcode":"75007",
    "addr:street":"Avenue De Tourville",
    "iso:country":"FR",
    "sg:address":"18 avenue de Tourville 75007 Paris",
    "sg:classifiers":[
        {
            "category":"Building & Trades",
            "subcategory":"Locksmith",
            "type":"Services"
        }
    ],
    "sg:phone":"+33 1 40 62 35 35",
    "sg:province":"Ile de France",
    "sg:tags":[
        "software"
    ],
    "wof:name":"Groupe Chauvin S.a.",
    "wof:placetype":"venue"
},
  "geometry": {"coordinates":[2.307662,48.854263],"type":"Point"}
}