{
  "type": "Feature",
  "properties": {
    "addr:full":"ZA - Les Lanches Cervens Rhone-Alpes 74550",
    "addr:postcode":"74550",
    "addr:street":"Za;Rhone-Alpes",
    "iso:country":"FR",
    "sg:address":"ZA - Les Lanches",
    "sg:city":"Cervens",
    "sg:orig_category":"Non-Classified Establishments",
    "sg:phone":"+33 4 50 72 03 46",
    "sg:postcode":"74550",
    "sg:province":"Rhone-Alpes",
    "wof:name":"Polydiam S.a.s.",
    "wof:placetype":"venue"
},
  "geometry": {"coordinates":[6.441158,46.286488],"type":"Point"}
}