{
  "type": "Feature",
  "properties": {
    "iso:country":"FR",
    "sg:address":"1 Chemin de St. Claude; Antibes; 06600",
    "sg:classifiers":[
        {
            "category":"Banks & Credit Unions",
            "subcategory":"Bank",
            "type":"Services"
        }
    ],
    "sg:phone":"+33 3393331849",
    "sg:province":"Franche Comt\u00e9",
    "wof:name":"Banca Commerciale, Italiana (france) Sa",
    "wof:placetype":"venue"
},
  "geometry": {"coordinates":[7.115051,43.592281],"type":"Point"}
}