{
  "type": "Feature",
  "properties": {
    "iso:country":"FR",
    "sg:address":"6, Rue de la Chapelle, 62217 Mercatel",
    "sg:orig_category":"Unclassifiable Establishments",
    "sg:phone":"+33 3 21 24 63 00",
    "sg:province":"Nord Pas-de-Calais",
    "wof:name":"J.m. Cauwet S.a.r.l.",
    "wof:placetype":"venue"
},
  "geometry": {"coordinates":[2.790541,50.234768],"type":"Point"}
}