{
  "type": "Feature",
  "properties": {
    "addr:full":"B.P. 25, 26140 Saint Rambert d'Albon C\u00e9dex^^ZI Le Cappa, 26140 Saint Rambert d'Albon Rhone-Alpes 26140",
    "addr:postcode":"26140;26140;26140",
    "addr:street":"B.P. 25;Rhone-Alpes",
    "iso:country":"FR",
    "sg:address":"B.P. 25, 26140 Saint Rambert d'Albon C\u00e9dex^^ZI Le Cappa, 26140 Saint Rambert d'Albon",
    "sg:orig_category":"Non-Classified Establishments",
    "sg:phone":"+33 4 75 31 32 25",
    "sg:postcode":"26140",
    "sg:province":"Rhone-Alpes",
    "wof:name":"Tarkett Sommer Rev\u00eatements France S.a.",
    "wof:placetype":"venue"
},
  "geometry": {"coordinates":[4.866955,45.249264],"type":"Point"}
}