{
  "type": "Feature",
  "properties": {
    "addr:full":"19 Rue Des Deux Gares 92500 Rueil-Malmaison Ile de France 92500",
    "addr:housenumber":"19",
    "addr:postcode":"92500;ile;92500",
    "addr:street":"Rue Des Deux Gares;France",
    "iso:country":"FR",
    "sg:address":"19 Rue Des Deux Gares 92500 Rueil-Malmaison",
    "sg:classifiers":[
        {
            "category":"Food Court",
            "type":"Food & Drink"
        }
    ],
    "sg:phone":"+33 1 47 14 36 50",
    "sg:postcode":"92500",
    "sg:province":"Ile de France",
    "sg:tags":[
        "product",
        "related"
    ],
    "wof:name":"Heineken",
    "wof:placetype":"venue"
},
  "geometry": {"coordinates":[2.172068,48.888123],"type":"Point"}
}