{
  "type": "Feature",
  "properties": {
    "addr:full":"Allee Jules Milhau Lotissement 223 Cc Polygone 34000 Montpellier Languedoc-Roussillon 34000",
    "addr:postcode":"34000;34000",
    "addr:street":"Allee Jules Milhau Lotissement 223 Cc Polygone",
    "iso:country":"FR",
    "sg:address":"Allee Jules Milhau Lotissement 223 Cc Polygone 34000 Montpellier",
    "sg:classifiers":[
        {
            "category":"Shopping",
            "subcategory":"Clothing, Apparel, & Fashions",
            "type":"Retail Goods"
        }
    ],
    "sg:phone":"+33 4 67 64 29 36",
    "sg:postcode":"34000",
    "sg:province":"Languedoc-Roussillon",
    "sg:tags":[
        "textile",
        "clothing",
        "clothes"
    ],
    "wof:name":"Promod",
    "wof:placetype":"venue"
},
  "geometry": {"coordinates":[3.87609,43.610855],"type":"Point"}
}