{
  "type": "Feature",
  "properties": {
    "iso:country":"FR",
    "sg:address":"7 Av Valparc 68440 Habsheim",
    "sg:city":"Habsheim",
    "sg:classifiers":[
        {
            "category":"Shopping",
            "subcategory":"Computers & Home Electronics",
            "type":"Retail Goods"
        }
    ],
    "sg:phone":"+33 3 89 65 93 00",
    "sg:postcode":"68440",
    "sg:province":"Alsace",
    "sg:tags":[
        "electronic",
        "electrical",
        "equipment"
    ],
    "wof:name":"Moteurs Leroy Somer",
    "wof:placetype":"venue"
},
  "geometry": {"coordinates":[7.42003,47.740181],"type":"Point"}
}