{
  "type": "Feature",
  "properties": {
    "iso:country":"FR",
    "sg:address":"Route De Bourgtheroulde 27670 Le Bosc Roger En Roumois",
    "sg:classifiers":[
        {
            "category":"Manufacturing",
            "subcategory":"Chemicals & Compounds",
            "type":"Manufacturing & Wholesale Goods"
        }
    ],
    "sg:phone":"+33 2 32 96 93 80",
    "sg:postcode":"27670",
    "sg:province":"Haute Normandie",
    "sg:tags":[
        "pharmaceutical",
        "chemistry",
        "-",
        "by-product"
    ],
    "wof:name":"Purodor Sa",
    "wof:placetype":"venue"
},
  "geometry": {"coordinates":[0.90228,49.297852],"type":"Point"}
}