{
  "type": "Feature",
  "properties": {
    "iso:country":"FR",
    "sg:address":"74, Rue Amp\u00e8re - ZI de Jarlard, 81000 Albi",
    "sg:orig_category":"Non-Classified Establishments",
    "sg:phone":"+33 5 63 77 37 90",
    "sg:province":"Midi Pyr\u00e9n\u00e9es",
    "wof:name":"M.c.a. S.a.r.l. - Manufacture De Chemiserie D'albi",
    "wof:placetype":"venue"
},
  "geometry": {"coordinates":[2.148375,43.926205],"type":"Point"}
}