{
  "type": "Feature",
  "properties": {
    "addr:full":"263, Av. J. B. Arnoux - ZA de la Sipi\u00e8re, 13730 Saint Victoret Midi Pyr\u00e9n\u00e9es",
    "addr:postcode":"13730",
    "addr:street":"263 Av. J. B. Arnoux Za De La Sipie\u0300Re",
    "iso:country":"FR",
    "sg:address":"263, Av. J. B. Arnoux - ZA de la Sipi\u00e8re, 13730 Saint Victoret",
    "sg:orig_category":"Non-Classified Establishments",
    "sg:phone":"+33 4 42 89 88 75",
    "sg:province":"Midi Pyr\u00e9n\u00e9es",
    "wof:name":"Delta-fusion E.u.r.l.",
    "wof:placetype":"venue"
},
  "geometry": {"coordinates":[5.23605,43.419994],"type":"Point"}
}