{
  "type": "Feature",
  "properties": {
    "addr:full":"69 Rue Jean Mermoz 95230 Soisy Sous Montmorency Ile de France",
    "addr:housenumber":"69",
    "addr:postcode":"95230",
    "addr:street":"Rue Jean Mermoz",
    "iso:country":"FR",
    "sg:address":"69 Rue Jean Mermoz 95230 Soisy Sous Montmorency",
    "sg:classifiers":[
        {
            "category":"Professional",
            "type":"Services"
        }
    ],
    "sg:phone":"+33 1 39 89 32 27",
    "sg:province":"Ile de France",
    "sg:tags":[
        "transport",
        "road"
    ],
    "wof:name":"Burguiere Marcel",
    "wof:placetype":"venue"
},
  "geometry": {"coordinates":[2.30522,48.983379],"type":"Point"}
}