{
  "type": "Feature",
  "properties": {
    "iso:country":"FR",
    "sg:address":"51 Av De La Gare 42680 St Marcellin En Forez",
    "sg:classifiers":[
        {
            "category":"Food Court",
            "type":"Food & Drink"
        }
    ],
    "sg:phone":"+33 4 77 52 96 88",
    "sg:postcode":"42680",
    "sg:province":"Rhone-Alpes",
    "sg:tags":[
        "product",
        "related"
    ],
    "wof:name":"Forez Levure Sarl",
    "wof:placetype":"venue"
},
  "geometry": {"coordinates":[4.18073,45.495079],"type":"Point"}
}