{
  "type": "Feature",
  "properties": {
    "iso:country":"FR",
    "sg:address":"18, Rue du Sauvoy, 77165 Saint Soupplets",
    "sg:orig_category":"Non-Classified Establishments",
    "sg:phone":"+33 1 60 01 03 67",
    "sg:province":"Ile de France",
    "wof:name":"Sardou S.a.",
    "wof:placetype":"venue"
},
  "geometry": {"coordinates":[2.802633,49.033508],"type":"Point"}
}