{
  "type": "Feature",
  "properties": {
    "iso:country":"FR",
    "sg:address":"Kerebars 29820 Guilers",
    "sg:city":"Guilers",
    "sg:classifiers":[
        {
            "category":"Manufacturing",
            "subcategory":"Chemicals & Compounds",
            "type":"Manufacturing & Wholesale Goods"
        }
    ],
    "sg:phone":"+33 2 98 07 53 70",
    "sg:postcode":"29820",
    "sg:province":"Bretagne",
    "sg:tags":[
        "pharmaceutical",
        "chemistry",
        "-",
        "by-product"
    ],
    "wof:name":"Raub Brest",
    "wof:placetype":"venue"
},
  "geometry": {"coordinates":[-4.576271,48.424911],"type":"Point"}
}