{
  "type": "Feature",
  "properties": {
    "iso:country":"FR",
    "sg:address":"ZA les Bredanes",
    "sg:city":"Baule",
    "sg:orig_category":"Unclassifiable Establishments",
    "sg:phone":"+33 2 38 45 00 70",
    "sg:postcode":"45130",
    "sg:province":"Centre",
    "wof:name":"M.d.e. S.a.",
    "wof:placetype":"venue"
},
  "geometry": {"coordinates":[1.671607,47.811596],"type":"Point"}
}