{
  "type": "Feature",
  "properties": {
    "addr:full":"Rte de Chatillon Ch\u00e2tillon le Duc Franche Comt\u00e9 25870",
    "addr:postcode":"25870",
    "addr:street":"Rte De Chatillon;Franche Comte\u0301",
    "iso:country":"FR",
    "sg:address":"Rte de Chatillon",
    "sg:city":"Ch\u00e2tillon le Duc",
    "sg:orig_category":"Unclassifiable Establishments",
    "sg:phone":"+33 3 81 88 63 33",
    "sg:postcode":"25870",
    "sg:province":"Franche Comt\u00e9",
    "wof:name":"M.b.s. S.a.r.l. - Mat\u00e9riel B\u00e2timent Services",
    "wof:placetype":"venue"
},
  "geometry": {"coordinates":[5.99286,47.284695],"type":"Point"}
}