{
  "type": "Feature",
  "properties": {
    "addr:full":"87, Rue Ernest Sylvain Boll\u00e9e - ZAC de la Rivi\u00e8re, 72230 Arnage Pays de Loire 72230",
    "addr:housenumber":"87",
    "addr:postcode":"72230;72230",
    "addr:street":"Rue Ernest Sylvain Bolle\u0301E Zac De La Rivie\u0300Re",
    "iso:country":"FR",
    "sg:address":"87, Rue Ernest Sylvain Boll\u00e9e - ZAC de la Rivi\u00e8re, 72230 Arnage",
    "sg:orig_category":"Non-Classified Establishments",
    "sg:phone":"+33 2 43 39 09 30",
    "sg:postcode":"72230",
    "sg:province":"Pays de Loire",
    "wof:name":"Axima R\u00e9frig\u00e9ration France S.a.",
    "wof:placetype":"venue"
},
  "geometry": {"coordinates":[0.12903,47.877361],"type":"Point"}
}