{
  "type": "Feature",
  "properties": {
    "iso:country":"FR",
    "sg:address":"44 Rn Ccal Auchan 02100 Fayet",
    "sg:classifiers":[
        {
            "category":"Travel",
            "subcategory":"Hotels & Motels",
            "type":"Entertainment"
        }
    ],
    "sg:phone":"+33 3 23 67 16 18",
    "sg:postcode":"02100",
    "sg:province":"Picardie",
    "sg:tags":[
        "hotels",
        "business",
        "restaurant"
    ],
    "wof:name":"Flunch",
    "wof:placetype":"venue"
},
  "geometry": {"coordinates":[3.291399,49.850842],"type":"Point"}
}