{
  "type": "Feature",
  "properties": {
    "iso:country":"FR",
    "sg:address":"22, Rue des Tambourins, 30230 Bouillargues",
    "sg:orig_category":"Unclassifiable Establishments",
    "sg:phone":"+33 4 66 20 72 00",
    "sg:province":"Languedoc-Roussillon",
    "wof:name":"I.m.a. S.a.r.l.",
    "wof:placetype":"venue"
},
  "geometry": {"coordinates":[4.432419,43.797588],"type":"Point"}
}