{
  "type": "Feature",
  "properties": {
    "iso:country":"FR",
    "sg:address":"69 Rue Francis Combe 95000 Cergy",
    "sg:classifiers":[
        {
            "category":"Professional",
            "subcategory":"Engineering",
            "type":"Services"
        }
    ],
    "sg:phone":"+33 1 34 24 92 58",
    "sg:postcode":"95000",
    "sg:province":"Ile de France",
    "sg:tags":[
        "machine",
        "-",
        "mechanical"
    ],
    "wof:name":"Climat Concept",
    "wof:placetype":"venue"
},
  "geometry": {"coordinates":[2.070635,49.045292],"type":"Point"}
}