{
  "type": "Feature",
  "properties": {
    "addr:full":"38 Rue Des Tanneries 03000 Moulins Moulins Auvergne 03000",
    "addr:housenumber":"38",
    "addr:postcode":"03000;03000",
    "addr:street":"Rue Des Tanneries",
    "iso:country":"FR",
    "sg:address":"38 Rue Des Tanneries 03000 Moulins",
    "sg:city":"Moulins",
    "sg:classifiers":[
        {
            "category":"Wholesale",
            "subcategory":"Medical Equipment & Supplies",
            "type":"Manufacturing & Wholesale Goods"
        }
    ],
    "sg:phone":"+33 4 70 20 49 41",
    "sg:postcode":"03000",
    "sg:province":"Auvergne",
    "sg:tags":[
        "instrument",
        "health",
        "-",
        "precision"
    ],
    "wof:name":"O Dubessay J R Dinet B Jean",
    "wof:placetype":"venue"
},
  "geometry": {"coordinates":[3.336903,46.566147],"type":"Point"}
}