{
  "type": "Feature",
  "properties": {
    "iso:country":"FR",
    "sg:address":"1, Rue Cl\u00e9ment Ader - Z.I. des Cirdiers, 91700 Fleury M\u00e9rogis",
    "sg:orig_category":"Non-Classified Establishments",
    "sg:phone":"+33 1 69 46 75 00",
    "sg:postcode":"91700",
    "sg:province":"Ile de France",
    "wof:name":"Agence T.s.n. S.a.r.l.",
    "wof:placetype":"venue"
},
  "geometry": {"coordinates":[2.326545,48.640656],"type":"Point"}
}