{
  "type": "Feature",
  "properties": {
    "addr:full":"4 Rue Anthoard 38000 Grenoble Rhone-Alpes 38000",
    "addr:housenumber":"4",
    "addr:postcode":"38000;38000",
    "addr:street":"Rue Anthoard",
    "iso:country":"FR",
    "sg:address":"4 Rue Anthoard 38000 Grenoble",
    "sg:classifiers":[
        {
            "category":"Building & Trades",
            "subcategory":"Electrical",
            "type":"Services"
        }
    ],
    "sg:phone":"+33 4 76 96 12 03",
    "sg:postcode":"38000",
    "sg:province":"Rhone-Alpes",
    "sg:tags":[
        "electronic",
        "lighting",
        "equipment"
    ],
    "wof:name":"Gaines Et Tableaux Electriques Get Electric",
    "wof:placetype":"venue"
},
  "geometry": {"coordinates":[5.713084,45.189438],"type":"Point"}
}