{
  "type": "Feature",
  "properties": {
    "iso:country":"FR",
    "sg:address":"B.P. 20, 73492 La Ravoire C\u00e9dex^^267, Rue Emile Zola, 73490 La Ravoire",
    "sg:orig_category":"Non-Classified Establishments",
    "sg:phone":"+33 4 79 72 82 62",
    "sg:province":"Rhone-Alpes",
    "wof:name":"I.c.r. Technique S.a.r.l. - Inox Concept R\u00e9alisation Technique",
    "wof:placetype":"venue"
},
  "geometry": {"coordinates":[5.961922,45.55677],"type":"Point"}
}