{
  "type": "Feature",
  "properties": {
    "iso:country":"FR",
    "sg:address":"Bourg 87130 Ch\u00e2teauneuf La For\u00eat",
    "sg:classifiers":[
        {
            "category":"Manufacturing",
            "subcategory":"Paper Products",
            "type":"Manufacturing & Wholesale Goods"
        }
    ],
    "sg:phone":"+33 5 55 69 80 80",
    "sg:province":"Limousin",
    "sg:tags":[
        "packaging",
        "material",
        "-",
        "cardboard"
    ],
    "wof:name":"Emin Leydier Emballages",
    "wof:placetype":"venue"
},
  "geometry": {"coordinates":[1.64908,45.606365],"type":"Point"}
}