{
  "type": "Feature",
  "properties": {
    "addr:full":"104, Av. du G\u00e9n\u00e9ral Leclerc, 28100 Dreux Dreux Centre 28100",
    "addr:housenumber":"dreux",
    "addr:postcode":"28100;28100",
    "addr:street":"104 Av. Du Ge\u0301Ne\u0301Ral Leclerc",
    "iso:country":"FR",
    "sg:address":"104, Av. du G\u00e9n\u00e9ral Leclerc, 28100 Dreux",
    "sg:city":"Dreux",
    "sg:orig_category":"Non-Classified Establishments",
    "sg:phone":"+33 2 37 38 58 88",
    "sg:postcode":"28100",
    "sg:province":"Centre",
    "wof:name":"Delta Conseil P.m.e. S.a.",
    "wof:placetype":"venue"
},
  "geometry": {"coordinates":[1.385128,48.741219],"type":"Point"}
}