{
  "type": "Feature",
  "properties": {
    "iso:country":"FR",
    "sg:address":"48 Av Gresivaudan 38700 Corenc",
    "sg:classifiers":[
        {
            "category":"Professional",
            "subcategory":"Business Services",
            "type":"Services"
        }
    ],
    "sg:phone":"+33 4 76 90 97 97",
    "sg:postcode":"38700",
    "sg:province":"Rhone-Alpes",
    "sg:tags":[
        "information",
        "advice",
        "technology",
        "software"
    ],
    "wof:name":"Sonart",
    "wof:placetype":"venue"
},
  "geometry": {"coordinates":[5.759933,45.20932],"type":"Point"}
}