{
  "type": "Feature",
  "properties": {
    "iso:country":"FR",
    "sg:address":"B.P. 18, 95221 Herblay C\u00e9dex^^138, Chemin des Ch\u00eane, 95220 Herblay",
    "sg:orig_category":"Non-Classified Establishments",
    "sg:phone":"+33 1 39 97 14 24",
    "sg:province":"Ile de France",
    "wof:name":"Fauquet S.a.",
    "wof:placetype":"venue"
},
  "geometry": {"coordinates":[2.163532,48.989609],"type":"Point"}
}