{
  "type": "Feature",
  "properties": {
    "iso:country":"FR",
    "sg:address":"Rue Jean Monnet",
    "sg:city":"Le Creusot",
    "sg:orig_category":"Unclassifiable Establishments",
    "sg:phone":"+33 3 85 77 47 00",
    "sg:postcode":"71200",
    "sg:province":"Bourgogne",
    "wof:name":"Seic S.a.",
    "wof:placetype":"venue"
},
  "geometry": {"coordinates":[4.42025,46.807213],"type":"Point"}
}