{
  "type": "Feature",
  "properties": {
    "addr:full":"50 Rue Du Stade 54660 Moutiers Lorraine 54660",
    "addr:housenumber":"50",
    "addr:postcode":"54660;54660",
    "addr:street":"Rue Du Stade",
    "iso:country":"FR",
    "sg:address":"50 Rue Du Stade 54660 Moutiers",
    "sg:classifiers":[
        {
            "category":"Shopping",
            "type":"Retail Goods"
        }
    ],
    "sg:phone":"+33 3 82 46 06 37",
    "sg:postcode":"54660",
    "sg:province":"Lorraine",
    "sg:tags":[
        "metallurgy",
        "finished",
        "-",
        "metalworking",
        "metallic"
    ],
    "wof:name":"Stima Ste",
    "wof:placetype":"venue"
},
  "geometry": {"coordinates":[5.97789,49.239731],"type":"Point"}
}