{
  "type": "Feature",
  "properties": {
    "addr:full":"24, All\u00e9e du Closeau - ZI les Richardets, 93160 Noisy le Grand Ile de France",
    "addr:housenumber":"24",
    "addr:postcode":"93160",
    "addr:street":"Alle\u0301E Du Closeau Zi Les Richardets",
    "iso:country":"FR",
    "sg:address":"24, All\u00e9e du Closeau - ZI les Richardets, 93160 Noisy le Grand",
    "sg:orig_category":"Unclassifiable Establishments",
    "sg:phone":"+33 1 43 03 17 17",
    "sg:province":"Ile de France",
    "wof:name":"D\u00e9part Presse S.a.r.l.",
    "wof:placetype":"venue"
},
  "geometry": {"coordinates":[2.553644,48.848892],"type":"Point"}
}