{
  "type": "Feature",
  "properties": {
    "addr:full":"77 Rte Du Collier 62650 Preures Nord Pas-de-Calais",
    "addr:housenumber":"77",
    "addr:postcode":"62650",
    "addr:street":"Rte Du Collier",
    "iso:country":"FR",
    "sg:address":"77 Rte Du Collier 62650 Preures",
    "sg:classifiers":[
        {
            "category":"Professional",
            "type":"Services"
        }
    ],
    "sg:phone":"+33 3 21 90 50 27",
    "sg:province":"Nord Pas-de-Calais",
    "sg:tags":[
        "transport",
        "road"
    ],
    "wof:name":"Jules Dacquin Sarl",
    "wof:placetype":"venue"
},
  "geometry": {"coordinates":[1.877404,50.572071],"type":"Point"}
}