{
  "type": "Feature",
  "properties": {
    "addr:full":"42 Rue De La Croix De Seguey 33000 Bordeaux Bordeaux Aquitaine 33000",
    "addr:housenumber":"42",
    "addr:postcode":"33000;33000",
    "addr:street":"Rue De La Croix De Seguey",
    "iso:country":"FR",
    "sg:address":"42 Rue De La Croix De Seguey 33000 Bordeaux",
    "sg:city":"Bordeaux",
    "sg:classifiers":[
        {
            "category":"Wholesale",
            "subcategory":"Medical Equipment & Supplies",
            "type":"Manufacturing & Wholesale Goods"
        }
    ],
    "sg:phone":"+33 5 56 48 24 14",
    "sg:postcode":"33000",
    "sg:province":"Aquitaine",
    "sg:tags":[
        "instrument",
        "health",
        "-",
        "precision"
    ],
    "wof:name":"Omnium Dentaire Sa Laurent Seguy",
    "wof:placetype":"venue"
},
  "geometry": {"coordinates":[-0.588657,44.850971],"type":"Point"}
}