{
  "type": "Feature",
  "properties": {
    "addr:full":"B.P. 3, 51190 Le Mesnil sur Oger^^5-7, Rue de la Breche d'Oger, 51190 Le Mesnil sur Oger Champagne",
    "addr:housenumber":"3;-7",
    "addr:postcode":"51190;51190",
    "addr:street":"B.P.;Mesnil;Oger^^5;Rue De La Breche D'Oger;Mesnil;Oger",
    "iso:country":"FR",
    "sg:address":"B.P. 3, 51190 Le Mesnil sur Oger^^5-7, Rue de la Breche d'Oger, 51190 Le Mesnil sur Oger",
    "sg:orig_category":"Non-Classified Establishments",
    "sg:phone":"+33 3 26 57 51 65",
    "sg:province":"Champagne",
    "wof:name":"Soci\u00e9t\u00e9 A.s. S.a.",
    "wof:placetype":"venue"
},
  "geometry": {"coordinates":[4.0138,48.958752],"type":"Point"}
}