{
  "type": "Feature",
  "properties": {
    "addr:full":"8 pl du Parlement; Rennes; 35004 Aquitaine",
    "addr:housenumber":"8",
    "addr:postcode":"35004",
    "addr:street":"Pl Du Parlement",
    "iso:country":"FR",
    "sg:address":"8 pl du Parlement; Rennes; 35004",
    "sg:classifiers":[
        {
            "category":"Banks & Credit Unions",
            "subcategory":"Bank",
            "type":"Services"
        }
    ],
    "sg:phone":"+33 3399792223",
    "sg:province":"Aquitaine",
    "wof:name":"Cr\u00e9dit Foncier De France",
    "wof:placetype":"venue"
},
  "geometry": {"coordinates":[-1.684477,48.107521],"type":"Point"}
}