{
  "type": "Feature",
  "properties": {
    "addr:full":"Rue Lanserre Juign\u00e9 sur Loire Pays de Loire 49610",
    "addr:postcode":"49610",
    "addr:street":"Rue Lanserre Juigne\u0301 Sur Loire",
    "iso:country":"FR",
    "sg:address":"Rue Lanserre",
    "sg:city":"Juign\u00e9 sur Loire",
    "sg:orig_category":"Unclassifiable Establishments",
    "sg:phone":"+33 2 41 45 60 00",
    "sg:postcode":"49610",
    "sg:province":"Pays de Loire",
    "wof:name":"F.c.i. S.a.r.l.",
    "wof:placetype":"venue"
},
  "geometry": {"coordinates":[-0.501623,47.390484],"type":"Point"}
}