{
  "type": "Feature",
  "properties": {
    "addr:full":"18 Rue Louis Pasteur 02800 Vendeuil Picardie",
    "addr:housenumber":"18",
    "addr:postcode":"02800",
    "addr:street":"Rue Louis Pasteur",
    "iso:country":"FR",
    "sg:address":"18 Rue Louis Pasteur 02800 Vendeuil",
    "sg:classifiers":[
        {
            "category":"Professional",
            "type":"Services"
        }
    ],
    "sg:phone":"+33 3 23 07 81 00",
    "sg:province":"Picardie",
    "sg:tags":[
        "transport",
        "road"
    ],
    "wof:name":"Saleine Transports Sa",
    "wof:placetype":"venue"
},
  "geometry": {"coordinates":[3.351216,49.716965],"type":"Point"}
}