{
  "type": "Feature",
  "properties": {
    "iso:country":"FR",
    "sg:address":"1 Bd Marcel Dassault Z I Du Velin 69330 Jonage",
    "sg:classifiers":[
        {
            "category":"Shopping",
            "type":"Retail Goods"
        }
    ],
    "sg:phone":"+33 4 78 04 09 69",
    "sg:province":"Rhone-Alpes",
    "sg:tags":[
        "metallurgy",
        "finished",
        "-",
        "metalworking",
        "metallic"
    ],
    "wof:name":"Exatole",
    "wof:placetype":"venue"
},
  "geometry": {"coordinates":[5.00581,45.766296],"type":"Point"}
}