{
  "type": "Feature",
  "properties": {
    "addr:full":"43 Rue St Jean 54000 Nancy Lorraine 54000",
    "addr:housenumber":"43",
    "addr:postcode":"54000;54000",
    "addr:street":"Rue St Jean",
    "iso:country":"FR",
    "sg:address":"43 Rue St Jean 54000 Nancy",
    "sg:classifiers":[
        {
            "category":"Shopping",
            "subcategory":"Luggage & Leather Goods",
            "type":"Retail Goods"
        }
    ],
    "sg:phone":"+33 3 83 39 11 39",
    "sg:postcode":"54000",
    "sg:province":"Lorraine",
    "sg:tags":[
        "shoe"
    ],
    "wof:name":"Chaussures Cendry",
    "wof:placetype":"venue"
},
  "geometry": {"coordinates":[6.18004,48.689899],"type":"Point"}
}