{
  "type": "Feature",
  "properties": {
    "addr:full":"B.P. 3, 49150 Baug\u00e9 C\u00e9dex^^Rte de Tours, 49150 Baug\u00e9 Pays de Loire",
    "addr:housenumber":"3",
    "addr:postcode":"49150;49150",
    "addr:street":"B.P.;Tours",
    "iso:country":"FR",
    "sg:address":"B.P. 3, 49150 Baug\u00e9 C\u00e9dex^^Rte de Tours, 49150 Baug\u00e9",
    "sg:orig_category":"Non-Classified Establishments",
    "sg:phone":"+33 2 41 84 12 00",
    "sg:province":"Pays de Loire",
    "wof:name":"S.a.m.a. S.a.",
    "wof:placetype":"venue"
},
  "geometry": {"coordinates":[-0.063909,47.46994],"type":"Point"}
}