{
  "type": "Feature",
  "properties": {
    "addr:full":"Z.I. de la Perelle Saint R\u00e9my sur Durolle Auvergne 63550",
    "addr:postcode":"63550",
    "addr:street":"Z.I. De La Perelle Saint Re\u0301My Sur Durolle",
    "iso:country":"FR",
    "sg:address":"Z.I. de la Perelle",
    "sg:city":"Saint R\u00e9my sur Durolle",
    "sg:orig_category":"Non-Classified Establishments",
    "sg:phone":"+33 4 73 94 31 65",
    "sg:postcode":"63550",
    "sg:province":"Auvergne",
    "wof:name":"Florinox S.a.",
    "wof:placetype":"venue"
},
  "geometry": {"coordinates":[3.596234,45.890507],"type":"Point"}
}