{
  "type": "Feature",
  "properties": {
    "addr:full":"ZAC de la Gobette 60540 Puiseux le Hauberger Picardie",
    "addr:postcode":"60540",
    "addr:street":"Zac De La Gobette",
    "iso:country":"FR",
    "sg:address":"ZAC de la Gobette 60540 Puiseux le Hauberger",
    "sg:classifiers":[
        {
            "category":"Wholesale",
            "subcategory":"Medical Equipment & Supplies",
            "type":"Manufacturing & Wholesale Goods"
        }
    ],
    "sg:phone":"+33 3 44 26 64 53",
    "sg:province":"Picardie",
    "sg:tags":[
        "instrument",
        "surgical"
    ],
    "wof:name":"Isomed Sarl",
    "wof:placetype":"venue"
},
  "geometry": {"coordinates":[2.234361,49.211147],"type":"Point"}
}