{
  "type": "Feature",
  "properties": {
    "addr:full":"ZA du Val Coric Guer Bretagne 56380",
    "addr:postcode":"56380",
    "addr:street":"Za Du Val Coric Guer",
    "iso:country":"FR",
    "sg:address":"ZA du Val Coric",
    "sg:city":"Guer",
    "sg:orig_category":"Non-Classified Establishments",
    "sg:phone":"+33 2 97 22 50 80",
    "sg:postcode":"56380",
    "sg:province":"Bretagne",
    "wof:name":"Le Villo S.a.r.l.",
    "wof:placetype":"venue"
},
  "geometry": {"coordinates":[-2.120234,47.902081],"type":"Point"}
}