{
  "type": "Feature",
  "properties": {
    "iso:country":"FR",
    "sg:address":"B.P. 130",
    "sg:city":"Saint Dizier C\u00e9dex",
    "sg:orig_category":"Non-Classified Establishments",
    "sg:phone":"+33 3 25 96 01 06",
    "sg:postcode":"52108",
    "sg:province":"Bourgogne",
    "wof:name":"C.p.h. Distribution S.a.r.l. - Comptoir Pneumatique Hydraulique",
    "wof:placetype":"venue"
},
  "geometry": {"coordinates":[4.946965,48.636589],"type":"Point"}
}