{
  "type": "Feature",
  "properties": {
    "addr:full":"109, Rue du Faubourg Saint Honor\u00e9, 75008 Paris Ile de France",
    "addr:housenumber":"109",
    "addr:postcode":"75008",
    "addr:street":"Rue Du Faubourg Saint Honore\u0301",
    "iso:country":"FR",
    "sg:address":"109, Rue du Faubourg Saint Honor\u00e9, 75008 Paris",
    "sg:orig_category":"Unclassifiable Establishments",
    "sg:phone":"+33 1 53 77 15 00",
    "sg:province":"Ile de France",
    "wof:name":"A\u00e9rolin\u00e9as Argentinas S.a.",
    "wof:placetype":"venue"
},
  "geometry": {"coordinates":[2.311182,48.872505],"type":"Point"}
}