{
  "type": "Feature",
  "properties": {
    "addr:full":"B.P. 38, 68501 Guebwiller^^3, Rue de la Plaine - ZI, 68500 Guebwiller Guebwiller Alsace 68500",
    "addr:postcode":"68501;68500;68500",
    "addr:street":"B.P. 38;Rue De La Plaine Zi",
    "iso:country":"FR",
    "sg:address":"B.P. 38, 68501 Guebwiller^^3, Rue de la Plaine - ZI, 68500 Guebwiller",
    "sg:city":"Guebwiller",
    "sg:orig_category":"Non-Classified Establishments",
    "sg:phone":"+33 3 89 74 99 99",
    "sg:postcode":"68500",
    "sg:province":"Alsace",
    "wof:name":"S.t.g. S.a.r.l. - Service Et Techniques De Guebwiller",
    "wof:placetype":"venue"
},
  "geometry": {"coordinates":[7.210785,47.9095],"type":"Point"}
}