{
  "type": "Feature",
  "properties": {
    "addr:full":"Ctre Cal Joli Mai; Meudon; 92360 Nord Pas-de-Calais",
    "addr:postcode":"92360",
    "iso:country":"FR",
    "sg:address":"Ctre Cal Joli Mai; Meudon; 92360",
    "sg:classifiers":[
        {
            "category":"Banks & Credit Unions",
            "subcategory":"Bank",
            "type":"Services"
        }
    ],
    "sg:phone":"+33 16304812",
    "sg:province":"Nord Pas-de-Calais",
    "wof:name":"Cr\u00e9dit Industriel Et, Commercial De Paris",
    "wof:placetype":"venue"
},
  "geometry": {"coordinates":[2.228995,48.785675],"type":"Point"}
}