{
  "type": "Feature",
  "properties": {
    "iso:country":"FR",
    "sg:address":"6, Impasse de la Fraternit\u00e9, 64400 Oloron Sainte Marie",
    "sg:city":"Oloron-Sainte-Marie",
    "sg:orig_category":"Unclassifiable Establishments",
    "sg:phone":"+33 5 59 39 11 49",
    "sg:postcode":"64400",
    "sg:province":"Aquitaine",
    "wof:name":"Cabinet Jean-michel Marestin S.a.r.l.",
    "wof:placetype":"venue"
},
  "geometry": {"coordinates":[-0.613728,43.19125],"type":"Point"}
}