{
  "type": "Feature",
  "properties": {
    "addr:full":"43230 St Georges D Aurac Chassagnes Auvergne 43230",
    "addr:housenumber":"43230",
    "addr:postcode":"43230",
    "addr:street":"St;Chassagnes",
    "iso:country":"FR",
    "sg:address":"43230 St Georges D Aurac",
    "sg:city":"Chassagnes",
    "sg:classifiers":[
        {
            "category":"Home & Garden",
            "subcategory":"Furniture",
            "type":"Retail Goods"
        }
    ],
    "sg:phone":"+33 4 71 77 52 70",
    "sg:postcode":"43230",
    "sg:province":"Auvergne",
    "sg:tags":[
        "wood"
    ],
    "wof:name":"Siozade Pere Et Fils",
    "wof:placetype":"venue"
},
  "geometry": {"coordinates":[3.54044,45.156738],"type":"Point"}
}