{
  "type": "Feature",
  "properties": {
    "iso:country":"FR",
    "sg:address":"Chateau Lagrange 33250 ST JULIEN BEYCHEVELLE",
    "sg:city":"Cissac-M\u00e9doc",
    "sg:classifiers":[
        {
            "category":"Wholesale",
            "subcategory":"Wine & Distilled Alcoholic Beverages",
            "type":"Manufacturing & Wholesale Goods"
        }
    ],
    "sg:phone":"+33 5 56 73 38 38",
    "sg:postcode":"33250",
    "sg:province":"Aquitaine",
    "sg:tags":[
        "french"
    ],
    "wof:name":"Chateau Lagrange S.a.",
    "wof:placetype":"venue"
},
  "geometry": {"coordinates":[-0.82935,45.225723],"type":"Point"}
}