{
  "type": "Feature",
  "properties": {
    "iso:country":"FR",
    "sg:address":"Rte De La Chimie 76700 Gonfreville L'Orcher",
    "sg:classifiers":[
        {
            "category":"Manufacturing",
            "subcategory":"Rubber & Plastics",
            "type":"Manufacturing & Wholesale Goods"
        }
    ],
    "sg:phone":"+33 2 35 24 18 55",
    "sg:province":"Haute Normandie",
    "wof:name":"Delaunay Plasturgie",
    "wof:placetype":"venue"
},
  "geometry": {"coordinates":[0.224485,49.485153],"type":"Point"}
}