{
  "type": "Feature",
  "properties": {
    "addr:full":"ZA des Ferri\u00e8res Le Muy Languedoc-Roussillon 83490",
    "addr:postcode":"83490",
    "addr:street":"Za Des Ferrie\u0300Res;Muy",
    "iso:country":"FR",
    "sg:address":"ZA des Ferri\u00e8res",
    "sg:city":"Le Muy",
    "sg:orig_category":"Non-Classified Establishments",
    "sg:phone":"+33 4 94 45 18 45",
    "sg:postcode":"83490",
    "sg:province":"Languedoc-Roussillon",
    "wof:name":"Berton Sicard S.a.",
    "wof:placetype":"venue"
},
  "geometry": {"coordinates":[6.566279,43.47168],"type":"Point"}
}