{
  "type": "Feature",
  "properties": {
    "addr:full":"Rue Saint-Marc 41200 Romorantin Lanthenay Villefranche-sur-Cher Centre 41200",
    "addr:postcode":"41200;41200",
    "addr:street":"Rue Saint-Marc",
    "iso:country":"FR",
    "sg:address":"Rue Saint-Marc 41200 Romorantin Lanthenay",
    "sg:city":"Villefranche-sur-Cher",
    "sg:classifiers":[
        {
            "category":"Manufacturing",
            "subcategory":"Metals",
            "type":"Manufacturing & Wholesale Goods"
        }
    ],
    "sg:phone":"+33 2 54 95 41 05",
    "sg:postcode":"41200",
    "sg:province":"Centre",
    "sg:tags":[
        "-",
        "machine",
        "equipment",
        "engineering",
        "machinery",
        "mechanical"
    ],
    "wof:name":"Abc Synergie Sa",
    "wof:placetype":"venue"
},
  "geometry": {"coordinates":[1.737815,47.348282],"type":"Point"}
}