{
  "type": "Feature",
  "properties": {
    "iso:country":"FR",
    "sg:address":"17 pl Jean Jaur\u00e8s; Tours",
    "sg:classifiers":[
        {
            "category":"Banks & Credit Unions",
            "subcategory":"Bank",
            "type":"Services"
        }
    ],
    "sg:phone":"+33 2 47 20 74 00",
    "sg:province":"Champagne",
    "wof:name":"Banque Hervet",
    "wof:placetype":"venue"
},
  "geometry": {"coordinates":[-97.04012299999999,31.758181],"type":"Point"}
}