{
  "type": "Feature",
  "properties": {
    "addr:full":"Innopolis Lab\u00e8ge Midi Pyr\u00e9n\u00e9es 31670",
    "addr:postcode":"31670",
    "iso:country":"FR",
    "sg:address":"Innopolis",
    "sg:city":"Lab\u00e8ge",
    "sg:orig_category":"Unclassifiable Establishments",
    "sg:phone":"+33 5 61 00 76 00",
    "sg:postcode":"31670",
    "sg:province":"Midi Pyr\u00e9n\u00e9es",
    "wof:name":"Micro Et C.a.o. S.a.r.l.",
    "wof:placetype":"venue"
},
  "geometry": {"coordinates":[1.527111,43.529713],"type":"Point"}
}