{
  "type": "Feature",
  "properties": {
    "addr:full":"6, Rue des Marguerites, 92737 Nanterre C\u00e9dex Languedoc-Roussillon",
    "addr:housenumber":"6",
    "addr:postcode":"92737;ce\u0301dex",
    "addr:street":"Rue Des Marguerites",
    "iso:country":"FR",
    "sg:address":"6, Rue des Marguerites, 92737 Nanterre C\u00e9dex",
    "sg:orig_category":"Non-Classified Establishments",
    "sg:phone":"+33 1 41 30 80 80",
    "sg:province":"Languedoc-Roussillon",
    "wof:name":"Btr Sealing Systems S.a.",
    "wof:placetype":"venue"
},
  "geometry": {"coordinates":[2.21981,48.9161],"type":"Point"}
}