{
  "type": "Feature",
  "properties": {
    "addr:full":"4 Rue Recamier 75007 Paris Ile de France 75007",
    "addr:housenumber":"4",
    "addr:postcode":"75007;75007",
    "addr:street":"Rue Recamier",
    "iso:country":"FR",
    "sg:address":"4 Rue Recamier 75007 Paris",
    "sg:classifiers":[
        {
            "category":"Professional",
            "subcategory":"Business Services",
            "type":"Services"
        }
    ],
    "sg:phone":"+33 1 45 48 86 58",
    "sg:postcode":"75007",
    "sg:province":"Ile de France",
    "sg:tags":[
        "travel",
        "fair"
    ],
    "wof:name":"Le Recamier Restaurant",
    "wof:placetype":"venue"
},
  "geometry": {"coordinates":[2.328098,48.852032],"type":"Point"}
}