{
  "type": "Feature",
  "properties": {
    "addr:full":"Route De Biron Zi Saligues 64300 Orthez Orthez Aquitaine 64300",
    "addr:postcode":"64300;64300",
    "addr:street":"Route De Biron Zi Saligues",
    "iso:country":"FR",
    "sg:address":"Route De Biron Zi Saligues 64300 Orthez",
    "sg:city":"Orthez",
    "sg:classifiers":[
        {
            "category":"Manufacturing",
            "subcategory":"Paper Products",
            "type":"Manufacturing & Wholesale Goods"
        }
    ],
    "sg:phone":"+33 5 59 69 82 60",
    "sg:postcode":"64300",
    "sg:province":"Aquitaine",
    "sg:tags":[
        "packaging",
        "material",
        "-",
        "cardboard"
    ],
    "wof:name":"Corint Sud",
    "wof:placetype":"venue"
},
  "geometry": {"coordinates":[-0.773174,43.48735],"type":"Point"}
}