{
  "type": "Feature",
  "properties": {
    "iso:country":"FR",
    "sg:address":"Rue De Bel Air 85130 Bazoges En Paillers",
    "sg:classifiers":[
        {
            "category":"Home & Garden",
            "subcategory":"Furniture",
            "type":"Retail Goods"
        }
    ],
    "sg:phone":"+33 2 51 07 79 27",
    "sg:postcode":"85130",
    "sg:province":"Pays de Loire",
    "sg:tags":[
        "household",
        "wood"
    ],
    "wof:name":"Petiot Andre",
    "wof:placetype":"venue"
},
  "geometry": {"coordinates":[-1.137284,46.908016],"type":"Point"}
}