{
  "type": "Feature",
  "properties": {
    "addr:full":"17 route de l'Isle d'Abeau 38300 Bourgoin Jallieu Rhone-Alpes 38300",
    "addr:housenumber":"17",
    "addr:postcode":"38300;38300",
    "addr:street":"Route De L'Isle D'Abeau;Rhone-Alpes",
    "iso:country":"FR",
    "sg:address":"17 route de l'Isle d'Abeau 38300 Bourgoin Jallieu",
    "sg:classifiers":[
        {
            "category":"Shopping",
            "subcategory":"Crafts & Fabrics",
            "type":"Retail Goods"
        }
    ],
    "sg:phone":"+33 4 74 93 40 88",
    "sg:postcode":"38300",
    "sg:province":"Rhone-Alpes",
    "sg:tags":[
        "knitted"
    ],
    "wof:name":"Rossignol S.a.",
    "wof:placetype":"venue"
},
  "geometry": {"coordinates":[5.29517,45.566559],"type":"Point"}
}