{
  "type": "Feature",
  "properties": {
    "addr:full":"4, Av. de Friedland, 75008 Paris Ile de France",
    "addr:postcode":"75008",
    "addr:street":"Av. De Friedland",
    "iso:country":"FR",
    "sg:address":"4, Av. de Friedland, 75008 Paris",
    "sg:orig_category":"Unclassifiable Establishments",
    "sg:phone":"+33 1 45 63 26 06",
    "sg:province":"Ile de France",
    "wof:name":"Caray S.a.",
    "wof:placetype":"venue"
},
  "geometry": {"coordinates":[2.304831,48.875034],"type":"Point"}
}