{
  "type": "Feature",
  "properties": {
    "iso:country":"FR",
    "sg:address":"ZI",
    "sg:city":"Lourdes",
    "sg:orig_category":"Unclassifiable Establishments",
    "sg:phone":"+33 5 62 94 20 85",
    "sg:postcode":"65100",
    "sg:province":"Midi Pyr\u00e9n\u00e9es",
    "wof:name":"Soci\u00e9t\u00e9 Exploitation Blanchisserie S.a.r.l.",
    "wof:placetype":"venue"
},
  "geometry": {"coordinates":[0.007055,43.032288],"type":"Point"}
}