{
  "type": "Feature",
  "properties": {
    "iso:country":"FR",
    "sg:address":"Av du G\u00e9n\u00e9ral de Gaulle",
    "sg:city":"Fourmies",
    "sg:orig_category":"Non-Classified Establishments",
    "sg:phone":"+33 3 27 59 94 77",
    "sg:postcode":"59610",
    "sg:province":"Nord Pas-de-Calais",
    "wof:name":"Soud'helpe",
    "wof:placetype":"venue"
},
  "geometry": {"coordinates":[4.051957,50.032188],"type":"Point"}
}