{
  "type": "Feature",
  "properties": {
    "iso:country":"FR",
    "sg:address":"93527 Saint Denis C\u00e9dex 2^^39/47, Bd Ornano, 93200 Saint Denis",
    "sg:orig_category":"Non-Classified Establishments",
    "sg:phone":"+33 1 49 22 31 00",
    "sg:province":"Ile de France",
    "wof:name":"Siemens France S.a.s.",
    "wof:placetype":"venue"
},
  "geometry": {"coordinates":[2.35497,48.938454],"type":"Point"}
}