{
  "type": "Feature",
  "properties": {
    "iso:country":"FR",
    "sg:address":"41 Av De La Croix Des Gardes 06400 Cannes",
    "sg:classifiers":[
        {
            "category":"Shopping",
            "subcategory":"Clothing, Apparel, & Fashions",
            "type":"Retail Goods"
        }
    ],
    "sg:phone":"+33 4 93 68 34 36",
    "sg:province":"Auvergne",
    "sg:tags":[
        "textile",
        "clothing",
        "clothes"
    ],
    "wof:name":"Sable",
    "wof:placetype":"venue"
},
  "geometry": {"coordinates":[7.002182,43.556992],"type":"Point"}
}