{
  "type": "Feature",
  "properties": {
    "addr:full":"21 Rue Sala 69002 Lyon Rhone-Alpes 69002",
    "addr:housenumber":"21",
    "addr:postcode":"69002;69002",
    "addr:street":"Rue Sala",
    "iso:country":"FR",
    "sg:address":"21 Rue Sala 69002 Lyon",
    "sg:classifiers":[
        {
            "category":"Professional",
            "subcategory":"Business Services",
            "type":"Services"
        }
    ],
    "sg:phone":"+33 4 78 38 20 00",
    "sg:postcode":"69002",
    "sg:province":"Rhone-Alpes",
    "sg:tags":[
        "training",
        "advice"
    ],
    "wof:name":"Ass Ecole Chevreul",
    "wof:placetype":"venue"
},
  "geometry": {"coordinates":[4.82904,45.756149],"type":"Point"}
}