{
  "type": "Feature",
  "properties": {
    "addr:full":"81 Avenue D Albi 81100 Castres Midi Pyr\u00e9n\u00e9es",
    "addr:housenumber":"81",
    "addr:postcode":"81100",
    "addr:street":"Avenue D",
    "iso:country":"FR",
    "sg:address":"81 Avenue D Albi 81100 Castres",
    "sg:classifiers":[
        {
            "category":"Home & Garden",
            "subcategory":"Furniture",
            "type":"Retail Goods"
        }
    ],
    "sg:phone":"+33 5 63 59 03 13",
    "sg:province":"Midi Pyr\u00e9n\u00e9es",
    "sg:tags":[
        "wood"
    ],
    "wof:name":"Etablissements Felix Moulis Et Fils",
    "wof:placetype":"venue"
},
  "geometry": {"coordinates":[2.234565,43.618656],"type":"Point"}
}