{
  "type": "Feature",
  "properties": {
    "addr:full":"Rte d'Annecy Thones Rhone-Alpes 74230",
    "addr:postcode":"74230",
    "addr:street":"Rte D'Annecy Thones Rhone-Alpes",
    "iso:country":"FR",
    "sg:address":"Rte d'Annecy",
    "sg:city":"Thones",
    "sg:orig_category":"Non-Classified Establishments",
    "sg:phone":"+33 4 50 02 06 79",
    "sg:postcode":"74230",
    "sg:province":"Rhone-Alpes",
    "wof:name":"Veyrat Equipement S.a.r.l.",
    "wof:placetype":"venue"
},
  "geometry": {"coordinates":[6.317418,45.885616],"type":"Point"}
}