{
  "type": "Feature",
  "properties": {
    "iso:country":"FR",
    "sg:address":"8 Rue Beyle Stendhal",
    "sg:city":"Grenoble",
    "sg:classifiers":[
        {
            "category":"Banks & Credit Unions",
            "subcategory":"Financial Services",
            "type":"Services"
        }
    ],
    "sg:phone":"+33 4 76 44 28 75",
    "sg:postcode":"38000",
    "sg:province":"Rhone-Alpes",
    "sg:tags":[
        "banking",
        "finance",
        "insurance"
    ],
    "wof:name":"Chanet Beaume Clement Et Cie",
    "wof:placetype":"venue"
},
  "geometry": {"coordinates":[5.730886,45.187485],"type":"Point"}
}