{
  "type": "Feature",
  "properties": {
    "addr:full":"ZI de K\u00e9riel Plou\u00e9dern Bretagne 29800",
    "addr:postcode":"29800",
    "addr:street":"Zi De Ke\u0301Riel Ploue\u0301Dern Bretagne",
    "iso:country":"FR",
    "sg:address":"ZI de K\u00e9riel",
    "sg:city":"Plou\u00e9dern",
    "sg:orig_category":"Non-Classified Establishments",
    "sg:phone":"+33 2 98 20 94 60",
    "sg:postcode":"29800",
    "sg:province":"Bretagne",
    "wof:name":"Entreprise Christian Faure S.a.s.",
    "wof:placetype":"venue"
},
  "geometry": {"coordinates":[-4.246176,48.48399],"type":"Point"}
}