{
  "type": "Feature",
  "properties": {
    "iso:country":"FR",
    "sg:address":"Av. Roger Salengro - Imm. Le Voltaire",
    "sg:city":"Aubagne",
    "sg:orig_category":"Non-Classified Establishments",
    "sg:phone":"+33 4 42 03 15 33",
    "sg:postcode":"13400",
    "sg:province":"Provence-Alpes-C\u00f4te d'Azur",
    "wof:name":"Nasal S.a.",
    "wof:placetype":"venue"
},
  "geometry": {"coordinates":[5.569848,43.300762],"type":"Point"}
}