{
  "type": "Feature",
  "properties": {
    "addr:full":"44 Rue De La Gare 44590 Lusanger Pays de Loire",
    "addr:housenumber":"44",
    "addr:postcode":"44590",
    "addr:street":"Rue De La Gare",
    "iso:country":"FR",
    "sg:address":"44 Rue De La Gare 44590 Lusanger",
    "sg:classifiers":[
        {
            "category":"Utilities",
            "subcategory":"Telephone",
            "type":"Services"
        }
    ],
    "sg:phone":"+33 2 40 07 72 04",
    "sg:province":"Pays de Loire",
    "sg:tags":[
        "telecommunication"
    ],
    "wof:name":"Deltacab",
    "wof:placetype":"venue"
},
  "geometry": {"coordinates":[-1.585431,47.676266],"type":"Point"}
}