{
  "type": "Feature",
  "properties": {
    "addr:full":"214, Rue de Chauny, 80400 Brouchy Picardie",
    "addr:housenumber":"214",
    "addr:postcode":"80400",
    "addr:street":"Rue De Chauny",
    "iso:country":"FR",
    "sg:address":"214, Rue de Chauny, 80400 Brouchy",
    "sg:orig_category":"Unclassifiable Establishments",
    "sg:phone":"+33 3 23 81 11 52",
    "sg:province":"Picardie",
    "wof:name":"R\u00e9pagri Fran\u00e7ois Fr\u00e8res S.a.r.l.",
    "wof:placetype":"venue"
},
  "geometry": {"coordinates":[3.100465,49.71719],"type":"Point"}
}