{
  "type": "Feature",
  "properties": {
    "iso:country":"FR",
    "sg:address":"B.P. 4, 89440 L'Isle sur Serein^^Rte de Guillon, 89440 L'Isle sur Serein",
    "sg:city":"Angely",
    "sg:orig_category":"Non-Classified Establishments",
    "sg:phone":"+33 3 86 33 83 33",
    "sg:postcode":"89440",
    "sg:province":"Bourgogne",
    "wof:name":"Billiat Et Compagnie S.a.r.l.",
    "wof:placetype":"venue"
},
  "geometry": {"coordinates":[3.994646,47.603165],"type":"Point"}
}