{
  "type": "Feature",
  "properties": {
    "addr:full":"65, Bd M\u00e9nilmontant, 75011 Paris Ile de France",
    "addr:housenumber":"65",
    "addr:postcode":"75011",
    "addr:street":"Bd",
    "iso:country":"FR",
    "sg:address":"65, Bd M\u00e9nilmontant, 75011 Paris",
    "sg:orig_category":"Non-Classified Establishments",
    "sg:phone":"+33 1 47 00 92 29",
    "sg:province":"Ile de France",
    "wof:name":"Soci\u00e9t\u00e9 Joseph Et Fils S.a.",
    "wof:placetype":"venue"
},
  "geometry": {"coordinates":[2.387243,48.862495],"type":"Point"}
}