{
  "type": "Feature",
  "properties": {
    "iso:country":"FR",
    "sg:address":"Route Nogaro 32460 Le Houga",
    "sg:classifiers":[
        {
            "category":"Farming",
            "subcategory":"Livestock Farm",
            "type":"Manufacturing & Wholesale Goods"
        }
    ],
    "sg:phone":"+33 5 62 09 10 02",
    "sg:postcode":"32460",
    "sg:province":"Midi Pyr\u00e9n\u00e9es",
    "sg:tags":[
        "grain",
        "agriculture",
        "cereal"
    ],
    "wof:name":"Vivadour Sa",
    "wof:placetype":"venue"
},
  "geometry": {"coordinates":[-0.179563,43.774776],"type":"Point"}
}