{
  "type": "Feature",
  "properties": {
    "addr:full":"115 Boulevard De Sebastopol 75002 Paris Ile de France 75002",
    "addr:housenumber":"115",
    "addr:postcode":"75002;75002",
    "addr:street":"Boulevard De Sebastopol",
    "iso:country":"FR",
    "sg:address":"115 Boulevard De Sebastopol 75002 Paris",
    "sg:classifiers":[
        {
            "category":"Shopping",
            "subcategory":"Clothing, Apparel, & Fashions",
            "type":"Retail Goods"
        }
    ],
    "sg:phone":"+33 1 42 21 49 59",
    "sg:postcode":"75002",
    "sg:province":"Ile de France",
    "sg:tags":[
        "textile",
        "clothing",
        "clothes"
    ],
    "wof:name":"Brin De Fille",
    "wof:placetype":"venue"
},
  "geometry": {"coordinates":[2.352868,48.867256],"type":"Point"}
}