{
  "type": "Feature",
  "properties": {
    "iso:country":"FR",
    "sg:address":"Rue du Lazaret",
    "sg:city":"Anglet",
    "sg:orig_category":"Unclassifiable Establishments",
    "sg:phone":"+33 5 59 57 09 22",
    "sg:postcode":"64600",
    "sg:province":"Aquitaine",
    "wof:name":"Soci\u00e9t\u00e9 Bayonnaise Des Viandes S.a.r.l.",
    "wof:placetype":"venue"
},
  "geometry": {"coordinates":[-1.500479,43.523201],"type":"Point"}
}