{
  "type": "Feature",
  "properties": {
    "addr:full":"43 Rue M\u00e9rim\u00e9e 06110 Le Cannet Midi Pyr\u00e9n\u00e9es",
    "addr:housenumber":"43",
    "addr:postcode":"06110",
    "addr:street":"Rue Me\u0301Rime\u0301E",
    "iso:country":"FR",
    "sg:address":"43 Rue M\u00e9rim\u00e9e 06110 Le Cannet",
    "sg:classifiers":[
        {
            "category":"Professional",
            "subcategory":"Advertising",
            "type":"Services"
        }
    ],
    "sg:phone":"+33 4 92 99 58 58",
    "sg:province":"Midi Pyr\u00e9n\u00e9es",
    "sg:tags":[
        "communication",
        "medium"
    ],
    "wof:name":"Bopca Sarl",
    "wof:placetype":"venue"
},
  "geometry": {"coordinates":[7.017725,43.566856],"type":"Point"}
}