{
  "type": "Feature",
  "properties": {
    "iso:country":"FR",
    "sg:address":"6 rue de V\u00e9drines 95100 Argenteuil",
    "sg:classifiers":[
        {
            "category":"Manufacturing",
            "subcategory":"Motor Vehicles & Parts",
            "type":"Manufacturing & Wholesale Goods"
        }
    ],
    "sg:phone":"+33 1 39 82 68 88",
    "sg:province":"Ile de France",
    "sg:tags":[
        "precision",
        "mechanic"
    ],
    "wof:name":"Sermia E.c.m Sarl",
    "wof:placetype":"venue"
},
  "geometry": {"coordinates":[2.240975,48.959129],"type":"Point"}
}