{
  "type": "Feature",
  "properties": {
    "addr:full":"10 rue Fernand Pelloutier 38130 Echirolles Rhone-Alpes 38130",
    "addr:housenumber":"10",
    "addr:postcode":"38130;38130",
    "addr:street":"Rue Fernand Pelloutier;Rhone-Alpes",
    "iso:country":"FR",
    "sg:address":"10 rue Fernand Pelloutier 38130 Echirolles",
    "sg:orig_category":"Fax Machine, Copier, Printer Combinations",
    "sg:phone":"+33 4 76 40 07 58",
    "sg:postcode":"38130",
    "sg:province":"Rhone-Alpes",
    "wof:name":"C Pro Isere Copieurs Sarl",
    "wof:placetype":"venue"
},
  "geometry": {"coordinates":[5.714944,45.152725],"type":"Point"}
}