{
  "type": "Feature",
  "properties": {
    "addr:full":"Z.I. de Tavannes 55100 Beaumont En Verdunois Lorraine 55100",
    "addr:postcode":"55100;55100",
    "addr:street":"Z.I. De Tavannes;Verdunois Lorraine",
    "iso:country":"FR",
    "sg:address":"Z.I. de Tavannes 55100 Beaumont En Verdunois",
    "sg:classifiers":[
        {
            "category":"Food & Beverages",
            "subcategory":"Meat & Fish",
            "type":"Retail Goods"
        }
    ],
    "sg:phone":"+33 3 29 84 16 01",
    "sg:postcode":"55100",
    "sg:province":"Lorraine",
    "sg:tags":[
        "sausage"
    ],
    "wof:name":"Ets Berni Sa",
    "wof:placetype":"venue"
},
  "geometry": {"coordinates":[5.383225,49.164806],"type":"Point"}
}