{
  "type": "Feature",
  "properties": {
    "iso:country":"FR",
    "sg:address":"11 RUE DE LUBECK 75116 Paris",
    "sg:classifiers":[
        {
            "category":"Professional",
            "subcategory":"Employment Agencies",
            "type":"Services"
        }
    ],
    "sg:phone":"+33 1 44 13 14 00",
    "sg:province":"Ile de France",
    "sg:tags":[
        "cargo"
    ],
    "wof:name":"S.f.t. Gondrand Fr\u00e8res Sa",
    "wof:placetype":"venue"
},
  "geometry": {"coordinates":[8.70641,48.896599],"type":"Point"}
}