{
  "type": "Feature",
  "properties": {
    "addr:full":"50 Rue Croix Des Petits Champs 75001 Paris Ile de France 75001",
    "addr:housenumber":"50",
    "addr:postcode":"75001;75001",
    "addr:street":"Rue Croix Des Petits Champs",
    "iso:country":"FR",
    "sg:address":"50 Rue Croix Des Petits Champs 75001 Paris",
    "sg:classifiers":[
        {
            "category":"Professional",
            "subcategory":"Advertising",
            "type":"Services"
        }
    ],
    "sg:phone":"+33 1 44 58 18 18",
    "sg:postcode":"75001",
    "sg:province":"Ile de France",
    "sg:tags":[
        "information",
        "medium",
        "communication"
    ],
    "wof:name":"Tele Europe Sa",
    "wof:placetype":"venue"
},
  "geometry": {"coordinates":[2.34086,48.865047],"type":"Point"}
}