{
  "type": "Feature",
  "properties": {
    "addr:full":"B.P. 168, 75363 Paris C\u00e9dex 8^^52, Av. des Champs-Elys\u00e9es, 75008 Paris Ile de France",
    "addr:housenumber":"b.p. 168;8;^ 52",
    "addr:postcode":"75363;75008",
    "addr:street":"^;Av. Des Champs-Elyse\u0301Es",
    "iso:country":"FR",
    "sg:address":"B.P. 168, 75363 Paris C\u00e9dex 8^^52, Av. des Champs-Elys\u00e9es, 75008 Paris",
    "sg:orig_category":"Non-Classified Establishments",
    "sg:phone":"+33 1 40 74 15 15",
    "sg:province":"Ile de France",
    "wof:name":"Finacor S.a.",
    "wof:placetype":"venue"
},
  "geometry": {"coordinates":[2.34121,48.856926],"type":"Point"}
}