{
  "type": "Feature",
  "properties": {
    "iso:country":"FR",
    "sg:address":"18 Rue Louis Moreau",
    "sg:city":"\u00c9tampes",
    "sg:classifiers":[
        {
            "category":"Banks & Credit Unions",
            "subcategory":"Financial Services",
            "type":"Services"
        }
    ],
    "sg:phone":"+33 1 69 92 57 00",
    "sg:postcode":"91150",
    "sg:province":"Ile de France",
    "sg:tags":[
        "banking",
        "finance",
        "insurance"
    ],
    "wof:name":"Societe Generale",
    "wof:placetype":"venue"
},
  "geometry": {"coordinates":[2.160982,48.436298],"type":"Point"}
}