{
  "type": "Feature",
  "properties": {
    "iso:country":"FR",
    "sg:address":"lotissement Terradou 84200 Carpentras",
    "sg:classifiers":[
        {
            "category":"Professional",
            "type":"Services"
        }
    ],
    "sg:phone":"+33 4 90 63 06 03",
    "sg:province":"Provence-Alpes-C\u00f4te d'Azur",
    "sg:tags":[
        "transport"
    ],
    "wof:name":"Transports Vincent Sa",
    "wof:placetype":"venue"
},
  "geometry": {"coordinates":[5.054164,44.035553],"type":"Point"}
}