{
  "type": "Feature",
  "properties": {
    "addr:full":"Ferme de Vaulucau 78870 Bailly Ile de France",
    "addr:postcode":"78870;ile",
    "iso:country":"FR",
    "sg:address":"Ferme de Vaulucau 78870 Bailly",
    "sg:orig_category":"Non-Classified Establishments",
    "sg:phone":"+33 1 39 63 20 20",
    "sg:province":"Ile de France",
    "wof:name":"Saisons Et Jardins S.a.s.",
    "wof:placetype":"venue"
},
  "geometry": {"coordinates":[2.079645,48.839886],"type":"Point"}
}