{
  "type": "Feature",
  "properties": {
    "addr:full":"3, Rue Pierre Boulanger - ZI le Br\u00e9zet Est, 63100 Clermont Ferrand Clermont-Ferrand Auvergne 63100",
    "addr:housenumber":"3",
    "addr:postcode":"63100;63100",
    "addr:street":"Rue Pierre Boulanger Zi Le Bre\u0301Zet Est",
    "iso:country":"FR",
    "sg:address":"3, Rue Pierre Boulanger - ZI le Br\u00e9zet Est, 63100 Clermont Ferrand",
    "sg:city":"Clermont-Ferrand",
    "sg:orig_category":"Non-Classified Establishments",
    "sg:phone":"+33 4 73 91 15 27",
    "sg:postcode":"63100",
    "sg:province":"Auvergne",
    "wof:name":"Techno Logistique S.a.r.l.",
    "wof:placetype":"venue"
},
  "geometry": {"coordinates":[2.09017,43.151814],"type":"Point"}
}