{
  "type": "Feature",
  "properties": {
    "iso:country":"FR",
    "sg:address":"ZAC de la Chevalerie",
    "sg:city":"Saint L\u00f4",
    "sg:orig_category":"Unclassifiable Establishments",
    "sg:phone":"+33 2 33 05 53 98",
    "sg:postcode":"50000",
    "sg:province":"Basse Normandie",
    "wof:name":"Entreprise Fouchard S.a.",
    "wof:placetype":"venue"
},
  "geometry": {"coordinates":[-1.090344,49.115974],"type":"Point"}
}