{
  "type": "Feature",
  "properties": {
    "addr:full":"11, Rue de la Motte Piquet, 35044 Rennes C\u00e9dex La Motte Bretagne 22600",
    "addr:housenumber":"11",
    "addr:postcode":"35044;22600",
    "addr:street":"Rue De La Motte Piquet;La Motte Bretagne",
    "iso:country":"FR",
    "sg:address":"11, Rue de la Motte Piquet, 35044 Rennes C\u00e9dex",
    "sg:city":"La Motte",
    "sg:orig_category":"Non-Classified Establishments",
    "sg:phone":"+33 2 99 03 50 35",
    "sg:postcode":"22600",
    "sg:province":"Bretagne",
    "wof:name":"E.d.f. G.d.f. Services",
    "wof:placetype":"venue"
},
  "geometry": {"coordinates":[-1.685447,48.107563],"type":"Point"}
}