{
  "type": "Feature",
  "properties": {
    "addr:full":"Les Chauvets Echangeur Aix Nord 73100 Gresy Sur Aix Rhone-Alpes",
    "addr:postcode":"73100",
    "iso:country":"FR",
    "sg:address":"Les Chauvets Echangeur Aix Nord 73100 Gresy Sur Aix",
    "sg:classifiers":[
        {
            "category":"Utilities",
            "subcategory":"Telephone",
            "type":"Services"
        }
    ],
    "sg:phone":"+33 4 79 34 86 64",
    "sg:province":"Rhone-Alpes",
    "sg:tags":[
        "telecommunication"
    ],
    "wof:name":"M. Ferre Andre F A I G O D",
    "wof:placetype":"venue"
},
  "geometry": {"coordinates":[5.899685,45.672455],"type":"Point"}
}