{
  "type": "Feature",
  "properties": {
    "addr:full":"Rue Boileau 87350 Panazol Limousin 87350",
    "addr:postcode":"87350;87350",
    "addr:street":"Rue Boileau",
    "iso:country":"FR",
    "sg:address":"Rue Boileau 87350 Panazol",
    "sg:classifiers":[
        {
            "category":"Professional",
            "subcategory":"Business Services",
            "type":"Services"
        }
    ],
    "sg:phone":"+33 5 55 30 63 84",
    "sg:postcode":"87350",
    "sg:province":"Limousin",
    "sg:tags":[
        "body",
        "advice"
    ],
    "wof:name":"Association Alaed",
    "wof:placetype":"venue"
},
  "geometry": {"coordinates":[1.295705,45.84095],"type":"Point"}
}