{
  "type": "Feature",
  "properties": {
    "addr:full":"20, Rue de l'H\u00f4tel de Ville, 08800 Les Hautes Rivi\u00e8res Deville Champagne 08800",
    "addr:housenumber":"20",
    "addr:postcode":"08800;08800",
    "addr:street":"Rue De L'Ho \u0302Tel De Ville",
    "iso:country":"FR",
    "sg:address":"20, Rue de l'H\u00f4tel de Ville, 08800 Les Hautes Rivi\u00e8res",
    "sg:city":"Deville",
    "sg:orig_category":"Non-Classified Establishments",
    "sg:phone":"+33 3 24 53 42 97",
    "sg:postcode":"08800",
    "sg:province":"Champagne",
    "wof:name":"L.j.b. S.a.r.l. - L\u00e9on Et Jean Badr\u00e9",
    "wof:placetype":"venue"
},
  "geometry": {"coordinates":[4.841513,49.885345],"type":"Point"}
}