{
  "type": "Feature",
  "properties": {
    "addr:full":"255, Bd Robert Ballanger - Central Parc, 93420 Villepinte Ile de France",
    "addr:housenumber":"255",
    "addr:postcode":"93420",
    "addr:street":"Bd Robert Ballanger Central Parc;Ile De France",
    "iso:country":"FR",
    "sg:address":"255, Bd Robert Ballanger - Central Parc, 93420 Villepinte",
    "sg:orig_category":"Non-Classified Establishments",
    "sg:phone":"+33 1 41 51 10 70",
    "sg:province":"Ile de France",
    "wof:name":"P.c. Chips Electronics S.a.r.l.",
    "wof:placetype":"venue"
},
  "geometry": {"coordinates":[2.558904,48.962353],"type":"Point"}
}