{
  "type": "Feature",
  "properties": {
    "addr:full":"Le Pont de l'Ane ZA 42650 ST JEAN BONNEFONDS Rhone-Alpes",
    "addr:postcode":"42650",
    "addr:street":"Le Pont De L'Ane Za",
    "iso:country":"FR",
    "sg:address":"Le Pont de l'Ane ZA 42650 ST JEAN BONNEFONDS",
    "sg:orig_category":"Sintering Plastics",
    "sg:phone":"+33 4 77 49 36 46",
    "sg:province":"Rhone-Alpes",
    "wof:name":"Fast Heat International S.a.",
    "wof:placetype":"venue"
},
  "geometry": {"coordinates":[4.420113,45.444534],"type":"Point"}
}