{
  "type": "Feature",
  "properties": {
    "addr:full":"88 Rue Industrie 01480 Jassans Riottier Rhone-Alpes 01480",
    "addr:housenumber":"88",
    "addr:postcode":"01480;01480",
    "addr:street":"Rue Industrie;Rhone-Alpes",
    "iso:country":"FR",
    "sg:address":"88 Rue Industrie 01480 Jassans Riottier",
    "sg:classifiers":[
        {
            "category":"Home & Garden",
            "subcategory":"Furniture",
            "type":"Retail Goods"
        }
    ],
    "sg:phone":"+33 4 74 09 50 50",
    "sg:postcode":"01480",
    "sg:province":"Rhone-Alpes",
    "sg:tags":[
        "wood"
    ],
    "wof:name":"Malaure Sa",
    "wof:placetype":"venue"
},
  "geometry": {"coordinates":[4.76509,45.98098],"type":"Point"}
}