{
  "type": "Feature",
  "properties": {
    "iso:country":"FR",
    "sg:address":"33, Rue du Hurepoix - ZAC Croix Blanche Est, 91708 Sainte Genevi\u00e8ve des Bois C\u00e9dex",
    "sg:city":"Anch\u00e9",
    "sg:orig_category":"Non-Classified Establishments",
    "sg:phone":"+33 1 69 46 64 80",
    "sg:postcode":"37500",
    "sg:province":"Centre",
    "wof:name":"Montgomery S.a.r.l.",
    "wof:placetype":"venue"
},
  "geometry": {"coordinates":[2.326545,48.640656],"type":"Point"}
}