{
  "type": "Feature",
  "properties": {
    "iso:country":"FR",
    "sg:address":"La Merindole 13621 Port De Bouc",
    "sg:classifiers":[
        {
            "category":"Building & Trades",
            "subcategory":"Construction",
            "type":"Services"
        }
    ],
    "sg:phone":"+33 4 42 40 50 30",
    "sg:province":"Centre",
    "sg:tags":[
        "work",
        "public"
    ],
    "wof:name":"Sscgt",
    "wof:placetype":"venue"
},
  "geometry": {"coordinates":[-75.066628,44.8484],"type":"Point"}
}