{
  "type": "Feature",
  "properties": {
    "iso:country":"FR",
    "sg:address":"ZA le C\u00e9sar",
    "sg:city":"Le Subdray",
    "sg:orig_category":"Non-Classified Establishments",
    "sg:phone":"+33 2 48 26 46 89",
    "sg:postcode":"18570",
    "sg:province":"Centre",
    "wof:name":"Bodycote Hit S.a.",
    "wof:placetype":"venue"
},
  "geometry": {"coordinates":[2.292035,47.011749],"type":"Point"}
}