{
  "type": "Feature",
  "properties": {
    "addr:full":"Avenue De Paris 50009 St L\u00f4 Ile de France",
    "addr:postcode":"50009",
    "addr:street":"Avenue De Paris;Ile De France",
    "iso:country":"FR",
    "sg:address":"Avenue De Paris 50009 St L\u00f4",
    "sg:classifiers":[
        {
            "category":"Banks & Credit Unions",
            "subcategory":"Financial Services",
            "type":"Services"
        }
    ],
    "sg:phone":"+33 2 33 06 61 61",
    "sg:province":"Ile de France",
    "sg:tags":[
        "banking",
        "insurance",
        "institution",
        "finance"
    ],
    "wof:name":"Credit Agricole Mutuel Normand",
    "wof:placetype":"venue"
},
  "geometry": {"coordinates":[-1.056604,49.116337],"type":"Point"}
}