{
  "type": "Feature",
  "properties": {
    "iso:country":"FR",
    "sg:address":"Lezigno 34500 Beziers",
    "sg:classifiers":[
        {
            "category":"Manufacturing",
            "subcategory":"Glass & Minerals",
            "type":"Manufacturing & Wholesale Goods"
        }
    ],
    "sg:phone":"+33 4 67 90 67 67",
    "sg:postcode":"34500",
    "sg:province":"Languedoc-Roussillon",
    "sg:tags":[
        "building",
        "material"
    ],
    "wof:name":"Technilum",
    "wof:placetype":"venue"
},
  "geometry": {"coordinates":[3.142775,43.350159],"type":"Point"}
}