{
  "type": "Feature",
  "properties": {
    "addr:full":"ZA des Graviers Brou\u00e9 Centre 28410",
    "addr:postcode":"28410",
    "addr:street":"Za Des Graviers",
    "iso:country":"FR",
    "sg:address":"ZA des Graviers",
    "sg:city":"Brou\u00e9",
    "sg:orig_category":"Non-Classified Establishments",
    "sg:phone":"+33 2 37 43 24 74",
    "sg:postcode":"28410",
    "sg:province":"Centre",
    "wof:name":"Fruitaflor International S.a.",
    "wof:placetype":"venue"
},
  "geometry": {"coordinates":[1.522322,48.75005],"type":"Point"}
}