{
  "type": "Feature",
  "properties": {
    "addr:full":"La Route Corbeil 77350 Le Mee Sur Seine Ile de France 77350",
    "addr:postcode":"77350;77350",
    "addr:street":"Corbeil;Mee;Seine;France",
    "iso:country":"FR",
    "sg:address":"La Route Corbeil 77350 Le Mee Sur Seine",
    "sg:classifiers":[
        {
            "category":"Home & Garden",
            "subcategory":"Furniture",
            "type":"Retail Goods"
        }
    ],
    "sg:phone":"+33 1 64 14 22 80",
    "sg:postcode":"77350",
    "sg:province":"Ile de France",
    "sg:tags":[
        "professional",
        "household",
        "wood"
    ],
    "wof:name":"Charon Sa",
    "wof:placetype":"venue"
},
  "geometry": {"coordinates":[2.64276,48.548985],"type":"Point"}
}