{
  "type": "Feature",
  "properties": {
    "addr:full":"B.P. 255, 94543 Orly A\u00e9rogare C\u00e9dex^^81, Rte de Fontainebleau, 91550 Paray Vieille Poste Ile de France",
    "addr:housenumber":"b.p. 255",
    "addr:postcode":"94543;91550",
    "addr:street":"Rte De Fontainebleau;Vieille Poste",
    "iso:country":"FR",
    "sg:address":"B.P. 255, 94543 Orly A\u00e9rogare C\u00e9dex^^81, Rte de Fontainebleau, 91550 Paray Vieille Poste",
    "sg:orig_category":"Non-Classified Establishments",
    "sg:phone":"+33 1 49 75 38 21",
    "sg:province":"Ile de France",
    "wof:name":"Transorly S.n.c.",
    "wof:placetype":"venue"
},
  "geometry": {"coordinates":[2.36467,48.71294],"type":"Point"}
}