{
  "type": "Feature",
  "properties": {
    "addr:full":"Place Des Charmes 63310 Randan Randan Auvergne 63310",
    "addr:postcode":"63310;63310",
    "addr:street":"Place Des Charmes",
    "iso:country":"FR",
    "sg:address":"Place Des Charmes 63310 Randan",
    "sg:city":"Randan",
    "sg:classifiers":[
        {
            "category":"Professional",
            "subcategory":"Business Services",
            "type":"Services"
        }
    ],
    "sg:phone":"+33 4 70 41 54 99",
    "sg:postcode":"63310",
    "sg:province":"Auvergne",
    "sg:tags":[
        "pharmaceutical",
        "advice",
        "-",
        "chemical",
        "chemistry",
        "energy",
        "by-product"
    ],
    "wof:name":"Randeco Sa",
    "wof:placetype":"venue"
},
  "geometry": {"coordinates":[3.34814,46.01593],"type":"Point"}
}