{
  "type": "Feature",
  "properties": {
    "iso:country":"FR",
    "sg:address":"56, Av. Georges Pompidou, 33500 Libourne",
    "sg:city":"Libourne",
    "sg:orig_category":"Non-Classified Establishments",
    "sg:phone":"+33 5 57 51 00 48",
    "sg:postcode":"33500",
    "sg:province":"Aquitaine",
    "wof:name":"Mazeyres Pomerol",
    "wof:placetype":"venue"
},
  "geometry": {"coordinates":[-0.237797,44.932384],"type":"Point"}
}