{
  "type": "Feature",
  "properties": {
    "addr:full":"5, Av. Corneille, 78360 Montesson Ile de France 78360",
    "addr:postcode":"78360;ile;78360",
    "addr:street":"Av. Corneille;France",
    "iso:country":"FR",
    "sg:address":"5, Av. Corneille, 78360 Montesson",
    "sg:orig_category":"Non-Classified Establishments",
    "sg:phone":"+33 1 39 14 42 27",
    "sg:postcode":"78360",
    "sg:province":"Ile de France",
    "wof:name":"Erce - Etude R\u00e9alisation C\u00e2blage Electronique S.a.r.l.",
    "wof:placetype":"venue"
},
  "geometry": {"coordinates":[2.13639,48.93034],"type":"Point"}
}