{
  "type": "Feature",
  "properties": {
    "iso:country":"FR",
    "sg:address":"107, Av. Daumesnil, 75012 Paris",
    "sg:orig_category":"Non-Classified Establishments",
    "sg:phone":"+33 1 43 45 72 72",
    "sg:postcode":"75012",
    "sg:province":"Ile de France",
    "wof:name":"Astier De Villatte S.a.r.l.",
    "wof:placetype":"venue"
},
  "geometry": {"coordinates":[2.380186,48.845047],"type":"Point"}
}