{
  "type": "Feature",
  "properties": {
    "addr:full":"2 Avenue De L'Universite Le Mercure Pau Aquitaine 64000",
    "addr:housenumber":"2",
    "addr:postcode":"64000",
    "addr:street":"Avenue De L'Universite Le Mercure Pau Aquitaine",
    "iso:country":"FR",
    "sg:address":"2 Avenue De L'Universite Le Mercure",
    "sg:city":"Pau",
    "sg:classifiers":[
        {
            "category":"Banks & Credit Unions",
            "subcategory":"Financial Services",
            "type":"Services"
        }
    ],
    "sg:phone":"+33 5 59 84 40 80",
    "sg:postcode":"64000",
    "sg:province":"Aquitaine",
    "sg:tags":[
        "banking",
        "finance",
        "insurance"
    ],
    "wof:name":"Assurances Generales De France Vie (agf Vie) Agfvie",
    "wof:placetype":"venue"
},
  "geometry": {"coordinates":[-0.34327,43.321529],"type":"Point"}
}