{
  "type": "Feature",
  "properties": {
    "addr:full":"All\u00e9e des Maronniers - ZI Ouest Heillecourt Lorraine 54180",
    "addr:postcode":"54180",
    "addr:street":"Alle\u0301E Des Maronniers Zi Ouest",
    "iso:country":"FR",
    "sg:address":"All\u00e9e des Maronniers - ZI Ouest",
    "sg:city":"Heillecourt",
    "sg:orig_category":"Unclassifiable Establishments",
    "sg:phone":"+33 3 83 55 11 86",
    "sg:postcode":"54180",
    "sg:province":"Lorraine",
    "wof:name":"Storest S.a.",
    "wof:placetype":"venue"
},
  "geometry": {"coordinates":[6.194192,48.653137],"type":"Point"}
}