{
  "type": "Feature",
  "properties": {
    "addr:full":"Kerloc'h la Torche 29120 Plomeur Plomeur Bretagne 29120",
    "addr:postcode":"29120;29120",
    "addr:street":"Kerloc'H",
    "iso:country":"FR",
    "sg:address":"Kerloc'h la Torche 29120 Plomeur",
    "sg:city":"Plomeur",
    "sg:orig_category":"Unclassifiable Establishments",
    "sg:phone":"+33 2 98 82 06 87",
    "sg:postcode":"29120",
    "sg:province":"Bretagne",
    "wof:name":"Kaandorp S.a.r.l.",
    "wof:placetype":"venue"
},
  "geometry": {"coordinates":[-4.214921,47.852547],"type":"Point"}
}