{
  "type": "Feature",
  "properties": {
    "addr:full":"Le Bourg Villexavier 17500 Jonzac Poitou-Charentes",
    "addr:postcode":"17500",
    "addr:street":"Le Bourg",
    "iso:country":"FR",
    "sg:address":"Le Bourg Villexavier 17500 Jonzac",
    "sg:orig_category":"Unclassifiable Establishments",
    "sg:phone":"+33 5 46 48 08 57",
    "sg:province":"Poitou-Charentes",
    "wof:name":"Kirogn S.a.r.l.",
    "wof:placetype":"venue"
},
  "geometry": {"coordinates":[-0.438104,45.371544],"type":"Point"}
}