{
  "type": "Feature",
  "properties": {
    "iso:country":"FR",
    "sg:address":"21 Rue Thiers 78100 St Germain En Laye",
    "sg:classifiers":[
        {
            "category":"Travel",
            "subcategory":"Hotels & Motels",
            "type":"Entertainment"
        }
    ],
    "sg:phone":"+33 1 39 10 15 15",
    "sg:postcode":"78100",
    "sg:province":"Ile de France",
    "sg:tags":[
        "hotels",
        "business",
        "restaurant"
    ],
    "wof:name":"Pavillon Henri Iv Sa",
    "wof:placetype":"venue"
},
  "geometry": {"coordinates":[2.100689,48.897957],"type":"Point"}
}