{
  "type": "Feature",
  "properties": {
    "addr:full":"Espace d'Activit\u00e9s Berthilliers Charnay l\u00e8s M\u00e2con Bourgogne 71850",
    "addr:postcode":"71850",
    "iso:country":"FR",
    "sg:address":"Espace d'Activit\u00e9s Berthilliers",
    "sg:city":"Charnay l\u00e8s M\u00e2con",
    "sg:orig_category":"Non-Classified Establishments",
    "sg:phone":"+33 3 85 20 55 20",
    "sg:postcode":"71850",
    "sg:province":"Bourgogne",
    "wof:name":"Breuil S.a.",
    "wof:placetype":"venue"
},
  "geometry": {"coordinates":[4.786419,46.288811],"type":"Point"}
}