{
  "type": "Feature",
  "properties": {
    "addr:full":"5, Rue Albert Einstein - Cit\u00e9 Descartes , 77420 Champs sur Marne Ile de France",
    "addr:housenumber":"5",
    "addr:postcode":"77420",
    "addr:street":"Rue Albert Einstein Cite\u0301 Descartes",
    "iso:country":"FR",
    "sg:address":"5, Rue Albert Einstein - Cit\u00e9 Descartes , 77420 Champs sur Marne",
    "sg:orig_category":"Unclassifiable Establishments",
    "sg:phone":"+33 1 64 73 50 56",
    "sg:province":"Ile de France",
    "wof:name":"Berti Paris S.a.",
    "wof:placetype":"venue"
},
  "geometry": {"coordinates":[2.58576,48.837208],"type":"Point"}
}