{
  "type": "Feature",
  "properties": {
    "iso:country":"FR",
    "sg:address":"4, Rue Guillaume de Bois de Nivard, 78640 Neauphle le Ch\u00e2teau",
    "sg:orig_category":"Unclassifiable Establishments",
    "sg:phone":"+33 1 34 89 59 19",
    "sg:province":"Ile de France",
    "wof:name":"Inter - Micron S.a.",
    "wof:placetype":"venue"
},
  "geometry": {"coordinates":[1.908855,48.815659],"type":"Point"}
}