{
  "type": "Feature",
  "properties": {
    "addr:full":"5 Rue Leva 01100 Oyonnax Rhone-Alpes 01100",
    "addr:housenumber":"5",
    "addr:postcode":"01100;01100",
    "addr:street":"Rue Leva",
    "iso:country":"FR",
    "sg:address":"5 Rue Leva 01100 Oyonnax",
    "sg:classifiers":[
        {
            "category":"Manufacturing",
            "subcategory":"Rubber & Plastics",
            "type":"Manufacturing & Wholesale Goods"
        }
    ],
    "sg:phone":"+33 4 74 77 80 08",
    "sg:postcode":"01100",
    "sg:province":"Rhone-Alpes",
    "wof:name":"Bmp Bernardi Metal Plastiques (bmp)",
    "wof:placetype":"venue"
},
  "geometry": {"coordinates":[5.656944,46.263916],"type":"Point"}
}