{
  "type": "Feature",
  "properties": {
    "addr:full":"Zi 45270 Bellegarde Bellegarde Centre 45270",
    "addr:postcode":"45270;45270",
    "addr:street":"Zi",
    "iso:country":"FR",
    "sg:address":"Zi 45270 Bellegarde",
    "sg:city":"Bellegarde",
    "sg:classifiers":[
        {
            "category":"Manufacturing",
            "subcategory":"Metals",
            "type":"Manufacturing & Wholesale Goods"
        }
    ],
    "sg:phone":"+33 2 38 95 02 30",
    "sg:postcode":"45270",
    "sg:province":"Centre",
    "sg:tags":[
        "metallurgy",
        "metalworking"
    ],
    "wof:name":"Hermex Sa",
    "wof:placetype":"venue"
},
  "geometry": {"coordinates":[2.452415,47.938614],"type":"Point"}
}