{
  "type": "Feature",
  "properties": {
    "addr:full":"24450 La Coquille La Coquille Aquitaine 24450",
    "addr:housenumber":"24450",
    "addr:postcode":"24450",
    "addr:street":"La Coquille La Coquille",
    "iso:country":"FR",
    "sg:address":"24450 La Coquille",
    "sg:city":"La Coquille",
    "sg:orig_category":"Non-Classified Establishments",
    "sg:phone":"+33 5 53 52 85 48",
    "sg:postcode":"24450",
    "sg:province":"Aquitaine",
    "wof:name":"M.e.m. S.a. - M\u00e9canique Et Engrenage Moderne",
    "wof:placetype":"venue"
},
  "geometry": {"coordinates":[0.976805,45.541626],"type":"Point"}
}