{
  "type": "Feature",
  "properties": {
    "iso:country":"FR",
    "sg:address":"Place Chateaubriand",
    "sg:city":"Planco\u00ebt",
    "sg:orig_category":"Unclassifiable Establishments",
    "sg:phone":"+33 2 96 84 13 66",
    "sg:postcode":"22130",
    "sg:province":"Bretagne",
    "wof:name":"C De Swan S.a.r.l.",
    "wof:placetype":"venue"
},
  "geometry": {"coordinates":[-2.238639,48.522671],"type":"Point"}
}