{
  "type": "Feature",
  "properties": {
    "iso:country":"FR",
    "sg:address":"Domaine De Clairac 34370 CAZOULS LES BEZIERS",
    "sg:classifiers":[
        {
            "category":"Wholesale",
            "subcategory":"Wine & Distilled Alcoholic Beverages",
            "type":"Manufacturing & Wholesale Goods"
        }
    ],
    "sg:phone":"+33 4 67 90 55 62",
    "sg:postcode":"34370",
    "sg:province":"Languedoc-Roussillon",
    "sg:tags":[
        "french"
    ],
    "wof:name":"Clairac Gfa",
    "wof:placetype":"venue"
},
  "geometry": {"coordinates":[3.15464,43.36832],"type":"Point"}
}