{
  "type": "Feature",
  "properties": {
    "iso:country":"FR",
    "sg:address":"Montpezat de Quercy 82270 Montpezat de Quercy",
    "sg:classifiers":[
        {
            "category":"Food & Beverages",
            "subcategory":"Fruits & Vegetables",
            "type":"Retail Goods"
        }
    ],
    "sg:phone":"+33 5 63 02 08 48",
    "sg:postcode":"82270",
    "sg:province":"Midi Pyr\u00e9n\u00e9es",
    "wof:name":"S.c.a. Des Product.de Montpezat De Quercy",
    "wof:placetype":"venue"
},
  "geometry": {"coordinates":[1.47572,44.238129],"type":"Point"}
}