{
  "type": "Feature",
  "properties": {
    "addr:full":"793 R Du G\u00e9n\u00e9ral De Gaulle 26801 Portes Les Valence Cedex Pays de Loire",
    "addr:housenumber":"793",
    "addr:postcode":"26801;cedex pays",
    "addr:street":"R Du Ge\u0301Ne\u0301Ral De Gaulle",
    "iso:country":"FR",
    "sg:address":"793 R Du G\u00e9n\u00e9ral De Gaulle 26801 Portes Les Valence Cedex",
    "sg:classifiers":[
        {
            "category":"Autos & Motor Vehicles",
            "subcategory":"Automobile Sales",
            "type":"Retail Goods"
        }
    ],
    "sg:phone":"+33 4 75 57 99 26",
    "sg:province":"Pays de Loire",
    "sg:tags":[
        "equipment",
        "industrial",
        "transport"
    ],
    "wof:name":"Thomas Constructeurs Sa",
    "wof:placetype":"venue"
},
  "geometry": {"coordinates":[4.87721,44.876316],"type":"Point"}
}