{
  "type": "Feature",
  "properties": {
    "addr:full":"ZA de la For\u00eat Le Bignon Pays de Loire 44140",
    "addr:postcode":"44140",
    "addr:street":"Za De La Fore\u0302T",
    "iso:country":"FR",
    "sg:address":"ZA de la For\u00eat",
    "sg:city":"Le Bignon",
    "sg:orig_category":"Unclassifiable Establishments",
    "sg:phone":"+33 2 40 26 18 40",
    "sg:postcode":"44140",
    "sg:province":"Pays de Loire",
    "wof:name":"Leray Transports S.a.",
    "wof:placetype":"venue"
},
  "geometry": {"coordinates":[-1.491806,47.097389],"type":"Point"}
}