{
  "type": "Feature",
  "properties": {
    "iso:country":"FR",
    "sg:address":"41 Rue Henri Giffard 87280 Limoges",
    "sg:classifiers":[
        {
            "category":"Professional",
            "subcategory":"Printing & Photocopies",
            "type":"Services"
        }
    ],
    "sg:phone":"+33 5 55 37 03 04",
    "sg:province":"Limousin",
    "sg:tags":[
        "publishing"
    ],
    "wof:name":"Librairie Biblioteca",
    "wof:placetype":"venue"
},
  "geometry": {"coordinates":[1.264928,45.876335],"type":"Point"}
}