{
  "type": "Feature",
  "properties": {
    "iso:country":"FR",
    "sg:address":"Les Berthiers 58150 Pouilly sur Loire",
    "sg:city":"Garchy",
    "sg:orig_category":"Non-Classified Establishments",
    "sg:phone":"+33 3 86 39 11 18",
    "sg:postcode":"58150",
    "sg:province":"Bourgogne",
    "wof:name":"Dagueneau Serge Et Filles",
    "wof:placetype":"venue"
},
  "geometry": {"coordinates":[2.95032,47.307598],"type":"Point"}
}