{
  "type": "Feature",
  "properties": {
    "addr:full":"27 R Bernard Palissy BP 33 Zi 45800 St Jean De Braye Combleux Centre 45800",
    "addr:housenumber":"27;bp 33;combleux",
    "addr:postcode":"45800;45800",
    "addr:street":"R Bernard Palissy;Zi",
    "iso:country":"FR",
    "sg:address":"27 R Bernard Palissy BP 33 Zi 45800 St Jean De Braye",
    "sg:city":"Combleux",
    "sg:classifiers":[
        {
            "category":"Manufacturing",
            "subcategory":"Printing",
            "type":"Manufacturing & Wholesale Goods"
        }
    ],
    "sg:phone":"+33 2 38 83 80 10",
    "sg:postcode":"45800",
    "sg:province":"Centre",
    "sg:tags":[
        "publishing"
    ],
    "wof:name":"Inter Bureau Assistance Reprographie Sa",
    "wof:placetype":"venue"
},
  "geometry": {"coordinates":[1.96818,47.912338],"type":"Point"}
}