{
  "type": "Feature",
  "properties": {
    "iso:country":"FR",
    "sg:address":"28, Rue de la Fa\u00efencerie, 57565 Niderviller",
    "sg:city":"Vill\u00e9",
    "sg:orig_category":"Non-Classified Establishments",
    "sg:phone":"+33 3 87 23 79 32",
    "sg:postcode":"67220",
    "sg:province":"Alsace",
    "wof:name":"Les Carri\u00e8res De Niderviller Metzger Fr\u00e8res S.a.r.l.",
    "wof:placetype":"venue"
},
  "geometry": {"coordinates":[7.10827,48.712105],"type":"Point"}
}