{
  "type": "Feature",
  "properties": {
    "addr:full":"Le Frambourg 25300 La Cluse et Mijoux Franche Comt\u00e9",
    "addr:postcode":"25300",
    "addr:street":"Le Frambourg;Franche Comte\u0301",
    "iso:country":"FR",
    "sg:address":"Le Frambourg 25300 La Cluse et Mijoux",
    "sg:orig_category":"Unclassifiable Establishments",
    "sg:phone":"+33 3 81 38 49 00",
    "sg:province":"Franche Comt\u00e9",
    "wof:name":"Frambourg Productions S.a.",
    "wof:placetype":"venue"
},
  "geometry": {"coordinates":[6.386785,46.87257],"type":"Point"}
}