{
  "type": "Feature",
  "properties": {
    "iso:country":"FR",
    "sg:address":"B.P. 118, 64121 Serres Castet C\u00e9dex^^Place d'Ossau, 64121 Serres Castet",
    "sg:city":"Montardon",
    "sg:orig_category":"Non-Classified Establishments",
    "sg:phone":"+33 5 59 33 30 70",
    "sg:postcode":"64121",
    "sg:province":"Aquitaine",
    "wof:name":"Manager S.a.",
    "wof:placetype":"venue"
},
  "geometry": {"coordinates":[-0.3603,43.37347],"type":"Point"}
}