{
  "type": "Feature",
  "properties": {
    "iso:country":"FR",
    "sg:address":"Zone Artisanale 08160 Flize",
    "sg:city":"Balaives-et-Butz",
    "sg:classifiers":[
        {
            "category":"Professional",
            "subcategory":"Engineering",
            "type":"Services"
        }
    ],
    "sg:phone":"+33 3 24 54 57 15",
    "sg:postcode":"08160",
    "sg:province":"Champagne",
    "sg:tags":[
        "machine",
        "-",
        "mechanical"
    ],
    "wof:name":"Etablissements Lecoche",
    "wof:placetype":"venue"
},
  "geometry": {"coordinates":[4.774066,49.702785],"type":"Point"}
}