{
  "type": "Feature",
  "properties": {
    "iso:country":"FR",
    "sg:address":"83, Chemin de Mimet, 13015 Marseille",
    "sg:orig_category":"Unclassifiable Establishments",
    "sg:phone":"+33 4 91 96 07 02",
    "sg:province":"Poitou-Charentes",
    "wof:name":"Ultranet S.a.r.l.",
    "wof:placetype":"venue"
},
  "geometry": {"coordinates":[5.355991,43.373196],"type":"Point"}
}