{
  "type": "Feature",
  "properties": {
    "addr:full":"Domaine De Terrefort 17100 Saintes Poitou-Charentes",
    "addr:postcode":"17100",
    "iso:country":"FR",
    "sg:address":"Domaine De Terrefort 17100 Saintes",
    "sg:classifiers":[
        {
            "category":"Home & Garden",
            "subcategory":"Furniture",
            "type":"Retail Goods"
        }
    ],
    "sg:phone":"+33 5 46 93 61 66",
    "sg:province":"Poitou-Charentes",
    "sg:tags":[
        "wood"
    ],
    "wof:name":"Bmso Point P Charentaise Des Bois",
    "wof:placetype":"venue"
},
  "geometry": {"coordinates":[-0.594466,45.744179],"type":"Point"}
}