{
  "type": "Feature",
  "properties": {
    "addr:full":"8, Av. du Champ de Mars - ZI de Plaisance, 11100 Narbonne Languedoc-Roussillon",
    "addr:postcode":"11100",
    "addr:street":"Av. Du Champ De Mars Zi De Plaisance",
    "iso:country":"FR",
    "sg:address":"8, Av. du Champ de Mars - ZI de Plaisance, 11100 Narbonne",
    "sg:orig_category":"Non-Classified Establishments",
    "sg:phone":"+33 4 68 41 74 00",
    "sg:province":"Languedoc-Roussillon",
    "wof:name":"S.c.t. S.a. - Soci\u00e9t\u00e9 Commerciale Tout\u00e9lectric",
    "wof:placetype":"venue"
},
  "geometry": {"coordinates":[6.52913,51.676762],"type":"Point"}
}