{
  "type": "Feature",
  "properties": {
    "iso:country":"FR",
    "sg:address":"2 Rte Sable Sur Sarthe 72140 Sill\u00e9 Le Guillaume",
    "sg:classifiers":[
        {
            "category":"Autos & Motor Vehicles",
            "subcategory":"Automobile Sales",
            "type":"Retail Goods"
        }
    ],
    "sg:phone":"+33 2 43 20 11 48",
    "sg:postcode":"72140",
    "sg:province":"Pays de Loire",
    "sg:tags":[
        "equipment",
        "motor-cars",
        "transport"
    ],
    "wof:name":"Pioger Et Fils Sarl",
    "wof:placetype":"venue"
},
  "geometry": {"coordinates":[-0.210974,48.093803],"type":"Point"}
}