{
  "type": "Feature",
  "properties": {
    "iso:country":"FR",
    "sg:address":"36, Av. des Chata\u00eegniers, 95157 Taverny C\u00e9dex",
    "sg:city":"Taverny",
    "sg:orig_category":"Non-Classified Establishments",
    "sg:phone":"+33 1 39 60 77 66",
    "sg:postcode":"95150",
    "sg:province":"Ile de France",
    "wof:name":"Ka\u00efcom S.a.r.l.",
    "wof:placetype":"venue"
},
  "geometry": {"coordinates":[2.18859,49.024815],"type":"Point"}
}