{
  "type": "Feature",
  "properties": {
    "iso:country":"FR",
    "sg:address":"Les Places 42110 Civens",
    "sg:classifiers":[
        {
            "category":"Bakery",
            "type":"Food & Drink"
        }
    ],
    "sg:phone":"+33 4 77 27 01 20",
    "sg:postcode":"42110",
    "sg:province":"Rhone-Alpes",
    "sg:tags":[
        "cake",
        "product",
        "related",
        "bread"
    ],
    "wof:name":"Guico",
    "wof:placetype":"venue"
},
  "geometry": {"coordinates":[4.21672,45.767021],"type":"Point"}
}