{
  "type": "Feature",
  "properties": {
    "iso:country":"FR",
    "sg:address":"ZI n\u00b0 458",
    "sg:city":"Gournay en Bray",
    "sg:orig_category":"Unclassifiable Establishments",
    "sg:phone":"+33 2 32 89 40 00",
    "sg:postcode":"76220",
    "sg:province":"Haute Normandie",
    "wof:name":"Autoliv France S.n.c.",
    "wof:placetype":"venue"
},
  "geometry": {"coordinates":[1.716074,49.421104],"type":"Point"}
}