{
  "type": "Feature",
  "properties": {
    "iso:country":"FR",
    "sg:address":"B.P. 15, 51801 Sainte M\u00e9n\u00e9hould C\u00e9dex^^Parc d'Activit\u00e9s des Accrues, 51800 Sainte M\u00e9n\u00e9hould",
    "sg:orig_category":"Non-Classified Establishments",
    "sg:phone":"+33 3 26 60 88 31",
    "sg:province":"Champagne",
    "wof:name":"S.e.c.m.a. S.a. - Soci\u00e9t\u00e9 D'etude Et Construction M\u00e9canique Et Automatisme",
    "wof:placetype":"venue"
},
  "geometry": {"coordinates":[4.892038,49.091434],"type":"Point"}
}