{
  "type": "Feature",
  "properties": {
    "addr:full":"Rue Bernard Palissy - ZI n\u00b0 2 Chinon Centre 37500",
    "addr:housenumber":"zi n\u00b0 2",
    "addr:postcode":"37500",
    "addr:street":"Rue Bernard Palissy;Chinon Centre",
    "iso:country":"FR",
    "sg:address":"Rue Bernard Palissy - ZI n\u00b0 2",
    "sg:city":"Chinon",
    "sg:orig_category":"Non-Classified Establishments",
    "sg:phone":"+33 2 47 93 43 00",
    "sg:postcode":"37500",
    "sg:province":"Centre",
    "wof:name":"Presta'bureau S.a.r.l.",
    "wof:placetype":"venue"
},
  "geometry": {"coordinates":[0.19145,47.077888],"type":"Point"}
}