{
  "type": "Feature",
  "properties": {
    "addr:full":"Parc Club Du Golf Bloc B-Les Galaxies 13856 Aix En Provence Nord Pas-de-Calais",
    "addr:postcode":"13856",
    "addr:street":"Galaxies;En Provence Nord",
    "iso:country":"FR",
    "sg:address":"Parc Club Du Golf Bloc B-Les Galaxies 13856 Aix En Provence",
    "sg:classifiers":[
        {
            "category":"Professional",
            "subcategory":"Engineering",
            "type":"Services"
        }
    ],
    "sg:phone":"+33 4 93 74 69 65",
    "sg:province":"Nord Pas-de-Calais",
    "sg:tags":[
        "machine",
        "-",
        "mechanical"
    ],
    "wof:name":"Wespar Sa",
    "wof:placetype":"venue"
},
  "geometry": {"coordinates":[5.4542,43.52494],"type":"Point"}
}