{
  "type": "Feature",
  "properties": {
    "addr:full":"Route De Dollon 72390 Semur En Vallon Pays de Loire 72390",
    "addr:postcode":"dollon 72390;72390",
    "addr:street":"Route De",
    "iso:country":"FR",
    "sg:address":"Route De Dollon 72390 Semur En Vallon",
    "sg:classifiers":[
        {
            "category":"Manufacturing",
            "subcategory":"Metals",
            "type":"Manufacturing & Wholesale Goods"
        }
    ],
    "sg:phone":"+33 2 43 93 67 64",
    "sg:postcode":"72390",
    "sg:province":"Pays de Loire",
    "sg:tags":[
        "-",
        "machine",
        "equipment",
        "engineering",
        "machinery",
        "mechanical"
    ],
    "wof:name":"Eroc Sas",
    "wof:placetype":"venue"
},
  "geometry": {"coordinates":[0.653929,48.023235],"type":"Point"}
}