{
  "type": "Feature",
  "properties": {
    "iso:country":"FR",
    "sg:address":"B.P. 19, 70101 Gray C\u00e9dex^^24, Quai Villeneuve, 70100 Gray",
    "sg:orig_category":"Non-Classified Establishments",
    "sg:phone":"+33 3 84 65 13 23",
    "sg:postcode":"70100",
    "sg:province":"Franche Comt\u00e9",
    "wof:name":"Baulard S.a.",
    "wof:placetype":"venue"
},
  "geometry": {"coordinates":[5.514565,47.369511],"type":"Point"}
}