{
  "type": "Feature",
  "properties": {
    "iso:country":"FR",
    "sg:address":"36, Av. Pierre Grenier, 92100 Boulogne Billancourt",
    "sg:orig_category":"Non-Classified Establishments",
    "sg:phone":"+33 1 46 08 13 69",
    "sg:province":"Ile de France",
    "wof:name":"Eurodis France Restauration S.a.r.l.",
    "wof:placetype":"venue"
},
  "geometry": {"coordinates":[2.251772,48.829868],"type":"Point"}
}