{
  "type": "Feature",
  "properties": {
    "iso:country":"FR",
    "sg:address":"4 Rue Du Nouvelet 94310 Orly",
    "sg:classifiers":[
        {
            "category":"Wholesale",
            "subcategory":"Machinery & Supplies",
            "type":"Manufacturing & Wholesale Goods"
        }
    ],
    "sg:phone":"+33 1 48 52 80 00",
    "sg:postcode":"94310",
    "sg:province":"Ile de France",
    "sg:tags":[
        "handling",
        "material",
        "-",
        "machine",
        "equipment",
        "engineering",
        "mechanical"
    ],
    "wof:name":"Saudem Sa",
    "wof:placetype":"venue"
},
  "geometry": {"coordinates":[2.405562,48.741131],"type":"Point"}
}