{
  "type": "Feature",
  "properties": {
    "iso:country":"FR",
    "sg:address":"74, Rue Raymond Duflo, 76150 Maromme",
    "sg:orig_category":"Non-Classified Establishments",
    "sg:phone":"+33 2 35 75 88 60",
    "sg:province":"Haute Normandie",
    "wof:name":"S.n.e.t.a. S.a.r.l. - Soci\u00e9t\u00e9 Normande D'etudes Techniques D'am\u00e9nagement",
    "wof:placetype":"venue"
},
  "geometry": {"coordinates":[-97.329231,32.748508],"type":"Point"}
}