{
  "type": "Feature",
  "properties": {
    "iso:country":"FR",
    "sg:address":"B.P. 5803, 31505 Toulouse C\u00e9dex 5^^2, Impasse Henri Pitot - Parc Technologique de la Plaine, 31500 T",
    "sg:orig_category":"Non-Classified Establishments",
    "sg:phone":"+33 5 61 36 76 36",
    "sg:postcode":"31500",
    "sg:province":"Midi Pyr\u00e9n\u00e9es",
    "wof:name":"Allium S.a.",
    "wof:placetype":"venue"
},
  "geometry": {"coordinates":[1.44301,43.604359],"type":"Point"}
}