{
  "type": "Feature",
  "properties": {
    "iso:country":"FR",
    "sg:address":"7 Rue Jeanne D Arc 55100 Verdun",
    "sg:classifiers":[
        {
            "category":"Professional",
            "subcategory":"Advertising",
            "type":"Services"
        }
    ],
    "sg:phone":"+33 3 29 86 19 20",
    "sg:postcode":"55100",
    "sg:province":"Lorraine",
    "sg:tags":[
        "communication",
        "medium",
        "telecommunication"
    ],
    "wof:name":"Prosper Guy",
    "wof:placetype":"venue"
},
  "geometry": {"coordinates":[5.382288,49.162788],"type":"Point"}
}