{
  "type": "Feature",
  "properties": {
    "addr:full":"4/6 rue Basson 42000 ST ETIENNE Rhone-Alpes 42000",
    "addr:housenumber":"4 / 6",
    "addr:postcode":"42000;42000",
    "addr:street":"Rue Basson",
    "iso:country":"FR",
    "sg:address":"4/6 rue Basson 42000 ST ETIENNE",
    "sg:classifiers":[
        {
            "category":"Health Services",
            "subcategory":"Dentist",
            "type":"Services"
        }
    ],
    "sg:phone":"+33 4 77 32 36 49",
    "sg:postcode":"42000",
    "sg:province":"Rhone-Alpes",
    "sg:tags":[
        "dental",
        "material",
        "protheses"
    ],
    "wof:name":"Vincenot R. Si",
    "wof:placetype":"venue"
},
  "geometry": {"coordinates":[4.37809,45.433334],"type":"Point"}
}