{
  "type": "Feature",
  "properties": {
    "addr:full":"route de Thuir 66000 Perpignan Languedoc-Roussillon 66000",
    "addr:postcode":"66000;66000",
    "addr:street":"Route De Thuir",
    "iso:country":"FR",
    "sg:address":"route de Thuir 66000 Perpignan",
    "sg:classifiers":[
        {
            "category":"Wholesale",
            "subcategory":"Home Furnishings",
            "type":"Manufacturing & Wholesale Goods"
        }
    ],
    "sg:phone":"+33 4 68 54 47 76",
    "sg:postcode":"66000",
    "sg:province":"Languedoc-Roussillon",
    "sg:tags":[
        "house",
        "paint"
    ],
    "wof:name":"La Maison Du Papier Peint Sa",
    "wof:placetype":"venue"
},
  "geometry": {"coordinates":[2.88743,42.69812],"type":"Point"}
}