{
  "type": "Feature",
  "properties": {
    "addr:full":"80 Av De Chateaudun 41000 Blois Blois Centre 41000",
    "addr:postcode":"41000;41000",
    "addr:street":"80 Av De Chateaudun",
    "iso:country":"FR",
    "sg:address":"80 Av De Chateaudun 41000 Blois",
    "sg:city":"Blois",
    "sg:classifiers":[
        {
            "category":"Manufacturing",
            "subcategory":"Chemicals & Compounds",
            "type":"Manufacturing & Wholesale Goods"
        }
    ],
    "sg:phone":"+33 2 54 78 68 52",
    "sg:postcode":"41000",
    "sg:province":"Centre",
    "sg:tags":[
        "pharmaceutical",
        "energy",
        "chemistry",
        "-",
        "by-product"
    ],
    "wof:name":"Caldeo Sa",
    "wof:placetype":"venue"
},
  "geometry": {"coordinates":[1.327851,47.603035],"type":"Point"}
}