{
  "type": "Feature",
  "properties": {
    "iso:country":"FR",
    "sg:address":"95 av Edouard Millaud; Lyon; 69290",
    "sg:classifiers":[
        {
            "category":"Banks & Credit Unions",
            "subcategory":"Bank",
            "type":"Services"
        }
    ],
    "sg:phone":"+33 3378446530",
    "sg:postcode":"69290",
    "sg:province":"Rhone-Alpes",
    "wof:name":"Soci\u00e9t\u00e9 G\u00e9n\u00e9rale",
    "wof:placetype":"venue"
},
  "geometry": {"coordinates":[4.723724,45.747219],"type":"Point"}
}