{
  "type": "Feature",
  "properties": {
    "iso:country":"FR",
    "sg:address":"chemin d'allive 38140 RENAGE",
    "sg:classifiers":[
        {
            "category":"Recreation",
            "subcategory":"Theme Park",
            "type":"Entertainment"
        }
    ],
    "sg:phone":"+33 4 76 91 21 21",
    "sg:postcode":"38140",
    "sg:province":"Rhone-Alpes",
    "sg:tags":[
        "paper",
        "wrapping"
    ],
    "wof:name":"Rescaset S.a.",
    "wof:placetype":"venue"
},
  "geometry": {"coordinates":[-89.977074,35.245281],"type":"Point"}
}