{
  "type": "Feature",
  "properties": {
    "iso:country":"FR",
    "sg:address":"17 Rue Jean Monnet 68271 Wittenheim Cedex",
    "sg:city":"Ittenheim",
    "sg:classifiers":[
        {
            "category":"Shopping",
            "subcategory":"Computers & Home Electronics",
            "type":"Retail Goods"
        }
    ],
    "sg:phone":"+33 3 89 50 73 73",
    "sg:postcode":"67117",
    "sg:province":"Alsace",
    "sg:tags":[
        "information",
        "telecommunication",
        "household",
        "appliance",
        "technology",
        "audio-visual"
    ],
    "wof:name":"Hyper Media Electronique 5",
    "wof:placetype":"venue"
},
  "geometry": {"coordinates":[7.314393,47.803299],"type":"Point"}
}