{
  "type": "Feature",
  "properties": {
    "addr:full":"Chaudoux 18300 VERDIGNY Verdigny Centre 18300",
    "addr:housenumber":"verdigny",
    "addr:postcode":"18300;18300",
    "addr:street":"Chaudoux",
    "iso:country":"FR",
    "sg:address":"Chaudoux 18300 VERDIGNY",
    "sg:city":"Verdigny",
    "sg:classifiers":[
        {
            "category":"Wholesale",
            "subcategory":"Wine & Distilled Alcoholic Beverages",
            "type":"Manufacturing & Wholesale Goods"
        }
    ],
    "sg:phone":"+33 2 48 79 35 24",
    "sg:postcode":"18300",
    "sg:province":"Centre",
    "sg:tags":[
        "french"
    ],
    "wof:name":"Fournier P\u00e8re Et Fils S.a.s",
    "wof:placetype":"venue"
},
  "geometry": {"coordinates":[2.81307,47.352901],"type":"Point"}
}