{
  "type": "Feature",
  "properties": {
    "addr:full":"B.P. 60, 95332 Domont C\u00e9dex^^3, Rue Pierre Emmanuel, 95330 Domont Ile de France",
    "addr:postcode":"95332;95330",
    "addr:street":"B.P. 60;Rue Pierre Emmanuel;Ile De France",
    "iso:country":"FR",
    "sg:address":"B.P. 60, 95332 Domont C\u00e9dex^^3, Rue Pierre Emmanuel, 95330 Domont",
    "sg:orig_category":"Non-Classified Establishments",
    "sg:phone":"+33 1 39 91 04 76",
    "sg:province":"Ile de France",
    "wof:name":"Quatro Agencements Placards Cuisines S.a.r.l.",
    "wof:placetype":"venue"
},
  "geometry": {"coordinates":[2.326687,49.026634],"type":"Point"}
}