{
  "type": "Feature",
  "properties": {
    "iso:country":"FR",
    "sg:address":"36, Rue Duranton, 75015 Paris",
    "sg:orig_category":"Unclassifiable Establishments",
    "sg:phone":"+33 1 45 57 07 07",
    "sg:province":"Ile de France",
    "wof:name":"J.d. Informatique S.a.",
    "wof:placetype":"venue"
},
  "geometry": {"coordinates":[2.287459,48.839176],"type":"Point"}
}