{
  "type": "Feature",
  "properties": {
    "iso:country":"FR",
    "sg:address":"36210 Dun le Po\u00eblier",
    "sg:city":"Anjouin",
    "sg:orig_category":"Non-Classified Establishments",
    "sg:phone":"+33 2 54 40 63 26",
    "sg:postcode":"36210",
    "sg:province":"Centre",
    "wof:name":"Jourdant S.a.r.l.",
    "wof:placetype":"venue"
},
  "geometry": {"coordinates":[1.752865,47.204288],"type":"Point"}
}