{
  "type": "Feature",
  "properties": {
    "addr:full":"18 ave Maurice Petsche; Brian\u00e7on Aquitaine",
    "addr:street":"18 Ave Maurice Petsche",
    "iso:country":"FR",
    "sg:address":"18 ave Maurice Petsche; Brian\u00e7on",
    "sg:classifiers":[
        {
            "category":"Banks & Credit Unions",
            "subcategory":"Bank",
            "type":"Services"
        }
    ],
    "sg:phone":"+33 3392202818",
    "sg:province":"Aquitaine",
    "wof:name":"Banque Populaire De La, Region Dauphinoise",
    "wof:placetype":"venue"
},
  "geometry": {"coordinates":[6.632562,44.895618],"type":"Point"}
}