{
  "type": "Feature",
  "properties": {
    "addr:full":"Place Jean Baptiste Corot 95380 Louvres Ile de France 95380",
    "addr:postcode":"95380;95380",
    "addr:street":"Place Jean Baptiste Corot;Ile De France",
    "iso:country":"FR",
    "sg:address":"Place Jean Baptiste Corot 95380 Louvres",
    "sg:classifiers":[
        {
            "category":"Bakery",
            "type":"Food & Drink"
        }
    ],
    "sg:phone":"+33 1 34 68 14 10",
    "sg:postcode":"95380",
    "sg:province":"Ile de France",
    "sg:tags":[
        "cake",
        "product",
        "related",
        "bread"
    ],
    "wof:name":"Au Fin Gourmet",
    "wof:placetype":"venue"
},
  "geometry": {"coordinates":[2.50608,49.046261],"type":"Point"}
}