{
  "type": "Feature",
  "properties": {
    "addr:full":"40, Av. Georges V, 35800 Dinard Dinard Bretagne 35800",
    "addr:postcode":"35800",
    "addr:street":"40 Av. Georges V",
    "iso:country":"FR",
    "sg:address":"40, Av. Georges V, 35800 Dinard",
    "sg:city":"Dinard",
    "sg:orig_category":"Non-Classified Establishments",
    "sg:phone":"+33 2 99 46 13 13",
    "sg:postcode":"35800",
    "sg:province":"Bretagne",
    "wof:name":"Jules Boutin Travel Bureau S.a.",
    "wof:placetype":"venue"
},
  "geometry": {"coordinates":[-2.050889,48.634045],"type":"Point"}
}