{
  "type": "Feature",
  "properties": {
    "addr:full":"29 Av De La Camargue 13632 Arles",
    "addr:postcode":"13632",
    "addr:street":"29 Av De La Camargue",
    "iso:country":"FR",
    "sg:address":"29 Av De La Camargue 13632 Arles",
    "sg:classifiers":[
        {
            "category":"Manufacturing",
            "subcategory":"Paper Products",
            "type":"Manufacturing & Wholesale Goods"
        }
    ],
    "sg:phone":"+33 4 90 99 44 00",
    "sg:tags":[
        "finished",
        "cardboard",
        "-"
    ],
    "wof:name":"Papeterie Etienne",
    "wof:placetype":"venue"
},
  "geometry": {"coordinates":[4.6278,43.676651],"type":"Point"}
}