{
  "type": "Feature",
  "properties": {
    "addr:full":"47 Rue De La R\u00e9publique 73200 Albertville Rhone-Alpes 73200",
    "addr:housenumber":"47",
    "addr:postcode":"73200;73200",
    "addr:street":"Rue De La Re\u0301Publique",
    "iso:country":"FR",
    "sg:address":"47 Rue De La R\u00e9publique 73200 Albertville",
    "sg:classifiers":[
        {
            "category":"Banks & Credit Unions",
            "subcategory":"Financial Services",
            "type":"Services"
        }
    ],
    "sg:phone":"+33 4 79 10 04 01",
    "sg:postcode":"73200",
    "sg:province":"Rhone-Alpes",
    "sg:tags":[
        "banking",
        "insurance",
        "institution",
        "finance"
    ],
    "wof:name":"Credit Lyonnais",
    "wof:placetype":"venue"
},
  "geometry": {"coordinates":[6.390592,45.67664],"type":"Point"}
}