{
  "type": "Feature",
  "properties": {
    "addr:full":"56 avenue Lef\u00e8vre 69120 Vaulx en Velin Rhone-Alpes 69120",
    "addr:housenumber":"56",
    "addr:postcode":"69120;69120",
    "addr:street":"Avenue Lefe\u0300Vre",
    "iso:country":"FR",
    "sg:address":"56 avenue Lef\u00e8vre 69120 Vaulx en Velin",
    "sg:classifiers":[
        {
            "category":"Building & Trades",
            "subcategory":"Construction",
            "type":"Services"
        }
    ],
    "sg:phone":"+33 4 72 04 92 92",
    "sg:postcode":"69120",
    "sg:province":"Rhone-Alpes",
    "sg:tags":[
        "tool",
        "cutting"
    ],
    "wof:name":"Fraisa Sarl",
    "wof:placetype":"venue"
},
  "geometry": {"coordinates":[4.911435,45.776066],"type":"Point"}
}