{
  "type": "Feature",
  "properties": {
    "addr:full":"10, Rue du Petit parc, 06000 Nice Picardie",
    "addr:housenumber":"10",
    "addr:postcode":"06000",
    "addr:street":"Rue Du Petit Parc",
    "iso:country":"FR",
    "sg:address":"10, Rue du Petit parc, 06000 Nice",
    "sg:orig_category":"Non-Classified Establishments",
    "sg:phone":"+33 4 93 96 19 11",
    "sg:province":"Picardie",
    "wof:name":"E.c.a. S.a.r.l. - Equipement Et Construction D'automatiques",
    "wof:placetype":"venue"
},
  "geometry": {"coordinates":[7.255343,43.705917],"type":"Point"}
}