{
  "type": "Feature",
  "properties": {
    "addr:full":"6, Bd H\u00e9rault, 49321 Cholet C\u00e9dex Picardie",
    "addr:housenumber":"6",
    "addr:postcode":"49321",
    "addr:street":"Bd He\u0301Rault",
    "iso:country":"FR",
    "sg:address":"6, Bd H\u00e9rault, 49321 Cholet C\u00e9dex",
    "sg:orig_category":"Non-Classified Establishments",
    "sg:phone":"+33 2 41 05 25 00",
    "sg:province":"Picardie",
    "wof:name":"C.d.c.",
    "wof:placetype":"venue"
},
  "geometry": {"coordinates":[-0.87999,47.068455],"type":"Point"}
}