{
  "type": "Feature",
  "properties": {
    "addr:full":"13, Rue Antoine Balard, 95310 Saint Ouen l'Aum\u00f4ne Ile de France",
    "addr:housenumber":"13",
    "addr:postcode":"95310",
    "addr:street":"Rue Antoine Balard",
    "iso:country":"FR",
    "sg:address":"13, Rue Antoine Balard, 95310 Saint Ouen l'Aum\u00f4ne",
    "sg:orig_category":"Non-Classified Establishments",
    "sg:phone":"+33 1 30 37 40 54",
    "sg:province":"Ile de France",
    "wof:name":"Silitro Electromagn\u00e9tisme S.a.r.l.",
    "wof:placetype":"venue"
},
  "geometry": {"coordinates":[0.972216,48.869061],"type":"Point"}
}