{
  "type": "Feature",
  "properties": {
    "addr:full":"3, Rue Brazza, 01200 Bellegarde sur Valserine Rhone-Alpes 01200",
    "addr:housenumber":"3",
    "addr:postcode":"01200;01200",
    "addr:street":"Rue Brazza;Rhone-Alpes",
    "iso:country":"FR",
    "sg:address":"3, Rue Brazza, 01200 Bellegarde sur Valserine",
    "sg:orig_category":"Unclassifiable Establishments",
    "sg:phone":"+33 4 50 48 22 35",
    "sg:postcode":"01200",
    "sg:province":"Rhone-Alpes",
    "wof:name":"Entreprise Vallier Roger",
    "wof:placetype":"venue"
},
  "geometry": {"coordinates":[5.823658,46.10693],"type":"Point"}
}