{
  "type": "Feature",
  "properties": {
    "addr:full":"48 Rue Beaurepaire 49400 Saumur Pays de Loire 49400",
    "addr:housenumber":"48",
    "addr:postcode":"49400;49400",
    "addr:street":"Rue Beaurepaire",
    "iso:country":"FR",
    "sg:address":"48 Rue Beaurepaire 49400 Saumur",
    "sg:classifiers":[
        {
            "category":"Food Court",
            "type":"Food & Drink"
        }
    ],
    "sg:phone":"+33 2 41 40 23 00",
    "sg:postcode":"49400",
    "sg:province":"Pays de Loire",
    "sg:tags":[
        "product",
        "related"
    ],
    "wof:name":"Combier",
    "wof:placetype":"venue"
},
  "geometry": {"coordinates":[-0.082575,47.260845],"type":"Point"}
}