{
  "type": "Feature",
  "properties": {
    "addr:full":"13 Av Paradis 65100 Lourdes Midi Pyr\u00e9n\u00e9es 65100",
    "addr:postcode":"65100;65100",
    "addr:street":"13 Av Paradis",
    "iso:country":"FR",
    "sg:address":"13 Av Paradis 65100 Lourdes",
    "sg:classifiers":[
        {
            "category":"Travel",
            "subcategory":"Hotels & Motels",
            "type":"Entertainment"
        }
    ],
    "sg:phone":"+33 5 62 94 20 59",
    "sg:postcode":"65100",
    "sg:province":"Midi Pyr\u00e9n\u00e9es",
    "sg:tags":[
        "hotels",
        "business",
        "restaurant"
    ],
    "wof:name":"Hotel Arcades",
    "wof:placetype":"venue"
},
  "geometry": {"coordinates":[-0.052993,43.093746],"type":"Point"}
}