{
  "type": "Feature",
  "properties": {
    "addr:full":"583 route de la Gare 84470 CHATEAUNEUF DE GADAGNE Ch\u00e2teau Bourgogne 71250",
    "addr:housenumber":"583",
    "addr:postcode":"84470;71250",
    "addr:street":"Route De La Gare",
    "iso:country":"FR",
    "sg:address":"583 route de la Gare 84470 CHATEAUNEUF DE GADAGNE",
    "sg:city":"Ch\u00e2teau",
    "sg:classifiers":[
        {
            "category":"Wholesale",
            "subcategory":"Wine & Distilled Alcoholic Beverages",
            "type":"Manufacturing & Wholesale Goods"
        }
    ],
    "sg:phone":"+33 4 90 22 63 63",
    "sg:postcode":"71250",
    "sg:province":"Bourgogne",
    "sg:tags":[
        "french"
    ],
    "wof:name":"Ste Coop Agricole Des Coteaux D'avignon",
    "wof:placetype":"venue"
},
  "geometry": {"coordinates":[4.954467,43.929253],"type":"Point"}
}