{
  "type": "Feature",
  "properties": {
    "addr:full":"Av Des Pap\u00e8teries 38190 Villard Bonnot Rhone-Alpes",
    "addr:postcode":"38190",
    "addr:street":"Av Des Pape\u0300Teries",
    "iso:country":"FR",
    "sg:address":"Av Des Pap\u00e8teries 38190 Villard Bonnot",
    "sg:classifiers":[
        {
            "category":"Manufacturing",
            "subcategory":"Paper Products",
            "type":"Manufacturing & Wholesale Goods"
        }
    ],
    "sg:phone":"+33 4 76 13 11 11",
    "sg:province":"Rhone-Alpes",
    "sg:tags":[
        "raw",
        "material",
        "-",
        "cardboard"
    ],
    "wof:name":"Ste Papeteries De Lancey",
    "wof:placetype":"venue"
},
  "geometry": {"coordinates":[5.894356,45.239876],"type":"Point"}
}