{
  "type": "Feature",
  "properties": {
    "iso:country":"FR",
    "sg:address":"1 Rue Pr\u00e9s Claux 48000 Mende",
    "sg:classifiers":[
        {
            "category":"Professional",
            "subcategory":"Business Services",
            "type":"Services"
        }
    ],
    "sg:phone":"+33 4 66 65 07 97",
    "sg:postcode":"48000",
    "sg:province":"Languedoc-Roussillon",
    "sg:tags":[
        "body",
        "advice"
    ],
    "wof:name":"Ass Lozerienne Aide A Domicile",
    "wof:placetype":"venue"
},
  "geometry": {"coordinates":[3.503138,44.519283],"type":"Point"}
}