{
  "type": "Feature",
  "properties": {
    "addr:full":"rue des Isles 89470 Moneteau Mon\u00e9teau Bourgogne 89470",
    "addr:postcode":"89470;89470",
    "addr:street":"Rue Des Isles",
    "iso:country":"FR",
    "sg:address":"rue des Isles 89470 Moneteau",
    "sg:city":"Mon\u00e9teau",
    "sg:orig_category":"Horse Saddleries",
    "sg:phone":"+33 3 86 46 36 14",
    "sg:postcode":"89470",
    "sg:province":"Bourgogne",
    "wof:name":"Auxerre B\u00e2ches Sci",
    "wof:placetype":"venue"
},
  "geometry": {"coordinates":[3.578025,47.829407],"type":"Point"}
}