{
  "type": "Feature",
  "properties": {
    "addr:full":"41 Rue Laon 02150 Sissonne Picardie 02150",
    "addr:housenumber":"41",
    "addr:postcode":"02150;02150",
    "addr:street":"Rue Laon",
    "iso:country":"FR",
    "sg:address":"41 Rue Laon 02150 Sissonne",
    "sg:classifiers":[
        {
            "category":"Autos & Motor Vehicles",
            "subcategory":"Automobile Sales",
            "type":"Retail Goods"
        }
    ],
    "sg:phone":"+33 3 23 80 02 02",
    "sg:postcode":"02150",
    "sg:province":"Picardie",
    "sg:tags":[
        "equipment",
        "industrial",
        "transport"
    ],
    "wof:name":"Valeo",
    "wof:placetype":"venue"
},
  "geometry": {"coordinates":[3.879604,49.571049],"type":"Point"}
}