{
  "type": "Feature",
  "properties": {
    "iso:country":"FR",
    "sg:address":"7, Rue Marcel Dassault, 33700 M\u00e9rignac",
    "sg:city":"M\u00e9rignac",
    "sg:orig_category":"Unclassifiable Establishments",
    "sg:phone":"+33 5 56 34 47 17",
    "sg:postcode":"33700",
    "sg:province":"Aquitaine",
    "wof:name":"Etandex S.a.",
    "wof:placetype":"venue"
},
  "geometry": {"coordinates":[-0.678129,44.847736],"type":"Point"}
}