{
  "type": "Feature",
  "properties": {
    "addr:full":"7, Rue Marcel Dassault, 33700 M\u00e9rignac M\u00e9rignac Aquitaine 33700",
    "addr:housenumber":"7",
    "addr:postcode":"33700;33700",
    "addr:street":"Rue Marcel Dassault",
    "iso:country":"FR",
    "sg:address":"7, Rue Marcel Dassault, 33700 M\u00e9rignac",
    "sg:city":"M\u00e9rignac",
    "sg:orig_category":"Unclassifiable Establishments",
    "sg:phone":"+33 5 56 34 47 17",
    "sg:postcode":"33700",
    "sg:province":"Aquitaine",
    "wof:name":"Etandex S.a.",
    "wof:placetype":"venue"
},
  "geometry": {"coordinates":[-0.678129,44.847736],"type":"Point"}
}