{
  "type": "Feature",
  "properties": {
    "addr:full":"151, Av. Aygalades, 13015 Marseille Provence-Alpes-C\u00f4te d'Azur",
    "addr:postcode":"13015",
    "addr:street":"151 Av. Aygalades",
    "iso:country":"FR",
    "sg:address":"151, Av. Aygalades, 13015 Marseille",
    "sg:orig_category":"Unclassifiable Establishments",
    "sg:phone":"+33 4 91 69 91 25",
    "sg:province":"Provence-Alpes-C\u00f4te d'Azur",
    "wof:name":"Itech S.a.",
    "wof:placetype":"venue"
},
  "geometry": {"coordinates":[5.366048,43.345402],"type":"Point"}
}