{
  "type": "Feature",
  "properties": {
    "addr:full":"48, Bd Galli\u00e9ni, 92137 Issy les Moulineaux C\u00e9dex \u00cele-de-France",
    "addr:housenumber":"48",
    "addr:postcode":"92137",
    "addr:street":"Bd Gallie\u0301Ni;Ce\u0301Dex",
    "iso:country":"FR",
    "sg:address":"48, Bd Galli\u00e9ni, 92137 Issy les Moulineaux C\u00e9dex",
    "sg:orig_category":"Non-Classified Establishments",
    "sg:phone":"+33 1 41 23 25 25",
    "sg:province":"\u00cele-de-France",
    "wof:name":"Sicma A\u00e9ro Seat S.a.",
    "wof:placetype":"venue"
},
  "geometry": {"coordinates":[2.26717,48.829456],"type":"Point"}
}