{
  "type": "Feature",
  "properties": {
    "iso:country":"FR",
    "sg:address":"Zi St Cl\u00e9ment 44450 La Chapelle Basse Mer",
    "sg:classifiers":[
        {
            "category":"Manufacturing",
            "subcategory":"Metals",
            "type":"Manufacturing & Wholesale Goods"
        }
    ],
    "sg:phone":"+33 2 40 03 61 46",
    "sg:postcode":"44450",
    "sg:province":"Pays de Loire",
    "sg:tags":[
        "metallurgy",
        "metalworking",
        "processing"
    ],
    "wof:name":"Mecam 44 Sarl",
    "wof:placetype":"venue"
},
  "geometry": {"coordinates":[-1.340579,47.274876],"type":"Point"}
}