{
  "type": "Feature",
  "properties": {
    "iso:country":"FR",
    "sg:address":"9/11, Rue Ren\u00e9 Cassin, 77173 Ch\u00e9vry Cossigny",
    "sg:orig_category":"Non-Classified Establishments",
    "sg:phone":"+33 1 60 62 32 00",
    "sg:province":"Ile de France",
    "wof:name":"M.t.r. S.a.",
    "wof:placetype":"venue"
},
  "geometry": {"coordinates":[2.652646,48.723507],"type":"Point"}
}