{
  "type": "Feature",
  "properties": {
    "addr:full":"45bis, Rue du Sergent Bobillot, 93100 Montreuil Ile de France",
    "addr:housenumber":"45bis",
    "addr:postcode":"93100",
    "addr:street":"Rue Du Sergent Bobillot",
    "iso:country":"FR",
    "sg:address":"45bis, Rue du Sergent Bobillot, 93100 Montreuil",
    "sg:orig_category":"Unclassifiable Establishments",
    "sg:phone":"+33 1 48 58 14 31",
    "sg:province":"Ile de France",
    "wof:name":"H\u00e9liosam S.a.",
    "wof:placetype":"venue"
},
  "geometry": {"coordinates":[2.433125,48.853603],"type":"Point"}
}