{
  "type": "Feature",
  "properties": {
    "addr:full":"Rte Montcenis Le Creusot Bourgogne 71200",
    "addr:postcode":"71200",
    "addr:street":"Rte Montcenis",
    "iso:country":"FR",
    "sg:address":"Rte Montcenis",
    "sg:city":"Le Creusot",
    "sg:orig_category":"Unclassifiable Establishments",
    "sg:phone":"+33 3 85 77 05 55",
    "sg:postcode":"71200",
    "sg:province":"Bourgogne",
    "wof:name":"B.m.s. S.a. - Bourgogne Machines Sp\u00e9ciales",
    "wof:placetype":"venue"
},
  "geometry": {"coordinates":[4.406655,46.800106],"type":"Point"}
}