{
  "type": "Feature",
  "properties": {
    "iso:country":"FR",
    "sg:address":"Rue Roger Anne",
    "sg:city":"Cherbourg",
    "sg:orig_category":"Unclassifiable Establishments",
    "sg:phone":"+33 2 33 87 64 20",
    "sg:postcode":"50100",
    "sg:province":"Basse Normandie",
    "wof:name":"Entreprise Burnouf S.n.c.",
    "wof:placetype":"venue"
},
  "geometry": {"coordinates":[-1.638769,49.641365],"type":"Point"}
}