{
  "type": "Feature",
  "properties": {
    "iso:country":"FR",
    "sg:address":"B.P. 13, 53290 Grez en Bou\u00e8re^^ZI La Promenade, 53290 Grez en Bou\u00e8re",
    "sg:orig_category":"Non-Classified Establishments",
    "sg:phone":"+33 2 43 09 14 50",
    "sg:postcode":"53290",
    "sg:province":"Pays de Loire",
    "wof:name":"Aprochim S.a.",
    "wof:placetype":"venue"
},
  "geometry": {"coordinates":[-0.546889,47.772057],"type":"Point"}
}