{
  "type": "Feature",
  "properties": {
    "addr:full":"Cidex 449 Charmeil Auvergne 03110",
    "addr:housenumber":"449",
    "addr:postcode":"03110",
    "addr:street":"Charmeil",
    "iso:country":"FR",
    "sg:address":"Cidex 449",
    "sg:city":"Charmeil",
    "sg:orig_category":"Non-Classified Establishments",
    "sg:phone":"+33 4 70 32 34 09",
    "sg:postcode":"03110",
    "sg:province":"Auvergne",
    "wof:name":"A\u00e9roport De Vichy Charmeil E.p.i.c.",
    "wof:placetype":"venue"
},
  "geometry": {"coordinates":[3.245541,46.18639],"type":"Point"}
}