{
  "type": "Feature",
  "properties": {
    "iso:country":"FR",
    "sg:address":"Zi Pied Gai 26400 Crest",
    "sg:classifiers":[
        {
            "category":"Utilities",
            "type":"Services"
        }
    ],
    "sg:phone":"+33 4 75 25 66 66",
    "sg:postcode":"26400",
    "sg:province":"Rhone-Alpes",
    "sg:tags":[
        "raw",
        "energy",
        "material"
    ],
    "wof:name":"Primagaz Prima Services",
    "wof:placetype":"venue"
},
  "geometry": {"coordinates":[5.02138,44.727585],"type":"Point"}
}