{
  "type": "Feature",
  "properties": {
    "addr:full":"23 Rue Des Peupliers 92007 Nanterre Cedex Languedoc-Roussillon",
    "addr:housenumber":"23",
    "addr:postcode":"92007;cedex",
    "addr:street":"Rue Des Peupliers",
    "iso:country":"FR",
    "sg:address":"23 Rue Des Peupliers 92007 Nanterre Cedex",
    "sg:classifiers":[
        {
            "category":"Manufacturing",
            "subcategory":"Textiles",
            "type":"Manufacturing & Wholesale Goods"
        }
    ],
    "sg:phone":"+33 1 47 80 99 78",
    "sg:province":"Languedoc-Roussillon",
    "sg:tags":[
        "clothing",
        "accessory"
    ],
    "wof:name":"Paritys",
    "wof:placetype":"venue"
},
  "geometry": {"coordinates":[2.213962,48.912575],"type":"Point"}
}