{
  "type": "Feature",
  "properties": {
    "addr:full":"25 Bis Rue Colbert 59800 Lille Nord Pas-de-Calais 59800",
    "addr:housenumber":"25 bis",
    "addr:postcode":"59800;59800",
    "addr:street":"Rue Colbert",
    "iso:country":"FR",
    "sg:address":"25 Bis Rue Colbert 59800 Lille",
    "sg:classifiers":[
        {
            "category":"Professional",
            "subcategory":"Business Services",
            "type":"Services"
        }
    ],
    "sg:phone":"+33 3 20 57 32 92",
    "sg:postcode":"59800",
    "sg:province":"Nord Pas-de-Calais",
    "sg:tags":[
        "training",
        "advice"
    ],
    "wof:name":"Association Scolaire Centre St Paul",
    "wof:placetype":"venue"
},
  "geometry": {"coordinates":[3.047732,50.627937],"type":"Point"}
}