{
  "type": "Feature",
  "properties": {
    "iso:country":"FR",
    "sg:address":"25 Bis Rue Colbert 59800 Lille",
    "sg:classifiers":[
        {
            "category":"Professional",
            "subcategory":"Business Services",
            "type":"Services"
        }
    ],
    "sg:phone":"+33 3 20 57 32 92",
    "sg:postcode":"59800",
    "sg:province":"Nord Pas-de-Calais",
    "sg:tags":[
        "training",
        "advice"
    ],
    "wof:name":"Association Scolaire Centre St Paul",
    "wof:placetype":"venue"
},
  "geometry": {"coordinates":[3.047732,50.627937],"type":"Point"}
}