{
  "type": "Feature",
  "properties": {
    "addr:full":"26, Rue du G\u00e9n\u00e9ral Gouraud, 68500 Guebwiller Guebwiller Alsace 68500",
    "addr:housenumber":"26",
    "addr:postcode":"68500;68500",
    "addr:street":"Rue Du Ge\u0301Ne\u0301Ral Gouraud",
    "iso:country":"FR",
    "sg:address":"26, Rue du G\u00e9n\u00e9ral Gouraud, 68500 Guebwiller",
    "sg:city":"Guebwiller",
    "sg:orig_category":"Non-Classified Establishments",
    "sg:phone":"+33 3 89 76 16 43",
    "sg:postcode":"68500",
    "sg:province":"Alsace",
    "wof:name":"C.g.s.t. Save S.a.s. - Compagnie Gazi\u00e8re Service Technique Save",
    "wof:placetype":"venue"
},
  "geometry": {"coordinates":[7.206487,47.91119],"type":"Point"}
}