{
  "type": "Feature",
  "properties": {
    "addr:full":"25, Rue Pierre Bourdan, 02930 Laon Picardie",
    "addr:housenumber":"25",
    "addr:postcode":"02930",
    "addr:street":"Rue Pierre Bourdan",
    "iso:country":"FR",
    "sg:address":"25, Rue Pierre Bourdan, 02930 Laon",
    "sg:orig_category":"Unclassifiable Establishments",
    "sg:phone":"+33 3 23 27 71 48",
    "sg:province":"Picardie",
    "wof:name":"C\u00e2bles Pirelli S.a.",
    "wof:placetype":"venue"
},
  "geometry": {"coordinates":[3.64621,49.571178],"type":"Point"}
}