{
  "type": "Feature",
  "properties": {
    "addr:full":"ferme de Galau 47520 Le Passage Le Passage Aquitaine 47520",
    "addr:postcode":"47520;47520",
    "iso:country":"FR",
    "sg:address":"ferme de Galau 47520 Le Passage",
    "sg:city":"Le Passage",
    "sg:classifiers":[
        {
            "category":"Professional",
            "subcategory":"Accounting & Tax Preparation",
            "type":"Services"
        }
    ],
    "sg:phone":"+33 5 53 77 39 00",
    "sg:postcode":"47520",
    "sg:province":"Aquitaine",
    "sg:tags":[
        "mixed",
        "feed"
    ],
    "wof:name":"Ferso Bio Sa",
    "wof:placetype":"venue"
},
  "geometry": {"coordinates":[0.605895,44.20142],"type":"Point"}
}