{
  "type": "Feature",
  "properties": {
    "addr:full":"1/9, Rue Antoine de St Exupery, 67120 Molsheim Molsheim Alsace 67120",
    "addr:housenumber":"1 / 9",
    "addr:postcode":"67120;67120",
    "addr:street":"Rue Antoine De St",
    "iso:country":"FR",
    "sg:address":"1/9, Rue Antoine de St Exupery, 67120 Molsheim",
    "sg:city":"Molsheim",
    "sg:orig_category":"Unclassifiable Establishments",
    "sg:phone":"+33 3 88 38 92 00",
    "sg:postcode":"67120",
    "sg:province":"Alsace",
    "wof:name":"Messier Bugatti",
    "wof:placetype":"venue"
},
  "geometry": {"coordinates":[7.503031,48.531963],"type":"Point"}
}