{
  "type": "Feature",
  "properties": {
    "addr:full":"Les Combes Salbris Centre 41300",
    "addr:postcode":"41300",
    "addr:street":"Combes",
    "iso:country":"FR",
    "sg:address":"Les Combes",
    "sg:city":"Salbris",
    "sg:classifiers":[
        {
            "category":"Professional",
            "subcategory":"Engineering",
            "type":"Services"
        }
    ],
    "sg:phone":"+33 2 54 97 19 22",
    "sg:postcode":"41300",
    "sg:province":"Centre",
    "sg:tags":[
        "machine",
        "-",
        "mechanical"
    ],
    "wof:name":"Les Plastiques Du Morin",
    "wof:placetype":"venue"
},
  "geometry": {"coordinates":[1.993075,47.278728],"type":"Point"}
}