{
  "type": "Feature",
  "properties": {
    "addr:full":"Ld Cremerieux 42600 Savigneux Rhone-Alpes 42600",
    "addr:postcode":"42600;42600",
    "addr:street":"Ld",
    "iso:country":"FR",
    "sg:address":"Ld Cremerieux 42600 Savigneux",
    "sg:classifiers":[
        {
            "category":"Home & Garden",
            "subcategory":"Furniture",
            "type":"Retail Goods"
        }
    ],
    "sg:phone":"+33 4 77 58 18 44",
    "sg:postcode":"42600",
    "sg:province":"Rhone-Alpes",
    "sg:tags":[
        "household",
        "wood"
    ],
    "wof:name":"Gg Creation Sa",
    "wof:placetype":"venue"
},
  "geometry": {"coordinates":[3.996271,45.571075],"type":"Point"}
}