{
  "type": "Feature",
  "properties": {
    "addr:full":"Avenue De Verdun 30133 Les Angles Languedoc-Roussillon 30133",
    "addr:postcode":"30133 les angles;30133",
    "addr:street":"Avenue De Verdun",
    "iso:country":"FR",
    "sg:address":"Avenue De Verdun 30133 Les Angles",
    "sg:classifiers":[
        {
            "category":"Manufacturing",
            "subcategory":"Building Materials",
            "type":"Manufacturing & Wholesale Goods"
        }
    ],
    "sg:phone":"+33 4 90 15 15 00",
    "sg:postcode":"30133",
    "sg:province":"Languedoc-Roussillon",
    "sg:tags":[
        "glass",
        "ceramic"
    ],
    "wof:name":"Ste Exploit Ateliers Des Mousselieres",
    "wof:placetype":"venue"
},
  "geometry": {"coordinates":[4.77075,43.958916],"type":"Point"}
}