{
  "type": "Feature",
  "properties": {
    "addr:full":"Zac De L'Anjoly Voie Angleterre Miniparc B 13127 Vitrolles Anglet Aquitaine 64600",
    "addr:postcode":"13127;64600",
    "addr:street":"Zac De L'Anjoly Voie Angleterre",
    "iso:country":"FR",
    "sg:address":"Zac De L'Anjoly Voie Angleterre Miniparc B 13127 Vitrolles",
    "sg:city":"Anglet",
    "sg:classifiers":[
        {
            "category":"Manufacturing",
            "subcategory":"Tools & Machinery",
            "type":"Manufacturing & Wholesale Goods"
        }
    ],
    "sg:phone":"+33 4 42 75 36 66",
    "sg:postcode":"64600",
    "sg:province":"Aquitaine",
    "sg:tags":[
        "equipment",
        "measurement",
        "-",
        "precision",
        "instrument"
    ],
    "wof:name":"Manufacture Francaise D'appareils Electroniques De Mesmanumesure",
    "wof:placetype":"venue"
},
  "geometry": {"coordinates":[5.260901,43.426197],"type":"Point"}
}