{
  "type": "Feature",
  "properties": {
    "iso:country":"FR",
    "sg:address":"12 Rue Jules Vernes BP 19 Z.A. Du Caillou 69630 Chaponost",
    "sg:classifiers":[
        {
            "category":"Shopping",
            "type":"Retail Goods"
        }
    ],
    "sg:phone":"+33 4 78 56 30 32",
    "sg:province":"Rhone-Alpes",
    "sg:tags":[
        "metallurgy",
        "finished",
        "-",
        "metalworking",
        "metallic"
    ],
    "wof:name":"Sodime Sa",
    "wof:placetype":"venue"
},
  "geometry": {"coordinates":[4.74319,45.710232],"type":"Point"}
}