{
  "type": "Feature",
  "properties": {
    "addr:full":"35, Bd Georges Cl\u00e9menceaux, 92400 Courbevoie Ile de France",
    "addr:housenumber":"35",
    "addr:postcode":"92400",
    "addr:street":"Bd Georges Cle\u0301Menceaux",
    "iso:country":"FR",
    "sg:address":"35, Bd Georges Cl\u00e9menceaux, 92400 Courbevoie",
    "sg:orig_category":"Non-Classified Establishments",
    "sg:phone":"+33 1 46 67 98 98",
    "sg:province":"Ile de France",
    "wof:name":"It Cal S.a.",
    "wof:placetype":"venue"
},
  "geometry": {"coordinates":[2.270927,48.902874],"type":"Point"}
}