{
  "type": "Feature",
  "properties": {
    "iso:country":"FR",
    "sg:address":"78/80, Av. Henri Lef\u00e9vre, 72100 Le Mans",
    "sg:orig_category":"Non-Classified Establishments",
    "sg:phone":"+33 2 43 84 33 31",
    "sg:postcode":"72100",
    "sg:province":"Pays de Loire",
    "wof:name":"Aff\u00fbtage 72",
    "wof:placetype":"venue"
},
  "geometry": {"coordinates":[0.193888,47.990849],"type":"Point"}
}