{
  "type": "Feature",
  "properties": {
    "iso:country":"FR",
    "sg:address":"B.P. 326, 37303 Jou\u00e9 l\u00e8s Tours C\u00e9dex^^18, Rue Prony, 37300 Jou\u00e9 l\u00e8s Tours",
    "sg:city":"Jou\u00e9-l\u00e8s-Tours",
    "sg:orig_category":"Non-Classified Establishments",
    "sg:phone":"+33 2 47 53 93 71",
    "sg:postcode":"37300",
    "sg:province":"Centre",
    "wof:name":"Petit S.a.",
    "wof:placetype":"venue"
},
  "geometry": {"coordinates":[0.662555,47.350945],"type":"Point"}
}