{
  "type": "Feature",
  "properties": {
    "iso:country":"FR",
    "sg:address":"44, Av Roger Salengro, 17440 Aytr\u00e9",
    "sg:orig_category":"Non-Classified Establishments",
    "sg:phone":"+33 5 46 44 27 10",
    "sg:province":"Poitou-Charentes",
    "wof:name":"S.p.g.o. S.a. - Soci\u00e9t\u00e9 Parisienne Du Groupe De L'ouest",
    "wof:placetype":"venue"
},
  "geometry": {"coordinates":[-1.134331,46.140076],"type":"Point"}
}