{
  "type": "Feature",
  "properties": {
    "iso:country":"FR",
    "sg:address":"12-14 place d'Armes; Haguenau; 67501",
    "sg:city":"Haguenau",
    "sg:classifiers":[
        {
            "category":"Banks & Credit Unions",
            "subcategory":"Bank",
            "type":"Services"
        }
    ],
    "sg:phone":"+33 3 88 90 50 50",
    "sg:postcode":"67500",
    "sg:province":"Alsace",
    "wof:name":"Cr\u00e9dit Industriel D'alsace, Et De Lorraine Sa",
    "wof:placetype":"venue"
},
  "geometry": {"coordinates":[7.788637,48.814079],"type":"Point"}
}