{
  "type": "Feature",
  "properties": {
    "addr:full":"Le Pont de Pierres 02140 Fontaine l\u00e8s Vervins Picardie",
    "addr:postcode":"02140",
    "addr:street":"Le Pont De Pierres",
    "iso:country":"FR",
    "sg:address":"Le Pont de Pierres 02140 Fontaine l\u00e8s Vervins",
    "sg:orig_category":"Unclassifiable Establishments",
    "sg:phone":"+33 3 23 91 34 34",
    "sg:province":"Picardie",
    "wof:name":"Trouw France S.a.",
    "wof:placetype":"venue"
},
  "geometry": {"coordinates":[3.91817,49.828499],"type":"Point"}
}