{
  "type": "Feature",
  "properties": {
    "addr:full":"R Bernard Palissy BP 414 86104 Ch\u00e2tellerault Picardie",
    "addr:housenumber":"414",
    "addr:postcode":"86104",
    "iso:country":"FR",
    "sg:address":"R Bernard Palissy BP 414 86104 Ch\u00e2tellerault",
    "sg:classifiers":[
        {
            "category":"Wholesale",
            "subcategory":"Medical Equipment & Supplies",
            "type":"Manufacturing & Wholesale Goods"
        }
    ],
    "sg:phone":"+33 5 49 21 01 33",
    "sg:province":"Picardie",
    "sg:tags":[
        "instrument",
        "health",
        "-",
        "precision"
    ],
    "wof:name":"Chatel Dent Sarl",
    "wof:placetype":"venue"
},
  "geometry": {"coordinates":[0.534755,46.830368],"type":"Point"}
}