{
  "type": "Feature",
  "properties": {
    "addr:full":"ZA de l'Escaut Reims Champagne 51100",
    "addr:postcode":"51100",
    "addr:street":"Za De L'Escaut;Champagne",
    "iso:country":"FR",
    "sg:address":"ZA de l'Escaut",
    "sg:city":"Reims",
    "sg:orig_category":"Non-Classified Establishments",
    "sg:phone":"+33 3 26 07 18 34",
    "sg:postcode":"51100",
    "sg:province":"Champagne",
    "wof:name":"Slivinsky S.a.r.l.",
    "wof:placetype":"venue"
},
  "geometry": {"coordinates":[4.067592,49.24794],"type":"Point"}
}