{
  "type": "Feature",
  "properties": {
    "addr:full":"44, Rue du Vieux Colombier, 51100 Reims Champagne",
    "addr:housenumber":"44",
    "addr:postcode":"51100",
    "addr:street":"Rue Du Vieux Colombier",
    "iso:country":"FR",
    "sg:address":"44, Rue du Vieux Colombier, 51100 Reims",
    "sg:orig_category":"Unclassifiable Establishments",
    "sg:phone":"+33 3 26 84 82 08",
    "sg:province":"Champagne",
    "wof:name":"Entreprise Renaudin S.a.r.l.",
    "wof:placetype":"venue"
},
  "geometry": {"coordinates":[4.022739,49.274002],"type":"Point"}
}