{
  "type": "Feature",
  "properties": {
    "addr:full":"8, All\u00e9e de la Javeleuse, 54425 Pulnoy Lorraine",
    "addr:housenumber":"8",
    "addr:postcode":"54425",
    "addr:street":"Alle\u0301E De La Javeleuse",
    "iso:country":"FR",
    "sg:address":"8, All\u00e9e de la Javeleuse, 54425 Pulnoy",
    "sg:orig_category":"Unclassifiable Establishments",
    "sg:phone":"+33 3 83 21 69 47",
    "sg:province":"Lorraine",
    "wof:name":"Heurequal 54 S.a.r.l.",
    "wof:placetype":"venue"
},
  "geometry": {"coordinates":[6.262689,48.709789],"type":"Point"}
}