{
  "type": "Feature",
  "properties": {
    "iso:country":"FR",
    "sg:address":"B.P. 51, 91371 Verri\u00e8res le Buisson C\u00e9dex^^7, Rue des Gardes, 91370 Verri\u00e8res le Buisson",
    "sg:orig_category":"Non-Classified Establishments",
    "sg:phone":"+33 1 69 53 64 53",
    "sg:province":"Ile de France",
    "wof:name":"Kathrein France S.a.r.l.",
    "wof:placetype":"venue"
},
  "geometry": {"coordinates":[2.266935,48.746086],"type":"Point"}
}