{
  "type": "Feature",
  "properties": {
    "iso:country":"FR",
    "sg:address":"9 Rue De Chaumont 75019 Paris",
    "sg:classifiers":[
        {
            "category":"Manufacturing",
            "subcategory":"Printing",
            "type":"Manufacturing & Wholesale Goods"
        }
    ],
    "sg:phone":"+33 1 42 06 55 53",
    "sg:province":"Ile de France",
    "sg:tags":[
        "publishing"
    ],
    "wof:name":"Danon Marcho",
    "wof:placetype":"venue"
},
  "geometry": {"coordinates":[2.371995,48.881153],"type":"Point"}
}