{
  "type": "Feature",
  "properties": {
    "addr:full":"1, All\u00e9e des Atlantes - Parc des Propyl\u00e9es, 28000 Chartres Chartres Centre 28000",
    "addr:housenumber":"1",
    "addr:postcode":"28000;28000",
    "addr:street":"Alle\u0301E Des Atlantes Parc Des Propyle\u0301Es",
    "iso:country":"FR",
    "sg:address":"1, All\u00e9e des Atlantes - Parc des Propyl\u00e9es, 28000 Chartres",
    "sg:city":"Chartres",
    "sg:orig_category":"Unclassifiable Establishments",
    "sg:phone":"+33 2 37 91 24 34",
    "sg:postcode":"28000",
    "sg:province":"Centre",
    "wof:name":"Eurotec & Synergie S.a.r.l.",
    "wof:placetype":"venue"
},
  "geometry": {"coordinates":[1.52777,48.454639],"type":"Point"}
}