{
  "type": "Feature",
  "properties": {
    "addr:full":"B.P. 70, 13315 Marseille C\u00e9dex 15^^16, Av. Saint Antoine, 13015 Marseille Poitou-Charentes",
    "addr:housenumber":"15 ^ ^ 16",
    "addr:postcode":"13315;13015",
    "addr:street":"B.P. 70;Ce\u0301Dex;Av. Saint Antoine",
    "iso:country":"FR",
    "sg:address":"B.P. 70, 13315 Marseille C\u00e9dex 15^^16, Av. Saint Antoine, 13015 Marseille",
    "sg:orig_category":"Non-Classified Establishments",
    "sg:phone":"+33 4 91 03 97 00",
    "sg:province":"Poitou-Charentes",
    "wof:name":"Lecourtier Drapeaux S.a.r.l.",
    "wof:placetype":"venue"
},
  "geometry": {"coordinates":[5.37278,43.344948],"type":"Point"}
}