{
  "type": "Feature",
  "properties": {
    "addr:full":"B.P. 1529, 87020 Limoges C\u00e9dex 9^^22, Rue de Dion Bouton - ZI Nord, 87280 Limoges Limousin 87280",
    "addr:housenumber":"9 ^ ^ 22",
    "addr:postcode":"87020;87280;87280",
    "addr:street":"B.P. 1529;Ce\u0301Dex;Rue De Dion Bouton Zi Nord",
    "iso:country":"FR",
    "sg:address":"B.P. 1529, 87020 Limoges C\u00e9dex 9^^22, Rue de Dion Bouton - ZI Nord, 87280 Limoges",
    "sg:orig_category":"Non-Classified Establishments",
    "sg:phone":"+33 5 55 38 46 30",
    "sg:postcode":"87280",
    "sg:province":"Limousin",
    "wof:name":"C.i.c Air S.a. - Chaudronnerie Industrielle Conditionnement De L'a",
    "wof:placetype":"venue"
},
  "geometry": {"coordinates":[1.299435,45.914837],"type":"Point"}
}