{
  "type": "Feature",
  "properties": {
    "addr:full":"Zi Gros Jacques Croix Au B 80880 St Quentin La Motte Picardie 80880",
    "addr:housenumber":"80880",
    "addr:postcode":"80880",
    "addr:street":"St Quentin",
    "iso:country":"FR",
    "sg:address":"Zi Gros Jacques Croix Au B 80880 St Quentin La Motte",
    "sg:classifiers":[
        {
            "category":"Shopping",
            "type":"Retail Goods"
        }
    ],
    "sg:phone":"+33 3 22 60 69 01",
    "sg:postcode":"80880",
    "sg:province":"Picardie",
    "sg:tags":[
        "metallurgy",
        "finished",
        "-",
        "metalworking",
        "metallic"
    ],
    "wof:name":"Capelle Injection",
    "wof:placetype":"venue"
},
  "geometry": {"coordinates":[1.454305,50.072044],"type":"Point"}
}