{
  "type": "Feature",
  "properties": {
    "addr:full":"Rte du Pont 7 - Quai du Rhin Le Havre Haute Normandie 76600",
    "addr:housenumber":"7",
    "addr:postcode":"76600",
    "addr:street":"Rte Du Pont;Quai Du Rhin",
    "iso:country":"FR",
    "sg:address":"Rte du Pont 7 - Quai du Rhin",
    "sg:city":"Le Havre",
    "sg:orig_category":"Non-Classified Establishments",
    "sg:phone":"+33 2 35 53 39 00",
    "sg:postcode":"76600",
    "sg:province":"Haute Normandie",
    "wof:name":"Danzas Chemicals S.a.r.l.",
    "wof:placetype":"venue"
},
  "geometry": {"coordinates":[0.18002,49.493755],"type":"Point"}
}