{
  "type": "Feature",
  "properties": {
    "addr:full":"22 rue de Belfort 69004 Lyon Rhone-Alpes 69004",
    "addr:housenumber":"22",
    "addr:postcode":"69004;69004",
    "addr:street":"Rue De Belfort",
    "iso:country":"FR",
    "sg:address":"22 rue de Belfort 69004 Lyon",
    "sg:classifiers":[
        {
            "category":"Utilities",
            "subcategory":"Cable",
            "type":"Services"
        }
    ],
    "sg:phone":"+33 4 72 07 91 12",
    "sg:postcode":"69004",
    "sg:province":"Rhone-Alpes",
    "sg:tags":[
        "wiring",
        "tester"
    ],
    "wof:name":"Transfer Equipment International Eurl",
    "wof:placetype":"venue"
},
  "geometry": {"coordinates":[4.8345,45.779449],"type":"Point"}
}