{
  "type": "Feature",
  "properties": {
    "addr:full":"3 Fabert 78500 Sartrouville Ile de France 78500",
    "addr:housenumber":"3",
    "addr:postcode":"78500;ile;78500",
    "addr:street":"Fabert;France",
    "iso:country":"FR",
    "sg:address":"3",
    "sg:city":"Fabert 78500 Sartrouville",
    "sg:classifiers":[
        {
            "category":"Professional",
            "subcategory":"Engineering",
            "type":"Services"
        }
    ],
    "sg:phone":"+33 1 30 86 55 55",
    "sg:postcode":"78500",
    "sg:province":"Ile de France",
    "sg:tags":[
        "machine",
        "-",
        "mechanical"
    ],
    "wof:name":"Sapem",
    "wof:placetype":"venue"
},
  "geometry": {"coordinates":[2.174681,48.934555],"type":"Point"}
}