{
  "type": "Feature",
  "properties": {
    "addr:full":"11, Rue Eug\u00e8ne Pottier, 93700 Drancy Ile de France",
    "addr:housenumber":"11",
    "addr:postcode":"93700;ile",
    "addr:street":"Rue Euge\u0300Ne Pottier",
    "iso:country":"FR",
    "sg:address":"11, Rue Eug\u00e8ne Pottier, 93700 Drancy",
    "sg:orig_category":"Non-Classified Establishments",
    "sg:phone":"+33 1 48 96 92 92",
    "sg:province":"Ile de France",
    "wof:name":"Gilcam S.a.",
    "wof:placetype":"venue"
},
  "geometry": {"coordinates":[2.43598,48.929222],"type":"Point"}
}