{
  "type": "Feature",
  "properties": {
    "iso:country":"FR",
    "sg:address":"71 B, Rue des Hautes P\u00e2tures, 92000 Nanterre",
    "sg:orig_category":"Non-Classified Establishments",
    "sg:phone":"+33 1 41 19 46 66",
    "sg:postcode":"92000",
    "sg:province":"Ile de France",
    "wof:name":"Advantech France S.a.",
    "wof:placetype":"venue"
},
  "geometry": {"coordinates":[2.219911,48.917793],"type":"Point"}
}