{
  "type": "Feature",
  "properties": {
    "addr:full":"3 Imp Lavoisier 26100 Romans Sur Is\u00e8re Rhone-Alpes 26100",
    "addr:housenumber":"3",
    "addr:postcode":"26100;26100",
    "addr:street":"Imp Lavoisier",
    "iso:country":"FR",
    "sg:address":"3 Imp Lavoisier 26100 Romans Sur Is\u00e8re",
    "sg:classifiers":[
        {
            "category":"Bakery",
            "type":"Food & Drink"
        }
    ],
    "sg:phone":"+33 4 75 70 74 20",
    "sg:postcode":"26100",
    "sg:province":"Rhone-Alpes",
    "sg:tags":[
        "cake",
        "product",
        "related",
        "bread"
    ],
    "wof:name":"Panavi Sa",
    "wof:placetype":"venue"
},
  "geometry": {"coordinates":[5.093047,45.052876],"type":"Point"}
}