{
  "type": "Feature",
  "properties": {
    "addr:full":"B.P. 724, 49007 Angers C\u00e9dex 01^^32, Rue Ch\u00e8vre, 49000 Angers Pays de Loire",
    "addr:housenumber":"b.p. 724;01 ^ ^ 32",
    "addr:postcode":"49007;49000",
    "addr:street":"Ce\u0301Dex;Rue Che\u0300Vre",
    "iso:country":"FR",
    "sg:address":"B.P. 724, 49007 Angers C\u00e9dex 01^^32, Rue Ch\u00e8vre, 49000 Angers",
    "sg:orig_category":"Non-Classified Establishments",
    "sg:phone":"+33 2 41 88 07 54",
    "sg:province":"Pays de Loire",
    "wof:name":"M.q.b. S.a. - Missenard Quint B.",
    "wof:placetype":"venue"
},
  "geometry": {"coordinates":[-0.56339,47.46315],"type":"Point"}
}