{
  "type": "Feature",
  "properties": {
    "addr:full":"30, Rue Georges Cl\u00e9menceau, 64320 Bizanos Bizanos Aquitaine 64320",
    "addr:housenumber":"30",
    "addr:postcode":"64320;64320",
    "addr:street":"Rue Georges Cle\u0301Menceau",
    "iso:country":"FR",
    "sg:address":"30, Rue Georges Cl\u00e9menceau, 64320 Bizanos",
    "sg:city":"Bizanos",
    "sg:orig_category":"Unclassifiable Establishments",
    "sg:phone":"+33 5 59 27 23 00",
    "sg:postcode":"64320",
    "sg:province":"Aquitaine",
    "wof:name":"S.o.s. S\u00e9curit\u00e9 S.a.r.l.",
    "wof:placetype":"venue"
},
  "geometry": {"coordinates":[-0.355675,43.289772],"type":"Point"}
}