{
  "type": "Feature",
  "properties": {
    "addr:full":"Place du Temple - ZI les Bosses Etoile sur Rh\u00f4ne Rhone-Alpes 26800",
    "addr:postcode":"26800",
    "addr:street":"Place Du Temple Zi Les;Etoile",
    "iso:country":"FR",
    "sg:address":"Place du Temple - ZI les Bosses",
    "sg:city":"Etoile sur Rh\u00f4ne",
    "sg:orig_category":"Unclassifiable Establishments",
    "sg:phone":"+33 4 75 60 77 30",
    "sg:postcode":"26800",
    "sg:province":"Rhone-Alpes",
    "wof:name":"Axxair S.a.",
    "wof:placetype":"venue"
},
  "geometry": {"coordinates":[4.907647,44.794395],"type":"Point"}
}