{
  "type": "Feature",
  "properties": {
    "iso:country":"FR",
    "sg:address":"Lieu-Dit Mestre Marty 47310 Estillac",
    "sg:city":"Estillac",
    "sg:classifiers":[
        {
            "category":"Manufacturing",
            "subcategory":"Printing",
            "type":"Manufacturing & Wholesale Goods"
        }
    ],
    "sg:phone":"+33 5 53 69 20 20",
    "sg:postcode":"47310",
    "sg:province":"Aquitaine",
    "sg:tags":[
        "publishing"
    ],
    "wof:name":"Roto Garonne",
    "wof:placetype":"venue"
},
  "geometry": {"coordinates":[0.518632,44.076218],"type":"Point"}
}