{
  "type": "Feature",
  "properties": {
    "iso:country":"FR",
    "sg:address":"Chemilly 70360 Scey sur Sa\u00f4ne et Saint Albin",
    "sg:orig_category":"Unclassifiable Establishments",
    "sg:phone":"+33 3 84 91 50 93",
    "sg:province":"Franche Comt\u00e9",
    "wof:name":"De Trevillers Emballages S.a.",
    "wof:placetype":"venue"
},
  "geometry": {"coordinates":[5.97174,47.664021],"type":"Point"}
}