{
  "type": "Feature",
  "properties": {
    "addr:full":"23, Chemin des R\u00e9niers, 92390 Villeneuve la Garenne Ile de France",
    "addr:housenumber":"23",
    "addr:postcode":"92390",
    "addr:street":"Chemin Des Re\u0301Niers;Ile",
    "iso:country":"FR",
    "sg:address":"23, Chemin des R\u00e9niers, 92390 Villeneuve la Garenne",
    "sg:orig_category":"Non-Classified Establishments",
    "sg:phone":"+33 1 46 13 93 93",
    "sg:province":"Ile de France",
    "wof:name":"Frantz Electrolyse S.a.",
    "wof:placetype":"venue"
},
  "geometry": {"coordinates":[2.32504,48.930634],"type":"Point"}
}