{
  "type": "Feature",
  "properties": {
    "addr:full":"17, Rue de la Brot, 21000 Dijon Dijon Bourgogne 21000",
    "addr:housenumber":"17",
    "addr:postcode":"21000;21000",
    "addr:street":"Rue De La Brot",
    "iso:country":"FR",
    "sg:address":"17, Rue de la Brot, 21000 Dijon",
    "sg:city":"Dijon",
    "sg:orig_category":"Unclassifiable Establishments",
    "sg:phone":"+33 3 80 78 40 40",
    "sg:postcode":"21000",
    "sg:province":"Bourgogne",
    "wof:name":"Pacotte Et Mignotte S.a.",
    "wof:placetype":"venue"
},
  "geometry": {"coordinates":[5.072039,47.346889],"type":"Point"}
}