{
  "type": "Feature",
  "properties": {
    "addr:full":"ZA 2 Quint Fons\u00e9grives Midi Pyr\u00e9n\u00e9es 31130",
    "addr:housenumber":"2",
    "addr:postcode":"31130",
    "addr:street":"Za;Fonse\u0301Grives",
    "iso:country":"FR",
    "sg:address":"ZA 2",
    "sg:city":"Quint Fons\u00e9grives",
    "sg:orig_category":"Non-Classified Establishments",
    "sg:phone":"+33 5 62 57 17 17",
    "sg:postcode":"31130",
    "sg:province":"Midi Pyr\u00e9n\u00e9es",
    "wof:name":"Etablissements Albert Llau S.a.r.l.",
    "wof:placetype":"venue"
},
  "geometry": {"coordinates":[1.550898,43.576588],"type":"Point"}
}