{
  "type": "Feature",
  "properties": {
    "iso:country":"FR",
    "sg:address":"42, Rue du Docteur Deutsch, 67250 Soultz sous For\u00eats",
    "sg:city":"Aschbach",
    "sg:orig_category":"Unclassifiable Establishments",
    "sg:phone":"+33 3 88 80 40 91",
    "sg:postcode":"67250",
    "sg:province":"Alsace",
    "wof:name":"Funfrock S.a.",
    "wof:placetype":"venue"
},
  "geometry": {"coordinates":[7.884652,48.938183],"type":"Point"}
}