{
  "type": "Feature",
  "properties": {
    "iso:country":"FR",
    "sg:address":"7, Rue du Sal\u00e9, 31000 Toulouse",
    "sg:orig_category":"Non-Classified Establishments",
    "sg:phone":"+33 5 61 21 00 41",
    "sg:province":"Midi Pyr\u00e9n\u00e9es",
    "wof:name":"Inconito S.a.r.l.",
    "wof:placetype":"venue"
},
  "geometry": {"coordinates":[1.4463,43.606701],"type":"Point"}
}