{
  "type": "Feature",
  "properties": {
    "iso:country":"FR",
    "sg:address":"Les Plaines",
    "sg:city":"Saint Martin en Haut",
    "sg:orig_category":"Unclassifiable Establishments",
    "sg:phone":"+33 4 78 48 63 07",
    "sg:postcode":"69850",
    "sg:province":"Rhone-Alpes",
    "wof:name":"Tarres E.u.r.l.",
    "wof:placetype":"venue"
},
  "geometry": {"coordinates":[4.56118,45.65181],"type":"Point"}
}