{
  "type": "Feature",
  "properties": {
    "addr:full":"10, Rue EA Beau de Rochas - ZI de Charmontet, 25200 Montb\u00e9liard Franche Comt\u00e9",
    "addr:housenumber":"10",
    "addr:postcode":"25200",
    "addr:street":"Rue Ea Beau De Rochas Zi De Charmontet;Franche Comte\u0301",
    "iso:country":"FR",
    "sg:address":"10, Rue EA Beau de Rochas - ZI de Charmontet, 25200 Montb\u00e9liard",
    "sg:orig_category":"Non-Classified Establishments",
    "sg:phone":"+33 3 81 32 09 44",
    "sg:province":"Franche Comt\u00e9",
    "wof:name":"Setal S.a.r.l. - Soci\u00e9t\u00e9 Europ\u00e9enne De Transformation D'aluminium",
    "wof:placetype":"venue"
},
  "geometry": {"coordinates":[6.80297,47.508614],"type":"Point"}
}