{
  "type": "Feature",
  "properties": {
    "iso:country":"FR",
    "sg:address":"Rue de la Constituante - ZI du Coin n\u00b02",
    "sg:city":"Saint Chamond",
    "sg:orig_category":"Unclassifiable Establishments",
    "sg:phone":"+33 4 77 31 57 94",
    "sg:postcode":"42400",
    "sg:province":"Rhone-Alpes",
    "wof:name":"S.t.u.v.g. S.n.c. - Soci\u00e9t\u00e9 De Transports Urbains De La Vall\u00e9e Du Gie",
    "wof:placetype":"venue"
},
  "geometry": {"coordinates":[4.512304,45.473969],"type":"Point"}
}