{
  "type": "Feature",
  "properties": {
    "addr:full":"31 Av George V 75008 Paris Ile de France 75008",
    "addr:postcode":"75008;75008",
    "addr:street":"31 Av George V",
    "iso:country":"FR",
    "sg:address":"31 Av George V 75008 Paris",
    "sg:classifiers":[
        {
            "category":"Travel",
            "subcategory":"Hotels & Motels",
            "type":"Entertainment"
        }
    ],
    "sg:phone":"+33 1 49 52 70 00",
    "sg:postcode":"75008",
    "sg:province":"Ile de France",
    "sg:tags":[
        "hotels",
        "business",
        "restaurant"
    ],
    "wof:name":"Hotel George V",
    "wof:placetype":"venue"
},
  "geometry": {"coordinates":[2.300692,48.86882],"type":"Point"}
}