{
  "type": "Feature",
  "properties": {
    "iso:country":"FR",
    "sg:address":"4, Rue F\u00e9lix M\u00e9zard, 63000 Clermont Ferrand",
    "sg:city":"Clermont-Ferrand",
    "sg:orig_category":"Unclassifiable Establishments",
    "sg:phone":"+33 4 73 24 22 67",
    "sg:postcode":"63000",
    "sg:province":"Auvergne",
    "wof:name":"Soci\u00e9t\u00e9 Nouvelle Des Etablissements Hardot S.a.",
    "wof:placetype":"venue"
},
  "geometry": {"coordinates":[3.08183,45.777618],"type":"Point"}
}