{
  "type": "Feature",
  "properties": {
    "iso:country":"FR",
    "sg:address":"112, Av. Georges Cl\u00e9menceau, 92014 Nanterre C\u00e9dex",
    "sg:orig_category":"Non-Classified Establishments",
    "sg:phone":"+33 1 55 17 31 80",
    "sg:province":"Languedoc-Roussillon",
    "wof:name":"Banco Pinto & Sotto Mayor",
    "wof:placetype":"venue"
},
  "geometry": {"coordinates":[2.20813,48.886246],"type":"Point"}
}