{
  "type": "Feature",
  "properties": {
    "addr:full":"Chem Du Kiosque Rn8 83190 Ollioules Nord Pas-de-Calais",
    "addr:postcode":"83190",
    "addr:street":"Chem;Rn8",
    "iso:country":"FR",
    "sg:address":"Chem Du Kiosque Rn8 83190 Ollioules",
    "sg:classifiers":[
        {
            "category":"Utilities",
            "subcategory":"Electric",
            "type":"Services"
        }
    ],
    "sg:phone":"+33 4 94 63 00 63",
    "sg:province":"Nord Pas-de-Calais",
    "sg:tags":[
        "electricity",
        "raw",
        "energy",
        "material"
    ],
    "wof:name":"Are Snc",
    "wof:placetype":"venue"
},
  "geometry": {"coordinates":[5.84722,43.137573],"type":"Point"}
}