{
  "type": "Feature",
  "properties": {
    "iso:country":"FR",
    "sg:address":"Ch Du Bois De Rocques 14100 Rocques",
    "sg:city":"Rocques",
    "sg:classifiers":[
        {
            "category":"Manufacturing",
            "subcategory":"Metals",
            "type":"Manufacturing & Wholesale Goods"
        }
    ],
    "sg:phone":"+33 2 31 62 42 93",
    "sg:postcode":"14100",
    "sg:province":"Basse Normandie",
    "sg:tags":[
        "metallurgy",
        "steel",
        "metalworking"
    ],
    "wof:name":"Erpi Sa",
    "wof:placetype":"venue"
},
  "geometry": {"coordinates":[0.24252,49.159752],"type":"Point"}
}