{
  "type": "Feature",
  "properties": {
    "iso:country":"FR",
    "sg:address":"158, Av. Francis de Pressense, 69200 V\u00e9nissieux",
    "sg:orig_category":"Unclassifiable Establishments",
    "sg:phone":"+33 4 78 77 93 36",
    "sg:province":"Rhone-Alpes",
    "wof:name":"Septam Protection S.a.",
    "wof:placetype":"venue"
},
  "geometry": {"coordinates":[4.86731,45.720879],"type":"Point"}
}