{
  "type": "Feature",
  "properties": {
    "iso:country":"FR",
    "sg:address":"48 Place De La Republique",
    "sg:city":"Le Mans",
    "sg:classifiers":[
        {
            "category":"Banks & Credit Unions",
            "subcategory":"Financial Services",
            "type":"Services"
        }
    ],
    "sg:phone":"+33 2 43 39 24 30",
    "sg:postcode":"72000",
    "sg:province":"Pays de Loire",
    "sg:tags":[
        "banking",
        "finance",
        "insurance"
    ],
    "wof:name":"Caisse Regionale De Credit Agricole Mutuel De L'anjou Et Du",
    "wof:placetype":"venue"
},
  "geometry": {"coordinates":[0.197543,48.004223],"type":"Point"}
}