{
  "type": "Feature",
  "properties": {
    "addr:full":"3, Rue Daniel Schoen, 68200 Mulhouse Mulhouse Alsace 68200",
    "addr:housenumber":"3",
    "addr:postcode":"68200;68200",
    "addr:street":"Rue Daniel Schoen",
    "iso:country":"FR",
    "sg:address":"3, Rue Daniel Schoen, 68200 Mulhouse",
    "sg:city":"Mulhouse",
    "sg:orig_category":"Unclassifiable Establishments",
    "sg:phone":"+33 3 89 42 12 28",
    "sg:postcode":"68200",
    "sg:province":"Alsace",
    "wof:name":"Kaiser Arthur Entreprise De Peinture S.a.r.l.",
    "wof:placetype":"venue"
},
  "geometry": {"coordinates":[7.28659,47.73159],"type":"Point"}
}