{
  "type": "Feature",
  "properties": {
    "addr:full":"2 cours Monseigneur Romiro; BP 135; EVRY; 91004 CEDEX Midi Pyr\u00e9n\u00e9es",
    "addr:housenumber":"2;135",
    "addr:postcode":"91004 cedex midi",
    "addr:street":"Cours Monseigneur Romiro Bp",
    "iso:country":"FR",
    "sg:address":"2 cours Monseigneur Romiro; BP 135; EVRY; 91004 CEDEX",
    "sg:classifiers":[
        {
            "category":"Shopping",
            "subcategory":"Computers & Home Electronics",
            "type":"Retail Goods"
        }
    ],
    "sg:phone":"+33 1 60 79 91 91",
    "sg:province":"Midi Pyr\u00e9n\u00e9es",
    "sg:tags":[
        "chamber",
        "commerce"
    ],
    "wof:name":"Chambre De Commerce De L'essonne",
    "wof:placetype":"venue"
},
  "geometry": {"coordinates":[2.43072,48.626919],"type":"Point"}
}