{
  "type": "Feature",
  "properties": {
    "addr:full":"24 route de Pitoys 64600 Anglet Anglet Aquitaine 64600",
    "addr:housenumber":"24",
    "addr:postcode":"64600;64600",
    "addr:street":"Route De Pitoys",
    "iso:country":"FR",
    "sg:address":"24 route de Pitoys 64600 Anglet",
    "sg:city":"Anglet",
    "sg:classifiers":[
        {
            "category":"Food & Beverages",
            "subcategory":"Meat & Fish",
            "type":"Retail Goods"
        }
    ],
    "sg:phone":"+33 5 59 31 48 84",
    "sg:postcode":"64600",
    "sg:province":"Aquitaine",
    "sg:tags":[
        "sausage"
    ],
    "wof:name":"Le Helder Distribution S.a.r.l.",
    "wof:placetype":"venue"
},
  "geometry": {"coordinates":[-1.519669,43.463345],"type":"Point"}
}