{
  "type": "Feature",
  "properties": {
    "addr:full":"136 Rue De La Sous Prefecture 69400 Villefranche Sur Saone Rhone-Alpes",
    "addr:housenumber":"136",
    "addr:postcode":"69400",
    "addr:street":"Rue De La Sous Prefecture",
    "iso:country":"FR",
    "sg:address":"136 Rue De La Sous Prefecture 69400 Villefranche Sur Saone",
    "sg:classifiers":[
        {
            "category":"Banks & Credit Unions",
            "subcategory":"Investment Brokerage",
            "type":"Services"
        }
    ],
    "sg:phone":"+33 4 74 60 69 60",
    "sg:province":"Rhone-Alpes",
    "sg:tags":[
        "-",
        "transport",
        "related"
    ],
    "wof:name":"Comareg Sa",
    "wof:placetype":"venue"
},
  "geometry": {"coordinates":[4.716843,45.988991],"type":"Point"}
}