{
  "type": "Feature",
  "properties": {
    "iso:country":"FR",
    "sg:address":"B.P. 4, 62250 Marquise^^12, Rue des Anciens Hts Fourneaux, 62250 Marquise",
    "sg:orig_category":"Non-Classified Establishments",
    "sg:phone":"+33 3 21 99 52 00",
    "sg:province":"Nord Pas-de-Calais",
    "wof:name":"Lenglet Ren\u00e9 Constructions Industrielles S.a.",
    "wof:placetype":"venue"
},
  "geometry": {"coordinates":[1.6679,50.768139],"type":"Point"}
}