{
  "type": "Feature",
  "properties": {
    "addr:full":"4 Rue Lesdiguieres Grenoble Rhone-Alpes 38000",
    "addr:housenumber":"4",
    "addr:postcode":"38000",
    "addr:street":"Rue Lesdiguieres",
    "iso:country":"FR",
    "sg:address":"4 Rue Lesdiguieres",
    "sg:city":"Grenoble",
    "sg:classifiers":[
        {
            "category":"Banks & Credit Unions",
            "subcategory":"Financial Services",
            "type":"Services"
        }
    ],
    "sg:phone":"+33 4 76 44 79 79",
    "sg:postcode":"38000",
    "sg:province":"Rhone-Alpes",
    "sg:tags":[
        "banking",
        "finance",
        "insurance"
    ],
    "wof:name":"Euler Sfac Credit",
    "wof:placetype":"venue"
},
  "geometry": {"coordinates":[5.730763,45.18848],"type":"Point"}
}