{
  "type": "Feature",
  "properties": {
    "iso:country":"FR",
    "sg:address":"7 rue d'Asfeld; S. Malo; 35402",
    "sg:classifiers":[
        {
            "category":"Banks & Credit Unions",
            "subcategory":"Bank",
            "type":"Services"
        }
    ],
    "sg:phone":"+33 2 99 20 53 00",
    "sg:province":"Outre-Mer",
    "wof:name":"Banque De France",
    "wof:placetype":"venue"
},
  "geometry": {"coordinates":[-87.56555899999999,33.210548],"type":"Point"}
}