{
  "type": "Feature",
  "properties": {
    "addr:full":"6 Rue De La Mare Jeanne St Gemme 78810 Feucherolles Ile de France",
    "addr:housenumber":"6",
    "addr:postcode":"78810;ile",
    "addr:street":"Rue De La Mare Jeanne St",
    "iso:country":"FR",
    "sg:address":"6 Rue De La Mare Jeanne St Gemme 78810 Feucherolles",
    "sg:classifiers":[
        {
            "category":"Manufacturing",
            "subcategory":"Paper Products",
            "type":"Manufacturing & Wholesale Goods"
        }
    ],
    "sg:phone":"+33 1 30 54 42 21",
    "sg:province":"Ile de France",
    "sg:tags":[
        "finished",
        "cardboard",
        "-"
    ],
    "wof:name":"Labeletiq",
    "wof:placetype":"venue"
},
  "geometry": {"coordinates":[1.985133,48.88187],"type":"Point"}
}