{
  "type": "Feature",
  "properties": {
    "iso:country":"FR",
    "sg:address":"220 avenue des Aureats 26000 Valence",
    "sg:orig_category":"Section Wire",
    "sg:phone":"+33 4 75 57 60 00",
    "sg:province":"Rhone-Alpes",
    "wof:name":"Setila S.a.",
    "wof:placetype":"venue"
},
  "geometry": {"coordinates":[4.88462,44.889801],"type":"Point"}
}