{
  "type": "Feature",
  "properties": {
    "iso:country":"FR",
    "sg:address":"St Isidore Colline De Cremat P A L 06200 Nice",
    "sg:classifiers":[
        {
            "category":"Shopping",
            "subcategory":"Clothing, Apparel, & Fashions",
            "type":"Retail Goods"
        }
    ],
    "sg:phone":"+33 4 92 29 12 19",
    "sg:province":"Pays de Loire",
    "sg:tags":[
        "textile",
        "clothing",
        "clothes"
    ],
    "wof:name":"Fa\u00c7onnable",
    "wof:placetype":"venue"
},
  "geometry": {"coordinates":[7.215093,43.745003],"type":"Point"}
}