{
  "type": "Feature",
  "properties": {
    "addr:full":"Ctre Commerc Nations Vandoeuvre Les Nancy Lorraine 54500",
    "addr:postcode":"54500",
    "addr:street":"Lorraine",
    "iso:country":"FR",
    "sg:address":"Ctre Commerc Nations",
    "sg:city":"Vandoeuvre Les Nancy",
    "sg:classifiers":[
        {
            "category":"Banks & Credit Unions",
            "subcategory":"Financial Services",
            "type":"Services"
        }
    ],
    "sg:phone":"+33 3 83 56 47 22",
    "sg:postcode":"54500",
    "sg:province":"Lorraine",
    "sg:tags":[
        "banking",
        "finance",
        "insurance"
    ],
    "wof:name":"Caisse Regionale De Credit Agricole Mutuel De Lorraine (crcam De Lorraine)",
    "wof:placetype":"venue"
},
  "geometry": {"coordinates":[6.172675,48.659737],"type":"Point"}
}