{
  "type": "Feature",
  "properties": {
    "iso:country":"FR",
    "sg:address":"Route De Chamagne Zi 88130 Charmes",
    "sg:classifiers":[
        {
            "category":"Professional",
            "subcategory":"Engineering",
            "type":"Services"
        }
    ],
    "sg:phone":"+33 3 29 31 73 00",
    "sg:postcode":"88130",
    "sg:province":"Lorraine",
    "sg:tags":[
        "machine",
        "-",
        "mechanical"
    ],
    "wof:name":"Trane",
    "wof:placetype":"venue"
},
  "geometry": {"coordinates":[6.290925,48.372807],"type":"Point"}
}