{
  "type": "Feature",
  "properties": {
    "iso:country":"FR",
    "sg:address":"28, Rue Pierre Brossolette, 93160 Noisy le Grand",
    "sg:orig_category":"Unclassifiable Establishments",
    "sg:phone":"+33 1 43 03 35 59",
    "sg:province":"Ile de France",
    "wof:name":"Technique Europ\u00e9enne Nouvelle S.a.r.l.",
    "wof:placetype":"venue"
},
  "geometry": {"coordinates":[2.537523,48.846077],"type":"Point"}
}