{
  "type": "Feature",
  "properties": {
    "iso:country":"FR",
    "sg:address":"30, Rue Emile Zola, 62420 Billy Montigny",
    "sg:orig_category":"Unclassifiable Establishments",
    "sg:phone":"+33 3 21 20 28 81",
    "sg:province":"Nord Pas-de-Calais",
    "wof:name":"Centre Fiduciaire Et Comptable S.a.",
    "wof:placetype":"venue"
},
  "geometry": {"coordinates":[2.911519,50.416344],"type":"Point"}
}