{
  "type": "Feature",
  "properties": {
    "addr:full":"5 - 7, Rue Sully Prud'homme, 24100 Bergerac Bergerac Aquitaine 24100",
    "addr:housenumber":"7",
    "addr:postcode":"24100;24100",
    "addr:street":"Rue Sully Prud'Homme",
    "iso:country":"FR",
    "sg:address":"5 - 7, Rue Sully Prud'homme, 24100 Bergerac",
    "sg:city":"Bergerac",
    "sg:orig_category":"Unclassifiable Establishments",
    "sg:phone":"+33 5 53 57 00 05",
    "sg:postcode":"24100",
    "sg:province":"Aquitaine",
    "wof:name":"Les Presses D'aquitaine S.a.",
    "wof:placetype":"venue"
},
  "geometry": {"coordinates":[0.482435,44.853004],"type":"Point"}
}