{
  "type": "Feature",
  "properties": {
    "iso:country":"FR",
    "sg:address":"2, All\u00e9e des Atlantes - Parc les Propyl\u00e9es 1, 28000 Chartres",
    "sg:city":"Chartres",
    "sg:orig_category":"Non-Classified Establishments",
    "sg:phone":"+33 2 37 33 67 67",
    "sg:postcode":"28000",
    "sg:province":"Centre",
    "wof:name":"Welser Profil\u00e9s S.a.r.l.",
    "wof:placetype":"venue"
},
  "geometry": {"coordinates":[1.528038,48.454403],"type":"Point"}
}