{
  "type": "Feature",
  "properties": {
    "addr:full":"3 Rue Moliere 69006 Lyon Rhone-Alpes",
    "addr:housenumber":"3",
    "addr:postcode":"69006",
    "addr:street":"Rue Moliere",
    "iso:country":"FR",
    "sg:address":"3 Rue Moliere 69006 Lyon",
    "sg:classifiers":[
        {
            "category":"Manufacturing",
            "subcategory":"Jewelry",
            "type":"Manufacturing & Wholesale Goods"
        }
    ],
    "sg:phone":"+33 4 78 24 06 11",
    "sg:province":"Rhone-Alpes",
    "sg:tags":[
        "product",
        "miscellaneous",
        "jewellery"
    ],
    "wof:name":"Isabelle De Millery",
    "wof:placetype":"venue"
},
  "geometry": {"coordinates":[4.842291,45.767693],"type":"Point"}
}