{
  "type": "Feature",
  "properties": {
    "iso:country":"FR",
    "sg:address":"407 Rue De Vaugirard 75015 Paris",
    "sg:classifiers":[
        {
            "category":"Travel",
            "subcategory":"Hotels & Motels",
            "type":"Entertainment"
        }
    ],
    "sg:phone":"+33 1 53 68 94 00",
    "sg:postcode":"75015",
    "sg:province":"Ile de France",
    "sg:tags":[
        "hotels",
        "business",
        "restaurant"
    ],
    "wof:name":"Chez Clement Porte De Versailles",
    "wof:placetype":"venue"
},
  "geometry": {"coordinates":[2.288705,48.832741],"type":"Point"}
}