{
  "type": "Feature",
  "properties": {
    "iso:country":"FR",
    "sg:address":"B.P. 72, 21604 Longvic C\u00e9dex^^4, Rue du Paquier, 21600 Longvic",
    "sg:city":"Longvic",
    "sg:orig_category":"Non-Classified Establishments",
    "sg:phone":"+33 3 80 63 17 17",
    "sg:postcode":"21600",
    "sg:province":"Bourgogne",
    "wof:name":"Danzas S.a.",
    "wof:placetype":"venue"
},
  "geometry": {"coordinates":[5.06327,47.286015],"type":"Point"}
}