{
  "type": "Feature",
  "properties": {
    "addr:full":"B.P. 137, 49183 Saint Barth\u00e9l\u00e9my d'Anjou C\u00e9dex^^21, Rue du Hanipet, 49124 Saint Barth\u00e9l\u00e9my d'Anjou Pays de Loire",
    "addr:housenumber":"b.p. 137",
    "addr:postcode":"49183;barthe\u0301le\u0301my;49124;barthe\u0301le\u0301my;pays",
    "addr:street":"Rue Du Hanipet;D'Anjou",
    "iso:country":"FR",
    "sg:address":"B.P. 137, 49183 Saint Barth\u00e9l\u00e9my d'Anjou C\u00e9dex^^21, Rue du Hanipet, 49124 Saint Barth\u00e9l\u00e9my d'Anjou",
    "sg:orig_category":"Non-Classified Establishments",
    "sg:phone":"+33 2 41 60 88 88",
    "sg:province":"Pays de Loire",
    "wof:name":"Kdi Nozal S.a.s.",
    "wof:placetype":"venue"
},
  "geometry": {"coordinates":[-73.538673,45.612267],"type":"Point"}
}