{
  "type": "Feature",
  "properties": {
    "addr:full":"Rue De Claron Lieu Dit L Usine 40530 Labenne Labenne Aquitaine 40530",
    "addr:postcode":"40530;40530",
    "addr:street":"Rue De Claron Lieu Dit L Usine",
    "iso:country":"FR",
    "sg:address":"Rue De Claron Lieu Dit L Usine 40530 Labenne",
    "sg:city":"Labenne",
    "sg:classifiers":[
        {
            "category":"Shopping",
            "subcategory":"Hobbies, Toys, & Games",
            "type":"Retail Goods"
        }
    ],
    "sg:phone":"+33 5 59 45 41 61",
    "sg:postcode":"40530",
    "sg:province":"Aquitaine",
    "sg:tags":[
        "product",
        "breeding",
        "miscellaneous",
        "animal",
        "entertainment"
    ],
    "wof:name":"C Maquine",
    "wof:placetype":"venue"
},
  "geometry": {"coordinates":[-1.426219,43.592579],"type":"Point"}
}