{
  "type": "Feature",
  "properties": {
    "addr:full":"9 rue de Cond\u00e9 33000 Bordeaux Bordeaux Aquitaine 33000",
    "addr:housenumber":"9",
    "addr:postcode":"33000;33000",
    "addr:street":"Rue De Conde\u0301",
    "iso:country":"FR",
    "sg:address":"9 rue de Cond\u00e9 33000 Bordeaux",
    "sg:city":"Bordeaux",
    "sg:classifiers":[
        {
            "category":"Government",
            "subcategory":"Post Office",
            "type":"Public Place"
        }
    ],
    "sg:phone":"+33 5 56 00 12 11",
    "sg:postcode":"33000",
    "sg:province":"Aquitaine",
    "sg:tags":[
        "telecommunication",
        "cable"
    ],
    "wof:name":"Parallele 47 S.a.",
    "wof:placetype":"venue"
},
  "geometry": {"coordinates":[-0.573437,44.843544],"type":"Point"}
}