{
  "type": "Feature",
  "properties": {
    "addr:full":"Za Des Agries 31860 Labarthe Sur Leze Midi Pyr\u00e9n\u00e9es 31860",
    "addr:postcode":"31860;31860",
    "addr:street":"Za Des Agries",
    "iso:country":"FR",
    "sg:address":"Za Des Agries 31860 Labarthe Sur Leze",
    "sg:classifiers":[
        {
            "category":"Wholesale",
            "subcategory":"Chemicals & Plastics",
            "type":"Manufacturing & Wholesale Goods"
        }
    ],
    "sg:phone":"+33 5 61 08 84 84",
    "sg:postcode":"31860",
    "sg:province":"Midi Pyr\u00e9n\u00e9es",
    "sg:tags":[
        "pharmaceutical",
        "energy"
    ],
    "wof:name":"Alvea",
    "wof:placetype":"venue"
},
  "geometry": {"coordinates":[1.399701,43.452229],"type":"Point"}
}