{
  "type": "Feature",
  "properties": {
    "iso:country":"FR",
    "sg:address":"75 Cours Emile Zola Immeuble Le Quartz",
    "sg:city":"Villeurbanne",
    "sg:classifiers":[
        {
            "category":"Banks & Credit Unions",
            "subcategory":"Financial Services",
            "type":"Services"
        }
    ],
    "sg:phone":"+33 4 72 82 53 00",
    "sg:postcode":"69100",
    "sg:province":"Rhone-Alpes",
    "sg:tags":[
        "banking",
        "finance",
        "insurance"
    ],
    "wof:name":"Societe Francaise Du Radiotelephone",
    "wof:placetype":"venue"
},
  "geometry": {"coordinates":[4.86986,45.771568],"type":"Point"}
}