{
  "type": "Feature",
  "properties": {
    "addr:full":"21, Av. du Hurepoix - ZI de la Croix Blanche, 91700 Sainte Genevi\u00e8ve des Bois Ile de France",
    "addr:postcode":"91700",
    "addr:street":"21 Av. Du Hurepoix Zi De La Croix Blanche;Des Bois Ile De France",
    "iso:country":"FR",
    "sg:address":"21, Av. du Hurepoix - ZI de la Croix Blanche, 91700 Sainte Genevi\u00e8ve des Bois",
    "sg:orig_category":"Unclassifiable Establishments",
    "sg:phone":"+33 1 69 04 61 23",
    "sg:province":"Ile de France",
    "wof:name":"Mac' Sys S.a.",
    "wof:placetype":"venue"
},
  "geometry": {"coordinates":[2.326545,48.640656],"type":"Point"}
}