{
  "type": "Feature",
  "properties": {
    "addr:full":"Rue Des Routiers Zi Jalday 64500 St Jean De Luz Ciboure Aquitaine 64500",
    "addr:postcode":"64500;64500",
    "addr:street":"Rue Des Routiers Zi Jalday",
    "iso:country":"FR",
    "sg:address":"Rue Des Routiers Zi Jalday 64500 St Jean De Luz",
    "sg:city":"Ciboure",
    "sg:classifiers":[
        {
            "category":"Manufacturing",
            "subcategory":"Metals",
            "type":"Manufacturing & Wholesale Goods"
        }
    ],
    "sg:phone":"+33 5 59 26 33 40",
    "sg:postcode":"64500",
    "sg:province":"Aquitaine",
    "sg:tags":[
        "metallurgy",
        "metalworking"
    ],
    "wof:name":"Entreprise Heguy",
    "wof:placetype":"venue"
},
  "geometry": {"coordinates":[-1.660884,43.38773],"type":"Point"}
}