{
  "type": "Feature",
  "properties": {
    "addr:full":"Bourg 22510 Br\u00e9hand Br\u00e9hand Bretagne 22510",
    "addr:postcode":"22510;22510",
    "addr:street":"Bourg;Bre\u0301Hand",
    "iso:country":"FR",
    "sg:address":"Bourg 22510 Br\u00e9hand",
    "sg:city":"Br\u00e9hand",
    "sg:classifiers":[
        {
            "category":"Education",
            "subcategory":"Special Training",
            "type":"Public Place"
        }
    ],
    "sg:phone":"+33 2 96 42 78 38",
    "sg:postcode":"22510",
    "sg:province":"Bretagne",
    "sg:tags":[
        "pharmaceutical",
        "livestock",
        "animal",
        "chemical",
        "grain",
        "cereal",
        "breeding",
        "chem",
        "agriculture"
    ],
    "wof:name":"Coopagri Bretagne",
    "wof:placetype":"venue"
},
  "geometry": {"coordinates":[-2.57346,48.40229],"type":"Point"}
}