{
  "type": "Feature",
  "properties": {
    "iso:country":"FR",
    "sg:address":"Alzitone 20240 Ghisonaccia",
    "sg:orig_category":"Non-Classified Establishments",
    "sg:phone":"+33 4 95 56 09 23",
    "sg:province":"Corse",
    "wof:name":"Farioli Philippe",
    "wof:placetype":"venue"
},
  "geometry": {"coordinates":[9.382218,42.058964],"type":"Point"}
}