{
  "type": "Feature",
  "properties": {
    "iso:country":"FR",
    "sg:address":"Zone industrielle de Vongy 74200 Thonon les Bains",
    "sg:classifiers":[
        {
            "category":"Banks & Credit Unions",
            "subcategory":"Investment Brokerage",
            "type":"Services"
        }
    ],
    "sg:phone":"+33 4 50 71 47 13",
    "sg:province":"Rhone-Alpes",
    "sg:tags":[
        "tin",
        "products",
        "product",
        "enamelled"
    ],
    "wof:name":"Ets Brelat Sa",
    "wof:placetype":"venue"
},
  "geometry": {"coordinates":[6.478236,46.369949],"type":"Point"}
}