{
  "type": "Feature",
  "properties": {
    "iso:country":"FR",
    "sg:address":"ZI Beauregard",
    "sg:city":"La Fert\u00e9 Mac\u00e9",
    "sg:orig_category":"Unclassifiable Establishments",
    "sg:phone":"+33 2 33 37 08 33",
    "sg:postcode":"61600",
    "sg:province":"Basse Normandie",
    "wof:name":"Comp\u00e9dit Beauregard S.a.",
    "wof:placetype":"venue"
},
  "geometry": {"coordinates":[-0.358359,48.589485],"type":"Point"}
}