{
  "type": "Feature",
  "properties": {
    "addr:full":"Z I24 Rue Marie Curie 26100 Romans Sur Isere Rhone-Alpes 26100",
    "addr:postcode":"26100;26100",
    "addr:street":"Rue Marie Curie",
    "iso:country":"FR",
    "sg:address":"Z I24 Rue Marie Curie 26100 Romans Sur Isere",
    "sg:classifiers":[
        {
            "category":"Food & Beverages",
            "subcategory":"Bakery",
            "type":"Retail Goods"
        }
    ],
    "sg:phone":"+33 4 75 72 20 13",
    "sg:postcode":"26100",
    "sg:province":"Rhone-Alpes",
    "sg:tags":[
        "long-keeping",
        "pastry"
    ],
    "wof:name":"Ste Nouvelle Des Douceurs De Jacquemart Sa",
    "wof:placetype":"venue"
},
  "geometry": {"coordinates":[5.049637,45.045036],"type":"Point"}
}