{
  "type": "Feature",
  "properties": {
    "addr:full":"Rte de Gisy - Burospace 13 Bi\u00e8vres C\u00e9dex Champagne 91572",
    "addr:housenumber":"13",
    "addr:postcode":"91572",
    "addr:street":"Rte De Gisy Burospace",
    "iso:country":"FR",
    "sg:address":"Rte de Gisy - Burospace 13",
    "sg:city":"Bi\u00e8vres C\u00e9dex",
    "sg:orig_category":"Non-Classified Establishments",
    "sg:phone":"+33 1 69 41 00 40",
    "sg:postcode":"91572",
    "sg:province":"Champagne",
    "wof:name":"A.pc.t. S.a. - Advanced Pc Technologies",
    "wof:placetype":"venue"
},
  "geometry": {"coordinates":[2.215318,48.753994],"type":"Point"}
}