{
  "type": "Feature",
  "properties": {
    "addr:full":"2 Impasse Des Alizes Carquefou Pays de Loire 44470",
    "addr:housenumber":"2",
    "addr:postcode":"44470",
    "addr:street":"Impasse Des Alizes Carquefou Pays",
    "iso:country":"FR",
    "sg:address":"2 Impasse Des Alizes",
    "sg:city":"Carquefou",
    "sg:classifiers":[
        {
            "category":"Banks & Credit Unions",
            "subcategory":"Financial Services",
            "type":"Services"
        }
    ],
    "sg:phone":"+33 2 40 18 10 10",
    "sg:postcode":"44470",
    "sg:province":"Pays de Loire",
    "sg:tags":[
        "banking",
        "finance",
        "insurance"
    ],
    "wof:name":"Adp Gsi",
    "wof:placetype":"venue"
},
  "geometry": {"coordinates":[-1.486337,47.268211],"type":"Point"}
}