{
  "type": "Feature",
  "properties": {
    "addr:full":"23 Rue De Campniac P\u00e9rigueux Aquitaine 24000",
    "addr:housenumber":"23",
    "addr:postcode":"24000",
    "addr:street":"Rue De Campniac",
    "iso:country":"FR",
    "sg:address":"23 Rue De Campniac",
    "sg:city":"P\u00e9rigueux",
    "sg:classifiers":[
        {
            "category":"Banks & Credit Unions",
            "subcategory":"Financial Services",
            "type":"Services"
        }
    ],
    "sg:phone":"+33 5 53 35 86 80",
    "sg:postcode":"24000",
    "sg:province":"Aquitaine",
    "sg:tags":[
        "banking",
        "finance",
        "insurance"
    ],
    "wof:name":"Cabinet Lempereur Sa",
    "wof:placetype":"venue"
},
  "geometry": {"coordinates":[0.715418,45.177704],"type":"Point"}
}