{
  "type": "Feature",
  "properties": {
    "iso:country":"FR",
    "sg:address":"30 rue Saint-Marc 75002 Paris",
    "sg:classifiers":[
        {
            "category":"Manufacturing",
            "subcategory":"Textiles",
            "type":"Manufacturing & Wholesale Goods"
        }
    ],
    "sg:phone":"+33 1 42 61 18 35",
    "sg:postcode":"75002",
    "sg:province":"Ile de France",
    "sg:tags":[
        "natural"
    ],
    "wof:name":"Saris Sa",
    "wof:placetype":"venue"
},
  "geometry": {"coordinates":[2.338959,48.870773],"type":"Point"}
}