{
  "type": "Feature",
  "properties": {
    "addr:full":"Rue Vincent Auriol 85000 La Roche Sur Yon Pays de Loire 85000",
    "addr:postcode":"85000;85000",
    "addr:street":"Rue Vincent Auriol;Roche;Yon",
    "iso:country":"FR",
    "sg:address":"Rue Vincent Auriol 85000 La Roche Sur Yon",
    "sg:classifiers":[
        {
            "category":"Professional",
            "subcategory":"Engineering",
            "type":"Services"
        }
    ],
    "sg:phone":"+33 2 51 37 18 22",
    "sg:postcode":"85000",
    "sg:province":"Pays de Loire",
    "sg:tags":[
        "machine",
        "-",
        "mechanical"
    ],
    "wof:name":"Johanny Sa (ets)",
    "wof:placetype":"venue"
},
  "geometry": {"coordinates":[-1.444341,46.657291],"type":"Point"}
}