{
  "type": "Feature",
  "properties": {
    "iso:country":"FR",
    "sg:address":"10, Rue de Nuits, 33100 Bordeaux",
    "sg:city":"Bordeaux",
    "sg:orig_category":"Non-Classified Establishments",
    "sg:phone":"+33 5 56 40 50 50",
    "sg:postcode":"33100",
    "sg:province":"Aquitaine",
    "wof:name":"Congas Rive Droite S.a.r.l.",
    "wof:placetype":"venue"
},
  "geometry": {"coordinates":[-0.554418,44.842815],"type":"Point"}
}