{
  "type": "Feature",
  "properties": {
    "addr:full":"25 Rue De Brioux 79230 Prahecq Poitou-Charentes",
    "addr:housenumber":"25",
    "addr:postcode":"79230",
    "addr:street":"Rue De Brioux",
    "iso:country":"FR",
    "sg:address":"25 Rue De Brioux 79230 Prahecq",
    "sg:classifiers":[
        {
            "category":"Professional",
            "subcategory":"Printing & Photocopies",
            "type":"Services"
        }
    ],
    "sg:phone":"+33 5 49 35 29 58",
    "sg:province":"Poitou-Charentes",
    "sg:tags":[
        "publishing"
    ],
    "wof:name":"Patrimoines Et Medias",
    "wof:placetype":"venue"
},
  "geometry": {"coordinates":[-0.343324,46.258484],"type":"Point"}
}