{
  "type": "Feature",
  "properties": {
    "addr:full":"55, Rue Nationale, 37000 Tours Tours Centre 37000",
    "addr:housenumber":"55",
    "addr:postcode":"37000;37000",
    "addr:street":"Rue Nationale",
    "iso:country":"FR",
    "sg:address":"55, Rue Nationale, 37000 Tours",
    "sg:city":"Tours",
    "sg:orig_category":"Unclassifiable Establishments",
    "sg:phone":"+33 2 47 75 25 25",
    "sg:postcode":"37000",
    "sg:province":"Centre",
    "wof:name":"R.c.p. Design Global S.a.r.l.",
    "wof:placetype":"venue"
},
  "geometry": {"coordinates":[0.687647,47.392532],"type":"Point"}
}