{
  "type": "Feature",
  "properties": {
    "iso:country":"FR",
    "sg:address":"32, Rue de Constantine, 62200 Boulogne sur Mer",
    "sg:orig_category":"Unclassifiable Establishments",
    "sg:phone":"+33 3 21 31 53 46",
    "sg:province":"Nord Pas-de-Calais",
    "wof:name":"D\u00e9martop Justin S.a.r.l.",
    "wof:placetype":"venue"
},
  "geometry": {"coordinates":[1.590953,50.720291],"type":"Point"}
}