{
  "type": "Feature",
  "properties": {
    "addr:full":"37 avenue Denis Papin 45800 St Jean de Braye Combleux Centre 45800",
    "addr:housenumber":"37;combleux",
    "addr:postcode":"45800;45800",
    "addr:street":"Avenue Denis Papin",
    "iso:country":"FR",
    "sg:address":"37 avenue Denis Papin 45800 St Jean de Braye",
    "sg:city":"Combleux",
    "sg:classifiers":[
        {
            "category":"Wholesale",
            "subcategory":"Medical Equipment & Supplies",
            "type":"Manufacturing & Wholesale Goods"
        }
    ],
    "sg:phone":"+33 2 38 86 04 64",
    "sg:postcode":"45800",
    "sg:province":"Centre",
    "wof:name":"Marvel Sa",
    "wof:placetype":"venue"
},
  "geometry": {"coordinates":[1.946569,47.912106],"type":"Point"}
}