{
  "type": "Feature",
  "properties": {
    "addr:full":"20 R \u00e0 Robert Jacques Turgot 29000 Quimper Quimper Bretagne 29000",
    "addr:housenumber":"20",
    "addr:postcode":"29000;29000",
    "addr:street":"R A\u0300 Robert Jacques Turgot",
    "iso:country":"FR",
    "sg:address":"20 R \u00e0 Robert Jacques Turgot 29000 Quimper",
    "sg:city":"Quimper",
    "sg:classifiers":[
        {
            "category":"Manufacturing",
            "subcategory":"Printing",
            "type":"Manufacturing & Wholesale Goods"
        }
    ],
    "sg:phone":"+33 2 98 95 07 29",
    "sg:postcode":"29000",
    "sg:province":"Bretagne",
    "sg:tags":[
        "house",
        "book"
    ],
    "wof:name":"Sa Imprimerie Du Commerce",
    "wof:placetype":"venue"
},
  "geometry": {"coordinates":[-4.091894,48.016098],"type":"Point"}
}