{
  "type": "Feature",
  "properties": {
    "iso:country":"FR",
    "sg:address":"1945, Av. de Toulouse, 34070 Montpellier",
    "sg:orig_category":"Non-Classified Establishments",
    "sg:phone":"+33 4 67 42 65 78",
    "sg:postcode":"34070",
    "sg:province":"Languedoc-Roussillon",
    "wof:name":"A.c.a. S.a. - Ateliers De La Croix D'argent",
    "wof:placetype":"venue"
},
  "geometry": {"coordinates":[3.853953,43.587719],"type":"Point"}
}