{
  "type": "Feature",
  "properties": {
    "addr:full":"ZI les Landelles Magnet Auvergne 03260",
    "addr:postcode":"03260",
    "addr:street":"Zi",
    "iso:country":"FR",
    "sg:address":"ZI les Landelles",
    "sg:city":"Magnet",
    "sg:orig_category":"Unclassifiable Establishments",
    "sg:phone":"+33 4 70 59 69 87",
    "sg:postcode":"03260",
    "sg:province":"Auvergne",
    "wof:name":"Transports Reviron S.a.",
    "wof:placetype":"venue"
},
  "geometry": {"coordinates":[3.500596,46.219158],"type":"Point"}
}