{
  "type": "Feature",
  "properties": {
    "addr:full":"54 blvd Aristide Briand; La Roche sur Yon; 85001 Basse Normandie",
    "addr:postcode":"85001",
    "addr:street":"54 Blvd Aristide Briand La Roche Sur Yon",
    "iso:country":"FR",
    "sg:address":"54 blvd Aristide Briand; La Roche sur Yon; 85001",
    "sg:classifiers":[
        {
            "category":"Banks & Credit Unions",
            "subcategory":"Bank",
            "type":"Services"
        }
    ],
    "sg:phone":"+33 2 51 62 29 45",
    "sg:province":"Basse Normandie",
    "wof:name":"Banque De France",
    "wof:placetype":"venue"
},
  "geometry": {"coordinates":[-1.432667,46.670895],"type":"Point"}
}