{
  "type": "Feature",
  "properties": {
    "addr:full":"25 Rue Des Buissons 52140 Is En Bassigny Champagne 52140",
    "addr:housenumber":"25",
    "addr:postcode":"52140;52140",
    "addr:street":"Rue Des Buissons;Champagne",
    "iso:country":"FR",
    "sg:address":"25 Rue Des Buissons 52140 Is En Bassigny",
    "sg:classifiers":[
        {
            "category":"Shopping",
            "type":"Retail Goods"
        }
    ],
    "sg:phone":"+33 3 25 30 58 23",
    "sg:postcode":"52140",
    "sg:province":"Champagne",
    "sg:tags":[
        "metallurgy",
        "finished",
        "-",
        "metalworking",
        "metallic"
    ],
    "wof:name":"Atelier Haquin",
    "wof:placetype":"venue"
},
  "geometry": {"coordinates":[5.43601,48.036098],"type":"Point"}
}