{
  "type": "Feature",
  "properties": {
    "addr:full":"B.P. 3 V\u00e9z\u00e9ronce Curtin^^La Botte 38510 V\u00e9z\u00e9ronce Curtin Rhone-Alpes 38510",
    "addr:postcode":"38510;38510",
    "addr:street":"B.P. 3 Ve\u0301Ze\u0301Ronce;Botte",
    "iso:country":"FR",
    "sg:address":"B.P. 3",
    "sg:city":"V\u00e9z\u00e9ronce Curtin^^La Botte 38510 V\u00e9z\u00e9ronce Curtin",
    "sg:orig_category":"Non-Classified Establishments",
    "sg:phone":"+33 4 74 80 12 24",
    "sg:postcode":"38510",
    "sg:province":"Rhone-Alpes",
    "wof:name":"C.m.v. Colombin S.a.r.l.",
    "wof:placetype":"venue"
},
  "geometry": {"coordinates":[5.475785,45.635395],"type":"Point"}
}