{
  "type": "Feature",
  "properties": {
    "iso:country":"FR",
    "sg:address":"B.P. 76, 03403 Yzeure C\u00e9dex^^67, Rue des Epoux Contoux, 03400 Yzeure",
    "sg:city":"Yzeure",
    "sg:orig_category":"Non-Classified Establishments",
    "sg:phone":"+33 4 70 20 96 50",
    "sg:postcode":"03400",
    "sg:province":"Auvergne",
    "wof:name":"Plastyzeure S.a.",
    "wof:placetype":"venue"
},
  "geometry": {"coordinates":[3.37215,46.573559],"type":"Point"}
}