{
  "type": "Feature",
  "properties": {
    "addr:full":"Place du March\u00e9 Couvert Bergerac Aquitaine 24100",
    "addr:postcode":"24100",
    "addr:street":"Place Du Marche\u0301 Couvert",
    "iso:country":"FR",
    "sg:address":"Place du March\u00e9 Couvert",
    "sg:city":"Bergerac",
    "sg:orig_category":"Non-Classified Establishments",
    "sg:phone":"+33 5 53 63 79 00",
    "sg:postcode":"24100",
    "sg:province":"Aquitaine",
    "wof:name":"A.2.c.e. S.a.r.l. - Audit Comptabilit\u00e9 Conseils Expertises",
    "wof:placetype":"venue"
},
  "geometry": {"coordinates":[0.48303,44.852032],"type":"Point"}
}