{
  "type": "Feature",
  "properties": {
    "iso:country":"FR",
    "sg:address":"46 Rue Gay Lussac 94430 Chennevi\u00e8res Sur Marne",
    "sg:classifiers":[
        {
            "category":"Health Services",
            "subcategory":"Optometrist",
            "type":"Services"
        }
    ],
    "sg:phone":"+33 1 45 94 81 93",
    "sg:postcode":"94430",
    "sg:province":"Ile de France",
    "sg:tags":[
        "instrument",
        "optical",
        "-",
        "precision",
        "equipment"
    ],
    "wof:name":"Cornelia Contact Sarl",
    "wof:placetype":"venue"
},
  "geometry": {"coordinates":[2.545279,48.793247],"type":"Point"}
}