{
  "type": "Feature",
  "properties": {
    "addr:full":"697, Rte de Beaurepaire, 38260 Semons Rhone-Alpes 38260",
    "addr:housenumber":"697",
    "addr:postcode":"38260;38260",
    "addr:street":"Rte De Beaurepaire;Rhone-Alpes",
    "iso:country":"FR",
    "sg:address":"697, Rte de Beaurepaire, 38260 Semons",
    "sg:orig_category":"Unclassifiable Establishments",
    "sg:phone":"+33 4 74 54 21 33",
    "sg:postcode":"38260",
    "sg:province":"Rhone-Alpes",
    "wof:name":"Deltour S.a.",
    "wof:placetype":"venue"
},
  "geometry": {"coordinates":[5.2094,45.431618],"type":"Point"}
}