{
  "type": "Feature",
  "properties": {
    "iso:country":"FR",
    "sg:address":"697, Rte de Beaurepaire, 38260 Semons",
    "sg:orig_category":"Unclassifiable Establishments",
    "sg:phone":"+33 4 74 54 21 33",
    "sg:postcode":"38260",
    "sg:province":"Rhone-Alpes",
    "wof:name":"Deltour S.a.",
    "wof:placetype":"venue"
},
  "geometry": {"coordinates":[5.2094,45.431618],"type":"Point"}
}