{
  "type": "Feature",
  "properties": {
    "addr:full":"7 Boulevard Pierre Brossolette 76120 Le Grand Quevilly Haute Normandie",
    "addr:housenumber":"7",
    "addr:postcode":"76120",
    "addr:street":"Boulevard Pierre Brossolette;Haute Normandie",
    "iso:country":"FR",
    "sg:address":"7 Boulevard Pierre Brossolette 76120 Le Grand Quevilly",
    "sg:classifiers":[
        {
            "category":"Banks & Credit Unions",
            "subcategory":"Investment Brokerage",
            "type":"Services"
        }
    ],
    "sg:phone":"+33 2 35 69 42 42",
    "sg:province":"Haute Normandie",
    "sg:tags":[
        "-",
        "transport",
        "related"
    ],
    "wof:name":"Frigoscandia Sa",
    "wof:placetype":"venue"
},
  "geometry": {"coordinates":[1.035,49.417461],"type":"Point"}
}