{
  "type": "Feature",
  "properties": {
    "addr:full":"5, Rue de J\u00e9zanne, 78711 Mantes la Ville C\u00e9dex \u00cele-de-France",
    "addr:housenumber":"5",
    "addr:postcode":"78711",
    "addr:street":"Rue De Je\u0301Zanne;Ce\u0301Dex",
    "iso:country":"FR",
    "sg:address":"5, Rue de J\u00e9zanne, 78711 Mantes la Ville C\u00e9dex",
    "sg:orig_category":"Non-Classified Establishments",
    "sg:phone":"+33 1 30 92 07 86",
    "sg:province":"\u00cele-de-France",
    "wof:name":"Gatine S.a.",
    "wof:placetype":"venue"
},
  "geometry": {"coordinates":[1.718,48.9795],"type":"Point"}
}