{
  "type": "Feature",
  "properties": {
    "addr:full":"12170 La Selve Midi Pyr\u00e9n\u00e9es 12170",
    "addr:housenumber":"12170",
    "addr:postcode":"pyre\u0301ne\u0301es 12170",
    "addr:street":"La",
    "iso:country":"FR",
    "sg:address":"12170 La Selve",
    "sg:classifiers":[
        {
            "category":"Bakery",
            "type":"Food & Drink"
        }
    ],
    "sg:phone":"+33 5 65 46 13 69",
    "sg:postcode":"12170",
    "sg:province":"Midi Pyr\u00e9n\u00e9es",
    "sg:tags":[
        "cake",
        "product",
        "related",
        "bread"
    ],
    "wof:name":"La Coupiagaise",
    "wof:placetype":"venue"
},
  "geometry": {"coordinates":[2.534098,44.112225],"type":"Point"}
}