{
  "type": "Feature",
  "properties": {
    "iso:country":"FR",
    "sg:address":"30",
    "sg:city":"du 9 A\u00f4ut 1944; Carquefou; 44470",
    "sg:classifiers":[
        {
            "category":"Banks & Credit Unions",
            "subcategory":"Bank",
            "type":"Services"
        }
    ],
    "sg:phone":"+33 3340509124",
    "sg:postcode":"44470",
    "sg:province":"Pays de Loire",
    "wof:name":"Caisse Regionale De Cr\u00e9dit Agricole",
    "wof:placetype":"venue"
},
  "geometry": {"coordinates":[-1.493728,47.297424],"type":"Point"}
}