{
  "type": "Feature",
  "properties": {
    "addr:full":"5, Bd des Deux Communes, 94120 Fontenay sous Bois Ile de France",
    "addr:housenumber":"5",
    "addr:postcode":"94120",
    "addr:street":"Bd Des Deux Communes;Bois Ile De France",
    "iso:country":"FR",
    "sg:address":"5, Bd des Deux Communes, 94120 Fontenay sous Bois",
    "sg:orig_category":"Unclassifiable Establishments",
    "sg:phone":"+33 1 48 73 14 78",
    "sg:province":"Ile de France",
    "wof:name":"I.e.s. S.a.r.l. - Import Export Service",
    "wof:placetype":"venue"
},
  "geometry": {"coordinates":[2.47353,48.840382],"type":"Point"}
}