{
  "type": "Feature",
  "properties": {
    "iso:country":"FR",
    "sg:address":"Rue Des Forges 53440 Aron",
    "sg:classifiers":[
        {
            "category":"Home & Garden",
            "subcategory":"Furniture",
            "type":"Retail Goods"
        }
    ],
    "sg:phone":"+33 2 43 04 25 98",
    "sg:province":"Pays de Loire",
    "sg:tags":[
        "wood"
    ],
    "wof:name":"Hubert Bois Sa",
    "wof:placetype":"venue"
},
  "geometry": {"coordinates":[-0.557559,48.294704],"type":"Point"}
}