{
  "type": "Feature",
  "properties": {
    "iso:country":"FR",
    "sg:address":"Zone Industrielle 76440 Forges Les Eaux",
    "sg:classifiers":[
        {
            "category":"Wholesale",
            "subcategory":"Machinery & Supplies",
            "type":"Manufacturing & Wholesale Goods"
        }
    ],
    "sg:phone":"+33 2 35 90 42 42",
    "sg:postcode":"76440",
    "sg:province":"Haute Normandie",
    "sg:tags":[
        "-",
        "machine",
        "equipment",
        "engineering",
        "animal",
        "mechanical",
        "breeding",
        "agriculture"
    ],
    "wof:name":"Packo France Sa",
    "wof:placetype":"venue"
},
  "geometry": {"coordinates":[1.546317,49.612804],"type":"Point"}
}