{
  "type": "Feature",
  "properties": {
    "iso:country":"FR",
    "sg:address":"29 Rue Notre-Dame De Nazareth 75003 Paris",
    "sg:classifiers":[
        {
            "category":"Shopping",
            "subcategory":"Clothing, Apparel, & Fashions",
            "type":"Retail Goods"
        }
    ],
    "sg:phone":"+33 1 42 72 78 72",
    "sg:postcode":"75003",
    "sg:province":"Ile de France",
    "sg:tags":[
        "textile",
        "clothing",
        "clothes"
    ],
    "wof:name":"Mely",
    "wof:placetype":"venue"
},
  "geometry": {"coordinates":[2.359144,48.867188],"type":"Point"}
}