{
  "type": "Feature",
  "properties": {
    "iso:country":"FR",
    "sg:address":"Chemin De Creil 60340 St Leu D'Esserent",
    "sg:classifiers":[
        {
            "category":"Manufacturing",
            "subcategory":"Chemicals & Compounds",
            "type":"Manufacturing & Wholesale Goods"
        }
    ],
    "sg:phone":"+33 3 44 61 28 00",
    "sg:postcode":"60340",
    "sg:province":"Picardie",
    "sg:tags":[
        "pharmaceutical",
        "chemistry",
        "-",
        "by-product"
    ],
    "wof:name":"Praxair Sas",
    "wof:placetype":"venue"
},
  "geometry": {"coordinates":[2.41845,49.215969],"type":"Point"}
}