{
  "type": "Feature",
  "properties": {
    "addr:full":"ZI de Thise Besan\u00e7on Franche Comt\u00e9 25000",
    "addr:postcode":"25000",
    "addr:street":"Zi De Thise;Franche Comte\u0301",
    "iso:country":"FR",
    "sg:address":"ZI de Thise",
    "sg:city":"Besan\u00e7on",
    "sg:orig_category":"Unclassifiable Establishments",
    "sg:phone":"+33 3 81 80 97 90",
    "sg:postcode":"25000",
    "sg:province":"Franche Comt\u00e9",
    "wof:name":"M.b. Am\u00e9nagement S.a.",
    "wof:placetype":"venue"
},
  "geometry": {"coordinates":[6.025686,47.242317],"type":"Point"}
}