{
  "type": "Feature",
  "properties": {
    "addr:full":"4 all\u00e9e de la Garenne 28100 Dreux Dreux Centre 28100",
    "addr:housenumber":"4;dreux",
    "addr:postcode":"28100;28100",
    "addr:street":"Alle\u0301E De La Garenne",
    "iso:country":"FR",
    "sg:address":"4 all\u00e9e de la Garenne 28100 Dreux",
    "sg:city":"Dreux",
    "sg:classifiers":[
        {
            "category":"Food & Beverages",
            "subcategory":"Fruits & Vegetables",
            "type":"Retail Goods"
        }
    ],
    "sg:phone":"+33 2 37 62 57 00",
    "sg:postcode":"28100",
    "sg:province":"Centre",
    "sg:tags":[
        "machine",
        "processing",
        "complete",
        "systems"
    ],
    "wof:name":"Stork Systemes Alimentaires S.a.",
    "wof:placetype":"venue"
},
  "geometry": {"coordinates":[1.360432,48.750412],"type":"Point"}
}