{
  "type": "Feature",
  "properties": {
    "addr:full":"B.P. 2154, 68060 Mulhouse C\u00e9dex^^34, Rue Marc Seguin, 68100 Colmar Mulhouse Alsace 68100",
    "addr:postcode":"68060;68100;68100",
    "addr:street":"B.P. 2154;Rue Marc Seguin",
    "iso:country":"FR",
    "sg:address":"B.P. 2154, 68060 Mulhouse C\u00e9dex^^34, Rue Marc Seguin, 68100 Colmar",
    "sg:city":"Mulhouse",
    "sg:orig_category":"Non-Classified Establishments",
    "sg:phone":"+33 3 89 59 02 96",
    "sg:postcode":"68100",
    "sg:province":"Alsace",
    "wof:name":"Stepper Energie France S.a.",
    "wof:placetype":"venue"
},
  "geometry": {"coordinates":[7.34365,47.751709],"type":"Point"}
}