{
  "type": "Feature",
  "properties": {
    "addr:full":"13, Rue Gutenberg - ZI, 77100 Meaux Ile de France",
    "addr:housenumber":"13",
    "addr:postcode":"77100;ile",
    "addr:street":"Rue Gutenberg Zi",
    "iso:country":"FR",
    "sg:address":"13, Rue Gutenberg - ZI, 77100 Meaux",
    "sg:orig_category":"Non-Classified Establishments",
    "sg:phone":"+33 1 64 33 12 89",
    "sg:province":"Ile de France",
    "wof:name":"Les Plastiques Delmas S.a.",
    "wof:placetype":"venue"
},
  "geometry": {"coordinates":[2.883054,48.959351],"type":"Point"}
}