{
  "type": "Feature",
  "properties": {
    "addr:full":"Rue des Pierres Noires - ZI de Kerlois Saint Renan Bretagne 29290",
    "addr:postcode":"29290",
    "addr:street":"Rue Des Pierres Noires Zi De Kerlois Saint Renan Bretagne",
    "iso:country":"FR",
    "sg:address":"Rue des Pierres Noires - ZI de Kerlois",
    "sg:city":"Saint Renan",
    "sg:orig_category":"Unclassifiable Establishments",
    "sg:phone":"+33 2 98 32 03 20",
    "sg:postcode":"29290",
    "sg:province":"Bretagne",
    "wof:name":"Viaporc",
    "wof:placetype":"venue"
},
  "geometry": {"coordinates":[-4.621414,48.434345],"type":"Point"}
}