{
  "type": "Feature",
  "properties": {
    "iso:country":"FR",
    "sg:address":"Rue des Pierres Noires - ZI de Kerlois",
    "sg:city":"Saint Renan",
    "sg:orig_category":"Unclassifiable Establishments",
    "sg:phone":"+33 2 98 32 03 20",
    "sg:postcode":"29290",
    "sg:province":"Bretagne",
    "wof:name":"Viaporc",
    "wof:placetype":"venue"
},
  "geometry": {"coordinates":[-4.621414,48.434345],"type":"Point"}
}