{
  "type": "Feature",
  "properties": {
    "addr:full":"Rte de Lannion Perros Saint Quay Perros Bretagne 22700",
    "addr:postcode":"22700",
    "addr:street":"Rte De Lannion;Saint Quay Perros Bretagne",
    "iso:country":"FR",
    "sg:address":"Rte de Lannion Perros",
    "sg:city":"Saint Quay Perros",
    "sg:orig_category":"Unclassifiable Establishments",
    "sg:phone":"+33 2 96 48 77 64",
    "sg:postcode":"22700",
    "sg:province":"Bretagne",
    "wof:name":"M.a.p S.a.r.l. - March\u00e9 Auto Perrosien",
    "wof:placetype":"venue"
},
  "geometry": {"coordinates":[-3.446654,48.792221],"type":"Point"}
}