{
  "type": "Feature",
  "properties": {
    "iso:country":"FR",
    "sg:address":"Rte d'Illiers",
    "sg:city":"Nogent sur Eure",
    "sg:orig_category":"Unclassifiable Establishments",
    "sg:phone":"+33 2 37 25 80 00",
    "sg:postcode":"28120",
    "sg:province":"Centre",
    "wof:name":"Supergel 28 S.a.r.l.",
    "wof:placetype":"venue"
},
  "geometry": {"coordinates":[1.24358,48.29974],"type":"Point"}
}