{
  "type": "Feature",
  "properties": {
    "iso:country":"FR",
    "sg:address":"23 Rue De La Sir\u00e8ne 41200 Romorantin Lanthenay",
    "sg:city":"Villefranche-sur-Cher",
    "sg:classifiers":[
        {
            "category":"Banks & Credit Unions",
            "subcategory":"Financial Services",
            "type":"Services"
        }
    ],
    "sg:phone":"+33 2 54 94 60 69",
    "sg:postcode":"41200",
    "sg:province":"Centre",
    "sg:tags":[
        "banking",
        "insurance",
        "institution",
        "finance"
    ],
    "wof:name":"Banque Regionale De L'ouest (bro)",
    "wof:placetype":"venue"
},
  "geometry": {"coordinates":[1.745963,47.359657],"type":"Point"}
}