{
  "type": "Feature",
  "properties": {
    "addr:full":"Quartier les Hauches Loriol sur Dr\u00f4me Rhone-Alpes 26270",
    "addr:postcode":"26270",
    "addr:street":"Quartier Les",
    "iso:country":"FR",
    "sg:address":"Quartier les Hauches",
    "sg:city":"Loriol sur Dr\u00f4me",
    "sg:orig_category":"Unclassifiable Establishments",
    "sg:phone":"+33 4 75 61 11 00",
    "sg:postcode":"26270",
    "sg:province":"Rhone-Alpes",
    "wof:name":"Lorifruit",
    "wof:placetype":"venue"
},
  "geometry": {"coordinates":[4.816455,44.755955],"type":"Point"}
}