{
  "type": "Feature",
  "properties": {
    "iso:country":"FR",
    "sg:address":"Av Du 33\u00e8 Ri 01300 Belley",
    "sg:classifiers":[
        {
            "category":"Home & Garden",
            "subcategory":"Furniture",
            "type":"Retail Goods"
        }
    ],
    "sg:phone":"+33 4 79 81 67 67",
    "sg:postcode":"01300",
    "sg:province":"Rhone-Alpes",
    "sg:tags":[
        "wood"
    ],
    "wof:name":"Margueron Et Cie",
    "wof:placetype":"venue"
},
  "geometry": {"coordinates":[5.67735,45.734741],"type":"Point"}
}