{
  "type": "Feature",
  "properties": {
    "addr:full":"197, Av. du Mar\u00e9chal de Lattre de Tassigny, 82100 Castelsarrasin Midi Pyr\u00e9n\u00e9es",
    "addr:postcode":"82100",
    "addr:street":"197 Av. Du Mare\u0301Chal De Lattre De Tassigny",
    "iso:country":"FR",
    "sg:address":"197, Av. du Mar\u00e9chal de Lattre de Tassigny, 82100 Castelsarrasin",
    "sg:orig_category":"Non-Classified Establishments",
    "sg:phone":"+33 5 63 95 10 15",
    "sg:province":"Midi Pyr\u00e9n\u00e9es",
    "wof:name":"I.t.w. Gunther S.a.",
    "wof:placetype":"venue"
},
  "geometry": {"coordinates":[1.112917,44.043846],"type":"Point"}
}