{
  "type": "Feature",
  "properties": {
    "iso:country":"FR",
    "sg:address":"B.P. 16",
    "sg:city":"Nanc l\u00e8s Saint Amour^^39160 Nanc l\u00e8s Saint Amour",
    "sg:orig_category":"Non-Classified Establishments",
    "sg:phone":"+33 3 84 87 02 60",
    "sg:postcode":"39160",
    "sg:province":"Franche Comt\u00e9",
    "wof:name":"Sotrafa S.a.r.l.",
    "wof:placetype":"venue"
},
  "geometry": {"coordinates":[5.353531,46.455875],"type":"Point"}
}