{
  "type": "Feature",
  "properties": {
    "iso:country":"FR",
    "sg:address":"4 rue de l'Industrie 67721 HOERDT CEDEX",
    "sg:city":"Hoerdt",
    "sg:classifiers":[
        {
            "category":"Building & Trades",
            "subcategory":"Construction",
            "type":"Services"
        }
    ],
    "sg:phone":"+33 3 88 69 23 10",
    "sg:postcode":"67720",
    "sg:province":"Alsace",
    "sg:tags":[
        "industrial",
        "timber"
    ],
    "wof:name":"La Compagnie Du Bois B\u00e2timent Sa",
    "wof:placetype":"venue"
},
  "geometry": {"coordinates":[7.795894,48.676208],"type":"Point"}
}