{
  "type": "Feature",
  "properties": {
    "addr:full":"Zac De La Croix St Nicolas 94510 La Queue En Brie Ile de France 94510",
    "addr:postcode":"94510;94510",
    "addr:street":"Zac De La Croix St Nicolas;Queue En Brie Ile De France",
    "iso:country":"FR",
    "sg:address":"Zac De La Croix St Nicolas 94510 La Queue En Brie",
    "sg:classifiers":[
        {
            "category":"Travel",
            "subcategory":"Hotels & Motels",
            "type":"Entertainment"
        }
    ],
    "sg:phone":"+33 1 49 62 73 73",
    "sg:postcode":"94510",
    "sg:province":"Ile de France",
    "sg:tags":[
        "hotels",
        "business",
        "restaurant"
    ],
    "wof:name":"Buffalo Grill",
    "wof:placetype":"venue"
},
  "geometry": {"coordinates":[2.573805,48.790321],"type":"Point"}
}