{
  "type": "Feature",
  "properties": {
    "addr:full":"B.P. 30 Herbignac Pays de Loire 44410",
    "addr:postcode":"44410",
    "addr:street":"B.P. 30 Herbignac Pays",
    "iso:country":"FR",
    "sg:address":"B.P. 30",
    "sg:city":"Herbignac",
    "sg:orig_category":"Non-Classified Establishments",
    "sg:phone":"+33 2 40 19 91 30",
    "sg:postcode":"44410",
    "sg:province":"Pays de Loire",
    "wof:name":"Andr\u00e9 Barrat S.a.r.l.",
    "wof:placetype":"venue"
},
  "geometry": {"coordinates":[-2.318004,47.448807],"type":"Point"}
}