{
  "type": "Feature",
  "properties": {
    "addr:full":"1 rue Jean Joseph Labb\u00e9 54730 GORCY Lorraine 54730",
    "addr:housenumber":"1",
    "addr:postcode":"54730;54730",
    "addr:street":"Rue Jean Joseph Labbe\u0301",
    "iso:country":"FR",
    "sg:address":"1 rue Jean Joseph Labb\u00e9 54730 GORCY",
    "sg:classifiers":[
        {
            "category":"Manufacturing",
            "subcategory":"Metals",
            "type":"Manufacturing & Wholesale Goods"
        }
    ],
    "sg:phone":"+33 3 82 26 89 89",
    "sg:postcode":"54730",
    "sg:province":"Lorraine",
    "sg:tags":[
        "aluminium"
    ],
    "wof:name":"Aliage De Lorraine Sa",
    "wof:placetype":"venue"
},
  "geometry": {"coordinates":[5.689955,49.531666],"type":"Point"}
}