{
  "type": "Feature",
  "properties": {
    "iso:country":"FR",
    "sg:address":"6, Rue de Montesquieu, 54000 Nancy",
    "sg:orig_category":"Non-Classified Establishments",
    "sg:phone":"+33 3 83 37 56 40",
    "sg:province":"Lorraine",
    "wof:name":"O.g.m.i. S.a. - Organisation Gestion Management Informatique",
    "wof:placetype":"venue"
},
  "geometry": {"coordinates":[6.185529,48.691315],"type":"Point"}
}