{
  "type": "Feature",
  "properties": {
    "iso:country":"FR",
    "sg:address":"11, Av. L\u00e9onard de Vinci, 63000 Clermont Ferrand",
    "sg:city":"Clermont-Ferrand",
    "sg:orig_category":"Non-Classified Establishments",
    "sg:phone":"+33 4 73 28 50 50",
    "sg:postcode":"63000",
    "sg:province":"Auvergne",
    "wof:name":"Industelec R\u00e9gion Du Centre S.a.",
    "wof:placetype":"venue"
},
  "geometry": {"coordinates":[3.134374,45.764587],"type":"Point"}
}