{
  "type": "Feature",
  "properties": {
    "iso:country":"FR",
    "sg:address":"26 Rue De Cond\u00e9 75006 Paris",
    "sg:classifiers":[
        {
            "category":"Professional",
            "subcategory":"Printing & Photocopies",
            "type":"Services"
        }
    ],
    "sg:phone":"+33 1 55 42 61 90",
    "sg:province":"Ile de France",
    "sg:tags":[
        "publishing"
    ],
    "wof:name":"Mercure France Sa",
    "wof:placetype":"venue"
},
  "geometry": {"coordinates":[2.337771,48.850189],"type":"Point"}
}