{
  "type": "Feature",
  "properties": {
    "iso:country":"FR",
    "sg:address":"18, Rue Grange Dame Rose, 78140 V\u00e9lizy Villacoublay",
    "sg:orig_category":"Unclassifiable Establishments",
    "sg:phone":"+33 1 39 26 10 00",
    "sg:province":"Ile de France",
    "wof:name":"Yokogawa France S.a.",
    "wof:placetype":"venue"
},
  "geometry": {"coordinates":[2.206681,48.784283],"type":"Point"}
}