{
  "type": "Feature",
  "properties": {
    "addr:full":"10 R De Lancry 75010 Paris Ile de France 75010",
    "addr:housenumber":"10 r",
    "addr:postcode":"75010;75010",
    "addr:street":"Lancry",
    "iso:country":"FR",
    "sg:address":"10 R De Lancry 75010 Paris",
    "sg:classifiers":[
        {
            "category":"Manufacturing",
            "subcategory":"Jewelry",
            "type":"Manufacturing & Wholesale Goods"
        }
    ],
    "sg:phone":"+33 1 42 49 11 44",
    "sg:postcode":"75010",
    "sg:province":"Ile de France",
    "sg:tags":[
        "product",
        "miscellaneous",
        "jewellery"
    ],
    "wof:name":"Loifrak",
    "wof:placetype":"venue"
},
  "geometry": {"coordinates":[2.360482,48.869205],"type":"Point"}
}