{
  "type": "Feature",
  "properties": {
    "iso:country":"FR",
    "sg:address":"B.P. 68, 26111 Nyons C\u00e9dex^^21/23, Rue Draye de Meyne, 26110 Nyons",
    "sg:orig_category":"Non-Classified Establishments",
    "sg:phone":"+33 4 75 26 26 21",
    "sg:postcode":"26110",
    "sg:province":"Rhone-Alpes",
    "wof:name":"C.c.i. De La Dr\u00f4me - Chambre De Commerce Et D'industrie De La Dr\u00f4me",
    "wof:placetype":"venue"
},
  "geometry": {"coordinates":[5.010615,44.29884],"type":"Point"}
}