{
  "type": "Feature",
  "properties": {
    "iso:country":"FR",
    "sg:address":"Chemin du Vieux Moulin - ZI",
    "sg:city":"Chelles C\u00e9dex",
    "sg:orig_category":"Non-Classified Establishments",
    "sg:phone":"+33 1 60 08 28 65",
    "sg:postcode":"77506",
    "sg:province":"\u00cele-de-France",
    "wof:name":"Vial Et Compagnie S.a.",
    "wof:placetype":"venue"
},
  "geometry": {"coordinates":[2.59116,48.87809],"type":"Point"}
}