{
  "type": "Feature",
  "properties": {
    "addr:full":"B.P. 11, 79410 Echir\u00e9^^76, Place de l'Eglise, 79410 Echir\u00e9 Poitou-Charentes 79410",
    "addr:postcode":"79410;79410;79410",
    "addr:street":"B.P. 11;Echire\u0301^^76 Place De L'Eglise;Echire\u0301",
    "iso:country":"FR",
    "sg:address":"B.P. 11, 79410 Echir\u00e9^^76, Place de l'Eglise, 79410 Echir\u00e9",
    "sg:orig_category":"Non-Classified Establishments",
    "sg:phone":"+33 5 49 25 70 01",
    "sg:postcode":"79410",
    "sg:province":"Poitou-Charentes",
    "wof:name":"Soci\u00e9t\u00e9 Coop\u00e9rative De Laiterie S.c.a.",
    "wof:placetype":"venue"
},
  "geometry": {"coordinates":[-0.415561,46.391613],"type":"Point"}
}