{
  "type": "Feature",
  "properties": {
    "addr:full":"rue Philippe le Bon 59260 Hellemmes Lille Nord Pas-de-Calais 59260",
    "addr:postcode":"59260;59260",
    "addr:street":"Rue Philippe Le Bon;Hellemmes Lille Nord",
    "iso:country":"FR",
    "sg:address":"rue Philippe le Bon 59260 Hellemmes Lille",
    "sg:classifiers":[
        {
            "category":"Manufacturing",
            "subcategory":"Tools & Machinery",
            "type":"Manufacturing & Wholesale Goods"
        }
    ],
    "sg:phone":"+33 3 20 43 91 40",
    "sg:postcode":"59260",
    "sg:province":"Nord Pas-de-Calais",
    "sg:tags":[
        "industrial",
        "handheld"
    ],
    "wof:name":"Semo Sa",
    "wof:placetype":"venue"
},
  "geometry": {"coordinates":[3.096011,50.628098],"type":"Point"}
}