{
  "type": "Feature",
  "properties": {
    "iso:country":"FR",
    "sg:address":"501 rue de Guigon 83140 Six Fours les Plages",
    "sg:classifiers":[
        {
            "category":"Professional",
            "subcategory":"Management & Consulting",
            "type":"Services"
        }
    ],
    "sg:phone":"+33 4 94 34 45 31",
    "sg:province":"Rhone-Alpes",
    "sg:tags":[
        "software"
    ],
    "wof:name":"Technical Data Systems Sa",
    "wof:placetype":"venue"
},
  "geometry": {"coordinates":[5.835591,43.087788],"type":"Point"}
}