{
  "type": "Feature",
  "properties": {
    "iso:country":"FR",
    "sg:address":"20, Bd Eug\u00e8ne Deruelle, 69003 Lyon",
    "sg:orig_category":"Unclassifiable Establishments",
    "sg:phone":"+33 4 72 60 65 00",
    "sg:province":"Rhone-Alpes",
    "wof:name":"Premi\u00e8re Vision",
    "wof:placetype":"venue"
},
  "geometry": {"coordinates":[4.853865,45.762825],"type":"Point"}
}