{
  "type": "Feature",
  "properties": {
    "iso:country":"FR",
    "sg:address":"3 rue Mas de Banal 34190 ST BAUZILLE DE PUTOIS",
    "sg:classifiers":[
        {
            "category":"Communications",
            "subcategory":"Television Station",
            "type":"Services"
        }
    ],
    "sg:phone":"+33 4 67 73 77 78",
    "sg:postcode":"34190",
    "sg:province":"Languedoc-Roussillon",
    "sg:tags":[
        "device",
        "portable",
        "antenna"
    ],
    "wof:name":"Seegc Espace Antennes S.a.r.l.",
    "wof:placetype":"venue"
},
  "geometry": {"coordinates":[3.739651,43.894688],"type":"Point"}
}