{
  "type": "Feature",
  "properties": {
    "addr:full":"10 Rue Stassin 59552 Courchelettes Nord Pas-de-Calais",
    "addr:housenumber":"10",
    "addr:postcode":"59552",
    "addr:street":"Rue Stassin",
    "iso:country":"FR",
    "sg:address":"10 Rue Stassin 59552 Courchelettes",
    "sg:classifiers":[
        {
            "category":"Manufacturing",
            "subcategory":"Paper Products",
            "type":"Manufacturing & Wholesale Goods"
        }
    ],
    "sg:phone":"+33 3 27 87 22 85",
    "sg:province":"Nord Pas-de-Calais",
    "sg:tags":[
        "raw",
        "material",
        "-",
        "cardboard"
    ],
    "wof:name":"Cordier Pierre",
    "wof:placetype":"venue"
},
  "geometry": {"coordinates":[3.064175,50.341],"type":"Point"}
}