{
  "type": "Feature",
  "properties": {
    "iso:country":"FR",
    "sg:address":"15 Av Baron Lacrosse 29850 Gouesnou",
    "sg:city":"Gouesnou",
    "sg:classifiers":[
        {
            "category":"Manufacturing",
            "subcategory":"Chemicals & Compounds",
            "type":"Manufacturing & Wholesale Goods"
        }
    ],
    "sg:phone":"+33 2 98 02 01 09",
    "sg:postcode":"29850",
    "sg:province":"Bretagne",
    "sg:tags":[
        "pharmaceutical",
        "chemistry",
        "-",
        "by-product"
    ],
    "wof:name":"Gama 29 Sa",
    "wof:placetype":"venue"
},
  "geometry": {"coordinates":[-4.462164,48.430046],"type":"Point"}
}