{
  "type": "Feature",
  "properties": {
    "iso:country":"FR",
    "sg:address":"Rte De Bergerac 24660 Coulounieix Chamiers",
    "sg:city":"Coulounieix-Chamiers",
    "sg:orig_category":"Miscellaneous Products",
    "sg:phone":"+33 5 53 08 07 47",
    "sg:postcode":"24660",
    "sg:province":"Aquitaine",
    "wof:name":"M. Vergnaud Jacques",
    "wof:placetype":"venue"
},
  "geometry": {"coordinates":[0.714495,45.122566],"type":"Point"}
}