{
  "type": "Feature",
  "properties": {
    "iso:country":"FR",
    "sg:address":"Rte D'Etroeungt 59440 Avesnelles",
    "sg:classifiers":[
        {
            "category":"Professional",
            "subcategory":"Engineering",
            "type":"Services"
        }
    ],
    "sg:phone":"+33 3 27 61 16 16",
    "sg:postcode":"59440",
    "sg:province":"Nord Pas-de-Calais",
    "sg:tags":[
        "machine",
        "-",
        "mechanical"
    ],
    "wof:name":"Sadi Sa",
    "wof:placetype":"venue"
},
  "geometry": {"coordinates":[3.94259,50.118931],"type":"Point"}
}