{
  "type": "Feature",
  "properties": {
    "addr:full":"Chemin du Magnon Saint Genix sur Guiers Rhone-Alpes 73240",
    "addr:postcode":"73240",
    "addr:street":"Chemin Du Magnon Saint Genix Sur Guiers Rhone-Alpes",
    "iso:country":"FR",
    "sg:address":"Chemin du Magnon",
    "sg:city":"Saint Genix sur Guiers",
    "sg:orig_category":"Unclassifiable Establishments",
    "sg:phone":"+33 4 76 32 56 85",
    "sg:postcode":"73240",
    "sg:province":"Rhone-Alpes",
    "wof:name":"Prospect Anais Company S.a.r.l.",
    "wof:placetype":"venue"
},
  "geometry": {"coordinates":[5.693824,45.571468],"type":"Point"}
}