{
  "type": "Feature",
  "properties": {
    "addr:full":"ZI Bazinquant Bl\u00e9rancourt Picardie 02300",
    "addr:postcode":"02300",
    "addr:street":"Picardie",
    "iso:country":"FR",
    "sg:address":"ZI Bazinquant",
    "sg:city":"Bl\u00e9rancourt",
    "sg:orig_category":"Unclassifiable Establishments",
    "sg:phone":"+33 3 23 39 61 87",
    "sg:postcode":"02300",
    "sg:province":"Picardie",
    "wof:name":"Gustin Fils Fonderie S.a.",
    "wof:placetype":"venue"
},
  "geometry": {"coordinates":[3.150555,49.51672],"type":"Point"}
}