{
  "type": "Feature",
  "properties": {
    "iso:country":"FR",
    "sg:address":"13, Av. de la Porte d'Italie, 75013 Paris",
    "sg:orig_category":"Non-Classified Establishments",
    "sg:phone":"+33 1 53 61 65 00",
    "sg:postcode":"75013",
    "sg:province":"Ile de France",
    "wof:name":"D.l. Consultant S.a.",
    "wof:placetype":"venue"
},
  "geometry": {"coordinates":[2.35708,48.827366],"type":"Point"}
}