{
  "type": "Feature",
  "properties": {
    "addr:full":"79160 Fenioux Poitou-Charentes",
    "addr:postcode":"79160",
    "addr:street":"Fenioux",
    "iso:country":"FR",
    "sg:address":"79160 Fenioux",
    "sg:orig_category":"Unclassifiable Establishments",
    "sg:phone":"+33 5 49 75 22 06",
    "sg:province":"Poitou-Charentes",
    "wof:name":"Rousseau S.a.",
    "wof:placetype":"venue"
},
  "geometry": {"coordinates":[-0.491842,46.548096],"type":"Point"}
}