{
  "type": "Feature",
  "properties": {
    "addr:full":"26 Chemin Du Moulin Carron Ecully Rhone-Alpes 69130",
    "addr:housenumber":"26",
    "addr:postcode":"69130",
    "addr:street":"Chemin Du Moulin Carron Ecully Rhone-Alpes",
    "iso:country":"FR",
    "sg:address":"26 Chemin Du Moulin Carron",
    "sg:city":"Ecully",
    "sg:classifiers":[
        {
            "category":"Banks & Credit Unions",
            "subcategory":"Financial Services",
            "type":"Services"
        }
    ],
    "sg:phone":"+33 4 72 18 70 00",
    "sg:postcode":"69130",
    "sg:province":"Rhone-Alpes",
    "sg:tags":[
        "banking",
        "finance",
        "insurance"
    ],
    "wof:name":"Expertises Galtier (eg)",
    "wof:placetype":"venue"
},
  "geometry": {"coordinates":[4.776274,45.794659],"type":"Point"}
}