{
  "type": "Feature",
  "properties": {
    "addr:full":"72, Rue des Ch\u00e9neaux, 76520 Ymare Haute Normandie",
    "addr:housenumber":"72",
    "addr:postcode":"76520",
    "addr:street":"Rue Des Che\u0301Neaux;Haute Normandie",
    "iso:country":"FR",
    "sg:address":"72, Rue des Ch\u00e9neaux, 76520 Ymare",
    "sg:orig_category":"Unclassifiable Establishments",
    "sg:phone":"+33 2 35 79 12 29",
    "sg:province":"Haute Normandie",
    "wof:name":"S.n.d. S.a. - Soci\u00e9t\u00e9 Normande De D\u00e9coupage",
    "wof:placetype":"venue"
},
  "geometry": {"coordinates":[1.174413,49.345787],"type":"Point"}
}