{
  "type": "Feature",
  "properties": {
    "iso:country":"FR",
    "sg:address":"Av Robert Schuman 95350 St Brice Sous For\u00eat",
    "sg:classifiers":[
        {
            "category":"Travel",
            "subcategory":"Hotels & Motels",
            "type":"Entertainment"
        }
    ],
    "sg:phone":"+33 1 39 94 33 00",
    "sg:postcode":"95350",
    "sg:province":"Ile de France",
    "sg:tags":[
        "hotels",
        "business",
        "restaurant"
    ],
    "wof:name":"Flunch",
    "wof:placetype":"venue"
},
  "geometry": {"coordinates":[2.35147,49.009109],"type":"Point"}
}