{
  "type": "Feature",
  "properties": {
    "addr:full":"Beaumois 49650 Allonnes Pays de Loire",
    "addr:postcode":"49650",
    "addr:street":"Beaumois",
    "iso:country":"FR",
    "sg:address":"Beaumois 49650 Allonnes",
    "sg:orig_category":"Non-Classified Establishments",
    "sg:phone":"+33 2 41 52 01 18",
    "sg:province":"Pays de Loire",
    "wof:name":"P\u00e9pini\u00e8res Joubert S.a.r.l.",
    "wof:placetype":"venue"
},
  "geometry": {"coordinates":[0.002065,47.270473],"type":"Point"}
}