{
  "type": "Feature",
  "properties": {
    "addr:full":"59 Av Des Mousquetaires 32100 Condom Midi Pyr\u00e9n\u00e9es 32100",
    "addr:postcode":"32100;32100",
    "addr:street":"59 Av Des Mousquetaires",
    "iso:country":"FR",
    "sg:address":"59 Av Des Mousquetaires 32100 Condom",
    "sg:classifiers":[
        {
            "category":"Farming",
            "subcategory":"Livestock Farm",
            "type":"Manufacturing & Wholesale Goods"
        }
    ],
    "sg:phone":"+33 5 62 28 26 77",
    "sg:postcode":"32100",
    "sg:province":"Midi Pyr\u00e9n\u00e9es",
    "sg:tags":[
        "grain",
        "agriculture",
        "cereal"
    ],
    "wof:name":"Terres De Gascognes Sca",
    "wof:placetype":"venue"
},
  "geometry": {"coordinates":[0.3642,43.954136],"type":"Point"}
}