{
  "type": "Feature",
  "properties": {
    "addr:full":"26 Avenue 8 Mai 83570 Carces Poitou-Charentes",
    "addr:housenumber":"26",
    "addr:postcode":"83570",
    "addr:street":"Avenue 8 Mai;Carces",
    "iso:country":"FR",
    "sg:address":"26 Avenue 8 Mai 83570 Carces",
    "sg:classifiers":[
        {
            "category":"Food Court",
            "type":"Food & Drink"
        }
    ],
    "sg:phone":"+33 4 94 04 53 23",
    "sg:province":"Poitou-Charentes",
    "sg:tags":[
        "product",
        "related"
    ],
    "wof:name":"Distillerie Entrepots Et Usines De Languedoc Et Provence (deulep)",
    "wof:placetype":"venue"
},
  "geometry": {"coordinates":[6.125903,43.472431],"type":"Point"}
}