{
  "type": "Feature",
  "properties": {
    "iso:country":"FR",
    "sg:address":"43, Bd Cordier, 02100 Saint Quentin",
    "sg:orig_category":"Unclassifiable Establishments",
    "sg:phone":"+33 3 23 68 19 62",
    "sg:province":"Picardie",
    "wof:name":"Hubau S.a.",
    "wof:placetype":"venue"
},
  "geometry": {"coordinates":[3.296166,49.837276],"type":"Point"}
}