{
  "type": "Feature",
  "properties": {
    "addr:full":"B.P. 2, 81170 Cordes sur Ciel^^Rte d'Albi, 81170 Cordes sur Ciel Midi Pyr\u00e9n\u00e9es",
    "addr:housenumber":"2",
    "addr:postcode":"81170;d'albi 81170",
    "addr:street":"B.P.",
    "iso:country":"FR",
    "sg:address":"B.P. 2, 81170 Cordes sur Ciel^^Rte d'Albi, 81170 Cordes sur Ciel",
    "sg:orig_category":"Non-Classified Establishments",
    "sg:phone":"+33 5 63 56 01 48",
    "sg:province":"Midi Pyr\u00e9n\u00e9es",
    "wof:name":"Rouquette S.a.r.l.",
    "wof:placetype":"venue"
},
  "geometry": {"coordinates":[1.95789,44.062611],"type":"Point"}
}