{
  "type": "Feature",
  "properties": {
    "iso:country":"FR",
    "sg:address":"rue de Larchant 77140 ST PIERRE LES NEMOURS",
    "sg:classifiers":[
        {
            "category":"Manufacturing",
            "subcategory":"Metals",
            "type":"Manufacturing & Wholesale Goods"
        }
    ],
    "sg:phone":"+33 1 64 78 55 55",
    "sg:postcode":"77140",
    "sg:province":"Ile de France",
    "sg:tags":[
        "heavy",
        "plate",
        "sheet",
        "thin",
        "blank"
    ],
    "wof:name":"Ets Piard F\u00e9lix Sa",
    "wof:placetype":"venue"
},
  "geometry": {"coordinates":[2.674745,48.268665],"type":"Point"}
}