{
  "type": "Feature",
  "properties": {
    "addr:full":"10 rue de Soultz 68200 Mulhouse Mulhouse Alsace 68200",
    "addr:housenumber":"10",
    "addr:postcode":"68200;68200",
    "addr:street":"Rue De Soultz",
    "iso:country":"FR",
    "sg:address":"10 rue de Soultz 68200 Mulhouse",
    "sg:city":"Mulhouse",
    "sg:classifiers":[
        {
            "category":"Manufacturing",
            "subcategory":"Tools & Machinery",
            "type":"Manufacturing & Wholesale Goods"
        }
    ],
    "sg:phone":"+33 3 89 62 33 34",
    "sg:postcode":"68200",
    "sg:province":"Alsace",
    "sg:tags":[
        "machine",
        "automation"
    ],
    "wof:name":"Manumeric Sa",
    "wof:placetype":"venue"
},
  "geometry": {"coordinates":[7.323549,47.76535],"type":"Point"}
}