{
  "type": "Feature",
  "properties": {
    "iso:country":"FR",
    "sg:address":"25 Quai Saint-Vincent",
    "sg:city":"Lyon",
    "sg:classifiers":[
        {
            "category":"Banks & Credit Unions",
            "subcategory":"Financial Services",
            "type":"Services"
        }
    ],
    "sg:phone":"+33 4 78 27 43 06",
    "sg:postcode":"69001",
    "sg:province":"Rhone-Alpes",
    "sg:tags":[
        "banking",
        "finance",
        "insurance"
    ],
    "wof:name":"Cabinet Expertise Comptable Cabinet Roche Sa",
    "wof:placetype":"venue"
},
  "geometry": {"coordinates":[4.822258,45.768475],"type":"Point"}
}