{
  "type": "Feature",
  "properties": {
    "addr:full":"B.P. 465, 89104 Sens C\u00e9dex^^2, Rue Saint Paul, 89100 Sens Sens Bourgogne 89100",
    "addr:housenumber":"b.p. 465",
    "addr:postcode":"89104;89100;89100",
    "addr:street":"Rue Saint Paul",
    "iso:country":"FR",
    "sg:address":"B.P. 465, 89104 Sens C\u00e9dex^^2, Rue Saint Paul, 89100 Sens",
    "sg:city":"Sens",
    "sg:orig_category":"Non-Classified Establishments",
    "sg:phone":"+33 3 86 95 83 20",
    "sg:postcode":"89100",
    "sg:province":"Bourgogne",
    "wof:name":"C.a.p.s.",
    "wof:placetype":"venue"
},
  "geometry": {"coordinates":[3.3115,48.150352],"type":"Point"}
}