{
  "type": "Feature",
  "properties": {
    "addr:full":"25, Rue Jean Martin, 68058 Mulhouse C\u00e9dex Alsace",
    "addr:housenumber":"25",
    "addr:postcode":"68058",
    "addr:street":"Rue Jean Martin;Ce\u0301Dex",
    "iso:country":"FR",
    "sg:address":"25, Rue Jean Martin, 68058 Mulhouse C\u00e9dex",
    "sg:orig_category":"Non-Classified Establishments",
    "sg:phone":"+33 3 89 59 66 66",
    "sg:province":"Alsace",
    "wof:name":"Schmerber Industrie Et B\u00e2timent S.a.",
    "wof:placetype":"venue"
},
  "geometry": {"coordinates":[7.307697,47.75375],"type":"Point"}
}