{
  "type": "Feature",
  "properties": {
    "addr:full":"Impasse Lavoisier - ZI de l'Echangeur Gresy sur Aix Rhone-Alpes 73100",
    "addr:postcode":"73100",
    "addr:street":"Impasse Lavoisier Zi De L'Echangeur Gresy",
    "iso:country":"FR",
    "sg:address":"Impasse Lavoisier - ZI de l'Echangeur",
    "sg:city":"Gresy sur Aix",
    "sg:orig_category":"Non-Classified Establishments",
    "sg:phone":"+33 4 76 61 16 14",
    "sg:postcode":"73100",
    "sg:province":"Rhone-Alpes",
    "wof:name":"L.m.s. S.a.r.l.",
    "wof:placetype":"venue"
},
  "geometry": {"coordinates":[5.922803,45.716892],"type":"Point"}
}