{
  "type": "Feature",
  "properties": {
    "iso:country":"FR",
    "sg:address":"64160 Sedzere",
    "sg:city":"Sedz\u00e8re",
    "sg:classifiers":[
        {
            "category":"Food & Beverages",
            "subcategory":"Groceries & Convenience Stores",
            "type":"Retail Goods"
        }
    ],
    "sg:phone":"+33 5 59 68 47 10",
    "sg:postcode":"64160",
    "sg:province":"Aquitaine",
    "sg:tags":[
        "product",
        "related"
    ],
    "wof:name":"Soconal",
    "wof:placetype":"venue"
},
  "geometry": {"coordinates":[-0.173225,43.339767],"type":"Point"}
}