{
  "type": "Feature",
  "properties": {
    "iso:country":"FR",
    "sg:address":"B.P. 9, 74131 Bonneville C\u00e9dex^^ZI d'Ayze, 74130 Bonneville",
    "sg:orig_category":"Non-Classified Establishments",
    "sg:phone":"+33 4 50 97 59 75",
    "sg:province":"Rhone-Alpes",
    "wof:name":"S.i.d.e.r. S.a.s.",
    "wof:placetype":"venue"
},
  "geometry": {"coordinates":[6.433218,46.070869],"type":"Point"}
}