{
  "type": "Feature",
  "properties": {
    "iso:country":"FR",
    "sg:address":"929 ave du G\u00e9n\u00e9ral de Gaulle; S. Laurent",
    "sg:classifiers":[
        {
            "category":"Banks & Credit Unions",
            "subcategory":"Bank",
            "type":"Services"
        }
    ],
    "sg:phone":"+33 3393312149",
    "sg:province":"Champagne",
    "wof:name":"Banque Nationale De Paris",
    "wof:placetype":"venue"
},
  "geometry": {"coordinates":[-54.028851,5.49691],"type":"Point"}
}