{
  "type": "Feature",
  "properties": {
    "iso:country":"FR",
    "sg:address":"19, Rte de Brumath, 67550 Vendenheim",
    "sg:city":"Vendenheim",
    "sg:orig_category":"Unclassifiable Establishments",
    "sg:phone":"+33 3 88 69 40 39",
    "sg:postcode":"67550",
    "sg:province":"Alsace",
    "wof:name":"Pyrmo Chimie France S.a.r.l.",
    "wof:placetype":"venue"
},
  "geometry": {"coordinates":[7.717862,48.6735],"type":"Point"}
}