{
  "type": "Feature",
  "properties": {
    "addr:full":"5, Impasse des Hauts Fourneaux, 57100 Thionville Lorraine",
    "addr:housenumber":"5",
    "addr:postcode":"57100",
    "addr:street":"Impasse Des Hauts Fourneaux",
    "iso:country":"FR",
    "sg:address":"5, Impasse des Hauts Fourneaux, 57100 Thionville",
    "sg:orig_category":"Unclassifiable Establishments",
    "sg:phone":"+33 3 82 88 22 90",
    "sg:province":"Lorraine",
    "wof:name":"Micropolluants Technologie S.a.",
    "wof:placetype":"venue"
},
  "geometry": {"coordinates":[6.159755,49.343441],"type":"Point"}
}