{
  "type": "Feature",
  "properties": {
    "addr:full":"24, Rte de Fort Mardyck, 59430 Saint Pol sur Mer Nord Pas-de-Calais",
    "addr:housenumber":"24",
    "addr:postcode":"59430",
    "addr:street":"Rte De Fort",
    "iso:country":"FR",
    "sg:address":"24, Rte de Fort Mardyck, 59430 Saint Pol sur Mer",
    "sg:orig_category":"Unclassifiable Establishments",
    "sg:phone":"+33 3 28 26 73 73",
    "sg:province":"Nord Pas-de-Calais",
    "wof:name":"Cegelec S.a.",
    "wof:placetype":"venue"
},
  "geometry": {"coordinates":[2.34198,51.027256],"type":"Point"}
}