{
  "type": "Feature",
  "properties": {
    "iso:country":"FR",
    "sg:address":"Av Antoine Pinay - ZAC des 4 Vents",
    "sg:city":"Hem",
    "sg:orig_category":"Unclassifiable Establishments",
    "sg:phone":"+33 3 20 83 28 44",
    "sg:postcode":"59510",
    "sg:province":"Nord Pas-de-Calais",
    "wof:name":"Climelec S.a.r.l.",
    "wof:placetype":"venue"
},
  "geometry": {"coordinates":[3.184105,50.653839],"type":"Point"}
}