{
  "type": "Feature",
  "properties": {
    "iso:country":"FR",
    "sg:address":"Rue Braie - Domaine de l'Abbaye Rivi\u00e8re - Le Repos Saint Martin",
    "sg:city":"Rivi\u00e8re",
    "sg:orig_category":"Non-Classified Establishments",
    "sg:phone":"+33 2 47 40 99 93",
    "sg:postcode":"37500",
    "sg:province":"Centre",
    "wof:name":"Fontaine S.a.r.l.",
    "wof:placetype":"venue"
},
  "geometry": {"coordinates":[0.205005,47.172779],"type":"Point"}
}