{
  "type": "Feature",
  "properties": {
    "addr:full":"1, Rue des Fr\u00e8res Lumi\u00e8re, 69680 Chassieu Rhone-Alpes 69680",
    "addr:housenumber":"1",
    "addr:postcode":"69680;69680",
    "addr:street":"Rue Des Fre\u0300Res Lumie\u0300Re",
    "iso:country":"FR",
    "sg:address":"1, Rue des Fr\u00e8res Lumi\u00e8re, 69680 Chassieu",
    "sg:orig_category":"Non-Classified Establishments",
    "sg:phone":"+33 4 78 90 39 53",
    "sg:postcode":"69680",
    "sg:province":"Rhone-Alpes",
    "wof:name":"Erdem S.a.",
    "wof:placetype":"venue"
},
  "geometry": {"coordinates":[4.962751,45.730148],"type":"Point"}
}