{
  "type": "Feature",
  "properties": {
    "addr:full":"159-163 Bd Brune 75014 Paris Ile de France 75014",
    "addr:postcode":"159-163;75014;75014",
    "addr:street":"Bd Brune",
    "iso:country":"FR",
    "sg:address":"159-163 Bd Brune 75014 Paris",
    "sg:classifiers":[
        {
            "category":"Banks & Credit Unions",
            "subcategory":"Investment Brokerage",
            "type":"Services"
        }
    ],
    "sg:phone":"+33 1 40 52 28 90",
    "sg:postcode":"75014",
    "sg:province":"Ile de France",
    "sg:tags":[
        "finance",
        "institution",
        "banking",
        "road",
        "insurance",
        "transport"
    ],
    "wof:name":"Franceval Sa",
    "wof:placetype":"venue"
},
  "geometry": {"coordinates":[2.321073,48.824364],"type":"Point"}
}