{
  "type": "Feature",
  "properties": {
    "addr:full":"28, Rue Eug\u00e8ne Millon, 75015 Paris Ile de France",
    "addr:housenumber":"28",
    "addr:postcode":"75015",
    "addr:street":"Rue Euge\u0300Ne Millon",
    "iso:country":"FR",
    "sg:address":"28, Rue Eug\u00e8ne Millon, 75015 Paris",
    "sg:orig_category":"Unclassifiable Establishments",
    "sg:phone":"+33 1 45 33 32 45",
    "sg:province":"Ile de France",
    "wof:name":"Scope S.a.",
    "wof:placetype":"venue"
},
  "geometry": {"coordinates":[2.292045,48.837582],"type":"Point"}
}