{
  "type": "Feature",
  "properties": {
    "iso:country":"FR",
    "sg:address":"37, Rue Faidherbe, 59800 Lille",
    "sg:orig_category":"Non-Classified Establishments",
    "sg:phone":"+33 3 20 55 02 22",
    "sg:province":"Nord Pas-de-Calais",
    "wof:name":"Fichet Centre S\u00e9curit\u00e9",
    "wof:placetype":"venue"
},
  "geometry": {"coordinates":[3.066439,50.637123],"type":"Point"}
}