{
  "type": "Feature",
  "properties": {
    "addr:full":"B.P. 7143, 95055 Cergy C\u00e9dex^^82, Av. du Ch\u00e2teau - ZI du Vert Galant, 95310 Saint Ouen l'Aum\u00f4ne Ile de France 95310",
    "addr:postcode":"95055;95310;95310",
    "addr:street":"B.P. 7143;Av. Du Cha\u0302Teau Zi Du Vert Galant",
    "iso:country":"FR",
    "sg:address":"B.P. 7143, 95055 Cergy C\u00e9dex^^82, Av. du Ch\u00e2teau - ZI du Vert Galant, 95310 Saint Ouen l'Aum\u00f4ne",
    "sg:orig_category":"Non-Classified Establishments",
    "sg:phone":"+33 1 30 37 62 60",
    "sg:postcode":"95310",
    "sg:province":"Ile de France",
    "wof:name":"Adiva E.u.r.l.",
    "wof:placetype":"venue"
},
  "geometry": {"coordinates":[2.136835,49.055286],"type":"Point"}
}