{
  "type": "Feature",
  "properties": {
    "iso:country":"FR",
    "sg:address":"17, Rue de Bellevue, 35260 Cancale",
    "sg:city":"Cancale",
    "sg:orig_category":"Unclassifiable Establishments",
    "sg:phone":"+33 2 99 89 61 74",
    "sg:postcode":"35260",
    "sg:province":"Bretagne",
    "wof:name":"Froc S.a.",
    "wof:placetype":"venue"
},
  "geometry": {"coordinates":[-1.849784,48.675598],"type":"Point"}
}