{
  "type": "Feature",
  "properties": {
    "addr:full":"B.P. 733, 61042 Alen\u00e7on C\u00e9dex^^Parc d'Activit\u00e9 du Londeau, 61000 Ceris\u00e9 Ceris\u00e9 Basse Normandie 61000",
    "addr:housenumber":"b.p. 733",
    "addr:postcode":"61042;61000;61000",
    "addr:street":"Londeau",
    "iso:country":"FR",
    "sg:address":"B.P. 733, 61042 Alen\u00e7on C\u00e9dex^^Parc d'Activit\u00e9 du Londeau, 61000 Ceris\u00e9",
    "sg:city":"Ceris\u00e9",
    "sg:orig_category":"Non-Classified Establishments",
    "sg:phone":"+33 2 33 29 62 62",
    "sg:postcode":"61000",
    "sg:province":"Basse Normandie",
    "wof:name":"Sonormat Location S.a.s.",
    "wof:placetype":"venue"
},
  "geometry": {"coordinates":[0.129535,48.442451],"type":"Point"}
}