{
  "type": "Feature",
  "properties": {
    "addr:full":"Les Onze Mille Vierges Aubenas Rhone-Alpes 07200",
    "addr:postcode":"07200",
    "iso:country":"FR",
    "sg:address":"Les Onze Mille Vierges",
    "sg:city":"Aubenas",
    "sg:orig_category":"Unclassifiable Establishments",
    "sg:phone":"+33 4 75 89 97 80",
    "sg:postcode":"07200",
    "sg:province":"Rhone-Alpes",
    "wof:name":"Augidier S.a.",
    "wof:placetype":"venue"
},
  "geometry": {"coordinates":[4.39417,44.613239],"type":"Point"}
}