{
  "type": "Feature",
  "properties": {
    "iso:country":"FR",
    "sg:address":"Route D Herbeauvilliers 77760 Amponville",
    "sg:classifiers":[
        {
            "category":"Manufacturing",
            "subcategory":"Metals",
            "type":"Manufacturing & Wholesale Goods"
        }
    ],
    "sg:phone":"+33 1 64 24 34 91",
    "sg:postcode":"77760",
    "sg:province":"Ile de France",
    "sg:tags":[
        "-",
        "machine",
        "equipment",
        "engineering",
        "machinery",
        "mechanical"
    ],
    "wof:name":"Precision Profils",
    "wof:placetype":"venue"
},
  "geometry": {"coordinates":[2.530113,48.281155],"type":"Point"}
}