{
  "type": "Feature",
  "properties": {
    "iso:country":"FR",
    "sg:address":"93, Av. du Mar\u00e9chal Delattre de Tassigny - Le Pouverel , 83130 La Garde",
    "sg:city":"Assigny",
    "sg:orig_category":"Unclassifiable Establishments",
    "sg:phone":"+33 4 94 75 96 10",
    "sg:postcode":"18260",
    "sg:province":"Centre",
    "wof:name":"Pianelli S. A.",
    "wof:placetype":"venue"
},
  "geometry": {"coordinates":[5.985217,43.11528],"type":"Point"}
}