{
  "type": "Feature",
  "properties": {
    "addr:full":"65, All\u00e9e des Pommiers, 74330 Poisy Rhone-Alpes 74330",
    "addr:housenumber":"65",
    "addr:postcode":"74330;74330",
    "addr:street":"Alle\u0301E Des Pommiers;Rhone-Alpes",
    "iso:country":"FR",
    "sg:address":"65, All\u00e9e des Pommiers, 74330 Poisy",
    "sg:orig_category":"Non-Classified Establishments",
    "sg:phone":"+33 4 50 46 23 06",
    "sg:postcode":"74330",
    "sg:province":"Rhone-Alpes",
    "wof:name":"B2d Conseil S.a.r.l.",
    "wof:placetype":"venue"
},
  "geometry": {"coordinates":[6.064635,45.921398],"type":"Point"}
}