{
  "type": "Feature",
  "properties": {
    "addr:full":"13, Mas de Baumani\u00e8re, 13520 Les Baux de Provence",
    "addr:housenumber":"13",
    "addr:postcode":"13520",
    "addr:street":"Mas De Baumanie\u0300Re",
    "iso:country":"FR",
    "sg:address":"13, Mas de Baumani\u00e8re, 13520 Les Baux de Provence",
    "sg:orig_category":"Non-Classified Establishments",
    "sg:phone":"+33 4 90 54 56 54",
    "wof:name":"Relais Et Ch\u00e2teaux S.a.",
    "wof:placetype":"venue"
},
  "geometry": {"coordinates":[4.808531,43.720318],"type":"Point"}
}