{
  "type": "Feature",
  "properties": {
    "addr:full":"B.P. 50306, 93940 Roissy Charles de Gaulle C\u00e9dex^^22, Av. des Nations, 93420 Villepinte Ile de France",
    "addr:postcode":"93940;93420",
    "addr:street":"Av. Des Nations;Ile De France",
    "iso:country":"FR",
    "sg:address":"B.P. 50306, 93940 Roissy Charles de Gaulle C\u00e9dex^^22, Av. des Nations, 93420 Villepinte",
    "sg:orig_category":"Non-Classified Establishments",
    "sg:phone":"+33 1 49 90 75 00",
    "sg:province":"Ile de France",
    "wof:name":"Ophtalmic - B. Et T. S.a.",
    "wof:placetype":"venue"
},
  "geometry": {"coordinates":[2.53979,48.955807],"type":"Point"}
}