{
  "type": "Feature",
  "properties": {
    "addr:full":"9 Av Henri Matisse 06200 Nice Champagne",
    "addr:postcode":"06200",
    "addr:street":"Av Henri Matisse",
    "iso:country":"FR",
    "sg:address":"9 Av Henri Matisse 06200 Nice",
    "sg:classifiers":[
        {
            "category":"Manufacturing",
            "subcategory":"Printing",
            "type":"Manufacturing & Wholesale Goods"
        }
    ],
    "sg:phone":"+33 4 92 29 25 00",
    "sg:province":"Champagne",
    "sg:tags":[
        "publishing"
    ],
    "wof:name":"Megapom",
    "wof:placetype":"venue"
},
  "geometry": {"coordinates":[7.220183,43.674248],"type":"Point"}
}