{
  "type": "Feature",
  "properties": {
    "addr:full":"5 place du Colonel Fabien 75010 Paris Ile de France",
    "addr:housenumber":"5",
    "addr:postcode":"75010",
    "addr:street":"Place Du Colonel Fabien",
    "iso:country":"FR",
    "sg:address":"5 place du Colonel Fabien 75010 Paris",
    "sg:classifiers":[
        {
            "category":"Farming",
            "subcategory":"Fish & Marine Products",
            "type":"Manufacturing & Wholesale Goods"
        }
    ],
    "sg:phone":"+33 1 42 40 35 35",
    "sg:province":"Ile de France",
    "sg:tags":[
        "management",
        "software"
    ],
    "wof:name":"Praxiel Sa",
    "wof:placetype":"venue"
},
  "geometry": {"coordinates":[2.369885,48.877754],"type":"Point"}
}