{
  "type": "Feature",
  "properties": {
    "addr:full":"32 Rue Du 22 Novembre Strasbourg Alsace 67000",
    "addr:housenumber":"32",
    "addr:postcode":"67000",
    "addr:street":"Rue Du 22 Novembre Strasbourg",
    "iso:country":"FR",
    "sg:address":"32 Rue Du 22 Novembre",
    "sg:city":"Strasbourg",
    "sg:classifiers":[
        {
            "category":"Banks & Credit Unions",
            "subcategory":"Financial Services",
            "type":"Services"
        }
    ],
    "sg:phone":"+33 3 88 32 50 01",
    "sg:postcode":"67000",
    "sg:province":"Alsace",
    "sg:tags":[
        "banking",
        "finance",
        "insurance"
    ],
    "wof:name":"Fiduciaire Alsec Sarl",
    "wof:placetype":"venue"
},
  "geometry": {"coordinates":[7.744835,48.582523],"type":"Point"}
}