{
  "type": "Feature",
  "properties": {
    "addr:full":"ZI la Chevallerie Saint L\u00f4 Basse Normandie 50000",
    "addr:postcode":"50000",
    "addr:street":"Zi La Chevallerie Saint;Basse",
    "iso:country":"FR",
    "sg:address":"ZI la Chevallerie",
    "sg:city":"Saint L\u00f4",
    "sg:orig_category":"Unclassifiable Establishments",
    "sg:phone":"+33 2 33 77 15 00",
    "sg:postcode":"50000",
    "sg:province":"Basse Normandie",
    "wof:name":"S.i.a.l. S.a. - Soci\u00e9t\u00e9 D'impression D'arts Le Rachinel",
    "wof:placetype":"venue"
},
  "geometry": {"coordinates":[-1.090344,49.115974],"type":"Point"}
}