{
  "type": "Feature",
  "properties": {
    "addr:full":"All\u00e9e des Ch\u00eanes - Zone Industrielle la Voivre Epinal Lorraine 88000",
    "addr:postcode":"88000",
    "addr:street":"Alle\u0301E Des Che\u0302Nes Zone Industrielle La Voivre",
    "iso:country":"FR",
    "sg:address":"All\u00e9e des Ch\u00eanes - Zone Industrielle la Voivre",
    "sg:city":"Epinal",
    "sg:orig_category":"Non-Classified Establishments",
    "sg:phone":"+33 3 29 68 40 40",
    "sg:postcode":"88000",
    "sg:province":"Lorraine",
    "wof:name":"G.e.d. Miller Poirot S.a.s.",
    "wof:placetype":"venue"
},
  "geometry": {"coordinates":[6.4497,48.175686],"type":"Point"}
}