{
  "type": "Feature",
  "properties": {
    "addr:full":"51 Rue Fran\u00e7ois Premier; Paris; 75008 Ile de France",
    "addr:housenumber":"51",
    "addr:postcode":"75008",
    "addr:street":"Rue Franc\u0327Ois Premier Paris",
    "iso:country":"FR",
    "sg:address":"51 Rue Fran\u00e7ois Premier; Paris; 75008",
    "sg:classifiers":[
        {
            "category":"Industrial Area",
            "type":"Public Place"
        }
    ],
    "sg:phone":"+33 1 40 74 60 60",
    "sg:province":"Ile de France",
    "sg:tags":[
        "large",
        "private"
    ],
    "wof:name":"Cartier Sa",
    "wof:placetype":"venue"
},
  "geometry": {"coordinates":[2.302274,48.86937],"type":"Point"}
}