{
  "type": "Feature",
  "properties": {
    "addr:full":"Le Bois des Drailles 88370 Bellefontaine Lorraine",
    "addr:postcode":"88370",
    "addr:street":"Bois Des Drailles",
    "iso:country":"FR",
    "sg:address":"Le Bois des Drailles 88370 Bellefontaine",
    "sg:orig_category":"Non-Classified Establishments",
    "sg:phone":"+33 3 29 30 17 00",
    "sg:province":"Lorraine",
    "wof:name":"S.a.f. S.a.r.l. - Soci\u00e9t\u00e9 Artisanale Du Fer - Sidre Fr\u00e8res",
    "wof:placetype":"venue"
},
  "geometry": {"coordinates":[6.461149,47.966366],"type":"Point"}
}