{
  "type": "Feature",
  "properties": {
    "iso:country":"FR",
    "sg:address":"27 Rue Des Dats 51520 St Martin Sur Le Pre",
    "sg:classifiers":[
        {
            "category":"Manufacturing",
            "subcategory":"Rubber & Plastics",
            "type":"Manufacturing & Wholesale Goods"
        }
    ],
    "sg:phone":"+33 3 26 65 31 31",
    "sg:province":"Champagne",
    "sg:tags":[
        "packaging",
        "material",
        "-"
    ],
    "wof:name":"Perichard Plastiques",
    "wof:placetype":"venue"
},
  "geometry": {"coordinates":[4.343006,48.976791],"type":"Point"}
}