{
  "type": "Feature",
  "properties": {
    "iso:country":"FR",
    "sg:address":"B.P. 38",
    "sg:city":"Kembs",
    "sg:orig_category":"Non-Classified Establishments",
    "sg:phone":"+33 3 89 48 40 33",
    "sg:postcode":"68680",
    "sg:province":"Alsace",
    "wof:name":"France Fixations S.a.r.l.",
    "wof:placetype":"venue"
},
  "geometry": {"coordinates":[7.503995,47.687706],"type":"Point"}
}