{
  "type": "Feature",
  "properties": {
    "iso:country":"FR",
    "sg:address":"13, Rue des Essios - ZA les Cray\u00e8res, 51430 Bezannes",
    "sg:orig_category":"Non-Classified Establishments",
    "sg:phone":"+33 3 26 49 94 71",
    "sg:postcode":"51430",
    "sg:province":"Champagne",
    "wof:name":"Camib S.a.",
    "wof:placetype":"venue"
},
  "geometry": {"coordinates":[3.989495,49.250576],"type":"Point"}
}