{
  "type": "Feature",
  "properties": {
    "addr:full":"B.P. 12, 35560 Antrain^^Rte de Rennes - Saint Laurent , 35560 Antrain Antrain Bretagne 35560",
    "addr:postcode":"35560;35560;35560",
    "addr:street":"B.P. 12;Antrain",
    "iso:country":"FR",
    "sg:address":"B.P. 12, 35560 Antrain^^Rte de Rennes - Saint Laurent , 35560 Antrain",
    "sg:city":"Antrain",
    "sg:orig_category":"Non-Classified Establishments",
    "sg:phone":"+33 2 99 98 31 01",
    "sg:postcode":"35560",
    "sg:province":"Bretagne",
    "wof:name":"Brient Jean S.a.",
    "wof:placetype":"venue"
},
  "geometry": {"coordinates":[-1.570554,48.368214],"type":"Point"}
}