{
  "type": "Feature",
  "properties": {
    "addr:full":"B.P. 331, 07003 Privas C\u00e9dex^^Place d'Onclaire-Coux, 07000 Coux Rhone-Alpes 07000",
    "addr:housenumber":"b.p. 331",
    "addr:postcode":"07003;07000;07000",
    "addr:street":"D'Onclaire-Coux",
    "iso:country":"FR",
    "sg:address":"B.P. 331, 07003 Privas C\u00e9dex^^Place d'Onclaire-Coux, 07000 Coux",
    "sg:orig_category":"Non-Classified Establishments",
    "sg:phone":"+33 4 75 64 18 60",
    "sg:postcode":"07000",
    "sg:province":"Rhone-Alpes",
    "wof:name":"Cevenole S.a.r.l.",
    "wof:placetype":"venue"
},
  "geometry": {"coordinates":[4.65211,44.705601],"type":"Point"}
}