{
  "type": "Feature",
  "properties": {
    "addr:full":"Rte de Saverne Steinbourg Alsace 67790",
    "addr:postcode":"67790",
    "addr:street":"Rte De Saverne",
    "iso:country":"FR",
    "sg:address":"Rte de Saverne",
    "sg:city":"Steinbourg",
    "sg:orig_category":"Unclassifiable Establishments",
    "sg:phone":"+33 3 88 71 80 33",
    "sg:postcode":"67790",
    "sg:province":"Alsace",
    "wof:name":"Menuiserie Jung",
    "wof:placetype":"venue"
},
  "geometry": {"coordinates":[7.405775,48.75856],"type":"Point"}
}