{
  "type": "Feature",
  "properties": {
    "addr:full":"42, Rue du Mal Leclerc, 58200 Cosne Cours sur Loire Cosne-Cours-sur-Loire Bourgogne 58200",
    "addr:housenumber":"42",
    "addr:postcode":"58200;58200",
    "addr:street":"Rue Du Mal Leclerc",
    "iso:country":"FR",
    "sg:address":"42, Rue du Mal Leclerc, 58200 Cosne Cours sur Loire",
    "sg:city":"Cosne-Cours-sur-Loire",
    "sg:orig_category":"Unclassifiable Establishments",
    "sg:phone":"+33 3 86 28 20 51",
    "sg:postcode":"58200",
    "sg:province":"Bourgogne",
    "wof:name":"Raisonnier Sylvette S.a.r.l.",
    "wof:placetype":"venue"
},
  "geometry": {"coordinates":[2.925907,47.41341],"type":"Point"}
}