{
  "type": "Feature",
  "properties": {
    "addr:full":"Rue Ren\u00e9 Cassin - ZI Tarbes Nord Bord\u00e8res sur l'Echez Midi Pyr\u00e9n\u00e9es 65320",
    "addr:postcode":"65320",
    "addr:street":"Rue Rene\u0301 Cassin",
    "iso:country":"FR",
    "sg:address":"Rue Ren\u00e9 Cassin - ZI Tarbes Nord",
    "sg:city":"Bord\u00e8res sur l'Echez",
    "sg:orig_category":"Unclassifiable Establishments",
    "sg:phone":"+33 5 62 37 10 52",
    "sg:postcode":"65320",
    "sg:province":"Midi Pyr\u00e9n\u00e9es",
    "wof:name":"Bmv Echafaudage S.a.r.l.",
    "wof:placetype":"venue"
},
  "geometry": {"coordinates":[0.056381,43.260227],"type":"Point"}
}