{
  "type": "Feature",
  "properties": {
    "addr:full":"73 Rue Jacquemars Gi\u00e8l\u00e9e 59800 Lille Nord Pas-de-Calais 59800",
    "addr:housenumber":"73",
    "addr:postcode":"59800;59800",
    "addr:street":"Rue Jacquemars Gie\u0300Le\u0301E",
    "iso:country":"FR",
    "sg:address":"73 Rue Jacquemars Gi\u00e8l\u00e9e 59800 Lille",
    "sg:classifiers":[
        {
            "category":"Wholesale",
            "subcategory":"Medical Equipment & Supplies",
            "type":"Manufacturing & Wholesale Goods"
        }
    ],
    "sg:phone":"+33 3 20 57 07 19",
    "sg:postcode":"59800",
    "sg:province":"Nord Pas-de-Calais",
    "sg:tags":[
        "instrument",
        "health",
        "-",
        "precision"
    ],
    "wof:name":"Carmaver Scm",
    "wof:placetype":"venue"
},
  "geometry": {"coordinates":[3.055745,50.633411],"type":"Point"}
}