{
  "type": "Feature",
  "properties": {
    "addr:full":"126 Rue Marietton 69130 Ecully Rhone-Alpes 69130",
    "addr:housenumber":"126",
    "addr:postcode":"69130;69130",
    "addr:street":"Rue Marietton;Rhone-Alpes",
    "iso:country":"FR",
    "sg:address":"126 Rue Marietton 69130 Ecully",
    "sg:classifiers":[
        {
            "category":"Home & Garden",
            "subcategory":"Furniture",
            "type":"Retail Goods"
        }
    ],
    "sg:phone":"+33 4 78 83 79 07",
    "sg:postcode":"69130",
    "sg:province":"Rhone-Alpes",
    "sg:tags":[
        "household",
        "wood"
    ],
    "wof:name":"Etablissements Favrot",
    "wof:placetype":"venue"
},
  "geometry": {"coordinates":[4.794308,45.775288],"type":"Point"}
}