{
  "type": "Feature",
  "properties": {
    "addr:full":"6, Rue Charles Desgranges - Z.I. du Grand Bois, 57200 Sarreguemines Lorraine 57200",
    "addr:housenumber":"6",
    "addr:postcode":"57200;57200",
    "addr:street":"Rue Charles Desgranges Z.I. Du Grand Bois",
    "iso:country":"FR",
    "sg:address":"6, Rue Charles Desgranges - Z.I. du Grand Bois, 57200 Sarreguemines",
    "sg:orig_category":"IMPORTATEUR: COMMERCIALISATION D'UN SYST\u00c8ME DE CHAUFFAGE ET DE RAFRA\u00ceCHISSEMENT PAR LE SOL DESTIN\u00c9 A",
    "sg:phone":"+33 3 87 98 69 11",
    "sg:postcode":"57200",
    "sg:province":"Lorraine",
    "wof:name":"Multib\u00e9ton France S.a.",
    "wof:placetype":"venue"
},
  "geometry": {"coordinates":[7.070569,49.108246],"type":"Point"}
}