{
  "type": "Feature",
  "properties": {
    "addr:full":"La Rochelle 17180 PERIGNY Poitou-Charentes",
    "addr:postcode":"17180 perigny",
    "addr:street":"La",
    "iso:country":"FR",
    "sg:address":"La Rochelle 17180 PERIGNY",
    "sg:classifiers":[
        {
            "category":"Recreation",
            "subcategory":"Sailing Club",
            "type":"Entertainment"
        }
    ],
    "sg:phone":"+33 5 46 44 17 31",
    "sg:province":"Poitou-Charentes",
    "sg:tags":[
        "ship"
    ],
    "wof:name":"Chantiers Amel S.a.",
    "wof:placetype":"venue"
},
  "geometry": {"coordinates":[-1.07994,46.155918],"type":"Point"}
}