{
  "type": "Feature",
  "properties": {
    "addr:full":"3 Av La Gardette 33560 Carbon Blanc Carbon-Blanc Aquitaine 33560",
    "addr:postcode":"33560;33560",
    "addr:street":"Av La Gardette;Blanc",
    "iso:country":"FR",
    "sg:address":"3 Av La Gardette 33560 Carbon Blanc",
    "sg:city":"Carbon-Blanc",
    "sg:classifiers":[
        {
            "category":"Food & Beverages",
            "subcategory":"Fruits & Vegetables",
            "type":"Retail Goods"
        }
    ],
    "sg:phone":"+33 5 56 31 70 56",
    "sg:postcode":"33560",
    "sg:province":"Aquitaine",
    "sg:tags":[
        "frozen",
        "product",
        "related"
    ],
    "wof:name":"Frigor Sa",
    "wof:placetype":"venue"
},
  "geometry": {"coordinates":[-0.510354,44.886227],"type":"Point"}
}