{
  "type": "Feature",
  "properties": {
    "addr:full":"61550 Gauville Gauville Basse Normandie 61550",
    "addr:postcode":"61550;61550",
    "iso:country":"FR",
    "sg:address":"61550 Gauville",
    "sg:city":"Gauville",
    "sg:orig_category":"Unclassifiable Establishments",
    "sg:phone":"+33 2 33 84 12 50",
    "sg:postcode":"61550",
    "sg:province":"Basse Normandie",
    "wof:name":"Sapl S.a.",
    "wof:placetype":"venue"
},
  "geometry": {"coordinates":[0.55376,48.828964],"type":"Point"}
}