{
  "type": "Feature",
  "properties": {
    "iso:country":"FR",
    "sg:address":"Cre Commercial Les 3 Fonta Lotissement 2107 Niveau 48 95003 Cergy Comptoise",
    "sg:classifiers":[
        {
            "category":"Manufacturing",
            "subcategory":"Jewelry",
            "type":"Manufacturing & Wholesale Goods"
        }
    ],
    "sg:phone":"+33 1 30 75 28 10",
    "sg:province":"Ile de France",
    "sg:tags":[
        "product",
        "miscellaneous",
        "jewellery"
    ],
    "wof:name":"Histoire D'or",
    "wof:placetype":"venue"
},
  "geometry": {"coordinates":[2.03861,49.052551],"type":"Point"}
}