{
  "type": "Feature",
  "properties": {
    "addr:full":"315, Rue de la Croix des Rosiers - Le Cathare, 34070 Montpellier C\u00e9dex Languedoc-Roussillon",
    "addr:housenumber":"315",
    "addr:postcode":"34070;ce\u0301dex",
    "addr:street":"Rue De La Croix Des Rosiers Le Cathare",
    "iso:country":"FR",
    "sg:address":"315, Rue de la Croix des Rosiers - Le Cathare, 34070 Montpellier C\u00e9dex",
    "sg:orig_category":"Non-Classified Establishments",
    "sg:phone":"+33 4 67 75 24 13",
    "sg:province":"Languedoc-Roussillon",
    "wof:name":"Protechnic S.a.r.l.",
    "wof:placetype":"venue"
},
  "geometry": {"coordinates":[3.84676,43.591499],"type":"Point"}
}