{
  "type": "Feature",
  "properties": {
    "addr:full":"B.P. 23, 62701 Bruay la Buissi\u00e8re C\u00e9dex^^Place Henri Cadot, 62700 Bruay la Buissi\u00e8re Nord Pas-de-Calais",
    "addr:postcode":"62701;62700",
    "addr:street":"B.P. 23;Henri Cadot",
    "iso:country":"FR",
    "sg:address":"B.P. 23, 62701 Bruay la Buissi\u00e8re C\u00e9dex^^Place Henri Cadot, 62700 Bruay la Buissi\u00e8re",
    "sg:orig_category":"Non-Classified Establishments",
    "sg:phone":"+33 3 21 64 56 00",
    "sg:province":"Nord Pas-de-Calais",
    "wof:name":"Mairie De Bruay La Buissi\u00e8re",
    "wof:placetype":"venue"
},
  "geometry": {"coordinates":[2.545135,50.482071],"type":"Point"}
}