{
  "type": "Feature",
  "properties": {
    "addr:full":"53, Rue de Claye, 77990 Le Mesnil Amelot Ile de France",
    "addr:housenumber":"53",
    "addr:postcode":"77990;ile",
    "addr:street":"Rue De Claye",
    "iso:country":"FR",
    "sg:address":"53, Rue de Claye, 77990 Le Mesnil Amelot",
    "sg:orig_category":"Non-Classified Establishments",
    "sg:phone":"+33 1 64 02 55 11",
    "sg:province":"Ile de France",
    "wof:name":"Id. Acier S.a.",
    "wof:placetype":"venue"
},
  "geometry": {"coordinates":[2.591438,49.018017],"type":"Point"}
}