{
  "type": "Feature",
  "properties": {
    "iso:country":"FR",
    "sg:address":"B.P. 4, 43220 Duni\u00e8res C\u00e9dex^^ZA de Faurie, 43220 Duni\u00e8res",
    "sg:city":"Duni\u00e8res",
    "sg:orig_category":"Non-Classified Establishments",
    "sg:phone":"+33 4 71 61 91 30",
    "sg:postcode":"43220",
    "sg:province":"Auvergne",
    "wof:name":"Soplatherm S.a.r.l.",
    "wof:placetype":"venue"
},
  "geometry": {"coordinates":[4.426631,45.186089],"type":"Point"}
}