{
  "type": "Feature",
  "properties": {
    "addr:full":"Rue Chamechaude 38360 Sassenage Rhone-Alpes",
    "addr:postcode":"38360",
    "addr:street":"Rue Chamechaude",
    "iso:country":"FR",
    "sg:address":"Rue Chamechaude 38360 Sassenage",
    "sg:classifiers":[
        {
            "category":"Banks & Credit Unions",
            "subcategory":"Investment Brokerage",
            "type":"Services"
        }
    ],
    "sg:phone":"+33 4 76 26 36 85",
    "sg:province":"Rhone-Alpes",
    "sg:tags":[
        "-",
        "transport",
        "related"
    ],
    "wof:name":"Inter Services",
    "wof:placetype":"venue"
},
  "geometry": {"coordinates":[5.68191,45.207909],"type":"Point"}
}