{
  "type": "Feature",
  "properties": {
    "addr:full":"24 Quai Ste Catherine 54042 Nancy Cedex Rhone-Alpes",
    "addr:housenumber":"24",
    "addr:postcode":"54042",
    "addr:street":"Quai Ste Catherine",
    "iso:country":"FR",
    "sg:address":"24 Quai Ste Catherine 54042 Nancy Cedex",
    "sg:classifiers":[
        {
            "category":"Manufacturing",
            "subcategory":"Chemicals & Compounds",
            "type":"Manufacturing & Wholesale Goods"
        }
    ],
    "sg:phone":"+33 3 83 85 35 35",
    "sg:province":"Rhone-Alpes",
    "sg:tags":[
        "pharmaceutical",
        "chemistry",
        "-",
        "by-product"
    ],
    "wof:name":"Gaz De France Gdf Service National (gdf)",
    "wof:placetype":"venue"
},
  "geometry": {"coordinates":[6.191676,48.693855],"type":"Point"}
}