{
  "type": "Feature",
  "properties": {
    "addr:full":"10 rue Lincoln, 75008 Paris, Dept 75 Ile de France 75008",
    "addr:housenumber":"10;75",
    "addr:postcode":"75008;75008",
    "addr:street":"Rue Lincoln;Ile De France",
    "iso:country":"FR",
    "sg:address":"10 rue Lincoln, 75008 Paris, Dept 75",
    "sg:classifiers":[
        {
            "category":"Banks & Credit Unions",
            "subcategory":"Bank",
            "type":"Services"
        }
    ],
    "sg:phone":"+33 1 44 35 15 00",
    "sg:postcode":"75008",
    "sg:province":"Ile de France",
    "wof:name":"Caisse Fonci\u00e8re De Cr\u00e9dit",
    "wof:placetype":"venue"
},
  "geometry": {"coordinates":[2.303114,48.870377],"type":"Point"}
}