{
  "type": "Feature",
  "properties": {
    "addr:full":"B.P. 28, 67601 S\u00e9lestat C\u00e9dex^^3, Rue des V\u00e9t\u00e9rans, 67600 Muttersholtz S\u00e9lestat Alsace 67600",
    "addr:postcode":"67601;67600;67600",
    "addr:street":"B.P. 28;Rue Des Ve\u0301Te\u0301Rans",
    "iso:country":"FR",
    "sg:address":"B.P. 28, 67601 S\u00e9lestat C\u00e9dex^^3, Rue des V\u00e9t\u00e9rans, 67600 Muttersholtz",
    "sg:city":"S\u00e9lestat",
    "sg:orig_category":"Non-Classified Establishments",
    "sg:phone":"+33 3 88 85 10 14",
    "sg:postcode":"67600",
    "sg:province":"Alsace",
    "wof:name":"Mathis Paul S.a.",
    "wof:placetype":"venue"
},
  "geometry": {"coordinates":[7.452325,48.257805],"type":"Point"}
}