{
  "type": "Feature",
  "properties": {
    "addr:full":"228 rue Paul Bellamy; Nantes Picardie",
    "addr:housenumber":"228",
    "addr:street":"Rue Paul Bellamy",
    "iso:country":"FR",
    "sg:address":"228 rue Paul Bellamy; Nantes",
    "sg:classifiers":[
        {
            "category":"Banks & Credit Unions",
            "subcategory":"Bank",
            "type":"Services"
        }
    ],
    "sg:phone":"+33 3340402751",
    "sg:province":"Picardie",
    "wof:name":"Banque Cio, Nantes Rond Point De Rennes",
    "wof:placetype":"venue"
},
  "geometry": {"coordinates":[-1.565502,47.233082],"type":"Point"}
}