{
  "type": "Feature",
  "properties": {
    "addr:full":"80, Rue Jean Jaur\u00e8s, 59920 Qui\u00e9vrechain Nord Pas-de-Calais 59920",
    "addr:housenumber":"80",
    "addr:postcode":"59920;59920",
    "addr:street":"Rue Jean Jaure\u0300S",
    "iso:country":"FR",
    "sg:address":"80, Rue Jean Jaur\u00e8s, 59920 Qui\u00e9vrechain",
    "sg:orig_category":"Non-Classified Establishments",
    "sg:phone":"+33 3 27 45 60 55",
    "sg:postcode":"59920",
    "sg:province":"Nord Pas-de-Calais",
    "wof:name":"B.s.l.t. S.a.",
    "wof:placetype":"venue"
},
  "geometry": {"coordinates":[3.67284,50.40332],"type":"Point"}
}