{
  "type": "Feature",
  "properties": {
    "iso:country":"FR",
    "sg:address":"45, Rue Aristide Briand, 92300 Levallois Perret",
    "sg:orig_category":"Non-Classified Establishments",
    "sg:phone":"+33 1 47 58 25 09",
    "sg:province":"Ile de France",
    "wof:name":"Oui Direct S.a.r.l.",
    "wof:placetype":"venue"
},
  "geometry": {"coordinates":[2.285043,48.891148],"type":"Point"}
}