{
  "type": "Feature",
  "properties": {
    "iso:country":"FR",
    "sg:address":"42 Chemin Du Moulin Carron 69130 Ecully",
    "sg:classifiers":[
        {
            "category":"Shopping",
            "type":"Retail Goods"
        }
    ],
    "sg:phone":"+33 4 72 86 00 06",
    "sg:postcode":"69130",
    "sg:province":"Rhone-Alpes",
    "sg:tags":[
        "metallurgy",
        "finished",
        "-",
        "metalworking",
        "metallic"
    ],
    "wof:name":"Villeroy Et Boch",
    "wof:placetype":"venue"
},
  "geometry": {"coordinates":[4.776112,45.793587],"type":"Point"}
}