{
  "type": "Feature",
  "properties": {
    "addr:full":"1, Place Alphonse Jourdain - Immeuble B, 31000 Toulouse Midi Pyr\u00e9n\u00e9es 31000",
    "addr:housenumber":"1;b",
    "addr:postcode":"31000;31000",
    "addr:street":"Place Alphonse Jourdain",
    "iso:country":"FR",
    "sg:address":"1, Place Alphonse Jourdain - Immeuble B, 31000 Toulouse",
    "sg:orig_category":"Non-Classified Establishments",
    "sg:phone":"+33 5 62 15 43 30",
    "sg:postcode":"31000",
    "sg:province":"Midi Pyr\u00e9n\u00e9es",
    "wof:name":"Ernst And Young Audit S.a.",
    "wof:placetype":"venue"
},
  "geometry": {"coordinates":[1.430128,43.611034],"type":"Point"}
}