{
  "type": "Feature",
  "properties": {
    "iso:country":"FR",
    "sg:address":"6, Rue Emile Zola, 93100 Montreuil",
    "sg:orig_category":"Non-Classified Establishments",
    "sg:phone":"+33 1 48 59 46 38",
    "sg:province":"Ile de France",
    "wof:name":"Reprotechnique Bis",
    "wof:placetype":"venue"
},
  "geometry": {"coordinates":[2.419362,48.854477],"type":"Point"}
}