{
  "type": "Feature",
  "properties": {
    "iso:country":"FR",
    "sg:address":"4, Rue Edouard Denis Baldus - P.A. des Bords de Sa\u00f4ne - de Sa\u00f4ne , 71100 Ch\u00e2lon sur Sa\u00f4ne",
    "sg:city":"Chalon-sur-Sa\u00f4ne",
    "sg:orig_category":"Non-Classified Establishments",
    "sg:phone":"+33 3 85 90 98 00",
    "sg:postcode":"71100",
    "sg:province":"Bourgogne",
    "wof:name":"Eurotest S.a.r.l.",
    "wof:placetype":"venue"
},
  "geometry": {"coordinates":[-77.604507,40.99464],"type":"Point"}
}