{
  "type": "Feature",
  "properties": {
    "addr:full":"184 Avenue Du Gal De Gaulle 92140 Clamart Ile de France 92140",
    "addr:housenumber":"184",
    "addr:postcode":"92140;ile;92140",
    "addr:street":"Avenue Du Gal De Gaulle;France",
    "iso:country":"FR",
    "sg:address":"184 Avenue Du Gal De Gaulle 92140 Clamart",
    "sg:classifiers":[
        {
            "category":"Professional",
            "subcategory":"Engineering",
            "type":"Services"
        }
    ],
    "sg:phone":"+33 1 46 30 10 90",
    "sg:postcode":"92140",
    "sg:province":"Ile de France",
    "sg:tags":[
        "machine",
        "-",
        "mechanical"
    ],
    "wof:name":"Repass Net Sarl",
    "wof:placetype":"venue"
},
  "geometry": {"coordinates":[2.259851,48.789017],"type":"Point"}
}