{
  "type": "Feature",
  "properties": {
    "iso:country":"FR",
    "sg:address":"12, Rue Marcel Dassault, 44980 Sainte Luce sur Loire",
    "sg:orig_category":"Unclassifiable Establishments",
    "sg:phone":"+33 2 51 85 08 20",
    "sg:province":"Pays de Loire",
    "wof:name":"Nantes Equipements S.a.s.",
    "wof:placetype":"venue"
},
  "geometry": {"coordinates":[-1.47137,47.272762],"type":"Point"}
}