{
  "type": "Feature",
  "properties": {
    "iso:country":"FR",
    "sg:address":"80, Chemin des Coverays, 74400 Chamonix Mont Blanc",
    "sg:orig_category":"Unclassifiable Establishments",
    "sg:phone":"+33 4 50 53 29 12",
    "sg:province":"Rhone-Alpes",
    "wof:name":"Cham-d\u00e9co S.a.r.l.",
    "wof:placetype":"venue"
},
  "geometry": {"coordinates":[6.885674,45.93124],"type":"Point"}
}