{
  "type": "Feature",
  "properties": {
    "iso:country":"FR",
    "sg:address":"B.P. 33, 39380 Mont sous Vaudrey^^2, Impasse Roch, 39380 Mont sous Vaudrey",
    "sg:orig_category":"Non-Classified Establishments",
    "sg:phone":"+33 3 84 80 04 44",
    "sg:postcode":"39380",
    "sg:province":"Franche Comt\u00e9",
    "wof:name":"Constructions Chauvin S.a.s.",
    "wof:placetype":"venue"
},
  "geometry": {"coordinates":[5.602845,46.981445],"type":"Point"}
}