{
  "type": "Feature",
  "properties": {
    "addr:full":"150, Rue de l'H\u00f4pital, 51200 Epernay Champagne",
    "addr:housenumber":"150",
    "addr:postcode":"51200",
    "addr:street":"Rue De L'Ho \u0302Pital",
    "iso:country":"FR",
    "sg:address":"150, Rue de l'H\u00f4pital, 51200 Epernay",
    "sg:orig_category":"Unclassifiable Establishments",
    "sg:phone":"+33 3 26 53 33 53",
    "sg:province":"Champagne",
    "wof:name":"Champagne Prospect S.a.r.l.",
    "wof:placetype":"venue"
},
  "geometry": {"coordinates":[3.953653,49.032108],"type":"Point"}
}