{
  "type": "Feature",
  "properties": {
    "iso:country":"FR",
    "sg:address":"1, Rue Gutemberg, 67720 Hoerdt",
    "sg:city":"Hoerdt",
    "sg:orig_category":"Unclassifiable Establishments",
    "sg:phone":"+33 3 88 68 22 68",
    "sg:postcode":"67720",
    "sg:province":"Alsace",
    "wof:name":"Macherey Nagel S.a.r.l.",
    "wof:placetype":"venue"
},
  "geometry": {"coordinates":[7.796102,48.672363],"type":"Point"}
}