{
  "type": "Feature",
  "properties": {
    "iso:country":"FR",
    "sg:address":"Lieu Dit La Fribaudiere 49710 Le Longeron",
    "sg:classifiers":[
        {
            "category":"Manufacturing",
            "subcategory":"Rubber & Plastics",
            "type":"Manufacturing & Wholesale Goods"
        }
    ],
    "sg:phone":"+33 2 41 46 62 22",
    "sg:province":"Pays de Loire",
    "wof:name":"Societe Industrielle De Prefab De L'ouest (sipo)",
    "wof:placetype":"venue"
},
  "geometry": {"coordinates":[-1.029179,47.013336],"type":"Point"}
}