{
  "type": "Feature",
  "properties": {
    "iso:country":"FR",
    "sg:address":"12 bis, Chemin des Alouettes, 31120 Portet sur Garonne",
    "sg:orig_category":"Non-Classified Establishments",
    "sg:phone":"+33 5 87 62 19 19",
    "sg:province":"Midi Pyr\u00e9n\u00e9es",
    "wof:name":"Serialu S.a.r.l.",
    "wof:placetype":"venue"
},
  "geometry": {"coordinates":[1.395475,43.535999],"type":"Point"}
}