{
  "type": "Feature",
  "properties": {
    "addr:full":"B.P. 378, 42353 La Talaudi\u00e8re C\u00e9dex^^15, Rue du Gros Ch\u00eane - ZI Molina la Chazette - Gros Ch\u00eane , 42 Centre",
    "addr:housenumber":"b.p. 378;42",
    "addr:postcode":"42353",
    "addr:street":"Talaudie\u0300Re;Rue Du Gros;Zi Molina La Chazette Gros",
    "iso:country":"FR",
    "sg:address":"B.P. 378, 42353 La Talaudi\u00e8re C\u00e9dex^^15, Rue du Gros Ch\u00eane - ZI Molina la Chazette - Gros Ch\u00eane , 42",
    "sg:orig_category":"Non-Classified Establishments",
    "sg:phone":"+33 4 77 47 61 30",
    "sg:province":"Centre",
    "wof:name":"D.j.a. S.a.",
    "wof:placetype":"venue"
},
  "geometry": {"coordinates":[4.422464,45.464455],"type":"Point"}
}