{
  "type": "Feature",
  "properties": {
    "addr:full":"1 Rue Du Doubs Zi De La Plaine Des Bouches 67100 Strasbourg Strasbourg Alsace 67100",
    "addr:housenumber":"1",
    "addr:postcode":"67100;67100",
    "addr:street":"Rue Du Doubs Zi De La Plaine Des Bouches",
    "iso:country":"FR",
    "sg:address":"1 Rue Du Doubs Zi De La Plaine Des Bouches 67100 Strasbourg",
    "sg:city":"Strasbourg",
    "sg:classifiers":[
        {
            "category":"Professional",
            "subcategory":"Engineering",
            "type":"Services"
        }
    ],
    "sg:phone":"+33 3 88 78 70 99",
    "sg:postcode":"67100",
    "sg:province":"Alsace",
    "sg:tags":[
        "machine",
        "-",
        "mechanical"
    ],
    "wof:name":"France Air Sa",
    "wof:placetype":"venue"
},
  "geometry": {"coordinates":[7.76865,48.534969],"type":"Point"}
}