{
  "type": "Feature",
  "properties": {
    "addr:full":"B.P. 79 Cadillac Aquitaine 33410",
    "addr:postcode":"33410",
    "addr:street":"B.P. 79",
    "iso:country":"FR",
    "sg:address":"B.P. 79",
    "sg:city":"Cadillac",
    "sg:orig_category":"Non-Classified Establishments",
    "sg:phone":"+33 5 56 76 74 80",
    "sg:postcode":"33410",
    "sg:province":"Aquitaine",
    "wof:name":"Groupe Saint R\u00e9my S.a.",
    "wof:placetype":"venue"
},
  "geometry": {"coordinates":[-0.280539,44.59306],"type":"Point"}
}