{
  "type": "Feature",
  "properties": {
    "addr:full":"Z I 12380 St Sernin Sur Rance Midi Pyr\u00e9n\u00e9es",
    "addr:housenumber":"12380",
    "addr:street":"Z",
    "iso:country":"FR",
    "sg:address":"Z I 12380 St Sernin Sur Rance",
    "sg:classifiers":[
        {
            "category":"Government",
            "subcategory":"City Hall",
            "type":"Public Place"
        }
    ],
    "sg:phone":"+33 5 65 99 67 44",
    "sg:province":"Midi Pyr\u00e9n\u00e9es",
    "sg:tags":[
        "picture",
        "agency"
    ],
    "wof:name":"Synelec Telecom Multimedia S.a.",
    "wof:placetype":"venue"
},
  "geometry": {"coordinates":[2.619367,43.797398],"type":"Point"}
}