{
  "type": "Feature",
  "properties": {
    "addr:full":"25 Rue Edouard Martel Zi La Chauveti\u00e8re 42012 St Etienne Cedex 2 Champagne",
    "addr:housenumber":"25",
    "addr:postcode":"42012;etienne cedex 2",
    "addr:street":"Rue Edouard Martel Zi La Chauvetie\u0300Re",
    "iso:country":"FR",
    "sg:address":"25 Rue Edouard Martel Zi La Chauveti\u00e8re 42012 St Etienne Cedex 2",
    "sg:classifiers":[
        {
            "category":"Manufacturing",
            "subcategory":"Printing",
            "type":"Manufacturing & Wholesale Goods"
        }
    ],
    "sg:phone":"+33 4 77 57 48 48",
    "sg:province":"Champagne",
    "sg:tags":[
        "publishing"
    ],
    "wof:name":"Imprimerie Et Cartonnage Du Sud Est",
    "wof:placetype":"venue"
},
  "geometry": {"coordinates":[4.38545,45.44096],"type":"Point"}
}