{
  "type": "Feature",
  "properties": {
    "addr:full":"55, Rue Meslay, 75003 Paris Ile de France 75003",
    "addr:housenumber":"55",
    "addr:postcode":"75003;75003",
    "addr:street":"Rue Meslay",
    "iso:country":"FR",
    "sg:address":"55, Rue Meslay, 75003 Paris",
    "sg:orig_category":"Non-Classified Establishments",
    "sg:phone":"+33 1 44 54 03 85",
    "sg:postcode":"75003",
    "sg:province":"Ile de France",
    "wof:name":"Edouard De Seine S.a.r.l.",
    "wof:placetype":"venue"
},
  "geometry": {"coordinates":[2.357032,48.868179],"type":"Point"}
}