{
  "type": "Feature",
  "properties": {
    "addr:full":"23 Avenue Bernard Palissy 92210 St Cloud Ile de France 92210",
    "addr:housenumber":"23",
    "addr:postcode":"92210;92210",
    "addr:street":"Avenue Bernard Palissy",
    "iso:country":"FR",
    "sg:address":"23 Avenue Bernard Palissy 92210 St Cloud",
    "sg:classifiers":[
        {
            "category":"Professional",
            "subcategory":"Advertising",
            "type":"Services"
        }
    ],
    "sg:phone":"+33 1 41 12 30 00",
    "sg:postcode":"92210",
    "sg:province":"Ile de France",
    "sg:tags":[
        "communication",
        "medium"
    ],
    "wof:name":"Premiere Heure Sa",
    "wof:placetype":"venue"
},
  "geometry": {"coordinates":[2.221567,48.854088],"type":"Point"}
}