{
  "type": "Feature",
  "properties": {
    "addr:full":"Ld La Croix Rouge 29610 Plouigneau Plouigneau Bretagne 29610",
    "addr:postcode":"29610;29610",
    "addr:street":"Ld La Croix Rouge;Plouigneau",
    "iso:country":"FR",
    "sg:address":"Ld La Croix Rouge 29610 Plouigneau",
    "sg:city":"Plouigneau",
    "sg:classifiers":[
        {
            "category":"Autos & Motor Vehicles",
            "subcategory":"Automobile Sales",
            "type":"Retail Goods"
        }
    ],
    "sg:phone":"+33 2 98 62 03 11",
    "sg:postcode":"29610",
    "sg:province":"Bretagne",
    "sg:tags":[
        "equipment",
        "transport"
    ],
    "wof:name":"Ste Morlaisgarages Bretagne Sa",
    "wof:placetype":"venue"
},
  "geometry": {"coordinates":[-3.793049,48.578285],"type":"Point"}
}