{
  "type": "Feature",
  "properties": {
    "iso:country":"FR",
    "sg:address":"B.P. 8, 57690 Cr\u00e9hange^^Rue Denis Papin, 57690 Cr\u00e9hange",
    "sg:orig_category":"Non-Classified Establishments",
    "sg:phone":"+33 3 87 00 34 65",
    "sg:postcode":"57690",
    "sg:province":"Lorraine",
    "wof:name":"Allround Echafaudages S.a.r.l.",
    "wof:placetype":"venue"
},
  "geometry": {"coordinates":[6.58013,49.062054],"type":"Point"}
}