{
  "type": "Feature",
  "properties": {
    "addr:full":"38 Rue Henri Gorjus 69004 Lyon Rhone-Alpes 69004",
    "addr:housenumber":"38",
    "addr:postcode":"69004;69004",
    "addr:street":"Rue Henri Gorjus",
    "iso:country":"FR",
    "sg:address":"38 Rue Henri Gorjus 69004 Lyon",
    "sg:classifiers":[
        {
            "category":"Manufacturing",
            "subcategory":"Jewelry",
            "type":"Manufacturing & Wholesale Goods"
        }
    ],
    "sg:phone":"+33 4 72 00 52 15",
    "sg:postcode":"69004",
    "sg:province":"Rhone-Alpes",
    "sg:tags":[
        "product",
        "miscellaneous",
        "jewellery"
    ],
    "wof:name":"Perignon Gavet",
    "wof:placetype":"venue"
},
  "geometry": {"coordinates":[4.823716,45.780277],"type":"Point"}
}