{
  "type": "Feature",
  "properties": {
    "iso:country":"FR",
    "sg:address":"25 rue Nobel; Quimper",
    "sg:city":"Quimper",
    "sg:classifiers":[
        {
            "category":"Banks & Credit Unions",
            "subcategory":"Bank",
            "type":"Services"
        }
    ],
    "sg:phone":"+33 3398551968",
    "sg:postcode":"29000",
    "sg:province":"Bretagne",
    "wof:name":"Cr\u00e9dit Maritime Mutuel, Conseiller Technique",
    "wof:placetype":"venue"
},
  "geometry": {"coordinates":[-4.148658,48.003071],"type":"Point"}
}