{
  "type": "Feature",
  "properties": {
    "iso:country":"FR",
    "sg:address":"Bourg 71640 Mellecey",
    "sg:city":"Mellecey",
    "sg:classifiers":[
        {
            "category":"Food Court",
            "type":"Food & Drink"
        }
    ],
    "sg:phone":"+33 3 85 98 99 90",
    "sg:postcode":"71640",
    "sg:province":"Bourgogne",
    "sg:tags":[
        "product",
        "related"
    ],
    "wof:name":"Landre Isabelle Et Robert",
    "wof:placetype":"venue"
},
  "geometry": {"coordinates":[4.728059,46.810719],"type":"Point"}
}