{
  "type": "Feature",
  "properties": {
    "addr:full":"57 Rue Condorcet Zi Des Ch\u00e2taigniers 95550 Taverny Ile de France",
    "addr:housenumber":"57",
    "addr:postcode":"95550",
    "addr:street":"Rue Condorcet Zi Des Cha\u0302Taigniers",
    "iso:country":"FR",
    "sg:address":"57 Rue Condorcet Zi Des Ch\u00e2taigniers 95550 Taverny",
    "sg:classifiers":[
        {
            "category":"Banks & Credit Unions",
            "subcategory":"Investment Brokerage",
            "type":"Services"
        }
    ],
    "sg:phone":"+33 1 30 40 51 51",
    "sg:province":"Ile de France",
    "sg:tags":[
        "-",
        "transport",
        "related"
    ],
    "wof:name":"Borzo-bel Sa",
    "wof:placetype":"venue"
},
  "geometry": {"coordinates":[2.21701,49.03841],"type":"Point"}
}