{
  "type": "Feature",
  "properties": {
    "addr:full":"B.P. 5, 33530 Bassens^^66, Quai Fran\u00e7ais, 33530 Bassens Bassens Aquitaine 33530",
    "addr:housenumber":"5",
    "addr:postcode":"33530;33530;33530",
    "addr:street":"B.P.;Quai Franc\u0327Ais",
    "iso:country":"FR",
    "sg:address":"B.P. 5, 33530 Bassens^^66, Quai Fran\u00e7ais, 33530 Bassens",
    "sg:city":"Bassens",
    "sg:orig_category":"Non-Classified Establishments",
    "sg:phone":"+33 5 57 80 83 77",
    "sg:postcode":"33530",
    "sg:province":"Aquitaine",
    "wof:name":"G.t. Logistics S.a.r.l.",
    "wof:placetype":"venue"
},
  "geometry": {"coordinates":[-0.516629,44.900097],"type":"Point"}
}