{
  "type": "Feature",
  "properties": {
    "addr:full":"ZAC des Pommiers Villiers sur Suize Champagne 52210",
    "addr:housenumber":"zac",
    "addr:postcode":"52210",
    "addr:street":"Des Pommiers Villiers Sur Suize Champagne",
    "iso:country":"FR",
    "sg:address":"ZAC des Pommiers",
    "sg:city":"Villiers sur Suize",
    "sg:orig_category":"Non-Classified Establishments",
    "sg:phone":"+33 3 25 31 49 49",
    "sg:postcode":"52210",
    "sg:province":"Champagne",
    "wof:name":"Vitrey Structure S.a.r.l.",
    "wof:placetype":"venue"
},
  "geometry": {"coordinates":[5.19592,47.980385],"type":"Point"}
}