{
  "type": "Feature",
  "properties": {
    "addr:full":"54, Av. de Saint M\u00e9dard, 33700 M\u00e9rignac M\u00e9rignac Aquitaine 33700",
    "addr:postcode":"33700;33700",
    "addr:street":"54 Av. De Saint Me\u0301Dard",
    "iso:country":"FR",
    "sg:address":"54, Av. de Saint M\u00e9dard, 33700 M\u00e9rignac",
    "sg:city":"M\u00e9rignac",
    "sg:orig_category":"Unclassifiable Establishments",
    "sg:phone":"+33 5 56 97 72 32",
    "sg:postcode":"33700",
    "sg:province":"Aquitaine",
    "wof:name":"Sgnis S.a.r.l.",
    "wof:placetype":"venue"
},
  "geometry": {"coordinates":[-0.644125,44.861664],"type":"Point"}
}