{
  "type": "Feature",
  "properties": {
    "addr:full":"172, Place du Barlet, 59500 Douai Nord Pas-de-Calais",
    "addr:housenumber":"172",
    "addr:postcode":"59500",
    "addr:street":"Place Du Barlet",
    "iso:country":"FR",
    "sg:address":"172, Place du Barlet, 59500 Douai",
    "sg:orig_category":"Unclassifiable Establishments",
    "sg:phone":"+33 3 27 88 80 60",
    "sg:province":"Nord Pas-de-Calais",
    "wof:name":"S.e.d. - S.a. - Soci\u00e9t\u00e9 Des Eaux De Douai",
    "wof:placetype":"venue"
},
  "geometry": {"coordinates":[3.082367,50.364822],"type":"Point"}
}