{
  "type": "Feature",
  "properties": {
    "iso:country":"FR",
    "sg:address":"Pl Des Marronniers 18000 Bourges",
    "sg:city":"Bourges",
    "sg:classifiers":[
        {
            "category":"Food Court",
            "type":"Food & Drink"
        }
    ],
    "sg:phone":"+33 2 48 50 64 36",
    "sg:postcode":"18000",
    "sg:province":"Centre",
    "sg:tags":[
        "product",
        "related"
    ],
    "wof:name":"Ets Monin",
    "wof:placetype":"venue"
},
  "geometry": {"coordinates":[2.38442,47.073605],"type":"Point"}
}