{
  "type": "Feature",
  "properties": {
    "addr:full":"8 route d'Altkirch 68720 Illfurth Illfurth Alsace 68720",
    "addr:housenumber":"8",
    "addr:postcode":"68720;68720",
    "addr:street":"Route D'Altkirch;Illfurth",
    "iso:country":"FR",
    "sg:address":"8 route d'Altkirch 68720 Illfurth",
    "sg:city":"Illfurth",
    "sg:classifiers":[
        {
            "category":"Manufacturing",
            "subcategory":"Wood Products",
            "type":"Manufacturing & Wholesale Goods"
        }
    ],
    "sg:phone":"+33 3 89 25 54 32",
    "sg:postcode":"68720",
    "sg:province":"Alsace",
    "sg:tags":[
        "installation",
        "sawmill"
    ],
    "wof:name":"Logsys Sarl",
    "wof:placetype":"venue"
},
  "geometry": {"coordinates":[7.264944,47.670765],"type":"Point"}
}