{
  "type": "Feature",
  "properties": {
    "addr:full":"Rue De La Pommellerie 28330 La Bazoche Gouet Authon-du-Perche Centre 28330",
    "addr:housenumber":"authon-du-perche",
    "addr:postcode":"28330;28330",
    "addr:street":"Rue De La Pommellerie;Bazoche Gouet",
    "iso:country":"FR",
    "sg:address":"Rue De La Pommellerie 28330 La Bazoche Gouet",
    "sg:city":"Authon-du-Perche",
    "sg:classifiers":[
        {
            "category":"Professional",
            "type":"Services"
        }
    ],
    "sg:phone":"+33 2 37 53 43 70",
    "sg:postcode":"28330",
    "sg:province":"Centre",
    "sg:tags":[
        "transport",
        "road"
    ],
    "wof:name":"Legendre Sa",
    "wof:placetype":"venue"
},
  "geometry": {"coordinates":[0.978809,48.140648],"type":"Point"}
}