{
  "type": "Feature",
  "properties": {
    "iso:country":"FR",
    "sg:address":"2 Ter Rue La Tour D'Auvergne 44200 Nantes",
    "sg:classifiers":[
        {
            "category":"Shopping",
            "subcategory":"Luggage & Leather Goods",
            "type":"Retail Goods"
        }
    ],
    "sg:phone":"+33 2 40 47 53 50",
    "sg:postcode":"44200",
    "sg:province":"Pays de Loire",
    "sg:tags":[
        "shoe"
    ],
    "wof:name":"Buet Bertrand Chaussures Et Semelles Orthopediques Sarl",
    "wof:placetype":"venue"
},
  "geometry": {"coordinates":[-1.559763,47.205872],"type":"Point"}
}