{
  "type": "Feature",
  "properties": {
    "addr:full":"101, Rue Pierre Semard - Technosud II, 92324 Ch\u00e2tillon C\u00e9dex Ch\u00e2tillon Ile de France 92320",
    "addr:housenumber":"101",
    "addr:postcode":"92324;92320",
    "addr:street":"Rue Pierre Semard Technosud Ii",
    "iso:country":"FR",
    "sg:address":"101, Rue Pierre Semard - Technosud II, 92324 Ch\u00e2tillon C\u00e9dex",
    "sg:city":"Ch\u00e2tillon",
    "sg:orig_category":"Non-Classified Establishments",
    "sg:phone":"+33 1 40 84 85 57",
    "sg:postcode":"92320",
    "sg:province":"Ile de France",
    "wof:name":"Elios Informatique S.a.",
    "wof:placetype":"venue"
},
  "geometry": {"coordinates":[2.28984,48.799801],"type":"Point"}
}