{
  "type": "Feature",
  "properties": {
    "addr:full":"3, Rue de Sienne, 31670 Lab\u00e8ge Midi Pyr\u00e9n\u00e9es",
    "addr:housenumber":"3",
    "addr:postcode":"31670",
    "addr:street":"Rue De Sienne",
    "iso:country":"FR",
    "sg:address":"3, Rue de Sienne, 31670 Lab\u00e8ge",
    "sg:orig_category":"Unclassifiable Establishments",
    "sg:phone":"+33 5 61 39 18 04",
    "sg:province":"Midi Pyr\u00e9n\u00e9es",
    "wof:name":"S.h.s. S.a.s.",
    "wof:placetype":"venue"
},
  "geometry": {"coordinates":[1.502342,43.550617],"type":"Point"}
}