{
  "type": "Feature",
  "properties": {
    "addr:full":"33, Bd des Alpes, 38240 Meylan Rhone-Alpes",
    "addr:housenumber":"33",
    "addr:postcode":"38240",
    "addr:street":"Bd Des Alpes",
    "iso:country":"FR",
    "sg:address":"33, Bd des Alpes, 38240 Meylan",
    "sg:orig_category":"Unclassifiable Establishments",
    "sg:phone":"+33 4 76 04 15 60",
    "sg:province":"Rhone-Alpes",
    "wof:name":"Experts Et Consultants Associ\u00e9s S.a.r.l.",
    "wof:placetype":"venue"
},
  "geometry": {"coordinates":[5.771444,45.20385],"type":"Point"}
}