{
  "type": "Feature",
  "properties": {
    "addr:full":"16 Rte De Chartres 28500 Vernouillet Vernouillet Centre 28500",
    "addr:housenumber":"16",
    "addr:postcode":"28500;28500",
    "addr:street":"Rte De Chartres;Vernouillet",
    "iso:country":"FR",
    "sg:address":"16 Rte De Chartres 28500 Vernouillet",
    "sg:city":"Vernouillet",
    "sg:classifiers":[
        {
            "category":"Utilities",
            "subcategory":"Electric",
            "type":"Services"
        }
    ],
    "sg:phone":"+33 2 37 38 98 00",
    "sg:postcode":"28500",
    "sg:province":"Centre",
    "sg:tags":[
        "electricity",
        "raw",
        "energy",
        "material"
    ],
    "wof:name":"Gerard Mang",
    "wof:placetype":"venue"
},
  "geometry": {"coordinates":[1.36587,48.720058],"type":"Point"}
}