{
  "type": "Feature",
  "properties": {
    "iso:country":"FR",
    "sg:address":"Rue des Treize Langues - ZI",
    "sg:city":"Ch\u00e2teaudun",
    "sg:orig_category":"Unclassifiable Establishments",
    "sg:phone":"+33 2 37 45 01 66",
    "sg:postcode":"28200",
    "sg:province":"Centre",
    "wof:name":"Carrosserie Industrielle Laumonier S.a.s.",
    "wof:placetype":"venue"
},
  "geometry": {"coordinates":[1.347449,48.085648],"type":"Point"}
}