{
  "type": "Feature",
  "properties": {
    "iso:country":"FR",
    "sg:address":"Acaplast 23210 BENEVENT L ABBAYE",
    "sg:orig_category":"Installations For The Manufacture Of Rubber Profiles For Wipers",
    "sg:phone":"+33 5 55 81 54 32",
    "sg:postcode":"23210",
    "sg:province":"Limousin",
    "wof:name":"Acaplast S.a.",
    "wof:placetype":"venue"
},
  "geometry": {"coordinates":[1.569865,46.071079],"type":"Point"}
}