{
  "type": "Feature",
  "properties": {
    "iso:country":"FR",
    "sg:address":"17, Rue Henri Sellier, 79000 Niort",
    "sg:orig_category":"Unclassifiable Establishments",
    "sg:phone":"+33 5 49 32 31 00",
    "sg:province":"Poitou-Charentes",
    "wof:name":"A.s.b.i. S.a. - Alliance Sant\u00e9 Bull Informatique",
    "wof:placetype":"venue"
},
  "geometry": {"coordinates":[-0.482325,46.313412],"type":"Point"}
}