{
  "type": "Feature",
  "properties": {
    "iso:country":"FR",
    "sg:address":"14 bis, Rue Mar\u00e9chal Foch, 77780 Bourron Marlotte",
    "sg:orig_category":"Non-Classified Establishments",
    "sg:phone":"+33 1 60 55 50 15",
    "sg:province":"Ile de France",
    "wof:name":"P\u00e9ri-cl\u00e9s S.a.",
    "wof:placetype":"venue"
},
  "geometry": {"coordinates":[2.697951,48.339874],"type":"Point"}
}