{
  "type": "Feature",
  "properties": {
    "iso:country":"FR",
    "sg:address":"14 Pl G\u00e9n\u00e9rale Leclerc; Amboise; 37400",
    "sg:city":"Amboise",
    "sg:classifiers":[
        {
            "category":"Banks & Credit Unions",
            "subcategory":"Bank",
            "type":"Services"
        }
    ],
    "sg:phone":"+33 3347572201",
    "sg:postcode":"37400",
    "sg:province":"Centre",
    "wof:name":"Banque Populaire Val De France",
    "wof:placetype":"venue"
},
  "geometry": {"coordinates":[0.98255,47.412853],"type":"Point"}
}