{
  "type": "Feature",
  "properties": {
    "addr:full":"250, Rue du G\u00e9n\u00e9ral Leclerc, 78400 Chatou Ile de France",
    "addr:housenumber":"250",
    "addr:postcode":"78400",
    "addr:street":"Rue Du Ge\u0301Ne\u0301Ral Leclerc;Ile De France",
    "iso:country":"FR",
    "sg:address":"250, Rue du G\u00e9n\u00e9ral Leclerc, 78400 Chatou",
    "sg:orig_category":"Non-Classified Establishments",
    "sg:phone":"+33 1 39 52 90 09",
    "sg:province":"Ile de France",
    "wof:name":"Fabrivox S.a.r.l.",
    "wof:placetype":"venue"
},
  "geometry": {"coordinates":[2.147349,48.903488],"type":"Point"}
}