{
  "type": "Feature",
  "properties": {
    "addr:full":"B.P. 6016, 14061 Caen C\u00e9dex^^Rte de Lion sur Mer, 14000 Caen Caen Basse Normandie 14000",
    "addr:postcode":"14061;14000;14000",
    "addr:street":"B.P. 6016;Mer",
    "iso:country":"FR",
    "sg:address":"B.P. 6016, 14061 Caen C\u00e9dex^^Rte de Lion sur Mer, 14000 Caen",
    "sg:city":"Caen",
    "sg:orig_category":"Non-Classified Establishments",
    "sg:phone":"+33 2 31 47 77 77",
    "sg:postcode":"14000",
    "sg:province":"Basse Normandie",
    "wof:name":"Papeteries Hamelin S.a.",
    "wof:placetype":"venue"
},
  "geometry": {"coordinates":[-0.36111,49.184361],"type":"Point"}
}