{
  "type": "Feature",
  "properties": {
    "addr:full":"Rue Victor Baltard - ZI des Milles Actiforum Aix en Provence C\u00e9dex 03 Nord Pas-de-Calais 13854",
    "addr:housenumber":"03",
    "addr:postcode":"13854",
    "addr:street":"Rue Victor Baltard Zi Des Milles;Ce\u0301Dex",
    "iso:country":"FR",
    "sg:address":"Rue Victor Baltard - ZI des Milles Actiforum",
    "sg:city":"Aix en Provence C\u00e9dex 03",
    "sg:orig_category":"Non-Classified Establishments",
    "sg:phone":"+33 4 42 24 29 30",
    "sg:postcode":"13854",
    "sg:province":"Nord Pas-de-Calais",
    "wof:name":"B.b.a. Mil'pack",
    "wof:placetype":"venue"
},
  "geometry": {"coordinates":[5.4542,43.52494],"type":"Point"}
}