{
  "type": "Feature",
  "properties": {
    "addr:full":"Rue Des Breholles 14540 Soliers Soliers Basse Normandie 14540",
    "addr:postcode":"14540;14540",
    "addr:street":"Rue Des Breholles",
    "iso:country":"FR",
    "sg:address":"Rue Des Breholles 14540 Soliers",
    "sg:city":"Soliers",
    "sg:classifiers":[
        {
            "category":"Professional",
            "type":"Services"
        }
    ],
    "sg:phone":"+33 2 31 23 78 30",
    "sg:postcode":"14540",
    "sg:province":"Basse Normandie",
    "sg:tags":[
        "-",
        "related",
        "road",
        "transport"
    ],
    "wof:name":"Transport Marescot Sarl",
    "wof:placetype":"venue"
},
  "geometry": {"coordinates":[-0.301721,49.137505],"type":"Point"}
}