{
  "type": "Feature",
  "properties": {
    "iso:country":"FR",
    "sg:address":"1",
    "sg:city":"de Friedland; Paris; 75008",
    "sg:classifiers":[
        {
            "category":"Shopping",
            "subcategory":"Computers & Home Electronics",
            "type":"Retail Goods"
        }
    ],
    "sg:phone":"+33 1 45 63 27 42",
    "sg:postcode":"75008",
    "sg:province":"Ile de France",
    "sg:tags":[
        "chamber",
        "commerce"
    ],
    "wof:name":"Chambre De Commerce Et D'industrie Japonaise En France",
    "wof:placetype":"venue"
},
  "geometry": {"coordinates":[2.305351,48.874783],"type":"Point"}
}