{
  "type": "Feature",
  "properties": {
    "addr:full":"10 Rue Bois D Amour 29930 Pont Aven Pont-Aven Bretagne 29930",
    "addr:housenumber":"10",
    "addr:postcode":"29930;29930",
    "addr:street":"Rue Bois D Amour;Aven",
    "iso:country":"FR",
    "sg:address":"10 Rue Bois D Amour 29930 Pont Aven",
    "sg:city":"Pont-Aven",
    "sg:classifiers":[
        {
            "category":"Food & Beverages",
            "subcategory":"Groceries & Convenience Stores",
            "type":"Retail Goods"
        }
    ],
    "sg:phone":"+33 2 98 06 02 03",
    "sg:postcode":"29930",
    "sg:province":"Bretagne",
    "sg:tags":[
        "product",
        "grain",
        "cereal",
        "related"
    ],
    "wof:name":"Sa Minoterie Le Derout Moulins De Penandros",
    "wof:placetype":"venue"
},
  "geometry": {"coordinates":[-3.74614,47.857254],"type":"Point"}
}