{
  "type": "Feature",
  "properties": {
    "addr:full":"Rte de Lorient - Rue du Colonel Dubois Rennes Bretagne 35000",
    "addr:postcode":"35000",
    "addr:street":"Rte De Lorient Rue Du Colonel Dubois Rennes",
    "iso:country":"FR",
    "sg:address":"Rte de Lorient - Rue du Colonel Dubois",
    "sg:city":"Rennes",
    "sg:orig_category":"Non-Classified Establishments",
    "sg:phone":"+33 2 99 54 06 22",
    "sg:postcode":"35000",
    "sg:province":"Bretagne",
    "wof:name":"S.r.v. S.a.r.l. - Soci\u00e9t\u00e9 Rennaise Des Viandes",
    "wof:placetype":"venue"
},
  "geometry": {"coordinates":[-1.734965,48.10688],"type":"Point"}
}