{
  "type": "Feature",
  "properties": {
    "iso:country":"FR",
    "sg:address":"8 Avenue Georges Pompidou 15000 Aurillac",
    "sg:city":"Aurillac",
    "sg:classifiers":[
        {
            "category":"Food & Beverages",
            "subcategory":"Dairy",
            "type":"Retail Goods"
        }
    ],
    "sg:phone":"+33 4 71 64 28 61",
    "sg:postcode":"15000",
    "sg:province":"Auvergne",
    "sg:tags":[
        "product",
        "related"
    ],
    "wof:name":"Les Fromagers Cantaliens (fc)",
    "wof:placetype":"venue"
},
  "geometry": {"coordinates":[2.446832,44.912235],"type":"Point"}
}