{
  "type": "Feature",
  "properties": {
    "iso:country":"FR",
    "sg:address":"131 Av Joliot Curie 83130 La Garde",
    "sg:city":"La Garde",
    "sg:classifiers":[
        {
            "category":"Manufacturing",
            "subcategory":"Metals",
            "type":"Manufacturing & Wholesale Goods"
        }
    ],
    "sg:phone":"+33 4 94 75 82 55",
    "sg:postcode":"38520",
    "sg:province":"Rhone-Alpes",
    "sg:tags":[
        "metallurgy",
        "metalworking",
        "processing"
    ],
    "wof:name":"Sud Mecanique Entreprise Sarl",
    "wof:placetype":"venue"
},
  "geometry": {"coordinates":[5.9885,43.112362],"type":"Point"}
}