{
  "type": "Feature",
  "properties": {
    "iso:country":"FR",
    "sg:address":"Route de Montdidier 60120 BONNEUIL LES EAUX",
    "sg:classifiers":[
        {
            "category":"Bus Stop",
            "subcategory":"None",
            "type":"Transportation"
        }
    ],
    "sg:phone":"+33 3 44 80 90 90",
    "sg:province":"Picardie",
    "sg:tags":[
        "transformer",
        "special-purpose"
    ],
    "wof:name":"Rolfax Sas",
    "wof:placetype":"venue"
},
  "geometry": {"coordinates":[2.293085,49.630306],"type":"Point"}
}