{
  "type": "Feature",
  "properties": {
    "iso:country":"FR",
    "sg:address":"rue de Montheard 72000 Le Mans",
    "sg:classifiers":[
        {
            "category":"Communications",
            "subcategory":"Newspaper",
            "type":"Services"
        }
    ],
    "sg:phone":"+33 2 43 39 16 20",
    "sg:province":"Pays de Loire",
    "sg:tags":[
        "specialist"
    ],
    "wof:name":"Ste D Edition Maxi B Sa",
    "wof:placetype":"venue"
},
  "geometry": {"coordinates":[0.21716,47.996719],"type":"Point"}
}