{
  "type": "Feature",
  "properties": {
    "iso:country":"FR",
    "sg:address":"260, Chemin de Saurin, 06370 Mouans Sartoux",
    "sg:orig_category":"Non-Classified Establishments",
    "sg:phone":"+33 4 92 92 20 53",
    "sg:province":"Provence-Alpes-C\u00f4te d'Azur",
    "wof:name":"Webd\u00e9veloppement",
    "wof:placetype":"venue"
},
  "geometry": {"coordinates":[6.979313,43.618195],"type":"Point"}
}