{
  "type": "Feature",
  "properties": {
    "addr:full":"Quartier Veyras Loriol sur Dr\u00f4me Rhone-Alpes 26270",
    "addr:postcode":"26270",
    "addr:street":"Quartier",
    "iso:country":"FR",
    "sg:address":"Quartier Veyras",
    "sg:city":"Loriol sur Dr\u00f4me",
    "sg:orig_category":"Non-Classified Establishments",
    "sg:phone":"+33 4 75 63 93 74",
    "sg:postcode":"26270",
    "sg:province":"Rhone-Alpes",
    "wof:name":"Accoplas Soci\u00e9t\u00e9 G\u00e9n\u00e9rale De Fermetures S.a.",
    "wof:placetype":"venue"
},
  "geometry": {"coordinates":[4.776026,44.742279],"type":"Point"}
}