{
  "type": "Feature",
  "properties": {
    "addr:full":"8 de la Fontaine 49450 ROUSSAY Pays de Loire 49450",
    "addr:housenumber":"8",
    "addr:postcode":"49450;49450",
    "addr:street":"De La Fontaine",
    "iso:country":"FR",
    "sg:address":"8",
    "sg:city":"de la Fontaine 49450 ROUSSAY",
    "sg:classifiers":[
        {
            "category":"Personal",
            "subcategory":"Shoe Repair & Shine",
            "type":"Services"
        }
    ],
    "sg:phone":"+33 2 41 70 81 81",
    "sg:postcode":"49450",
    "sg:province":"Pays de Loire",
    "sg:tags":[
        "industry",
        "last"
    ],
    "wof:name":"Botemo Sarl",
    "wof:placetype":"venue"
},
  "geometry": {"coordinates":[-1.065412,47.091526],"type":"Point"}
}