{
  "type": "Feature",
  "properties": {
    "iso:country":"FR",
    "sg:address":"385, Rue Famille Laurens - P\u00f4le d'Activit\u00e9, 13854 Aix en Provence C\u00e9dex 03^^385, Rue Famille Laurens",
    "sg:orig_category":"Non-Classified Establishments",
    "sg:phone":"+33 4 42 39 73 63",
    "sg:province":"Nord Pas-de-Calais",
    "wof:name":"Alchemy Telecom S.a.r.l.",
    "wof:placetype":"venue"
},
  "geometry": {"coordinates":[5.381866,43.480785],"type":"Point"}
}