{
  "type": "Feature",
  "properties": {
    "iso:country":"FR",
    "sg:address":"Ccal L'Etoile 14120 Mondeville",
    "sg:city":"Mondeville",
    "sg:classifiers":[
        {
            "category":"Shopping",
            "subcategory":"Computers & Home Electronics",
            "type":"Retail Goods"
        }
    ],
    "sg:phone":"+33 2 31 35 40 00",
    "sg:postcode":"14120",
    "sg:province":"Basse Normandie",
    "sg:tags":[
        "equipment",
        "household",
        "electrical",
        "appliance",
        "electronic"
    ],
    "wof:name":"Darty Normandie",
    "wof:placetype":"venue"
},
  "geometry": {"coordinates":[-0.301696,49.165936],"type":"Point"}
}