{
  "type": "Feature",
  "properties": {
    "iso:country":"FR",
    "sg:address":"67, Av. Gambetta, 26000 Valence",
    "sg:orig_category":"Non-Classified Establishments",
    "sg:phone":"+33 4 75 78 55 00",
    "sg:postcode":"26000",
    "sg:province":"Rhone-Alpes",
    "wof:name":"Synergie",
    "wof:placetype":"venue"
},
  "geometry": {"coordinates":[4.889781,44.930576],"type":"Point"}
}