{
  "type": "Feature",
  "properties": {
    "iso:country":"FR",
    "sg:address":"B.P. 113, 78192 Trappes C\u00e9dex^^5/7, Rue Albert Einstein, 78190 Trappes",
    "sg:orig_category":"Non-Classified Establishments",
    "sg:phone":"+33 1 30 50 61 10",
    "sg:province":"Ile de France",
    "wof:name":"Ingersoll Rand Europe S.a.r.l.",
    "wof:placetype":"venue"
},
  "geometry": {"coordinates":[1.999285,48.774651],"type":"Point"}
}