{
  "type": "Feature",
  "properties": {
    "addr:full":"27, Rue de l'industrie - ZA Mainville, 91124 Draveil C\u00e9dex California",
    "addr:housenumber":"27",
    "addr:postcode":"91124",
    "addr:street":"Rue De L'Industrie Za",
    "iso:country":"FR",
    "sg:address":"27, Rue de l'industrie - ZA Mainville, 91124 Draveil C\u00e9dex",
    "sg:orig_category":"Non-Classified Establishments",
    "sg:phone":"+33 1 69 52 48 90",
    "sg:province":"California",
    "wof:name":"Sol System S.a.r.l.",
    "wof:placetype":"venue"
},
  "geometry": {"coordinates":[-118.144218,34.147228],"type":"Point"}
}