{
  "type": "Feature",
  "properties": {
    "addr:full":"17026 La Rochelle C\u00e9dex 1^^24, Rue Audran, 17000 La Rochelle Poitou-Charentes 17000",
    "addr:housenumber":"17026;1 ^ ^ 24",
    "addr:postcode":"17000;17000",
    "addr:street":"Ce\u0301Dex;Rue Audran",
    "iso:country":"FR",
    "sg:address":"17026 La Rochelle C\u00e9dex 1^^24, Rue Audran, 17000 La Rochelle",
    "sg:orig_category":"Non-Classified Establishments",
    "sg:phone":"+33 5 46 27 14 00",
    "sg:postcode":"17000",
    "sg:province":"Poitou-Charentes",
    "wof:name":"C.c.c. S.a. - Comptoir Charentais Du Chauffage",
    "wof:placetype":"venue"
},
  "geometry": {"coordinates":[-1.151639,46.159435],"type":"Point"}
}