{
  "type": "Feature",
  "properties": {
    "addr:full":"B.P. 5, 38290 Frontonas C\u00e9dex^^ZA des Quatre Vies, 38290 Frontonas Rhone-Alpes 38290",
    "addr:housenumber":"5",
    "addr:postcode":"38290;38290;38290",
    "addr:street":"B.P.;Vies",
    "iso:country":"FR",
    "sg:address":"B.P. 5, 38290 Frontonas C\u00e9dex^^ZA des Quatre Vies, 38290 Frontonas",
    "sg:orig_category":"Non-Classified Establishments",
    "sg:phone":"+33 4 74 94 17 33",
    "sg:postcode":"38290",
    "sg:province":"Rhone-Alpes",
    "wof:name":"Simeet S.a.",
    "wof:placetype":"venue"
},
  "geometry": {"coordinates":[5.147387,45.632999],"type":"Point"}
}