{
  "type": "Feature",
  "properties": {
    "addr:full":"La Fuste 04210 VALENSOLE Midi Pyr\u00e9n\u00e9es",
    "addr:postcode":"04210",
    "iso:country":"FR",
    "sg:address":"La Fuste 04210 VALENSOLE",
    "sg:classifiers":[
        {
            "category":"Food & Beverages",
            "subcategory":"Fruits & Vegetables",
            "type":"Retail Goods"
        }
    ],
    "sg:phone":"+33 4 92 72 08 40",
    "sg:province":"Midi Pyr\u00e9n\u00e9es",
    "wof:name":"Soleil Des Alpes Sica",
    "wof:placetype":"venue"
},
  "geometry": {"coordinates":[5.841796,43.804325],"type":"Point"}
}