{
  "type": "Feature",
  "properties": {
    "iso:country":"FR",
    "sg:address":"5 Avenue Colonel D'Ornano 34500 B\u00e9ziers",
    "sg:classifiers":[
        {
            "category":"Professional",
            "subcategory":"Engineering",
            "type":"Services"
        }
    ],
    "sg:phone":"+33 4 67 28 20 15",
    "sg:postcode":"34500",
    "sg:province":"Languedoc-Roussillon",
    "sg:tags":[
        "machine",
        "-",
        "mechanical"
    ],
    "wof:name":"Billard Et Clindoux Sa",
    "wof:placetype":"venue"
},
  "geometry": {"coordinates":[3.213055,43.337784],"type":"Point"}
}