{
  "type": "Feature",
  "properties": {
    "addr:full":"7, Av. Saint Fran\u00e7ois de Salles, 74200 Thonon les Bains Rhone-Alpes 74200",
    "addr:postcode":"74200;74200",
    "addr:street":"Av. Saint Franc\u0327Ois De Salles",
    "iso:country":"FR",
    "sg:address":"7, Av. Saint Fran\u00e7ois de Salles, 74200 Thonon les Bains",
    "sg:orig_category":"Unclassifiable Establishments",
    "sg:phone":"+33 4 50 71 64 03",
    "sg:postcode":"74200",
    "sg:province":"Rhone-Alpes",
    "wof:name":"Ad\u00e9cco Travail Temporaire",
    "wof:placetype":"venue"
},
  "geometry": {"coordinates":[6.481714,46.353142],"type":"Point"}
}