{
  "type": "Feature",
  "properties": {
    "addr:full":"4 Route de Cannes 06650 OPIO",
    "addr:housenumber":"4",
    "addr:postcode":"06650",
    "addr:street":"Route De Cannes",
    "iso:country":"FR",
    "sg:address":"4 Route de Cannes 06650 OPIO",
    "sg:classifiers":[
        {
            "category":"Home & Garden",
            "subcategory":"Carpets & Floor Coverings",
            "type":"Retail Goods"
        }
    ],
    "sg:phone":"+33 4 92 60 32 10",
    "sg:tags":[
        "mosaic"
    ],
    "wof:name":"Opiocolor Sa",
    "wof:placetype":"venue"
},
  "geometry": {"coordinates":[6.98692,43.662762],"type":"Point"}
}