{
  "type": "Feature",
  "properties": {
    "iso:country":"FR",
    "sg:address":"rue Mairie; Le Bignon",
    "sg:city":"Le Bignon",
    "sg:classifiers":[
        {
            "category":"Banks & Credit Unions",
            "subcategory":"Bank",
            "type":"Services"
        }
    ],
    "sg:phone":"+33 3340781504",
    "sg:postcode":"44140",
    "sg:province":"Pays de Loire",
    "wof:name":"Cr\u00e9dit Agricole Mutuel",
    "wof:placetype":"venue"
},
  "geometry": {"coordinates":[-1.490821,47.098099],"type":"Point"}
}