{
  "type": "Feature",
  "properties": {
    "addr:full":"15, Rue Lat\u00e9rale, 92404 Courbevoie C\u00e9dex \u00cele-de-France",
    "addr:housenumber":"15",
    "addr:postcode":"92404",
    "addr:street":"Rue Late\u0301Rale;Ce\u0301Dex",
    "iso:country":"FR",
    "sg:address":"15, Rue Lat\u00e9rale, 92404 Courbevoie C\u00e9dex",
    "sg:orig_category":"Non-Classified Establishments",
    "sg:phone":"+33 1 43 34 67 00",
    "sg:province":"\u00cele-de-France",
    "wof:name":"John Crane France S.a.",
    "wof:placetype":"venue"
},
  "geometry": {"coordinates":[2.261639,48.903263],"type":"Point"}
}