{
  "type": "Feature",
  "properties": {
    "addr:full":"Route De Castelnaudary 31540 St Felix Lauragais Midi Pyr\u00e9n\u00e9es 31540",
    "addr:postcode":"31540;31540",
    "addr:street":"Route De Castelnaudary",
    "iso:country":"FR",
    "sg:address":"Route De Castelnaudary 31540 St Felix Lauragais",
    "sg:classifiers":[
        {
            "category":"Home & Garden",
            "subcategory":"Furniture",
            "type":"Retail Goods"
        }
    ],
    "sg:phone":"+33 5 61 83 52 14",
    "sg:postcode":"31540",
    "sg:province":"Midi Pyr\u00e9n\u00e9es",
    "sg:tags":[
        "household",
        "wood"
    ],
    "wof:name":"Societe D'exploitation Des Etablissements Cornac Roger",
    "wof:placetype":"venue"
},
  "geometry": {"coordinates":[1.816325,43.425625],"type":"Point"}
}