{
  "type": "Feature",
  "properties": {
    "iso:country":"FR",
    "sg:address":"83 rue des Ponts de C\u00e9 49000 Angers",
    "sg:classifiers":[
        {
            "category":"Food & Beverages",
            "subcategory":"Fruits & Vegetables",
            "type":"Retail Goods"
        }
    ],
    "sg:phone":"+33 2 41 66 01 01",
    "sg:postcode":"49000",
    "sg:province":"Pays de Loire",
    "sg:tags":[
        "bulb",
        "flower",
        "tuber"
    ],
    "wof:name":"Etablissements E. Turc Sa",
    "wof:placetype":"venue"
},
  "geometry": {"coordinates":[-0.54081,47.454876],"type":"Point"}
}