{
  "type": "Feature",
  "properties": {
    "iso:country":"FR",
    "sg:address":"La Loue 03410 St Victor",
    "sg:city":"Dom\u00e9rat",
    "sg:classifiers":[
        {
            "category":"Professional",
            "subcategory":"Engineering",
            "type":"Services"
        }
    ],
    "sg:phone":"+33 4 70 28 81 81",
    "sg:postcode":"03410",
    "sg:province":"Auvergne",
    "sg:tags":[
        "building",
        "machinery"
    ],
    "wof:name":"Pieces Usures Materiel Entreprises Sa",
    "wof:placetype":"venue"
},
  "geometry": {"coordinates":[2.592635,46.377151],"type":"Point"}
}