{
  "type": "Feature",
  "properties": {
    "addr:full":"6 Av Des Andes 91941 Courtaboeuf Haute Normandie",
    "addr:postcode":"91941",
    "addr:street":"Av Des Andes;Haute Normandie",
    "iso:country":"FR",
    "sg:address":"6 Av Des Andes 91941 Courtaboeuf",
    "sg:classifiers":[
        {
            "category":"Shopping",
            "subcategory":"Computers & Home Electronics",
            "type":"Retail Goods"
        }
    ],
    "sg:phone":"+33 1 69 18 46 00",
    "sg:province":"Haute Normandie",
    "sg:tags":[
        "equipment",
        "electrical",
        "component",
        "electric",
        "electronic"
    ],
    "wof:name":"Avx Sas",
    "wof:placetype":"venue"
},
  "geometry": {"coordinates":[-116.999268,32.760078],"type":"Point"}
}