{
  "type": "Feature",
  "properties": {
    "addr:full":"Pl du Beam; Mourenx; 64150 Mourenx Aquitaine 64150",
    "addr:postcode":"64150;64150",
    "addr:street":"Pl Du Beam Mourenx",
    "iso:country":"FR",
    "sg:address":"Pl du Beam; Mourenx; 64150",
    "sg:city":"Mourenx",
    "sg:classifiers":[
        {
            "category":"Banks & Credit Unions",
            "subcategory":"Bank",
            "type":"Services"
        }
    ],
    "sg:phone":"+33 3359600517",
    "sg:postcode":"64150",
    "sg:province":"Aquitaine",
    "wof:name":"Banque Nationale De Paris",
    "wof:placetype":"venue"
},
  "geometry": {"coordinates":[-0.629704,43.371262],"type":"Point"}
}