{
  "type": "Feature",
  "properties": {
    "addr:full":"B.P. 80 Saint Girons C\u00e9dex^^Carri\u00e8re Fount del Jouil Encourtiech 09200 Saint Girons Midi Pyr\u00e9n\u00e9es 09200",
    "addr:housenumber":"80",
    "addr:postcode":"09200;09200",
    "addr:street":"B.P.;Saint Girons Ce\u0301Dex^^Carrie\u0300Re Fount Del Jouil",
    "iso:country":"FR",
    "sg:address":"B.P. 80",
    "sg:city":"Saint Girons C\u00e9dex^^Carri\u00e8re Fount del Jouil Encourtiech 09200 Saint Girons",
    "sg:orig_category":"Non-Classified Establishments",
    "sg:phone":"+33 5 61 66 36 93",
    "sg:postcode":"09200",
    "sg:province":"Midi Pyr\u00e9n\u00e9es",
    "wof:name":"Soum Et Compagnie S.n.c.",
    "wof:placetype":"venue"
},
  "geometry": {"coordinates":[1.16257,42.974041],"type":"Point"}
}