{
  "type": "Feature",
  "properties": {
    "addr:full":"5 rue de Mar\u00e9chal Foch; L'Hopital; 57490 Lorraine 57490",
    "addr:housenumber":"5",
    "addr:postcode":"57490;57490",
    "addr:street":"Rue De Mare\u0301Chal Foch L'Hopital",
    "iso:country":"FR",
    "sg:address":"5 rue de Mar\u00e9chal Foch; L'Hopital; 57490",
    "sg:classifiers":[
        {
            "category":"Banks & Credit Unions",
            "subcategory":"Bank",
            "type":"Services"
        }
    ],
    "sg:phone":"+33 3 87 93 40 44",
    "sg:postcode":"57490",
    "sg:province":"Lorraine",
    "wof:name":"Cr\u00e9dit Industriel D'alsace, Et De Lorraine Sa",
    "wof:placetype":"venue"
},
  "geometry": {"coordinates":[6.72704,49.160751],"type":"Point"}
}