{
  "type": "Feature",
  "properties": {
    "iso:country":"FR",
    "sg:address":"Place du 8 Mai 1945",
    "sg:city":"Golbey",
    "sg:orig_category":"Unclassifiable Establishments",
    "sg:phone":"+33 3 29 34 24 48",
    "sg:postcode":"88190",
    "sg:province":"Lorraine",
    "wof:name":"Carteron Soci\u00e9t\u00e9 D'expertise Comptable S.a.",
    "wof:placetype":"venue"
},
  "geometry": {"coordinates":[6.435427,48.198486],"type":"Point"}
}