{
  "type": "Feature",
  "properties": {
    "addr:full":"18, Rue du Pr\u00e9 Faucon, 74940 Annecy le Vieux Rhone-Alpes 74940",
    "addr:housenumber":"18",
    "addr:postcode":"74940;74940",
    "addr:street":"Rue Du Pre\u0301 Faucon",
    "iso:country":"FR",
    "sg:address":"18, Rue du Pr\u00e9 Faucon, 74940 Annecy le Vieux",
    "sg:orig_category":"Unclassifiable Establishments",
    "sg:phone":"+33 4 50 64 02 09",
    "sg:postcode":"74940",
    "sg:province":"Rhone-Alpes",
    "wof:name":"Saga Isolation S.a.r.l.",
    "wof:placetype":"venue"
},
  "geometry": {"coordinates":[6.164747,45.930855],"type":"Point"}
}