{
  "type": "Feature",
  "properties": {
    "addr:full":"Bd du Pr\u00e9 Poitiers Nevers Bourgogne 58000",
    "addr:postcode":"58000",
    "addr:street":"Bd Du Pre\u0301",
    "iso:country":"FR",
    "sg:address":"Bd du Pr\u00e9 Poitiers",
    "sg:city":"Nevers",
    "sg:orig_category":"Unclassifiable Establishments",
    "sg:phone":"+33 3 86 57 31 07",
    "sg:postcode":"58000",
    "sg:province":"Bourgogne",
    "wof:name":"Sag S\u00e9rigraphie S.a.r.l.",
    "wof:placetype":"venue"
},
  "geometry": {"coordinates":[3.12953,46.920444],"type":"Point"}
}