{
  "type": "Feature",
  "properties": {
    "addr:full":"22 route du Midi 43220 RIOTORD Riotord Auvergne 43220",
    "addr:housenumber":"22",
    "addr:postcode":"43220;riotord;43220",
    "addr:street":"Route Du Midi",
    "iso:country":"FR",
    "sg:address":"22 route du Midi 43220 RIOTORD",
    "sg:city":"Riotord",
    "sg:classifiers":[
        {
            "category":"Government",
            "subcategory":"Department Of Motor Vehicles",
            "type":"Public Place"
        }
    ],
    "sg:phone":"+33 4 71 75 30 79",
    "sg:postcode":"43220",
    "sg:province":"Auvergne",
    "sg:tags":[
        "town",
        "citymobiles",
        "different",
        "drive",
        "kind"
    ],
    "wof:name":"Etablissements Emehy S.a.",
    "wof:placetype":"venue"
},
  "geometry": {"coordinates":[4.40784,45.235161],"type":"Point"}
}