{
  "type": "Feature",
  "properties": {
    "addr:full":"B.P. 535, 53005 Laval C\u00e9dex^^19, Bd du 8 Mai, 53000 Laval Pays de Loire 53000",
    "addr:housenumber":"b.p. 535",
    "addr:postcode":"53005;ce\u0301dex^^19;53000;53000",
    "addr:street":"Bd Du 8 Mai",
    "iso:country":"FR",
    "sg:address":"B.P. 535, 53005 Laval C\u00e9dex^^19, Bd du 8 Mai, 53000 Laval",
    "sg:orig_category":"Non-Classified Establishments",
    "sg:phone":"+33 2 43 02 95 55",
    "sg:postcode":"53000",
    "sg:province":"Pays de Loire",
    "wof:name":"Constructions M\u00e9talliques Gruau S.a.",
    "wof:placetype":"venue"
},
  "geometry": {"coordinates":[-0.756451,48.036293],"type":"Point"}
}