{
  "type": "Feature",
  "properties": {
    "addr:full":"rue des Charmilles 74460 MARNAZ Rhone-Alpes",
    "addr:postcode":"74460",
    "addr:street":"Rue Des Charmilles",
    "iso:country":"FR",
    "sg:address":"rue des Charmilles 74460 MARNAZ",
    "sg:classifiers":[
        {
            "category":"Utilities",
            "subcategory":"Recycling",
            "type":"Services"
        }
    ],
    "sg:phone":"+33 4 50 98 05 56",
    "sg:province":"Rhone-Alpes",
    "sg:tags":[
        "grinding",
        "robotic"
    ],
    "wof:name":"Ets Zedce S.a.",
    "wof:placetype":"venue"
},
  "geometry": {"coordinates":[6.535555,46.070705],"type":"Point"}
}