{
  "type": "Feature",
  "properties": {
    "addr:full":"5, Av. de la R\u00e9publique, 33430 Bazas Bazas Aquitaine 33430",
    "addr:postcode":"33430;33430",
    "addr:street":"Av. De La Re\u0301Publique",
    "iso:country":"FR",
    "sg:address":"5, Av. de la R\u00e9publique, 33430 Bazas",
    "sg:city":"Bazas",
    "sg:orig_category":"Non-Classified Establishments",
    "sg:phone":"+33 5 56 25 11 71",
    "sg:postcode":"33430",
    "sg:province":"Aquitaine",
    "wof:name":"Saint Marc S.a.r.l.",
    "wof:placetype":"venue"
},
  "geometry": {"coordinates":[-0.229029,44.434315],"type":"Point"}
}