{
  "type": "Feature",
  "properties": {
    "addr:full":"26, Rue Foch, 10160 Aix en Othe Champagne",
    "addr:housenumber":"26",
    "addr:postcode":"10160",
    "addr:street":"Rue Foch",
    "iso:country":"FR",
    "sg:address":"26, Rue Foch, 10160 Aix en Othe",
    "sg:orig_category":"Non-Classified Establishments",
    "sg:phone":"+33 3 25 46 65 15",
    "sg:province":"Champagne",
    "wof:name":"Fauconnet Ing\u00e9nierie S.a.",
    "wof:placetype":"venue"
},
  "geometry": {"coordinates":[3.731835,48.222092],"type":"Point"}
}