{
  "type": "Feature",
  "properties": {
    "iso:country":"FR",
    "sg:address":"91 Bd National 92257 La Garenne Colombes",
    "sg:classifiers":[
        {
            "category":"Wholesale",
            "subcategory":"Medical Equipment & Supplies",
            "type":"Manufacturing & Wholesale Goods"
        }
    ],
    "sg:phone":"+33 1 46 49 66 00",
    "sg:province":"Aquitaine",
    "sg:tags":[
        "instrument",
        "health",
        "-",
        "precision"
    ],
    "wof:name":"Boston Scientific International",
    "wof:placetype":"venue"
},
  "geometry": {"coordinates":[2.237738,48.90773],"type":"Point"}
}