{
  "type": "Feature",
  "properties": {
    "addr:full":"16 Rue Du Poitou 67100 Strasbourg Strasbourg Alsace 67100",
    "addr:housenumber":"16",
    "addr:postcode":"67100;67100",
    "addr:street":"Rue Du Poitou",
    "iso:country":"FR",
    "sg:address":"16 Rue Du Poitou 67100 Strasbourg",
    "sg:city":"Strasbourg",
    "sg:classifiers":[
        {
            "category":"Professional",
            "subcategory":"Business Services",
            "type":"Services"
        }
    ],
    "sg:phone":"+33 3 88 39 12 69",
    "sg:postcode":"67100",
    "sg:province":"Alsace",
    "sg:tags":[
        "training",
        "advice"
    ],
    "wof:name":"College Nationalise Lezay Marnesia",
    "wof:placetype":"venue"
},
  "geometry": {"coordinates":[7.745517,48.549046],"type":"Point"}
}