{
  "type": "Feature",
  "properties": {
    "iso:country":"FR",
    "sg:address":"B.P. 213",
    "sg:city":"Saint Amand les Eaux C\u00e9dex",
    "sg:orig_category":"Non-Classified Establishments",
    "sg:phone":"+33 3 27 21 66 34",
    "sg:postcode":"59734",
    "sg:province":"Basse Normandie",
    "wof:name":"Alupic Nord S.a.",
    "wof:placetype":"venue"
},
  "geometry": {"coordinates":[3.42938,50.44751],"type":"Point"}
}