{
  "type": "Feature",
  "properties": {
    "iso:country":"FR",
    "sg:address":"208, Rte de Paris, 44980 Sainte Luce sur Loire",
    "sg:orig_category":"Non-Classified Establishments",
    "sg:phone":"+33 2 40 52 98 98",
    "sg:postcode":"44980",
    "sg:province":"Pays de Loire",
    "wof:name":"Blanchard Oxycoupage S.a.",
    "wof:placetype":"venue"
},
  "geometry": {"coordinates":[-1.489124,47.265045],"type":"Point"}
}