{
  "type": "Feature",
  "properties": {
    "iso:country":"FR",
    "sg:address":"1 Place De L'Ancienne Halle 27200 Vernon",
    "sg:classifiers":[
        {
            "category":"Professional",
            "subcategory":"Advertising",
            "type":"Services"
        }
    ],
    "sg:phone":"+33 2 32 71 00 20",
    "sg:postcode":"27200",
    "sg:province":"Haute Normandie",
    "sg:tags":[
        "information",
        "medium",
        "communication"
    ],
    "wof:name":"Cristal Fm Sarl",
    "wof:placetype":"venue"
},
  "geometry": {"coordinates":[1.484871,49.0914],"type":"Point"}
}