{
  "type": "Feature",
  "properties": {
    "addr:full":"Avenue De La Voulzie 77160 Provins Ile de France 77160",
    "addr:postcode":"77160;77160",
    "addr:street":"Avenue De La Voulzie",
    "iso:country":"FR",
    "sg:address":"Avenue De La Voulzie 77160 Provins",
    "sg:classifiers":[
        {
            "category":"Shopping",
            "subcategory":"Clothing, Apparel, & Fashions",
            "type":"Retail Goods"
        }
    ],
    "sg:phone":"+33 1 64 00 20 45",
    "sg:postcode":"77160",
    "sg:province":"Ile de France",
    "sg:tags":[
        "textile",
        "clothing",
        "clothes"
    ],
    "wof:name":"Vetements Weill",
    "wof:placetype":"venue"
},
  "geometry": {"coordinates":[3.293665,48.548962],"type":"Point"}
}