{
  "type": "Feature",
  "properties": {
    "iso:country":"FR",
    "sg:address":"3, Rue Thomas Lindet, 27270 Bernay",
    "sg:orig_category":"Unclassifiable Establishments",
    "sg:phone":"+33 2 32 43 04 70",
    "sg:province":"Haute Normandie",
    "wof:name":"Sofac S.a.",
    "wof:placetype":"venue"
},
  "geometry": {"coordinates":[8.96803,55.19598],"type":"Point"}
}