{
  "type": "Feature",
  "properties": {
    "iso:country":"FR",
    "sg:address":"21320 Creancey",
    "sg:city":"Cr\u00e9ancey",
    "sg:classifiers":[
        {
            "category":"Travel",
            "subcategory":"Hotels & Motels",
            "type":"Entertainment"
        }
    ],
    "sg:phone":"+33 3 80 90 70 34",
    "sg:postcode":"21320",
    "sg:province":"Bourgogne",
    "sg:tags":[
        "hotels",
        "business",
        "restaurant"
    ],
    "wof:name":"Serare",
    "wof:placetype":"venue"
},
  "geometry": {"coordinates":[4.58566,47.245544],"type":"Point"}
}