{
  "type": "Feature",
  "properties": {
    "iso:country":"FR",
    "sg:address":"19, Rue du Grand Veymont, 38320 Eybens",
    "sg:orig_category":"Non-Classified Establishments",
    "sg:phone":"+33 4 76 24 71 70",
    "sg:postcode":"38320",
    "sg:province":"Rhone-Alpes",
    "wof:name":"Atelier Perret",
    "wof:placetype":"venue"
},
  "geometry": {"coordinates":[5.74655,45.161659],"type":"Point"}
}