{
  "type": "Feature",
  "properties": {
    "addr:full":"19, Rue du Grand Veymont, 38320 Eybens Rhone-Alpes 38320",
    "addr:housenumber":"19",
    "addr:postcode":"38320;38320",
    "addr:street":"Rue Du Grand Veymont",
    "iso:country":"FR",
    "sg:address":"19, Rue du Grand Veymont, 38320 Eybens",
    "sg:orig_category":"Non-Classified Establishments",
    "sg:phone":"+33 4 76 24 71 70",
    "sg:postcode":"38320",
    "sg:province":"Rhone-Alpes",
    "wof:name":"Atelier Perret",
    "wof:placetype":"venue"
},
  "geometry": {"coordinates":[5.74655,45.161659],"type":"Point"}
}