{
  "type": "Feature",
  "properties": {
    "addr:full":"59 Rue Georges Cl\u00e9menceau 59552 Lambres Lez Douai Nord Pas-de-Calais 59552",
    "addr:housenumber":"59",
    "addr:postcode":"59552;59552",
    "addr:street":"Rue Georges Cle\u0301Menceau",
    "iso:country":"FR",
    "sg:address":"59 Rue Georges Cl\u00e9menceau 59552 Lambres Lez Douai",
    "sg:classifiers":[
        {
            "category":"Wholesale",
            "subcategory":"Medical Equipment & Supplies",
            "type":"Manufacturing & Wholesale Goods"
        }
    ],
    "sg:phone":"+33 3 27 87 38 29",
    "sg:postcode":"59552",
    "sg:province":"Nord Pas-de-Calais",
    "sg:tags":[
        "instrument",
        "health",
        "-",
        "precision"
    ],
    "wof:name":"Descamps L'avenu Sarl",
    "wof:placetype":"venue"
},
  "geometry": {"coordinates":[3.064857,50.353138],"type":"Point"}
}