{
  "type": "Feature",
  "properties": {
    "addr:full":"Av Descartes Beauvais Picardie 60000",
    "addr:postcode":"60000",
    "addr:street":"Av Descartes;Picardie",
    "iso:country":"FR",
    "sg:address":"Av Descartes",
    "sg:city":"Beauvais",
    "sg:orig_category":"Unclassifiable Establishments",
    "sg:phone":"+33 3 44 05 40 35",
    "sg:postcode":"60000",
    "sg:province":"Picardie",
    "wof:name":"Paris Caramels S.a.",
    "wof:placetype":"venue"
},
  "geometry": {"coordinates":[2.115149,49.409241],"type":"Point"}
}