{
  "type": "Feature",
  "properties": {
    "addr:full":"36 Rue Des Etats G\u00e9n\u00e9raux 78000 Versailles Ile de France 78000",
    "addr:housenumber":"36",
    "addr:postcode":"78000;78000",
    "addr:street":"Rue Des Etats Ge\u0301Ne\u0301Raux",
    "iso:country":"FR",
    "sg:address":"36 Rue Des Etats G\u00e9n\u00e9raux 78000 Versailles",
    "sg:classifiers":[
        {
            "category":"Banks & Credit Unions",
            "subcategory":"Financial Services",
            "type":"Services"
        }
    ],
    "sg:phone":"+33 1 39 50 00 80",
    "sg:postcode":"78000",
    "sg:province":"Ile de France",
    "sg:tags":[
        "banking",
        "finance",
        "insurance"
    ],
    "wof:name":"Cecgav",
    "wof:placetype":"venue"
},
  "geometry": {"coordinates":[2.134985,48.797623],"type":"Point"}
}