{
  "type": "Feature",
  "properties": {
    "addr:full":"9 route du Cor de Chasse 67400 Illkirch Graffenstaden Geispolsheim Alsace 67400",
    "addr:housenumber":"9",
    "addr:postcode":"67400;67400",
    "addr:street":"Route Du Cor De Chasse",
    "iso:country":"FR",
    "sg:address":"9 route du Cor de Chasse 67400 Illkirch Graffenstaden",
    "sg:city":"Geispolsheim",
    "sg:orig_category":"Personal Security Units",
    "sg:phone":"+33 3 90 40 34 70",
    "sg:postcode":"67400",
    "sg:province":"Alsace",
    "wof:name":"Deral Systemes Sa",
    "wof:placetype":"venue"
},
  "geometry": {"coordinates":[7.716636,48.512871],"type":"Point"}
}