{
  "type": "Feature",
  "properties": {
    "iso:country":"FR",
    "sg:address":"25 avenue Pierre 1er de Serbie 75116 Paris",
    "sg:classifiers":[
        {
            "category":"Manufacturing",
            "subcategory":"Metals",
            "type":"Manufacturing & Wholesale Goods"
        }
    ],
    "sg:phone":"+33 1 47 20 57 00",
    "sg:province":"Languedoc-Roussillon",
    "sg:tags":[
        "ironmongery"
    ],
    "wof:name":"Botex International Sarl",
    "wof:placetype":"venue"
},
  "geometry": {"coordinates":[2.29786,48.866879],"type":"Point"}
}