{
  "type": "Feature",
  "properties": {
    "addr:full":"A\u00e9roport Campo Dell'Oro Ajaccio Corse 20090",
    "addr:postcode":"20090",
    "iso:country":"FR",
    "sg:address":"A\u00e9roport Campo Dell'Oro",
    "sg:city":"Ajaccio",
    "sg:orig_category":"Non-Classified Establishments",
    "sg:phone":"+33 4 95 23 57 80",
    "sg:postcode":"20090",
    "sg:province":"Corse",
    "wof:name":"Air France S.a.",
    "wof:placetype":"venue"
},
  "geometry": {"coordinates":[8.778594,41.926685],"type":"Point"}
}