{
  "type": "Feature",
  "properties": {
    "addr:full":"134 Avenue D'Avignon 84700 Sorgues Midi Pyr\u00e9n\u00e9es",
    "addr:housenumber":"134",
    "addr:postcode":"84700",
    "addr:street":"Avenue D'Avignon",
    "iso:country":"FR",
    "sg:address":"134 Avenue D'Avignon 84700 Sorgues",
    "sg:classifiers":[
        {
            "category":"Manufacturing",
            "subcategory":"Chemicals & Compounds",
            "type":"Manufacturing & Wholesale Goods"
        }
    ],
    "sg:phone":"+33 4 90 33 62 00",
    "sg:province":"Midi Pyr\u00e9n\u00e9es",
    "sg:tags":[
        "pharmaceutical",
        "chemistry",
        "-",
        "by-product"
    ],
    "wof:name":"Snpe",
    "wof:placetype":"venue"
},
  "geometry": {"coordinates":[4.872004,44.008018],"type":"Point"}
}