{
  "type": "Feature",
  "properties": {
    "addr:full":"Zi Sablotiers 49350 Gennes Pays de Loire 49350",
    "addr:postcode":"49350;49350",
    "addr:street":"Gennes",
    "iso:country":"FR",
    "sg:address":"Zi Sablotiers 49350 Gennes",
    "sg:classifiers":[
        {
            "category":"Farming",
            "subcategory":"Farm & Veterinary Services",
            "type":"Manufacturing & Wholesale Goods"
        }
    ],
    "sg:phone":"+33 2 41 51 90 87",
    "sg:postcode":"49350",
    "sg:province":"Pays de Loire",
    "sg:tags":[
        "pharmaceutical",
        "livestock",
        "-",
        "chemical",
        "animal",
        "breeding",
        "chemistry",
        "agriculture",
        "by-product"
    ],
    "wof:name":"Caval",
    "wof:placetype":"venue"
},
  "geometry": {"coordinates":[-0.232118,47.343426],"type":"Point"}
}