{
  "type": "Feature",
  "properties": {
    "iso:country":"FR",
    "sg:address":"33, Av. de la Commune de Paris, 91220 Br\u00e9tigny sur Orge",
    "sg:orig_category":"Unclassifiable Establishments",
    "sg:phone":"+33 1 60 84 49 81",
    "sg:province":"Ile de France",
    "wof:name":"Entreprise Bouget S.a.",
    "wof:placetype":"venue"
},
  "geometry": {"coordinates":[2.302144,48.592178],"type":"Point"}
}