{
  "type": "Feature",
  "properties": {
    "iso:country":"FR",
    "sg:address":"Quai du Rh\u00f4ne - Quartier la Bocquette",
    "sg:city":"Miribel",
    "sg:orig_category":"Unclassifiable Establishments",
    "sg:phone":"+33 4 78 55 69 28",
    "sg:postcode":"01700",
    "sg:province":"Rhone-Alpes",
    "wof:name":"Promafor S.a.r.l.",
    "wof:placetype":"venue"
},
  "geometry": {"coordinates":[4.96153,45.828629],"type":"Point"}
}