{
  "type": "Feature",
  "properties": {
    "addr:full":"5 Route De Puits Berteau 18100 Vierzon Vierzon Centre 18100",
    "addr:housenumber":"5;vierzon",
    "addr:postcode":"18100;18100",
    "addr:street":"Route De Puits Berteau",
    "iso:country":"FR",
    "sg:address":"5 Route De Puits Berteau 18100 Vierzon",
    "sg:city":"Vierzon",
    "sg:classifiers":[
        {
            "category":"Utilities",
            "type":"Services"
        }
    ],
    "sg:phone":"+33 2 48 52 93 60",
    "sg:postcode":"18100",
    "sg:province":"Centre",
    "sg:tags":[
        "raw",
        "energy",
        "material"
    ],
    "wof:name":"Generale Des Eaux",
    "wof:placetype":"venue"
},
  "geometry": {"coordinates":[2.080752,47.231617],"type":"Point"}
}