{
  "type": "Feature",
  "properties": {
    "addr:full":"Zone Industrielle Canal Terray 10400 Nogent Sur Seine Champagne 10400",
    "addr:postcode":"10400;10400",
    "addr:street":"Zone Industrielle Canal Terray",
    "iso:country":"FR",
    "sg:address":"Zone Industrielle Canal Terray 10400 Nogent Sur Seine",
    "sg:classifiers":[
        {
            "category":"Manufacturing",
            "subcategory":"Wood Products",
            "type":"Manufacturing & Wholesale Goods"
        }
    ],
    "sg:phone":"+33 3 25 39 78 70",
    "sg:postcode":"10400",
    "sg:province":"Champagne",
    "sg:tags":[
        "printing",
        "miscellaneous",
        "publishing"
    ],
    "wof:name":"Alves Rei Sarl",
    "wof:placetype":"venue"
},
  "geometry": {"coordinates":[3.50251,48.492336],"type":"Point"}
}