{
  "type": "Feature",
  "properties": {
    "iso:country":"FR",
    "sg:address":"B.P. 7, 76210 Saint Eustache la For\u00eat^^ZA de la Mare Carel, 76210 Saint Eustache la For\u00eat",
    "sg:orig_category":"Fer g\u00e9n\u00e9ral Fournitures industrielles M\u00e9taux Quincailleries",
    "sg:phone":"+33 2 35 39 61 51",
    "sg:postcode":"76210",
    "sg:province":"Haute Normandie",
    "wof:name":"Letierce S.a.",
    "wof:placetype":"venue"
},
  "geometry": {"coordinates":[0.536504,49.57217],"type":"Point"}
}