{
  "type": "Feature",
  "properties": {
    "addr:full":"1, Place Thierry Nieg, 68800 Vieux Thann Thann Alsace 68800",
    "addr:housenumber":"1",
    "addr:postcode":"68800;68800",
    "addr:street":"Place Thierry Nieg",
    "iso:country":"FR",
    "sg:address":"1, Place Thierry Nieg, 68800 Vieux Thann",
    "sg:city":"Thann",
    "sg:orig_category":"Unclassifiable Establishments",
    "sg:phone":"+33 3 89 37 87 87",
    "sg:postcode":"68800",
    "sg:province":"Alsace",
    "wof:name":"Automatismes Et Electricit\u00e9 Industrielle S.a.r.l.",
    "wof:placetype":"venue"
},
  "geometry": {"coordinates":[7.124266,47.807201],"type":"Point"}
}