{
  "type": "Feature",
  "properties": {
    "iso:country":"FR",
    "sg:address":"Le Vertin 56660 St Jean Brevelay",
    "sg:city":"Saint-Jean-Br\u00e9velay",
    "sg:classifiers":[
        {
            "category":"Farming",
            "subcategory":"Livestock Farm",
            "type":"Manufacturing & Wholesale Goods"
        }
    ],
    "sg:phone":"+33 2 97 60 31 44",
    "sg:postcode":"56660",
    "sg:province":"Bretagne",
    "sg:tags":[
        "grain",
        "agriculture",
        "cereal"
    ],
    "wof:name":"Centrale Cooperative Agricole Bretonne (cecab)",
    "wof:placetype":"venue"
},
  "geometry": {"coordinates":[-2.719759,47.846764],"type":"Point"}
}