{
  "type": "Feature",
  "properties": {
    "addr:full":"Rue Victor Hugo 59195 Herin Nord Pas-de-Calais 59195",
    "addr:postcode":"59195;59195",
    "addr:street":"Rue Victor Hugo;Herin Nord",
    "iso:country":"FR",
    "sg:address":"Rue Victor Hugo 59195 Herin",
    "sg:classifiers":[
        {
            "category":"Professional",
            "subcategory":"Business Services",
            "type":"Services"
        }
    ],
    "sg:phone":"+33 3 27 29 03 78",
    "sg:postcode":"59195",
    "sg:province":"Nord Pas-de-Calais",
    "sg:tags":[
        "industrial",
        "advice",
        "motor-cars",
        "equipment",
        "vehicle",
        "transport"
    ],
    "wof:name":"Ibanez Pere Et Fils",
    "wof:placetype":"venue"
},
  "geometry": {"coordinates":[3.45515,50.362736],"type":"Point"}
}