{
  "type": "Feature",
  "properties": {
    "iso:country":"FR",
    "sg:address":"15, Rue Eug\u00e8ne Flachat, 75017 Paris",
    "sg:orig_category":"Unclassifiable Establishments",
    "sg:phone":"+33 1 42 12 82 82",
    "sg:province":"Ile de France",
    "wof:name":"B. Et H. Viandes S.a.",
    "wof:placetype":"venue"
},
  "geometry": {"coordinates":[2.299183,48.88699],"type":"Point"}
}