{
  "type": "Feature",
  "properties": {
    "iso:country":"FR",
    "sg:address":"ZI Fosse Maussoin",
    "sg:city":"Clichy sous Bois",
    "sg:orig_category":"Non-Classified Establishments",
    "sg:phone":"+33 1 43 01 31 50",
    "sg:postcode":"93390",
    "sg:province":"Ile de France",
    "wof:name":"C.d.e. S.a. - Construction D\u00e9coration Equipement",
    "wof:placetype":"venue"
},
  "geometry": {"coordinates":[2.545846,48.910027],"type":"Point"}
}