{
  "type": "Feature",
  "properties": {
    "iso:country":"FR",
    "sg:address":"RN 44",
    "sg:city":"Moncetz Longevas",
    "sg:orig_category":"Non-Classified Establishments",
    "sg:phone":"+33 3 26 68 30 22",
    "sg:postcode":"51470",
    "sg:province":"Champagne",
    "wof:name":"Caravanex S.a.r.l.",
    "wof:placetype":"venue"
},
  "geometry": {"coordinates":[4.384128,48.954563],"type":"Point"}
}