{
  "type": "Feature",
  "properties": {
    "iso:country":"FR",
    "sg:address":"4 Rue Mens 55000 Bar Le Duc",
    "sg:classifiers":[
        {
            "category":"Manufacturing",
            "subcategory":"Chemicals & Compounds",
            "type":"Manufacturing & Wholesale Goods"
        }
    ],
    "sg:phone":"+33 3 29 79 49 50",
    "sg:postcode":"55000",
    "sg:province":"Lorraine",
    "sg:tags":[
        "pharmaceutical",
        "energy",
        "chemistry",
        "-",
        "by-product"
    ],
    "wof:name":"Compagnie Petroliere De L'est (cpe)",
    "wof:placetype":"venue"
},
  "geometry": {"coordinates":[5.173839,48.770531],"type":"Point"}
}