{
  "type": "Feature",
  "properties": {
    "iso:country":"FR",
    "sg:address":"les Chaffangeons 69820 Fleurie",
    "sg:orig_category":"Unclassifiable Establishments",
    "sg:phone":"+33 4 74 04 11 20",
    "sg:postcode":"69820",
    "sg:province":"Rhone-Alpes",
    "wof:name":"Domaine Des Chaffangeons",
    "wof:placetype":"venue"
},
  "geometry": {"coordinates":[4.70286,46.190022],"type":"Point"}
}