{
  "type": "Feature",
  "properties": {
    "addr:full":"38 Rue Roubaix 59242 Templeuve Nord Pas-de-Calais 59242",
    "addr:housenumber":"38",
    "addr:postcode":"59242;59242",
    "addr:street":"Rue Roubaix",
    "iso:country":"FR",
    "sg:address":"38 Rue Roubaix 59242 Templeuve",
    "sg:classifiers":[
        {
            "category":"Shopping",
            "subcategory":"Clothing, Apparel, & Fashions",
            "type":"Retail Goods"
        }
    ],
    "sg:phone":"+33 3 20 59 33 11",
    "sg:postcode":"59242",
    "sg:province":"Nord Pas-de-Calais",
    "sg:tags":[
        "textile",
        "clothing",
        "clothes"
    ],
    "wof:name":"Etablissements Marchand",
    "wof:placetype":"venue"
},
  "geometry": {"coordinates":[3.173416,50.527954],"type":"Point"}
}