{
  "type": "Feature",
  "properties": {
    "iso:country":"FR",
    "sg:address":"11 bis, Impasse Abel Varet, 92110 Clichy",
    "sg:orig_category":"Non-Classified Establishments",
    "sg:phone":"+33 1 47 31 47 00",
    "sg:postcode":"92110",
    "sg:province":"Ile de France",
    "wof:name":"Arbois S.a.",
    "wof:placetype":"venue"
},
  "geometry": {"coordinates":[2.315971,48.89999],"type":"Point"}
}