{
  "type": "Feature",
  "properties": {
    "addr:full":"35 Rue Jean Pierre Timbaud 93240 Stains Ile de France",
    "addr:housenumber":"35",
    "addr:postcode":"93240;ile",
    "addr:street":"Rue Jean Pierre Timbaud",
    "iso:country":"FR",
    "sg:address":"35 Rue Jean Pierre Timbaud 93240 Stains",
    "sg:classifiers":[
        {
            "category":"Manufacturing",
            "subcategory":"Paper Products",
            "type":"Manufacturing & Wholesale Goods"
        }
    ],
    "sg:phone":"+33 1 48 21 60 41",
    "sg:province":"Ile de France",
    "sg:tags":[
        "packaging",
        "material",
        "-",
        "cardboard"
    ],
    "wof:name":"Lasys Sa",
    "wof:placetype":"venue"
},
  "geometry": {"coordinates":[2.37387,48.962311],"type":"Point"}
}