{
  "type": "Feature",
  "properties": {
    "addr:full":"111 Rue De Rosny BP 85 93511 Montreuil Haute Normandie",
    "addr:housenumber":"111;85",
    "addr:postcode":"93511",
    "addr:street":"Rue De Rosny Bp",
    "iso:country":"FR",
    "sg:address":"111 Rue De Rosny BP 85 93511 Montreuil",
    "sg:classifiers":[
        {
            "category":"Professional",
            "subcategory":"Engineering",
            "type":"Services"
        }
    ],
    "sg:phone":"+33 1 42 87 57 96",
    "sg:province":"Haute Normandie",
    "sg:tags":[
        "machine",
        "-",
        "mechanical"
    ],
    "wof:name":"Spg Tech Sa",
    "wof:placetype":"venue"
},
  "geometry": {"coordinates":[2.43687,48.858181],"type":"Point"}
}