{
  "type": "Feature",
  "properties": {
    "iso:country":"FR",
    "sg:address":"23, ZI Chuslan, 30200 Bagnols sur C\u00e8ze",
    "sg:orig_category":"Unclassifiable Establishments",
    "sg:phone":"+33 4 66 90 05 14",
    "sg:province":"Languedoc-Roussillon",
    "wof:name":"Verboom Durouchard",
    "wof:placetype":"venue"
},
  "geometry": {"coordinates":[4.541553,44.125595],"type":"Point"}
}