{
  "type": "Feature",
  "properties": {
    "iso:country":"FR",
    "sg:address":"Port de P\u00eache",
    "sg:city":"Lorient",
    "sg:orig_category":"Non-Classified Establishments",
    "sg:phone":"+33 2 97 37 30 46",
    "sg:postcode":"56100",
    "sg:province":"Bretagne",
    "wof:name":"Le Chalut Des 2 Ports S.a.",
    "wof:placetype":"venue"
},
  "geometry": {"coordinates":[-3.365181,47.748108],"type":"Point"}
}