{
  "type": "Feature",
  "properties": {
    "iso:country":"FR",
    "sg:address":"Za Les Pr\u00e9s d'Andy 77950 St Germain Laxis",
    "sg:classifiers":[
        {
            "category":"Autos & Motor Vehicles",
            "subcategory":"Auto Supplies",
            "type":"Retail Goods"
        }
    ],
    "sg:phone":"+33 1 64 38 44 44",
    "sg:postcode":"77950",
    "sg:province":"Ile de France",
    "sg:tags":[
        "automobile",
        "accessory"
    ],
    "wof:name":"Goodridge France S.a.r.l.",
    "wof:placetype":"venue"
},
  "geometry": {"coordinates":[2.71183,48.581059],"type":"Point"}
}