{
  "type": "Feature",
  "properties": {
    "addr:full":"7 Rue Ampere Zac De Kerfontaine 56400 Pluneret Pluneret Bretagne 56400",
    "addr:housenumber":"7",
    "addr:postcode":"56400;56400",
    "addr:street":"Rue Ampere Zac De Kerfontaine",
    "iso:country":"FR",
    "sg:address":"7 Rue Ampere Zac De Kerfontaine 56400 Pluneret",
    "sg:city":"Pluneret",
    "sg:classifiers":[
        {
            "category":"Autos & Motor Vehicles",
            "subcategory":"Boat Sales",
            "type":"Retail Goods"
        }
    ],
    "sg:phone":"+33 2 97 56 30 89",
    "sg:postcode":"56400",
    "sg:province":"Bretagne",
    "sg:tags":[
        "equipment",
        "transport"
    ],
    "wof:name":"Jb Assistance",
    "wof:placetype":"venue"
},
  "geometry": {"coordinates":[-2.949126,47.63744],"type":"Point"}
}