{
  "type": "Feature",
  "properties": {
    "iso:country":"FR",
    "sg:address":"49, Rue Marcel Paul, 93290 Tremblay en France",
    "sg:orig_category":"Unclassifiable Establishments",
    "sg:phone":"+33 1 48 60 09 25",
    "sg:province":"Ile de France",
    "wof:name":"D.p.n. S.a.s. - D\u00e9veloppement De Produits Nouveaux",
    "wof:placetype":"venue"
},
  "geometry": {"coordinates":[2.561057,48.964336],"type":"Point"}
}