{
  "type": "Feature",
  "properties": {
    "iso:country":"FR",
    "sg:address":"12, Av Gambetta, 46500 Gramat",
    "sg:orig_category":"Unclassifiable Establishments",
    "sg:phone":"+33 5 65 38 80 11",
    "sg:province":"Midi Pyr\u00e9n\u00e9es",
    "wof:name":"Axa S.a.",
    "wof:placetype":"venue"
},
  "geometry": {"coordinates":[1.71894,44.700165],"type":"Point"}
}