{
  "type": "Feature",
  "properties": {
    "addr:full":"32 rue du Fort Gassion 62120 Aire sur la Lys Nord Pas-de-Calais 62120",
    "addr:housenumber":"32",
    "addr:postcode":"62120;62120",
    "addr:street":"Rue Du Fort Gassion;Aire;La Lys Nord",
    "iso:country":"FR",
    "sg:address":"32 rue du Fort Gassion 62120 Aire sur la Lys",
    "sg:classifiers":[
        {
            "category":"Manufacturing",
            "subcategory":"Building Materials",
            "type":"Manufacturing & Wholesale Goods"
        }
    ],
    "sg:phone":"+33 3 21 95 60 80",
    "sg:postcode":"62120",
    "sg:province":"Nord Pas-de-Calais",
    "sg:tags":[
        "masonry",
        "brick",
        "fired"
    ],
    "wof:name":"C\u00e9ramique De La Lys Sa",
    "wof:placetype":"venue"
},
  "geometry": {"coordinates":[2.403457,50.643696],"type":"Point"}
}