{
  "type": "Feature",
  "properties": {
    "iso:country":"FR",
    "sg:address":"73 Rue De La Tour 42002 St Etienne",
    "sg:city":"La Tour",
    "sg:classifiers":[
        {
            "category":"Health Services",
            "subcategory":"Health Practitioner",
            "type":"Services"
        }
    ],
    "sg:phone":"+33 4 77 91 30 30",
    "sg:postcode":"74250",
    "sg:province":"Rhone-Alpes",
    "sg:tags":[
        "fabric",
        "equipment",
        "-",
        "precision",
        "textile",
        "instrument",
        "clothing"
    ],
    "wof:name":"Gibaud",
    "wof:placetype":"venue"
},
  "geometry": {"coordinates":[4.38815,45.467533],"type":"Point"}
}