{
  "type": "Feature",
  "properties": {
    "addr:full":"19, Av. du Grand Ramier, 31400 Toulouse Midi Pyr\u00e9n\u00e9es",
    "addr:postcode":"31400",
    "addr:street":"19 Av. Du Grand Ramier",
    "iso:country":"FR",
    "sg:address":"19, Av. du Grand Ramier, 31400 Toulouse",
    "sg:orig_category":"Non-Classified Establishments",
    "sg:phone":"+33 5 61 14 81 14",
    "sg:province":"Midi Pyr\u00e9n\u00e9es",
    "wof:name":"R\u00e9gie Municipale D'electricit\u00e9",
    "wof:placetype":"venue"
},
  "geometry": {"coordinates":[1.439529,43.591751],"type":"Point"}
}