{
  "type": "Feature",
  "properties": {
    "iso:country":"FR",
    "sg:address":"220 Rte De Rambouillet 78125 St Hilarion",
    "sg:classifiers":[
        {
            "category":"Wholesale",
            "subcategory":"Meat",
            "type":"Manufacturing & Wholesale Goods"
        }
    ],
    "sg:phone":"+33 1 34 83 57 27",
    "sg:postcode":"78125",
    "sg:province":"Ile de France",
    "sg:tags":[
        "food",
        "cooked",
        "product",
        "related"
    ],
    "wof:name":"Ste Nouvelle Domaine De Sery",
    "wof:placetype":"venue"
},
  "geometry": {"coordinates":[1.71825,48.61607],"type":"Point"}
}