{
  "type": "Feature",
  "properties": {
    "addr:full":"400, Rue Joseph L\u00e9on Jacquemaire, 69400 Villefranche sur Sa\u00f4ne Rhone-Alpes",
    "addr:housenumber":"400",
    "addr:postcode":"69400",
    "addr:street":"Rue Joseph Le\u0301On Jacquemaire",
    "iso:country":"FR",
    "sg:address":"400, Rue Joseph L\u00e9on Jacquemaire, 69400 Villefranche sur Sa\u00f4ne",
    "sg:orig_category":"Unclassifiable Establishments",
    "sg:phone":"+33 4 74 68 24 65",
    "sg:province":"Rhone-Alpes",
    "wof:name":"Theis Cerclage S.a.",
    "wof:placetype":"venue"
},
  "geometry": {"coordinates":[4.743487,45.992931],"type":"Point"}
}