{
  "type": "Feature",
  "properties": {
    "iso:country":"FR",
    "sg:address":"140, Cours Charlemagne, 69286 Lyon C\u00e9dex 02",
    "sg:orig_category":"Non-Classified Establishments",
    "sg:phone":"+33 4 72 77 10 50",
    "sg:province":"Rhone-Alpes",
    "wof:name":"Jacobs Serete S.a.",
    "wof:placetype":"venue"
},
  "geometry": {"coordinates":[4.81821,45.73975],"type":"Point"}
}