{
  "type": "Feature",
  "properties": {
    "iso:country":"FR",
    "sg:address":"51 rue Gambetta 69240 Thizy",
    "sg:classifiers":[
        {
            "category":"Organizations",
            "subcategory":"Professional Association",
            "type":"Services"
        }
    ],
    "sg:phone":"+33 825 84 40 36",
    "sg:postcode":"69240",
    "sg:province":"Rhone-Alpes",
    "sg:tags":[
        "call"
    ],
    "wof:name":"Absys",
    "wof:placetype":"venue"
},
  "geometry": {"coordinates":[4.316623,46.025753],"type":"Point"}
}