{
  "type": "Feature",
  "properties": {
    "addr:full":"58 Avenue Montaigne 75008 Paris Ile de France 75008",
    "addr:housenumber":"58",
    "addr:postcode":"75008;75008",
    "addr:street":"Avenue Montaigne",
    "iso:country":"FR",
    "sg:address":"58 Avenue Montaigne 75008 Paris",
    "sg:classifiers":[
        {
            "category":"Shopping",
            "subcategory":"Clothing, Apparel, & Fashions",
            "type":"Retail Goods"
        }
    ],
    "sg:phone":"+33 1 45 61 08 39",
    "sg:postcode":"75008",
    "sg:province":"Ile de France",
    "sg:tags":[
        "textile",
        "clothing",
        "clothes"
    ],
    "wof:name":"St Dupont",
    "wof:placetype":"venue"
},
  "geometry": {"coordinates":[2.309047,48.86816],"type":"Point"}
}