{
  "type": "Feature",
  "properties": {
    "iso:country":"FR",
    "sg:address":"97 Rue Charles Van Wyngene 77181 Courtry",
    "sg:classifiers":[
        {
            "category":"Manufacturing",
            "subcategory":"Printing",
            "type":"Manufacturing & Wholesale Goods"
        }
    ],
    "sg:phone":"+33 1 60 08 38 48",
    "sg:province":"Ile de France",
    "sg:tags":[
        "publishing"
    ],
    "wof:name":"Imprimerie Blanc Noir Couleur Sa",
    "wof:placetype":"venue"
},
  "geometry": {"coordinates":[2.603692,48.910397],"type":"Point"}
}