{
  "type": "Feature",
  "properties": {
    "iso:country":"FR",
    "sg:address":"La Mouchere 61130 St Cyr La Rosiere",
    "sg:city":"Appenai-sous-Bell\u00eame",
    "sg:classifiers":[
        {
            "category":"Farming",
            "subcategory":"Livestock Farm",
            "type":"Manufacturing & Wholesale Goods"
        }
    ],
    "sg:phone":"+33 2 33 73 43 10",
    "sg:postcode":"61130",
    "sg:province":"Basse Normandie",
    "sg:tags":[
        "breeding",
        "agriculture",
        "animal"
    ],
    "wof:name":"Sarl Agricole De Famille Ferme De La Mouchere (sarl Ferme De La Mouchere)",
    "wof:placetype":"venue"
},
  "geometry": {"coordinates":[0.64795,48.336258],"type":"Point"}
}