{
  "type": "Feature",
  "properties": {
    "addr:full":"Rue du Site Munchhausen Alsace 67470",
    "addr:postcode":"67470",
    "addr:street":"Rue Du Site",
    "iso:country":"FR",
    "sg:address":"Rue du Site",
    "sg:city":"Munchhausen",
    "sg:orig_category":"Non-Classified Establishments",
    "sg:phone":"+33 3 88 86 51 45",
    "sg:postcode":"67470",
    "sg:province":"Alsace",
    "wof:name":"Menuiserie-scierie A. Wargel S.a.r.l.",
    "wof:placetype":"venue"
},
  "geometry": {"coordinates":[8.152843,48.918537],"type":"Point"}
}