{
  "type": "Feature",
  "properties": {
    "addr:full":"23, Av. de Buros, 64000 Pau Pau Aquitaine 64000",
    "addr:postcode":"64000;64000",
    "addr:street":"23 Av. De Buros",
    "iso:country":"FR",
    "sg:address":"23, Av. de Buros, 64000 Pau",
    "sg:city":"Pau",
    "sg:orig_category":"Unclassifiable Establishments",
    "sg:phone":"+33 5 59 80 10 44",
    "sg:postcode":"64000",
    "sg:province":"Aquitaine",
    "wof:name":"Dimatrap S.a.",
    "wof:placetype":"venue"
},
  "geometry": {"coordinates":[-0.35251,43.309647],"type":"Point"}
}