{
  "type": "Feature",
  "properties": {
    "addr:full":"Z.A. du Champ du Latin Cosne Cours sur Loire Bourgogne 58200",
    "addr:postcode":"58200",
    "addr:street":"Z.A. Du Champ Du;Bourgogne",
    "iso:country":"FR",
    "sg:address":"Z.A. du Champ du Latin",
    "sg:city":"Cosne Cours sur Loire",
    "sg:orig_category":"Unclassifiable Establishments",
    "sg:phone":"+33 3 86 28 20 99",
    "sg:postcode":"58200",
    "sg:province":"Bourgogne",
    "wof:name":"Cosne Cintrage S.a.r.l.",
    "wof:placetype":"venue"
},
  "geometry": {"coordinates":[2.91696,47.394798],"type":"Point"}
}