{
  "type": "Feature",
  "properties": {
    "iso:country":"FR",
    "sg:address":"B.P. 25, 39401 Morez C\u00e9dex^^22, Rue de la R\u00e9publique, 39400 Morez",
    "sg:orig_category":"Non-Classified Establishments",
    "sg:phone":"+33 3 84 33 70 00",
    "sg:province":"Franche Comt\u00e9",
    "wof:name":"Finasse Pierre S.a.",
    "wof:placetype":"venue"
},
  "geometry": {"coordinates":[6.023062,46.525715],"type":"Point"}
}