{
  "type": "Feature",
  "properties": {
    "iso:country":"FR",
    "sg:address":"29 Rue Des Petits Ruisseaux 91370 Verri\u00e8res Le Buisson",
    "sg:classifiers":[
        {
            "category":"Professional",
            "subcategory":"Engineering",
            "type":"Services"
        }
    ],
    "sg:phone":"+33 1 69 75 20 60",
    "sg:postcode":"91370",
    "sg:province":"Ile de France",
    "sg:tags":[
        "machine",
        "-",
        "mechanical"
    ],
    "wof:name":"Soleclim",
    "wof:placetype":"venue"
},
  "geometry": {"coordinates":[2.283072,48.748741],"type":"Point"}
}