{
  "type": "Feature",
  "properties": {
    "addr:full":"14 Rue D Assas 75006 Paris Ile de France",
    "addr:housenumber":"14",
    "addr:postcode":"75006",
    "addr:street":"Rue D Assas",
    "iso:country":"FR",
    "sg:address":"14 Rue D Assas 75006 Paris",
    "sg:classifiers":[
        {
            "category":"Professional",
            "subcategory":"Printing & Photocopies",
            "type":"Services"
        }
    ],
    "sg:phone":"+33 1 44 39 48 48",
    "sg:province":"Ile de France",
    "sg:tags":[
        "publishing"
    ],
    "wof:name":"Societe D'editions De Revues",
    "wof:placetype":"venue"
},
  "geometry": {"coordinates":[2.328294,48.849236],"type":"Point"}
}