{
  "type": "Feature",
  "properties": {
    "iso:country":"FR",
    "sg:address":"178 rue de Courcelles 75017 Paris",
    "sg:classifiers":[
        {
            "category":"Wholesale",
            "subcategory":"Fruits & Vegetables",
            "type":"Manufacturing & Wholesale Goods"
        }
    ],
    "sg:phone":"+33 1 42 12 26 60",
    "sg:postcode":"75017",
    "sg:province":"Ile de France",
    "sg:tags":[
        "product",
        "cereal"
    ],
    "wof:name":"Compagnie Europeenne De Cereales Sas",
    "wof:placetype":"venue"
},
  "geometry": {"coordinates":[2.298336,48.884132],"type":"Point"}
}