{
  "type": "Feature",
  "properties": {
    "addr:full":"22, Rue de la Bresse, 94550 Chevilly Larue Ile de France",
    "addr:housenumber":"22",
    "addr:postcode":"94550",
    "addr:street":"Rue De La Bresse",
    "iso:country":"FR",
    "sg:address":"22, Rue de la Bresse, 94550 Chevilly Larue",
    "sg:orig_category":"Unclassifiable Establishments",
    "sg:phone":"+33 1 46 86 21 06",
    "sg:province":"Ile de France",
    "wof:name":"Coquet Et Boussion S.a.",
    "wof:placetype":"venue"
},
  "geometry": {"coordinates":[2.36433,48.758095],"type":"Point"}
}