{
  "type": "Feature",
  "properties": {
    "iso:country":"FR",
    "sg:address":"B.P. 50, 33230 Coutras^^ZI, 33230 Coutras",
    "sg:city":"Coutras",
    "sg:orig_category":"Non-Classified Establishments",
    "sg:phone":"+33 5 57 49 81 00",
    "sg:postcode":"33230",
    "sg:province":"Aquitaine",
    "wof:name":"S.i.v.a.q. S.a. - Soci\u00e9t\u00e9 Industrielle Vitrage D'aquitaine",
    "wof:placetype":"venue"
},
  "geometry": {"coordinates":[-0.051856,45.004955],"type":"Point"}
}