{
  "type": "Feature",
  "properties": {
    "addr:full":"16, Chemin du Bois de Saget, 31240 Saint Jean Midi Pyr\u00e9n\u00e9es",
    "addr:housenumber":"16",
    "addr:postcode":"31240",
    "addr:street":"Chemin Du Bois De Saget",
    "iso:country":"FR",
    "sg:address":"16, Chemin du Bois de Saget, 31240 Saint Jean",
    "sg:orig_category":"Unclassifiable Establishments",
    "sg:phone":"+33 5 61 74 31 16",
    "sg:province":"Midi Pyr\u00e9n\u00e9es",
    "wof:name":"D.m.e. S.a.r.l. - Distribution Mesures Electroniques",
    "wof:placetype":"venue"
},
  "geometry": {"coordinates":[1.498827,43.660553],"type":"Point"}
}