{
  "type": "Feature",
  "properties": {
    "addr:full":"86, Av. d'Ar\u00e8s, 33000 Bordeaux Bordeaux Aquitaine 33000",
    "addr:postcode":"33000;33000",
    "addr:street":"86 Av. D'Are \u0300S",
    "iso:country":"FR",
    "sg:address":"86, Av. d'Ar\u00e8s, 33000 Bordeaux",
    "sg:city":"Bordeaux",
    "sg:orig_category":"Unclassifiable Establishments",
    "sg:phone":"+33 5 56 24 22 92",
    "sg:postcode":"33000",
    "sg:province":"Aquitaine",
    "wof:name":"Degert Et Rousseil E.u.r.l.",
    "wof:placetype":"venue"
},
  "geometry": {"coordinates":[-0.601003,44.836407],"type":"Point"}
}