{
  "type": "Feature",
  "properties": {
    "iso:country":"FR",
    "sg:address":"17, Rue Roger Saget, 28190 Saint Georges sur Eure",
    "sg:city":"Billancelles",
    "sg:orig_category":"Unclassifiable Establishments",
    "sg:phone":"+33 2 37 26 87 20",
    "sg:postcode":"28190",
    "sg:province":"Centre",
    "wof:name":"A.i.e.c. S.a.r.l. - Application Industrielle Equipement Construction",
    "wof:placetype":"venue"
},
  "geometry": {"coordinates":[1.352561,48.419212],"type":"Point"}
}