{
  "type": "Feature",
  "properties": {
    "addr:full":"190, Av Olivier Heuze, 72000 Le Mans Pays de Loire",
    "addr:housenumber":"190",
    "addr:postcode":"72000",
    "addr:street":"Av Olivier Heuze",
    "iso:country":"FR",
    "sg:address":"190, Av Olivier Heuze, 72000 Le Mans",
    "sg:orig_category":"Unclassifiable Establishments",
    "sg:phone":"+33 2 43 23 15 00",
    "sg:province":"Pays de Loire",
    "wof:name":"La Bureauth\u00e8que S.a.r.l.",
    "wof:placetype":"venue"
},
  "geometry": {"coordinates":[0.174216,47.993004],"type":"Point"}
}