{
  "type": "Feature",
  "properties": {
    "addr:full":"5 Avenue Du Marechal Foch 25000 Besan\u00e7on Franche Comt\u00e9 25000",
    "addr:housenumber":"5",
    "addr:postcode":"25000;25000",
    "addr:street":"Avenue Du Marechal Foch;Franche Comte\u0301",
    "iso:country":"FR",
    "sg:address":"5 Avenue Du Marechal Foch 25000 Besan\u00e7on",
    "sg:classifiers":[
        {
            "category":"Travel",
            "subcategory":"Hotels & Motels",
            "type":"Entertainment"
        }
    ],
    "sg:phone":"+33 3 81 88 27 26",
    "sg:postcode":"25000",
    "sg:province":"Franche Comt\u00e9",
    "sg:tags":[
        "professional",
        "hotels",
        "fair",
        "business",
        "restaurant"
    ],
    "wof:name":"Ibis Besan\u00c7on Centre Gare",
    "wof:placetype":"venue"
},
  "geometry": {"coordinates":[6.023034,47.246319],"type":"Point"}
}