{
  "type": "Feature",
  "properties": {
    "iso:country":"FR",
    "sg:address":"150 R Anne et Pierre de Beaujeu 69400 VILLEFRANCHE SUR SAONE",
    "sg:classifiers":[
        {
            "category":"Shopping",
            "subcategory":"Clothing, Apparel, & Fashions",
            "type":"Retail Goods"
        }
    ],
    "sg:phone":"+33 4 74 62 47 00",
    "sg:postcode":"69400",
    "sg:province":"Rhone-Alpes",
    "sg:tags":[
        "sportswear"
    ],
    "wof:name":"St\u00e9 Cepovett Sa",
    "wof:placetype":"venue"
},
  "geometry": {"coordinates":[4.719075,45.989071],"type":"Point"}
}