{
  "type": "Feature",
  "properties": {
    "addr:full":"zone d'Activit\u00e9 Ecoparc 27400 Heudebouville Haute Normandie",
    "addr:postcode":"27400",
    "addr:street":"Zone;Ecoparc;Haute Normandie",
    "iso:country":"FR",
    "sg:address":"zone d'Activit\u00e9 Ecoparc 27400 Heudebouville",
    "sg:classifiers":[
        {
            "category":"Government",
            "subcategory":"Post Office",
            "type":"Public Place"
        }
    ],
    "sg:phone":"+33 2 32 40 29 00",
    "sg:province":"Haute Normandie",
    "sg:tags":[
        "armchair",
        "chair",
        "period"
    ],
    "wof:name":"Polmarg Sa",
    "wof:placetype":"venue"
},
  "geometry": {"coordinates":[1.2364,49.195011],"type":"Point"}
}