{
  "type": "Feature",
  "properties": {
    "iso:country":"FR",
    "sg:address":"Grands Vernays 73730 Rognaix",
    "sg:classifiers":[
        {
            "category":"Manufacturing",
            "subcategory":"Wood Products",
            "type":"Manufacturing & Wholesale Goods"
        }
    ],
    "sg:phone":"+33 4 79 38 20 67",
    "sg:province":"Rhone-Alpes",
    "sg:tags":[
        "furniture"
    ],
    "wof:name":"Scierie Reunie De Savoie Sa",
    "wof:placetype":"venue"
},
  "geometry": {"coordinates":[6.438065,45.59708],"type":"Point"}
}