{
  "type": "Feature",
  "properties": {
    "iso:country":"FR",
    "sg:address":"1 rue du Docteur Friry; BP 199; BELFORT; 90004 CEDEX",
    "sg:city":"Belfort",
    "sg:classifiers":[
        {
            "category":"Shopping",
            "subcategory":"Computers & Home Electronics",
            "type":"Retail Goods"
        }
    ],
    "sg:phone":"+33 3 84 54 54 54",
    "sg:postcode":"90000",
    "sg:province":"Franche Comt\u00e9",
    "sg:tags":[
        "chamber",
        "commerce"
    ],
    "wof:name":"Chambre De Commerce De Belfort",
    "wof:placetype":"venue"
},
  "geometry": {"coordinates":[6.85731,47.634129],"type":"Point"}
}