{
  "type": "Feature",
  "properties": {
    "addr:full":"45, Rue de Verclun, 94500 Champigny sur Marne Ile de France 94500",
    "addr:housenumber":"45",
    "addr:postcode":"94500;94500",
    "addr:street":"Rue De Verclun",
    "iso:country":"FR",
    "sg:address":"45, Rue de Verclun, 94500 Champigny sur Marne",
    "sg:orig_category":"Non-Classified Establishments",
    "sg:phone":"+33 1 47 06 93 42",
    "sg:postcode":"94500",
    "sg:province":"Ile de France",
    "wof:name":"Clim\u00e9ole S.a.",
    "wof:placetype":"venue"
},
  "geometry": {"coordinates":[2.51158,48.813404],"type":"Point"}
}