{
  "type": "Feature",
  "properties": {
    "iso:country":"FR",
    "sg:address":"13 Rue Du Tanay 74960 Cran Gevrier",
    "sg:classifiers":[
        {
            "category":"Professional",
            "subcategory":"Engineering",
            "type":"Services"
        }
    ],
    "sg:phone":"+33 4 50 69 36 91",
    "sg:postcode":"74960",
    "sg:province":"Rhone-Alpes",
    "sg:tags":[
        "machine",
        "-",
        "mechanical"
    ],
    "wof:name":"Lam Sa",
    "wof:placetype":"venue"
},
  "geometry": {"coordinates":[6.090166,45.892452],"type":"Point"}
}