{
  "type": "Feature",
  "properties": {
    "addr:full":"503, Av. du Dauphin\u00e9, 38530 Pontcharra Rhone-Alpes",
    "addr:postcode":"38530",
    "addr:street":"503 Av. Du Dauphine\u0301",
    "iso:country":"FR",
    "sg:address":"503, Av. du Dauphin\u00e9, 38530 Pontcharra",
    "sg:orig_category":"Unclassifiable Establishments",
    "sg:phone":"+33 4 76 71 90 22",
    "sg:province":"Rhone-Alpes",
    "wof:name":"Moulin Vieux S.a.",
    "wof:placetype":"venue"
},
  "geometry": {"coordinates":[6.01692,45.426331],"type":"Point"}
}