{
  "type": "Feature",
  "properties": {
    "addr:full":"B.P. 225 Gravelines Nord Pas-de-Calais 59820",
    "addr:housenumber":"b.p. 225",
    "addr:postcode":"59820",
    "addr:street":"Gravelines Nord",
    "iso:country":"FR",
    "sg:address":"B.P. 225",
    "sg:city":"Gravelines",
    "sg:orig_category":"Non-Classified Establishments",
    "sg:phone":"+33 3 28 65 35 97",
    "sg:postcode":"59820",
    "sg:province":"Nord Pas-de-Calais",
    "wof:name":"Entreprise Nouvelle Isotherma S.a.",
    "wof:placetype":"venue"
},
  "geometry": {"coordinates":[2.13518,50.990211],"type":"Point"}
}