{
  "type": "Feature",
  "properties": {
    "addr:full":"Rte De Bellec\u00f4te 73121 Courchevel Cedex Franche Comt\u00e9",
    "addr:postcode":"73121",
    "addr:street":"Rte De Belleco\u0302Te",
    "iso:country":"FR",
    "sg:address":"Rte De Bellec\u00f4te 73121 Courchevel Cedex",
    "sg:classifiers":[
        {
            "category":"Travel",
            "subcategory":"Hotels & Motels",
            "type":"Entertainment"
        }
    ],
    "sg:phone":"+33 4 79 08 01 10",
    "sg:province":"Franche Comt\u00e9",
    "sg:tags":[
        "hotels",
        "business",
        "restaurant"
    ],
    "wof:name":"Hotel Le Lana Courchevel",
    "wof:placetype":"venue"
},
  "geometry": {"coordinates":[-97.432793,35.515968],"type":"Point"}
}