{
  "type": "Feature",
  "properties": {
    "addr:full":"2 R Des Varennes Parc D'Activit\u00e9s De Varennes 10140 Vendeuvre Sur Barse Champagne 10140",
    "addr:housenumber":"2",
    "addr:postcode":"10140;10140",
    "addr:street":"R Des Varennes Parc D'Activite \u0301S De Varennes",
    "iso:country":"FR",
    "sg:address":"2 R Des Varennes Parc D'Activit\u00e9s De Varennes 10140 Vendeuvre Sur Barse",
    "sg:classifiers":[
        {
            "category":"Professional",
            "subcategory":"Engineering",
            "type":"Services"
        }
    ],
    "sg:phone":"+33 3 25 43 83 93",
    "sg:postcode":"10140",
    "sg:province":"Champagne",
    "sg:tags":[
        "machine",
        "-",
        "environment",
        "equipment",
        "machinery",
        "mechanical"
    ],
    "wof:name":"Sa Gamba & Rota",
    "wof:placetype":"venue"
},
  "geometry": {"coordinates":[4.452115,48.236336],"type":"Point"}
}