{
  "type": "Feature",
  "properties": {
    "iso:country":"FR",
    "sg:address":"7/9, Rue Constantin Pecqueur - ZAE des Ch\u00e2taigniers, 95157 Taverny C\u00e9dex",
    "sg:orig_category":"Non-Classified Establishments",
    "sg:phone":"+33 1 34 18 76 00",
    "sg:province":"Midi Pyr\u00e9n\u00e9es",
    "wof:name":"Saturnes Services S.a.r.l.",
    "wof:placetype":"venue"
},
  "geometry": {"coordinates":[2.22329,49.026966],"type":"Point"}
}