{
  "type": "Feature",
  "properties": {
    "addr:full":"Zi Champs De Berre 43240 St Just Malmont Saint-Just-Malmont Auvergne 43240",
    "addr:postcode":"43240;43240",
    "addr:street":"Zi Champs De Berre",
    "iso:country":"FR",
    "sg:address":"Zi Champs De Berre 43240 St Just Malmont",
    "sg:city":"Saint-Just-Malmont",
    "sg:classifiers":[
        {
            "category":"Wholesale",
            "subcategory":"Medical Equipment & Supplies",
            "type":"Manufacturing & Wholesale Goods"
        }
    ],
    "sg:phone":"+33 4 77 35 03 03",
    "sg:postcode":"43240",
    "sg:province":"Auvergne",
    "sg:tags":[
        "instrument",
        "health",
        "-",
        "precision"
    ],
    "wof:name":"Microval Sa",
    "wof:placetype":"venue"
},
  "geometry": {"coordinates":[4.313666,45.339558],"type":"Point"}
}