{
  "type": "Feature",
  "properties": {
    "addr:full":"38 Rue Du Mal Leclerc 94410 St Maurice Ile de France 94410",
    "addr:housenumber":"38",
    "addr:postcode":"94410;94410",
    "addr:street":"Rue Du Mal Leclerc;Ile De France",
    "iso:country":"FR",
    "sg:address":"38 Rue Du Mal Leclerc 94410 St Maurice",
    "sg:classifiers":[
        {
            "category":"Professional",
            "subcategory":"Advertising",
            "type":"Services"
        }
    ],
    "sg:phone":"+33 1 58 73 44 60",
    "sg:postcode":"94410",
    "sg:province":"Ile de France",
    "sg:tags":[
        "communication",
        "medium"
    ],
    "wof:name":"Black Line Sarl",
    "wof:placetype":"venue"
},
  "geometry": {"coordinates":[2.432502,48.818005],"type":"Point"}
}