{
  "type": "Feature",
  "properties": {
    "iso:country":"FR",
    "sg:address":"Zi La Sont Du Loup 43240 St Just Malmont",
    "sg:city":"Saint-Just-Malmont",
    "sg:classifiers":[
        {
            "category":"Manufacturing",
            "subcategory":"Paper Products",
            "type":"Manufacturing & Wholesale Goods"
        }
    ],
    "sg:phone":"+33 4 77 35 99 40",
    "sg:postcode":"43240",
    "sg:province":"Auvergne",
    "sg:tags":[
        "raw",
        "material",
        "-",
        "cardboard"
    ],
    "wof:name":"Cartonnerie De St Just Malmont",
    "wof:placetype":"venue"
},
  "geometry": {"coordinates":[4.313666,45.339558],"type":"Point"}
}