{
  "type": "Feature",
  "properties": {
    "iso:country":"FR",
    "sg:address":"Lieu Dit Les Ribouts 85540 Le Champ St Pere",
    "sg:classifiers":[
        {
            "category":"Shopping",
            "subcategory":"Hobbies, Toys, & Games",
            "type":"Retail Goods"
        }
    ],
    "sg:phone":"+33 2 51 40 99 93",
    "sg:postcode":"85540",
    "sg:province":"Pays de Loire",
    "sg:tags":[
        "product",
        "miscellaneous",
        "entertainment"
    ],
    "wof:name":"Ocean Gravure",
    "wof:placetype":"venue"
},
  "geometry": {"coordinates":[-1.340424,46.511414],"type":"Point"}
}