{
  "type": "Feature",
  "properties": {
    "iso:country":"FR",
    "sg:address":"3 avenue Elie Reumaux; BP 14; LENS; 62307 CEDEX",
    "sg:classifiers":[
        {
            "category":"Shopping",
            "subcategory":"Computers & Home Electronics",
            "type":"Retail Goods"
        }
    ],
    "sg:phone":"+33 3 21 69 23 23",
    "sg:province":"Midi Pyr\u00e9n\u00e9es",
    "sg:tags":[
        "chamber",
        "commerce"
    ],
    "wof:name":"Chambre De Commerce De Lens",
    "wof:placetype":"venue"
},
  "geometry": {"coordinates":[2.82799,50.433029],"type":"Point"}
}