{
  "type": "Feature",
  "properties": {
    "addr:full":"24, Rue Georges Pompidou - ZI de l'Aqueduc, 78690 Les Essarts le Roi Ile de France 78690",
    "addr:housenumber":"24",
    "addr:postcode":"78690;78690",
    "addr:street":"Rue Georges Pompidou Zi De L'Aqueduc",
    "iso:country":"FR",
    "sg:address":"24, Rue Georges Pompidou - ZI de l'Aqueduc, 78690 Les Essarts le Roi",
    "sg:orig_category":"Non-Classified Establishments",
    "sg:phone":"+33 1 30 88 90 92",
    "sg:postcode":"78690",
    "sg:province":"Ile de France",
    "wof:name":"Epuro S.a.",
    "wof:placetype":"venue"
},
  "geometry": {"coordinates":[1.897923,48.725281],"type":"Point"}
}