{
  "type": "Feature",
  "properties": {
    "iso:country":"FR",
    "sg:address":"22, Place Jean Jaur\u00e8s, 34500 B\u00e9ziers",
    "sg:orig_category":"Unclassifiable Establishments",
    "sg:phone":"+33 4 67 49 12 16",
    "sg:province":"Languedoc-Roussillon",
    "wof:name":"Banco Popular Comercial",
    "wof:placetype":"venue"
},
  "geometry": {"coordinates":[3.217125,43.340931],"type":"Point"}
}