{
  "type": "Feature",
  "properties": {
    "iso:country":"FR",
    "sg:address":"92 Belle All\u00e9e 63460 Combronde",
    "sg:city":"Combronde",
    "sg:classifiers":[
        {
            "category":"Utilities",
            "subcategory":"Electric",
            "type":"Services"
        }
    ],
    "sg:phone":"+33 4 73 97 12 69",
    "sg:postcode":"63460",
    "sg:province":"Auvergne",
    "sg:tags":[
        "electricity",
        "electronic",
        "electrical",
        "equipment"
    ],
    "wof:name":"Ste Fabrication Et Distribution Sarl",
    "wof:placetype":"venue"
},
  "geometry": {"coordinates":[3.100552,45.984055],"type":"Point"}
}