{
  "type": "Feature",
  "properties": {
    "addr:full":"161, Chemin de Gibbes, 13014 Marseille Poitou-Charentes",
    "addr:housenumber":"161",
    "addr:postcode":"13014",
    "addr:street":"Chemin De Gibbes",
    "iso:country":"FR",
    "sg:address":"161, Chemin de Gibbes, 13014 Marseille",
    "sg:orig_category":"Unclassifiable Establishments",
    "sg:phone":"+33 4 91 67 06 56",
    "sg:province":"Poitou-Charentes",
    "wof:name":"G\u00e9n\u00e9rale Des Desserts S.a.r.l.",
    "wof:placetype":"venue"
},
  "geometry": {"coordinates":[5.383223,43.325787],"type":"Point"}
}