{
  "type": "Feature",
  "properties": {
    "addr:full":"12, Rue de Boigne, 73000 Chamb\u00e9ry Rhone-Alpes",
    "addr:housenumber":"12",
    "addr:postcode":"73000",
    "addr:street":"Rue De Boigne",
    "iso:country":"FR",
    "sg:address":"12, Rue de Boigne, 73000 Chamb\u00e9ry",
    "sg:orig_category":"Unclassifiable Establishments",
    "sg:phone":"+33 4 79 33 78 33",
    "sg:province":"Rhone-Alpes",
    "wof:name":"Soci\u00e9t\u00e9 D'exploitation Boucherie Parisienne S.a.",
    "wof:placetype":"venue"
},
  "geometry": {"coordinates":[5.92032,45.565495],"type":"Point"}
}