{
  "type": "Feature",
  "properties": {
    "iso:country":"FR",
    "sg:address":"48 Av Gabriel P\u00e9ri 78360 Montesson",
    "sg:classifiers":[
        {
            "category":"Building & Trades",
            "subcategory":"Construction",
            "type":"Services"
        }
    ],
    "sg:phone":"+33 1 30 15 26 26",
    "sg:postcode":"78360",
    "sg:province":"Ile de France",
    "sg:tags":[
        "work",
        "public"
    ],
    "wof:name":"Eurovia",
    "wof:placetype":"venue"
},
  "geometry": {"coordinates":[2.117048,48.907791],"type":"Point"}
}