{
  "type": "Feature",
  "properties": {
    "addr:full":"boulevard John Kennedy 25000 BESANCON Franche Comt\u00e9 25000",
    "addr:postcode":"25000;25000",
    "addr:street":"Boulevard John Kennedy;Franche Comte\u0301",
    "iso:country":"FR",
    "sg:address":"boulevard John Kennedy 25000 BESANCON",
    "sg:classifiers":[
        {
            "category":"Banks & Credit Unions",
            "subcategory":"Financial Services",
            "type":"Services"
        }
    ],
    "sg:phone":"+33 3 81 50 81 41",
    "sg:postcode":"25000",
    "sg:province":"Franche Comt\u00e9",
    "sg:tags":[
        "mail",
        "processing",
        "fulfilment",
        "order"
    ],
    "wof:name":"Maty Sa",
    "wof:placetype":"venue"
},
  "geometry": {"coordinates":[5.994415,47.242634],"type":"Point"}
}