{
  "type": "Feature",
  "properties": {
    "iso:country":"FR",
    "sg:address":"B.P. 601, 01506 Amb\u00e9rieu en Bugey C\u00e9dex^^Rue Marius Berliet - ZI, 01500 Amb\u00e9rieu en Bugey",
    "sg:orig_category":"Non-Classified Establishments",
    "sg:phone":"+33 4 74 38 02 11",
    "sg:province":"Rhone-Alpes",
    "wof:name":"Filtres Monnet S.a.",
    "wof:placetype":"venue"
},
  "geometry": {"coordinates":[5.34274,45.970829],"type":"Point"}
}