{
  "type": "Feature",
  "properties": {
    "iso:country":"FR",
    "sg:address":"17, Bd du Lac, 95880 Enghien les Bains",
    "sg:orig_category":"Unclassifiable Establishments",
    "sg:phone":"+33 1 39 89 99 43",
    "sg:province":"Ile de France",
    "wof:name":"Hep'net S.a.r.l.",
    "wof:placetype":"venue"
},
  "geometry": {"coordinates":[2.299258,48.966805],"type":"Point"}
}