{
  "type": "Feature",
  "properties": {
    "iso:country":"FR",
    "sg:address":"5 Rue Entreprises 16400 Puymoyen",
    "sg:classifiers":[
        {
            "category":"Professional",
            "subcategory":"Engineering",
            "type":"Services"
        }
    ],
    "sg:phone":"+33 5 45 61 42 46",
    "sg:postcode":"16400",
    "sg:province":"Poitou-Charentes",
    "sg:tags":[
        "machine",
        "-",
        "environment",
        "equipment",
        "machinery",
        "mechanical"
    ],
    "wof:name":"General Incendie Sa",
    "wof:placetype":"venue"
},
  "geometry": {"coordinates":[0.159454,45.623512],"type":"Point"}
}