{
  "type": "Feature",
  "properties": {
    "iso:country":"FR",
    "sg:address":"Av de la Dordogne - ZI Petite Synthe",
    "sg:city":"Dunkerque",
    "sg:orig_category":"Unclassifiable Establishments",
    "sg:phone":"+33 3 28 58 72 92",
    "sg:postcode":"59640",
    "sg:province":"Nord-Pas-de-Calais",
    "wof:name":"P.m.m. S.a. - Ponticelli Martin M\u00e9canique",
    "wof:placetype":"venue"
},
  "geometry": {"coordinates":[2.35294,51.022812],"type":"Point"}
}