{
  "type": "Feature",
  "properties": {
    "addr:full":"Zone Industrielle 60110 Meru Picardie 60110",
    "addr:postcode":"60110;60110",
    "addr:street":"Zone Industrielle",
    "iso:country":"FR",
    "sg:address":"Zone Industrielle 60110 Meru",
    "sg:classifiers":[
        {
            "category":"Manufacturing",
            "subcategory":"Chemicals & Compounds",
            "type":"Manufacturing & Wholesale Goods"
        }
    ],
    "sg:phone":"+33 3 44 52 60 60",
    "sg:postcode":"60110",
    "sg:province":"Picardie",
    "sg:tags":[
        "pharmaceutical",
        "chemistry",
        "-",
        "by-product"
    ],
    "wof:name":"Itw De France",
    "wof:placetype":"venue"
},
  "geometry": {"coordinates":[2.135155,49.235676],"type":"Point"}
}