{
  "type": "Feature",
  "properties": {
    "addr:full":"1, Av. Louison Bobet - ZAC des Marais, 94124 Fontenay sous Bois C\u00e9dex \u00cele-de-France",
    "addr:postcode":"94124",
    "addr:street":"Av. Louison Bobet Zac Des Marais;Bois Ce\u0301Dex",
    "iso:country":"FR",
    "sg:address":"1, Av. Louison Bobet - ZAC des Marais, 94124 Fontenay sous Bois C\u00e9dex",
    "sg:orig_category":"Non-Classified Establishments",
    "sg:phone":"+33 1 53 99 95 00",
    "sg:province":"\u00cele-de-France",
    "wof:name":"Hasson S.a.",
    "wof:placetype":"venue"
},
  "geometry": {"coordinates":[2.474705,48.850994],"type":"Point"}
}