{
  "type": "Feature",
  "properties": {
    "addr:full":"Impasse Prairies 69400 Arnas Rhone-Alpes",
    "addr:postcode":"69400",
    "addr:street":"Impasse Prairies",
    "iso:country":"FR",
    "sg:address":"Impasse Prairies 69400 Arnas",
    "sg:classifiers":[
        {
            "category":"Professional",
            "type":"Services"
        }
    ],
    "sg:phone":"+33 4 74 62 84 60",
    "sg:province":"Rhone-Alpes",
    "sg:tags":[
        "transport",
        "road"
    ],
    "wof:name":"Transports Georges Fray Sarl",
    "wof:placetype":"venue"
},
  "geometry": {"coordinates":[4.708661,46.024044],"type":"Point"}
}