{
  "type": "Feature",
  "properties": {
    "addr:full":"Site De Montesquieu Bordeaux Technopolis 33650 Martillac Martillac Aquitaine 33650",
    "addr:postcode":"33650;33650",
    "iso:country":"FR",
    "sg:address":"Site De Montesquieu Bordeaux Technopolis 33650 Martillac",
    "sg:city":"Martillac",
    "sg:classifiers":[
        {
            "category":"Manufacturing",
            "subcategory":"Chemicals & Compounds",
            "type":"Manufacturing & Wholesale Goods"
        }
    ],
    "sg:phone":"+33 5 57 96 04 04",
    "sg:postcode":"33650",
    "sg:province":"Aquitaine",
    "sg:tags":[
        "pharmaceutical",
        "chemistry",
        "-",
        "by-product"
    ],
    "wof:name":"Reactifs Ral S.a.",
    "wof:placetype":"venue"
},
  "geometry": {"coordinates":[-0.550096,44.714546],"type":"Point"}
}