{
  "type": "Feature",
  "properties": {
    "iso:country":"FR",
    "sg:address":"3 rue Pierre et Marie Curie 31520 RAMONVILLE ST AGNE",
    "sg:classifiers":[
        {
            "category":"Retail",
            "subcategory":"Emissions Testing",
            "type":"Services"
        }
    ],
    "sg:phone":"+33 5 61 75 15 13",
    "sg:postcode":"31520",
    "sg:province":"Midi Pyr\u00e9n\u00e9es",
    "sg:tags":[
        "instrument",
        "immission",
        "measurement"
    ],
    "wof:name":"Its Sa",
    "wof:placetype":"venue"
},
  "geometry": {"coordinates":[1.47836,43.543671],"type":"Point"}
}