{
  "type": "Feature",
  "properties": {
    "iso:country":"FR",
    "sg:address":"9 Av Condorcet",
    "sg:city":"91240 St Michel Sur Orge",
    "sg:classifiers":[
        {
            "category":"Professional",
            "subcategory":"Engineering",
            "type":"Services"
        }
    ],
    "sg:phone":"+33 1 69 46 68 88",
    "sg:postcode":"91240",
    "sg:province":"Ile de France",
    "sg:tags":[
        "machine",
        "-",
        "environment",
        "equipment",
        "machinery",
        "mechanical"
    ],
    "wof:name":"Autogyre",
    "wof:placetype":"venue"
},
  "geometry": {"coordinates":[2.303101,48.630775],"type":"Point"}
}