{
  "type": "Feature",
  "properties": {
    "iso:country":"FR",
    "sg:address":"Zi De Jalday Jalday Ii 64500 St Jean De Luz",
    "sg:city":"Ciboure",
    "sg:classifiers":[
        {
            "category":"Professional",
            "type":"Services"
        }
    ],
    "sg:phone":"+33 5 59 51 82 40",
    "sg:postcode":"64500",
    "sg:province":"Aquitaine",
    "sg:tags":[
        "transport",
        "road"
    ],
    "wof:name":"Gefco",
    "wof:placetype":"venue"
},
  "geometry": {"coordinates":[-1.660884,43.38773],"type":"Point"}
}