{
  "type": "Feature",
  "properties": {
    "iso:country":"FR",
    "sg:address":"9, Rue de Lesdigui\u00e8res, 75004 Paris",
    "sg:orig_category":"Non-Classified Establishments",
    "sg:phone":"+33 1 48 87 33 10",
    "sg:postcode":"75004",
    "sg:province":"Ile de France",
    "wof:name":"Boithias Et Martin S.a.",
    "wof:placetype":"venue"
},
  "geometry": {"coordinates":[2.366736,48.853001],"type":"Point"}
}