{
  "type": "Feature",
  "properties": {
    "addr:full":"6, Place du 11 Novembre, 92250 La Garenne Colombes Ile de France",
    "addr:housenumber":"6",
    "addr:postcode":"92250",
    "addr:street":"Place Du 11 Novembre",
    "iso:country":"FR",
    "sg:address":"6, Place du 11 Novembre, 92250 La Garenne Colombes",
    "sg:orig_category":"Non-Classified Establishments",
    "sg:phone":"+33 1 47 86 28 01",
    "sg:province":"Ile de France",
    "wof:name":"L\u00e9oni France S.a.r.l.",
    "wof:placetype":"venue"
},
  "geometry": {"coordinates":[2.236744,48.905087],"type":"Point"}
}