{
  "type": "Feature",
  "properties": {
    "addr:full":"B.P. 2019, 44406 Rez\u00e9 C\u00e9dex^^2, Rue du Seil, 44400 Rez\u00e9 Pays de Loire",
    "addr:postcode":"44406;44400",
    "addr:street":"B.P. 2019;Rue Du Seil",
    "iso:country":"FR",
    "sg:address":"B.P. 2019, 44406 Rez\u00e9 C\u00e9dex^^2, Rue du Seil, 44400 Rez\u00e9",
    "sg:orig_category":"Non-Classified Establishments",
    "sg:phone":"+33 2 51 70 33 10",
    "sg:province":"Pays de Loire",
    "wof:name":"Sapr\u00e9na S.a.r.l.",
    "wof:placetype":"venue"
},
  "geometry": {"coordinates":[-1.569829,47.191238],"type":"Point"}
}