{
  "type": "Feature",
  "properties": {
    "addr:full":"3 R De La Petite Fin 21121 Fontaine Le Dijon Ahuy Bourgogne 21121",
    "addr:housenumber":"3",
    "addr:postcode":"21121;21121",
    "addr:street":"R De La Petite Fin;Bourgogne",
    "iso:country":"FR",
    "sg:address":"3 R De La Petite Fin 21121 Fontaine Le Dijon",
    "sg:city":"Ahuy",
    "sg:classifiers":[
        {
            "category":"Professional",
            "subcategory":"Engineering",
            "type":"Services"
        }
    ],
    "sg:phone":"+33 3 80 53 97 97",
    "sg:postcode":"21121",
    "sg:province":"Bourgogne",
    "sg:tags":[
        "machine",
        "-",
        "environment",
        "equipment",
        "machinery",
        "mechanical"
    ],
    "wof:name":"General Incendie Sa",
    "wof:placetype":"venue"
},
  "geometry": {"coordinates":[5.029366,47.349079],"type":"Point"}
}