{
  "type": "Feature",
  "properties": {
    "iso:country":"FR",
    "sg:address":"1, Rue Joseph Cugnot - Tour Marcel Brot, 54000 Nancy",
    "sg:orig_category":"Non-Classified Establishments",
    "sg:phone":"+33 3 83 32 78 44",
    "sg:province":"Lorraine",
    "wof:name":"Sodigep S.a.",
    "wof:placetype":"venue"
},
  "geometry": {"coordinates":[6.201301,48.679764],"type":"Point"}
}