{
  "type": "Feature",
  "properties": {
    "addr:full":"17 Rue Paul Bert 62110 Henin Beaumont Nord Pas-de-Calais 62110",
    "addr:housenumber":"17",
    "addr:postcode":"62110;62110",
    "addr:street":"Rue Paul Bert",
    "iso:country":"FR",
    "sg:address":"17 Rue Paul Bert 62110 Henin Beaumont",
    "sg:classifiers":[
        {
            "category":"Manufacturing",
            "subcategory":"Metals",
            "type":"Manufacturing & Wholesale Goods"
        }
    ],
    "sg:phone":"+33 3 21 77 40 00",
    "sg:postcode":"62110",
    "sg:province":"Nord Pas-de-Calais",
    "sg:tags":[
        "metallurgy",
        "metalworking",
        "processing"
    ],
    "wof:name":"Meca Stamp International Snc",
    "wof:placetype":"venue"
},
  "geometry": {"coordinates":[2.9485,50.41489],"type":"Point"}
}