{
  "type": "Feature",
  "properties": {
    "iso:country":"FR",
    "sg:address":"B.P. 2, 45110 Ch\u00e2teauneuf sur Loire^^12, Rue du Petit Hameau, 45110 Ch\u00e2teauneuf sur Loire",
    "sg:city":"Ch\u00e2teauneuf-sur-Loire",
    "sg:orig_category":"Non-Classified Establishments",
    "sg:phone":"+33 2 38 58 43 37",
    "sg:postcode":"45110",
    "sg:province":"Centre",
    "wof:name":"Exploitation Foresti\u00e8re Barillet S.a.",
    "wof:placetype":"venue"
},
  "geometry": {"coordinates":[2.225067,47.835693],"type":"Point"}
}