{
  "type": "Feature",
  "properties": {
    "addr:full":"9, Chemin du Halage, 76300 Sotteville l\u00e8s Rouen Haute Normandie",
    "addr:housenumber":"9",
    "addr:postcode":"76300",
    "addr:street":"Chemin Du Halage;Haute Normandie",
    "iso:country":"FR",
    "sg:address":"9, Chemin du Halage, 76300 Sotteville l\u00e8s Rouen",
    "sg:orig_category":"Unclassifiable Establishments",
    "sg:phone":"+33 2 35 73 90 10",
    "sg:province":"Haute Normandie",
    "wof:name":"Loxam S.a.",
    "wof:placetype":"venue"
},
  "geometry": {"coordinates":[1.10792,49.424358],"type":"Point"}
}