{
  "type": "Feature",
  "properties": {
    "addr:full":"1, Rue de la Croix du Ch\u00eane, 35400 Saint Malo Saint-Malo Bretagne 35400",
    "addr:housenumber":"1",
    "addr:postcode":"35400;35400",
    "addr:street":"Rue De La Croix Du Che\u0302Ne;Saint-Malo",
    "iso:country":"FR",
    "sg:address":"1, Rue de la Croix du Ch\u00eane, 35400 Saint Malo",
    "sg:city":"Saint-Malo",
    "sg:orig_category":"Unclassifiable Establishments",
    "sg:phone":"+33 2 99 81 41 85",
    "sg:postcode":"35400",
    "sg:province":"Bretagne",
    "wof:name":"Cyclelect S.a.r.l.",
    "wof:placetype":"venue"
},
  "geometry": {"coordinates":[-1.983627,48.647434],"type":"Point"}
}