{
  "type": "Feature",
  "properties": {
    "iso:country":"FR",
    "sg:address":"39, Rue Canrobert, 51400 Mourmelon le Grand",
    "sg:orig_category":"Unclassifiable Establishments",
    "sg:phone":"+33 3 26 40 20 20",
    "sg:province":"Champagne",
    "wof:name":"Sageb Electronique S.a.",
    "wof:placetype":"venue"
},
  "geometry": {"coordinates":[4.353717,49.136639],"type":"Point"}
}