{
  "type": "Feature",
  "properties": {
    "iso:country":"FR",
    "sg:address":"71 Rue Henri Gautier 44550 Montoir De Bretagne",
    "sg:classifiers":[
        {
            "category":"Autos & Motor Vehicles",
            "subcategory":"Boat Sales",
            "type":"Retail Goods"
        }
    ],
    "sg:phone":"+33 2 40 90 32 26",
    "sg:postcode":"44550",
    "sg:province":"Pays de Loire",
    "sg:tags":[
        "equipment",
        "transport"
    ],
    "wof:name":"Modular Marine System (2 Ms)",
    "wof:placetype":"venue"
},
  "geometry": {"coordinates":[-2.172339,47.31274],"type":"Point"}
}