{
  "type": "Feature",
  "properties": {
    "iso:country":"FR",
    "sg:address":"9, Rue Roger Salengro, 59191 Caullery",
    "sg:orig_category":"Non-Classified Establishments",
    "sg:phone":"+33 3 27 85 25 80",
    "sg:province":"Nord Pas-de-Calais",
    "wof:name":"La Ouate Synth\u00e9tique S.a.",
    "wof:placetype":"venue"
},
  "geometry": {"coordinates":[3.372941,50.086922],"type":"Point"}
}