{
  "type": "Feature",
  "properties": {
    "iso:country":"FR",
    "sg:address":"428, Rte de Chevroux, 01570 Manziat",
    "sg:orig_category":"Unclassifiable Establishments",
    "sg:phone":"+33 3 85 30 01 56",
    "sg:province":"Rhone-Alpes",
    "wof:name":"Entreprise Gonod Fr\u00e8res",
    "wof:placetype":"venue"
},
  "geometry": {"coordinates":[4.92177,46.367062],"type":"Point"}
}