{
  "type": "Feature",
  "properties": {
    "addr:full":"Rte Nationale 17 F\u00e9rin Nord Pas-de-Calais 59169",
    "addr:postcode":"59169",
    "addr:street":"Rte Nationale 17 Fe\u0301Rin Nord",
    "iso:country":"FR",
    "sg:address":"Rte Nationale 17",
    "sg:city":"F\u00e9rin",
    "sg:orig_category":"Non-Classified Establishments",
    "sg:phone":"+33 3 27 88 58 57",
    "sg:postcode":"59169",
    "sg:province":"Nord Pas-de-Calais",
    "wof:name":"Huilerie Saint Christophe S.a.r.l.",
    "wof:placetype":"venue"
},
  "geometry": {"coordinates":[3.073608,50.327969],"type":"Point"}
}