{
  "type": "Feature",
  "properties": {
    "addr:full":"2 Pierres Beregovoy 92110 Clichy Ile de France 92110",
    "addr:housenumber":"2",
    "addr:postcode":"92110;92110",
    "addr:street":"Pierres Beregovoy;Ile De France",
    "iso:country":"FR",
    "sg:address":"2 Pierres Beregovoy 92110 Clichy",
    "sg:classifiers":[
        {
            "category":"Building & Trades",
            "subcategory":"Construction",
            "type":"Services"
        }
    ],
    "sg:phone":"+33 1 47 37 01 78",
    "sg:postcode":"92110",
    "sg:province":"Ile de France",
    "sg:tags":[
        "work",
        "public"
    ],
    "wof:name":"Sade Compagnie Generale De Travaux D'hydraullique",
    "wof:placetype":"venue"
},
  "geometry": {"coordinates":[2.293812,48.901192],"type":"Point"}
}