{
  "type": "Feature",
  "properties": {
    "iso:country":"FR",
    "sg:address":"58, Bd Gustave Roch, 44200 Nantes",
    "sg:orig_category":"Unclassifiable Establishments",
    "sg:phone":"+33 2 40 12 03 89",
    "sg:province":"Pays de Loire",
    "wof:name":"S.d.i. S.a.r.l. - Soci\u00e9t\u00e9 De Distribution Internationale",
    "wof:placetype":"venue"
},
  "geometry": {"coordinates":[-1.555667,47.200958],"type":"Point"}
}