{
  "type": "Feature",
  "properties": {
    "addr:full":"Za Les Champs Francs 85490 Benet Pays de Loire 85490",
    "addr:postcode":"85490;85490",
    "addr:street":"Za Les Champs;Loire",
    "iso:country":"FR",
    "sg:address":"Za Les Champs Francs 85490 Benet",
    "sg:classifiers":[
        {
            "category":"Farming",
            "subcategory":"Farm",
            "type":"Manufacturing & Wholesale Goods"
        }
    ],
    "sg:phone":"+33 2 51 00 91 10",
    "sg:postcode":"85490",
    "sg:province":"Pays de Loire",
    "sg:tags":[
        "horticulture",
        "agriculture",
        "livestock"
    ],
    "wof:name":"Cavac",
    "wof:placetype":"venue"
},
  "geometry": {"coordinates":[-0.595849,46.369236],"type":"Point"}
}