{
  "type": "Feature",
  "properties": {
    "iso:country":"FR",
    "sg:address":"24, Rue de la P\u00e9pini\u00e8re, 75008 Paris",
    "sg:orig_category":"Unclassifiable Establishments",
    "sg:phone":"+33 1 42 93 33 10",
    "sg:province":"Ile de France",
    "wof:name":"Ordinter",
    "wof:placetype":"venue"
},
  "geometry": {"coordinates":[2.321002,48.875065],"type":"Point"}
}