{
  "type": "Feature",
  "properties": {
    "addr:full":"La Prade 11800 Floure Languedoc-Roussillon",
    "addr:postcode":"11800",
    "addr:street":"La Prade",
    "iso:country":"FR",
    "sg:address":"La Prade 11800 Floure",
    "sg:orig_category":"Non-Classified Establishments",
    "sg:phone":"+33 4 68 79 15 55",
    "sg:province":"Languedoc-Roussillon",
    "wof:name":"P\u00e9pini\u00e8res Casadesus Georges S.c.e.a.",
    "wof:placetype":"venue"
},
  "geometry": {"coordinates":[2.443605,43.210781],"type":"Point"}
}