{
  "type": "Feature",
  "properties": {
    "addr:full":"123, Rue L\u00e9opold R\u00e9chossi\u00e8re, 93300 Aubervilliers Ile de France",
    "addr:housenumber":"123",
    "addr:postcode":"93300",
    "addr:street":"Rue Le\u0301Opold Re\u0301Chossie\u0300Re",
    "iso:country":"FR",
    "sg:address":"123, Rue L\u00e9opold R\u00e9chossi\u00e8re, 93300 Aubervilliers",
    "sg:orig_category":"Unclassifiable Establishments",
    "sg:phone":"+33 1 48 33 38 92",
    "sg:province":"Ile de France",
    "wof:name":"Br\u00e9ard S.a.",
    "wof:placetype":"venue"
},
  "geometry": {"coordinates":[2.398014,48.912289],"type":"Point"}
}