{
  "type": "Feature",
  "properties": {
    "addr:full":"Route De Chalais Zi 16300 Barbezieux St Hilaire Poitou-Charentes",
    "addr:postcode":"16300",
    "addr:street":"Route De Chalais Zi;St Hilaire",
    "iso:country":"FR",
    "sg:address":"Route De Chalais Zi 16300 Barbezieux St Hilaire",
    "sg:classifiers":[
        {
            "category":"Manufacturing",
            "subcategory":"Printing",
            "type":"Manufacturing & Wholesale Goods"
        }
    ],
    "sg:phone":"+33 5 45 78 39 47",
    "sg:province":"Poitou-Charentes",
    "sg:tags":[
        "publishing"
    ],
    "wof:name":"Seriprint",
    "wof:placetype":"venue"
},
  "geometry": {"coordinates":[-0.079554,45.41621],"type":"Point"}
}