{
  "type": "Feature",
  "properties": {
    "iso:country":"FR",
    "sg:address":"42, Rue des Hauts Pav\u00e9s, 44000 Nantes",
    "sg:orig_category":"Unclassifiable Establishments",
    "sg:phone":"+33 2 40 08 03 65",
    "sg:province":"Pays de Loire",
    "wof:name":"Cinq Sur Cinq S.a.r.l.",
    "wof:placetype":"venue"
},
  "geometry": {"coordinates":[-1.564932,47.224594],"type":"Point"}
}