{
  "type": "Feature",
  "properties": {
    "addr:full":"42, Rue des Hauts Pav\u00e9s, 44000 Nantes Pays de Loire",
    "addr:housenumber":"42",
    "addr:postcode":"44000",
    "addr:street":"Rue Des Hauts Pave\u0301S",
    "iso:country":"FR",
    "sg:address":"42, Rue des Hauts Pav\u00e9s, 44000 Nantes",
    "sg:orig_category":"Unclassifiable Establishments",
    "sg:phone":"+33 2 40 08 03 65",
    "sg:province":"Pays de Loire",
    "wof:name":"Cinq Sur Cinq S.a.r.l.",
    "wof:placetype":"venue"
},
  "geometry": {"coordinates":[-1.564932,47.224594],"type":"Point"}
}