{
  "type": "Feature",
  "properties": {
    "iso:country":"FR",
    "sg:address":"117, Av. Pierre et Marie Curie, 45800 Saint Jean de Braye",
    "sg:city":"Combleux",
    "sg:orig_category":"Unclassifiable Establishments",
    "sg:phone":"+33 2 38 60 40 03",
    "sg:postcode":"45800",
    "sg:province":"Centre",
    "wof:name":"Smas Services S.a.r.l.",
    "wof:placetype":"venue"
},
  "geometry": {"coordinates":[1.988424,47.905655],"type":"Point"}
}