{
  "type": "Feature",
  "properties": {
    "addr:full":"B.P. 20, 90800 Bavilliers^^Zone Industrielle, 90800 Bavilliers Franche Comt\u00e9",
    "addr:postcode":"90800;90800",
    "addr:street":"B.P. 20;Industrielle;Franche Comte\u0301",
    "iso:country":"FR",
    "sg:address":"B.P. 20, 90800 Bavilliers^^Zone Industrielle, 90800 Bavilliers",
    "sg:orig_category":"Non-Classified Establishments",
    "sg:phone":"+33 3 84 21 32 57",
    "sg:province":"Franche Comt\u00e9",
    "wof:name":"Sol Service S.a.",
    "wof:placetype":"venue"
},
  "geometry": {"coordinates":[6.833895,47.620541],"type":"Point"}
}