{
  "type": "Feature",
  "properties": {
    "iso:country":"FR",
    "sg:address":"B.P. 75, 29280 Plouzan\u00e9^^Technopole Brest Iroise, 29280 Plouzan\u00e9",
    "sg:city":"Plouzan\u00e9",
    "sg:orig_category":"Non-Classified Establishments",
    "sg:phone":"+33 2 98 05 65 00",
    "sg:postcode":"29280",
    "sg:province":"Bretagne",
    "wof:name":"I.f.r.t.p. G.i.e. - Institut Fran\u00e7ais Pour La Recherche Et La Technologie",
    "wof:placetype":"venue"
},
  "geometry": {"coordinates":[-4.622545,48.38055],"type":"Point"}
}