{
  "type": "Feature",
  "properties": {
    "iso:country":"FR",
    "sg:address":"52, Quai de Dion Bouton - Tour Horizon, 92800 Puteaux",
    "sg:orig_category":"Unclassifiable Establishments",
    "sg:phone":"+33 1 41 26 28 00",
    "sg:province":"Ile de France",
    "wof:name":"A.g.i. S.a. - Assistance Gestion Et Informatique",
    "wof:placetype":"venue"
},
  "geometry": {"coordinates":[2.249403,48.884102],"type":"Point"}
}