{
  "type": "Feature",
  "properties": {
    "iso:country":"FR",
    "sg:address":"Za 49460 Cantenay Epinard",
    "sg:classifiers":[
        {
            "category":"Manufacturing",
            "subcategory":"Rubber & Plastics",
            "type":"Manufacturing & Wholesale Goods"
        }
    ],
    "sg:phone":"+33 2 41 32 13 63",
    "sg:province":"Pays de Loire",
    "wof:name":"Barbe Menuisiers Sarl",
    "wof:placetype":"venue"
},
  "geometry": {"coordinates":[-0.611961,47.52935],"type":"Point"}
}