{
  "type": "Feature",
  "properties": {
    "addr:full":"Pa La Peyri\u00e8re R Du Trait\u00e9 De Rome 34430 St Jean De Vedas Languedoc-Roussillon",
    "addr:postcode":"34430",
    "addr:street":"R Du Traite\u0301 De Rome;Vedas",
    "iso:country":"FR",
    "sg:address":"Pa La Peyri\u00e8re R Du Trait\u00e9 De Rome 34430 St Jean De Vedas",
    "sg:classifiers":[
        {
            "category":"Professional",
            "type":"Services"
        }
    ],
    "sg:phone":"+33 4 67 07 14 07",
    "sg:province":"Languedoc-Roussillon",
    "sg:tags":[
        "transport",
        "road"
    ],
    "wof:name":"Calberson Mediterranee",
    "wof:placetype":"venue"
},
  "geometry": {"coordinates":[3.8289,43.575985],"type":"Point"}
}