{
  "type": "Feature",
  "properties": {
    "iso:country":"FR",
    "sg:address":"10 Avenue De La Gloriette Zi De Fontcouverte 84000 Avignon",
    "sg:classifiers":[
        {
            "category":"Manufacturing",
            "subcategory":"Rubber & Plastics",
            "type":"Manufacturing & Wholesale Goods"
        }
    ],
    "sg:phone":"+33 4 90 87 49 81",
    "sg:province":"Provence-Alpes-C\u00f4te d'Azur",
    "sg:tags":[
        "packaging",
        "material",
        "-"
    ],
    "wof:name":"E Burles Distribution",
    "wof:placetype":"venue"
},
  "geometry": {"coordinates":[4.806015,43.948753],"type":"Point"}
}