{
  "type": "Feature",
  "properties": {
    "iso:country":"FR",
    "sg:address":"ZA des Ferri\u00e8res",
    "sg:city":"Gr\u00e9zieu la Varenne",
    "sg:orig_category":"Unclassifiable Establishments",
    "sg:phone":"+33 4 78 57 09 69",
    "sg:postcode":"69290",
    "sg:province":"Rhone-Alpes",
    "wof:name":"C.s.l. S.a.s. - Constructions Soud\u00e9es Lyonnaises",
    "wof:placetype":"venue"
},
  "geometry": {"coordinates":[4.691225,45.747162],"type":"Point"}
}