{
  "type": "Feature",
  "properties": {
    "addr:full":"B.P. 104, 95613 Cergy Pontoise C\u00e9dex^^Av. du Gros Ch\u00eane, 95610 Eragny Ile de France",
    "addr:housenumber":"b.p. 104",
    "addr:postcode":"95613;95610",
    "addr:street":"Gros Che\u0302Ne;Ile De France",
    "iso:country":"FR",
    "sg:address":"B.P. 104, 95613 Cergy Pontoise C\u00e9dex^^Av. du Gros Ch\u00eane, 95610 Eragny",
    "sg:orig_category":"Non-Classified Establishments",
    "sg:phone":"+33 1 34 30 46 40",
    "sg:province":"Ile de France",
    "wof:name":"S.p. Loc Century S.a.r.l.",
    "wof:placetype":"venue"
},
  "geometry": {"coordinates":[2.091,49.019009],"type":"Point"}
}