{
  "type": "Feature",
  "properties": {
    "addr:full":"N 3 - Immeuble le Beaupr\u00e9 Conflans Sainte Honorine Ile de France 78700",
    "addr:housenumber":"3",
    "addr:postcode":"78700",
    "addr:street":"N;Immeuble Le Beaupre\u0301",
    "iso:country":"FR",
    "sg:address":"N 3 - Immeuble le Beaupr\u00e9",
    "sg:city":"Conflans Sainte Honorine",
    "sg:orig_category":"Unclassifiable Establishments",
    "sg:phone":"+33 1 39 19 57 57",
    "sg:postcode":"78700",
    "sg:province":"Ile de France",
    "wof:name":"Stego France S.a.",
    "wof:placetype":"venue"
},
  "geometry": {"coordinates":[2.093755,48.99337],"type":"Point"}
}