{
  "type": "Feature",
  "properties": {
    "addr:full":"20, Rue Patet, 25560 Frasne Franche Comt\u00e9",
    "addr:housenumber":"20",
    "addr:postcode":"25560",
    "addr:street":"Rue Patet;Franche Comte\u0301",
    "iso:country":"FR",
    "sg:address":"20, Rue Patet, 25560 Frasne",
    "sg:orig_category":"Non-Classified Establishments",
    "sg:phone":"+33 3 81 49 83 10",
    "sg:province":"Franche Comt\u00e9",
    "wof:name":"Vieille Robert S.a.r.l.",
    "wof:placetype":"venue"
},
  "geometry": {"coordinates":[6.161837,46.857552],"type":"Point"}
}