{
  "type": "Feature",
  "properties": {
    "iso:country":"FR",
    "sg:address":"Le Bel Avenir 71570 La Chapelle de Guinchay",
    "sg:city":"Chaintr\u00e9",
    "sg:orig_category":"Unclassifiable Establishments",
    "sg:phone":"+33 3 85 36 70 26",
    "sg:postcode":"71570",
    "sg:province":"Bourgogne",
    "wof:name":"Champale S.a.",
    "wof:placetype":"venue"
},
  "geometry": {"coordinates":[4.75923,46.21994],"type":"Point"}
}