{
  "type": "Feature",
  "properties": {
    "addr:full":"Chemin du Halage Flogny la Chapelle Bourgogne 89360",
    "addr:postcode":"89360",
    "addr:street":"Chemin Du Halage",
    "iso:country":"FR",
    "sg:address":"Chemin du Halage",
    "sg:city":"Flogny la Chapelle",
    "sg:orig_category":"Unclassifiable Establishments",
    "sg:phone":"+33 3 86 75 40 55",
    "sg:postcode":"89360",
    "sg:province":"Bourgogne",
    "wof:name":"Joussot S.a.",
    "wof:placetype":"venue"
},
  "geometry": {"coordinates":[3.880411,47.945248],"type":"Point"}
}