{
  "type": "Feature",
  "properties": {
    "iso:country":"FR",
    "sg:address":"ZA la Maladi\u00e8re",
    "sg:city":"Saint P\u00e9ray",
    "sg:orig_category":"Unclassifiable Establishments",
    "sg:phone":"+33 4 75 81 67 00",
    "sg:postcode":"07130",
    "sg:province":"Rhone-Alpes",
    "wof:name":"Rhonetex S.a.",
    "wof:placetype":"venue"
},
  "geometry": {"coordinates":[4.84053,44.944061],"type":"Point"}
}