{
  "type": "Feature",
  "properties": {
    "iso:country":"FR",
    "sg:address":"241 Av De La Belle Etoile Zi Paris Nord Ii 95957 Roissy-Charles De Gaulle Cedex",
    "sg:classifiers":[
        {
            "category":"Banks & Credit Unions",
            "subcategory":"Investment Brokerage",
            "type":"Services"
        }
    ],
    "sg:phone":"+33 1 49 38 70 70",
    "sg:province":"Picardie",
    "sg:tags":[
        "-",
        "transport",
        "related"
    ],
    "wof:name":"Dhl International",
    "wof:placetype":"venue"
},
  "geometry": {"coordinates":[2.51524,49.004028],"type":"Point"}
}