{
  "type": "Feature",
  "properties": {
    "iso:country":"FR",
    "sg:address":"Rue du Vent de Bise",
    "sg:city":"Grand Rullecourt",
    "sg:orig_category":"Unclassifiable Establishments",
    "sg:phone":"+33 3 21 48 42 42",
    "sg:postcode":"62810",
    "sg:province":"Nord Pas-de-Calais",
    "wof:name":"Fi\u00e9dor S.a.",
    "wof:placetype":"venue"
},
  "geometry": {"coordinates":[2.482852,50.254734],"type":"Point"}
}