{
  "type": "Feature",
  "properties": {
    "addr:full":"B.P. 48, 03402 Yzeure C\u00e9dex^^26, rue Beauregard, 03400 Yzeure Yzeure Auvergne 03400",
    "addr:postcode":"03402;03400;03400",
    "addr:street":"B.P. 48;Rue Beauregard",
    "iso:country":"FR",
    "sg:address":"B.P. 48, 03402 Yzeure C\u00e9dex^^26, rue Beauregard, 03400 Yzeure",
    "sg:city":"Yzeure",
    "sg:orig_category":"Non-Classified Establishments",
    "sg:phone":"+33 4 70 44 08 57",
    "sg:postcode":"03400",
    "sg:province":"Auvergne",
    "wof:name":"Laboratoires Augot S.a.",
    "wof:placetype":"venue"
},
  "geometry": {"coordinates":[3.37215,46.573559],"type":"Point"}
}