{
  "type": "Feature",
  "properties": {
    "addr:full":"12, Av de l'Europe, 02405 Ch\u00e2teau Thierry Picardie",
    "addr:postcode":"02405",
    "addr:street":"12 Av De L'Europe",
    "iso:country":"FR",
    "sg:address":"12, Av de l'Europe, 02405 Ch\u00e2teau Thierry",
    "sg:orig_category":"Non-Classified Establishments",
    "sg:phone":"+33 3 23 84 98 00",
    "sg:province":"Picardie",
    "wof:name":"Point P S.a.",
    "wof:placetype":"venue"
},
  "geometry": {"coordinates":[3.39891,49.045719],"type":"Point"}
}