{
  "type": "Feature",
  "properties": {
    "addr:full":"21, Rue du Faubourg Saint Antoine, 75011 Paris Ile de France",
    "addr:housenumber":"21",
    "addr:postcode":"75011",
    "addr:street":"Rue Du Faubourg Saint Antoine",
    "iso:country":"FR",
    "sg:address":"21, Rue du Faubourg Saint Antoine, 75011 Paris",
    "sg:orig_category":"Non-Classified Establishments",
    "sg:phone":"+33 1 40 02 62 70",
    "sg:province":"Ile de France",
    "wof:name":"Fidelity Programs S.a.",
    "wof:placetype":"venue"
},
  "geometry": {"coordinates":[2.371423,48.852703],"type":"Point"}
}