{
  "type": "Feature",
  "properties": {
    "addr:full":"6 Rue Royale 75008 Paris Ile de France 75008",
    "addr:housenumber":"6",
    "addr:postcode":"75008;75008",
    "addr:street":"Rue Royale",
    "iso:country":"FR",
    "sg:address":"6 Rue Royale 75008 Paris",
    "sg:classifiers":[
        {
            "category":"Manufacturing",
            "subcategory":"Tools & Machinery",
            "type":"Manufacturing & Wholesale Goods"
        }
    ],
    "sg:phone":"+33 1 42 44 24 07",
    "sg:postcode":"75008",
    "sg:province":"Ile de France",
    "sg:tags":[
        "metallurgy",
        "metalworking"
    ],
    "wof:name":"Bronzes De France",
    "wof:placetype":"venue"
},
  "geometry": {"coordinates":[2.322615,48.867287],"type":"Point"}
}