{
  "type": "Feature",
  "properties": {
    "addr:full":"Laiterie 50480 Chef Du Pont Amfreville Basse Normandie 50480",
    "addr:postcode":"50480;du;50480",
    "addr:street":"Laiterie;Basse",
    "iso:country":"FR",
    "sg:address":"Laiterie 50480 Chef Du Pont",
    "sg:city":"Amfreville",
    "sg:classifiers":[
        {
            "category":"Food & Beverages",
            "subcategory":"Dairy",
            "type":"Retail Goods"
        }
    ],
    "sg:phone":"+33 2 33 21 71 71",
    "sg:postcode":"50480",
    "sg:province":"Basse Normandie",
    "sg:tags":[
        "product",
        "related"
    ],
    "wof:name":"Nestle France",
    "wof:placetype":"venue"
},
  "geometry": {"coordinates":[-1.348079,49.380295],"type":"Point"}
}