{
  "type": "Feature",
  "properties": {
    "iso:country":"FR",
    "sg:address":"B.P. 426, 29174 Douarnenez C\u00e9dex^^ZI de Pouldavid, 29100 Douarnenez",
    "sg:city":"Douarnenez",
    "sg:orig_category":"Non-Classified Establishments",
    "sg:phone":"+33 2 98 92 11 91",
    "sg:postcode":"29100",
    "sg:province":"Bretagne",
    "wof:name":"K.l.m. S.a. - Kersaudy Et Le Meur",
    "wof:placetype":"venue"
},
  "geometry": {"coordinates":[-4.327149,48.043324],"type":"Point"}
}