{
  "type": "Feature",
  "properties": {
    "addr:full":"1 du Point du Jour; Boulogne Cedex; 92656 \u00cele-de-France",
    "addr:housenumber":"1",
    "addr:postcode":"boulogne cedex 92656",
    "addr:street":"Du Point Du Jour",
    "iso:country":"FR",
    "sg:address":"1",
    "sg:city":"du Point du Jour; Boulogne Cedex; 92656",
    "sg:classifiers":[
        {
            "category":"Industrial Area",
            "type":"Public Place"
        }
    ],
    "sg:phone":"+33 1 41 41 25 99",
    "sg:province":"\u00cele-de-France",
    "sg:tags":[
        "large",
        "private"
    ],
    "wof:name":"Soci\u00e9t\u00e9 T\u00e9l\u00e9vision Fran\u00e7aise 1",
    "wof:placetype":"venue"
},
  "geometry": {"coordinates":[2.24347,48.83382],"type":"Point"}
}