{
  "type": "Feature",
  "properties": {
    "addr:full":"Chemin de Mancy Luttange Lorraine 57144",
    "addr:postcode":"57144",
    "addr:street":"Chemin De Mancy",
    "iso:country":"FR",
    "sg:address":"Chemin de Mancy",
    "sg:city":"Luttange",
    "sg:orig_category":"Unclassifiable Establishments",
    "sg:phone":"+33 3 82 82 29 29",
    "sg:postcode":"57144",
    "sg:province":"Lorraine",
    "wof:name":"S.n. Lutrac Industrie S.a.",
    "wof:placetype":"venue"
},
  "geometry": {"coordinates":[6.308049,49.265762],"type":"Point"}
}