{
  "type": "Feature",
  "properties": {
    "iso:country":"FR",
    "sg:address":"Rte Ch\u00e2teau Du Loir 72800 Le Lude",
    "sg:classifiers":[
        {
            "category":"Shopping",
            "subcategory":"Hobbies, Toys, & Games",
            "type":"Retail Goods"
        }
    ],
    "sg:phone":"+33 2 43 48 25 25",
    "sg:postcode":"72800",
    "sg:province":"Pays de Loire",
    "sg:tags":[
        "product",
        "miscellaneous",
        "entertainment"
    ],
    "wof:name":"Jemini Sa",
    "wof:placetype":"venue"
},
  "geometry": {"coordinates":[0.154635,47.647072],"type":"Point"}
}