{
  "type": "Feature",
  "properties": {
    "iso:country":"FR",
    "sg:address":"La Baulini\u00e8re 72200 Clermont Cr\u00e9ans",
    "sg:orig_category":"Unclassifiable Establishments",
    "sg:phone":"+33 2 43 94 37 15",
    "sg:province":"Pays de Loire",
    "wof:name":"Brunort Productions",
    "wof:placetype":"venue"
},
  "geometry": {"coordinates":[0.003105,47.74577],"type":"Point"}
}