{
  "type": "Feature",
  "properties": {
    "addr:full":"Frontenex 73460 FRONTENEX Rhone-Alpes 73460",
    "addr:postcode":"73460;73460",
    "iso:country":"FR",
    "sg:address":"Frontenex 73460 FRONTENEX",
    "sg:classifiers":[
        {
            "category":"Taxi",
            "type":"Transportation"
        }
    ],
    "sg:phone":"+33 4 79 38 48 29",
    "sg:postcode":"73460",
    "sg:province":"Rhone-Alpes",
    "sg:tags":[
        "air"
    ],
    "wof:name":"Saf Helicopt\u00e9res Sa",
    "wof:placetype":"venue"
},
  "geometry": {"coordinates":[6.31096,45.635201],"type":"Point"}
}