{
  "type": "Feature",
  "properties": {
    "iso:country":"FR",
    "sg:address":"35 Rue Lucien Sampaix 75010 Paris",
    "sg:classifiers":[
        {
            "category":"Communications",
            "subcategory":"Film & Video Production",
            "type":"Services"
        }
    ],
    "sg:phone":"+33 1 46 07 84 70",
    "sg:postcode":"75010",
    "sg:province":"Ile de France",
    "sg:tags":[
        "leather",
        "material",
        "-",
        "machine",
        "raw",
        "engineering",
        "shoe",
        "mechanical"
    ],
    "wof:name":"Osb Sa",
    "wof:placetype":"venue"
},
  "geometry": {"coordinates":[2.361555,48.873497],"type":"Point"}
}