{
  "type": "Feature",
  "properties": {
    "addr:full":"28 Route De La Foret 76113 Sahurs Haute Normandie",
    "addr:housenumber":"28",
    "addr:postcode":"76113",
    "addr:street":"Route De La Foret;Haute Normandie",
    "iso:country":"FR",
    "sg:address":"28 Route De La Foret 76113 Sahurs",
    "sg:classifiers":[
        {
            "category":"Manufacturing",
            "subcategory":"Rubber & Plastics",
            "type":"Manufacturing & Wholesale Goods"
        }
    ],
    "sg:phone":"+33 2 35 32 47 00",
    "sg:province":"Haute Normandie",
    "wof:name":"Les Plastiques De Saint Aubin",
    "wof:placetype":"venue"
},
  "geometry": {"coordinates":[0.944939,49.358677],"type":"Point"}
}