{
  "type": "Feature",
  "properties": {
    "addr:full":"Za 49360 Yzernay Pays de Loire 49360",
    "addr:postcode":"49360;49360",
    "addr:street":"Za",
    "iso:country":"FR",
    "sg:address":"Za 49360 Yzernay",
    "sg:classifiers":[
        {
            "category":"Building & Trades",
            "subcategory":"Construction",
            "type":"Services"
        }
    ],
    "sg:phone":"+33 2 41 55 01 99",
    "sg:postcode":"49360",
    "sg:province":"Pays de Loire",
    "sg:tags":[
        "livestock",
        "business",
        "advice",
        "animal",
        "breeding",
        "agriculture"
    ],
    "wof:name":"M. Mairesse",
    "wof:placetype":"venue"
},
  "geometry": {"coordinates":[-0.641124,46.999599],"type":"Point"}
}