{
  "type": "Feature",
  "properties": {
    "addr:full":"B.P. 6 Domblans^^La Muyre 39210 Domblans Franche Comt\u00e9 39210",
    "addr:postcode":"39210;39210",
    "addr:street":"B.P. 6 Domblans^^La Muyre;Franche Comte\u0301",
    "iso:country":"FR",
    "sg:address":"B.P. 6",
    "sg:city":"Domblans^^La Muyre 39210 Domblans",
    "sg:orig_category":"Extrusion des mati\u00e8res plastiques Mati\u00e8res plastiques, Articles en Mati\u00e8res plastiques, Transformati",
    "sg:phone":"+33 3 84 44 64 20",
    "sg:postcode":"39210",
    "sg:province":"Franche Comt\u00e9",
    "wof:name":"Prenas Plastique S.a.r.l.",
    "wof:placetype":"venue"
},
  "geometry": {"coordinates":[5.59976,46.762726],"type":"Point"}
}