{
  "type": "Feature",
  "properties": {
    "addr:full":"B.P. 21, 71210 Montchanin^^Parc d'Activit\u00e9s Les Morands, 71210 Montchanin Montchanin Bourgogne 71210",
    "addr:postcode":"71210;71210;71210",
    "addr:street":"B.P. 21;\u0301S;Morands",
    "iso:country":"FR",
    "sg:address":"B.P. 21, 71210 Montchanin^^Parc d'Activit\u00e9s Les Morands, 71210 Montchanin",
    "sg:city":"Montchanin",
    "sg:orig_category":"Non-Classified Establishments",
    "sg:phone":"+33 3 85 78 87 78",
    "sg:postcode":"71210",
    "sg:province":"Bourgogne",
    "wof:name":"R\u00e9tif S.a.",
    "wof:placetype":"venue"
},
  "geometry": {"coordinates":[4.427426,46.707455],"type":"Point"}
}