{
  "type": "Feature",
  "properties": {
    "addr:full":"64, Chemin de la Capellane - Parc Burotel, 83140 Six Fours les Plages Centre",
    "addr:housenumber":"64",
    "addr:postcode":"83140",
    "addr:street":"Chemin De La Capellane Parc Burotel;Fours Les Plages Centre",
    "iso:country":"FR",
    "sg:address":"64, Chemin de la Capellane - Parc Burotel, 83140 Six Fours les Plages",
    "sg:orig_category":"Unclassifiable Establishments",
    "sg:phone":"+33 4 94 63 71 71",
    "sg:province":"Centre",
    "wof:name":"Brime Sud S.a.",
    "wof:placetype":"venue"
},
  "geometry": {"coordinates":[5.848281,43.121456],"type":"Point"}
}