{
  "type": "Feature",
  "properties": {
    "addr:full":"2, Rue du Pr\u00e9sident Carnot, 69002 Lyon Rhone-Alpes",
    "addr:housenumber":"2",
    "addr:postcode":"69002",
    "addr:street":"Rue Du Pre\u0301Sident Carnot",
    "iso:country":"FR",
    "sg:address":"2, Rue du Pr\u00e9sident Carnot, 69002 Lyon",
    "sg:orig_category":"Unclassifiable Establishments",
    "sg:phone":"+33 4 72 56 91 00",
    "sg:province":"Rhone-Alpes",
    "wof:name":"Banque De Vizille S.a.",
    "wof:placetype":"venue"
},
  "geometry": {"coordinates":[4.836181,45.761238],"type":"Point"}
}