{
  "type": "Feature",
  "properties": {
    "addr:full":"117 quai du Pr\u00e9sident Roosevelt 92130 Issy les Moulineaux Ile de France 92130",
    "addr:housenumber":"117",
    "addr:postcode":"92130;92130",
    "addr:street":"Quai Du Pre\u0301Sident Roosevelt",
    "iso:country":"FR",
    "sg:address":"117 quai du Pr\u00e9sident Roosevelt 92130 Issy les Moulineaux",
    "sg:classifiers":[
        {
            "category":"Manufacturing",
            "subcategory":"Paper Products",
            "type":"Manufacturing & Wholesale Goods"
        }
    ],
    "sg:phone":"+33 1 41 08 60 00",
    "sg:postcode":"92130",
    "sg:province":"Ile de France",
    "sg:tags":[
        "drawing"
    ],
    "wof:name":"Arjo Wiggins S.a.",
    "wof:placetype":"venue"
},
  "geometry": {"coordinates":[2.261629,48.830067],"type":"Point"}
}