{
  "type": "Feature",
  "properties": {
    "addr:full":"K\u00e9risnel 29250 Saint Pol de L\u00e9on Plougoulm Bretagne 29250",
    "addr:postcode":"29250;29250",
    "addr:street":"Ke\u0301Risnel;Plougoulm Bretagne",
    "iso:country":"FR",
    "sg:address":"K\u00e9risnel 29250 Saint Pol de L\u00e9on",
    "sg:city":"Plougoulm",
    "sg:orig_category":"Non-Classified Establishments",
    "sg:phone":"+33 2 98 69 14 61",
    "sg:postcode":"29250",
    "sg:province":"Bretagne",
    "wof:name":"S.b.l.p. S.a. - Soci\u00e9t\u00e9 Bretonne De L\u00e9gumes Pr\u00e9par\u00e9s",
    "wof:placetype":"venue"
},
  "geometry": {"coordinates":[-3.983367,48.660107],"type":"Point"}
}