{
  "type": "Feature",
  "properties": {
    "iso:country":"FR",
    "sg:address":"91, Rue Nationale, 59040 Lille C\u00e9dex",
    "sg:orig_category":"Non-Classified Establishments",
    "sg:phone":"+33 3 20 30 48 00",
    "sg:province":"Nord Pas-de-Calais",
    "wof:name":"Dumez Eps S.n.c.",
    "wof:placetype":"venue"
},
  "geometry": {"coordinates":[3.057937,50.634972],"type":"Point"}
}