{
  "type": "Feature",
  "properties": {
    "iso:country":"FR",
    "sg:address":"139 Av De La Californie 06200 Nice",
    "sg:classifiers":[
        {
            "category":"Shopping",
            "subcategory":"Gifts & Souvenirs",
            "type":"Retail Goods"
        }
    ],
    "sg:phone":"+33 4 93 86 61 03",
    "sg:tags":[
        "product",
        "miscellaneous"
    ],
    "wof:name":"Medias Presents Multi Cadeaux Eurl",
    "wof:placetype":"venue"
},
  "geometry": {"coordinates":[7.235854,43.685497],"type":"Point"}
}