{
  "type": "Feature",
  "properties": {
    "addr:full":"27, Grande Rue, 73140 Saint Michel de Maurienne Rhone-Alpes",
    "addr:housenumber":"27",
    "addr:postcode":"73140",
    "addr:street":"Grande Rue",
    "iso:country":"FR",
    "sg:address":"27, Grande Rue, 73140 Saint Michel de Maurienne",
    "sg:orig_category":"Unclassifiable Establishments",
    "sg:phone":"+33 4 79 56 54 87",
    "sg:province":"Rhone-Alpes",
    "wof:name":"Trivero S.a.r.l.",
    "wof:placetype":"venue"
},
  "geometry": {"coordinates":[6.470304,45.218559],"type":"Point"}
}