{
  "type": "Feature",
  "properties": {
    "addr:full":"17, Rue des Martyrs, 38054 Grenoble C\u00e9dex 9 Rhone-Alpes",
    "addr:housenumber":"17;9",
    "addr:postcode":"38054",
    "addr:street":"Rue Des Martyrs;Rhone-Alpes",
    "iso:country":"FR",
    "sg:address":"17, Rue des Martyrs, 38054 Grenoble C\u00e9dex 9",
    "sg:orig_category":"Non-Classified Establishments",
    "sg:phone":"+33 4 76 88 41 60",
    "sg:province":"Rhone-Alpes",
    "wof:name":"L.e.t.i. C.e.a. - Laboratoire Electronique De Technique Et D'instrumentation Commissariat Energie At",
    "wof:placetype":"venue"
},
  "geometry": {"coordinates":[5.703657,45.202721],"type":"Point"}
}