{
  "type": "Feature",
  "properties": {
    "addr:full":"Avenue monseigneur de Langle 11401 CASTELNAUDARY CEDEX Midi Pyr\u00e9n\u00e9es",
    "addr:postcode":"11401",
    "addr:street":"Avenue Monseigneur De Langle",
    "iso:country":"FR",
    "sg:address":"Avenue monseigneur de Langle 11401 CASTELNAUDARY CEDEX",
    "sg:classifiers":[
        {
            "category":"Shopping",
            "subcategory":"Clothing, Apparel, & Fashions",
            "type":"Retail Goods"
        }
    ],
    "sg:phone":"+33 4 68 94 40 17",
    "sg:province":"Midi Pyr\u00e9n\u00e9es",
    "sg:tags":[
        "jean"
    ],
    "wof:name":"Ateca France Sa",
    "wof:placetype":"venue"
},
  "geometry": {"coordinates":[1.96656,43.312763],"type":"Point"}
}