{
  "type": "Feature",
  "properties": {
    "iso:country":"FR",
    "sg:address":"40, Rue Principale, 57580 Adaincourt",
    "sg:orig_category":"Non-Classified Establishments",
    "sg:phone":"+33 3 87 64 72 26",
    "sg:province":"Lorraine",
    "wof:name":"Nicolas S.a.r.l.",
    "wof:placetype":"venue"
},
  "geometry": {"coordinates":[6.436241,49.004494],"type":"Point"}
}