{
  "type": "Feature",
  "properties": {
    "addr:full":"2558 Grand Poujeaux Sud 33480 Moulis En M\u00e9doc Avensan Aquitaine 33480",
    "addr:housenumber":"2558",
    "addr:postcode":"33480;33480",
    "addr:street":"Grand Poujeaux Sud",
    "iso:country":"FR",
    "sg:address":"2558 Grand Poujeaux Sud 33480 Moulis En M\u00e9doc",
    "sg:city":"Avensan",
    "sg:classifiers":[
        {
            "category":"Food Court",
            "type":"Food & Drink"
        }
    ],
    "sg:phone":"+33 5 56 58 02 37",
    "sg:postcode":"33480",
    "sg:province":"Aquitaine",
    "sg:tags":[
        "product",
        "related"
    ],
    "wof:name":"Chateau Chasse Spleen Sa",
    "wof:placetype":"venue"
},
  "geometry": {"coordinates":[-0.886118,44.968613],"type":"Point"}
}