{
  "type": "Feature",
  "properties": {
    "iso:country":"FR",
    "sg:address":"Rue Wittholz 67340 Ingwiller",
    "sg:city":"Ingwiller",
    "sg:classifiers":[
        {
            "category":"Professional",
            "type":"Services"
        }
    ],
    "sg:phone":"+33 3 88 89 58 09",
    "sg:postcode":"67340",
    "sg:province":"Alsace",
    "sg:tags":[
        "transport",
        "road"
    ],
    "wof:name":"Transports Bergantz Setab Sarl",
    "wof:placetype":"venue"
},
  "geometry": {"coordinates":[7.474477,48.867935],"type":"Point"}
}