{
  "type": "Feature",
  "properties": {
    "iso:country":"FR",
    "sg:address":"Chemin Jouques 13881 GEMENOS CEDEX",
    "sg:orig_category":"Tarpaulin Bodies",
    "sg:phone":"+33 4 42 32 20 59",
    "sg:province":"Provence-Alpes-C\u00f4te d'Azur",
    "wof:name":"Carrosserie Lambert - Igloo Sa",
    "wof:placetype":"venue"
},
  "geometry": {"coordinates":[5.615988,43.278427],"type":"Point"}
}