{
  "type": "Feature",
  "properties": {
    "addr:full":"6, Chemin du Moulin Rose, 33460 Lamarque Lamarque Aquitaine 33460",
    "addr:housenumber":"6",
    "addr:postcode":"33460;33460",
    "addr:street":"Chemin Du Moulin Rose",
    "iso:country":"FR",
    "sg:address":"6, Chemin du Moulin Rose, 33460 Lamarque",
    "sg:city":"Lamarque",
    "sg:orig_category":"Unclassifiable Establishments",
    "sg:phone":"+33 5 56 58 90 09",
    "sg:postcode":"33460",
    "sg:province":"Aquitaine",
    "wof:name":"Ch\u00e2teau Malescasse S.a.",
    "wof:placetype":"venue"
},
  "geometry": {"coordinates":[-0.716282,45.092873],"type":"Point"}
}