{
  "type": "Feature",
  "properties": {
    "iso:country":"FR",
    "sg:address":"17 rue Marius Berliet Le Chanay 69720 ST BONNET DE MURE",
    "sg:classifiers":[
        {
            "category":"Shopping",
            "subcategory":"Gifts & Souvenirs",
            "type":"Retail Goods"
        }
    ],
    "sg:phone":"+33 4 78 40 42 74",
    "sg:postcode":"69720",
    "sg:province":"Rhone-Alpes",
    "sg:tags":[
        "greeting",
        "card"
    ],
    "wof:name":"Les R\u00e9alisations Herlitz Sa",
    "wof:placetype":"venue"
},
  "geometry": {"coordinates":[5.02467,45.694511],"type":"Point"}
}