{
  "type": "Feature",
  "properties": {
    "addr:full":"230, Rue Fr\u00e9d\u00e9ric Joliot - Pole d'Activit\u00e9s des Milles, 13791 Aix en Provence Nord Pas-de-Calais",
    "addr:housenumber":"230",
    "addr:postcode":"13791",
    "addr:street":"Rue Fre\u0301De\u0301Ric Joliot Pole;Aix En Provence Nord",
    "iso:country":"FR",
    "sg:address":"230, Rue Fr\u00e9d\u00e9ric Joliot - Pole d'Activit\u00e9s des Milles, 13791 Aix en Provence",
    "sg:orig_category":"Unclassifiable Establishments",
    "sg:phone":"+33 4 42 16 86 00",
    "sg:province":"Nord Pas-de-Calais",
    "wof:name":"St\u00e9ria S.a.",
    "wof:placetype":"venue"
},
  "geometry": {"coordinates":[5.442481,43.510448],"type":"Point"}
}