{
  "type": "Feature",
  "properties": {
    "iso:country":"FR",
    "sg:address":"ZI St Denis Chevasse Les Lucs 85170 ST DENIS LA CHEVASSE",
    "sg:classifiers":[
        {
            "category":"Professional",
            "subcategory":"Engineering",
            "type":"Services"
        }
    ],
    "sg:phone":"+33 2 51 41 18 08",
    "sg:postcode":"85170",
    "sg:province":"Pays de Loire",
    "sg:tags":[
        "plant",
        "industrial"
    ],
    "wof:name":"Immequip",
    "wof:placetype":"venue"
},
  "geometry": {"coordinates":[-1.357874,46.822441],"type":"Point"}
}