{
  "type": "Feature",
  "properties": {
    "addr:full":"B.P. 59, 28231 Epernon C\u00e9dex^^ZI des Longs R\u00e9ages, 28230 Epernon \u00c9pernon Centre 28230",
    "addr:housenumber":"e\u0301pernon",
    "addr:postcode":"28231;28230;28230",
    "addr:street":"B.P. 59",
    "iso:country":"FR",
    "sg:address":"B.P. 59, 28231 Epernon C\u00e9dex^^ZI des Longs R\u00e9ages, 28230 Epernon",
    "sg:city":"\u00c9pernon",
    "sg:orig_category":"Non-Classified Establishments",
    "sg:phone":"+33 2 37 18 48 00",
    "sg:postcode":"28230",
    "sg:province":"Centre",
    "wof:name":"C.e.r.i.b. - Centre D'etudes Et De Recherche De L'industrie Du B\u00e9ton",
    "wof:placetype":"venue"
},
  "geometry": {"coordinates":[1.67713,48.609051],"type":"Point"}
}