{
  "type": "Feature",
  "properties": {
    "addr:full":"Av Joliot Curie 64146 Lons (Bill\u00e8re) Bretagne",
    "addr:postcode":"64146",
    "addr:street":"Av Joliot Curie;Bille\u0300Re",
    "iso:country":"FR",
    "sg:address":"Av Joliot Curie 64146 Lons (Bill\u00e8re)",
    "sg:orig_category":"Miscellaneous Products",
    "sg:phone":"+33 5 59 92 35 50",
    "sg:province":"Bretagne",
    "wof:name":"Smith International France Sarl",
    "wof:placetype":"venue"
},
  "geometry": {"coordinates":[-0.413078,43.317261],"type":"Point"}
}