{
  "type": "Feature",
  "properties": {
    "iso:country":"FR",
    "sg:address":"11 bis, Av. Gabriel P\u00e9ri, 78360 Montesson",
    "sg:orig_category":"Unclassifiable Establishments",
    "sg:phone":"+33 1 34 80 89 00",
    "sg:province":"Ile de France",
    "wof:name":"C\u00e9g\u00e9lec S.a.",
    "wof:placetype":"venue"
},
  "geometry": {"coordinates":[2.115432,48.905746],"type":"Point"}
}