{
  "type": "Feature",
  "properties": {
    "addr:full":"10 rue de Reuilly 75012 Paris Ile de France 75012",
    "addr:housenumber":"10",
    "addr:postcode":"75012;75012",
    "addr:street":"Rue De Reuilly",
    "iso:country":"FR",
    "sg:address":"10 rue de Reuilly 75012 Paris",
    "sg:classifiers":[
        {
            "category":"Manufacturing",
            "subcategory":"Metals",
            "type":"Manufacturing & Wholesale Goods"
        }
    ],
    "sg:phone":"+33 1 43 72 18 68",
    "sg:postcode":"75012",
    "sg:province":"Ile de France",
    "sg:tags":[
        "ironmongery"
    ],
    "wof:name":"Christ Et Rudel Sa",
    "wof:placetype":"venue"
},
  "geometry": {"coordinates":[2.385404,48.848808],"type":"Point"}
}