{
  "type": "Feature",
  "properties": {
    "addr:full":"37 Rue Du Croisic Les Salines 44740 Batz Sur Mer Pays de Loire 44740",
    "addr:housenumber":"37",
    "addr:postcode":"44740;44740",
    "addr:street":"Rue Du Croisic Les;Mer",
    "iso:country":"FR",
    "sg:address":"37 Rue Du Croisic Les Salines 44740 Batz Sur Mer",
    "sg:classifiers":[
        {
            "category":"Sports & Exercise",
            "subcategory":"Sports Center",
            "type":"Entertainment"
        }
    ],
    "sg:phone":"+33 2 40 62 62 62",
    "sg:postcode":"44740",
    "sg:province":"Pays de Loire",
    "sg:tags":[
        "game"
    ],
    "wof:name":"Vvf Vacances",
    "wof:placetype":"venue"
},
  "geometry": {"coordinates":[-2.480819,47.276844],"type":"Point"}
}