{
  "type": "Feature",
  "properties": {
    "iso:country":"FR",
    "sg:address":"73 rue Sainte-Anne 75002 Paris",
    "sg:classifiers":[
        {
            "category":"Home & Garden",
            "subcategory":"Building Materials",
            "type":"Retail Goods"
        }
    ],
    "sg:phone":"+33 1 44 77 36 00",
    "sg:postcode":"75002",
    "sg:province":"Ile de France",
    "sg:tags":[
        "fibre",
        "natural",
        "weave"
    ],
    "wof:name":"Ste Pierre Frey Sa",
    "wof:placetype":"venue"
},
  "geometry": {"coordinates":[2.336407,48.868729],"type":"Point"}
}