{
  "type": "Feature",
  "properties": {
    "iso:country":"FR",
    "sg:address":"Mazac 30340 Saint Privat des Vieux",
    "sg:orig_category":"Non-Classified Establishments",
    "sg:phone":"+33 4 66 30 16 88",
    "sg:province":"Languedoc-Roussillon",
    "wof:name":"Fargier Fils S.a.r.l.",
    "wof:placetype":"venue"
},
  "geometry": {"coordinates":[4.117267,44.159325],"type":"Point"}
}