{
  "type": "Feature",
  "properties": {
    "addr:full":"Rte de Sauvigny le Bois Avallon Bourgogne 89200",
    "addr:postcode":"89200",
    "addr:street":"Rte De Sauvigny Le",
    "iso:country":"FR",
    "sg:address":"Rte de Sauvigny le Bois",
    "sg:city":"Avallon",
    "sg:orig_category":"Unclassifiable Establishments",
    "sg:phone":"+33 3 86 31 43 00",
    "sg:postcode":"89200",
    "sg:province":"Bourgogne",
    "wof:name":"Pneu Laurent S.n.c.",
    "wof:placetype":"venue"
},
  "geometry": {"coordinates":[3.924805,47.49662],"type":"Point"}
}