{
  "type": "Feature",
  "properties": {
    "addr:full":"54, Rue du Docteur Mercier, 01130 Nantua Rhone-Alpes 01130",
    "addr:housenumber":"54",
    "addr:postcode":"01130;01130",
    "addr:street":"Rue Du Docteur Mercier",
    "iso:country":"FR",
    "sg:address":"54, Rue du Docteur Mercier, 01130 Nantua",
    "sg:orig_category":"Non-Classified Establishments",
    "sg:phone":"+33 4 74 75 00 87",
    "sg:postcode":"01130",
    "sg:province":"Rhone-Alpes",
    "wof:name":"D.m.g. - Allombert Diffusion Marquage Gravure",
    "wof:placetype":"venue"
},
  "geometry": {"coordinates":[5.605408,46.153023],"type":"Point"}
}