{
  "type": "Feature",
  "properties": {
    "iso:country":"FR",
    "sg:address":"B.P. 18, 57365 Ennery^^ZI Les Jonqui\u00e8res, 57365 Ennery",
    "sg:orig_category":"Non-Classified Establishments",
    "sg:phone":"+33 3 87 73 86 83",
    "sg:province":"Lorraine",
    "wof:name":"Mory Team S.a.",
    "wof:placetype":"venue"
},
  "geometry": {"coordinates":[6.221613,49.22702],"type":"Point"}
}