{
  "type": "Feature",
  "properties": {
    "addr:full":"195, Rue Saint Jacques, 75005 Paris Ile de France",
    "addr:housenumber":"195",
    "addr:postcode":"75005",
    "addr:street":"Rue Saint Jacques",
    "iso:country":"FR",
    "sg:address":"195, Rue Saint Jacques, 75005 Paris",
    "sg:orig_category":"Non-Classified Establishments",
    "sg:phone":"+33 1 44 32 10 70",
    "sg:province":"Ile de France",
    "wof:name":"Institut Oc\u00e9anographique",
    "wof:placetype":"venue"
},
  "geometry": {"coordinates":[2.342436,48.844723],"type":"Point"}
}