{
  "type": "Feature",
  "properties": {
    "addr:full":"11, Av. des Marronniers, 93400 Saint Ouen Ile de France",
    "addr:postcode":"93400;ile",
    "addr:street":"11 Av. Des Marronniers",
    "iso:country":"FR",
    "sg:address":"11, Av. des Marronniers, 93400 Saint Ouen",
    "sg:orig_category":"Non-Classified Establishments",
    "sg:phone":"+33 1 40 10 98 67",
    "sg:province":"Ile de France",
    "wof:name":"L.p.h. S.a.",
    "wof:placetype":"venue"
},
  "geometry": {"coordinates":[2.338457,48.910591],"type":"Point"}
}