{
  "type": "Feature",
  "properties": {
    "addr:full":"14, Rue de Nantes - Le Charlebourg, 92711 Colombes C\u00e9dex \u00cele-de-France",
    "addr:housenumber":"14",
    "addr:postcode":"92711",
    "addr:street":"Rue De Nantes Le Charlebourg;Ce\u0301Dex",
    "iso:country":"FR",
    "sg:address":"14, Rue de Nantes - Le Charlebourg, 92711 Colombes C\u00e9dex",
    "sg:orig_category":"Non-Classified Establishments",
    "sg:phone":"+33 1 46 13 02 70",
    "sg:province":"\u00cele-de-France",
    "wof:name":"Viquel S.a.",
    "wof:placetype":"venue"
},
  "geometry": {"coordinates":[2.25458,48.923481],"type":"Point"}
}