{
  "type": "Feature",
  "properties": {
    "addr:full":"All\u00e9e des Platanes - ZI Saint Hippolyte - Lot. N\u00b011 Venelles Provence-Alpes-C\u00f4te d'Azur 13770",
    "addr:housenumber":"lot. n\u00b011",
    "addr:postcode":"13770",
    "addr:street":"Alle\u0301E Des Platanes Zi;Venelles",
    "iso:country":"FR",
    "sg:address":"All\u00e9e des Platanes - ZI Saint Hippolyte - Lot. N\u00b011",
    "sg:city":"Venelles",
    "sg:orig_category":"Non-Classified Establishments",
    "sg:phone":"+33 2 97 50 92 12",
    "sg:postcode":"13770",
    "sg:province":"Provence-Alpes-C\u00f4te d'Azur",
    "wof:name":"Hill Rom S.a.s",
    "wof:placetype":"venue"
},
  "geometry": {"coordinates":[5.485145,43.599094],"type":"Point"}
}