{
  "type": "Feature",
  "properties": {
    "addr:full":"impasse Amp\u00e8re 69330 Pusignan Rhone-Alpes",
    "addr:postcode":"69330",
    "addr:street":"Impasse Ampe\u0300Re",
    "iso:country":"FR",
    "sg:address":"impasse Amp\u00e8re 69330 Pusignan",
    "sg:classifiers":[
        {
            "category":"Manufacturing",
            "subcategory":"Metals",
            "type":"Manufacturing & Wholesale Goods"
        }
    ],
    "sg:phone":"+33 4 72 05 18 40",
    "sg:province":"Rhone-Alpes",
    "sg:tags":[
        "finishing",
        "surface"
    ],
    "wof:name":"Bodycote Hit Sa",
    "wof:placetype":"venue"
},
  "geometry": {"coordinates":[5.08092,45.763836],"type":"Point"}
}