{
  "type": "Feature",
  "properties": {
    "addr:full":"6 Place Du Pilat St Gaudens Midi Pyr\u00e9n\u00e9es 31800",
    "addr:housenumber":"6",
    "addr:postcode":"31800",
    "addr:street":"Place Du Pilat St",
    "iso:country":"FR",
    "sg:address":"6 Place Du Pilat",
    "sg:city":"St Gaudens",
    "sg:classifiers":[
        {
            "category":"Banks & Credit Unions",
            "subcategory":"Financial Services",
            "type":"Services"
        }
    ],
    "sg:phone":"+33 5 61 95 49 95",
    "sg:postcode":"31800",
    "sg:province":"Midi Pyr\u00e9n\u00e9es",
    "sg:tags":[
        "banking",
        "finance",
        "insurance"
    ],
    "wof:name":"Societe Fiduciaire Nationale Juridique Et Fiscale Fiducial (sofiral)",
    "wof:placetype":"venue"
},
  "geometry": {"coordinates":[0.72051,43.11021],"type":"Point"}
}