{
  "type": "Feature",
  "properties": {
    "addr:full":"1, Rue de Grenette, 71120 Charolles Charolles Bourgogne 71120",
    "addr:housenumber":"1",
    "addr:postcode":"71120;71120",
    "addr:street":"Rue De Grenette",
    "iso:country":"FR",
    "sg:address":"1, Rue de Grenette, 71120 Charolles",
    "sg:city":"Charolles",
    "sg:orig_category":"Unclassifiable Establishments",
    "sg:phone":"+33 3 85 24 29 00",
    "sg:postcode":"71120",
    "sg:province":"Bourgogne",
    "wof:name":"Charolais D\u00e9veloppement",
    "wof:placetype":"venue"
},
  "geometry": {"coordinates":[4.275027,46.43589],"type":"Point"}
}