{
  "type": "Feature",
  "properties": {
    "addr:full":"Parc Industriel de la Rivi\u00e8re de Mansac Mansac Limousin 19520",
    "addr:postcode":"19520",
    "addr:street":"Parc Industriel De La Rivie\u0300Re De Mansac",
    "iso:country":"FR",
    "sg:address":"Parc Industriel de la Rivi\u00e8re de Mansac",
    "sg:city":"Mansac",
    "sg:orig_category":"Non-Classified Establishments",
    "sg:phone":"+33 5 55 85 29 64",
    "sg:postcode":"19520",
    "sg:province":"Limousin",
    "wof:name":"Lucid S.a.s.",
    "wof:placetype":"venue"
},
  "geometry": {"coordinates":[1.306292,45.143715],"type":"Point"}
}