{
  "type": "Feature",
  "properties": {
    "addr:full":"Zone Industrielle 25120 MAICHE Franche Comt\u00e9 25120",
    "addr:postcode":"25120;25120",
    "addr:street":"Zone Industrielle;Franche Comte\u0301",
    "iso:country":"FR",
    "sg:address":"Zone Industrielle 25120 MAICHE",
    "sg:classifiers":[
        {
            "category":"Building & Trades",
            "subcategory":"Plumbing",
            "type":"Services"
        }
    ],
    "sg:phone":"+33 3 81 64 07 89",
    "sg:postcode":"25120",
    "sg:province":"Franche Comt\u00e9",
    "sg:tags":[
        "cropping",
        "tool"
    ],
    "wof:name":"B.m.d. S.a.",
    "wof:placetype":"venue"
},
  "geometry": {"coordinates":[6.798859,47.249786],"type":"Point"}
}