{
  "type": "Feature",
  "properties": {
    "addr:full":"Zone Industrielle F\u00e8re en Tardenois Picardie 02130",
    "addr:postcode":"02130",
    "addr:street":"Zone Industrielle Fe\u0300Re En Tardenois Picardie",
    "iso:country":"FR",
    "sg:address":"Zone Industrielle",
    "sg:city":"F\u00e8re en Tardenois",
    "sg:orig_category":"Non-Classified Establishments",
    "sg:phone":"+33 3 23 82 35 97",
    "sg:postcode":"02130",
    "sg:province":"Picardie",
    "wof:name":"Le Tube Reclass\u00e9 S.a.",
    "wof:placetype":"venue"
},
  "geometry": {"coordinates":[3.51333,49.200764],"type":"Point"}
}