{
  "type": "Feature",
  "properties": {
    "addr:full":"74 Rue De Rennes 75006 Paris Ile de France 75006",
    "addr:housenumber":"74",
    "addr:postcode":"75006;75006",
    "addr:street":"Rue De Rennes",
    "iso:country":"FR",
    "sg:address":"74 Rue De Rennes 75006 Paris",
    "sg:classifiers":[
        {
            "category":"Wholesale",
            "subcategory":"Jewelry",
            "type":"Manufacturing & Wholesale Goods"
        }
    ],
    "sg:phone":"+33 1 42 84 16 17",
    "sg:postcode":"75006",
    "sg:province":"Ile de France",
    "sg:tags":[
        "product",
        "jewellery",
        "miscellaneous",
        "accessory",
        "textile",
        "clothing"
    ],
    "wof:name":"Sarl Ohara",
    "wof:placetype":"venue"
},
  "geometry": {"coordinates":[2.330716,48.851379],"type":"Point"}
}