{
  "type": "Feature",
  "properties": {
    "addr:full":"B.P. 31 Vimoutiers Basse Normandie 61120",
    "addr:postcode":"61120",
    "addr:street":"B.P. 31 Vimoutiers Basse",
    "iso:country":"FR",
    "sg:address":"B.P. 31",
    "sg:city":"Vimoutiers",
    "sg:orig_category":"Non-Classified Establishments",
    "sg:phone":"+33 2 33 39 07 04",
    "sg:postcode":"61120",
    "sg:province":"Basse Normandie",
    "wof:name":"Rings Verseron S.a.",
    "wof:placetype":"venue"
},
  "geometry": {"coordinates":[0.232705,48.851215],"type":"Point"}
}