{
  "type": "Feature",
  "properties": {
    "addr:full":"24 bis, Rue Buffon, 42100 Saint Etienne Rhone-Alpes 42100",
    "addr:housenumber":"24 bis",
    "addr:postcode":"42100;42100",
    "addr:street":"Rue Buffon",
    "iso:country":"FR",
    "sg:address":"24 bis, Rue Buffon, 42100 Saint Etienne",
    "sg:orig_category":"Non-Classified Establishments",
    "sg:phone":"+33 4 77 59 29 79",
    "sg:postcode":"42100",
    "sg:province":"Rhone-Alpes",
    "wof:name":"E.p.e. S.a.r.l. - Euro Plast Electronique",
    "wof:placetype":"venue"
},
  "geometry": {"coordinates":[4.387124,45.416981],"type":"Point"}
}