{
  "type": "Feature",
  "properties": {
    "iso:country":"FR",
    "sg:address":"6, Rue du Pont, 29470 Plougastel Daoulas",
    "sg:city":"Loperhet",
    "sg:orig_category":"Non-Classified Establishments",
    "sg:phone":"+33 2 98 37 57 00",
    "sg:postcode":"29470",
    "sg:province":"Bretagne",
    "wof:name":"France Boissons S.a.",
    "wof:placetype":"venue"
},
  "geometry": {"coordinates":[-4.370008,48.375637],"type":"Point"}
}