{
  "type": "Feature",
  "properties": {
    "iso:country":"FR",
    "sg:address":"136, Bd Maxime Gorki, 94800 Villejuif",
    "sg:orig_category":"Non-Classified Establishments",
    "sg:phone":"+33 1 53 14 36 30",
    "sg:postcode":"94800",
    "sg:province":"Ile de France",
    "wof:name":"Alibastock S.a.r.l.",
    "wof:placetype":"venue"
},
  "geometry": {"coordinates":[2.368593,48.789867],"type":"Point"}
}