{
  "type": "Feature",
  "properties": {
    "addr:full":"47 Rue Montlhery 87000 Limoges Limousin 87000",
    "addr:housenumber":"47",
    "addr:postcode":"87000;87000",
    "addr:street":"Rue Montlhery",
    "iso:country":"FR",
    "sg:address":"47 Rue Montlhery 87000 Limoges",
    "sg:classifiers":[
        {
            "category":"Home & Garden",
            "subcategory":"Furniture",
            "type":"Retail Goods"
        }
    ],
    "sg:phone":"+33 5 55 34 21 94",
    "sg:postcode":"87000",
    "sg:province":"Limousin",
    "sg:tags":[
        "household",
        "wood"
    ],
    "wof:name":"Limogis Diffusion Sa",
    "wof:placetype":"venue"
},
  "geometry": {"coordinates":[1.275763,45.840576],"type":"Point"}
}