{
  "type": "Feature",
  "properties": {
    "addr:full":"34 quai de Boisguilbert 76020 ROUEN CEDEX Auvergne",
    "addr:housenumber":"34",
    "addr:postcode":"76020;cedex",
    "addr:street":"Quai De Boisguilbert",
    "iso:country":"FR",
    "sg:address":"34 quai de Boisguilbert 76020 ROUEN CEDEX",
    "sg:classifiers":[
        {
            "category":"Professional",
            "subcategory":"Engineering",
            "type":"Services"
        }
    ],
    "sg:phone":"+33 2 35 52 54 56",
    "sg:province":"Auvergne",
    "sg:tags":[
        "harbour"
    ],
    "wof:name":"Port Autonome De Rouen Sa",
    "wof:placetype":"venue"
},
  "geometry": {"coordinates":[1.07207,49.444229],"type":"Point"}
}