{
  "type": "Feature",
  "properties": {
    "addr:full":"Rue Georges Mazoyer - ZI la Grande Condemine Tournus Bourgogne 71700",
    "addr:postcode":"71700",
    "addr:street":"Rue Georges Mazoyer Zi La Grande Condemine;Bourgogne",
    "iso:country":"FR",
    "sg:address":"Rue Georges Mazoyer - ZI la Grande Condemine",
    "sg:city":"Tournus",
    "sg:orig_category":"Non-Classified Establishments",
    "sg:phone":"+33 3 85 51 75 00",
    "sg:postcode":"71700",
    "sg:province":"Bourgogne",
    "wof:name":"Arfa S.a.s.",
    "wof:placetype":"venue"
},
  "geometry": {"coordinates":[4.830926,46.504631],"type":"Point"}
}