{
  "type": "Feature",
  "properties": {
    "addr:full":"65 Cs Dupr\u00e9 33041 Bordeaux Cedex Aquitaine",
    "addr:postcode":"33041 bordeaux cedex",
    "addr:street":"Cs Dupre\u0301",
    "iso:country":"FR",
    "sg:address":"65 Cs Dupr\u00e9",
    "sg:city":"33041 Bordeaux Cedex",
    "sg:classifiers":[
        {
            "category":"Autos & Motor Vehicles",
            "subcategory":"Automobile Sales",
            "type":"Retail Goods"
        }
    ],
    "sg:phone":"+33 5 56 11 71 40",
    "sg:province":"Aquitaine",
    "sg:tags":[
        "equipment",
        "industrial",
        "transport"
    ],
    "wof:name":"Aquitaine Vehicules Industriels Sa",
    "wof:placetype":"venue"
},
  "geometry": {"coordinates":[-0.54581,44.8027],"type":"Point"}
}