{
  "type": "Feature",
  "properties": {
    "iso:country":"FR",
    "sg:address":"5, Esplanade Charles de Gaulle, 92733 Nanterre",
    "sg:orig_category":"Non-Classified Establishments",
    "sg:phone":"+33 1 47 67 15 00",
    "sg:province":"Midi Pyr\u00e9n\u00e9es",
    "wof:name":"Sedit Marianne S.a.",
    "wof:placetype":"venue"
},
  "geometry": {"coordinates":[2.22199,48.89563],"type":"Point"}
}