{
  "type": "Feature",
  "properties": {
    "addr:full":"Le Flacher 07340 F\u00e9lines Rhone-Alpes 07340",
    "addr:postcode":"07340;07340",
    "addr:street":"Rhone-Alpes",
    "iso:country":"FR",
    "sg:address":"Le Flacher 07340 F\u00e9lines",
    "sg:classifiers":[
        {
            "category":"Wholesale",
            "subcategory":"Machinery & Supplies",
            "type":"Manufacturing & Wholesale Goods"
        }
    ],
    "sg:phone":"+33 4 75 34 86 31",
    "sg:postcode":"07340",
    "sg:province":"Rhone-Alpes",
    "sg:tags":[
        "equipment",
        "precision"
    ],
    "wof:name":"Sadela Industrie",
    "wof:placetype":"venue"
},
  "geometry": {"coordinates":[4.73679,45.306499],"type":"Point"}
}