{
  "type": "Feature",
  "properties": {
    "addr:full":"1 Av Gal De Gaulle 58000 Nevers Nevers Bourgogne 58000",
    "addr:postcode":"58000;58000",
    "addr:street":"Av Gal De Gaulle",
    "iso:country":"FR",
    "sg:address":"1 Av Gal De Gaulle 58000 Nevers",
    "sg:city":"Nevers",
    "sg:classifiers":[
        {
            "category":"Professional",
            "subcategory":"Business Services",
            "type":"Services"
        }
    ],
    "sg:phone":"+33 3 86 61 37 34",
    "sg:postcode":"58000",
    "sg:province":"Bourgogne",
    "sg:tags":[
        "travel",
        "fair"
    ],
    "wof:name":"Nivexpo-foires Et Salons Nivernais Morvan",
    "wof:placetype":"venue"
},
  "geometry": {"coordinates":[3.156828,46.98867],"type":"Point"}
}