{
  "type": "Feature",
  "properties": {
    "addr:full":"100, R de la Plaine des Bouchers, 67100 Strasbourg Strasbourg Alsace 67100",
    "addr:housenumber":"100",
    "addr:postcode":"67100;67100",
    "addr:street":"R De La Plaine Des Bouchers",
    "iso:country":"FR",
    "sg:address":"100, R de la Plaine des Bouchers, 67100 Strasbourg",
    "sg:city":"Strasbourg",
    "sg:orig_category":"Unclassifiable Establishments",
    "sg:phone":"+33 3 88 79 32 32",
    "sg:postcode":"67100",
    "sg:province":"Alsace",
    "wof:name":"Maechler Fr\u00e8res S.a.",
    "wof:placetype":"venue"
},
  "geometry": {"coordinates":[7.737402,48.556168],"type":"Point"}
}