{
  "type": "Feature",
  "properties": {
    "iso:country":"FR",
    "sg:address":"122 R Du G\u00e9n\u00e9ral De Lobit 40000 Mont De Marsan",
    "sg:city":"Mont-de-Marsan",
    "sg:classifiers":[
        {
            "category":"Professional",
            "subcategory":"Business Services",
            "type":"Services"
        }
    ],
    "sg:phone":"+33 5 58 06 31 32",
    "sg:postcode":"40000",
    "sg:province":"Aquitaine",
    "sg:tags":[
        "body",
        "advice"
    ],
    "wof:name":"Federation Ass Laique Education Permanente",
    "wof:placetype":"venue"
},
  "geometry": {"coordinates":[-0.48761,43.896175],"type":"Point"}
}