{
  "type": "Feature",
  "properties": {
    "addr:full":"B.P. 2908, 75369 Paris C\u00e9dex 8^^14, Av. Franklin Roosevelt, 75008 Paris Ile de France 75008",
    "addr:housenumber":"2908;8;^ 14",
    "addr:postcode":"75369;75008;75008",
    "addr:street":"B.P.;^;Av. Franklin Roosevelt",
    "iso:country":"FR",
    "sg:address":"B.P. 2908, 75369 Paris C\u00e9dex 8^^14, Av. Franklin Roosevelt, 75008 Paris",
    "sg:orig_category":"Non-Classified Establishments",
    "sg:phone":"+33 1 44 20 50 50",
    "sg:postcode":"75008",
    "sg:province":"Ile de France",
    "wof:name":"Banco Pinto Et Sotto Mayor",
    "wof:placetype":"venue"
},
  "geometry": {"coordinates":[2.34121,48.856926],"type":"Point"}
}