{
  "type": "Feature",
  "properties": {
    "addr:full":"6 Av Charles De Gaulle 85340 Olonne Sur Mer Pays de Loire 85340",
    "addr:postcode":"85340;85340",
    "addr:street":"Av Charles De Gaulle",
    "iso:country":"FR",
    "sg:address":"6 Av Charles De Gaulle 85340 Olonne Sur Mer",
    "sg:classifiers":[
        {
            "category":"Autos & Motor Vehicles",
            "subcategory":"Automobile Sales",
            "type":"Retail Goods"
        }
    ],
    "sg:phone":"+33 2 51 21 01 07",
    "sg:postcode":"85340",
    "sg:province":"Pays de Loire",
    "sg:tags":[
        "equipment",
        "motor-cars",
        "transport"
    ],
    "wof:name":"Central Garage (sa)",
    "wof:placetype":"venue"
},
  "geometry": {"coordinates":[-1.773394,46.504326],"type":"Point"}
}