{
  "type": "Feature",
  "properties": {
    "addr:full":"B.P. 147, 38354 La Tour du Pin C\u00e9dex^^Rue Ren\u00e9 Duchamp, 38110 La Tour du Pin Rhone-Alpes",
    "addr:housenumber":"b.p. 147;38110",
    "addr:postcode":"38354",
    "iso:country":"FR",
    "sg:address":"B.P. 147, 38354 La Tour du Pin C\u00e9dex^^Rue Ren\u00e9 Duchamp, 38110 La Tour du Pin",
    "sg:orig_category":"Non-Classified Establishments",
    "sg:phone":"+33 4 74 83 20 80",
    "sg:province":"Rhone-Alpes",
    "wof:name":"Isoc\u00e8le S.a.",
    "wof:placetype":"venue"
},
  "geometry": {"coordinates":[5.454585,45.52478],"type":"Point"}
}