{
  "type": "Feature",
  "properties": {
    "iso:country":"FR",
    "sg:address":"134 Rue D Aboukir 75002 Paris",
    "sg:classifiers":[
        {
            "category":"Shopping",
            "subcategory":"Clothing, Apparel, & Fashions",
            "type":"Retail Goods"
        }
    ],
    "sg:phone":"+33 1 40 28 11 70",
    "sg:postcode":"75002",
    "sg:province":"Ile de France",
    "sg:tags":[
        "textile",
        "clothing",
        "clothes"
    ],
    "wof:name":"Mirami",
    "wof:placetype":"venue"
},
  "geometry": {"coordinates":[2.351821,48.869083],"type":"Point"}
}