{
  "type": "Feature",
  "properties": {
    "addr:full":"3, Bd Eiffel, 21600 Longvic Longvic Bourgogne 21600",
    "addr:housenumber":"3",
    "addr:postcode":"21600;21600",
    "addr:street":"Bd Eiffel",
    "iso:country":"FR",
    "sg:address":"3, Bd Eiffel, 21600 Longvic",
    "sg:city":"Longvic",
    "sg:orig_category":"Unclassifiable Establishments",
    "sg:phone":"+33 3 80 69 14 00",
    "sg:postcode":"21600",
    "sg:province":"Bourgogne",
    "wof:name":"Sim\u00e9lectro S.a.",
    "wof:placetype":"venue"
},
  "geometry": {"coordinates":[5.056567,47.277546],"type":"Point"}
}