{
  "type": "Feature",
  "properties": {
    "iso:country":"FR",
    "sg:address":"3, Bd Eiffel, 21600 Longvic",
    "sg:city":"Longvic",
    "sg:orig_category":"Unclassifiable Establishments",
    "sg:phone":"+33 3 80 69 14 00",
    "sg:postcode":"21600",
    "sg:province":"Bourgogne",
    "wof:name":"Sim\u00e9lectro S.a.",
    "wof:placetype":"venue"
},
  "geometry": {"coordinates":[5.056567,47.277546],"type":"Point"}
}