{
  "type": "Feature",
  "properties": {
    "addr:full":"4 Rue Gay Lussac 22000 Saint Brieuc Saint-Brieuc Bretagne 22000",
    "addr:housenumber":"4",
    "addr:postcode":"22000;22000",
    "addr:street":"Rue Gay Lussac;Brieuc;Bretagne",
    "iso:country":"FR",
    "sg:address":"4 Rue Gay Lussac 22000 Saint Brieuc",
    "sg:city":"Saint-Brieuc",
    "sg:orig_category":"Clothes Plastics Rubber Rubber and Plastics Textiles and Clothing",
    "sg:phone":"+33 2 96 61 42 66",
    "sg:postcode":"22000",
    "sg:province":"Bretagne",
    "wof:name":"Ets Cardon Et Fils",
    "wof:placetype":"venue"
},
  "geometry": {"coordinates":[-2.733913,48.50729],"type":"Point"}
}