{
  "type": "Feature",
  "properties": {
    "addr:full":"191 C av Saint Exup\u00e9ry; Bron Rhone-Alpes",
    "addr:housenumber":"191",
    "addr:street":"C Av Saint Exupe\u0301Ry;Rhone-Alpes",
    "iso:country":"FR",
    "sg:address":"191 C av Saint Exup\u00e9ry; Bron",
    "sg:classifiers":[
        {
            "category":"Banks & Credit Unions",
            "subcategory":"Bank",
            "type":"Services"
        }
    ],
    "sg:phone":"+33 3378772727",
    "sg:province":"Rhone-Alpes",
    "wof:name":"C.g.l Direction Sud Est",
    "wof:placetype":"venue"
},
  "geometry": {"coordinates":[4.913522,45.725834],"type":"Point"}
}