{
  "type": "Feature",
  "properties": {
    "addr:full":"60, Rue de Vaudemont Redlach, 57385 Tritteling Aquitaine",
    "addr:housenumber":"60",
    "addr:postcode":"57385",
    "addr:street":"Rue De Vaudemont Redlach",
    "iso:country":"FR",
    "sg:address":"60, Rue de Vaudemont Redlach, 57385 Tritteling",
    "sg:orig_category":"Unclassifiable Establishments",
    "sg:phone":"+33 3 87 94 46 43",
    "sg:province":"Aquitaine",
    "wof:name":"S.3.r. S.a.r.l.",
    "wof:placetype":"venue"
},
  "geometry": {"coordinates":[6.66125,49.05661],"type":"Point"}
}