{
  "type": "Feature",
  "properties": {
    "addr:full":"Contour Cial Regional Belle 94320 Thiais Ile de France 94320",
    "addr:postcode":"94320;94320",
    "addr:street":"Contour Cial",
    "iso:country":"FR",
    "sg:address":"Contour Cial Regional Belle 94320 Thiais",
    "sg:classifiers":[
        {
            "category":"Travel",
            "subcategory":"Hotels & Motels",
            "type":"Entertainment"
        }
    ],
    "sg:phone":"+33 1 46 87 94 66",
    "sg:postcode":"94320",
    "sg:province":"Ile de France",
    "sg:tags":[
        "hotels",
        "business",
        "restaurant"
    ],
    "wof:name":"Mc Donalds France Restaurants Mc Donalds",
    "wof:placetype":"venue"
},
  "geometry": {"coordinates":[2.390409,48.765186],"type":"Point"}
}