{
  "type": "Feature",
  "properties": {
    "iso:country":"FR",
    "sg:address":"Z.A les Planches",
    "sg:city":"Digoin",
    "sg:orig_category":"Non-Classified Establishments",
    "sg:phone":"+33 3 85 53 07 50",
    "sg:postcode":"71160",
    "sg:province":"Bourgogne",
    "wof:name":"Totaro Armatures S.a.r.l.",
    "wof:placetype":"venue"
},
  "geometry": {"coordinates":[3.977895,46.481796],"type":"Point"}
}