{
  "type": "Feature",
  "properties": {
    "addr:full":"Ancienne Gare De Soulosse 88630 Coussey Lorraine 88630",
    "addr:postcode":"88630;88630",
    "iso:country":"FR",
    "sg:address":"Ancienne Gare De Soulosse 88630 Coussey",
    "sg:classifiers":[
        {
            "category":"Farming",
            "subcategory":"Farm & Veterinary Services",
            "type":"Manufacturing & Wholesale Goods"
        }
    ],
    "sg:phone":"+33 3 29 06 92 71",
    "sg:postcode":"88630",
    "sg:province":"Lorraine",
    "sg:tags":[
        "advice",
        "agriculture",
        "livestock",
        "business"
    ],
    "wof:name":"Gaillard Rondino",
    "wof:placetype":"venue"
},
  "geometry": {"coordinates":[5.733325,48.402817],"type":"Point"}
}