{
  "type": "Feature",
  "properties": {
    "iso:country":"FR",
    "sg:address":"23230 La Celle sous Gouzon",
    "sg:orig_category":"Unclassifiable Establishments",
    "sg:phone":"+33 5 55 62 20 62",
    "sg:province":"Limousin",
    "wof:name":"Etablissements Champeval S.a.",
    "wof:placetype":"venue"
},
  "geometry": {"coordinates":[2.21027,46.214432],"type":"Point"}
}