{
  "type": "Feature",
  "properties": {
    "iso:country":"FR",
    "sg:address":"28 avenue Charles de Gaulle 25460 Etupes",
    "sg:classifiers":[
        {
            "category":"Wholesale",
            "subcategory":"Painting Supplies",
            "type":"Manufacturing & Wholesale Goods"
        }
    ],
    "sg:phone":"+33 3 81 94 28 78",
    "sg:postcode":"25460",
    "sg:province":"Franche Comt\u00e9",
    "sg:tags":[
        "paint",
        "industrial"
    ],
    "wof:name":"Geraldy S.a.",
    "wof:placetype":"venue"
},
  "geometry": {"coordinates":[6.85871,47.506649],"type":"Point"}
}