{
  "type": "Feature",
  "properties": {
    "addr:full":"67, Rue Lafayette, 75009 Paris Ile de France",
    "addr:housenumber":"67",
    "addr:postcode":"75009",
    "addr:street":"Rue Lafayette",
    "iso:country":"FR",
    "sg:address":"67, Rue Lafayette, 75009 Paris",
    "sg:orig_category":"Unclassifiable Establishments",
    "sg:phone":"+33 1 48 78 35 15",
    "sg:province":"Ile de France",
    "wof:name":"La Nouvelle Holding S.a.",
    "wof:placetype":"venue"
},
  "geometry": {"coordinates":[2.340605,48.87368],"type":"Point"}
}