{
  "type": "Feature",
  "properties": {
    "addr:full":"8, Rue Paul Langevin - Z.A.C. Parc Saint Jacques II, 54320 Max\u00e9ville Lorraine",
    "addr:housenumber":"8",
    "addr:postcode":"54320",
    "addr:street":"Rue Paul Langevin Z.A.C. Parc Saint;Ii",
    "iso:country":"FR",
    "sg:address":"8, Rue Paul Langevin - Z.A.C. Parc Saint Jacques II, 54320 Max\u00e9ville",
    "sg:orig_category":"Non-Classified Establishments",
    "sg:phone":"+33 3 83 98 10 39",
    "sg:province":"Lorraine",
    "wof:name":"G.t.m. Agence Lorraine",
    "wof:placetype":"venue"
},
  "geometry": {"coordinates":[6.130915,48.704048],"type":"Point"}
}