{
  "type": "Feature",
  "properties": {
    "addr:full":"1 rue Jules Ferry; Roscoff; 29211 Languedoc-Roussillon",
    "addr:housenumber":"1",
    "addr:postcode":"29211",
    "addr:street":"Rue Jules Ferry",
    "iso:country":"FR",
    "sg:address":"1 rue Jules Ferry; Roscoff; 29211",
    "sg:classifiers":[
        {
            "category":"Banks & Credit Unions",
            "subcategory":"Bank",
            "type":"Services"
        }
    ],
    "sg:phone":"+33 3398697351",
    "sg:province":"Languedoc-Roussillon",
    "wof:name":"Soci\u00e9t\u00e9 G\u00e9n\u00e9rale",
    "wof:placetype":"venue"
},
  "geometry": {"coordinates":[-3.982432,48.723461],"type":"Point"}
}