{
  "type": "Feature",
  "properties": {
    "iso:country":"FR",
    "sg:address":"Fbg de Cambrai - Premier Pont",
    "sg:city":"Le Cateau Cambresis",
    "sg:orig_category":"Unclassifiable Establishments",
    "sg:phone":"+33 3 27 84 14 72",
    "sg:postcode":"59360",
    "sg:province":"Nord Pas-de-Calais",
    "wof:name":"Caffiaux Debatte Aciers S.a.s.",
    "wof:placetype":"venue"
},
  "geometry": {"coordinates":[3.543052,50.105213],"type":"Point"}
}