{
  "type": "Feature",
  "properties": {
    "addr:full":"1/3, Av. des 3 Peuples, 78180 Montigny le Bretonneux Ile de France",
    "addr:housenumber":"1 / 3",
    "addr:postcode":"78180",
    "addr:street":"Av. Des 3 Peuples",
    "iso:country":"FR",
    "sg:address":"1/3, Av. des 3 Peuples, 78180 Montigny le Bretonneux",
    "sg:orig_category":"Unclassifiable Establishments",
    "sg:phone":"+33 1 30 64 98 80",
    "sg:province":"Ile de France",
    "wof:name":"Fimatec S.a.",
    "wof:placetype":"venue"
},
  "geometry": {"coordinates":[2.015855,48.773685],"type":"Point"}
}