{
  "type": "Feature",
  "properties": {
    "iso:country":"FR",
    "sg:address":"1 Rond Point Pariwest 78310 Maurepas",
    "sg:classifiers":[
        {
            "category":"Manufacturing",
            "subcategory":"Chemicals & Compounds",
            "type":"Manufacturing & Wholesale Goods"
        }
    ],
    "sg:phone":"+33 1 30 05 10 00",
    "sg:postcode":"78310",
    "sg:province":"Ile de France",
    "sg:tags":[
        "pharmaceutical",
        "chemistry",
        "-",
        "by-product"
    ],
    "wof:name":"Ondeo Nalco France",
    "wof:placetype":"venue"
},
  "geometry": {"coordinates":[1.92177,48.759521],"type":"Point"}
}