{
  "type": "Feature",
  "properties": {
    "addr:full":"59 avenue F\u00e9lix Faure 69003 Lyon Rhone-Alpes 69003",
    "addr:housenumber":"59",
    "addr:postcode":"69003;69003",
    "addr:street":"Avenue Fe\u0301Lix Faure",
    "iso:country":"FR",
    "sg:address":"59 avenue F\u00e9lix Faure 69003 Lyon",
    "sg:classifiers":[
        {
            "category":"Military Area",
            "subcategory":"Air Force Base",
            "type":"Public Place"
        }
    ],
    "sg:phone":"+33 4 78 62 77 13",
    "sg:postcode":"69003",
    "sg:province":"Rhone-Alpes",
    "sg:tags":[
        "institutional",
        "linen",
        "use"
    ],
    "wof:name":"Pero's S.a.r.l.",
    "wof:placetype":"venue"
},
  "geometry": {"coordinates":[4.854938,45.753258],"type":"Point"}
}