{
  "type": "Feature",
  "properties": {
    "iso:country":"FR",
    "sg:address":"ZA des Marli\u00e8res",
    "sg:city":"Avelin",
    "sg:orig_category":"Unclassifiable Establishments",
    "sg:phone":"+33 3 20 62 56 30",
    "sg:postcode":"59710",
    "sg:province":"Nord Pas-de-Calais",
    "wof:name":"Logilift S.a.",
    "wof:placetype":"venue"
},
  "geometry": {"coordinates":[3.080295,50.53793],"type":"Point"}
}