{
  "type": "Feature",
  "properties": {
    "iso:country":"FR",
    "sg:address":"ZI de la Coindrie",
    "sg:city":"Tr\u00e9mentines",
    "sg:orig_category":"Non-Classified Establishments",
    "sg:phone":"+33 2 41 46 41 82",
    "sg:postcode":"49340",
    "sg:province":"Pays de Loire",
    "wof:name":"M\u00e9carect E.u.r.l.",
    "wof:placetype":"venue"
},
  "geometry": {"coordinates":[-0.788103,47.123554],"type":"Point"}
}