{
  "type": "Feature",
  "properties": {
    "addr:full":"4, All\u00e9e Lorentz - Cit\u00e9 des Cartes, 77420 Champs sur Marne Ile de France 77420",
    "addr:housenumber":"4",
    "addr:postcode":"77420;77420",
    "addr:street":"Alle\u0301E Lorentz Cite\u0301 Des Cartes",
    "iso:country":"FR",
    "sg:address":"4, All\u00e9e Lorentz - Cit\u00e9 des Cartes, 77420 Champs sur Marne",
    "sg:orig_category":"Non-Classified Establishments",
    "sg:phone":"+33 1 64 68 06 06",
    "sg:postcode":"77420",
    "sg:province":"Ile de France",
    "wof:name":"B.c. Int\u00e9rieur S.a.r.l.",
    "wof:placetype":"venue"
},
  "geometry": {"coordinates":[2.591621,48.834396],"type":"Point"}
}