{
  "type": "Feature",
  "properties": {
    "iso:country":"FR",
    "sg:address":"B.P. 58",
    "sg:city":"Valognes",
    "sg:orig_category":"Non-Classified Establishments",
    "sg:phone":"+33 2 33 40 19 16",
    "sg:postcode":"50700",
    "sg:province":"Basse Normandie",
    "wof:name":"A.m.c. Folliot S.a.",
    "wof:placetype":"venue"
},
  "geometry": {"coordinates":[-1.468479,49.508766],"type":"Point"}
}