{
  "type": "Feature",
  "properties": {
    "addr:full":"Rue du Docteur Guerry - Zone des 3 Canons Fontenay le Comte Pays de Loire 85200",
    "addr:postcode":"85200",
    "addr:street":"Rue Du Docteur Guerry;Des 3 Canons;Comte",
    "iso:country":"FR",
    "sg:address":"Rue du Docteur Guerry - Zone des 3 Canons",
    "sg:city":"Fontenay le Comte",
    "sg:orig_category":"Non-Classified Establishments",
    "sg:phone":"+33 2 51 69 90 90",
    "sg:postcode":"85200",
    "sg:province":"Pays de Loire",
    "wof:name":"Hydroland S.a.",
    "wof:placetype":"venue"
},
  "geometry": {"coordinates":[-0.807965,46.392536],"type":"Point"}
}