{
  "type": "Feature",
  "properties": {
    "iso:country":"FR",
    "sg:address":"8",
    "sg:city":"Fournier; Clichy; 92110",
    "sg:classifiers":[
        {
            "category":"Industrial Area",
            "type":"Public Place"
        }
    ],
    "sg:phone":"+33 1 49 68 12 12",
    "sg:province":"Ile de France",
    "sg:tags":[
        "large",
        "private"
    ],
    "wof:name":"Business Interactif Sa",
    "wof:placetype":"venue"
},
  "geometry": {"coordinates":[2.298283,48.905441],"type":"Point"}
}