{
  "type": "Feature",
  "properties": {
    "addr:full":"Le Bourg 22650 Tr\u00e9gon Tr\u00e9gon Bretagne 22650",
    "addr:postcode":"22650;22650",
    "addr:street":"Le Bourg;Tre\u0301Gon",
    "iso:country":"FR",
    "sg:address":"Le Bourg 22650 Tr\u00e9gon",
    "sg:city":"Tr\u00e9gon",
    "sg:orig_category":"Unclassifiable Establishments",
    "sg:phone":"+33 2 96 27 20 32",
    "sg:postcode":"22650",
    "sg:province":"Bretagne",
    "wof:name":"Etablissements Bonenfant E.u.r.l.",
    "wof:placetype":"venue"
},
  "geometry": {"coordinates":[-2.182513,48.570801],"type":"Point"}
}