{
  "type": "Feature",
  "properties": {
    "iso:country":"FR",
    "sg:address":"Rue du Mont Sainghin - Centre de Gros N\u00b0 1",
    "sg:city":"Lesquin",
    "sg:orig_category":"Unclassifiable Establishments",
    "sg:phone":"+33 2 20 90 45 90",
    "sg:postcode":"59810",
    "sg:province":"Nord Pas-de-Calais",
    "wof:name":"Lex Manutention - Agence Nord",
    "wof:placetype":"venue"
},
  "geometry": {"coordinates":[3.11003,50.588009],"type":"Point"}
}