{
  "type": "Feature",
  "properties": {
    "addr:full":"23, Rue Michael Faraday, 37174 Chambray l\u00e8s Tours Centre",
    "addr:housenumber":"23",
    "addr:postcode":"37174",
    "addr:street":"Rue Michael Faraday",
    "iso:country":"FR",
    "sg:address":"23, Rue Michael Faraday, 37174 Chambray l\u00e8s Tours",
    "sg:orig_category":"Unclassifiable Establishments",
    "sg:phone":"+33 2 47 80 46 80",
    "sg:province":"Centre",
    "wof:name":"A.p.a.v.e. Ouest",
    "wof:placetype":"venue"
},
  "geometry": {"coordinates":[0.698098,47.334557],"type":"Point"}
}