{
  "type": "Feature",
  "properties": {
    "iso:country":"FR",
    "sg:address":"B.P. 119, 51480 Damery^^8, Rue G Cl\u00e9menceau, 51480 Damery",
    "sg:orig_category":"Non-Classified Establishments",
    "sg:phone":"+33 3 26 58 41 23",
    "sg:postcode":"51480",
    "sg:province":"Champagne",
    "wof:name":"Champagne Jeeper S.a.",
    "wof:placetype":"venue"
},
  "geometry": {"coordinates":[3.878572,49.072487],"type":"Point"}
}