{
  "type": "Feature",
  "properties": {
    "iso:country":"FR",
    "sg:address":"11 rue des Cayennes 78700 CONFLANS STE HONORINE",
    "sg:classifiers":[
        {
            "category":"Autos & Motor Vehicles",
            "subcategory":"Fuel & Gas Station",
            "type":"Retail Goods"
        }
    ],
    "sg:phone":"+33 1 39 19 99 70",
    "sg:province":"Ile de France",
    "sg:tags":[
        "component"
    ],
    "wof:name":"Distribution Informatique Internationale S.a.r.l.",
    "wof:placetype":"venue"
},
  "geometry": {"coordinates":[2.082998,49.008881],"type":"Point"}
}