{
  "type": "Feature",
  "properties": {
    "addr:full":"440, Rue L\u00e9on Blum, 59460 Jeumont Nord Pas-de-Calais",
    "addr:housenumber":"440",
    "addr:postcode":"59460",
    "addr:street":"Rue Le\u0301On Blum",
    "iso:country":"FR",
    "sg:address":"440, Rue L\u00e9on Blum, 59460 Jeumont",
    "sg:orig_category":"Unclassifiable Establishments",
    "sg:phone":"+33 3 27 39 51 87",
    "sg:province":"Nord Pas-de-Calais",
    "wof:name":"Rou\u00e9 Imprimerie S.a.r.l.",
    "wof:placetype":"venue"
},
  "geometry": {"coordinates":[4.087686,50.295437],"type":"Point"}
}