{
  "type": "Feature",
  "properties": {
    "iso:country":"FR",
    "sg:address":"All\u00e9e des Prunus - Parc Industriel Plaine de l'Ain",
    "sg:city":"Blyes",
    "sg:orig_category":"Unclassifiable Establishments",
    "sg:phone":"+33 4 74 46 24 24",
    "sg:postcode":"01150",
    "sg:province":"Rhone-Alpes",
    "wof:name":"Inserlec S.a.",
    "wof:placetype":"venue"
},
  "geometry": {"coordinates":[5.261127,45.84079],"type":"Point"}
}