{
  "type": "Feature",
  "properties": {
    "iso:country":"FR",
    "sg:address":"Av. des Mel\u00e8zes",
    "sg:city":"Thyez",
    "sg:orig_category":"Unclassifiable Establishments",
    "sg:phone":"+33 4 50 89 39 00",
    "sg:postcode":"74300",
    "sg:province":"Rhone-Alpes",
    "wof:name":"E.m.t. 74 S.a.s",
    "wof:placetype":"venue"
},
  "geometry": {"coordinates":[6.54059,46.07777],"type":"Point"}
}