{
  "type": "Feature",
  "properties": {
    "addr:full":"8, Rue Arnavielle, 40000 N\u00eemes Mont-de-Marsan Aquitaine 40000",
    "addr:housenumber":"8",
    "addr:postcode":"40000;40000",
    "addr:street":"Rue Arnavielle",
    "iso:country":"FR",
    "sg:address":"8, Rue Arnavielle, 40000 N\u00eemes",
    "sg:city":"Mont-de-Marsan",
    "sg:orig_category":"Unclassifiable Establishments",
    "sg:phone":"+33 4 66 64 34 37",
    "sg:postcode":"40000",
    "sg:province":"Aquitaine",
    "wof:name":"S.l.e.c. S.a.",
    "wof:placetype":"venue"
},
  "geometry": {"coordinates":[4.350772,43.823677],"type":"Point"}
}