{
  "type": "Feature",
  "properties": {
    "iso:country":"FR",
    "sg:address":"Le Ch\u00eane Du Moulin 35600 Bains Sur Oust",
    "sg:city":"Bains-sur-Oust",
    "sg:classifiers":[
        {
            "category":"Shopping",
            "type":"Retail Goods"
        }
    ],
    "sg:phone":"+33 2 99 91 76 56",
    "sg:postcode":"35600",
    "sg:province":"Bretagne",
    "sg:tags":[
        "metallurgy",
        "finished",
        "-",
        "metalworking",
        "metallic"
    ],
    "wof:name":"Scm Sarl",
    "wof:placetype":"venue"
},
  "geometry": {"coordinates":[-2.085934,47.651035],"type":"Point"}
}