{
  "type": "Feature",
  "properties": {
    "addr:full":"2 Rue Du Champ Dor\u00e9 Zac Du Bois Guillaume 21850 St-Apollinaire Saint-Apollinaire Bourgogne 21850",
    "addr:housenumber":"2",
    "addr:postcode":"21850;21850",
    "addr:street":"Rue Du Champ Dore\u0301 Zac Du Bois Guillaume",
    "iso:country":"FR",
    "sg:address":"2 Rue Du Champ Dor\u00e9 Zac Du Bois Guillaume 21850 St-Apollinaire",
    "sg:city":"Saint-Apollinaire",
    "sg:orig_category":"Agriculture and Livestock Cereals and grains Food and Related Products Frozen food",
    "sg:phone":"+33 3 80 73 07 77",
    "sg:postcode":"21850",
    "sg:province":"Bourgogne",
    "wof:name":"Eurogerm Sa",
    "wof:placetype":"venue"
},
  "geometry": {"coordinates":[5.083654,47.333641],"type":"Point"}
}