{
  "type": "Feature",
  "properties": {
    "addr:full":"6, Rue Revel, 83000 Toulon Provence-Alpes-C\u00f4te d'Azur",
    "addr:housenumber":"6",
    "addr:postcode":"83000",
    "addr:street":"Rue Revel",
    "iso:country":"FR",
    "sg:address":"6, Rue Revel, 83000 Toulon",
    "sg:orig_category":"Non-Classified Establishments",
    "sg:phone":"+33 4 94 22 91 52",
    "sg:province":"Provence-Alpes-C\u00f4te d'Azur",
    "wof:name":"Projectbase Evolution S.a.r.l.",
    "wof:placetype":"venue"
},
  "geometry": {"coordinates":[5.927675,43.126534],"type":"Point"}
}