{
  "type": "Feature",
  "properties": {
    "iso:country":"FR",
    "sg:address":"B.P. 1, 82200 Malause C\u00e9dex^^ZI Laspeyres Sud, 82200 Malause",
    "sg:orig_category":"Non-Classified Establishments",
    "sg:phone":"+33 5 63 39 55 01",
    "sg:province":"Midi Pyr\u00e9n\u00e9es",
    "wof:name":"Sabla S.n.c.",
    "wof:placetype":"venue"
},
  "geometry": {"coordinates":[0.968309,44.092819],"type":"Point"}
}