{
  "type": "Feature",
  "properties": {
    "addr:full":"Zi Des Petits Carreaux 94380 Bonneuil Sur Marne Ile de France 94380",
    "addr:postcode":"94380;94380",
    "addr:street":"Des Petits Carreaux",
    "iso:country":"FR",
    "sg:address":"Zi Des Petits Carreaux 94380 Bonneuil Sur Marne",
    "sg:classifiers":[
        {
            "category":"Wholesale",
            "subcategory":"Farm Supplies",
            "type":"Manufacturing & Wholesale Goods"
        }
    ],
    "sg:phone":"+33 1 41 94 99 85",
    "sg:postcode":"94380",
    "sg:province":"Ile de France",
    "sg:tags":[
        "-",
        "machine",
        "equipment",
        "engineering",
        "machinery",
        "mechanical",
        "agriculture"
    ],
    "wof:name":"Eria",
    "wof:placetype":"venue"
},
  "geometry": {"coordinates":[2.48703,48.773804],"type":"Point"}
}