{
  "type": "Feature",
  "properties": {
    "iso:country":"FR",
    "sg:address":"rue de la Buhoterie 91160 Saulx les Chartreux",
    "sg:classifiers":[
        {
            "category":"Manufacturing",
            "subcategory":"Printing",
            "type":"Manufacturing & Wholesale Goods"
        }
    ],
    "sg:phone":"+33 1 64 48 35 80",
    "sg:postcode":"91160",
    "sg:province":"Ile de France",
    "sg:tags":[
        "house",
        "book"
    ],
    "wof:name":"Trapinex Sa",
    "wof:placetype":"venue"
},
  "geometry": {"coordinates":[2.26252,48.689129],"type":"Point"}
}