{
  "type": "Feature",
  "properties": {
    "addr:full":"68 Bd Albert Einstein 44316 Nantes Alb\u00e9 Alsace 67220",
    "addr:housenumber":"68",
    "addr:postcode":"44316;67220",
    "addr:street":"Bd Albert Einstein",
    "iso:country":"FR",
    "sg:address":"68 Bd Albert Einstein 44316 Nantes",
    "sg:city":"Alb\u00e9",
    "sg:classifiers":[
        {
            "category":"Professional",
            "subcategory":"Computer Services",
            "type":"Services"
        }
    ],
    "sg:phone":"+33 2 40 94 34 04",
    "sg:postcode":"67220",
    "sg:province":"Alsace",
    "sg:tags":[
        "information",
        "technology",
        "software"
    ],
    "wof:name":"Sep-riep",
    "wof:placetype":"venue"
},
  "geometry": {"coordinates":[-1.566619,47.262321],"type":"Point"}
}