{
  "type": "Feature",
  "properties": {
    "iso:country":"FR",
    "sg:address":"Rue De La Sabli\u00e8re 38300 Ruy",
    "sg:classifiers":[
        {
            "category":"Bakery",
            "type":"Food & Drink"
        }
    ],
    "sg:phone":"+33 4 74 43 21 55",
    "sg:postcode":"38300",
    "sg:province":"Rhone-Alpes",
    "sg:tags":[
        "cake",
        "product",
        "related",
        "bread"
    ],
    "wof:name":"Boulangerie Robert Thevenet",
    "wof:placetype":"venue"
},
  "geometry": {"coordinates":[5.30075,45.4981],"type":"Point"}
}