{
  "type": "Feature",
  "properties": {
    "addr:full":"38, Av. de Saint Gaudens, 31210 Montr\u00e9jeau Midi Pyr\u00e9n\u00e9es",
    "addr:postcode":"31210",
    "addr:street":"38 Av. De Saint Gaudens",
    "iso:country":"FR",
    "sg:address":"38, Av. de Saint Gaudens, 31210 Montr\u00e9jeau",
    "sg:orig_category":"Unclassifiable Establishments",
    "sg:phone":"+33 5 61 95 85 12",
    "sg:province":"Midi Pyr\u00e9n\u00e9es",
    "wof:name":"C.c.m. S.a.r.l. - Coma-cominges M\u00e9taux",
    "wof:placetype":"venue"
},
  "geometry": {"coordinates":[0.57618,43.087471],"type":"Point"}
}