{
  "type": "Feature",
  "properties": {
    "addr:full":"Ld Les Berg\u00e9ons 16480 Brossac Poitou-Charentes 16480",
    "addr:postcode":"16480;16480",
    "addr:street":"Ld;Brossac",
    "iso:country":"FR",
    "sg:address":"Ld Les Berg\u00e9ons 16480 Brossac",
    "sg:orig_category":"Drinks Food and Related Products Frozen food Meats and cooked meat",
    "sg:phone":"+33 5 45 98 70 27",
    "sg:postcode":"16480",
    "sg:province":"Poitou-Charentes",
    "wof:name":"Achille Bertrand Aquitaine Sarl",
    "wof:placetype":"venue"
},
  "geometry": {"coordinates":[-0.030649,45.348381],"type":"Point"}
}