{
  "type": "Feature",
  "properties": {
    "addr:full":"33, Av. de Mar\u00e9chal de Lattre de Tassigny, 94120 Fontenay sous Bois Ile de France 94120",
    "addr:postcode":"94120;94120",
    "addr:street":"33 Av. De Mare\u0301Chal De Lattre De Tassigny;Bois Ile De France",
    "iso:country":"FR",
    "sg:address":"33, Av. de Mar\u00e9chal de Lattre de Tassigny, 94120 Fontenay sous Bois",
    "sg:orig_category":"Non-Classified Establishments",
    "sg:phone":"+33 1 48 77 69 69",
    "sg:postcode":"94120",
    "sg:province":"Ile de France",
    "wof:name":"Alda Bureau S.a.r.l.",
    "wof:placetype":"venue"
},
  "geometry": {"coordinates":[2.492251,48.855625],"type":"Point"}
}