{
  "type": "Feature",
  "properties": {
    "addr:full":"111, Rue Maurice Burrus, 68160 Sainte Croix aux Mines Sainte-Croix-aux-Mines Alsace 68160",
    "addr:housenumber":"111",
    "addr:postcode":"68160;sainte-croix-aux-mines;68160",
    "addr:street":"Rue Maurice Burrus",
    "iso:country":"FR",
    "sg:address":"111, Rue Maurice Burrus, 68160 Sainte Croix aux Mines",
    "sg:city":"Sainte-Croix-aux-Mines",
    "sg:orig_category":"Unclassifiable Establishments",
    "sg:phone":"+33 3 89 58 73 24",
    "sg:postcode":"68160",
    "sg:province":"Alsace",
    "wof:name":"Kurtzemann Louis Produits Laitiers S.a.r.l.",
    "wof:placetype":"venue"
},
  "geometry": {"coordinates":[7.215736,48.258472],"type":"Point"}
}