{
  "type": "Feature",
  "properties": {
    "iso:country":"FR",
    "sg:address":"B.P. 1034, 86060 Poitiers C\u00e9dex 9^^Rue Eug\u00e8ne Chevreuil - ZI de la R\u00e9publique, 86000 Poitiers",
    "sg:orig_category":"Non-Classified Establishments",
    "sg:phone":"+33 5 49 30 08 40",
    "sg:postcode":"86000",
    "sg:province":"Poitou-Charentes",
    "wof:name":"Groupe Vinet S.a.",
    "wof:placetype":"venue"
},
  "geometry": {"coordinates":[0.34169,46.58057],"type":"Point"}
}