{
  "type": "Feature",
  "properties": {
    "iso:country":"FR",
    "sg:address":"Za De Milhartz 22800 Lanfains",
    "sg:city":"Lanfains",
    "sg:classifiers":[
        {
            "category":"Food & Beverages",
            "subcategory":"Dairy",
            "type":"Retail Goods"
        }
    ],
    "sg:phone":"+33 2 96 74 83 40",
    "sg:postcode":"22800",
    "sg:province":"Bretagne",
    "sg:tags":[
        "product",
        "related"
    ],
    "wof:name":"L'armoricaine Laitiere",
    "wof:placetype":"venue"
},
  "geometry": {"coordinates":[-2.913515,48.353207],"type":"Point"}
}