{
  "type": "Feature",
  "properties": {
    "iso:country":"FR",
    "sg:address":"Rte du Canal de Bossi\u00e8re",
    "sg:city":"Le Havre",
    "sg:orig_category":"Unclassifiable Establishments",
    "sg:phone":"+33 2 35 53 31 51",
    "sg:postcode":"76600",
    "sg:province":"Haute Normandie",
    "wof:name":"I.m.2. S.a. - Industrie M\u00e9trologie Maintenance",
    "wof:placetype":"venue"
},
  "geometry": {"coordinates":[0.188613,49.490398],"type":"Point"}
}