{
  "type": "Feature",
  "properties": {
    "iso:country":"FR",
    "sg:address":"ZAL Le Minop\u00f4le",
    "sg:city":"Bully les Mines",
    "sg:orig_category":"Unclassifiable Establishments",
    "sg:phone":"+33 3 21 44 15 15",
    "sg:postcode":"62160",
    "sg:province":"Nord Pas-de-Calais",
    "wof:name":"S.e.i.t.e.c. S.a.r.l. - Soci\u00e9t\u00e9 Etudes Installations Tuyauteries Equipements Chauffages",
    "wof:placetype":"venue"
},
  "geometry": {"coordinates":[2.717265,50.44249],"type":"Point"}
}