{
  "type": "Feature",
  "properties": {
    "addr:full":"35-39 R Chappe 63100 Clermont Ferrand Clermont-Ferrand Auvergne 63100",
    "addr:housenumber":"35-39",
    "addr:postcode":"63100;63100",
    "addr:street":"R Chappe",
    "iso:country":"FR",
    "sg:address":"35-39 R Chappe 63100 Clermont Ferrand",
    "sg:city":"Clermont-Ferrand",
    "sg:classifiers":[
        {
            "category":"Wholesale",
            "subcategory":"Machinery & Supplies",
            "type":"Manufacturing & Wholesale Goods"
        }
    ],
    "sg:phone":"+33 4 73 92 63 24",
    "sg:postcode":"63100",
    "sg:province":"Auvergne",
    "sg:tags":[
        "food",
        "processing",
        "-",
        "machine",
        "equipment",
        "engineering",
        "mechanical"
    ],
    "wof:name":"Ets Delaire Sa",
    "wof:placetype":"venue"
},
  "geometry": {"coordinates":[3.121885,45.78661],"type":"Point"}
}