{
  "type": "Feature",
  "properties": {
    "addr:full":"15, Rue Alexandre Volta, 39300 Champagnole Franche Comt\u00e9",
    "addr:housenumber":"15",
    "addr:postcode":"39300",
    "addr:street":"Rue Alexandre Volta;Franche Comte\u0301",
    "iso:country":"FR",
    "sg:address":"15, Rue Alexandre Volta, 39300 Champagnole",
    "sg:orig_category":"Non-Classified Establishments",
    "sg:phone":"+33 3 84 52 07 47",
    "sg:province":"Franche Comt\u00e9",
    "wof:name":"M\u00e9tallerie Bavoysi S.a.",
    "wof:placetype":"venue"
},
  "geometry": {"coordinates":[5.926433,46.742764],"type":"Point"}
}