{
  "type": "Feature",
  "properties": {
    "iso:country":"FR",
    "sg:address":"B.P. 534, 13400 Aubagne C\u00e9dex^^Parc de l'Angevini\u00e8re, 13400 Aubagne",
    "sg:orig_category":"Non-Classified Establishments",
    "sg:phone":"+33 4 91 19 02 00",
    "sg:province":"Centre",
    "wof:name":"Intersud Services S.a.",
    "wof:placetype":"venue"
},
  "geometry": {"coordinates":[5.521601,43.285622],"type":"Point"}
}