{
  "type": "Feature",
  "properties": {
    "addr:full":"13, Place Alphonse Fiquet - Tour Perret, 80000 Amiens Picardie",
    "addr:housenumber":"13",
    "addr:postcode":"80000",
    "addr:street":"Place Alphonse Fiquet Tour Perret",
    "iso:country":"FR",
    "sg:address":"13, Place Alphonse Fiquet - Tour Perret, 80000 Amiens",
    "sg:orig_category":"Unclassifiable Establishments",
    "sg:phone":"+33 3 22 91 78 87",
    "sg:province":"Picardie",
    "wof:name":"D.r.c.e. - Direction R\u00e9gionale Du Commerce Ext\u00e9rieur",
    "wof:placetype":"venue"
},
  "geometry": {"coordinates":[2.306379,49.891159],"type":"Point"}
}