{
  "type": "Feature",
  "properties": {
    "addr:full":"19 Rue Des Carri\u00e8res 58180 Marzy Marzy Bourgogne 58180",
    "addr:housenumber":"19",
    "addr:postcode":"58180;58180",
    "addr:street":"Rue Des Carrie\u0300Res",
    "iso:country":"FR",
    "sg:address":"19 Rue Des Carri\u00e8res 58180 Marzy",
    "sg:city":"Marzy",
    "sg:classifiers":[
        {
            "category":"Professional",
            "subcategory":"Business Services",
            "type":"Services"
        }
    ],
    "sg:phone":"+33 3 86 90 99 06",
    "sg:postcode":"58180",
    "sg:province":"Bourgogne",
    "sg:tags":[
        "training",
        "advice"
    ],
    "wof:name":"Association Formation Btp Ass",
    "wof:placetype":"venue"
},
  "geometry": {"coordinates":[3.077395,47.004559],"type":"Point"}
}