{
  "type": "Feature",
  "properties": {
    "addr:full":"Les Charmes M\u00e9n\u00e9trol 63200 M\u00e9n\u00e9trol M\u00e9n\u00e9trol Auvergne 63200",
    "addr:postcode":"63200;me\u0301ne\u0301trol;63200",
    "iso:country":"FR",
    "sg:address":"Les Charmes M\u00e9n\u00e9trol 63200 M\u00e9n\u00e9trol",
    "sg:city":"M\u00e9n\u00e9trol",
    "sg:orig_category":"Unclassifiable Establishments",
    "sg:phone":"+33 4 73 63 09 95",
    "sg:postcode":"63200",
    "sg:province":"Auvergne",
    "wof:name":"V\u00e9riferme S.a.",
    "wof:placetype":"venue"
},
  "geometry": {"coordinates":[3.052114,45.84782],"type":"Point"}
}