{
  "type": "Feature",
  "properties": {
    "iso:country":"FR",
    "sg:address":"14 rue des Reculettes 75013 Paris",
    "sg:classifiers":[
        {
            "category":"Professional",
            "subcategory":"Art Services",
            "type":"Services"
        }
    ],
    "sg:phone":"+33 1 44 08 83 40",
    "sg:postcode":"75013",
    "sg:province":"Ile de France",
    "sg:tags":[
        "graphic",
        "studio"
    ],
    "wof:name":"Visuel Design Sarl Jean Widmer",
    "wof:placetype":"venue"
},
  "geometry": {"coordinates":[2.351205,48.831783],"type":"Point"}
}