{
  "type": "Feature",
  "properties": {
    "addr:full":"34 rue de Penthi\u00e8vre 75008 Paris Ile de France 75008",
    "addr:housenumber":"34",
    "addr:postcode":"75008;75008",
    "addr:street":"Rue De Penthie\u0300Vre",
    "iso:country":"FR",
    "sg:address":"34 rue de Penthi\u00e8vre 75008 Paris",
    "sg:classifiers":[
        {
            "category":"Education",
            "subcategory":"College",
            "type":"Public Place"
        }
    ],
    "sg:phone":"+33 1 53 96 81 00",
    "sg:postcode":"75008",
    "sg:province":"Ile de France",
    "sg:tags":[
        "development",
        "manufacture",
        "cosmetic"
    ],
    "wof:name":"Copexport Sa",
    "wof:placetype":"venue"
},
  "geometry": {"coordinates":[2.313541,48.872486],"type":"Point"}
}