{
  "type": "Feature",
  "properties": {
    "addr:full":"7 Rue Flandre Dunkerque 35150 Janze Janz\u00e9 Bretagne 35150",
    "addr:housenumber":"7",
    "addr:postcode":"35150;35150",
    "addr:street":"Rue Flandre Dunkerque;Janze\u0301",
    "iso:country":"FR",
    "sg:address":"7 Rue Flandre Dunkerque 35150 Janze",
    "sg:city":"Janz\u00e9",
    "sg:classifiers":[
        {
            "category":"Food Court",
            "type":"Food & Drink"
        }
    ],
    "sg:phone":"+33 2 99 47 03 01",
    "sg:postcode":"35150",
    "sg:province":"Bretagne",
    "sg:tags":[
        "product",
        "related"
    ],
    "wof:name":"Michel Maman Services",
    "wof:placetype":"venue"
},
  "geometry": {"coordinates":[-1.504147,47.959106],"type":"Point"}
}