{
  "type": "Feature",
  "properties": {
    "iso:country":"FR",
    "sg:address":"40 Avenue De Grammont 37000 Tours",
    "sg:city":"Tours",
    "sg:classifiers":[
        {
            "category":"Professional",
            "subcategory":"Engineering",
            "type":"Services"
        }
    ],
    "sg:phone":"+33 2 47 05 43 48",
    "sg:postcode":"37000",
    "sg:province":"Centre",
    "sg:tags":[
        "machine",
        "-",
        "mechanical"
    ],
    "wof:name":"Tigre Royal Sarl",
    "wof:placetype":"venue"
},
  "geometry": {"coordinates":[0.69073,47.386261],"type":"Point"}
}