{
  "type": "Feature",
  "properties": {
    "iso:country":"FR",
    "sg:address":"La Seynie 87500 St Yrieix La Perche",
    "sg:classifiers":[
        {
            "category":"Farming",
            "subcategory":"Livestock Farm",
            "type":"Manufacturing & Wholesale Goods"
        }
    ],
    "sg:phone":"+33 5 55 08 20 82",
    "sg:postcode":"87500",
    "sg:province":"Limousin",
    "sg:tags":[
        "breeding",
        "agriculture",
        "animal"
    ],
    "wof:name":"Laredy",
    "wof:placetype":"venue"
},
  "geometry": {"coordinates":[1.219695,45.510532],"type":"Point"}
}