{
  "type": "Feature",
  "properties": {
    "iso:country":"FR",
    "sg:address":"5 R De La Dut\u00e9e 44800 St Herblain",
    "sg:classifiers":[
        {
            "category":"Autos & Motor Vehicles",
            "subcategory":"Boat Sales",
            "type":"Retail Goods"
        }
    ],
    "sg:phone":"+33 2 40 92 16 36",
    "sg:postcode":"44800",
    "sg:province":"Pays de Loire",
    "sg:tags":[
        "equipment",
        "transport"
    ],
    "wof:name":"Maucour Nantes France",
    "wof:placetype":"venue"
},
  "geometry": {"coordinates":[-1.644208,47.227722],"type":"Point"}
}