{
  "type": "Feature",
  "properties": {
    "addr:full":"Route De Grasse Marguerite Fischer 06600 Antibes Rhone-Alpes",
    "addr:postcode":"06600",
    "addr:street":"Route De Grasse Marguerite Fischer",
    "iso:country":"FR",
    "sg:address":"Route De Grasse Marguerite Fischer 06600 Antibes",
    "sg:classifiers":[
        {
            "category":"Professional",
            "subcategory":"Engineering",
            "type":"Services"
        }
    ],
    "sg:phone":"+33 4 93 33 16 19",
    "sg:province":"Rhone-Alpes",
    "sg:tags":[
        "machine",
        "-",
        "mechanical"
    ],
    "wof:name":"Utilair",
    "wof:placetype":"venue"
},
  "geometry": {"coordinates":[7.10839,43.590439],"type":"Point"}
}