{
  "type": "Feature",
  "properties": {
    "addr:full":"Ch\u00e2teau Beaumont 33460 Cussac Fort M\u00e9doc Macau Aquitaine 33460",
    "addr:postcode":"33460;33460",
    "addr:street":"Fort",
    "iso:country":"FR",
    "sg:address":"Ch\u00e2teau Beaumont 33460 Cussac Fort M\u00e9doc",
    "sg:city":"Macau",
    "sg:orig_category":"Unclassifiable Establishments",
    "sg:phone":"+33 5 56 58 92 29",
    "sg:postcode":"33460",
    "sg:province":"Aquitaine",
    "wof:name":"Ch\u00e2teau Beaumont S.c.e.a.",
    "wof:placetype":"venue"
},
  "geometry": {"coordinates":[-0.743107,45.109058],"type":"Point"}
}