{
  "type": "Feature",
  "properties": {
    "iso:country":"FR",
    "sg:address":"7, Rue Livio, 67100 Strasbourg",
    "sg:city":"Strasbourg",
    "sg:orig_category":"Non-Classified Establishments",
    "sg:phone":"+33 3 90 40 24 02",
    "sg:postcode":"67100",
    "sg:province":"Alsace",
    "wof:name":"Upat S.a.s.",
    "wof:placetype":"venue"
},
  "geometry": {"coordinates":[7.741314,48.551682],"type":"Point"}
}