{
  "type": "Feature",
  "properties": {
    "addr:full":"22, Rue Laclau, 64800 Nay Bourdettes Bourdettes Aquitaine 64800",
    "addr:housenumber":"22",
    "addr:postcode":"64800;64800",
    "addr:street":"Rue Laclau",
    "iso:country":"FR",
    "sg:address":"22, Rue Laclau, 64800 Nay Bourdettes",
    "sg:city":"Bourdettes",
    "sg:orig_category":"Non-Classified Establishments",
    "sg:phone":"+33 5 59 61 18 74",
    "sg:postcode":"64800",
    "sg:province":"Aquitaine",
    "wof:name":"Sodexma S.a.r.l.",
    "wof:placetype":"venue"
},
  "geometry": {"coordinates":[-0.252886,43.090973],"type":"Point"}
}