{
  "type": "Feature",
  "properties": {
    "iso:country":"FR",
    "sg:address":"8",
    "sg:city":"S\u00e9journ\u00e9 Cr\u00e9teil Parc 94000 Cr\u00e9teil",
    "sg:classifiers":[
        {
            "category":"Communications",
            "subcategory":"Television Station",
            "type":"Services"
        }
    ],
    "sg:phone":"+33 1 45 13 18 60",
    "sg:postcode":"94000",
    "sg:province":"Ile de France",
    "sg:tags":[
        "telecommunication",
        "instrument",
        "precision",
        "equipment",
        "optical",
        "audio-visual"
    ],
    "wof:name":"Gitzo",
    "wof:placetype":"venue"
},
  "geometry": {"coordinates":[2.455115,48.777866],"type":"Point"}
}