{
  "type": "Feature",
  "properties": {
    "addr:full":"Rue Desuert 62113 Labourse Nord Pas-de-Calais 62113",
    "addr:postcode":"62113;62113",
    "addr:street":"Rue Desuert",
    "iso:country":"FR",
    "sg:address":"Rue Desuert 62113 Labourse",
    "sg:classifiers":[
        {
            "category":"Professional",
            "subcategory":"Engineering",
            "type":"Services"
        }
    ],
    "sg:phone":"+33 3 21 64 13 38",
    "sg:postcode":"62113",
    "sg:province":"Nord Pas-de-Calais",
    "sg:tags":[
        "machine",
        "-",
        "mechanical"
    ],
    "wof:name":"Dassonneville",
    "wof:placetype":"venue"
},
  "geometry": {"coordinates":[2.683726,50.508137],"type":"Point"}
}