{
  "type": "Feature",
  "properties": {
    "iso:country":"FR",
    "sg:address":"Rte de la Gare",
    "sg:city":"Pouzauges",
    "sg:orig_category":"Unclassifiable Establishments",
    "sg:phone":"+33 2 51 66 35 35",
    "sg:postcode":"85700",
    "sg:province":"Pays de Loire",
    "wof:name":"Fleury Michon Charcuterie S.a.",
    "wof:placetype":"venue"
},
  "geometry": {"coordinates":[-0.80288,46.721252],"type":"Point"}
}