{
  "type": "Feature",
  "properties": {
    "addr:full":"B.P. 31, 33370 Artigues pr\u00e8s Bordeaux^^Place Pierre Curie, 33370 Artigues pr\u00e8s Bordeaux Artigues-pr\u00e8s-Bordeaux Aquitaine 33370",
    "addr:postcode":"33370;33370;33370",
    "addr:street":"B.P. 31;Curie",
    "iso:country":"FR",
    "sg:address":"B.P. 31, 33370 Artigues pr\u00e8s Bordeaux^^Place Pierre Curie, 33370 Artigues pr\u00e8s Bordeaux",
    "sg:city":"Artigues-pr\u00e8s-Bordeaux",
    "sg:orig_category":"Non-Classified Establishments",
    "sg:phone":"+33 5 57 77 73 77",
    "sg:postcode":"33370",
    "sg:province":"Aquitaine",
    "wof:name":"E.m.i.a. S.a.r.l. - Etudes Fabrication Et Maintenance Pour L' Industr",
    "wof:placetype":"venue"
},
  "geometry": {"coordinates":[-0.392679,44.808125],"type":"Point"}
}