{
  "type": "Feature",
  "properties": {
    "iso:country":"FR",
    "sg:address":"58220 Donzy",
    "sg:city":"Donzy",
    "sg:orig_category":"Unclassifiable Establishments",
    "sg:phone":"+33 3 86 39 58 50",
    "sg:postcode":"58220",
    "sg:province":"Bourgogne",
    "wof:name":"Soyez Fr. S.a.",
    "wof:placetype":"venue"
},
  "geometry": {"coordinates":[3.124245,47.371471],"type":"Point"}
}