{
  "type": "Feature",
  "properties": {
    "addr:full":"2 Rue Du Comte Vert Amedee Vi Le Richelieu 06300 Nice Ch\u00e9lieu Rhone-Alpes 38730",
    "addr:housenumber":"2",
    "addr:postcode":"06300;38730",
    "addr:street":"Rue Du Comte Vert Amedee Vi Le Richelieu;Rhone-Alpes",
    "iso:country":"FR",
    "sg:address":"2 Rue Du Comte Vert Amedee Vi Le Richelieu 06300 Nice",
    "sg:city":"Ch\u00e9lieu",
    "sg:classifiers":[
        {
            "category":"Utilities",
            "subcategory":"Electric",
            "type":"Services"
        }
    ],
    "sg:phone":"+33 4 93 27 09 54",
    "sg:postcode":"38730",
    "sg:province":"Rhone-Alpes",
    "sg:tags":[
        "electricity",
        "electronic",
        "electrical",
        "equipment"
    ],
    "wof:name":"Gms Telephonie",
    "wof:placetype":"venue"
},
  "geometry": {"coordinates":[7.29101,43.709393],"type":"Point"}
}