{
  "type": "Feature",
  "properties": {
    "addr:full":"128 avenue Francois Mitterand 65600 Semeac Midi Pyr\u00e9n\u00e9es 65600",
    "addr:housenumber":"128",
    "addr:postcode":"65600;65600",
    "addr:street":"Avenue Francois Mitterand",
    "iso:country":"FR",
    "sg:address":"128 avenue Francois Mitterand 65600 Semeac",
    "sg:classifiers":[
        {
            "category":"Banks & Credit Unions",
            "subcategory":"Investment Brokerage",
            "type":"Services"
        }
    ],
    "sg:phone":"+33 5 62 37 00 07",
    "sg:postcode":"65600",
    "sg:province":"Midi Pyr\u00e9n\u00e9es",
    "sg:tags":[
        "equipment",
        "material",
        "heat-shrink",
        "installation",
        "electric"
    ],
    "wof:name":"Raymi Karvan Sarl",
    "wof:placetype":"venue"
},
  "geometry": {"coordinates":[0.104531,43.221813],"type":"Point"}
}