{
  "type": "Feature",
  "properties": {
    "addr:full":"93 Rue De La Charte 68400 Riedisheim Riedisheim Alsace 68400",
    "addr:housenumber":"93",
    "addr:postcode":"68400;68400",
    "addr:street":"Rue De La Charte;Riedisheim",
    "iso:country":"FR",
    "sg:address":"93 Rue De La Charte 68400 Riedisheim",
    "sg:city":"Riedisheim",
    "sg:classifiers":[
        {
            "category":"Wholesale",
            "subcategory":"Chemicals & Plastics",
            "type":"Manufacturing & Wholesale Goods"
        }
    ],
    "sg:phone":"+33 3 89 44 70 23",
    "sg:postcode":"68400",
    "sg:province":"Alsace",
    "sg:tags":[
        "pharmaceutical",
        "energy",
        "material",
        "-",
        "raw",
        "chemistry",
        "by-product"
    ],
    "wof:name":"Bollore Energie",
    "wof:placetype":"venue"
},
  "geometry": {"coordinates":[7.370231,47.757145],"type":"Point"}
}