{
  "type": "Feature",
  "properties": {
    "iso:country":"FR",
    "sg:address":"203, Av. des Etats-Unis, 31200 Toulouse",
    "sg:orig_category":"Unclassifiable Establishments",
    "sg:phone":"+33 5 61 13 52 40",
    "sg:province":"Midi Pyr\u00e9n\u00e9es",
    "wof:name":"Boncolac S.a.",
    "wof:placetype":"venue"
},
  "geometry": {"coordinates":[1.428131,43.641773],"type":"Point"}
}