{
  "type": "Feature",
  "properties": {
    "addr:full":"Clos Novel 01300 Saint Champ Rhone-Alpes",
    "addr:postcode":"01300",
    "addr:street":"Clos Novel;Champ Rhone-Alpes",
    "iso:country":"FR",
    "sg:address":"Clos Novel 01300 Saint Champ",
    "sg:orig_category":"Unclassifiable Establishments",
    "sg:phone":"+33 4 79 42 17 79",
    "sg:province":"Rhone-Alpes",
    "wof:name":"Musso S.a.r.l.",
    "wof:placetype":"venue"
},
  "geometry": {"coordinates":[5.67735,45.734741],"type":"Point"}
}