{
  "type": "Feature",
  "properties": {
    "iso:country":"FR",
    "sg:address":"Quartier Notre Dame 06620 LE BAR SUR LOUP",
    "sg:classifiers":[
        {
            "category":"Retail",
            "subcategory":"Car Wash",
            "type":"Services"
        }
    ],
    "sg:phone":"+33 4 93 09 70 00",
    "sg:province":"Limousin",
    "sg:tags":[
        "oil",
        "essential"
    ],
    "wof:name":"V. Mane Fils Sa",
    "wof:placetype":"venue"
},
  "geometry": {"coordinates":[6.975947,43.694519],"type":"Point"}
}