{
  "type": "Feature",
  "properties": {
    "addr:full":"75 Sablaret 40230 B\u00e9nesse Maremne Aquitaine",
    "addr:housenumber":"75",
    "addr:postcode":"40230",
    "addr:street":"Sablaret",
    "iso:country":"FR",
    "sg:address":"75",
    "sg:city":"Sablaret 40230 B\u00e9nesse Maremne",
    "sg:classifiers":[
        {
            "category":"Home & Garden",
            "subcategory":"Furniture",
            "type":"Retail Goods"
        }
    ],
    "sg:phone":"+33 5 58 77 50 57",
    "sg:province":"Aquitaine",
    "sg:tags":[
        "wood"
    ],
    "wof:name":"Forestiere Nicolas",
    "wof:placetype":"venue"
},
  "geometry": {"coordinates":[-1.360134,43.62664],"type":"Point"}
}