{
  "type": "Feature",
  "properties": {
    "iso:country":"FR",
    "sg:address":"32 Rue Etampes 02400 Chierry",
    "sg:classifiers":[
        {
            "category":"Farming",
            "subcategory":"Livestock Farm",
            "type":"Manufacturing & Wholesale Goods"
        }
    ],
    "sg:phone":"+33 3 23 83 23 45",
    "sg:postcode":"02400",
    "sg:province":"Picardie",
    "sg:tags":[
        "breeding",
        "agriculture",
        "animal"
    ],
    "wof:name":"Villette Viandes",
    "wof:placetype":"venue"
},
  "geometry": {"coordinates":[3.367425,49.001549],"type":"Point"}
}