{
  "type": "Feature",
  "properties": {
    "iso:country":"FR",
    "sg:address":"24210 La Bachellerie",
    "sg:city":"La Bachellerie",
    "sg:orig_category":"Non-Classified Establishments",
    "sg:phone":"+33 5 53 50 60 11",
    "sg:postcode":"24210",
    "sg:province":"Aquitaine",
    "wof:name":"Dupuy Et Fils S.a.r.l.",
    "wof:placetype":"venue"
},
  "geometry": {"coordinates":[1.15294,45.147434],"type":"Point"}
}