{
  "type": "Feature",
  "properties": {
    "iso:country":"FR",
    "sg:address":"B.P. 109, 93123 La Courneuve C\u00e9dex^^2, Av Marcel Cachin, 93120 La Courneuve",
    "sg:orig_category":"Non-Classified Establishments",
    "sg:phone":"+33 1 49 34 40 00",
    "sg:province":"Ile de France",
    "wof:name":"Eurocopter",
    "wof:placetype":"venue"
},
  "geometry": {"coordinates":[2.3891,48.92701],"type":"Point"}
}