{
  "type": "Feature",
  "properties": {
    "addr:full":"ZI de R\u00e9melfing Sarreguemines C\u00e9dex Lorraine 57208",
    "addr:postcode":"57208",
    "addr:street":"Zi De Re\u0301Melfing",
    "iso:country":"FR",
    "sg:address":"ZI de R\u00e9melfing",
    "sg:city":"Sarreguemines C\u00e9dex",
    "sg:orig_category":"TRANSFORMATION DE TUBES",
    "sg:phone":"+33 3 87 98 35 29",
    "sg:postcode":"57208",
    "sg:province":"Lorraine",
    "wof:name":"Fey Othon S.a.",
    "wof:placetype":"venue"
},
  "geometry": {"coordinates":[7.070569,49.108246],"type":"Point"}
}