{
  "type": "Feature",
  "properties": {
    "addr:full":"B.P. 61, 01002 Bourg en Bresse C\u00e9dex^^5, Rue du Colonel Gastaldo, 01000 Bourg en Bresse Rhone-Alpes",
    "addr:postcode":"01002;01000",
    "addr:street":"B.P. 61;Rue Du Colonel Gastaldo",
    "iso:country":"FR",
    "sg:address":"B.P. 61, 01002 Bourg en Bresse C\u00e9dex^^5, Rue du Colonel Gastaldo, 01000 Bourg en Bresse",
    "sg:orig_category":"Non-Classified Establishments",
    "sg:phone":"+33 4 74 21 62 80",
    "sg:province":"Rhone-Alpes",
    "wof:name":"Vernus-desbonne S.a.r.l.",
    "wof:placetype":"venue"
},
  "geometry": {"coordinates":[5.18957,46.199814],"type":"Point"}
}