{
  "type": "Feature",
  "properties": {
    "addr:full":"8, Rue de l'industrie, 35400 Saint Malo Saint-Malo Bretagne 35400",
    "addr:housenumber":"8",
    "addr:postcode":"35400;35400",
    "addr:street":"Rue De L'Industrie;Saint-Malo",
    "iso:country":"FR",
    "sg:address":"8, Rue de l'industrie, 35400 Saint Malo",
    "sg:city":"Saint-Malo",
    "sg:orig_category":"Unclassifiable Establishments",
    "sg:phone":"+33 2 99 40 63 90",
    "sg:postcode":"35400",
    "sg:province":"Bretagne",
    "wof:name":"Cabinet D'expertise Comptable Daniel Quiniou",
    "wof:placetype":"venue"
},
  "geometry": {"coordinates":[-2.011328,48.65274],"type":"Point"}
}