{
  "type": "Feature",
  "properties": {
    "addr:full":"45, Bd de la Muette, 95140 Garges l\u00e8s Gonesse Ile de France",
    "addr:housenumber":"45",
    "addr:postcode":"95140",
    "addr:street":"Bd De La Muette",
    "iso:country":"FR",
    "sg:address":"45, Bd de la Muette, 95140 Garges l\u00e8s Gonesse",
    "sg:orig_category":"Unclassifiable Establishments",
    "sg:phone":"+33 1 39 86 06 00",
    "sg:province":"Ile de France",
    "wof:name":"Socomolec Industrie S.a.r.l.",
    "wof:placetype":"venue"
},
  "geometry": {"coordinates":[2.415217,48.976231],"type":"Point"}
}