{
  "type": "Feature",
  "properties": {
    "iso:country":"FR",
    "sg:address":"19 All D'Ath\u00e8nes 83870 Signes",
    "sg:classifiers":[
        {
            "category":"Professional",
            "subcategory":"Engineering",
            "type":"Services"
        }
    ],
    "sg:phone":"+33 4 94 88 55 00",
    "sg:tags":[
        "machine",
        "-",
        "mechanical"
    ],
    "wof:name":"International Microbio Sa",
    "wof:placetype":"venue"
},
  "geometry": {"coordinates":[5.799031,43.261028],"type":"Point"}
}