{
  "type": "Feature",
  "properties": {
    "iso:country":"FR",
    "sg:address":"33, Rue des Lilas, 75019 Paris",
    "sg:orig_category":"Non-Classified Establishments",
    "sg:phone":"+33 1 40 18 00 33",
    "sg:postcode":"75019",
    "sg:province":"Ile de France",
    "wof:name":"E.r.m.s. - S.a.r.l. - Europe Multiservices",
    "wof:placetype":"venue"
},
  "geometry": {"coordinates":[2.396336,48.879765],"type":"Point"}
}