{
  "type": "Feature",
  "properties": {
    "addr:full":"4, Av. Louis Lumi\u00e8re, 50100 Cherbourg Cherbourg-Octeville Basse Normandie 50100",
    "addr:postcode":"50100;50100",
    "addr:street":"Av. Louis Lumie\u0300Re",
    "iso:country":"FR",
    "sg:address":"4, Av. Louis Lumi\u00e8re, 50100 Cherbourg",
    "sg:city":"Cherbourg-Octeville",
    "sg:orig_category":"Unclassifiable Establishments",
    "sg:phone":"+33 2 33 88 18 00",
    "sg:postcode":"50100",
    "sg:province":"Basse Normandie",
    "wof:name":"P\u00e9pini\u00e8re D'entreprise De Cherbourg",
    "wof:placetype":"venue"
},
  "geometry": {"coordinates":[-1.616124,49.640484],"type":"Point"}
}