{
  "type": "Feature",
  "properties": {
    "addr:full":"30/32, Bd de S\u00e9bastopol, 75004 Paris Ile de France",
    "addr:housenumber":"30 / 32",
    "addr:postcode":"75004",
    "addr:street":"Bd De Se\u0301Bastopol",
    "iso:country":"FR",
    "sg:address":"30/32, Bd de S\u00e9bastopol, 75004 Paris",
    "sg:orig_category":"Non-Classified Establishments",
    "sg:phone":"+33 1 49 46 80 77",
    "sg:province":"Ile de France",
    "wof:name":"La Vie Des M\u00e9tiers S.a.",
    "wof:placetype":"venue"
},
  "geometry": {"coordinates":[2.349783,48.860958],"type":"Point"}
}