{
  "type": "Feature",
  "properties": {
    "addr:full":"Rue De L'Hautil Zac Les Boutries 78700 Conflans Ste Honorine Ile de France 78700",
    "addr:postcode":"78700;78700",
    "addr:street":"Rue De L'Hautil Zac Les Boutries;Ste Honorine Ile De France",
    "iso:country":"FR",
    "sg:address":"Rue De L'Hautil Zac Les Boutries 78700 Conflans Ste Honorine",
    "sg:classifiers":[
        {
            "category":"Health Services",
            "subcategory":"Medical Lab",
            "type":"Services"
        }
    ],
    "sg:phone":"+33 1 39 77 10 80",
    "sg:postcode":"78700",
    "sg:province":"Ile de France",
    "sg:tags":[
        "chemical",
        "pharmaceutical",
        "pharmacy"
    ],
    "wof:name":"Cooperative D'exploitation Et De Repartition Pharmaceutique",
    "wof:placetype":"venue"
},
  "geometry": {"coordinates":[2.084135,49.00668],"type":"Point"}
}