{
  "type": "Feature",
  "properties": {
    "addr:full":"8, Bd du Mar\u00e9chal Lannes, 81000 Albi Midi Pyr\u00e9n\u00e9es",
    "addr:housenumber":"8",
    "addr:postcode":"81000;midi pyre\u0301ne\u0301es",
    "addr:street":"Bd Du Mare\u0301Chal Lannes",
    "iso:country":"FR",
    "sg:address":"8, Bd du Mar\u00e9chal Lannes, 81000 Albi",
    "sg:orig_category":"Unclassifiable Establishments",
    "sg:phone":"+33 5 63 60 97 39",
    "sg:province":"Midi Pyr\u00e9n\u00e9es",
    "wof:name":"Etablissements Malrieu 81 S.a.",
    "wof:placetype":"venue"
},
  "geometry": {"coordinates":[2.150726,43.94273],"type":"Point"}
}