{
  "type": "Feature",
  "properties": {
    "iso:country":"FR",
    "sg:address":"9 Rue Maurice Daniel",
    "sg:city":"St Sebastien Sur Loire",
    "sg:classifiers":[
        {
            "category":"Banks & Credit Unions",
            "subcategory":"Financial Services",
            "type":"Services"
        }
    ],
    "sg:phone":"+33 2 40 80 54 75",
    "sg:postcode":"44230",
    "sg:province":"Pays de Loire",
    "sg:tags":[
        "banking",
        "finance",
        "insurance"
    ],
    "wof:name":"Banque Populaire Bretagne Atlantique (bpba)",
    "wof:placetype":"venue"
},
  "geometry": {"coordinates":[-1.505336,47.20702],"type":"Point"}
}