{
  "type": "Feature",
  "properties": {
    "iso:country":"FR",
    "sg:address":"35",
    "sg:city":"L\u00e9on Blum; Jeumont; 59460",
    "sg:classifiers":[
        {
            "category":"Banks & Credit Unions",
            "subcategory":"Bank",
            "type":"Services"
        }
    ],
    "sg:phone":"+33 27395077",
    "sg:postcode":"59460",
    "sg:province":"Nord Pas-de-Calais",
    "wof:name":"Banque Nationale De Paris",
    "wof:placetype":"venue"
},
  "geometry": {"coordinates":[4.092778,50.295818],"type":"Point"}
}