{
  "type": "Feature",
  "properties": {
    "addr:full":"Rue Eug\u00e9ne Pont 69004 Lyon Rhone-Alpes",
    "addr:postcode":"69004",
    "addr:street":"Rue Euge\u0301Ne Pont",
    "iso:country":"FR",
    "sg:address":"Rue Eug\u00e9ne Pont 69004 Lyon",
    "sg:classifiers":[
        {
            "category":"Manufacturing",
            "subcategory":"Printing",
            "type":"Manufacturing & Wholesale Goods"
        }
    ],
    "sg:phone":"+33 4 72 65 33 65",
    "sg:province":"Rhone-Alpes",
    "sg:tags":[
        "publishing"
    ],
    "wof:name":"Polyplan Sa",
    "wof:placetype":"venue"
},
  "geometry": {"coordinates":[4.837385,45.781715],"type":"Point"}
}