{
  "type": "Feature",
  "properties": {
    "addr:full":"77, Rue Chantereine, 08190 Asfeld Aire Champagne 08190",
    "addr:housenumber":"77",
    "addr:postcode":"08190;08190",
    "addr:street":"Rue Chantereine;Aire Champagne",
    "iso:country":"FR",
    "sg:address":"77, Rue Chantereine, 08190 Asfeld",
    "sg:city":"Aire",
    "sg:orig_category":"Unclassifiable Establishments",
    "sg:phone":"+33 3 24 72 94 16",
    "sg:postcode":"08190",
    "sg:province":"Champagne",
    "wof:name":"Marechalle S.a.",
    "wof:placetype":"venue"
},
  "geometry": {"coordinates":[4.114792,49.466438],"type":"Point"}
}