{
  "type": "Feature",
  "properties": {
    "addr:full":"Rue de la Ravaude - ZAC la Croisette Charleville M\u00e9zi\u00e8res Champagne 08000",
    "addr:postcode":"08000",
    "addr:street":"Rue De La Ravaude Zac La Croisette",
    "iso:country":"FR",
    "sg:address":"Rue de la Ravaude - ZAC la Croisette",
    "sg:city":"Charleville M\u00e9zi\u00e8res",
    "sg:orig_category":"Non-Classified Establishments",
    "sg:phone":"+33 3 24 56 20 20",
    "sg:postcode":"08000",
    "sg:province":"Champagne",
    "wof:name":"Frige Aisne - Agence Zammattio",
    "wof:placetype":"venue"
},
  "geometry": {"coordinates":[4.7174,49.758801],"type":"Point"}
}