{
  "type": "Feature",
  "properties": {
    "addr:full":"52, Av du Mal Leclerc - Zone Industrielle des Alouettes, 71300 Montceau les Mines Saint-Berain-sous-Sanvignes Bourgogne 71300",
    "addr:postcode":"71300;71300",
    "addr:street":"52 Av Du Mal Leclerc;Industrielle Des Alouettes;Bourgogne",
    "iso:country":"FR",
    "sg:address":"52, Av du Mal Leclerc - Zone Industrielle des Alouettes, 71300 Montceau les Mines",
    "sg:city":"Saint-Berain-sous-Sanvignes",
    "sg:orig_category":"Unclassifiable Establishments",
    "sg:phone":"+33 3 85 69 06 71",
    "sg:postcode":"71300",
    "sg:province":"Bourgogne",
    "wof:name":"Porc 71 S.a.",
    "wof:placetype":"venue"
},
  "geometry": {"coordinates":[4.498485,46.618446],"type":"Point"}
}