{
  "type": "Feature",
  "properties": {
    "iso:country":"FR",
    "sg:address":"6 R Du G\u00e9n\u00e9ral Lanrezac 75017 Paris",
    "sg:classifiers":[
        {
            "category":"Travel",
            "subcategory":"Hotels & Motels",
            "type":"Entertainment"
        }
    ],
    "sg:phone":"+33 1 43 80 30 50",
    "sg:postcode":"75017",
    "sg:province":"Ile de France",
    "sg:tags":[
        "hotels",
        "business",
        "restaurant"
    ],
    "wof:name":"Hotel Balmoral",
    "wof:placetype":"venue"
},
  "geometry": {"coordinates":[2.293973,48.875973],"type":"Point"}
}