{
  "type": "Feature",
  "properties": {
    "addr:full":"zi Rousset av Villevieille 13790 Rousset Vill\u00e9 Alsace 67220",
    "addr:postcode":"13790;67220",
    "addr:street":"Av Villevieille",
    "iso:country":"FR",
    "sg:address":"zi Rousset av Villevieille 13790 Rousset",
    "sg:city":"Vill\u00e9",
    "sg:classifiers":[
        {
            "category":"Utilities",
            "subcategory":"Cable",
            "type":"Services"
        }
    ],
    "sg:phone":"+33 4 42 29 19 99",
    "sg:postcode":"67220",
    "sg:province":"Alsace",
    "sg:tags":[
        "machine",
        "industry",
        "special"
    ],
    "wof:name":"Fluidair S.a.",
    "wof:placetype":"venue"
},
  "geometry": {"coordinates":[5.621815,43.479946],"type":"Point"}
}