{
  "type": "Feature",
  "properties": {
    "addr:full":"B.P. 18, 74801 La Roche sur Foron C\u00e9dex^^Parc des Expositions, 74800 La Roche sur Foron Rhone-Alpes",
    "addr:housenumber":"74801",
    "addr:postcode":"74800",
    "addr:street":"B.P. 18",
    "iso:country":"FR",
    "sg:address":"B.P. 18, 74801 La Roche sur Foron C\u00e9dex^^Parc des Expositions, 74800 La Roche sur Foron",
    "sg:orig_category":"Non-Classified Establishments",
    "sg:phone":"+33 4 50 03 03 37",
    "sg:province":"Rhone-Alpes",
    "wof:name":"Foire De La Haute Savoie Mont Blanc",
    "wof:placetype":"venue"
},
  "geometry": {"coordinates":[6.357741,46.047504],"type":"Point"}
}