{
  "type": "Feature",
  "properties": {
    "addr:full":"22 rue Saint Desir\u00e9; Lons le Saunier; 39000 Franche Comt\u00e9 39000",
    "addr:housenumber":"22",
    "addr:postcode":"39000;39000",
    "addr:street":"Rue Saint Desire\u0301;Franche Comte\u0301",
    "iso:country":"FR",
    "sg:address":"22 rue Saint Desir\u00e9; Lons le Saunier; 39000",
    "sg:classifiers":[
        {
            "category":"Banks & Credit Unions",
            "subcategory":"Bank",
            "type":"Services"
        }
    ],
    "sg:phone":"+33 3384240725",
    "sg:postcode":"39000",
    "sg:province":"Franche Comt\u00e9",
    "wof:name":"Banque Nationale De Paris",
    "wof:placetype":"venue"
},
  "geometry": {"coordinates":[5.551163,46.673431],"type":"Point"}
}