{
  "type": "Feature",
  "properties": {
    "addr:full":"87 route de Seurre 21910 CORCELLES LES CITEAUX Barges Bourgogne 21910",
    "addr:housenumber":"87",
    "addr:postcode":"21910;21910",
    "addr:street":"Route De Seurre",
    "iso:country":"FR",
    "sg:address":"87 route de Seurre 21910 CORCELLES LES CITEAUX",
    "sg:city":"Barges",
    "sg:classifiers":[
        {
            "category":"Shopping",
            "subcategory":"Stationery & Office Supplies",
            "type":"Retail Goods"
        }
    ],
    "sg:phone":"+33 3 80 70 71 00",
    "sg:postcode":"21910",
    "sg:province":"Bourgogne",
    "sg:tags":[
        "packaging",
        "material"
    ],
    "wof:name":"Cermex S.a.",
    "wof:placetype":"venue"
},
  "geometry": {"coordinates":[5.08282,47.166023],"type":"Point"}
}