{
  "type": "Feature",
  "properties": {
    "iso:country":"FR",
    "sg:address":"Rue Hippolyte Monteil - Lev\u00e9e de la Rochepinard",
    "sg:city":"Saint Pierre des Corps",
    "sg:orig_category":"Unclassifiable Establishments",
    "sg:phone":"+33 2 47 63 23 23",
    "sg:postcode":"37700",
    "sg:province":"Centre",
    "wof:name":"Manuli Sonatra S.a.",
    "wof:placetype":"venue"
},
  "geometry": {"coordinates":[0.721319,47.382225],"type":"Point"}
}