{
  "type": "Feature",
  "properties": {
    "addr:full":"10, Rue Daguerre - Zone Industrielle, 21300 Chen\u00f4ve Chen\u00f4ve Bourgogne 21300",
    "addr:housenumber":"10",
    "addr:postcode":"21300;21300",
    "addr:street":"Rue Daguerre Zone Industrielle",
    "iso:country":"FR",
    "sg:address":"10, Rue Daguerre - Zone Industrielle, 21300 Chen\u00f4ve",
    "sg:city":"Chen\u00f4ve",
    "sg:orig_category":"Non-Classified Establishments",
    "sg:phone":"+33 3 80 52 37 34",
    "sg:postcode":"21300",
    "sg:province":"Bourgogne",
    "wof:name":"S.n.j.b. S.a.r.l.",
    "wof:placetype":"venue"
},
  "geometry": {"coordinates":[5.004665,47.294296],"type":"Point"}
}