{
  "type": "Feature",
  "properties": {
    "addr:full":"10, Rue de la Gi\u00e8ze, 50410 Percy Percy Basse Normandie 50410",
    "addr:housenumber":"10",
    "addr:postcode":"50410;50410",
    "addr:street":"Rue De La Gie\u0300Ze;Percy Basse",
    "iso:country":"FR",
    "sg:address":"10, Rue de la Gi\u00e8ze, 50410 Percy",
    "sg:city":"Percy",
    "sg:orig_category":"Unclassifiable Establishments",
    "sg:phone":"+33 2 33 61 17 69",
    "sg:postcode":"50410",
    "sg:province":"Basse Normandie",
    "wof:name":"M.p.g.p. S.a.r.l. - M\u00e9canique De Pr\u00e9cision G\u00e9n\u00e9rale De Percy",
    "wof:placetype":"venue"
},
  "geometry": {"coordinates":[-1.182802,48.914982],"type":"Point"}
}