{
  "type": "Feature",
  "properties": {
    "iso:country":"FR",
    "sg:address":"B.P. 39, 89301 Joigny C\u00e9dex^^3, Rue des Entrepreneurs, 89300 Joigny",
    "sg:city":"Joigny",
    "sg:orig_category":"Non-Classified Establishments",
    "sg:phone":"+33 3 86 92 18 18",
    "sg:postcode":"89300",
    "sg:province":"Bourgogne",
    "wof:name":"Simel S.a.r.l.",
    "wof:placetype":"venue"
},
  "geometry": {"coordinates":[3.399532,47.9809],"type":"Point"}
}