{
  "type": "Feature",
  "properties": {
    "addr:full":"27, Rue Paillon, 42000 Saint Etienne Rhone-Alpes",
    "addr:housenumber":"27",
    "addr:postcode":"42000",
    "addr:street":"Rue Paillon",
    "iso:country":"FR",
    "sg:address":"27, Rue Paillon, 42000 Saint Etienne",
    "sg:orig_category":"Unclassifiable Establishments",
    "sg:phone":"+33 4 77 33 23 98",
    "sg:province":"Rhone-Alpes",
    "wof:name":"Comarane France S.a.r.l.",
    "wof:placetype":"venue"
},
  "geometry": {"coordinates":[4.379014,45.431377],"type":"Point"}
}