{
  "type": "Feature",
  "properties": {
    "addr:full":"Rte Mesnois Thuron 39130 Mesnois Franche Comt\u00e9 39130",
    "addr:postcode":"39130;39130",
    "addr:street":"Rte Mesnois Thuron;Franche Comte\u0301",
    "iso:country":"FR",
    "sg:address":"Rte Mesnois Thuron 39130 Mesnois",
    "sg:classifiers":[
        {
            "category":"Manufacturing",
            "subcategory":"Metals",
            "type":"Manufacturing & Wholesale Goods"
        }
    ],
    "sg:phone":"+33 3 84 48 39 69",
    "sg:postcode":"39130",
    "sg:province":"Franche Comt\u00e9",
    "sg:tags":[
        "metallurgy",
        "metalworking",
        "processing"
    ],
    "wof:name":"Techniforms Sodex Ets Picod Robert Sarl",
    "wof:placetype":"venue"
},
  "geometry": {"coordinates":[5.748384,46.57431],"type":"Point"}
}