{
  "type": "Feature",
  "properties": {
    "addr:full":"All\u00e9e Paul Avon Le Teil Rhone-Alpes 07400",
    "addr:postcode":"07400",
    "addr:street":"Alle\u0301E Paul Avon",
    "iso:country":"FR",
    "sg:address":"All\u00e9e Paul Avon",
    "sg:city":"Le Teil",
    "sg:orig_category":"Unclassifiable Establishments",
    "sg:phone":"+33 4 75 52 15 40",
    "sg:postcode":"07400",
    "sg:province":"Rhone-Alpes",
    "wof:name":"Delta Electricit\u00e9 S.a.r.l.",
    "wof:placetype":"venue"
},
  "geometry": {"coordinates":[4.689375,44.551109],"type":"Point"}
}