{
  "type": "Feature",
  "properties": {
    "addr:full":"8, Rue Pierre D\u00e9chanet - Zone Industrielle, 25300 Pontarlier Franche Comt\u00e9",
    "addr:housenumber":"8",
    "addr:postcode":"25300",
    "addr:street":"Rue Pierre De\u0301Chanet Zone Industrielle;Franche Comte\u0301",
    "iso:country":"FR",
    "sg:address":"8, Rue Pierre D\u00e9chanet - Zone Industrielle, 25300 Pontarlier",
    "sg:orig_category":"Unclassifiable Establishments",
    "sg:phone":"+33 3 81 69 87 87",
    "sg:province":"Franche Comt\u00e9",
    "wof:name":"Parker Hannifin S.a.",
    "wof:placetype":"venue"
},
  "geometry": {"coordinates":[6.40966,46.833256],"type":"Point"}
}