{
  "type": "Feature",
  "properties": {
    "iso:country":"FR",
    "sg:address":"28, Rue Diderot, 92170 Vanves",
    "sg:orig_category":"Non-Classified Establishments",
    "sg:phone":"+33 1 46 44 52 03",
    "sg:province":"Ile de France",
    "wof:name":"S.t.r.v. S.a. - Soci\u00e9t\u00e9 Des Transports Roblet Et Vallot",
    "wof:placetype":"venue"
},
  "geometry": {"coordinates":[2.288026,48.817467],"type":"Point"}
}