{
  "type": "Feature",
  "properties": {
    "addr:full":"16 Rue Auguste Gautier 49100 Angers Pays de Loire 49100",
    "addr:housenumber":"16",
    "addr:postcode":"49100;49100",
    "addr:street":"Rue Auguste Gautier",
    "iso:country":"FR",
    "sg:address":"16 Rue Auguste Gautier 49100 Angers",
    "sg:classifiers":[
        {
            "category":"Wholesale",
            "subcategory":"Medical Equipment & Supplies",
            "type":"Manufacturing & Wholesale Goods"
        }
    ],
    "sg:phone":"+33 2 41 25 33 50",
    "sg:postcode":"49100",
    "sg:province":"Pays de Loire",
    "sg:tags":[
        "instrument",
        "health",
        "-",
        "precision"
    ],
    "wof:name":"Alternat Sa",
    "wof:placetype":"venue"
},
  "geometry": {"coordinates":[-0.561023,47.464607],"type":"Point"}
}