{
  "type": "Feature",
  "properties": {
    "iso:country":"FR",
    "sg:address":"4 Av Jacques Cartier Immeuble Le Sextant 44800 St Herblain",
    "sg:classifiers":[
        {
            "category":"Professional",
            "subcategory":"Computer Services",
            "type":"Services"
        }
    ],
    "sg:phone":"+33 2 40 92 19 18",
    "sg:postcode":"44800",
    "sg:province":"Pays de Loire",
    "sg:tags":[
        "information",
        "technology",
        "software"
    ],
    "wof:name":"Service Informatique Logiciel Materiel Maintenance (silmm)",
    "wof:placetype":"venue"
},
  "geometry": {"coordinates":[-1.633467,47.223141],"type":"Point"}
}