{
  "type": "Feature",
  "properties": {
    "addr:full":"23, Rue Maryse Basti\u00e9, 69500 Bron Rhone-Alpes 69500",
    "addr:housenumber":"23",
    "addr:postcode":"69500;69500",
    "addr:street":"Rue Maryse Bastie\u0301",
    "iso:country":"FR",
    "sg:address":"23, Rue Maryse Basti\u00e9, 69500 Bron",
    "sg:orig_category":"Unclassifiable Establishments",
    "sg:phone":"+33 4 78 41 28 00",
    "sg:postcode":"69500",
    "sg:province":"Rhone-Alpes",
    "wof:name":"G.f.c.",
    "wof:placetype":"venue"
},
  "geometry": {"coordinates":[4.92339,45.72662],"type":"Point"}
}