{
  "type": "Feature",
  "properties": {
    "addr:full":"2 rue des H\u00eatres 78190 Trappes Ile de France",
    "addr:housenumber":"2",
    "addr:postcode":"78190;ile",
    "addr:street":"Rue Des He\u0302Tres",
    "iso:country":"FR",
    "sg:address":"2 rue des H\u00eatres 78190 Trappes",
    "sg:classifiers":[
        {
            "category":"Manufacturing",
            "subcategory":"Rubber & Plastics",
            "type":"Manufacturing & Wholesale Goods"
        }
    ],
    "sg:phone":"+33 1 30 13 80 00",
    "sg:province":"Ile de France",
    "sg:tags":[
        "material"
    ],
    "wof:name":"Hellermann-france Sa",
    "wof:placetype":"venue"
},
  "geometry": {"coordinates":[2.007453,48.769936],"type":"Point"}
}