{
  "type": "Feature",
  "properties": {
    "iso:country":"FR",
    "sg:address":"30 Rue De Meaux 60300 Senlis",
    "sg:classifiers":[
        {
            "category":"Professional",
            "subcategory":"Business Services",
            "type":"Services"
        }
    ],
    "sg:phone":"+33 3 44 53 96 40",
    "sg:postcode":"60300",
    "sg:province":"Picardie",
    "sg:tags":[
        "training",
        "advice"
    ],
    "wof:name":"Lycee Prive St Vincent",
    "wof:placetype":"venue"
},
  "geometry": {"coordinates":[2.588584,49.203362],"type":"Point"}
}