{
  "type": "Feature",
  "properties": {
    "iso:country":"FR",
    "sg:address":"RN 7 - Le Pigeonnier",
    "sg:city":"le Pontet",
    "sg:orig_category":"Unclassifiable Establishments",
    "sg:phone":"+33 4 90 32 42 91",
    "sg:postcode":"84130",
    "sg:province":"Provence-Alpes-C\u00f4te d'Azur",
    "wof:name":"Les Agassins",
    "wof:placetype":"venue"
},
  "geometry": {"coordinates":[4.859935,43.96188],"type":"Point"}
}