{
  "type": "Feature",
  "properties": {
    "iso:country":"FR",
    "sg:address":"15, Rue des Bas Tr\u00e9vois, 10000 Troyes",
    "sg:orig_category":"Unclassifiable Establishments",
    "sg:phone":"+33 3 25 83 12 22",
    "sg:province":"Champagne",
    "wof:name":"Teinturerie Des Bas Tr\u00e9vois S.a.",
    "wof:placetype":"venue"
},
  "geometry": {"coordinates":[4.081701,48.291103],"type":"Point"}
}