{
  "type": "Feature",
  "properties": {
    "iso:country":"FR",
    "sg:address":"route de Villeneuve 34500 BEZIERS",
    "sg:classifiers":[
        {
            "category":"Retail",
            "subcategory":"Auto Repair",
            "type":"Services"
        }
    ],
    "sg:phone":"+33 4 67 11 84 00",
    "sg:province":"Languedoc-Roussillon",
    "sg:tags":[
        "railway",
        "carriage"
    ],
    "wof:name":"A.c.v. Industrie Sa",
    "wof:placetype":"venue"
},
  "geometry": {"coordinates":[3.205515,43.351227],"type":"Point"}
}