{
  "type": "Feature",
  "properties": {
    "iso:country":"FR",
    "sg:address":"ZI des Pr\u00e9s Roseaux",
    "sg:city":"Villers Saint Paul",
    "sg:orig_category":"Unclassifiable Establishments",
    "sg:phone":"+33 3 44 66 30 80",
    "sg:postcode":"60870",
    "sg:province":"Picardie",
    "wof:name":"C.m.o. S.a. - Caoutchouc Manufacture De L'oise",
    "wof:placetype":"venue"
},
  "geometry": {"coordinates":[2.487537,49.288544],"type":"Point"}
}