{
  "type": "Feature",
  "properties": {
    "iso:country":"FR",
    "sg:address":"11, Av du Mal Foch, 68100 Mulhouse",
    "sg:city":"Mulhouse",
    "sg:orig_category":"Non-Classified Establishments",
    "sg:phone":"+33 3 89 66 14 14",
    "sg:postcode":"68100",
    "sg:province":"Alsace",
    "wof:name":"Actua S.a.",
    "wof:placetype":"venue"
},
  "geometry": {"coordinates":[7.341839,47.745186],"type":"Point"}
}