{
  "type": "Feature",
  "properties": {
    "iso:country":"FR",
    "sg:address":"61, Rte Jean Briand - Le Tertiopole, 33700 M\u00e9rignac",
    "sg:city":"M\u00e9rignac",
    "sg:orig_category":"Unclassifiable Establishments",
    "sg:phone":"+33 5 57 92 11 11",
    "sg:postcode":"33700",
    "sg:province":"Aquitaine",
    "wof:name":"Supporter Sud-ouest",
    "wof:placetype":"venue"
},
  "geometry": {"coordinates":[-0.64762,44.841808],"type":"Point"}
}