{
  "type": "Feature",
  "properties": {
    "addr:full":"16 Rue Gay Lussac 33695 Merignac Cedex Champagne",
    "addr:housenumber":"16",
    "addr:postcode":"33695 merignac cedex",
    "addr:street":"Rue Gay Lussac",
    "iso:country":"FR",
    "sg:address":"16 Rue Gay Lussac 33695 Merignac Cedex",
    "sg:classifiers":[
        {
            "category":"Manufacturing",
            "subcategory":"Printing",
            "type":"Manufacturing & Wholesale Goods"
        }
    ],
    "sg:phone":"+33 5 56 34 39 95",
    "sg:province":"Champagne",
    "sg:tags":[
        "publishing"
    ],
    "wof:name":"Wetterwald Lacoste",
    "wof:placetype":"venue"
},
  "geometry": {"coordinates":[-0.680159,44.849415],"type":"Point"}
}