{
  "type": "Feature",
  "properties": {
    "addr:full":"159, Bd Pierre et Marie Curie, 44150 Ancenis Pays de Loire",
    "addr:housenumber":"159",
    "addr:postcode":"44150",
    "addr:street":"Bd Pierre Et Marie Curie",
    "iso:country":"FR",
    "sg:address":"159, Bd Pierre et Marie Curie, 44150 Ancenis",
    "sg:orig_category":"Unclassifiable Establishments",
    "sg:phone":"+33 2 40 83 04 13",
    "sg:province":"Pays de Loire",
    "wof:name":"Entreprise De Couverture Pineau E.u.r.l.",
    "wof:placetype":"venue"
},
  "geometry": {"coordinates":[-1.179869,47.377296],"type":"Point"}
}