{
  "type": "Feature",
  "properties": {
    "addr:full":"Lamadeleine 46100 Figeac Midi Pyr\u00e9n\u00e9es 46100",
    "addr:postcode":"46100;46100",
    "addr:street":"Lamadeleine",
    "iso:country":"FR",
    "sg:address":"Lamadeleine 46100 Figeac",
    "sg:classifiers":[
        {
            "category":"Manufacturing",
            "subcategory":"Metals",
            "type":"Manufacturing & Wholesale Goods"
        }
    ],
    "sg:phone":"+33 5 65 34 68 45",
    "sg:postcode":"46100",
    "sg:province":"Midi Pyr\u00e9n\u00e9es",
    "sg:tags":[
        "-",
        "machine",
        "equipment",
        "engineering",
        "machinery",
        "mechanical"
    ],
    "wof:name":"Systeme Sud-ouest Sa",
    "wof:placetype":"venue"
},
  "geometry": {"coordinates":[2.024565,44.560276],"type":"Point"}
}