{
  "type": "Feature",
  "properties": {
    "iso:country":"FR",
    "sg:address":"B.P. 10429, 95707 Roissy Charles de Gaulle C\u00e9dex^^Rue du Chapelier - Zone de fr\u00eat 4 - B\u00e2t. 3404, 957",
    "sg:orig_category":"Non-Classified Establishments",
    "sg:phone":"+33 1 48 16 51 60",
    "sg:province":"Picardie",
    "wof:name":"Lemoine Perignon A.p.s. S.a.",
    "wof:placetype":"venue"
},
  "geometry": {"coordinates":[121.531891,25.066339],"type":"Point"}
}