{
  "type": "Feature",
  "properties": {
    "iso:country":"FR",
    "sg:address":"7, Rue des Trois Rois, 50300 Avranches",
    "sg:city":"Avranches",
    "sg:orig_category":"Unclassifiable Establishments",
    "sg:phone":"+33 2 33 58 23 99",
    "sg:postcode":"50300",
    "sg:province":"Basse Normandie",
    "wof:name":"Batel S.a.r.l.",
    "wof:placetype":"venue"
},
  "geometry": {"coordinates":[-1.359604,48.68655],"type":"Point"}
}