{
  "type": "Feature",
  "properties": {
    "addr:full":"175 chemin de la Madrague Ville 13002 Marseille Vill\u00e9 Alsace 67220",
    "addr:housenumber":"175",
    "addr:postcode":"13002;67220",
    "addr:street":"Chemin De La Madrague Ville",
    "iso:country":"FR",
    "sg:address":"175 chemin de la Madrague Ville 13002 Marseille",
    "sg:city":"Vill\u00e9",
    "sg:classifiers":[
        {
            "category":"Sports & Exercise",
            "subcategory":"Sports Center",
            "type":"Entertainment"
        }
    ],
    "sg:phone":"+33 4 91 58 50 26",
    "sg:postcode":"67220",
    "sg:province":"Alsace",
    "sg:tags":[
        "billiards",
        "accessory"
    ],
    "wof:name":"Billards Gomez Entreprise Ferrari & Cie",
    "wof:placetype":"venue"
},
  "geometry": {"coordinates":[5.358942,43.328789],"type":"Point"}
}