{
  "type": "Feature",
  "properties": {
    "iso:country":"FR",
    "sg:address":"106, Av. Tolosane, 31520 Ramonville Saint Agne",
    "sg:orig_category":"Unclassifiable Establishments",
    "sg:phone":"+33 5 62 19 08 90",
    "sg:province":"Midi Pyr\u00e9n\u00e9es",
    "wof:name":"Interface Ing\u00e9nierie Informatique S.a.",
    "wof:placetype":"venue"
},
  "geometry": {"coordinates":[1.481077,43.538261],"type":"Point"}
}