{
  "type": "Feature",
  "properties": {
    "addr:full":"Bourg De Landrevarzec 29510 LANDREVARZEC Landr\u00e9varzec Bretagne 29510",
    "addr:postcode":"29510;29510",
    "addr:street":"Bourg;Landre\u0301Varzec",
    "iso:country":"FR",
    "sg:address":"Bourg De Landrevarzec 29510 LANDREVARZEC",
    "sg:city":"Landr\u00e9varzec",
    "sg:classifiers":[
        {
            "category":"Food & Beverages",
            "subcategory":"Meat & Fish",
            "type":"Retail Goods"
        }
    ],
    "sg:phone":"+33 2 98 57 91 22",
    "sg:postcode":"29510",
    "sg:province":"Bretagne",
    "sg:tags":[
        "fresh"
    ],
    "wof:name":"Etablissements Guyader Sa",
    "wof:placetype":"venue"
},
  "geometry": {"coordinates":[-3.977899,48.062744],"type":"Point"}
}