{
  "type": "Feature",
  "properties": {
    "iso:country":"FR",
    "sg:address":"2 Av Le Verrier Zi Les Bruy\u00e8res Lot 5 78190 Trappes",
    "sg:classifiers":[
        {
            "category":"Wholesale",
            "subcategory":"Machinery & Supplies",
            "type":"Manufacturing & Wholesale Goods"
        }
    ],
    "sg:phone":"+33 1 30 13 81 81",
    "sg:postcode":"78190",
    "sg:province":"Ile de France",
    "sg:tags":[
        "equipment",
        "-",
        "precision",
        "glass",
        "optical",
        "health",
        "instrument"
    ],
    "wof:name":"Les Opticiens Economes (loe) La Generale D Optique",
    "wof:placetype":"venue"
},
  "geometry": {"coordinates":[1.999285,48.774651],"type":"Point"}
}