{
  "type": "Feature",
  "properties": {
    "addr:full":"B.P. 405, 03004 Moulins C\u00e9dex^^19, Rue Delorme, 03000 Moulins Moulins Auvergne 03000",
    "addr:housenumber":"b.p. 405",
    "addr:postcode":"03004;03000;03000",
    "addr:street":"Rue Delorme",
    "iso:country":"FR",
    "sg:address":"B.P. 405, 03004 Moulins C\u00e9dex^^19, Rue Delorme, 03000 Moulins",
    "sg:city":"Moulins",
    "sg:orig_category":"Non-Classified Establishments",
    "sg:phone":"+33 4 70 46 95 46",
    "sg:postcode":"03000",
    "sg:province":"Auvergne",
    "wof:name":"O.r.e.c.a. S.a. - Organisation R\u00e9vision Expertise Comptable Audit",
    "wof:placetype":"venue"
},
  "geometry": {"coordinates":[3.30848,46.5658],"type":"Point"}
}