{
  "type": "Feature",
  "properties": {
    "iso:country":"FR",
    "sg:address":"ZI du Pont Noget 85200 Fontenay le Comte",
    "sg:classifiers":[
        {
            "category":"Autos & Motor Vehicles",
            "subcategory":"Auto Supplies",
            "type":"Retail Goods"
        }
    ],
    "sg:phone":"+33 2 51 53 12 13",
    "sg:postcode":"85200",
    "sg:province":"Pays de Loire",
    "sg:tags":[
        "body",
        "car",
        "truck",
        "trailer",
        "superstructure"
    ],
    "wof:name":"Seg Samro Sa",
    "wof:placetype":"venue"
},
  "geometry": {"coordinates":[-0.802274,46.464867],"type":"Point"}
}