{
  "type": "Feature",
  "properties": {
    "iso:country":"FR",
    "sg:address":"B.P. 190, 33503 Libourne C\u00e9dex^^Rte du Milieu - M\u00e8de , 33330 Saint Emilion",
    "sg:city":"Saint-\u00c9tienne-de-Lisse",
    "sg:orig_category":"Non-Classified Establishments",
    "sg:phone":"+33 5 57 55 58 00",
    "sg:postcode":"33330",
    "sg:province":"Aquitaine",
    "wof:name":"Antoine Moueix Et Leb\u00e8gue S.a.",
    "wof:placetype":"venue"
},
  "geometry": {"coordinates":[-0.148079,44.848289],"type":"Point"}
}