{
  "type": "Feature",
  "properties": {
    "addr:full":"208, Rue de Rivoli, 75001 Paris Ile de France 75001",
    "addr:housenumber":"208",
    "addr:postcode":"75001;75001",
    "addr:street":"Rue De Rivoli",
    "iso:country":"FR",
    "sg:address":"208, Rue de Rivoli, 75001 Paris",
    "sg:orig_category":"Non-Classified Establishments",
    "sg:phone":"+33 1 42 86 11 11",
    "sg:postcode":"75001",
    "sg:province":"Ile de France",
    "wof:name":"Answering Service S.a.r.l.",
    "wof:placetype":"venue"
},
  "geometry": {"coordinates":[2.330229,48.864384],"type":"Point"}
}