{
  "type": "Feature",
  "properties": {
    "iso:country":"FR",
    "sg:address":"B.P. 4, 51530 Pierry^^48, Rue L\u00e9on Bourgeois, 51530 Pierry",
    "sg:orig_category":"Non-Classified Establishments",
    "sg:phone":"+33 3 26 54 03 05",
    "sg:province":"Centre",
    "wof:name":"Champagne Vollereaux S.a.",
    "wof:placetype":"venue"
},
  "geometry": {"coordinates":[3.93405,49.05574],"type":"Point"}
}