{
  "type": "Feature",
  "properties": {
    "addr:full":"B.P. 80, 51432 Tinqueux C\u00e9dex^^9, Rue Pierre Salmon, 51430 Bezannes Champagne",
    "addr:postcode":"51432;51430",
    "addr:street":"B.P. 80;Rue Pierre Salmon",
    "iso:country":"FR",
    "sg:address":"B.P. 80, 51432 Tinqueux C\u00e9dex^^9, Rue Pierre Salmon, 51430 Bezannes",
    "sg:orig_category":"Non-Classified Establishments",
    "sg:phone":"+33 3 26 50 32 70",
    "sg:province":"Champagne",
    "wof:name":"Sollier Soudure S.a.r.l.",
    "wof:placetype":"venue"
},
  "geometry": {"coordinates":[3.989495,49.250576],"type":"Point"}
}