{
  "type": "Feature",
  "properties": {
    "addr:full":"Kaergantic 56270 Ploemeur Ploemeur Bretagne 56270",
    "addr:postcode":"56270;56270",
    "addr:street":"Kaergantic",
    "iso:country":"FR",
    "sg:address":"Kaergantic 56270 Ploemeur",
    "sg:city":"Ploemeur",
    "sg:orig_category":"Raw Clay",
    "sg:phone":"+33 2 97 86 16 16",
    "sg:postcode":"56270",
    "sg:province":"Bretagne",
    "wof:name":"Denain Anzin Min\u00e9raux Kaolins De Ploemeur Sa",
    "wof:placetype":"venue"
},
  "geometry": {"coordinates":[-3.459337,47.732822],"type":"Point"}
}