{
  "type": "Feature",
  "properties": {
    "addr:full":"Rue Ren\u00e9 Lassin - Immeuble Le Mazi\u00e8re Evry C\u00e9dex Haute Normandie 91033",
    "addr:postcode":"91033",
    "addr:street":"Rue Rene\u0301 Lassin Immeuble Le Mazie\u0300Re;Normandie",
    "iso:country":"FR",
    "sg:address":"Rue Ren\u00e9 Lassin - Immeuble Le Mazi\u00e8re",
    "sg:city":"Evry C\u00e9dex",
    "sg:orig_category":"Non-Classified Establishments",
    "sg:phone":"+33 1 60 91 86 86",
    "sg:postcode":"91033",
    "sg:province":"Haute Normandie",
    "wof:name":"Apave Parisienne",
    "wof:placetype":"venue"
},
  "geometry": {"coordinates":[2.431646,48.629627],"type":"Point"}
}