{
  "type": "Feature",
  "properties": {
    "iso:country":"FR",
    "sg:address":"2, Rue de l'Eglise, 10440 Torvilliers",
    "sg:orig_category":"Unclassifiable Establishments",
    "sg:phone":"+33 3 25 74 25 39",
    "sg:province":"Champagne",
    "wof:name":"A.b. Marketing E.u.r.l.",
    "wof:placetype":"venue"
},
  "geometry": {"coordinates":[3.980985,48.2757],"type":"Point"}
}