{
  "type": "Feature",
  "properties": {
    "iso:country":"FR",
    "sg:address":"Domaine du Crampilh 64350 AURIONS IDERNES",
    "sg:city":"Anoye",
    "sg:classifiers":[
        {
            "category":"Wholesale",
            "subcategory":"Wine & Distilled Alcoholic Beverages",
            "type":"Manufacturing & Wholesale Goods"
        }
    ],
    "sg:phone":"+33 5 59 04 00 63",
    "sg:postcode":"64350",
    "sg:province":"Aquitaine",
    "sg:tags":[
        "french"
    ],
    "wof:name":"Domaine Du Crampilh Sc",
    "wof:placetype":"venue"
},
  "geometry": {"coordinates":[-0.135316,43.544422],"type":"Point"}
}