{
  "type": "Feature",
  "properties": {
    "addr:full":"23800 Colondannes Limousin",
    "addr:postcode":"23800",
    "iso:country":"FR",
    "sg:address":"23800 Colondannes",
    "sg:orig_category":"Unclassifiable Establishments",
    "sg:phone":"+33 5 55 89 00 85",
    "sg:province":"Limousin",
    "wof:name":"Etablissements Chaput L. S.a.r.l.",
    "wof:placetype":"venue"
},
  "geometry": {"coordinates":[1.611745,46.289204],"type":"Point"}
}