{
  "type": "Feature",
  "properties": {
    "addr:full":"Rue Claude Monet D\u00e9cines Charpieu Rhone-Alpes 69150",
    "addr:postcode":"69150",
    "addr:street":"Rue Claude Monet;Rhone-Alpes",
    "iso:country":"FR",
    "sg:address":"Rue Claude Monet",
    "sg:city":"D\u00e9cines Charpieu",
    "sg:orig_category":"Unclassifiable Establishments",
    "sg:phone":"+33 4 78 49 02 37",
    "sg:postcode":"69150",
    "sg:province":"Rhone-Alpes",
    "wof:name":"E.m. Fagot S.a.",
    "wof:placetype":"venue"
},
  "geometry": {"coordinates":[4.968553,45.793755],"type":"Point"}
}