{
  "type": "Feature",
  "properties": {
    "addr:full":"5 Route De Saint Georges Bonnillet 86360 Chasseneuil Du Poitou Poitou-Charentes",
    "addr:housenumber":"5",
    "addr:postcode":"86360",
    "addr:street":"Route De Saint Georges Bonnillet",
    "iso:country":"FR",
    "sg:address":"5 Route De Saint Georges Bonnillet 86360 Chasseneuil Du Poitou",
    "sg:classifiers":[
        {
            "category":"Farming",
            "subcategory":"Farm & Veterinary Services",
            "type":"Manufacturing & Wholesale Goods"
        }
    ],
    "sg:phone":"+33 5 49 39 30 00",
    "sg:province":"Poitou-Charentes",
    "sg:tags":[
        "food",
        "product",
        "breeding",
        "animal",
        "related"
    ],
    "wof:name":"Bonilait Proteines",
    "wof:placetype":"venue"
},
  "geometry": {"coordinates":[0.368775,46.630028],"type":"Point"}
}