{
  "type": "Feature",
  "properties": {
    "addr:full":"115, Rue du Temple, 75003 Paris Ile de France",
    "addr:housenumber":"115",
    "addr:postcode":"75003",
    "addr:street":"Rue Du Temple",
    "iso:country":"FR",
    "sg:address":"115, Rue du Temple, 75003 Paris",
    "sg:orig_category":"Non-Classified Establishments",
    "sg:phone":"+33 1 40 27 97 27",
    "sg:province":"Ile de France",
    "wof:name":"Gekkor S.a.r.l.",
    "wof:placetype":"venue"
},
  "geometry": {"coordinates":[2.357799,48.863014],"type":"Point"}
}