{
  "type": "Feature",
  "properties": {
    "addr:full":"Le Rey 33430 Bazas Bazas Aquitaine 33430",
    "addr:postcode":"33430;33430",
    "iso:country":"FR",
    "sg:address":"Le Rey 33430 Bazas",
    "sg:city":"Bazas",
    "sg:classifiers":[
        {
            "category":"Manufacturing",
            "subcategory":"Tools & Machinery",
            "type":"Manufacturing & Wholesale Goods"
        }
    ],
    "sg:phone":"+33 5 56 25 05 17",
    "sg:postcode":"33430",
    "sg:province":"Aquitaine",
    "sg:tags":[
        "equipment",
        "measurement",
        "-",
        "precision",
        "instrument"
    ],
    "wof:name":"Sa Persohn",
    "wof:placetype":"venue"
},
  "geometry": {"coordinates":[-0.220729,44.427086],"type":"Point"}
}