{
  "type": "Feature",
  "properties": {
    "iso:country":"FR",
    "sg:address":"La Guierche 79700 Mauleon",
    "sg:classifiers":[
        {
            "category":"Food & Beverages",
            "subcategory":"Groceries & Convenience Stores",
            "type":"Retail Goods"
        }
    ],
    "sg:phone":"+33 5 49 81 67 43",
    "sg:postcode":"79700",
    "sg:province":"Poitou-Charentes",
    "sg:tags":[
        "product",
        "grain",
        "cereal",
        "related"
    ],
    "wof:name":"Societe En Nom Collectif Minoterie Beraud",
    "wof:placetype":"venue"
},
  "geometry": {"coordinates":[-0.795684,46.869335],"type":"Point"}
}