{
  "type": "Feature",
  "properties": {
    "iso:country":"FR",
    "sg:address":"4, All\u00e9e Jean Paul Sarthe, 77186 Noisiel",
    "sg:orig_category":"Unclassifiable Establishments",
    "sg:phone":"+33 1 60 17 37 00",
    "sg:province":"Ile de France",
    "wof:name":"Cornet Ing\u00e9nierie S.a.",
    "wof:placetype":"venue"
},
  "geometry": {"coordinates":[2.618688,48.843853],"type":"Point"}
}