{
  "type": "Feature",
  "properties": {
    "iso:country":"FR",
    "sg:address":"68, Rue Mademoiselle, 75015 Paris",
    "sg:orig_category":"Non-Classified Establishments",
    "sg:phone":"+33 1 47 34 93 11",
    "sg:postcode":"75015",
    "sg:province":"Ile de France",
    "wof:name":"Ateliers Frangindus S.a.",
    "wof:placetype":"venue"
},
  "geometry": {"coordinates":[2.301397,48.842884],"type":"Point"}
}