{
  "type": "Feature",
  "properties": {
    "iso:country":"FR",
    "sg:address":"Ch\u00e2teau d'Aroze - Les saegnas",
    "sg:city":"Landiras",
    "sg:orig_category":"Unclassifiable Establishments",
    "sg:phone":"+33 5 57 98 09 09",
    "sg:postcode":"33720",
    "sg:province":"Aquitaine",
    "wof:name":"Aquiland S.a.",
    "wof:placetype":"venue"
},
  "geometry": {"coordinates":[-0.384844,44.534374],"type":"Point"}
}