{
  "type": "Feature",
  "properties": {
    "iso:country":"FR",
    "sg:address":"48 Rue Pierre Curie",
    "sg:city":"Industriel Des Gatins 78370 Plaisir",
    "sg:classifiers":[
        {
            "category":"Manufacturing",
            "subcategory":"Printing",
            "type":"Manufacturing & Wholesale Goods"
        }
    ],
    "sg:phone":"+33 1 30 54 01 63",
    "sg:province":"Ile de France",
    "sg:tags":[
        "publishing"
    ],
    "wof:name":"Priminform",
    "wof:placetype":"venue"
},
  "geometry": {"coordinates":[1.949255,48.816689],"type":"Point"}
}