{
  "type": "Feature",
  "properties": {
    "iso:country":"FR",
    "sg:address":"167, Rte de Saint Leu, 93806 Epinay sur Seine C\u00e9dex",
    "sg:orig_category":"Non-Classified Establishments",
    "sg:phone":"+33 1 48 22 64 32",
    "sg:province":"Champagne",
    "wof:name":"Etablissements Impr\u00e9gna S.a.r.l.",
    "wof:placetype":"venue"
},
  "geometry": {"coordinates":[2.334613,48.954227],"type":"Point"}
}