{
  "type": "Feature",
  "properties": {
    "iso:country":"FR",
    "sg:address":"Route Evron 72140 Sill\u00e9 Le Guillaume",
    "sg:classifiers":[
        {
            "category":"Shopping",
            "subcategory":"Clothing, Apparel, & Fashions",
            "type":"Retail Goods"
        }
    ],
    "sg:phone":"+33 2 43 52 10 10",
    "sg:postcode":"72140",
    "sg:province":"Pays de Loire",
    "sg:tags":[
        "textile",
        "clothing",
        "clothes"
    ],
    "wof:name":"Confection Sille Le Guillaume Sa",
    "wof:placetype":"venue"
},
  "geometry": {"coordinates":[-0.126007,48.174728],"type":"Point"}
}