{
  "type": "Feature",
  "properties": {
    "iso:country":"FR",
    "sg:address":"1, Place de la Gare, 35000 Rennes",
    "sg:city":"Rennes",
    "sg:orig_category":"Non-Classified Establishments",
    "sg:phone":"+33 2 99 67 40 67",
    "sg:postcode":"35000",
    "sg:province":"Bretagne",
    "wof:name":"Pointcarr\u00e9 S.a.r.l.",
    "wof:placetype":"venue"
},
  "geometry": {"coordinates":[-1.673496,48.104046],"type":"Point"}
}