{
  "type": "Feature",
  "properties": {
    "addr:full":"ZA des Morands Montchanin Bourgogne 71210",
    "addr:postcode":"71210",
    "addr:street":"Za Des Morands;Bourgogne",
    "iso:country":"FR",
    "sg:address":"ZA des Morands",
    "sg:city":"Montchanin",
    "sg:orig_category":"Non-Classified Establishments",
    "sg:phone":"+33 3 85 78 52 00",
    "sg:postcode":"71210",
    "sg:province":"Bourgogne",
    "wof:name":"Matrex Industries S.a.",
    "wof:placetype":"venue"
},
  "geometry": {"coordinates":[4.46917,46.748814],"type":"Point"}
}