{
  "type": "Feature",
  "properties": {
    "addr:full":"5, Rte de Nemours, 77250 Villecerf Ile de France 77250",
    "addr:housenumber":"5",
    "addr:postcode":"77250;ile;77250",
    "addr:street":"Rte De Nemours;France",
    "iso:country":"FR",
    "sg:address":"5, Rte de Nemours, 77250 Villecerf",
    "sg:orig_category":"Non-Classified Establishments",
    "sg:phone":"+33 1 64 24 93 75",
    "sg:postcode":"77250",
    "sg:province":"Ile de France",
    "wof:name":"Co.me.vi. Eriaud S.a. - Constructions M\u00e9talliques De Villecerf",
    "wof:placetype":"venue"
},
  "geometry": {"coordinates":[2.84817,48.324196],"type":"Point"}
}