{
  "type": "Feature",
  "properties": {
    "addr:full":"7, Rue du Moulin Br\u00fbl\u00e9, 51100 Reims Champagne 51100",
    "addr:housenumber":"7",
    "addr:postcode":"51100;51100",
    "addr:street":"Rue Du Moulin Bru\u0302Le\u0301",
    "iso:country":"FR",
    "sg:address":"7, Rue du Moulin Br\u00fbl\u00e9, 51100 Reims",
    "sg:orig_category":"Non-Classified Establishments",
    "sg:phone":"+33 3 26 08 72 91",
    "sg:postcode":"51100",
    "sg:province":"Champagne",
    "wof:name":"A.d.s. S.a. - Auto Distribution Services",
    "wof:placetype":"venue"
},
  "geometry": {"coordinates":[4.017704,49.250603],"type":"Point"}
}