{
  "type": "Feature",
  "properties": {
    "addr:full":"4 Rue Rene Razel Parc Technologique Apollo 91892 Orsay Cedex Champagne",
    "addr:housenumber":"4",
    "addr:postcode":"91892",
    "addr:street":"Rue Rene Razel Parc",
    "iso:country":"FR",
    "sg:address":"4 Rue Rene Razel Parc Technologique Apollo 91892 Orsay Cedex",
    "sg:classifiers":[
        {
            "category":"Wholesale",
            "subcategory":"Medical Equipment & Supplies",
            "type":"Manufacturing & Wholesale Goods"
        }
    ],
    "sg:phone":"+33 1 69 35 59 00",
    "sg:province":"Champagne",
    "sg:tags":[
        "instrument",
        "health",
        "-",
        "precision"
    ],
    "wof:name":"Kiscomedica",
    "wof:placetype":"venue"
},
  "geometry": {"coordinates":[2.18775,48.698891],"type":"Point"}
}