{
  "type": "Feature",
  "properties": {
    "addr:full":"22 All\u00e9e Du Clos Des Charmes Za Porte De La For\u00eat 77090 Coll\u00e9gien Ile de France 77090",
    "addr:housenumber":"22",
    "addr:postcode":"77090;77090",
    "addr:street":"Alle\u0301E Du Clos Des Charmes Za Porte De La Fore\u0302T;Ile De France",
    "iso:country":"FR",
    "sg:address":"22 All\u00e9e Du Clos Des Charmes Za Porte De La For\u00eat 77090 Coll\u00e9gien",
    "sg:classifiers":[
        {
            "category":"Shopping",
            "subcategory":"Computers & Home Electronics",
            "type":"Retail Goods"
        }
    ],
    "sg:phone":"+33 1 60 37 55 55",
    "sg:postcode":"77090",
    "sg:province":"Ile de France",
    "sg:tags":[
        "equipment",
        "electrical",
        "component",
        "electric",
        "electronic"
    ],
    "wof:name":"Myrra Sa",
    "wof:placetype":"venue"
},
  "geometry": {"coordinates":[2.674854,48.830006],"type":"Point"}
}