{
  "type": "Feature",
  "properties": {
    "iso:country":"FR",
    "sg:address":"route de la Valentine 13011 Marseille",
    "sg:orig_category":"Caoutchouc",
    "sg:phone":"+33 4 91 43 21 84",
    "sg:province":"Poitou-Charentes",
    "wof:name":"Ste Vulcanis Indust Caoutchout Sarl",
    "wof:placetype":"venue"
},
  "geometry": {"coordinates":[5.463185,43.290417],"type":"Point"}
}