{
  "type": "Feature",
  "properties": {
    "addr:full":"26, Rue Treilhard, 75008 Paris Ile de France 75008",
    "addr:housenumber":"26",
    "addr:postcode":"75008;75008",
    "addr:street":"Rue Treilhard",
    "iso:country":"FR",
    "sg:address":"26, Rue Treilhard, 75008 Paris",
    "sg:orig_category":"Non-Classified Establishments",
    "sg:phone":"+33 1 44 35 21 00",
    "sg:postcode":"75008",
    "sg:province":"Ile de France",
    "wof:name":"Danone International Brands S.a.",
    "wof:placetype":"venue"
},
  "geometry": {"coordinates":[2.313046,48.876957],"type":"Point"}
}