{
  "type": "Feature",
  "properties": {
    "addr:full":"214, Rue de Seine, 77190 Dammarie les Lys Ile de France",
    "addr:housenumber":"214",
    "addr:postcode":"77190",
    "addr:street":"Rue De Seine",
    "iso:country":"FR",
    "sg:address":"214, Rue de Seine, 77190 Dammarie les Lys",
    "sg:orig_category":"Non-Classified Establishments",
    "sg:phone":"+33 1 64 37 39 23",
    "sg:province":"Ile de France",
    "wof:name":"M.a.p. 77 - Moules Application Plasturgie",
    "wof:placetype":"venue"
},
  "geometry": {"coordinates":[2.615759,48.516785],"type":"Point"}
}