{
  "type": "Feature",
  "properties": {
    "addr:full":"Les Veyssieres 24570 Condat sur V\u00e9z\u00e8re Condat-sur-V\u00e9z\u00e8re Aquitaine 24570",
    "addr:postcode":"24570;24570",
    "iso:country":"FR",
    "sg:address":"Les Veyssieres 24570 Condat sur V\u00e9z\u00e8re",
    "sg:city":"Condat-sur-V\u00e9z\u00e8re",
    "sg:orig_category":"Unclassifiable Establishments",
    "sg:phone":"+33 5 53 51 40 60",
    "sg:postcode":"24570",
    "sg:province":"Aquitaine",
    "wof:name":"B.i.p. S.a.",
    "wof:placetype":"venue"
},
  "geometry": {"coordinates":[1.22628,45.129089],"type":"Point"}
}