{
  "type": "Feature",
  "properties": {
    "addr:full":"37, Rue du Bignon, 35510 Cesson S\u00e9vign\u00e9 Cesson-S\u00e9vign\u00e9 Bretagne 35510",
    "addr:housenumber":"37",
    "addr:postcode":"35510;se\u0301vigne\u0301 cesson-se\u0301vigne\u0301;35510",
    "addr:street":"Rue Du Bignon",
    "iso:country":"FR",
    "sg:address":"37, Rue du Bignon, 35510 Cesson S\u00e9vign\u00e9",
    "sg:city":"Cesson-S\u00e9vign\u00e9",
    "sg:orig_category":"Non-Classified Establishments",
    "sg:phone":"+33 2 99 51 34 51",
    "sg:postcode":"35510",
    "sg:province":"Bretagne",
    "wof:name":"Adec Bretagne S.a.",
    "wof:placetype":"venue"
},
  "geometry": {"coordinates":[-1.620102,48.099537],"type":"Point"}
}