{
  "type": "Feature",
  "properties": {
    "iso:country":"FR",
    "sg:address":"10, Place du Temple, 79000 Niort",
    "sg:orig_category":"Unclassifiable Establishments",
    "sg:phone":"+33 5 49 28 79 79",
    "sg:postcode":"79000",
    "sg:province":"Poitou-Charentes",
    "wof:name":"C.c.i. Des Deux S\u00e8vres",
    "wof:placetype":"venue"
},
  "geometry": {"coordinates":[-0.461472,46.323017],"type":"Point"}
}