{
  "type": "Feature",
  "properties": {
    "addr:full":"10, Place du Temple, 79000 Niort Poitou-Charentes 79000",
    "addr:housenumber":"10",
    "addr:postcode":"79000;79000",
    "addr:street":"Place Du Temple",
    "iso:country":"FR",
    "sg:address":"10, Place du Temple, 79000 Niort",
    "sg:orig_category":"Unclassifiable Establishments",
    "sg:phone":"+33 5 49 28 79 79",
    "sg:postcode":"79000",
    "sg:province":"Poitou-Charentes",
    "wof:name":"C.c.i. Des Deux S\u00e8vres",
    "wof:placetype":"venue"
},
  "geometry": {"coordinates":[-0.461472,46.323017],"type":"Point"}
}