{
  "type": "Feature",
  "properties": {
    "addr:full":"Troyes 10 Bourgogne",
    "addr:housenumber":"10",
    "addr:street":"Bourgogne",
    "iso:country":"FR",
    "sg:address":"Troyes",
    "sg:city":"10",
    "sg:classifiers":[
        {
            "category":"Banks & Credit Unions",
            "subcategory":"Bank",
            "type":"Services"
        }
    ],
    "sg:province":"Bourgogne",
    "wof:name":"Sedis 1",
    "wof:placetype":"venue"
},
  "geometry": {"coordinates":[4.07434,48.297871],"type":"Point"}
}