{
  "type": "Feature",
  "properties": {
    "addr:full":"8 \u00e8me Rue, 1\u00e8re Avenue. - ZI de Carros, 06510 Carros Provence-Alpes-C\u00f4te d'Azur",
    "addr:housenumber":"8",
    "addr:postcode":"06510",
    "addr:street":"Rue 1E\u0300Re Avenue. Zi De Carros",
    "iso:country":"FR",
    "sg:address":"8 \u00e8me Rue, 1\u00e8re Avenue. - ZI de Carros, 06510 Carros",
    "sg:orig_category":"Unclassifiable Establishments",
    "sg:phone":"+33 4 92 08 62 00",
    "sg:province":"Provence-Alpes-C\u00f4te d'Azur",
    "wof:name":"Augier S.a.",
    "wof:placetype":"venue"
},
  "geometry": {"coordinates":[7.194835,43.803421],"type":"Point"}
}