{
  "type": "Feature",
  "properties": {
    "iso:country":"FR",
    "sg:address":"Rte de Montauban - Memer",
    "sg:city":"Vailhourles",
    "sg:orig_category":"Non-Classified Establishments",
    "sg:phone":"+33 5 65 29 50 44",
    "sg:postcode":"12200",
    "sg:province":"Midi Pyr\u00e9n\u00e9es",
    "wof:name":"Etablissements Truchis",
    "wof:placetype":"venue"
},
  "geometry": {"coordinates":[1.996273,44.265919],"type":"Point"}
}