{
  "type": "Feature",
  "properties": {
    "addr:full":"22 Chem Du Garrabot 31770 Colomiers Midi Pyr\u00e9n\u00e9es 31770",
    "addr:housenumber":"22",
    "addr:postcode":"31770;31770",
    "addr:street":"Chem Du Garrabot",
    "iso:country":"FR",
    "sg:address":"22 Chem Du Garrabot 31770 Colomiers",
    "sg:orig_category":"Miscellaneous Products",
    "sg:phone":"+33 5 61 78 55 44",
    "sg:postcode":"31770",
    "sg:province":"Midi Pyr\u00e9n\u00e9es",
    "wof:name":"Centech Sa",
    "wof:placetype":"venue"
},
  "geometry": {"coordinates":[1.304287,43.598167],"type":"Point"}
}