{
  "type": "Feature",
  "properties": {
    "addr:full":"48 Cs Suchet Angle Rues Smith-Quivogne 69002 Lyon Rhone-Alpes 69002",
    "addr:postcode":"69002;69002",
    "addr:street":"Cs;Angle Rues Smith-Quivogne",
    "iso:country":"FR",
    "sg:address":"48 Cs Suchet Angle Rues Smith-Quivogne 69002 Lyon",
    "sg:classifiers":[
        {
            "category":"Professional",
            "subcategory":"Business Services",
            "type":"Services"
        }
    ],
    "sg:phone":"+33 4 72 56 42 10",
    "sg:postcode":"69002",
    "sg:province":"Rhone-Alpes",
    "sg:tags":[
        "training",
        "advice"
    ],
    "wof:name":"Ste Pour La Promotion De La Culture Et Des Loisirs",
    "wof:placetype":"venue"
},
  "geometry": {"coordinates":[4.828975,45.759399],"type":"Point"}
}