{
  "type": "Feature",
  "properties": {
    "addr:full":"Les Relandieres 44850 LE CELLIER Pays de Loire 44850",
    "addr:postcode":"44850;44850",
    "addr:street":"Cellier",
    "iso:country":"FR",
    "sg:address":"Les Relandieres 44850 LE CELLIER",
    "sg:orig_category":"Adhesives For The Leather Industry",
    "sg:phone":"+33 2 28 22 00 00",
    "sg:postcode":"44850",
    "sg:province":"Pays de Loire",
    "wof:name":"Aplix S.a.",
    "wof:placetype":"venue"
},
  "geometry": {"coordinates":[-1.370154,47.317944],"type":"Point"}
}