{
  "type": "Feature",
  "properties": {
    "addr:full":"ZI Saint Joseph Manosque Provence-Alpes-C\u00f4te d'Azur 04100",
    "addr:postcode":"04100",
    "addr:street":"Joseph",
    "iso:country":"FR",
    "sg:address":"ZI Saint Joseph",
    "sg:city":"Manosque",
    "sg:orig_category":"Unclassifiable Establishments",
    "sg:phone":"+33 4 92 70 16 16",
    "sg:postcode":"04100",
    "sg:province":"Provence-Alpes-C\u00f4te d'Azur",
    "wof:name":"A.b.b. Barras Provence S.a.",
    "wof:placetype":"venue"
},
  "geometry": {"coordinates":[5.784205,43.831474],"type":"Point"}
}