{
  "type": "Feature",
  "properties": {
    "iso:country":"FR",
    "sg:address":"31-43 quai des Gresillons 92230 Gennevilliers",
    "sg:orig_category":"Paternoster Lifts",
    "sg:phone":"+33 1 40 80 10 10",
    "sg:province":"Ile de France",
    "wof:name":"Siminor Sa",
    "wof:placetype":"venue"
},
  "geometry": {"coordinates":[2.323437,48.920471],"type":"Point"}
}