{
  "type": "Feature",
  "properties": {
    "addr:full":"31-43 quai des Gresillons 92230 Gennevilliers Ile de France",
    "addr:housenumber":"31-43",
    "addr:postcode":"92230;ile",
    "addr:street":"Quai Des Gresillons",
    "iso:country":"FR",
    "sg:address":"31-43 quai des Gresillons 92230 Gennevilliers",
    "sg:orig_category":"Paternoster Lifts",
    "sg:phone":"+33 1 40 80 10 10",
    "sg:province":"Ile de France",
    "wof:name":"Siminor Sa",
    "wof:placetype":"venue"
},
  "geometry": {"coordinates":[2.323437,48.920471],"type":"Point"}
}