{
  "type": "Feature",
  "properties": {
    "iso:country":"FR",
    "sg:address":"131 R De S\u00e9ville 66000 Perpignan",
    "sg:classifiers":[
        {
            "category":"Professional",
            "type":"Services"
        }
    ],
    "sg:phone":"+33 4 68 68 19 33",
    "sg:province":"Languedoc-Roussillon",
    "sg:tags":[
        "-",
        "related",
        "road",
        "transport"
    ],
    "wof:name":"Lm Medina Sas",
    "wof:placetype":"venue"
},
  "geometry": {"coordinates":[2.852335,42.683914],"type":"Point"}
}