{
  "type": "Feature",
  "properties": {
    "iso:country":"FR",
    "sg:address":"149 Quai Jules Guesde 94405 Vitry Sur Seine Cedex",
    "sg:classifiers":[
        {
            "category":"Manufacturing",
            "subcategory":"Wood Products",
            "type":"Manufacturing & Wholesale Goods"
        }
    ],
    "sg:phone":"+33 1 43 90 44 00",
    "sg:province":"\u00cele-de-France",
    "sg:tags":[
        "furniture"
    ],
    "wof:name":"Diffusion International Mobilier Sarl",
    "wof:placetype":"venue"
},
  "geometry": {"coordinates":[2.407537,48.80685],"type":"Point"}
}