{
  "type": "Feature",
  "properties": {
    "addr:full":"84240 La Bastide Des Jourdans La Bastide Languedoc-Roussillon 66110",
    "addr:housenumber":"84240",
    "addr:postcode":"66110",
    "addr:street":"La",
    "iso:country":"FR",
    "sg:address":"84240 La Bastide Des Jourdans",
    "sg:city":"La Bastide",
    "sg:classifiers":[
        {
            "category":"Home & Garden",
            "subcategory":"Furniture",
            "type":"Retail Goods"
        }
    ],
    "sg:phone":"+33 4 90 77 81 20",
    "sg:postcode":"66110",
    "sg:province":"Languedoc-Roussillon",
    "sg:tags":[
        "household",
        "wood"
    ],
    "wof:name":"Les Meubles Abello",
    "wof:placetype":"venue"
},
  "geometry": {"coordinates":[5.635216,43.785988],"type":"Point"}
}