{
  "type": "Feature",
  "properties": {
    "iso:country":"FR",
    "sg:address":"6, Rue de l'Industrie - ZI la Courbi\u00e8re, 49450 Saint Macaire en Mauges",
    "sg:orig_category":"Non-Classified Establishments",
    "sg:phone":"+33 2 41 55 36 46",
    "sg:province":"Pays de Loire",
    "wof:name":"Semac S.a.r.l.",
    "wof:placetype":"venue"
},
  "geometry": {"coordinates":[-0.976353,47.119495],"type":"Point"}
}