{
  "type": "Feature",
  "properties": {
    "addr:full":"L'Oisivi\u00e8re 61600 La Fert\u00e9 Mac\u00e9 Beauvain Basse Normandie 61600",
    "addr:postcode":"61600;61600",
    "iso:country":"FR",
    "sg:address":"L'Oisivi\u00e8re 61600 La Fert\u00e9 Mac\u00e9",
    "sg:city":"Beauvain",
    "sg:orig_category":"Non-Classified Establishments",
    "sg:phone":"+33 2 33 37 01 89",
    "sg:postcode":"61600",
    "sg:province":"Basse Normandie",
    "wof:name":"Motin Scierie S.a.r.l.",
    "wof:placetype":"venue"
},
  "geometry": {"coordinates":[-0.35835,48.589481],"type":"Point"}
}