{
  "type": "Feature",
  "properties": {
    "addr:full":"Puits Barrois 57150 Creutzwald Lorraine 57150",
    "addr:postcode":"57150;57150",
    "addr:street":"Puits Barrois",
    "iso:country":"FR",
    "sg:address":"Puits Barrois 57150 Creutzwald",
    "sg:orig_category":"D\u00c9GRAISSANTS, D\u00c9CAPANTS POUR B\u00c2TIMENTS, INDUSTRIES ET COLLECTIVIT\u00c9S PRODUITS DE TRAITEMENT DE SURFAC",
    "sg:phone":"+33 3 87 82 69 90",
    "sg:postcode":"57150",
    "sg:province":"Lorraine",
    "wof:name":"Etablissements Alchim",
    "wof:placetype":"venue"
},
  "geometry": {"coordinates":[6.70768,49.191784],"type":"Point"}
}