{
  "type": "Feature",
  "properties": {
    "addr:full":"Rte Couthezon 84230 Ch\u00e2teauneuf Du Pape Ch\u00e2teau Bourgogne 71250",
    "addr:postcode":"84230;71250",
    "addr:street":"Rte Couthezon",
    "iso:country":"FR",
    "sg:address":"Rte Couthezon 84230 Ch\u00e2teauneuf Du Pape",
    "sg:city":"Ch\u00e2teau",
    "sg:classifiers":[
        {
            "category":"Food Court",
            "type":"Food & Drink"
        }
    ],
    "sg:phone":"+33 4 90 83 73 09",
    "sg:postcode":"71250",
    "sg:province":"Bourgogne",
    "sg:tags":[
        "product",
        "related"
    ],
    "wof:name":"Chateau Rayas Scea",
    "wof:placetype":"venue"
},
  "geometry": {"coordinates":[4.83468,44.058636],"type":"Point"}
}