{
  "type": "Feature",
  "properties": {
    "addr:full":"31 bis, Cours de Verdun, 01112 Oyonnax Rhone-Alpes",
    "addr:housenumber":"31 bis",
    "addr:postcode":"01112",
    "addr:street":"Cours De Verdun",
    "iso:country":"FR",
    "sg:address":"31 bis, Cours de Verdun, 01112 Oyonnax",
    "sg:orig_category":"Non-Classified Establishments",
    "sg:phone":"+33 4 74 73 15 80",
    "sg:province":"Rhone-Alpes",
    "wof:name":"Superjouet International S.a.r.l.",
    "wof:placetype":"venue"
},
  "geometry": {"coordinates":[5.654216,46.266476],"type":"Point"}
}