{
  "type": "Feature",
  "properties": {
    "iso:country":"FR",
    "sg:address":"20, Av. Lucien Cornet, 89100 Sens",
    "sg:city":"Sens",
    "sg:orig_category":"Non-Classified Establishments",
    "sg:phone":"+33 3 86 65 56 91",
    "sg:postcode":"89100",
    "sg:province":"Bourgogne",
    "wof:name":"Sam Couture",
    "wof:placetype":"venue"
},
  "geometry": {"coordinates":[3.274283,48.197575],"type":"Point"}
}