{
  "type": "Feature",
  "properties": {
    "iso:country":"FR",
    "sg:address":"Zi D'Etriche 49500 Segr\u00e9",
    "sg:classifiers":[
        {
            "category":"Manufacturing",
            "subcategory":"Leather Goods",
            "type":"Manufacturing & Wholesale Goods"
        }
    ],
    "sg:phone":"+33 2 41 94 74 40",
    "sg:postcode":"49500",
    "sg:province":"Pays de Loire",
    "sg:tags":[
        "shoe"
    ],
    "wof:name":"Longchamp",
    "wof:placetype":"venue"
},
  "geometry": {"coordinates":[-0.859661,47.69688],"type":"Point"}
}