{
  "type": "Feature",
  "properties": {
    "iso:country":"FR",
    "sg:address":"B.P. 35, 49180 Saint Barth\u00e9l\u00e9my d'Anjou C\u00e9dex^^6, Rue Joliot Curie, 49124 Saint Barth\u00e9l\u00e9my d'Anjou",
    "sg:orig_category":"Non-Classified Establishments",
    "sg:phone":"+33 2 41 93 02 95",
    "sg:province":"Pays de Loire",
    "wof:name":"P.r.o.",
    "wof:placetype":"venue"
},
  "geometry": {"coordinates":[-73.538673,45.612267],"type":"Point"}
}