{
  "type": "Feature",
  "properties": {
    "addr:full":"102 Rue De Paris 95720 Le Mesnil Aubry Ile de France 95720",
    "addr:housenumber":"102",
    "addr:postcode":"95720;ile;95720",
    "addr:street":"Rue De Paris;France",
    "iso:country":"FR",
    "sg:address":"102 Rue De Paris 95720 Le Mesnil Aubry",
    "sg:classifiers":[
        {
            "category":"Farming",
            "subcategory":"Crops",
            "type":"Manufacturing & Wholesale Goods"
        }
    ],
    "sg:phone":"+33 1 34 71 10 11",
    "sg:postcode":"95720",
    "sg:province":"Ile de France",
    "sg:tags":[
        "vegetable",
        "fruit",
        "agriculture",
        "livestock"
    ],
    "wof:name":"Prim A Nord Sa",
    "wof:placetype":"venue"
},
  "geometry": {"coordinates":[2.398669,49.05648],"type":"Point"}
}