{
  "type": "Feature",
  "properties": {
    "addr:full":"ZI de Chablis Chablis Bourgogne 89800",
    "addr:postcode":"89800",
    "addr:street":"Zi De Chablis;Bourgogne",
    "iso:country":"FR",
    "sg:address":"ZI de Chablis",
    "sg:city":"Chablis",
    "sg:orig_category":"Unclassifiable Establishments",
    "sg:phone":"+33 3 86 42 89 42",
    "sg:postcode":"89800",
    "sg:province":"Bourgogne",
    "wof:name":"A.s. Birambeau S.a.",
    "wof:placetype":"venue"
},
  "geometry": {"coordinates":[3.80125,47.815182],"type":"Point"}
}