{
  "type": "Feature",
  "properties": {
    "addr:full":"134 Av De Gen\u00e8ve 74000 Annecy Rhone-Alpes 74000",
    "addr:postcode":"74000;74000",
    "addr:street":"134 Av De Gene\u0300Ve",
    "iso:country":"FR",
    "sg:address":"134 Av De Gen\u00e8ve 74000 Annecy",
    "sg:classifiers":[
        {
            "category":"Travel",
            "subcategory":"Hotels & Motels",
            "type":"Entertainment"
        }
    ],
    "sg:phone":"+33 4 50 67 75 78",
    "sg:postcode":"74000",
    "sg:province":"Rhone-Alpes",
    "sg:tags":[
        "hotels",
        "business",
        "restaurant"
    ],
    "wof:name":"Casino Cafeteria",
    "wof:placetype":"venue"
},
  "geometry": {"coordinates":[6.12405,45.924404],"type":"Point"}
}