{
  "type": "Feature",
  "properties": {
    "addr:full":"20 Rue Louis Adam 69100 Villeurbanne Rhone-Alpes 69100",
    "addr:housenumber":"20",
    "addr:postcode":"69100;69100",
    "addr:street":"Rue Louis Adam",
    "iso:country":"FR",
    "sg:address":"20 Rue Louis Adam 69100 Villeurbanne",
    "sg:classifiers":[
        {
            "category":"Manufacturing",
            "subcategory":"Metals",
            "type":"Manufacturing & Wholesale Goods"
        }
    ],
    "sg:phone":"+33 4 78 84 87 36",
    "sg:postcode":"69100",
    "sg:province":"Rhone-Alpes",
    "sg:tags":[
        "metallurgy",
        "metalworking",
        "processing"
    ],
    "wof:name":"Mollard Et Fils Sa",
    "wof:placetype":"venue"
},
  "geometry": {"coordinates":[4.871643,45.768265],"type":"Point"}
}