{
  "type": "Feature",
  "properties": {
    "iso:country":"FR",
    "sg:address":"8/10, Rue Victor Noir, 92200 Neuilly sur Seine",
    "sg:orig_category":"Non-Classified Establishments",
    "sg:phone":"+33 1 55 62 33 33",
    "sg:province":"Ile de France",
    "wof:name":"Kearney Interactive S.a.s.",
    "wof:placetype":"venue"
},
  "geometry": {"coordinates":[2.266274,48.881615],"type":"Point"}
}