{
  "type": "Feature",
  "properties": {
    "addr:full":"B.P. 15, 23220 Bonnat^^Rte du Bourg d'Hem, 23220 Bonnat Limousin",
    "addr:postcode":"23220;23220",
    "addr:street":"B.P. 15;Du Bourg D'Hem",
    "iso:country":"FR",
    "sg:address":"B.P. 15, 23220 Bonnat^^Rte du Bourg d'Hem, 23220 Bonnat",
    "sg:orig_category":"Non-Classified Establishments",
    "sg:phone":"+33 5 55 62 16 37",
    "sg:province":"Limousin",
    "wof:name":"S.e.e.l.e.c. S.a.r.l. - Services D'equipements Electrom\u00e9caniques",
    "wof:placetype":"venue"
},
  "geometry": {"coordinates":[1.918303,46.39468],"type":"Point"}
}