{
  "type": "Feature",
  "properties": {
    "addr:full":"Rue de la Gare - ZA Neuilly l'Ev\u00eaque Champagne 52360",
    "addr:postcode":"52360",
    "addr:street":"Rue De La Gare Za Neuilly L'Eve \u0302Que Champagne",
    "iso:country":"FR",
    "sg:address":"Rue de la Gare - ZA",
    "sg:city":"Neuilly l'Ev\u00eaque",
    "sg:orig_category":"Unclassifiable Establishments",
    "sg:phone":"+33 3 25 84 01 33",
    "sg:postcode":"52360",
    "sg:province":"Champagne",
    "wof:name":"Jo\u00ebl Lesserteur S.a.",
    "wof:placetype":"venue"
},
  "geometry": {"coordinates":[5.442223,47.916069],"type":"Point"}
}