{
  "type": "Feature",
  "properties": {
    "iso:country":"FR",
    "sg:address":"8 Chem Des Martinaz 74300 Magland",
    "sg:classifiers":[
        {
            "category":"Manufacturing",
            "subcategory":"Metals",
            "type":"Manufacturing & Wholesale Goods"
        }
    ],
    "sg:phone":"+33 4 50 34 70 12",
    "sg:postcode":"74300",
    "sg:province":"Rhone-Alpes",
    "sg:tags":[
        "metallurgy",
        "metalworking",
        "processing"
    ],
    "wof:name":"Ets Aristide Burnier Sa",
    "wof:placetype":"venue"
},
  "geometry": {"coordinates":[6.614535,46.012402],"type":"Point"}
}