{
  "type": "Feature",
  "properties": {
    "addr:full":"12, Rue Vignon, 75009 Paris Ile de France",
    "addr:housenumber":"12",
    "addr:postcode":"75009",
    "addr:street":"Rue Vignon",
    "iso:country":"FR",
    "sg:address":"12, Rue Vignon, 75009 Paris",
    "sg:orig_category":"Unclassifiable Establishments",
    "sg:phone":"+33 1 44 51 60 51",
    "sg:province":"Ile de France",
    "wof:name":"Icelandair",
    "wof:placetype":"venue"
},
  "geometry": {"coordinates":[2.32634,48.870819],"type":"Point"}
}