{
  "type": "Feature",
  "properties": {
    "addr:full":"ZA de Girouflat Marmande Aquitaine 47200",
    "addr:postcode":"47200",
    "addr:street":"Za De Girouflat Marmande",
    "iso:country":"FR",
    "sg:address":"ZA de Girouflat",
    "sg:city":"Marmande",
    "sg:orig_category":"Non-Classified Establishments",
    "sg:phone":"+33 5 53 20 18 16",
    "sg:postcode":"47200",
    "sg:province":"Aquitaine",
    "wof:name":"Locadour G.l.r.",
    "wof:placetype":"venue"
},
  "geometry": {"coordinates":[0.165555,44.50359],"type":"Point"}
}