{
  "type": "Feature",
  "properties": {
    "addr:full":"15 Rue De Montmorency 95600 Eaubonne Ile de France 95600",
    "addr:housenumber":"15",
    "addr:postcode":"95600;95600",
    "addr:street":"Rue De Montmorency",
    "iso:country":"FR",
    "sg:address":"15 Rue De Montmorency 95600 Eaubonne",
    "sg:classifiers":[
        {
            "category":"Utilities",
            "subcategory":"Mobile Phone",
            "type":"Services"
        }
    ],
    "sg:phone":"+33 1 34 06 18 71",
    "sg:postcode":"95600",
    "sg:province":"Ile de France",
    "sg:tags":[
        "telecommunication",
        "audio-visual"
    ],
    "wof:name":"Hms",
    "wof:placetype":"venue"
},
  "geometry": {"coordinates":[2.278957,49.004219],"type":"Point"}
}