{
  "type": "Feature",
  "properties": {
    "addr:full":"2, Av. Jeanne, 92600 Asni\u00e8res sur Seine Ile de France 92600",
    "addr:postcode":"92600;92600",
    "addr:street":"Av. Jeanne",
    "iso:country":"FR",
    "sg:address":"2, Av. Jeanne, 92600 Asni\u00e8res sur Seine",
    "sg:orig_category":"Non-Classified Establishments",
    "sg:phone":"+33 1 41 11 25 68",
    "sg:postcode":"92600",
    "sg:province":"Ile de France",
    "wof:name":"Carr\u00e9 Jaune S.a.r.l.",
    "wof:placetype":"venue"
},
  "geometry": {"coordinates":[2.272282,48.907806],"type":"Point"}
}