{
  "type": "Feature",
  "properties": {
    "addr:full":"14, Rue de la Saulgeot, 71640 Givry Givry Bourgogne 71640",
    "addr:housenumber":"14",
    "addr:postcode":"71640;71640",
    "addr:street":"Rue De La Saulgeot",
    "iso:country":"FR",
    "sg:address":"14, Rue de la Saulgeot, 71640 Givry",
    "sg:city":"Givry",
    "sg:orig_category":"Non-Classified Establishments",
    "sg:phone":"+33 3 85 94 16 70",
    "sg:postcode":"71640",
    "sg:province":"Bourgogne",
    "wof:name":"A\u00e9rosa\u00f4ne S.a.r.l.",
    "wof:placetype":"venue"
},
  "geometry": {"coordinates":[4.767414,46.77747],"type":"Point"}
}