{
  "type": "Feature",
  "properties": {
    "addr:full":"B.P. 82, 60640 Guiscard C\u00e9dex 04^^8, Rue de l'Equip\u00e9e - Zone Industrielle, 60640 Guiscard Picardie",
    "addr:housenumber":"04 ^ ^ 8",
    "addr:postcode":"60640;60640",
    "addr:street":"B.P. 82;Ce\u0301Dex;Rue De L'Equipe \u0301E Zone Industrielle",
    "iso:country":"FR",
    "sg:address":"B.P. 82, 60640 Guiscard C\u00e9dex 04^^8, Rue de l'Equip\u00e9e - Zone Industrielle, 60640 Guiscard",
    "sg:orig_category":"Non-Classified Establishments",
    "sg:phone":"+33 3 44 43 52 00",
    "sg:province":"Picardie",
    "wof:name":"Nobel Plastiques S.a.",
    "wof:placetype":"venue"
},
  "geometry": {"coordinates":[3.053649,49.65926],"type":"Point"}
}