{
  "type": "Feature",
  "properties": {
    "iso:country":"FR",
    "sg:address":"95, Rte de B\u00e9thune, 62223 Sainte Catherine",
    "sg:orig_category":"Unclassifiable Establishments",
    "sg:phone":"+33 3 21 24 91 07",
    "sg:province":"Nord Pas-de-Calais",
    "wof:name":"Etablissements Charles Corbeau S.a.",
    "wof:placetype":"venue"
},
  "geometry": {"coordinates":[2.758711,50.320061],"type":"Point"}
}