{
  "type": "Feature",
  "properties": {
    "addr:full":"B.P. 73, 62201 Boulogne sur Mer C\u00e9dex^^170, Rue Vanheeckhoet, 62480 Le Portel Nord Pas-de-Calais",
    "addr:postcode":"62201;62480",
    "addr:street":"B.P. 73;Rue Vanheeckhoet",
    "iso:country":"FR",
    "sg:address":"B.P. 73, 62201 Boulogne sur Mer C\u00e9dex^^170, Rue Vanheeckhoet, 62480 Le Portel",
    "sg:orig_category":"Non-Classified Establishments",
    "sg:phone":"+33 3 21 87 46 18",
    "sg:province":"Nord Pas-de-Calais",
    "wof:name":"Nordvik S.a.",
    "wof:placetype":"venue"
},
  "geometry": {"coordinates":[1.574208,50.706753],"type":"Point"}
}