{
  "type": "Feature",
  "properties": {
    "addr:full":"1156 chemin de la Sine 06140 Vence Franche Comt\u00e9",
    "addr:housenumber":"1156",
    "addr:postcode":"06140",
    "addr:street":"Chemin De La Sine;Franche Comte\u0301",
    "iso:country":"FR",
    "sg:address":"1156 chemin de la Sine 06140 Vence",
    "sg:classifiers":[
        {
            "category":"Food & Beverages",
            "subcategory":"Fruits & Vegetables",
            "type":"Retail Goods"
        }
    ],
    "sg:phone":"+33 4 93 58 29 29",
    "sg:province":"Franche Comt\u00e9",
    "sg:tags":[
        "processing",
        "machinery"
    ],
    "wof:name":"Dynamic Sa",
    "wof:placetype":"venue"
},
  "geometry": {"coordinates":[7.08766,43.714001],"type":"Point"}
}