{
  "type": "Feature",
  "properties": {
    "iso:country":"FR",
    "sg:address":"Bd du Vivarais - ZI du Lac",
    "sg:city":"Privas",
    "sg:orig_category":"Unclassifiable Establishments",
    "sg:phone":"+33 4 75 66 92 90",
    "sg:postcode":"07000",
    "sg:province":"Rhone-Alpes",
    "wof:name":"Giraud Delay S.a.",
    "wof:placetype":"venue"
},
  "geometry": {"coordinates":[4.59695,44.738419],"type":"Point"}
}