{
  "type": "Feature",
  "properties": {
    "addr:full":"Avenue De La Voulzie 77160 Provins Ile de France",
    "addr:postcode":"77160",
    "addr:street":"Avenue De La Voulzie",
    "iso:country":"FR",
    "sg:address":"Avenue De La Voulzie 77160 Provins",
    "sg:classifiers":[
        {
            "category":"Manufacturing",
            "subcategory":"Rubber & Plastics",
            "type":"Manufacturing & Wholesale Goods"
        }
    ],
    "sg:phone":"+33 1 64 00 08 06",
    "sg:province":"Ile de France",
    "sg:tags":[
        "packaging",
        "material",
        "-"
    ],
    "wof:name":"Lir France Sa",
    "wof:placetype":"venue"
},
  "geometry": {"coordinates":[3.293665,48.548962],"type":"Point"}
}