{
  "type": "Feature",
  "properties": {
    "addr:full":"Village 21250 PAGNY LE CHATEAU Villy-le-Moutier Bourgogne 21250",
    "addr:postcode":"21250;21250",
    "addr:street":"Pagny Le;Bourgogne",
    "iso:country":"FR",
    "sg:address":"Village 21250 PAGNY LE CHATEAU",
    "sg:city":"Villy-le-Moutier",
    "sg:classifiers":[
        {
            "category":"Building & Trades",
            "subcategory":"Plumbing",
            "type":"Services"
        }
    ],
    "sg:phone":"+33 3 80 36 30 60",
    "sg:postcode":"21250",
    "sg:province":"Bourgogne",
    "sg:tags":[
        "tub",
        "bath"
    ],
    "wof:name":"Sodim Sa",
    "wof:placetype":"venue"
},
  "geometry": {"coordinates":[5.147255,46.996616],"type":"Point"}
}