{
  "type": "Feature",
  "properties": {
    "addr:full":"Richemont 57270 RICHEMONT Lorraine 57270",
    "addr:postcode":"57270;57270",
    "iso:country":"FR",
    "sg:address":"Richemont 57270 RICHEMONT",
    "sg:classifiers":[
        {
            "category":"Retail",
            "subcategory":"Auto Repair",
            "type":"Services"
        }
    ],
    "sg:phone":"+33 3 87 71 83 60",
    "sg:postcode":"57270",
    "sg:province":"Lorraine",
    "sg:tags":[
        "machine",
        "equipment",
        "construction"
    ],
    "wof:name":"Timeca Sarl",
    "wof:placetype":"venue"
},
  "geometry": {"coordinates":[6.16624,49.279491],"type":"Point"}
}