{
  "type": "Feature",
  "properties": {
    "iso:country":"FR",
    "sg:address":"B.P. 14, 34741 Vendargues C\u00e9dex^^ZI, 34740 Vendargues",
    "sg:orig_category":"Non-Classified Establishments",
    "sg:phone":"+33 4 67 87 67 00",
    "sg:province":"Languedoc-Roussillon",
    "wof:name":"Sovatol S.a.",
    "wof:placetype":"venue"
},
  "geometry": {"coordinates":[3.968675,43.655514],"type":"Point"}
}