{
  "type": "Feature",
  "properties": {
    "iso:country":"FR",
    "sg:address":"5-7 avenue Marcellin Berthelot 92160 Antony",
    "sg:classifiers":[
        {
            "category":"Professional",
            "subcategory":"Engineering",
            "type":"Services"
        }
    ],
    "sg:phone":"+33 1 55 59 52 52",
    "sg:postcode":"92160",
    "sg:province":"Ile de France",
    "sg:tags":[
        "light",
        "technology",
        "guide",
        "illumination"
    ],
    "wof:name":"Euronano Sarl",
    "wof:placetype":"venue"
},
  "geometry": {"coordinates":[2.314333,48.735111],"type":"Point"}
}