{
  "type": "Feature",
  "properties": {
    "iso:country":"FR",
    "sg:address":"12 Place Audiffred",
    "sg:city":"Troyes",
    "sg:classifiers":[
        {
            "category":"Banks & Credit Unions",
            "subcategory":"Financial Services",
            "type":"Services"
        }
    ],
    "sg:phone":"+33 3 25 43 53 06",
    "sg:postcode":"10000",
    "sg:province":"Champagne",
    "sg:tags":[
        "banking",
        "finance",
        "insurance"
    ],
    "wof:name":"Credit Lyonnais",
    "wof:placetype":"venue"
},
  "geometry": {"coordinates":[4.071455,48.295666],"type":"Point"}
}