{
  "type": "Feature",
  "properties": {
    "iso:country":"FR",
    "sg:address":"88, Rue de la Hulotais, 35400 Saint Malo",
    "sg:city":"Saint-Malo",
    "sg:orig_category":"Unclassifiable Establishments",
    "sg:phone":"+33 2 99 56 06 06",
    "sg:postcode":"35400",
    "sg:province":"Bretagne",
    "wof:name":"Saint Malo Bus",
    "wof:placetype":"venue"
},
  "geometry": {"coordinates":[-1.990599,48.632019],"type":"Point"}
}