{
  "type": "Feature",
  "properties": {
    "addr:full":"rue de la Maison Rouge 37510 Ballan Mire Ballan-Mir\u00e9 Centre 37510",
    "addr:housenumber":"ballan-mire\u0301",
    "addr:postcode":"37510;37510",
    "addr:street":"Rue De La Maison Rouge",
    "iso:country":"FR",
    "sg:address":"rue de la Maison Rouge 37510 Ballan Mire",
    "sg:city":"Ballan-Mir\u00e9",
    "sg:classifiers":[
        {
            "category":"Farming",
            "subcategory":"Fish & Marine Products",
            "type":"Manufacturing & Wholesale Goods"
        }
    ],
    "sg:phone":"+33 2 47 73 65 65",
    "sg:postcode":"37510",
    "sg:province":"Centre",
    "sg:tags":[
        "bait"
    ],
    "wof:name":"Delalande Peche Sa",
    "wof:placetype":"venue"
},
  "geometry": {"coordinates":[0.600395,47.328991],"type":"Point"}
}