{
  "type": "Feature",
  "properties": {
    "iso:country":"FR",
    "sg:address":"488 rue d'Arques 76510 ST NICOLAS D ALIERMONT",
    "sg:classifiers":[
        {
            "category":"Government",
            "subcategory":"Department Of Motor Vehicles",
            "type":"Public Place"
        }
    ],
    "sg:phone":"+33 2 35 85 80 93",
    "sg:postcode":"76510",
    "sg:province":"Haute Normandie",
    "sg:tags":[
        "town",
        "citymobiles",
        "different",
        "drive",
        "kind"
    ],
    "wof:name":"A.m.a. Sa",
    "wof:placetype":"venue"
},
  "geometry": {"coordinates":[1.218625,49.880943],"type":"Point"}
}