{
  "type": "Feature",
  "properties": {
    "addr:full":"01115 Oyonnax Oyonnax Rhone-Alpes 01100",
    "addr:postcode":"01115;01100",
    "iso:country":"FR",
    "sg:address":"01115 Oyonnax",
    "sg:city":"Oyonnax",
    "sg:classifiers":[
        {
            "category":"Wholesale",
            "subcategory":"Construction Materials",
            "type":"Manufacturing & Wholesale Goods"
        }
    ],
    "sg:phone":"+33 4 74 77 23 95",
    "sg:postcode":"01100",
    "sg:province":"Rhone-Alpes",
    "sg:tags":[
        "mould",
        "injection"
    ],
    "wof:name":"Scrm Moules Sa",
    "wof:placetype":"venue"
},
  "geometry": {"coordinates":[5.65863,46.25827],"type":"Point"}
}