{
  "type": "Feature",
  "properties": {
    "iso:country":"FR",
    "sg:address":"All Yves Stoudz\u00e9 BP 4167 34092 Monpellier Cedex 05",
    "sg:classifiers":[
        {
            "category":"Professional",
            "subcategory":"Advertising",
            "type":"Services"
        }
    ],
    "sg:phone":"+33 4 67 14 44 44",
    "sg:province":"Picardie",
    "sg:tags":[
        "information",
        "medium",
        "communication"
    ],
    "wof:name":"Institut Audiovisuel Telecomm En Europe",
    "wof:placetype":"venue"
},
  "geometry": {"coordinates":[109.973579,29.06946],"type":"Point"}
}