{
  "type": "Feature",
  "properties": {
    "iso:country":"FR",
    "sg:address":"Av. Pierre Marzin",
    "sg:city":"Lannion",
    "sg:orig_category":"Unclassifiable Establishments",
    "sg:phone":"+33 2 96 05 63 00",
    "sg:postcode":"22300",
    "sg:province":"Bretagne",
    "wof:name":"Sagem S.a.",
    "wof:placetype":"venue"
},
  "geometry": {"coordinates":[-3.458589,48.75317],"type":"Point"}
}