{
  "type": "Feature",
  "properties": {
    "addr:full":"39 Chemin Des Mattefeux 72230 Arnage Pays de Loire 72230",
    "addr:housenumber":"39",
    "addr:postcode":"72230;72230",
    "addr:street":"Chemin Des Mattefeux",
    "iso:country":"FR",
    "sg:address":"39 Chemin Des Mattefeux 72230 Arnage",
    "sg:classifiers":[
        {
            "category":"Shopping",
            "subcategory":"Clothing, Apparel, & Fashions",
            "type":"Retail Goods"
        }
    ],
    "sg:phone":"+33 2 43 21 34 01",
    "sg:postcode":"72230",
    "sg:province":"Pays de Loire",
    "sg:tags":[
        "textile",
        "clothing",
        "clothes"
    ],
    "wof:name":"Mulliez Uniforme",
    "wof:placetype":"venue"
},
  "geometry": {"coordinates":[0.178012,47.918102],"type":"Point"}
}