{
  "type": "Feature",
  "properties": {
    "addr:full":"Le Vieux Cr\u00e9zin 87220 Feytiat Limousin",
    "addr:postcode":"87220",
    "iso:country":"FR",
    "sg:address":"Le Vieux Cr\u00e9zin 87220 Feytiat",
    "sg:orig_category":"Unclassifiable Establishments",
    "sg:phone":"+33 5 55 30 55 41",
    "sg:province":"Limousin",
    "wof:name":"Madrange S.a.",
    "wof:placetype":"venue"
},
  "geometry": {"coordinates":[1.310471,45.813766],"type":"Point"}
}