{
  "type": "Feature",
  "properties": {
    "iso:country":"FR",
    "sg:address":"Chemin du Parc - ZI",
    "sg:city":"Pierrelaye",
    "sg:orig_category":"Unclassifiable Establishments",
    "sg:phone":"+33 1 30 40 00 25",
    "sg:postcode":"95480",
    "sg:province":"Ile de France",
    "wof:name":"Cardinal S.a.",
    "wof:placetype":"venue"
},
  "geometry": {"coordinates":[2.156565,49.022736],"type":"Point"}
}