{
  "type": "Feature",
  "properties": {
    "iso:country":"FR",
    "sg:address":"Av Marcelin Berthelot - ZAC de Merci\u00e8res",
    "sg:city":"Compi\u00e8gne",
    "sg:orig_category":"Unclassifiable Establishments",
    "sg:phone":"+33 3 44 23 08 22",
    "sg:postcode":"60200",
    "sg:province":"Picardie",
    "wof:name":"Techstar S.a.",
    "wof:placetype":"venue"
},
  "geometry": {"coordinates":[2.790159,49.393097],"type":"Point"}
}