{
  "type": "Feature",
  "properties": {
    "addr:full":"B.P. 90202, 57506 Saint Avold C\u00e9dex^^ZI du Gros H\u00eatre, 57500 Saint Avold Lorraine",
    "addr:housenumber":"57506",
    "addr:postcode":"57500",
    "addr:street":"Saint Avold Ce\u0301Dex^^Zi Du Gros He\u0302Tre;Avold",
    "iso:country":"FR",
    "sg:address":"B.P. 90202, 57506 Saint Avold C\u00e9dex^^ZI du Gros H\u00eatre, 57500 Saint Avold",
    "sg:orig_category":"Non-Classified Establishments",
    "sg:phone":"+33 3 87 91 33 89",
    "sg:province":"Lorraine",
    "wof:name":"S.m.l. S.a. - Soci\u00e9t\u00e9 De Manutention Et De Levage",
    "wof:placetype":"venue"
},
  "geometry": {"coordinates":[6.705505,49.104275],"type":"Point"}
}