{
  "type": "Feature",
  "properties": {
    "iso:country":"FR",
    "sg:address":"B.P. 46, 84232 Ch\u00e2teauneuf du Pape C\u00e9dex^^Av. Pasteur, 84230 Ch\u00e2teauneuf du Pape",
    "sg:orig_category":"Non-Classified Establishments",
    "sg:phone":"+33 4 90 83 70 57",
    "sg:province":"Midi Pyr\u00e9n\u00e9es",
    "wof:name":"Domaine Chante Cigale S.a.",
    "wof:placetype":"venue"
},
  "geometry": {"coordinates":[4.835999,44.049744],"type":"Point"}
}