{
  "type": "Feature",
  "properties": {
    "addr:full":"Ld Les Touches 37173 Chambray L\u00e8s Tours Champagne",
    "addr:postcode":"37173",
    "addr:street":"Ld",
    "iso:country":"FR",
    "sg:address":"Ld Les Touches 37173 Chambray L\u00e8s Tours",
    "sg:classifiers":[
        {
            "category":"Professional",
            "type":"Services"
        }
    ],
    "sg:phone":"+33 2 47 25 23 00",
    "sg:province":"Champagne",
    "sg:tags":[
        "transport",
        "road"
    ],
    "wof:name":"Cofiroute",
    "wof:placetype":"venue"
},
  "geometry": {"coordinates":[0.692525,47.33366],"type":"Point"}
}