{
  "type": "Feature",
  "properties": {
    "addr:full":"630, Rte des Artisans, 40200 Aureilhan Aureilhan Aquitaine 40200",
    "addr:housenumber":"630",
    "addr:postcode":"40200;40200",
    "addr:street":"Rte Des Artisans",
    "iso:country":"FR",
    "sg:address":"630, Rte des Artisans, 40200 Aureilhan",
    "sg:city":"Aureilhan",
    "sg:orig_category":"Unclassifiable Establishments",
    "sg:phone":"+33 5 58 82 40 56",
    "sg:postcode":"40200",
    "sg:province":"Aquitaine",
    "wof:name":"S.e.e.f. S.a.r.l.",
    "wof:placetype":"venue"
},
  "geometry": {"coordinates":[-1.193129,44.212605],"type":"Point"}
}