{
  "type": "Feature",
  "properties": {
    "iso:country":"FR",
    "sg:address":"12 Avenue Robert Schuman",
    "sg:city":"Metz",
    "sg:classifiers":[
        {
            "category":"Banks & Credit Unions",
            "subcategory":"Financial Services",
            "type":"Services"
        }
    ],
    "sg:phone":"+33 3 87 39 94 00",
    "sg:postcode":"57000",
    "sg:province":"Lorraine",
    "sg:tags":[
        "banking",
        "finance",
        "insurance"
    ],
    "wof:name":"Banque De France",
    "wof:placetype":"venue"
},
  "geometry": {"coordinates":[6.173089,49.114342],"type":"Point"}
}