{
  "type": "Feature",
  "properties": {
    "addr:full":"15 bis, Rte de Bessi\u00e8res, 31240 L'union Midi Pyr\u00e9n\u00e9es",
    "addr:housenumber":"15 bis",
    "addr:postcode":"31240",
    "addr:street":"Rte De Bessie\u0300Res",
    "iso:country":"FR",
    "sg:address":"15 bis, Rte de Bessi\u00e8res, 31240 L'union",
    "sg:orig_category":"Unclassifiable Establishments",
    "sg:phone":"+33 5 61 74 90 35",
    "sg:province":"Midi Pyr\u00e9n\u00e9es",
    "wof:name":"Amys S.a.r.l.",
    "wof:placetype":"venue"
},
  "geometry": {"coordinates":[-87.905098,32.996254],"type":"Point"}
}