{
  "type": "Feature",
  "properties": {
    "iso:country":"FR",
    "sg:address":"8, Rue de Douvieux, 80200 Monchy Lagache",
    "sg:orig_category":"Non-Classified Establishments",
    "sg:phone":"+33 3 22 85 63 28",
    "sg:province":"Picardie",
    "wof:name":"Les Plastiques De Mitry S.a.r.l.",
    "wof:placetype":"venue"
},
  "geometry": {"coordinates":[3.044239,49.847599],"type":"Point"}
}