{
  "type": "Feature",
  "properties": {
    "iso:country":"FR",
    "sg:address":"2 Pl Fran\u00e7ois Mireur Immeuble Communica 13001 Marseille",
    "sg:classifiers":[
        {
            "category":"Professional",
            "subcategory":"Advertising",
            "type":"Services"
        }
    ],
    "sg:phone":"+33 4 91 14 34 34",
    "sg:province":"Poitou-Charentes",
    "sg:tags":[
        "communication",
        "medium"
    ],
    "wof:name":"Regie Networks Sud Est Sa",
    "wof:placetype":"venue"
},
  "geometry": {"coordinates":[5.376155,43.298923],"type":"Point"}
}