{
  "type": "Feature",
  "properties": {
    "addr:full":"14/16, Rue de Miromesnil, 75008 Paris Ile de France",
    "addr:housenumber":"14 / 16",
    "addr:postcode":"75008",
    "addr:street":"Rue De Miromesnil",
    "iso:country":"FR",
    "sg:address":"14/16, Rue de Miromesnil, 75008 Paris",
    "sg:orig_category":"Unclassifiable Establishments",
    "sg:phone":"+33 1 53 05 06 07",
    "sg:province":"Ile de France",
    "wof:name":"Coty France S.a.",
    "wof:placetype":"venue"
},
  "geometry": {"coordinates":[2.316236,48.872189],"type":"Point"}
}