{
  "type": "Feature",
  "properties": {
    "addr:full":"29, Rue Joseph Cugnot - ZI n\u00b0 2, 37300 Jou\u00e9 l\u00e8s Tours Jou\u00e9-l\u00e8s-Tours Centre 37300",
    "addr:housenumber":"29;n\u00b0 2",
    "addr:postcode":"37300;37300",
    "addr:street":"Rue Joseph Cugnot Zi",
    "iso:country":"FR",
    "sg:address":"29, Rue Joseph Cugnot - ZI n\u00b0 2, 37300 Jou\u00e9 l\u00e8s Tours",
    "sg:city":"Jou\u00e9-l\u00e8s-Tours",
    "sg:orig_category":"Unclassifiable Establishments",
    "sg:phone":"+33 2 47 53 84 11",
    "sg:postcode":"37300",
    "sg:province":"Centre",
    "wof:name":"Carty S.a.",
    "wof:placetype":"venue"
},
  "geometry": {"coordinates":[0.662555,47.350945],"type":"Point"}
}