{
  "type": "Feature",
  "properties": {
    "addr:full":"470 avenue de Lossbourg 69480 Anse Rhone-Alpes",
    "addr:housenumber":"470",
    "addr:postcode":"69480",
    "addr:street":"Avenue De Lossbourg",
    "iso:country":"FR",
    "sg:address":"470 avenue de Lossbourg 69480 Anse",
    "sg:classifiers":[
        {
            "category":"Retail",
            "subcategory":"Car Wash",
            "type":"Services"
        }
    ],
    "sg:phone":"+33 4 74 09 97 00",
    "sg:province":"Rhone-Alpes",
    "sg:tags":[
        "oil",
        "essential"
    ],
    "wof:name":"Laboratoires Saint Benoit - Heuprophax Sa",
    "wof:placetype":"venue"
},
  "geometry": {"coordinates":[4.716361,45.947392],"type":"Point"}
}