{
  "type": "Feature",
  "properties": {
    "iso:country":"FR",
    "sg:address":"15, Rue de la Gravelle - Sorendal, 08800 Les Hautes Rivi\u00e8res",
    "sg:city":"Deville",
    "sg:orig_category":"Boulonnerie Estampage de m\u00e9taux Forge",
    "sg:phone":"+33 3 24 54 22 74",
    "sg:postcode":"08800",
    "sg:province":"Champagne",
    "wof:name":"Wap S.a.r.l.",
    "wof:placetype":"venue"
},
  "geometry": {"coordinates":[4.767382,49.882172],"type":"Point"}
}