{
  "type": "Feature",
  "properties": {
    "addr:full":"2 B Rue De La Fraternelle 69009 Lyon Rhone-Alpes 69009",
    "addr:housenumber":"2 b",
    "addr:postcode":"69009;69009",
    "addr:street":"Rue De La Fraternelle",
    "iso:country":"FR",
    "sg:address":"2 B Rue De La Fraternelle 69009 Lyon",
    "sg:classifiers":[
        {
            "category":"Professional",
            "subcategory":"Printing & Photocopies",
            "type":"Services"
        }
    ],
    "sg:phone":"+33 4 72 85 37 00",
    "sg:postcode":"69009",
    "sg:province":"Rhone-Alpes",
    "sg:tags":[
        "publishing"
    ],
    "wof:name":"Lyon Mag",
    "wof:placetype":"venue"
},
  "geometry": {"coordinates":[4.80332,45.769604],"type":"Point"}
}