{
  "type": "Feature",
  "properties": {
    "addr:full":"34 Rue Claude Henri Gorceix 87280 Limoges Limousin",
    "addr:housenumber":"34",
    "addr:postcode":"87280",
    "addr:street":"Rue Claude Henri Gorceix",
    "iso:country":"FR",
    "sg:address":"34 Rue Claude Henri Gorceix 87280 Limoges",
    "sg:classifiers":[
        {
            "category":"Manufacturing",
            "subcategory":"Printing",
            "type":"Manufacturing & Wholesale Goods"
        }
    ],
    "sg:phone":"+33 5 55 37 88 26",
    "sg:province":"Limousin",
    "sg:tags":[
        "publishing"
    ],
    "wof:name":"Sofrimap Laucournet Sa",
    "wof:placetype":"venue"
},
  "geometry": {"coordinates":[1.288478,45.886913],"type":"Point"}
}