{
  "type": "Feature",
  "properties": {
    "addr:full":"270, Rue du Faubourg Croncels, 10042 Troyes C\u00e9dex Champagne-Ardenne",
    "addr:housenumber":"270",
    "addr:postcode":"10042",
    "addr:street":"Rue Du Faubourg Croncels",
    "iso:country":"FR",
    "sg:address":"270, Rue du Faubourg Croncels, 10042 Troyes C\u00e9dex",
    "sg:orig_category":"Non-Classified Establishments",
    "sg:phone":"+33 3 20 19 74 00",
    "sg:province":"Champagne-Ardenne",
    "wof:name":"I.f.t.h. S.a. - Institut Fran\u00e7ais Du Textile Et De L'habillement",
    "wof:placetype":"venue"
},
  "geometry": {"coordinates":[4.081867,48.277939],"type":"Point"}
}