{
  "type": "Feature",
  "properties": {
    "iso:country":"FR",
    "sg:address":"19, Rue du Cadran Saint Pierre, 51100 Reims",
    "sg:orig_category":"Unclassifiable Establishments",
    "sg:phone":"+33 3 26 50 55 59",
    "sg:province":"Champagne",
    "wof:name":"Contact Distribution S.a.r.l.",
    "wof:placetype":"venue"
},
  "geometry": {"coordinates":[4.02896,49.25568],"type":"Point"}
}