{
  "type": "Feature",
  "properties": {
    "addr:full":"61, Rue Denis Papin, 72000 Le Mans Pays de Loire",
    "addr:housenumber":"61",
    "addr:postcode":"72000",
    "addr:street":"Rue Denis Papin",
    "iso:country":"FR",
    "sg:address":"61, Rue Denis Papin, 72000 Le Mans",
    "sg:orig_category":"Unclassifiable Establishments",
    "sg:phone":"+33 2 43 50 55 55",
    "sg:province":"Pays de Loire",
    "wof:name":"C.m.e.n. S.a.s. - Comptoirs Modernes Economiques De Normandie",
    "wof:placetype":"venue"
},
  "geometry": {"coordinates":[0.200731,47.977783],"type":"Point"}
}