{
  "type": "Feature",
  "properties": {
    "addr:full":"5 R Des Entrepreneurs 95210 Saint Gratien Ile de France 95210",
    "addr:housenumber":"5",
    "addr:postcode":"95210;95210",
    "addr:street":"R Des Entrepreneurs",
    "iso:country":"FR",
    "sg:address":"5 R Des Entrepreneurs 95210 Saint Gratien",
    "sg:classifiers":[
        {
            "category":"Home & Garden",
            "subcategory":"Furniture",
            "type":"Retail Goods"
        }
    ],
    "sg:phone":"+33 1 34 12 75 00",
    "sg:postcode":"95210",
    "sg:province":"Ile de France",
    "sg:tags":[
        "household",
        "wood"
    ],
    "wof:name":"Anglo Trench Trading Compagnie",
    "wof:placetype":"venue"
},
  "geometry": {"coordinates":[2.277179,48.969917],"type":"Point"}
}