{
  "type": "Feature",
  "properties": {
    "iso:country":"FR",
    "sg:address":"8, rue Denis Papin - ZI Nord Est, 51100 Reims",
    "sg:orig_category":"Non-Classified Establishments",
    "sg:phone":"+33 3 26 02 36 36",
    "sg:postcode":"51100",
    "sg:province":"Champagne",
    "wof:name":"Champagne Textile S.a.r.l.",
    "wof:placetype":"venue"
},
  "geometry": {"coordinates":[4.028445,49.26284],"type":"Point"}
}