{
  "type": "Feature",
  "properties": {
    "addr:full":"01400 Condeissiat Rhone-Alpes 01400",
    "addr:postcode":"01400;01400",
    "addr:street":"Rhone-Alpes",
    "iso:country":"FR",
    "sg:address":"01400 Condeissiat",
    "sg:orig_category":"Unclassifiable Establishments",
    "sg:phone":"+33 4 74 51 41 59",
    "sg:postcode":"01400",
    "sg:province":"Rhone-Alpes",
    "wof:name":"Chavagnat-muzy S.a.r.l.",
    "wof:placetype":"venue"
},
  "geometry": {"coordinates":[5.079535,46.157829],"type":"Point"}
}