{
  "type": "Feature",
  "properties": {
    "addr:full":"58, Bd Pierre Curie, 31200 Toulouse Midi Pyr\u00e9n\u00e9es",
    "addr:housenumber":"58",
    "addr:postcode":"31200",
    "addr:street":"Bd Pierre Curie",
    "iso:country":"FR",
    "sg:address":"58, Bd Pierre Curie, 31200 Toulouse",
    "sg:orig_category":"Unclassifiable Establishments",
    "sg:phone":"+33 5 61 47 54 82",
    "sg:province":"Midi Pyr\u00e9n\u00e9es",
    "wof:name":"Laho Equipement S.a.",
    "wof:placetype":"venue"
},
  "geometry": {"coordinates":[1.445093,43.618431],"type":"Point"}
}