{
  "type": "Feature",
  "properties": {
    "iso:country":"FR",
    "sg:address":"57 Quai De La Tournelle 75005 Paris",
    "sg:classifiers":[
        {
            "category":"Professional",
            "subcategory":"Business Services",
            "type":"Services"
        }
    ],
    "sg:phone":"+33 1 55 42 60 00",
    "sg:postcode":"75005",
    "sg:province":"Ile de France",
    "sg:tags":[
        "body",
        "advice"
    ],
    "wof:name":"La Demeure Historique",
    "wof:placetype":"venue"
},
  "geometry": {"coordinates":[2.351409,48.850967],"type":"Point"}
}