{
  "type": "Feature",
  "properties": {
    "addr:full":"chemin Cr\u00e8ve Coeur 10380 PLANCY L ABBAYE Champagne 10380",
    "addr:postcode":"10380;10380",
    "addr:street":"Chemin Cre\u0300Ve Coeur;Champagne",
    "iso:country":"FR",
    "sg:address":"chemin Cr\u00e8ve Coeur 10380 PLANCY L ABBAYE",
    "sg:classifiers":[
        {
            "category":"Personal",
            "subcategory":"Skin Care",
            "type":"Services"
        }
    ],
    "sg:phone":"+33 3 25 37 70 00",
    "sg:postcode":"10380",
    "sg:province":"Champagne",
    "sg:tags":[
        "cloths",
        "bandage",
        "triangular",
        "dressing"
    ],
    "wof:name":"Lohmann & Rauscher Sa",
    "wof:placetype":"venue"
},
  "geometry": {"coordinates":[3.970565,48.57386],"type":"Point"}
}