{
  "type": "Feature",
  "properties": {
    "addr:full":"44, Av. de Paris, 79320 Montcoutant Poitou-Charentes 79320",
    "addr:postcode":"79320;79320",
    "addr:street":"44 Av. De Paris;Montcoutant",
    "iso:country":"FR",
    "sg:address":"44, Av. de Paris, 79320 Montcoutant",
    "sg:orig_category":"Unclassifiable Establishments",
    "sg:phone":"+33 5 49 72 71 51",
    "sg:postcode":"79320",
    "sg:province":"Poitou-Charentes",
    "wof:name":"Sourice S.a.",
    "wof:placetype":"venue"
},
  "geometry": {"coordinates":[-0.618819,46.673008],"type":"Point"}
}