{
  "type": "Feature",
  "properties": {
    "iso:country":"FR",
    "sg:address":"64 rue Neuve d'Argenson; Bergerac; 24100",
    "sg:city":"Bergerac",
    "sg:classifiers":[
        {
            "category":"Banks & Credit Unions",
            "subcategory":"Bank",
            "type":"Services"
        }
    ],
    "sg:phone":"+33 3353571409",
    "sg:postcode":"24100",
    "sg:province":"Aquitaine",
    "wof:name":"Soci\u00e9t\u00e9 G\u00e9n\u00e9rale",
    "wof:placetype":"venue"
},
  "geometry": {"coordinates":[0.485061,44.851009],"type":"Point"}
}