{
  "type": "Feature",
  "properties": {
    "iso:country":"FR",
    "sg:address":"Bd Des Dr. Cheverel BP 104 44502 La Baule",
    "sg:classifiers":[
        {
            "category":"Autos & Motor Vehicles",
            "subcategory":"Automobile Sales",
            "type":"Retail Goods"
        }
    ],
    "sg:phone":"+33 2 40 60 20 30",
    "sg:province":"Centre",
    "sg:tags":[
        "equipment",
        "motor-cars",
        "transport"
    ],
    "wof:name":"Societe Des Garages Richard",
    "wof:placetype":"venue"
},
  "geometry": {"coordinates":[-2.39136,47.286991],"type":"Point"}
}