{
  "type": "Feature",
  "properties": {
    "addr:full":"184 Rue Joseph Aubenas 83600 Frejus Basse Normandie",
    "addr:housenumber":"184",
    "addr:postcode":"83600",
    "addr:street":"Rue Joseph Aubenas",
    "iso:country":"FR",
    "sg:address":"184 Rue Joseph Aubenas 83600 Frejus",
    "sg:classifiers":[
        {
            "category":"Manufacturing",
            "subcategory":"Metals",
            "type":"Manufacturing & Wholesale Goods"
        }
    ],
    "sg:phone":"+33 4 94 40 11 03",
    "sg:province":"Basse Normandie",
    "sg:tags":[
        "metallurgy",
        "-",
        "metalworking",
        "metallic",
        "machine",
        "engineering",
        "finished",
        "mechanical"
    ],
    "wof:name":"Brossette Bti",
    "wof:placetype":"venue"
},
  "geometry": {"coordinates":[6.735332,43.434631],"type":"Point"}
}