{
  "type": "Feature",
  "properties": {
    "addr:full":"Bel Air Decazeville 12000 Rodez Midi Pyr\u00e9n\u00e9es 12000",
    "addr:postcode":"12000;12000",
    "iso:country":"FR",
    "sg:address":"Bel Air",
    "sg:city":"Decazeville 12000 Rodez",
    "sg:classifiers":[
        {
            "category":"Wholesale",
            "subcategory":"Farm Supplies",
            "type":"Manufacturing & Wholesale Goods"
        }
    ],
    "sg:phone":"+33 5 65 42 20 03",
    "sg:postcode":"12000",
    "sg:province":"Midi Pyr\u00e9n\u00e9es",
    "sg:tags":[
        "-",
        "machine",
        "equipment",
        "engineering",
        "machinery",
        "mechanical",
        "agriculture"
    ],
    "wof:name":"Espace Emeraude Rodima Franchise Independant",
    "wof:placetype":"venue"
},
  "geometry": {"coordinates":[2.54251,44.375561],"type":"Point"}
}