{
  "type": "Feature",
  "properties": {
    "iso:country":"FR",
    "sg:address":"8, Rue du Printemps, 44700 Orvault",
    "sg:orig_category":"Unclassifiable Establishments",
    "sg:phone":"+33 2 40 76 40 35",
    "sg:province":"Pays de Loire",
    "wof:name":"Ablain Gilbert S.a.r.l.",
    "wof:placetype":"venue"
},
  "geometry": {"coordinates":[-1.585489,47.261269],"type":"Point"}
}