{
  "type": "Feature",
  "properties": {
    "iso:country":"FR",
    "sg:address":"3, Rue Henri Becquerel, 33700 M\u00e9rignac",
    "sg:city":"M\u00e9rignac",
    "sg:orig_category":"Non-Classified Establishments",
    "sg:phone":"+33 5 57 92 26 60",
    "sg:postcode":"33700",
    "sg:province":"Aquitaine",
    "wof:name":"G2p G.i.e.",
    "wof:placetype":"venue"
},
  "geometry": {"coordinates":[-0.69414,44.836437],"type":"Point"}
}