{
  "type": "Feature",
  "properties": {
    "iso:country":"FR",
    "sg:address":"2 Rue Migneville 54450 Herbeviller",
    "sg:classifiers":[
        {
            "category":"Food & Beverages",
            "subcategory":"Dairy",
            "type":"Retail Goods"
        }
    ],
    "sg:phone":"+33 3 83 72 27 08",
    "sg:postcode":"54450",
    "sg:province":"Lorraine",
    "sg:tags":[
        "product",
        "related"
    ],
    "wof:name":"Cooperative Laitiere De Blamont",
    "wof:placetype":"venue"
},
  "geometry": {"coordinates":[6.752732,48.555107],"type":"Point"}
}