{
  "type": "Feature",
  "properties": {
    "iso:country":"FR",
    "sg:address":"rue Vavin",
    "sg:city":"Paris",
    "sg:classifiers":[
        {
            "category":"Professional",
            "subcategory":"Computer Services",
            "type":"Services"
        }
    ],
    "sg:postcode":"75006",
    "sg:tags":[
        "realestate",
        "real-estate",
        "immobilier",
        "immobilio"
    ],
    "sg:website":"http://www.immobilio.com",
    "wof:name":"Immobilio",
    "wof:placetype":"venue"
},
  "geometry": {"coordinates":[2.331507,48.84441],"type":"Point"}
}