{
  "type": "Feature",
  "properties": {
    "addr:full":"Zi Les Lanches R Marvays 74300 Thyez Rhone-Alpes 74300",
    "addr:postcode":"74300;74300",
    "addr:street":"Zi;Rhone-Alpes",
    "iso:country":"FR",
    "sg:address":"Zi Les Lanches",
    "sg:city":"R Marvays 74300 Thyez",
    "sg:orig_category":"Business advice and other services Measurement - equipment and instruments Mechanical Engineering - ",
    "sg:phone":"+33 4 50 98 59 30",
    "sg:postcode":"74300",
    "sg:province":"Rhone-Alpes",
    "wof:name":"Ste Florenza Sa",
    "wof:placetype":"venue"
},
  "geometry": {"coordinates":[6.527876,46.083324],"type":"Point"}
}