{
  "type": "Feature",
  "properties": {
    "iso:country":"FR",
    "sg:address":"43 rue Roger Salengro; Isbergues; 62330",
    "sg:classifiers":[
        {
            "category":"Banks & Credit Unions",
            "subcategory":"Bank",
            "type":"Services"
        }
    ],
    "sg:phone":"+33 21021676",
    "sg:postcode":"62330",
    "sg:province":"Nord Pas-de-Calais",
    "wof:name":"Soci\u00e9t\u00e9 G\u00e9n\u00e9rale",
    "wof:placetype":"venue"
},
  "geometry": {"coordinates":[2.470965,50.619049],"type":"Point"}
}