{
  "type": "Feature",
  "properties": {
    "addr:full":"19, Rue du Faubourg de Neaufles, 27140 Gisors Haute Normandie",
    "addr:housenumber":"19",
    "addr:postcode":"27140",
    "addr:street":"Rue Du Faubourg De Neaufles;Haute Normandie",
    "iso:country":"FR",
    "sg:address":"19, Rue du Faubourg de Neaufles, 27140 Gisors",
    "sg:orig_category":"Unclassifiable Establishments",
    "sg:phone":"+33 2 32 55 24 01",
    "sg:province":"Haute Normandie",
    "wof:name":"Etablissements Ferret Jean S.a.r.l.",
    "wof:placetype":"venue"
},
  "geometry": {"coordinates":[1.769046,49.278278],"type":"Point"}
}