{
  "type": "Feature",
  "properties": {
    "addr:full":"B.P. 1567, 80015 Amiens C\u00e9dex 2^^Rue du Fief, 80000 Amiens Picardie 80000",
    "addr:housenumber":"1567",
    "addr:postcode":"80015;80000;80000",
    "addr:street":"B.P.",
    "iso:country":"FR",
    "sg:address":"B.P. 1567, 80015 Amiens C\u00e9dex 2^^Rue du Fief, 80000 Amiens",
    "sg:orig_category":"Non-Classified Establishments",
    "sg:phone":"+33 3 22 54 31 90",
    "sg:postcode":"80000",
    "sg:province":"Picardie",
    "wof:name":"Dubois Edouard Et Fils Transports S.a.",
    "wof:placetype":"venue"
},
  "geometry": {"coordinates":[2.293165,49.894733],"type":"Point"}
}