{
  "type": "Feature",
  "properties": {
    "addr:full":"Rue Cardabelles 12340 Bozouls Midi Pyr\u00e9n\u00e9es 12340",
    "addr:postcode":"12340;12340",
    "addr:street":"Rue Cardabelles",
    "iso:country":"FR",
    "sg:address":"Rue Cardabelles 12340 Bozouls",
    "sg:classifiers":[
        {
            "category":"Home & Garden",
            "subcategory":"Furniture",
            "type":"Retail Goods"
        }
    ],
    "sg:phone":"+33 5 65 44 90 42",
    "sg:postcode":"12340",
    "sg:province":"Midi Pyr\u00e9n\u00e9es",
    "sg:tags":[
        "household",
        "wood"
    ],
    "wof:name":"Societe Nouvelle Des Etablissements Lacroix",
    "wof:placetype":"venue"
},
  "geometry": {"coordinates":[2.727057,44.47179],"type":"Point"}
}