{
  "type": "Feature",
  "properties": {
    "addr:full":"B.P. 23, 13560 Senas^^Chemin du Pigeonnier, 13560 Senas Provence-Alpes-C\u00f4te d'Azur",
    "addr:postcode":"13560;13560",
    "addr:street":"B.P. 23;Pigeonnier;Senas",
    "iso:country":"FR",
    "sg:address":"B.P. 23, 13560 Senas^^Chemin du Pigeonnier, 13560 Senas",
    "sg:orig_category":"Non-Classified Establishments",
    "sg:phone":"+33 4 90 59 22 90",
    "sg:province":"Provence-Alpes-C\u00f4te d'Azur",
    "wof:name":"Lamprien Provence S.a.r.l.",
    "wof:placetype":"venue"
},
  "geometry": {"coordinates":[5.078521,43.74268],"type":"Point"}
}