{
  "type": "Feature",
  "properties": {
    "addr:full":"8, Rue de Cassel, 59270 Bailleul Nord Pas-de-Calais",
    "addr:housenumber":"8",
    "addr:postcode":"59270",
    "addr:street":"Rue De Cassel",
    "iso:country":"FR",
    "sg:address":"8, Rue de Cassel, 59270 Bailleul",
    "sg:orig_category":"Unclassifiable Establishments",
    "sg:phone":"+33 3 28 44 04 30",
    "sg:province":"Nord Pas-de-Calais",
    "wof:name":"A.n.p.e. De Bailleul-merville",
    "wof:placetype":"venue"
},
  "geometry": {"coordinates":[2.730525,50.738232],"type":"Point"}
}