{
  "type": "Feature",
  "properties": {
    "addr:full":"132, Rue Antonin Reynaud, 92300 Levallois Perret Ile de France",
    "addr:housenumber":"132",
    "addr:postcode":"92300;ile",
    "addr:street":"Rue Antonin Reynaud;France",
    "iso:country":"FR",
    "sg:address":"132, Rue Antonin Reynaud, 92300 Levallois Perret",
    "sg:orig_category":"Non-Classified Establishments",
    "sg:phone":"+33 1 55 63 82 01",
    "sg:province":"Ile de France",
    "wof:name":"Publicit\u00e9 Claude Michel S.a.",
    "wof:placetype":"venue"
},
  "geometry": {"coordinates":[2.28301,48.895821],"type":"Point"}
}