{
  "type": "Feature",
  "properties": {
    "iso:country":"FR",
    "sg:address":"Rte De Sepmes 37800 Ste Maure De Touraine",
    "sg:city":"Sepmes",
    "sg:classifiers":[
        {
            "category":"Sports & Exercise",
            "subcategory":"Sports Center",
            "type":"Entertainment"
        }
    ],
    "sg:phone":"+33 2 47 65 41 61",
    "sg:postcode":"37800",
    "sg:province":"Centre",
    "sg:tags":[
        "product",
        "game",
        "miscellaneous"
    ],
    "wof:name":"Ets Garbolino Sa",
    "wof:placetype":"venue"
},
  "geometry": {"coordinates":[0.615235,47.107182],"type":"Point"}
}