{
  "type": "Feature",
  "properties": {
    "addr:full":"5 Boulevard Carnot Argentan Basse Normandie 61200",
    "addr:housenumber":"5",
    "addr:postcode":"61200",
    "addr:street":"Boulevard Carnot;Basse",
    "iso:country":"FR",
    "sg:address":"5 Boulevard Carnot",
    "sg:city":"Argentan",
    "sg:classifiers":[
        {
            "category":"Banks & Credit Unions",
            "subcategory":"Financial Services",
            "type":"Services"
        }
    ],
    "sg:phone":"+33 2 33 67 08 27",
    "sg:postcode":"61200",
    "sg:province":"Basse Normandie",
    "sg:tags":[
        "banking",
        "finance",
        "insurance"
    ],
    "wof:name":"Societe Fiduciaire Nationale D'expertise Comptable Fidexpert (fid)",
    "wof:placetype":"venue"
},
  "geometry": {"coordinates":[-0.024462,48.739346],"type":"Point"}
}