{
  "type": "Feature",
  "properties": {
    "addr:full":"B.P. 20422, 57954 Montigny l\u00e8s Metz C\u00e9dex^^25, Rue de Nom\u00e9ny, 57950 Montigny l\u00e8s Metz Ile de France",
    "addr:housenumber":"57954",
    "addr:postcode":"57950",
    "addr:street":"Rue De Nome\u0301Ny",
    "iso:country":"FR",
    "sg:address":"B.P. 20422, 57954 Montigny l\u00e8s Metz C\u00e9dex^^25, Rue de Nom\u00e9ny, 57950 Montigny l\u00e8s Metz",
    "sg:orig_category":"Non-Classified Establishments",
    "sg:phone":"+33 3 87 66 60 22",
    "sg:province":"Ile de France",
    "wof:name":"T\u00e9l\u00e9phonie Mosellane S.a.",
    "wof:placetype":"venue"
},
  "geometry": {"coordinates":[6.15241,49.099918],"type":"Point"}
}