{
  "type": "Feature",
  "properties": {
    "addr:full":"19 quai du Moulin de Cage 92230 Gennevilliers Ile de France 92230",
    "addr:housenumber":"19",
    "addr:postcode":"92230;ile;92230",
    "addr:street":"Quai Du Moulin De Cage;France",
    "iso:country":"FR",
    "sg:address":"19 quai du Moulin de Cage 92230 Gennevilliers",
    "sg:classifiers":[
        {
            "category":"Professional",
            "subcategory":"Advertising",
            "type":"Services"
        }
    ],
    "sg:phone":"+33 1 40 80 53 80",
    "sg:postcode":"92230",
    "sg:province":"Ile de France",
    "sg:tags":[
        "illuminated"
    ],
    "wof:name":"Jc Decaux Publicit\u00e9 Lumineuse Sa",
    "wof:placetype":"venue"
},
  "geometry": {"coordinates":[2.327391,48.922997],"type":"Point"}
}