{
  "type": "Feature",
  "properties": {
    "addr:full":"Centre Routier 79260 La Cr\u00e8che Poitou-Charentes",
    "addr:postcode":"79260",
    "addr:street":"La Cre\u0300Che",
    "iso:country":"FR",
    "sg:address":"Centre Routier 79260 La Cr\u00e8che",
    "sg:orig_category":"Unclassifiable Establishments",
    "sg:phone":"+33 5 49 05 36 50",
    "sg:province":"Poitou-Charentes",
    "wof:name":"Atlantal S.a.",
    "wof:placetype":"venue"
},
  "geometry": {"coordinates":[-0.299454,46.36187],"type":"Point"}
}