{
  "type": "Feature",
  "properties": {
    "addr:full":"Rue Industrie 01460 Port Rhone-Alpes 01460",
    "addr:postcode":"01460;01460",
    "addr:street":"Rue Industrie",
    "iso:country":"FR",
    "sg:address":"Rue Industrie 01460 Port",
    "sg:classifiers":[
        {
            "category":"Manufacturing",
            "subcategory":"Rubber & Plastics",
            "type":"Manufacturing & Wholesale Goods"
        }
    ],
    "sg:phone":"+33 4 74 76 07 41",
    "sg:postcode":"01460",
    "sg:province":"Rhone-Alpes",
    "wof:name":"Plastiques Industriels De Port Sa",
    "wof:placetype":"venue"
},
  "geometry": {"coordinates":[5.570441,46.165977],"type":"Point"}
}