{
  "type": "Feature",
  "properties": {
    "iso:country":"FR",
    "sg:address":"Zi Le Voyen 88550 Pouxeux",
    "sg:classifiers":[
        {
            "category":"Home & Garden",
            "subcategory":"Furniture",
            "type":"Retail Goods"
        }
    ],
    "sg:phone":"+33 3 29 36 91 16",
    "sg:postcode":"88550",
    "sg:province":"Lorraine",
    "sg:tags":[
        "household",
        "wood"
    ],
    "wof:name":"Domaxel",
    "wof:placetype":"venue"
},
  "geometry": {"coordinates":[6.577077,48.105],"type":"Point"}
}