{
  "type": "Feature",
  "properties": {
    "iso:country":"FR",
    "sg:address":"664 Rue De La Resistance 59167 Lallaing",
    "sg:classifiers":[
        {
            "category":"Home & Garden",
            "subcategory":"Furniture",
            "type":"Retail Goods"
        }
    ],
    "sg:phone":"+33 3 27 71 52 52",
    "sg:province":"Nord Pas-de-Calais",
    "sg:tags":[
        "wood"
    ],
    "wof:name":"Sa Dujardin Et Fils",
    "wof:placetype":"venue"
},
  "geometry": {"coordinates":[3.15683,50.392231],"type":"Point"}
}