{
  "type": "Feature",
  "properties": {
    "iso:country":"FR",
    "sg:address":"Rue Des Scieries 59640 Dunkerque",
    "sg:classifiers":[
        {
            "category":"Wholesale",
            "subcategory":"Machinery & Supplies",
            "type":"Manufacturing & Wholesale Goods"
        }
    ],
    "sg:phone":"+33 3 28 20 34 60",
    "sg:province":"Midi Pyr\u00e9n\u00e9es",
    "sg:tags":[
        "handling",
        "material",
        "-",
        "machine",
        "equipment",
        "engineering",
        "mechanical"
    ],
    "wof:name":"Dk Pal",
    "wof:placetype":"venue"
},
  "geometry": {"coordinates":[2.36604,51.025024],"type":"Point"}
}