{
  "type": "Feature",
  "properties": {
    "iso:country":"FR",
    "sg:address":"Chemin de Lamballard",
    "sg:city":"Bretteville sur Odon",
    "sg:orig_category":"Non-Classified Establishments",
    "sg:phone":"+33 2 31 75 07 70",
    "sg:postcode":"14760",
    "sg:province":"Basse Normandie",
    "wof:name":"Ledard S.a.",
    "wof:placetype":"venue"
},
  "geometry": {"coordinates":[-0.405295,49.168312],"type":"Point"}
}