{
  "type": "Feature",
  "properties": {
    "addr:full":"Le Bourg 64130 Viodos Abense de Bas Ainharp Aquitaine 64130",
    "addr:postcode":"64130;64130",
    "addr:street":"Le Bourg",
    "iso:country":"FR",
    "sg:address":"Le Bourg 64130 Viodos Abense de Bas",
    "sg:city":"Ainharp",
    "sg:orig_category":"Non-Classified Establishments",
    "sg:phone":"+33 5 59 28 05 92",
    "sg:postcode":"64130",
    "sg:province":"Aquitaine",
    "wof:name":"Oroc Bat S.a.",
    "wof:placetype":"venue"
},
  "geometry": {"coordinates":[-0.933393,43.148788],"type":"Point"}
}