{
  "type": "Feature",
  "properties": {
    "iso:country":"FR",
    "sg:address":"4, Place Felix Ebou\u00e9, 75012 Paris",
    "sg:orig_category":"Unclassifiable Establishments",
    "sg:phone":"+33 1 53 46 31 00",
    "sg:province":"Ile de France",
    "wof:name":"Acmi S.a.",
    "wof:placetype":"venue"
},
  "geometry": {"coordinates":[2.3955,48.839401],"type":"Point"}
}