{
  "type": "Feature",
  "properties": {
    "addr:full":"605, Rue Saint Fuscien, 80000 Amiens Picardie",
    "addr:housenumber":"605",
    "addr:postcode":"80000",
    "addr:street":"Rue Saint Fuscien",
    "iso:country":"FR",
    "sg:address":"605, Rue Saint Fuscien, 80000 Amiens",
    "sg:orig_category":"Unclassifiable Establishments",
    "sg:phone":"+33 3 22 33 60 60",
    "sg:province":"Picardie",
    "wof:name":"Secovi S.a.",
    "wof:placetype":"venue"
},
  "geometry": {"coordinates":[2.30515,49.87899],"type":"Point"}
}