{
  "type": "Feature",
  "properties": {
    "addr:full":"Zone d'Emploi de la Baudri\u00e8re 27520 BOURGTHEROULDE INFREVILLE Haute Normandie",
    "addr:postcode":"27520",
    "addr:street":"Haute Normandie",
    "iso:country":"FR",
    "sg:address":"Zone d'Emploi de la Baudri\u00e8re 27520 BOURGTHEROULDE INFREVILLE",
    "sg:orig_category":"Works Equipment",
    "sg:phone":"+33 2 35 77 76 64",
    "sg:province":"Haute Normandie",
    "wof:name":"Delta Energie S.a.",
    "wof:placetype":"venue"
},
  "geometry": {"coordinates":[0.87393,49.29908],"type":"Point"}
}