{
  "type": "Feature",
  "properties": {
    "addr:full":"Les Granges 44840 Les Sorinieres Pays de Loire 44840",
    "addr:postcode":"44840;44840",
    "addr:street":"Granges;Sorinieres",
    "iso:country":"FR",
    "sg:address":"Les Granges 44840 Les Sorinieres",
    "sg:classifiers":[
        {
            "category":"Food Court",
            "type":"Food & Drink"
        }
    ],
    "sg:phone":"+33 2 40 05 78 73",
    "sg:postcode":"44840",
    "sg:province":"Pays de Loire",
    "sg:tags":[
        "product",
        "related"
    ],
    "wof:name":"Le Nantillais",
    "wof:placetype":"venue"
},
  "geometry": {"coordinates":[-1.532032,47.128487],"type":"Point"}
}