{
  "type": "Feature",
  "properties": {
    "addr:full":"51 cours de G\u00e9n\u00e9ral; Bordeaux; 33850 L\u00e9ognan Aquitaine 33850",
    "addr:housenumber":"51",
    "addr:postcode":"33850;33850",
    "addr:street":"Cours De Ge\u0301Ne\u0301Ral Bordeaux",
    "iso:country":"FR",
    "sg:address":"51 cours de G\u00e9n\u00e9ral; Bordeaux; 33850",
    "sg:city":"L\u00e9ognan",
    "sg:classifiers":[
        {
            "category":"Banks & Credit Unions",
            "subcategory":"Bank",
            "type":"Services"
        }
    ],
    "sg:phone":"+33 3356647058",
    "sg:postcode":"33850",
    "sg:province":"Aquitaine",
    "wof:name":"Cr\u00e9dit Agricole De La Gironde",
    "wof:placetype":"venue"
},
  "geometry": {"coordinates":[-0.600611,44.730312],"type":"Point"}
}