{
  "type": "Feature",
  "properties": {
    "addr:full":"18, Rue Henri Warnier, 51500 Taissy Champagne",
    "addr:housenumber":"18",
    "addr:postcode":"51500",
    "addr:street":"Rue Henri Warnier",
    "iso:country":"FR",
    "sg:address":"18, Rue Henri Warnier, 51500 Taissy",
    "sg:orig_category":"Unclassifiable Establishments",
    "sg:phone":"+33 3 26 85 06 97",
    "sg:province":"Champagne",
    "wof:name":"Sjv Peintures S.a.r.l.",
    "wof:placetype":"venue"
},
  "geometry": {"coordinates":[4.085972,49.216747],"type":"Point"}
}