{
  "type": "Feature",
  "properties": {
    "addr:full":"7, Rue de la Motte, 76100 Rouen Haute Normandie",
    "addr:housenumber":"7",
    "addr:postcode":"76100",
    "addr:street":"Rue De La Motte;Haute Normandie",
    "iso:country":"FR",
    "sg:address":"7, Rue de la Motte, 76100 Rouen",
    "sg:orig_category":"Unclassifiable Establishments",
    "sg:phone":"+33 2 35 63 04 40",
    "sg:province":"Haute Normandie",
    "wof:name":"E.t.i. S.a. - Etude Technique Industrielle",
    "wof:placetype":"venue"
},
  "geometry": {"coordinates":[1.073473,49.434391],"type":"Point"}
}