{
  "type": "Feature",
  "properties": {
    "addr:full":"Zi De Glaire 08203 Sedan Cedex Champagne",
    "addr:postcode":"08203",
    "addr:street":"Zi De Glaire",
    "iso:country":"FR",
    "sg:address":"Zi De Glaire 08203 Sedan Cedex",
    "sg:classifiers":[
        {
            "category":"Building & Trades",
            "subcategory":"Construction",
            "type":"Services"
        }
    ],
    "sg:phone":"+33 3 24 27 08 86",
    "sg:province":"Champagne",
    "sg:tags":[
        "work",
        "public"
    ],
    "wof:name":"Eurovia Champagne Ardenne Lorraine",
    "wof:placetype":"venue"
},
  "geometry": {"coordinates":[4.902774,49.695869],"type":"Point"}
}