{
  "type": "Feature",
  "properties": {
    "iso:country":"FR",
    "sg:address":"18 Avenue Pasteur 33450 St Loubes",
    "sg:city":"Saint-Loub\u00e8s",
    "sg:classifiers":[
        {
            "category":"Food Court",
            "type":"Food & Drink"
        }
    ],
    "sg:phone":"+33 5 57 97 14 60",
    "sg:postcode":"33450",
    "sg:province":"Aquitaine",
    "sg:tags":[
        "product",
        "related"
    ],
    "wof:name":"Meneau Sa",
    "wof:placetype":"venue"
},
  "geometry": {"coordinates":[-0.437953,44.919556],"type":"Point"}
}