{
  "type": "Feature",
  "properties": {
    "addr:full":"35, Rue Emile Combes, 83340 Le Luc Provence-Alpes-C\u00f4te d'Azur",
    "addr:housenumber":"35",
    "addr:postcode":"83340",
    "addr:street":"Rue Emile Combes;Luc",
    "iso:country":"FR",
    "sg:address":"35, Rue Emile Combes, 83340 Le Luc",
    "sg:orig_category":"Unclassifiable Establishments",
    "sg:phone":"+33 4 95 50 00 50",
    "sg:province":"Provence-Alpes-C\u00f4te d'Azur",
    "wof:name":"Unitra S.a.",
    "wof:placetype":"venue"
},
  "geometry": {"coordinates":[6.313469,43.395214],"type":"Point"}
}