{
  "type": "Feature",
  "properties": {
    "addr:full":"R Du 11 Novembre 37 Rn 60240 Fresne L\u00e9guillon Picardie 60240",
    "addr:housenumber":"37",
    "addr:postcode":"60240;60240",
    "addr:street":"R Du 11 Novembre;Le\u0301Guillon Picardie",
    "iso:country":"FR",
    "sg:address":"R Du 11 Novembre 37 Rn 60240 Fresne L\u00e9guillon",
    "sg:classifiers":[
        {
            "category":"Manufacturing",
            "subcategory":"Tools & Machinery",
            "type":"Manufacturing & Wholesale Goods"
        }
    ],
    "sg:phone":"+33 3 44 49 04 21",
    "sg:postcode":"60240",
    "sg:province":"Picardie",
    "sg:tags":[
        "equipment",
        "measurement",
        "-",
        "precision",
        "instrument"
    ],
    "wof:name":"Sn Dyona",
    "wof:placetype":"venue"
},
  "geometry": {"coordinates":[1.98599,49.253216],"type":"Point"}
}