{
  "type": "Feature",
  "properties": {
    "addr:full":"84 Bis Avenue Du General Leclerc 78220 Viroflay Ile de France 78220",
    "addr:housenumber":"84 bis",
    "addr:postcode":"78220;ile;78220",
    "addr:street":"Avenue Du General Leclerc;France",
    "iso:country":"FR",
    "sg:address":"84 Bis Avenue Du General Leclerc 78220 Viroflay",
    "sg:classifiers":[
        {
            "category":"Banks & Credit Unions",
            "subcategory":"Financial Services",
            "type":"Services"
        }
    ],
    "sg:phone":"+33 1 30 83 28 40",
    "sg:postcode":"78220",
    "sg:province":"Ile de France",
    "sg:tags":[
        "banking",
        "insurance",
        "institution",
        "finance"
    ],
    "wof:name":"Itex Informatique",
    "wof:placetype":"venue"
},
  "geometry": {"coordinates":[2.174298,48.804173],"type":"Point"}
}