{
  "type": "Feature",
  "properties": {
    "addr:full":"3 rue Roger Salengro; Caudry; 59540 Nord Pas-de-Calais 59540",
    "addr:housenumber":"3",
    "addr:postcode":"59540;59540",
    "addr:street":"Rue Roger Salengro",
    "iso:country":"FR",
    "sg:address":"3 rue Roger Salengro; Caudry; 59540",
    "sg:classifiers":[
        {
            "category":"Banks & Credit Unions",
            "subcategory":"Bank",
            "type":"Services"
        }
    ],
    "sg:phone":"+33 27852038",
    "sg:postcode":"59540",
    "sg:province":"Nord Pas-de-Calais",
    "wof:name":"Soci\u00e9t\u00e9 G\u00e9n\u00e9rale",
    "wof:placetype":"venue"
},
  "geometry": {"coordinates":[3.410229,50.124092],"type":"Point"}
}