{
  "type": "Feature",
  "properties": {
    "iso:country":"FR",
    "sg:address":"Zone D'Activit\u00e9s La Saubole 47200 Fourques Sur Garonne",
    "sg:city":"Marmande",
    "sg:classifiers":[
        {
            "category":"Shopping",
            "subcategory":"Clothing, Apparel, & Fashions",
            "type":"Retail Goods"
        }
    ],
    "sg:phone":"+33 5 53 20 06 53",
    "sg:postcode":"47200",
    "sg:province":"Aquitaine",
    "sg:tags":[
        "textile",
        "clothing",
        "clothes"
    ],
    "wof:name":"Coline Diffusion Sa",
    "wof:placetype":"venue"
},
  "geometry": {"coordinates":[0.158235,44.51944],"type":"Point"}
}