{
  "type": "Feature",
  "properties": {
    "iso:country":"FR",
    "sg:address":"37, Rue Michel Hubert Descours, 27300 Bernay",
    "sg:orig_category":"Non-Classified Establishments",
    "sg:phone":"+33 2 32 43 11 42",
    "sg:postcode":"27300",
    "sg:province":"Haute Normandie",
    "wof:name":"Cabinet Bellanger Fran\u00e7ois",
    "wof:placetype":"venue"
},
  "geometry": {"coordinates":[0.597468,49.089924],"type":"Point"}
}