{
  "type": "Feature",
  "properties": {
    "iso:country":"FR",
    "sg:address":"Petit Condal 71480 Condal",
    "sg:city":"Condal",
    "sg:classifiers":[
        {
            "category":"Professional",
            "subcategory":"Engineering",
            "type":"Services"
        }
    ],
    "sg:phone":"+33 3 85 76 61 60",
    "sg:postcode":"71480",
    "sg:province":"Bourgogne",
    "sg:tags":[
        "machine",
        "-",
        "mechanical"
    ],
    "wof:name":"Puget Production Mecanique Sa",
    "wof:placetype":"venue"
},
  "geometry": {"coordinates":[5.261715,46.460533],"type":"Point"}
}