{
  "type": "Feature",
  "properties": {
    "iso:country":"FR",
    "sg:address":"1 Place Carnot 51360 Verzenay",
    "sg:classifiers":[
        {
            "category":"Food Court",
            "type":"Food & Drink"
        }
    ],
    "sg:phone":"+33 3 26 49 40 63",
    "sg:postcode":"51360",
    "sg:province":"Champagne",
    "sg:tags":[
        "product",
        "related"
    ],
    "wof:name":"Champagne Quenardel Et Fils",
    "wof:placetype":"venue"
},
  "geometry": {"coordinates":[4.146429,49.16003],"type":"Point"}
}