{
  "type": "Feature",
  "properties": {
    "addr:full":"B.P. 31 Premi\u00e8res Bourgogne 21110",
    "addr:postcode":"21110",
    "addr:street":"B.P. 31 Premie\u0300Res Bourgogne",
    "iso:country":"FR",
    "sg:address":"B.P. 31",
    "sg:city":"Premi\u00e8res",
    "sg:orig_category":"Non-Classified Establishments",
    "sg:phone":"+33 3 80 31 58 01",
    "sg:postcode":"21110",
    "sg:province":"Bourgogne",
    "wof:name":"Criter S.a.",
    "wof:placetype":"venue"
},
  "geometry": {"coordinates":[5.220228,47.241528],"type":"Point"}
}