{
  "type": "Feature",
  "properties": {
    "addr:full":"11, Rue de Cambrais, 75019 Paris Ile de France 75019",
    "addr:housenumber":"11",
    "addr:postcode":"75019;75019",
    "addr:street":"Rue De Cambrais",
    "iso:country":"FR",
    "sg:address":"11, Rue de Cambrais, 75019 Paris",
    "sg:orig_category":"Non-Classified Establishments",
    "sg:phone":"+33 1 55 26 70 70",
    "sg:postcode":"75019",
    "sg:province":"Ile de France",
    "wof:name":"Agro March\u00e9s Internationaux S.a.",
    "wof:placetype":"venue"
},
  "geometry": {"coordinates":[2.377907,48.89473],"type":"Point"}
}