{
  "type": "Feature",
  "properties": {
    "addr:full":"boulevard Winston Churchill 17000 La Rochelle Poitou-Charentes 17000",
    "addr:postcode":"17000;17000",
    "addr:street":"Boulevard Winston Churchill",
    "iso:country":"FR",
    "sg:address":"boulevard Winston Churchill 17000 La Rochelle",
    "sg:orig_category":"Marine Electronic Systems",
    "sg:phone":"+33 5 46 42 42 18",
    "sg:postcode":"17000",
    "sg:province":"Poitou-Charentes",
    "wof:name":"Iris S.a.",
    "wof:placetype":"venue"
},
  "geometry": {"coordinates":[-1.178897,46.153561],"type":"Point"}
}