{
  "type": "Feature",
  "properties": {
    "iso:country":"FR",
    "sg:address":"31134 Balma C\u00e9dex",
    "sg:orig_category":"Non-Classified Establishments",
    "sg:phone":"+33 5 62 57 65 18",
    "sg:province":"Midi Pyr\u00e9n\u00e9es",
    "wof:name":"E.s.i.m. - Ecole Sup\u00e9rieure Des Industries De La Mode",
    "wof:placetype":"venue"
},
  "geometry": {"coordinates":[1.49756,43.60989],"type":"Point"}
}