{
  "type": "Feature",
  "properties": {
    "addr:full":"2, Rue Jean Zay, 94380 Bonneuil sur Marne Ile de France",
    "addr:housenumber":"2",
    "addr:postcode":"94380",
    "addr:street":"Rue Jean Zay",
    "iso:country":"FR",
    "sg:address":"2, Rue Jean Zay, 94380 Bonneuil sur Marne",
    "sg:orig_category":"Unclassifiable Establishments",
    "sg:phone":"+33 1 43 99 58 88",
    "sg:province":"Ile de France",
    "wof:name":"Alizes Photogravure S.a.r.l.",
    "wof:placetype":"venue"
},
  "geometry": {"coordinates":[2.483755,48.766014],"type":"Point"}
}