{
  "type": "Feature",
  "properties": {
    "addr:full":"Rue G\u00e9rard Philippe - ZA de Pendreff Lanester Bretagne 56600",
    "addr:postcode":"56600",
    "addr:street":"Rue Ge\u0301Rard Philippe Za De Pendreff Lanester Bretagne",
    "iso:country":"FR",
    "sg:address":"Rue G\u00e9rard Philippe - ZA de Pendreff",
    "sg:city":"Lanester",
    "sg:orig_category":"Non-Classified Establishments",
    "sg:phone":"+33 2 97 76 16 54",
    "sg:postcode":"56600",
    "sg:province":"Bretagne",
    "wof:name":"Goulias Fr\u00e8res S.a.",
    "wof:placetype":"venue"
},
  "geometry": {"coordinates":[-3.345244,47.76532],"type":"Point"}
}