{
  "type": "Feature",
  "properties": {
    "iso:country":"FR",
    "sg:address":"82 Rue Jb Calvignac Zae De La Biste 34670 Baillargues",
    "sg:classifiers":[
        {
            "category":"Building & Trades",
            "subcategory":"Construction",
            "type":"Services"
        }
    ],
    "sg:phone":"+33 4 67 91 26 26",
    "sg:postcode":"34670",
    "sg:province":"Languedoc-Roussillon",
    "sg:tags":[
        "work",
        "public"
    ],
    "wof:name":"Eurovia Mediterranee",
    "wof:placetype":"venue"
},
  "geometry": {"coordinates":[4.013353,43.65834],"type":"Point"}
}