{
  "type": "Feature",
  "properties": {
    "addr:full":"Rue Marc Seguin Sud 41101 Vend\u00f4me Picardie",
    "addr:postcode":"41101",
    "addr:street":"Rue Marc Seguin Sud",
    "iso:country":"FR",
    "sg:address":"Rue Marc Seguin",
    "sg:city":"Sud 41101 Vend\u00f4me",
    "sg:classifiers":[
        {
            "category":"Shopping",
            "subcategory":"Computers & Home Electronics",
            "type":"Retail Goods"
        }
    ],
    "sg:phone":"+33 2 54 23 14 54",
    "sg:province":"Picardie",
    "sg:tags":[
        "electronic",
        "electrical",
        "equipment"
    ],
    "wof:name":"Ecofit Sa",
    "wof:placetype":"venue"
},
  "geometry": {"coordinates":[1.064763,47.792313],"type":"Point"}
}