{
  "type": "Feature",
  "properties": {
    "iso:country":"FR",
    "sg:address":"16 Rue 19 Mars 1962 46130 Biars Sur C\u00e8re",
    "sg:classifiers":[
        {
            "category":"Wholesale",
            "subcategory":"Machinery & Supplies",
            "type":"Manufacturing & Wholesale Goods"
        }
    ],
    "sg:phone":"+33 5 65 39 72 00",
    "sg:province":"Midi Pyr\u00e9n\u00e9es",
    "sg:tags":[
        "equipment",
        "precision"
    ],
    "wof:name":"Hydrau-elect",
    "wof:placetype":"venue"
},
  "geometry": {"coordinates":[1.842299,44.927849],"type":"Point"}
}