{
  "type": "Feature",
  "properties": {
    "addr:full":"7, Chemin du Dodin - Immeuble le Parsonge, 69570 Dardilly Rhone-Alpes 69570",
    "addr:housenumber":"7",
    "addr:postcode":"69570;69570",
    "addr:street":"Chemin Du Dodin Immeuble Le Parsonge",
    "iso:country":"FR",
    "sg:address":"7, Chemin du Dodin - Immeuble le Parsonge, 69570 Dardilly",
    "sg:orig_category":"Non-Classified Establishments",
    "sg:phone":"+33 4 78 35 46 84",
    "sg:postcode":"69570",
    "sg:province":"Rhone-Alpes",
    "wof:name":"Arc Informatique S.a.",
    "wof:placetype":"venue"
},
  "geometry": {"coordinates":[4.761305,45.818096],"type":"Point"}
}