{
  "type": "Feature",
  "properties": {
    "addr:full":"Rue des Forgerons - ZI Torcy Ile de France 77200",
    "addr:postcode":"77200",
    "addr:street":"Rue Des Forgerons Zi",
    "iso:country":"FR",
    "sg:address":"Rue des Forgerons - ZI",
    "sg:city":"Torcy",
    "sg:orig_category":"Unclassifiable Establishments",
    "sg:phone":"+33 1 60 05 83 81",
    "sg:postcode":"77200",
    "sg:province":"Ile de France",
    "wof:name":"Getrac S.a.",
    "wof:placetype":"venue"
},
  "geometry": {"coordinates":[2.651845,48.849575],"type":"Point"}
}