{
  "type": "Feature",
  "properties": {
    "iso:country":"FR",
    "sg:address":"15, Av. la Yatz, 64500 Saint Jean de Luz",
    "sg:city":"Ciboure",
    "sg:orig_category":"Unclassifiable Establishments",
    "sg:phone":"+33 5 59 51 90 90",
    "sg:postcode":"64500",
    "sg:province":"Aquitaine",
    "wof:name":"B. Braun M\u00e9dical S.a.s.",
    "wof:placetype":"venue"
},
  "geometry": {"coordinates":[-1.660884,43.38773],"type":"Point"}
}