{
  "type": "Feature",
  "properties": {
    "addr:full":"15, Quai du Commerce, 69009 Lyon Rhone-Alpes",
    "addr:housenumber":"15",
    "addr:postcode":"69009",
    "addr:street":"Quai Du Commerce",
    "iso:country":"FR",
    "sg:address":"15, Quai du Commerce, 69009 Lyon",
    "sg:orig_category":"Unclassifiable Establishments",
    "sg:phone":"+33 4 78 43 45 55",
    "sg:province":"Rhone-Alpes",
    "wof:name":"Corec S.a.",
    "wof:placetype":"venue"
},
  "geometry": {"coordinates":[4.811531,45.783569],"type":"Point"}
}