{
  "type": "Feature",
  "properties": {
    "iso:country":"FR",
    "sg:address":"5 Rue De La Janaie 35400 St Malo",
    "sg:city":"Saint-Malo",
    "sg:classifiers":[
        {
            "category":"Banks & Credit Unions",
            "subcategory":"Investment Brokerage",
            "type":"Services"
        }
    ],
    "sg:phone":"+33 2 99 82 83 22",
    "sg:postcode":"35400",
    "sg:province":"Bretagne",
    "sg:tags":[
        "-",
        "transport",
        "related"
    ],
    "wof:name":"Saint Malo Portage Sarl",
    "wof:placetype":"venue"
},
  "geometry": {"coordinates":[-1.982359,48.631954],"type":"Point"}
}