{
  "type": "Feature",
  "properties": {
    "addr:full":"970 Rue De La Bergeresse Olivet Centre 45160",
    "addr:housenumber":"970",
    "addr:postcode":"45160",
    "addr:street":"Rue De La Bergeresse Olivet",
    "iso:country":"FR",
    "sg:address":"970 Rue De La Bergeresse",
    "sg:city":"Olivet",
    "sg:classifiers":[
        {
            "category":"Banks & Credit Unions",
            "subcategory":"Financial Services",
            "type":"Services"
        }
    ],
    "sg:phone":"+33 2 38 69 09 00",
    "sg:postcode":"45160",
    "sg:province":"Centre",
    "sg:tags":[
        "banking",
        "finance",
        "insurance"
    ],
    "wof:name":"A T N Sa",
    "wof:placetype":"venue"
},
  "geometry": {"coordinates":[1.918769,47.845753],"type":"Point"}
}