{
  "type": "Feature",
  "properties": {
    "addr:full":"79, Rue du Foss\u00e9 Blanc, 92230 Gennevilliers Ile de France",
    "addr:housenumber":"79",
    "addr:postcode":"92230;ile",
    "addr:street":"Rue Du Fosse\u0301 Blanc",
    "iso:country":"FR",
    "sg:address":"79, Rue du Foss\u00e9 Blanc, 92230 Gennevilliers",
    "sg:orig_category":"Non-Classified Establishments",
    "sg:phone":"+33 1 47 98 51 90",
    "sg:province":"Ile de France",
    "wof:name":"Raisch Ile De France S.a.",
    "wof:placetype":"venue"
},
  "geometry": {"coordinates":[2.307668,48.926575],"type":"Point"}
}