{
  "type": "Feature",
  "properties": {
    "addr:full":"141, Av. de Verdun, 92442 Issy les Moulineaux C\u00e9dex Midi Pyr\u00e9n\u00e9es",
    "addr:postcode":"92442",
    "addr:street":"141 Av. De Verdun",
    "iso:country":"FR",
    "sg:address":"141, Av. de Verdun, 92442 Issy les Moulineaux C\u00e9dex",
    "sg:orig_category":"Non-Classified Establishments",
    "sg:phone":"+33 1 45 29 46 00",
    "sg:province":"Midi Pyr\u00e9n\u00e9es",
    "wof:name":"Elyo S.a.",
    "wof:placetype":"venue"
},
  "geometry": {"coordinates":[2.251605,48.818066],"type":"Point"}
}