{
  "type": "Feature",
  "properties": {
    "addr:full":"6 Rue Jean Devaux 79100 Thouars Poitou-Charentes 79100",
    "addr:housenumber":"6",
    "addr:postcode":"79100;79100",
    "addr:street":"Rue Jean Devaux",
    "iso:country":"FR",
    "sg:address":"6 Rue Jean Devaux 79100 Thouars",
    "sg:classifiers":[
        {
            "category":"Farming",
            "subcategory":"Farm & Veterinary Services",
            "type":"Manufacturing & Wholesale Goods"
        }
    ],
    "sg:phone":"+33 5 49 96 31 20",
    "sg:postcode":"79100",
    "sg:province":"Poitou-Charentes",
    "sg:tags":[
        "food",
        "product",
        "breeding",
        "animal",
        "related"
    ],
    "wof:name":"Rocvent",
    "wof:placetype":"venue"
},
  "geometry": {"coordinates":[-0.198695,46.998043],"type":"Point"}
}