{
  "type": "Feature",
  "properties": {
    "addr:full":"1475 route de Caunan 81090 LABRUGUIERE Midi Pyr\u00e9n\u00e9es",
    "addr:housenumber":"1475",
    "addr:postcode":"81090",
    "addr:street":"Route De Caunan",
    "iso:country":"FR",
    "sg:address":"1475 route de Caunan 81090 LABRUGUIERE",
    "sg:classifiers":[
        {
            "category":"Home & Garden",
            "subcategory":"Building Materials",
            "type":"Retail Goods"
        }
    ],
    "sg:phone":"+33 6 99 98 65 00",
    "sg:province":"Midi Pyr\u00e9n\u00e9es",
    "sg:tags":[
        "carding",
        "plant",
        "carbonating",
        "washing",
        "wool"
    ],
    "wof:name":"Wool Trading International S.a.r.l.",
    "wof:placetype":"venue"
},
  "geometry": {"coordinates":[2.280378,43.523376],"type":"Point"}
}