{
  "type": "Feature",
  "properties": {
    "iso:country":"FR",
    "sg:address":"ZI de felet 63309 THIERS CEDEX",
    "sg:classifiers":[
        {
            "category":"Wholesale",
            "subcategory":"Plants",
            "type":"Manufacturing & Wholesale Goods"
        }
    ],
    "sg:phone":"+33 4 73 80 21 09",
    "sg:province":"Basse Normandie",
    "sg:tags":[
        "part",
        "spare",
        "smelting"
    ],
    "wof:name":"S.e.p.p. Sa",
    "wof:placetype":"venue"
},
  "geometry": {"coordinates":[3.548272,45.855244],"type":"Point"}
}