{
  "type": "Feature",
  "properties": {
    "iso:country":"FR",
    "sg:address":"rue St Pierre; Aignay le Duc",
    "sg:classifiers":[
        {
            "category":"Banks & Credit Unions",
            "subcategory":"Bank",
            "type":"Services"
        }
    ],
    "sg:phone":"+33 3380938376",
    "sg:province":"Champagne",
    "wof:name":"Cr\u00e9dit Agricole, Mutuel (c.a.m)",
    "wof:placetype":"venue"
},
  "geometry": {"coordinates":[4.732477,47.665337],"type":"Point"}
}