{
  "type": "Feature",
  "properties": {
    "addr:full":"Rue les Amias Saulxures sur Moselotte Lorraine 88290",
    "addr:postcode":"88290",
    "addr:street":"Rue Les Amias;Moselotte Lorraine",
    "iso:country":"FR",
    "sg:address":"Rue les Amias",
    "sg:city":"Saulxures sur Moselotte",
    "sg:orig_category":"Unclassifiable Establishments",
    "sg:phone":"+33 3 29 24 60 55",
    "sg:postcode":"88290",
    "sg:province":"Lorraine",
    "wof:name":"Gerbois S.a.",
    "wof:placetype":"venue"
},
  "geometry": {"coordinates":[6.758575,47.951035],"type":"Point"}
}