{
  "type": "Feature",
  "properties": {
    "addr:full":"2, Rue Champr\u00e9, 67500 Haguenau Haguenau Alsace 67500",
    "addr:housenumber":"2",
    "addr:postcode":"67500;67500",
    "addr:street":"Rue Champre\u0301",
    "iso:country":"FR",
    "sg:address":"2, Rue Champr\u00e9, 67500 Haguenau",
    "sg:city":"Haguenau",
    "sg:orig_category":"Non-Classified Establishments",
    "sg:phone":"+33 3 88 06 14 30",
    "sg:postcode":"67500",
    "sg:province":"Alsace",
    "wof:name":"Maitr-carre S.a.r.l.",
    "wof:placetype":"venue"
},
  "geometry": {"coordinates":[7.800019,48.812359],"type":"Point"}
}