{
  "type": "Feature",
  "properties": {
    "addr:full":"15 Quai De Lattre De Tassigny 34200 Sete Languedoc-Roussillon 34200",
    "addr:housenumber":"15",
    "addr:postcode":"34200;34200",
    "addr:street":"Quai De Lattre De Tassigny",
    "iso:country":"FR",
    "sg:address":"15 Quai De Lattre De Tassigny 34200 Sete",
    "sg:classifiers":[
        {
            "category":"Banks & Credit Unions",
            "subcategory":"Financial Services",
            "type":"Services"
        }
    ],
    "sg:phone":"+33 4 67 46 86 00",
    "sg:postcode":"34200",
    "sg:province":"Languedoc-Roussillon",
    "sg:tags":[
        "banking",
        "insurance",
        "institution",
        "finance"
    ],
    "wof:name":"Caisse Regionale De Credit Agricole Mutuelle De Sete",
    "wof:placetype":"venue"
},
  "geometry": {"coordinates":[3.696586,43.405293],"type":"Point"}
}