{
  "type": "Feature",
  "properties": {
    "iso:country":"FR",
    "sg:address":"11, Rue des Fr\u00e8res Lumi\u00e8re - ZI de Revoisson, 69740 Genas",
    "sg:orig_category":"Unclassifiable Establishments",
    "sg:phone":"+33 4 78 90 85 08",
    "sg:province":"Rhone-Alpes",
    "wof:name":"Fraispers S.a.r.l.",
    "wof:placetype":"venue"
},
  "geometry": {"coordinates":[5.000308,45.731804],"type":"Point"}
}