{
  "type": "Feature",
  "properties": {
    "addr:full":"Quartier les Mouettes Ch\u00e2teauneuf les Martigues Midi Pyr\u00e9n\u00e9es 13220",
    "addr:postcode":"13220",
    "addr:street":"Quartier Les;Cha\u0302Teauneuf Les;Midi",
    "iso:country":"FR",
    "sg:address":"Quartier les Mouettes",
    "sg:city":"Ch\u00e2teauneuf les Martigues",
    "sg:orig_category":"Non-Classified Establishments",
    "sg:phone":"+33 4 42 07 12 94",
    "sg:postcode":"13220",
    "sg:province":"Midi Pyr\u00e9n\u00e9es",
    "wof:name":"Phocomex",
    "wof:placetype":"venue"
},
  "geometry": {"coordinates":[5.10525,43.397942],"type":"Point"}
}