{
  "type": "Feature",
  "properties": {
    "addr:full":"Rue De L Epinoy Zone Industrielle 59175 Templemars Nord Pas-de-Calais 59175",
    "addr:postcode":"59175;59175",
    "addr:street":"Rue De L Epinoy Zone Industrielle",
    "iso:country":"FR",
    "sg:address":"Rue De L Epinoy Zone Industrielle 59175 Templemars",
    "sg:orig_category":"Miscellaneous Products",
    "sg:phone":"+33 3 20 90 42 00",
    "sg:postcode":"59175",
    "sg:province":"Nord Pas-de-Calais",
    "wof:name":"Etablissements Parent Et Compagnie",
    "wof:placetype":"venue"
},
  "geometry": {"coordinates":[3.053042,50.575886],"type":"Point"}
}