{
  "type": "Feature",
  "properties": {
    "iso:country":"FR",
    "sg:address":"Hameau les Roches N\u00b014 26120 Malissard",
    "sg:orig_category":"Non-Classified Establishments",
    "sg:phone":"+33 4 75 85 43 21",
    "sg:province":"Rhone-Alpes",
    "wof:name":"M.k.m. France S.a.r.l.",
    "wof:placetype":"venue"
},
  "geometry": {"coordinates":[4.980202,44.804939],"type":"Point"}
}