{
  "type": "Feature",
  "properties": {
    "iso:country":"FR",
    "sg:address":"2, Place de Catalogne, 66000 Perpignan",
    "sg:orig_category":"Non-Classified Establishments",
    "sg:phone":"+33 4 68 35 63 63",
    "sg:postcode":"66000",
    "sg:province":"Languedoc-Roussillon",
    "wof:name":"Caixabank S.a.",
    "wof:placetype":"venue"
},
  "geometry": {"coordinates":[2.887473,42.698753],"type":"Point"}
}