{
  "type": "Feature",
  "properties": {
    "addr:full":"105, Rte d'Argenteuil, 95240 Cormeilles en Parisis Ile de France",
    "addr:housenumber":"105",
    "addr:postcode":"95240;ile",
    "addr:street":"Rte D'Argenteuil",
    "iso:country":"FR",
    "sg:address":"105, Rte d'Argenteuil, 95240 Cormeilles en Parisis",
    "sg:orig_category":"Non-Classified Establishments",
    "sg:phone":"+33 1 34 50 40 20",
    "sg:province":"Ile de France",
    "wof:name":"Placopl\u00e2tre S.a.",
    "wof:placetype":"venue"
},
  "geometry": {"coordinates":[2.19989,48.976398],"type":"Point"}
}