{
  "type": "Feature",
  "properties": {
    "iso:country":"FR",
    "sg:address":"15 cours Sablon; Clermont Ferrand; 63002",
    "sg:classifiers":[
        {
            "category":"Banks & Credit Unions",
            "subcategory":"Bank",
            "type":"Services"
        }
    ],
    "sg:phone":"+33 4 73 40 69 40",
    "sg:province":"Basse Normandie",
    "wof:name":"Banque De France",
    "wof:placetype":"venue"
},
  "geometry": {"coordinates":[3.090201,45.776184],"type":"Point"}
}