{
  "type": "Feature",
  "properties": {
    "iso:country":"FR",
    "sg:address":"2 Rue Cardinal Richaud Immeuble Burotel 33300 Bordeaux",
    "sg:city":"Bordeaux",
    "sg:classifiers":[
        {
            "category":"Professional",
            "subcategory":"Computer Services",
            "type":"Services"
        }
    ],
    "sg:phone":"+33 5 56 39 82 00",
    "sg:postcode":"33300",
    "sg:province":"Aquitaine",
    "sg:tags":[
        "information",
        "technology",
        "software"
    ],
    "wof:name":"Sinorg Gfi Informatique",
    "wof:placetype":"venue"
},
  "geometry": {"coordinates":[-0.562784,44.888535],"type":"Point"}
}