{
  "type": "Feature",
  "properties": {
    "addr:full":"53 Rue Jeanne D'Arc 55190 Void Vacon Lorraine 55190",
    "addr:housenumber":"53",
    "addr:postcode":"55190;55190",
    "addr:street":"Rue Jeanne D'Arc",
    "iso:country":"FR",
    "sg:address":"53 Rue Jeanne D'Arc 55190 Void Vacon",
    "sg:classifiers":[
        {
            "category":"Manufacturing",
            "subcategory":"Chemicals & Compounds",
            "type":"Manufacturing & Wholesale Goods"
        }
    ],
    "sg:phone":"+33 3 29 89 89 89",
    "sg:postcode":"55190",
    "sg:province":"Lorraine",
    "sg:tags":[
        "pharmaceutical",
        "-",
        "environment",
        "equipment",
        "machinery",
        "mechanic",
        "chemistry",
        "by-product"
    ],
    "wof:name":"Sarl L2pi",
    "wof:placetype":"venue"
},
  "geometry": {"coordinates":[5.62024,48.688946],"type":"Point"}
}