{
  "type": "Feature",
  "properties": {
    "addr:full":"38 rue Francine Fromont 69120 Vaulx en Velin Rhone-Alpes 69120",
    "addr:housenumber":"38",
    "addr:postcode":"69120;69120",
    "addr:street":"Rue Francine",
    "iso:country":"FR",
    "sg:address":"38 rue Francine Fromont 69120 Vaulx en Velin",
    "sg:classifiers":[
        {
            "category":"Airport",
            "type":"Transportation"
        }
    ],
    "sg:phone":"+33 4 78 79 51 10",
    "sg:postcode":"69120",
    "sg:province":"Rhone-Alpes",
    "sg:tags":[
        "air-freight",
        "forwarders"
    ],
    "wof:name":"Somatrans Sa",
    "wof:placetype":"venue"
},
  "geometry": {"coordinates":[4.942894,45.780708],"type":"Point"}
}