{
  "type": "Feature",
  "properties": {
    "iso:country":"FR",
    "sg:address":"4, Impasse Marcel Bourgogne, 95140 Garges l\u00e8s Gonesse",
    "sg:orig_category":"Unclassifiable Establishments",
    "sg:phone":"+33 1 39 86 58 17",
    "sg:province":"Ile de France",
    "wof:name":"L.v.o. Literie Du Val D'oise S.a.",
    "wof:placetype":"venue"
},
  "geometry": {"coordinates":[2.414835,48.969131],"type":"Point"}
}