{
  "type": "Feature",
  "properties": {
    "iso:country":"FR",
    "sg:address":"B.P. 5333, 20503 Ajaccio C\u00e9dex 05^^ZI de Bal\u00e9one, 20500 Ajaccio",
    "sg:orig_category":"Non-Classified Establishments",
    "sg:phone":"+33 4 95 23 13 03",
    "sg:province":"Languedoc-Roussillon",
    "wof:name":"Corsica Caf\u00e9 S.a.",
    "wof:placetype":"venue"
},
  "geometry": {"coordinates":[8.73908,41.917889],"type":"Point"}
}