{
  "type": "Feature",
  "properties": {
    "iso:country":"FR",
    "sg:address":"60, Fbg de Belfort, 90100 Delle",
    "sg:orig_category":"Unclassifiable Establishments",
    "sg:phone":"+33 3 84 58 48 48",
    "sg:province":"Franche Comt\u00e9",
    "wof:name":"Igol Nord Est S.a.",
    "wof:placetype":"venue"
},
  "geometry": {"coordinates":[7.001381,47.518642],"type":"Point"}
}