{
  "type": "Feature",
  "properties": {
    "addr:full":"B.P. 134, 69151 D\u00e9cines Charpieu C\u00e9dex^^37, Av. des Bruy\u00e8res - ZI, 69150 D\u00e9cines Charpieu Rhone-Alpes 69150",
    "addr:housenumber":"b.p. 134",
    "addr:postcode":"69151;69150;69150",
    "addr:street":"Av. Des Bruye\u0300Res Zi;Rhone-Alpes",
    "iso:country":"FR",
    "sg:address":"B.P. 134, 69151 D\u00e9cines Charpieu C\u00e9dex^^37, Av. des Bruy\u00e8res - ZI, 69150 D\u00e9cines Charpieu",
    "sg:orig_category":"Non-Classified Establishments",
    "sg:phone":"+33 4 72 05 67 77",
    "sg:postcode":"69150",
    "sg:province":"Rhone-Alpes",
    "wof:name":"N.d.p. - Nationale Des Papeteries",
    "wof:placetype":"venue"
},
  "geometry": {"coordinates":[4.95911,45.770794],"type":"Point"}
}