{
  "type": "Feature",
  "properties": {
    "addr:full":"Scierie Du Montoir 02670 Champs Picardie 02670",
    "addr:postcode":"02670;02670",
    "addr:street":"Picardie",
    "iso:country":"FR",
    "sg:address":"Scierie Du Montoir 02670 Champs",
    "sg:classifiers":[
        {
            "category":"Manufacturing",
            "subcategory":"Lumber",
            "type":"Manufacturing & Wholesale Goods"
        }
    ],
    "sg:phone":"+33 3 23 52 74 14",
    "sg:postcode":"02670",
    "sg:province":"Picardie",
    "sg:tags":[
        "hardwood",
        "sawmill"
    ],
    "wof:name":"Ets L Peltier Et Fils Et Cie Sa",
    "wof:placetype":"venue"
},
  "geometry": {"coordinates":[3.28211,49.543678],"type":"Point"}
}