{
  "type": "Feature",
  "properties": {
    "addr:full":"22, Grande Rue, 23200 Aubusson Limousin 23200",
    "addr:housenumber":"22",
    "addr:postcode":"23200;23200",
    "addr:street":"Grande Rue",
    "iso:country":"FR",
    "sg:address":"22, Grande Rue, 23200 Aubusson",
    "sg:orig_category":"Non-Classified Establishments",
    "sg:phone":"+33 5 55 66 11 52",
    "sg:postcode":"23200",
    "sg:province":"Limousin",
    "wof:name":"Alja France S.a.r.l.",
    "wof:placetype":"venue"
},
  "geometry": {"coordinates":[2.167777,45.956474],"type":"Point"}
}