{
  "type": "Feature",
  "properties": {
    "addr:full":"18, Rue de Cugnaux, 31300 Toulouse Midi Pyr\u00e9n\u00e9es",
    "addr:housenumber":"18",
    "addr:postcode":"31300",
    "addr:street":"Rue De Cugnaux",
    "iso:country":"FR",
    "sg:address":"18, Rue de Cugnaux, 31300 Toulouse",
    "sg:orig_category":"Non-Classified Establishments",
    "sg:phone":"+33 5 61 42 23 01",
    "sg:province":"Midi Pyr\u00e9n\u00e9es",
    "wof:name":"Point P. La M\u00e9riodionale S.a.",
    "wof:placetype":"venue"
},
  "geometry": {"coordinates":[1.421009,43.591812],"type":"Point"}
}