{
  "type": "Feature",
  "properties": {
    "addr:full":"B.P. 22, 29150 Ch\u00e2teaulin C\u00e9dex^^ZI de Lospars, 29150 Ch\u00e2teaulin Ch\u00e2teaulin Bretagne 29150",
    "addr:postcode":"29150;29150;cha\u0302teaulin;29150",
    "addr:street":"B.P. 22;Lospars",
    "iso:country":"FR",
    "sg:address":"B.P. 22, 29150 Ch\u00e2teaulin C\u00e9dex^^ZI de Lospars, 29150 Ch\u00e2teaulin",
    "sg:city":"Ch\u00e2teaulin",
    "sg:orig_category":"Non-Classified Establishments",
    "sg:phone":"+33 2 98 86 69 00",
    "sg:postcode":"29150",
    "sg:province":"Bretagne",
    "wof:name":"Doux S.a.",
    "wof:placetype":"venue"
},
  "geometry": {"coordinates":[-4.138809,48.157623],"type":"Point"}
}