{
  "type": "Feature",
  "properties": {
    "iso:country":"FR",
    "sg:address":"52, Rue Corneille, 31000 Toulouse",
    "sg:orig_category":"Unclassifiable Establishments",
    "sg:phone":"+33 5 61 43 66 43",
    "sg:province":"Midi Pyr\u00e9n\u00e9es",
    "wof:name":"S.e.s.o. S.a. - Soci\u00e9t\u00e9 D'entreprise Du Sud-ouest",
    "wof:placetype":"venue"
},
  "geometry": {"coordinates":[1.411398,43.592621],"type":"Point"}
}