{
  "type": "Feature",
  "properties": {
    "addr:full":"58 Avenue De L'Europe 86310 St Germain Poitou-Charentes 86310",
    "addr:housenumber":"58",
    "addr:postcode":"86310;86310",
    "addr:street":"Avenue De L'Europe;St Germain",
    "iso:country":"FR",
    "sg:address":"58 Avenue De L'Europe 86310 St Germain",
    "sg:classifiers":[
        {
            "category":"Shopping",
            "type":"Retail Goods"
        }
    ],
    "sg:phone":"+33 5 49 48 00 44",
    "sg:postcode":"86310",
    "sg:province":"Poitou-Charentes",
    "sg:tags":[
        "metallurgy",
        "finished",
        "-",
        "metalworking",
        "metallic"
    ],
    "wof:name":"Ets Tartarin Sarl",
    "wof:placetype":"venue"
},
  "geometry": {"coordinates":[-0.748838,46.106045],"type":"Point"}
}