{
  "type": "Feature",
  "properties": {
    "iso:country":"FR",
    "sg:address":"ZI Plan de Campagne 13480 CABRIES",
    "sg:classifiers":[
        {
            "category":"Food & Beverages",
            "subcategory":"Groceries & Convenience Stores",
            "type":"Retail Goods"
        }
    ],
    "sg:phone":"+33 4 42 02 92 57",
    "sg:province":"Bretagne",
    "sg:tags":[
        "fresh"
    ],
    "wof:name":"E.m.t. Process S.a.",
    "wof:placetype":"venue"
},
  "geometry": {"coordinates":[5.379897,43.441792],"type":"Point"}
}