{
  "type": "Feature",
  "properties": {
    "iso:country":"FR",
    "sg:address":"9c Av Pierre Et Marie Curie Synergie Park 59260 Lezennes",
    "sg:classifiers":[
        {
            "category":"Professional",
            "subcategory":"Advertising",
            "type":"Services"
        }
    ],
    "sg:phone":"+33 3 28 80 00 80",
    "sg:postcode":"59260",
    "sg:province":"Nord Pas-de-Calais",
    "sg:tags":[
        "marketing",
        "medium",
        "communication"
    ],
    "wof:name":"B C Conseil Sarl",
    "wof:placetype":"venue"
},
  "geometry": {"coordinates":[3.11705,50.614567],"type":"Point"}
}