{
  "type": "Feature",
  "properties": {
    "addr:full":"5 Rue Christian D Espic 81100 Castres Midi Pyr\u00e9n\u00e9es 81100",
    "addr:housenumber":"5",
    "addr:postcode":"81100;81100",
    "addr:street":"Rue Christian D Espic",
    "iso:country":"FR",
    "sg:address":"5 Rue Christian D Espic 81100 Castres",
    "sg:classifiers":[
        {
            "category":"Farming",
            "subcategory":"Farm & Veterinary Services",
            "type":"Manufacturing & Wholesale Goods"
        }
    ],
    "sg:phone":"+33 5 63 62 12 60",
    "sg:postcode":"81100",
    "sg:province":"Midi Pyr\u00e9n\u00e9es",
    "sg:tags":[
        "advice",
        "agriculture",
        "livestock",
        "business"
    ],
    "wof:name":"Office National Des Forets (onf)",
    "wof:placetype":"venue"
},
  "geometry": {"coordinates":[2.246763,43.602215],"type":"Point"}
}