{
  "type": "Feature",
  "properties": {
    "addr:full":"B.P. 367, 44816 Saint Herblain C\u00e9dex^^Rue G. Marconi - Le Moulin Neuf, 44800 Saint Herblain Pays de Loire",
    "addr:housenumber":"b.p. 367",
    "addr:postcode":"44816;44800",
    "addr:street":"Ce\u0301Dex^^Rue G. Marconi;Moulin Neuf;Herblain",
    "iso:country":"FR",
    "sg:address":"B.P. 367, 44816 Saint Herblain C\u00e9dex^^Rue G. Marconi - Le Moulin Neuf, 44800 Saint Herblain",
    "sg:orig_category":"Non-Classified Establishments",
    "sg:phone":"+33 2 40 92 23 23",
    "sg:province":"Pays de Loire",
    "wof:name":"Jes S.a.",
    "wof:placetype":"venue"
},
  "geometry": {"coordinates":[-1.620873,47.22736],"type":"Point"}
}