{
  "type": "Feature",
  "properties": {
    "addr:full":"19, Rue de l'H\u00f4tel de Ville, 77890 Beaumont du G\u00e2tinais Ile de France",
    "addr:housenumber":"19",
    "addr:postcode":"77890",
    "addr:street":"Rue De L'Ho \u0302Tel De Ville",
    "iso:country":"FR",
    "sg:address":"19, Rue de l'H\u00f4tel de Ville, 77890 Beaumont du G\u00e2tinais",
    "sg:orig_category":"Unclassifiable Establishments",
    "sg:phone":"+33 1 64 29 96 30",
    "sg:province":"Ile de France",
    "wof:name":"M\u00e9sutronic France",
    "wof:placetype":"venue"
},
  "geometry": {"coordinates":[2.477284,48.137547],"type":"Point"}
}