{
  "type": "Feature",
  "properties": {
    "addr:full":"226 R De La R\u00e9publique 59541 Caudry Cedex Nord Pas-de-Calais",
    "addr:housenumber":"226",
    "addr:postcode":"59541;cedex nord",
    "addr:street":"R De La Re\u0301Publique",
    "iso:country":"FR",
    "sg:address":"226 R De La R\u00e9publique 59541 Caudry Cedex",
    "sg:classifiers":[
        {
            "category":"Shopping",
            "subcategory":"Crafts & Fabrics",
            "type":"Retail Goods"
        }
    ],
    "sg:phone":"+33 3 27 85 22 66",
    "sg:province":"Nord Pas-de-Calais",
    "sg:tags":[
        "textile",
        "clothing"
    ],
    "wof:name":"Bouillon Sa",
    "wof:placetype":"venue"
},
  "geometry": {"coordinates":[3.40071,50.135506],"type":"Point"}
}