{
  "type": "Feature",
  "properties": {
    "addr:full":"21 rue du Logis 79400 Azay Le Brul\u00e9 Poitou-Charentes 79400",
    "addr:housenumber":"21",
    "addr:postcode":"79400;79400",
    "addr:street":"Rue Du Logis;Azay Le Brule\u0301",
    "iso:country":"FR",
    "sg:address":"21 rue du Logis 79400 Azay Le Brul\u00e9",
    "sg:classifiers":[
        {
            "category":"Bus Stop",
            "subcategory":"None",
            "type":"Transportation"
        }
    ],
    "sg:phone":"+33 5 49 06 60 28",
    "sg:postcode":"79400",
    "sg:province":"Poitou-Charentes",
    "sg:tags":[
        "trucks",
        "buses",
        "cars",
        "system",
        "driver's",
        "air-conditioning",
        "cab",
        "crane"
    ],
    "wof:name":"Vim S.a.",
    "wof:placetype":"venue"
},
  "geometry": {"coordinates":[-0.246839,46.40073],"type":"Point"}
}