{
  "type": "Feature",
  "properties": {
    "iso:country":"FR",
    "sg:address":"Chemin des C\u00f4teaux",
    "sg:city":"Bourdettes",
    "sg:orig_category":"Unclassifiable Establishments",
    "sg:phone":"+33 5 59 61 15 43",
    "sg:postcode":"64800",
    "sg:province":"Aquitaine",
    "wof:name":"Petit Boys S.a.",
    "wof:placetype":"venue"
},
  "geometry": {"coordinates":[-0.252886,43.090973],"type":"Point"}
}