{
  "type": "Feature",
  "properties": {
    "iso:country":"FR",
    "sg:address":"Rue du Pr\u00e9 de la Mare - Z.A. du Bourg",
    "sg:city":"Gergy",
    "sg:orig_category":"Unclassifiable Establishments",
    "sg:phone":"+33 3 85 98 98 98",
    "sg:postcode":"71590",
    "sg:province":"Bourgogne",
    "wof:name":"A\u00e9rom\u00e9tal S.a.",
    "wof:placetype":"venue"
},
  "geometry": {"coordinates":[4.954137,46.863567],"type":"Point"}
}