{
  "type": "Feature",
  "properties": {
    "iso:country":"FR",
    "sg:address":"Lieu Dit D Arny Zone Industrielle 91680 Bruyeres Le Chatel",
    "sg:classifiers":[
        {
            "category":"Manufacturing",
            "subcategory":"Metals",
            "type":"Manufacturing & Wholesale Goods"
        }
    ],
    "sg:phone":"+33 1 64 90 21 08",
    "sg:postcode":"91680",
    "sg:province":"Ile de France",
    "sg:tags":[
        "metallurgy",
        "metalworking",
        "processing"
    ],
    "wof:name":"Societe D'assemblages Par Faisceaux D'electrons Et Laser (safel)",
    "wof:placetype":"venue"
},
  "geometry": {"coordinates":[2.192535,48.59354],"type":"Point"}
}