{
  "type": "Feature",
  "properties": {
    "iso:country":"FR",
    "sg:address":"852, Quartier la Roseyre, 06390 Contes",
    "sg:orig_category":"Non-Classified Establishments",
    "sg:phone":"+33 4 93 91 60 10",
    "sg:province":"Franche Comt\u00e9",
    "wof:name":"Aluminor S.a.",
    "wof:placetype":"venue"
},
  "geometry": {"coordinates":[7.32517,43.795315],"type":"Point"}
}