{
  "type": "Feature",
  "properties": {
    "iso:country":"FR",
    "sg:address":"455 Pro Des Anglais Immeuble Communica 06200 Nice",
    "sg:classifiers":[
        {
            "category":"Wholesale",
            "subcategory":"Medical Equipment & Supplies",
            "type":"Manufacturing & Wholesale Goods"
        }
    ],
    "sg:phone":"+33 4 97 25 85 00",
    "sg:province":"Haute Normandie",
    "sg:tags":[
        "instrument",
        "health",
        "-",
        "precision"
    ],
    "wof:name":"Agilent Technologies France (agilent Tech)",
    "wof:placetype":"venue"
},
  "geometry": {"coordinates":[7.215069,43.667114],"type":"Point"}
}