{
  "type": "Feature",
  "properties": {
    "addr:full":"ZI de la Loue Montlu\u00e7on Auvergne 03100",
    "addr:postcode":"03100",
    "addr:street":"Zi De La Loue",
    "iso:country":"FR",
    "sg:address":"ZI de la Loue",
    "sg:city":"Montlu\u00e7on",
    "sg:orig_category":"Unclassifiable Establishments",
    "sg:phone":"+33 4 70 05 48 90",
    "sg:postcode":"03100",
    "sg:province":"Auvergne",
    "wof:name":"03 France Express S.a.",
    "wof:placetype":"venue"
},
  "geometry": {"coordinates":[2.602068,46.338787],"type":"Point"}
}