{
  "type": "Feature",
  "properties": {
    "addr:full":"Route De Najauge 08320 Hierges Aubrives Champagne 08320",
    "addr:postcode":"08320;08320",
    "addr:street":"Route De Najauge;Champagne",
    "iso:country":"FR",
    "sg:address":"Route De Najauge 08320 Hierges",
    "sg:city":"Aubrives",
    "sg:classifiers":[
        {
            "category":"Shopping",
            "type":"Retail Goods"
        }
    ],
    "sg:phone":"+33 3 24 41 78 94",
    "sg:postcode":"08320",
    "sg:province":"Champagne",
    "sg:tags":[
        "metallurgy",
        "finished",
        "-",
        "metalworking",
        "metallic"
    ],
    "wof:name":"Atelier De Chaudronnerie Et Metallerie De Precision (acmp)",
    "wof:placetype":"venue"
},
  "geometry": {"coordinates":[4.73813,50.087101],"type":"Point"}
}