{
  "type": "Feature",
  "properties": {
    "addr:full":"18, Rue Gabriel Sarrazin, 69008 Lyon Rhone-Alpes 69008",
    "addr:housenumber":"18",
    "addr:postcode":"69008;69008",
    "addr:street":"Rue Gabriel Sarrazin",
    "iso:country":"FR",
    "sg:address":"18, Rue Gabriel Sarrazin, 69008 Lyon",
    "sg:orig_category":"Non-Classified Establishments",
    "sg:phone":"+33 4 78 74 18 85",
    "sg:postcode":"69008",
    "sg:province":"Rhone-Alpes",
    "wof:name":"S\u00e9rrano S.a.r.l.",
    "wof:placetype":"venue"
},
  "geometry": {"coordinates":[4.877867,45.740082],"type":"Point"}
}