{
  "type": "Feature",
  "properties": {
    "iso:country":"FR",
    "sg:address":"11 Rue Moli\u00e8re 13001 Marseille",
    "sg:classifiers":[
        {
            "category":"Professional",
            "subcategory":"Printing & Photocopies",
            "type":"Services"
        }
    ],
    "sg:phone":"+33 4 91 33 57 14",
    "sg:province":"Poitou-Charentes",
    "sg:tags":[
        "publishing"
    ],
    "wof:name":"Diffusion Generale De Librairie Sa",
    "wof:placetype":"venue"
},
  "geometry": {"coordinates":[5.376319,43.29343],"type":"Point"}
}