{
  "type": "Feature",
  "properties": {
    "iso:country":"FR",
    "sg:address":"Chemin des Sept Deniers - Parc Club 78 - B\u00e2t. 2",
    "sg:city":"Toulouse",
    "sg:orig_category":"Non-Classified Establishments",
    "sg:phone":"+33 5 62 72 07 08",
    "sg:postcode":"31200",
    "sg:province":"Midi Pyr\u00e9n\u00e9es",
    "wof:name":"Soci\u00e9t\u00e9 Suisse A.d.g. S.a.",
    "wof:placetype":"venue"
},
  "geometry": {"coordinates":[1.411881,43.620327],"type":"Point"}
}