{
  "type": "Feature",
  "properties": {
    "iso:country":"FR",
    "sg:address":"1, Av. du Brugeaud, 79250 Bessines",
    "sg:orig_category":"Unclassifiable Establishments",
    "sg:phone":"+33 5 55 60 50 00",
    "sg:postcode":"79250",
    "sg:province":"Poitou-Charentes",
    "wof:name":"Algade S.a.r.l.",
    "wof:placetype":"venue"
},
  "geometry": {"coordinates":[-101.665009,33.932171],"type":"Point"}
}