{
  "type": "Feature",
  "properties": {
    "iso:country":"FR",
    "sg:address":"BP 2070, 144 route de Thionville, 57051 Metz Cedex 2, Dept 57",
    "sg:city":"Vill\u00e9",
    "sg:classifiers":[
        {
            "category":"Banks & Credit Unions",
            "subcategory":"Bank",
            "type":"Services"
        }
    ],
    "sg:postcode":"67220",
    "sg:province":"Alsace",
    "wof:name":"Banque Du Cr\u00e9dit Mutuel Lorrain",
    "wof:placetype":"venue"
},
  "geometry": {"coordinates":[6.164996,49.141842],"type":"Point"}
}