{
  "type": "Feature",
  "properties": {
    "iso:country":"FR",
    "sg:address":"Linglas 29470 Loperhet",
    "sg:city":"Loperhet",
    "sg:classifiers":[
        {
            "category":"Farming",
            "subcategory":"Fish & Marine Products",
            "type":"Manufacturing & Wholesale Goods"
        }
    ],
    "sg:phone":"+33 2 98 34 33 00",
    "sg:postcode":"29470",
    "sg:province":"Bretagne",
    "sg:tags":[
        "animal",
        "food",
        "related",
        "grain",
        "cereal",
        "breeding"
    ],
    "wof:name":"Cobrena",
    "wof:placetype":"venue"
},
  "geometry": {"coordinates":[-4.288661,48.383743],"type":"Point"}
}