{
  "type": "Feature",
  "properties": {
    "iso:country":"FR",
    "sg:address":"13 rue Condorcet ZI les Radars 91351 GRIGNY",
    "sg:classifiers":[
        {
            "category":"Manufacturing",
            "subcategory":"Printing",
            "type":"Manufacturing & Wholesale Goods"
        }
    ],
    "sg:phone":"+33 1 69 02 45 45",
    "sg:province":"Poitou-Charentes",
    "sg:tags":[
        "house",
        "book"
    ],
    "wof:name":"Ste Nouvelle Mizeret Sa",
    "wof:placetype":"venue"
},
  "geometry": {"coordinates":[2.393095,48.653549],"type":"Point"}
}