{
  "type": "Feature",
  "properties": {
    "addr:full":"les Troques 69630 CHAPONOST Rhone-Alpes",
    "addr:postcode":"69630",
    "iso:country":"FR",
    "sg:address":"les Troques 69630 CHAPONOST",
    "sg:classifiers":[
        {
            "category":"Food & Beverages",
            "subcategory":"Meat & Fish",
            "type":"Retail Goods"
        }
    ],
    "sg:phone":"+33 4 72 39 59 39",
    "sg:province":"Rhone-Alpes",
    "sg:tags":[
        "bacon",
        "ham"
    ],
    "wof:name":"Chevallier Sa",
    "wof:placetype":"venue"
},
  "geometry": {"coordinates":[4.762128,45.698334],"type":"Point"}
}