{
  "type": "Feature",
  "properties": {
    "iso:country":"FR",
    "sg:address":"Rue Marcel Bruneli\u00e8re",
    "sg:city":"Machecoul",
    "sg:orig_category":"Non-Classified Establishments",
    "sg:phone":"+33 2 40 78 23 23",
    "sg:postcode":"44270",
    "sg:province":"Pays de Loire",
    "wof:name":"Machecoul Cycleurope S.a.",
    "wof:placetype":"venue"
},
  "geometry": {"coordinates":[-1.811949,46.984825],"type":"Point"}
}