{
  "type": "Feature",
  "properties": {
    "iso:country":"FR",
    "sg:address":"1 rte Fogot; Loperhet",
    "sg:city":"Loperhet",
    "sg:classifiers":[
        {
            "category":"Banks & Credit Unions",
            "subcategory":"Bank",
            "type":"Services"
        }
    ],
    "sg:phone":"+33 3398070369",
    "sg:postcode":"29470",
    "sg:province":"Bretagne",
    "wof:name":"Cr\u00e9dit Mutuel Bretagne",
    "wof:placetype":"venue"
},
  "geometry": {"coordinates":[-4.304259,48.375332],"type":"Point"}
}