{
  "type": "Feature",
  "properties": {
    "iso:country":"FR",
    "sg:address":"9 R L\u00e9o Lagrange 42270 St Priest En Jarez",
    "sg:classifiers":[
        {
            "category":"Professional",
            "subcategory":"Engineering",
            "type":"Services"
        }
    ],
    "sg:phone":"+33 4 77 91 18 40",
    "sg:postcode":"42270",
    "sg:province":"Rhone-Alpes",
    "sg:tags":[
        "machine",
        "-",
        "mechanical"
    ],
    "wof:name":"Shmp",
    "wof:placetype":"venue"
},
  "geometry": {"coordinates":[4.386164,45.475395],"type":"Point"}
}