{
  "type": "Feature",
  "properties": {
    "addr:full":"B.P. 295, 17312 Rochefort C\u00e9dex^^57, Av. Bernadotte, 17300 Rochefort Poitou-Charentes 17300",
    "addr:housenumber":"b.p. 295",
    "addr:postcode":"17312;17300 rochefort;17300",
    "addr:street":"Av. Bernadotte",
    "iso:country":"FR",
    "sg:address":"B.P. 295, 17312 Rochefort C\u00e9dex^^57, Av. Bernadotte, 17300 Rochefort",
    "sg:orig_category":"Non-Classified Establishments",
    "sg:phone":"+33 5 46 83 60 00",
    "sg:postcode":"17300",
    "sg:province":"Poitou-Charentes",
    "wof:name":"A.f.p.a.",
    "wof:placetype":"venue"
},
  "geometry": {"coordinates":[-0.958704,45.934818],"type":"Point"}
}