{
  "type": "Feature",
  "properties": {
    "addr:full":"Rte de Valeille Feurs Rhone-Alpes 42110",
    "addr:postcode":"42110",
    "addr:street":"Rte De Valeille;Rhone-Alpes",
    "iso:country":"FR",
    "sg:address":"Rte de Valeille",
    "sg:city":"Feurs",
    "sg:orig_category":"Non-Classified Establishments",
    "sg:phone":"+33 4 77 27 50 00",
    "sg:postcode":"42110",
    "sg:province":"Rhone-Alpes",
    "wof:name":"B.s.a. Distribution S.a.",
    "wof:placetype":"venue"
},
  "geometry": {"coordinates":[4.234931,45.735519],"type":"Point"}
}