{
  "type": "Feature",
  "properties": {
    "addr:full":"4 Rue De La Ferme 68700 Cernay Cernay Alsace 68700",
    "addr:housenumber":"4",
    "addr:postcode":"68700;68700",
    "addr:street":"Rue De La Ferme",
    "iso:country":"FR",
    "sg:address":"4 Rue De La Ferme 68700 Cernay",
    "sg:city":"Cernay",
    "sg:classifiers":[
        {
            "category":"Shopping",
            "subcategory":"Hobbies, Toys, & Games",
            "type":"Retail Goods"
        }
    ],
    "sg:phone":"+33 3 89 38 32 00",
    "sg:postcode":"68700",
    "sg:province":"Alsace",
    "sg:tags":[
        "product",
        "miscellaneous",
        "entertainment"
    ],
    "wof:name":"Aubert Sa",
    "wof:placetype":"venue"
},
  "geometry": {"coordinates":[7.168314,47.799484],"type":"Point"}
}