{
  "type": "Feature",
  "properties": {
    "addr:full":"78156 Le Chesnay C\u00e9dex^^4, Rue du Ch\u00e8vreloup, 78150 Rocquencourt Ile de France",
    "addr:postcode":"78156;78150;ile",
    "addr:street":"Rue Du Che\u0300Vreloup",
    "iso:country":"FR",
    "sg:address":"78156 Le Chesnay C\u00e9dex^^4, Rue du Ch\u00e8vreloup, 78150 Rocquencourt",
    "sg:orig_category":"Non-Classified Establishments",
    "sg:phone":"+33 1 39 54 33 28",
    "sg:province":"Ile de France",
    "wof:name":"Quavis System S.a.",
    "wof:placetype":"venue"
},
  "geometry": {"coordinates":[2.12592,48.825603],"type":"Point"}
}