{
  "type": "Feature",
  "properties": {
    "addr:full":"Avenue Du Viguier Zac De Villeneuve 34420 Villeneuve Les Beziers Languedoc-Roussillon 34420",
    "addr:postcode":"34420;34420",
    "addr:street":"Avenue Du Viguier Zac De Villeneuve;Beziers",
    "iso:country":"FR",
    "sg:address":"Avenue Du Viguier Zac De Villeneuve 34420 Villeneuve Les Beziers",
    "sg:classifiers":[
        {
            "category":"Shopping",
            "subcategory":"Clothing, Apparel, & Fashions",
            "type":"Retail Goods"
        }
    ],
    "sg:phone":"+33 4 67 35 89 00",
    "sg:postcode":"34420",
    "sg:province":"Languedoc-Roussillon",
    "sg:tags":[
        "textile",
        "clothing",
        "clothes"
    ],
    "wof:name":"Brasseries Heineken (bh)",
    "wof:placetype":"venue"
},
  "geometry": {"coordinates":[3.334264,43.303394],"type":"Point"}
}