{
  "type": "Feature",
  "properties": {
    "iso:country":"FR",
    "sg:address":"Rte de Nantes",
    "sg:city":"Montaigu",
    "sg:orig_category":"Unclassifiable Establishments",
    "sg:phone":"+33 2 51 94 01 04",
    "sg:postcode":"85600",
    "sg:province":"Pays de Loire",
    "wof:name":"Boutet S.a.r.l.",
    "wof:placetype":"venue"
},
  "geometry": {"coordinates":[-1.319044,46.9841],"type":"Point"}
}