{
  "type": "Feature",
  "properties": {
    "iso:country":"FR",
    "sg:address":"Chemin d'Imling",
    "sg:city":"Sarrebourg",
    "sg:orig_category":"Unclassifiable Establishments",
    "sg:phone":"+33 3 87 23 82 66",
    "sg:postcode":"57400",
    "sg:province":"Lorraine",
    "wof:name":"Nicolait S.a.",
    "wof:placetype":"venue"
},
  "geometry": {"coordinates":[7.02248,48.719929],"type":"Point"}
}