{
  "type": "Feature",
  "properties": {
    "iso:country":"FR",
    "sg:address":"102 Av De La Libert\u00e9 94700 Maisons Alfort",
    "sg:classifiers":[
        {
            "category":"Building & Trades",
            "subcategory":"Construction",
            "type":"Services"
        }
    ],
    "sg:phone":"+33 1 43 53 62 10",
    "sg:postcode":"94700",
    "sg:province":"Ile de France",
    "sg:tags":[
        "work",
        "public"
    ],
    "wof:name":"Sotraisol Sa",
    "wof:placetype":"venue"
},
  "geometry": {"coordinates":[2.432763,48.790058],"type":"Point"}
}