{
  "type": "Feature",
  "properties": {
    "addr:full":"30 Rue De Chabrol 75010 Paris Ile de France",
    "addr:housenumber":"30",
    "addr:postcode":"75010",
    "addr:street":"Rue De Chabrol",
    "iso:country":"FR",
    "sg:address":"30 Rue De Chabrol 75010 Paris",
    "sg:classifiers":[
        {
            "category":"Professional",
            "subcategory":"Printing & Photocopies",
            "type":"Services"
        }
    ],
    "sg:phone":"+33 1 40 22 75 00",
    "sg:province":"Ile de France",
    "sg:tags":[
        "publishing"
    ],
    "wof:name":"Editions Bauer",
    "wof:placetype":"venue"
},
  "geometry": {"coordinates":[2.352908,48.876991],"type":"Point"}
}