{
  "type": "Feature",
  "properties": {
    "addr:full":"11, Rue des R\u00e9mouleurs, 51350 Cormontreuil Champagne",
    "addr:housenumber":"11",
    "addr:postcode":"51350",
    "addr:street":"Rue Des Re\u0301Mouleurs",
    "iso:country":"FR",
    "sg:address":"11, Rue des R\u00e9mouleurs, 51350 Cormontreuil",
    "sg:orig_category":"Unclassifiable Establishments",
    "sg:phone":"+33 3 26 05 19 33",
    "sg:province":"Champagne",
    "wof:name":"F.s.b.l. S.a.r.l. - Froid Service Bordet Laplace",
    "wof:placetype":"venue"
},
  "geometry": {"coordinates":[4.064509,49.215828],"type":"Point"}
}