{
  "type": "Feature",
  "properties": {
    "addr:full":"11 Chasles; Rambouillet; 78120 Ile de France 78120",
    "addr:housenumber":"11",
    "addr:postcode":"78120;78120",
    "addr:street":"Chasles Rambouillet;France",
    "iso:country":"FR",
    "sg:address":"11",
    "sg:city":"Chasles; Rambouillet; 78120",
    "sg:classifiers":[
        {
            "category":"Banks & Credit Unions",
            "subcategory":"Bank",
            "type":"Services"
        }
    ],
    "sg:phone":"+33 3334831045",
    "sg:postcode":"78120",
    "sg:province":"Ile de France",
    "wof:name":"Banque Nationale De Paris",
    "wof:placetype":"venue"
},
  "geometry": {"coordinates":[1.82709,48.642879],"type":"Point"}
}