{
  "type": "Feature",
  "properties": {
    "addr:full":"7 Rue De Thorigny 75003 Paris Ile de France 75003",
    "addr:housenumber":"7",
    "addr:postcode":"75003;75003",
    "addr:street":"Rue De Thorigny",
    "iso:country":"FR",
    "sg:address":"7 Rue De Thorigny 75003 Paris",
    "sg:classifiers":[
        {
            "category":"Shopping",
            "subcategory":"Clothing, Apparel, & Fashions",
            "type":"Retail Goods"
        }
    ],
    "sg:phone":"+33 1 42 72 69 31",
    "sg:postcode":"75003",
    "sg:province":"Ile de France",
    "sg:tags":[
        "textile",
        "clothing",
        "clothes"
    ],
    "wof:name":"Habinou",
    "wof:placetype":"venue"
},
  "geometry": {"coordinates":[2.362855,48.859879],"type":"Point"}
}