{
  "type": "Feature",
  "properties": {
    "addr:full":"78306 Poissy C\u00e9dex^^9, Rue Charles Edouard Jeanneret - Technoparc, 78300 Poissy Ile de France 78300",
    "addr:postcode":"78306;78300;ile;78300",
    "addr:street":"Rue Charles Edouard Jeanneret Technoparc;France",
    "iso:country":"FR",
    "sg:address":"78306 Poissy C\u00e9dex^^9, Rue Charles Edouard Jeanneret - Technoparc, 78300 Poissy",
    "sg:orig_category":"Non-Classified Establishments",
    "sg:phone":"+33 1 39 11 48 80",
    "sg:postcode":"78300",
    "sg:province":"Ile de France",
    "wof:name":"Burostar S.a.",
    "wof:placetype":"venue"
},
  "geometry": {"coordinates":[2.04256,48.927971],"type":"Point"}
}