{
  "type": "Feature",
  "properties": {
    "iso:country":"FR",
    "sg:address":"2 Avenue De Kaolac 33700 Merignac",
    "sg:city":"M\u00e9rignac",
    "sg:classifiers":[
        {
            "category":"Home & Garden",
            "subcategory":"Furniture",
            "type":"Retail Goods"
        }
    ],
    "sg:phone":"+33 5 56 13 11 60",
    "sg:postcode":"33700",
    "sg:province":"Aquitaine",
    "sg:tags":[
        "household",
        "wood"
    ],
    "wof:name":"L'atelier D'agencement",
    "wof:placetype":"venue"
},
  "geometry": {"coordinates":[-0.66581,44.820919],"type":"Point"}
}