{
  "type": "Feature",
  "properties": {
    "iso:country":"FR",
    "sg:address":"B.P. 71, 59582 Marly C\u00e9dex^^Rue du 19 Mars 1962, 59770 Marly",
    "sg:orig_category":"Non-Classified Establishments",
    "sg:phone":"+33 3 27 33 33 96",
    "sg:province":"Nord Pas-de-Calais",
    "wof:name":"Solideal France S.a.r.l.",
    "wof:placetype":"venue"
},
  "geometry": {"coordinates":[3.54378,50.350315],"type":"Point"}
}