{
  "type": "Feature",
  "properties": {
    "iso:country":"FR",
    "sg:address":"1075 Av De Bruxelles 66962 Perpignan Cedex 9",
    "sg:classifiers":[
        {
            "category":"Wholesale",
            "subcategory":"Farm Supplies",
            "type":"Manufacturing & Wholesale Goods"
        }
    ],
    "sg:phone":"+33 4 68 54 18 22",
    "sg:province":"Lorraine",
    "sg:tags":[
        "-",
        "machine",
        "equipment",
        "engineering",
        "machinery",
        "mechanical",
        "agriculture"
    ],
    "wof:name":"Mercier Sanchez",
    "wof:placetype":"venue"
},
  "geometry": {"coordinates":[2.84868,42.692131],"type":"Point"}
}