{
  "type": "Feature",
  "properties": {
    "addr:full":"7 Rue Pierre Curie 68012 Colmar Cedex Alsace",
    "addr:housenumber":"7",
    "addr:postcode":"68012;cedex",
    "addr:street":"Rue Pierre Curie",
    "iso:country":"FR",
    "sg:address":"7 Rue Pierre Curie 68012 Colmar Cedex",
    "sg:classifiers":[
        {
            "category":"Manufacturing",
            "subcategory":"Rubber & Plastics",
            "type":"Manufacturing & Wholesale Goods"
        }
    ],
    "sg:phone":"+33 3 89 23 05 75",
    "sg:province":"Alsace",
    "wof:name":"Eglinsdoerfer Pfohl Sa",
    "wof:placetype":"venue"
},
  "geometry": {"coordinates":[7.36206,48.08844],"type":"Point"}
}