{
  "type": "Feature",
  "properties": {
    "addr:full":"18-22 rue de Verdun 69100 Villeurbanne Rhone-Alpes",
    "addr:housenumber":"18-22",
    "addr:postcode":"69100",
    "addr:street":"Rue De Verdun",
    "iso:country":"FR",
    "sg:address":"18-22 rue de Verdun 69100 Villeurbanne",
    "sg:orig_category":"Safety Shock Absorbers",
    "sg:phone":"+33 4 72 04 26 00",
    "sg:province":"Rhone-Alpes",
    "wof:name":"Emc Experience Maximum Control S.a.",
    "wof:placetype":"venue"
},
  "geometry": {"coordinates":[4.897115,45.784351],"type":"Point"}
}