{
  "type": "Feature",
  "properties": {
    "addr:full":"Chateau D Ampuis 69420 AMPUIS Rhone-Alpes 69420",
    "addr:postcode":"69420;69420",
    "addr:street":"Rhone-Alpes",
    "iso:country":"FR",
    "sg:address":"Chateau D Ampuis 69420 AMPUIS",
    "sg:classifiers":[
        {
            "category":"Wholesale",
            "subcategory":"Wine & Distilled Alcoholic Beverages",
            "type":"Manufacturing & Wholesale Goods"
        }
    ],
    "sg:phone":"+33 4 74 56 10 22",
    "sg:postcode":"69420",
    "sg:province":"Rhone-Alpes",
    "sg:tags":[
        "french"
    ],
    "wof:name":"E.guigal Sa",
    "wof:placetype":"venue"
},
  "geometry": {"coordinates":[4.838305,45.504742],"type":"Point"}
}