{
  "type": "Feature",
  "properties": {
    "iso:country":"FR",
    "sg:address":"Rte De Sabl\u00e9 49330 Champign\u00e9",
    "sg:classifiers":[
        {
            "category":"Bakery",
            "type":"Food & Drink"
        }
    ],
    "sg:phone":"+33 2 41 96 15 74",
    "sg:postcode":"49330",
    "sg:province":"Pays de Loire",
    "sg:tags":[
        "cake",
        "product",
        "related",
        "bread"
    ],
    "wof:name":"Pomone",
    "wof:placetype":"venue"
},
  "geometry": {"coordinates":[-0.606432,47.62117],"type":"Point"}
}