{
  "type": "Feature",
  "properties": {
    "iso:country":"FR",
    "sg:address":"14, Rue du Temple, 75189 Paris C\u00e9dex 04",
    "sg:orig_category":"Non-Classified Establishments",
    "sg:phone":"+33 1 53 01 40 30",
    "sg:province":"Ile-de-France",
    "wof:name":"Kyrielles Groupe Galeries Lafayette G.i.e.",
    "wof:placetype":"venue"
},
  "geometry": {"coordinates":[2.353021,48.857788],"type":"Point"}
}