{
  "type": "Feature",
  "properties": {
    "iso:country":"FR",
    "sg:address":"ham Bretonni\u00e8re 37190 Sach\u00e9",
    "sg:city":"Sach\u00e9",
    "sg:classifiers":[
        {
            "category":"Professional",
            "subcategory":"Advertising",
            "type":"Services"
        }
    ],
    "sg:phone":"+33 2 47 34 66 00",
    "sg:postcode":"37190",
    "sg:province":"Centre",
    "sg:tags":[
        "information",
        "medium",
        "communication"
    ],
    "wof:name":"Tfv",
    "wof:placetype":"venue"
},
  "geometry": {"coordinates":[0.519965,47.239765],"type":"Point"}
}