{
  "type": "Feature",
  "properties": {
    "iso:country":"FR",
    "sg:address":"19, Rue Centuelle, 64400 Oloron Sainte Marie",
    "sg:city":"Oloron-Sainte-Marie",
    "sg:orig_category":"Unclassifiable Establishments",
    "sg:phone":"+33 5 59 36 08 09",
    "sg:postcode":"64400",
    "sg:province":"Aquitaine",
    "wof:name":"Emploi Service",
    "wof:placetype":"venue"
},
  "geometry": {"coordinates":[-0.605439,43.189369],"type":"Point"}
}