{
  "type": "Feature",
  "properties": {
    "addr:full":"1 Av Platanes 78940 La Queue Les Yvelines Ile de France 78940",
    "addr:postcode":"78940;78940",
    "addr:street":"Av Platanes;Queue",
    "iso:country":"FR",
    "sg:address":"1 Av Platanes 78940 La Queue Les Yvelines",
    "sg:orig_category":"Games and entertainment Horticulture Miscellaneous Products",
    "sg:phone":"+33 1 34 86 24 00",
    "sg:postcode":"78940",
    "sg:province":"Ile de France",
    "wof:name":"Horti Service",
    "wof:placetype":"venue"
},
  "geometry": {"coordinates":[1.777912,48.804447],"type":"Point"}
}