{
  "type": "Feature",
  "properties": {
    "iso:country":"FR",
    "sg:address":"1, Rue du Fbg de B\u00e9thune, 59000 Lille",
    "sg:orig_category":"Non-Classified Establishments",
    "sg:phone":"+33 3 20 07 07 80",
    "sg:postcode":"59000",
    "sg:province":"Nord Pas-de-Calais",
    "wof:name":"Durr Nouveaux Etablissements S.a.",
    "wof:placetype":"venue"
},
  "geometry": {"coordinates":[3.02975,50.617981],"type":"Point"}
}