{
  "type": "Feature",
  "properties": {
    "iso:country":"FR",
    "sg:address":"Moulin D'Enfour 09600 Laroque D'Olmes",
    "sg:classifiers":[
        {
            "category":"Professional",
            "subcategory":"Engineering",
            "type":"Services"
        }
    ],
    "sg:phone":"+33 5 61 01 46 60",
    "sg:postcode":"09600",
    "sg:province":"Midi Pyr\u00e9n\u00e9es",
    "sg:tags":[
        "machine",
        "-",
        "mechanical"
    ],
    "wof:name":"Ets Andre Icre Sarl",
    "wof:placetype":"venue"
},
  "geometry": {"coordinates":[-73.647232,41.523285],"type":"Point"}
}