{
  "type": "Feature",
  "properties": {
    "addr:full":"ZI de la Naurais Bachaud Naintr\u00e9 Poitou-Charentes 86530",
    "addr:postcode":"86530",
    "addr:street":"Zi De La Naurais Bachaud Naintre\u0301",
    "iso:country":"FR",
    "sg:address":"ZI de la Naurais Bachaud",
    "sg:city":"Naintr\u00e9",
    "sg:orig_category":"Non-Classified Establishments",
    "sg:phone":"+33 5 49 90 08 61",
    "sg:postcode":"86530",
    "sg:province":"Poitou-Charentes",
    "wof:name":"L.m.86 S.a.r.l. - Laboratoire De M\u00e9trologie De La Vienne",
    "wof:placetype":"venue"
},
  "geometry": {"coordinates":[0.48177,46.758995],"type":"Point"}
}