{
  "type": "Feature",
  "properties": {
    "iso:country":"FR",
    "sg:address":"3, Rue Meyerbeer, 75009 Paris",
    "sg:orig_category":"Non-Classified Establishments",
    "sg:phone":"+33 1 47 42 68 68",
    "sg:postcode":"75009",
    "sg:province":"Ile de France",
    "wof:name":"Compagnie De Croisi\u00e8res Festival France S.a.",
    "wof:placetype":"venue"
},
  "geometry": {"coordinates":[2.333423,48.871735],"type":"Point"}
}