{
  "type": "Feature",
  "properties": {
    "iso:country":"FR",
    "sg:address":"Pl De L'Eglise 22780 Loguivy Plougras",
    "sg:city":"Plougras",
    "sg:classifiers":[
        {
            "category":"Professional",
            "subcategory":"Engineering",
            "type":"Services"
        }
    ],
    "sg:phone":"+33 2 96 46 68 90",
    "sg:postcode":"22780",
    "sg:province":"Bretagne",
    "sg:tags":[
        "ma",
        "business",
        "advice",
        "-",
        "equipment",
        "machinery",
        "mechanical",
        "agriculture"
    ],
    "wof:name":"Ste Alexandre Machines Agricoles Sarl",
    "wof:placetype":"venue"
},
  "geometry": {"coordinates":[-3.487797,48.521255],"type":"Point"}
}