{
  "type": "Feature",
  "properties": {
    "iso:country":"FR",
    "sg:address":"B.P. 319, 85403 Lucon C\u00e9dex^^45, Av. Wilson, 85400 Lucon",
    "sg:orig_category":"Non-Classified Establishments",
    "sg:phone":"+33 2 51 29 14 14",
    "sg:postcode":"85400",
    "sg:province":"Pays de Loire",
    "wof:name":"Etablissement Libaud S.a.",
    "wof:placetype":"venue"
},
  "geometry": {"coordinates":[-1.266444,46.447922],"type":"Point"}
}