{
  "type": "Feature",
  "properties": {
    "iso:country":"FR",
    "sg:address":"22",
    "sg:city":"Louis Armand 75015 PARIS",
    "sg:classifiers":[
        {
            "category":"Autos & Motor Vehicles",
            "subcategory":"Automobile Sales",
            "type":"Retail Goods"
        }
    ],
    "sg:phone":"+33 1 45 57 74 74",
    "sg:postcode":"75015",
    "sg:province":"Ile de France",
    "sg:tags":[
        "equipment",
        "motor-cars",
        "transport"
    ],
    "wof:name":"Alte",
    "wof:placetype":"venue"
},
  "geometry": {"coordinates":[2.27867,48.832741],"type":"Point"}
}