{
  "type": "Feature",
  "properties": {
    "addr:full":"Rte Toulouse Cidex 4033 31840 Seilh Midi Pyr\u00e9n\u00e9es",
    "addr:housenumber":"4033",
    "addr:postcode":"31840",
    "addr:street":"Rte Toulouse",
    "iso:country":"FR",
    "sg:address":"Rte Toulouse Cidex 4033 31840 Seilh",
    "sg:classifiers":[
        {
            "category":"Professional",
            "type":"Services"
        }
    ],
    "sg:phone":"+33 5 61 77 06 20",
    "sg:province":"Midi Pyr\u00e9n\u00e9es",
    "sg:tags":[
        "transport",
        "road"
    ],
    "wof:name":"Demenageurs Bretons Thyal Commercant Independant",
    "wof:placetype":"venue"
},
  "geometry": {"coordinates":[1.318074,43.682056],"type":"Point"}
}