{
  "type": "Feature",
  "properties": {
    "addr:full":"4 Rue De Boudieu Zi De Lescudilliers 15000 Aurillac Aurillac Auvergne 15000",
    "addr:housenumber":"4",
    "addr:postcode":"15000;15000",
    "addr:street":"Rue De Boudieu Zi De Lescudilliers",
    "iso:country":"FR",
    "sg:address":"4 Rue De Boudieu Zi De Lescudilliers 15000 Aurillac",
    "sg:city":"Aurillac",
    "sg:classifiers":[
        {
            "category":"Building & Trades",
            "subcategory":"Construction",
            "type":"Services"
        }
    ],
    "sg:phone":"+33 4 71 64 58 56",
    "sg:postcode":"15000",
    "sg:province":"Auvergne",
    "sg:tags":[
        "work",
        "public"
    ],
    "wof:name":"Eurovia",
    "wof:placetype":"venue"
},
  "geometry": {"coordinates":[2.445125,44.927765],"type":"Point"}
}