{
  "type": "Feature",
  "properties": {
    "addr:full":"01100 Martignat Rhone-Alpes 01100",
    "addr:postcode":"01100;01100",
    "addr:street":"Rhone-Alpes",
    "iso:country":"FR",
    "sg:address":"01100 Martignat",
    "sg:classifiers":[
        {
            "category":"Personal",
            "subcategory":"Shoe Repair & Shine",
            "type":"Services"
        }
    ],
    "sg:phone":"+33 4 74 81 19 19",
    "sg:postcode":"01100",
    "sg:province":"Rhone-Alpes",
    "sg:tags":[
        "injection",
        "moulding",
        "plastic"
    ],
    "wof:name":"Erc\u00e9 Plasturgie Sa",
    "wof:placetype":"venue"
},
  "geometry": {"coordinates":[5.608977,46.208912],"type":"Point"}
}