{
  "type": "Feature",
  "properties": {
    "addr:full":"Baterses 01700 Beynost Rhone-Alpes 01700",
    "addr:postcode":"01700;01700",
    "addr:street":"Baterses",
    "iso:country":"FR",
    "sg:address":"Baterses 01700 Beynost",
    "sg:classifiers":[
        {
            "category":"Banks & Credit Unions",
            "subcategory":"Bank",
            "type":"Services"
        }
    ],
    "sg:phone":"+33 4 78 55 41 25",
    "sg:postcode":"01700",
    "sg:province":"Rhone-Alpes",
    "sg:tags":[
        "device",
        "lifting"
    ],
    "wof:name":"A.b.m. Sa",
    "wof:placetype":"venue"
},
  "geometry": {"coordinates":[4.98804,45.83168],"type":"Point"}
}