{
  "type": "Feature",
  "properties": {
    "iso:country":"FR",
    "sg:address":"B.P. 316, 73003 Chamb\u00e9ry C\u00e9dex^^506, Av. du Grand Verger, 73000 Chamb\u00e9ry",
    "sg:orig_category":"Non-Classified Establishments",
    "sg:phone":"+33 4 79 62 32 37",
    "sg:postcode":"73000",
    "sg:province":"Rhone-Alpes",
    "wof:name":"S.n.p.p. - Coudurier S.a.r.l.",
    "wof:placetype":"venue"
},
  "geometry": {"coordinates":[5.90839,45.538151],"type":"Point"}
}