{
  "type": "Feature",
  "properties": {
    "iso:country":"FR",
    "sg:address":"23 rue de la Fr\u00e9bardi\u00e8re 35000 Rennes",
    "sg:city":"Rennes",
    "sg:classifiers":[
        {
            "category":"Education",
            "subcategory":"Music School",
            "type":"Public Place"
        }
    ],
    "sg:phone":"+33 2 99 26 87 40",
    "sg:postcode":"35000",
    "sg:province":"Bretagne",
    "sg:tags":[
        "sound",
        "equipment",
        "insulating",
        "element"
    ],
    "wof:name":"Langlois Sobreti S.a.",
    "wof:placetype":"venue"
},
  "geometry": {"coordinates":[-1.628082,48.100677],"type":"Point"}
}