{
  "type": "Feature",
  "properties": {
    "iso:country":"FR",
    "sg:address":"B.P. 82, 57505 Saint Avold C\u00e9dex^^ZI du G\u00e9n\u00e9ral Altmayer, 57500 Saint Avold",
    "sg:orig_category":"Non-Classified Establishments",
    "sg:phone":"+33 3 87 91 34 55",
    "sg:province":"Lorraine",
    "wof:name":"Ponticelli Fr\u00e8res S.a.",
    "wof:placetype":"venue"
},
  "geometry": {"coordinates":[6.705505,49.104275],"type":"Point"}
}