{
  "type": "Feature",
  "properties": {
    "iso:country":"FR",
    "sg:address":"9, Rue du P\u00e2tis des Couasnes, 35136 Saint Jacques de la Lande",
    "sg:city":"Saint-Jacques-de-la-Lande",
    "sg:orig_category":"Non-Classified Establishments",
    "sg:phone":"+33 2 99 35 20 00",
    "sg:postcode":"35136",
    "sg:province":"Bretagne",
    "wof:name":"Le Roy Logistique S.a.",
    "wof:placetype":"venue"
},
  "geometry": {"coordinates":[-1.723444,48.079636],"type":"Point"}
}