{
  "type": "Feature",
  "properties": {
    "addr:full":"3 Passage Madeleine 92320 Ch\u00e2tillon Ile de France 92320",
    "addr:housenumber":"3",
    "addr:postcode":"92320;ile;92320",
    "addr:street":"Passage Madeleine;France",
    "iso:country":"FR",
    "sg:address":"3 Passage Madeleine 92320 Ch\u00e2tillon",
    "sg:classifiers":[
        {
            "category":"Utilities",
            "subcategory":"Electric",
            "type":"Services"
        }
    ],
    "sg:phone":"+33 1 40 95 07 59",
    "sg:postcode":"92320",
    "sg:province":"Ile de France",
    "sg:tags":[
        "electricity",
        "electronic",
        "electrical",
        "equipment"
    ],
    "wof:name":"Cme Sarl",
    "wof:placetype":"venue"
},
  "geometry": {"coordinates":[2.280939,48.806656],"type":"Point"}
}