{
  "type": "Feature",
  "properties": {
    "iso:country":"FR",
    "sg:address":"134, Rue Aristide Briand, 92300 Levallois Perret",
    "sg:orig_category":"Non-Classified Establishments",
    "sg:phone":"+33 1 41 40 85 85",
    "sg:province":"Ile de France",
    "wof:name":"Partners S.a.r.l.",
    "wof:placetype":"venue"
},
  "geometry": {"coordinates":[2.295141,48.895233],"type":"Point"}
}