{
  "type": "Feature",
  "properties": {
    "addr:full":"70, Grand Rue, 54530 Arnaville Lorraine",
    "addr:housenumber":"70",
    "addr:postcode":"54530",
    "addr:street":"Grand Rue",
    "iso:country":"FR",
    "sg:address":"70, Grand Rue, 54530 Arnaville",
    "sg:orig_category":"Unclassifiable Establishments",
    "sg:phone":"+33 3 83 81 71 56",
    "sg:province":"Lorraine",
    "wof:name":"Altmann Etablissements S.a.r.l.",
    "wof:placetype":"venue"
},
  "geometry": {"coordinates":[6.030501,49.011028],"type":"Point"}
}