{
  "type": "Feature",
  "properties": {
    "iso:country":"FR",
    "sg:address":"14 Rue Gu\u00e9 Des Plaqu\u00e9es 27180 Aulnay Sur Iton",
    "sg:classifiers":[
        {
            "category":"Manufacturing",
            "subcategory":"Metals",
            "type":"Manufacturing & Wholesale Goods"
        }
    ],
    "sg:phone":"+33 2 32 37 61 21",
    "sg:postcode":"27180",
    "sg:province":"Haute Normandie",
    "sg:tags":[
        "metallurgy",
        "metalworking",
        "processing"
    ],
    "wof:name":"Monfort 3m Sa",
    "wof:placetype":"venue"
},
  "geometry": {"coordinates":[1.04487,48.993031],"type":"Point"}
}