{
  "type": "Feature",
  "properties": {
    "iso:country":"FR",
    "sg:address":"178 Av Paul Vaillant Couturier 93126 La Courneuve",
    "sg:classifiers":[
        {
            "category":"Shopping",
            "type":"Retail Goods"
        }
    ],
    "sg:phone":"+33 1 49 92 67 00",
    "sg:province":"Haute Normandie",
    "sg:tags":[
        "metallurgy",
        "finished",
        "-",
        "metalworking",
        "metallic"
    ],
    "wof:name":"Saint Gobain Abrasifs",
    "wof:placetype":"venue"
},
  "geometry": {"coordinates":[2.420293,48.929417],"type":"Point"}
}