{
  "type": "Feature",
  "properties": {
    "addr:full":"B.P. 75, 55002 Bar le Duc C\u00e9dex^^18, Rue Jean Errard, 55000 Bar le Duc Lorraine",
    "addr:postcode":"55002;55000",
    "addr:street":"B.P. 75;Le Duc;Rue Jean Errard;Le Duc",
    "iso:country":"FR",
    "sg:address":"B.P. 75, 55002 Bar le Duc C\u00e9dex^^18, Rue Jean Errard, 55000 Bar le Duc",
    "sg:orig_category":"Non-Classified Establishments",
    "sg:phone":"+33 3 29 79 35 24",
    "sg:province":"Lorraine",
    "wof:name":"No.so.co.ba. S.a. - Nouvelle Soci\u00e9t\u00e9 De Confection Du Barrois",
    "wof:placetype":"venue"
},
  "geometry": {"coordinates":[5.084741,48.685223],"type":"Point"}
}