{
  "type": "Feature",
  "properties": {
    "addr:full":"Imp Kohlgaerten 67390 Marckolsheim Marckolsheim Alsace 67390",
    "addr:postcode":"67390;67390",
    "addr:street":"Imp Kohlgaerten",
    "iso:country":"FR",
    "sg:address":"Imp Kohlgaerten 67390 Marckolsheim",
    "sg:city":"Marckolsheim",
    "sg:classifiers":[
        {
            "category":"Shopping",
            "subcategory":"Computers & Home Electronics",
            "type":"Retail Goods"
        }
    ],
    "sg:phone":"+33 3 88 58 62 00",
    "sg:postcode":"67390",
    "sg:province":"Alsace",
    "sg:tags":[
        "information",
        "peripheral",
        "-",
        "technology"
    ],
    "wof:name":"Pim Industrie Sa",
    "wof:placetype":"venue"
},
  "geometry": {"coordinates":[7.537948,48.159351],"type":"Point"}
}