{
  "type": "Feature",
  "properties": {
    "addr:full":"208 Rue St L\u00e9onard 53100 Mayenne Pays de Loire 53100",
    "addr:housenumber":"208",
    "addr:postcode":"53100 mayenne;53100",
    "addr:street":"Rue St Le\u0301Onard",
    "iso:country":"FR",
    "sg:address":"208 Rue St L\u00e9onard 53100 Mayenne",
    "sg:classifiers":[
        {
            "category":"Shopping",
            "subcategory":"Clothing, Apparel, & Fashions",
            "type":"Retail Goods"
        }
    ],
    "sg:phone":"+33 2 43 04 23 98",
    "sg:postcode":"53100",
    "sg:province":"Pays de Loire",
    "sg:tags":[
        "textile",
        "clothing",
        "clothes"
    ],
    "wof:name":"Warein Sa",
    "wof:placetype":"venue"
},
  "geometry": {"coordinates":[-0.615136,48.309109],"type":"Point"}
}