{
  "type": "Feature",
  "properties": {
    "addr:full":"ZA des 5 Chemins Margencel Rhone-Alpes 74200",
    "addr:postcode":"74200",
    "addr:street":"Za Des 5 Chemins;Rhone-Alpes",
    "iso:country":"FR",
    "sg:address":"ZA des 5 Chemins",
    "sg:city":"Margencel",
    "sg:orig_category":"Unclassifiable Establishments",
    "sg:phone":"+33 4 50 72 70 40",
    "sg:postcode":"74200",
    "sg:province":"Rhone-Alpes",
    "wof:name":"Villegas S.a.r.l.",
    "wof:placetype":"venue"
},
  "geometry": {"coordinates":[6.61462,46.305523],"type":"Point"}
}