{
  "type": "Feature",
  "properties": {
    "addr:full":"40, Av du Gard, 54460 Liverdun Lorraine 54460",
    "addr:postcode":"54460;54460",
    "addr:street":"40 Av Du Gard",
    "iso:country":"FR",
    "sg:address":"40, Av du Gard, 54460 Liverdun",
    "sg:orig_category":"Non-Classified Establishments",
    "sg:phone":"+33 3 83 24 43 54",
    "sg:postcode":"54460",
    "sg:province":"Lorraine",
    "wof:name":"Chenel Distribution S.a.",
    "wof:placetype":"venue"
},
  "geometry": {"coordinates":[6.061066,48.763763],"type":"Point"}
}