{
  "type": "Feature",
  "properties": {
    "addr:full":"Pinson 33330 Saint Sulpice de Faleyrens Saint-\u00c9tienne-de-Lisse Aquitaine 33330",
    "addr:postcode":"33330;33330",
    "addr:street":"Pinson",
    "iso:country":"FR",
    "sg:address":"Pinson 33330 Saint Sulpice de Faleyrens",
    "sg:city":"Saint-\u00c9tienne-de-Lisse",
    "sg:orig_category":"Non-Classified Establishments",
    "sg:phone":"+33 5 57 84 62 11",
    "sg:postcode":"33330",
    "sg:province":"Aquitaine",
    "wof:name":"Courcelas S.a.r.l.",
    "wof:placetype":"venue"
},
  "geometry": {"coordinates":[-0.159539,44.857128],"type":"Point"}
}