{
  "type": "Feature",
  "properties": {
    "addr:full":"7 Rue De La Croix De Fer 76012 Rouen Cedex Franche Comt\u00e9",
    "addr:housenumber":"7",
    "addr:postcode":"76012",
    "addr:street":"Rue De La Croix De Fer",
    "iso:country":"FR",
    "sg:address":"7 Rue De La Croix De Fer 76012 Rouen Cedex",
    "sg:classifiers":[
        {
            "category":"Travel",
            "subcategory":"Hotels & Motels",
            "type":"Entertainment"
        }
    ],
    "sg:phone":"+33 2 35 52 69 52",
    "sg:province":"Franche Comt\u00e9",
    "sg:tags":[
        "hotels",
        "business",
        "restaurant"
    ],
    "wof:name":"Dgr Normandie Nord Et Est Hotel Mercure Rouen Centre",
    "wof:placetype":"venue"
},
  "geometry": {"coordinates":[1.09518,49.44133],"type":"Point"}
}