{
  "type": "Feature",
  "properties": {
    "iso:country":"FR",
    "sg:address":"27 Bd Bourdon",
    "sg:city":"Paris Cedex 4",
    "sg:classifiers":[
        {
            "category":"Banks & Credit Unions",
            "subcategory":"Financial Services",
            "type":"Services"
        }
    ],
    "sg:phone":"+33 1 49 96 90 00",
    "sg:postcode":"75185",
    "sg:province":"Centre",
    "sg:tags":[
        "banking",
        "finance",
        "insurance"
    ],
    "wof:name":"Fructivie Sa",
    "wof:placetype":"venue"
},
  "geometry": {"coordinates":[2.367206,48.851074],"type":"Point"}
}