{
  "type": "Feature",
  "properties": {
    "addr:full":"9, Rue de la Tuilerie, 01100 Arbent Rhone-Alpes 01100",
    "addr:housenumber":"9",
    "addr:postcode":"01100;01100",
    "addr:street":"Rue De La Tuilerie;Rhone-Alpes",
    "iso:country":"FR",
    "sg:address":"9, Rue de la Tuilerie, 01100 Arbent",
    "sg:orig_category":"Non-Classified Establishments",
    "sg:phone":"+33 4 74 77 01 51",
    "sg:postcode":"01100",
    "sg:province":"Rhone-Alpes",
    "wof:name":"Antonin Claude S.a.",
    "wof:placetype":"venue"
},
  "geometry": {"coordinates":[5.66568,46.271927],"type":"Point"}
}