{
  "type": "Feature",
  "properties": {
    "addr:full":"7, Rue de Verdun, 71170 Chauffailles Chauffailles Bourgogne 71170",
    "addr:housenumber":"7",
    "addr:postcode":"71170;71170",
    "addr:street":"Rue De Verdun",
    "iso:country":"FR",
    "sg:address":"7, Rue de Verdun, 71170 Chauffailles",
    "sg:city":"Chauffailles",
    "sg:orig_category":"Non-Classified Establishments",
    "sg:phone":"+33 3 85 26 01 74",
    "sg:postcode":"71170",
    "sg:province":"Bourgogne",
    "wof:name":"Guyot Pierre",
    "wof:placetype":"venue"
},
  "geometry": {"coordinates":[4.340584,46.201809],"type":"Point"}
}