{
  "type": "Feature",
  "properties": {
    "addr:full":"Place de la Mairie Fleigneux Champagne 08200",
    "addr:postcode":"08200",
    "addr:street":"Place De La Mairie;Champagne",
    "iso:country":"FR",
    "sg:address":"Place de la Mairie",
    "sg:city":"Fleigneux",
    "sg:orig_category":"Unclassifiable Establishments",
    "sg:phone":"+33 3 24 26 31 31",
    "sg:postcode":"08200",
    "sg:province":"Champagne",
    "wof:name":"Reinbold Transports S.a.r.l.",
    "wof:placetype":"venue"
},
  "geometry": {"coordinates":[4.927525,49.722023],"type":"Point"}
}