{
  "type": "Feature",
  "properties": {
    "addr:full":"B.P. 9, 83481 Puget sur Argens C\u00e9dex^^Bd de l'Industrie - ZI C, 83480 Puget sur Argens Provence-Alpes-C\u00f4te d'Azur",
    "addr:housenumber":"9;83480",
    "addr:postcode":"83481",
    "addr:street":"B.P.;Puget;Argens",
    "iso:country":"FR",
    "sg:address":"B.P. 9, 83481 Puget sur Argens C\u00e9dex^^Bd de l'Industrie - ZI C, 83480 Puget sur Argens",
    "sg:orig_category":"Non-Classified Establishments",
    "sg:phone":"+33 4 94 45 50 08",
    "sg:province":"Provence-Alpes-C\u00f4te d'Azur",
    "wof:name":"Forges De Saint Eloi S.a.",
    "wof:placetype":"venue"
},
  "geometry": {"coordinates":[6.698362,43.446472],"type":"Point"}
}