{
  "type": "Feature",
  "properties": {
    "addr:full":"5 Rue Marc Seguin Vend\u00f4me Centre 41100",
    "addr:housenumber":"5",
    "addr:postcode":"41100",
    "addr:street":"Rue Marc Seguin Vendo\u0302Me",
    "iso:country":"FR",
    "sg:address":"5 Rue Marc Seguin",
    "sg:city":"Vend\u00f4me",
    "sg:classifiers":[
        {
            "category":"Manufacturing",
            "subcategory":"Rubber & Plastics",
            "type":"Manufacturing & Wholesale Goods"
        }
    ],
    "sg:phone":"+33 2 54 73 54 00",
    "sg:postcode":"41100",
    "sg:province":"Centre",
    "sg:tags":[
        "packaging",
        "material",
        "-"
    ],
    "wof:name":"Imprisac Sa",
    "wof:placetype":"venue"
},
  "geometry": {"coordinates":[1.17829,47.712414],"type":"Point"}
}