{
  "type": "Feature",
  "properties": {
    "addr:full":"27, Rue Gutenberg, 42100 Saint Etienne Rhone-Alpes",
    "addr:housenumber":"27",
    "addr:postcode":"42100",
    "addr:street":"Rue Gutenberg",
    "iso:country":"FR",
    "sg:address":"27, Rue Gutenberg, 42100 Saint Etienne",
    "sg:orig_category":"Unclassifiable Establishments",
    "sg:phone":"+33 4 77 59 38 30",
    "sg:province":"Rhone-Alpes",
    "wof:name":"T.i.m.e. S.a.r.l. - Tenacit\u00e9 Initiative Motivations Efficacit\u00e9",
    "wof:placetype":"venue"
},
  "geometry": {"coordinates":[4.398583,45.415237],"type":"Point"}
}