{
  "type": "Feature",
  "properties": {
    "iso:country":"FR",
    "sg:address":"24, Chemin de l' Ou Tribail - ZI de Toctoucau, 33610 Cestas",
    "sg:city":"Cestas",
    "sg:orig_category":"Unclassifiable Establishments",
    "sg:phone":"+33 5 57 97 13 20",
    "sg:postcode":"33610",
    "sg:province":"Aquitaine",
    "wof:name":"A.m.i.s. S.a.",
    "wof:placetype":"venue"
},
  "geometry": {"coordinates":[-0.728362,44.760586],"type":"Point"}
}