{
  "type": "Feature",
  "properties": {
    "addr:full":"Zi Gave 42330 St Galmier Rhone-Alpes 42330",
    "addr:postcode":"42330;42330",
    "addr:street":"Zi Gave;Rhone-Alpes",
    "iso:country":"FR",
    "sg:address":"Zi Gave 42330 St Galmier",
    "sg:classifiers":[
        {
            "category":"Food Court",
            "type":"Food & Drink"
        }
    ],
    "sg:phone":"+33 4 77 36 22 90",
    "sg:postcode":"42330",
    "sg:province":"Rhone-Alpes",
    "sg:tags":[
        "product",
        "related"
    ],
    "wof:name":"Ravel Sa Distillerie Saint Galmier",
    "wof:placetype":"venue"
},
  "geometry": {"coordinates":[4.316973,45.59219],"type":"Point"}
}