{
  "type": "Feature",
  "properties": {
    "iso:country":"FR",
    "sg:address":"Zac Des CampveiresRoute De La Garan 84310 MORIERES LES AVIGNON",
    "sg:classifiers":[
        {
            "category":"Professional",
            "subcategory":"Printing & Photocopies",
            "type":"Services"
        }
    ],
    "sg:phone":"+33 4 90 02 09 80",
    "sg:province":"Basse Normandie",
    "sg:tags":[
        "offset"
    ],
    "wof:name":"Sept Emball Sarl",
    "wof:placetype":"venue"
},
  "geometry": {"coordinates":[4.903519,43.941059],"type":"Point"}
}