{
  "type": "Feature",
  "properties": {
    "addr:full":"21, Bd Richard Lenoir, 75011 Paris Ile de France",
    "addr:housenumber":"21",
    "addr:postcode":"75011",
    "addr:street":"Bd Richard Lenoir",
    "iso:country":"FR",
    "sg:address":"21, Bd Richard Lenoir, 75011 Paris",
    "sg:orig_category":"Unclassifiable Establishments",
    "sg:phone":"+33 1 49 29 55 10",
    "sg:province":"Ile de France",
    "wof:name":"Conseil Et Expertise S.a.",
    "wof:placetype":"venue"
},
  "geometry": {"coordinates":[2.37019,48.856506],"type":"Point"}
}