{
  "type": "Feature",
  "properties": {
    "iso:country":"FR",
    "sg:address":"24, Rue G. Guynemer - ZI, 33290 Blanquefort",
    "sg:city":"Blanquefort",
    "sg:orig_category":"Non-Classified Establishments",
    "sg:phone":"+33 5 56 95 54 00",
    "sg:postcode":"33290",
    "sg:province":"Aquitaine",
    "wof:name":"Castel Fr\u00e8res S.a.",
    "wof:placetype":"venue"
},
  "geometry": {"coordinates":[-0.634838,44.914902],"type":"Point"}
}