{
  "type": "Feature",
  "properties": {
    "addr:full":"3, Rue de la For\u00eat, 57145 Woustviller Lorraine",
    "addr:housenumber":"3",
    "addr:postcode":"57145",
    "addr:street":"Rue De La Fore\u0302T",
    "iso:country":"FR",
    "sg:address":"3, Rue de la For\u00eat, 57145 Woustviller",
    "sg:orig_category":"Unclassifiable Establishments",
    "sg:phone":"+33 3 87 98 37 00",
    "sg:province":"Lorraine",
    "wof:name":"Efco France S.n.c.",
    "wof:placetype":"venue"
},
  "geometry": {"coordinates":[7.008839,49.076687],"type":"Point"}
}