{
  "type": "Feature",
  "properties": {
    "iso:country":"FR",
    "sg:address":"1 Av 10\u00e8me Rue 06510 Carros",
    "sg:classifiers":[
        {
            "category":"Shopping",
            "subcategory":"Computers & Home Electronics",
            "type":"Retail Goods"
        }
    ],
    "sg:phone":"+33 4 93 08 86 33",
    "sg:province":"Corse",
    "sg:tags":[
        "information",
        "peripheral",
        "-",
        "technology"
    ],
    "wof:name":"Seri Industrie Sa",
    "wof:placetype":"venue"
},
  "geometry": {"coordinates":[7.208825,43.789494],"type":"Point"}
}