{
  "type": "Feature",
  "properties": {
    "addr:full":"3, Rue Bluche, 78490 Montfort l'Amaury Ile de France",
    "addr:housenumber":"3",
    "addr:postcode":"78490",
    "addr:street":"Rue Bluche",
    "iso:country":"FR",
    "sg:address":"3, Rue Bluche, 78490 Montfort l'Amaury",
    "sg:orig_category":"Unclassifiable Establishments",
    "sg:phone":"+33 1 34 86 29 55",
    "sg:province":"Ile de France",
    "wof:name":"Prest Edit S.a.s.",
    "wof:placetype":"venue"
},
  "geometry": {"coordinates":[1.809144,48.771984],"type":"Point"}
}