{
  "type": "Feature",
  "properties": {
    "addr:full":"B.P. 3116, 54013 Nancy C\u00e9dex^^4, Av. de la Garenne, 54000 Nancy Lorraine 54000",
    "addr:postcode":"54013;54000;54000",
    "addr:street":"B.P. 3116;Av. De La Garenne",
    "iso:country":"FR",
    "sg:address":"B.P. 3116, 54013 Nancy C\u00e9dex^^4, Av. de la Garenne, 54000 Nancy",
    "sg:orig_category":"Non-Classified Establishments",
    "sg:phone":"+33 3 83 41 15 31",
    "sg:postcode":"54000",
    "sg:province":"Lorraine",
    "wof:name":"D.r.c.e. - Direction R\u00e9gionale Du Commerce Ext\u00e9rieur",
    "wof:placetype":"venue"
},
  "geometry": {"coordinates":[6.183405,48.689548],"type":"Point"}
}