{
  "type": "Feature",
  "properties": {
    "addr:full":"B.P. 57, 71300 Montceau les Mines^^Parc Minier - Les Alouettes, 71300 Montceau les Mines Saint-Berain-sous-Sanvignes Bourgogne 71300",
    "addr:postcode":"71300;71300;71300",
    "addr:street":"B.P. 57;Minier;Alouettes;Bourgogne",
    "iso:country":"FR",
    "sg:address":"B.P. 57, 71300 Montceau les Mines^^Parc Minier - Les Alouettes, 71300 Montceau les Mines",
    "sg:city":"Saint-Berain-sous-Sanvignes",
    "sg:orig_category":"Non-Classified Establishments",
    "sg:phone":"+33 3 85 57 23 22",
    "sg:postcode":"71300",
    "sg:province":"Bourgogne",
    "wof:name":"Boutron G. S.a.",
    "wof:placetype":"venue"
},
  "geometry": {"coordinates":[4.36287,46.681721],"type":"Point"}
}