{
  "type": "Feature",
  "properties": {
    "addr:full":"9 avenue Chorot 38430 MOIRANS Rhone-Alpes 38430",
    "addr:housenumber":"9",
    "addr:postcode":"38430;38430",
    "addr:street":"Avenue Chorot",
    "iso:country":"FR",
    "sg:address":"9 avenue Chorot 38430 MOIRANS",
    "sg:classifiers":[
        {
            "category":"Shopping",
            "subcategory":"Shoes",
            "type":"Retail Goods"
        }
    ],
    "sg:phone":"+33 4 76 35 31 06",
    "sg:postcode":"38430",
    "sg:province":"Rhone-Alpes",
    "sg:tags":[
        "ski-boots",
        "ski"
    ],
    "wof:name":"Chaussures La Sure S.a.r.l",
    "wof:placetype":"venue"
},
  "geometry": {"coordinates":[5.570944,45.326553],"type":"Point"}
}