{
  "type": "Feature",
  "properties": {
    "addr:full":"Rue Chaptal Saint Brieuc Bretagne 22000",
    "addr:postcode":"22000",
    "addr:street":"Rue Chaptal Saint Brieuc Bretagne",
    "iso:country":"FR",
    "sg:address":"Rue Chaptal",
    "sg:city":"Saint Brieuc",
    "sg:orig_category":"Non-Classified Establishments",
    "sg:phone":"+33 2 96 68 26 34",
    "sg:postcode":"22000",
    "sg:province":"Bretagne",
    "wof:name":"Mad Ouest S.a.",
    "wof:placetype":"venue"
},
  "geometry": {"coordinates":[-2.734209,48.509056],"type":"Point"}
}