{
  "type": "Feature",
  "properties": {
    "iso:country":"FR",
    "sg:address":"7, Rue d'Isle, 02100 Saint Quentin",
    "sg:orig_category":"Non-Classified Establishments",
    "sg:phone":"+33 3 23 64 19 12",
    "sg:postcode":"02100",
    "sg:province":"Picardie",
    "wof:name":"Comit\u00e9 De Bassin D'emploi De Saint Quentin",
    "wof:placetype":"venue"
},
  "geometry": {"coordinates":[3.280453,49.839333],"type":"Point"}
}