{
  "type": "Feature",
  "properties": {
    "iso:country":"FR",
    "sg:address":"48, Chemin de l'Hermine, 88400 Xonrupt Longemer",
    "sg:orig_category":"Unclassifiable Establishments",
    "sg:phone":"+33 3 29 27 10 10",
    "sg:province":"Lorraine",
    "wof:name":"Saazor S.a.",
    "wof:placetype":"venue"
},
  "geometry": {"coordinates":[6.927601,48.081245],"type":"Point"}
}