{
  "type": "Feature",
  "properties": {
    "iso:country":"FR",
    "sg:address":"B.P. 2052, 21602 Longvic C\u00e9dex^^11, Rue de l'Ing\u00e9nieur Bertin, 21600 Longvic",
    "sg:city":"Longvic",
    "sg:orig_category":"Non-Classified Establishments",
    "sg:phone":"+33 3 80 63 08 60",
    "sg:postcode":"21600",
    "sg:province":"Bourgogne",
    "wof:name":"B.f.c. Automatismes S.a.",
    "wof:placetype":"venue"
},
  "geometry": {"coordinates":[5.032022,47.295349],"type":"Point"}
}