{
  "type": "Feature",
  "properties": {
    "iso:country":"FR",
    "sg:address":"ZI",
    "sg:city":"Tarnos",
    "sg:orig_category":"Non-Classified Establishments",
    "sg:phone":"+33 5 59 64 48 48",
    "sg:postcode":"40220",
    "sg:province":"Aquitaine",
    "wof:name":"C. Maquin\u00e9 S.a.",
    "wof:placetype":"venue"
},
  "geometry": {"coordinates":[-1.501113,43.54092],"type":"Point"}
}