{
  "type": "Feature",
  "properties": {
    "addr:full":"119 Rue Pierre Corneille 69003 Lyon Rhone-Alpes 69003",
    "addr:housenumber":"119",
    "addr:postcode":"69003;69003",
    "addr:street":"Rue Pierre Corneille",
    "iso:country":"FR",
    "sg:address":"119 Rue Pierre Corneille 69003 Lyon",
    "sg:classifiers":[
        {
            "category":"Shopping",
            "subcategory":"Pharmacy",
            "type":"Retail Goods"
        }
    ],
    "sg:phone":"+33 4 78 71 07 75",
    "sg:postcode":"69003",
    "sg:province":"Rhone-Alpes",
    "sg:tags":[
        "chemical",
        "pharmaceutical",
        "chemistry"
    ],
    "wof:name":"Cheminova Agro France Sa",
    "wof:placetype":"venue"
},
  "geometry": {"coordinates":[4.844511,45.76112],"type":"Point"}
}