{
  "type": "Feature",
  "properties": {
    "addr:full":"B.P. 108, 88130 Charmes^^Rte de Chamagne - Zone Industrielle, 88130 Charmes Lorraine",
    "addr:housenumber":"b.p. 108",
    "addr:postcode":"88130;88130",
    "addr:street":"Zone Industrielle",
    "iso:country":"FR",
    "sg:address":"B.P. 108, 88130 Charmes^^Rte de Chamagne - Zone Industrielle, 88130 Charmes",
    "sg:orig_category":"Non-Classified Establishments",
    "sg:phone":"+33 3 29 38 88 00",
    "sg:province":"Lorraine",
    "wof:name":"Oxydec S.a.",
    "wof:placetype":"venue"
},
  "geometry": {"coordinates":[6.290925,48.372807],"type":"Point"}
}