{
  "type": "Feature",
  "properties": {
    "addr:full":"B.P. 15, 04201 Sisteron C\u00e9dex^^45, Chemin de M\u00e9t\u00e9line, 04200 Sisteron Provence-Alpes-C\u00f4te d'Azur",
    "addr:postcode":"04201;04200",
    "addr:street":"B.P. 15;Chemin De Me\u0301Te\u0301Line",
    "iso:country":"FR",
    "sg:address":"B.P. 15, 04201 Sisteron C\u00e9dex^^45, Chemin de M\u00e9t\u00e9line, 04200 Sisteron",
    "sg:orig_category":"Non-Classified Establishments",
    "sg:phone":"+33 4 92 33 12 00",
    "sg:province":"Provence-Alpes-C\u00f4te d'Azur",
    "wof:name":"Sanofi Chimie S.a.",
    "wof:placetype":"venue"
},
  "geometry": {"coordinates":[5.920801,44.19574],"type":"Point"}
}