{
  "type": "Feature",
  "properties": {
    "iso:country":"FR",
    "sg:address":"B.P. 2437, 03204 Vichy C\u00e9dex^^40, Rue de la Tour, 03200 Abrest",
    "sg:city":"Vichy",
    "sg:orig_category":"Non-Classified Establishments",
    "sg:phone":"+33 4 70 58 71 04",
    "sg:postcode":"03200",
    "sg:province":"Auvergne",
    "wof:name":"Val S.a.",
    "wof:placetype":"venue"
},
  "geometry": {"coordinates":[3.433,46.122379],"type":"Point"}
}