{
  "type": "Feature",
  "properties": {
    "addr:full":"B.P. 222, 13308 Marseille C\u00e9dex 14^^Rue Payan d'Augery, 13014 Marseille Poitou-Charentes",
    "addr:housenumber":"b.p. 222",
    "addr:postcode":"13308;13014",
    "addr:street":"D'Augery",
    "iso:country":"FR",
    "sg:address":"B.P. 222, 13308 Marseille C\u00e9dex 14^^Rue Payan d'Augery, 13014 Marseille",
    "sg:orig_category":"Non-Classified Establishments",
    "sg:phone":"+33 4 91 10 31 70",
    "sg:province":"Poitou-Charentes",
    "wof:name":"Frigorifiques De L'union S.a.",
    "wof:placetype":"venue"
},
  "geometry": {"coordinates":[5.373223,43.329144],"type":"Point"}
}