{
  "type": "Feature",
  "properties": {
    "addr:full":"10 Av Durance Parc Act De Buchelay 3000 78200 Buchelay Ile de France 78200",
    "addr:housenumber":"3000",
    "addr:postcode":"78200;78200",
    "addr:street":"10 Av Durance Parc;Buchelay;Ile De France",
    "iso:country":"FR",
    "sg:address":"10 Av Durance Parc Act De Buchelay 3000 78200 Buchelay",
    "sg:classifiers":[
        {
            "category":"Professional",
            "subcategory":"Engineering",
            "type":"Services"
        }
    ],
    "sg:phone":"+33 1 30 94 02 91",
    "sg:postcode":"78200",
    "sg:province":"Ile de France",
    "sg:tags":[
        "metallurgy",
        "good",
        "-",
        "metal",
        "mac",
        "metallic",
        "machine",
        "metalworking",
        "finished",
        "mechanical"
    ],
    "wof:name":"Societe D'etude Et De Construction Industrielle Metall",
    "wof:placetype":"venue"
},
  "geometry": {"coordinates":[1.674073,48.993275],"type":"Point"}
}