{
  "type": "Feature",
  "properties": {
    "iso:country":"FR",
    "sg:address":"Za Des Tattes 74580 Viry",
    "sg:classifiers":[
        {
            "category":"Professional",
            "subcategory":"Engineering",
            "type":"Services"
        }
    ],
    "sg:phone":"+33 4 50 04 74 02",
    "sg:postcode":"74580",
    "sg:province":"Rhone-Alpes",
    "sg:tags":[
        "machine",
        "-",
        "environment",
        "equipment",
        "machinery",
        "mechanical"
    ],
    "wof:name":"Societe Electro Mecanique Du Genevois Sarl (semg)",
    "wof:placetype":"venue"
},
  "geometry": {"coordinates":[6.037754,46.117142],"type":"Point"}
}