{
  "type": "Feature",
  "properties": {
    "iso:country":"FR",
    "sg:address":"44 Rue De Turenne 75003 Paris",
    "sg:classifiers":[
        {
            "category":"Shopping",
            "subcategory":"Clothing, Apparel, & Fashions",
            "type":"Retail Goods"
        }
    ],
    "sg:phone":"+33 1 48 87 71 17",
    "sg:postcode":"75003",
    "sg:province":"Ile de France",
    "sg:tags":[
        "textile",
        "clothing",
        "clothes"
    ],
    "wof:name":"Alessandro",
    "wof:placetype":"venue"
},
  "geometry": {"coordinates":[2.364685,48.857891],"type":"Point"}
}