{
  "type": "Feature",
  "properties": {
    "addr:full":"6, Rue Salneuve, 75017 Paris Ile de France",
    "addr:housenumber":"6",
    "addr:postcode":"75017",
    "addr:street":"Rue Salneuve",
    "iso:country":"FR",
    "sg:address":"6, Rue Salneuve, 75017 Paris",
    "sg:orig_category":"Unclassifiable Establishments",
    "sg:phone":"+33 1 43 18 22 88",
    "sg:province":"Ile de France",
    "wof:name":"Chronomicro S.a.",
    "wof:placetype":"venue"
},
  "geometry": {"coordinates":[2.314784,48.884888],"type":"Point"}
}