{
  "type": "Feature",
  "properties": {
    "addr:full":"B.P. 37, 57232 Bitche C\u00e9dex^^6, Rue Trumelet-Faber, 57230 Bitche Lorraine",
    "addr:postcode":"57232;57230",
    "addr:street":"B.P. 37;Rue Trumelet-Faber",
    "iso:country":"FR",
    "sg:address":"B.P. 37, 57232 Bitche C\u00e9dex^^6, Rue Trumelet-Faber, 57230 Bitche",
    "sg:orig_category":"Non-Classified Establishments",
    "sg:phone":"+33 3 87 96 24 22",
    "sg:province":"Lorraine",
    "wof:name":"Soci\u00e9t\u00e9 Bo Ma Trans S.a.",
    "wof:placetype":"venue"
},
  "geometry": {"coordinates":[7.427533,49.050041],"type":"Point"}
}