{
  "type": "Feature",
  "properties": {
    "iso:country":"FR",
    "sg:address":"Zi De La Norge 21800 Chevigny St Sauveur",
    "sg:city":"Neuilly-l\u00e8s-Dijon",
    "sg:classifiers":[
        {
            "category":"Banks & Credit Unions",
            "subcategory":"Investment Brokerage",
            "type":"Services"
        }
    ],
    "sg:phone":"+33 3 80 46 13 32",
    "sg:postcode":"21800",
    "sg:province":"Bourgogne",
    "sg:tags":[
        "-",
        "transport",
        "related"
    ],
    "wof:name":"Magasin Generaux De Champagne Ardene",
    "wof:placetype":"venue"
},
  "geometry": {"coordinates":[5.135262,47.301807],"type":"Point"}
}