{
  "type": "Feature",
  "properties": {
    "addr:full":"32 Quai De La Douane 29200 Brest Brest Bretagne 29200",
    "addr:housenumber":"32",
    "addr:postcode":"29200;29200",
    "addr:street":"Quai De La Douane",
    "iso:country":"FR",
    "sg:address":"32 Quai De La Douane 29200 Brest",
    "sg:city":"Brest",
    "sg:classifiers":[
        {
            "category":"Marine",
            "type":"Transportation"
        }
    ],
    "sg:phone":"+33 2 98 44 36 47",
    "sg:postcode":"29200",
    "sg:province":"Bretagne",
    "sg:tags":[
        "transport",
        "sea"
    ],
    "wof:name":"Fourniership Sas",
    "wof:placetype":"venue"
},
  "geometry": {"coordinates":[-4.484496,48.382969],"type":"Point"}
}