{
  "type": "Feature",
  "properties": {
    "iso:country":"FR",
    "sg:address":"270 Rue Vendome 69003 Lyon",
    "sg:classifiers":[
        {
            "category":"Wholesale",
            "subcategory":"Medical Equipment & Supplies",
            "type":"Manufacturing & Wholesale Goods"
        }
    ],
    "sg:phone":"+33 4 72 84 77 30",
    "sg:postcode":"69003",
    "sg:province":"Rhone-Alpes",
    "sg:tags":[
        "instrument",
        "health",
        "-",
        "precision"
    ],
    "wof:name":"R Lecante Sa",
    "wof:placetype":"venue"
},
  "geometry": {"coordinates":[4.8472,45.756325],"type":"Point"}
}