{
  "type": "Feature",
  "properties": {
    "addr:full":"12 Route De Murviel Ld Pech Du Cayrou Ch N 12 34500 Beziers Languedoc-Roussillon 34500",
    "addr:housenumber":"12;12",
    "addr:postcode":"34500;34500",
    "addr:street":"Route De Murviel Ld Pech Du Cayrou Ch N",
    "iso:country":"FR",
    "sg:address":"12 Route De Murviel Ld Pech Du Cayrou Ch N 12 34500 Beziers",
    "sg:classifiers":[
        {
            "category":"Professional",
            "subcategory":"Engineering",
            "type":"Services"
        }
    ],
    "sg:phone":"+33 4 67 49 88 30",
    "sg:postcode":"34500",
    "sg:province":"Languedoc-Roussillon",
    "sg:tags":[
        "machine",
        "-",
        "mechanical"
    ],
    "wof:name":"Mas La Chevaliere",
    "wof:placetype":"venue"
},
  "geometry": {"coordinates":[3.202727,43.36105],"type":"Point"}
}