{
  "type": "Feature",
  "properties": {
    "addr:full":"Rue du Pont de Notre Dame Vic Fezensac Midi Pyr\u00e9n\u00e9es 32190",
    "addr:postcode":"32190",
    "addr:street":"Rue Du Pont De Notre",
    "iso:country":"FR",
    "sg:address":"Rue du Pont de Notre Dame",
    "sg:city":"Vic Fezensac",
    "sg:orig_category":"Unclassifiable Establishments",
    "sg:phone":"+33 5 62 06 30 54",
    "sg:postcode":"32190",
    "sg:province":"Midi Pyr\u00e9n\u00e9es",
    "wof:name":"De Fezensac S.a.",
    "wof:placetype":"venue"
},
  "geometry": {"coordinates":[0.308295,43.75993],"type":"Point"}
}