{
  "type": "Feature",
  "properties": {
    "iso:country":"FR",
    "sg:address":"Lascierie 41150 Chouzy sur Cisse",
    "sg:city":"Chouzy-sur-Cisse",
    "sg:orig_category":"Non-Classified Establishments",
    "sg:phone":"+33 2 54 20 44 10",
    "sg:postcode":"41150",
    "sg:province":"Centre",
    "wof:name":"Lig\u00e9rienne Granulats S.a.",
    "wof:placetype":"venue"
},
  "geometry": {"coordinates":[1.132808,47.455837],"type":"Point"}
}