{
  "type": "Feature",
  "properties": {
    "iso:country":"FR",
    "sg:address":"68 rue Edouard Vaillant; Bezons; 95870",
    "sg:classifiers":[
        {
            "category":"Banks & Credit Unions",
            "subcategory":"Bank",
            "type":"Services"
        }
    ],
    "sg:phone":"+33 3339827888",
    "sg:postcode":"95870",
    "sg:province":"Ile de France",
    "wof:name":"Soci\u00e9t\u00e9 G\u00e9n\u00e9rale",
    "wof:placetype":"venue"
},
  "geometry": {"coordinates":[2.214254,48.92683],"type":"Point"}
}