{
  "type": "Feature",
  "properties": {
    "addr:full":"B.P. 69, 91570 Bi\u00e8vres^^26, Rte de la Plaine Eisy - Parc Burospace, 91570 Bi\u00e8vres Ile de France 91570",
    "addr:postcode":"91570;91570;ile;91570",
    "addr:street":"B.P. 69;Rte De La Plaine Eisy Parc Burospace;France",
    "iso:country":"FR",
    "sg:address":"B.P. 69, 91570 Bi\u00e8vres^^26, Rte de la Plaine Eisy - Parc Burospace, 91570 Bi\u00e8vres",
    "sg:orig_category":"Non-Classified Establishments",
    "sg:phone":"+33 1 69 33 88 00",
    "sg:postcode":"91570",
    "sg:province":"Ile de France",
    "wof:name":"Brossard France S.a.",
    "wof:placetype":"venue"
},
  "geometry": {"coordinates":[2.215318,48.753994],"type":"Point"}
}