{
  "type": "Feature",
  "properties": {
    "iso:country":"FR",
    "sg:address":"B.P. 28, 21601 Longvic C\u00e9dex^^12, Rue Romelet, 21600 Longvic",
    "sg:city":"Longvic",
    "sg:orig_category":"Non-Classified Establishments",
    "sg:phone":"+33 3 80 66 87 93",
    "sg:postcode":"21600",
    "sg:province":"Bourgogne",
    "wof:name":"Michaud Chailly - Agence Sonotec S.a.",
    "wof:placetype":"venue"
},
  "geometry": {"coordinates":[5.06327,47.286015],"type":"Point"}
}