{
  "type": "Feature",
  "properties": {
    "addr:full":"Zac Du Clos Des Ante 76410 Tourville La Riviere Haute Normandie",
    "addr:postcode":"76410",
    "addr:street":"Zac Du Clos Des Ante",
    "iso:country":"FR",
    "sg:address":"Zac Du Clos Des Ante 76410 Tourville La Riviere",
    "sg:classifiers":[
        {
            "category":"Manufacturing",
            "subcategory":"Rubber & Plastics",
            "type":"Manufacturing & Wholesale Goods"
        }
    ],
    "sg:phone":"+33 2 35 81 88 88",
    "sg:province":"Haute Normandie",
    "wof:name":"Metifiot Sa",
    "wof:placetype":"venue"
},
  "geometry": {"coordinates":[1.104654,49.328636],"type":"Point"}
}