{
  "type": "Feature",
  "properties": {
    "iso:country":"FR",
    "sg:address":"48, Rue Victor Duret, 92420 Vaucresson",
    "sg:orig_category":"Unclassifiable Establishments",
    "sg:phone":"+33 1 47 41 55 17",
    "sg:province":"Ile de France",
    "wof:name":"Compagnie G\u00e9n\u00e9rale D'hygi\u00e8ne S.a.r.l.",
    "wof:placetype":"venue"
},
  "geometry": {"coordinates":[2.16912,48.846443],"type":"Point"}
}