{
  "type": "Feature",
  "properties": {
    "addr:full":"85 Rue De Maubeuge 75010 Paris Ile de France",
    "addr:housenumber":"85",
    "addr:postcode":"75010",
    "addr:street":"Rue De Maubeuge",
    "iso:country":"FR",
    "sg:address":"85 Rue De Maubeuge 75010 Paris",
    "sg:classifiers":[
        {
            "category":"Professional",
            "subcategory":"Printing & Photocopies",
            "type":"Services"
        }
    ],
    "sg:phone":"+33 1 53 24 53 00",
    "sg:province":"Ile de France",
    "sg:tags":[
        "publishing"
    ],
    "wof:name":"Fun Book France",
    "wof:placetype":"venue"
},
  "geometry": {"coordinates":[2.352687,48.880882],"type":"Point"}
}