{
  "type": "Feature",
  "properties": {
    "iso:country":"FR",
    "sg:address":"62, Rue Villeneuve, 92110 Clichy",
    "sg:orig_category":"Unclassifiable Establishments",
    "sg:phone":"+33 1 47 37 52 08",
    "sg:province":"Ile de France",
    "wof:name":"L.b. S.a.r.l. - La Brenne",
    "wof:placetype":"venue"
},
  "geometry": {"coordinates":[2.313766,48.906178],"type":"Point"}
}