{
  "type": "Feature",
  "properties": {
    "iso:country":"FR",
    "sg:address":"Rue Jacques Louis Th\u00e9nard",
    "sg:city":"Champforgeuil",
    "sg:orig_category":"Unclassifiable Establishments",
    "sg:phone":"+33 3 85 46 99 99",
    "sg:postcode":"71530",
    "sg:province":"Bourgogne",
    "wof:name":"Rigard S.a.a.",
    "wof:placetype":"venue"
},
  "geometry": {"coordinates":[4.88201,46.816959],"type":"Point"}
}