{
  "type": "Feature",
  "properties": {
    "iso:country":"FR",
    "sg:address":"Zi Armanville 50700 Valognes",
    "sg:city":"Valognes",
    "sg:classifiers":[
        {
            "category":"Food Court",
            "type":"Food & Drink"
        }
    ],
    "sg:phone":"+33 2 33 21 68 88",
    "sg:postcode":"50700",
    "sg:province":"Basse Normandie",
    "sg:tags":[
        "product",
        "related"
    ],
    "wof:name":"Elidis Valognes",
    "wof:placetype":"venue"
},
  "geometry": {"coordinates":[-1.468479,49.508766],"type":"Point"}
}