{
  "type": "Feature",
  "properties": {
    "addr:full":"79, Rue Marcel Dassault, 92773 Boulogne Billancourt C\u00e9dex Ancourt Haute Normandie 76370",
    "addr:housenumber":"79",
    "addr:postcode":"92773;76370",
    "addr:street":"Rue Marcel Dassault;Haute Normandie",
    "iso:country":"FR",
    "sg:address":"79, Rue Marcel Dassault, 92773 Boulogne Billancourt C\u00e9dex",
    "sg:city":"Ancourt",
    "sg:orig_category":"Unclassifiable Establishments",
    "sg:phone":"+33 1 46 94 10 00",
    "sg:postcode":"76370",
    "sg:province":"Haute Normandie",
    "wof:name":"Shise\u00efdo France S.a.",
    "wof:placetype":"venue"
},
  "geometry": {"coordinates":[2.249706,48.834118],"type":"Point"}
}