{
  "type": "Feature",
  "properties": {
    "addr:full":"7, Rue Pierre et Marie Curie, 33290 Blanquefort Blanquefort Aquitaine 33290",
    "addr:housenumber":"7",
    "addr:postcode":"33290;33290",
    "addr:street":"Rue Pierre Et Marie Curie",
    "iso:country":"FR",
    "sg:address":"7, Rue Pierre et Marie Curie, 33290 Blanquefort",
    "sg:city":"Blanquefort",
    "sg:orig_category":"Unclassifiable Establishments",
    "sg:phone":"+33 5 56 35 23 98",
    "sg:postcode":"33290",
    "sg:province":"Aquitaine",
    "wof:name":"Inter Equipement S.a.",
    "wof:placetype":"venue"
},
  "geometry": {"coordinates":[-0.610376,44.924316],"type":"Point"}
}