{
  "type": "Feature",
  "properties": {
    "iso:country":"FR",
    "sg:address":"8, Rue des Galus, 33700 M\u00e9rignac",
    "sg:city":"M\u00e9rignac",
    "sg:orig_category":"Unclassifiable Establishments",
    "sg:phone":"+33 5 56 34 80 24",
    "sg:postcode":"33700",
    "sg:province":"Aquitaine",
    "wof:name":"C.p.v.d. S.a.r.l. - Comptoir Des Produits Vanilles Et D\u00e9riv\u00e9s",
    "wof:placetype":"venue"
},
  "geometry": {"coordinates":[-0.678343,44.845379],"type":"Point"}
}