{
  "type": "Feature",
  "properties": {
    "iso:country":"FR",
    "sg:address":"15, Rue des Saints P\u00e8res, 75006 Paris",
    "sg:orig_category":"Non-Classified Establishments",
    "sg:phone":"+33 1 44 77 97 77",
    "sg:province":"Ile de France",
    "wof:name":"Rial Trading S.a.",
    "wof:placetype":"venue"
},
  "geometry": {"coordinates":[2.332474,48.857124],"type":"Point"}
}