{
  "type": "Feature",
  "properties": {
    "addr:full":"Min de Brienne Bordeaux C\u00e9dex Aquitaine 33076",
    "addr:postcode":"33076",
    "addr:street":"Min De Brienne",
    "iso:country":"FR",
    "sg:address":"Min de Brienne",
    "sg:city":"Bordeaux C\u00e9dex",
    "sg:orig_category":"Non-Classified Establishments",
    "sg:phone":"+33 5 56 49 36 50",
    "sg:postcode":"33076",
    "sg:province":"Aquitaine",
    "wof:name":"Eliane Laplace S.a.",
    "wof:placetype":"venue"
},
  "geometry": {"coordinates":[-0.54581,44.8027],"type":"Point"}
}