{
  "type": "Feature",
  "properties": {
    "addr:full":"195 Rue Ernestine De Tremaudan 29200 Brest Brest Bretagne 29200",
    "addr:housenumber":"195",
    "addr:postcode":"29200;29200",
    "addr:street":"Rue Ernestine De Tremaudan",
    "iso:country":"FR",
    "sg:address":"195 Rue Ernestine De Tremaudan 29200 Brest",
    "sg:city":"Brest",
    "sg:classifiers":[
        {
            "category":"Utilities",
            "type":"Services"
        }
    ],
    "sg:phone":"+33 2 98 00 70 00",
    "sg:postcode":"29200",
    "sg:province":"Bretagne",
    "sg:tags":[
        "raw",
        "energy",
        "material"
    ],
    "wof:name":"Electricite De France (edf)",
    "wof:placetype":"venue"
},
  "geometry": {"coordinates":[-4.476449,48.427238],"type":"Point"}
}