{
  "type": "Feature",
  "properties": {
    "iso:country":"FR",
    "sg:address":"30, Bd du Doyenn\u00e9, 49000 Angers",
    "sg:orig_category":"Non-Classified Establishments",
    "sg:phone":"+33 2 41 43 31 00",
    "sg:province":"Pays de Loire",
    "wof:name":"Mainexpress S.a.r.l.",
    "wof:placetype":"venue"
},
  "geometry": {"coordinates":[-0.533512,47.490101],"type":"Point"}
}