{
  "type": "Feature",
  "properties": {
    "addr:full":"20 R Notre-Dame De Recouvrance 75002 Paris Ile de France 75002",
    "addr:housenumber":"20",
    "addr:postcode":"75002;75002",
    "addr:street":"R Notre-Dame De Recouvrance",
    "iso:country":"FR",
    "sg:address":"20 R Notre-Dame De Recouvrance 75002 Paris",
    "sg:classifiers":[
        {
            "category":"Shopping",
            "subcategory":"Clothing, Apparel, & Fashions",
            "type":"Retail Goods"
        }
    ],
    "sg:phone":"+33 1 42 33 80 92",
    "sg:postcode":"75002",
    "sg:province":"Ile de France",
    "sg:tags":[
        "textile",
        "clothing",
        "clothes"
    ],
    "wof:name":"Solva Sa",
    "wof:placetype":"venue"
},
  "geometry": {"coordinates":[2.348423,48.870453],"type":"Point"}
}