{
  "type": "Feature",
  "properties": {
    "addr:full":"La Vitarelle 47400 Fauguerolles Fauguerolles Aquitaine 47400",
    "addr:postcode":"47400;47400",
    "addr:street":"Vitarelle",
    "iso:country":"FR",
    "sg:address":"La Vitarelle 47400 Fauguerolles",
    "sg:city":"Fauguerolles",
    "sg:orig_category":"Unclassifiable Establishments",
    "sg:phone":"+33 5 53 83 32 24",
    "sg:postcode":"47400",
    "sg:province":"Aquitaine",
    "wof:name":"I.f.i.i.m. S.a.",
    "wof:placetype":"venue"
},
  "geometry": {"coordinates":[0.319993,44.345749],"type":"Point"}
}