{
  "type": "Feature",
  "properties": {
    "iso:country":"FR",
    "sg:address":"17210 Bussac For\u00eat",
    "sg:orig_category":"Non-Classified Establishments",
    "sg:phone":"+33 5 46 04 34 40",
    "sg:postcode":"17210",
    "sg:province":"Poitou-Charentes",
    "wof:name":"Ciments Calcia S.a.",
    "wof:placetype":"venue"
},
  "geometry": {"coordinates":[-0.369394,45.212204],"type":"Point"}
}