{
  "type": "Feature",
  "properties": {
    "iso:country":"FR",
    "sg:address":"ZA le Saluant",
    "sg:city":"Reventin Vaugris",
    "sg:orig_category":"Unclassifiable Establishments",
    "sg:phone":"+33 4 74 58 96 96",
    "sg:postcode":"38121",
    "sg:province":"Rhone-Alpes",
    "wof:name":"Transports P.o. Scandex S.a.",
    "wof:placetype":"venue"
},
  "geometry": {"coordinates":[4.840308,45.466057],"type":"Point"}
}