{
  "type": "Feature",
  "properties": {
    "iso:country":"FR",
    "sg:address":"B.P. 16634",
    "sg:city":"Montgermont",
    "sg:orig_category":"Non-Classified Establishments",
    "sg:phone":"+33 2 99 68 99 11",
    "sg:postcode":"35760",
    "sg:province":"Bretagne",
    "wof:name":"T.p.r. - Trauvaux Publics Rohou",
    "wof:placetype":"venue"
},
  "geometry": {"coordinates":[-1.656712,48.148029],"type":"Point"}
}