{
  "type": "Feature",
  "properties": {
    "addr:full":"38 Rue De Li\u00e8ge 75008 Paris Ile de France",
    "addr:housenumber":"38",
    "addr:postcode":"75008",
    "addr:street":"Rue De Lie\u0300Ge",
    "iso:country":"FR",
    "sg:address":"38 Rue De Li\u00e8ge 75008 Paris",
    "sg:classifiers":[
        {
            "category":"Utilities",
            "subcategory":"Telephone",
            "type":"Services"
        }
    ],
    "sg:phone":"+33 1 44 69 44 69",
    "sg:province":"Ile de France",
    "sg:tags":[
        "telecommunication"
    ],
    "wof:name":"Parson France",
    "wof:placetype":"venue"
},
  "geometry": {"coordinates":[2.324298,48.879307],"type":"Point"}
}