{
  "type": "Feature",
  "properties": {
    "iso:country":"FR",
    "sg:address":"56, Rue Oberkampf, 91100 Corbeil Essonnes",
    "sg:orig_category":"Non-Classified Establishments",
    "sg:phone":"+33 1 60 88 01 92",
    "sg:province":"Ile de France",
    "wof:name":"Synergie",
    "wof:placetype":"venue"
},
  "geometry": {"coordinates":[2.476159,48.607841],"type":"Point"}
}