{
  "type": "Feature",
  "properties": {
    "addr:full":"Route Nationale 7 La Traille 84130 Le Pontet Le Pontet Rhone-Alpes 73110",
    "addr:postcode":"84130;73110",
    "addr:street":"Route Nationale 7 La Traille;Rhone-Alpes",
    "iso:country":"FR",
    "sg:address":"Route Nationale 7 La Traille 84130 Le Pontet",
    "sg:city":"Le Pontet",
    "sg:classifiers":[
        {
            "category":"Manufacturing",
            "subcategory":"Paper Products",
            "type":"Manufacturing & Wholesale Goods"
        }
    ],
    "sg:phone":"+33 4 90 03 98 04",
    "sg:postcode":"73110",
    "sg:province":"Rhone-Alpes",
    "sg:tags":[
        "raw",
        "material",
        "-",
        "cardboard"
    ],
    "wof:name":"Alfa D'avignon (alfa)",
    "wof:placetype":"venue"
},
  "geometry": {"coordinates":[4.859935,43.96188],"type":"Point"}
}