{
  "type": "Feature",
  "properties": {
    "iso:country":"FR",
    "sg:address":"71290 Rancy",
    "sg:city":"Rancy",
    "sg:orig_category":"Non-Classified Establishments",
    "sg:phone":"+33 3 85 74 22 35",
    "sg:postcode":"71290",
    "sg:province":"Bourgogne",
    "wof:name":"Badaut - Duquet S.a.r.l.",
    "wof:placetype":"venue"
},
  "geometry": {"coordinates":[5.091985,46.598339],"type":"Point"}
}