{
  "type": "Feature",
  "properties": {
    "iso:country":"FR",
    "sg:address":"17, Bd des Fr\u00e8res Voisin, 75015 Paris",
    "sg:orig_category":"Unclassifiable Establishments",
    "sg:phone":"+33 1 45 54 53 33",
    "sg:province":"Ile de France",
    "wof:name":"Megan S.a.r.l.",
    "wof:placetype":"venue"
},
  "geometry": {"coordinates":[2.272219,48.827988],"type":"Point"}
}