{
  "type": "Feature",
  "properties": {
    "iso:country":"FR",
    "sg:address":"18, Rue des Trois Moulins, 85120 La Chataigneraie",
    "sg:orig_category":"Non-Classified Establishments",
    "sg:phone":"+33 2 51 69 61 98",
    "sg:province":"Pays de Loire",
    "wof:name":"M.t.m. S.a. - Mat\u00e9riaux Des Trois Moulins",
    "wof:placetype":"venue"
},
  "geometry": {"coordinates":[-0.728652,46.646015],"type":"Point"}
}