{
  "type": "Feature",
  "properties": {
    "iso:country":"FR",
    "sg:address":"Le Haut Fourneau Zone Industrielle 88700 Rambervillers",
    "sg:classifiers":[
        {
            "category":"Manufacturing",
            "subcategory":"Paper Products",
            "type":"Manufacturing & Wholesale Goods"
        }
    ],
    "sg:phone":"+33 3 29 65 03 61",
    "sg:province":"Lorraine",
    "sg:tags":[
        "raw",
        "material",
        "-",
        "cardboard"
    ],
    "wof:name":"Vosges Embal",
    "wof:placetype":"venue"
},
  "geometry": {"coordinates":[6.63509,48.345825],"type":"Point"}
}