{
  "type": "Feature",
  "properties": {
    "addr:full":"15 All Ste Lucie Les Trois Moulins 92130 Issy Les Moulineaux Ile de France 92130",
    "addr:housenumber":"15",
    "addr:postcode":"92130;92130",
    "addr:street":"All Ste Lucie Les",
    "iso:country":"FR",
    "sg:address":"15 All Ste Lucie",
    "sg:city":"Les Trois Moulins 92130 Issy Les Moulineaux",
    "sg:classifiers":[
        {
            "category":"Manufacturing",
            "subcategory":"Chemicals & Compounds",
            "type":"Manufacturing & Wholesale Goods"
        }
    ],
    "sg:phone":"+33 1 46 48 91 08",
    "sg:postcode":"92130",
    "sg:province":"Ile de France",
    "sg:tags":[
        "pharmaceutical",
        "-",
        "cosmetic",
        "pharmacy",
        "chemistry",
        "by-product"
    ],
    "wof:name":"Miriannaud",
    "wof:placetype":"venue"
},
  "geometry": {"coordinates":[2.285689,48.844532],"type":"Point"}
}