{
  "type": "Feature",
  "properties": {
    "iso:country":"FR",
    "sg:address":"10 Route Bourges 18110 Allogny",
    "sg:city":"Allogny",
    "sg:classifiers":[
        {
            "category":"Manufacturing",
            "subcategory":"Tools & Machinery",
            "type":"Manufacturing & Wholesale Goods"
        }
    ],
    "sg:phone":"+33 2 48 64 01 78",
    "sg:postcode":"18110",
    "sg:province":"Centre",
    "sg:tags":[
        "metallurgy",
        "metalworking"
    ],
    "wof:name":"Elektrobox Sa",
    "wof:placetype":"venue"
},
  "geometry": {"coordinates":[2.321627,47.221661],"type":"Point"}
}