{
  "type": "Feature",
  "properties": {
    "iso:country":"FR",
    "sg:address":"192 Bd De Brou 01000 Bourg En Bresse",
    "sg:classifiers":[
        {
            "category":"Autos & Motor Vehicles",
            "subcategory":"Automobile Sales",
            "type":"Retail Goods"
        }
    ],
    "sg:phone":"+33 4 74 45 93 00",
    "sg:postcode":"01000",
    "sg:province":"Rhone-Alpes",
    "sg:tags":[
        "equipment",
        "industrial",
        "transport"
    ],
    "wof:name":"Ste Industrielle Et Commerciale Du Materiel",
    "wof:placetype":"venue"
},
  "geometry": {"coordinates":[5.237579,46.195133],"type":"Point"}
}