{
  "type": "Feature",
  "properties": {
    "iso:country":"FR",
    "sg:address":"Chemin Des Moulins 84120 Pertuis",
    "sg:classifiers":[
        {
            "category":"Food & Beverages",
            "subcategory":"Groceries & Convenience Stores",
            "type":"Retail Goods"
        }
    ],
    "sg:phone":"+33 4 90 09 59 00",
    "sg:province":"Franche Comt\u00e9",
    "sg:tags":[
        "product",
        "grain",
        "cereal",
        "related"
    ],
    "wof:name":"Moulins Soufflet Sa",
    "wof:placetype":"venue"
},
  "geometry": {"coordinates":[5.497024,43.688728],"type":"Point"}
}