{
  "type": "Feature",
  "properties": {
    "addr:full":"2 Place Saint Martin 02300 Chauny Picardie 02300",
    "addr:housenumber":"2",
    "addr:postcode":"02300;02300",
    "addr:street":"Place Saint Martin",
    "iso:country":"FR",
    "sg:address":"2 Place Saint Martin 02300 Chauny",
    "sg:orig_category":"Miscellaneous Products",
    "sg:phone":"+33 3 23 52 01 77",
    "sg:postcode":"02300",
    "sg:province":"Picardie",
    "wof:name":"Sarl Bernasconi",
    "wof:placetype":"venue"
},
  "geometry": {"coordinates":[3.217999,49.615223],"type":"Point"}
}