{
  "type": "Feature",
  "properties": {
    "addr:full":"Zi Croix Sud 11100 Narbonne Languedoc-Roussillon 11100",
    "addr:postcode":"11100;11100",
    "addr:street":"Zi Croix Sud",
    "iso:country":"FR",
    "sg:address":"Zi Croix Sud 11100 Narbonne",
    "sg:classifiers":[
        {
            "category":"Shopping Center",
            "type":"Public Place"
        }
    ],
    "sg:phone":"+33 4 68 41 22 57",
    "sg:postcode":"11100",
    "sg:province":"Languedoc-Roussillon",
    "sg:tags":[
        "product",
        "meat",
        "cooked",
        "frozen",
        "related",
        "food"
    ],
    "wof:name":"Argel Sud",
    "wof:placetype":"venue"
},
  "geometry": {"coordinates":[3.004325,43.188354],"type":"Point"}
}