{
  "type": "Feature",
  "properties": {
    "addr:full":"Parc Agropolis Montferrier sur Lez Languedoc-Roussillon 34980",
    "addr:postcode":"34980",
    "addr:street":"Montferrier;Lez",
    "iso:country":"FR",
    "sg:address":"Parc Agropolis",
    "sg:city":"Montferrier sur Lez",
    "sg:orig_category":"Unclassifiable Establishments",
    "sg:phone":"+33 4 67 10 38 99",
    "sg:postcode":"34980",
    "sg:province":"Languedoc-Roussillon",
    "wof:name":"Bepac S.a.r.l.",
    "wof:placetype":"venue"
},
  "geometry": {"coordinates":[3.866011,43.651386],"type":"Point"}
}