{
  "type": "Feature",
  "properties": {
    "iso:country":"FR",
    "sg:address":"22, Rte des Creuses, 74960 Cran Gevrier",
    "sg:orig_category":"Non-Classified Establishments",
    "sg:phone":"+33 4 50 52 15 85",
    "sg:province":"Rhone-Alpes",
    "wof:name":"Philippe Vallanzasca Miroiterie Ann\u00e9cienne S.a.",
    "wof:placetype":"venue"
},
  "geometry": {"coordinates":[6.105701,45.894142],"type":"Point"}
}