{
  "type": "Feature",
  "properties": {
    "addr:full":"Rte du Service EDF PK 300 Strasbourg Alsace 67000",
    "addr:postcode":"67000",
    "addr:street":"Rte Du Service Edf Pk 300",
    "iso:country":"FR",
    "sg:address":"Rte du Service EDF PK 300",
    "sg:city":"Strasbourg",
    "sg:orig_category":"Unclassifiable Establishments",
    "sg:phone":"+33 3 88 41 86 14",
    "sg:postcode":"67000",
    "sg:province":"Alsace",
    "wof:name":"S.a.s.e. S.n.c. - Soci\u00e9t\u00e9 Alsacienne De Services Et D'environnement",
    "wof:placetype":"venue"
},
  "geometry": {"coordinates":[7.73643,48.585079],"type":"Point"}
}