{
  "type": "Feature",
  "properties": {
    "addr:full":"ZI des Pays-Bas n\u00b02 Briec Bretagne 29510",
    "addr:postcode":"29510",
    "addr:street":"Des;N\u00b02 Briec Bretagne",
    "iso:country":"FR",
    "sg:address":"ZI des Pays-Bas n\u00b02",
    "sg:city":"Briec",
    "sg:orig_category":"Non-Classified Establishments",
    "sg:phone":"+33 2 98 57 74 37",
    "sg:postcode":"29510",
    "sg:province":"Bretagne",
    "wof:name":"Biscuits Panier S.a.",
    "wof:placetype":"venue"
},
  "geometry": {"coordinates":[-3.977899,48.062744],"type":"Point"}
}