{
  "type": "Feature",
  "properties": {
    "addr:full":"72 Rue La Walck 67350 Uberach Uberach Alsace 67350",
    "addr:housenumber":"72",
    "addr:postcode":"67350;67350",
    "addr:street":"Rue La Walck;Uberach",
    "iso:country":"FR",
    "sg:address":"72 Rue La Walck 67350 Uberach",
    "sg:city":"Uberach",
    "sg:classifiers":[
        {
            "category":"Home & Garden",
            "subcategory":"Furniture",
            "type":"Retail Goods"
        }
    ],
    "sg:phone":"+33 3 88 07 72 94",
    "sg:postcode":"67350",
    "sg:province":"Alsace",
    "sg:tags":[
        "wood"
    ],
    "wof:name":"Ste Exploit De La Scierie Grabler Sarl",
    "wof:placetype":"venue"
},
  "geometry": {"coordinates":[7.62145,48.849098],"type":"Point"}
}