{
  "type": "Feature",
  "properties": {
    "iso:country":"FR",
    "sg:address":"84 Rue Du Portail Vert",
    "sg:city":"Entraigues Sur La Sorgue",
    "sg:classifiers":[
        {
            "category":"Banks & Credit Unions",
            "subcategory":"Financial Services",
            "type":"Services"
        }
    ],
    "sg:phone":"+33 4 90 83 27 87",
    "sg:postcode":"84320",
    "sg:province":"Auvergne",
    "sg:tags":[
        "banking",
        "finance",
        "insurance"
    ],
    "wof:name":"Societe Fiduciaire Nationale D'expertise Comptable Fidexpert (fid)",
    "wof:placetype":"venue"
},
  "geometry": {"coordinates":[4.92704,44.003231],"type":"Point"}
}