{
  "type": "Feature",
  "properties": {
    "iso:country":"FR",
    "sg:address":"ZA du Pr\u00e9 Roux",
    "sg:city":"Froges",
    "sg:orig_category":"Non-Classified Establishments",
    "sg:phone":"+33 4 76 71 46 33",
    "sg:postcode":"38190",
    "sg:province":"Rhone-Alpes",
    "wof:name":"M\u00e9ca Pr\u00e9cis Brignoud S.a.r.l.",
    "wof:placetype":"venue"
},
  "geometry": {"coordinates":[5.924355,45.27322],"type":"Point"}
}