{
  "type": "Feature",
  "properties": {
    "iso:country":"FR",
    "sg:address":"Rue des Landacres - Parc d'Activit\u00e9s de Landacres",
    "sg:city":"Hesdin l'Abb\u00e9",
    "sg:orig_category":"Non-Classified Establishments",
    "sg:phone":"+33 3 21 30 40 20",
    "sg:postcode":"62360",
    "sg:province":"Nord Pas-de-Calais",
    "wof:name":"S.n.l.c. S.a. - Soci\u00e9t\u00e9 Nouvelle La Charlotte",
    "wof:placetype":"venue"
},
  "geometry": {"coordinates":[1.679462,50.677269],"type":"Point"}
}