{
  "type": "Feature",
  "properties": {
    "iso:country":"FR",
    "sg:address":"4, Chemin des Fourches, 93380 Pierrefitte sur Seine",
    "sg:orig_category":"Non-Classified Establishments",
    "sg:phone":"+33 1 42 35 23 24",
    "sg:postcode":"93380",
    "sg:province":"Ile de France",
    "wof:name":"Etablissements Martignon S.a.",
    "wof:placetype":"venue"
},
  "geometry": {"coordinates":[2.37322,48.96228],"type":"Point"}
}