{
  "type": "Feature",
  "properties": {
    "iso:country":"FR",
    "sg:address":"16 Rue Source 77320 Beton Bazoches",
    "sg:classifiers":[
        {
            "category":"Professional",
            "type":"Services"
        }
    ],
    "sg:phone":"+33 1 64 01 03 14",
    "sg:province":"Ile de France",
    "sg:tags":[
        "transport",
        "road"
    ],
    "wof:name":"Societe Trans Aubetin Sarl",
    "wof:placetype":"venue"
},
  "geometry": {"coordinates":[3.242209,48.704609],"type":"Point"}
}