{
  "type": "Feature",
  "properties": {
    "iso:country":"FR",
    "sg:address":"La Cornaille 01800 Meximieux",
    "sg:classifiers":[
        {
            "category":"Farming",
            "subcategory":"Farm & Veterinary Services",
            "type":"Manufacturing & Wholesale Goods"
        }
    ],
    "sg:phone":"+33 4 74 61 00 15",
    "sg:postcode":"01800",
    "sg:province":"Rhone-Alpes",
    "sg:tags":[
        "food",
        "product",
        "breeding",
        "animal",
        "related"
    ],
    "wof:name":"Sita Sa",
    "wof:placetype":"venue"
},
  "geometry": {"coordinates":[5.20423,45.897804],"type":"Point"}
}