{
  "type": "Feature",
  "properties": {
    "addr:full":"Parc Technologique du Bois Chaland Lisses Ile de France 91090",
    "addr:postcode":"91090",
    "iso:country":"FR",
    "sg:address":"Parc Technologique du Bois Chaland",
    "sg:city":"Lisses",
    "sg:orig_category":"Unclassifiable Establishments",
    "sg:phone":"+33 1 69 89 89 89",
    "sg:postcode":"91090",
    "sg:province":"Ile de France",
    "wof:name":"Busch France S.a.",
    "wof:placetype":"venue"
},
  "geometry": {"coordinates":[2.423843,48.597694],"type":"Point"}
}