{
  "type": "Feature",
  "properties": {
    "addr:full":"113, Rue Marietton, 69009 Lyon Rhone-Alpes 69009",
    "addr:housenumber":"113",
    "addr:postcode":"69009;69009",
    "addr:street":"Rue Marietton",
    "iso:country":"FR",
    "sg:address":"113, Rue Marietton, 69009 Lyon",
    "sg:orig_category":"Non-Classified Establishments",
    "sg:phone":"+33 4 72 85 66 66",
    "sg:postcode":"69009",
    "sg:province":"Rhone-Alpes",
    "wof:name":"Audisafe Conseil S.a.r.l.",
    "wof:placetype":"venue"
},
  "geometry": {"coordinates":[4.793192,45.773945],"type":"Point"}
}