{
  "type": "Feature",
  "properties": {
    "iso:country":"FR",
    "sg:address":"113, Rue Marietton, 69009 Lyon",
    "sg:orig_category":"Non-Classified Establishments",
    "sg:phone":"+33 4 72 85 66 66",
    "sg:postcode":"69009",
    "sg:province":"Rhone-Alpes",
    "wof:name":"Audisafe Conseil S.a.r.l.",
    "wof:placetype":"venue"
},
  "geometry": {"coordinates":[4.793192,45.773945],"type":"Point"}
}