{
  "type": "Feature",
  "properties": {
    "addr:full":"Avenue De L' Europe 59270 Bailleul Nord Pas-de-Calais 59270",
    "addr:postcode":"59270;59270",
    "addr:street":"Avenue De L ' Europe",
    "iso:country":"FR",
    "sg:address":"Avenue De L' Europe 59270 Bailleul",
    "sg:classifiers":[
        {
            "category":"Wholesale",
            "subcategory":"Farm Supplies",
            "type":"Manufacturing & Wholesale Goods"
        }
    ],
    "sg:phone":"+33 3 28 43 81 91",
    "sg:postcode":"59270",
    "sg:province":"Nord Pas-de-Calais",
    "sg:tags":[
        "-",
        "machine",
        "equipment",
        "engineering",
        "machinery",
        "mechanical",
        "agriculture"
    ],
    "wof:name":"Frans Baele Sa",
    "wof:placetype":"venue"
},
  "geometry": {"coordinates":[2.227244,49.383434],"type":"Point"}
}