{
  "type": "Feature",
  "properties": {
    "addr:full":"13, Place du G\u00e9n\u00e9ral de Gaulle, 33210 Langon Langon Aquitaine 33210",
    "addr:housenumber":"13",
    "addr:postcode":"33210;33210",
    "addr:street":"Place Du Ge\u0301Ne\u0301Ral De Gaulle",
    "iso:country":"FR",
    "sg:address":"13, Place du G\u00e9n\u00e9ral de Gaulle, 33210 Langon",
    "sg:city":"Langon",
    "sg:orig_category":"Non-Classified Establishments",
    "sg:phone":"+33 5 57 98 04 40",
    "sg:postcode":"33210",
    "sg:province":"Aquitaine",
    "wof:name":"Banque Populaire Du Sud Ouest S.a.",
    "wof:placetype":"venue"
},
  "geometry": {"coordinates":[-0.246198,44.552845],"type":"Point"}
}