{
  "type": "Feature",
  "properties": {
    "iso:country":"FR",
    "sg:address":"Rte de Tours",
    "sg:city":"M\u00e9ry sur Cher",
    "sg:orig_category":"Non-Classified Establishments",
    "sg:phone":"+33 2 48 75 25 81",
    "sg:postcode":"18100",
    "sg:province":"Centre",
    "wof:name":"E.s.m.p. S.a.r.l.",
    "wof:placetype":"venue"
},
  "geometry": {"coordinates":[2.020555,47.206581],"type":"Point"}
}