{
  "type": "Feature",
  "properties": {
    "addr:full":"ZA de la Blanche T\u00e2che Camon Picardie 80450",
    "addr:postcode":"80450",
    "addr:street":"Za De La Blanche",
    "iso:country":"FR",
    "sg:address":"ZA de la Blanche T\u00e2che",
    "sg:city":"Camon",
    "sg:orig_category":"Non-Classified Establishments",
    "sg:phone":"+33 3 22 70 27 70",
    "sg:postcode":"80450",
    "sg:province":"Picardie",
    "wof:name":"Eurovia Nord S.n.c.",
    "wof:placetype":"venue"
},
  "geometry": {"coordinates":[2.34342,49.887493],"type":"Point"}
}