{
  "type": "Feature",
  "properties": {
    "iso:country":"FR",
    "sg:address":"10 Boulevard De La Marne 59420 Mouvaux",
    "sg:classifiers":[
        {
            "category":"Shopping",
            "subcategory":"Clothing, Apparel, & Fashions",
            "type":"Retail Goods"
        }
    ],
    "sg:phone":"+33 3 20 28 37 00",
    "sg:postcode":"59420",
    "sg:province":"Nord Pas-de-Calais",
    "sg:tags":[
        "textile",
        "clothing",
        "clothes"
    ],
    "wof:name":"Etam",
    "wof:placetype":"venue"
},
  "geometry": {"coordinates":[3.15046,50.708721],"type":"Point"}
}