{
  "type": "Feature",
  "properties": {
    "addr:full":"145 rue de Belleville 75019 Paris Ile de France 75019",
    "addr:housenumber":"145",
    "addr:postcode":"75019;75019",
    "addr:street":"Rue De Belleville",
    "iso:country":"FR",
    "sg:address":"145 rue de Belleville 75019 Paris",
    "sg:classifiers":[
        {
            "category":"Structure",
            "subcategory":"Tower",
            "type":"Public Place"
        }
    ],
    "sg:phone":"+33 1 42 03 24 56",
    "sg:postcode":"75019",
    "sg:province":"Ile de France",
    "sg:tags":[
        "steel",
        "knife"
    ],
    "wof:name":"Sabre S.a.r.l.",
    "wof:placetype":"venue"
},
  "geometry": {"coordinates":[2.389878,48.875496],"type":"Point"}
}