{
  "type": "Feature",
  "properties": {
    "addr:full":"12 Avenue Louis Ricoux 87210 Le Dorat Limousin 87210",
    "addr:housenumber":"12",
    "addr:postcode":"87210;87210",
    "addr:street":"Avenue Louis Ricoux",
    "iso:country":"FR",
    "sg:address":"12 Avenue Louis Ricoux 87210 Le Dorat",
    "sg:classifiers":[
        {
            "category":"Shopping",
            "subcategory":"Clothing, Apparel, & Fashions",
            "type":"Retail Goods"
        }
    ],
    "sg:phone":"+33 5 55 60 70 71",
    "sg:postcode":"87210",
    "sg:province":"Limousin",
    "sg:tags":[
        "textile",
        "clothing",
        "clothes"
    ],
    "wof:name":"Allande",
    "wof:placetype":"venue"
},
  "geometry": {"coordinates":[1.086165,46.213997],"type":"Point"}
}