{
  "type": "Feature",
  "properties": {
    "iso:country":"FR",
    "sg:address":"Zone Industrielle 71210 Torcy",
    "sg:city":"Torcy",
    "sg:classifiers":[
        {
            "category":"Professional",
            "type":"Services"
        }
    ],
    "sg:phone":"+33 3 85 77 02 50",
    "sg:postcode":"71210",
    "sg:province":"Bourgogne",
    "sg:tags":[
        "transport"
    ],
    "wof:name":"Euro Messagerie Sa",
    "wof:placetype":"venue"
},
  "geometry": {"coordinates":[4.434358,46.78389],"type":"Point"}
}