{
  "type": "Feature",
  "properties": {
    "iso:country":"FR",
    "sg:address":"138, Rue L\u00e9on Foucher, 51450 B\u00e9theny",
    "sg:orig_category":"Unclassifiable Establishments",
    "sg:phone":"+33 3 26 88 34 93",
    "sg:province":"Champagne",
    "wof:name":"A.j.c. International S.a.r.l.",
    "wof:placetype":"venue"
},
  "geometry": {"coordinates":[4.042631,49.271778],"type":"Point"}
}