{
  "type": "Feature",
  "properties": {
    "iso:country":"FR",
    "sg:address":"48 All Des Platanes 77100 Meaux",
    "sg:classifiers":[
        {
            "category":"Wholesale",
            "subcategory":"Farm Supplies",
            "type":"Manufacturing & Wholesale Goods"
        }
    ],
    "sg:phone":"+33 1 60 09 95 55",
    "sg:postcode":"77100",
    "sg:province":"Ile de France",
    "sg:tags":[
        "-",
        "machine",
        "equipment",
        "engineering",
        "machinery",
        "mechanical",
        "agriculture"
    ],
    "wof:name":"Ste Fernand Depla Sa",
    "wof:placetype":"venue"
},
  "geometry": {"coordinates":[2.928589,48.950531],"type":"Point"}
}