{
  "type": "Feature",
  "properties": {
    "addr:full":"Rue Denis Papin Zi De Kerpont 56600 Lanester Lanester Bretagne 56600",
    "addr:postcode":"56600;56600",
    "addr:street":"Rue Denis Papin Zi De Kerpont",
    "iso:country":"FR",
    "sg:address":"Rue Denis Papin Zi De Kerpont 56600 Lanester",
    "sg:city":"Lanester",
    "sg:classifiers":[
        {
            "category":"Professional",
            "subcategory":"Engineering",
            "type":"Services"
        }
    ],
    "sg:phone":"+33 2 97 76 40 44",
    "sg:postcode":"56600",
    "sg:province":"Bretagne",
    "sg:tags":[
        "machine",
        "-",
        "mechanical"
    ],
    "wof:name":"Guerbet",
    "wof:placetype":"venue"
},
  "geometry": {"coordinates":[-3.345244,47.76532],"type":"Point"}
}