{
  "type": "Feature",
  "properties": {
    "addr:full":"199, Av. de Jouques - ZI des Paluds, 13685 Aubagne C\u00e9dex",
    "addr:postcode":"13685",
    "addr:street":"199 Av. De Jouques Zi Des Paluds",
    "iso:country":"FR",
    "sg:address":"199, Av. de Jouques - ZI des Paluds, 13685 Aubagne C\u00e9dex",
    "sg:orig_category":"Non-Classified Establishments",
    "sg:phone":"+33 4 42 84 47 84",
    "wof:name":"Sara S.a.",
    "wof:placetype":"venue"
},
  "geometry": {"coordinates":[5.57028,43.293251],"type":"Point"}
}