{
  "type": "Feature",
  "properties": {
    "iso:country":"FR",
    "sg:address":"5 Rue De La Ruette Au Loup 35400 St Malo",
    "sg:city":"Saint-Malo",
    "sg:classifiers":[
        {
            "category":"Manufacturing",
            "subcategory":"Printing",
            "type":"Manufacturing & Wholesale Goods"
        }
    ],
    "sg:phone":"+33 2 99 82 85 85",
    "sg:postcode":"35400",
    "sg:province":"Bretagne",
    "sg:tags":[
        "publishing"
    ],
    "wof:name":"Servicheque Sa",
    "wof:placetype":"venue"
},
  "geometry": {"coordinates":[-1.98133,48.63649],"type":"Point"}
}