{
  "type": "Feature",
  "properties": {
    "iso:country":"FR",
    "sg:address":"375 rue des Techniques 74970 MARIGNIER",
    "sg:classifiers":[
        {
            "category":"Wholesale",
            "subcategory":"Auto Parts",
            "type":"Manufacturing & Wholesale Goods"
        }
    ],
    "sg:phone":"+33 4 50 34 64 60",
    "sg:province":"Rhone-Alpes",
    "sg:tags":[
        "machine",
        "screw"
    ],
    "wof:name":"Pernat Emile Sa",
    "wof:placetype":"venue"
},
  "geometry": {"coordinates":[6.50713,46.076172],"type":"Point"}
}