{
  "type": "Feature",
  "properties": {
    "addr:full":"Za Les Arrailles 65400 Agos Vidalos Midi Pyr\u00e9n\u00e9es",
    "addr:postcode":"65400",
    "addr:street":"Za Les Arrailles",
    "iso:country":"FR",
    "sg:address":"Za Les Arrailles 65400 Agos Vidalos",
    "sg:classifiers":[
        {
            "category":"Home & Garden",
            "subcategory":"Furniture",
            "type":"Retail Goods"
        }
    ],
    "sg:phone":"+33 5 62 90 30 69",
    "sg:province":"Midi Pyr\u00e9n\u00e9es",
    "sg:tags":[
        "wood"
    ],
    "wof:name":"K Bois",
    "wof:placetype":"venue"
},
  "geometry": {"coordinates":[-0.070154,43.036144],"type":"Point"}
}