{
  "type": "Feature",
  "properties": {
    "addr:full":"21, Rue de la Noue Guimante - ZI de la Courtilli\u00e8re, 77400 Saint Thibault des Vignes Ile de France",
    "addr:housenumber":"21",
    "addr:postcode":"77400;ile",
    "addr:street":"Rue De La;Zi De La Courtillie\u0300Re",
    "iso:country":"FR",
    "sg:address":"21, Rue de la Noue Guimante - ZI de la Courtilli\u00e8re, 77400 Saint Thibault des Vignes",
    "sg:orig_category":"Unclassifiable Establishments",
    "sg:phone":"+33 1 64 12 45 67",
    "sg:province":"Ile de France",
    "wof:name":"Fiopteck S.a.",
    "wof:placetype":"venue"
},
  "geometry": {"coordinates":[2.701485,48.87775],"type":"Point"}
}