{
  "type": "Feature",
  "properties": {
    "addr:full":"14 Quai Du Commerce 69009 Lyon Rhone-Alpes 69009",
    "addr:housenumber":"14",
    "addr:postcode":"69009;69009",
    "addr:street":"Quai Du Commerce",
    "iso:country":"FR",
    "sg:address":"14 Quai Du Commerce 69009 Lyon",
    "sg:classifiers":[
        {
            "category":"Shopping",
            "subcategory":"Crafts & Fabrics",
            "type":"Retail Goods"
        }
    ],
    "sg:phone":"+33 4 37 64 26 60",
    "sg:postcode":"69009",
    "sg:province":"Rhone-Alpes",
    "sg:tags":[
        "textile",
        "clothing"
    ],
    "wof:name":"Reynaud Rexo",
    "wof:placetype":"venue"
},
  "geometry": {"coordinates":[4.81091,45.782829],"type":"Point"}
}