{
  "type": "Feature",
  "properties": {
    "addr:full":"Rte d'Etusson Argenton Ch\u00e2teau Poitou-Charentes 79150",
    "addr:postcode":"79150",
    "addr:street":"Rte D'Etusson;Cha\u0302Teau",
    "iso:country":"FR",
    "sg:address":"Rte d'Etusson",
    "sg:city":"Argenton Ch\u00e2teau",
    "sg:orig_category":"Unclassifiable Establishments",
    "sg:phone":"+33 5 49 65 96 47",
    "sg:postcode":"79150",
    "sg:province":"Poitou-Charentes",
    "wof:name":"Toltex S.a.",
    "wof:placetype":"venue"
},
  "geometry": {"coordinates":[-0.51475,47.013962],"type":"Point"}
}