{
  "type": "Feature",
  "properties": {
    "addr:full":"Avenue du Docteur Guilhem 11401 CASTELNAUDARY CEDEX Midi Pyr\u00e9n\u00e9es",
    "addr:postcode":"11401",
    "addr:street":"Avenue Du Docteur Guilhem",
    "iso:country":"FR",
    "sg:address":"Avenue du Docteur Guilhem 11401 CASTELNAUDARY CEDEX",
    "sg:classifiers":[
        {
            "category":"Food & Beverages",
            "subcategory":"Meat & Fish",
            "type":"Retail Goods"
        }
    ],
    "sg:phone":"+33 4 68 94 47 55",
    "sg:province":"Midi Pyr\u00e9n\u00e9es",
    "wof:name":"Spanghero S.a.viandes",
    "wof:placetype":"venue"
},
  "geometry": {"coordinates":[1.953495,43.318245],"type":"Point"}
}