{
  "type": "Feature",
  "properties": {
    "addr:full":"36 R Des Jeneurs 75002 Paris Ile de France 75002",
    "addr:housenumber":"36",
    "addr:postcode":"75002;75002",
    "addr:street":"R Des Jeneurs",
    "iso:country":"FR",
    "sg:address":"36 R Des Jeneurs 75002 Paris",
    "sg:classifiers":[
        {
            "category":"Shopping",
            "subcategory":"Crafts & Fabrics",
            "type":"Retail Goods"
        }
    ],
    "sg:phone":"+33 1 40 26 54 69",
    "sg:postcode":"75002",
    "sg:province":"Ile de France",
    "sg:tags":[
        "rubber",
        "textile",
        "linen",
        "clothing",
        "plastic"
    ],
    "wof:name":"Pinton Sa",
    "wof:placetype":"venue"
},
  "geometry": {"coordinates":[2.3443,48.869774],"type":"Point"}
}