{
  "type": "Feature",
  "properties": {
    "iso:country":"FR",
    "sg:address":"Chemin De La Cochiette 62138 Violaines",
    "sg:classifiers":[
        {
            "category":"Banks & Credit Unions",
            "subcategory":"Investment Brokerage",
            "type":"Services"
        }
    ],
    "sg:phone":"+33 3 21 25 04 41",
    "sg:province":"Nord Pas-de-Calais",
    "sg:tags":[
        "-",
        "transport",
        "related"
    ],
    "wof:name":"Ardo Violaines",
    "wof:placetype":"venue"
},
  "geometry": {"coordinates":[2.784263,50.548634],"type":"Point"}
}