{
  "type": "Feature",
  "properties": {
    "addr:full":"6 B Rue Des Sadinettes 78400 Chatou Ile de France 78400",
    "addr:housenumber":"6 b",
    "addr:postcode":"78400;78400",
    "addr:street":"Rue Des Sadinettes;Ile De France",
    "iso:country":"FR",
    "sg:address":"6 B Rue Des Sadinettes 78400 Chatou",
    "sg:classifiers":[
        {
            "category":"Professional",
            "subcategory":"Business Services",
            "type":"Services"
        }
    ],
    "sg:phone":"+33 1 30 71 46 15",
    "sg:postcode":"78400",
    "sg:province":"Ile de France",
    "sg:tags":[
        "body",
        "advice"
    ],
    "wof:name":"Aide Aux Personnes Agees",
    "wof:placetype":"venue"
},
  "geometry": {"coordinates":[2.1558,48.889992],"type":"Point"}
}