{
  "type": "Feature",
  "properties": {
    "iso:country":"FR",
    "sg:address":"18 rue du Mail 75002 Paris",
    "sg:classifiers":[
        {
            "category":"Manufacturing",
            "subcategory":"Textiles",
            "type":"Manufacturing & Wholesale Goods"
        }
    ],
    "sg:phone":"+33 1 42 36 99 70",
    "sg:postcode":"75002",
    "sg:province":"Ile de France",
    "sg:tags":[
        "natural"
    ],
    "wof:name":"Bonair Paris Sarl",
    "wof:placetype":"venue"
},
  "geometry": {"coordinates":[2.342625,48.866653],"type":"Point"}
}