{
  "type": "Feature",
  "properties": {
    "addr:full":"10, Rue de la Gare, 55000 Longeville en Barrois Lorraine",
    "addr:housenumber":"10",
    "addr:postcode":"55000",
    "addr:street":"Rue De La Gare",
    "iso:country":"FR",
    "sg:address":"10, Rue de la Gare, 55000 Longeville en Barrois",
    "sg:orig_category":"Unclassifiable Establishments",
    "sg:phone":"+33 3 29 79 14 15",
    "sg:province":"Lorraine",
    "wof:name":"Colombo S.a.",
    "wof:placetype":"venue"
},
  "geometry": {"coordinates":[5.212805,48.742222],"type":"Point"}
}