{
  "type": "Feature",
  "properties": {
    "iso:country":"FR",
    "sg:address":"48, Rue Vivienne, 75002 Paris",
    "sg:orig_category":"Unclassifiable Establishments",
    "sg:phone":"+33 1 40 13 79 79",
    "sg:province":"Ile de France",
    "wof:name":"Giphar France",
    "wof:placetype":"venue"
},
  "geometry": {"coordinates":[2.341676,48.871571],"type":"Point"}
}