{
  "type": "Feature",
  "properties": {
    "addr:full":"16/18, Rue Marcel Vigneron, 94110 Arcueil Ile de France",
    "addr:housenumber":"16 / 18",
    "addr:postcode":"94110;ile",
    "addr:street":"Rue Marcel Vigneron",
    "iso:country":"FR",
    "sg:address":"16/18, Rue Marcel Vigneron, 94110 Arcueil",
    "sg:orig_category":"Non-Classified Establishments",
    "sg:phone":"+33 1 46 15 05 50",
    "sg:province":"Ile de France",
    "wof:name":"Soci\u00e9t\u00e9 D'edition Graphi Plus S.a.",
    "wof:placetype":"venue"
},
  "geometry": {"coordinates":[2.34252,48.80228],"type":"Point"}
}