{
  "type": "Feature",
  "properties": {
    "iso:country":"FR",
    "sg:address":"ZI des Bourguignons",
    "sg:city":"Apt",
    "sg:orig_category":"Unclassifiable Establishments",
    "sg:phone":"+33 4 90 74 57 08",
    "sg:postcode":"84400",
    "sg:province":"Centre",
    "wof:name":"Sid\u00e9ral S.a.",
    "wof:placetype":"venue"
},
  "geometry": {"coordinates":[5.395111,43.875885],"type":"Point"}
}