{
  "type": "Feature",
  "properties": {
    "iso:country":"FR",
    "sg:address":"B.P. 2, 59920 Qui\u00e9vrechain^^94, Rue Valeriani, 59920 Qui\u00e9vrechain",
    "sg:orig_category":"Non-Classified Establishments",
    "sg:phone":"+33 3 27 22 76 00",
    "sg:province":"Nord Pas-de-Calais",
    "wof:name":"Sofanor S.a. - Soci\u00e9t\u00e9 De Fabrication Du Nord",
    "wof:placetype":"venue"
},
  "geometry": {"coordinates":[3.66632,50.403015],"type":"Point"}
}