{
  "type": "Feature",
  "properties": {
    "iso:country":"FR",
    "sg:address":"3/5, Av. Galli\u00e9ni - B\u00e2t. Orsud, 94250 Gentilly",
    "sg:orig_category":"Non-Classified Establishments",
    "sg:phone":"+33 1 49 69 86 86",
    "sg:postcode":"94250",
    "sg:province":"Ile de France",
    "wof:name":"Chronopost International S.a.",
    "wof:placetype":"venue"
},
  "geometry": {"coordinates":[2.353187,48.816429],"type":"Point"}
}