{
  "type": "Feature",
  "properties": {
    "addr:full":"7 bis, Rue Nationale, 57660 Grostenquin Lorraine",
    "addr:housenumber":"7 bis",
    "addr:postcode":"57660",
    "addr:street":"Rue Nationale",
    "iso:country":"FR",
    "sg:address":"7 bis, Rue Nationale, 57660 Grostenquin",
    "sg:orig_category":"Unclassifiable Establishments",
    "sg:phone":"+33 3 87 01 70 40",
    "sg:province":"Lorraine",
    "wof:name":"Becher S.a.r.l.",
    "wof:placetype":"venue"
},
  "geometry": {"coordinates":[6.737473,48.979416],"type":"Point"}
}