{
  "type": "Feature",
  "properties": {
    "iso:country":"FR",
    "sg:address":"Rte de Marmagne - ZI N\u00b0 2",
    "sg:city":"Bourges",
    "sg:orig_category":"Unclassifiable Establishments",
    "sg:phone":"+33 2 48 21 87 10",
    "sg:postcode":"18000",
    "sg:province":"Centre",
    "wof:name":"Transports H\u00e9l\u00e8s S.a.r.l.",
    "wof:placetype":"venue"
},
  "geometry": {"coordinates":[2.39293,47.085854],"type":"Point"}
}