{
  "type": "Feature",
  "properties": {
    "addr:full":"71 rue F\u00e9lix Pyat 13300 Salon de Provence Provence-Alpes-C\u00f4te d'Azur",
    "addr:housenumber":"71",
    "addr:postcode":"13300",
    "addr:street":"Rue Fe\u0301Lix Pyat;Provence",
    "iso:country":"FR",
    "sg:address":"71 rue F\u00e9lix Pyat 13300 Salon de Provence",
    "sg:classifiers":[
        {
            "category":"Manufacturing",
            "subcategory":"Soap",
            "type":"Manufacturing & Wholesale Goods"
        }
    ],
    "sg:phone":"+33 4 90 56 07 28",
    "sg:province":"Provence-Alpes-C\u00f4te d'Azur",
    "sg:tags":[
        "bubble",
        "individual",
        "hotel",
        "portions",
        "bath"
    ],
    "wof:name":"Rampal Patou S.a.r.l.",
    "wof:placetype":"venue"
},
  "geometry": {"coordinates":[5.092254,43.642097],"type":"Point"}
}