{
  "type": "Feature",
  "properties": {
    "addr:full":"4, Chemin de l'Industrie, 69570 Dardilly Rhone-Alpes 69570",
    "addr:housenumber":"4",
    "addr:postcode":"69570;69570",
    "addr:street":"Chemin De L'Industrie",
    "iso:country":"FR",
    "sg:address":"4, Chemin de l'Industrie, 69570 Dardilly",
    "sg:orig_category":"Non-Classified Establishments",
    "sg:phone":"+33 4 72 52 32 52",
    "sg:postcode":"69570",
    "sg:province":"Rhone-Alpes",
    "wof:name":"Cerniaut S.a.",
    "wof:placetype":"venue"
},
  "geometry": {"coordinates":[4.76868,45.804382],"type":"Point"}
}