{
  "type": "Feature",
  "properties": {
    "addr:full":"Rte de Moulins Decize Bourgogne 58300",
    "addr:postcode":"58300",
    "addr:street":"Rte De Moulins;Bourgogne",
    "iso:country":"FR",
    "sg:address":"Rte de Moulins",
    "sg:city":"Decize",
    "sg:orig_category":"Unclassifiable Establishments",
    "sg:phone":"+33 3 86 25 17 23",
    "sg:postcode":"58300",
    "sg:province":"Bourgogne",
    "wof:name":"S.g.l. S.a. - Sables Et Graviers De Loire",
    "wof:placetype":"venue"
},
  "geometry": {"coordinates":[3.45125,46.820049],"type":"Point"}
}