{
  "type": "Feature",
  "properties": {
    "addr:full":"31 Rue Cauchy 94110 Arcueil Ile de France 94110",
    "addr:housenumber":"31",
    "addr:postcode":"94110;ile;94110",
    "addr:street":"Rue Cauchy;France",
    "iso:country":"FR",
    "sg:address":"31 Rue Cauchy 94110 Arcueil",
    "sg:classifiers":[
        {
            "category":"Wholesale",
            "subcategory":"Machinery & Supplies",
            "type":"Manufacturing & Wholesale Goods"
        }
    ],
    "sg:phone":"+33 1 45 47 67 87",
    "sg:postcode":"94110",
    "sg:province":"Ile de France",
    "sg:tags":[
        "handling",
        "material",
        "-",
        "machine",
        "equipment",
        "engineering",
        "mechanical"
    ],
    "wof:name":"Ascenseur Technologie Serrurerie Sa",
    "wof:placetype":"venue"
},
  "geometry": {"coordinates":[2.333664,48.803253],"type":"Point"}
}