{
  "type": "Feature",
  "properties": {
    "iso:country":"FR",
    "sg:address":"807 Rue Des Merci\u00e9res 69140 Rillieux La Pape",
    "sg:classifiers":[
        {
            "category":"Farming",
            "subcategory":"Crops",
            "type":"Manufacturing & Wholesale Goods"
        }
    ],
    "sg:phone":"+33 4 78 88 06 66",
    "sg:postcode":"69140",
    "sg:province":"Rhone-Alpes",
    "sg:tags":[
        "vegetable",
        "fruit",
        "agriculture",
        "livestock"
    ],
    "wof:name":"Mariano Sa",
    "wof:placetype":"venue"
},
  "geometry": {"coordinates":[4.876698,45.815254],"type":"Point"}
}