{
  "type": "Feature",
  "properties": {
    "iso:country":"FR",
    "sg:address":"B.P. 46",
    "sg:city":"Frans^^Le Crozat 01480 Frans",
    "sg:orig_category":"Non-Classified Establishments",
    "sg:phone":"+33 4 74 67 54 62",
    "sg:postcode":"01480",
    "sg:province":"Rhone-Alpes",
    "wof:name":"Soci\u00e9t\u00e9 Bressane De Pl\u00e2trerie S.a.r.l.",
    "wof:placetype":"venue"
},
  "geometry": {"coordinates":[4.78928,46.00367],"type":"Point"}
}