{
  "type": "Feature",
  "properties": {
    "iso:country":"FR",
    "sg:address":"B.P. 2741, 51061 Reims C\u00e9dex^^9, Place Saint Nicaise, 51100 Reims",
    "sg:orig_category":"Non-Classified Establishments",
    "sg:phone":"+33 3 26 85 45 35",
    "sg:postcode":"51100",
    "sg:province":"Champagne",
    "wof:name":"Champagne Taittinger S.a.",
    "wof:placetype":"venue"
},
  "geometry": {"coordinates":[4.028445,49.26284],"type":"Point"}
}