{
  "type": "Feature",
  "properties": {
    "iso:country":"FR",
    "sg:address":"90 rue Fr\u00e9d\u00e9ric Joliot 13100 Aix en Provence",
    "sg:classifiers":[
        {
            "category":"Personal",
            "subcategory":"Barber",
            "type":"Services"
        }
    ],
    "sg:phone":"+33 4 42 90 07 77",
    "sg:province":"Provence-Alpes-C\u00f4te d'Azur",
    "sg:tags":[
        "hairdresser",
        "software"
    ],
    "wof:name":"Ikosoft S.a.",
    "wof:placetype":"venue"
},
  "geometry": {"coordinates":[5.49167,43.509033],"type":"Point"}
}