{
  "type": "Feature",
  "properties": {
    "addr:full":"Z I ouest 67150 Erstein Erstein Alsace 67150",
    "addr:postcode":"67150;67150",
    "addr:street":"Z I Ouest",
    "iso:country":"FR",
    "sg:address":"Z I ouest 67150 Erstein",
    "sg:city":"Erstein",
    "sg:classifiers":[
        {
            "category":"Banks & Credit Unions",
            "subcategory":"Investment Brokerage",
            "type":"Services"
        }
    ],
    "sg:phone":"+33 3 88 98 12 40",
    "sg:postcode":"67150",
    "sg:province":"Alsace",
    "sg:tags":[
        "support",
        "scaffolding"
    ],
    "wof:name":"Baumert C.m. Sas",
    "wof:placetype":"venue"
},
  "geometry": {"coordinates":[7.634835,48.422699],"type":"Point"}
}