{
  "type": "Feature",
  "properties": {
    "iso:country":"FR",
    "sg:address":"68 Rue Des Sazieres 92700 Colombes",
    "sg:classifiers":[
        {
            "category":"Manufacturing",
            "subcategory":"Metals",
            "type":"Manufacturing & Wholesale Goods"
        }
    ],
    "sg:phone":"+33 1 42 42 85 27",
    "sg:postcode":"92700",
    "sg:province":"Ile de France",
    "sg:tags":[
        "metallurgy",
        "steel",
        "metalworking"
    ],
    "wof:name":"Fransor Industrie",
    "wof:placetype":"venue"
},
  "geometry": {"coordinates":[2.269959,48.927624],"type":"Point"}
}