{
  "type": "Feature",
  "properties": {
    "iso:country":"FR",
    "sg:address":"15 Place Notre Dame 76270 Neufchatel En Bray",
    "sg:classifiers":[
        {
            "category":"Professional",
            "subcategory":"Advertising",
            "type":"Services"
        }
    ],
    "sg:phone":"+33 2 35 93 02 68",
    "sg:postcode":"76270",
    "sg:province":"Haute Normandie",
    "sg:tags":[
        "information",
        "medium",
        "communication"
    ],
    "wof:name":"Societe Normande De Presse Republicaine (snpr)",
    "wof:placetype":"venue"
},
  "geometry": {"coordinates":[1.44168,49.73204],"type":"Point"}
}