{
  "type": "Feature",
  "properties": {
    "iso:country":"FR",
    "sg:address":"42, Rue Gustave Eiffel - ZI de la Capelette, 13010 Marseille",
    "sg:orig_category":"Non-Classified Establishments",
    "sg:phone":"+33 4 91 79 57 70",
    "sg:province":"Poitou-Charentes",
    "wof:name":"Vink France S.a.",
    "wof:placetype":"venue"
},
  "geometry": {"coordinates":[5.39525,43.281929],"type":"Point"}
}