{
  "type": "Feature",
  "properties": {
    "addr:full":"3, Rue de la Motte, 28110 Luc\u00e9 Luc\u00e9 Centre 28110",
    "addr:housenumber":"3",
    "addr:postcode":"28110;28110",
    "addr:street":"Rue De La Motte",
    "iso:country":"FR",
    "sg:address":"3, Rue de la Motte, 28110 Luc\u00e9",
    "sg:city":"Luc\u00e9",
    "sg:orig_category":"Unclassifiable Establishments",
    "sg:phone":"+33 2 37 88 09 99",
    "sg:postcode":"28110",
    "sg:province":"Centre",
    "wof:name":"Axmatel S.a.",
    "wof:placetype":"venue"
},
  "geometry": {"coordinates":[1.454908,48.426853],"type":"Point"}
}