{
  "type": "Feature",
  "properties": {
    "addr:full":"68, Av. de K\u00e9radennec, 29000 Quimper Quimper Bretagne 29000",
    "addr:postcode":"29000;29000",
    "addr:street":"68 Av. De Ke\u0301Radennec",
    "iso:country":"FR",
    "sg:address":"68, Av. de K\u00e9radennec, 29000 Quimper",
    "sg:city":"Quimper",
    "sg:orig_category":"Non-Classified Establishments",
    "sg:phone":"+33 2 98 53 30 48",
    "sg:postcode":"29000",
    "sg:province":"Bretagne",
    "wof:name":"Institut Coop\u00e9rative Breton Getion Comptabilit\u00e9 G\u00e9n\u00e9rale Agricole",
    "wof:placetype":"venue"
},
  "geometry": {"coordinates":[-4.083179,47.97488],"type":"Point"}
}