{
  "type": "Feature",
  "properties": {
    "addr:full":"8 Rue De L'Industrie 08400 Vouziers Champagne",
    "addr:housenumber":"8",
    "addr:postcode":"08400",
    "addr:street":"Rue De L'Industrie",
    "iso:country":"FR",
    "sg:address":"8 Rue De L'Industrie 08400 Vouziers",
    "sg:classifiers":[
        {
            "category":"Professional",
            "type":"Services"
        }
    ],
    "sg:phone":"+33 3 24 71 82 39",
    "sg:province":"Champagne",
    "sg:tags":[
        "transport",
        "road"
    ],
    "wof:name":"Copel Sarl",
    "wof:placetype":"venue"
},
  "geometry": {"coordinates":[4.68923,49.394745],"type":"Point"}
}