{
  "type": "Feature",
  "properties": {
    "addr:full":"26, Rue Jallois, 93120 La Courneuve Ile de France",
    "addr:housenumber":"26",
    "addr:postcode":"93120",
    "addr:street":"Rue Jallois",
    "iso:country":"FR",
    "sg:address":"26, Rue Jallois, 93120 La Courneuve",
    "sg:orig_category":"Unclassifiable Establishments",
    "sg:phone":"+33 1 43 52 10 21",
    "sg:province":"Ile de France",
    "wof:name":"Vilnoy Fils Et Compagnie S.a.r.l.",
    "wof:placetype":"venue"
},
  "geometry": {"coordinates":[2.38335,48.92178],"type":"Point"}
}