{
  "type": "Feature",
  "properties": {
    "addr:full":"Rue Anatole France - ZI Beauregard Luxeuil les Bains Franche Comt\u00e9 70300",
    "addr:postcode":"70300",
    "addr:street":"Rue Anatole France Zi Beauregard;Franche Comte\u0301",
    "iso:country":"FR",
    "sg:address":"Rue Anatole France - ZI Beauregard",
    "sg:city":"Luxeuil les Bains",
    "sg:orig_category":"Non-Classified Establishments",
    "sg:phone":"+33 3 84 93 88 21",
    "sg:postcode":"70300",
    "sg:province":"Franche Comt\u00e9",
    "wof:name":"Cattinair International S.a.",
    "wof:placetype":"venue"
},
  "geometry": {"coordinates":[6.3795,47.819172],"type":"Point"}
}