{
  "type": "Feature",
  "properties": {
    "addr:full":"Rte De Sarre Union 57670 Munster Lorraine 57670",
    "addr:postcode":"57670;57670",
    "addr:street":"Rte De Sarre",
    "iso:country":"FR",
    "sg:address":"Rte De Sarre Union 57670 Munster",
    "sg:classifiers":[
        {
            "category":"Food Court",
            "type":"Food & Drink"
        }
    ],
    "sg:phone":"+33 3 87 01 62 01",
    "sg:postcode":"57670",
    "sg:province":"Lorraine",
    "sg:tags":[
        "product",
        "related"
    ],
    "wof:name":"Etablissements Geyer Freres",
    "wof:placetype":"venue"
},
  "geometry": {"coordinates":[6.857435,48.932426],"type":"Point"}
}