{
  "type": "Feature",
  "properties": {
    "iso:country":"FR",
    "sg:address":"5, Quai de Tourville, 44000 Nantes",
    "sg:orig_category":"Unclassifiable Establishments",
    "sg:phone":"+33 2 40 47 75 88",
    "sg:province":"Pays de Loire",
    "wof:name":"T\u00f4lerie De La Loire S.a.",
    "wof:placetype":"venue"
},
  "geometry": {"coordinates":[-1.557668,47.209679],"type":"Point"}
}