{
  "type": "Feature",
  "properties": {
    "addr:full":"38, Rue Marbeuf, 75008 Paris Ile de France",
    "addr:housenumber":"38",
    "addr:postcode":"75008",
    "addr:street":"Rue Marbeuf",
    "iso:country":"FR",
    "sg:address":"38, Rue Marbeuf, 75008 Paris",
    "sg:orig_category":"Unclassifiable Establishments",
    "sg:phone":"+33 1 49 53 10 00",
    "sg:province":"Ile de France",
    "wof:name":"Chargeurs Textiles S.a.",
    "wof:placetype":"venue"
},
  "geometry": {"coordinates":[2.305876,48.869713],"type":"Point"}
}