{
  "type": "Feature",
  "properties": {
    "addr:full":"23 Rue Auguste Vitu 75015 Paris Ile de France 75015",
    "addr:housenumber":"23",
    "addr:postcode":"75015;75015",
    "addr:street":"Rue Auguste Vitu",
    "iso:country":"FR",
    "sg:address":"23 Rue Auguste Vitu 75015 Paris",
    "sg:classifiers":[
        {
            "category":"Manufacturing",
            "subcategory":"Textiles",
            "type":"Manufacturing & Wholesale Goods"
        }
    ],
    "sg:phone":"+33 1 56 77 02 50",
    "sg:postcode":"75015",
    "sg:province":"Ile de France",
    "sg:tags":[
        "linen",
        "clothing",
        "fabric"
    ],
    "wof:name":"Etablissements Drouault",
    "wof:placetype":"venue"
},
  "geometry": {"coordinates":[2.278279,48.84486],"type":"Point"}
}