{
  "type": "Feature",
  "properties": {
    "iso:country":"FR",
    "sg:address":"Rue De La Vallee D Ossau 64811 SERRES CASTET",
    "sg:classifiers":[
        {
            "category":"Manufacturing",
            "subcategory":"Motor Vehicles & Parts",
            "type":"Manufacturing & Wholesale Goods"
        }
    ],
    "sg:phone":"+33 5 59 33 31 95",
    "sg:province":"Midi Pyr\u00e9n\u00e9es",
    "sg:tags":[
        "machine",
        "wear-resistant",
        "components"
    ],
    "wof:name":"Socomexp Sarl",
    "wof:placetype":"venue"
},
  "geometry": {"coordinates":[-0.381356,43.358955],"type":"Point"}
}