{
  "type": "Feature",
  "properties": {
    "iso:country":"FR",
    "sg:address":"Rue Du Port De Bercy Port Amont 75012 Paris",
    "sg:classifiers":[
        {
            "category":"Manufacturing",
            "subcategory":"Glass & Minerals",
            "type":"Manufacturing & Wholesale Goods"
        }
    ],
    "sg:phone":"+33 1 43 44 47 04",
    "sg:postcode":"75012",
    "sg:province":"Ile de France",
    "sg:tags":[
        "building",
        "material"
    ],
    "wof:name":"Beton De Paris",
    "wof:placetype":"venue"
},
  "geometry": {"coordinates":[2.389295,48.841045],"type":"Point"}
}