{
  "type": "Feature",
  "properties": {
    "iso:country":"FR",
    "sg:address":"13, Bd du Roussillon - ZI, 19250 Meymac",
    "sg:orig_category":"Unclassifiable Establishments",
    "sg:phone":"+33 5 55 95 11 14",
    "sg:province":"Limousin",
    "wof:name":"S.t.i.c.a.m. S.a.r.l. - Soci\u00e9t\u00e9 T\u00f4lerie Industrielle Centre Automatisme M\u00e9canique",
    "wof:placetype":"venue"
},
  "geometry": {"coordinates":[2.14335,45.47224],"type":"Point"}
}