{
  "type": "Feature",
  "properties": {
    "addr:full":"148, Av. Louis Roche, 92230 Gennevilliers Ile de France",
    "addr:postcode":"92230;ile",
    "addr:street":"148 Av. Louis Roche",
    "iso:country":"FR",
    "sg:address":"148, Av. Louis Roche, 92230 Gennevilliers",
    "sg:orig_category":"Unclassifiable Establishments",
    "sg:phone":"+33 1 41 47 34 00",
    "sg:province":"Ile de France",
    "wof:name":"U.t.s. S.a. - Vide Et Traitements Services",
    "wof:placetype":"venue"
},
  "geometry": {"coordinates":[2.310171,48.929344],"type":"Point"}
}