{
  "type": "Feature",
  "properties": {
    "addr:full":"chemin de l'Epinoy Templemars Nord Pas-de-Calais 59175",
    "addr:postcode":"59175",
    "addr:street":"Chemin De L'Epinoy Templemars Nord",
    "iso:country":"FR",
    "sg:address":"chemin de l'Epinoy",
    "sg:city":"Templemars",
    "sg:orig_category":"Non-Classified Establishments",
    "sg:phone":"+33 3 20 16 07 80",
    "sg:postcode":"59175",
    "sg:province":"Nord Pas-de-Calais",
    "wof:name":"I.s.s. France S.a.",
    "wof:placetype":"venue"
},
  "geometry": {"coordinates":[3.068528,50.567921],"type":"Point"}
}