{
  "type": "Feature",
  "properties": {
    "addr:full":"29/31, Rue des Terres au Cur\u00e9, 75013 Paris Ile de France",
    "addr:housenumber":"29 / 31",
    "addr:postcode":"75013",
    "addr:street":"Rue Des Terres Au Cure\u0301",
    "iso:country":"FR",
    "sg:address":"29/31, Rue des Terres au Cur\u00e9, 75013 Paris",
    "sg:orig_category":"Unclassifiable Establishments",
    "sg:phone":"+33 1 53 82 85 90",
    "sg:province":"Ile de France",
    "wof:name":"Gorgy Timing S.a.",
    "wof:placetype":"venue"
},
  "geometry": {"coordinates":[2.371755,48.82468],"type":"Point"}
}