{
  "type": "Feature",
  "properties": {
    "iso:country":"FR",
    "sg:address":"16 Rue Du Manoir 95380 Epiais Les Louvres",
    "sg:classifiers":[
        {
            "category":"Building & Trades",
            "subcategory":"Construction",
            "type":"Services"
        }
    ],
    "sg:phone":"+33 1 34 47 70 00",
    "sg:postcode":"95380",
    "sg:province":"Ile de France",
    "sg:tags":[
        "work",
        "public"
    ],
    "wof:name":"Maurice Bousquet Traveaux Publics",
    "wof:placetype":"venue"
},
  "geometry": {"coordinates":[2.55612,49.031841],"type":"Point"}
}