{
  "type": "Feature",
  "properties": {
    "addr:full":"13 Rue De Prague 75012 Paris Ile de France 75012",
    "addr:housenumber":"13",
    "addr:postcode":"75012;75012",
    "addr:street":"Rue De Prague",
    "iso:country":"FR",
    "sg:address":"13 Rue De Prague 75012 Paris",
    "sg:classifiers":[
        {
            "category":"Professional",
            "subcategory":"Business Services",
            "type":"Services"
        }
    ],
    "sg:phone":"+33 1 43 43 55 03",
    "sg:postcode":"75012",
    "sg:province":"Ile de France",
    "sg:tags":[
        "training",
        "advice"
    ],
    "wof:name":"Institut St Pierre Fourier",
    "wof:placetype":"venue"
},
  "geometry": {"coordinates":[2.375641,48.849777],"type":"Point"}
}