{
  "type": "Feature",
  "properties": {
    "addr:full":"Le Chatelet 01240 Dompierre sur Veyle Rhone-Alpes",
    "addr:postcode":"01240",
    "addr:street":"Le Chatelet",
    "iso:country":"FR",
    "sg:address":"Le Chatelet 01240 Dompierre sur Veyle",
    "sg:orig_category":"Unclassifiable Establishments",
    "sg:phone":"+33 4 74 30 34 67",
    "sg:province":"Rhone-Alpes",
    "wof:name":"Maisson S.a.r.l.",
    "wof:placetype":"venue"
},
  "geometry": {"coordinates":[5.205665,46.074471],"type":"Point"}
}