{
  "type": "Feature",
  "properties": {
    "addr:full":"6/10, Rue de Panical\u00e9, 78320 Le Mesnil Saint Denis Ile de France",
    "addr:housenumber":"6 / 10",
    "addr:postcode":"78320",
    "addr:street":"Rue De Panicale\u0301",
    "iso:country":"FR",
    "sg:address":"6/10, Rue de Panical\u00e9, 78320 Le Mesnil Saint Denis",
    "sg:orig_category":"Unclassifiable Establishments",
    "sg:phone":"+33 1 39 38 28 28",
    "sg:province":"Ile de France",
    "wof:name":"Photobition S.a.r.l.",
    "wof:placetype":"venue"
},
  "geometry": {"coordinates":[1.945881,48.756828],"type":"Point"}
}