{
  "type": "Feature",
  "properties": {
    "addr:full":"70 Rue Pasteur 02200 Belleu Picardie",
    "addr:housenumber":"70",
    "addr:postcode":"02200",
    "addr:street":"Rue Pasteur",
    "iso:country":"FR",
    "sg:address":"70 Rue Pasteur 02200 Belleu",
    "sg:classifiers":[
        {
            "category":"Professional",
            "type":"Services"
        }
    ],
    "sg:phone":"+33 3 23 73 22 16",
    "sg:province":"Picardie",
    "sg:tags":[
        "transport",
        "road"
    ],
    "wof:name":"Houbrexhe Sarl",
    "wof:placetype":"venue"
},
  "geometry": {"coordinates":[3.332438,49.360168],"type":"Point"}
}