{
  "type": "Feature",
  "properties": {
    "addr:full":"240 Rue Gabriel Peri 92700 Colombes Ile de France 92700",
    "addr:housenumber":"240",
    "addr:postcode":"92700;ile;92700",
    "addr:street":"Rue Gabriel Peri;France",
    "iso:country":"FR",
    "sg:address":"240 Rue Gabriel Peri 92700 Colombes",
    "sg:classifiers":[
        {
            "category":"Shopping",
            "subcategory":"Computers & Home Electronics",
            "type":"Retail Goods"
        }
    ],
    "sg:phone":"+33 1 47 86 85 00",
    "sg:postcode":"92700",
    "sg:province":"Ile de France",
    "sg:tags":[
        "electric",
        "electricity",
        "component",
        "equipment",
        "electrical",
        "electronic"
    ],
    "wof:name":"Ome",
    "wof:placetype":"venue"
},
  "geometry": {"coordinates":[2.238592,48.918217],"type":"Point"}
}