{
  "type": "Feature",
  "properties": {
    "iso:country":"FR",
    "sg:address":"9 Avenue Des Prades 15006 Aurillac Cedex",
    "sg:classifiers":[
        {
            "category":"Professional",
            "subcategory":"Printing & Photocopies",
            "type":"Services"
        }
    ],
    "sg:phone":"+33 4 71 63 95 95",
    "sg:province":"Midi Pyr\u00e9n\u00e9es",
    "sg:tags":[
        "publishing"
    ],
    "wof:name":"Soprav",
    "wof:placetype":"venue"
},
  "geometry": {"coordinates":[2.438033,44.917824],"type":"Point"}
}