{
  "type": "Feature",
  "properties": {
    "iso:country":"FR",
    "sg:address":"1 Rue Bernard Palissy Centre Artisanal 59160 Lomme",
    "sg:classifiers":[
        {
            "category":"Wholesale",
            "subcategory":"Medical Equipment & Supplies",
            "type":"Manufacturing & Wholesale Goods"
        }
    ],
    "sg:phone":"+33 3 20 92 11 21",
    "sg:postcode":"59160",
    "sg:province":"Nord Pas-de-Calais",
    "sg:tags":[
        "instrument",
        "health",
        "-",
        "precision"
    ],
    "wof:name":"Laboratoire Jourdain Landat",
    "wof:placetype":"venue"
},
  "geometry": {"coordinates":[2.961047,50.643799],"type":"Point"}
}