{
  "type": "Feature",
  "properties": {
    "addr:full":"68, Rte de Nantes, 44830 Bouaye Pays de Loire",
    "addr:housenumber":"68",
    "addr:postcode":"44830",
    "addr:street":"Rte De Nantes",
    "iso:country":"FR",
    "sg:address":"68, Rte de Nantes, 44830 Bouaye",
    "sg:orig_category":"Unclassifiable Establishments",
    "sg:phone":"+33 2 40 65 47 78",
    "sg:province":"Pays de Loire",
    "wof:name":"Clos Des Epinettes E.a.r.l.",
    "wof:placetype":"venue"
},
  "geometry": {"coordinates":[-1.687623,47.144264],"type":"Point"}
}