{
  "type": "Feature",
  "properties": {
    "addr:full":"17, Promenade des Bertholet, 08000 Warcq Charleville-M\u00e9zi\u00e8res Champagne 08000",
    "addr:housenumber":"17",
    "addr:postcode":"08000;08000",
    "addr:street":"Promenade Des Bertholet",
    "iso:country":"FR",
    "sg:address":"17, Promenade des Bertholet, 08000 Warcq",
    "sg:city":"Charleville-M\u00e9zi\u00e8res",
    "sg:orig_category":"Non-Classified Establishments",
    "sg:phone":"+33 3 24 32 55 34",
    "sg:postcode":"08000",
    "sg:province":"Champagne",
    "wof:name":"Climatec S.a.r.l.",
    "wof:placetype":"venue"
},
  "geometry": {"coordinates":[4.69123,49.777538],"type":"Point"}
}