{
  "type": "Feature",
  "properties": {
    "iso:country":"FR",
    "sg:address":"12 rue Frederic Thomas; Castres; 81100",
    "sg:classifiers":[
        {
            "category":"Banks & Credit Unions",
            "subcategory":"Bank",
            "type":"Services"
        }
    ],
    "sg:phone":"+33 3363596130",
    "sg:postcode":"81100",
    "sg:province":"Midi Pyr\u00e9n\u00e9es",
    "wof:name":"Soci\u00e9t\u00e9 G\u00e9n\u00e9rale",
    "wof:placetype":"venue"
},
  "geometry": {"coordinates":[2.240179,43.606487],"type":"Point"}
}