{
  "type": "Feature",
  "properties": {
    "addr:full":"B.P. 50037, 49180 Saint Barth\u00e9l\u00e9my d'Anjou C\u00e9dex^^Rue de Champfleur - ZI, 49000 Angers Pays de Loire",
    "addr:housenumber":"49180",
    "addr:postcode":"49000",
    "addr:street":"Saint Barthe\u0301Le\u0301My D'Anjou;Zi",
    "iso:country":"FR",
    "sg:address":"B.P. 50037, 49180 Saint Barth\u00e9l\u00e9my d'Anjou C\u00e9dex^^Rue de Champfleur - ZI, 49000 Angers",
    "sg:orig_category":"Non-Classified Establishments",
    "sg:phone":"+33 2 41 18 82 82",
    "sg:province":"Pays de Loire",
    "wof:name":"M.r.s. S.a. - Maison Rose Signature",
    "wof:placetype":"venue"
},
  "geometry": {"coordinates":[-0.570877,47.450382],"type":"Point"}
}