{
  "type": "Feature",
  "properties": {
    "iso:country":"FR",
    "sg:address":"chemin du Pr\u00e9 Moliet 01120 La Boisse",
    "sg:classifiers":[
        {
            "category":"Professional",
            "subcategory":"Engineering",
            "type":"Services"
        }
    ],
    "sg:phone":"+33 4 72 25 92 18",
    "sg:postcode":"01120",
    "sg:province":"Rhone-Alpes",
    "sg:tags":[
        "technique",
        "measurement"
    ],
    "wof:name":"Mse S.a.",
    "wof:placetype":"venue"
},
  "geometry": {"coordinates":[5.038362,45.836185],"type":"Point"}
}