{
  "type": "Feature",
  "properties": {
    "iso:country":"FR",
    "sg:address":"44, Rue Jeanne d'Arc, 69003 Lyon",
    "sg:orig_category":"Non-Classified Establishments",
    "sg:phone":"+33 4 72 33 59 59",
    "sg:province":"Rhone-Alpes",
    "wof:name":"Rh\u00f4ne Mat\u00e9riaux S.a.",
    "wof:placetype":"venue"
},
  "geometry": {"coordinates":[4.879343,45.751469],"type":"Point"}
}