{
  "type": "Feature",
  "properties": {
    "iso:country":"FR",
    "sg:address":"ZI du Fournalet",
    "sg:city":"Sorgues",
    "sg:orig_category":"Unclassifiable Establishments",
    "sg:phone":"+33 4 90 39 44 79",
    "sg:postcode":"84700",
    "sg:province":"Rhone-Alpes",
    "wof:name":"Cermix",
    "wof:placetype":"venue"
},
  "geometry": {"coordinates":[4.873481,44.00827],"type":"Point"}
}