{
  "type": "Feature",
  "properties": {
    "iso:country":"FR",
    "sg:address":"24, Rue Pierre Corneille, 76300 Sotteville Les Rouen",
    "sg:orig_category":"Unclassifiable Establishments",
    "sg:phone":"+33 2 35 72 35 67",
    "sg:province":"Haute Normandie",
    "wof:name":"Soval S.a.",
    "wof:placetype":"venue"
},
  "geometry": {"coordinates":[1.09055,49.422703],"type":"Point"}
}