{
  "type": "Feature",
  "properties": {
    "addr:full":"Domaine de Lagune 33340 Saint Germain d'Esteuil B\u00e9gadan Aquitaine 33340",
    "addr:housenumber":"be\u0301gadan",
    "addr:postcode":"33340;33340",
    "iso:country":"FR",
    "sg:address":"Domaine de Lagune 33340 Saint Germain d'Esteuil",
    "sg:city":"B\u00e9gadan",
    "sg:orig_category":"Non-Classified Establishments",
    "sg:phone":"+33 5 56 73 05 05",
    "sg:postcode":"33340",
    "sg:province":"Aquitaine",
    "wof:name":"Philippe Gerbaud S.a.",
    "wof:placetype":"venue"
},
  "geometry": {"coordinates":[-0.90348,45.25589],"type":"Point"}
}