{
  "type": "Feature",
  "properties": {
    "addr:full":"3, Rue Michel Marion, 29000 Quimper Quimper Bretagne 29000",
    "addr:housenumber":"3",
    "addr:postcode":"29000;29000",
    "addr:street":"Rue Michel Marion",
    "iso:country":"FR",
    "sg:address":"3, Rue Michel Marion, 29000 Quimper",
    "sg:city":"Quimper",
    "sg:orig_category":"Unclassifiable Establishments",
    "sg:phone":"+33 2 98 55 20 38",
    "sg:postcode":"29000",
    "sg:province":"Bretagne",
    "wof:name":"Le Bihan Vitraux S.a.r.l.",
    "wof:placetype":"venue"
},
  "geometry": {"coordinates":[-4.117326,47.986462],"type":"Point"}
}