{
  "type": "Feature",
  "properties": {
    "addr:full":"142, Rue de la Perrodi\u00e8re, 73230 Saint Alban Leysse Rhone-Alpes 73230",
    "addr:housenumber":"142",
    "addr:postcode":"73230;73230",
    "addr:street":"Rue De La Perrodie\u0300Re;Rhone-Alpes",
    "iso:country":"FR",
    "sg:address":"142, Rue de la Perrodi\u00e8re, 73230 Saint Alban Leysse",
    "sg:orig_category":"Unclassifiable Establishments",
    "sg:phone":"+33 4 79 85 24 33",
    "sg:postcode":"73230",
    "sg:province":"Rhone-Alpes",
    "wof:name":"Packing Dispatch S.a.",
    "wof:placetype":"venue"
},
  "geometry": {"coordinates":[5.957609,45.576996],"type":"Point"}
}