{
  "type": "Feature",
  "properties": {
    "addr:full":"899 Boulevard Du Boucanet Immeuble Le Priska Le Grau Du Roi Languedoc-Roussillon 30240",
    "addr:housenumber":"899;immeuble",
    "addr:postcode":"30240",
    "addr:street":"Boulevard Du Boucanet",
    "iso:country":"FR",
    "sg:address":"899 Boulevard Du Boucanet Immeuble Le Priska",
    "sg:city":"Le Grau Du Roi",
    "sg:classifiers":[
        {
            "category":"Banks & Credit Unions",
            "subcategory":"Financial Services",
            "type":"Services"
        }
    ],
    "sg:phone":"+33 4 66 53 10 02",
    "sg:postcode":"30240",
    "sg:province":"Languedoc-Roussillon",
    "sg:tags":[
        "banking",
        "finance",
        "insurance"
    ],
    "wof:name":"Societe Fiduciaire Nationale D'expertise Comptable Fidexpert (fid)",
    "wof:placetype":"venue"
},
  "geometry": {"coordinates":[4.138094,43.534302],"type":"Point"}
}