{
  "type": "Feature",
  "properties": {
    "iso:country":"FR",
    "sg:address":"B.P. 10, 08010 Charleville M\u00e9zi\u00e8res C\u00e9dex^^2, Promenade des Remparts, 08000 Warcq",
    "sg:city":"Charleville-M\u00e9zi\u00e8res",
    "sg:orig_category":"Non-Classified Establishments",
    "sg:phone":"+33 3 24 33 10 29",
    "sg:postcode":"08000",
    "sg:province":"Champagne",
    "wof:name":"Del Giglio S.a.",
    "wof:placetype":"venue"
},
  "geometry": {"coordinates":[4.7174,49.758801],"type":"Point"}
}