{
  "type": "Feature",
  "properties": {
    "addr:full":"13 rue Raymond Teiss\u00e8re 13008 Marseille Poitou-Charentes",
    "addr:housenumber":"13",
    "addr:postcode":"13008",
    "addr:street":"Rue Raymond Teisse\u0300Re",
    "iso:country":"FR",
    "sg:address":"13 rue Raymond Teiss\u00e8re 13008 Marseille",
    "sg:classifiers":[
        {
            "category":"Home & Garden",
            "subcategory":"Household Appliances",
            "type":"Retail Goods"
        }
    ],
    "sg:phone":"+33 4 91 80 90 21",
    "sg:province":"Poitou-Charentes",
    "sg:tags":[
        "heater",
        "industrial",
        "electric",
        "us"
    ],
    "wof:name":"Pillard (egci) S.a.",
    "wof:placetype":"venue"
},
  "geometry": {"coordinates":[5.397038,43.27483],"type":"Point"}
}