{
  "type": "Feature",
  "properties": {
    "iso:country":"FR",
    "sg:address":"30 Route De Orschwiller 67602 S\u00e9lestat Cedex",
    "sg:city":"Orschwiller",
    "sg:classifiers":[
        {
            "category":"Transit Center",
            "subcategory":"Freight",
            "type":"Transportation"
        }
    ],
    "sg:phone":"+33 3 88 92 10 47",
    "sg:postcode":"67600",
    "sg:province":"Alsace",
    "sg:tags":[
        "metallurgy",
        "pipe",
        "metalworking",
        "sheet"
    ],
    "wof:name":"Quincaillerie Centrale Dreyfus Sa",
    "wof:placetype":"venue"
},
  "geometry": {"coordinates":[7.430771,48.254963],"type":"Point"}
}