{
  "type": "Feature",
  "properties": {
    "addr:full":"Rte De Beaudinard Lot Clos Fleuri 13400 Aubagne Bretagne",
    "addr:postcode":"13400",
    "addr:street":"Rte De Beaudinard Lot Clos Fleuri",
    "iso:country":"FR",
    "sg:address":"Rte De Beaudinard Lot Clos Fleuri 13400 Aubagne",
    "sg:classifiers":[
        {
            "category":"Professional",
            "subcategory":"Computer Services",
            "type":"Services"
        }
    ],
    "sg:phone":"+33 4 42 84 55 80",
    "sg:province":"Bretagne",
    "sg:tags":[
        "information",
        "technology",
        "software"
    ],
    "wof:name":"Sem Sigec Inform Gestion Commu",
    "wof:placetype":"venue"
},
  "geometry": {"coordinates":[5.5687,43.292141],"type":"Point"}
}