{
  "type": "Feature",
  "properties": {
    "addr:full":"B.P. 55, 50800 Villedieu les Po\u00eales^^30, Av. Armand Ligot, 50800 Sainte C\u00e9cile Boisyvon Basse Normandie 50800",
    "addr:postcode":"50800;50800",
    "addr:street":"B.P. 55;Av. Armand Ligot;Basse",
    "iso:country":"FR",
    "sg:address":"B.P. 55, 50800 Villedieu les Po\u00eales^^30, Av. Armand Ligot, 50800 Sainte C\u00e9cile",
    "sg:city":"Boisyvon",
    "sg:orig_category":"Non-Classified Establishments",
    "sg:phone":"+33 2 33 91 41 50",
    "sg:postcode":"50800",
    "sg:province":"Basse Normandie",
    "wof:name":"A.i.m. S.a. - Abattoirs Industriels De La Manche",
    "wof:placetype":"venue"
},
  "geometry": {"coordinates":[-1.178043,48.785904],"type":"Point"}
}