{
  "type": "Feature",
  "properties": {
    "iso:country":"FR",
    "sg:address":"37, Bd Rougier - Immeuble le Mercure, 13004 Marseille",
    "sg:orig_category":"Non-Classified Establishments",
    "sg:phone":"+33 4 91 86 40 46",
    "sg:province":"Provence-Alpes-C\u00f4te d'Azur",
    "wof:name":"Sophel S.a.r.l. - Soci\u00e9t\u00e9 Phoc\u00e9enne D'electronique",
    "wof:placetype":"venue"
},
  "geometry": {"coordinates":[5.40161,43.30444],"type":"Point"}
}