{
  "type": "Feature",
  "properties": {
    "iso:country":"FR",
    "sg:address":"Rte d'Irigny - ZI Nord",
    "sg:city":"Brignais",
    "sg:orig_category":"Unclassifiable Establishments",
    "sg:phone":"+33 4 78 05 54 54",
    "sg:postcode":"69530",
    "sg:province":"Rhone-Alpes",
    "wof:name":"La Vivration Industrielle S.a.",
    "wof:placetype":"venue"
},
  "geometry": {"coordinates":[4.75394,45.67403],"type":"Point"}
}