{
  "type": "Feature",
  "properties": {
    "iso:country":"FR",
    "sg:address":"199-200 Bd National 13003 Marseille",
    "sg:classifiers":[
        {
            "category":"Autos & Motor Vehicles",
            "subcategory":"Automobile Sales",
            "type":"Retail Goods"
        }
    ],
    "sg:phone":"+33 4 91 08 01 08",
    "sg:province":"Poitou-Charentes",
    "sg:tags":[
        "equipment",
        "motor-cars",
        "transport"
    ],
    "wof:name":"Reparations Auto Lautard Sa",
    "wof:placetype":"venue"
},
  "geometry": {"coordinates":[5.379691,43.309479],"type":"Point"}
}