{
  "type": "Feature",
  "properties": {
    "addr:full":"5, Rue des Closeaux, 78200 Buchelay Ile de France",
    "addr:housenumber":"5",
    "addr:postcode":"78200",
    "addr:street":"Rue Des Closeaux;Ile De France",
    "iso:country":"FR",
    "sg:address":"5, Rue des Closeaux, 78200 Buchelay",
    "sg:orig_category":"Non-Classified Establishments",
    "sg:phone":"+33 1 30 33 05 93",
    "sg:province":"Ile de France",
    "wof:name":"T.v.m. S.a. - Transports Voyageurs Du Mantois",
    "wof:placetype":"venue"
},
  "geometry": {"coordinates":[1.679721,48.993046],"type":"Point"}
}