{
  "type": "Feature",
  "properties": {
    "iso:country":"FR",
    "sg:address":"B.P. 6, 43620 Saint Pal de Mons C\u00e9dex^^ZI de Campine, 43620 Saint Pal de Mons",
    "sg:city":"Saint-Romain-Lachalm",
    "sg:orig_category":"Non-Classified Establishments",
    "sg:phone":"+33 4 71 75 63 00",
    "sg:postcode":"43620",
    "sg:province":"Auvergne",
    "wof:name":"S.t.e.p. S.a. - Soci\u00e9t\u00e9 Transformation D'emballages Plastiques",
    "wof:placetype":"venue"
},
  "geometry": {"coordinates":[4.344406,45.219765],"type":"Point"}
}