{
  "type": "Feature",
  "properties": {
    "addr:full":"Rue Thomas Edison 87220 Feytiat Limousin 87220",
    "addr:postcode":"87220;87220",
    "addr:street":"Rue Thomas Edison",
    "iso:country":"FR",
    "sg:address":"Rue Thomas Edison 87220 Feytiat",
    "sg:classifiers":[
        {
            "category":"Home & Garden",
            "subcategory":"Furniture",
            "type":"Retail Goods"
        }
    ],
    "sg:phone":"+33 5 55 31 34 74",
    "sg:postcode":"87220",
    "sg:province":"Limousin",
    "sg:tags":[
        "household",
        "wood"
    ],
    "wof:name":"Atelier D'art De Limoges",
    "wof:placetype":"venue"
},
  "geometry": {"coordinates":[1.30506,45.818947],"type":"Point"}
}