{
  "type": "Feature",
  "properties": {
    "addr:full":"Rue Malgras - ZI des Trois Fontaines Saint Dizier Champagne 52100",
    "addr:postcode":"52100",
    "addr:street":"Rue Malgras Zi Des Trois Fontaines Saint;Champagne",
    "iso:country":"FR",
    "sg:address":"Rue Malgras - ZI des Trois Fontaines",
    "sg:city":"Saint Dizier",
    "sg:orig_category":"Non-Classified Establishments",
    "sg:phone":"+33 3 25 07 33 70",
    "sg:postcode":"52100",
    "sg:province":"Champagne",
    "wof:name":"Prevot Smeta S.a.",
    "wof:placetype":"venue"
},
  "geometry": {"coordinates":[4.934152,48.647793],"type":"Point"}
}