{
  "type": "Feature",
  "properties": {
    "addr:full":"240/241, March\u00e9 de Saumaty, 13016 Marseille Poitou-Charentes",
    "addr:housenumber":"240 / 241",
    "addr:postcode":"13016",
    "addr:street":"Marche\u0301 De Saumaty",
    "iso:country":"FR",
    "sg:address":"240/241, March\u00e9 de Saumaty, 13016 Marseille",
    "sg:orig_category":"Non-Classified Establishments",
    "sg:phone":"+33 4 91 46 26 47",
    "sg:province":"Poitou-Charentes",
    "wof:name":"Sudfish S.a.r.l.",
    "wof:placetype":"venue"
},
  "geometry": {"coordinates":[5.321475,43.362785],"type":"Point"}
}