{
  "type": "Feature",
  "properties": {
    "addr:full":"4, Chemin de Chaumasson, 89140 Villethierry Villethierry Bourgogne 89140",
    "addr:housenumber":"4",
    "addr:postcode":"89140;89140",
    "addr:street":"Chemin De Chaumasson",
    "iso:country":"FR",
    "sg:address":"4, Chemin de Chaumasson, 89140 Villethierry",
    "sg:city":"Villethierry",
    "sg:orig_category":"Non-Classified Establishments",
    "sg:phone":"+33 3 86 66 50 33",
    "sg:postcode":"89140",
    "sg:province":"Bourgogne",
    "wof:name":"Delvall\u00e9e S.a.",
    "wof:placetype":"venue"
},
  "geometry": {"coordinates":[3.08459,48.280094],"type":"Point"}
}