{
  "type": "Feature",
  "properties": {
    "iso:country":"FR",
    "sg:address":"21/23, Rue Courteline, 78500 Sartrouville",
    "sg:orig_category":"Unclassifiable Establishments",
    "sg:phone":"+33 1 39 13 63 64",
    "sg:province":"Ile de France",
    "wof:name":"S.f.m.s. S.a.r.l. - Soci\u00e9t\u00e9 Fabrication M\u00e9canique Sartrouvilloise",
    "wof:placetype":"venue"
},
  "geometry": {"coordinates":[2.178084,48.939362],"type":"Point"}
}