{
  "type": "Feature",
  "properties": {
    "iso:country":"FR",
    "sg:address":"ZAC de la Marquette",
    "sg:city":"Sorgues",
    "sg:orig_category":"Non-Classified Establishments",
    "sg:phone":"+33 4 90 83 20 10",
    "sg:postcode":"84700",
    "sg:province":"Midi Pyr\u00e9n\u00e9es",
    "wof:name":"Sicatel S.a.r.l.",
    "wof:placetype":"venue"
},
  "geometry": {"coordinates":[4.873481,44.00827],"type":"Point"}
}