{
  "type": "Feature",
  "properties": {
    "addr:full":"1, Rue des Fr\u00e8res Chausson - ., 92600 Asni\u00e8res sur Seine Ile de France",
    "addr:housenumber":"1",
    "addr:postcode":"92600",
    "addr:street":"Rue Des Fre\u0300Res Chausson",
    "iso:country":"FR",
    "sg:address":"1, Rue des Fr\u00e8res Chausson - ., 92600 Asni\u00e8res sur Seine",
    "sg:orig_category":"Unclassifiable Establishments",
    "sg:phone":"+33 1 47 93 06 36",
    "sg:province":"Ile de France",
    "wof:name":"C.e.r.a. S.a. - Compagnie Europ\u00e9enne De R\u00e9alisations Antiparasitaires",
    "wof:placetype":"venue"
},
  "geometry": {"coordinates":[2.286499,48.91526],"type":"Point"}
}