{
  "type": "Feature",
  "properties": {
    "addr:full":"Rue Nic\u00e9phore Niepce Zi Aupretin 71500 Louhans Louhans Bourgogne 71500",
    "addr:postcode":"71500;71500",
    "addr:street":"Rue Nice\u0301Phore Niepce Zi Aupretin",
    "iso:country":"FR",
    "sg:address":"Rue Nic\u00e9phore Niepce Zi Aupretin 71500 Louhans",
    "sg:city":"Louhans",
    "sg:classifiers":[
        {
            "category":"Food & Beverages",
            "subcategory":"Groceries & Convenience Stores",
            "type":"Retail Goods"
        }
    ],
    "sg:phone":"+33 3 85 75 71 50",
    "sg:postcode":"71500",
    "sg:province":"Bourgogne",
    "sg:tags":[
        "product",
        "related"
    ],
    "wof:name":"Ste Comtoise De Specialites Fromageres Sa",
    "wof:placetype":"venue"
},
  "geometry": {"coordinates":[5.190305,46.591961],"type":"Point"}
}