{
  "type": "Feature",
  "properties": {
    "addr:full":"26 Av Franklin Roosevelt 75002 Paris Ile de France 75002",
    "addr:postcode":"75002;75002",
    "addr:street":"26 Av Franklin Roosevelt",
    "iso:country":"FR",
    "sg:address":"26 Av Franklin Roosevelt 75002 Paris",
    "sg:classifiers":[
        {
            "category":"Banks & Credit Unions",
            "subcategory":"Financial Services",
            "type":"Services"
        }
    ],
    "sg:phone":"+33 1 42 66 81 00",
    "sg:postcode":"75002",
    "sg:province":"Ile de France",
    "sg:tags":[
        "banking",
        "insurance",
        "institution",
        "finance"
    ],
    "wof:name":"Europeen Intermediat Financier Boursiere",
    "wof:placetype":"venue"
},
  "geometry": {"coordinates":[2.34069,48.866241],"type":"Point"}
}