{
  "type": "Feature",
  "properties": {
    "addr:full":"159, Rue Georges Mangin - Zone Portuaire, 69400 Villefranche sur Sa\u00f4ne Rhone-Alpes 69400",
    "addr:housenumber":"159",
    "addr:postcode":"69400;69400",
    "addr:street":"Rue Georges Mangin;Portuaire;Rhone-Alpes",
    "iso:country":"FR",
    "sg:address":"159, Rue Georges Mangin - Zone Portuaire, 69400 Villefranche sur Sa\u00f4ne",
    "sg:orig_category":"Unclassifiable Establishments",
    "sg:phone":"+33 4 74 65 36 39",
    "sg:postcode":"69400",
    "sg:province":"Rhone-Alpes",
    "wof:name":"Tremblay S.a.",
    "wof:placetype":"venue"
},
  "geometry": {"coordinates":[4.738612,45.989773],"type":"Point"}
}