{
  "type": "Feature",
  "properties": {
    "addr:full":"105 Paul Foucaut 59450 Sin le Noble Nord Pas-de-Calais",
    "addr:housenumber":"105",
    "addr:postcode":"59450",
    "addr:street":"Paul Foucaut;Sin Le Noble Nord",
    "iso:country":"FR",
    "sg:address":"105",
    "sg:city":"Paul Foucaut 59450 Sin le Noble",
    "sg:classifiers":[
        {
            "category":"Banks & Credit Unions",
            "subcategory":"Investment Brokerage",
            "type":"Services"
        }
    ],
    "sg:phone":"+33 3 27 71 70 70",
    "sg:province":"Nord Pas-de-Calais",
    "sg:tags":[
        "-",
        "transport",
        "related"
    ],
    "wof:name":"Sdm",
    "wof:placetype":"venue"
},
  "geometry": {"coordinates":[3.107995,50.349403],"type":"Point"}
}