{
  "type": "Feature",
  "properties": {
    "addr:full":"78, Rue Fr\u00e9d\u00e9ric Fays, 69100 Villeurbanne Rhone-Alpes",
    "addr:housenumber":"78",
    "addr:postcode":"69100",
    "addr:street":"Rue Fre\u0301De\u0301Ric Fays",
    "iso:country":"FR",
    "sg:address":"78, Rue Fr\u00e9d\u00e9ric Fays, 69100 Villeurbanne",
    "sg:orig_category":"Non-Classified Establishments",
    "sg:phone":"+33 4 72 34 80 80",
    "sg:province":"Rhone-Alpes",
    "wof:name":"J. Charrin S.a.r.l.",
    "wof:placetype":"venue"
},
  "geometry": {"coordinates":[4.905812,45.759926],"type":"Point"}
}