{
  "type": "Feature",
  "properties": {
    "iso:country":"FR",
    "sg:address":"Rue Haluch\u00e8re; Nantes",
    "sg:classifiers":[
        {
            "category":"Banks & Credit Unions",
            "subcategory":"Bank",
            "type":"Services"
        }
    ],
    "sg:phone":"+33 3340930707",
    "sg:province":"Midi Pyr\u00e9n\u00e9es",
    "wof:name":"Banque Populaire Bretagne, Atlantique",
    "wof:placetype":"venue"
},
  "geometry": {"coordinates":[-1.515868,47.247547],"type":"Point"}
}