{
  "type": "Feature",
  "properties": {
    "addr:full":"B.P. 760, 24107 Bergerac C\u00e9dex^^19, Rue Sainte Catherine, 24100 Bergerac Bergerac Aquitaine 24100",
    "addr:housenumber":"b.p. 760",
    "addr:postcode":"24107;24100;24100",
    "addr:street":"Rue Sainte Catherine",
    "iso:country":"FR",
    "sg:address":"B.P. 760, 24107 Bergerac C\u00e9dex^^19, Rue Sainte Catherine, 24100 Bergerac",
    "sg:city":"Bergerac",
    "sg:orig_category":"Non-Classified Establishments",
    "sg:phone":"+33 5 53 63 70 00",
    "sg:postcode":"24100",
    "sg:province":"Aquitaine",
    "wof:name":"B.p.c. - Banque Populaire Du Centre",
    "wof:placetype":"venue"
},
  "geometry": {"coordinates":[0.45362,44.815235],"type":"Point"}
}