{
  "type": "Feature",
  "properties": {
    "iso:country":"FR",
    "sg:address":"80, Chemin Saint Martin - Parc d'Activit\u00e9s de la Plaine de Jouques, 13420 G\u00e9menos",
    "sg:city":"Plaine",
    "sg:orig_category":"Non-Classified Establishments",
    "sg:phone":"+33 4 42 32 13 42",
    "sg:postcode":"67420",
    "sg:province":"Alsace",
    "wof:name":"Cop\u00e9rior France S.a.",
    "wof:placetype":"venue"
},
  "geometry": {"coordinates":[5.610561,43.283669],"type":"Point"}
}