{
  "type": "Feature",
  "properties": {
    "iso:country":"FR",
    "sg:address":"17, Av. Jean Jaur\u00e8s, 10150 Pont Sainte Marie",
    "sg:orig_category":"Unclassifiable Establishments",
    "sg:phone":"+33 3 25 83 21 31",
    "sg:province":"Champagne",
    "wof:name":"Apave Parisienne",
    "wof:placetype":"venue"
},
  "geometry": {"coordinates":[4.097797,48.316326],"type":"Point"}
}