{
  "type": "Feature",
  "properties": {
    "addr:full":"28 Ch\u00e2teau 33460 Lamarque Lamarque Aquitaine 33460",
    "addr:housenumber":"28",
    "addr:postcode":"33460;33460",
    "addr:street":"Cha\u0302Teau",
    "iso:country":"FR",
    "sg:address":"28 Ch\u00e2teau 33460 Lamarque",
    "sg:city":"Lamarque",
    "sg:classifiers":[
        {
            "category":"Food Court",
            "type":"Food & Drink"
        }
    ],
    "sg:phone":"+33 5 56 58 90 03",
    "sg:postcode":"33460",
    "sg:province":"Aquitaine",
    "sg:tags":[
        "product",
        "related"
    ],
    "wof:name":"Gromand Devry",
    "wof:placetype":"venue"
},
  "geometry": {"coordinates":[-0.712874,44.964851],"type":"Point"}
}