{
  "type": "Feature",
  "properties": {
    "iso:country":"FR",
    "sg:address":"5, Av. du Pr\u00e9 F\u00e9lin, 74940 Annecy le Vieux",
    "sg:orig_category":"Non-Classified Establishments",
    "sg:phone":"+33 4 50 09 48 50",
    "sg:postcode":"74940",
    "sg:province":"Rhone-Alpes",
    "wof:name":"A.m.s. Entreprises S.a.r.l.",
    "wof:placetype":"venue"
},
  "geometry": {"coordinates":[6.166944,45.926914],"type":"Point"}
}