{
  "type": "Feature",
  "properties": {
    "addr:full":"41, Rue du G\u00e9n\u00e9ral Patton, 54410 Laneuveville devant Nancy Lorraine",
    "addr:housenumber":"41",
    "addr:postcode":"54410",
    "addr:street":"Rue Du Ge\u0301Ne\u0301Ral Patton",
    "iso:country":"FR",
    "sg:address":"41, Rue du G\u00e9n\u00e9ral Patton, 54410 Laneuveville devant Nancy",
    "sg:orig_category":"Unclassifiable Establishments",
    "sg:phone":"+33 3 83 51 01 78",
    "sg:province":"Lorraine",
    "wof:name":"Breton Et Compagnie S.a.",
    "wof:placetype":"venue"
},
  "geometry": {"coordinates":[6.231938,48.655853],"type":"Point"}
}