{
  "type": "Feature",
  "properties": {
    "addr:full":"3 rue de la Mairie; Billere; 64140 Bill\u00e8re Aquitaine 64140",
    "addr:housenumber":"3",
    "addr:postcode":"64140;64140",
    "addr:street":"Rue De La Mairie Billere",
    "iso:country":"FR",
    "sg:address":"3 rue de la Mairie; Billere; 64140",
    "sg:city":"Bill\u00e8re",
    "sg:classifiers":[
        {
            "category":"Banks & Credit Unions",
            "subcategory":"Bank",
            "type":"Services"
        }
    ],
    "sg:phone":"+33 3359324545",
    "sg:postcode":"64140",
    "sg:province":"Aquitaine",
    "wof:name":"Banque Nationale De Paris",
    "wof:placetype":"venue"
},
  "geometry": {"coordinates":[-0.395134,43.303158],"type":"Point"}
}