{
  "type": "Feature",
  "properties": {
    "iso:country":"FR",
    "sg:address":"5, Rue Georges Citerne, 75015 Paris",
    "sg:orig_category":"Unclassifiable Establishments",
    "sg:phone":"+33 1 53 95 26 26",
    "sg:province":"Ile de France",
    "wof:name":"Paris Seine",
    "wof:placetype":"venue"
},
  "geometry": {"coordinates":[2.289298,48.849022],"type":"Point"}
}