{
  "type": "Feature",
  "properties": {
    "iso:country":"FR",
    "sg:address":"1 Place Des Marseillais 94220 Charenton Le Pont",
    "sg:classifiers":[
        {
            "category":"Professional",
            "subcategory":"Computer Services",
            "type":"Services"
        }
    ],
    "sg:phone":"+33 1 49 77 57 00",
    "sg:postcode":"94220",
    "sg:province":"Ile de France",
    "sg:tags":[
        "information",
        "technology",
        "software"
    ],
    "wof:name":"Elsop",
    "wof:placetype":"venue"
},
  "geometry": {"coordinates":[2.405709,48.826454],"type":"Point"}
}