{
  "type": "Feature",
  "properties": {
    "addr:full":"4, Rue Philippe Lebon, 37300 Joue les Tours Jou\u00e9-l\u00e8s-Tours Centre 37300",
    "addr:housenumber":"4",
    "addr:postcode":"37300;37300",
    "addr:street":"Rue Philippe Lebon",
    "iso:country":"FR",
    "sg:address":"4, Rue Philippe Lebon, 37300 Joue les Tours",
    "sg:city":"Jou\u00e9-l\u00e8s-Tours",
    "sg:orig_category":"Non-Classified Establishments",
    "sg:phone":"+33 2 47 67 69 69",
    "sg:postcode":"37300",
    "sg:province":"Centre",
    "wof:name":"M.i.s Poitouraine S.a.r.l.",
    "wof:placetype":"venue"
},
  "geometry": {"coordinates":[0.640022,47.344337],"type":"Point"}
}