{
  "type": "Feature",
  "properties": {
    "addr:full":"1, Av. de Fuveau, 13013 Marseille Poitou-Charentes",
    "addr:postcode":"13013",
    "addr:street":"Av. De Fuveau",
    "iso:country":"FR",
    "sg:address":"1, Av. de Fuveau, 13013 Marseille",
    "sg:orig_category":"Non-Classified Establishments",
    "sg:phone":"+33 4 91 06 00 04",
    "sg:province":"Poitou-Charentes",
    "wof:name":"Delta Sertec S.a.",
    "wof:placetype":"venue"
},
  "geometry": {"coordinates":[5.42202,43.327709],"type":"Point"}
}