{
  "type": "Feature",
  "properties": {
    "addr:full":"77550 Moissy Cramayel Ile de France 77550",
    "addr:postcode":"77550;77550",
    "iso:country":"FR",
    "sg:address":"77550 Moissy Cramayel",
    "sg:orig_category":"Non-Classified Establishments",
    "sg:phone":"+33 1 64 14 27 30",
    "sg:postcode":"77550",
    "sg:province":"Ile de France",
    "wof:name":"A\u00e9rodrome De Melun Villaroche",
    "wof:placetype":"venue"
},
  "geometry": {"coordinates":[2.64179,48.618641],"type":"Point"}
}