{
  "type": "Feature",
  "properties": {
    "iso:country":"FR",
    "sg:address":"Rte De Paris Ccal Auchan 80480 Amiens",
    "sg:classifiers":[
        {
            "category":"Travel",
            "subcategory":"Hotels & Motels",
            "type":"Entertainment"
        }
    ],
    "sg:phone":"+33 3 22 33 25 50",
    "sg:postcode":"80480",
    "sg:province":"Picardie",
    "sg:tags":[
        "hotels",
        "business",
        "restaurant"
    ],
    "wof:name":"Flunch",
    "wof:placetype":"venue"
},
  "geometry": {"coordinates":[2.243165,49.870926],"type":"Point"}
}