{
  "type": "Feature",
  "properties": {
    "addr:full":"B.P. 40, 13367 Marseille C\u00e9dex 11^^25, Av. du Docteur Heckel, 13011 Marseille Poitou-Charentes",
    "addr:housenumber":"11 ^ ^ 25",
    "addr:postcode":"13367;13011",
    "addr:street":"B.P. 40;Ce\u0301Dex;Av. Du Docteur Heckel",
    "iso:country":"FR",
    "sg:address":"B.P. 40, 13367 Marseille C\u00e9dex 11^^25, Av. du Docteur Heckel, 13011 Marseille",
    "sg:orig_category":"Non-Classified Establishments",
    "sg:phone":"+33 4 91 45 45 45",
    "sg:province":"Poitou-Charentes",
    "wof:name":"Les Desserts Gavroche S.a.s.",
    "wof:placetype":"venue"
},
  "geometry": {"coordinates":[5.437165,43.289322],"type":"Point"}
}