{
  "type": "Feature",
  "properties": {
    "addr:full":"88 Av Ambroise Croizat 38400 St Martin D'Her\u00e8s Rhone-Alpes 38400",
    "addr:postcode":"38400;38400",
    "addr:street":"88 Av Ambroise Croizat;Rhone-Alpes",
    "iso:country":"FR",
    "sg:address":"88 Av Ambroise Croizat 38400 St Martin D'Her\u00e8s",
    "sg:classifiers":[
        {
            "category":"Building & Trades",
            "subcategory":"Construction",
            "type":"Services"
        }
    ],
    "sg:phone":"+33 4 76 54 09 45",
    "sg:postcode":"38400",
    "sg:province":"Rhone-Alpes",
    "sg:tags":[
        "work",
        "public"
    ],
    "wof:name":"Entreprise Generale Leon Grosse Eglg",
    "wof:placetype":"venue"
},
  "geometry": {"coordinates":[5.750627,45.184731],"type":"Point"}
}