{
  "type": "Feature",
  "properties": {
    "iso:country":"FR",
    "sg:address":"B.P. 113, 33704 M\u00e9rignac C\u00e9dex^^Av. Jean Perrin - Parc Industriel Naulin, 33700 M\u00e9rignac",
    "sg:city":"M\u00e9rignac",
    "sg:orig_category":"Non-Classified Establishments",
    "sg:phone":"+33 5 56 34 84 86",
    "sg:postcode":"33700",
    "sg:province":"Aquitaine",
    "wof:name":"P.a.t. S.a. - Paris Aquitaine Transports",
    "wof:placetype":"venue"
},
  "geometry": {"coordinates":[-0.64762,44.841808],"type":"Point"}
}