{
  "type": "Feature",
  "properties": {
    "addr:full":"Chem Du Vallon Des Vaux 06610 La Gaude Nord Pas-de-Calais",
    "addr:postcode":"06610",
    "addr:street":"Chem Du Vallon Des Vaux;Gaude Nord",
    "iso:country":"FR",
    "sg:address":"Chem Du Vallon Des Vaux 06610 La Gaude",
    "sg:classifiers":[
        {
            "category":"Building & Trades",
            "subcategory":"Electrical",
            "type":"Services"
        }
    ],
    "sg:phone":"+33 4 93 31 05 48",
    "sg:province":"Nord Pas-de-Calais",
    "sg:tags":[
        "electronic",
        "lighting",
        "equipment"
    ],
    "wof:name":"Ragni",
    "wof:placetype":"venue"
},
  "geometry": {"coordinates":[7.15433,43.722321],"type":"Point"}
}