{
  "type": "Feature",
  "properties": {
    "iso:country":"FR",
    "sg:address":"B.P. 336, 78533 Buc C\u00e9dex^^418, Av. Roland Garros, 78530 Buc",
    "sg:orig_category":"Non-Classified Establishments",
    "sg:phone":"+33 1 39 56 17 56",
    "sg:postcode":"78530",
    "sg:province":"Ile de France",
    "wof:name":"C.d.e. 4 S.a.r.l. - Conseil D\u00e9veloppement Edition",
    "wof:placetype":"venue"
},
  "geometry": {"coordinates":[2.126343,48.774464],"type":"Point"}
}