{
  "type": "Feature",
  "properties": {
    "addr:full":"Chemin du Moulin de Tussac - ZA du Moulin Saint Mesmes Ile de France 77410",
    "addr:postcode":"77410",
    "addr:street":"Chemin Du Moulin De Tussac Za Du Moulin Saint Mesmes Ile De France",
    "iso:country":"FR",
    "sg:address":"Chemin du Moulin de Tussac - ZA du Moulin",
    "sg:city":"Saint Mesmes",
    "sg:orig_category":"Unclassifiable Establishments",
    "sg:phone":"+33 1 60 26 88 61",
    "sg:postcode":"77410",
    "sg:province":"Ile de France",
    "wof:name":"S.e.t. S.a. - Soci\u00e9t\u00e9 Europ\u00e9enne Technico-commerciale",
    "wof:placetype":"venue"
},
  "geometry": {"coordinates":[2.69566,48.984428],"type":"Point"}
}