{
  "type": "Feature",
  "properties": {
    "iso:country":"FR",
    "sg:address":"16 Rue Alfred Kastler La Vatine 76130 Mont St Aignan",
    "sg:classifiers":[
        {
            "category":"Manufacturing",
            "subcategory":"Rubber & Plastics",
            "type":"Manufacturing & Wholesale Goods"
        }
    ],
    "sg:phone":"+33 2 35 12 40 40",
    "sg:province":"Haute Normandie",
    "wof:name":"Metifiot Sa",
    "wof:placetype":"venue"
},
  "geometry": {"coordinates":[1.097292,49.476513],"type":"Point"}
}