{
  "type": "Feature",
  "properties": {
    "addr:full":"11 bis, Rue du Coliz\u00e9e, 75008 Paris Ile de France",
    "addr:housenumber":"11 bis",
    "addr:postcode":"75008",
    "addr:street":"Rue Du Colize\u0301E",
    "iso:country":"FR",
    "sg:address":"11 bis, Rue du Coliz\u00e9e, 75008 Paris",
    "sg:orig_category":"Non-Classified Establishments",
    "sg:phone":"+33 1 44 64 84 30",
    "sg:province":"Ile de France",
    "wof:name":"S.2e. Informatique S.a.r.l.",
    "wof:placetype":"venue"
},
  "geometry": {"coordinates":[2.307594,48.870647],"type":"Point"}
}