{
  "type": "Feature",
  "properties": {
    "iso:country":"FR",
    "sg:address":"4, Rue de l'Industrie - ZA de Mainville, 91214 Draveil C\u00e9dex",
    "sg:orig_category":"Non-Classified Establishments",
    "sg:phone":"+33 1 69 40 15 20",
    "sg:province":"California",
    "wof:name":"S.t.o.p. Plv S.a. - Soci\u00e9t\u00e9 De Thermoformage De L'ouest Parisien",
    "wof:placetype":"venue"
},
  "geometry": {"coordinates":[-118.245506,34.23122],"type":"Point"}
}