{
  "type": "Feature",
  "properties": {
    "addr:full":"2, Av. des Roses - Parc des Petits Carreaux, 94386 Bonneuil sur Marne C\u00e9dex \u00cele-de-France",
    "addr:postcode":"94386",
    "addr:street":"Av. Des Roses Parc Des Petits Carreaux;Ce\u0301Dex",
    "iso:country":"FR",
    "sg:address":"2, Av. des Roses - Parc des Petits Carreaux, 94386 Bonneuil sur Marne C\u00e9dex",
    "sg:orig_category":"Non-Classified Establishments",
    "sg:phone":"+33 1 56 71 21 30",
    "sg:province":"\u00cele-de-France",
    "wof:name":"Q.p.s. Europe S.a.r.l.",
    "wof:placetype":"venue"
},
  "geometry": {"coordinates":[2.48703,48.773804],"type":"Point"}
}