{
  "type": "Feature",
  "properties": {
    "iso:country":"FR",
    "sg:address":"6, Quai des Ramparts, 14100 Lisieux",
    "sg:city":"Lisieux",
    "sg:orig_category":"Unclassifiable Establishments",
    "sg:phone":"+33 2 31 62 27 88",
    "sg:postcode":"14100",
    "sg:province":"Basse Normandie",
    "wof:name":"Facompo S.a.r.l.",
    "wof:placetype":"venue"
},
  "geometry": {"coordinates":[0.221427,49.145863],"type":"Point"}
}