{
  "type": "Feature",
  "properties": {
    "iso:country":"FR",
    "sg:address":"158, Rue Anatole France, 71230 Saint Vallier",
    "sg:city":"Saint-Romain-sous-Gourdon",
    "sg:orig_category":"Unclassifiable Establishments",
    "sg:phone":"+33 3 85 69 07 90",
    "sg:postcode":"71230",
    "sg:province":"Bourgogne",
    "wof:name":"Productions Horticoles Thibaudier",
    "wof:placetype":"venue"
},
  "geometry": {"coordinates":[4.388716,46.654858],"type":"Point"}
}