{
  "type": "Feature",
  "properties": {
    "iso:country":"FR",
    "sg:address":"90 chemin du Ruisseau Mirabeau 13016 Marseille",
    "sg:orig_category":"Fruits, Dried",
    "sg:phone":"+33 4 91 60 82 04",
    "sg:province":"Poitou-Charentes",
    "wof:name":"Compagnie Alimentaire Sa",
    "wof:placetype":"venue"
},
  "geometry": {"coordinates":[5.34572,43.348595],"type":"Point"}
}