{
  "type": "Feature",
  "properties": {
    "addr:full":"34, Rue du T\u00e9l\u00e9graphe, 75020 Paris Ile de France",
    "addr:housenumber":"34",
    "addr:postcode":"75020",
    "addr:street":"Rue Du Te\u0301Le\u0301Graphe",
    "iso:country":"FR",
    "sg:address":"34, Rue du T\u00e9l\u00e9graphe, 75020 Paris",
    "sg:orig_category":"Non-Classified Establishments",
    "sg:phone":"+33 1 46 36 15 01",
    "sg:province":"Ile de France",
    "wof:name":"Infog\u00e9nia S.a.",
    "wof:placetype":"venue"
},
  "geometry": {"coordinates":[2.399404,48.873703],"type":"Point"}
}