{
  "type": "Feature",
  "properties": {
    "addr:full":"57 Avenue Michelet St Ouen Ile de France 93400",
    "addr:housenumber":"57",
    "addr:postcode":"93400",
    "addr:street":"Avenue Michelet St",
    "iso:country":"FR",
    "sg:address":"57 Avenue Michelet",
    "sg:city":"St Ouen",
    "sg:classifiers":[
        {
            "category":"Banks & Credit Unions",
            "subcategory":"Financial Services",
            "type":"Services"
        }
    ],
    "sg:phone":"+33 1 49 48 12 72",
    "sg:postcode":"93400",
    "sg:province":"Ile de France",
    "sg:tags":[
        "banking",
        "finance",
        "insurance"
    ],
    "wof:name":"Kyto Agence Sa",
    "wof:placetype":"venue"
},
  "geometry": {"coordinates":[2.344405,48.909115],"type":"Point"}
}