{
  "type": "Feature",
  "properties": {
    "addr:full":"Les Coup\u00e9es 01340 Foissiat Rhone-Alpes 01340",
    "addr:postcode":"01340;01340",
    "addr:street":"Rhone-Alpes",
    "iso:country":"FR",
    "sg:address":"Les Coup\u00e9es 01340 Foissiat",
    "sg:orig_category":"Non-Classified Establishments",
    "sg:phone":"+33 4 74 52 36 17",
    "sg:postcode":"01340",
    "sg:province":"Rhone-Alpes",
    "wof:name":"Entreprise Giroud Ren\u00e9",
    "wof:placetype":"venue"
},
  "geometry": {"coordinates":[5.174545,46.375366],"type":"Point"}
}