{
  "type": "Feature",
  "properties": {
    "iso:country":"FR",
    "sg:address":"B.P. 9205, 95076 Cergy Pontoise C\u00e9dex^^20, Av. de l'Ile de France, 95310 Saint Ouen l'Aum\u00f4ne",
    "sg:orig_category":"Non-Classified Establishments",
    "sg:phone":"+33 1 34 30 03 18",
    "sg:postcode":"95310",
    "sg:province":"Ile de France",
    "wof:name":"A.e.e.n. S.a. - Automatismes Exploitation Energies Nouvelles",
    "wof:placetype":"venue"
},
  "geometry": {"coordinates":[2.103637,49.04726],"type":"Point"}
}