{
  "type": "Feature",
  "properties": {
    "iso:country":"FR",
    "sg:address":"113, Rte de paris, 31150 Fenouillet",
    "sg:orig_category":"Unclassifiable Establishments",
    "sg:phone":"+33 5 61 70 26 75",
    "sg:province":"Midi Pyr\u00e9n\u00e9es",
    "wof:name":"E.m.b. Barot",
    "wof:placetype":"venue"
},
  "geometry": {"coordinates":[1.40913,43.675049],"type":"Point"}
}