{
  "type": "Feature",
  "properties": {
    "addr:full":"Rte de Blaye Bussac For\u00eat Poitou-Charentes 17210",
    "addr:postcode":"17210",
    "addr:street":"Rte De Blaye;Fore\u0302T",
    "iso:country":"FR",
    "sg:address":"Rte de Blaye",
    "sg:city":"Bussac For\u00eat",
    "sg:orig_category":"Unclassifiable Establishments",
    "sg:phone":"+33 5 46 04 31 01",
    "sg:postcode":"17210",
    "sg:province":"Poitou-Charentes",
    "wof:name":"Pin D\u00e9cor S.a.",
    "wof:placetype":"venue"
},
  "geometry": {"coordinates":[-0.418934,45.208496],"type":"Point"}
}