{
  "type": "Feature",
  "properties": {
    "addr:full":"11 av Jean Jaur\u00e8s; Bassens Champagne",
    "addr:street":"11 Av Jean Jaure\u0300S",
    "iso:country":"FR",
    "sg:address":"11 av Jean Jaur\u00e8s; Bassens",
    "sg:classifiers":[
        {
            "category":"Banks & Credit Unions",
            "subcategory":"Bank",
            "type":"Services"
        }
    ],
    "sg:phone":"+33 3356062796",
    "sg:province":"Champagne",
    "wof:name":"Cr\u00e9dit Agricole",
    "wof:placetype":"venue"
},
  "geometry": {"coordinates":[-0.516681,44.900986],"type":"Point"}
}