{
  "type": "Feature",
  "properties": {
    "addr:full":"10, Rue de la Combe aux Puits, 25480 Ecole Valentin Franche Comt\u00e9 25480",
    "addr:housenumber":"10",
    "addr:postcode":"25480;25480",
    "addr:street":"Rue De La Combe Aux Puits;Franche Comte\u0301",
    "iso:country":"FR",
    "sg:address":"10, Rue de la Combe aux Puits, 25480 Ecole Valentin",
    "sg:orig_category":"Non-Classified Establishments",
    "sg:phone":"+33 3 81 53 78 78",
    "sg:postcode":"25480",
    "sg:province":"Franche Comt\u00e9",
    "wof:name":"Blanchon Claude E.u.r.l.",
    "wof:placetype":"venue"
},
  "geometry": {"coordinates":[5.996483,47.275768],"type":"Point"}
}