{
  "type": "Feature",
  "properties": {
    "addr:full":"54 Rue Laennec 29681 ROSCOFF CEDEX Brittany",
    "addr:housenumber":"54",
    "addr:postcode":"29681",
    "addr:street":"Rue Laennec",
    "iso:country":"FR",
    "sg:address":"54 Rue Laennec 29681 ROSCOFF CEDEX",
    "sg:classifiers":[
        {
            "category":"Wholesale",
            "subcategory":"Fruits & Vegetables",
            "type":"Manufacturing & Wholesale Goods"
        }
    ],
    "sg:phone":"+33 2 98 69 79 52",
    "sg:province":"Brittany",
    "sg:tags":[
        "industrial",
        "purpose",
        "sea",
        "algae"
    ],
    "wof:name":"Biocean S.a.r.l.",
    "wof:placetype":"venue"
},
  "geometry": {"coordinates":[-3.984729,48.716591],"type":"Point"}
}