{
  "type": "Feature",
  "properties": {
    "iso:country":"FR",
    "sg:address":"96, Av. Albert 1er, 92500 Rueil Malmaison",
    "sg:orig_category":"Non-Classified Establishments",
    "sg:phone":"+33 1 41 39 03 50",
    "sg:province":"Ile de France",
    "wof:name":"Progexion S.a.",
    "wof:placetype":"venue"
},
  "geometry": {"coordinates":[2.172123,48.885601],"type":"Point"}
}