{
  "type": "Feature",
  "properties": {
    "addr:full":"B.P. 4202, 31031 Toulouse C\u00e9dex^^34, Rue des Cosmonautes - Zone du Palays - P\u00e9risud 4, 31400 Toulous Midi Pyr\u00e9n\u00e9es",
    "addr:housenumber":"4",
    "addr:postcode":"31031;31400",
    "addr:street":"B.P. 4202;Rue Des Cosmonautes;Du Palays Pe\u0301Risud",
    "iso:country":"FR",
    "sg:address":"B.P. 4202, 31031 Toulouse C\u00e9dex^^34, Rue des Cosmonautes - Zone du Palays - P\u00e9risud 4, 31400 Toulous",
    "sg:orig_category":"Non-Classified Establishments",
    "sg:phone":"+33 5 62 47 36 47",
    "sg:province":"Midi Pyr\u00e9n\u00e9es",
    "wof:name":"S.m.s. France S.a.",
    "wof:placetype":"venue"
},
  "geometry": {"coordinates":[1.44301,43.604359],"type":"Point"}
}