{
  "type": "Feature",
  "properties": {
    "iso:country":"FR",
    "sg:address":"26 R De L Engelbreit 67200 Strasbourg",
    "sg:city":"Strasbourg",
    "sg:classifiers":[
        {
            "category":"Wholesale",
            "subcategory":"Medical Equipment & Supplies",
            "type":"Manufacturing & Wholesale Goods"
        }
    ],
    "sg:phone":"+33 3 88 29 06 46",
    "sg:postcode":"67200",
    "sg:province":"Alsace",
    "sg:tags":[
        "instrument",
        "health",
        "-",
        "precision"
    ],
    "wof:name":"M. Flottau Francis Laboratoire Dentaire Flottau",
    "wof:placetype":"venue"
},
  "geometry": {"coordinates":[7.707896,48.580524],"type":"Point"}
}