{
  "type": "Feature",
  "properties": {
    "iso:country":"FR",
    "sg:address":"69/71, Rue Archereau, 75019 Paris",
    "sg:orig_category":"Non-Classified Establishments",
    "sg:phone":"+33 1 55 26 63 85",
    "sg:province":"Ile de France",
    "wof:name":"Oxalide S.a.",
    "wof:placetype":"venue"
},
  "geometry": {"coordinates":[2.376125,48.8932],"type":"Point"}
}