{
  "type": "Feature",
  "properties": {
    "iso:country":"FR",
    "sg:address":"20 bis, Rte de Marchon, 01100 Oyonnax",
    "sg:orig_category":"Non-Classified Establishments",
    "sg:phone":"+33 4 74 73 85 23",
    "sg:postcode":"01100",
    "sg:province":"Rhone-Alpes",
    "wof:name":"Virgeof S.a.r.l.",
    "wof:placetype":"venue"
},
  "geometry": {"coordinates":[5.660966,46.265747],"type":"Point"}
}