{
  "type": "Feature",
  "properties": {
    "addr:full":"2, Rue des Potiers - ZI la Mirande, 66240 Saint Est\u00e8ve Languedoc-Roussillon",
    "addr:housenumber":"2",
    "addr:postcode":"66240 saint este\u0300ve",
    "addr:street":"Rue Des Potiers Zi La Mirande",
    "iso:country":"FR",
    "sg:address":"2, Rue des Potiers - ZI la Mirande, 66240 Saint Est\u00e8ve",
    "sg:orig_category":"Non-Classified Establishments",
    "sg:phone":"+33 4 68 92 27 17",
    "sg:province":"Languedoc-Roussillon",
    "wof:name":"Pichon Pierre Marcel",
    "wof:placetype":"venue"
},
  "geometry": {"coordinates":[2.845377,42.709045],"type":"Point"}
}