{
  "type": "Feature",
  "properties": {
    "iso:country":"FR",
    "sg:address":"B.P. 56",
    "sg:city":"Le Puy en Velay",
    "sg:orig_category":"Non-Classified Establishments",
    "sg:phone":"+33 4 71 09 28 71",
    "sg:postcode":"43000",
    "sg:province":"Auvergne",
    "wof:name":"Sansac S.a.",
    "wof:placetype":"venue"
},
  "geometry": {"coordinates":[3.883285,45.042027],"type":"Point"}
}