{
  "type": "Feature",
  "properties": {
    "addr:full":"Zi Nord 01100 Arbent Rhone-Alpes",
    "addr:postcode":"01100",
    "addr:street":"Zi",
    "iso:country":"FR",
    "sg:address":"Zi Nord 01100 Arbent",
    "sg:classifiers":[
        {
            "category":"Manufacturing",
            "subcategory":"Rubber & Plastics",
            "type":"Manufacturing & Wholesale Goods"
        }
    ],
    "sg:phone":"+33 4 74 77 06 17",
    "sg:province":"Rhone-Alpes",
    "wof:name":"Promoplas",
    "wof:placetype":"venue"
},
  "geometry": {"coordinates":[5.682105,46.29575],"type":"Point"}
}