{
  "type": "Feature",
  "properties": {
    "addr:full":"Z I 16160 Gond Pontouvre Poitou-Charentes",
    "addr:postcode":"16160",
    "addr:street":"Z;Pontouvre",
    "iso:country":"FR",
    "sg:address":"Z I 16160 Gond Pontouvre",
    "sg:orig_category":"Recuperators",
    "sg:phone":"+33 5 45 37 14 20",
    "sg:province":"Poitou-Charentes",
    "wof:name":"Etablissements Bernon Et Compagnie Sa",
    "wof:placetype":"venue"
},
  "geometry": {"coordinates":[0.166295,45.668095],"type":"Point"}
}