{
  "type": "Feature",
  "properties": {
    "addr:full":"4, Place G. Cl\u00e9menceau, 73100 Aix les Bains Rhone-Alpes 73100",
    "addr:housenumber":"4",
    "addr:postcode":"73100;73100",
    "addr:street":"Place G. Cle\u0301Menceau",
    "iso:country":"FR",
    "sg:address":"4, Place G. Cl\u00e9menceau, 73100 Aix les Bains",
    "sg:orig_category":"Non-Classified Establishments",
    "sg:phone":"+33 4 79 34 37 65",
    "sg:postcode":"73100",
    "sg:province":"Rhone-Alpes",
    "wof:name":"A.g. Consultants S.a.r.l.",
    "wof:placetype":"venue"
},
  "geometry": {"coordinates":[5.90949,45.692848],"type":"Point"}
}