{
  "type": "Feature",
  "properties": {
    "iso:country":"FR",
    "sg:address":"1650 Rte De Tournai 59500 Douai",
    "sg:classifiers":[
        {
            "category":"Professional",
            "subcategory":"Engineering",
            "type":"Services"
        }
    ],
    "sg:phone":"+33 3 27 88 02 06",
    "sg:postcode":"59500",
    "sg:province":"Nord Pas-de-Calais",
    "sg:tags":[
        "machine",
        "-",
        "mechanical"
    ],
    "wof:name":"Compagnie Gaziere De Services Et D'entretien (cgst Save)",
    "wof:placetype":"venue"
},
  "geometry": {"coordinates":[3.11952,50.401711],"type":"Point"}
}