{
  "type": "Feature",
  "properties": {
    "iso:country":"FR",
    "sg:address":"Hameau de la Motte 27270 Ferri\u00e8res Saint Hilaire",
    "sg:orig_category":"Unclassifiable Establishments",
    "sg:phone":"+33 2 32 44 92 01",
    "sg:province":"Haute Normandie",
    "wof:name":"Soci\u00e9t\u00e9 De Reliure Industrielle De Normandie S.a.r.l.",
    "wof:placetype":"venue"
},
  "geometry": {"coordinates":[0.556081,49.016579],"type":"Point"}
}