{
  "type": "Feature",
  "properties": {
    "addr:full":"221 Rue Du Docteur Guichard Angers Pays de Loire 49000",
    "addr:housenumber":"221",
    "addr:postcode":"49000",
    "addr:street":"Rue Du Docteur Guichard Angers Pays",
    "iso:country":"FR",
    "sg:address":"221 Rue Du Docteur Guichard",
    "sg:city":"Angers",
    "sg:classifiers":[
        {
            "category":"Banks & Credit Unions",
            "subcategory":"Financial Services",
            "type":"Services"
        }
    ],
    "sg:phone":"+33 2 41 66 62 80",
    "sg:postcode":"49000",
    "sg:province":"Pays de Loire",
    "sg:tags":[
        "banking",
        "finance",
        "insurance"
    ],
    "wof:name":"Sjvl",
    "wof:placetype":"venue"
},
  "geometry": {"coordinates":[-0.550587,47.447945],"type":"Point"}
}