{
  "type": "Feature",
  "properties": {
    "iso:country":"FR",
    "sg:address":"1 rue Lyc\u00e9e; Nice",
    "sg:classifiers":[
        {
            "category":"Banks & Credit Unions",
            "subcategory":"Bank",
            "type":"Services"
        }
    ],
    "sg:phone":"+33 3393625030",
    "sg:province":"Picardie",
    "wof:name":"Cr\u00e9dit Agricole Des Alpes Maritimes, Habitat Conseil",
    "wof:placetype":"venue"
},
  "geometry": {"coordinates":[-122.8386,39.121292],"type":"Point"}
}