{
  "type": "Feature",
  "properties": {
    "iso:country":"FR",
    "sg:address":"4 pl Jean Jaur\u00e8s; Castres; 81100",
    "sg:classifiers":[
        {
            "category":"Banks & Credit Unions",
            "subcategory":"Bank",
            "type":"Services"
        }
    ],
    "sg:phone":"+33 3363595919",
    "sg:postcode":"81100",
    "sg:province":"Midi Pyr\u00e9n\u00e9es",
    "wof:name":"Banque Nationale De Paris",
    "wof:placetype":"venue"
},
  "geometry": {"coordinates":[2.242177,43.605614],"type":"Point"}
}