{
  "type": "Feature",
  "properties": {
    "addr:full":"66, Quai Charles de Gaulle, 69006 Lyon Rhone-Alpes",
    "addr:housenumber":"66",
    "addr:postcode":"69006",
    "addr:street":"Quai Charles De Gaulle",
    "iso:country":"FR",
    "sg:address":"66, Quai Charles de Gaulle, 69006 Lyon",
    "sg:orig_category":"Unclassifiable Establishments",
    "sg:phone":"+33 4 72 69 56 70",
    "sg:province":"Rhone-Alpes",
    "wof:name":"Groupe Emin Leydier S.a.",
    "wof:placetype":"venue"
},
  "geometry": {"coordinates":[4.85262,45.785145],"type":"Point"}
}