{
  "type": "Feature",
  "properties": {
    "iso:country":"FR",
    "sg:address":"B.P. 31093, 67382 Lingolsheim C\u00e9dex^^16, Rue de la Batterie - Parc Activa, 67118 Geispolsheim",
    "sg:city":"Geispolsheim",
    "sg:orig_category":"Non-Classified Establishments",
    "sg:phone":"+33 3 88 67 29 19",
    "sg:postcode":"67400",
    "sg:province":"Alsace",
    "wof:name":"Dreyfus Gaston Et Compagnie S.a.",
    "wof:placetype":"venue"
},
  "geometry": {"coordinates":[7.643295,48.515163],"type":"Point"}
}