{
  "type": "Feature",
  "properties": {
    "iso:country":"FR",
    "sg:address":"1, Parc du Saint Laurent, 78230 Le Pecq",
    "sg:orig_category":"Unclassifiable Establishments",
    "sg:phone":"+33 1 34 80 35 05",
    "sg:province":"Ile de France",
    "wof:name":"Compagnie Laiti\u00e8re Food Service S.a.s.",
    "wof:placetype":"venue"
},
  "geometry": {"coordinates":[2.117571,48.901684],"type":"Point"}
}