{
  "type": "Feature",
  "properties": {
    "iso:country":"FR",
    "sg:address":"26, Rue du Vernand, 74100 Annemasse",
    "sg:orig_category":"Unclassifiable Establishments",
    "sg:phone":"+33 4 50 37 08 12",
    "sg:postcode":"74100",
    "sg:province":"Rhone-Alpes",
    "wof:name":"Frocal S.a.r.l.",
    "wof:placetype":"venue"
},
  "geometry": {"coordinates":[6.238056,46.179817],"type":"Point"}
}