{
  "type": "Feature",
  "properties": {
    "iso:country":"FR",
    "sg:address":"8 rue Hoche 42300 Roanne",
    "sg:classifiers":[
        {
            "category":"Utilities",
            "subcategory":"Recycling",
            "type":"Services"
        }
    ],
    "sg:phone":"+33 4 77 67 03 79",
    "sg:postcode":"42300",
    "sg:province":"Rhone-Alpes",
    "sg:tags":[
        "paper",
        "waste"
    ],
    "wof:name":"Guyonnet Freres Sarl",
    "wof:placetype":"venue"
},
  "geometry": {"coordinates":[4.074405,46.029259],"type":"Point"}
}