{
  "type": "Feature",
  "properties": {
    "addr:full":"92 Rue Jean Augustin Fresnel 11000 Carcassonne Languedoc-Roussillon",
    "addr:housenumber":"92",
    "addr:postcode":"11000",
    "addr:street":"Rue Jean Augustin Fresnel",
    "iso:country":"FR",
    "sg:address":"92 Rue Jean Augustin Fresnel 11000 Carcassonne",
    "sg:classifiers":[
        {
            "category":"Professional",
            "type":"Services"
        }
    ],
    "sg:phone":"+33 4 68 47 24 94",
    "sg:province":"Languedoc-Roussillon",
    "sg:tags":[
        "transport",
        "road"
    ],
    "wof:name":"Demenageurs Bretons Cabrie Demenag Franchise Sarl",
    "wof:placetype":"venue"
},
  "geometry": {"coordinates":[2.32507,43.217571],"type":"Point"}
}