{
  "type": "Feature",
  "properties": {
    "addr:full":"39 rue du Commerce; Paris; 75015 Ile de France 75015",
    "addr:housenumber":"39",
    "addr:postcode":"75015 ile;france 75015",
    "addr:street":"Rue Du Commerce",
    "iso:country":"FR",
    "sg:address":"39 rue du Commerce; Paris; 75015",
    "sg:classifiers":[
        {
            "category":"Banks & Credit Unions",
            "subcategory":"Bank",
            "type":"Services"
        }
    ],
    "sg:phone":"+33 1 44 37 57 50",
    "sg:postcode":"75015",
    "sg:province":"Ile de France",
    "wof:name":"Soci\u00e9t\u00e9 G\u00e9n\u00e9rale",
    "wof:placetype":"venue"
},
  "geometry": {"coordinates":[2.29592,48.846874],"type":"Point"}
}