{
  "type": "Feature",
  "properties": {
    "addr:full":"109 Rue Des Peupliers 62120 Racquinghem Nord Pas-de-Calais 62120",
    "addr:housenumber":"109",
    "addr:postcode":"62120;62120",
    "addr:street":"Rue Des Peupliers",
    "iso:country":"FR",
    "sg:address":"109 Rue Des Peupliers 62120 Racquinghem",
    "sg:classifiers":[
        {
            "category":"Manufacturing",
            "subcategory":"Textiles",
            "type":"Manufacturing & Wholesale Goods"
        }
    ],
    "sg:phone":"+33 3 21 38 39 30",
    "sg:postcode":"62120",
    "sg:province":"Nord Pas-de-Calais",
    "sg:tags":[
        "clothing",
        "accessory"
    ],
    "wof:name":"Marie Joseph",
    "wof:placetype":"venue"
},
  "geometry": {"coordinates":[2.346732,50.692924],"type":"Point"}
}