{
  "type": "Feature",
  "properties": {
    "addr:full":"10, Rue Henri Turner, 31100 Toulouse Midi Pyr\u00e9n\u00e9es",
    "addr:housenumber":"10",
    "addr:postcode":"31100",
    "addr:street":"Rue Henri Turner",
    "iso:country":"FR",
    "sg:address":"10, Rue Henri Turner, 31100 Toulouse",
    "sg:orig_category":"Unclassifiable Establishments",
    "sg:phone":"+33 5 61 40 98 30",
    "sg:province":"Midi Pyr\u00e9n\u00e9es",
    "wof:name":"Industriel Nettoyage Services S.a.r.l.",
    "wof:placetype":"venue"
},
  "geometry": {"coordinates":[1.406609,43.552277],"type":"Point"}
}