{
  "type": "Feature",
  "properties": {
    "iso:country":"FR",
    "sg:address":"21, Rue Saint Vincent, 92700 Colombes",
    "sg:orig_category":"Non-Classified Establishments",
    "sg:phone":"+33 1 47 81 64 03",
    "sg:province":"Ile de France",
    "wof:name":"Foca Volt S.a.",
    "wof:placetype":"venue"
},
  "geometry": {"coordinates":[2.259969,48.92141],"type":"Point"}
}