{
  "type": "Feature",
  "properties": {
    "addr:full":"B.P. 26 Annesse et Beaulieu C\u00e9dex^^24430 Annesse et Beaulieu Aquitaine 24430",
    "addr:postcode":"24430",
    "addr:street":"B.P. 26 Annesse Et Beaulieu Ce\u0301Dex^^24430;Et",
    "iso:country":"FR",
    "sg:address":"B.P. 26",
    "sg:city":"Annesse et Beaulieu C\u00e9dex^^24430 Annesse et Beaulieu",
    "sg:orig_category":"Non-Classified Establishments",
    "sg:phone":"+33 5 53 04 05 25",
    "sg:postcode":"24430",
    "sg:province":"Aquitaine",
    "wof:name":"Cr\u00e9ation Philippe Vallereuil S.a.",
    "wof:placetype":"venue"
},
  "geometry": {"coordinates":[0.638874,45.128197],"type":"Point"}
}