{
  "type": "Feature",
  "properties": {
    "addr:full":"5 Pasteur; Somain; 59490 Nord Pas-de-Calais 59490",
    "addr:housenumber":"5",
    "addr:postcode":"59490;59490",
    "addr:street":"Pasteur",
    "iso:country":"FR",
    "sg:address":"5",
    "sg:city":"Pasteur; Somain; 59490",
    "sg:classifiers":[
        {
            "category":"Banks & Credit Unions",
            "subcategory":"Bank",
            "type":"Services"
        }
    ],
    "sg:phone":"+33 27862950",
    "sg:postcode":"59490",
    "sg:province":"Nord Pas-de-Calais",
    "wof:name":"Banque Nationale De Paris",
    "wof:placetype":"venue"
},
  "geometry": {"coordinates":[3.280704,50.359386],"type":"Point"}
}