{
  "type": "Feature",
  "properties": {
    "addr:full":"30C, All\u00e9e de Saint Malo - Mar\u00e9e 103, 94519 Rungis C\u00e9dex Ile-de-France",
    "addr:housenumber":"30c;103",
    "addr:postcode":"94519",
    "addr:street":"Alle\u0301E De Saint Malo Mare\u0301E",
    "iso:country":"FR",
    "sg:address":"30C, All\u00e9e de Saint Malo - Mar\u00e9e 103, 94519 Rungis C\u00e9dex",
    "sg:orig_category":"Non-Classified Establishments",
    "sg:phone":"+33 1 46 86 05 67",
    "sg:province":"Ile-de-France",
    "wof:name":"Pecunia Fr\u00e8res S.a.r.l.",
    "wof:placetype":"venue"
},
  "geometry": {"coordinates":[2.35325,48.751419],"type":"Point"}
}