{
  "type": "Feature",
  "properties": {
    "iso:country":"FR",
    "sg:address":"63 rue du G\u00e9n\u00e9ral de Gaulle 78300 Poissy",
    "sg:orig_category":"Sound Insulation Work",
    "sg:phone":"+33 1 30 74 61 50",
    "sg:province":"Ile de France",
    "wof:name":"S.i.r.a. Sa",
    "wof:placetype":"venue"
},
  "geometry": {"coordinates":[2.042208,48.929886],"type":"Point"}
}