{
  "type": "Feature",
  "properties": {
    "iso:country":"FR",
    "sg:address":"16, Rue de Bel Air, 44470 Carquefou",
    "sg:orig_category":"Unclassifiable Establishments",
    "sg:phone":"+33 2 40 30 11 81",
    "sg:province":"Pays de Loire",
    "wof:name":"Sercel S.a. - Soci\u00e9t\u00e9 D'etudes Recherches Et Constructions Electroniques",
    "wof:placetype":"venue"
},
  "geometry": {"coordinates":[-1.49125,47.265797],"type":"Point"}
}