{
  "type": "Feature",
  "properties": {
    "iso:country":"FR",
    "sg:address":"Za N 2 Rn 7 Lot 1 Ld Gaillardes Et Olivettes 13670 St Andiol",
    "sg:classifiers":[
        {
            "category":"Professional",
            "subcategory":"Engineering",
            "type":"Services"
        }
    ],
    "sg:phone":"+33 4 90 90 24 24",
    "sg:province":"Auvergne",
    "sg:tags":[
        "machine",
        "-",
        "mechanical"
    ],
    "wof:name":"Euro Label 06",
    "wof:placetype":"venue"
},
  "geometry": {"coordinates":[4.94301,43.836479],"type":"Point"}
}