{
  "type": "Feature",
  "properties": {
    "addr:full":"Rte d'Agen - ZI Nord Auch Midi Pyr\u00e9n\u00e9es 32000",
    "addr:postcode":"32000",
    "addr:street":"Rte D'Agen Zi Nord",
    "iso:country":"FR",
    "sg:address":"Rte d'Agen - ZI Nord",
    "sg:city":"Auch",
    "sg:orig_category":"Non-Classified Establishments",
    "sg:phone":"+33 5 62 63 61 63",
    "sg:postcode":"32000",
    "sg:province":"Midi Pyr\u00e9n\u00e9es",
    "wof:name":"Euromaster France Poids Lourds",
    "wof:placetype":"venue"
},
  "geometry": {"coordinates":[0.601285,43.663429],"type":"Point"}
}