{
  "type": "Feature",
  "properties": {
    "addr:full":"B.P. 7506, 95040 Cergy Pontoise C\u00e9dex^^18, Rue des Oziers - ZI du Vert Galant, 95310 Saint Ouen l'Au Ile de France",
    "addr:postcode":"95040;95310;l'au ile",
    "addr:street":"B.P. 7506;Rue Des Oziers Zi Du Vert Galant",
    "iso:country":"FR",
    "sg:address":"B.P. 7506, 95040 Cergy Pontoise C\u00e9dex^^18, Rue des Oziers - ZI du Vert Galant, 95310 Saint Ouen l'Au",
    "sg:orig_category":"Non-Classified Establishments",
    "sg:phone":"+33 1 34 21 99 44",
    "sg:province":"Ile de France",
    "wof:name":"N.i.c. S.a.r.l - N\u00e9gociation Industrielle Et Commerciale",
    "wof:placetype":"venue"
},
  "geometry": {"coordinates":[2.933116,48.55759],"type":"Point"}
}