{
  "type": "Feature",
  "properties": {
    "addr:full":"Rue de Munich - Gare Saint Charles Perpignan Languedoc-Roussillon 66030",
    "addr:postcode":"66030",
    "addr:street":"Rue De Munich;Charles",
    "iso:country":"FR",
    "sg:address":"Rue de Munich - Gare Saint Charles",
    "sg:city":"Perpignan",
    "sg:orig_category":"Unclassifiable Establishments",
    "sg:phone":"+33 4 68 54 36 35",
    "sg:postcode":"66030",
    "sg:province":"Languedoc-Roussillon",
    "wof:name":"Transporteurs R\u00e9unis Fl\u00e8che Cavaillon S.a.",
    "wof:placetype":"venue"
},
  "geometry": {"coordinates":[2.8966,42.700611],"type":"Point"}
}