{
  "type": "Feature",
  "properties": {
    "addr:full":"393, Av. du Prado, 13008 Marseille Provence-Alpes-C\u00f4te d'Azur",
    "addr:postcode":"13008",
    "addr:street":"393 Av. Du Prado",
    "iso:country":"FR",
    "sg:address":"393, Av. du Prado, 13008 Marseille",
    "sg:orig_category":"Unclassifiable Establishments",
    "sg:phone":"+33 4 91 16 73 50",
    "sg:province":"Provence-Alpes-C\u00f4te d'Azur",
    "wof:name":"Soci\u00e9t\u00e9 Expertise Comptable Raufast Et Compagnie S.a.",
    "wof:placetype":"venue"
},
  "geometry": {"coordinates":[5.385797,43.268547],"type":"Point"}
}