{
  "type": "Feature",
  "properties": {
    "iso:country":"FR",
    "sg:address":"995 Route Des Arcs 83510 Lorgues",
    "sg:classifiers":[
        {
            "category":"Professional",
            "subcategory":"Printing & Photocopies",
            "type":"Services"
        }
    ],
    "sg:phone":"+33 4 94 85 90 16",
    "sg:province":"Picardie",
    "sg:tags":[
        "publishing"
    ],
    "wof:name":"Information Medicale Express (ime France)",
    "wof:placetype":"venue"
},
  "geometry": {"coordinates":[6.38802,43.466774],"type":"Point"}
}