{
  "type": "Feature",
  "properties": {
    "iso:country":"FR",
    "sg:address":"40 Avenue Carnot 94100 St Maur Des Fosses",
    "sg:classifiers":[
        {
            "category":"Manufacturing",
            "subcategory":"Tools & Machinery",
            "type":"Manufacturing & Wholesale Goods"
        }
    ],
    "sg:phone":"+33 1 48 85 11 24",
    "sg:postcode":"94100",
    "sg:province":"Ile de France",
    "sg:tags":[
        "equipment",
        "measurement",
        "-",
        "precision",
        "instrument"
    ],
    "wof:name":"Item Sarl",
    "wof:placetype":"venue"
},
  "geometry": {"coordinates":[2.486912,48.800587],"type":"Point"}
}