{
  "type": "Feature",
  "properties": {
    "iso:country":"FR",
    "sg:address":"45, Rue Saint S\u00e9bastien, 75011 Paris",
    "sg:orig_category":"Unclassifiable Establishments",
    "sg:phone":"+33 1 55 28 35 55",
    "sg:province":"Ile de France",
    "wof:name":"A.c.c.o.m. Multim\u00e9dia S.a.r.l.",
    "wof:placetype":"venue"
},
  "geometry": {"coordinates":[2.371553,48.861885],"type":"Point"}
}