{
  "type": "Feature",
  "properties": {
    "addr:full":"1 Rue De La Gare 62152 Neufchatel Hardelot Nord Pas-de-Calais 62152",
    "addr:housenumber":"1",
    "addr:postcode":"62152;62152",
    "addr:street":"Rue De La Gare;Hardelot Nord",
    "iso:country":"FR",
    "sg:address":"1 Rue De La Gare 62152 Neufchatel Hardelot",
    "sg:classifiers":[
        {
            "category":"Wholesale",
            "subcategory":"Medical Equipment & Supplies",
            "type":"Manufacturing & Wholesale Goods"
        }
    ],
    "sg:phone":"+33 3 21 32 24 85",
    "sg:postcode":"62152",
    "sg:province":"Nord Pas-de-Calais",
    "sg:tags":[
        "instrument",
        "health",
        "-",
        "precision"
    ],
    "wof:name":"Dental Associes",
    "wof:placetype":"venue"
},
  "geometry": {"coordinates":[1.645996,50.623013],"type":"Point"}
}