{
  "type": "Feature",
  "properties": {
    "addr:full":"Av Normandy Sussex Dieppe Haute Normandie 76200",
    "addr:postcode":"76200",
    "addr:street":"Av Normandy",
    "iso:country":"FR",
    "sg:address":"Av Normandy Sussex",
    "sg:city":"Dieppe",
    "sg:orig_category":"Unclassifiable Establishments",
    "sg:phone":"+33 2 32 90 51 51",
    "sg:postcode":"76200",
    "sg:province":"Haute Normandie",
    "wof:name":"Marchand S.a.",
    "wof:placetype":"venue"
},
  "geometry": {"coordinates":[1.08803,49.917515],"type":"Point"}
}