{
  "type": "Feature",
  "properties": {
    "iso:country":"FR",
    "sg:address":"67, Rue Pierre Baizet, 69009 Lyon",
    "sg:orig_category":"Unclassifiable Establishments",
    "sg:phone":"+33 4 78 47 81 55",
    "sg:postcode":"69009",
    "sg:province":"Rhone-Alpes",
    "wof:name":"B.m.g. Geoffroy S.a.r.l.",
    "wof:placetype":"venue"
},
  "geometry": {"coordinates":[4.81642,45.796246],"type":"Point"}
}