{
  "type": "Feature",
  "properties": {
    "addr:full":"13 Route De Limonest De La Braille 69380 Lissieu Rhone-Alpes 69380",
    "addr:housenumber":"13",
    "addr:postcode":"69380;69380",
    "addr:street":"Route De Limonest De La Braille",
    "iso:country":"FR",
    "sg:address":"13 Route De Limonest",
    "sg:city":"De La Braille 69380 Lissieu",
    "sg:classifiers":[
        {
            "category":"Professional",
            "subcategory":"Engineering",
            "type":"Services"
        }
    ],
    "sg:phone":"+33 4 72 54 80 00",
    "sg:postcode":"69380",
    "sg:province":"Rhone-Alpes",
    "sg:tags":[
        "machine",
        "-",
        "mechanical"
    ],
    "wof:name":"Sic Marking",
    "wof:placetype":"venue"
},
  "geometry": {"coordinates":[4.71535,45.835541],"type":"Point"}
}