{
  "type": "Feature",
  "properties": {
    "iso:country":"FR",
    "sg:address":"22, Rue des Forges, 36100 Les Bordes",
    "sg:city":"Les Bordes",
    "sg:orig_category":"Unclassifiable Establishments",
    "sg:phone":"+33 2 54 49 78 32",
    "sg:postcode":"36100",
    "sg:province":"Centre",
    "wof:name":"Soci\u00e9t\u00e9 Nouvelle Cerap S.a.r.l.",
    "wof:placetype":"venue"
},
  "geometry": {"coordinates":[1.970208,46.982719],"type":"Point"}
}