{
  "type": "Feature",
  "properties": {
    "addr:full":"Rte de Mezzavia - Kilom\u00e9tre 5 Ajaccio Corse 20090",
    "addr:housenumber":"5",
    "addr:postcode":"20090",
    "addr:street":"Rte De Mezzavia Kilome\u0301Tre;Corse",
    "iso:country":"FR",
    "sg:address":"Rte de Mezzavia - Kilom\u00e9tre 5",
    "sg:city":"Ajaccio",
    "sg:orig_category":"Non-Classified Establishments",
    "sg:phone":"+33 4 95 22 38 36",
    "sg:postcode":"20090",
    "sg:province":"Corse",
    "wof:name":"C.g.a.i. S.a.r.l. - Comptoir G\u00e9n\u00e9ral Agricole Et Industriel",
    "wof:placetype":"venue"
},
  "geometry": {"coordinates":[8.781228,41.952419],"type":"Point"}
}