{
  "type": "Feature",
  "properties": {
    "addr:full":"6 Quai De Danemark 76380 Canteleu Haute Normandie 76380",
    "addr:housenumber":"6",
    "addr:postcode":"76380;76380",
    "addr:street":"Quai De Danemark;Haute Normandie",
    "iso:country":"FR",
    "sg:address":"6 Quai De Danemark 76380 Canteleu",
    "sg:classifiers":[
        {
            "category":"Professional",
            "subcategory":"Advertising",
            "type":"Services"
        }
    ],
    "sg:phone":"+33 2 35 36 01 21",
    "sg:postcode":"76380",
    "sg:province":"Haute Normandie",
    "sg:tags":[
        "marketing",
        "medium",
        "communication"
    ],
    "wof:name":"Adrexo",
    "wof:placetype":"venue"
},
  "geometry": {"coordinates":[1.017705,49.420551],"type":"Point"}
}