{
  "type": "Feature",
  "properties": {
    "addr:full":"21, Impasse de la T\u00eate Noire, 69250 Neuville sur Sa\u00f4ne Rhone-Alpes",
    "addr:housenumber":"21",
    "addr:postcode":"69250",
    "addr:street":"Impasse De La Te\u0302Te Noire",
    "iso:country":"FR",
    "sg:address":"21, Impasse de la T\u00eate Noire, 69250 Neuville sur Sa\u00f4ne",
    "sg:orig_category":"Unclassifiable Establishments",
    "sg:phone":"+33 4 78 91 27 45",
    "sg:province":"Rhone-Alpes",
    "wof:name":"Bouhey S.a.",
    "wof:placetype":"venue"
},
  "geometry": {"coordinates":[4.843699,45.866322],"type":"Point"}
}