{
  "type": "Feature",
  "properties": {
    "iso:country":"FR",
    "sg:address":"28 Route De Longjumeau 91380 Chilly Mazarin",
    "sg:classifiers":[
        {
            "category":"Building & Trades",
            "subcategory":"Construction",
            "type":"Services"
        }
    ],
    "sg:phone":"+33 1 69 10 40 00",
    "sg:postcode":"91380",
    "sg:province":"Ile de France",
    "sg:tags":[
        "work",
        "public"
    ],
    "wof:name":"Bouygues",
    "wof:placetype":"venue"
},
  "geometry": {"coordinates":[2.296887,48.706982],"type":"Point"}
}