{
  "type": "Feature",
  "properties": {
    "iso:country":"FR",
    "sg:address":"6, Rue de la Bauve, 60000 Beauvais",
    "sg:orig_category":"Non-Classified Establishments",
    "sg:phone":"+33 3 44 05 94 94",
    "sg:province":"Picardie",
    "wof:name":"Quintana S.a.",
    "wof:placetype":"venue"
},
  "geometry": {"coordinates":[2.093397,49.439026],"type":"Point"}
}