{
  "type": "Feature",
  "properties": {
    "iso:country":"FR",
    "sg:address":"1, Rue des Montagnes de Lans - ZI de Comboire, 38130 Echirolles",
    "sg:orig_category":"Unclassifiable Establishments",
    "sg:phone":"+33 4 76 09 96 97",
    "sg:postcode":"38130",
    "sg:province":"Rhone-Alpes",
    "wof:name":"Tyko S.a.r.l.",
    "wof:placetype":"venue"
},
  "geometry": {"coordinates":[5.7194,45.149536],"type":"Point"}
}