{
  "type": "Feature",
  "properties": {
    "iso:country":"FR",
    "sg:address":"Avenue De La Gare 34310 QUARANTE",
    "sg:classifiers":[
        {
            "category":"Wholesale",
            "subcategory":"Wine & Distilled Alcoholic Beverages",
            "type":"Manufacturing & Wholesale Goods"
        }
    ],
    "sg:phone":"+33 4 67 89 40 39",
    "sg:postcode":"34310",
    "sg:province":"Languedoc-Roussillon",
    "sg:tags":[
        "french"
    ],
    "wof:name":"Cooperative De Vinification De Quarante Coop.",
    "wof:placetype":"venue"
},
  "geometry": {"coordinates":[2.964375,43.346771],"type":"Point"}
}