{
  "type": "Feature",
  "properties": {
    "addr:full":"156 Bd Delebecque 59500 Douai Nord Pas-de-Calais 59500",
    "addr:housenumber":"156",
    "addr:postcode":"59500;59500",
    "addr:street":"Bd Delebecque",
    "iso:country":"FR",
    "sg:address":"156 Bd Delebecque 59500 Douai",
    "sg:classifiers":[
        {
            "category":"Professional",
            "subcategory":"Computer Services",
            "type":"Services"
        }
    ],
    "sg:phone":"+33 3 27 94 30 20",
    "sg:postcode":"59500",
    "sg:province":"Nord Pas-de-Calais",
    "sg:tags":[
        "information",
        "technology",
        "software"
    ],
    "wof:name":"Tetra Informatique Sarl",
    "wof:placetype":"venue"
},
  "geometry": {"coordinates":[3.086084,50.365444],"type":"Point"}
}