{
  "type": "Feature",
  "properties": {
    "addr:full":"B.P. 2020, 71020 Macon C\u00e9dex^^33, Bd de la R\u00e9sistance, 71000 M\u00e2con Sanc\u00e9 Bourgogne 71000",
    "addr:housenumber":"71020",
    "addr:postcode":"71000;71000",
    "addr:street":"B.P. 2020;Bd De La Re\u0301Sistance",
    "iso:country":"FR",
    "sg:address":"B.P. 2020, 71020 Macon C\u00e9dex^^33, Bd de la R\u00e9sistance, 71000 M\u00e2con",
    "sg:city":"Sanc\u00e9",
    "sg:orig_category":"Non-Classified Establishments",
    "sg:phone":"+33 3 85 34 47 76",
    "sg:postcode":"71000",
    "sg:province":"Bourgogne",
    "wof:name":"Maringue - Sagetat S.a.",
    "wof:placetype":"venue"
},
  "geometry": {"coordinates":[4.833055,46.303043],"type":"Point"}
}