{
  "type": "Feature",
  "properties": {
    "iso:country":"FR",
    "sg:address":"12, Chemin du Haut de Saint Denis, 93300 Aubervilliers",
    "sg:orig_category":"Non-Classified Establishments",
    "sg:phone":"+33 1 48 33 13 37",
    "sg:province":"Ile de France",
    "wof:name":"Num\u00e9ric S.a.",
    "wof:placetype":"venue"
},
  "geometry": {"coordinates":[2.368472,48.922626],"type":"Point"}
}