{
  "type": "Feature",
  "properties": {
    "addr:full":"42, Rue Jean Monnet, 68100 Mulhouse Mulhouse Alsace 68100",
    "addr:housenumber":"42",
    "addr:postcode":"68100;68100",
    "addr:street":"Rue Jean Monnet",
    "iso:country":"FR",
    "sg:address":"42, Rue Jean Monnet, 68100 Mulhouse",
    "sg:city":"Mulhouse",
    "sg:orig_category":"Unclassifiable Establishments",
    "sg:phone":"+33 3 89 33 52 52",
    "sg:postcode":"68100",
    "sg:province":"Alsace",
    "wof:name":"Schneider Et Boisson R\u00e9unis S.a.",
    "wof:placetype":"venue"
},
  "geometry": {"coordinates":[7.346073,47.75124],"type":"Point"}
}