{
  "type": "Feature",
  "properties": {
    "addr:full":"ZI le Rival La C\u00f4te Saint Andr\u00e9 Rhone-Alpes 38260",
    "addr:postcode":"38260",
    "addr:street":"Zi Le Rival La",
    "iso:country":"FR",
    "sg:address":"ZI le Rival",
    "sg:city":"La C\u00f4te Saint Andr\u00e9",
    "sg:orig_category":"Unclassifiable Establishments",
    "sg:phone":"+33 4 74 20 42 59",
    "sg:postcode":"38260",
    "sg:province":"Rhone-Alpes",
    "wof:name":"Protect M\u00e9tal S.a.",
    "wof:placetype":"venue"
},
  "geometry": {"coordinates":[5.261475,45.392185],"type":"Point"}
}