{
  "type": "Feature",
  "properties": {
    "iso:country":"FR",
    "sg:address":"55, Rue L\u00e9on Jost, 44300 Nantes",
    "sg:orig_category":"Non-Classified Establishments",
    "sg:phone":"+33 2 40 40 05 61",
    "sg:province":"Pays de Loire",
    "wof:name":"Graphy Prim' Saint Donatien S.a.",
    "wof:placetype":"venue"
},
  "geometry": {"coordinates":[-1.568667,47.238422],"type":"Point"}
}