{
  "type": "Feature",
  "properties": {
    "addr:full":"31 rue Malaingre 52800 NOGENT Champagne",
    "addr:housenumber":"31",
    "addr:postcode":"52800",
    "addr:street":"Rue Malaingre",
    "iso:country":"FR",
    "sg:address":"31 rue Malaingre 52800 NOGENT",
    "sg:classifiers":[
        {
            "category":"Wholesale",
            "subcategory":"Medical Equipment & Supplies",
            "type":"Manufacturing & Wholesale Goods"
        }
    ],
    "sg:phone":"+33 3 25 31 81 04",
    "sg:province":"Champagne",
    "sg:tags":[
        "instrument",
        "surgical"
    ],
    "wof:name":"Etablissement Oury Guy\u00e9 Et Fils Sa",
    "wof:placetype":"venue"
},
  "geometry": {"coordinates":[5.344737,48.028095],"type":"Point"}
}