{
  "type": "Feature",
  "properties": {
    "addr:full":"16, Rue Christian Huygens, 37000 Tours Tours Centre 37000",
    "addr:housenumber":"16",
    "addr:postcode":"37000;37000",
    "addr:street":"Rue Christian Huygens",
    "iso:country":"FR",
    "sg:address":"16, Rue Christian Huygens, 37000 Tours",
    "sg:city":"Tours",
    "sg:orig_category":"Unclassifiable Establishments",
    "sg:phone":"+33 2 47 85 55 55",
    "sg:postcode":"37000",
    "sg:province":"Centre",
    "wof:name":"Salva Industries S.a.r.l.",
    "wof:placetype":"venue"
},
  "geometry": {"coordinates":[0.700242,47.437092],"type":"Point"}
}