{
  "type": "Feature",
  "properties": {
    "iso:country":"FR",
    "sg:address":"16 rue Gaston Castel 13016 Marseille",
    "sg:orig_category":"Fruits, Dried",
    "sg:phone":"+33 4 91 46 64 74",
    "sg:province":"Poitou-Charentes",
    "wof:name":"Color S.a.r.l.",
    "wof:placetype":"venue"
},
  "geometry": {"coordinates":[5.335855,43.356899],"type":"Point"}
}