{
  "type": "Feature",
  "properties": {
    "iso:country":"FR",
    "sg:address":"B.P. 57, 74963 Cran Gevrier C\u00e9dex^^8 bis, Rte des Creuses, 74960 Cran Gevrier",
    "sg:orig_category":"Non-Classified Establishments",
    "sg:phone":"+33 4 50 52 27 12",
    "sg:postcode":"74960",
    "sg:province":"Rhone-Alpes",
    "wof:name":"I.p.m. S.a.r.l. - Isolation Plaquiste Menuiserie",
    "wof:placetype":"venue"
},
  "geometry": {"coordinates":[6.10647,45.907654],"type":"Point"}
}