{
  "type": "Feature",
  "properties": {
    "addr:full":"B.P. 13, 52290 Eclaron Braucourt Sainte Livi\u00e8re^^46bis, Rue de la Gare, 52290 Eclaron Braucourt Sain Champagne 52290",
    "addr:postcode":"52290;52290;52290",
    "addr:street":"B.P. 13;Rue De La Gare",
    "iso:country":"FR",
    "sg:address":"B.P. 13, 52290 Eclaron Braucourt Sainte Livi\u00e8re^^46bis, Rue de la Gare, 52290 Eclaron Braucourt Sain",
    "sg:orig_category":"Non-Classified Establishments",
    "sg:phone":"+33 3 25 05 20 16",
    "sg:postcode":"52290",
    "sg:province":"Champagne",
    "wof:name":"Entreprise Boulogne S.a.",
    "wof:placetype":"venue"
},
  "geometry": {"coordinates":[4.86946,48.589443],"type":"Point"}
}