{
  "type": "Feature",
  "properties": {
    "addr:full":"28 rue Charles Bass\u00e9e 94120 Fontenay sous Bois Ile de France 94120",
    "addr:housenumber":"28",
    "addr:postcode":"94120;94120",
    "addr:street":"Rue Charles Basse\u0301E;Bois Ile De France",
    "iso:country":"FR",
    "sg:address":"28 rue Charles Bass\u00e9e 94120 Fontenay sous Bois",
    "sg:classifiers":[
        {
            "category":"Manufacturing",
            "subcategory":"Tools & Machinery",
            "type":"Manufacturing & Wholesale Goods"
        }
    ],
    "sg:phone":"+33 1 48 76 28 04",
    "sg:postcode":"94120",
    "sg:province":"Ile de France",
    "sg:tags":[
        "fine-boring"
    ],
    "wof:name":"Outillage Magafor Sa",
    "wof:placetype":"venue"
},
  "geometry": {"coordinates":[2.467721,48.848988],"type":"Point"}
}