{
  "type": "Feature",
  "properties": {
    "addr:full":"4 Rue Brunel Paris Ile de France 75017",
    "addr:housenumber":"4",
    "addr:postcode":"75017",
    "addr:street":"Rue Brunel",
    "iso:country":"FR",
    "sg:address":"4 Rue Brunel",
    "sg:city":"Paris",
    "sg:classifiers":[
        {
            "category":"Banks & Credit Unions",
            "subcategory":"Financial Services",
            "type":"Services"
        }
    ],
    "sg:phone":"+33 1 48 88 44 44",
    "sg:postcode":"75017",
    "sg:province":"Ile de France",
    "sg:tags":[
        "banking",
        "finance",
        "insurance"
    ],
    "wof:name":"Borloo Saigne & Associ\u00c9s",
    "wof:placetype":"venue"
},
  "geometry": {"coordinates":[2.289138,48.876274],"type":"Point"}
}