{
  "type": "Feature",
  "properties": {
    "iso:country":"FR",
    "sg:address":"SIAUGUES ST ROMAIN 43300 SIAUGUES STE MARIE",
    "sg:city":"Chanteuges",
    "sg:classifiers":[
        {
            "category":"Manufacturing",
            "subcategory":"Metals",
            "type":"Manufacturing & Wholesale Goods"
        }
    ],
    "sg:phone":"+33 4 71 74 21 09",
    "sg:postcode":"43300",
    "sg:province":"Auvergne",
    "sg:tags":[
        "finishing",
        "surface"
    ],
    "wof:name":"P.e.m. Sas",
    "wof:placetype":"venue"
},
  "geometry": {"coordinates":[3.6325,45.0937],"type":"Point"}
}