{
  "type": "Feature",
  "properties": {
    "addr:full":"9, Rue du Colmeau, 89100 Nailly Nailly Bourgogne 89100",
    "addr:housenumber":"9",
    "addr:postcode":"89100;89100",
    "addr:street":"Rue Du Colmeau",
    "iso:country":"FR",
    "sg:address":"9, Rue du Colmeau, 89100 Nailly",
    "sg:city":"Nailly",
    "sg:orig_category":"Non-Classified Establishments",
    "sg:phone":"+33 3 86 97 02 13",
    "sg:postcode":"89100",
    "sg:province":"Bourgogne",
    "wof:name":"Michel Alain Denis",
    "wof:placetype":"venue"
},
  "geometry": {"coordinates":[3.216855,48.220833],"type":"Point"}
}