{
  "type": "Feature",
  "properties": {
    "iso:country":"FR",
    "sg:address":"52 rue Beno\u00eet Malon 94250 Gentilly",
    "sg:classifiers":[
        {
            "category":"Home & Garden",
            "subcategory":"Carpets & Floor Coverings",
            "type":"Retail Goods"
        }
    ],
    "sg:phone":"+33 1 49 86 00 26",
    "sg:province":"Ile de France",
    "sg:tags":[
        "tile",
        "ceramic",
        "printed"
    ],
    "wof:name":"Formes Prospective Diffusion Ceramique Sarl",
    "wof:placetype":"venue"
},
  "geometry": {"coordinates":[2.341243,48.815605],"type":"Point"}
}