{
  "type": "Feature",
  "properties": {
    "addr:full":"Rue De L'Industrie 14500 Vire Vire Basse Normandie 14500",
    "addr:postcode":"14500;14500",
    "addr:street":"Rue De L'Industrie",
    "iso:country":"FR",
    "sg:address":"Rue De L'Industrie 14500 Vire",
    "sg:city":"Vire",
    "sg:classifiers":[
        {
            "category":"Government",
            "subcategory":"Department Of Motor Vehicles",
            "type":"Public Place"
        }
    ],
    "sg:phone":"+33 2 31 66 13 20",
    "sg:postcode":"14500",
    "sg:province":"Basse Normandie",
    "sg:tags":[
        "equipment",
        "industrial",
        "transport",
        "motor-cars"
    ],
    "wof:name":"Aries Meca",
    "wof:placetype":"venue"
},
  "geometry": {"coordinates":[-0.88219,48.854107],"type":"Point"}
}