{
  "type": "Feature",
  "properties": {
    "addr:full":"7 Avenue Du Lac Parentis En Born Aquitaine 40160",
    "addr:housenumber":"7",
    "addr:postcode":"40160",
    "addr:street":"Avenue Du Lac Parentis En Born",
    "iso:country":"FR",
    "sg:address":"7 Avenue Du Lac",
    "sg:city":"Parentis En Born",
    "sg:classifiers":[
        {
            "category":"Banks & Credit Unions",
            "subcategory":"Financial Services",
            "type":"Services"
        }
    ],
    "sg:phone":"+33 5 58 78 49 67",
    "sg:postcode":"40160",
    "sg:province":"Aquitaine",
    "sg:tags":[
        "banking",
        "finance",
        "insurance"
    ],
    "wof:name":"Societe Fiduciaire Nationale D'expertise Comptable Fidexpert (fid)",
    "wof:placetype":"venue"
},
  "geometry": {"coordinates":[-1.075824,44.348518],"type":"Point"}
}