{
  "type": "Feature",
  "properties": {
    "iso:country":"FR",
    "sg:address":"13 Cours La Fayette; Lyon; 69006",
    "sg:classifiers":[
        {
            "category":"Banks & Credit Unions",
            "subcategory":"Bank",
            "type":"Services"
        }
    ],
    "sg:phone":"+33 4 78 52 47 42",
    "sg:province":"Rhone-Alpes",
    "wof:name":"Banco Pinto, & Sotto Mayor",
    "wof:placetype":"venue"
},
  "geometry": {"coordinates":[4.849785,45.769245],"type":"Point"}
}