{
  "type": "Feature",
  "properties": {
    "iso:country":"FR",
    "sg:address":"Quai Armand Lalande Hangar G2 Bsns A Flot 33300 Bordeaux",
    "sg:city":"Bordeaux",
    "sg:classifiers":[
        {
            "category":"Professional",
            "subcategory":"Printing & Photocopies",
            "type":"Services"
        }
    ],
    "sg:phone":"+33 5 56 11 20 00",
    "sg:postcode":"33300",
    "sg:province":"Aquitaine",
    "sg:tags":[
        "machine",
        "engineering",
        "-",
        "mechanical"
    ],
    "wof:name":"Sam L'atelier Numerique",
    "wof:placetype":"venue"
},
  "geometry": {"coordinates":[-0.56244,44.87672],"type":"Point"}
}