{
  "type": "Feature",
  "properties": {
    "addr:full":"La Rivi\u00e8re de Mansac Mansac Limousin 19520",
    "addr:postcode":"19520",
    "iso:country":"FR",
    "sg:address":"La Rivi\u00e8re de Mansac",
    "sg:city":"Mansac",
    "sg:orig_category":"Unclassifiable Establishments",
    "sg:phone":"+33 5 55 85 20 48",
    "sg:postcode":"19520",
    "sg:province":"Limousin",
    "wof:name":"Constructions M\u00e9talliques Pommarel S.a.r.l.",
    "wof:placetype":"venue"
},
  "geometry": {"coordinates":[1.306292,45.143715],"type":"Point"}
}