{
  "type": "Feature",
  "properties": {
    "addr:full":"87 Av De La Grande Arm\u00e9e 75782 Paris Cedex 16 Haute Normandie",
    "addr:postcode":"75782",
    "addr:street":"87 Av De La Grande Arme\u0301E",
    "iso:country":"FR",
    "sg:address":"87 Av De La Grande Arm\u00e9e 75782 Paris Cedex 16",
    "sg:classifiers":[
        {
            "category":"Shopping",
            "subcategory":"Clothing, Apparel, & Fashions",
            "type":"Retail Goods"
        }
    ],
    "sg:phone":"+33 1 40 67 22 00",
    "sg:province":"Haute Normandie",
    "sg:tags":[
        "textile",
        "clothing",
        "clothes"
    ],
    "wof:name":"Poloco Sas",
    "wof:placetype":"venue"
},
  "geometry": {"coordinates":[2.28423,48.877064],"type":"Point"}
}