{
  "type": "Feature",
  "properties": {
    "addr:full":"R Gabriel Faur\u00e9 54140 Jarville La Malgrange Lorraine",
    "addr:postcode":"54140",
    "iso:country":"FR",
    "sg:address":"R Gabriel Faur\u00e9 54140 Jarville La Malgrange",
    "sg:classifiers":[
        {
            "category":"Manufacturing",
            "subcategory":"Printing",
            "type":"Manufacturing & Wholesale Goods"
        }
    ],
    "sg:phone":"+33 3 83 51 51 81",
    "sg:province":"Lorraine",
    "sg:tags":[
        "publishing"
    ],
    "wof:name":"Nancy Print Sa",
    "wof:placetype":"venue"
},
  "geometry": {"coordinates":[6.213245,48.66745],"type":"Point"}
}