{
  "type": "Feature",
  "properties": {
    "addr:full":"B.P. 2, 57410 Petit R\u00e9derching^^10, Rue du Stade, 57410 Petit R\u00e9derching Lorraine 57410",
    "addr:housenumber":"2",
    "addr:postcode":"57410;57410;57410",
    "addr:street":"B.P.;Rue Du Stade",
    "iso:country":"FR",
    "sg:address":"B.P. 2, 57410 Petit R\u00e9derching^^10, Rue du Stade, 57410 Petit R\u00e9derching",
    "sg:orig_category":"Non-Classified Establishments",
    "sg:phone":"+33 3 87 09 82 22",
    "sg:postcode":"57410",
    "sg:province":"Lorraine",
    "wof:name":"'s' Garnitures - Spieldenner Garnitures S.a.r.l.",
    "wof:placetype":"venue"
},
  "geometry": {"coordinates":[7.276636,49.045319],"type":"Point"}
}