{
  "type": "Feature",
  "properties": {
    "iso:country":"FR",
    "sg:address":"Rue Ampere Z I De La Maine 76150 Maromme",
    "sg:classifiers":[
        {
            "category":"Professional",
            "subcategory":"Printing & Photocopies",
            "type":"Services"
        }
    ],
    "sg:phone":"+33 2 35 74 00 67",
    "sg:province":"Haute Normandie",
    "sg:tags":[
        "publishing"
    ],
    "wof:name":"Hachette Livre",
    "wof:placetype":"venue"
},
  "geometry": {"coordinates":[-97.32923099999999,32.748508],"type":"Point"}
}