{
  "type": "Feature",
  "properties": {
    "addr:full":"Le Village 26300 Charpey Rhone-Alpes",
    "addr:postcode":"26300",
    "addr:street":"Le Village",
    "iso:country":"FR",
    "sg:address":"Le Village 26300 Charpey",
    "sg:classifiers":[
        {
            "category":"Home & Garden",
            "subcategory":"Furniture",
            "type":"Retail Goods"
        }
    ],
    "sg:phone":"+33 4 75 59 87 91",
    "sg:province":"Rhone-Alpes",
    "sg:tags":[
        "wood"
    ],
    "wof:name":"Atelier Thierry Goux",
    "wof:placetype":"venue"
},
  "geometry": {"coordinates":[5.09157,44.938511],"type":"Point"}
}