{
  "type": "Feature",
  "properties": {
    "addr:full":"11 R Des Immeubles Industriels Paris Ile de France 75011",
    "addr:housenumber":"11",
    "addr:postcode":"75011",
    "addr:street":"R Des Immeubles Industriels",
    "iso:country":"FR",
    "sg:address":"11 R Des Immeubles Industriels",
    "sg:city":"Paris",
    "sg:classifiers":[
        {
            "category":"Banks & Credit Unions",
            "subcategory":"Financial Services",
            "type":"Services"
        }
    ],
    "sg:phone":"+33 1 43 73 90 79",
    "sg:postcode":"75011",
    "sg:province":"Ile de France",
    "sg:tags":[
        "banking",
        "finance",
        "insurance"
    ],
    "wof:name":"Cie Expertise Comptables Et Financieres",
    "wof:placetype":"venue"
},
  "geometry": {"coordinates":[2.392464,48.849716],"type":"Point"}
}