{
  "type": "Feature",
  "properties": {
    "iso:country":"FR",
    "sg:address":"Le Krystal 06271 VILLENEUVE LOUBET CEDEX",
    "sg:classifiers":[
        {
            "category":"Organizations",
            "subcategory":"Professional Association",
            "type":"Services"
        }
    ],
    "sg:phone":"+33 4 93 20 84 00",
    "sg:province":"Provence-Alpes-C\u00f4te d'Azur",
    "sg:tags":[
        "department",
        "legal",
        "software"
    ],
    "wof:name":"T\u00e9l\u00e9 Big Sa",
    "wof:placetype":"venue"
},
  "geometry": {"coordinates":[7.12296,43.657749],"type":"Point"}
}