{
  "type": "Feature",
  "properties": {
    "iso:country":"FR",
    "sg:address":"Av. des Templiers - Parc d'Activit\u00e9 Napollon",
    "sg:city":"Aubagne",
    "sg:orig_category":"Unclassifiable Establishments",
    "sg:phone":"+33 4 42 18 70 90",
    "sg:postcode":"13670",
    "sg:province":"Provence-Alpes-C\u00f4te d'Azur",
    "wof:name":"Lartigot S.a.",
    "wof:placetype":"venue"
},
  "geometry": {"coordinates":[5.587868,43.315205],"type":"Point"}
}