{
  "type": "Feature",
  "properties": {
    "iso:country":"FR",
    "sg:address":"5 rue du Canal 68780 SENTHEIM",
    "sg:city":"Sentheim",
    "sg:classifiers":[
        {
            "category":"Autos & Motor Vehicles",
            "subcategory":"Automobile Sales",
            "type":"Retail Goods"
        }
    ],
    "sg:phone":"+33 3 89 38 57 00",
    "sg:postcode":"68780",
    "sg:province":"Alsace",
    "sg:tags":[
        "passenger",
        "car"
    ],
    "wof:name":"Automobiles Dangel Sa",
    "wof:placetype":"venue"
},
  "geometry": {"coordinates":[7.047345,47.756897],"type":"Point"}
}