{
  "type": "Feature",
  "properties": {
    "addr:full":"Zone Industrielle 45210 Ferri\u00e8res La Selle-en-Hermoy Centre 45210",
    "addr:housenumber":"selle-en-hermoy",
    "addr:postcode":"45210;45210",
    "addr:street":"Zone Industrielle",
    "iso:country":"FR",
    "sg:address":"Zone Industrielle 45210 Ferri\u00e8res",
    "sg:city":"La Selle-en-Hermoy",
    "sg:orig_category":"Miscellaneous Products",
    "sg:phone":"+33 2 38 96 68 45",
    "sg:postcode":"45210",
    "sg:province":"Centre",
    "wof:name":"Gero Cnditionnement Tercodis Sa",
    "wof:placetype":"venue"
},
  "geometry": {"coordinates":[2.924385,48.001736],"type":"Point"}
}