{
  "type": "Feature",
  "properties": {
    "iso:country":"FR",
    "sg:address":"7 rue Ren\u00e9 Cassin 44600 ST NAZAIRE",
    "sg:classifiers":[
        {
            "category":"Wholesale",
            "subcategory":"Machinery & Supplies",
            "type":"Manufacturing & Wholesale Goods"
        }
    ],
    "sg:phone":"+33 2 40 66 53 37",
    "sg:postcode":"44600",
    "sg:province":"Pays de Loire",
    "sg:tags":[
        "agricultural",
        "equipment"
    ],
    "wof:name":"Imelec Sarl",
    "wof:placetype":"venue"
},
  "geometry": {"coordinates":[-2.20199,47.290031],"type":"Point"}
}