{
  "type": "Feature",
  "properties": {
    "addr:full":"Au Croyat 01290 Saint Jean sur Veyle Rhone-Alpes 01290",
    "addr:postcode":"01290;01290",
    "addr:street":"Saint Jean Sur Veyle Rhone-Alpes",
    "iso:country":"FR",
    "sg:address":"Au Croyat 01290 Saint Jean sur Veyle",
    "sg:orig_category":"Non-Classified Establishments",
    "sg:phone":"+33 3 85 31 58 88",
    "sg:postcode":"01290",
    "sg:province":"Rhone-Alpes",
    "wof:name":"Entreprise Poncet Jean Bernard",
    "wof:placetype":"venue"
},
  "geometry": {"coordinates":[4.914649,46.262779],"type":"Point"}
}