{
  "type": "Feature",
  "properties": {
    "iso:country":"FR",
    "sg:address":"7 rue Lacaille 75017 Paris",
    "sg:orig_category":"Halogen Spotlights",
    "sg:phone":"+33 1 42 29 44 44",
    "sg:postcode":"75017",
    "sg:province":"Ile de France",
    "wof:name":"Technic Electronic Conseil Sa",
    "wof:placetype":"venue"
},
  "geometry": {"coordinates":[2.324979,48.893166],"type":"Point"}
}