{
  "type": "Feature",
  "properties": {
    "iso:country":"FR",
    "sg:address":"76570 Ste Austreberthe",
    "sg:classifiers":[
        {
            "category":"Professional",
            "subcategory":"Engineering",
            "type":"Services"
        }
    ],
    "sg:phone":"+33 2 35 91 24 87",
    "sg:postcode":"76570",
    "sg:province":"Haute Normandie",
    "sg:tags":[
        "machine",
        "-",
        "environment",
        "equipment",
        "machinery",
        "mechanical"
    ],
    "wof:name":"Etablissements Biard Roy",
    "wof:placetype":"venue"
},
  "geometry": {"coordinates":[0.9746,49.598045],"type":"Point"}
}