{
  "type": "Feature",
  "properties": {
    "iso:country":"FR",
    "sg:address":"8, Rue Louvois, 75002 Paris",
    "sg:orig_category":"Unclassifiable Establishments",
    "sg:phone":"+33 1 42 60 05 90",
    "sg:province":"Ile de France",
    "wof:name":"Help International S.a.",
    "wof:placetype":"venue"
},
  "geometry": {"coordinates":[2.337152,48.868378],"type":"Point"}
}