{
  "type": "Feature",
  "properties": {
    "iso:country":"FR",
    "sg:address":"ZI des Moli\u00e8res",
    "sg:city":"Miramas",
    "sg:orig_category":"Non-Classified Establishments",
    "sg:phone":"+33 4 90 58 24 00",
    "sg:postcode":"13140",
    "sg:province":"Nord Pas-de-Calais",
    "wof:name":"Micro M\u00e9ca S.a.r.l.",
    "wof:placetype":"venue"
},
  "geometry": {"coordinates":[5.00306,43.584637],"type":"Point"}
}