{
  "type": "Feature",
  "properties": {
    "addr:full":"89100 Sens Sens Bourgogne 89100",
    "addr:postcode":"89100;89100",
    "iso:country":"FR",
    "sg:address":"89100 Sens",
    "sg:city":"Sens",
    "sg:classifiers":[
        {
            "category":"Shopping",
            "subcategory":"Photographic Equipment",
            "type":"Retail Goods"
        }
    ],
    "sg:phone":"+33 3 86 65 01 44",
    "sg:postcode":"89100",
    "sg:province":"Bourgogne",
    "sg:tags":[
        "photo-engravings"
    ],
    "wof:name":"Publigrafa Sas",
    "wof:placetype":"venue"
},
  "geometry": {"coordinates":[3.29621,48.205719],"type":"Point"}
}