{
  "type": "Feature",
  "properties": {
    "iso:country":"FR",
    "sg:address":"10, Rue de Soultz, 68100 Mulhouse",
    "sg:city":"Mulhouse",
    "sg:orig_category":"Unclassifiable Establishments",
    "sg:phone":"+33 3 89 62 33 33",
    "sg:postcode":"68100",
    "sg:province":"Alsace",
    "wof:name":"Manurhin K.m.x. S.a.",
    "wof:placetype":"venue"
},
  "geometry": {"coordinates":[7.323549,47.76535],"type":"Point"}
}