{
  "type": "Feature",
  "properties": {
    "addr:full":"255, Bd Robert Ballanger, 93421 Villepinte C\u00e9dex Vill\u00e9 Alsace 67220",
    "addr:housenumber":"255",
    "addr:postcode":"93421;67220",
    "addr:street":"Bd Robert Ballanger",
    "iso:country":"FR",
    "sg:address":"255, Bd Robert Ballanger, 93421 Villepinte C\u00e9dex",
    "sg:city":"Vill\u00e9",
    "sg:orig_category":"Unclassifiable Establishments",
    "sg:phone":"+33 1 49 63 59 00",
    "sg:postcode":"67220",
    "sg:province":"Alsace",
    "wof:name":"T.r.a. S.a. - Transport Rapide Automobile",
    "wof:placetype":"venue"
},
  "geometry": {"coordinates":[2.558904,48.962353],"type":"Point"}
}