{
  "type": "Feature",
  "properties": {
    "addr:full":"Zi Appoigny Bourgogne 89380",
    "addr:postcode":"89380",
    "addr:street":"Bourgogne",
    "iso:country":"FR",
    "sg:address":"Zi",
    "sg:city":"Appoigny",
    "sg:classifiers":[
        {
            "category":"Marine",
            "type":"Transportation"
        }
    ],
    "sg:phone":"+33 3 86 53 19 70",
    "sg:postcode":"89380",
    "sg:province":"Bourgogne",
    "sg:tags":[
        "transport",
        "sea"
    ],
    "wof:name":"Transports Alloin Sa",
    "wof:placetype":"venue"
},
  "geometry": {"coordinates":[3.52591,47.877048],"type":"Point"}
}