{
  "type": "Feature",
  "properties": {
    "iso:country":"FR",
    "sg:address":"Chemin Du Moulin 35580 Guichen",
    "sg:city":"Guichen",
    "sg:classifiers":[
        {
            "category":"Farming",
            "subcategory":"Farm & Veterinary Services",
            "type":"Manufacturing & Wholesale Goods"
        }
    ],
    "sg:phone":"+33 2 99 42 84 00",
    "sg:postcode":"35580",
    "sg:province":"Bretagne",
    "sg:tags":[
        "food",
        "product",
        "breeding",
        "animal",
        "related"
    ],
    "wof:name":"Sopral",
    "wof:placetype":"venue"
},
  "geometry": {"coordinates":[-1.788483,47.905689],"type":"Point"}
}