{
  "type": "Feature",
  "properties": {
    "addr:full":"Domaine Garenne 18300 Verdigny Verdigny Centre 18300",
    "addr:housenumber":"verdigny",
    "addr:postcode":"18300;18300",
    "addr:street":"Domaine Garenne",
    "iso:country":"FR",
    "sg:address":"Domaine Garenne 18300 Verdigny",
    "sg:city":"Verdigny",
    "sg:classifiers":[
        {
            "category":"Food Court",
            "type":"Food & Drink"
        }
    ],
    "sg:phone":"+33 2 48 79 35 79",
    "sg:postcode":"18300",
    "sg:province":"Centre",
    "sg:tags":[
        "product",
        "related"
    ],
    "wof:name":"Reverdy Bernard-noel (domaine De La Garenne)",
    "wof:placetype":"venue"
},
  "geometry": {"coordinates":[2.810835,47.348621],"type":"Point"}
}