{
  "type": "Feature",
  "properties": {
    "addr:full":"18, Rue Saint Joseph, 59700 Marcq en Baroeul Nord Pas-de-Calais",
    "addr:housenumber":"18",
    "addr:postcode":"59700",
    "addr:street":"Rue Saint Joseph;En Baroeul Nord",
    "iso:country":"FR",
    "sg:address":"18, Rue Saint Joseph, 59700 Marcq en Baroeul",
    "sg:orig_category":"Unclassifiable Establishments",
    "sg:phone":"+33 3 20 21 97 60",
    "sg:province":"Nord Pas-de-Calais",
    "wof:name":"So.si.dec. S.a. - Soci\u00e9t\u00e9 De Signalisation Et D'eclairage",
    "wof:placetype":"venue"
},
  "geometry": {"coordinates":[3.075293,50.667995],"type":"Point"}
}