{
  "type": "Feature",
  "properties": {
    "iso:country":"FR",
    "sg:address":"ZA de la Boissi\u00e8re",
    "sg:city":"Morlaix",
    "sg:orig_category":"Unclassifiable Establishments",
    "sg:phone":"+33 2 98 88 40 42",
    "sg:postcode":"29600",
    "sg:province":"Bretagne",
    "wof:name":"Pinault Ouest S.n.c.",
    "wof:placetype":"venue"
},
  "geometry": {"coordinates":[-3.826259,48.577026],"type":"Point"}
}