{
  "type": "Feature",
  "properties": {
    "addr:full":"19, Rue Edmond Michelet, 33000 Bordeaux Bordeaux Aquitaine 33000",
    "addr:housenumber":"19",
    "addr:postcode":"33000;33000",
    "addr:street":"Rue Edmond Michelet",
    "iso:country":"FR",
    "sg:address":"19, Rue Edmond Michelet, 33000 Bordeaux",
    "sg:city":"Bordeaux",
    "sg:orig_category":"Unclassifiable Establishments",
    "sg:phone":"+33 5 56 00 87 50",
    "sg:postcode":"33000",
    "sg:province":"Aquitaine",
    "wof:name":"V\u00e9diorbis S.a.s.",
    "wof:placetype":"venue"
},
  "geometry": {"coordinates":[-0.57835,44.830936],"type":"Point"}
}