{
  "type": "Feature",
  "properties": {
    "iso:country":"FR",
    "sg:address":"B.P. 1212, 49306 Cholet C\u00e9dex^^2, Av. de la Tessoualle, 49300 Cholet",
    "sg:orig_category":"Non-Classified Establishments",
    "sg:phone":"+33 2 41 65 85 32",
    "sg:province":"Pays de Loire",
    "wof:name":"Maugin S.a.",
    "wof:placetype":"venue"
},
  "geometry": {"coordinates":[-0.892689,46.99659],"type":"Point"}
}