{
  "type": "Feature",
  "properties": {
    "iso:country":"FR",
    "sg:address":"4, Av. des Cravailles - Les Bureaux du Lac B\u00e2t. 8, 33520 Bruges",
    "sg:city":"Bruges",
    "sg:orig_category":"Non-Classified Establishments",
    "sg:phone":"+33 5 56 69 25 00",
    "sg:postcode":"33520",
    "sg:province":"Aquitaine",
    "wof:name":"Isagri Bordeaux S.a.",
    "wof:placetype":"venue"
},
  "geometry": {"coordinates":[-0.610265,44.887768],"type":"Point"}
}