{
  "type": "Feature",
  "properties": {
    "addr:full":"18, Rue du Billon, 69720 Saint Laurent de Mure Rhone-Alpes",
    "addr:housenumber":"18",
    "addr:postcode":"69720",
    "addr:street":"Rue Du Billon;Rhone-Alpes",
    "iso:country":"FR",
    "sg:address":"18, Rue du Billon, 69720 Saint Laurent de Mure",
    "sg:orig_category":"Non-Classified Establishments",
    "sg:phone":"+33 4 78 40 93 47",
    "sg:province":"Rhone-Alpes",
    "wof:name":"I.t.l.c. S.a.r.l.",
    "wof:placetype":"venue"
},
  "geometry": {"coordinates":[5.039795,45.682533],"type":"Point"}
}