{
  "type": "Feature",
  "properties": {
    "addr:full":"49 Boulevard Des Alpes 38240 Meylan Rhone-Alpes 38240",
    "addr:housenumber":"49",
    "addr:postcode":"38240;38240",
    "addr:street":"Boulevard Des Alpes",
    "iso:country":"FR",
    "sg:address":"49 Boulevard Des Alpes 38240 Meylan",
    "sg:classifiers":[
        {
            "category":"Utilities",
            "type":"Services"
        }
    ],
    "sg:phone":"+33 810 00 07 77",
    "sg:postcode":"38240",
    "sg:province":"Rhone-Alpes",
    "sg:tags":[
        "raw",
        "energy",
        "material"
    ],
    "wof:name":"Compagnie Generale Des Eaux",
    "wof:placetype":"venue"
},
  "geometry": {"coordinates":[5.775696,45.204479],"type":"Point"}
}