{
  "type": "Feature",
  "properties": {
    "iso:country":"FR",
    "sg:address":"rue Kroedemenouck 59180 Cappelle La Grande",
    "sg:classifiers":[
        {
            "category":"Train Station",
            "subcategory":"Rail",
            "type":"Transportation"
        }
    ],
    "sg:phone":"+33 3 28 29 24 30",
    "sg:postcode":"59180",
    "sg:province":"Nord Pas-de-Calais",
    "sg:tags":[
        "casting",
        "bronze"
    ],
    "wof:name":"Vanywaede Sa",
    "wof:placetype":"venue"
},
  "geometry": {"coordinates":[2.364833,50.99826],"type":"Point"}
}