{
  "type": "Feature",
  "properties": {
    "iso:country":"FR",
    "sg:address":"Lieu Dit Les Marais 74410 St Jorioz",
    "sg:classifiers":[
        {
            "category":"Autos & Motor Vehicles",
            "subcategory":"Boat Sales",
            "type":"Retail Goods"
        }
    ],
    "sg:phone":"+33 4 50 77 23 63",
    "sg:postcode":"74410",
    "sg:province":"Rhone-Alpes",
    "sg:tags":[
        "equipment",
        "transport"
    ],
    "wof:name":"Savoie Marine",
    "wof:placetype":"venue"
},
  "geometry": {"coordinates":[6.180588,45.833733],"type":"Point"}
}