{
  "type": "Feature",
  "properties": {
    "addr:full":"475 ave du Prado; Marseille; 13001 Poitou-Charentes",
    "addr:housenumber":"475",
    "addr:postcode":"13001",
    "addr:street":"Ave Du Prado",
    "iso:country":"FR",
    "sg:address":"475 ave du Prado; Marseille; 13001",
    "sg:classifiers":[
        {
            "category":"Banks & Credit Unions",
            "subcategory":"Bank",
            "type":"Services"
        }
    ],
    "sg:phone":"+33 3391762884",
    "sg:province":"Poitou-Charentes",
    "wof:name":"Banque Nationale De Paris",
    "wof:placetype":"venue"
},
  "geometry": {"coordinates":[5.381528,43.265808],"type":"Point"}
}