{
  "type": "Feature",
  "properties": {
    "iso:country":"FR",
    "sg:address":"15, Chemin de Gondran, 13770 Fos sur Mer",
    "sg:orig_category":"Unclassifiable Establishments",
    "sg:phone":"+33 4 42 05 09 83",
    "sg:province":"Nebraska",
    "wof:name":"Sud Echafaudage S.a.r.l.",
    "wof:placetype":"venue"
},
  "geometry": {"coordinates":[-99.76664,41.48312],"type":"Point"}
}