{
  "type": "Feature",
  "properties": {
    "iso:country":"FR",
    "sg:address":"15, Av. de Norv\u00e8ge, 91940 Les Ulis",
    "sg:orig_category":"Unclassifiable Establishments",
    "sg:phone":"+33 1 69 18 51 00",
    "sg:province":"Ile de France",
    "wof:name":"Eurotherm Mesures S.a.",
    "wof:placetype":"venue"
},
  "geometry": {"coordinates":[2.169475,48.68161],"type":"Point"}
}