{
  "type": "Feature",
  "properties": {
    "iso:country":"FR",
    "sg:address":"95, Rue du Perry, 74800 Saint Pierre en Faucigny",
    "sg:orig_category":"Non-Classified Establishments",
    "sg:phone":"+33 4 50 97 05 13",
    "sg:province":"Rhone-Alpes",
    "wof:name":"Montessuit F. S.a.",
    "wof:placetype":"venue"
},
  "geometry": {"coordinates":[6.391886,46.071079],"type":"Point"}
}