{
  "type": "Feature",
  "properties": {
    "addr:full":"Zone Industrielle de la Glaci\u00e8re Foussemagne Franche Comt\u00e9 90150",
    "addr:postcode":"90150",
    "addr:street":"Zone Industrielle De La Glacie\u0300Re;Franche Comte\u0301",
    "iso:country":"FR",
    "sg:address":"Zone Industrielle de la Glaci\u00e8re",
    "sg:city":"Foussemagne",
    "sg:orig_category":"Non-Classified Establishments",
    "sg:phone":"+33 3 84 23 49 74",
    "sg:postcode":"90150",
    "sg:province":"Franche Comt\u00e9",
    "wof:name":"C.c.e. S.a. - C\u00e2blage Connectique Europ\u00e9en",
    "wof:placetype":"venue"
},
  "geometry": {"coordinates":[7.00695,47.634411],"type":"Point"}
}