{
  "type": "Feature",
  "properties": {
    "addr:full":"2 Pl De La Bourse 44000 Nantes Pays de Loire 44000",
    "addr:housenumber":"2",
    "addr:postcode":"44000;44000",
    "addr:street":"Pl De La Bourse",
    "iso:country":"FR",
    "sg:address":"2 Pl De La Bourse 44000 Nantes",
    "sg:classifiers":[
        {
            "category":"Farming",
            "subcategory":"Livestock Farm",
            "type":"Manufacturing & Wholesale Goods"
        }
    ],
    "sg:phone":"+33 2 51 82 14 00",
    "sg:postcode":"44000",
    "sg:province":"Pays de Loire",
    "sg:tags":[
        "agriculture"
    ],
    "wof:name":"Loiret Et Haentjens Sa",
    "wof:placetype":"venue"
},
  "geometry": {"coordinates":[-1.559134,47.212845],"type":"Point"}
}