{
  "type": "Feature",
  "properties": {
    "addr:full":"28, Rte de Steinbourg, 67700 Saverne Saverne Alsace 67700",
    "addr:housenumber":"28",
    "addr:postcode":"67700;67700",
    "addr:street":"Rte De Steinbourg",
    "iso:country":"FR",
    "sg:address":"28, Rte de Steinbourg, 67700 Saverne",
    "sg:city":"Saverne",
    "sg:orig_category":"Unclassifiable Establishments",
    "sg:phone":"+33 3 88 01 85 00",
    "sg:postcode":"67700",
    "sg:province":"Alsace",
    "wof:name":"Haemmerlin S.a.s.",
    "wof:placetype":"venue"
},
  "geometry": {"coordinates":[7.366026,48.739471],"type":"Point"}
}