{
  "type": "Feature",
  "properties": {
    "iso:country":"FR",
    "sg:address":"75 Avenue La Grande Armee 75116 Paris",
    "sg:classifiers":[
        {
            "category":"Autos & Motor Vehicles",
            "subcategory":"Automobile Sales",
            "type":"Retail Goods"
        }
    ],
    "sg:phone":"+33 1 40 66 55 11",
    "sg:province":"Haute Normandie",
    "sg:tags":[
        "equipment",
        "transport"
    ],
    "wof:name":"Ste Commerciale Automobile",
    "wof:placetype":"venue"
},
  "geometry": {"coordinates":[2.285296,48.876518],"type":"Point"}
}