{
  "type": "Feature",
  "properties": {
    "iso:country":"FR",
    "sg:address":"71 Av Charles De Gaulle 92130 Issy Les Moulineaux",
    "sg:classifiers":[
        {
            "category":"Health Services",
            "subcategory":"Medical Lab",
            "type":"Services"
        }
    ],
    "sg:phone":"+33 1 46 45 21 99",
    "sg:postcode":"92130",
    "sg:province":"Ile de France",
    "sg:tags":[
        "chemical",
        "pharmaceutical",
        "pharmacy"
    ],
    "wof:name":"Ste Exploit Laboratoires Jacques Logeais",
    "wof:placetype":"venue"
},
  "geometry": {"coordinates":[2.274726,48.879818],"type":"Point"}
}