{
  "type": "Feature",
  "properties": {
    "addr:full":"Bruy\u00e8res 71130 Neuvy Grandchamp Chapelle-au-Mans Bourgogne 71130",
    "addr:postcode":"71130;71130",
    "addr:street":"Bruye\u0300Res;Grandchamp;Bourgogne",
    "iso:country":"FR",
    "sg:address":"Bruy\u00e8res 71130 Neuvy Grandchamp",
    "sg:city":"Chapelle-au-Mans",
    "sg:classifiers":[
        {
            "category":"Shopping",
            "subcategory":"Clothing, Apparel, & Fashions",
            "type":"Retail Goods"
        }
    ],
    "sg:phone":"+33 3 85 84 39 39",
    "sg:postcode":"71130",
    "sg:province":"Bourgogne",
    "sg:tags":[
        "textile",
        "clothing",
        "clothes"
    ],
    "wof:name":"Gt Partenaires",
    "wof:placetype":"venue"
},
  "geometry": {"coordinates":[4.08623,46.557331],"type":"Point"}
}