{
  "type": "Feature",
  "properties": {
    "addr:full":"Z Activite Du Gault 43330 PONT SALOMON Pont-Salomon Auvergne 43330",
    "addr:postcode":"43330;43330",
    "addr:street":"Salomon Pont-Salomon",
    "iso:country":"FR",
    "sg:address":"Z Activite Du Gault 43330 PONT SALOMON",
    "sg:city":"Pont-Salomon",
    "sg:classifiers":[
        {
            "category":"Building & Trades",
            "subcategory":"Equipment Rental",
            "type":"Services"
        }
    ],
    "sg:phone":"+33 4 77 35 59 21",
    "sg:postcode":"43330",
    "sg:province":"Auvergne",
    "sg:tags":[
        "clothing",
        "industry",
        "knitting",
        "accessory"
    ],
    "wof:name":"Multitricot Eurl",
    "wof:placetype":"venue"
},
  "geometry": {"coordinates":[4.26105,45.358402],"type":"Point"}
}