{
  "type": "Feature",
  "properties": {
    "addr:full":"B\u00e2t L2 Avignon Provence-Alpes-C\u00f4te d'Azur 84000",
    "addr:housenumber":"ba\u0302t l2",
    "addr:postcode":"84000",
    "addr:street":"Avignon",
    "iso:country":"FR",
    "sg:address":"B\u00e2t L2",
    "sg:city":"Avignon",
    "sg:orig_category":"Unclassifiable Establishments",
    "sg:phone":"+33 4 90 88 13 02",
    "sg:postcode":"84000",
    "sg:province":"Provence-Alpes-C\u00f4te d'Azur",
    "wof:name":"Dole France",
    "wof:placetype":"venue"
},
  "geometry": {"coordinates":[4.806015,43.948753],"type":"Point"}
}