{
  "type": "Feature",
  "properties": {
    "iso:country":"FR",
    "sg:address":"43 rue du Landy 93210 La Plaine St Denis",
    "sg:city":"Plaine",
    "sg:classifiers":[
        {
            "category":"Mining & Drilling",
            "type":"Manufacturing & Wholesale Goods"
        }
    ],
    "sg:phone":"+33 1 41 62 41 62",
    "sg:postcode":"67420",
    "sg:province":"Alsace",
    "sg:tags":[
        "pick",
        "mechanical"
    ],
    "wof:name":"Etablissement Favre Sa",
    "wof:placetype":"venue"
},
  "geometry": {"coordinates":[2.361924,48.915306],"type":"Point"}
}