{
  "type": "Feature",
  "properties": {
    "iso:country":"FR",
    "sg:address":"Rte Estreys - ZA",
    "sg:city":"Espaly Saint Marcel",
    "sg:orig_category":"Unclassifiable Establishments",
    "sg:phone":"+33 4 71 02 28 66",
    "sg:postcode":"43000",
    "sg:province":"Auvergne",
    "wof:name":"Transports Visconte S.a.",
    "wof:placetype":"venue"
},
  "geometry": {"coordinates":[3.895839,45.017532],"type":"Point"}
}