{
  "type": "Feature",
  "properties": {
    "iso:country":"FR",
    "sg:address":"2 Rue De La Paix 75002 Paris",
    "sg:classifiers":[
        {
            "category":"Real Estate",
            "subcategory":"Architect",
            "type":"Services"
        }
    ],
    "sg:phone":"+33 1 42 61 58 45",
    "sg:province":"Ile de France",
    "sg:tags":[
        "textile",
        "clothing"
    ],
    "wof:name":"Petillault Sa",
    "wof:placetype":"venue"
},
  "geometry": {"coordinates":[2.330646,48.86845],"type":"Point"}
}