{
  "type": "Feature",
  "properties": {
    "iso:country":"FR",
    "sg:address":"Za La Courtilliere 62123 Beaumetz Les Loges",
    "sg:classifiers":[
        {
            "category":"Food & Beverages",
            "subcategory":"Groceries & Convenience Stores",
            "type":"Retail Goods"
        }
    ],
    "sg:phone":"+33 3 21 55 61 04",
    "sg:postcode":"62123",
    "sg:province":"Nord Pas-de-Calais",
    "sg:tags":[
        "product",
        "grain",
        "cereal",
        "related"
    ],
    "wof:name":"Comptoir Europeen De Dist En Elements Nutritifs Agricoles (cedena)",
    "wof:placetype":"venue"
},
  "geometry": {"coordinates":[2.655353,50.24345],"type":"Point"}
}