{
  "type": "Feature",
  "properties": {
    "iso:country":"FR",
    "sg:address":"2 rue Sainte-Genevi\u00e8ve 54600 Villers les Nancy",
    "sg:classifiers":[
        {
            "category":"Building & Trades",
            "subcategory":"Electrical",
            "type":"Services"
        }
    ],
    "sg:phone":"+33 3 83 28 66 94",
    "sg:postcode":"54600",
    "sg:province":"Lorraine",
    "sg:tags":[
        "tool",
        "high-quality"
    ],
    "wof:name":"Outiqua Sa",
    "wof:placetype":"venue"
},
  "geometry": {"coordinates":[6.16063,48.678337],"type":"Point"}
}