{
  "type": "Feature",
  "properties": {
    "iso:country":"FR",
    "sg:address":"69, Rue Albert Thomas, 51100 Reims",
    "sg:orig_category":"Unclassifiable Establishments",
    "sg:phone":"+33 3 26 85 78 78",
    "sg:province":"Champagne",
    "wof:name":"Bsn Glass Pack S.a.",
    "wof:placetype":"venue"
},
  "geometry": {"coordinates":[4.04862,49.232361],"type":"Point"}
}