{
  "type": "Feature",
  "properties": {
    "addr:full":"Rte De La Breque 76700 Gonfreville L Orcher Haute Normandie 76700",
    "addr:postcode":"76700;76700",
    "addr:street":"Rte De La Breque",
    "iso:country":"FR",
    "sg:address":"Rte De La Breque 76700 Gonfreville L Orcher",
    "sg:classifiers":[
        {
            "category":"Manufacturing",
            "subcategory":"Chemicals & Compounds",
            "type":"Manufacturing & Wholesale Goods"
        }
    ],
    "sg:phone":"+33 2 35 24 08 56",
    "sg:postcode":"76700",
    "sg:province":"Haute Normandie",
    "sg:tags":[
        "pharmaceutical",
        "chemistry",
        "-",
        "by-product"
    ],
    "wof:name":"Societe Normande De L'azote (sna)",
    "wof:placetype":"venue"
},
  "geometry": {"coordinates":[0.19577,49.481274],"type":"Point"}
}