{
  "type": "Feature",
  "properties": {
    "addr:full":"B.P. 51, 13880 Velaux^^ZA la Verdi\u00e8reII, 13880 Velaux Rhone-Alpes",
    "addr:postcode":"13880;13880",
    "addr:street":"B.P. 51",
    "iso:country":"FR",
    "sg:address":"B.P. 51, 13880 Velaux^^ZA la Verdi\u00e8reII, 13880 Velaux",
    "sg:orig_category":"Non-Classified Establishments",
    "sg:phone":"+33 4 42 74 72 22",
    "sg:province":"Rhone-Alpes",
    "wof:name":"T.w.o. S.a.r.l. - Travel World Organisation",
    "wof:placetype":"venue"
},
  "geometry": {"coordinates":[5.257606,43.523071],"type":"Point"}
}