{
  "type": "Feature",
  "properties": {
    "addr:full":"24, Rue de la Gare, 02250 Tavaux et Ponts\u00e9ricourt Picardie",
    "addr:housenumber":"24",
    "addr:postcode":"02250",
    "addr:street":"Rue De La Gare",
    "iso:country":"FR",
    "sg:address":"24, Rue de la Gare, 02250 Tavaux et Ponts\u00e9ricourt",
    "sg:orig_category":"Non-Classified Establishments",
    "sg:phone":"+33 3 23 20 03 80",
    "sg:province":"Picardie",
    "wof:name":"S.t.b. - Soci\u00e9t\u00e9 De Transformation Du Bois S.a.",
    "wof:placetype":"venue"
},
  "geometry": {"coordinates":[3.906213,49.72736],"type":"Point"}
}