{
  "type": "Feature",
  "properties": {
    "iso:country":"FR",
    "sg:address":"197, Rue Galli\u00e9ni, 92100 Boulogne Billancourt",
    "sg:orig_category":"Non-Classified Establishments",
    "sg:phone":"+33 1 46 04 94 66",
    "sg:postcode":"92100",
    "sg:province":"Ile de France",
    "wof:name":"B.r.c. Syst\u00e8mes S.a.r.l.",
    "wof:placetype":"venue"
},
  "geometry": {"coordinates":[2.23269,48.835541],"type":"Point"}
}