{
  "type": "Feature",
  "properties": {
    "iso:country":"FR",
    "sg:address":"Rte De Rennes BP 41 53400 Craon",
    "sg:classifiers":[
        {
            "category":"Farming",
            "subcategory":"Livestock Farm",
            "type":"Manufacturing & Wholesale Goods"
        }
    ],
    "sg:phone":"+33 2 43 06 10 41",
    "sg:postcode":"53400",
    "sg:province":"Pays de Loire",
    "sg:tags":[
        "breeding",
        "agriculture",
        "animal"
    ],
    "wof:name":"Richard Patrick",
    "wof:placetype":"venue"
},
  "geometry": {"coordinates":[-0.962879,47.852917],"type":"Point"}
}