{
  "type": "Feature",
  "properties": {
    "addr:full":"Rue de la Lib\u00e9ration Chantenay Villedieu Pays de Loire 72430",
    "addr:postcode":"72430",
    "addr:street":"Rue De La Libe\u0301Ration",
    "iso:country":"FR",
    "sg:address":"Rue de la Lib\u00e9ration",
    "sg:city":"Chantenay Villedieu",
    "sg:orig_category":"Unclassifiable Establishments",
    "sg:phone":"+33 2 43 95 05 04",
    "sg:postcode":"72430",
    "sg:province":"Pays de Loire",
    "wof:name":"Lodev S.a.r.l.",
    "wof:placetype":"venue"
},
  "geometry": {"coordinates":[-0.162391,47.919689],"type":"Point"}
}