{
  "type": "Feature",
  "properties": {
    "iso:country":"FR",
    "sg:address":"7, Terrasse des Reflets, 92400 Courbevoie",
    "sg:orig_category":"Non-Classified Establishments",
    "sg:phone":"+33 1 41 97 41 16",
    "sg:province":"Ile de France",
    "wof:name":"Haworth S.a.s.",
    "wof:placetype":"venue"
},
  "geometry": {"coordinates":[2.24489,48.89056],"type":"Point"}
}