{
  "type": "Feature",
  "properties": {
    "addr:full":"87, Rue du Barb\u00e2tre, 51100 Reims Champagne",
    "addr:housenumber":"87",
    "addr:postcode":"51100",
    "addr:street":"Rue Du Barba\u0302Tre",
    "iso:country":"FR",
    "sg:address":"87, Rue du Barb\u00e2tre, 51100 Reims",
    "sg:orig_category":"Non-Classified Establishments",
    "sg:phone":"+33 3 26 85 48 32",
    "sg:province":"Champagne",
    "wof:name":"Jaloux S.a.",
    "wof:placetype":"venue"
},
  "geometry": {"coordinates":[4.040464,49.248718],"type":"Point"}
}