{
  "type": "Feature",
  "properties": {
    "addr:full":"Rte du Conquet Plouzan\u00e9 Bretagne 29280",
    "addr:postcode":"29280",
    "addr:street":"Rte Du Conquet;Bretagne",
    "iso:country":"FR",
    "sg:address":"Rte du Conquet",
    "sg:city":"Plouzan\u00e9",
    "sg:orig_category":"Non-Classified Establishments",
    "sg:phone":"+33 2 98 45 89 37",
    "sg:postcode":"29280",
    "sg:province":"Bretagne",
    "wof:name":"Paysages D'iroise S.a.r.l.",
    "wof:placetype":"venue"
},
  "geometry": {"coordinates":[-4.595219,48.365566],"type":"Point"}
}