{
  "type": "Feature",
  "properties": {
    "addr:full":"35 Rue Du Puits 25400 Exincourt Franche Comt\u00e9 25400",
    "addr:housenumber":"35",
    "addr:postcode":"25400;25400",
    "addr:street":"Rue Du Puits;Franche Comte\u0301",
    "iso:country":"FR",
    "sg:address":"35 Rue Du Puits 25400 Exincourt",
    "sg:classifiers":[
        {
            "category":"Shopping",
            "type":"Retail Goods"
        }
    ],
    "sg:phone":"+33 3 81 90 74 44",
    "sg:postcode":"25400",
    "sg:province":"Franche Comt\u00e9",
    "sg:tags":[
        "metallurgy",
        "finished",
        "-",
        "metalworking",
        "metallic"
    ],
    "wof:name":"L'enseigne Etablissements G Fayolle",
    "wof:placetype":"venue"
},
  "geometry": {"coordinates":[6.83494,47.496181],"type":"Point"}
}