{
  "type": "Feature",
  "properties": {
    "addr:full":"1 Rue Des Eparges 28100 Dreux Dreux Centre 28100",
    "addr:housenumber":"1;dreux",
    "addr:postcode":"28100;28100",
    "addr:street":"Rue Des Eparges",
    "iso:country":"FR",
    "sg:address":"1 Rue Des Eparges 28100 Dreux",
    "sg:city":"Dreux",
    "sg:classifiers":[
        {
            "category":"Wholesale",
            "subcategory":"Medical Equipment & Supplies",
            "type":"Manufacturing & Wholesale Goods"
        }
    ],
    "sg:phone":"+33 2 37 50 07 47",
    "sg:postcode":"28100",
    "sg:province":"Centre",
    "sg:tags":[
        "instrument",
        "health",
        "-",
        "precision"
    ],
    "wof:name":"Mainiere Jean Claude",
    "wof:placetype":"venue"
},
  "geometry": {"coordinates":[1.37037,48.731979],"type":"Point"}
}