{
  "type": "Feature",
  "properties": {
    "addr:full":"24, Rue de la Feyssine, 69100 Villeurbanne Rhone-Alpes 69100",
    "addr:housenumber":"24",
    "addr:postcode":"69100;69100",
    "addr:street":"Rue De La Feyssine",
    "iso:country":"FR",
    "sg:address":"24, Rue de la Feyssine, 69100 Villeurbanne",
    "sg:orig_category":"Unclassifiable Establishments",
    "sg:phone":"+33 4 78 93 77 00",
    "sg:postcode":"69100",
    "sg:province":"Rhone-Alpes",
    "wof:name":"Scie Crel S.a.",
    "wof:placetype":"venue"
},
  "geometry": {"coordinates":[4.889159,45.78476],"type":"Point"}
}