{
  "type": "Feature",
  "properties": {
    "addr:full":"B.P. 220, 69632 V\u00e9nissieux C\u00e9dex^^2, Chemin du G\u00e9nie, 69200 V\u00e9nissieux Rhone-Alpes 69200",
    "addr:housenumber":"b.p. 220",
    "addr:postcode":"69632;69200;69200",
    "addr:street":"Chemin Du Ge\u0301Nie",
    "iso:country":"FR",
    "sg:address":"B.P. 220, 69632 V\u00e9nissieux C\u00e9dex^^2, Chemin du G\u00e9nie, 69200 V\u00e9nissieux",
    "sg:orig_category":"Non-Classified Establishments",
    "sg:phone":"+33 4 78 70 06 06",
    "sg:postcode":"69200",
    "sg:province":"Rhone-Alpes",
    "wof:name":"Th\u00e9venet Sobrh\u00f4ne S.a.",
    "wof:placetype":"venue"
},
  "geometry": {"coordinates":[4.885109,45.696575],"type":"Point"}
}