{
  "type": "Feature",
  "properties": {
    "addr:full":"2, Av. Gambetta, 92400 Courbevoie Ile de France",
    "addr:postcode":"92400",
    "addr:street":"Av. Gambetta",
    "iso:country":"FR",
    "sg:address":"2, Av. Gambetta, 92400 Courbevoie",
    "sg:orig_category":"Unclassifiable Establishments",
    "sg:phone":"+33 1 41 88 60 00",
    "sg:province":"Ile de France",
    "wof:name":"Ibm Europe Middle East Africa S.a.",
    "wof:placetype":"venue"
},
  "geometry": {"coordinates":[2.246465,48.892761],"type":"Point"}
}