{
  "type": "Feature",
  "properties": {
    "iso:country":"FR",
    "sg:address":"Rue des Archicamps - ZI",
    "sg:city":"Amiens",
    "sg:orig_category":"Unclassifiable Establishments",
    "sg:phone":"+33 3 22 54 28 80",
    "sg:postcode":"80080",
    "sg:province":"Picardie",
    "wof:name":"Calberson Picardie S.a.",
    "wof:placetype":"venue"
},
  "geometry": {"coordinates":[2.2913,49.924992],"type":"Point"}
}