{
  "type": "Feature",
  "properties": {
    "iso:country":"FR",
    "sg:address":"B.P. 73, 59112 Annoeullin^^Rue Lavoisier - ZA, 59112 Annoeullin",
    "sg:orig_category":"Non-Classified Establishments",
    "sg:phone":"+33 3 20 85 72 00",
    "sg:province":"Nord Pas-de-Calais",
    "wof:name":"Sofapi S.a.r.l.",
    "wof:placetype":"venue"
},
  "geometry": {"coordinates":[2.931675,50.529125],"type":"Point"}
}