{
  "type": "Feature",
  "properties": {
    "addr:full":"31C, Rue des Landelles, 35510 Cesson S\u00e9vign\u00e9 Cesson-S\u00e9vign\u00e9 Bretagne 35510",
    "addr:housenumber":"31c",
    "addr:postcode":"35510;se\u0301vigne\u0301 cesson-se\u0301vigne\u0301;35510",
    "addr:street":"Rue Des Landelles",
    "iso:country":"FR",
    "sg:address":"31C, Rue des Landelles, 35510 Cesson S\u00e9vign\u00e9",
    "sg:city":"Cesson-S\u00e9vign\u00e9",
    "sg:orig_category":"Unclassifiable Establishments",
    "sg:phone":"+33 2 99 26 31 57",
    "sg:postcode":"35510",
    "sg:province":"Bretagne",
    "wof:name":"Aptitude Informatique S.a.r.l.",
    "wof:placetype":"venue"
},
  "geometry": {"coordinates":[-1.622268,48.100014],"type":"Point"}
}