{
  "type": "Feature",
  "properties": {
    "addr:full":"ZA de Font Vergnes Decazeville Midi Pyr\u00e9n\u00e9es 12300",
    "addr:postcode":"12300",
    "addr:street":"Za De Font Vergnes",
    "iso:country":"FR",
    "sg:address":"ZA de Font Vergnes",
    "sg:city":"Decazeville",
    "sg:orig_category":"Unclassifiable Establishments",
    "sg:phone":"+33 5 65 43 13 82",
    "sg:postcode":"12300",
    "sg:province":"Midi Pyr\u00e9n\u00e9es",
    "wof:name":"Blanchisserie Cantoss S.a.",
    "wof:placetype":"venue"
},
  "geometry": {"coordinates":[2.251405,44.562115],"type":"Point"}
}