{
  "type": "Feature",
  "properties": {
    "addr:full":"59, Bd Roger Dodin, 35136 Saint Jacques de la Lande Saint-Jacques-de-la-Lande Bretagne 35136",
    "addr:housenumber":"59",
    "addr:postcode":"35136;35136",
    "addr:street":"Bd Roger Dodin;Saint-Jacques-De-La-Lande",
    "iso:country":"FR",
    "sg:address":"59, Bd Roger Dodin, 35136 Saint Jacques de la Lande",
    "sg:city":"Saint-Jacques-de-la-Lande",
    "sg:orig_category":"Non-Classified Establishments",
    "sg:phone":"+33 2 99 35 52 52",
    "sg:postcode":"35136",
    "sg:province":"Bretagne",
    "wof:name":"G.t.m. Construction S.a.",
    "wof:placetype":"venue"
},
  "geometry": {"coordinates":[-1.710685,48.082649],"type":"Point"}
}