{
  "type": "Feature",
  "properties": {
    "iso:country":"FR",
    "sg:address":"B.P. 48, 01102 Oyonnax C\u00e9dex^^Rue Fran\u00e7ois Rochaix - ZI Nord, 01100 Oyonnax",
    "sg:orig_category":"Non-Classified Establishments",
    "sg:phone":"+33 4 74 12 12 60",
    "sg:postcode":"01100",
    "sg:province":"Rhone-Alpes",
    "wof:name":"S.m.p.o. S.a. - Soci\u00e9t\u00e9 M\u00e9cano Plastiques Oyonnaxienne",
    "wof:placetype":"venue"
},
  "geometry": {"coordinates":[5.64405,46.24968],"type":"Point"}
}