{
  "type": "Feature",
  "properties": {
    "iso:country":"FR",
    "sg:address":"10 Rue Pasteur 51470 St Memmie",
    "sg:classifiers":[
        {
            "category":"Home & Garden",
            "subcategory":"Furniture",
            "type":"Retail Goods"
        }
    ],
    "sg:phone":"+33 3 26 21 89 10",
    "sg:province":"Champagne",
    "sg:tags":[
        "wood"
    ],
    "wof:name":"Office National Des Forets (onf)",
    "wof:placetype":"venue"
},
  "geometry": {"coordinates":[4.383202,48.954865],"type":"Point"}
}