{
  "type": "Feature",
  "properties": {
    "addr:full":"ZI les Mourgues Cardet Languedoc-Roussillon 30350",
    "addr:postcode":"30350",
    "addr:street":"Zi Les",
    "iso:country":"FR",
    "sg:address":"ZI les Mourgues",
    "sg:city":"Cardet",
    "sg:orig_category":"Unclassifiable Establishments",
    "sg:phone":"+33 4 66 83 87 92",
    "sg:postcode":"30350",
    "sg:province":"Languedoc-Roussillon",
    "wof:name":"Socom S.a.r.l.",
    "wof:placetype":"venue"
},
  "geometry": {"coordinates":[4.08114,44.025631],"type":"Point"}
}