{
  "type": "Feature",
  "properties": {
    "addr:full":"Ch\u00e2teau la Cardonne 33340 Blaignan Blaignan Aquitaine 33340",
    "addr:postcode":"33340;33340",
    "iso:country":"FR",
    "sg:address":"Ch\u00e2teau la Cardonne 33340 Blaignan",
    "sg:city":"Blaignan",
    "sg:orig_category":"Non-Classified Establishments",
    "sg:phone":"+33 5 56 73 31 51",
    "sg:postcode":"33340",
    "sg:province":"Aquitaine",
    "wof:name":"Domaines C.g.r. S.a.",
    "wof:placetype":"venue"
},
  "geometry": {"coordinates":[-0.857951,45.319683],"type":"Point"}
}