{
  "type": "Feature",
  "properties": {
    "addr:full":"222-22, Bd Gustave Flaubert, 63000 Clermont Ferrand Clermont-Ferrand Auvergne 63000",
    "addr:postcode":"222-22;63000;63000",
    "addr:street":"Bd Gustave Flaubert",
    "iso:country":"FR",
    "sg:address":"222-22, Bd Gustave Flaubert, 63000 Clermont Ferrand",
    "sg:city":"Clermont-Ferrand",
    "sg:orig_category":"Unclassifiable Establishments",
    "sg:phone":"+33 4 73 28 63 63",
    "sg:postcode":"63000",
    "sg:province":"Auvergne",
    "wof:name":"Ant\u00e9a",
    "wof:placetype":"venue"
},
  "geometry": {"coordinates":[3.12689,45.758686],"type":"Point"}
}