{
  "type": "Feature",
  "properties": {
    "iso:country":"FR",
    "sg:address":"15/27, Rue du 1er Mai, 92000 Nanterre",
    "sg:orig_category":"Unclassifiable Establishments",
    "sg:phone":"+33 1 41 19 25 00",
    "sg:province":"Ile de France",
    "wof:name":"Orditec Services S.a.",
    "wof:placetype":"venue"
},
  "geometry": {"coordinates":[2.213536,48.908756],"type":"Point"}
}