{
  "type": "Feature",
  "properties": {
    "addr:full":"275 Avenue De Laon 51100 Reims Champagne 51100",
    "addr:housenumber":"275",
    "addr:postcode":"51100;51100",
    "addr:street":"Avenue De Laon",
    "iso:country":"FR",
    "sg:address":"275 Avenue De Laon 51100 Reims",
    "sg:classifiers":[
        {
            "category":"Wholesale",
            "subcategory":"Meat",
            "type":"Manufacturing & Wholesale Goods"
        }
    ],
    "sg:phone":"+33 3 26 09 31 86",
    "sg:postcode":"51100",
    "sg:province":"Champagne",
    "sg:tags":[
        "food",
        "cooked",
        "product",
        "related"
    ],
    "wof:name":"Roger Digrazia Sa",
    "wof:placetype":"venue"
},
  "geometry": {"coordinates":[4.020236,49.272217],"type":"Point"}
}