{
  "type": "Feature",
  "properties": {
    "addr:full":"1, Rue Julien Videment - Immeuble Anne de Bretagne, 44000 Nantes Pays de Loire 44000",
    "addr:housenumber":"1",
    "addr:postcode":"44000;44000",
    "addr:street":"Rue Julien Videment Immeuble Anne De Bretagne",
    "iso:country":"FR",
    "sg:address":"1, Rue Julien Videment - Immeuble Anne de Bretagne, 44000 Nantes",
    "sg:orig_category":"Non-Classified Establishments",
    "sg:phone":"+33 2 40 48 20 37",
    "sg:postcode":"44000",
    "sg:province":"Pays de Loire",
    "wof:name":"Engelhard Clal",
    "wof:placetype":"venue"
},
  "geometry": {"coordinates":[-1.564191,47.207752],"type":"Point"}
}