{
  "type": "Feature",
  "properties": {
    "iso:country":"FR",
    "sg:address":"104, Rue des Usines, 59330 Hautmont",
    "sg:orig_category":"Non-Classified Establishments",
    "sg:phone":"+33 3 27 66 22 66",
    "sg:province":"Nord Pas-de-Calais",
    "wof:name":"Socomas S.a. - Soci\u00e9t\u00e9 De Construction En M\u00e9taux Et Alliages Soud\u00e9s",
    "wof:placetype":"venue"
},
  "geometry": {"coordinates":[3.900322,50.245155],"type":"Point"}
}