{
  "type": "Feature",
  "properties": {
    "iso:country":"FR",
    "sg:address":"105, Av. du Progr\u00e8s, 69680 Chassieu",
    "sg:orig_category":"Non-Classified Establishments",
    "sg:phone":"+33 4 72 79 01 01",
    "sg:province":"Rhone-Alpes",
    "wof:name":"Thenon Fleurs Et Plantes S.a.r.l.",
    "wof:placetype":"venue"
},
  "geometry": {"coordinates":[4.96213,45.723907],"type":"Point"}
}