{
  "type": "Feature",
  "properties": {
    "addr:full":"111 rue R\u00e9aumur 75002 Paris Ile de France",
    "addr:housenumber":"111",
    "addr:postcode":"75002",
    "addr:street":"Rue Re\u0301Aumur",
    "iso:country":"FR",
    "sg:address":"111 rue R\u00e9aumur 75002 Paris",
    "sg:classifiers":[
        {
            "category":"Building & Trades",
            "subcategory":"Locksmith",
            "type":"Services"
        }
    ],
    "sg:phone":"+33 1 40 13 77 88",
    "sg:province":"Ile de France",
    "sg:tags":[
        "software"
    ],
    "wof:name":"Document Sciences Europe S.a.r.l.",
    "wof:placetype":"venue"
},
  "geometry": {"coordinates":[2.343536,48.868118],"type":"Point"}
}