{
  "type": "Feature",
  "properties": {
    "addr:full":"7bis, Rue de la Maladi\u00e8re, 10300 Sainte Savine Champagne",
    "addr:housenumber":"7bis",
    "addr:postcode":"10300",
    "addr:street":"Rue De La Maladie\u0300Re",
    "iso:country":"FR",
    "sg:address":"7bis, Rue de la Maladi\u00e8re, 10300 Sainte Savine",
    "sg:orig_category":"Unclassifiable Establishments",
    "sg:phone":"+33 3 25 74 93 95",
    "sg:province":"Champagne",
    "wof:name":"Aub'inox S.a.",
    "wof:placetype":"venue"
},
  "geometry": {"coordinates":[4.023868,48.292839],"type":"Point"}
}