{
  "type": "Feature",
  "properties": {
    "addr:full":"3, All\u00e9e des Garays, 91120 Palaiseau Ile de France",
    "addr:housenumber":"3",
    "addr:postcode":"91120;ile",
    "addr:street":"Alle\u0301E Des Garays",
    "iso:country":"FR",
    "sg:address":"3, All\u00e9e des Garays, 91120 Palaiseau",
    "sg:orig_category":"Unclassifiable Establishments",
    "sg:phone":"+33 1 69 32 04 58",
    "sg:province":"Ile de France",
    "wof:name":"G.m.i. S.a.r.l. - Global Manufacturing Improvement",
    "wof:placetype":"venue"
},
  "geometry": {"coordinates":[2.254018,48.713802],"type":"Point"}
}