{
  "type": "Feature",
  "properties": {
    "addr:full":"Rn 41 Za Du Petit Sailly 62113 Sailly Labourse Nord Pas-de-Calais 62113",
    "addr:postcode":"62113;62113",
    "addr:street":"Rn 41 Za Du Petit Sailly",
    "iso:country":"FR",
    "sg:address":"Rn 41 Za Du Petit Sailly 62113 Sailly Labourse",
    "sg:classifiers":[
        {
            "category":"Manufacturing",
            "subcategory":"Metals",
            "type":"Manufacturing & Wholesale Goods"
        }
    ],
    "sg:phone":"+33 3 21 65 45 22",
    "sg:postcode":"62113",
    "sg:province":"Nord Pas-de-Calais",
    "sg:tags":[
        "pipe",
        "sheet",
        "-",
        "metalworking",
        "metallic",
        "metallurgy",
        "finished"
    ],
    "wof:name":"Stapi",
    "wof:placetype":"venue"
},
  "geometry": {"coordinates":[2.696664,50.500561],"type":"Point"}
}