{
  "type": "Feature",
  "properties": {
    "addr:full":"Rue Pierre Doutreleau 76280 Gonneville La Mallet Haute Normandie 76280",
    "addr:postcode":"76280;76280",
    "addr:street":"Rue Pierre Doutreleau",
    "iso:country":"FR",
    "sg:address":"Rue Pierre Doutreleau 76280 Gonneville La Mallet",
    "sg:classifiers":[
        {
            "category":"Autos & Motor Vehicles",
            "subcategory":"Automobile Sales",
            "type":"Retail Goods"
        }
    ],
    "sg:phone":"+33 6 07 15 60 37",
    "sg:postcode":"76280",
    "sg:province":"Haute Normandie",
    "sg:tags":[
        "equipment",
        "motor-cars",
        "transport"
    ],
    "wof:name":"Etablissements Guerin",
    "wof:placetype":"venue"
},
  "geometry": {"coordinates":[0.217623,49.642155],"type":"Point"}
}