{
  "type": "Feature",
  "properties": {
    "addr:full":"88, Av. du G\u00e9n\u00e9ral Leclerc, 92100 Boulogne Billancourt Ile de France",
    "addr:postcode":"92100",
    "addr:street":"88 Av. Du Ge\u0301Ne\u0301Ral Leclerc",
    "iso:country":"FR",
    "sg:address":"88, Av. du G\u00e9n\u00e9ral Leclerc, 92100 Boulogne Billancourt",
    "sg:orig_category":"Unclassifiable Establishments",
    "sg:phone":"+33 1 41 31 61 00",
    "sg:province":"Ile de France",
    "wof:name":"Brocelia S.a.r.l.",
    "wof:placetype":"venue"
},
  "geometry": {"coordinates":[2.236119,48.831493],"type":"Point"}
}