{
  "type": "Feature",
  "properties": {
    "iso:country":"FR",
    "sg:address":"Quartier du Petit P\u00e9lican",
    "sg:city":"Mont\u00e9limar",
    "sg:orig_category":"Unclassifiable Establishments",
    "sg:phone":"+33 4 75 00 83 00",
    "sg:postcode":"26200",
    "sg:province":"Rhone-Alpes",
    "wof:name":"Entrepose",
    "wof:placetype":"venue"
},
  "geometry": {"coordinates":[4.745595,44.528545],"type":"Point"}
}