{
  "type": "Feature",
  "properties": {
    "iso:country":"FR",
    "sg:address":"ZA. de Penboat",
    "sg:city":"Plabennec",
    "sg:orig_category":"Non-Classified Establishments",
    "sg:phone":"+33 2 98 07 88 80",
    "sg:postcode":"29860",
    "sg:province":"Bretagne",
    "wof:name":"Aber Propret\u00e9 Ouest S.a.",
    "wof:placetype":"venue"
},
  "geometry": {"coordinates":[-4.426449,48.502136],"type":"Point"}
}