{
  "type": "Feature",
  "properties": {
    "iso:country":"FR",
    "sg:address":"Zone Logistique de Colombiers",
    "sg:city":"B\u00e9ziers",
    "sg:orig_category":"Unclassifiable Establishments",
    "sg:phone":"+33 4 67 35 85 00",
    "sg:postcode":"34500",
    "sg:province":"Languedoc-Roussillon",
    "wof:name":"S.t.l. S.a.r.l. - Sud Transport Location",
    "wof:placetype":"venue"
},
  "geometry": {"coordinates":[3.216105,43.344234],"type":"Point"}
}