{
  "type": "Feature",
  "properties": {
    "iso:country":"FR",
    "sg:address":"Bd R\u00e9publique 49380 Thouarce",
    "sg:classifiers":[
        {
            "category":"Farming",
            "subcategory":"Farm",
            "type":"Manufacturing & Wholesale Goods"
        }
    ],
    "sg:phone":"+33 2 41 54 09 08",
    "sg:postcode":"49380",
    "sg:province":"Pays de Loire",
    "sg:tags":[
        "horticulture",
        "agriculture",
        "livestock"
    ],
    "wof:name":"Union Agricole Neufbourg",
    "wof:placetype":"venue"
},
  "geometry": {"coordinates":[-0.504784,47.270489],"type":"Point"}
}