{
  "type": "Feature",
  "properties": {
    "addr:full":"Rte D'Osnes 08110 Carignan Champagne 08110",
    "addr:postcode":"08110;08110",
    "addr:street":"Rte D'Osnes;Champagne",
    "iso:country":"FR",
    "sg:address":"Rte D'Osnes 08110 Carignan",
    "sg:classifiers":[
        {
            "category":"Manufacturing",
            "subcategory":"Metals",
            "type":"Manufacturing & Wholesale Goods"
        }
    ],
    "sg:phone":"+33 3 24 22 31 60",
    "sg:postcode":"08110",
    "sg:province":"Champagne",
    "sg:tags":[
        "metallurgy",
        "metalworking",
        "processing"
    ],
    "wof:name":"A T M Sarl",
    "wof:placetype":"venue"
},
  "geometry": {"coordinates":[5.16276,49.654919],"type":"Point"}
}