{
  "type": "Feature",
  "properties": {
    "addr:full":"ZAC Val de Croze; 130-140 Quai Flora Tristan / Immeuble Le Seranne; Montpellier; 34 077 Languedoc-Roussillon",
    "addr:housenumber":"130-140;34",
    "addr:postcode":"077",
    "addr:street":"Zac Val De Croze;Quai Flora Tristan / Immeuble Le Seranne Montpellier",
    "iso:country":"FR",
    "sg:address":"ZAC Val de Croze; 130-140 Quai Flora Tristan / Immeuble Le Seranne; Montpellier; 34 077",
    "sg:classifiers":[
        {
            "category":"Travel",
            "subcategory":"Travel Agent",
            "type":"Entertainment"
        }
    ],
    "sg:phone":"+33 3346740761",
    "sg:province":"Languedoc-Roussillon",
    "wof:name":"Chateaux & Residences Group",
    "wof:placetype":"venue"
},
  "geometry": {"coordinates":[3.87609,43.610851],"type":"Point"}
}