{
  "type": "Feature",
  "properties": {
    "addr:full":"131 Rue Augustin Fresnel 54710 Ludres Lorraine 54710",
    "addr:housenumber":"131",
    "addr:postcode":"54710;54710",
    "addr:street":"Rue Augustin Fresnel",
    "iso:country":"FR",
    "sg:address":"131 Rue Augustin Fresnel 54710 Ludres",
    "sg:classifiers":[
        {
            "category":"Manufacturing",
            "subcategory":"Metals",
            "type":"Manufacturing & Wholesale Goods"
        }
    ],
    "sg:phone":"+33 3 83 15 11 52",
    "sg:postcode":"54710",
    "sg:province":"Lorraine",
    "sg:tags":[
        "metallurgy",
        "metalworking"
    ],
    "wof:name":"Impress Sa",
    "wof:placetype":"venue"
},
  "geometry": {"coordinates":[6.161059,48.621563],"type":"Point"}
}