{
  "type": "Feature",
  "properties": {
    "addr:full":"Le Plantier Rte De Brian\u00e7on 05000 Gap Midi Pyr\u00e9n\u00e9es",
    "addr:postcode":"05000",
    "addr:street":"Rte De Brianc\u0327On",
    "iso:country":"FR",
    "sg:address":"Le Plantier Rte De Brian\u00e7on 05000 Gap",
    "sg:classifiers":[
        {
            "category":"Autos & Motor Vehicles",
            "subcategory":"Automobile Sales",
            "type":"Retail Goods"
        }
    ],
    "sg:phone":"+33 4 92 52 25 56",
    "sg:province":"Midi Pyr\u00e9n\u00e9es",
    "sg:tags":[
        "equipment",
        "motor-cars",
        "transport"
    ],
    "wof:name":"Gap Sa",
    "wof:placetype":"venue"
},
  "geometry": {"coordinates":[6.07483,44.554939],"type":"Point"}
}