{
  "type": "Feature",
  "properties": {
    "iso:country":"FR",
    "sg:address":"Centre Commercial; Courcouronnes; 91000",
    "sg:classifiers":[
        {
            "category":"Banks & Credit Unions",
            "subcategory":"Bank",
            "type":"Services"
        }
    ],
    "sg:phone":"+33 3369772581",
    "sg:postcode":"91000",
    "sg:province":"Ile de France",
    "wof:name":"Banque Nationale De Paris",
    "wof:placetype":"venue"
},
  "geometry": {"coordinates":[2.4293,48.624664],"type":"Point"}
}