{
  "type": "Feature",
  "properties": {
    "iso:country":"FR",
    "sg:address":"51320 Soudron",
    "sg:orig_category":"Non-Classified Establishments",
    "sg:phone":"+33 3 26 67 40 45",
    "sg:postcode":"51320",
    "sg:province":"Champagne",
    "wof:name":"Coop\u00e9rative De D\u00e9shydratation De Soudron Et Environs",
    "wof:placetype":"venue"
},
  "geometry": {"coordinates":[4.200027,48.838928],"type":"Point"}
}