{
  "type": "Feature",
  "properties": {
    "addr:full":"3 rue Kuhlmann 59000 Lille Nord Pas-de-Calais",
    "addr:housenumber":"3",
    "addr:postcode":"59000",
    "addr:street":"Rue Kuhlmann",
    "iso:country":"FR",
    "sg:address":"3 rue Kuhlmann 59000 Lille",
    "sg:classifiers":[
        {
            "category":"Manufacturing",
            "subcategory":"Metals",
            "type":"Manufacturing & Wholesale Goods"
        }
    ],
    "sg:phone":"+33 3 20 54 68 47",
    "sg:province":"Nord Pas-de-Calais",
    "sg:tags":[
        "special"
    ],
    "wof:name":"Flandre Aluminium Sarl",
    "wof:placetype":"venue"
},
  "geometry": {"coordinates":[3.052846,50.621239],"type":"Point"}
}