{
  "type": "Feature",
  "properties": {
    "iso:country":"FR",
    "sg:address":"33710 Samonac",
    "sg:city":"Samonac",
    "sg:orig_category":"Unclassifiable Establishments",
    "sg:phone":"+33 5 57 68 46 34",
    "sg:postcode":"33710",
    "sg:province":"Aquitaine",
    "wof:name":"Ch\u00e2teau Rousset S.a.r.l.",
    "wof:placetype":"venue"
},
  "geometry": {"coordinates":[-0.568415,45.074539],"type":"Point"}
}