{
  "type": "Feature",
  "properties": {
    "iso:country":"FR",
    "sg:address":"A\u00e9rodrome de Nangis",
    "sg:city":"Nangis",
    "sg:orig_category":"Unclassifiable Establishments",
    "sg:phone":"+33 1 60 58 55 70",
    "sg:postcode":"77370",
    "sg:province":"Ile de France",
    "wof:name":"A\u00e9rodima S.a.r.l.",
    "wof:placetype":"venue"
},
  "geometry": {"coordinates":[2.948903,48.507874],"type":"Point"}
}