{
  "type": "Feature",
  "properties": {
    "addr:full":"106 Grande Rue 68150 Ribeauville Ribeauvill\u00e9 Alsace 68150",
    "addr:housenumber":"106",
    "addr:postcode":"68150;68150",
    "addr:street":"Grande Rue",
    "iso:country":"FR",
    "sg:address":"106 Grande Rue 68150 Ribeauville",
    "sg:city":"Ribeauvill\u00e9",
    "sg:classifiers":[
        {
            "category":"Bakery",
            "type":"Food & Drink"
        }
    ],
    "sg:phone":"+33 3 89 73 67 45",
    "sg:postcode":"68150",
    "sg:province":"Alsace",
    "sg:tags":[
        "cake",
        "product",
        "related",
        "bread"
    ],
    "wof:name":"Epi D'or",
    "wof:placetype":"venue"
},
  "geometry": {"coordinates":[7.315436,48.196083],"type":"Point"}
}