{
  "type": "Feature",
  "properties": {
    "iso:country":"FR",
    "sg:address":"B.P. 36, 60290 Rantigny^^Rue Parmentier - Usine de la Br\u00e8che, 60290 Rantigny",
    "sg:orig_category":"Non-Classified Establishments",
    "sg:phone":"+33 3 44 73 08 22",
    "sg:postcode":"60290",
    "sg:province":"Picardie",
    "wof:name":"Applications Industrielles S.a.",
    "wof:placetype":"venue"
},
  "geometry": {"coordinates":[2.44369,49.293819],"type":"Point"}
}