{
  "type": "Feature",
  "properties": {
    "addr:full":"9, Rue Santos Dumont, 75015 Paris Ile de France",
    "addr:housenumber":"9",
    "addr:postcode":"75015",
    "addr:street":"Rue Santos Dumont",
    "iso:country":"FR",
    "sg:address":"9, Rue Santos Dumont, 75015 Paris",
    "sg:orig_category":"Unclassifiable Establishments",
    "sg:phone":"+33 1 45 30 07 37",
    "sg:province":"Ile de France",
    "wof:name":"Compusol 2000 S.a.r.l.",
    "wof:placetype":"venue"
},
  "geometry": {"coordinates":[2.305697,48.833984],"type":"Point"}
}