{
  "type": "Feature",
  "properties": {
    "addr:full":"5, Quai du Commerce, 69009 Lyon Rhone-Alpes 69009",
    "addr:housenumber":"5",
    "addr:postcode":"69009;69009",
    "addr:street":"Quai Du Commerce",
    "iso:country":"FR",
    "sg:address":"5, Quai du Commerce, 69009 Lyon",
    "sg:orig_category":"Unclassifiable Establishments",
    "sg:phone":"+33 4 72 19 22 01",
    "sg:postcode":"69009",
    "sg:province":"Rhone-Alpes",
    "wof:name":"Eurotelis S.a.",
    "wof:placetype":"venue"
},
  "geometry": {"coordinates":[4.812119,45.784321],"type":"Point"}
}