{
  "type": "Feature",
  "properties": {
    "iso:country":"FR",
    "sg:address":"2, Rte de Ch\u00e2teau Thierry, 02210 Breny",
    "sg:orig_category":"Non-Classified Establishments",
    "sg:phone":"+33 3 23 55 20 40",
    "sg:postcode":"02210",
    "sg:province":"Picardie",
    "wof:name":"Decoster S.a.",
    "wof:placetype":"venue"
},
  "geometry": {"coordinates":[3.353173,49.188709],"type":"Point"}
}