{
  "type": "Feature",
  "properties": {
    "iso:country":"FR",
    "sg:address":"Rte de Chartreuse - ZI",
    "sg:city":"Saint Etienne de Saint Geoirs",
    "sg:orig_category":"Unclassifiable Establishments",
    "sg:phone":"+33 4 76 93 53 49",
    "sg:postcode":"38590",
    "sg:province":"Rhone-Alpes",
    "wof:name":"X. Part S.a.r.l.",
    "wof:placetype":"venue"
},
  "geometry": {"coordinates":[5.337711,45.293369],"type":"Point"}
}