{
  "type": "Feature",
  "properties": {
    "addr:full":"170, Rue des Techniques, 74970 Marignier Rhone-Alpes",
    "addr:housenumber":"170",
    "addr:postcode":"74970",
    "addr:street":"Rue Des Techniques",
    "iso:country":"FR",
    "sg:address":"170, Rue des Techniques, 74970 Marignier",
    "sg:orig_category":"Unclassifiable Establishments",
    "sg:phone":"+33 4 50 89 49 49",
    "sg:province":"Rhone-Alpes",
    "wof:name":"Pronic S.a.s.",
    "wof:placetype":"venue"
},
  "geometry": {"coordinates":[6.506163,46.076126],"type":"Point"}
}