{
  "type": "Feature",
  "properties": {
    "addr:full":"B.P. 26, 84141 Montfavet C\u00e9dex^^Clos du Souspiron, 84140 Montfavet Languedoc-Roussillon",
    "addr:postcode":"84141;84140",
    "addr:street":"B.P. 26;Montfavet",
    "iso:country":"FR",
    "sg:address":"B.P. 26, 84141 Montfavet C\u00e9dex^^Clos du Souspiron, 84140 Montfavet",
    "sg:orig_category":"Non-Classified Establishments",
    "sg:phone":"+33 4 90 32 19 83",
    "sg:province":"Languedoc-Roussillon",
    "wof:name":"Etablissement L. Henry S.a.s.",
    "wof:placetype":"venue"
},
  "geometry": {"coordinates":[4.87188,43.935669],"type":"Point"}
}