{
  "type": "Feature",
  "properties": {
    "addr:full":"27 Rue D Arras 92000 Nanterre Ile de France",
    "addr:housenumber":"27",
    "addr:postcode":"92000",
    "addr:street":"Rue D",
    "iso:country":"FR",
    "sg:address":"27 Rue D Arras 92000 Nanterre",
    "sg:classifiers":[
        {
            "category":"Utilities",
            "subcategory":"Telephone",
            "type":"Services"
        }
    ],
    "sg:phone":"+33 1 41 30 83 83",
    "sg:province":"Ile de France",
    "sg:tags":[
        "telecommunication"
    ],
    "wof:name":"Les Ateliers De Telecommunications Attel",
    "wof:placetype":"venue"
},
  "geometry": {"coordinates":[2.225609,48.900513],"type":"Point"}
}