{
  "type": "Feature",
  "properties": {
    "iso:country":"FR",
    "sg:address":"8, Place Martroi, 45000 Orl\u00e9ans",
    "sg:city":"Orl\u00e9ans",
    "sg:orig_category":"Non-Classified Establishments",
    "sg:phone":"+33 2 38 53 59 80",
    "sg:postcode":"45000",
    "sg:province":"Centre",
    "wof:name":"Delaloy Design",
    "wof:placetype":"venue"
},
  "geometry": {"coordinates":[1.904578,47.902603],"type":"Point"}
}