{
  "type": "Feature",
  "properties": {
    "iso:country":"FR",
    "sg:address":"19, Rue Maurice Petit, 69360 S\u00e9r\u00e9zin du Rh\u00f4ne",
    "sg:orig_category":"Unclassifiable Establishments",
    "sg:phone":"+33 4 78 02 48 48",
    "sg:postcode":"69360",
    "sg:province":"Rhone-Alpes",
    "wof:name":"Charron S.a.",
    "wof:placetype":"venue"
},
  "geometry": {"coordinates":[4.823689,45.63142],"type":"Point"}
}