{
  "type": "Feature",
  "properties": {
    "addr:full":"82 R De La Feschotte Du Haut Parc D'Activit\u00e9 Du Moulin 25490 Dampierre Les Bois Franche Comt\u00e9 25490",
    "addr:housenumber":"82",
    "addr:postcode":"25490;25490",
    "addr:street":"R De La Feschotte Du Haut Parc D'Activite \u0301 Du Moulin;Franche Comte\u0301",
    "iso:country":"FR",
    "sg:address":"82 R De La Feschotte Du Haut Parc D'Activit\u00e9 Du Moulin 25490 Dampierre Les Bois",
    "sg:classifiers":[
        {
            "category":"Utilities",
            "subcategory":"Electric",
            "type":"Services"
        }
    ],
    "sg:phone":"+33 3 81 90 74 60",
    "sg:postcode":"25490",
    "sg:province":"Franche Comt\u00e9",
    "sg:tags":[
        "electricity",
        "electronic",
        "electrical",
        "equipment"
    ],
    "wof:name":"Eurocade",
    "wof:placetype":"venue"
},
  "geometry": {"coordinates":[6.915658,47.506413],"type":"Point"}
}