{
  "type": "Feature",
  "properties": {
    "addr:full":"19, Rue du Mail, 75002 Paris Ile de France",
    "addr:housenumber":"19",
    "addr:postcode":"75002",
    "addr:street":"Rue Du Mail",
    "iso:country":"FR",
    "sg:address":"19, Rue du Mail, 75002 Paris",
    "sg:orig_category":"Unclassifiable Establishments",
    "sg:phone":"+33 1 40 41 17 76",
    "sg:province":"Ile de France",
    "wof:name":"Arthur Sanderson And Sons France S.a.r.l.",
    "wof:placetype":"venue"
},
  "geometry": {"coordinates":[2.342543,48.866932],"type":"Point"}
}