{
  "type": "Feature",
  "properties": {
    "addr:full":"14, All\u00e9e du Cantal, 91018 Lisses C\u00e9dex Champagne",
    "addr:housenumber":"14",
    "addr:postcode":"91018",
    "addr:street":"Alle\u0301E Du Cantal",
    "iso:country":"FR",
    "sg:address":"14, All\u00e9e du Cantal, 91018 Lisses C\u00e9dex",
    "sg:orig_category":"Non-Classified Establishments",
    "sg:phone":"+33 1 60 86 14 68",
    "sg:province":"Champagne",
    "wof:name":"Konelab S.a.",
    "wof:placetype":"venue"
},
  "geometry": {"coordinates":[2.426228,48.61187],"type":"Point"}
}