{
  "type": "Feature",
  "properties": {
    "addr:full":"92 Rue D Amsterdam 75009 Paris Ile de France",
    "addr:housenumber":"92",
    "addr:postcode":"75009",
    "addr:street":"Rue D",
    "iso:country":"FR",
    "sg:address":"92 Rue D Amsterdam 75009 Paris",
    "sg:classifiers":[
        {
            "category":"Manufacturing",
            "subcategory":"Printing",
            "type":"Manufacturing & Wholesale Goods"
        }
    ],
    "sg:phone":"+33 1 45 26 30 32",
    "sg:province":"Ile de France",
    "sg:tags":[
        "publishing"
    ],
    "wof:name":"Roto Smeets France",
    "wof:placetype":"venue"
},
  "geometry": {"coordinates":[2.327371,48.882233],"type":"Point"}
}