{
  "type": "Feature",
  "properties": {
    "addr:full":"1, Rue des Petits Ruisseaux - ZAC des Godets, 91370 Verri\u00e8res le Buisson Ile de France 91370",
    "addr:housenumber":"1;zac",
    "addr:postcode":"91370;91370",
    "addr:street":"Rue Des Petits Ruisseaux;Des Godets",
    "iso:country":"FR",
    "sg:address":"1, Rue des Petits Ruisseaux - ZAC des Godets, 91370 Verri\u00e8res le Buisson",
    "sg:orig_category":"Non-Classified Establishments",
    "sg:phone":"+33 1 69 20 50 31",
    "sg:postcode":"91370",
    "sg:province":"Ile de France",
    "wof:name":"C.d.e. S.a.s. - Construction D\u00e9coration Entretien",
    "wof:placetype":"venue"
},
  "geometry": {"coordinates":[2.283244,48.746063],"type":"Point"}
}