{
  "type": "Feature",
  "properties": {
    "iso:country":"FR",
    "sg:address":"Av. de la Grande Thumine - Parc d'Ariane - B\u00e2t C, 13083 Aix en Provence C\u00e9dex 02^^Av. de la Grande T",
    "sg:orig_category":"Non-Classified Establishments",
    "sg:phone":"+33 4 42 24 51 51",
    "sg:province":"Nord Pas-de-Calais",
    "wof:name":"Euro M\u00e9dias S.a.r.l.",
    "wof:placetype":"venue"
},
  "geometry": {"coordinates":[5.412446,43.523373],"type":"Point"}
}