{
  "type": "Feature",
  "properties": {
    "addr:full":"15 Impasse Du Tropic 16000 Angouleme Poitou-Charentes 16000",
    "addr:housenumber":"15",
    "addr:postcode":"16000;16000",
    "addr:street":"Impasse Du Tropic;Angouleme",
    "iso:country":"FR",
    "sg:address":"15 Impasse Du Tropic 16000 Angouleme",
    "sg:classifiers":[
        {
            "category":"Food Court",
            "type":"Food & Drink"
        }
    ],
    "sg:phone":"+33 5 45 95 02 77",
    "sg:postcode":"16000",
    "sg:province":"Poitou-Charentes",
    "sg:tags":[
        "product",
        "related"
    ],
    "wof:name":"Charlemagne (camc)",
    "wof:placetype":"venue"
},
  "geometry": {"coordinates":[0.17123,45.6427],"type":"Point"}
}