{
  "type": "Feature",
  "properties": {
    "iso:country":"FR",
    "sg:address":"4, Rue de la Gare, 57920 K\u00e9dange sur Canner",
    "sg:orig_category":"Unclassifiable Establishments",
    "sg:phone":"+33 3 82 83 53 57",
    "sg:province":"Lorraine",
    "wof:name":"Semin S.a.",
    "wof:placetype":"venue"
},
  "geometry": {"coordinates":[6.333448,49.306503],"type":"Point"}
}