{
  "type": "Feature",
  "properties": {
    "iso:country":"FR",
    "sg:address":"116 avenue de Lombez 31300 Toulouse",
    "sg:orig_category":"Tinplate",
    "sg:phone":"+33 5 34 51 12 00",
    "sg:province":"Midi Pyr\u00e9n\u00e9es",
    "wof:name":"Etablissements Nadal Sa",
    "wof:placetype":"venue"
},
  "geometry": {"coordinates":[1.413026,43.594746],"type":"Point"}
}