{
  "type": "Feature",
  "properties": {
    "addr:full":"ZAE Champagne Tournon sur Rh\u00f4ne Rhone-Alpes 07300",
    "addr:postcode":"07300",
    "iso:country":"FR",
    "sg:address":"ZAE Champagne",
    "sg:city":"Tournon sur Rh\u00f4ne",
    "sg:orig_category":"Non-Classified Establishments",
    "sg:phone":"+33 4 75 08 90 00",
    "sg:postcode":"07300",
    "sg:province":"Rhone-Alpes",
    "wof:name":"Rh\u00f4ne Chimie Industrie S.a.",
    "wof:placetype":"venue"
},
  "geometry": {"coordinates":[4.831534,45.044914],"type":"Point"}
}