{
  "type": "Feature",
  "properties": {
    "addr:full":"3, Av. des C\u00f4tes de Bourg, 33710 Tauriac Tauriac Aquitaine 33710",
    "addr:postcode":"33710;33710",
    "addr:street":"Av. Des Co\u0302Tes De Bourg",
    "iso:country":"FR",
    "sg:address":"3, Av. des C\u00f4tes de Bourg, 33710 Tauriac",
    "sg:city":"Tauriac",
    "sg:orig_category":"Unclassifiable Establishments",
    "sg:phone":"+33 5 57 94 07 07",
    "sg:postcode":"33710",
    "sg:province":"Aquitaine",
    "wof:name":"Cave Vinicole De Bourg Tauriac",
    "wof:placetype":"venue"
},
  "geometry": {"coordinates":[-0.511338,45.036465],"type":"Point"}
}