{
  "type": "Feature",
  "properties": {
    "addr:full":"Rue de la Chapelle - Hameau de Sotteville Saint Romain de Colbosc Haute Normandie 76430",
    "addr:postcode":"76430",
    "addr:street":"Rue De La Chapelle Hameau De Sotteville Saint",
    "iso:country":"FR",
    "sg:address":"Rue de la Chapelle - Hameau de Sotteville",
    "sg:city":"Saint Romain de Colbosc",
    "sg:orig_category":"R\u00c9PARATION ET CONSTRUCTION NAVALE TRAVAUX DE CHAUDRONNERIE ET TUYAUTERIE INDUSTRIELLE",
    "sg:phone":"+33 2 35 20 10 82",
    "sg:postcode":"76430",
    "sg:province":"Haute Normandie",
    "wof:name":"Mouquet S.a.",
    "wof:placetype":"venue"
},
  "geometry": {"coordinates":[0.363674,49.530796],"type":"Point"}
}