{
  "type": "Feature",
  "properties": {
    "iso:country":"FR",
    "sg:address":"B.P. 80419, 57954 Montigny l\u00e8s Metz C\u00e9dex^^3, Rue Saint Quentin, 57950 Montigny l\u00e8s Metz",
    "sg:orig_category":"Non-Classified Establishments",
    "sg:phone":"+33 3 87 66 13 13",
    "sg:province":"Ile de France",
    "wof:name":"Dibacs S.a.",
    "wof:placetype":"venue"
},
  "geometry": {"coordinates":[6.142607,49.097046],"type":"Point"}
}