{
  "type": "Feature",
  "properties": {
    "iso:country":"FR",
    "sg:address":"16, Rue des Montils, 37520 La Riche",
    "sg:city":"La Riche",
    "sg:orig_category":"Unclassifiable Establishments",
    "sg:phone":"+33 2 47 38 05 83",
    "sg:postcode":"37520",
    "sg:province":"Centre",
    "wof:name":"2p.g.n. S.a.r.l. - 2p Gravure Num\u00e9rique",
    "wof:placetype":"venue"
},
  "geometry": {"coordinates":[0.643163,47.380959],"type":"Point"}
}