{
  "type": "Feature",
  "properties": {
    "addr:full":"Impasse De La Croix Bleue 42500 Le Chambon Feugerolles Rhone-Alpes 42500",
    "addr:postcode":"42500;42500",
    "addr:street":"Impasse De La Croix Bleue;Chambon Feugerolles Rhone-Alpes",
    "iso:country":"FR",
    "sg:address":"Impasse De La Croix Bleue 42500 Le Chambon Feugerolles",
    "sg:classifiers":[
        {
            "category":"Manufacturing",
            "subcategory":"Tools & Machinery",
            "type":"Manufacturing & Wholesale Goods"
        }
    ],
    "sg:phone":"+33 4 77 61 03 44",
    "sg:postcode":"42500",
    "sg:province":"Rhone-Alpes",
    "sg:tags":[
        "metallurgy",
        "metalworking"
    ],
    "wof:name":"Allary Sa",
    "wof:placetype":"venue"
},
  "geometry": {"coordinates":[4.32229,45.393585],"type":"Point"}
}