{
  "type": "Feature",
  "properties": {
    "addr:full":"Rue de la Mairie Lacourt Saint Pierre Midi Pyr\u00e9n\u00e9es 82290",
    "addr:postcode":"82290",
    "addr:street":"Rue De La Mairie Lacourt",
    "iso:country":"FR",
    "sg:address":"Rue de la Mairie",
    "sg:city":"Lacourt Saint Pierre",
    "sg:orig_category":"Non-Classified Establishments",
    "sg:phone":"+33 5 63 67 46 55",
    "sg:postcode":"82290",
    "sg:province":"Midi Pyr\u00e9n\u00e9es",
    "wof:name":"Le Parfait Jardinier S.n.c.",
    "wof:placetype":"venue"
},
  "geometry": {"coordinates":[1.264604,43.986267],"type":"Point"}
}