{
  "type": "Feature",
  "properties": {
    "iso:country":"FR",
    "sg:address":"16 rue Ferdinand Farjon 62200 Boulogne sur Mer",
    "sg:orig_category":"Fish, Smoked",
    "sg:phone":"+33 3 21 99 61 90",
    "sg:postcode":"62200",
    "sg:province":"Nord Pas-de-Calais",
    "wof:name":"Jean-baptiste Delpierre Sa",
    "wof:placetype":"venue"
},
  "geometry": {"coordinates":[1.598344,50.721481],"type":"Point"}
}