{
  "type": "Feature",
  "properties": {
    "iso:country":"FR",
    "sg:address":"27, Av. de la Baltique - Z.A. Courtaboeuf - B\u00e2t. 'Les Aigrins', 91140 Villebon sur Yvette",
    "sg:orig_category":"Unclassifiable Establishments",
    "sg:phone":"+33 1 69 07 16 90",
    "sg:province":"Ile de France",
    "wof:name":"Azur Net S.a.",
    "wof:placetype":"venue"
},
  "geometry": {"coordinates":[2.216852,48.692535],"type":"Point"}
}