{
  "type": "Feature",
  "properties": {
    "addr:full":"55 Rue Champagne 94700 Maisons Alfort Ile de France 94700",
    "addr:housenumber":"55",
    "addr:postcode":"94700;94700",
    "addr:street":"Rue Champagne",
    "iso:country":"FR",
    "sg:address":"55 Rue Champagne 94700 Maisons Alfort",
    "sg:classifiers":[
        {
            "category":"Autos & Motor Vehicles",
            "subcategory":"Automobile Sales",
            "type":"Retail Goods"
        }
    ],
    "sg:phone":"+33 1 45 18 01 01",
    "sg:postcode":"94700",
    "sg:province":"Ile de France",
    "sg:tags":[
        "equipment",
        "industrial",
        "transport"
    ],
    "wof:name":"Sarl Dan France",
    "wof:placetype":"venue"
},
  "geometry": {"coordinates":[2.436827,48.81308],"type":"Point"}
}