{
  "type": "Feature",
  "properties": {
    "addr:full":"33 Rue Des Vanesses Za Paris Nord Ii 95942 Roissy Cedex Poitou-Charentes",
    "addr:housenumber":"33",
    "addr:postcode":"95942;cedex",
    "addr:street":"Rue Des Vanesses Za Paris",
    "iso:country":"FR",
    "sg:address":"33 Rue Des Vanesses Za Paris Nord Ii 95942 Roissy Cedex",
    "sg:classifiers":[
        {
            "category":"Manufacturing",
            "subcategory":"Tools & Machinery",
            "type":"Manufacturing & Wholesale Goods"
        }
    ],
    "sg:phone":"+33 1 49 90 90 00",
    "sg:province":"Poitou-Charentes",
    "sg:tags":[
        "equipment",
        "measurement",
        "-",
        "precision",
        "instrument"
    ],
    "wof:name":"Beckman Coulter France",
    "wof:placetype":"venue"
},
  "geometry": {"coordinates":[2.51524,49.004028],"type":"Point"}
}