{
  "type": "Feature",
  "properties": {
    "addr:full":"14 Rue Du Vercors 42100 St Etienne Rhone-Alpes 42100",
    "addr:housenumber":"14",
    "addr:postcode":"42100;42100",
    "addr:street":"Rue Du Vercors",
    "iso:country":"FR",
    "sg:address":"14 Rue Du Vercors 42100 St Etienne",
    "sg:classifiers":[
        {
            "category":"Professional",
            "subcategory":"Advertising",
            "type":"Services"
        }
    ],
    "sg:phone":"+33 4 77 57 65 46",
    "sg:postcode":"42100",
    "sg:province":"Rhone-Alpes",
    "sg:tags":[
        "marketing",
        "medium",
        "communication"
    ],
    "wof:name":"Adrexo",
    "wof:placetype":"venue"
},
  "geometry": {"coordinates":[4.38418,45.416313],"type":"Point"}
}