{
  "type": "Feature",
  "properties": {
    "iso:country":"FR",
    "sg:address":"3A, Rue Pasteur, 76117 Incheville",
    "sg:orig_category":"Unclassifiable Establishments",
    "sg:phone":"+33 2 35 86 50 20",
    "sg:province":"Haute Normandie",
    "wof:name":"M.g.o.p. S.a.r.l. - Maintenance G\u00e9n\u00e9rale De L'outil De Production",
    "wof:placetype":"venue"
},
  "geometry": {"coordinates":[1.503104,50.011608],"type":"Point"}
}