{
  "type": "Feature",
  "properties": {
    "iso:country":"FR",
    "sg:address":"12 B, Rue de Ham, 57880 Ham sous Varsberg",
    "sg:orig_category":"Unclassifiable Establishments",
    "sg:phone":"+33 3 87 82 76 69",
    "sg:province":"Lorraine",
    "wof:name":"Delta Isothermie S.a.r.l.",
    "wof:placetype":"venue"
},
  "geometry": {"coordinates":[6.662978,49.191956],"type":"Point"}
}