{
  "type": "Feature",
  "properties": {
    "iso:country":"FR",
    "sg:address":"Zi Les Chauds Basses 43100 Cohade",
    "sg:city":"Cohade",
    "sg:classifiers":[
        {
            "category":"Manufacturing",
            "subcategory":"Jewelry",
            "type":"Manufacturing & Wholesale Goods"
        }
    ],
    "sg:phone":"+33 4 71 74 55 20",
    "sg:postcode":"43100",
    "sg:province":"Auvergne",
    "sg:tags":[
        "product",
        "miscellaneous",
        "jewellery"
    ],
    "wof:name":"Ets Sauvat Et Cie",
    "wof:placetype":"venue"
},
  "geometry": {"coordinates":[3.371685,45.336849],"type":"Point"}
}