{
  "type": "Feature",
  "properties": {
    "addr:full":"B.P. 13, 42271 Saint Priest en Jarez C\u00e9dex^^4, Rue de l'Artisanat - ZA de la Bargette, 42270 Saint P Rhone-Alpes 42270",
    "addr:postcode":"42271;42270;42270",
    "addr:street":"B.P. 13;Priest;Rue De L'Artisanat Za De La Bargette",
    "iso:country":"FR",
    "sg:address":"B.P. 13, 42271 Saint Priest en Jarez C\u00e9dex^^4, Rue de l'Artisanat - ZA de la Bargette, 42270 Saint P",
    "sg:orig_category":"Non-Classified Establishments",
    "sg:phone":"+33 4 77 74 07 94",
    "sg:postcode":"42270",
    "sg:province":"Rhone-Alpes",
    "wof:name":"S.o.r.e.c.a.l. S.a. - Soci\u00e9t\u00e9 R\u00e9gionale D'isolation Et Calorifuge",
    "wof:placetype":"venue"
},
  "geometry": {"coordinates":[-93.765739,35.824165],"type":"Point"}
}