{
  "type": "Feature",
  "properties": {
    "addr:full":"Usine des Douves Tiffauges Pays de Loire 85130",
    "addr:postcode":"85130",
    "iso:country":"FR",
    "sg:address":"Usine des Douves",
    "sg:city":"Tiffauges",
    "sg:orig_category":"Non-Classified Establishments",
    "sg:phone":"+33 2 51 65 75 75",
    "sg:postcode":"85130",
    "sg:province":"Pays de Loire",
    "wof:name":"Lussault Outillage S.a.s.",
    "wof:placetype":"venue"
},
  "geometry": {"coordinates":[-1.133929,46.907703],"type":"Point"}
}