{
  "type": "Feature",
  "properties": {
    "iso:country":"FR",
    "sg:address":"Buxerulles",
    "sg:city":"Buxi\u00e8res sous les C\u00f4tes",
    "sg:orig_category":"Non-Classified Establishments",
    "sg:phone":"+33 3 29 89 36 14",
    "sg:postcode":"55300",
    "sg:province":"Lorraine",
    "wof:name":"Robatech S.a.",
    "wof:placetype":"venue"
},
  "geometry": {"coordinates":[5.541056,48.891834],"type":"Point"}
}