{
  "type": "Feature",
  "properties": {
    "addr:full":"269 Rue St Denis 75002 Paris Ile de France 75002",
    "addr:housenumber":"269",
    "addr:postcode":"75002;75002",
    "addr:street":"Rue St Denis",
    "iso:country":"FR",
    "sg:address":"269 Rue St Denis 75002 Paris",
    "sg:classifiers":[
        {
            "category":"Shopping",
            "subcategory":"Clothing, Apparel, & Fashions",
            "type":"Retail Goods"
        }
    ],
    "sg:phone":"+33 1 45 08 07 24",
    "sg:postcode":"75002",
    "sg:province":"Ile de France",
    "sg:tags":[
        "textile",
        "clothing",
        "clothes"
    ],
    "wof:name":"Cpp Fel Deux",
    "wof:placetype":"venue"
},
  "geometry": {"coordinates":[2.351845,48.868546],"type":"Point"}
}