{
  "type": "Feature",
  "properties": {
    "addr:full":"Domaine De Conquet 26780 CHATEAUNEUF DU RHONE Rhone-Alpes 26780",
    "addr:postcode":"26780;26780",
    "addr:street":"Rhone-Alpes",
    "iso:country":"FR",
    "sg:address":"Domaine De Conquet 26780 CHATEAUNEUF DU RHONE",
    "sg:classifiers":[
        {
            "category":"Food & Beverages",
            "subcategory":"Fruits & Vegetables",
            "type":"Retail Goods"
        }
    ],
    "sg:phone":"+33 4 75 90 72 29",
    "sg:postcode":"26780",
    "sg:province":"Rhone-Alpes",
    "wof:name":"Sca Domaine De Conquet",
    "wof:placetype":"venue"
},
  "geometry": {"coordinates":[4.759943,44.507416],"type":"Point"}
}