{
  "type": "Feature",
  "properties": {
    "addr:full":"5, Rue Toussaint Catros, 33185 Le Haillan Le Haillan Aquitaine 33185",
    "addr:housenumber":"5;haillan;haillan",
    "addr:postcode":"33185;33185",
    "addr:street":"Rue Toussaint Catros",
    "iso:country":"FR",
    "sg:address":"5, Rue Toussaint Catros, 33185 Le Haillan",
    "sg:city":"Le Haillan",
    "sg:orig_category":"Non-Classified Establishments",
    "sg:phone":"+33 5 56 34 02 02",
    "sg:postcode":"33185",
    "sg:province":"Aquitaine",
    "wof:name":"Livra France Express S.a.",
    "wof:placetype":"venue"
},
  "geometry": {"coordinates":[-0.694099,44.854679],"type":"Point"}
}