{
  "type": "Feature",
  "properties": {
    "addr:full":"B.P. 133, 71603 Paray le Monial C\u00e9dex^^ZA Champ Bossu, 71600 Paray le Monial Varenne-Saint-Germain Bourgogne 71600",
    "addr:housenumber":"b.p. 133",
    "addr:postcode":"71603;71600;71600",
    "addr:street":"Champ Bossu",
    "iso:country":"FR",
    "sg:address":"B.P. 133, 71603 Paray le Monial C\u00e9dex^^ZA Champ Bossu, 71600 Paray le Monial",
    "sg:city":"Varenne-Saint-Germain",
    "sg:orig_category":"Non-Classified Establishments",
    "sg:phone":"+33 3 85 81 50 20",
    "sg:postcode":"71600",
    "sg:province":"Bourgogne",
    "wof:name":"S.p.c.m. S.a.r.l. - Soci\u00e9t\u00e9 Parodienne De Constructions M\u00e9talliques",
    "wof:placetype":"venue"
},
  "geometry": {"coordinates":[4.127668,46.384384],"type":"Point"}
}