{
  "type": "Feature",
  "properties": {
    "addr:full":"Rue des Verroti\u00e8res - ZI des Dunes Calais Nord Pas-de-Calais 62100",
    "addr:postcode":"62100",
    "addr:street":"Rue Des Verrotie\u0300Res Zi Des Dunes Calais Nord",
    "iso:country":"FR",
    "sg:address":"Rue des Verroti\u00e8res - ZI des Dunes",
    "sg:city":"Calais",
    "sg:orig_category":"Non-Classified Establishments",
    "sg:phone":"+33 3 21 46 09 46",
    "sg:postcode":"62100",
    "sg:province":"Nord Pas-de-Calais",
    "wof:name":"Gressier Et Fils S.a.r.l.",
    "wof:placetype":"venue"
},
  "geometry": {"coordinates":[1.85305,50.953079],"type":"Point"}
}