{
  "type": "Feature",
  "properties": {
    "iso:country":"FR",
    "sg:address":"18, Rue de la Motte, 35770 Vern sur Seiche",
    "sg:city":"Vern-sur-Seiche",
    "sg:orig_category":"Non-Classified Establishments",
    "sg:phone":"+33 2 99 04 84 60",
    "sg:postcode":"35770",
    "sg:province":"Bretagne",
    "wof:name":"B.c.i.g. S.a.r.l. - Bremont C\u00e2blage Industriel Gravure",
    "wof:placetype":"venue"
},
  "geometry": {"coordinates":[-1.608709,48.06152],"type":"Point"}
}