{
  "type": "Feature",
  "properties": {
    "addr:full":"La Pyr\u00e9n\u00e9enne - B\u00e2t. Strat\u00e8ge Lab\u00e8ge Midi Pyr\u00e9n\u00e9es 31670",
    "addr:postcode":"31670",
    "iso:country":"FR",
    "sg:address":"La Pyr\u00e9n\u00e9enne - B\u00e2t. Strat\u00e8ge",
    "sg:city":"Lab\u00e8ge",
    "sg:orig_category":"Unclassifiable Establishments",
    "sg:phone":"+33 5 61 39 11 21",
    "sg:postcode":"31670",
    "sg:province":"Midi Pyr\u00e9n\u00e9es",
    "wof:name":"Dionex S.a.",
    "wof:placetype":"venue"
},
  "geometry": {"coordinates":[1.50298,43.549999],"type":"Point"}
}