{
  "type": "Feature",
  "properties": {
    "addr:full":"54 rue de Poissy; S. Germain en Laye; 78100 Ile de France 78100",
    "addr:housenumber":"54",
    "addr:postcode":"78100;78100",
    "addr:street":"Rue De Poissy S. Germain En Laye;France",
    "iso:country":"FR",
    "sg:address":"54 rue de Poissy; S. Germain en Laye; 78100",
    "sg:classifiers":[
        {
            "category":"Banks & Credit Unions",
            "subcategory":"Bank",
            "type":"Services"
        }
    ],
    "sg:phone":"+33 3334517432",
    "sg:postcode":"78100",
    "sg:province":"Ile de France",
    "wof:name":"Cr\u00e9dit Foncier De France",
    "wof:placetype":"venue"
},
  "geometry": {"coordinates":[2.089648,48.897873],"type":"Point"}
}