{
  "type": "Feature",
  "properties": {
    "addr:full":"4, Rue du Moulin, 77940 Blennes Ile de France",
    "addr:housenumber":"4",
    "addr:postcode":"77940",
    "addr:street":"Rue Du Moulin;Ile De France",
    "iso:country":"FR",
    "sg:address":"4, Rue du Moulin, 77940 Blennes",
    "sg:orig_category":"Unclassifiable Establishments",
    "sg:phone":"+33 1 64 31 93 24",
    "sg:province":"Ile de France",
    "wof:name":"Soci\u00e9t\u00e9 Anonyme Des Anciens Etablissements Ducrocq S.a.r.l.",
    "wof:placetype":"venue"
},
  "geometry": {"coordinates":[3.007889,48.266697],"type":"Point"}
}