{
  "type": "Feature",
  "properties": {
    "addr:full":"1, Rue Pierre Montet, 67082 Strasbourg C\u00e9dex Strasbourg Alsace 67000",
    "addr:housenumber":"1",
    "addr:postcode":"67082;ce\u0301dex;67000",
    "addr:street":"Rue Pierre Montet",
    "iso:country":"FR",
    "sg:address":"1, Rue Pierre Montet, 67082 Strasbourg C\u00e9dex",
    "sg:city":"Strasbourg",
    "sg:orig_category":"Non-Classified Establishments",
    "sg:phone":"+33 3 88 25 92 92",
    "sg:postcode":"67000",
    "sg:province":"Alsace",
    "wof:name":"D.r.i.r.e. - Direction R\u00e9gionale De L'industrie De La Recherche Et De L'environnement",
    "wof:placetype":"venue"
},
  "geometry": {"coordinates":[7.761515,48.578781],"type":"Point"}
}