{
  "type": "Feature",
  "properties": {
    "addr:full":"11, Rue des Alouettes, 95140 Garges l\u00e8s Gonesse Ile de France 95140",
    "addr:housenumber":"11",
    "addr:postcode":"95140;95140",
    "addr:street":"Rue Des Alouettes",
    "iso:country":"FR",
    "sg:address":"11, Rue des Alouettes, 95140 Garges l\u00e8s Gonesse",
    "sg:orig_category":"Non-Classified Establishments",
    "sg:phone":"+33 1 39 93 08 35",
    "sg:postcode":"95140",
    "sg:province":"Ile de France",
    "wof:name":"Alphasec",
    "wof:placetype":"venue"
},
  "geometry": {"coordinates":[2.411374,48.96244],"type":"Point"}
}