{
  "type": "Feature",
  "properties": {
    "addr:full":"B.P. 23, 70160 Faverney^^Rue de Vesoul, 70160 Faverney Franche Comt\u00e9",
    "addr:postcode":"70160;70160",
    "addr:street":"B.P. 23;Franche Comte\u0301",
    "iso:country":"FR",
    "sg:address":"B.P. 23, 70160 Faverney^^Rue de Vesoul, 70160 Faverney",
    "sg:orig_category":"Non-Classified Establishments",
    "sg:phone":"+33 3 84 91 30 11",
    "sg:province":"Franche Comt\u00e9",
    "wof:name":"Pr\u00e9famat S.a.r.l.",
    "wof:placetype":"venue"
},
  "geometry": {"coordinates":[6.105665,47.768379],"type":"Point"}
}