{
  "type": "Feature",
  "properties": {
    "iso:country":"FR",
    "sg:address":"Braguillou 82170 Fabas",
    "sg:orig_category":"Unclassifiable Establishments",
    "sg:phone":"+33 5 63 64 12 00",
    "sg:province":"Midi Pyr\u00e9n\u00e9es",
    "wof:name":"Sa.po.me.ca S.a.r.l.",
    "wof:placetype":"venue"
},
  "geometry": {"coordinates":[1.296795,43.826965],"type":"Point"}
}