{
  "type": "Feature",
  "properties": {
    "iso:country":"FR",
    "sg:address":"5, Av. Louis Delage - ZA de l' Autodrome, 91310 Linas",
    "sg:orig_category":"Non-Classified Establishments",
    "sg:phone":"+33 1 69 80 68 67",
    "sg:province":"Ile de France",
    "wof:name":"Mondial Frigo I.f.c. S.a.s.",
    "wof:placetype":"venue"
},
  "geometry": {"coordinates":[2.265409,48.627949],"type":"Point"}
}