{
  "type": "Feature",
  "properties": {
    "iso:country":"FR",
    "sg:address":"1, Rue Jean-Baptiste Mathias, 73200 Albertville",
    "sg:orig_category":"Unclassifiable Establishments",
    "sg:phone":"+33 4 79 32 73 73",
    "sg:province":"Rhone-Alpes",
    "wof:name":"Comareg",
    "wof:placetype":"venue"
},
  "geometry": {"coordinates":[6.388308,45.674084],"type":"Point"}
}