{
  "type": "Feature",
  "properties": {
    "addr:full":"100 Avenue Du General Leclerc 93500 Pantin Ile de France 93500",
    "addr:housenumber":"100",
    "addr:postcode":"93500;ile;93500",
    "addr:street":"Avenue Du General Leclerc;France",
    "iso:country":"FR",
    "sg:address":"100 Avenue Du General Leclerc 93500 Pantin",
    "sg:classifiers":[
        {
            "category":"Shopping",
            "subcategory":"Clothing, Apparel, & Fashions",
            "type":"Retail Goods"
        }
    ],
    "sg:phone":"+33 1 49 15 96 96",
    "sg:postcode":"93500",
    "sg:province":"Ile de France",
    "sg:tags":[
        "textile",
        "clothing",
        "clothes"
    ],
    "wof:name":"Eljipe (ljp)",
    "wof:placetype":"venue"
},
  "geometry": {"coordinates":[2.40312,48.896889],"type":"Point"}
}