{
  "type": "Feature",
  "properties": {
    "addr:full":"4, Rue Arc de Triomphe, 17100 Saintes Poitou-Charentes",
    "addr:housenumber":"4",
    "addr:postcode":"17100",
    "addr:street":"Rue Arc De Triomphe",
    "iso:country":"FR",
    "sg:address":"4, Rue Arc de Triomphe, 17100 Saintes",
    "sg:orig_category":"Unclassifiable Establishments",
    "sg:phone":"+33 5 46 74 37 55",
    "sg:province":"Poitou-Charentes",
    "wof:name":"L' Eveil Charentais S.a.r.l.",
    "wof:placetype":"venue"
},
  "geometry": {"coordinates":[-0.628594,45.745716],"type":"Point"}
}