{
  "type": "Feature",
  "properties": {
    "iso:country":"FR",
    "sg:address":"Zone D'Activit\u00e9 Lamboux 56250 Elven",
    "sg:city":"Elven",
    "sg:classifiers":[
        {
            "category":"Professional",
            "type":"Services"
        }
    ],
    "sg:phone":"+33 2 97 53 54 55",
    "sg:postcode":"56250",
    "sg:province":"Bretagne",
    "sg:tags":[
        "transport",
        "road"
    ],
    "wof:name":"Transports Denoual Sas",
    "wof:placetype":"venue"
},
  "geometry": {"coordinates":[-2.58925,47.724258],"type":"Point"}
}