{
  "type": "Feature",
  "properties": {
    "iso:country":"FR",
    "sg:address":"B.P. 34, 03500 Saint Pour\u00e7ain sur Sioule C\u00e9dex^^39, Rue Pierre et Marie Curie - ZI du Pont Pannay, 0",
    "sg:city":"Ch\u00e2tel-de-Neuvre",
    "sg:orig_category":"Non-Classified Establishments",
    "sg:phone":"+33 4 70 45 95 11",
    "sg:postcode":"03500",
    "sg:province":"Auvergne",
    "wof:name":"Galva Eclair S.a.s.",
    "wof:placetype":"venue"
},
  "geometry": {"coordinates":[3.304218,46.311104],"type":"Point"}
}