{
  "type": "Feature",
  "properties": {
    "addr:full":"Rue Jean Moulin - ZA Devant Nouzon Nouzonville Champagne 08700",
    "addr:postcode":"08700",
    "addr:street":"Rue Jean Moulin Za Devant Nouzon;Champagne",
    "iso:country":"FR",
    "sg:address":"Rue Jean Moulin - ZA Devant Nouzon",
    "sg:city":"Nouzonville",
    "sg:orig_category":"Non-Classified Establishments",
    "sg:phone":"+33 3 24 53 99 99",
    "sg:postcode":"08700",
    "sg:province":"Champagne",
    "wof:name":"Ma\u00e7onneries Pierquin S.a.r.l.",
    "wof:placetype":"venue"
},
  "geometry": {"coordinates":[4.777144,49.816383],"type":"Point"}
}