{
  "type": "Feature",
  "properties": {
    "iso:country":"FR",
    "sg:address":"6/8, Rue de la Garenne, 41000 Blois",
    "sg:city":"Blois",
    "sg:orig_category":"Unclassifiable Establishments",
    "sg:phone":"+33 2 54 74 31 70",
    "sg:postcode":"41000",
    "sg:province":"Centre",
    "wof:name":"Actual Int\u00e9rim S.a.",
    "wof:placetype":"venue"
},
  "geometry": {"coordinates":[1.326784,47.587463],"type":"Point"}
}