{
  "type": "Feature",
  "properties": {
    "addr:full":"6/8, Rue de la Garenne, 41000 Blois Blois Centre 41000",
    "addr:housenumber":"6 / 8",
    "addr:postcode":"41000;41000",
    "addr:street":"Rue De La Garenne",
    "iso:country":"FR",
    "sg:address":"6/8, Rue de la Garenne, 41000 Blois",
    "sg:city":"Blois",
    "sg:orig_category":"Unclassifiable Establishments",
    "sg:phone":"+33 2 54 74 31 70",
    "sg:postcode":"41000",
    "sg:province":"Centre",
    "wof:name":"Actual Int\u00e9rim S.a.",
    "wof:placetype":"venue"
},
  "geometry": {"coordinates":[1.326784,47.587463],"type":"Point"}
}