{
  "type": "Feature",
  "properties": {
    "iso:country":"FR",
    "sg:address":"14, Rue Vannes, 10250 Gy\u00e9 sur Seine",
    "sg:orig_category":"Unclassifiable Establishments",
    "sg:phone":"+33 3 25 38 21 48",
    "sg:province":"Champagne",
    "wof:name":"Champagne Jean Josselinet Et Fils S.a.",
    "wof:placetype":"venue"
},
  "geometry": {"coordinates":[4.429,48.02766],"type":"Point"}
}