{
  "type": "Feature",
  "properties": {
    "iso:country":"FR",
    "sg:address":"Ch\u00e2teau-Abbaye des Monges",
    "sg:city":"Gruissan 11100 Narbonne",
    "sg:classifiers":[
        {
            "category":"Food Court",
            "type":"Food & Drink"
        }
    ],
    "sg:phone":"+33 4 68 32 26 61",
    "sg:postcode":"11100",
    "sg:province":"Languedoc-Roussillon",
    "sg:tags":[
        "product",
        "related"
    ],
    "wof:name":"Abbaye Des Monges",
    "wof:placetype":"venue"
},
  "geometry": {"coordinates":[2.953635,43.119781],"type":"Point"}
}