{
  "type": "Feature",
  "properties": {
    "addr:full":"38, Rte de Saint Omer, 59285 Arneke Nord Pas-de-Calais",
    "addr:housenumber":"38",
    "addr:postcode":"59285",
    "addr:street":"Rte De Saint Omer;Arneke Nord",
    "iso:country":"FR",
    "sg:address":"38, Rte de Saint Omer, 59285 Arneke",
    "sg:orig_category":"Non-Classified Establishments",
    "sg:phone":"+33 3 28 43 08 88",
    "sg:province":"Nord Pas-de-Calais",
    "wof:name":"Etablissements Vaesken S.a.",
    "wof:placetype":"venue"
},
  "geometry": {"coordinates":[2.407394,50.830639],"type":"Point"}
}