{
  "type": "Feature",
  "properties": {
    "addr:full":"14, Rue de la Papeterie, 25350 Mandeure Franche Comt\u00e9",
    "addr:housenumber":"14",
    "addr:postcode":"25350",
    "addr:street":"Rue De La Papeterie;Franche Comte\u0301",
    "iso:country":"FR",
    "sg:address":"14, Rue de la Papeterie, 25350 Mandeure",
    "sg:orig_category":"Unclassifiable Establishments",
    "sg:phone":"+33 3 81 35 20 52",
    "sg:province":"Franche Comt\u00e9",
    "wof:name":"Papeterie De Mandeure S.a.",
    "wof:placetype":"venue"
},
  "geometry": {"coordinates":[6.808257,47.452927],"type":"Point"}
}