{
  "type": "Feature",
  "properties": {
    "addr:full":"Rte de la Mer - ZI Blainville Blainville sur Orne Basse Normandie 14550",
    "addr:postcode":"14550",
    "addr:street":"Rte De La Mer Zi",
    "iso:country":"FR",
    "sg:address":"Rte de la Mer - ZI Blainville",
    "sg:city":"Blainville sur Orne",
    "sg:orig_category":"Non-Classified Establishments",
    "sg:phone":"+33 2 31 33 57 14",
    "sg:postcode":"14550",
    "sg:province":"Basse Normandie",
    "wof:name":"B\u00e9ton De France Normandie",
    "wof:placetype":"venue"
},
  "geometry": {"coordinates":[-0.299093,49.228649],"type":"Point"}
}