{
  "type": "Feature",
  "properties": {
    "addr:full":"Rue d'Activit\u00e9s de la Hainaud- 53500 Ern\u00e9e Pays de Loire 53500",
    "addr:postcode":"53500;53500",
    "addr:street":"Rue D'Activite \u0301S De La Hainaud",
    "iso:country":"FR",
    "sg:address":"Rue",
    "sg:city":"d'Activit\u00e9s de la Hainaud- 53500 Ern\u00e9e",
    "sg:classifiers":[
        {
            "category":"Shopping",
            "subcategory":"Crafts & Fabrics",
            "type":"Retail Goods"
        }
    ],
    "sg:phone":"+33 2 43 05 13 86",
    "sg:postcode":"53500",
    "sg:province":"Pays de Loire",
    "sg:tags":[
        "textile",
        "clothing"
    ],
    "wof:name":"Lancelin Henri (sa)",
    "wof:placetype":"venue"
},
  "geometry": {"coordinates":[-0.923261,48.292484],"type":"Point"}
}