{
  "type": "Feature",
  "properties": {
    "iso:country":"FR",
    "sg:address":"7, Avenue - sac postal 2 M I N - Bat e2 Cases 6 A 18, 59465 Lomme C\u00e9dex",
    "sg:orig_category":"Unclassifiable Establishments",
    "sg:phone":"+33 3 20 93 93 33",
    "sg:province":"Montana",
    "wof:name":"Santolaria S.a.",
    "wof:placetype":"venue"
},
  "geometry": {"coordinates":[-110.746384,46.957161],"type":"Point"}
}