{
  "type": "Feature",
  "properties": {
    "addr:full":"7, Avenue - sac postal 2 M I N - Bat e2 Cases 6 A 18, 59465 Lomme C\u00e9dex Montana",
    "addr:housenumber":"7;2;6 a 18",
    "addr:postcode":"e2;59465",
    "addr:street":"Avenue Sac Postal;M I N;Cases",
    "iso:country":"FR",
    "sg:address":"7, Avenue - sac postal 2 M I N - Bat e2 Cases 6 A 18, 59465 Lomme C\u00e9dex",
    "sg:orig_category":"Unclassifiable Establishments",
    "sg:phone":"+33 3 20 93 93 33",
    "sg:province":"Montana",
    "wof:name":"Santolaria S.a.",
    "wof:placetype":"venue"
},
  "geometry": {"coordinates":[-110.74638400000001,46.957161],"type":"Point"}
}