{
  "type": "Feature",
  "properties": {
    "addr:full":"quartier Peyrou 07200 Vesseaux Rhone-Alpes 07200",
    "addr:postcode":"07200;07200",
    "addr:street":"Quartier Peyrou;Rhone-Alpes",
    "iso:country":"FR",
    "sg:address":"quartier Peyrou 07200 Vesseaux",
    "sg:classifiers":[
        {
            "category":"Food & Beverages",
            "subcategory":"Fruits & Vegetables",
            "type":"Retail Goods"
        }
    ],
    "sg:phone":"+33 4 75 93 32 91",
    "sg:postcode":"07200",
    "sg:province":"Rhone-Alpes",
    "wof:name":"Ste Expl Ets Chabert Et Fils Sarl",
    "wof:placetype":"venue"
},
  "geometry": {"coordinates":[4.444635,44.652699],"type":"Point"}
}