{
  "type": "Feature",
  "properties": {
    "addr:full":"4, Rue Nansouty, 75014 Paris Ile de France 75014",
    "addr:housenumber":"4",
    "addr:postcode":"75014;75014",
    "addr:street":"Rue Nansouty",
    "iso:country":"FR",
    "sg:address":"4, Rue Nansouty, 75014 Paris",
    "sg:orig_category":"Non-Classified Establishments",
    "sg:phone":"+33 1 45 89 40 21",
    "sg:postcode":"75014",
    "sg:province":"Ile de France",
    "wof:name":"Edition Dusserre S.a.",
    "wof:placetype":"venue"
},
  "geometry": {"coordinates":[2.335783,48.823963],"type":"Point"}
}