{
  "type": "Feature",
  "properties": {
    "addr:full":"570, Rue du Valibout, 78370 Plaisir Ile de France",
    "addr:housenumber":"570",
    "addr:postcode":"78370",
    "addr:street":"Rue Du Valibout",
    "iso:country":"FR",
    "sg:address":"570, Rue du Valibout, 78370 Plaisir",
    "sg:orig_category":"Non-Classified Establishments",
    "sg:phone":"+33 1 30 55 91 56",
    "sg:province":"Ile de France",
    "wof:name":"Isolkit S.a.",
    "wof:placetype":"venue"
},
  "geometry": {"coordinates":[1.957715,48.82082],"type":"Point"}
}