{
  "type": "Feature",
  "properties": {
    "addr:full":"B.P. 27, 57590 Delme^^Rue Maurice Vautrin, 57590 Delme Lorraine",
    "addr:postcode":"57590;57590",
    "addr:street":"B.P. 27;Maurice Vautrin",
    "iso:country":"FR",
    "sg:address":"B.P. 27, 57590 Delme^^Rue Maurice Vautrin, 57590 Delme",
    "sg:orig_category":"Non-Classified Establishments",
    "sg:phone":"+33 3 87 01 36 83",
    "sg:province":"Lorraine",
    "wof:name":"Pneus Diffusion S.a.",
    "wof:placetype":"venue"
},
  "geometry": {"coordinates":[6.39156,48.88731],"type":"Point"}
}