{
  "type": "Feature",
  "properties": {
    "addr:full":"73, Av. de la Madrague de Montredon, 13008 Marseille Poitou-Charentes",
    "addr:postcode":"13008",
    "addr:street":"73 Av. De La Madrague De Montredon",
    "iso:country":"FR",
    "sg:address":"73, Av. de la Madrague de Montredon, 13008 Marseille",
    "sg:orig_category":"Non-Classified Establishments",
    "sg:phone":"+33 4 91 16 76 00",
    "sg:province":"Poitou-Charentes",
    "wof:name":"Rossi Boissons S.a.",
    "wof:placetype":"venue"
},
  "geometry": {"coordinates":[5.362021,43.236073],"type":"Point"}
}