{
  "type": "Feature",
  "properties": {
    "iso:country":"FR",
    "sg:address":"1 Rue Jules Verne 44700 Orvault",
    "sg:classifiers":[
        {
            "category":"Banks & Credit Unions",
            "subcategory":"Financial Services",
            "type":"Services"
        }
    ],
    "sg:phone":"+33 2 28 09 03 00",
    "sg:postcode":"44700",
    "sg:province":"Pays de Loire",
    "sg:tags":[
        "banking",
        "insurance",
        "institution",
        "finance"
    ],
    "wof:name":"Euvoxa Services Sa",
    "wof:placetype":"venue"
},
  "geometry": {"coordinates":[-1.615495,47.253685],"type":"Point"}
}