{
  "type": "Feature",
  "properties": {
    "iso:country":"FR",
    "sg:address":"66, Rue des Chantiers de France, 59140 Dunkerque",
    "sg:orig_category":"Unclassifiable Establishments",
    "sg:phone":"+33 3 28 22 64 40",
    "sg:province":"Nord Pas-de-Calais",
    "wof:name":"Dunkerque Promotion",
    "wof:placetype":"venue"
},
  "geometry": {"coordinates":[2.381335,51.046505],"type":"Point"}
}