{
  "type": "Feature",
  "properties": {
    "addr:full":"Route Stade 23600 Boussac Limousin 23600",
    "addr:postcode":"23600;23600",
    "addr:street":"Route Stade",
    "iso:country":"FR",
    "sg:address":"Route Stade 23600 Boussac",
    "sg:classifiers":[
        {
            "category":"Professional",
            "subcategory":"Engineering",
            "type":"Services"
        }
    ],
    "sg:phone":"+33 5 55 82 40 00",
    "sg:postcode":"23600",
    "sg:province":"Limousin",
    "sg:tags":[
        "machine",
        "-",
        "mechanical"
    ],
    "wof:name":"Dagard Sa",
    "wof:placetype":"venue"
},
  "geometry": {"coordinates":[2.23043,46.349628],"type":"Point"}
}