{
  "type": "Feature",
  "properties": {
    "iso:country":"FR",
    "sg:address":"250 bis, Bd Jean Jaur\u00e8s, 92100 Boulogne Billancourt",
    "sg:orig_category":"Non-Classified Establishments",
    "sg:phone":"+33 1 49 10 99 88",
    "sg:postcode":"92100",
    "sg:province":"Ile de France",
    "wof:name":"Arizona S.a.r.l.",
    "wof:placetype":"venue"
},
  "geometry": {"coordinates":[2.246448,48.828014],"type":"Point"}
}