{
  "type": "Feature",
  "properties": {
    "addr:full":"30 route de Marray CHAMBOURG SUR INDRE 37310",
    "addr:housenumber":"30",
    "addr:postcode":"37310",
    "addr:street":"Route De Marray Chambourg Sur Indre",
    "iso:country":"FR",
    "sg:address":"30 route de Marray",
    "sg:city":"CHAMBOURG SUR INDRE",
    "sg:classifiers":[
        {
            "category":"Professional",
            "subcategory":"Management & Consulting",
            "type":"Services"
        }
    ],
    "sg:postcode":"37310",
    "sg:tags":[
        "maple",
        "control",
        "cms",
        "ecommerce"
    ],
    "sg:website":"http://www.3sigma.fr",
    "wof:name":"3Sigma",
    "wof:placetype":"venue"
},
  "geometry": {"coordinates":[0.975455,47.166583],"type":"Point"}
}