{
  "type": "Feature",
  "properties": {
    "iso:country":"FR",
    "sg:address":"15, Rue Amp\u00e8re, 01100 Oyonnax",
    "sg:orig_category":"Non-Classified Establishments",
    "sg:phone":"+33 4 74 81 71 71",
    "sg:province":"Rhone-Alpes",
    "wof:name":"Zanini France S.a.",
    "wof:placetype":"venue"
},
  "geometry": {"coordinates":[5.665318,46.266354],"type":"Point"}
}