{
  "type": "Feature",
  "properties": {
    "iso:country":"FR",
    "sg:address":"Rue Clement Ader Zi Pic 09100 Pamiers",
    "sg:classifiers":[
        {
            "category":"Utilities",
            "subcategory":"Telephone",
            "type":"Services"
        }
    ],
    "sg:phone":"+33 5 61 68 02 66",
    "sg:province":"Midi Pyr\u00e9n\u00e9es",
    "sg:tags":[
        "telecommunication"
    ],
    "wof:name":"Chausson Publicite",
    "wof:placetype":"venue"
},
  "geometry": {"coordinates":[1.60874,43.119801],"type":"Point"}
}