{
  "type": "Feature",
  "properties": {
    "iso:country":"FR",
    "sg:address":"ZA la Lauzi\u00e8re",
    "sg:city":"La Batie Neuve",
    "sg:orig_category":"Non-Classified Establishments",
    "sg:phone":"+33 4 92 50 95 30",
    "sg:postcode":"05230",
    "sg:province":"Haute Normandie",
    "wof:name":"A.m.t.e. S.a. - Alpes M\u00e9diterran\u00e9e Technologies Electriques",
    "wof:placetype":"venue"
},
  "geometry": {"coordinates":[6.207653,44.563091],"type":"Point"}
}