{
  "type": "Feature",
  "properties": {
    "iso:country":"FR",
    "sg:address":"Bourg 71220 Martigny Le Comte",
    "sg:city":"Ballore",
    "sg:classifiers":[
        {
            "category":"Professional",
            "subcategory":"Engineering",
            "type":"Services"
        }
    ],
    "sg:phone":"+33 3 85 24 42 98",
    "sg:postcode":"71220",
    "sg:province":"Bourgogne",
    "sg:tags":[
        "machine",
        "-",
        "mechanical"
    ],
    "wof:name":"Fricaud (ets) Sa",
    "wof:placetype":"venue"
},
  "geometry": {"coordinates":[4.398024,46.40279],"type":"Point"}
}