{
  "type": "Feature",
  "properties": {
    "addr:full":"10, Rue Gutenberg - ZAC de la Butte, 91620 Nozay Ile de France",
    "addr:housenumber":"10",
    "addr:postcode":"91620;ile",
    "addr:street":"Rue Gutenberg Zac De La Butte",
    "iso:country":"FR",
    "sg:address":"10, Rue Gutenberg - ZAC de la Butte, 91620 Nozay",
    "sg:orig_category":"Unclassifiable Establishments",
    "sg:phone":"+33 1 64 49 82 29",
    "sg:province":"Ile de France",
    "wof:name":"Soppelsa V.l.g. S.a.",
    "wof:placetype":"venue"
},
  "geometry": {"coordinates":[2.242235,48.66037],"type":"Point"}
}