{
  "type": "Feature",
  "properties": {
    "addr:full":"18 Square Edouard Vii 75009 Paris Ile de France 75009",
    "addr:housenumber":"18",
    "addr:postcode":"75009;75009",
    "addr:street":"Square Edouard Vii",
    "iso:country":"FR",
    "sg:address":"18 Square Edouard Vii 75009 Paris",
    "sg:classifiers":[
        {
            "category":"Building & Trades",
            "subcategory":"Equipment Rental",
            "type":"Services"
        }
    ],
    "sg:phone":"+33 1 68 18 50 00",
    "sg:postcode":"75009",
    "sg:province":"Ile de France",
    "sg:tags":[
        "environment",
        "advice",
        "-",
        "machinery",
        "business"
    ],
    "wof:name":"Sita",
    "wof:placetype":"venue"
},
  "geometry": {"coordinates":[2.329019,48.871246],"type":"Point"}
}