{
  "type": "Feature",
  "properties": {
    "addr:full":"42 avenue de la Grande Arm\u00e9e Paris Ile de France 75017",
    "addr:housenumber":"42",
    "addr:postcode":"75017",
    "addr:street":"Avenue De La Grande Arme\u0301E",
    "iso:country":"FR",
    "sg:address":"42 avenue de la Grande Arm\u00e9e",
    "sg:city":"Paris",
    "sg:classifiers":[
        {
            "category":"Banks & Credit Unions",
            "subcategory":"Financial Services",
            "type":"Services"
        }
    ],
    "sg:phone":"+33 1 45 72 63 10",
    "sg:postcode":"75017",
    "sg:province":"Ile de France",
    "sg:tags":[
        "banking",
        "finance",
        "insurance"
    ],
    "wof:name":"G.s.c (garantie Sociale Des Chefs D'entreprises)",
    "wof:placetype":"venue"
},
  "geometry": {"coordinates":[2.288483,48.876217],"type":"Point"}
}