{
  "type": "Feature",
  "properties": {
    "addr:full":"34, Rue de Bagneaux, 45140 Saint Jean de la Ruelle Ingr\u00e9 Centre 45140",
    "addr:housenumber":"34",
    "addr:postcode":"45140;45140",
    "addr:street":"Rue De Bagneaux;La Ruelle Ingre\u0301",
    "iso:country":"FR",
    "sg:address":"34, Rue de Bagneaux, 45140 Saint Jean de la Ruelle",
    "sg:city":"Ingr\u00e9",
    "sg:orig_category":"Unclassifiable Establishments",
    "sg:phone":"+33 2 38 70 40 06",
    "sg:postcode":"45140",
    "sg:province":"Centre",
    "wof:name":"Ifti S.a.r.l. - Institut De Formation Aux Technologies Industriel",
    "wof:placetype":"venue"
},
  "geometry": {"coordinates":[1.879571,47.915283],"type":"Point"}
}