{
  "type": "Feature",
  "properties": {
    "addr:full":"Rue Du Chesnay Beauregard 35760 St Gregoire Montgermont Bretagne 35760",
    "addr:postcode":"35760;35760",
    "addr:street":"Rue Du Chesnay Beauregard;Bretagne",
    "iso:country":"FR",
    "sg:address":"Rue Du Chesnay Beauregard 35760 St Gregoire",
    "sg:city":"Montgermont",
    "sg:classifiers":[
        {
            "category":"Government",
            "subcategory":"Department Of Motor Vehicles",
            "type":"Public Place"
        }
    ],
    "sg:phone":"+33 2 99 87 90 50",
    "sg:postcode":"35760",
    "sg:province":"Bretagne",
    "sg:tags":[
        "equipment",
        "industrial",
        "transport",
        "motor-cars"
    ],
    "wof:name":"Norauto Rennes",
    "wof:placetype":"venue"
},
  "geometry": {"coordinates":[-1.690438,48.137001],"type":"Point"}
}