{
  "type": "Feature",
  "properties": {
    "iso:country":"FR",
    "sg:address":"18/20, Av. Edouard Herriot - B\u00e2t. le K\u00e9pler, 92350 Le Plessis Robinson",
    "sg:orig_category":"Non-Classified Establishments",
    "sg:phone":"+33 1 46 31 12 34",
    "sg:postcode":"92350",
    "sg:province":"Ile de France",
    "wof:name":"Albright France S.a.r.l.",
    "wof:placetype":"venue"
},
  "geometry": {"coordinates":[2.25248,48.782349],"type":"Point"}
}