{
  "type": "Feature",
  "properties": {
    "iso:country":"FR",
    "sg:address":"Av Francis Tonner A\u00e9roport 06150 Cannes La Bocca",
    "sg:classifiers":[
        {
            "category":"Professional",
            "subcategory":"Advertising",
            "type":"Services"
        }
    ],
    "sg:phone":"+33 4 93 48 17 11",
    "sg:province":"Rhone-Alpes",
    "sg:tags":[
        "communication",
        "medium"
    ],
    "wof:name":"Action Communication Sarl",
    "wof:placetype":"venue"
},
  "geometry": {"coordinates":[6.98076,43.549374],"type":"Point"}
}