{
  "type": "Feature",
  "properties": {
    "iso:country":"FR",
    "sg:address":"29, Rue Charles Dutreix, 10000 Troyes",
    "sg:orig_category":"Non-Classified Establishments",
    "sg:phone":"+33 3 25 82 53 67",
    "sg:postcode":"10000",
    "sg:province":"Champagne",
    "wof:name":"Asturienne P\u00e9namet S.a.",
    "wof:placetype":"venue"
},
  "geometry": {"coordinates":[4.084286,48.287159],"type":"Point"}
}