{
  "type": "Feature",
  "properties": {
    "addr:full":"B.P. 2036, 69228 Lyon C\u00e9dex 02^^25, Rue Smith, 69002 Lyon Rhone-Alpes 69002",
    "addr:housenumber":"69228;02 ^ ^ 25",
    "addr:postcode":"69002;69002",
    "addr:street":"B.P. 2036;Ce\u0301Dex;Rue Smith",
    "iso:country":"FR",
    "sg:address":"B.P. 2036, 69228 Lyon C\u00e9dex 02^^25, Rue Smith, 69002 Lyon",
    "sg:orig_category":"Non-Classified Establishments",
    "sg:phone":"+33 4 72 77 52 58",
    "sg:postcode":"69002",
    "sg:province":"Rhone-Alpes",
    "wof:name":"Mermet Balas S.a.",
    "wof:placetype":"venue"
},
  "geometry": {"coordinates":[4.828975,45.759399],"type":"Point"}
}