{
  "type": "Feature",
  "properties": {
    "iso:country":"FR",
    "sg:address":"1, Rue du G\u00e9n\u00e9ral de Gaulle, 68290 Masevaux",
    "sg:city":"Masevaux",
    "sg:orig_category":"Unclassifiable Establishments",
    "sg:phone":"+33 3 89 82 46 12",
    "sg:postcode":"68290",
    "sg:province":"Alsace",
    "wof:name":"Etablissements Baumann S.a.",
    "wof:placetype":"venue"
},
  "geometry": {"coordinates":[6.999432,47.77409],"type":"Point"}
}