{
  "type": "Feature",
  "properties": {
    "addr:full":"Za 38790 Diemoz Rhone-Alpes 38790",
    "addr:postcode":"38790;38790",
    "addr:street":"Za",
    "iso:country":"FR",
    "sg:address":"Za 38790 Diemoz",
    "sg:classifiers":[
        {
            "category":"Manufacturing",
            "subcategory":"Metals",
            "type":"Manufacturing & Wholesale Goods"
        }
    ],
    "sg:phone":"+33 4 72 70 29 00",
    "sg:postcode":"38790",
    "sg:province":"Rhone-Alpes",
    "sg:tags":[
        "-",
        "machine",
        "equipment",
        "engineering",
        "machinery",
        "mechanical"
    ],
    "wof:name":"Haironville Sa",
    "wof:placetype":"venue"
},
  "geometry": {"coordinates":[5.079405,45.555649],"type":"Point"}
}