{
  "type": "Feature",
  "properties": {
    "addr:full":"3 place d'Assas 30900 NIMES Languedoc-Roussillon 30900",
    "addr:housenumber":"3",
    "addr:postcode":"30900;30900",
    "addr:street":"Place D'Assas",
    "iso:country":"FR",
    "sg:address":"3 place d'Assas 30900 NIMES",
    "sg:classifiers":[
        {
            "category":"Shopping",
            "subcategory":"Books",
            "type":"Retail Goods"
        }
    ],
    "sg:phone":"+33 4 66 67 63 96",
    "sg:postcode":"30900",
    "sg:province":"Languedoc-Roussillon",
    "wof:name":"Editions Jacqueline Chambon S.a.r.l.",
    "wof:placetype":"venue"
},
  "geometry": {"coordinates":[4.32252,43.824821],"type":"Point"}
}