{
  "type": "Feature",
  "properties": {
    "addr:full":"Rue de Bielle Serres Castet Aquitaine 64121",
    "addr:postcode":"64121",
    "addr:street":"Rue De Bielle Serres",
    "iso:country":"FR",
    "sg:address":"Rue de Bielle",
    "sg:city":"Serres Castet",
    "sg:orig_category":"Unclassifiable Establishments",
    "sg:phone":"+33 5 59 33 38 80",
    "sg:postcode":"64121",
    "sg:province":"Aquitaine",
    "wof:name":"E.c.c.i. S.a.r.l. - Essais De Contr\u00f4le Confirm\u00e9s Industriels",
    "wof:placetype":"venue"
},
  "geometry": {"coordinates":[-0.383805,43.368252],"type":"Point"}
}