{
  "type": "Feature",
  "properties": {
    "addr:full":"104, Rue du Faubourg Saint Honor\u00e9, 75008 Paris Ile de France 75008",
    "addr:housenumber":"104",
    "addr:postcode":"75008;75008",
    "addr:street":"Rue Du Faubourg Saint Honore\u0301",
    "iso:country":"FR",
    "sg:address":"104, Rue du Faubourg Saint Honor\u00e9, 75008 Paris",
    "sg:orig_category":"Non-Classified Establishments",
    "sg:phone":"+33 1 49 24 99 04",
    "sg:postcode":"75008",
    "sg:province":"Ile de France",
    "wof:name":"Atlex S.a.",
    "wof:placetype":"venue"
},
  "geometry": {"coordinates":[2.315356,48.871559],"type":"Point"}
}