{
  "type": "Feature",
  "properties": {
    "addr:full":"Zone Industrielle Le Meux Picardie 60880",
    "addr:postcode":"60880",
    "addr:street":"Zone Industrielle;Meux Picardie",
    "iso:country":"FR",
    "sg:address":"Zone Industrielle",
    "sg:city":"Le Meux",
    "sg:orig_category":"Unclassifiable Establishments",
    "sg:phone":"+33 3 44 91 01 00",
    "sg:postcode":"60880",
    "sg:province":"Picardie",
    "wof:name":"Corne Emballages S.a.",
    "wof:placetype":"venue"
},
  "geometry": {"coordinates":[2.750679,49.361313],"type":"Point"}
}