{
  "type": "Feature",
  "properties": {
    "addr:full":"35 Rue Notre Dame De Nazareth 75003 Paris Ile de France 75003",
    "addr:housenumber":"35",
    "addr:postcode":"75003;75003",
    "addr:street":"Rue Notre Dame De Nazareth",
    "iso:country":"FR",
    "sg:address":"35 Rue Notre Dame De Nazareth 75003 Paris",
    "sg:classifiers":[
        {
            "category":"Shopping",
            "subcategory":"Clothing, Apparel, & Fashions",
            "type":"Retail Goods"
        }
    ],
    "sg:phone":"+33 1 42 77 65 74",
    "sg:postcode":"75003",
    "sg:province":"Ile de France",
    "sg:tags":[
        "textile",
        "clothing",
        "clothes"
    ],
    "wof:name":"Gilric",
    "wof:placetype":"venue"
},
  "geometry": {"coordinates":[2.358043,48.867344],"type":"Point"}
}