{
  "type": "Feature",
  "properties": {
    "addr:full":"465, Rue Fourny, 78530 Buc Ile de France",
    "addr:housenumber":"465",
    "addr:postcode":"78530;ile",
    "addr:street":"Rue Fourny",
    "iso:country":"FR",
    "sg:address":"465, Rue Fourny, 78530 Buc",
    "sg:orig_category":"Unclassifiable Establishments",
    "sg:phone":"+33 1 39 07 18 30",
    "sg:province":"Ile de France",
    "wof:name":"Nosem S.a. - Nouvelle Soci\u00e9t\u00e9 Electro M\u00e9canique",
    "wof:placetype":"venue"
},
  "geometry": {"coordinates":[2.123024,48.764366],"type":"Point"}
}