{
  "type": "Feature",
  "properties": {
    "addr:full":"Bellevue 42110 Civens Rhone-Alpes",
    "addr:postcode":"42110",
    "iso:country":"FR",
    "sg:address":"Bellevue 42110 Civens",
    "sg:classifiers":[
        {
            "category":"Professional",
            "type":"Services"
        }
    ],
    "sg:phone":"+33 4 77 27 05 00",
    "sg:province":"Rhone-Alpes",
    "sg:tags":[
        "transport",
        "road"
    ],
    "wof:name":"Sa Fourchet Frigo",
    "wof:placetype":"venue"
},
  "geometry": {"coordinates":[4.23564,45.760254],"type":"Point"}
}