{
  "type": "Feature",
  "properties": {
    "iso:country":"FR",
    "sg:address":"Moulin de Coureau 71250 Bray",
    "sg:city":"Bray",
    "sg:orig_category":"Non-Classified Establishments",
    "sg:phone":"+33 3 85 50 10 45",
    "sg:postcode":"71250",
    "sg:province":"Bourgogne",
    "wof:name":"Minoterie Forest S.a.",
    "wof:placetype":"venue"
},
  "geometry": {"coordinates":[4.618545,46.388313],"type":"Point"}
}