{
  "type": "Feature",
  "properties": {
    "addr:full":"283 avenue du bois de la Pie 95700 Roissy en France Ile de France 95700",
    "addr:housenumber":"283",
    "addr:postcode":"95700;95700",
    "addr:street":"Avenue Du Bois De La Pie",
    "iso:country":"FR",
    "sg:address":"283 avenue du bois de la Pie 95700 Roissy en France",
    "sg:classifiers":[
        {
            "category":"Military Area",
            "subcategory":"Barracks",
            "type":"Public Place"
        }
    ],
    "sg:phone":"+33 1 48 63 20 46",
    "sg:postcode":"95700",
    "sg:province":"Ile de France",
    "sg:tags":[
        "scale",
        "electronic"
    ],
    "wof:name":"A \u00e0 Z Pesage Gastineau",
    "wof:placetype":"venue"
},
  "geometry": {"coordinates":[2.516582,48.987392],"type":"Point"}
}