{
  "type": "Feature",
  "properties": {
    "iso:country":"FR",
    "sg:address":"4-6, Av. Louis Lumi\u00e8re, 50100 Cherbourg",
    "sg:city":"Cherbourg-Octeville",
    "sg:orig_category":"Non-Classified Establishments",
    "sg:phone":"+33 2 33 44 61 81",
    "sg:postcode":"50100",
    "sg:province":"Basse Normandie",
    "wof:name":"Daher Lhotellier Services S.a.",
    "wof:placetype":"venue"
},
  "geometry": {"coordinates":[-1.616124,49.640484],"type":"Point"}
}