{
  "type": "Feature",
  "properties": {
    "addr:full":"Av. des Congres Royan Poitou-Charentes 17200",
    "addr:postcode":"17200",
    "addr:street":"Av. Des Congres",
    "iso:country":"FR",
    "sg:address":"Av. des Congres",
    "sg:city":"Royan",
    "sg:orig_category":"Unclassifiable Establishments",
    "sg:phone":"+33 5 46 23 00 00",
    "sg:postcode":"17200",
    "sg:province":"Poitou-Charentes",
    "wof:name":"Office De Tourisme De Royan",
    "wof:placetype":"venue"
},
  "geometry": {"coordinates":[-1.031804,45.622372],"type":"Point"}
}