{
  "type": "Feature",
  "properties": {
    "addr:full":"17, Av. du Polygone, 29200 Brest Brest Bretagne 29200",
    "addr:postcode":"29200;29200",
    "addr:street":"17 Av. Du Polygone",
    "iso:country":"FR",
    "sg:address":"17, Av. du Polygone, 29200 Brest",
    "sg:city":"Brest",
    "sg:orig_category":"Non-Classified Establishments",
    "sg:phone":"+33 2 98 49 25 57",
    "sg:postcode":"29200",
    "sg:province":"Bretagne",
    "wof:name":"S\u00e9ma Group",
    "wof:placetype":"venue"
},
  "geometry": {"coordinates":[-4.512554,48.383919],"type":"Point"}
}