{
  "type": "Feature",
  "properties": {
    "addr:full":"6 rue Joseph Jacquard 26100 ROMANS SUR ISERE Rhone-Alpes 26100",
    "addr:housenumber":"6",
    "addr:postcode":"26100;26100",
    "addr:street":"Rue Joseph Jacquard",
    "iso:country":"FR",
    "sg:address":"6 rue Joseph Jacquard 26100 ROMANS SUR ISERE",
    "sg:classifiers":[
        {
            "category":"Manufacturing",
            "subcategory":"Tools & Machinery",
            "type":"Manufacturing & Wholesale Goods"
        }
    ],
    "sg:phone":"+33 4 75 70 48 58",
    "sg:postcode":"26100",
    "sg:province":"Rhone-Alpes",
    "sg:tags":[
        "industrial",
        "handheld"
    ],
    "wof:name":"Regad S.a.r.l.",
    "wof:placetype":"venue"
},
  "geometry": {"coordinates":[5.091587,45.053143],"type":"Point"}
}