{
  "type": "Feature",
  "properties": {
    "iso:country":"FR",
    "sg:address":"1 ave du Mar\u00e9chal Joffre; Chantilly; 60500",
    "sg:classifiers":[
        {
            "category":"Banks & Credit Unions",
            "subcategory":"Bank",
            "type":"Services"
        }
    ],
    "sg:phone":"+33 3344573141",
    "sg:postcode":"60500",
    "sg:province":"Picardie",
    "wof:name":"Soci\u00e9t\u00e9 G\u00e9n\u00e9rale",
    "wof:placetype":"venue"
},
  "geometry": {"coordinates":[2.465221,49.192997],"type":"Point"}
}