{
  "type": "Feature",
  "properties": {
    "addr:full":"1BIS rue de Delemont 68300 ST LOUIS Saint-Louis Alsace 68300",
    "addr:housenumber":"1bis",
    "addr:postcode":"68300;68300",
    "addr:street":"Rue De Delemont",
    "iso:country":"FR",
    "sg:address":"1BIS rue de Delemont 68300 ST LOUIS",
    "sg:city":"Saint-Louis",
    "sg:classifiers":[
        {
            "category":"Utilities",
            "subcategory":"Electric",
            "type":"Services"
        }
    ],
    "sg:phone":"+33 3 89 70 20 11",
    "sg:postcode":"68300",
    "sg:province":"Alsace",
    "sg:tags":[
        "insulation",
        "sheath",
        "electrical",
        "braided"
    ],
    "wof:name":"Ses Sterling Sa",
    "wof:placetype":"venue"
},
  "geometry": {"coordinates":[7.56366,47.58041],"type":"Point"}
}