{
  "type": "Feature",
  "properties": {
    "iso:country":"FR",
    "sg:address":"Z.I. de la Goulgati\u00e8re",
    "sg:city":"Ch\u00e2teaubourg",
    "sg:orig_category":"Non-Classified Establishments",
    "sg:phone":"+33 2 99 62 34 62",
    "sg:postcode":"35220",
    "sg:province":"Bretagne",
    "wof:name":"Etablissements Collet S.a.",
    "wof:placetype":"venue"
},
  "geometry": {"coordinates":[-1.371241,48.095028],"type":"Point"}
}