{
  "type": "Feature",
  "properties": {
    "iso:country":"FR",
    "sg:address":"1 Rue De La Papinerie Zi Roubaix Est 59390 Lys Lez Lannoy",
    "sg:classifiers":[
        {
            "category":"Shopping",
            "subcategory":"Clothing, Apparel, & Fashions",
            "type":"Retail Goods"
        }
    ],
    "sg:phone":"+33 3 20 89 52 00",
    "sg:postcode":"59390",
    "sg:province":"Nord Pas-de-Calais",
    "sg:tags":[
        "textile",
        "clothing",
        "clothes"
    ],
    "wof:name":"La Halle Vetement",
    "wof:placetype":"venue"
},
  "geometry": {"coordinates":[3.215299,50.669788],"type":"Point"}
}