{
  "type": "Feature",
  "properties": {
    "iso:country":"FR",
    "sg:address":"333, Rte de la Bergue, 74380 Cranves Sales",
    "sg:orig_category":"Unclassifiable Establishments",
    "sg:phone":"+33 4 50 39 30 16",
    "sg:province":"Rhone-Alpes",
    "wof:name":"Constructions R. Delucinge S.a.",
    "wof:placetype":"venue"
},
  "geometry": {"coordinates":[6.297123,46.180386],"type":"Point"}
}