{
  "type": "Feature",
  "properties": {
    "addr:full":"Quartier Saint Jean Moustiers Sainte Marie Provence-Alpes-C\u00f4te d'Azur 04360",
    "addr:postcode":"d'azur 04360",
    "addr:street":"Marie",
    "iso:country":"FR",
    "sg:address":"Quartier Saint Jean",
    "sg:city":"Moustiers Sainte Marie",
    "sg:orig_category":"Non-Classified Establishments",
    "sg:phone":"+33 4 92 74 66 41",
    "sg:postcode":"04360",
    "sg:province":"Provence-Alpes-C\u00f4te d'Azur",
    "wof:name":"Fa\u00efencier Lallier S.a.r.l.",
    "wof:placetype":"venue"
},
  "geometry": {"coordinates":[6.22028,43.848461],"type":"Point"}
}