{
  "type": "Feature",
  "properties": {
    "iso:country":"FR",
    "sg:address":"ZI du Petit Parc",
    "sg:city":"Ecquevilly",
    "sg:orig_category":"Non-Classified Establishments",
    "sg:phone":"+33 1 34 75 15 15",
    "sg:postcode":"78920",
    "sg:province":"Ile de France",
    "wof:name":"Henri Portier S.a.",
    "wof:placetype":"venue"
},
  "geometry": {"coordinates":[1.918925,48.949734],"type":"Point"}
}