{
  "type": "Feature",
  "properties": {
    "addr:full":"160, Cours du M\u00e9doc, 33000 Bordeaux Bordeaux Aquitaine 33000",
    "addr:housenumber":"160",
    "addr:postcode":"33000;33000",
    "addr:street":"Cours Du Me\u0301Doc",
    "iso:country":"FR",
    "sg:address":"160, Cours du M\u00e9doc, 33000 Bordeaux",
    "sg:city":"Bordeaux",
    "sg:orig_category":"Unclassifiable Establishments",
    "sg:phone":"+33 5 56 69 11 24",
    "sg:postcode":"33000",
    "sg:province":"Aquitaine",
    "wof:name":"I.f.p.a. S.a. - Institut De Formation Professionnelle Apliqu\u00e9e",
    "wof:placetype":"venue"
},
  "geometry": {"coordinates":[-0.571034,44.861771],"type":"Point"}
}