{
  "type": "Feature",
  "properties": {
    "addr:full":"26, Rue le Puech Radier, 34970 Lattes Languedoc-Roussillon",
    "addr:housenumber":"26",
    "addr:postcode":"34970",
    "addr:street":"Rue Le Puech Radier",
    "iso:country":"FR",
    "sg:address":"26, Rue le Puech Radier, 34970 Lattes",
    "sg:orig_category":"Unclassifiable Establishments",
    "sg:phone":"+33 4 67 99 43 30",
    "sg:province":"Languedoc-Roussillon",
    "wof:name":"Laboratoire Martin-privat S.a.",
    "wof:placetype":"venue"
},
  "geometry": {"coordinates":[3.878906,43.579456],"type":"Point"}
}