{
  "type": "Feature",
  "properties": {
    "addr:full":"405, Av. des Fr\u00e8res Lumi\u00e8re, 69730 Genay Rhone-Alpes",
    "addr:housenumber":"405",
    "addr:postcode":"69730",
    "addr:street":"Av. Des Fre\u0300Res Lumie\u0300Re",
    "iso:country":"FR",
    "sg:address":"405, Av. des Fr\u00e8res Lumi\u00e8re, 69730 Genay",
    "sg:orig_category":"Unclassifiable Establishments",
    "sg:phone":"+33 4 78 91 37 73",
    "sg:province":"Rhone-Alpes",
    "wof:name":"I.p.s. S.a. - Ing\u00e9nierie Produits Services",
    "wof:placetype":"venue"
},
  "geometry": {"coordinates":[4.821161,45.887859],"type":"Point"}
}