{
  "type": "Feature",
  "properties": {
    "addr:full":"5 Rue De La Louviere 25480 Pirey Franche Comt\u00e9",
    "addr:housenumber":"5",
    "addr:postcode":"25480",
    "addr:street":"Rue De La Louviere;Franche Comte\u0301",
    "iso:country":"FR",
    "sg:address":"5 Rue De La Louviere 25480 Pirey",
    "sg:classifiers":[
        {
            "category":"Wholesale",
            "subcategory":"Machinery & Supplies",
            "type":"Manufacturing & Wholesale Goods"
        }
    ],
    "sg:phone":"+33 3 81 48 34 60",
    "sg:province":"Franche Comt\u00e9",
    "sg:tags":[
        "equipment",
        "precision"
    ],
    "wof:name":"Laser Cheval",
    "wof:placetype":"venue"
},
  "geometry": {"coordinates":[5.967546,47.254303],"type":"Point"}
}