{
  "type": "Feature",
  "properties": {
    "iso:country":"FR",
    "sg:address":"95 Boulevard Carnot 06400 Cannes",
    "sg:classifiers":[
        {
            "category":"Health Services",
            "subcategory":"Optometrist",
            "type":"Services"
        }
    ],
    "sg:phone":"+33 4 93 68 06 47",
    "sg:province":"Centre",
    "sg:tags":[
        "instrument",
        "optical",
        "-",
        "precision",
        "equipment"
    ],
    "wof:name":"Optique Carnot Le Capitole Eurl",
    "wof:placetype":"venue"
},
  "geometry": {"coordinates":[7.016559,43.562603],"type":"Point"}
}