{
  "type": "Feature",
  "properties": {
    "iso:country":"FR",
    "sg:address":"4A rue de l'Industrie 67720 Hoerdt",
    "sg:city":"Hoerdt",
    "sg:classifiers":[
        {
            "category":"Manufacturing",
            "subcategory":"Wood Products",
            "type":"Manufacturing & Wholesale Goods"
        }
    ],
    "sg:phone":"+33 3 88 68 22 44",
    "sg:postcode":"67720",
    "sg:province":"Alsace",
    "sg:tags":[
        "insulating",
        "board"
    ],
    "wof:name":"Telewig Sa",
    "wof:placetype":"venue"
},
  "geometry": {"coordinates":[7.795894,48.676208],"type":"Point"}
}