{
  "type": "Feature",
  "properties": {
    "addr:full":"Rte Neuve La Tremblade Poitou-Charentes 17390",
    "addr:postcode":"17390",
    "addr:street":"Rte Neuve La Tremblade",
    "iso:country":"FR",
    "sg:address":"Rte Neuve",
    "sg:city":"La Tremblade",
    "sg:orig_category":"Unclassifiable Establishments",
    "sg:phone":"+33 5 46 36 00 57",
    "sg:postcode":"17390",
    "sg:province":"Poitou-Charentes",
    "wof:name":"Grolleau Bernard",
    "wof:placetype":"venue"
},
  "geometry": {"coordinates":[-1.129774,45.782894],"type":"Point"}
}