{
  "type": "Feature",
  "properties": {
    "iso:country":"FR",
    "sg:address":"44 Rue Ren\u00e9 Lanoy 62300 Lens",
    "sg:classifiers":[
        {
            "category":"Wholesale",
            "subcategory":"Meat",
            "type":"Manufacturing & Wholesale Goods"
        }
    ],
    "sg:phone":"+33 3 21 28 16 53",
    "sg:postcode":"62300",
    "sg:province":"Nord Pas-de-Calais",
    "sg:tags":[
        "food",
        "cooked",
        "product",
        "related"
    ],
    "wof:name":"Sabatier Jean Claude Sarl",
    "wof:placetype":"venue"
},
  "geometry": {"coordinates":[2.833352,50.431328],"type":"Point"}
}