{
  "type": "Feature",
  "properties": {
    "addr:full":"2, Rue de l'Europe - ZI de Carquefou, 44300 Nantes Pays de Loire",
    "addr:housenumber":"2",
    "addr:postcode":"44300",
    "addr:street":"Rue De L'Europe Zi De Carquefou",
    "iso:country":"FR",
    "sg:address":"2, Rue de l'Europe - ZI de Carquefou, 44300 Nantes",
    "sg:orig_category":"Unclassifiable Establishments",
    "sg:phone":"+33 2 40 18 36 36",
    "sg:province":"Pays de Loire",
    "wof:name":"S.a.d. S.a. - Soci\u00e9t\u00e9 D'agences Et De Diffusion",
    "wof:placetype":"venue"
},
  "geometry": {"coordinates":[-1.58314,47.219967],"type":"Point"}
}