{
  "type": "Feature",
  "properties": {
    "addr:full":"54, Rue Tronchet, 69006 Lyon Rhone-Alpes 69006",
    "addr:housenumber":"54",
    "addr:postcode":"69006;69006",
    "addr:street":"Rue Tronchet",
    "iso:country":"FR",
    "sg:address":"54, Rue Tronchet, 69006 Lyon",
    "sg:orig_category":"Non-Classified Establishments",
    "sg:phone":"+33 4 78 89 20 07",
    "sg:postcode":"69006",
    "sg:province":"Rhone-Alpes",
    "wof:name":"Brotteaux-plans Scp S.a.r.l.",
    "wof:placetype":"venue"
},
  "geometry": {"coordinates":[4.849483,45.769852],"type":"Point"}
}