{
  "type": "Feature",
  "properties": {
    "iso:country":"FR",
    "sg:address":"Bd Des Ferri\u00e8res 83490 Le Muy",
    "sg:classifiers":[
        {
            "category":"Manufacturing",
            "subcategory":"Chemicals & Compounds",
            "type":"Manufacturing & Wholesale Goods"
        }
    ],
    "sg:phone":"+33 4 94 45 10 24",
    "sg:province":"Languedoc-Roussillon",
    "sg:tags":[
        "pharmaceutical",
        "chemistry"
    ],
    "wof:name":"Ets Bardon Et Cie",
    "wof:placetype":"venue"
},
  "geometry": {"coordinates":[6.546489,43.475967],"type":"Point"}
}