{
  "type": "Feature",
  "properties": {
    "iso:country":"FR",
    "sg:address":"Rue Saint Eloy",
    "sg:city":"Vergigny",
    "sg:orig_category":"Unclassifiable Establishments",
    "sg:phone":"+33 3 86 43 75 70",
    "sg:postcode":"89600",
    "sg:province":"Bourgogne",
    "wof:name":"Roy Agencements S.a.",
    "wof:placetype":"venue"
},
  "geometry": {"coordinates":[3.715961,47.975868],"type":"Point"}
}