{
  "type": "Feature",
  "properties": {
    "iso:country":"FR",
    "sg:address":"18 pl Commerce; Plouzan\u00e9",
    "sg:classifiers":[
        {
            "category":"Banks & Credit Unions",
            "subcategory":"Bank",
            "type":"Services"
        }
    ],
    "sg:phone":"+33 3398458602",
    "sg:province":"Pays de Loire",
    "wof:name":"Cr\u00e9dit Mutuel De Bretagne",
    "wof:placetype":"venue"
},
  "geometry": {"coordinates":[-4.589543,48.371361],"type":"Point"}
}