{
  "type": "Feature",
  "properties": {
    "addr:full":"B.P. 28, 70140 Broye Aubigney Montseugny^^Rte du Port Saint Pierre, 70140 Broye Aubigney Montseugny Franche Comt\u00e9",
    "addr:postcode":"70140;70140",
    "addr:street":"B.P. 28;Aubigney;Saint Pierre;Aubigney Montseugny Franche Comte\u0301",
    "iso:country":"FR",
    "sg:address":"B.P. 28, 70140 Broye Aubigney Montseugny^^Rte du Port Saint Pierre, 70140 Broye Aubigney Montseugny",
    "sg:orig_category":"Non-Classified Establishments",
    "sg:phone":"+33 3 84 31 60 90",
    "sg:province":"Franche Comt\u00e9",
    "wof:name":"Sodramec S.a.r.l.",
    "wof:placetype":"venue"
},
  "geometry": {"coordinates":[5.568141,47.279697],"type":"Point"}
}