{
  "type": "Feature",
  "properties": {
    "addr:full":"57, Rue de Bourgogne, 75007 Paris Ile de France",
    "addr:housenumber":"57",
    "addr:postcode":"75007",
    "addr:street":"Rue De Bourgogne",
    "iso:country":"FR",
    "sg:address":"57, Rue de Bourgogne, 75007 Paris",
    "sg:orig_category":"Unclassifiable Establishments",
    "sg:phone":"+33 1 44 42 01 61",
    "sg:province":"Ile de France",
    "wof:name":"Art\u00e9lano S.a.",
    "wof:placetype":"venue"
},
  "geometry": {"coordinates":[2.31725,48.856178],"type":"Point"}
}