{
  "type": "Feature",
  "properties": {
    "addr:full":"119, Av. de Lattre de Tassigny, 44500 La Baule Escoublac Pays de Loire",
    "addr:postcode":"44500",
    "addr:street":"119 Av. De Lattre De Tassigny",
    "iso:country":"FR",
    "sg:address":"119, Av. de Lattre de Tassigny, 44500 La Baule Escoublac",
    "sg:orig_category":"Unclassifiable Establishments",
    "sg:phone":"+33 2 40 11 51 51",
    "sg:province":"Pays de Loire",
    "wof:name":"Centre Culturel Et De Congr\u00e8s",
    "wof:placetype":"venue"
},
  "geometry": {"coordinates":[-2.409642,47.282547],"type":"Point"}
}