{
  "type": "Feature",
  "properties": {
    "iso:country":"FR",
    "sg:address":"Rue Arago, 92823 Puteaux, Dept 92",
    "sg:city":"Puteaux",
    "sg:classifiers":[
        {
            "category":"Banks & Credit Unions",
            "subcategory":"Bank",
            "type":"Services"
        }
    ],
    "sg:postcode":"92800",
    "sg:province":"Ile de France",
    "wof:name":"Bnp Bail",
    "wof:placetype":"venue"
},
  "geometry": {"coordinates":[2.24484,48.883961],"type":"Point"}
}