{
  "type": "Feature",
  "properties": {
    "iso:country":"FR",
    "sg:address":"10, Rue Solf\u00e9rino, 92170 Vanves",
    "sg:orig_category":"Non-Classified Establishments",
    "sg:phone":"+33 1 46 45 43 80",
    "sg:postcode":"92170",
    "sg:province":"Ile de France",
    "wof:name":"Actuavision S.a.r.l.",
    "wof:placetype":"venue"
},
  "geometry": {"coordinates":[2.289242,48.823124],"type":"Point"}
}