{
  "type": "Feature",
  "properties": {
    "iso:country":"FR",
    "sg:address":"Rte de Barbazan - Valentine",
    "sg:city":"Saint Gaudens",
    "sg:orig_category":"Unclassifiable Establishments",
    "sg:phone":"+33 5 61 89 90 00",
    "sg:postcode":"31800",
    "sg:province":"Midi Pyr\u00e9n\u00e9es",
    "wof:name":"Sercel S.a.",
    "wof:placetype":"venue"
},
  "geometry": {"coordinates":[0.723251,43.050159],"type":"Point"}
}