{
  "type": "Feature",
  "properties": {
    "addr:full":"21, Av. de Bordeaux, 86490 Beaumont Poitou-Charentes",
    "addr:postcode":"86490",
    "addr:street":"21 Av. De Bordeaux",
    "iso:country":"FR",
    "sg:address":"21, Av. de Bordeaux, 86490 Beaumont",
    "sg:orig_category":"Unclassifiable Establishments",
    "sg:phone":"+33 5 49 85 53 91",
    "sg:province":"Poitou-Charentes",
    "wof:name":"S\u00e9curit Dog Man S.a.r.l.",
    "wof:placetype":"venue"
},
  "geometry": {"coordinates":[0.440061,46.731144],"type":"Point"}
}