{
  "type": "Feature",
  "properties": {
    "iso:country":"FR",
    "sg:address":"1, Rue Alexandre Fleming, 49066 Angers C\u00e9dex",
    "sg:orig_category":"Non-Classified Establishments",
    "sg:phone":"+33 2 41 72 16 90",
    "sg:province":"Pays de la Loire",
    "wof:name":"Shelly S.a.r.l.",
    "wof:placetype":"venue"
},
  "geometry": {"coordinates":[-0.605927,47.477551],"type":"Point"}
}