{
  "type": "Feature",
  "properties": {
    "addr:full":"Av Gabriel Voisin 13300 Salon De Provence Provence-Alpes-C\u00f4te d'Azur",
    "addr:postcode":"13300",
    "addr:street":"Av Gabriel Voisin;Provence",
    "iso:country":"FR",
    "sg:address":"Av Gabriel Voisin 13300 Salon De Provence",
    "sg:classifiers":[
        {
            "category":"Professional",
            "type":"Services"
        }
    ],
    "sg:phone":"+33 4 90 56 55 65",
    "sg:province":"Provence-Alpes-C\u00f4te d'Azur",
    "sg:tags":[
        "transport",
        "road"
    ],
    "wof:name":"Demenagements Robert Sa",
    "wof:placetype":"venue"
},
  "geometry": {"coordinates":[5.049794,43.635189],"type":"Point"}
}