{
  "type": "Feature",
  "properties": {
    "addr:full":"6 Rue Louis Agla\u00e9 Crett\u00e9 94400 Vitry Sur Seine Ile de France 94400",
    "addr:housenumber":"6",
    "addr:postcode":"94400;94400",
    "addr:street":"Rue Louis Aglae\u0301 Crette\u0301;France",
    "iso:country":"FR",
    "sg:address":"6 Rue Louis Agla\u00e9 Crett\u00e9 94400 Vitry Sur Seine",
    "sg:classifiers":[
        {
            "category":"Professional",
            "subcategory":"Computer Services",
            "type":"Services"
        }
    ],
    "sg:phone":"+33 1 45 73 04 51",
    "sg:postcode":"94400",
    "sg:province":"Ile de France",
    "sg:tags":[
        "information",
        "technology",
        "software"
    ],
    "wof:name":"Infaudit Conseil",
    "wof:placetype":"venue"
},
  "geometry": {"coordinates":[2.395327,48.793404],"type":"Point"}
}