{
  "type": "Feature",
  "properties": {
    "iso:country":"FR",
    "sg:address":"45, Chemin des Hirondelles - ZAC du Paisy, 69570 Dardilly",
    "sg:orig_category":"Non-Classified Establishments",
    "sg:phone":"+33 4 78 64 50 50",
    "sg:postcode":"69570",
    "sg:province":"Rhone-Alpes",
    "wof:name":"Gid S.a.",
    "wof:placetype":"venue"
},
  "geometry": {"coordinates":[4.753535,45.805908],"type":"Point"}
}