{
  "type": "Feature",
  "properties": {
    "iso:country":"FR",
    "sg:address":"1 Rue Neuve 27430 St Etienne Du Vauray",
    "sg:classifiers":[
        {
            "category":"Farming",
            "subcategory":"Farm",
            "type":"Manufacturing & Wholesale Goods"
        }
    ],
    "sg:phone":"+33 2 32 59 90 96",
    "sg:postcode":"27430",
    "sg:province":"Haute Normandie",
    "sg:tags":[
        "horticulture",
        "agriculture",
        "livestock"
    ],
    "wof:name":"Cedest Engrais Sa",
    "wof:placetype":"venue"
},
  "geometry": {"coordinates":[4.391736,45.449642],"type":"Point"}
}