{
  "type": "Feature",
  "properties": {
    "iso:country":"FR",
    "sg:address":"ZI La Petite Marine",
    "sg:city":"L'Isle sur la Sorgue",
    "sg:orig_category":"Non-Classified Establishments",
    "sg:phone":"+33 4 90 81 15 15",
    "sg:postcode":"84800",
    "sg:province":"Limousin",
    "wof:name":"G\u00e9dimat Farel Clavel",
    "wof:placetype":"venue"
},
  "geometry": {"coordinates":[5.027958,43.922089],"type":"Point"}
}