{
  "type": "Feature",
  "properties": {
    "iso:country":"FR",
    "sg:address":"38 Rue Augustin Drapiez 59000 Lille",
    "sg:classifiers":[
        {
            "category":"Manufacturing",
            "subcategory":"Paper Products",
            "type":"Manufacturing & Wholesale Goods"
        }
    ],
    "sg:phone":"+33 3 20 88 39 79",
    "sg:province":"Nord Pas-de-Calais",
    "sg:tags":[
        "finished",
        "cardboard",
        "-"
    ],
    "wof:name":"Prodeco Services",
    "wof:placetype":"venue"
},
  "geometry": {"coordinates":[3.052177,50.613617],"type":"Point"}
}