{
  "type": "Feature",
  "properties": {
    "addr:full":"Rue du Pr\u00e9 Didier - ZI le Fontanil Saint Egr\u00e8ve Rhone-Alpes 38120",
    "addr:postcode":"38120",
    "addr:street":"Rue Du Pre\u0301 Didier Zi Le Fontanil Saint;Rhone-Alpes",
    "iso:country":"FR",
    "sg:address":"Rue du Pr\u00e9 Didier - ZI le Fontanil",
    "sg:city":"Saint Egr\u00e8ve",
    "sg:orig_category":"Unclassifiable Establishments",
    "sg:phone":"+33 4 76 75 42 38",
    "sg:postcode":"38120",
    "sg:province":"Rhone-Alpes",
    "wof:name":"Soloplast Vosschemie S.a.",
    "wof:placetype":"venue"
},
  "geometry": {"coordinates":[5.68088,45.232937],"type":"Point"}
}