{
  "type": "Feature",
  "properties": {
    "addr:full":"Rte de Roybon Saint Sim\u00e9on de Bressieux Rhone-Alpes 38870",
    "addr:postcode":"38870",
    "addr:street":"Rte De Roybon Saint Sime\u0301On De Bressieux Rhone-Alpes",
    "iso:country":"FR",
    "sg:address":"Rte de Roybon",
    "sg:city":"Saint Sim\u00e9on de Bressieux",
    "sg:orig_category":"Unclassifiable Establishments",
    "sg:phone":"+33 4 74 20 17 00",
    "sg:postcode":"38870",
    "sg:province":"Rhone-Alpes",
    "wof:name":"Sachs Automotive France S.a.",
    "wof:placetype":"venue"
},
  "geometry": {"coordinates":[5.264201,45.310524],"type":"Point"}
}