{
  "type": "Feature",
  "properties": {
    "addr:full":"Rue Edouard Branly - ZI Mitry Compans Mitry Mory Ile de France 77290",
    "addr:postcode":"77290",
    "addr:street":"Rue Edouard Branly Zi Mitry Compans",
    "iso:country":"FR",
    "sg:address":"Rue Edouard Branly - ZI Mitry Compans",
    "sg:city":"Mitry Mory",
    "sg:orig_category":"Unclassifiable Establishments",
    "sg:phone":"+33 1 60 21 60 21",
    "sg:postcode":"77290",
    "sg:province":"Ile de France",
    "wof:name":"S.m.a. Interacciai S.a. - Soci\u00e9t\u00e9 M\u00e9tallurgique D'aubervilliers",
    "wof:placetype":"venue"
},
  "geometry": {"coordinates":[2.619585,48.984165],"type":"Point"}
}