{
  "type": "Feature",
  "properties": {
    "iso:country":"FR",
    "sg:address":"13-17, Rue Joseph Priestley - ZI la Milleti\u00e8re, 37100 Tours C\u00e9dex^^13-17, Rue Joseph Priestley - ZI ",
    "sg:city":"Tours",
    "sg:orig_category":"Non-Classified Establishments",
    "sg:phone":"+33 2 47 51 20 31",
    "sg:postcode":"37100",
    "sg:province":"Centre",
    "wof:name":"O.c.p R\u00e9paration",
    "wof:placetype":"venue"
},
  "geometry": {"coordinates":[0.69944,47.418121],"type":"Point"}
}