{
  "type": "Feature",
  "properties": {
    "addr:full":"19100 Brive la Gaillarde Limousin 19100",
    "addr:postcode":"19100;19100",
    "iso:country":"FR",
    "sg:address":"19100 Brive la Gaillarde",
    "sg:classifiers":[
        {
            "category":"Wholesale",
            "subcategory":"Wine & Distilled Alcoholic Beverages",
            "type":"Manufacturing & Wholesale Goods"
        }
    ],
    "sg:phone":"+33 5 55 86 90 06",
    "sg:postcode":"19100",
    "sg:province":"Limousin",
    "sg:tags":[
        "french"
    ],
    "wof:name":"C.s.a. S.a.",
    "wof:placetype":"venue"
},
  "geometry": {"coordinates":[1.51439,45.14529],"type":"Point"}
}