{
  "type": "Feature",
  "properties": {
    "addr:full":"M\u00e9ritein 64190 Navarrenx Navarrenx Aquitaine 64190",
    "addr:postcode":"64190;64190",
    "iso:country":"FR",
    "sg:address":"M\u00e9ritein 64190 Navarrenx",
    "sg:city":"Navarrenx",
    "sg:orig_category":"Non-Classified Establishments",
    "sg:phone":"+33 5 59 66 50 77",
    "sg:postcode":"64190",
    "sg:province":"Aquitaine",
    "wof:name":"Soci\u00e9t\u00e9 Exploitation Des Etablissements Poey S.a.",
    "wof:placetype":"venue"
},
  "geometry": {"coordinates":[-0.759604,43.322487],"type":"Point"}
}