{
  "type": "Feature",
  "properties": {
    "addr:full":"34360 Prades sur Vernazobre Languedoc-Roussillon 34360",
    "addr:postcode":"34360;34360",
    "addr:street":"Vernazobre",
    "iso:country":"FR",
    "sg:address":"34360 Prades sur Vernazobre",
    "sg:orig_category":"Non-Classified Establishments",
    "sg:phone":"+33 4 67 38 06 02",
    "sg:postcode":"34360",
    "sg:province":"Languedoc-Roussillon",
    "wof:name":"Domaine Des Jougla S.c.e.a.",
    "wof:placetype":"venue"
},
  "geometry": {"coordinates":[2.984203,43.447792],"type":"Point"}
}