{
  "type": "Feature",
  "properties": {
    "iso:country":"FR",
    "sg:address":"27 Route De La Wantzenau 67800 Hoenheim",
    "sg:city":"Hoenheim",
    "sg:classifiers":[
        {
            "category":"Shopping",
            "subcategory":"Computers & Home Electronics",
            "type":"Retail Goods"
        }
    ],
    "sg:phone":"+33 3 88 83 30 83",
    "sg:postcode":"67800",
    "sg:province":"Alsace",
    "sg:tags":[
        "equipment",
        "household",
        "electrical",
        "appliance",
        "electronic"
    ],
    "wof:name":"Mena Alsace Service",
    "wof:placetype":"venue"
},
  "geometry": {"coordinates":[7.766098,48.63221],"type":"Point"}
}