{
  "type": "Feature",
  "properties": {
    "iso:country":"FR",
    "sg:address":"32, Rue Lavoisier, 17200 Royan",
    "sg:orig_category":"Unclassifiable Establishments",
    "sg:phone":"+33 5 46 05 01 55",
    "sg:province":"Poitou-Charentes",
    "wof:name":"Bonnin Pierre S.a.r.l.",
    "wof:placetype":"venue"
},
  "geometry": {"coordinates":[-1.030124,45.626137],"type":"Point"}
}