{
  "type": "Feature",
  "properties": {
    "addr:full":"B.P. 14, 79440 Courlay^^51, Rue du Boccage, 79440 Courlay Poitou-Charentes 79440",
    "addr:postcode":"79440;79440;79440",
    "addr:street":"B.P. 14;Rue Du Boccage",
    "iso:country":"FR",
    "sg:address":"B.P. 14, 79440 Courlay^^51, Rue du Boccage, 79440 Courlay",
    "sg:orig_category":"Non-Classified Establishments",
    "sg:phone":"+33 5 49 72 31 19",
    "sg:postcode":"79440",
    "sg:province":"Poitou-Charentes",
    "wof:name":"C.2.s. S.a. - Confection Des Deux-s\u00e8vres",
    "wof:placetype":"venue"
},
  "geometry": {"coordinates":[-0.566497,46.779575],"type":"Point"}
}