{
  "type": "Feature",
  "properties": {
    "addr:full":"Ld La Poch\u00e8re 42480 La Fouillouse Rhone-Alpes 42480",
    "addr:postcode":"42480;42480",
    "addr:street":"Ld",
    "iso:country":"FR",
    "sg:address":"Ld La Poch\u00e8re 42480 La Fouillouse",
    "sg:classifiers":[
        {
            "category":"Travel",
            "subcategory":"Hotels & Motels",
            "type":"Entertainment"
        }
    ],
    "sg:phone":"+33 4 77 93 07 30",
    "sg:postcode":"42480",
    "sg:province":"Rhone-Alpes",
    "sg:tags":[
        "hotels",
        "business",
        "restaurant"
    ],
    "wof:name":"Buffalo Grill",
    "wof:placetype":"venue"
},
  "geometry": {"coordinates":[4.342973,45.484634],"type":"Point"}
}