{
  "type": "Feature",
  "properties": {
    "addr:full":"B.P. 52, 39202 Saint Claude C\u00e9dex^^6, Rue du March\u00e9, 39200 Saint Claude Franche Comt\u00e9",
    "addr:postcode":"39202;39200",
    "addr:street":"B.P. 52;Rue Du Marche\u0301;Franche Comte\u0301",
    "iso:country":"FR",
    "sg:address":"B.P. 52, 39202 Saint Claude C\u00e9dex^^6, Rue du March\u00e9, 39200 Saint Claude",
    "sg:orig_category":"Non-Classified Establishments",
    "sg:phone":"+33 3 84 45 72 37",
    "sg:province":"Franche Comt\u00e9",
    "wof:name":"Haut Jura Tourisme",
    "wof:placetype":"venue"
},
  "geometry": {"coordinates":[5.84194,46.34193],"type":"Point"}
}