{
  "type": "Feature",
  "properties": {
    "addr:full":"8, Rue Jean Cocteau, 72190 Coulaines Pays de Loire",
    "addr:housenumber":"8",
    "addr:postcode":"72190",
    "addr:street":"Rue Jean Cocteau",
    "iso:country":"FR",
    "sg:address":"8, Rue Jean Cocteau, 72190 Coulaines",
    "sg:orig_category":"Unclassifiable Establishments",
    "sg:phone":"+33 2 43 54 30 00",
    "sg:province":"Pays de Loire",
    "wof:name":"D\u00e9lices De La Tour S.a.",
    "wof:placetype":"venue"
},
  "geometry": {"coordinates":[0.203778,48.026535],"type":"Point"}
}