{
  "type": "Feature",
  "properties": {
    "iso:country":"FR",
    "sg:address":"17 Rue Le Notre 49016 Angers Cedex 01",
    "sg:classifiers":[
        {
            "category":"Professional",
            "subcategory":"Engineering",
            "type":"Services"
        }
    ],
    "sg:phone":"+33 2 41 73 83 73",
    "sg:province":"Centre",
    "sg:tags":[
        "machine",
        "-",
        "mechanical"
    ],
    "wof:name":"Euraltech Assemblage Sa",
    "wof:placetype":"venue"
},
  "geometry": {"coordinates":[-0.606616,47.477013],"type":"Point"}
}