{
  "type": "Feature",
  "properties": {
    "addr:full":"3 pl Jean Payra; Perpignan; 66853 Champagne",
    "addr:housenumber":"3",
    "addr:postcode":"66853",
    "addr:street":"Pl Jean Payra",
    "iso:country":"FR",
    "sg:address":"3 pl Jean Payra; Perpignan; 66853",
    "sg:classifiers":[
        {
            "category":"Banks & Credit Unions",
            "subcategory":"Bank",
            "type":"Services"
        }
    ],
    "sg:phone":"+33 4 68 51 39 33",
    "sg:province":"Champagne",
    "wof:name":"Banque De France",
    "wof:placetype":"venue"
},
  "geometry": {"coordinates":[2.889693,42.698368],"type":"Point"}
}