{
  "type": "Feature",
  "properties": {
    "iso:country":"FR",
    "sg:address":"10, Rue Augustin Vincent, 49450 Saint Andr\u00e9 de la Marche",
    "sg:orig_category":"Unclassifiable Establishments",
    "sg:phone":"+33 2 41 49 03 80",
    "sg:province":"Pays de Loire",
    "wof:name":"Entreprise Blouin S.a.r.l.",
    "wof:placetype":"venue"
},
  "geometry": {"coordinates":[-0.993389,47.101395],"type":"Point"}
}