{
  "type": "Feature",
  "properties": {
    "addr:full":"B.P. 7 Vincey^^88450 Vincey Lorraine 88450",
    "addr:postcode":"88450",
    "addr:street":"B.P. 7 Vincey^^88450",
    "iso:country":"FR",
    "sg:address":"B.P. 7",
    "sg:city":"Vincey^^88450 Vincey",
    "sg:orig_category":"Non-Classified Establishments",
    "sg:phone":"+33 3 29 68 38 25",
    "sg:postcode":"88450",
    "sg:province":"Lorraine",
    "wof:name":"Tubeurop France S.a.",
    "wof:placetype":"venue"
},
  "geometry": {"coordinates":[6.328075,48.3447],"type":"Point"}
}