{
  "type": "Feature",
  "properties": {
    "iso:country":"FR",
    "sg:address":"6 Av Du Gouverneur Gen L Bin 94100 St Maur Des Fosses",
    "sg:classifiers":[
        {
            "category":"Professional",
            "subcategory":"Printing & Photocopies",
            "type":"Services"
        }
    ],
    "sg:phone":"+33 1 43 97 22 14",
    "sg:province":"Ile de France",
    "sg:tags":[
        "publishing"
    ],
    "wof:name":"Sepia",
    "wof:placetype":"venue"
},
  "geometry": {"coordinates":[2.487022,48.807434],"type":"Point"}
}