{
  "type": "Feature",
  "properties": {
    "addr:full":"175 rue de Belfort 68200 Mulhouse Mulhouse Alsace 68200",
    "addr:housenumber":"175",
    "addr:postcode":"68200;68200",
    "addr:street":"Rue De Belfort",
    "iso:country":"FR",
    "sg:address":"175 rue de Belfort 68200 Mulhouse",
    "sg:city":"Mulhouse",
    "sg:classifiers":[
        {
            "category":"Personal",
            "subcategory":"Skin Care",
            "type":"Services"
        }
    ],
    "sg:phone":"+33 3 89 33 42 55",
    "sg:postcode":"68200",
    "sg:province":"Alsace",
    "sg:tags":[
        "sun",
        "product"
    ],
    "wof:name":"Juvex Sa",
    "wof:placetype":"venue"
},
  "geometry": {"coordinates":[7.298028,47.739101],"type":"Point"}
}