{
  "type": "Feature",
  "properties": {
    "iso:country":"FR",
    "sg:address":"39570 Courlaoux",
    "sg:classifiers":[
        {
            "category":"Food & Beverages",
            "subcategory":"Dairy",
            "type":"Retail Goods"
        }
    ],
    "sg:phone":"+33 3 84 35 30 56",
    "sg:postcode":"39570",
    "sg:province":"Franche Comt\u00e9",
    "sg:tags":[
        "product",
        "related"
    ],
    "wof:name":"Jura Courlaoux",
    "wof:placetype":"venue"
},
  "geometry": {"coordinates":[5.46095,46.66806],"type":"Point"}
}