{
  "type": "Feature",
  "properties": {
    "addr:full":"7 rue Bernard Palissy 75006 Paris Ile de France 75006",
    "addr:housenumber":"7",
    "addr:postcode":"75006;75006",
    "addr:street":"Rue Bernard Palissy",
    "iso:country":"FR",
    "sg:address":"7 rue Bernard Palissy 75006 Paris",
    "sg:classifiers":[
        {
            "category":"Wholesale",
            "subcategory":"Books, Periodicals, & Newspapers",
            "type":"Manufacturing & Wholesale Goods"
        }
    ],
    "sg:phone":"+33 1 44 39 39 20",
    "sg:postcode":"75006",
    "sg:province":"Ile de France",
    "sg:tags":[
        "publisher",
        "book",
        "art"
    ],
    "wof:name":"Editions De Minuit Sarl",
    "wof:placetype":"venue"
},
  "geometry": {"coordinates":[2.331854,48.853039],"type":"Point"}
}