{
  "type": "Feature",
  "properties": {
    "iso:country":"FR",
    "sg:address":"34, Av. des Champs Elys\u00e9es, 75008 Paris",
    "sg:orig_category":"Unclassifiable Establishments",
    "sg:phone":"+33 1 45 34 34 29",
    "sg:province":"Ile de France",
    "wof:name":"T.n.i. S.a.r.l. -top Neg International",
    "wof:placetype":"venue"
},
  "geometry": {"coordinates":[2.307806,48.869858],"type":"Point"}
}