{
  "type": "Feature",
  "properties": {
    "iso:country":"FR",
    "sg:address":"9 Rue Du Trou Samson 95150 Taverny",
    "sg:classifiers":[
        {
            "category":"Wholesale",
            "subcategory":"Medical Equipment & Supplies",
            "type":"Manufacturing & Wholesale Goods"
        }
    ],
    "sg:phone":"+33 1 39 95 30 00",
    "sg:postcode":"95150",
    "sg:province":"Ile de France",
    "sg:tags":[
        "instrument",
        "health",
        "-",
        "precision"
    ],
    "wof:name":"Artisans Reunis Techdental (art) Sa",
    "wof:placetype":"venue"
},
  "geometry": {"coordinates":[2.230359,49.02179],"type":"Point"}
}