{
  "type": "Feature",
  "properties": {
    "addr:full":"Rue Cortalin - ZI P\u00e9chiney Pommeuse Ile de France 77515",
    "addr:postcode":"77515",
    "addr:street":"Rue Cortalin Zi Pe\u0301Chiney",
    "iso:country":"FR",
    "sg:address":"Rue Cortalin - ZI P\u00e9chiney",
    "sg:city":"Pommeuse",
    "sg:orig_category":"Non-Classified Establishments",
    "sg:phone":"+33 1 64 03 99 22",
    "sg:postcode":"77515",
    "sg:province":"Ile de France",
    "wof:name":"Sami",
    "wof:placetype":"venue"
},
  "geometry": {"coordinates":[3.015135,48.816429],"type":"Point"}
}