{
  "type": "Feature",
  "properties": {
    "addr:full":"Impasse Flemming Chasse sur Rh\u00f4ne Rhone-Alpes 38670",
    "addr:postcode":"38670",
    "addr:street":"Impasse Flemming Chasse",
    "iso:country":"FR",
    "sg:address":"Impasse Flemming",
    "sg:city":"Chasse sur Rh\u00f4ne",
    "sg:orig_category":"Non-Classified Establishments",
    "sg:phone":"+33 4 72 49 23 30",
    "sg:postcode":"38670",
    "sg:province":"Rhone-Alpes",
    "wof:name":"Cfr S.a.",
    "wof:placetype":"venue"
},
  "geometry": {"coordinates":[4.793355,45.582935],"type":"Point"}
}