{
  "type": "Feature",
  "properties": {
    "addr:full":"Rue Louis Antoine Beaunier 42160 Andr\u00e9zieux Bouth\u00e9on Rhone-Alpes 42160",
    "addr:postcode":"42160;42160",
    "addr:street":"Rue Louis Antoine Beaunier;Rhone-Alpes",
    "iso:country":"FR",
    "sg:address":"Rue Louis Antoine Beaunier 42160 Andr\u00e9zieux Bouth\u00e9on",
    "sg:classifiers":[
        {
            "category":"Professional",
            "subcategory":"Engineering",
            "type":"Services"
        }
    ],
    "sg:phone":"+33 4 77 36 25 25",
    "sg:postcode":"42160",
    "sg:province":"Rhone-Alpes",
    "sg:tags":[
        "machine",
        "-",
        "environment",
        "equipment",
        "machinery",
        "mechanical"
    ],
    "wof:name":"Ccma",
    "wof:placetype":"venue"
},
  "geometry": {"coordinates":[4.27834,45.5247],"type":"Point"}
}