{
  "type": "Feature",
  "properties": {
    "addr:full":"3 pl de la D\u00e9fense; Puteaux; 92800 Ile de France 92800",
    "addr:housenumber":"3",
    "addr:postcode":"92800 ile;france 92800",
    "addr:street":"Pl De La De\u0301Fense",
    "iso:country":"FR",
    "sg:address":"3 pl de la D\u00e9fense; Puteaux; 92800",
    "sg:classifiers":[
        {
            "category":"Banks & Credit Unions",
            "subcategory":"Bank",
            "type":"Services"
        }
    ],
    "sg:phone":"+33 17764166",
    "sg:postcode":"92800",
    "sg:province":"Ile de France",
    "wof:name":"Banque Nationale De Paris",
    "wof:placetype":"venue"
},
  "geometry": {"coordinates":[2.237553,48.891174],"type":"Point"}
}