{
  "type": "Feature",
  "properties": {
    "iso:country":"FR",
    "sg:address":"B.P. 7507, 29275 Brest C\u00e9dex^^19, Rue de la Villeneuve, 29200 Brest",
    "sg:city":"Brest",
    "sg:orig_category":"Non-Classified Establishments",
    "sg:phone":"+33 2 98 02 04 06",
    "sg:postcode":"29200",
    "sg:province":"Bretagne",
    "wof:name":"Grenat Gestion S.a.r.l.",
    "wof:placetype":"venue"
},
  "geometry": {"coordinates":[-4.486228,48.39024],"type":"Point"}
}