{
  "type": "Feature",
  "properties": {
    "iso:country":"FR",
    "sg:address":"B.P. 12, 70001 Vesoul C\u00e9dex^^ZAC - Espace de la Motte, 70000 Vesoul",
    "sg:orig_category":"Non-Classified Establishments",
    "sg:phone":"+33 3 84 75 21 59",
    "sg:postcode":"70000",
    "sg:province":"Franche Comt\u00e9",
    "wof:name":"Emann Fr\u00e8res S.a.r.l.",
    "wof:placetype":"venue"
},
  "geometry": {"coordinates":[6.034054,47.524078],"type":"Point"}
}