{
  "type": "Feature",
  "properties": {
    "iso:country":"FR",
    "sg:address":"11, Rue Littr\u00e9, 42300 Roanne",
    "sg:orig_category":"Non-Classified Establishments",
    "sg:phone":"+33 4 77 44 09 30",
    "sg:postcode":"42300",
    "sg:province":"Rhone-Alpes",
    "wof:name":"Montrico S.a.",
    "wof:placetype":"venue"
},
  "geometry": {"coordinates":[4.054661,46.040199],"type":"Point"}
}