{
  "type": "Feature",
  "properties": {
    "iso:country":"FR",
    "sg:address":"152 Route Berck 62180 Rang Du Fliers",
    "sg:classifiers":[
        {
            "category":"Transit Center",
            "subcategory":"Freight",
            "type":"Transportation"
        }
    ],
    "sg:phone":"+33 3 21 89 18 18",
    "sg:postcode":"62180",
    "sg:province":"Nord Pas-de-Calais",
    "sg:tags":[
        "metallurgy",
        "pipe",
        "metalworking",
        "sheet"
    ],
    "wof:name":"Safef Rang Du Filiers Snc",
    "wof:placetype":"venue"
},
  "geometry": {"coordinates":[1.645347,50.417374],"type":"Point"}
}