{
  "type": "Feature",
  "properties": {
    "addr:full":"12, Rue des Terres Rouges - ZI Metzange, 57100 Thionville Lorraine",
    "addr:housenumber":"12",
    "addr:postcode":"57100",
    "addr:street":"Rue Des Terres Rouges Zi Metzange",
    "iso:country":"FR",
    "sg:address":"12, Rue des Terres Rouges - ZI Metzange, 57100 Thionville",
    "sg:orig_category":"Unclassifiable Establishments",
    "sg:phone":"+33 3 82 88 61 61",
    "sg:province":"Lorraine",
    "wof:name":"Evatec S.a.r.l.",
    "wof:placetype":"venue"
},
  "geometry": {"coordinates":[6.16909,49.357601],"type":"Point"}
}