{
  "type": "Feature",
  "properties": {
    "addr:full":"Rue Du Santerre 80046 Amiens Amiens Picardie 80000",
    "addr:postcode":"80046 amiens;80000",
    "addr:street":"Rue Du Santerre",
    "iso:country":"FR",
    "sg:address":"Rue Du Santerre 80046 Amiens",
    "sg:city":"Amiens",
    "sg:classifiers":[
        {
            "category":"Transit Center",
            "subcategory":"Freight",
            "type":"Transportation"
        }
    ],
    "sg:phone":"+33 3 22 43 53 68",
    "sg:postcode":"80000",
    "sg:province":"Picardie",
    "sg:tags":[
        "metallurgy",
        "pipe",
        "metalworking",
        "sheet"
    ],
    "wof:name":"Oz Alu",
    "wof:placetype":"venue"
},
  "geometry": {"coordinates":[2.2693,49.932835],"type":"Point"}
}