{
  "type": "Feature",
  "properties": {
    "addr:full":"Grande Rue Guyans Vennes Franche Comt\u00e9 25390",
    "addr:postcode":"25390",
    "addr:street":"Grande Rue Guyans Vennes Franche Comte\u0301",
    "iso:country":"FR",
    "sg:address":"Grande Rue",
    "sg:city":"Guyans Vennes",
    "sg:orig_category":"Unclassifiable Establishments",
    "sg:phone":"+33 3 81 43 60 11",
    "sg:postcode":"25390",
    "sg:province":"Franche Comt\u00e9",
    "wof:name":"T.b.m.b. S.a.r.l. - Terminage De Bo\u00eete De Montre Et Bijouterie",
    "wof:placetype":"venue"
},
  "geometry": {"coordinates":[6.57046,47.156101],"type":"Point"}
}