{
  "type": "Feature",
  "properties": {
    "iso:country":"FR",
    "sg:address":"18, Av. de l'Ile Brune, 38120 Saint Egr\u00e8ve",
    "sg:orig_category":"Unclassifiable Establishments",
    "sg:phone":"+33 4 76 75 70 73",
    "sg:province":"Tennessee",
    "wof:name":"A'stral",
    "wof:placetype":"venue"
},
  "geometry": {"coordinates":[-89.842308,35.12442],"type":"Point"}
}