{
  "type": "Feature",
  "properties": {
    "addr:full":"3 avenue du Luxembourg 54810 Longlaville Lorraine",
    "addr:housenumber":"3",
    "addr:postcode":"54810",
    "addr:street":"Avenue Du Luxembourg",
    "iso:country":"FR",
    "sg:address":"3 avenue du Luxembourg 54810 Longlaville",
    "sg:orig_category":"Poultry, Slaughtered",
    "sg:phone":"+33 3 82 24 33 57",
    "sg:province":"Lorraine",
    "wof:name":"Etablissements Angelini Freres Sarl",
    "wof:placetype":"venue"
},
  "geometry": {"coordinates":[5.794075,49.527996],"type":"Point"}
}