{
  "type": "Feature",
  "properties": {
    "addr:full":"30/32, Av. des Trois Peuples, 78180 Montigny le Bretonneux Ile de France",
    "addr:housenumber":"30 / 32",
    "addr:postcode":"78180",
    "addr:street":"Av. Des Trois Peuples",
    "iso:country":"FR",
    "sg:address":"30/32, Av. des Trois Peuples, 78180 Montigny le Bretonneux",
    "sg:orig_category":"Unclassifiable Establishments",
    "sg:phone":"+33 1 30 12 73 00",
    "sg:province":"Ile de France",
    "wof:name":"S.k.f. Equipements S.a.s.",
    "wof:placetype":"venue"
},
  "geometry": {"coordinates":[2.021227,48.776985],"type":"Point"}
}