{
  "type": "Feature",
  "properties": {
    "addr:full":"5 Av Jean D' Alembert 78851 Elancourt Ancourt Haute Normandie 76370",
    "addr:postcode":"78851;76370",
    "addr:street":"Av Jean D ' Alembert;Haute Normandie",
    "iso:country":"FR",
    "sg:address":"5 Av Jean D' Alembert 78851 Elancourt",
    "sg:city":"Ancourt",
    "sg:classifiers":[
        {
            "category":"Utilities",
            "subcategory":"Telephone",
            "type":"Services"
        }
    ],
    "sg:phone":"+33 1 34 81 60 00",
    "sg:postcode":"76370",
    "sg:province":"Haute Normandie",
    "sg:tags":[
        "telecommunication"
    ],
    "wof:name":"Thales Systemes Aeroportes",
    "wof:placetype":"venue"
},
  "geometry": {"coordinates":[1.976289,48.791924],"type":"Point"}
}