{
  "type": "Feature",
  "properties": {
    "iso:country":"FR",
    "sg:address":"RN 10",
    "sg:city":"Maine de Boixe",
    "sg:orig_category":"Unclassifiable Establishments",
    "sg:phone":"+33 5 45 20 34 11",
    "sg:postcode":"16230",
    "sg:province":"Poitou-Charentes",
    "wof:name":"Harmand Et Fils S.a.r.l.",
    "wof:placetype":"venue"
},
  "geometry": {"coordinates":[0.31836,45.833389],"type":"Point"}
}