{
  "type": "Feature",
  "properties": {
    "iso:country":"FR",
    "sg:address":"88210 Moussey",
    "sg:orig_category":"Unclassifiable Establishments",
    "sg:phone":"+33 3 29 42 52 52",
    "sg:province":"Lorraine",
    "wof:name":"Celair Technologies S.a.",
    "wof:placetype":"venue"
},
  "geometry": {"coordinates":[7.01792,48.426628],"type":"Point"}
}