{
  "type": "Feature",
  "properties": {
    "addr:full":"93, Rue de Borre, 59232 Vieux Berquin Nord Pas-de-Calais",
    "addr:housenumber":"93",
    "addr:postcode":"59232",
    "addr:street":"Rue De Borre;Berquin Nord",
    "iso:country":"FR",
    "sg:address":"93, Rue de Borre, 59232 Vieux Berquin",
    "sg:orig_category":"Non-Classified Establishments",
    "sg:phone":"+33 3 28 43 59 24",
    "sg:province":"Nord Pas-de-Calais",
    "wof:name":"Hestia S.a.",
    "wof:placetype":"venue"
},
  "geometry": {"coordinates":[2.59556,50.713039],"type":"Point"}
}