{
  "type": "Feature",
  "properties": {
    "addr:full":"B.P. 25, 87500 Saint Yrieix la Perche^^33, Rue du Commandant Dugros, 87500 Saint Yrieix la Perche Limousin 87500",
    "addr:postcode":"87500;87500;87500",
    "addr:street":"B.P. 25;Rue Du Commandant Dugros",
    "iso:country":"FR",
    "sg:address":"B.P. 25, 87500 Saint Yrieix la Perche^^33, Rue du Commandant Dugros, 87500 Saint Yrieix la Perche",
    "sg:orig_category":"Non-Classified Establishments",
    "sg:phone":"+33 5 55 08 32 00",
    "sg:postcode":"87500",
    "sg:province":"Limousin",
    "wof:name":"Entreprise Darlavoix S.a.",
    "wof:placetype":"venue"
},
  "geometry": {"coordinates":[1.20264,45.513241],"type":"Point"}
}