{
  "type": "Feature",
  "properties": {
    "addr:full":"15 Rue Pierre Pays Usine 15 69660 Collonges Au Mont D Or Rhone-Alpes 69660",
    "addr:housenumber":"15;15",
    "addr:postcode":"69660;69660",
    "addr:street":"Rue Pierre Pays Usine;Au Mont D;Rhone-Alpes",
    "iso:country":"FR",
    "sg:address":"15 Rue Pierre Pays Usine 15 69660 Collonges Au Mont D Or",
    "sg:classifiers":[
        {
            "category":"Manufacturing",
            "subcategory":"Chemicals & Compounds",
            "type":"Manufacturing & Wholesale Goods"
        }
    ],
    "sg:phone":"+33 4 72 42 14 00",
    "sg:postcode":"69660",
    "sg:province":"Rhone-Alpes",
    "sg:tags":[
        "pharmaceutical",
        "chemistry"
    ],
    "wof:name":"Rhodia Silices",
    "wof:placetype":"venue"
},
  "geometry": {"coordinates":[4.839795,45.823441],"type":"Point"}
}