{
  "type": "Feature",
  "properties": {
    "iso:country":"FR",
    "sg:address":"ZI du Bois Rigault Nord",
    "sg:city":"Vendin le Vieil",
    "sg:orig_category":"Non-Classified Establishments",
    "sg:phone":"+33 3 21 13 64 40",
    "sg:postcode":"62880",
    "sg:province":"Nord Pas-de-Calais",
    "wof:name":"Bio Inox S.a.",
    "wof:placetype":"venue"
},
  "geometry": {"coordinates":[2.862925,50.474388],"type":"Point"}
}