{
  "type": "Feature",
  "properties": {
    "addr:full":"Route De Tours 37210 Vernou Sur Brenne Chan\u00e7ay Centre 37210",
    "addr:housenumber":"chanc\u0327ay",
    "addr:postcode":"37210;37210",
    "addr:street":"Route De Tours",
    "iso:country":"FR",
    "sg:address":"Route De Tours 37210 Vernou Sur Brenne",
    "sg:city":"Chan\u00e7ay",
    "sg:classifiers":[
        {
            "category":"Government",
            "subcategory":"Department Of Motor Vehicles",
            "type":"Public Place"
        }
    ],
    "sg:phone":"+33 2 47 52 03 27",
    "sg:postcode":"37210",
    "sg:province":"Centre",
    "sg:tags":[
        "equipment",
        "industrial",
        "transport",
        "motor-cars"
    ],
    "wof:name":"Esquiss Auto Sarl",
    "wof:placetype":"venue"
},
  "geometry": {"coordinates":[0.798817,47.41206],"type":"Point"}
}