{
  "type": "Feature",
  "properties": {
    "addr:full":"La Lombardi\u00e8re 07100 Annonay Rhone-Alpes 07100",
    "addr:postcode":"07100;07100",
    "iso:country":"FR",
    "sg:address":"La Lombardi\u00e8re 07100 Annonay",
    "sg:classifiers":[
        {
            "category":"Park",
            "type":"Public Place"
        }
    ],
    "sg:phone":"+33 4 75 32 41 00",
    "sg:postcode":"07100",
    "sg:province":"Rhone-Alpes",
    "sg:tags":[
        "work",
        "construction",
        "sport"
    ],
    "wof:name":"Annonay Productions France Sarl",
    "wof:placetype":"venue"
},
  "geometry": {"coordinates":[4.692955,45.252338],"type":"Point"}
}