{
  "type": "Feature",
  "properties": {
    "iso:country":"FR",
    "sg:address":"229 Rue St Denis 75002 Paris",
    "sg:classifiers":[
        {
            "category":"Shopping",
            "subcategory":"Clothing, Apparel, & Fashions",
            "type":"Retail Goods"
        }
    ],
    "sg:phone":"+33 1 40 26 41 25",
    "sg:postcode":"75002",
    "sg:province":"Ile de France",
    "sg:tags":[
        "textile",
        "clothing",
        "clothes"
    ],
    "wof:name":"Dgl Sarl",
    "wof:placetype":"venue"
},
  "geometry": {"coordinates":[2.351285,48.867184],"type":"Point"}
}