{
  "type": "Feature",
  "properties": {
    "addr:full":"15, Rue de la Vall\u00e9e Saint Ulrich, 67140 Barr Barr Alsace 67140",
    "addr:housenumber":"15",
    "addr:postcode":"67140;67140",
    "addr:street":"Rue De La Valle\u0301E;Barr",
    "iso:country":"FR",
    "sg:address":"15, Rue de la Vall\u00e9e Saint Ulrich, 67140 Barr",
    "sg:city":"Barr",
    "sg:orig_category":"Unclassifiable Establishments",
    "sg:phone":"+33 3 88 08 90 42",
    "sg:postcode":"67140",
    "sg:province":"Alsace",
    "wof:name":"Vilbar Manufacture De Papier S.a.r.l.",
    "wof:placetype":"venue"
},
  "geometry": {"coordinates":[7.452449,48.406513],"type":"Point"}
}