{
  "type": "Feature",
  "properties": {
    "addr:full":"B.P. 22, 55430 Belleville sur Meuse^^8, Rue Alfred Sauvy, 55430 Belleville sur Meuse Lorraine",
    "addr:postcode":"55430;55430",
    "addr:street":"B.P. 22;Rue Alfred Sauvy;Meuse",
    "iso:country":"FR",
    "sg:address":"B.P. 22, 55430 Belleville sur Meuse^^8, Rue Alfred Sauvy, 55430 Belleville sur Meuse",
    "sg:orig_category":"Non-Classified Establishments",
    "sg:phone":"+33 3 29 86 85 60",
    "sg:province":"Lorraine",
    "wof:name":"S.e.a.v. S.a. - Soci\u00e9t\u00e9 D'exploitation Des Abattoirs De Verdun",
    "wof:placetype":"venue"
},
  "geometry": {"coordinates":[5.381125,49.174049],"type":"Point"}
}