{
  "type": "Feature",
  "properties": {
    "iso:country":"FR",
    "sg:address":"B.P. 46, 69881 Meyzieu C\u00e9dex^^19, Av. du Mar\u00e9chal de Lattre de Tassigny, 69330 Meyzieu",
    "sg:orig_category":"Non-Classified Establishments",
    "sg:phone":"+33 4 72 45 22 00",
    "sg:province":"Rhone-Alpes",
    "wof:name":"Sandvik Tamrock S.a.s.",
    "wof:placetype":"venue"
},
  "geometry": {"coordinates":[5.00581,45.766296],"type":"Point"}
}