{
  "type": "Feature",
  "properties": {
    "iso:country":"FR",
    "sg:address":"B.P. 622, 31002 Toulouse C\u00e9dex^^1, Esplanade Compans Caffarelli, 31000 Toulouse",
    "sg:orig_category":"Non-Classified Establishments",
    "sg:phone":"+33 5 62 15 44 00",
    "sg:postcode":"31000",
    "sg:province":"Midi Pyr\u00e9n\u00e9es",
    "wof:name":"Cr\u00e9dit Lyonnais S.a.",
    "wof:placetype":"venue"
},
  "geometry": {"coordinates":[1.44869,43.60574],"type":"Point"}
}