{
  "type": "Feature",
  "properties": {
    "addr:full":"B.P. 2, 42011 Saint Etienne C\u00e9dex 2^^8, Rue Bertrand Russel, 42000 Saint Etienne Rhone-Alpes 42000",
    "addr:housenumber":"2;2 ^ ^ 8",
    "addr:postcode":"42011;42000;42000",
    "addr:street":"B.P.;Ce\u0301Dex;Rue Bertrand Russel",
    "iso:country":"FR",
    "sg:address":"B.P. 2, 42011 Saint Etienne C\u00e9dex 2^^8, Rue Bertrand Russel, 42000 Saint Etienne",
    "sg:orig_category":"Non-Classified Establishments",
    "sg:phone":"+33 4 77 95 87 88",
    "sg:postcode":"42000",
    "sg:province":"Rhone-Alpes",
    "wof:name":"Thomas Guinamand S.a.",
    "wof:placetype":"venue"
},
  "geometry": {"coordinates":[1.420503,46.892673],"type":"Point"}
}