{
  "type": "Feature",
  "properties": {
    "addr:full":"B.P. 266 Saint Brandan Bretagne 22800",
    "addr:housenumber":"b.p. 266",
    "addr:postcode":"22800",
    "addr:street":"Saint Brandan Bretagne",
    "iso:country":"FR",
    "sg:address":"B.P. 266",
    "sg:city":"Saint Brandan",
    "sg:orig_category":"Non-Classified Establishments",
    "sg:phone":"+33 2 96 79 63 63",
    "sg:postcode":"22800",
    "sg:province":"Bretagne",
    "wof:name":"Socavol S.a.",
    "wof:placetype":"venue"
},
  "geometry": {"coordinates":[-2.8699,48.38998],"type":"Point"}
}