{
  "type": "Feature",
  "properties": {
    "addr:full":"12 Av De La Saudrune 31128 Portet Sur Garonne Pays de Loire",
    "addr:postcode":"31128",
    "addr:street":"12 Av De La Saudrune;Garonne",
    "iso:country":"FR",
    "sg:address":"12 Av De La Saudrune 31128 Portet Sur Garonne",
    "sg:classifiers":[
        {
            "category":"Food Court",
            "type":"Food & Drink"
        }
    ],
    "sg:phone":"+33 5 62 11 77 11",
    "sg:province":"Pays de Loire",
    "sg:tags":[
        "product",
        "related"
    ],
    "wof:name":"Midi Pyrenees Boissons",
    "wof:placetype":"venue"
},
  "geometry": {"coordinates":[1.381846,43.531452],"type":"Point"}
}