{
  "type": "Feature",
  "properties": {
    "addr:full":"9 rue Royale 75008 Paris Ile de France 75008",
    "addr:housenumber":"9",
    "addr:postcode":"75008;75008",
    "addr:street":"Rue Royale",
    "iso:country":"FR",
    "sg:address":"9 rue Royale 75008 Paris",
    "sg:classifiers":[
        {
            "category":"Shopping",
            "subcategory":"Jewelry",
            "type":"Retail Goods"
        }
    ],
    "sg:phone":"+33 1 40 17 01 00",
    "sg:postcode":"75008",
    "sg:province":"Ile de France",
    "sg:tags":[
        "jewellery",
        "gold"
    ],
    "wof:name":"Ercuis Sa",
    "wof:placetype":"venue"
},
  "geometry": {"coordinates":[2.322379,48.867596],"type":"Point"}
}