{
  "type": "Feature",
  "properties": {
    "addr:full":"7, Av. L\u00e9on Blum, 59370 Mons en Baroeul Nord Pas-de-Calais",
    "addr:postcode":"59370",
    "addr:street":"Av. Le\u0301On Blum",
    "iso:country":"FR",
    "sg:address":"7, Av. L\u00e9on Blum, 59370 Mons en Baroeul",
    "sg:orig_category":"Non-Classified Establishments",
    "sg:phone":"+33 3 20 61 75 75",
    "sg:province":"Nord Pas-de-Calais",
    "wof:name":"Vannieu Agencements S.a.r.l.",
    "wof:placetype":"venue"
},
  "geometry": {"coordinates":[3.10574,50.650059],"type":"Point"}
}