{
  "type": "Feature",
  "properties": {
    "addr:full":"247, Av. Nationale, 72230 Arnage Pays de Loire",
    "addr:postcode":"72230",
    "addr:street":"247 Av. Nationale",
    "iso:country":"FR",
    "sg:address":"247, Av. Nationale, 72230 Arnage",
    "sg:orig_category":"Unclassifiable Establishments",
    "sg:phone":"+33 2 43 21 12 36",
    "sg:province":"Pays de Loire",
    "wof:name":"S.t.e.r.n. S.a. -soci\u00e9t\u00e9 Technique D'etudes Et De R\u00e9alisations Nouvelles",
    "wof:placetype":"venue"
},
  "geometry": {"coordinates":[0.181722,47.92009],"type":"Point"}
}