{
  "type": "Feature",
  "properties": {
    "addr:full":"379, Rue de Bordeaux Ango\u00fbl\u00e8me, 16007 Angoul\u00eame Poitou-Charentes",
    "addr:housenumber":"379",
    "addr:postcode":"16007",
    "addr:street":"Rue De Bordeaux Angou\u0302Le\u0300Me",
    "iso:country":"FR",
    "sg:address":"379, Rue de Bordeaux Ango\u00fbl\u00e8me, 16007 Angoul\u00eame",
    "sg:orig_category":"Unclassifiable Establishments",
    "sg:phone":"+33 5 45 25 99 99",
    "sg:province":"Poitou-Charentes",
    "wof:name":"Citram Poitou Charentes S.a.",
    "wof:placetype":"venue"
},
  "geometry": {"coordinates":[0.156985,45.649239],"type":"Point"}
}