{
  "type": "Feature",
  "properties": {
    "iso:country":"FR",
    "sg:address":"38, Bd Joseph Garnier, 06000 Nice",
    "sg:orig_category":"Non-Classified Establishments",
    "sg:phone":"+33 4 92 09 00 34",
    "wof:name":"Echelle 06",
    "wof:placetype":"venue"
},
  "geometry": {"coordinates":[7.257392,43.710194],"type":"Point"}
}