{
  "type": "Feature",
  "properties": {
    "addr:full":"16, Chemin de Saquier, 06200 Nice Provence-Alpes-C\u00f4te d'Azur",
    "addr:housenumber":"16",
    "addr:postcode":"06200",
    "addr:street":"Chemin De Saquier",
    "iso:country":"FR",
    "sg:address":"16, Chemin de Saquier, 06200 Nice",
    "sg:orig_category":"Unclassifiable Establishments",
    "sg:phone":"+33 4 93 18 12 90",
    "sg:province":"Provence-Alpes-C\u00f4te d'Azur",
    "wof:name":"L'etanch\u00e9it\u00e9 Rationnelle S.a.",
    "wof:placetype":"venue"
},
  "geometry": {"coordinates":[7.194933,43.720028],"type":"Point"}
}