{
  "type": "Feature",
  "properties": {
    "addr:full":"27, Rue de la Chapelle, 92500 Rueil Malmaison Ile de France",
    "addr:housenumber":"27",
    "addr:postcode":"92500",
    "addr:street":"Rue De La Chapelle",
    "iso:country":"FR",
    "sg:address":"27, Rue de la Chapelle, 92500 Rueil Malmaison",
    "sg:orig_category":"Non-Classified Establishments",
    "sg:phone":"+33 1 41 29 00 64",
    "sg:province":"Ile de France",
    "wof:name":"M.p.a.b. S.a.",
    "wof:placetype":"venue"
},
  "geometry": {"coordinates":[2.199828,48.870712],"type":"Point"}
}