{
  "type": "Feature",
  "properties": {
    "addr:full":"85-87 Av Henri Barbusse 92140 Clamart Ile de France 92140",
    "addr:housenumber":"85-87",
    "addr:postcode":"92140;ile;92140",
    "addr:street":"Av Henri Barbusse;France",
    "iso:country":"FR",
    "sg:address":"85-87 Av Henri Barbusse 92140 Clamart",
    "sg:classifiers":[
        {
            "category":"Shopping",
            "subcategory":"Clothing, Apparel, & Fashions",
            "type":"Retail Goods"
        }
    ],
    "sg:phone":"+33 1 41 08 83 83",
    "sg:postcode":"92140",
    "sg:province":"Ile de France",
    "sg:tags":[
        "textile",
        "clothing",
        "clothes"
    ],
    "wof:name":"Stoll France Sarl",
    "wof:placetype":"venue"
},
  "geometry": {"coordinates":[2.258398,48.811459],"type":"Point"}
}