{
  "type": "Feature",
  "properties": {
    "iso:country":"FR",
    "sg:address":"Z I 62970 COURCELLES LES LENS",
    "sg:classifiers":[
        {
            "category":"Manufacturing",
            "subcategory":"Paper Products",
            "type":"Manufacturing & Wholesale Goods"
        }
    ],
    "sg:phone":"+33 3 21 08 18 80",
    "sg:province":"Nord Pas-de-Calais",
    "sg:tags":[
        "roofing"
    ],
    "wof:name":"Mcp Defrancq Sa",
    "wof:placetype":"venue"
},
  "geometry": {"coordinates":[3.01822,50.418064],"type":"Point"}
}