{
  "type": "Feature",
  "properties": {
    "iso:country":"FR",
    "sg:address":"39, Rue du 8 Mai 1945, 69320 Feyzin",
    "sg:orig_category":"Non-Classified Establishments",
    "sg:phone":"+33 4 72 89 19 19",
    "sg:province":"Rhone-Alpes",
    "wof:name":"S.m.s. S.a. - Sud Machines Service",
    "wof:placetype":"venue"
},
  "geometry": {"coordinates":[4.847653,45.660725],"type":"Point"}
}