{
  "type": "Feature",
  "properties": {
    "addr:full":"B.P. 3, 49450 Roussay C\u00e9dex^^Rue de la Fontaine, 49450 Roussay Pays de Loire",
    "addr:housenumber":"3",
    "addr:postcode":"49450;49450",
    "addr:street":"B.P.;La Fontaine",
    "iso:country":"FR",
    "sg:address":"B.P. 3, 49450 Roussay C\u00e9dex^^Rue de la Fontaine, 49450 Roussay",
    "sg:orig_category":"Non-Classified Establishments",
    "sg:phone":"+33 2 41 70 38 32",
    "sg:province":"Pays de Loire",
    "wof:name":"Sportex S.a.r.l.",
    "wof:placetype":"venue"
},
  "geometry": {"coordinates":[-1.064815,47.091267],"type":"Point"}
}