{
  "type": "Feature",
  "properties": {
    "iso:country":"FR",
    "sg:address":"184 R Jean Lebas BP 5",
    "sg:city":"Wattrelos Cedex",
    "sg:classifiers":[
        {
            "category":"Banks & Credit Unions",
            "subcategory":"Financial Services",
            "type":"Services"
        }
    ],
    "sg:phone":"+33 3 20 89 38 82",
    "sg:postcode":"59392",
    "sg:province":"Nord Pas-de-Calais",
    "sg:tags":[
        "banking",
        "finance",
        "insurance"
    ],
    "wof:name":"Blomme Marcel",
    "wof:placetype":"venue"
},
  "geometry": {"coordinates":[3.21509,50.701679],"type":"Point"}
}