{
  "type": "Feature",
  "properties": {
    "iso:country":"FR",
    "sg:address":"Le Sablon 38480 Pressins",
    "sg:classifiers":[
        {
            "category":"Manufacturing",
            "subcategory":"Metals",
            "type":"Manufacturing & Wholesale Goods"
        }
    ],
    "sg:phone":"+33 4 76 31 30 20",
    "sg:postcode":"38480",
    "sg:province":"Rhone-Alpes",
    "sg:tags":[
        "metallurgy",
        "metalworking"
    ],
    "wof:name":"Jps Industries",
    "wof:placetype":"venue"
},
  "geometry": {"coordinates":[5.62703,45.531937],"type":"Point"}
}