{
  "type": "Feature",
  "properties": {
    "addr:full":"53, Rue Jean Jaur\u00e8s, 42190 Charlieu Rhone-Alpes",
    "addr:housenumber":"53",
    "addr:postcode":"42190",
    "addr:street":"Rue Jean Jaure\u0300S",
    "iso:country":"FR",
    "sg:address":"53, Rue Jean Jaur\u00e8s, 42190 Charlieu",
    "sg:orig_category":"Non-Classified Establishments",
    "sg:phone":"+33 4 77 60 04 24",
    "sg:province":"Rhone-Alpes",
    "wof:name":"Moncorg\u00e9 Parcs Et Jardins S.a.r.l.",
    "wof:placetype":"venue"
},
  "geometry": {"coordinates":[4.17805,46.163422],"type":"Point"}
}