{
  "type": "Feature",
  "properties": {
    "addr:full":"Avenue Castres 81210 Roquecourbe Midi Pyr\u00e9n\u00e9es 81210",
    "addr:postcode":"81210;81210",
    "addr:street":"Avenue",
    "iso:country":"FR",
    "sg:address":"Avenue Castres 81210 Roquecourbe",
    "sg:classifiers":[
        {
            "category":"Shopping",
            "subcategory":"Clothing, Apparel, & Fashions",
            "type":"Retail Goods"
        }
    ],
    "sg:phone":"+33 5 63 75 80 10",
    "sg:postcode":"81210",
    "sg:province":"Midi Pyr\u00e9n\u00e9es",
    "sg:tags":[
        "textile",
        "clothing",
        "clothes"
    ],
    "wof:name":"Soci\u00c9t\u00c9 Molinier Laur Sa",
    "wof:placetype":"venue"
},
  "geometry": {"coordinates":[2.283661,43.663219],"type":"Point"}
}