{
  "type": "Feature",
  "properties": {
    "addr:full":"19, Rue de R\u00e9publique, 76210 Bolbec Haute Normandie",
    "addr:housenumber":"19",
    "addr:postcode":"76210",
    "addr:street":"Rue De Re\u0301Publique;Haute Normandie",
    "iso:country":"FR",
    "sg:address":"19, Rue de R\u00e9publique, 76210 Bolbec",
    "sg:orig_category":"Unclassifiable Establishments",
    "sg:phone":"+33 2 35 31 00 98",
    "sg:province":"Haute Normandie",
    "wof:name":"Ferric S.a.",
    "wof:placetype":"venue"
},
  "geometry": {"coordinates":[0.471666,49.572018],"type":"Point"}
}