{
  "type": "Feature",
  "properties": {
    "addr:full":"27, Rue de la Sapini\u00e8re - ., 54520 Laxou Lorraine",
    "addr:housenumber":"27",
    "addr:postcode":"54520",
    "addr:street":"Rue De La Sapinie\u0300Re",
    "iso:country":"FR",
    "sg:address":"27, Rue de la Sapini\u00e8re - ., 54520 Laxou",
    "sg:orig_category":"Unclassifiable Establishments",
    "sg:phone":"+33 3 83 96 46 21",
    "sg:province":"Lorraine",
    "wof:name":"Axima Nord S.a.",
    "wof:placetype":"venue"
},
  "geometry": {"coordinates":[6.127807,48.694],"type":"Point"}
}