{
  "type": "Feature",
  "properties": {
    "iso:country":"FR",
    "sg:address":"22 Rue Chateaufavier 23200 Aubusson",
    "sg:classifiers":[
        {
            "category":"Manufacturing",
            "subcategory":"Textiles",
            "type":"Manufacturing & Wholesale Goods"
        }
    ],
    "sg:phone":"+33 5 55 83 88 43",
    "sg:postcode":"23200",
    "sg:province":"Limousin",
    "sg:tags":[
        "linen",
        "clothing",
        "fabric"
    ],
    "wof:name":"Tapisseries Legoueix",
    "wof:placetype":"venue"
},
  "geometry": {"coordinates":[2.171122,45.956612],"type":"Point"}
}