{
  "type": "Feature",
  "properties": {
    "addr:full":"1, Rue de Strasbourg, 57400 Sarrebourg Lorraine",
    "addr:housenumber":"1",
    "addr:postcode":"57400",
    "addr:street":"Rue De Strasbourg",
    "iso:country":"FR",
    "sg:address":"1, Rue de Strasbourg, 57400 Sarrebourg",
    "sg:orig_category":"Unclassifiable Establishments",
    "sg:phone":"+33 3 87 03 11 13",
    "sg:province":"Lorraine",
    "wof:name":"Kirchner Adrien Bureautique - Proth Bureau Groupe S.a.",
    "wof:placetype":"venue"
},
  "geometry": {"coordinates":[7.074258,48.741074],"type":"Point"}
}