{
  "type": "Feature",
  "properties": {
    "iso:country":"FR",
    "sg:address":"10 Bis Av De La Grande Arm\u00e9e 75017 Paris",
    "sg:classifiers":[
        {
            "category":"Manufacturing",
            "subcategory":"Printing",
            "type":"Manufacturing & Wholesale Goods"
        }
    ],
    "sg:phone":"+33 1 47 66 19 19",
    "sg:province":"Ile de France",
    "sg:tags":[
        "publishing"
    ],
    "wof:name":"Paradise Moto",
    "wof:placetype":"venue"
},
  "geometry": {"coordinates":[2.292461,48.875038],"type":"Point"}
}