{
  "type": "Feature",
  "properties": {
    "iso:country":"FR",
    "sg:address":"Zac De L'Agneau 19240 St Viance",
    "sg:classifiers":[
        {
            "category":"Health Services",
            "subcategory":"Medical Lab",
            "type":"Services"
        }
    ],
    "sg:phone":"+33 5 55 17 67 87",
    "sg:postcode":"19240",
    "sg:province":"Limousin",
    "sg:tags":[
        "chemical",
        "pharmaceutical",
        "pharmacy"
    ],
    "wof:name":"Alliance Sante",
    "wof:placetype":"venue"
},
  "geometry": {"coordinates":[-2.914296,40.902073],"type":"Point"}
}