{
  "type": "Feature",
  "properties": {
    "iso:country":"FR",
    "sg:address":"Rue Benoit Frachon Zaet Les Haies 60740 Saint Maximin",
    "sg:classifiers":[
        {
            "category":"Home & Garden",
            "subcategory":"Furniture",
            "type":"Retail Goods"
        }
    ],
    "sg:phone":"+33 3 44 64 76 00",
    "sg:postcode":"60740",
    "sg:province":"Picardie",
    "sg:tags":[
        "household",
        "wood"
    ],
    "wof:name":"Mouss'oise Pro Literie",
    "wof:placetype":"venue"
},
  "geometry": {"coordinates":[2.454171,49.220432],"type":"Point"}
}