{
  "type": "Feature",
  "properties": {
    "iso:country":"FR",
    "sg:address":"1 avenue du G\u00e9n\u00e9ral de Gaulle 92800 Puteaux",
    "sg:classifiers":[
        {
            "category":"Autos & Motor Vehicles",
            "subcategory":"Automobile Sales",
            "type":"Retail Goods"
        }
    ],
    "sg:phone":"+33 1 46 98 80 00",
    "sg:province":"Ile de France",
    "sg:tags":[
        "passenger",
        "car"
    ],
    "wof:name":"Ppg Refinish France Sa",
    "wof:placetype":"venue"
},
  "geometry": {"coordinates":[2.23313,48.887321],"type":"Point"}
}