{
  "type": "Feature",
  "properties": {
    "addr:full":"7, Rue du Grand Veymont, 38320 Eybens Rhone-Alpes 38320",
    "addr:housenumber":"7",
    "addr:postcode":"38320;38320",
    "addr:street":"Rue Du Grand Veymont",
    "iso:country":"FR",
    "sg:address":"7, Rue du Grand Veymont, 38320 Eybens",
    "sg:orig_category":"Non-Classified Establishments",
    "sg:phone":"+33 4 76 62 22 52",
    "sg:postcode":"38320",
    "sg:province":"Rhone-Alpes",
    "wof:name":"Bastrenta Assistance Services Etudes+ S.a.r.l.",
    "wof:placetype":"venue"
},
  "geometry": {"coordinates":[5.746956,45.162067],"type":"Point"}
}