{
  "type": "Feature",
  "properties": {
    "iso:country":"FR",
    "sg:address":"201, Clos des Baz, 74700 Sallanches",
    "sg:orig_category":"Unclassifiable Establishments",
    "sg:phone":"+33 4 50 58 26 93",
    "sg:postcode":"74700",
    "sg:province":"Rhone-Alpes",
    "wof:name":"Etablissement Blondet Alcide S.a.",
    "wof:placetype":"venue"
},
  "geometry": {"coordinates":[6.636961,45.939308],"type":"Point"}
}