{
  "type": "Feature",
  "properties": {
    "addr:full":"1 Avenue Ratisbonne 91000 Evry Ile de France 91000",
    "addr:housenumber":"1",
    "addr:postcode":"91000;91000",
    "addr:street":"Avenue",
    "iso:country":"FR",
    "sg:address":"1 Avenue Ratisbonne 91000 Evry",
    "sg:classifiers":[
        {
            "category":"Professional",
            "subcategory":"Business Services",
            "type":"Services"
        }
    ],
    "sg:phone":"+33 1 69 47 32 32",
    "sg:postcode":"91000",
    "sg:province":"Ile de France",
    "sg:tags":[
        "training",
        "advice"
    ],
    "wof:name":"Association Notre Dame De Sion College Et Lycee",
    "wof:placetype":"venue"
},
  "geometry": {"coordinates":[2.435055,48.643963],"type":"Point"}
}