{
  "type": "Feature",
  "properties": {
    "addr:full":"620, Rue des Marways - ZI des Lanches, 74300 Thyez Rhone-Alpes 74300",
    "addr:housenumber":"620",
    "addr:postcode":"74300;74300",
    "addr:street":"Rue Des Marways Zi Des Lanches;Rhone-Alpes",
    "iso:country":"FR",
    "sg:address":"620, Rue des Marways - ZI des Lanches, 74300 Thyez",
    "sg:orig_category":"Unclassifiable Establishments",
    "sg:phone":"+33 4 50 98 10 90",
    "sg:postcode":"74300",
    "sg:province":"Rhone-Alpes",
    "wof:name":"Chardon Marius Et Fils S.a.",
    "wof:placetype":"venue"
},
  "geometry": {"coordinates":[6.633185,45.987919],"type":"Point"}
}