{
  "type": "Feature",
  "properties": {
    "iso:country":"FR",
    "sg:address":"14 Rue De Normandie 93120 La Courneuve",
    "sg:classifiers":[
        {
            "category":"Professional",
            "subcategory":"Advertising",
            "type":"Services"
        }
    ],
    "sg:phone":"+33 1 48 38 23 23",
    "sg:postcode":"93120",
    "sg:province":"Ile de France",
    "sg:tags":[
        "communication",
        "medium"
    ],
    "wof:name":"L'atelier Des Deux Pas",
    "wof:placetype":"venue"
},
  "geometry": {"coordinates":[2.406642,48.919632],"type":"Point"}
}