{
  "type": "Feature",
  "properties": {
    "iso:country":"FR",
    "sg:address":"110, Rue Jean Jaur\u00e8s, 62240 Desvres",
    "sg:orig_category":"Unclassifiable Establishments",
    "sg:phone":"+33 3 21 83 42 30",
    "sg:province":"Nord Pas-de-Calais",
    "wof:name":"Servitix - Consolists S.a.r.l.",
    "wof:placetype":"venue"
},
  "geometry": {"coordinates":[1.832428,50.673508],"type":"Point"}
}