{
  "type": "Feature",
  "properties": {
    "iso:country":"FR",
    "sg:address":"58, Rte de Vologne, 88250 La Bresse",
    "sg:orig_category":"Non-Classified Establishments",
    "sg:phone":"+33 3 29 25 47 35",
    "sg:province":"Lorraine",
    "wof:name":"Roci S.a.",
    "wof:placetype":"venue"
},
  "geometry": {"coordinates":[6.940653,48.011726],"type":"Point"}
}