{
  "type": "Feature",
  "properties": {
    "addr:full":"Le Glatey 73410 LA BIOLLE Rhone-Alpes 73410",
    "addr:housenumber":"73410",
    "addr:postcode":"73410",
    "addr:street":"La Biolle Rhone-Alpes",
    "iso:country":"FR",
    "sg:address":"Le Glatey 73410 LA BIOLLE",
    "sg:classifiers":[
        {
            "category":"Wholesale",
            "subcategory":"Chemicals & Plastics",
            "type":"Manufacturing & Wholesale Goods"
        }
    ],
    "sg:phone":"+33 4 79 54 75 58",
    "sg:postcode":"73410",
    "sg:province":"Rhone-Alpes",
    "sg:tags":[
        "ground"
    ],
    "wof:name":"Aplast Sa",
    "wof:placetype":"venue"
},
  "geometry": {"coordinates":[5.960386,45.739845],"type":"Point"}
}