{
  "type": "Feature",
  "properties": {
    "iso:country":"FR",
    "sg:address":"11, Av. de la Plaine, 31130 Balma",
    "sg:orig_category":"Unclassifiable Establishments",
    "sg:phone":"+33 5 62 57 67 77",
    "sg:province":"Midi Pyr\u00e9n\u00e9es",
    "wof:name":"Les Paveurs R\u00e9unis S.a.",
    "wof:placetype":"venue"
},
  "geometry": {"coordinates":[1.49576,43.60165],"type":"Point"}
}