{
  "type": "Feature",
  "properties": {
    "addr:full":"B.P. 6 Riorges Rhone-Alpes 42153",
    "addr:postcode":"42153",
    "addr:street":"B.P. 6 Riorges Rhone-Alpes",
    "iso:country":"FR",
    "sg:address":"B.P. 6",
    "sg:city":"Riorges",
    "sg:orig_category":"Non-Classified Establishments",
    "sg:phone":"+33 4 77 44 09 70",
    "sg:postcode":"42153",
    "sg:province":"Rhone-Alpes",
    "wof:name":"Bel Maille S.a.",
    "wof:placetype":"venue"
},
  "geometry": {"coordinates":[4.04235,46.039371],"type":"Point"}
}