{
  "type": "Feature",
  "properties": {
    "addr:full":"rue Suzanne Valadon 01000 Bourg en Bresse Rhone-Alpes 01000",
    "addr:postcode":"01000;01000",
    "addr:street":"Rue Suzanne Valadon;Rhone-Alpes",
    "iso:country":"FR",
    "sg:address":"rue Suzanne Valadon 01000 Bourg en Bresse",
    "sg:orig_category":"Material Flow Equipment, Inplant",
    "sg:phone":"+33 4 74 22 13 93",
    "sg:postcode":"01000",
    "sg:province":"Rhone-Alpes",
    "wof:name":"Egml Chatelet S.a.",
    "wof:placetype":"venue"
},
  "geometry": {"coordinates":[5.256494,46.196888],"type":"Point"}
}