{
  "type": "Feature",
  "properties": {
    "iso:country":"FR",
    "sg:address":"7 Cs Montaigne 24000 P\u00e9rigueux",
    "sg:city":"P\u00e9rigueux",
    "sg:classifiers":[
        {
            "category":"Shopping",
            "subcategory":"Clothing, Apparel, & Fashions",
            "type":"Retail Goods"
        }
    ],
    "sg:phone":"+33 5 53 35 15 00",
    "sg:postcode":"24000",
    "sg:province":"Aquitaine",
    "sg:tags":[
        "textile",
        "clothing",
        "clothes"
    ],
    "wof:name":"Ste Theo Sarl",
    "wof:placetype":"venue"
},
  "geometry": {"coordinates":[0.721447,45.185886],"type":"Point"}
}