{
  "type": "Feature",
  "properties": {
    "addr:full":"7 All De Villepreux Station Du Carr\u00e9 De R\u00e9union 78210 St Cyr L'Ecole Ile de France 78210",
    "addr:housenumber":"7",
    "addr:postcode":"78210;ile;78210",
    "addr:street":"All De Villepreux Station Du Carre\u0301 De Re\u0301Union;France",
    "iso:country":"FR",
    "sg:address":"7 All De Villepreux Station Du Carr\u00e9 De R\u00e9union 78210 St Cyr L'Ecole",
    "sg:classifiers":[
        {
            "category":"Manufacturing",
            "subcategory":"Tools & Machinery",
            "type":"Manufacturing & Wholesale Goods"
        }
    ],
    "sg:phone":"+33 1 30 45 86 21",
    "sg:postcode":"78210",
    "sg:province":"Ile de France",
    "sg:tags":[
        "environment",
        "equipment",
        "-"
    ],
    "wof:name":"Societe Des Eaux De Versailles Et De St Cloud",
    "wof:placetype":"venue"
},
  "geometry": {"coordinates":[55.532059,-21.114531],"type":"Point"}
}