{
  "type": "Feature",
  "properties": {
    "addr:full":"rue de Ch\u00e2tillon 71300 Montceau les Mines Saint-Berain-sous-Sanvignes Bourgogne 71300",
    "addr:postcode":"71300;71300",
    "addr:street":"Rue De Cha\u0302Tillon;Bourgogne",
    "iso:country":"FR",
    "sg:address":"rue de Ch\u00e2tillon 71300 Montceau les Mines",
    "sg:city":"Saint-Berain-sous-Sanvignes",
    "sg:classifiers":[
        {
            "category":"Manufacturing",
            "subcategory":"Wood Products",
            "type":"Manufacturing & Wholesale Goods"
        }
    ],
    "sg:phone":"+33 3 85 57 60 11",
    "sg:postcode":"71300",
    "sg:province":"Bourgogne",
    "sg:tags":[
        "lumber"
    ],
    "wof:name":"Jacques Matherat Sa",
    "wof:placetype":"venue"
},
  "geometry": {"coordinates":[4.356045,46.688087],"type":"Point"}
}