{
  "type": "Feature",
  "properties": {
    "addr:full":"6 Rue Francis Vovelle 28004 Chartres Cedex Nord Pas-de-Calais",
    "addr:housenumber":"6",
    "addr:postcode":"28004;cedex nord",
    "addr:street":"Rue Francis Vovelle",
    "iso:country":"FR",
    "sg:address":"6 Rue Francis Vovelle 28004 Chartres Cedex",
    "sg:classifiers":[
        {
            "category":"Professional",
            "subcategory":"Printing & Photocopies",
            "type":"Services"
        }
    ],
    "sg:phone":"+33 2 37 88 11 20",
    "sg:province":"Nord Pas-de-Calais",
    "sg:tags":[
        "publishing"
    ],
    "wof:name":"Societe D'edition D'horizons Du Centre Ile De France (sa Horizons)",
    "wof:placetype":"venue"
},
  "geometry": {"coordinates":[1.515504,48.44141],"type":"Point"}
}