{
  "type": "Feature",
  "properties": {
    "addr:full":"Zi Du Gros H\u00e2tre BP 20143 57504 St Avold Corse 20143",
    "addr:housenumber":"57504",
    "addr:postcode":"20143",
    "addr:street":"Zi Du Gros Ha\u0302Tre Bp 20143",
    "iso:country":"FR",
    "sg:address":"Zi Du Gros H\u00e2tre BP 20143 57504 St Avold",
    "sg:classifiers":[
        {
            "category":"Manufacturing",
            "subcategory":"Motor Vehicles & Parts",
            "type":"Manufacturing & Wholesale Goods"
        }
    ],
    "sg:phone":"+33 3 87 91 17 71",
    "sg:postcode":"20143",
    "sg:province":"Corse",
    "sg:tags":[
        "engine",
        "machine",
        "engineering",
        "-",
        "mechanical"
    ],
    "wof:name":"Eles France",
    "wof:placetype":"venue"
},
  "geometry": {"coordinates":[6.724514,49.117352],"type":"Point"}
}