{
  "type": "Feature",
  "properties": {
    "addr:full":"B.P. 89, 54704 Pont \u00e0 Mousson C\u00e9dex^^89, Chemin de Montrichard, 54700 Pont \u00e0 Mousson Lorraine",
    "addr:postcode":"54704;54700",
    "addr:street":"B.P. 89;Chemin De Montrichard",
    "iso:country":"FR",
    "sg:address":"B.P. 89, 54704 Pont \u00e0 Mousson C\u00e9dex^^89, Chemin de Montrichard, 54700 Pont \u00e0 Mousson",
    "sg:orig_category":"Non-Classified Establishments",
    "sg:phone":"+33 3 83 81 01 56",
    "sg:province":"Lorraine",
    "wof:name":"S.u.t.e. S.a. - Soci\u00e9t\u00e9 D'usinage De Tubes Pour L'electricit\u00e9",
    "wof:placetype":"venue"
},
  "geometry": {"coordinates":[6.054945,48.902954],"type":"Point"}
}