{
  "type": "Feature",
  "properties": {
    "addr:full":"Avenue 1\u00e8re 9e Rue 28 Cedex 06511 Carros Corse",
    "addr:housenumber":"9e;28",
    "addr:postcode":"cedex 06511",
    "addr:street":"Avenue 1E\u0300Re;Rue",
    "iso:country":"FR",
    "sg:address":"Avenue 1\u00e8re 9e Rue",
    "sg:city":"28 Cedex 06511 Carros",
    "sg:classifiers":[
        {
            "category":"Manufacturing",
            "subcategory":"Chemicals & Compounds",
            "type":"Manufacturing & Wholesale Goods"
        }
    ],
    "sg:phone":"+33 4 93 29 11 28",
    "sg:province":"Corse",
    "sg:tags":[
        "pharmaceutical",
        "chemistry",
        "-",
        "by-product"
    ],
    "wof:name":"Arkopharma (sa)",
    "wof:placetype":"venue"
},
  "geometry": {"coordinates":[7.194835,43.803421],"type":"Point"}
}