{
  "type": "Feature",
  "properties": {
    "addr:full":"91951 Courtaboeuf C\u00e9dex^^19, Av. du Qu\u00e9bec, 91140 Villebon sur Yvette Ile de France",
    "addr:postcode":"91951;91140",
    "addr:street":"Av. Du Que\u0301Bec",
    "iso:country":"FR",
    "sg:address":"91951 Courtaboeuf C\u00e9dex^^19, Av. du Qu\u00e9bec, 91140 Villebon sur Yvette",
    "sg:orig_category":"Non-Classified Establishments",
    "sg:phone":"+33 1 69 18 85 85",
    "sg:province":"Ile de France",
    "wof:name":"Fauba France S.a.",
    "wof:placetype":"venue"
},
  "geometry": {"coordinates":[2.227225,48.700069],"type":"Point"}
}