{
  "type": "Feature",
  "properties": {
    "iso:country":"FR",
    "sg:address":"9, Rue de la Paix, 75002 Paris",
    "sg:orig_category":"Non-Classified Establishments",
    "sg:phone":"+33 1 44 55 39 96",
    "sg:postcode":"75002",
    "sg:province":"Ile de France",
    "wof:name":"Compagnie A\u00e9rienne Nationale Du Vietnam",
    "wof:placetype":"venue"
},
  "geometry": {"coordinates":[2.330802,48.869091],"type":"Point"}
}