{
  "type": "Feature",
  "properties": {
    "addr:full":"Bd des Tourelles - ZI Le Lude Pays de Loire 72800",
    "addr:postcode":"72800",
    "addr:street":"Bd Des Tourelles Zi",
    "iso:country":"FR",
    "sg:address":"Bd des Tourelles - ZI",
    "sg:city":"Le Lude",
    "sg:orig_category":"Unclassifiable Establishments",
    "sg:phone":"+33 2 43 94 54 30",
    "sg:postcode":"72800",
    "sg:province":"Pays de Loire",
    "wof:name":"Cureau Daniel",
    "wof:placetype":"venue"
},
  "geometry": {"coordinates":[0.154635,47.647072],"type":"Point"}
}