{
  "type": "Feature",
  "properties": {
    "addr:full":"B.P. 1080, 76173 Rouen C\u00e9dex^^34, Bd du Midi, 76100 Rouen Haute Normandie",
    "addr:housenumber":"1080",
    "addr:postcode":"76173;76100",
    "addr:street":"B.P.;Bd Du Midi;Haute Normandie",
    "iso:country":"FR",
    "sg:address":"B.P. 1080, 76173 Rouen C\u00e9dex^^34, Bd du Midi, 76100 Rouen",
    "sg:orig_category":"Non-Classified Establishments",
    "sg:phone":"+33 2 35 58 17 17",
    "sg:province":"Haute Normandie",
    "wof:name":"Westerlund France S.a.",
    "wof:placetype":"venue"
},
  "geometry": {"coordinates":[1.0879,49.433601],"type":"Point"}
}