{
  "type": "Feature",
  "properties": {
    "iso:country":"FR",
    "sg:address":"38, Rue Jules Verne, 44700 Orvault",
    "sg:orig_category":"Unclassifiable Establishments",
    "sg:phone":"+33 2 40 63 63 93",
    "sg:province":"Pays de Loire",
    "wof:name":"Image S.a.r.l.",
    "wof:placetype":"venue"
},
  "geometry": {"coordinates":[-1.618845,47.252186],"type":"Point"}
}