{
  "type": "Feature",
  "properties": {
    "addr:full":"route du Mole 2 59140 Dunkerque Nord Pas-de-Calais 59140",
    "addr:housenumber":"2",
    "addr:postcode":"59140;59140",
    "addr:street":"Route Du Mole",
    "iso:country":"FR",
    "sg:address":"route du Mole 2 59140 Dunkerque",
    "sg:classifiers":[
        {
            "category":"Wholesale",
            "subcategory":"Construction Materials",
            "type":"Manufacturing & Wholesale Goods"
        }
    ],
    "sg:phone":"+33 3 28 59 90 00",
    "sg:postcode":"59140",
    "sg:province":"Nord Pas-de-Calais",
    "sg:tags":[
        "technology",
        "industry",
        "handling",
        "heavy-duty"
    ],
    "wof:name":"Barra Soc Nouvelle De Manutention Sarl",
    "wof:placetype":"venue"
},
  "geometry": {"coordinates":[2.365136,51.041443],"type":"Point"}
}