{
  "type": "Feature",
  "properties": {
    "iso:country":"FR",
    "sg:address":"69 Boulevard Blanqui 06340 La Trinit\u00e9",
    "sg:classifiers":[
        {
            "category":"Manufacturing",
            "subcategory":"Wood Products",
            "type":"Manufacturing & Wholesale Goods"
        }
    ],
    "sg:phone":"+33 4 93 54 55 22",
    "sg:province":"Midi Pyr\u00e9n\u00e9es",
    "sg:tags":[
        "furniture"
    ],
    "wof:name":"Delf Sa",
    "wof:placetype":"venue"
},
  "geometry": {"coordinates":[7.32292,43.749081],"type":"Point"}
}