{
  "type": "Feature",
  "properties": {
    "iso:country":"FR",
    "sg:address":"81-83 Av De Rouen 27200 Vernon",
    "sg:classifiers":[
        {
            "category":"Manufacturing",
            "subcategory":"Tools & Machinery",
            "type":"Manufacturing & Wholesale Goods"
        }
    ],
    "sg:phone":"+33 2 32 51 63 11",
    "sg:postcode":"27200",
    "sg:province":"Haute Normandie",
    "sg:tags":[
        "metallurgy",
        "metalworking"
    ],
    "wof:name":"Societe De Negoce De Normandie (sonen) Point P Batiself",
    "wof:placetype":"venue"
},
  "geometry": {"coordinates":[1.46969,49.101025],"type":"Point"}
}