{
  "type": "Feature",
  "properties": {
    "addr:full":"76400 Tourville Les Ifs Haute Normandie 76400",
    "addr:postcode":"76400;76400",
    "addr:street":"Haute Normandie",
    "iso:country":"FR",
    "sg:address":"76400 Tourville Les Ifs",
    "sg:classifiers":[
        {
            "category":"Food Court",
            "type":"Food & Drink"
        }
    ],
    "sg:phone":"+33 2 35 10 30 60",
    "sg:postcode":"76400",
    "sg:province":"Haute Normandie",
    "sg:tags":[
        "product",
        "related"
    ],
    "wof:name":"Bacardi Martini Production",
    "wof:placetype":"venue"
},
  "geometry": {"coordinates":[0.40003,49.713741],"type":"Point"}
}