{
  "type": "Feature",
  "properties": {
    "iso:country":"FR",
    "sg:address":"20, Bd Louis Sicre, 82100 Castelsarrasin",
    "sg:orig_category":"Unclassifiable Establishments",
    "sg:phone":"+33 5 63 29 40 05",
    "sg:province":"Midi Pyr\u00e9n\u00e9es",
    "wof:name":"Edf Et Gaz De France",
    "wof:placetype":"venue"
},
  "geometry": {"coordinates":[1.103236,44.040928],"type":"Point"}
}