{
  "type": "Feature",
  "properties": {
    "iso:country":"FR",
    "sg:address":"12, Av. du Docteur Jacques Arnaud, 74300 Cluses",
    "sg:orig_category":"Non-Classified Establishments",
    "sg:phone":"+33 4 50 98 27 36",
    "sg:postcode":"74300",
    "sg:province":"Rhone-Alpes",
    "wof:name":"Plancher S.a.",
    "wof:placetype":"venue"
},
  "geometry": {"coordinates":[6.574081,46.061455],"type":"Point"}
}