{
  "type": "Feature",
  "properties": {
    "addr:full":"6, Rte de Toulouse, 09100 Pamiers Midi Pyr\u00e9n\u00e9es 09100",
    "addr:housenumber":"6",
    "addr:postcode":"09100;09100",
    "addr:street":"Rte De Toulouse",
    "iso:country":"FR",
    "sg:address":"6, Rte de Toulouse, 09100 Pamiers",
    "sg:orig_category":"Non-Classified Establishments",
    "sg:phone":"+33 5 61 60 08 62",
    "sg:postcode":"09100",
    "sg:province":"Midi Pyr\u00e9n\u00e9es",
    "wof:name":"Acitec S.a.r.l.",
    "wof:placetype":"venue"
},
  "geometry": {"coordinates":[1.611076,43.122963],"type":"Point"}
}