{
  "type": "Feature",
  "properties": {
    "addr:full":"17/19 boulevard de la Muette 95140 Garges les Gonesse Ile de France",
    "addr:housenumber":"17 / 19",
    "addr:postcode":"95140",
    "addr:street":"Boulevard De La Muette",
    "iso:country":"FR",
    "sg:address":"17/19 boulevard de la Muette 95140 Garges les Gonesse",
    "sg:classifiers":[
        {
            "category":"Professional",
            "type":"Services"
        }
    ],
    "sg:phone":"+33 1 34 53 34 34",
    "sg:province":"Ile de France",
    "sg:tags":[
        "transport"
    ],
    "wof:name":"Bursped-france Sarl",
    "wof:placetype":"venue"
},
  "geometry": {"coordinates":[2.41221,48.977249],"type":"Point"}
}