{
  "type": "Feature",
  "properties": {
    "iso:country":"FR",
    "sg:address":"6, Rue des Fr\u00e8res Lumi\u00e8re, 67201 Eckbolsheim",
    "sg:city":"Eckbolsheim",
    "sg:orig_category":"Unclassifiable Establishments",
    "sg:phone":"+33 3 88 76 58 75",
    "sg:postcode":"67201",
    "sg:province":"Alsace",
    "wof:name":"Binzel Soudage S.a.r.l.",
    "wof:placetype":"venue"
},
  "geometry": {"coordinates":[7.686251,48.587257],"type":"Point"}
}