{
  "type": "Feature",
  "properties": {
    "iso:country":"FR",
    "sg:address":"16 Boulevard De L'Ouest 76000 Rouen",
    "sg:classifiers":[
        {
            "category":"Banks & Credit Unions",
            "subcategory":"Investment Brokerage",
            "type":"Services"
        }
    ],
    "sg:phone":"+33 2 35 52 42 70",
    "sg:postcode":"76000",
    "sg:province":"Haute Normandie",
    "sg:tags":[
        "sea",
        "transport",
        "air"
    ],
    "wof:name":"Compagnie D'affretement Et De Transport (cat)",
    "wof:placetype":"venue"
},
  "geometry": {"coordinates":[1.050296,49.449322],"type":"Point"}
}