{
  "type": "Feature",
  "properties": {
    "addr:full":"26/28 rue Gaylussac 95500 Gonesse Ile de France 95500",
    "addr:housenumber":"26 / 28",
    "addr:postcode":"95500;ile;95500",
    "addr:street":"Rue Gaylussac;France",
    "iso:country":"FR",
    "sg:address":"26/28 rue Gaylussac 95500 Gonesse",
    "sg:classifiers":[
        {
            "category":"Manufacturing",
            "subcategory":"Electronics",
            "type":"Manufacturing & Wholesale Goods"
        }
    ],
    "sg:phone":"+33 1 34 45 30 00",
    "sg:postcode":"95500",
    "sg:province":"Ile de France",
    "sg:tags":[
        "machine",
        "line",
        "answering",
        "multiple"
    ],
    "wof:name":"Ducros Euro Espresses Sa",
    "wof:placetype":"venue"
},
  "geometry": {"coordinates":[2.458674,48.981071],"type":"Point"}
}