{
  "type": "Feature",
  "properties": {
    "iso:country":"FR",
    "sg:address":"rue Paul Painlev\u00e9 95310 St Ouen l'Aumone",
    "sg:classifiers":[
        {
            "category":"Professional",
            "subcategory":"Employment Agencies",
            "type":"Services"
        }
    ],
    "sg:phone":"+33 1 34 30 28 30",
    "sg:postcode":"95310",
    "sg:province":"Ile de France",
    "sg:tags":[
        "import"
    ],
    "wof:name":"Mobrey S.a.",
    "wof:placetype":"venue"
},
  "geometry": {"coordinates":[-120.396912,38.051048],"type":"Point"}
}