{
  "type": "Feature",
  "properties": {
    "addr:full":"271, Rte de Gen\u00e8ve - Immeuble la Corraterie, 74160 Collonges sous Sal\u00e8ve Rhone-Alpes 74160",
    "addr:housenumber":"271",
    "addr:postcode":"74160;74160",
    "addr:street":"Rte De Gene\u0300Ve;La Corraterie;Sale\u0300Ve Rhone-Alpes",
    "iso:country":"FR",
    "sg:address":"271, Rte de Gen\u00e8ve - Immeuble la Corraterie, 74160 Collonges sous Sal\u00e8ve",
    "sg:orig_category":"Non-Classified Establishments",
    "sg:phone":"+33 820 33 79 33",
    "sg:postcode":"74160",
    "sg:province":"Rhone-Alpes",
    "wof:name":"B.p.s. - Banque Populaire Savoisienne",
    "wof:placetype":"venue"
},
  "geometry": {"coordinates":[6.139279,46.142635],"type":"Point"}
}