{
  "type": "Feature",
  "properties": {
    "addr:full":"14, Rue des Reculettes, 75013 Paris Ile de France",
    "addr:housenumber":"14",
    "addr:postcode":"75013",
    "addr:street":"Rue Des Reculettes",
    "iso:country":"FR",
    "sg:address":"14, Rue des Reculettes, 75013 Paris",
    "sg:orig_category":"Non-Classified Establishments",
    "sg:phone":"+33 1 44 08 19 00",
    "sg:province":"Ile de France",
    "wof:name":"I.f.t.h. - Institut Fran\u00e7ais Du Textile Et De L'habillement",
    "wof:placetype":"venue"
},
  "geometry": {"coordinates":[2.351205,48.831783],"type":"Point"}
}