{
  "type": "Feature",
  "properties": {
    "iso:country":"FR",
    "sg:address":"14 rue de la Fraternit\u00e9 38800 Le Pont de Claix",
    "sg:classifiers":[
        {
            "category":"Manufacturing",
            "subcategory":"Motor Vehicles & Parts",
            "type":"Manufacturing & Wholesale Goods"
        }
    ],
    "sg:phone":"+33 4 76 98 77 77",
    "sg:province":"Rhone-Alpes",
    "sg:tags":[
        "precision",
        "mechanic"
    ],
    "wof:name":"At. Nicr\u00e9 S.a.",
    "wof:placetype":"venue"
},
  "geometry": {"coordinates":[5.706418,45.136246],"type":"Point"}
}