{
  "type": "Feature",
  "properties": {
    "addr:full":"19 ter, Rue de Sentheim, 68290 Bourbach le Bas Bourbach-le-Haut Alsace 68290",
    "addr:housenumber":"19 ter",
    "addr:postcode":"68290;68290",
    "addr:street":"Rue De Sentheim;Le Bas Bourbach-Le-Haut",
    "iso:country":"FR",
    "sg:address":"19 ter, Rue de Sentheim, 68290 Bourbach le Bas",
    "sg:city":"Bourbach-le-Haut",
    "sg:orig_category":"Unclassifiable Establishments",
    "sg:phone":"+33 3 89 82 82 18",
    "sg:postcode":"68290",
    "sg:province":"Alsace",
    "wof:name":"M.i.d. S.a.r.l. - Maintenance Industrielle De La Doller",
    "wof:placetype":"venue"
},
  "geometry": {"coordinates":[7.060382,47.771679],"type":"Point"}
}