{
  "type": "Feature",
  "properties": {
    "iso:country":"FR",
    "sg:address":"B.P. 104, 74604 Seynod C\u00e9dex^^704, Av. d'Aix les Bains, 74600 Seynod",
    "sg:orig_category":"Non-Classified Establishments",
    "sg:phone":"+33 4 50 46 60 29",
    "sg:postcode":"74600",
    "sg:province":"Rhone-Alpes",
    "wof:name":"Alpes Jardins Paysages S.a.",
    "wof:placetype":"venue"
},
  "geometry": {"coordinates":[6.07243,45.852188],"type":"Point"}
}