{
  "type": "Feature",
  "properties": {
    "addr:full":"B.P. 45, 91470 Limours^^Centre Commercial les Arcades, 91470 Limours Ile de France 91470",
    "addr:postcode":"91470;91470;91470",
    "addr:street":"B.P. 45;Commercial;Arcades",
    "iso:country":"FR",
    "sg:address":"B.P. 45, 91470 Limours^^Centre Commercial les Arcades, 91470 Limours",
    "sg:orig_category":"Non-Classified Establishments",
    "sg:phone":"+33 820 33 69 59",
    "sg:postcode":"91470",
    "sg:province":"Ile de France",
    "wof:name":"B.i.c.s.",
    "wof:placetype":"venue"
},
  "geometry": {"coordinates":[2.07557,48.645081],"type":"Point"}
}