{
  "type": "Feature",
  "properties": {
    "iso:country":"FR",
    "sg:address":"41 Chemin Des Silos 31100 Toulouse",
    "sg:classifiers":[
        {
            "category":"Professional",
            "subcategory":"Engineering",
            "type":"Services"
        }
    ],
    "sg:phone":"+33 5 34 60 30 80",
    "sg:postcode":"31100",
    "sg:province":"Midi Pyr\u00e9n\u00e9es",
    "sg:tags":[
        "machine",
        "-",
        "mechanical"
    ],
    "wof:name":"Chaffoteaux & Maury",
    "wof:placetype":"venue"
},
  "geometry": {"coordinates":[1.417604,43.557655],"type":"Point"}
}