{
  "type": "Feature",
  "properties": {
    "addr:full":"Za Du Bois De L Abbesse 68660 Liepvre Li\u00e8pvre Alsace 68660",
    "addr:postcode":"68660;68660",
    "addr:street":"Za Du Bois De L Abbesse",
    "iso:country":"FR",
    "sg:address":"Za Du Bois De L Abbesse 68660 Liepvre",
    "sg:city":"Li\u00e8pvre",
    "sg:classifiers":[
        {
            "category":"Food & Beverages",
            "subcategory":"Groceries & Convenience Stores",
            "type":"Retail Goods"
        }
    ],
    "sg:phone":"+33 3 89 58 42 43",
    "sg:postcode":"68660",
    "sg:province":"Alsace",
    "sg:tags":[
        "product",
        "related"
    ],
    "wof:name":"Safapac",
    "wof:placetype":"venue"
},
  "geometry": {"coordinates":[7.327519,48.270386],"type":"Point"}
}