{
  "type": "Feature",
  "properties": {
    "iso:country":"FR",
    "sg:address":"77, Rue Saint Fuscien, 80000 Amiens",
    "sg:orig_category":"Unclassifiable Establishments",
    "sg:phone":"+33 3 22 82 81 00",
    "sg:province":"Picardie",
    "wof:name":"K.p.m.g. S.a.",
    "wof:placetype":"venue"
},
  "geometry": {"coordinates":[2.304693,49.882278],"type":"Point"}
}