{
  "type": "Feature",
  "properties": {
    "addr:full":"21, Rue Jean-Pierre Timbaud, 92320 Ch\u00e2tillon Ile de France",
    "addr:housenumber":"21",
    "addr:postcode":"92320;ile",
    "addr:street":"Rue Jean-Pierre Timbaud",
    "iso:country":"FR",
    "sg:address":"21, Rue Jean-Pierre Timbaud, 92320 Ch\u00e2tillon",
    "sg:orig_category":"Unclassifiable Establishments",
    "sg:phone":"+33 1 46 56 22 80",
    "sg:province":"Ile de France",
    "wof:name":"B.i.c.s.",
    "wof:placetype":"venue"
},
  "geometry": {"coordinates":[2.285783,48.802578],"type":"Point"}
}