{
  "type": "Feature",
  "properties": {
    "addr:full":"5 Verdun 51700 Vincelles Champagne 51700",
    "addr:housenumber":"5",
    "addr:postcode":"51700;51700",
    "addr:street":"Verdun;Champagne",
    "iso:country":"FR",
    "sg:address":"5",
    "sg:city":"Verdun 51700 Vincelles",
    "sg:classifiers":[
        {
            "category":"Food Court",
            "type":"Food & Drink"
        }
    ],
    "sg:phone":"+33 3 26 58 20 04",
    "sg:postcode":"51700",
    "sg:province":"Champagne",
    "sg:tags":[
        "product",
        "related"
    ],
    "wof:name":"Champagne H.blin Et Cie",
    "wof:placetype":"venue"
},
  "geometry": {"coordinates":[3.644475,49.092899],"type":"Point"}
}