{
  "type": "Feature",
  "properties": {
    "addr:full":"B.P. 15, 57920 K\u00e9dange sur Canner^^4, Rue de la Gare, 57920 K\u00e9dange sur Canner Lorraine",
    "addr:postcode":"57920;57920",
    "addr:street":"B.P. 15;Rue De La Gare;Canner",
    "iso:country":"FR",
    "sg:address":"B.P. 15, 57920 K\u00e9dange sur Canner^^4, Rue de la Gare, 57920 K\u00e9dange sur Canner",
    "sg:orig_category":"Non-Classified Establishments",
    "sg:phone":"+33 3 82 83 53 57",
    "sg:province":"Lorraine",
    "wof:name":"Semin S.a.",
    "wof:placetype":"venue"
},
  "geometry": {"coordinates":[6.37561,49.338692],"type":"Point"}
}