{
  "type": "Feature",
  "properties": {
    "iso:country":"FR",
    "sg:address":"route de Pontarlier 25500 Morteau",
    "sg:classifiers":[
        {
            "category":"Food & Beverages",
            "subcategory":"Meat & Fish",
            "type":"Retail Goods"
        }
    ],
    "sg:phone":"+33 3 81 67 68 70",
    "sg:postcode":"25500",
    "sg:province":"Franche Comt\u00e9",
    "wof:name":"Morteau Saucisse S.a.",
    "wof:placetype":"venue"
},
  "geometry": {"coordinates":[6.610826,47.022823],"type":"Point"}
}