{
  "type": "Feature",
  "properties": {
    "addr:full":"2, Av. de l'Europe, 54810 Longlaville Lorraine",
    "addr:postcode":"54810",
    "addr:street":"Av. De L'Europe",
    "iso:country":"FR",
    "sg:address":"2, Av. de l'Europe, 54810 Longlaville",
    "sg:orig_category":"Unclassifiable Establishments",
    "sg:phone":"+33 3 82 24 27 27",
    "sg:province":"Lorraine",
    "wof:name":"Acc\u00e8s Industrie S.a.",
    "wof:placetype":"venue"
},
  "geometry": {"coordinates":[5.790409,49.531136],"type":"Point"}
}