{
  "type": "Feature",
  "properties": {
    "addr:full":"867 avenue de la R\u00e9publique 59700 Marcq en Baroeul Nord Pas-de-Calais",
    "addr:housenumber":"867",
    "addr:postcode":"59700",
    "addr:street":"Avenue De La Re\u0301Publique;En Baroeul Nord",
    "iso:country":"FR",
    "sg:address":"867 avenue de la R\u00e9publique 59700 Marcq en Baroeul",
    "sg:orig_category":"Non-Classified Establishments",
    "sg:phone":"+33 3 20 72 22 80",
    "sg:province":"Nord Pas-de-Calais",
    "wof:name":"Lienard Freres Sa",
    "wof:placetype":"venue"
},
  "geometry": {"coordinates":[3.092353,50.659615],"type":"Point"}
}