{
  "type": "Feature",
  "properties": {
    "addr:full":"Chemin Coulommier Saint Souplet sur Py Champagne 51600",
    "addr:postcode":"51600",
    "addr:street":"Chemin Coulommier;Souplet Sur Py Champagne",
    "iso:country":"FR",
    "sg:address":"Chemin Coulommier",
    "sg:city":"Saint Souplet sur Py",
    "sg:orig_category":"Non-Classified Establishments",
    "sg:phone":"+33 3 26 03 73 26",
    "sg:postcode":"51600",
    "sg:province":"Champagne",
    "wof:name":"Sodine S.a.r.l.",
    "wof:placetype":"venue"
},
  "geometry": {"coordinates":[4.46665,49.236038],"type":"Point"}
}