{
  "type": "Feature",
  "properties": {
    "iso:country":"FR",
    "sg:address":"28, Av. Paul Vaillant Couturier, 94250 Gentilly",
    "sg:orig_category":"Unclassifiable Establishments",
    "sg:phone":"+33 1 45 46 16 49",
    "sg:province":"Ile de France",
    "wof:name":"Les Professionnels Du Nettoyage S.a.r.l.",
    "wof:placetype":"venue"
},
  "geometry": {"coordinates":[2.344973,48.815441],"type":"Point"}
}