{
  "type": "Feature",
  "properties": {
    "iso:country":"FR",
    "sg:address":"37, Rue de Lorraine, 59100 Roubaix",
    "sg:orig_category":"Non-Classified Establishments",
    "sg:phone":"+33 3 28 09 99 99",
    "sg:postcode":"59100",
    "sg:province":"Nord Pas-de-Calais",
    "wof:name":"Distri-pack S.a.r.l.",
    "wof:placetype":"venue"
},
  "geometry": {"coordinates":[3.160993,50.698833],"type":"Point"}
}