{
  "type": "Feature",
  "properties": {
    "addr:full":"Abattoirs Le Neubourg Haute Normandie 27110",
    "addr:postcode":"27110",
    "addr:street":"Abattoirs;Haute Normandie",
    "iso:country":"FR",
    "sg:address":"Abattoirs",
    "sg:city":"Le Neubourg",
    "sg:orig_category":"Unclassifiable Establishments",
    "sg:phone":"+33 2 32 38 97 11",
    "sg:postcode":"27110",
    "sg:province":"Haute Normandie",
    "wof:name":"Socopa S.a.",
    "wof:placetype":"venue"
},
  "geometry": {"coordinates":[0.940293,49.089191],"type":"Point"}
}