{
  "type": "Feature",
  "properties": {
    "iso:country":"FR",
    "sg:address":"9 rue de l'Industrie 67240 Bischwiller",
    "sg:city":"Bischwiller",
    "sg:classifiers":[
        {
            "category":"Building & Trades",
            "subcategory":"Plumbing",
            "type":"Services"
        }
    ],
    "sg:phone":"+33 3 88 53 94 94",
    "sg:postcode":"67240",
    "sg:province":"Alsace",
    "sg:tags":[
        "piping"
    ],
    "wof:name":"S.i.r.c. Sa",
    "wof:placetype":"venue"
},
  "geometry": {"coordinates":[7.85192,48.764832],"type":"Point"}
}