{
  "type": "Feature",
  "properties": {
    "addr:full":"3 Rue De L'Abrivado 34000 Montpellier Languedoc-Roussillon 34000",
    "addr:housenumber":"3",
    "addr:postcode":"34000;34000",
    "addr:street":"Rue De L'Abrivado",
    "iso:country":"FR",
    "sg:address":"3 Rue De L'Abrivado 34000 Montpellier",
    "sg:classifiers":[
        {
            "category":"Utilities",
            "subcategory":"Electric",
            "type":"Services"
        }
    ],
    "sg:phone":"+33 4 67 06 12 67",
    "sg:postcode":"34000",
    "sg:province":"Languedoc-Roussillon",
    "sg:tags":[
        "electricity",
        "electronic",
        "electrical",
        "equipment"
    ],
    "wof:name":"Ets Jean Jacques Teissier Sa",
    "wof:placetype":"venue"
},
  "geometry": {"coordinates":[3.885914,43.590199],"type":"Point"}
}