{
  "type": "Feature",
  "properties": {
    "addr:full":"45BIS avenue Edouard Vaillant 92100 Boulogne Billancourt Ile de France 92100",
    "addr:housenumber":"45bis",
    "addr:postcode":"92100;92100",
    "addr:street":"Avenue Edouard Vaillant",
    "iso:country":"FR",
    "sg:address":"45BIS avenue Edouard Vaillant 92100 Boulogne Billancourt",
    "sg:orig_category":"Fusible Conductors For Fuse Elements",
    "sg:phone":"+33 1 46 94 85 20",
    "sg:postcode":"92100",
    "sg:province":"Ile de France",
    "wof:name":"Etablissements Bardin Sas",
    "wof:placetype":"venue"
},
  "geometry": {"coordinates":[2.2512,48.835728],"type":"Point"}
}