{
  "type": "Feature",
  "properties": {
    "addr:full":"200, Chemin des Ormeaux, 69760 Limonest Rhone-Alpes 69760",
    "addr:housenumber":"200",
    "addr:postcode":"69760;69760",
    "addr:street":"Chemin Des Ormeaux",
    "iso:country":"FR",
    "sg:address":"200, Chemin des Ormeaux, 69760 Limonest",
    "sg:orig_category":"Unclassifiable Establishments",
    "sg:phone":"+33 4 78 66 34 66",
    "sg:postcode":"69760",
    "sg:province":"Rhone-Alpes",
    "wof:name":"M.v.i. Technologies S.a. - Monitoring Vibration Instrumentation Technologies",
    "wof:placetype":"venue"
},
  "geometry": {"coordinates":[4.772876,45.81007],"type":"Point"}
}