{
  "type": "Feature",
  "properties": {
    "addr:full":"B.P. 1023, 26010 Valence C\u00e9dex^^52-74, Rue Barth\u00e9l\u00e9my de Laffemaz, 26000 Valence Rhone-Alpes 26000",
    "addr:housenumber":"1023;-74",
    "addr:postcode":"26010;26000;26000",
    "addr:street":"B.P.;Rue Barthe\u0301Le\u0301My De Laffemaz",
    "iso:country":"FR",
    "sg:address":"B.P. 1023, 26010 Valence C\u00e9dex^^52-74, Rue Barth\u00e9l\u00e9my de Laffemaz, 26000 Valence",
    "sg:orig_category":"Non-Classified Establishments",
    "sg:phone":"+33 4 75 75 70 63",
    "sg:postcode":"26000",
    "sg:province":"Rhone-Alpes",
    "wof:name":"C.f.a.",
    "wof:placetype":"venue"
},
  "geometry": {"coordinates":[4.889246,44.930458],"type":"Point"}
}