{
  "type": "Feature",
  "properties": {
    "addr:full":"B.P. 116, 76430 Saint Romain de Colbosc^^Rte de Gommerville, 76430 Saint Romain de Colbosc Haute Normandie",
    "addr:housenumber":"b.p. 116",
    "addr:postcode":"76430;76430",
    "addr:street":"Haute Normandie",
    "iso:country":"FR",
    "sg:address":"B.P. 116, 76430 Saint Romain de Colbosc^^Rte de Gommerville, 76430 Saint Romain de Colbosc",
    "sg:orig_category":"Non-Classified Establishments",
    "sg:phone":"+33 2 32 79 29 29",
    "sg:province":"Haute Normandie",
    "wof:name":"S.i.m.p. S.a. - Soci\u00e9t\u00e9 Industrielle Menuiserie Plastique",
    "wof:placetype":"venue"
},
  "geometry": {"coordinates":[0.359242,49.52816],"type":"Point"}
}