{
  "type": "Feature",
  "properties": {
    "addr:full":"Villeneuve Sur Lot 47300 STE COLOMBE DE VILLENEUVE Villeneuve-sur-Lot Aquitaine 47300",
    "addr:housenumber":"lot 47300 ste",
    "addr:postcode":"47300",
    "iso:country":"FR",
    "sg:address":"Villeneuve Sur Lot 47300 STE COLOMBE DE VILLENEUVE",
    "sg:city":"Villeneuve-sur-Lot",
    "sg:classifiers":[
        {
            "category":"Professional",
            "type":"Services"
        }
    ],
    "sg:phone":"+33 5 53 41 50 00",
    "sg:postcode":"47300",
    "sg:province":"Aquitaine",
    "sg:tags":[
        "transport"
    ],
    "wof:name":"Transports E.h. Cugnenc Sa",
    "wof:placetype":"venue"
},
  "geometry": {"coordinates":[0.65937,44.35968],"type":"Point"}
}