{
  "type": "Feature",
  "properties": {
    "addr:full":"B.P. 561, 19107 Brive la Gaillarde C\u00e9dex^^15, Rue Daniel de Cosnac, 19100 Brive la Gaillarde Limousin",
    "addr:housenumber":"b.p. 561",
    "addr:postcode":"19107;19100",
    "addr:street":"Rue Daniel De Cosnac",
    "iso:country":"FR",
    "sg:address":"B.P. 561, 19107 Brive la Gaillarde C\u00e9dex^^15, Rue Daniel de Cosnac, 19100 Brive la Gaillarde",
    "sg:orig_category":"Non-Classified Establishments",
    "sg:phone":"+33 5 55 18 38 00",
    "sg:province":"Limousin",
    "wof:name":"G.e.b. S.a. - G\u00e9n\u00e9ral Electronique De Brive",
    "wof:placetype":"venue"
},
  "geometry": {"coordinates":[1.53587,45.157036],"type":"Point"}
}