{
  "type": "Feature",
  "properties": {
    "iso:country":"FR",
    "sg:address":"1 Rue Thiers 76210 Bolbec",
    "sg:classifiers":[
        {
            "category":"Manufacturing",
            "subcategory":"Chemicals & Compounds",
            "type":"Manufacturing & Wholesale Goods"
        }
    ],
    "sg:phone":"+33 2 35 31 00 04",
    "sg:postcode":"76210",
    "sg:province":"Haute Normandie",
    "sg:tags":[
        "pharmaceutical",
        "energy",
        "chemistry",
        "-",
        "by-product"
    ],
    "wof:name":"Dms Snc",
    "wof:placetype":"venue"
},
  "geometry": {"coordinates":[0.471445,49.570988],"type":"Point"}
}