{
  "type": "Feature",
  "properties": {
    "iso:country":"FR",
    "sg:address":"47 Rue Gallienie 77166 Grisy Suisnes",
    "sg:classifiers":[
        {
            "category":"Farming",
            "subcategory":"Farm",
            "type":"Manufacturing & Wholesale Goods"
        }
    ],
    "sg:phone":"+33 1 64 05 92 15",
    "sg:postcode":"77166",
    "sg:province":"Ile de France",
    "sg:tags":[
        "horticulture",
        "agriculture",
        "livestock"
    ],
    "wof:name":"Emmanuelli Paul",
    "wof:placetype":"venue"
},
  "geometry": {"coordinates":[2.634074,48.652786],"type":"Point"}
}