{
  "type": "Feature",
  "properties": {
    "addr:full":"B.P. 19, 71210 Montchanin^^Zone Industrielle de Torcy, 71210 Montchanin Montchanin Bourgogne 71210",
    "addr:postcode":"71210;71210;71210",
    "addr:street":"B.P. 19;Industrielle De Torcy",
    "iso:country":"FR",
    "sg:address":"B.P. 19, 71210 Montchanin^^Zone Industrielle de Torcy, 71210 Montchanin",
    "sg:city":"Montchanin",
    "sg:orig_category":"Non-Classified Establishments",
    "sg:phone":"+33 3 85 80 22 11",
    "sg:postcode":"71210",
    "sg:province":"Bourgogne",
    "wof:name":"Titan International S.a.",
    "wof:placetype":"venue"
},
  "geometry": {"coordinates":[4.463261,46.713284],"type":"Point"}
}