{
  "type": "Feature",
  "properties": {
    "addr:full":"Rte de Gouvieux Saint Maximin Picardie 60740",
    "addr:postcode":"60740",
    "addr:street":"Rte De Gouvieux Saint Maximin Picardie",
    "iso:country":"FR",
    "sg:address":"Rte de Gouvieux",
    "sg:city":"Saint Maximin",
    "sg:orig_category":"Non-Classified Establishments",
    "sg:phone":"+33 3 44 56 30 97",
    "sg:postcode":"60740",
    "sg:province":"Picardie",
    "wof:name":"Degan S.a.",
    "wof:placetype":"venue"
},
  "geometry": {"coordinates":[2.449529,49.215992],"type":"Point"}
}