{
  "type": "Feature",
  "properties": {
    "addr:full":"74 avenue Olivier Perroy 13790 Rousset Languedoc-Roussillon",
    "addr:housenumber":"74",
    "addr:postcode":"13790",
    "addr:street":"Avenue Olivier Perroy",
    "iso:country":"FR",
    "sg:address":"74 avenue Olivier Perroy 13790 Rousset",
    "sg:classifiers":[
        {
            "category":"Banks & Credit Unions",
            "subcategory":"Atm",
            "type":"Services"
        }
    ],
    "sg:phone":"+33 4 42 29 13 00",
    "sg:province":"Languedoc-Roussillon",
    "sg:tags":[
        "miscellaneous",
        "devices",
        "microelectronic"
    ],
    "wof:name":"Dupont Photomasks S.a.",
    "wof:placetype":"venue"
},
  "geometry": {"coordinates":[5.610615,43.468632],"type":"Point"}
}