{
  "type": "Feature",
  "properties": {
    "addr:full":"Chem Carri\u00e8res 73100 Gr\u00e9sy Sur Aix Rhone-Alpes",
    "addr:postcode":"73100",
    "addr:street":"Gre\u0301Sy",
    "iso:country":"FR",
    "sg:address":"Chem Carri\u00e8res 73100 Gr\u00e9sy Sur Aix",
    "sg:classifiers":[
        {
            "category":"Professional",
            "type":"Services"
        }
    ],
    "sg:phone":"+33 4 79 34 88 75",
    "sg:province":"Rhone-Alpes",
    "sg:tags":[
        "transport",
        "road"
    ],
    "wof:name":"Gianre Et Gaillard Industries Sa",
    "wof:placetype":"venue"
},
  "geometry": {"coordinates":[5.917358,45.71936],"type":"Point"}
}