{
  "type": "Feature",
  "properties": {
    "addr:full":"B.P. 233 Killem Nord Pas-de-Calais 59122",
    "addr:housenumber":"b.p. 233",
    "addr:postcode":"59122",
    "addr:street":"Killem Nord",
    "iso:country":"FR",
    "sg:address":"B.P. 233",
    "sg:city":"Killem",
    "sg:orig_category":"Non-Classified Establishments",
    "sg:phone":"+33 3 28 68 34 38",
    "sg:postcode":"59122",
    "sg:province":"Nord Pas-de-Calais",
    "wof:name":"Denis Pacquet S.a.r.l.",
    "wof:placetype":"venue"
},
  "geometry": {"coordinates":[2.564025,50.958481],"type":"Point"}
}