{
  "type": "Feature",
  "properties": {
    "addr:full":"107 rue Emile Zola 9e; Marseille Poitou-Charentes",
    "addr:housenumber":"107;9e",
    "addr:street":"Rue Emile Zola",
    "iso:country":"FR",
    "sg:address":"107 rue Emile Zola 9e; Marseille",
    "sg:classifiers":[
        {
            "category":"Banks & Credit Unions",
            "subcategory":"Bank",
            "type":"Services"
        }
    ],
    "sg:phone":"+33 3391401237",
    "sg:province":"Poitou-Charentes",
    "wof:name":"Cr\u00e9dit Lyonnais",
    "wof:placetype":"venue"
},
  "geometry": {"coordinates":[5.37249,43.293686],"type":"Point"}
}