{
  "type": "Feature",
  "properties": {
    "addr:full":"38210 VOUREY Rhone-Alpes 38210",
    "addr:postcode":"38210;38210",
    "addr:street":"Rhone-Alpes",
    "iso:country":"FR",
    "sg:address":"38210 VOUREY",
    "sg:classifiers":[
        {
            "category":"Manufacturing",
            "subcategory":"Metals",
            "type":"Manufacturing & Wholesale Goods"
        }
    ],
    "sg:phone":"+33 4 76 07 94 70",
    "sg:postcode":"38210",
    "sg:province":"Rhone-Alpes",
    "sg:tags":[
        "working"
    ],
    "wof:name":"M.g.i. S.a.",
    "wof:placetype":"venue"
},
  "geometry": {"coordinates":[5.520529,45.318779],"type":"Point"}
}