{
  "type": "Feature",
  "properties": {
    "iso:country":"FR",
    "sg:address":"Rue du Luxembourg",
    "sg:city":"Evreux",
    "sg:orig_category":"Unclassifiable Establishments",
    "sg:phone":"+33 2 32 39 05 28",
    "sg:postcode":"27000",
    "sg:province":"Haute Normandie",
    "wof:name":"Wattelet Michel",
    "wof:placetype":"venue"
},
  "geometry": {"coordinates":[1.18321,49.030369],"type":"Point"}
}