{
  "type": "Feature",
  "properties": {
    "addr:full":"31, Av. Marcel Pagnol, 81300 Graulhet Midi Pyr\u00e9n\u00e9es",
    "addr:postcode":"81300",
    "addr:street":"31 Av. Marcel Pagnol",
    "iso:country":"FR",
    "sg:address":"31, Av. Marcel Pagnol, 81300 Graulhet",
    "sg:orig_category":"Unclassifiable Establishments",
    "sg:phone":"+33 5 63 34 50 66",
    "sg:province":"Midi Pyr\u00e9n\u00e9es",
    "wof:name":"Etablissements Camille Sudre S.a.",
    "wof:placetype":"venue"
},
  "geometry": {"coordinates":[1.997936,43.768955],"type":"Point"}
}