{
  "type": "Feature",
  "properties": {
    "addr:full":"ZI de Blavozy Blavozy Auvergne 43700",
    "addr:postcode":"43700",
    "addr:street":"Zi De Blavozy Blavozy",
    "iso:country":"FR",
    "sg:address":"ZI de Blavozy",
    "sg:city":"Blavozy",
    "sg:orig_category":"Unclassifiable Establishments",
    "sg:phone":"+33 4 71 03 57 67",
    "sg:postcode":"43700",
    "sg:province":"Auvergne",
    "wof:name":"Bouchery S.a.",
    "wof:placetype":"venue"
},
  "geometry": {"coordinates":[3.969325,45.03875],"type":"Point"}
}