{
  "type": "Feature",
  "properties": {
    "iso:country":"FR",
    "sg:address":"24, Rue Fran\u00e7oise - ZI de la Plaine, 31140 Aucamville",
    "sg:orig_category":"Non-Classified Establishments",
    "sg:phone":"+33 5 61 70 54 02",
    "sg:province":"Midi Pyr\u00e9n\u00e9es",
    "wof:name":"Pons Fameco Et Compagnie S.a.",
    "wof:placetype":"venue"
},
  "geometry": {"coordinates":[1.429025,43.668308],"type":"Point"}
}