{
  "type": "Feature",
  "properties": {
    "addr:full":"Rte de Parthenay - ZAC de Luc Echire Poitou-Charentes 79410",
    "addr:postcode":"79410",
    "addr:street":"Rte De Parthenay Zac De Luc Echire",
    "iso:country":"FR",
    "sg:address":"Rte de Parthenay - ZAC de Luc",
    "sg:city":"Echire",
    "sg:orig_category":"Non-Classified Establishments",
    "sg:phone":"+33 5 49 33 15 00",
    "sg:postcode":"79410",
    "sg:province":"Poitou-Charentes",
    "wof:name":"Sevrienne Du Sanitaire Et Du Chauffage S.a.",
    "wof:placetype":"venue"
},
  "geometry": {"coordinates":[-0.528299,46.370762],"type":"Point"}
}