{
  "type": "Feature",
  "properties": {
    "addr:full":"433, Rue de la Tour, 94576 Chevilly Larue C\u00e9dex Aquitaine",
    "addr:housenumber":"433",
    "addr:postcode":"94576",
    "addr:street":"Rue De La Tour",
    "iso:country":"FR",
    "sg:address":"433, Rue de la Tour, 94576 Chevilly Larue C\u00e9dex",
    "sg:orig_category":"Non-Classified Establishments",
    "sg:phone":"+33 1 46 86 41 70",
    "sg:province":"Aquitaine",
    "wof:name":"Meseguer S.a.r.l.",
    "wof:placetype":"venue"
},
  "geometry": {"coordinates":[2.35325,48.751419],"type":"Point"}
}