{
  "type": "Feature",
  "properties": {
    "addr:full":"B.P. 32, 69126 Brindas C\u00e9dex^^72, Chemin du Devay, 69126 Brindas Rhone-Alpes",
    "addr:postcode":"69126;69126",
    "addr:street":"B.P. 32;Chemin Du Devay",
    "iso:country":"FR",
    "sg:address":"B.P. 32, 69126 Brindas C\u00e9dex^^72, Chemin du Devay, 69126 Brindas",
    "sg:orig_category":"Non-Classified Establishments",
    "sg:phone":"+33 4 78 45 05 70",
    "sg:province":"Rhone-Alpes",
    "wof:name":"Soci\u00e9t\u00e9 Odin S.a.r.l.",
    "wof:placetype":"venue"
},
  "geometry": {"coordinates":[4.693745,45.720596],"type":"Point"}
}