{
  "type": "Feature",
  "properties": {
    "addr:full":"za Naujac 12450 Primaube (La) Midi Pyr\u00e9n\u00e9es 12450",
    "addr:postcode":"12450;12450",
    "addr:street":"Za Naujac",
    "iso:country":"FR",
    "sg:address":"za Naujac 12450 Primaube (La)",
    "sg:classifiers":[
        {
            "category":"Home & Garden",
            "subcategory":"Furniture",
            "type":"Retail Goods"
        }
    ],
    "sg:phone":"+33 5 65 71 44 41",
    "sg:postcode":"12450",
    "sg:province":"Midi Pyr\u00e9n\u00e9es",
    "sg:tags":[
        "household",
        "wood"
    ],
    "wof:name":"Technilat",
    "wof:placetype":"venue"
},
  "geometry": {"coordinates":[2.513122,44.248798],"type":"Point"}
}