{
  "type": "Feature",
  "properties": {
    "addr:full":"16 chemin des Hirondelles 69570 Dardilly Rhone-Alpes 69570",
    "addr:housenumber":"16",
    "addr:postcode":"69570;69570",
    "addr:street":"Chemin Des Hirondelles",
    "iso:country":"FR",
    "sg:address":"16 chemin des Hirondelles 69570 Dardilly",
    "sg:classifiers":[
        {
            "category":"Wholesale",
            "subcategory":"Auto Parts",
            "type":"Manufacturing & Wholesale Goods"
        }
    ],
    "sg:phone":"+33 4 72 52 26 60",
    "sg:postcode":"69570",
    "sg:province":"Rhone-Alpes",
    "sg:tags":[
        "automobile",
        "component",
        "structural"
    ],
    "wof:name":"Mahle France S.a.r.l.",
    "wof:placetype":"venue"
},
  "geometry": {"coordinates":[4.76331,45.807388],"type":"Point"}
}