{
  "type": "Feature",
  "properties": {
    "iso:country":"FR",
    "sg:address":"64, Rue Galill\u00e9e, 75008 Paris",
    "sg:orig_category":"Non-Classified Establishments",
    "sg:phone":"+33 1 40 70 37 26",
    "sg:province":"Ile de France",
    "wof:name":"Nobel S.a.",
    "wof:placetype":"venue"
},
  "geometry": {"coordinates":[2.29923,48.871964],"type":"Point"}
}