{
  "type": "Feature",
  "properties": {
    "iso:country":"FR",
    "sg:address":"Rte Sainte Croix - La Fosse Guillotin",
    "sg:city":"Vauville",
    "sg:orig_category":"Unclassifiable Establishments",
    "sg:phone":"+33 2 33 52 63 76",
    "sg:postcode":"50440",
    "sg:province":"Basse Normandie",
    "wof:name":"Entreprise Nouvelle Isotherma S.a.",
    "wof:placetype":"venue"
},
  "geometry": {"coordinates":[-1.771329,49.639149],"type":"Point"}
}