{
  "type": "Feature",
  "properties": {
    "addr:full":"Zi Des Couflants Bd De L'Industrie 49000 Angers Pays de Loire",
    "addr:postcode":"49000",
    "addr:street":"Des;Bd De L'Industrie",
    "iso:country":"FR",
    "sg:address":"Zi Des Couflants",
    "sg:city":"Bd De L'Industrie 49000 Angers",
    "sg:classifiers":[
        {
            "category":"Manufacturing",
            "subcategory":"Rubber & Plastics",
            "type":"Manufacturing & Wholesale Goods"
        }
    ],
    "sg:phone":"+33 2 41 21 13 33",
    "sg:province":"Pays de Loire",
    "wof:name":"Imtec",
    "wof:placetype":"venue"
},
  "geometry": {"coordinates":[-0.507665,47.503178],"type":"Point"}
}