{
  "type": "Feature",
  "properties": {
    "iso:country":"FR",
    "sg:address":"59 Rue Bretonneau 37150 Chenonceaux",
    "sg:city":"Chenonceaux",
    "sg:classifiers":[
        {
            "category":"Building & Trades",
            "subcategory":"Construction",
            "type":"Services"
        }
    ],
    "sg:phone":"+33 2 47 23 84 84",
    "sg:postcode":"37150",
    "sg:province":"Centre",
    "sg:tags":[
        "pipe",
        "sheet",
        "work",
        "metallurgy",
        "metalworking",
        "public"
    ],
    "wof:name":"Etablissements Chottin Sa",
    "wof:placetype":"venue"
},
  "geometry": {"coordinates":[1.06966,47.33149],"type":"Point"}
}