{
  "type": "Feature",
  "properties": {
    "addr:full":"B.P. 3, 67831 Tanneries C\u00e9dex^^6, Rue de la faisanderie, 67380 Lingolsheim Lingolsheim Alsace 67380",
    "addr:housenumber":"3",
    "addr:postcode":"67831;67380;67380",
    "addr:street":"B.P.;Rue De La Faisanderie",
    "iso:country":"FR",
    "sg:address":"B.P. 3, 67831 Tanneries C\u00e9dex^^6, Rue de la faisanderie, 67380 Lingolsheim",
    "sg:city":"Lingolsheim",
    "sg:orig_category":"Non-Classified Establishments",
    "sg:phone":"+33 3 88 10 37 80",
    "sg:postcode":"67380",
    "sg:province":"Alsace",
    "wof:name":"Oc\u00e9 France S.a.",
    "wof:placetype":"venue"
},
  "geometry": {"coordinates":[7.68126,48.554295],"type":"Point"}
}