{
  "type": "Feature",
  "properties": {
    "addr:full":"75 Rue Castellion 01100 Oyonnax Rhone-Alpes 01100",
    "addr:housenumber":"75",
    "addr:postcode":"01100;01100",
    "addr:street":"Rue Castellion",
    "iso:country":"FR",
    "sg:address":"75 Rue Castellion 01100 Oyonnax",
    "sg:classifiers":[
        {
            "category":"Manufacturing",
            "subcategory":"Metals",
            "type":"Manufacturing & Wholesale Goods"
        }
    ],
    "sg:phone":"+33 4 74 77 09 78",
    "sg:postcode":"01100",
    "sg:province":"Rhone-Alpes",
    "sg:tags":[
        "metallurgy",
        "steel",
        "metalworking"
    ],
    "wof:name":"Locatelli Aciers Sa",
    "wof:placetype":"venue"
},
  "geometry": {"coordinates":[5.644649,46.24662],"type":"Point"}
}