{
  "type": "Feature",
  "properties": {
    "addr:full":"Cd 10 Gragnodere 33810 Amb\u00e8s Amb\u00e8s Aquitaine 33810",
    "addr:postcode":"33810;33810",
    "addr:street":"Cd 10 Gragnodere",
    "iso:country":"FR",
    "sg:address":"Cd 10 Gragnodere 33810 Amb\u00e8s",
    "sg:city":"Amb\u00e8s",
    "sg:classifiers":[
        {
            "category":"Banks & Credit Unions",
            "subcategory":"Investment Brokerage",
            "type":"Services"
        }
    ],
    "sg:phone":"+33 5 56 77 34 80",
    "sg:postcode":"33810",
    "sg:province":"Aquitaine",
    "sg:tags":[
        "-",
        "transport",
        "related"
    ],
    "wof:name":"E P G Entrepots Petroliers De La Gironde",
    "wof:placetype":"venue"
},
  "geometry": {"coordinates":[-0.529699,45.013222],"type":"Point"}
}