{
  "type": "Feature",
  "properties": {
    "iso:country":"FR",
    "sg:address":"14, Rue de la Blanchardi\u00e8re, 49300 Cholet",
    "sg:orig_category":"Unclassifiable Establishments",
    "sg:phone":"+33 2 41 71 57 50",
    "sg:province":"Pays de Loire",
    "wof:name":"U.s.m. France S.a.",
    "wof:placetype":"venue"
},
  "geometry": {"coordinates":[-0.842923,47.070621],"type":"Point"}
}