{
  "type": "Feature",
  "properties": {
    "iso:country":"FR",
    "sg:address":"11 rue du Verdier 69500 Bron",
    "sg:orig_category":"Gaskets, Washers, Seals",
    "sg:phone":"+33 4 72 91 22 00",
    "sg:postcode":"69500",
    "sg:province":"Rhone-Alpes",
    "wof:name":"Joint Lyonnais Techniques Indus Sa",
    "wof:placetype":"venue"
},
  "geometry": {"coordinates":[4.896227,45.733196],"type":"Point"}
}