{
  "type": "Feature",
  "properties": {
    "iso:country":"FR",
    "sg:address":"101-109 rue Jean Jaur\u00e8s 92300 Levallois Perret",
    "sg:classifiers":[
        {
            "category":"Banks & Credit Unions",
            "subcategory":"Investment Brokerage",
            "type":"Services"
        }
    ],
    "sg:phone":"+33 1 41 40 36 00",
    "sg:postcode":"92300",
    "sg:province":"Ile de France",
    "sg:tags":[
        "development",
        "consulting",
        "management",
        "corporate"
    ],
    "wof:name":"Ecti Ass",
    "wof:placetype":"venue"
},
  "geometry": {"coordinates":[2.296142,48.894966],"type":"Point"}
}