{
  "type": "Feature",
  "properties": {
    "addr:full":"32 rue de l'Expansion 67150 Erstein Erstein Alsace 67150",
    "addr:housenumber":"32",
    "addr:postcode":"67150;67150",
    "addr:street":"Rue De L'Expansion",
    "iso:country":"FR",
    "sg:address":"32 rue de l'Expansion 67150 Erstein",
    "sg:city":"Erstein",
    "sg:classifiers":[
        {
            "category":"Manufacturing",
            "subcategory":"Rubber & Plastics",
            "type":"Manufacturing & Wholesale Goods"
        }
    ],
    "sg:phone":"+33 3 88 59 85 59",
    "sg:postcode":"67150",
    "sg:province":"Alsace",
    "sg:tags":[
        "material"
    ],
    "wof:name":"Stac Enichem Polyurethanne France Sa",
    "wof:placetype":"venue"
},
  "geometry": {"coordinates":[7.633605,48.412617],"type":"Point"}
}