{
  "type": "Feature",
  "properties": {
    "addr:full":"Chemin du Bernoud Rumilly Nord Pas-de-Calais 74150",
    "addr:postcode":"74150",
    "addr:street":"Chemin Du Bernoud Rumilly Nord",
    "iso:country":"FR",
    "sg:address":"Chemin du Bernoud",
    "sg:city":"Rumilly",
    "sg:orig_category":"Unclassifiable Establishments",
    "sg:phone":"+33 4 50 01 03 68",
    "sg:postcode":"74150",
    "sg:province":"Nord Pas-de-Calais",
    "wof:name":"Dagand S.a.",
    "wof:placetype":"venue"
},
  "geometry": {"coordinates":[5.947225,45.867912],"type":"Point"}
}