{
  "type": "Feature",
  "properties": {
    "addr:full":"B.P. 17, 37210 Rochecorbon C\u00e9dex^^95, Quai de la Loire, 37210 Rochecorbon Rochecorbon Centre 37210",
    "addr:postcode":"37210;37210;37210",
    "addr:street":"B.P. 17;Quai De La Loire",
    "iso:country":"FR",
    "sg:address":"B.P. 17, 37210 Rochecorbon C\u00e9dex^^95, Quai de la Loire, 37210 Rochecorbon",
    "sg:city":"Rochecorbon",
    "sg:orig_category":"Non-Classified Establishments",
    "sg:phone":"+33 2 47 40 40 20",
    "sg:postcode":"37210",
    "sg:province":"Centre",
    "wof:name":"Blanc Foussy S.a.",
    "wof:placetype":"venue"
},
  "geometry": {"coordinates":[0.798817,47.41206],"type":"Point"}
}