{
  "type": "Feature",
  "properties": {
    "addr:full":"9, Rue du Mont Dore, 75017 Paris Ile de France",
    "addr:housenumber":"9",
    "addr:postcode":"75017",
    "addr:street":"Rue Du Mont Dore",
    "iso:country":"FR",
    "sg:address":"9, Rue du Mont Dore, 75017 Paris",
    "sg:orig_category":"Unclassifiable Establishments",
    "sg:phone":"+33 1 42 93 49 80",
    "sg:province":"Ile de France",
    "wof:name":"E.m.c. S.a. - Europ\u00e9enne De Mat\u00e9riaux Composites",
    "wof:placetype":"venue"
},
  "geometry": {"coordinates":[2.322857,48.883186],"type":"Point"}
}