{
  "type": "Feature",
  "properties": {
    "iso:country":"FR",
    "sg:address":"6, Rue des Fr\u00e8res Cubbedu, 13014 Marseille",
    "sg:orig_category":"Non-Classified Establishments",
    "sg:phone":"+33 4 91 11 63 50",
    "sg:province":"Poitou-Charentes",
    "wof:name":"Macor Neptun S.a.r.l.",
    "wof:placetype":"venue"
},
  "geometry": {"coordinates":[5.382876,43.316936],"type":"Point"}
}