{
  "type": "Feature",
  "properties": {
    "iso:country":"FR",
    "sg:address":"B.P. 79, 71103 Ch\u00e2lon sur Sa\u00f4ne C\u00e9dex^^11, Rue Georges Eastman, 71100 Ch\u00e2lon sur Sa\u00f4ne",
    "sg:city":"Chalon-sur-Sa\u00f4ne",
    "sg:orig_category":"Non-Classified Establishments",
    "sg:phone":"+33 3 85 42 32 00",
    "sg:postcode":"71100",
    "sg:province":"Bourgogne",
    "wof:name":"Ravensburger Cartonnages S.a.",
    "wof:placetype":"venue"
},
  "geometry": {"coordinates":[-93.77623,32.491989],"type":"Point"}
}