{
  "type": "Feature",
  "properties": {
    "iso:country":"FR",
    "sg:address":"160, Rue Montmartre, 75002 Paris",
    "sg:orig_category":"Non-Classified Establishments",
    "sg:phone":"+33 1 56 80 12 00",
    "sg:postcode":"75002",
    "sg:province":"Ile de France",
    "wof:name":"C\u00e9drom-sni S.a.",
    "wof:placetype":"venue"
},
  "geometry": {"coordinates":[2.342797,48.870159],"type":"Point"}
}