{
  "type": "Feature",
  "properties": {
    "iso:country":"FR",
    "sg:address":"Rte de la Retardais",
    "sg:city":"Rennes",
    "sg:orig_category":"Unclassifiable Establishments",
    "sg:phone":"+33 2 99 54 01 50",
    "sg:postcode":"35000",
    "sg:province":"Bretagne",
    "wof:name":"Casa S.a.r.l.",
    "wof:placetype":"venue"
},
  "geometry": {"coordinates":[-1.728554,48.104324],"type":"Point"}
}