{
  "type": "Feature",
  "properties": {
    "addr:full":"41, All\u00e9e des Mousquetaires - Parc de Tr\u00e9ville, 91070 Bondoufle Ile de France",
    "addr:housenumber":"41",
    "addr:postcode":"91070;ile",
    "addr:street":"Alle\u0301E Des Mousquetaires Parc De Tre\u0301Ville",
    "iso:country":"FR",
    "sg:address":"41, All\u00e9e des Mousquetaires - Parc de Tr\u00e9ville, 91070 Bondoufle",
    "sg:orig_category":"Unclassifiable Establishments",
    "sg:phone":"+33 1 69 64 10 40",
    "sg:province":"Ile de France",
    "wof:name":"Direction V\u00e9timarch\u00e9 S.a.",
    "wof:placetype":"venue"
},
  "geometry": {"coordinates":[2.379516,48.615681],"type":"Point"}
}