{
  "type": "Feature",
  "properties": {
    "addr:full":"1104, Rte de Chemery - Les Riavents , 41230 Mur de Sologne Courmemin Centre 41230",
    "addr:housenumber":"1104",
    "addr:postcode":"41230;41230",
    "addr:street":"Rte De Chemery Les Riavents",
    "iso:country":"FR",
    "sg:address":"1104, Rte de Chemery - Les Riavents , 41230 Mur de Sologne",
    "sg:city":"Courmemin",
    "sg:orig_category":"Non-Classified Establishments",
    "sg:phone":"+33 2 54 83 82 93",
    "sg:postcode":"41230",
    "sg:province":"Centre",
    "wof:name":"Entreprise Soupiron S.a.r.l.",
    "wof:placetype":"venue"
},
  "geometry": {"coordinates":[1.535743,47.362568],"type":"Point"}
}