{
  "type": "Feature",
  "properties": {
    "addr:full":"Parc Activites Zone 2 8 Rue Jacques Messager 59175 Templemars Nord Pas-de-Calais 59175",
    "addr:housenumber":"8",
    "addr:postcode":"59175;59175",
    "addr:street":"Zone 2;Rue Jacques Messager",
    "iso:country":"FR",
    "sg:address":"Parc Activites Zone 2 8 Rue Jacques Messager 59175 Templemars",
    "sg:classifiers":[
        {
            "category":"Shopping",
            "subcategory":"Clothing, Apparel, & Fashions",
            "type":"Retail Goods"
        }
    ],
    "sg:phone":"+33 3 20 60 28 70",
    "sg:postcode":"59175",
    "sg:province":"Nord Pas-de-Calais",
    "sg:tags":[
        "textile",
        "clothing",
        "clothes"
    ],
    "wof:name":"Viking Industries Sarl",
    "wof:placetype":"venue"
},
  "geometry": {"coordinates":[3.06248,50.566944],"type":"Point"}
}