{
  "type": "Feature",
  "properties": {
    "addr:full":"rue Alexandre Fl\u00e9ming 14100 Lisieux Lisieux Basse Normandie 14100",
    "addr:postcode":"14100;14100",
    "addr:street":"Rue Alexandre Fle\u0301Ming",
    "iso:country":"FR",
    "sg:address":"rue Alexandre Fl\u00e9ming 14100 Lisieux",
    "sg:city":"Lisieux",
    "sg:classifiers":[
        {
            "category":"Communications",
            "subcategory":"Film & Video Production",
            "type":"Services"
        }
    ],
    "sg:phone":"+33 2 31 62 99 00",
    "sg:postcode":"14100",
    "sg:province":"Basse Normandie",
    "sg:tags":[
        "packaging",
        "adhesive",
        "imprinted",
        "tapes"
    ],
    "wof:name":"I.c.a.m. S.a.",
    "wof:placetype":"venue"
},
  "geometry": {"coordinates":[0.254875,49.15028],"type":"Point"}
}