{
  "type": "Feature",
  "properties": {
    "addr:full":"Plan Des Berg\u00e8res 73210 Aime Rhone-Alpes 73210",
    "addr:postcode":"73210;73210",
    "addr:street":"Plan Des Berge\u0300Res",
    "iso:country":"FR",
    "sg:address":"Plan Des Berg\u00e8res 73210 Aime",
    "sg:classifiers":[
        {
            "category":"Building & Trades",
            "subcategory":"Construction",
            "type":"Services"
        }
    ],
    "sg:phone":"+33 4 79 09 73 24",
    "sg:postcode":"73210",
    "sg:province":"Rhone-Alpes",
    "sg:tags":[
        "work",
        "public"
    ],
    "wof:name":"Carret Vettier Sa",
    "wof:placetype":"venue"
},
  "geometry": {"coordinates":[6.656135,45.55529],"type":"Point"}
}