{
  "type": "Feature",
  "properties": {
    "addr:full":"2 Rue Domaine De Perignon 51480 Cormoyeux Champagne 51480",
    "addr:housenumber":"2",
    "addr:postcode":"51480;51480",
    "addr:street":"Rue Domaine;Champagne",
    "iso:country":"FR",
    "sg:address":"2 Rue Domaine De Perignon 51480 Cormoyeux",
    "sg:classifiers":[
        {
            "category":"Food Court",
            "type":"Food & Drink"
        }
    ],
    "sg:phone":"+33 3 26 58 64 15",
    "sg:postcode":"51480",
    "sg:province":"Champagne",
    "sg:tags":[
        "product",
        "related"
    ],
    "wof:name":"Sarl Champagne Francis Mondet",
    "wof:placetype":"venue"
},
  "geometry": {"coordinates":[3.878572,49.072487],"type":"Point"}
}