{
  "type": "Feature",
  "properties": {
    "addr:full":"B.P. 117, 57371 Phalsbourg C\u00e9dex^^Chemin des Dames, 57370 Phalsbourg Lorraine 57370",
    "addr:housenumber":"b.p. 117",
    "addr:postcode":"57371;57370;57370",
    "addr:street":"Des Dames",
    "iso:country":"FR",
    "sg:address":"B.P. 117, 57371 Phalsbourg C\u00e9dex^^Chemin des Dames, 57370 Phalsbourg",
    "sg:orig_category":"Non-Classified Establishments",
    "sg:phone":"+33 3 87 24 13 91",
    "sg:postcode":"57370",
    "sg:province":"Lorraine",
    "wof:name":"Depalor S.a.s.",
    "wof:placetype":"venue"
},
  "geometry": {"coordinates":[7.262298,48.763966],"type":"Point"}
}