{
  "type": "Feature",
  "properties": {
    "iso:country":"FR",
    "sg:address":"ZI",
    "sg:city":"Le Cergne",
    "sg:orig_category":"Unclassifiable Establishments",
    "sg:phone":"+33 4 74 89 73 52",
    "sg:postcode":"42460",
    "sg:province":"Rhone-Alpes",
    "wof:name":"J. Plasse S.a.",
    "wof:placetype":"venue"
},
  "geometry": {"coordinates":[4.210919,46.073792],"type":"Point"}
}