{
  "type": "Feature",
  "properties": {
    "addr:full":"7 Rte Galice; Aix en Provence; 13090 Nord Pas-de-Calais",
    "addr:housenumber":"7;13090",
    "addr:street":"Rte Galice",
    "iso:country":"FR",
    "sg:address":"7 Rte Galice; Aix en Provence; 13090",
    "sg:classifiers":[
        {
            "category":"Banks & Credit Unions",
            "subcategory":"Bank",
            "type":"Services"
        }
    ],
    "sg:phone":"+33 3342951781",
    "sg:province":"Nord Pas-de-Calais",
    "wof:name":"Lyonnaise De Banque Sa, Immeuble Mirabeau",
    "wof:placetype":"venue"
},
  "geometry": {"coordinates":[5.434741,43.528366],"type":"Point"}
}