{
  "type": "Feature",
  "properties": {
    "addr:full":"Parc Pompidou - Entr\u00e9e 3 Vannes Bretagne 56000",
    "addr:postcode":"56000",
    "addr:street":"Vannes Bretagne",
    "iso:country":"FR",
    "sg:address":"Parc Pompidou - Entr\u00e9e 3",
    "sg:city":"Vannes",
    "sg:orig_category":"Unclassifiable Establishments",
    "sg:phone":"+33 2 97 47 95 43",
    "sg:postcode":"56000",
    "sg:province":"Bretagne",
    "wof:name":"Burotic Assistantes Routage S.a.r.l.",
    "wof:placetype":"venue"
},
  "geometry": {"coordinates":[-2.770283,47.666241],"type":"Point"}
}