{
  "type": "Feature",
  "properties": {
    "addr:full":"Gare Sncf Marchandise Avenue De Franckfort Chantier Roussillon 66000 Perpignan Languedoc-Roussillon",
    "addr:postcode":"66000",
    "addr:street":"Marchandise Avenue De Franckfort Chantier",
    "iso:country":"FR",
    "sg:address":"Gare Sncf Marchandise Avenue De Franckfort Chantier Roussillon 66000 Perpignan",
    "sg:classifiers":[
        {
            "category":"Professional",
            "type":"Services"
        }
    ],
    "sg:phone":"+33 4 68 85 39 42",
    "sg:province":"Languedoc-Roussillon",
    "sg:tags":[
        "transport",
        "road"
    ],
    "wof:name":"Tels Jodis",
    "wof:placetype":"venue"
},
  "geometry": {"coordinates":[2.88743,42.69812],"type":"Point"}
}