{
  "type": "Feature",
  "properties": {
    "iso:country":"FR",
    "sg:address":"Carreau de la Mine 57380 Faulquemont",
    "sg:orig_category":"Non-Classified Establishments",
    "sg:phone":"+33 3 87 90 70 36",
    "sg:province":"Lorraine",
    "wof:name":"Humus Innovation S.a.",
    "wof:placetype":"venue"
},
  "geometry": {"coordinates":[6.599175,49.042831],"type":"Point"}
}