{
  "type": "Feature",
  "properties": {
    "addr:full":"142/176, Av. de Stalingrad, 92712 Colombes C\u00e9dex \u00cele-de-France",
    "addr:housenumber":"142 / 176",
    "addr:postcode":"92712",
    "addr:street":"Av. De Stalingrad;Ce\u0301Dex",
    "iso:country":"FR",
    "sg:address":"142/176, Av. de Stalingrad, 92712 Colombes C\u00e9dex",
    "sg:orig_category":"Non-Classified Establishments",
    "sg:phone":"+33 1 47 80 35 12",
    "sg:province":"\u00cele-de-France",
    "wof:name":"Rota S.a.r.l.",
    "wof:placetype":"venue"
},
  "geometry": {"coordinates":[2.262461,48.934883],"type":"Point"}
}