{
  "type": "Feature",
  "properties": {
    "addr:full":"14 Rue Leonard De Vinci 75116 Paris Aquitaine",
    "addr:housenumber":"14",
    "addr:postcode":"75116",
    "addr:street":"Rue Leonard De Vinci",
    "iso:country":"FR",
    "sg:address":"14 Rue Leonard De Vinci 75116 Paris",
    "sg:classifiers":[
        {
            "category":"Communications",
            "type":"Services"
        }
    ],
    "sg:phone":"+33 1 45 00 40 15",
    "sg:province":"Aquitaine",
    "sg:tags":[
        "translation",
        "training",
        "interpretation",
        "advice",
        "business"
    ],
    "wof:name":"Ecole France Langue",
    "wof:placetype":"venue"
},
  "geometry": {"coordinates":[2.285777,48.870659],"type":"Point"}
}