{
  "type": "Feature",
  "properties": {
    "addr:full":"ZA les Pr\u00e9s Mouchets Morteau Franche Comt\u00e9 25500",
    "addr:postcode":"25500",
    "addr:street":"Za Les;Mouchets;Franche Comte\u0301",
    "iso:country":"FR",
    "sg:address":"ZA les Pr\u00e9s Mouchets",
    "sg:city":"Morteau",
    "sg:orig_category":"Non-Classified Establishments",
    "sg:phone":"+33 3 81 67 53 39",
    "sg:postcode":"25500",
    "sg:province":"Franche Comt\u00e9",
    "wof:name":"B.i.p.",
    "wof:placetype":"venue"
},
  "geometry": {"coordinates":[6.60495,47.058907],"type":"Point"}
}