{
  "type": "Feature",
  "properties": {
    "iso:country":"FR",
    "sg:address":"3 Allee De Chantilly Parc Club De Nancy Brabois 54500 Vandoeuvre Les Nancy",
    "sg:classifiers":[
        {
            "category":"Banks & Credit Unions",
            "subcategory":"Investment Brokerage",
            "type":"Services"
        }
    ],
    "sg:phone":"+33 3 83 44 34 00",
    "sg:province":"Lorraine",
    "sg:tags":[
        "-",
        "transport",
        "related"
    ],
    "wof:name":"Neopost France",
    "wof:placetype":"venue"
},
  "geometry": {"coordinates":[6.137425,48.653759],"type":"Point"}
}