{
  "type": "Feature",
  "properties": {
    "iso:country":"FR",
    "sg:address":"62060 Arras C\u00e9dex^^Av. du Portugal",
    "sg:city":"Monchy le Preux",
    "sg:orig_category":"Non-Classified Establishments",
    "sg:phone":"+33 3 21 21 74 60",
    "sg:postcode":"62118",
    "sg:province":"Nord Pas-de-Calais",
    "wof:name":"New Transunion S.a.",
    "wof:placetype":"venue"
},
  "geometry": {"coordinates":[2.94502,50.310165],"type":"Point"}
}