{
  "type": "Feature",
  "properties": {
    "addr:full":"22130 Planco\u00ebt Planco\u00ebt Bretagne 22130",
    "addr:postcode":"22130;22130",
    "iso:country":"FR",
    "sg:address":"22130 Planco\u00ebt",
    "sg:city":"Planco\u00ebt",
    "sg:orig_category":"Unclassifiable Establishments",
    "sg:phone":"+33 2 96 84 39 10",
    "sg:postcode":"22130",
    "sg:province":"Bretagne",
    "wof:name":"Eaux Min\u00e9rales Naturelles De Planco\u00ebt Source De Sassay S.a.",
    "wof:placetype":"venue"
},
  "geometry": {"coordinates":[-2.239071,48.523045],"type":"Point"}
}