{
  "type": "Feature",
  "properties": {
    "iso:country":"FR",
    "sg:address":"96, Chemin du Raisin, 31200 Toulouse",
    "sg:orig_category":"Unclassifiable Establishments",
    "sg:phone":"+33 5 61 61 62 20",
    "sg:province":"Midi Pyr\u00e9n\u00e9es",
    "wof:name":"Calberson Sud Ouest S.a.",
    "wof:placetype":"venue"
},
  "geometry": {"coordinates":[1.447473,43.61684],"type":"Point"}
}