{
  "type": "Feature",
  "properties": {
    "addr:full":"58 rue des Papeteries 68000 Colmar Colmar Alsace 68000",
    "addr:housenumber":"58",
    "addr:postcode":"68000;68000",
    "addr:street":"Rue Des Papeteries",
    "iso:country":"FR",
    "sg:address":"58 rue des Papeteries 68000 Colmar",
    "sg:city":"Colmar",
    "sg:classifiers":[
        {
            "category":"Home & Garden",
            "subcategory":"Building Materials",
            "type":"Retail Goods"
        }
    ],
    "sg:phone":"+33 3 89 20 30 40",
    "sg:postcode":"68000",
    "sg:province":"Alsace",
    "sg:tags":[
        "tile",
        "granite"
    ],
    "wof:name":"Alsace Carreaux S A",
    "wof:placetype":"venue"
},
  "geometry": {"coordinates":[7.351746,48.091759],"type":"Point"}
}