{
  "type": "Feature",
  "properties": {
    "addr:full":"46, Rue Thiers, 51360 Verzenay Champagne 51360",
    "addr:housenumber":"46",
    "addr:postcode":"51360;51360",
    "addr:street":"Rue Thiers;Champagne",
    "iso:country":"FR",
    "sg:address":"46, Rue Thiers, 51360 Verzenay",
    "sg:orig_category":"Non-Classified Establishments",
    "sg:phone":"+33 3 26 49 40 90",
    "sg:postcode":"51360",
    "sg:province":"Champagne",
    "wof:name":"Champagne Bernard Hatt\u00e9 Et Fils",
    "wof:placetype":"venue"
},
  "geometry": {"coordinates":[4.146955,49.158333],"type":"Point"}
}