{
  "type": "Feature",
  "properties": {
    "addr:full":"63, Rue des Villas, 59200 Tourcoing Nord Pas-de-Calais",
    "addr:housenumber":"63",
    "addr:postcode":"59200",
    "addr:street":"Rue Des Villas",
    "iso:country":"FR",
    "sg:address":"63, Rue des Villas, 59200 Tourcoing",
    "sg:orig_category":"Unclassifiable Establishments",
    "sg:phone":"+33 3 20 26 70 90",
    "sg:province":"Nord Pas-de-Calais",
    "wof:name":"Vandenbulcke S.a.",
    "wof:placetype":"venue"
},
  "geometry": {"coordinates":[3.153125,50.696236],"type":"Point"}
}