{
  "type": "Feature",
  "properties": {
    "iso:country":"FR",
    "sg:address":"B.P. 4, 76320 Caudebec les Elbeuf^^247, Rue F\u00e9lix Faure, 76320 Caudebec les Elbeuf",
    "sg:orig_category":"Non-Classified Establishments",
    "sg:phone":"+33 2 32 96 01 81",
    "sg:postcode":"76320",
    "sg:province":"Haute Normandie",
    "wof:name":"Ecb Thommeret S.a.",
    "wof:placetype":"venue"
},
  "geometry": {"coordinates":[1.01608,49.283875],"type":"Point"}
}