{
  "type": "Feature",
  "properties": {
    "addr:full":"ZI Bergerac Aquitaine 24100",
    "addr:postcode":"24100",
    "iso:country":"FR",
    "sg:address":"ZI",
    "sg:city":"Bergerac",
    "sg:orig_category":"Unclassifiable Establishments",
    "sg:phone":"+33 5 53 73 13 29",
    "sg:postcode":"24100",
    "sg:province":"Aquitaine",
    "wof:name":"Palmigord S.a.",
    "wof:placetype":"venue"
},
  "geometry": {"coordinates":[0.45362,44.815235],"type":"Point"}
}