{
  "type": "Feature",
  "properties": {
    "addr:full":"87 rue Dalayrac; Fontenay sous Bois; 94120 Ile de France 94120",
    "addr:housenumber":"87",
    "addr:postcode":"94120;94120",
    "addr:street":"Rue Dalayrac;Bois;France",
    "iso:country":"FR",
    "sg:address":"87 rue Dalayrac; Fontenay sous Bois; 94120",
    "sg:classifiers":[
        {
            "category":"Banks & Credit Unions",
            "subcategory":"Bank",
            "type":"Services"
        }
    ],
    "sg:phone":"+33 18730842",
    "sg:postcode":"94120",
    "sg:province":"Ile de France",
    "wof:name":"Banque Nationale De Paris",
    "wof:placetype":"venue"
},
  "geometry": {"coordinates":[2.460579,48.848763],"type":"Point"}
}