{
  "type": "Feature",
  "properties": {
    "iso:country":"FR",
    "sg:address":"19/25, Rue Auguste Comte, 87000 Limoges",
    "sg:orig_category":"Unclassifiable Establishments",
    "sg:phone":"+33 5 55 04 59 99",
    "sg:province":"Limousin",
    "wof:name":"A.b.x. Logistics France S.a.",
    "wof:placetype":"venue"
},
  "geometry": {"coordinates":[1.271596,45.875607],"type":"Point"}
}