{
  "type": "Feature",
  "properties": {
    "iso:country":"FR",
    "sg:address":"6, Bd Valentin, 13011 Marseille",
    "sg:orig_category":"Unclassifiable Establishments",
    "sg:phone":"+33 4 91 43 17 80",
    "sg:province":"Provence-Alpes-C\u00f4te d'Azur",
    "wof:name":"Biscuiterie Castellane S.a.r.l.",
    "wof:placetype":"venue"
},
  "geometry": {"coordinates":[5.481959,43.296303],"type":"Point"}
}