{
  "type": "Feature",
  "properties": {
    "addr:full":"4, Rue de la Rotonde, 67200 Strasbourg Strasbourg Alsace 67200",
    "addr:housenumber":"4",
    "addr:postcode":"67200;67200",
    "addr:street":"Rue De La Rotonde",
    "iso:country":"FR",
    "sg:address":"4, Rue de la Rotonde, 67200 Strasbourg",
    "sg:city":"Strasbourg",
    "sg:orig_category":"Unclassifiable Establishments",
    "sg:phone":"+33 3 88 27 03 03",
    "sg:postcode":"67200",
    "sg:province":"Alsace",
    "wof:name":"P\u00e9pini\u00e8res Rietsch",
    "wof:placetype":"venue"
},
  "geometry": {"coordinates":[7.725977,48.593864],"type":"Point"}
}