{
  "type": "Feature",
  "properties": {
    "iso:country":"FR",
    "sg:address":"B.P. 149, 37401 Amboise C\u00e9dex^^15, Bd de l'industrie - ZI de Nazelles, 37400 Amboise",
    "sg:city":"Amboise",
    "sg:orig_category":"Non-Classified Establishments",
    "sg:phone":"+33 2 47 23 42 00",
    "sg:postcode":"37400",
    "sg:province":"Centre",
    "wof:name":"Equip Labo S.a.",
    "wof:placetype":"venue"
},
  "geometry": {"coordinates":[0.980454,47.418278],"type":"Point"}
}