{
  "type": "Feature",
  "properties": {
    "addr:full":"Zone Industrielle Coquet 03260 St Germain Des Foss\u00e9s Marcenat Auvergne 03260",
    "addr:postcode":"03260;03260",
    "addr:street":"Zone Industrielle Coquet;Des Fosse\u0301S Marcenat",
    "iso:country":"FR",
    "sg:address":"Zone Industrielle Coquet 03260 St Germain Des Foss\u00e9s",
    "sg:city":"Marcenat",
    "sg:classifiers":[
        {
            "category":"Manufacturing",
            "subcategory":"Wood Products",
            "type":"Manufacturing & Wholesale Goods"
        }
    ],
    "sg:phone":"+33 4 70 59 60 19",
    "sg:postcode":"03260",
    "sg:province":"Auvergne",
    "sg:tags":[
        "professional",
        "furniture"
    ],
    "wof:name":"Ste Industrielle Du Mobilier Sa",
    "wof:placetype":"venue"
},
  "geometry": {"coordinates":[3.43254,46.204044],"type":"Point"}
}