{
  "type": "Feature",
  "properties": {
    "addr:full":"63, Av. de Villiers, 75017 Paris Ile de France",
    "addr:postcode":"75017",
    "addr:street":"63 Av. De Villiers",
    "iso:country":"FR",
    "sg:address":"63, Av. de Villiers, 75017 Paris",
    "sg:orig_category":"Non-Classified Establishments",
    "sg:phone":"+33 1 42 12 85 00",
    "sg:province":"Ile de France",
    "wof:name":"Risc International Europe S.a.",
    "wof:placetype":"venue"
},
  "geometry": {"coordinates":[2.305436,48.88353],"type":"Point"}
}