{
  "type": "Feature",
  "properties": {
    "iso:country":"FR",
    "sg:address":"4 Rue Des Ponts Neuf 85770 L'Ile D'Elle",
    "sg:classifiers":[
        {
            "category":"Manufacturing",
            "subcategory":"Paper Products",
            "type":"Manufacturing & Wholesale Goods"
        }
    ],
    "sg:phone":"+33 2 51 53 15 15",
    "sg:province":"Pays de Loire",
    "sg:tags":[
        "packaging",
        "material",
        "-",
        "cardboard"
    ],
    "wof:name":"Huhtamaki La Rochelle",
    "wof:placetype":"venue"
},
  "geometry": {"coordinates":[-82.76387,38.059769],"type":"Point"}
}