{
  "type": "Feature",
  "properties": {
    "iso:country":"FR",
    "sg:address":"B.P. 51, 38242 Meylan C\u00e9dex^^10, Place des Tuileaux, 38240 Meylan",
    "sg:orig_category":"Non-Classified Establishments",
    "sg:phone":"+33 4 76 41 38 22",
    "sg:postcode":"38240",
    "sg:province":"Rhone-Alpes",
    "wof:name":"S\u00e9lectour Envol Voyages S.a.",
    "wof:placetype":"venue"
},
  "geometry": {"coordinates":[5.77846,45.209316],"type":"Point"}
}