{
  "type": "Feature",
  "properties": {
    "iso:country":"FR",
    "sg:address":"4 bis, Rue Lescure, 49300 Cholet",
    "sg:orig_category":"Unclassifiable Establishments",
    "sg:phone":"+33 2 41 62 25 31",
    "sg:province":"Pays de Loire",
    "wof:name":"Soci\u00e9t\u00e9 Aumon Constructions S.a.r.l.",
    "wof:placetype":"venue"
},
  "geometry": {"coordinates":[-0.864898,47.070271],"type":"Point"}
}