{
  "type": "Feature",
  "properties": {
    "addr:full":"1, All\u00e9e des Ch\u00e2taigniers - ZA du Buisson de la Couldre, 78190 Trappes Ile de France",
    "addr:housenumber":"1",
    "addr:postcode":"78190;ile",
    "addr:street":"Alle\u0301E Des Cha\u0302Taigniers Za Du Buisson De La Couldre",
    "iso:country":"FR",
    "sg:address":"1, All\u00e9e des Ch\u00e2taigniers - ZA du Buisson de la Couldre, 78190 Trappes",
    "sg:orig_category":"Non-Classified Establishments",
    "sg:phone":"+33 1 30 66 10 99",
    "sg:province":"Ile de France",
    "wof:name":"G.d.i. S.a. - Graeff Dessin Industriel",
    "wof:placetype":"venue"
},
  "geometry": {"coordinates":[1.999285,48.774651],"type":"Point"}
}