{
  "type": "Feature",
  "properties": {
    "iso:country":"FR",
    "sg:address":"2, Rue Charles Edouard Jeanneret - Technoparc de Poissy, 78300 Poissy",
    "sg:orig_category":"Non-Classified Establishments",
    "sg:phone":"+33 1 39 22 33 00",
    "sg:postcode":"78300",
    "sg:province":"Ile de France",
    "wof:name":"A.i.s. S.a. - Aries Industries Structures",
    "wof:placetype":"venue"
},
  "geometry": {"coordinates":[2.04256,48.927971],"type":"Point"}
}