{
  "type": "Feature",
  "properties": {
    "addr:full":"L Atrium 6 Place Abel Gance Boulogne Billancourt Cedex Aquitaine 92652",
    "addr:housenumber":"6",
    "addr:postcode":"92652",
    "addr:street":"Place Abel Gance",
    "iso:country":"FR",
    "sg:address":"L Atrium 6 Place Abel Gance",
    "sg:city":"Boulogne Billancourt Cedex",
    "sg:classifiers":[
        {
            "category":"Banks & Credit Unions",
            "subcategory":"Financial Services",
            "type":"Services"
        }
    ],
    "sg:phone":"+33 1 46 94 47 11",
    "sg:postcode":"92652",
    "sg:province":"Aquitaine",
    "sg:tags":[
        "banking",
        "finance",
        "insurance"
    ],
    "wof:name":"Caisse Des Depots Developpement Sa",
    "wof:placetype":"venue"
},
  "geometry": {"coordinates":[2.24347,48.83382],"type":"Point"}
}