{
  "type": "Feature",
  "properties": {
    "iso:country":"FR",
    "sg:address":"B.P. 1",
    "sg:city":"Touillon",
    "sg:orig_category":"Non-Classified Establishments",
    "sg:phone":"+33 3 80 89 00 30",
    "sg:postcode":"21500",
    "sg:province":"Bourgogne",
    "wof:name":"Jacquenet Malin S.a.",
    "wof:placetype":"venue"
},
  "geometry": {"coordinates":[4.425196,47.651402],"type":"Point"}
}