{
  "type": "Feature",
  "properties": {
    "addr:full":"4 Rue De La Farandole 84130 Le Pontet Franche Comt\u00e9",
    "addr:housenumber":"4",
    "addr:postcode":"84130",
    "addr:street":"Rue De La Farandole;Franche Comte\u0301",
    "iso:country":"FR",
    "sg:address":"4 Rue De La Farandole 84130 Le Pontet",
    "sg:classifiers":[
        {
            "category":"Health Services",
            "subcategory":"Medical Lab",
            "type":"Services"
        }
    ],
    "sg:phone":"+33 4 90 03 05 05",
    "sg:province":"Franche Comt\u00e9",
    "sg:tags":[
        "chemical",
        "pharmaceutical",
        "pharmacy"
    ],
    "wof:name":"Boiron",
    "wof:placetype":"venue"
},
  "geometry": {"coordinates":[4.869503,43.958599],"type":"Point"}
}