{
  "type": "Feature",
  "properties": {
    "iso:country":"FR",
    "sg:address":"9, Bd des Ravali\u00e8res, 72560 Chang\u00e9",
    "sg:orig_category":"Unclassifiable Establishments",
    "sg:phone":"+33 2 43 40 17 00",
    "sg:province":"Pays de Loire",
    "wof:name":"Codipro S.a.",
    "wof:placetype":"venue"
},
  "geometry": {"coordinates":[0.27179,47.977608],"type":"Point"}
}