{
  "type": "Feature",
  "properties": {
    "iso:country":"FR",
    "sg:address":"234 Rue De La Motte Julien 59500 Douai",
    "sg:classifiers":[
        {
            "category":"Farming",
            "subcategory":"Farm",
            "type":"Manufacturing & Wholesale Goods"
        }
    ],
    "sg:phone":"+33 3 27 88 97 89",
    "sg:postcode":"59500",
    "sg:province":"Nord Pas-de-Calais",
    "sg:tags":[
        "horticulture",
        "agriculture",
        "livestock"
    ],
    "wof:name":"Sa Dehaese",
    "wof:placetype":"venue"
},
  "geometry": {"coordinates":[3.067468,50.386597],"type":"Point"}
}