{
  "type": "Feature",
  "properties": {
    "addr:full":"Pl Des Marronniers 21190 Puligny Montrachet Auxey-Duresses Bourgogne 21190",
    "addr:postcode":"21190;21190",
    "addr:street":"Pl Des Marronniers;Bourgogne",
    "iso:country":"FR",
    "sg:address":"Pl Des Marronniers 21190 Puligny Montrachet",
    "sg:city":"Auxey-Duresses",
    "sg:classifiers":[
        {
            "category":"Travel",
            "subcategory":"Hotels & Motels",
            "type":"Entertainment"
        }
    ],
    "sg:phone":"+33 3 80 21 30 06",
    "sg:postcode":"21190",
    "sg:province":"Bourgogne",
    "sg:tags":[
        "hotels",
        "business",
        "restaurant"
    ],
    "wof:name":"Sarl Usso",
    "wof:placetype":"venue"
},
  "geometry": {"coordinates":[4.753875,46.944946],"type":"Point"}
}