{
  "type": "Feature",
  "properties": {
    "addr:full":"RD Arthez de B\u00e9arn Aquitaine 64370",
    "addr:postcode":"64370",
    "addr:street":"Rd",
    "iso:country":"FR",
    "sg:address":"RD",
    "sg:city":"Arthez de B\u00e9arn",
    "sg:orig_category":"Unclassifiable Establishments",
    "sg:phone":"+33 5 59 67 70 17",
    "sg:postcode":"64370",
    "sg:province":"Aquitaine",
    "wof:name":"Etablissements Lacad\u00e9e S.a.",
    "wof:placetype":"venue"
},
  "geometry": {"coordinates":[-0.519984,43.444916],"type":"Point"}
}