{
  "type": "Feature",
  "properties": {
    "addr:full":"ZAC des Ponts de Baillets - La Croix Verte Baillet en France Ile de France 95560",
    "addr:housenumber":"zac",
    "addr:postcode":"95560",
    "addr:street":"Des Ponts De Baillets La Croix",
    "iso:country":"FR",
    "sg:address":"ZAC des Ponts de Baillets - La Croix Verte",
    "sg:city":"Baillet en France",
    "sg:orig_category":"Non-Classified Establishments",
    "sg:phone":"+33 1 34 69 90 81",
    "sg:postcode":"95560",
    "sg:province":"Ile de France",
    "wof:name":"Soci\u00e9t\u00e9 Des Anciens Etablissementschassin S.a.r.l.",
    "wof:placetype":"venue"
},
  "geometry": {"coordinates":[2.309886,49.070625],"type":"Point"}
}