{
  "type": "Feature",
  "properties": {
    "addr:full":"26 Rue Marcel Dassault 59113 Seclin Nord Pas-de-Calais 59113",
    "addr:housenumber":"26",
    "addr:postcode":"59113;59113",
    "addr:street":"Rue Marcel Dassault",
    "iso:country":"FR",
    "sg:address":"26 Rue Marcel Dassault 59113 Seclin",
    "sg:classifiers":[
        {
            "category":"Food Court",
            "type":"Food & Drink"
        }
    ],
    "sg:phone":"+33 3 20 90 02 12",
    "sg:postcode":"59113",
    "sg:province":"Nord Pas-de-Calais",
    "sg:tags":[
        "product",
        "related"
    ],
    "wof:name":"Maison Fichel Sa",
    "wof:placetype":"venue"
},
  "geometry": {"coordinates":[3.039603,50.571064],"type":"Point"}
}