{
  "type": "Feature",
  "properties": {
    "addr:full":"1ter, Rue Jules Guesdes, 59390 Lys lez Lannoy Nord Pas-de-Calais",
    "addr:housenumber":"1ter",
    "addr:postcode":"59390",
    "addr:street":"Rue Jules Guesdes",
    "iso:country":"FR",
    "sg:address":"1ter, Rue Jules Guesdes, 59390 Lys lez Lannoy",
    "sg:orig_category":"Unclassifiable Establishments",
    "sg:phone":"+33 3 20 99 59 59",
    "sg:province":"Nord Pas-de-Calais",
    "wof:name":"Abb Alstom Power Combustion S.a.",
    "wof:placetype":"venue"
},
  "geometry": {"coordinates":[3.20925,50.66943],"type":"Point"}
}