{
  "type": "Feature",
  "properties": {
    "iso:country":"FR",
    "sg:address":"Le viilage 26300 BARBIERES",
    "sg:classifiers":[
        {
            "category":"Military Area",
            "subcategory":"Restricted Area",
            "type":"Public Place"
        }
    ],
    "sg:phone":"+33 4 75 47 26 26",
    "sg:postcode":"26300",
    "sg:province":"Rhone-Alpes",
    "sg:tags":[
        "canvas",
        "made",
        "police",
        "leather",
        "plastic",
        "equipment",
        "webbing"
    ],
    "wof:name":"Sert Sa",
    "wof:placetype":"venue"
},
  "geometry": {"coordinates":[5.09157,44.938511],"type":"Point"}
}