{
  "type": "Feature",
  "properties": {
    "addr:full":"156 R du Faubourg de Bourgogne 45800 ST JEAN DE BRAYE Combleux Centre 45800",
    "addr:housenumber":"156;combleux",
    "addr:postcode":"45800;45800",
    "addr:street":"R Du Faubourg De Bourgogne",
    "iso:country":"FR",
    "sg:address":"156 R du Faubourg de Bourgogne 45800 ST JEAN DE BRAYE",
    "sg:city":"Combleux",
    "sg:classifiers":[
        {
            "category":"Communications",
            "subcategory":"Television Station",
            "type":"Services"
        }
    ],
    "sg:phone":"+33 2 38 86 29 47",
    "sg:postcode":"45800",
    "sg:province":"Centre",
    "sg:tags":[
        "carillon",
        "bell"
    ],
    "wof:name":"Boll\u00e9e Dominique Sarl",
    "wof:placetype":"venue"
},
  "geometry": {"coordinates":[1.937742,47.903843],"type":"Point"}
}