{
  "type": "Feature",
  "properties": {
    "addr:full":"69 blvd Alexandre Martin; Orl\u00e9ans; 45006 Rhone-Alpes",
    "addr:postcode":"45006",
    "addr:street":"69 Blvd Alexandre Martin",
    "iso:country":"FR",
    "sg:address":"69 blvd Alexandre Martin; Orl\u00e9ans; 45006",
    "sg:classifiers":[
        {
            "category":"Banks & Credit Unions",
            "subcategory":"Bank",
            "type":"Services"
        }
    ],
    "sg:phone":"+33 2 38 65 46 60",
    "sg:province":"Rhone-Alpes",
    "wof:name":"Banque Francaise, De Cr\u00e9dit Cooperatif",
    "wof:placetype":"venue"
},
  "geometry": {"coordinates":[1.907087,47.905708],"type":"Point"}
}