{
  "type": "Feature",
  "properties": {
    "addr:full":"18 Rue Cyprian Parc D'Activit\u00e9s L'Atlantique 69100 Villeurbanne Rhone-Alpes 69100",
    "addr:housenumber":"18",
    "addr:postcode":"69100;69100",
    "addr:street":"Rue Cyprian Parc D'Activite \u0301S L'Atlantique",
    "iso:country":"FR",
    "sg:address":"18 Rue Cyprian Parc D'Activit\u00e9s L'Atlantique 69100 Villeurbanne",
    "sg:classifiers":[
        {
            "category":"Shopping",
            "subcategory":"Computers & Home Electronics",
            "type":"Retail Goods"
        }
    ],
    "sg:phone":"+33 4 72 91 55 55",
    "sg:postcode":"69100",
    "sg:province":"Rhone-Alpes",
    "sg:tags":[
        "equipment",
        "electrical",
        "component",
        "electric",
        "electronic"
    ],
    "wof:name":"Composants Electroniques Lyonnais Sa",
    "wof:placetype":"venue"
},
  "geometry": {"coordinates":[4.901827,45.756828],"type":"Point"}
}