{
  "type": "Feature",
  "properties": {
    "addr:full":"32, Rue Michel Rondet, 42700 Firminy Rhone-Alpes 42700",
    "addr:housenumber":"32",
    "addr:postcode":"42700;42700",
    "addr:street":"Rue Michel Rondet",
    "iso:country":"FR",
    "sg:address":"32, Rue Michel Rondet, 42700 Firminy",
    "sg:orig_category":"Non-Classified Establishments",
    "sg:phone":"+33 4 77 56 83 04",
    "sg:postcode":"42700",
    "sg:province":"Rhone-Alpes",
    "wof:name":"A.c.t.m.s. S.a.r.l. - Atelier De Chaudronnerie Tuyauterie Montage Soudure",
    "wof:placetype":"venue"
},
  "geometry": {"coordinates":[4.296906,45.397873],"type":"Point"}
}