{
  "type": "Feature",
  "properties": {
    "iso:country":"FR",
    "sg:address":"Les Places 85600 St Hilaire De Loulay",
    "sg:classifiers":[
        {
            "category":"Farming",
            "subcategory":"Livestock Farm",
            "type":"Manufacturing & Wholesale Goods"
        }
    ],
    "sg:phone":"+33 2 51 94 04 29",
    "sg:postcode":"85600",
    "sg:province":"Pays de Loire",
    "sg:tags":[
        "breeding",
        "agriculture",
        "animal"
    ],
    "wof:name":"Boye Accouvage",
    "wof:placetype":"venue"
},
  "geometry": {"coordinates":[-1.355199,47.034981],"type":"Point"}
}