{
  "type": "Feature",
  "properties": {
    "iso:country":"FR",
    "sg:address":"113, Rte de Lab\u00e8ge, 31400 Toulouse",
    "sg:orig_category":"Unclassifiable Establishments",
    "sg:phone":"+33 5 61 20 33 99",
    "sg:province":"Midi Pyr\u00e9n\u00e9es",
    "wof:name":"Etablissements Galinier S.a.r.l.",
    "wof:placetype":"venue"
},
  "geometry": {"coordinates":[1.501247,43.563408],"type":"Point"}
}