{
  "type": "Feature",
  "properties": {
    "addr:full":"1243, Rte de Cretet - Les Villards , 74300 Magland Rhone-Alpes",
    "addr:housenumber":"1243",
    "addr:postcode":"74300",
    "addr:street":"Rte De Cretet Les Villards",
    "iso:country":"FR",
    "sg:address":"1243, Rte de Cretet - Les Villards , 74300 Magland",
    "sg:orig_category":"Non-Classified Establishments",
    "sg:phone":"+33 4 50 34 70 38",
    "sg:province":"Rhone-Alpes",
    "wof:name":"J.a. Cartier S.a.r.l.",
    "wof:placetype":"venue"
},
  "geometry": {"coordinates":[6.633185,45.987919],"type":"Point"}
}