{
  "type": "Feature",
  "properties": {
    "iso:country":"FR",
    "sg:address":"Les Cerisi\u00e8res 21200 Beaune",
    "sg:city":"Beaune",
    "sg:orig_category":"Unclassifiable Establishments",
    "sg:phone":"+33 3 80 26 27 77",
    "sg:postcode":"21200",
    "sg:province":"Bourgogne",
    "wof:name":"Beaune Brioche S.a.",
    "wof:placetype":"venue"
},
  "geometry": {"coordinates":[4.861214,47.005554],"type":"Point"}
}