{
  "type": "Feature",
  "properties": {
    "iso:country":"FR",
    "sg:address":"16 Rue De La Gait\u00e9 03100 Montlu\u00e7on",
    "sg:city":"Montlu\u00e7on",
    "sg:classifiers":[
        {
            "category":"Wholesale",
            "subcategory":"Medical Equipment & Supplies",
            "type":"Manufacturing & Wholesale Goods"
        }
    ],
    "sg:phone":"+33 4 70 64 30 07",
    "sg:postcode":"03100",
    "sg:province":"Auvergne",
    "sg:tags":[
        "instrument",
        "health",
        "-",
        "precision"
    ],
    "wof:name":"Ortho Medic",
    "wof:placetype":"venue"
},
  "geometry": {"coordinates":[2.603308,46.343262],"type":"Point"}
}