{
  "type": "Feature",
  "properties": {
    "addr:full":"7 R Du Mar\u00e9chal Foch 65000 Tarbes Midi Pyr\u00e9n\u00e9es 65000",
    "addr:housenumber":"7",
    "addr:postcode":"65000;65000",
    "addr:street":"R Du Mare\u0301Chal Foch",
    "iso:country":"FR",
    "sg:address":"7 R Du Mar\u00e9chal Foch 65000 Tarbes",
    "sg:classifiers":[
        {
            "category":"Manufacturing",
            "subcategory":"Jewelry",
            "type":"Manufacturing & Wholesale Goods"
        }
    ],
    "sg:phone":"+33 5 62 93 07 98",
    "sg:postcode":"65000",
    "sg:province":"Midi Pyr\u00e9n\u00e9es",
    "sg:tags":[
        "product",
        "miscellaneous",
        "jewellery"
    ],
    "wof:name":"Castella Sa",
    "wof:placetype":"venue"
},
  "geometry": {"coordinates":[0.074055,43.232399],"type":"Point"}
}