{
  "type": "Feature",
  "properties": {
    "addr:full":"B.P. 24, 74490 Saint Jeoire^^Av. des Colombi\u00e8res, 74490 Saint Jeoire Rhone-Alpes",
    "addr:postcode":"74490;jeoire^^av;74490",
    "addr:street":"B.P. 24;Colombie\u0300Res;Jeoire Rhone-Alpes",
    "iso:country":"FR",
    "sg:address":"B.P. 24, 74490 Saint Jeoire^^Av. des Colombi\u00e8res, 74490 Saint Jeoire",
    "sg:orig_category":"Non-Classified Establishments",
    "sg:phone":"+33 4 50 35 83 92",
    "sg:province":"Rhone-Alpes",
    "wof:name":"Karl Suss France S.a.r.l",
    "wof:placetype":"venue"
},
  "geometry": {"coordinates":[6.489805,46.120033],"type":"Point"}
}