{
  "type": "Feature",
  "properties": {
    "addr:full":"8, Rue des Bouleaux, 25150 Pont de Roide Franche Comt\u00e9 25150",
    "addr:housenumber":"8",
    "addr:postcode":"25150;25150",
    "addr:street":"Rue Des Bouleaux;Franche Comte\u0301",
    "iso:country":"FR",
    "sg:address":"8, Rue des Bouleaux, 25150 Pont de Roide",
    "sg:orig_category":"Non-Classified Establishments",
    "sg:phone":"+33 3 81 96 41 22",
    "sg:postcode":"25150",
    "sg:province":"Franche Comt\u00e9",
    "wof:name":"Devillers S.a.r.l.",
    "wof:placetype":"venue"
},
  "geometry": {"coordinates":[6.769494,47.392365],"type":"Point"}
}