{
  "type": "Feature",
  "properties": {
    "iso:country":"FR",
    "sg:address":"8, Rue des Bouleaux, 25150 Pont de Roide",
    "sg:orig_category":"Non-Classified Establishments",
    "sg:phone":"+33 3 81 96 41 22",
    "sg:postcode":"25150",
    "sg:province":"Franche Comt\u00e9",
    "wof:name":"Devillers S.a.r.l.",
    "wof:placetype":"venue"
},
  "geometry": {"coordinates":[6.769494,47.392365],"type":"Point"}
}