{
  "type": "Feature",
  "properties": {
    "addr:full":"50, Grande Rue, 78770 Marcq Ile de France 78770",
    "addr:housenumber":"50",
    "addr:postcode":"78770;france 78770",
    "addr:street":"Grande Rue",
    "iso:country":"FR",
    "sg:address":"50, Grande Rue, 78770 Marcq",
    "sg:orig_category":"Non-Classified Establishments",
    "sg:phone":"+33 1 30 88 57 57",
    "sg:postcode":"78770",
    "sg:province":"Ile de France",
    "wof:name":"Dimension 4 S.a.",
    "wof:placetype":"venue"
},
  "geometry": {"coordinates":[1.816728,48.861473],"type":"Point"}
}