{
  "type": "Feature",
  "properties": {
    "addr:full":"8, Rue Champs Odes, 78200 Buchelay Ile de France",
    "addr:housenumber":"8",
    "addr:postcode":"78200",
    "addr:street":"Rue Champs Odes;Ile De France",
    "iso:country":"FR",
    "sg:address":"8, Rue Champs Odes, 78200 Buchelay",
    "sg:orig_category":"Unclassifiable Establishments",
    "sg:phone":"+33 1 34 76 89 88",
    "sg:province":"Ile de France",
    "wof:name":"Arts Graphiques Vall\u00e9e De Seine S.a.r.l.",
    "wof:placetype":"venue"
},
  "geometry": {"coordinates":[1.678818,48.992054],"type":"Point"}
}