{
  "type": "Feature",
  "properties": {
    "addr:full":"44 Quai De Jemmapes 75010 Paris Ile de France 75010",
    "addr:housenumber":"44",
    "addr:postcode":"75010;75010",
    "addr:street":"Quai De Jemmapes",
    "iso:country":"FR",
    "sg:address":"44 Quai De Jemmapes 75010 Paris",
    "sg:classifiers":[
        {
            "category":"Professional",
            "subcategory":"Computer Services",
            "type":"Services"
        }
    ],
    "sg:phone":"+33 1 44 52 51 15",
    "sg:postcode":"75010",
    "sg:province":"Ile de France",
    "sg:tags":[
        "information",
        "technology",
        "software"
    ],
    "wof:name":"Gestafax Sarl",
    "wof:placetype":"venue"
},
  "geometry": {"coordinates":[2.367261,48.869549],"type":"Point"}
}