{
  "type": "Feature",
  "properties": {
    "addr:full":"All\u00e9e Royale - Ferme Ville p\u00eache Lieusaint Ile de France 77127",
    "addr:postcode":"77127",
    "addr:street":"Alle\u0301E Royale",
    "iso:country":"FR",
    "sg:address":"All\u00e9e Royale - Ferme Ville p\u00eache",
    "sg:city":"Lieusaint",
    "sg:orig_category":"Non-Classified Establishments",
    "sg:phone":"+33 1 64 13 33 90",
    "sg:postcode":"77127",
    "sg:province":"Ile de France",
    "wof:name":"Debrie Durual M\u00e9canique De Precision S.a.r.l.",
    "wof:placetype":"venue"
},
  "geometry": {"coordinates":[2.551919,48.63187],"type":"Point"}
}