{
  "type": "Feature",
  "properties": {
    "addr:full":"R Jolin BP 1 58440 La Celle Sur Loire Celle-sur-Loire Bourgogne 58440",
    "addr:housenumber":"1",
    "addr:postcode":"58440;58440",
    "addr:street":"Bourgogne",
    "iso:country":"FR",
    "sg:address":"R Jolin BP 1 58440 La Celle Sur Loire",
    "sg:city":"Celle-sur-Loire",
    "sg:classifiers":[
        {
            "category":"Home & Garden",
            "subcategory":"Furniture",
            "type":"Retail Goods"
        }
    ],
    "sg:phone":"+33 3 86 26 02 15",
    "sg:postcode":"58440",
    "sg:province":"Bourgogne",
    "sg:tags":[
        "household",
        "wood"
    ],
    "wof:name":"Billebault Sarl",
    "wof:placetype":"venue"
},
  "geometry": {"coordinates":[2.92315,47.481785],"type":"Point"}
}