{
  "type": "Feature",
  "properties": {
    "iso:country":"FR",
    "sg:address":"5, Rue de l'Arcelle, 38600 Fontaine",
    "sg:orig_category":"Non-Classified Establishments",
    "sg:phone":"+33 4 76 26 14 15",
    "sg:postcode":"38600",
    "sg:province":"Rhone-Alpes",
    "wof:name":"Bischoff S.a.",
    "wof:placetype":"venue"
},
  "geometry": {"coordinates":[5.681134,45.203438],"type":"Point"}
}