{
  "type": "Feature",
  "properties": {
    "iso:country":"FR",
    "sg:address":"7, Rte de Nesle, 80320 Chaulnes",
    "sg:orig_category":"Non-Classified Establishments",
    "sg:phone":"+33 3 22 83 55 55",
    "sg:province":"Picardie",
    "wof:name":"La Santerroise S.c.a.",
    "wof:placetype":"venue"
},
  "geometry": {"coordinates":[2.810341,49.806381],"type":"Point"}
}