{
  "type": "Feature",
  "properties": {
    "addr:full":"14, Bd du Jeu de Paume, 34000 Montpellier Languedoc-Roussillon",
    "addr:housenumber":"14",
    "addr:postcode":"34000",
    "addr:street":"Bd Du Jeu De Paume",
    "iso:country":"FR",
    "sg:address":"14, Bd du Jeu de Paume, 34000 Montpellier",
    "sg:orig_category":"Unclassifiable Establishments",
    "sg:phone":"+33 4 67 92 86 87",
    "sg:province":"Languedoc-Roussillon",
    "wof:name":"Banco Popular Comercial",
    "wof:placetype":"venue"
},
  "geometry": {"coordinates":[3.873349,43.608047],"type":"Point"}
}