{
  "type": "Feature",
  "properties": {
    "addr:full":"50-52 Rue De Br\u00e9querecque 62206 Boulogne Sur Mer Cedex Centre",
    "addr:housenumber":"50-52",
    "addr:postcode":"62206",
    "addr:street":"Rue De Bre\u0301Querecque",
    "iso:country":"FR",
    "sg:address":"50-52 Rue De Br\u00e9querecque 62206 Boulogne Sur Mer Cedex",
    "sg:classifiers":[
        {
            "category":"Manufacturing",
            "subcategory":"Tools & Machinery",
            "type":"Manufacturing & Wholesale Goods"
        }
    ],
    "sg:phone":"+33 3 21 99 14 13",
    "sg:province":"Centre",
    "sg:tags":[
        "metallurgy",
        "metalworking"
    ],
    "wof:name":"Trolle Sa",
    "wof:placetype":"venue"
},
  "geometry": {"coordinates":[1.615514,50.727444],"type":"Point"}
}