{
  "type": "Feature",
  "properties": {
    "iso:country":"FR",
    "sg:address":"2 All\u00e9e Du Pinson 51100 Reims",
    "sg:classifiers":[
        {
            "category":"Professional",
            "subcategory":"Business Services",
            "type":"Services"
        }
    ],
    "sg:phone":"+33 3 26 85 05 26",
    "sg:postcode":"51100",
    "sg:province":"Champagne",
    "sg:tags":[
        "training",
        "advice"
    ],
    "wof:name":"Centre Formation Apprentis Batiment",
    "wof:placetype":"venue"
},
  "geometry": {"coordinates":[4.057897,49.248894],"type":"Point"}
}