{
  "type": "Feature",
  "properties": {
    "addr:full":"42, Rue Corvisart, 08090 Aiglemont Aiglemont Champagne 08090",
    "addr:housenumber":"42",
    "addr:postcode":"08090;08090",
    "addr:street":"Rue Corvisart;Champagne",
    "iso:country":"FR",
    "sg:address":"42, Rue Corvisart, 08090 Aiglemont",
    "sg:city":"Aiglemont",
    "sg:orig_category":"Unclassifiable Establishments",
    "sg:phone":"+33 3 24 33 23 15",
    "sg:postcode":"08090",
    "sg:province":"Champagne",
    "wof:name":"Champeaux S.a.r.l.",
    "wof:placetype":"venue"
},
  "geometry": {"coordinates":[4.76527,49.779888],"type":"Point"}
}