{
  "type": "Feature",
  "properties": {
    "addr:full":"11 Vignoble 44190 Saint Lumine de Clisson Pays de Loire 44190",
    "addr:housenumber":"11",
    "addr:postcode":"44190;44190",
    "addr:street":"Vignoble;Clisson",
    "iso:country":"FR",
    "sg:address":"11",
    "sg:city":"Vignoble 44190 Saint Lumine de Clisson",
    "sg:classifiers":[
        {
            "category":"Professional",
            "subcategory":"Engineering",
            "type":"Services"
        }
    ],
    "sg:phone":"+33 2 40 54 76 76",
    "sg:postcode":"44190",
    "sg:province":"Pays de Loire",
    "sg:tags":[
        "machine",
        "-",
        "mechanical"
    ],
    "wof:name":"Cablage Sud Loire",
    "wof:placetype":"venue"
},
  "geometry": {"coordinates":[-1.338089,47.082905],"type":"Point"}
}