{
  "type": "Feature",
  "properties": {
    "addr:full":"4 Av De Verdun 06000 Nice Midi Pyr\u00e9n\u00e9es",
    "addr:postcode":"06000",
    "addr:street":"Av De Verdun",
    "iso:country":"FR",
    "sg:address":"4 Av De Verdun 06000 Nice",
    "sg:classifiers":[
        {
            "category":"Manufacturing",
            "subcategory":"Jewelry",
            "type":"Manufacturing & Wholesale Goods"
        }
    ],
    "sg:phone":"+33 4 92 14 48 20",
    "sg:province":"Midi Pyr\u00e9n\u00e9es",
    "sg:tags":[
        "product",
        "jewellery",
        "equipement",
        "miscellaneous",
        "timekeeping",
        "equipment",
        "precision"
    ],
    "wof:name":"Cartier",
    "wof:placetype":"venue"
},
  "geometry": {"coordinates":[7.269375,43.697224],"type":"Point"}
}