{
  "type": "Feature",
  "properties": {
    "iso:country":"FR",
    "sg:address":"Rue Jean Moulin",
    "sg:city":"Dainville",
    "sg:orig_category":"Unclassifiable Establishments",
    "sg:phone":"+33 3 21 51 63 63",
    "sg:postcode":"62000",
    "sg:province":"Nord Pas-de-Calais",
    "wof:name":"Pharma Dom S.a.",
    "wof:placetype":"venue"
},
  "geometry": {"coordinates":[2.721045,50.270676],"type":"Point"}
}