{
  "type": "Feature",
  "properties": {
    "addr:full":"ZA La Rigourdi\u00e8re Cesson S\u00e9vign\u00e9 Brittany 35511",
    "addr:postcode":"35511",
    "addr:street":"Za La Rigourdie\u0300Re;Se\u0301Vigne\u0301",
    "iso:country":"FR",
    "sg:address":"ZA La Rigourdi\u00e8re",
    "sg:city":"Cesson S\u00e9vign\u00e9",
    "sg:orig_category":"Unclassifiable Establishments",
    "sg:phone":"+33 2 99 83 82 28",
    "sg:postcode":"35511",
    "sg:province":"Brittany",
    "wof:name":"Gauvain S.a.",
    "wof:placetype":"venue"
},
  "geometry": {"coordinates":[-1.574789,48.115681],"type":"Point"}
}