{
  "type": "Feature",
  "properties": {
    "addr:full":"61 - 69 rue de Bercy; 75589 Paris Cedex 12 Aquitaine",
    "addr:housenumber":"69",
    "addr:postcode":"75589",
    "addr:street":"Rue De Bercy",
    "iso:country":"FR",
    "sg:address":"61 - 69 rue de Bercy; 75589 Paris Cedex 12",
    "sg:classifiers":[
        {
            "category":"Industrial Area",
            "type":"Public Place"
        }
    ],
    "sg:phone":"+33 1 40 19 50 00",
    "sg:province":"Aquitaine",
    "sg:tags":[
        "large",
        "private"
    ],
    "wof:name":"Elior S.a.",
    "wof:placetype":"venue"
},
  "geometry": {"coordinates":[2.381293,48.838383],"type":"Point"}
}