{
  "type": "Feature",
  "properties": {
    "addr:full":"ZA Guimet Fleurieu sur Sa\u00f4ne Rhone-Alpes 69250",
    "addr:postcode":"69250",
    "addr:street":"Za Guimet Fleurieu",
    "iso:country":"FR",
    "sg:address":"ZA Guimet",
    "sg:city":"Fleurieu sur Sa\u00f4ne",
    "sg:orig_category":"Unclassifiable Establishments",
    "sg:phone":"+33 4 78 91 72 44",
    "sg:postcode":"69250",
    "sg:province":"Rhone-Alpes",
    "wof:name":"D.t.f. S.a.r.l. - D\u00e9lavage Teinture De Fleurieu",
    "wof:placetype":"venue"
},
  "geometry": {"coordinates":[4.84541,45.862637],"type":"Point"}
}