{
  "type": "Feature",
  "properties": {
    "addr:full":"12 rue Notre-Dame 60150 Coudun Picardie 60150",
    "addr:housenumber":"12",
    "addr:postcode":"60150;60150",
    "addr:street":"Rue Notre-Dame;Picardie",
    "iso:country":"FR",
    "sg:address":"12 rue Notre-Dame 60150 Coudun",
    "sg:classifiers":[
        {
            "category":"Manufacturing",
            "subcategory":"Textiles",
            "type":"Manufacturing & Wholesale Goods"
        }
    ],
    "sg:phone":"+33 3 44 90 05 51",
    "sg:postcode":"60150",
    "sg:province":"Picardie",
    "sg:tags":[
        "pads",
        "mattress"
    ],
    "wof:name":"Ste De Marketing Creation Developpement Sarl",
    "wof:placetype":"venue"
},
  "geometry": {"coordinates":[2.81213,49.46262],"type":"Point"}
}