{
  "type": "Feature",
  "properties": {
    "iso:country":"FR",
    "sg:address":"12-14 Rue Thomas Edison 92230 Gennevilliers",
    "sg:orig_category":"Business advice and other services Clothes Environment - machinery and equipment Fabrics Mechanical ",
    "sg:phone":"+33 1 47 99 39 73",
    "sg:postcode":"92230",
    "sg:province":"Ile de France",
    "wof:name":"Ubogi Freres Sa",
    "wof:placetype":"venue"
},
  "geometry": {"coordinates":[2.311669,48.930107],"type":"Point"}
}