{
  "type": "Feature",
  "properties": {
    "iso:country":"FR",
    "sg:address":"Rue Pablo N\u00e9ruda - ZAC du Haut Mad\u00e8re",
    "sg:city":"Villenave d'Ornon C\u00e9dex",
    "sg:orig_category":"Non-Classified Establishments",
    "sg:phone":"+33 5 57 35 83 10",
    "sg:postcode":"33881",
    "sg:province":"Alsace",
    "wof:name":"Exp\u00e9rian",
    "wof:placetype":"venue"
},
  "geometry": {"coordinates":[-0.582347,44.787178],"type":"Point"}
}