{
  "type": "Feature",
  "properties": {
    "addr:full":"Le Sauze 38350 Sousville Rhone-Alpes",
    "addr:postcode":"38350",
    "addr:street":"Le Sauze",
    "iso:country":"FR",
    "sg:address":"Le Sauze 38350 Sousville",
    "sg:orig_category":"Unclassifiable Establishments",
    "sg:phone":"+33 4 76 81 18 83",
    "sg:province":"Rhone-Alpes",
    "wof:name":"Atelier Chaudronnerie De La Mure S.a.r.l.",
    "wof:placetype":"venue"
},
  "geometry": {"coordinates":[5.79945,44.9137],"type":"Point"}
}