{
  "type": "Feature",
  "properties": {
    "addr:full":"8 Rue Du Cloteau Zi La Romanerie Nord 49124 St Barthelemy Anjou Cedex Pays de Loire 49124",
    "addr:housenumber":"8",
    "addr:postcode":"49124;anjou cedex pays;49124",
    "addr:street":"Rue Du Cloteau Zi La Romanerie Nord",
    "iso:country":"FR",
    "sg:address":"8 Rue Du Cloteau Zi La Romanerie Nord 49124 St Barthelemy Anjou Cedex",
    "sg:classifiers":[
        {
            "category":"Wholesale",
            "subcategory":"Machinery & Supplies",
            "type":"Manufacturing & Wholesale Goods"
        }
    ],
    "sg:phone":"+33 2 41 27 35 50",
    "sg:postcode":"49124",
    "sg:province":"Pays de Loire",
    "sg:tags":[
        "food",
        "processing",
        "-",
        "machine",
        "equipment",
        "engineering",
        "mechanical"
    ],
    "wof:name":"Etablissements Schneider Jaquet Et Cie",
    "wof:placetype":"venue"
},
  "geometry": {"coordinates":[-0.494339,47.468246],"type":"Point"}
}