{
  "type": "Feature",
  "properties": {
    "addr:full":"41 Rue Paul Claudel 91000 Evry Ile de France",
    "addr:housenumber":"41",
    "addr:postcode":"91000",
    "addr:street":"Rue Paul Claudel",
    "iso:country":"FR",
    "sg:address":"41 Rue Paul Claudel 91000 Evry",
    "sg:classifiers":[
        {
            "category":"Professional",
            "subcategory":"Printing & Photocopies",
            "type":"Services"
        }
    ],
    "sg:phone":"+33 1 69 36 99 90",
    "sg:province":"Ile de France",
    "sg:tags":[
        "publishing"
    ],
    "wof:name":"Editions Fly International (efi)",
    "wof:placetype":"venue"
},
  "geometry": {"coordinates":[2.42739,48.638641],"type":"Point"}
}