{
  "type": "Feature",
  "properties": {
    "iso:country":"FR",
    "sg:address":"23",
    "sg:city":"Bossuet -- Z.I. de la Vigne aux Loups; Longjumeau; 91160",
    "sg:classifiers":[
        {
            "category":"Industrial Area",
            "type":"Public Place"
        }
    ],
    "sg:phone":"+33 1 69 09 77 85",
    "sg:province":"Ile de France",
    "sg:tags":[
        "large",
        "private"
    ],
    "wof:name":"Produits Chimiques Auxiliaires Et De Synth\u00e8se",
    "wof:placetype":"venue"
},
  "geometry": {"coordinates":[2.301612,48.704369],"type":"Point"}
}