{
  "type": "Feature",
  "properties": {
    "iso:country":"FR",
    "sg:address":"B.P. 79, 93104 Montreuil C\u00e9dex^^45bis, Rue du Sergent Bobillot, 93100 Montreuil",
    "sg:orig_category":"Non-Classified Establishments",
    "sg:phone":"+33 1 48 58 14 31",
    "sg:province":"Ile de France",
    "wof:name":"H\u00e9liosam S.a.",
    "wof:placetype":"venue"
},
  "geometry": {"coordinates":[2.442661,48.864525],"type":"Point"}
}