{
  "type": "Feature",
  "properties": {
    "iso:country":"FR",
    "sg:address":"ZA Bastillac 65000 Tarbes",
    "sg:orig_category":"Adhesives, Thermoplastic",
    "sg:phone":"+33 5 62 51 78 89",
    "sg:postcode":"65000",
    "sg:province":"Midi Pyr\u00e9n\u00e9es",
    "wof:name":"Adhetec S.a.",
    "wof:placetype":"venue"
},
  "geometry": {"coordinates":[0.073125,43.230011],"type":"Point"}
}