{
  "type": "Feature",
  "properties": {
    "iso:country":"FR",
    "sg:address":"Za Champ Au Roi 70000 Noidans L\u00e8s Vesoul",
    "sg:classifiers":[
        {
            "category":"Professional",
            "type":"Services"
        }
    ],
    "sg:phone":"+33 3 84 76 01 00",
    "sg:province":"Franche Comt\u00e9",
    "sg:tags":[
        "transport",
        "road"
    ],
    "wof:name":"Rigoulot (transports) Sarl",
    "wof:placetype":"venue"
},
  "geometry": {"coordinates":[6.124331,47.613808],"type":"Point"}
}