{
  "type": "Feature",
  "properties": {
    "iso:country":"FR",
    "sg:address":"71, Rue de Billancourt, 92100 Boulogne Billancourt",
    "sg:orig_category":"Unclassifiable Establishments",
    "sg:phone":"+33 1 55 38 90 90",
    "sg:province":"Ile de France",
    "wof:name":"Ludimus S.a.r.l.",
    "wof:placetype":"venue"
},
  "geometry": {"coordinates":[2.236286,48.83894],"type":"Point"}
}