{
  "type": "Feature",
  "properties": {
    "iso:country":"FR",
    "sg:address":"ZI 2 de Rouvignies - Batterie 100",
    "sg:city":"Valenciennes C\u00e9dex",
    "sg:orig_category":"Unclassifiable Establishments",
    "sg:phone":"+33 3 27 21 14 15",
    "sg:postcode":"59309",
    "sg:province":"Nord-Pas-de-Calais",
    "wof:name":"Dekerpel Hainaut S.a.",
    "wof:placetype":"venue"
},
  "geometry": {"coordinates":[3.524105,50.358494],"type":"Point"}
}