{
  "type": "Feature",
  "properties": {
    "addr:full":"18, Rte de Paris, 72470 Champagn\u00e9 Pays de Loire",
    "addr:housenumber":"18",
    "addr:postcode":"72470",
    "addr:street":"Rte De Paris",
    "iso:country":"FR",
    "sg:address":"18, Rte de Paris, 72470 Champagn\u00e9",
    "sg:orig_category":"Unclassifiable Establishments",
    "sg:phone":"+33 2 43 54 54 54",
    "sg:province":"Pays de Loire",
    "wof:name":"Vals S.a. - Veau Allaitement Schils",
    "wof:placetype":"venue"
},
  "geometry": {"coordinates":[0.39876,48.017715],"type":"Point"}
}