{
  "type": "Feature",
  "properties": {
    "iso:country":"FR",
    "sg:address":"7 Rue Du Sapeur Michel Jouan 35005 Rennes",
    "sg:classifiers":[
        {
            "category":"Utilities",
            "subcategory":"Telephone",
            "type":"Services"
        }
    ],
    "sg:phone":"+33 2 99 30 23 25",
    "sg:province":"Brittany",
    "sg:tags":[
        "telecommunication"
    ],
    "wof:name":"Compagnie Telephonique De L'ouest Sarl",
    "wof:placetype":"venue"
},
  "geometry": {"coordinates":[-1.684477,48.107521],"type":"Point"}
}