{
  "type": "Feature",
  "properties": {
    "addr:full":"23, Rue B\u00e9nard, 75014 Paris Ile de France",
    "addr:housenumber":"23",
    "addr:postcode":"75014",
    "addr:street":"Rue Be\u0301Nard",
    "iso:country":"FR",
    "sg:address":"23, Rue B\u00e9nard, 75014 Paris",
    "sg:orig_category":"Unclassifiable Establishments",
    "sg:phone":"+33 1 45 39 14 00",
    "sg:province":"Ile de France",
    "wof:name":"F.b.i. S.a.r.l. - Fourniture Bureau Informatique",
    "wof:placetype":"venue"
},
  "geometry": {"coordinates":[2.322523,48.831402],"type":"Point"}
}