{
  "type": "Feature",
  "properties": {
    "iso:country":"FR",
    "sg:address":"129 Rue De La Loire 16000 Angoul\u00eame",
    "sg:classifiers":[
        {
            "category":"Shopping",
            "subcategory":"Clothing, Apparel, & Fashions",
            "type":"Retail Goods"
        }
    ],
    "sg:phone":"+33 5 45 90 02 02",
    "sg:postcode":"16000",
    "sg:province":"Poitou-Charentes",
    "sg:tags":[
        "textile",
        "clothing",
        "clothes"
    ],
    "wof:name":"Moving Sarl",
    "wof:placetype":"venue"
},
  "geometry": {"coordinates":[0.165142,45.643002],"type":"Point"}
}