{
  "type": "Feature",
  "properties": {
    "iso:country":"FR",
    "sg:address":"18, Rue Jules Vercruysse, 95100 Argenteuil",
    "sg:orig_category":"Unclassifiable Establishments",
    "sg:phone":"+33 1 34 10 57 17",
    "sg:province":"Ile de France",
    "wof:name":"Pivicat S.a.",
    "wof:placetype":"venue"
},
  "geometry": {"coordinates":[2.210685,48.954681],"type":"Point"}
}