{
  "type": "Feature",
  "properties": {
    "iso:country":"FR",
    "sg:address":"34 avenue Pablo Picasso 69120 Vaulx en Velin",
    "sg:classifiers":[
        {
            "category":"Manufacturing",
            "subcategory":"Printing",
            "type":"Manufacturing & Wholesale Goods"
        }
    ],
    "sg:phone":"+33 4 72 04 48 12",
    "sg:postcode":"69120",
    "sg:province":"Rhone-Alpes",
    "sg:tags":[
        "adhesive",
        "screen",
        "silk"
    ],
    "wof:name":"St\u00e9 Cotonni\u00e8re Lyonnaise Sa",
    "wof:placetype":"venue"
},
  "geometry": {"coordinates":[4.919136,45.774719],"type":"Point"}
}