{
  "type": "Feature",
  "properties": {
    "iso:country":"FR",
    "sg:address":"ZI du Patis",
    "sg:city":"Saint Barth\u00e9l\u00e9my d'Anjou",
    "sg:orig_category":"Unclassifiable Establishments",
    "sg:phone":"+33 2 41 43 84 12",
    "sg:postcode":"49124",
    "sg:province":"Pays de Loire",
    "wof:name":"Rochais Bonnet",
    "wof:placetype":"venue"
},
  "geometry": {"coordinates":[-1.334822,47.273693],"type":"Point"}
}