{
  "type": "Feature",
  "properties": {
    "addr:full":"1, Rue de la Butte Rouge - ZI du Parc, 95480 Pierrelaye Ile de France",
    "addr:housenumber":"1",
    "addr:postcode":"95480;ile",
    "addr:street":"Rue De La Butte Rouge Zi Du Parc",
    "iso:country":"FR",
    "sg:address":"1, Rue de la Butte Rouge - ZI du Parc, 95480 Pierrelaye",
    "sg:orig_category":"Unclassifiable Establishments",
    "sg:phone":"+33 1 30 40 79 80",
    "sg:province":"Ile de France",
    "wof:name":"A.t.e. S.a. - Automatismes Techniques Electriques",
    "wof:placetype":"venue"
},
  "geometry": {"coordinates":[2.156565,49.022736],"type":"Point"}
}