{
  "type": "Feature",
  "properties": {
    "iso:country":"FR",
    "sg:address":"75838 Paris C\u00e9dex 17^^9, Rue Labie, 75017 Paris",
    "sg:orig_category":"Non-Classified Establishments",
    "sg:phone":"+33 1 45 74 21 62",
    "sg:province":"Ile de France",
    "wof:name":"F.l. R\u00e9gie S.a.",
    "wof:placetype":"venue"
},
  "geometry": {"coordinates":[2.318885,48.883629],"type":"Point"}
}