{
  "type": "Feature",
  "properties": {
    "addr:full":"27, Rue du Pr\u00e9 Naud - Zone Artisanale, 63510 Malintrat Malintrat Auvergne 63510",
    "addr:housenumber":"27",
    "addr:postcode":"63510;malintrat;63510",
    "addr:street":"Rue Du Pre\u0301 Naud Zone Artisanale",
    "iso:country":"FR",
    "sg:address":"27, Rue du Pr\u00e9 Naud - Zone Artisanale, 63510 Malintrat",
    "sg:city":"Malintrat",
    "sg:orig_category":"Non-Classified Establishments",
    "sg:phone":"+33 4 73 61 02 80",
    "sg:postcode":"63510",
    "sg:province":"Auvergne",
    "wof:name":"Tichit S.a.",
    "wof:placetype":"venue"
},
  "geometry": {"coordinates":[3.186092,45.814594],"type":"Point"}
}