{
  "type": "Feature",
  "properties": {
    "addr:full":"ZI des Gaudi\u00e8res Mettray Centre 37390",
    "addr:postcode":"37390",
    "addr:street":"Des Gaudie\u0300Res",
    "iso:country":"FR",
    "sg:address":"ZI des Gaudi\u00e8res",
    "sg:city":"Mettray",
    "sg:orig_category":"Unclassifiable Establishments",
    "sg:phone":"+33 2 47 51 84 05",
    "sg:postcode":"37390",
    "sg:province":"Centre",
    "wof:name":"C.m.a. Bigmat S.a. - Soci\u00e9t\u00e9 Des Chaux Et Mat\u00e9riaux D'amboise",
    "wof:placetype":"venue"
},
  "geometry": {"coordinates":[0.649573,47.453693],"type":"Point"}
}