{
  "type": "Feature",
  "properties": {
    "addr:full":"Zi Bonne Nouvelle Rte De Savenay 44480 Donges Pays de Loire 44480",
    "addr:postcode":"44480;44480",
    "addr:street":"Zi Bonne Nouvelle Rte De Savenay",
    "iso:country":"FR",
    "sg:address":"Zi Bonne Nouvelle Rte De Savenay 44480 Donges",
    "sg:classifiers":[
        {
            "category":"Wholesale",
            "subcategory":"Chemicals & Plastics",
            "type":"Manufacturing & Wholesale Goods"
        }
    ],
    "sg:phone":"+33 2 40 45 34 10",
    "sg:postcode":"44480",
    "sg:province":"Pays de Loire",
    "sg:tags":[
        "pharmaceutical",
        "energy"
    ],
    "wof:name":"Antargaz",
    "wof:placetype":"venue"
},
  "geometry": {"coordinates":[-2.074624,47.319061],"type":"Point"}
}