{
  "type": "Feature",
  "properties": {
    "addr:full":"16, Place du g\u00e9n\u00e9ral de Gaulle, 93100 Montreuil Ile de France",
    "addr:housenumber":"16",
    "addr:postcode":"93100",
    "addr:street":"Place Du Ge\u0301Ne\u0301Ral De Gaulle",
    "iso:country":"FR",
    "sg:address":"16, Place du g\u00e9n\u00e9ral de Gaulle, 93100 Montreuil",
    "sg:orig_category":"Non-Classified Establishments",
    "sg:phone":"+33 1 48 70 23 24",
    "sg:province":"Ile de France",
    "wof:name":"Vilpa S.a.r.l.",
    "wof:placetype":"venue"
},
  "geometry": {"coordinates":[2.434107,48.868214],"type":"Point"}
}