{
  "type": "Feature",
  "properties": {
    "addr:full":"RN 7 - ZI P\u00e9rigord Nord Le Pontet Rhone-Alpes 84130",
    "addr:postcode":"84130",
    "addr:street":"Rn 7 Zi Pe\u0301Rigord Nord;Rhone-Alpes",
    "iso:country":"FR",
    "sg:address":"RN 7 - ZI P\u00e9rigord Nord",
    "sg:city":"Le Pontet",
    "sg:orig_category":"Unclassifiable Establishments",
    "sg:phone":"+33 4 90 31 37 53",
    "sg:postcode":"84130",
    "sg:province":"Rhone-Alpes",
    "wof:name":"S.a.f.i. S.a. - Soci\u00e9t\u00e9 D'assistance De Fournitures Industrielles",
    "wof:placetype":"venue"
},
  "geometry": {"coordinates":[4.859935,43.96188],"type":"Point"}
}