{
  "type": "Feature",
  "properties": {
    "addr:full":"B.P. 142, 31774 Colomiers C\u00e9dex^^9, Chemin de Garrabot - Z.I. d'En Jacca, 31770 Colomiers Midi Pyr\u00e9n\u00e9es 31770",
    "addr:housenumber":"b.p. 142",
    "addr:postcode":"31774;31770;31770",
    "addr:street":"Chemin De Garrabot Z.I. D'En Jacca",
    "iso:country":"FR",
    "sg:address":"B.P. 142, 31774 Colomiers C\u00e9dex^^9, Chemin de Garrabot - Z.I. d'En Jacca, 31770 Colomiers",
    "sg:orig_category":"Non-Classified Establishments",
    "sg:phone":"+33 5 61 78 40 66",
    "sg:postcode":"31770",
    "sg:province":"Midi Pyr\u00e9n\u00e9es",
    "wof:name":"Cogifer T.f. S.a. - Travaux Ferroviaires",
    "wof:placetype":"venue"
},
  "geometry": {"coordinates":[1.304249,43.598186],"type":"Point"}
}