{
  "type": "Feature",
  "properties": {
    "addr:full":"13 Route De Paris 44300 Nantes Pays de Loire 44300",
    "addr:housenumber":"13",
    "addr:postcode":"44300;44300",
    "addr:street":"Route De Paris",
    "iso:country":"FR",
    "sg:address":"13 Route De Paris 44300 Nantes",
    "sg:classifiers":[
        {
            "category":"Autos & Motor Vehicles",
            "subcategory":"Automobile Sales",
            "type":"Retail Goods"
        }
    ],
    "sg:phone":"+33 2 51 13 29 30",
    "sg:postcode":"44300",
    "sg:province":"Pays de Loire",
    "sg:tags":[
        "equipment",
        "motor-cars",
        "transport"
    ],
    "wof:name":"Mustiere Automobiles Ford Paridis",
    "wof:placetype":"venue"
},
  "geometry": {"coordinates":[-1.519005,47.250759],"type":"Point"}
}