{
  "type": "Feature",
  "properties": {
    "addr:full":"Rte de Bandol Saint Cyr sur Mer Provence-Alpes-C\u00f4te d'Azur 83270",
    "addr:postcode":"83270",
    "addr:street":"Rte De Bandol Saint Cyr Sur Mer",
    "iso:country":"FR",
    "sg:address":"Rte de Bandol",
    "sg:city":"Saint Cyr sur Mer",
    "sg:orig_category":"Unclassifiable Establishments",
    "sg:phone":"+33 4 94 29 39 39",
    "sg:postcode":"83270",
    "sg:province":"Provence-Alpes-C\u00f4te d'Azur",
    "wof:name":"Dolce Fr\u00e9gate S.n.c.",
    "wof:placetype":"venue"
},
  "geometry": {"coordinates":[5.71089,43.180401],"type":"Point"}
}