{
  "type": "Feature",
  "properties": {
    "iso:country":"FR",
    "sg:address":"1, Rue Jules Vedrines - ZI de Montaudran, 31400 Toulouse",
    "sg:orig_category":"Unclassifiable Establishments",
    "sg:phone":"+33 5 62 71 80 80",
    "sg:province":"Midi Pyr\u00e9n\u00e9es",
    "wof:name":"Rso-tas S.a. - Routier Du Sud Ouest-transport Andr\u00e9i Serge",
    "wof:placetype":"venue"
},
  "geometry": {"coordinates":[1.4579,43.57795],"type":"Point"}
}