{
  "type": "Feature",
  "properties": {
    "iso:country":"FR",
    "sg:address":"Rue Augustin Lhermitte - ZI de Seclin",
    "sg:city":"Wattignies",
    "sg:orig_category":"Unclassifiable Establishments",
    "sg:phone":"+33 3 20 62 04 40",
    "sg:postcode":"59139",
    "sg:province":"Nord Pas-de-Calais",
    "wof:name":"Bergerat Monnoyeur Travaux Publics S.a.",
    "wof:placetype":"venue"
},
  "geometry": {"coordinates":[3.051425,50.58807],"type":"Point"}
}