{
  "type": "Feature",
  "properties": {
    "addr:full":"669, Chemin des Surveillants, 34400 Lunel Languedoc-Roussillon",
    "addr:housenumber":"669",
    "addr:postcode":"34400",
    "addr:street":"Chemin Des Surveillants",
    "iso:country":"FR",
    "sg:address":"669, Chemin des Surveillants, 34400 Lunel",
    "sg:orig_category":"Unclassifiable Establishments",
    "sg:phone":"+33 4 67 71 13 41",
    "sg:province":"Languedoc-Roussillon",
    "wof:name":"Indeldis S.a. - Inter Delta Distribution",
    "wof:placetype":"venue"
},
  "geometry": {"coordinates":[4.150482,43.678799],"type":"Point"}
}