{
  "type": "Feature",
  "properties": {
    "addr:full":"23 bis, Rue Colbert - Point de vente, 56300 Pontivy Pontivy Bretagne 56300",
    "addr:housenumber":"23 bis",
    "addr:postcode":"56300;56300",
    "addr:street":"Rue Colbert;Vente;Pontivy",
    "iso:country":"FR",
    "sg:address":"23 bis, Rue Colbert - Point de vente, 56300 Pontivy",
    "sg:city":"Pontivy",
    "sg:orig_category":"Unclassifiable Establishments",
    "sg:phone":"+33 2 97 25 21 64",
    "sg:postcode":"56300",
    "sg:province":"Bretagne",
    "wof:name":"Revimex S.a.",
    "wof:placetype":"venue"
},
  "geometry": {"coordinates":[-2.951319,48.018394],"type":"Point"}
}