{
  "type": "Feature",
  "properties": {
    "iso:country":"FR",
    "sg:address":"23 bis, Rue Colbert - Point de vente, 56300 Pontivy",
    "sg:city":"Pontivy",
    "sg:orig_category":"Unclassifiable Establishments",
    "sg:phone":"+33 2 97 25 21 64",
    "sg:postcode":"56300",
    "sg:province":"Bretagne",
    "wof:name":"Revimex S.a.",
    "wof:placetype":"venue"
},
  "geometry": {"coordinates":[-2.951319,48.018394],"type":"Point"}
}