{
  "type": "Feature",
  "properties": {
    "addr:full":"Quartier Bauquier 83600 Les Adrets De L'Est\u00e9rel Les Adrets Rhone-Alpes 38190",
    "addr:postcode":"83600;38190",
    "addr:street":"Rhone-Alpes",
    "iso:country":"FR",
    "sg:address":"Quartier Bauquier 83600 Les Adrets De L'Est\u00e9rel",
    "sg:city":"Les Adrets",
    "sg:classifiers":[
        {
            "category":"Home & Garden",
            "subcategory":"Furniture",
            "type":"Retail Goods"
        }
    ],
    "sg:phone":"+33 4 94 40 92 44",
    "sg:postcode":"38190",
    "sg:province":"Rhone-Alpes",
    "sg:tags":[
        "household",
        "wood"
    ],
    "wof:name":"Sarl Barrois",
    "wof:placetype":"venue"
},
  "geometry": {"coordinates":[6.81423,43.525761],"type":"Point"}
}