{
  "type": "Feature",
  "properties": {
    "addr:full":"impasse Roger Vicari 13190 Allauch Midi Pyr\u00e9n\u00e9es",
    "addr:postcode":"13190",
    "addr:street":"Impasse Roger Vicari",
    "iso:country":"FR",
    "sg:address":"impasse Roger Vicari 13190 Allauch",
    "sg:classifiers":[
        {
            "category":"Manufacturing",
            "subcategory":"Tools & Machinery",
            "type":"Manufacturing & Wholesale Goods"
        }
    ],
    "sg:phone":"+33 4 91 87 35 17",
    "sg:province":"Midi Pyr\u00e9n\u00e9es",
    "sg:tags":[
        "machine"
    ],
    "wof:name":"Technidif Sarl",
    "wof:placetype":"venue"
},
  "geometry": {"coordinates":[5.482075,43.336685],"type":"Point"}
}