{
  "type": "Feature",
  "properties": {
    "iso:country":"FR",
    "sg:address":"4/6, Rue Charrin, 69100 Villeurbanne",
    "sg:orig_category":"Unclassifiable Establishments",
    "sg:phone":"+33 4 78 54 56 57",
    "sg:province":"Rhone-Alpes",
    "wof:name":"Corelec S.a.",
    "wof:placetype":"venue"
},
  "geometry": {"coordinates":[4.887528,45.756027],"type":"Point"}
}