{
  "type": "Feature",
  "properties": {
    "addr:full":"9, Rue du Pr\u00e9, 25510 Pierrefontaine les Varans Franche Comt\u00e9 25510",
    "addr:housenumber":"9",
    "addr:postcode":"25510;25510",
    "addr:street":"Rue Du Pre\u0301;Franche Comte\u0301",
    "iso:country":"FR",
    "sg:address":"9, Rue du Pr\u00e9, 25510 Pierrefontaine les Varans",
    "sg:orig_category":"Non-Classified Establishments",
    "sg:phone":"+33 3 81 56 11 43",
    "sg:postcode":"25510",
    "sg:province":"Franche Comt\u00e9",
    "wof:name":"Dubois Scierie S.a.r.l.",
    "wof:placetype":"venue"
},
  "geometry": {"coordinates":[6.535559,47.210995],"type":"Point"}
}