{
  "type": "Feature",
  "properties": {
    "addr:full":"30, Rue des Sangliers, 68170 Rixheim Rixheim Alsace 68170",
    "addr:housenumber":"30",
    "addr:postcode":"68170;68170",
    "addr:street":"Rue Des Sangliers;Rixheim",
    "iso:country":"FR",
    "sg:address":"30, Rue des Sangliers, 68170 Rixheim",
    "sg:city":"Rixheim",
    "sg:orig_category":"Unclassifiable Establishments",
    "sg:phone":"+33 3 89 44 86 05",
    "sg:postcode":"68170",
    "sg:province":"Alsace",
    "wof:name":"Coquillon G\u00e9rard",
    "wof:placetype":"venue"
},
  "geometry": {"coordinates":[7.41334,47.755741],"type":"Point"}
}