{
  "type": "Feature",
  "properties": {
    "addr:full":"246 Route De Vercors 38690 Le Grand Lemps Rhone-Alpes 38690",
    "addr:housenumber":"246",
    "addr:postcode":"38690;38690",
    "addr:street":"Route De Vercors",
    "iso:country":"FR",
    "sg:address":"246 Route De Vercors 38690 Le Grand Lemps",
    "sg:classifiers":[
        {
            "category":"Shopping",
            "subcategory":"Crafts & Fabrics",
            "type":"Retail Goods"
        }
    ],
    "sg:phone":"+33 4 76 55 52 62",
    "sg:postcode":"38690",
    "sg:province":"Rhone-Alpes",
    "sg:tags":[
        "textile",
        "clothing"
    ],
    "wof:name":"Louis Vidon Sa",
    "wof:placetype":"venue"
},
  "geometry": {"coordinates":[5.419945,45.392208],"type":"Point"}
}