{
  "type": "Feature",
  "properties": {
    "addr:full":"21 rue de Neuilly 92000 Nanterre Ile de France",
    "addr:housenumber":"21",
    "addr:postcode":"92000",
    "addr:street":"Rue De Neuilly",
    "iso:country":"FR",
    "sg:address":"21 rue de Neuilly 92000 Nanterre",
    "sg:classifiers":[
        {
            "category":"Health Services",
            "subcategory":"Medical Lab",
            "type":"Services"
        }
    ],
    "sg:phone":"+33 1 47 29 44 35",
    "sg:province":"Ile de France",
    "sg:tags":[
        "pharmaceutical",
        "agent"
    ],
    "wof:name":"Ucb Pharma Sa",
    "wof:placetype":"venue"
},
  "geometry": {"coordinates":[2.209162,48.886898],"type":"Point"}
}