{
  "type": "Feature",
  "properties": {
    "iso:country":"FR",
    "sg:address":"26 Fbg De Besan\u00e7on 25200 Montb\u00e9liard",
    "sg:classifiers":[
        {
            "category":"Professional",
            "subcategory":"Business Services",
            "type":"Services"
        }
    ],
    "sg:phone":"+33 3 81 99 88 00",
    "sg:postcode":"25200",
    "sg:province":"Franche Comt\u00e9",
    "sg:tags":[
        "travel",
        "fair"
    ],
    "wof:name":"Centre De Conferences Montbeliard St Georges",
    "wof:placetype":"venue"
},
  "geometry": {"coordinates":[6.790973,47.509174],"type":"Point"}
}