{
  "type": "Feature",
  "properties": {
    "addr:full":"Moulin De Hauret 40700 Ste Colombe Argelos Aquitaine 40700",
    "addr:postcode":"40700;40700",
    "addr:street":"Moulin;Colombe",
    "iso:country":"FR",
    "sg:address":"Moulin De Hauret 40700 Ste Colombe",
    "sg:city":"Argelos",
    "sg:classifiers":[
        {
            "category":"Shopping",
            "subcategory":"Computers & Home Electronics",
            "type":"Retail Goods"
        }
    ],
    "sg:phone":"+33 5 58 79 48 75",
    "sg:postcode":"40700",
    "sg:province":"Aquitaine",
    "sg:tags":[
        "electronic",
        "electrical",
        "equipment"
    ],
    "wof:name":"Etablissements Guignard",
    "wof:placetype":"venue"
},
  "geometry": {"coordinates":[-0.624728,43.552284],"type":"Point"}
}