{
  "type": "Feature",
  "properties": {
    "iso:country":"FR",
    "sg:address":"Rue Ayguelongue Zi De Berlanne 64160 Morlaas",
    "sg:city":"Morla\u00e0s",
    "sg:classifiers":[
        {
            "category":"Professional",
            "type":"Services"
        }
    ],
    "sg:phone":"+33 5 59 02 72 53",
    "sg:postcode":"64160",
    "sg:province":"Aquitaine",
    "sg:tags":[
        "transport",
        "road"
    ],
    "wof:name":"Destandau Sarl",
    "wof:placetype":"venue"
},
  "geometry": {"coordinates":[-0.187904,43.318733],"type":"Point"}
}