{
  "type": "Feature",
  "properties": {
    "addr:full":"18, Quai du Val, 35400 Saint Malo Saint-Malo Bretagne 35400",
    "addr:housenumber":"18",
    "addr:postcode":"35400;35400",
    "addr:street":"Quai Du Val;Saint-Malo",
    "iso:country":"FR",
    "sg:address":"18, Quai du Val, 35400 Saint Malo",
    "sg:city":"Saint-Malo",
    "sg:orig_category":"Unclassifiable Establishments",
    "sg:phone":"+33 2 99 81 60 06",
    "sg:postcode":"35400",
    "sg:province":"Bretagne",
    "wof:name":"Renault Mar\u00e9e S.a.",
    "wof:placetype":"venue"
},
  "geometry": {"coordinates":[-2.012854,48.6395],"type":"Point"}
}