{
  "type": "Feature",
  "properties": {
    "addr:full":"7, Rue Robert Shuman, 33174 Gradignan C\u00e9dex Auvergne",
    "addr:housenumber":"7",
    "addr:postcode":"33174;ce\u0301dex",
    "addr:street":"Rue Robert Shuman",
    "iso:country":"FR",
    "sg:address":"7, Rue Robert Shuman, 33174 Gradignan C\u00e9dex",
    "sg:orig_category":"Non-Classified Establishments",
    "sg:phone":"+33 5 56 89 20 50",
    "sg:province":"Auvergne",
    "wof:name":"Grim S.a.",
    "wof:placetype":"venue"
},
  "geometry": {"coordinates":[-0.614138,44.773132],"type":"Point"}
}