{
  "type": "Feature",
  "properties": {
    "addr:full":"R Vx Cheminement De Gravelines 59279 Loon Plage Nord Pas-de-Calais 59279",
    "addr:postcode":"59279;59279",
    "addr:street":"Cheminement;Gravelines;Pas-De-Calais",
    "iso:country":"FR",
    "sg:address":"R Vx Cheminement De Gravelines 59279 Loon Plage",
    "sg:classifiers":[
        {
            "category":"Manufacturing",
            "subcategory":"Metals",
            "type":"Manufacturing & Wholesale Goods"
        }
    ],
    "sg:phone":"+33 3 28 27 32 60",
    "sg:postcode":"59279",
    "sg:province":"Nord Pas-de-Calais",
    "sg:tags":[
        "-",
        "machine",
        "equipment",
        "engineering",
        "machinery",
        "mechanical"
    ],
    "wof:name":"Ste Loonoise De Travaux Metalliques",
    "wof:placetype":"venue"
},
  "geometry": {"coordinates":[2.21125,50.99456],"type":"Point"}
}