{
  "type": "Feature",
  "properties": {
    "iso:country":"FR",
    "sg:address":"10 Rue Bois De L'Ile 73460 Frontenex",
    "sg:classifiers":[
        {
            "category":"Professional",
            "subcategory":"Engineering",
            "type":"Services"
        }
    ],
    "sg:phone":"+33 4 79 31 41 56",
    "sg:postcode":"73460",
    "sg:province":"Rhone-Alpes",
    "sg:tags":[
        "machine",
        "-",
        "mechanical"
    ],
    "wof:name":"Charbogne (entreprise)",
    "wof:placetype":"venue"
},
  "geometry": {"coordinates":[6.319822,45.628387],"type":"Point"}
}