{
  "type": "Feature",
  "properties": {
    "iso:country":"FR",
    "sg:address":"Joli Coeur 56920 Noyal Pontivy",
    "sg:city":"Croixanvec",
    "sg:classifiers":[
        {
            "category":"Professional",
            "subcategory":"Engineering",
            "type":"Services"
        }
    ],
    "sg:phone":"+33 2 97 25 35 55",
    "sg:postcode":"56920",
    "sg:province":"Bretagne",
    "sg:tags":[
        "machine",
        "-",
        "mechanical"
    ],
    "wof:name":"Ouest Automatisation",
    "wof:placetype":"venue"
},
  "geometry": {"coordinates":[-2.927429,48.09166],"type":"Point"}
}