{
  "type": "Feature",
  "properties": {
    "iso:country":"FR",
    "sg:address":"B.P. 904, 53009 Laval C\u00e9dex^^202, Rue du Bas des Bois, 53000 Laval",
    "sg:orig_category":"Non-Classified Establishments",
    "sg:phone":"+33 2 43 59 24 50",
    "sg:province":"Pays de Loire",
    "wof:name":"S.t.a.l. S.a. - Soci\u00e9t\u00e9 Technique D'abattage De Laval",
    "wof:placetype":"venue"
},
  "geometry": {"coordinates":[-0.756451,48.036293],"type":"Point"}
}