{
  "type": "Feature",
  "properties": {
    "addr:full":"8, Rue Jules Verne, 35000 Rennes Rennes Bretagne 35000",
    "addr:housenumber":"8",
    "addr:postcode":"35000;35000",
    "addr:street":"Rue Jules Verne",
    "iso:country":"FR",
    "sg:address":"8, Rue Jules Verne, 35000 Rennes",
    "sg:city":"Rennes",
    "sg:orig_category":"Unclassifiable Establishments",
    "sg:phone":"+33 2 99 67 46 74",
    "sg:postcode":"35000",
    "sg:province":"Bretagne",
    "wof:name":"Fr\u00e8res S.a.",
    "wof:placetype":"venue"
},
  "geometry": {"coordinates":[-1.69064,48.100815],"type":"Point"}
}