{
  "type": "Feature",
  "properties": {
    "iso:country":"FR",
    "sg:address":"22 Bd Fosse 4 62980 Vermelles",
    "sg:classifiers":[
        {
            "category":"Autos & Motor Vehicles",
            "subcategory":"Automobile Sales",
            "type":"Retail Goods"
        }
    ],
    "sg:phone":"+33 3 21 61 93 30",
    "sg:postcode":"62980",
    "sg:province":"Nord Pas-de-Calais",
    "sg:tags":[
        "equipment",
        "motor-cars",
        "transport"
    ],
    "wof:name":"Space Car Sa",
    "wof:placetype":"venue"
},
  "geometry": {"coordinates":[2.750654,50.487705],"type":"Point"}
}