{
  "type": "Feature",
  "properties": {
    "addr:full":"5 Rue Alouettes 49450 St Macaire En Mauges Pays de Loire 49450",
    "addr:housenumber":"5",
    "addr:postcode":"49450;49450",
    "addr:street":"Rue Alouettes;Mauges",
    "iso:country":"FR",
    "sg:address":"5 Rue Alouettes 49450 St Macaire En Mauges",
    "sg:classifiers":[
        {
            "category":"Manufacturing",
            "subcategory":"Metals",
            "type":"Manufacturing & Wholesale Goods"
        }
    ],
    "sg:phone":"+33 2 41 55 39 52",
    "sg:postcode":"49450",
    "sg:province":"Pays de Loire",
    "sg:tags":[
        "metallurgy",
        "metalworking",
        "processing"
    ],
    "wof:name":"A4 Sarl",
    "wof:placetype":"venue"
},
  "geometry": {"coordinates":[-0.974044,47.118713],"type":"Point"}
}