{
  "type": "Feature",
  "properties": {
    "addr:full":"17, Impasse Truillot, 75011 Paris Ile de France",
    "addr:housenumber":"17",
    "addr:postcode":"75011",
    "addr:street":"Impasse Truillot",
    "iso:country":"FR",
    "sg:address":"17, Impasse Truillot, 75011 Paris",
    "sg:orig_category":"Non-Classified Establishments",
    "sg:phone":"+33 1 49 29 53 00",
    "sg:province":"Ile de France",
    "wof:name":"Hyptique S.a.r.l.",
    "wof:placetype":"venue"
},
  "geometry": {"coordinates":[2.374132,48.860088],"type":"Point"}
}