{
  "type": "Feature",
  "properties": {
    "addr:full":"8 Rue Vercors 69960 Corbas Rhone-Alpes",
    "addr:housenumber":"8",
    "addr:postcode":"69960",
    "addr:street":"Rue Vercors",
    "iso:country":"FR",
    "sg:address":"8 Rue Vercors 69960 Corbas",
    "sg:classifiers":[
        {
            "category":"Manufacturing",
            "subcategory":"Paper Products",
            "type":"Manufacturing & Wholesale Goods"
        }
    ],
    "sg:phone":"+33 4 78 20 73 07",
    "sg:province":"Rhone-Alpes",
    "sg:tags":[
        "raw",
        "material",
        "-",
        "cardboard"
    ],
    "wof:name":"Papier A Paviot Sa",
    "wof:placetype":"venue"
},
  "geometry": {"coordinates":[4.914762,45.672031],"type":"Point"}
}