{
  "type": "Feature",
  "properties": {
    "iso:country":"FR",
    "sg:address":"35, Rue Marthe Aureau, 77400 Lagny sur Marne",
    "sg:orig_category":"Non-Classified Establishments",
    "sg:phone":"+33 1 64 30 14 91",
    "sg:province":"Ile de France",
    "wof:name":"Modelage Et M\u00e9canique Clerc S.a.",
    "wof:placetype":"venue"
},
  "geometry": {"coordinates":[2.696935,48.87656],"type":"Point"}
}