{
  "type": "Feature",
  "properties": {
    "addr:full":"65, Rue Jules Vall\u00e8s, 44340 Bouguenais Pays de Loire",
    "addr:housenumber":"65",
    "addr:postcode":"44340",
    "addr:street":"Rue Jules Valle\u0300S",
    "iso:country":"FR",
    "sg:address":"65, Rue Jules Vall\u00e8s, 44340 Bouguenais",
    "sg:orig_category":"Unclassifiable Establishments",
    "sg:phone":"+33 2 40 75 43 14",
    "sg:province":"Pays de Loire",
    "wof:name":"Sapel S.a.r.l.",
    "wof:placetype":"venue"
},
  "geometry": {"coordinates":[-1.574185,47.171364],"type":"Point"}
}