{
  "type": "Feature",
  "properties": {
    "addr:full":"8, Bd de M\u00e9nilmontant, 75020 Paris Ile de France",
    "addr:housenumber":"8",
    "addr:postcode":"75020",
    "addr:street":"Bd De Me\u0301Nilmontant",
    "iso:country":"FR",
    "sg:address":"8, Bd de M\u00e9nilmontant, 75020 Paris",
    "sg:orig_category":"Non-Classified Establishments",
    "sg:phone":"+33 1 43 71 77 28",
    "sg:province":"Ile de France",
    "wof:name":"Hanrot S.a.",
    "wof:placetype":"venue"
},
  "geometry": {"coordinates":[2.389742,48.858757],"type":"Point"}
}