{
  "type": "Feature",
  "properties": {
    "iso:country":"FR",
    "sg:address":"B.P. 138, 60771 Rib\u00e9court C\u00e9dex^^ZAC la Grerie, 60771 Rib\u00e9court Dreslincourt",
    "sg:orig_category":"Non-Classified Establishments",
    "sg:phone":"+33 3 44 76 82 14",
    "sg:province":"Picardie",
    "wof:name":"Ribeprim S.a.",
    "wof:placetype":"venue"
},
  "geometry": {"coordinates":[2.87836,49.789406],"type":"Point"}
}