{
  "type": "Feature",
  "properties": {
    "addr:full":"98, Av de Strasbourg, 57070 Metz Lorraine",
    "addr:postcode":"57070",
    "addr:street":"98 Av De Strasbourg",
    "iso:country":"FR",
    "sg:address":"98, Av de Strasbourg, 57070 Metz",
    "sg:orig_category":"Unclassifiable Establishments",
    "sg:phone":"+33 3 87 74 34 29",
    "sg:province":"Lorraine",
    "wof:name":"Barth Menuiserie Eb\u00e9nisterie S.a.r.l.",
    "wof:placetype":"venue"
},
  "geometry": {"coordinates":[6.196306,49.112347],"type":"Point"}
}