{
  "type": "Feature",
  "properties": {
    "addr:full":"rue de Marienthal 67240 Bischwiller Bischwiller Alsace 67240",
    "addr:postcode":"67240;67240",
    "addr:street":"Rue De Marienthal",
    "iso:country":"FR",
    "sg:address":"rue de Marienthal 67240 Bischwiller",
    "sg:city":"Bischwiller",
    "sg:classifiers":[
        {
            "category":"Home & Garden",
            "subcategory":"Building Materials",
            "type":"Retail Goods"
        }
    ],
    "sg:phone":"+33 3 88 90 61 00",
    "sg:postcode":"67240",
    "sg:province":"Alsace",
    "sg:tags":[
        "plumbing",
        "ceramic",
        "fixture"
    ],
    "wof:name":"Duravit Sa",
    "wof:placetype":"venue"
},
  "geometry": {"coordinates":[7.832117,48.771584],"type":"Point"}
}