{
  "type": "Feature",
  "properties": {
    "iso:country":"FR",
    "sg:address":"9, Grande Rue, 92310 S\u00e8vres",
    "sg:orig_category":"Unclassifiable Establishments",
    "sg:phone":"+33 1 55 64 03 70",
    "sg:province":"Ile de France",
    "wof:name":"Banco Pinto & Sotto Mayor S.a.",
    "wof:placetype":"venue"
},
  "geometry": {"coordinates":[2.222082,48.826969],"type":"Point"}
}