{
  "type": "Feature",
  "properties": {
    "addr:full":"73130 Saint Martin sur la Chambre Rhone-Alpes",
    "addr:housenumber":"73130",
    "addr:street":"Saint Martin Sur La",
    "iso:country":"FR",
    "sg:address":"73130 Saint Martin sur la Chambre",
    "sg:orig_category":"Unclassifiable Establishments",
    "sg:phone":"+33 4 79 56 23 56",
    "sg:province":"Rhone-Alpes",
    "wof:name":"Reffet S.a.r.l.",
    "wof:placetype":"venue"
},
  "geometry": {"coordinates":[6.315847,45.366699],"type":"Point"}
}