{
  "type": "Feature",
  "properties": {
    "iso:country":"FR",
    "sg:address":"B.P. 101, 92230 Gennevilliers C\u00e9dex^^106, Rue du Foss\u00e9 Blanc, 92230 Gennevilliers",
    "sg:orig_category":"Non-Classified Establishments",
    "sg:phone":"+33 1 40 85 75 00",
    "sg:postcode":"92230",
    "sg:province":"Ile de France",
    "wof:name":"Caf\u00e9s Richard S.a.",
    "wof:placetype":"venue"
},
  "geometry": {"coordinates":[2.29447,48.925026],"type":"Point"}
}