{
  "type": "Feature",
  "properties": {
    "addr:full":"2 Bis Avenue Garibaldi 87000 Limoges Limousin",
    "addr:housenumber":"2 bis",
    "addr:postcode":"87000",
    "addr:street":"Avenue Garibaldi",
    "iso:country":"FR",
    "sg:address":"2 Bis Avenue Garibaldi 87000 Limoges",
    "sg:classifiers":[
        {
            "category":"Manufacturing",
            "subcategory":"Printing",
            "type":"Manufacturing & Wholesale Goods"
        }
    ],
    "sg:phone":"+33 5 55 79 53 00",
    "sg:province":"Limousin",
    "sg:tags":[
        "publishing"
    ],
    "wof:name":"Tirage Plan Sa",
    "wof:placetype":"venue"
},
  "geometry": {"coordinates":[1.262268,45.832649],"type":"Point"}
}