{
  "type": "Feature",
  "properties": {
    "addr:full":"116/118, Rue Jules Guesde, 92300 Levallois Perret Ile de France",
    "addr:housenumber":"116 / 118",
    "addr:postcode":"92300;ile",
    "addr:street":"Rue Jules Guesde",
    "iso:country":"FR",
    "sg:address":"116/118, Rue Jules Guesde, 92300 Levallois Perret",
    "sg:orig_category":"Unclassifiable Establishments",
    "sg:phone":"+33 1 45 19 39 90",
    "sg:province":"Ile de France",
    "wof:name":"Walther S.a.r.l.",
    "wof:placetype":"venue"
},
  "geometry": {"coordinates":[2.289748,48.89682],"type":"Point"}
}