{
  "type": "Feature",
  "properties": {
    "addr:full":"Rte de Collobri\u00e8res - Ch\u00e2teau Saint Maur Cogolin Bretagne 83310",
    "addr:postcode":"83310",
    "addr:street":"Rte De Collobrie\u0300Res Cha\u0302Teau Saint Maur",
    "iso:country":"FR",
    "sg:address":"Rte de Collobri\u00e8res - Ch\u00e2teau Saint Maur",
    "sg:city":"Cogolin",
    "sg:orig_category":"Unclassifiable Establishments",
    "sg:phone":"+33 4 94 54 63 12",
    "sg:postcode":"83310",
    "sg:province":"Bretagne",
    "wof:name":"Soci\u00e9t\u00e9 Agricole Ch\u00e2teau Saint-maur S.a.",
    "wof:placetype":"venue"
},
  "geometry": {"coordinates":[6.465188,43.207832],"type":"Point"}
}