{
  "type": "Feature",
  "properties": {
    "addr:full":"18 rue Solange Boutel 78840 Freneuse Ile de France",
    "addr:housenumber":"18",
    "addr:postcode":"78840",
    "addr:street":"Rue Solange Boutel;Ile De France",
    "iso:country":"FR",
    "sg:address":"18 rue Solange Boutel 78840 Freneuse",
    "sg:classifiers":[
        {
            "category":"Home & Garden",
            "subcategory":"Building Materials",
            "type":"Retail Goods"
        }
    ],
    "sg:phone":"+33 1 30 93 27 84",
    "sg:province":"Ile de France",
    "sg:tags":[
        "plant",
        "industry",
        "textile",
        "stp",
        "treatment",
        "sewage"
    ],
    "wof:name":"Asepta S.a.r.l.",
    "wof:placetype":"venue"
},
  "geometry": {"coordinates":[1.590874,49.041004],"type":"Point"}
}