{
  "type": "Feature",
  "properties": {
    "addr:full":"ZI 25320 CHEMAUDIN Franche Comt\u00e9 25320",
    "addr:postcode":"25320;25320",
    "addr:street":"Zi;Franche Comte\u0301",
    "iso:country":"FR",
    "sg:address":"ZI 25320 CHEMAUDIN",
    "sg:classifiers":[
        {
            "category":"Manufacturing",
            "subcategory":"Printing",
            "type":"Manufacturing & Wholesale Goods"
        }
    ],
    "sg:phone":"+33 3 81 48 36 15",
    "sg:postcode":"25320",
    "sg:province":"Franche Comt\u00e9",
    "sg:tags":[
        "house",
        "book"
    ],
    "wof:name":"Mignot Graphie S.a.",
    "wof:placetype":"venue"
},
  "geometry": {"coordinates":[5.909899,47.177418],"type":"Point"}
}