{
  "type": "Feature",
  "properties": {
    "iso:country":"FR",
    "sg:address":"La Haute Rivi\u00e8re 35370 Le Pertre",
    "sg:city":"Le Pertre",
    "sg:classifiers":[
        {
            "category":"Bakery",
            "type":"Food & Drink"
        }
    ],
    "sg:phone":"+33 2 99 96 80 90",
    "sg:postcode":"35370",
    "sg:province":"Bretagne",
    "sg:tags":[
        "cake",
        "product",
        "related",
        "bread"
    ],
    "wof:name":"Les Desserts Xavier Gourmet Sa",
    "wof:placetype":"venue"
},
  "geometry": {"coordinates":[-1.036799,48.020695],"type":"Point"}
}