{
  "type": "Feature",
  "properties": {
    "iso:country":"FR",
    "sg:address":"60, Rue de l'Industrie - Parc d'Activit\u00e9s Secteur 2, 77176 Savigny le Temple",
    "sg:orig_category":"Unclassifiable Establishments",
    "sg:phone":"+33 1 64 10 54 30",
    "sg:province":"Ile de France",
    "wof:name":"Hydro Gas And Chemical France S.a.",
    "wof:placetype":"venue"
},
  "geometry": {"coordinates":[2.581195,48.60358],"type":"Point"}
}