{
  "type": "Feature",
  "properties": {
    "addr:full":"La Grande Haie 44170 Nozay Pays de Loire",
    "addr:postcode":"44170",
    "addr:street":"La Grande Haie",
    "iso:country":"FR",
    "sg:address":"La Grande Haie 44170 Nozay",
    "sg:classifiers":[
        {
            "category":"Home & Garden",
            "subcategory":"Furniture",
            "type":"Retail Goods"
        }
    ],
    "sg:phone":"+33 2 40 79 43 32",
    "sg:province":"Pays de Loire",
    "sg:tags":[
        "wood"
    ],
    "wof:name":"Bourdaud Sa",
    "wof:placetype":"venue"
},
  "geometry": {"coordinates":[-1.625024,47.578217],"type":"Point"}
}