{
  "type": "Feature",
  "properties": {
    "addr:full":"Hotel Entreprises Ecopolis 73 Avenue De L Europe 80080 Amiens Amiens Picardie 80000",
    "addr:housenumber":"73",
    "addr:postcode":"80080 amiens;80000",
    "addr:street":"Avenue De L Europe",
    "iso:country":"FR",
    "sg:address":"Hotel Entreprises Ecopolis 73 Avenue De L Europe 80080 Amiens",
    "sg:city":"Amiens",
    "sg:classifiers":[
        {
            "category":"Wholesale",
            "subcategory":"Medical Equipment & Supplies",
            "type":"Manufacturing & Wholesale Goods"
        }
    ],
    "sg:phone":"+33 3 22 66 01 00",
    "sg:postcode":"80000",
    "sg:province":"Picardie",
    "sg:tags":[
        "instrument",
        "health",
        "-",
        "precision"
    ],
    "wof:name":"Dentechnica",
    "wof:placetype":"venue"
},
  "geometry": {"coordinates":[2.2913,49.924992],"type":"Point"}
}