{
  "type": "Feature",
  "properties": {
    "iso:country":"FR",
    "sg:address":"21 R D\u00e9port\u00e9s 11 Novembre 1943 38100 Grenoble",
    "sg:classifiers":[
        {
            "category":"Banks & Credit Unions",
            "subcategory":"Bureau De Change",
            "type":"Services"
        }
    ],
    "sg:phone":"+33 4 76 87 82 38",
    "sg:postcode":"38100",
    "sg:province":"Rhone-Alpes",
    "sg:tags":[
        "device",
        "short-circuit",
        "protection",
        "grounding",
        "equipment"
    ],
    "wof:name":"Tectra Sa",
    "wof:placetype":"venue"
},
  "geometry": {"coordinates":[5.728085,45.178761],"type":"Point"}
}