{
  "type": "Feature",
  "properties": {
    "iso:country":"FR",
    "sg:address":"Za De Kerganet 29720 Ploneour Lanvern",
    "sg:city":"Plon\u00e9our-Lanvern",
    "sg:classifiers":[
        {
            "category":"Autos & Motor Vehicles",
            "subcategory":"Boat Sales",
            "type":"Retail Goods"
        }
    ],
    "sg:phone":"+33 2 98 87 12 79",
    "sg:postcode":"29720",
    "sg:province":"Bretagne",
    "sg:tags":[
        "equipment",
        "transport"
    ],
    "wof:name":"Atelier De Constructions Composites Du Finistere (accf)",
    "wof:placetype":"venue"
},
  "geometry": {"coordinates":[-4.282665,47.903004],"type":"Point"}
}