{
  "type": "Feature",
  "properties": {
    "addr:full":"33, Rue Maxime Gorki, 42500 Le Chambon Feugerolles Rhone-Alpes",
    "addr:housenumber":"33",
    "addr:postcode":"42500",
    "addr:street":"Rue Maxime Gorki;Chambon Feugerolles Rhone-Alpes",
    "iso:country":"FR",
    "sg:address":"33, Rue Maxime Gorki, 42500 Le Chambon Feugerolles",
    "sg:orig_category":"Unclassifiable Establishments",
    "sg:phone":"+33 4 77 56 97 71",
    "sg:province":"Rhone-Alpes",
    "wof:name":"S.e.r.p.p. S.a.r.l. - Soci\u00e9t\u00e9 Etude R\u00e9alisation Pi\u00e8ces Plastiques",
    "wof:placetype":"venue"
},
  "geometry": {"coordinates":[4.347736,45.399384],"type":"Point"}
}