{
  "type": "Feature",
  "properties": {
    "iso:country":"FR",
    "sg:address":"36, Rue Henri Ginou, 92120 Montrouge",
    "sg:orig_category":"Non-Classified Establishments",
    "sg:phone":"+33 1 46 55 36 40",
    "sg:province":"Ile de France",
    "wof:name":"Ultrapeint S.a.",
    "wof:placetype":"venue"
},
  "geometry": {"coordinates":[2.323407,48.819675],"type":"Point"}
}