{
  "type": "Feature",
  "properties": {
    "addr:full":"Za Des Vernays 74210 Doussard Rhone-Alpes",
    "addr:postcode":"74210",
    "addr:street":"Za Des Vernays",
    "iso:country":"FR",
    "sg:address":"Za Des Vernays 74210 Doussard",
    "sg:classifiers":[
        {
            "category":"Food & Beverages",
            "subcategory":"Meat & Fish",
            "type":"Retail Goods"
        }
    ],
    "sg:phone":"+33 4 50 44 82 74",
    "sg:province":"Rhone-Alpes",
    "sg:tags":[
        "preserve",
        "cooked",
        "product",
        "related"
    ],
    "wof:name":"Societe D'exploitation Des Salaisons Du Mont Charvin",
    "wof:placetype":"venue"
},
  "geometry": {"coordinates":[6.223346,45.779167],"type":"Point"}
}