{
  "type": "Feature",
  "properties": {
    "iso:country":"FR",
    "sg:address":"5 rue R\u00e9aumur 75003 Paris",
    "sg:classifiers":[
        {
            "category":"Travel",
            "subcategory":"Campground",
            "type":"Entertainment"
        }
    ],
    "sg:phone":"+33 1 48 87 88 11",
    "sg:province":"Ile de France",
    "sg:tags":[
        "rental",
        "tent"
    ],
    "wof:name":"Laval Fanni Organisation S.a.r.l.",
    "wof:placetype":"venue"
},
  "geometry": {"coordinates":[2.359059,48.864697],"type":"Point"}
}