{
  "type": "Feature",
  "properties": {
    "addr:full":"10, Av. de Bellevue, 35136 Saint Jacques de la Lande Saint-Jacques-de-la-Lande Bretagne 35136",
    "addr:postcode":"35136;35136",
    "addr:street":"10 Av. De Bellevue;Saint-Jacques-De-La-Lande",
    "iso:country":"FR",
    "sg:address":"10, Av. de Bellevue, 35136 Saint Jacques de la Lande",
    "sg:city":"Saint-Jacques-de-la-Lande",
    "sg:orig_category":"Non-Classified Establishments",
    "sg:phone":"+33 2 99 65 49 36",
    "sg:postcode":"35136",
    "sg:province":"Bretagne",
    "wof:name":"Loyer Philippe Yves",
    "wof:placetype":"venue"
},
  "geometry": {"coordinates":[-1.733695,48.079716],"type":"Point"}
}