{
  "type": "Feature",
  "properties": {
    "iso:country":"FR",
    "sg:address":"16, Rue Raymond Brosse, 93430 Villetaneuse",
    "sg:orig_category":"Unclassifiable Establishments",
    "sg:phone":"+33 1 48 29 37 38",
    "sg:province":"Ile de France",
    "wof:name":"Litra S.a.",
    "wof:placetype":"venue"
},
  "geometry": {"coordinates":[2.346325,48.956123],"type":"Point"}
}