{
  "type": "Feature",
  "properties": {
    "addr:full":"905, Av. du Camp de Menthe, 13090 Aix en Provence Provence-Alpes-C\u00f4te d'Azur",
    "addr:postcode":"13090",
    "addr:street":"905 Av. Du Camp De Menthe;En Provence",
    "iso:country":"FR",
    "sg:address":"905, Av. du Camp de Menthe, 13090 Aix en Provence",
    "sg:orig_category":"Unclassifiable Establishments",
    "sg:phone":"+33 4 42 95 95 95",
    "sg:province":"Provence-Alpes-C\u00f4te d'Azur",
    "wof:name":"E.d.f. S.q.r. T.e.g.g.",
    "wof:placetype":"venue"
},
  "geometry": {"coordinates":[5.41778,43.510792],"type":"Point"}
}