{
  "type": "Feature",
  "properties": {
    "iso:country":"FR",
    "sg:address":"16 boulevard d'Orient 34070 Montpellier",
    "sg:classifiers":[
        {
            "category":"Social Services",
            "subcategory":"Job Training",
            "type":"Services"
        }
    ],
    "sg:phone":"+33 4 67 65 01 82",
    "sg:province":"Languedoc-Roussillon",
    "sg:tags":[
        "personnel",
        "staff"
    ],
    "wof:name":"Adhara Informatique",
    "wof:placetype":"venue"
},
  "geometry": {"coordinates":[3.84676,43.591499],"type":"Point"}
}