{
  "type": "Feature",
  "properties": {
    "iso:country":"FR",
    "sg:address":"18, Rue Nagelstall, 68140 Luttenbach",
    "sg:city":"Eschbach-au-Val",
    "sg:orig_category":"Unclassifiable Establishments",
    "sg:phone":"+33 3 89 77 34 25",
    "sg:postcode":"68140",
    "sg:province":"Alsace",
    "wof:name":"Basso Franc S.a.r.l. - Entreprise De Construction",
    "wof:placetype":"venue"
},
  "geometry": {"coordinates":[7.145949,48.028965],"type":"Point"}
}