{
  "type": "Feature",
  "properties": {
    "iso:country":"FR",
    "sg:address":"Quai Berthelot",
    "sg:city":"Saint Dizier",
    "sg:orig_category":"Unclassifiable Establishments",
    "sg:phone":"+33 3 25 05 09 81",
    "sg:postcode":"52100",
    "sg:province":"Champagne",
    "wof:name":"Bragarde Amenagement S.a.r.l.",
    "wof:placetype":"venue"
},
  "geometry": {"coordinates":[4.940891,48.642029],"type":"Point"}
}