{
  "type": "Feature",
  "properties": {
    "addr:full":"Zi De La Bergerie 49280 La Seguini\u00e8re Pays de Loire",
    "addr:postcode":"49280",
    "addr:street":"Zi De La Bergerie;Seguinie\u0300Re",
    "iso:country":"FR",
    "sg:address":"Zi De La Bergerie 49280 La Seguini\u00e8re",
    "sg:classifiers":[
        {
            "category":"Professional",
            "type":"Services"
        }
    ],
    "sg:phone":"+33 2 41 56 02 80",
    "sg:province":"Pays de Loire",
    "sg:tags":[
        "transport",
        "road"
    ],
    "wof:name":"Heppner Societe De Transports",
    "wof:placetype":"venue"
},
  "geometry": {"coordinates":[-0.936754,47.060074],"type":"Point"}
}