{
  "type": "Feature",
  "properties": {
    "addr:full":"6, Rue du Mar\u00e9chal Juin, 95210 Saint Gratien Ile de France 95210",
    "addr:housenumber":"6",
    "addr:postcode":"95210;95210",
    "addr:street":"Rue Du Mare\u0301Chal Juin",
    "iso:country":"FR",
    "sg:address":"6, Rue du Mar\u00e9chal Juin, 95210 Saint Gratien",
    "sg:orig_category":"Non-Classified Establishments",
    "sg:phone":"+33 1 34 05 15 00",
    "sg:postcode":"95210",
    "sg:province":"Ile de France",
    "wof:name":"Edifis S.a.r.l.",
    "wof:placetype":"venue"
},
  "geometry": {"coordinates":[2.287109,48.963638],"type":"Point"}
}