{
  "type": "Feature",
  "properties": {
    "iso:country":"FR",
    "sg:address":"6, Rue du Mar\u00e9chal Juin, 95210 Saint Gratien",
    "sg:orig_category":"Non-Classified Establishments",
    "sg:phone":"+33 1 34 05 15 00",
    "sg:postcode":"95210",
    "sg:province":"Ile de France",
    "wof:name":"Edifis S.a.r.l.",
    "wof:placetype":"venue"
},
  "geometry": {"coordinates":[2.287109,48.963638],"type":"Point"}
}