{
  "type": "Feature",
  "properties": {
    "iso:country":"FR",
    "sg:address":"170 Avenue Jean Jaures 75019 Paris",
    "sg:classifiers":[
        {
            "category":"Wholesale",
            "subcategory":"Machinery & Supplies",
            "type":"Manufacturing & Wholesale Goods"
        }
    ],
    "sg:phone":"+33 1 42 02 55 35",
    "sg:postcode":"75019",
    "sg:province":"Ile de France",
    "sg:tags":[
        "food",
        "processing",
        "-",
        "machine",
        "equipment",
        "engineering",
        "mechanical"
    ],
    "wof:name":"Capic",
    "wof:placetype":"venue"
},
  "geometry": {"coordinates":[2.388844,48.887489],"type":"Point"}
}