{
  "type": "Feature",
  "properties": {
    "iso:country":"FR",
    "sg:address":"182, Rue du Faubourg Saint -Denis, 75010 Paris",
    "sg:orig_category":"Unclassifiable Establishments",
    "sg:phone":"+33 1 40 35 38 80",
    "sg:province":"Ile de France",
    "wof:name":"L.s.i. S.a. - La Solution Int\u00e9rimaire",
    "wof:placetype":"venue"
},
  "geometry": {"coordinates":[2.358013,48.880814],"type":"Point"}
}