{
  "type": "Feature",
  "properties": {
    "addr:full":"56, Rue Houdart, 95700 Roissy en France Ile de France 95700",
    "addr:housenumber":"56",
    "addr:postcode":"95700;95700",
    "addr:street":"Rue Houdart",
    "iso:country":"FR",
    "sg:address":"56, Rue Houdart, 95700 Roissy en France",
    "sg:orig_category":"Non-Classified Establishments",
    "sg:phone":"+33 1 34 29 36 00",
    "sg:postcode":"95700",
    "sg:province":"Ile de France",
    "wof:name":"Cosson S.a.",
    "wof:placetype":"venue"
},
  "geometry": {"coordinates":[2.517005,49.003883],"type":"Point"}
}