{
  "type": "Feature",
  "properties": {
    "iso:country":"FR",
    "sg:address":"RN 86 - La Ponche Sud",
    "sg:city":"Marguerittes",
    "sg:orig_category":"Non-Classified Establishments",
    "sg:phone":"+33 4 66 02 22 00",
    "sg:postcode":"30320",
    "sg:province":"Languedoc-Roussillon",
    "wof:name":"M\u00e9ac S.a.",
    "wof:placetype":"venue"
},
  "geometry": {"coordinates":[4.445175,43.859467],"type":"Point"}
}