{
  "type": "Feature",
  "properties": {
    "addr:full":"Pl Pierre S\u00e9mard 17100 Saintes Poitou-Charentes 17100",
    "addr:postcode":"17100;17100",
    "addr:street":"Pl Pierre Se\u0301Mard",
    "iso:country":"FR",
    "sg:address":"Pl Pierre S\u00e9mard 17100 Saintes",
    "sg:classifiers":[
        {
            "category":"Professional",
            "type":"Services"
        }
    ],
    "sg:phone":"+33 5 46 92 82 00",
    "sg:postcode":"17100",
    "sg:province":"Poitou-Charentes",
    "sg:tags":[
        "transport",
        "road"
    ],
    "wof:name":"Sernam",
    "wof:placetype":"venue"
},
  "geometry": {"coordinates":[-0.618231,45.747948],"type":"Point"}
}