{
  "type": "Feature",
  "properties": {
    "addr:full":"17 Rue Eug\u00e8ne P\u00e9reire 91610 Ballancourt Sur Essonne Ile de France",
    "addr:housenumber":"17",
    "addr:postcode":"91610;ile",
    "addr:street":"Rue Euge\u0300Ne Pe\u0301Reire",
    "iso:country":"FR",
    "sg:address":"17 Rue Eug\u00e8ne P\u00e9reire 91610 Ballancourt Sur Essonne",
    "sg:classifiers":[
        {
            "category":"Manufacturing",
            "subcategory":"Paper Products",
            "type":"Manufacturing & Wholesale Goods"
        }
    ],
    "sg:phone":"+33 1 69 90 72 00",
    "sg:province":"Ile de France",
    "sg:tags":[
        "finished",
        "cardboard",
        "-"
    ],
    "wof:name":"Monttecolino France Sa",
    "wof:placetype":"venue"
},
  "geometry": {"coordinates":[2.368427,48.53091],"type":"Point"}
}