{
  "type": "Feature",
  "properties": {
    "iso:country":"FR",
    "sg:address":"avenue des Mouli\u00e8res 13140 Miramas",
    "sg:orig_category":"Swimming-Pools Of Aluminium",
    "sg:phone":"+33 4 90 50 20 85",
    "sg:province":"Provence-Alpes-C\u00f4te d'Azur",
    "wof:name":"Aluminium Liner Piscines Sa",
    "wof:placetype":"venue"
},
  "geometry": {"coordinates":[5.00581,43.594666],"type":"Point"}
}