{
  "type": "Feature",
  "properties": {
    "iso:country":"FR",
    "sg:address":"B.P. 553, 64012 Pau C\u00e9dex 02^^77, Av. des Lilas, 64000 Pau",
    "sg:city":"Pau",
    "sg:orig_category":"Non-Classified Establishments",
    "sg:phone":"+33 5 59 30 88 88",
    "sg:postcode":"64000",
    "sg:province":"Aquitaine",
    "wof:name":"Altis S.a.",
    "wof:placetype":"venue"
},
  "geometry": {"coordinates":[-0.374294,43.296558],"type":"Point"}
}