{
  "type": "Feature",
  "properties": {
    "iso:country":"FR",
    "sg:address":"24, Av. des Gr\u00e9sillons, 92600 Asni\u00e8res sur Seine",
    "sg:orig_category":"Non-Classified Establishments",
    "sg:phone":"+33 1 41 11 86 00",
    "sg:province":"Ile de France",
    "wof:name":"Europ\u00e9enne De Nettoyage S.a.r.l.",
    "wof:placetype":"venue"
},
  "geometry": {"coordinates":[2.303372,48.915623],"type":"Point"}
}