{
  "type": "Feature",
  "properties": {
    "iso:country":"FR",
    "sg:address":"88, Av. de la Poterie, 33170 Gradignan",
    "sg:city":"Gradignan",
    "sg:orig_category":"Unclassifiable Establishments",
    "sg:phone":"+33 5 56 89 23 00",
    "sg:postcode":"33170",
    "sg:province":"Aquitaine",
    "wof:name":"Vsl Sport Diffusion S.a.",
    "wof:placetype":"venue"
},
  "geometry": {"coordinates":[-0.644759,44.772209],"type":"Point"}
}