{
  "type": "Feature",
  "properties": {
    "iso:country":"FR",
    "sg:address":"Pont De Peille 06340 Drap",
    "sg:classifiers":[
        {
            "category":"Professional",
            "type":"Services"
        }
    ],
    "sg:phone":"+33 4 93 91 27 32",
    "sg:province":"Provence-Alpes-C\u00f4te d'Azur",
    "sg:tags":[
        "transport",
        "road"
    ],
    "wof:name":"Dragotrans Sarl",
    "wof:placetype":"venue"
},
  "geometry": {"coordinates":[7.330558,43.767124],"type":"Point"}
}