{
  "type": "Feature",
  "properties": {
    "addr:full":"5, Av Martyrs de la R\u00e9sistance, 08200 Floing Champagne",
    "addr:postcode":"08200",
    "addr:street":"Av Martyrs De La Re\u0301Sistance",
    "iso:country":"FR",
    "sg:address":"5, Av Martyrs de la R\u00e9sistance, 08200 Floing",
    "sg:orig_category":"NOUVELLE CHAINE AUTOMATIS\u00c9E DE REV\u00caTEMENTS TOUTES S\u00c9RIES TRAVAUX DE GRENAILLAGE, REV\u00caTEMENT POUR PRO",
    "sg:phone":"+33 3 24 29 79 88",
    "sg:province":"Champagne",
    "wof:name":"Applitec S.a.",
    "wof:placetype":"venue"
},
  "geometry": {"coordinates":[4.926836,49.71183],"type":"Point"}
}