{
  "type": "Feature",
  "properties": {
    "addr:full":"Chem De St Bernard 64100 Bayonne Bayonne Aquitaine 64100",
    "addr:postcode":"64100 bayonne;64100",
    "addr:street":"Chem De St Bernard",
    "iso:country":"FR",
    "sg:address":"Chem De St Bernard 64100 Bayonne",
    "sg:city":"Bayonne",
    "sg:classifiers":[
        {
            "category":"Home & Garden",
            "subcategory":"Furniture",
            "type":"Retail Goods"
        }
    ],
    "sg:phone":"+33 5 59 50 37 37",
    "sg:postcode":"64100",
    "sg:province":"Aquitaine",
    "sg:tags":[
        "wood"
    ],
    "wof:name":"Louis Cazenave Landes Sa",
    "wof:placetype":"venue"
},
  "geometry": {"coordinates":[-1.488277,43.510147],"type":"Point"}
}