{
  "type": "Feature",
  "properties": {
    "iso:country":"FR",
    "sg:address":"35, Rue Tessier, 41160 Fr\u00e9teval",
    "sg:city":"Fr\u00e9teval",
    "sg:orig_category":"Unclassifiable Establishments",
    "sg:phone":"+33 2 54 82 01 45",
    "sg:postcode":"41160",
    "sg:province":"Centre",
    "wof:name":"Market-art S.a.r.l.",
    "wof:placetype":"venue"
},
  "geometry": {"coordinates":[1.225643,47.860203],"type":"Point"}
}