{
  "type": "Feature",
  "properties": {
    "addr:full":"4, All\u00e9e du Doyen Georges Brus - Parc Unitec 1, 33600 Pessac Pessac Aquitaine 33600",
    "addr:housenumber":"4;1",
    "addr:postcode":"33600;33600",
    "addr:street":"Alle\u0301E Du Doyen Georges Brus Parc Unitec",
    "iso:country":"FR",
    "sg:address":"4, All\u00e9e du Doyen Georges Brus - Parc Unitec 1, 33600 Pessac",
    "sg:city":"Pessac",
    "sg:orig_category":"Non-Classified Establishments",
    "sg:phone":"+33 5 57 02 10 60",
    "sg:postcode":"33600",
    "sg:province":"Aquitaine",
    "wof:name":"Astek S.a.",
    "wof:placetype":"venue"
},
  "geometry": {"coordinates":[-0.623704,44.793983],"type":"Point"}
}