{
  "type": "Feature",
  "properties": {
    "iso:country":"FR",
    "sg:address":"8 Esplanade Compans Caffarelli 31000 Toulouse",
    "sg:classifiers":[
        {
            "category":"Travel",
            "subcategory":"Hotels & Motels",
            "type":"Entertainment"
        }
    ],
    "sg:phone":"+33 5 61 11 09 09",
    "sg:postcode":"31000",
    "sg:province":"Midi Pyr\u00e9n\u00e9es",
    "sg:tags":[
        "hotels",
        "business",
        "restaurant"
    ],
    "wof:name":"Atria Hotel Mercure Compans-caffarelli Sa",
    "wof:placetype":"venue"
},
  "geometry": {"coordinates":[1.435325,43.610695],"type":"Point"}
}