{
  "type": "Feature",
  "properties": {
    "addr:full":"Rue des Commerces Marsac sur l'Isle Aquitaine 24430",
    "addr:postcode":"24430",
    "addr:street":"Rue Des Commerces",
    "iso:country":"FR",
    "sg:address":"Rue des Commerces",
    "sg:city":"Marsac sur l'Isle",
    "sg:orig_category":"Unclassifiable Establishments",
    "sg:phone":"+33 5 53 04 81 94",
    "sg:postcode":"24430",
    "sg:province":"Aquitaine",
    "wof:name":"G.e.a. Matal S.a.",
    "wof:placetype":"venue"
},
  "geometry": {"coordinates":[0.662757,45.193253],"type":"Point"}
}