{
  "type": "Feature",
  "properties": {
    "addr:full":"21, Rue de Paris, 02100 Saint Quentin Picardie",
    "addr:housenumber":"21",
    "addr:postcode":"02100",
    "addr:street":"Rue De Paris",
    "iso:country":"FR",
    "sg:address":"21, Rue de Paris, 02100 Saint Quentin",
    "sg:orig_category":"Unclassifiable Establishments",
    "sg:phone":"+33 3 23 62 01 91",
    "sg:province":"Picardie",
    "wof:name":"C.g.s.t. Save S.a.s. - Compagnie Gazi\u00e8re De Service Technique Save",
    "wof:placetype":"venue"
},
  "geometry": {"coordinates":[3.277332,49.842606],"type":"Point"}
}