{
  "type": "Feature",
  "properties": {
    "iso:country":"FR",
    "sg:address":"Rue Charles Cros Zi 95322 St La For\u00eat",
    "sg:classifiers":[
        {
            "category":"Manufacturing",
            "subcategory":"Motor Vehicles & Parts",
            "type":"Manufacturing & Wholesale Goods"
        }
    ],
    "sg:phone":"+33 1 39 32 77 50",
    "sg:province":"Auvergne",
    "sg:tags":[
        "engine",
        "machine",
        "engineering",
        "-",
        "mechanical"
    ],
    "wof:name":"Site Sa",
    "wof:placetype":"venue"
},
  "geometry": {"coordinates":[-120.95797,37.196579],"type":"Point"}
}