{
  "type": "Feature",
  "properties": {
    "addr:full":"60 Grande Rue 67360 Walbourg Walbourg Alsace 67360",
    "addr:housenumber":"60",
    "addr:postcode":"67360;67360",
    "addr:street":"Grande Rue;Walbourg",
    "iso:country":"FR",
    "sg:address":"60 Grande Rue 67360 Walbourg",
    "sg:city":"Walbourg",
    "sg:classifiers":[
        {
            "category":"Professional",
            "subcategory":"Business Services",
            "type":"Services"
        }
    ],
    "sg:phone":"+33 3 88 90 29 29",
    "sg:postcode":"67360",
    "sg:province":"Alsace",
    "sg:tags":[
        "training",
        "advice"
    ],
    "wof:name":"Seminaire Des Jeunes",
    "wof:placetype":"venue"
},
  "geometry": {"coordinates":[7.781544,48.888271],"type":"Point"}
}