{
  "type": "Feature",
  "properties": {
    "iso:country":"FR",
    "sg:address":"113, Rue Nationale, 75013 Paris",
    "sg:orig_category":"Non-Classified Establishments",
    "sg:phone":"+33 1 44 24 59 00",
    "sg:province":"Ile de France",
    "wof:name":"Unilogic S.a.",
    "wof:placetype":"venue"
},
  "geometry": {"coordinates":[2.36513,48.829189],"type":"Point"}
}