{
  "type": "Feature",
  "properties": {
    "iso:country":"FR",
    "sg:address":"Chemin d'Auguste",
    "sg:city":"Cestas C\u00e9dex",
    "sg:orig_category":"Non-Classified Establishments",
    "sg:phone":"+33 5 56 68 08 80",
    "sg:postcode":"33612",
    "sg:province":"Florida",
    "wof:name":"Milhares S.a.",
    "wof:placetype":"venue"
},
  "geometry": {"coordinates":[-82.450737,28.05092],"type":"Point"}
}