{
  "type": "Feature",
  "properties": {
    "addr:full":"r Chamerose 71640 Mercurey Mercurey Bourgogne 71640",
    "addr:postcode":"71640;71640",
    "iso:country":"FR",
    "sg:address":"r Chamerose 71640 Mercurey",
    "sg:city":"Mercurey",
    "sg:classifiers":[
        {
            "category":"Food Court",
            "type":"Food & Drink"
        }
    ],
    "sg:phone":"+33 3 85 45 10 83",
    "sg:postcode":"71640",
    "sg:province":"Bourgogne",
    "sg:tags":[
        "product",
        "related"
    ],
    "wof:name":"Tramier L Et Fils",
    "wof:placetype":"venue"
},
  "geometry": {"coordinates":[4.718062,46.838451],"type":"Point"}
}