{
  "type": "Feature",
  "properties": {
    "iso:country":"FR",
    "sg:address":"Rte de Puiseaux",
    "sg:city":"Estouy",
    "sg:orig_category":"Unclassifiable Establishments",
    "sg:phone":"+33 2 38 39 71 30",
    "sg:postcode":"45300",
    "sg:province":"Centre",
    "wof:name":"Brouillet Surre S.a.",
    "wof:placetype":"venue"
},
  "geometry": {"coordinates":[2.29716,48.18206],"type":"Point"}
}