{
  "type": "Feature",
  "properties": {
    "iso:country":"FR",
    "sg:address":"51, Esplanade G\u00e9n\u00e9ral De Gaulle - Tour Galil\u00e9e, 92907 Paris la D\u00e9fence C\u00e9dex",
    "sg:orig_category":"Non-Classified Establishments",
    "sg:phone":"+33 1 41 35 40 00",
    "sg:province":"\u00cele-de-France",
    "wof:name":"Total Outremer S.a.",
    "wof:placetype":"venue"
},
  "geometry": {"coordinates":[2.208,48.896141],"type":"Point"}
}