{
  "type": "Feature",
  "properties": {
    "addr:full":"42 Rue De Rochechouart 87000 Limoges Limousin 87000",
    "addr:housenumber":"42",
    "addr:postcode":"87000;87000",
    "addr:street":"Rue De Rochechouart",
    "iso:country":"FR",
    "sg:address":"42 Rue De Rochechouart 87000 Limoges",
    "sg:classifiers":[
        {
            "category":"Home & Garden",
            "subcategory":"Furniture",
            "type":"Retail Goods"
        }
    ],
    "sg:phone":"+33 5 55 32 34 70",
    "sg:postcode":"87000",
    "sg:province":"Limousin",
    "sg:tags":[
        "professional",
        "household",
        "wood"
    ],
    "wof:name":"Jfd Menuiseries",
    "wof:placetype":"venue"
},
  "geometry": {"coordinates":[1.244159,45.827553],"type":"Point"}
}