{
  "type": "Feature",
  "properties": {
    "iso:country":"FR",
    "sg:address":"B.P. 281, 68315 Illzach C\u00e9dex^^14, Av d'Italie, 68110 Illzach",
    "sg:city":"Illzach",
    "sg:orig_category":"Non-Classified Establishments",
    "sg:phone":"+33 3 89 61 80 91",
    "sg:postcode":"68110",
    "sg:province":"Alsace",
    "wof:name":"F.a.a.c. S.a. - Fournitures D'accessoires Pour Automobiles Et Carrosserie",
    "wof:placetype":"venue"
},
  "geometry": {"coordinates":[7.372461,47.762276],"type":"Point"}
}