{
  "type": "Feature",
  "properties": {
    "iso:country":"FR",
    "sg:address":"2 Rue Des Meuniers Zac De Jailly 57535 Marange Silvange",
    "sg:classifiers":[
        {
            "category":"Autos & Motor Vehicles",
            "subcategory":"Automobile Sales",
            "type":"Retail Goods"
        }
    ],
    "sg:phone":"+33 3 87 80 16 16",
    "sg:province":"Haute Normandie",
    "sg:tags":[
        "equipment",
        "industrial",
        "transport"
    ],
    "wof:name":"La Metallurgie Generale (metag)",
    "wof:placetype":"venue"
},
  "geometry": {"coordinates":[6.11731,49.216114],"type":"Point"}
}