{
  "type": "Feature",
  "properties": {
    "addr:full":"B.P. 48 Gaillon C\u00e9dex^^Les Granges 27600 Champenard Haute Normandie 27600",
    "addr:postcode":"27600;27600",
    "addr:street":"B.P. 48;Ce\u0301Dex^^Les Granges;Haute Normandie",
    "iso:country":"FR",
    "sg:address":"B.P. 48",
    "sg:city":"Gaillon C\u00e9dex^^Les Granges 27600 Champenard",
    "sg:orig_category":"Non-Classified Establishments",
    "sg:phone":"+33 2 32 21 47 00",
    "sg:postcode":"27600",
    "sg:province":"Haute Normandie",
    "wof:name":"Cinran France S.a.",
    "wof:placetype":"venue"
},
  "geometry": {"coordinates":[1.334565,49.160366],"type":"Point"}
}