{
  "type": "Feature",
  "properties": {
    "iso:country":"FR",
    "sg:address":"ZI La Gare",
    "sg:city":"Saint Laurent sur S\u00e8vre",
    "sg:orig_category":"Unclassifiable Establishments",
    "sg:phone":"+33 2 51 67 81 40",
    "sg:postcode":"85290",
    "sg:province":"Pays de Loire",
    "wof:name":"Transports Et Combustibles S.a.r.l.",
    "wof:placetype":"venue"
},
  "geometry": {"coordinates":[-0.891658,46.959106],"type":"Point"}
}