{
  "type": "Feature",
  "properties": {
    "addr:full":"6 r Brigadier Claverie; Cagnes sur Mer Poitou-Charentes",
    "addr:housenumber":"6",
    "addr:street":"R Brigadier Claverie Cagnes;Mer",
    "iso:country":"FR",
    "sg:address":"6 r Brigadier Claverie; Cagnes sur Mer",
    "sg:classifiers":[
        {
            "category":"Banks & Credit Unions",
            "subcategory":"Bank",
            "type":"Services"
        }
    ],
    "sg:phone":"+33 3393226547",
    "sg:province":"Poitou-Charentes",
    "wof:name":"Banque Populaire C\u00f4te D'azur",
    "wof:placetype":"venue"
},
  "geometry": {"coordinates":[7.152253,43.662529],"type":"Point"}
}