{
  "type": "Feature",
  "properties": {
    "addr:full":"B.P. 1 Senarpont^^76340 Hodeng au Bosc Haute Normandie 76140",
    "addr:postcode":"76140",
    "addr:street":"B.P. 1 Senarpont^^76340 Hodeng Au Bosc Haute Normandie",
    "iso:country":"FR",
    "sg:address":"B.P. 1",
    "sg:city":"Senarpont^^76340 Hodeng au Bosc",
    "sg:orig_category":"Non-Classified Establishments",
    "sg:phone":"+33 2 32 97 50 00",
    "sg:postcode":"76140",
    "sg:province":"Haute Normandie",
    "wof:name":"Verreries Du Courval S.a.",
    "wof:placetype":"venue"
},
  "geometry": {"coordinates":[1.593718,49.821468],"type":"Point"}
}