{
  "type": "Feature",
  "properties": {
    "iso:country":"FR",
    "sg:address":"2 Ave Aristide Briand; S. Maxime; 83120",
    "sg:classifiers":[
        {
            "category":"Banks & Credit Unions",
            "subcategory":"Bank",
            "type":"Services"
        }
    ],
    "sg:phone":"+33 4 94 96 32 61",
    "sg:province":"Basse Normandie",
    "wof:name":"Banque Populaire, De La C\u00f4te D'azur",
    "wof:placetype":"venue"
},
  "geometry": {"coordinates":[-111.03632399999999,43.012043],"type":"Point"}
}