{
  "type": "Feature",
  "properties": {
    "addr:full":"120, Chemin des Granges Bains, 88400 G\u00e9rardmer Lorraine",
    "addr:housenumber":"120",
    "addr:postcode":"88400",
    "addr:street":"Chemin Des Granges",
    "iso:country":"FR",
    "sg:address":"120, Chemin des Granges Bains, 88400 G\u00e9rardmer",
    "sg:orig_category":"Unclassifiable Establishments",
    "sg:phone":"+33 3 29 63 04 74",
    "sg:province":"Lorraine",
    "wof:name":"Blanchiment Des Hautes Vosges S.a.",
    "wof:placetype":"venue"
},
  "geometry": {"coordinates":[6.810343,48.069874],"type":"Point"}
}