{
  "type": "Feature",
  "properties": {
    "iso:country":"FR",
    "sg:address":"14 Rue Marcel Pagnol 69200 V\u00e9nissieux",
    "sg:classifiers":[
        {
            "category":"Retail",
            "subcategory":"Event Space",
            "type":"Services"
        }
    ],
    "sg:phone":"+33 4 72 78 45 45",
    "sg:postcode":"69200",
    "sg:province":"Rhone-Alpes",
    "sg:tags":[
        "product",
        "transport",
        "road",
        "miscellaneous"
    ],
    "wof:name":"Compagnie G\u00c9n\u00c9rale De Pompes Fun\u00c8bres (afm)",
    "wof:placetype":"venue"
},
  "geometry": {"coordinates":[4.889013,45.713734],"type":"Point"}
}