{
  "type": "Feature",
  "properties": {
    "addr:full":"B.P. 13, 47450 Colayrac Saint Cirq C\u00e9dex^^Chemin de Rabanel, 47450 Colayrac Saint Cirq Colayrac-Saint-Cirq Aquitaine 47450",
    "addr:postcode":"47450;47450;47450",
    "addr:street":"B.P. 13;Rabanel",
    "iso:country":"FR",
    "sg:address":"B.P. 13, 47450 Colayrac Saint Cirq C\u00e9dex^^Chemin de Rabanel, 47450 Colayrac Saint Cirq",
    "sg:city":"Colayrac-Saint-Cirq",
    "sg:orig_category":"Non-Classified Establishments",
    "sg:phone":"+33 5 53 67 60 33",
    "sg:postcode":"47450",
    "sg:province":"Aquitaine",
    "wof:name":"Shannon Rewinds France S.a.r.l.",
    "wof:placetype":"venue"
},
  "geometry": {"coordinates":[0.55394,44.221859],"type":"Point"}
}