{
  "type": "Feature",
  "properties": {
    "addr:full":"Zi 64121 Montardon Montardon Aquitaine 64121",
    "addr:postcode":"64121;64121",
    "addr:street":"Zi",
    "iso:country":"FR",
    "sg:address":"Zi 64121 Montardon",
    "sg:city":"Montardon",
    "sg:classifiers":[
        {
            "category":"Professional",
            "type":"Services"
        }
    ],
    "sg:phone":"+33 5 59 33 15 99",
    "sg:postcode":"64121",
    "sg:province":"Aquitaine",
    "sg:tags":[
        "transport",
        "road"
    ],
    "wof:name":"Verdy Sa",
    "wof:placetype":"venue"
},
  "geometry": {"coordinates":[-0.380334,43.376003],"type":"Point"}
}