{
  "type": "Feature",
  "properties": {
    "iso:country":"FR",
    "sg:address":"Rue du Ch\u00eane Vert - ZI - Parc d'Activit\u00e9",
    "sg:city":"Saint Barth\u00e9l\u00e9my d'Anjou",
    "sg:orig_category":"Non-Classified Establishments",
    "sg:phone":"+33 2 41 43 60 20",
    "sg:postcode":"49124",
    "sg:province":"Pays de Loire",
    "wof:name":"Anjou Pompes B\u00e9cot S.a.",
    "wof:placetype":"venue"
},
  "geometry": {"coordinates":[-1.334822,47.273693],"type":"Point"}
}