{
  "type": "Feature",
  "properties": {
    "addr:full":"B.P. 80014, 57801 Freyming Merlebach C\u00e9dex^^Rue Jean Gobert - Puits Cuvelette, 57800 Freyming Merleb Lorraine",
    "addr:housenumber":"57801",
    "addr:postcode":"57800",
    "addr:street":"Freyming Merlebach;Merleb",
    "iso:country":"FR",
    "sg:address":"B.P. 80014, 57801 Freyming Merlebach C\u00e9dex^^Rue Jean Gobert - Puits Cuvelette, 57800 Freyming Merleb",
    "sg:orig_category":"Non-Classified Establishments",
    "sg:phone":"+33 3 87 81 46 21",
    "sg:province":"Lorraine",
    "wof:name":"S.a.r.e.c. S.a.",
    "wof:placetype":"venue"
},
  "geometry": {"coordinates":[6.793515,49.143681],"type":"Point"}
}