{
  "type": "Feature",
  "properties": {
    "iso:country":"FR",
    "sg:address":"Rte de Montgaillard",
    "sg:city":"Montgaillard",
    "sg:orig_category":"Unclassifiable Establishments",
    "sg:phone":"+33 5 58 76 16 08",
    "sg:postcode":"40500",
    "sg:province":"Aquitaine",
    "wof:name":"A.l.s. S.a. - Aquitaine L\u00e9gumes Surgel\u00e9s",
    "wof:placetype":"venue"
},
  "geometry": {"coordinates":[-0.521911,43.692204],"type":"Point"}
}