{
  "type": "Feature",
  "properties": {
    "addr:full":"13 Rue Karl Probst 14000 Caen Caen Basse Normandie 14000",
    "addr:housenumber":"13",
    "addr:postcode":"14000;14000",
    "addr:street":"Rue Karl Probst",
    "iso:country":"FR",
    "sg:address":"13 Rue Karl Probst 14000 Caen",
    "sg:city":"Caen",
    "sg:classifiers":[
        {
            "category":"Manufacturing",
            "subcategory":"Tools & Machinery",
            "type":"Manufacturing & Wholesale Goods"
        }
    ],
    "sg:phone":"+33 2 31 95 21 00",
    "sg:postcode":"14000",
    "sg:province":"Basse Normandie",
    "sg:tags":[
        "environment",
        "equipment",
        "-"
    ],
    "wof:name":"Sogeti",
    "wof:placetype":"venue"
},
  "geometry": {"coordinates":[-0.389818,49.200169],"type":"Point"}
}