{
  "type": "Feature",
  "properties": {
    "iso:country":"FR",
    "sg:address":"1 place Renault 92500 Rueil Malmaison",
    "sg:classifiers":[
        {
            "category":"Professional",
            "subcategory":"Testing Lab",
            "type":"Services"
        }
    ],
    "sg:phone":"+33 1 41 29 40 00",
    "sg:postcode":"92500",
    "sg:province":"Ile de France",
    "sg:tags":[
        "laboratory"
    ],
    "wof:name":"Zeneca Pharma Sa",
    "wof:placetype":"venue"
},
  "geometry": {"coordinates":[2.189432,48.858528],"type":"Point"}
}