{
  "type": "Feature",
  "properties": {
    "addr:full":"Av. Georges Barres M\u00e9rignac Aquitaine 33700",
    "addr:postcode":"33700",
    "addr:street":"Av. Georges Barres",
    "iso:country":"FR",
    "sg:address":"Av. Georges Barres",
    "sg:city":"M\u00e9rignac",
    "sg:orig_category":"Unclassifiable Establishments",
    "sg:phone":"+33 5 56 34 10 21",
    "sg:postcode":"33700",
    "sg:province":"Aquitaine",
    "wof:name":"A.t.e. - A\u00e9ro Technique Espace",
    "wof:placetype":"venue"
},
  "geometry": {"coordinates":[-0.69984,44.84568],"type":"Point"}
}