{
  "type": "Feature",
  "properties": {
    "iso:country":"FR",
    "sg:address":"B.P. 0716, 53007 Laval C\u00e9dex^^343, Rue de Bretagne, 53000 Laval",
    "sg:orig_category":"Non-Classified Establishments",
    "sg:phone":"+33 2 43 91 48 48",
    "sg:province":"Pays de Loire",
    "wof:name":"Horticoles Sauv\u00e9 S.a.r.l.",
    "wof:placetype":"venue"
},
  "geometry": {"coordinates":[-0.756451,48.036293],"type":"Point"}
}