{
  "type": "Feature",
  "properties": {
    "addr:full":"B.P. 19, 80220 Buigny les Gamaches^^Rue du Grand Selves, 80220 Buigny les Gamaches Picardie",
    "addr:postcode":"80220;80220",
    "addr:street":"B.P. 19;Du Grand Selves",
    "iso:country":"FR",
    "sg:address":"B.P. 19, 80220 Buigny les Gamaches^^Rue du Grand Selves, 80220 Buigny les Gamaches",
    "sg:orig_category":"Non-Classified Establishments",
    "sg:phone":"+33 3 22 30 92 06",
    "sg:province":"Picardie",
    "wof:name":"Picardie Palettes S.a.",
    "wof:placetype":"venue"
},
  "geometry": {"coordinates":[1.556783,49.986042],"type":"Point"}
}