{
  "type": "Feature",
  "properties": {
    "iso:country":"FR",
    "sg:address":"24 Boulevard des Alliis; BP 199; CALAIS; 62104 CEDEX",
    "sg:classifiers":[
        {
            "category":"Shopping",
            "subcategory":"Computers & Home Electronics",
            "type":"Retail Goods"
        }
    ],
    "sg:phone":"+33 3 21 46 00 00",
    "sg:province":"Centre",
    "sg:tags":[
        "chamber",
        "commerce"
    ],
    "wof:name":"Chambre De Commerce De Calais",
    "wof:placetype":"venue"
},
  "geometry": {"coordinates":[1.85214,50.957859],"type":"Point"}
}