{
  "type": "Feature",
  "properties": {
    "addr:full":"35, Rue des Fr\u00e8res Martel, 59247 F\u00e9chain Nord Pas-de-Calais",
    "addr:housenumber":"35",
    "addr:postcode":"59247",
    "addr:street":"Rue Des Fre\u0300Res Martel",
    "iso:country":"FR",
    "sg:address":"35, Rue des Fr\u00e8res Martel, 59247 F\u00e9chain",
    "sg:orig_category":"Unclassifiable Establishments",
    "sg:phone":"+33 3 27 95 75 55",
    "sg:province":"Nord Pas-de-Calais",
    "wof:name":"Sofedis S.a.r.l.",
    "wof:placetype":"venue"
},
  "geometry": {"coordinates":[3.213825,50.265869],"type":"Point"}
}