{
  "type": "Feature",
  "properties": {
    "addr:full":"B.P. 3 Samer Nord Pas-de-Calais 62830",
    "addr:postcode":"62830",
    "addr:street":"B.P. 3 Samer Nord",
    "iso:country":"FR",
    "sg:address":"B.P. 3",
    "sg:city":"Samer",
    "sg:orig_category":"Non-Classified Establishments",
    "sg:phone":"+33 3 21 83 12 39",
    "sg:postcode":"62830",
    "sg:province":"Nord Pas-de-Calais",
    "wof:name":"Sp\u00e9citubes S.a.",
    "wof:placetype":"venue"
},
  "geometry": {"coordinates":[1.742815,50.635666],"type":"Point"}
}