{
  "type": "Feature",
  "properties": {
    "addr:full":"Rue Aricie Caruel 80630 Beauval Picardie 80630",
    "addr:postcode":"80630;80630",
    "addr:street":"Rue Aricie Caruel",
    "iso:country":"FR",
    "sg:address":"Rue Aricie Caruel 80630 Beauval",
    "sg:classifiers":[
        {
            "category":"Autos & Motor Vehicles",
            "subcategory":"Automobile Sales",
            "type":"Retail Goods"
        }
    ],
    "sg:phone":"+33 3 22 32 91 48",
    "sg:postcode":"80630",
    "sg:province":"Picardie",
    "sg:tags":[
        "equipment",
        "industrial",
        "transport"
    ],
    "wof:name":"Etablissements Danel",
    "wof:placetype":"venue"
},
  "geometry": {"coordinates":[2.331235,50.109066],"type":"Point"}
}