{
  "type": "Feature",
  "properties": {
    "addr:full":"8, Rue de Delle, 90140 Bourogne Franche Comt\u00e9",
    "addr:housenumber":"8",
    "addr:postcode":"90140",
    "addr:street":"Rue De Delle;Franche Comte\u0301",
    "iso:country":"FR",
    "sg:address":"8, Rue de Delle, 90140 Bourogne",
    "sg:orig_category":"Non-Classified Establishments",
    "sg:phone":"+33 3 84 27 82 70",
    "sg:province":"Franche Comt\u00e9",
    "wof:name":"Malnati Et Compagnie S.a.r.l.",
    "wof:placetype":"venue"
},
  "geometry": {"coordinates":[6.927265,47.556084],"type":"Point"}
}