{
  "type": "Feature",
  "properties": {
    "addr:full":"17 Avenue De Grammont 76100 Rouen Haute Normandie 76100",
    "addr:housenumber":"17",
    "addr:postcode":"76100;76100",
    "addr:street":"Avenue De Grammont;Haute Normandie",
    "iso:country":"FR",
    "sg:address":"17 Avenue De Grammont 76100 Rouen",
    "sg:classifiers":[
        {
            "category":"Wholesale",
            "subcategory":"Meat",
            "type":"Manufacturing & Wholesale Goods"
        }
    ],
    "sg:phone":"+33 2 35 72 84 91",
    "sg:postcode":"76100",
    "sg:province":"Haute Normandie",
    "sg:tags":[
        "food",
        "cooked",
        "product",
        "related"
    ],
    "wof:name":"Societe Normande D'appro Des Charcutiers (snac)",
    "wof:placetype":"venue"
},
  "geometry": {"coordinates":[1.095345,49.426651],"type":"Point"}
}