{
  "type": "Feature",
  "properties": {
    "iso:country":"FR",
    "sg:address":"B.P. 1186, 76176 Rouen C\u00e9dex^^Av de Bretagne - Immeuble Normandie I, 76100 Rouen",
    "sg:orig_category":"Non-Classified Establishments",
    "sg:phone":"+33 2 35 03 48 60",
    "sg:postcode":"76100",
    "sg:province":"Haute Normandie",
    "wof:name":"Dalkia S.c.a.",
    "wof:placetype":"venue"
},
  "geometry": {"coordinates":[1.0879,49.433601],"type":"Point"}
}