{
  "type": "Feature",
  "properties": {
    "iso:country":"FR",
    "sg:address":"13 Rue Du Bois Galon 94120 Fontenay Sous Bois",
    "sg:classifiers":[
        {
            "category":"Manufacturing",
            "subcategory":"Metals",
            "type":"Manufacturing & Wholesale Goods"
        }
    ],
    "sg:phone":"+33 1 43 94 00 87",
    "sg:postcode":"94120",
    "sg:province":"Ile de France",
    "sg:tags":[
        "metallurgy",
        "metalworking",
        "processing"
    ],
    "wof:name":"Sipm",
    "wof:placetype":"venue"
},
  "geometry": {"coordinates":[2.492981,48.859306],"type":"Point"}
}