{
  "type": "Feature",
  "properties": {
    "addr:full":"25 av des Freres Montgolfier 69680 CHASSIEU Rhone-Alpes 69680",
    "addr:postcode":"69680;69680",
    "addr:street":"25 Av Des Freres Montgolfier",
    "iso:country":"FR",
    "sg:address":"25 av des Freres Montgolfier 69680 CHASSIEU",
    "sg:classifiers":[
        {
            "category":"Utilities",
            "subcategory":"Sewage",
            "type":"Services"
        }
    ],
    "sg:phone":"+33 4 78 90 08 28",
    "sg:postcode":"69680",
    "sg:province":"Rhone-Alpes",
    "sg:tags":[
        "screw",
        "anchor"
    ],
    "wof:name":"Metaplast S.a.",
    "wof:placetype":"venue"
},
  "geometry": {"coordinates":[4.96926,45.726063],"type":"Point"}
}