{
  "type": "Feature",
  "properties": {
    "addr:full":"Les Taillas 43600 Ste Sigolene Les Villettes Auvergne 43600",
    "addr:postcode":"43600;43600",
    "addr:street":"Taillas;Sigolene;Villettes",
    "iso:country":"FR",
    "sg:address":"Les Taillas 43600 Ste Sigolene",
    "sg:city":"Les Villettes",
    "sg:classifiers":[
        {
            "category":"Manufacturing",
            "subcategory":"Textiles",
            "type":"Manufacturing & Wholesale Goods"
        }
    ],
    "sg:phone":"+33 4 71 66 60 47",
    "sg:postcode":"43600",
    "sg:province":"Auvergne",
    "sg:tags":[
        "clothing",
        "accessory"
    ],
    "wof:name":"Etablissements Pierre Quioc",
    "wof:placetype":"venue"
},
  "geometry": {"coordinates":[4.25532,45.25658],"type":"Point"}
}