{
  "type": "Feature",
  "properties": {
    "addr:full":"B.P. 1, 59175 Templemars^^Rue de l'Epinoy - ZI, 59175 Templemars Nord Pas-de-Calais",
    "addr:housenumber":"1",
    "addr:postcode":"59175;59175",
    "addr:street":"B.P.;Zi",
    "iso:country":"FR",
    "sg:address":"B.P. 1, 59175 Templemars^^Rue de l'Epinoy - ZI, 59175 Templemars",
    "sg:orig_category":"Non-Classified Establishments",
    "sg:phone":"+33 3 20 90 42 00",
    "sg:province":"Nord Pas-de-Calais",
    "wof:name":"Parent & Compagnie S.a.",
    "wof:placetype":"venue"
},
  "geometry": {"coordinates":[3.068528,50.567921],"type":"Point"}
}