{
  "type": "Feature",
  "properties": {
    "addr:full":"17 Bis Rue Vimaine 38200 Vienne Rhone-Alpes 38200",
    "addr:housenumber":"17 bis",
    "addr:postcode":"38200;38200",
    "addr:street":"Rue Vimaine",
    "iso:country":"FR",
    "sg:address":"17 Bis Rue Vimaine 38200 Vienne",
    "sg:classifiers":[
        {
            "category":"Professional",
            "subcategory":"Engineering",
            "type":"Services"
        }
    ],
    "sg:phone":"+33 4 74 53 01 78",
    "sg:postcode":"38200",
    "sg:province":"Rhone-Alpes",
    "sg:tags":[
        "machine",
        "-",
        "mechanical"
    ],
    "wof:name":"Novat Et Bey",
    "wof:placetype":"venue"
},
  "geometry": {"coordinates":[4.865231,45.515472],"type":"Point"}
}