{
  "type": "Feature",
  "properties": {
    "addr:full":"15, Cour Bonodine, 26000 Valence Rhone-Alpes 26000",
    "addr:housenumber":"15",
    "addr:postcode":"26000;26000",
    "addr:street":"Cour Bonodine",
    "iso:country":"FR",
    "sg:address":"15, Cour Bonodine, 26000 Valence",
    "sg:orig_category":"Non-Classified Establishments",
    "sg:phone":"+33 4 75 42 41 21",
    "sg:postcode":"26000",
    "sg:province":"Rhone-Alpes",
    "wof:name":"Akita Productions",
    "wof:placetype":"venue"
},
  "geometry": {"coordinates":[4.889246,44.930458],"type":"Point"}
}