{
  "type": "Feature",
  "properties": {
    "addr:full":"Rte d'Auch Orleix Midi Pyr\u00e9n\u00e9es 65800",
    "addr:postcode":"65800",
    "addr:street":"Rte D'Auch",
    "iso:country":"FR",
    "sg:address":"Rte d'Auch",
    "sg:city":"Orleix",
    "sg:orig_category":"Non-Classified Establishments",
    "sg:phone":"+33 5 62 36 65 95",
    "sg:postcode":"65800",
    "sg:province":"Midi Pyr\u00e9n\u00e9es",
    "wof:name":"Oxy M\u00e9ca Pyr\u00e9n\u00e9es S.a.",
    "wof:placetype":"venue"
},
  "geometry": {"coordinates":[0.102902,43.261997],"type":"Point"}
}