{
  "type": "Feature",
  "properties": {
    "iso:country":"FR",
    "sg:address":"8, Impasse aux Ances, 86440 Migne Auxances",
    "sg:orig_category":"Unclassifiable Establishments",
    "sg:phone":"+33 5 49 51 48 23",
    "sg:province":"Poitou-Charentes",
    "wof:name":"Gault Fran\u00e7ois",
    "wof:placetype":"venue"
},
  "geometry": {"coordinates":[0.311651,46.626766],"type":"Point"}
}