{
  "type": "Feature",
  "properties": {
    "addr:full":"21-23 Rue De L'Hospice 34110 Frontignan Languedoc-Roussillon 34110",
    "addr:housenumber":"21-23",
    "addr:postcode":"34110;34110",
    "addr:street":"Rue De L'Hospice",
    "iso:country":"FR",
    "sg:address":"21-23 Rue De L'Hospice 34110 Frontignan",
    "sg:classifiers":[
        {
            "category":"Professional",
            "subcategory":"Business Services",
            "type":"Services"
        }
    ],
    "sg:phone":"+33 4 67 46 66 66",
    "sg:postcode":"34110",
    "sg:province":"Languedoc-Roussillon",
    "sg:tags":[
        "training",
        "advice"
    ],
    "wof:name":"Ogec College Et Ecole Ste-therese",
    "wof:placetype":"venue"
},
  "geometry": {"coordinates":[3.752695,43.447552],"type":"Point"}
}