{
  "type": "Feature",
  "properties": {
    "iso:country":"FR",
    "sg:address":"Impasse Nungesser Et Coli",
    "sg:city":"St Girons",
    "sg:classifiers":[
        {
            "category":"Banks & Credit Unions",
            "subcategory":"Financial Services",
            "type":"Services"
        }
    ],
    "sg:phone":"+33 5 61 66 29 77",
    "sg:postcode":"09200",
    "sg:province":"Midi Pyr\u00e9n\u00e9es",
    "sg:tags":[
        "banking",
        "finance",
        "insurance"
    ],
    "wof:name":"Societe Fiduciaire Nationale Juridique Et Fiscale Fiducial (sofiral)",
    "wof:placetype":"venue"
},
  "geometry": {"coordinates":[1.145151,42.987568],"type":"Point"}
}