{
  "type": "Feature",
  "properties": {
    "iso:country":"FR",
    "sg:address":"282, Av. Andr\u00e9 Lasquin, 74703 Sallanches C\u00e9dex",
    "sg:orig_category":"Non-Classified Establishments",
    "sg:phone":"+33 4 50 58 43 43",
    "sg:province":"Rhone-Alpes",
    "wof:name":"Faire France S.a.r.l.",
    "wof:placetype":"venue"
},
  "geometry": {"coordinates":[6.638858,45.941628],"type":"Point"}
}