{
  "type": "Feature",
  "properties": {
    "iso:country":"FR",
    "sg:address":"Le Bourg 24190 ST GERMAIN DU SALEMBRE",
    "sg:city":"Chant\u00e9rac",
    "sg:classifiers":[
        {
            "category":"Shopping",
            "subcategory":"Shoes",
            "type":"Retail Goods"
        }
    ],
    "sg:phone":"+33 5 53 80 84 00",
    "sg:postcode":"24190",
    "sg:province":"Aquitaine",
    "sg:tags":[
        "children's"
    ],
    "wof:name":"Aster Chaussures Sa",
    "wof:placetype":"venue"
},
  "geometry": {"coordinates":[0.47692,45.051495],"type":"Point"}
}