{
  "type": "Feature",
  "properties": {
    "iso:country":"FR",
    "sg:address":"Zac",
    "sg:city":"Plabennec",
    "sg:classifiers":[
        {
            "category":"Home & Garden",
            "subcategory":"Furniture",
            "type":"Retail Goods"
        }
    ],
    "sg:phone":"+33 2 98 40 15 15",
    "sg:postcode":"29860",
    "sg:province":"Bretagne",
    "sg:tags":[
        "household",
        "wood"
    ],
    "wof:name":"Somatex Sa",
    "wof:placetype":"venue"
},
  "geometry": {"coordinates":[-4.373429,48.471745],"type":"Point"}
}