{
  "type": "Feature",
  "properties": {
    "addr:full":"4 rue de la R\u00e9publique; Ile Bouchard Centre",
    "addr:housenumber":"4",
    "addr:street":"Rue De La Re\u0301Publique;Bouchard",
    "iso:country":"FR",
    "sg:address":"4 rue de la R\u00e9publique; Ile Bouchard",
    "sg:classifiers":[
        {
            "category":"Banks & Credit Unions",
            "subcategory":"Bank",
            "type":"Services"
        }
    ],
    "sg:phone":"+33 3347585388",
    "sg:province":"Centre",
    "wof:name":"Banque Populaire Val De France",
    "wof:placetype":"venue"
},
  "geometry": {"coordinates":[0.424153,47.118145],"type":"Point"}
}