{
  "type": "Feature",
  "properties": {
    "addr:full":"Zi Pommenauque 50500 Carentan Carentan Basse Normandie 50500",
    "addr:postcode":"50500;50500",
    "iso:country":"FR",
    "sg:address":"Zi Pommenauque 50500 Carentan",
    "sg:city":"Carentan",
    "sg:classifiers":[
        {
            "category":"Professional",
            "type":"Services"
        }
    ],
    "sg:phone":"+33 2 33 71 67 16",
    "sg:postcode":"50500",
    "sg:province":"Basse Normandie",
    "sg:tags":[
        "transport",
        "road"
    ],
    "wof:name":"Sarl Transports Deshayes",
    "wof:placetype":"venue"
},
  "geometry": {"coordinates":[-1.247078,49.30291],"type":"Point"}
}