{
  "type": "Feature",
  "properties": {
    "addr:full":"ZAC Entraigues Embrun Provence-Alpes-C\u00f4te d'Azur 05200",
    "addr:postcode":"05200",
    "addr:street":"Zac Entraigues Embrun",
    "iso:country":"FR",
    "sg:address":"ZAC Entraigues",
    "sg:city":"Embrun",
    "sg:orig_category":"Non-Classified Establishments",
    "sg:phone":"+33 4 92 43 21 90",
    "sg:postcode":"05200",
    "sg:province":"Provence-Alpes-C\u00f4te d'Azur",
    "wof:name":"Altech International S.a.r.l.",
    "wof:placetype":"venue"
},
  "geometry": {"coordinates":[6.496019,44.565468],"type":"Point"}
}