{
  "type": "Feature",
  "properties": {
    "iso:country":"FR",
    "sg:address":"ZAC du Porche",
    "sg:city":"Plaimpied Givaudins",
    "sg:orig_category":"Non-Classified Establishments",
    "sg:phone":"+33 2 48 50 17 78",
    "sg:postcode":"18340",
    "sg:province":"Centre",
    "wof:name":"Cagnot Christophe",
    "wof:placetype":"venue"
},
  "geometry": {"coordinates":[2.453301,46.997719],"type":"Point"}
}