{
  "type": "Feature",
  "properties": {
    "addr:full":"202 Avenue De Colmar Centre D'Affaires Le Mathi Strasbourg Alsace 67100",
    "addr:housenumber":"202",
    "addr:postcode":"67100",
    "addr:street":"Avenue De Colmar",
    "iso:country":"FR",
    "sg:address":"202 Avenue De Colmar Centre D'Affaires Le Mathi",
    "sg:city":"Strasbourg",
    "sg:classifiers":[
        {
            "category":"Banks & Credit Unions",
            "subcategory":"Financial Services",
            "type":"Services"
        }
    ],
    "sg:phone":"+33 3 88 43 02 20",
    "sg:postcode":"67100",
    "sg:province":"Alsace",
    "sg:tags":[
        "banking",
        "finance",
        "insurance"
    ],
    "wof:name":"La Mondiale",
    "wof:placetype":"venue"
},
  "geometry": {"coordinates":[7.747819,48.557816],"type":"Point"}
}