{
  "type": "Feature",
  "properties": {
    "addr:full":"40 rue Vladimir Jankelevitch 77184 Emerainville Ile de France",
    "addr:housenumber":"40",
    "addr:postcode":"77184",
    "addr:street":"Rue Vladimir Jankelevitch;Ile De France",
    "iso:country":"FR",
    "sg:address":"40 rue Vladimir Jankelevitch 77184 Emerainville",
    "sg:classifiers":[
        {
            "category":"Shopping",
            "subcategory":"Stationery & Office Supplies",
            "type":"Retail Goods"
        }
    ],
    "sg:phone":"+33 1 64 61 61 00",
    "sg:province":"Ile de France",
    "wof:name":"Sprint Paris Sarl",
    "wof:placetype":"venue"
},
  "geometry": {"coordinates":[2.586605,48.829418],"type":"Point"}
}