{
  "type": "Feature",
  "properties": {
    "iso:country":"FR",
    "sg:address":"40 rue Vladimir Jankelevitch 77184 Emerainville",
    "sg:classifiers":[
        {
            "category":"Shopping",
            "subcategory":"Stationery & Office Supplies",
            "type":"Retail Goods"
        }
    ],
    "sg:phone":"+33 1 64 61 61 00",
    "sg:province":"Ile de France",
    "wof:name":"Sprint Paris Sarl",
    "wof:placetype":"venue"
},
  "geometry": {"coordinates":[2.586605,48.829418],"type":"Point"}
}