{
  "type": "Feature",
  "properties": {
    "addr:full":"92795 Issy les Moulineaux C\u00e9dex^^14, Bd des Fr\u00e8res Voisin, 92130 Issy les Moulineaux Ile de France 92130",
    "addr:housenumber":"92795",
    "addr:postcode":"92130;92130",
    "addr:street":"Issy;Bd Des Fre\u0300Res Voisin",
    "iso:country":"FR",
    "sg:address":"92795 Issy les Moulineaux C\u00e9dex^^14, Bd des Fr\u00e8res Voisin, 92130 Issy les Moulineaux",
    "sg:orig_category":"Non-Classified Establishments",
    "sg:phone":"+33 1 46 48 13 98",
    "sg:postcode":"92130",
    "sg:province":"Ile de France",
    "wof:name":"Chronopost International S.a.",
    "wof:placetype":"venue"
},
  "geometry": {"coordinates":[2.251248,48.821148],"type":"Point"}
}