{
  "type": "Feature",
  "properties": {
    "addr:full":"12, Rue des Palis, 77140 Nemours Ile de France",
    "addr:housenumber":"12",
    "addr:postcode":"77140",
    "addr:street":"Rue Des Palis;Ile De France",
    "iso:country":"FR",
    "sg:address":"12, Rue des Palis, 77140 Nemours",
    "sg:orig_category":"Non-Classified Establishments",
    "sg:phone":"+33 1 64 28 27 45",
    "sg:province":"Ile de France",
    "wof:name":"Lewis Industrie S.a.",
    "wof:placetype":"venue"
},
  "geometry": {"coordinates":[2.71752,48.26466],"type":"Point"}
}