{
  "type": "Feature",
  "properties": {
    "iso:country":"FR",
    "sg:address":"B.P. 9402, 73094 Chamb\u00e9ry C\u00e9dex 9^^153, Rue Aristide Berg\u00e8s, 73000 Chamb\u00e9ry",
    "sg:orig_category":"Non-Classified Establishments",
    "sg:phone":"+33 4 79 62 06 73",
    "sg:postcode":"73000",
    "sg:province":"Rhone-Alpes",
    "wof:name":"Savoy Decoup S.a.",
    "wof:placetype":"venue"
},
  "geometry": {"coordinates":[5.90839,45.538151],"type":"Point"}
}