{
  "type": "Feature",
  "properties": {
    "addr:full":"19-29 R Du Capitaine Guynemer Berkeley Building 92903 Paris La D\u00e9fense Centre",
    "addr:housenumber":"19-29",
    "addr:postcode":"92903",
    "addr:street":"R Du Capitaine Guynemer",
    "iso:country":"FR",
    "sg:address":"19-29 R Du Capitaine Guynemer Berkeley Building 92903 Paris La D\u00e9fense",
    "sg:classifiers":[
        {
            "category":"Health Services",
            "subcategory":"Medical Lab",
            "type":"Services"
        }
    ],
    "sg:phone":"+33 1 42 91 21 00",
    "sg:province":"Centre",
    "sg:tags":[
        "chemical",
        "pharmaceutical",
        "pharmacy"
    ],
    "wof:name":"Dade Behring Sa",
    "wof:placetype":"venue"
},
  "geometry": {"coordinates":[2.24119,48.888939],"type":"Point"}
}