{
  "type": "Feature",
  "properties": {
    "addr:full":"13, Av. des Alpes, 74300 Cluses Rhone-Alpes",
    "addr:postcode":"74300",
    "addr:street":"13 Av. Des Alpes",
    "iso:country":"FR",
    "sg:address":"13, Av. des Alpes, 74300 Cluses",
    "sg:orig_category":"Non-Classified Establishments",
    "sg:phone":"+33 4 50 98 27 13",
    "sg:province":"Rhone-Alpes",
    "wof:name":"Sd 2 M S.a.r.l. - Soci\u00e9t\u00e9 De D\u00e9colletage Maurice Molliex",
    "wof:placetype":"venue"
},
  "geometry": {"coordinates":[6.579451,46.066486],"type":"Point"}
}