{
  "type": "Feature",
  "properties": {
    "addr:full":"Rte de l'Argenti\u00e8re - Pr\u00e9 Chenavay Sainte Foy l'Argenti\u00e8re Rhone-Alpes 69610",
    "addr:postcode":"69610",
    "addr:street":"Rte De L'Argentie \u0300Re Pre\u0301 Chenavay;Rhone-Alpes",
    "iso:country":"FR",
    "sg:address":"Rte de l'Argenti\u00e8re - Pr\u00e9 Chenavay",
    "sg:city":"Sainte Foy l'Argenti\u00e8re",
    "sg:orig_category":"Unclassifiable Establishments",
    "sg:phone":"+33 4 74 70 04 18",
    "sg:postcode":"69610",
    "sg:province":"Rhone-Alpes",
    "wof:name":"Etablissements Ogier M. S.a.",
    "wof:placetype":"venue"
},
  "geometry": {"coordinates":[4.469997,45.703117],"type":"Point"}
}