{
  "type": "Feature",
  "properties": {
    "iso:country":"FR",
    "sg:address":"10 Rue Antoine Coet 59119 Waziers",
    "sg:orig_category":"Miscellaneous Products",
    "sg:phone":"+33 3 27 98 07 76",
    "sg:postcode":"59119",
    "sg:province":"Nord Pas-de-Calais",
    "wof:name":"Etablissements Gerard Doisy",
    "wof:placetype":"venue"
},
  "geometry": {"coordinates":[3.115514,50.386665],"type":"Point"}
}