{
  "type": "Feature",
  "properties": {
    "addr:full":"Prairie de Geniquet 33920 Saugon Saugon Aquitaine 33920",
    "addr:postcode":"33920;33920",
    "addr:street":"Prairie",
    "iso:country":"FR",
    "sg:address":"Prairie de Geniquet 33920 Saugon",
    "sg:city":"Saugon",
    "sg:orig_category":"Non-Classified Establishments",
    "sg:phone":"+33 5 57 42 51 29",
    "sg:postcode":"33920",
    "sg:province":"Aquitaine",
    "wof:name":"Etablissements Raymond Chaumet S.a.",
    "wof:placetype":"venue"
},
  "geometry": {"coordinates":[-0.505143,45.175419],"type":"Point"}
}