{
  "type": "Feature",
  "properties": {
    "iso:country":"FR",
    "sg:address":"Rte De Pont Scorff 29300 Quimperl\u00e9",
    "sg:city":"Quimperl\u00e9",
    "sg:classifiers":[
        {
            "category":"Autos & Motor Vehicles",
            "subcategory":"Automobile Sales",
            "type":"Retail Goods"
        }
    ],
    "sg:phone":"+33 2 98 96 07 93",
    "sg:postcode":"29300",
    "sg:province":"Bretagne",
    "sg:tags":[
        "equipment",
        "motor-cars",
        "transport"
    ],
    "wof:name":"Laita Automobiles Sa",
    "wof:placetype":"venue"
},
  "geometry": {"coordinates":[-3.461656,47.859921],"type":"Point"}
}