{
  "type": "Feature",
  "properties": {
    "addr:full":"Bd de Seattle Nantes Pays de Loire 44300",
    "addr:postcode":"44300",
    "addr:street":"Bd De",
    "iso:country":"FR",
    "sg:address":"Bd de Seattle",
    "sg:city":"Nantes",
    "sg:orig_category":"Unclassifiable Establishments",
    "sg:phone":"+33 2 40 49 03 85",
    "sg:postcode":"44300",
    "sg:province":"Pays de Loire",
    "wof:name":"S. Et C. S.a. - Sort Et Chasle",
    "wof:placetype":"venue"
},
  "geometry": {"coordinates":[-1.517172,47.221386],"type":"Point"}
}