{
  "type": "Feature",
  "properties": {
    "addr:full":"B.P. 49, 92174 Vanves C\u00e9dex^^40, Rue Jean Bleuzen, 92170 Vanves Ile de France",
    "addr:postcode":"92174;92170;ile",
    "addr:street":"B.P. 49;Rue Jean Bleuzen",
    "iso:country":"FR",
    "sg:address":"B.P. 49, 92174 Vanves C\u00e9dex^^40, Rue Jean Bleuzen, 92170 Vanves",
    "sg:orig_category":"Non-Classified Establishments",
    "sg:phone":"+33 1 40 93 66 00",
    "sg:province":"Ile de France",
    "wof:name":"S.n.r. Roulements S.a.",
    "wof:placetype":"venue"
},
  "geometry": {"coordinates":[2.291016,48.820904],"type":"Point"}
}