{
  "type": "Feature",
  "properties": {
    "addr:full":"7, Rue Cl\u00e9ment Ader, 44980 Sainte Luce sur Loire Pays de Loire",
    "addr:housenumber":"7",
    "addr:postcode":"44980",
    "addr:street":"Rue Cle\u0301Ment Ader;Luce;Loire",
    "iso:country":"FR",
    "sg:address":"7, Rue Cl\u00e9ment Ader, 44980 Sainte Luce sur Loire",
    "sg:orig_category":"Unclassifiable Establishments",
    "sg:phone":"+33 2 40 25 60 54",
    "sg:province":"Pays de Loire",
    "wof:name":"Simop S.a.r.l.",
    "wof:placetype":"venue"
},
  "geometry": {"coordinates":[-1.465043,47.270756],"type":"Point"}
}