{
  "type": "Feature",
  "properties": {
    "addr:full":"Drouillau 33500 N\u00e9ac N\u00e9ac Aquitaine 33500",
    "addr:postcode":"33500;33500",
    "addr:street":"Drouillau",
    "iso:country":"FR",
    "sg:address":"Drouillau 33500 N\u00e9ac",
    "sg:city":"N\u00e9ac",
    "sg:orig_category":"Non-Classified Establishments",
    "sg:phone":"+33 5 57 51 09 61",
    "sg:postcode":"33500",
    "sg:province":"Aquitaine",
    "wof:name":"Ch\u00e2teau Belles Graves S.c.e.a.",
    "wof:placetype":"venue"
},
  "geometry": {"coordinates":[-0.286437,44.884071],"type":"Point"}
}