{
  "type": "Feature",
  "properties": {
    "addr:full":"5, Chemin Dursigny, 78117 Toussus le Noble Ile de France",
    "addr:housenumber":"5",
    "addr:postcode":"78117",
    "addr:street":"Chemin Dursigny",
    "iso:country":"FR",
    "sg:address":"5, Chemin Dursigny, 78117 Toussus le Noble",
    "sg:orig_category":"Unclassifiable Establishments",
    "sg:phone":"+33 1 39 56 78 00",
    "sg:province":"Ile de France",
    "wof:name":"F.i. S.a. - Fran\u00e7aise D'isolation",
    "wof:placetype":"venue"
},
  "geometry": {"coordinates":[2.092255,48.736919],"type":"Point"}
}