{
  "type": "Feature",
  "properties": {
    "iso:country":"FR",
    "sg:address":"6",
    "sg:city":"Paul Henri Spaak 60000 Beauvais",
    "sg:classifiers":[
        {
            "category":"Professional",
            "subcategory":"Business Services",
            "type":"Services"
        }
    ],
    "sg:phone":"+33 3 44 12 37 80",
    "sg:postcode":"60000",
    "sg:province":"Picardie",
    "sg:tags":[
        "training",
        "advice"
    ],
    "wof:name":"Cfai Sifor Oise",
    "wof:placetype":"venue"
},
  "geometry": {"coordinates":[2.099116,49.451046],"type":"Point"}
}