{
  "type": "Feature",
  "properties": {
    "iso:country":"FR",
    "sg:address":"173 Rue Du Grand Gigognan Zi De Courtine 84000 Avignon",
    "sg:classifiers":[
        {
            "category":"Banks & Credit Unions",
            "subcategory":"Investment Brokerage",
            "type":"Services"
        }
    ],
    "sg:phone":"+33 4 90 85 40 08",
    "sg:province":"Lorraine",
    "sg:tags":[
        "-",
        "transport",
        "related"
    ],
    "wof:name":"Sud Transport",
    "wof:placetype":"venue"
},
  "geometry": {"coordinates":[4.806015,43.948753],"type":"Point"}
}