{
  "type": "Feature",
  "properties": {
    "addr:full":"92213 Saint Cloud C\u00e9dex^^368, Bureaux de la Colline, 92210 Saint Cloud Ile de France",
    "addr:housenumber":"92213",
    "addr:postcode":"92210",
    "addr:street":"Saint;Ce\u0301Dex^^368;La Colline",
    "iso:country":"FR",
    "sg:address":"92213 Saint Cloud C\u00e9dex^^368, Bureaux de la Colline, 92210 Saint Cloud",
    "sg:orig_category":"Non-Classified Establishments",
    "sg:phone":"+33 1 55 39 08 00",
    "sg:province":"Ile de France",
    "wof:name":"Sysium S.a.r.l.",
    "wof:placetype":"venue"
},
  "geometry": {"coordinates":[2.22036,48.84441],"type":"Point"}
}