{
  "type": "Feature",
  "properties": {
    "iso:country":"FR",
    "sg:address":"189, Rue d'Aubervilliers - Voie D - Porte 44 \u00e0 50, 75018 Paris",
    "sg:orig_category":"Unclassifiable Establishments",
    "sg:phone":"+33 1 40 05 59 59",
    "sg:province":"Ile de France",
    "wof:name":"Imprimerie De Chabrol S.a.r.l.",
    "wof:placetype":"venue"
},
  "geometry": {"coordinates":[2.366598,48.886738],"type":"Point"}
}