{
  "type": "Feature",
  "properties": {
    "addr:full":"189, Rue d'Aubervilliers - Voie D - Porte 44 \u00e0 50, 75018 Paris Ile de France",
    "addr:housenumber":"189;44 a\u0300 50",
    "addr:postcode":"75018",
    "addr:street":"Rue D'Aubervilliers Voie D Porte",
    "iso:country":"FR",
    "sg:address":"189, Rue d'Aubervilliers - Voie D - Porte 44 \u00e0 50, 75018 Paris",
    "sg:orig_category":"Unclassifiable Establishments",
    "sg:phone":"+33 1 40 05 59 59",
    "sg:province":"Ile de France",
    "wof:name":"Imprimerie De Chabrol S.a.r.l.",
    "wof:placetype":"venue"
},
  "geometry": {"coordinates":[2.366598,48.886738],"type":"Point"}
}