{
  "type": "Feature",
  "properties": {
    "addr:full":"34, Rue du Docteur Prouff, 29600 Morlaix Morlaix Bretagne 29600",
    "addr:housenumber":"34",
    "addr:postcode":"29600;29600",
    "addr:street":"Rue Du Docteur Prouff",
    "iso:country":"FR",
    "sg:address":"34, Rue du Docteur Prouff, 29600 Morlaix",
    "sg:city":"Morlaix",
    "sg:orig_category":"Non-Classified Establishments",
    "sg:phone":"+33 2 98 88 02 40",
    "sg:postcode":"29600",
    "sg:province":"Bretagne",
    "wof:name":"Imprimerie De Bretagne S.a.r.l.",
    "wof:placetype":"venue"
},
  "geometry": {"coordinates":[-3.836799,48.576435],"type":"Point"}
}