{
  "type": "Feature",
  "properties": {
    "addr:full":"3 Rue Des Jardins 68160 Ste Marie Aux Mines Sainte-Croix-aux-Mines Alsace 68160",
    "addr:housenumber":"3",
    "addr:postcode":"68160;68160",
    "addr:street":"Rue Des Jardins;Aux Mines",
    "iso:country":"FR",
    "sg:address":"3 Rue Des Jardins 68160 Ste Marie Aux Mines",
    "sg:city":"Sainte-Croix-aux-Mines",
    "sg:classifiers":[
        {
            "category":"Building & Trades",
            "subcategory":"Construction",
            "type":"Services"
        }
    ],
    "sg:phone":"+33 3 89 58 70 75",
    "sg:postcode":"68160",
    "sg:province":"Alsace",
    "sg:tags":[
        "work",
        "public"
    ],
    "wof:name":"Societe D'exploitation Des Etss Alfred Meyer Et Fils",
    "wof:placetype":"venue"
},
  "geometry": {"coordinates":[7.1834,48.246616],"type":"Point"}
}