{
  "type": "Feature",
  "properties": {
    "iso:country":"FR",
    "sg:address":"86 boulevard Chanzy 62200 Boulogne sur Mer",
    "sg:orig_category":"Slaughter-Houses, Abattoirs",
    "sg:phone":"+33 3 21 91 14 03",
    "sg:province":"Nord Pas-de-Calais",
    "wof:name":"Etablissements Convert S.a.",
    "wof:placetype":"venue"
},
  "geometry": {"coordinates":[1.605592,50.71207],"type":"Point"}
}