{
  "type": "Feature",
  "properties": {
    "addr:full":"14, Rue Gambetta, 54152 Briey Lorraine",
    "addr:housenumber":"14",
    "addr:postcode":"54152",
    "addr:street":"Rue Gambetta",
    "iso:country":"FR",
    "sg:address":"14, Rue Gambetta, 54152 Briey",
    "sg:orig_category":"Unclassifiable Establishments",
    "sg:phone":"+33 3 82 47 15 90",
    "sg:province":"Lorraine",
    "wof:name":"Caldaroni S.a.r.l.",
    "wof:placetype":"venue"
},
  "geometry": {"coordinates":[5.943441,49.241447],"type":"Point"}
}