{
  "type": "Feature",
  "properties": {
    "iso:country":"FR",
    "sg:address":"9, Rue du Ch\u00e2teau, 68640 Waldighoffen",
    "sg:city":"Muespach",
    "sg:orig_category":"Unclassifiable Establishments",
    "sg:phone":"+33 3 89 07 93 07",
    "sg:postcode":"68640",
    "sg:province":"Alsace",
    "wof:name":"Jet Plast S.a.",
    "wof:placetype":"venue"
},
  "geometry": {"coordinates":[7.316683,47.54884],"type":"Point"}
}