{
  "type": "Feature",
  "properties": {
    "iso:country":"FR",
    "sg:address":"1, Coutreau, 33141 Saillans",
    "sg:city":"Saillans",
    "sg:orig_category":"Unclassifiable Establishments",
    "sg:phone":"+33 5 57 84 32 05",
    "sg:postcode":"33141",
    "sg:province":"Aquitaine",
    "wof:name":"Ch\u00e2teau De La Vieille Cure S.n.c.",
    "wof:placetype":"venue"
},
  "geometry": {"coordinates":[-0.274804,44.956429],"type":"Point"}
}