{
  "type": "Feature",
  "properties": {
    "iso:country":"FR",
    "sg:address":"Beau Voir 78630 Bures Orgeval",
    "sg:orig_category":"Unclassifiable Establishments",
    "sg:phone":"+33 1 39 75 80 19",
    "sg:province":"Ile de France",
    "wof:name":"Pardos Marketing",
    "wof:placetype":"venue"
},
  "geometry": {"coordinates":[1.936707,48.927883],"type":"Point"}
}