{
  "type": "Feature",
  "properties": {
    "iso:country":"FR",
    "sg:address":"4 Square Villaret De Joyeux 75017 Paris",
    "sg:classifiers":[
        {
            "category":"Professional",
            "subcategory":"Advertising",
            "type":"Services"
        }
    ],
    "sg:phone":"+33 1 58 05 49 00",
    "sg:postcode":"75017",
    "sg:province":"Ile de France",
    "sg:tags":[
        "communication",
        "medium"
    ],
    "wof:name":"Publications Willy Fischer",
    "wof:placetype":"venue"
},
  "geometry": {"coordinates":[2.289443,48.877167],"type":"Point"}
}