{
  "type": "Feature",
  "properties": {
    "addr:full":"143, Grande Rue, 92310 S\u00e8vres Ile de France",
    "addr:housenumber":"143",
    "addr:postcode":"92310",
    "addr:street":"Grande Rue",
    "iso:country":"FR",
    "sg:address":"143, Grande Rue, 92310 S\u00e8vres",
    "sg:orig_category":"Non-Classified Establishments",
    "sg:phone":"+33 1 45 34 87 70",
    "sg:province":"Ile de France",
    "wof:name":"Novasol S.a.",
    "wof:placetype":"venue"
},
  "geometry": {"coordinates":[2.212127,48.824337],"type":"Point"}
}