{
  "type": "Feature",
  "properties": {
    "addr:full":"B.P. 36311, 44263 Nantes C\u00e9dex 02^^30, Bd Vincent Gache, 44100 Nantes Pays de Loire",
    "addr:housenumber":"02;^ 30",
    "addr:postcode":"44263;44100",
    "addr:street":"^;Bd Vincent Gache",
    "iso:country":"FR",
    "sg:address":"B.P. 36311, 44263 Nantes C\u00e9dex 02^^30, Bd Vincent Gache, 44100 Nantes",
    "sg:orig_category":"Non-Classified Establishments",
    "sg:phone":"+33 2 51 72 95 45",
    "sg:province":"Pays de Loire",
    "wof:name":"Promodata S.n.c.",
    "wof:placetype":"venue"
},
  "geometry": {"coordinates":[-1.60436,47.211891],"type":"Point"}
}