{
  "type": "Feature",
  "properties": {
    "addr:full":"B.P. 78, 67016 Strasbourg C\u00e9dex^^12, Rue de la Minoterie, 67016 Strasbourg C\u00e9dex Strasbourg Alsace 67000",
    "addr:postcode":"67016;67016;ce\u0301dex;67000",
    "addr:street":"B.P. 78;Rue De La Minoterie",
    "iso:country":"FR",
    "sg:address":"B.P. 78, 67016 Strasbourg C\u00e9dex^^12, Rue de la Minoterie, 67016 Strasbourg C\u00e9dex",
    "sg:city":"Strasbourg",
    "sg:orig_category":"Non-Classified Establishments",
    "sg:phone":"+33 3 88 45 57 45",
    "sg:postcode":"67000",
    "sg:province":"Alsace",
    "wof:name":"Alsace Armatures S.a.",
    "wof:placetype":"venue"
},
  "geometry": {"coordinates":[7.75193,48.606339],"type":"Point"}
}