{
  "type": "Feature",
  "properties": {
    "addr:full":"Les Pierrelles 26240 Beausemblant Rhone-Alpes 26240",
    "addr:postcode":"26240;26240",
    "iso:country":"FR",
    "sg:address":"Les Pierrelles 26240 Beausemblant",
    "sg:orig_category":"Non-Classified Establishments",
    "sg:phone":"+33 4 75 23 25 26",
    "sg:postcode":"26240",
    "sg:province":"Rhone-Alpes",
    "wof:name":"Ndb S.n.c.",
    "wof:placetype":"venue"
},
  "geometry": {"coordinates":[4.836268,45.159122],"type":"Point"}
}