{
  "type": "Feature",
  "properties": {
    "iso:country":"FR",
    "sg:address":"B.P. 37, 16102 Cognac C\u00e9dex^^20, Rue de la Soci\u00e9t\u00e9 Vinicole, 16100 Cognac",
    "sg:orig_category":"Non-Classified Establishments",
    "sg:phone":"+33 5 45 35 76 00",
    "sg:province":"Poitou-Charentes",
    "wof:name":"R\u00e9my Martin Et Compagnie S.a.",
    "wof:placetype":"venue"
},
  "geometry": {"coordinates":[-0.313384,45.67149],"type":"Point"}
}