{
  "type": "Feature",
  "properties": {
    "iso:country":"FR",
    "sg:address":"Mandelieu Technologie Center Parc D Activite De La Siagne 06210 Mandelieu La Napoule",
    "sg:classifiers":[
        {
            "category":"Autos & Motor Vehicles",
            "subcategory":"Boat Sales",
            "type":"Retail Goods"
        }
    ],
    "sg:phone":"+33 4 92 19 60 60",
    "sg:province":"Haute Normandie",
    "sg:tags":[
        "equipment",
        "transport"
    ],
    "wof:name":"Max Power",
    "wof:placetype":"venue"
},
  "geometry": {"coordinates":[6.93623,43.542488],"type":"Point"}
}