{
  "type": "Feature",
  "properties": {
    "iso:country":"FR",
    "sg:address":"17, Rue de Belfort, 33160 Saint M\u00e9dard en Jalles",
    "sg:city":"Salaunes",
    "sg:orig_category":"Non-Classified Establishments",
    "sg:phone":"+33 5 56 70 13 51",
    "sg:postcode":"33160",
    "sg:province":"Aquitaine",
    "wof:name":"European Data S.a.r.l.",
    "wof:placetype":"venue"
},
  "geometry": {"coordinates":[-0.769189,44.89328],"type":"Point"}
}