{
  "type": "Feature",
  "properties": {
    "addr:full":"Coat Ecuff 29300 Arzano Arzano Bretagne 29300",
    "addr:postcode":"29300;29300",
    "iso:country":"FR",
    "sg:address":"Coat Ecuff 29300 Arzano",
    "sg:city":"Arzano",
    "sg:classifiers":[
        {
            "category":"Food & Beverages",
            "subcategory":"Meat & Fish",
            "type":"Retail Goods"
        }
    ],
    "sg:phone":"+33 2 98 71 70 97",
    "sg:postcode":"29300",
    "sg:province":"Bretagne",
    "sg:tags":[
        "preserve",
        "cooked",
        "product",
        "related"
    ],
    "wof:name":"Eurl Cochon De Coat Ecuff",
    "wof:placetype":"venue"
},
  "geometry": {"coordinates":[-3.434444,47.919605],"type":"Point"}
}