{
  "type": "Feature",
  "properties": {
    "addr:full":"30120 Moli\u00e8res Cavaillac Languedoc-Roussillon",
    "addr:postcode":"30120;cavaillac",
    "iso:country":"FR",
    "sg:address":"30120 Moli\u00e8res Cavaillac",
    "sg:orig_category":"Unclassifiable Establishments",
    "sg:phone":"+33 4 67 81 67 81",
    "sg:province":"Languedoc-Roussillon",
    "wof:name":"Vincent Cadeau S.a.",
    "wof:placetype":"venue"
},
  "geometry": {"coordinates":[3.57821,43.975174],"type":"Point"}
}