{
  "type": "Feature",
  "properties": {
    "iso:country":"FR",
    "sg:address":"B.P. 1, 80480 Pont de Metz^^6, Rue du Ch\u00e2teau, 80480 Pont de Metz",
    "sg:orig_category":"Non-Classified Establishments",
    "sg:phone":"+33 3 22 95 00 66",
    "sg:province":"Picardie",
    "wof:name":"O.p.f. S.a.",
    "wof:placetype":"venue"
},
  "geometry": {"coordinates":[2.243165,49.870926],"type":"Point"}
}