{
  "type": "Feature",
  "properties": {
    "addr:full":"B.P. 20677, 54063 Nancy C\u00e9dex^^101, Av. de la Lib\u00e9ration, 54000 Nancy Lorraine 54000",
    "addr:housenumber":"54063",
    "addr:postcode":"54000;54000",
    "addr:street":"Nancy Ce\u0301Dex^^101 Av. De La Libe\u0301Ration",
    "iso:country":"FR",
    "sg:address":"B.P. 20677, 54063 Nancy C\u00e9dex^^101, Av. de la Lib\u00e9ration, 54000 Nancy",
    "sg:orig_category":"Non-Classified Establishments",
    "sg:phone":"+33 3 83 95 85 85",
    "sg:postcode":"54000",
    "sg:province":"Lorraine",
    "wof:name":"Cap G\u00e9mini S.a.",
    "wof:placetype":"venue"
},
  "geometry": {"coordinates":[6.183405,48.689548],"type":"Point"}
}