{
  "type": "Feature",
  "properties": {
    "iso:country":"FR",
    "sg:address":"7 Rue Champeau Zi St Appolinaire 21060 Dijon Cedex",
    "sg:classifiers":[
        {
            "category":"Professional",
            "subcategory":"Engineering",
            "type":"Services"
        }
    ],
    "sg:phone":"+33 3 80 73 96 50",
    "sg:province":"Champagne",
    "sg:tags":[
        "machine",
        "-",
        "mechanical"
    ],
    "wof:name":"Domoservices Maintenance",
    "wof:placetype":"venue"
},
  "geometry": {"coordinates":[5.04399,47.327209],"type":"Point"}
}