{
  "type": "Feature",
  "properties": {
    "iso:country":"FR",
    "sg:address":"110, Rue Jules Guesde, 92300 Levallois Perret",
    "sg:orig_category":"Unclassifiable Establishments",
    "sg:phone":"+33 1 55 46 98 00",
    "sg:province":"Ile de France",
    "wof:name":"Evidence S.a.",
    "wof:placetype":"venue"
},
  "geometry": {"coordinates":[2.289949,48.896587],"type":"Point"}
}