{
  "type": "Feature",
  "properties": {
    "addr:full":"B.P. 163, 92631 Gennevilliers C\u00e9dex^^Rte du Bassin N\u00b01 - B\u00e2t. A9, 92630 Gennevilliers \u00cele-de-France",
    "addr:housenumber":"b.p. 163;a9",
    "addr:postcode":"92631;92630",
    "iso:country":"FR",
    "sg:address":"B.P. 163, 92631 Gennevilliers C\u00e9dex^^Rte du Bassin N\u00b01 - B\u00e2t. A9, 92630 Gennevilliers",
    "sg:orig_category":"Non-Classified Establishments",
    "sg:phone":"+33 1 47 94 29 83",
    "sg:province":"\u00cele-de-France",
    "wof:name":"Sodimo S.a.r.l. - Soci\u00e9t\u00e9 De Distribution Moderne",
    "wof:placetype":"venue"
},
  "geometry": {"coordinates":[2.29927,48.933479],"type":"Point"}
}