{
  "type": "Feature",
  "properties": {
    "iso:country":"FR",
    "sg:address":"Rue du Pont - ZI du Landry",
    "sg:city":"Boulazac",
    "sg:orig_category":"Unclassifiable Establishments",
    "sg:phone":"+33 5 53 54 24 00",
    "sg:postcode":"24750",
    "sg:province":"Aquitaine",
    "wof:name":"Fenwick S.a.r.l.",
    "wof:placetype":"venue"
},
  "geometry": {"coordinates":[0.789735,45.09977],"type":"Point"}
}