{
  "type": "Feature",
  "properties": {
    "addr:full":"41, Rue Etienne Marcel, 75001 Paris Ile de France",
    "addr:housenumber":"41",
    "addr:postcode":"75001",
    "addr:street":"Rue Etienne Marcel",
    "iso:country":"FR",
    "sg:address":"41, Rue Etienne Marcel, 75001 Paris",
    "sg:orig_category":"Non-Classified Establishments",
    "sg:phone":"+33 1 40 13 83 13",
    "sg:province":"Ile de France",
    "wof:name":"Lesaffre Normandie S.a.r.l.",
    "wof:placetype":"venue"
},
  "geometry": {"coordinates":[2.345036,48.864704],"type":"Point"}
}