{
  "type": "Feature",
  "properties": {
    "addr:full":"679, Av. du Docteur Lef\u00e8bvre - Le Twins 1, 06270 Villeneuve Loubet Vill\u00e9 Alsace 67220",
    "addr:housenumber":"1",
    "addr:postcode":"06270;67220",
    "addr:street":"679 Av. Du Docteur Lefe\u0300Bvre Le Twins",
    "iso:country":"FR",
    "sg:address":"679, Av. du Docteur Lef\u00e8bvre - Le Twins 1, 06270 Villeneuve Loubet",
    "sg:city":"Vill\u00e9",
    "sg:orig_category":"Unclassifiable Establishments",
    "sg:phone":"+33 4 92 13 82 82",
    "sg:postcode":"67220",
    "sg:province":"Alsace",
    "wof:name":"Ikon Office Solutions S.a.",
    "wof:placetype":"venue"
},
  "geometry": {"coordinates":[7.120035,43.646286],"type":"Point"}
}