{
  "type": "Feature",
  "properties": {
    "addr:full":"B\u00e2t t Avignon 84000",
    "addr:housenumber":"ba\u0302t",
    "addr:postcode":"84000",
    "iso:country":"FR",
    "sg:address":"B\u00e2t t",
    "sg:city":"Avignon",
    "sg:orig_category":"Unclassifiable Establishments",
    "sg:phone":"+33 4 90 13 62 62",
    "sg:postcode":"84000",
    "wof:name":"Distrimex S.a.",
    "wof:placetype":"venue"
},
  "geometry": {"coordinates":[4.80514,43.938587],"type":"Point"}
}