{
  "type": "Feature",
  "properties": {
    "addr:full":"Malonze 23300 La Souterraine Limousin",
    "addr:postcode":"23300",
    "addr:street":"Malonze",
    "iso:country":"FR",
    "sg:address":"Malonze 23300 La Souterraine",
    "sg:orig_category":"Unclassifiable Establishments",
    "sg:phone":"+33 5 55 63 04 53",
    "sg:province":"Limousin",
    "wof:name":"Coop\u00e9rative Des Eleveurs De La Marche",
    "wof:placetype":"venue"
},
  "geometry": {"coordinates":[1.49647,46.223572],"type":"Point"}
}