{
  "type": "Feature",
  "properties": {
    "addr:full":"B.P. 2079 Pfastatt Alsace 68120",
    "addr:postcode":"68120",
    "addr:street":"B.P. 2079 Pfastatt Alsace",
    "iso:country":"FR",
    "sg:address":"B.P. 2079",
    "sg:city":"Pfastatt",
    "sg:orig_category":"Non-Classified Establishments",
    "sg:phone":"+33 3 89 51 30 00",
    "sg:postcode":"68120",
    "sg:province":"Alsace",
    "wof:name":"D.m.c. Tissu S.a.",
    "wof:placetype":"venue"
},
  "geometry": {"coordinates":[7.30214,47.768375],"type":"Point"}
}