{
  "type": "Feature",
  "properties": {
    "addr:full":"ZAC de la Croix de Fer Longueau Picardie 80330",
    "addr:postcode":"80330",
    "addr:street":"Zac De La Croix De Fer;Picardie",
    "iso:country":"FR",
    "sg:address":"ZAC de la Croix de Fer",
    "sg:city":"Longueau",
    "sg:orig_category":"Unclassifiable Establishments",
    "sg:phone":"+33 3 22 38 30 30",
    "sg:postcode":"80330",
    "sg:province":"Picardie",
    "wof:name":"Devred S.a.",
    "wof:placetype":"venue"
},
  "geometry": {"coordinates":[2.35752,49.870491],"type":"Point"}
}