{
  "type": "Feature",
  "properties": {
    "iso:country":"FR",
    "sg:address":"111, Chemin des Grands Moulins, 69400 Gleiz\u00e9",
    "sg:orig_category":"Non-Classified Establishments",
    "sg:phone":"+33 4 74 60 43 54",
    "sg:postcode":"69400",
    "sg:province":"Rhone-Alpes",
    "wof:name":"A.s.r.t. S.a.r.l. - Assistance De R\u00e9alisation Technique",
    "wof:placetype":"venue"
},
  "geometry": {"coordinates":[4.706984,45.988811],"type":"Point"}
}