{
  "type": "Feature",
  "properties": {
    "iso:country":"FR",
    "sg:address":"50 Bd De La Marne 94100 St Maur Des Foss\u00e9s",
    "sg:classifiers":[
        {
            "category":"Manufacturing",
            "subcategory":"Printing",
            "type":"Manufacturing & Wholesale Goods"
        }
    ],
    "sg:phone":"+33 1 41 81 18 00",
    "sg:province":"Ile de France",
    "sg:tags":[
        "publishing"
    ],
    "wof:name":"Dinaprim - 2h Communication",
    "wof:placetype":"venue"
},
  "geometry": {"coordinates":[2.49783,48.79332],"type":"Point"}
}