{
  "type": "Feature",
  "properties": {
    "iso:country":"FR",
    "sg:address":"Rue Du Tritshler 29200 Brest",
    "sg:city":"Brest",
    "sg:classifiers":[
        {
            "category":"Utilities",
            "type":"Services"
        }
    ],
    "sg:phone":"+33 2 98 44 22 87",
    "sg:postcode":"29200",
    "sg:province":"Bretagne",
    "sg:tags":[
        "raw",
        "energy",
        "material"
    ],
    "wof:name":"L'air Liquide Sa A Directoire Et Conseil De Surveillance",
    "wof:placetype":"venue"
},
  "geometry": {"coordinates":[-4.458429,48.388771],"type":"Point"}
}