{
  "type": "Feature",
  "properties": {
    "iso:country":"FR",
    "sg:address":"18 avenue de Normandie 94150 Rungis",
    "sg:classifiers":[
        {
            "category":"Food & Beverages",
            "subcategory":"Groceries & Convenience Stores",
            "type":"Retail Goods"
        }
    ],
    "sg:phone":"+33 1 46 87 35 16",
    "sg:postcode":"94150",
    "sg:province":"Ile de France",
    "sg:tags":[
        "fresh"
    ],
    "wof:name":"Europe Distrib Charcutiere Alimentaire Sa",
    "wof:placetype":"venue"
},
  "geometry": {"coordinates":[2.358027,48.760098],"type":"Point"}
}