{
  "type": "Feature",
  "properties": {
    "iso:country":"FR",
    "sg:address":"B.P. 820, 87015 Limoges C\u00e9dex^^RN 20 - ZI de Magr\u00e9, 87000 Limoges",
    "sg:orig_category":"Non-Classified Establishments",
    "sg:phone":"+33 5 55 30 90 90",
    "sg:province":"Limousin",
    "wof:name":"Pinault Bois Mat\u00e9riaux S.n.c.",
    "wof:placetype":"venue"
},
  "geometry": {"coordinates":[1.26201,45.828785],"type":"Point"}
}