{
  "type": "Feature",
  "properties": {
    "addr:full":"70/74, Rue des Roches, 93100 Montreuil Ile de France",
    "addr:housenumber":"70 / 74",
    "addr:postcode":"93100",
    "addr:street":"Rue Des Roches",
    "iso:country":"FR",
    "sg:address":"70/74, Rue des Roches, 93100 Montreuil",
    "sg:orig_category":"Unclassifiable Establishments",
    "sg:phone":"+33 1 49 88 63 05",
    "sg:province":"Ile de France",
    "wof:name":"Echali\u00e9 S.a.",
    "wof:placetype":"venue"
},
  "geometry": {"coordinates":[2.464966,48.871197],"type":"Point"}
}