{
  "type": "Feature",
  "properties": {
    "iso:country":"FR",
    "sg:address":"1, rue Ing\u00e9nieur Bertin, 21600 Longvic",
    "sg:city":"Longvic",
    "sg:orig_category":"Unclassifiable Establishments",
    "sg:phone":"+33 3 80 68 29 68",
    "sg:postcode":"21600",
    "sg:province":"Bourgogne",
    "wof:name":"Still Et Saxby S.a.r.l.",
    "wof:placetype":"venue"
},
  "geometry": {"coordinates":[5.0358,47.293941],"type":"Point"}
}