{
  "type": "Feature",
  "properties": {
    "iso:country":"FR",
    "sg:address":"Allee Des Cypres 83490 Le Muy",
    "sg:classifiers":[
        {
            "category":"Professional",
            "subcategory":"Engineering",
            "type":"Services"
        }
    ],
    "sg:phone":"+33 4 94 45 01 01",
    "sg:province":"Aquitaine",
    "sg:tags":[
        "machine",
        "-",
        "mechanical"
    ],
    "wof:name":"Clim Var Froid",
    "wof:placetype":"venue"
},
  "geometry": {"coordinates":[6.5846,43.473335],"type":"Point"}
}