{
  "type": "Feature",
  "properties": {
    "addr:full":"33, Av. du Docteur L\u00e9vy - Parc Club du Moulin \u00e0 Vent, 69693 V\u00e9nissieux C\u00e9dex Haute Normandie",
    "addr:postcode":"69693",
    "addr:street":"33 Av. Du Docteur Le\u0301Vy Parc Club Du Moulin A\u0300 Vent;Haute Normandie",
    "iso:country":"FR",
    "sg:address":"33, Av. du Docteur L\u00e9vy - Parc Club du Moulin \u00e0 Vent, 69693 V\u00e9nissieux C\u00e9dex",
    "sg:orig_category":"Non-Classified Establishments",
    "sg:phone":"+33 4 72 78 54 54",
    "sg:province":"Haute Normandie",
    "wof:name":"A.d. Ing\u00e9nierie S.a.r.l. - Acoustique D\u00e9veloppement Ing\u00e9nierie",
    "wof:placetype":"venue"
},
  "geometry": {"coordinates":[4.88381,45.696381],"type":"Point"}
}