{
  "type": "Feature",
  "properties": {
    "addr:full":"Quartier du Logis du Roy Privas Rhone-Alpes 07000",
    "addr:postcode":"07000",
    "addr:street":"Quartier Du Logis Du Roy Privas Rhone-Alpes",
    "iso:country":"FR",
    "sg:address":"Quartier du Logis du Roy",
    "sg:city":"Privas",
    "sg:orig_category":"Unclassifiable Establishments",
    "sg:phone":"+33 4 75 64 07 11",
    "sg:postcode":"07000",
    "sg:province":"Rhone-Alpes",
    "wof:name":"Faugier S.a.",
    "wof:placetype":"venue"
},
  "geometry": {"coordinates":[4.59982,44.721054],"type":"Point"}
}