{
  "type": "Feature",
  "properties": {
    "iso:country":"FR",
    "sg:address":"ZA Bastillac Sud 65000 Tarbes",
    "sg:classifiers":[
        {
            "category":"Manufacturing",
            "subcategory":"Chemicals & Compounds",
            "type":"Manufacturing & Wholesale Goods"
        }
    ],
    "sg:phone":"+33 5 62 51 78 80",
    "sg:postcode":"65000",
    "sg:province":"Midi Pyr\u00e9n\u00e9es",
    "sg:tags":[
        "pharmaceutical",
        "chemistry",
        "-",
        "by-product"
    ],
    "wof:name":"Adhetec Sa",
    "wof:placetype":"venue"
},
  "geometry": {"coordinates":[0.073125,43.230011],"type":"Point"}
}