{
  "type": "Feature",
  "properties": {
    "iso:country":"FR",
    "sg:address":"89100 Soucy",
    "sg:city":"Soucy",
    "sg:orig_category":"Non-Classified Establishments",
    "sg:phone":"+33 3 86 86 50 23",
    "sg:postcode":"89100",
    "sg:province":"Bourgogne",
    "wof:name":"Compagnie Des Sabli\u00e8res De La Seine S.a.",
    "wof:placetype":"venue"
},
  "geometry": {"coordinates":[3.324013,48.245991],"type":"Point"}
}