{
  "type": "Feature",
  "properties": {
    "addr:full":"23 Rue Guy De Plage Zi Du Vieux Thann 68801 Thann Haute Normandie",
    "addr:housenumber":"23",
    "addr:postcode":"68801",
    "addr:street":"Rue Guy De Plage Zi Du Vieux Thann;Haute Normandie",
    "iso:country":"FR",
    "sg:address":"23 Rue Guy De Plage Zi Du Vieux Thann 68801 Thann",
    "sg:classifiers":[
        {
            "category":"Manufacturing",
            "subcategory":"Chemicals & Compounds",
            "type":"Manufacturing & Wholesale Goods"
        }
    ],
    "sg:phone":"+33 3 89 35 74 20",
    "sg:province":"Haute Normandie",
    "sg:tags":[
        "pharmaceutical",
        "chemistry",
        "-",
        "by-product"
    ],
    "wof:name":"Air Products",
    "wof:placetype":"venue"
},
  "geometry": {"coordinates":[7.10335,47.810196],"type":"Point"}
}