{
  "type": "Feature",
  "properties": {
    "addr:full":"131, Bd Carnot, 78110 Le V\u00e9sinet Ile de France 78110",
    "addr:housenumber":"131",
    "addr:postcode":"78110;78110",
    "addr:street":"Bd Carnot",
    "iso:country":"FR",
    "sg:address":"131, Bd Carnot, 78110 Le V\u00e9sinet",
    "sg:orig_category":"Non-Classified Establishments",
    "sg:phone":"+33 1 34 80 62 96",
    "sg:postcode":"78110",
    "sg:province":"Ile de France",
    "wof:name":"Eosys S.a.r.l.",
    "wof:placetype":"venue"
},
  "geometry": {"coordinates":[2.11571,48.897572],"type":"Point"}
}