{
  "type": "Feature",
  "properties": {
    "addr:full":"23, Rue Alfred Kastler - PA Technologiques de la Vatine, 76130 Mont Saint Aignan Haute Normandie",
    "addr:housenumber":"23",
    "addr:postcode":"76130",
    "addr:street":"Rue Alfred Kastler",
    "iso:country":"FR",
    "sg:address":"23, Rue Alfred Kastler - PA Technologiques de la Vatine, 76130 Mont Saint Aignan",
    "sg:orig_category":"Unclassifiable Establishments",
    "sg:phone":"+33 2 35 12 58 00",
    "sg:province":"Haute Normandie",
    "wof:name":"Ricoh France S.a.",
    "wof:placetype":"venue"
},
  "geometry": {"coordinates":[1.070859,49.46204],"type":"Point"}
}