{
  "type": "Feature",
  "properties": {
    "addr:full":"Issy-les-Moulineaux, Paris, Dept 75 Issy-les-Moulineaux Ile de France 92130",
    "addr:housenumber":"75",
    "addr:postcode":"92130",
    "addr:street":"Ile De France",
    "iso:country":"FR",
    "sg:address":"Issy-les-Moulineaux, Paris, Dept 75",
    "sg:city":"Issy-les-Moulineaux",
    "sg:classifiers":[
        {
            "category":"Banks & Credit Unions",
            "subcategory":"Bank",
            "type":"Services"
        }
    ],
    "sg:postcode":"92130",
    "sg:province":"Ile de France",
    "wof:name":"Fulcrum Sa",
    "wof:placetype":"venue"
},
  "geometry": {"coordinates":[2.25124,48.82114],"type":"Point"}
}