{
  "type": "Feature",
  "properties": {
    "addr:full":"B.P. 53 La Tremblade^^Prise des Roberts 17390 La Tremblade Poitou-Charentes 17390",
    "addr:housenumber":"17390",
    "addr:postcode":"17390",
    "addr:street":"B.P. 53 La Tremblade^^Prise Des Roberts;Tremblade",
    "iso:country":"FR",
    "sg:address":"B.P. 53",
    "sg:city":"La Tremblade^^Prise des Roberts 17390 La Tremblade",
    "sg:orig_category":"Non-Classified Establishments",
    "sg:phone":"+33 5 46 36 09 56",
    "sg:postcode":"17390",
    "sg:province":"Poitou-Charentes",
    "wof:name":"Bechemilh Lauby S.a.r.l.",
    "wof:placetype":"venue"
},
  "geometry": {"coordinates":[-1.143087,45.774155],"type":"Point"}
}