{
  "type": "Feature",
  "properties": {
    "addr:full":"Rue De La Ville Es Cours Zi Sud 35400 St Malo Saint-Malo Bretagne 35400",
    "addr:postcode":"35400;35400",
    "addr:street":"Rue De La Ville;Cours Zi Sud;Saint-Malo Bretagne",
    "iso:country":"FR",
    "sg:address":"Rue De La Ville Es Cours Zi Sud 35400 St Malo",
    "sg:city":"Saint-Malo",
    "sg:classifiers":[
        {
            "category":"Manufacturing",
            "subcategory":"Rubber & Plastics",
            "type":"Manufacturing & Wholesale Goods"
        }
    ],
    "sg:phone":"+33 2 99 81 68 46",
    "sg:postcode":"35400",
    "sg:province":"Bretagne",
    "sg:tags":[
        "packaging",
        "material",
        "-"
    ],
    "wof:name":"Frans Bonhomme",
    "wof:placetype":"venue"
},
  "geometry": {"coordinates":[-2.003669,48.604897],"type":"Point"}
}