{
  "type": "Feature",
  "properties": {
    "iso:country":"FR",
    "sg:address":"91, Rue P\u00e9reire - Parc P\u00e9reire, 78100 Saint Germain en Laye",
    "sg:orig_category":"Non-Classified Establishments",
    "sg:phone":"+33 1 30 61 81 90",
    "sg:postcode":"78100",
    "sg:province":"Ile de France",
    "wof:name":"Aprochim S.a.",
    "wof:placetype":"venue"
},
  "geometry": {"coordinates":[2.068047,48.901249],"type":"Point"}
}