{
  "type": "Feature",
  "properties": {
    "addr:full":"Rue de l'Egalit\u00e9 - ZA Bernard Palissy - B\u00e2t. 6 - Prouvy Lomme Nord Pas-de-Calais 59160",
    "addr:housenumber":"ba\u0302t",
    "addr:street":"Rue De L'Egalite;Za Bernard Palissy;Pas-De-Calais",
    "iso:country":"FR",
    "sg:address":"Rue de l'Egalit\u00e9 - ZA Bernard Palissy - B\u00e2t. 6 - Prouvy",
    "sg:city":"Lomme",
    "sg:orig_category":"Non-Classified Establishments",
    "sg:phone":"+33 3 20 92 87 75",
    "sg:postcode":"59160",
    "sg:province":"Nord Pas-de-Calais",
    "wof:name":"Vandevelde S.a.r.l.",
    "wof:placetype":"venue"
},
  "geometry": {"coordinates":[3.05721,50.636951],"type":"Point"}
}