{
  "type": "Feature",
  "properties": {
    "iso:country":"FR",
    "sg:address":"15 rue Louis Saulnier; Meyzieu",
    "sg:classifiers":[
        {
            "category":"Banks & Credit Unions",
            "subcategory":"Bank",
            "type":"Services"
        }
    ],
    "sg:phone":"+33 3378316266",
    "sg:province":"Haute Normandie",
    "wof:name":"Cr\u00e9dit Agricole Is\u00e8re",
    "wof:placetype":"venue"
},
  "geometry": {"coordinates":[5.003178,45.765099],"type":"Point"}
}