{
  "type": "Feature",
  "properties": {
    "iso:country":"FR",
    "sg:address":"Synergiparc - ZA de l'Agavon",
    "sg:city":"Les Pennes Mirabeau",
    "sg:orig_category":"Unclassifiable Establishments",
    "sg:phone":"+33 4 42 10 61 00",
    "sg:postcode":"13170",
    "sg:province":"Poitou-Charentes",
    "wof:name":"Provence Service Industries S.a.r.l.",
    "wof:placetype":"venue"
},
  "geometry": {"coordinates":[5.282638,43.417511],"type":"Point"}
}