{
  "type": "Feature",
  "properties": {
    "addr:full":"Av. de l'Industrie - ZI du Terroir Saint Alban Midi Pyr\u00e9n\u00e9es 31140",
    "addr:postcode":"31140",
    "addr:street":"Av. De L'Industrie Zi Du Terroir",
    "iso:country":"FR",
    "sg:address":"Av. de l'Industrie - ZI du Terroir",
    "sg:city":"Saint Alban",
    "sg:orig_category":"Unclassifiable Establishments",
    "sg:phone":"+33 5 61 35 80 80",
    "sg:postcode":"31140",
    "sg:province":"Midi Pyr\u00e9n\u00e9es",
    "wof:name":"Etablissements Bernard Pag\u00e8s S.a.",
    "wof:placetype":"venue"
},
  "geometry": {"coordinates":[1.400911,43.700218],"type":"Point"}
}