{
  "type": "Feature",
  "properties": {
    "iso:country":"FR",
    "sg:address":"B.P. 1, 94111 Arcueil C\u00e9dex^^80, Av. Gabriel P\u00e9ri, 94110 Arcueil",
    "sg:orig_category":"Non-Classified Establishments",
    "sg:phone":"+33 1 45 47 30 93",
    "sg:province":"Ile de France",
    "wof:name":"Euro Packaging S.a.s.",
    "wof:placetype":"venue"
},
  "geometry": {"coordinates":[2.337826,48.805691],"type":"Point"}
}