{
  "type": "Feature",
  "properties": {
    "addr:full":"5 Av D\u00e9fense Passive 80136 Rivery Picardie 80136",
    "addr:postcode":"80136;80136",
    "addr:street":"Av De\u0301Fense Passive",
    "iso:country":"FR",
    "sg:address":"5 Av D\u00e9fense Passive 80136 Rivery",
    "sg:classifiers":[
        {
            "category":"Government",
            "subcategory":"Department Of Motor Vehicles",
            "type":"Public Place"
        }
    ],
    "sg:phone":"+33 3 22 66 36 00",
    "sg:postcode":"80136",
    "sg:province":"Picardie",
    "sg:tags":[
        "equipment",
        "industrial",
        "transport",
        "motor-cars"
    ],
    "wof:name":"C L C Sa",
    "wof:placetype":"venue"
},
  "geometry": {"coordinates":[2.322283,49.907768],"type":"Point"}
}