{
  "type": "Feature",
  "properties": {
    "iso:country":"FR",
    "sg:address":"14/16, Rue Saint Hilaire - Parc Activit\u00e9 du Vert Galant, 95310 Saint Ouen l'Aum\u00f4ne",
    "sg:orig_category":"Unclassifiable Establishments",
    "sg:phone":"+33 1 34 02 90 00",
    "sg:province":"Ile de France",
    "wof:name":"Bct France S.a.",
    "wof:placetype":"venue"
},
  "geometry": {"coordinates":[2.933116,48.55759],"type":"Point"}
}