{
  "type": "Feature",
  "properties": {
    "iso:country":"FR",
    "sg:address":"La Ribeyre 43380 Lavoute Chilhac",
    "sg:city":"Chilhac",
    "sg:orig_category":"Unclassifiable Establishments",
    "sg:phone":"+33 4 71 77 45 90",
    "sg:postcode":"43380",
    "sg:province":"Auvergne",
    "wof:name":"Exhafilm S.a.r.l.",
    "wof:placetype":"venue"
},
  "geometry": {"coordinates":[3.406843,45.153477],"type":"Point"}
}