{
  "type": "Feature",
  "properties": {
    "addr:full":"24 Avenue Du General Roques 66509 PRADES Midi Pyr\u00e9n\u00e9es",
    "addr:housenumber":"24",
    "addr:postcode":"66509",
    "addr:street":"Avenue Du General Roques",
    "iso:country":"FR",
    "sg:address":"24 Avenue Du General Roques 66509 PRADES",
    "sg:classifiers":[
        {
            "category":"Wholesale",
            "subcategory":"Machinery & Supplies",
            "type":"Manufacturing & Wholesale Goods"
        }
    ],
    "sg:phone":"+33 4 68 55 44 19",
    "sg:province":"Midi Pyr\u00e9n\u00e9es",
    "sg:tags":[
        "agricultural",
        "equipment"
    ],
    "wof:name":"Agri Tet Sa",
    "wof:placetype":"venue"
},
  "geometry": {"coordinates":[2.42574,42.615379],"type":"Point"}
}