{
  "type": "Feature",
  "properties": {
    "iso:country":"FR",
    "sg:address":"Bat Le Rennaisance -3 Rampoint Du Sel 78280 Guyancourt",
    "sg:classifiers":[
        {
            "category":"Wholesale",
            "subcategory":"Machinery & Supplies",
            "type":"Manufacturing & Wholesale Goods"
        }
    ],
    "sg:phone":"+33 1 30 12 35 53",
    "sg:postcode":"78280",
    "sg:province":"Ile de France",
    "sg:tags":[
        "handling",
        "material",
        "-",
        "machine",
        "equipment",
        "engineering",
        "mechanical"
    ],
    "wof:name":"Storage Technology France Sa",
    "wof:placetype":"venue"
},
  "geometry": {"coordinates":[2.06956,48.771046],"type":"Point"}
}