{
  "type": "Feature",
  "properties": {
    "iso:country":"FR",
    "sg:address":"1, Bd d'Alsace - Zone Industrielle Nord, 68330 Huningue",
    "sg:city":"Huningue",
    "sg:orig_category":"Unclassifiable Establishments",
    "sg:phone":"+33 3 89 89 75 40",
    "sg:postcode":"68330",
    "sg:province":"Alsace",
    "wof:name":"Lesage Et Compagnie S.a.",
    "wof:placetype":"venue"
},
  "geometry": {"coordinates":[7.57985,47.588249],"type":"Point"}
}