{
  "type": "Feature",
  "properties": {
    "addr:full":"173 Av Port J\u00e9r\u00f4me 76170 Lillebonne Haute Normandie 76170",
    "addr:postcode":"76170;76170",
    "addr:street":"173 Av Port Je\u0301Ro\u0302Me;Haute Normandie",
    "iso:country":"FR",
    "sg:address":"173 Av Port J\u00e9r\u00f4me 76170 Lillebonne",
    "sg:classifiers":[
        {
            "category":"Shopping",
            "type":"Retail Goods"
        }
    ],
    "sg:phone":"+33 2 35 39 60 10",
    "sg:postcode":"76170",
    "sg:province":"Haute Normandie",
    "sg:tags":[
        "metallurgy",
        "finished",
        "-",
        "metalworking",
        "metallic"
    ],
    "wof:name":"Ponticelli Freres (ets) Sa",
    "wof:placetype":"venue"
},
  "geometry": {"coordinates":[0.5367,49.502998],"type":"Point"}
}