{
  "type": "Feature",
  "properties": {
    "addr:full":"38 pl d'Armes; Vitry; 51300 Champagne 51300",
    "addr:housenumber":"38",
    "addr:postcode":"51300;51300",
    "addr:street":"Pl D'Armes Vitry",
    "iso:country":"FR",
    "sg:address":"38 pl d'Armes; Vitry; 51300",
    "sg:classifiers":[
        {
            "category":"Banks & Credit Unions",
            "subcategory":"Bank",
            "type":"Services"
        }
    ],
    "sg:phone":"+33 26740005",
    "sg:postcode":"51300",
    "sg:province":"Champagne",
    "wof:name":"Soci\u00e9t\u00e9 G\u00e9n\u00e9rale",
    "wof:placetype":"venue"
},
  "geometry": {"coordinates":[4.58616,48.725872],"type":"Point"}
}