{
  "type": "Feature",
  "properties": {
    "iso:country":"FR",
    "sg:address":"13, Rte Nationale, 62161 Duisans",
    "sg:orig_category":"Unclassifiable Establishments",
    "sg:phone":"+33 3 21 58 24 13",
    "sg:province":"Nord Pas-de-Calais",
    "wof:name":"Artois Nettoyage S.a.r.l.",
    "wof:placetype":"venue"
},
  "geometry": {"coordinates":[2.687328,50.306469],"type":"Point"}
}