{
  "type": "Feature",
  "properties": {
    "addr:full":"80 Rue Blanche Paris Ile de France 75009",
    "addr:housenumber":"80",
    "addr:postcode":"75009",
    "addr:street":"Rue Blanche",
    "iso:country":"FR",
    "sg:address":"80 Rue Blanche",
    "sg:city":"Paris",
    "sg:classifiers":[
        {
            "category":"Banks & Credit Unions",
            "subcategory":"Financial Services",
            "type":"Services"
        }
    ],
    "sg:phone":"+33 1 42 85 16 55",
    "sg:postcode":"75009",
    "sg:province":"Ile de France",
    "sg:tags":[
        "banking",
        "finance",
        "insurance"
    ],
    "wof:name":"Guibert Et Associes Sa",
    "wof:placetype":"venue"
},
  "geometry": {"coordinates":[2.331902,48.882019],"type":"Point"}
}