{
  "type": "Feature",
  "properties": {
    "iso:country":"FR",
    "sg:address":"371, Av. Georges Cl\u00e9menceau, 59680 Ferri\u00e8re la Grande",
    "sg:orig_category":"Non-Classified Establishments",
    "sg:phone":"+33 3 27 58 27 45",
    "sg:province":"Nord Pas-de-Calais",
    "wof:name":"I.m.d. S.a. - Inter M\u00e9tal Distribution",
    "wof:placetype":"venue"
},
  "geometry": {"coordinates":[3.999951,50.260143],"type":"Point"}
}