{
  "type": "Feature",
  "properties": {
    "iso:country":"FR",
    "sg:address":"17 Boulevard Pasteur 93380 Pierrefitte Sur Seine",
    "sg:classifiers":[
        {
            "category":"Professional",
            "subcategory":"Business Services",
            "type":"Services"
        }
    ],
    "sg:phone":"+33 1 48 22 66 88",
    "sg:postcode":"93380",
    "sg:province":"Ile de France",
    "sg:tags":[
        "body",
        "advice"
    ],
    "wof:name":"Afl",
    "wof:placetype":"venue"
},
  "geometry": {"coordinates":[2.362204,48.966129],"type":"Point"}
}