{
  "type": "Feature",
  "properties": {
    "iso:country":"FR",
    "sg:address":"10 Rue D'Aguesseau 44000 Nantes",
    "sg:classifiers":[
        {
            "category":"Farming",
            "subcategory":"Farm",
            "type":"Manufacturing & Wholesale Goods"
        }
    ],
    "sg:phone":"+33 2 40 35 07 80",
    "sg:postcode":"44000",
    "sg:province":"Pays de Loire",
    "sg:tags":[
        "horticulture",
        "agriculture",
        "livestock"
    ],
    "wof:name":"Grande Paroisse Sa",
    "wof:placetype":"venue"
},
  "geometry": {"coordinates":[-1.552996,47.219498],"type":"Point"}
}