{
  "type": "Feature",
  "properties": {
    "iso:country":"FR",
    "sg:address":"76 Bd Gambetta 62100 Calais",
    "sg:classifiers":[
        {
            "category":"Shopping",
            "subcategory":"Crafts & Fabrics",
            "type":"Retail Goods"
        }
    ],
    "sg:phone":"+33 3 21 00 76 00",
    "sg:postcode":"62100",
    "sg:province":"Nord Pas-de-Calais",
    "sg:tags":[
        "textile",
        "clothing"
    ],
    "wof:name":"Desseilles Textiles Sa",
    "wof:placetype":"venue"
},
  "geometry": {"coordinates":[1.850274,50.947388],"type":"Point"}
}