{
  "type": "Feature",
  "properties": {
    "iso:country":"FR",
    "sg:address":"3/5, Rue Coste Bellonce - Parc d'Activit\u00e9s Sully, 78200 Mantes la Jolie",
    "sg:orig_category":"Non-Classified Establishments",
    "sg:phone":"+33 1 30 33 08 34",
    "sg:province":"Ile de France",
    "wof:name":"Soci\u00e9t\u00e9 Mantes Primeurs S.a.",
    "wof:placetype":"venue"
},
  "geometry": {"coordinates":[1.675336,48.99361],"type":"Point"}
}