{
  "type": "Feature",
  "properties": {
    "addr:full":"56 rue de la Joliette 13002 Marseille Poitou-Charentes",
    "addr:housenumber":"56",
    "addr:postcode":"13002",
    "addr:street":"Rue De La Joliette",
    "iso:country":"FR",
    "sg:address":"56 rue de la Joliette 13002 Marseille",
    "sg:classifiers":[
        {
            "category":"Retail",
            "subcategory":"Auto Rental",
            "type":"Services"
        }
    ],
    "sg:phone":"+33 4 91 99 43 80",
    "sg:province":"Poitou-Charentes",
    "sg:tags":[
        "car",
        "transport"
    ],
    "wof:name":"Nicolas Fr\u00e8res S.a.",
    "wof:placetype":"venue"
},
  "geometry": {"coordinates":[5.370863,43.302879],"type":"Point"}
}