{
  "type": "Feature",
  "properties": {
    "addr:full":"1 Av Newton 92142 Clamart Poitou-Charentes",
    "addr:postcode":"92142",
    "addr:street":"Av Newton",
    "iso:country":"FR",
    "sg:address":"1 Av Newton 92142 Clamart",
    "sg:classifiers":[
        {
            "category":"Building & Trades",
            "subcategory":"Construction",
            "type":"Services"
        }
    ],
    "sg:phone":"+33 1 41 28 48 80",
    "sg:province":"Poitou-Charentes",
    "sg:tags":[
        "information",
        "work",
        "technology",
        "public",
        "software"
    ],
    "wof:name":"Societe De Realisations Informatiques Et Logiciels",
    "wof:placetype":"venue"
},
  "geometry": {"coordinates":[2.242233,48.779762],"type":"Point"}
}