{
  "type": "Feature",
  "properties": {
    "addr:full":"7 Place Charles Hernu 69100 Villeurbanne Rhone-Alpes",
    "addr:housenumber":"7",
    "addr:postcode":"69100",
    "addr:street":"Place Charles Hernu",
    "iso:country":"FR",
    "sg:address":"7 Place Charles Hernu 69100 Villeurbanne",
    "sg:classifiers":[
        {
            "category":"Travel",
            "subcategory":"Hotels & Motels",
            "type":"Entertainment"
        }
    ],
    "sg:phone":"+33 4 72 44 46 46",
    "sg:province":"Rhone-Alpes",
    "sg:tags":[
        "hotels",
        "business",
        "restaurant"
    ],
    "wof:name":"Jd Investissement",
    "wof:placetype":"venue"
},
  "geometry": {"coordinates":[4.862848,45.770618],"type":"Point"}
}