{
  "type": "Feature",
  "properties": {
    "addr:full":"ZI des Gailletrous La Chauss\u00e9e Saint Victor Centre 41260",
    "addr:postcode":"41260",
    "addr:street":"Des Gailletrous La;Saint",
    "iso:country":"FR",
    "sg:address":"ZI des Gailletrous",
    "sg:city":"La Chauss\u00e9e Saint Victor",
    "sg:orig_category":"Unclassifiable Establishments",
    "sg:phone":"+33 2 54 90 28 28",
    "sg:postcode":"41260",
    "sg:province":"Centre",
    "wof:name":"S.i.d.a.m.o. S.a. - Soci\u00e9t\u00e9 D'importation Distribution Abrasifs Et Machines-outils",
    "wof:placetype":"venue"
},
  "geometry": {"coordinates":[1.36532,47.613747],"type":"Point"}
}