{
  "type": "Feature",
  "properties": {
    "addr:full":"LD VERMONT 69910 VILLIE-MORGON Rhone-Alpes 69910",
    "addr:postcode":"69910;69910",
    "addr:street":"Ld;Rhone-Alpes",
    "iso:country":"FR",
    "sg:address":"LD VERMONT 69910 VILLIE-MORGON",
    "sg:classifiers":[
        {
            "category":"Food Court",
            "type":"Food & Drink"
        }
    ],
    "sg:phone":"+33 4 74 04 23 23",
    "sg:postcode":"69910",
    "sg:province":"Rhone-Alpes",
    "sg:tags":[
        "product",
        "related"
    ],
    "wof:name":"Domaine Gravallon Fernand",
    "wof:placetype":"venue"
},
  "geometry": {"coordinates":[4.65254,46.171364],"type":"Point"}
}