{
  "type": "Feature",
  "properties": {
    "iso:country":"FR",
    "sg:address":"12 rue de la Patelle 95220 Herblay",
    "sg:classifiers":[
        {
            "category":"Professional",
            "type":"Services"
        }
    ],
    "sg:phone":"+33 1 34 40 30 50",
    "sg:province":"Ile de France",
    "sg:tags":[
        "transport"
    ],
    "wof:name":"France Cargo Systems S.a.r.l.",
    "wof:placetype":"venue"
},
  "geometry": {"coordinates":[2.123433,49.028172],"type":"Point"}
}