{
  "type": "Feature",
  "properties": {
    "iso:country":"FR",
    "sg:address":"221 Av Du Pr\u00e9sident Wilson 93214 Saint Denis La Pleine Cedex",
    "sg:classifiers":[
        {
            "category":"Building & Trades",
            "subcategory":"Construction",
            "type":"Services"
        }
    ],
    "sg:phone":"+33 1 49 17 85 50",
    "sg:province":"Basse Normandie",
    "sg:tags":[
        "work",
        "public"
    ],
    "wof:name":"Sanem Stade De France Sa",
    "wof:placetype":"venue"
},
  "geometry": {"coordinates":[2.357314,48.914471],"type":"Point"}
}