{
  "type": "Feature",
  "properties": {
    "addr:full":"13, Rue Sadi Carnot, 78120 Rambouillet Ile de France",
    "addr:housenumber":"13",
    "addr:postcode":"78120;ile",
    "addr:street":"Rue Sadi Carnot",
    "iso:country":"FR",
    "sg:address":"13, Rue Sadi Carnot, 78120 Rambouillet",
    "sg:orig_category":"Non-Classified Establishments",
    "sg:phone":"+33 1 34 83 83 33",
    "sg:province":"Ile de France",
    "wof:name":"H\u00e9r\u00e8s Propret\u00e9",
    "wof:placetype":"venue"
},
  "geometry": {"coordinates":[1.83036,48.64407],"type":"Point"}
}