{
  "type": "Feature",
  "properties": {
    "addr:full":"Av. de Magudas - Parc H\u00e9liopolis B3 M\u00e9rignac Aquitaine 33700",
    "addr:housenumber":"b3",
    "addr:postcode":"33700",
    "addr:street":"Av. De Magudas Parc He\u0301Liopolis",
    "iso:country":"FR",
    "sg:address":"Av. de Magudas - Parc H\u00e9liopolis B3",
    "sg:city":"M\u00e9rignac",
    "sg:orig_category":"Non-Classified Establishments",
    "sg:phone":"+33 5 57 35 06 50",
    "sg:postcode":"33700",
    "sg:province":"Aquitaine",
    "wof:name":"Constantin S.a.",
    "wof:placetype":"venue"
},
  "geometry": {"coordinates":[-0.665269,44.858124],"type":"Point"}
}