{
  "type": "Feature",
  "properties": {
    "iso:country":"FR",
    "sg:address":"Zone Industrielle Val Guiers 73330 Belmont Tramonet",
    "sg:classifiers":[
        {
            "category":"Manufacturing",
            "subcategory":"Rubber & Plastics",
            "type":"Manufacturing & Wholesale Goods"
        }
    ],
    "sg:phone":"+33 4 76 37 39 39",
    "sg:province":"Rhone-Alpes",
    "wof:name":"Applications Plastiques Industrielles Rhone Alpes (apira)",
    "wof:placetype":"venue"
},
  "geometry": {"coordinates":[5.682691,45.559105],"type":"Point"}
}