{
  "type": "Feature",
  "properties": {
    "iso:country":"FR",
    "sg:address":"3 avenue du Garigliano 91600 SAVIGNY SUR ORGE",
    "sg:classifiers":[
        {
            "category":"Utilities",
            "subcategory":"Sewage",
            "type":"Services"
        }
    ],
    "sg:phone":"+33 1 69 05 72 83",
    "sg:postcode":"91600",
    "sg:province":"Ile de France",
    "sg:tags":[
        "cock",
        "accessory"
    ],
    "wof:name":"Vraco Sa",
    "wof:placetype":"venue"
},
  "geometry": {"coordinates":[2.335108,48.691696],"type":"Point"}
}