{
  "type": "Feature",
  "properties": {
    "addr:full":"6, Rue Thimonnier, 71000 M\u00e2con Sanc\u00e9 Bourgogne 71000",
    "addr:housenumber":"6",
    "addr:postcode":"71000;71000",
    "addr:street":"Rue Thimonnier",
    "iso:country":"FR",
    "sg:address":"6, Rue Thimonnier, 71000 M\u00e2con",
    "sg:city":"Sanc\u00e9",
    "sg:orig_category":"Unclassifiable Establishments",
    "sg:phone":"+33 3 85 34 72 78",
    "sg:postcode":"71000",
    "sg:province":"Bourgogne",
    "wof:name":"Somroc S.a.",
    "wof:placetype":"venue"
},
  "geometry": {"coordinates":[4.810127,46.294468],"type":"Point"}
}