{
  "type": "Feature",
  "properties": {
    "addr:full":"Rue Du Clos Barrois 60183 Nogent Cedex Barr Alsace 67140",
    "addr:postcode":"60183;67140",
    "addr:street":"Rue Du Clos Barrois",
    "iso:country":"FR",
    "sg:address":"Rue Du Clos Barrois 60183 Nogent Cedex",
    "sg:city":"Barr",
    "sg:classifiers":[
        {
            "category":"Health Services",
            "subcategory":"Medical Lab",
            "type":"Services"
        }
    ],
    "sg:phone":"+33 3 44 55 36 82",
    "sg:postcode":"67140",
    "sg:province":"Alsace",
    "sg:tags":[
        "chemical",
        "pharmaceutical",
        "pharmacy"
    ],
    "wof:name":"Eurand France Sas",
    "wof:placetype":"venue"
},
  "geometry": {"coordinates":[-88.402023,41.938179],"type":"Point"}
}