{
  "type": "Feature",
  "properties": {
    "iso:country":"FR",
    "sg:address":"56 bis, Rue de l'Egalit\u00e9, 69330 Pusignan",
    "sg:orig_category":"Unclassifiable Establishments",
    "sg:phone":"+33 4 78 04 44 37",
    "sg:postcode":"69330",
    "sg:province":"Rhone-Alpes",
    "wof:name":"M.g.p. S.a.r.l. - M\u00e9canique G\u00e9n\u00e9rale De Pr\u00e9cision",
    "wof:placetype":"venue"
},
  "geometry": {"coordinates":[4.989414,45.781185],"type":"Point"}
}