{
  "type": "Feature",
  "properties": {
    "addr:full":"70 rue Pierre Dhuem 13290 AIX EN PROVENCE Nord Pas-de-Calais",
    "addr:housenumber":"70",
    "addr:postcode":"13290",
    "addr:street":"Rue Pierre Dhuem;En Provence Nord",
    "iso:country":"FR",
    "sg:address":"70 rue Pierre Dhuem 13290 AIX EN PROVENCE",
    "sg:classifiers":[
        {
            "category":"Professional",
            "subcategory":"Engineering",
            "type":"Services"
        }
    ],
    "sg:phone":"+33 4 42 16 65 00",
    "sg:province":"Nord Pas-de-Calais",
    "sg:tags":[
        "hydraulics"
    ],
    "wof:name":"Guigues S.a.",
    "wof:placetype":"venue"
},
  "geometry": {"coordinates":[5.38935,43.50206],"type":"Point"}
}