{
  "type": "Feature",
  "properties": {
    "iso:country":"FR",
    "sg:address":"69, Bd Gallieni, 92130 Issy les Moulineaux",
    "sg:orig_category":"Non-Classified Establishments",
    "sg:phone":"+33 1 55 95 53 00",
    "sg:postcode":"92130",
    "sg:province":"Ile de France",
    "wof:name":"C.g.b.i. S.a.",
    "wof:placetype":"venue"
},
  "geometry": {"coordinates":[2.268037,48.824146],"type":"Point"}
}