{
  "type": "Feature",
  "properties": {
    "iso:country":"FR",
    "sg:address":"66 Cours Charlemagne 69002 Lyon",
    "sg:classifiers":[
        {
            "category":"Health Services",
            "subcategory":"Medical Lab",
            "type":"Services"
        }
    ],
    "sg:phone":"+33 4 78 38 53 10",
    "sg:postcode":"69002",
    "sg:province":"Rhone-Alpes",
    "sg:tags":[
        "chemical",
        "pharmaceutical",
        "pharmacy"
    ],
    "wof:name":"Arrow Generiques",
    "wof:placetype":"venue"
},
  "geometry": {"coordinates":[4.821692,45.744076],"type":"Point"}
}