{
  "type": "Feature",
  "properties": {
    "addr:full":"B.P. 14, 40501 Saint Sever C\u00e9dex^^Rte de Mont de Marsan, 40500 Saint Sever Audignon Aquitaine 40500",
    "addr:postcode":"40501;40500;40500",
    "addr:street":"B.P. 14;De Marsan",
    "iso:country":"FR",
    "sg:address":"B.P. 14, 40501 Saint Sever C\u00e9dex^^Rte de Mont de Marsan, 40500 Saint Sever",
    "sg:city":"Audignon",
    "sg:orig_category":"Non-Classified Establishments",
    "sg:phone":"+33 5 58 76 43 43",
    "sg:postcode":"40500",
    "sg:province":"Aquitaine",
    "wof:name":"M.c.f. S.a. - Contructions M\u00e9talliques Feugas",
    "wof:placetype":"venue"
},
  "geometry": {"coordinates":[-0.635392,43.781681],"type":"Point"}
}