{
  "type": "Feature",
  "properties": {
    "iso:country":"FR",
    "sg:address":"Rue des Oziers - ZI du Vert Galant",
    "sg:city":"Saint Ouen l'Aum\u00f4ne",
    "sg:orig_category":"Unclassifiable Establishments",
    "sg:phone":"+33 1 34 32 39 70",
    "sg:postcode":"95310",
    "sg:province":"Ile de France",
    "wof:name":"Ceac",
    "wof:placetype":"venue"
},
  "geometry": {"coordinates":[2.933116,48.55759],"type":"Point"}
}