{
  "type": "Feature",
  "properties": {
    "iso:country":"FR",
    "sg:address":"B.P. 3, 62920 Chocques^^Rue R\u00e9veillon, 62920 Chocques",
    "sg:orig_category":"Non-Classified Establishments",
    "sg:phone":"+33 3 21 57 41 10",
    "sg:province":"Nord Pas-de-Calais",
    "wof:name":"R\u00e9cup\u00e9ration M\u00e9tallurgique De L'artois S.a.r.l.",
    "wof:placetype":"venue"
},
  "geometry": {"coordinates":[2.574546,50.562511],"type":"Point"}
}