{
  "type": "Feature",
  "properties": {
    "addr:full":"16, Chemin de Saquier Bellet - ZA Lingasti\u00e8re, 06000 Nice Provence-Alpes-C\u00f4te d'Azur",
    "addr:housenumber":"16",
    "addr:postcode":"06000",
    "addr:street":"Chemin De Saquier Bellet Za Lingastie\u0300Re",
    "iso:country":"FR",
    "sg:address":"16, Chemin de Saquier Bellet - ZA Lingasti\u00e8re, 06000 Nice",
    "sg:orig_category":"Non-Classified Establishments",
    "sg:phone":"+33 4 92 29 18 49",
    "sg:province":"Provence-Alpes-C\u00f4te d'Azur",
    "wof:name":"Seven S.a.r.l.",
    "wof:placetype":"venue"
},
  "geometry": {"coordinates":[7.27434,43.718231],"type":"Point"}
}