{
  "type": "Feature",
  "properties": {
    "addr:full":"B.P. 26, 38490 Aoste C\u00e9dex^^Rue des Moulins, 38490 Aoste Rhone-Alpes 38490",
    "addr:postcode":"38490;38490;38490",
    "addr:street":"B.P. 26",
    "iso:country":"FR",
    "sg:address":"B.P. 26, 38490 Aoste C\u00e9dex^^Rue des Moulins, 38490 Aoste",
    "sg:orig_category":"Non-Classified Establishments",
    "sg:phone":"+33 4 76 32 50 31",
    "sg:postcode":"38490",
    "sg:province":"Rhone-Alpes",
    "wof:name":"A.m.d. S.a.r.l. - Alpes M\u00e9tal Diffusion",
    "wof:placetype":"venue"
},
  "geometry": {"coordinates":[5.59776,45.510784],"type":"Point"}
}