{
  "type": "Feature",
  "properties": {
    "addr:full":"20, Av. de l'Ile de France, 95310 Saint Ouen l'Aum\u00f4ne Ile de France",
    "addr:postcode":"95310",
    "addr:street":"20 Av. De L'Ile De France",
    "iso:country":"FR",
    "sg:address":"20, Av. de l'Ile de France, 95310 Saint Ouen l'Aum\u00f4ne",
    "sg:orig_category":"Unclassifiable Establishments",
    "sg:phone":"+33 1 34 30 03 18",
    "sg:province":"Ile de France",
    "wof:name":"A.e.e.n. S.a. - Automatismes Exploitation Energies Nouvelles",
    "wof:placetype":"venue"
},
  "geometry": {"coordinates":[2.12935,49.04504],"type":"Point"}
}