{
  "type": "Feature",
  "properties": {
    "iso:country":"FR",
    "sg:address":"11, Av. Didier Daurat, 31400 Toulouse",
    "sg:orig_category":"Unclassifiable Establishments",
    "sg:phone":"+33 5 62 16 60 60",
    "sg:province":"Midi Pyr\u00e9n\u00e9es",
    "wof:name":"Forclum Midi Pyr\u00e9n\u00e9es S.n.c.",
    "wof:placetype":"venue"
},
  "geometry": {"coordinates":[1.491055,43.566513],"type":"Point"}
}