{
  "type": "Feature",
  "properties": {
    "iso:country":"FR",
    "sg:address":"B.P. 21, 26301 Bourg de P\u00e9age C\u00e9dex^^All\u00e9e du Dauphin\u00e9 - ZI, 26300 Bourg de P\u00e9age",
    "sg:orig_category":"Non-Classified Establishments",
    "sg:phone":"+33 4 75 72 46 47",
    "sg:postcode":"26300",
    "sg:province":"Rhone-Alpes",
    "wof:name":"S.i.c. S.a.r.l. - Soci\u00e9t\u00e9 Industrielle De Chromage",
    "wof:placetype":"venue"
},
  "geometry": {"coordinates":[5.09157,44.938511],"type":"Point"}
}