{
  "type": "Feature",
  "properties": {
    "iso:country":"FR",
    "sg:address":"B.P. 49, 57801 Freyming Merlebach C\u00e9dex^^39, Av. Roosevelt, 57800 Freyming Merlebach",
    "sg:orig_category":"Non-Classified Establishments",
    "sg:phone":"+33 3 87 04 54 70",
    "sg:postcode":"57800",
    "sg:province":"Lorraine",
    "wof:name":"Etablissements Brunot",
    "wof:placetype":"venue"
},
  "geometry": {"coordinates":[6.793515,49.143681],"type":"Point"}
}