{
  "type": "Feature",
  "properties": {
    "addr:full":"B.P. 2012, 31017 Toulouse C\u00e9dex^^10, Chemin Henri Bessemer, 31200 Toulouse Midi Pyr\u00e9n\u00e9es",
    "addr:postcode":"31017;31200",
    "addr:street":"B.P. 2012;Chemin Henri Bessemer",
    "iso:country":"FR",
    "sg:address":"B.P. 2012, 31017 Toulouse C\u00e9dex^^10, Chemin Henri Bessemer, 31200 Toulouse",
    "sg:orig_category":"Non-Classified Establishments",
    "sg:phone":"+33 5 61 13 57 30",
    "sg:province":"Midi Pyr\u00e9n\u00e9es",
    "wof:name":"Mirouze Novacier S.a.",
    "wof:placetype":"venue"
},
  "geometry": {"coordinates":[1.44954,43.639011],"type":"Point"}
}