{
  "type": "Feature",
  "properties": {
    "addr:full":"2, Av. des Cit\u00e9s Unies d'Europe - B\u00e2t. C\u00e9ladon, 41100 Vend\u00f4me Vend\u00f4me Centre 41100",
    "addr:housenumber":"ba\u0302t",
    "addr:postcode":"41100;41100",
    "addr:street":"Av. Des Cite\u0301S Unies D'Europe",
    "iso:country":"FR",
    "sg:address":"2, Av. des Cit\u00e9s Unies d'Europe - B\u00e2t. C\u00e9ladon, 41100 Vend\u00f4me",
    "sg:city":"Vend\u00f4me",
    "sg:orig_category":"Non-Classified Establishments",
    "sg:phone":"+33 2 54 80 00 45",
    "sg:postcode":"41100",
    "sg:province":"Centre",
    "wof:name":"S'pec Environnement S.a.",
    "wof:placetype":"venue"
},
  "geometry": {"coordinates":[-2.15848,47.16864],"type":"Point"}
}