{
  "type": "Feature",
  "properties": {
    "addr:full":"56, Rue des Pr\u00e9voyants, 93240 Stains Ile de France",
    "addr:housenumber":"56",
    "addr:postcode":"93240;ile",
    "addr:street":"Rue Des Pre\u0301Voyants",
    "iso:country":"FR",
    "sg:address":"56, Rue des Pr\u00e9voyants, 93240 Stains",
    "sg:orig_category":"Non-Classified Establishments",
    "sg:phone":"+33 1 48 23 06 03",
    "sg:province":"Ile de France",
    "wof:name":"Transports Libessart Et Fils S.a.",
    "wof:placetype":"venue"
},
  "geometry": {"coordinates":[2.38691,48.967724],"type":"Point"}
}