{
  "type": "Feature",
  "properties": {
    "iso:country":"FR",
    "sg:address":"BP 241, 457 Promenade des Anglais, 06024 Nice Cedex, Dept 06",
    "sg:classifiers":[
        {
            "category":"Banks & Credit Unions",
            "subcategory":"Bank",
            "type":"Services"
        }
    ],
    "sg:phone":"+33 4 93 21 52 00",
    "sg:province":"Midi Pyr\u00e9n\u00e9es",
    "wof:name":"Banque Populaire De La C\u00f4te D'azur",
    "wof:placetype":"venue"
},
  "geometry": {"coordinates":[7.214637,43.667068],"type":"Point"}
}