{
  "type": "Feature",
  "properties": {
    "iso:country":"FR",
    "sg:address":"Place Pierre Bouchard",
    "sg:city":"Caen",
    "sg:classifiers":[
        {
            "category":"Banks & Credit Unions",
            "subcategory":"Financial Services",
            "type":"Services"
        }
    ],
    "sg:phone":"+33 2 31 27 75 75",
    "sg:postcode":"14000",
    "sg:province":"Basse Normandie",
    "sg:tags":[
        "banking",
        "finance",
        "insurance"
    ],
    "wof:name":"Caisse D'epargne Et De Prevoya Nce De Basse Normandie",
    "wof:placetype":"venue"
},
  "geometry": {"coordinates":[-0.364289,49.183834],"type":"Point"}
}