{
  "type": "Feature",
  "properties": {
    "addr:full":"13, Rue de Brest, 22100 Dinan Dinan Bretagne 22100",
    "addr:housenumber":"13",
    "addr:postcode":"22100;22100",
    "addr:street":"Rue De Brest",
    "iso:country":"FR",
    "sg:address":"13, Rue de Brest, 22100 Dinan",
    "sg:city":"Dinan",
    "sg:orig_category":"Non-Classified Establishments",
    "sg:phone":"+33 2 96 39 20 88",
    "sg:postcode":"22100",
    "sg:province":"Bretagne",
    "wof:name":"Etablissement Jules Mac\u00e9 S.a.",
    "wof:placetype":"venue"
},
  "geometry": {"coordinates":[-2.052302,48.453655],"type":"Point"}
}