{
  "type": "Feature",
  "properties": {
    "iso:country":"FR",
    "sg:address":"131 R Paul Vaillant Couturier 92240 Malakoff",
    "sg:classifiers":[
        {
            "category":"Professional",
            "subcategory":"Printing & Photocopies",
            "type":"Services"
        }
    ],
    "sg:phone":"+33 1 46 56 26 93",
    "sg:province":"Ile de France",
    "sg:tags":[
        "publishing"
    ],
    "wof:name":"Desclee De Brouwer Sa",
    "wof:placetype":"venue"
},
  "geometry": {"coordinates":[2.291978,48.816818],"type":"Point"}
}