{
  "type": "Feature",
  "properties": {
    "addr:full":"7, Rue des F\u00e9es, 49410 Saint Laurent du Mottay Pays de Loire",
    "addr:housenumber":"7",
    "addr:postcode":"49410",
    "addr:street":"Rue Des Fe\u0301Es;Mottay",
    "iso:country":"FR",
    "sg:address":"7, Rue des F\u00e9es, 49410 Saint Laurent du Mottay",
    "sg:orig_category":"Unclassifiable Establishments",
    "sg:phone":"+33 2 41 36 86 00",
    "sg:province":"Pays de Loire",
    "wof:name":"Etablissements Chapron Leroy Industrie S.a.",
    "wof:placetype":"venue"
},
  "geometry": {"coordinates":[-0.947655,47.352158],"type":"Point"}
}