{
  "type": "Feature",
  "properties": {
    "addr:full":"23, Rue Philibert Delorme, 75017 Paris Ile de France",
    "addr:housenumber":"23",
    "addr:postcode":"75017",
    "addr:street":"Rue Philibert Delorme",
    "iso:country":"FR",
    "sg:address":"23, Rue Philibert Delorme, 75017 Paris",
    "sg:orig_category":"Unclassifiable Establishments",
    "sg:phone":"+33 1 40 68 74 34",
    "sg:province":"Ile de France",
    "wof:name":"G.d.f. -gaz De France",
    "wof:placetype":"venue"
},
  "geometry": {"coordinates":[2.302563,48.88876],"type":"Point"}
}