{
  "type": "Feature",
  "properties": {
    "addr:full":"39 Route Nationale 66700 Argeles Sur Mer Languedoc-Roussillon 66700",
    "addr:housenumber":"39",
    "addr:postcode":"66700;66700",
    "addr:street":"Route Nationale;Argeles;Mer",
    "iso:country":"FR",
    "sg:address":"39 Route Nationale 66700 Argeles Sur Mer",
    "sg:classifiers":[
        {
            "category":"Manufacturing",
            "subcategory":"Jewelry",
            "type":"Manufacturing & Wholesale Goods"
        }
    ],
    "sg:phone":"+33 4 68 81 14 34",
    "sg:postcode":"66700",
    "sg:province":"Languedoc-Roussillon",
    "sg:tags":[
        "product",
        "miscellaneous",
        "jewellery"
    ],
    "wof:name":"Bijouterie Blanc",
    "wof:placetype":"venue"
},
  "geometry": {"coordinates":[3.02421,42.544521],"type":"Point"}
}