{
  "type": "Feature",
  "properties": {
    "addr:full":"Rte de Vannes Saint Herblain Pays de Loire 44800",
    "addr:postcode":"44800",
    "addr:street":"Rte De Vannes;Herblain",
    "iso:country":"FR",
    "sg:address":"Rte de Vannes",
    "sg:city":"Saint Herblain",
    "sg:orig_category":"Unclassifiable Establishments",
    "sg:phone":"+33 2 28 01 17 30",
    "sg:postcode":"44800",
    "sg:province":"Pays de Loire",
    "wof:name":"Secora S.a.r.l.",
    "wof:placetype":"venue"
},
  "geometry": {"coordinates":[-1.617495,47.25032],"type":"Point"}
}