{
  "type": "Feature",
  "properties": {
    "iso:country":"FR",
    "sg:address":"4, Bd Henri Becquerel, 57970 Yutz",
    "sg:orig_category":"Unclassifiable Establishments",
    "sg:phone":"+33 3 82 59 13 80",
    "sg:province":"Basse Normandie",
    "wof:name":"Institut De Soudure - Centre Laser",
    "wof:placetype":"venue"
},
  "geometry": {"coordinates":[6.17323,49.349098],"type":"Point"}
}