{
  "type": "Feature",
  "properties": {
    "iso:country":"FR",
    "sg:address":"Rue De L'Epinoy 59175 Templemars",
    "sg:classifiers":[
        {
            "category":"Shopping",
            "subcategory":"Crafts & Fabrics",
            "type":"Retail Goods"
        }
    ],
    "sg:phone":"+33 3 20 95 91 91",
    "sg:postcode":"59175",
    "sg:province":"Nord Pas-de-Calais",
    "sg:tags":[
        "textile",
        "clothing"
    ],
    "wof:name":"Nord Baches Ets",
    "wof:placetype":"venue"
},
  "geometry": {"coordinates":[3.068528,50.567921],"type":"Point"}
}