{
  "type": "Feature",
  "properties": {
    "addr:full":"ZI de Lospars 29510 Chateaulin Briec Bretagne 29510",
    "addr:postcode":"29510;29510",
    "addr:street":"Zi De Lospars;Briec",
    "iso:country":"FR",
    "sg:address":"ZI de Lospars 29510 Chateaulin",
    "sg:city":"Briec",
    "sg:classifiers":[
        {
            "category":"Professional",
            "type":"Services"
        }
    ],
    "sg:phone":"+33 2 98 16 11 00",
    "sg:postcode":"29510",
    "sg:province":"Bretagne",
    "sg:tags":[
        "transport",
        "road"
    ],
    "wof:name":"T.e.c.l",
    "wof:placetype":"venue"
},
  "geometry": {"coordinates":[-4.053139,48.226147],"type":"Point"}
}