{
  "type": "Feature",
  "properties": {
    "addr:full":"58 Rue Francois Mitterrand 58000 Nevers Nevers Bourgogne 58000",
    "addr:housenumber":"58",
    "addr:postcode":"58000;58000",
    "addr:street":"Rue Francois Mitterrand",
    "iso:country":"FR",
    "sg:address":"58 Rue Francois Mitterrand 58000 Nevers",
    "sg:city":"Nevers",
    "sg:classifiers":[
        {
            "category":"Shopping",
            "subcategory":"Clothing, Apparel, & Fashions",
            "type":"Retail Goods"
        }
    ],
    "sg:phone":"+33 3 86 57 40 88",
    "sg:postcode":"58000",
    "sg:province":"Bourgogne",
    "sg:tags":[
        "textile",
        "clothing",
        "clothes"
    ],
    "wof:name":"Promod",
    "wof:placetype":"venue"
},
  "geometry": {"coordinates":[3.162347,46.989594],"type":"Point"}
}