{
  "type": "Feature",
  "properties": {
    "addr:full":"Rte De Jean Mouton 64600 Anglet Anglet Aquitaine 64600",
    "addr:postcode":"64600;64600",
    "addr:street":"Rte De Jean Mouton",
    "iso:country":"FR",
    "sg:address":"Rte De Jean Mouton 64600 Anglet",
    "sg:city":"Anglet",
    "sg:classifiers":[
        {
            "category":"Health Services",
            "subcategory":"Medical Lab",
            "type":"Services"
        }
    ],
    "sg:phone":"+33 5 59 74 02 20",
    "sg:postcode":"64600",
    "sg:province":"Aquitaine",
    "sg:tags":[
        "chemical",
        "pharmaceutical",
        "pharmacy"
    ],
    "wof:name":"Ocp Repartition",
    "wof:placetype":"venue"
},
  "geometry": {"coordinates":[-1.525128,43.493431],"type":"Point"}
}