{
  "type": "Feature",
  "properties": {
    "iso:country":"FR",
    "sg:address":"866 Rn 7 Marina Airport 06270 Villeneuve Loubet",
    "sg:city":"Vill\u00e9",
    "sg:classifiers":[
        {
            "category":"Professional",
            "subcategory":"Computer Services",
            "type":"Services"
        }
    ],
    "sg:phone":"+33 4 93 22 52 00",
    "sg:postcode":"67220",
    "sg:province":"Alsace",
    "sg:tags":[
        "information",
        "technology",
        "software"
    ],
    "wof:name":"Tgs Europmedica",
    "wof:placetype":"venue"
},
  "geometry": {"coordinates":[7.120035,43.646286],"type":"Point"}
}