{
  "type": "Feature",
  "properties": {
    "addr:full":"26 Av Marcellin Berthelot 38036 Grenoble Cedex 2 Auvergne",
    "addr:postcode":"38036",
    "addr:street":"26 Av Marcellin Berthelot",
    "iso:country":"FR",
    "sg:address":"26 Av Marcellin Berthelot 38036 Grenoble Cedex 2",
    "sg:classifiers":[
        {
            "category":"Banks & Credit Unions",
            "subcategory":"Financial Services",
            "type":"Services"
        }
    ],
    "sg:phone":"+33 4 76 28 43 30",
    "sg:province":"Auvergne",
    "sg:tags":[
        "banking",
        "insurance",
        "institution",
        "finance"
    ],
    "wof:name":"Abcia",
    "wof:placetype":"venue"
},
  "geometry": {"coordinates":[5.72557,45.189621],"type":"Point"}
}