{
  "type": "Feature",
  "properties": {
    "addr:full":"2 Bernabo 13015 Marseille Provence-Alpes-C\u00f4te d'Azur",
    "addr:housenumber":"2",
    "addr:postcode":"13015",
    "addr:street":"Bernabo",
    "iso:country":"FR",
    "sg:address":"2",
    "sg:city":"Bernabo 13015 Marseille",
    "sg:classifiers":[
        {
            "category":"Professional",
            "type":"Services"
        }
    ],
    "sg:phone":"+33 4 91 69 35 95",
    "sg:province":"Provence-Alpes-C\u00f4te d'Azur",
    "sg:tags":[
        "transport"
    ],
    "wof:name":"Cdt",
    "wof:placetype":"venue"
},
  "geometry": {"coordinates":[5.355042,43.336433],"type":"Point"}
}