{
  "type": "Feature",
  "properties": {
    "addr:full":"70 Balard cedex 15 75502 Paris Ile de France",
    "addr:housenumber":"70;15",
    "addr:postcode":"75502",
    "addr:street":"Balard Cedex",
    "iso:country":"FR",
    "sg:address":"70",
    "sg:city":"Balard cedex 15 75502 Paris",
    "sg:classifiers":[
        {
            "category":"Utilities",
            "subcategory":"Telephone",
            "type":"Services"
        }
    ],
    "sg:phone":"+33 1 53 98 47 47",
    "sg:province":"Ile de France",
    "sg:tags":[
        "telecommunication"
    ],
    "wof:name":"Eutelsat (sa)",
    "wof:placetype":"venue"
},
  "geometry": {"coordinates":[2.29386,48.841679],"type":"Point"}
}