{
  "type": "Feature",
  "properties": {
    "iso:country":"FR",
    "sg:address":"17, Le Lac, 19700 Seilhac",
    "sg:orig_category":"Unclassifiable Establishments",
    "sg:phone":"+33 5 55 27 02 65",
    "sg:province":"Limousin",
    "wof:name":"Salaisons Du Lac S.a.r.l.",
    "wof:placetype":"venue"
},
  "geometry": {"coordinates":[1.697541,45.372787],"type":"Point"}
}