{
  "type": "Feature",
  "properties": {
    "iso:country":"FR",
    "sg:address":"11",
    "sg:city":"M\u00e9rignac",
    "sg:classifiers":[
        {
            "category":"Wholesale",
            "subcategory":"Machinery & Supplies",
            "type":"Manufacturing & Wholesale Goods"
        }
    ],
    "sg:phone":"+33 5 56 97 64 78",
    "sg:postcode":"33700",
    "sg:province":"Aquitaine",
    "sg:tags":[
        "equipment",
        "equipement",
        "precision",
        "timekeeping"
    ],
    "wof:name":"Tilko",
    "wof:placetype":"venue"
},
  "geometry": {"coordinates":[-0.65871,44.842037],"type":"Point"}
}