{
  "type": "Feature",
  "properties": {
    "addr:full":"B.P. 2002, 31017 Toulouse C\u00e9dex^^90, Rue de Fenouillet, 31200 Toulouse Midi Pyr\u00e9n\u00e9es 31200",
    "addr:postcode":"31017;31200;31200",
    "addr:street":"B.P. 2002;Rue De Fenouillet",
    "iso:country":"FR",
    "sg:address":"B.P. 2002, 31017 Toulouse C\u00e9dex^^90, Rue de Fenouillet, 31200 Toulouse",
    "sg:orig_category":"Non-Classified Establishments",
    "sg:phone":"+33 5 61 32 69 93",
    "sg:postcode":"31200",
    "sg:province":"Midi Pyr\u00e9n\u00e9es",
    "wof:name":"Delagnes Location Et Services S.a.",
    "wof:placetype":"venue"
},
  "geometry": {"coordinates":[1.39133,43.67865],"type":"Point"}
}