{
  "type": "Feature",
  "properties": {
    "iso:country":"FR",
    "sg:address":"Imp Des Fusains Za Des C\u00f4tes 74960 Meythet",
    "sg:classifiers":[
        {
            "category":"Manufacturing",
            "subcategory":"Motor Vehicles & Parts",
            "type":"Manufacturing & Wholesale Goods"
        }
    ],
    "sg:phone":"+33 4 50 22 77 00",
    "sg:postcode":"74960",
    "sg:province":"Rhone-Alpes",
    "sg:tags":[
        "engine",
        "machine",
        "engineering",
        "-",
        "mechanical"
    ],
    "wof:name":"Ets Michaud Et Chailly",
    "wof:placetype":"venue"
},
  "geometry": {"coordinates":[6.10647,45.907654],"type":"Point"}
}