{
  "type": "Feature",
  "properties": {
    "iso:country":"FR",
    "sg:address":"10, Av. de Chablis, 89144 Ligny le Ch\u00e2tel",
    "sg:city":"Ligny-le-Ch\u00e2tel",
    "sg:orig_category":"Unclassifiable Establishments",
    "sg:phone":"+33 3 86 47 42 04",
    "sg:postcode":"89144",
    "sg:province":"Bourgogne",
    "wof:name":"Gaunet S.a.r.l.",
    "wof:placetype":"venue"
},
  "geometry": {"coordinates":[3.757157,47.896427],"type":"Point"}
}