{
  "type": "Feature",
  "properties": {
    "iso:country":"FR",
    "sg:address":"47 Rue De Clichy 75009 Paris",
    "sg:classifiers":[
        {
            "category":"Professional",
            "subcategory":"Business Services",
            "type":"Services"
        }
    ],
    "sg:phone":"+33 1 48 78 64 06",
    "sg:postcode":"75009",
    "sg:province":"Ile de France",
    "sg:tags":[
        "body",
        "advice"
    ],
    "wof:name":"Unacerf",
    "wof:placetype":"venue"
},
  "geometry": {"coordinates":[2.328724,48.880268],"type":"Point"}
}