{
  "type": "Feature",
  "properties": {
    "iso:country":"FR",
    "sg:address":"ZI de la Pierre Foll\u00e8ge",
    "sg:city":"M\u00e9r\u00e9ville",
    "sg:orig_category":"Unclassifiable Establishments",
    "sg:phone":"+33 1 64 95 02 25",
    "sg:postcode":"91660",
    "sg:province":"Ile de France",
    "wof:name":"L' Union Des Forgerons S.a.",
    "wof:placetype":"venue"
},
  "geometry": {"coordinates":[2.087647,48.315521],"type":"Point"}
}