{
  "type": "Feature",
  "properties": {
    "iso:country":"FR",
    "sg:address":"72 rue Choletaise 49450 ST MACAIRE EN MAUGES",
    "sg:orig_category":"Ladies' Shoes",
    "sg:phone":"+33 2 41 46 29 00",
    "sg:postcode":"49450",
    "sg:province":"Pays de Loire",
    "wof:name":"Etablissements Pierre Chupin Sa",
    "wof:placetype":"venue"
},
  "geometry": {"coordinates":[-0.988629,47.12281],"type":"Point"}
}