{
  "type": "Feature",
  "properties": {
    "addr:full":"7, Rue du Mar\u00e9chal Juin, 64100 Bayonne Bayonne Aquitaine 64100",
    "addr:housenumber":"7",
    "addr:postcode":"64100 bayonne;64100",
    "addr:street":"Rue Du Mare\u0301Chal Juin",
    "iso:country":"FR",
    "sg:address":"7, Rue du Mar\u00e9chal Juin, 64100 Bayonne",
    "sg:city":"Bayonne",
    "sg:orig_category":"Unclassifiable Establishments",
    "sg:phone":"+33 5 59 55 02 26",
    "sg:postcode":"64100",
    "sg:province":"Aquitaine",
    "wof:name":"Aga S.a.",
    "wof:placetype":"venue"
},
  "geometry": {"coordinates":[-1.460669,43.49049],"type":"Point"}
}