{
  "type": "Feature",
  "properties": {
    "iso:country":"FR",
    "sg:address":"B.P. 39, 61600 La Fert\u00e9 Mac\u00e9 C\u00e9dex^^ZI Beauregard, 61600 La Fert\u00e9 Mac\u00e9",
    "sg:city":"Beauvain",
    "sg:orig_category":"Non-Classified Establishments",
    "sg:phone":"+33 2 33 37 08 33",
    "sg:postcode":"61600",
    "sg:province":"Basse Normandie",
    "wof:name":"Comp\u00e9dit Beauregard S.a.",
    "wof:placetype":"venue"
},
  "geometry": {"coordinates":[-0.300768,48.54089],"type":"Point"}
}