{
  "type": "Feature",
  "properties": {
    "iso:country":"FR",
    "sg:address":"RN 75",
    "sg:city":"Arandon",
    "sg:orig_category":"Unclassifiable Establishments",
    "sg:phone":"+33 4 74 80 81 55",
    "sg:postcode":"38510",
    "sg:province":"Rhone-Alpes",
    "wof:name":"Pouget Solami S.a.",
    "wof:placetype":"venue"
},
  "geometry": {"coordinates":[5.475785,45.635395],"type":"Point"}
}