{
  "type": "Feature",
  "properties": {
    "addr:full":"Rue des Minais Bouguenais Pays de Loire 44340",
    "addr:postcode":"44340",
    "addr:street":"Rue Des Minais Bouguenais Pays",
    "iso:country":"FR",
    "sg:address":"Rue des Minais",
    "sg:city":"Bouguenais",
    "sg:orig_category":"Non-Classified Establishments",
    "sg:phone":"+33 2 40 26 96 95",
    "sg:postcode":"44340",
    "sg:province":"Pays de Loire",
    "wof:name":"M.d. Electronic S.a.r.l.",
    "wof:placetype":"venue"
},
  "geometry": {"coordinates":[-1.637325,47.171162],"type":"Point"}
}