{
  "type": "Feature",
  "properties": {
    "addr:full":"B.P. 1043, 68053 Mulhouse C\u00e9dex^^9, Rue des Tanneurs, 68100 Mulhouse Mulhouse Alsace 68100",
    "addr:postcode":"68053;68100;68100",
    "addr:street":"B.P. 1043;Rue Des Tanneurs",
    "iso:country":"FR",
    "sg:address":"B.P. 1043, 68053 Mulhouse C\u00e9dex^^9, Rue des Tanneurs, 68100 Mulhouse",
    "sg:city":"Mulhouse",
    "sg:orig_category":"Non-Classified Establishments",
    "sg:phone":"+33 3 89 46 52 50",
    "sg:postcode":"68100",
    "sg:province":"Alsace",
    "wof:name":"Wiessler S.a.",
    "wof:placetype":"venue"
},
  "geometry": {"coordinates":[7.34365,47.751709],"type":"Point"}
}