{
  "type": "Feature",
  "properties": {
    "addr:full":"161 Rte De D\u00f4le 25000 Besan\u00e7on Franche Comt\u00e9 25000",
    "addr:housenumber":"161",
    "addr:postcode":"25000;25000",
    "addr:street":"Rte De Do\u0302Le;Franche Comte\u0301",
    "iso:country":"FR",
    "sg:address":"161 Rte De D\u00f4le 25000 Besan\u00e7on",
    "sg:classifiers":[
        {
            "category":"Wholesale",
            "subcategory":"Farm Supplies",
            "type":"Manufacturing & Wholesale Goods"
        }
    ],
    "sg:phone":"+33 3 81 41 64 64",
    "sg:postcode":"25000",
    "sg:province":"Franche Comt\u00e9",
    "sg:tags":[
        "-",
        "machine",
        "equipment",
        "engineering",
        "machinery",
        "mechanical",
        "agriculture"
    ],
    "wof:name":"Jardinerie Baudoin Sa",
    "wof:placetype":"venue"
},
  "geometry": {"coordinates":[6.025686,47.242317],"type":"Point"}
}