{
  "type": "Feature",
  "properties": {
    "addr:full":"3 place Louis Pradel 69001 Lyon Rhone-Alpes 69001",
    "addr:housenumber":"3",
    "addr:postcode":"69001;69001",
    "addr:street":"Place Louis Pradel",
    "iso:country":"FR",
    "sg:address":"3 place Louis Pradel 69001 Lyon",
    "sg:classifiers":[
        {
            "category":"Shopping",
            "subcategory":"Jewelry",
            "type":"Retail Goods"
        }
    ],
    "sg:phone":"+33 4 78 28 17 89",
    "sg:postcode":"69001",
    "sg:province":"Rhone-Alpes",
    "sg:tags":[
        "gemstone",
        "jewellery"
    ],
    "wof:name":"Golliat Et Didier Sa",
    "wof:placetype":"venue"
},
  "geometry": {"coordinates":[4.837209,45.767929],"type":"Point"}
}