{
  "type": "Feature",
  "properties": {
    "addr:full":"14 Rue De L Industrie 74160 St Julien En Genevois Rhone-Alpes",
    "addr:housenumber":"14",
    "addr:postcode":"74160 st",
    "addr:street":"Rue De L Industrie",
    "iso:country":"FR",
    "sg:address":"14 Rue De L Industrie 74160 St Julien En Genevois",
    "sg:classifiers":[
        {
            "category":"Manufacturing",
            "subcategory":"Rubber & Plastics",
            "type":"Manufacturing & Wholesale Goods"
        }
    ],
    "sg:phone":"+33 4 50 49 28 97",
    "sg:province":"Rhone-Alpes",
    "sg:tags":[
        "packaging",
        "material",
        "-"
    ],
    "wof:name":"Gilbert Cogne Et Fils Sarl",
    "wof:placetype":"venue"
},
  "geometry": {"coordinates":[6.085691,46.141304],"type":"Point"}
}