{
  "type": "Feature",
  "properties": {
    "addr:full":"4, Rue de l'Energie, 67720 Hoerdt Hoerdt Alsace 67720",
    "addr:housenumber":"4",
    "addr:postcode":"67720;67720",
    "addr:street":"Rue De L'Energie",
    "iso:country":"FR",
    "sg:address":"4, Rue de l'Energie, 67720 Hoerdt",
    "sg:city":"Hoerdt",
    "sg:orig_category":"Unclassifiable Establishments",
    "sg:phone":"+33 3 88 68 26 60",
    "sg:postcode":"67720",
    "sg:province":"Alsace",
    "wof:name":"Speck Pompes Industries",
    "wof:placetype":"venue"
},
  "geometry": {"coordinates":[7.791481,48.67453],"type":"Point"}
}