{
  "type": "Feature",
  "properties": {
    "iso:country":"FR",
    "sg:address":"B.P. 8307, 95803 Cergy Pontoise C\u00e9dex^^6, Av. du Centaure, 95800 Cergy",
    "sg:orig_category":"Non-Classified Establishments",
    "sg:phone":"+33 1 30 30 92 92",
    "sg:province":"Ile de France",
    "wof:name":"Oxalys S.a.r.l.",
    "wof:placetype":"venue"
},
  "geometry": {"coordinates":[2.000455,49.035156],"type":"Point"}
}