{
  "type": "Feature",
  "properties": {
    "addr:full":"Rue De Doullens 80045 Amiens Amiens Picardie 80000",
    "addr:postcode":"80045 amiens;80000",
    "addr:street":"Rue De Doullens",
    "iso:country":"FR",
    "sg:address":"Rue De Doullens 80045 Amiens",
    "sg:city":"Amiens",
    "sg:classifiers":[
        {
            "category":"Travel",
            "subcategory":"Hotels & Motels",
            "type":"Entertainment"
        }
    ],
    "sg:phone":"+33 3 22 43 51 91",
    "sg:postcode":"80000",
    "sg:province":"Picardie",
    "sg:tags":[
        "hotels",
        "business",
        "restaurant"
    ],
    "wof:name":"Casino Cafeteria",
    "wof:placetype":"venue"
},
  "geometry": {"coordinates":[2.30315,49.908428],"type":"Point"}
}