{
  "type": "Feature",
  "properties": {
    "addr:full":"24, Rte de Thionville, 57050 Metz Lorraine",
    "addr:housenumber":"24",
    "addr:postcode":"57050",
    "addr:street":"Rte De Thionville",
    "iso:country":"FR",
    "sg:address":"24, Rte de Thionville, 57050 Metz",
    "sg:orig_category":"Non-Classified Establishments",
    "sg:phone":"+33 3 87 30 02 49",
    "sg:province":"Lorraine",
    "wof:name":"Pinto Electricit\u00e9 G\u00e9n\u00e9rale S.a.r.l.",
    "wof:placetype":"venue"
},
  "geometry": {"coordinates":[6.168786,49.132805],"type":"Point"}
}