{
  "type": "Feature",
  "properties": {
    "addr:full":"91 Rte De La Roche-Sur-Yon 85300 Challans Pays de Loire 85300",
    "addr:housenumber":"91",
    "addr:postcode":"85300;85300",
    "addr:street":"Rte De La Roche-Sur-Yon",
    "iso:country":"FR",
    "sg:address":"91 Rte De La Roche-Sur-Yon 85300 Challans",
    "sg:classifiers":[
        {
            "category":"Professional",
            "subcategory":"Engineering",
            "type":"Services"
        }
    ],
    "sg:phone":"+33 2 51 49 18 06",
    "sg:postcode":"85300",
    "sg:province":"Pays de Loire",
    "sg:tags":[
        "-",
        "household",
        "appliance",
        "machine",
        "equipment",
        "electrical",
        "mechanical",
        "electronic"
    ],
    "wof:name":"Jf Cesbron Le Froid Sablais",
    "wof:placetype":"venue"
},
  "geometry": {"coordinates":[-1.861656,46.841194],"type":"Point"}
}