{
  "type": "Feature",
  "properties": {
    "iso:country":"FR",
    "sg:address":"rue Lavoisier 91430 Igny",
    "sg:classifiers":[
        {
            "category":"Wholesale",
            "subcategory":"Medical Equipment & Supplies",
            "type":"Manufacturing & Wholesale Goods"
        }
    ],
    "sg:phone":"+33 1 69 35 36 50",
    "sg:postcode":"91430",
    "sg:province":"Ile de France",
    "sg:tags":[
        "product",
        "medico-technical"
    ],
    "wof:name":"W. Epp Sa",
    "wof:placetype":"venue"
},
  "geometry": {"coordinates":[2.23289,48.731506],"type":"Point"}
}