{
  "type": "Feature",
  "properties": {
    "iso:country":"FR",
    "sg:address":"185, Bd de la Libert\u00e9, 59000 Lille",
    "sg:orig_category":"Unclassifiable Establishments",
    "sg:phone":"+33 3 20 14 44 00",
    "sg:province":"Nord Pas-de-Calais",
    "wof:name":"Agence R\u00e9gionale De D\u00e9veloppement",
    "wof:placetype":"venue"
},
  "geometry": {"coordinates":[3.064884,50.630161],"type":"Point"}
}