{
  "type": "Feature",
  "properties": {
    "iso:country":"FR",
    "sg:address":"B.P. 33, 68701 Cernay C\u00e9dex^^80, Rue de Wittelsheim, 68700 Cernay",
    "sg:city":"Cernay",
    "sg:orig_category":"Non-Classified Establishments",
    "sg:phone":"+33 3 89 75 44 13",
    "sg:postcode":"68700",
    "sg:province":"Alsace",
    "wof:name":"Sierra S.a.r.l.",
    "wof:placetype":"venue"
},
  "geometry": {"coordinates":[7.178375,47.809181],"type":"Point"}
}