{
  "type": "Feature",
  "properties": {
    "addr:full":"6, Rue Gutemberg, 57200 Sarreguemines Lorraine",
    "addr:housenumber":"6",
    "addr:postcode":"57200",
    "addr:street":"Rue Gutemberg",
    "iso:country":"FR",
    "sg:address":"6, Rue Gutemberg, 57200 Sarreguemines",
    "sg:orig_category":"Unclassifiable Establishments",
    "sg:phone":"+33 3 87 95 29 27",
    "sg:province":"Lorraine",
    "wof:name":"Refuge Diffusion S.a.r.l.",
    "wof:placetype":"venue"
},
  "geometry": {"coordinates":[7.094851,49.109921],"type":"Point"}
}