{
  "type": "Feature",
  "properties": {
    "addr:full":"6 Rue De Breteuil 94100 St Maur Des Foss\u00e9s Ile de France 94100",
    "addr:housenumber":"6",
    "addr:postcode":"94100;94100",
    "addr:street":"Rue De Breteuil;Des Fosse\u0301S Ile De France",
    "iso:country":"FR",
    "sg:address":"6 Rue De Breteuil 94100 St Maur Des Foss\u00e9s",
    "sg:classifiers":[
        {
            "category":"Professional",
            "subcategory":"Business Services",
            "type":"Services"
        }
    ],
    "sg:phone":"+33 1 45 11 23 04",
    "sg:postcode":"94100",
    "sg:province":"Ile de France",
    "sg:tags":[
        "rubber",
        "advice",
        "plastic"
    ],
    "wof:name":"Ste D'expansion De Nettoyage Sarl",
    "wof:placetype":"venue"
},
  "geometry": {"coordinates":[2.475565,48.804657],"type":"Point"}
}