{
  "type": "Feature",
  "properties": {
    "iso:country":"FR",
    "sg:address":"44, Rue Georges Cl\u00e9menceau, 41200 Romorantin Lanthenay",
    "sg:city":"Villefranche-sur-Cher",
    "sg:orig_category":"Non-Classified Establishments",
    "sg:phone":"+33 2 54 76 02 41",
    "sg:postcode":"41200",
    "sg:province":"Centre",
    "wof:name":"Photo Perraguin S.a.r.l.",
    "wof:placetype":"venue"
},
  "geometry": {"coordinates":[1.744221,47.35918],"type":"Point"}
}