{
  "type": "Feature",
  "properties": {
    "iso:country":"FR",
    "sg:address":"Av. du R\u00e9giment de Bigorre",
    "sg:city":"Vic en Bigorre",
    "sg:orig_category":"Unclassifiable Establishments",
    "sg:phone":"+33 5 62 33 73 50",
    "sg:postcode":"65500",
    "sg:province":"Midi Pyr\u00e9n\u00e9es",
    "wof:name":"C.a.d. Tarbes - Coop\u00e9rative Agricole D\u00e9partementale Tarbes",
    "wof:placetype":"venue"
},
  "geometry": {"coordinates":[0.06396,43.387035],"type":"Point"}
}