{
  "type": "Feature",
  "properties": {
    "iso:country":"FR",
    "sg:address":"ZI Vic",
    "sg:city":"Castanet Tolosan",
    "sg:orig_category":"Unclassifiable Establishments",
    "sg:phone":"+33 5 61 27 80 21",
    "sg:postcode":"31320",
    "sg:province":"Midi Pyr\u00e9n\u00e9es",
    "wof:name":"Alpha Vague S.a.r.l.",
    "wof:placetype":"venue"
},
  "geometry": {"coordinates":[1.49836,43.516346],"type":"Point"}
}