{
  "type": "Feature",
  "properties": {
    "addr:full":"Rue Henri Barbusse Saint Amand les Eaux Nord Pas-de-Calais 59230",
    "addr:postcode":"59230",
    "addr:street":"Rue Henri Barbusse Saint;Les;Pas-De-Calais",
    "iso:country":"FR",
    "sg:address":"Rue Henri Barbusse",
    "sg:city":"Saint Amand les Eaux",
    "sg:orig_category":"Unclassifiable Establishments",
    "sg:phone":"+33 3 27 48 59 31",
    "sg:postcode":"59230",
    "sg:province":"Nord Pas-de-Calais",
    "wof:name":"Winter Paul S.a.",
    "wof:placetype":"venue"
},
  "geometry": {"coordinates":[3.425281,50.445984],"type":"Point"}
}