{
  "type": "Feature",
  "properties": {
    "iso:country":"FR",
    "sg:address":"Rue Henri Barbusse",
    "sg:city":"Saint Amand les Eaux",
    "sg:orig_category":"Unclassifiable Establishments",
    "sg:phone":"+33 3 27 48 59 31",
    "sg:postcode":"59230",
    "sg:province":"Nord Pas-de-Calais",
    "wof:name":"Winter Paul S.a.",
    "wof:placetype":"venue"
},
  "geometry": {"coordinates":[3.425281,50.445984],"type":"Point"}
}