{
  "type": "Feature",
  "properties": {
    "iso:country":"FR",
    "sg:address":"3, Av. Marcel Casti\u00e9 - Immeuble la Boussole, 83000 Toulon",
    "sg:orig_category":"Unclassifiable Establishments",
    "sg:phone":"+33 4 98 00 80 00",
    "sg:province":"Provence-Alpes-C\u00f4te d'Azur",
    "wof:name":"Alliance Sant\u00e9 S.a.s.",
    "wof:placetype":"venue"
},
  "geometry": {"coordinates":[5.939256,43.123123],"type":"Point"}
}