{
  "type": "Feature",
  "properties": {
    "addr:full":"13 rue des Fr\u00e8res Lumi\u00e8re 39200 AVIGNON LES ST CLAUDE Franche Comt\u00e9 39200",
    "addr:housenumber":"13",
    "addr:postcode":"39200;39200",
    "addr:street":"Rue Des Fre\u0300Res Lumie\u0300Re;Les St;Franche Comte\u0301",
    "iso:country":"FR",
    "sg:address":"13 rue des Fr\u00e8res Lumi\u00e8re 39200 AVIGNON LES ST CLAUDE",
    "sg:classifiers":[
        {
            "category":"Wholesale",
            "subcategory":"Plants",
            "type":"Manufacturing & Wholesale Goods"
        }
    ],
    "sg:phone":"+33 3 84 45 23 10",
    "sg:postcode":"39200",
    "sg:province":"Franche Comt\u00e9",
    "sg:tags":[
        "extraction",
        "apparatus"
    ],
    "wof:name":"Sicom\u00e9tal Jura S.a.",
    "wof:placetype":"venue"
},
  "geometry": {"coordinates":[5.827136,46.383099],"type":"Point"}
}