{
  "type": "Feature",
  "properties": {
    "iso:country":"FR",
    "sg:address":"12 Rue Tonnellerie BP 187 16106 Cognac",
    "sg:classifiers":[
        {
            "category":"Home & Garden",
            "subcategory":"Furniture",
            "type":"Retail Goods"
        }
    ],
    "sg:phone":"+33 5 46 96 43 01",
    "sg:province":"Franche Comt\u00e9",
    "sg:tags":[
        "wood"
    ],
    "wof:name":"Tonnellerie Garnier Sa",
    "wof:placetype":"venue"
},
  "geometry": {"coordinates":[-0.325174,45.693745],"type":"Point"}
}