{
  "type": "Feature",
  "properties": {
    "iso:country":"FR",
    "sg:address":"2, Rue Marmiesse, 76600 Le Havre",
    "sg:orig_category":"Non-Classified Establishments",
    "sg:phone":"+33 2 35 53 06 26",
    "sg:province":"Haute Normandie",
    "wof:name":"Inger Transport S.a.r.l.",
    "wof:placetype":"venue"
},
  "geometry": {"coordinates":[0.156336,49.47723],"type":"Point"}
}