{
  "type": "Feature",
  "properties": {
    "iso:country":"FR",
    "sg:address":"Rue Joseph Marie Jacquard 82000 Montauban",
    "sg:classifiers":[
        {
            "category":"Professional",
            "type":"Services"
        }
    ],
    "sg:phone":"+33 5 63 66 85 85",
    "sg:province":"Midi Pyr\u00e9n\u00e9es",
    "sg:tags":[
        "transport",
        "road"
    ],
    "wof:name":"Laporte Emile Sarl",
    "wof:placetype":"venue"
},
  "geometry": {"coordinates":[1.36068,44.038296],"type":"Point"}
}