{
  "type": "Feature",
  "properties": {
    "iso:country":"FR",
    "sg:address":"Hameau De Boscherville Route Du Neubourg 27520 Bourgtheroulde Infreville",
    "sg:classifiers":[
        {
            "category":"Shopping",
            "subcategory":"Hobbies, Toys, & Games",
            "type":"Retail Goods"
        }
    ],
    "sg:phone":"+33 2 35 87 60 33",
    "sg:postcode":"27520",
    "sg:province":"Haute Normandie",
    "sg:tags":[
        "machine",
        "engineering",
        "mechanical",
        "-",
        "entertainment"
    ],
    "wof:name":"Sarl Carrosserie Pain",
    "wof:placetype":"venue"
},
  "geometry": {"coordinates":[0.873935,49.299084],"type":"Point"}
}