{
  "type": "Feature",
  "properties": {
    "iso:country":"FR",
    "sg:address":"Chemin Cartallier 38780 PONT EVEQUE",
    "sg:classifiers":[
        {
            "category":"Shopping",
            "subcategory":"Stationery & Office Supplies",
            "type":"Retail Goods"
        }
    ],
    "sg:phone":"+33 4 74 16 10 10",
    "sg:postcode":"38780",
    "sg:province":"Rhone-Alpes",
    "sg:tags":[
        "adhesive",
        "label"
    ],
    "wof:name":"Ahlstrom La Gere S.a.",
    "wof:placetype":"venue"
},
  "geometry": {"coordinates":[4.911575,45.526772],"type":"Point"}
}