{
  "type": "Feature",
  "properties": {
    "iso:country":"FR",
    "sg:address":"Chemin De Sellieres 10100 Romilly Sur Seine",
    "sg:classifiers":[
        {
            "category":"Shopping",
            "subcategory":"Clothing, Apparel, & Fashions",
            "type":"Retail Goods"
        }
    ],
    "sg:phone":"+33 3 25 21 03 13",
    "sg:postcode":"10100",
    "sg:province":"Champagne",
    "sg:tags":[
        "textile",
        "clothing",
        "clothes"
    ],
    "wof:name":"Sarl Upa Lingerie",
    "wof:placetype":"venue"
},
  "geometry": {"coordinates":[3.687855,48.51775],"type":"Point"}
}