{
  "type": "Feature",
  "properties": {
    "addr:full":"1890 Chemin St Bernard 06221 VALLAURIS CEDEX Provence-Alpes-C\u00f4te d'Azur",
    "addr:housenumber":"1890",
    "addr:postcode":"06221;cedex",
    "addr:street":"Chemin St Bernard",
    "iso:country":"FR",
    "sg:address":"1890 Chemin St Bernard 06221 VALLAURIS CEDEX",
    "sg:classifiers":[
        {
            "category":"Professional",
            "subcategory":"Business Services",
            "type":"Services"
        }
    ],
    "sg:phone":"+33 4 93 65 23 03",
    "sg:province":"Provence-Alpes-C\u00f4te d'Azur",
    "sg:tags":[
        "industry",
        "trade"
    ],
    "wof:name":"Hygienarome Services Sarl",
    "wof:placetype":"venue"
},
  "geometry": {"coordinates":[7.057408,43.593834],"type":"Point"}
}