{
  "type": "Feature",
  "properties": {
    "addr:full":"8, Rue de Denain, 03100 Montlu\u00e7on Montlu\u00e7on Auvergne 03100",
    "addr:housenumber":"8",
    "addr:postcode":"03100;03100",
    "addr:street":"Rue De Denain",
    "iso:country":"FR",
    "sg:address":"8, Rue de Denain, 03100 Montlu\u00e7on",
    "sg:city":"Montlu\u00e7on",
    "sg:orig_category":"Unclassifiable Establishments",
    "sg:phone":"+33 4 70 28 34 24",
    "sg:postcode":"03100",
    "sg:province":"Auvergne",
    "wof:name":"Etablissements Mon Jardin S.a.",
    "wof:placetype":"venue"
},
  "geometry": {"coordinates":[2.588742,46.34549],"type":"Point"}
}