{
  "type": "Feature",
  "properties": {
    "addr:full":"1, Rue du Fonds Pernant - Zone 3, 60200 Compi\u00e8gne Picardie",
    "addr:housenumber":"1",
    "addr:postcode":"60200",
    "addr:street":"Rue Du Fonds Pernant",
    "iso:country":"FR",
    "sg:address":"1, Rue du Fonds Pernant - Zone 3, 60200 Compi\u00e8gne",
    "sg:orig_category":"Non-Classified Establishments",
    "sg:phone":"+33 3 44 86 58 00",
    "sg:province":"Picardie",
    "wof:name":"Or\u00e9fi Transmissions Stock S.a.",
    "wof:placetype":"venue"
},
  "geometry": {"coordinates":[2.825,49.417671],"type":"Point"}
}