{
  "type": "Feature",
  "properties": {
    "addr:full":"6 ter, Av. de la Lib\u00e9ration, 95220 Herblay Ile de France",
    "addr:housenumber":"6",
    "addr:postcode":"95220;ile",
    "addr:street":"Ter Av. De La Libe\u0301Ration",
    "iso:country":"FR",
    "sg:address":"6 ter, Av. de la Lib\u00e9ration, 95220 Herblay",
    "sg:orig_category":"Non-Classified Establishments",
    "sg:phone":"+33 1 39 31 33 00",
    "sg:province":"Ile de France",
    "wof:name":"Location Distribution Entreposage S.a.r.l.",
    "wof:placetype":"venue"
},
  "geometry": {"coordinates":[2.183042,49.001022],"type":"Point"}
}