{
  "type": "Feature",
  "properties": {
    "iso:country":"FR",
    "sg:address":"7 pl du 8 Septembre; Besan\u00e7on; 25090",
    "sg:city":"Besan\u00e7on",
    "sg:classifiers":[
        {
            "category":"Banks & Credit Unions",
            "subcategory":"Bank",
            "type":"Services"
        }
    ],
    "sg:phone":"+33 3381834790",
    "sg:postcode":"25000",
    "sg:province":"Franche Comt\u00e9",
    "wof:name":"Cr\u00e9dit Foncier De France",
    "wof:placetype":"venue"
},
  "geometry": {"coordinates":[6.024318,47.238346],"type":"Point"}
}