{
  "type": "Feature",
  "properties": {
    "addr:full":"Zi D'En Tourre Rue Joseph Jacquard 11400 Castelnaudary Languedoc-Roussillon 11400",
    "addr:postcode":"11400;11400",
    "addr:street":"Zi D'En Tourre Rue Joseph Jacquard",
    "iso:country":"FR",
    "sg:address":"Zi D'En Tourre",
    "sg:city":"Rue Joseph Jacquard 11400 Castelnaudary",
    "sg:classifiers":[
        {
            "category":"Manufacturing",
            "subcategory":"Metals",
            "type":"Manufacturing & Wholesale Goods"
        }
    ],
    "sg:phone":"+33 4 68 23 15 57",
    "sg:postcode":"11400",
    "sg:province":"Languedoc-Roussillon",
    "sg:tags":[
        "metallurgy",
        "steel",
        "metalworking"
    ],
    "wof:name":"Plastisud Sa",
    "wof:placetype":"venue"
},
  "geometry": {"coordinates":[1.955583,43.308224],"type":"Point"}
}