{
  "type": "Feature",
  "properties": {
    "iso:country":"FR",
    "sg:address":"5 avenue du Mar\u00e9chal Juin 92100 Boulogne Billancourt",
    "sg:classifiers":[
        {
            "category":"Retail",
            "subcategory":"Event Space",
            "type":"Services"
        }
    ],
    "sg:phone":"+33 1 46 05 13 95",
    "sg:province":"Ile de France",
    "sg:tags":[
        "telecommunication"
    ],
    "wof:name":"Ouverture Internationale Sa",
    "wof:placetype":"venue"
},
  "geometry": {"coordinates":[2.228614,48.832394],"type":"Point"}
}