{
  "type": "Feature",
  "properties": {
    "addr:full":"133, Bd Davout, 75020 Paris Ile de France",
    "addr:housenumber":"133",
    "addr:postcode":"75020",
    "addr:street":"Bd Davout",
    "iso:country":"FR",
    "sg:address":"133, Bd Davout, 75020 Paris",
    "sg:orig_category":"Unclassifiable Establishments",
    "sg:phone":"+33 1 56 06 20 00",
    "sg:province":"Ile de France",
    "wof:name":"I.n.e.d. - Institut National D'etudes D\u00e9mographiques",
    "wof:placetype":"venue"
},
  "geometry": {"coordinates":[2.409587,48.857952],"type":"Point"}
}