{
  "type": "Feature",
  "properties": {
    "addr:full":"Route Quatre Chemins 83460 Les Arcs Franche Comt\u00e9",
    "addr:postcode":"83460",
    "addr:street":"Route Quatre Chemins;Franche Comte\u0301",
    "iso:country":"FR",
    "sg:address":"Route Quatre Chemins 83460 Les Arcs",
    "sg:classifiers":[
        {
            "category":"Wholesale",
            "subcategory":"Machinery & Supplies",
            "type":"Manufacturing & Wholesale Goods"
        }
    ],
    "sg:phone":"+33 4 94 47 41 63",
    "sg:province":"Franche Comt\u00e9",
    "sg:tags":[
        "handling",
        "material",
        "-",
        "machine",
        "equipment",
        "engineering",
        "mechanical"
    ],
    "wof:name":"Chieusse Levage Sarl",
    "wof:placetype":"venue"
},
  "geometry": {"coordinates":[6.480395,43.461021],"type":"Point"}
}