{
  "type": "Feature",
  "properties": {
    "addr:full":"12, Rue du Parc, 91430 Igny Ile de France",
    "addr:housenumber":"12",
    "addr:postcode":"91430",
    "addr:street":"Rue Du Parc",
    "iso:country":"FR",
    "sg:address":"12, Rue du Parc, 91430 Igny",
    "sg:orig_category":"Unclassifiable Establishments",
    "sg:phone":"+33 1 60 19 10 92",
    "sg:province":"Ile de France",
    "wof:name":"3.c. S.a.r.l. - Claude Cornec Consultant",
    "wof:placetype":"venue"
},
  "geometry": {"coordinates":[2.237288,48.735054],"type":"Point"}
}