{
  "type": "Feature",
  "properties": {
    "addr:full":"3, Place du Mar\u00e9chal Foch, 95880 Enghien les Bains Ile de France",
    "addr:housenumber":"3",
    "addr:postcode":"95880;ile",
    "addr:street":"Place Du Mare\u0301Chal Foch",
    "iso:country":"FR",
    "sg:address":"3, Place du Mar\u00e9chal Foch, 95880 Enghien les Bains",
    "sg:orig_category":"Unclassifiable Establishments",
    "sg:phone":"+33 1 34 28 52 25",
    "sg:province":"Ile de France",
    "wof:name":"Caixabank S.a.",
    "wof:placetype":"venue"
},
  "geometry": {"coordinates":[2.309095,48.971916],"type":"Point"}
}