{
  "type": "Feature",
  "properties": {
    "addr:full":"Zi 25440 Quingey Franche Comt\u00e9 25440",
    "addr:postcode":"25440;25440",
    "addr:street":"Zi;Franche Comte\u0301",
    "iso:country":"FR",
    "sg:address":"Zi 25440 Quingey",
    "sg:classifiers":[
        {
            "category":"Shopping",
            "type":"Retail Goods"
        }
    ],
    "sg:phone":"+33 3 81 63 79 00",
    "sg:postcode":"25440",
    "sg:province":"Franche Comt\u00e9",
    "sg:tags":[
        "metallurgy",
        "finished",
        "-",
        "metalworking",
        "metallic"
    ],
    "wof:name":"Usines Metallurgiques Jean Simon Sa",
    "wof:placetype":"venue"
},
  "geometry": {"coordinates":[5.959787,47.139881],"type":"Point"}
}