{
  "type": "Feature",
  "properties": {
    "addr:full":"1 Rue Pointe 72700 Spay Pays de Loire",
    "addr:housenumber":"1",
    "addr:postcode":"72700",
    "addr:street":"Rue Pointe",
    "iso:country":"FR",
    "sg:address":"1 Rue Pointe 72700 Spay",
    "sg:classifiers":[
        {
            "category":"Manufacturing",
            "subcategory":"Rubber & Plastics",
            "type":"Manufacturing & Wholesale Goods"
        }
    ],
    "sg:phone":"+33 2 43 21 11 11",
    "sg:province":"Pays de Loire",
    "wof:name":"Saf Froid Sarl",
    "wof:placetype":"venue"
},
  "geometry": {"coordinates":[0.139275,47.94276],"type":"Point"}
}