{
  "type": "Feature",
  "properties": {
    "iso:country":"FR",
    "sg:address":"37, Rue Prosper Cabriol, 54940 Belleville",
    "sg:orig_category":"Non-Classified Establishments",
    "sg:phone":"+33 3 83 24 08 35",
    "sg:postcode":"54940",
    "sg:province":"Lorraine",
    "wof:name":"Acometal S.a.r.l.",
    "wof:placetype":"venue"
},
  "geometry": {"coordinates":[6.103096,48.81971],"type":"Point"}
}