{
  "type": "Feature",
  "properties": {
    "iso:country":"FR",
    "sg:address":"16 Rue Carpont 22440 Ploufragan",
    "sg:city":"Ploufragan",
    "sg:classifiers":[
        {
            "category":"Farming",
            "subcategory":"Livestock Farm",
            "type":"Manufacturing & Wholesale Goods"
        }
    ],
    "sg:phone":"+33 2 96 01 58 58",
    "sg:postcode":"22440",
    "sg:province":"Bretagne",
    "sg:tags":[
        "grain",
        "agriculture",
        "cereal"
    ],
    "wof:name":"Ets Alfred Kervegant Eurl",
    "wof:placetype":"venue"
},
  "geometry": {"coordinates":[-2.777181,48.501087],"type":"Point"}
}