{
  "type": "Feature",
  "properties": {
    "addr:full":"B.P. 77, 68392 Sausheim C\u00e9dex^^RN - 1 Centre d'activit\u00e9 Actipolis, 68390 Sausheim Sausheim Alsace 68390",
    "addr:housenumber":"1",
    "addr:postcode":"68392;68390;68390",
    "addr:street":"B.P. 77;Ce\u0301Dex^^Rn;Actipolis;Sausheim",
    "iso:country":"FR",
    "sg:address":"B.P. 77, 68392 Sausheim C\u00e9dex^^RN - 1 Centre d'activit\u00e9 Actipolis, 68390 Sausheim",
    "sg:city":"Sausheim",
    "sg:orig_category":"Non-Classified Establishments",
    "sg:phone":"+33 3 89 61 52 12",
    "sg:postcode":"68390",
    "sg:province":"Alsace",
    "wof:name":"C2b International S.a.r.l.",
    "wof:placetype":"venue"
},
  "geometry": {"coordinates":[7.40721,47.802368],"type":"Point"}
}