{
  "type": "Feature",
  "properties": {
    "addr:full":"18 Avenue De Kergroise 56326 Lorient Cedex Picardie",
    "addr:housenumber":"18",
    "addr:postcode":"56326",
    "addr:street":"Avenue De Kergroise",
    "iso:country":"FR",
    "sg:address":"18 Avenue De Kergroise 56326 Lorient Cedex",
    "sg:classifiers":[
        {
            "category":"Wholesale",
            "subcategory":"Machinery & Supplies",
            "type":"Manufacturing & Wholesale Goods"
        }
    ],
    "sg:phone":"+33 2 97 37 37 11",
    "sg:province":"Picardie",
    "sg:tags":[
        "handling",
        "material",
        "-",
        "machine",
        "equipment",
        "engineering",
        "mechanical"
    ],
    "wof:name":"Ateliers De Kergroise Sa",
    "wof:placetype":"venue"
},
  "geometry": {"coordinates":[-3.359185,47.735397],"type":"Point"}
}