{
  "type": "Feature",
  "properties": {
    "addr:full":"Rue d'Humbecourt Eclaron Braucourt Sainte Livi\u00e8re Champagne 52290",
    "addr:postcode":"52290",
    "addr:street":"Rue D'Humbecourt;Champagne",
    "iso:country":"FR",
    "sg:address":"Rue d'Humbecourt",
    "sg:city":"Eclaron Braucourt Sainte Livi\u00e8re",
    "sg:orig_category":"Unclassifiable Establishments",
    "sg:phone":"+33 3 25 04 10 03",
    "sg:postcode":"52290",
    "sg:province":"Champagne",
    "wof:name":"Coop\u00e9rative Agricole De Distillerie Et De D\u00e9shydratation D'eclaron",
    "wof:placetype":"venue"
},
  "geometry": {"coordinates":[4.90084,48.58189],"type":"Point"}
}