{
  "type": "Feature",
  "properties": {
    "iso:country":"FR",
    "sg:address":"53, Av. Gustave Flaubert et 44 rue de Buffon, 76000 Rouen",
    "sg:orig_category":"Non-Classified Establishments",
    "sg:phone":"+33 2 32 08 44 47",
    "sg:postcode":"76000",
    "sg:province":"Haute Normandie",
    "wof:name":"Altex France S.a.r.l.",
    "wof:placetype":"venue"
},
  "geometry": {"coordinates":[1.08933,49.44038],"type":"Point"}
}