{
  "type": "Feature",
  "properties": {
    "addr:full":"25, Av. Paul Laurens, 26110 Nyons Rhone-Alpes",
    "addr:postcode":"26110",
    "addr:street":"25 Av. Paul Laurens",
    "iso:country":"FR",
    "sg:address":"25, Av. Paul Laurens, 26110 Nyons",
    "sg:orig_category":"Non-Classified Establishments",
    "sg:phone":"+33 4 75 26 29 97",
    "sg:province":"Rhone-Alpes",
    "wof:name":"Ile",
    "wof:placetype":"venue"
},
  "geometry": {"coordinates":[5.137088,44.360325],"type":"Point"}
}