{
  "type": "Feature",
  "properties": {
    "iso:country":"FR",
    "sg:address":"B.P. 7124, 69302 Lyon C\u00e9dex 07^^32/34, Rue Domer, 69007 Lyon",
    "sg:orig_category":"Non-Classified Establishments",
    "sg:phone":"+33 4 78 72 61 61",
    "sg:postcode":"69007",
    "sg:province":"Rhone-Alpes",
    "wof:name":"J. Par\u00e9 Et Compagnie S.a.",
    "wof:placetype":"venue"
},
  "geometry": {"coordinates":[4.842415,45.746235],"type":"Point"}
}