{
  "type": "Feature",
  "properties": {
    "iso:country":"FR",
    "sg:address":"Rte des Dolines - Le Thalassa",
    "sg:city":"Valbonne",
    "sg:orig_category":"Unclassifiable Establishments",
    "sg:phone":"+33 4 93 95 85 95",
    "sg:postcode":"06560",
    "sg:province":"Rhone-Alpes",
    "wof:name":"Oger International",
    "wof:placetype":"venue"
},
  "geometry": {"coordinates":[7.0314,43.63126],"type":"Point"}
}