{
  "type": "Feature",
  "properties": {
    "addr:full":"7, Rue du Chapelet - ZAC de la N\u00e9gresse, 64200 Biarritz Biarritz Aquitaine 64200",
    "addr:housenumber":"7",
    "addr:postcode":"64200;64200",
    "addr:street":"Rue Du Chapelet Zac De La Ne\u0301Gresse",
    "iso:country":"FR",
    "sg:address":"7, Rue du Chapelet - ZAC de la N\u00e9gresse, 64200 Biarritz",
    "sg:city":"Biarritz",
    "sg:orig_category":"Non-Classified Establishments",
    "sg:phone":"+33 5 59 23 99 85",
    "sg:postcode":"64200",
    "sg:province":"Aquitaine",
    "wof:name":"M\u00e9canique D'aquitaine S.a.",
    "wof:placetype":"venue"
},
  "geometry": {"coordinates":[-1.558793,43.482571],"type":"Point"}
}