{
  "type": "Feature",
  "properties": {
    "addr:full":"371, Av. du March\u00e9 Gare, 34000 Montpellier Languedoc-Roussillon",
    "addr:housenumber":"371",
    "addr:postcode":"34000",
    "addr:street":"Av. Du Marche\u0301 Gare",
    "iso:country":"FR",
    "sg:address":"371, Av. du March\u00e9 Gare, 34000 Montpellier",
    "sg:orig_category":"Unclassifiable Establishments",
    "sg:phone":"+33 4 67 92 21 23",
    "sg:province":"Languedoc-Roussillon",
    "wof:name":"Breguiboul Jean Distribution S.a.",
    "wof:placetype":"venue"
},
  "geometry": {"coordinates":[3.881168,43.585613],"type":"Point"}
}