{
  "type": "Feature",
  "properties": {
    "addr:full":"351, Rue de la Morandi\u00e8re, 37260 Monts Monts Centre 37260",
    "addr:housenumber":"351",
    "addr:postcode":"37260;37260",
    "addr:street":"Rue De La Morandie\u0300Re;Monts",
    "iso:country":"FR",
    "sg:address":"351, Rue de la Morandi\u00e8re, 37260 Monts",
    "sg:city":"Monts",
    "sg:orig_category":"Non-Classified Establishments",
    "sg:phone":"+33 2 47 26 71 82",
    "sg:postcode":"37260",
    "sg:province":"Centre",
    "wof:name":"M.t.m S.n.c.",
    "wof:placetype":"venue"
},
  "geometry": {"coordinates":[0.65593,47.280266],"type":"Point"}
}