{
  "type": "Feature",
  "properties": {
    "addr:full":"Rue des Famards - Acticentre Lesquin C\u00e9dex Languedoc-Roussillon 59818",
    "addr:postcode":"ce\u0301dex;59818",
    "addr:street":"Rue Des Famards Acticentre",
    "iso:country":"FR",
    "sg:address":"Rue des Famards - Acticentre",
    "sg:city":"Lesquin C\u00e9dex",
    "sg:orig_category":"Unclassifiable Establishments",
    "sg:phone":"+33 3 20 87 59 14",
    "sg:postcode":"59818",
    "sg:province":"Languedoc-Roussillon",
    "wof:name":"Sin & St\u00e9s S.a.",
    "wof:placetype":"venue"
},
  "geometry": {"coordinates":[3.11003,50.588009],"type":"Point"}
}