{
  "type": "Feature",
  "properties": {
    "iso:country":"FR",
    "sg:address":"Rue St Eloi Zi Des Gravieres 89600 Vergigny",
    "sg:city":"Vergigny",
    "sg:classifiers":[
        {
            "category":"Manufacturing",
            "subcategory":"Wood Products",
            "type":"Manufacturing & Wholesale Goods"
        }
    ],
    "sg:phone":"+33 3 86 43 75 70",
    "sg:postcode":"89600",
    "sg:province":"Bourgogne",
    "sg:tags":[
        "furniture"
    ],
    "wof:name":"Roy Agencements",
    "wof:placetype":"venue"
},
  "geometry": {"coordinates":[3.72972,48.002575],"type":"Point"}
}