{
  "type": "Feature",
  "properties": {
    "iso:country":"FR",
    "sg:address":"Rue Denis Papin - ZA",
    "sg:city":"Villelongue de la Salanque",
    "sg:orig_category":"Non-Classified Establishments",
    "sg:phone":"+33 4 68 73 33 07",
    "sg:postcode":"66410",
    "sg:province":"Languedoc-Roussillon",
    "wof:name":"S.i.d.e.m. S.a.r.l.",
    "wof:placetype":"venue"
},
  "geometry": {"coordinates":[2.98555,42.727612],"type":"Point"}
}