{
  "type": "Feature",
  "properties": {
    "addr:full":"110 Rue De La Cigale 45110 Ch\u00e2teauneuf Sur Loire Ch\u00e2teauneuf-sur-Loire Centre 45110",
    "addr:housenumber":"110;cha\u0302teauneuf-sur-loire",
    "addr:postcode":"45110;45110",
    "addr:street":"Rue De La Cigale",
    "iso:country":"FR",
    "sg:address":"110 Rue De La Cigale 45110 Ch\u00e2teauneuf Sur Loire",
    "sg:city":"Ch\u00e2teauneuf-sur-Loire",
    "sg:classifiers":[
        {
            "category":"Shopping",
            "type":"Retail Goods"
        }
    ],
    "sg:phone":"+33 2 38 58 41 31",
    "sg:postcode":"45110",
    "sg:province":"Centre",
    "sg:tags":[
        "metallurgy",
        "finished",
        "-",
        "metalworking",
        "metallic"
    ],
    "wof:name":"Ets Boudard Sa",
    "wof:placetype":"venue"
},
  "geometry": {"coordinates":[2.231428,47.863819],"type":"Point"}
}