{
  "type": "Feature",
  "properties": {
    "iso:country":"FR",
    "sg:address":"Rue Du Moulin 55700 Stenay",
    "sg:classifiers":[
        {
            "category":"Manufacturing",
            "subcategory":"Metals",
            "type":"Manufacturing & Wholesale Goods"
        }
    ],
    "sg:phone":"+33 3 29 80 30 09",
    "sg:postcode":"55700",
    "sg:province":"Lorraine",
    "sg:tags":[
        "metallurgy",
        "steel",
        "metalworking"
    ],
    "wof:name":"Fonderie D'acier Lorraine",
    "wof:placetype":"venue"
},
  "geometry": {"coordinates":[5.18718,49.487049],"type":"Point"}
}