{
  "type": "Feature",
  "properties": {
    "iso:country":"FR",
    "sg:address":"18, Rue Saarinen, 94568 Rungis C\u00e9dex",
    "sg:orig_category":"Non-Classified Establishments",
    "sg:phone":"+33 1 45 12 50 50",
    "sg:province":"Basse Normandie",
    "wof:name":"B.d. France S.a. - Bectib Dickinson France S.a.",
    "wof:placetype":"venue"
},
  "geometry": {"coordinates":[2.353376,48.747597],"type":"Point"}
}