{
  "type": "Feature",
  "properties": {
    "addr:full":"111 rue Beno\u00eet Frachon 93000 Bobigny Ile de France",
    "addr:housenumber":"111",
    "addr:postcode":"93000;ile",
    "addr:street":"Rue Benoi\u0302T Frachon",
    "iso:country":"FR",
    "sg:address":"111 rue Beno\u00eet Frachon 93000 Bobigny",
    "sg:classifiers":[
        {
            "category":"Professional",
            "subcategory":"Employment Agencies",
            "type":"Services"
        }
    ],
    "sg:phone":"+33 1 41 83 07 50",
    "sg:province":"Ile de France",
    "sg:tags":[
        "overseas",
        "shipping"
    ],
    "wof:name":"Lacotrans S.a.r.l.",
    "wof:placetype":"venue"
},
  "geometry": {"coordinates":[2.429153,48.901512],"type":"Point"}
}