{
  "type": "Feature",
  "properties": {
    "iso:country":"FR",
    "sg:address":"11 rue du Renard 92250 La Garenne Colombes",
    "sg:classifiers":[
        {
            "category":"Real Estate",
            "subcategory":"Surveying",
            "type":"Services"
        }
    ],
    "sg:phone":"+33 1 47 86 74 86",
    "sg:postcode":"92250",
    "sg:province":"Ile de France",
    "sg:tags":[
        "analyser"
    ],
    "wof:name":"Panametrics S.a.",
    "wof:placetype":"venue"
},
  "geometry": {"coordinates":[2.2383,48.90852],"type":"Point"}
}