{
  "type": "Feature",
  "properties": {
    "addr:full":"34, Rte de Lyon, 73160 Cognin Rhone-Alpes 73160",
    "addr:housenumber":"34",
    "addr:postcode":"73160;73160",
    "addr:street":"Rte De Lyon;Rhone-Alpes",
    "iso:country":"FR",
    "sg:address":"34, Rte de Lyon, 73160 Cognin",
    "sg:orig_category":"Unclassifiable Establishments",
    "sg:phone":"+33 4 79 69 20 70",
    "sg:postcode":"73160",
    "sg:province":"Rhone-Alpes",
    "wof:name":"Banque De Savoie",
    "wof:placetype":"venue"
},
  "geometry": {"coordinates":[5.89999,45.562553],"type":"Point"}
}