{
  "type": "Feature",
  "properties": {
    "iso:country":"FR",
    "sg:address":"72019 Le Mans C\u00e9dex 2^^2, All\u00e9e des G\u00e9meaux, 72000 Le Mans",
    "sg:orig_category":"Non-Classified Establishments",
    "sg:phone":"+33 2 43 57 70 00",
    "sg:postcode":"72000",
    "sg:province":"Pays de Loire",
    "wof:name":"B.m.i. S.a.s. - B\u00e9ton Moul\u00e9 Industriel",
    "wof:placetype":"venue"
},
  "geometry": {"coordinates":[0.197813,48.008095],"type":"Point"}
}