{
  "type": "Feature",
  "properties": {
    "addr:full":"89-91 rue du Faubourg; Paris; 75008 Ile de France 75008",
    "addr:housenumber":"89-91",
    "addr:postcode":"75008;75008",
    "addr:street":"Rue Du Faubourg Paris;France",
    "iso:country":"FR",
    "sg:address":"89-91 rue du Faubourg; Paris; 75008",
    "sg:classifiers":[
        {
            "category":"Banks & Credit Unions",
            "subcategory":"Bank",
            "type":"Services"
        }
    ],
    "sg:phone":"+33 1 42 66 80 00",
    "sg:postcode":"75008",
    "sg:province":"Ile de France",
    "wof:name":"Intermedia Banque",
    "wof:placetype":"venue"
},
  "geometry": {"coordinates":[2.313266,48.871853],"type":"Point"}
}