{
  "type": "Feature",
  "properties": {
    "addr:full":"16 rue Guilloud 69003 Lyon Rhone-Alpes 69003",
    "addr:housenumber":"16",
    "addr:postcode":"69003;69003",
    "addr:street":"Rue Guilloud",
    "iso:country":"FR",
    "sg:address":"16 rue Guilloud 69003 Lyon",
    "sg:classifiers":[
        {
            "category":"Organizations",
            "subcategory":"Religious Organization",
            "type":"Services"
        }
    ],
    "sg:phone":"+33 4 78 53 78 19",
    "sg:postcode":"69003",
    "sg:province":"Rhone-Alpes",
    "sg:tags":[
        "ventilation",
        "system",
        "maintenance",
        "servicing"
    ],
    "wof:name":"Sogemo Sa",
    "wof:placetype":"venue"
},
  "geometry": {"coordinates":[4.868581,45.747517],"type":"Point"}
}