{
  "type": "Feature",
  "properties": {
    "iso:country":"FR",
    "sg:address":"77312 MARNE LA VALLEE CEDEX 2",
    "sg:classifiers":[
        {
            "category":"Government",
            "subcategory":"Department Of Motor Vehicles",
            "type":"Public Place"
        }
    ],
    "sg:phone":"+33 1 60 37 30 00",
    "sg:province":"Midi Pyr\u00e9n\u00e9es",
    "sg:tags":[
        "town",
        "citymobiles",
        "different",
        "drive",
        "kind"
    ],
    "wof:name":"Honda Motor Europe (south)",
    "wof:placetype":"venue"
},
  "geometry": {"coordinates":[2.62284,48.855671],"type":"Point"}
}