{
  "type": "Feature",
  "properties": {
    "addr:full":"42b Bd Thiers 42190 Charlieu Rhone-Alpes 42190",
    "addr:housenumber":"42b",
    "addr:postcode":"42190;42190",
    "addr:street":"Bd Thiers",
    "iso:country":"FR",
    "sg:address":"42b Bd Thiers 42190 Charlieu",
    "sg:classifiers":[
        {
            "category":"Building & Trades",
            "subcategory":"Construction",
            "type":"Services"
        }
    ],
    "sg:phone":"+33 4 77 69 09 00",
    "sg:postcode":"42190",
    "sg:province":"Rhone-Alpes",
    "sg:tags":[
        "work",
        "public"
    ],
    "wof:name":"Fayolle Societe Anonyme Fayolle Sa",
    "wof:placetype":"venue"
},
  "geometry": {"coordinates":[4.166953,46.158737],"type":"Point"}
}