{
  "type": "Feature",
  "properties": {
    "iso:country":"FR",
    "sg:address":"Bd du B.A.B.",
    "sg:city":"Bayonne",
    "sg:orig_category":"Non-Classified Establishments",
    "sg:phone":"+33 5 59 52 34 20",
    "sg:postcode":"64100",
    "sg:province":"Aquitaine",
    "wof:name":"R.a.m. S.a.r.l. - Roger Agrech Menuiseries",
    "wof:placetype":"venue"
},
  "geometry": {"coordinates":[-1.487159,43.496964],"type":"Point"}
}