{
  "type": "Feature",
  "properties": {
    "addr:full":"3, Rue de Rumilly, 74000 Annecy Rhone-Alpes 74000",
    "addr:housenumber":"3",
    "addr:postcode":"74000;74000",
    "addr:street":"Rue De Rumilly",
    "iso:country":"FR",
    "sg:address":"3, Rue de Rumilly, 74000 Annecy",
    "sg:orig_category":"Non-Classified Establishments",
    "sg:phone":"+33 4 50 51 35 41",
    "sg:postcode":"74000",
    "sg:province":"Rhone-Alpes",
    "wof:name":"Bureaux D'etudes Bri\u00e8re S.a.s.",
    "wof:placetype":"venue"
},
  "geometry": {"coordinates":[6.118705,45.899738],"type":"Point"}
}