{
  "type": "Feature",
  "properties": {
    "addr:full":"B.P. 9049, 64050 Pau C\u00e9dex 9^^128, Av. Alfred Nobel, 64400 Pau Oloron-Sainte-Marie Aquitaine 64400",
    "addr:housenumber":"9 ^ ^ 128",
    "addr:postcode":"64050;64400;64400",
    "addr:street":"B.P. 9049;Ce\u0301Dex;Av. Alfred Nobel",
    "iso:country":"FR",
    "sg:address":"B.P. 9049, 64050 Pau C\u00e9dex 9^^128, Av. Alfred Nobel, 64400 Pau",
    "sg:city":"Oloron-Sainte-Marie",
    "sg:orig_category":"Non-Classified Establishments",
    "sg:phone":"+33 5 59 30 12 88",
    "sg:postcode":"64400",
    "sg:province":"Aquitaine",
    "wof:name":"S.o.g.e.b.a. S.a. - Soci\u00e9t\u00e9 G\u00e9n\u00e9rale D'entreprises Du Bassin De L'ado",
    "wof:placetype":"venue"
},
  "geometry": {"coordinates":[-0.593104,43.138924],"type":"Point"}
}