{
  "type": "Feature",
  "properties": {
    "addr:full":"22 R De La Paix 38130 Echirolles Rhone-Alpes 38130",
    "addr:housenumber":"22",
    "addr:postcode":"38130;38130",
    "addr:street":"R De La Paix;Rhone-Alpes",
    "iso:country":"FR",
    "sg:address":"22 R De La Paix 38130 Echirolles",
    "sg:classifiers":[
        {
            "category":"Shopping",
            "subcategory":"Computers & Home Electronics",
            "type":"Retail Goods"
        }
    ],
    "sg:phone":"+33 4 76 33 26 60",
    "sg:postcode":"38130",
    "sg:province":"Rhone-Alpes",
    "sg:tags":[
        "electric",
        "electricity",
        "component",
        "equipment",
        "electrical",
        "electronic"
    ],
    "wof:name":"Comptoir Lyonnais D'electricite",
    "wof:placetype":"venue"
},
  "geometry": {"coordinates":[5.707885,45.141037],"type":"Point"}
}