{
  "type": "Feature",
  "properties": {
    "addr:full":"16 Rue Du Chateau 50100 Cherbourg Octeville Cherbourg-Octeville Basse Normandie 50100",
    "addr:housenumber":"16",
    "addr:postcode":"50100;50100",
    "addr:street":"Rue Du Chateau",
    "iso:country":"FR",
    "sg:address":"16 Rue Du Chateau 50100 Cherbourg Octeville",
    "sg:city":"Cherbourg-Octeville",
    "sg:classifiers":[
        {
            "category":"Shopping",
            "subcategory":"Clothing, Apparel, & Fashions",
            "type":"Retail Goods"
        }
    ],
    "sg:phone":"+33 2 33 01 26 94",
    "sg:postcode":"50100",
    "sg:province":"Basse Normandie",
    "sg:tags":[
        "textile",
        "clothing",
        "clothes"
    ],
    "wof:name":"Promod",
    "wof:placetype":"venue"
},
  "geometry": {"coordinates":[-1.623398,49.638885],"type":"Point"}
}