{
  "type": "Feature",
  "properties": {
    "addr:full":"Zi Beacpuy 85000 Mouilleron Le Captif Pays de Loire 85000",
    "addr:postcode":"85000;85000",
    "addr:street":"Le Captif Pays",
    "iso:country":"FR",
    "sg:address":"Zi Beacpuy 85000 Mouilleron Le Captif",
    "sg:classifiers":[
        {
            "category":"Manufacturing",
            "subcategory":"Metals",
            "type":"Manufacturing & Wholesale Goods"
        }
    ],
    "sg:phone":"+33 2 51 34 10 98",
    "sg:postcode":"85000",
    "sg:province":"Pays de Loire",
    "sg:tags":[
        "processing",
        "-",
        "metalworking",
        "metallic",
        "metallurgy",
        "finished"
    ],
    "wof:name":"L Mallard",
    "wof:placetype":"venue"
},
  "geometry": {"coordinates":[-1.458889,46.71957],"type":"Point"}
}