{
  "type": "Feature",
  "properties": {
    "iso:country":"FR",
    "sg:address":"13, Rue de la r\u00e9publique, 59187 Dechy",
    "sg:orig_category":"Unclassifiable Establishments",
    "sg:phone":"+33 3 27 98 58 81",
    "sg:province":"Nord Pas-de-Calais",
    "wof:name":"Olczak Electricit\u00e9 S.a.",
    "wof:placetype":"venue"
},
  "geometry": {"coordinates":[3.135761,50.358391],"type":"Point"}
}