{
  "type": "Feature",
  "properties": {
    "addr:full":"Route National 27 76550 SAUQUEVILLE Haute Normandie 76550",
    "addr:housenumber":"27",
    "addr:postcode":"76550;76550",
    "addr:street":"Route National;Haute Normandie",
    "iso:country":"FR",
    "sg:address":"Route National 27 76550 SAUQUEVILLE",
    "sg:classifiers":[
        {
            "category":"Manufacturing",
            "subcategory":"Glass & Minerals",
            "type":"Manufacturing & Wholesale Goods"
        }
    ],
    "sg:phone":"+33 2 32 06 30 00",
    "sg:postcode":"76550",
    "sg:province":"Haute Normandie",
    "sg:tags":[
        "industrial"
    ],
    "wof:name":"Le Moulin Des Pr\u00e8s Sa",
    "wof:placetype":"venue"
},
  "geometry": {"coordinates":[1.030699,49.897762],"type":"Point"}
}