{
  "type": "Feature",
  "properties": {
    "addr:full":"114, Av. Marcelin Berthelot, 69520 Grigny Rhone-Alpes",
    "addr:postcode":"69520",
    "addr:street":"114 Av. Marcelin Berthelot",
    "iso:country":"FR",
    "sg:address":"114, Av. Marcelin Berthelot, 69520 Grigny",
    "sg:orig_category":"Unclassifiable Establishments",
    "sg:phone":"+33 4 78 73 37 73",
    "sg:province":"Rhone-Alpes",
    "wof:name":"T.i.b. S.a. - Transport Isabelle Bourgeois",
    "wof:placetype":"venue"
},
  "geometry": {"coordinates":[4.776915,45.595551],"type":"Point"}
}