{
  "type": "Feature",
  "properties": {
    "iso:country":"FR",
    "sg:address":"28, Rue Pasteur, 62540 Marles les Mines",
    "sg:orig_category":"Unclassifiable Establishments",
    "sg:phone":"+33 3 21 62 71 06",
    "sg:province":"Nord Pas-de-Calais",
    "wof:name":"Mand\u00e9ra Plastique S.a.r.l.",
    "wof:placetype":"venue"
},
  "geometry": {"coordinates":[2.506961,50.501839],"type":"Point"}
}