{
  "type": "Feature",
  "properties": {
    "addr:full":"route de Chartres 28160 Brou Brou Centre 28160",
    "addr:postcode":"28160;28160",
    "addr:street":"Route De Chartres",
    "iso:country":"FR",
    "sg:address":"route de Chartres 28160 Brou",
    "sg:city":"Brou",
    "sg:classifiers":[
        {
            "category":"Shopping",
            "subcategory":"Beauty & Cosmetics",
            "type":"Retail Goods"
        }
    ],
    "sg:phone":"+33 2 37 96 22 28",
    "sg:postcode":"28160",
    "sg:province":"Centre",
    "sg:tags":[
        "perfume"
    ],
    "wof:name":"Chris Sarl",
    "wof:placetype":"venue"
},
  "geometry": {"coordinates":[1.179514,48.215706],"type":"Point"}
}