{
  "type": "Feature",
  "properties": {
    "addr:full":"Zone Industrielle St Marcel Quartier Gamba Torte 06580 Pegomas Pays de Loire",
    "addr:postcode":"06580",
    "addr:street":"Zone Industrielle St Marcel",
    "iso:country":"FR",
    "sg:address":"Zone Industrielle St Marcel Quartier Gamba Torte 06580 Pegomas",
    "sg:classifiers":[
        {
            "category":"Professional",
            "subcategory":"Engineering",
            "type":"Services"
        }
    ],
    "sg:phone":"+33 4 93 93 04 33",
    "sg:province":"Pays de Loire",
    "sg:tags":[
        "machine",
        "-",
        "mechanical"
    ],
    "wof:name":"Societe D'exploitation Decor'laque",
    "wof:placetype":"venue"
},
  "geometry": {"coordinates":[6.931395,43.597576],"type":"Point"}
}