{
  "type": "Feature",
  "properties": {
    "iso:country":"FR",
    "sg:address":"77465 Lagny sur Marne Cedex^^64, Rue Jacquard, 77400 Lagny sur Marne",
    "sg:orig_category":"Non-Classified Establishments",
    "sg:phone":"+33 1 64 30 05 87",
    "sg:province":"Ile de France",
    "wof:name":"Japa Maintenance S.a.r.l.",
    "wof:placetype":"venue"
},
  "geometry": {"coordinates":[2.701485,48.87775],"type":"Point"}
}