{
  "type": "Feature",
  "properties": {
    "addr:full":"2, Rte de Bergues, 59210 Coudekerque Branche Nord Pas-de-Calais",
    "addr:housenumber":"2",
    "addr:postcode":"59210",
    "addr:street":"Rte De Bergues;Branche Nord",
    "iso:country":"FR",
    "sg:address":"2, Rte de Bergues, 59210 Coudekerque Branche",
    "sg:orig_category":"Unclassifiable Establishments",
    "sg:phone":"+33 3 28 26 76 36",
    "sg:province":"Nord Pas-de-Calais",
    "wof:name":"Open E.u.r.l.",
    "wof:placetype":"venue"
},
  "geometry": {"coordinates":[2.374879,51.021671],"type":"Point"}
}