{
  "type": "Feature",
  "properties": {
    "iso:country":"FR",
    "sg:address":"9, Rue de la Tour le Mesnil Renard, 78270 Bonni\u00e8res sur Seine",
    "sg:orig_category":"Non-Classified Establishments",
    "sg:phone":"+33 1 30 93 00 88",
    "sg:province":"Ile de France",
    "wof:name":"Galvatek S.a.r.l.",
    "wof:placetype":"venue"
},
  "geometry": {"coordinates":[1.569299,49.022449],"type":"Point"}
}