{
  "type": "Feature",
  "properties": {
    "addr:full":"89, Bd du Parc de l'Artillerie, 69007 Lyon Rhone-Alpes",
    "addr:housenumber":"89",
    "addr:postcode":"69007",
    "addr:street":"Bd Du Parc De L'Artillerie",
    "iso:country":"FR",
    "sg:address":"89, Bd du Parc de l'Artillerie, 69007 Lyon",
    "sg:orig_category":"Unclassifiable Establishments",
    "sg:phone":"+33 4 72 76 50 35",
    "sg:province":"Rhone-Alpes",
    "wof:name":"Gea Erge Spirale Et Soramat S.a.",
    "wof:placetype":"venue"
},
  "geometry": {"coordinates":[4.842434,45.733753],"type":"Point"}
}