{
  "type": "Feature",
  "properties": {
    "addr:full":"Rue du 19 Mars 1962 - ZI Marly C\u00e9dex Nord-Pas-de-Calais 59584",
    "addr:postcode":"59584",
    "addr:street":"Rue Du 19 Mars 1962 Zi;Ce\u0301Dex",
    "iso:country":"FR",
    "sg:address":"Rue du 19 Mars 1962 - ZI",
    "sg:city":"Marly C\u00e9dex",
    "sg:orig_category":"Non-Classified Establishments",
    "sg:phone":"+33 3 27 23 66 66",
    "sg:postcode":"59584",
    "sg:province":"Nord-Pas-de-Calais",
    "wof:name":"Lyreco Gestion S.a.s.",
    "wof:placetype":"venue"
},
  "geometry": {"coordinates":[3.561522,50.340137],"type":"Point"}
}