{
  "type": "Feature",
  "properties": {
    "addr:full":"Les Ajeux 72400 La Fert\u00e9 Bernard Pays de Loire",
    "addr:postcode":"72400",
    "addr:street":"Bernard",
    "iso:country":"FR",
    "sg:address":"Les Ajeux 72400 La Fert\u00e9 Bernard",
    "sg:classifiers":[
        {
            "category":"Manufacturing",
            "subcategory":"Rubber & Plastics",
            "type":"Manufacturing & Wholesale Goods"
        }
    ],
    "sg:phone":"+33 2 43 93 17 15",
    "sg:province":"Pays de Loire",
    "wof:name":"Fci France",
    "wof:placetype":"venue"
},
  "geometry": {"coordinates":[0.64127,48.164291],"type":"Point"}
}