{
  "type": "Feature",
  "properties": {
    "addr:full":"74440 Mieussy Rhone-Alpes 74440",
    "addr:postcode":"74440;74440",
    "iso:country":"FR",
    "sg:address":"74440 Mieussy",
    "sg:orig_category":"Non-Classified Establishments",
    "sg:phone":"+33 4 50 43 01 43",
    "sg:postcode":"74440",
    "sg:province":"Rhone-Alpes",
    "wof:name":"A.f.d. S.a. - Anthonioz Fabrique D\u00e9colletage",
    "wof:placetype":"venue"
},
  "geometry": {"coordinates":[6.519711,46.134258],"type":"Point"}
}