{
  "type": "Feature",
  "properties": {
    "iso:country":"FR",
    "sg:address":"B.P. 37, 94800 Villejuif C\u00e9dex^^128, Av. de Stalingrad, 94800 Villejuif",
    "sg:orig_category":"Non-Classified Establishments",
    "sg:phone":"+33 1 46 77 18 24",
    "sg:province":"Ile de France",
    "wof:name":"Orofiamma S.a.",
    "wof:placetype":"venue"
},
  "geometry": {"coordinates":[2.36366,48.792385],"type":"Point"}
}