{
  "type": "Feature",
  "properties": {
    "addr:full":"7, Rue Grande Cave, 68980 Beblenheim Beblenheim Alsace 68980",
    "addr:housenumber":"7",
    "addr:postcode":"68980;68980",
    "addr:street":"Rue Grande Cave",
    "iso:country":"FR",
    "sg:address":"7, Rue Grande Cave, 68980 Beblenheim",
    "sg:city":"Beblenheim",
    "sg:orig_category":"Unclassifiable Establishments",
    "sg:phone":"+33 3 89 47 90 01",
    "sg:postcode":"68980",
    "sg:province":"Alsace",
    "wof:name":"Maison Fischer S.a.r.l.",
    "wof:placetype":"venue"
},
  "geometry": {"coordinates":[7.327534,48.158367],"type":"Point"}
}