{
  "type": "Feature",
  "properties": {
    "addr:full":"15 Rue Alain Savary 25000 Besan\u00e7on Franche Comt\u00e9 25000",
    "addr:housenumber":"15",
    "addr:postcode":"25000;25000",
    "addr:street":"Rue Alain Savary;Franche Comte\u0301",
    "iso:country":"FR",
    "sg:address":"15 Rue Alain Savary 25000 Besan\u00e7on",
    "sg:classifiers":[
        {
            "category":"Manufacturing",
            "subcategory":"Tools & Machinery",
            "type":"Manufacturing & Wholesale Goods"
        }
    ],
    "sg:phone":"+33 3 81 40 31 30",
    "sg:postcode":"25000",
    "sg:province":"Franche Comt\u00e9",
    "sg:tags":[
        "equipment",
        "measurement",
        "-",
        "precision",
        "instrument"
    ],
    "wof:name":"Imasonic",
    "wof:placetype":"venue"
},
  "geometry": {"coordinates":[6.001119,47.253296],"type":"Point"}
}