{
  "type": "Feature",
  "properties": {
    "addr:full":"Rue du Chemin de Fer - ZI Rammelplatz Reichstett Alsace 67116",
    "addr:postcode":"67116",
    "addr:street":"Rue Du Chemin De Fer Zi Rammelplatz",
    "iso:country":"FR",
    "sg:address":"Rue du Chemin de Fer - ZI Rammelplatz",
    "sg:city":"Reichstett",
    "sg:orig_category":"Unclassifiable Establishments",
    "sg:phone":"+33 3 88 20 98 20",
    "sg:postcode":"67116",
    "sg:province":"Alsace",
    "wof:name":"Bronner S.a.r.l.",
    "wof:placetype":"venue"
},
  "geometry": {"coordinates":[7.753589,48.648308],"type":"Point"}
}