{
  "type": "Feature",
  "properties": {
    "iso:country":"FR",
    "sg:address":"Le Bas Des Landes 50680 St Clair Sur L'Elle",
    "sg:city":"Airel",
    "sg:classifiers":[
        {
            "category":"Farming",
            "subcategory":"Crops",
            "type":"Manufacturing & Wholesale Goods"
        }
    ],
    "sg:phone":"+33 2 33 05 85 18",
    "sg:postcode":"50680",
    "sg:province":"Basse Normandie",
    "sg:tags":[
        "horticulture",
        "agriculture",
        "grain",
        "livestock",
        "cereal"
    ],
    "wof:name":"Agrial",
    "wof:placetype":"venue"
},
  "geometry": {"coordinates":[-0.897923,48.846443],"type":"Point"}
}