{
  "type": "Feature",
  "properties": {
    "iso:country":"FR",
    "sg:address":"Rue Jean De Gutenberg 62126 Wimille",
    "sg:classifiers":[
        {
            "category":"Manufacturing",
            "subcategory":"Printing",
            "type":"Manufacturing & Wholesale Goods"
        }
    ],
    "sg:phone":"+33 3 21 87 89 89",
    "sg:province":"Nord Pas-de-Calais",
    "sg:tags":[
        "publishing"
    ],
    "wof:name":"Imprimerie Debusschere Sa",
    "wof:placetype":"venue"
},
  "geometry": {"coordinates":[1.64928,50.772354],"type":"Point"}
}