{
  "type": "Feature",
  "properties": {
    "addr:full":"35, Rue des Peupliers, 92000 Nanterre Ile de France",
    "addr:housenumber":"35",
    "addr:postcode":"92000",
    "addr:street":"Rue Des Peupliers",
    "iso:country":"FR",
    "sg:address":"35, Rue des Peupliers, 92000 Nanterre",
    "sg:orig_category":"Unclassifiable Establishments",
    "sg:phone":"+33 1 46 49 19 19",
    "sg:province":"Ile de France",
    "wof:name":"Foss France S.a.",
    "wof:placetype":"venue"
},
  "geometry": {"coordinates":[2.211757,48.911854],"type":"Point"}
}