{
  "type": "Feature",
  "properties": {
    "addr:full":"16 Rue Du Chateau 67891 Niederbronn Cedex Rhone-Alpes",
    "addr:housenumber":"16",
    "addr:postcode":"67891 niederbronn cedex rhone-alpes",
    "addr:street":"Rue Du Chateau",
    "iso:country":"FR",
    "sg:address":"16 Rue Du Chateau 67891 Niederbronn Cedex",
    "sg:classifiers":[
        {
            "category":"Professional",
            "subcategory":"Engineering",
            "type":"Services"
        }
    ],
    "sg:phone":"+33 3 88 80 26 00",
    "sg:province":"Rhone-Alpes",
    "sg:tags":[
        "machine",
        "-",
        "mechanical"
    ],
    "wof:name":"De Dietrich",
    "wof:placetype":"venue"
},
  "geometry": {"coordinates":[7.64589,48.950272],"type":"Point"}
}