{
  "type": "Feature",
  "properties": {
    "addr:full":"3, Rue Alfred de Vigny - ZAC de Basses Auges, 78112 Fourqueux Ile de France",
    "addr:housenumber":"3",
    "addr:postcode":"78112;ile",
    "addr:street":"Rue Alfred De Vigny Zac De Basses Auges",
    "iso:country":"FR",
    "sg:address":"3, Rue Alfred de Vigny - ZAC de Basses Auges, 78112 Fourqueux",
    "sg:orig_category":"Unclassifiable Establishments",
    "sg:phone":"+33 1 39 21 81 81",
    "sg:province":"Ile de France",
    "wof:name":"Menshen Emballages S.a.r.l.",
    "wof:placetype":"venue"
},
  "geometry": {"coordinates":[2.063075,48.890217],"type":"Point"}
}