{
  "type": "Feature",
  "properties": {
    "addr:full":"149 bvd de la R\u00e9publique; Andernos les Bains; 33510 Andernos-les-Bains Aquitaine 33510",
    "addr:housenumber":"149",
    "addr:postcode":"33510;33510",
    "addr:street":"Bvd De La Re\u0301Publique;Les",
    "iso:country":"FR",
    "sg:address":"149 bvd de la R\u00e9publique; Andernos les Bains; 33510",
    "sg:city":"Andernos-les-Bains",
    "sg:classifiers":[
        {
            "category":"Banks & Credit Unions",
            "subcategory":"Bank",
            "type":"Services"
        }
    ],
    "sg:phone":"+33 3356820395",
    "sg:postcode":"33510",
    "sg:province":"Aquitaine",
    "wof:name":"Cr\u00e9dit Commercial, Du Sud-ouest",
    "wof:placetype":"venue"
},
  "geometry": {"coordinates":[-1.098758,44.741985],"type":"Point"}
}