{
  "type": "Feature",
  "properties": {
    "iso:country":"FR",
    "sg:address":"50 avenue d'Alsace 68027 Colmar",
    "sg:classifiers":[
        {
            "category":"Wholesale",
            "subcategory":"Auto Parts",
            "type":"Manufacturing & Wholesale Goods"
        }
    ],
    "sg:phone":"+33 3 89 20 43 99",
    "sg:province":"Alsace",
    "sg:tags":[
        "leather",
        "automotive",
        "upholstery"
    ],
    "wof:name":"Bernhard Fischer Cuirs Et Peaux En Gros",
    "wof:placetype":"venue"
},
  "geometry": {"coordinates":[7.365457,48.077438],"type":"Point"}
}