{
  "type": "Feature",
  "properties": {
    "iso:country":"FR",
    "sg:address":"900 Av Pontchy 74130 Bonneville",
    "sg:classifiers":[
        {
            "category":"Manufacturing",
            "subcategory":"Metals",
            "type":"Manufacturing & Wholesale Goods"
        }
    ],
    "sg:phone":"+33 4 50 97 03 09",
    "sg:postcode":"74130",
    "sg:province":"Rhone-Alpes",
    "sg:tags":[
        "metallurgy",
        "metalworking",
        "processing"
    ],
    "wof:name":"Perrotton Jean Sa",
    "wof:placetype":"venue"
},
  "geometry": {"coordinates":[6.401797,46.066174],"type":"Point"}
}