{
  "type": "Feature",
  "properties": {
    "addr:full":"Rte de Castets - 82 Village d'Entreprises Saint Paul l\u00e8s Dax Aquitaine 40990",
    "addr:housenumber":"82",
    "addr:postcode":"40990",
    "addr:street":"Rte De Castets",
    "iso:country":"FR",
    "sg:address":"Rte de Castets - 82 Village d'Entreprises",
    "sg:city":"Saint Paul l\u00e8s Dax",
    "sg:orig_category":"Non-Classified Establishments",
    "sg:phone":"+33 5 58 91 57 28",
    "sg:postcode":"40990",
    "sg:province":"Aquitaine",
    "wof:name":"Auditec Aquitaine S.a.r.l.",
    "wof:placetype":"venue"
},
  "geometry": {"coordinates":[-1.127477,43.806652],"type":"Point"}
}