{
  "type": "Feature",
  "properties": {
    "iso:country":"FR",
    "sg:address":"B.P. 11, 76320 Saint-Pierre l\u00e8s Elbeuf^^758, Rue de la For\u00eat, 76320 Saint Pierre l\u00e8s Elbeuf",
    "sg:orig_category":"Non-Classified Establishments",
    "sg:phone":"+33 2 32 96 03 90",
    "sg:province":"Haute Normandie",
    "wof:name":"S.e.t.i.c. S.a. - Soci\u00e9t\u00e9 Elbeuvienne De Tuyauterie Industrielle Et Chaudronnerie",
    "wof:placetype":"venue"
},
  "geometry": {"coordinates":[1.054978,49.280209],"type":"Point"}
}