{
  "type": "Feature",
  "properties": {
    "iso:country":"FR",
    "sg:address":"12 Rue Elie Vinet",
    "sg:city":"Barbezieux St Hilaire",
    "sg:classifiers":[
        {
            "category":"Banks & Credit Unions",
            "subcategory":"Financial Services",
            "type":"Services"
        }
    ],
    "sg:phone":"+33 5 45 78 02 07",
    "sg:postcode":"16300",
    "sg:province":"Poitou-Charentes",
    "sg:tags":[
        "banking",
        "finance",
        "insurance"
    ],
    "wof:name":"Fiduciaire Mecanocomptable Du Centre Ouest (fimeco)",
    "wof:placetype":"venue"
},
  "geometry": {"coordinates":[-0.152754,45.472401],"type":"Point"}
}