{
  "type": "Feature",
  "properties": {
    "iso:country":"FR",
    "sg:address":"1, Place des Platanes, 71150 Fontaines",
    "sg:city":"Fontaines",
    "sg:orig_category":"Non-Classified Establishments",
    "sg:phone":"+33 3 85 91 43 79",
    "sg:postcode":"71150",
    "sg:province":"Bourgogne",
    "wof:name":"T.p. G\u00e9o S.a.",
    "wof:placetype":"venue"
},
  "geometry": {"coordinates":[4.760638,46.849331],"type":"Point"}
}