{
  "type": "Feature",
  "properties": {
    "addr:full":"222 Boulevard Du Mal Juin Mantes La Jolie Ile de France 78200",
    "addr:housenumber":"222",
    "addr:postcode":"78200",
    "addr:street":"Boulevard Du Mal Juin Mantes La Jolie Ile De France",
    "iso:country":"FR",
    "sg:address":"222 Boulevard Du Mal Juin",
    "sg:city":"Mantes La Jolie",
    "sg:classifiers":[
        {
            "category":"Banks & Credit Unions",
            "subcategory":"Financial Services",
            "type":"Services"
        }
    ],
    "sg:phone":"+33 1 30 94 01 58",
    "sg:postcode":"78200",
    "sg:province":"Ile de France",
    "sg:tags":[
        "banking",
        "finance",
        "insurance"
    ],
    "wof:name":"Fiduciaire Juridique Et Fiscale De France Fidal (fjff)",
    "wof:placetype":"venue"
},
  "geometry": {"coordinates":[1.694499,48.994862],"type":"Point"}
}