{
  "type": "Feature",
  "properties": {
    "iso:country":"FR",
    "sg:address":"2, Rue Pierre Cremel, 54410 Laneuveville devant Nancy",
    "sg:orig_category":"CONCEPTION ET VENTE D'ENSEIGNES PUBLICITAIRES SIGNAL\u00c9TIQUE. INSTALLATEUR: ENSEIGNES ET STORES d\u00e9cors",
    "sg:phone":"+33 3 83 48 49 60",
    "sg:postcode":"54410",
    "sg:province":"Lorraine",
    "wof:name":"Challenge S.a.r.l.",
    "wof:placetype":"venue"
},
  "geometry": {"coordinates":[6.254782,48.64312],"type":"Point"}
}