{
  "type": "Feature",
  "properties": {
    "addr:full":"2, Rue Pierre Cremel, 54410 Laneuveville devant Nancy Lorraine 54410",
    "addr:housenumber":"2",
    "addr:postcode":"54410;54410",
    "addr:street":"Rue Pierre Cremel",
    "iso:country":"FR",
    "sg:address":"2, Rue Pierre Cremel, 54410 Laneuveville devant Nancy",
    "sg:orig_category":"CONCEPTION ET VENTE D'ENSEIGNES PUBLICITAIRES SIGNAL\u00c9TIQUE. INSTALLATEUR: ENSEIGNES ET STORES d\u00e9cors",
    "sg:phone":"+33 3 83 48 49 60",
    "sg:postcode":"54410",
    "sg:province":"Lorraine",
    "wof:name":"Challenge S.a.r.l.",
    "wof:placetype":"venue"
},
  "geometry": {"coordinates":[6.254782,48.64312],"type":"Point"}
}