{
  "type": "Feature",
  "properties": {
    "addr:full":"B.P. 30, 25038 Besan\u00e7on C\u00e9dex^^5, Rue Berthelot - ZI des Tr\u00e9pillots, 25000 Besan\u00e7on Franche Comt\u00e9",
    "addr:postcode":"25038;25000",
    "addr:street":"B.P. 30;Rue Berthelot Zi Des Tre\u0301Pillots;Franche Comte\u0301",
    "iso:country":"FR",
    "sg:address":"B.P. 30, 25038 Besan\u00e7on C\u00e9dex^^5, Rue Berthelot - ZI des Tr\u00e9pillots, 25000 Besan\u00e7on",
    "sg:orig_category":"Non-Classified Establishments",
    "sg:phone":"+33 3 81 50 23 12",
    "sg:province":"Franche Comt\u00e9",
    "wof:name":"Loxam S.a.",
    "wof:placetype":"venue"
},
  "geometry": {"coordinates":[6.025686,47.242317],"type":"Point"}
}