{
  "type": "Feature",
  "properties": {
    "iso:country":"FR",
    "sg:address":"B.P. 39",
    "sg:city":"Ch\u00e2teau du Loir C\u00e9dex^^72500 Dissay sous Courcillon",
    "sg:orig_category":"Non-Classified Establishments",
    "sg:phone":"+33 2 43 44 03 94",
    "sg:postcode":"72500",
    "sg:province":"Pays de Loire",
    "wof:name":"Polypack S.a.r.l.",
    "wof:placetype":"venue"
},
  "geometry": {"coordinates":[0.33858,47.612446],"type":"Point"}
}