{
  "type": "Feature",
  "properties": {
    "addr:full":"Clos d'Asseville 95450 Us Ile de France",
    "addr:postcode":"95450",
    "addr:street":"Clos",
    "iso:country":"FR",
    "sg:address":"Clos d'Asseville 95450 Us",
    "sg:orig_category":"Unclassifiable Establishments",
    "sg:phone":"+33 1 30 27 95 00",
    "sg:province":"Ile de France",
    "wof:name":"Huck France S.a.",
    "wof:placetype":"venue"
},
  "geometry": {"coordinates":[1.9686,49.100811],"type":"Point"}
}