{
  "type": "Feature",
  "properties": {
    "iso:country":"FR",
    "sg:address":"A\u00e9roport Clermont Ferrand 63510 Aulnat",
    "sg:city":"Aulnat",
    "sg:classifiers":[
        {
            "category":"Manufacturing",
            "subcategory":"Aerospace",
            "type":"Manufacturing & Wholesale Goods"
        }
    ],
    "sg:phone":"+33 4 73 60 41 41",
    "sg:postcode":"63510",
    "sg:province":"Auvergne",
    "sg:tags":[
        "equipment",
        "aeronautic",
        "transport",
        "vehicle"
    ],
    "wof:name":"Auvergne Aeronautique Sa",
    "wof:placetype":"venue"
},
  "geometry": {"coordinates":[3.16013,45.78957],"type":"Point"}
}