{
  "type": "Feature",
  "properties": {
    "addr:full":"26, Place de la R\u00e9publique, 77140 Nemours Ile de France",
    "addr:housenumber":"26",
    "addr:postcode":"77140",
    "addr:street":"Place De La Re\u0301Publique;Ile De France",
    "iso:country":"FR",
    "sg:address":"26, Place de la R\u00e9publique, 77140 Nemours",
    "sg:orig_category":"Unclassifiable Establishments",
    "sg:phone":"+33 1 64 29 13 71",
    "sg:province":"Ile de France",
    "wof:name":"Alliance M\u00e9dia",
    "wof:placetype":"venue"
},
  "geometry": {"coordinates":[2.696296,48.267036],"type":"Point"}
}