{
  "type": "Feature",
  "properties": {
    "iso:country":"FR",
    "sg:address":"Rte de Siltzheim - Zone Industrielle",
    "sg:city":"R\u00e9melfing",
    "sg:orig_category":"Unclassifiable Establishments",
    "sg:phone":"+33 3 87 98 30 56",
    "sg:postcode":"57200",
    "sg:province":"Lorraine",
    "wof:name":"Gerbo France S.a.",
    "wof:placetype":"venue"
},
  "geometry": {"coordinates":[7.070569,49.108246],"type":"Point"}
}