{
  "type": "Feature",
  "properties": {
    "addr:full":"B.P. 92502, 44325 Nantes C\u00e9dex 03^^116, Rte de Saint Joseph, 44300 Nantes Pays de Loire",
    "addr:housenumber":"03;^ 116",
    "addr:postcode":"44325;44300",
    "addr:street":"^;Rte De Saint Joseph",
    "iso:country":"FR",
    "sg:address":"B.P. 92502, 44325 Nantes C\u00e9dex 03^^116, Rte de Saint Joseph, 44300 Nantes",
    "sg:orig_category":"Non-Classified Establishments",
    "sg:phone":"+33 2 40 49 23 39",
    "sg:province":"Pays de Loire",
    "wof:name":"Poussin Et Compagnie S.a.r.l.",
    "wof:placetype":"venue"
},
  "geometry": {"coordinates":[-1.51955,47.269741],"type":"Point"}
}