{
  "type": "Feature",
  "properties": {
    "addr:full":"1 rue Eug\u00e8ne Mar\u00e9chal 69200 VENISSIEUX Rhone-Alpes",
    "addr:housenumber":"1",
    "addr:postcode":"69200",
    "addr:street":"Rue Euge\u0300Ne Mare\u0301Chal",
    "iso:country":"FR",
    "sg:address":"1 rue Eug\u00e8ne Mar\u00e9chal 69200 VENISSIEUX",
    "sg:orig_category":"Edp Projects",
    "sg:phone":"+33 4 72 90 10 00",
    "sg:province":"Rhone-Alpes",
    "wof:name":"Open Space S.a.",
    "wof:placetype":"venue"
},
  "geometry": {"coordinates":[4.878622,45.706448],"type":"Point"}
}