{
  "type": "Feature",
  "properties": {
    "iso:country":"FR",
    "sg:address":"Za Du Rampy 85550 La Barre De Monts",
    "sg:classifiers":[
        {
            "category":"Professional",
            "type":"Services"
        }
    ],
    "sg:phone":"+33 2 51 68 51 06",
    "sg:province":"Pays de Loire",
    "sg:tags":[
        "transport",
        "road"
    ],
    "wof:name":"Sarl Transports Fortin Et Preneau",
    "wof:placetype":"venue"
},
  "geometry": {"coordinates":[-2.119254,46.881886],"type":"Point"}
}