{
  "type": "Feature",
  "properties": {
    "iso:country":"FR",
    "sg:address":"485 route du Pin Montard; Les Bouillides - BP 69; Sophia Antipolis; 06902",
    "sg:classifiers":[
        {
            "category":"Travel",
            "subcategory":"Travel Agent",
            "type":"Entertainment"
        }
    ],
    "sg:phone":"+33 3349294378",
    "sg:province":"Connecticut",
    "wof:name":"Amadeus S.a.s",
    "wof:placetype":"venue"
},
  "geometry": {"coordinates":[-73.54806499999999,41.025002],"type":"Point"}
}