{
  "type": "Feature",
  "properties": {
    "addr:full":"B.P. 19, 78920 Ecquevilly^^ZAI du Petit Parc, 78920 Ecquevilly Ile de France",
    "addr:postcode":"78920;78920;ile",
    "addr:street":"B.P. 19;Parc",
    "iso:country":"FR",
    "sg:address":"B.P. 19, 78920 Ecquevilly^^ZAI du Petit Parc, 78920 Ecquevilly",
    "sg:orig_category":"Non-Classified Establishments",
    "sg:phone":"+33 1 34 75 54 00",
    "sg:province":"Ile de France",
    "wof:name":"K.w.c. Robineterie S.a.r.l.",
    "wof:placetype":"venue"
},
  "geometry": {"coordinates":[1.918925,48.949734],"type":"Point"}
}