{
  "type": "Feature",
  "properties": {
    "addr:full":"5 pl Mairie; Ploun\u00e9vez Lochrist Picardie",
    "addr:housenumber":"5",
    "addr:street":"Pl",
    "iso:country":"FR",
    "sg:address":"5 pl Mairie; Ploun\u00e9vez Lochrist",
    "sg:classifiers":[
        {
            "category":"Banks & Credit Unions",
            "subcategory":"Bank",
            "type":"Services"
        }
    ],
    "sg:phone":"+33 3398614510",
    "sg:province":"Picardie",
    "wof:name":"Cr\u00e9dit Agricole Mutuel",
    "wof:placetype":"venue"
},
  "geometry": {"coordinates":[-4.211479,48.617153],"type":"Point"}
}