{
  "type": "Feature",
  "properties": {
    "addr:full":"R\u00e9sidence I'Abbaye; Fontaine; 38600 Rhone-Alpes 38600",
    "addr:postcode":"38600;38600",
    "addr:street":"Fontaine",
    "iso:country":"FR",
    "sg:address":"R\u00e9sidence I'Abbaye; Fontaine; 38600",
    "sg:classifiers":[
        {
            "category":"Banks & Credit Unions",
            "subcategory":"Bank",
            "type":"Services"
        }
    ],
    "sg:phone":"+33 3376266436",
    "sg:postcode":"38600",
    "sg:province":"Rhone-Alpes",
    "wof:name":"Soci\u00e9t\u00e9 G\u00e9n\u00e9rale",
    "wof:placetype":"venue"
},
  "geometry": {"coordinates":[5.672567,45.1968],"type":"Point"}
}