{
  "type": "Feature",
  "properties": {
    "addr:full":"B.P. 113, 44143 Ch\u00e2teaubriant C\u00e9dex^^12/14, Rue de Launay, 44140 Ch\u00e2teaubriant Pays de Loire",
    "addr:housenumber":"b.p. 113;14",
    "addr:postcode":"44143;44140",
    "addr:street":"Rue De Launay",
    "iso:country":"FR",
    "sg:address":"B.P. 113, 44143 Ch\u00e2teaubriant C\u00e9dex^^12/14, Rue de Launay, 44140 Ch\u00e2teaubriant",
    "sg:orig_category":"Non-Classified Establishments",
    "sg:phone":"+33 2 40 28 02 24",
    "sg:province":"Pays de Loire",
    "wof:name":"Thermi-centre",
    "wof:placetype":"venue"
},
  "geometry": {"coordinates":[-1.426909,47.009285],"type":"Point"}
}