{
  "type": "Feature",
  "properties": {
    "addr:full":"4 Rue Du Train De Loos 59160 Lomme Nord Pas-de-Calais 59160",
    "addr:housenumber":"4",
    "addr:postcode":"59160;59160",
    "addr:street":"Rue Du Train De Loos",
    "iso:country":"FR",
    "sg:address":"4 Rue Du Train De Loos 59160 Lomme",
    "sg:classifiers":[
        {
            "category":"Farming",
            "subcategory":"Crops",
            "type":"Manufacturing & Wholesale Goods"
        }
    ],
    "sg:phone":"+33 3 20 08 11 08",
    "sg:postcode":"59160",
    "sg:province":"Nord Pas-de-Calais",
    "sg:tags":[
        "vegetable",
        "fruit",
        "agriculture",
        "livestock"
    ],
    "wof:name":"Lomme",
    "wof:placetype":"venue"
},
  "geometry": {"coordinates":[3.004727,50.627064],"type":"Point"}
}