{
  "type": "Feature",
  "properties": {
    "iso:country":"FR",
    "sg:address":"Carri\u00e8re du Cailloit",
    "sg:city":"Glageon",
    "sg:orig_category":"Non-Classified Establishments",
    "sg:phone":"+33 3 27 60 82 82",
    "sg:postcode":"59132",
    "sg:province":"Nord Pas-de-Calais",
    "wof:name":"S.c.b.g. S.a.r.l. - Soci\u00e9t\u00e9 Des Carri\u00e8res Bocahut De Glageon",
    "wof:placetype":"venue"
},
  "geometry": {"coordinates":[4.082308,50.056953],"type":"Point"}
}