{
  "type": "Feature",
  "properties": {
    "addr:full":"23, Rue des Jardins Fleuris, 54420 Saulxures l\u00e8s Nancy Lorraine",
    "addr:housenumber":"23",
    "addr:postcode":"54420",
    "addr:street":"Rue Des Jardins Fleuris",
    "iso:country":"FR",
    "sg:address":"23, Rue des Jardins Fleuris, 54420 Saulxures l\u00e8s Nancy",
    "sg:orig_category":"Unclassifiable Establishments",
    "sg:phone":"+33 3 83 29 05 51",
    "sg:province":"Lorraine",
    "wof:name":"Rulquin S.a.",
    "wof:placetype":"venue"
},
  "geometry": {"coordinates":[6.247936,48.69128],"type":"Point"}
}