{
  "type": "Feature",
  "properties": {
    "addr:full":"B.P. 120, 60130 Saint Just en Chauss\u00e9e^^Rte de Fournival, 60130 Saint Just en Chauss\u00e9e Picardie 60130",
    "addr:housenumber":"b.p. 120",
    "addr:postcode":"60130;60130;60130",
    "addr:street":"Just;Fournival;Just En Chausse\u0301E Picardie",
    "iso:country":"FR",
    "sg:address":"B.P. 120, 60130 Saint Just en Chauss\u00e9e^^Rte de Fournival, 60130 Saint Just en Chauss\u00e9e",
    "sg:orig_category":"Non-Classified Establishments",
    "sg:phone":"+33 3 44 78 50 03",
    "sg:postcode":"60130",
    "sg:province":"Picardie",
    "wof:name":"Bavard Maurice Etablissements S.a.",
    "wof:placetype":"venue"
},
  "geometry": {"coordinates":[2.373278,49.516033],"type":"Point"}
}