{
  "type": "Feature",
  "properties": {
    "addr:full":"Les Rivets; Domene; 38420 Rhone-Alpes 38420",
    "addr:postcode":"38420;38420",
    "addr:street":"Domene",
    "iso:country":"FR",
    "sg:address":"Les Rivets; Domene; 38420",
    "sg:classifiers":[
        {
            "category":"Banks & Credit Unions",
            "subcategory":"Bank",
            "type":"Services"
        }
    ],
    "sg:phone":"+33 4 76 77 10 80",
    "sg:postcode":"38420",
    "sg:province":"Rhone-Alpes",
    "wof:name":"Banque Rh\u00f4ne Alpes",
    "wof:placetype":"venue"
},
  "geometry": {"coordinates":[5.838225,45.202049],"type":"Point"}
}