{
  "type": "Feature",
  "properties": {
    "addr:full":"56, Rue Henri Dunant, 80400 Ham Picardie",
    "addr:housenumber":"56",
    "addr:postcode":"80400",
    "addr:street":"Rue Henri Dunant",
    "iso:country":"FR",
    "sg:address":"56, Rue Henri Dunant, 80400 Ham",
    "sg:orig_category":"Non-Classified Establishments",
    "sg:phone":"+33 3 23 36 49 79",
    "sg:province":"Picardie",
    "wof:name":"M\u00e9ca Hydro S.a.r.l.",
    "wof:placetype":"venue"
},
  "geometry": {"coordinates":[3.081271,49.741268],"type":"Point"}
}