{
  "type": "Feature",
  "properties": {
    "iso:country":"FR",
    "sg:address":"4, Rue Niepce les Tertiales, 60471 Compi\u00e8gne C\u00e9dex",
    "sg:orig_category":"Unclassifiable Establishments",
    "sg:phone":"+33 3 44 20 02 85",
    "sg:province":"Languedoc-Roussillon",
    "wof:name":"Bureau V\u00e9ritas",
    "wof:placetype":"venue"
},
  "geometry": {"coordinates":[2.82248,49.415771],"type":"Point"}
}