{
  "type": "Feature",
  "properties": {
    "addr:full":"Le Bouyge 19600 Saint Pantal\u00e9on de Larche Limousin",
    "addr:postcode":"19600 saint",
    "iso:country":"FR",
    "sg:address":"Le Bouyge 19600 Saint Pantal\u00e9on de Larche",
    "sg:orig_category":"Unclassifiable Establishments",
    "sg:phone":"+33 5 55 86 08 45",
    "sg:province":"Limousin",
    "wof:name":"Tonnellerie Saury S.a.",
    "wof:placetype":"venue"
},
  "geometry": {"coordinates":[1.469713,45.159481],"type":"Point"}
}