{
  "type": "Feature",
  "properties": {
    "iso:country":"FR",
    "sg:address":"3 Rue Du Chemin Vert 93800 \u00c9pinay Sur Seine",
    "sg:classifiers":[
        {
            "category":"Professional",
            "subcategory":"Advertising",
            "type":"Services"
        }
    ],
    "sg:phone":"+33 1 49 40 13 00",
    "sg:postcode":"93800",
    "sg:province":"Ile de France",
    "sg:tags":[
        "information",
        "medium",
        "communication"
    ],
    "wof:name":"Videodio Direction Sa",
    "wof:placetype":"venue"
},
  "geometry": {"coordinates":[2.322213,48.957497],"type":"Point"}
}