{
  "type": "Feature",
  "properties": {
    "iso:country":"FR",
    "sg:address":"9, Rue de Brotterote, 38950 Saint Martin le Vinoux",
    "sg:orig_category":"Unclassifiable Establishments",
    "sg:phone":"+33 4 38 02 18 60",
    "sg:postcode":"38950",
    "sg:province":"Rhone-Alpes",
    "wof:name":"Imprimerie Des Montagnes S.a.r.l.",
    "wof:placetype":"venue"
},
  "geometry": {"coordinates":[5.688492,45.214054],"type":"Point"}
}