{
  "type": "Feature",
  "properties": {
    "addr:full":"ZAC l' Arn\u00e8de Sommi\u00e8res Languedoc-Roussillon 30250",
    "addr:postcode":"30250",
    "addr:street":"Zac L ' Arne\u0300De",
    "iso:country":"FR",
    "sg:address":"ZAC l' Arn\u00e8de",
    "sg:city":"Sommi\u00e8res",
    "sg:orig_category":"Unclassifiable Establishments",
    "sg:phone":"+33 4 66 80 34 02",
    "sg:postcode":"30250",
    "sg:province":"Languedoc-Roussillon",
    "wof:name":"Romain Pag\u00e8s S.a.r.l.",
    "wof:placetype":"venue"
},
  "geometry": {"coordinates":[4.08675,43.808849],"type":"Point"}
}