{
  "type": "Feature",
  "properties": {
    "addr:full":"18, Rue Ernest Hiolle, 59300 Valenciennes Nord Pas-de-Calais",
    "addr:housenumber":"18",
    "addr:postcode":"59300",
    "addr:street":"Rue Ernest Hiolle",
    "iso:country":"FR",
    "sg:address":"18, Rue Ernest Hiolle, 59300 Valenciennes",
    "sg:orig_category":"Unclassifiable Establishments",
    "sg:phone":"+33 3 27 46 32 27",
    "sg:province":"Nord Pas-de-Calais",
    "wof:name":"Glardon S.a.r.l.",
    "wof:placetype":"venue"
},
  "geometry": {"coordinates":[3.534635,50.35778],"type":"Point"}
}