{
  "type": "Feature",
  "properties": {
    "iso:country":"FR",
    "sg:address":"52 Mail Des Charmilles 10000 Troyes",
    "sg:classifiers":[
        {
            "category":"Utilities",
            "subcategory":"Telephone",
            "type":"Services"
        }
    ],
    "sg:phone":"+33 3 25 78 45 00",
    "sg:province":"Champagne",
    "sg:tags":[
        "telecommunication"
    ],
    "wof:name":"Mag 2 Equipement Sarl",
    "wof:placetype":"venue"
},
  "geometry": {"coordinates":[4.087677,48.300373],"type":"Point"}
}