{
  "type": "Feature",
  "properties": {
    "addr:full":"56, Rue Diderot, 66000 Perpignan Languedoc-Roussillon",
    "addr:housenumber":"56",
    "addr:postcode":"66000",
    "addr:street":"Rue Diderot",
    "iso:country":"FR",
    "sg:address":"56, Rue Diderot, 66000 Perpignan",
    "sg:orig_category":"Non-Classified Establishments",
    "sg:phone":"+33 4 68 35 04 27",
    "sg:province":"Languedoc-Roussillon",
    "wof:name":"M\u00e9diterrann\u00e9enne De Polyester S.a.r.l.",
    "wof:placetype":"venue"
},
  "geometry": {"coordinates":[2.907975,42.702507],"type":"Point"}
}