{
  "type": "Feature",
  "properties": {
    "addr:full":"11, ZI, 39140 Bletterans Franche Comt\u00e9",
    "addr:housenumber":"11",
    "addr:postcode":"39140",
    "addr:street":"Zi;Franche Comte\u0301",
    "iso:country":"FR",
    "sg:address":"11, ZI, 39140 Bletterans",
    "sg:orig_category":"Non-Classified Establishments",
    "sg:phone":"+33 3 84 85 04 82",
    "sg:province":"Franche Comt\u00e9",
    "wof:name":"Spiteri Georges S.a.r.l.",
    "wof:placetype":"venue"
},
  "geometry": {"coordinates":[5.415271,46.683315],"type":"Point"}
}