{
  "type": "Feature",
  "properties": {
    "iso:country":"FR",
    "sg:address":"1, Rue du Ch\u00e2teau, 55400 Braquis",
    "sg:orig_category":"Unclassifiable Establishments",
    "sg:phone":"+33 3 29 87 20 57",
    "sg:province":"Lorraine",
    "wof:name":"Lambert S.a.",
    "wof:placetype":"venue"
},
  "geometry": {"coordinates":[5.628345,49.155682],"type":"Point"}
}