{
  "type": "Feature",
  "properties": {
    "iso:country":"FR",
    "sg:address":"20 Rue Bouvier 75011 Paris",
    "sg:classifiers":[
        {
            "category":"Shopping",
            "subcategory":"Hobbies, Toys, & Games",
            "type":"Retail Goods"
        }
    ],
    "sg:phone":"+33 1 44 93 20 93",
    "sg:postcode":"75011",
    "sg:province":"Ile de France",
    "sg:tags":[
        "product",
        "miscellaneous",
        "entertainment"
    ],
    "wof:name":"Atelier Von Nagel",
    "wof:placetype":"venue"
},
  "geometry": {"coordinates":[2.387125,48.852116],"type":"Point"}
}