{
  "type": "Feature",
  "properties": {
    "iso:country":"FR",
    "sg:address":"Rue des Artisans - B\u00e2t. Sicah Lorraine",
    "sg:city":"Florange",
    "sg:orig_category":"Non-Classified Establishments",
    "sg:phone":"+33 3 82 84 73 36",
    "sg:postcode":"57190",
    "sg:province":"Lorraine",
    "wof:name":"Soci\u00e9t\u00e9 D'exploitation Des Etablissements Rossi S.a.r.l.",
    "wof:placetype":"venue"
},
  "geometry": {"coordinates":[6.127649,49.314823],"type":"Point"}
}