{
  "type": "Feature",
  "properties": {
    "addr:full":"La Royaute 79200 Pompaire Poitou-Charentes",
    "addr:postcode":"79200",
    "iso:country":"FR",
    "sg:address":"La Royaute 79200 Pompaire",
    "sg:classifiers":[
        {
            "category":"Utilities",
            "subcategory":"Mobile Phone",
            "type":"Services"
        }
    ],
    "sg:phone":"+33 5 49 95 27 45",
    "sg:province":"Poitou-Charentes",
    "sg:tags":[
        "utensil",
        "enamelled"
    ],
    "wof:name":"Vital Ouest S.a.",
    "wof:placetype":"venue"
},
  "geometry": {"coordinates":[-0.238664,46.635441],"type":"Point"}
}