{
  "type": "Feature",
  "properties": {
    "addr:full":"Le Pont Du Loup 06140 Tourrettes Sur Loup Franche Comt\u00e9",
    "addr:postcode":"06140",
    "addr:street":"Franche Comte\u0301",
    "iso:country":"FR",
    "sg:address":"Le Pont Du Loup 06140 Tourrettes Sur Loup",
    "sg:classifiers":[
        {
            "category":"Wholesale",
            "subcategory":"Fruits & Vegetables",
            "type":"Manufacturing & Wholesale Goods"
        }
    ],
    "sg:phone":"+33 4 93 59 32 91",
    "sg:province":"Franche Comt\u00e9",
    "sg:tags":[
        "food",
        "product",
        "related"
    ],
    "wof:name":"Societe Meridionale Des Confiseries Florian",
    "wof:placetype":"venue"
},
  "geometry": {"coordinates":[7.09318,43.723228],"type":"Point"}
}