{
  "type": "Feature",
  "properties": {
    "iso:country":"FR",
    "sg:address":"Z.I. de Beaune Savigny",
    "sg:city":"Beaune",
    "sg:orig_category":"Unclassifiable Establishments",
    "sg:phone":"+33 3 80 22 06 13",
    "sg:postcode":"21200",
    "sg:province":"Bourgogne",
    "wof:name":"S.i.m.a. S.a. - Soci\u00e9t\u00e9 D'importation De Motos Et Accessoires",
    "wof:placetype":"venue"
},
  "geometry": {"coordinates":[4.835545,47.019245],"type":"Point"}
}