{
  "type": "Feature",
  "properties": {
    "addr:full":"ZI du Dr\u00e9sseve Baud Bretagne 56150",
    "addr:postcode":"56150",
    "addr:street":"Zi Du Dre\u0301Sseve Baud Bretagne",
    "iso:country":"FR",
    "sg:address":"ZI du Dr\u00e9sseve",
    "sg:city":"Baud",
    "sg:orig_category":"Unclassifiable Establishments",
    "sg:phone":"+33 2 97 39 16 16",
    "sg:postcode":"56150",
    "sg:province":"Bretagne",
    "wof:name":"Nijal S.a.",
    "wof:placetype":"venue"
},
  "geometry": {"coordinates":[-3.019457,47.87542],"type":"Point"}
}