{
  "type": "Feature",
  "properties": {
    "addr:full":"Zi Du Martray Zone Industrielle 14730 Giberville Giberville Basse Normandie 14730",
    "addr:postcode":"14730;14730",
    "addr:street":"Zi Du Martray Zone Industrielle",
    "iso:country":"FR",
    "sg:address":"Zi Du Martray Zone Industrielle 14730 Giberville",
    "sg:city":"Giberville",
    "sg:classifiers":[
        {
            "category":"Food Court",
            "type":"Food & Drink"
        }
    ],
    "sg:phone":"+33 2 31 72 22 22",
    "sg:postcode":"14730",
    "sg:province":"Basse Normandie",
    "sg:tags":[
        "product",
        "related"
    ],
    "wof:name":"Elidis",
    "wof:placetype":"venue"
},
  "geometry": {"coordinates":[-0.283609,49.182594],"type":"Point"}
}