{
  "type": "Feature",
  "properties": {
    "iso:country":"FR",
    "sg:address":"19, Bd Gaston Doumergue, 44200 Nantes",
    "sg:orig_category":"Unclassifiable Establishments",
    "sg:phone":"+33 2 40 41 43 91",
    "sg:province":"Pays de Loire",
    "wof:name":"I.b.m.",
    "wof:placetype":"venue"
},
  "geometry": {"coordinates":[-1.547199,47.207409],"type":"Point"}
}