{
  "type": "Feature",
  "properties": {
    "iso:country":"FR",
    "sg:address":"B.P. 82, 02302 Chauny C\u00e9dex^^16, Rue des Anciens Combattants, 02300 Chauny",
    "sg:orig_category":"Non-Classified Establishments",
    "sg:phone":"+33 3 23 52 13 26",
    "sg:province":"Picardie",
    "wof:name":"Tayon S.a.",
    "wof:placetype":"venue"
},
  "geometry": {"coordinates":[3.203075,49.601242],"type":"Point"}
}