{
  "type": "Feature",
  "properties": {
    "addr:full":"45, Av de Stalingrad, 21000 Dijon Dijon Bourgogne 21000",
    "addr:postcode":"21000;21000",
    "addr:street":"45 Av De Stalingrad",
    "iso:country":"FR",
    "sg:address":"45, Av de Stalingrad, 21000 Dijon",
    "sg:city":"Dijon",
    "sg:orig_category":"Unclassifiable Establishments",
    "sg:phone":"+33 3 80 74 55 00",
    "sg:postcode":"21000",
    "sg:province":"Bourgogne",
    "wof:name":"S.f.i.m. O.d.s. S.a. - Soci\u00e9t\u00e9 Fran\u00e7aise D'instruments De Mesure",
    "wof:placetype":"venue"
},
  "geometry": {"coordinates":[5.057589,47.341404],"type":"Point"}
}