{
  "type": "Feature",
  "properties": {
    "iso:country":"FR",
    "sg:address":"B.P. 7",
    "sg:city":"Amb\u00e8s",
    "sg:orig_category":"Non-Classified Establishments",
    "sg:phone":"+33 5 57 80 88 50",
    "sg:postcode":"33810",
    "sg:province":"Aquitaine",
    "wof:name":"Bernard Et Meneret S.a.",
    "wof:placetype":"venue"
},
  "geometry": {"coordinates":[-0.529699,45.013222],"type":"Point"}
}