{
  "type": "Feature",
  "properties": {
    "iso:country":"FR",
    "sg:address":"B.P. 30026, 57955 Montigny l\u00e8s Metz C\u00e9dex^^Chemin de Blory, 57950 Montigny l\u00e8s Metz",
    "sg:orig_category":"Non-Classified Establishments",
    "sg:phone":"+33 3 87 50 41 33",
    "sg:province":"Lorraine",
    "wof:name":"Starun S.a.",
    "wof:placetype":"venue"
},
  "geometry": {"coordinates":[6.15241,49.099918],"type":"Point"}
}