{
  "type": "Feature",
  "properties": {
    "iso:country":"FR",
    "sg:address":"Frejorgues Zi N 4 Espace C Cial Frejo 34130 Mauguio",
    "sg:classifiers":[
        {
            "category":"Shopping",
            "subcategory":"Bicycles & Sporting Goods",
            "type":"Retail Goods"
        }
    ],
    "sg:phone":"+33 4 67 20 12 11",
    "sg:postcode":"34130",
    "sg:province":"Languedoc-Roussillon",
    "sg:tags":[
        "product",
        "sport",
        "miscellaneous"
    ],
    "wof:name":"Dessault Sub Sarl",
    "wof:placetype":"venue"
},
  "geometry": {"coordinates":[4.0079,43.617867],"type":"Point"}
}