{
  "type": "Feature",
  "properties": {
    "addr:full":"51, Rue du Commerce, 51678 Reims C\u00e9dex 02^^51, Rue du Commerce, 51350 Cormontreuil Champagne 51350",
    "addr:housenumber":"51;02 ^ ^ 51",
    "addr:postcode":"51678;51350;51350",
    "addr:street":"Rue Du Commerce;Ce\u0301Dex;Rue Du Commerce;Champagne",
    "iso:country":"FR",
    "sg:address":"51, Rue du Commerce, 51678 Reims C\u00e9dex 02^^51, Rue du Commerce, 51350 Cormontreuil",
    "sg:orig_category":"Bandes transporteuses en caoutchouc Bandes transporteuses en mati\u00e8res plastiques Bandes transporteus",
    "sg:phone":"+33 3 26 40 62 00",
    "sg:postcode":"51350",
    "sg:province":"Champagne",
    "wof:name":"I.b.s. Bandes Transporteuses S.a.r.l.",
    "wof:placetype":"venue"
},
  "geometry": {"coordinates":[4.05395,49.223545],"type":"Point"}
}