{
  "type": "Feature",
  "properties": {
    "addr:full":"5 Rue Rhin 68330 Huningue Huningue Alsace 68330",
    "addr:housenumber":"5",
    "addr:postcode":"68330;68330",
    "addr:street":"Rue Rhin",
    "iso:country":"FR",
    "sg:address":"5 Rue Rhin 68330 Huningue",
    "sg:city":"Huningue",
    "sg:classifiers":[
        {
            "category":"Professional",
            "type":"Services"
        }
    ],
    "sg:phone":"+33 3 89 70 26 00",
    "sg:postcode":"68330",
    "sg:province":"Alsace",
    "sg:tags":[
        "transport",
        "road"
    ],
    "wof:name":"Fel Fiege Euro Logistik Sarl",
    "wof:placetype":"venue"
},
  "geometry": {"coordinates":[7.588057,47.598373],"type":"Point"}
}