{
  "type": "Feature",
  "properties": {
    "addr:full":"9/13, Av. du Lac - Parc du Bois Briard, 91080 Courcouronnes Ile de France",
    "addr:housenumber":"9 / 13",
    "addr:postcode":"91080",
    "addr:street":"Av. Du Lac Parc",
    "iso:country":"FR",
    "sg:address":"9/13, Av. du Lac - Parc du Bois Briard, 91080 Courcouronnes",
    "sg:orig_category":"Unclassifiable Establishments",
    "sg:phone":"+33 1 69 87 51 11",
    "sg:province":"Ile de France",
    "wof:name":"Compaq S.a.r.l.",
    "wof:placetype":"venue"
},
  "geometry": {"coordinates":[2.424326,48.621529],"type":"Point"}
}