{
  "type": "Feature",
  "properties": {
    "addr:full":"Rue de l'Abbaye - Usine de Boh\u00e9ries Vadencourt Picardie 02120",
    "addr:postcode":"02120",
    "addr:street":"Rue De L'Abbaye;Picardie",
    "iso:country":"FR",
    "sg:address":"Rue de l'Abbaye - Usine de Boh\u00e9ries",
    "sg:city":"Vadencourt",
    "sg:orig_category":"Unclassifiable Establishments",
    "sg:phone":"+33 3 23 05 71 70",
    "sg:postcode":"02120",
    "sg:province":"Picardie",
    "wof:name":"Sadosky Fr\u00e8res S.a.",
    "wof:placetype":"venue"
},
  "geometry": {"coordinates":[3.573767,49.916897],"type":"Point"}
}