{
  "type": "Feature",
  "properties": {
    "iso:country":"FR",
    "sg:address":"41, Bd Champy Richardets, 93160 Noisy le Grand",
    "sg:orig_category":"Unclassifiable Establishments",
    "sg:phone":"+33 1 48 15 42 42",
    "sg:province":"Ile de France",
    "wof:name":"Atep S.a.r.l.",
    "wof:placetype":"venue"
},
  "geometry": {"coordinates":[2.570179,48.837608],"type":"Point"}
}