{
  "type": "Feature",
  "properties": {
    "addr:full":"16 Rue De Boussange 57304 Hagondange Centre",
    "addr:housenumber":"16",
    "addr:postcode":"57304",
    "addr:street":"Rue De Boussange",
    "iso:country":"FR",
    "sg:address":"16 Rue De Boussange 57304 Hagondange",
    "sg:classifiers":[
        {
            "category":"Manufacturing",
            "subcategory":"Metals",
            "type":"Manufacturing & Wholesale Goods"
        }
    ],
    "sg:phone":"+33 3 87 71 44 10",
    "sg:province":"Centre",
    "sg:tags":[
        "metallurgy",
        "metalworking",
        "processing"
    ],
    "wof:name":"Technilor Sa",
    "wof:placetype":"venue"
},
  "geometry": {"coordinates":[6.16994,49.254086],"type":"Point"}
}