{
  "type": "Feature",
  "properties": {
    "addr:full":"Chem De La Loge 31400 Toulouse Midi Pyr\u00e9n\u00e9es 31400",
    "addr:postcode":"31400;31400",
    "addr:street":"Chem De La Loge",
    "iso:country":"FR",
    "sg:address":"Chem De La Loge 31400 Toulouse",
    "sg:classifiers":[
        {
            "category":"Manufacturing",
            "subcategory":"Chemicals & Compounds",
            "type":"Manufacturing & Wholesale Goods"
        }
    ],
    "sg:phone":"+33 5 62 25 72 80",
    "sg:postcode":"31400",
    "sg:province":"Midi Pyr\u00e9n\u00e9es",
    "sg:tags":[
        "pharmaceutical",
        "chemistry"
    ],
    "wof:name":"Raisio France",
    "wof:placetype":"venue"
},
  "geometry": {"coordinates":[1.43623,43.572006],"type":"Point"}
}