{
  "type": "Feature",
  "properties": {
    "iso:country":"FR",
    "sg:address":"B.P. 5302, 66033 Perpignan C\u00e9dex^^Rue de Murcia - March\u00e9 International Saint Charles, 66000 Perpigna",
    "sg:orig_category":"Non-Classified Establishments",
    "sg:phone":"+33 4 68 68 35 25",
    "sg:province":"Languedoc-Roussillon",
    "wof:name":"Primar France S.a.r.l.",
    "wof:placetype":"venue"
},
  "geometry": {"coordinates":[2.88743,42.69812],"type":"Point"}
}