{
  "type": "Feature",
  "properties": {
    "addr:full":"60, Rue de Luzais, 38070 Saint Quentin Fallavier Rhone-Alpes",
    "addr:housenumber":"60",
    "addr:postcode":"38070",
    "addr:street":"Rue De Luzais",
    "iso:country":"FR",
    "sg:address":"60, Rue de Luzais, 38070 Saint Quentin Fallavier",
    "sg:orig_category":"Unclassifiable Establishments",
    "sg:phone":"+33 4 74 95 59 48",
    "sg:province":"Rhone-Alpes",
    "wof:name":"Opaline S.a.s",
    "wof:placetype":"venue"
},
  "geometry": {"coordinates":[5.095886,45.644623],"type":"Point"}
}