{
  "type": "Feature",
  "properties": {
    "addr:full":"Zone De Planuya 64200 Arcangues Arcangues Aquitaine 64200",
    "addr:postcode":"64200;64200",
    "iso:country":"FR",
    "sg:address":"Zone De Planuya 64200 Arcangues",
    "sg:city":"Arcangues",
    "sg:classifiers":[
        {
            "category":"Transit Center",
            "subcategory":"Freight",
            "type":"Transportation"
        }
    ],
    "sg:phone":"+33 5 59 70 36 81",
    "sg:postcode":"64200",
    "sg:province":"Aquitaine",
    "sg:tags":[
        "metallurgy",
        "pipe",
        "metalworking",
        "sheet"
    ],
    "wof:name":"Ets Bourden",
    "wof:placetype":"venue"
},
  "geometry": {"coordinates":[-1.519779,43.435661],"type":"Point"}
}