{
  "type": "Feature",
  "properties": {
    "addr:full":"139-143 Rue De La Libre Pens\u00e9e 93230 Romainville Ile de France",
    "addr:housenumber":"139-143",
    "addr:postcode":"93230;ile",
    "addr:street":"Rue De La Libre Pense\u0301E",
    "iso:country":"FR",
    "sg:address":"139-143 Rue De La Libre Pens\u00e9e 93230 Romainville",
    "sg:classifiers":[
        {
            "category":"Manufacturing",
            "subcategory":"Printing",
            "type":"Manufacturing & Wholesale Goods"
        }
    ],
    "sg:phone":"+33 1 49 88 87 30",
    "sg:province":"Ile de France",
    "sg:tags":[
        "publishing"
    ],
    "wof:name":"Atouts Sa",
    "wof:placetype":"venue"
},
  "geometry": {"coordinates":[2.438608,48.872387],"type":"Point"}
}