{
  "type": "Feature",
  "properties": {
    "addr:full":"B.P. 17, 38170 Seyssinet Pariset^^13, Rue de la Tuilerie, 38170 Seyssinet Pariset Rhone-Alpes 38170",
    "addr:postcode":"38170;38170;38170",
    "addr:street":"B.P. 17;Rue De La Tuilerie;Rhone-Alpes",
    "iso:country":"FR",
    "sg:address":"B.P. 17, 38170 Seyssinet Pariset^^13, Rue de la Tuilerie, 38170 Seyssinet Pariset",
    "sg:orig_category":"Non-Classified Establishments",
    "sg:phone":"+33 4 76 70 05 55",
    "sg:postcode":"38170",
    "sg:province":"Rhone-Alpes",
    "wof:name":"Ameg S.a.r.l.",
    "wof:placetype":"venue"
},
  "geometry": {"coordinates":[5.696125,45.180908],"type":"Point"}
}