{
  "type": "Feature",
  "properties": {
    "addr:full":"Rue De Buray Zi 41500 Mer Mer Centre 41500",
    "addr:postcode":"41500;41500",
    "addr:street":"Rue De Buray Zi",
    "iso:country":"FR",
    "sg:address":"Rue De Buray Zi 41500 Mer",
    "sg:city":"Mer",
    "sg:classifiers":[
        {
            "category":"Manufacturing",
            "subcategory":"Metals",
            "type":"Manufacturing & Wholesale Goods"
        }
    ],
    "sg:phone":"+33 2 54 81 44 54",
    "sg:postcode":"41500",
    "sg:province":"Centre",
    "sg:tags":[
        "metallurgy",
        "metalworking",
        "processing"
    ],
    "wof:name":"Talbot Decoupage Emboutissage",
    "wof:placetype":"venue"
},
  "geometry": {"coordinates":[1.431871,47.654369],"type":"Point"}
}