{
  "type": "Feature",
  "properties": {
    "iso:country":"FR",
    "sg:address":"7 Boulevard Chanzy 08200 Sedan",
    "sg:classifiers":[
        {
            "category":"Manufacturing",
            "subcategory":"Tools & Machinery",
            "type":"Manufacturing & Wholesale Goods"
        }
    ],
    "sg:phone":"+33 3 24 27 01 40",
    "sg:postcode":"08200",
    "sg:province":"Champagne",
    "sg:tags":[
        "metallurgy",
        "metalworking"
    ],
    "wof:name":"Industrielle De Sedan (l)",
    "wof:placetype":"venue"
},
  "geometry": {"coordinates":[4.928036,49.701469],"type":"Point"}
}