{
  "type": "Feature",
  "properties": {
    "addr:full":"56, Rue Fondary, 75015 Paris Ile de France",
    "addr:housenumber":"56",
    "addr:postcode":"75015",
    "addr:street":"Rue Fondary",
    "iso:country":"FR",
    "sg:address":"56, Rue Fondary, 75015 Paris",
    "sg:orig_category":"Unclassifiable Establishments",
    "sg:phone":"+33 1 45 79 55 55",
    "sg:province":"Ile de France",
    "wof:name":"Seri Electronique S.a.r.l.",
    "wof:placetype":"venue"
},
  "geometry": {"coordinates":[2.296331,48.84671],"type":"Point"}
}