{
  "type": "Feature",
  "properties": {
    "addr:full":"Blecheins 74160 Archamps Rhone-Alpes 74160",
    "addr:postcode":"74160;74160",
    "addr:street":"Blecheins",
    "iso:country":"FR",
    "sg:address":"Blecheins 74160 Archamps",
    "sg:classifiers":[
        {
            "category":"Wholesale",
            "subcategory":"Medical Equipment & Supplies",
            "type":"Manufacturing & Wholesale Goods"
        }
    ],
    "sg:phone":"+33 4 50 43 63 41",
    "sg:postcode":"74160",
    "sg:province":"Rhone-Alpes",
    "sg:tags":[
        "instrument",
        "health",
        "-",
        "precision"
    ],
    "wof:name":"Sarl Ballery",
    "wof:placetype":"venue"
},
  "geometry": {"coordinates":[6.129,46.122856],"type":"Point"}
}