{
  "type": "Feature",
  "properties": {
    "iso:country":"FR",
    "sg:address":"17, Rue Saint Michel, 69007 Lyon",
    "sg:orig_category":"Unclassifiable Establishments",
    "sg:phone":"+33 4 72 76 80 69",
    "sg:postcode":"69007",
    "sg:province":"Rhone-Alpes",
    "wof:name":"Egide S.a.",
    "wof:placetype":"venue"
},
  "geometry": {"coordinates":[4.843961,45.752785],"type":"Point"}
}