{
  "type": "Feature",
  "properties": {
    "addr:full":"17, Rue Gaston Evrard - Centre Commercial de Larrieu, 31094 Toulouse C\u00e9dex 1 Midi Pyr\u00e9n\u00e9es",
    "addr:housenumber":"17;1",
    "addr:postcode":"31094",
    "addr:street":"Rue Gaston Evrard Centre",
    "iso:country":"FR",
    "sg:address":"17, Rue Gaston Evrard - Centre Commercial de Larrieu, 31094 Toulouse C\u00e9dex 1",
    "sg:orig_category":"Non-Classified Establishments",
    "sg:phone":"+33 5 61 19 33 33",
    "sg:province":"Midi Pyr\u00e9n\u00e9es",
    "wof:name":"C.e.i.c.o.m. S.a.",
    "wof:placetype":"venue"
},
  "geometry": {"coordinates":[1.44301,43.604359],"type":"Point"}
}