{
  "type": "Feature",
  "properties": {
    "addr:full":"32 Fbg Des Balmettes 74000 Annecy Rhone-Alpes 74000",
    "addr:housenumber":"32",
    "addr:postcode":"74000;74000",
    "addr:street":"Fbg Des Balmettes",
    "iso:country":"FR",
    "sg:address":"32 Fbg Des Balmettes 74000 Annecy",
    "sg:classifiers":[
        {
            "category":"Building & Trades",
            "subcategory":"Construction",
            "type":"Services"
        }
    ],
    "sg:phone":"+33 4 50 51 40 15",
    "sg:postcode":"74000",
    "sg:province":"Rhone-Alpes",
    "sg:tags":[
        "work",
        "public"
    ],
    "wof:name":"Colas Rhone Alpes",
    "wof:placetype":"venue"
},
  "geometry": {"coordinates":[6.123626,45.890743],"type":"Point"}
}