{
  "type": "Feature",
  "properties": {
    "addr:full":"ZI Fontaine Notre Dame Cambrai Nord Pas-de-Calais 59400",
    "addr:postcode":"59400",
    "addr:street":"Notre;Pas-De-Calais",
    "iso:country":"FR",
    "sg:address":"ZI Fontaine Notre Dame",
    "sg:city":"Cambrai",
    "sg:orig_category":"Unclassifiable Establishments",
    "sg:phone":"+33 3 27 72 40 40",
    "sg:postcode":"59400",
    "sg:province":"Nord Pas-de-Calais",
    "wof:name":"Giraud Nord Picardie S.a. - Agence De Cambrai",
    "wof:placetype":"venue"
},
  "geometry": {"coordinates":[3.23419,50.175018],"type":"Point"}
}