{
  "type": "Feature",
  "properties": {
    "iso:country":"FR",
    "sg:address":"B.P. 110, 37171 Chambray l\u00e8s Tours C\u00e9dex^^85, Av. Grand Sud, 37170 Chambray l\u00e8s Tours",
    "sg:city":"Chambray-l\u00e8s-Tours",
    "sg:orig_category":"Non-Classified Establishments",
    "sg:phone":"+33 2 47 80 32 00",
    "sg:postcode":"37170",
    "sg:province":"Centre",
    "wof:name":"Auto-distribution Touraine S.a.",
    "wof:placetype":"venue"
},
  "geometry": {"coordinates":[0.71327,47.33884],"type":"Point"}
}