{
  "type": "Feature",
  "properties": {
    "iso:country":"FR",
    "sg:address":"29 bis, Rue Dailly, 92210 Saint Cloud",
    "sg:orig_category":"Unclassifiable Establishments",
    "sg:phone":"+33 1 41 12 06 69",
    "sg:province":"Ile de France",
    "wof:name":"Dominex France S.a.",
    "wof:placetype":"venue"
},
  "geometry": {"coordinates":[2.218326,48.845768],"type":"Point"}
}