{
  "type": "Feature",
  "properties": {
    "addr:full":"6 Pl Mabuse 59600 Maubeuge Nord Pas-de-Calais 59600",
    "addr:housenumber":"6",
    "addr:postcode":"59600;59600",
    "addr:street":"Pl Mabuse",
    "iso:country":"FR",
    "sg:address":"6 Pl Mabuse 59600 Maubeuge",
    "sg:classifiers":[
        {
            "category":"Banks & Credit Unions",
            "subcategory":"Financial Services",
            "type":"Services"
        }
    ],
    "sg:phone":"+33 3 27 63 02 07",
    "sg:postcode":"59600",
    "sg:province":"Nord Pas-de-Calais",
    "sg:tags":[
        "banking",
        "insurance",
        "institution",
        "finance"
    ],
    "wof:name":"Credit Lyonnais",
    "wof:placetype":"venue"
},
  "geometry": {"coordinates":[3.973548,50.276882],"type":"Point"}
}