{
  "type": "Feature",
  "properties": {
    "addr:full":"18, Place du Breuil, 42700 Firminy Auvergne",
    "addr:housenumber":"18",
    "addr:postcode":"42700",
    "addr:street":"Place Du Breuil",
    "iso:country":"FR",
    "sg:address":"18, Place du Breuil, 42700 Firminy",
    "sg:orig_category":"Non-Classified Establishments",
    "sg:phone":"+33 4 77 10 04 88",
    "sg:province":"Auvergne",
    "wof:name":"Protravel S.a.",
    "wof:placetype":"venue"
},
  "geometry": {"coordinates":[4.288372,45.388355],"type":"Point"}
}