{
  "type": "Feature",
  "properties": {
    "addr:full":"67, Bd du Capitaine G\u00e8ze, 13014 Marseille Provence-Alpes-C\u00f4te d'Azur",
    "addr:housenumber":"67",
    "addr:postcode":"13014",
    "addr:street":"Bd Du Capitaine Ge\u0300Ze",
    "iso:country":"FR",
    "sg:address":"67, Bd du Capitaine G\u00e8ze, 13014 Marseille",
    "sg:orig_category":"Unclassifiable Establishments",
    "sg:phone":"+33 4 91 61 53 00",
    "sg:province":"Provence-Alpes-C\u00f4te d'Azur",
    "wof:name":"Haribo Ricql\u00e8s Zan S.a.",
    "wof:placetype":"venue"
},
  "geometry": {"coordinates":[5.375386,43.331535],"type":"Point"}
}