{
  "type": "Feature",
  "properties": {
    "iso:country":"FR",
    "sg:address":"Usine de la Mousse",
    "sg:city":"L'Aigle",
    "sg:orig_category":"Unclassifiable Establishments",
    "sg:phone":"+33 2 33 84 21 21",
    "sg:postcode":"61300",
    "sg:province":"Basse Normandie",
    "wof:name":"Fr\u00e9n\u00e9hard Et Michaux S.a.",
    "wof:placetype":"venue"
},
  "geometry": {"coordinates":[0.64151,48.73592],"type":"Point"}
}