{
  "type": "Feature",
  "properties": {
    "addr:full":"17, Rue Cartier Bresson, 93500 Pantin Ile de France",
    "addr:housenumber":"17",
    "addr:postcode":"93500;ile",
    "addr:street":"Rue Cartier Bresson",
    "iso:country":"FR",
    "sg:address":"17, Rue Cartier Bresson, 93500 Pantin",
    "sg:orig_category":"Non-Classified Establishments",
    "sg:phone":"+33 1 48 44 87 99",
    "sg:province":"Ile de France",
    "wof:name":"F.a.c. S.a. - France Automatisme Cr\u00e9ations",
    "wof:placetype":"venue"
},
  "geometry": {"coordinates":[2.395707,48.903419],"type":"Point"}
}