{
  "type": "Feature",
  "properties": {
    "iso:country":"FR",
    "sg:address":"6 Chem Des Alamans 39270 Orgelet",
    "sg:classifiers":[
        {
            "category":"Manufacturing",
            "subcategory":"Rubber & Plastics",
            "type":"Manufacturing & Wholesale Goods"
        }
    ],
    "sg:phone":"+33 3 84 87 18 00",
    "sg:province":"Franche Comt\u00e9",
    "wof:name":"Verchere Plastiques Industriels Sa",
    "wof:placetype":"venue"
},
  "geometry": {"coordinates":[5.600665,46.529617],"type":"Point"}
}