{
  "type": "Feature",
  "properties": {
    "addr:full":"Zi Chaudannes 73410 Albens Rhone-Alpes 73410",
    "addr:postcode":"73410;73410",
    "iso:country":"FR",
    "sg:address":"Zi Chaudannes 73410 Albens",
    "sg:classifiers":[
        {
            "category":"Manufacturing",
            "subcategory":"Wood Products",
            "type":"Manufacturing & Wholesale Goods"
        }
    ],
    "sg:phone":"+33 4 79 54 18 57",
    "sg:postcode":"73410",
    "sg:province":"Rhone-Alpes",
    "sg:tags":[
        "professional",
        "furniture"
    ],
    "wof:name":"Duwic",
    "wof:placetype":"venue"
},
  "geometry": {"coordinates":[5.94599,45.788052],"type":"Point"}
}