{
  "type": "Feature",
  "properties": {
    "addr:full":"72 Rue De Chennebrun 61300 L'Aigle Chandai Basse Normandie 61300",
    "addr:housenumber":"72",
    "addr:postcode":"61300;61300",
    "addr:street":"Rue De Chennebrun",
    "iso:country":"FR",
    "sg:address":"72 Rue De Chennebrun 61300 L'Aigle",
    "sg:city":"Chandai",
    "sg:orig_category":"Construction and Public Works Finished goods - metallic Mechanical Engineering - machines Metallurgy",
    "sg:phone":"+33 2 33 84 99 33",
    "sg:postcode":"61300",
    "sg:province":"Basse Normandie",
    "wof:name":"Boulay Sa",
    "wof:placetype":"venue"
},
  "geometry": {"coordinates":[0.642973,48.754955],"type":"Point"}
}