{
  "type": "Feature",
  "properties": {
    "addr:full":"7, Rue Ren\u00e9 Cassin - ZI de la Bonde, 91742 Massy C\u00e9dex Bourgogne",
    "addr:housenumber":"7",
    "addr:postcode":"91742",
    "addr:street":"Rue Rene\u0301 Cassin Zi De La Bonde",
    "iso:country":"FR",
    "sg:address":"7, Rue Ren\u00e9 Cassin - ZI de la Bonde, 91742 Massy C\u00e9dex",
    "sg:orig_category":"Non-Classified Establishments",
    "sg:phone":"+33 1 69 20 86 16",
    "sg:province":"Bourgogne",
    "wof:name":"Soci\u00e9t\u00e9 Boucher S.a.r.l.",
    "wof:placetype":"venue"
},
  "geometry": {"coordinates":[2.27287,48.730301],"type":"Point"}
}