{
  "type": "Feature",
  "properties": {
    "addr:full":"B.P. 1, 62730 Les Attaques^^Rte Nationale, 62730 Les Attaques Nord Pas-de-Calais",
    "addr:housenumber":"1",
    "addr:postcode":"62730;62730",
    "addr:street":"B.P.;Nationale;Attaques Nord",
    "iso:country":"FR",
    "sg:address":"B.P. 1, 62730 Les Attaques^^Rte Nationale, 62730 Les Attaques",
    "sg:orig_category":"Non-Classified Establishments",
    "sg:phone":"+33 3 21 82 27 87",
    "sg:province":"Nord Pas-de-Calais",
    "wof:name":"Honor\u00e9 S.a.",
    "wof:placetype":"venue"
},
  "geometry": {"coordinates":[1.956175,50.949181],"type":"Point"}
}