{
  "type": "Feature",
  "properties": {
    "iso:country":"FR",
    "sg:address":"Rue de Metz",
    "sg:city":"Carling",
    "sg:orig_category":"Unclassifiable Establishments",
    "sg:phone":"+33 3 87 83 29 35",
    "sg:postcode":"57800",
    "sg:province":"Lorraine",
    "wof:name":"H.b.l. E.p.i.c. - S.a. - Houill\u00e8res De Bassin De Lorraine",
    "wof:placetype":"venue"
},
  "geometry": {"coordinates":[-116.106003,40.716801],"type":"Point"}
}