{
  "type": "Feature",
  "properties": {
    "addr:full":"Pl Des Paraiges Centre St Jacques 57000 Metz Lorraine 57000",
    "addr:postcode":"57000;57000",
    "addr:street":"Pl;St Jacques",
    "iso:country":"FR",
    "sg:address":"Pl Des Paraiges Centre St Jacques 57000 Metz",
    "sg:classifiers":[
        {
            "category":"Travel",
            "subcategory":"Hotels & Motels",
            "type":"Entertainment"
        }
    ],
    "sg:phone":"+33 3 87 37 38 39",
    "sg:postcode":"57000",
    "sg:province":"Lorraine",
    "sg:tags":[
        "hotels",
        "business",
        "restaurant"
    ],
    "wof:name":"Dgr Normandie Nord Et Est Novotel Metz Centre",
    "wof:placetype":"venue"
},
  "geometry": {"coordinates":[6.183995,49.07645],"type":"Point"}
}