{
  "type": "Feature",
  "properties": {
    "iso:country":"FR",
    "sg:address":"5, Bd Marcel Pourtout, 92563 Rueil Malmaison C\u00e9dex",
    "sg:orig_category":"Non-Classified Establishments",
    "sg:phone":"+33 1 41 39 26 26",
    "sg:province":"\u00cele-de-France",
    "wof:name":"Grundig France S.a.",
    "wof:placetype":"venue"
},
  "geometry": {"coordinates":[2.165899,48.875179],"type":"Point"}
}