{
  "type": "Feature",
  "properties": {
    "iso:country":"FR",
    "sg:address":"Rte de Saint Galmier - ZI de Montl\u00e8gre",
    "sg:city":"Chazelles sur Lyon",
    "sg:orig_category":"Non-Classified Establishments",
    "sg:phone":"+33 4 77 54 23 49",
    "sg:postcode":"42140",
    "sg:province":"Rhone-Alpes",
    "wof:name":"Bruy\u00e8re S.a.r.l.",
    "wof:placetype":"venue"
},
  "geometry": {"coordinates":[4.437882,45.547447],"type":"Point"}
}