{
  "type": "Feature",
  "properties": {
    "addr:full":"13, Rue de la Bouchardi\u00e8re - ZA, 41100 Naveil Naveil Centre 41100",
    "addr:housenumber":"13;naveil",
    "addr:postcode":"41100;41100",
    "addr:street":"Rue De La Bouchardie\u0300Re Za",
    "iso:country":"FR",
    "sg:address":"13, Rue de la Bouchardi\u00e8re - ZA, 41100 Naveil",
    "sg:city":"Naveil",
    "sg:orig_category":"Unclassifiable Establishments",
    "sg:phone":"+33 2 54 80 02 75",
    "sg:postcode":"41100",
    "sg:province":"Centre",
    "wof:name":"Naveil Inox S.a.r.l.",
    "wof:placetype":"venue"
},
  "geometry": {"coordinates":[1.17829,47.712414],"type":"Point"}
}