{
  "type": "Feature",
  "properties": {
    "iso:country":"FR",
    "sg:address":"B.P. 104, 38243 Meylan C\u00e9dex^^36, Chemin du Vieux Ch\u00eane, 38240 Meylan",
    "sg:orig_category":"Non-Classified Establishments",
    "sg:phone":"+33 4 76 41 46 00",
    "sg:province":"Rhone-Alpes",
    "wof:name":"S\u00e9ma Group S.a.",
    "wof:placetype":"venue"
},
  "geometry": {"coordinates":[5.77846,45.209316],"type":"Point"}
}