{
  "type": "Feature",
  "properties": {
    "iso:country":"FR",
    "sg:address":"23 pl Emile Loubet; Mont\u00e9limar; 26200",
    "sg:classifiers":[
        {
            "category":"Banks & Credit Unions",
            "subcategory":"Bank",
            "type":"Services"
        }
    ],
    "sg:phone":"+33 3375012577",
    "sg:postcode":"26200",
    "sg:province":"Rhone-Alpes",
    "wof:name":"Soci\u00e9t\u00e9 Marseillaise De Cr\u00e9dit",
    "wof:placetype":"venue"
},
  "geometry": {"coordinates":[4.749507,44.557232],"type":"Point"}
}