{
  "type": "Feature",
  "properties": {
    "addr:full":"19, Rue Baudin, 33110 Le Bouscat Le Bouscat Aquitaine 33110",
    "addr:housenumber":"19",
    "addr:postcode":"33110;33110",
    "addr:street":"Rue Baudin",
    "iso:country":"FR",
    "sg:address":"19, Rue Baudin, 33110 Le Bouscat",
    "sg:city":"Le Bouscat",
    "sg:orig_category":"Unclassifiable Establishments",
    "sg:phone":"+33 5 56 29 17 43",
    "sg:postcode":"33110",
    "sg:province":"Aquitaine",
    "wof:name":"Laplage Fluid'industries S.a.r.l.",
    "wof:placetype":"venue"
},
  "geometry": {"coordinates":[-0.586913,44.862347],"type":"Point"}
}