{
  "type": "Feature",
  "properties": {
    "iso:country":"FR",
    "sg:address":"27, Rte deVitry en Perthois, 51300 Vitry le Fran\u00e7ois",
    "sg:orig_category":"Non-Classified Establishments",
    "sg:phone":"+33 3 26 74 62 59",
    "sg:postcode":"51300",
    "sg:province":"Champagne",
    "wof:name":"Debourdeau Bigmat S.a.",
    "wof:placetype":"venue"
},
  "geometry": {"coordinates":[4.591711,48.728809],"type":"Point"}
}