{
  "type": "Feature",
  "properties": {
    "addr:full":"Le Fief Du Bois De La Fen\u00eatre 17600 Medis Poitou-Charentes 17600",
    "addr:postcode":"17600;17600",
    "addr:street":"Bois De La Fene\u0302Tre;Medis",
    "iso:country":"FR",
    "sg:address":"Le Fief Du Bois De La Fen\u00eatre 17600 Medis",
    "sg:classifiers":[
        {
            "category":"Utilities",
            "subcategory":"Electric",
            "type":"Services"
        }
    ],
    "sg:phone":"+33 5 46 05 24 46",
    "sg:postcode":"17600",
    "sg:province":"Poitou-Charentes",
    "sg:tags":[
        "electricity",
        "electronic",
        "electrical",
        "equipment"
    ],
    "wof:name":"Cee Sarl",
    "wof:placetype":"venue"
},
  "geometry": {"coordinates":[-0.936514,45.622566],"type":"Point"}
}