{
  "type": "Feature",
  "properties": {
    "addr:full":"Rue Gustave Eiffel Zi 24102 Bergerac Berg Alsace 67320",
    "addr:postcode":"24102;67320",
    "addr:street":"Rue Gustave Eiffel Zi;Berg",
    "iso:country":"FR",
    "sg:address":"Rue Gustave Eiffel Zi 24102 Bergerac",
    "sg:city":"Berg",
    "sg:classifiers":[
        {
            "category":"Manufacturing",
            "subcategory":"Printing",
            "type":"Manufacturing & Wholesale Goods"
        }
    ],
    "sg:phone":"+33 5 53 22 22 40",
    "sg:postcode":"67320",
    "sg:province":"Alsace",
    "sg:tags":[
        "publishing"
    ],
    "wof:name":"Impression En Perigord Sa",
    "wof:placetype":"venue"
},
  "geometry": {"coordinates":[0.4838,44.853226],"type":"Point"}
}