{
  "type": "Feature",
  "properties": {
    "iso:country":"FR",
    "sg:address":"10 Bd Amp\u00e8re 13014 Marseille",
    "sg:classifiers":[
        {
            "category":"Manufacturing",
            "subcategory":"Chemicals & Compounds",
            "type":"Manufacturing & Wholesale Goods"
        }
    ],
    "sg:phone":"+33 4 91 98 90 35",
    "sg:province":"Poitou-Charentes",
    "sg:tags":[
        "pharmaceutical",
        "energy",
        "chemistry",
        "-",
        "by-product"
    ],
    "wof:name":"Worex Snc",
    "wof:placetype":"venue"
},
  "geometry": {"coordinates":[5.373974,43.337543],"type":"Point"}
}