{
  "type": "Feature",
  "properties": {
    "addr:full":"La Bourdonnais 35520 La Mezi\u00e8re La M\u00e9zi\u00e8re Bretagne 35520",
    "addr:postcode":"35520;35520",
    "addr:street":"La Me\u0301Zie\u0300Re Bretagne",
    "iso:country":"FR",
    "sg:address":"La Bourdonnais 35520 La Mezi\u00e8re",
    "sg:city":"La M\u00e9zi\u00e8re",
    "sg:orig_category":"Unclassifiable Establishments",
    "sg:phone":"+33 2 99 13 12 25",
    "sg:postcode":"35520",
    "sg:province":"Bretagne",
    "wof:name":"Mariault S.a.",
    "wof:placetype":"venue"
},
  "geometry": {"coordinates":[-1.734799,48.192486],"type":"Point"}
}