{
  "type": "Feature",
  "properties": {
    "addr:full":"All\u00e9e de Chantereine Mantes la Ville \u00cele-de-France 78711",
    "addr:postcode":"78711",
    "addr:street":"Alle\u0301E De Chantereine Mantes La Ville",
    "iso:country":"FR",
    "sg:address":"All\u00e9e de Chantereine",
    "sg:city":"Mantes la Ville",
    "sg:orig_category":"Unclassifiable Establishments",
    "sg:phone":"+33 1 30 92 80 80",
    "sg:postcode":"78711",
    "sg:province":"\u00cele-de-France",
    "wof:name":"Dupont Performance Coatings France S.a.",
    "wof:placetype":"venue"
},
  "geometry": {"coordinates":[1.722777,48.979008],"type":"Point"}
}