{
  "type": "Feature",
  "properties": {
    "addr:full":"B.P. 45, 56204 Cournon C\u00e9dex^^ZA de Lestun, 56200 Cournon Cournon Bretagne 56200",
    "addr:postcode":"56204;56200;56200",
    "addr:street":"B.P. 45;Cournon",
    "iso:country":"FR",
    "sg:address":"B.P. 45, 56204 Cournon C\u00e9dex^^ZA de Lestun, 56200 Cournon",
    "sg:city":"Cournon",
    "sg:orig_category":"Non-Classified Establishments",
    "sg:phone":"+33 2 99 08 00 88",
    "sg:postcode":"56200",
    "sg:province":"Bretagne",
    "wof:name":"R.o.g. S.a. - Roto Ouest Graphic",
    "wof:placetype":"venue"
},
  "geometry": {"coordinates":[-2.132382,47.727661],"type":"Point"}
}