{
  "type": "Feature",
  "properties": {
    "iso:country":"FR",
    "sg:address":"15 rue Commerce; Neuill\u00e9 Pont Pierre; 37360",
    "sg:city":"Beaumont-la-Ronce",
    "sg:classifiers":[
        {
            "category":"Banks & Credit Unions",
            "subcategory":"Bank",
            "type":"Services"
        }
    ],
    "sg:phone":"+33 2 47 24 31 58",
    "sg:postcode":"37360",
    "sg:province":"Centre",
    "wof:name":"Cr\u00e9dit Agricole Mutuel",
    "wof:placetype":"venue"
},
  "geometry": {"coordinates":[0.54609,47.547409],"type":"Point"}
}