{
  "type": "Feature",
  "properties": {
    "iso:country":"FR",
    "sg:address":"9, Chemin du Plateau, 69570 Dardilly",
    "sg:orig_category":"Non-Classified Establishments",
    "sg:phone":"+33 4 78 35 73 44",
    "sg:postcode":"69570",
    "sg:province":"Rhone-Alpes",
    "wof:name":"Vachon S.a.",
    "wof:placetype":"venue"
},
  "geometry": {"coordinates":[4.76802,45.80072],"type":"Point"}
}