{
  "type": "Feature",
  "properties": {
    "addr:full":"1, Rue de Paris - Immeuble Atalis 1, 35517 Cesson S\u00e9vign\u00e9 Ile de France",
    "addr:housenumber":"1;1",
    "addr:postcode":"35517;ile",
    "addr:street":"Rue De Paris;Atalis",
    "iso:country":"FR",
    "sg:address":"1, Rue de Paris - Immeuble Atalis 1, 35517 Cesson S\u00e9vign\u00e9",
    "sg:orig_category":"Non-Classified Establishments",
    "sg:phone":"+33 2 99 83 58 00",
    "sg:province":"Ile de France",
    "wof:name":"C.g.e. Distribution",
    "wof:placetype":"venue"
},
  "geometry": {"coordinates":[-1.604404,48.117016],"type":"Point"}
}