{
  "type": "Feature",
  "properties": {
    "addr:full":"1 rue de Maupas 69380 LES CHERES Rhone-Alpes 69380",
    "addr:housenumber":"1",
    "addr:postcode":"69380;69380",
    "addr:street":"Rue De Maupas;Rhone-Alpes",
    "iso:country":"FR",
    "sg:address":"1 rue de Maupas 69380 LES CHERES",
    "sg:classifiers":[
        {
            "category":"Government",
            "subcategory":"City Hall",
            "type":"Public Place"
        }
    ],
    "sg:phone":"+33 4 78 47 33 55",
    "sg:postcode":"69380",
    "sg:province":"Rhone-Alpes",
    "sg:tags":[
        "lighting"
    ],
    "wof:name":"Sogexi Sa",
    "wof:placetype":"venue"
},
  "geometry": {"coordinates":[4.739655,45.891323],"type":"Point"}
}