{
  "type": "Feature",
  "properties": {
    "addr:full":"65, ZI Eygreteau, 33230 Coutras Coutras Aquitaine 33230",
    "addr:housenumber":"65",
    "addr:postcode":"33230;33230",
    "addr:street":"Zi Eygreteau",
    "iso:country":"FR",
    "sg:address":"65, ZI Eygreteau, 33230 Coutras",
    "sg:city":"Coutras",
    "sg:orig_category":"Unclassifiable Establishments",
    "sg:phone":"+33 5 57 49 18 00",
    "sg:postcode":"33230",
    "sg:province":"Aquitaine",
    "wof:name":"D.m.o. S.a.r.l. - Diffusion De Mat\u00e9riel Outillage",
    "wof:placetype":"venue"
},
  "geometry": {"coordinates":[-0.051856,45.004955],"type":"Point"}
}