{
  "type": "Feature",
  "properties": {
    "addr:full":"134 Grande Rue 76200 Dieppe Haute Normandie 76200",
    "addr:housenumber":"134",
    "addr:postcode":"76200;76200",
    "addr:street":"Grande Rue",
    "iso:country":"FR",
    "sg:address":"134 Grande Rue 76200 Dieppe",
    "sg:classifiers":[
        {
            "category":"Bakery",
            "type":"Food & Drink"
        }
    ],
    "sg:phone":"+33 2 35 84 13 87",
    "sg:postcode":"76200",
    "sg:province":"Haute Normandie",
    "sg:tags":[
        "cake",
        "product",
        "related",
        "bread"
    ],
    "wof:name":"Le Relais Henri Iv",
    "wof:placetype":"venue"
},
  "geometry": {"coordinates":[1.076339,49.926159],"type":"Point"}
}