{
  "type": "Feature",
  "properties": {
    "addr:full":"14 Pl Amp\u00e8re 69250 Neuville Sur Sa\u00f4ne Rhone-Alpes 69250",
    "addr:housenumber":"14",
    "addr:postcode":"69250;69250",
    "addr:street":"Pl Ampe\u0300Re",
    "iso:country":"FR",
    "sg:address":"14 Pl Amp\u00e8re 69250 Neuville Sur Sa\u00f4ne",
    "sg:classifiers":[
        {
            "category":"Manufacturing",
            "subcategory":"Jewelry",
            "type":"Manufacturing & Wholesale Goods"
        }
    ],
    "sg:phone":"+33 4 78 91 70 52",
    "sg:postcode":"69250",
    "sg:province":"Rhone-Alpes",
    "sg:tags":[
        "product",
        "miscellaneous",
        "jewellery"
    ],
    "wof:name":"Bijouterie Guglielmetto Thierry Sarl",
    "wof:placetype":"venue"
},
  "geometry": {"coordinates":[4.83878,45.876415],"type":"Point"}
}