{
  "type": "Feature",
  "properties": {
    "addr:full":"42, Fbg de Montb\u00e9liard, 90000 Belfort Franche Comt\u00e9",
    "addr:housenumber":"42",
    "addr:postcode":"90000",
    "addr:street":"Fbg De Montbe\u0301Liard;Franche Comte\u0301",
    "iso:country":"FR",
    "sg:address":"42, Fbg de Montb\u00e9liard, 90000 Belfort",
    "sg:orig_category":"Unclassifiable Establishments",
    "sg:phone":"+33 3 84 58 47 00",
    "sg:province":"Franche Comt\u00e9",
    "wof:name":"Maillot Jean-pierre S.a.r.l.",
    "wof:placetype":"venue"
},
  "geometry": {"coordinates":[6.857179,47.633636],"type":"Point"}
}