{
  "type": "Feature",
  "properties": {
    "addr:full":"16bis, Rte Nationale, 62580 Vimy Nord Pas-de-Calais 62580",
    "addr:housenumber":"16bis",
    "addr:postcode":"62580;62580",
    "addr:street":"Rte Nationale",
    "iso:country":"FR",
    "sg:address":"16bis, Rte Nationale, 62580 Vimy",
    "sg:orig_category":"Non-Classified Establishments",
    "sg:phone":"+33 3 21 73 84 71",
    "sg:postcode":"62580",
    "sg:province":"Nord Pas-de-Calais",
    "wof:name":"Direct D\u00e9cor S.a.r.l.",
    "wof:placetype":"venue"
},
  "geometry": {"coordinates":[2.800431,50.369141],"type":"Point"}
}