{
  "type": "Feature",
  "properties": {
    "addr:full":"20, Rue Jacques Dulud, 92521 Neuilly sur Seine C\u00e9dex \u00cele-de-France",
    "addr:housenumber":"20",
    "addr:postcode":"92521",
    "addr:street":"Rue Jacques Dulud",
    "iso:country":"FR",
    "sg:address":"20, Rue Jacques Dulud, 92521 Neuilly sur Seine C\u00e9dex",
    "sg:orig_category":"Non-Classified Establishments",
    "sg:phone":"+33 1 41 43 70 10",
    "sg:province":"\u00cele-de-France",
    "wof:name":"Vid\u00e9oth\u00e8que S.a.",
    "wof:placetype":"venue"
},
  "geometry": {"coordinates":[2.270687,48.880508],"type":"Point"}
}