{
  "type": "Feature",
  "properties": {
    "iso:country":"FR",
    "sg:address":"44, Av. Chamoine Cartellier, 69230 Saint Genis Laval",
    "sg:orig_category":"Non-Classified Establishments",
    "sg:phone":"+33 4 78 56 35 32",
    "sg:province":"Rhone-Alpes",
    "wof:name":"I.t.l. S.a. - Intallation Thermique Lyonnaise",
    "wof:placetype":"venue"
},
  "geometry": {"coordinates":[4.78383,45.67572],"type":"Point"}
}