{
  "type": "Feature",
  "properties": {
    "addr:full":"13 Tournus Bourgogne 71700",
    "addr:housenumber":"13",
    "addr:postcode":"71700",
    "addr:street":"Bourgogne",
    "iso:country":"FR",
    "sg:address":"13",
    "sg:city":"Tournus",
    "sg:classifiers":[
        {
            "category":"Banks & Credit Unions",
            "subcategory":"Bank",
            "type":"Services"
        }
    ],
    "sg:phone":"+33 3385510394",
    "sg:postcode":"71700",
    "sg:province":"Bourgogne",
    "wof:name":"Soci\u00e9t\u00e9 G\u00e9n\u00e9rale",
    "wof:placetype":"venue"
},
  "geometry": {"coordinates":[4.912734,46.562267],"type":"Point"}
}