{
  "type": "Feature",
  "properties": {
    "addr:full":"348 rue des Reys 74300 Magland Rhone-Alpes 74300",
    "addr:housenumber":"348",
    "addr:postcode":"74300;74300",
    "addr:street":"Rue Des Reys",
    "iso:country":"FR",
    "sg:address":"348 rue des Reys 74300 Magland",
    "sg:classifiers":[
        {
            "category":"Manufacturing",
            "subcategory":"Motor Vehicles & Parts",
            "type":"Manufacturing & Wholesale Goods"
        }
    ],
    "sg:phone":"+33 4 50 34 71 41",
    "sg:postcode":"74300",
    "sg:province":"Rhone-Alpes",
    "sg:tags":[
        "high-precision",
        "hard",
        "turning"
    ],
    "wof:name":"Perret Georges Et Fils Sarl",
    "wof:placetype":"venue"
},
  "geometry": {"coordinates":[6.607905,46.006996],"type":"Point"}
}