{
  "type": "Feature",
  "properties": {
    "addr:full":"Maltaverne 58150 Tracy Sur Loire Garchy Bourgogne 58150",
    "addr:postcode":"58150;58150",
    "addr:street":"Maltaverne;Bourgogne",
    "iso:country":"FR",
    "sg:address":"Maltaverne 58150 Tracy Sur Loire",
    "sg:city":"Garchy",
    "sg:classifiers":[
        {
            "category":"Food & Beverages",
            "subcategory":"Dairy",
            "type":"Retail Goods"
        }
    ],
    "sg:phone":"+33 3 86 26 11 69",
    "sg:postcode":"58150",
    "sg:province":"Bourgogne",
    "sg:tags":[
        "product",
        "related"
    ],
    "wof:name":"Fromagerie Pasdeloup",
    "wof:placetype":"venue"
},
  "geometry": {"coordinates":[2.92478,47.336651],"type":"Point"}
}