{
  "type": "Feature",
  "properties": {
    "iso:country":"FR",
    "sg:address":"295, Av. Denfert Rochereau, 17000 La Rochelle",
    "sg:orig_category":"Non-Classified Establishments",
    "sg:phone":"+33 5 46 67 09 90",
    "sg:postcode":"17000",
    "sg:province":"Poitou-Charentes",
    "wof:name":"Alter France S.a.r.l.",
    "wof:placetype":"venue"
},
  "geometry": {"coordinates":[-1.213053,46.163422],"type":"Point"}
}