{
  "type": "Feature",
  "properties": {
    "addr:full":"B.P. 1508, 87020 Limoges C\u00e9dex^^7, Impase Joseph Cugnot, 87280 Limoges Limousin",
    "addr:postcode":"87020;87280",
    "addr:street":"B.P. 1508;Impase Joseph Cugnot",
    "iso:country":"FR",
    "sg:address":"B.P. 1508, 87020 Limoges C\u00e9dex^^7, Impase Joseph Cugnot, 87280 Limoges",
    "sg:orig_category":"Non-Classified Establishments",
    "sg:phone":"+33 5 55 38 48 62",
    "sg:province":"Limousin",
    "wof:name":"T.t.a. Air Fret S.a. - Tous Transports A\u00e9riens",
    "wof:placetype":"venue"
},
  "geometry": {"coordinates":[1.299435,45.914837],"type":"Point"}
}