{
  "type": "Feature",
  "properties": {
    "iso:country":"FR",
    "sg:address":"Rue Alfred de Musset - ZI de Thouans",
    "sg:city":"Talence",
    "sg:orig_category":"Unclassifiable Establishments",
    "sg:phone":"+33 5 56 80 38 38",
    "sg:postcode":"33400",
    "sg:province":"Aquitaine",
    "wof:name":"Imprimerie Boucherie Et Fils S.a.",
    "wof:placetype":"venue"
},
  "geometry": {"coordinates":[-0.592884,44.803986],"type":"Point"}
}