{
  "type": "Feature",
  "properties": {
    "addr:full":"27 quai de la Gironde 76600 Le Havre Haute Normandie",
    "addr:housenumber":"27",
    "addr:postcode":"76600",
    "addr:street":"Quai De La Gironde",
    "iso:country":"FR",
    "sg:address":"27 quai de la Gironde 76600 Le Havre",
    "sg:classifiers":[
        {
            "category":"Shopping",
            "subcategory":"Stationery & Office Supplies",
            "type":"Retail Goods"
        }
    ],
    "sg:phone":"+33 2 35 25 09 21",
    "sg:province":"Haute Normandie",
    "sg:tags":[
        "furniture"
    ],
    "wof:name":"Anciens Etablissements Jean Bisson Sa",
    "wof:placetype":"venue"
},
  "geometry": {"coordinates":[0.14251,49.482491],"type":"Point"}
}