{
  "type": "Feature",
  "properties": {
    "addr:full":"124, Bd de Verdun, 92400 Courbevoie Ile de France 92400",
    "addr:housenumber":"124",
    "addr:postcode":"92400;92400",
    "addr:street":"Bd De Verdun",
    "iso:country":"FR",
    "sg:address":"124, Bd de Verdun, 92400 Courbevoie",
    "sg:orig_category":"Non-Classified Establishments",
    "sg:phone":"+33 1 43 34 74 00",
    "sg:postcode":"92400",
    "sg:province":"Ile de France",
    "wof:name":"Air Industrie Syst\u00e8mes S.a.",
    "wof:placetype":"venue"
},
  "geometry": {"coordinates":[2.257615,48.903915],"type":"Point"}
}