{
  "type": "Feature",
  "properties": {
    "addr:full":"11-13 Cs Valmy 92800 Puteaux Ile de France 92800",
    "addr:postcode":"11-13 cs;92800;92800",
    "iso:country":"FR",
    "sg:address":"11-13 Cs Valmy 92800 Puteaux",
    "sg:classifiers":[
        {
            "category":"Manufacturing",
            "subcategory":"Metals",
            "type":"Manufacturing & Wholesale Goods"
        }
    ],
    "sg:phone":"+33 1 41 25 55 88",
    "sg:postcode":"92800",
    "sg:province":"Ile de France",
    "sg:tags":[
        "metallurgy",
        "metalworking",
        "processing"
    ],
    "wof:name":"Imphy Service",
    "wof:placetype":"venue"
},
  "geometry": {"coordinates":[2.23944,48.884205],"type":"Point"}
}