{
  "type": "Feature",
  "properties": {
    "iso:country":"FR",
    "sg:address":"Zac Grenoble Air Parc 38590 St Etienne De St Geoirs",
    "sg:classifiers":[
        {
            "category":"Manufacturing",
            "subcategory":"Leather Goods",
            "type":"Manufacturing & Wholesale Goods"
        }
    ],
    "sg:phone":"+33 4 76 93 46 00",
    "sg:postcode":"38590",
    "sg:province":"Rhone-Alpes",
    "sg:tags":[
        "shoe"
    ],
    "wof:name":"Sidas Production",
    "wof:placetype":"venue"
},
  "geometry": {"coordinates":[5.345985,45.338837],"type":"Point"}
}