{
  "type": "Feature",
  "properties": {
    "addr:full":"26, Rue des Pionniers, 38250 Villard de Lans Rhone-Alpes",
    "addr:housenumber":"26",
    "addr:postcode":"38250",
    "addr:street":"Rue Des Pionniers",
    "iso:country":"FR",
    "sg:address":"26, Rue des Pionniers, 38250 Villard de Lans",
    "sg:orig_category":"Unclassifiable Establishments",
    "sg:phone":"+33 4 76 47 76 19",
    "sg:province":"Rhone-Alpes",
    "wof:name":"Saphor Conseil S.a.r.l.",
    "wof:placetype":"venue"
},
  "geometry": {"coordinates":[5.527228,45.03178],"type":"Point"}
}