{
  "type": "Feature",
  "properties": {
    "iso:country":"FR",
    "sg:address":"Ld Loiseau 33126 Fronsac",
    "sg:city":"Fronsac",
    "sg:orig_category":"Glass Glass and Building Materials Professional goods Wood and Furniture",
    "sg:phone":"+33 5 57 74 09 83",
    "sg:postcode":"33126",
    "sg:province":"Aquitaine",
    "wof:name":"Ste De Distribution De Couleurs Verres Et Miroiterie",
    "wof:placetype":"venue"
},
  "geometry": {"coordinates":[-0.246016,44.920116],"type":"Point"}
}