{
  "type": "Feature",
  "properties": {
    "addr:full":"83, Rue Jouffroy d'Abbans, 75017 Paris Ile de France",
    "addr:housenumber":"83",
    "addr:postcode":"75017",
    "addr:street":"Rue Jouffroy D'Abbans",
    "iso:country":"FR",
    "sg:address":"83, Rue Jouffroy d'Abbans, 75017 Paris",
    "sg:orig_category":"Unclassifiable Establishments",
    "sg:phone":"+33 1 47 66 23 66",
    "sg:province":"Ile de France",
    "wof:name":"Lettering S.a.r.l.",
    "wof:placetype":"venue"
},
  "geometry": {"coordinates":[2.308338,48.885452],"type":"Point"}
}