{
  "type": "Feature",
  "properties": {
    "iso:country":"FR",
    "sg:address":"15, Bd des Ch\u00eanes - Parc Ariane, 78280 Guyancourt",
    "sg:orig_category":"Non-Classified Establishments",
    "sg:phone":"+33 1 39 30 46 00",
    "sg:province":"Ile de France",
    "wof:name":"Silicom Paris S.a.",
    "wof:placetype":"venue"
},
  "geometry": {"coordinates":[2.051305,48.790192],"type":"Point"}
}