{
  "type": "Feature",
  "properties": {
    "addr:full":"1, Rue des Vergers, 69760 Limonest Rhone-Alpes",
    "addr:housenumber":"1",
    "addr:postcode":"69760",
    "addr:street":"Rue Des Vergers",
    "iso:country":"FR",
    "sg:address":"1, Rue des Vergers, 69760 Limonest",
    "sg:orig_category":"Unclassifiable Establishments",
    "sg:phone":"+33 4 72 52 08 08",
    "sg:province":"Rhone-Alpes",
    "wof:name":"B.b.r. Automation S.a.s.",
    "wof:placetype":"venue"
},
  "geometry": {"coordinates":[4.77387,45.807426],"type":"Point"}
}