{
  "type": "Feature",
  "properties": {
    "addr:full":"19 route du Petit Rhin 67000 Strasbourg Strasbourg Alsace 67000",
    "addr:housenumber":"19",
    "addr:postcode":"67000;67000",
    "addr:street":"Route Du Petit Rhin",
    "iso:country":"FR",
    "sg:address":"19 route du Petit Rhin 67000 Strasbourg",
    "sg:city":"Strasbourg",
    "sg:classifiers":[
        {
            "category":"Autos & Motor Vehicles",
            "subcategory":"Auto Supplies",
            "type":"Retail Goods"
        }
    ],
    "sg:phone":"+33 3 88 61 18 67",
    "sg:postcode":"67000",
    "sg:province":"Alsace",
    "sg:tags":[
        "automobile",
        "accessory"
    ],
    "wof:name":"Accessoires France Strasbourg Sa",
    "wof:placetype":"venue"
},
  "geometry": {"coordinates":[7.7854,48.57193],"type":"Point"}
}