{
  "type": "Feature",
  "properties": {
    "addr:full":"90 Faubourg Cassel 59380 Socx Nord Pas-de-Calais 59380",
    "addr:housenumber":"90",
    "addr:postcode":"59380;59380",
    "addr:street":"Faubourg Cassel",
    "iso:country":"FR",
    "sg:address":"90 Faubourg Cassel 59380 Socx",
    "sg:classifiers":[
        {
            "category":"Farming",
            "subcategory":"Livestock Farm",
            "type":"Manufacturing & Wholesale Goods"
        }
    ],
    "sg:phone":"+33 3 28 68 60 48",
    "sg:postcode":"59380",
    "sg:province":"Nord Pas-de-Calais",
    "sg:tags":[
        "breeding",
        "agriculture",
        "animal"
    ],
    "wof:name":"Ste Exploit Ets R Barbet",
    "wof:placetype":"venue"
},
  "geometry": {"coordinates":[2.43303,50.962521],"type":"Point"}
}