{
  "type": "Feature",
  "properties": {
    "addr:full":"1 bis, Rue Fleury Richarme, 42100 Saint Etienne Rhone-Alpes 42100",
    "addr:housenumber":"1 bis",
    "addr:postcode":"42100;42100",
    "addr:street":"Rue Fleury Richarme",
    "iso:country":"FR",
    "sg:address":"1 bis, Rue Fleury Richarme, 42100 Saint Etienne",
    "sg:orig_category":"Unclassifiable Establishments",
    "sg:phone":"+33 4 77 25 88 32",
    "sg:postcode":"42100",
    "sg:province":"Rhone-Alpes",
    "wof:name":"M\u00e9dia Express 42 S.a.r.l.",
    "wof:placetype":"venue"
},
  "geometry": {"coordinates":[4.414937,45.440189],"type":"Point"}
}