{
  "type": "Feature",
  "properties": {
    "iso:country":"FR",
    "sg:address":"679, Chemin de l'Estang, 82130 Villemade",
    "sg:orig_category":"Unclassifiable Establishments",
    "sg:phone":"+33 5 63 66 65 09",
    "sg:province":"Midi Pyr\u00e9n\u00e9es",
    "wof:name":"L.p.s. Aff\u00fbtage S.a.r.l. - Lame Pliage Sciage",
    "wof:placetype":"venue"
},
  "geometry": {"coordinates":[1.288615,44.074001],"type":"Point"}
}