{
  "type": "Feature",
  "properties": {
    "iso:country":"FR",
    "sg:address":"Parc D'Exposition Route Nationale 174 50890 Cond\u00e9 Sur Vire",
    "sg:city":"Cond\u00e9-sur-Vire",
    "sg:orig_category":"Games and entertainment Miscellaneous Products Motor-cars Vehicles and Transport Equipment",
    "sg:phone":"+33 2 33 56 50 49",
    "sg:postcode":"50890",
    "sg:province":"Basse Normandie",
    "wof:name":"Leneveu Sa",
    "wof:placetype":"venue"
},
  "geometry": {"coordinates":[-1.03805,49.051411],"type":"Point"}
}