{
  "type": "Feature",
  "properties": {
    "addr:full":"B.P. 55, 57155 Marly^^60, Rue des Garennes, 57155 Marly Aquitaine",
    "addr:postcode":"57155;57155",
    "addr:street":"B.P. 55;Rue Des Garennes",
    "iso:country":"FR",
    "sg:address":"B.P. 55, 57155 Marly^^60, Rue des Garennes, 57155 Marly",
    "sg:orig_category":"Non-Classified Establishments",
    "sg:phone":"+33 3 87 66 62 31",
    "sg:province":"Aquitaine",
    "wof:name":"T.e.p. Conseil S.a.",
    "wof:placetype":"venue"
},
  "geometry": {"coordinates":[6.154125,49.060066],"type":"Point"}
}