{
  "type": "Feature",
  "properties": {
    "addr:full":"ZI Crest Rhone-Alpes 26400",
    "addr:postcode":"26400",
    "addr:street":"Zi Crest Rhone-Alpes",
    "iso:country":"FR",
    "sg:address":"ZI",
    "sg:city":"Crest",
    "sg:orig_category":"Non-Classified Establishments",
    "sg:phone":"+33 4 75 25 05 57",
    "sg:postcode":"26400",
    "sg:province":"Rhone-Alpes",
    "wof:name":"Nutrisud Groupe Loire Aliments S.a.",
    "wof:placetype":"venue"
},
  "geometry": {"coordinates":[5.084799,44.623848],"type":"Point"}
}