{
  "type": "Feature",
  "properties": {
    "addr:full":"120, Bd Saint Germain, 75006 Paris Ile de France 75006",
    "addr:housenumber":"120",
    "addr:postcode":"75006;75006",
    "addr:street":"Bd Saint Germain",
    "iso:country":"FR",
    "sg:address":"120, Bd Saint Germain, 75006 Paris",
    "sg:orig_category":"Non-Classified Establishments",
    "sg:phone":"+33 1 40 46 60 00",
    "sg:postcode":"75006",
    "sg:province":"Ile de France",
    "wof:name":"Editions Masson S.a.",
    "wof:placetype":"venue"
},
  "geometry": {"coordinates":[2.339775,48.852348],"type":"Point"}
}