{
  "type": "Feature",
  "properties": {
    "addr:full":"513, Rue Robert Estienne, 60400 Noyon Picardie",
    "addr:housenumber":"513",
    "addr:postcode":"60400",
    "addr:street":"Rue Robert Estienne",
    "iso:country":"FR",
    "sg:address":"513, Rue Robert Estienne, 60400 Noyon",
    "sg:orig_category":"Unclassifiable Establishments",
    "sg:phone":"+33 3 44 44 66 66",
    "sg:province":"Picardie",
    "wof:name":"Bahlsen S.a.",
    "wof:placetype":"venue"
},
  "geometry": {"coordinates":[3.028342,49.57505],"type":"Point"}
}