{
  "type": "Feature",
  "properties": {
    "iso:country":"FR",
    "sg:address":"La Croix Blanche 44260 Malville",
    "sg:classifiers":[
        {
            "category":"Manufacturing",
            "subcategory":"Food",
            "type":"Manufacturing & Wholesale Goods"
        }
    ],
    "sg:phone":"+33 2 40 56 46 46",
    "sg:postcode":"44260",
    "sg:province":"Pays de Loire",
    "sg:tags":[
        "preserve",
        "product",
        "related"
    ],
    "wof:name":"Maro Oceans Sa",
    "wof:placetype":"venue"
},
  "geometry": {"coordinates":[-1.863875,47.356895],"type":"Point"}
}