{
  "type": "Feature",
  "properties": {
    "addr:full":"65, Rue du Ruisseau, 38070 Saint Quentin Fallavier Rhone-Alpes",
    "addr:housenumber":"65",
    "addr:postcode":"38070",
    "addr:street":"Rue Du Ruisseau",
    "iso:country":"FR",
    "sg:address":"65, Rue du Ruisseau, 38070 Saint Quentin Fallavier",
    "sg:orig_category":"Unclassifiable Establishments",
    "sg:phone":"+33 4 74 94 34 44",
    "sg:province":"Rhone-Alpes",
    "wof:name":"B.m.i. S.a.s.",
    "wof:placetype":"venue"
},
  "geometry": {"coordinates":[5.099189,45.641533],"type":"Point"}
}