{
  "type": "Feature",
  "properties": {
    "iso:country":"FR",
    "sg:address":"B.P. 25, 38291 La Verpilli\u00e8re C\u00e9dex^^Rue Victor Duplessis, 38290 La Verpilli\u00e8re",
    "sg:orig_category":"Non-Classified Establishments",
    "sg:phone":"+33 4 74 94 10 37",
    "sg:province":"Rhone-Alpes",
    "wof:name":"Technifer S.a.",
    "wof:placetype":"venue"
},
  "geometry": {"coordinates":[5.147387,45.632999],"type":"Point"}
}