{
  "type": "Feature",
  "properties": {
    "addr:full":"Rte De Biarne 39100 Sampans Franche Comt\u00e9 39100",
    "addr:postcode":"39100;39100",
    "addr:street":"Rte De Biarne;Franche Comte\u0301",
    "iso:country":"FR",
    "sg:address":"Rte De Biarne 39100 Sampans",
    "sg:classifiers":[
        {
            "category":"Wholesale",
            "subcategory":"Machinery & Supplies",
            "type":"Manufacturing & Wholesale Goods"
        }
    ],
    "sg:phone":"+33 3 84 72 42 08",
    "sg:postcode":"39100",
    "sg:province":"Franche Comt\u00e9",
    "sg:tags":[
        "handling",
        "material",
        "-",
        "machine",
        "equipment",
        "engineering",
        "mechanical"
    ],
    "wof:name":"Jurapal Sarl",
    "wof:placetype":"venue"
},
  "geometry": {"coordinates":[5.456946,47.126671],"type":"Point"}
}