{
  "type": "Feature",
  "properties": {
    "addr:full":"Rte d'Aunay Vassy Basse Normandie 14410",
    "addr:postcode":"14410",
    "addr:street":"Rte D'Aunay",
    "iso:country":"FR",
    "sg:address":"Rte d'Aunay",
    "sg:city":"Vassy",
    "sg:orig_category":"Non-Classified Establishments",
    "sg:phone":"+33 2 31 66 33 00",
    "sg:postcode":"14410",
    "sg:province":"Basse Normandie",
    "wof:name":"A.b.l. S.a.",
    "wof:placetype":"venue"
},
  "geometry": {"coordinates":[-0.677546,48.853855],"type":"Point"}
}