{
  "type": "Feature",
  "properties": {
    "iso:country":"FR",
    "sg:address":"6 pl du 8 Mai 1945; S. Bel",
    "sg:classifiers":[
        {
            "category":"Banks & Credit Unions",
            "subcategory":"Bank",
            "type":"Services"
        }
    ],
    "sg:phone":"+33 3374012510",
    "wof:name":"Cr\u00e9dit Agricole Du Sud Est",
    "wof:placetype":"venue"
},
  "geometry": {"coordinates":[-93.085678,30.520035],"type":"Point"}
}