{
  "type": "Feature",
  "properties": {
    "addr:full":"5 Bd Du G\u00e9n\u00e9ral Leclerc 06310 Beaulieu Sur Mer Beaulieu Auvergne 15270",
    "addr:housenumber":"5",
    "addr:postcode":"06310;15270",
    "addr:street":"Bd Du Ge\u0301Ne\u0301Ral Leclerc",
    "iso:country":"FR",
    "sg:address":"5 Bd Du G\u00e9n\u00e9ral Leclerc 06310 Beaulieu Sur Mer",
    "sg:city":"Beaulieu",
    "sg:classifiers":[
        {
            "category":"Travel",
            "subcategory":"Hotels & Motels",
            "type":"Entertainment"
        }
    ],
    "sg:phone":"+33 4 93 01 00 01",
    "sg:postcode":"15270",
    "sg:province":"Auvergne",
    "sg:tags":[
        "hotels",
        "business",
        "restaurant"
    ],
    "wof:name":"Hotel La Reserve De Beaulieu",
    "wof:placetype":"venue"
},
  "geometry": {"coordinates":[7.330169,43.706413],"type":"Point"}
}