{
  "type": "Feature",
  "properties": {
    "iso:country":"FR",
    "sg:address":"Cardry St Brandan 22800 Quintin",
    "sg:city":"Quintin",
    "sg:classifiers":[
        {
            "category":"Food & Beverages",
            "subcategory":"Dairy",
            "type":"Retail Goods"
        }
    ],
    "sg:phone":"+33 2 96 74 87 52",
    "sg:postcode":"22800",
    "sg:province":"Bretagne",
    "sg:tags":[
        "product",
        "related"
    ],
    "wof:name":"Toury Sa",
    "wof:placetype":"venue"
},
  "geometry": {"coordinates":[-2.913515,48.353207],"type":"Point"}
}