{
  "type": "Feature",
  "properties": {
    "iso:country":"FR",
    "sg:address":"605, Rte de N\u00eemes - Parc Affaires de l'Aube Rouge, 34170 Castelnau Le Lez",
    "sg:orig_category":"Non-Classified Establishments",
    "sg:phone":"+33 4 67 02 64 64",
    "sg:province":"Languedoc-Roussillon",
    "wof:name":"Volseu Alarm S.a.",
    "wof:placetype":"venue"
},
  "geometry": {"coordinates":[3.926962,43.636547],"type":"Point"}
}