{
  "type": "Feature",
  "properties": {
    "addr:full":"5 rue Paul Mespl\u00e9 31100 Toulouse Midi Pyr\u00e9n\u00e9es",
    "addr:housenumber":"5",
    "addr:postcode":"31100",
    "addr:street":"Rue Paul Mesple\u0301",
    "iso:country":"FR",
    "sg:address":"5 rue Paul Mespl\u00e9 31100 Toulouse",
    "sg:classifiers":[
        {
            "category":"Banks & Credit Unions",
            "subcategory":"Investment Brokerage",
            "type":"Services"
        }
    ],
    "sg:phone":"+33 5 62 11 17 17",
    "sg:province":"Midi Pyr\u00e9n\u00e9es",
    "sg:tags":[
        "overhead",
        "conductor"
    ],
    "wof:name":"Sinters Sa",
    "wof:placetype":"venue"
},
  "geometry": {"coordinates":[1.38505,43.568459],"type":"Point"}
}