{
  "type": "Feature",
  "properties": {
    "iso:country":"FR",
    "sg:address":"1 Rue Pierre Rambaud 33600 Pessac",
    "sg:city":"Pessac",
    "sg:orig_category":"Mechanical Engineering - machines Metals - machinery and equipment Printing Printing and Publishing",
    "sg:phone":"+33 5 56 45 50 50",
    "sg:postcode":"33600",
    "sg:province":"Aquitaine",
    "wof:name":"Clicherie Aquitaine",
    "wof:placetype":"venue"
},
  "geometry": {"coordinates":[-0.641563,44.810463],"type":"Point"}
}