{
  "type": "Feature",
  "properties": {
    "iso:country":"FR",
    "sg:address":"485, Av. de l'Europe, 38330 Montbonnot Saint Martin",
    "sg:orig_category":"Unclassifiable Establishments",
    "sg:phone":"+33 4 76 52 62 00",
    "sg:province":"Rhone-Alpes",
    "wof:name":"Ernst And Young S.a.",
    "wof:placetype":"venue"
},
  "geometry": {"coordinates":[5.808954,45.220104],"type":"Point"}
}