{
  "type": "Feature",
  "properties": {
    "iso:country":"FR",
    "sg:address":"1A, Rue Ettore Bugatti, 67201 Eckbolsheim",
    "sg:city":"Eckbolsheim",
    "sg:orig_category":"Non-Classified Establishments",
    "sg:phone":"+33 3 88 76 57 03",
    "sg:postcode":"67201",
    "sg:province":"Alsace",
    "wof:name":"Euro Technic S.a.r.l.",
    "wof:placetype":"venue"
},
  "geometry": {"coordinates":[7.685993,48.589901],"type":"Point"}
}