{
  "type": "Feature",
  "properties": {
    "iso:country":"FR",
    "sg:address":"B.P. 3",
    "sg:city":"Millau C\u00e9dex^^Creissels 12100 Millau",
    "sg:orig_category":"Non-Classified Establishments",
    "sg:phone":"+33 5 65 59 26 00",
    "sg:postcode":"12100",
    "sg:province":"Midi Pyr\u00e9n\u00e9es",
    "wof:name":"Megisserie Richard S.a.r.l.",
    "wof:placetype":"venue"
},
  "geometry": {"coordinates":[2.98414,44.063969],"type":"Point"}
}