{
  "type": "Feature",
  "properties": {
    "addr:full":"20 Rue Du Manoir 27490 Autheuil Authouillet Haute Normandie",
    "addr:housenumber":"20",
    "addr:postcode":"27490",
    "addr:street":"Rue Du Manoir;Haute Normandie",
    "iso:country":"FR",
    "sg:address":"20 Rue Du Manoir 27490 Autheuil Authouillet",
    "sg:classifiers":[
        {
            "category":"Manufacturing",
            "subcategory":"Paper Products",
            "type":"Manufacturing & Wholesale Goods"
        }
    ],
    "sg:phone":"+33 2 32 35 66 92",
    "sg:province":"Haute Normandie",
    "sg:tags":[
        "packaging",
        "material",
        "-",
        "cardboard"
    ],
    "wof:name":"Societe Des Etablissements Picourt",
    "wof:placetype":"venue"
},
  "geometry": {"coordinates":[1.275895,49.093475],"type":"Point"}
}