{
  "type": "Feature",
  "properties": {
    "addr:full":"48, Rue de l'Atlantique - ZA P\u00f4le Sud, 44115 Basse Goulaine Pays de Loire",
    "addr:housenumber":"48",
    "addr:postcode":"44115",
    "addr:street":"Rue De L'Atlantique Za Po\u0302Le Sud;Goulaine",
    "iso:country":"FR",
    "sg:address":"48, Rue de l'Atlantique - ZA P\u00f4le Sud, 44115 Basse Goulaine",
    "sg:orig_category":"Non-Classified Establishments",
    "sg:phone":"+33 2 40 34 80 34",
    "sg:province":"Pays de Loire",
    "wof:name":"Ill Bruck S.a.s.",
    "wof:placetype":"venue"
},
  "geometry": {"coordinates":[-1.463597,47.187096],"type":"Point"}
}