{
  "type": "Feature",
  "properties": {
    "addr:full":"10, Rue Etienne Deforges, 92320 Ch\u00e2tillon Ile de France 92320",
    "addr:housenumber":"10",
    "addr:postcode":"92320;ile;92320",
    "addr:street":"Rue Etienne Deforges;France",
    "iso:country":"FR",
    "sg:address":"10, Rue Etienne Deforges, 92320 Ch\u00e2tillon",
    "sg:orig_category":"Non-Classified Establishments",
    "sg:phone":"+33 1 47 46 01 02",
    "sg:postcode":"92320",
    "sg:province":"Ile de France",
    "wof:name":"A.d.l. S.a. - Action D\u00e9veloppement Langage",
    "wof:placetype":"venue"
},
  "geometry": {"coordinates":[2.294118,48.806316],"type":"Point"}
}