{
  "type": "Feature",
  "properties": {
    "addr:full":"Porte 4 Terre Plein de Mourepiane Marseille Poitou-Charentes 13015",
    "addr:housenumber":"4",
    "addr:postcode":"13015",
    "addr:street":"Porte;Plein;Mourepiane",
    "iso:country":"FR",
    "sg:address":"Porte 4 Terre Plein de Mourepiane",
    "sg:city":"Marseille",
    "sg:orig_category":"Unclassifiable Establishments",
    "sg:phone":"+33 4 91 03 52 00",
    "sg:postcode":"13015",
    "sg:province":"Poitou-Charentes",
    "wof:name":"C.m.r. S.a.",
    "wof:placetype":"venue"
},
  "geometry": {"coordinates":[5.347935,43.349232],"type":"Point"}
}