{
  "type": "Feature",
  "properties": {
    "iso:country":"FR",
    "sg:address":"Rue du Baty",
    "sg:city":"Neuve Maison",
    "sg:orig_category":"Unclassifiable Establishments",
    "sg:phone":"+33 3 23 58 48 13",
    "sg:postcode":"02500",
    "sg:province":"Picardie",
    "wof:name":"I.p.p. Emballages Et Plastiques S.a.r.l.",
    "wof:placetype":"venue"
},
  "geometry": {"coordinates":[4.091558,49.905891],"type":"Point"}
}