{
  "type": "Feature",
  "properties": {
    "addr:full":"43, Rue Roger Salengro, 71360 Epinac \u00c9pinac Bourgogne 71360",
    "addr:housenumber":"43",
    "addr:postcode":"71360;71360",
    "addr:street":"Rue Roger Salengro",
    "iso:country":"FR",
    "sg:address":"43, Rue Roger Salengro, 71360 Epinac",
    "sg:city":"\u00c9pinac",
    "sg:orig_category":"Unclassifiable Establishments",
    "sg:phone":"+33 3 85 82 90 08",
    "sg:postcode":"71360",
    "sg:province":"Bourgogne",
    "wof:name":"Allo Coup D'main",
    "wof:placetype":"venue"
},
  "geometry": {"coordinates":[4.512932,46.991402],"type":"Point"}
}