{
  "type": "Feature",
  "properties": {
    "iso:country":"FR",
    "sg:address":"5, All\u00e9e de Vincennes, 54500 Vandoeuvre les Nancy",
    "sg:orig_category":"Unclassifiable Establishments",
    "sg:phone":"+33 3 83 44 21 21",
    "sg:province":"Lorraine",
    "wof:name":"Weisrock Constructions Bois S.a.",
    "wof:placetype":"venue"
},
  "geometry": {"coordinates":[6.136439,48.65398],"type":"Point"}
}