{
  "type": "Feature",
  "properties": {
    "iso:country":"FR",
    "sg:address":"Le Cumont 73520 La Bridoire",
    "sg:classifiers":[
        {
            "category":"Manufacturing",
            "subcategory":"Tools & Machinery",
            "type":"Manufacturing & Wholesale Goods"
        }
    ],
    "sg:phone":"+33 4 76 31 24 20",
    "sg:postcode":"73520",
    "sg:province":"Rhone-Alpes",
    "sg:tags":[
        "metallurgy",
        "metalworking"
    ],
    "wof:name":"Produits Trefiles De La Bridoire Sarl",
    "wof:placetype":"venue"
},
  "geometry": {"coordinates":[5.743411,45.530396],"type":"Point"}
}