{
  "type": "Feature",
  "properties": {
    "addr:full":"3, Rue des Mouliniers, 43220 Duni\u00e8res Duni\u00e8res Auvergne 43220",
    "addr:housenumber":"3",
    "addr:postcode":"43220;dunie\u0300res;43220",
    "addr:street":"Rue Des Mouliniers",
    "iso:country":"FR",
    "sg:address":"3, Rue des Mouliniers, 43220 Duni\u00e8res",
    "sg:city":"Duni\u00e8res",
    "sg:orig_category":"Unclassifiable Establishments",
    "sg:phone":"+33 4 71 66 82 70",
    "sg:postcode":"43220",
    "sg:province":"Auvergne",
    "wof:name":"Cofitex Pochon",
    "wof:placetype":"venue"
},
  "geometry": {"coordinates":[4.426631,45.186089],"type":"Point"}
}