{
  "type": "Feature",
  "properties": {
    "iso:country":"FR",
    "sg:address":"19 Route Nationale 10100 St Hilaire Sous Romilly",
    "sg:classifiers":[
        {
            "category":"Wholesale",
            "subcategory":"Machinery & Supplies",
            "type":"Manufacturing & Wholesale Goods"
        }
    ],
    "sg:phone":"+33 3 25 21 07 00",
    "sg:postcode":"10100",
    "sg:province":"Champagne",
    "sg:tags":[
        "handling",
        "material",
        "-",
        "machine",
        "equipment",
        "engineering",
        "mechanical"
    ],
    "wof:name":"Tractel Sas",
    "wof:placetype":"venue"
},
  "geometry": {"coordinates":[3.732477,48.491051],"type":"Point"}
}