{
  "type": "Feature",
  "properties": {
    "addr:full":"Rue de l'Anni\u00e8re - Parc d'activit\u00e9s du Maupas Vire Basse Normandie 14500",
    "addr:postcode":"14500",
    "addr:street":"Rue De L'Annie \u0300Re Parc D'Activite \u0301S Du Maupas Vire Basse",
    "iso:country":"FR",
    "sg:address":"Rue de l'Anni\u00e8re - Parc d'activit\u00e9s du Maupas",
    "sg:city":"Vire",
    "sg:orig_category":"Non-Classified Establishments",
    "sg:phone":"+33 2 31 66 22 22",
    "sg:postcode":"14500",
    "sg:province":"Basse Normandie",
    "wof:name":"Chauvin Arnoux S.c.a.",
    "wof:placetype":"venue"
},
  "geometry": {"coordinates":[0.987473,44.47797],"type":"Point"}
}