{
  "type": "Feature",
  "properties": {
    "addr:full":"La Murette 43140 Saint Didier en Velay Saint-Didier-en-Velay Auvergne 43140",
    "addr:postcode":"43140;43140",
    "addr:street":"La;Didier En Velay",
    "iso:country":"FR",
    "sg:address":"La Murette 43140 Saint Didier en Velay",
    "sg:city":"Saint-Didier-en-Velay",
    "sg:orig_category":"Unclassifiable Establishments",
    "sg:phone":"+33 4 71 61 12 00",
    "sg:postcode":"43140",
    "sg:province":"Auvergne",
    "wof:name":"Noriver S.a.r.l.",
    "wof:placetype":"venue"
},
  "geometry": {"coordinates":[4.27155,45.298294],"type":"Point"}
}