{
  "type": "Feature",
  "properties": {
    "addr:full":"Puy De Chat 16220 Ecuras Poitou-Charentes",
    "addr:housenumber":"16220",
    "addr:street":"Ecuras",
    "iso:country":"FR",
    "sg:address":"Puy De Chat 16220 Ecuras",
    "sg:classifiers":[
        {
            "category":"Farming",
            "subcategory":"Farm & Veterinary Services",
            "type":"Manufacturing & Wholesale Goods"
        }
    ],
    "sg:phone":"+33 5 45 63 03 37",
    "sg:province":"Poitou-Charentes",
    "sg:tags":[
        "advice",
        "agriculture",
        "livestock",
        "business"
    ],
    "wof:name":"Valembois",
    "wof:placetype":"venue"
},
  "geometry": {"coordinates":[0.583807,45.677841],"type":"Point"}
}