{
  "type": "Feature",
  "properties": {
    "addr:full":"La Piotiere 39140 Commenailles Franche Comt\u00e9 39140",
    "addr:postcode":"39140;39140",
    "addr:street":"Franche Comte\u0301",
    "iso:country":"FR",
    "sg:address":"La Piotiere 39140 Commenailles",
    "sg:orig_category":"Non-Classified Establishments",
    "sg:phone":"+33 3 84 48 60 92",
    "sg:postcode":"39140",
    "sg:province":"Franche Comt\u00e9",
    "wof:name":"Bresse Sciages S.a.r.l.",
    "wof:placetype":"venue"
},
  "geometry": {"coordinates":[5.44831,46.820675],"type":"Point"}
}