{
  "type": "Feature",
  "properties": {
    "addr:full":"33, Quai de Queyries - ZA de Queyries, 33100 Bordeaux C\u00e9dex Bordeaux Aquitaine 33100",
    "addr:housenumber":"33",
    "addr:postcode":"33100;ce\u0301dex;33100",
    "addr:street":"Quai De Queyries Za De Queyries",
    "iso:country":"FR",
    "sg:address":"33, Quai de Queyries - ZA de Queyries, 33100 Bordeaux C\u00e9dex",
    "sg:city":"Bordeaux",
    "sg:orig_category":"Non-Classified Establishments",
    "sg:phone":"+33 5 57 77 55 33",
    "sg:postcode":"33100",
    "sg:province":"Aquitaine",
    "wof:name":"Transports De Savoie S.a.",
    "wof:placetype":"venue"
},
  "geometry": {"coordinates":[-0.54975,44.845039],"type":"Point"}
}