{
  "type": "Feature",
  "properties": {
    "addr:full":"Rte de Saverne Dettwiller Alsace 67490",
    "addr:postcode":"67490",
    "addr:street":"Rte De Saverne",
    "iso:country":"FR",
    "sg:address":"Rte de Saverne",
    "sg:city":"Dettwiller",
    "sg:orig_category":"Unclassifiable Establishments",
    "sg:phone":"+33 3 88 91 41 37",
    "sg:postcode":"67490",
    "sg:province":"Alsace",
    "wof:name":"Heschung S.a.",
    "wof:placetype":"venue"
},
  "geometry": {"coordinates":[7.461479,48.751167],"type":"Point"}
}