{
  "type": "Feature",
  "properties": {
    "addr:full":"26 Bd Saint Michel 75006 Paris Ile de France",
    "addr:housenumber":"26",
    "addr:postcode":"75006",
    "addr:street":"Bd Saint Michel",
    "iso:country":"FR",
    "sg:address":"26 Bd Saint Michel 75006 Paris",
    "sg:classifiers":[
        {
            "category":"Professional",
            "subcategory":"Printing & Photocopies",
            "type":"Services"
        }
    ],
    "sg:phone":"+33 1 44 41 88 88",
    "sg:province":"Ile de France",
    "sg:tags":[
        "publishing"
    ],
    "wof:name":"Joseph Gibert Sa",
    "wof:placetype":"venue"
},
  "geometry": {"coordinates":[2.342579,48.850555],"type":"Point"}
}