{
  "type": "Feature",
  "properties": {
    "iso:country":"FR",
    "sg:address":"18 Boulevard Michel Briant 29490 Guipavas",
    "sg:city":"Guipavas",
    "sg:classifiers":[
        {
            "category":"Autos & Motor Vehicles",
            "subcategory":"Automobile Sales",
            "type":"Retail Goods"
        }
    ],
    "sg:phone":"+33 2 98 28 42 17",
    "sg:postcode":"29490",
    "sg:province":"Bretagne",
    "sg:tags":[
        "equipment",
        "motor-cars",
        "transport"
    ],
    "wof:name":"Le Bris (garage Poids Lourds) Sa",
    "wof:placetype":"venue"
},
  "geometry": {"coordinates":[-4.422309,48.42231],"type":"Point"}
}