{
  "type": "Feature",
  "properties": {
    "iso:country":"FR",
    "sg:address":"1, Rue Louis Bloquet, 60110 M\u00e9ru",
    "sg:orig_category":"Non-Classified Establishments",
    "sg:phone":"+33 3 44 52 62 20",
    "sg:province":"Picardie",
    "wof:name":"La Quincaillerie Principale S.a.",
    "wof:placetype":"venue"
},
  "geometry": {"coordinates":[2.136611,49.235542],"type":"Point"}
}