{
  "type": "Feature",
  "properties": {
    "addr:full":"30 Yserhouck Weg 59470 Volckerinckhove Nord Pas-de-Calais 59470",
    "addr:housenumber":"30",
    "addr:postcode":"59470;59470",
    "addr:street":"Yserhouck Weg",
    "iso:country":"FR",
    "sg:address":"30 Yserhouck Weg 59470 Volckerinckhove",
    "sg:classifiers":[
        {
            "category":"Farming",
            "subcategory":"Farm & Veterinary Services",
            "type":"Manufacturing & Wholesale Goods"
        }
    ],
    "sg:phone":"+33 3 28 68 00 80",
    "sg:postcode":"59470",
    "sg:province":"Nord Pas-de-Calais",
    "sg:tags":[
        "advice",
        "agriculture",
        "livestock",
        "business"
    ],
    "wof:name":"Entreprise Toulouse Achte Sarl",
    "wof:placetype":"venue"
},
  "geometry": {"coordinates":[2.30662,50.837746],"type":"Point"}
}