{
  "type": "Feature",
  "properties": {
    "addr:full":"2, Rue du Pavillon, 49070 Beaucouz\u00e9 Pays de Loire",
    "addr:housenumber":"2",
    "addr:postcode":"49070",
    "addr:street":"Rue Du Pavillon",
    "iso:country":"FR",
    "sg:address":"2, Rue du Pavillon, 49070 Beaucouz\u00e9",
    "sg:orig_category":"Unclassifiable Establishments",
    "sg:phone":"+33 2 41 36 60 00",
    "sg:province":"Pays de Loire",
    "wof:name":"Spie - Trindel S.a.",
    "wof:placetype":"venue"
},
  "geometry": {"coordinates":[-0.622177,47.466331],"type":"Point"}
}