{
  "type": "Feature",
  "properties": {
    "addr:full":"423 Rue De La Gare 65200 Montgaillard Midi Pyr\u00e9n\u00e9es 65200",
    "addr:housenumber":"423",
    "addr:postcode":"65200;65200",
    "addr:street":"Rue De La Gare",
    "iso:country":"FR",
    "sg:address":"423 Rue De La Gare 65200 Montgaillard",
    "sg:classifiers":[
        {
            "category":"Bakery",
            "type":"Food & Drink"
        }
    ],
    "sg:phone":"+33 5 62 91 50 62",
    "sg:postcode":"65200",
    "sg:province":"Midi Pyr\u00e9n\u00e9es",
    "sg:tags":[
        "cake",
        "product",
        "related",
        "bread"
    ],
    "wof:name":"Biscuiterie Vedere",
    "wof:placetype":"venue"
},
  "geometry": {"coordinates":[0.11313,43.125862],"type":"Point"}
}