{
  "type": "Feature",
  "properties": {
    "addr:full":"11, Voie la Cardon - Parc Gutenberg, 91120 Palaiseau Ile de France",
    "addr:housenumber":"11",
    "addr:postcode":"91120;ile",
    "addr:street":"Voie La Cardon Parc Gutenberg",
    "iso:country":"FR",
    "sg:address":"11, Voie la Cardon - Parc Gutenberg, 91120 Palaiseau",
    "sg:orig_category":"Unclassifiable Establishments",
    "sg:phone":"+33 1 64 53 14 14",
    "sg:province":"Ile de France",
    "wof:name":"Retis Communication S.a.",
    "wof:placetype":"venue"
},
  "geometry": {"coordinates":[2.257042,48.707394],"type":"Point"}
}