{
  "type": "Feature",
  "properties": {
    "iso:country":"FR",
    "sg:address":"36 Rue De La Croix De Mission 42012 St \u00c9tienne",
    "sg:classifiers":[
        {
            "category":"Professional",
            "subcategory":"Engineering",
            "type":"Services"
        }
    ],
    "sg:phone":"+33 4 77 43 89 89",
    "sg:province":"Franche Comt\u00e9",
    "sg:tags":[
        "machine",
        "-",
        "mechanical"
    ],
    "wof:name":"Ste Nouvelle Emafu Sa",
    "wof:placetype":"venue"
},
  "geometry": {"coordinates":[4.376586,45.431408],"type":"Point"}
}