{
  "type": "Feature",
  "properties": {
    "addr:full":"B.P. 617, 71324 Ch\u00e2lon sur Sa\u00f4ne C\u00e9dex^^16, Bd de la R\u00e9publique, 71100 Ch\u00e2lon sur Sa\u00f4ne Chalon-sur-Sa\u00f4ne Bourgogne 71100",
    "addr:housenumber":"b.p. 617",
    "addr:postcode":"71324;71100;71100",
    "addr:street":"Bd De La Re\u0301Publique",
    "iso:country":"FR",
    "sg:address":"B.P. 617, 71324 Ch\u00e2lon sur Sa\u00f4ne C\u00e9dex^^16, Bd de la R\u00e9publique, 71100 Ch\u00e2lon sur Sa\u00f4ne",
    "sg:city":"Chalon-sur-Sa\u00f4ne",
    "sg:orig_category":"Non-Classified Establishments",
    "sg:phone":"+33 3 85 94 04 05",
    "sg:postcode":"71100",
    "sg:province":"Bourgogne",
    "wof:name":"Curchal S.a.",
    "wof:placetype":"venue"
},
  "geometry": {"coordinates":[-91.703262,32.105309],"type":"Point"}
}