{
  "type": "Feature",
  "properties": {
    "iso:country":"FR",
    "sg:address":"522 ave du Prado; Marseille; 13001",
    "sg:classifiers":[
        {
            "category":"Banks & Credit Unions",
            "subcategory":"Bank",
            "type":"Services"
        }
    ],
    "sg:phone":"+33 4 91 30 78 78",
    "sg:province":"Poitou-Charentes",
    "wof:name":"Cr\u00e9dit Commercial, De France Sa",
    "wof:placetype":"venue"
},
  "geometry": {"coordinates":[5.379526,43.265347],"type":"Point"}
}