{
  "type": "Feature",
  "properties": {
    "addr:full":"Rn 4 Village Ero 84700 Sorgues Midi Pyr\u00e9n\u00e9es",
    "addr:postcode":"84700",
    "addr:street":"Rn 4 Village",
    "iso:country":"FR",
    "sg:address":"Rn 4 Village Ero 84700 Sorgues",
    "sg:classifiers":[
        {
            "category":"Manufacturing",
            "subcategory":"Building Materials",
            "type":"Manufacturing & Wholesale Goods"
        }
    ],
    "sg:phone":"+33 4 90 39 34 56",
    "sg:province":"Midi Pyr\u00e9n\u00e9es",
    "sg:tags":[
        "glass",
        "ceramic"
    ],
    "wof:name":"4 M Provence Route",
    "wof:placetype":"venue"
},
  "geometry": {"coordinates":[4.873481,44.00827],"type":"Point"}
}