{
  "type": "Feature",
  "properties": {
    "addr:full":"B.P. 26, 54425 Pulnoy^^34bis, Av Charles de Gaulle, 54420 Pulnoy Lorraine",
    "addr:postcode":"54425;54420",
    "addr:street":"B.P. 26;Av Charles De Gaulle",
    "iso:country":"FR",
    "sg:address":"B.P. 26, 54425 Pulnoy^^34bis, Av Charles de Gaulle, 54420 Pulnoy",
    "sg:orig_category":"Non-Classified Establishments",
    "sg:phone":"+33 3 83 29 31 84",
    "sg:province":"Lorraine",
    "wof:name":"S.p.e.i. S.a.",
    "wof:placetype":"venue"
},
  "geometry": {"coordinates":[6.24509,48.687649],"type":"Point"}
}