{
  "type": "Feature",
  "properties": {
    "iso:country":"FR",
    "sg:address":"16, Av. Jean Mermoz, 93120 La Courneuve",
    "sg:orig_category":"Unclassifiable Establishments",
    "sg:phone":"+33 1 48 37 02 12",
    "sg:province":"Ile de France",
    "wof:name":"C\u00e9dip S.a.",
    "wof:placetype":"venue"
},
  "geometry": {"coordinates":[2.400198,48.931942],"type":"Point"}
}