{
  "type": "Feature",
  "properties": {
    "addr:full":"Av. Lavoisier - ZA de Ragon Treilli\u00e8res Pays de Loire 44119",
    "addr:postcode":"44119",
    "addr:street":"Av. Lavoisier Za De Ragon Treillie\u0300Res Pays",
    "iso:country":"FR",
    "sg:address":"Av. Lavoisier - ZA de Ragon",
    "sg:city":"Treilli\u00e8res",
    "sg:orig_category":"Non-Classified Establishments",
    "sg:phone":"+33 2 40 72 56 79",
    "sg:postcode":"44119",
    "sg:province":"Pays de Loire",
    "wof:name":"L.t.a. S.a.r.l. - La T\u00f4lerie Armoricaine",
    "wof:placetype":"venue"
},
  "geometry": {"coordinates":[-1.622475,47.330029],"type":"Point"}
}