{
  "type": "Feature",
  "properties": {
    "addr:full":"Route De Mantes 78410 Bouafle Ile de France 78410",
    "addr:postcode":"78410;ile;78410",
    "addr:street":"Route De Mantes;France",
    "iso:country":"FR",
    "sg:address":"Route De Mantes 78410 Bouafle",
    "sg:classifiers":[
        {
            "category":"Building & Trades",
            "subcategory":"Construction",
            "type":"Services"
        }
    ],
    "sg:phone":"+33 1 30 91 02 72",
    "sg:postcode":"78410",
    "sg:province":"Ile de France",
    "sg:tags":[
        "work",
        "public"
    ],
    "wof:name":"La Francilienne De Travaux Publics Ftp Ftp Francilienne De Travauxpublics",
    "wof:placetype":"venue"
},
  "geometry": {"coordinates":[1.89065,48.96476],"type":"Point"}
}