{
  "type": "Feature",
  "properties": {
    "iso:country":"FR",
    "sg:address":"24 Rue Armand Benet 27000 Evreux",
    "sg:classifiers":[
        {
            "category":"Professional",
            "subcategory":"Engineering",
            "type":"Services"
        }
    ],
    "sg:phone":"+33 2 32 39 07 22",
    "sg:postcode":"27000",
    "sg:province":"Haute Normandie",
    "sg:tags":[
        "machine",
        "-",
        "mechanical"
    ],
    "wof:name":"Demolin Evreux",
    "wof:placetype":"venue"
},
  "geometry": {"coordinates":[1.159636,49.02615],"type":"Point"}
}