{
  "type": "Feature",
  "properties": {
    "addr:full":"26 Chemin Du Grand Chassagnon 69200 V\u00e9nissieux Rhone-Alpes 69200",
    "addr:housenumber":"26",
    "addr:postcode":"69200;69200",
    "addr:street":"Chemin Du Grand Chassagnon",
    "iso:country":"FR",
    "sg:address":"26 Chemin Du Grand Chassagnon 69200 V\u00e9nissieux",
    "sg:classifiers":[
        {
            "category":"Manufacturing",
            "subcategory":"Paper Products",
            "type":"Manufacturing & Wholesale Goods"
        }
    ],
    "sg:phone":"+33 4 78 70 85 92",
    "sg:postcode":"69200",
    "sg:province":"Rhone-Alpes",
    "sg:tags":[
        "finished",
        "cardboard",
        "-"
    ],
    "wof:name":"Rhone Alpes Etiquettes Sa",
    "wof:placetype":"venue"
},
  "geometry": {"coordinates":[4.863081,45.701519],"type":"Point"}
}