{
  "type": "Feature",
  "properties": {
    "addr:full":"6 quai de la Bourse des Consuls; Boite Postale 641; ROUEN Cedex; 76007 Centre",
    "addr:housenumber":"6;641",
    "addr:postcode":"76007",
    "addr:street":"Quai De La Bourse Des Consuls Boite Postale",
    "iso:country":"FR",
    "sg:address":"6 quai de la Bourse",
    "sg:city":"des Consuls; Boite Postale 641; ROUEN Cedex; 76007",
    "sg:classifiers":[
        {
            "category":"Shopping",
            "subcategory":"Computers & Home Electronics",
            "type":"Retail Goods"
        }
    ],
    "sg:phone":"+33 2 35 14 37 37",
    "sg:province":"Centre",
    "sg:tags":[
        "chamber",
        "commerce"
    ],
    "wof:name":"Chambre De Commerce Et D'industrie De Rouen",
    "wof:placetype":"venue"
},
  "geometry": {"coordinates":[1.10154,49.443089],"type":"Point"}
}