{
  "type": "Feature",
  "properties": {
    "addr:full":"41-51 Av Du Vieux Chemin De St-Denis 92230 Gennevilliers Ile de France 92230",
    "addr:housenumber":"41-51",
    "addr:postcode":"92230;ile;92230",
    "addr:street":"Av Du Vieux Chemin De St-Denis;France",
    "iso:country":"FR",
    "sg:address":"41-51 Av Du Vieux Chemin De St-Denis 92230 Gennevilliers",
    "sg:classifiers":[
        {
            "category":"Manufacturing",
            "subcategory":"Metals",
            "type":"Manufacturing & Wholesale Goods"
        }
    ],
    "sg:phone":"+33 1 47 99 94 13",
    "sg:postcode":"92230",
    "sg:province":"Ile de France",
    "sg:tags":[
        "metallurgy",
        "metalworking",
        "processing"
    ],
    "wof:name":"Ste Frechetnet Cie Protection Des Metaux",
    "wof:placetype":"venue"
},
  "geometry": {"coordinates":[2.314484,48.932583],"type":"Point"}
}