{
  "type": "Feature",
  "properties": {
    "addr:full":"12, Place de la Croix Blanche, 71150 Rully Rully Bourgogne 71150",
    "addr:housenumber":"12",
    "addr:postcode":"71150;71150",
    "addr:street":"Place De La Croix Blanche",
    "iso:country":"FR",
    "sg:address":"12, Place de la Croix Blanche, 71150 Rully",
    "sg:city":"Rully",
    "sg:orig_category":"Unclassifiable Establishments",
    "sg:phone":"+33 3 85 87 13 60",
    "sg:postcode":"71150",
    "sg:province":"Bourgogne",
    "wof:name":"Etablissements Picamelot S.a.r.l.",
    "wof:placetype":"venue"
},
  "geometry": {"coordinates":[4.74394,46.874954],"type":"Point"}
}