{
  "type": "Feature",
  "properties": {
    "addr:full":"60, Av. de la Timone, 13010 Marseille Poitou-Charentes",
    "addr:postcode":"13010",
    "addr:street":"60 Av. De La Timone",
    "iso:country":"FR",
    "sg:address":"60, Av. de la Timone, 13010 Marseille",
    "sg:orig_category":"Unclassifiable Establishments",
    "sg:phone":"+33 4 91 32 80 10",
    "sg:province":"Poitou-Charentes",
    "wof:name":"Chaffoteaux Et Maury",
    "wof:placetype":"venue"
},
  "geometry": {"coordinates":[5.4029,43.285782],"type":"Point"}
}