{
  "type": "Feature",
  "properties": {
    "iso:country":"FR",
    "sg:address":"1025, Av. Henri Becquerel - B\u00e2t. 27 Parc Club Mill\u00e9naire, 34000 Montpellier",
    "sg:orig_category":"Unclassifiable Establishments",
    "sg:phone":"+33 4 67 58 24 90",
    "sg:province":"Languedoc-Roussillon",
    "wof:name":"C.d.c.a. - Comit\u00e9 D\u00e9fense Commer\u00e7ants Et Artisans",
    "wof:placetype":"venue"
},
  "geometry": {"coordinates":[3.914558,43.609131],"type":"Point"}
}