{
  "type": "Feature",
  "properties": {
    "iso:country":"FR",
    "sg:address":"B.P. 13",
    "sg:city":"Ormes^^10700 Ormes",
    "sg:orig_category":"Non-Classified Establishments",
    "sg:phone":"+33 3 25 37 86 56",
    "sg:postcode":"10700",
    "sg:province":"Champagne",
    "wof:name":"Coop\u00e9rative De D\u00e9shydratation",
    "wof:placetype":"venue"
},
  "geometry": {"coordinates":[4.138695,48.536194],"type":"Point"}
}