{
  "type": "Feature",
  "properties": {
    "addr:full":"22 rue des Jardins 57000 Metz Lorraine 57000",
    "addr:housenumber":"22",
    "addr:postcode":"57000;57000",
    "addr:street":"Rue Des Jardins",
    "iso:country":"FR",
    "sg:address":"22 rue des Jardins 57000 Metz",
    "sg:classifiers":[
        {
            "category":"Wholesale",
            "subcategory":"Wine & Distilled Alcoholic Beverages",
            "type":"Manufacturing & Wholesale Goods"
        }
    ],
    "sg:phone":"+33 3 87 76 91 73",
    "sg:postcode":"57000",
    "sg:province":"Lorraine",
    "sg:tags":[
        "french"
    ],
    "wof:name":"Venus Vins Sarl",
    "wof:placetype":"venue"
},
  "geometry": {"coordinates":[6.177546,49.121838],"type":"Point"}
}