{
  "type": "Feature",
  "properties": {
    "addr:full":"Lapoujade 47500 Condezaygues Condezaygues Aquitaine 47500",
    "addr:postcode":"47500;47500",
    "addr:street":"Lapoujade",
    "iso:country":"FR",
    "sg:address":"Lapoujade 47500 Condezaygues",
    "sg:city":"Condezaygues",
    "sg:orig_category":"Non-Classified Establishments",
    "sg:phone":"+33 5 53 71 20 16",
    "sg:postcode":"47500",
    "sg:province":"Aquitaine",
    "wof:name":"B.c.l. S.a.r.l.",
    "wof:placetype":"venue"
},
  "geometry": {"coordinates":[0.91499,44.467369],"type":"Point"}
}