{
  "type": "Feature",
  "properties": {
    "addr:full":"Zone Du Relais 53410 La Gravelle Pays de Loire",
    "addr:postcode":"53410",
    "addr:street":"Gravelle",
    "iso:country":"FR",
    "sg:address":"Zone Du Relais 53410 La Gravelle",
    "sg:classifiers":[
        {
            "category":"Manufacturing",
            "subcategory":"Paper Products",
            "type":"Manufacturing & Wholesale Goods"
        }
    ],
    "sg:phone":"+33 2 43 01 86 38",
    "sg:province":"Pays de Loire",
    "sg:tags":[
        "packaging",
        "material",
        "-",
        "cardboard"
    ],
    "wof:name":"Cartonnages Mayennais Sa",
    "wof:placetype":"venue"
},
  "geometry": {"coordinates":[-1.013198,48.072639],"type":"Point"}
}