{
  "type": "Feature",
  "properties": {
    "addr:full":"B.P. 126, 59471 Seclin C\u00e9dex^^ZI A, 59113 Seclin Nord Pas-de-Calais",
    "addr:housenumber":"b.p. 126;a",
    "addr:postcode":"59471;59113",
    "iso:country":"FR",
    "sg:address":"B.P. 126, 59471 Seclin C\u00e9dex^^ZI A, 59113 Seclin",
    "sg:orig_category":"Non-Classified Establishments",
    "sg:phone":"+33 3 20 90 96 90",
    "sg:province":"Nord Pas-de-Calais",
    "wof:name":"Hussor Erecta S.a.",
    "wof:placetype":"venue"
},
  "geometry": {"coordinates":[3.026865,50.54681],"type":"Point"}
}