{
  "type": "Feature",
  "properties": {
    "iso:country":"FR",
    "sg:address":"ZI de Gabor",
    "sg:city":"Saint Sulpice",
    "sg:orig_category":"Non-Classified Establishments",
    "sg:phone":"+33 5 63 40 23 00",
    "sg:postcode":"81370",
    "sg:province":"Midi Pyr\u00e9n\u00e9es",
    "wof:name":"Sud Graphie Rotative S.a.",
    "wof:placetype":"venue"
},
  "geometry": {"coordinates":[1.685785,43.774029],"type":"Point"}
}