{
  "type": "Feature",
  "properties": {
    "addr:full":"7 Bd Lamarck 18000 Bourges Bourges Centre 18000",
    "addr:housenumber":"7",
    "addr:postcode":"18000;18000",
    "addr:street":"Bd Lamarck",
    "iso:country":"FR",
    "sg:address":"7 Bd Lamarck 18000 Bourges",
    "sg:city":"Bourges",
    "sg:classifiers":[
        {
            "category":"Professional",
            "subcategory":"Business Services",
            "type":"Services"
        }
    ],
    "sg:phone":"+33 2 48 70 11 22",
    "sg:postcode":"18000",
    "sg:province":"Centre",
    "sg:tags":[
        "travel",
        "fair"
    ],
    "wof:name":"Palais Des Congres De Bourges",
    "wof:placetype":"venue"
},
  "geometry": {"coordinates":[2.391434,47.078342],"type":"Point"}
}