{
  "type": "Feature",
  "properties": {
    "iso:country":"FR",
    "sg:address":"31-33 Rue Ren\u00e9 Magne 33083 Bordeaux",
    "sg:city":"Bordeaux",
    "sg:classifiers":[
        {
            "category":"Manufacturing",
            "subcategory":"Metals",
            "type":"Manufacturing & Wholesale Goods"
        }
    ],
    "sg:phone":"+33 5 56 11 32 32",
    "sg:postcode":"33100",
    "sg:province":"Aquitaine",
    "sg:tags":[
        "-",
        "machine",
        "equipment",
        "engineering",
        "machinery",
        "mechanical"
    ],
    "wof:name":"Eural Sa",
    "wof:placetype":"venue"
},
  "geometry": {"coordinates":[-0.544274,44.888786],"type":"Point"}
}