{
  "type": "Feature",
  "properties": {
    "addr:full":"22, Rue Amiral du Foss\u00e9, 29200 Brest Brest Bretagne 29200",
    "addr:housenumber":"22",
    "addr:postcode":"29200;29200",
    "addr:street":"Rue Amiral Du Fosse\u0301",
    "iso:country":"FR",
    "sg:address":"22, Rue Amiral du Foss\u00e9, 29200 Brest",
    "sg:city":"Brest",
    "sg:orig_category":"Unclassifiable Establishments",
    "sg:phone":"+33 2 98 47 72 82",
    "sg:postcode":"29200",
    "sg:province":"Bretagne",
    "wof:name":"Bureau V\u00e9ritas S.a.",
    "wof:placetype":"venue"
},
  "geometry": {"coordinates":[-4.492013,48.384975],"type":"Point"}
}