{
  "type": "Feature",
  "properties": {
    "addr:full":"4 rue de la Poterne 45330 MALESHERBES Malesherbes Centre 45330",
    "addr:housenumber":"4",
    "addr:postcode":"45330;45330",
    "addr:street":"Rue De La Poterne;Malesherbes",
    "iso:country":"FR",
    "sg:address":"4 rue de la Poterne 45330 MALESHERBES",
    "sg:city":"Malesherbes",
    "sg:classifiers":[
        {
            "category":"Manufacturing",
            "subcategory":"Rubber & Plastics",
            "type":"Manufacturing & Wholesale Goods"
        }
    ],
    "sg:phone":"+33 2 38 34 91 29",
    "sg:postcode":"45330",
    "sg:province":"Centre",
    "sg:tags":[
        "product",
        "part",
        "moulded"
    ],
    "wof:name":"Sami Sa",
    "wof:placetype":"venue"
},
  "geometry": {"coordinates":[2.399498,48.284687],"type":"Point"}
}