{
  "type": "Feature",
  "properties": {
    "iso:country":"FR",
    "sg:address":"Parc Economique de Rorthais 79700 Maul\u00e9on",
    "sg:classifiers":[
        {
            "category":"Manufacturing",
            "subcategory":"Rubber & Plastics",
            "type":"Manufacturing & Wholesale Goods"
        }
    ],
    "sg:phone":"+33 5 49 81 09 67",
    "sg:postcode":"79700",
    "sg:province":"Poitou-Charentes",
    "sg:tags":[
        "injection",
        "moulding",
        "dy"
    ],
    "wof:name":"Micheletti S.a.r.l.",
    "wof:placetype":"venue"
},
  "geometry": {"coordinates":[-0.795684,46.869335],"type":"Point"}
}