{
  "type": "Feature",
  "properties": {
    "addr:full":"Zone Artisanale de Fontvieille - Lot C5 Allauch Provence-Alpes-C\u00f4te d'Azur 13190",
    "addr:postcode":"13190",
    "addr:street":"Zone Artisanale De;C5 Allauch",
    "iso:country":"FR",
    "sg:address":"Zone Artisanale de Fontvieille - Lot C5",
    "sg:city":"Allauch",
    "sg:orig_category":"Unclassifiable Establishments",
    "sg:phone":"+33 4 91 07 37 07",
    "sg:postcode":"13190",
    "sg:province":"Provence-Alpes-C\u00f4te d'Azur",
    "wof:name":"Sapc M\u00e9diterran\u00e9e S.a.r.l.",
    "wof:placetype":"venue"
},
  "geometry": {"coordinates":[5.482075,43.336685],"type":"Point"}
}