{
  "type": "Feature",
  "properties": {
    "addr:full":"59, Rue des Charmettes, 69100 Villeurbanne Rhone-Alpes",
    "addr:housenumber":"59",
    "addr:postcode":"69100",
    "addr:street":"Rue Des Charmettes",
    "iso:country":"FR",
    "sg:address":"59, Rue des Charmettes, 69100 Villeurbanne",
    "sg:orig_category":"Unclassifiable Establishments",
    "sg:phone":"+33 4 78 52 25 76",
    "sg:province":"Rhone-Alpes",
    "wof:name":"S.i.t. S.a. - Soci\u00e9t\u00e9 Industrielle De Transformateurs",
    "wof:placetype":"venue"
},
  "geometry": {"coordinates":[4.867238,45.768509],"type":"Point"}
}