{
  "type": "Feature",
  "properties": {
    "addr:full":"B.P. 157 Annecy C\u00e9dex^^Grandes Teppes 74600 Seynod Rhone-Alpes 74600",
    "addr:housenumber":"b.p. 157",
    "addr:postcode":"74600;74600",
    "addr:street":"Teppes",
    "iso:country":"FR",
    "sg:address":"B.P. 157",
    "sg:city":"Annecy C\u00e9dex^^Grandes Teppes 74600 Seynod",
    "sg:orig_category":"Non-Classified Establishments",
    "sg:phone":"+33 4 50 69 11 96",
    "sg:postcode":"74600",
    "sg:province":"Rhone-Alpes",
    "wof:name":"S.i.c.a. S.a. - Soci\u00e9t\u00e9 Industrielle De Cartonnage",
    "wof:placetype":"venue"
},
  "geometry": {"coordinates":[6.100926,45.888924],"type":"Point"}
}