{
  "type": "Feature",
  "properties": {
    "iso:country":"FR",
    "sg:address":"430, Bd L\u00e9ry, 83140 Six Fours les Plages",
    "sg:orig_category":"Non-Classified Establishments",
    "sg:phone":"+33 4 94 30 19 48",
    "sg:province":"Rhone-Alpes",
    "wof:name":"A.g.e.i.",
    "wof:placetype":"venue"
},
  "geometry": {"coordinates":[5.847682,43.112526],"type":"Point"}
}