{
  "type": "Feature",
  "properties": {
    "iso:country":"FR",
    "sg:address":"B.P. 195, 60306 Senlis C\u00e9dex^^13, Av. F\u00e9lix Louat, 60300 Senlis",
    "sg:orig_category":"Non-Classified Establishments",
    "sg:phone":"+33 3 44 63 80 00",
    "sg:province":"Picardie",
    "wof:name":"Fronius S.a.r.l.",
    "wof:placetype":"venue"
},
  "geometry": {"coordinates":[2.5857,49.206364],"type":"Point"}
}