{
  "type": "Feature",
  "properties": {
    "iso:country":"FR",
    "sg:address":"Bellevue 24240 Monbazillac",
    "sg:city":"Monbazillac",
    "sg:orig_category":"Unclassifiable Establishments",
    "sg:phone":"+33 5 53 57 17 96",
    "sg:postcode":"24240",
    "sg:province":"Aquitaine",
    "wof:name":"Vignobles Lajonie S.a.r.l.",
    "wof:placetype":"venue"
},
  "geometry": {"coordinates":[0.511351,44.798866],"type":"Point"}
}