{
  "type": "Feature",
  "properties": {
    "iso:country":"FR",
    "sg:address":"Immeuble Le Meijetel; BP 11; Les Deux Alpes; 38860",
    "sg:classifiers":[
        {
            "category":"Travel",
            "subcategory":"Travel Agent",
            "type":"Entertainment"
        }
    ],
    "sg:phone":"+33 3347679751",
    "sg:postcode":"38860",
    "sg:province":"Rhone-Alpes",
    "wof:name":"Deux Alpes Voyages",
    "wof:placetype":"venue"
},
  "geometry": {"coordinates":[6.13007,45.035946],"type":"Point"}
}