{
  "type": "Feature",
  "properties": {
    "addr:full":"20, Bd Eug\u00e8ne Deruelle, 69002 Lyon Rhone-Alpes 69002",
    "addr:housenumber":"20",
    "addr:postcode":"69002;69002",
    "addr:street":"Bd Euge\u0300Ne Deruelle",
    "iso:country":"FR",
    "sg:address":"20, Bd Eug\u00e8ne Deruelle, 69002 Lyon",
    "sg:orig_category":"Unclassifiable Establishments",
    "sg:phone":"+33 4 78 14 14 41",
    "sg:postcode":"69002",
    "sg:province":"Rhone-Alpes",
    "wof:name":"Bonna Sabla S.n.c.",
    "wof:placetype":"venue"
},
  "geometry": {"coordinates":[4.853865,45.762825],"type":"Point"}
}