{
  "type": "Feature",
  "properties": {
    "addr:full":"19 Avenue D Ashton Under Lyne 52008 Chaumont Cedex Franche Comt\u00e9",
    "addr:housenumber":"19",
    "addr:postcode":"52008",
    "addr:street":"Avenue D;Under Lyne",
    "iso:country":"FR",
    "sg:address":"19 Avenue D Ashton Under Lyne 52008 Chaumont Cedex",
    "sg:classifiers":[
        {
            "category":"Farming",
            "subcategory":"Livestock Farm",
            "type":"Manufacturing & Wholesale Goods"
        }
    ],
    "sg:phone":"+33 3 25 35 36 40",
    "sg:province":"Franche Comt\u00e9",
    "sg:tags":[
        "agriculture"
    ],
    "wof:name":"Office National Des Forets (onf)",
    "wof:placetype":"venue"
},
  "geometry": {"coordinates":[5.135536,48.110767],"type":"Point"}
}