{
  "type": "Feature",
  "properties": {
    "addr:full":"93 Av De Bobigny 93130 Noisy Le Sec Ile de France 93130",
    "addr:postcode":"93130;93130",
    "addr:street":"93 Av De Bobigny",
    "iso:country":"FR",
    "sg:address":"93 Av De Bobigny 93130 Noisy Le Sec",
    "sg:classifiers":[
        {
            "category":"Professional",
            "subcategory":"Printing & Photocopies",
            "type":"Services"
        }
    ],
    "sg:phone":"+33 1 48 91 23 95",
    "sg:postcode":"93130",
    "sg:province":"Ile de France",
    "sg:tags":[
        "information",
        "technology",
        "publishing",
        "software"
    ],
    "wof:name":"Cogifa",
    "wof:placetype":"venue"
},
  "geometry": {"coordinates":[2.446533,48.89455],"type":"Point"}
}