{
  "type": "Feature",
  "properties": {
    "addr:full":"50 Rue D Hauteville 75010 Paris Ile de France 75010",
    "addr:housenumber":"50",
    "addr:postcode":"75010;75010",
    "addr:street":"Rue D",
    "iso:country":"FR",
    "sg:address":"50 Rue D Hauteville 75010 Paris",
    "sg:classifiers":[
        {
            "category":"Farming",
            "subcategory":"Livestock Farm",
            "type":"Manufacturing & Wholesale Goods"
        }
    ],
    "sg:phone":"+33 1 42 46 95 26",
    "sg:postcode":"75010",
    "sg:province":"Ile de France",
    "sg:tags":[
        "breeding",
        "agriculture",
        "animal"
    ],
    "wof:name":"Poucci",
    "wof:placetype":"venue"
},
  "geometry": {"coordinates":[2.350806,48.874123],"type":"Point"}
}