{
  "type": "Feature",
  "properties": {
    "addr:full":"39 Rue De La Gare De Reuilly 75012 Paris Ile de France 75012",
    "addr:housenumber":"39",
    "addr:postcode":"75012;75012",
    "addr:street":"Rue De La Gare De Reuilly",
    "iso:country":"FR",
    "sg:address":"39 Rue De La Gare De Reuilly 75012 Paris",
    "sg:classifiers":[
        {
            "category":"Farming",
            "subcategory":"Farm & Veterinary Services",
            "type":"Manufacturing & Wholesale Goods"
        }
    ],
    "sg:phone":"+33 1 53 17 11 50",
    "sg:postcode":"75012",
    "sg:province":"Ile de France",
    "sg:tags":[
        "advice",
        "agriculture",
        "livestock",
        "business"
    ],
    "wof:name":"Lacema",
    "wof:placetype":"venue"
},
  "geometry": {"coordinates":[2.395983,48.842159],"type":"Point"}
}