{
  "type": "Feature",
  "properties": {
    "iso:country":"FR",
    "sg:address":"6 chemin d'Auguste 33610 Cestas",
    "sg:city":"Cestas",
    "sg:classifiers":[
        {
            "category":"Ice Cream",
            "type":"Food & Drink"
        }
    ],
    "sg:phone":"+33 5 56 68 00 25",
    "sg:postcode":"33610",
    "sg:province":"Aquitaine",
    "sg:tags":[
        "sugar"
    ],
    "wof:name":"Sucre Distribution S.a.",
    "wof:placetype":"venue"
},
  "geometry": {"coordinates":[-0.715478,44.763626],"type":"Point"}
}