{
  "type": "Feature",
  "properties": {
    "addr:full":"Rte de Busci\u00e8re Dange Saint Romain Poitou-Charentes 86220",
    "addr:postcode":"86220",
    "addr:street":"Rte De Buscie\u0300Re;Romain",
    "iso:country":"FR",
    "sg:address":"Rte de Busci\u00e8re",
    "sg:city":"Dange Saint Romain",
    "sg:orig_category":"Unclassifiable Establishments",
    "sg:phone":"+33 5 49 86 32 86",
    "sg:postcode":"86220",
    "sg:province":"Poitou-Charentes",
    "wof:name":"D\u00e9cap'center S.a.r.l.",
    "wof:placetype":"venue"
},
  "geometry": {"coordinates":[0.628151,46.872829],"type":"Point"}
}