{
  "type": "Feature",
  "properties": {
    "addr:full":"18 Rue Amsterdam 75009 Paris Ile de France 75009",
    "addr:housenumber":"18",
    "addr:postcode":"75009;75009",
    "addr:street":"Rue Amsterdam",
    "iso:country":"FR",
    "sg:address":"18 Rue Amsterdam 75009 Paris",
    "sg:classifiers":[
        {
            "category":"Travel",
            "subcategory":"Hotels & Motels",
            "type":"Entertainment"
        }
    ],
    "sg:phone":"+33 1 42 85 72 74",
    "sg:postcode":"75009",
    "sg:province":"Ile de France",
    "sg:tags":[
        "hotels",
        "business",
        "restaurant"
    ],
    "wof:name":"Hotel Du Havre",
    "wof:placetype":"venue"
},
  "geometry": {"coordinates":[2.327082,48.876652],"type":"Point"}
}