{
  "type": "Feature",
  "properties": {
    "iso:country":"FR",
    "sg:address":"53, Av. Pasteur, 93260 Les Lilas",
    "sg:orig_category":"Non-Classified Establishments",
    "sg:phone":"+33 1 48 97 87 07",
    "sg:province":"Ile de France",
    "wof:name":"Expo Surveillance S.a.",
    "wof:placetype":"venue"
},
  "geometry": {"coordinates":[2.41246,48.876835],"type":"Point"}
}