{
  "type": "Feature",
  "properties": {
    "addr:full":"Bourg 49124 Le Plessis Grammoire Pays de Loire 49124",
    "addr:postcode":"49124;49124",
    "addr:street":"Bourg",
    "iso:country":"FR",
    "sg:address":"Bourg 49124 Le Plessis Grammoire",
    "sg:classifiers":[
        {
            "category":"Education",
            "subcategory":"Special Training",
            "type":"Public Place"
        }
    ],
    "sg:phone":"+33 2 41 76 72 10",
    "sg:postcode":"49124",
    "sg:province":"Pays de Loire",
    "sg:tags":[
        "pharmaceutical",
        "livestock",
        "animal",
        "chemical",
        "grain",
        "cereal",
        "breeding",
        "chem",
        "agriculture"
    ],
    "wof:name":"Caval",
    "wof:placetype":"venue"
},
  "geometry": {"coordinates":[-0.494339,47.468246],"type":"Point"}
}