{
  "type": "Feature",
  "properties": {
    "addr:full":"110 Rue Du Pdt Faure 74800 La Roche Sur Foron Rhone-Alpes 74800",
    "addr:housenumber":"110",
    "addr:postcode":"74800;74800",
    "addr:street":"Rue Du Pdt Faure",
    "iso:country":"FR",
    "sg:address":"110 Rue Du Pdt Faure 74800 La Roche Sur Foron",
    "sg:classifiers":[
        {
            "category":"Shopping",
            "subcategory":"Computers & Home Electronics",
            "type":"Retail Goods"
        }
    ],
    "sg:phone":"+33 4 50 03 43 76",
    "sg:postcode":"74800",
    "sg:province":"Rhone-Alpes",
    "sg:tags":[
        "equipment",
        "household",
        "electrical",
        "appliance",
        "electronic"
    ],
    "wof:name":"Sarl Moltronic",
    "wof:placetype":"venue"
},
  "geometry": {"coordinates":[6.307706,46.067097],"type":"Point"}
}