{
  "type": "Feature",
  "properties": {
    "iso:country":"FR",
    "sg:address":"B.P. 14, 33886 Villenave d'Orgnon C\u00e9dex^^9, Chemin Touton, 33880 Villenave d'Ornon",
    "sg:city":"Baurech",
    "sg:orig_category":"Non-Classified Establishments",
    "sg:phone":"+33 5 56 87 71 40",
    "sg:postcode":"33880",
    "sg:province":"Aquitaine",
    "wof:name":"Salprolait Boedeaux S.n.c.",
    "wof:placetype":"venue"
},
  "geometry": {"coordinates":[-0.541576,44.773445],"type":"Point"}
}