{
  "type": "Feature",
  "properties": {
    "addr:full":"2 Rue Commdt Charcot 76310 Ste Adresse Haute Normandie",
    "addr:housenumber":"2",
    "addr:postcode":"76310",
    "addr:street":"Rue Commdt Charcot;Haute Normandie",
    "iso:country":"FR",
    "sg:address":"2 Rue Commdt Charcot 76310 Ste Adresse",
    "sg:classifiers":[
        {
            "category":"Manufacturing",
            "subcategory":"Paper Products",
            "type":"Manufacturing & Wholesale Goods"
        }
    ],
    "sg:phone":"+33 2 35 54 32 52",
    "sg:province":"Haute Normandie",
    "sg:tags":[
        "finished",
        "cardboard",
        "-"
    ],
    "wof:name":"Etablissements Bouilliaud Sa",
    "wof:placetype":"venue"
},
  "geometry": {"coordinates":[0.073825,49.511536],"type":"Point"}
}