{
  "type": "Feature",
  "properties": {
    "iso:country":"FR",
    "sg:address":"ZAC du Mardaric",
    "sg:city":"Peyruis",
    "sg:orig_category":"Non-Classified Establishments",
    "sg:phone":"+33 4 92 68 07 08",
    "sg:postcode":"04310",
    "sg:province":"Aquitaine",
    "wof:name":"04 Express S.a.r.l.",
    "wof:placetype":"venue"
},
  "geometry": {"coordinates":[5.936729,44.026161],"type":"Point"}
}