{
  "type": "Feature",
  "properties": {
    "addr:full":"Grande Rue 54740 Benney Lorraine 54740",
    "addr:postcode":"54740;54740",
    "addr:street":"Grande Rue",
    "iso:country":"FR",
    "sg:address":"Grande Rue 54740 Benney",
    "sg:classifiers":[
        {
            "category":"Shopping",
            "type":"Retail Goods"
        }
    ],
    "sg:phone":"+33 3 83 25 01 45",
    "sg:postcode":"54740",
    "sg:province":"Lorraine",
    "sg:tags":[
        "metallurgy",
        "finished",
        "-",
        "metalworking",
        "metallic"
    ],
    "wof:name":"Transforebo",
    "wof:placetype":"venue"
},
  "geometry": {"coordinates":[6.219498,48.513519],"type":"Point"}
}