{
  "type": "Feature",
  "properties": {
    "addr:full":"19 Rue De Prague 75012 Paris Ile de France 75012",
    "addr:housenumber":"19",
    "addr:postcode":"75012;75012",
    "addr:street":"Rue De Prague",
    "iso:country":"FR",
    "sg:address":"19 Rue De Prague 75012 Paris",
    "sg:classifiers":[
        {
            "category":"Transit Center",
            "subcategory":"Freight",
            "type":"Transportation"
        }
    ],
    "sg:phone":"+33 1 43 07 58 65",
    "sg:postcode":"75012",
    "sg:province":"Ile de France",
    "sg:tags":[
        "metallurgy",
        "pipe",
        "metalworking",
        "sheet"
    ],
    "wof:name":"Adesol Tego Sarl",
    "wof:placetype":"venue"
},
  "geometry": {"coordinates":[2.375569,48.850292],"type":"Point"}
}