{
  "type": "Feature",
  "properties": {
    "iso:country":"FR",
    "sg:address":"ZA de Kerj\u00e9gu",
    "sg:city":"Ch\u00e2teauneuf du Faou",
    "sg:orig_category":"Unclassifiable Establishments",
    "sg:phone":"+33 2 98 81 78 05",
    "sg:postcode":"29520",
    "sg:province":"Bretagne",
    "wof:name":"Kastell Klinos S.a.",
    "wof:placetype":"venue"
},
  "geometry": {"coordinates":[-3.814039,48.186878],"type":"Point"}
}