{
  "type": "Feature",
  "properties": {
    "addr:full":"15 Rte De Fo\u00ebcy 18100 Vierzon Vierzon Centre 18100",
    "addr:housenumber":"15;vierzon",
    "addr:postcode":"18100;18100",
    "addr:street":"Rte De Foe\u0308Cy",
    "iso:country":"FR",
    "sg:address":"15 Rte De Fo\u00ebcy 18100 Vierzon",
    "sg:city":"Vierzon",
    "sg:orig_category":"Chemicals and Pharmaceuticals Energy Energy and Raw Materials Pharmacy",
    "sg:phone":"+33 2 48 52 95 95",
    "sg:postcode":"18100",
    "sg:province":"Centre",
    "wof:name":"Pica",
    "wof:placetype":"venue"
},
  "geometry": {"coordinates":[2.100676,47.211796],"type":"Point"}
}