{
  "type": "Feature",
  "properties": {
    "iso:country":"FR",
    "sg:address":"10 Rue Grande 77123 Noisy Sur \u00c9cole",
    "sg:classifiers":[
        {
            "category":"Professional",
            "subcategory":"Engineering",
            "type":"Services"
        }
    ],
    "sg:phone":"+33 1 64 24 52 69",
    "sg:postcode":"77123",
    "sg:province":"Ile de France",
    "sg:tags":[
        "machine",
        "-",
        "environment",
        "equipment",
        "machinery",
        "mechanical"
    ],
    "wof:name":"Henry Sarl",
    "wof:placetype":"venue"
},
  "geometry": {"coordinates":[2.49841,48.37141],"type":"Point"}
}