{
  "type": "Feature",
  "properties": {
    "iso:country":"FR",
    "sg:address":"13, Rue Moissons des Roches, 42600 Montbrison",
    "sg:orig_category":"Unclassifiable Establishments",
    "sg:phone":"+33 4 77 58 73 00",
    "sg:postcode":"42600",
    "sg:province":"Rhone-Alpes",
    "wof:name":"Vaco France S.a.",
    "wof:placetype":"venue"
},
  "geometry": {"coordinates":[4.079849,45.601959],"type":"Point"}
}