{
  "type": "Feature",
  "properties": {
    "addr:full":"Rte de Saint V\u00e9rain Arquian Bourgogne 58310",
    "addr:postcode":"58310",
    "addr:street":"Rte De Saint;Bourgogne",
    "iso:country":"FR",
    "sg:address":"Rte de Saint V\u00e9rain",
    "sg:city":"Arquian",
    "sg:orig_category":"Unclassifiable Establishments",
    "sg:phone":"+33 3 86 39 67 63",
    "sg:postcode":"58310",
    "sg:province":"Bourgogne",
    "wof:name":"M\u00e9canique De Pr\u00e9cision Alain Le Batard",
    "wof:placetype":"venue"
},
  "geometry": {"coordinates":[3.035907,47.535851],"type":"Point"}
}