{
  "type": "Feature",
  "properties": {
    "addr:full":"Rue de Plouvier Templemars Nord Pas-de-Calais 59175",
    "addr:postcode":"59175",
    "addr:street":"Rue De Plouvier Templemars Nord",
    "iso:country":"FR",
    "sg:address":"Rue de Plouvier",
    "sg:city":"Templemars",
    "sg:orig_category":"Non-Classified Establishments",
    "sg:phone":"+33 3 28 55 22 00",
    "sg:postcode":"59175",
    "sg:province":"Nord Pas-de-Calais",
    "wof:name":"Technal S.a.",
    "wof:placetype":"venue"
},
  "geometry": {"coordinates":[3.06484,50.565056],"type":"Point"}
}