{
  "type": "Feature",
  "properties": {
    "addr:full":"1 Ave De Fontreal Eurocentre 31620 Villeneuve Les Bouloc Midi Pyr\u00e9n\u00e9es 31620",
    "addr:postcode":"31620;31620",
    "addr:street":"1 Ave De Fontreal Eurocentre",
    "iso:country":"FR",
    "sg:address":"1 Ave De Fontreal Eurocentre 31620 Villeneuve Les Bouloc",
    "sg:classifiers":[
        {
            "category":"Food & Beverages",
            "subcategory":"Dairy",
            "type":"Retail Goods"
        }
    ],
    "sg:phone":"+33 5 34 27 21 11",
    "sg:postcode":"31620",
    "sg:province":"Midi Pyr\u00e9n\u00e9es",
    "sg:tags":[
        "product",
        "related"
    ],
    "wof:name":"Danone",
    "wof:placetype":"venue"
},
  "geometry": {"coordinates":[1.470783,43.738724],"type":"Point"}
}