{
  "type": "Feature",
  "properties": {
    "addr:full":"2, Rue Charles Heller, 94400 Vitry sur Seine Ile de France",
    "addr:housenumber":"2",
    "addr:postcode":"94400",
    "addr:street":"Rue Charles Heller",
    "iso:country":"FR",
    "sg:address":"2, Rue Charles Heller, 94400 Vitry sur Seine",
    "sg:orig_category":"Unclassifiable Establishments",
    "sg:phone":"+33 1 45 73 41 00",
    "sg:province":"Ile de France",
    "wof:name":"S.p.a.p.a. S.a. - Soci\u00e9t\u00e9 De Pavage Et Des Asphaltes De Paris",
    "wof:placetype":"venue"
},
  "geometry": {"coordinates":[2.41229,48.787933],"type":"Point"}
}