{
  "type": "Feature",
  "properties": {
    "addr:full":"1 Bd Gambetta 69220 Belleville Rhone-Alpes 69220",
    "addr:housenumber":"1",
    "addr:postcode":"69220;69220",
    "addr:street":"Bd Gambetta",
    "iso:country":"FR",
    "sg:address":"1 Bd Gambetta 69220 Belleville",
    "sg:classifiers":[
        {
            "category":"Professional",
            "subcategory":"Engineering",
            "type":"Services"
        }
    ],
    "sg:phone":"+33 4 74 69 61 61",
    "sg:postcode":"69220",
    "sg:province":"Rhone-Alpes",
    "sg:tags":[
        "machine",
        "-",
        "mechanical"
    ],
    "wof:name":"Camus Industrie Sa",
    "wof:placetype":"venue"
},
  "geometry": {"coordinates":[4.732935,46.108799],"type":"Point"}
}