{
  "type": "Feature",
  "properties": {
    "iso:country":"FR",
    "sg:address":"46, Rue de la T\u00e9l\u00e9matique - Immeuble le Polygone, 42000 Saint Etienne",
    "sg:orig_category":"Unclassifiable Establishments",
    "sg:phone":"+33 4 77 92 34 34",
    "sg:province":"Rhone-Alpes",
    "wof:name":"Gr Da Communication S.a.r.l.",
    "wof:placetype":"venue"
},
  "geometry": {"coordinates":[4.396167,45.45747],"type":"Point"}
}