{
  "type": "Feature",
  "properties": {
    "addr:full":"ZAC de Beaulieu - B\u00e2t. l'Etage Puilboreau Poitou-Charentes 17138",
    "addr:housenumber":"ba\u0302t",
    "addr:postcode":"17138",
    "addr:street":"Zac De Beaulieu;Puilboreau",
    "iso:country":"FR",
    "sg:address":"ZAC de Beaulieu - B\u00e2t. l'Etage",
    "sg:city":"Puilboreau",
    "sg:orig_category":"Unclassifiable Establishments",
    "sg:phone":"+33 5 46 67 72 00",
    "sg:postcode":"17138",
    "sg:province":"Poitou-Charentes",
    "wof:name":"Scati La Rochelle S.a.",
    "wof:placetype":"venue"
},
  "geometry": {"coordinates":[-2.214802,47.375622],"type":"Point"}
}