{
  "type": "Feature",
  "properties": {
    "iso:country":"FR",
    "sg:address":"ZAC de Chalan\u00e7on 2",
    "sg:city":"V\u00e9d\u00e8ne",
    "sg:orig_category":"Unclassifiable Establishments",
    "sg:phone":"+33 4 90 31 17 84",
    "sg:postcode":"84270",
    "sg:province":"Midi Pyr\u00e9n\u00e9es",
    "wof:name":"V.t.v. S.a.r.l. - V\u00e9d\u00e8ne Transports Volumineux",
    "wof:placetype":"venue"
},
  "geometry": {"coordinates":[4.905397,43.977158],"type":"Point"}
}