{
  "type": "Feature",
  "properties": {
    "iso:country":"FR",
    "sg:address":"Plati\u00e8res 71290 Cuisery",
    "sg:city":"Cuisery",
    "sg:classifiers":[
        {
            "category":"Food & Beverages",
            "subcategory":"Meat & Fish",
            "type":"Retail Goods"
        }
    ],
    "sg:phone":"+33 3 85 32 28 40",
    "sg:postcode":"71290",
    "sg:province":"Bourgogne",
    "sg:tags":[
        "domestic",
        "animal"
    ],
    "wof:name":"Girard Et Cie Sa",
    "wof:placetype":"venue"
},
  "geometry": {"coordinates":[4.999224,46.553257],"type":"Point"}
}