{
  "type": "Feature",
  "properties": {
    "iso:country":"FR",
    "sg:address":"Le Fenouiller 85800 St Gilles Croix De Vie",
    "sg:classifiers":[
        {
            "category":"Professional",
            "type":"Services"
        }
    ],
    "sg:phone":"+33 2 51 55 54 07",
    "sg:province":"Pays de Loire",
    "sg:tags":[
        "transport",
        "road"
    ],
    "wof:name":"Augizeau Transports",
    "wof:placetype":"venue"
},
  "geometry": {"coordinates":[-1.90107,46.719631],"type":"Point"}
}