{
  "type": "Feature",
  "properties": {
    "addr:full":"50 rue du G\u00e9n\u00e9ral Chanzy 59100 Roubaix Nord Pas-de-Calais 59100",
    "addr:housenumber":"50",
    "addr:postcode":"59100;59100",
    "addr:street":"Rue Du Ge\u0301Ne\u0301Ral Chanzy",
    "iso:country":"FR",
    "sg:address":"50 rue du G\u00e9n\u00e9ral Chanzy 59100 Roubaix",
    "sg:classifiers":[
        {
            "category":"Organizations",
            "subcategory":"Professional Association",
            "type":"Services"
        }
    ],
    "sg:phone":"+33 3 20 89 42 50",
    "sg:postcode":"59100",
    "sg:province":"Nord Pas-de-Calais",
    "sg:tags":[
        "darning",
        "yarn"
    ],
    "wof:name":"Lebaufil Sa",
    "wof:placetype":"venue"
},
  "geometry": {"coordinates":[3.175629,50.685085],"type":"Point"}
}