{
  "type": "Feature",
  "properties": {
    "addr:full":"13, Rue Jules Verne - ZI de l'Hippodrome, 29000 Quimper Quimper Bretagne 29000",
    "addr:housenumber":"13",
    "addr:postcode":"29000;29000",
    "addr:street":"Rue Jules Verne Zi De L'Hippodrome",
    "iso:country":"FR",
    "sg:address":"13, Rue Jules Verne - ZI de l'Hippodrome, 29000 Quimper",
    "sg:city":"Quimper",
    "sg:orig_category":"Unclassifiable Establishments",
    "sg:phone":"+33 2 98 52 01 02",
    "sg:postcode":"29000",
    "sg:province":"Bretagne",
    "wof:name":"Dourmap",
    "wof:placetype":"venue"
},
  "geometry": {"coordinates":[-4.070981,47.995804],"type":"Point"}
}