{
  "type": "Feature",
  "properties": {
    "iso:country":"FR",
    "sg:address":"23 rue Ren\u00e9 Goubin; Loperhet",
    "sg:city":"Loperhet",
    "sg:classifiers":[
        {
            "category":"Banks & Credit Unions",
            "subcategory":"Bank",
            "type":"Services"
        }
    ],
    "sg:phone":"+33 3398070312",
    "sg:postcode":"29470",
    "sg:province":"Bretagne",
    "wof:name":"Cr\u00e9dit Agricole Mutuel",
    "wof:placetype":"venue"
},
  "geometry": {"coordinates":[-4.30734,48.375828],"type":"Point"}
}