{
  "type": "Feature",
  "properties": {
    "addr:full":"B.P. 2019, 66011 Perpignan C\u00e9dex^^March\u00e9 Saint Charles - Mag. 14 \u00e0 16, 66000 Perpignan Languedoc-Roussillon",
    "addr:housenumber":"14 a\u0300 16",
    "addr:postcode":"66011;66000",
    "addr:street":"B.P. 2019",
    "iso:country":"FR",
    "sg:address":"B.P. 2019, 66011 Perpignan C\u00e9dex^^March\u00e9 Saint Charles - Mag. 14 \u00e0 16, 66000 Perpignan",
    "sg:orig_category":"Non-Classified Establishments",
    "sg:phone":"+33 4 68 68 35 35",
    "sg:province":"Languedoc-Roussillon",
    "wof:name":"Faus Dura S.a.",
    "wof:placetype":"venue"
},
  "geometry": {"coordinates":[2.88743,42.69812],"type":"Point"}
}