{
  "type": "Feature",
  "properties": {
    "addr:full":"ZI Carrefour de l'Europe Forbach Lorraine 57600",
    "addr:postcode":"57600",
    "addr:street":"Carrefour De L'Europe",
    "iso:country":"FR",
    "sg:address":"ZI Carrefour de l'Europe",
    "sg:city":"Forbach",
    "sg:orig_category":"Unclassifiable Establishments",
    "sg:phone":"+33 3 87 87 71 26",
    "sg:postcode":"57600",
    "sg:province":"Lorraine",
    "wof:name":"Weber Technologie S.a.r.l.",
    "wof:placetype":"venue"
},
  "geometry": {"coordinates":[6.89571,49.171749],"type":"Point"}
}