{
  "type": "Feature",
  "properties": {
    "iso:country":"FR",
    "sg:address":"Rue Avenir 52200 Saints Geosmes",
    "sg:classifiers":[
        {
            "category":"Manufacturing",
            "subcategory":"Printing",
            "type":"Manufacturing & Wholesale Goods"
        }
    ],
    "sg:phone":"+33 3 25 87 04 21",
    "sg:province":"Champagne",
    "sg:tags":[
        "publishing"
    ],
    "wof:name":"Idg",
    "wof:placetype":"venue"
},
  "geometry": {"coordinates":[5.336805,47.831547],"type":"Point"}
}