{
  "type": "Feature",
  "properties": {
    "iso:country":"FR",
    "sg:address":"9 Pl Du Gal Leclerc 92300 Levallois Perret",
    "sg:classifiers":[
        {
            "category":"Banks & Credit Unions",
            "subcategory":"Financial Services",
            "type":"Services"
        }
    ],
    "sg:phone":"+33 1 47 15 27 20",
    "sg:postcode":"92300",
    "sg:province":"Ile de France",
    "sg:tags":[
        "banking",
        "insurance",
        "institution",
        "finance"
    ],
    "wof:name":"Societe Generale",
    "wof:placetype":"venue"
},
  "geometry": {"coordinates":[2.285035,48.892284],"type":"Point"}
}