{
  "type": "Feature",
  "properties": {
    "iso:country":"FR",
    "sg:address":"19, Rue Cassini, 60250 Mouy",
    "sg:orig_category":"Non-Classified Establishments",
    "sg:phone":"+33 3 44 56 12 33",
    "sg:province":"Picardie",
    "wof:name":"Idegrif S.a.r.l.",
    "wof:placetype":"venue"
},
  "geometry": {"coordinates":[2.322815,49.320976],"type":"Point"}
}