{
  "type": "Feature",
  "properties": {
    "addr:full":"1, Av. Henri Debord, 18230 Saint Doulchard Saint-Doulchard Centre 18230",
    "addr:postcode":"18230;18230",
    "addr:street":"Av. Henri Debord",
    "iso:country":"FR",
    "sg:address":"1, Av. Henri Debord, 18230 Saint Doulchard",
    "sg:city":"Saint-Doulchard",
    "sg:orig_category":"Unclassifiable Establishments",
    "sg:phone":"+33 2 48 23 00 50",
    "sg:postcode":"18230",
    "sg:province":"Centre",
    "wof:name":"S.n.e.f. S.a.",
    "wof:placetype":"venue"
},
  "geometry": {"coordinates":[2.372717,47.095779],"type":"Point"}
}