{
  "type": "Feature",
  "properties": {
    "addr:full":"3 Rte De Pau 65000 Tarbes Midi Pyr\u00e9n\u00e9es 65000",
    "addr:housenumber":"3",
    "addr:postcode":"65000;65000",
    "addr:street":"Rte De Pau",
    "iso:country":"FR",
    "sg:address":"3 Rte De Pau 65000 Tarbes",
    "sg:classifiers":[
        {
            "category":"Manufacturing",
            "subcategory":"Metals",
            "type":"Manufacturing & Wholesale Goods"
        }
    ],
    "sg:phone":"+33 5 62 93 98 11",
    "sg:postcode":"65000",
    "sg:province":"Midi Pyr\u00e9n\u00e9es",
    "sg:tags":[
        "-",
        "machine",
        "equipment",
        "engineering",
        "machinery",
        "mechanical"
    ],
    "wof:name":"Mopa Outillage Pyrenees Affutage Sarl",
    "wof:placetype":"venue"
},
  "geometry": {"coordinates":[0.044898,43.237488],"type":"Point"}
}