{
  "type": "Feature",
  "properties": {
    "iso:country":"FR",
    "sg:address":"Plaine de la Bache",
    "sg:city":"Estipouy",
    "sg:orig_category":"Unclassifiable Establishments",
    "sg:phone":"+33 5 62 66 51 19",
    "sg:postcode":"32300",
    "sg:province":"Midi Pyr\u00e9n\u00e9es",
    "wof:name":"Soci\u00e9t\u00e9 Nouvelle Des Biscuits Bertin S.a.r.l.",
    "wof:placetype":"venue"
},
  "geometry": {"coordinates":[0.410443,43.53849],"type":"Point"}
}