{
  "type": "Feature",
  "properties": {
    "addr:full":"B.P. 611, 85306 Challans C\u00e9dex^^Chemin du Pas, 85300 Challans Pays de Loire 85300",
    "addr:housenumber":"b.p. 611",
    "addr:postcode":"85306;85300;85300",
    "addr:street":"Pas",
    "iso:country":"FR",
    "sg:address":"B.P. 611, 85306 Challans C\u00e9dex^^Chemin du Pas, 85300 Challans",
    "sg:orig_category":"Non-Classified Establishments",
    "sg:phone":"+33 2 51 68 05 31",
    "sg:postcode":"85300",
    "sg:province":"Pays de Loire",
    "wof:name":"Atlantique Paysage S.a.",
    "wof:placetype":"venue"
},
  "geometry": {"coordinates":[-1.879324,46.845879],"type":"Point"}
}