{
  "type": "Feature",
  "properties": {
    "iso:country":"FR",
    "sg:address":"29, Rue Voltaire, 08500 Revin",
    "sg:city":"Les Mazures",
    "sg:orig_category":"Unclassifiable Establishments",
    "sg:phone":"+33 3 24 40 38 90",
    "sg:postcode":"08500",
    "sg:province":"Champagne",
    "wof:name":"Serumeta S.a.r.l.",
    "wof:placetype":"venue"
},
  "geometry": {"coordinates":[4.64294,49.936192],"type":"Point"}
}