{
  "type": "Feature",
  "properties": {
    "iso:country":"FR",
    "sg:address":"2, Rue de l'Industrie, 45073 Orl\u00e9ans C\u00e9dex 2",
    "sg:orig_category":"Non-Classified Establishments",
    "sg:phone":"+33 2 38 76 38 76",
    "sg:province":"Centre",
    "wof:name":"Metz S.a.",
    "wof:placetype":"venue"
},
  "geometry": {"coordinates":[1.920786,47.866474],"type":"Point"}
}