{
  "type": "Feature",
  "properties": {
    "addr:full":"2, Rue Etienne Dolet, 08330 Vrigne aux Bois Champagne",
    "addr:housenumber":"2",
    "addr:postcode":"08330",
    "addr:street":"Rue Etienne Dolet;Aux Bois Champagne",
    "iso:country":"FR",
    "sg:address":"2, Rue Etienne Dolet, 08330 Vrigne aux Bois",
    "sg:orig_category":"PAUMELLES DE B\u00c2TIMENTS, CR\u00c9MONES, ARR\u00caTS POUR PERSIENNES OU VOLETS, GALETS, POULIES, ARR\u00caTS DE GRILL",
    "sg:phone":"+33 3 24 52 32 01",
    "sg:province":"Champagne",
    "wof:name":"Jardinier Massard S.a.",
    "wof:placetype":"venue"
},
  "geometry": {"coordinates":[4.854443,49.736938],"type":"Point"}
}