{
  "type": "Feature",
  "properties": {
    "iso:country":"FR",
    "sg:address":"Rue Louis Farges 15000 Aurillac",
    "sg:city":"Aurillac",
    "sg:classifiers":[
        {
            "category":"Professional",
            "subcategory":"Business Services",
            "type":"Services"
        }
    ],
    "sg:phone":"+33 4 71 48 20 15",
    "sg:postcode":"15000",
    "sg:province":"Auvergne",
    "sg:tags":[
        "training",
        "advice"
    ],
    "wof:name":"Etablissement Albert Monier",
    "wof:placetype":"venue"
},
  "geometry": {"coordinates":[2.455334,44.939991],"type":"Point"}
}