{
  "type": "Feature",
  "properties": {
    "addr:full":"B.P. 9 Etreux Picardie 02510",
    "addr:postcode":"02510",
    "addr:street":"B.P. 9 Etreux Picardie",
    "iso:country":"FR",
    "sg:address":"B.P. 9",
    "sg:city":"Etreux",
    "sg:orig_category":"Non-Classified Establishments",
    "sg:phone":"+33 3 23 60 30 00",
    "sg:postcode":"02510",
    "sg:province":"Picardie",
    "wof:name":"Barelec S.a.",
    "wof:placetype":"venue"
},
  "geometry": {"coordinates":[3.657125,49.995533],"type":"Point"}
}