{
  "type": "Feature",
  "properties": {
    "iso:country":"FR",
    "sg:address":"41 Av Jean Jaur\u00e8s 67100 Strasbourg",
    "sg:city":"Strasbourg",
    "sg:classifiers":[
        {
            "category":"Professional",
            "subcategory":"Computer Services",
            "type":"Services"
        }
    ],
    "sg:phone":"+33 3 88 44 96 10",
    "sg:postcode":"67100",
    "sg:province":"Alsace",
    "sg:tags":[
        "information",
        "technology",
        "software"
    ],
    "wof:name":"Perez Informatique Sa",
    "wof:placetype":"venue"
},
  "geometry": {"coordinates":[7.76598,48.569046],"type":"Point"}
}