{
  "type": "Feature",
  "properties": {
    "iso:country":"FR",
    "sg:address":"Rue Thal\u00e8s 25410 Dannemarie Sur Cr\u00eate",
    "sg:classifiers":[
        {
            "category":"Manufacturing",
            "subcategory":"Tools & Machinery",
            "type":"Manufacturing & Wholesale Goods"
        }
    ],
    "sg:phone":"+33 3 81 58 62 92",
    "sg:postcode":"25410",
    "sg:province":"Franche Comt\u00e9",
    "sg:tags":[
        "metallurgy",
        "metalworking"
    ],
    "wof:name":"Ste D Exploit Ateliers Leboeuf",
    "wof:placetype":"venue"
},
  "geometry": {"coordinates":[5.882455,47.204224],"type":"Point"}
}