{
  "type": "Feature",
  "properties": {
    "iso:country":"FR",
    "sg:address":"8 rue Raoul Follereau 38170 Seyssinet Pariset",
    "sg:classifiers":[
        {
            "category":"Professional",
            "subcategory":"Engineering",
            "type":"Services"
        }
    ],
    "sg:phone":"+33 4 76 84 23 20",
    "sg:province":"Rhone-Alpes",
    "sg:tags":[
        "plant",
        "construction",
        "safety",
        "module",
        "mechanical"
    ],
    "wof:name":"Automatisme Et Contr\u00f4le Sa",
    "wof:placetype":"venue"
},
  "geometry": {"coordinates":[5.696125,45.180908],"type":"Point"}
}