{
  "type": "Feature",
  "properties": {
    "addr:full":"B.P. 5 Kilstett Alsace 67840",
    "addr:postcode":"67840",
    "addr:street":"B.P. 5",
    "iso:country":"FR",
    "sg:address":"B.P. 5",
    "sg:city":"Kilstett",
    "sg:orig_category":"Non-Classified Establishments",
    "sg:phone":"+33 3 88 96 38 56",
    "sg:postcode":"67840",
    "sg:province":"Alsace",
    "wof:name":"Spimat T.h.p. S.a.r.l.",
    "wof:placetype":"venue"
},
  "geometry": {"coordinates":[7.857985,48.674736],"type":"Point"}
}