{
  "type": "Feature",
  "properties": {
    "iso:country":"FR",
    "sg:address":"Carrefour des Estuaires",
    "sg:city":"Derval",
    "sg:orig_category":"Non-Classified Establishments",
    "sg:phone":"+33 2 40 79 41 97",
    "sg:postcode":"44590",
    "sg:province":"Pays de Loire",
    "wof:name":"Salaisons Du Castel S.a.",
    "wof:placetype":"venue"
},
  "geometry": {"coordinates":[-1.658912,47.647388],"type":"Point"}
}