{
  "type": "Feature",
  "properties": {
    "addr:full":"550, Rue Alfred Nobel - Parc Club du Mill\u00e9naire, 34000 Montpellier Languedoc-Roussillon",
    "addr:housenumber":"550",
    "addr:postcode":"34000",
    "addr:street":"Rue Alfred Nobel Parc Club Du Mille\u0301Naire",
    "iso:country":"FR",
    "sg:address":"550, Rue Alfred Nobel - Parc Club du Mill\u00e9naire, 34000 Montpellier",
    "sg:orig_category":"Non-Classified Establishments",
    "sg:phone":"+33 4 67 15 45 75",
    "sg:province":"Languedoc-Roussillon",
    "wof:name":"Fac Simil\u00e9 Languedoc Roussillon S.a.",
    "wof:placetype":"venue"
},
  "geometry": {"coordinates":[3.91237,43.611454],"type":"Point"}
}