{
  "type": "Feature",
  "properties": {
    "addr:full":"B.P. 111000, 13793 Aix en Provence C\u00e9dex 03^^Parc Club du Golf - B\u00e2t 19, 13790 Aix en Provence Languedoc-Roussillon",
    "addr:housenumber":"111000;19",
    "addr:postcode":"13793;13790",
    "addr:street":"En",
    "iso:country":"FR",
    "sg:address":"B.P. 111000, 13793 Aix en Provence C\u00e9dex 03^^Parc Club du Golf - B\u00e2t 19, 13790 Aix en Provence",
    "sg:orig_category":"Non-Classified Establishments",
    "sg:phone":"+33 4 42 24 27 66",
    "sg:province":"Languedoc-Roussillon",
    "wof:name":"L.p.f. S.a. - Lease Plan France",
    "wof:placetype":"venue"
},
  "geometry": {"coordinates":[5.63957,43.446781],"type":"Point"}
}