{
  "type": "Feature",
  "properties": {
    "addr:full":"ZA Pierre Fondelle 01580 IZERNORE Rhone-Alpes",
    "addr:postcode":"01580",
    "addr:street":"Za Pierre Fondelle",
    "iso:country":"FR",
    "sg:address":"ZA Pierre Fondelle 01580 IZERNORE",
    "sg:classifiers":[
        {
            "category":"Manufacturing",
            "subcategory":"Rubber & Plastics",
            "type":"Manufacturing & Wholesale Goods"
        }
    ],
    "sg:phone":"+33 4 74 49 14 00",
    "sg:province":"Rhone-Alpes",
    "sg:tags":[
        "technical",
        "parts"
    ],
    "wof:name":"Apnyl Sa",
    "wof:placetype":"venue"
},
  "geometry": {"coordinates":[5.55378,46.218575],"type":"Point"}
}