{
  "type": "Feature",
  "properties": {
    "addr:full":"54 Grand rue 57620 Lemberg Lorraine",
    "addr:housenumber":"54",
    "addr:postcode":"57620",
    "addr:street":"Grand Rue",
    "iso:country":"FR",
    "sg:address":"54 Grand rue 57620 Lemberg",
    "sg:classifiers":[
        {
            "category":"Bars & Pubs",
            "subcategory":"Hookah Bar",
            "type":"Food & Drink"
        }
    ],
    "sg:phone":"+33 3 87 06 48 20",
    "sg:province":"Lorraine",
    "sg:tags":[
        "steel",
        "sectional"
    ],
    "wof:name":"Profilmetal S.a.",
    "wof:placetype":"venue"
},
  "geometry": {"coordinates":[7.379299,49.003834],"type":"Point"}
}