{
  "type": "Feature",
  "properties": {
    "addr:full":"B.P. 237, 88006 Epinal C\u00e9dex^^28, Rte de M\u00e9m\u00e9nil, 88600 Aydoilles Lorraine",
    "addr:housenumber":"b.p. 237",
    "addr:postcode":"88006;88600",
    "addr:street":"Rte De Me\u0301Me\u0301Nil",
    "iso:country":"FR",
    "sg:address":"B.P. 237, 88006 Epinal C\u00e9dex^^28, Rte de M\u00e9m\u00e9nil, 88600 Aydoilles",
    "sg:orig_category":"Non-Classified Establishments",
    "sg:phone":"+33 3 29 65 85 65",
    "sg:province":"Lorraine",
    "wof:name":"Soci\u00e9t\u00e9 Nouvelle M.i.s. S.a.r.l. - Micro Informatique Service",
    "wof:placetype":"venue"
},
  "geometry": {"coordinates":[6.681395,48.143887],"type":"Point"}
}