{
  "type": "Feature",
  "properties": {
    "addr:full":"Za Des Ravalieres 72560 Change Pays de Loire",
    "addr:postcode":"72560",
    "addr:street":"Za Des Ravalieres;Change",
    "iso:country":"FR",
    "sg:address":"Za Des Ravalieres 72560 Change",
    "sg:classifiers":[
        {
            "category":"Professional",
            "type":"Services"
        }
    ],
    "sg:phone":"+33 2 43 61 43 43",
    "sg:province":"Pays de Loire",
    "sg:tags":[
        "transport",
        "road"
    ],
    "wof:name":"Heppner Societe De Transports Heppner Sa",
    "wof:placetype":"venue"
},
  "geometry": {"coordinates":[0.282235,47.987331],"type":"Point"}
}