{
  "type": "Feature",
  "properties": {
    "addr:full":"3 pl Souvenir; Cestas Aquitaine",
    "addr:housenumber":"3",
    "addr:street":"Pl Souvenir",
    "iso:country":"FR",
    "sg:address":"3 pl Souvenir; Cestas",
    "sg:classifiers":[
        {
            "category":"Banks & Credit Unions",
            "subcategory":"Bank",
            "type":"Services"
        }
    ],
    "sg:phone":"+33 3356782635",
    "sg:province":"Aquitaine",
    "wof:name":"Soci\u00e9t\u00e9 G\u00e9n\u00e9rale",
    "wof:placetype":"venue"
},
  "geometry": {"coordinates":[-0.685097,44.741707],"type":"Point"}
}