{
  "type": "Feature",
  "properties": {
    "iso:country":"FR",
    "sg:address":"B.P. 60109, 60880 Le Meux^^Z.I., 60880 Le Meux",
    "sg:orig_category":"Non-Classified Establishments",
    "sg:phone":"+33 3 44 90 58 58",
    "sg:postcode":"60880",
    "sg:province":"Picardie",
    "wof:name":"Causse Walon S.a.",
    "wof:placetype":"venue"
},
  "geometry": {"coordinates":[2.776811,49.389362],"type":"Point"}
}