{
  "type": "Feature",
  "properties": {
    "iso:country":"FR",
    "sg:address":"B.P. 29, 63700 Saint Eloy les Mines C\u00e9dex^^Rue du Puits du Manoir, 63700 Saint Eloy les Mines",
    "sg:city":"Ars-les-Favets",
    "sg:orig_category":"Non-Classified Establishments",
    "sg:phone":"+33 4 73 85 90 15",
    "sg:postcode":"63700",
    "sg:province":"Auvergne",
    "wof:name":"Techno-m\u00e9tal S.a.r.l.",
    "wof:placetype":"venue"
},
  "geometry": {"coordinates":[2.834537,46.165066],"type":"Point"}
}