{
  "type": "Feature",
  "properties": {
    "iso:country":"FR",
    "sg:address":"B.P. 23431, 67455 Mundolsheim C\u00e9dex^^Rue de l'Embranchement, 67116 Reichstett",
    "sg:city":"Reichstett",
    "sg:orig_category":"Non-Classified Establishments",
    "sg:phone":"+33 3 88 20 95 88",
    "sg:postcode":"67116",
    "sg:province":"Alsace",
    "wof:name":"Waldmann Eclairage S.a.",
    "wof:placetype":"venue"
},
  "geometry": {"coordinates":[7.773746,48.643925],"type":"Point"}
}