{
  "type": "Feature",
  "properties": {
    "iso:country":"FR",
    "sg:address":"7 R De Selestat 68180 Horbourg Wihr",
    "sg:city":"Horbourg-Wihr",
    "sg:classifiers":[
        {
            "category":"Building & Trades",
            "subcategory":"Construction",
            "type":"Services"
        }
    ],
    "sg:phone":"+33 3 89 23 03 29",
    "sg:postcode":"68180",
    "sg:province":"Alsace",
    "sg:tags":[
        "work",
        "public"
    ],
    "wof:name":"Pontiggia",
    "wof:placetype":"venue"
},
  "geometry": {"coordinates":[7.405292,48.076927],"type":"Point"}
}