{
  "type": "Feature",
  "properties": {
    "addr:full":"Zi La Promenade 49360 La Plaine Pays de Loire 49360",
    "addr:postcode":"49360;49360",
    "addr:street":"Zi La Promenade;Plaine",
    "iso:country":"FR",
    "sg:address":"Zi La Promenade 49360 La Plaine",
    "sg:classifiers":[
        {
            "category":"Manufacturing",
            "subcategory":"Textiles",
            "type":"Manufacturing & Wholesale Goods"
        }
    ],
    "sg:phone":"+33 2 41 55 92 52",
    "sg:postcode":"49360",
    "sg:province":"Pays de Loire",
    "sg:tags":[
        "clothing",
        "accessory"
    ],
    "wof:name":"Manufacture D'epaulettes Froga Societe Andureau Godin",
    "wof:placetype":"venue"
},
  "geometry": {"coordinates":[-0.635019,47.068264],"type":"Point"}
}