{
  "type": "Feature",
  "properties": {
    "addr:full":"Rue du Fort Penthi\u00e8vre Locmin\u00e9 Bretagne 56500",
    "addr:postcode":"56500",
    "addr:street":"Rue Du Fort Penthie\u0300Vre Locmine\u0301 Bretagne",
    "iso:country":"FR",
    "sg:address":"Rue du Fort Penthi\u00e8vre",
    "sg:city":"Locmin\u00e9",
    "sg:orig_category":"Unclassifiable Establishments",
    "sg:phone":"+33 2 97 60 01 58",
    "sg:postcode":"56500",
    "sg:province":"Bretagne",
    "wof:name":"Maryvet V\u00eatements S.a.r.l.",
    "wof:placetype":"venue"
},
  "geometry": {"coordinates":[-2.837074,47.882195],"type":"Point"}
}