{
  "type": "Feature",
  "properties": {
    "iso:country":"FR",
    "sg:address":"190 Rue Jean Catelas 80480 Saleux",
    "sg:classifiers":[
        {
            "category":"Home & Garden",
            "subcategory":"Furniture",
            "type":"Retail Goods"
        }
    ],
    "sg:phone":"+33 3 22 89 52 00",
    "sg:postcode":"80480",
    "sg:province":"Picardie",
    "sg:tags":[
        "household",
        "wood"
    ],
    "wof:name":"Sapsa Bedding",
    "wof:placetype":"venue"
},
  "geometry": {"coordinates":[2.23595,49.855961],"type":"Point"}
}