{
  "type": "Feature",
  "properties": {
    "addr:full":"132, Av. de Lombez, 31300 Toulouse Midi Pyr\u00e9n\u00e9es",
    "addr:postcode":"31300",
    "addr:street":"132 Av. De Lombez",
    "iso:country":"FR",
    "sg:address":"132, Av. de Lombez, 31300 Toulouse",
    "sg:orig_category":"Unclassifiable Establishments",
    "sg:phone":"+33 5 34 51 19 00",
    "sg:province":"Midi Pyr\u00e9n\u00e9es",
    "wof:name":"Blue River Systems S.a.r.l.",
    "wof:placetype":"venue"
},
  "geometry": {"coordinates":[1.410763,43.594322],"type":"Point"}
}