{
  "type": "Feature",
  "properties": {
    "addr:full":"23 Rue Fontaine 75009 Paris Ile de France 75009",
    "addr:housenumber":"23",
    "addr:postcode":"75009;75009",
    "addr:street":"Rue Fontaine",
    "iso:country":"FR",
    "sg:address":"23 Rue Fontaine 75009 Paris",
    "sg:classifiers":[
        {
            "category":"Professional",
            "subcategory":"Engineering",
            "type":"Services"
        }
    ],
    "sg:phone":"+33 1 48 78 64 63",
    "sg:postcode":"75009",
    "sg:province":"Ile de France",
    "sg:tags":[
        "machine",
        "-",
        "mechanical"
    ],
    "wof:name":"Montmartre Verreries Sa",
    "wof:placetype":"venue"
},
  "geometry": {"coordinates":[2.333788,48.88176],"type":"Point"}
}