{
  "type": "Feature",
  "properties": {
    "addr:full":"20, Rue B\u00e9ranger, 42300 Roanne Rhone-Alpes 42300",
    "addr:housenumber":"20",
    "addr:postcode":"42300;42300",
    "addr:street":"Rue Be\u0301Ranger;Rhone-Alpes",
    "iso:country":"FR",
    "sg:address":"20, Rue B\u00e9ranger, 42300 Roanne",
    "sg:orig_category":"Non-Classified Establishments",
    "sg:phone":"+33 4 77 71 50 39",
    "sg:postcode":"42300",
    "sg:province":"Rhone-Alpes",
    "wof:name":"Etablissements Vivi\u00e8re",
    "wof:placetype":"venue"
},
  "geometry": {"coordinates":[4.061326,46.036514],"type":"Point"}
}