{
  "type": "Feature",
  "properties": {
    "addr:full":"8, Cottage Beaus\u00e9jour, 33370 Fargues Saint Hilaire Artigues-pr\u00e8s-Bordeaux Aquitaine 33370",
    "addr:housenumber":"8",
    "addr:postcode":"33370;33370",
    "addr:street":"Cottage Beause\u0301Jour",
    "iso:country":"FR",
    "sg:address":"8, Cottage Beaus\u00e9jour, 33370 Fargues Saint Hilaire",
    "sg:city":"Artigues-pr\u00e8s-Bordeaux",
    "sg:orig_category":"Non-Classified Establishments",
    "sg:phone":"+33 5 56 68 39 30",
    "sg:postcode":"33370",
    "sg:province":"Aquitaine",
    "wof:name":"D.c.p. International - Douard Corinne Patrice International",
    "wof:placetype":"venue"
},
  "geometry": {"coordinates":[-0.435397,44.828529],"type":"Point"}
}