{
  "type": "Feature",
  "properties": {
    "addr:full":"7 rue du Ch\u00e2teau 27550 Fontaine la Soret Haute Normandie",
    "addr:housenumber":"7",
    "addr:postcode":"27550",
    "addr:street":"Rue Du Cha\u0302Teau;Haute Normandie",
    "iso:country":"FR",
    "sg:address":"7 rue du Ch\u00e2teau 27550 Fontaine la Soret",
    "sg:classifiers":[
        {
            "category":"Food & Beverages",
            "subcategory":"Fruits & Vegetables",
            "type":"Retail Goods"
        }
    ],
    "sg:phone":"+33 2 32 44 91 03",
    "sg:province":"Haute Normandie",
    "sg:tags":[
        "plant",
        "seed"
    ],
    "wof:name":"Omnisem Sarl",
    "wof:placetype":"venue"
},
  "geometry": {"coordinates":[0.716359,49.149792],"type":"Point"}
}