{
  "type": "Feature",
  "properties": {
    "addr:full":"46 Quai Fran\u00e7ois Mitterand 13600 La Ciotat Fran\u00e7ois Poitou-Charentes 79260",
    "addr:housenumber":"46;13600",
    "addr:postcode":"79260",
    "addr:street":"Quai Franc\u0327Ois Mitterand;Franc\u0327Ois",
    "iso:country":"FR",
    "sg:address":"46 Quai Fran\u00e7ois Mitterand 13600 La Ciotat",
    "sg:city":"Fran\u00e7ois",
    "sg:classifiers":[
        {
            "category":"Autos & Motor Vehicles",
            "subcategory":"Boat Sales",
            "type":"Retail Goods"
        }
    ],
    "sg:phone":"+33 4 42 08 25 76",
    "sg:postcode":"79260",
    "sg:province":"Poitou-Charentes",
    "sg:tags":[
        "equipment",
        "transport"
    ],
    "wof:name":"Watershed International",
    "wof:placetype":"venue"
},
  "geometry": {"coordinates":[5.60579,43.17218],"type":"Point"}
}