{
  "type": "Feature",
  "properties": {
    "iso:country":"FR",
    "sg:address":"232 Avenue De Colmar 67100 Strasbourg",
    "sg:city":"Strasbourg",
    "sg:classifiers":[
        {
            "category":"Autos & Motor Vehicles",
            "subcategory":"Automobile Sales",
            "type":"Retail Goods"
        }
    ],
    "sg:phone":"+33 3 88 79 16 79",
    "sg:postcode":"67100",
    "sg:province":"Alsace",
    "sg:tags":[
        "equipment",
        "motor-cars",
        "transport"
    ],
    "wof:name":"Ars Sa",
    "wof:placetype":"venue"
},
  "geometry": {"coordinates":[7.745791,48.55584],"type":"Point"}
}