{
  "type": "Feature",
  "properties": {
    "addr:full":"79 rue du Faubourg Poissonni\u00e8re Paris 75009",
    "addr:housenumber":"79",
    "addr:postcode":"75009",
    "addr:street":"Rue Du Faubourg Poissonnie\u0300Re",
    "iso:country":"FR",
    "sg:address":"79 rue du Faubourg Poissonni\u00e8re",
    "sg:city":"Paris",
    "sg:classifiers":[
        {
            "category":"Professional",
            "subcategory":"Computer Services",
            "type":"Services"
        }
    ],
    "sg:postcode":"75009",
    "sg:website":"http://www.keldelice.com",
    "wof:name":"Keldelice",
    "wof:placetype":"venue"
},
  "geometry": {"coordinates":[2.348423,48.876286],"type":"Point"}
}