{
  "type": "Feature",
  "properties": {
    "addr:full":"30, Rue Jean Moulin, 62000 Dainville Nord Pas-de-Calais",
    "addr:housenumber":"30",
    "addr:postcode":"62000",
    "addr:street":"Rue Jean Moulin",
    "iso:country":"FR",
    "sg:address":"30, Rue Jean Moulin, 62000 Dainville",
    "sg:orig_category":"Unclassifiable Establishments",
    "sg:phone":"+33 3 21 51 93 93",
    "sg:province":"Nord Pas-de-Calais",
    "wof:name":"Knauf Nord S.a.",
    "wof:placetype":"venue"
},
  "geometry": {"coordinates":[2.72108,50.269611],"type":"Point"}
}