{
  "type": "Feature",
  "properties": {
    "iso:country":"FR",
    "sg:address":"25, Bd de Brosses, 21000 Dijon",
    "sg:city":"Dijon",
    "sg:orig_category":"Unclassifiable Establishments",
    "sg:phone":"+33 3 80 49 96 76",
    "sg:postcode":"21000",
    "sg:province":"Bourgogne",
    "wof:name":"Lequien Alain",
    "wof:placetype":"venue"
},
  "geometry": {"coordinates":[5.035032,47.323879],"type":"Point"}
}