{
  "type": "Feature",
  "properties": {
    "addr:full":"175 rue de Coureilles 17042 LA ROCHELLE CEDEX 1 Poitou-Charentes",
    "addr:housenumber":"175",
    "addr:postcode":"17042",
    "addr:street":"Rue De Coureilles",
    "iso:country":"FR",
    "sg:address":"175 rue de Coureilles 17042 LA ROCHELLE CEDEX 1",
    "sg:classifiers":[
        {
            "category":"Shopping",
            "subcategory":"Computers & Home Electronics",
            "type":"Retail Goods"
        }
    ],
    "sg:phone":"+33 5 46 45 45 11",
    "sg:province":"Poitou-Charentes",
    "sg:tags":[
        "tube",
        "manipulation"
    ],
    "wof:name":"Innov Ia Industrie Sa",
    "wof:placetype":"venue"
},
  "geometry": {"coordinates":[-1.150847,46.140919],"type":"Point"}
}