{
  "type": "Feature",
  "properties": {
    "addr:full":"5 Chem Charpenay 38280 Janneyrias Rhone-Alpes 38280",
    "addr:housenumber":"5",
    "addr:postcode":"38280;38280",
    "addr:street":"Chem Charpenay;Rhone-Alpes",
    "iso:country":"FR",
    "sg:address":"5 Chem Charpenay 38280 Janneyrias",
    "sg:classifiers":[
        {
            "category":"Manufacturing",
            "subcategory":"Chemicals & Compounds",
            "type":"Manufacturing & Wholesale Goods"
        }
    ],
    "sg:phone":"+33 4 72 46 09 40",
    "sg:postcode":"38280",
    "sg:province":"Rhone-Alpes",
    "sg:tags":[
        "pharmaceutical",
        "chemistry",
        "-",
        "by-product"
    ],
    "wof:name":"Galliacolor Sa",
    "wof:placetype":"venue"
},
  "geometry": {"coordinates":[5.10509,45.756134],"type":"Point"}
}