{
  "type": "Feature",
  "properties": {
    "iso:country":"FR",
    "sg:address":"76 Av Du G\u00e9n\u00e9ral De Gaulle 85120 Chataigneraie",
    "sg:classifiers":[
        {
            "category":"Manufacturing",
            "subcategory":"Wood Products",
            "type":"Manufacturing & Wholesale Goods"
        }
    ],
    "sg:phone":"+33 2 51 51 65 09",
    "sg:province":"Pays de Loire",
    "sg:tags":[
        "furniture"
    ],
    "wof:name":"Couture Sa",
    "wof:placetype":"venue"
},
  "geometry": {"coordinates":[-92.321831,30.568584],"type":"Point"}
}