{
  "type": "Feature",
  "properties": {
    "addr:full":"Pontsonneau 42530 St Genest Lerpt Rhone-Alpes",
    "addr:postcode":"42530",
    "addr:street":"Pontsonneau",
    "iso:country":"FR",
    "sg:address":"Pontsonneau 42530 St Genest Lerpt",
    "sg:classifiers":[
        {
            "category":"Building & Trades",
            "subcategory":"Construction",
            "type":"Services"
        }
    ],
    "sg:phone":"+33 4 77 90 91 32",
    "sg:province":"Rhone-Alpes",
    "sg:tags":[
        "work",
        "public"
    ],
    "wof:name":"Arnaud Auguste Demolition",
    "wof:placetype":"venue"
},
  "geometry": {"coordinates":[4.34877,45.449116],"type":"Point"}
}