{
  "type": "Feature",
  "properties": {
    "iso:country":"FR",
    "sg:address":"Le Bas Bourg 42310 Le Crozet",
    "sg:orig_category":"Unclassifiable Establishments",
    "sg:phone":"+33 4 77 64 15 48",
    "sg:province":"Rhone-Alpes",
    "wof:name":"L.j.c. Productique S.a.r.l.",
    "wof:placetype":"venue"
},
  "geometry": {"coordinates":[3.857065,46.172115],"type":"Point"}
}