{
  "type": "Feature",
  "properties": {
    "addr:full":"B.P. 229, 94203 Ivry sur Seine C\u00e9dex^^7, All\u00e9e de la Seine, 94200 Ivry sur Seine Ile de France 94200",
    "addr:housenumber":"b.p. 229",
    "addr:postcode":"94203;94200;94200",
    "addr:street":"Alle\u0301E De La Seine;France",
    "iso:country":"FR",
    "sg:address":"B.P. 229, 94203 Ivry sur Seine C\u00e9dex^^7, All\u00e9e de la Seine, 94200 Ivry sur Seine",
    "sg:orig_category":"Non-Classified Establishments",
    "sg:phone":"+33 1 49 59 74 31",
    "sg:postcode":"94200",
    "sg:province":"Ile de France",
    "wof:name":"Cin\u00e9tic Service S.a.",
    "wof:placetype":"venue"
},
  "geometry": {"coordinates":[2.384885,48.811668],"type":"Point"}
}