{
  "type": "Feature",
  "properties": {
    "addr:full":"242, Bd Voltaire, 75011 Paris Ile de France",
    "addr:housenumber":"242",
    "addr:postcode":"75011",
    "addr:street":"Bd Voltaire",
    "iso:country":"FR",
    "sg:address":"242, Bd Voltaire, 75011 Paris",
    "sg:orig_category":"Unclassifiable Establishments",
    "sg:phone":"+33 1 41 50 05 15",
    "sg:province":"Ile de France",
    "wof:name":"T.l.c. S.a.r.l.",
    "wof:placetype":"venue"
},
  "geometry": {"coordinates":[2.390696,48.85133],"type":"Point"}
}