{
  "type": "Feature",
  "properties": {
    "addr:full":"8, Impasse de la Lande Bourne, 44220 Cou\u00ebron Pays de Loire",
    "addr:housenumber":"8",
    "addr:postcode":"44220",
    "addr:street":"Impasse De La Lande",
    "iso:country":"FR",
    "sg:address":"8, Impasse de la Lande Bourne, 44220 Cou\u00ebron",
    "sg:orig_category":"Non-Classified Establishments",
    "sg:phone":"+33 2 28 01 78 00",
    "sg:province":"Pays de Loire",
    "wof:name":"Memorex Telex S.a.",
    "wof:placetype":"venue"
},
  "geometry": {"coordinates":[-1.663914,47.240665],"type":"Point"}
}