{
  "type": "Feature",
  "properties": {
    "addr:full":"lotissement le Pr\u00e9 Chariot 01120 LA BOISSE Rhone-Alpes 01120",
    "addr:postcode":"01120;01120",
    "addr:street":"Lotissement Le Pre\u0301 Chariot",
    "iso:country":"FR",
    "sg:address":"lotissement le Pr\u00e9 Chariot 01120 LA BOISSE",
    "sg:classifiers":[
        {
            "category":"Organizations",
            "subcategory":"Labor Organization",
            "type":"Services"
        }
    ],
    "sg:phone":"+33 4 78 06 24 46",
    "sg:postcode":"01120",
    "sg:province":"Rhone-Alpes",
    "sg:tags":[
        "work",
        "assembling",
        "assembly",
        "contract"
    ],
    "wof:name":"Somse Sa",
    "wof:placetype":"venue"
},
  "geometry": {"coordinates":[5.031815,45.847164],"type":"Point"}
}