{
  "type": "Feature",
  "properties": {
    "iso:country":"FR",
    "sg:address":"15, Rue Paul Seramy - ZA les Vingt Arpents, 77990 Le Mesnil Amelot",
    "sg:orig_category":"Unclassifiable Establishments",
    "sg:phone":"+33 1 60 54 62 66",
    "sg:province":"Ile de France",
    "wof:name":"Daric S.a.",
    "wof:placetype":"venue"
},
  "geometry": {"coordinates":[2.590909,49.017994],"type":"Point"}
}