{
  "type": "Feature",
  "properties": {
    "addr:full":"21bis, Rue Malines - ZI Nord, 21000 Dijon Dijon Bourgogne 21000",
    "addr:housenumber":"21bis",
    "addr:postcode":"21000;21000",
    "addr:street":"Rue Malines Zi Nord",
    "iso:country":"FR",
    "sg:address":"21bis, Rue Malines - ZI Nord, 21000 Dijon",
    "sg:city":"Dijon",
    "sg:orig_category":"Non-Classified Establishments",
    "sg:phone":"+33 3 80 70 15 15",
    "sg:postcode":"21000",
    "sg:province":"Bourgogne",
    "wof:name":"C\u00e2blerie Et Corderie De Bourgogne S.a.r.l.",
    "wof:placetype":"venue"
},
  "geometry": {"coordinates":[5.044195,47.326458],"type":"Point"}
}