{
  "type": "Feature",
  "properties": {
    "addr:full":"12 Boulevard Beausoleil 24100 Bergerac Bergerac Aquitaine 24100",
    "addr:housenumber":"12",
    "addr:postcode":"24100;24100",
    "addr:street":"Boulevard Beausoleil",
    "iso:country":"FR",
    "sg:address":"12 Boulevard Beausoleil 24100 Bergerac",
    "sg:city":"Bergerac",
    "sg:classifiers":[
        {
            "category":"Shopping",
            "subcategory":"Bicycles & Sporting Goods",
            "type":"Retail Goods"
        }
    ],
    "sg:phone":"+33 5 53 57 09 93",
    "sg:postcode":"24100",
    "sg:province":"Aquitaine",
    "sg:tags":[
        "product",
        "sport",
        "miscellaneous"
    ],
    "wof:name":"Sprint Line",
    "wof:placetype":"venue"
},
  "geometry": {"coordinates":[0.477839,44.854023],"type":"Point"}
}