{
  "type": "Feature",
  "properties": {
    "addr:full":"ZI les Mourges Saint Gilles Languedoc-Roussillon 30800",
    "addr:postcode":"30800",
    "addr:street":"Zi Les Mourges Saint Gilles",
    "iso:country":"FR",
    "sg:address":"ZI les Mourges",
    "sg:city":"Saint Gilles",
    "sg:orig_category":"Unclassifiable Establishments",
    "sg:phone":"+33 4 66 87 12 19",
    "sg:postcode":"30800",
    "sg:province":"Languedoc-Roussillon",
    "wof:name":"Sudac S.a.",
    "wof:placetype":"venue"
},
  "geometry": {"coordinates":[4.429848,43.676762],"type":"Point"}
}