{
  "type": "Feature",
  "properties": {
    "iso:country":"FR",
    "sg:address":"901, Rte de Bordeaux, 65700 Maubourguet",
    "sg:orig_category":"Non-Classified Establishments",
    "sg:phone":"+33 5 62 96 30 41",
    "sg:postcode":"65700",
    "sg:province":"Midi Pyr\u00e9n\u00e9es",
    "wof:name":"Etablissements Casaus Casamayor S.a.",
    "wof:placetype":"venue"
},
  "geometry": {"coordinates":[0.02947,43.468388],"type":"Point"}
}