{
  "type": "Feature",
  "properties": {
    "addr:full":"30 Rue Du Gal De Gaulle 68270 Ruelisheim Ruelisheim Alsace 68270",
    "addr:housenumber":"30",
    "addr:postcode":"68270;68270",
    "addr:street":"Rue Du Gal De Gaulle;Ruelisheim",
    "iso:country":"FR",
    "sg:address":"30 Rue Du Gal De Gaulle 68270 Ruelisheim",
    "sg:city":"Ruelisheim",
    "sg:classifiers":[
        {
            "category":"Shopping",
            "subcategory":"Crafts & Fabrics",
            "type":"Retail Goods"
        }
    ],
    "sg:phone":"+33 3 89 57 57 89",
    "sg:postcode":"68270",
    "sg:province":"Alsace",
    "sg:tags":[
        "textile",
        "clothing"
    ],
    "wof:name":"Philea Textiles",
    "wof:placetype":"venue"
},
  "geometry": {"coordinates":[7.339937,47.810852],"type":"Point"}
}