{
  "type": "Feature",
  "properties": {
    "iso:country":"FR",
    "sg:address":"6 Impasse Des Issards 30340 St Privat Des Vieux",
    "sg:classifiers":[
        {
            "category":"Professional",
            "subcategory":"Engineering",
            "type":"Services"
        }
    ],
    "sg:phone":"+33 4 66 86 27 27",
    "sg:postcode":"30340",
    "sg:province":"Languedoc-Roussillon",
    "sg:tags":[
        "machine",
        "-",
        "environment",
        "equipment",
        "machinery",
        "mechanical"
    ],
    "wof:name":"Poitevin Chantal Elisabeth",
    "wof:placetype":"venue"
},
  "geometry": {"coordinates":[4.127573,44.145905],"type":"Point"}
}