{
  "type": "Feature",
  "properties": {
    "iso:country":"FR",
    "sg:address":"14 AV DU PR ANDRE LEMIERRE 75966 PARIS CEDEX 20",
    "sg:classifiers":[
        {
            "category":"Shopping",
            "subcategory":"Comic Books",
            "type":"Retail Goods"
        }
    ],
    "sg:phone":"+33 1 49 20 67 89",
    "sg:province":"Languedoc-Roussillon",
    "sg:tags":[
        "binding"
    ],
    "wof:name":"Filmolux Neschen Sarl",
    "wof:placetype":"venue"
},
  "geometry": {"coordinates":[2.39671,48.862499],"type":"Point"}
}