{
  "type": "Feature",
  "properties": {
    "iso:country":"FR",
    "sg:address":"Rte de Nice - Les F\u00e9rr\u00e9ols",
    "sg:city":"Digne les Bains",
    "sg:orig_category":"Unclassifiable Establishments",
    "sg:phone":"+33 4 92 31 33 84",
    "sg:postcode":"04000",
    "sg:province":"Provence-Alpes-C\u00f4te d'Azur",
    "wof:name":"Coullet S.a.r.l.",
    "wof:placetype":"venue"
},
  "geometry": {"coordinates":[6.22509,44.08886],"type":"Point"}
}