{
  "type": "Feature",
  "properties": {
    "addr:full":"59 Rue Du G\u00e9n\u00e9ral Patton 57330 Hettange Grande Lorraine 57330",
    "addr:housenumber":"59",
    "addr:postcode":"57330;57330",
    "addr:street":"Rue Du Ge\u0301Ne\u0301Ral Patton;Grande Lorraine",
    "iso:country":"FR",
    "sg:address":"59 Rue Du G\u00e9n\u00e9ral Patton 57330 Hettange Grande",
    "sg:classifiers":[
        {
            "category":"Bakery",
            "type":"Food & Drink"
        }
    ],
    "sg:phone":"+33 3 82 53 19 24",
    "sg:postcode":"57330",
    "sg:province":"Lorraine",
    "sg:tags":[
        "cake",
        "product",
        "related",
        "bread"
    ],
    "wof:name":"Foretnoire Sarl",
    "wof:placetype":"venue"
},
  "geometry": {"coordinates":[6.159541,49.401085],"type":"Point"}
}