{
  "type": "Feature",
  "properties": {
    "addr:full":"Centre Commercial; Meaux; 77100 Ile de France 77100",
    "addr:postcode":"77100;77100",
    "addr:street":"Ile De France",
    "iso:country":"FR",
    "sg:address":"Centre Commercial; Meaux; 77100",
    "sg:classifiers":[
        {
            "category":"Banks & Credit Unions",
            "subcategory":"Bank",
            "type":"Services"
        }
    ],
    "sg:phone":"+33 1 64 33 30 78",
    "sg:postcode":"77100",
    "sg:province":"Ile de France",
    "wof:name":"Bred Banque Populaire",
    "wof:placetype":"venue"
},
  "geometry": {"coordinates":[2.859679,48.926022],"type":"Point"}
}