{
  "type": "Feature",
  "properties": {
    "addr:full":"RD 26 - Quartier de la Grave Pujaut Languedoc-Roussillon 30131",
    "addr:postcode":"30131",
    "addr:street":"Rd 26",
    "iso:country":"FR",
    "sg:address":"RD 26 - Quartier de la Grave",
    "sg:city":"Pujaut",
    "sg:orig_category":"Non-Classified Establishments",
    "sg:phone":"+33 4 90 15 25 00",
    "sg:postcode":"30131",
    "sg:province":"Languedoc-Roussillon",
    "wof:name":"B.d.i. S.a.s. - B\u00e9daricienne Doras Industries",
    "wof:placetype":"venue"
},
  "geometry": {"coordinates":[4.741025,43.97694],"type":"Point"}
}