{
  "type": "Feature",
  "properties": {
    "iso:country":"FR",
    "sg:address":"14, Rue d'Anthoine, 13002 Marseille",
    "sg:orig_category":"Unclassifiable Establishments",
    "sg:phone":"+33 4 91 13 20 08",
    "sg:province":"Provence-Alpes-C\u00f4te d'Azur",
    "wof:name":"S.m.c.m. S.a. - Soci\u00e9t\u00e9 Marseillaise De Camionnage Et De Messager",
    "wof:placetype":"venue"
},
  "geometry": {"coordinates":[5.35658,43.315281],"type":"Point"}
}