{
  "type": "Feature",
  "properties": {
    "iso:country":"FR",
    "sg:address":"131 Boulevard De Sebastopol 75002 Paris",
    "sg:classifiers":[
        {
            "category":"Shopping",
            "subcategory":"Clothing, Apparel, & Fashions",
            "type":"Retail Goods"
        }
    ],
    "sg:phone":"+33 1 42 36 41 31",
    "sg:postcode":"75002",
    "sg:province":"Ile de France",
    "sg:tags":[
        "textile",
        "clothing",
        "clothes"
    ],
    "wof:name":"Anagram",
    "wof:placetype":"venue"
},
  "geometry": {"coordinates":[2.353459,48.868141],"type":"Point"}
}