{
  "type": "Feature",
  "properties": {
    "iso:country":"FR",
    "sg:address":"56/58 Rue De Ponthieu",
    "sg:city":"Paris",
    "sg:classifiers":[
        {
            "category":"Banks & Credit Unions",
            "subcategory":"Financial Services",
            "type":"Services"
        }
    ],
    "sg:phone":"+33 1 53 77 84 20",
    "sg:postcode":"75008",
    "sg:province":"Ile de France",
    "sg:tags":[
        "banking",
        "finance",
        "insurance"
    ],
    "wof:name":"Thomson-csf Ventures",
    "wof:placetype":"venue"
},
  "geometry": {"coordinates":[2.306023,48.871891],"type":"Point"}
}