{
  "type": "Feature",
  "properties": {
    "iso:country":"FR",
    "sg:address":"55, Rue Framery, 62200 Boulogne sur Mer",
    "sg:orig_category":"Non-Classified Establishments",
    "sg:phone":"+33 3 21 10 14 40",
    "sg:postcode":"62200",
    "sg:province":"Nord Pas-de-Calais",
    "wof:name":"Arobax S.a.",
    "wof:placetype":"venue"
},
  "geometry": {"coordinates":[1.620093,50.726181],"type":"Point"}
}