{
  "type": "Feature",
  "properties": {
    "addr:full":"Rue Gay Lussac - ZI Tonneins Aquitaine 47400",
    "addr:postcode":"47400",
    "addr:street":"Rue Gay Lussac Zi",
    "iso:country":"FR",
    "sg:address":"Rue Gay Lussac - ZI",
    "sg:city":"Tonneins",
    "sg:orig_category":"Unclassifiable Establishments",
    "sg:phone":"+33 5 53 84 57 96",
    "sg:postcode":"47400",
    "sg:province":"Aquitaine",
    "wof:name":"Veraflex S.a.",
    "wof:placetype":"venue"
},
  "geometry": {"coordinates":[0.319993,44.345749],"type":"Point"}
}