{
  "type": "Feature",
  "properties": {
    "addr:full":"10 Rue Corps Franc Du Sidobre 81210 Roquecourbe Midi Pyr\u00e9n\u00e9es 81210",
    "addr:housenumber":"10",
    "addr:postcode":"81210;81210",
    "addr:street":"Rue Corps Franc Du Sidobre",
    "iso:country":"FR",
    "sg:address":"10 Rue Corps Franc Du Sidobre 81210 Roquecourbe",
    "sg:classifiers":[
        {
            "category":"Shopping",
            "subcategory":"Clothing, Apparel, & Fashions",
            "type":"Retail Goods"
        }
    ],
    "sg:phone":"+33 5 63 75 80 14",
    "sg:postcode":"81210",
    "sg:province":"Midi Pyr\u00e9n\u00e9es",
    "sg:tags":[
        "textile",
        "clothing",
        "clothes"
    ],
    "wof:name":"Bonneterie Cros Et Fils Sarl",
    "wof:placetype":"venue"
},
  "geometry": {"coordinates":[2.287146,43.662426],"type":"Point"}
}