{
  "type": "Feature",
  "properties": {
    "addr:full":"20, Rue Victor Leydet, 13090 Aix en Provence Provence-Alpes-C\u00f4te d'Azur",
    "addr:housenumber":"20",
    "addr:postcode":"13090",
    "addr:street":"Rue Victor Leydet;En Provence",
    "iso:country":"FR",
    "sg:address":"20, Rue Victor Leydet, 13090 Aix en Provence",
    "sg:orig_category":"Unclassifiable Establishments",
    "sg:phone":"+33 803 80 31 13",
    "sg:province":"Provence-Alpes-C\u00f4te d'Azur",
    "wof:name":"Vacances H\u00e9liades S.a.",
    "wof:placetype":"venue"
},
  "geometry": {"coordinates":[5.445617,43.527287],"type":"Point"}
}