{
  "type": "Feature",
  "properties": {
    "iso:country":"FR",
    "sg:address":"7-13 Bd Paul-Emile Victor 92200 Neuilly Sur Seine",
    "sg:classifiers":[
        {
            "category":"Health Services",
            "subcategory":"Medical Lab",
            "type":"Services"
        }
    ],
    "sg:phone":"+33 1 55 61 53 25",
    "sg:postcode":"92200",
    "sg:province":"Ile de France",
    "sg:tags":[
        "chemical",
        "pharmaceutical",
        "pharmacy"
    ],
    "wof:name":"Laboratoires Fornet",
    "wof:placetype":"venue"
},
  "geometry": {"coordinates":[2.26259,48.89328],"type":"Point"}
}