{
  "type": "Feature",
  "properties": {
    "iso:country":"FR",
    "sg:address":"43, Bd des Alpes, 38240 Meylan",
    "sg:orig_category":"Unclassifiable Establishments",
    "sg:phone":"+33 4 76 18 28 82",
    "sg:postcode":"38240",
    "sg:province":"Rhone-Alpes",
    "wof:name":"Gamo S.a.r.l.",
    "wof:placetype":"venue"
},
  "geometry": {"coordinates":[5.772399,45.203705],"type":"Point"}
}