{
  "type": "Feature",
  "properties": {
    "addr:full":"B.P. 21, 62290 Noeux les Mines^^ZI, 62290 Noeux les Mines Nord Pas-de-Calais",
    "addr:postcode":"62290;62290 noeux",
    "addr:street":"B.P. 21;Mines;Pas-De-Calais",
    "iso:country":"FR",
    "sg:address":"B.P. 21, 62290 Noeux les Mines^^ZI, 62290 Noeux les Mines",
    "sg:orig_category":"Non-Classified Establishments",
    "sg:phone":"+33 3 21 64 58 48",
    "sg:province":"Nord Pas-de-Calais",
    "wof:name":"M.o.b. S.a.",
    "wof:placetype":"venue"
},
  "geometry": {"coordinates":[2.661913,50.480907],"type":"Point"}
}