{
  "type": "Feature",
  "properties": {
    "iso:country":"FR",
    "sg:address":"44600 Saint Nazaire",
    "sg:orig_category":"Unclassifiable Establishments",
    "sg:phone":"+33 2 51 10 91 00",
    "sg:province":"Pays de Loire",
    "wof:name":"Chantiers De L'atlantique S.a.",
    "wof:placetype":"venue"
},
  "geometry": {"coordinates":[-2.23916,47.276218],"type":"Point"}
}