{
  "type": "Feature",
  "properties": {
    "iso:country":"FR",
    "sg:address":"86 Rue Henri Gautier 44600 St Nazaire",
    "sg:classifiers":[
        {
            "category":"Utilities",
            "subcategory":"Electric",
            "type":"Services"
        }
    ],
    "sg:phone":"+33 2 40 22 31 14",
    "sg:postcode":"44600",
    "sg:province":"Pays de Loire",
    "sg:tags":[
        "electricity",
        "electronic",
        "electrical",
        "equipment"
    ],
    "wof:name":"Cge Distribution",
    "wof:placetype":"venue"
},
  "geometry": {"coordinates":[-2.207649,47.274311],"type":"Point"}
}