{
  "type": "Feature",
  "properties": {
    "addr:full":"11, Chemin du Barret - ZA, 13160 Ch\u00e2teaurenard Barr Alsace 67140",
    "addr:housenumber":"11",
    "addr:postcode":"13160;67140",
    "addr:street":"Chemin Du Barret Za;Barr",
    "iso:country":"FR",
    "sg:address":"11, Chemin du Barret - ZA, 13160 Ch\u00e2teaurenard",
    "sg:city":"Barr",
    "sg:orig_category":"Non-Classified Establishments",
    "sg:phone":"+33 4 90 94 78 02",
    "sg:postcode":"67140",
    "sg:province":"Alsace",
    "wof:name":"Hardy Et Compagnie S.a.",
    "wof:placetype":"venue"
},
  "geometry": {"coordinates":[4.85405,43.882477],"type":"Point"}
}