{
  "type": "Feature",
  "properties": {
    "iso:country":"FR",
    "sg:address":"B.P. 30",
    "sg:city":"Mertzwiller",
    "sg:orig_category":"Non-Classified Establishments",
    "sg:phone":"+33 3 88 80 27 00",
    "sg:postcode":"67580",
    "sg:province":"Alsace",
    "wof:name":"De Dietrich Thermique S.a.",
    "wof:placetype":"venue"
},
  "geometry": {"coordinates":[7.67937,48.862595],"type":"Point"}
}