{
  "type": "Feature",
  "properties": {
    "addr:full":"437 rue de la Meurthe 88650 St L\u00e9onard Lorraine",
    "addr:housenumber":"437",
    "addr:postcode":"88650",
    "addr:street":"Rue De La Meurthe",
    "iso:country":"FR",
    "sg:address":"437 rue de la Meurthe 88650 St L\u00e9onard",
    "sg:classifiers":[
        {
            "category":"Manufacturing",
            "subcategory":"Rubber & Plastics",
            "type":"Manufacturing & Wholesale Goods"
        }
    ],
    "sg:phone":"+33 3 29 50 01 11",
    "sg:province":"Lorraine",
    "sg:tags":[
        "processing"
    ],
    "wof:name":"P.s.v. Sa",
    "wof:placetype":"venue"
},
  "geometry": {"coordinates":[6.94963,48.221092],"type":"Point"}
}