{
  "type": "Feature",
  "properties": {
    "iso:country":"FR",
    "sg:address":"ZA",
    "sg:city":"Voves",
    "sg:orig_category":"Unclassifiable Establishments",
    "sg:phone":"+33 2 37 99 20 43",
    "sg:postcode":"28150",
    "sg:province":"Centre",
    "wof:name":"M.d.o. S.a. - Micro - Doc - Organisation",
    "wof:placetype":"venue"
},
  "geometry": {"coordinates":[1.622624,48.172813],"type":"Point"}
}