{
  "type": "Feature",
  "properties": {
    "addr:full":"120 rue Morel; Boite Postale 659; DOUAI; F-59506 Nord Pas-de-Calais",
    "addr:housenumber":"120;659",
    "addr:street":"Rue Morel Boite Postale;F-59506 Nord",
    "iso:country":"FR",
    "sg:address":"120 rue Morel; Boite Postale 659; DOUAI; F-59506",
    "sg:classifiers":[
        {
            "category":"Shopping",
            "subcategory":"Computers & Home Electronics",
            "type":"Retail Goods"
        }
    ],
    "sg:phone":"+33 3 27 93 74 74",
    "sg:province":"Nord Pas-de-Calais",
    "sg:tags":[
        "chamber",
        "commerce"
    ],
    "wof:name":"C.c.i. Douai",
    "wof:placetype":"venue"
},
  "geometry": {"coordinates":[3.0825,50.367538],"type":"Point"}
}