{
  "type": "Feature",
  "properties": {
    "addr:full":"16, Rte Boofzheim, 67860 Rhinau Rhinau Alsace 67860",
    "addr:housenumber":"16",
    "addr:postcode":"67860;67860",
    "addr:street":"Rte Boofzheim",
    "iso:country":"FR",
    "sg:address":"16, Rte Boofzheim, 67860 Rhinau",
    "sg:city":"Rhinau",
    "sg:orig_category":"Unclassifiable Establishments",
    "sg:phone":"+33 3 88 58 72 72",
    "sg:postcode":"67860",
    "sg:province":"Alsace",
    "wof:name":"Rhin Location S.a.",
    "wof:placetype":"venue"
},
  "geometry": {"coordinates":[7.698489,48.323685],"type":"Point"}
}