{
  "type": "Feature",
  "properties": {
    "iso:country":"FR",
    "sg:address":"103/105, Rue des 3 Fontanot - Immeuble Axe Etoile, 92022 Nanterre C\u00e9dex",
    "sg:orig_category":"Non-Classified Establishments",
    "sg:phone":"+33 1 55 69 32 32",
    "sg:province":"Languedoc-Roussillon",
    "wof:name":"Altys Multiservice S.a.",
    "wof:placetype":"venue"
},
  "geometry": {"coordinates":[2.224895,48.894882],"type":"Point"}
}