{
  "type": "Feature",
  "properties": {
    "addr:full":"B.P. 1001, 69612 Villeurbanne C\u00e9dex^^109, Rue du 1er Mars 1943, 69100 Villeurbanne Rhone-Alpes 69100",
    "addr:postcode":"69612;69100;69100",
    "addr:street":"B.P. 1001;Rue Du 1Er Mars 1943",
    "iso:country":"FR",
    "sg:address":"B.P. 1001, 69612 Villeurbanne C\u00e9dex^^109, Rue du 1er Mars 1943, 69100 Villeurbanne",
    "sg:orig_category":"Non-Classified Establishments",
    "sg:phone":"+33 4 72 35 31 72",
    "sg:postcode":"69100",
    "sg:province":"Rhone-Alpes",
    "wof:name":"Radialex S.a.",
    "wof:placetype":"venue"
},
  "geometry": {"coordinates":[4.87905,45.769596],"type":"Point"}
}