{
  "type": "Feature",
  "properties": {
    "addr:full":"1, Av. Charles Cros - Parc Cl\u00e9ment Ader, 34830 Jacou Languedoc-Roussillon",
    "addr:postcode":"34830",
    "addr:street":"Av. Charles Cros Parc Cle\u0301Ment Ader",
    "iso:country":"FR",
    "sg:address":"1, Av. Charles Cros - Parc Cl\u00e9ment Ader, 34830 Jacou",
    "sg:orig_category":"Non-Classified Establishments",
    "sg:phone":"+33 4 67 55 99 01",
    "sg:province":"Languedoc-Roussillon",
    "wof:name":"Faux And Co S.a.r.l.",
    "wof:placetype":"venue"
},
  "geometry": {"coordinates":[3.90169,43.656849],"type":"Point"}
}