{
  "type": "Feature",
  "properties": {
    "addr:full":"ZI les Quatre Tours - La Grande B\u00e9gude Venelles Provence-Alpes-C\u00f4te d'Azur 13770",
    "addr:postcode":"13770",
    "addr:street":"Zi Les Quatre Tours La Grande Be\u0301Gude Venelles",
    "iso:country":"FR",
    "sg:address":"ZI les Quatre Tours - La Grande B\u00e9gude",
    "sg:city":"Venelles",
    "sg:orig_category":"Non-Classified Establishments",
    "sg:phone":"+33 4 42 54 00 79",
    "sg:postcode":"13770",
    "sg:province":"Provence-Alpes-C\u00f4te d'Azur",
    "wof:name":"Etablissements Dossetto Seedo S.a.r.l.",
    "wof:placetype":"venue"
},
  "geometry": {"coordinates":[5.485145,43.599094],"type":"Point"}
}