{
  "type": "Feature",
  "properties": {
    "addr:full":"221 Av Francis De Pressens\u00e9 69200 V\u00e9nissieux Rhone-Alpes",
    "addr:housenumber":"221",
    "addr:postcode":"69200",
    "addr:street":"Av Francis De Pressense\u0301",
    "iso:country":"FR",
    "sg:address":"221 Av Francis De Pressens\u00e9 69200 V\u00e9nissieux",
    "sg:classifiers":[
        {
            "category":"Wholesale",
            "subcategory":"Machinery & Supplies",
            "type":"Manufacturing & Wholesale Goods"
        }
    ],
    "sg:phone":"+33 4 78 75 41 84",
    "sg:province":"Rhone-Alpes",
    "sg:tags":[
        "handling",
        "material",
        "-",
        "machine",
        "equipment",
        "engineering",
        "mechanical"
    ],
    "wof:name":"Teleflex Gallet",
    "wof:placetype":"venue"
},
  "geometry": {"coordinates":[4.875182,45.711681],"type":"Point"}
}