{
  "type": "Feature",
  "properties": {
    "addr:full":"B.P. 322000, 13799 Aix en Provence C\u00e9dex 03^^275, Rue Paul Langevin, 13100 Aix en Provence Bretagne 22000",
    "addr:housenumber":"322000;03 ^ ^ 275",
    "addr:postcode":"13799;13100;22000",
    "addr:street":"Ce\u0301Dex;Rue Paul Langevin;En Provence Bretagne",
    "iso:country":"FR",
    "sg:address":"B.P. 322000, 13799 Aix en Provence C\u00e9dex 03^^275, Rue Paul Langevin, 13100 Aix en Provence",
    "sg:orig_category":"Non-Classified Establishments",
    "sg:phone":"+33 4 42 16 30 30",
    "sg:postcode":"22000",
    "sg:province":"Bretagne",
    "wof:name":"Ast\u00e9ria S.a.",
    "wof:placetype":"venue"
},
  "geometry": {"coordinates":[5.49167,43.509033],"type":"Point"}
}