{
  "type": "Feature",
  "properties": {
    "iso:country":"FR",
    "sg:address":"19 Rue De Bretagne 38070 St Quentin Fallavier",
    "sg:classifiers":[
        {
            "category":"Professional",
            "type":"Services"
        }
    ],
    "sg:phone":"+33 4 74 82 19 19",
    "sg:postcode":"38070",
    "sg:province":"Rhone-Alpes",
    "sg:tags":[
        "transport",
        "road"
    ],
    "wof:name":"Nd Logistics",
    "wof:placetype":"venue"
},
  "geometry": {"coordinates":[5.110146,45.6455],"type":"Point"}
}