{
  "type": "Feature",
  "properties": {
    "iso:country":"FR",
    "sg:address":"1, Rue Mignard, 62100 Calais",
    "sg:orig_category":"Non-Classified Establishments",
    "sg:phone":"+33 3 21 97 31 77",
    "sg:province":"Nord Pas-de-Calais",
    "wof:name":"Soci\u00e9t\u00e9 Nouvelle Tresco S.a.",
    "wof:placetype":"venue"
},
  "geometry": {"coordinates":[1.874317,50.946346],"type":"Point"}
}