{
  "type": "Feature",
  "properties": {
    "iso:country":"FR",
    "sg:address":"5 Esplanade Compans Caffarelli B\u00e2t A 31000 Toulouse",
    "sg:classifiers":[
        {
            "category":"Food Court",
            "type":"Food & Drink"
        }
    ],
    "sg:phone":"+33 5 61 12 64 00",
    "sg:postcode":"31000",
    "sg:province":"Midi Pyr\u00e9n\u00e9es",
    "sg:tags":[
        "product",
        "related"
    ],
    "wof:name":"Espace Paul Ricard",
    "wof:placetype":"venue"
},
  "geometry": {"coordinates":[1.435147,43.61084],"type":"Point"}
}