{
  "type": "Feature",
  "properties": {
    "addr:full":"14, Rue de la Batterie - Parc d'Activit\u00e9 Activa, 67118 Geispolsheim Geispolsheim Alsace 67400",
    "addr:housenumber":"14",
    "addr:postcode":"67118;67400",
    "addr:street":"Rue De La Batterie Parc D'Activite \u0301 Activa",
    "iso:country":"FR",
    "sg:address":"14, Rue de la Batterie - Parc d'Activit\u00e9 Activa, 67118 Geispolsheim",
    "sg:city":"Geispolsheim",
    "sg:orig_category":"Non-Classified Establishments",
    "sg:phone":"+33 3 88 67 38 77",
    "sg:postcode":"67400",
    "sg:province":"Alsace",
    "wof:name":"Sc\u00e8ne Et Son S.a.r.l.",
    "wof:placetype":"venue"
},
  "geometry": {"coordinates":[7.685043,48.536156],"type":"Point"}
}