{
  "type": "Feature",
  "properties": {
    "addr:full":"B.P. 517, 85505 Les Herbiers C\u00e9dex^^43, rue du 11 Novembre 1918, 85500 Les Herbiers Pays de Loire",
    "addr:housenumber":"b.p. 517",
    "addr:postcode":"85505;85500",
    "addr:street":"Herbiers;Rue Du 11 Novembre 1918;Herbiers",
    "iso:country":"FR",
    "sg:address":"B.P. 517, 85505 Les Herbiers C\u00e9dex^^43, rue du 11 Novembre 1918, 85500 Les Herbiers",
    "sg:orig_category":"Non-Classified Establishments",
    "sg:phone":"+33 2 51 92 98 98",
    "sg:province":"Pays de Loire",
    "wof:name":"Novestyle S.a.",
    "wof:placetype":"venue"
},
  "geometry": {"coordinates":[-1.019829,46.815769],"type":"Point"}
}