{
  "type": "Feature",
  "properties": {
    "iso:country":"FR",
    "sg:address":"Place de l'H\u00f4tel de Ville",
    "sg:city":"Reims C\u00e9dex",
    "sg:orig_category":"Unclassifiable Establishments",
    "sg:phone":"+33 3 26 77 78 79",
    "sg:postcode":"51096",
    "sg:province":"Alsace",
    "wof:name":"Mairie De Reims",
    "wof:placetype":"venue"
},
  "geometry": {"coordinates":[4.03384,49.25415],"type":"Point"}
}