{
  "type": "Feature",
  "properties": {
    "iso:country":"FR",
    "sg:address":"81210 Roquecourbe",
    "sg:orig_category":"Unclassifiable Establishments",
    "sg:phone":"+33 5 63 75 80 94",
    "sg:province":"Midi Pyr\u00e9n\u00e9es",
    "wof:name":"Gout - Usine Du Parc S.a.",
    "wof:placetype":"venue"
},
  "geometry": {"coordinates":[2.293234,43.666641],"type":"Point"}
}