{
  "type": "Feature",
  "properties": {
    "addr:full":"B.P. 61, 91072 Bondoufle Cedex^^22, Rue Gutenberg - ZI la Marini\u00e8re, 91070 Bondoufle Ile de France",
    "addr:postcode":"91072;91070;ile",
    "addr:street":"B.P. 61;Rue Gutenberg Zi La Marinie\u0300Re",
    "iso:country":"FR",
    "sg:address":"B.P. 61, 91072 Bondoufle Cedex^^22, Rue Gutenberg - ZI la Marini\u00e8re, 91070 Bondoufle",
    "sg:orig_category":"Non-Classified Establishments",
    "sg:phone":"+33 1 60 86 87 78",
    "sg:province":"Ile de France",
    "wof:name":"Euro Transmissions S.a.",
    "wof:placetype":"venue"
},
  "geometry": {"coordinates":[2.379516,48.615681],"type":"Point"}
}