{
  "type": "Feature",
  "properties": {
    "iso:country":"FR",
    "sg:address":"Zi De Eaux Blanches 34200 S\u00eate",
    "sg:classifiers":[
        {
            "category":"Farming",
            "subcategory":"Livestock Farm",
            "type":"Manufacturing & Wholesale Goods"
        }
    ],
    "sg:phone":"+33 4 67 48 65 49",
    "sg:postcode":"34200",
    "sg:province":"Languedoc-Roussillon",
    "sg:tags":[
        "breeding",
        "agriculture",
        "animal"
    ],
    "wof:name":"Azais J R Maree Sarl",
    "wof:placetype":"venue"
},
  "geometry": {"coordinates":[-75.92742200000001,40.3978],"type":"Point"}
}