{
  "type": "Feature",
  "properties": {
    "addr:full":"25 Avenue Alfred Bouat 34140 Bouzigues Languedoc-Roussillon 34140",
    "addr:housenumber":"25",
    "addr:postcode":"34140;34140",
    "addr:street":"Avenue Alfred Bouat",
    "iso:country":"FR",
    "sg:address":"25 Avenue Alfred Bouat 34140 Bouzigues",
    "sg:classifiers":[
        {
            "category":"Manufacturing",
            "subcategory":"Metals",
            "type":"Manufacturing & Wholesale Goods"
        }
    ],
    "sg:phone":"+33 4 67 78 31 22",
    "sg:postcode":"34140",
    "sg:province":"Languedoc-Roussillon",
    "sg:tags":[
        "-",
        "machine",
        "equipment",
        "engineering",
        "machinery",
        "mechanical"
    ],
    "wof:name":"Caubel Et Enfants",
    "wof:placetype":"venue"
},
  "geometry": {"coordinates":[3.65449,43.452625],"type":"Point"}
}