{
  "type": "Feature",
  "properties": {
    "addr:full":"Rue Pablo Neruda Zac De Madere 33140 Villenave D Ornon Cadaujac Aquitaine 33140",
    "addr:housenumber":"cadaujac",
    "addr:postcode":"33140;33140",
    "addr:street":"Rue Pablo Neruda Zac De Madere",
    "iso:country":"FR",
    "sg:address":"Rue Pablo Neruda Zac De Madere 33140 Villenave D Ornon",
    "sg:city":"Cadaujac",
    "sg:classifiers":[
        {
            "category":"Manufacturing",
            "subcategory":"Wood Products",
            "type":"Manufacturing & Wholesale Goods"
        }
    ],
    "sg:phone":"+33 5 57 35 15 40",
    "sg:postcode":"33140",
    "sg:province":"Aquitaine",
    "sg:tags":[
        "furniture"
    ],
    "wof:name":"Suber France",
    "wof:placetype":"venue"
},
  "geometry": {"coordinates":[-0.581072,44.785847],"type":"Point"}
}