{
  "type": "Feature",
  "properties": {
    "addr:full":"Rue Jean Moulin 72110 Bonnetable Pays de Loire 72110",
    "addr:postcode":"72110;72110",
    "addr:street":"Rue Jean Moulin;Bonnetable",
    "iso:country":"FR",
    "sg:address":"Rue Jean Moulin 72110 Bonnetable",
    "sg:classifiers":[
        {
            "category":"Shopping",
            "subcategory":"Clothing, Apparel, & Fashions",
            "type":"Retail Goods"
        }
    ],
    "sg:phone":"+33 2 43 52 14 14",
    "sg:postcode":"72110",
    "sg:province":"Pays de Loire",
    "sg:tags":[
        "textile",
        "clothing",
        "clothes"
    ],
    "wof:name":"Manufacture De Confection Du Saosnois Sa",
    "wof:placetype":"venue"
},
  "geometry": {"coordinates":[0.416424,48.171852],"type":"Point"}
}