{
  "type": "Feature",
  "properties": {
    "iso:country":"FR",
    "sg:address":"34 av L\u00e9on Blum; Quimper",
    "sg:classifiers":[
        {
            "category":"Banks & Credit Unions",
            "subcategory":"Bank",
            "type":"Services"
        }
    ],
    "sg:phone":"+33 3398906921",
    "sg:province":"Aquitaine",
    "wof:name":"Cr\u00e9dit Mutuel De Bretagne",
    "wof:placetype":"venue"
},
  "geometry": {"coordinates":[-4.079694,47.986095],"type":"Point"}
}