{
  "type": "Feature",
  "properties": {
    "addr:full":"12, Av. Garibaldi, 69120 Vaulx en Velin Rhone-Alpes",
    "addr:postcode":"69120",
    "addr:street":"12 Av. Garibaldi",
    "iso:country":"FR",
    "sg:address":"12, Av. Garibaldi, 69120 Vaulx en Velin",
    "sg:orig_category":"Unclassifiable Establishments",
    "sg:phone":"+33 4 72 37 03 05",
    "sg:province":"Rhone-Alpes",
    "wof:name":"Etablissement Jardoux",
    "wof:placetype":"venue"
},
  "geometry": {"coordinates":[4.933364,45.767174],"type":"Point"}
}