{
  "type": "Feature",
  "properties": {
    "addr:full":"38 R Antoine Lumi\u00e8re 69008 Lyon Rhone-Alpes 69008",
    "addr:housenumber":"38",
    "addr:postcode":"69008;69008",
    "addr:street":"R Antoine Lumie\u0300Re",
    "iso:country":"FR",
    "sg:address":"38 R Antoine Lumi\u00e8re 69008 Lyon",
    "sg:classifiers":[
        {
            "category":"Professional",
            "type":"Services"
        }
    ],
    "sg:phone":"+33 4 78 00 74 70",
    "sg:postcode":"69008",
    "sg:province":"Rhone-Alpes",
    "sg:tags":[
        "transport",
        "road"
    ],
    "wof:name":"Guille Sa",
    "wof:placetype":"venue"
},
  "geometry": {"coordinates":[4.867972,45.740955],"type":"Point"}
}