{
  "type": "Feature",
  "properties": {
    "iso:country":"FR",
    "sg:address":"18, Rue de l'Industrie, 56500 Bignan",
    "sg:city":"Bignan",
    "sg:orig_category":"Non-Classified Establishments",
    "sg:phone":"+33 2 97 60 00 83",
    "sg:postcode":"56500",
    "sg:province":"Bretagne",
    "wof:name":"Ronsard S.a.",
    "wof:placetype":"venue"
},
  "geometry": {"coordinates":[-2.775155,47.878426],"type":"Point"}
}