{
  "type": "Feature",
  "properties": {
    "iso:country":"FR",
    "sg:address":"18 Rue Du Grand S\u00e9minaire 28630 Le Coudray",
    "sg:city":"Le Coudray",
    "sg:classifiers":[
        {
            "category":"Professional",
            "type":"Services"
        }
    ],
    "sg:phone":"+33 2 37 30 28 15",
    "sg:postcode":"28630",
    "sg:province":"Centre",
    "sg:tags":[
        "transport",
        "road"
    ],
    "wof:name":"Ambulance Chartraine Sarl",
    "wof:placetype":"venue"
},
  "geometry": {"coordinates":[1.50973,48.42643],"type":"Point"}
}