{
  "type": "Feature",
  "properties": {
    "addr:full":"25, Av. du Docteur Arnold Netter, 75012 Paris Ile de France",
    "addr:postcode":"75012",
    "addr:street":"25 Av. Du Docteur Arnold Netter",
    "iso:country":"FR",
    "sg:address":"25, Av. du Docteur Arnold Netter, 75012 Paris",
    "sg:orig_category":"Unclassifiable Establishments",
    "sg:phone":"+33 1 43 47 22 88",
    "sg:province":"Ile de France",
    "wof:name":"J.m Simon S.a.r.l.",
    "wof:placetype":"venue"
},
  "geometry": {"coordinates":[2.404886,48.842453],"type":"Point"}
}