{
  "type": "Feature",
  "properties": {
    "addr:full":"C\u00f4te De St Pierre 12000 Rodez Midi Pyr\u00e9n\u00e9es 12000",
    "addr:postcode":"12000;12000",
    "addr:street":"Co\u0302Te De St Pierre",
    "iso:country":"FR",
    "sg:address":"C\u00f4te De St Pierre 12000 Rodez",
    "sg:classifiers":[
        {
            "category":"Farming",
            "subcategory":"Livestock Farm",
            "type":"Manufacturing & Wholesale Goods"
        }
    ],
    "sg:phone":"+33 5 65 73 41 00",
    "sg:postcode":"12000",
    "sg:province":"Midi Pyr\u00e9n\u00e9es",
    "sg:tags":[
        "product",
        "cereal",
        "food",
        "related",
        "horticul",
        "grain",
        "animal",
        "breeding",
        "agriculture"
    ],
    "wof:name":"Ragt",
    "wof:placetype":"venue"
},
  "geometry": {"coordinates":[2.556696,44.358059],"type":"Point"}
}