{
  "type": "Feature",
  "properties": {
    "addr:full":"B.P. 228, 22402 Lamballe C\u00e9dex^^1, Rue Jeannaie Marou\u00e9 - Z.I., 22400 Lamballe Lamballe Bretagne 22400",
    "addr:housenumber":"b.p. 228",
    "addr:postcode":"22402;22400;22400",
    "addr:street":"Rue Jeannaie Maroue\u0301 Z.I.",
    "iso:country":"FR",
    "sg:address":"B.P. 228, 22402 Lamballe C\u00e9dex^^1, Rue Jeannaie Marou\u00e9 - Z.I., 22400 Lamballe",
    "sg:city":"Lamballe",
    "sg:orig_category":"Non-Classified Establishments",
    "sg:phone":"+33 2 96 30 72 72",
    "sg:postcode":"22400",
    "sg:province":"Bretagne",
    "wof:name":"Coop\u00e9rative Agricole De Gouessant",
    "wof:placetype":"venue"
},
  "geometry": {"coordinates":[-2.539697,48.428795],"type":"Point"}
}