{
  "type": "Feature",
  "properties": {
    "iso:country":"FR",
    "sg:address":"3, Rue Edouard Branly, 45700 Villemandeur",
    "sg:city":"Villemandeur",
    "sg:orig_category":"Non-Classified Establishments",
    "sg:phone":"+33 2 38 93 08 60",
    "sg:postcode":"45700",
    "sg:province":"Centre",
    "wof:name":"A.d. S.a.",
    "wof:placetype":"venue"
},
  "geometry": {"coordinates":[2.716865,47.976902],"type":"Point"}
}