{
  "type": "Feature",
  "properties": {
    "iso:country":"FR",
    "sg:address":"1 Rue Du Mesnil 60420 Royaucourt",
    "sg:classifiers":[
        {
            "category":"Manufacturing",
            "subcategory":"Metals",
            "type":"Manufacturing & Wholesale Goods"
        }
    ],
    "sg:phone":"+33 3 44 51 22 83",
    "sg:postcode":"60420",
    "sg:province":"Picardie",
    "sg:tags":[
        "pipe",
        "sheet",
        "-",
        "metalworking",
        "metallic",
        "metallurgy",
        "finished"
    ],
    "wof:name":"Romanyszyn Sa",
    "wof:placetype":"venue"
},
  "geometry": {"coordinates":[2.528158,49.611069],"type":"Point"}
}