{
  "type": "Feature",
  "properties": {
    "addr:full":"9 Boulevard De La Republique Cosne Cours Sur Loire Bourgogne 58200",
    "addr:housenumber":"9",
    "addr:postcode":"58200",
    "addr:street":"Boulevard De La;Bourgogne",
    "iso:country":"FR",
    "sg:address":"9 Boulevard De La Republique",
    "sg:city":"Cosne Cours Sur Loire",
    "sg:classifiers":[
        {
            "category":"Banks & Credit Unions",
            "subcategory":"Financial Services",
            "type":"Services"
        }
    ],
    "sg:phone":"+33 3 86 39 57 00",
    "sg:postcode":"58200",
    "sg:province":"Bourgogne",
    "sg:tags":[
        "banking",
        "finance",
        "insurance"
    ],
    "wof:name":"Caisse D Epargne Et De Prevoyance De Bourgognecosne Cours Sur Loire",
    "wof:placetype":"venue"
},
  "geometry": {"coordinates":[2.925595,47.410332],"type":"Point"}
}