{
  "type": "Feature",
  "properties": {
    "addr:full":"Bd Judovici Honfleur Basse Normandie 14600",
    "addr:postcode":"14600",
    "addr:street":"Basse",
    "iso:country":"FR",
    "sg:address":"Bd Judovici",
    "sg:city":"Honfleur",
    "sg:orig_category":"Unclassifiable Establishments",
    "sg:phone":"+33 2 31 89 57 70",
    "sg:postcode":"14600",
    "sg:province":"Basse Normandie",
    "wof:name":"Montage Lebrun Cnc2 S.a.r.l.",
    "wof:placetype":"venue"
},
  "geometry": {"coordinates":[0.270977,49.425571],"type":"Point"}
}