{
  "type": "Feature",
  "properties": {
    "addr:full":"B.P. 12 Languidic Bretagne 56440",
    "addr:postcode":"56440",
    "addr:street":"B.P. 12 Languidic Bretagne",
    "iso:country":"FR",
    "sg:address":"B.P. 12",
    "sg:city":"Languidic",
    "sg:orig_category":"Non-Classified Establishments",
    "sg:phone":"+33 2 97 85 99 00",
    "sg:postcode":"56440",
    "sg:province":"Bretagne",
    "wof:name":"Unicopa Nutrition Animale",
    "wof:placetype":"venue"
},
  "geometry": {"coordinates":[-3.162875,47.78611],"type":"Point"}
}