{
  "type": "Feature",
  "properties": {
    "addr:full":"B.P. 266, 68332 Huningue C\u00e9dex^^5, Rue du Rhin, 68330 Huningue Huningue Alsace 68330",
    "addr:housenumber":"b.p. 266",
    "addr:postcode":"68332;68330;68330",
    "addr:street":"Rue Du Rhin",
    "iso:country":"FR",
    "sg:address":"B.P. 266, 68332 Huningue C\u00e9dex^^5, Rue du Rhin, 68330 Huningue",
    "sg:city":"Huningue",
    "sg:orig_category":"Non-Classified Establishments",
    "sg:phone":"+33 3 89 70 26 00",
    "sg:postcode":"68330",
    "sg:province":"Alsace",
    "wof:name":"Fel Fiege Euro Logistik S.a.r.l.",
    "wof:placetype":"venue"
},
  "geometry": {"coordinates":[7.583745,47.59119],"type":"Point"}
}