{
  "type": "Feature",
  "properties": {
    "addr:full":"Z d'Activit\u00e9 42940 Chatelneuf Rhone-Alpes 42940",
    "addr:postcode":"42940;42940",
    "addr:street":"\u0301;Rhone-Alpes",
    "iso:country":"FR",
    "sg:address":"Z d'Activit\u00e9 42940 Chatelneuf",
    "sg:classifiers":[
        {
            "category":"Autos & Motor Vehicles",
            "subcategory":"Auto Supplies",
            "type":"Retail Goods"
        }
    ],
    "sg:phone":"+33 4 77 76 82 95",
    "sg:postcode":"42940",
    "sg:province":"Rhone-Alpes",
    "sg:tags":[
        "car",
        "brake"
    ],
    "wof:name":"Beringer Sa",
    "wof:placetype":"venue"
},
  "geometry": {"coordinates":[3.9814,45.637878],"type":"Point"}
}