{
  "type": "Feature",
  "properties": {
    "addr:full":"29, Bd de la R\u00e9publique, 34110 Frontignan Languedoc-Roussillon",
    "addr:housenumber":"29",
    "addr:postcode":"34110",
    "addr:street":"Bd De La Re\u0301Publique",
    "iso:country":"FR",
    "sg:address":"29, Bd de la R\u00e9publique, 34110 Frontignan",
    "sg:orig_category":"Unclassifiable Establishments",
    "sg:phone":"+33 4 67 48 13 76",
    "sg:province":"Languedoc-Roussillon",
    "wof:name":"Balta Et Compagnie S.n.c.",
    "wof:placetype":"venue"
},
  "geometry": {"coordinates":[3.758528,43.44442],"type":"Point"}
}