{
  "type": "Feature",
  "properties": {
    "iso:country":"FR",
    "sg:address":"164 rue Jeanne d'Arc 75013 Paris",
    "sg:classifiers":[
        {
            "category":"Travel",
            "subcategory":"Travel Agent",
            "type":"Entertainment"
        }
    ],
    "sg:phone":"+33 1 43 36 10 11",
    "sg:postcode":"75013",
    "sg:province":"Ile de France",
    "sg:tags":[
        "incentive"
    ],
    "wof:name":"Oriensce S.a.r.l.",
    "wof:placetype":"venue"
},
  "geometry": {"coordinates":[2.367239,48.830154],"type":"Point"}
}