{
  "type": "Feature",
  "properties": {
    "addr:full":"B.P. 124, 44503 La Baule Escoublac C\u00e9dex^^3, Av. des No\u00eblles, 44500 La Baule Escoublac Pays de Loire",
    "addr:housenumber":"b.p. 124",
    "addr:postcode":"44503;44500",
    "addr:street":"Av. Des Noe\u0308Lles",
    "iso:country":"FR",
    "sg:address":"B.P. 124, 44503 La Baule Escoublac C\u00e9dex^^3, Av. des No\u00eblles, 44500 La Baule Escoublac",
    "sg:orig_category":"Non-Classified Establishments",
    "sg:phone":"+33 2 51 75 07 00",
    "sg:province":"Pays de Loire",
    "wof:name":"L.c.a. S.a.r.l. - La Nouvelle Imprimerie",
    "wof:placetype":"venue"
},
  "geometry": {"coordinates":[-2.391584,47.281715],"type":"Point"}
}