{
  "type": "Feature",
  "properties": {
    "iso:country":"FR",
    "sg:address":"70 Rue Paix 71210 Montchanin",
    "sg:city":"Montchanin",
    "sg:classifiers":[
        {
            "category":"Professional",
            "subcategory":"Engineering",
            "type":"Services"
        }
    ],
    "sg:phone":"+33 3 85 73 09 20",
    "sg:postcode":"71210",
    "sg:province":"Bourgogne",
    "sg:tags":[
        "machine",
        "-",
        "mechanical"
    ],
    "wof:name":"Fonderie D'ajustage Reunis Sa",
    "wof:placetype":"venue"
},
  "geometry": {"coordinates":[4.464477,46.743145],"type":"Point"}
}