{
  "type": "Feature",
  "properties": {
    "iso:country":"FR",
    "sg:address":"34, Rue Rahling, 67430 Butten",
    "sg:city":"Butten",
    "sg:orig_category":"Non-Classified Establishments",
    "sg:phone":"+33 3 88 01 40 76",
    "sg:postcode":"67430",
    "sg:province":"Alsace",
    "wof:name":"Schmidt Fr\u00e8res S.a.r.l.",
    "wof:placetype":"venue"
},
  "geometry": {"coordinates":[7.21965,48.973404],"type":"Point"}
}