{
  "type": "Feature",
  "properties": {
    "addr:full":"B.P. 2, 88540 Bussang^^6, Av de la Gare, 88540 Bussang Lorraine",
    "addr:housenumber":"2",
    "addr:postcode":"88540;88540",
    "addr:street":"B.P.;Av De La Gare",
    "iso:country":"FR",
    "sg:address":"B.P. 2, 88540 Bussang^^6, Av de la Gare, 88540 Bussang",
    "sg:orig_category":"Non-Classified Establishments",
    "sg:phone":"+33 3 29 61 51 75",
    "sg:province":"Lorraine",
    "wof:name":"Menuiserie Des Hautes Vosges S.a.r.l.",
    "wof:placetype":"venue"
},
  "geometry": {"coordinates":[6.853918,47.885452],"type":"Point"}
}