{
  "type": "Feature",
  "properties": {
    "iso:country":"FR",
    "sg:address":"B.P. 532, 03108 Montlu\u00e7on C\u00e9dex^^46/48, Rue Benoist d'Azy - Porte d'Auvergne, 03100 Montlu\u00e7on",
    "sg:city":"Montlu\u00e7on",
    "sg:orig_category":"Non-Classified Establishments",
    "sg:phone":"+33 4 70 03 48 50",
    "sg:postcode":"03100",
    "sg:province":"Auvergne",
    "wof:name":"Alstom Contracting Entreprise Centre Est S.a.",
    "wof:placetype":"venue"
},
  "geometry": {"coordinates":[2.606608,46.356499],"type":"Point"}
}