{
  "type": "Feature",
  "properties": {
    "addr:full":"35 Rue Lavoisier N\u00b0 4 79301 Bressuire Poitou-Charentes",
    "addr:housenumber":"35;n\u00b0 4",
    "addr:postcode":"79301",
    "addr:street":"Rue Lavoisier",
    "iso:country":"FR",
    "sg:address":"35 Rue Lavoisier",
    "sg:city":"N\u00b0 4 79301 Bressuire",
    "sg:classifiers":[
        {
            "category":"Manufacturing",
            "subcategory":"Tools & Machinery",
            "type":"Manufacturing & Wholesale Goods"
        }
    ],
    "sg:phone":"+33 5 49 65 04 14",
    "sg:province":"Poitou-Charentes",
    "sg:tags":[
        "metallurgy",
        "metalworking"
    ],
    "wof:name":"Ets Laveix Sa",
    "wof:placetype":"venue"
},
  "geometry": {"coordinates":[-0.492539,46.840065],"type":"Point"}
}