{
  "type": "Feature",
  "properties": {
    "iso:country":"FR",
    "sg:address":"La Joneliere",
    "sg:city":"Sportif 44311 Nantes Cedex 3",
    "sg:classifiers":[
        {
            "category":"Sports & Exercise",
            "subcategory":"Sports Center",
            "type":"Entertainment"
        }
    ],
    "sg:phone":"+33 2 40 37 29 29",
    "sg:province":"R\u00e9gion Pays de la Loire",
    "wof:name":"Fc Nantes Atlantique",
    "wof:placetype":"venue"
},
  "geometry": {"coordinates":[-1.54947,47.219791],"type":"Point"}
}