{
  "type": "Feature",
  "properties": {
    "addr:full":"Av. Mar\u00e9chal Juin Bayonne Aquitaine 64100",
    "addr:postcode":"64100",
    "addr:street":"Av. Mare\u0301Chal Juin",
    "iso:country":"FR",
    "sg:address":"Av. Mar\u00e9chal Juin",
    "sg:city":"Bayonne",
    "sg:orig_category":"Unclassifiable Establishments",
    "sg:phone":"+33 5 53 55 00 01",
    "sg:postcode":"64100",
    "sg:province":"Aquitaine",
    "wof:name":"Omnia Equip Auto S.a.",
    "wof:placetype":"venue"
},
  "geometry": {"coordinates":[-1.461739,43.490437],"type":"Point"}
}