{
  "type": "Feature",
  "properties": {
    "iso:country":"FR",
    "sg:address":"La Vaure 63120 Courpi\u00e8re",
    "sg:city":"Courpi\u00e8re",
    "sg:orig_category":"Unclassifiable Establishments",
    "sg:phone":"+33 4 73 53 29 00",
    "sg:postcode":"63120",
    "sg:province":"Auvergne",
    "wof:name":"S.c.i.e. S.a.",
    "wof:placetype":"venue"
},
  "geometry": {"coordinates":[3.535275,45.715576],"type":"Point"}
}