{
  "type": "Feature",
  "properties": {
    "addr:full":"67 Rte Du Blanc 36700 Ch\u00e2tillon Sur Indre Arpheuilles Centre 36700",
    "addr:housenumber":"67",
    "addr:postcode":"36700;36700",
    "addr:street":"Rte Du Blanc",
    "iso:country":"FR",
    "sg:address":"67 Rte Du Blanc 36700 Ch\u00e2tillon Sur Indre",
    "sg:city":"Arpheuilles",
    "sg:classifiers":[
        {
            "category":"Manufacturing",
            "subcategory":"Rubber & Plastics",
            "type":"Manufacturing & Wholesale Goods"
        }
    ],
    "sg:phone":"+33 2 54 38 83 36",
    "sg:postcode":"36700",
    "sg:province":"Centre",
    "wof:name":"Aflex Sarl",
    "wof:placetype":"venue"
},
  "geometry": {"coordinates":[1.16534,46.972836],"type":"Point"}
}