{
  "type": "Feature",
  "properties": {
    "addr:full":"5 Rue Jean Charcot 26100 Romans Sur Is\u00e8re Rhone-Alpes 26100",
    "addr:housenumber":"5",
    "addr:postcode":"26100;26100",
    "addr:street":"Rue Jean Charcot",
    "iso:country":"FR",
    "sg:address":"5 Rue Jean Charcot 26100 Romans Sur Is\u00e8re",
    "sg:classifiers":[
        {
            "category":"Professional",
            "subcategory":"Computer Services",
            "type":"Services"
        }
    ],
    "sg:phone":"+33 4 75 02 84 34",
    "sg:postcode":"26100",
    "sg:province":"Rhone-Alpes",
    "sg:tags":[
        "information",
        "technology",
        "software"
    ],
    "wof:name":"Fingerprint Sa",
    "wof:placetype":"venue"
},
  "geometry": {"coordinates":[5.087177,45.048573],"type":"Point"}
}