{
  "type": "Feature",
  "properties": {
    "addr:full":"41, Rue de la Jappe, 59155 Faches Thumesnil Nord Pas-de-Calais",
    "addr:housenumber":"41",
    "addr:postcode":"59155",
    "addr:street":"Rue De La Jappe;Thumesnil",
    "iso:country":"FR",
    "sg:address":"41, Rue de la Jappe, 59155 Faches Thumesnil",
    "sg:orig_category":"Unclassifiable Establishments",
    "sg:phone":"+33 3 20 96 33 70",
    "sg:province":"Nord Pas-de-Calais",
    "wof:name":"Verbruggen S.a.",
    "wof:placetype":"venue"
},
  "geometry": {"coordinates":[3.070545,50.601566],"type":"Point"}
}