{
  "type": "Feature",
  "properties": {
    "iso:country":"FR",
    "sg:address":"B.P. 438, 69655 Villefranche sur Sa\u00f4ne C\u00e9dex^^299, Rue Grange Morin - ZI Nord Arnas, 69400 Villefran",
    "sg:orig_category":"Non-Classified Establishments",
    "sg:phone":"+33 4 74 02 38 00",
    "sg:province":"Rhone-Alpes",
    "wof:name":"National Starch & Chemical S.a.",
    "wof:placetype":"venue"
},
  "geometry": {"coordinates":[4.64756,45.957378],"type":"Point"}
}