{
  "type": "Feature",
  "properties": {
    "addr:full":"5 Rue Saint Guillaume 92400 Courbevoie Ile de France 92400",
    "addr:housenumber":"5",
    "addr:postcode":"92400;92400",
    "addr:street":"Rue Saint Guillaume",
    "iso:country":"FR",
    "sg:address":"5 Rue Saint Guillaume 92400 Courbevoie",
    "sg:classifiers":[
        {
            "category":"Professional",
            "subcategory":"Engineering",
            "type":"Services"
        }
    ],
    "sg:phone":"+33 1 41 99 95 95",
    "sg:postcode":"92400",
    "sg:province":"Ile de France",
    "sg:tags":[
        "machine",
        "-",
        "mechanical"
    ],
    "wof:name":"Delostal Et Thibault",
    "wof:placetype":"venue"
},
  "geometry": {"coordinates":[2.281133,48.902489],"type":"Point"}
}