{
  "type": "Feature",
  "properties": {
    "addr:full":"3 Chemin De L Usine 17250 Pont L Abbe D Arnoult Poitou-Charentes 17250",
    "addr:housenumber":"3",
    "addr:postcode":"17250;17250",
    "addr:street":"Chemin De L Usine;Arnoult",
    "iso:country":"FR",
    "sg:address":"3 Chemin De L Usine 17250 Pont L Abbe D Arnoult",
    "sg:classifiers":[
        {
            "category":"Farming",
            "subcategory":"Farm & Veterinary Services",
            "type":"Manufacturing & Wholesale Goods"
        }
    ],
    "sg:phone":"+33 5 46 90 22 88",
    "sg:postcode":"17250",
    "sg:province":"Poitou-Charentes",
    "sg:tags":[
        "food",
        "product",
        "breeding",
        "animal",
        "related"
    ],
    "wof:name":"Complements De Saintonge",
    "wof:placetype":"venue"
},
  "geometry": {"coordinates":[-77.524399,39.738201],"type":"Point"}
}