{
  "type": "Feature",
  "properties": {
    "iso:country":"FR",
    "sg:address":"Chemin des Carri\u00e8res",
    "sg:city":"Chalezeule",
    "sg:orig_category":"Unclassifiable Establishments",
    "sg:phone":"+33 3 81 50 03 01",
    "sg:postcode":"25220",
    "sg:province":"Franche Comt\u00e9",
    "wof:name":"Riva S.a.r.l.",
    "wof:placetype":"venue"
},
  "geometry": {"coordinates":[6.07996,47.283707],"type":"Point"}
}