{
  "type": "Feature",
  "properties": {
    "addr:full":"B.P. 70252 H\u00e9rouville Saint Clair C\u00e9dex Basse-Normandie 14209",
    "addr:postcode":"70252;ce\u0301dex;14209",
    "iso:country":"FR",
    "sg:address":"B.P. 70252",
    "sg:city":"H\u00e9rouville Saint Clair C\u00e9dex",
    "sg:orig_category":"Non-Classified Establishments",
    "sg:phone":"+33 2 31 06 91 91",
    "sg:postcode":"14209",
    "sg:province":"Basse-Normandie",
    "wof:name":"Silog S.a.",
    "wof:placetype":"venue"
},
  "geometry": {"coordinates":[-0.328299,49.203964],"type":"Point"}
}