{
  "type": "Feature",
  "properties": {
    "iso:country":"FR",
    "sg:address":"12 Route D Espagne 66760 Ur",
    "sg:classifiers":[
        {
            "category":"Shopping",
            "subcategory":"Computers & Home Electronics",
            "type":"Retail Goods"
        }
    ],
    "sg:phone":"+33 4 68 04 82 75",
    "sg:postcode":"66760",
    "sg:province":"Languedoc-Roussillon",
    "sg:tags":[
        "household",
        "appliance",
        "telecommunication",
        "audio-visual"
    ],
    "wof:name":"Fortier Daniel",
    "wof:placetype":"venue"
},
  "geometry": {"coordinates":[1.939965,42.459583],"type":"Point"}
}