{
  "type": "Feature",
  "properties": {
    "addr:full":"10 Avenue L\u00e9once Duteil 86100 Ch\u00e2tellerault Poitou-Charentes 86100",
    "addr:housenumber":"10",
    "addr:postcode":"86100;86100",
    "addr:street":"Avenue Le\u0301Once Duteil",
    "iso:country":"FR",
    "sg:address":"10 Avenue L\u00e9once Duteil 86100 Ch\u00e2tellerault",
    "sg:classifiers":[
        {
            "category":"Manufacturing",
            "subcategory":"Aerospace",
            "type":"Manufacturing & Wholesale Goods"
        }
    ],
    "sg:phone":"+33 5 49 02 53 40",
    "sg:postcode":"86100",
    "sg:province":"Poitou-Charentes",
    "sg:tags":[
        "equipment",
        "aeronautic",
        "transport",
        "vehicle"
    ],
    "wof:name":"Hydrautest",
    "wof:placetype":"venue"
},
  "geometry": {"coordinates":[0.53653,46.827099],"type":"Point"}
}