{
  "type": "Feature",
  "properties": {
    "addr:full":"Parc D'Activites Des Tourrais 69290 Craponne Rhone-Alpes 69290",
    "addr:postcode":"69290;69290",
    "iso:country":"FR",
    "sg:address":"Parc D'Activites Des Tourrais 69290 Craponne",
    "sg:classifiers":[
        {
            "category":"Manufacturing",
            "subcategory":"Printing",
            "type":"Manufacturing & Wholesale Goods"
        }
    ],
    "sg:phone":"+33 4 78 57 80 80",
    "sg:postcode":"69290",
    "sg:province":"Rhone-Alpes",
    "sg:tags":[
        "house",
        "book"
    ],
    "wof:name":"Sallaz-grenier S.a.",
    "wof:placetype":"venue"
},
  "geometry": {"coordinates":[4.74607,45.748997],"type":"Point"}
}