{
  "type": "Feature",
  "properties": {
    "iso:country":"FR",
    "sg:address":"Rue Charles Tellier 56300 Pontivy",
    "sg:city":"Pontivy",
    "sg:classifiers":[
        {
            "category":"Banks & Credit Unions",
            "subcategory":"Investment Brokerage",
            "type":"Services"
        }
    ],
    "sg:phone":"+33 2 97 25 06 04",
    "sg:postcode":"56300",
    "sg:province":"Bretagne",
    "sg:tags":[
        "-",
        "transport",
        "related"
    ],
    "wof:name":"Bretagne Frigo",
    "wof:placetype":"venue"
},
  "geometry": {"coordinates":[-2.964889,48.053471],"type":"Point"}
}