{
  "type": "Feature",
  "properties": {
    "addr:full":"Lieu Dit La Jugie 16310 St Adjutory Poitou-Charentes 16310",
    "addr:postcode":"16310;adjutory;16310",
    "addr:street":"Lieu Dit La Jugie",
    "iso:country":"FR",
    "sg:address":"Lieu Dit La Jugie 16310 St Adjutory",
    "sg:classifiers":[
        {
            "category":"Sports & Exercise",
            "subcategory":"Sports Center",
            "type":"Entertainment"
        }
    ],
    "sg:phone":"+33 5 45 65 04 43",
    "sg:postcode":"16310",
    "sg:province":"Poitou-Charentes",
    "sg:tags":[
        "product",
        "game",
        "miscellaneous"
    ],
    "wof:name":"Chambonnaud Verminiere",
    "wof:placetype":"venue"
},
  "geometry": {"coordinates":[0.517305,45.762539],"type":"Point"}
}