{
  "type": "Feature",
  "properties": {
    "addr:full":"10, Av. du 8 Mai 1945, 16140 Aigre Poitou-Charentes",
    "addr:postcode":"16140",
    "addr:street":"10 Av. Du 8 Mai 1945",
    "iso:country":"FR",
    "sg:address":"10, Av. du 8 Mai 1945, 16140 Aigre",
    "sg:orig_category":"Unclassifiable Establishments",
    "sg:phone":"+33 5 45 21 25 03",
    "sg:province":"Poitou-Charentes",
    "wof:name":"A.m.g. Violet S.a.r.l.",
    "wof:placetype":"venue"
},
  "geometry": {"coordinates":[0.008897,45.886318],"type":"Point"}
}