{
  "type": "Feature",
  "properties": {
    "iso:country":"FR",
    "sg:address":"16 Rue Paul Bert 93170 Bagnolet",
    "sg:classifiers":[
        {
            "category":"Manufacturing",
            "subcategory":"Chemicals & Compounds",
            "type":"Manufacturing & Wholesale Goods"
        }
    ],
    "sg:phone":"+33 1 42 87 11 55",
    "sg:postcode":"93170",
    "sg:province":"Ile de France",
    "sg:tags":[
        "pharmaceutical",
        "chemistry",
        "-",
        "by-product"
    ],
    "wof:name":"Lumer (ste) Sa",
    "wof:placetype":"venue"
},
  "geometry": {"coordinates":[2.418472,48.858894],"type":"Point"}
}