{
  "type": "Feature",
  "properties": {
    "addr:full":"5, All\u00e9e de Longchamp, 54600 Villers l\u00e8s Nancy Lorraine",
    "addr:housenumber":"5",
    "addr:postcode":"54600",
    "addr:street":"Alle\u0301E De Longchamp",
    "iso:country":"FR",
    "sg:address":"5, All\u00e9e de Longchamp, 54600 Villers l\u00e8s Nancy",
    "sg:orig_category":"Unclassifiable Establishments",
    "sg:phone":"+33 3 83 44 95 00",
    "sg:province":"Lorraine",
    "wof:name":"Nestl\u00e9 France S.a.",
    "wof:placetype":"venue"
},
  "geometry": {"coordinates":[6.137756,48.655258],"type":"Point"}
}