{
  "type": "Feature",
  "properties": {
    "iso:country":"FR",
    "sg:address":"23 Chemin Des Ecureuils 65690 Barbazan Debat",
    "sg:classifiers":[
        {
            "category":"Wholesale",
            "subcategory":"Machinery & Supplies",
            "type":"Manufacturing & Wholesale Goods"
        }
    ],
    "sg:phone":"+33 5 62 33 81 20",
    "sg:postcode":"65690",
    "sg:province":"Midi Pyr\u00e9n\u00e9es",
    "sg:tags":[
        "handling",
        "material",
        "-",
        "machine",
        "equipment",
        "engineering",
        "mechanical"
    ],
    "wof:name":"Pyrenees Ascenseurs",
    "wof:placetype":"venue"
},
  "geometry": {"coordinates":[0.118743,43.211117],"type":"Point"}
}