{
  "type": "Feature",
  "properties": {
    "addr:full":"Zi Du Vazzio De Sart\u00e8ne 20090 Ajaccio Corse 20090",
    "addr:postcode":"20090;20090",
    "addr:street":"Zi Du Vazzio De Sarte\u0300Ne",
    "iso:country":"FR",
    "sg:address":"Zi Du Vazzio",
    "sg:city":"De Sart\u00e8ne 20090 Ajaccio",
    "sg:classifiers":[
        {
            "category":"Professional",
            "subcategory":"Engineering",
            "type":"Services"
        }
    ],
    "sg:phone":"+33 4 95 22 18 43",
    "sg:postcode":"20090",
    "sg:province":"Corse",
    "sg:tags":[
        "machine",
        "-",
        "mechanical"
    ],
    "wof:name":"Climatisation (corse) Sarl",
    "wof:placetype":"venue"
},
  "geometry": {"coordinates":[8.781228,41.952419],"type":"Point"}
}