{
  "type": "Feature",
  "properties": {
    "iso:country":"FR",
    "sg:address":"12 Bd Industriel 76300 Sotteville Les Rouen",
    "sg:classifiers":[
        {
            "category":"Building & Trades",
            "subcategory":"Construction",
            "type":"Services"
        }
    ],
    "sg:phone":"+33 2 35 63 74 35",
    "sg:postcode":"76300",
    "sg:province":"Haute Normandie",
    "sg:tags":[
        "work",
        "public"
    ],
    "wof:name":"Sade Cie",
    "wof:placetype":"venue"
},
  "geometry": {"coordinates":[1.106763,49.420616],"type":"Point"}
}