{
  "type": "Feature",
  "properties": {
    "iso:country":"FR",
    "sg:address":"avenue Marcel Pagnol 43120 MONISTROL SUR LOIRE",
    "sg:city":"Monistrol-sur-Loire",
    "sg:classifiers":[
        {
            "category":"Building & Trades",
            "subcategory":"Construction",
            "type":"Services"
        }
    ],
    "sg:phone":"+33 4 71 75 11 70",
    "sg:postcode":"43120",
    "sg:province":"Auvergne",
    "sg:tags":[
        "turning",
        "vertical"
    ],
    "wof:name":"Massard Et Cie S.a.",
    "wof:placetype":"venue"
},
  "geometry": {"coordinates":[4.160135,45.290939],"type":"Point"}
}