{
  "type": "Feature",
  "properties": {
    "iso:country":"FR",
    "sg:address":"22, Rue Louis Armand, 77330 Ozoir la Ferri\u00e8re",
    "sg:orig_category":"Unclassifiable Establishments",
    "sg:phone":"+33 1 64 40 05 93",
    "sg:province":"Ile de France",
    "wof:name":"S.n.p.i. S.a.r.l. - Soci\u00e9t\u00e9 Nouvelle Pict Industrie",
    "wof:placetype":"venue"
},
  "geometry": {"coordinates":[2.689093,48.763428],"type":"Point"}
}