{
  "type": "Feature",
  "properties": {
    "addr:full":"13, All\u00e9e du Parc du ch\u00e2teau, 69800 Saint Priest Rhone-Alpes",
    "addr:housenumber":"13",
    "addr:postcode":"69800",
    "addr:street":"Alle\u0301E Du Parc Du Cha\u0302Teau;Priest Rhone-Alpes",
    "iso:country":"FR",
    "sg:address":"13, All\u00e9e du Parc du ch\u00e2teau, 69800 Saint Priest",
    "sg:orig_category":"Non-Classified Establishments",
    "sg:phone":"+33 4 78 21 06 56",
    "sg:province":"Rhone-Alpes",
    "wof:name":"Ifra Rh\u00f4ne - Institut De Formation De La R\u00e9gion Rh\u00f4ne Alpes",
    "wof:placetype":"venue"
},
  "geometry": {"coordinates":[4.942225,45.696106],"type":"Point"}
}