{
  "type": "Feature",
  "properties": {
    "addr:full":"22, Rue Martin Luther King, 34500 B\u00e9ziers Languedoc-Roussillon",
    "addr:housenumber":"22",
    "addr:postcode":"34500",
    "addr:street":"Rue Martin Luther King",
    "iso:country":"FR",
    "sg:address":"22, Rue Martin Luther King, 34500 B\u00e9ziers",
    "sg:orig_category":"Unclassifiable Establishments",
    "sg:phone":"+33 4 67 76 17 14",
    "sg:province":"Languedoc-Roussillon",
    "wof:name":"Panofrance",
    "wof:placetype":"venue"
},
  "geometry": {"coordinates":[3.257628,43.325272],"type":"Point"}
}