{
  "type": "Feature",
  "properties": {
    "addr:full":"10, Rte de la Durance - Parc Tertiaire de la Meinau, 67100 Strasbourg Strasbourg Alsace 67100",
    "addr:housenumber":"10",
    "addr:postcode":"meinau 67100;67100",
    "addr:street":"Rte De La Durance;Tertiaire De La",
    "iso:country":"FR",
    "sg:address":"10, Rte de la Durance - Parc Tertiaire de la Meinau, 67100 Strasbourg",
    "sg:city":"Strasbourg",
    "sg:orig_category":"Unclassifiable Establishments",
    "sg:phone":"+33 3 88 65 80 20",
    "sg:postcode":"67100",
    "sg:province":"Alsace",
    "wof:name":"Poly Labo Paul Block Et Compagnie S.a.",
    "wof:placetype":"venue"
},
  "geometry": {"coordinates":[7.734353,48.55238],"type":"Point"}
}