{
  "type": "Feature",
  "properties": {
    "addr:full":"B.P. 3, 53410 Port Brillet^^ZA la Croix des Aulnays, 53410 Port Brillet Pays de Loire",
    "addr:housenumber":"3",
    "addr:postcode":"53410;53410",
    "addr:street":"B.P.;La Croix Des Aulnays;Brillet",
    "iso:country":"FR",
    "sg:address":"B.P. 3, 53410 Port Brillet^^ZA la Croix des Aulnays, 53410 Port Brillet",
    "sg:orig_category":"Non-Classified Establishments",
    "sg:phone":"+33 2 43 68 80 85",
    "sg:province":"Pays de Loire",
    "wof:name":"Maille Cr\u00e9ation S.a.",
    "wof:placetype":"venue"
},
  "geometry": {"coordinates":[-1.013198,48.072639],"type":"Point"}
}