{
  "type": "Feature",
  "properties": {
    "iso:country":"FR",
    "sg:address":"13 place du G\u00e9n\u00e9ral de Gaulle 68150 RIBEAUVILLE",
    "sg:city":"Ribeauvill\u00e9",
    "sg:classifiers":[
        {
            "category":"Wholesale",
            "subcategory":"Wine & Distilled Alcoholic Beverages",
            "type":"Manufacturing & Wholesale Goods"
        }
    ],
    "sg:phone":"+33 3 89 73 22 50",
    "sg:postcode":"68150",
    "sg:province":"Alsace",
    "sg:tags":[
        "french"
    ],
    "wof:name":"Domaine Bott Freressa",
    "wof:placetype":"venue"
},
  "geometry": {"coordinates":[7.325647,48.192406],"type":"Point"}
}