{
  "type": "Feature",
  "properties": {
    "iso:country":"FR",
    "sg:address":"32 blvd de la R\u00e9publique; Pornichet; 44380",
    "sg:classifiers":[
        {
            "category":"Banks & Credit Unions",
            "subcategory":"Bank",
            "type":"Services"
        }
    ],
    "sg:phone":"+33 3340610078",
    "sg:postcode":"44380",
    "sg:province":"Pays de Loire",
    "wof:name":"Caisse Regionale, De Cr\u00e9dit Agricole",
    "wof:placetype":"venue"
},
  "geometry": {"coordinates":[-2.337246,47.259899],"type":"Point"}
}