{
  "type": "Feature",
  "properties": {
    "addr:full":"B.P. 470, 69659 Villefranche sur Sa\u00f4ne C\u00e9dex^^1, Av. de Beaujeu - ZI, 69400 Arnas Rhone-Alpes 69400",
    "addr:housenumber":"b.p. 470",
    "addr:postcode":"69659;69400;69400",
    "addr:street":"Av. De Beaujeu Zi",
    "iso:country":"FR",
    "sg:address":"B.P. 470, 69659 Villefranche sur Sa\u00f4ne C\u00e9dex^^1, Av. de Beaujeu - ZI, 69400 Arnas",
    "sg:orig_category":"Non-Classified Establishments",
    "sg:phone":"+33 4 74 68 45 49",
    "sg:postcode":"69400",
    "sg:province":"Rhone-Alpes",
    "wof:name":"Transports Giraud S.a.s.",
    "wof:placetype":"venue"
},
  "geometry": {"coordinates":[4.64756,45.957378],"type":"Point"}
}