{
  "type": "Feature",
  "properties": {
    "addr:full":"Place Raoul Larche; S. Andr\u00e9 de Cubzac; 33240 Aubie-et-Espessas Aquitaine 33240",
    "addr:postcode":"33240;33240",
    "addr:street":"Place Raoul Larche S. Andre\u0301 De Cubzac",
    "iso:country":"FR",
    "sg:address":"Place Raoul Larche; S. Andr\u00e9 de Cubzac; 33240",
    "sg:city":"Aubie-et-Espessas",
    "sg:classifiers":[
        {
            "category":"Banks & Credit Unions",
            "subcategory":"Bank",
            "type":"Services"
        }
    ],
    "sg:phone":"+33 5 57 94 03 50",
    "sg:postcode":"33240",
    "sg:province":"Aquitaine",
    "wof:name":"Cr\u00e9dit Commercial, Du Sud-ouest",
    "wof:placetype":"venue"
},
  "geometry": {"coordinates":[-0.446146,44.994579],"type":"Point"}
}