{
  "type": "Feature",
  "properties": {
    "addr:full":"Rue Buissoni\u00e8re BP 710 31683 Labege Cedex Centre",
    "addr:housenumber":"710",
    "addr:postcode":"31683;cedex",
    "addr:street":"Rue Buissonie\u0300Re Bp",
    "iso:country":"FR",
    "sg:address":"Rue Buissoni\u00e8re BP 710 31683 Labege Cedex",
    "sg:classifiers":[
        {
            "category":"Travel",
            "subcategory":"Hotels & Motels",
            "type":"Entertainment"
        }
    ],
    "sg:phone":"+33 5 61 39 44 00",
    "sg:province":"Centre",
    "sg:tags":[
        "hotels",
        "business",
        "restaurant"
    ],
    "wof:name":"Bowling Center H\u00d4tel",
    "wof:placetype":"venue"
},
  "geometry": {"coordinates":[1.514645,43.54137],"type":"Point"}
}