{
  "type": "Feature",
  "properties": {
    "addr:full":"5 Route De Carbon Blanc 33310 Lormont Lormont Aquitaine 33310",
    "addr:housenumber":"5",
    "addr:postcode":"33310;33310",
    "addr:street":"Route De Carbon Blanc",
    "iso:country":"FR",
    "sg:address":"5 Route De Carbon Blanc 33310 Lormont",
    "sg:city":"Lormont",
    "sg:classifiers":[
        {
            "category":"Food Court",
            "type":"Food & Drink"
        }
    ],
    "sg:phone":"+33 5 57 77 70 70",
    "sg:postcode":"33310",
    "sg:province":"Aquitaine",
    "sg:tags":[
        "product",
        "related"
    ],
    "wof:name":"Soc Nouvelle Des Ets Cazaux",
    "wof:placetype":"venue"
},
  "geometry": {"coordinates":[-0.518772,44.883289],"type":"Point"}
}