{
  "type": "Feature",
  "properties": {
    "addr:full":"Route De Taller 40260 CASTETS Taller Aquitaine 40260",
    "addr:postcode":"40260;40260",
    "addr:street":"Route De Taller",
    "iso:country":"FR",
    "sg:address":"Route De Taller 40260 CASTETS",
    "sg:city":"Taller",
    "sg:classifiers":[
        {
            "category":"Home & Garden",
            "subcategory":"Garden Supply",
            "type":"Retail Goods"
        }
    ],
    "sg:phone":"+33 5 58 56 68 68",
    "sg:postcode":"40260",
    "sg:province":"Aquitaine",
    "sg:tags":[
        "pond",
        "fish"
    ],
    "wof:name":"Viviers De France Sa",
    "wof:placetype":"venue"
},
  "geometry": {"coordinates":[-1.068398,43.872623],"type":"Point"}
}