{
  "type": "Feature",
  "properties": {
    "addr:full":"16, Rue Faidherbe, 59127 Walincourt Selvigny Nord Pas-de-Calais",
    "addr:housenumber":"16",
    "addr:postcode":"59127",
    "addr:street":"Rue Faidherbe;Selvigny Nord",
    "iso:country":"FR",
    "sg:address":"16, Rue Faidherbe, 59127 Walincourt Selvigny",
    "sg:orig_category":"Unclassifiable Establishments",
    "sg:phone":"+33 3 27 82 73 77",
    "sg:province":"Nord Pas-de-Calais",
    "wof:name":"Isabelle Vincent S.a.r.l.",
    "wof:placetype":"venue"
},
  "geometry": {"coordinates":[3.33485,50.069],"type":"Point"}
}