{
  "type": "Feature",
  "properties": {
    "addr:full":"11 Rue Ambroise Croizat 91120 Palaiseau Ile de France 91120",
    "addr:housenumber":"11",
    "addr:postcode":"91120;ile;91120",
    "addr:street":"Rue Ambroise Croizat;France",
    "iso:country":"FR",
    "sg:address":"11 Rue Ambroise Croizat 91120 Palaiseau",
    "sg:classifiers":[
        {
            "category":"Manufacturing",
            "subcategory":"Tools & Machinery",
            "type":"Manufacturing & Wholesale Goods"
        }
    ],
    "sg:phone":"+33 1 64 53 50 00",
    "sg:postcode":"91120",
    "sg:province":"Ile de France",
    "sg:tags":[
        "equipment",
        "measurement",
        "-",
        "precision",
        "instrument"
    ],
    "wof:name":"Agilent Technologies France (agilent Tech)",
    "wof:placetype":"venue"
},
  "geometry": {"coordinates":[2.254699,48.713058],"type":"Point"}
}