{
  "type": "Feature",
  "properties": {
    "iso:country":"FR",
    "sg:address":"12, Av de l'Europe, 02400 Ch\u00e2teau Thierry",
    "sg:orig_category":"Unclassifiable Establishments",
    "sg:phone":"+33 3 23 83 21 54",
    "sg:province":"Picardie",
    "wof:name":"Bollor\u00e9 Energie S.a.",
    "wof:placetype":"venue"
},
  "geometry": {"coordinates":[3.39228,49.054321],"type":"Point"}
}