{
  "type": "Feature",
  "properties": {
    "addr:full":"Rte de Bastia Porto Vecchio Corse 20537",
    "addr:postcode":"20537",
    "addr:street":"Rte De Bastia",
    "iso:country":"FR",
    "sg:address":"Rte de Bastia",
    "sg:city":"Porto Vecchio",
    "sg:orig_category":"Non-Classified Establishments",
    "sg:phone":"+33 4 95 70 18 22",
    "sg:postcode":"20537",
    "sg:province":"Corse",
    "wof:name":"Castelli S.a.",
    "wof:placetype":"venue"
},
  "geometry": {"coordinates":[9.277007,41.603928],"type":"Point"}
}