{
  "type": "Feature",
  "properties": {
    "addr:full":"Av Du Vert Galant 64230 Lescar Lescar Aquitaine 64230",
    "addr:postcode":"64230;64230",
    "addr:street":"Av Du Vert Galant",
    "iso:country":"FR",
    "sg:address":"Av Du Vert Galant 64230 Lescar",
    "sg:city":"Lescar",
    "sg:classifiers":[
        {
            "category":"Manufacturing",
            "subcategory":"Glass & Minerals",
            "type":"Manufacturing & Wholesale Goods"
        }
    ],
    "sg:phone":"+33 5 59 81 20 31",
    "sg:postcode":"64230",
    "sg:province":"Aquitaine",
    "sg:tags":[
        "building",
        "material"
    ],
    "wof:name":"Beton Controle Du Bearn",
    "wof:placetype":"venue"
},
  "geometry": {"coordinates":[-0.440804,43.326012],"type":"Point"}
}