{
  "type": "Feature",
  "properties": {
    "iso:country":"FR",
    "sg:address":"2 Chemin Des Trois Villes 77230 Thieux",
    "sg:classifiers":[
        {
            "category":"Manufacturing",
            "subcategory":"Rubber & Plastics",
            "type":"Manufacturing & Wholesale Goods"
        }
    ],
    "sg:phone":"+33 1 60 26 80 00",
    "sg:province":"Ile de France",
    "wof:name":"Cetem (cetem)",
    "wof:placetype":"venue"
},
  "geometry": {"coordinates":[2.666855,49.007809],"type":"Point"}
}