{
  "type": "Feature",
  "properties": {
    "iso:country":"FR",
    "sg:address":"2, Av. de Vignate - Centre Equation, 38610 Gi\u00e8res",
    "sg:orig_category":"Non-Classified Establishments",
    "sg:phone":"+33 4 76 63 49 49",
    "sg:postcode":"38610",
    "sg:province":"Rhone-Alpes",
    "wof:name":"Aricie S.a.",
    "wof:placetype":"venue"
},
  "geometry": {"coordinates":[5.790945,45.180096],"type":"Point"}
}