{
  "type": "Feature",
  "properties": {
    "addr:full":"Rue Nicolas Copernic - ZI du Coudray - Garonor B\u00e2t. 24E Aulnay sous Bois Ile de France 93600",
    "addr:housenumber":"ba\u0302t 24e",
    "addr:postcode":"93600",
    "addr:street":"Rue Nicolas Copernic Zi Du Coudray",
    "iso:country":"FR",
    "sg:address":"Rue Nicolas Copernic - ZI du Coudray - Garonor B\u00e2t. 24E",
    "sg:city":"Aulnay sous Bois",
    "sg:orig_category":"Unclassifiable Establishments",
    "sg:phone":"+33 1 48 65 27 11",
    "sg:postcode":"93600",
    "sg:province":"Ile de France",
    "wof:name":"C.e.a. S.a.r.l. - Container Equipement Et Arrimage",
    "wof:placetype":"venue"
},
  "geometry": {"coordinates":[2.49124,48.927509],"type":"Point"}
}