{
  "type": "Feature",
  "properties": {
    "iso:country":"FR",
    "sg:address":"72-76 Av Raymon Poincarr\u00e9 BP 290 21078 Dijon",
    "sg:classifiers":[
        {
            "category":"Banks & Credit Unions",
            "subcategory":"Financial Services",
            "type":"Services"
        }
    ],
    "sg:phone":"+33 3 80 73 73 00",
    "sg:province":"Languedoc-Roussillon",
    "sg:tags":[
        "banking",
        "insurance",
        "institution",
        "finance"
    ],
    "wof:name":"Ineo Cap",
    "wof:placetype":"venue"
},
  "geometry": {"coordinates":[5.065564,47.328678],"type":"Point"}
}