{
  "type": "Feature",
  "properties": {
    "iso:country":"FR",
    "sg:address":"130, Rue Eug\u00e8ne Pottier - Immeuble le Calypso, 35000 Rennes",
    "sg:city":"Rennes",
    "sg:orig_category":"Unclassifiable Establishments",
    "sg:phone":"+33 2 99 31 09 09",
    "sg:postcode":"35000",
    "sg:province":"Bretagne",
    "wof:name":"Plastic Omnium S.a.",
    "wof:placetype":"venue"
},
  "geometry": {"coordinates":[-1.712838,48.102367],"type":"Point"}
}