{
  "type": "Feature",
  "properties": {
    "addr:full":"62, Rue des Papeteries, 68027 Colmar C\u00e9dex Alsace",
    "addr:housenumber":"62",
    "addr:postcode":"68027",
    "addr:street":"Rue Des Papeteries;Ce\u0301Dex",
    "iso:country":"FR",
    "sg:address":"62, Rue des Papeteries, 68027 Colmar C\u00e9dex",
    "sg:orig_category":"Non-Classified Establishments",
    "sg:phone":"+33 3 89 20 30 00",
    "sg:province":"Alsace",
    "wof:name":"S.c.r.e.g. Est S.a.",
    "wof:placetype":"venue"
},
  "geometry": {"coordinates":[7.353193,48.092571],"type":"Point"}
}