{
  "type": "Feature",
  "properties": {
    "addr:full":"22-24 Rue Du Pont Aux Halles 86220 Les Ormes Poitou-Charentes 86220",
    "addr:housenumber":"22-24",
    "addr:postcode":"86220;86220",
    "addr:street":"Rue Du Pont Aux Halles",
    "iso:country":"FR",
    "sg:address":"22-24 Rue Du Pont Aux Halles 86220 Les Ormes",
    "sg:classifiers":[
        {
            "category":"Shopping",
            "subcategory":"Clothing, Apparel, & Fashions",
            "type":"Retail Goods"
        }
    ],
    "sg:phone":"+33 5 49 85 67 05",
    "sg:postcode":"86220",
    "sg:province":"Poitou-Charentes",
    "sg:tags":[
        "textile",
        "clothing",
        "clothes"
    ],
    "wof:name":"Creations Hubert Nat Sarl",
    "wof:placetype":"venue"
},
  "geometry": {"coordinates":[0.603126,46.971771],"type":"Point"}
}