{
  "type": "Feature",
  "properties": {
    "addr:full":"9, Rue Notre Dame des Victoires, 59181 Steenwerck Nord Pas-de-Calais",
    "addr:housenumber":"9",
    "addr:postcode":"59181",
    "addr:street":"Rue Notre Dame Des Victoires",
    "iso:country":"FR",
    "sg:address":"9, Rue Notre Dame des Victoires, 59181 Steenwerck",
    "sg:orig_category":"Unclassifiable Establishments",
    "sg:phone":"+33 3 28 49 96 58",
    "sg:province":"Nord Pas-de-Calais",
    "wof:name":"Turb\u00e9 S.a.r.l.",
    "wof:placetype":"venue"
},
  "geometry": {"coordinates":[2.780892,50.705044],"type":"Point"}
}