{
  "type": "Feature",
  "properties": {
    "iso:country":"FR",
    "sg:address":"Rue la D\u00e9sir\u00e9e - La Ville en Bois",
    "sg:city":"La Rochelle",
    "sg:orig_category":"Unclassifiable Establishments",
    "sg:phone":"+33 5 46 41 49 47",
    "sg:postcode":"17000",
    "sg:province":"Poitou-Charentes",
    "wof:name":"Caf\u00e9s Merling C.h.r S.a.",
    "wof:placetype":"venue"
},
  "geometry": {"coordinates":[-1.151639,46.159435],"type":"Point"}
}