{
  "type": "Feature",
  "properties": {
    "iso:country":"FR",
    "sg:address":"Les Filatures 69240 Saint Vincent de Reins",
    "sg:orig_category":"Unclassifiable Establishments",
    "sg:phone":"+33 4 74 89 69 00",
    "sg:province":"Rhone-Alpes",
    "wof:name":"Actua'tex S.a.",
    "wof:placetype":"venue"
},
  "geometry": {"coordinates":[4.3876,46.095501],"type":"Point"}
}