{
  "type": "Feature",
  "properties": {
    "addr:full":"2, Av. du Pr\u00e9sident Pierre Angot, 64009 Pau C\u00e9dex Aquitaine",
    "addr:postcode":"64009",
    "addr:street":"Av. Du Pre\u0301Sident Pierre Angot",
    "iso:country":"FR",
    "sg:address":"2, Av. du Pr\u00e9sident Pierre Angot, 64009 Pau C\u00e9dex",
    "sg:orig_category":"Non-Classified Establishments",
    "sg:phone":"+33 5 59 84 14 18",
    "sg:province":"Aquitaine",
    "wof:name":"Heliantis S.a.r.l.",
    "wof:placetype":"venue"
},
  "geometry": {"coordinates":[-0.366987,43.32032],"type":"Point"}
}