{
  "type": "Feature",
  "properties": {
    "iso:country":"FR",
    "sg:address":"B.P. 129, 59443 Wasquehal C\u00e9dex^^18, Rue de Croix, 59290 Wasquehal",
    "sg:orig_category":"Non-Classified Establishments",
    "sg:phone":"+33 3 20 66 59 00",
    "sg:province":"Nord Pas-de-Calais",
    "wof:name":"Inbrand France S.a.",
    "wof:placetype":"venue"
},
  "geometry": {"coordinates":[3.132085,50.669395],"type":"Point"}
}