{
  "type": "Feature",
  "properties": {
    "addr:full":"10 rue des Fr\u00e8res Lumi\u00e8re 57200 Sarreguemines Lorraine 57200",
    "addr:housenumber":"10",
    "addr:postcode":"57200;57200",
    "addr:street":"Rue Des Fre\u0300Res Lumie\u0300Re",
    "iso:country":"FR",
    "sg:address":"10 rue des Fr\u00e8res Lumi\u00e8re 57200 Sarreguemines",
    "sg:classifiers":[
        {
            "category":"Building & Trades",
            "subcategory":"Construction",
            "type":"Services"
        }
    ],
    "sg:phone":"+33 3 87 98 40 21",
    "sg:postcode":"57200",
    "sg:province":"Lorraine",
    "sg:tags":[
        "industry",
        "air-conditioning",
        "system"
    ],
    "wof:name":"Ets Houll\u00e9 Sa",
    "wof:placetype":"venue"
},
  "geometry": {"coordinates":[7.096641,49.111839],"type":"Point"}
}