{
  "type": "Feature",
  "properties": {
    "addr:full":"190, Av du Pr\u00e9sident Kennedy, 62400 B\u00e9thune Nord Pas-de-Calais 62400",
    "addr:housenumber":"190",
    "addr:postcode":"62400;62400",
    "addr:street":"Av Du Pre\u0301Sident Kennedy",
    "iso:country":"FR",
    "sg:address":"190, Av du Pr\u00e9sident Kennedy, 62400 B\u00e9thune",
    "sg:orig_category":"Non-Classified Establishments",
    "sg:phone":"+33 3 21 57 20 52",
    "sg:postcode":"62400",
    "sg:province":"Nord Pas-de-Calais",
    "wof:name":"Descamps S.a.",
    "wof:placetype":"venue"
},
  "geometry": {"coordinates":[2.647213,50.535294],"type":"Point"}
}