{
  "type": "Feature",
  "properties": {
    "iso:country":"FR",
    "sg:address":"Zi La Prade 33650 Saint M\u00e9dard D'Eyrans",
    "sg:city":"Cabanac-et-Villagrains",
    "sg:classifiers":[
        {
            "category":"Professional",
            "subcategory":"Engineering",
            "type":"Services"
        }
    ],
    "sg:phone":"+33 5 56 20 22 12",
    "sg:postcode":"33650",
    "sg:province":"Aquitaine",
    "sg:tags":[
        "electric",
        "-",
        "component",
        "machine",
        "mechanical",
        "electronic"
    ],
    "wof:name":"Electronique Bobinage D'aquitaine (eba)",
    "wof:placetype":"venue"
},
  "geometry": {"coordinates":[-0.694469,44.739594],"type":"Point"}
}