{
  "type": "Feature",
  "properties": {
    "addr:full":"57 A Chemin Des Sauzes 63170 Aubiere Aubi\u00e8re Auvergne 63170",
    "addr:housenumber":"57 a",
    "addr:postcode":"63170;63170",
    "addr:street":"Chemin Des Sauzes",
    "iso:country":"FR",
    "sg:address":"57 A Chemin Des Sauzes 63170 Aubiere",
    "sg:city":"Aubi\u00e8re",
    "sg:classifiers":[
        {
            "category":"Utilities",
            "subcategory":"Electric",
            "type":"Services"
        }
    ],
    "sg:phone":"+33 4 73 28 28 92",
    "sg:postcode":"63170",
    "sg:province":"Auvergne",
    "sg:tags":[
        "electricity",
        "electronic",
        "electrical",
        "equipment"
    ],
    "wof:name":"Mci",
    "wof:placetype":"venue"
},
  "geometry": {"coordinates":[3.138241,45.757927],"type":"Point"}
}