{
  "type": "Feature",
  "properties": {
    "addr:full":"42, Rue Bancel, 77000 Melun Ile de France",
    "addr:housenumber":"42",
    "addr:postcode":"77000;ile",
    "addr:street":"Rue Bancel",
    "iso:country":"FR",
    "sg:address":"42, Rue Bancel, 77000 Melun",
    "sg:orig_category":"Unclassifiable Establishments",
    "sg:phone":"+33 1 64 22 97 97",
    "sg:province":"Ile de France",
    "wof:name":"Id - Com S.a.r.l.",
    "wof:placetype":"venue"
},
  "geometry": {"coordinates":[2.660484,48.54155],"type":"Point"}
}