{
  "type": "Feature",
  "properties": {
    "iso:country":"FR",
    "sg:address":"Rue de la Gare",
    "sg:city":"Brimeux",
    "sg:orig_category":"Unclassifiable Establishments",
    "sg:phone":"+33 3 21 06 00 33",
    "sg:postcode":"62170",
    "sg:province":"Nord Pas-de-Calais",
    "wof:name":"Duhel S.a.",
    "wof:placetype":"venue"
},
  "geometry": {"coordinates":[1.830635,50.448544],"type":"Point"}
}