{
  "type": "Feature",
  "properties": {
    "iso:country":"FR",
    "sg:address":"175 rue G\u00e9n de Gaulle; Milizac",
    "sg:classifiers":[
        {
            "category":"Banks & Credit Unions",
            "subcategory":"Bank",
            "type":"Services"
        }
    ],
    "sg:phone":"+33 3398079698",
    "sg:province":"Midi Pyr\u00e9n\u00e9es",
    "wof:name":"Cr\u00e9dit Agricole Mutuel",
    "wof:placetype":"venue"
},
  "geometry": {"coordinates":[-4.567424,48.466061],"type":"Point"}
}