{
  "type": "Feature",
  "properties": {
    "addr:full":"95862 Cergy Pontoise C\u00e9dex^^P\u00f4le Vinci - Parc Saint Christophe Cergy Ile de France 95000",
    "addr:postcode":"95862;95000",
    "addr:street":"Parc",
    "iso:country":"FR",
    "sg:address":"95862 Cergy Pontoise C\u00e9dex^^P\u00f4le Vinci - Parc Saint Christophe",
    "sg:city":"Cergy",
    "sg:orig_category":"Non-Classified Establishments",
    "sg:phone":"+33 1 34 24 34 00",
    "sg:postcode":"95000",
    "sg:province":"Ile de France",
    "wof:name":"Spie Batignolles T.p. S.a.",
    "wof:placetype":"venue"
},
  "geometry": {"coordinates":[2.07982,49.035198],"type":"Point"}
}