{
  "type": "Feature",
  "properties": {
    "addr:full":"116, Av. du Pr\u00e9sident Kennedy, 75016 Paris Ile de France",
    "addr:postcode":"75016",
    "addr:street":"116 Av. Du Pre\u0301Sident Kennedy",
    "iso:country":"FR",
    "sg:address":"116, Av. du Pr\u00e9sident Kennedy, 75016 Paris",
    "sg:orig_category":"Unclassifiable Establishments",
    "sg:phone":"+33 1 45 25 22 20",
    "sg:province":"Ile de France",
    "wof:name":"Air France",
    "wof:placetype":"venue"
},
  "geometry": {"coordinates":[2.279466,48.852074],"type":"Point"}
}