{
  "type": "Feature",
  "properties": {
    "iso:country":"FR",
    "sg:address":"46, Av. Lanessan, 69410 Champagne au Mont d'Or",
    "sg:orig_category":"Non-Classified Establishments",
    "sg:phone":"+33 4 78 66 05 05",
    "sg:postcode":"69410",
    "sg:province":"Rhone-Alpes",
    "wof:name":"Apor S.n.c.",
    "wof:placetype":"venue"
},
  "geometry": {"coordinates":[-0.100754,47.869232],"type":"Point"}
}