{
  "type": "Feature",
  "properties": {
    "iso:country":"FR",
    "sg:address":"240 Route De Beauregard 69400 Villefranche Sur Sa\u00f4ne",
    "sg:classifiers":[
        {
            "category":"Farming",
            "subcategory":"Farm",
            "type":"Manufacturing & Wholesale Goods"
        }
    ],
    "sg:phone":"+33 4 74 62 85 89",
    "sg:postcode":"69400",
    "sg:province":"Rhone-Alpes",
    "sg:tags":[
        "horticulture",
        "agriculture",
        "livestock"
    ],
    "wof:name":"Cedest Engrais",
    "wof:placetype":"venue"
},
  "geometry": {"coordinates":[4.74168,45.999279],"type":"Point"}
}