{
  "type": "Feature",
  "properties": {
    "addr:full":"20 Rue Du Moulin 39700 Audelange Franche Comt\u00e9 39700",
    "addr:housenumber":"20",
    "addr:postcode":"39700;39700",
    "addr:street":"Rue Du Moulin;Franche Comte\u0301",
    "iso:country":"FR",
    "sg:address":"20 Rue Du Moulin 39700 Audelange",
    "sg:classifiers":[
        {
            "category":"Farming",
            "subcategory":"Farm & Veterinary Services",
            "type":"Manufacturing & Wholesale Goods"
        }
    ],
    "sg:phone":"+33 3 84 70 60 12",
    "sg:postcode":"39700",
    "sg:province":"Franche Comt\u00e9",
    "sg:tags":[
        "food",
        "product",
        "breeding",
        "animal",
        "related"
    ],
    "wof:name":"Le Moulin Rouge",
    "wof:placetype":"venue"
},
  "geometry": {"coordinates":[5.740925,47.154335],"type":"Point"}
}