{
  "type": "Feature",
  "properties": {
    "addr:full":"43, Rue Beaubourg, 75003 Paris Ile de France",
    "addr:housenumber":"43",
    "addr:postcode":"75003",
    "addr:street":"Rue Beaubourg",
    "iso:country":"FR",
    "sg:address":"43, Rue Beaubourg, 75003 Paris",
    "sg:orig_category":"Non-Classified Establishments",
    "sg:phone":"+33 1 40 29 11 96",
    "sg:province":"Ile de France",
    "wof:name":"Thesee Com",
    "wof:placetype":"venue"
},
  "geometry": {"coordinates":[2.354058,48.86261],"type":"Point"}
}