{
  "type": "Feature",
  "properties": {
    "addr:full":"4, Rue Joseph Cugnot, 51500 Taissy Champagne 51500",
    "addr:housenumber":"4",
    "addr:postcode":"51500;51500",
    "addr:street":"Rue Joseph Cugnot;Champagne",
    "iso:country":"FR",
    "sg:address":"4, Rue Joseph Cugnot, 51500 Taissy",
    "sg:orig_category":"Non-Classified Establishments",
    "sg:phone":"+33 3 26 77 50 10",
    "sg:postcode":"51500",
    "sg:province":"Champagne",
    "wof:name":"Alain Thienot Champagne S.a.",
    "wof:placetype":"venue"
},
  "geometry": {"coordinates":[4.076829,49.21471],"type":"Point"}
}