{
  "type": "Feature",
  "properties": {
    "iso:country":"FR",
    "sg:address":"5 Rue Pierre Cot 71100 Chalon Sur Sa\u00f4ne",
    "sg:city":"Chalon-sur-Sa\u00f4ne",
    "sg:classifiers":[
        {
            "category":"Utilities",
            "subcategory":"Electric",
            "type":"Services"
        }
    ],
    "sg:phone":"+33 3 85 46 23 89",
    "sg:postcode":"71100",
    "sg:province":"Bourgogne",
    "sg:tags":[
        "electricity",
        "electronic",
        "electrical",
        "equipment"
    ],
    "wof:name":"Le Materiel Electrique Et Industriel (lmei)",
    "wof:placetype":"venue"
},
  "geometry": {"coordinates":[4.859567,46.812744],"type":"Point"}
}