{
  "type": "Feature",
  "properties": {
    "iso:country":"FR",
    "sg:address":"11, Chemin du Vieux Ch\u00eane, 38240 Meylan",
    "sg:orig_category":"Unclassifiable Establishments",
    "sg:phone":"+33 4 76 61 34 00",
    "sg:postcode":"38240",
    "sg:province":"Rhone-Alpes",
    "wof:name":"X.l. Consultants S.a.",
    "wof:placetype":"venue"
},
  "geometry": {"coordinates":[5.785038,45.206837],"type":"Point"}
}