{
  "type": "Feature",
  "properties": {
    "iso:country":"FR",
    "sg:address":"3, Rue de Thessalie - Erdre Active B\u00e9rangerais, 44240 La Chapelle sur Erdre",
    "sg:orig_category":"Unclassifiable Establishments",
    "sg:phone":"+33 2 40 72 86 02",
    "sg:province":"Pays de Loire",
    "wof:name":"Technicis S.a.r.l.",
    "wof:placetype":"venue"
},
  "geometry": {"coordinates":[-1.536342,47.28133],"type":"Point"}
}