{
  "type": "Feature",
  "properties": {
    "addr:full":"Rte du Pic Saint Loup Saint Martin de Londres Languedoc-Roussillon 34380",
    "addr:postcode":"34380",
    "addr:street":"Rte Du Pic Saint Loup;Martin;Londres",
    "iso:country":"FR",
    "sg:address":"Rte du Pic Saint Loup",
    "sg:city":"Saint Martin de Londres",
    "sg:orig_category":"Non-Classified Establishments",
    "sg:phone":"+33 4 67 55 01 33",
    "sg:postcode":"34380",
    "sg:province":"Languedoc-Roussillon",
    "wof:name":"Celectron S.a.r.l.",
    "wof:placetype":"venue"
},
  "geometry": {"coordinates":[3.738175,43.789356],"type":"Point"}
}