{
  "type": "Feature",
  "properties": {
    "addr:full":"Place du Commandant Boidot Clamecy Bourgogne 58500",
    "addr:postcode":"58500",
    "addr:street":"Place Du Commandant Boidot",
    "iso:country":"FR",
    "sg:address":"Place du Commandant Boidot",
    "sg:city":"Clamecy",
    "sg:orig_category":"Unclassifiable Establishments",
    "sg:phone":"+33 3 86 27 31 61",
    "sg:postcode":"58500",
    "sg:province":"Bourgogne",
    "wof:name":"E.d.f. - G.d.f. Services",
    "wof:placetype":"venue"
},
  "geometry": {"coordinates":[3.521693,47.458427],"type":"Point"}
}