{
  "type": "Feature",
  "properties": {
    "iso:country":"FR",
    "sg:address":"7, Rte de Marillais, 49410 Saint Florent le Vieil",
    "sg:orig_category":"Non-Classified Establishments",
    "sg:phone":"+33 2 41 72 16 60",
    "sg:postcode":"49410",
    "sg:province":"Pays de Loire",
    "wof:name":"Chen\u00e9 Pouplard S.a.",
    "wof:placetype":"venue"
},
  "geometry": {"coordinates":[-0.927774,47.320755],"type":"Point"}
}