{
  "type": "Feature",
  "properties": {
    "addr:full":"25, Rue de la F\u00eate Dieu, 89470 Mon\u00e9teau Mon\u00e9teau Bourgogne 89470",
    "addr:housenumber":"25",
    "addr:postcode":"89470;89470",
    "addr:street":"Rue De La Fe\u0302Te Dieu",
    "iso:country":"FR",
    "sg:address":"25, Rue de la F\u00eate Dieu, 89470 Mon\u00e9teau",
    "sg:city":"Mon\u00e9teau",
    "sg:orig_category":"Unclassifiable Establishments",
    "sg:phone":"+33 3 86 40 74 75",
    "sg:postcode":"89470",
    "sg:province":"Bourgogne",
    "wof:name":"S.m.b.i. S.a.r.l.",
    "wof:placetype":"venue"
},
  "geometry": {"coordinates":[3.5721,47.849731],"type":"Point"}
}