{
  "type": "Feature",
  "properties": {
    "addr:full":"Lestre 50310 Montebourg Montebourg Basse Normandie 50310",
    "addr:postcode":"50310;50310",
    "addr:street":"Lestre",
    "iso:country":"FR",
    "sg:address":"Lestre 50310 Montebourg",
    "sg:city":"Montebourg",
    "sg:orig_category":"Unclassifiable Establishments",
    "sg:phone":"+33 2 33 21 42 62",
    "sg:postcode":"50310",
    "sg:province":"Basse Normandie",
    "wof:name":"Cl\u00f4tures Du Cotentin S.a.r.l.",
    "wof:placetype":"venue"
},
  "geometry": {"coordinates":[-1.33203,49.526218],"type":"Point"}
}