{
  "type": "Feature",
  "properties": {
    "addr:full":"Av. Vabre Rodez Midi-Pyr\u00e9n\u00e9es 12033",
    "addr:postcode":"12033",
    "addr:street":"Av. Vabre",
    "iso:country":"FR",
    "sg:address":"Av. Vabre",
    "sg:city":"Rodez",
    "sg:orig_category":"Unclassifiable Establishments",
    "sg:phone":"+33 5 65 75 44 44",
    "sg:postcode":"12033",
    "sg:province":"Midi-Pyr\u00e9n\u00e9es",
    "wof:name":"Point P S.a.",
    "wof:placetype":"venue"
},
  "geometry": {"coordinates":[2.570845,44.368382],"type":"Point"}
}