{
  "type": "Feature",
  "properties": {
    "addr:full":"98, Rue du Barrault, 75013 Paris Ile de France",
    "addr:housenumber":"98",
    "addr:postcode":"75013",
    "addr:street":"Rue Du Barrault",
    "iso:country":"FR",
    "sg:address":"98, Rue du Barrault, 75013 Paris",
    "sg:orig_category":"Non-Classified Establishments",
    "sg:phone":"+33 1 45 88 53 80",
    "sg:province":"Ile de France",
    "wof:name":"R\u00e9vision Gestion Audit S.a.r.l.",
    "wof:placetype":"venue"
},
  "geometry": {"coordinates":[2.346542,48.822971],"type":"Point"}
}