{
  "type": "Feature",
  "properties": {
    "addr:full":"9 Route Colonel Marcel Moraine 92365 Meudon La For\u00eat Nord Pas-de-Calais",
    "addr:housenumber":"9",
    "addr:postcode":"92365",
    "addr:street":"Route Colonel Marcel Moraine",
    "iso:country":"FR",
    "sg:address":"9 Route Colonel Marcel Moraine 92365 Meudon La For\u00eat",
    "sg:classifiers":[
        {
            "category":"Professional",
            "subcategory":"Computer Services",
            "type":"Services"
        }
    ],
    "sg:phone":"+33 1 46 32 32 49",
    "sg:province":"Nord Pas-de-Calais",
    "sg:tags":[
        "information",
        "technology",
        "software"
    ],
    "wof:name":"Eris Informatique Sarl",
    "wof:placetype":"venue"
},
  "geometry": {"coordinates":[1.649876,45.972038],"type":"Point"}
}