{
  "type": "Feature",
  "properties": {
    "addr:full":"25, Rte Magny, 27200 Vernon Haute Normandie",
    "addr:housenumber":"25",
    "addr:postcode":"27200",
    "addr:street":"Rte Magny;Haute Normandie",
    "iso:country":"FR",
    "sg:address":"25, Rte Magny, 27200 Vernon",
    "sg:orig_category":"Unclassifiable Establishments",
    "sg:phone":"+33 2 32 51 15 46",
    "sg:province":"Haute Normandie",
    "wof:name":"Bouquet S.a.",
    "wof:placetype":"venue"
},
  "geometry": {"coordinates":[1.501443,49.099049],"type":"Point"}
}