{
  "type": "Feature",
  "properties": {
    "addr:full":"1, Rue Grand Communal, 25130 Villers le Lac Franche Comt\u00e9",
    "addr:housenumber":"1",
    "addr:postcode":"25130",
    "addr:street":"Rue Grand Communal;Villers Le;Franche Comte\u0301",
    "iso:country":"FR",
    "sg:address":"1, Rue Grand Communal, 25130 Villers le Lac",
    "sg:orig_category":"Unclassifiable Establishments",
    "sg:phone":"+33 3 81 68 90 50",
    "sg:province":"Franche Comt\u00e9",
    "wof:name":"F.f.b. S.a.r.l. - Fabrique De Fournitures De Bonn\u00e9tage",
    "wof:placetype":"venue"
},
  "geometry": {"coordinates":[6.670145,47.058926],"type":"Point"}
}