{
  "type": "Feature",
  "properties": {
    "addr:full":"Gare Terre Plein De La Gare 20250 Corte Corse 20250",
    "addr:postcode":"20250;20250",
    "addr:street":"Corte Corse",
    "iso:country":"FR",
    "sg:address":"Gare Terre Plein De La Gare 20250 Corte",
    "sg:classifiers":[
        {
            "category":"Home & Garden",
            "subcategory":"Furniture",
            "type":"Retail Goods"
        }
    ],
    "sg:phone":"+33 4 95 46 28 74",
    "sg:postcode":"20250",
    "sg:province":"Corse",
    "sg:tags":[
        "household",
        "wood"
    ],
    "wof:name":"Terraghja",
    "wof:placetype":"venue"
},
  "geometry": {"coordinates":[9.150334,42.307598],"type":"Point"}
}