{
  "type": "Feature",
  "properties": {
    "addr:full":"62 Rue Marc Seguin BP 8 Zone De La Hazaie 22950 Tregueux Tr\u00e9gueux Bretagne 22950",
    "addr:housenumber":"62;8",
    "addr:postcode":"22950;22950",
    "addr:street":"Rue Marc Seguin Bp;Zone De La Hazaie",
    "iso:country":"FR",
    "sg:address":"62 Rue Marc Seguin BP 8 Zone De La Hazaie 22950 Tregueux",
    "sg:city":"Tr\u00e9gueux",
    "sg:classifiers":[
        {
            "category":"Wholesale",
            "subcategory":"Machinery & Supplies",
            "type":"Manufacturing & Wholesale Goods"
        }
    ],
    "sg:phone":"+33 2 96 33 67 51",
    "sg:postcode":"22950",
    "sg:province":"Bretagne",
    "sg:tags":[
        "handling",
        "material",
        "-",
        "machine",
        "equipment",
        "engineering",
        "mechanical"
    ],
    "wof:name":"Thyssen Ascenseurs",
    "wof:placetype":"venue"
},
  "geometry": {"coordinates":[-2.736668,48.489059],"type":"Point"}
}