{
  "type": "Feature",
  "properties": {
    "addr:full":"tour Iris CEDEX 92095 PARIS LA DEFENSE Midi Pyr\u00e9n\u00e9es",
    "addr:postcode":"92095",
    "addr:street":"Cedex",
    "iso:country":"FR",
    "sg:address":"tour",
    "sg:city":"Iris CEDEX 92095 PARIS LA DEFENSE",
    "sg:classifiers":[
        {
            "category":"Professional",
            "subcategory":"Computer Services",
            "type":"Services"
        }
    ],
    "sg:phone":"+33 1 41 45 70 00",
    "sg:province":"Midi Pyr\u00e9n\u00e9es",
    "sg:tags":[
        "information",
        "technology",
        "software"
    ],
    "wof:name":"Bea Systems (sa)",
    "wof:placetype":"venue"
},
  "geometry": {"coordinates":[2.24119,48.888939],"type":"Point"}
}