{
  "type": "Feature",
  "properties": {
    "iso:country":"FR",
    "sg:address":"ZAC des Escampades",
    "sg:city":"Monteux",
    "sg:orig_category":"Non-Classified Establishments",
    "sg:phone":"+33 4 90 61 12 12",
    "sg:postcode":"84170",
    "sg:province":"Provence-Alpes-C\u00f4te d'Azur",
    "wof:name":"S.m.v. S.a.r.l.",
    "wof:placetype":"venue"
},
  "geometry": {"coordinates":[4.99467,44.034355],"type":"Point"}
}