{
  "type": "Feature",
  "properties": {
    "iso:country":"FR",
    "sg:address":"69, Av. de Cornebarrieu - Technoclub A, 31700 Blagnac",
    "sg:orig_category":"Non-Classified Establishments",
    "sg:phone":"+33 5 61 71 41 32",
    "sg:province":"Midi Pyr\u00e9n\u00e9es",
    "wof:name":"Sier S.a. - Soci\u00e9t\u00e9 Industrielle D'etudes Et De R\u00e9alisations",
    "wof:placetype":"venue"
},
  "geometry": {"coordinates":[1.379102,43.638657],"type":"Point"}
}