{
  "type": "Feature",
  "properties": {
    "addr:full":"66 Rue De La Gare 88430 Corcieux Lorraine 88430",
    "addr:housenumber":"66",
    "addr:postcode":"88430;88430",
    "addr:street":"Rue De La Gare",
    "iso:country":"FR",
    "sg:address":"66 Rue De La Gare 88430 Corcieux",
    "sg:classifiers":[
        {
            "category":"Food & Beverages",
            "subcategory":"Dairy",
            "type":"Retail Goods"
        }
    ],
    "sg:phone":"+33 3 29 52 34 29",
    "sg:postcode":"88430",
    "sg:province":"Lorraine",
    "sg:tags":[
        "product",
        "related"
    ],
    "wof:name":"Asmar Sa Snc",
    "wof:placetype":"venue"
},
  "geometry": {"coordinates":[6.883845,48.178493],"type":"Point"}
}