{
  "type": "Feature",
  "properties": {
    "iso:country":"FR",
    "sg:address":"ZI les Gassas",
    "sg:city":"Saint Agnan",
    "sg:orig_category":"Non-Classified Establishments",
    "sg:phone":"+33 3 85 53 82 48",
    "sg:postcode":"71160",
    "sg:province":"Bourgogne",
    "wof:name":"Sicop S.a.",
    "wof:placetype":"venue"
},
  "geometry": {"coordinates":[3.879165,46.502655],"type":"Point"}
}