{
  "type": "Feature",
  "properties": {
    "addr:full":"Rte de Suze Boll\u00e8ne Centre 84500",
    "addr:postcode":"84500",
    "addr:street":"Rte De Suze",
    "iso:country":"FR",
    "sg:address":"Rte de Suze",
    "sg:city":"Boll\u00e8ne",
    "sg:orig_category":"Unclassifiable Establishments",
    "sg:phone":"+33 4 90 30 13 35",
    "sg:postcode":"84500",
    "sg:province":"Centre",
    "wof:name":"S.p.r.b. Valabr\u00e8gue S.a. - Soci\u00e9t\u00e9 Produits R\u00e9fractaires De Boll\u00e8ne Valabr\u00e8g",
    "wof:placetype":"venue"
},
  "geometry": {"coordinates":[4.748432,44.282192],"type":"Point"}
}