{
  "type": "Feature",
  "properties": {
    "addr:full":"11, Rue du Vide Arpents - ZA la Bauve, 77109 Meaux C\u00e9dex \u00cele-de-France",
    "addr:housenumber":"11",
    "addr:postcode":"77109",
    "addr:street":"Rue Du Vide Arpents Za La Bauve;Ce\u0301Dex",
    "iso:country":"FR",
    "sg:address":"11, Rue du Vide Arpents - ZA la Bauve, 77109 Meaux C\u00e9dex",
    "sg:orig_category":"Non-Classified Establishments",
    "sg:phone":"+33 1 64 36 55 30",
    "sg:province":"\u00cele-de-France",
    "wof:name":"Produits Aug\u00e9 Roger S.a.",
    "wof:placetype":"venue"
},
  "geometry": {"coordinates":[2.883054,48.959351],"type":"Point"}
}