{
  "type": "Feature",
  "properties": {
    "addr:full":"11 Rue De Cambrai 75019 Paris Ile de France 75019",
    "addr:housenumber":"11",
    "addr:postcode":"75019;75019",
    "addr:street":"Rue De Cambrai",
    "iso:country":"FR",
    "sg:address":"11 Rue De Cambrai 75019 Paris",
    "sg:classifiers":[
        {
            "category":"Professional",
            "subcategory":"Advertising",
            "type":"Services"
        }
    ],
    "sg:phone":"+33 1 40 38 03 73",
    "sg:postcode":"75019",
    "sg:province":"Ile de France",
    "sg:tags":[
        "communication",
        "medium"
    ],
    "wof:name":"Jet Realisation Sa",
    "wof:placetype":"venue"
},
  "geometry": {"coordinates":[2.377907,48.89473],"type":"Point"}
}