{
  "type": "Feature",
  "properties": {
    "addr:full":"Avenue Commandos D'Afrique 83980 Le Lavandou Basse Normandie",
    "addr:postcode":"83980",
    "addr:street":"Avenue Commandos D'Afrique",
    "iso:country":"FR",
    "sg:address":"Avenue Commandos D'Afrique 83980 Le Lavandou",
    "sg:classifiers":[
        {
            "category":"Travel",
            "subcategory":"Hotels & Motels",
            "type":"Entertainment"
        }
    ],
    "sg:phone":"+33 4 94 71 11 09",
    "sg:province":"Basse Normandie",
    "sg:tags":[
        "hotels",
        "business",
        "restaurant"
    ],
    "wof:name":"Hotel Beau Rivage",
    "wof:placetype":"venue"
},
  "geometry": {"coordinates":[6.367015,43.136353],"type":"Point"}
}