{
  "type": "Feature",
  "properties": {
    "iso:country":"FR",
    "sg:address":"157, Rue Auguste Bonte, 59130 Lambersart",
    "sg:orig_category":"Unclassifiable Establishments",
    "sg:phone":"+33 3 20 22 77 99",
    "sg:province":"Nord Pas-de-Calais",
    "wof:name":"Schindler S.a.",
    "wof:placetype":"venue"
},
  "geometry": {"coordinates":[3.020633,50.645233],"type":"Point"}
}