{
  "type": "Feature",
  "properties": {
    "addr:full":"1, Rue du Ruisseau Blanc - Centre d' Activit\u00e9s de Lunezy, 91620 Nozay Ile de France",
    "addr:housenumber":"1",
    "addr:postcode":"91620;ile",
    "addr:street":"Rue Du Ruisseau Blanc;D",
    "iso:country":"FR",
    "sg:address":"1, Rue du Ruisseau Blanc - Centre d' Activit\u00e9s de Lunezy, 91620 Nozay",
    "sg:orig_category":"Non-Classified Establishments",
    "sg:phone":"+33 1 64 49 63 50",
    "sg:province":"Ile de France",
    "wof:name":"Schaefer Techniques S.a.r.l.",
    "wof:placetype":"venue"
},
  "geometry": {"coordinates":[2.250208,48.664791],"type":"Point"}
}