{
  "type": "Feature",
  "properties": {
    "addr:full":"107 Rue Henri Barbusse 92111 Clichy Aquitaine",
    "addr:housenumber":"107",
    "addr:postcode":"92111",
    "addr:street":"Rue Henri Barbusse",
    "iso:country":"FR",
    "sg:address":"107 Rue Henri Barbusse 92111 Clichy",
    "sg:classifiers":[
        {
            "category":"Shopping",
            "subcategory":"Stationery & Office Supplies",
            "type":"Retail Goods"
        }
    ],
    "sg:phone":"+33 1 41 06 73 00",
    "sg:province":"Aquitaine",
    "sg:tags":[
        "information",
        "technology",
        "telecommunication",
        "equipment"
    ],
    "wof:name":"Slg Satas Sarl",
    "wof:placetype":"venue"
},
  "geometry": {"coordinates":[2.308657,48.901337],"type":"Point"}
}