{
  "type": "Feature",
  "properties": {
    "addr:full":"3 Rue St Charles 71360 Epinac \u00c9pinac Bourgogne 71360",
    "addr:housenumber":"3",
    "addr:postcode":"71360;71360",
    "addr:street":"Rue St Charles",
    "iso:country":"FR",
    "sg:address":"3 Rue St Charles 71360 Epinac",
    "sg:city":"\u00c9pinac",
    "sg:classifiers":[
        {
            "category":"Shopping",
            "type":"Retail Goods"
        }
    ],
    "sg:phone":"+33 3 85 82 40 40",
    "sg:postcode":"71360",
    "sg:province":"Bourgogne",
    "sg:tags":[
        "metallurgy",
        "finished",
        "-",
        "metalworking",
        "metallic"
    ],
    "wof:name":"Lioret Sa",
    "wof:placetype":"venue"
},
  "geometry": {"coordinates":[4.53966,46.984509],"type":"Point"}
}