{
  "type": "Feature",
  "properties": {
    "iso:country":"FR",
    "sg:address":"Rue Chazot 2",
    "sg:city":"Guereins",
    "sg:orig_category":"Unclassifiable Establishments",
    "sg:phone":"+33 4 74 66 48 27",
    "sg:postcode":"01090",
    "sg:province":"Rhone-Alpes",
    "wof:name":"Entreprise Lendaro Guy",
    "wof:placetype":"venue"
},
  "geometry": {"coordinates":[4.784129,46.110104],"type":"Point"}
}