{
  "type": "Feature",
  "properties": {
    "iso:country":"FR",
    "sg:address":"B.P. 56, 54182 Heillecourt C\u00e9dex^^15, Av. des Erables - ZI Ouest, 54180 Heillecourt",
    "sg:orig_category":"Bo\u00eetes en carton compact Caisses en bois Coffrets en bois pour vins Conditionnement \u00e0 fa\u00e7on Emballag",
    "sg:phone":"+33 3 83 55 47 55",
    "sg:postcode":"54180",
    "sg:province":"Lorraine",
    "wof:name":"C.a.t. Andr\u00e9 Lanciot - A.e.i.m.",
    "wof:placetype":"venue"
},
  "geometry": {"coordinates":[6.194192,48.653137],"type":"Point"}
}