{
  "type": "Feature",
  "properties": {
    "iso:country":"FR",
    "sg:address":"ZA de Penhoat",
    "sg:city":"Saint Divy",
    "sg:orig_category":"Non-Classified Establishments",
    "sg:phone":"+33 2 98 20 29 16",
    "sg:postcode":"29800",
    "sg:province":"Bretagne",
    "wof:name":"Gyma Bretagne S.a.",
    "wof:placetype":"venue"
},
  "geometry": {"coordinates":[-4.335159,48.454025],"type":"Point"}
}