{
  "type": "Feature",
  "properties": {
    "addr:full":"58, Rue de Londres, 75008 Paris Ile de France",
    "addr:housenumber":"58",
    "addr:postcode":"75008",
    "addr:street":"Rue De Londres",
    "iso:country":"FR",
    "sg:address":"58, Rue de Londres, 75008 Paris",
    "sg:orig_category":"Unclassifiable Establishments",
    "sg:phone":"+33 1 42 93 38 74",
    "sg:province":"Ile de France",
    "wof:name":"Rail France Suisse S.a.s.",
    "wof:placetype":"venue"
},
  "geometry": {"coordinates":[2.324252,48.878864],"type":"Point"}
}