{
  "type": "Feature",
  "properties": {
    "addr:full":"14 Rue Racine Nantes Pays de Loire 44000",
    "addr:housenumber":"14",
    "addr:postcode":"44000",
    "addr:street":"Rue Racine",
    "iso:country":"FR",
    "sg:address":"14 Rue Racine",
    "sg:city":"Nantes",
    "sg:classifiers":[
        {
            "category":"Banks & Credit Unions",
            "subcategory":"Financial Services",
            "type":"Services"
        }
    ],
    "sg:phone":"+33 2 40 71 09 00",
    "sg:postcode":"44000",
    "sg:province":"Pays de Loire",
    "sg:tags":[
        "banking",
        "finance",
        "insurance"
    ],
    "wof:name":"Caisse Generale D Assurance Mutuelles",
    "wof:placetype":"venue"
},
  "geometry": {"coordinates":[-1.564495,47.213863],"type":"Point"}
}