{
  "type": "Feature",
  "properties": {
    "iso:country":"FR",
    "sg:address":"B.P. 25, 17320 Marennes^^ZA les Grossines, 17320 Marennes",
    "sg:orig_category":"Non-Classified Establishments",
    "sg:phone":"+33 5 46 85 18 73",
    "sg:postcode":"17320",
    "sg:province":"Poitou-Charentes",
    "wof:name":"D.a.z.a. S.a.r.l.",
    "wof:placetype":"venue"
},
  "geometry": {"coordinates":[-1.053868,45.796875],"type":"Point"}
}