{
  "type": "Feature",
  "properties": {
    "iso:country":"FR",
    "sg:address":"B.P. 92, 92232 Gennevilliers C\u00e9dex^^23, Rue du 19 Mars 1952, 92230 Gennevilliers",
    "sg:orig_category":"Non-Classified Establishments",
    "sg:phone":"+33 1 40 80 59 24",
    "sg:province":"Ile de France",
    "wof:name":"Serae S.a. - Soci\u00e9t\u00e9 D'etudes Et R\u00e9alisations A\u00e9rothermiques",
    "wof:placetype":"venue"
},
  "geometry": {"coordinates":[2.29447,48.925026],"type":"Point"}
}