{
  "type": "Feature",
  "properties": {
    "iso:country":"FR",
    "sg:address":"9 bd du Pr\u00e9sident Wilson 67000 Strasbourg",
    "sg:city":"Strasbourg",
    "sg:classifiers":[
        {
            "category":"Personal",
            "subcategory":"Skin Care",
            "type":"Services"
        }
    ],
    "sg:phone":"+33 3 88 32 69 87",
    "sg:postcode":"67000",
    "sg:province":"Alsace",
    "sg:tags":[
        "cleaning",
        "maintenance"
    ],
    "wof:name":"Tschoeppe Sa",
    "wof:placetype":"venue"
},
  "geometry": {"coordinates":[7.771805,48.591312],"type":"Point"}
}