{
  "type": "Feature",
  "properties": {
    "addr:full":"206, Bd Anatole France, 93200 Saint Denis Ile de France",
    "addr:housenumber":"206",
    "addr:postcode":"93200",
    "addr:street":"Bd Anatole France",
    "iso:country":"FR",
    "sg:address":"206, Bd Anatole France, 93200 Saint Denis",
    "sg:orig_category":"Non-Classified Establishments",
    "sg:phone":"+33 1 48 13 35 00",
    "sg:province":"Ile de France",
    "wof:name":"S.n.e.f.",
    "wof:placetype":"venue"
},
  "geometry": {"coordinates":[2.341359,48.918228],"type":"Point"}
}