{
  "type": "Feature",
  "properties": {
    "addr:full":"23, Rue de la Performance - Europarc Les Pr\u00e9s - B\u00e2t. B.V.3, 59650 Villeneuve d'Ascq Vill\u00e9 Alsace 67220",
    "addr:housenumber":"23;b.v.3",
    "addr:postcode":"59650;67220",
    "addr:street":"Rue De La",
    "iso:country":"FR",
    "sg:address":"23, Rue de la Performance - Europarc Les Pr\u00e9s - B\u00e2t. B.V.3, 59650 Villeneuve d'Ascq",
    "sg:city":"Vill\u00e9",
    "sg:orig_category":"Unclassifiable Establishments",
    "sg:phone":"+33 3 20 41 42 20",
    "sg:postcode":"67220",
    "sg:province":"Alsace",
    "wof:name":"A.b.b. - S.n.c. - Asea Brown Boveri, Solyvent Ventec",
    "wof:placetype":"venue"
},
  "geometry": {"coordinates":[5.57882,44.527309],"type":"Point"}
}