{
  "type": "Feature",
  "properties": {
    "iso:country":"FR",
    "sg:address":"101, Rue de Paris, 16000 Angoul\u00eame",
    "sg:orig_category":"Non-Classified Establishments",
    "sg:phone":"+33 5 45 92 37 22",
    "sg:postcode":"16000",
    "sg:province":"Poitou-Charentes",
    "wof:name":"D\u00e9m\u00e9nagements Delage S.a.r.l.",
    "wof:placetype":"venue"
},
  "geometry": {"coordinates":[0.162537,45.65649],"type":"Point"}
}