{
  "type": "Feature",
  "properties": {
    "addr:full":"101, Rue de Paris, 16000 Angoul\u00eame Poitou-Charentes 16000",
    "addr:housenumber":"101",
    "addr:postcode":"16000;16000",
    "addr:street":"Rue De Paris",
    "iso:country":"FR",
    "sg:address":"101, Rue de Paris, 16000 Angoul\u00eame",
    "sg:orig_category":"Non-Classified Establishments",
    "sg:phone":"+33 5 45 92 37 22",
    "sg:postcode":"16000",
    "sg:province":"Poitou-Charentes",
    "wof:name":"D\u00e9m\u00e9nagements Delage S.a.r.l.",
    "wof:placetype":"venue"
},
  "geometry": {"coordinates":[0.162537,45.65649],"type":"Point"}
}