{
  "type": "Feature",
  "properties": {
    "addr:full":"B.P. 11, 54110 Dombasle sur Meurthe^^1, Rue Cl\u00e9menceau, 54110 Dombasle sur Meurthe Lorraine 54110",
    "addr:postcode":"54110;54110;54110",
    "addr:street":"B.P. 11;Rue Cle\u0301Menceau",
    "iso:country":"FR",
    "sg:address":"B.P. 11, 54110 Dombasle sur Meurthe^^1, Rue Cl\u00e9menceau, 54110 Dombasle sur Meurthe",
    "sg:orig_category":"Non-Classified Establishments",
    "sg:phone":"+33 3 83 45 37 65",
    "sg:postcode":"54110",
    "sg:province":"Lorraine",
    "wof:name":"A.c.m.r. S.a. - Les Anciens De La Construction M\u00e9canique R\u00e9paration",
    "wof:placetype":"venue"
},
  "geometry": {"coordinates":[6.349435,48.622681],"type":"Point"}
}