{
  "type": "Feature",
  "properties": {
    "iso:country":"FR",
    "sg:address":"3 rue de Zimmersheim 68400 Riedisheim",
    "sg:city":"Riedisheim",
    "sg:orig_category":"Furniture, General",
    "sg:phone":"+33 3 89 31 88 40",
    "sg:postcode":"68400",
    "sg:province":"Alsace",
    "wof:name":"Euro Diffusion Sarl",
    "wof:placetype":"venue"
},
  "geometry": {"coordinates":[7.354882,47.739483],"type":"Point"}
}