{
  "type": "Feature",
  "properties": {
    "addr:full":"Z.A. du Klintz Oberhaslach Alsace 67280",
    "addr:postcode":"67280",
    "addr:street":"Z.A. Du Klintz Oberhaslach",
    "iso:country":"FR",
    "sg:address":"Z.A. du Klintz",
    "sg:city":"Oberhaslach",
    "sg:orig_category":"Non-Classified Establishments",
    "sg:phone":"+33 3 88 50 91 28",
    "sg:postcode":"67280",
    "sg:province":"Alsace",
    "wof:name":"Boehm Construction Terrassement S.a.r.l.",
    "wof:placetype":"venue"
},
  "geometry": {"coordinates":[7.330461,48.549908],"type":"Point"}
}