{
  "type": "Feature",
  "properties": {
    "addr:full":"4 Rue Paul Val\u00e9rien P\u00e9rin 38170 Seyssinet Pariset Rhone-Alpes 38170",
    "addr:housenumber":"4",
    "addr:postcode":"38170;38170",
    "addr:street":"Rue Paul Vale\u0301Rien Pe\u0301Rin;Rhone-Alpes",
    "iso:country":"FR",
    "sg:address":"4 Rue Paul Val\u00e9rien P\u00e9rin 38170 Seyssinet Pariset",
    "sg:classifiers":[
        {
            "category":"Banks & Credit Unions",
            "subcategory":"Financial Services",
            "type":"Services"
        }
    ],
    "sg:phone":"+33 4 76 48 48 49",
    "sg:postcode":"38170",
    "sg:province":"Rhone-Alpes",
    "sg:tags":[
        "banking",
        "finance",
        "insurance"
    ],
    "wof:name":"Buiron Bret Magnin Et Associes Sarl",
    "wof:placetype":"venue"
},
  "geometry": {"coordinates":[5.689261,45.172302],"type":"Point"}
}