{
  "type": "Feature",
  "properties": {
    "addr:full":"12 Mail Des Copistes 95220 Herblay Ile de France 95220",
    "addr:housenumber":"12",
    "addr:postcode":"95220;ile;95220",
    "addr:street":"Mail Des Copistes;France",
    "iso:country":"FR",
    "sg:address":"12 Mail Des Copistes 95220 Herblay",
    "sg:classifiers":[
        {
            "category":"Shopping",
            "subcategory":"Bicycles & Sporting Goods",
            "type":"Retail Goods"
        }
    ],
    "sg:phone":"+33 1 34 50 66 50",
    "sg:postcode":"95220",
    "sg:province":"Ile de France",
    "sg:tags":[
        "product",
        "sport",
        "miscellaneous"
    ],
    "wof:name":"Decathlon Sa",
    "wof:placetype":"venue"
},
  "geometry": {"coordinates":[2.189645,48.998734],"type":"Point"}
}