{
  "type": "Feature",
  "properties": {
    "addr:full":"8 Rue Des Champs 62217 Achicourt Nord Pas-de-Calais",
    "addr:housenumber":"8",
    "addr:postcode":"62217",
    "addr:street":"Rue Des Champs",
    "iso:country":"FR",
    "sg:address":"8 Rue Des Champs 62217 Achicourt",
    "sg:classifiers":[
        {
            "category":"Professional",
            "type":"Services"
        }
    ],
    "sg:phone":"+33 3 21 23 30 76",
    "sg:province":"Nord Pas-de-Calais",
    "sg:tags":[
        "transport",
        "road"
    ],
    "wof:name":"Intervrac Sa",
    "wof:placetype":"venue"
},
  "geometry": {"coordinates":[2.767112,50.281799],"type":"Point"}
}