{
  "type": "Feature",
  "properties": {
    "iso:country":"FR",
    "sg:address":"Z.I. du puits 72500 Ch\u00e2teau du Loir",
    "sg:orig_category":"Electrode Holders For Automated Welding Systems",
    "sg:phone":"+33 2 43 44 02 48",
    "sg:postcode":"72500",
    "sg:province":"Pays de Loire",
    "wof:name":"Serv Sa",
    "wof:placetype":"venue"
},
  "geometry": {"coordinates":[0.33858,47.612446],"type":"Point"}
}