{
  "type": "Feature",
  "properties": {
    "addr:full":"Les Bernardines Hall 5 Box 91 84300 Cavaillon Provence-Alpes-C\u00f4te d'Azur",
    "addr:housenumber":"5 box 91",
    "addr:postcode":"84300",
    "iso:country":"FR",
    "sg:address":"Les Bernardines Hall 5 Box 91 84300 Cavaillon",
    "sg:classifiers":[
        {
            "category":"Professional",
            "type":"Services"
        }
    ],
    "sg:phone":"+33 4 90 06 38 00",
    "sg:province":"Provence-Alpes-C\u00f4te d'Azur",
    "sg:tags":[
        "transport",
        "road"
    ],
    "wof:name":"Ste De Transports Et D Affretements Du Tregor (stat)",
    "wof:placetype":"venue"
},
  "geometry": {"coordinates":[5.039415,43.837685],"type":"Point"}
}