{
  "type": "Feature",
  "properties": {
    "addr:full":"149 R D'Ensisheim 68270 Wittenheim Wittenheim Alsace 68270",
    "addr:housenumber":"149",
    "addr:postcode":"68270;68270",
    "addr:street":"R D'Ensisheim",
    "iso:country":"FR",
    "sg:address":"149 R D'Ensisheim 68270 Wittenheim",
    "sg:city":"Wittenheim",
    "sg:classifiers":[
        {
            "category":"Food Court",
            "type":"Food & Drink"
        }
    ],
    "sg:phone":"+33 3 89 62 03 21",
    "sg:postcode":"68270",
    "sg:province":"Alsace",
    "sg:tags":[
        "product",
        "related"
    ],
    "wof:name":"Bilger Et Fils Sarl",
    "wof:placetype":"venue"
},
  "geometry": {"coordinates":[7.339793,47.812237],"type":"Point"}
}