{
  "type": "Feature",
  "properties": {
    "addr:full":"96 Av De Paris 79000 Niort Poitou-Charentes 79000",
    "addr:postcode":"79000;79000",
    "addr:street":"96 Av De Paris",
    "iso:country":"FR",
    "sg:address":"96 Av De Paris 79000 Niort",
    "sg:classifiers":[
        {
            "category":"Travel",
            "subcategory":"Hotels & Motels",
            "type":"Entertainment"
        }
    ],
    "sg:phone":"+33 5 49 24 36 21",
    "sg:postcode":"79000",
    "sg:province":"Poitou-Charentes",
    "sg:tags":[
        "hotels",
        "business",
        "restaurant"
    ],
    "wof:name":"Hotel Du Parc Sarl",
    "wof:placetype":"venue"
},
  "geometry": {"coordinates":[-0.452223,46.32579],"type":"Point"}
}