{
  "type": "Feature",
  "properties": {
    "iso:country":"FR",
    "sg:address":"68, Rue Michel Ange, 75016 Paris",
    "sg:orig_category":"Unclassifiable Establishments",
    "sg:phone":"+33 1 40 71 25 25",
    "sg:province":"Ile de France",
    "wof:name":"T.d.l. Le Syst\u00e8me P\u00e9ricl\u00e8s S.a.",
    "wof:placetype":"venue"
},
  "geometry": {"coordinates":[2.259477,48.842617],"type":"Point"}
}