{
  "type": "Feature",
  "properties": {
    "iso:country":"FR",
    "sg:address":"B.P. 176, 67506 Haguenau C\u00e9dex^^18, Grand' rue, 67500 Haguenau",
    "sg:city":"Haguenau",
    "sg:orig_category":"Non-Classified Establishments",
    "sg:phone":"+33 3 88 06 17 18",
    "sg:postcode":"67500",
    "sg:province":"Alsace",
    "wof:name":"Zuber Michael S.a.",
    "wof:placetype":"venue"
},
  "geometry": {"coordinates":[7.82145,48.81979],"type":"Point"}
}