{
  "type": "Feature",
  "properties": {
    "addr:full":"Le Pastenc 82710 Bressols Midi Pyr\u00e9n\u00e9es",
    "addr:postcode":"82710",
    "iso:country":"FR",
    "sg:address":"Le Pastenc 82710 Bressols",
    "sg:orig_category":"Unclassifiable Establishments",
    "sg:phone":"+33 5 63 02 90 80",
    "sg:province":"Midi Pyr\u00e9n\u00e9es",
    "wof:name":"Occa Palette",
    "wof:placetype":"venue"
},
  "geometry": {"coordinates":[1.322402,43.943333],"type":"Point"}
}