{
  "type": "Feature",
  "properties": {
    "iso:country":"FR",
    "sg:address":"15 rue Louis Armand 77330 OZOIR LA FERRIERE",
    "sg:classifiers":[
        {
            "category":"Manufacturing",
            "subcategory":"Signs",
            "type":"Manufacturing & Wholesale Goods"
        }
    ],
    "sg:phone":"+33 1 64 43 56 56",
    "sg:postcode":"77330",
    "sg:province":"Ile de France",
    "sg:tags":[
        "display"
    ],
    "wof:name":"Ravel Sa",
    "wof:placetype":"venue"
},
  "geometry": {"coordinates":[2.689349,48.764362],"type":"Point"}
}