{
  "type": "Feature",
  "properties": {
    "iso:country":"FR",
    "sg:address":"11 Chemin Montifault BP 2 18800 Baugy",
    "sg:city":"Baugy",
    "sg:classifiers":[
        {
            "category":"Shopping",
            "subcategory":"Clothing, Apparel, & Fashions",
            "type":"Retail Goods"
        }
    ],
    "sg:phone":"+33 2 48 26 18 32",
    "sg:postcode":"18800",
    "sg:province":"Centre",
    "sg:tags":[
        "textile",
        "clothing",
        "clothes"
    ],
    "wof:name":"Gerard Pasquier - Paris Sa",
    "wof:placetype":"venue"
},
  "geometry": {"coordinates":[2.735473,47.082607],"type":"Point"}
}