{
  "type": "Feature",
  "properties": {
    "addr:full":"10, Rue Henri Farman, 93290 Tremblay en France Ile de France",
    "addr:housenumber":"10",
    "addr:postcode":"93290",
    "addr:street":"Rue Henri Farman",
    "iso:country":"FR",
    "sg:address":"10, Rue Henri Farman, 93290 Tremblay en France",
    "sg:orig_category":"Non-Classified Establishments",
    "sg:phone":"+33 1 48 60 90 32",
    "sg:province":"Ile de France",
    "wof:name":"K.b.a. Graphic S.a.r.l.",
    "wof:placetype":"venue"
},
  "geometry": {"coordinates":[2.562882,48.965767],"type":"Point"}
}