{
  "type": "Feature",
  "properties": {
    "addr:full":"247 rue de Chambourg 01100 Oyonnax Rhone-Alpes 01100",
    "addr:housenumber":"247",
    "addr:postcode":"01100;01100",
    "addr:street":"Rue De Chambourg",
    "iso:country":"FR",
    "sg:address":"247 rue de Chambourg 01100 Oyonnax",
    "sg:classifiers":[
        {
            "category":"Shopping",
            "subcategory":"Beauty & Cosmetics",
            "type":"Retail Goods"
        }
    ],
    "sg:phone":"+33 4 74 81 22 60",
    "sg:postcode":"01100",
    "sg:province":"Rhone-Alpes",
    "sg:tags":[
        "natural"
    ],
    "wof:name":"Productions Realisations Plastiques S.a.r.l.",
    "wof:placetype":"venue"
},
  "geometry": {"coordinates":[5.607399,46.268654],"type":"Point"}
}