{
  "type": "Feature",
  "properties": {
    "addr:full":"20 Rue D'En Haut 59161 Cagnoncles Nord Pas-de-Calais 59161",
    "addr:housenumber":"20",
    "addr:postcode":"59161;59161",
    "addr:street":"Rue D'En Haut",
    "iso:country":"FR",
    "sg:address":"20 Rue D'En Haut 59161 Cagnoncles",
    "sg:classifiers":[
        {
            "category":"Building & Trades",
            "subcategory":"Construction",
            "type":"Services"
        }
    ],
    "sg:phone":"+33 3 27 37 84 45",
    "sg:postcode":"59161",
    "sg:province":"Nord Pas-de-Calais",
    "sg:tags":[
        "work",
        "public"
    ],
    "wof:name":"Groupe Paveurs Unis",
    "wof:placetype":"venue"
},
  "geometry": {"coordinates":[3.31121,50.193851],"type":"Point"}
}