{
  "type": "Feature",
  "properties": {
    "iso:country":"FR",
    "sg:address":"Le Raumarais 50440 Diguelleville",
    "sg:city":"Acqueville",
    "sg:classifiers":[
        {
            "category":"Shopping",
            "type":"Retail Goods"
        }
    ],
    "sg:phone":"+33 2 33 10 04 40",
    "sg:postcode":"50440",
    "sg:province":"Basse Normandie",
    "sg:tags":[
        "metallurgy",
        "finished",
        "-",
        "metalworking",
        "metallic"
    ],
    "wof:name":"Ste D'exploitation Des Ets Grisel Seeg",
    "wof:placetype":"venue"
},
  "geometry": {"coordinates":[-93.082802,43.31329],"type":"Point"}
}