{
  "type": "Feature",
  "properties": {
    "addr:full":"Rue de Chatham Esternay Champagne 51310",
    "addr:housenumber":"esternay",
    "addr:postcode":"51310",
    "addr:street":"Rue De Chatham",
    "iso:country":"FR",
    "sg:address":"Rue de Chatham",
    "sg:city":"Esternay",
    "sg:orig_category":"Unclassifiable Establishments",
    "sg:phone":"+33 3 26 81 73 80",
    "sg:postcode":"51310",
    "sg:province":"Champagne",
    "wof:name":"Coop\u00e9rative Agricole D'esternay",
    "wof:placetype":"venue"
},
  "geometry": {"coordinates":[3.560831,48.729393],"type":"Point"}
}