{
  "type": "Feature",
  "properties": {
    "iso:country":"FR",
    "sg:address":"zi Capitany 09000 Foix",
    "sg:classifiers":[
        {
            "category":"Professional",
            "type":"Services"
        }
    ],
    "sg:phone":"+33 5 61 02 86 50",
    "sg:province":"Midi Pyr\u00e9n\u00e9es",
    "sg:tags":[
        "transport",
        "road"
    ],
    "wof:name":"Ariege Ambulances",
    "wof:placetype":"venue"
},
  "geometry": {"coordinates":[1.60547,42.963703],"type":"Point"}
}