{
  "type": "Feature",
  "properties": {
    "iso:country":"FR",
    "sg:address":"Za 17150 Mirambeau",
    "sg:classifiers":[
        {
            "category":"Military Area",
            "subcategory":"Air Force Base",
            "type":"Public Place"
        }
    ],
    "sg:phone":"+33 5 46 70 73 73",
    "sg:province":"Poitou-Charentes",
    "sg:tags":[
        "tube",
        "socket"
    ],
    "wof:name":"Axcyl Composite Sa",
    "wof:placetype":"venue"
},
  "geometry": {"coordinates":[-0.539129,45.313686],"type":"Point"}
}