{
  "type": "Feature",
  "properties": {
    "addr:full":"RD 737 Sainte Eanne Poitou-Charentes 79800",
    "addr:postcode":"79800",
    "addr:street":"Rd 737 Sainte Eanne",
    "iso:country":"FR",
    "sg:address":"RD 737",
    "sg:city":"Sainte Eanne",
    "sg:orig_category":"Unclassifiable Establishments",
    "sg:phone":"+33 5 49 77 25 25",
    "sg:postcode":"79800",
    "sg:province":"Poitou-Charentes",
    "wof:name":"Soviba Saint Maixent S.a.",
    "wof:placetype":"venue"
},
  "geometry": {"coordinates":[-0.160149,46.320221],"type":"Point"}
}