{
  "type": "Feature",
  "properties": {
    "addr:full":"490 Avenue Des Forgeron 40150 SOORTS HOSSEGOR Angresse Aquitaine 40150",
    "addr:housenumber":"490",
    "addr:postcode":"40150;40150",
    "addr:street":"Avenue Des Forgeron",
    "iso:country":"FR",
    "sg:address":"490 Avenue Des Forgeron 40150 SOORTS HOSSEGOR",
    "sg:city":"Angresse",
    "sg:orig_category":"Wetsuits, Surfwear",
    "sg:phone":"+33 5 58 70 00 00",
    "sg:postcode":"40150",
    "sg:province":"Aquitaine",
    "wof:name":"Kala Sarl",
    "wof:placetype":"venue"
},
  "geometry": {"coordinates":[-1.383619,43.672428],"type":"Point"}
}