{
  "type": "Feature",
  "properties": {
    "addr:full":"8 R Antoine Lavoisier 76305 Sotteville Les Rouen Vill\u00e9 Alsace 67220",
    "addr:housenumber":"8",
    "addr:postcode":"76305;67220",
    "addr:street":"R Antoine Lavoisier",
    "iso:country":"FR",
    "sg:address":"8 R Antoine Lavoisier 76305 Sotteville Les Rouen",
    "sg:city":"Vill\u00e9",
    "sg:classifiers":[
        {
            "category":"Manufacturing",
            "subcategory":"Paper Products",
            "type":"Manufacturing & Wholesale Goods"
        }
    ],
    "sg:phone":"+33 2 35 64 38 00",
    "sg:postcode":"67220",
    "sg:province":"Alsace",
    "sg:tags":[
        "finished",
        "cardboard",
        "-"
    ],
    "wof:name":"Kimberley Clark Snc",
    "wof:placetype":"venue"
},
  "geometry": {"coordinates":[1.114032,49.40509],"type":"Point"}
}