{
  "type": "Feature",
  "properties": {
    "addr:full":"ZI le Champ Fleuri Les Sorini\u00e8res Pays de Loire 44840",
    "addr:postcode":"44840",
    "addr:street":"Zi Le Champ Fleuri Les Sorinie\u0300Res Pays",
    "iso:country":"FR",
    "sg:address":"ZI le Champ Fleuri",
    "sg:city":"Les Sorini\u00e8res",
    "sg:orig_category":"Unclassifiable Establishments",
    "sg:phone":"+33 2 40 31 22 73",
    "sg:postcode":"44840",
    "sg:province":"Pays de Loire",
    "wof:name":"Lesimple S.a.",
    "wof:placetype":"venue"
},
  "geometry": {"coordinates":[-1.531499,47.148575],"type":"Point"}
}