{
  "type": "Feature",
  "properties": {
    "iso:country":"FR",
    "sg:address":"Rue Arago 89400 Migennes",
    "sg:city":"Migennes",
    "sg:classifiers":[
        {
            "category":"Autos & Motor Vehicles",
            "subcategory":"Automobile Sales",
            "type":"Retail Goods"
        }
    ],
    "sg:phone":"+33 3 86 80 23 11",
    "sg:postcode":"89400",
    "sg:province":"Bourgogne",
    "sg:tags":[
        "equipment",
        "motor-cars",
        "transport"
    ],
    "wof:name":"Lhussiez Sa",
    "wof:placetype":"venue"
},
  "geometry": {"coordinates":[3.542833,47.971241],"type":"Point"}
}