{
  "type": "Feature",
  "properties": {
    "addr:full":"15 Boulevard Benoite Danesi 20200 Bastia Corse 20200",
    "addr:housenumber":"15",
    "addr:postcode":"20200;20200",
    "addr:street":"Boulevard Benoite Danesi",
    "iso:country":"FR",
    "sg:address":"15 Boulevard Benoite Danesi 20200 Bastia",
    "sg:classifiers":[
        {
            "category":"Professional",
            "subcategory":"Business Services",
            "type":"Services"
        }
    ],
    "sg:phone":"+33 4 95 32 81 00",
    "sg:postcode":"20200",
    "sg:province":"Corse",
    "sg:tags":[
        "training",
        "advice"
    ],
    "wof:name":"College Et Lycee Prives Mixtes Jeanne D Arc Ass",
    "wof:placetype":"venue"
},
  "geometry": {"coordinates":[9.444171,42.697063],"type":"Point"}
}