{
  "type": "Feature",
  "properties": {
    "iso:country":"FR",
    "sg:address":"268 B Avenue Henri Barbusse 91210 Draveil",
    "sg:classifiers":[
        {
            "category":"Manufacturing",
            "subcategory":"Metals",
            "type":"Manufacturing & Wholesale Goods"
        }
    ],
    "sg:phone":"+33 1 69 83 08 80",
    "sg:postcode":"91210",
    "sg:province":"Ile de France",
    "sg:tags":[
        "metallurgy",
        "metalworking",
        "processing"
    ],
    "wof:name":"Societe D'etudes Et De Reals D'equ Ipements Electriques (serec)",
    "wof:placetype":"venue"
},
  "geometry": {"coordinates":[2.411333,48.690605],"type":"Point"}
}