{
  "type": "Feature",
  "properties": {
    "iso:country":"FR",
    "sg:address":"1, Rue Arago, 03100 Montlu\u00e7on",
    "sg:city":"Montlu\u00e7on",
    "sg:orig_category":"Non-Classified Establishments",
    "sg:phone":"+33 4 70 08 32 40",
    "sg:postcode":"03100",
    "sg:province":"Auvergne",
    "wof:name":"Bernex France S.a.r.l.",
    "wof:placetype":"venue"
},
  "geometry": {"coordinates":[2.60504,46.3382],"type":"Point"}
}