{
  "type": "Feature",
  "properties": {
    "iso:country":"FR",
    "sg:address":"B.P. 131, 06703 Saint Laurent du Var C\u00e9dex^^146, Av. Mar\u00e9chal Juin - Immeuble Patricia, 06700 Saint ",
    "sg:orig_category":"Non-Classified Establishments",
    "sg:phone":"+33 4 92 12 38 00",
    "sg:province":"Provence-Alpes-C\u00f4te d'Azur",
    "wof:name":"Plein Vent S.a.",
    "wof:placetype":"venue"
},
  "geometry": {"coordinates":[7.188655,43.676384],"type":"Point"}
}