{
  "type": "Feature",
  "properties": {
    "iso:country":"FR",
    "sg:address":"4 Rue Les Freres Montgolfier Zi Des Landes 49240 Avrille",
    "sg:classifiers":[
        {
            "category":"Shopping",
            "subcategory":"Computers & Home Electronics",
            "type":"Retail Goods"
        }
    ],
    "sg:phone":"+33 2 41 34 45 40",
    "sg:postcode":"49240",
    "sg:province":"Pays de Loire",
    "sg:tags":[
        "equipment",
        "electrical",
        "component",
        "electric",
        "electronic"
    ],
    "wof:name":"Incatronic",
    "wof:placetype":"venue"
},
  "geometry": {"coordinates":[-0.587263,47.504822],"type":"Point"}
}