{
  "type": "Feature",
  "properties": {
    "addr:full":"27 Avenue Saint Jean 31800 Valentine Midi Pyr\u00e9n\u00e9es 31800",
    "addr:housenumber":"27",
    "addr:postcode":"31800;31800",
    "addr:street":"Avenue Saint Jean",
    "iso:country":"FR",
    "sg:address":"27 Avenue Saint Jean 31800 Valentine",
    "sg:classifiers":[
        {
            "category":"Manufacturing",
            "subcategory":"Glass & Minerals",
            "type":"Manufacturing & Wholesale Goods"
        }
    ],
    "sg:phone":"+33 5 61 89 05 82",
    "sg:postcode":"31800",
    "sg:province":"Midi Pyr\u00e9n\u00e9es",
    "sg:tags":[
        "building",
        "material"
    ],
    "wof:name":"Beton Controle Du Comminges",
    "wof:placetype":"venue"
},
  "geometry": {"coordinates":[0.701682,43.094318],"type":"Point"}
}