{
  "type": "Feature",
  "properties": {
    "addr:full":"Quai Est De L'Ile Jeanty 59140 Dunkerque Nord Pas-de-Calais 59140",
    "addr:postcode":"59140;59140",
    "addr:street":"Quai Est De L'Ile Jeanty",
    "iso:country":"FR",
    "sg:address":"Quai Est De L'Ile Jeanty 59140 Dunkerque",
    "sg:classifiers":[
        {
            "category":"Manufacturing",
            "subcategory":"Glass & Minerals",
            "type":"Manufacturing & Wholesale Goods"
        }
    ],
    "sg:phone":"+33 3 28 66 99 97",
    "sg:postcode":"59140",
    "sg:province":"Nord Pas-de-Calais",
    "sg:tags":[
        "building",
        "material"
    ],
    "wof:name":"Beton De France Nord Alsace",
    "wof:placetype":"venue"
},
  "geometry": {"coordinates":[2.34684,51.041801],"type":"Point"}
}