{
  "type": "Feature",
  "properties": {
    "iso:country":"FR",
    "sg:address":"33 Rue Jules Nadi 26600 Tain L Hermitage",
    "sg:classifiers":[
        {
            "category":"Wholesale",
            "subcategory":"Meat",
            "type":"Manufacturing & Wholesale Goods"
        }
    ],
    "sg:phone":"+33 4 75 08 29 02",
    "sg:postcode":"26600",
    "sg:province":"Rhone-Alpes",
    "sg:tags":[
        "food",
        "cooked",
        "product",
        "related"
    ],
    "wof:name":"Societe D Exploitation Des Jambons De L'hermitage",
    "wof:placetype":"venue"
},
  "geometry": {"coordinates":[4.842182,45.070499],"type":"Point"}
}