{
  "type": "Feature",
  "properties": {
    "addr:full":"431 Rue Saint Pierre 13005 Marseille Poitou-Charentes",
    "addr:housenumber":"431",
    "addr:postcode":"13005",
    "addr:street":"Rue Saint Pierre",
    "iso:country":"FR",
    "sg:address":"431 Rue Saint Pierre 13005 Marseille",
    "sg:classifiers":[
        {
            "category":"Retail",
            "subcategory":"Event Space",
            "type":"Services"
        }
    ],
    "sg:phone":"+33 4 91 42 18 33",
    "sg:province":"Poitou-Charentes",
    "sg:tags":[
        "product",
        "transport",
        "road",
        "miscellaneous"
    ],
    "wof:name":"Ogf",
    "wof:placetype":"venue"
},
  "geometry": {"coordinates":[5.41038,43.291698],"type":"Point"}
}