{
  "type": "Feature",
  "properties": {
    "addr:full":"Zi La Palue 86220 Ingrandes Sur Vienne Poitou-Charentes 86220",
    "addr:postcode":"86220;86220",
    "addr:street":"Zi La Palue",
    "iso:country":"FR",
    "sg:address":"Zi La Palue 86220 Ingrandes Sur Vienne",
    "sg:classifiers":[
        {
            "category":"Shopping",
            "subcategory":"Clothing, Apparel, & Fashions",
            "type":"Retail Goods"
        }
    ],
    "sg:phone":"+33 5 49 02 19 19",
    "sg:postcode":"86220",
    "sg:province":"Poitou-Charentes",
    "sg:tags":[
        "textile",
        "clothing",
        "clothes"
    ],
    "wof:name":"Ets Petit Et Alleaume Sa",
    "wof:placetype":"venue"
},
  "geometry": {"coordinates":[0.565525,46.877033],"type":"Point"}
}