{
  "type": "Feature",
  "properties": {
    "addr:full":"B.P. 7, 63201 Riom C\u00e9dex^^16, Rue du Commerce, 63200 Riom Riom Auvergne 63200",
    "addr:housenumber":"7",
    "addr:postcode":"63201;63200;63200",
    "addr:street":"B.P.;Rue Du Commerce",
    "iso:country":"FR",
    "sg:address":"B.P. 7, 63201 Riom C\u00e9dex^^16, Rue du Commerce, 63200 Riom",
    "sg:city":"Riom",
    "sg:orig_category":"Non-Classified Establishments",
    "sg:phone":"+33 4 73 33 74 74",
    "sg:postcode":"63200",
    "sg:province":"Auvergne",
    "wof:name":"C.c.i. De Riom - Chambre De Commerce Et D'industrie De Riom",
    "wof:placetype":"venue"
},
  "geometry": {"coordinates":[3.052114,45.84782],"type":"Point"}
}