{
  "type": "Feature",
  "properties": {
    "addr:full":"194, Rue des Puits, 60240 Chaumont en Vexin Picardie",
    "addr:housenumber":"194",
    "addr:postcode":"60240",
    "addr:street":"Rue Des Puits",
    "iso:country":"FR",
    "sg:address":"194, Rue des Puits, 60240 Chaumont en Vexin",
    "sg:orig_category":"Unclassifiable Establishments",
    "sg:phone":"+33 3 44 47 74 84",
    "sg:province":"Picardie",
    "wof:name":"M\u00e9zi\u00e8res Louis S.a.r.l.",
    "wof:placetype":"venue"
},
  "geometry": {"coordinates":[1.90337,49.176022],"type":"Point"}
}