{
  "type": "Feature",
  "properties": {
    "iso:country":"FR",
    "sg:address":"3 bd Camille Pelletan; BP 13; CARCASSONNE; 11001 CEDEX",
    "sg:classifiers":[
        {
            "category":"Shopping",
            "subcategory":"Computers & Home Electronics",
            "type":"Retail Goods"
        }
    ],
    "sg:phone":"+33 4 68 10 36 00",
    "sg:province":"Aquitaine",
    "sg:tags":[
        "chamber",
        "commerce"
    ],
    "wof:name":"Chambre De Commerce De Carcassonne-limoux-castelnaudary",
    "wof:placetype":"venue"
},
  "geometry": {"coordinates":[2.35484,43.214909],"type":"Point"}
}