{
  "type": "Feature",
  "properties": {
    "iso:country":"FR",
    "sg:address":"14, Rue de l'Ours, 68200 Mulhouse",
    "sg:city":"Mulhouse",
    "sg:orig_category":"Unclassifiable Establishments",
    "sg:phone":"+33 3 89 42 45 30",
    "sg:postcode":"68200",
    "sg:province":"Alsace",
    "wof:name":"Sima Import S.a.r.l.",
    "wof:placetype":"venue"
},
  "geometry": {"coordinates":[7.31201,47.75547],"type":"Point"}
}