{
  "type": "Feature",
  "properties": {
    "addr:full":"Rue Issanchou Montauban Midi Pyr\u00e9n\u00e9es 82000",
    "addr:postcode":"82000",
    "addr:street":"Rue Issanchou",
    "iso:country":"FR",
    "sg:address":"Rue Issanchou",
    "sg:city":"Montauban",
    "sg:orig_category":"Unclassifiable Establishments",
    "sg:phone":"+33 5 63 03 32 66",
    "sg:postcode":"82000",
    "sg:province":"Midi Pyr\u00e9n\u00e9es",
    "wof:name":"Treacy Boutonnet S.a.",
    "wof:placetype":"venue"
},
  "geometry": {"coordinates":[1.352323,44.032604],"type":"Point"}
}