{
  "type": "Feature",
  "properties": {
    "addr:full":"40 Avenue Karl Marx Zi Est 69120 Vaulx En Velin Rhone-Alpes 69120",
    "addr:housenumber":"40",
    "addr:postcode":"69120;69120",
    "addr:street":"Avenue Karl Marx Zi Est",
    "iso:country":"FR",
    "sg:address":"40 Avenue Karl Marx Zi Est 69120 Vaulx En Velin",
    "sg:classifiers":[
        {
            "category":"Manufacturing",
            "subcategory":"Metals",
            "type":"Manufacturing & Wholesale Goods"
        }
    ],
    "sg:phone":"+33 4 78 80 04 62",
    "sg:postcode":"69120",
    "sg:province":"Rhone-Alpes",
    "sg:tags":[
        "metallurgy",
        "metalworking",
        "processing"
    ],
    "wof:name":"Sauma Industrie",
    "wof:placetype":"venue"
},
  "geometry": {"coordinates":[4.916895,45.779022],"type":"Point"}
}