{
  "type": "Feature",
  "properties": {
    "addr:full":"19 boulevard des Varennes 51700 Dormans Champagne 51700",
    "addr:housenumber":"19",
    "addr:postcode":"51700;51700",
    "addr:street":"Boulevard Des Varennes;Champagne",
    "iso:country":"FR",
    "sg:address":"19 boulevard des Varennes 51700 Dormans",
    "sg:classifiers":[
        {
            "category":"Wholesale",
            "subcategory":"Construction Materials",
            "type":"Manufacturing & Wholesale Goods"
        }
    ],
    "sg:phone":"+33 3 26 58 20 66",
    "sg:postcode":"51700",
    "sg:province":"Champagne",
    "sg:tags":[
        "girder",
        "made",
        "concrete",
        "floor",
        "formworks",
        "slab",
        "reinforced"
    ],
    "wof:name":"Rennepont Sa",
    "wof:placetype":"venue"
},
  "geometry": {"coordinates":[3.642336,49.079063],"type":"Point"}
}