{
  "type": "Feature",
  "properties": {
    "iso:country":"FR",
    "sg:address":"76, Bd. Victor Hugo, 92110 Clichy",
    "sg:orig_category":"Unclassifiable Establishments",
    "sg:phone":"+33 1 49 68 05 25",
    "sg:province":"Ile de France",
    "wof:name":"Entreprise Chassagne S.a.r.l.",
    "wof:placetype":"venue"
},
  "geometry": {"coordinates":[2.315633,48.900455],"type":"Point"}
}