{
  "type": "Feature",
  "properties": {
    "iso:country":"FR",
    "sg:address":"boulevard des Tourelles 72800 Le Lude",
    "sg:classifiers":[
        {
            "category":"Bus Stop",
            "subcategory":"None",
            "type":"Transportation"
        }
    ],
    "sg:phone":"+33 2 43 48 72 72",
    "sg:province":"Pays de Loire",
    "sg:tags":[
        "period",
        "furniture"
    ],
    "wof:name":"Christie Tayler Continentale Sa",
    "wof:placetype":"venue"
},
  "geometry": {"coordinates":[0.168556,47.636311],"type":"Point"}
}