{
  "type": "Feature",
  "properties": {
    "addr:full":"4 Rue Des Ormes 37530 Nazelles Negron Cangey Centre 37530",
    "addr:housenumber":"4;cangey",
    "addr:postcode":"37530;37530",
    "addr:street":"Rue Des Ormes",
    "iso:country":"FR",
    "sg:address":"4 Rue Des Ormes 37530 Nazelles Negron",
    "sg:city":"Cangey",
    "sg:classifiers":[
        {
            "category":"Manufacturing",
            "subcategory":"Metals",
            "type":"Manufacturing & Wholesale Goods"
        }
    ],
    "sg:phone":"+33 2 47 23 24 22",
    "sg:postcode":"37530",
    "sg:province":"Centre",
    "sg:tags":[
        "metallurgy",
        "metalworking",
        "processing"
    ],
    "wof:name":"Affut 41",
    "wof:placetype":"venue"
},
  "geometry": {"coordinates":[0.97243,47.418777],"type":"Point"}
}