{
  "type": "Feature",
  "properties": {
    "addr:full":"5 Chemin Jean Marie Vianney 69130 Ecully Rhone-Alpes 69130",
    "addr:housenumber":"5",
    "addr:postcode":"69130;69130",
    "addr:street":"Chemin Jean Marie Vianney;Rhone-Alpes",
    "iso:country":"FR",
    "sg:address":"5 Chemin Jean Marie Vianney 69130 Ecully",
    "sg:classifiers":[
        {
            "category":"Government",
            "subcategory":"Department Of Motor Vehicles",
            "type":"Public Place"
        }
    ],
    "sg:phone":"+33 4 72 18 77 32",
    "sg:postcode":"69130",
    "sg:province":"Rhone-Alpes",
    "sg:tags":[
        "equipment",
        "industrial",
        "transport",
        "motor-cars"
    ],
    "wof:name":"Automobiles Citroen",
    "wof:placetype":"venue"
},
  "geometry": {"coordinates":[4.782301,45.787998],"type":"Point"}
}