{
  "type": "Feature",
  "properties": {
    "addr:full":"Les Bas Banquets Rte D\u00e9partemental 84300 Cavaillon Languedoc-Roussillon",
    "addr:postcode":"84300",
    "addr:street":"Rte De\u0301Partemental",
    "iso:country":"FR",
    "sg:address":"Les Bas Banquets Rte D\u00e9partemental 84300 Cavaillon",
    "sg:classifiers":[
        {
            "category":"Building & Trades",
            "subcategory":"Construction",
            "type":"Services"
        }
    ],
    "sg:phone":"+33 4 90 06 32 32",
    "sg:province":"Languedoc-Roussillon",
    "sg:tags":[
        "work",
        "public"
    ],
    "wof:name":"Sobeca",
    "wof:placetype":"venue"
},
  "geometry": {"coordinates":[5.039415,43.837685],"type":"Point"}
}