{
  "type": "Feature",
  "properties": {
    "iso:country":"FR",
    "sg:address":"4, Rue Berchotti\u00e8re, 37170 Chambray l\u00e8s Tours",
    "sg:city":"Chambray-l\u00e8s-Tours",
    "sg:orig_category":"Non-Classified Establishments",
    "sg:phone":"+33 2 47 28 50 00",
    "sg:postcode":"37170",
    "sg:province":"Centre",
    "wof:name":"T.c.p.e. S.a.r.l. - Technique Chauffage Plomberie Electricit\u00e9",
    "wof:placetype":"venue"
},
  "geometry": {"coordinates":[0.707437,47.334499],"type":"Point"}
}