{
  "type": "Feature",
  "properties": {
    "addr:full":"RN 7 - Espace Coq - La Petite Calade Puyricard Midi Pyr\u00e9n\u00e9es 13540",
    "addr:postcode":"13540",
    "addr:street":"Rn 7 Espace Coq La",
    "iso:country":"FR",
    "sg:address":"RN 7 - Espace Coq - La Petite Calade",
    "sg:city":"Puyricard",
    "sg:orig_category":"Non-Classified Establishments",
    "sg:phone":"+33 4 42 96 57 05",
    "sg:postcode":"13540",
    "sg:province":"Midi Pyr\u00e9n\u00e9es",
    "wof:name":"Mecanic'air S.a.r.l.",
    "wof:placetype":"venue"
},
  "geometry": {"coordinates":[5.421925,43.582729],"type":"Point"}
}