{
  "type": "Feature",
  "properties": {
    "addr:full":"14 Rue St Louis 55100 Verdun Lorraine 55100",
    "addr:housenumber":"14",
    "addr:postcode":"55100;55100",
    "addr:street":"Rue St Louis",
    "iso:country":"FR",
    "sg:address":"14 Rue St Louis 55100 Verdun",
    "sg:classifiers":[
        {
            "category":"Building & Trades",
            "subcategory":"Construction",
            "type":"Services"
        }
    ],
    "sg:phone":"+33 3 87 66 73 11",
    "sg:postcode":"55100",
    "sg:province":"Lorraine",
    "sg:tags":[
        "work",
        "public"
    ],
    "wof:name":"Demathieu Et Bard",
    "wof:placetype":"venue"
},
  "geometry": {"coordinates":[5.382747,49.157333],"type":"Point"}
}