{
  "type": "Feature",
  "properties": {
    "iso:country":"FR",
    "sg:address":"Rue de la Technique - ZI de Vic",
    "sg:city":"Castanet Tolosan",
    "sg:orig_category":"Non-Classified Establishments",
    "sg:phone":"+33 5 61 81 33 33",
    "sg:postcode":"31320",
    "sg:province":"Midi Pyr\u00e9n\u00e9es",
    "wof:name":"Elaparc S.a.",
    "wof:placetype":"venue"
},
  "geometry": {"coordinates":[1.452547,43.482239],"type":"Point"}
}