{
  "type": "Feature",
  "properties": {
    "addr:full":"69, Rte Nationale, 57580 Herny Lorraine",
    "addr:housenumber":"69",
    "addr:postcode":"57580",
    "addr:street":"Rte Nationale",
    "iso:country":"FR",
    "sg:address":"69, Rte Nationale, 57580 Herny",
    "sg:orig_category":"Non-Classified Establishments",
    "sg:phone":"+33 3 87 01 02 15",
    "sg:province":"Lorraine",
    "wof:name":"Lapointe Royer Marie-th\u00e9r\u00e8se",
    "wof:placetype":"venue"
},
  "geometry": {"coordinates":[6.392282,49.013313],"type":"Point"}
}