{
  "type": "Feature",
  "properties": {
    "addr:full":"27, Rue Joubert, 75009 Paris Ile de France",
    "addr:housenumber":"27",
    "addr:postcode":"75009",
    "addr:street":"Rue Joubert",
    "iso:country":"FR",
    "sg:address":"27, Rue Joubert, 75009 Paris",
    "sg:orig_category":"Unclassifiable Establishments",
    "sg:phone":"+33 1 42 80 65 00",
    "sg:province":"Ile de France",
    "wof:name":"Cr\u00e9ation Et Communication S.a.r.l.",
    "wof:placetype":"venue"
},
  "geometry": {"coordinates":[2.33059,48.874512],"type":"Point"}
}