{
  "type": "Feature",
  "properties": {
    "iso:country":"FR",
    "sg:address":"43, Rue du Vieux Ch\u00eane, 38240 Meylan",
    "sg:orig_category":"Non-Classified Establishments",
    "sg:phone":"+33 4 76 41 85 05",
    "sg:postcode":"38240",
    "sg:province":"Rhone-Alpes",
    "wof:name":"Alsyd S.a.",
    "wof:placetype":"venue"
},
  "geometry": {"coordinates":[5.79624,45.208054],"type":"Point"}
}