{
  "type": "Feature",
  "properties": {
    "addr:full":"3, Av. de Gennes - Parc d'Activit\u00e9 les Ajeux, 72400 La Fert\u00e9 Bernard Pays de Loire 72400",
    "addr:postcode":"72400;72400",
    "addr:street":"Av. De Gennes Parc D'Activite \u0301 Les Ajeux;Bernard",
    "iso:country":"FR",
    "sg:address":"3, Av. de Gennes - Parc d'Activit\u00e9 les Ajeux, 72400 La Fert\u00e9 Bernard",
    "sg:orig_category":"Non-Classified Establishments",
    "sg:phone":"+33 2 43 93 66 66",
    "sg:postcode":"72400",
    "sg:province":"Pays de Loire",
    "wof:name":"D.p. Tech S.a.",
    "wof:placetype":"venue"
},
  "geometry": {"coordinates":[0.63723,48.18829],"type":"Point"}
}