{
  "type": "Feature",
  "properties": {
    "iso:country":"FR",
    "sg:address":"1 A",
    "sg:city":"Ar\u00e8ne; Cassis",
    "sg:classifiers":[
        {
            "category":"Banks & Credit Unions",
            "subcategory":"Bank",
            "type":"Services"
        }
    ],
    "sg:phone":"+33 3342018848",
    "sg:province":"Aquitaine",
    "wof:name":"Cr\u00e9dit Mutuel M\u00e9diterran\u00e9en",
    "wof:placetype":"venue"
},
  "geometry": {"coordinates":[5.539545,43.213894],"type":"Point"}
}