{
  "type": "Feature",
  "properties": {
    "iso:country":"FR",
    "sg:address":"B.P. 1062, 76260 Eu^^15, Place Saint Jacques, 76260 Eu",
    "sg:orig_category":"Non-Classified Establishments",
    "sg:phone":"+33 2 35 86 07 11",
    "sg:province":"Haute Normandie",
    "wof:name":"I.m.e. S.a.r.l. - Imprimerie Du Messager Eudois",
    "wof:placetype":"venue"
},
  "geometry": {"coordinates":[1.42007,50.049061],"type":"Point"}
}