{
  "type": "Feature",
  "properties": {
    "addr:full":"37, Rue Jean Giraudoux, 75116 Paris Poitou-Charentes",
    "addr:housenumber":"37",
    "addr:postcode":"75116",
    "addr:street":"Rue Jean Giraudoux",
    "iso:country":"FR",
    "sg:address":"37, Rue Jean Giraudoux, 75116 Paris",
    "sg:orig_category":"Non-Classified Establishments",
    "sg:phone":"+33 1 45 01 93 38",
    "sg:province":"Poitou-Charentes",
    "wof:name":"Cyprus Airways",
    "wof:placetype":"venue"
},
  "geometry": {"coordinates":[2.294241,48.870834],"type":"Point"}
}