{
  "type": "Feature",
  "properties": {
    "iso:country":"FR",
    "sg:address":"ZA Ir\u00e8ne Joliot-Curie 93270 Sevran",
    "sg:classifiers":[
        {
            "category":"Utilities",
            "subcategory":"Recycling",
            "type":"Services"
        }
    ],
    "sg:phone":"+33 1 49 36 13 94",
    "sg:province":"Ile de France",
    "sg:tags":[
        "rubber",
        "processing"
    ],
    "wof:name":"Etm Sarl",
    "wof:placetype":"venue"
},
  "geometry": {"coordinates":[2.530945,48.938911],"type":"Point"}
}