{
  "type": "Feature",
  "properties": {
    "addr:full":"67 bis, Rue de la Gare, 67240 Oberhoffen sur Moder Bischwiller Alsace 67240",
    "addr:housenumber":"67 bis",
    "addr:postcode":"67240;67240",
    "addr:street":"Rue De La Gare",
    "iso:country":"FR",
    "sg:address":"67 bis, Rue de la Gare, 67240 Oberhoffen sur Moder",
    "sg:city":"Bischwiller",
    "sg:orig_category":"Non-Classified Establishments",
    "sg:phone":"+33 3 88 06 41 00",
    "sg:postcode":"67240",
    "sg:province":"Alsace",
    "wof:name":"Ad Hoc Distribution S.a.r.l.",
    "wof:placetype":"venue"
},
  "geometry": {"coordinates":[7.853456,48.788754],"type":"Point"}
}