{
  "type": "Feature",
  "properties": {
    "addr:full":"176, Rue Vouachalons - B\u00e2timent Stendhal, 54200 Toul Lorraine 54200",
    "addr:housenumber":"176",
    "addr:postcode":"54200;54200",
    "addr:street":"Rue Vouachalons",
    "iso:country":"FR",
    "sg:address":"176, Rue Vouachalons - B\u00e2timent Stendhal, 54200 Toul",
    "sg:orig_category":"Non-Classified Establishments",
    "sg:phone":"+33 3 83 43 24 97",
    "sg:postcode":"54200",
    "sg:province":"Lorraine",
    "wof:name":"C.g.s.t. Save S.a.s. - Compagnie Gazi\u00e8re Service Technique Save",
    "wof:placetype":"venue"
},
  "geometry": {"coordinates":[5.896054,48.688389],"type":"Point"}
}