{
  "type": "Feature",
  "properties": {
    "addr:full":"2 rue Buffon lot n\u00b0 104 76600 Le Havre Haute Normandie 76600",
    "addr:housenumber":"2",
    "addr:postcode":"76600;76600",
    "addr:street":"Rue Buffon",
    "iso:country":"FR",
    "sg:address":"2 rue Buffon lot n\u00b0 104 76600 Le Havre",
    "sg:orig_category":"Fittings, Valves",
    "sg:phone":"+33 2 35 24 46 48",
    "sg:postcode":"76600",
    "sg:province":"Haute Normandie",
    "wof:name":"M.d.n. Sarl",
    "wof:placetype":"venue"
},
  "geometry": {"coordinates":[0.101405,49.493511],"type":"Point"}
}