{
  "type": "Feature",
  "properties": {
    "addr:full":"16, Av. de la Haute Voie, 41310 Huisseau en Beauce Ambloy Centre 41310",
    "addr:postcode":"41310;41310",
    "addr:street":"16 Av. De La Haute Voie",
    "iso:country":"FR",
    "sg:address":"16, Av. de la Haute Voie, 41310 Huisseau en Beauce",
    "sg:city":"Ambloy",
    "sg:orig_category":"Non-Classified Establishments",
    "sg:phone":"+33 2 54 82 81 31",
    "sg:postcode":"41310",
    "sg:province":"Centre",
    "wof:name":"S.v.d. S.a.r.l. - Soci\u00e9t\u00e9 Verdier Diguet",
    "wof:placetype":"venue"
},
  "geometry": {"coordinates":[1.012081,47.716099],"type":"Point"}
}