{
  "type": "Feature",
  "properties": {
    "iso:country":"FR",
    "sg:address":"22, Rue de la Bo\u00e9tie, 75008 Paris",
    "sg:orig_category":"Unclassifiable Establishments",
    "sg:phone":"+33 1 47 42 33 16",
    "sg:province":"Ile de France",
    "wof:name":"B.u.t.e.c. Bureau Technique D'etudes Et D'entreprise Butec Ingineering",
    "wof:placetype":"venue"
},
  "geometry": {"coordinates":[2.316391,48.874142],"type":"Point"}
}