{
  "type": "Feature",
  "properties": {
    "addr:full":"Rte d'Agen - Les Abattoirs Auch Midi Pyr\u00e9n\u00e9es 32810",
    "addr:postcode":"32810",
    "addr:street":"Rte D'Agen Les Abattoirs",
    "iso:country":"FR",
    "sg:address":"Rte d'Agen - Les Abattoirs",
    "sg:city":"Auch",
    "sg:orig_category":"Unclassifiable Establishments",
    "sg:phone":"+33 5 62 60 06 82",
    "sg:postcode":"32810",
    "sg:province":"Midi Pyr\u00e9n\u00e9es",
    "wof:name":"Vegarom International S.a.r.l.",
    "wof:placetype":"venue"
},
  "geometry": {"coordinates":[0.595975,43.654484],"type":"Point"}
}