{
  "type": "Feature",
  "properties": {
    "addr:full":"Rte de Nantes Cholet Pays de Loire 49300",
    "addr:postcode":"49300",
    "addr:street":"Rte De Nantes",
    "iso:country":"FR",
    "sg:address":"Rte de Nantes",
    "sg:city":"Cholet",
    "sg:orig_category":"Non-Classified Establishments",
    "sg:phone":"+33 2 41 62 46 34",
    "sg:postcode":"49300",
    "sg:province":"Pays de Loire",
    "wof:name":"P.r.l. S.a.r.l.",
    "wof:placetype":"venue"
},
  "geometry": {"coordinates":[-0.892909,47.060936],"type":"Point"}
}