{
  "type": "Feature",
  "properties": {
    "addr:full":"29 Place Du Breuil 43000 Le Puy En Velay Le Puy-en-Velay Auvergne 43000",
    "addr:housenumber":"29",
    "addr:postcode":"43000;43000",
    "addr:street":"Place Du Breuil;Puy En Velay",
    "iso:country":"FR",
    "sg:address":"29 Place Du Breuil 43000 Le Puy En Velay",
    "sg:city":"Le Puy-en-Velay",
    "sg:classifiers":[
        {
            "category":"Health Services",
            "subcategory":"Optometrist",
            "type":"Services"
        }
    ],
    "sg:phone":"+33 4 71 09 02 82",
    "sg:postcode":"43000",
    "sg:province":"Auvergne",
    "sg:tags":[
        "instrument",
        "optical",
        "-",
        "precision",
        "equipment"
    ],
    "wof:name":"Martel Optique Sa",
    "wof:placetype":"venue"
},
  "geometry": {"coordinates":[3.88421,45.042145],"type":"Point"}
}