{
  "type": "Feature",
  "properties": {
    "addr:full":"8 Chem De La Cav\u00e9e 27410 Ajou Haute Normandie 27410",
    "addr:housenumber":"8",
    "addr:postcode":"27410;27410",
    "addr:street":"Chem De La Cave\u0301E;Haute Normandie",
    "iso:country":"FR",
    "sg:address":"8 Chem De La Cav\u00e9e 27410 Ajou",
    "sg:classifiers":[
        {
            "category":"Manufacturing",
            "subcategory":"Leather Goods",
            "type":"Manufacturing & Wholesale Goods"
        }
    ],
    "sg:phone":"+33 2 32 30 76 59",
    "sg:postcode":"27410",
    "sg:province":"Haute Normandie",
    "sg:tags":[
        "shoe"
    ],
    "wof:name":"Carr\u00c9 Royal Sarl",
    "wof:placetype":"venue"
},
  "geometry": {"coordinates":[0.782417,48.979656],"type":"Point"}
}