{
  "type": "Feature",
  "properties": {
    "addr:full":"5, Bd Pierre Lecoq - La Novath\u00e8que, 49300 Cholet Pays de Loire",
    "addr:housenumber":"5",
    "addr:postcode":"49300",
    "addr:street":"Bd Pierre Lecoq La Novathe\u0300Que",
    "iso:country":"FR",
    "sg:address":"5, Bd Pierre Lecoq - La Novath\u00e8que, 49300 Cholet",
    "sg:orig_category":"Unclassifiable Establishments",
    "sg:phone":"+33 2 41 58 50 50",
    "sg:province":"Pays de Loire",
    "wof:name":"Seroux Jean-fran\u00e7ois",
    "wof:placetype":"venue"
},
  "geometry": {"coordinates":[-0.892689,46.99659],"type":"Point"}
}