{
  "type": "Feature",
  "properties": {
    "addr:full":"3, All\u00e9e de Longchamps, 54500 Vandoeuvre l\u00e8s Nancy Lorraine",
    "addr:housenumber":"3",
    "addr:postcode":"54500",
    "addr:street":"Alle\u0301E De Longchamps",
    "iso:country":"FR",
    "sg:address":"3, All\u00e9e de Longchamps, 54500 Vandoeuvre l\u00e8s Nancy",
    "sg:orig_category":"Non-Classified Establishments",
    "sg:phone":"+33 3 83 44 25 25",
    "sg:province":"Lorraine",
    "wof:name":"T\u00e9novis S.a.",
    "wof:placetype":"venue"
},
  "geometry": {"coordinates":[6.137305,48.65443],"type":"Point"}
}