{
  "type": "Feature",
  "properties": {
    "addr:full":"Ld Prades Rocade De Monteil 47240 Lafox Lafox Aquitaine 47240",
    "addr:postcode":"47240;47240",
    "addr:street":"Ld;Monteil",
    "iso:country":"FR",
    "sg:address":"Ld Prades Rocade De Monteil 47240 Lafox",
    "sg:city":"Lafox",
    "sg:classifiers":[
        {
            "category":"Manufacturing",
            "subcategory":"Tools & Machinery",
            "type":"Manufacturing & Wholesale Goods"
        }
    ],
    "sg:phone":"+33 5 53 68 54 44",
    "sg:postcode":"47240",
    "sg:province":"Aquitaine",
    "sg:tags":[
        "metallurgy",
        "metalworking"
    ],
    "wof:name":"La Clouterie Fran\u00c7aise",
    "wof:placetype":"venue"
},
  "geometry": {"coordinates":[0.71531,44.163422],"type":"Point"}
}