{
  "type": "Feature",
  "properties": {
    "addr:full":"72 Route Du Palais 87000 Limoges Limousin 87000",
    "addr:housenumber":"72",
    "addr:postcode":"87000;87000",
    "addr:street":"Route Du Palais",
    "iso:country":"FR",
    "sg:address":"72 Route Du Palais 87000 Limoges",
    "sg:classifiers":[
        {
            "category":"Government",
            "subcategory":"Department Of Motor Vehicles",
            "type":"Public Place"
        }
    ],
    "sg:phone":"+33 5 55 04 93 11",
    "sg:postcode":"87000",
    "sg:province":"Limousin",
    "sg:tags":[
        "equipment",
        "industrial",
        "transport",
        "motor-cars"
    ],
    "wof:name":"Renault Truck Sa",
    "wof:placetype":"venue"
},
  "geometry": {"coordinates":[1.291978,45.846275],"type":"Point"}
}