{
  "type": "Feature",
  "properties": {
    "addr:full":"R Sorbiers 61120 Vimoutiers Vimoutiers Basse Normandie 61120",
    "addr:postcode":"61120;61120",
    "addr:street":"R Sorbiers",
    "iso:country":"FR",
    "sg:address":"R Sorbiers 61120 Vimoutiers",
    "sg:city":"Vimoutiers",
    "sg:classifiers":[
        {
            "category":"Shopping",
            "subcategory":"Bicycles & Sporting Goods",
            "type":"Retail Goods"
        }
    ],
    "sg:phone":"+33 2 33 39 31 73",
    "sg:postcode":"61120",
    "sg:province":"Basse Normandie",
    "sg:tags":[
        "product",
        "sport",
        "miscellaneous"
    ],
    "wof:name":"Cotenor Confection Technique De Normandie Sa",
    "wof:placetype":"venue"
},
  "geometry": {"coordinates":[0.197385,48.934353],"type":"Point"}
}