{
  "type": "Feature",
  "properties": {
    "iso:country":"FR",
    "sg:address":"82, Rte de Paris, 31790 Saint Jory",
    "sg:orig_category":"Unclassifiable Establishments",
    "sg:phone":"+33 5 61 09 03 44",
    "sg:province":"Midi Pyr\u00e9n\u00e9es",
    "wof:name":"S.a.m.i. S.a. - Soci\u00e9t\u00e9 Anichoise Maintenance Industrielle",
    "wof:placetype":"venue"
},
  "geometry": {"coordinates":[1.379634,43.727558],"type":"Point"}
}