{
  "type": "Feature",
  "properties": {
    "iso:country":"FR",
    "sg:address":"Rue Octave Virgilly",
    "sg:city":"Toulon",
    "sg:orig_category":"Non-Classified Establishments",
    "sg:phone":"+33 4 94 03 87 17",
    "sg:postcode":"83100",
    "sg:province":"Champagne",
    "wof:name":"R.m.t.t. S.a. - R\u00e9gie Mixte Des Transports Toulonnais",
    "wof:placetype":"venue"
},
  "geometry": {"coordinates":[5.965634,43.12817],"type":"Point"}
}