{
  "type": "Feature",
  "properties": {
    "addr:full":"12 Zone Emploi Gate Grenier 16730 Fl\u00e9ac Poitou-Charentes",
    "addr:housenumber":"12",
    "addr:postcode":"16730",
    "addr:street":"Zone Emploi Gate Grenier",
    "iso:country":"FR",
    "sg:address":"12 Zone Emploi Gate Grenier 16730 Fl\u00e9ac",
    "sg:classifiers":[
        {
            "category":"Manufacturing",
            "subcategory":"Printing",
            "type":"Manufacturing & Wholesale Goods"
        }
    ],
    "sg:phone":"+33 5 45 91 21 21",
    "sg:province":"Poitou-Charentes",
    "sg:tags":[
        "publishing"
    ],
    "wof:name":"Zag Incorpor Sa",
    "wof:placetype":"venue"
},
  "geometry": {"coordinates":[0.087647,45.675678],"type":"Point"}
}