{
  "type": "Feature",
  "properties": {
    "addr:full":"140, Av. Saint Antoine, 13015 Marseille Poitou-Charentes",
    "addr:postcode":"13015",
    "addr:street":"140 Av. Saint Antoine",
    "iso:country":"FR",
    "sg:address":"140, Av. Saint Antoine, 13015 Marseille",
    "sg:orig_category":"Non-Classified Establishments",
    "sg:phone":"+33 4 91 09 05 11",
    "sg:province":"Poitou-Charentes",
    "wof:name":"Lenient Samantha Jane",
    "wof:placetype":"venue"
},
  "geometry": {"coordinates":[5.356155,43.371449],"type":"Point"}
}