{
  "type": "Feature",
  "properties": {
    "iso:country":"FR",
    "sg:address":"Chemin de la Croix Dor\u00e9e",
    "sg:city":"L\u00e9cousse",
    "sg:orig_category":"Unclassifiable Establishments",
    "sg:phone":"+33 2 99 99 21 96",
    "sg:postcode":"35133",
    "sg:province":"Bretagne",
    "wof:name":"Atlantem S.a.",
    "wof:placetype":"venue"
},
  "geometry": {"coordinates":[-1.211513,48.372116],"type":"Point"}
}