{
  "type": "Feature",
  "properties": {
    "iso:country":"FR",
    "sg:address":"1, Rue Marcel Doret, 31700 Blagnac",
    "sg:orig_category":"Unclassifiable Establishments",
    "sg:phone":"+33 5 62 12 15 00",
    "sg:province":"Midi Pyr\u00e9n\u00e9es",
    "wof:name":"Honeywell A\u00e9rospace S.a.",
    "wof:placetype":"venue"
},
  "geometry": {"coordinates":[1.37822,43.633316],"type":"Point"}
}