{
  "type": "Feature",
  "properties": {
    "iso:country":"FR",
    "sg:address":"24 Rue Du G\u00e9n\u00e9ral Leclerc 91420 Morangis",
    "sg:classifiers":[
        {
            "category":"Wholesale",
            "subcategory":"Meat",
            "type":"Manufacturing & Wholesale Goods"
        }
    ],
    "sg:phone":"+33 1 69 09 11 55",
    "sg:postcode":"91420",
    "sg:province":"Ile de France",
    "sg:tags":[
        "food",
        "cooked",
        "product",
        "related"
    ],
    "wof:name":"Boiton Ravain",
    "wof:placetype":"venue"
},
  "geometry": {"coordinates":[2.329704,48.707504],"type":"Point"}
}