{
  "type": "Feature",
  "properties": {
    "addr:full":"21 Rue Laffitte, 75009 Paris, Dept 75 Ile de France 75009",
    "addr:housenumber":"21;75",
    "addr:postcode":"75009;75009",
    "addr:street":"Rue Laffitte;Ile De France",
    "iso:country":"FR",
    "sg:address":"21 Rue Laffitte, 75009 Paris, Dept 75",
    "sg:classifiers":[
        {
            "category":"Banks & Credit Unions",
            "subcategory":"Bank",
            "type":"Services"
        }
    ],
    "sg:postcode":"75009",
    "sg:province":"Ile de France",
    "wof:name":"Barclays Bank Sa",
    "wof:placetype":"venue"
},
  "geometry": {"coordinates":[2.337554,48.873337],"type":"Point"}
}