{
  "type": "Feature",
  "properties": {
    "addr:full":"12 Rue Du Lieu Dieu 80770 Beauchamps Picardie 80770",
    "addr:housenumber":"12",
    "addr:postcode":"80770;80770",
    "addr:street":"Rue Du Lieu Dieu",
    "iso:country":"FR",
    "sg:address":"12 Rue Du Lieu Dieu 80770 Beauchamps",
    "sg:classifiers":[
        {
            "category":"Manufacturing",
            "subcategory":"Chemicals & Compounds",
            "type":"Manufacturing & Wholesale Goods"
        }
    ],
    "sg:phone":"+33 3 22 60 25 25",
    "sg:postcode":"80770",
    "sg:province":"Picardie",
    "sg:tags":[
        "pharmaceutical",
        "energy",
        "chemistry",
        "-",
        "by-product"
    ],
    "wof:name":"Dms",
    "wof:placetype":"venue"
},
  "geometry": {"coordinates":[1.519376,50.004623],"type":"Point"}
}