{
  "type": "Feature",
  "properties": {
    "addr:full":"50 Avenue Albert Beaufils St Fargeau Ponthierry Ile de France 77310",
    "addr:housenumber":"50",
    "addr:postcode":"77310",
    "addr:street":"Avenue Albert Beaufils St",
    "iso:country":"FR",
    "sg:address":"50 Avenue Albert Beaufils",
    "sg:city":"St Fargeau Ponthierry",
    "sg:classifiers":[
        {
            "category":"Banks & Credit Unions",
            "subcategory":"Financial Services",
            "type":"Services"
        }
    ],
    "sg:phone":"+33 1 64 89 50 05",
    "sg:postcode":"77310",
    "sg:province":"Ile de France",
    "sg:tags":[
        "banking",
        "finance",
        "insurance"
    ],
    "wof:name":"Caisse Regionale De Credit Agricole Mutuel De La Brie",
    "wof:placetype":"venue"
},
  "geometry": {"coordinates":[2.544106,48.530197],"type":"Point"}
}