{
  "type": "Feature",
  "properties": {
    "addr:full":"55 Rue Beaucaire 30510 G\u00e9n\u00e9rac Languedoc-Roussillon",
    "addr:housenumber":"55",
    "addr:postcode":"30510",
    "addr:street":"Rue Beaucaire",
    "iso:country":"FR",
    "sg:address":"55 Rue Beaucaire 30510 G\u00e9n\u00e9rac",
    "sg:classifiers":[
        {
            "category":"Manufacturing",
            "subcategory":"Paper Products",
            "type":"Manufacturing & Wholesale Goods"
        }
    ],
    "sg:phone":"+33 4 66 01 76 00",
    "sg:province":"Languedoc-Roussillon",
    "sg:tags":[
        "packaging",
        "material",
        "-",
        "cardboard"
    ],
    "wof:name":"Molliere Et Cannoge Draussin Succ.sarl",
    "wof:placetype":"venue"
},
  "geometry": {"coordinates":[4.357422,43.729156],"type":"Point"}
}