{
  "type": "Feature",
  "properties": {
    "iso:country":"FR",
    "sg:address":"B.P. 4244, 59378 Dunkerque C\u00e9dex 1^^30, Rue de l'Hermitte - Centre Tertiaire les 3 Ponts, 59140 Dunk",
    "sg:orig_category":"Non-Classified Establishments",
    "sg:phone":"+33 3 28 24 41 41",
    "sg:province":"Nord Pas-de-Calais",
    "wof:name":"United Arab Agencies France S.a.",
    "wof:placetype":"venue"
},
  "geometry": {"coordinates":[2.383479,51.036842],"type":"Point"}
}