{
  "type": "Feature",
  "properties": {
    "addr:full":"B.P. 60, 78185 Saint Quentin en Yvelines C\u00e9dex^^3, All\u00e9e des Aulnes - ZA du Buisson de la Couldre, 7 \u00cele-de-France",
    "addr:housenumber":"7",
    "addr:postcode":"78185",
    "addr:street":"B.P. 60;Alle\u0301E Des Aulnes Za Du Buisson De La Couldre",
    "iso:country":"FR",
    "sg:address":"B.P. 60, 78185 Saint Quentin en Yvelines C\u00e9dex^^3, All\u00e9e des Aulnes - ZA du Buisson de la Couldre, 7",
    "sg:orig_category":"Non-Classified Establishments",
    "sg:phone":"+33 1 30 51 66 88",
    "sg:province":"\u00cele-de-France",
    "wof:name":"Via Line S.a.r.l.",
    "wof:placetype":"venue"
},
  "geometry": {"coordinates":[2.025652,48.774487],"type":"Point"}
}