{
  "type": "Feature",
  "properties": {
    "addr:full":"B.P. 28, 77792 Nemours C\u00e9dex^^19, Rue du Chatelet, 77140 Nemours Ile de France 77140",
    "addr:postcode":"77792;77140;77140",
    "addr:street":"B.P. 28;Rue Du Chatelet;Ile De France",
    "iso:country":"FR",
    "sg:address":"B.P. 28, 77792 Nemours C\u00e9dex^^19, Rue du Chatelet, 77140 Nemours",
    "sg:orig_category":"Non-Classified Establishments",
    "sg:phone":"+33 1 64 28 00 89",
    "sg:postcode":"77140",
    "sg:province":"Ile de France",
    "wof:name":"E.c.g.m. S.a.",
    "wof:placetype":"venue"
},
  "geometry": {"coordinates":[2.69474,48.2672],"type":"Point"}
}