{
  "type": "Feature",
  "properties": {
    "iso:country":"FR",
    "sg:address":"142 Rue Destilleuls 60530 Ercuis",
    "sg:classifiers":[
        {
            "category":"Manufacturing",
            "subcategory":"Jewelry",
            "type":"Manufacturing & Wholesale Goods"
        }
    ],
    "sg:phone":"+33 3 44 26 54 92",
    "sg:postcode":"60530",
    "sg:province":"Picardie",
    "sg:tags":[
        "product",
        "miscellaneous",
        "jewellery"
    ],
    "wof:name":"Orfevrerie Ercuis",
    "wof:placetype":"venue"
},
  "geometry": {"coordinates":[2.28664,49.177341],"type":"Point"}
}