{
  "type": "Feature",
  "properties": {
    "addr:full":"142 Rue Destilleuls 60530 Ercuis Picardie 60530",
    "addr:housenumber":"142",
    "addr:postcode":"60530;60530",
    "addr:street":"Rue Destilleuls",
    "iso:country":"FR",
    "sg:address":"142 Rue Destilleuls 60530 Ercuis",
    "sg:classifiers":[
        {
            "category":"Manufacturing",
            "subcategory":"Jewelry",
            "type":"Manufacturing & Wholesale Goods"
        }
    ],
    "sg:phone":"+33 3 44 26 54 92",
    "sg:postcode":"60530",
    "sg:province":"Picardie",
    "sg:tags":[
        "product",
        "miscellaneous",
        "jewellery"
    ],
    "wof:name":"Orfevrerie Ercuis",
    "wof:placetype":"venue"
},
  "geometry": {"coordinates":[2.28664,49.177341],"type":"Point"}
}