{
  "type": "Feature",
  "properties": {
    "iso:country":"FR",
    "sg:address":"14 Rue De La P\u00e9pini\u00e8re 75008 Paris",
    "sg:classifiers":[
        {
            "category":"Communications",
            "type":"Services"
        }
    ],
    "sg:phone":"+33 1 44 90 88 70",
    "sg:postcode":"75008",
    "sg:province":"Ile de France",
    "sg:tags":[
        "advice",
        "interpretation",
        "translation",
        "business"
    ],
    "wof:name":"Elys\u00c9es Traduction Sarl",
    "wof:placetype":"venue"
},
  "geometry": {"coordinates":[2.322094,48.87516],"type":"Point"}
}