{
  "type": "Feature",
  "properties": {
    "iso:country":"FR",
    "sg:address":"845 R Pic De Bertagne BP 110 13420 Gemenos",
    "sg:classifiers":[
        {
            "category":"Manufacturing",
            "subcategory":"Rubber & Plastics",
            "type":"Manufacturing & Wholesale Goods"
        }
    ],
    "sg:phone":"+33 4 42 32 70 42",
    "sg:province":"Auvergne",
    "wof:name":"Plasti De France",
    "wof:placetype":"venue"
},
  "geometry": {"coordinates":[5.614684,43.281914],"type":"Point"}
}