{
  "type": "Feature",
  "properties": {
    "addr:full":"2 Impasse Des Vernes Zone Artisanale 71370 St Germain Du Plain Abergement-Sainte-Colombe Bourgogne 71370",
    "addr:housenumber":"2",
    "addr:postcode":"71370;71370",
    "addr:street":"Impasse Des Vernes Zone Artisanale;Plain;Bourgogne",
    "iso:country":"FR",
    "sg:address":"2 Impasse Des Vernes Zone Artisanale 71370 St Germain Du Plain",
    "sg:city":"Abergement-Sainte-Colombe",
    "sg:classifiers":[
        {
            "category":"Wholesale",
            "subcategory":"Machinery & Supplies",
            "type":"Manufacturing & Wholesale Goods"
        }
    ],
    "sg:phone":"+33 3 85 47 37 80",
    "sg:postcode":"71370",
    "sg:province":"Bourgogne",
    "sg:tags":[
        "handling",
        "material",
        "-",
        "machine",
        "equipment",
        "engineering",
        "mechanical"
    ],
    "wof:name":"Comege Sas",
    "wof:placetype":"venue"
},
  "geometry": {"coordinates":[4.9812,46.652473],"type":"Point"}
}