{
  "type": "Feature",
  "properties": {
    "addr:full":"18 des Clayes; Villepreux; 78450 Ile de France 78450",
    "addr:housenumber":"18",
    "addr:postcode":"78450 ile;france 78450",
    "addr:street":"Des Clayes",
    "iso:country":"FR",
    "sg:address":"18",
    "sg:city":"des Clayes; Villepreux; 78450",
    "sg:classifiers":[
        {
            "category":"Banks & Credit Unions",
            "subcategory":"Bank",
            "type":"Services"
        }
    ],
    "sg:phone":"+33 3334624520",
    "sg:postcode":"78450",
    "sg:province":"Ile de France",
    "wof:name":"Banque Nationale De Paris",
    "wof:placetype":"venue"
},
  "geometry": {"coordinates":[1.999647,48.828045],"type":"Point"}
}