{
  "type": "Feature",
  "properties": {
    "addr:full":"60, Rue d'Ostwald, 67200 Strasbourg Strasbourg Alsace 67200",
    "addr:housenumber":"60",
    "addr:postcode":"67200;67200",
    "addr:street":"Rue D'Ostwald",
    "iso:country":"FR",
    "sg:address":"60, Rue d'Ostwald, 67200 Strasbourg",
    "sg:city":"Strasbourg",
    "sg:orig_category":"Unclassifiable Establishments",
    "sg:phone":"+33 3 88 30 13 13",
    "sg:postcode":"67200",
    "sg:province":"Alsace",
    "wof:name":"A.f. 2 Sonorisation Eclairage",
    "wof:placetype":"venue"
},
  "geometry": {"coordinates":[7.710494,48.562656],"type":"Point"}
}