{
  "type": "Feature",
  "properties": {
    "addr:full":"Ch\u00e2teau Poujeaux 33480 Moulis en M\u00e9doc Avensan Aquitaine 33480",
    "addr:postcode":"33480;33480",
    "iso:country":"FR",
    "sg:address":"Ch\u00e2teau Poujeaux 33480 Moulis en M\u00e9doc",
    "sg:city":"Avensan",
    "sg:orig_category":"Non-Classified Establishments",
    "sg:phone":"+33 5 56 58 02 96",
    "sg:postcode":"33480",
    "sg:province":"Aquitaine",
    "wof:name":"Jean Theil S.a.",
    "wof:placetype":"venue"
},
  "geometry": {"coordinates":[-0.886118,44.968613],"type":"Point"}
}