{
  "type": "Feature",
  "properties": {
    "addr:full":"B.P. 29, 92151 Suresnes C\u00e9dex^^154, Rue Gambetta, 92150 Suresnes Ile de France 92150",
    "addr:postcode":"92151;92150;ile;92150",
    "addr:street":"B.P. 29;Rue Gambetta;France",
    "iso:country":"FR",
    "sg:address":"B.P. 29, 92151 Suresnes C\u00e9dex^^154, Rue Gambetta, 92150 Suresnes",
    "sg:orig_category":"Non-Classified Establishments",
    "sg:phone":"+33 1 45 06 90 90",
    "sg:postcode":"92150",
    "sg:province":"Ile de France",
    "wof:name":"A.a.a. S.a.r.l. - Air Ambiance Assistance",
    "wof:placetype":"venue"
},
  "geometry": {"coordinates":[2.22677,48.867504],"type":"Point"}
}