{
  "type": "Feature",
  "properties": {
    "addr:full":"31 Bd Winston Churchill 76600 Le Havre Haute Normandie 76600",
    "addr:housenumber":"31",
    "addr:postcode":"76600;76600",
    "addr:street":"Bd Winston Churchill",
    "iso:country":"FR",
    "sg:address":"31 Bd Winston Churchill 76600 Le Havre",
    "sg:classifiers":[
        {
            "category":"Professional",
            "subcategory":"Business Services",
            "type":"Services"
        }
    ],
    "sg:phone":"+33 2 35 25 52 25",
    "sg:postcode":"76600",
    "sg:province":"Haute Normandie",
    "sg:tags":[
        "body",
        "advice"
    ],
    "wof:name":"Dresser Rand Sa",
    "wof:placetype":"venue"
},
  "geometry": {"coordinates":[0.140316,49.4949],"type":"Point"}
}