{
  "type": "Feature",
  "properties": {
    "addr:full":"375, Rue des Fr\u00e8res Lumi\u00e8re - La Garde , 83000 Toulon La Garde Rhone-Alpes 38520",
    "addr:housenumber":"375",
    "addr:postcode":"83000;38520",
    "addr:street":"Rue Des Fre\u0300Res Lumie\u0300Re La Garde;Rhone-Alpes",
    "iso:country":"FR",
    "sg:address":"375, Rue des Fr\u00e8res Lumi\u00e8re - La Garde , 83000 Toulon",
    "sg:city":"La Garde",
    "sg:orig_category":"Unclassifiable Establishments",
    "sg:phone":"+33 4 94 08 00 19",
    "sg:postcode":"38520",
    "sg:province":"Rhone-Alpes",
    "wof:name":"Senec S.a.",
    "wof:placetype":"venue"
},
  "geometry": {"coordinates":[5.930305,43.125324],"type":"Point"}
}