{
  "type": "Feature",
  "properties": {
    "addr:full":"257 Rue De Vaugirard 75015 Paris Ile de France 75015",
    "addr:housenumber":"257",
    "addr:postcode":"75015;75015",
    "addr:street":"Rue De Vaugirard",
    "iso:country":"FR",
    "sg:address":"257 Rue De Vaugirard 75015 Paris",
    "sg:classifiers":[
        {
            "category":"Travel",
            "subcategory":"Hotels & Motels",
            "type":"Entertainment"
        }
    ],
    "sg:phone":"+33 1 40 45 10 00",
    "sg:postcode":"75015",
    "sg:province":"Ile de France",
    "sg:tags":[
        "hotels",
        "business",
        "restaurant"
    ],
    "wof:name":"Novotel",
    "wof:placetype":"venue"
},
  "geometry": {"coordinates":[2.303696,48.840111],"type":"Point"}
}