{
  "type": "Feature",
  "properties": {
    "iso:country":"FR",
    "sg:address":"B.P. 33, 22360 Langueux^^8, Rue Ambroise Par\u00e9, 22360 Langueux",
    "sg:city":"Langueux",
    "sg:orig_category":"Non-Classified Establishments",
    "sg:phone":"+33 2 96 52 47 00",
    "sg:postcode":"22360",
    "sg:province":"Bretagne",
    "wof:name":"Centrib\u00e9ton S.a.",
    "wof:placetype":"venue"
},
  "geometry": {"coordinates":[-2.715357,48.494778],"type":"Point"}
}