{
  "type": "Feature",
  "properties": {
    "addr:full":"Av. Br\u00e9mer Haven Cherbourg Basse Normandie 50100",
    "addr:postcode":"50100",
    "addr:street":"Av. Bre\u0301Mer Haven;Basse",
    "iso:country":"FR",
    "sg:address":"Av. Br\u00e9mer Haven",
    "sg:city":"Cherbourg",
    "sg:orig_category":"Unclassifiable Establishments",
    "sg:phone":"+33 2 33 43 38 28",
    "sg:postcode":"50100",
    "sg:province":"Basse Normandie",
    "wof:name":"M.p.h. Cotentin S.a.",
    "wof:placetype":"venue"
},
  "geometry": {"coordinates":[-1.603579,49.630589],"type":"Point"}
}