{
  "type": "Feature",
  "properties": {
    "addr:full":"01290 CORMORANCHE SUR SAONE Rhone-Alpes 01290",
    "addr:postcode":"01290;01290",
    "addr:street":"Cormoranche",
    "iso:country":"FR",
    "sg:address":"01290 CORMORANCHE SUR SAONE",
    "sg:classifiers":[
        {
            "category":"Banks & Credit Unions",
            "subcategory":"Investment Brokerage",
            "type":"Services"
        }
    ],
    "sg:phone":"+33 3 85 36 22 58",
    "sg:postcode":"01290",
    "sg:province":"Rhone-Alpes",
    "sg:tags":[
        "wooden",
        "packaging"
    ],
    "wof:name":"Ets Rabuel Sa",
    "wof:placetype":"venue"
},
  "geometry": {"coordinates":[4.831727,46.240025],"type":"Point"}
}