{
  "type": "Feature",
  "properties": {
    "addr:full":"105 Rue Du Franclos 54714 Ludres Lorraine",
    "addr:housenumber":"105",
    "addr:postcode":"54714",
    "addr:street":"Rue Du Franclos",
    "iso:country":"FR",
    "sg:address":"105 Rue Du Franclos 54714 Ludres",
    "sg:classifiers":[
        {
            "category":"Autos & Motor Vehicles",
            "subcategory":"Automobile Sales",
            "type":"Retail Goods"
        }
    ],
    "sg:phone":"+33 3 83 26 28 28",
    "sg:province":"Lorraine",
    "sg:tags":[
        "equipment",
        "industrial",
        "transport"
    ],
    "wof:name":"Iveco Selvi",
    "wof:placetype":"venue"
},
  "geometry": {"coordinates":[6.178874,48.625187],"type":"Point"}
}