{
  "type": "Feature",
  "properties": {
    "iso:country":"FR",
    "sg:address":"1, All\u00e9e de Vincennes - Technop\u00f4le de Nancy-Bradois , 54500 Vandoeuvre l\u00e8s Nancy",
    "sg:orig_category":"Unclassifiable Establishments",
    "sg:phone":"+33 3 83 44 77 50",
    "sg:province":"Lorraine",
    "wof:name":"Cocirel S.a.r.l.",
    "wof:placetype":"venue"
},
  "geometry": {"coordinates":[6.172675,48.659737],"type":"Point"}
}