{
  "type": "Feature",
  "properties": {
    "addr:full":"B.P. 24, 38270 Beaurepaire C\u00e9dex^^1109, Rte de Jarcieu, 38270 Baurepaire Rhone-Alpes 38270",
    "addr:postcode":"38270;38270;38270",
    "addr:street":"B.P. 24;Rte De Jarcieu;Rhone-Alpes",
    "iso:country":"FR",
    "sg:address":"B.P. 24, 38270 Beaurepaire C\u00e9dex^^1109, Rte de Jarcieu, 38270 Baurepaire",
    "sg:orig_category":"Non-Classified Establishments",
    "sg:phone":"+33 4 74 84 63 77",
    "sg:postcode":"38270",
    "sg:province":"Rhone-Alpes",
    "wof:name":"Ritec S.a.r.l.",
    "wof:placetype":"venue"
},
  "geometry": {"coordinates":[5.11297,45.299309],"type":"Point"}
}