{
  "type": "Feature",
  "properties": {
    "iso:country":"FR",
    "sg:address":"109, Rue de Liverdun, 54390 Frouard",
    "sg:orig_category":"Unclassifiable Establishments",
    "sg:phone":"+33 3 83 49 05 86",
    "sg:province":"Lorraine",
    "wof:name":"Le Castel S.a.",
    "wof:placetype":"venue"
},
  "geometry": {"coordinates":[6.108346,48.757778],"type":"Point"}
}