{
  "type": "Feature",
  "properties": {
    "addr:full":"La Prade 03380 Quinssaines Quinssaines Auvergne 03380",
    "addr:postcode":"03380;03380",
    "addr:street":"La Prade",
    "iso:country":"FR",
    "sg:address":"La Prade 03380 Quinssaines",
    "sg:city":"Quinssaines",
    "sg:classifiers":[
        {
            "category":"Professional",
            "subcategory":"Engineering",
            "type":"Services"
        }
    ],
    "sg:phone":"+33 4 70 51 84 10",
    "sg:postcode":"03380",
    "sg:province":"Auvergne",
    "sg:tags":[
        "electric",
        "-",
        "component",
        "machine",
        "mechanical",
        "electronic"
    ],
    "wof:name":"Promatex S A",
    "wof:placetype":"venue"
},
  "geometry": {"coordinates":[2.509585,46.331734],"type":"Point"}
}