{
  "type": "Feature",
  "properties": {
    "addr:full":"Rue Jean Jacques Rousseau Residence Le Bearn Bat D4 Bill\u00e8re Aquitaine 64140",
    "addr:housenumber":"d4",
    "addr:postcode":"64140",
    "addr:street":"Rue Jean Jacques",
    "iso:country":"FR",
    "sg:address":"Rue Jean Jacques Rousseau Residence Le Bearn Bat D4",
    "sg:city":"Bill\u00e8re",
    "sg:classifiers":[
        {
            "category":"Banks & Credit Unions",
            "subcategory":"Financial Services",
            "type":"Services"
        }
    ],
    "sg:phone":"+33 5 59 40 24 82",
    "sg:postcode":"64140",
    "sg:province":"Aquitaine",
    "sg:tags":[
        "banking",
        "finance",
        "insurance"
    ],
    "wof:name":"Societe D'arbitrage Et D'expertise Technique Saretec (saretec)",
    "wof:placetype":"venue"
},
  "geometry": {"coordinates":[-0.382666,43.302395],"type":"Point"}
}