{
  "type": "Feature",
  "properties": {
    "iso:country":"FR",
    "sg:address":"151 Rue D'Uelzen",
    "sg:city":"Bois Guillaume",
    "sg:classifiers":[
        {
            "category":"Banks & Credit Unions",
            "subcategory":"Financial Services",
            "type":"Services"
        }
    ],
    "sg:phone":"+33 2 35 59 42 00",
    "sg:postcode":"76230",
    "sg:province":"Haute Normandie",
    "sg:tags":[
        "banking",
        "finance",
        "insurance"
    ],
    "wof:name":"Caisse Depargne De Haute Normandie",
    "wof:placetype":"venue"
},
  "geometry": {"coordinates":[1.108353,49.474674],"type":"Point"}
}