{
  "type": "Feature",
  "properties": {
    "iso:country":"FR",
    "sg:address":"2, Rue des M\u00e9tiers - ZA, 49770 La Meignanne",
    "sg:city":"La Meignanne",
    "sg:orig_category":"Unclassifiable Establishments",
    "sg:phone":"+33 2 41 32 77 77",
    "sg:postcode":"49220",
    "sg:province":"Pays de Loire",
    "wof:name":"Amis S.a.r.l.",
    "wof:placetype":"venue"
},
  "geometry": {"coordinates":[-0.669794,47.519283],"type":"Point"}
}