{
  "type": "Feature",
  "properties": {
    "addr:full":"Rue Norbert S\u00e9gard 59223 Roncq Nord Pas-de-Calais 59223",
    "addr:postcode":"59223;59223",
    "addr:street":"Rue Norbert Se\u0301Gard",
    "iso:country":"FR",
    "sg:address":"Rue Norbert S\u00e9gard 59223 Roncq",
    "sg:classifiers":[
        {
            "category":"Professional",
            "subcategory":"Engineering",
            "type":"Services"
        }
    ],
    "sg:phone":"+33 3 20 25 92 90",
    "sg:postcode":"59223",
    "sg:province":"Nord Pas-de-Calais",
    "sg:tags":[
        "machine",
        "-",
        "mechanical"
    ],
    "wof:name":"Wittendal Sa",
    "wof:placetype":"venue"
},
  "geometry": {"coordinates":[3.13887,50.746361],"type":"Point"}
}