{
  "type": "Feature",
  "properties": {
    "iso:country":"FR",
    "sg:address":"B.P. 14, 13741 Vitrolles C\u00e9dex^^6, Rue de Copenhague - ZI les Estroublancs, 13127 Vitrolles",
    "sg:orig_category":"Non-Classified Establishments",
    "sg:phone":"+33 4 42 89 08 53",
    "sg:province":"Provence-Alpes-C\u00f4te d'Azur",
    "wof:name":"Fraikin Location",
    "wof:placetype":"venue"
},
  "geometry": {"coordinates":[5.253005,43.449944],"type":"Point"}
}