{
  "type": "Feature",
  "properties": {
    "addr:full":"4, Rue Jean Mermoz, 71000 M\u00e2con Sanc\u00e9 Bourgogne 71000",
    "addr:housenumber":"4",
    "addr:postcode":"71000;71000",
    "addr:street":"Rue Jean Mermoz",
    "iso:country":"FR",
    "sg:address":"4, Rue Jean Mermoz, 71000 M\u00e2con",
    "sg:city":"Sanc\u00e9",
    "sg:orig_category":"Unclassifiable Establishments",
    "sg:phone":"+33 3 85 29 00 81",
    "sg:postcode":"71000",
    "sg:province":"Bourgogne",
    "wof:name":"Berthoud S.a.s.",
    "wof:placetype":"venue"
},
  "geometry": {"coordinates":[4.809479,46.29343],"type":"Point"}
}