{
  "type": "Feature",
  "properties": {
    "addr:full":"148 rue Breteuil MARSEILLE 13006",
    "addr:housenumber":"148",
    "addr:postcode":"13006",
    "addr:street":"Rue Breteuil",
    "iso:country":"FR",
    "sg:address":"148 rue Breteuil",
    "sg:city":"MARSEILLE",
    "sg:classifiers":[
        {
            "category":"Professional",
            "subcategory":"Computer Services",
            "type":"Services"
        }
    ],
    "sg:postcode":"13006",
    "sg:tags":[
        "web-service",
        "video",
        "video-encoding",
        "video-uploading"
    ],
    "sg:website":"http://particle-s.com/",
    "wof:name":"Particles",
    "wof:placetype":"venue"
},
  "geometry": {"coordinates":[5.378357,43.283994],"type":"Point"}
}