{
  "type": "Feature",
  "properties": {
    "iso:country":"FR",
    "sg:address":"16 Rue Dellevaux 69410 Champagne Au Mont D'Or",
    "sg:classifiers":[
        {
            "category":"Health Services",
            "subcategory":"Optometrist",
            "type":"Services"
        }
    ],
    "sg:phone":"+33 4 72 52 01 70",
    "sg:postcode":"69410",
    "sg:province":"Rhone-Alpes",
    "sg:tags":[
        "instrument",
        "optical",
        "-",
        "precision",
        "equipment"
    ],
    "wof:name":"Odlm Sa",
    "wof:placetype":"venue"
},
  "geometry": {"coordinates":[-0.100754,47.869232],"type":"Point"}
}