{
  "type": "Feature",
  "properties": {
    "addr:full":"ZI le Cardonnoy Aumale Haute Normandie 76390",
    "addr:postcode":"76390",
    "addr:street":"Zi Le Cardonnoy;Haute Normandie",
    "iso:country":"FR",
    "sg:address":"ZI le Cardonnoy",
    "sg:city":"Aumale",
    "sg:orig_category":"Non-Classified Establishments",
    "sg:phone":"+33 2 35 94 12 00",
    "sg:postcode":"76390",
    "sg:province":"Haute Normandie",
    "wof:name":"Labilait",
    "wof:placetype":"venue"
},
  "geometry": {"coordinates":[1.753135,49.767895],"type":"Point"}
}