{
  "type": "Feature",
  "properties": {
    "iso:country":"FR",
    "sg:address":"B.P. 10, 16101 Cognac C\u00e9dex^^26, Rue Pascal Combeau, 16100 Cognac",
    "sg:orig_category":"Non-Classified Establishments",
    "sg:phone":"+33 5 45 82 32 10",
    "sg:postcode":"16100",
    "sg:province":"Poitou-Charentes",
    "wof:name":"C.d.g. S.a. - Compagnie De Guyenne",
    "wof:placetype":"venue"
},
  "geometry": {"coordinates":[-0.313384,45.67149],"type":"Point"}
}