{
  "type": "Feature",
  "properties": {
    "addr:full":"Savoie Technolac Le Bourget du Lac C\u00e9dex Centre 73373",
    "addr:housenumber":"73373",
    "iso:country":"FR",
    "sg:address":"Savoie Technolac",
    "sg:city":"Le Bourget du Lac C\u00e9dex",
    "sg:orig_category":"Non-Classified Establishments",
    "sg:phone":"+33 4 79 60 60 60",
    "sg:postcode":"73373",
    "sg:province":"Centre",
    "wof:name":"E.d.f. C.i.h.",
    "wof:placetype":"venue"
},
  "geometry": {"coordinates":[5.87793,45.59708],"type":"Point"}
}