{
  "type": "Feature",
  "properties": {
    "iso:country":"FR",
    "sg:address":"Rte de Jarnosse",
    "sg:city":"Pouilly sous Charlieu",
    "sg:orig_category":"Unclassifiable Establishments",
    "sg:phone":"+33 4 77 69 99 99",
    "sg:postcode":"42720",
    "sg:province":"Rhone-Alpes",
    "wof:name":"S.e.b.i.co. S.a. - Soci\u00e9t\u00e9 D'exploitation Des Brevets Int\u00e9ressants La Construction",
    "wof:placetype":"venue"
},
  "geometry": {"coordinates":[4.111659,46.128551],"type":"Point"}
}