{
  "type": "Feature",
  "properties": {
    "iso:country":"FR",
    "sg:address":"27, Chemin de Monteau, 30400 Villeneuve l\u00e8s Avignon",
    "sg:orig_category":"Unclassifiable Establishments",
    "sg:phone":"+33 4 90 15 92 92",
    "sg:province":"Languedoc-Roussillon",
    "wof:name":"A 2 Ing\u00e9nierie S.a.r.l.",
    "wof:placetype":"venue"
},
  "geometry": {"coordinates":[4.78852,43.955753],"type":"Point"}
}