{
  "type": "Feature",
  "properties": {
    "addr:full":"B.P. 229, 95614 Cergy C\u00e9dex^^11, Rue Rosa Luxembourg - Eragny Parc - B\u00e2t. Floride, 95610 Eragny Ile de France",
    "addr:housenumber":"b.p. 229",
    "addr:postcode":"95614;95610",
    "addr:street":"Rue Rosa Luxembourg Eragny Parc Ba\u0302T;Ile De France",
    "iso:country":"FR",
    "sg:address":"B.P. 229, 95614 Cergy C\u00e9dex^^11, Rue Rosa Luxembourg - Eragny Parc - B\u00e2t. Floride, 95610 Eragny",
    "sg:orig_category":"Non-Classified Establishments",
    "sg:phone":"+33 1 30 37 70 70",
    "sg:province":"Ile de France",
    "wof:name":"P.i.i. S.a. - P\u00e9ri Informatique Industries",
    "wof:placetype":"venue"
},
  "geometry": {"coordinates":[2.091,49.019009],"type":"Point"}
}