{
  "type": "Feature",
  "properties": {
    "addr:full":"15, Place Saint Ursule, 64100 Bayonne Bayonne Aquitaine 64100",
    "addr:housenumber":"15",
    "addr:postcode":"64100 bayonne;64100",
    "addr:street":"Place Saint Ursule",
    "iso:country":"FR",
    "sg:address":"15, Place Saint Ursule, 64100 Bayonne",
    "sg:city":"Bayonne",
    "sg:orig_category":"Unclassifiable Establishments",
    "sg:phone":"+33 5 59 50 35 10",
    "sg:postcode":"64100",
    "sg:province":"Aquitaine",
    "wof:name":"C.e.r.t.i.m. S.a.r.l. - Centre D'etudes Et De Recherches Techniques Pour",
    "wof:placetype":"venue"
},
  "geometry": {"coordinates":[-1.471425,43.496132],"type":"Point"}
}