{
  "type": "Feature",
  "properties": {
    "iso:country":"FR",
    "sg:address":"4 Avenue Marguerites 94600 Choisy Le Roi",
    "sg:classifiers":[
        {
            "category":"Autos & Motor Vehicles",
            "subcategory":"Boat Sales",
            "type":"Retail Goods"
        }
    ],
    "sg:phone":"+33 1 48 90 90 11",
    "sg:postcode":"94600",
    "sg:province":"Ile de France",
    "sg:tags":[
        "equipment",
        "transport"
    ],
    "wof:name":"Fournitures Accastillage Mecanique Manutention (famm)",
    "wof:placetype":"venue"
},
  "geometry": {"coordinates":[2.413056,48.772846],"type":"Point"}
}