{
  "type": "Feature",
  "properties": {
    "addr:full":"7 rue de l'Hospice 69240 Thizy Rhone-Alpes 69240",
    "addr:housenumber":"7",
    "addr:postcode":"69240;69240",
    "addr:street":"Rue De L'Hospice",
    "iso:country":"FR",
    "sg:address":"7 rue de l'Hospice 69240 Thizy",
    "sg:classifiers":[
        {
            "category":"Banks & Credit Unions",
            "subcategory":"Investment Brokerage",
            "type":"Services"
        }
    ],
    "sg:phone":"+33 4 74 64 66 50",
    "sg:postcode":"69240",
    "sg:province":"Rhone-Alpes",
    "sg:tags":[
        "women's",
        "clothing",
        "accessory"
    ],
    "wof:name":"Ren\u00e9 Couturier Sa",
    "wof:placetype":"venue"
},
  "geometry": {"coordinates":[4.313966,46.027817],"type":"Point"}
}