{
  "type": "Feature",
  "properties": {
    "iso:country":"FR",
    "sg:address":"60 Rue Brosse 45110 Chateauneuf Sur Loire",
    "sg:city":"Ch\u00e2teauneuf-sur-Loire",
    "sg:classifiers":[
        {
            "category":"Professional",
            "type":"Services"
        }
    ],
    "sg:phone":"+33 2 38 58 91 50",
    "sg:postcode":"45110",
    "sg:province":"Centre",
    "sg:tags":[
        "transport",
        "road"
    ],
    "wof:name":"Stex Sarl",
    "wof:placetype":"venue"
},
  "geometry": {"coordinates":[2.2259,47.869564],"type":"Point"}
}