{
  "type": "Feature",
  "properties": {
    "addr:full":"B.P. 39 Monistrol sur Loire Auvergne 43120",
    "addr:postcode":"43120",
    "addr:street":"B.P. 39 Monistrol Sur Loire",
    "iso:country":"FR",
    "sg:address":"B.P. 39",
    "sg:city":"Monistrol sur Loire",
    "sg:orig_category":"Non-Classified Establishments",
    "sg:phone":"+33 4 71 75 16 00",
    "sg:postcode":"43120",
    "sg:province":"Auvergne",
    "wof:name":"Durafour Informatique S.a.r.l.",
    "wof:placetype":"venue"
},
  "geometry": {"coordinates":[4.172515,45.292206],"type":"Point"}
}