{
  "type": "Feature",
  "properties": {
    "iso:country":"FR",
    "sg:address":"24, Rue du Puits Sur, 11560 Fleury",
    "sg:orig_category":"Unclassifiable Establishments",
    "sg:phone":"+33 4 68 33 62 68",
    "sg:province":"Languedoc-Roussillon",
    "wof:name":"Bottero Robert",
    "wof:placetype":"venue"
},
  "geometry": {"coordinates":[3.135567,43.231495],"type":"Point"}
}