{
  "type": "Feature",
  "properties": {
    "addr:full":"Avenue Du Mal Foch Residence Toumalin Saint Paul Les Dax Aquitaine 40990",
    "addr:housenumber":"foch",
    "addr:postcode":"40990",
    "addr:street":"Avenue Du Mal",
    "iso:country":"FR",
    "sg:address":"Avenue Du Mal Foch Residence Toumalin",
    "sg:city":"Saint Paul Les Dax",
    "sg:classifiers":[
        {
            "category":"Banks & Credit Unions",
            "subcategory":"Financial Services",
            "type":"Services"
        }
    ],
    "sg:phone":"+33 5 58 91 65 60",
    "sg:postcode":"40990",
    "sg:province":"Aquitaine",
    "sg:tags":[
        "banking",
        "finance",
        "insurance"
    ],
    "wof:name":"Societe Fiduciaire Nationale D'expertise Comptable Fidexpert (fid)",
    "wof:placetype":"venue"
},
  "geometry": {"coordinates":[-1.048704,43.73016],"type":"Point"}
}