{
  "type": "Feature",
  "properties": {
    "addr:full":"3, Rue de la Fecht, 68126 Bennwihr Bennwihr Alsace 68630",
    "addr:housenumber":"3",
    "addr:postcode":"68126;68630",
    "addr:street":"Rue De La Fecht",
    "iso:country":"FR",
    "sg:address":"3, Rue de la Fecht, 68126 Bennwihr",
    "sg:city":"Bennwihr",
    "sg:orig_category":"Unclassifiable Establishments",
    "sg:phone":"+33 3 89 21 41 00",
    "sg:postcode":"68630",
    "sg:province":"Alsace",
    "wof:name":"St\u00e9vial S.a.r.l.",
    "wof:placetype":"venue"
},
  "geometry": {"coordinates":[7.35161,48.12878],"type":"Point"}
}