{
  "type": "Feature",
  "properties": {
    "addr:full":"108-110 R Saint-Maur 75011 Paris Ile de France 75011",
    "addr:housenumber":"108-110",
    "addr:postcode":"75011;75011",
    "addr:street":"R Saint-Maur",
    "iso:country":"FR",
    "sg:address":"108-110 R Saint-Maur 75011 Paris",
    "sg:classifiers":[
        {
            "category":"Professional",
            "subcategory":"Business Services",
            "type":"Services"
        }
    ],
    "sg:phone":"+33 1 49 23 82 52",
    "sg:postcode":"75011",
    "sg:province":"Ile de France",
    "sg:tags":[
        "body",
        "advice"
    ],
    "wof:name":"Association Unassad",
    "wof:placetype":"venue"
},
  "geometry": {"coordinates":[2.376838,48.866463],"type":"Point"}
}