{
  "type": "Feature",
  "properties": {
    "addr:full":"Av. Gustave Eiffel - ZI Pessac Bersol 2 Pessac Aquitaine 33600",
    "addr:housenumber":"2",
    "addr:postcode":"33600",
    "addr:street":"Av. Gustave Eiffel Zi;Bersol",
    "iso:country":"FR",
    "sg:address":"Av. Gustave Eiffel - ZI Pessac Bersol 2",
    "sg:city":"Pessac",
    "sg:orig_category":"Unclassifiable Establishments",
    "sg:phone":"+33 5 56 07 90 30",
    "sg:postcode":"33600",
    "sg:province":"Aquitaine",
    "wof:name":"Koba Bordeaux S.a.",
    "wof:placetype":"venue"
},
  "geometry": {"coordinates":[-0.630989,44.80616],"type":"Point"}
}