{
  "type": "Feature",
  "properties": {
    "iso:country":"FR",
    "sg:address":"Zi 2 67490 Dettwiller",
    "sg:city":"Dettwiller",
    "sg:classifiers":[
        {
            "category":"Shopping",
            "subcategory":"Luggage & Leather Goods",
            "type":"Retail Goods"
        }
    ],
    "sg:phone":"+33 3 88 91 41 37",
    "sg:postcode":"67490",
    "sg:province":"Alsace",
    "sg:tags":[
        "shoe"
    ],
    "wof:name":"Heschung Sa",
    "wof:placetype":"venue"
},
  "geometry": {"coordinates":[7.46685,48.754059],"type":"Point"}
}