{
  "type": "Feature",
  "properties": {
    "addr:full":"B.P. 128 Ch\u00e2tellerault C\u00e9dex Picardie 86101",
    "addr:housenumber":"b.p.",
    "addr:postcode":"86101",
    "addr:street":"128",
    "iso:country":"FR",
    "sg:address":"B.P. 128",
    "sg:city":"Ch\u00e2tellerault C\u00e9dex",
    "sg:orig_category":"Non-Classified Establishments",
    "sg:phone":"+33 5 49 93 94 37",
    "sg:postcode":"86101",
    "sg:province":"Picardie",
    "wof:name":"Tis-livingston S.a.",
    "wof:placetype":"venue"
},
  "geometry": {"coordinates":[0.54494,46.819901],"type":"Point"}
}