{
  "type": "Feature",
  "properties": {
    "addr:full":"77 bis, Av. Gambetta, 93170 Bagnolet Ile de France",
    "addr:housenumber":"77 bis",
    "addr:postcode":"93170;ile",
    "addr:street":"Av. Gambetta",
    "iso:country":"FR",
    "sg:address":"77 bis, Av. Gambetta, 93170 Bagnolet",
    "sg:orig_category":"Unclassifiable Establishments",
    "sg:phone":"+33 1 43 62 15 15",
    "sg:province":"Ile de France",
    "wof:name":"F.c.b.i. S.a.",
    "wof:placetype":"venue"
},
  "geometry": {"coordinates":[2.417458,48.871063],"type":"Point"}
}