{
  "type": "Feature",
  "properties": {
    "iso:country":"FR",
    "sg:address":"1, Rue Louis de Broglie - Synergie Park, 59260 Lezennes",
    "sg:orig_category":"Unclassifiable Establishments",
    "sg:phone":"+33 3 28 76 55 55",
    "sg:province":"Nord Pas-de-Calais",
    "wof:name":"Chronopost International",
    "wof:placetype":"venue"
},
  "geometry": {"coordinates":[3.11705,50.614567],"type":"Point"}
}