{
  "type": "Feature",
  "properties": {
    "addr:full":"10, Bd Duguet, 42600 Savigneux Rhone-Alpes 42600",
    "addr:housenumber":"10",
    "addr:postcode":"42600;42600",
    "addr:street":"Bd Duguet",
    "iso:country":"FR",
    "sg:address":"10, Bd Duguet, 42600 Savigneux",
    "sg:orig_category":"Non-Classified Establishments",
    "sg:phone":"+33 4 77 58 27 33",
    "sg:postcode":"42600",
    "sg:province":"Rhone-Alpes",
    "wof:name":"Cottin Prioux Cars Planche S.a.",
    "wof:placetype":"venue"
},
  "geometry": {"coordinates":[4.068289,45.609409],"type":"Point"}
}