{
  "type": "Feature",
  "properties": {
    "addr:full":"Roussannes 47320 Clairac Clairac Aquitaine 47320",
    "addr:postcode":"47320;47320",
    "addr:street":"Roussannes",
    "iso:country":"FR",
    "sg:address":"Roussannes 47320 Clairac",
    "sg:city":"Clairac",
    "sg:orig_category":"Non-Classified Establishments",
    "sg:phone":"+33 5 53 84 02 21",
    "sg:postcode":"47320",
    "sg:province":"Aquitaine",
    "wof:name":"Bosi Serge",
    "wof:placetype":"venue"
},
  "geometry": {"coordinates":[0.437809,44.373337],"type":"Point"}
}