{
  "type": "Feature",
  "properties": {
    "addr:full":"Rue De Lhotaud 25560 Frasne Franche Comt\u00e9",
    "addr:postcode":"25560",
    "addr:street":"Rue De Lhotaud;Franche Comte\u0301",
    "iso:country":"FR",
    "sg:address":"Rue De Lhotaud 25560 Frasne",
    "sg:classifiers":[
        {
            "category":"Manufacturing",
            "subcategory":"Paper Products",
            "type":"Manufacturing & Wholesale Goods"
        }
    ],
    "sg:phone":"+33 3 81 49 80 42",
    "sg:province":"Franche Comt\u00e9",
    "sg:tags":[
        "packaging",
        "material",
        "-",
        "cardboard"
    ],
    "wof:name":"Boissellerie Petite",
    "wof:placetype":"venue"
},
  "geometry": {"coordinates":[6.163377,46.857418],"type":"Point"}
}