{
  "type": "Feature",
  "properties": {
    "iso:country":"FR",
    "sg:address":"36, Av. Jos\u00e9 Nobre, 13500 Martigues",
    "sg:orig_category":"Unclassifiable Establishments",
    "sg:phone":"+33 4 42 81 63 01",
    "sg:province":"Provence-Alpes-C\u00f4te d'Azur",
    "wof:name":"Auxitec Technologies S.a.",
    "wof:placetype":"venue"
},
  "geometry": {"coordinates":[5.04006,43.399677],"type":"Point"}
}