{
  "type": "Feature",
  "properties": {
    "iso:country":"FR",
    "sg:address":"33 Rte De Thionville 57140 St R\u00e9my",
    "sg:classifiers":[
        {
            "category":"Professional",
            "type":"Services"
        }
    ],
    "sg:phone":"+33 3 87 30 87 75",
    "sg:province":"Lorraine",
    "sg:tags":[
        "transport",
        "road"
    ],
    "wof:name":"Sa Transport Langlade",
    "wof:placetype":"venue"
},
  "geometry": {"coordinates":[6.150305,49.15131],"type":"Point"}
}