{
  "type": "Feature",
  "properties": {
    "iso:country":"FR",
    "sg:address":"5 Rue Gal Pershing 60600 Clermont",
    "sg:classifiers":[
        {
            "category":"Banks & Credit Unions",
            "subcategory":"Financial Services",
            "type":"Services"
        }
    ],
    "sg:phone":"+33 3 44 68 22 10",
    "sg:postcode":"60600",
    "sg:province":"Picardie",
    "sg:tags":[
        "banking",
        "insurance",
        "institution",
        "finance"
    ],
    "wof:name":"Caisse Regionale De Credit Agricole Mutuel De L'oise (crcamo)",
    "wof:placetype":"venue"
},
  "geometry": {"coordinates":[2.414864,49.378986],"type":"Point"}
}