{
  "type": "Feature",
  "properties": {
    "iso:country":"FR",
    "sg:address":"rue Larregain 64140 Lons",
    "sg:city":"Lons",
    "sg:classifiers":[
        {
            "category":"Manufacturing",
            "subcategory":"Rubber & Plastics",
            "type":"Manufacturing & Wholesale Goods"
        }
    ],
    "sg:phone":"+33 5 59 13 30 00",
    "sg:postcode":"64140",
    "sg:province":"Aquitaine",
    "sg:tags":[
        "packaging",
        "mean"
    ],
    "wof:name":"Roskoplast Sa",
    "wof:placetype":"venue"
},
  "geometry": {"coordinates":[-0.428855,43.307472],"type":"Point"}
}