{
  "type": "Feature",
  "properties": {
    "iso:country":"FR",
    "sg:address":"2 Rue Du Haut D' Avon 77300 Fontainebleau Avon",
    "sg:classifiers":[
        {
            "category":"Utilities",
            "subcategory":"Electric",
            "type":"Services"
        }
    ],
    "sg:phone":"+33 1 64 22 02 72",
    "sg:postcode":"77300",
    "sg:province":"Ile de France",
    "sg:tags":[
        "electricity",
        "electronic",
        "electrical",
        "equipment"
    ],
    "wof:name":"Smetc Snc",
    "wof:placetype":"venue"
},
  "geometry": {"coordinates":[2.72196,48.415932],"type":"Point"}
}