{
  "type": "Feature",
  "properties": {
    "addr:full":"301, Chauss\u00e9e Jules C\u00e9sar, 95250 Beauchamp Ile de France 95250",
    "addr:housenumber":"301",
    "addr:postcode":"95250;ile;95250",
    "addr:street":"Chausse\u0301E Jules Ce\u0301Sar;France",
    "iso:country":"FR",
    "sg:address":"301, Chauss\u00e9e Jules C\u00e9sar, 95250 Beauchamp",
    "sg:orig_category":"Non-Classified Establishments",
    "sg:phone":"+33 1 39 95 33 33",
    "sg:postcode":"95250",
    "sg:province":"Ile de France",
    "wof:name":"Dubois Industries S.a.r.l.",
    "wof:placetype":"venue"
},
  "geometry": {"coordinates":[2.175622,49.01638],"type":"Point"}
}