{
  "type": "Feature",
  "properties": {
    "iso:country":"FR",
    "sg:address":"B.P. 83, 93503 Pantin C\u00e9dex^^6, Rue Beaurepaire, 93500 Pantin",
    "sg:orig_category":"Non-Classified Establishments",
    "sg:phone":"+33 1 48 44 45 23",
    "sg:postcode":"93500",
    "sg:province":"Ile de France",
    "wof:name":"Calder Chauffage S.a.r.l.",
    "wof:placetype":"venue"
},
  "geometry": {"coordinates":[2.40168,48.89658],"type":"Point"}
}