{
  "type": "Feature",
  "properties": {
    "addr:full":"Av. Marcel le Mignot - Gonfreville l'Orcher Harfleur Haute Normandie 76700",
    "addr:postcode":"76700",
    "addr:street":"Av. Marcel Le Mignot Gonfreville L'Orcher;Haute Normandie",
    "iso:country":"FR",
    "sg:address":"Av. Marcel le Mignot - Gonfreville l'Orcher",
    "sg:city":"Harfleur",
    "sg:orig_category":"Non-Classified Establishments",
    "sg:phone":"+33 2 35 24 08 37",
    "sg:postcode":"76700",
    "sg:province":"Haute Normandie",
    "wof:name":"Sotrasi S.a.r.l. - Soci\u00e9t\u00e9 De Travaux Et De Services Industriels",
    "wof:placetype":"venue"
},
  "geometry": {"coordinates":[0.209034,49.504463],"type":"Point"}
}