{
  "type": "Feature",
  "properties": {
    "addr:full":"4 Rue Isaac Newton Parc Chemin Long 33705 Merignac Cedex Franche Comt\u00e9",
    "addr:housenumber":"4",
    "addr:postcode":"33705 merignac cedex franche comte\u0301",
    "addr:street":"Rue Isaac Newton Parc Chemin Long",
    "iso:country":"FR",
    "sg:address":"4 Rue Isaac Newton Parc Chemin Long 33705 Merignac Cedex",
    "sg:classifiers":[
        {
            "category":"Utilities",
            "subcategory":"Electric",
            "type":"Services"
        }
    ],
    "sg:phone":"+33 5 57 92 76 54",
    "sg:province":"Franche Comt\u00e9",
    "sg:tags":[
        "electricity",
        "raw",
        "energy",
        "material"
    ],
    "wof:name":"Electricite De France (edf)",
    "wof:placetype":"venue"
},
  "geometry": {"coordinates":[-0.666007,44.832176],"type":"Point"}
}