{
  "type": "Feature",
  "properties": {
    "addr:full":"1 Lignorelles Bourgogne 89800",
    "addr:housenumber":"1",
    "addr:postcode":"89800",
    "addr:street":"Lignorelles Bourgogne",
    "iso:country":"FR",
    "sg:address":"1",
    "sg:city":"Lignorelles",
    "sg:classifiers":[
        {
            "category":"Food Court",
            "type":"Food & Drink"
        }
    ],
    "sg:phone":"+33 3 86 47 50 59",
    "sg:postcode":"89800",
    "sg:province":"Bourgogne",
    "sg:tags":[
        "product",
        "related"
    ],
    "wof:name":"Domaine Jean-claude Courtault",
    "wof:placetype":"venue"
},
  "geometry": {"coordinates":[3.721411,47.859371],"type":"Point"}
}