{
  "type": "Feature",
  "properties": {
    "addr:full":"23, Rue du Lyonnais, 69800 Saint Priest Rhone-Alpes 69800",
    "addr:housenumber":"23",
    "addr:postcode":"69800;69800",
    "addr:street":"Rue Du Lyonnais;Priest Rhone-Alpes",
    "iso:country":"FR",
    "sg:address":"23, Rue du Lyonnais, 69800 Saint Priest",
    "sg:orig_category":"Non-Classified Establishments",
    "sg:phone":"+33 4 72 23 58 28",
    "sg:postcode":"69800",
    "sg:province":"Rhone-Alpes",
    "wof:name":"Distelec S.a.r.l.",
    "wof:placetype":"venue"
},
  "geometry": {"coordinates":[4.920647,45.698009],"type":"Point"}
}