{
  "type": "Feature",
  "properties": {
    "iso:country":"FR",
    "sg:address":"ZI de Popey",
    "sg:city":"Bar le Duc",
    "sg:orig_category":"FOURS INDUSTRIELS ET \u00c9QUIPEMENTS THERMIQUES sous-traitance en m\u00e9cano-soudure",
    "sg:phone":"+33 3 29 76 82 00",
    "sg:postcode":"55000",
    "sg:province":"Lorraine",
    "wof:name":"Stein Heurtey S.a.",
    "wof:placetype":"venue"
},
  "geometry": {"coordinates":[5.164777,48.77103],"type":"Point"}
}