{
  "type": "Feature",
  "properties": {
    "iso:country":"FR",
    "sg:address":"12, Rue des Ecoles, 60360 Cr\u00e8vecoeur le Grand",
    "sg:orig_category":"Unclassifiable Establishments",
    "sg:phone":"+33 3 44 46 87 34",
    "sg:province":"Picardie",
    "wof:name":"Dumont S.a.r.l.",
    "wof:placetype":"venue"
},
  "geometry": {"coordinates":[2.074956,49.608047],"type":"Point"}
}