{
  "type": "Feature",
  "properties": {
    "iso:country":"FR",
    "sg:address":"66, Cours Charlemagne - Le Factory , 69002 Lyon",
    "sg:orig_category":"Unclassifiable Establishments",
    "sg:phone":"+33 4 72 41 15 00",
    "sg:postcode":"69002",
    "sg:province":"Rhone-Alpes",
    "wof:name":"Lise Charmel S.a.",
    "wof:placetype":"venue"
},
  "geometry": {"coordinates":[4.828975,45.759399],"type":"Point"}
}