{
  "type": "Feature",
  "properties": {
    "iso:country":"FR",
    "sg:address":"12, Rue Partouneaux, 10100 Romilly sur Seine",
    "sg:orig_category":"Non-Classified Establishments",
    "sg:phone":"+33 3 25 24 81 34",
    "sg:postcode":"10100",
    "sg:province":"Champagne",
    "wof:name":"Colson Et Compagnie S.a.",
    "wof:placetype":"venue"
},
  "geometry": {"coordinates":[3.723433,48.520405],"type":"Point"}
}