{
  "type": "Feature",
  "properties": {
    "iso:country":"FR",
    "sg:address":"19, Rue Landivisiau, 29400 Lampaul Guimiliau",
    "sg:city":"Landivisiau",
    "sg:orig_category":"Unclassifiable Establishments",
    "sg:phone":"+33 2 98 68 69 70",
    "sg:postcode":"29400",
    "sg:province":"Bretagne",
    "wof:name":"Gad S.a.",
    "wof:placetype":"venue"
},
  "geometry": {"coordinates":[-4.043833,48.491642],"type":"Point"}
}