{
  "type": "Feature",
  "properties": {
    "iso:country":"FR",
    "sg:address":"20, Grand Quai, 76400 F\u00e9camp",
    "sg:orig_category":"Unclassifiable Establishments",
    "sg:phone":"+33 2 35 10 25 35",
    "sg:province":"Haute Normandie",
    "wof:name":"Filextra S.a.",
    "wof:placetype":"venue"
},
  "geometry": {"coordinates":[0.368703,49.762218],"type":"Point"}
}