{
  "type": "Feature",
  "properties": {
    "addr:full":"Domaine de Lacroux Cestayrols Midi Pyr\u00e9n\u00e9es 81150",
    "addr:postcode":"81150",
    "iso:country":"FR",
    "sg:address":"Domaine de Lacroux",
    "sg:city":"Cestayrols",
    "sg:orig_category":"Unclassifiable Establishments",
    "sg:phone":"+33 5 63 56 88 88",
    "sg:postcode":"81150",
    "sg:province":"Midi Pyr\u00e9n\u00e9es",
    "wof:name":"Derrieux Pierre Et Fils G.a.e.c. - Ch\u00e2teau De Lacroux",
    "wof:placetype":"venue"
},
  "geometry": {"coordinates":[1.994878,43.966835],"type":"Point"}
}