{
  "type": "Feature",
  "properties": {
    "addr:full":"B.P. 2112, 31020 Toulouse C\u00e9dex^^58, Bd Pierre Curie, 31200 Toulouse Midi Pyr\u00e9n\u00e9es",
    "addr:housenumber":"2112",
    "addr:postcode":"31020;31200",
    "addr:street":"B.P.;Bd Pierre Curie",
    "iso:country":"FR",
    "sg:address":"B.P. 2112, 31020 Toulouse C\u00e9dex^^58, Bd Pierre Curie, 31200 Toulouse",
    "sg:orig_category":"Non-Classified Establishments",
    "sg:phone":"+33 5 61 47 54 82",
    "sg:province":"Midi Pyr\u00e9n\u00e9es",
    "wof:name":"Laho Equipement S.a.",
    "wof:placetype":"venue"
},
  "geometry": {"coordinates":[1.44954,43.639011],"type":"Point"}
}