{
  "type": "Feature",
  "properties": {
    "addr:full":"Le Pr\u00e9 Sec 72210 La Suze sur Sarthe Pays de Loire",
    "addr:postcode":"72210",
    "addr:street":"La",
    "iso:country":"FR",
    "sg:address":"Le Pr\u00e9 Sec 72210 La Suze sur Sarthe",
    "sg:orig_category":"Unclassifiable Establishments",
    "sg:phone":"+33 2 43 77 67 00",
    "sg:province":"Pays de Loire",
    "wof:name":"Siemens Automotive Moteurs Electriques S.a.",
    "wof:placetype":"venue"
},
  "geometry": {"coordinates":[0.02721,47.889709],"type":"Point"}
}