{
  "type": "Feature",
  "properties": {
    "addr:full":"6 Myrha 75018 Paris Ile de France 75018",
    "addr:housenumber":"6",
    "addr:postcode":"75018;75018",
    "addr:street":"Myrha",
    "iso:country":"FR",
    "sg:address":"6",
    "sg:city":"Myrha 75018 Paris",
    "sg:classifiers":[
        {
            "category":"Professional",
            "subcategory":"Business Services",
            "type":"Services"
        }
    ],
    "sg:phone":"+33 1 42 57 20 11",
    "sg:postcode":"75018",
    "sg:province":"Ile de France",
    "sg:tags":[
        "transport",
        "-",
        "road",
        "related",
        "air"
    ],
    "wof:name":"Allo Action",
    "wof:placetype":"venue"
},
  "geometry": {"coordinates":[2.355755,48.887413],"type":"Point"}
}