{
  "type": "Feature",
  "properties": {
    "iso:country":"FR",
    "sg:address":"ZI les Echets",
    "sg:city":"Miribel C\u00e9dex",
    "sg:orig_category":"Non-Classified Establishments",
    "sg:phone":"+33 4 72 26 26 26",
    "sg:postcode":"01706",
    "sg:province":"Rhone-Alpes",
    "wof:name":"Air Liquide S.a.",
    "wof:placetype":"venue"
},
  "geometry": {"coordinates":[4.910279,45.85638],"type":"Point"}
}