{
  "type": "Feature",
  "properties": {
    "iso:country":"FR",
    "sg:address":"Parc Technologique de la Bechade",
    "sg:city":"Issoire",
    "sg:orig_category":"Unclassifiable Establishments",
    "sg:phone":"+33 4 73 55 53 20",
    "sg:postcode":"63500",
    "sg:province":"Auvergne",
    "wof:name":"Biodome S.a.",
    "wof:placetype":"venue"
},
  "geometry": {"coordinates":[3.246695,45.544281],"type":"Point"}
}