{
  "type": "Feature",
  "properties": {
    "addr:full":"5 rue Maurice Berteaux 78711 Mantes la Ville Vill\u00e9 Alsace 67220",
    "addr:housenumber":"5",
    "addr:postcode":"78711;67220",
    "addr:street":"Rue Maurice Berteaux",
    "iso:country":"FR",
    "sg:address":"5 rue Maurice Berteaux 78711 Mantes la Ville",
    "sg:city":"Vill\u00e9",
    "sg:classifiers":[
        {
            "category":"Shopping",
            "subcategory":"Musical Instruments",
            "type":"Retail Goods"
        }
    ],
    "sg:phone":"+33 1 30 98 51 30",
    "sg:postcode":"67220",
    "sg:province":"Alsace",
    "sg:tags":[
        "brass"
    ],
    "wof:name":"Buffet Crampon Sa",
    "wof:placetype":"venue"
},
  "geometry": {"coordinates":[1.714778,48.98283],"type":"Point"}
}