{
  "type": "Feature",
  "properties": {
    "iso:country":"FR",
    "sg:address":"17 Rue Dayde 31200 Toulouse",
    "sg:classifiers":[
        {
            "category":"Professional",
            "subcategory":"Engineering",
            "type":"Services"
        }
    ],
    "sg:phone":"+33 5 34 40 10 10",
    "sg:postcode":"31200",
    "sg:province":"Midi Pyr\u00e9n\u00e9es",
    "sg:tags":[
        "machine",
        "-",
        "mechanical"
    ],
    "wof:name":"Sem Angles Sa",
    "wof:placetype":"venue"
},
  "geometry": {"coordinates":[1.420097,43.615471],"type":"Point"}
}