{
  "type": "Feature",
  "properties": {
    "addr:full":"B.P. 21, 14510 Houlgate^^ZA, 14510 Houlgate Houlgate Basse Normandie 14510",
    "addr:postcode":"14510;14510;14510",
    "addr:street":"B.P. 21;Houlgate Basse",
    "iso:country":"FR",
    "sg:address":"B.P. 21, 14510 Houlgate^^ZA, 14510 Houlgate",
    "sg:city":"Houlgate",
    "sg:orig_category":"Non-Classified Establishments",
    "sg:phone":"+33 2 31 28 18 00",
    "sg:postcode":"14510",
    "sg:province":"Basse Normandie",
    "wof:name":"Soci\u00e9t\u00e9 Patrelle S.a.",
    "wof:placetype":"venue"
},
  "geometry": {"coordinates":[-0.074692,49.300598],"type":"Point"}
}