{
  "type": "Feature",
  "properties": {
    "iso:country":"FR",
    "sg:address":"Rue Ponant 29400 Landivisiau",
    "sg:city":"Landivisiau",
    "sg:classifiers":[
        {
            "category":"Professional",
            "type":"Services"
        }
    ],
    "sg:phone":"+33 2 98 24 48 48",
    "sg:postcode":"29400",
    "sg:province":"Bretagne",
    "sg:tags":[
        "transport",
        "road"
    ],
    "wof:name":"Le Bras Froid Sa",
    "wof:placetype":"venue"
},
  "geometry": {"coordinates":[-4.080177,48.519333],"type":"Point"}
}