{
  "type": "Feature",
  "properties": {
    "iso:country":"FR",
    "sg:address":"B.P. 145, 67723 Hoerdt C\u00e9dex^^13, Rue du Travail - Zone Industrielle, 67720 Hoerdt",
    "sg:city":"Hoerdt",
    "sg:orig_category":"Non-Classified Establishments",
    "sg:phone":"+33 3 88 51 39 51",
    "sg:postcode":"67720",
    "sg:province":"Alsace",
    "wof:name":"Moguntia-est Epices S.a.",
    "wof:placetype":"venue"
},
  "geometry": {"coordinates":[7.782795,48.693417],"type":"Point"}
}