{
  "type": "Feature",
  "properties": {
    "addr:full":"20 rue de Pereisc; Toulon; 83056 Bourgogne",
    "addr:housenumber":"20",
    "addr:postcode":"83056",
    "addr:street":"Rue De Pereisc",
    "iso:country":"FR",
    "sg:address":"20 rue de Pereisc; Toulon; 83056",
    "sg:classifiers":[
        {
            "category":"Banks & Credit Unions",
            "subcategory":"Bank",
            "type":"Services"
        }
    ],
    "sg:phone":"+33 4 94 09 88 88",
    "sg:province":"Bourgogne",
    "wof:name":"Caisse D'epargne, De C\u00f4te D'azur",
    "wof:placetype":"venue"
},
  "geometry": {"coordinates":[5.9052,43.13773],"type":"Point"}
}