{
  "type": "Feature",
  "properties": {
    "iso:country":"FR",
    "sg:address":"135 Rue Des Plesses Ziat Des Plesses 85180 Ch\u00e2teau D'Olonne",
    "sg:classifiers":[
        {
            "category":"Professional",
            "subcategory":"Printing & Photocopies",
            "type":"Services"
        }
    ],
    "sg:phone":"+33 2 51 23 11 00",
    "sg:province":"Pays de Loire",
    "sg:tags":[
        "publishing"
    ],
    "wof:name":"Codes Rousseau",
    "wof:placetype":"venue"
},
  "geometry": {"coordinates":[-1.732654,46.489773],"type":"Point"}
}