{
  "type": "Feature",
  "properties": {
    "addr:full":"Oise",
    "iso:country":"FR",
    "sg:address":"Oise",
    "sg:orig_category":"Non-Classified Establishments",
    "sg:phone":"+33 3 27 78 00 30",
    "wof:name":"Fountain Industries Picardie S.a.",
    "wof:placetype":"venue"
},
  "geometry": {"coordinates":[2.42761,49.412231],"type":"Point"}
}