{
  "type": "Feature",
  "properties": {
    "addr:full":"8 bis, Rue du Chemin Vert, 28100 Dreux Dreux Centre 28100",
    "addr:housenumber":"8 bis;dreux",
    "addr:postcode":"28100;28100",
    "addr:street":"Rue Du Chemin Vert",
    "iso:country":"FR",
    "sg:address":"8 bis, Rue du Chemin Vert, 28100 Dreux",
    "sg:city":"Dreux",
    "sg:orig_category":"Unclassifiable Establishments",
    "sg:phone":"+33 2 37 42 07 88",
    "sg:postcode":"28100",
    "sg:province":"Centre",
    "wof:name":"Rapa S.a.",
    "wof:placetype":"venue"
},
  "geometry": {"coordinates":[1.382919,48.739716],"type":"Point"}
}