{
  "type": "Feature",
  "properties": {
    "iso:country":"FR",
    "sg:address":"B.P. 515, 93619 Aulnay sous Bois C\u00e9dex^^Garonor B\u00e2t. 19, 93600 Aulnay sous Bois",
    "sg:orig_category":"Non-Classified Establishments",
    "sg:phone":"+33 1 45 91 26 13",
    "sg:province":"Ile de France",
    "wof:name":"Victor France S.a.r.l.",
    "wof:placetype":"venue"
},
  "geometry": {"coordinates":[2.49124,48.927509],"type":"Point"}
}