{
  "type": "Feature",
  "properties": {
    "iso:country":"FR",
    "sg:address":"13 rue du Sentier 75002 Paris",
    "sg:classifiers":[
        {
            "category":"Shopping",
            "subcategory":"Clothing, Apparel, & Fashions",
            "type":"Retail Goods"
        }
    ],
    "sg:phone":"+33 1 40 26 07 55",
    "sg:province":"Ile de France",
    "sg:tags":[
        "adults'",
        "clothing",
        "young"
    ],
    "wof:name":"Frank Al Sa",
    "wof:placetype":"venue"
},
  "geometry": {"coordinates":[2.345521,48.868496],"type":"Point"}
}