{
  "type": "Feature",
  "properties": {
    "addr:full":"Quai De Lattre De Tassigny; BP 941; PERPIGNAN; 66020 CEDEX Assigny Centre 18260",
    "addr:housenumber":"941",
    "addr:postcode":"66020 cedex assigny;18260",
    "addr:street":"Quai De Lattre De Tassigny Bp",
    "iso:country":"FR",
    "sg:address":"Quai De Lattre De Tassigny; BP 941; PERPIGNAN; 66020 CEDEX",
    "sg:city":"Assigny",
    "sg:classifiers":[
        {
            "category":"Shopping",
            "subcategory":"Computers & Home Electronics",
            "type":"Retail Goods"
        }
    ],
    "sg:phone":"+33 4 68 35 66 33",
    "sg:postcode":"18260",
    "sg:province":"Centre",
    "sg:tags":[
        "chamber",
        "commerce"
    ],
    "wof:name":"Chambre De Commerce De Perpignan Et Des Pyrinies Orientales",
    "wof:placetype":"venue"
},
  "geometry": {"coordinates":[2.8966,42.700611],"type":"Point"}
}