{
  "type": "Feature",
  "properties": {
    "addr:full":"41, Rue des Bussys, 95600 Eaubonne Ile de France",
    "addr:housenumber":"41",
    "addr:postcode":"95600",
    "addr:street":"Rue Des Bussys",
    "iso:country":"FR",
    "sg:address":"41, Rue des Bussys, 95600 Eaubonne",
    "sg:orig_category":"Unclassifiable Establishments",
    "sg:phone":"+33 1 34 27 34 00",
    "sg:province":"Ile de France",
    "wof:name":"Fontelec S.a.",
    "wof:placetype":"venue"
},
  "geometry": {"coordinates":[2.279759,48.978409],"type":"Point"}
}