{
  "type": "Feature",
  "properties": {
    "addr:full":"15 Rue Des Alouettes Za Les Alouettes 95600 Eaubonne Ile de France 95600",
    "addr:housenumber":"15",
    "addr:postcode":"95600;95600",
    "addr:street":"Rue Des Alouettes Za Les Alouettes",
    "iso:country":"FR",
    "sg:address":"15 Rue Des Alouettes Za Les Alouettes 95600 Eaubonne",
    "sg:classifiers":[
        {
            "category":"Wholesale",
            "subcategory":"Medical Equipment & Supplies",
            "type":"Manufacturing & Wholesale Goods"
        }
    ],
    "sg:phone":"+33 1 39 59 86 00",
    "sg:postcode":"95600",
    "sg:province":"Ile de France",
    "sg:tags":[
        "instrument",
        "health",
        "-",
        "precision"
    ],
    "wof:name":"Gamida Tech",
    "wof:placetype":"venue"
},
  "geometry": {"coordinates":[2.277595,48.990578],"type":"Point"}
}