{
  "type": "Feature",
  "properties": {
    "addr:full":"15, Chemin du Val Fleuri, 06800 Cagnes sur Mer Provence-Alpes-C\u00f4te d'Azur",
    "addr:housenumber":"15",
    "addr:postcode":"06800",
    "addr:street":"Chemin Du Val Fleuri;Mer",
    "iso:country":"FR",
    "sg:address":"15, Chemin du Val Fleuri, 06800 Cagnes sur Mer",
    "sg:orig_category":"Unclassifiable Establishments",
    "sg:phone":"+33 4 93 14 14 88",
    "sg:province":"Provence-Alpes-C\u00f4te d'Azur",
    "wof:name":"Richardson S.a.",
    "wof:placetype":"venue"
},
  "geometry": {"coordinates":[7.172461,43.662235],"type":"Point"}
}