{
  "type": "Feature",
  "properties": {
    "iso:country":"FR",
    "sg:address":"B.P. 29",
    "sg:city":"Lacaune^^Sagnens 81230 Lacaune",
    "sg:orig_category":"Non-Classified Establishments",
    "sg:phone":"+33 5 63 37 81 31",
    "sg:postcode":"81230",
    "sg:province":"Midi Pyr\u00e9n\u00e9es",
    "wof:name":"Etablissements R. Cabrol S.a.r.l.",
    "wof:placetype":"venue"
},
  "geometry": {"coordinates":[2.691754,43.707535],"type":"Point"}
}