{
  "type": "Feature",
  "properties": {
    "iso:country":"FR",
    "sg:address":"2, Rue du Port Saint Jean, 28260 Saussay",
    "sg:city":"Saussay",
    "sg:orig_category":"Unclassifiable Establishments",
    "sg:phone":"+33 2 37 41 49 90",
    "sg:postcode":"28260",
    "sg:province":"Centre",
    "wof:name":"Siaco S.a.",
    "wof:placetype":"venue"
},
  "geometry": {"coordinates":[1.386779,48.824169],"type":"Point"}
}