{
  "type": "Feature",
  "properties": {
    "iso:country":"FR",
    "sg:address":"March\u00e9 de Gros Rochepinard",
    "sg:city":"Tours",
    "sg:orig_category":"Unclassifiable Establishments",
    "sg:phone":"+33 2 47 32 22 00",
    "sg:postcode":"37000",
    "sg:province":"Centre",
    "wof:name":"Estivin Logistique Services S.a.",
    "wof:placetype":"venue"
},
  "geometry": {"coordinates":[0.715469,47.376244],"type":"Point"}
}