{
  "type": "Feature",
  "properties": {
    "iso:country":"FR",
    "sg:address":"157, Rue de Roubaix, 59200 Tourcoing",
    "sg:orig_category":"Unclassifiable Establishments",
    "sg:phone":"+33 3 20 81 30 60",
    "sg:province":"Nord Pas-de-Calais",
    "wof:name":"Standard Wool France S.a.",
    "wof:placetype":"venue"
},
  "geometry": {"coordinates":[3.167716,50.709469],"type":"Point"}
}