{
  "type": "Feature",
  "properties": {
    "addr:full":"505 Route Des Lucioles Antipolis Navigator 06560 Valbonne Provence-Alpes-C\u00f4te d'Azur",
    "addr:housenumber":"505",
    "addr:postcode":"06560",
    "addr:street":"Route Des Lucioles;Navigator",
    "iso:country":"FR",
    "sg:address":"505 Route Des Lucioles",
    "sg:city":"Antipolis Navigator 06560 Valbonne",
    "sg:classifiers":[
        {
            "category":"Communications",
            "subcategory":"Television Station",
            "type":"Services"
        }
    ],
    "sg:phone":"+33 4 92 96 11 00",
    "sg:province":"Provence-Alpes-C\u00f4te d'Azur",
    "sg:tags":[
        "equipment",
        "optical",
        "instrument",
        "telecommunication",
        "precision"
    ],
    "wof:name":"Philips Semi Conducteur",
    "wof:placetype":"venue"
},
  "geometry": {"coordinates":[7.031405,43.631126],"type":"Point"}
}