{
  "type": "Feature",
  "properties": {
    "addr:full":"10 rue Duguay Trouin; Douarnenez Midi Pyr\u00e9n\u00e9es",
    "addr:housenumber":"10",
    "addr:street":"Rue Duguay Trouin",
    "iso:country":"FR",
    "sg:address":"10 rue Duguay Trouin; Douarnenez",
    "sg:classifiers":[
        {
            "category":"Banks & Credit Unions",
            "subcategory":"Bank",
            "type":"Services"
        }
    ],
    "sg:phone":"+33 3398922433",
    "sg:province":"Midi Pyr\u00e9n\u00e9es",
    "wof:name":"Cr\u00e9dit Lyonnais",
    "wof:placetype":"venue"
},
  "geometry": {"coordinates":[-4.329654,48.092964],"type":"Point"}
}