{
  "type": "Feature",
  "properties": {
    "addr:full":"5 all\u00e9e des Ch\u00eanes 06906 SOPHIA ANTIPOLIS CEDEX Aquitaine",
    "addr:housenumber":"5",
    "addr:postcode":"06906",
    "addr:street":"Alle\u0301E Des Che\u0302Nes",
    "iso:country":"FR",
    "sg:address":"5 all\u00e9e des Ch\u00eanes 06906 SOPHIA ANTIPOLIS CEDEX",
    "sg:classifiers":[
        {
            "category":"Food & Beverages",
            "subcategory":"Groceries & Convenience Stores",
            "type":"Retail Goods"
        }
    ],
    "sg:phone":"+33 4 93 12 23 07",
    "sg:province":"Aquitaine",
    "sg:tags":[
        "frozen",
        "goods",
        "baked"
    ],
    "wof:name":"Gastronomie De France Sa",
    "wof:placetype":"venue"
},
  "geometry": {"coordinates":[-73.522232,41.073818],"type":"Point"}
}