{
  "type": "Feature",
  "properties": {
    "iso:country":"FR",
    "sg:address":"10, Rue Edouard Belin, 25400 Exincourt",
    "sg:orig_category":"Non-Classified Establishments",
    "sg:phone":"+33 3 81 95 52 24",
    "sg:postcode":"25400",
    "sg:province":"Franche Comt\u00e9",
    "wof:name":"Air Pur Industries S.a.r.l.",
    "wof:placetype":"venue"
},
  "geometry": {"coordinates":[6.823838,47.496609],"type":"Point"}
}