{
  "type": "Feature",
  "properties": {
    "iso:country":"FR",
    "sg:address":"83, Boucle de la Ram\u00e9e, 38070 Saint Quentin Fallavier",
    "sg:orig_category":"Non-Classified Establishments",
    "sg:phone":"+33 4 74 94 48 17",
    "sg:postcode":"38070",
    "sg:province":"Rhone-Alpes",
    "wof:name":"D\u00e9comi France S.a.r.l.",
    "wof:placetype":"venue"
},
  "geometry": {"coordinates":[5.104155,45.652126],"type":"Point"}
}