{
  "type": "Feature",
  "properties": {
    "addr:full":"83, Boucle de la Ram\u00e9e, 38070 Saint Quentin Fallavier Rhone-Alpes 38070",
    "addr:housenumber":"83",
    "addr:postcode":"38070;38070",
    "addr:street":"Boucle De La Rame\u0301E",
    "iso:country":"FR",
    "sg:address":"83, Boucle de la Ram\u00e9e, 38070 Saint Quentin Fallavier",
    "sg:orig_category":"Non-Classified Establishments",
    "sg:phone":"+33 4 74 94 48 17",
    "sg:postcode":"38070",
    "sg:province":"Rhone-Alpes",
    "wof:name":"D\u00e9comi France S.a.r.l.",
    "wof:placetype":"venue"
},
  "geometry": {"coordinates":[5.104155,45.652126],"type":"Point"}
}