{
  "type": "Feature",
  "properties": {
    "iso:country":"FR",
    "sg:address":"73 Rue Des Grandes Arcades 67000 Strasbourg",
    "sg:city":"Strasbourg",
    "sg:classifiers":[
        {
            "category":"Real Estate",
            "subcategory":"Surveying",
            "type":"Services"
        }
    ],
    "sg:phone":"+33 3 88 32 19 33",
    "sg:postcode":"67000",
    "sg:province":"Alsace",
    "sg:tags":[
        "leather",
        "raw",
        "material",
        "-",
        "shoe"
    ],
    "wof:name":"Fourrures Au Canada Sa",
    "wof:placetype":"venue"
},
  "geometry": {"coordinates":[7.74771,48.582119],"type":"Point"}
}