{
  "type": "Feature",
  "properties": {
    "iso:country":"FR",
    "sg:address":"ZI de Kerbriand",
    "sg:city":"Plouigneau",
    "sg:orig_category":"Unclassifiable Establishments",
    "sg:phone":"+33 2 98 79 81 00",
    "sg:postcode":"29610",
    "sg:province":"Bretagne",
    "wof:name":"Agrimages S.a.r.l.",
    "wof:placetype":"venue"
},
  "geometry": {"coordinates":[-3.701579,48.569355],"type":"Point"}
}