{
  "type": "Feature",
  "properties": {
    "iso:country":"FR",
    "sg:address":"9, Rue des Longues Raies - ZI des Garennes, 78440 Gargenville",
    "sg:orig_category":"Non-Classified Establishments",
    "sg:phone":"+33 1 30 93 74 84",
    "sg:province":"Ile de France",
    "wof:name":"G.m.i. S.a.r.l. - Gravure M\u00e9canique Industrielle",
    "wof:placetype":"venue"
},
  "geometry": {"coordinates":[1.81015,48.989475],"type":"Point"}
}