{
  "type": "Feature",
  "properties": {
    "addr:full":"114 Rue Leon Geffroy 94400 Vitry Sur Seine Ile de France 94400",
    "addr:housenumber":"114",
    "addr:postcode":"94400;94400",
    "addr:street":"Rue Leon Geffroy;France",
    "iso:country":"FR",
    "sg:address":"114 Rue Leon Geffroy 94400 Vitry Sur Seine",
    "sg:classifiers":[
        {
            "category":"Shopping",
            "type":"Retail Goods"
        }
    ],
    "sg:phone":"+33 1 55 53 14 00",
    "sg:postcode":"94400",
    "sg:province":"Ile de France",
    "sg:tags":[
        "metallurgy",
        "finished",
        "-",
        "metalworking",
        "metallic"
    ],
    "wof:name":"Espace Metal",
    "wof:placetype":"venue"
},
  "geometry": {"coordinates":[2.407725,48.782158],"type":"Point"}
}