{
  "type": "Feature",
  "properties": {
    "iso:country":"FR",
    "sg:address":"41 R Jean Jaur\u00e8s 29120 Pont L'Abb\u00e9",
    "sg:city":"Combrit",
    "sg:classifiers":[
        {
            "category":"Food & Beverages",
            "subcategory":"Groceries & Convenience Stores",
            "type":"Retail Goods"
        }
    ],
    "sg:phone":"+33 2 98 66 03 10",
    "sg:postcode":"29120",
    "sg:province":"Bretagne",
    "sg:tags":[
        "product",
        "grain",
        "cereal",
        "related"
    ],
    "wof:name":"Amo Moulins Du Finistere",
    "wof:placetype":"venue"
},
  "geometry": {"coordinates":[-83.347374,31.756863],"type":"Point"}
}