{
  "type": "Feature",
  "properties": {
    "addr:full":"Grande Rue - Le Chalency Perrecy les Forges Bourgogne 71420",
    "addr:postcode":"71420",
    "addr:street":"Grande Rue Le;Perrecy Les Forges Bourgogne",
    "iso:country":"FR",
    "sg:address":"Grande Rue - Le Chalency",
    "sg:city":"Perrecy les Forges",
    "sg:orig_category":"Non-Classified Establishments",
    "sg:phone":"+33 3 85 79 30 65",
    "sg:postcode":"71420",
    "sg:province":"Bourgogne",
    "wof:name":"S.c.t.m. S.a. - Soci\u00e9t\u00e9 De Chaudronnerie Tuyauterie Perrecycoise",
    "wof:placetype":"venue"
},
  "geometry": {"coordinates":[4.215219,46.617085],"type":"Point"}
}