{
  "type": "Feature",
  "properties": {
    "iso:country":"FR",
    "sg:address":"Av. Laure Monsarrat",
    "sg:city":"Saint Paul Cap de Joux",
    "sg:orig_category":"Unclassifiable Establishments",
    "sg:phone":"+33 5 63 82 54 90",
    "sg:postcode":"81220",
    "sg:province":"Midi Pyr\u00e9n\u00e9es",
    "wof:name":"Marquier S.a.",
    "wof:placetype":"venue"
},
  "geometry": {"coordinates":[1.97387,43.649025],"type":"Point"}
}