{
  "type": "Feature",
  "properties": {
    "addr:full":"Mas Des Tilleuls 66680 Canoh\u00e9s Languedoc-Roussillon 66680",
    "addr:postcode":"66680;66680",
    "addr:street":"Canohe\u0301S",
    "iso:country":"FR",
    "sg:address":"Mas Des Tilleuls 66680 Canoh\u00e9s",
    "sg:classifiers":[
        {
            "category":"Professional",
            "subcategory":"Computer Services",
            "type":"Services"
        }
    ],
    "sg:phone":"+33 4 68 68 39 68",
    "sg:postcode":"66680",
    "sg:province":"Languedoc-Roussillon",
    "sg:tags":[
        "information",
        "technology",
        "software"
    ],
    "wof:name":"Pyrescom Sa",
    "wof:placetype":"venue"
},
  "geometry": {"coordinates":[2.83193,42.660179],"type":"Point"}
}