{
  "type": "Feature",
  "properties": {
    "addr:full":"22 rue Pierre Mend\u00e8s-France 77200 Torcy Ile de France 77200",
    "addr:housenumber":"22",
    "addr:postcode":"77200;ile;77200",
    "addr:street":"Rue Pierre Mende\u0300S-France;France",
    "iso:country":"FR",
    "sg:address":"22 rue Pierre Mend\u00e8s-France 77200 Torcy",
    "sg:classifiers":[
        {
            "category":"Professional",
            "subcategory":"Engineering",
            "type":"Services"
        }
    ],
    "sg:phone":"+33 1 60 17 12 63",
    "sg:postcode":"77200",
    "sg:province":"Ile de France",
    "sg:tags":[
        "application",
        "engineer"
    ],
    "wof:name":"Dorr-oliver France Sarl",
    "wof:placetype":"venue"
},
  "geometry": {"coordinates":[2.653839,48.838253],"type":"Point"}
}