{
  "type": "Feature",
  "properties": {
    "iso:country":"FR",
    "sg:address":"17, Rue Marcel Sembat, 21000 Dijon",
    "sg:city":"Dijon",
    "sg:orig_category":"Unclassifiable Establishments",
    "sg:phone":"+33 3 80 52 53 58",
    "sg:postcode":"21000",
    "sg:province":"Bourgogne",
    "wof:name":"Cocard S.a.r.l.",
    "wof:placetype":"venue"
},
  "geometry": {"coordinates":[5.022473,47.298817],"type":"Point"}
}