{
  "type": "Feature",
  "properties": {
    "iso:country":"FR",
    "sg:address":"Boulevard Gilloux Et Raymond 84200 Carpentras",
    "sg:classifiers":[
        {
            "category":"Food & Beverages",
            "subcategory":"Fruits & Vegetables",
            "type":"Retail Goods"
        }
    ],
    "sg:phone":"+33 4 90 67 24 81",
    "sg:province":"Champagne",
    "sg:tags":[
        "preserve",
        "product",
        "related"
    ],
    "wof:name":"Conserves Guintrand",
    "wof:placetype":"venue"
},
  "geometry": {"coordinates":[5.046923,44.046974],"type":"Point"}
}