{
  "type": "Feature",
  "properties": {
    "iso:country":"FR",
    "sg:address":"1306 Route Argent Zi 38510 Morestel",
    "sg:classifiers":[
        {
            "category":"Autos & Motor Vehicles",
            "subcategory":"Automobile Sales",
            "type":"Retail Goods"
        }
    ],
    "sg:phone":"+33 4 74 80 01 68",
    "sg:postcode":"38510",
    "sg:province":"Rhone-Alpes",
    "sg:tags":[
        "equipment",
        "industrial",
        "transport"
    ],
    "wof:name":"Mecatiss Technique Service",
    "wof:placetype":"venue"
},
  "geometry": {"coordinates":[5.420305,45.650581],"type":"Point"}
}