{
  "type": "Feature",
  "properties": {
    "addr:full":"25, Bd Jean-Baptiste Lebas, 59000 Lille Nord Pas-de-Calais",
    "addr:housenumber":"25",
    "addr:postcode":"59000",
    "addr:street":"Bd Jean-Baptiste Lebas",
    "iso:country":"FR",
    "sg:address":"25, Bd Jean-Baptiste Lebas, 59000 Lille",
    "sg:orig_category":"Unclassifiable Establishments",
    "sg:phone":"+33 3 20 52 43 16",
    "sg:province":"Nord Pas-de-Calais",
    "wof:name":"Lildom S.a. - Soci\u00e9t\u00e9 Lilloise De Camionnage \u00e0 Domicile",
    "wof:placetype":"venue"
},
  "geometry": {"coordinates":[3.069883,50.625095],"type":"Point"}
}