{
  "type": "Feature",
  "properties": {
    "addr:full":"49 Rue Des Acieries 42000 St Etienne Rhone-Alpes 42000",
    "addr:housenumber":"49",
    "addr:postcode":"42000;42000",
    "addr:street":"Rue Des Acieries",
    "iso:country":"FR",
    "sg:address":"49 Rue Des Acieries 42000 St Etienne",
    "sg:classifiers":[
        {
            "category":"Building & Trades",
            "subcategory":"Electrical",
            "type":"Services"
        }
    ],
    "sg:phone":"+33 4 77 92 27 30",
    "sg:postcode":"42000",
    "sg:province":"Rhone-Alpes",
    "sg:tags":[
        "electronic",
        "lighting",
        "equipment"
    ],
    "wof:name":"Sli France",
    "wof:placetype":"venue"
},
  "geometry": {"coordinates":[4.392132,45.456776],"type":"Point"}
}