{
  "type": "Feature",
  "properties": {
    "addr:full":"55 Rue Pierre Legrand 59800 Lille Nord Pas-de-Calais 59800",
    "addr:housenumber":"55",
    "addr:postcode":"59800;59800",
    "addr:street":"Rue Pierre Legrand",
    "iso:country":"FR",
    "sg:address":"55 Rue Pierre Legrand 59800 Lille",
    "sg:classifiers":[
        {
            "category":"Wholesale",
            "subcategory":"Medical Equipment & Supplies",
            "type":"Manufacturing & Wholesale Goods"
        }
    ],
    "sg:phone":"+33 3 20 04 41 71",
    "sg:postcode":"59800",
    "sg:province":"Nord Pas-de-Calais",
    "sg:tags":[
        "instrument",
        "health",
        "-",
        "precision"
    ],
    "wof:name":"Ets Proteor",
    "wof:placetype":"venue"
},
  "geometry": {"coordinates":[3.087065,50.632328],"type":"Point"}
}