{
  "type": "Feature",
  "properties": {
    "addr:full":"18, Av. Gustave Eiffel - ZI, 33608 Pessac C\u00e9dex^^18, Av. Gustave Eiffel - ZI, 33600 Pessac Pessac Aquitaine 33600",
    "addr:postcode":"33608;33600;33600",
    "addr:street":"18 Av. Gustave Eiffel Zi;Av. Gustave Eiffel Zi",
    "iso:country":"FR",
    "sg:address":"18, Av. Gustave Eiffel - ZI, 33608 Pessac C\u00e9dex^^18, Av. Gustave Eiffel - ZI, 33600 Pessac",
    "sg:city":"Pessac",
    "sg:orig_category":"Non-Classified Establishments",
    "sg:phone":"+33 5 57 89 16 78",
    "sg:postcode":"33600",
    "sg:province":"Aquitaine",
    "wof:name":"Balineau S.a.",
    "wof:placetype":"venue"
},
  "geometry": {"coordinates":[-0.630989,44.80616],"type":"Point"}
}