{
  "type": "Feature",
  "properties": {
    "addr:full":"916, Rte de Gen\u00e9ve, 74190 Le Fayet Rhone-Alpes",
    "addr:housenumber":"916",
    "addr:postcode":"74190",
    "addr:street":"Rte De Gene\u0301Ve;Fayet Rhone-Alpes",
    "iso:country":"FR",
    "sg:address":"916, Rte de Gen\u00e9ve, 74190 Le Fayet",
    "sg:orig_category":"Non-Classified Establishments",
    "sg:phone":"+33 4 50 78 10 54",
    "sg:province":"Rhone-Alpes",
    "wof:name":"Soci\u00e9t\u00e9 Rosset S.a.",
    "wof:placetype":"venue"
},
  "geometry": {"coordinates":[6.693217,45.904102],"type":"Point"}
}