{
  "type": "Feature",
  "properties": {
    "addr:full":"145 Rue Nicolas Louis Vauquelin 31100 Toulouse Midi Pyr\u00e9n\u00e9es 31100",
    "addr:housenumber":"145",
    "addr:postcode":"31100;31100",
    "addr:street":"Rue Nicolas Louis Vauquelin",
    "iso:country":"FR",
    "sg:address":"145 Rue Nicolas Louis Vauquelin 31100 Toulouse",
    "sg:classifiers":[
        {
            "category":"Government",
            "subcategory":"Department Of Motor Vehicles",
            "type":"Public Place"
        }
    ],
    "sg:phone":"+33 5 61 44 30 48",
    "sg:postcode":"31100",
    "sg:province":"Midi Pyr\u00e9n\u00e9es",
    "sg:tags":[
        "equipment",
        "industrial",
        "transport",
        "motor-cars"
    ],
    "wof:name":"Pelras Sa",
    "wof:placetype":"venue"
},
  "geometry": {"coordinates":[1.403496,43.582741],"type":"Point"}
}