{
  "type": "Feature",
  "properties": {
    "iso:country":"FR",
    "sg:address":"232 rue Jean Jaur\u00e8s; Fr\u00e9jus; 83600",
    "sg:classifiers":[
        {
            "category":"Banks & Credit Unions",
            "subcategory":"Bank",
            "type":"Services"
        }
    ],
    "sg:phone":"+33 3394512213",
    "sg:province":"Champagne",
    "wof:name":"Banque Nationale De Paris",
    "wof:placetype":"venue"
},
  "geometry": {"coordinates":[6.736984,43.433838],"type":"Point"}
}