{
  "type": "Feature",
  "properties": {
    "addr:full":"16, Rue Fernand Pelloutier, 38130 Echirolles Rhone-Alpes",
    "addr:housenumber":"16",
    "addr:postcode":"38130",
    "addr:street":"Rue Fernand Pelloutier",
    "iso:country":"FR",
    "sg:address":"16, Rue Fernand Pelloutier, 38130 Echirolles",
    "sg:orig_category":"Non-Classified Establishments",
    "sg:phone":"+33 4 76 09 33 70",
    "sg:province":"Rhone-Alpes",
    "wof:name":"Technico Plast S.a.",
    "wof:placetype":"venue"
},
  "geometry": {"coordinates":[5.715595,45.152164],"type":"Point"}
}