{
  "type": "Feature",
  "properties": {
    "iso:country":"FR",
    "sg:address":"3 rue de Bruxelles 14120 Mondeville",
    "sg:city":"Mondeville",
    "sg:classifiers":[
        {
            "category":"Manufacturing",
            "subcategory":"Electronics",
            "type":"Manufacturing & Wholesale Goods"
        }
    ],
    "sg:phone":"+33 2 31 35 43 54",
    "sg:postcode":"14120",
    "sg:province":"Basse Normandie",
    "sg:tags":[
        "measurement"
    ],
    "wof:name":"Digit Concept S.a.",
    "wof:placetype":"venue"
},
  "geometry": {"coordinates":[-0.308062,49.170742],"type":"Point"}
}