{
  "type": "Feature",
  "properties": {
    "addr:full":"12340 Cruejouls Midi Pyr\u00e9n\u00e9es 12340",
    "addr:housenumber":"12340",
    "addr:postcode":"12340",
    "addr:street":"Cruejouls Midi Pyre\u0301Ne\u0301Es",
    "iso:country":"FR",
    "sg:address":"12340 Cruejouls",
    "sg:classifiers":[
        {
            "category":"Manufacturing",
            "subcategory":"Chemicals & Compounds",
            "type":"Manufacturing & Wholesale Goods"
        }
    ],
    "sg:phone":"+33 5 65 44 93 82",
    "sg:postcode":"12340",
    "sg:province":"Midi Pyr\u00e9n\u00e9es",
    "sg:tags":[
        "pharmaceutical",
        "chemistry",
        "-",
        "by-product"
    ],
    "wof:name":"Burguiere Verdeille (houilleres De Crejouls)",
    "wof:placetype":"venue"
},
  "geometry": {"coordinates":[2.856818,44.444103],"type":"Point"}
}