{
  "type": "Feature",
  "properties": {
    "iso:country":"FR",
    "sg:address":"rue Freycinet 77400 Lagny sur Marne",
    "sg:orig_category":"Field Kitchens, Trailer Mounted Kitchens",
    "sg:phone":"+33 1 64 12 17 77",
    "sg:postcode":"77400",
    "sg:province":"Ile de France",
    "wof:name":"Groupe Pkl S.a.",
    "wof:placetype":"venue"
},
  "geometry": {"coordinates":[2.683602,48.877403],"type":"Point"}
}