{
  "type": "Feature",
  "properties": {
    "addr:full":"Za Meuni\u00e9res 38260 La C\u00f4te St Andr\u00e9 Rhone-Alpes",
    "addr:postcode":"38260",
    "addr:street":"Za Meunie\u0301Res;Co\u0302Te St",
    "iso:country":"FR",
    "sg:address":"Za",
    "sg:city":"Meuni\u00e9res 38260 La C\u00f4te St Andr\u00e9",
    "sg:classifiers":[
        {
            "category":"Communications",
            "subcategory":"Newspaper",
            "type":"Services"
        }
    ],
    "sg:phone":"+33 4 74 20 51 10",
    "sg:province":"Rhone-Alpes",
    "sg:tags":[
        "printing",
        "publishing"
    ],
    "wof:name":"Imprimerie Rochat Sa",
    "wof:placetype":"venue"
},
  "geometry": {"coordinates":[5.261475,45.392185],"type":"Point"}
}