{
  "type": "Feature",
  "properties": {
    "addr:full":"ZI de Ville James Gu\u00e9rande Pays de Loire 44350",
    "addr:postcode":"44350",
    "addr:street":"Zi De Ville James Gue\u0301Rande Pays",
    "iso:country":"FR",
    "sg:address":"ZI de Ville James",
    "sg:city":"Gu\u00e9rande",
    "sg:orig_category":"Unclassifiable Establishments",
    "sg:phone":"+33 2 40 24 83 31",
    "sg:postcode":"44350",
    "sg:province":"Pays de Loire",
    "wof:name":"B.s.i. C\u00f4te D'amour E.u.r.l.",
    "wof:placetype":"venue"
},
  "geometry": {"coordinates":[-2.429531,47.327911],"type":"Point"}
}