{
  "type": "Feature",
  "properties": {
    "iso:country":"FR",
    "sg:address":"route de Pont d'Ain 01250 Montagnat",
    "sg:classifiers":[
        {
            "category":"Wholesale",
            "subcategory":"Vending Machines",
            "type":"Manufacturing & Wholesale Goods"
        }
    ],
    "sg:phone":"+33 4 74 22 49 58",
    "sg:postcode":"01250",
    "sg:province":"Rhone-Alpes",
    "sg:tags":[
        "filling",
        "bottle"
    ],
    "wof:name":"Intech S.a.r.l.",
    "wof:placetype":"venue"
},
  "geometry": {"coordinates":[5.28424,46.17012],"type":"Point"}
}