{
  "type": "Feature",
  "properties": {
    "addr:full":"Zone Portuaire 44550 Montoir De Bretagne Pays de Loire 44550",
    "addr:postcode":"44550;44550",
    "addr:street":"Portuaire",
    "iso:country":"FR",
    "sg:address":"Zone Portuaire 44550 Montoir De Bretagne",
    "sg:classifiers":[
        {
            "category":"Farming",
            "subcategory":"Farm",
            "type":"Manufacturing & Wholesale Goods"
        }
    ],
    "sg:phone":"+33 2 40 17 16 13",
    "sg:postcode":"44550",
    "sg:province":"Pays de Loire",
    "sg:tags":[
        "horticulture",
        "agriculture",
        "livestock"
    ],
    "wof:name":"Hydro Agri France",
    "wof:placetype":"venue"
},
  "geometry": {"coordinates":[-2.153179,47.327759],"type":"Point"}
}