{
  "type": "Feature",
  "properties": {
    "addr:full":"83, Chemin de l'Olivet, 06110 Le Cannet Midi Pyr\u00e9n\u00e9es",
    "addr:housenumber":"83",
    "addr:postcode":"06110",
    "addr:street":"Chemin De L'Olivet",
    "iso:country":"FR",
    "sg:address":"83, Chemin de l'Olivet, 06110 Le Cannet",
    "sg:orig_category":"Non-Classified Establishments",
    "sg:phone":"+33 4 93 45 03 11",
    "sg:province":"Midi Pyr\u00e9n\u00e9es",
    "wof:name":"Editions A.i.o. S.a.r.l.",
    "wof:placetype":"venue"
},
  "geometry": {"coordinates":[6.99483,43.572483],"type":"Point"}
}