{
  "type": "Feature",
  "properties": {
    "addr:full":"64, Av. de Pessicart, 06100 Nice",
    "addr:postcode":"06100",
    "addr:street":"64 Av. De Pessicart",
    "iso:country":"FR",
    "sg:address":"64, Av. de Pessicart, 06100 Nice",
    "sg:orig_category":"Non-Classified Establishments",
    "sg:phone":"+33 4 93 97 00 10",
    "wof:name":"A.e.e.e. S.a. - Assainissement Entretien Environnement Ecologie",
    "wof:placetype":"venue"
},
  "geometry": {"coordinates":[7.2495,43.71331],"type":"Point"}
}