{
  "type": "Feature",
  "properties": {
    "iso:country":"FR",
    "sg:address":"Le Champety 38309 Bourgoin Jallieu Cedex",
    "sg:classifiers":[
        {
            "category":"Farming",
            "subcategory":"Farm",
            "type":"Manufacturing & Wholesale Goods"
        }
    ],
    "sg:phone":"+33 4 74 43 52 30",
    "sg:province":"Centre",
    "sg:tags":[
        "horticulture",
        "agriculture",
        "livestock"
    ],
    "wof:name":"Klasmann France Sarl",
    "wof:placetype":"venue"
},
  "geometry": {"coordinates":[5.28195,45.589127],"type":"Point"}
}