{
  "type": "Feature",
  "properties": {
    "addr:full":"Rue De La Feyssine 69100 Villeurbanne Rhone-Alpes 69100",
    "addr:postcode":"69100;69100",
    "addr:street":"Rue De La Feyssine",
    "iso:country":"FR",
    "sg:address":"Rue De La Feyssine 69100 Villeurbanne",
    "sg:classifiers":[
        {
            "category":"Utilities",
            "type":"Services"
        }
    ],
    "sg:phone":"+33 810 00 07 77",
    "sg:postcode":"69100",
    "sg:province":"Rhone-Alpes",
    "sg:tags":[
        "raw",
        "energy",
        "material"
    ],
    "wof:name":"Compagnie Generale Des Eaux",
    "wof:placetype":"venue"
},
  "geometry": {"coordinates":[4.88995,45.784309],"type":"Point"}
}