{
  "type": "Feature",
  "properties": {
    "iso:country":"FR",
    "sg:address":"B.P. 127, 42613 Andr\u00e9zieux Bouth\u00e9on C\u00e9dex^^Rue Charles Voisin - ZAC Migalon, 42160 Andr\u00e9zieux Bouth\u00e9",
    "sg:orig_category":"Non-Classified Establishments",
    "sg:phone":"+33 4 77 36 26 40",
    "sg:province":"Rhone-Alpes",
    "wof:name":"Giraud Logistique S.a.s.",
    "wof:placetype":"venue"
},
  "geometry": {"coordinates":[4.25674,45.52943],"type":"Point"}
}