{
  "type": "Feature",
  "properties": {
    "addr:full":"B.P. 68, 84302 Cavaillon C\u00e9dex^^ZAC du Min, 84300 Cavaillon Languedoc-Roussillon",
    "addr:postcode":"84302;84300",
    "addr:street":"B.P. 68;Min",
    "iso:country":"FR",
    "sg:address":"B.P. 68, 84302 Cavaillon C\u00e9dex^^ZAC du Min, 84300 Cavaillon",
    "sg:orig_category":"Non-Classified Establishments",
    "sg:phone":"+33 4 90 06 67 67",
    "sg:province":"Languedoc-Roussillon",
    "wof:name":"Malagutti Vezinhet S.a.",
    "wof:placetype":"venue"
},
  "geometry": {"coordinates":[5.039415,43.837685],"type":"Point"}
}