{
  "type": "Feature",
  "properties": {
    "iso:country":"FR",
    "sg:address":"rue Ir\u00e8ne Joliot-Curie 38320 Eybens",
    "sg:classifiers":[
        {
            "category":"Manufacturing",
            "subcategory":"Motor Vehicles & Parts",
            "type":"Manufacturing & Wholesale Goods"
        }
    ],
    "sg:phone":"+33 4 76 24 02 36",
    "sg:postcode":"38320",
    "sg:province":"Rhone-Alpes",
    "sg:tags":[
        "precision",
        "mechanic"
    ],
    "wof:name":"Gmp-atim S.a.",
    "wof:placetype":"venue"
},
  "geometry": {"coordinates":[5.74067,45.150036],"type":"Point"}
}