{
  "type": "Feature",
  "properties": {
    "addr:full":"45 R De Dijon 33100 Bordeaux Bordeaux Aquitaine 33100",
    "addr:housenumber":"45",
    "addr:postcode":"33100;33100",
    "addr:street":"R De Dijon",
    "iso:country":"FR",
    "sg:address":"45 R De Dijon 33100 Bordeaux",
    "sg:city":"Bordeaux",
    "sg:classifiers":[
        {
            "category":"Professional",
            "subcategory":"Business Services",
            "type":"Services"
        }
    ],
    "sg:phone":"+33 5 57 80 12 00",
    "sg:postcode":"33100",
    "sg:province":"Aquitaine",
    "sg:tags":[
        "training",
        "advice"
    ],
    "wof:name":"Ogec Ste Marie La Bastide",
    "wof:placetype":"venue"
},
  "geometry": {"coordinates":[-0.552071,44.842903],"type":"Point"}
}