{
  "type": "Feature",
  "properties": {
    "iso:country":"FR",
    "sg:address":"75755 Paris C\u00e9dex 15^^33, Av. du Maine - Tour Maine Montparnasse, 75015 Paris",
    "sg:orig_category":"Non-Classified Establishments",
    "sg:phone":"+33 1 45 38 42 42",
    "sg:postcode":"75015",
    "sg:province":"Ile de France",
    "wof:name":"Eramet S.a.",
    "wof:placetype":"venue"
},
  "geometry": {"coordinates":[2.299265,48.841057],"type":"Point"}
}