{
  "type": "Feature",
  "properties": {
    "addr:full":"B.P. 70, 91422 Morangis C\u00e9dex^^4bis, Rue du Docteur Schweitzer, 91420 Morangis Ile de France 91420",
    "addr:postcode":"91422;91420;ile;91420",
    "addr:street":"B.P. 70;Rue Du Docteur Schweitzer;France",
    "iso:country":"FR",
    "sg:address":"B.P. 70, 91422 Morangis C\u00e9dex^^4bis, Rue du Docteur Schweitzer, 91420 Morangis",
    "sg:orig_category":"Non-Classified Establishments",
    "sg:phone":"+33 1 55 23 57 00",
    "sg:postcode":"91420",
    "sg:province":"Ile de France",
    "wof:name":"Carboxyque Fran\u00e7aise S.a.",
    "wof:placetype":"venue"
},
  "geometry": {"coordinates":[2.332276,48.704742],"type":"Point"}
}