{
  "type": "Feature",
  "properties": {
    "iso:country":"FR",
    "sg:address":"10 Place Alfonse Jourdain",
    "sg:city":"Toulouse",
    "sg:classifiers":[
        {
            "category":"Banks & Credit Unions",
            "subcategory":"Financial Services",
            "type":"Services"
        }
    ],
    "sg:phone":"+33 5 62 30 15 15",
    "sg:postcode":"31000",
    "sg:province":"Midi Pyr\u00e9n\u00e9es",
    "sg:tags":[
        "banking",
        "finance",
        "insurance"
    ],
    "wof:name":"Irdi Sa",
    "wof:placetype":"venue"
},
  "geometry": {"coordinates":[1.430062,43.611145],"type":"Point"}
}