{
  "type": "Feature",
  "properties": {
    "addr:full":"Rte de Castets Saint Paul l\u00e8s Dax Aquitaine 40990",
    "addr:postcode":"40990",
    "addr:street":"Rte De Castets",
    "iso:country":"FR",
    "sg:address":"Rte de Castets",
    "sg:city":"Saint Paul l\u00e8s Dax",
    "sg:orig_category":"Non-Classified Establishments",
    "sg:phone":"+33 5 58 91 87 99",
    "sg:postcode":"40990",
    "sg:province":"Aquitaine",
    "wof:name":"Brunateau S.a.",
    "wof:placetype":"venue"
},
  "geometry": {"coordinates":[-1.116004,43.709412],"type":"Point"}
}