{
  "type": "Feature",
  "properties": {
    "addr:full":"4 Rue Des Violettes 68210 Ballersdorf Ballersdorf Alsace 68210",
    "addr:housenumber":"4",
    "addr:postcode":"68210;68210",
    "addr:street":"Rue Des Violettes;Ballersdorf",
    "iso:country":"FR",
    "sg:address":"4 Rue Des Violettes 68210 Ballersdorf",
    "sg:city":"Ballersdorf",
    "sg:classifiers":[
        {
            "category":"Utilities",
            "subcategory":"Electric",
            "type":"Services"
        }
    ],
    "sg:phone":"+33 3 89 25 04 76",
    "sg:postcode":"68210",
    "sg:province":"Alsace",
    "sg:tags":[
        "electricity",
        "electronic",
        "electrical",
        "equipment"
    ],
    "wof:name":"Electro Mecanique Bihl Et Compagnie Sarl",
    "wof:placetype":"venue"
},
  "geometry": {"coordinates":[7.161477,47.627659],"type":"Point"}
}