{
  "type": "Feature",
  "properties": {
    "addr:full":"41 Av Martyrs Du 24 Ao\u00fbt 10800 Buch\u00e8res Champagne 10800",
    "addr:postcode":"10800;10800",
    "addr:street":"41 Av Martyrs Du 24 Aou\u0302T;Champagne",
    "iso:country":"FR",
    "sg:address":"41 Av Martyrs Du 24 Ao\u00fbt 10800 Buch\u00e8res",
    "sg:classifiers":[
        {
            "category":"Wholesale",
            "subcategory":"Farm Supplies",
            "type":"Manufacturing & Wholesale Goods"
        }
    ],
    "sg:phone":"+33 3 25 41 78 50",
    "sg:postcode":"10800",
    "sg:province":"Champagne",
    "sg:tags":[
        "-",
        "machine",
        "equipment",
        "engineering",
        "machinery",
        "mechanical",
        "agriculture"
    ],
    "wof:name":"Tract Equipement Sa",
    "wof:placetype":"venue"
},
  "geometry": {"coordinates":[4.10615,48.240181],"type":"Point"}
}