{
  "type": "Feature",
  "properties": {
    "iso:country":"FR",
    "sg:address":"41, Rue Edouard le Corbusier, 94035 Cr\u00e9teil C\u00e9dex",
    "sg:orig_category":"Non-Classified Establishments",
    "sg:phone":"+33 1 49 56 50 00",
    "sg:province":"Centre",
    "wof:name":"Avis Fleet Services S.a.",
    "wof:placetype":"venue"
},
  "geometry": {"coordinates":[2.45203,48.788891],"type":"Point"}
}