{
  "type": "Feature",
  "properties": {
    "addr:full":"Lieu dit Pirolles 43590 BEAUZAC Beauzac Auvergne 43590",
    "addr:postcode":"43590;beauzac;43590",
    "addr:street":"Lieu Dit Pirolles",
    "iso:country":"FR",
    "sg:address":"Lieu dit Pirolles 43590 BEAUZAC",
    "sg:city":"Beauzac",
    "sg:classifiers":[
        {
            "category":"Food & Beverages",
            "subcategory":"Cheese",
            "type":"Retail Goods"
        }
    ],
    "sg:phone":"+33 4 71 61 47 91",
    "sg:postcode":"43590",
    "sg:province":"Auvergne",
    "wof:name":"C.f.v.a. Sas",
    "wof:placetype":"venue"
},
  "geometry": {"coordinates":[4.113391,45.269756],"type":"Point"}
}