{
  "type": "Feature",
  "properties": {
    "iso:country":"FR",
    "sg:address":"3, Rue Saint Eloi, 49123 Ingrandes",
    "sg:orig_category":"Unclassifiable Establishments",
    "sg:phone":"+33 2 41 39 20 48",
    "sg:province":"Pays de Loire",
    "wof:name":"Grandin S.a.r.l.",
    "wof:placetype":"venue"
},
  "geometry": {"coordinates":[-0.921994,47.40406],"type":"Point"}
}