{
  "type": "Feature",
  "properties": {
    "iso:country":"FR",
    "sg:address":"5 Avenue Duquesne 75007 Paris",
    "sg:classifiers":[
        {
            "category":"Travel",
            "subcategory":"Hotels & Motels",
            "type":"Entertainment"
        }
    ],
    "sg:phone":"+33 1 47 05 12 05",
    "sg:postcode":"75007",
    "sg:province":"Ile de France",
    "sg:tags":[
        "hotels",
        "business",
        "restaurant"
    ],
    "wof:name":"Derby Eiffel Hotel Sa",
    "wof:placetype":"venue"
},
  "geometry": {"coordinates":[2.307302,48.853718],"type":"Point"}
}