{
  "type": "Feature",
  "properties": {
    "addr:full":"4, Rue Louis Colas, 64600 Anglet Anglet Aquitaine 64600",
    "addr:housenumber":"4",
    "addr:postcode":"64600;64600",
    "addr:street":"Rue Louis Colas",
    "iso:country":"FR",
    "sg:address":"4, Rue Louis Colas, 64600 Anglet",
    "sg:city":"Anglet",
    "sg:orig_category":"Unclassifiable Establishments",
    "sg:phone":"+33 5 59 52 14 81",
    "sg:postcode":"64600",
    "sg:province":"Aquitaine",
    "wof:name":"Danielle S.a.r.l.",
    "wof:placetype":"venue"
},
  "geometry": {"coordinates":[-1.506147,43.482887],"type":"Point"}
}