{
  "type": "Feature",
  "properties": {
    "addr:full":"Technopole de Ch\u00e2teau Gombert - B\u00e2t. C Marseille Provence-Alpes-C\u00f4te d'Azur 13013",
    "addr:housenumber":"ba\u0302t c",
    "addr:postcode":"13013",
    "addr:street":"Gombert",
    "iso:country":"FR",
    "sg:address":"Technopole de Ch\u00e2teau Gombert - B\u00e2t. C",
    "sg:city":"Marseille",
    "sg:orig_category":"Unclassifiable Establishments",
    "sg:phone":"+33 4 91 95 50 17",
    "sg:postcode":"13013",
    "sg:province":"Provence-Alpes-C\u00f4te d'Azur",
    "wof:name":"Articc M\u00e9diterran\u00e9e S.a.",
    "wof:placetype":"venue"
},
  "geometry": {"coordinates":[5.417715,43.322464],"type":"Point"}
}