{
  "type": "Feature",
  "properties": {
    "iso:country":"FR",
    "sg:address":"208 Rue Robert Schuman Za Des Uselles 77350 Le Mee Sur Seine",
    "sg:classifiers":[
        {
            "category":"Professional",
            "subcategory":"Engineering",
            "type":"Services"
        }
    ],
    "sg:phone":"+33 1 64 79 75 80",
    "sg:postcode":"77350",
    "sg:province":"Ile de France",
    "sg:tags":[
        "machine",
        "-",
        "mechanical"
    ],
    "wof:name":"Ems Electronique Mecanique Services",
    "wof:placetype":"venue"
},
  "geometry": {"coordinates":[2.63157,48.542267],"type":"Point"}
}