{
  "type": "Feature",
  "properties": {
    "iso:country":"FR",
    "sg:address":"Rue de l'Usine",
    "sg:city":"Witry l\u00e8s Reims",
    "sg:orig_category":"Unclassifiable Establishments",
    "sg:phone":"+33 3 26 50 52 10",
    "sg:postcode":"51420",
    "sg:province":"Champagne",
    "wof:name":"Secan S.a.",
    "wof:placetype":"venue"
},
  "geometry": {"coordinates":[4.117264,49.294453],"type":"Point"}
}