{
  "type": "Feature",
  "properties": {
    "addr:full":"13, Rue des Serruriers, 57070 Metz Lorraine",
    "addr:housenumber":"13",
    "addr:postcode":"57070",
    "addr:street":"Rue Des Serruriers",
    "iso:country":"FR",
    "sg:address":"13, Rue des Serruriers, 57070 Metz",
    "sg:orig_category":"Unclassifiable Establishments",
    "sg:phone":"+33 3 87 36 50 05",
    "sg:province":"Lorraine",
    "wof:name":"Tout Inox Logistok S.a.",
    "wof:placetype":"venue"
},
  "geometry": {"coordinates":[6.240676,49.115414],"type":"Point"}
}