{
  "type": "Feature",
  "properties": {
    "addr:full":"Rte de Servies Damiatte Midi Pyr\u00e9n\u00e9es 81220",
    "addr:postcode":"81220",
    "addr:street":"Rte De Servies",
    "iso:country":"FR",
    "sg:address":"Rte de Servies",
    "sg:city":"Damiatte",
    "sg:orig_category":"Unclassifiable Establishments",
    "sg:phone":"+33 5 63 70 80 78",
    "sg:postcode":"81220",
    "sg:province":"Midi Pyr\u00e9n\u00e9es",
    "wof:name":"S.f.p. S.a. - Sud Fili\u00e8res Plast.",
    "wof:placetype":"venue"
},
  "geometry": {"coordinates":[1.975185,43.65147],"type":"Point"}
}