{
  "type": "Feature",
  "properties": {
    "addr:full":"42, Rue Brillat Savarin, 01100 Oyonnax Rhone-Alpes 01100",
    "addr:housenumber":"42",
    "addr:postcode":"01100;01100",
    "addr:street":"Rue Brillat Savarin",
    "iso:country":"FR",
    "sg:address":"42, Rue Brillat Savarin, 01100 Oyonnax",
    "sg:orig_category":"Non-Classified Establishments",
    "sg:phone":"+33 4 74 81 20 10",
    "sg:postcode":"01100",
    "sg:province":"Rhone-Alpes",
    "wof:name":"Cabinet Mermet S.a.",
    "wof:placetype":"venue"
},
  "geometry": {"coordinates":[5.645969,46.250523],"type":"Point"}
}