{
  "type": "Feature",
  "properties": {
    "addr:full":"Rte de Sermaz Neyron Rhone-Alpes 01700",
    "addr:postcode":"01700",
    "addr:street":"Rte De Sermaz;Rhone-Alpes",
    "iso:country":"FR",
    "sg:address":"Rte de Sermaz",
    "sg:city":"Neyron",
    "sg:orig_category":"Non-Classified Establishments",
    "sg:phone":"+33 4 78 23 45 58",
    "sg:postcode":"01700",
    "sg:province":"Rhone-Alpes",
    "wof:name":"S.e.b.m.o. S.a.r.l.",
    "wof:placetype":"venue"
},
  "geometry": {"coordinates":[4.96153,45.828629],"type":"Point"}
}