{
  "type": "Feature",
  "properties": {
    "addr:full":"69/73, Bd. Victor Hugo, 93585 Saint Ouen C\u00e9dex Ile-de-France",
    "addr:housenumber":"69 / 73",
    "addr:postcode":"93585;ce\u0301dex",
    "addr:street":"Bd. Victor Hugo",
    "iso:country":"FR",
    "sg:address":"69/73, Bd. Victor Hugo, 93585 Saint Ouen C\u00e9dex",
    "sg:orig_category":"Non-Classified Establishments",
    "sg:phone":"+33 1 40 12 70 99",
    "sg:province":"Ile-de-France",
    "wof:name":"S.a.p. S.a.r.l. - Soudures Alliages Produits",
    "wof:placetype":"venue"
},
  "geometry": {"coordinates":[2.328847,48.908745],"type":"Point"}
}