{
  "type": "Feature",
  "properties": {
    "addr:full":"Rue De Marais 59147 Gondecourt Nord Pas-de-Calais 59147",
    "addr:postcode":"59147;59147",
    "addr:street":"Rue De Marais",
    "iso:country":"FR",
    "sg:address":"Rue De Marais 59147 Gondecourt",
    "sg:classifiers":[
        {
            "category":"Manufacturing",
            "subcategory":"Chemicals & Compounds",
            "type":"Manufacturing & Wholesale Goods"
        }
    ],
    "sg:phone":"+33 3 20 62 95 00",
    "sg:postcode":"59147",
    "sg:province":"Nord Pas-de-Calais",
    "sg:tags":[
        "pharmaceutical",
        "chemistry",
        "-",
        "by-product"
    ],
    "wof:name":"Catry (ets) Sa",
    "wof:placetype":"venue"
},
  "geometry": {"coordinates":[2.986804,50.548714],"type":"Point"}
}