{
  "type": "Feature",
  "properties": {
    "iso:country":"FR",
    "sg:address":"Les Manteaux ZI 89330 ST JULIEN DU SAULT",
    "sg:city":"Villevallier",
    "sg:orig_category":"Fruits, Dried",
    "sg:phone":"+33 3 86 63 29 75",
    "sg:postcode":"89330",
    "sg:province":"Bourgogne",
    "wof:name":"Silvarem International Sarl",
    "wof:placetype":"venue"
},
  "geometry": {"coordinates":[3.164885,48.016033],"type":"Point"}
}