{
  "type": "Feature",
  "properties": {
    "addr:full":"1 Reims 51150 Ambonnay Champagne 51150",
    "addr:housenumber":"1",
    "addr:postcode":"51150;51150",
    "addr:street":"Reims;Champagne",
    "iso:country":"FR",
    "sg:address":"1",
    "sg:city":"Reims 51150 Ambonnay",
    "sg:classifiers":[
        {
            "category":"Food Court",
            "type":"Food & Drink"
        }
    ],
    "sg:phone":"+33 3 26 57 01 65",
    "sg:postcode":"51150",
    "sg:province":"Champagne",
    "sg:tags":[
        "product",
        "related"
    ],
    "wof:name":"Champagne Bernard Bremont",
    "wof:placetype":"venue"
},
  "geometry": {"coordinates":[4.170114,49.079327],"type":"Point"}
}