{
  "type": "Feature",
  "properties": {
    "iso:country":"FR",
    "sg:address":"40, Rue Paul Sabatier Prolong\u00e9e - ZI des Confreries, 71530 Crissey",
    "sg:city":"Crissey",
    "sg:orig_category":"Unclassifiable Establishments",
    "sg:phone":"+33 3 85 46 46 12",
    "sg:postcode":"71530",
    "sg:province":"Bourgogne",
    "wof:name":"C.e.v. S.a.s. - Centre Est Village",
    "wof:placetype":"venue"
},
  "geometry": {"coordinates":[4.88201,46.816959],"type":"Point"}
}