{
  "type": "Feature",
  "properties": {
    "iso:country":"FR",
    "sg:address":"64 Avenue Franklin Roosevelt 69517 Vaulx En Velin Cedex",
    "sg:classifiers":[
        {
            "category":"Government",
            "subcategory":"Department Of Motor Vehicles",
            "type":"Public Place"
        }
    ],
    "sg:phone":"+33 4 72 02 69 79",
    "sg:province":"Picardie",
    "sg:tags":[
        "equipment",
        "industrial",
        "transport",
        "motor-cars"
    ],
    "wof:name":"Equipement Automobile Busnengo Et Cie Sa",
    "wof:placetype":"venue"
},
  "geometry": {"coordinates":[4.936889,45.762192],"type":"Point"}
}