{
  "type": "Feature",
  "properties": {
    "addr:full":"ZA du Pr\u00e8s Avrin Maul\u00e9vrier Pays de Loire 49360",
    "addr:postcode":"49360",
    "addr:street":"Za Du Pre\u0300S Avrin",
    "iso:country":"FR",
    "sg:address":"ZA du Pr\u00e8s Avrin",
    "sg:city":"Maul\u00e9vrier",
    "sg:orig_category":"Unclassifiable Establishments",
    "sg:phone":"+33 2 41 49 17 50",
    "sg:postcode":"49360",
    "sg:province":"Pays de Loire",
    "wof:name":"Batistyl Menuiserie S.a.",
    "wof:placetype":"venue"
},
  "geometry": {"coordinates":[-0.745819,47.007374],"type":"Point"}
}