{
  "type": "Feature",
  "properties": {
    "addr:full":"All\u00e9e de la Clairi\u00e8re - ZA Wavrin Nord Pas-de-Calais 59136",
    "addr:postcode":"59136",
    "addr:street":"Alle\u0301E De La Clairie\u0300Re Za Wavrin Nord",
    "iso:country":"FR",
    "sg:address":"All\u00e9e de la Clairi\u00e8re - ZA",
    "sg:city":"Wavrin",
    "sg:orig_category":"Non-Classified Establishments",
    "sg:phone":"+33 3 20 58 80 90",
    "sg:postcode":"59136",
    "sg:province":"Nord Pas-de-Calais",
    "wof:name":"A.m.t.p. E.u.r.l.",
    "wof:placetype":"venue"
},
  "geometry": {"coordinates":[2.93284,50.570339],"type":"Point"}
}