{
  "type": "Feature",
  "properties": {
    "iso:country":"FR",
    "sg:address":"18, Rue Thierry Sabine - Domaine de Bellevue, 33700 M\u00e9rignac",
    "sg:city":"M\u00e9rignac",
    "sg:orig_category":"Unclassifiable Establishments",
    "sg:phone":"+33 5 56 13 11 77",
    "sg:postcode":"33700",
    "sg:province":"Aquitaine",
    "wof:name":"Eurovia Aquitaine S.n.c.",
    "wof:placetype":"venue"
},
  "geometry": {"coordinates":[-0.64762,44.841808],"type":"Point"}
}