{
  "type": "Feature",
  "properties": {
    "addr:full":"Rte de Ferrussac - L' Ayrette Meyrueis Languedoc-Roussillon 48150",
    "addr:postcode":"48150",
    "addr:street":"Rte De Ferrussac L ' Ayrette",
    "iso:country":"FR",
    "sg:address":"Rte de Ferrussac - L' Ayrette",
    "sg:city":"Meyrueis",
    "sg:orig_category":"Non-Classified Establishments",
    "sg:phone":"+33 4 66 45 62 51",
    "sg:postcode":"48150",
    "sg:province":"Languedoc-Roussillon",
    "wof:name":"Scierie De B\u00e9thuzon S.a.r.l.",
    "wof:placetype":"venue"
},
  "geometry": {"coordinates":[3.451188,44.147774],"type":"Point"}
}