{
  "type": "Feature",
  "properties": {
    "addr:full":"91 Rue Carnot 62505 St Omer Centre",
    "addr:housenumber":"91",
    "addr:postcode":"62505",
    "addr:street":"Rue Carnot",
    "iso:country":"FR",
    "sg:address":"91 Rue Carnot 62505 St Omer",
    "sg:classifiers":[
        {
            "category":"Banks & Credit Unions",
            "subcategory":"Financial Services",
            "type":"Services"
        }
    ],
    "sg:phone":"+33 3 21 38 84 00",
    "sg:province":"Centre",
    "sg:tags":[
        "banking",
        "insurance",
        "institution",
        "finance"
    ],
    "wof:name":"Credit Du Nord",
    "wof:placetype":"venue"
},
  "geometry": {"coordinates":[2.258226,50.750351],"type":"Point"}
}