{
  "type": "Feature",
  "properties": {
    "addr:full":"20 Chablis Bourgogne 89800",
    "addr:housenumber":"20",
    "addr:postcode":"89800",
    "addr:street":"Chablis Bourgogne",
    "iso:country":"FR",
    "sg:address":"20",
    "sg:city":"Chablis",
    "sg:classifiers":[
        {
            "category":"Food Court",
            "type":"Food & Drink"
        }
    ],
    "sg:phone":"+33 3 86 18 90 00",
    "sg:postcode":"89800",
    "sg:province":"Bourgogne",
    "sg:tags":[
        "product",
        "related"
    ],
    "wof:name":"Domaine Servin",
    "wof:placetype":"venue"
},
  "geometry": {"coordinates":[3.804813,47.815922],"type":"Point"}
}