{
  "type": "Feature",
  "properties": {
    "iso:country":"FR",
    "sg:address":"22, Rue de la S\u00e8vre, 85700 Saint Mesmin",
    "sg:orig_category":"Unclassifiable Establishments",
    "sg:phone":"+33 2 51 91 20 18",
    "sg:province":"Pays de Loire",
    "wof:name":"C.i.c.c. S.a.",
    "wof:placetype":"venue"
},
  "geometry": {"coordinates":[-0.730036,46.795181],"type":"Point"}
}