{
  "type": "Feature",
  "properties": {
    "iso:country":"FR",
    "sg:address":"12, Rue Cluj - ZI Nord, 21002 Dijon C\u00e9dex",
    "sg:orig_category":"Non-Classified Establishments",
    "sg:phone":"+33 3 80 78 79 80",
    "sg:province":"Bourgogne",
    "wof:name":"Entreprise Demongeot Electricit\u00e9 S.a.",
    "wof:placetype":"venue"
},
  "geometry": {"coordinates":[5.044195,47.326458],"type":"Point"}
}