{
  "type": "Feature",
  "properties": {
    "iso:country":"FR",
    "sg:address":"Quartier Peyreguins 83390 Cuers",
    "sg:classifiers":[
        {
            "category":"Farming",
            "subcategory":"Livestock Farm",
            "type":"Manufacturing & Wholesale Goods"
        }
    ],
    "sg:phone":"+33 4 94 48 55 27",
    "sg:province":"Aquitaine",
    "sg:tags":[
        "agriculture"
    ],
    "wof:name":"Nirp International Les Roses Du Succes",
    "wof:placetype":"venue"
},
  "geometry": {"coordinates":[6.075937,43.232903],"type":"Point"}
}