{
  "type": "Feature",
  "properties": {
    "addr:full":"36210 Anjouin Anjouin Centre 36210",
    "addr:housenumber":"anjouin",
    "addr:postcode":"36210;36210",
    "iso:country":"FR",
    "sg:address":"36210 Anjouin",
    "sg:city":"Anjouin",
    "sg:orig_category":"Non-Classified Establishments",
    "sg:phone":"+33 2 54 40 63 67",
    "sg:postcode":"36210",
    "sg:province":"Centre",
    "wof:name":"Fromagerie Ch\u00eavre De La Vall\u00e9e Du Cher Coop\u00e9rative",
    "wof:placetype":"venue"
},
  "geometry": {"coordinates":[1.801901,47.189747],"type":"Point"}
}