{
  "type": "Feature",
  "properties": {
    "iso:country":"FR",
    "sg:address":"Chemin des Canaux - Gara de Paille",
    "sg:city":"Bouillargues",
    "sg:orig_category":"Non-Classified Establishments",
    "sg:phone":"+33 4 66 20 59 01",
    "sg:postcode":"30230",
    "sg:province":"Languedoc-Roussillon",
    "wof:name":"Manie Bat S.a.",
    "wof:placetype":"venue"
},
  "geometry": {"coordinates":[4.42806,43.798744],"type":"Point"}
}