{
  "type": "Feature",
  "properties": {
    "iso:country":"FR",
    "sg:address":"58 A Rue Du Dessous Des Berges 75013 Paris",
    "sg:classifiers":[
        {
            "category":"Banks & Credit Unions",
            "subcategory":"Financial Services",
            "type":"Services"
        }
    ],
    "sg:phone":"+33 1 53 79 17 00",
    "sg:postcode":"75013",
    "sg:province":"Ile de France",
    "sg:tags":[
        "banking",
        "finance",
        "insurance"
    ],
    "wof:name":"Ste Saretec",
    "wof:placetype":"venue"
},
  "geometry": {"coordinates":[2.373996,48.827557],"type":"Point"}
}