{
  "type": "Feature",
  "properties": {
    "iso:country":"FR",
    "sg:address":"37",
    "sg:city":"4 Septembre; Ch\u00e2teauneuf les Martigues",
    "sg:classifiers":[
        {
            "category":"Banks & Credit Unions",
            "subcategory":"Bank",
            "type":"Services"
        }
    ],
    "sg:phone":"+33 3342798910",
    "sg:province":"Midi Pyr\u00e9n\u00e9es",
    "wof:name":"Caisse R\u00e9gionale Cr\u00e9dit, Agricole (c.r.c.a.)",
    "wof:placetype":"venue"
},
  "geometry": {"coordinates":[5.164144,43.383595],"type":"Point"}
}