{
  "type": "Feature",
  "properties": {
    "iso:country":"FR",
    "sg:address":"17 Rue De Lanvignac BP 132 22503 Paimpol",
    "sg:city":"Paimpol",
    "sg:classifiers":[
        {
            "category":"Professional",
            "subcategory":"Business Services",
            "type":"Services"
        }
    ],
    "sg:phone":"+33 2 96 55 35 40",
    "sg:postcode":"22500",
    "sg:province":"Bretagne",
    "sg:tags":[
        "training",
        "advice"
    ],
    "wof:name":"College Nationalise Lanvignec",
    "wof:placetype":"venue"
},
  "geometry": {"coordinates":[-3.039429,48.778301],"type":"Point"}
}