{
  "type": "Feature",
  "properties": {
    "addr:full":"5 R De La R\u00e9publique 38000 Grenoble Rhone-Alpes 38000",
    "addr:housenumber":"5",
    "addr:postcode":"38000;38000",
    "addr:street":"R De La Re\u0301Publique",
    "iso:country":"FR",
    "sg:address":"5 R De La R\u00e9publique 38000 Grenoble",
    "sg:classifiers":[
        {
            "category":"Travel",
            "subcategory":"Hotels & Motels",
            "type":"Entertainment"
        }
    ],
    "sg:phone":"+33 4 76 44 49 36",
    "sg:postcode":"38000",
    "sg:province":"Rhone-Alpes",
    "sg:tags":[
        "hotels",
        "business",
        "restaurant"
    ],
    "wof:name":"Le Grand Hotel",
    "wof:placetype":"venue"
},
  "geometry": {"coordinates":[5.728613,45.190845],"type":"Point"}
}