{
  "type": "Feature",
  "properties": {
    "addr:full":"16, Rue Denis Papin, 17200 Royan Poitou-Charentes",
    "addr:housenumber":"16",
    "addr:postcode":"17200",
    "addr:street":"Rue Denis Papin",
    "iso:country":"FR",
    "sg:address":"16, Rue Denis Papin, 17200 Royan",
    "sg:orig_category":"Unclassifiable Establishments",
    "sg:phone":"+33 5 46 05 01 52",
    "sg:province":"Poitou-Charentes",
    "wof:name":"Transports Fr\u00e9d\u00e9ric Montay S.a.",
    "wof:placetype":"venue"
},
  "geometry": {"coordinates":[-0.988757,45.631969],"type":"Point"}
}