{
  "type": "Feature",
  "properties": {
    "addr:full":"37 Chem Du Puissanton B\u00e2timent A Centre Puissanton 06220 Vallauris Rhone-Alpes",
    "addr:housenumber":"37",
    "addr:postcode":"06220",
    "addr:street":"Chem Du",
    "iso:country":"FR",
    "sg:address":"37 Chem Du Puissanton B\u00e2timent A Centre Puissanton 06220 Vallauris",
    "sg:classifiers":[
        {
            "category":"Manufacturing",
            "subcategory":"Printing",
            "type":"Manufacturing & Wholesale Goods"
        }
    ],
    "sg:phone":"+33 4 92 95 15 40",
    "sg:province":"Rhone-Alpes",
    "sg:tags":[
        "publishing"
    ],
    "wof:name":"Danel",
    "wof:placetype":"venue"
},
  "geometry": {"coordinates":[7.0632,43.596073],"type":"Point"}
}