{
  "type": "Feature",
  "properties": {
    "addr:full":"49 Avenue Franklin Roosevelt 69150 Decines Charpieu Rhone-Alpes 69150",
    "addr:housenumber":"49",
    "addr:postcode":"69150;69150",
    "addr:street":"Avenue Franklin Roosevelt;Rhone-Alpes",
    "iso:country":"FR",
    "sg:address":"49 Avenue Franklin Roosevelt 69150 Decines Charpieu",
    "sg:classifiers":[
        {
            "category":"Manufacturing",
            "subcategory":"Motor Vehicles & Parts",
            "type":"Manufacturing & Wholesale Goods"
        }
    ],
    "sg:phone":"+33 4 37 42 30 60",
    "sg:postcode":"69150",
    "sg:province":"Rhone-Alpes",
    "sg:tags":[
        "engine",
        "machine",
        "engineering",
        "-",
        "mechanical"
    ],
    "wof:name":"Ecovil Equinox",
    "wof:placetype":"venue"
},
  "geometry": {"coordinates":[4.937273,45.762623],"type":"Point"}
}