{
  "type": "Feature",
  "properties": {
    "iso:country":"FR",
    "sg:address":"17, Rue Jo\u00ebl le Theule, 78180 Montigny le Bretonneux",
    "sg:orig_category":"Unclassifiable Establishments",
    "sg:phone":"+33 1 39 44 27 00",
    "sg:province":"Ile de France",
    "wof:name":"B.e.c.m. - Banque Economie Du Commerce Et Mon\u00e9tique S.a.",
    "wof:placetype":"venue"
},
  "geometry": {"coordinates":[2.04448,48.786209],"type":"Point"}
}