{
  "type": "Feature",
  "properties": {
    "addr:full":"B.P. 2, 57255 Sainte Marie aux Ch\u00eanes^^Rue Antoine M\u00e9nard, 57255 Sainte Marie aux Ch\u00eanes Basse Normandie",
    "addr:housenumber":"2",
    "addr:postcode":"57255;57255",
    "addr:street":"B.P.;Aux Che\u0302Nes^^Rue Antoine Me\u0301Nard;Aux Che\u0302Nes Basse Normandie",
    "iso:country":"FR",
    "sg:address":"B.P. 2, 57255 Sainte Marie aux Ch\u00eanes^^Rue Antoine M\u00e9nard, 57255 Sainte Marie aux Ch\u00eanes",
    "sg:orig_category":"Non-Classified Establishments",
    "sg:phone":"+33 3 87 61 91 11",
    "sg:province":"Basse Normandie",
    "wof:name":"Cardinal Industrie S.a.",
    "wof:placetype":"venue"
},
  "geometry": {"coordinates":[6.00664,49.190941],"type":"Point"}
}