{
  "type": "Feature",
  "properties": {
    "addr:full":"34, Impasse des Epinettes, 74300 Magland Rhone-Alpes",
    "addr:housenumber":"34",
    "addr:postcode":"74300",
    "addr:street":"Impasse Des Epinettes",
    "iso:country":"FR",
    "sg:address":"34, Impasse des Epinettes, 74300 Magland",
    "sg:orig_category":"Unclassifiable Establishments",
    "sg:phone":"+33 4 50 34 71 90",
    "sg:province":"Rhone-Alpes",
    "wof:name":"Bouvier G\u00e9rard",
    "wof:placetype":"venue"
},
  "geometry": {"coordinates":[6.633185,45.987919],"type":"Point"}
}