{
  "type": "Feature",
  "properties": {
    "addr:full":"8 rue Jean Goujon 75008 Paris Ile de France 75008",
    "addr:housenumber":"8",
    "addr:postcode":"75008;75008",
    "addr:street":"Rue Jean Goujon",
    "iso:country":"FR",
    "sg:address":"8 rue Jean Goujon 75008 Paris",
    "sg:classifiers":[
        {
            "category":"Professional",
            "subcategory":"Business Services",
            "type":"Services"
        }
    ],
    "sg:phone":"+33 1 49 05 91 93",
    "sg:postcode":"75008",
    "sg:province":"Ile de France",
    "sg:tags":[
        "data"
    ],
    "wof:name":"Assistance Logistique Organisation Sarl",
    "wof:placetype":"venue"
},
  "geometry": {"coordinates":[2.308919,48.866611],"type":"Point"}
}