{
  "type": "Feature",
  "properties": {
    "addr:full":"Pont Du Canal 71150 Cheilly Les Maranges Cheilly-l\u00e8s-Maranges Bourgogne 71150",
    "addr:postcode":"71150;71150",
    "addr:street":"Pont Du Canal;Bourgogne",
    "iso:country":"FR",
    "sg:address":"Pont Du Canal 71150 Cheilly Les Maranges",
    "sg:city":"Cheilly-l\u00e8s-Maranges",
    "sg:classifiers":[
        {
            "category":"Food Court",
            "type":"Food & Drink"
        }
    ],
    "sg:phone":"+33 3 85 91 14 51",
    "sg:postcode":"71150",
    "sg:province":"Bourgogne",
    "sg:tags":[
        "product",
        "related"
    ],
    "wof:name":"Rene Martin",
    "wof:placetype":"venue"
},
  "geometry": {"coordinates":[4.75459,46.910526],"type":"Point"}
}