{
  "type": "Feature",
  "properties": {
    "addr:full":"Espace D'Activit\u00e9s De Le F\u00e9e Des Eaux 69390 Vernaison Rhone-Alpes 69390",
    "addr:postcode":"69390;69390",
    "addr:street":"Eaux",
    "iso:country":"FR",
    "sg:address":"Espace D'Activit\u00e9s De Le F\u00e9e Des Eaux 69390 Vernaison",
    "sg:classifiers":[
        {
            "category":"Utilities",
            "subcategory":"Telephone",
            "type":"Services"
        }
    ],
    "sg:phone":"+33 4 72 30 52 00",
    "sg:postcode":"69390",
    "sg:province":"Rhone-Alpes",
    "sg:tags":[
        "telecommunication"
    ],
    "wof:name":"Jv Electronique Sa",
    "wof:placetype":"venue"
},
  "geometry": {"coordinates":[4.81149,45.64682],"type":"Point"}
}