{
  "type": "Feature",
  "properties": {
    "addr:full":"181, Rue Andr\u00e9 Karman, 93303 Aubervilliers C\u00e9dex Basse Normandie",
    "addr:housenumber":"181",
    "addr:postcode":"93303",
    "addr:street":"Rue Andre\u0301 Karman",
    "iso:country":"FR",
    "sg:address":"181, Rue Andr\u00e9 Karman, 93303 Aubervilliers C\u00e9dex",
    "sg:orig_category":"Non-Classified Establishments",
    "sg:phone":"+33 1 48 34 75 03",
    "sg:province":"Basse Normandie",
    "wof:name":"Elerte S.a.",
    "wof:placetype":"venue"
},
  "geometry": {"coordinates":[2.385039,48.912903],"type":"Point"}
}