{
  "type": "Feature",
  "properties": {
    "iso:country":"FR",
    "sg:address":"B.P. 517, 18105 Vierzon C\u00e9dex^^8, Rte de Ch\u00e2teauroux, 18100 Vierzon",
    "sg:city":"Vierzon",
    "sg:orig_category":"Non-Classified Establishments",
    "sg:phone":"+33 2 48 75 25 25",
    "sg:postcode":"18100",
    "sg:province":"Centre",
    "wof:name":"V.d.i. S.a.",
    "wof:placetype":"venue"
},
  "geometry": {"coordinates":[2.020555,47.206581],"type":"Point"}
}