{
  "type": "Feature",
  "properties": {
    "addr:full":"280 Rue Du Quesne 59700 Marcq En Baroeul Nord Pas-de-Calais 59700",
    "addr:housenumber":"280",
    "addr:postcode":"59700;59700",
    "addr:street":"Rue Du Quesne;En Baroeul Nord",
    "iso:country":"FR",
    "sg:address":"280 Rue Du Quesne 59700 Marcq En Baroeul",
    "sg:classifiers":[
        {
            "category":"Professional",
            "subcategory":"Engineering",
            "type":"Services"
        }
    ],
    "sg:phone":"+33 3 20 66 27 00",
    "sg:postcode":"59700",
    "sg:province":"Nord Pas-de-Calais",
    "sg:tags":[
        "machine",
        "-",
        "mechanical"
    ],
    "wof:name":"Scam Filtres",
    "wof:placetype":"venue"
},
  "geometry": {"coordinates":[3.113904,50.674004],"type":"Point"}
}