{
  "type": "Feature",
  "properties": {
    "addr:full":"80 rue Martre 92110 Clichy Ile de France 92110",
    "addr:housenumber":"80",
    "addr:postcode":"92110;92110",
    "addr:street":"Rue Martre;Ile De France",
    "iso:country":"FR",
    "sg:address":"80 rue Martre 92110 Clichy",
    "sg:orig_category":"Drawing Magazines",
    "sg:phone":"+33 1 47 31 93 09",
    "sg:postcode":"92110",
    "sg:province":"Ile de France",
    "wof:name":"Gris Marine S.a.r.l.",
    "wof:placetype":"venue"
},
  "geometry": {"coordinates":[2.306836,48.90258],"type":"Point"}
}