{
  "type": "Feature",
  "properties": {
    "iso:country":"FR",
    "sg:address":"Avenue De Sainte Barbe Za 30520 St Martin De Valgalgues",
    "sg:classifiers":[
        {
            "category":"Farming",
            "subcategory":"Farm & Veterinary Services",
            "type":"Manufacturing & Wholesale Goods"
        }
    ],
    "sg:phone":"+33 4 66 56 73 60",
    "sg:postcode":"30520",
    "sg:province":"Languedoc-Roussillon",
    "sg:tags":[
        "advice",
        "agriculture",
        "livestock",
        "business"
    ],
    "wof:name":"Arnal Sofocev",
    "wof:placetype":"venue"
},
  "geometry": {"coordinates":[4.083545,44.162254],"type":"Point"}
}