{
  "type": "Feature",
  "properties": {
    "addr:full":"565, Rue d'Ypres, 59118 Wambrechies Nord Pas-de-Calais 59118",
    "addr:housenumber":"565",
    "addr:postcode":"59118;59118",
    "addr:street":"Rue D'Ypres",
    "iso:country":"FR",
    "sg:address":"565, Rue d'Ypres, 59118 Wambrechies",
    "sg:orig_category":"Non-Classified Establishments",
    "sg:phone":"+33 3 20 78 75 57",
    "sg:postcode":"59118",
    "sg:province":"Nord Pas-de-Calais",
    "wof:name":"Crombet S.a.r.l.",
    "wof:placetype":"venue"
},
  "geometry": {"coordinates":[3.048398,50.677441],"type":"Point"}
}