{
  "type": "Feature",
  "properties": {
    "iso:country":"FR",
    "sg:address":"Rue de Poirouse",
    "sg:city":"Pontcey",
    "sg:orig_category":"Non-Classified Establishments",
    "sg:phone":"+33 3 84 91 53 26",
    "sg:postcode":"70360",
    "sg:province":"Franche Comt\u00e9",
    "wof:name":"Mariot S.a.r.l.",
    "wof:placetype":"venue"
},
  "geometry": {"coordinates":[6.030722,47.628754],"type":"Point"}
}