{
  "type": "Feature",
  "properties": {
    "iso:country":"FR",
    "sg:address":"Rue Guillaume du Var - La Pioline",
    "sg:city":"Aix en Provence",
    "sg:orig_category":"Unclassifiable Establishments",
    "sg:phone":"+33 4 42 39 29 89",
    "sg:postcode":"13290",
    "sg:province":"Provence-Alpes-C\u00f4te d'Azur",
    "wof:name":"Calissons Du Roy Ren\u00e9 S.a.",
    "wof:placetype":"venue"
},
  "geometry": {"coordinates":[5.38935,43.50206],"type":"Point"}
}