{
  "type": "Feature",
  "properties": {
    "addr:full":"55, Bd de l'Embouchure - B\u00e2t C, 31200 Toulouse Midi Pyr\u00e9n\u00e9es",
    "addr:housenumber":"55;ba\u0302t c",
    "addr:postcode":"31200",
    "addr:street":"Bd De L'Embouchure",
    "iso:country":"FR",
    "sg:address":"55, Bd de l'Embouchure - B\u00e2t C, 31200 Toulouse",
    "sg:orig_category":"Unclassifiable Establishments",
    "sg:phone":"+33 5 62 72 36 00",
    "sg:province":"Midi Pyr\u00e9n\u00e9es",
    "wof:name":"Secafi Alpha S.a.",
    "wof:placetype":"venue"
},
  "geometry": {"coordinates":[1.432791,43.614876],"type":"Point"}
}