{
  "type": "Feature",
  "properties": {
    "iso:country":"FR",
    "sg:address":"Rte De Lyon 38230 Charvieu Chavagneux",
    "sg:classifiers":[
        {
            "category":"Utilities",
            "subcategory":"Electric",
            "type":"Services"
        }
    ],
    "sg:phone":"+33 4 72 46 75 00",
    "sg:postcode":"38230",
    "sg:province":"Rhone-Alpes",
    "sg:tags":[
        "electricity",
        "electronic",
        "electrical",
        "equipment"
    ],
    "wof:name":"Cables Pirelli",
    "wof:placetype":"venue"
},
  "geometry": {"coordinates":[5.15704,45.749825],"type":"Point"}
}