{
  "type": "Feature",
  "properties": {
    "addr:full":"ZI du Petit Boiss\u00e9 87200 St Junien Limousin",
    "addr:postcode":"87200",
    "addr:street":"Zi Du Petit Boisse\u0301",
    "iso:country":"FR",
    "sg:address":"ZI du Petit Boiss\u00e9 87200 St Junien",
    "sg:classifiers":[
        {
            "category":"Organizations",
            "subcategory":"Non-profit Organization",
            "type":"Services"
        }
    ],
    "sg:phone":"+33 5 55 02 26 32",
    "sg:province":"Limousin",
    "sg:tags":[
        "pneumatic",
        "component",
        "system"
    ],
    "wof:name":"Pneumatic Union Sa",
    "wof:placetype":"venue"
},
  "geometry": {"coordinates":[0.901046,45.887379],"type":"Point"}
}