{
  "type": "Feature",
  "properties": {
    "addr:full":"Vaugoin 41220 Dhuizon Dhuizon Centre 41220",
    "addr:housenumber":"dhuizon",
    "addr:postcode":"41220;41220",
    "addr:street":"Vaugoin",
    "iso:country":"FR",
    "sg:address":"Vaugoin 41220 Dhuizon",
    "sg:city":"Dhuizon",
    "sg:orig_category":"Unclassifiable Establishments",
    "sg:phone":"+33 2 54 98 39 48",
    "sg:postcode":"41220",
    "sg:province":"Centre",
    "wof:name":"Astacus France S.a.r.l.",
    "wof:placetype":"venue"
},
  "geometry": {"coordinates":[1.657628,47.58931],"type":"Point"}
}