{
  "type": "Feature",
  "properties": {
    "addr:full":"La Brindossi\u00e8re Magny le D\u00e9sert Basse Normandie 61600",
    "addr:postcode":"61600",
    "addr:street":"De\u0301Sert Basse",
    "iso:country":"FR",
    "sg:address":"La Brindossi\u00e8re",
    "sg:city":"Magny le D\u00e9sert",
    "sg:orig_category":"Unclassifiable Establishments",
    "sg:phone":"+33 2 33 30 28 00",
    "sg:postcode":"61600",
    "sg:province":"Basse Normandie",
    "wof:name":"Base Basse Normandie Magny S.a.",
    "wof:placetype":"venue"
},
  "geometry": {"coordinates":[-0.329754,48.588291],"type":"Point"}
}