{
  "type": "Feature",
  "properties": {
    "addr:full":"108 Rue Petit Hameau 45110 Chat\u00eaauneuf Sur Loire Ch\u00e2teauneuf-sur-Loire Centre 45110",
    "addr:housenumber":"108;cha\u0302teauneuf-sur-loire",
    "addr:postcode":"45110;45110",
    "addr:street":"Rue Petit Hameau",
    "iso:country":"FR",
    "sg:address":"108 Rue Petit Hameau 45110 Chat\u00eaauneuf Sur Loire",
    "sg:city":"Ch\u00e2teauneuf-sur-Loire",
    "sg:classifiers":[
        {
            "category":"Professional",
            "subcategory":"Engineering",
            "type":"Services"
        }
    ],
    "sg:phone":"+33 2 38 58 44 77",
    "sg:postcode":"45110",
    "sg:province":"Centre",
    "sg:tags":[
        "machine",
        "-",
        "mechanical"
    ],
    "wof:name":"Mecanique De Precision De L Orleanais Sa",
    "wof:placetype":"venue"
},
  "geometry": {"coordinates":[2.21668,47.876678],"type":"Point"}
}