{
  "type": "Feature",
  "properties": {
    "iso:country":"FR",
    "sg:address":"B.P. 65, 45120 Ch\u00e2lette sur Loing C\u00e9dex^^2, Av. L\u00e9on Blum, 45120 Ch\u00e2lette sur Loing",
    "sg:city":"Cepoy",
    "sg:orig_category":"Non-Classified Establishments",
    "sg:phone":"+33 2 38 85 80 80",
    "sg:postcode":"45120",
    "sg:province":"Centre",
    "wof:name":"D.i.u.a. S.a. - Deglarges Isolants Usines Arzens",
    "wof:placetype":"venue"
},
  "geometry": {"coordinates":[2.731191,48.014793],"type":"Point"}
}