{
  "type": "Feature",
  "properties": {
    "addr:full":"B.P. 99, 35407 Saint Malo C\u00e9dex^^Rue de Pierre de Coubertin, 35400 Saint Malo Saint-Malo Bretagne 35400",
    "addr:postcode":"35407;35400;35400",
    "addr:street":"B.P. 99;Pierre De Coubertin;Saint-Malo",
    "iso:country":"FR",
    "sg:address":"B.P. 99, 35407 Saint Malo C\u00e9dex^^Rue de Pierre de Coubertin, 35400 Saint Malo",
    "sg:city":"Saint-Malo",
    "sg:orig_category":"Non-Classified Establishments",
    "sg:phone":"+33 2 99 21 12 22",
    "sg:postcode":"35400",
    "sg:province":"Bretagne",
    "wof:name":"Gr\u00e9ta Pays De Rance",
    "wof:placetype":"venue"
},
  "geometry": {"coordinates":[-1.97509,48.60231],"type":"Point"}
}