{
  "type": "Feature",
  "properties": {
    "iso:country":"FR",
    "sg:address":"116 quai de Bezons 95100 Argenteuil",
    "sg:classifiers":[
        {
            "category":"Banks & Credit Unions",
            "subcategory":"Atm",
            "type":"Services"
        }
    ],
    "sg:phone":"+33 1 39 47 09 36",
    "sg:province":"Ile de France",
    "sg:tags":[
        "absorber",
        "temperature"
    ],
    "wof:name":"Jules Richard Instruments",
    "wof:placetype":"venue"
},
  "geometry": {"coordinates":[2.238861,48.932915],"type":"Point"}
}