{
  "type": "Feature",
  "properties": {
    "iso:country":"FR",
    "sg:address":"B.P. 161, 71407 Autun C\u00e9dex^^7, Rue Ni\u00e8pce - ZI Saint Pantal\u00e9on, 71400 Autun",
    "sg:city":"Autun",
    "sg:orig_category":"Maintenance industrielle M\u00e9canique de pr\u00e9cision Tournage sur tours verticaux",
    "sg:phone":"+33 3 85 86 59 30",
    "sg:postcode":"71400",
    "sg:province":"Bourgogne",
    "wof:name":"E.m.g. Industrie S.a.",
    "wof:placetype":"venue"
},
  "geometry": {"coordinates":[4.411325,46.902779],"type":"Point"}
}