{
  "type": "Feature",
  "properties": {
    "iso:country":"FR",
    "sg:address":"31 rue Gambetta; Fig\u00e9ac; 46100",
    "sg:classifiers":[
        {
            "category":"Banks & Credit Unions",
            "subcategory":"Bank",
            "type":"Services"
        }
    ],
    "sg:phone":"+33 3365340713",
    "sg:postcode":"46100",
    "sg:province":"Midi Pyr\u00e9n\u00e9es",
    "wof:name":"Soci\u00e9t\u00e9 G\u00e9n\u00e9rale",
    "wof:placetype":"venue"
},
  "geometry": {"coordinates":[2.033852,44.608479],"type":"Point"}
}