{
  "type": "Feature",
  "properties": {
    "addr:full":"11, Rue de l'Ile Mac\u00e9, 44400 Rez\u00e9 Pays de Loire",
    "addr:housenumber":"11",
    "addr:postcode":"44400",
    "addr:street":"Rue De L'Ile Mace\u0301",
    "iso:country":"FR",
    "sg:address":"11, Rue de l'Ile Mac\u00e9, 44400 Rez\u00e9",
    "sg:orig_category":"Unclassifiable Establishments",
    "sg:phone":"+33 2 40 75 67 27",
    "sg:province":"Pays de Loire",
    "wof:name":"Fabory Nantes S.a.",
    "wof:placetype":"venue"
},
  "geometry": {"coordinates":[-1.55687,47.1749],"type":"Point"}
}