{
  "type": "Feature",
  "properties": {
    "iso:country":"FR",
    "sg:address":"93534 Aubervilliers C\u00e9dex C^^43/45, Av. Victor Hugo - B\u00e2t. 273, 93500 Aubervilliers",
    "sg:orig_category":"Non-Classified Establishments",
    "sg:phone":"+33 1 43 52 60 37",
    "sg:province":"Ile de France",
    "wof:name":"Vitrine Center S.a.r.l.",
    "wof:placetype":"venue"
},
  "geometry": {"coordinates":[2.40168,48.89658],"type":"Point"}
}