{
  "type": "Feature",
  "properties": {
    "addr:full":"Le Garon 69700 Montagny Rhone-Alpes 69700",
    "addr:postcode":"69700;69700",
    "iso:country":"FR",
    "sg:address":"Le Garon 69700 Montagny",
    "sg:classifiers":[
        {
            "category":"Professional",
            "subcategory":"Engineering",
            "type":"Services"
        }
    ],
    "sg:phone":"+33 4 37 20 15 00",
    "sg:postcode":"69700",
    "sg:province":"Rhone-Alpes",
    "sg:tags":[
        "machine",
        "-",
        "mechanical"
    ],
    "wof:name":"Msc",
    "wof:placetype":"venue"
},
  "geometry": {"coordinates":[4.772675,45.611607],"type":"Point"}
}