{
  "type": "Feature",
  "properties": {
    "addr:full":"31 Rue Amelin 93440 Dugny Ile de France 93440",
    "addr:housenumber":"31",
    "addr:postcode":"93440;ile;93440",
    "addr:street":"Rue Amelin;France",
    "iso:country":"FR",
    "sg:address":"31 Rue Amelin 93440 Dugny",
    "sg:classifiers":[
        {
            "category":"Utilities",
            "subcategory":"Electric",
            "type":"Services"
        }
    ],
    "sg:phone":"+33 1 49 92 63 40",
    "sg:postcode":"93440",
    "sg:province":"Ile de France",
    "sg:tags":[
        "electricity",
        "electronic",
        "electrical",
        "equipment"
    ],
    "wof:name":"Adelec",
    "wof:placetype":"venue"
},
  "geometry": {"coordinates":[2.41985,48.941109],"type":"Point"}
}