{
  "type": "Feature",
  "properties": {
    "iso:country":"FR",
    "sg:address":"B.P. 64, 74602 Seynod C\u00e9dex^^153, Chemin des Pr\u00e9s Bouvaux, 74960 Cran Gevrier",
    "sg:orig_category":"Non-Classified Establishments",
    "sg:phone":"+33 4 50 69 12 65",
    "sg:postcode":"74960",
    "sg:province":"Rhone-Alpes",
    "wof:name":"Bernardi S.a.",
    "wof:placetype":"venue"
},
  "geometry": {"coordinates":[6.10647,45.907654],"type":"Point"}
}