{
  "type": "Feature",
  "properties": {
    "addr:full":"Rue Aristide Berg\u00e8s Zi Des Moulins Lot Artisanal 31840 Aussonne Midi Pyr\u00e9n\u00e9es",
    "addr:postcode":"31840",
    "addr:street":"Rue Aristide Berge\u0300S Zi Des Moulins;Artisanal",
    "iso:country":"FR",
    "sg:address":"Rue Aristide Berg\u00e8s Zi Des Moulins",
    "sg:city":"Lot Artisanal 31840 Aussonne",
    "sg:classifiers":[
        {
            "category":"Wholesale",
            "subcategory":"Machinery & Supplies",
            "type":"Manufacturing & Wholesale Goods"
        }
    ],
    "sg:phone":"+33 5 61 85 75 34",
    "sg:province":"Midi Pyr\u00e9n\u00e9es",
    "sg:tags":[
        "equipment",
        "precision"
    ],
    "wof:name":"Navocap Sa",
    "wof:placetype":"venue"
},
  "geometry": {"coordinates":[1.318074,43.682056],"type":"Point"}
}