{
  "type": "Feature",
  "properties": {
    "iso:country":"FR",
    "sg:address":"26 rue Armengaud 92210 ST CLOUD",
    "sg:classifiers":[
        {
            "category":"Manufacturing",
            "subcategory":"Paper Products",
            "type":"Manufacturing & Wholesale Goods"
        }
    ],
    "sg:phone":"+33 1 41 12 14 14",
    "sg:province":"Ile de France",
    "sg:tags":[
        "toilet",
        "humidified"
    ],
    "wof:name":"Kimberly-clark Snc",
    "wof:placetype":"venue"
},
  "geometry": {"coordinates":[2.216959,48.848232],"type":"Point"}
}