{
  "type": "Feature",
  "properties": {
    "addr:full":"51, Rue de Belleville, 75019 Paris Ile de France",
    "addr:housenumber":"51",
    "addr:postcode":"75019",
    "addr:street":"Rue De Belleville",
    "iso:country":"FR",
    "sg:address":"51, Rue de Belleville, 75019 Paris",
    "sg:orig_category":"Unclassifiable Establishments",
    "sg:phone":"+33 1 42 39 69 67",
    "sg:province":"Ile de France",
    "wof:name":"Etablissements Noury S.a.r.l.",
    "wof:placetype":"venue"
},
  "geometry": {"coordinates":[2.38093,48.873199],"type":"Point"}
}