{
  "type": "Feature",
  "properties": {
    "addr:full":"B.P. 24, 83171 Brignoles C\u00e9dex^^Bd Saint Louis, 83170 Brignoles Centre",
    "addr:postcode":"83171;83170",
    "addr:street":"B.P. 24",
    "iso:country":"FR",
    "sg:address":"B.P. 24, 83171 Brignoles C\u00e9dex^^Bd Saint Louis, 83170 Brignoles",
    "sg:orig_category":"Non-Classified Establishments",
    "sg:phone":"+33 4 94 37 03 20",
    "sg:province":"Centre",
    "wof:name":"Sodexpert S.a.",
    "wof:placetype":"venue"
},
  "geometry": {"coordinates":[5.853343,43.393883],"type":"Point"}
}