{
  "type": "Feature",
  "properties": {
    "addr:full":"81, Av. Georges Pompidou, 59400 Cambrai Nord Pas-de-Calais",
    "addr:postcode":"59400",
    "addr:street":"81 Av. Georges Pompidou",
    "iso:country":"FR",
    "sg:address":"81, Av. Georges Pompidou, 59400 Cambrai",
    "sg:orig_category":"Non-Classified Establishments",
    "sg:phone":"+33 3 27 82 29 59",
    "sg:province":"Nord Pas-de-Calais",
    "wof:name":"Ouverture S.a.",
    "wof:placetype":"venue"
},
  "geometry": {"coordinates":[3.218197,50.174831],"type":"Point"}
}