{
  "type": "Feature",
  "properties": {
    "iso:country":"FR",
    "sg:address":"74 Rue du Chanoine Boulogne; S. Andr\u00e9",
    "sg:classifiers":[
        {
            "category":"Banks & Credit Unions",
            "subcategory":"Bank",
            "type":"Services"
        }
    ],
    "sg:phone":"+33 32372013",
    "sg:province":"Centre",
    "wof:name":"Soci\u00e9t\u00e9 G\u00e9n\u00e9rale",
    "wof:placetype":"venue"
},
  "geometry": {"coordinates":[-86.75808000000001,41.720268],"type":"Point"}
}