{
  "type": "Feature",
  "properties": {
    "addr:full":"215, Rue de la Malcense, 59200 Tourcoing Nord Pas-de-Calais",
    "addr:housenumber":"215",
    "addr:postcode":"59200",
    "addr:street":"Rue De La Malcense",
    "iso:country":"FR",
    "sg:address":"215, Rue de la Malcense, 59200 Tourcoing",
    "sg:orig_category":"Unclassifiable Establishments",
    "sg:phone":"+33 3 20 25 15 14",
    "sg:province":"Nord Pas-de-Calais",
    "wof:name":"Snv S.a.",
    "wof:placetype":"venue"
},
  "geometry": {"coordinates":[3.165603,50.732685],"type":"Point"}
}