{
  "type": "Feature",
  "properties": {
    "addr:full":"3, Rte de Rohrschollen, 67100 Strasbourg Strasbourg Alsace 67100",
    "addr:housenumber":"3",
    "addr:postcode":"67100;67100",
    "addr:street":"Rte De Rohrschollen",
    "iso:country":"FR",
    "sg:address":"3, Rte de Rohrschollen, 67100 Strasbourg",
    "sg:city":"Strasbourg",
    "sg:orig_category":"Unclassifiable Establishments",
    "sg:phone":"+33 3 88 79 50 00",
    "sg:postcode":"67100",
    "sg:province":"Alsace",
    "wof:name":"Protires S.a.",
    "wof:placetype":"venue"
},
  "geometry": {"coordinates":[7.792818,48.524574],"type":"Point"}
}