{
  "type": "Feature",
  "properties": {
    "iso:country":"FR",
    "sg:address":"Avenue Milou Urdy BP 12 13500 Martigues",
    "sg:city":"Artigue",
    "sg:classifiers":[
        {
            "category":"Professional",
            "type":"Services"
        }
    ],
    "sg:phone":"+33 4 42 42 14 11",
    "sg:postcode":"31110",
    "sg:province":"Midi Pyr\u00e9n\u00e9es",
    "sg:tags":[
        "transport",
        "road"
    ],
    "wof:name":"Demenagement Aime Sarl",
    "wof:placetype":"venue"
},
  "geometry": {"coordinates":[5.04221,43.404324],"type":"Point"}
}