{
  "type": "Feature",
  "properties": {
    "addr:full":"805 Lavall\u00e9e Quart Des Pioux 83210 La Farl\u00e8de Languedoc-Roussillon",
    "addr:housenumber":"805",
    "addr:postcode":"83210",
    "addr:street":"Lavalle\u0301E Quart Des Pioux",
    "iso:country":"FR",
    "sg:address":"805 Lavall\u00e9e Quart Des Pioux 83210 La Farl\u00e8de",
    "sg:classifiers":[
        {
            "category":"Professional",
            "subcategory":"Advertising",
            "type":"Services"
        }
    ],
    "sg:phone":"+33 4 94 27 81 00",
    "sg:province":"Languedoc-Roussillon",
    "sg:tags":[
        "information",
        "medium",
        "communication"
    ],
    "wof:name":"Jean Claude Decaux Communication",
    "wof:placetype":"venue"
},
  "geometry": {"coordinates":[6.042811,43.166992],"type":"Point"}
}