{
  "type": "Feature",
  "properties": {
    "iso:country":"FR",
    "sg:address":"Z.I. Beausoleil 14290 LA VESPIERE",
    "sg:city":"La Vespi\u00e8re",
    "sg:classifiers":[
        {
            "category":"Industrial Area",
            "type":"Public Place"
        }
    ],
    "sg:phone":"+33 2 31 48 54 80",
    "sg:postcode":"14290",
    "sg:province":"Basse Normandie",
    "sg:tags":[
        "fan"
    ],
    "wof:name":"F\u00e9vi International Sa",
    "wof:placetype":"venue"
},
  "geometry": {"coordinates":[0.35542,48.966606],"type":"Point"}
}