{
  "type": "Feature",
  "properties": {
    "iso:country":"FR",
    "sg:address":"150, Chemin de la Petite Conte, 11000 Carcassonne",
    "sg:orig_category":"Non-Classified Establishments",
    "sg:phone":"+33 4 68 25 27 21",
    "sg:province":"Languedoc-Roussillon",
    "wof:name":"Py Jean",
    "wof:placetype":"venue"
},
  "geometry": {"coordinates":[2.38194,43.213749],"type":"Point"}
}