{
  "type": "Feature",
  "properties": {
    "addr:full":"Avenue Des Lacs Zone Induspal 64140 Lons Lons Aquitaine 64140",
    "addr:postcode":"64140;64140",
    "addr:street":"Avenue Des Lacs Zone Induspal",
    "iso:country":"FR",
    "sg:address":"Avenue Des Lacs Zone Induspal 64140 Lons",
    "sg:city":"Lons",
    "sg:classifiers":[
        {
            "category":"Building & Trades",
            "subcategory":"Construction",
            "type":"Services"
        }
    ],
    "sg:phone":"+33 5 59 13 01 40",
    "sg:postcode":"64140",
    "sg:province":"Aquitaine",
    "sg:tags":[
        "work",
        "public"
    ],
    "wof:name":"Service Compagnie (serco Sa)",
    "wof:placetype":"venue"
},
  "geometry": {"coordinates":[-0.413078,43.317261],"type":"Point"}
}