{
  "type": "Feature",
  "properties": {
    "iso:country":"FR",
    "sg:address":"61 rue de la Fontaine 57410 Montbronn",
    "sg:orig_category":"Crystal, Cut",
    "sg:phone":"+33 3 87 96 32 31",
    "sg:postcode":"57410",
    "sg:province":"Lorraine",
    "wof:name":"Cristallerie Des Vosges Du Nord S.a.",
    "wof:placetype":"venue"
},
  "geometry": {"coordinates":[7.276636,49.045319],"type":"Point"}
}