{
  "type": "Feature",
  "properties": {
    "addr:full":"5 Bd De La Madeleine 75001 Paris Ile de France 75001",
    "addr:housenumber":"5",
    "addr:postcode":"75001;75001",
    "addr:street":"Bd De La Madeleine",
    "iso:country":"FR",
    "sg:address":"5 Bd De La Madeleine 75001 Paris",
    "sg:classifiers":[
        {
            "category":"Shopping",
            "subcategory":"Luggage & Leather Goods",
            "type":"Retail Goods"
        }
    ],
    "sg:phone":"+33 1 42 61 15 89",
    "sg:postcode":"75001",
    "sg:province":"Ile de France",
    "sg:tags":[
        "shoe"
    ],
    "wof:name":"Charles Jourdan Sas",
    "wof:placetype":"venue"
},
  "geometry": {"coordinates":[2.327334,48.869694],"type":"Point"}
}