{
  "type": "Feature",
  "properties": {
    "iso:country":"FR",
    "sg:address":"69 avenue Danielle Casanova 94200 Ivry sur Seine",
    "sg:classifiers":[
        {
            "category":"Shopping",
            "subcategory":"Stationery & Office Supplies",
            "type":"Retail Goods"
        }
    ],
    "sg:phone":"+33 1 46 72 71 71",
    "sg:province":"Ile de France",
    "sg:tags":[
        "packaging",
        "material"
    ],
    "wof:name":"Cb Emballage Sa",
    "wof:placetype":"venue"
},
  "geometry": {"coordinates":[2.384021,48.814922],"type":"Point"}
}