{
  "type": "Feature",
  "properties": {
    "iso:country":"FR",
    "sg:address":"Rue Joliot Curie 76650 PETIT COURONNE",
    "sg:orig_category":"Fittings, Valves",
    "sg:phone":"+33 2 35 67 56 20",
    "sg:postcode":"76650",
    "sg:province":"Haute Normandie",
    "wof:name":"I.f.c. Sa",
    "wof:placetype":"venue"
},
  "geometry": {"coordinates":[1.035725,49.381378],"type":"Point"}
}