{
  "type": "Feature",
  "properties": {
    "addr:full":"6 Rue Du Sablon 02650 Fossoy Picardie 02650",
    "addr:housenumber":"6",
    "addr:postcode":"02650;02650",
    "addr:street":"Rue Du Sablon",
    "iso:country":"FR",
    "sg:address":"6 Rue Du Sablon 02650 Fossoy",
    "sg:classifiers":[
        {
            "category":"Food Court",
            "type":"Food & Drink"
        }
    ],
    "sg:phone":"+33 3 23 71 59 40",
    "sg:postcode":"02650",
    "sg:province":"Picardie",
    "sg:tags":[
        "product",
        "related"
    ],
    "wof:name":"Alain Robert",
    "wof:placetype":"venue"
},
  "geometry": {"coordinates":[3.47851,49.044586],"type":"Point"}
}