{
  "type": "Feature",
  "properties": {
    "addr:full":"222 Rte De Vienne 38260 Faramans Rhone-Alpes 38260",
    "addr:housenumber":"222",
    "addr:postcode":"38260;38260",
    "addr:street":"Rte De Vienne",
    "iso:country":"FR",
    "sg:address":"222 Rte De Vienne 38260 Faramans",
    "sg:classifiers":[
        {
            "category":"Autos & Motor Vehicles",
            "subcategory":"Automobile Sales",
            "type":"Retail Goods"
        }
    ],
    "sg:phone":"+33 4 74 54 22 42",
    "sg:postcode":"38260",
    "sg:province":"Rhone-Alpes",
    "sg:tags":[
        "equipment",
        "industrial",
        "transport"
    ],
    "wof:name":"Gilibert Remorques (j ) Sa",
    "wof:placetype":"venue"
},
  "geometry": {"coordinates":[5.150535,45.396545],"type":"Point"}
}