{
  "type": "Feature",
  "properties": {
    "addr:full":"Rue Du Fourneau 08160 Vendresse Balaives-et-Butz Champagne 08160",
    "addr:postcode":"08160;08160",
    "addr:street":"Rue Du Fourneau;Champagne",
    "iso:country":"FR",
    "sg:address":"Rue Du Fourneau 08160 Vendresse",
    "sg:city":"Balaives-et-Butz",
    "sg:classifiers":[
        {
            "category":"Building & Trades",
            "subcategory":"Construction",
            "type":"Services"
        }
    ],
    "sg:phone":"+33 3 24 35 40 17",
    "sg:postcode":"08160",
    "sg:province":"Champagne",
    "sg:tags":[
        "work",
        "public"
    ],
    "wof:name":"Transport Et Sables J. Ponsignon Fils",
    "wof:placetype":"venue"
},
  "geometry": {"coordinates":[4.789295,49.603939],"type":"Point"}
}