{
  "type": "Feature",
  "properties": {
    "addr:full":"16, Rue L\u00e9on Foucault, 77290 Mitry Mory Ile de France",
    "addr:housenumber":"16",
    "addr:postcode":"77290",
    "addr:street":"Rue Le\u0301On Foucault",
    "iso:country":"FR",
    "sg:address":"16, Rue L\u00e9on Foucault, 77290 Mitry Mory",
    "sg:orig_category":"Non-Classified Establishments",
    "sg:phone":"+33 1 60 21 14 90",
    "sg:province":"Ile de France",
    "wof:name":"Logic Computer International S.a.",
    "wof:placetype":"venue"
},
  "geometry": {"coordinates":[2.63566,48.985519],"type":"Point"}
}