{
  "type": "Feature",
  "properties": {
    "addr:full":"48, All\u00e9e des Erables, 93420 Villepinte Ile de France",
    "addr:housenumber":"48",
    "addr:postcode":"93420",
    "addr:street":"Alle\u0301E Des Erables;Ile De France",
    "iso:country":"FR",
    "sg:address":"48, All\u00e9e des Erables, 93420 Villepinte",
    "sg:orig_category":"Unclassifiable Establishments",
    "sg:phone":"+33 1 49 38 47 60",
    "sg:province":"Ile de France",
    "wof:name":"N.s.c. S.a. - Nord Stock Chem",
    "wof:placetype":"venue"
},
  "geometry": {"coordinates":[2.49924,48.974201],"type":"Point"}
}