{
  "type": "Feature",
  "properties": {
    "addr:full":"6 Av Des Platanes 35310 Mordelles Mordelles Bretagne 35310",
    "addr:postcode":"35310;35310",
    "addr:street":"Av Des Platanes;Mordelles",
    "iso:country":"FR",
    "sg:address":"6 Av Des Platanes 35310 Mordelles",
    "sg:city":"Mordelles",
    "sg:classifiers":[
        {
            "category":"Utilities",
            "type":"Services"
        }
    ],
    "sg:phone":"+33 2 99 85 12 12",
    "sg:postcode":"35310",
    "sg:province":"Bretagne",
    "sg:tags":[
        "raw",
        "energy",
        "material"
    ],
    "wof:name":"Saur France",
    "wof:placetype":"venue"
},
  "geometry": {"coordinates":[-1.835071,48.080173],"type":"Point"}
}