{
  "type": "Feature",
  "properties": {
    "addr:full":"Rte de Reuilly Quincy Centre 18120",
    "addr:postcode":"18120",
    "addr:street":"Rte De Reuilly",
    "iso:country":"FR",
    "sg:address":"Rte de Reuilly",
    "sg:city":"Quincy",
    "sg:orig_category":"Unclassifiable Establishments",
    "sg:phone":"+33 2 48 51 31 60",
    "sg:postcode":"18120",
    "sg:province":"Centre",
    "wof:name":"Mardon Pierre Et Jean G.a.e.c.",
    "wof:placetype":"venue"
},
  "geometry": {"coordinates":[2.153509,47.129532],"type":"Point"}
}