{
  "type": "Feature",
  "properties": {
    "iso:country":"FR",
    "sg:address":"35210 Ch\u00e2tillon en Vendelais",
    "sg:city":"Combourtill\u00e9",
    "sg:orig_category":"Non-Classified Establishments",
    "sg:phone":"+33 2 99 76 06 24",
    "sg:postcode":"35210",
    "sg:province":"Bretagne",
    "wof:name":"Nounours S.a.",
    "wof:placetype":"venue"
},
  "geometry": {"coordinates":[-1.178124,48.225246],"type":"Point"}
}