{
  "type": "Feature",
  "properties": {
    "addr:full":"82, Rue de la Bourgeonni\u00e8re, 44300 Nantes Pays de Loire",
    "addr:housenumber":"82",
    "addr:postcode":"44300",
    "addr:street":"Rue De La Bourgeonnie\u0300Re",
    "iso:country":"FR",
    "sg:address":"82, Rue de la Bourgeonni\u00e8re, 44300 Nantes",
    "sg:orig_category":"Non-Classified Establishments",
    "sg:phone":"+33 2 40 76 98 60",
    "sg:province":"Pays de Loire",
    "wof:name":"Ina Roulements S.a.",
    "wof:placetype":"venue"
},
  "geometry": {"coordinates":[-1.559121,47.253437],"type":"Point"}
}