{
  "type": "Feature",
  "properties": {
    "addr:full":"21, Rue Francine Fromont, 69120 Vaulx en Velin Rhone-Alpes 69120",
    "addr:housenumber":"21",
    "addr:postcode":"69120;69120",
    "addr:street":"Rue Francine",
    "iso:country":"FR",
    "sg:address":"21, Rue Francine Fromont, 69120 Vaulx en Velin",
    "sg:orig_category":"Non-Classified Establishments",
    "sg:phone":"+33 4 72 04 21 21",
    "sg:postcode":"69120",
    "sg:province":"Rhone-Alpes",
    "wof:name":"Rochman France S.a.r.l.",
    "wof:placetype":"venue"
},
  "geometry": {"coordinates":[4.938025,45.778904],"type":"Point"}
}