{
  "type": "Feature",
  "properties": {
    "iso:country":"FR",
    "sg:address":"40 bis cours National; Saintes; 17100",
    "sg:classifiers":[
        {
            "category":"Banks & Credit Unions",
            "subcategory":"Bank",
            "type":"Services"
        }
    ],
    "sg:phone":"+33 3346930384",
    "sg:postcode":"17100",
    "sg:province":"Poitou-Charentes",
    "wof:name":"Banque Nationale De Paris",
    "wof:placetype":"venue"
},
  "geometry": {"coordinates":[-0.632732,45.747318],"type":"Point"}
}