{
  "type": "Feature",
  "properties": {
    "iso:country":"FR",
    "sg:address":"25, 1\u00e8re Avenue - ZI des Estroublans, 13127 Vitrolles",
    "sg:orig_category":"Unclassifiable Establishments",
    "sg:phone":"+33 4 42 89 01 05",
    "sg:province":"Midi Pyr\u00e9n\u00e9es",
    "wof:name":"M.a.e. S.a.r.l. - Mesure Automatisme Electronique",
    "wof:placetype":"venue"
},
  "geometry": {"coordinates":[5.238286,43.429127],"type":"Point"}
}