{
  "type": "Feature",
  "properties": {
    "addr:full":"6, Rue Marie Curie, 91701 Villiers sur Orge C\u00e9dex Basse Normandie",
    "addr:housenumber":"6",
    "addr:postcode":"91701",
    "addr:street":"Rue Marie Curie",
    "iso:country":"FR",
    "sg:address":"6, Rue Marie Curie, 91701 Villiers sur Orge C\u00e9dex",
    "sg:orig_category":"Non-Classified Establishments",
    "sg:phone":"+33 1 69 04 27 33",
    "sg:province":"Basse Normandie",
    "wof:name":"Cartonnages Chabany S.a.r.l.",
    "wof:placetype":"venue"
},
  "geometry": {"coordinates":[-117.62185700000001,34.146412],"type":"Point"}
}