{
  "type": "Feature",
  "properties": {
    "addr:full":"16, Rue Saint Joseph, 75002 Paris Ile de France 75002",
    "addr:housenumber":"16",
    "addr:postcode":"75002;75002",
    "addr:street":"Rue Saint Joseph",
    "iso:country":"FR",
    "sg:address":"16, Rue Saint Joseph, 75002 Paris",
    "sg:orig_category":"Non-Classified Establishments",
    "sg:phone":"+33 1 40 39 95 50",
    "sg:postcode":"75002",
    "sg:province":"Ile de France",
    "wof:name":"C.t.m. S.a.r.l. - Compagnie Des Tissus Modernes",
    "wof:placetype":"venue"
},
  "geometry": {"coordinates":[2.344438,48.868694],"type":"Point"}
}