{
  "type": "Feature",
  "properties": {
    "addr:full":"432, Rue des Grandes Teppes, 71000 M\u00e2con Sanc\u00e9 Bourgogne 71000",
    "addr:housenumber":"432",
    "addr:postcode":"71000;71000",
    "addr:street":"Rue Des Grandes Teppes",
    "iso:country":"FR",
    "sg:address":"432, Rue des Grandes Teppes, 71000 M\u00e2con",
    "sg:city":"Sanc\u00e9",
    "sg:orig_category":"Unclassifiable Establishments",
    "sg:phone":"+33 3 85 32 28 28",
    "sg:postcode":"71000",
    "sg:province":"Bourgogne",
    "wof:name":"Transports Nonin S.a.r.l.",
    "wof:placetype":"venue"
},
  "geometry": {"coordinates":[4.847217,46.360161],"type":"Point"}
}