{
  "type": "Feature",
  "properties": {
    "addr:full":"165, Rue Louis Mallet, 18000 Bourges Bourges Centre 18000",
    "addr:housenumber":"165",
    "addr:postcode":"18000;18000",
    "addr:street":"Rue Louis Mallet",
    "iso:country":"FR",
    "sg:address":"165, Rue Louis Mallet, 18000 Bourges",
    "sg:city":"Bourges",
    "sg:orig_category":"Non-Classified Establishments",
    "sg:phone":"+33 2 48 21 87 61",
    "sg:postcode":"18000",
    "sg:province":"Centre",
    "wof:name":"Satelit S.a.r.l.",
    "wof:placetype":"venue"
},
  "geometry": {"coordinates":[2.36268,47.081825],"type":"Point"}
}