{
  "type": "Feature",
  "properties": {
    "addr:full":"B.P. 28, 42660 Saint Genest Malifaux^^Rue de Saint Rambert, 42660 Saint Genest Malifaux Rhone-Alpes",
    "addr:postcode":"42660;42660",
    "addr:street":"B.P. 28;Genest;De Saint Rambert;Genest Malifaux Rhone-Alpes",
    "iso:country":"FR",
    "sg:address":"B.P. 28, 42660 Saint Genest Malifaux^^Rue de Saint Rambert, 42660 Saint Genest Malifaux",
    "sg:orig_category":"Non-Classified Establishments",
    "sg:phone":"+33 4 77 51 20 35",
    "sg:province":"Rhone-Alpes",
    "wof:name":"Fima Production Saint Genest S.a.",
    "wof:placetype":"venue"
},
  "geometry": {"coordinates":[4.399652,45.285004],"type":"Point"}
}