{
  "type": "Feature",
  "properties": {
    "iso:country":"FR",
    "sg:address":"Za De La Pile 13760 St Cannat",
    "sg:classifiers":[
        {
            "category":"Manufacturing",
            "subcategory":"Wood Products",
            "type":"Manufacturing & Wholesale Goods"
        }
    ],
    "sg:phone":"+33 4 42 50 68 17",
    "sg:province":"Provence-Alpes-C\u00f4te d'Azur",
    "sg:tags":[
        "professional",
        "furniture"
    ],
    "wof:name":"Les Ateliers",
    "wof:placetype":"venue"
},
  "geometry": {"coordinates":[5.298045,43.621151],"type":"Point"}
}