{
  "type": "Feature",
  "properties": {
    "iso:country":"FR",
    "sg:address":"185 Avenue Franklin Roosevelt 69150 Decines Charpieu",
    "sg:classifiers":[
        {
            "category":"Autos & Motor Vehicles",
            "subcategory":"Automobile Sales",
            "type":"Retail Goods"
        }
    ],
    "sg:phone":"+33 4 78 26 45 68",
    "sg:postcode":"69150",
    "sg:province":"Rhone-Alpes",
    "sg:tags":[
        "equipment",
        "motor-cars",
        "transport"
    ],
    "wof:name":"Kalli Mouloud",
    "wof:placetype":"venue"
},
  "geometry": {"coordinates":[4.93425,45.750153],"type":"Point"}
}