{
  "type": "Feature",
  "properties": {
    "addr:full":"18 Rue Denfert Rochereau 90000 Belfort Franche Comt\u00e9",
    "addr:housenumber":"18",
    "addr:postcode":"90000",
    "addr:street":"Rue Denfert Rochereau;Franche Comte\u0301",
    "iso:country":"FR",
    "sg:address":"18 Rue Denfert Rochereau 90000 Belfort",
    "sg:classifiers":[
        {
            "category":"Professional",
            "type":"Services"
        }
    ],
    "sg:phone":"+33 3 84 28 04 30",
    "sg:province":"Franche Comt\u00e9",
    "sg:tags":[
        "-",
        "related",
        "road",
        "transport"
    ],
    "wof:name":"Alphonse Charpiot Et Compagnie",
    "wof:placetype":"venue"
},
  "geometry": {"coordinates":[6.85861,47.634258],"type":"Point"}
}