{
  "type": "Feature",
  "properties": {
    "iso:country":"FR",
    "sg:address":"91280 Saint Pierre du Perray",
    "sg:orig_category":"Non-Classified Establishments",
    "sg:phone":"+33 1 60 81 17 50",
    "sg:province":"Ile de France",
    "wof:name":"Sagem S.a.",
    "wof:placetype":"venue"
},
  "geometry": {"coordinates":[2.494705,48.612675],"type":"Point"}
}