{
  "type": "Feature",
  "properties": {
    "addr:full":"12370 Murasson Midi Pyr\u00e9n\u00e9es 12370",
    "addr:housenumber":"12370",
    "addr:postcode":"12370",
    "addr:street":"Murasson Midi Pyre\u0301Ne\u0301Es",
    "iso:country":"FR",
    "sg:address":"12370 Murasson",
    "sg:classifiers":[
        {
            "category":"Wholesale",
            "subcategory":"Meat",
            "type":"Manufacturing & Wholesale Goods"
        }
    ],
    "sg:phone":"+33 5 65 99 95 83",
    "sg:postcode":"12370",
    "sg:province":"Midi Pyr\u00e9n\u00e9es",
    "sg:tags":[
        "food",
        "cooked",
        "product",
        "related"
    ],
    "wof:name":"Sarl Salaisons Du Landoulet",
    "wof:placetype":"venue"
},
  "geometry": {"coordinates":[2.762959,43.76086],"type":"Point"}
}