{
  "type": "Feature",
  "properties": {
    "iso:country":"FR",
    "sg:address":"12370 Murasson",
    "sg:classifiers":[
        {
            "category":"Wholesale",
            "subcategory":"Meat",
            "type":"Manufacturing & Wholesale Goods"
        }
    ],
    "sg:phone":"+33 5 65 99 95 83",
    "sg:postcode":"12370",
    "sg:province":"Midi Pyr\u00e9n\u00e9es",
    "sg:tags":[
        "food",
        "cooked",
        "product",
        "related"
    ],
    "wof:name":"Sarl Salaisons Du Landoulet",
    "wof:placetype":"venue"
},
  "geometry": {"coordinates":[2.762959,43.76086],"type":"Point"}
}