{
  "type": "Feature",
  "properties": {
    "addr:full":"6, Rue de Nantes, 75019 Paris Ile de France",
    "addr:housenumber":"6",
    "addr:postcode":"75019",
    "addr:street":"Rue De Nantes",
    "iso:country":"FR",
    "sg:address":"6, Rue de Nantes, 75019 Paris",
    "sg:orig_category":"Non-Classified Establishments",
    "sg:phone":"+33 1 40 38 00 33",
    "sg:province":"Ile de France",
    "wof:name":"Print Offset Promo Service S.a.",
    "wof:placetype":"venue"
},
  "geometry": {"coordinates":[2.383469,48.891262],"type":"Point"}
}