{
  "type": "Feature",
  "properties": {
    "addr:full":"Rue Marcel Nogrette Brionne Haute Normandie 27800",
    "addr:postcode":"27800",
    "addr:street":"Rue Marcel Nogrette;Haute Normandie",
    "iso:country":"FR",
    "sg:address":"Rue Marcel Nogrette",
    "sg:city":"Brionne",
    "sg:orig_category":"Non-Classified Establishments",
    "sg:phone":"+33 2 32 47 40 60",
    "sg:postcode":"27800",
    "sg:province":"Haute Normandie",
    "wof:name":"Compin S.a.",
    "wof:placetype":"venue"
},
  "geometry": {"coordinates":[0.71516,49.202156],"type":"Point"}
}