{
  "type": "Feature",
  "properties": {
    "addr:full":"101 Boulevard Richard Lenoir 75011 Paris Ile de France",
    "addr:housenumber":"101",
    "addr:postcode":"75011",
    "addr:street":"Boulevard Richard Lenoir",
    "iso:country":"FR",
    "sg:address":"101 Boulevard Richard Lenoir 75011 Paris",
    "sg:classifiers":[
        {
            "category":"Utilities",
            "subcategory":"Telephone",
            "type":"Services"
        }
    ],
    "sg:phone":"+33 1 48 06 29 05",
    "sg:province":"Ile de France",
    "sg:tags":[
        "telecommunication"
    ],
    "wof:name":"A 3 Pub",
    "wof:placetype":"venue"
},
  "geometry": {"coordinates":[2.370569,48.864014],"type":"Point"}
}