{
  "type": "Feature",
  "properties": {
    "addr:full":"18, Rue des Granges Galand - ZA des Granges Galand, 37550 Saint Avertin Saint-Avertin Centre 37550",
    "addr:housenumber":"18;saint-avertin",
    "addr:postcode":"37550;37550",
    "addr:street":"Rue Des Granges Galand Za Des Granges Galand",
    "iso:country":"FR",
    "sg:address":"18, Rue des Granges Galand - ZA des Granges Galand, 37550 Saint Avertin",
    "sg:city":"Saint-Avertin",
    "sg:orig_category":"Unclassifiable Establishments",
    "sg:phone":"+33 2 47 71 25 50",
    "sg:postcode":"37550",
    "sg:province":"Centre",
    "wof:name":"Mj 80 Equipement Industriel S.a.",
    "wof:placetype":"venue"
},
  "geometry": {"coordinates":[0.718577,47.369476],"type":"Point"}
}