{
  "type": "Feature",
  "properties": {
    "addr:full":"ZI les Iles Cord\u00e9s Veurey Voroize Rhone-Alpes 38113",
    "addr:postcode":"38113",
    "addr:street":"Zi Les Iles Corde\u0301S Veurey Voroize Rhone-Alpes",
    "iso:country":"FR",
    "sg:address":"ZI les Iles Cord\u00e9s",
    "sg:city":"Veurey Voroize",
    "sg:orig_category":"Non-Classified Establishments",
    "sg:phone":"+33 4 76 53 70 70",
    "sg:postcode":"38113",
    "sg:province":"Rhone-Alpes",
    "wof:name":"Safite Rh\u00f4ne-alpes S.a.r.l.",
    "wof:placetype":"venue"
},
  "geometry": {"coordinates":[5.613688,45.271927],"type":"Point"}
}