{
  "type": "Feature",
  "properties": {
    "addr:full":"13, rue de la Perdrix - ZI Paris Nord, 95700 Roissy en France Ile de France",
    "addr:housenumber":"13",
    "addr:postcode":"95700",
    "addr:street":"Rue De La Perdrix Zi",
    "iso:country":"FR",
    "sg:address":"13, rue de la Perdrix - ZI Paris Nord, 95700 Roissy en France",
    "sg:orig_category":"Unclassifiable Establishments",
    "sg:phone":"+33 1 48 17 21 99",
    "sg:province":"Ile de France",
    "wof:name":"Johnson Matthey S.a.",
    "wof:placetype":"venue"
},
  "geometry": {"coordinates":[2.517005,49.003883],"type":"Point"}
}