{
  "type": "Feature",
  "properties": {
    "addr:full":"18 rue Mado Robin 26000 Valence Rhone-Alpes 26000",
    "addr:housenumber":"18",
    "addr:postcode":"26000;26000",
    "addr:street":"Rue Mado Robin",
    "iso:country":"FR",
    "sg:address":"18 rue Mado Robin 26000 Valence",
    "sg:classifiers":[
        {
            "category":"Shopping",
            "subcategory":"Beauty & Cosmetics",
            "type":"Retail Goods"
        }
    ],
    "sg:phone":"+33 4 75 82 10 20",
    "sg:postcode":"26000",
    "sg:province":"Rhone-Alpes",
    "sg:tags":[
        "natural"
    ],
    "wof:name":"Sla Creation S.a.",
    "wof:placetype":"venue"
},
  "geometry": {"coordinates":[4.925785,44.92617],"type":"Point"}
}