{
  "type": "Feature",
  "properties": {
    "iso:country":"FR",
    "sg:address":"Petit Port Des Seynes 17320 Marennes",
    "sg:classifiers":[
        {
            "category":"Manufacturing",
            "subcategory":"Chemicals & Compounds",
            "type":"Manufacturing & Wholesale Goods"
        }
    ],
    "sg:phone":"+33 5 46 85 07 34",
    "sg:postcode":"17320",
    "sg:province":"Poitou-Charentes",
    "sg:tags":[
        "pharmaceutical",
        "chemistry",
        "-",
        "by-product"
    ],
    "wof:name":"Oleronlac (sa)",
    "wof:placetype":"venue"
},
  "geometry": {"coordinates":[-1.099493,45.805401],"type":"Point"}
}