{
  "type": "Feature",
  "properties": {
    "addr:full":"42 Rue Du Docteur Jean Fiolle 13006 Marseille Poitou-Charentes",
    "addr:housenumber":"42",
    "addr:postcode":"13006",
    "addr:street":"Rue Du Docteur Jean Fiolle",
    "iso:country":"FR",
    "sg:address":"42 Rue Du Docteur Jean Fiolle 13006 Marseille",
    "sg:classifiers":[
        {
            "category":"Shopping",
            "subcategory":"Hobbies, Toys, & Games",
            "type":"Retail Goods"
        }
    ],
    "sg:phone":"+33 4 91 37 94 94",
    "sg:province":"Poitou-Charentes",
    "sg:tags":[
        "product",
        "miscellaneous",
        "entertainment"
    ],
    "wof:name":"Star Mediterranee",
    "wof:placetype":"venue"
},
  "geometry": {"coordinates":[5.380915,43.284676],"type":"Point"}
}