{
  "type": "Feature",
  "properties": {
    "addr:full":"Av. Louis Lescure - ZI de Boulazac Boulazac Aquitaine 24750",
    "addr:postcode":"24750",
    "addr:street":"Av. Louis Lescure Zi De Boulazac",
    "iso:country":"FR",
    "sg:address":"Av. Louis Lescure - ZI de Boulazac",
    "sg:city":"Boulazac",
    "sg:orig_category":"Non-Classified Establishments",
    "sg:phone":"+33 5 53 02 73 73",
    "sg:postcode":"24750",
    "sg:province":"Aquitaine",
    "wof:name":"Sobeval Elevage S.a.",
    "wof:placetype":"venue"
},
  "geometry": {"coordinates":[0.789735,45.09977],"type":"Point"}
}