{
  "type": "Feature",
  "properties": {
    "addr:full":"31, Bd Paul Langevin, 38600 Fontaine Rhone-Alpes",
    "addr:housenumber":"31",
    "addr:postcode":"38600",
    "addr:street":"Bd Paul Langevin",
    "iso:country":"FR",
    "sg:address":"31, Bd Paul Langevin, 38600 Fontaine",
    "sg:orig_category":"Unclassifiable Establishments",
    "sg:phone":"+33 4 76 84 00 56",
    "sg:province":"Rhone-Alpes",
    "wof:name":"S2ns S.a.r.l.",
    "wof:placetype":"venue"
},
  "geometry": {"coordinates":[5.683144,45.189049],"type":"Point"}
}