{
  "type": "Feature",
  "properties": {
    "iso:country":"FR",
    "sg:address":"4 R Des Voyeux 77860 St Germain Sur Morin",
    "sg:classifiers":[
        {
            "category":"Manufacturing",
            "subcategory":"Tools & Machinery",
            "type":"Manufacturing & Wholesale Goods"
        }
    ],
    "sg:phone":"+33 1 60 04 70 51",
    "sg:postcode":"77860",
    "sg:province":"Ile de France",
    "sg:tags":[
        "equipment",
        "measurement",
        "-",
        "precision",
        "instrument"
    ],
    "wof:name":"Jpc Sarl",
    "wof:placetype":"venue"
},
  "geometry": {"coordinates":[2.851542,48.884678],"type":"Point"}
}