{
  "type": "Feature",
  "properties": {
    "iso:country":"FR",
    "sg:address":"Rue de Verdet",
    "sg:city":"Bergerac",
    "sg:orig_category":"Unclassifiable Establishments",
    "sg:phone":"+33 5 53 57 08 30",
    "sg:postcode":"24100",
    "sg:province":"Aquitaine",
    "wof:name":"Etablissements Jean Chambon S.a.",
    "wof:placetype":"venue"
},
  "geometry": {"coordinates":[0.45362,44.815235],"type":"Point"}
}