{
  "type": "Feature",
  "properties": {
    "addr:full":"6, Place Aristide Briand, 52000 Chaumont Champagne",
    "addr:housenumber":"6",
    "addr:postcode":"52000",
    "addr:street":"Place Aristide Briand",
    "iso:country":"FR",
    "sg:address":"6, Place Aristide Briand, 52000 Chaumont",
    "sg:orig_category":"Unclassifiable Establishments",
    "sg:phone":"+33 3 25 32 19 87",
    "sg:province":"Champagne",
    "wof:name":"Devarennes Fils S.a.",
    "wof:placetype":"venue"
},
  "geometry": {"coordinates":[5.142533,48.116951],"type":"Point"}
}