{
  "type": "Feature",
  "properties": {
    "iso:country":"FR",
    "sg:address":"52",
    "sg:city":"Gare 08800 Hautes Rivi\u00e8res (Les)",
    "sg:classifiers":[
        {
            "category":"Manufacturing",
            "subcategory":"Metals",
            "type":"Manufacturing & Wholesale Goods"
        }
    ],
    "sg:phone":"+33 3 24 53 40 20",
    "sg:postcode":"08800",
    "sg:province":"Champagne",
    "sg:tags":[
        "metallurgy",
        "metalworking",
        "processing"
    ],
    "wof:name":"Barre - Servais Et Cie",
    "wof:placetype":"venue"
},
  "geometry": {"coordinates":[4.83685,49.888538],"type":"Point"}
}