{
  "type": "Feature",
  "properties": {
    "addr:full":"2, All\u00e9e des Flamands, 33290 Blanquefort Blanquefort Aquitaine 33290",
    "addr:housenumber":"2",
    "addr:postcode":"33290;33290",
    "addr:street":"Alle\u0301E Des Flamands",
    "iso:country":"FR",
    "sg:address":"2, All\u00e9e des Flamands, 33290 Blanquefort",
    "sg:city":"Blanquefort",
    "sg:orig_category":"Non-Classified Establishments",
    "sg:phone":"+33 5 56 35 21 81",
    "sg:postcode":"33290",
    "sg:province":"Aquitaine",
    "wof:name":"G.s.m. S.a.",
    "wof:placetype":"venue"
},
  "geometry": {"coordinates":[-0.567626,44.93018],"type":"Point"}
}