{
  "type": "Feature",
  "properties": {
    "iso:country":"FR",
    "sg:address":"61, Rue JB Colbert - ZI Ouest, 10600 La Chapelle Saint Luc",
    "sg:orig_category":"Unclassifiable Establishments",
    "sg:phone":"+33 3 25 71 93 55",
    "sg:province":"Champagne",
    "wof:name":"Begaud Entreprise E.u.r.l.",
    "wof:placetype":"venue"
},
  "geometry": {"coordinates":[4.04779,48.311729],"type":"Point"}
}