{
  "type": "Feature",
  "properties": {
    "addr:full":"7, Rue de l'Horloge, 63720 Ennezat Ennezat Auvergne 63720",
    "addr:housenumber":"7",
    "addr:postcode":"63720;63720",
    "addr:street":"Rue De L'Horloge",
    "iso:country":"FR",
    "sg:address":"7, Rue de l'Horloge, 63720 Ennezat",
    "sg:city":"Ennezat",
    "sg:orig_category":"Non-Classified Establishments",
    "sg:phone":"+33 4 73 63 96 17",
    "sg:postcode":"63720",
    "sg:province":"Auvergne",
    "wof:name":"Cth",
    "wof:placetype":"venue"
},
  "geometry": {"coordinates":[3.223731,45.897285],"type":"Point"}
}