{
  "type": "Feature",
  "properties": {
    "addr:full":"12 Rue Charles Martigny 94700 Maisons Alfort Ile de France 94700",
    "addr:housenumber":"12",
    "addr:postcode":"94700;94700",
    "addr:street":"Rue Charles Martigny",
    "iso:country":"FR",
    "sg:address":"12 Rue Charles Martigny 94700 Maisons Alfort",
    "sg:classifiers":[
        {
            "category":"Manufacturing",
            "subcategory":"Textiles",
            "type":"Manufacturing & Wholesale Goods"
        }
    ],
    "sg:phone":"+33 1 48 98 51 49",
    "sg:postcode":"94700",
    "sg:province":"Ile de France",
    "sg:tags":[
        "printing",
        "clothing",
        "fabric"
    ],
    "wof:name":"Etablissements Gaspar Psssy",
    "wof:placetype":"venue"
},
  "geometry": {"coordinates":[2.436292,48.789581],"type":"Point"}
}