{
  "type": "Feature",
  "properties": {
    "iso:country":"FR",
    "sg:address":"Za Motte 22690 Pleudihen Sur Rance",
    "sg:city":"La Vicomt\u00e9-sur-Rance",
    "sg:classifiers":[
        {
            "category":"Shopping",
            "subcategory":"Clothing, Apparel, & Fashions",
            "type":"Retail Goods"
        }
    ],
    "sg:phone":"+33 2 96 83 38 38",
    "sg:postcode":"22690",
    "sg:province":"Bretagne",
    "sg:tags":[
        "textile",
        "clothing",
        "clothes"
    ],
    "wof:name":"Madame De Rance Sas",
    "wof:placetype":"venue"
},
  "geometry": {"coordinates":[-1.951554,48.510845],"type":"Point"}
}