{
  "type": "Feature",
  "properties": {
    "iso:country":"FR",
    "sg:address":"Rte Sologne 41320 Mennetou Sur Cher",
    "sg:city":"Ch\u00e2tres-sur-Cher",
    "sg:classifiers":[
        {
            "category":"Manufacturing",
            "subcategory":"Paper Products",
            "type":"Manufacturing & Wholesale Goods"
        }
    ],
    "sg:phone":"+33 2 54 98 03 40",
    "sg:postcode":"41320",
    "sg:province":"Centre",
    "sg:tags":[
        "packaging",
        "material",
        "-",
        "cardboard"
    ],
    "wof:name":"2 Cp Sa",
    "wof:placetype":"venue"
},
  "geometry": {"coordinates":[1.879796,47.296234],"type":"Point"}
}