{
  "type": "Feature",
  "properties": {
    "addr:full":"33, Rue Lamartine, 49130 Les Ponts de C\u00e9 Pays de Loire",
    "addr:housenumber":"33",
    "addr:postcode":"49130",
    "addr:street":"Rue Lamartine;Ponts De Ce\u0301",
    "iso:country":"FR",
    "sg:address":"33, Rue Lamartine, 49130 Les Ponts de C\u00e9",
    "sg:orig_category":"Unclassifiable Establishments",
    "sg:phone":"+33 2 41 69 04 20",
    "sg:province":"Pays de Loire",
    "wof:name":"T.r.d.l. S.a.r.l.",
    "wof:placetype":"venue"
},
  "geometry": {"coordinates":[-0.486692,47.435783],"type":"Point"}
}