{
  "type": "Feature",
  "properties": {
    "iso:country":"FR",
    "sg:address":"2, Rue Jean Perronet, 30000 N\u00eemes",
    "sg:orig_category":"Non-Classified Establishments",
    "sg:phone":"+33 4 66 02 19 30",
    "sg:province":"Languedoc-Roussillon",
    "wof:name":"Nor\u00e9mat S.a.",
    "wof:placetype":"venue"
},
  "geometry": {"coordinates":[4.42157,43.833569],"type":"Point"}
}