{
  "type": "Feature",
  "properties": {
    "addr:full":"34 Rue Vezelois 90400 Danjoutin Franche Comt\u00e9 90400",
    "addr:housenumber":"34",
    "addr:postcode":"90400;90400",
    "addr:street":"Rue Vezelois;Franche Comte\u0301",
    "iso:country":"FR",
    "sg:address":"34 Rue Vezelois 90400 Danjoutin",
    "sg:classifiers":[
        {
            "category":"Wholesale",
            "subcategory":"Medical Equipment & Supplies",
            "type":"Manufacturing & Wholesale Goods"
        }
    ],
    "sg:phone":"+33 3 84 28 58 83",
    "sg:postcode":"90400",
    "sg:province":"Franche Comt\u00e9",
    "sg:tags":[
        "instrument",
        "health",
        "-",
        "precision"
    ],
    "wof:name":"Fresse",
    "wof:placetype":"venue"
},
  "geometry": {"coordinates":[6.875309,47.619995],"type":"Point"}
}