{
  "type": "Feature",
  "properties": {
    "iso:country":"FR",
    "sg:address":"128, Av. de la R\u00e9publique, 44600 Saint Nazaire",
    "sg:orig_category":"Unclassifiable Establishments",
    "sg:phone":"+33 2 40 22 52 52",
    "sg:province":"Pays de Loire",
    "wof:name":"Instant S.a.",
    "wof:placetype":"venue"
},
  "geometry": {"coordinates":[-2.210441,47.284878],"type":"Point"}
}