{
  "type": "Feature",
  "properties": {
    "addr:full":"4/6, Rue Edouard Vaillant, 91200 Athis Mons Ile de France",
    "addr:housenumber":"4 / 6",
    "addr:postcode":"91200",
    "addr:street":"Rue Edouard Vaillant",
    "iso:country":"FR",
    "sg:address":"4/6, Rue Edouard Vaillant, 91200 Athis Mons",
    "sg:orig_category":"Unclassifiable Establishments",
    "sg:phone":"+33 1 69 54 10 10",
    "sg:province":"Ile de France",
    "wof:name":"Heudebert S.a.",
    "wof:placetype":"venue"
},
  "geometry": {"coordinates":[2.392905,48.70528],"type":"Point"}
}