{
  "type": "Feature",
  "properties": {
    "addr:full":"118 Rue La Fayette 75010 Paris Ile de France",
    "addr:housenumber":"118",
    "addr:postcode":"75010",
    "addr:street":"Rue La Fayette",
    "iso:country":"FR",
    "sg:address":"118 Rue La Fayette 75010 Paris",
    "sg:classifiers":[
        {
            "category":"Manufacturing",
            "subcategory":"Printing",
            "type":"Manufacturing & Wholesale Goods"
        }
    ],
    "sg:phone":"+33 1 45 23 00 07",
    "sg:province":"Ile de France",
    "sg:tags":[
        "publishing"
    ],
    "wof:name":"France Loisirs (fl)",
    "wof:placetype":"venue"
},
  "geometry": {"coordinates":[2.352548,48.877941],"type":"Point"}
}