{
  "type": "Feature",
  "properties": {
    "iso:country":"FR",
    "sg:address":"1, Place de l'Eglise, 41240 Saint Laurent des Bois",
    "sg:city":"Autainville",
    "sg:orig_category":"Unclassifiable Establishments",
    "sg:phone":"+33 2 54 82 20 86",
    "sg:postcode":"41240",
    "sg:province":"Centre",
    "wof:name":"Sodexe",
    "wof:placetype":"venue"
},
  "geometry": {"coordinates":[1.448023,47.851364],"type":"Point"}
}