{
  "type": "Feature",
  "properties": {
    "addr:full":"Av. du Mar\u00e9chal Foch Clermont l'H\u00e9rault Languedoc-Roussillon 34800",
    "addr:postcode":"34800",
    "addr:street":"Av. Du Mare\u0301Chal Foch;\u0301Rault",
    "iso:country":"FR",
    "sg:address":"Av. du Mar\u00e9chal Foch",
    "sg:city":"Clermont l'H\u00e9rault",
    "sg:orig_category":"Unclassifiable Establishments",
    "sg:phone":"+33 4 67 96 00 11",
    "sg:postcode":"34800",
    "sg:province":"Languedoc-Roussillon",
    "wof:name":"Maison Clovis Salasc S.a.",
    "wof:placetype":"venue"
},
  "geometry": {"coordinates":[3.433762,43.625179],"type":"Point"}
}