{
  "type": "Feature",
  "properties": {
    "addr:full":"Avenue Paul Girod 73400 Ugine Rhone-Alpes 73400",
    "addr:postcode":"73400;73400",
    "addr:street":"Avenue Paul Girod",
    "iso:country":"FR",
    "sg:address":"Avenue Paul Girod 73400 Ugine",
    "sg:classifiers":[
        {
            "category":"Farming",
            "subcategory":"Livestock Farm",
            "type":"Manufacturing & Wholesale Goods"
        }
    ],
    "sg:phone":"+33 4 79 37 31 58",
    "sg:postcode":"73400",
    "sg:province":"Rhone-Alpes",
    "sg:tags":[
        "breeding",
        "agriculture",
        "animal"
    ],
    "wof:name":"Paccard (ets) Sarl",
    "wof:placetype":"venue"
},
  "geometry": {"coordinates":[6.424925,45.746193],"type":"Point"}
}