{
  "type": "Feature",
  "properties": {
    "addr:full":"av de Tournamy; Mougins Picardie",
    "addr:street":"Av De Tournamy",
    "iso:country":"FR",
    "sg:address":"av de Tournamy; Mougins",
    "sg:classifiers":[
        {
            "category":"Banks & Credit Unions",
            "subcategory":"Bank",
            "type":"Services"
        }
    ],
    "sg:phone":"+33 3393900972",
    "sg:province":"Picardie",
    "wof:name":"Cr\u00e9dit Agricole Des Alpes Maritimes",
    "wof:placetype":"venue"
},
  "geometry": {"coordinates":[6.987094,43.603397],"type":"Point"}
}