{
  "type": "Feature",
  "properties": {
    "addr:full":"Rn 83 De Bourg 01390 Mionnay Rhone-Alpes 01390",
    "addr:postcode":"01390;01390",
    "addr:street":"Rn 83 De Bourg",
    "iso:country":"FR",
    "sg:address":"Rn 83",
    "sg:city":"De Bourg 01390 Mionnay",
    "sg:classifiers":[
        {
            "category":"Travel",
            "subcategory":"Hotels & Motels",
            "type":"Entertainment"
        }
    ],
    "sg:phone":"+33 4 78 91 82 02",
    "sg:postcode":"01390",
    "sg:province":"Rhone-Alpes",
    "sg:tags":[
        "hotels",
        "business",
        "restaurant"
    ],
    "wof:name":"Restaurant Chapel Sa",
    "wof:placetype":"venue"
},
  "geometry": {"coordinates":[4.93107,45.919559],"type":"Point"}
}