{
  "type": "Feature",
  "properties": {
    "addr:full":"ZI Campagne les Hesdin Campagne l\u00e8s Hesdin Nord Pas-de-Calais 62870",
    "addr:postcode":"62870",
    "addr:street":"Pas-De-Calais",
    "iso:country":"FR",
    "sg:address":"ZI Campagne les Hesdin",
    "sg:city":"Campagne l\u00e8s Hesdin",
    "sg:orig_category":"Unclassifiable Establishments",
    "sg:phone":"+33 3 21 81 32 59",
    "sg:postcode":"62870",
    "sg:province":"Nord Pas-de-Calais",
    "wof:name":"Kett Fr\u00e8res S.a.r.l.",
    "wof:placetype":"venue"
},
  "geometry": {"coordinates":[1.8815,50.398579],"type":"Point"}
}