{
  "type": "Feature",
  "properties": {
    "iso:country":"FR",
    "sg:address":"4, Rue Girlenhirsch, 67400 Illkirch Graffenstaden",
    "sg:city":"Geispolsheim",
    "sg:orig_category":"Non-Classified Establishments",
    "sg:phone":"+33 3 88 55 29 30",
    "sg:postcode":"67400",
    "sg:province":"Alsace",
    "wof:name":"Pharma Dom S.a.",
    "wof:placetype":"venue"
},
  "geometry": {"coordinates":[7.707798,48.516247],"type":"Point"}
}