{
  "type": "Feature",
  "properties": {
    "addr:full":"53 Av Du 15 Septembre 15290 Le Rouget Le Rouget Auvergne 15290",
    "addr:postcode":"15290;15290",
    "addr:street":"53 Av Du 15 Septembre",
    "iso:country":"FR",
    "sg:address":"53 Av Du 15 Septembre 15290 Le Rouget",
    "sg:city":"Le Rouget",
    "sg:classifiers":[
        {
            "category":"Wholesale",
            "subcategory":"Meat",
            "type":"Manufacturing & Wholesale Goods"
        }
    ],
    "sg:phone":"+33 4 71 46 10 19",
    "sg:postcode":"15290",
    "sg:province":"Auvergne",
    "sg:tags":[
        "food",
        "cooked",
        "product",
        "related"
    ],
    "wof:name":"Mas Sa",
    "wof:placetype":"venue"
},
  "geometry": {"coordinates":[2.232944,44.855175],"type":"Point"}
}