{
  "type": "Feature",
  "properties": {
    "iso:country":"FR",
    "sg:address":"22 pl de la Madeleine; Paris; 75008",
    "sg:classifiers":[
        {
            "category":"Banks & Credit Unions",
            "subcategory":"Bank",
            "type":"Services"
        }
    ],
    "sg:phone":"+33 1 42 65 25 83",
    "sg:postcode":"75008",
    "sg:province":"Ile de France",
    "wof:name":"Union De Banques \u00e0 Paris, \u00e0 Paris",
    "wof:placetype":"venue"
},
  "geometry": {"coordinates":[2.325693,48.870224],"type":"Point"}
}