{
  "type": "Feature",
  "properties": {
    "addr:full":"5, Rue Jean Rochon, 63000 Clermont Ferrand Clermont-Ferrand Auvergne 63000",
    "addr:housenumber":"5",
    "addr:postcode":"63000;63000",
    "addr:street":"Rue Jean Rochon",
    "iso:country":"FR",
    "sg:address":"5, Rue Jean Rochon, 63000 Clermont Ferrand",
    "sg:city":"Clermont-Ferrand",
    "sg:orig_category":"Non-Classified Establishments",
    "sg:phone":"+33 4 73 19 24 10",
    "sg:postcode":"63000",
    "sg:province":"Auvergne",
    "wof:name":"Garon Bonvalot S.a.",
    "wof:placetype":"venue"
},
  "geometry": {"coordinates":[3.081937,45.779125],"type":"Point"}
}