{
  "type": "Feature",
  "properties": {
    "addr:full":"11, Av. du Granier, 38240 Meylan Rhone-Alpes 38240",
    "addr:postcode":"38240;38240",
    "addr:street":"11 Av. Du Granier",
    "iso:country":"FR",
    "sg:address":"11, Av. du Granier, 38240 Meylan",
    "sg:orig_category":"Non-Classified Establishments",
    "sg:phone":"+33 4 76 90 40 24",
    "sg:postcode":"38240",
    "sg:province":"Rhone-Alpes",
    "wof:name":"Etablissements Pesquet S.a.r.l.",
    "wof:placetype":"venue"
},
  "geometry": {"coordinates":[5.780916,45.209484],"type":"Point"}
}