{
  "type": "Feature",
  "properties": {
    "iso:country":"FR",
    "sg:address":"1 Rte Herrlisheim 67410 Drusenheim",
    "sg:city":"Drusenheim",
    "sg:classifiers":[
        {
            "category":"Wholesale",
            "subcategory":"Machinery & Supplies",
            "type":"Manufacturing & Wholesale Goods"
        }
    ],
    "sg:phone":"+33 3 88 90 62 62",
    "sg:postcode":"67410",
    "sg:province":"Alsace",
    "sg:tags":[
        "handling",
        "material",
        "-",
        "machine",
        "equipment",
        "engineering",
        "mechanical"
    ],
    "wof:name":"Ateliers Reunis Caddie",
    "wof:placetype":"venue"
},
  "geometry": {"coordinates":[7.934591,48.74958],"type":"Point"}
}