{
  "type": "Feature",
  "properties": {
    "iso:country":"FR",
    "sg:address":"61, Rte de Saint Montaine, 18700 Aubigny sur N\u00e8re",
    "sg:city":"Aubigny-sur-N\u00e8re",
    "sg:orig_category":"Non-Classified Establishments",
    "sg:phone":"+33 2 48 81 51 70",
    "sg:postcode":"18700",
    "sg:province":"Centre",
    "wof:name":"Risoud Pr\u00e9cision S.a.",
    "wof:placetype":"venue"
},
  "geometry": {"coordinates":[2.42544,47.488972],"type":"Point"}
}