{
  "type": "Feature",
  "properties": {
    "addr:full":"5, Rue Camille Saint Saens, 38300 Bourgoin Jallieu Rhone-Alpes 38300",
    "addr:housenumber":"5",
    "addr:postcode":"38300;38300",
    "addr:street":"Rue Camille Saint Saens;Rhone-Alpes",
    "iso:country":"FR",
    "sg:address":"5, Rue Camille Saint Saens, 38300 Bourgoin Jallieu",
    "sg:orig_category":"Unclassifiable Establishments",
    "sg:phone":"+33 4 74 28 33 31",
    "sg:postcode":"38300",
    "sg:province":"Rhone-Alpes",
    "wof:name":"Sadec S.a.r.l.",
    "wof:placetype":"venue"
},
  "geometry": {"coordinates":[5.271426,45.605968],"type":"Point"}
}