{
  "type": "Feature",
  "properties": {
    "iso:country":"FR",
    "sg:address":"Z I De Moutti Sud 74540 Alby Sur Cheran",
    "sg:classifiers":[
        {
            "category":"Home & Garden",
            "subcategory":"Kitchen Supply",
            "type":"Retail Goods"
        }
    ],
    "sg:phone":"+33 4 50 68 34 30",
    "sg:postcode":"74540",
    "sg:province":"Rhone-Alpes",
    "sg:tags":[
        "item",
        "commercial",
        "disposable"
    ],
    "wof:name":"Julius Blum France Sarl",
    "wof:placetype":"venue"
},
  "geometry": {"coordinates":[6.079054,45.751701],"type":"Point"}
}