{
  "type": "Feature",
  "properties": {
    "addr:full":"B.P. 14, 50110 Tourlaville^^Rue Jean Bovin, 50110 Tourlaville Tourlaville Basse Normandie 50110",
    "addr:postcode":"50110;50110;50110",
    "addr:street":"B.P. 14",
    "iso:country":"FR",
    "sg:address":"B.P. 14, 50110 Tourlaville^^Rue Jean Bovin, 50110 Tourlaville",
    "sg:city":"Tourlaville",
    "sg:orig_category":"Non-Classified Establishments",
    "sg:phone":"+33 2 33 88 51 00",
    "sg:postcode":"50110",
    "sg:province":"Basse Normandie",
    "wof:name":"S.t.n. S.a. - Soci\u00e9t\u00e9 De Transports De Normandie",
    "wof:placetype":"venue"
},
  "geometry": {"coordinates":[-1.524824,49.60664],"type":"Point"}
}