{
  "type": "Feature",
  "properties": {
    "addr:full":"18 Av Amp\u00e8re 91320 Wissous Ile de France 91320",
    "addr:postcode":"91320;ile;91320",
    "addr:street":"18 Av Ampe\u0300Re;France",
    "iso:country":"FR",
    "sg:address":"18 Av Amp\u00e8re 91320 Wissous",
    "sg:classifiers":[
        {
            "category":"Shopping",
            "subcategory":"Clothing, Apparel, & Fashions",
            "type":"Retail Goods"
        }
    ],
    "sg:phone":"+33 1 69 81 46 46",
    "sg:postcode":"91320",
    "sg:province":"Ile de France",
    "sg:tags":[
        "textile",
        "clothing",
        "clothes"
    ],
    "wof:name":"Du Pareil Au Meme Sa",
    "wof:placetype":"venue"
},
  "geometry": {"coordinates":[2.320539,48.728291],"type":"Point"}
}