{
  "type": "Feature",
  "properties": {
    "addr:full":"Rte de Sorle le Ch\u00e2teau - ZI de la Sacra Ferri\u00e8re la Petite Nord Pas-de-Calais 59680",
    "addr:postcode":"59680",
    "addr:street":"Rte De Sorle;Pas-De-Calais",
    "iso:country":"FR",
    "sg:address":"Rte de Sorle le Ch\u00e2teau - ZI de la Sacra",
    "sg:city":"Ferri\u00e8re la Petite",
    "sg:orig_category":"Non-Classified Establishments",
    "sg:phone":"+33 3 27 65 73 41",
    "sg:postcode":"59680",
    "sg:province":"Nord Pas-de-Calais",
    "wof:name":"E.d.i. S.a.r.l. - Etudes Et D\u00e9veloppements Industriels",
    "wof:placetype":"venue"
},
  "geometry": {"coordinates":[4.076595,50.253876],"type":"Point"}
}