{
  "type": "Feature",
  "properties": {
    "addr:full":"B.P. 4101 Rouen C\u00e9dex^^76000 Rouen Haute Normandie 76020",
    "addr:housenumber":"4101",
    "addr:postcode":"76020",
    "addr:street":"B.P.;Haute Normandie",
    "iso:country":"FR",
    "sg:address":"B.P. 4101",
    "sg:city":"Rouen C\u00e9dex^^76000 Rouen",
    "sg:orig_category":"Non-Classified Establishments",
    "sg:phone":"+33 2 35 98 41 60",
    "sg:postcode":"76020",
    "sg:province":"Haute Normandie",
    "wof:name":"S\u00e9rimatec S.a. - Soci\u00e9t\u00e9 D'etudes Et R\u00e9alisation Industrielle De Manutention Technique",
    "wof:placetype":"venue"
},
  "geometry": {"coordinates":[1.08933,49.44038],"type":"Point"}
}