{
  "type": "Feature",
  "properties": {
    "iso:country":"FR",
    "sg:address":"B.P. 18, 45450 Fay aux Loges C\u00e9dex^^7, Rue Notre Dame, 45450 Fay aux Loges",
    "sg:city":"Fay-aux-Loges",
    "sg:orig_category":"Non-Classified Establishments",
    "sg:phone":"+33 2 38 59 57 28",
    "sg:postcode":"45450",
    "sg:province":"Centre",
    "wof:name":"Rousselet Pascal",
    "wof:placetype":"venue"
},
  "geometry": {"coordinates":[2.11513,47.891796],"type":"Point"}
}