{
  "type": "Feature",
  "properties": {
    "addr:full":"Zi Secteur Le Moulin 62620 Ruitz Nord Pas-de-Calais 62620",
    "addr:postcode":"62620;62620",
    "addr:street":"Zi Secteur;Moulin",
    "iso:country":"FR",
    "sg:address":"Zi Secteur Le Moulin 62620 Ruitz",
    "sg:classifiers":[
        {
            "category":"Manufacturing",
            "subcategory":"Motor Vehicles & Parts",
            "type":"Manufacturing & Wholesale Goods"
        }
    ],
    "sg:phone":"+33 3 21 63 46 46",
    "sg:postcode":"62620",
    "sg:province":"Nord Pas-de-Calais",
    "sg:tags":[
        "engine",
        "machine",
        "engineering",
        "-",
        "mechanical"
    ],
    "wof:name":"Societe De Transmissions Automatiques (sta)",
    "wof:placetype":"venue"
},
  "geometry": {"coordinates":[2.580328,50.453682],"type":"Point"}
}