{
  "type": "Feature",
  "properties": {
    "addr:full":"98, Av. du G\u00e9n\u00e9ral Leclerc, 92100 Boulogne Billancourt Ile de France",
    "addr:postcode":"92100",
    "addr:street":"98 Av. Du Ge\u0301Ne\u0301Ral Leclerc",
    "iso:country":"FR",
    "sg:address":"98, Av. du G\u00e9n\u00e9ral Leclerc, 92100 Boulogne Billancourt",
    "sg:orig_category":"Unclassifiable Establishments",
    "sg:phone":"+33 1 48 25 88 55",
    "sg:province":"Ile de France",
    "wof:name":"Lorris Consulting S.a.",
    "wof:placetype":"venue"
},
  "geometry": {"coordinates":[2.235159,48.831203],"type":"Point"}
}