{
  "type": "Feature",
  "properties": {
    "addr:full":"Rue Jean Perrin Douai Nord Pas-de-Calais 59500",
    "addr:postcode":"59500",
    "addr:street":"Rue Jean Perrin",
    "iso:country":"FR",
    "sg:address":"Rue Jean Perrin",
    "sg:city":"Douai",
    "sg:orig_category":"Unclassifiable Establishments",
    "sg:phone":"+33 3 27 94 32 32",
    "sg:postcode":"59500",
    "sg:province":"Nord Pas-de-Calais",
    "wof:name":"I.c.t. S.a. - Isolants Composites Techniques",
    "wof:placetype":"venue"
},
  "geometry": {"coordinates":[3.101215,50.397202],"type":"Point"}
}