{
  "type": "Feature",
  "properties": {
    "iso:country":"FR",
    "sg:address":"2 Rue Du Sergent Harris 35506 Vitr\u00e9",
    "sg:classifiers":[
        {
            "category":"Professional",
            "subcategory":"Business Services",
            "type":"Services"
        }
    ],
    "sg:phone":"+33 2 99 75 07 97",
    "sg:province":"Basse Normandie",
    "sg:tags":[
        "training",
        "advice"
    ],
    "wof:name":"Lycee Professionnel Reg La Champagne",
    "wof:placetype":"venue"
},
  "geometry": {"coordinates":[-1.232249,48.120144],"type":"Point"}
}