{
  "type": "Feature",
  "properties": {
    "addr:full":"122, Rue Vaillant Couturier, 93130 Noisy le Sec Ile de France",
    "addr:housenumber":"122",
    "addr:postcode":"93130",
    "addr:street":"Rue Vaillant Couturier",
    "iso:country":"FR",
    "sg:address":"122, Rue Vaillant Couturier, 93130 Noisy le Sec",
    "sg:orig_category":"Unclassifiable Establishments",
    "sg:phone":"+33 1 48 91 08 00",
    "sg:province":"Ile de France",
    "wof:name":"Gap Froid Climatisation S.a.",
    "wof:placetype":"venue"
},
  "geometry": {"coordinates":[2.441644,48.892616],"type":"Point"}
}