{
  "type": "Feature",
  "properties": {
    "iso:country":"FR",
    "sg:address":"8 Rue Du Pre Aux Clercs 75007 Paris",
    "sg:classifiers":[
        {
            "category":"Shopping",
            "subcategory":"Clothing, Apparel, & Fashions",
            "type":"Retail Goods"
        }
    ],
    "sg:phone":"+33 1 42 61 24 01",
    "sg:postcode":"75007",
    "sg:province":"Ile de France",
    "sg:tags":[
        "textile",
        "clothing",
        "clothes"
    ],
    "wof:name":"Vague 7",
    "wof:placetype":"venue"
},
  "geometry": {"coordinates":[2.329916,48.856304],"type":"Point"}
}