{
  "type": "Feature",
  "properties": {
    "iso:country":"FR",
    "sg:address":"Zi Du Jasmin 73240 St Genix Sur Guiers",
    "sg:classifiers":[
        {
            "category":"Communications",
            "subcategory":"Newspaper",
            "type":"Services"
        }
    ],
    "sg:phone":"+33 4 76 31 61 18",
    "sg:province":"Rhone-Alpes",
    "sg:tags":[
        "printing",
        "publishing"
    ],
    "wof:name":"Gauthier Imprimeur Sa",
    "wof:placetype":"venue"
},
  "geometry": {"coordinates":[5.632419,45.598377],"type":"Point"}
}