{
  "type": "Feature",
  "properties": {
    "iso:country":"FR",
    "sg:address":"25, Rue Saint Fuscien, 80000 Amiens",
    "sg:orig_category":"Non-Classified Establishments",
    "sg:phone":"+33 3 22 71 01 01",
    "sg:postcode":"80000",
    "sg:province":"Picardie",
    "wof:name":"Dambreville S.a.",
    "wof:placetype":"venue"
},
  "geometry": {"coordinates":[2.303879,49.886089],"type":"Point"}
}