{
  "type": "Feature",
  "properties": {
    "iso:country":"FR",
    "sg:address":"Rte de Metz",
    "sg:city":"Saulny",
    "sg:orig_category":"Unclassifiable Establishments",
    "sg:phone":"+33 3 87 31 13 96",
    "sg:postcode":"57140",
    "sg:province":"Lorraine",
    "wof:name":"Blanco S.a.r.l.",
    "wof:placetype":"venue"
},
  "geometry": {"coordinates":[6.11701,49.154915],"type":"Point"}
}