{
  "type": "Feature",
  "properties": {
    "addr:full":"B.P. 29, 87500 Saint Yrieix la Perche^^6, Rue Victor Hugo, 87500 Saint Yrieix la Perche Limousin 87500",
    "addr:postcode":"87500;87500;87500",
    "addr:street":"B.P. 29;Rue Victor Hugo",
    "iso:country":"FR",
    "sg:address":"B.P. 29, 87500 Saint Yrieix la Perche^^6, Rue Victor Hugo, 87500 Saint Yrieix la Perche",
    "sg:orig_category":"Non-Classified Establishments",
    "sg:phone":"+33 5 55 08 34 30",
    "sg:postcode":"87500",
    "sg:province":"Limousin",
    "wof:name":"B.p.c. - Banque Populaire Du Centre",
    "wof:placetype":"venue"
},
  "geometry": {"coordinates":[1.203934,45.514183],"type":"Point"}
}