{
  "type": "Feature",
  "properties": {
    "addr:full":"108 Rue Nationale 59800 Lille Nord Pas-de-Calais",
    "addr:housenumber":"108",
    "addr:postcode":"59800",
    "addr:street":"Rue Nationale",
    "iso:country":"FR",
    "sg:address":"108 Rue Nationale 59800 Lille",
    "sg:classifiers":[
        {
            "category":"Manufacturing",
            "subcategory":"Printing",
            "type":"Manufacturing & Wholesale Goods"
        }
    ],
    "sg:phone":"+33 3 20 57 61 44",
    "sg:province":"Nord Pas-de-Calais",
    "sg:tags":[
        "publishing"
    ],
    "wof:name":"Actidoc",
    "wof:placetype":"venue"
},
  "geometry": {"coordinates":[3.057355,50.635006],"type":"Point"}
}