{
  "type": "Feature",
  "properties": {
    "iso:country":"FR",
    "sg:address":"45, Av. de la Concorde, 93270 Sevran",
    "sg:orig_category":"Unclassifiable Establishments",
    "sg:phone":"+33 1 43 83 50 13",
    "sg:province":"Ile de France",
    "wof:name":"Ryczaj Jean",
    "wof:placetype":"venue"
},
  "geometry": {"coordinates":[2.51775,48.937428],"type":"Point"}
}