{
  "type": "Feature",
  "properties": {
    "iso:country":"FR",
    "sg:address":"1000, Rue de la Li\u00e8me - ZI, 39570 Perrigny",
    "sg:orig_category":"Non-Classified Establishments",
    "sg:phone":"+33 3 84 47 29 06",
    "sg:province":"Franche Comt\u00e9",
    "wof:name":"La Comtoise Des Viandes Jean Royer S.a.",
    "wof:placetype":"venue"
},
  "geometry": {"coordinates":[5.516002,46.599735],"type":"Point"}
}