{
  "type": "Feature",
  "properties": {
    "addr:full":"B.P. 16, 22150 Ploeuc sur Li\u00e9^^ZA de Chantepie, 22150 Ploeuc sur Li\u00e9 H\u00e9non Bretagne 22150",
    "addr:postcode":"22150;22150;22150",
    "addr:street":"B.P. 16;He\u0301Non",
    "iso:country":"FR",
    "sg:address":"B.P. 16, 22150 Ploeuc sur Li\u00e9^^ZA de Chantepie, 22150 Ploeuc sur Li\u00e9",
    "sg:city":"H\u00e9non",
    "sg:orig_category":"Non-Classified Establishments",
    "sg:phone":"+33 2 96 64 21 00",
    "sg:postcode":"22150",
    "sg:province":"Bretagne",
    "wof:name":"Sercap S.a.",
    "wof:placetype":"venue"
},
  "geometry": {"coordinates":[-2.716559,48.259186],"type":"Point"}
}