{
  "type": "Feature",
  "properties": {
    "addr:full":"7, Rue Macon, 71210 Montchanin Montchanin Bourgogne 71210",
    "addr:housenumber":"7",
    "addr:postcode":"71210;71210",
    "addr:street":"Rue Macon",
    "iso:country":"FR",
    "sg:address":"7, Rue Macon, 71210 Montchanin",
    "sg:city":"Montchanin",
    "sg:orig_category":"Unclassifiable Establishments",
    "sg:phone":"+33 3 85 78 10 82",
    "sg:postcode":"71210",
    "sg:province":"Bourgogne",
    "wof:name":"Laboratoire Pierre Chatonnier S.a.",
    "wof:placetype":"venue"
},
  "geometry": {"coordinates":[4.474569,46.744694],"type":"Point"}
}