{
  "type": "Feature",
  "properties": {
    "iso:country":"FR",
    "sg:address":"Rue Michel Poulmarch - Centre Multimarchandises",
    "sg:city":"Saint Etienne du Rouvray",
    "sg:orig_category":"Unclassifiable Establishments",
    "sg:phone":"+33 2 35 66 02 78",
    "sg:postcode":"76800",
    "sg:province":"Haute Normandie",
    "wof:name":"P.g.s. S.a.r.l. - Palettes Gestion Services",
    "wof:placetype":"venue"
},
  "geometry": {"coordinates":[1.10721,49.379585],"type":"Point"}
}