{
  "type": "Feature",
  "properties": {
    "addr:full":"Rte De Chamberia 39270 Sarrogna Franche Comt\u00e9 39270",
    "addr:postcode":"39270;39270",
    "addr:street":"Rte De Chamberia;Franche Comte\u0301",
    "iso:country":"FR",
    "sg:address":"Rte De Chamberia 39270 Sarrogna",
    "sg:classifiers":[
        {
            "category":"Home & Garden",
            "subcategory":"Furniture",
            "type":"Retail Goods"
        }
    ],
    "sg:phone":"+33 3 84 35 70 36",
    "sg:postcode":"39270",
    "sg:province":"Franche Comt\u00e9",
    "sg:tags":[
        "household",
        "wood"
    ],
    "wof:name":"Polymeubles",
    "wof:placetype":"venue"
},
  "geometry": {"coordinates":[5.610467,46.52206],"type":"Point"}
}