{
  "type": "Feature",
  "properties": {
    "iso:country":"FR",
    "sg:address":"8 Rue Eglise 14540 Bourgu\u00e9bus",
    "sg:city":"Bourgu\u00e9bus",
    "sg:classifiers":[
        {
            "category":"Shopping",
            "subcategory":"Crafts & Fabrics",
            "type":"Retail Goods"
        }
    ],
    "sg:phone":"+33 2 31 23 11 08",
    "sg:postcode":"14540",
    "sg:province":"Basse Normandie",
    "sg:tags":[
        "textile",
        "clothing"
    ],
    "wof:name":"Vandecandelaere Sarl",
    "wof:placetype":"venue"
},
  "geometry": {"coordinates":[-0.296059,49.120529],"type":"Point"}
}