{
  "type": "Feature",
  "properties": {
    "addr:full":"121 rue du Parc 93130 Noisy le Sec Ile de France 93130",
    "addr:housenumber":"121",
    "addr:postcode":"93130;93130",
    "addr:street":"Rue Du Parc",
    "iso:country":"FR",
    "sg:address":"121 rue du Parc 93130 Noisy le Sec",
    "sg:classifiers":[
        {
            "category":"Building & Trades",
            "subcategory":"Construction",
            "type":"Services"
        }
    ],
    "sg:phone":"+33 1 48 40 44 33",
    "sg:postcode":"93130",
    "sg:province":"Ile de France",
    "sg:tags":[
        "fork",
        "lift",
        "truck"
    ],
    "wof:name":"Charles Services S.a.",
    "wof:placetype":"venue"
},
  "geometry": {"coordinates":[2.442533,48.897125],"type":"Point"}
}