{
  "type": "Feature",
  "properties": {
    "addr:full":"58 Cours Clemenceau Alen\u00e7on Basse Normandie 61000",
    "addr:housenumber":"58",
    "addr:postcode":"61000",
    "addr:street":"Cours Clemenceau;Basse",
    "iso:country":"FR",
    "sg:address":"58 Cours Clemenceau",
    "sg:city":"Alen\u00e7on",
    "sg:classifiers":[
        {
            "category":"Banks & Credit Unions",
            "subcategory":"Financial Services",
            "type":"Services"
        }
    ],
    "sg:phone":"+33 2 33 82 21 50",
    "sg:postcode":"61000",
    "sg:province":"Basse Normandie",
    "sg:tags":[
        "banking",
        "finance",
        "insurance"
    ],
    "wof:name":"Banque Regionale De L'ouest (bro)",
    "wof:placetype":"venue"
},
  "geometry": {"coordinates":[0.08648,48.432693],"type":"Point"}
}