{
  "type": "Feature",
  "properties": {
    "addr:full":"1020, Chemin de Beauregard, 78955 Carri\u00e8res sous Poissy Ile de France",
    "addr:housenumber":"1020",
    "addr:postcode":"78955",
    "addr:street":"Chemin De Beauregard",
    "iso:country":"FR",
    "sg:address":"1020, Chemin de Beauregard, 78955 Carri\u00e8res sous Poissy",
    "sg:orig_category":"Non-Classified Establishments",
    "sg:phone":"+33 1 30 74 44 29",
    "sg:province":"Ile de France",
    "wof:name":"Michel Monnier",
    "wof:placetype":"venue"
},
  "geometry": {"coordinates":[2.020298,48.935589],"type":"Point"}
}