{
  "type": "Feature",
  "properties": {
    "iso:country":"FR",
    "sg:address":"99, Rue du Grand Gaillot Marcillieux, 01150 Saint Vulbas",
    "sg:orig_category":"Non-Classified Establishments",
    "sg:phone":"+33 4 72 36 10 72",
    "sg:province":"Rhone-Alpes",
    "wof:name":"I.n.e.o. Activit\u00e9 Nuclaire Et Centrales S.n.c.",
    "wof:placetype":"venue"
},
  "geometry": {"coordinates":[5.3382,45.88237],"type":"Point"}
}