{
  "type": "Feature",
  "properties": {
    "addr:full":"54 rue Michel-Ange 75016 Paris Ile de France",
    "addr:housenumber":"54",
    "addr:postcode":"75016",
    "addr:street":"Rue Michel-Ange",
    "iso:country":"FR",
    "sg:address":"54 rue Michel-Ange 75016 Paris",
    "sg:classifiers":[
        {
            "category":"Sports & Exercise",
            "subcategory":"Athletic Track",
            "type":"Entertainment"
        }
    ],
    "sg:phone":"+33 1 46 51 03 05",
    "sg:province":"Ile de France",
    "sg:tags":[
        "record"
    ],
    "wof:name":"Studio Sm S.a.r.l.",
    "wof:placetype":"venue"
},
  "geometry": {"coordinates":[2.260625,48.844002],"type":"Point"}
}