{
  "type": "Feature",
  "properties": {
    "addr:full":"300, Av. du G\u00e9n\u00e9ral de Gaulle, 83300 Draguignan Pays de Loire",
    "addr:postcode":"83300",
    "addr:street":"300 Av. Du Ge\u0301Ne\u0301Ral De Gaulle",
    "iso:country":"FR",
    "sg:address":"300, Av. du G\u00e9n\u00e9ral de Gaulle, 83300 Draguignan",
    "sg:orig_category":"Unclassifiable Establishments",
    "sg:phone":"+33 4 94 68 16 41",
    "sg:province":"Pays de Loire",
    "wof:name":"Soci\u00e9t\u00e9 Bakalian S.a.r.l",
    "wof:placetype":"venue"
},
  "geometry": {"coordinates":[6.471576,43.527515],"type":"Point"}
}