{
  "type": "Feature",
  "properties": {
    "iso:country":"FR",
    "sg:address":"4, Rue de la Californie - ZI du Mont Blanc, 74100 Ville la Grand",
    "sg:orig_category":"Unclassifiable Establishments",
    "sg:phone":"+33 4 50 37 47 95",
    "sg:province":"Rhone-Alpes",
    "wof:name":"Plantard S.a.",
    "wof:placetype":"venue"
},
  "geometry": {"coordinates":[6.23712,46.192455],"type":"Point"}
}