{
  "type": "Feature",
  "properties": {
    "iso:country":"FR",
    "sg:address":"51, Rue Etienne Marcel, 75001 Paris",
    "sg:orig_category":"Non-Classified Establishments",
    "sg:phone":"+33 1 40 39 72 02",
    "sg:province":"Ile de France",
    "wof:name":"Parfums Kenzo S.a.",
    "wof:placetype":"venue"
},
  "geometry": {"coordinates":[2.341814,48.865448],"type":"Point"}
}