{
  "type": "Feature",
  "properties": {
    "iso:country":"FR",
    "sg:address":"14 rue de Vic 62100 Calais",
    "sg:classifiers":[
        {
            "category":"Shopping",
            "subcategory":"Crafts & Fabrics",
            "type":"Retail Goods"
        }
    ],
    "sg:phone":"+33 3 21 34 59 37",
    "sg:postcode":"62100",
    "sg:province":"Nord Pas-de-Calais",
    "sg:tags":[
        "textile",
        "industry"
    ],
    "wof:name":"Ets Jean Sabau S.a.r.l.",
    "wof:placetype":"venue"
},
  "geometry": {"coordinates":[1.857017,50.949505],"type":"Point"}
}