{
  "type": "Feature",
  "properties": {
    "addr:full":"Chemin Des Pourceaux Le Dessus De Monplaisir 02100 St Quentin Picardie 02100",
    "addr:postcode":"02100;02100",
    "addr:street":"Chemin Des Pourceaux Le Dessus De Monplaisir",
    "iso:country":"FR",
    "sg:address":"Chemin Des Pourceaux Le Dessus De Monplaisir 02100 St Quentin",
    "sg:classifiers":[
        {
            "category":"Wholesale",
            "subcategory":"Machinery & Supplies",
            "type":"Manufacturing & Wholesale Goods"
        }
    ],
    "sg:phone":"+33 3 23 64 69 14",
    "sg:postcode":"02100",
    "sg:province":"Picardie",
    "sg:tags":[
        "handling",
        "material",
        "-",
        "machine",
        "equipment",
        "engineering",
        "mechanical"
    ],
    "wof:name":"Gestpal Picardie",
    "wof:placetype":"venue"
},
  "geometry": {"coordinates":[3.291286,49.850952],"type":"Point"}
}