{
  "type": "Feature",
  "properties": {
    "addr:full":"10, Rue de l'Industrie - ZI Est, 68700 Cernay Cernay Alsace 68700",
    "addr:housenumber":"10",
    "addr:postcode":"68700;68700",
    "addr:street":"Rue De L'Industrie Zi Est",
    "iso:country":"FR",
    "sg:address":"10, Rue de l'Industrie - ZI Est, 68700 Cernay",
    "sg:city":"Cernay",
    "sg:orig_category":"Non-Classified Establishments",
    "sg:phone":"+33 3 89 75 71 25",
    "sg:postcode":"68700",
    "sg:province":"Alsace",
    "wof:name":"Bodycote Hit S.a.",
    "wof:placetype":"venue"
},
  "geometry": {"coordinates":[7.186859,47.798317],"type":"Point"}
}