{
  "type": "Feature",
  "properties": {
    "addr:full":"112/114, Av. du Br\u00e9zet, 63100 Clermont Ferrand Clermont-Ferrand Auvergne 63100",
    "addr:housenumber":"112 / 114",
    "addr:postcode":"63100;63100",
    "addr:street":"Av. Du Bre\u0301Zet",
    "iso:country":"FR",
    "sg:address":"112/114, Av. du Br\u00e9zet, 63100 Clermont Ferrand",
    "sg:city":"Clermont-Ferrand",
    "sg:orig_category":"Non-Classified Establishments",
    "sg:phone":"+33 4 73 91 96 03",
    "sg:postcode":"63100",
    "sg:province":"Auvergne",
    "wof:name":"D\u00e9co Glace S.a.",
    "wof:placetype":"venue"
},
  "geometry": {"coordinates":[3.131066,45.779819],"type":"Point"}
}