{
  "type": "Feature",
  "properties": {
    "iso:country":"FR",
    "sg:address":"B.P. 51, 45141 Saint Jean de la Ruelle C\u00e9dex^^160, Rue L\u00e9on Foucault - ZA la Vall\u00e9e, 45140 Saint Jea",
    "sg:city":"Ingr\u00e9",
    "sg:orig_category":"Non-Classified Establishments",
    "sg:phone":"+33 2 38 70 72 00",
    "sg:postcode":"45140",
    "sg:province":"Centre",
    "wof:name":"Entreprise Gallier S.a.",
    "wof:placetype":"venue"
},
  "geometry": {"coordinates":[-115.325089,35.779205],"type":"Point"}
}