{
  "type": "Feature",
  "properties": {
    "addr:full":"239, Rue Saint Martin, 75003 Paris Ile de France",
    "addr:housenumber":"239",
    "addr:postcode":"75003",
    "addr:street":"Rue Saint Martin",
    "iso:country":"FR",
    "sg:address":"239, Rue Saint Martin, 75003 Paris",
    "sg:orig_category":"Unclassifiable Establishments",
    "sg:phone":"+33 1 44 54 92 91",
    "sg:province":"Ile de France",
    "wof:name":"Atelier Miki S.a.r.l.",
    "wof:placetype":"venue"
},
  "geometry": {"coordinates":[2.35328,48.865288],"type":"Point"}
}