{
  "type": "Feature",
  "properties": {
    "addr:full":"72, Av. Anatole France, 69700 Givors Rhone-Alpes",
    "addr:postcode":"69700",
    "addr:street":"72 Av. Anatole France",
    "iso:country":"FR",
    "sg:address":"72, Av. Anatole France, 69700 Givors",
    "sg:orig_category":"Unclassifiable Establishments",
    "sg:phone":"+33 4 78 73 25 78",
    "sg:province":"Rhone-Alpes",
    "wof:name":"Martinet Fr\u00e8res S.a.r.l.",
    "wof:placetype":"venue"
},
  "geometry": {"coordinates":[4.794081,45.572231],"type":"Point"}
}