{
  "type": "Feature",
  "properties": {
    "addr:full":"Les Sarraix Apa Sa 63250 Celles Sur Durolle Arconsat Auvergne 63250",
    "addr:postcode":"63250;63250",
    "iso:country":"FR",
    "sg:address":"Les Sarraix Apa Sa 63250 Celles Sur Durolle",
    "sg:city":"Arconsat",
    "sg:classifiers":[
        {
            "category":"Manufacturing",
            "subcategory":"Rubber & Plastics",
            "type":"Manufacturing & Wholesale Goods"
        }
    ],
    "sg:phone":"+33 4 73 51 57 24",
    "sg:postcode":"63250",
    "sg:province":"Auvergne",
    "wof:name":"Apa Sa Application Plastique Arconsat (apa)",
    "wof:placetype":"venue"
},
  "geometry": {"coordinates":[3.704752,45.82304],"type":"Point"}
}