{
  "type": "Feature",
  "properties": {
    "iso:country":"FR",
    "sg:address":"5, Rue de la Musau, 67100 Strasbourg",
    "sg:city":"Strasbourg",
    "sg:orig_category":"Non-Classified Establishments",
    "sg:phone":"+33 3 88 34 22 36",
    "sg:postcode":"67100",
    "sg:province":"Alsace",
    "wof:name":"Sintese S.a.r.l.",
    "wof:placetype":"venue"
},
  "geometry": {"coordinates":[7.780493,48.561142],"type":"Point"}
}