{
  "type": "Feature",
  "properties": {
    "addr:full":"21, Rue du Port - Parc de l'Ile, 92000 Nanterre Ile de France",
    "addr:housenumber":"21",
    "addr:postcode":"92000",
    "addr:street":"Rue Du Port Parc De L'Ile",
    "iso:country":"FR",
    "sg:address":"21, Rue du Port - Parc de l'Ile, 92000 Nanterre",
    "sg:orig_category":"Unclassifiable Establishments",
    "sg:phone":"+33 1 55 69 32 00",
    "sg:province":"Ile de France",
    "wof:name":"Huppe S.a.r.l.",
    "wof:placetype":"venue"
},
  "geometry": {"coordinates":[2.178608,48.893337],"type":"Point"}
}