{
  "type": "Feature",
  "properties": {
    "addr:full":"T\u00e9l\u00e9base Lyon Saint Didier au Mont d'Or C\u00e9dex Rhone-Alpes 69771",
    "addr:postcode":"69771",
    "iso:country":"FR",
    "sg:address":"T\u00e9l\u00e9base Lyon",
    "sg:city":"Saint Didier au Mont d'Or C\u00e9dex",
    "sg:orig_category":"Non-Classified Establishments",
    "sg:phone":"+33 4 78 64 32 94",
    "sg:postcode":"69771",
    "sg:province":"Rhone-Alpes",
    "wof:name":"Solutec S.a.",
    "wof:placetype":"venue"
},
  "geometry": {"coordinates":[4.79846,45.81007],"type":"Point"}
}