{
  "type": "Feature",
  "properties": {
    "addr:full":"4 rue des 7 Arpents 93310 LE PRE ST GERVAIS Ile de France",
    "addr:housenumber":"4",
    "addr:postcode":"93310",
    "addr:street":"Rue Des 7 Arpents;Pre St",
    "iso:country":"FR",
    "sg:address":"4 rue des 7 Arpents 93310 LE PRE ST GERVAIS",
    "sg:classifiers":[
        {
            "category":"Food & Beverages",
            "subcategory":"Groceries & Convenience Stores",
            "type":"Retail Goods"
        }
    ],
    "sg:phone":"+33 1 48 46 66 91",
    "sg:province":"Ile de France",
    "sg:tags":[
        "product",
        "industry",
        "system"
    ],
    "wof:name":"Ravet S.a.r.l.",
    "wof:placetype":"venue"
},
  "geometry": {"coordinates":[2.398816,48.889473],"type":"Point"}
}