{
  "type": "Feature",
  "properties": {
    "addr:full":"72 Rue Maurice Ripoche 75014 Paris Ile de France",
    "addr:housenumber":"72",
    "addr:postcode":"75014",
    "addr:street":"Rue Maurice Ripoche",
    "iso:country":"FR",
    "sg:address":"72 Rue Maurice Ripoche 75014 Paris",
    "sg:classifiers":[
        {
            "category":"Professional",
            "type":"Services"
        }
    ],
    "sg:phone":"+33 1 45 40 52 39",
    "sg:province":"Ile de France",
    "sg:tags":[
        "transport",
        "road"
    ],
    "wof:name":"Somadem Sarl",
    "wof:placetype":"venue"
},
  "geometry": {"coordinates":[2.322273,48.833698],"type":"Point"}
}