{
  "type": "Feature",
  "properties": {
    "addr:full":"39 Rue Marechal Joffre 18160 LIGNIERES Ligni\u00e8res Centre 18160",
    "addr:housenumber":"39",
    "addr:postcode":"18160;18160",
    "addr:street":"Rue Marechal Joffre",
    "iso:country":"FR",
    "sg:address":"39 Rue Marechal Joffre 18160 LIGNIERES",
    "sg:city":"Ligni\u00e8res",
    "sg:classifiers":[
        {
            "category":"Juice Bar",
            "subcategory":"None",
            "type":"Food & Drink"
        }
    ],
    "sg:phone":"+33 2 48 60 06 11",
    "sg:postcode":"18160",
    "sg:province":"Centre",
    "sg:tags":[
        "spices",
        "whole",
        "ground"
    ],
    "wof:name":"Sarl Roy Et Fils",
    "wof:placetype":"venue"
},
  "geometry": {"coordinates":[2.17386,46.749931],"type":"Point"}
}