{
  "type": "Feature",
  "properties": {
    "iso:country":"FR",
    "sg:address":"13, Rue du Compas - ZA Des B\u00e9thunes, 95310 Saint Ouen l'Aum\u00f4ne",
    "sg:orig_category":"Unclassifiable Establishments",
    "sg:phone":"+33 1 34 21 93 88",
    "sg:province":"Ile de France",
    "wof:name":"A.b.c. Protection Et Environnement S.a.",
    "wof:placetype":"venue"
},
  "geometry": {"coordinates":[1.151225,47.715446],"type":"Point"}
}