{
  "type": "Feature",
  "properties": {
    "iso:country":"FR",
    "sg:address":"88 Rue Des Rigondes 93100 Montreuil",
    "sg:classifiers":[
        {
            "category":"Manufacturing",
            "subcategory":"Glass & Minerals",
            "type":"Manufacturing & Wholesale Goods"
        }
    ],
    "sg:phone":"+33 1 43 63 09 09",
    "sg:postcode":"93100",
    "sg:province":"Ile de France",
    "sg:tags":[
        "building",
        "material"
    ],
    "wof:name":"Anciens Ets Reverchon",
    "wof:placetype":"venue"
},
  "geometry": {"coordinates":[2.434599,48.874077],"type":"Point"}
}