{
  "type": "Feature",
  "properties": {
    "iso:country":"FR",
    "sg:address":"4, Rue de la Porte Fraboulet, 22800 Lanfains",
    "sg:city":"Lanfains",
    "sg:orig_category":"Non-Classified Establishments",
    "sg:phone":"+33 2 96 32 43 72",
    "sg:postcode":"22800",
    "sg:province":"Bretagne",
    "wof:name":"Visio Web S.a.r.l.",
    "wof:placetype":"venue"
},
  "geometry": {"coordinates":[-2.914553,48.3526],"type":"Point"}
}