{
  "type": "Feature",
  "properties": {
    "iso:country":"FR",
    "sg:address":"RN",
    "sg:city":"d'Orl\u00e9ans - 45380 Chaingy",
    "sg:classifiers":[
        {
            "category":"Government",
            "subcategory":"Department Of Motor Vehicles",
            "type":"Public Place"
        }
    ],
    "sg:phone":"+33 2 38 80 65 15",
    "sg:postcode":"45380",
    "sg:province":"Centre",
    "sg:tags":[
        "equipment",
        "industrial",
        "transport",
        "motor-cars"
    ],
    "wof:name":"Lambert Sarl",
    "wof:placetype":"venue"
},
  "geometry": {"coordinates":[1.853738,47.893929],"type":"Point"}
}