{
  "type": "Feature",
  "properties": {
    "addr:full":"B.P. 457 Reims C\u00e9dex Champagne 51066",
    "addr:housenumber":"b.p. 457",
    "addr:postcode":"51066",
    "iso:country":"FR",
    "sg:address":"B.P. 457",
    "sg:city":"Reims C\u00e9dex",
    "sg:orig_category":"Non-Classified Establishments",
    "sg:phone":"+33 3 26 89 53 00",
    "sg:postcode":"51066",
    "sg:province":"Champagne",
    "wof:name":"Champagne Henriot S.a.s.",
    "wof:placetype":"venue"
},
  "geometry": {"coordinates":[4.03384,49.25415],"type":"Point"}
}