{
  "type": "Feature",
  "properties": {
    "addr:full":"Lasnauzes Est 47300 Bias Bias Aquitaine 47300",
    "addr:postcode":"47300;47300",
    "addr:street":"Lasnauzes Est",
    "iso:country":"FR",
    "sg:address":"Lasnauzes Est 47300 Bias",
    "sg:city":"Bias",
    "sg:classifiers":[
        {
            "category":"Professional",
            "subcategory":"Engineering",
            "type":"Services"
        }
    ],
    "sg:phone":"+33 5 53 40 28 55",
    "sg:postcode":"47300",
    "sg:province":"Aquitaine",
    "sg:tags":[
        "machine",
        "-",
        "mechanical"
    ],
    "wof:name":"Villeneuve Pneus Sa",
    "wof:placetype":"venue"
},
  "geometry": {"coordinates":[0.680036,44.400497],"type":"Point"}
}