{
  "type": "Feature",
  "properties": {
    "addr:full":"ZI de Bordeaux Fr\u00eat - B\u00e2t 3 - Entr\u00e9e A Bruges C\u00e9dex Aquitaine 33521",
    "addr:postcode":"33521",
    "addr:street":"Zi De Bordeaux",
    "iso:country":"FR",
    "sg:address":"ZI de Bordeaux Fr\u00eat - B\u00e2t 3 - Entr\u00e9e A",
    "sg:city":"Bruges C\u00e9dex",
    "sg:orig_category":"Non-Classified Establishments",
    "sg:phone":"+33 5 56 43 85 85",
    "sg:postcode":"33521",
    "sg:province":"Aquitaine",
    "wof:name":"Saint Gobain V.g. Emballage",
    "wof:placetype":"venue"
},
  "geometry": {"coordinates":[-0.610265,44.887768],"type":"Point"}
}