{
  "type": "Feature",
  "properties": {
    "iso:country":"FR",
    "sg:address":"6, Rue de Bellevue, 68350 Brunstatt",
    "sg:city":"Brunstatt",
    "sg:orig_category":"Non-Classified Establishments",
    "sg:phone":"+33 3 84 57 85 16",
    "sg:postcode":"68350",
    "sg:province":"Alsace",
    "wof:name":"Laiterie Schmitlin S.a.",
    "wof:placetype":"venue"
},
  "geometry": {"coordinates":[7.32866,47.729321],"type":"Point"}
}