{
  "type": "Feature",
  "properties": {
    "addr:full":"B.P. 53, 71602 Paray le Monial^^RN 79, 71600 Hautefond Hautefond Bourgogne 71600",
    "addr:housenumber":"79",
    "addr:postcode":"71602;71600;71600",
    "addr:street":"B.P. 53;Monial^^Rn",
    "iso:country":"FR",
    "sg:address":"B.P. 53, 71602 Paray le Monial^^RN 79, 71600 Hautefond",
    "sg:city":"Hautefond",
    "sg:orig_category":"Non-Classified Establishments",
    "sg:phone":"+33 3 85 81 29 98",
    "sg:postcode":"71600",
    "sg:province":"Bourgogne",
    "wof:name":"S.t.c. Dardouillet S.a.",
    "wof:placetype":"venue"
},
  "geometry": {"coordinates":[4.127668,46.384384],"type":"Point"}
}