{
  "type": "Feature",
  "properties": {
    "iso:country":"FR",
    "sg:address":"ZAC les Vall\u00e9es",
    "sg:city":"Ambri\u00e8res les Vall\u00e9es",
    "sg:orig_category":"Unclassifiable Establishments",
    "sg:phone":"+33 2 43 00 07 36",
    "sg:postcode":"53300",
    "sg:province":"Pays de Loire",
    "wof:name":"Corlet Roto S.a.s.",
    "wof:placetype":"venue"
},
  "geometry": {"coordinates":[-0.630014,48.401634],"type":"Point"}
}