{
  "type": "Feature",
  "properties": {
    "addr:full":"201, Av. Pierre Brossolette, 92120 Montrouge Ile de France",
    "addr:housenumber":"201",
    "addr:postcode":"92120",
    "addr:street":"Av. Pierre Brossolette",
    "iso:country":"FR",
    "sg:address":"201, Av. Pierre Brossolette, 92120 Montrouge",
    "sg:orig_category":"Non-Classified Establishments",
    "sg:phone":"+33 1 55 58 00 37",
    "sg:province":"Ile de France",
    "wof:name":"R V B Editions S.a.r.l.",
    "wof:placetype":"venue"
},
  "geometry": {"coordinates":[2.302429,48.813427],"type":"Point"}
}