{
  "type": "Feature",
  "properties": {
    "iso:country":"FR",
    "sg:address":"278, Av. de la Marne - Parc d'Affaires le Ch\u00e2teau Rouge, 59700 Marcq en Baroeul",
    "sg:orig_category":"Non-Classified Establishments",
    "sg:phone":"+33 3 20 98 11 22",
    "sg:postcode":"59700",
    "sg:province":"Nord Pas-de-Calais",
    "wof:name":"Atelier D'architecture Van Oost S.a.r.l.",
    "wof:placetype":"venue"
},
  "geometry": {"coordinates":[3.10832,50.682526],"type":"Point"}
}