{
  "type": "Feature",
  "properties": {
    "addr:full":"11 route de Cornimont 88250 La Bresse Lorraine",
    "addr:housenumber":"11",
    "addr:postcode":"88250",
    "addr:street":"Route De Cornimont",
    "iso:country":"FR",
    "sg:address":"11 route de Cornimont 88250 La Bresse",
    "sg:classifiers":[
        {
            "category":"Building & Trades",
            "subcategory":"Construction",
            "type":"Services"
        }
    ],
    "sg:phone":"+33 3 29 25 53 80",
    "sg:province":"Lorraine",
    "sg:tags":[
        "warehouse",
        "equipment",
        "premise",
        "business"
    ],
    "wof:name":"Grandemange Agencement Sa",
    "wof:placetype":"venue"
},
  "geometry": {"coordinates":[6.858298,47.996616],"type":"Point"}
}