{
  "type": "Feature",
  "properties": {
    "addr:full":"rue Thomas Edison 44600 ST NAZAIRE Pays de Loire",
    "addr:postcode":"44600 st nazaire",
    "addr:street":"Rue Thomas Edison",
    "iso:country":"FR",
    "sg:address":"rue Thomas Edison 44600 ST NAZAIRE",
    "sg:classifiers":[
        {
            "category":"Manufacturing",
            "subcategory":"Motor Vehicles & Parts",
            "type":"Manufacturing & Wholesale Goods"
        }
    ],
    "sg:phone":"+33 2 40 17 27 27",
    "sg:province":"Pays de Loire",
    "sg:tags":[
        "transmission"
    ],
    "wof:name":"Eaton Sa",
    "wof:placetype":"venue"
},
  "geometry": {"coordinates":[-2.296397,47.288124],"type":"Point"}
}