{
  "type": "Feature",
  "properties": {
    "iso:country":"FR",
    "sg:address":"8, Rue du Professeur Joseph Rousselot, 14000 Caen",
    "sg:city":"Caen",
    "sg:orig_category":"Unclassifiable Establishments",
    "sg:phone":"+33 2 31 46 19 00",
    "sg:postcode":"14000",
    "sg:province":"Basse Normandie",
    "wof:name":"I.f.t.i.m. Collectivit\u00e9s - Institut De Formation Aux Techniques Implantation Manutention",
    "wof:placetype":"venue"
},
  "geometry": {"coordinates":[-0.359685,49.207806],"type":"Point"}
}