{
  "type": "Feature",
  "properties": {
    "iso:country":"FR",
    "sg:address":"Rue de la Pate",
    "sg:city":"Firminy",
    "sg:orig_category":"Non-Classified Establishments",
    "sg:phone":"+33 4 77 56 29 00",
    "sg:postcode":"42701",
    "sg:province":"Auvergne",
    "wof:name":"S.d.c.f. S.a. - Soci\u00e9t\u00e9 Distribution Chaleur Firminy",
    "wof:placetype":"venue"
},
  "geometry": {"coordinates":[4.290399,45.384834],"type":"Point"}
}