{
  "type": "Feature",
  "properties": {
    "addr:full":"35 Rue Froidevaux 75014 Paris Ile de France",
    "addr:housenumber":"35",
    "addr:postcode":"75014",
    "addr:street":"Rue Froidevaux",
    "iso:country":"FR",
    "sg:address":"35 Rue Froidevaux 75014 Paris",
    "sg:classifiers":[
        {
            "category":"Professional",
            "subcategory":"Printing & Photocopies",
            "type":"Services"
        }
    ],
    "sg:phone":"+33 1 40 64 54 54",
    "sg:province":"Ile de France",
    "sg:tags":[
        "publishing"
    ],
    "wof:name":"Dalloz Editions",
    "wof:placetype":"venue"
},
  "geometry": {"coordinates":[2.327888,48.83577],"type":"Point"}
}