{
  "type": "Feature",
  "properties": {
    "addr:full":"169, Av. Georges Cl\u00e9menceau, 92000 Nanterre Ile de France 92000",
    "addr:postcode":"92000;92000",
    "addr:street":"169 Av. Georges Cle\u0301Menceau",
    "iso:country":"FR",
    "sg:address":"169, Av. Georges Cl\u00e9menceau, 92000 Nanterre",
    "sg:orig_category":"Non-Classified Establishments",
    "sg:phone":"+33 1 46 69 30 00",
    "sg:postcode":"92000",
    "sg:province":"Ile de France",
    "wof:name":"Cfta S.a.",
    "wof:placetype":"venue"
},
  "geometry": {"coordinates":[2.212698,48.886356],"type":"Point"}
}