{
  "type": "Feature",
  "properties": {
    "iso:country":"FR",
    "sg:address":"Usine De L'Elze 30120 Le Vigan",
    "sg:classifiers":[
        {
            "category":"Shopping",
            "subcategory":"Clothing, Apparel, & Fashions",
            "type":"Retail Goods"
        }
    ],
    "sg:phone":"+33 4 67 81 60 15",
    "sg:postcode":"30120",
    "sg:province":"Languedoc-Roussillon",
    "sg:tags":[
        "textile",
        "clothing",
        "clothes"
    ],
    "wof:name":"Textiles Well",
    "wof:placetype":"venue"
},
  "geometry": {"coordinates":[9.764839,52.397278],"type":"Point"}
}