{
  "type": "Feature",
  "properties": {
    "addr:full":"Le Chaumoy 18570 Le Subdray Le Subdray Centre 18570",
    "addr:housenumber":"le subdray le subdray",
    "addr:postcode":"18570;18570",
    "iso:country":"FR",
    "sg:address":"Le Chaumoy 18570 Le Subdray",
    "sg:city":"Le Subdray",
    "sg:orig_category":"Unclassifiable Establishments",
    "sg:phone":"+33 2 48 66 62 62",
    "sg:postcode":"18570",
    "sg:province":"Centre",
    "wof:name":"Cebeco Semences S.a.",
    "wof:placetype":"venue"
},
  "geometry": {"coordinates":[2.331235,47.030994],"type":"Point"}
}