{
  "type": "Feature",
  "properties": {
    "iso:country":"FR",
    "sg:address":"Rue Du Stand 10700 Arcis Sur Aube",
    "sg:classifiers":[
        {
            "category":"Manufacturing",
            "subcategory":"Rubber & Plastics",
            "type":"Manufacturing & Wholesale Goods"
        }
    ],
    "sg:phone":"+33 3 25 37 13 02",
    "sg:province":"Champagne",
    "wof:name":"Brodart Sa",
    "wof:placetype":"venue"
},
  "geometry": {"coordinates":[4.15844,48.532097],"type":"Point"}
}