{
  "type": "Feature",
  "properties": {
    "addr:full":"Rte de Nievroz Dagneux Rhone-Alpes 01120",
    "addr:postcode":"01120",
    "addr:street":"Rte De Nievroz;Rhone-Alpes",
    "iso:country":"FR",
    "sg:address":"Rte de Nievroz",
    "sg:city":"Dagneux",
    "sg:orig_category":"Unclassifiable Establishments",
    "sg:phone":"+33 4 78 06 08 03",
    "sg:postcode":"01120",
    "sg:province":"Rhone-Alpes",
    "wof:name":"Butin - Terrier S.a.",
    "wof:placetype":"venue"
},
  "geometry": {"coordinates":[5.05126,45.85828],"type":"Point"}
}