{
  "type": "Feature",
  "properties": {
    "iso:country":"FR",
    "sg:address":"1 rue de Gironde 33300 Bordeaux",
    "sg:city":"Bordeaux",
    "sg:classifiers":[
        {
            "category":"Home & Garden",
            "subcategory":"Building Materials",
            "type":"Retail Goods"
        }
    ],
    "sg:phone":"+33 5 56 29 50 50",
    "sg:postcode":"33300",
    "sg:province":"Aquitaine",
    "sg:tags":[
        "slab",
        "marble"
    ],
    "wof:name":"Etablissements Jean Missegue S.a.",
    "wof:placetype":"venue"
},
  "geometry": {"coordinates":[-0.55248,44.865089],"type":"Point"}
}