{
  "type": "Feature",
  "properties": {
    "iso:country":"FR",
    "sg:address":"3 Cours Mirabeau",
    "sg:city":"Aix En Provence",
    "sg:classifiers":[
        {
            "category":"Banks & Credit Unions",
            "subcategory":"Financial Services",
            "type":"Services"
        }
    ],
    "sg:phone":"+33 4 42 93 59 59",
    "sg:postcode":"13100",
    "sg:province":"Nord Pas-de-Calais",
    "sg:tags":[
        "banking",
        "finance",
        "insurance"
    ],
    "wof:name":"Bignon & Lebray",
    "wof:placetype":"venue"
},
  "geometry": {"coordinates":[5.446176,43.526585],"type":"Point"}
}