{
  "type": "Feature",
  "properties": {
    "addr:full":"ZAC d'Augny Augny Lorraine 57685",
    "addr:postcode":"57685",
    "addr:street":"Zac D'Augny Augny Lorraine",
    "iso:country":"FR",
    "sg:address":"ZAC d'Augny",
    "sg:city":"Augny",
    "sg:orig_category":"Non-Classified Establishments",
    "sg:phone":"+33 3 87 38 39 99",
    "sg:postcode":"57685",
    "sg:province":"Lorraine",
    "wof:name":"La Kermesse S.a.",
    "wof:placetype":"venue"
},
  "geometry": {"coordinates":[6.10956,49.053631],"type":"Point"}
}