{
  "type": "Feature",
  "properties": {
    "addr:full":"69, Quai du Levant, 17045 La Rochelle C\u00e9dex 1 Poitou-Charentes",
    "addr:housenumber":"69;1",
    "addr:postcode":"17045",
    "addr:street":"Quai Du Levant;Ce\u0301Dex",
    "iso:country":"FR",
    "sg:address":"69, Quai du Levant, 17045 La Rochelle C\u00e9dex 1",
    "sg:orig_category":"Non-Classified Establishments",
    "sg:phone":"+33 5 46 67 30 30",
    "sg:province":"Poitou-Charentes",
    "wof:name":"Framer S.a.r.l.",
    "wof:placetype":"venue"
},
  "geometry": {"coordinates":[-1.218904,46.148376],"type":"Point"}
}