{
  "type": "Feature",
  "properties": {
    "addr:full":"B.P. 44, 31122 Portet sur Garonne C\u00e9dex^^5, Rue Gutenberg, 31120 Portet sur Garonne Midi Pyr\u00e9n\u00e9es",
    "addr:postcode":"31122;31120",
    "addr:street":"B.P. 44;Rue Gutenberg",
    "iso:country":"FR",
    "sg:address":"B.P. 44, 31122 Portet sur Garonne C\u00e9dex^^5, Rue Gutenberg, 31120 Portet sur Garonne",
    "sg:orig_category":"Non-Classified Establishments",
    "sg:phone":"+33 5 62 20 19 01",
    "sg:province":"Midi Pyr\u00e9n\u00e9es",
    "wof:name":"Hydro Sud Composants S.a.r.l.",
    "wof:placetype":"venue"
},
  "geometry": {"coordinates":[1.398561,43.52187],"type":"Point"}
}