{
  "type": "Feature",
  "properties": {
    "addr:full":"2 rue Charles de Beaumanoir 72100 Le Mans Pays de Loire 72100",
    "addr:housenumber":"2",
    "addr:postcode":"72100;72100",
    "addr:street":"Rue Charles De Beaumanoir",
    "iso:country":"FR",
    "sg:address":"2 rue Charles de Beaumanoir 72100 Le Mans",
    "sg:classifiers":[
        {
            "category":"Food & Beverages",
            "subcategory":"Groceries & Convenience Stores",
            "type":"Retail Goods"
        }
    ],
    "sg:phone":"+33 2 43 84 96 09",
    "sg:postcode":"72100",
    "sg:province":"Pays de Loire",
    "sg:tags":[
        "fresh"
    ],
    "wof:name":"Ets Daudibon Sa",
    "wof:placetype":"venue"
},
  "geometry": {"coordinates":[0.203093,47.978386],"type":"Point"}
}