{
  "type": "Feature",
  "properties": {
    "iso:country":"FR",
    "sg:address":"Parc d'Activit\u00e9",
    "sg:city":"Montluel",
    "sg:orig_category":"Non-Classified Establishments",
    "sg:phone":"+33 4 78 06 36 41",
    "sg:postcode":"01120",
    "sg:province":"Rhone-Alpes",
    "wof:name":"Lindab France S.a.",
    "wof:placetype":"venue"
},
  "geometry": {"coordinates":[5.03833,45.87001],"type":"Point"}
}