{
  "type": "Feature",
  "properties": {
    "iso:country":"FR",
    "sg:address":"Av. du Bois l'Abb\u00e9",
    "sg:city":"Beaucouz\u00e9",
    "sg:orig_category":"Non-Classified Establishments",
    "sg:phone":"+33 2 41 73 05 60",
    "sg:postcode":"49070",
    "sg:province":"Pays de Loire",
    "wof:name":"Axodym S.a.r.l.",
    "wof:placetype":"venue"
},
  "geometry": {"coordinates":[-0.66946,47.471519],"type":"Point"}
}