{
  "type": "Feature",
  "properties": {
    "addr:full":"B.P. 44, 14125 Mondeville C\u00e9dex^^Rue Georges Claude - ZA, 14120 Mondeville Mondeville Basse Normandie 14120",
    "addr:postcode":"14125;14120;14120",
    "addr:street":"B.P. 44;Ce\u0301Dex^^Rue Georges Claude Za;Basse",
    "iso:country":"FR",
    "sg:address":"B.P. 44, 14125 Mondeville C\u00e9dex^^Rue Georges Claude - ZA, 14120 Mondeville",
    "sg:city":"Mondeville",
    "sg:orig_category":"Non-Classified Establishments",
    "sg:phone":"+33 2 31 35 35 35",
    "sg:postcode":"14120",
    "sg:province":"Basse Normandie",
    "wof:name":"Tampleu Spriet S.a.",
    "wof:placetype":"venue"
},
  "geometry": {"coordinates":[-0.318344,49.178711],"type":"Point"}
}