{
  "type": "Feature",
  "properties": {
    "iso:country":"FR",
    "sg:address":"Campus Villegen",
    "sg:city":"Du Recteur Henri Le Moal Cs 24307 35043 Rennes Cedex",
    "sg:classifiers":[
        {
            "category":"Professional",
            "subcategory":"Business Services",
            "type":"Services"
        }
    ],
    "sg:phone":"+33 2 99 14 10 36",
    "sg:province":"Alsace",
    "sg:tags":[
        "training",
        "advice"
    ],
    "wof:name":"Universite De Rennes Ii",
    "wof:placetype":"venue"
},
  "geometry": {"coordinates":[-1.67777,48.111721],"type":"Point"}
}