{
  "type": "Feature",
  "properties": {
    "addr:full":". 35220 CHATEAUBOURG Ch\u00e2teaubourg Bretagne 35220",
    "addr:postcode":"35220;35220",
    "iso:country":"FR",
    "sg:address":". 35220 CHATEAUBOURG",
    "sg:city":"Ch\u00e2teaubourg",
    "sg:classifiers":[
        {
            "category":"Professional",
            "subcategory":"Testing Lab",
            "type":"Services"
        }
    ],
    "sg:phone":"+33 2 99 00 93 00",
    "sg:postcode":"35220",
    "sg:province":"Bretagne",
    "sg:tags":[
        "appliance",
        "data"
    ],
    "wof:name":"Testelec S.a.r.l.",
    "wof:placetype":"venue"
},
  "geometry": {"coordinates":[-1.392459,48.111],"type":"Point"}
}