{
  "type": "Feature",
  "properties": {
    "iso:country":"FR",
    "sg:address":"Les Echets Zac 01700 Miribel",
    "sg:classifiers":[
        {
            "category":"Manufacturing",
            "subcategory":"Musical Instruments",
            "type":"Manufacturing & Wholesale Goods"
        }
    ],
    "sg:phone":"+33 4 72 26 27 00",
    "sg:postcode":"01700",
    "sg:province":"Rhone-Alpes",
    "sg:tags":[
        "instruments",
        "electronic"
    ],
    "wof:name":"Musikengro Sarl",
    "wof:placetype":"venue"
},
  "geometry": {"coordinates":[4.910279,45.85638],"type":"Point"}
}