{
  "type": "Feature",
  "properties": {
    "addr:full":"B.P. 16, 69641 Caluire et Cuire C\u00e9dex^^24/26, Av. Barth\u00e9l\u00e9my Thimonnier - ZI, 69300 Caluire et Cuire Rhone-Alpes 69300",
    "addr:postcode":"69641;69300;69300",
    "addr:street":"B.P. 16;26 Av. Barthe\u0301Le\u0301My Thimonnier Zi",
    "iso:country":"FR",
    "sg:address":"B.P. 16, 69641 Caluire et Cuire C\u00e9dex^^24/26, Av. Barth\u00e9l\u00e9my Thimonnier - ZI, 69300 Caluire et Cuire",
    "sg:orig_category":"Non-Classified Establishments",
    "sg:phone":"+33 4 78 98 56 00",
    "sg:postcode":"69300",
    "sg:province":"Rhone-Alpes",
    "wof:name":"K Philibert S.a.",
    "wof:placetype":"venue"
},
  "geometry": {"coordinates":[4.845985,45.798859],"type":"Point"}
}