{
  "type": "Feature",
  "properties": {
    "iso:country":"FR",
    "sg:address":"Za",
    "sg:city":"Domfront",
    "sg:classifiers":[
        {
            "category":"Wholesale",
            "subcategory":"Machinery & Supplies",
            "type":"Manufacturing & Wholesale Goods"
        }
    ],
    "sg:phone":"+33 2 33 30 75 70",
    "sg:postcode":"61700",
    "sg:province":"Basse Normandie",
    "sg:tags":[
        "handling",
        "material",
        "-",
        "machine",
        "equipment",
        "engineering",
        "mechanical"
    ],
    "wof:name":"France Elevateurs Sa",
    "wof:placetype":"venue"
},
  "geometry": {"coordinates":[-0.64848,48.591648],"type":"Point"}
}