{
  "type": "Feature",
  "properties": {
    "addr:full":"10 Rue Du General De Gaulle 60700 Fleurines Picardie 60700",
    "addr:housenumber":"10",
    "addr:postcode":"60700;60700",
    "addr:street":"Rue Du General De Gaulle;Picardie",
    "iso:country":"FR",
    "sg:address":"10 Rue Du General De Gaulle 60700 Fleurines",
    "sg:orig_category":"Chimney Dampers",
    "sg:phone":"+33 3 44 54 11 26",
    "sg:postcode":"60700",
    "sg:province":"Picardie",
    "wof:name":"Chemt Vincent S.a.",
    "wof:placetype":"venue"
},
  "geometry": {"coordinates":[2.583816,49.259125],"type":"Point"}
}