{
  "type": "Feature",
  "properties": {
    "iso:country":"FR",
    "sg:address":"37 Rue N\u00e9ricault Destouches 37000 Tours",
    "sg:city":"Tours",
    "sg:classifiers":[
        {
            "category":"Wholesale",
            "subcategory":"Medical Equipment & Supplies",
            "type":"Manufacturing & Wholesale Goods"
        }
    ],
    "sg:phone":"+33 2 47 05 72 81",
    "sg:postcode":"37000",
    "sg:province":"Centre",
    "sg:tags":[
        "instrument",
        "health",
        "-",
        "precision"
    ],
    "wof:name":"Chataigner Sarl",
    "wof:placetype":"venue"
},
  "geometry": {"coordinates":[0.684622,47.392239],"type":"Point"}
}