{
  "type": "Feature",
  "properties": {
    "addr:full":"Filature Des Landes 12580 Villebomtal Midi Pyr\u00e9n\u00e9es 12580",
    "addr:postcode":"12580;12580",
    "iso:country":"FR",
    "sg:address":"Filature Des Landes 12580 Villebomtal",
    "sg:classifiers":[
        {
            "category":"Shopping",
            "subcategory":"Crafts & Fabrics",
            "type":"Retail Goods"
        }
    ],
    "sg:phone":"+33 5 65 44 61 13",
    "sg:postcode":"12580",
    "sg:province":"Midi Pyr\u00e9n\u00e9es",
    "sg:tags":[
        "textile",
        "linen",
        "clothing"
    ],
    "wof:name":"Ets Catusse Sarl",
    "wof:placetype":"venue"
},
  "geometry": {"coordinates":[-73.868263,41.853569],"type":"Point"}
}