{
  "type": "Feature",
  "properties": {
    "addr:full":"39 Boulevard De La Tour Maubourg 75007 Paris Ile de France 75007",
    "addr:housenumber":"39",
    "addr:postcode":"75007;75007",
    "addr:street":"Boulevard De La Tour Maubourg",
    "iso:country":"FR",
    "sg:address":"39 Boulevard De La Tour Maubourg 75007 Paris",
    "sg:classifiers":[
        {
            "category":"Banks & Credit Unions",
            "subcategory":"Financial Services",
            "type":"Services"
        }
    ],
    "sg:phone":"+33 1 40 62 04 00",
    "sg:postcode":"75007",
    "sg:province":"Ile de France",
    "sg:tags":[
        "banking",
        "finance",
        "insurance"
    ],
    "wof:name":"Caisse Generale De Retraite Des Cadres Par Repartition",
    "wof:placetype":"venue"
},
  "geometry": {"coordinates":[2.31024,48.858719],"type":"Point"}
}