{
  "type": "Feature",
  "properties": {
    "addr:full":"Rue des Alli\u00e9s Algrange Lorraine 57440",
    "addr:postcode":"57440",
    "addr:street":"Rue Des Allie\u0301S",
    "iso:country":"FR",
    "sg:address":"Rue des Alli\u00e9s",
    "sg:city":"Algrange",
    "sg:orig_category":"MAT\u00c9RIEL DE MANUTENTION CONTINUE SYST\u00c8MES DE CONVOYEURS",
    "sg:phone":"+33 3 82 85 33 44",
    "sg:postcode":"57440",
    "sg:province":"Lorraine",
    "wof:name":"Trapo France S.a.r.l.",
    "wof:placetype":"venue"
},
  "geometry": {"coordinates":[6.05138,49.363575],"type":"Point"}
}