{
  "type": "Feature",
  "properties": {
    "addr:full":"Bd des Loges - Les Ch\u00eanes Saint Berthevin Pays de Loire 53940",
    "addr:postcode":"53940",
    "addr:street":"Bd Des Loges Les;Saint Berthevin Pays",
    "iso:country":"FR",
    "sg:address":"Bd des Loges - Les Ch\u00eanes",
    "sg:city":"Saint Berthevin",
    "sg:orig_category":"Unclassifiable Establishments",
    "sg:phone":"+33 2 43 64 16 41",
    "sg:postcode":"53940",
    "sg:province":"Pays de Loire",
    "wof:name":"Mauguin S.a.",
    "wof:placetype":"venue"
},
  "geometry": {"coordinates":[-0.870805,48.019588],"type":"Point"}
}