{
  "type": "Feature",
  "properties": {
    "addr:full":"92508 Rueil Malmaison C\u00e9dex^^1, Av. du Pr\u00e9sident Pompidou, 92500 Rueil Malmaison Ile de France",
    "addr:postcode":"92508;92500",
    "addr:street":"Av. Du Pre\u0301Sident Pompidou",
    "iso:country":"FR",
    "sg:address":"92508 Rueil Malmaison C\u00e9dex^^1, Av. du Pr\u00e9sident Pompidou, 92500 Rueil Malmaison",
    "sg:orig_category":"Non-Classified Establishments",
    "sg:phone":"+33 1 47 32 92 77",
    "sg:province":"Ile de France",
    "wof:name":"Lefort Francheteau S.n.c.",
    "wof:placetype":"venue"
},
  "geometry": {"coordinates":[2.179085,48.877396],"type":"Point"}
}