{
  "type": "Feature",
  "properties": {
    "iso:country":"FR",
    "sg:address":"Rue Du Remont",
    "sg:city":"Neuville en Ferrain",
    "sg:orig_category":"Unclassifiable Establishments",
    "sg:phone":"+33 3 20 69 26 10",
    "sg:postcode":"59960",
    "sg:province":"Nord Pas-de-Calais",
    "wof:name":"Amima S.a.",
    "wof:placetype":"venue"
},
  "geometry": {"coordinates":[3.15239,50.750355],"type":"Point"}
}