{
  "type": "Feature",
  "properties": {
    "addr:full":"37, Rue Lucien Sergent, 91301 Massy C\u00e9dex Midi Pyr\u00e9n\u00e9es",
    "addr:housenumber":"37",
    "addr:postcode":"91301",
    "addr:street":"Rue Lucien Sergent",
    "iso:country":"FR",
    "sg:address":"37, Rue Lucien Sergent, 91301 Massy C\u00e9dex",
    "sg:orig_category":"Non-Classified Establishments",
    "sg:phone":"+33 1 69 20 24 11",
    "sg:province":"Midi Pyr\u00e9n\u00e9es",
    "wof:name":"C.m.m. G\u00e9dimat",
    "wof:placetype":"venue"
},
  "geometry": {"coordinates":[2.260971,48.729568],"type":"Point"}
}