{
  "type": "Feature",
  "properties": {
    "addr:full":"4, Rondf Point Champs Elys\u00e9es Marcel Dassault, 75008 Paris Ile de France",
    "addr:housenumber":"4",
    "addr:postcode":"75008",
    "addr:street":"Rondf Point Champs Elyse\u0301Es Marcel Dassault",
    "iso:country":"FR",
    "sg:address":"4, Rondf Point Champs Elys\u00e9es Marcel Dassault, 75008 Paris",
    "sg:orig_category":"Unclassifiable Establishments",
    "sg:phone":"+33 1 53 77 00 00",
    "sg:province":"Ile de France",
    "wof:name":"Inter Parfums S.a.",
    "wof:placetype":"venue"
},
  "geometry": {"coordinates":[2.34121,48.856926],"type":"Point"}
}