{
  "type": "Feature",
  "properties": {
    "iso:country":"FR",
    "sg:address":"Route Nationale 17 95508 Le Thillay",
    "sg:classifiers":[
        {
            "category":"Manufacturing",
            "subcategory":"Metals",
            "type":"Manufacturing & Wholesale Goods"
        }
    ],
    "sg:phone":"+33 1 34 38 87 20",
    "sg:province":"Champagne",
    "sg:tags":[
        "metallurgy",
        "steel",
        "metalworking"
    ],
    "wof:name":"Robert Et Cie Sas",
    "wof:placetype":"venue"
},
  "geometry": {"coordinates":[4.804995,49.872356],"type":"Point"}
}