{
  "type": "Feature",
  "properties": {
    "addr:full":"20, Rue de la Gare, 18510 Menetou Salon Menetou-Salon Centre 18510",
    "addr:housenumber":"20",
    "addr:postcode":"18510;18510",
    "addr:street":"Rue De La Gare",
    "iso:country":"FR",
    "sg:address":"20, Rue de la Gare, 18510 Menetou Salon",
    "sg:city":"Menetou-Salon",
    "sg:orig_category":"Non-Classified Establishments",
    "sg:phone":"+33 2 48 64 84 15",
    "sg:postcode":"18510",
    "sg:province":"Centre",
    "wof:name":"J.m.c. S.a.r.l.",
    "wof:placetype":"venue"
},
  "geometry": {"coordinates":[2.479116,47.226643],"type":"Point"}
}