{
  "type": "Feature",
  "properties": {
    "addr:full":"B.P. 4159, 53941 Saint Berthevin C\u00e9dex^^134, Bd des Loges, 53940 Saint Berthevin Pays de Loire",
    "addr:postcode":"53941;ce\u0301dex^^134;53940;berthevin",
    "addr:street":"B.P. 4159;Bd Des Loges",
    "iso:country":"FR",
    "sg:address":"B.P. 4159, 53941 Saint Berthevin C\u00e9dex^^134, Bd des Loges, 53940 Saint Berthevin",
    "sg:orig_category":"Non-Classified Establishments",
    "sg:phone":"+33 2 43 01 23 60",
    "sg:province":"Pays de Loire",
    "wof:name":"Gys S.a.",
    "wof:placetype":"venue"
},
  "geometry": {"coordinates":[-0.870805,48.019588],"type":"Point"}
}