{
  "type": "Feature",
  "properties": {
    "addr:full":"ZI Cormelles le Royal Caen Basse Normandie 14000",
    "addr:postcode":"14000",
    "iso:country":"FR",
    "sg:address":"ZI Cormelles le Royal",
    "sg:city":"Caen",
    "sg:orig_category":"Unclassifiable Establishments",
    "sg:phone":"+33 2 31 78 21 55",
    "sg:postcode":"14000",
    "sg:province":"Basse Normandie",
    "wof:name":"Gefco S.a.",
    "wof:placetype":"venue"
},
  "geometry": {"coordinates":[-0.36111,49.184361],"type":"Point"}
}