{
  "type": "Feature",
  "properties": {
    "addr:full":"Rue des Petits Champs - ZI Nord Saint Gr\u00e9goire Bretagne 35760",
    "addr:postcode":"35760",
    "addr:street":"Rue Des Petits Champs Zi Nord Saint Gre\u0301Goire Bretagne",
    "iso:country":"FR",
    "sg:address":"Rue des Petits Champs - ZI Nord",
    "sg:city":"Saint Gr\u00e9goire",
    "sg:orig_category":"Unclassifiable Establishments",
    "sg:phone":"+33 2 99 38 64 64",
    "sg:postcode":"35760",
    "sg:province":"Bretagne",
    "wof:name":"Karakula Isolation S.a.r.l.",
    "wof:placetype":"venue"
},
  "geometry": {"coordinates":[-1.656712,48.148029],"type":"Point"}
}