{
  "type": "Feature",
  "properties": {
    "addr:full":"8, Rue Vauban - Immeuble Garruteigt, 64500 Saint Jean de Luz Ciboure Aquitaine 64500",
    "addr:housenumber":"8",
    "addr:postcode":"64500;64500",
    "addr:street":"Rue Vauban;Garruteigt",
    "iso:country":"FR",
    "sg:address":"8, Rue Vauban - Immeuble Garruteigt, 64500 Saint Jean de Luz",
    "sg:city":"Ciboure",
    "sg:orig_category":"Non-Classified Establishments",
    "sg:phone":"+33 5 59 08 10 10",
    "sg:postcode":"64500",
    "sg:province":"Aquitaine",
    "wof:name":"Lapix B\u00e2timent S.a.r.l.",
    "wof:placetype":"venue"
},
  "geometry": {"coordinates":[-1.660884,43.38773],"type":"Point"}
}