{
  "type": "Feature",
  "properties": {
    "addr:full":"B.P. 29 Plouguerneau Bretagne 29880",
    "addr:postcode":"29880",
    "addr:street":"B.P. 29 Plouguerneau Bretagne",
    "iso:country":"FR",
    "sg:address":"B.P. 29",
    "sg:city":"Plouguerneau",
    "sg:orig_category":"Non-Classified Establishments",
    "sg:phone":"+33 2 98 04 54 11",
    "sg:postcode":"29880",
    "sg:province":"Bretagne",
    "wof:name":"Agrimer S.a.",
    "wof:placetype":"venue"
},
  "geometry": {"coordinates":[-4.462985,48.591148],"type":"Point"}
}