{
  "type": "Feature",
  "properties": {
    "iso:country":"FR",
    "sg:address":"10, Rue Gustave Eiffel, 31140 Aucamville",
    "sg:orig_category":"Unclassifiable Establishments",
    "sg:phone":"+33 5 61 37 57 37",
    "sg:province":"Midi Pyr\u00e9n\u00e9es",
    "wof:name":"Via Location France Provinces S.a.",
    "wof:placetype":"venue"
},
  "geometry": {"coordinates":[1.418934,43.664192],"type":"Point"}
}