{
  "type": "Feature",
  "properties": {
    "addr:full":"355, Av. Patton, 49000 Angers Pays de Loire",
    "addr:housenumber":"355",
    "addr:postcode":"49000",
    "addr:street":"Av. Patton",
    "iso:country":"FR",
    "sg:address":"355, Av. Patton, 49000 Angers",
    "sg:orig_category":"Unclassifiable Establishments",
    "sg:phone":"+33 2 41 73 68 47",
    "sg:province":"Pays de Loire",
    "wof:name":"Brink's Ouest",
    "wof:placetype":"venue"
},
  "geometry": {"coordinates":[-0.598544,47.473049],"type":"Point"}
}