{
  "type": "Feature",
  "properties": {
    "addr:full":"Chautignac 17240 Plassac Poitou-Charentes 17240",
    "addr:postcode":"17240;17240",
    "addr:street":"Chautignac",
    "iso:country":"FR",
    "sg:address":"Chautignac 17240 Plassac",
    "sg:classifiers":[
        {
            "category":"Manufacturing",
            "subcategory":"Paper Products",
            "type":"Manufacturing & Wholesale Goods"
        }
    ],
    "sg:phone":"+33 5 46 49 72 75",
    "sg:postcode":"17240",
    "sg:province":"Poitou-Charentes",
    "sg:tags":[
        "packaging",
        "biodegradable",
        "material"
    ],
    "wof:name":"Agripack S.a.r.l.",
    "wof:placetype":"venue"
},
  "geometry": {"coordinates":[-0.591989,45.435085],"type":"Point"}
}