{
  "type": "Feature",
  "properties": {
    "iso:country":"FR",
    "sg:address":"Zi De Qu\u00e9vert Rue Petit Pr\u00e9 22100 Qu\u00e9vert",
    "sg:city":"Qu\u00e9vert",
    "sg:classifiers":[
        {
            "category":"Professional",
            "subcategory":"Computer Services",
            "type":"Services"
        }
    ],
    "sg:phone":"+33 2 96 39 78 62",
    "sg:postcode":"22100",
    "sg:province":"Bretagne",
    "sg:tags":[
        "information",
        "technology",
        "software"
    ],
    "wof:name":"Sesame Informatique Sa",
    "wof:placetype":"venue"
},
  "geometry": {"coordinates":[-2.087962,48.465378],"type":"Point"}
}