{
  "type": "Feature",
  "properties": {
    "iso:country":"FR",
    "sg:address":"ZI de Lavazan",
    "sg:city":"Lavazan",
    "sg:orig_category":"Unclassifiable Establishments",
    "sg:phone":"+33 5 56 25 53 05",
    "sg:postcode":"33690",
    "sg:province":"Aquitaine",
    "wof:name":"Mourlan S.a.",
    "wof:placetype":"venue"
},
  "geometry": {"coordinates":[-0.109449,44.393745],"type":"Point"}
}