{
  "type": "Feature",
  "properties": {
    "addr:full":"Place Maurice Thorez; S. Pierre Aquitaine",
    "addr:street":"Place Maurice Thorez S. Pierre",
    "iso:country":"FR",
    "sg:address":"Place Maurice Thorez; S. Pierre",
    "sg:classifiers":[
        {
            "category":"Banks & Credit Unions",
            "subcategory":"Bank",
            "type":"Services"
        }
    ],
    "sg:phone":"+33 3347443542",
    "sg:province":"Aquitaine",
    "wof:name":"Banque Populaire Val De France",
    "wof:placetype":"venue"
},
  "geometry": {"coordinates":[-100.350159,44.368923],"type":"Point"}
}