{
  "type": "Feature",
  "properties": {
    "iso:country":"FR",
    "sg:address":"69460 Odenas",
    "sg:orig_category":"Unclassifiable Establishments",
    "sg:phone":"+33 4 74 03 41 38",
    "sg:province":"Rhone-Alpes",
    "wof:name":"Roussy De Sales S.a.",
    "wof:placetype":"venue"
},
  "geometry": {"coordinates":[4.646743,46.087975],"type":"Point"}
}