{
  "type": "Feature",
  "properties": {
    "iso:country":"FR",
    "sg:address":"29 Rue Du Mar\u00e9chal De Lattre Tassigny 79000 Niort",
    "sg:classifiers":[
        {
            "category":"Manufacturing",
            "subcategory":"Printing",
            "type":"Manufacturing & Wholesale Goods"
        }
    ],
    "sg:phone":"+33 5 49 73 34 27",
    "sg:province":"Poitou-Charentes",
    "sg:tags":[
        "publishing"
    ],
    "wof:name":"Barreau Sa Imprineur",
    "wof:placetype":"venue"
},
  "geometry": {"coordinates":[-0.470471,46.330357],"type":"Point"}
}