{
  "type": "Feature",
  "properties": {
    "iso:country":"FR",
    "sg:address":"11, Rue Watt, 75626 Paris C\u00e9dex 13",
    "sg:orig_category":"Non-Classified Establishments",
    "sg:phone":"+33 1 55 75 39 88",
    "sg:province":"\u00cele-de-France",
    "wof:name":"Sagem S.a.",
    "wof:placetype":"venue"
},
  "geometry": {"coordinates":[2.36562,48.830421],"type":"Point"}
}