{
  "type": "Feature",
  "properties": {
    "iso:country":"FR",
    "sg:address":"66, Rue Chauss\u00e9e d'Antin, 75009 Paris",
    "sg:orig_category":"Unclassifiable Establishments",
    "sg:phone":"+33 1 55 07 17 10",
    "sg:province":"Ile de France",
    "wof:name":"Cofranlait S.a.",
    "wof:placetype":"venue"
},
  "geometry": {"coordinates":[2.332278,48.874851],"type":"Point"}
}