{
  "type": "Feature",
  "properties": {
    "addr:full":"B.P. 203 Saint Di\u00e9 C\u00e9dex Rhone-Alpes 88106",
    "addr:housenumber":"b.p. 203",
    "addr:postcode":"88106",
    "addr:street":"Saint Die\u0301 Ce\u0301Dex Rhone-Alpes",
    "iso:country":"FR",
    "sg:address":"B.P. 203",
    "sg:city":"Saint Di\u00e9 C\u00e9dex",
    "sg:orig_category":"Boutons pour l'industrie \u00e9lectronique Boutons poussoirs Capteurs de pression Commutateurs \u00e0 boutons-",
    "sg:phone":"+33 3 29 56 23 82",
    "sg:postcode":"88106",
    "sg:province":"Rhone-Alpes",
    "wof:name":"T.h. Contact S.\u00e0.r.l.",
    "wof:placetype":"venue"
},
  "geometry": {"coordinates":[6.94889,48.283661],"type":"Point"}
}