{
  "type": "Feature",
  "properties": {
    "iso:country":"FR",
    "sg:address":"Lieu Dit La Chassagne 19100 Brive la Gaillarde",
    "sg:classifiers":[
        {
            "category":"Manufacturing",
            "subcategory":"Motor Vehicles & Parts",
            "type":"Manufacturing & Wholesale Goods"
        }
    ],
    "sg:phone":"+33 5 55 88 40 00",
    "sg:province":"Limousin",
    "sg:tags":[
        "precision",
        "mechanic"
    ],
    "wof:name":"Ets A. Deshors Sas",
    "wof:placetype":"venue"
},
  "geometry": {"coordinates":[1.475285,45.138958],"type":"Point"}
}