{
  "type": "Feature",
  "properties": {
    "iso:country":"FR",
    "sg:address":"Zi Forges 56650 Inzinzac Lochrist",
    "sg:city":"Inzinzac-Lochrist",
    "sg:classifiers":[
        {
            "category":"Autos & Motor Vehicles",
            "subcategory":"Automobile Sales",
            "type":"Retail Goods"
        }
    ],
    "sg:phone":"+33 2 97 36 02 37",
    "sg:postcode":"56650",
    "sg:province":"Bretagne",
    "sg:tags":[
        "equipment",
        "motor-cars",
        "transport"
    ],
    "wof:name":"Cim Sa",
    "wof:placetype":"venue"
},
  "geometry": {"coordinates":[-3.250278,47.826729],"type":"Point"}
}