{
  "type": "Feature",
  "properties": {
    "addr:full":"10 Rue Lionel Terray 92500 Rueil Malmaison Ile de France 92500",
    "addr:housenumber":"10",
    "addr:postcode":"92500;92500",
    "addr:street":"Rue Lionel Terray",
    "iso:country":"FR",
    "sg:address":"10 Rue Lionel Terray 92500 Rueil Malmaison",
    "sg:classifiers":[
        {
            "category":"Shopping",
            "subcategory":"Computers & Home Electronics",
            "type":"Retail Goods"
        }
    ],
    "sg:phone":"+33 1 41 39 02 70",
    "sg:postcode":"92500",
    "sg:province":"Ile de France",
    "sg:tags":[
        "electronic",
        "electrical",
        "equipment"
    ],
    "wof:name":"Marposs Sa",
    "wof:placetype":"venue"
},
  "geometry": {"coordinates":[2.180591,48.861134],"type":"Point"}
}