{
  "type": "Feature",
  "properties": {
    "addr:full":"100 rue France; Nice Aquitaine",
    "addr:housenumber":"100",
    "addr:street":"Rue France",
    "iso:country":"FR",
    "sg:address":"100 rue France; Nice",
    "sg:classifiers":[
        {
            "category":"Banks & Credit Unions",
            "subcategory":"Bank",
            "type":"Services"
        }
    ],
    "sg:phone":"+33 3393445054",
    "sg:province":"Aquitaine",
    "wof:name":"Banque Populaire De La C\u00f4te D'azur",
    "wof:placetype":"venue"
},
  "geometry": {"coordinates":[7.25184,43.694111],"type":"Point"}
}