{
  "type": "Feature",
  "properties": {
    "addr:full":"5, Bd du Midi, 76107 Rouen C\u00e9dex Haute Normandie",
    "addr:housenumber":"5",
    "addr:postcode":"76107",
    "addr:street":"Bd Du Midi;Haute Normandie",
    "iso:country":"FR",
    "sg:address":"5, Bd du Midi, 76107 Rouen C\u00e9dex",
    "sg:orig_category":"Unclassifiable Establishments",
    "sg:phone":"+33 2 32 81 63 10",
    "sg:province":"Haute Normandie",
    "wof:name":"Hoyer France S.a.",
    "wof:placetype":"venue"
},
  "geometry": {"coordinates":[1.043198,49.433491],"type":"Point"}
}