{
  "type": "Feature",
  "properties": {
    "addr:full":"B.P. 12, 72260 Marolles les Braults C\u00e9dex^^ZI Sud, 72260 Marolles les Braults Pays de Loire 72260",
    "addr:postcode":"72260;72260;72260",
    "addr:street":"B.P. 12;Ce\u0301Dex^^Zi Sud;Braults",
    "iso:country":"FR",
    "sg:address":"B.P. 12, 72260 Marolles les Braults C\u00e9dex^^ZI Sud, 72260 Marolles les Braults",
    "sg:orig_category":"Non-Classified Establishments",
    "sg:phone":"+33 2 43 97 48 99",
    "sg:postcode":"72260",
    "sg:province":"Pays de Loire",
    "wof:name":"Com\u00e9ma Equipement S.a.r.l.",
    "wof:placetype":"venue"
},
  "geometry": {"coordinates":[0.29722,48.238029],"type":"Point"}
}