{
  "type": "Feature",
  "properties": {
    "iso:country":"FR",
    "sg:address":"Zi La Roseraie 80500 Montdidier",
    "sg:classifiers":[
        {
            "category":"Bakery",
            "type":"Food & Drink"
        }
    ],
    "sg:phone":"+33 3 22 78 76 40",
    "sg:postcode":"80500",
    "sg:province":"Picardie",
    "sg:tags":[
        "cake",
        "product",
        "related",
        "bread"
    ],
    "wof:name":"Dailycer",
    "wof:placetype":"venue"
},
  "geometry": {"coordinates":[2.571364,49.647224],"type":"Point"}
}