{
  "type": "Feature",
  "properties": {
    "addr:full":"24 rue York; Dijon Bourgogne",
    "addr:housenumber":"24",
    "addr:street":"Rue York",
    "iso:country":"FR",
    "sg:address":"24 rue York; Dijon",
    "sg:classifiers":[
        {
            "category":"Banks & Credit Unions",
            "subcategory":"Bank",
            "type":"Services"
        }
    ],
    "sg:phone":"+33 3380713945",
    "sg:province":"Bourgogne",
    "wof:name":"Banque Populaire De Bourgogne",
    "wof:placetype":"venue"
},
  "geometry": {"coordinates":[5.06031,47.334435],"type":"Point"}
}