{
  "type": "Feature",
  "properties": {
    "addr:full":"30, Rue Amp\u00e8re - ZI de Jarlard, 81000 Albi Midi Pyr\u00e9n\u00e9es",
    "addr:housenumber":"30",
    "addr:postcode":"81000",
    "addr:street":"Rue Ampe\u0300Re Zi De Jarlard",
    "iso:country":"FR",
    "sg:address":"30, Rue Amp\u00e8re - ZI de Jarlard, 81000 Albi",
    "sg:orig_category":"Non-Classified Establishments",
    "sg:phone":"+33 5 63 46 01 07",
    "sg:province":"Midi Pyr\u00e9n\u00e9es",
    "wof:name":"Euromaster France S.n.c.",
    "wof:placetype":"venue"
},
  "geometry": {"coordinates":[2.148375,43.926205],"type":"Point"}
}