{
  "type": "Feature",
  "properties": {
    "iso:country":"FR",
    "sg:address":"46, Rte de Meung - Bizy , 41240 Ouzouer le March\u00e9",
    "sg:city":"Autainville",
    "sg:orig_category":"Unclassifiable Establishments",
    "sg:phone":"+33 2 54 82 46 73",
    "sg:postcode":"41240",
    "sg:province":"Centre",
    "wof:name":"Etablissements Violon S.a.",
    "wof:placetype":"venue"
},
  "geometry": {"coordinates":[1.508777,47.845856],"type":"Point"}
}