{
  "type": "Feature",
  "properties": {
    "addr:full":"route de St Augustin 49170 St Germain des Pr\u00e9s Pays de Loire",
    "addr:postcode":"49170",
    "addr:street":"Route De St Augustin;Des Pre\u0301S",
    "iso:country":"FR",
    "sg:address":"route de St Augustin 49170 St Germain des Pr\u00e9s",
    "sg:orig_category":"Powders For Highly Corrosion-Resistant Coatings",
    "sg:phone":"+33 2 41 39 98 80",
    "sg:province":"Pays de Loire",
    "wof:name":"Sgp Ste Germanoprataine Poudre Sarl",
    "wof:placetype":"venue"
},
  "geometry": {"coordinates":[-0.644095,47.380253],"type":"Point"}
}