{
  "type": "Feature",
  "properties": {
    "iso:country":"FR",
    "sg:address":"3, Impasse Michelet, 94200 Ivry sur Seine C\u00e9dex",
    "sg:orig_category":"Non-Classified Establishments",
    "sg:phone":"+33 1 45 15 20 50",
    "sg:province":"Ile de France",
    "wof:name":"S.e.r.t.e. S.a.r.l. Soci\u00e9t\u00e9 D'etudes Et De R\u00e9alisations De Travaux Electriques",
    "wof:placetype":"venue"
},
  "geometry": {"coordinates":[2.376712,48.807838],"type":"Point"}
}