{
  "type": "Feature",
  "properties": {
    "addr:full":"B.P. 7, 57740 Long\u00e9ville l\u00e8s Saint Avold^^Rte de Faulquemont, 57740 Long\u00e9ville l\u00e8s Saint Avold Lorraine",
    "addr:housenumber":"7",
    "addr:postcode":"57740;57740",
    "addr:street":"B.P.",
    "iso:country":"FR",
    "sg:address":"B.P. 7, 57740 Long\u00e9ville l\u00e8s Saint Avold^^Rte de Faulquemont, 57740 Long\u00e9ville l\u00e8s Saint Avold",
    "sg:orig_category":"Non-Classified Establishments",
    "sg:phone":"+33 3 87 91 84 00",
    "sg:province":"Lorraine",
    "wof:name":"Pompes Grundfos S.a.",
    "wof:placetype":"venue"
},
  "geometry": {"coordinates":[6.660749,49.112217],"type":"Point"}
}