{
  "type": "Feature",
  "properties": {
    "addr:full":"501 R Paradis 13008 Marseille Poitou-Charentes",
    "addr:housenumber":"501",
    "addr:postcode":"13008",
    "addr:street":"R Paradis",
    "iso:country":"FR",
    "sg:address":"501 R Paradis 13008 Marseille",
    "sg:classifiers":[
        {
            "category":"Banks & Credit Unions",
            "subcategory":"Financial Services",
            "type":"Services"
        }
    ],
    "sg:phone":"+33 4 96 20 30 81",
    "sg:province":"Poitou-Charentes",
    "sg:tags":[
        "banking",
        "insurance",
        "institution",
        "finance"
    ],
    "wof:name":"Credit Du Nord",
    "wof:placetype":"venue"
},
  "geometry": {"coordinates":[5.386252,43.271278],"type":"Point"}
}