{
  "type": "Feature",
  "properties": {
    "addr:full":"28, Rue du Docteur Gallet - ZI des Grands Pr\u00e9s, 74300 Cluses Rhone-Alpes 74300",
    "addr:housenumber":"28",
    "addr:postcode":"74300;74300",
    "addr:street":"Rue Du Docteur Gallet Zi Des Grands Pre\u0301S",
    "iso:country":"FR",
    "sg:address":"28, Rue du Docteur Gallet - ZI des Grands Pr\u00e9s, 74300 Cluses",
    "sg:orig_category":"Unclassifiable Establishments",
    "sg:phone":"+33 4 50 98 35 11",
    "sg:postcode":"74300",
    "sg:province":"Rhone-Alpes",
    "wof:name":"Savoy-d\u00e9colletage S.a.",
    "wof:placetype":"venue"
},
  "geometry": {"coordinates":[6.633185,45.987919],"type":"Point"}
}