{
  "type": "Feature",
  "properties": {
    "addr:full":"113, Bd S\u00e9bastopol, 75002 Paris Ile de France",
    "addr:housenumber":"113",
    "addr:postcode":"75002",
    "addr:street":"Bd Se\u0301Bastopol",
    "iso:country":"FR",
    "sg:address":"113, Bd S\u00e9bastopol, 75002 Paris",
    "sg:orig_category":"Non-Classified Establishments",
    "sg:phone":"+33 1 42 36 22 71",
    "sg:province":"Ile de France",
    "wof:name":"Gilou",
    "wof:placetype":"venue"
},
  "geometry": {"coordinates":[2.352921,48.867146],"type":"Point"}
}