{
  "type": "Feature",
  "properties": {
    "addr:full":"1 Rue Marcel Paul 95870 Bezons Ile de France 95870",
    "addr:housenumber":"1",
    "addr:postcode":"95870;ile;95870",
    "addr:street":"Rue Marcel Paul;France",
    "iso:country":"FR",
    "sg:address":"1 Rue Marcel Paul 95870 Bezons",
    "sg:classifiers":[
        {
            "category":"Manufacturing",
            "subcategory":"Metals",
            "type":"Manufacturing & Wholesale Goods"
        }
    ],
    "sg:phone":"+33 1 39 47 09 16",
    "sg:postcode":"95870",
    "sg:province":"Ile de France",
    "sg:tags":[
        "metallurgy",
        "steel",
        "metalworking"
    ],
    "wof:name":"Fonderie D Aluminium Et Kayem Sa",
    "wof:placetype":"venue"
},
  "geometry": {"coordinates":[2.211064,48.918095],"type":"Point"}
}