{
  "type": "Feature",
  "properties": {
    "addr:full":"3 Rue Alcazar 42700 Firminy Rhone-Alpes 42700",
    "addr:housenumber":"3",
    "addr:postcode":"42700;42700",
    "addr:street":"Rue Alcazar",
    "iso:country":"FR",
    "sg:address":"3 Rue Alcazar 42700 Firminy",
    "sg:classifiers":[
        {
            "category":"Shopping",
            "subcategory":"Clothing, Apparel, & Fashions",
            "type":"Retail Goods"
        }
    ],
    "sg:phone":"+33 4 77 56 33 10",
    "sg:postcode":"42700",
    "sg:province":"Rhone-Alpes",
    "sg:tags":[
        "textile",
        "clothing",
        "clothes"
    ],
    "wof:name":"Lejaby Sas",
    "wof:placetype":"venue"
},
  "geometry": {"coordinates":[4.292707,45.395733],"type":"Point"}
}