{
  "type": "Feature",
  "properties": {
    "addr:full":"Zone Artisanale Les Forges Lorraine 88390",
    "addr:postcode":"88390",
    "addr:street":"Zone Artisanale Les Forges",
    "iso:country":"FR",
    "sg:address":"Zone Artisanale",
    "sg:city":"Les Forges",
    "sg:orig_category":"Unclassifiable Establishments",
    "sg:phone":"+33 3 29 64 28 29",
    "sg:postcode":"88390",
    "sg:province":"Lorraine",
    "wof:name":"H.i. S.a.r.l. - Honor\u00e9 Industrie",
    "wof:placetype":"venue"
},
  "geometry": {"coordinates":[6.38716,48.178116],"type":"Point"}
}