{
  "type": "Feature",
  "properties": {
    "addr:full":"57620 Saint Louis l\u00e8s Bitche Lorraine",
    "addr:housenumber":"57620",
    "iso:country":"FR",
    "sg:address":"57620 Saint Louis l\u00e8s Bitche",
    "sg:orig_category":"Unclassifiable Establishments",
    "sg:phone":"+33 3 87 06 40 04",
    "sg:province":"Lorraine",
    "wof:name":"Compagnie Des Cristalleries De Saint Louis S.a.",
    "wof:placetype":"venue"
},
  "geometry": {"coordinates":[7.352776,48.987164],"type":"Point"}
}