{
  "type": "Feature",
  "properties": {
    "addr:full":"8, Chemin de la Lauvette - L'Ariane, 06300 Nice Champagne",
    "addr:housenumber":"8",
    "addr:postcode":"06300",
    "addr:street":"Chemin De La Lauvette L'Ariane",
    "iso:country":"FR",
    "sg:address":"8, Chemin de la Lauvette - L'Ariane, 06300 Nice",
    "sg:orig_category":"Non-Classified Establishments",
    "sg:phone":"+33 4 93 27 22 22",
    "sg:province":"Champagne",
    "wof:name":"Inter Protection 06 S.a.r.l.",
    "wof:placetype":"venue"
},
  "geometry": {"coordinates":[7.308157,43.74258],"type":"Point"}
}