{
  "type": "Feature",
  "properties": {
    "addr:full":"88/90, Rue Cardinet, 75847 Paris Poitou-Charentes",
    "addr:housenumber":"88 / 90",
    "addr:postcode":"75847",
    "addr:street":"Rue Cardinet",
    "iso:country":"FR",
    "sg:address":"88/90, Rue Cardinet, 75847 Paris",
    "sg:orig_category":"Non-Classified Establishments",
    "sg:phone":"+33 1 44 01 10 10",
    "sg:province":"Poitou-Charentes",
    "wof:name":"Cr\u00e9dit Mutuel",
    "wof:placetype":"venue"
},
  "geometry": {"coordinates":[2.309983,48.884472],"type":"Point"}
}