{
  "type": "Feature",
  "properties": {
    "iso:country":"FR",
    "sg:address":"RN 2160 - Les Moulinets",
    "sg:city":"Venansault",
    "sg:orig_category":"Non-Classified Establishments",
    "sg:phone":"+33 2 51 40 35 37",
    "sg:postcode":"85190",
    "sg:province":"Pays de Loire",
    "wof:name":"Armins S.a.",
    "wof:placetype":"venue"
},
  "geometry": {"coordinates":[-1.610729,46.676075],"type":"Point"}
}