{
  "type": "Feature",
  "properties": {
    "addr:full":"Rue Pierre Cot 71100 Chalons Sur Sa\u00f4ne Chalon-sur-Sa\u00f4ne Bourgogne 71100",
    "addr:postcode":"71100;71100",
    "addr:street":"Rue Pierre Cot;Sur Sao\u0302Ne;Bourgogne",
    "iso:country":"FR",
    "sg:address":"Rue Pierre Cot 71100 Chalons Sur Sa\u00f4ne",
    "sg:city":"Chalon-sur-Sa\u00f4ne",
    "sg:classifiers":[
        {
            "category":"Manufacturing",
            "subcategory":"Metals",
            "type":"Manufacturing & Wholesale Goods"
        }
    ],
    "sg:phone":"+33 3 85 41 11 40",
    "sg:postcode":"71100",
    "sg:province":"Bourgogne",
    "sg:tags":[
        "pipe",
        "sheet",
        "-",
        "metalworking",
        "metallic",
        "metallurgy",
        "finished"
    ],
    "wof:name":"Chauffage Industriel Tuyauteries Entretien Lelay",
    "wof:placetype":"venue"
},
  "geometry": {"coordinates":[4.859742,46.812683],"type":"Point"}
}