{
  "type": "Feature",
  "properties": {
    "iso:country":"FR",
    "sg:address":"Rue Bois De Treval 62850 Alquines",
    "sg:classifiers":[
        {
            "category":"Professional",
            "type":"Services"
        }
    ],
    "sg:phone":"+33 3 21 12 23 23",
    "sg:province":"Nord Pas-de-Calais",
    "sg:tags":[
        "transport",
        "road"
    ],
    "wof:name":"Transports Wintrebert Bernard Sa",
    "wof:placetype":"venue"
},
  "geometry": {"coordinates":[1.996175,50.726181],"type":"Point"}
}