{
  "type": "Feature",
  "properties": {
    "iso:country":"FR",
    "sg:address":"3, Rue Fran\u00e7ois Cuny - ZI de Villeneuve Braouic, 29300 Quimperl\u00e9",
    "sg:city":"Quimperl\u00e9",
    "sg:orig_category":"Unclassifiable Establishments",
    "sg:phone":"+33 2 98 96 09 73",
    "sg:postcode":"29300",
    "sg:province":"Bretagne",
    "wof:name":"Le Floch S.a.r.l.",
    "wof:placetype":"venue"
},
  "geometry": {"coordinates":[-3.461656,47.859921],"type":"Point"}
}