{
  "type": "Feature",
  "properties": {
    "addr:full":"B.P. 20 Mallemort C\u00e9dex^^Le Pont de Douneau 13370 Mallemort Pays de Loire 13370",
    "addr:postcode":"13370;13370",
    "addr:street":"B.P. 20 Mallemort Ce\u0301Dex^^Le Pont De Douneau",
    "iso:country":"FR",
    "sg:address":"B.P. 20",
    "sg:city":"Mallemort C\u00e9dex^^Le Pont de Douneau 13370 Mallemort",
    "sg:orig_category":"Non-Classified Establishments",
    "sg:phone":"+33 4 90 57 40 09",
    "sg:postcode":"13370",
    "sg:province":"Pays de Loire",
    "wof:name":"Transbis S.a.",
    "wof:placetype":"venue"
},
  "geometry": {"coordinates":[5.1776,43.729191],"type":"Point"}
}