{
  "type": "Feature",
  "properties": {
    "addr:full":"18 avenue Louise Michel 28500 Vernouillet Vernouillet Centre 28500",
    "addr:housenumber":"18",
    "addr:postcode":"28500;28500",
    "addr:street":"Avenue Louise Michel;Vernouillet",
    "iso:country":"FR",
    "sg:address":"18 avenue Louise Michel 28500 Vernouillet",
    "sg:city":"Vernouillet",
    "sg:classifiers":[
        {
            "category":"Shopping",
            "subcategory":"Department Store",
            "type":"Retail Goods"
        }
    ],
    "sg:phone":"+33 2 37 46 14 03",
    "sg:postcode":"28500",
    "sg:province":"Centre",
    "sg:tags":[
        "shop",
        "equipment",
        "bakery"
    ],
    "wof:name":"Essor Fournil S.a.",
    "wof:placetype":"venue"
},
  "geometry": {"coordinates":[1.325077,48.73225],"type":"Point"}
}