{
  "type": "Feature",
  "properties": {
    "iso:country":"FR",
    "sg:address":"B.P. 419, 22404 Lamballe C\u00e9dex^^7, Pont Saint Jacques, 22400 Lamballe",
    "sg:city":"Lamballe",
    "sg:orig_category":"Non-Classified Establishments",
    "sg:phone":"+33 2 96 31 20 37",
    "sg:postcode":"22400",
    "sg:province":"Bretagne",
    "wof:name":"Armor Magazine Sopel S.a.r.l.",
    "wof:placetype":"venue"
},
  "geometry": {"coordinates":[-2.539697,48.428795],"type":"Point"}
}