{
  "type": "Feature",
  "properties": {
    "iso:country":"FR",
    "sg:address":"6 rue Nobel 29000 Quimper",
    "sg:city":"Quimper",
    "sg:classifiers":[
        {
            "category":"Wholesale",
            "subcategory":"Medical Equipment & Supplies",
            "type":"Manufacturing & Wholesale Goods"
        }
    ],
    "sg:phone":"+33 2 98 55 68 95",
    "sg:postcode":"29000",
    "sg:province":"Bretagne",
    "sg:tags":[
        "implant",
        "orthopaedic"
    ],
    "wof:name":"Fournitures Hospitalieres Industrie Sa",
    "wof:placetype":"venue"
},
  "geometry": {"coordinates":[-4.151505,48.00214],"type":"Point"}
}