{
  "type": "Feature",
  "properties": {
    "iso:country":"FR",
    "sg:address":"ZI Jean Mal\u00e8ze",
    "sg:city":"Bon Encontre",
    "sg:orig_category":"Non-Classified Establishments",
    "sg:phone":"+33 5 53 77 32 77",
    "sg:postcode":"47240",
    "sg:province":"Aquitaine",
    "wof:name":"Drink Service S.a.",
    "wof:placetype":"venue"
},
  "geometry": {"coordinates":[0.668345,44.186184],"type":"Point"}
}