{
  "type": "Feature",
  "properties": {
    "iso:country":"FR",
    "sg:address":"4, Rue de l'Eglise, 60190 Sacy le Petit",
    "sg:orig_category":"Unclassifiable Establishments",
    "sg:phone":"+33 3 44 29 68 38",
    "sg:province":"Picardie",
    "wof:name":"Agrosem S.a.",
    "wof:placetype":"venue"
},
  "geometry": {"coordinates":[2.629631,49.360603],"type":"Point"}
}