{
  "type": "Feature",
  "properties": {
    "iso:country":"FR",
    "sg:address":"40, Rue Camille Roy, 69007 Lyon",
    "sg:orig_category":"Non-Classified Establishments",
    "sg:phone":"+33 4 37 28 37 38",
    "sg:postcode":"69007",
    "sg:province":"Rhone-Alpes",
    "wof:name":"Cospirit S.a.",
    "wof:placetype":"venue"
},
  "geometry": {"coordinates":[4.847464,45.745106],"type":"Point"}
}