{
  "type": "Feature",
  "properties": {
    "addr:full":"805, Rte de la Gare, 83110 Sanary sur Mer Provence-Alpes-C\u00f4te d'Azur",
    "addr:housenumber":"805",
    "addr:postcode":"83110",
    "addr:street":"Rte De La Gare;Mer",
    "iso:country":"FR",
    "sg:address":"805, Rte de la Gare, 83110 Sanary sur Mer",
    "sg:orig_category":"Unclassifiable Establishments",
    "sg:phone":"+33 4 94 07 63 08",
    "sg:province":"Provence-Alpes-C\u00f4te d'Azur",
    "wof:name":"L\u00e9zard Graphique S.a.r.l.",
    "wof:placetype":"venue"
},
  "geometry": {"coordinates":[5.819558,43.121628],"type":"Point"}
}