{
  "type": "Feature",
  "properties": {
    "iso:country":"FR",
    "sg:address":"11 Route Arbois 39380 Vaudrey",
    "sg:classifiers":[
        {
            "category":"Transit Center",
            "subcategory":"Freight",
            "type":"Transportation"
        }
    ],
    "sg:phone":"+33 3 84 71 72 72",
    "sg:postcode":"39380",
    "sg:province":"Franche Comt\u00e9",
    "sg:tags":[
        "metallurgy",
        "pipe",
        "metalworking",
        "sheet"
    ],
    "wof:name":"Profil C Sarl",
    "wof:placetype":"venue"
},
  "geometry": {"coordinates":[5.621955,46.973721],"type":"Point"}
}