{
  "type": "Feature",
  "properties": {
    "addr:full":"39 Chemin Des Chenes Zi De Ternier 74300 Thyez Rhone-Alpes 74300",
    "addr:housenumber":"39",
    "addr:postcode":"74300;74300",
    "addr:street":"Chemin Des Chenes Zi De Ternier;Rhone-Alpes",
    "iso:country":"FR",
    "sg:address":"39 Chemin Des Chenes Zi De Ternier 74300 Thyez",
    "sg:classifiers":[
        {
            "category":"Government",
            "subcategory":"Department Of Motor Vehicles",
            "type":"Public Place"
        }
    ],
    "sg:phone":"+33 4 50 34 68 38",
    "sg:postcode":"74300",
    "sg:province":"Rhone-Alpes",
    "sg:tags":[
        "equipment",
        "industrial",
        "transport",
        "motor-cars"
    ],
    "wof:name":"Revil Taillage Engrenages (rte)",
    "wof:placetype":"venue"
},
  "geometry": {"coordinates":[6.633185,45.987919],"type":"Point"}
}