{
  "type": "Feature",
  "properties": {
    "addr:full":"Le Parun 56870 Baden Baden Bretagne 56870",
    "addr:postcode":"56870;56870",
    "addr:street":"Baden Bretagne",
    "iso:country":"FR",
    "sg:address":"Le Parun 56870 Baden",
    "sg:city":"Baden",
    "sg:classifiers":[
        {
            "category":"Autos & Motor Vehicles",
            "subcategory":"Boat Sales",
            "type":"Retail Goods"
        }
    ],
    "sg:phone":"+33 2 97 57 00 15",
    "sg:postcode":"56870",
    "sg:province":"Bretagne",
    "sg:tags":[
        "equipment",
        "transport"
    ],
    "wof:name":"Chantier Naval Le Borgne Sarl",
    "wof:placetype":"venue"
},
  "geometry": {"coordinates":[-2.941564,47.611031],"type":"Point"}
}