{
  "type": "Feature",
  "properties": {
    "iso:country":"FR",
    "sg:address":"27, Rue Ch\u00e2teau Briand, 75383 Paris C\u00e9dex 08",
    "sg:city":"Ch\u00e2teau",
    "sg:orig_category":"Non-Classified Establishments",
    "sg:phone":"+33 1 42 99 00 00",
    "sg:postcode":"71250",
    "sg:province":"Bourgogne",
    "wof:name":"Sucre Union S.a.",
    "wof:placetype":"venue"
},
  "geometry": {"coordinates":[2.299861,48.873886],"type":"Point"}
}