{
  "type": "Feature",
  "properties": {
    "addr:full":"29, Rue Pajol, 75018 Paris Ile de France",
    "addr:housenumber":"29",
    "addr:postcode":"75018",
    "addr:street":"Rue Pajol",
    "iso:country":"FR",
    "sg:address":"29, Rue Pajol, 75018 Paris",
    "sg:orig_category":"Unclassifiable Establishments",
    "sg:phone":"+33 1 55 26 08 88",
    "sg:province":"Ile de France",
    "wof:name":"Powersource S.a.r.l.",
    "wof:placetype":"venue"
},
  "geometry": {"coordinates":[2.36153,48.887691],"type":"Point"}
}