{
  "type": "Feature",
  "properties": {
    "addr:full":"13 Boulevard Charles 5 54000 Nancy Lorraine 54000",
    "addr:housenumber":"13;5",
    "addr:postcode":"54000;54000",
    "addr:street":"Boulevard Charles",
    "iso:country":"FR",
    "sg:address":"13 Boulevard Charles 5 54000 Nancy",
    "sg:classifiers":[
        {
            "category":"Food Court",
            "type":"Food & Drink"
        }
    ],
    "sg:phone":"+33 3 83 85 51 51",
    "sg:postcode":"54000",
    "sg:province":"Lorraine",
    "sg:tags":[
        "product",
        "related"
    ],
    "wof:name":"Pernod",
    "wof:placetype":"venue"
},
  "geometry": {"coordinates":[6.175906,48.699989],"type":"Point"}
}