{
  "type": "Feature",
  "properties": {
    "iso:country":"FR",
    "sg:address":"B.P. 41107, 44311 Nantes C\u00e9dex 03^^1, Rue du Ch\u00e2teau de l'Eraudi\u00e8re - Immeuble Idao, 44300 Nantes",
    "sg:orig_category":"Non-Classified Establishments",
    "sg:phone":"+33 2 40 93 88 78",
    "sg:postcode":"44300",
    "sg:province":"Pays de Loire",
    "wof:name":"A.m.s. S.a. - Atlantique Merchandising Service",
    "wof:placetype":"venue"
},
  "geometry": {"coordinates":[-1.540981,47.238392],"type":"Point"}
}