{
  "type": "Feature",
  "properties": {
    "addr:full":"3 Saint Louis; Seclin; 59113 Nord Pas-de-Calais 59113",
    "addr:housenumber":"3",
    "addr:postcode":"59113;59113",
    "addr:street":"Saint",
    "iso:country":"FR",
    "sg:address":"3",
    "sg:city":"Saint Louis; Seclin; 59113",
    "sg:classifiers":[
        {
            "category":"Banks & Credit Unions",
            "subcategory":"Bank",
            "type":"Services"
        }
    ],
    "sg:phone":"+33 20901576",
    "sg:postcode":"59113",
    "sg:province":"Nord Pas-de-Calais",
    "wof:name":"Banque Nationale De Paris",
    "wof:placetype":"venue"
},
  "geometry": {"coordinates":[3.030181,50.550987],"type":"Point"}
}