{
  "type": "Feature",
  "properties": {
    "iso:country":"FR",
    "sg:address":"6 all\u00e9e des Peinieres 85670 Falleron",
    "sg:classifiers":[
        {
            "category":"Food & Beverages",
            "subcategory":"Meat & Fish",
            "type":"Retail Goods"
        }
    ],
    "sg:phone":"+33 2 51 93 25 10",
    "sg:postcode":"85670",
    "sg:province":"Pays de Loire",
    "wof:name":"Ste Ciale Import Export Produits Aliment Sas",
    "wof:placetype":"venue"
},
  "geometry": {"coordinates":[-1.6963,46.883408],"type":"Point"}
}