{
  "type": "Feature",
  "properties": {
    "addr:full":"3, Rue des Pays-Bas, 86170 Ciss\u00e9 Poitou-Charentes",
    "addr:housenumber":"3",
    "addr:postcode":"86170",
    "addr:street":"Rue Des Pays-Bas",
    "iso:country":"FR",
    "sg:address":"3, Rue des Pays-Bas, 86170 Ciss\u00e9",
    "sg:orig_category":"Unclassifiable Establishments",
    "sg:phone":"+33 5 49 51 92 52",
    "sg:province":"Poitou-Charentes",
    "wof:name":"A.g.i.s. S.a.r.l. - Atelier G\u00e9n\u00e9ral D'impressions Sp\u00e9ciales",
    "wof:placetype":"venue"
},
  "geometry": {"coordinates":[0.28149,46.653343],"type":"Point"}
}