{
  "type": "Feature",
  "properties": {
    "addr:full":"Rue Pierre Boulanger Lempdes Auvergne 63370",
    "addr:postcode":"63370",
    "addr:street":"Rue Pierre Boulanger",
    "iso:country":"FR",
    "sg:address":"Rue Pierre Boulanger",
    "sg:city":"Lempdes",
    "sg:orig_category":"Non-Classified Establishments",
    "sg:phone":"+33 4 73 83 64 91",
    "sg:postcode":"63370",
    "sg:province":"Auvergne",
    "wof:name":"Laboratoires Sauber - C.f.a. S.a.",
    "wof:placetype":"venue"
},
  "geometry": {"coordinates":[3.207748,45.775696],"type":"Point"}
}