{
  "type": "Feature",
  "properties": {
    "addr:full":"za Pr\u00e9s Mouchets 25500 Fins (Les) Franche Comt\u00e9 25500",
    "addr:postcode":"25500;25500",
    "addr:street":"Za Pre\u0301S Mouchets;Franche Comte\u0301",
    "iso:country":"FR",
    "sg:address":"za Pr\u00e9s Mouchets 25500 Fins (Les)",
    "sg:classifiers":[
        {
            "category":"Professional",
            "subcategory":"Engineering",
            "type":"Services"
        }
    ],
    "sg:phone":"+33 3 81 67 18 28",
    "sg:postcode":"25500",
    "sg:province":"Franche Comt\u00e9",
    "sg:tags":[
        "machine",
        "-",
        "jewellery",
        "mechanical"
    ],
    "wof:name":"Lerrac Outillage",
    "wof:placetype":"venue"
},
  "geometry": {"coordinates":[-80.580406,38.937016],"type":"Point"}
}