{
  "type": "Feature",
  "properties": {
    "addr:full":"47 Av Pierre Mend\u00e8s France 29000 Quimper Quimper Bretagne 29000",
    "addr:postcode":"29000;29000",
    "addr:street":"47 Av Pierre Mende\u0300S France",
    "iso:country":"FR",
    "sg:address":"47 Av Pierre Mend\u00e8s France 29000 Quimper",
    "sg:city":"Quimper",
    "sg:classifiers":[
        {
            "category":"Shopping",
            "subcategory":"Computers & Home Electronics",
            "type":"Retail Goods"
        }
    ],
    "sg:phone":"+33 2 98 53 80 82",
    "sg:postcode":"29000",
    "sg:province":"Bretagne",
    "sg:tags":[
        "equipment",
        "electrical",
        "component",
        "electric",
        "electronic"
    ],
    "wof:name":"Cristec Industries Sa",
    "wof:placetype":"venue"
},
  "geometry": {"coordinates":[-4.127989,47.97541],"type":"Point"}
}