{
  "type": "Feature",
  "properties": {
    "addr:full":"rue de l'Usine 68116 Guewenheim Guewenheim Alsace 68116",
    "addr:postcode":"68116;68116",
    "addr:street":"Rue De L'Usine;Guewenheim",
    "iso:country":"FR",
    "sg:address":"rue de l'Usine 68116 Guewenheim",
    "sg:city":"Guewenheim",
    "sg:classifiers":[
        {
            "category":"Manufacturing",
            "subcategory":"Metals",
            "type":"Manufacturing & Wholesale Goods"
        }
    ],
    "sg:phone":"+33 3 89 38 51 00",
    "sg:postcode":"68116",
    "sg:province":"Alsace",
    "sg:tags":[
        "made",
        "fa\u00e7ade",
        "panel"
    ],
    "wof:name":"Munch Constructions M\u00e9talliques Sa",
    "wof:placetype":"venue"
},
  "geometry": {"coordinates":[7.091996,47.753811],"type":"Point"}
}