{
  "type": "Feature",
  "properties": {
    "iso:country":"FR",
    "sg:address":"le Grand Patis 44850 ST MARS DU DESERT",
    "sg:classifiers":[
        {
            "category":"Shopping",
            "subcategory":"Discount & Variety Stores",
            "type":"Retail Goods"
        }
    ],
    "sg:phone":"+33 2 40 77 45 44",
    "sg:province":"Pays de Loire",
    "sg:tags":[
        "mix",
        "potting"
    ],
    "wof:name":"Tourbi\u00e8res De France Sa",
    "wof:placetype":"venue"
},
  "geometry": {"coordinates":[-1.451319,47.375648],"type":"Point"}
}