{
  "type": "Feature",
  "properties": {
    "iso:country":"FR",
    "sg:address":"92, Chemin de Gabardie, 31200 Toulouse",
    "sg:orig_category":"Non-Classified Establishments",
    "sg:phone":"+33 5 61 26 43 40",
    "sg:postcode":"31200",
    "sg:province":"Midi Pyr\u00e9n\u00e9es",
    "wof:name":"E.a.s. S.a. - Electricit\u00e9 Automatismes Syst\u00e8mes",
    "wof:placetype":"venue"
},
  "geometry": {"coordinates":[1.482668,43.629772],"type":"Point"}
}