{
  "type": "Feature",
  "properties": {
    "iso:country":"FR",
    "sg:address":"17 Avenue Marcellin Berthelot 92160 Antony",
    "sg:classifiers":[
        {
            "category":"Professional",
            "subcategory":"Engineering",
            "type":"Services"
        }
    ],
    "sg:phone":"+33 1 46 11 45 00",
    "sg:postcode":"92160",
    "sg:province":"Ile de France",
    "sg:tags":[
        "machine",
        "-",
        "mechanical"
    ],
    "wof:name":"Aldes Aeraulique Sa",
    "wof:placetype":"venue"
},
  "geometry": {"coordinates":[2.31611,48.737381],"type":"Point"}
}