{
  "type": "Feature",
  "properties": {
    "iso:country":"FR",
    "sg:address":"460, Rue A. Japy, 25460 Etupes",
    "sg:orig_category":"Non-Classified Establishments",
    "sg:phone":"+33 3 81 99 10 90",
    "sg:province":"Franche Comt\u00e9",
    "wof:name":"Sysio S.a.r.l.",
    "wof:placetype":"venue"
},
  "geometry": {"coordinates":[6.862814,47.506931],"type":"Point"}
}