{
  "type": "Feature",
  "properties": {
    "iso:country":"FR",
    "sg:address":"52340 Ageville",
    "sg:orig_category":"Non-Classified Establishments",
    "sg:phone":"+33 3 25 31 93 37",
    "sg:postcode":"52340",
    "sg:province":"Champagne",
    "wof:name":"Coop\u00e9rative Laiti\u00e8re De La Vall\u00e9e Du Rognon",
    "wof:placetype":"venue"
},
  "geometry": {"coordinates":[5.352009,48.109421],"type":"Point"}
}