{
  "type": "Feature",
  "properties": {
    "addr:full":"Rte de Douai Orchies Nord Pas-de-Calais 59310",
    "addr:postcode":"59310",
    "addr:street":"Rte De Douai",
    "iso:country":"FR",
    "sg:address":"Rte de Douai",
    "sg:city":"Orchies",
    "sg:orig_category":"Non-Classified Establishments",
    "sg:phone":"+33 3 20 64 64 84",
    "sg:postcode":"59310",
    "sg:province":"Nord Pas-de-Calais",
    "wof:name":"Slosse S.a.r.l.",
    "wof:placetype":"venue"
},
  "geometry": {"coordinates":[3.238862,50.473221],"type":"Point"}
}