{
  "type": "Feature",
  "properties": {
    "iso:country":"FR",
    "sg:address":"10 Rue De La Batellerie 52100 St Dizier",
    "sg:classifiers":[
        {
            "category":"Wholesale",
            "subcategory":"Machinery & Supplies",
            "type":"Manufacturing & Wholesale Goods"
        }
    ],
    "sg:phone":"+33 3 25 56 55 67",
    "sg:province":"Champagne",
    "sg:tags":[
        "equipment",
        "optical",
        "precision",
        "instrument"
    ],
    "wof:name":"Mecascenic",
    "wof:placetype":"venue"
},
  "geometry": {"coordinates":[4.933402,48.636021],"type":"Point"}
}