{
  "type": "Feature",
  "properties": {
    "addr:full":"19, Bd Jean Jaur\u00e8s, 54000 Nancy Lorraine",
    "addr:housenumber":"19",
    "addr:postcode":"54000",
    "addr:street":"Bd Jean Jaure\u0300S",
    "iso:country":"FR",
    "sg:address":"19, Bd Jean Jaur\u00e8s, 54000 Nancy",
    "sg:orig_category":"Non-Classified Establishments",
    "sg:phone":"+33 3 83 90 30 30",
    "sg:province":"Lorraine",
    "wof:name":"Lorraine T\u00e9l\u00e9com",
    "wof:placetype":"venue"
},
  "geometry": {"coordinates":[6.177404,48.683247],"type":"Point"}
}