{
  "type": "Feature",
  "properties": {
    "iso:country":"FR",
    "sg:address":"45, Av. Andr\u00e9 Roussin, 13016 Marseille",
    "sg:orig_category":"Unclassifiable Establishments",
    "sg:phone":"+33 4 96 15 25 70",
    "sg:province":"Provence-Alpes-C\u00f4te d'Azur",
    "wof:name":"P.f.s. S.a. - Processed Fruit Suppliers",
    "wof:placetype":"venue"
},
  "geometry": {"coordinates":[5.337393,43.358269],"type":"Point"}
}