{
  "type": "Feature",
  "properties": {
    "addr:full":"B.P. 33, 71601 Paray le Monial C\u00e9dex^^Place de la Visitation, 71600 Paray le Monial Varenne-Saint-Germain Bourgogne 71600",
    "addr:postcode":"71601;71600;71600",
    "addr:street":"B.P. 33;Visitation",
    "iso:country":"FR",
    "sg:address":"B.P. 33, 71601 Paray le Monial C\u00e9dex^^Place de la Visitation, 71600 Paray le Monial",
    "sg:city":"Varenne-Saint-Germain",
    "sg:orig_category":"Non-Classified Establishments",
    "sg:phone":"+33 3 85 81 60 08",
    "sg:postcode":"71600",
    "sg:province":"Bourgogne",
    "wof:name":"Cercle Entreprise S.a.",
    "wof:placetype":"venue"
},
  "geometry": {"coordinates":[4.127668,46.384384],"type":"Point"}
}