{
  "type": "Feature",
  "properties": {
    "addr:full":"3 Rue Soufflot 75005 Paris Ile de France",
    "addr:housenumber":"3",
    "addr:postcode":"75005",
    "addr:street":"Rue Soufflot",
    "iso:country":"FR",
    "sg:address":"3 Rue Soufflot 75005 Paris",
    "sg:classifiers":[
        {
            "category":"Professional",
            "subcategory":"Printing & Photocopies",
            "type":"Services"
        }
    ],
    "sg:phone":"+33 1 55 42 61 30",
    "sg:province":"Ile de France",
    "sg:tags":[
        "publishing"
    ],
    "wof:name":"Les Editions Techniques Et Economiques",
    "wof:placetype":"venue"
},
  "geometry": {"coordinates":[2.343953,48.8465],"type":"Point"}
}