{
  "type": "Feature",
  "properties": {
    "iso:country":"FR",
    "sg:address":"15 Avenue Albert 1er 21000 Dijon",
    "sg:city":"Dijon",
    "sg:classifiers":[
        {
            "category":"Travel",
            "subcategory":"Hotels & Motels",
            "type":"Entertainment"
        }
    ],
    "sg:phone":"+33 3 80 43 01 12",
    "sg:postcode":"21000",
    "sg:province":"Bourgogne",
    "sg:tags":[
        "hotels",
        "business",
        "restaurant"
    ],
    "wof:name":"Ste De Notellerie De Bourgogne",
    "wof:placetype":"venue"
},
  "geometry": {"coordinates":[5.023181,47.322239],"type":"Point"}
}