{
  "type": "Feature",
  "properties": {
    "addr:full":"36400 Montgivray Montgivray Centre 36400",
    "addr:housenumber":"montgivray",
    "addr:postcode":"36400;36400",
    "iso:country":"FR",
    "sg:address":"36400 Montgivray",
    "sg:city":"Montgivray",
    "sg:orig_category":"Unclassifiable Establishments",
    "sg:phone":"+33 2 54 06 11 11",
    "sg:postcode":"36400",
    "sg:province":"Centre",
    "wof:name":"Imprimerie George Sand S.a.r.l.",
    "wof:placetype":"venue"
},
  "geometry": {"coordinates":[1.98586,46.604855],"type":"Point"}
}