{
  "type": "Feature",
  "properties": {
    "addr:full":"Route D'Argent Zi De Morestel 38510 Morestel Rhone-Alpes 38510",
    "addr:postcode":"38510;38510",
    "addr:street":"Route D'Argent Zi De Morestel",
    "iso:country":"FR",
    "sg:address":"Route D'Argent Zi De Morestel 38510 Morestel",
    "sg:classifiers":[
        {
            "category":"Building & Trades",
            "subcategory":"Construction",
            "type":"Services"
        }
    ],
    "sg:phone":"+33 4 74 80 17 23",
    "sg:postcode":"38510",
    "sg:province":"Rhone-Alpes",
    "sg:tags":[
        "work",
        "public"
    ],
    "wof:name":"Travaux Routier Pl",
    "wof:placetype":"venue"
},
  "geometry": {"coordinates":[5.471241,45.672802],"type":"Point"}
}