{
  "type": "Feature",
  "properties": {
    "addr:full":"ZI d'Argentan La Fert\u00e9 Mac\u00e9 Basse Normandie 61600",
    "addr:postcode":"61600",
    "addr:street":"D'Argentan",
    "iso:country":"FR",
    "sg:address":"ZI d'Argentan",
    "sg:city":"La Fert\u00e9 Mac\u00e9",
    "sg:orig_category":"Unclassifiable Establishments",
    "sg:phone":"+33 2 33 30 69 70",
    "sg:postcode":"61600",
    "sg:province":"Basse Normandie",
    "wof:name":"Etablissement Ren\u00e9 Lacroix Et Compagnie",
    "wof:placetype":"venue"
},
  "geometry": {"coordinates":[-0.35835,48.589481],"type":"Point"}
}