{
  "type": "Feature",
  "properties": {
    "iso:country":"FR",
    "sg:address":"ZA la Plaine",
    "sg:city":"Unieux",
    "sg:orig_category":"Non-Classified Establishments",
    "sg:phone":"+33 4 77 61 78 61",
    "sg:postcode":"42240",
    "sg:province":"Rhone-Alpes",
    "wof:name":"L'a.c.n. S.a.r.l. - L'auvergne Commerciale Num\u00e9rique",
    "wof:placetype":"venue"
},
  "geometry": {"coordinates":[4.261915,45.399975],"type":"Point"}
}