{
  "type": "Feature",
  "properties": {
    "addr:full":"91 Rue Longwy 54720 Lexy Lorraine 54720",
    "addr:housenumber":"91",
    "addr:postcode":"54720;54720",
    "addr:street":"Rue Longwy",
    "iso:country":"FR",
    "sg:address":"91 Rue Longwy 54720 Lexy",
    "sg:classifiers":[
        {
            "category":"Manufacturing",
            "subcategory":"Tools & Machinery",
            "type":"Manufacturing & Wholesale Goods"
        }
    ],
    "sg:phone":"+33 3 82 23 25 97",
    "sg:postcode":"54720",
    "sg:province":"Lorraine",
    "sg:tags":[
        "metallurgy",
        "metalworking"
    ],
    "wof:name":"Monsieur Bricolage",
    "wof:placetype":"venue"
},
  "geometry": {"coordinates":[5.734998,49.51413],"type":"Point"}
}