{
  "type": "Feature",
  "properties": {
    "addr:full":"38 Rue De Berri Chez Sdm Artisans Contact 75008 Paris Ile de France 75008",
    "addr:housenumber":"38",
    "addr:postcode":"75008;75008",
    "addr:street":"Rue De Berri Chez",
    "iso:country":"FR",
    "sg:address":"38 Rue De Berri Chez Sdm Artisans Contact 75008 Paris",
    "sg:classifiers":[
        {
            "category":"Professional",
            "subcategory":"Engineering",
            "type":"Services"
        }
    ],
    "sg:phone":"+33 1 47 82 25 94",
    "sg:postcode":"75008",
    "sg:province":"Ile de France",
    "sg:tags":[
        "machine",
        "-",
        "mechanical"
    ],
    "wof:name":"Aep Electronique",
    "wof:placetype":"venue"
},
  "geometry": {"coordinates":[2.34121,48.856926],"type":"Point"}
}