{
  "type": "Feature",
  "properties": {
    "addr:full":"Rue De La Fraternite 69740 Genas Rhone-Alpes 69740",
    "addr:postcode":"69740;69740",
    "addr:street":"Rue De La Fraternite",
    "iso:country":"FR",
    "sg:address":"Rue De La Fraternite 69740 Genas",
    "sg:classifiers":[
        {
            "category":"Professional",
            "subcategory":"Engineering",
            "type":"Services"
        }
    ],
    "sg:phone":"+33 4 78 90 12 93",
    "sg:postcode":"69740",
    "sg:province":"Rhone-Alpes",
    "sg:tags":[
        "machine",
        "-",
        "environment",
        "equipment",
        "machinery",
        "mechanical"
    ],
    "wof:name":"Est Metal",
    "wof:placetype":"venue"
},
  "geometry": {"coordinates":[5.01518,45.728249],"type":"Point"}
}