{
  "type": "Feature",
  "properties": {
    "iso:country":"FR",
    "sg:address":"12 Avenue De Verdun 93140 Bondy",
    "sg:classifiers":[
        {
            "category":"Professional",
            "subcategory":"Business Services",
            "type":"Services"
        }
    ],
    "sg:phone":"+33 1 48 49 51 74",
    "sg:postcode":"93140",
    "sg:province":"Ile de France",
    "sg:tags":[
        "training",
        "advice"
    ],
    "wof:name":"Association Gestion Ets Assomption Bondy",
    "wof:placetype":"venue"
},
  "geometry": {"coordinates":[2.489718,48.905193],"type":"Point"}
}