{
  "type": "Feature",
  "properties": {
    "addr:full":"30 rue Le Corbusier; Ronchamp; 70250 Franche Comt\u00e9 70250",
    "addr:housenumber":"30",
    "addr:postcode":"70250;70250",
    "addr:street":"Rue Le Corbusier;Comte\u0301",
    "iso:country":"FR",
    "sg:address":"30 rue Le Corbusier; Ronchamp; 70250",
    "sg:classifiers":[
        {
            "category":"Banks & Credit Unions",
            "subcategory":"Bank",
            "type":"Services"
        }
    ],
    "sg:phone":"+33 3 84 20 69 00",
    "sg:postcode":"70250",
    "sg:province":"Franche Comt\u00e9",
    "wof:name":"Cr\u00e9dit Industriel D'alsace, Et De Lorraine Sa",
    "wof:placetype":"venue"
},
  "geometry": {"coordinates":[6.630042,47.700249],"type":"Point"}
}