{
  "type": "Feature",
  "properties": {
    "addr:full":"B.P. 200, 91300 Massy C\u00e9dex^^1, Rue du Saule Trapu, 91300 Massy Ile de France",
    "addr:housenumber":"b.p. 200",
    "addr:postcode":"91300;91300",
    "addr:street":"Rue Du Saule Trapu;Ile De France",
    "iso:country":"FR",
    "sg:address":"B.P. 200, 91300 Massy C\u00e9dex^^1, Rue du Saule Trapu, 91300 Massy",
    "sg:orig_category":"Non-Classified Establishments",
    "sg:phone":"+33 1 69 75 41 70",
    "sg:province":"Ile de France",
    "wof:name":"Wright Line S.a.",
    "wof:placetype":"venue"
},
  "geometry": {"coordinates":[2.27325,48.730282],"type":"Point"}
}