{
  "type": "Feature",
  "properties": {
    "iso:country":"FR",
    "sg:address":"Rte de Franquevaux - Domaine Bel Air la C\u00f4te",
    "sg:city":"Beauvoisin",
    "sg:orig_category":"Non-Classified Establishments",
    "sg:phone":"+33 4 66 73 30 22",
    "sg:postcode":"30640",
    "sg:province":"Languedoc-Roussillon",
    "wof:name":"Moine E.a.r.l.",
    "wof:placetype":"venue"
},
  "geometry": {"coordinates":[4.323261,43.719765],"type":"Point"}
}