{
  "type": "Feature",
  "properties": {
    "addr:full":"22, Rue de Kingersheim, 68120 Richwiller Richwiller Alsace 68120",
    "addr:housenumber":"22",
    "addr:postcode":"68120;68120",
    "addr:street":"Rue De Kingersheim",
    "iso:country":"FR",
    "sg:address":"22, Rue de Kingersheim, 68120 Richwiller",
    "sg:city":"Richwiller",
    "sg:orig_category":"Unclassifiable Establishments",
    "sg:phone":"+33 3 89 57 45 25",
    "sg:postcode":"68120",
    "sg:province":"Alsace",
    "wof:name":"Level S.a.r.l.",
    "wof:placetype":"venue"
},
  "geometry": {"coordinates":[7.299928,47.788311],"type":"Point"}
}