{
  "type": "Feature",
  "properties": {
    "addr:full":"Ch\u00e2teau Labatut 33490 Saint Maixant Caudrot Aquitaine 33490",
    "addr:postcode":"33490;33490",
    "iso:country":"FR",
    "sg:address":"Ch\u00e2teau Labatut 33490 Saint Maixant",
    "sg:city":"Caudrot",
    "sg:orig_category":"Non-Classified Establishments",
    "sg:phone":"+33 5 56 62 02 44",
    "sg:postcode":"33490",
    "sg:province":"Aquitaine",
    "wof:name":"Vignobles Michel Bouchard S.c.e.a.",
    "wof:placetype":"venue"
},
  "geometry": {"coordinates":[-0.19024,44.571815],"type":"Point"}
}