{
  "type": "Feature",
  "properties": {
    "iso:country":"FR",
    "sg:address":"Hotel Rihouey 50570 Carantilly",
    "sg:city":"Carantilly",
    "sg:classifiers":[
        {
            "category":"Wholesale",
            "subcategory":"Meat",
            "type":"Manufacturing & Wholesale Goods"
        }
    ],
    "sg:phone":"+33 2 33 56 62 41",
    "sg:postcode":"50570",
    "sg:province":"Basse Normandie",
    "sg:tags":[
        "food",
        "cooked",
        "product",
        "related"
    ],
    "wof:name":"Jambon Normand Jourdan",
    "wof:placetype":"venue"
},
  "geometry": {"coordinates":[-1.244295,49.060257],"type":"Point"}
}