{
  "type": "Feature",
  "properties": {
    "addr:full":"33125 Hostens Hostens Aquitaine 33125",
    "addr:postcode":"33125;33125",
    "iso:country":"FR",
    "sg:address":"33125 Hostens",
    "sg:city":"Hostens",
    "sg:classifiers":[
        {
            "category":"Home & Garden",
            "subcategory":"Furniture",
            "type":"Retail Goods"
        }
    ],
    "sg:phone":"+33 5 56 88 54 90",
    "sg:postcode":"33125",
    "sg:province":"Aquitaine",
    "sg:tags":[
        "household",
        "wood"
    ],
    "wof:name":"Entreprise J Masse Et Fils",
    "wof:placetype":"venue"
},
  "geometry": {"coordinates":[-0.639979,44.492809],"type":"Point"}
}