{
  "type": "Feature",
  "properties": {
    "iso:country":"FR",
    "sg:address":"B.P. 16, 42230 Roche la Moli\u00e8re^^23, Bd Pierre et Marie Curie, 42230 Roche la Moli\u00e8re",
    "sg:orig_category":"Non-Classified Establishments",
    "sg:phone":"+33 4 77 90 09 10",
    "sg:province":"Rhone-Alpes",
    "wof:name":"Roche Industrie S.a.",
    "wof:placetype":"venue"
},
  "geometry": {"coordinates":[4.322345,45.432907],"type":"Point"}
}