{
  "type": "Feature",
  "properties": {
    "iso:country":"FR",
    "sg:address":"189, Bd Faidherbe, 59280 Armenti\u00e8res",
    "sg:orig_category":"Unclassifiable Establishments",
    "sg:phone":"+33 3 20 10 34 44",
    "sg:province":"Nord Pas-de-Calais",
    "wof:name":"A.n.p.e.",
    "wof:placetype":"venue"
},
  "geometry": {"coordinates":[2.86959,50.68457],"type":"Point"}
}