{
  "type": "Feature",
  "properties": {
    "iso:country":"FR",
    "sg:address":"9, Rue du Docteur Calmette, 93100 Montreuil",
    "sg:orig_category":"Non-Classified Establishments",
    "sg:phone":"+33 1 48 59 19 19",
    "sg:province":"Ile de France",
    "wof:name":"Valoutil S.a.",
    "wof:placetype":"venue"
},
  "geometry": {"coordinates":[2.440935,48.866913],"type":"Point"}
}