{
  "type": "Feature",
  "properties": {
    "addr:full":"12, Av. du Val de l'Eure, 28630 Fontenay sur Eure Berch\u00e8res-les-Pierres Centre 28630",
    "addr:postcode":"28630;28630",
    "addr:street":"12 Av. Du Val De L'Eure",
    "iso:country":"FR",
    "sg:address":"12, Av. du Val de l'Eure, 28630 Fontenay sur Eure",
    "sg:city":"Berch\u00e8res-les-Pierres",
    "sg:orig_category":"Non-Classified Establishments",
    "sg:phone":"+33 2 37 30 98 44",
    "sg:postcode":"28630",
    "sg:province":"Centre",
    "wof:name":"L.g.i. Industrie S.a.",
    "wof:placetype":"venue"
},
  "geometry": {"coordinates":[1.437771,48.422684],"type":"Point"}
}