{
  "type": "Feature",
  "properties": {
    "addr:full":"31 pl du 10 Juin; Issoudun; 36100 Issoudun Centre 36100",
    "addr:housenumber":"31",
    "addr:postcode":"36100;36100",
    "addr:street":"Pl Du 10 Juin",
    "iso:country":"FR",
    "sg:address":"31 pl du 10 Juin; Issoudun; 36100",
    "sg:city":"Issoudun",
    "sg:classifiers":[
        {
            "category":"Banks & Credit Unions",
            "subcategory":"Bank",
            "type":"Services"
        }
    ],
    "sg:phone":"+33 3354211073",
    "sg:postcode":"36100",
    "sg:province":"Centre",
    "wof:name":"Soci\u00e9t\u00e9 G\u00e9n\u00e9rale",
    "wof:placetype":"venue"
},
  "geometry": {"coordinates":[1.991181,46.948769],"type":"Point"}
}