{
  "type": "Feature",
  "properties": {
    "iso:country":"FR",
    "sg:address":"6 Rond Point; Blois; 41000",
    "sg:city":"Blois",
    "sg:classifiers":[
        {
            "category":"Banks & Credit Unions",
            "subcategory":"Bank",
            "type":"Services"
        }
    ],
    "sg:phone":"+33 3354788799",
    "sg:postcode":"41000",
    "sg:province":"Centre",
    "wof:name":"Cr\u00e9dit Foncier De France",
    "wof:placetype":"venue"
},
  "geometry": {"coordinates":[1.331433,47.586849],"type":"Point"}
}