{
  "type": "Feature",
  "properties": {
    "addr:full":"2, Rue de la Glaci\u00e8re, 17700 Surg\u00e8res Poitou-Charentes",
    "addr:housenumber":"2",
    "addr:postcode":"17700",
    "addr:street":"Rue De La Glacie\u0300Re",
    "iso:country":"FR",
    "sg:address":"2, Rue de la Glaci\u00e8re, 17700 Surg\u00e8res",
    "sg:orig_category":"Unclassifiable Establishments",
    "sg:phone":"+33 5 46 07 58 80",
    "sg:province":"Poitou-Charentes",
    "wof:name":"Charentes Lait Surg\u00e8res",
    "wof:placetype":"venue"
},
  "geometry": {"coordinates":[-0.758705,46.109154],"type":"Point"}
}