{
  "type": "Feature",
  "properties": {
    "addr:full":"71 cours Albert Thomas 69003 Lyon Rhone-Alpes",
    "addr:housenumber":"71",
    "addr:postcode":"69003",
    "addr:street":"Cours Albert Thomas",
    "iso:country":"FR",
    "sg:address":"71 cours Albert Thomas 69003 Lyon",
    "sg:classifiers":[
        {
            "category":"Professional",
            "subcategory":"Printing & Photocopies",
            "type":"Services"
        }
    ],
    "sg:phone":"+33 4 78 54 64 00",
    "sg:province":"Rhone-Alpes",
    "sg:tags":[
        "publishing",
        "software"
    ],
    "wof:name":"Soft Concept Sarl",
    "wof:placetype":"venue"
},
  "geometry": {"coordinates":[4.867836,45.746826],"type":"Point"}
}