{
  "type": "Feature",
  "properties": {
    "iso:country":"FR",
    "sg:address":"17 rue de la R\u00e9publique; Guebwiller; 68500",
    "sg:city":"Guebwiller",
    "sg:classifiers":[
        {
            "category":"Banks & Credit Unions",
            "subcategory":"Bank",
            "type":"Services"
        }
    ],
    "sg:phone":"+33 3389769462",
    "sg:postcode":"68500",
    "sg:province":"Alsace",
    "wof:name":"Soci\u00e9t\u00e9 G\u00e9n\u00e9rale",
    "wof:placetype":"venue"
},
  "geometry": {"coordinates":[7.213412,47.907322],"type":"Point"}
}