{
  "type": "Feature",
  "properties": {
    "addr:full":"39/45, Rue de la Soie, 69627 Villeurbanne C\u00e9dex Vill\u00e9 Alsace 67220",
    "addr:housenumber":"39 / 45",
    "addr:postcode":"69627;67220",
    "addr:street":"Rue De La Soie",
    "iso:country":"FR",
    "sg:address":"39/45, Rue de la Soie, 69627 Villeurbanne C\u00e9dex",
    "sg:city":"Vill\u00e9",
    "sg:orig_category":"Non-Classified Establishments",
    "sg:phone":"+33 4 72 36 11 67",
    "sg:postcode":"67220",
    "sg:province":"Alsace",
    "wof:name":"E.i. Energie S.n.c.",
    "wof:placetype":"venue"
},
  "geometry": {"coordinates":[4.919428,45.761333],"type":"Point"}
}