{
  "type": "Feature",
  "properties": {
    "addr:full":"Herville BP 28 28270 Brezolles Brezolles Centre 28270",
    "addr:housenumber":"bp 28;brezolles",
    "addr:postcode":"28270;28270",
    "iso:country":"FR",
    "sg:address":"Herville BP 28 28270 Brezolles",
    "sg:city":"Brezolles",
    "sg:classifiers":[
        {
            "category":"Professional",
            "subcategory":"Printing & Photocopies",
            "type":"Services"
        }
    ],
    "sg:phone":"+33 2 37 43 66 60",
    "sg:postcode":"28270",
    "sg:province":"Centre",
    "sg:tags":[
        "publishing"
    ],
    "wof:name":"Les Editions Du Verbe",
    "wof:placetype":"venue"
},
  "geometry": {"coordinates":[0.977539,48.644032],"type":"Point"}
}