{
  "type": "Feature",
  "properties": {
    "iso:country":"FR",
    "sg:address":"Chemin de Nar\u00e9aux",
    "sg:city":"Auch",
    "sg:orig_category":"Non-Classified Establishments",
    "sg:phone":"+33 5 62 60 10 80",
    "sg:postcode":"32000",
    "sg:province":"Midi Pyr\u00e9n\u00e9es",
    "wof:name":"Braton Groupe S.a.r.l.",
    "wof:placetype":"venue"
},
  "geometry": {"coordinates":[0.62845,43.656933],"type":"Point"}
}