{
  "type": "Feature",
  "properties": {
    "iso:country":"FR",
    "sg:address":"Boulevard Maritime Zi 76530 Grand Couronne",
    "sg:classifiers":[
        {
            "category":"Food & Beverages",
            "subcategory":"Groceries & Convenience Stores",
            "type":"Retail Goods"
        }
    ],
    "sg:phone":"+33 2 35 18 23 23",
    "sg:postcode":"76530",
    "sg:province":"Haute Normandie",
    "sg:tags":[
        "product",
        "related"
    ],
    "wof:name":"Societe Agro Industrielle De Patrimoine Oleagineux (saipol)",
    "wof:placetype":"venue"
},
  "geometry": {"coordinates":[1.00869,49.357891],"type":"Point"}
}