{
  "type": "Feature",
  "properties": {
    "iso:country":"FR",
    "sg:address":"B.P. 12, 54420 Saulxures l\u00e8s Nancy^^Rte de Bosserville, 54420 Saulxures l\u00e8s Nancy",
    "sg:orig_category":"Non-Classified Establishments",
    "sg:phone":"+33 3 83 51 36 30",
    "sg:province":"Lorraine",
    "wof:name":"Gauthrot Fr\u00e8res S.a.",
    "wof:placetype":"venue"
},
  "geometry": {"coordinates":[6.245006,48.686962],"type":"Point"}
}