{
  "type": "Feature",
  "properties": {
    "addr:full":"ZI Villecomtal sur Arros Midi Pyr\u00e9n\u00e9es 32730",
    "addr:postcode":"32730",
    "addr:street":"Villecomtal",
    "iso:country":"FR",
    "sg:address":"ZI",
    "sg:city":"Villecomtal sur Arros",
    "sg:orig_category":"Unclassifiable Establishments",
    "sg:phone":"+33 5 62 64 86 19",
    "sg:postcode":"32730",
    "sg:province":"Midi Pyr\u00e9n\u00e9es",
    "wof:name":"Curdi S.a.r.l.",
    "wof:placetype":"venue"
},
  "geometry": {"coordinates":[0.19418,43.401199],"type":"Point"}
}