{
  "type": "Feature",
  "properties": {
    "iso:country":"FR",
    "sg:address":"21, Rue H\u00e9bert, 92140 Clamart",
    "sg:orig_category":"Non-Classified Establishments",
    "sg:phone":"+33 1 46 42 52 77",
    "sg:postcode":"92140",
    "sg:province":"Ile de France",
    "wof:name":"D. Cr\u00e9a S.a.r.l.",
    "wof:placetype":"venue"
},
  "geometry": {"coordinates":[2.273455,48.812557],"type":"Point"}
}