{
  "type": "Feature",
  "properties": {
    "iso:country":"FR",
    "sg:address":"287, Chemin de la Madrague Ville, 13015 Marseille",
    "sg:city":"Vill\u00e9",
    "sg:orig_category":"Unclassifiable Establishments",
    "sg:phone":"+33 4 91 09 10 10",
    "sg:postcode":"67220",
    "sg:province":"Alsace",
    "wof:name":"Aldis Sud Est 2 S.a.",
    "wof:placetype":"venue"
},
  "geometry": {"coordinates":[5.357688,43.335129],"type":"Point"}
}