{
  "type": "Feature",
  "properties": {
    "iso:country":"FR",
    "sg:address":"Avenue Antoine De St Exupery 76800 St Etienne Du Rouvray",
    "sg:classifiers":[
        {
            "category":"Professional",
            "subcategory":"Printing & Photocopies",
            "type":"Services"
        }
    ],
    "sg:phone":"+33 2 32 95 90 90",
    "sg:province":"Haute Normandie",
    "sg:tags":[
        "publishing"
    ],
    "wof:name":"Offset Numerique",
    "wof:placetype":"venue"
},
  "geometry": {"coordinates":[1.076245,49.393364],"type":"Point"}
}