{
  "type": "Feature",
  "properties": {
    "addr:full":"Le Chauchay 01230 Torcieu Rhone-Alpes 01230",
    "addr:postcode":"01230;01230",
    "addr:street":"Rhone-Alpes",
    "iso:country":"FR",
    "sg:address":"Le Chauchay 01230 Torcieu",
    "sg:orig_category":"Non-Classified Establishments",
    "sg:phone":"+33 4 74 37 42 66",
    "sg:postcode":"01230",
    "sg:province":"Rhone-Alpes",
    "wof:name":"Art De B\u00e2tir Et Restaurer S.a.r.l.",
    "wof:placetype":"venue"
},
  "geometry": {"coordinates":[5.404477,45.92915],"type":"Point"}
}