{
  "type": "Feature",
  "properties": {
    "addr:full":"26, Chemin aux Boeufs - ZAC les Bosquets, 95540 M\u00e9ry sur Oise Ile de France",
    "addr:housenumber":"26",
    "addr:postcode":"95540",
    "addr:street":"Chemin Aux Boeufs Zac Les Bosquets",
    "iso:country":"FR",
    "sg:address":"26, Chemin aux Boeufs - ZAC les Bosquets, 95540 M\u00e9ry sur Oise",
    "sg:orig_category":"Unclassifiable Establishments",
    "sg:phone":"+33 1 30 36 26 26",
    "sg:province":"Ile de France",
    "wof:name":"Peintures Funget S.a.",
    "wof:placetype":"venue"
},
  "geometry": {"coordinates":[2.185465,49.064209],"type":"Point"}
}