{
  "type": "Feature",
  "properties": {
    "addr:full":"94, Av. du Merlan, 13014 Marseille Poitou-Charentes",
    "addr:postcode":"13014",
    "addr:street":"94 Av. Du Merlan",
    "iso:country":"FR",
    "sg:address":"94, Av. du Merlan, 13014 Marseille",
    "sg:orig_category":"Unclassifiable Establishments",
    "sg:phone":"+33 4 91 98 20 08",
    "sg:province":"Poitou-Charentes",
    "wof:name":"Armand Fabre S.a.r.l.",
    "wof:placetype":"venue"
},
  "geometry": {"coordinates":[5.407642,43.340599],"type":"Point"}
}