{
  "type": "Feature",
  "properties": {
    "addr:full":"Quartier Gavy Cruet Rhone-Alpes 73800",
    "addr:postcode":"73800",
    "addr:street":"Rhone-Alpes",
    "iso:country":"FR",
    "sg:address":"Quartier Gavy",
    "sg:city":"Cruet",
    "sg:orig_category":"Unclassifiable Establishments",
    "sg:phone":"+33 4 79 84 28 52",
    "sg:postcode":"73800",
    "sg:province":"Rhone-Alpes",
    "wof:name":"Cave Coop\u00e9rative Des Vins De Cruet S.c.a.",
    "wof:placetype":"venue"
},
  "geometry": {"coordinates":[6.088821,45.519722],"type":"Point"}
}