{
  "type": "Feature",
  "properties": {
    "addr:full":"20 Rue Porte Cote 41000 Blois Blois Centre 41000",
    "addr:housenumber":"20",
    "addr:postcode":"41000;41000",
    "addr:street":"Rue Porte Cote",
    "iso:country":"FR",
    "sg:address":"20 Rue Porte Cote 41000 Blois",
    "sg:city":"Blois",
    "sg:classifiers":[
        {
            "category":"Manufacturing",
            "subcategory":"Printing",
            "type":"Manufacturing & Wholesale Goods"
        }
    ],
    "sg:phone":"+33 2 54 74 28 91",
    "sg:postcode":"41000",
    "sg:province":"Centre",
    "sg:tags":[
        "publishing"
    ],
    "wof:name":"France Loisirs (fl)",
    "wof:placetype":"venue"
},
  "geometry": {"coordinates":[1.317499,47.589317],"type":"Point"}
}