{
  "type": "Feature",
  "properties": {
    "addr:full":"Ch\u00e2teau Des Massiots 33190 Lamothe Landerron Barie Aquitaine 33190",
    "addr:housenumber":"barie",
    "addr:postcode":"33190;33190",
    "iso:country":"FR",
    "sg:address":"Ch\u00e2teau Des Massiots 33190 Lamothe Landerron",
    "sg:city":"Barie",
    "sg:classifiers":[
        {
            "category":"Professional",
            "subcategory":"Business Services",
            "type":"Services"
        }
    ],
    "sg:phone":"+33 5 56 61 71 31",
    "sg:postcode":"33190",
    "sg:province":"Aquitaine",
    "sg:tags":[
        "body",
        "advice"
    ],
    "wof:name":"Ass Etude Action Enfance Inadaptee",
    "wof:placetype":"venue"
},
  "geometry": {"coordinates":[-0.012771,44.516201],"type":"Point"}
}