{
  "type": "Feature",
  "properties": {
    "addr:full":"2, Av. du Manet, 78180 Montigny le Bretonneux Ile de France",
    "addr:postcode":"78180",
    "addr:street":"Av. Du Manet",
    "iso:country":"FR",
    "sg:address":"2, Av. du Manet, 78180 Montigny le Bretonneux",
    "sg:orig_category":"Unclassifiable Establishments",
    "sg:phone":"+33 1 30 57 66 00",
    "sg:province":"Ile de France",
    "wof:name":"Kontron M\u00e9dical S.a.s.",
    "wof:placetype":"venue"
},
  "geometry": {"coordinates":[2.02308,48.767792],"type":"Point"}
}