{
  "type": "Feature",
  "properties": {
    "addr:full":"B.P. 28, 76320 Saint Pierre l\u00e8s Elbeuf^^Zone Industrielle de l'Oison, 76320 Saint Pierre l\u00e8s Elbeuf Haute Normandie",
    "addr:postcode":"76320;76320",
    "addr:street":"B.P. 28;L'Oison;Haute Normandie",
    "iso:country":"FR",
    "sg:address":"B.P. 28, 76320 Saint Pierre l\u00e8s Elbeuf^^Zone Industrielle de l'Oison, 76320 Saint Pierre l\u00e8s Elbeuf",
    "sg:orig_category":"Non-Classified Establishments",
    "sg:phone":"+33 2 35 78 75 75",
    "sg:province":"Haute Normandie",
    "wof:name":"Gamma Service S.a.r.l.",
    "wof:placetype":"venue"
},
  "geometry": {"coordinates":[1.036363,49.289288],"type":"Point"}
}