{
  "type": "Feature",
  "properties": {
    "addr:full":"2 Rue Meyerbeer 75009 Paris Ile de France 75009",
    "addr:housenumber":"2",
    "addr:postcode":"75009;75009",
    "addr:street":"Rue Meyerbeer",
    "iso:country":"FR",
    "sg:address":"2 Rue Meyerbeer 75009 Paris",
    "sg:classifiers":[
        {
            "category":"Banks & Credit Unions",
            "subcategory":"Financial Services",
            "type":"Services"
        }
    ],
    "sg:phone":"+33 1 45 23 72 22",
    "sg:postcode":"75009",
    "sg:province":"Ile de France",
    "sg:tags":[
        "banking",
        "insurance",
        "institution",
        "finance"
    ],
    "wof:name":"Banca Commerciale Italiana France",
    "wof:placetype":"venue"
},
  "geometry": {"coordinates":[2.33389,48.871784],"type":"Point"}
}