{
  "type": "Feature",
  "properties": {
    "addr:full":"937, Rue de la Castelle - Parc Acherb\u00e9 Garosud, 34000 Montpellier Languedoc-Roussillon 34000",
    "addr:housenumber":"937",
    "addr:postcode":"34000;34000",
    "addr:street":"Rue De La Castelle Parc Acherbe\u0301 Garosud",
    "iso:country":"FR",
    "sg:address":"937, Rue de la Castelle - Parc Acherb\u00e9 Garosud, 34000 Montpellier",
    "sg:orig_category":"Non-Classified Establishments",
    "sg:phone":"+33 4 67 42 10 10",
    "sg:postcode":"34000",
    "sg:province":"Languedoc-Roussillon",
    "wof:name":"C.e.r.p. Rhin Rh\u00f4ne M\u00e9diterran\u00e9e S.a.",
    "wof:placetype":"venue"
},
  "geometry": {"coordinates":[3.869128,43.578979],"type":"Point"}
}