{
  "type": "Feature",
  "properties": {
    "addr:full":"23 place du Martroi; ORLEANS; 45044 cedex 1 Orl\u00e9ans Centre 45000",
    "addr:housenumber":"23;1",
    "addr:postcode":"45044 cedex;45000",
    "addr:street":"Place Du Martroi",
    "iso:country":"FR",
    "sg:address":"23 place du Martroi; ORLEANS; 45044 cedex 1",
    "sg:city":"Orl\u00e9ans",
    "sg:classifiers":[
        {
            "category":"Shopping",
            "subcategory":"Computers & Home Electronics",
            "type":"Retail Goods"
        }
    ],
    "sg:phone":"+33 2 38 77 77 77",
    "sg:postcode":"45000",
    "sg:province":"Centre",
    "sg:tags":[
        "chamber",
        "commerce"
    ],
    "wof:name":"Chambre De Commerce Et D'industrie Du Loiret",
    "wof:placetype":"venue"
},
  "geometry": {"coordinates":[1.903581,47.902061],"type":"Point"}
}