{
  "type": "Feature",
  "properties": {
    "iso:country":"FR",
    "sg:address":"Rte de Champeix",
    "sg:city":"Coudes",
    "sg:orig_category":"Non-Classified Establishments",
    "sg:phone":"+33 4 73 96 61 58",
    "sg:postcode":"63114",
    "sg:province":"Auvergne",
    "wof:name":"S.t.v. S.a.r.l.",
    "wof:placetype":"venue"
},
  "geometry": {"coordinates":[3.202452,45.610374],"type":"Point"}
}