{
  "type": "Feature",
  "properties": {
    "addr:full":"7, Rue du Gal, 84000 Avignon Picardie",
    "addr:housenumber":"7",
    "addr:postcode":"84000",
    "addr:street":"Rue Du Gal",
    "iso:country":"FR",
    "sg:address":"7, Rue du Gal, 84000 Avignon",
    "sg:orig_category":"Non-Classified Establishments",
    "sg:phone":"+33 4 32 76 73 10",
    "sg:province":"Picardie",
    "wof:name":"E.i.d. S.a.",
    "wof:placetype":"venue"
},
  "geometry": {"coordinates":[4.80924,43.95005],"type":"Point"}
}