{
  "type": "Feature",
  "properties": {
    "addr:full":"Rue Cl\u00e9ment Ader 91700 Fleury M\u00e9rogis Ile de France",
    "addr:postcode":"91700",
    "addr:street":"Rue Cle\u0301Ment Ader",
    "iso:country":"FR",
    "sg:address":"Rue Cl\u00e9ment Ader 91700 Fleury M\u00e9rogis",
    "sg:classifiers":[
        {
            "category":"Manufacturing",
            "subcategory":"Wood Products",
            "type":"Manufacturing & Wholesale Goods"
        }
    ],
    "sg:phone":"+33 1 69 46 56 00",
    "sg:province":"Ile de France",
    "sg:tags":[
        "professional",
        "furniture"
    ],
    "wof:name":"Informater",
    "wof:placetype":"venue"
},
  "geometry": {"coordinates":[2.363965,48.623692],"type":"Point"}
}