{
  "type": "Feature",
  "properties": {
    "addr:full":"31 Cours Mirabeau 13100 Aix En Provence Nord Pas-de-Calais",
    "addr:housenumber":"31",
    "addr:postcode":"13100",
    "addr:street":"Cours Mirabeau;En Provence Nord",
    "iso:country":"FR",
    "sg:address":"31 Cours Mirabeau 13100 Aix En Provence",
    "sg:classifiers":[
        {
            "category":"Professional",
            "subcategory":"Printing & Photocopies",
            "type":"Services"
        }
    ],
    "sg:phone":"+33 4 42 26 07 23",
    "sg:province":"Nord Pas-de-Calais",
    "sg:tags":[
        "publishing"
    ],
    "wof:name":"Librairie De Provence",
    "wof:placetype":"venue"
},
  "geometry": {"coordinates":[5.44882,43.526871],"type":"Point"}
}