{
  "type": "Feature",
  "properties": {
    "iso:country":"FR",
    "sg:address":"16 place du G\u00e9n\u00e9ral de Gaulle 59142 Villers Outreaux",
    "sg:classifiers":[
        {
            "category":"Banks & Credit Unions",
            "subcategory":"Bureau De Change",
            "type":"Services"
        }
    ],
    "sg:phone":"+33 3 27 82 01 97",
    "sg:postcode":"59142",
    "sg:province":"Nord Pas-de-Calais",
    "sg:tags":[
        "machine",
        "embroidery"
    ],
    "wof:name":"Alexandre Quennesson Sarl",
    "wof:placetype":"venue"
},
  "geometry": {"coordinates":[3.298669,50.032681],"type":"Point"}
}