{
  "type": "Feature",
  "properties": {
    "addr:full":"1 All\u00e9e Des Pins 66700 Argel\u00e8s Sur Mer Languedoc-Roussillon 66700",
    "addr:housenumber":"1",
    "addr:postcode":"66700;66700",
    "addr:street":"Alle\u0301E Des Pins;Mer",
    "iso:country":"FR",
    "sg:address":"1 All\u00e9e Des Pins 66700 Argel\u00e8s Sur Mer",
    "sg:classifiers":[
        {
            "category":"Travel",
            "subcategory":"Hotels & Motels",
            "type":"Entertainment"
        }
    ],
    "sg:phone":"+33 4 68 81 09 05",
    "sg:postcode":"66700",
    "sg:province":"Languedoc-Roussillon",
    "sg:tags":[
        "hotels",
        "business",
        "restaurant"
    ],
    "wof:name":"Hotel De La Plage Des Pins Sarl",
    "wof:placetype":"venue"
},
  "geometry": {"coordinates":[3.046633,42.555382],"type":"Point"}
}