{
  "type": "Feature",
  "properties": {
    "addr:full":"Rte Imp\u00e9riale 45420 Thou Thou Centre 45420",
    "addr:housenumber":"thou",
    "addr:postcode":"45420;45420",
    "addr:street":"Rte Impe\u0301Riale",
    "iso:country":"FR",
    "sg:address":"Rte Imp\u00e9riale 45420 Thou",
    "sg:city":"Thou",
    "sg:classifiers":[
        {
            "category":"Wholesale",
            "subcategory":"Vending Machines",
            "type":"Manufacturing & Wholesale Goods"
        }
    ],
    "sg:phone":"+33 2 38 31 55 76",
    "sg:postcode":"45420",
    "sg:province":"Centre",
    "sg:tags":[
        "-",
        "engineering",
        "metallic",
        "environment",
        "equipment",
        "finished",
        "machinery",
        "mechanical"
    ],
    "wof:name":"Thou Industrie Sarl",
    "wof:placetype":"venue"
},
  "geometry": {"coordinates":[2.908525,47.580235],"type":"Point"}
}