{
  "type": "Feature",
  "properties": {
    "iso:country":"FR",
    "sg:address":"Espace Commercial Fr\u00e9jorgues-Est",
    "sg:city":"Du Salaison 34130 Mauguio",
    "sg:classifiers":[
        {
            "category":"Professional",
            "subcategory":"Advertising",
            "type":"Services"
        }
    ],
    "sg:phone":"+33 4 67 20 01 69",
    "sg:postcode":"34130",
    "sg:province":"Languedoc-Roussillon",
    "sg:tags":[
        "information",
        "medium",
        "communication"
    ],
    "wof:name":"Viacom Outdoor Sa",
    "wof:placetype":"venue"
},
  "geometry": {"coordinates":[4.0079,43.617867],"type":"Point"}
}