{
  "type": "Feature",
  "properties": {
    "addr:full":"01310 Curtafond Rhone-Alpes 01310",
    "addr:postcode":"01310;01310",
    "addr:street":"Rhone-Alpes",
    "iso:country":"FR",
    "sg:address":"01310 Curtafond",
    "sg:orig_category":"Non-Classified Establishments",
    "sg:phone":"+33 4 74 30 40 31",
    "sg:postcode":"01310",
    "sg:province":"Rhone-Alpes",
    "wof:name":"Scappaticci S.a.",
    "wof:placetype":"venue"
},
  "geometry": {"coordinates":[5.089001,46.271317],"type":"Point"}
}