{
  "type": "Feature",
  "properties": {
    "iso:country":"FR",
    "sg:address":"755 Rue Tour De L Eveque; Nimes",
    "sg:classifiers":[
        {
            "category":"Travel",
            "subcategory":"Travel Agent",
            "type":"Entertainment"
        }
    ],
    "sg:province":"Languedoc-Roussillon",
    "wof:name":"Best Western L Orangerie",
    "wof:placetype":"venue"
},
  "geometry": {"coordinates":[4.368873,43.825027],"type":"Point"}
}