{
  "type": "Feature",
  "properties": {
    "addr:full":"1 rue l'Hermitte 59140 Dunkerque Nord Pas-de-Calais",
    "addr:housenumber":"1",
    "addr:postcode":"59140",
    "addr:street":"Rue L'Hermitte",
    "iso:country":"FR",
    "sg:address":"1 rue l'Hermitte 59140 Dunkerque",
    "sg:classifiers":[
        {
            "category":"Banks & Credit Unions",
            "subcategory":"Investment Brokerage",
            "type":"Services"
        }
    ],
    "sg:phone":"+33 3 28 66 63 80",
    "sg:province":"Nord Pas-de-Calais",
    "sg:tags":[
        "fork",
        "prime",
        "power",
        "system",
        "lift",
        "truck",
        "mover",
        "steering"
    ],
    "wof:name":"Le Pilotage Hauturier Coop.",
    "wof:placetype":"venue"
},
  "geometry": {"coordinates":[2.383177,51.036549],"type":"Point"}
}