{
  "type": "Feature",
  "properties": {
    "iso:country":"FR",
    "sg:address":"110 rue d'Isly 59000 Lille",
    "sg:classifiers":[
        {
            "category":"Professional",
            "subcategory":"Advertising",
            "type":"Services"
        }
    ],
    "sg:phone":"+33 3 20 09 50 09",
    "sg:postcode":"59000",
    "sg:province":"Nord Pas-de-Calais",
    "sg:tags":[
        "agency"
    ],
    "wof:name":"B - Publicit\u00e9 Sa",
    "wof:placetype":"venue"
},
  "geometry": {"coordinates":[3.038273,50.624081],"type":"Point"}
}