{
  "type": "Feature",
  "properties": {
    "addr:full":"16 Rue Dupetit Thouars 75003 Paris Ile de France 75003",
    "addr:housenumber":"16",
    "addr:postcode":"75003;75003",
    "addr:street":"Rue Dupetit Thouars",
    "iso:country":"FR",
    "sg:address":"16 Rue Dupetit Thouars 75003 Paris",
    "sg:classifiers":[
        {
            "category":"Manufacturing",
            "subcategory":"Jewelry",
            "type":"Manufacturing & Wholesale Goods"
        }
    ],
    "sg:phone":"+33 1 48 87 88 85",
    "sg:postcode":"75003",
    "sg:province":"Ile de France",
    "sg:tags":[
        "product",
        "miscellaneous",
        "jewellery"
    ],
    "wof:name":"Paul Platroz Joaillier",
    "wof:placetype":"venue"
},
  "geometry": {"coordinates":[2.361576,48.865559],"type":"Point"}
}