{
  "type": "Feature",
  "properties": {
    "addr:full":"All\u00e9e Louis Renault Vend\u00f4me Centre 41100",
    "addr:postcode":"41100",
    "addr:street":"Alle\u0301E Louis Renault",
    "iso:country":"FR",
    "sg:address":"All\u00e9e Louis Renault",
    "sg:city":"Vend\u00f4me",
    "sg:orig_category":"Non-Classified Establishments",
    "sg:phone":"+33 2 54 89 08 06",
    "sg:postcode":"41100",
    "sg:province":"Centre",
    "wof:name":"V\u00e9g\u00e8terie Compostage S.a.r.l.",
    "wof:placetype":"venue"
},
  "geometry": {"coordinates":[1.072885,47.775894],"type":"Point"}
}