{
  "type": "Feature",
  "properties": {
    "addr:full":"B.P. 63, 84302 Cavaillon C\u00e9dex^^ZAC Cabedan, 84300 Cavaillon Languedoc-Roussillon",
    "addr:postcode":"84302;84300",
    "addr:street":"B.P. 63;Cabedan",
    "iso:country":"FR",
    "sg:address":"B.P. 63, 84302 Cavaillon C\u00e9dex^^ZAC Cabedan, 84300 Cavaillon",
    "sg:orig_category":"Non-Classified Establishments",
    "sg:phone":"+33 4 90 71 24 02",
    "sg:province":"Languedoc-Roussillon",
    "wof:name":"A.b.x. Logistics S.a.",
    "wof:placetype":"venue"
},
  "geometry": {"coordinates":[5.039415,43.837685],"type":"Point"}
}