{
  "type": "Feature",
  "properties": {
    "addr:full":"B.P. 63, 64130 Maul\u00e9on Licharre^^12, Rue Jean Baptiste Heugas, 64130 Maul\u00e9on Licharre Ainharp Aquitaine 64130",
    "addr:postcode":"64130;64130;64130",
    "addr:street":"B.P. 63;Rue Jean Baptiste Heugas",
    "iso:country":"FR",
    "sg:address":"B.P. 63, 64130 Maul\u00e9on Licharre^^12, Rue Jean Baptiste Heugas, 64130 Maul\u00e9on Licharre",
    "sg:city":"Ainharp",
    "sg:orig_category":"Non-Classified Establishments",
    "sg:phone":"+33 5 59 28 49 10",
    "sg:postcode":"64130",
    "sg:province":"Aquitaine",
    "wof:name":"Banque Populaire Du Sud Ouest",
    "wof:placetype":"venue"
},
  "geometry": {"coordinates":[-0.933393,43.148788],"type":"Point"}
}