{
  "type": "Feature",
  "properties": {
    "iso:country":"FR",
    "sg:address":"Z A Les Paquelins 71210 St Laurent D Andenay",
    "sg:city":"Torcy",
    "sg:classifiers":[
        {
            "category":"Shopping",
            "type":"Retail Goods"
        }
    ],
    "sg:phone":"+33 3 85 78 05 40",
    "sg:postcode":"71210",
    "sg:province":"Bourgogne",
    "sg:tags":[
        "metallurgy",
        "finished",
        "-",
        "metalworking",
        "metallic"
    ],
    "wof:name":"Modelage Jean Louis Fauchon",
    "wof:placetype":"venue"
},
  "geometry": {"coordinates":[4.463261,46.713284],"type":"Point"}
}