{
  "type": "Feature",
  "properties": {
    "iso:country":"FR",
    "sg:address":"rue du Marvay 74300 Thyez",
    "sg:classifiers":[
        {
            "category":"Wholesale",
            "subcategory":"Auto Parts",
            "type":"Manufacturing & Wholesale Goods"
        }
    ],
    "sg:phone":"+33 4 50 34 05 34",
    "sg:postcode":"74300",
    "sg:province":"Rhone-Alpes",
    "sg:tags":[
        "machine",
        "screw"
    ],
    "wof:name":"D\u00e9colletage Serge Berthet Sas",
    "wof:placetype":"venue"
},
  "geometry": {"coordinates":[6.527462,46.083275],"type":"Point"}
}