{
  "type": "Feature",
  "properties": {
    "iso:country":"FR",
    "sg:address":"51, Rte Nationale, 59360 Catillon sur Sambre",
    "sg:orig_category":"Non-Classified Establishments",
    "sg:phone":"+33 3 27 77 60 04",
    "sg:province":"Nord Pas-de-Calais",
    "wof:name":"Fillion S.a.r.l.",
    "wof:placetype":"venue"
},
  "geometry": {"coordinates":[3.64323,50.075466],"type":"Point"}
}