{
  "type": "Feature",
  "properties": {
    "iso:country":"FR",
    "sg:address":"B.P. 262, 47007 Agen C\u00e9dex^^1456, Av. de Colmar, 47000 Agen",
    "sg:city":"Agen",
    "sg:orig_category":"Non-Classified Establishments",
    "sg:phone":"+33 5 53 77 78 88",
    "sg:postcode":"47000",
    "sg:province":"Aquitaine",
    "wof:name":"Sotraser",
    "wof:placetype":"venue"
},
  "geometry": {"coordinates":[0.62061,44.205109],"type":"Point"}
}