{
  "type": "Feature",
  "properties": {
    "iso:country":"FR",
    "sg:address":"6-8 Av De Verdun BP 57 92253 La Garenne Colombes Cedex",
    "sg:classifiers":[
        {
            "category":"Professional",
            "subcategory":"Business Services",
            "type":"Services"
        }
    ],
    "sg:phone":"+33 1 41 19 80 00",
    "sg:province":"Aquitaine",
    "sg:tags":[
        "information",
        "advice",
        "technology",
        "software"
    ],
    "wof:name":"Axialog",
    "wof:placetype":"venue"
},
  "geometry": {"coordinates":[2.24592,48.906719],"type":"Point"}
}