{
  "type": "Feature",
  "properties": {
    "iso:country":"FR",
    "sg:address":"20 boulevard Gallieni 92130 Issy les Moulineaux",
    "sg:orig_category":"Ophthalmological Instruments",
    "sg:phone":"+33 1 40 93 07 77",
    "sg:province":"Ile de France",
    "wof:name":"France Chirurgie Instrumentation S.a.",
    "wof:placetype":"venue"
},
  "geometry": {"coordinates":[2.266888,48.832775],"type":"Point"}
}