{
  "type": "Feature",
  "properties": {
    "addr:full":"18 Carnot 71410 Sanvignes les Mines Bourgogne 71410",
    "addr:housenumber":"18",
    "addr:postcode":"71410;71410",
    "addr:street":"Carnot;Sanvignes Les;Bourgogne",
    "iso:country":"FR",
    "sg:address":"18",
    "sg:city":"Carnot 71410 Sanvignes les Mines",
    "sg:classifiers":[
        {
            "category":"Manufacturing",
            "subcategory":"Leather Goods",
            "type":"Manufacturing & Wholesale Goods"
        }
    ],
    "sg:phone":"+33 3 85 67 29 95",
    "sg:postcode":"71410",
    "sg:province":"Bourgogne",
    "sg:tags":[
        "shoe"
    ],
    "wof:name":"Tsd (tapisserie Sellerie Dieudonne)",
    "wof:placetype":"venue"
},
  "geometry": {"coordinates":[4.2859,46.641731],"type":"Point"}
}