{
  "type": "Feature",
  "properties": {
    "addr:full":"54, Quai du Priourat, 33500 Libourne Libourne Aquitaine 33500",
    "addr:housenumber":"54",
    "addr:postcode":"33500;33500",
    "addr:street":"Quai Du Priourat",
    "iso:country":"FR",
    "sg:address":"54, Quai du Priourat, 33500 Libourne",
    "sg:city":"Libourne",
    "sg:orig_category":"Unclassifiable Establishments",
    "sg:phone":"+33 5 57 51 78 96",
    "sg:postcode":"33500",
    "sg:province":"Aquitaine",
    "wof:name":"Etablissements Jean-pierre Moueix S.a.",
    "wof:placetype":"venue"
},
  "geometry": {"coordinates":[-0.248397,44.908699],"type":"Point"}
}