{
  "type": "Feature",
  "properties": {
    "addr:full":"4, Rue Chabaud, 51100 Reims Champagne",
    "addr:housenumber":"4",
    "addr:postcode":"51100",
    "addr:street":"Rue Chabaud",
    "iso:country":"FR",
    "sg:address":"4, Rue Chabaud, 51100 Reims",
    "sg:orig_category":"Unclassifiable Establishments",
    "sg:phone":"+33 3 26 50 31 10",
    "sg:province":"Champagne",
    "wof:name":"Sylvain Lefebvre S.a.",
    "wof:placetype":"venue"
},
  "geometry": {"coordinates":[4.025305,49.251572],"type":"Point"}
}