{
  "type": "Feature",
  "properties": {
    "addr:full":"1 R Docteur Henri Dalmon BP 215 La Rochelle Cedex Haute Normandie 17011",
    "addr:housenumber":"1;215",
    "addr:postcode":"17011",
    "addr:street":"R Docteur Henri Dalmon Bp",
    "iso:country":"FR",
    "sg:address":"1 R Docteur Henri Dalmon BP 215",
    "sg:city":"La Rochelle Cedex",
    "sg:classifiers":[
        {
            "category":"Banks & Credit Unions",
            "subcategory":"Financial Services",
            "type":"Services"
        }
    ],
    "sg:phone":"+33 5 46 42 24 34",
    "sg:postcode":"17011",
    "sg:province":"Haute Normandie",
    "sg:tags":[
        "banking",
        "finance",
        "insurance"
    ],
    "wof:name":"Charente Maritime Expertises Cme",
    "wof:placetype":"venue"
},
  "geometry": {"coordinates":[-1.171513,46.163342],"type":"Point"}
}