{
  "type": "Feature",
  "properties": {
    "addr:full":"Av. de Toureilles Montr\u00e9jeau Midi Pyr\u00e9n\u00e9es 31210",
    "addr:postcode":"31210",
    "addr:street":"Av. De Toureilles;Midi",
    "iso:country":"FR",
    "sg:address":"Av. de Toureilles",
    "sg:city":"Montr\u00e9jeau",
    "sg:orig_category":"Non-Classified Establishments",
    "sg:phone":"+33 5 61 95 81 44",
    "sg:postcode":"31210",
    "sg:province":"Midi Pyr\u00e9n\u00e9es",
    "wof:name":"Entreprise Daval S.a.",
    "wof:placetype":"venue"
},
  "geometry": {"coordinates":[0.561658,43.089001],"type":"Point"}
}