{
  "type": "Feature",
  "properties": {
    "addr:full":"rue des Abattoires 50200 ST PIERRE DE COUTANCES Coutances Basse Normandie 50200",
    "addr:postcode":"50200;50200",
    "addr:street":"Rue Des Abattoires",
    "iso:country":"FR",
    "sg:address":"rue des Abattoires 50200 ST PIERRE DE COUTANCES",
    "sg:city":"Coutances",
    "sg:classifiers":[
        {
            "category":"Food & Beverages",
            "subcategory":"Meat & Fish",
            "type":"Retail Goods"
        }
    ],
    "sg:phone":"+33 2 33 76 33 33",
    "sg:postcode":"50200",
    "sg:province":"Basse Normandie",
    "sg:tags":[
        "product"
    ],
    "wof:name":"Sovico Sas",
    "wof:placetype":"venue"
},
  "geometry": {"coordinates":[-1.441718,49.039745],"type":"Point"}
}