{
  "type": "Feature",
  "properties": {
    "iso:country":"FR",
    "sg:address":"B.P. 55, 70500 Jussey^^Av de Verdun, 70500 Jussey",
    "sg:orig_category":"Non-Classified Establishments",
    "sg:phone":"+33 3 84 68 11 11",
    "sg:province":"Franche Comt\u00e9",
    "wof:name":"Vernier",
    "wof:placetype":"venue"
},
  "geometry": {"coordinates":[5.902907,47.823547],"type":"Point"}
}