{
  "type": "Feature",
  "properties": {
    "iso:country":"FR",
    "sg:address":"8 rue Madame 75006 Paris",
    "sg:classifiers":[
        {
            "category":"Shopping",
            "subcategory":"Books",
            "type":"Retail Goods"
        }
    ],
    "sg:phone":"+33 1 45 44 64 02",
    "sg:postcode":"75006",
    "sg:province":"Ile de France",
    "wof:name":"Mediaspaul Editions Sa",
    "wof:placetype":"venue"
},
  "geometry": {"coordinates":[2.331719,48.851761],"type":"Point"}
}