{
  "type": "Feature",
  "properties": {
    "iso:country":"FR",
    "sg:address":"203, Rue Jean Morin - ZI des Dragiez, 74800 La Roche sur Foron",
    "sg:orig_category":"Unclassifiable Establishments",
    "sg:phone":"+33 4 50 25 94 31",
    "sg:postcode":"74800",
    "sg:province":"Rhone-Alpes",
    "wof:name":"Boivin S.a.",
    "wof:placetype":"venue"
},
  "geometry": {"coordinates":[6.343543,46.066856],"type":"Point"}
}