{
  "type": "Feature",
  "properties": {
    "addr:full":"Les Vernays 73540 La Bathie Rhone-Alpes 73540",
    "addr:postcode":"73540;73540",
    "addr:street":"Bathie Rhone-Alpes",
    "iso:country":"FR",
    "sg:address":"Les Vernays 73540 La Bathie",
    "sg:classifiers":[
        {
            "category":"Food & Beverages",
            "subcategory":"Dairy",
            "type":"Retail Goods"
        }
    ],
    "sg:phone":"+33 4 79 31 01 33",
    "sg:postcode":"73540",
    "sg:province":"Rhone-Alpes",
    "sg:tags":[
        "product",
        "related"
    ],
    "wof:name":"Les Fromageries De Tarentaise",
    "wof:placetype":"venue"
},
  "geometry": {"coordinates":[6.449745,45.626606],"type":"Point"}
}