{
  "type": "Feature",
  "properties": {
    "addr:full":"RN 17 Le Thillay Ile de France 95500",
    "addr:housenumber":"17",
    "addr:postcode":"95500",
    "addr:street":"Rn",
    "iso:country":"FR",
    "sg:address":"RN 17",
    "sg:city":"Le Thillay",
    "sg:orig_category":"Unclassifiable Establishments",
    "sg:phone":"+33 1 39 92 80 07",
    "sg:postcode":"95500",
    "sg:province":"Ile de France",
    "wof:name":"S.u.m.i. S.a.r.l. - Soci\u00e9t\u00e9 Usinage M\u00e9canique Industrielle",
    "wof:placetype":"venue"
},
  "geometry": {"coordinates":[2.449633,48.986462],"type":"Point"}
}