{
  "type": "Feature",
  "properties": {
    "addr:full":"62 Rue Du Marechal Foch 59100 Roubaix Nord Pas-de-Calais 59100",
    "addr:housenumber":"62",
    "addr:postcode":"59100;59100",
    "addr:street":"Rue Du Marechal Foch",
    "iso:country":"FR",
    "sg:address":"62 Rue Du Marechal Foch 59100 Roubaix",
    "sg:classifiers":[
        {
            "category":"Manufacturing",
            "subcategory":"Building Materials",
            "type":"Manufacturing & Wholesale Goods"
        }
    ],
    "sg:phone":"+33 3 20 99 96 15",
    "sg:postcode":"59100",
    "sg:province":"Nord Pas-de-Calais",
    "sg:tags":[
        "-",
        "machine",
        "raw",
        "engineering",
        "paper",
        "mechanical",
        "cardboard"
    ],
    "wof:name":"Faconnage Roland Van Meenen",
    "wof:placetype":"venue"
},
  "geometry": {"coordinates":[3.174015,50.688328],"type":"Point"}
}