{
  "type": "Feature",
  "properties": {
    "iso:country":"FR",
    "sg:address":"4, Rue Paul langevin - ZI du Hellu, 59260 Lezennes",
    "sg:orig_category":"Unclassifiable Establishments",
    "sg:phone":"+33 891 70 03 50",
    "sg:province":"Nord Pas-de-Calais",
    "wof:name":"Ricoh France Nord Est S.a.",
    "wof:placetype":"venue"
},
  "geometry": {"coordinates":[3.11705,50.614567],"type":"Point"}
}