{
  "type": "Feature",
  "properties": {
    "iso:country":"FR",
    "sg:address":"Chem De Butez Rn 17 62580 Vimy",
    "sg:classifiers":[
        {
            "category":"Banks & Credit Unions",
            "subcategory":"Investment Brokerage",
            "type":"Services"
        }
    ],
    "sg:phone":"+33 3 21 15 12 12",
    "sg:province":"Nord Pas-de-Calais",
    "sg:tags":[
        "-",
        "transport",
        "related"
    ],
    "wof:name":"Base De Vimy",
    "wof:placetype":"venue"
},
  "geometry": {"coordinates":[2.813412,50.371101],"type":"Point"}
}