{
  "type": "Feature",
  "properties": {
    "addr:full":"15, Rue Abbaye, 86360 Montamise Poitou-Charentes 86360",
    "addr:housenumber":"15",
    "addr:postcode":"86360;86360",
    "addr:street":"Rue Abbaye;Montamise",
    "iso:country":"FR",
    "sg:address":"15, Rue Abbaye, 86360 Montamise",
    "sg:orig_category":"Non-Classified Establishments",
    "sg:phone":"+33 5 49 52 83 50",
    "sg:postcode":"86360",
    "sg:province":"Poitou-Charentes",
    "wof:name":"Audoin D\u00e9colletage",
    "wof:placetype":"venue"
},
  "geometry": {"coordinates":[0.397804,46.63879],"type":"Point"}
}