{
  "type": "Feature",
  "properties": {
    "iso:country":"FR",
    "sg:address":"86035 Poitiers C\u00e9dex^^1, Rue des Transporteurs - ZI R\u00e9publique, 86000 Poitiers",
    "sg:orig_category":"Non-Classified Establishments",
    "sg:phone":"+33 5 49 41 49 49",
    "sg:postcode":"86000",
    "sg:province":"Poitou-Charentes",
    "wof:name":"C.o.f.a.q. S.a. - Comptoir Fran\u00e7ais De Quincaillerie",
    "wof:placetype":"venue"
},
  "geometry": {"coordinates":[0.34169,46.58057],"type":"Point"}
}