{
  "type": "Feature",
  "properties": {
    "addr:full":"B.P. 291, 31677 Lab\u00e8ge C\u00e9dex^^Rue Garance - High Tech Buro B, 31320 Lab\u00e8ge Midi Pyr\u00e9n\u00e9es",
    "addr:housenumber":"b.p. 291",
    "addr:postcode":"31677;31320",
    "addr:street":"High",
    "iso:country":"FR",
    "sg:address":"B.P. 291, 31677 Lab\u00e8ge C\u00e9dex^^Rue Garance - High Tech Buro B, 31320 Lab\u00e8ge",
    "sg:orig_category":"Non-Classified Establishments",
    "sg:phone":"+33 5 61 00 20 15",
    "sg:province":"Midi Pyr\u00e9n\u00e9es",
    "wof:name":"Innetis",
    "wof:placetype":"venue"
},
  "geometry": {"coordinates":[1.452547,43.482239],"type":"Point"}
}