{
  "type": "Feature",
  "properties": {
    "addr:full":"B.P. CE 18/31, 91018 Evry C\u00e9dex^^10, All\u00e9e du Cantal - ZI la Petite Montagne Sud, 91000 Evry Ile de France",
    "addr:housenumber":"18 / 31",
    "addr:postcode":"91018;la;91000",
    "addr:street":"Alle\u0301E Du Cantal Zi;Petite Montagne Sud",
    "iso:country":"FR",
    "sg:address":"B.P. CE 18/31, 91018 Evry C\u00e9dex^^10, All\u00e9e du Cantal - ZI la Petite Montagne Sud, 91000 Evry",
    "sg:orig_category":"Non-Classified Establishments",
    "sg:phone":"+33 1 69 11 36 36",
    "sg:province":"Ile de France",
    "wof:name":"Rofin Baasel France S.a.",
    "wof:placetype":"venue"
},
  "geometry": {"coordinates":[2.4293,48.624664],"type":"Point"}
}