{
  "type": "Feature",
  "properties": {
    "iso:country":"FR",
    "sg:address":"Rte D'Auxerre 89800 Chablis",
    "sg:city":"Chablis",
    "sg:classifiers":[
        {
            "category":"Food Court",
            "type":"Food & Drink"
        }
    ],
    "sg:phone":"+33 3 86 42 88 00",
    "sg:postcode":"89800",
    "sg:province":"Bourgogne",
    "sg:tags":[
        "product",
        "related"
    ],
    "wof:name":"Moreau Et Fils Sa",
    "wof:placetype":"venue"
},
  "geometry": {"coordinates":[3.78814,47.816589],"type":"Point"}
}