{
  "type": "Feature",
  "properties": {
    "addr:full":"B.P. 105, 88804 Vittel C\u00e9dex^^130, Rue de la Scierie, 88800 Vittel Lorraine 88800",
    "addr:housenumber":"b.p. 105",
    "addr:postcode":"88804;88800;88800",
    "addr:street":"Rue De La Scierie",
    "iso:country":"FR",
    "sg:address":"B.P. 105, 88804 Vittel C\u00e9dex^^130, Rue de la Scierie, 88800 Vittel",
    "sg:orig_category":"Non-Classified Establishments",
    "sg:phone":"+33 3 29 08 07 45",
    "sg:postcode":"88800",
    "sg:province":"Lorraine",
    "wof:name":"Caremat S.a.s.",
    "wof:placetype":"venue"
},
  "geometry": {"coordinates":[5.944675,48.202614],"type":"Point"}
}