{
  "type": "Feature",
  "properties": {
    "iso:country":"FR",
    "sg:address":"40, Bd Pochet Lagaye, 63000 Clermont Ferrand",
    "sg:city":"Clermont-Ferrand",
    "sg:orig_category":"Unclassifiable Establishments",
    "sg:phone":"+33 4 73 15 11 30",
    "sg:postcode":"63000",
    "sg:province":"Auvergne",
    "wof:name":"Morlat Barth\u00e9l\u00e9my Et Associ\u00e9s S.a.",
    "wof:placetype":"venue"
},
  "geometry": {"coordinates":[3.10245,45.764641],"type":"Point"}
}