{
  "type": "Feature",
  "properties": {
    "addr:full":"24 Rue Max Tourailles 24120 Terrasson Lavilledieu Beauregard-de-Terrasson Aquitaine 24120",
    "addr:housenumber":"24",
    "addr:postcode":"24120;24120",
    "addr:street":"Rue Max",
    "iso:country":"FR",
    "sg:address":"24 Rue Max Tourailles 24120 Terrasson Lavilledieu",
    "sg:city":"Beauregard-de-Terrasson",
    "sg:classifiers":[
        {
            "category":"Manufacturing",
            "subcategory":"Rubber & Plastics",
            "type":"Manufacturing & Wholesale Goods"
        }
    ],
    "sg:phone":"+33 5 53 51 48 00",
    "sg:postcode":"24120",
    "sg:province":"Aquitaine",
    "wof:name":"Socat Sa",
    "wof:placetype":"venue"
},
  "geometry": {"coordinates":[1.297598,45.134735],"type":"Point"}
}