{
  "type": "Feature",
  "properties": {
    "addr:full":"24, Rue Neuve, 51450 B\u00e9theny Champagne",
    "addr:housenumber":"24",
    "addr:postcode":"51450",
    "addr:street":"Rue Neuve",
    "iso:country":"FR",
    "sg:address":"24, Rue Neuve, 51450 B\u00e9theny",
    "sg:orig_category":"Unclassifiable Establishments",
    "sg:phone":"+33 3 26 02 04 02",
    "sg:province":"Champagne",
    "wof:name":"V.m. Nettoyage S.a.",
    "wof:placetype":"venue"
},
  "geometry": {"coordinates":[4.056193,49.286121],"type":"Point"}
}