{
  "type": "Feature",
  "properties": {
    "addr:full":"B.P. 1005, 87051 Limoges C\u00e9dex^^27, Av. Albert Thomas, 87100 Limoges Limousin 87100",
    "addr:postcode":"87051;87100;87100",
    "addr:street":"B.P. 1005;Av. Albert Thomas",
    "iso:country":"FR",
    "sg:address":"B.P. 1005, 87051 Limoges C\u00e9dex^^27, Av. Albert Thomas, 87100 Limoges",
    "sg:orig_category":"Non-Classified Establishments",
    "sg:phone":"+33 5 55 10 55 50",
    "sg:postcode":"87100",
    "sg:province":"Limousin",
    "wof:name":"Bernardaud S.a.",
    "wof:placetype":"venue"
},
  "geometry": {"coordinates":[1.193255,45.843124],"type":"Point"}
}