{
  "type": "Feature",
  "properties": {
    "addr:full":"20, Rue Saint Laurent, 75010 Paris Ile de France",
    "addr:housenumber":"20",
    "addr:postcode":"75010",
    "addr:street":"Rue Saint Laurent",
    "iso:country":"FR",
    "sg:address":"20, Rue Saint Laurent, 75010 Paris",
    "sg:orig_category":"Non-Classified Establishments",
    "sg:phone":"+33 1 40 35 72 18",
    "sg:province":"Ile de France",
    "wof:name":"Imprimerie Lacroix Fr\u00e8res S.a.r.l.",
    "wof:placetype":"venue"
},
  "geometry": {"coordinates":[2.3572,48.875683],"type":"Point"}
}