{
  "type": "Feature",
  "properties": {
    "iso:country":"FR",
    "sg:address":"14 Du Port L Auge 95430 Butry Sur Oise",
    "sg:classifiers":[
        {
            "category":"Farming",
            "subcategory":"Farm",
            "type":"Manufacturing & Wholesale Goods"
        }
    ],
    "sg:phone":"+33 1 34 69 68 04",
    "sg:postcode":"95430",
    "sg:province":"Ile de France",
    "sg:tags":[
        "horticulture",
        "agriculture",
        "livestock"
    ],
    "wof:name":"Etablissement Horticole Roger Bouet",
    "wof:placetype":"venue"
},
  "geometry": {"coordinates":[-123.053108,38.459251],"type":"Point"}
}