{
  "type": "Feature",
  "properties": {
    "addr:full":"B.P. 43, 01152 Lagnieu C\u00e9dex^^Zone Industrielle, 01150 Saint Sorlin en Bugey Rhone-Alpes 01150",
    "addr:postcode":"01152;industrielle 01150 saint;01150",
    "addr:street":"B.P. 43;Sorlin En;Rhone-Alpes",
    "iso:country":"FR",
    "sg:address":"B.P. 43, 01152 Lagnieu C\u00e9dex^^Zone Industrielle, 01150 Saint Sorlin en Bugey",
    "sg:orig_category":"Non-Classified Establishments",
    "sg:phone":"+33 4 74 34 40 40",
    "sg:postcode":"01150",
    "sg:province":"Rhone-Alpes",
    "wof:name":"C.m.s.s.e. S.a.s. - Comptoirs Modernes Supermarch\u00e9s Sud Est",
    "wof:placetype":"venue"
},
  "geometry": {"coordinates":[5.3382,45.88237],"type":"Point"}
}