{
  "type": "Feature",
  "properties": {
    "iso:country":"FR",
    "sg:address":"Zone Industrielle 3",
    "sg:city":"Golbey",
    "sg:orig_category":"Unclassifiable Establishments",
    "sg:phone":"+33 3 29 31 16 87",
    "sg:postcode":"88190",
    "sg:province":"Lorraine",
    "wof:name":"Nouveaux Docks S.a.",
    "wof:placetype":"venue"
},
  "geometry": {"coordinates":[6.438855,48.197556],"type":"Point"}
}