{
  "type": "Feature",
  "properties": {
    "iso:country":"FR",
    "sg:address":"22, Rue du Magny, 70200 Lure",
    "sg:orig_category":"Non-Classified Establishments",
    "sg:phone":"+33 3 84 30 02 79",
    "sg:province":"Franche Comt\u00e9",
    "wof:name":"Malat S.a.r.l.",
    "wof:placetype":"venue"
},
  "geometry": {"coordinates":[6.494442,47.678196],"type":"Point"}
}