{
  "type": "Feature",
  "properties": {
    "addr:full":"3 Rue Paul Montrochet 69002 Lyon Rhone-Alpes 69002",
    "addr:housenumber":"3",
    "addr:postcode":"69002;69002",
    "addr:street":"Rue Paul Montrochet",
    "iso:country":"FR",
    "sg:address":"3 Rue Paul Montrochet 69002 Lyon",
    "sg:classifiers":[
        {
            "category":"Building & Trades",
            "subcategory":"Construction",
            "type":"Services"
        }
    ],
    "sg:phone":"+33 4 72 41 11 72",
    "sg:postcode":"69002",
    "sg:province":"Rhone-Alpes",
    "sg:tags":[
        "work",
        "public"
    ],
    "wof:name":"Colas Rhone-alpes Sa",
    "wof:placetype":"venue"
},
  "geometry": {"coordinates":[4.817444,45.740219],"type":"Point"}
}