{
  "type": "Feature",
  "properties": {
    "iso:country":"FR",
    "sg:address":"B.P. 168, 81205 Mazamet C\u00e9dex^^4, Rue de la Ferronnerie - ZI de Bonnecombe, 81200 Mazamet",
    "sg:orig_category":"Non-Classified Establishments",
    "sg:phone":"+33 5 63 61 00 06",
    "sg:postcode":"81200",
    "sg:province":"Midi Pyr\u00e9n\u00e9es",
    "wof:name":"Averpeaux S.a.r.l.",
    "wof:placetype":"venue"
},
  "geometry": {"coordinates":[2.36605,43.460224],"type":"Point"}
}