{
  "type": "Feature",
  "properties": {
    "iso:country":"FR",
    "sg:address":"5, All\u00e9e Bernard de Palissy - ZA les Prunus, 69780 Mions",
    "sg:orig_category":"Non-Classified Establishments",
    "sg:phone":"+33 4 78 21 10 49",
    "sg:postcode":"69780",
    "sg:province":"Rhone-Alpes",
    "wof:name":"T.s.m.g. S.a.r.l.",
    "wof:placetype":"venue"
},
  "geometry": {"coordinates":[4.954582,45.662968],"type":"Point"}
}