{
  "type": "Feature",
  "properties": {
    "addr:full":"40, Rue Pierre Chantelauze, 79000 Niort Poitou-Charentes 79000",
    "addr:housenumber":"40",
    "addr:postcode":"79000;79000",
    "addr:street":"Rue Pierre Chantelauze",
    "iso:country":"FR",
    "sg:address":"40, Rue Pierre Chantelauze, 79000 Niort",
    "sg:orig_category":"Unclassifiable Establishments",
    "sg:phone":"+33 5 49 77 16 16",
    "sg:postcode":"79000",
    "sg:province":"Poitou-Charentes",
    "wof:name":"A.f.p.a.",
    "wof:placetype":"venue"
},
  "geometry": {"coordinates":[-0.440696,46.312134],"type":"Point"}
}