{
  "type": "Feature",
  "properties": {
    "iso:country":"FR",
    "sg:address":"Rue du Paradis",
    "sg:city":"Ormes",
    "sg:orig_category":"Unclassifiable Establishments",
    "sg:phone":"+33 2 38 70 89 95",
    "sg:postcode":"45140",
    "sg:province":"Centre",
    "wof:name":"Assistrans S.a.",
    "wof:placetype":"venue"
},
  "geometry": {"coordinates":[1.823785,47.941002],"type":"Point"}
}