{
  "type": "Feature",
  "properties": {
    "addr:full":"B.P. 4, 67700 Monswiller^^8, Rue du Baron Chouard, 67700 Monswiller Monswiller Alsace 67700",
    "addr:housenumber":"4",
    "addr:postcode":"67700;67700;67700",
    "addr:street":"B.P.;Rue Du Baron Chouard;Monswiller",
    "iso:country":"FR",
    "sg:address":"B.P. 4, 67700 Monswiller^^8, Rue du Baron Chouard, 67700 Monswiller",
    "sg:city":"Monswiller",
    "sg:orig_category":"Non-Classified Establishments",
    "sg:phone":"+33 3 88 71 24 70",
    "sg:postcode":"67700",
    "sg:province":"Alsace",
    "wof:name":"Halbwachs Paul S.a.",
    "wof:placetype":"venue"
},
  "geometry": {"coordinates":[7.366026,48.739471],"type":"Point"}
}