{
  "type": "Feature",
  "properties": {
    "addr:full":"B.P. 7, 92301 Levallois Perret C\u00e9dex^^7/9, Rue Paul Vaillant Couturier, 92300 Levallois Perret Ile de France",
    "addr:housenumber":"7;9",
    "addr:postcode":"92301;92300;ile",
    "addr:street":"B.P.;Rue Paul Vaillant Couturier",
    "iso:country":"FR",
    "sg:address":"B.P. 7, 92301 Levallois Perret C\u00e9dex^^7/9, Rue Paul Vaillant Couturier, 92300 Levallois Perret",
    "sg:orig_category":"Non-Classified Establishments",
    "sg:phone":"+33 1 40 89 68 00",
    "sg:province":"Ile de France",
    "wof:name":"Umanis S.a.",
    "wof:placetype":"venue"
},
  "geometry": {"coordinates":[2.28505,48.890995],"type":"Point"}
}