{
  "type": "Feature",
  "properties": {
    "iso:country":"FR",
    "sg:address":"34, Rue du Manoir de Servign\u00e9, 35000 Rennes",
    "sg:city":"Rennes",
    "sg:orig_category":"Unclassifiable Establishments",
    "sg:phone":"+33 2 99 14 51 00",
    "sg:postcode":"35000",
    "sg:province":"Bretagne",
    "wof:name":"A.f.m. Recyclage",
    "wof:placetype":"venue"
},
  "geometry": {"coordinates":[-1.734711,48.102032],"type":"Point"}
}