{
  "type": "Feature",
  "properties": {
    "iso:country":"FR",
    "sg:address":"28/30 rue Edouard Vaillant 92300 Levallois Perret",
    "sg:classifiers":[
        {
            "category":"Utilities",
            "subcategory":"Water",
            "type":"Services"
        }
    ],
    "sg:phone":"+33 1 41 49 52 00",
    "sg:province":"Ile de France",
    "sg:tags":[
        "installation",
        "recirculation"
    ],
    "wof:name":"Calindex S.a.",
    "wof:placetype":"venue"
},
  "geometry": {"coordinates":[2.291632,48.893299],"type":"Point"}
}