{
  "type": "Feature",
  "properties": {
    "iso:country":"FR",
    "sg:address":"30",
    "sg:city":"REAUMUR 75003 PARIS",
    "sg:classifiers":[
        {
            "category":"Professional",
            "subcategory":"Engineering",
            "type":"Services"
        }
    ],
    "sg:phone":"+33 1 48 87 59 04",
    "sg:postcode":"75003",
    "sg:province":"Ile de France",
    "sg:tags":[
        "machine",
        "-",
        "jewellery",
        "mechanical"
    ],
    "wof:name":"Vibrograf France",
    "wof:placetype":"venue"
},
  "geometry": {"coordinates":[2.357911,48.865288],"type":"Point"}
}