{
  "type": "Feature",
  "properties": {
    "addr:full":"7, Rue des Bordes - Pouilly le Fort , 77240 Vert Saint Denis Ile de France",
    "addr:housenumber":"7;pouilly",
    "addr:postcode":"77240",
    "addr:street":"Rue Des Bordes;Vert",
    "iso:country":"FR",
    "sg:address":"7, Rue des Bordes - Pouilly le Fort , 77240 Vert Saint Denis",
    "sg:orig_category":"Non-Classified Establishments",
    "sg:phone":"+33 1 64 09 60 61",
    "sg:province":"Ile de France",
    "wof:name":"Vill'equip Sarl",
    "wof:placetype":"venue"
},
  "geometry": {"coordinates":[2.600472,48.563885],"type":"Point"}
}