{
  "type": "Feature",
  "properties": {
    "addr:full":"15 r Centrale; Cours Midi Pyr\u00e9n\u00e9es",
    "addr:housenumber":"15",
    "addr:street":"R;Cours",
    "iso:country":"FR",
    "sg:address":"15 r Centrale; Cours",
    "sg:classifiers":[
        {
            "category":"Banks & Credit Unions",
            "subcategory":"Bank",
            "type":"Services"
        }
    ],
    "sg:phone":"+33 3374897207",
    "sg:province":"Midi Pyr\u00e9n\u00e9es",
    "wof:name":"Lyonnaise De Banque",
    "wof:placetype":"venue"
},
  "geometry": {"coordinates":[0.589401,44.322197],"type":"Point"}
}