{
  "type": "Feature",
  "properties": {
    "addr:full":"57, Rue du 8 Mai - ZA, 72800 Aubign\u00e9 Racan Pays de Loire",
    "addr:housenumber":"57",
    "addr:postcode":"72800",
    "addr:street":"Rue Du 8 Mai Za;Racan",
    "iso:country":"FR",
    "sg:address":"57, Rue du 8 Mai - ZA, 72800 Aubign\u00e9 Racan",
    "sg:orig_category":"Unclassifiable Establishments",
    "sg:phone":"+33 2 43 46 65 99",
    "sg:province":"Pays de Loire",
    "wof:name":"Sph S.a.r.l. - Stratifi\u00e9s Polyester Hurteloup",
    "wof:placetype":"venue"
},
  "geometry": {"coordinates":[0.264116,47.689735],"type":"Point"}
}