{
  "type": "Feature",
  "properties": {
    "iso:country":"FR",
    "sg:address":"B.P. 104, 74953 Scionzier C\u00e9dex^^27, Rue Bourg Dehors, 74130 Vougy",
    "sg:orig_category":"Non-Classified Establishments",
    "sg:phone":"+33 4 50 89 29 50",
    "sg:province":"Rhone-Alpes",
    "wof:name":"Vuarchex C\u00e9sar S.a.",
    "wof:placetype":"venue"
},
  "geometry": {"coordinates":[6.388322,45.95652],"type":"Point"}
}