{
  "type": "Feature",
  "properties": {
    "iso:country":"FR",
    "sg:address":"Hameau de Chapotin 69970 Chaponnay",
    "sg:orig_category":"Non-Classified Establishments",
    "sg:phone":"+33 4 78 96 96 80",
    "sg:province":"Rhone-Alpes",
    "wof:name":"Flash Projet S.a.r.l.",
    "wof:placetype":"venue"
},
  "geometry": {"coordinates":[4.927305,45.65081],"type":"Point"}
}