{
  "type": "Feature",
  "properties": {
    "addr:full":"B.P. 234, 74320 S\u00e9vrier^^370, Rte de Piron, 74320 S\u00e9vrier Rhone-Alpes 74320",
    "addr:housenumber":"b.p. 234",
    "addr:postcode":"74320;74320;74320",
    "addr:street":"Rte De Piron;Rhone-Alpes",
    "iso:country":"FR",
    "sg:address":"B.P. 234, 74320 S\u00e9vrier^^370, Rte de Piron, 74320 S\u00e9vrier",
    "sg:orig_category":"Non-Classified Establishments",
    "sg:phone":"+33 4 50 52 64 42",
    "sg:postcode":"74320",
    "sg:province":"Rhone-Alpes",
    "wof:name":"Jardinerie Du Lac Les Plaisirs Verts S.a.r.l.",
    "wof:placetype":"venue"
},
  "geometry": {"coordinates":[6.14032,45.86393],"type":"Point"}
}