{
  "type": "Feature",
  "properties": {
    "addr:full":"13 Rue Prieur De La Marne 51100 Reims Champagne 51100",
    "addr:housenumber":"13",
    "addr:postcode":"51100;51100",
    "addr:street":"Rue Prieur De La Marne",
    "iso:country":"FR",
    "sg:address":"13 Rue Prieur De La Marne 51100 Reims",
    "sg:classifiers":[
        {
            "category":"Farming",
            "subcategory":"Farm",
            "type":"Manufacturing & Wholesale Goods"
        }
    ],
    "sg:phone":"+33 3 26 07 27 79",
    "sg:postcode":"51100",
    "sg:province":"Champagne",
    "sg:tags":[
        "horticulture",
        "agriculture",
        "livestock"
    ],
    "wof:name":"Sarl Roger Lemaitre",
    "wof:placetype":"venue"
},
  "geometry": {"coordinates":[4.04708,49.262203],"type":"Point"}
}