{
  "type": "Feature",
  "properties": {
    "iso:country":"FR",
    "sg:address":"46 Rue Du G\u00e9n\u00e9ral De Gaulle BP 9 67521 Marlenheim",
    "sg:city":"Marlenheim",
    "sg:classifiers":[
        {
            "category":"Food Court",
            "type":"Food & Drink"
        }
    ],
    "sg:phone":"+33 3 88 87 77 86",
    "sg:postcode":"67520",
    "sg:province":"Alsace",
    "sg:tags":[
        "product",
        "related"
    ],
    "wof:name":"Vinotheque Du Lys Sarl",
    "wof:placetype":"venue"
},
  "geometry": {"coordinates":[-99.696411,38.624722],"type":"Point"}
}