{
  "type": "Feature",
  "properties": {
    "addr:full":"Chemin D\u00e9partemental 205 64350 Aurions Idernes Anoye Aquitaine 64350",
    "addr:housenumber":"205",
    "addr:postcode":"64350;64350",
    "addr:street":"Chemin De\u0301Partemental",
    "iso:country":"FR",
    "sg:address":"Chemin D\u00e9partemental 205 64350 Aurions Idernes",
    "sg:city":"Anoye",
    "sg:classifiers":[
        {
            "category":"Food Court",
            "type":"Food & Drink"
        }
    ],
    "sg:phone":"+33 5 59 04 00 63",
    "sg:postcode":"64350",
    "sg:province":"Aquitaine",
    "sg:tags":[
        "product",
        "related"
    ],
    "wof:name":"Scea",
    "wof:placetype":"venue"
},
  "geometry": {"coordinates":[-0.138224,43.394199],"type":"Point"}
}