{
  "type": "Feature",
  "properties": {
    "iso:country":"FR",
    "sg:address":"Lafarrayrie 46100 Figeac",
    "sg:orig_category":"Unclassifiable Establishments",
    "sg:phone":"+33 5 65 50 07 77",
    "sg:province":"Midi Pyr\u00e9n\u00e9es",
    "wof:name":"Nestor Technologies E.u.r.l.",
    "wof:placetype":"venue"
},
  "geometry": {"coordinates":[2.011682,44.601627],"type":"Point"}
}