{
  "type": "Feature",
  "properties": {
    "addr:full":"Zone Industrielle 09310 ASTON Midi Pyr\u00e9n\u00e9es 09310",
    "addr:postcode":"09310;09310",
    "addr:street":"Zone Industrielle",
    "iso:country":"FR",
    "sg:address":"Zone Industrielle 09310 ASTON",
    "sg:classifiers":[
        {
            "category":"Manufacturing",
            "subcategory":"Electronics",
            "type":"Manufacturing & Wholesale Goods"
        }
    ],
    "sg:phone":"+33 5 61 64 97 43",
    "sg:postcode":"09310",
    "sg:province":"Midi Pyr\u00e9n\u00e9es",
    "sg:tags":[
        "equipment",
        "electronic"
    ],
    "wof:name":"Aria Electronique Sarl",
    "wof:placetype":"venue"
},
  "geometry": {"coordinates":[1.674366,42.775761],"type":"Point"}
}