{
  "type": "Feature",
  "properties": {
    "addr:full":"Zi Du Lord 57150 Creutzwald Lorraine",
    "addr:postcode":"57150",
    "addr:street":"Zi Du Lord",
    "iso:country":"FR",
    "sg:address":"Zi Du Lord 57150 Creutzwald",
    "sg:classifiers":[
        {
            "category":"Banks & Credit Unions",
            "subcategory":"Investment Brokerage",
            "type":"Services"
        }
    ],
    "sg:phone":"+33 3 87 82 65 50",
    "sg:province":"Lorraine",
    "sg:tags":[
        "-",
        "transport",
        "related"
    ],
    "wof:name":"Hasbro France",
    "wof:placetype":"venue"
},
  "geometry": {"coordinates":[6.694479,49.204865],"type":"Point"}
}