{
  "type": "Feature",
  "properties": {
    "iso:country":"FR",
    "sg:address":"Chemin Des Pres 77810 Thomery",
    "sg:classifiers":[
        {
            "category":"Shopping",
            "type":"Retail Goods"
        }
    ],
    "sg:phone":"+33 1 60 73 50 00",
    "sg:postcode":"77810",
    "sg:province":"Ile de France",
    "sg:tags":[
        "metallurgy",
        "finished",
        "-",
        "metalworking",
        "metallic"
    ],
    "wof:name":"Ste Briarde De Roulements Sks",
    "wof:placetype":"venue"
},
  "geometry": {"coordinates":[2.791011,48.411392],"type":"Point"}
}