{
  "type": "Feature",
  "properties": {
    "addr:full":"84 Rue Ampere 03400 Yzeure Yzeure Auvergne 03400",
    "addr:housenumber":"84",
    "addr:postcode":"03400;03400",
    "addr:street":"Rue Ampere",
    "iso:country":"FR",
    "sg:address":"84 Rue Ampere 03400 Yzeure",
    "sg:city":"Yzeure",
    "sg:classifiers":[
        {
            "category":"Shopping",
            "type":"Retail Goods"
        }
    ],
    "sg:phone":"+33 4 70 44 51 68",
    "sg:postcode":"03400",
    "sg:province":"Auvergne",
    "sg:tags":[
        "metallurgy",
        "finished",
        "-",
        "metalworking",
        "metallic"
    ],
    "wof:name":"Serrurerie Nouvelle",
    "wof:placetype":"venue"
},
  "geometry": {"coordinates":[3.344422,46.552498],"type":"Point"}
}