{
  "type": "Feature",
  "properties": {
    "iso:country":"FR",
    "sg:address":"8, Rte de Dung, 25550 Pr\u00e9sentevillers",
    "sg:orig_category":"Non-Classified Establishments",
    "sg:phone":"+33 3 81 92 35 47",
    "sg:postcode":"25550",
    "sg:province":"Franche Comt\u00e9",
    "wof:name":"Agro 2000 S.a.",
    "wof:placetype":"venue"
},
  "geometry": {"coordinates":[6.73575,47.50061],"type":"Point"}
}