{
  "type": "Feature",
  "properties": {
    "addr:full":"58 Bd Gustave Roch Min Bat Nord 44261 Nantes Cedex Midi Pyr\u00e9n\u00e9es",
    "addr:housenumber":"58",
    "addr:postcode":"44261",
    "addr:street":"Bd Gustave Roch Min",
    "iso:country":"FR",
    "sg:address":"58 Bd Gustave Roch Min Bat Nord 44261 Nantes Cedex",
    "sg:classifiers":[
        {
            "category":"Food & Beverages",
            "subcategory":"Meat & Fish",
            "type":"Retail Goods"
        }
    ],
    "sg:phone":"+33 2 51 72 92 35",
    "sg:province":"Midi Pyr\u00e9n\u00e9es",
    "sg:tags":[
        "preserve",
        "cooked",
        "product",
        "related"
    ],
    "wof:name":"Berjac Viandes",
    "wof:placetype":"venue"
},
  "geometry": {"coordinates":[-1.555667,47.200958],"type":"Point"}
}