{
  "type": "Feature",
  "properties": {
    "iso:country":"FR",
    "sg:address":"2, All\u00e9e des Erables - Parc d'Activit\u00e9s R\u00e9publique Carnot, 69692 V\u00e9nissieux C\u00e9dex",
    "sg:orig_category":"Non-Classified Establishments",
    "sg:phone":"+33 4 78 70 55 55",
    "sg:province":"Haute Normandie",
    "wof:name":"Peintures Min\u00e9rales Keim S.a.r.l.",
    "wof:placetype":"venue"
},
  "geometry": {"coordinates":[4.867407,45.709717],"type":"Point"}
}