{
  "type": "Feature",
  "properties": {
    "iso:country":"FR",
    "sg:address":"73 rue Francis de Pressens\u00e9 69100 Villeurbanne",
    "sg:classifiers":[
        {
            "category":"Professional",
            "subcategory":"Advertising",
            "type":"Services"
        }
    ],
    "sg:phone":"+33 4 72 69 40 90",
    "sg:province":"Rhone-Alpes",
    "sg:tags":[
        "glass",
        "made",
        "gift",
        "crystal"
    ],
    "wof:name":"Ideal Promotion Sarl",
    "wof:placetype":"venue"
},
  "geometry": {"coordinates":[4.87604,45.771809],"type":"Point"}
}