{
  "type": "Feature",
  "properties": {
    "addr:full":"581 R Des Fr\u00e8res Lumi\u00e8re Sud 71000 Macon Bourgogne 71000",
    "addr:housenumber":"581",
    "addr:postcode":"71000;71000",
    "addr:street":"R Des Fre\u0300Res Lumie\u0300Re Sud;Bourgogne",
    "iso:country":"FR",
    "sg:address":"581 R Des Fr\u00e8res Lumi\u00e8re",
    "sg:city":"Sud 71000 Macon",
    "sg:classifiers":[
        {
            "category":"Structure",
            "subcategory":"Office Building",
            "type":"Public Place"
        }
    ],
    "sg:phone":"+33 3 85 32 87 00",
    "sg:postcode":"71000",
    "sg:province":"Bourgogne",
    "sg:tags":[
        "publishing",
        "processing",
        "metal",
        "metallurgy",
        "metalworking",
        "printing"
    ],
    "wof:name":"Bindschedler Sas",
    "wof:placetype":"venue"
},
  "geometry": {"coordinates":[4.833055,46.303043],"type":"Point"}
}