{
  "type": "Feature",
  "properties": {
    "iso:country":"FR",
    "sg:address":"37/39, Rue Carnot, 69190 Saint Fons",
    "sg:orig_category":"Non-Classified Establishments",
    "sg:phone":"+33 4 72 89 05 60",
    "sg:postcode":"69190",
    "sg:province":"Rhone-Alpes",
    "wof:name":"Nicollin S.a.",
    "wof:placetype":"venue"
},
  "geometry": {"coordinates":[4.859145,45.708107],"type":"Point"}
}