{
  "type": "Feature",
  "properties": {
    "addr:full":"Zi La Pise Ouest 30110 La Grand Combe Languedoc-Roussillon 30110",
    "addr:postcode":"30110;30110",
    "addr:street":"Zi La Pise Ouest;Combe",
    "iso:country":"FR",
    "sg:address":"Zi La Pise Ouest 30110 La Grand Combe",
    "sg:classifiers":[
        {
            "category":"Manufacturing",
            "subcategory":"Metals",
            "type":"Manufacturing & Wholesale Goods"
        }
    ],
    "sg:phone":"+33 4 66 34 16 18",
    "sg:postcode":"30110",
    "sg:province":"Languedoc-Roussillon",
    "sg:tags":[
        "pipe",
        "sheet",
        "-",
        "metalworking",
        "metallic",
        "metallurgy",
        "finished"
    ],
    "wof:name":"Ste Cevenole Tuyauterie Et Chaudronnerie",
    "wof:placetype":"venue"
},
  "geometry": {"coordinates":[4.029854,44.210121],"type":"Point"}
}