{
  "type": "Feature",
  "properties": {
    "iso:country":"FR",
    "sg:address":"Rue De La R\u00e9publique 60280 Clairoix",
    "sg:classifiers":[
        {
            "category":"Manufacturing",
            "subcategory":"Rubber & Plastics",
            "type":"Manufacturing & Wholesale Goods"
        }
    ],
    "sg:phone":"+33 3 44 40 71 33",
    "sg:province":"Picardie",
    "wof:name":"Continental Snc",
    "wof:placetype":"venue"
},
  "geometry": {"coordinates":[2.839835,49.43248],"type":"Point"}
}