{
  "type": "Feature",
  "properties": {
    "iso:country":"FR",
    "sg:address":"8 R Tr\u00e9bois 92300 Levallois Perret",
    "sg:classifiers":[
        {
            "category":"Professional",
            "subcategory":"Advertising",
            "type":"Services"
        }
    ],
    "sg:phone":"+33 1 42 70 34 34",
    "sg:postcode":"92300",
    "sg:province":"Ile de France",
    "sg:tags":[
        "communication",
        "medium"
    ],
    "wof:name":"Birdie Productions Sa",
    "wof:placetype":"venue"
},
  "geometry": {"coordinates":[2.290719,48.890446],"type":"Point"}
}