{
  "type": "Feature",
  "properties": {
    "addr:full":"Hameau Normandie 77710 Lorrez le Bocage Pr\u00e9aux Ile de France",
    "addr:postcode":"77710",
    "addr:street":"Hameau Normandie",
    "iso:country":"FR",
    "sg:address":"Hameau Normandie 77710 Lorrez le Bocage Pr\u00e9aux",
    "sg:orig_category":"Non-Classified Establishments",
    "sg:phone":"+33 1 64 31 52 19",
    "sg:province":"Ile de France",
    "wof:name":"Soci\u00e9t\u00e9 Des Proc\u00e9d\u00e9s Colombino S.a.r.l.",
    "wof:placetype":"venue"
},
  "geometry": {"coordinates":[2.906583,48.223289],"type":"Point"}
}