{
  "type": "Feature",
  "properties": {
    "addr:full":"51 R Martyrs; Elbeuf; 76500 Haute Normandie 76500",
    "addr:housenumber":"51",
    "addr:postcode":"76500;76500",
    "addr:street":"R Martyrs;Normandie",
    "iso:country":"FR",
    "sg:address":"51 R Martyrs; Elbeuf; 76500",
    "sg:classifiers":[
        {
            "category":"Banks & Credit Unions",
            "subcategory":"Bank",
            "type":"Services"
        }
    ],
    "sg:phone":"+33 3335812249",
    "sg:postcode":"76500",
    "sg:province":"Haute Normandie",
    "wof:name":"Cr\u00e9dit Lyonnais",
    "wof:placetype":"venue"
},
  "geometry": {"coordinates":[1.005591,49.289196],"type":"Point"}
}