{
  "type": "Feature",
  "properties": {
    "addr:full":"Chemin De La Fontaine Saint Loup 89210 Brienon Sur Armancon Bellechaume Bourgogne 89210",
    "addr:postcode":"89210;89210",
    "addr:street":"Chemin De La Fontaine Saint Loup",
    "iso:country":"FR",
    "sg:address":"Chemin De La Fontaine Saint Loup 89210 Brienon Sur Armancon",
    "sg:city":"Bellechaume",
    "sg:classifiers":[
        {
            "category":"Building & Trades",
            "subcategory":"Electrical",
            "type":"Services"
        }
    ],
    "sg:phone":"+33 3 86 56 08 07",
    "sg:postcode":"89210",
    "sg:province":"Bourgogne",
    "sg:tags":[
        "electronic",
        "lighting",
        "equipment"
    ],
    "wof:name":"M Decoration Ets Muller",
    "wof:placetype":"venue"
},
  "geometry": {"coordinates":[3.617082,47.992756],"type":"Point"}
}