{
  "type": "Feature",
  "properties": {
    "iso:country":"FR",
    "sg:address":"7 Impasse Du Reve 69100 Villeurbanne",
    "sg:classifiers":[
        {
            "category":"Manufacturing",
            "subcategory":"Rubber & Plastics",
            "type":"Manufacturing & Wholesale Goods"
        }
    ],
    "sg:phone":"+33 4 78 80 19 19",
    "sg:postcode":"69100",
    "sg:province":"Rhone-Alpes",
    "wof:name":"Plastiflon",
    "wof:placetype":"venue"
},
  "geometry": {"coordinates":[4.90372,45.78315],"type":"Point"}
}