{
  "type": "Feature",
  "properties": {
    "addr:full":"ZA Noyal sur Vilaine Bretagne 35530",
    "addr:postcode":"35530",
    "addr:street":"Za Noyal;Vilaine Bretagne",
    "iso:country":"FR",
    "sg:address":"ZA",
    "sg:city":"Noyal sur Vilaine",
    "sg:orig_category":"Non-Classified Establishments",
    "sg:phone":"+33 2 99 04 18 18",
    "sg:postcode":"35530",
    "sg:province":"Bretagne",
    "wof:name":"M.p.i. Services S.a.",
    "wof:placetype":"venue"
},
  "geometry": {"coordinates":[-1.521279,48.110287],"type":"Point"}
}