{
  "type": "Feature",
  "properties": {
    "addr:full":"B.P. 109 Chamb\u00e9ry C\u00e9dex Rhone-Alpes 73001",
    "addr:housenumber":"b.p. 109",
    "addr:postcode":"73001",
    "addr:street":"Rhone-Alpes",
    "iso:country":"FR",
    "sg:address":"B.P. 109",
    "sg:city":"Chamb\u00e9ry C\u00e9dex",
    "sg:orig_category":"Non-Classified Establishments",
    "sg:phone":"+33 4 79 33 93 10",
    "sg:postcode":"73001",
    "sg:province":"Rhone-Alpes",
    "wof:name":"Banque De Savoie",
    "wof:placetype":"venue"
},
  "geometry": {"coordinates":[5.92092,45.566647],"type":"Point"}
}