{
  "type": "Feature",
  "properties": {
    "addr:full":"15 Rue Crabi\u00e9 81103 Castres Cedex Bretagne",
    "addr:housenumber":"15",
    "addr:postcode":"81103;cedex",
    "addr:street":"Rue Crabie\u0301",
    "iso:country":"FR",
    "sg:address":"15 Rue Crabi\u00e9 81103 Castres Cedex",
    "sg:classifiers":[
        {
            "category":"Shopping",
            "subcategory":"Crafts & Fabrics",
            "type":"Retail Goods"
        }
    ],
    "sg:phone":"+33 5 63 35 64 54",
    "sg:province":"Bretagne",
    "sg:tags":[
        "textile",
        "clothing"
    ],
    "wof:name":"Filature Du Maroulet Sa",
    "wof:placetype":"venue"
},
  "geometry": {"coordinates":[2.243894,43.598709],"type":"Point"}
}