{
  "type": "Feature",
  "properties": {
    "addr:full":"35, Rue du Puits Mauger, 35000 Rennes Rennes Bretagne 35000",
    "addr:housenumber":"35",
    "addr:postcode":"35000;35000",
    "addr:street":"Rue Du Puits Mauger",
    "iso:country":"FR",
    "sg:address":"35, Rue du Puits Mauger, 35000 Rennes",
    "sg:city":"Rennes",
    "sg:orig_category":"Unclassifiable Establishments",
    "sg:phone":"+33 2 23 44 81 61",
    "sg:postcode":"35000",
    "sg:province":"Bretagne",
    "wof:name":"Actual Int\u00e9rim S.a.",
    "wof:placetype":"venue"
},
  "geometry": {"coordinates":[-1.683739,48.105427],"type":"Point"}
}