{
  "type": "Feature",
  "properties": {
    "iso:country":"FR",
    "sg:address":"15, Rue Jules Ferry, 65600 S\u00e9m\u00e9ac",
    "sg:orig_category":"Non-Classified Establishments",
    "sg:phone":"+33 5 62 37 58 18",
    "sg:province":"Midi Pyr\u00e9n\u00e9es",
    "wof:name":"Mich\u00e8le Borg S.a.r.l.",
    "wof:placetype":"venue"
},
  "geometry": {"coordinates":[0.104145,43.2257],"type":"Point"}
}