{
  "type": "Feature",
  "properties": {
    "iso:country":"FR",
    "sg:address":"58 Rue Ernest Savart 93102 Montreuil Cedex",
    "sg:classifiers":[
        {
            "category":"Manufacturing",
            "subcategory":"Metals",
            "type":"Manufacturing & Wholesale Goods"
        }
    ],
    "sg:phone":"+33 1 42 87 47 72",
    "sg:province":"Basse Normandie",
    "sg:tags":[
        "metallurgy",
        "steel",
        "metalworking"
    ],
    "wof:name":"Anelli Sa",
    "wof:placetype":"venue"
},
  "geometry": {"coordinates":[2.439401,48.868248],"type":"Point"}
}