{
  "type": "Feature",
  "properties": {
    "addr:full":"17 Av De Garndgend 33440 Ambaresse Ambar\u00e8s-et-Lagrave Aquitaine 33440",
    "addr:postcode":"33440;33440",
    "addr:street":"17 Av De Garndgend",
    "iso:country":"FR",
    "sg:address":"17 Av De Garndgend 33440 Ambaresse",
    "sg:city":"Ambar\u00e8s-et-Lagrave",
    "sg:classifiers":[
        {
            "category":"Professional",
            "subcategory":"Business Services",
            "type":"Services"
        }
    ],
    "sg:phone":"+33 5 56 95 39 40",
    "sg:postcode":"33440",
    "sg:province":"Aquitaine",
    "sg:tags":[
        "travel",
        "transport",
        "road"
    ],
    "wof:name":"Autocars Serveau Sa",
    "wof:placetype":"venue"
},
  "geometry": {"coordinates":[-80.989273,26.60747],"type":"Point"}
}