{
  "type": "Feature",
  "properties": {
    "iso:country":"FR",
    "sg:address":"3, Cit\u00e9 de Londres, 75009 Paris",
    "sg:orig_category":"Unclassifiable Establishments",
    "sg:phone":"+33 1 42 81 93 79",
    "sg:province":"Ile de France",
    "wof:name":"Aliachem France S.a.",
    "wof:placetype":"venue"
},
  "geometry": {"coordinates":[2.329142,48.876705],"type":"Point"}
}