{
  "type": "Feature",
  "properties": {
    "addr:full":"43, Rte d'Aulnay, 95500 Gonesse Ile de France",
    "addr:housenumber":"43",
    "addr:postcode":"95500;ile",
    "addr:street":"Rte D'Aulnay",
    "iso:country":"FR",
    "sg:address":"43, Rte d'Aulnay, 95500 Gonesse",
    "sg:orig_category":"Unclassifiable Establishments",
    "sg:phone":"+33 1 34 07 94 00",
    "sg:province":"Ile de France",
    "wof:name":"G.t.l. S.a. - Gestion Transport Location",
    "wof:placetype":"venue"
},
  "geometry": {"coordinates":[2.44967,48.980476],"type":"Point"}
}