{
  "type": "Feature",
  "properties": {
    "iso:country":"FR",
    "sg:address":"4 Rue Victor Hugo 77460 Souppes Sur Loing",
    "sg:classifiers":[
        {
            "category":"Wholesale",
            "subcategory":"Medical Equipment & Supplies",
            "type":"Manufacturing & Wholesale Goods"
        }
    ],
    "sg:phone":"+33 1 64 29 73 43",
    "sg:postcode":"77460",
    "sg:province":"Ile de France",
    "sg:tags":[
        "instrument",
        "health",
        "-",
        "precision"
    ],
    "wof:name":"Societe D'exploitation Gainoplast",
    "wof:placetype":"venue"
},
  "geometry": {"coordinates":[2.732772,48.182713],"type":"Point"}
}