{
  "type": "Feature",
  "properties": {
    "addr:full":"Avenue Jean Jaur\u00e8s 47360 Prayssas Prayssas Aquitaine 47360",
    "addr:postcode":"47360;47360",
    "addr:street":"Avenue Jean Jaure\u0300S",
    "iso:country":"FR",
    "sg:address":"Avenue Jean Jaur\u00e8s 47360 Prayssas",
    "sg:city":"Prayssas",
    "sg:classifiers":[
        {
            "category":"Farming",
            "subcategory":"Crops",
            "type":"Manufacturing & Wholesale Goods"
        }
    ],
    "sg:phone":"+33 5 53 95 02 98",
    "sg:postcode":"47360",
    "sg:province":"Aquitaine",
    "sg:tags":[
        "vegetable",
        "fruit",
        "agriculture",
        "livestock"
    ],
    "wof:name":"Coop Prayssica",
    "wof:placetype":"venue"
},
  "geometry": {"coordinates":[0.510995,44.289665],"type":"Point"}
}