{
  "type": "Feature",
  "properties": {
    "iso:country":"FR",
    "sg:address":"23, Rue de Rosheim, 67870 Griesheim pr\u00e8s Molsheim",
    "sg:city":"Bischoffsheim",
    "sg:orig_category":"Non-Classified Establishments",
    "sg:phone":"+33 3 88 49 76 20",
    "sg:postcode":"67870",
    "sg:province":"Alsace",
    "wof:name":"Vetter International S.a.",
    "wof:placetype":"venue"
},
  "geometry": {"coordinates":[7.525422,48.505016],"type":"Point"}
}