{
  "type": "Feature",
  "properties": {
    "iso:country":"FR",
    "sg:address":"68 Rue Des Roches 93100 Montreuil",
    "sg:classifiers":[
        {
            "category":"Shopping",
            "subcategory":"Computers & Home Electronics",
            "type":"Retail Goods"
        }
    ],
    "sg:phone":"+33 1 48 70 14 14",
    "sg:postcode":"93100",
    "sg:province":"Ile de France",
    "sg:tags":[
        "electronic",
        "electrical",
        "equipment"
    ],
    "wof:name":"D2 Diffusion Sa",
    "wof:placetype":"venue"
},
  "geometry": {"coordinates":[2.464793,48.871334],"type":"Point"}
}