{
  "type": "Feature",
  "properties": {
    "iso:country":"FR",
    "sg:address":"B.P. 7, 86201 Loudun C\u00e9dex^^Av. de Ouagadougou - ZI Nord, 86200 Loudun",
    "sg:orig_category":"Non-Classified Establishments",
    "sg:phone":"+33 5 49 98 03 00",
    "sg:province":"Poitou-Charentes",
    "wof:name":"Soci\u00e9t\u00e9 Loudunaise Des Viandes S.a.",
    "wof:placetype":"venue"
},
  "geometry": {"coordinates":[0.156242,46.958393],"type":"Point"}
}