{
  "type": "Feature",
  "properties": {
    "iso:country":"FR",
    "sg:address":"Ham les Moines 08090 Charleville M\u00e9zi\u00e8res",
    "sg:city":"Aiglemont",
    "sg:orig_category":"Non-Classified Establishments",
    "sg:phone":"+33 3 24 59 54 54",
    "sg:postcode":"08090",
    "sg:province":"Champagne",
    "wof:name":"S.a.e. S.a. - Soci\u00e9t\u00e9 Ardennaise D'essieux",
    "wof:placetype":"venue"
},
  "geometry": {"coordinates":[4.667313,49.792923],"type":"Point"}
}