{
  "type": "Feature",
  "properties": {
    "addr:full":"Rue Jean Moulin - ZI de Bayon La Ricamarie Rhone-Alpes 42150",
    "addr:postcode":"42150",
    "addr:street":"Rue Jean Moulin Zi De Bayon La;Rhone-Alpes",
    "iso:country":"FR",
    "sg:address":"Rue Jean Moulin - ZI de Bayon",
    "sg:city":"La Ricamarie",
    "sg:orig_category":"Non-Classified Establishments",
    "sg:phone":"+33 4 77 59 99 10",
    "sg:postcode":"42150",
    "sg:province":"Rhone-Alpes",
    "wof:name":"Ravni Technologies S.a.r.l.",
    "wof:placetype":"venue"
},
  "geometry": {"coordinates":[4.36615,45.40406],"type":"Point"}
}