{
  "type": "Feature",
  "properties": {
    "iso:country":"FR",
    "sg:address":"ZA",
    "sg:city":"M. Robespierre 93130 Noisy le Sec",
    "sg:classifiers":[
        {
            "category":"Professional",
            "subcategory":"Printing & Photocopies",
            "type":"Services"
        }
    ],
    "sg:phone":"+33 1 48 10 64 64",
    "sg:postcode":"93130",
    "sg:province":"Ile de France",
    "sg:tags":[
        "machine",
        "engineering",
        "-",
        "mechanical"
    ],
    "wof:name":"Coci S.a.",
    "wof:placetype":"venue"
},
  "geometry": {"coordinates":[2.45075,48.889885],"type":"Point"}
}