{
  "type": "Feature",
  "properties": {
    "addr:full":"2, Rue Robert le Ricolais, 44000 Nantes Pays de Loire",
    "addr:housenumber":"2",
    "addr:postcode":"44000",
    "addr:street":"Rue Robert Le Ricolais",
    "iso:country":"FR",
    "sg:address":"2, Rue Robert le Ricolais, 44000 Nantes",
    "sg:orig_category":"Non-Classified Establishments",
    "sg:phone":"+33 2 40 93 11 78",
    "sg:province":"Pays de Loire",
    "wof:name":"Nantes Cr\u00e9atic",
    "wof:placetype":"venue"
},
  "geometry": {"coordinates":[-1.505183,47.246929],"type":"Point"}
}