{
  "type": "Feature",
  "properties": {
    "iso:country":"FR",
    "sg:address":"B.P. 2308, 31020 Toulouse C\u00e9dex 2^^8, Av. de Fondeyre, 31200 Toulouse",
    "sg:orig_category":"Non-Classified Establishments",
    "sg:phone":"+33 5 61 34 19 67",
    "sg:province":"Midi Pyr\u00e9n\u00e9es",
    "wof:name":"V.s.o. G.i.e. - Les Vignerons Du Sud-ouest",
    "wof:placetype":"venue"
},
  "geometry": {"coordinates":[1.44954,43.639011],"type":"Point"}
}