{
  "type": "Feature",
  "properties": {
    "addr:full":"ZI Merpins Cognac Poitou-Charentes 16100",
    "addr:postcode":"16100",
    "addr:street":"Cognac",
    "iso:country":"FR",
    "sg:address":"ZI Merpins",
    "sg:city":"Cognac",
    "sg:orig_category":"Non-Classified Establishments",
    "sg:phone":"+33 5 45 82 26 23",
    "sg:postcode":"16100",
    "sg:province":"Poitou-Charentes",
    "wof:name":"Recyclage Schneid S.a.",
    "wof:placetype":"venue"
},
  "geometry": {"coordinates":[-0.325174,45.693745],"type":"Point"}
}