{
  "type": "Feature",
  "properties": {
    "addr:full":"57100 Thionville Lorraine",
    "addr:postcode":"57100",
    "iso:country":"FR",
    "sg:address":"57100 Thionville",
    "sg:orig_category":"Unclassifiable Establishments",
    "sg:phone":"+33 3 82 82 25 25",
    "sg:province":"Lorraine",
    "wof:name":"Mairie De Thionville",
    "wof:placetype":"venue"
},
  "geometry": {"coordinates":[6.14425,49.371449],"type":"Point"}
}