{
  "type": "Feature",
  "properties": {
    "iso:country":"FR",
    "sg:address":"43000 Le Puy en Velay",
    "sg:city":"Le Puy-en-Velay",
    "sg:orig_category":"Unclassifiable Establishments",
    "sg:phone":"+33 4 71 09 60 44",
    "sg:postcode":"43000",
    "sg:province":"Auvergne",
    "wof:name":"Les Tanneries Du Puy S.a.",
    "wof:placetype":"venue"
},
  "geometry": {"coordinates":[3.86981,45.053169],"type":"Point"}
}