{
  "type": "Feature",
  "properties": {
    "addr:full":"48, Rue Montmartre, 75002 Paris Ile de France",
    "addr:housenumber":"48",
    "addr:postcode":"75002",
    "addr:street":"Rue Montmartre",
    "iso:country":"FR",
    "sg:address":"48, Rue Montmartre, 75002 Paris",
    "sg:orig_category":"Non-Classified Establishments",
    "sg:phone":"+33 1 53 00 92 00",
    "sg:province":"Ile de France",
    "wof:name":"Foods S.a.",
    "wof:placetype":"venue"
},
  "geometry": {"coordinates":[2.34516,48.865185],"type":"Point"}
}