{
  "type": "Feature",
  "properties": {
    "iso:country":"FR",
    "sg:address":"1, Rue de Grasse, 29200 Brest",
    "sg:city":"Brest",
    "sg:orig_category":"Non-Classified Establishments",
    "sg:phone":"+33 2 98 44 56 83",
    "sg:postcode":"29200",
    "sg:province":"Bretagne",
    "wof:name":"C.i.s.c.o. S.a.r.l. - Centre International Sciences Techniques Orthodentistes",
    "wof:placetype":"venue"
},
  "geometry": {"coordinates":[-4.479823,48.404964],"type":"Point"}
}