{
  "type": "Feature",
  "properties": {
    "addr:full":"rue de Bretagne 56260 Larmor Plage Larmor-Plage Bretagne 56260",
    "addr:postcode":"56260;56260",
    "addr:street":"Rue De Bretagne;Larmor-Plage Bretagne",
    "iso:country":"FR",
    "sg:address":"rue de Bretagne 56260 Larmor Plage",
    "sg:city":"Larmor-Plage",
    "sg:orig_category":"Fish, Frozen",
    "sg:phone":"+33 2 97 87 84 84",
    "sg:postcode":"56260",
    "sg:province":"Bretagne",
    "wof:name":"Detfood Sas",
    "wof:placetype":"venue"
},
  "geometry": {"coordinates":[-3.389079,47.72493],"type":"Point"}
}