{
  "type": "Feature",
  "properties": {
    "addr:full":"La Ville du Bois 35133 La Chapelle Janson Beauc\u00e9 Bretagne 35133",
    "addr:postcode":"35133;35133",
    "addr:street":"La Ville Du Bois;Beauce\u0301 Bretagne",
    "iso:country":"FR",
    "sg:address":"La Ville du Bois 35133 La Chapelle Janson",
    "sg:city":"Beauc\u00e9",
    "sg:orig_category":"Unclassifiable Establishments",
    "sg:phone":"+33 2 99 95 26 09",
    "sg:postcode":"35133",
    "sg:province":"Bretagne",
    "wof:name":"Etablissements Helbert S.a.r.l.",
    "wof:placetype":"venue"
},
  "geometry": {"coordinates":[-1.101174,48.329895],"type":"Point"}
}