{
  "type": "Feature",
  "properties": {
    "iso:country":"FR",
    "sg:address":"3 Av De La D\u00e9portation 26100 Romans Sur Is\u00e8re",
    "sg:classifiers":[
        {
            "category":"Wholesale",
            "subcategory":"Farm Supplies",
            "type":"Manufacturing & Wholesale Goods"
        }
    ],
    "sg:phone":"+33 4 75 70 41 01",
    "sg:postcode":"26100",
    "sg:province":"Rhone-Alpes",
    "sg:tags":[
        "-",
        "machine",
        "equipment",
        "engineering",
        "machinery",
        "mechanical",
        "agriculture"
    ],
    "wof:name":"Peillet Sa",
    "wof:placetype":"venue"
},
  "geometry": {"coordinates":[5.081882,45.050152],"type":"Point"}
}