{
  "type": "Feature",
  "properties": {
    "addr:full":"B.P. 32, 70100 Arc l\u00e8s Gray^^Zone Industrielle les Giranaux, 70100 Arc l\u00e8s Gray Franche Comt\u00e9",
    "addr:postcode":"70100;70100",
    "addr:street":"B.P. 32;Industrielle;Giranaux;Franche Comte\u0301",
    "iso:country":"FR",
    "sg:address":"B.P. 32, 70100 Arc l\u00e8s Gray^^Zone Industrielle les Giranaux, 70100 Arc l\u00e8s Gray",
    "sg:orig_category":"Non-Classified Establishments",
    "sg:phone":"+33 3 84 64 91 00",
    "sg:province":"Franche Comt\u00e9",
    "wof:name":"Tpre S.a.r.l. - Travaux Publics R\u00e9seau De L'est",
    "wof:placetype":"venue"
},
  "geometry": {"coordinates":[5.514565,47.369511],"type":"Point"}
}