{
  "type": "Feature",
  "properties": {
    "iso:country":"FR",
    "sg:address":"2, Rue Tellier - ZA de Villepecle, 91280 Saint Pierre du Perray",
    "sg:orig_category":"Non-Classified Establishments",
    "sg:phone":"+33 1 69 89 61 61",
    "sg:province":"Ile de France",
    "wof:name":"I.l.s. S.a. - Informatique Logistique Service",
    "wof:placetype":"venue"
},
  "geometry": {"coordinates":[2.494705,48.612675],"type":"Point"}
}