{
  "type": "Feature",
  "properties": {
    "iso:country":"FR",
    "sg:address":"3 bis, Bd de Verdun, 44600 Saint Nazaire",
    "sg:orig_category":"Unclassifiable Establishments",
    "sg:phone":"+33 2 40 00 45 20",
    "sg:province":"Pays de Loire",
    "wof:name":"Port Autonome De Nantes - Saint Nazaire",
    "wof:placetype":"venue"
},
  "geometry": {"coordinates":[-2.20311,47.271278],"type":"Point"}
}