{
  "type": "Feature",
  "properties": {
    "addr:full":"4, Rue de N\u00e9gron, 37530 Nazelles N\u00e9gron Cangey Centre 37530",
    "addr:housenumber":"4",
    "addr:postcode":"37530;37530",
    "addr:street":"Rue De Ne\u0301Gron",
    "iso:country":"FR",
    "sg:address":"4, Rue de N\u00e9gron, 37530 Nazelles N\u00e9gron",
    "sg:city":"Cangey",
    "sg:orig_category":"Unclassifiable Establishments",
    "sg:phone":"+33 2 47 57 00 29",
    "sg:postcode":"37530",
    "sg:province":"Centre",
    "wof:name":"S.o.r.i.t. S.a.r.l.",
    "wof:placetype":"venue"
},
  "geometry": {"coordinates":[0.954688,47.411739],"type":"Point"}
}