{
  "type": "Feature",
  "properties": {
    "addr:full":"205, Rue de Bayeux, 14000 Caen Caen Basse Normandie 14000",
    "addr:housenumber":"205",
    "addr:postcode":"14000;14000",
    "addr:street":"Rue De Bayeux",
    "iso:country":"FR",
    "sg:address":"205, Rue de Bayeux, 14000 Caen",
    "sg:city":"Caen",
    "sg:orig_category":"Non-Classified Establishments",
    "sg:phone":"+33 2 31 73 70 00",
    "sg:postcode":"14000",
    "sg:province":"Basse Normandie",
    "wof:name":"Green Consulting S.a.",
    "wof:placetype":"venue"
},
  "geometry": {"coordinates":[-0.39363,49.184425],"type":"Point"}
}