{
  "type": "Feature",
  "properties": {
    "addr:full":"19 Rue Du G\u00e9n\u00e9ral Foy Paris Ile de France 75008",
    "addr:housenumber":"19",
    "addr:postcode":"75008",
    "addr:street":"Rue Du Ge\u0301Ne\u0301Ral Foy",
    "iso:country":"FR",
    "sg:address":"19 Rue Du G\u00e9n\u00e9ral Foy",
    "sg:city":"Paris",
    "sg:classifiers":[
        {
            "category":"Banks & Credit Unions",
            "subcategory":"Financial Services",
            "type":"Services"
        }
    ],
    "sg:phone":"+33 1 44 90 60 60",
    "sg:postcode":"75008",
    "sg:province":"Ile de France",
    "sg:tags":[
        "banking",
        "finance",
        "insurance"
    ],
    "wof:name":"Invesco France (sa)",
    "wof:placetype":"venue"
},
  "geometry": {"coordinates":[2.317626,48.878326],"type":"Point"}
}