{
  "type": "Feature",
  "properties": {
    "addr:full":"15 avenue de l'Industrie 69960 Corbas Rhone-Alpes 69960",
    "addr:housenumber":"15",
    "addr:postcode":"69960;69960",
    "addr:street":"Avenue De L'Industrie",
    "iso:country":"FR",
    "sg:address":"15 avenue de l'Industrie 69960 Corbas",
    "sg:classifiers":[
        {
            "category":"Professional",
            "type":"Services"
        }
    ],
    "sg:phone":"+33 4 72 23 15 60",
    "sg:postcode":"69960",
    "sg:province":"Rhone-Alpes",
    "sg:tags":[
        "transport"
    ],
    "wof:name":"S.l.m.n. Sa",
    "wof:placetype":"venue"
},
  "geometry": {"coordinates":[4.922905,45.679386],"type":"Point"}
}