{
  "type": "Feature",
  "properties": {
    "addr:full":"Pont de Lamothe Lamothe Auvergne 43100",
    "addr:postcode":"43100",
    "addr:street":"Pont De Lamothe Lamothe",
    "iso:country":"FR",
    "sg:address":"Pont de Lamothe",
    "sg:city":"Lamothe",
    "sg:orig_category":"Unclassifiable Establishments",
    "sg:phone":"+33 4 71 50 15 24",
    "sg:postcode":"43100",
    "sg:province":"Auvergne",
    "wof:name":"Entreprise Veuve Bertrand Et Ses Enfants S.a.r.l.",
    "wof:placetype":"venue"
},
  "geometry": {"coordinates":[3.38735,45.294071],"type":"Point"}
}