{
  "type": "Feature",
  "properties": {
    "iso:country":"FR",
    "sg:address":"Rte de Jonzieux - Champs de Berre",
    "sg:city":"Saint Just Malmont",
    "sg:orig_category":"Non-Classified Establishments",
    "sg:phone":"+33 4 77 35 62 32",
    "sg:postcode":"43240",
    "sg:province":"Auvergne",
    "wof:name":"Transports Mat\u00e9riaux Combustibles Yves Boute S.a.",
    "wof:placetype":"venue"
},
  "geometry": {"coordinates":[4.313666,45.339558],"type":"Point"}
}