{
  "type": "Feature",
  "properties": {
    "addr:full":"40, Av. Andr\u00e9 Morisset, 92213 Boulogne Billancourt C\u00e9dex \u00cele-de-France",
    "addr:postcode":"92213",
    "addr:street":"40 Av. Andre\u0301 Morisset;Ce\u0301Dex",
    "iso:country":"FR",
    "sg:address":"40, Av. Andr\u00e9 Morisset, 92213 Boulogne Billancourt C\u00e9dex",
    "sg:orig_category":"Non-Classified Establishments",
    "sg:phone":"+33 1 46 08 67 00",
    "sg:province":"\u00cele-de-France",
    "wof:name":"G.i.s.t. S.a. - Groupe Informatique Scientifique Et Technique",
    "wof:placetype":"venue"
},
  "geometry": {"coordinates":[2.237699,48.83659],"type":"Point"}
}