{
  "type": "Feature",
  "properties": {
    "addr:full":"Avenue Georges Deloffre 86270 La Roche Posay Poitou-Charentes",
    "addr:postcode":"86270",
    "addr:street":"Avenue Georges Deloffre;Posay",
    "iso:country":"FR",
    "sg:address":"Avenue Georges Deloffre 86270 La Roche Posay",
    "sg:classifiers":[
        {
            "category":"Sports & Exercise",
            "subcategory":"Sports Center",
            "type":"Entertainment"
        }
    ],
    "sg:phone":"+33 5 49 86 20 10",
    "sg:province":"Poitou-Charentes",
    "sg:tags":[
        "game"
    ],
    "wof:name":"Complexe Commercial De La Roche Posay Sa",
    "wof:placetype":"venue"
},
  "geometry": {"coordinates":[0.824633,46.779217],"type":"Point"}
}