{
  "type": "Feature",
  "properties": {
    "addr:full":"Av. Maurice Printignant N\u00eemes Languedoc-Roussillon 30900",
    "addr:postcode":"30900",
    "addr:street":"Av. Maurice Printignant",
    "iso:country":"FR",
    "sg:address":"Av. Maurice Printignant",
    "sg:city":"N\u00eemes",
    "sg:orig_category":"Unclassifiable Establishments",
    "sg:phone":"+33 4 66 04 97 97",
    "sg:postcode":"30900",
    "sg:province":"Languedoc-Roussillon",
    "wof:name":"S.t.n. Trinity S.a.r.l.",
    "wof:placetype":"venue"
},
  "geometry": {"coordinates":[4.340773,43.814972],"type":"Point"}
}