{
  "type": "Feature",
  "properties": {
    "iso:country":"FR",
    "sg:address":"18 R Du Golf 95560 Baillet En France",
    "sg:classifiers":[
        {
            "category":"Sports & Exercise",
            "subcategory":"Sports Center",
            "type":"Entertainment"
        }
    ],
    "sg:phone":"+33 1 34 69 88 99",
    "sg:postcode":"95560",
    "sg:province":"Ile de France",
    "sg:tags":[
        "game"
    ],
    "wof:name":"Paris International Club Sa",
    "wof:placetype":"venue"
},
  "geometry": {"coordinates":[2.299456,49.050835],"type":"Point"}
}