{
  "type": "Feature",
  "properties": {
    "addr:full":"Les Plans 63290 Ch\u00e2teldon Ch\u00e2teldon Auvergne 63290",
    "addr:postcode":"63290;cha\u0302teldon;63290",
    "iso:country":"FR",
    "sg:address":"Les Plans 63290 Ch\u00e2teldon",
    "sg:city":"Ch\u00e2teldon",
    "sg:orig_category":"Non-Classified Establishments",
    "sg:phone":"+33 4 73 94 62 69",
    "sg:postcode":"63290",
    "sg:province":"Auvergne",
    "wof:name":"C.p. Engineering E.u.r.l.",
    "wof:placetype":"venue"
},
  "geometry": {"coordinates":[3.463962,45.910576],"type":"Point"}
}