{
  "type": "Feature",
  "properties": {
    "addr:full":"1, Rue de l'Industrie, 40220 Tarnos Tarnos Aquitaine 40220",
    "addr:housenumber":"1",
    "addr:postcode":"40220;40220",
    "addr:street":"Rue De L'Industrie",
    "iso:country":"FR",
    "sg:address":"1, Rue de l'Industrie, 40220 Tarnos",
    "sg:city":"Tarnos",
    "sg:orig_category":"Unclassifiable Establishments",
    "sg:phone":"+33 5 59 64 66 17",
    "sg:postcode":"40220",
    "sg:province":"Aquitaine",
    "wof:name":"Darrigues S.a.r.l.",
    "wof:placetype":"venue"
},
  "geometry": {"coordinates":[-1.501146,43.540897],"type":"Point"}
}