{
  "type": "Feature",
  "properties": {
    "addr:full":"ZA Pont des Charrettes Uz\u00e8s Languedoc-Roussillon 30700",
    "addr:postcode":"30700",
    "addr:street":"Za Pont Des Charrettes",
    "iso:country":"FR",
    "sg:address":"ZA Pont des Charrettes",
    "sg:city":"Uz\u00e8s",
    "sg:orig_category":"Unclassifiable Establishments",
    "sg:phone":"+33 4 66 03 03 31",
    "sg:postcode":"30700",
    "sg:province":"Languedoc-Roussillon",
    "wof:name":"Elista Languedoc S.a.r.l.",
    "wof:placetype":"venue"
},
  "geometry": {"coordinates":[4.41826,44.008324],"type":"Point"}
}