{
  "type": "Feature",
  "properties": {
    "iso:country":"FR",
    "sg:address":"49 rue des Mathurins 75008 Paris",
    "sg:classifiers":[
        {
            "category":"Travel",
            "subcategory":"Travel Agent",
            "type":"Entertainment"
        }
    ],
    "sg:phone":"+33 1 42 68 68 00",
    "sg:postcode":"75008",
    "sg:province":"Ile de France",
    "sg:tags":[
        "incentive"
    ],
    "wof:name":"Kts Tourisme Voyage Sa",
    "wof:placetype":"venue"
},
  "geometry": {"coordinates":[2.323018,48.87326],"type":"Point"}
}