{
  "type": "Feature",
  "properties": {
    "addr:full":"276, Rte de la Laiterie, 29800 Plouedern Plou\u00e9dern Bretagne 29800",
    "addr:housenumber":"276",
    "addr:postcode":"29800;29800",
    "addr:street":"Rte De La Laiterie;Ploue\u0301Dern",
    "iso:country":"FR",
    "sg:address":"276, Rte de la Laiterie, 29800 Plouedern",
    "sg:city":"Plou\u00e9dern",
    "sg:orig_category":"Non-Classified Establishments",
    "sg:phone":"+33 2 98 20 92 92",
    "sg:postcode":"29800",
    "sg:province":"Bretagne",
    "wof:name":"Rolland S.a.",
    "wof:placetype":"venue"
},
  "geometry": {"coordinates":[-4.247802,48.482594],"type":"Point"}
}