{
  "type": "Feature",
  "properties": {
    "addr:full":"ZA Le Mas d'Agenais Aquitaine 47430",
    "addr:postcode":"47430",
    "addr:street":"Za Le;D'Agenais",
    "iso:country":"FR",
    "sg:address":"ZA",
    "sg:city":"Le Mas d'Agenais",
    "sg:orig_category":"Unclassifiable Establishments",
    "sg:phone":"+33 5 53 89 50 34",
    "sg:postcode":"47430",
    "sg:province":"Aquitaine",
    "wof:name":"M\u00e9tal Mobil S.a.",
    "wof:placetype":"venue"
},
  "geometry": {"coordinates":[0.21426,44.409649],"type":"Point"}
}