{
  "type": "Feature",
  "properties": {
    "addr:full":"201, Av. de Strasbourg, 67170 Brumath Brumath Alsace 67170",
    "addr:housenumber":"201",
    "addr:postcode":"67170;67170",
    "addr:street":"Av. De Strasbourg",
    "iso:country":"FR",
    "sg:address":"201, Av. de Strasbourg, 67170 Brumath",
    "sg:city":"Brumath",
    "sg:orig_category":"Unclassifiable Establishments",
    "sg:phone":"+33 3 88 51 90 03",
    "sg:postcode":"67170",
    "sg:province":"Alsace",
    "wof:name":"Kauffer's Fine Cuisine D'alsace S.a.r.l.",
    "wof:placetype":"venue"
},
  "geometry": {"coordinates":[7.710198,48.706261],"type":"Point"}
}