{
  "type": "Feature",
  "properties": {
    "addr:full":"12 ave Matignon; Paris; 75008 Ile de France 75008",
    "addr:postcode":"75008 ile;france 75008",
    "addr:street":"12 Ave Matignon",
    "iso:country":"FR",
    "sg:address":"12 ave Matignon; Paris; 75008",
    "sg:classifiers":[
        {
            "category":"Banks & Credit Unions",
            "subcategory":"Bank",
            "type":"Services"
        }
    ],
    "sg:phone":"+33 1 44 35 40 40",
    "sg:postcode":"75008",
    "sg:province":"Ile de France",
    "wof:name":"Banque De La Cit\u00e9, Private Stock Bank",
    "wof:placetype":"venue"
},
  "geometry": {"coordinates":[2.313418,48.870644],"type":"Point"}
}