{
  "type": "Feature",
  "properties": {
    "addr:full":"Av. de la Messesselle Nogent le Rotrou Centre 28400",
    "addr:postcode":"28400",
    "addr:street":"Av. De La Messesselle Nogent Le",
    "iso:country":"FR",
    "sg:address":"Av. de la Messesselle",
    "sg:city":"Nogent le Rotrou",
    "sg:orig_category":"Non-Classified Establishments",
    "sg:phone":"+33 2 37 53 50 20",
    "sg:postcode":"28400",
    "sg:province":"Centre",
    "wof:name":"Calpac S.a.",
    "wof:placetype":"venue"
},
  "geometry": {"coordinates":[0.811737,48.330948],"type":"Point"}
}