{
  "type": "Feature",
  "properties": {
    "addr:full":"Rue Bonneret 77230 Moussy Le Neuf Ile de France 77230",
    "addr:postcode":"77230;77230",
    "addr:street":"Rue Bonneret;France",
    "iso:country":"FR",
    "sg:address":"Rue Bonneret 77230 Moussy Le Neuf",
    "sg:classifiers":[
        {
            "category":"Utilities",
            "subcategory":"Electric",
            "type":"Services"
        }
    ],
    "sg:phone":"+33 1 60 03 60 90",
    "sg:postcode":"77230",
    "sg:province":"Ile de France",
    "sg:tags":[
        "electricity",
        "electronic",
        "electrical",
        "equipment"
    ],
    "wof:name":"Artos Engineering France Sarl",
    "wof:placetype":"venue"
},
  "geometry": {"coordinates":[2.595027,49.064198],"type":"Point"}
}