{
  "type": "Feature",
  "properties": {
    "addr:full":"Rte de Bonneville V\u00e9traz Monthoux Rhone-Alpes 74100",
    "addr:postcode":"74100",
    "addr:street":"Rte De Bonneville;Rhone-Alpes",
    "iso:country":"FR",
    "sg:address":"Rte de Bonneville",
    "sg:city":"V\u00e9traz Monthoux",
    "sg:orig_category":"Non-Classified Establishments",
    "sg:phone":"+33 4 50 37 46 72",
    "sg:postcode":"74100",
    "sg:province":"Rhone-Alpes",
    "wof:name":"Escofier Technologie S.a.",
    "wof:placetype":"venue"
},
  "geometry": {"coordinates":[6.244613,46.176716],"type":"Point"}
}