{
  "type": "Feature",
  "properties": {
    "addr:full":"1 Rue De Plas 09000 St Paul De Jarrat Midi Pyr\u00e9n\u00e9es",
    "addr:housenumber":"1",
    "addr:postcode":"09000",
    "addr:street":"Rue De Plas",
    "iso:country":"FR",
    "sg:address":"1 Rue De Plas 09000 St Paul De Jarrat",
    "sg:classifiers":[
        {
            "category":"Professional",
            "type":"Services"
        }
    ],
    "sg:phone":"+33 5 61 64 17 26",
    "sg:province":"Midi Pyr\u00e9n\u00e9es",
    "sg:tags":[
        "transport",
        "road"
    ],
    "wof:name":"Ste Ariegeoise De Transports",
    "wof:placetype":"venue"
},
  "geometry": {"coordinates":[1.659567,42.913277],"type":"Point"}
}