{
  "type": "Feature",
  "properties": {
    "addr:full":"24 rue Murillo; Paris; 75008 Ile de France 75008",
    "addr:housenumber":"24",
    "addr:postcode":"75008 ile;france 75008",
    "addr:street":"Rue Murillo",
    "iso:country":"FR",
    "sg:address":"24 rue Murillo; Paris; 75008",
    "sg:classifiers":[
        {
            "category":"Banks & Credit Unions",
            "subcategory":"Bank",
            "type":"Services"
        }
    ],
    "sg:phone":"+33 1 44 29 80 00",
    "sg:postcode":"75008",
    "sg:province":"Ile de France",
    "wof:name":"Paluel-marmont Banque",
    "wof:placetype":"venue"
},
  "geometry": {"coordinates":[2.306577,48.877918],"type":"Point"}
}