{
  "type": "Feature",
  "properties": {
    "iso:country":"FR",
    "sg:address":"B.P. 34, 67122 Molsheim C\u00e9dex^^18, Rue de Dachstein, 67120 Molsheim",
    "sg:city":"Molsheim",
    "sg:orig_category":"Non-Classified Establishments",
    "sg:phone":"+33 3 88 38 16 44",
    "sg:postcode":"67120",
    "sg:province":"Alsace",
    "wof:name":"Soci\u00e9t\u00e9 Alsacienne De Maroquinerie S.a.",
    "wof:placetype":"venue"
},
  "geometry": {"coordinates":[7.490672,48.540382],"type":"Point"}
}