{
  "type": "Feature",
  "properties": {
    "addr:full":"All\u00e9e Du Bic\u00eatre Amiens Cedex Picardie 80026",
    "addr:postcode":"80026",
    "addr:street":"Alle\u0301E Du Bice\u0302Tre",
    "iso:country":"FR",
    "sg:address":"All\u00e9e Du Bic\u00eatre",
    "sg:city":"Amiens Cedex",
    "sg:classifiers":[
        {
            "category":"Banks & Credit Unions",
            "subcategory":"Financial Services",
            "type":"Services"
        }
    ],
    "sg:phone":"+33 3 22 97 18 18",
    "sg:postcode":"80026",
    "sg:province":"Picardie",
    "sg:tags":[
        "banking",
        "finance",
        "insurance"
    ],
    "wof:name":"Service Departemental D Incendie",
    "wof:placetype":"venue"
},
  "geometry": {"coordinates":[2.284475,49.897411],"type":"Point"}
}