{
  "type": "Feature",
  "properties": {
    "addr:full":"7 bis, Rue Alexnadre Coutureau, 92210 Saint Cloud Ile de France 92210",
    "addr:housenumber":"7 bis",
    "addr:postcode":"92210;92210",
    "addr:street":"Rue Alexnadre Coutureau",
    "iso:country":"FR",
    "sg:address":"7 bis, Rue Alexnadre Coutureau, 92210 Saint Cloud",
    "sg:orig_category":"Non-Classified Establishments",
    "sg:phone":"+33 1 46 02 09 09",
    "sg:postcode":"92210",
    "sg:province":"Ile de France",
    "wof:name":"Avantage F.m. S.a.r.l.",
    "wof:placetype":"venue"
},
  "geometry": {"coordinates":[2.215684,48.845787],"type":"Point"}
}