{
  "type": "Feature",
  "properties": {
    "addr:full":"13, Rue S\u00e9guier, 75006 Paris Ile de France",
    "addr:housenumber":"13",
    "addr:postcode":"75006",
    "addr:street":"Rue Se\u0301Guier",
    "iso:country":"FR",
    "sg:address":"13, Rue S\u00e9guier, 75006 Paris",
    "sg:orig_category":"Unclassifiable Establishments",
    "sg:phone":"+33 1 43 26 84 45",
    "sg:province":"Ile de France",
    "wof:name":"Imprimerie Sigogne S.a.",
    "wof:placetype":"venue"
},
  "geometry": {"coordinates":[2.341907,48.853645],"type":"Point"}
}