{
  "type": "Feature",
  "properties": {
    "addr:full":"Rue Bobby Sands - ZI IV Saint Herblain Pays de Loire 44800",
    "addr:postcode":"44800",
    "addr:street":"Rue Bobby Sands Zi Iv Saint Herblain Pays",
    "iso:country":"FR",
    "sg:address":"Rue Bobby Sands - ZI IV",
    "sg:city":"Saint Herblain",
    "sg:orig_category":"Non-Classified Establishments",
    "sg:phone":"+33 2 40 63 83 78",
    "sg:postcode":"44800",
    "sg:province":"Pays de Loire",
    "wof:name":"Bhr Nantes S.a.r.l.",
    "wof:placetype":"venue"
},
  "geometry": {"coordinates":[-1.654052,47.211758],"type":"Point"}
}