{
  "type": "Feature",
  "properties": {
    "iso:country":"FR",
    "sg:address":"10, Rue de la Procession, 75015 Paris",
    "sg:orig_category":"Non-Classified Establishments",
    "sg:phone":"+33 1 42 19 00 44",
    "sg:province":"Ile de France",
    "wof:name":"L.c.d. Consultants S.a.r.l.",
    "wof:placetype":"venue"
},
  "geometry": {"coordinates":[2.305301,48.839943],"type":"Point"}
}