{
  "type": "Feature",
  "properties": {
    "iso:country":"FR",
    "sg:address":"Av. du Docteur Schinazy",
    "sg:city":"Bordeaux",
    "sg:orig_category":"Unclassifiable Establishments",
    "sg:phone":"+33 5 56 43 54 00",
    "sg:postcode":"33300",
    "sg:province":"Aquitaine",
    "wof:name":"E.i. Aquitaine Nord Travaux S.n.c.",
    "wof:placetype":"venue"
},
  "geometry": {"coordinates":[-0.541467,44.891956],"type":"Point"}
}