{
  "type": "Feature",
  "properties": {
    "iso:country":"FR",
    "sg:address":"Pl Jean Jaur\u00e8s; Maromme; 76150",
    "sg:classifiers":[
        {
            "category":"Banks & Credit Unions",
            "subcategory":"Bank",
            "type":"Services"
        }
    ],
    "sg:phone":"+33 3335741673",
    "sg:postcode":"76150",
    "sg:province":"Haute Normandie",
    "wof:name":"Soci\u00e9t\u00e9 G\u00e9n\u00e9rale",
    "wof:placetype":"venue"
},
  "geometry": {"coordinates":[-97.32923099999999,32.748508],"type":"Point"}
}