{
  "type": "Feature",
  "properties": {
    "addr:full":"76 Rue Du Temple 75003 Paris Ile de France 75003",
    "addr:housenumber":"76",
    "addr:postcode":"75003;75003",
    "addr:street":"Rue Du Temple",
    "iso:country":"FR",
    "sg:address":"76 Rue Du Temple 75003 Paris",
    "sg:classifiers":[
        {
            "category":"Manufacturing",
            "subcategory":"Leather Goods",
            "type":"Manufacturing & Wholesale Goods"
        }
    ],
    "sg:phone":"+33 1 48 87 27 93",
    "sg:postcode":"75003",
    "sg:province":"Ile de France",
    "sg:tags":[
        "shoe"
    ],
    "wof:name":"Amitie",
    "wof:placetype":"venue"
},
  "geometry": {"coordinates":[2.35683,48.861626],"type":"Point"}
}