{
  "type": "Feature",
  "properties": {
    "iso:country":"FR",
    "sg:address":"6, Rue Pablo Picasso - ZA de Gomberville, 78114 Magny les Hameaux",
    "sg:orig_category":"Unclassifiable Establishments",
    "sg:phone":"+33 1 30 52 45 45",
    "sg:province":"Ile de France",
    "wof:name":"Cedrey S.a.r.l.",
    "wof:placetype":"venue"
},
  "geometry": {"coordinates":[2.103455,48.71944],"type":"Point"}
}