{
  "type": "Feature",
  "properties": {
    "iso:country":"FR",
    "sg:address":"Zone Industrielle",
    "sg:city":"Harnes",
    "sg:orig_category":"Unclassifiable Establishments",
    "sg:phone":"+33 3 21 28 76 76",
    "sg:postcode":"62440",
    "sg:province":"Nord Pas-de-Calais",
    "wof:name":"Broutin S.a.",
    "wof:placetype":"venue"
},
  "geometry": {"coordinates":[2.904579,50.444313],"type":"Point"}
}