{
  "type": "Feature",
  "properties": {
    "addr:full":"1, Quartier de l'Etang, 54370 Parroy Lorraine",
    "addr:housenumber":"1",
    "addr:postcode":"54370",
    "addr:street":"Quartier;L'Etang",
    "iso:country":"FR",
    "sg:address":"1, Quartier de l'Etang, 54370 Parroy",
    "sg:orig_category":"Non-Classified Establishments",
    "sg:phone":"+33 3 83 71 30 95",
    "sg:province":"Lorraine",
    "wof:name":"Richard Francis S.a.r.l.",
    "wof:placetype":"venue"
},
  "geometry": {"coordinates":[6.580867,48.67944],"type":"Point"}
}