{
  "type": "Feature",
  "properties": {
    "addr:full":"210 Bd Br\u00e9mont 95320 St Lieu La For\u00eat Ile de France 95320",
    "addr:housenumber":"210",
    "addr:postcode":"95320;ile;95320",
    "addr:street":"Bd Bre\u0301Mont;France",
    "iso:country":"FR",
    "sg:address":"210 Bd Br\u00e9mont 95320 St Lieu La For\u00eat",
    "sg:classifiers":[
        {
            "category":"Home & Garden",
            "subcategory":"Furniture",
            "type":"Retail Goods"
        }
    ],
    "sg:phone":"+33 1 39 95 88 88",
    "sg:postcode":"95320",
    "sg:province":"Ile de France",
    "sg:tags":[
        "household",
        "wood"
    ],
    "wof:name":"Sadim",
    "wof:placetype":"venue"
},
  "geometry": {"coordinates":[1.242107,45.823475],"type":"Point"}
}