{
  "type": "Feature",
  "properties": {
    "iso:country":"FR",
    "sg:address":"162, Bd de Fourmies, 59100 Roubaix",
    "sg:orig_category":"Unclassifiable Establishments",
    "sg:phone":"+33 3 28 33 99 33",
    "sg:province":"Nord Pas-de-Calais",
    "wof:name":"Okaidi S.a.",
    "wof:placetype":"venue"
},
  "geometry": {"coordinates":[3.184065,50.674145],"type":"Point"}
}