{
  "type": "Feature",
  "properties": {
    "iso:country":"FR",
    "sg:address":"B.P. 9, 91263 Juvisy sur Orge C\u00e9dex^^3, Rue Condorcet, 91260 Juvisy sur Orge",
    "sg:orig_category":"Non-Classified Establishments",
    "sg:phone":"+33 1 69 12 16 03",
    "sg:province":"Ile de France",
    "wof:name":"P.g.a. S.a.",
    "wof:placetype":"venue"
},
  "geometry": {"coordinates":[2.37306,48.689716],"type":"Point"}
}