{
  "type": "Feature",
  "properties": {
    "addr:full":"584, Av. de la Fleuride - ZI les Paluds, 13780 Aubagne Provence-Alpes-C\u00f4te d'Azur",
    "addr:postcode":"13780",
    "addr:street":"584 Av. De La Fleuride Zi Les Paluds",
    "iso:country":"FR",
    "sg:address":"584, Av. de la Fleuride - ZI les Paluds, 13780 Aubagne",
    "sg:orig_category":"Unclassifiable Establishments",
    "sg:phone":"+33 4 42 82 07 53",
    "sg:province":"Provence-Alpes-C\u00f4te d'Azur",
    "wof:name":"Alquier S.a.",
    "wof:placetype":"venue"
},
  "geometry": {"coordinates":[5.699832,43.27586],"type":"Point"}
}