{
  "type": "Feature",
  "properties": {
    "iso:country":"FR",
    "sg:address":"32, Grande Rue, 72300 Sabl\u00e9 sur Sarthe",
    "sg:orig_category":"Unclassifiable Establishments",
    "sg:phone":"+33 2 43 92 06 30",
    "sg:province":"Pays de Loire",
    "wof:name":"Adhilettre S.a.r.l.",
    "wof:placetype":"venue"
},
  "geometry": {"coordinates":[-0.332766,47.839642],"type":"Point"}
}