{
  "type": "Feature",
  "properties": {
    "addr:full":"218 R Du Fbg Saint Honor\u00e9 75008 Paris Ile de France 75008",
    "addr:housenumber":"218",
    "addr:postcode":"75008;75008",
    "addr:street":"R Du Fbg Saint Honore\u0301",
    "iso:country":"FR",
    "sg:address":"218 R Du Fbg Saint Honor\u00e9 75008 Paris",
    "sg:classifiers":[
        {
            "category":"Travel",
            "subcategory":"Hotels & Motels",
            "type":"Entertainment"
        }
    ],
    "sg:phone":"+33 1 49 53 03 03",
    "sg:postcode":"75008",
    "sg:province":"Ile de France",
    "sg:tags":[
        "hotels",
        "business",
        "restaurant"
    ],
    "wof:name":"Golden Tulip St Honore",
    "wof:placetype":"venue"
},
  "geometry": {"coordinates":[2.303488,48.87579],"type":"Point"}
}