{
  "type": "Feature",
  "properties": {
    "iso:country":"FR",
    "sg:address":"117 Rue De La Duche 50100 Cherbourg Octeville",
    "sg:city":"Cherbourg-Octeville",
    "sg:orig_category":"Miscellaneous Products",
    "sg:phone":"+33 2 33 53 07 24",
    "sg:postcode":"50100",
    "sg:province":"Basse Normandie",
    "wof:name":"Aux Artisans Marbriers",
    "wof:placetype":"venue"
},
  "geometry": {"coordinates":[-1.633585,49.636917],"type":"Point"}
}