{
  "type": "Feature",
  "properties": {
    "addr:full":"6 Chemin De La Nitri\u00e8re BP 96 26203 Mont\u00e9limar Cedex Franche Comt\u00e9",
    "addr:housenumber":"6;96",
    "addr:postcode":"26203",
    "addr:street":"Chemin De La Nitrie\u0300Re Bp",
    "iso:country":"FR",
    "sg:address":"6 Chemin De La Nitri\u00e8re BP 96 26203 Mont\u00e9limar Cedex",
    "sg:classifiers":[
        {
            "category":"Professional",
            "subcategory":"Engineering",
            "type":"Services"
        }
    ],
    "sg:phone":"+33 4 75 51 04 42",
    "sg:province":"Franche Comt\u00e9",
    "sg:tags":[
        "machine",
        "-",
        "mechanical"
    ],
    "wof:name":"Froid 2607 Sarl",
    "wof:placetype":"venue"
},
  "geometry": {"coordinates":[4.753982,44.570663],"type":"Point"}
}