{
  "type": "Feature",
  "properties": {
    "iso:country":"FR",
    "sg:address":"B.P. 80, 95612 Cergy Pontoise C\u00e9dex^^Av. du Gros Ch\u00eane - Parc des Bellevues, 95610 Eragny",
    "sg:orig_category":"Non-Classified Establishments",
    "sg:phone":"+33 1 34 21 27 00",
    "sg:province":"Ile de France",
    "wof:name":"Spie-trindel S.a.",
    "wof:placetype":"venue"
},
  "geometry": {"coordinates":[2.091,49.019009],"type":"Point"}
}