{
  "type": "Feature",
  "properties": {
    "addr:full":"79, Rue Amp\u00e8re, 75017 Paris Ile de France 75017",
    "addr:housenumber":"79",
    "addr:postcode":"75017;75017",
    "addr:street":"Rue Ampe\u0300Re",
    "iso:country":"FR",
    "sg:address":"79, Rue Amp\u00e8re, 75017 Paris",
    "sg:orig_category":"Non-Classified Establishments",
    "sg:phone":"+33 1 46 22 16 70",
    "sg:postcode":"75017",
    "sg:province":"Ile de France",
    "wof:name":"Amboile Services Sa",
    "wof:placetype":"venue"
},
  "geometry": {"coordinates":[2.299861,48.885174],"type":"Point"}
}