{
  "type": "Feature",
  "properties": {
    "addr:full":"10, Rue Lambert, 59191 Ligny en Cambr\u00e9sis Nord Pas-de-Calais",
    "addr:housenumber":"10",
    "addr:postcode":"59191",
    "addr:street":"Rue Lambert",
    "iso:country":"FR",
    "sg:address":"10, Rue Lambert, 59191 Ligny en Cambr\u00e9sis",
    "sg:orig_category":"Unclassifiable Establishments",
    "sg:phone":"+33 3 27 75 90 36",
    "sg:province":"Nord Pas-de-Calais",
    "wof:name":"Manum\u00e9ca S.a.r.l.",
    "wof:placetype":"venue"
},
  "geometry": {"coordinates":[3.383653,50.099113],"type":"Point"}
}