{
  "type": "Feature",
  "properties": {
    "addr:full":"167, Rue d'Aubenton, 59100 Roubaix Nord Pas-de-Calais",
    "addr:housenumber":"167",
    "addr:postcode":"59100",
    "addr:street":"Rue D'Aubenton",
    "iso:country":"FR",
    "sg:address":"167, Rue d'Aubenton, 59100 Roubaix",
    "sg:orig_category":"Unclassifiable Establishments",
    "sg:phone":"+33 3 20 70 52 73",
    "sg:province":"Nord Pas-de-Calais",
    "wof:name":"Barbe Robert Carrosserie S.a.",
    "wof:placetype":"venue"
},
  "geometry": {"coordinates":[3.176869,50.700592],"type":"Point"}
}