{
  "type": "Feature",
  "properties": {
    "iso:country":"FR",
    "sg:address":"ZI de l'Esp\u00e9rance - Saint Hilaire de Loulay",
    "sg:city":"Montaigu C\u00e9dex",
    "sg:orig_category":"Non-Classified Establishments",
    "sg:phone":"+33 2 51 43 06 00",
    "sg:postcode":"85607",
    "sg:province":"Champagne",
    "wof:name":"Sermo Industrie S.a.",
    "wof:placetype":"venue"
},
  "geometry": {"coordinates":[-1.31272,46.975361],"type":"Point"}
}