{
  "type": "Feature",
  "properties": {
    "iso:country":"FR",
    "sg:address":"23 Rue Du Jard 51100 Reims",
    "sg:classifiers":[
        {
            "category":"Professional",
            "subcategory":"Computer Services",
            "type":"Services"
        }
    ],
    "sg:phone":"+33 3 26 48 33 33",
    "sg:postcode":"51100",
    "sg:province":"Champagne",
    "sg:tags":[
        "information",
        "technology",
        "software"
    ],
    "wof:name":"Jfi Progiciels",
    "wof:placetype":"venue"
},
  "geometry": {"coordinates":[4.033992,49.249744],"type":"Point"}
}