{
  "type": "Feature",
  "properties": {
    "iso:country":"FR",
    "sg:address":"Kerzeven 29400 Locm\u00e9lar",
    "sg:city":"Locm\u00e9lar",
    "sg:orig_category":"Non-Classified Establishments",
    "sg:phone":"+33 2 98 68 06 57",
    "sg:postcode":"29400",
    "sg:province":"Bretagne",
    "wof:name":"Elorn Plants S.a.r.l.",
    "wof:placetype":"venue"
},
  "geometry": {"coordinates":[-4.074319,48.443626],"type":"Point"}
}