{
  "type": "Feature",
  "properties": {
    "addr:full":"525, Rue Serge Clergeot, 60170 Cambronne l\u00e8s Rib\u00e9court Picardie 60170",
    "addr:housenumber":"525",
    "addr:postcode":"60170;60170",
    "addr:street":"Rue Serge Clergeot;Picardie",
    "iso:country":"FR",
    "sg:address":"525, Rue Serge Clergeot, 60170 Cambronne l\u00e8s Rib\u00e9court",
    "sg:orig_category":"FABRICATION DE FONDS BOMB\u00c9S, EMBOUTIS OU REPOUSS\u00c9S, EN ACIER CARBONE OU INOX, D\u00c9COUPAGE ET FORMAGE S",
    "sg:phone":"+33 3 44 76 76 06",
    "sg:postcode":"60170",
    "sg:province":"Picardie",
    "wof:name":"Copri S.a.r.l.",
    "wof:placetype":"venue"
},
  "geometry": {"coordinates":[2.899165,49.50071],"type":"Point"}
}