{
  "type": "Feature",
  "properties": {
    "addr:full":"30, Rue des Fr\u00e8res Lumi\u00e8re - ZI Meaux Nord, 77100 Meaux Ile de France",
    "addr:housenumber":"30",
    "addr:postcode":"77100;ile",
    "addr:street":"Rue Des Fre\u0300Res Lumie\u0300Re Zi",
    "iso:country":"FR",
    "sg:address":"30, Rue des Fr\u00e8res Lumi\u00e8re - ZI Meaux Nord, 77100 Meaux",
    "sg:orig_category":"Non-Classified Establishments",
    "sg:phone":"+33 1 64 34 50 50",
    "sg:province":"Ile de France",
    "wof:name":"Stock Industrie Soudage S.a.r.l.",
    "wof:placetype":"venue"
},
  "geometry": {"coordinates":[2.883054,48.959351],"type":"Point"}
}