{
  "type": "Feature",
  "properties": {
    "addr:full":"9, Rue de la Charit\u00e9, 69002 Lyon Rhone-Alpes",
    "addr:housenumber":"9",
    "addr:postcode":"69002",
    "addr:street":"Rue De La Charite\u0301",
    "iso:country":"FR",
    "sg:address":"9, Rue de la Charit\u00e9, 69002 Lyon",
    "sg:orig_category":"Unclassifiable Establishments",
    "sg:phone":"+33 4 78 42 09 82",
    "sg:province":"Rhone-Alpes",
    "wof:name":"Etablissement Pierre Ginet S.a.",
    "wof:placetype":"venue"
},
  "geometry": {"coordinates":[4.832463,45.754227],"type":"Point"}
}