{
  "type": "Feature",
  "properties": {
    "addr:full":"16 Rue Nationale 95260 Beaumont Sur Oise Ile de France 95260",
    "addr:housenumber":"16",
    "addr:postcode":"95260;95260",
    "addr:street":"Rue Nationale",
    "iso:country":"FR",
    "sg:address":"16 Rue Nationale 95260 Beaumont Sur Oise",
    "sg:classifiers":[
        {
            "category":"Banks & Credit Unions",
            "subcategory":"Financial Services",
            "type":"Services"
        }
    ],
    "sg:phone":"+33 1 39 37 42 00",
    "sg:postcode":"95260",
    "sg:province":"Ile de France",
    "sg:tags":[
        "banking",
        "insurance",
        "institution",
        "finance"
    ],
    "wof:name":"Banque De France",
    "wof:placetype":"venue"
},
  "geometry": {"coordinates":[2.285422,49.144028],"type":"Point"}
}