{
  "type": "Feature",
  "properties": {
    "iso:country":"FR",
    "sg:address":"Rte de la Cave",
    "sg:city":"Calvisson",
    "sg:orig_category":"Unclassifiable Establishments",
    "sg:phone":"+33 4 66 01 20 21",
    "sg:postcode":"30420",
    "sg:province":"Languedoc-Roussillon",
    "wof:name":"Les Vignerons De Calvisson",
    "wof:placetype":"venue"
},
  "geometry": {"coordinates":[4.197743,43.781845],"type":"Point"}
}