{
  "type": "Feature",
  "properties": {
    "iso:country":"FR",
    "sg:address":"1 rue Dewoitine 78140 Velizy Villacoublay",
    "sg:classifiers":[
        {
            "category":"Transit Center",
            "subcategory":"Passenger",
            "type":"Transportation"
        }
    ],
    "sg:phone":"+33 1 30 70 70 70",
    "sg:province":"Ile de France",
    "sg:tags":[
        "lift",
        "elevator"
    ],
    "wof:name":"Schindler Sa",
    "wof:placetype":"venue"
},
  "geometry": {"coordinates":[2.215509,48.783005],"type":"Point"}
}