{
  "type": "Feature",
  "properties": {
    "addr:full":"8A, Av Gustave Dolfus, 68400 Riedisheim Riedisheim Alsace 68400",
    "addr:postcode":"68400;68400",
    "addr:street":"Av Gustave Dolfus;Riedisheim",
    "iso:country":"FR",
    "sg:address":"8A, Av Gustave Dolfus, 68400 Riedisheim",
    "sg:city":"Riedisheim",
    "sg:orig_category":"Non-Classified Establishments",
    "sg:phone":"+33 3 89 65 05 75",
    "sg:postcode":"68400",
    "sg:province":"Alsace",
    "wof:name":"Atoll Photographie S.a.r.l.",
    "wof:placetype":"venue"
},
  "geometry": {"coordinates":[7.35846,47.746944],"type":"Point"}
}