{
  "type": "Feature",
  "properties": {
    "addr:full":"CD 2 Camp Major - Espace Galaxie Aubagne Provence-Alpes-C\u00f4te d'Azur 13400",
    "addr:housenumber":"2",
    "addr:postcode":"13400",
    "addr:street":"Cd;Aubagne",
    "iso:country":"FR",
    "sg:address":"CD 2 Camp Major - Espace Galaxie",
    "sg:city":"Aubagne",
    "sg:orig_category":"Unclassifiable Establishments",
    "sg:phone":"+33 4 42 18 76 00",
    "sg:postcode":"13400",
    "sg:province":"Provence-Alpes-C\u00f4te d'Azur",
    "wof:name":"Sud Est D\u00e9cor S.a.",
    "wof:placetype":"venue"
},
  "geometry": {"coordinates":[5.5687,43.292141],"type":"Point"}
}