{
  "type": "Feature",
  "properties": {
    "addr:full":"Sayat 63530 Sayat Sayat Auvergne 63530",
    "addr:postcode":"63530;sayat;63530",
    "iso:country":"FR",
    "sg:address":"Sayat 63530 Sayat",
    "sg:city":"Sayat",
    "sg:classifiers":[
        {
            "category":"Wholesale",
            "subcategory":"Plants",
            "type":"Manufacturing & Wholesale Goods"
        }
    ],
    "sg:phone":"+33 4 73 62 81 81",
    "sg:postcode":"63530",
    "sg:province":"Auvergne",
    "sg:tags":[
        "plants",
        "dairy",
        "turnkey"
    ],
    "wof:name":"Ste Laitiere Dischamp Sa",
    "wof:placetype":"venue"
},
  "geometry": {"coordinates":[3.025296,45.837345],"type":"Point"}
}