{
  "type": "Feature",
  "properties": {
    "addr:full":"B.P. 7431 Bruz Bretagne 35170",
    "addr:postcode":"35170",
    "addr:street":"B.P. 7431;Bretagne",
    "iso:country":"FR",
    "sg:address":"B.P. 7431",
    "sg:city":"Bruz",
    "sg:orig_category":"Non-Classified Establishments",
    "sg:phone":"+33 2 99 77 16 16",
    "sg:postcode":"35170",
    "sg:province":"Bretagne",
    "wof:name":"Dolfrance S.a.",
    "wof:placetype":"venue"
},
  "geometry": {"coordinates":[-1.773184,48.006374],"type":"Point"}
}