{
  "type": "Feature",
  "properties": {
    "addr:full":"168 Rte St. Joseph; Nantes Midi Pyr\u00e9n\u00e9es",
    "addr:housenumber":"168",
    "addr:street":"Rte St. Joseph",
    "iso:country":"FR",
    "sg:address":"168 Rte St. Joseph; Nantes",
    "sg:classifiers":[
        {
            "category":"Banks & Credit Unions",
            "subcategory":"Bank",
            "type":"Services"
        }
    ],
    "sg:phone":"+33 3340931503",
    "sg:province":"Midi Pyr\u00e9n\u00e9es",
    "wof:name":"Financo, Agence De Nantes",
    "wof:placetype":"venue"
},
  "geometry": {"coordinates":[-1.533893,47.242954],"type":"Point"}
}