{
  "type": "Feature",
  "properties": {
    "addr:full":"01130 Les Neyrolles Rhone-Alpes 01130",
    "addr:postcode":"01130;01130",
    "addr:street":"Neyrolles Rhone-Alpes",
    "iso:country":"FR",
    "sg:address":"01130 Les Neyrolles",
    "sg:classifiers":[
        {
            "category":"Manufacturing",
            "subcategory":"Rubber & Plastics",
            "type":"Manufacturing & Wholesale Goods"
        }
    ],
    "sg:phone":"+33 4 74 75 03 94",
    "sg:postcode":"01130",
    "sg:province":"Rhone-Alpes",
    "wof:name":"Etablissements Louis Germain",
    "wof:placetype":"venue"
},
  "geometry": {"coordinates":[5.63205,46.141331],"type":"Point"}
}