{
  "type": "Feature",
  "properties": {
    "iso:country":"FR",
    "sg:address":"47500 Sauveterre la L\u00e9mance",
    "sg:city":"Blanquefort-sur-Briolance",
    "sg:orig_category":"Unclassifiable Establishments",
    "sg:phone":"+33 5 53 40 62 05",
    "sg:postcode":"47500",
    "sg:province":"Aquitaine",
    "wof:name":"Le Gant Rigaudy S.a.",
    "wof:placetype":"venue"
},
  "geometry": {"coordinates":[1.012324,44.590363],"type":"Point"}
}