{
  "type": "Feature",
  "properties": {
    "iso:country":"FR",
    "sg:address":"6 Pl De L'Ander 15100 St Flour",
    "sg:city":"Soulages",
    "sg:classifiers":[
        {
            "category":"Building & Trades",
            "subcategory":"Construction",
            "type":"Services"
        }
    ],
    "sg:phone":"+33 4 71 60 90 66",
    "sg:postcode":"15100",
    "sg:province":"Auvergne",
    "sg:tags":[
        "work",
        "public"
    ],
    "wof:name":"Roziere Tp Sarl",
    "wof:placetype":"venue"
},
  "geometry": {"coordinates":[3.040169,45.051247],"type":"Point"}
}