{
  "type": "Feature",
  "properties": {
    "iso:country":"FR",
    "sg:address":"ZI de Grangeneuve 26800 Portes les Valence",
    "sg:classifiers":[
        {
            "category":"Wholesale",
            "subcategory":"Auto Parts",
            "type":"Manufacturing & Wholesale Goods"
        }
    ],
    "sg:phone":"+33 4 75 57 25 05",
    "sg:postcode":"26800",
    "sg:province":"Rhone-Alpes",
    "sg:tags":[
        "machine",
        "lift",
        "truck",
        "conveyor"
    ],
    "wof:name":"Framatecq Rhones-alpes S.a.",
    "wof:placetype":"venue"
},
  "geometry": {"coordinates":[4.87721,44.876316],"type":"Point"}
}