{
  "type": "Feature",
  "properties": {
    "iso:country":"FR",
    "sg:address":"16 rue Henri Turner 31100 Toulouse",
    "sg:classifiers":[
        {
            "category":"Banks & Credit Unions",
            "subcategory":"Investment Brokerage",
            "type":"Services"
        }
    ],
    "sg:phone":"+33 5 61 43 91 92",
    "sg:postcode":"31100",
    "sg:province":"Midi Pyr\u00e9n\u00e9es",
    "sg:tags":[
        "equestrian",
        "items",
        "accessory",
        "equipment",
        "harness",
        "riding"
    ],
    "wof:name":"Equi Diffusion 2 Snc",
    "wof:placetype":"venue"
},
  "geometry": {"coordinates":[1.407268,43.551815],"type":"Point"}
}