{
  "type": "Feature",
  "properties": {
    "iso:country":"FR",
    "sg:address":"Rte De La Daleure 38590 St Etienne De St Geoirs",
    "sg:classifiers":[
        {
            "category":"Shopping",
            "subcategory":"Crafts & Fabrics",
            "type":"Retail Goods"
        }
    ],
    "sg:phone":"+33 4 76 65 40 04",
    "sg:postcode":"38590",
    "sg:province":"Rhone-Alpes",
    "sg:tags":[
        "textile",
        "clothing"
    ],
    "wof:name":"Tissage Bonvallet Sa",
    "wof:placetype":"venue"
},
  "geometry": {"coordinates":[5.343575,45.343178],"type":"Point"}
}