{
  "type": "Feature",
  "properties": {
    "iso:country":"FR",
    "sg:address":"Za De Troyalac H 29170 St Evarzec",
    "sg:city":"Fouesnant",
    "sg:classifiers":[
        {
            "category":"Professional",
            "subcategory":"Engineering",
            "type":"Services"
        }
    ],
    "sg:phone":"+33 2 98 94 84 00",
    "sg:postcode":"29170",
    "sg:province":"Bretagne",
    "sg:tags":[
        "machine",
        "-",
        "mechanical"
    ],
    "wof:name":"Emballage Technologies",
    "wof:placetype":"venue"
},
  "geometry": {"coordinates":[-4.021977,47.936459],"type":"Point"}
}