{
  "type": "Feature",
  "properties": {
    "addr:full":"B.P. 31, 84110 Vaison la Romaine^^Av. Marcel Pagnol, 84110 Vaison la Romaine Pays de Loire",
    "addr:postcode":"84110;84110",
    "addr:street":"B.P. 31;Marcel Pagnol;La Romaine",
    "iso:country":"FR",
    "sg:address":"B.P. 31, 84110 Vaison la Romaine^^Av. Marcel Pagnol, 84110 Vaison la Romaine",
    "sg:orig_category":"Non-Classified Establishments",
    "sg:phone":"+33 4 90 36 02 59",
    "sg:province":"Pays de Loire",
    "wof:name":"Entreprise De Travaux Publics Teyssier P\u00e8re Et Fils S.a.",
    "wof:placetype":"venue"
},
  "geometry": {"coordinates":[5.008068,44.190483],"type":"Point"}
}