{
  "type": "Feature",
  "properties": {
    "addr:full":"10, Bd Paul Verley, 59140 Dunkerque Nord Pas-de-Calais",
    "addr:housenumber":"10",
    "addr:postcode":"59140",
    "addr:street":"Bd Paul Verley",
    "iso:country":"FR",
    "sg:address":"10, Bd Paul Verley, 59140 Dunkerque",
    "sg:orig_category":"Non-Classified Establishments",
    "sg:phone":"+33 3 28 59 34 00",
    "sg:province":"Nord Pas-de-Calais",
    "wof:name":"Nord Protection Proviacom S.a.r.l. -(protection Vid\u00e9o Alarme Communication)",
    "wof:placetype":"venue"
},
  "geometry": {"coordinates":[2.383842,51.040695],"type":"Point"}
}