{
  "type": "Feature",
  "properties": {
    "addr:full":"2 Av De Bellevue 93220 Gagny Ile de France 93220",
    "addr:postcode":"93220;93220",
    "addr:street":"Av De Bellevue",
    "iso:country":"FR",
    "sg:address":"2 Av De Bellevue 93220 Gagny",
    "sg:classifiers":[
        {
            "category":"Professional",
            "subcategory":"Business Services",
            "type":"Services"
        }
    ],
    "sg:phone":"+33 1 43 30 42 00",
    "sg:postcode":"93220",
    "sg:province":"Ile de France",
    "sg:tags":[
        "body",
        "advice"
    ],
    "wof:name":"Arpi Montguichet",
    "wof:placetype":"venue"
},
  "geometry": {"coordinates":[2.557626,48.884403],"type":"Point"}
}