{
  "type": "Feature",
  "properties": {
    "iso:country":"FR",
    "sg:address":"B.P. 59, 67460 Souffelweyersheim^^32, Rue des Tuileries - ZA de la Souffel, 67460 Souffelweyersheim",
    "sg:city":"Souffelweyersheim",
    "sg:orig_category":"Non-Classified Establishments",
    "sg:phone":"+33 3 88 20 96 11",
    "sg:postcode":"67460",
    "sg:province":"Alsace",
    "wof:name":"Toiles Industrielles Du Rhin S.a.",
    "wof:placetype":"venue"
},
  "geometry": {"coordinates":[7.74147,48.635509],"type":"Point"}
}