{
  "type": "Feature",
  "properties": {
    "addr:full":"2 R Du Bicentenaire 59780 Willems Nord Pas-de-Calais",
    "addr:housenumber":"2",
    "addr:postcode":"59780",
    "addr:street":"R Du Bicentenaire",
    "iso:country":"FR",
    "sg:address":"2 R Du Bicentenaire 59780 Willems",
    "sg:classifiers":[
        {
            "category":"Manufacturing",
            "subcategory":"Printing",
            "type":"Manufacturing & Wholesale Goods"
        }
    ],
    "sg:phone":"+33 3 20 61 77 00",
    "sg:province":"Nord Pas-de-Calais",
    "sg:tags":[
        "publishing"
    ],
    "wof:name":"Skyflex Sarl",
    "wof:placetype":"venue"
},
  "geometry": {"coordinates":[3.235095,50.628727],"type":"Point"}
}