{
  "type": "Feature",
  "properties": {
    "iso:country":"FR",
    "sg:address":"7, Rue Alfred Kastler, 14000 Caen",
    "sg:city":"Caen",
    "sg:orig_category":"Unclassifiable Establishments",
    "sg:phone":"+33 2 31 46 26 53",
    "sg:postcode":"14000",
    "sg:province":"Basse Normandie",
    "wof:name":"B.r.d. T\u00e9l\u00e9secr\u00e9tariat Trilingue - Brigitte Rouget Deleuze T\u00e9l\u00e9secr\u00e9tariat Trilingue",
    "wof:placetype":"venue"
},
  "geometry": {"coordinates":[-0.392205,49.202225],"type":"Point"}
}