{
  "type": "Feature",
  "properties": {
    "addr:full":"Zi Du Prunay Rue Jean-Pierre Timbaud BP 134 78500 Sartrouville Ile de France 78500",
    "addr:housenumber":"134",
    "addr:postcode":"78500;ile;78500",
    "addr:street":"Zi Du Prunay Rue Jean-Pierre Timbaud Bp;France",
    "iso:country":"FR",
    "sg:address":"Zi Du Prunay",
    "sg:city":"Rue Jean-Pierre Timbaud BP 134 78500 Sartrouville",
    "sg:classifiers":[
        {
            "category":"Manufacturing",
            "subcategory":"Metals",
            "type":"Manufacturing & Wholesale Goods"
        }
    ],
    "sg:phone":"+33 1 61 04 22 60",
    "sg:postcode":"78500",
    "sg:province":"Ile de France",
    "sg:tags":[
        "-",
        "machine",
        "equipment",
        "engineering",
        "machinery",
        "mechanical"
    ],
    "wof:name":"Rene Clement Forage Sa",
    "wof:placetype":"venue"
},
  "geometry": {"coordinates":[2.194966,48.949272],"type":"Point"}
}