{
  "type": "Feature",
  "properties": {
    "addr:full":"10, Rue aux Saussaies des Dames, 57950 Montigny l\u00e8s Metz Nord Pas-de-Calais",
    "addr:housenumber":"10",
    "addr:postcode":"57950",
    "addr:street":"Rue Aux Saussaies Des Dames",
    "iso:country":"FR",
    "sg:address":"10, Rue aux Saussaies des Dames, 57950 Montigny l\u00e8s Metz",
    "sg:orig_category":"Non-Classified Establishments",
    "sg:phone":"+33 3 87 66 93 33",
    "sg:province":"Nord Pas-de-Calais",
    "wof:name":"Papeterie Boucton",
    "wof:placetype":"venue"
},
  "geometry": {"coordinates":[6.144953,49.103233],"type":"Point"}
}