{
  "type": "Feature",
  "properties": {
    "addr:full":"B.P. 131, 69151 D\u00e9cines Charpieu C\u00e9dex^^34/36, Chemin des Bruy\u00e8res, 69150 D\u00e9cines Charpieu Rhone-Alpes 69150",
    "addr:housenumber":"b.p. 131;36",
    "addr:postcode":"69151;69150;69150",
    "addr:street":"Chemin Des Bruye\u0300Res;Rhone-Alpes",
    "iso:country":"FR",
    "sg:address":"B.P. 131, 69151 D\u00e9cines Charpieu C\u00e9dex^^34/36, Chemin des Bruy\u00e8res, 69150 D\u00e9cines Charpieu",
    "sg:orig_category":"Non-Classified Establishments",
    "sg:phone":"+33 4 78 49 26 67",
    "sg:postcode":"69150",
    "sg:province":"Rhone-Alpes",
    "wof:name":"A.m.c. S.a. - Ateliers Michaud Et Compagnie Et Trilland R\u00e9unis",
    "wof:placetype":"venue"
},
  "geometry": {"coordinates":[4.95911,45.770794],"type":"Point"}
}