{
  "type": "Feature",
  "properties": {
    "addr:full":"Bd Georges Milville 27300 Bernay Haute Normandie 27300",
    "addr:postcode":"27300;27300",
    "addr:street":"Bd Georges Milville;Haute Normandie",
    "iso:country":"FR",
    "sg:address":"Bd Georges Milville 27300 Bernay",
    "sg:classifiers":[
        {
            "category":"Manufacturing",
            "subcategory":"Chemicals & Compounds",
            "type":"Manufacturing & Wholesale Goods"
        }
    ],
    "sg:phone":"+33 2 32 47 36 00",
    "sg:postcode":"27300",
    "sg:province":"Haute Normandie",
    "sg:tags":[
        "pharmaceutical",
        "chemistry",
        "-",
        "cosmetic",
        "by-product"
    ],
    "wof:name":"Aerochim",
    "wof:placetype":"venue"
},
  "geometry": {"coordinates":[0.610155,49.091759],"type":"Point"}
}