{
  "type": "Feature",
  "properties": {
    "addr:full":"Zi Estagnol 11200 L\u00e9zignan Corbi\u00e8res Languedoc-Roussillon",
    "addr:postcode":"11200",
    "addr:street":"Estagnol",
    "iso:country":"FR",
    "sg:address":"Zi Estagnol 11200 L\u00e9zignan Corbi\u00e8res",
    "sg:classifiers":[
        {
            "category":"Professional",
            "type":"Services"
        }
    ],
    "sg:phone":"+33 4 68 27 18 20",
    "sg:province":"Languedoc-Roussillon",
    "sg:tags":[
        "transport",
        "road"
    ],
    "wof:name":"Meditrans",
    "wof:placetype":"venue"
},
  "geometry": {"coordinates":[2.75713,43.20089],"type":"Point"}
}