{
  "type": "Feature",
  "properties": {
    "addr:full":"B.P. 38, 60105 Creil C\u00e9dex^^Rue Charles Somasco, 60180 Nogent sur Oise Picardie",
    "addr:postcode":"60105;60180",
    "addr:street":"B.P. 38;Ce\u0301Dex^^Rue Charles Somasco",
    "iso:country":"FR",
    "sg:address":"B.P. 38, 60105 Creil C\u00e9dex^^Rue Charles Somasco, 60180 Nogent sur Oise",
    "sg:orig_category":"Non-Classified Establishments",
    "sg:phone":"+33 3 44 55 08 09",
    "sg:province":"Picardie",
    "wof:name":"Lenormant Manutention S.a.",
    "wof:placetype":"venue"
},
  "geometry": {"coordinates":[2.46198,49.278976],"type":"Point"}
}