{
  "type": "Feature",
  "properties": {
    "addr:full":"1 ter, Rue du Moulin Neuf, 93240 Stains Ile de France",
    "addr:housenumber":"1 ter",
    "addr:postcode":"93240;ile",
    "addr:street":"Rue Du Moulin Neuf",
    "iso:country":"FR",
    "sg:address":"1 ter, Rue du Moulin Neuf, 93240 Stains",
    "sg:orig_category":"Unclassifiable Establishments",
    "sg:phone":"+33 1 48 29 03 98",
    "sg:province":"Ile de France",
    "wof:name":"Asercom S.a.r.l.",
    "wof:placetype":"venue"
},
  "geometry": {"coordinates":[2.39275,48.95155],"type":"Point"}
}