{
  "type": "Feature",
  "properties": {
    "iso:country":"FR",
    "sg:address":"11, Rue Sadi Carnot, 02300 Bl\u00e9rancourt",
    "sg:orig_category":"Unclassifiable Establishments",
    "sg:phone":"+33 3 23 39 60 12",
    "sg:province":"Picardie",
    "wof:name":"Le Temps Des Fleurs S.a.r.l.",
    "wof:placetype":"venue"
},
  "geometry": {"coordinates":[3.150159,49.517376],"type":"Point"}
}