{
  "type": "Feature",
  "properties": {
    "addr:full":"17 R Du Gal Leclerc 78000 Versailles Ile de France 78000",
    "addr:housenumber":"17",
    "addr:postcode":"78000;78000",
    "addr:street":"R Du Gal Leclerc",
    "iso:country":"FR",
    "sg:address":"17 R Du Gal Leclerc 78000 Versailles",
    "sg:classifiers":[
        {
            "category":"Professional",
            "subcategory":"Advertising",
            "type":"Services"
        }
    ],
    "sg:phone":"+33 1 39 24 84 44",
    "sg:postcode":"78000",
    "sg:province":"Ile de France",
    "sg:tags":[
        "information",
        "medium",
        "communication"
    ],
    "wof:name":"Manchette Publicite",
    "wof:placetype":"venue"
},
  "geometry": {"coordinates":[2.126308,48.799255],"type":"Point"}
}