{
  "type": "Feature",
  "properties": {
    "iso:country":"FR",
    "sg:address":"19, Rue de la Glaci\u00e8re, 67300 Schiltigheim",
    "sg:city":"Schiltigheim",
    "sg:orig_category":"Non-Classified Establishments",
    "sg:phone":"+33 3 88 81 30 60",
    "sg:postcode":"67300",
    "sg:province":"Alsace",
    "wof:name":"Actua S.a.",
    "wof:placetype":"venue"
},
  "geometry": {"coordinates":[7.756708,48.605534],"type":"Point"}
}