{
  "type": "Feature",
  "properties": {
    "addr:full":"19, Rue de la Glaci\u00e8re, 67300 Schiltigheim Schiltigheim Alsace 67300",
    "addr:housenumber":"19",
    "addr:postcode":"67300;67300",
    "addr:street":"Rue De La Glacie\u0300Re",
    "iso:country":"FR",
    "sg:address":"19, Rue de la Glaci\u00e8re, 67300 Schiltigheim",
    "sg:city":"Schiltigheim",
    "sg:orig_category":"Non-Classified Establishments",
    "sg:phone":"+33 3 88 81 30 60",
    "sg:postcode":"67300",
    "sg:province":"Alsace",
    "wof:name":"Actua S.a.",
    "wof:placetype":"venue"
},
  "geometry": {"coordinates":[7.756708,48.605534],"type":"Point"}
}