{
  "type": "Feature",
  "properties": {
    "iso:country":"FR",
    "sg:address":"1 Place De Richelieu 85400 Lucon",
    "sg:classifiers":[
        {
            "category":"Food Court",
            "type":"Food & Drink"
        }
    ],
    "sg:phone":"+33 2 51 56 11 48",
    "sg:postcode":"85400",
    "sg:province":"Pays de Loire",
    "sg:tags":[
        "product",
        "related"
    ],
    "wof:name":"Societe H Vrignaud Et Fils",
    "wof:placetype":"venue"
},
  "geometry": {"coordinates":[-1.167466,46.45462],"type":"Point"}
}