{
  "type": "Feature",
  "properties": {
    "iso:country":"FR",
    "sg:address":"La Clielle 79270 Frontenay Rohan Rohan",
    "sg:classifiers":[
        {
            "category":"Professional",
            "type":"Services"
        }
    ],
    "sg:phone":"+33 5 49 04 60 22",
    "sg:postcode":"79270",
    "sg:province":"Poitou-Charentes",
    "sg:tags":[
        "transport",
        "road"
    ],
    "wof:name":"Transports Genty Sa",
    "wof:placetype":"venue"
},
  "geometry": {"coordinates":[-0.525983,46.261223],"type":"Point"}
}