{
  "type": "Feature",
  "properties": {
    "addr:full":"Montdauphin Gare Eygliers Aquitaine 05600",
    "addr:postcode":"05600",
    "iso:country":"FR",
    "sg:address":"Montdauphin Gare",
    "sg:city":"Eygliers",
    "sg:orig_category":"Non-Classified Establishments",
    "sg:phone":"+33 4 92 45 07 10",
    "sg:postcode":"05600",
    "sg:province":"Aquitaine",
    "wof:name":"Gu\u00e9rin S.a.",
    "wof:placetype":"venue"
},
  "geometry": {"coordinates":[6.616996,44.675369],"type":"Point"}
}