{
  "type": "Feature",
  "properties": {
    "iso:country":"FR",
    "sg:address":"13, Rue des Champs Corbilly, 94700 Maisons Alfort",
    "sg:orig_category":"Unclassifiable Establishments",
    "sg:phone":"+33 1 41 79 10 00",
    "sg:province":"Ile de France",
    "wof:name":"Imprimerie Bardet L S.a.r.l.",
    "wof:placetype":"venue"
},
  "geometry": {"coordinates":[2.441594,48.806644],"type":"Point"}
}