{
  "type": "Feature",
  "properties": {
    "iso:country":"FR",
    "sg:address":"40 Quai De Dion Bouton 92806 Puteaux",
    "sg:classifiers":[
        {
            "category":"Professional",
            "subcategory":"Advertising",
            "type":"Services"
        }
    ],
    "sg:phone":"+33 1 46 93 35 66",
    "sg:province":"Centre",
    "sg:tags":[
        "communication",
        "medium"
    ],
    "wof:name":"Mpg",
    "wof:placetype":"venue"
},
  "geometry": {"coordinates":[2.246716,48.882084],"type":"Point"}
}