{
  "type": "Feature",
  "properties": {
    "addr:full":"B.P. 266, 73375 Le Bourget du Lac^^ZI Savoie Technolac - B\u00e2t. Ath\u00e9na, 73370 Le Bourget du Lac Rhone-Alpes",
    "addr:housenumber":"b.p. 266;ba\u0302t",
    "addr:postcode":"73375;73370",
    "iso:country":"FR",
    "sg:address":"B.P. 266, 73375 Le Bourget du Lac^^ZI Savoie Technolac - B\u00e2t. Ath\u00e9na, 73370 Le Bourget du Lac",
    "sg:orig_category":"Non-Classified Establishments",
    "sg:phone":"+33 4 79 26 50 00",
    "sg:province":"Rhone-Alpes",
    "wof:name":"Pietercil Interco S.a.",
    "wof:placetype":"venue"
},
  "geometry": {"coordinates":[5.86225,45.643875],"type":"Point"}
}