{
  "type": "Feature",
  "properties": {
    "iso:country":"FR",
    "sg:address":"24 Rue Monsieur Le Prince 75006 Paris",
    "sg:classifiers":[
        {
            "category":"Manufacturing",
            "subcategory":"Printing",
            "type":"Manufacturing & Wholesale Goods"
        }
    ],
    "sg:phone":"+33 1 43 26 73 40",
    "sg:province":"Ile de France",
    "sg:tags":[
        "publishing"
    ],
    "wof:name":"Sarl Imprimerie Monsieur Le Prince",
    "wof:placetype":"venue"
},
  "geometry": {"coordinates":[2.339902,48.849648],"type":"Point"}
}