{
  "type": "Feature",
  "properties": {
    "iso:country":"FR",
    "sg:address":"La Croix Verte 01290 Gri\u00e8ges",
    "sg:orig_category":"Unclassifiable Establishments",
    "sg:phone":"+33 3 85 36 25 45",
    "sg:province":"Rhone-Alpes",
    "wof:name":"Entreprise Evangelista Carlos",
    "wof:placetype":"venue"
},
  "geometry": {"coordinates":[4.846845,46.252609],"type":"Point"}
}