{
  "type": "Feature",
  "properties": {
    "addr:full":"127, Rue Cl\u00e9ment Ader - ZI, 51470 Saint Memmie Champagne",
    "addr:housenumber":"127",
    "addr:postcode":"51470",
    "addr:street":"Rue Cle\u0301Ment Ader Zi",
    "iso:country":"FR",
    "sg:address":"127, Rue Cl\u00e9ment Ader - ZI, 51470 Saint Memmie",
    "sg:orig_category":"Unclassifiable Establishments",
    "sg:phone":"+33 3 26 65 73 26",
    "sg:province":"Champagne",
    "wof:name":"Janson S.a.",
    "wof:placetype":"venue"
},
  "geometry": {"coordinates":[4.384128,48.954563],"type":"Point"}
}