{
  "type": "Feature",
  "properties": {
    "iso:country":"FR",
    "sg:address":"21 Bd Gambetta 92136 Issy Les Moulineaux Cedex",
    "sg:city":"Moulineaux",
    "sg:classifiers":[
        {
            "category":"Professional",
            "subcategory":"Advertising",
            "type":"Services"
        }
    ],
    "sg:phone":"+33 1 40 95 25 00",
    "sg:postcode":"76530",
    "sg:province":"Haute Normandie",
    "sg:tags":[
        "marketing",
        "medium",
        "communication"
    ],
    "wof:name":"Cpm",
    "wof:placetype":"venue"
},
  "geometry": {"coordinates":[2.27664,48.827633],"type":"Point"}
}