{
  "type": "Feature",
  "properties": {
    "addr:full":"6, Bd de l'Industrie, 85170 Belleville sur Vie Pays de Loire",
    "addr:housenumber":"6",
    "addr:postcode":"85170",
    "addr:street":"Bd De L'Industrie;Vie",
    "iso:country":"FR",
    "sg:address":"6, Bd de l'Industrie, 85170 Belleville sur Vie",
    "sg:orig_category":"Unclassifiable Establishments",
    "sg:phone":"+33 2 51 41 06 00",
    "sg:province":"Pays de Loire",
    "wof:name":"Novadal-privat S.a.r.l.",
    "wof:placetype":"venue"
},
  "geometry": {"coordinates":[-1.434393,46.78759],"type":"Point"}
}