{
  "type": "Feature",
  "properties": {
    "iso:country":"FR",
    "sg:address":"Rue Amp\u00e8re 03300 Cusset",
    "sg:city":"Cusset",
    "sg:classifiers":[
        {
            "category":"Professional",
            "subcategory":"Engineering",
            "type":"Services"
        }
    ],
    "sg:phone":"+33 4 70 98 42 42",
    "sg:postcode":"03300",
    "sg:province":"Auvergne",
    "sg:tags":[
        "electric",
        "-",
        "component",
        "machine",
        "mechanical",
        "electronic"
    ],
    "wof:name":"Lescure Sa",
    "wof:placetype":"venue"
},
  "geometry": {"coordinates":[3.437585,46.139801],"type":"Point"}
}