{
  "type": "Feature",
  "properties": {
    "addr:full":"24, Rue des Moulins, 95110 Sannois Ile de France",
    "addr:housenumber":"24",
    "addr:postcode":"95110;ile",
    "addr:street":"Rue Des Moulins",
    "iso:country":"FR",
    "sg:address":"24, Rue des Moulins, 95110 Sannois",
    "sg:orig_category":"Unclassifiable Establishments",
    "sg:phone":"+33 1 34 10 91 00",
    "sg:province":"Ile de France",
    "wof:name":"C.m.s. S.a. - Contr\u00f4le Machines Services",
    "wof:placetype":"venue"
},
  "geometry": {"coordinates":[2.243757,48.968353],"type":"Point"}
}