{
  "type": "Feature",
  "properties": {
    "iso:country":"FR",
    "sg:address":"Route D\u00e9partementale 108 - ZAC de Valentin",
    "sg:city":"Ch\u00e2tillon le Duc",
    "sg:orig_category":"Unclassifiable Establishments",
    "sg:phone":"+33 3 81 80 39 29",
    "sg:postcode":"25870",
    "sg:province":"Franche Comt\u00e9",
    "wof:name":"G.s.f. Orion S.a. - Groupe Services France",
    "wof:placetype":"venue"
},
  "geometry": {"coordinates":[6.006115,47.308216],"type":"Point"}
}