{
  "type": "Feature",
  "properties": {
    "iso:country":"FR",
    "sg:address":"857, Av. L\u00e9on Blum, 47000 Agen",
    "sg:city":"Agen",
    "sg:orig_category":"Unclassifiable Establishments",
    "sg:phone":"+33 5 53 66 76 77",
    "sg:postcode":"47000",
    "sg:province":"Aquitaine",
    "wof:name":"S.e.g. Fayat S.n.c.",
    "wof:placetype":"venue"
},
  "geometry": {"coordinates":[0.649149,44.213043],"type":"Point"}
}