{
  "type": "Feature",
  "properties": {
    "addr:full":"30 rue du Docteur Gallet 74300 Cluses Rhone-Alpes",
    "addr:housenumber":"30",
    "addr:postcode":"74300",
    "addr:street":"Rue Du Docteur Gallet",
    "iso:country":"FR",
    "sg:address":"30 rue du Docteur Gallet 74300 Cluses",
    "sg:classifiers":[
        {
            "category":"Manufacturing",
            "subcategory":"Tools & Machinery",
            "type":"Manufacturing & Wholesale Goods"
        }
    ],
    "sg:phone":"+33 4 50 98 13 83",
    "sg:province":"Rhone-Alpes",
    "sg:tags":[
        "special"
    ],
    "wof:name":"Guillen Sa",
    "wof:placetype":"venue"
},
  "geometry": {"coordinates":[6.570946,46.077389],"type":"Point"}
}