{
  "type": "Feature",
  "properties": {
    "addr:full":"Rue d'Iena - Les Tertiales b\u00e2t G Lesquin C\u00e9dex Nord-Pas-de-Calais 59818",
    "addr:housenumber":"ba\u0302t",
    "addr:postcode":"59818",
    "addr:street":"Rue D'Iena Les;Ce\u0301Dex",
    "iso:country":"FR",
    "sg:address":"Rue d'Iena - Les Tertiales b\u00e2t G",
    "sg:city":"Lesquin C\u00e9dex",
    "sg:orig_category":"Non-Classified Establishments",
    "sg:phone":"+33 3 20 87 64 75",
    "sg:postcode":"59818",
    "sg:province":"Nord-Pas-de-Calais",
    "wof:name":"L'entreprise Ferroviaire Safen S.a.",
    "wof:placetype":"venue"
},
  "geometry": {"coordinates":[3.113906,50.586945],"type":"Point"}
}