{
  "type": "Feature",
  "properties": {
    "iso:country":"FR",
    "sg:address":"Rue d'Iena - Les Tertiales b\u00e2t G",
    "sg:city":"Lesquin C\u00e9dex",
    "sg:orig_category":"Non-Classified Establishments",
    "sg:phone":"+33 3 20 87 64 75",
    "sg:postcode":"59818",
    "sg:province":"Nord-Pas-de-Calais",
    "wof:name":"L'entreprise Ferroviaire Safen S.a.",
    "wof:placetype":"venue"
},
  "geometry": {"coordinates":[3.113906,50.586945],"type":"Point"}
}