{
  "type": "Feature",
  "properties": {
    "addr:full":"La Borie Basse 24130 Prigonrieux Prigonrieux Aquitaine 24130",
    "addr:postcode":"24130;24130",
    "addr:street":"Borie Basse",
    "iso:country":"FR",
    "sg:address":"La Borie Basse 24130 Prigonrieux",
    "sg:city":"Prigonrieux",
    "sg:orig_category":"Non-Classified Establishments",
    "sg:phone":"+33 5 53 63 70 90",
    "sg:postcode":"24130",
    "sg:province":"Aquitaine",
    "wof:name":"Delviel S.a.",
    "wof:placetype":"venue"
},
  "geometry": {"coordinates":[0.438325,44.842869],"type":"Point"}
}