{
  "type": "Feature",
  "properties": {
    "iso:country":"FR",
    "sg:address":"28330 Authon du Perche",
    "sg:city":"Authon-du-Perche",
    "sg:orig_category":"Unclassifiable Establishments",
    "sg:phone":"+33 1 30 88 23 23",
    "sg:postcode":"28330",
    "sg:province":"Centre",
    "wof:name":"Mocap France",
    "wof:placetype":"venue"
},
  "geometry": {"coordinates":[0.892036,48.195324],"type":"Point"}
}