{
  "type": "Feature",
  "properties": {
    "iso:country":"FR",
    "sg:address":"5, Rue du Canal - ZAC de la Marini\u00e8re, 91070 Bondoufle",
    "sg:orig_category":"Unclassifiable Establishments",
    "sg:phone":"+33 1 69 47 31 31",
    "sg:province":"Ile de France",
    "wof:name":"Transevry S.a.",
    "wof:placetype":"venue"
},
  "geometry": {"coordinates":[2.379516,48.615681],"type":"Point"}
}