{
  "type": "Feature",
  "properties": {
    "addr:full":"B.P. 1257, 25004 Besan\u00e7on C\u00e9dex^^16, Rue Gay Lussac, 25000 Besan\u00e7on Franche Comt\u00e9",
    "addr:postcode":"25004;25000",
    "addr:street":"B.P. 1257;Rue Gay Lussac;Franche Comte\u0301",
    "iso:country":"FR",
    "sg:address":"B.P. 1257, 25004 Besan\u00e7on C\u00e9dex^^16, Rue Gay Lussac, 25000 Besan\u00e7on",
    "sg:orig_category":"Non-Classified Establishments",
    "sg:phone":"+33 3 81 40 12 12",
    "sg:province":"Franche Comt\u00e9",
    "wof:name":"Intech Enoma S.a.s.",
    "wof:placetype":"venue"
},
  "geometry": {"coordinates":[6.025686,47.242317],"type":"Point"}
}