{
  "type": "Feature",
  "properties": {
    "addr:full":"28, Rue Desaix, 75015 Paris Ile de France",
    "addr:housenumber":"28",
    "addr:postcode":"75015",
    "addr:street":"Rue Desaix",
    "iso:country":"FR",
    "sg:address":"28, Rue Desaix, 75015 Paris",
    "sg:orig_category":"Non-Classified Establishments",
    "sg:phone":"+33 1 64 53 12 12",
    "sg:province":"Ile de France",
    "wof:name":"Internet F.r. S.a.",
    "wof:placetype":"venue"
},
  "geometry": {"coordinates":[2.292782,48.852802],"type":"Point"}
}