{
  "type": "Feature",
  "properties": {
    "iso:country":"FR",
    "sg:address":"ZI Lann S\u00e9velin",
    "sg:city":"Caudan",
    "sg:orig_category":"Unclassifiable Establishments",
    "sg:phone":"+33 2 97 76 84 14",
    "sg:postcode":"56850",
    "sg:province":"Bretagne",
    "wof:name":"Les Moules J S.a.",
    "wof:placetype":"venue"
},
  "geometry": {"coordinates":[-3.340384,47.810596],"type":"Point"}
}