{
  "type": "Feature",
  "properties": {
    "addr:full":"10, Rue Joseph Cugnot, 51430 Tinqueux Champagne",
    "addr:housenumber":"10",
    "addr:postcode":"51430",
    "addr:street":"Rue Joseph Cugnot",
    "iso:country":"FR",
    "sg:address":"10, Rue Joseph Cugnot, 51430 Tinqueux",
    "sg:orig_category":"Unclassifiable Establishments",
    "sg:phone":"+33 3 26 50 40 30",
    "sg:province":"Champagne",
    "wof:name":"Bijot Transports S.a.",
    "wof:placetype":"venue"
},
  "geometry": {"coordinates":[3.986214,49.240868],"type":"Point"}
}