{
  "type": "Feature",
  "properties": {
    "addr:full":"Les Plates 63210 Olby Olby Auvergne 63210",
    "addr:postcode":"63210;olby;63210",
    "iso:country":"FR",
    "sg:address":"Les Plates 63210 Olby",
    "sg:city":"Olby",
    "sg:classifiers":[
        {
            "category":"Autos & Motor Vehicles",
            "subcategory":"Automobile Sales",
            "type":"Retail Goods"
        }
    ],
    "sg:phone":"+33 4 73 87 15 16",
    "sg:postcode":"63210",
    "sg:province":"Auvergne",
    "sg:tags":[
        "equipment",
        "motor-cars",
        "transport"
    ],
    "wof:name":"Sarl Carrosserie Mangot",
    "wof:placetype":"venue"
},
  "geometry": {"coordinates":[2.878997,45.669094],"type":"Point"}
}