{
  "type": "Feature",
  "properties": {
    "iso:country":"FR",
    "sg:address":"43, Chauss\u00e9e Brunehaut, 62223 Sainte Catherine",
    "sg:orig_category":"Unclassifiable Establishments",
    "sg:phone":"+33 3 21 51 03 82",
    "sg:province":"Nord Pas-de-Calais",
    "wof:name":"Imprimerie Brunehaut S.a.r.l.",
    "wof:placetype":"venue"
},
  "geometry": {"coordinates":[2.758386,50.305286],"type":"Point"}
}