{
  "type": "Feature",
  "properties": {
    "addr:full":"37/39, Av. de la R\u00e9publique, 92320 Ch\u00e2tillon Ile de France 92320",
    "addr:housenumber":"37 / 39",
    "addr:postcode":"92320;ile;92320",
    "addr:street":"Av. De La Re\u0301Publique;France",
    "iso:country":"FR",
    "sg:address":"37/39, Av. de la R\u00e9publique, 92320 Ch\u00e2tillon",
    "sg:orig_category":"Non-Classified Establishments",
    "sg:phone":"+33 1 46 12 17 18",
    "sg:postcode":"92320",
    "sg:province":"Ile de France",
    "wof:name":"Caron Service Automatique S.a.",
    "wof:placetype":"venue"
},
  "geometry": {"coordinates":[2.294095,48.801361],"type":"Point"}
}