{
  "type": "Feature",
  "properties": {
    "addr:full":"6, Place Robert Mottu, 41600 Chaumont sur Tharonne Chaon Centre 41600",
    "addr:housenumber":"6",
    "addr:postcode":"41600;41600",
    "addr:street":"Place Robert Mottu",
    "iso:country":"FR",
    "sg:address":"6, Place Robert Mottu, 41600 Chaumont sur Tharonne",
    "sg:city":"Chaon",
    "sg:orig_category":"Unclassifiable Establishments",
    "sg:phone":"+33 2 54 88 53 40",
    "sg:postcode":"41600",
    "sg:province":"Centre",
    "wof:name":"Maurice Gougeon S.a.r.l.",
    "wof:placetype":"venue"
},
  "geometry": {"coordinates":[1.904694,47.610107],"type":"Point"}
}