{
  "type": "Feature",
  "properties": {
    "iso:country":"FR",
    "sg:address":"34, Rue Anatole France, 59160 Lomme",
    "sg:orig_category":"Unclassifiable Establishments",
    "sg:phone":"+33 3 20 92 45 11",
    "sg:province":"Nord Pas-de-Calais",
    "wof:name":"Catteau F. Et Compagnie S.a.",
    "wof:placetype":"venue"
},
  "geometry": {"coordinates":[3.006983,50.634022],"type":"Point"}
}