{
  "type": "Feature",
  "properties": {
    "addr:full":"ZI Lucy L\u00e9vis Auvergne 03320",
    "addr:postcode":"03320",
    "iso:country":"FR",
    "sg:address":"ZI",
    "sg:city":"Lucy L\u00e9vis",
    "sg:orig_category":"Unclassifiable Establishments",
    "sg:phone":"+33 4 70 67 80 04",
    "sg:postcode":"03320",
    "sg:province":"Auvergne",
    "wof:name":"Baudin S.a.r.l.",
    "wof:placetype":"venue"
},
  "geometry": {"coordinates":[2.95718,46.723],"type":"Point"}
}