{
  "type": "Feature",
  "properties": {
    "iso:country":"FR",
    "sg:address":"ZI des Chaumes",
    "sg:city":"La Chapelle Saint Ursin",
    "sg:orig_category":"Unclassifiable Establishments",
    "sg:phone":"+33 2 48 26 48 76",
    "sg:postcode":"18570",
    "sg:province":"Centre",
    "wof:name":"A.t.e.l. S.a.r.l.",
    "wof:placetype":"venue"
},
  "geometry": {"coordinates":[2.321243,47.063713],"type":"Point"}
}