{
  "type": "Feature",
  "properties": {
    "addr:full":"60117 Russy B\u00e9mont Picardie",
    "addr:postcode":"60117",
    "iso:country":"FR",
    "sg:address":"60117 Russy B\u00e9mont",
    "sg:orig_category":"Unclassifiable Establishments",
    "sg:phone":"+33 3 44 88 32 40",
    "sg:province":"Picardie",
    "wof:name":"Primeurop",
    "wof:placetype":"venue"
},
  "geometry": {"coordinates":[2.964332,49.243679],"type":"Point"}
}