{
  "type": "Feature",
  "properties": {
    "iso:country":"FR",
    "sg:address":"8 route de Krafft 67150 Erstein",
    "sg:city":"Erstein",
    "sg:classifiers":[
        {
            "category":"Animal Shelter",
            "type":"Public Place"
        }
    ],
    "sg:phone":"+33 3 88 98 10 97",
    "sg:postcode":"67150",
    "sg:province":"Alsace",
    "sg:tags":[
        "agricultural",
        "requirement",
        "husbandry",
        "domestic"
    ],
    "wof:name":"Ste Exploitation Ets A Grass Sarl",
    "wof:placetype":"venue"
},
  "geometry": {"coordinates":[7.66915,48.429996],"type":"Point"}
}