{
  "type": "Feature",
  "properties": {
    "addr:full":"17bis, Rue Racine, 02200 Soissons Picardie",
    "addr:housenumber":"17bis",
    "addr:postcode":"02200",
    "addr:street":"Rue Racine",
    "iso:country":"FR",
    "sg:address":"17bis, Rue Racine, 02200 Soissons",
    "sg:orig_category":"Unclassifiable Establishments",
    "sg:phone":"+33 3 23 59 86 86",
    "sg:province":"Picardie",
    "wof:name":"Leviel S.a.",
    "wof:placetype":"venue"
},
  "geometry": {"coordinates":[3.32716,49.375828],"type":"Point"}
}