{
  "type": "Feature",
  "properties": {
    "addr:full":"Rte de Lafenasse R\u00e9almont Midi Pyr\u00e9n\u00e9es 81120",
    "addr:postcode":"81120",
    "addr:street":"Rte De Lafenasse",
    "iso:country":"FR",
    "sg:address":"Rte de Lafenasse",
    "sg:city":"R\u00e9almont",
    "sg:orig_category":"Non-Classified Establishments",
    "sg:phone":"+33 5 63 55 51 23",
    "sg:postcode":"81120",
    "sg:province":"Midi Pyr\u00e9n\u00e9es",
    "wof:name":"Carceller Entreprise S.a.",
    "wof:placetype":"venue"
},
  "geometry": {"coordinates":[2.288703,43.764061],"type":"Point"}
}