{
  "type": "Feature",
  "properties": {
    "iso:country":"FR",
    "sg:address":"Z.A.C. des Longues Rayes",
    "sg:city":"Lacroix Saint Ouen",
    "sg:orig_category":"Unclassifiable Establishments",
    "sg:phone":"+33 3 44 91 69 00",
    "sg:postcode":"60610",
    "sg:province":"Picardie",
    "wof:name":"Alcatel T\u00e9l\u00e9com S.a.",
    "wof:placetype":"venue"
},
  "geometry": {"coordinates":[2.785204,49.353703],"type":"Point"}
}