{
  "type": "Feature",
  "properties": {
    "addr:full":"15 rue du Bief 25500 Morteau Franche Comt\u00e9 25500",
    "addr:housenumber":"15",
    "addr:postcode":"25500;25500",
    "addr:street":"Rue Du Bief;Franche Comte\u0301",
    "iso:country":"FR",
    "sg:address":"15 rue du Bief 25500 Morteau",
    "sg:classifiers":[
        {
            "category":"Manufacturing",
            "subcategory":"Tools & Machinery",
            "type":"Manufacturing & Wholesale Goods"
        }
    ],
    "sg:phone":"+33 3 81 67 01 63",
    "sg:postcode":"25500",
    "sg:province":"Franche Comt\u00e9",
    "sg:tags":[
        "industrial",
        "handheld"
    ],
    "wof:name":"Feuvrier Eurl",
    "wof:placetype":"venue"
},
  "geometry": {"coordinates":[6.615364,47.057674],"type":"Point"}
}