{
  "type": "Feature",
  "properties": {
    "iso:country":"FR",
    "sg:address":"33, Av. du Docteur Georges L\u00e9vy, 69630 V\u00e9nissieux",
    "sg:orig_category":"Unclassifiable Establishments",
    "sg:phone":"+33 4 72 78 84 04",
    "sg:province":"Rhone-Alpes",
    "wof:name":"C.e.t.e. Apave S.a.",
    "wof:placetype":"venue"
},
  "geometry": {"coordinates":[4.860519,45.719555],"type":"Point"}
}