{
  "type": "Feature",
  "properties": {
    "iso:country":"FR",
    "sg:address":"5, Av. Virecourt, 33370 Artigues Pr\u00e8s Bordeaux",
    "sg:city":"Artigues-pr\u00e8s-Bordeaux",
    "sg:orig_category":"Unclassifiable Establishments",
    "sg:phone":"+33 5 57 54 26 60",
    "sg:postcode":"33370",
    "sg:province":"Aquitaine",
    "wof:name":"C.e.b.i.g. S.a.r.l. - Centre Bordelais Informatique Et Gestion",
    "wof:placetype":"venue"
},
  "geometry": {"coordinates":[-0.495965,44.856239],"type":"Point"}
}