{
  "type": "Feature",
  "properties": {
    "addr:full":"24, Av Carnot, 02250 Marle Picardie",
    "addr:postcode":"02250",
    "addr:street":"24 Av Carnot",
    "iso:country":"FR",
    "sg:address":"24, Av Carnot, 02250 Marle",
    "sg:orig_category":"Non-Classified Establishments",
    "sg:phone":"+33 3 23 21 79 00",
    "sg:province":"Picardie",
    "wof:name":"Lef\u00e8vre Et Fils S.a.",
    "wof:placetype":"venue"
},
  "geometry": {"coordinates":[3.771774,49.747925],"type":"Point"}
}