{
  "type": "Feature",
  "properties": {
    "addr:full":"116, Rue de Thionville, 57140 Woippy Lorraine 57140",
    "addr:housenumber":"116",
    "addr:postcode":"57140;57140",
    "addr:street":"Rue De Thionville",
    "iso:country":"FR",
    "sg:address":"116, Rue de Thionville, 57140 Woippy",
    "sg:orig_category":"Non-Classified Establishments",
    "sg:phone":"+33 3 87 32 13 13",
    "sg:postcode":"57140",
    "sg:province":"Lorraine",
    "wof:name":"Equip'service S.a.r.l.",
    "wof:placetype":"venue"
},
  "geometry": {"coordinates":[6.15708,49.155571],"type":"Point"}
}