{
  "type": "Feature",
  "properties": {
    "iso:country":"FR",
    "sg:address":"B.P. 56, 14650 Carpiquet C\u00e9dex^^Rue de Bellevue, 14650 Carpiquet",
    "sg:city":"Carpiquet",
    "sg:orig_category":"Non-Classified Establishments",
    "sg:phone":"+33 2 31 71 13 71",
    "sg:postcode":"14650",
    "sg:province":"Basse Normandie",
    "wof:name":"Borelec S.a.",
    "wof:placetype":"venue"
},
  "geometry": {"coordinates":[-0.443854,49.183708],"type":"Point"}
}