{
  "type": "Feature",
  "properties": {
    "iso:country":"FR",
    "sg:address":"B.P. 18, 79370 Celles sur Belle^^5, Av. de Niort, 79370 Celles sur Belle",
    "sg:orig_category":"Non-Classified Establishments",
    "sg:phone":"+33 5 49 32 89 09",
    "sg:province":"Poitou-Charentes",
    "wof:name":"S\u00e8vre Et Belle S.a.",
    "wof:placetype":"venue"
},
  "geometry": {"coordinates":[-0.238469,46.214119],"type":"Point"}
}