{
  "type": "Feature",
  "properties": {
    "addr:full":"12 Place Carnot; Aix les Bains; 73100 Rhone-Alpes 73100",
    "addr:housenumber":"12",
    "addr:postcode":"73100;73100",
    "addr:street":"Place Carnot",
    "iso:country":"FR",
    "sg:address":"12 Place Carnot; Aix les Bains; 73100",
    "sg:classifiers":[
        {
            "category":"Banks & Credit Unions",
            "subcategory":"Bank",
            "type":"Services"
        }
    ],
    "sg:phone":"+33 3379353044",
    "sg:postcode":"73100",
    "sg:province":"Rhone-Alpes",
    "wof:name":"Soci\u00e9t\u00e9 G\u00e9n\u00e9rale",
    "wof:placetype":"venue"
},
  "geometry": {"coordinates":[5.914171,45.689072],"type":"Point"}
}