{
  "type": "Feature",
  "properties": {
    "iso:country":"FR",
    "sg:address":"B.P. 222, 11102 Narbonne C\u00e9dex^^ZI de Malvesi, 11100 Narbonne",
    "sg:orig_category":"Non-Classified Establishments",
    "sg:phone":"+33 4 68 42 55 00",
    "sg:province":"Languedoc-Roussillon",
    "wof:name":"Usine Comurhex S.a.",
    "wof:placetype":"venue"
},
  "geometry": {"coordinates":[2.953635,43.119781],"type":"Point"}
}