{
  "type": "Feature",
  "properties": {
    "addr:full":"B.P. 103, 88204 Remiremont C\u00e9dex^^Rue des Ponc\u00e9es, 88200 Saint Etienne l\u00e8s Remiremont Lorraine",
    "addr:housenumber":"b.p. 103",
    "addr:postcode":"88204;88200",
    "iso:country":"FR",
    "sg:address":"B.P. 103, 88204 Remiremont C\u00e9dex^^Rue des Ponc\u00e9es, 88200 Saint Etienne l\u00e8s Remiremont",
    "sg:orig_category":"Non-Classified Establishments",
    "sg:phone":"+33 3 29 23 23 46",
    "sg:province":"Lorraine",
    "wof:name":"Valdenaire Ren\u00e9 S.a.",
    "wof:placetype":"venue"
},
  "geometry": {"coordinates":[6.599603,48.0196],"type":"Point"}
}