{
  "type": "Feature",
  "properties": {
    "iso:country":"FR",
    "sg:address":"RN 143 - ZI Saint Malo",
    "sg:city":"Esvres",
    "sg:orig_category":"Non-Classified Establishments",
    "sg:phone":"+33 2 47 26 43 03",
    "sg:postcode":"37320",
    "sg:province":"Centre",
    "wof:name":"Dravert Technologies S.a.",
    "wof:placetype":"venue"
},
  "geometry": {"coordinates":[0.74494,47.185612],"type":"Point"}
}