{
  "type": "Feature",
  "properties": {
    "iso:country":"FR",
    "sg:address":"Rte d'Epegard",
    "sg:city":"Le Neubourg",
    "sg:orig_category":"Unclassifiable Establishments",
    "sg:phone":"+33 2 32 35 03 93",
    "sg:postcode":"27110",
    "sg:province":"Haute Normandie",
    "wof:name":"Gamet Pr\u00e9cision S.a.",
    "wof:placetype":"venue"
},
  "geometry": {"coordinates":[0.87777,49.180721],"type":"Point"}
}