{
  "type": "Feature",
  "properties": {
    "addr:full":"4 Rue Du Caire 75002 Paris Ile de France 75002",
    "addr:housenumber":"4",
    "addr:postcode":"75002;75002",
    "addr:street":"Rue Du Caire",
    "iso:country":"FR",
    "sg:address":"4 Rue Du Caire 75002 Paris",
    "sg:classifiers":[
        {
            "category":"Shopping",
            "subcategory":"Clothing, Apparel, & Fashions",
            "type":"Retail Goods"
        }
    ],
    "sg:phone":"+33 1 42 36 44 72",
    "sg:postcode":"75002",
    "sg:province":"Ile de France",
    "sg:tags":[
        "textile",
        "clothing",
        "clothes"
    ],
    "wof:name":"Jus D'orange",
    "wof:placetype":"venue"
},
  "geometry": {"coordinates":[2.352806,48.867218],"type":"Point"}
}