{
  "type": "Feature",
  "properties": {
    "addr:full":"31, Rue de l'Hospice, 59100 Roubaix Nord Pas-de-Calais",
    "addr:housenumber":"31",
    "addr:postcode":"59100",
    "addr:street":"Rue De L'Hospice",
    "iso:country":"FR",
    "sg:address":"31, Rue de l'Hospice, 59100 Roubaix",
    "sg:orig_category":"Unclassifiable Establishments",
    "sg:phone":"+33 3 20 70 80 10",
    "sg:province":"Nord Pas-de-Calais",
    "wof:name":"Aux Ciseaux D'or S.a.r.l.",
    "wof:placetype":"venue"
},
  "geometry": {"coordinates":[3.160883,50.695164],"type":"Point"}
}