{
  "type": "Feature",
  "properties": {
    "iso:country":"FR",
    "sg:address":"27, Rue du Chail, 16200 Jarnac",
    "sg:orig_category":"Unclassifiable Establishments",
    "sg:phone":"+33 5 45 81 02 03",
    "sg:province":"Poitou-Charentes",
    "wof:name":"Louis Saveur S.a.r.l.",
    "wof:placetype":"venue"
},
  "geometry": {"coordinates":[-0.181474,45.681606],"type":"Point"}
}