{
  "type": "Feature",
  "properties": {
    "iso:country":"FR",
    "sg:address":"Le Bourg 87310 Cognac la For\u00eat",
    "sg:orig_category":"Unclassifiable Establishments",
    "sg:phone":"+33 5 55 03 82 03",
    "sg:province":"Limousin",
    "wof:name":"M.i.c. S.a. - Manufacture Industrielle De Confection",
    "wof:placetype":"venue"
},
  "geometry": {"coordinates":[1.010116,45.836521],"type":"Point"}
}