{
  "type": "Feature",
  "properties": {
    "addr:full":"6, Rue Collinet, 77590 Bois le Roi Ile de France",
    "addr:housenumber":"6",
    "addr:postcode":"77590",
    "addr:street":"Rue Collinet;Bois Le Roi Ile De France",
    "iso:country":"FR",
    "sg:address":"6, Rue Collinet, 77590 Bois le Roi",
    "sg:orig_category":"Non-Classified Establishments",
    "sg:phone":"+33 1 60 69 12 13",
    "sg:province":"Ile de France",
    "wof:name":"P.g.f. Partner S.a.r.l.",
    "wof:placetype":"venue"
},
  "geometry": {"coordinates":[2.69148,48.466843],"type":"Point"}
}