{
  "type": "Feature",
  "properties": {
    "iso:country":"FR",
    "sg:address":"10 Avenue Edouard Serres 31770 Colomiers",
    "sg:classifiers":[
        {
            "category":"Professional",
            "subcategory":"Engineering",
            "type":"Services"
        }
    ],
    "sg:phone":"+33 5 62 74 34 00",
    "sg:postcode":"31770",
    "sg:province":"Midi Pyr\u00e9n\u00e9es",
    "sg:tags":[
        "machine",
        "-",
        "mechanical"
    ],
    "wof:name":"Actia",
    "wof:placetype":"venue"
},
  "geometry": {"coordinates":[1.352733,43.613007],"type":"Point"}
}