{
  "type": "Feature",
  "properties": {
    "iso:country":"FR",
    "sg:address":"95 Rue De La Semm 68000 Colmar",
    "sg:city":"Colmar",
    "sg:classifiers":[
        {
            "category":"Professional",
            "subcategory":"Advertising",
            "type":"Services"
        }
    ],
    "sg:phone":"+33 3 89 24 30 80",
    "sg:postcode":"68000",
    "sg:province":"Alsace",
    "sg:tags":[
        "marketing",
        "medium",
        "communication"
    ],
    "wof:name":"Distri Pub (dp)",
    "wof:placetype":"venue"
},
  "geometry": {"coordinates":[7.376605,48.068722],"type":"Point"}
}