{
  "type": "Feature",
  "properties": {
    "iso:country":"FR",
    "sg:address":"7 Rue Alfred Nobel 93600 Aulnay Sous Bois",
    "sg:classifiers":[
        {
            "category":"Professional",
            "type":"Services"
        }
    ],
    "sg:phone":"+33 1 48 66 03 63",
    "sg:province":"Ile de France",
    "sg:tags":[
        "transport",
        "road"
    ],
    "wof:name":"Sarl Lg",
    "wof:placetype":"venue"
},
  "geometry": {"coordinates":[2.477642,48.947048],"type":"Point"}
}