{
  "type": "Feature",
  "properties": {
    "addr:full":"5 rue du Chateau d'Eaux 76640 Normanville Haute Normandie 76640",
    "addr:housenumber":"5",
    "addr:postcode":"76640;76640",
    "addr:street":"Rue Du Chateau D'Eaux;Haute Normandie",
    "iso:country":"FR",
    "sg:address":"5 rue du Chateau d'Eaux 76640 Normanville",
    "sg:classifiers":[
        {
            "category":"Banks & Credit Unions",
            "subcategory":"Investment Brokerage",
            "type":"Services"
        }
    ],
    "sg:phone":"+33 2 35 29 36 04",
    "sg:postcode":"76640",
    "sg:province":"Haute Normandie",
    "sg:tags":[
        "machine",
        "blasting",
        "centrifugal",
        "system"
    ],
    "wof:name":"Lamotte Gmp Sarl",
    "wof:placetype":"venue"
},
  "geometry": {"coordinates":[0.58977,49.691608],"type":"Point"}
}