{
  "type": "Feature",
  "properties": {
    "addr:full":"15, Rue Achille Pruvost, 80130 Tully Picardie",
    "addr:housenumber":"15",
    "addr:postcode":"80130",
    "addr:street":"Rue Achille Pruvost",
    "iso:country":"FR",
    "sg:address":"15, Rue Achille Pruvost, 80130 Tully",
    "sg:orig_category":"Unclassifiable Establishments",
    "sg:phone":"+33 3 22 30 70 01",
    "sg:province":"Picardie",
    "wof:name":"Meaux Et Fils S.a.r.l.",
    "wof:placetype":"venue"
},
  "geometry": {"coordinates":[1.520108,50.085751],"type":"Point"}
}