{
  "type": "Feature",
  "properties": {
    "addr:full":"B.P. 26, 65300 Lannemezan^^999, Rue des Usines, 65300 Lannemezan Midi Pyr\u00e9n\u00e9es 65300",
    "addr:postcode":"65300;65300;65300",
    "addr:street":"B.P. 26;Rue Des Usines",
    "iso:country":"FR",
    "sg:address":"B.P. 26, 65300 Lannemezan^^999, Rue des Usines, 65300 Lannemezan",
    "sg:orig_category":"Non-Classified Establishments",
    "sg:phone":"+33 5 62 99 58 00",
    "sg:postcode":"65300",
    "sg:province":"Midi Pyr\u00e9n\u00e9es",
    "wof:name":"Aluminium P\u00e9chiney S.a.",
    "wof:placetype":"venue"
},
  "geometry": {"coordinates":[0.434825,43.115124],"type":"Point"}
}