{
  "type": "Feature",
  "properties": {
    "addr:full":"26 R Des Olivettes BP 9 85700 La Flocelliere Pays de Loire 85700",
    "addr:housenumber":"26;9",
    "addr:postcode":"85700;85700",
    "addr:street":"R Des Olivettes Bp;Flocelliere",
    "iso:country":"FR",
    "sg:address":"26 R Des Olivettes BP 9 85700 La Flocelliere",
    "sg:classifiers":[
        {
            "category":"Home & Garden",
            "subcategory":"Furniture",
            "type":"Retail Goods"
        }
    ],
    "sg:phone":"+33 2 51 57 22 14",
    "sg:postcode":"85700",
    "sg:province":"Pays de Loire",
    "sg:tags":[
        "household",
        "wood"
    ],
    "wof:name":"Frederic Sourisseau",
    "wof:placetype":"venue"
},
  "geometry": {"coordinates":[-0.866033,46.828716],"type":"Point"}
}