{
  "type": "Feature",
  "properties": {
    "addr:full":"22, Place des Epars, 28005 Chartres Poitou-Charentes",
    "addr:housenumber":"22",
    "addr:postcode":"28005",
    "addr:street":"Place Des Epars",
    "iso:country":"FR",
    "sg:address":"22, Place des Epars, 28005 Chartres",
    "sg:orig_category":"Non-Classified Establishments",
    "sg:phone":"+33 2 37 21 00 72",
    "sg:province":"Poitou-Charentes",
    "wof:name":"Best Western Le Grand Monarque",
    "wof:placetype":"venue"
},
  "geometry": {"coordinates":[1.483311,48.444313],"type":"Point"}
}