{
  "type": "Feature",
  "properties": {
    "iso:country":"FR",
    "sg:address":"10 rue Abb\u00e9s Courtais; Maisdon",
    "sg:classifiers":[
        {
            "category":"Banks & Credit Unions",
            "subcategory":"Bank",
            "type":"Services"
        }
    ],
    "sg:phone":"+33 3340038860",
    "sg:province":"Nord Pas-de-Calais",
    "wof:name":"Cr\u00e9dit Mutuel",
    "wof:placetype":"venue"
},
  "geometry": {"coordinates":[-1.38484,47.097111],"type":"Point"}
}