{
  "type": "Feature",
  "properties": {
    "addr:full":"133 Rue Du G\u00e9n\u00e9ral De Gaulle 14360 Trouville Sur Mer Trouville-sur-Mer Basse Normandie 14360",
    "addr:housenumber":"133",
    "addr:postcode":"14360;14360",
    "addr:street":"Rue Du Ge\u0301Ne\u0301Ral De Gaulle",
    "iso:country":"FR",
    "sg:address":"133 Rue Du G\u00e9n\u00e9ral De Gaulle 14360 Trouville Sur Mer",
    "sg:city":"Trouville-sur-Mer",
    "sg:classifiers":[
        {
            "category":"Shopping",
            "subcategory":"Gifts & Souvenirs",
            "type":"Retail Goods"
        }
    ],
    "sg:phone":"+33 2 31 87 37 63",
    "sg:postcode":"14360",
    "sg:province":"Basse Normandie",
    "sg:tags":[
        "product",
        "miscellaneous"
    ],
    "wof:name":"Au Bric A Brac Eurl",
    "wof:placetype":"venue"
},
  "geometry": {"coordinates":[0.087506,49.360462],"type":"Point"}
}