{
  "type": "Feature",
  "properties": {
    "addr:full":"La Gare Beaubery Bourgogne 71220",
    "addr:postcode":"71220",
    "addr:street":"Bourgogne",
    "iso:country":"FR",
    "sg:address":"La Gare",
    "sg:city":"Beaubery",
    "sg:orig_category":"Unclassifiable Establishments",
    "sg:phone":"+33 3 85 24 84 12",
    "sg:postcode":"71220",
    "sg:province":"Bourgogne",
    "wof:name":"Turboprint S.a.s.",
    "wof:placetype":"venue"
},
  "geometry": {"coordinates":[4.408345,46.428493],"type":"Point"}
}