{
  "type": "Feature",
  "properties": {
    "iso:country":"FR",
    "sg:address":"12, Av. Pascal Bagn\u00e8res, 33610 Cestas",
    "sg:city":"Cestas",
    "sg:orig_category":"Non-Classified Establishments",
    "sg:phone":"+33 5 57 97 16 20",
    "sg:postcode":"33610",
    "sg:province":"Aquitaine",
    "wof:name":"Les Mat\u00e9riaux Bagn\u00e8res S.a.",
    "wof:placetype":"venue"
},
  "geometry": {"coordinates":[-0.764839,44.740589],"type":"Point"}
}