{
  "type": "Feature",
  "properties": {
    "addr:full":"354 Rue Nationale 41250 Mont Pr\u00e8s Chambord Chambord Centre 41250",
    "addr:housenumber":"354",
    "addr:postcode":"41250;41250",
    "addr:street":"Rue Nationale;Pre\u0300S",
    "iso:country":"FR",
    "sg:address":"354 Rue Nationale 41250 Mont Pr\u00e8s Chambord",
    "sg:city":"Chambord",
    "sg:classifiers":[
        {
            "category":"Professional",
            "type":"Services"
        }
    ],
    "sg:phone":"+33 2 54 70 71 09",
    "sg:postcode":"41250",
    "sg:province":"Centre",
    "sg:tags":[
        "transport",
        "road"
    ],
    "wof:name":"Parent Et Rampal Ets Sarl",
    "wof:placetype":"venue"
},
  "geometry": {"coordinates":[1.461189,47.562622],"type":"Point"}
}