{
  "type": "Feature",
  "properties": {
    "iso:country":"FR",
    "sg:address":"39, Rue Georges Ohnet, 31200 Toulouse",
    "sg:orig_category":"Unclassifiable Establishments",
    "sg:phone":"+33 5 61 61 60 99",
    "sg:province":"Midi Pyr\u00e9n\u00e9es",
    "wof:name":"Color Studio Station Graphique Publicit\u00e9 S.a.r.l.",
    "wof:placetype":"venue"
},
  "geometry": {"coordinates":[1.472633,43.638157],"type":"Point"}
}