{
  "type": "Feature",
  "properties": {
    "addr:full":"Avenue Charles De Gaulle Porte De Beaune 21207 Beaune Cedex Bourgogne",
    "addr:postcode":"21207",
    "addr:street":"Avenue Charles De Gaulle Porte De Beaune",
    "iso:country":"FR",
    "sg:address":"Avenue Charles De Gaulle Porte De Beaune 21207 Beaune Cedex",
    "sg:classifiers":[
        {
            "category":"Professional",
            "subcategory":"Engineering",
            "type":"Services"
        }
    ],
    "sg:phone":"+33 3 80 24 01 30",
    "sg:province":"Bourgogne",
    "sg:tags":[
        "machine",
        "-",
        "environment",
        "equipment",
        "machinery",
        "mechanical"
    ],
    "wof:name":"Horstmann France Sa",
    "wof:placetype":"venue"
},
  "geometry": {"coordinates":[4.836629,47.016109],"type":"Point"}
}