{
  "type": "Feature",
  "properties": {
    "iso:country":"FR",
    "sg:address":"6, Bd Lassagne, 69530 Brignais",
    "sg:orig_category":"Non-Classified Establishments",
    "sg:phone":"+33 4 78 05 30 20",
    "sg:province":"Rhone-Alpes",
    "wof:name":"Rhonis S.a.",
    "wof:placetype":"venue"
},
  "geometry": {"coordinates":[4.754084,45.666527],"type":"Point"}
}