{
  "type": "Feature",
  "properties": {
    "addr:full":"Av. Henri Becquerel - Parc d'Activit\u00e9 Kennedy - B\u00e2t K M\u00e9rignac Aquitaine 33700",
    "addr:housenumber":"ba\u0302t k",
    "addr:postcode":"33700",
    "addr:street":"Av. Henri Becquerel Parc D'Activite \u0301 Kennedy",
    "iso:country":"FR",
    "sg:address":"Av. Henri Becquerel - Parc d'Activit\u00e9 Kennedy - B\u00e2t K",
    "sg:city":"M\u00e9rignac",
    "sg:orig_category":"Unclassifiable Establishments",
    "sg:phone":"+33 5 56 34 26 76",
    "sg:postcode":"33700",
    "sg:province":"Aquitaine",
    "wof:name":"Digital Control Isin S.a.",
    "wof:placetype":"venue"
},
  "geometry": {"coordinates":[-0.689798,44.836823],"type":"Point"}
}