{
  "type": "Feature",
  "properties": {
    "iso:country":"FR",
    "sg:address":"Za De Briqueterie 76160 St Jacques Sur Darnetal",
    "sg:classifiers":[
        {
            "category":"Shopping",
            "subcategory":"Clothing, Apparel, & Fashions",
            "type":"Retail Goods"
        }
    ],
    "sg:phone":"+33 2 35 02 03 84",
    "sg:postcode":"76160",
    "sg:province":"Haute Normandie",
    "sg:tags":[
        "textile",
        "clothing",
        "clothes"
    ],
    "wof:name":"Magasins Bleus",
    "wof:placetype":"venue"
},
  "geometry": {"coordinates":[1.20254,49.440216],"type":"Point"}
}