{
  "type": "Feature",
  "properties": {
    "addr:full":"3, Place Saint Bruno, 38500 Voiron Rhone-Alpes 38500",
    "addr:housenumber":"3",
    "addr:postcode":"38500;38500",
    "addr:street":"Place Saint Bruno",
    "iso:country":"FR",
    "sg:address":"3, Place Saint Bruno, 38500 Voiron",
    "sg:orig_category":"Unclassifiable Establishments",
    "sg:phone":"+33 4 76 65 66 40",
    "sg:postcode":"38500",
    "sg:province":"Rhone-Alpes",
    "wof:name":"Atout Voiron S.a.s.",
    "wof:placetype":"venue"
},
  "geometry": {"coordinates":[5.592797,45.367111],"type":"Point"}
}