{
  "type": "Feature",
  "properties": {
    "iso:country":"FR",
    "sg:address":"Rue du Vaux Fourch\u00e9 - ZA",
    "sg:city":"Bucy le Long",
    "sg:orig_category":"Non-Classified Establishments",
    "sg:phone":"+33 3 23 72 22 00",
    "sg:postcode":"02880",
    "sg:province":"Picardie",
    "wof:name":"Suin Imprimerie S.a.",
    "wof:placetype":"venue"
},
  "geometry": {"coordinates":[3.37811,49.41016],"type":"Point"}
}