{
  "type": "Feature",
  "properties": {
    "iso:country":"FR",
    "sg:address":"6 rue Gaston Montmousseau 38130 Echirolles",
    "sg:classifiers":[
        {
            "category":"Autos & Motor Vehicles",
            "subcategory":"Boat Sales",
            "type":"Retail Goods"
        }
    ],
    "sg:phone":"+33 4 76 09 23 09",
    "sg:postcode":"38130",
    "sg:province":"Rhone-Alpes",
    "sg:tags":[
        "machine",
        "beverage",
        "vending",
        "dispensing"
    ],
    "wof:name":"Dia Vendors France Sa",
    "wof:placetype":"venue"
},
  "geometry": {"coordinates":[5.711432,45.155994],"type":"Point"}
}