{
  "type": "Feature",
  "properties": {
    "addr:full":"Za Du Bouillon 79430 La Chapelle St Laurent Poitou-Charentes 79430",
    "addr:postcode":"79430;79430",
    "addr:street":"Za Du Bouillon;La Chapelle St Laurent",
    "iso:country":"FR",
    "sg:address":"Za Du Bouillon 79430 La Chapelle St Laurent",
    "sg:classifiers":[
        {
            "category":"Social Services",
            "subcategory":"Job Training",
            "type":"Services"
        }
    ],
    "sg:phone":"+33 5 49 72 08 85",
    "sg:postcode":"79430",
    "sg:province":"Poitou-Charentes",
    "sg:tags":[
        "metallurgy",
        "metal",
        "processing",
        "-",
        "metalworking",
        "machine",
        "engineering",
        "mechanical"
    ],
    "wof:name":"Jpmg Sarl",
    "wof:placetype":"venue"
},
  "geometry": {"coordinates":[-0.476169,46.745403],"type":"Point"}
}