{
  "type": "Feature",
  "properties": {
    "iso:country":"FR",
    "sg:address":"B.P. 5, 08330 Vrigne aux Bois^^6, Rue J.J. Rousseau, 08330 Vrigne aux Bois",
    "sg:orig_category":"Non-Classified Establishments",
    "sg:phone":"+33 3 24 52 14 58",
    "sg:postcode":"08330",
    "sg:province":"Champagne",
    "wof:name":"E.a.i. S.a.r.l. - Exploitation Automatismes Industriels",
    "wof:placetype":"venue"
},
  "geometry": {"coordinates":[4.854222,49.737251],"type":"Point"}
}