{
  "type": "Feature",
  "properties": {
    "addr:full":"Zone Industrielle Les Taillades 12700 Capdenac Gare Midi Pyr\u00e9n\u00e9es 12700",
    "addr:postcode":"12700;12700",
    "addr:street":"Zone Industrielle Les Taillades",
    "iso:country":"FR",
    "sg:address":"Zone Industrielle Les Taillades 12700 Capdenac Gare",
    "sg:classifiers":[
        {
            "category":"Wholesale",
            "subcategory":"Meat",
            "type":"Manufacturing & Wholesale Goods"
        }
    ],
    "sg:phone":"+33 5 65 63 80 04",
    "sg:postcode":"12700",
    "sg:province":"Midi Pyr\u00e9n\u00e9es",
    "sg:tags":[
        "food",
        "cooked",
        "product",
        "related"
    ],
    "wof:name":"Serrault Sa",
    "wof:placetype":"venue"
},
  "geometry": {"coordinates":[2.08064,44.574406],"type":"Point"}
}