{
  "type": "Feature",
  "properties": {
    "addr:full":"B.P. 63 Morestel C\u00e9dex^^38510 Morestel Rhone-Alpes 38510",
    "addr:postcode":"38510",
    "addr:street":"B.P. 63;Ce\u0301Dex^^38510;Rhone-Alpes",
    "iso:country":"FR",
    "sg:address":"B.P. 63",
    "sg:city":"Morestel C\u00e9dex^^38510 Morestel",
    "sg:orig_category":"Non-Classified Establishments",
    "sg:phone":"+33 4 74 33 34 35",
    "sg:postcode":"38510",
    "sg:province":"Rhone-Alpes",
    "wof:name":"E.d.f.",
    "wof:placetype":"venue"
},
  "geometry": {"coordinates":[5.420305,45.650581],"type":"Point"}
}