{
  "type": "Feature",
  "properties": {
    "iso:country":"FR",
    "sg:address":"12 Av Gal Charles De Gaulle 39400 Morez",
    "sg:classifiers":[
        {
            "category":"Health Services",
            "subcategory":"Optometrist",
            "type":"Services"
        }
    ],
    "sg:phone":"+33 3 84 33 72 00",
    "sg:postcode":"39400",
    "sg:province":"Franche Comt\u00e9",
    "sg:tags":[
        "instrument",
        "optical",
        "-",
        "precision",
        "equipment"
    ],
    "wof:name":"Cebe Sa",
    "wof:placetype":"venue"
},
  "geometry": {"coordinates":[6.02252,46.52433],"type":"Point"}
}