{
  "type": "Feature",
  "properties": {
    "iso:country":"FR",
    "sg:address":"2 Rue Emile Souvestre Zi Mi Voie 35136 St Jacques De La Lande",
    "sg:city":"Saint-Jacques-de-la-Lande",
    "sg:classifiers":[
        {
            "category":"Shopping",
            "subcategory":"Computers & Home Electronics",
            "type":"Retail Goods"
        }
    ],
    "sg:phone":"+33 2 99 35 53 40",
    "sg:postcode":"35136",
    "sg:province":"Bretagne",
    "sg:tags":[
        "electric",
        "electricity",
        "component",
        "equipment",
        "electrical",
        "electronic"
    ],
    "wof:name":"Isolants De Bretagne",
    "wof:placetype":"venue"
},
  "geometry": {"coordinates":[-1.693249,48.089439],"type":"Point"}
}