{
  "type": "Feature",
  "properties": {
    "iso:country":"FR",
    "sg:address":"Route Nationale 7 Zone Industrielle 58320 Pougues Les Eaux",
    "sg:city":"Germigny-sur-Loire",
    "sg:classifiers":[
        {
            "category":"Wholesale",
            "subcategory":"Medical Equipment & Supplies",
            "type":"Manufacturing & Wholesale Goods"
        }
    ],
    "sg:phone":"+33 3 86 68 83 22",
    "sg:postcode":"58320",
    "sg:province":"Bourgogne",
    "sg:tags":[
        "instrument",
        "health",
        "-",
        "precision"
    ],
    "wof:name":"Etablissements Franco Et Fils",
    "wof:placetype":"venue"
},
  "geometry": {"coordinates":[3.100895,47.075207],"type":"Point"}
}