{
  "type": "Feature",
  "properties": {
    "addr:full":"9 Rue Sadi Carnot 59177 Sains Du Nord Nord Pas-de-Calais 59177",
    "addr:housenumber":"9",
    "addr:postcode":"59177;59177",
    "addr:street":"Rue Sadi Carnot;Du Nord Nord",
    "iso:country":"FR",
    "sg:address":"9 Rue Sadi Carnot 59177 Sains Du Nord",
    "sg:classifiers":[
        {
            "category":"Manufacturing",
            "subcategory":"Metals",
            "type":"Manufacturing & Wholesale Goods"
        }
    ],
    "sg:phone":"+33 3 27 59 80 00",
    "sg:postcode":"59177",
    "sg:province":"Nord Pas-de-Calais",
    "sg:tags":[
        "metallurgy",
        "metalworking",
        "processing"
    ],
    "wof:name":"L M Prodim",
    "wof:placetype":"venue"
},
  "geometry": {"coordinates":[4.003681,50.087017],"type":"Point"}
}