{
  "type": "Feature",
  "properties": {
    "addr:full":"7, Av. des Droits de l'Homme, 45000 Orl\u00e9ans Orl\u00e9ans Centre 45000",
    "addr:postcode":"45000;45000",
    "addr:street":"Av. Des Droits De L'Homme",
    "iso:country":"FR",
    "sg:address":"7, Av. des Droits de l'Homme, 45000 Orl\u00e9ans",
    "sg:city":"Orl\u00e9ans",
    "sg:orig_category":"Non-Classified Establishments",
    "sg:phone":"+33 2 38 62 52 42",
    "sg:postcode":"45000",
    "sg:province":"Centre",
    "wof:name":"Altride S.a.",
    "wof:placetype":"venue"
},
  "geometry": {"coordinates":[1.923373,47.913208],"type":"Point"}
}