{
  "type": "Feature",
  "properties": {
    "addr:full":"De Montauban Zi 74910 Seyssel Rhone-Alpes 74910",
    "addr:postcode":"74910;74910",
    "addr:street":"De;Zi",
    "iso:country":"FR",
    "sg:address":"De Montauban Zi 74910 Seyssel",
    "sg:classifiers":[
        {
            "category":"Autos & Motor Vehicles",
            "subcategory":"Automobile Sales",
            "type":"Retail Goods"
        }
    ],
    "sg:phone":"+33 4 50 59 06 25",
    "sg:postcode":"74910",
    "sg:province":"Rhone-Alpes",
    "sg:tags":[
        "equipment",
        "motor-cars",
        "transport"
    ],
    "wof:name":"Sotira 73",
    "wof:placetype":"venue"
},
  "geometry": {"coordinates":[5.836425,45.95776],"type":"Point"}
}