{
  "type": "Feature",
  "properties": {
    "addr:full":"Zone Industrielle Les Chaumes 24600 RIBERAC Rib\u00e9rac Aquitaine 24600",
    "addr:postcode":"24600;24600",
    "addr:street":"Zone Industrielle Les Chaumes",
    "iso:country":"FR",
    "sg:address":"Zone Industrielle Les Chaumes 24600 RIBERAC",
    "sg:city":"Rib\u00e9rac",
    "sg:classifiers":[
        {
            "category":"Professional",
            "subcategory":"Business Services",
            "type":"Services"
        }
    ],
    "sg:phone":"+33 5 53 90 06 19",
    "sg:postcode":"24600",
    "sg:province":"Aquitaine",
    "sg:tags":[
        "high-precision",
        "mechanic"
    ],
    "wof:name":"M.p.s.o. S.a.",
    "wof:placetype":"venue"
},
  "geometry": {"coordinates":[0.34064,45.253696],"type":"Point"}
}