{
  "type": "Feature",
  "properties": {
    "addr:full":"672, Av. de la Fleuride - ZI les Paluds, 13400 Aubagne Provence-Alpes-C\u00f4te d'Azur",
    "addr:postcode":"13400",
    "addr:street":"672 Av. De La Fleuride Zi Les Paluds",
    "iso:country":"FR",
    "sg:address":"672, Av. de la Fleuride - ZI les Paluds, 13400 Aubagne",
    "sg:orig_category":"Unclassifiable Establishments",
    "sg:phone":"+33 4 42 18 64 20",
    "sg:province":"Provence-Alpes-C\u00f4te d'Azur",
    "wof:name":"Canyon Technologies S.a.r.l.",
    "wof:placetype":"venue"
},
  "geometry": {"coordinates":[5.5687,43.292141],"type":"Point"}
}