{
  "type": "Feature",
  "properties": {
    "iso:country":"FR",
    "sg:address":"41, Rue Arthur Rozier, 75019 Paris",
    "sg:orig_category":"Non-Classified Establishments",
    "sg:phone":"+33 1 42 40 24 46",
    "sg:postcode":"75019",
    "sg:province":"Ile de France",
    "wof:name":"Emballage Service S.a.",
    "wof:placetype":"venue"
},
  "geometry": {"coordinates":[2.390586,48.878155],"type":"Point"}
}