{
  "type": "Feature",
  "properties": {
    "addr:full":"B.P. 431, 77317 Marne la Vall\u00e9e C\u00e9dex 2^^Chemindu Haha, 77183 Croissy Beaubourg Ile de France 77183",
    "addr:housenumber":"b.p. 431",
    "addr:postcode":"77317;77183;77183",
    "addr:street":"Haha",
    "iso:country":"FR",
    "sg:address":"B.P. 431, 77317 Marne la Vall\u00e9e C\u00e9dex 2^^Chemindu Haha, 77183 Croissy Beaubourg",
    "sg:orig_category":"Non-Classified Establishments",
    "sg:phone":"+33 1 60 06 08 09",
    "sg:postcode":"77183",
    "sg:province":"Ile de France",
    "wof:name":"Entreprise Robert S.a.",
    "wof:placetype":"venue"
},
  "geometry": {"coordinates":[2.659334,48.828526],"type":"Point"}
}