{
  "type": "Feature",
  "properties": {
    "iso:country":"FR",
    "sg:address":"31, Av. Georges Cl\u00e9menceau, 93420 Villepinte",
    "sg:orig_category":"Unclassifiable Establishments",
    "sg:phone":"+33 1 49 63 25 00",
    "sg:province":"Ile de France",
    "wof:name":"Crailco S.a.",
    "wof:placetype":"venue"
},
  "geometry": {"coordinates":[2.563205,48.953297],"type":"Point"}
}