{
  "type": "Feature",
  "properties": {
    "addr:full":"5, Rue Br\u00e9montier, 40140 Magescq Magescq Aquitaine 40140",
    "addr:housenumber":"5",
    "addr:postcode":"40140;40140",
    "addr:street":"Rue Bre\u0301Montier",
    "iso:country":"FR",
    "sg:address":"5, Rue Br\u00e9montier, 40140 Magescq",
    "sg:city":"Magescq",
    "sg:orig_category":"Non-Classified Establishments",
    "sg:phone":"+33 5 58 47 71 61",
    "sg:postcode":"40140",
    "sg:province":"Aquitaine",
    "wof:name":"Les Cr\u00e9ations Brocas S.a.r.l.",
    "wof:placetype":"venue"
},
  "geometry": {"coordinates":[-1.215795,43.778671],"type":"Point"}
}