{
  "type": "Feature",
  "properties": {
    "addr:full":"22 rue du Docteur Gallet 74300 Cluses Rhone-Alpes 74300",
    "addr:housenumber":"22",
    "addr:postcode":"74300;74300",
    "addr:street":"Rue Du Docteur Gallet",
    "iso:country":"FR",
    "sg:address":"22 rue du Docteur Gallet 74300 Cluses",
    "sg:orig_category":"Hydraulic Systems For Models",
    "sg:phone":"+33 4 50 98 11 97",
    "sg:postcode":"74300",
    "sg:province":"Rhone-Alpes",
    "wof:name":"Robydro S.a.r.l.",
    "wof:placetype":"venue"
},
  "geometry": {"coordinates":[6.568757,46.075851],"type":"Point"}
}