{
  "type": "Feature",
  "properties": {
    "addr:full":"Zac Les Montagnes 16430 Champniers Poitou-Charentes 16430",
    "addr:postcode":"16430;16430",
    "addr:street":"Zac Les Montagnes",
    "iso:country":"FR",
    "sg:address":"Zac Les Montagnes 16430 Champniers",
    "sg:classifiers":[
        {
            "category":"Utilities",
            "subcategory":"Electric",
            "type":"Services"
        }
    ],
    "sg:phone":"+33 5 45 93 01 10",
    "sg:postcode":"16430",
    "sg:province":"Poitou-Charentes",
    "sg:tags":[
        "electricity",
        "electronic",
        "electrical",
        "equipment"
    ],
    "wof:name":"Technor Atex",
    "wof:placetype":"venue"
},
  "geometry": {"coordinates":[0.207096,45.714806],"type":"Point"}
}