{
  "type": "Feature",
  "properties": {
    "iso:country":"FR",
    "sg:address":"40 av Jean Jaur\u00e8s; Lugon",
    "sg:classifiers":[
        {
            "category":"Banks & Credit Unions",
            "subcategory":"Bank",
            "type":"Services"
        }
    ],
    "sg:phone":"+33 3357844361",
    "sg:province":"Champagne",
    "wof:name":"Cr\u00e9dit Agricole Mutuel, Du Libournais",
    "wof:placetype":"venue"
},
  "geometry": {"coordinates":[-115.325089,35.779202],"type":"Point"}
}