{
  "type": "Feature",
  "properties": {
    "addr:full":"Route De Sottevast Za Armanville 50700 Valognes Valognes Basse Normandie 50700",
    "addr:postcode":"50700;50700",
    "addr:street":"Route De Sottevast Za Armanville",
    "iso:country":"FR",
    "sg:address":"Route De Sottevast Za Armanville 50700 Valognes",
    "sg:city":"Valognes",
    "sg:classifiers":[
        {
            "category":"Manufacturing",
            "subcategory":"Textiles",
            "type":"Manufacturing & Wholesale Goods"
        }
    ],
    "sg:phone":"+33 2 33 21 08 88",
    "sg:postcode":"50700",
    "sg:province":"Basse Normandie",
    "sg:tags":[
        "clothing",
        "accessory"
    ],
    "wof:name":"Adn Couture",
    "wof:placetype":"venue"
},
  "geometry": {"coordinates":[-1.43503,49.451469],"type":"Point"}
}