{
  "type": "Feature",
  "properties": {
    "addr:full":"Lamerey 88270 Dompaire Lorraine 88270",
    "addr:postcode":"88270;88270",
    "addr:street":"Lamerey",
    "iso:country":"FR",
    "sg:address":"Lamerey 88270 Dompaire",
    "sg:orig_category":"Non-Classified Establishments",
    "sg:phone":"+33 3 29 36 52 42",
    "sg:postcode":"88270",
    "sg:province":"Lorraine",
    "wof:name":"Bazard Etablissements S.a.",
    "wof:placetype":"venue"
},
  "geometry": {"coordinates":[6.23104,48.220379],"type":"Point"}
}