{
  "type": "Feature",
  "properties": {
    "addr:full":"177, Rue Jeanne Jugan, 50407 Granville C\u00e9dex Basse-Normandie",
    "addr:housenumber":"177",
    "addr:postcode":"50407",
    "addr:street":"Rue Jeanne Jugan",
    "iso:country":"FR",
    "sg:address":"177, Rue Jeanne Jugan, 50407 Granville C\u00e9dex",
    "sg:orig_category":"Non-Classified Establishments",
    "sg:phone":"+33 2 33 50 27 92",
    "sg:province":"Basse-Normandie",
    "wof:name":"Flashmer S.a",
    "wof:placetype":"venue"
},
  "geometry": {"coordinates":[-1.58158,48.834393],"type":"Point"}
}