{
  "type": "Feature",
  "properties": {
    "addr:full":"77515 Faremoutiers^^2, Rue Favier - ZI P\u00e9chiney - Pommeuse , 77515 Pommeuse Ile de France",
    "addr:postcode":"77515;77515",
    "addr:street":"Rue Favier Zi Pe\u0301Chiney;Ile De France",
    "iso:country":"FR",
    "sg:address":"77515 Faremoutiers^^2, Rue Favier - ZI P\u00e9chiney - Pommeuse , 77515 Pommeuse",
    "sg:orig_category":"Non-Classified Establishments",
    "sg:phone":"+33 1 64 65 30 20",
    "sg:province":"Ile de France",
    "wof:name":"Intercal S.a.",
    "wof:placetype":"venue"
},
  "geometry": {"coordinates":[3.015135,48.816429],"type":"Point"}
}