{
  "type": "Feature",
  "properties": {
    "addr:full":"52, Rue de Dornach, 68120 Pfastatt Pfastatt Alsace 68120",
    "addr:housenumber":"52",
    "addr:postcode":"68120;68120",
    "addr:street":"Rue De Dornach;Pfastatt",
    "iso:country":"FR",
    "sg:address":"52, Rue de Dornach, 68120 Pfastatt",
    "sg:city":"Pfastatt",
    "sg:orig_category":"Unclassifiable Establishments",
    "sg:phone":"+33 3 89 50 72 72",
    "sg:postcode":"68120",
    "sg:province":"Alsace",
    "wof:name":"I.f.s. France S.a. - Industrial And Financial Systems",
    "wof:placetype":"venue"
},
  "geometry": {"coordinates":[7.293755,47.760067],"type":"Point"}
}