{
  "type": "Feature",
  "properties": {
    "iso:country":"FR",
    "sg:address":"112, Tssede la Serviane, 13012 Marseille",
    "sg:orig_category":"Unclassifiable Establishments",
    "sg:phone":"+33 4 91 87 58 75",
    "sg:province":"Poitou-Charentes",
    "wof:name":"T.g. Soft S.a.",
    "wof:placetype":"venue"
},
  "geometry": {"coordinates":[5.416456,43.305122],"type":"Point"}
}