{
  "type": "Feature",
  "properties": {
    "addr:full":"1, All\u00e9e Louis Renault, 41100 Vend\u00f4me Vend\u00f4me Centre 41100",
    "addr:housenumber":"1",
    "addr:postcode":"41100",
    "addr:street":"Alle\u0301E Louis Renault",
    "iso:country":"FR",
    "sg:address":"1, All\u00e9e Louis Renault, 41100 Vend\u00f4me",
    "sg:city":"Vend\u00f4me",
    "sg:orig_category":"Unclassifiable Establishments",
    "sg:phone":"+33 2 54 89 06 06",
    "sg:postcode":"41100",
    "sg:province":"Centre",
    "wof:name":"D.j.c. Vend\u00f4me S.a.r.l.",
    "wof:placetype":"venue"
},
  "geometry": {"coordinates":[1.072885,47.775894],"type":"Point"}
}