{
  "type": "Feature",
  "properties": {
    "addr:full":"90, Rue de Bic\u00eatre, 94240 L'Ha\u00ff les Roses Ile de France 94240",
    "addr:housenumber":"90",
    "addr:postcode":"94240;94240",
    "addr:street":"Rue De Bice\u0302Tre;\u0308",
    "iso:country":"FR",
    "sg:address":"90, Rue de Bic\u00eatre, 94240 L'Ha\u00ff les Roses",
    "sg:orig_category":"Non-Classified Establishments",
    "sg:phone":"+33 1 46 86 60 73",
    "sg:postcode":"94240",
    "sg:province":"Ile de France",
    "wof:name":"Entreprise Leli\u00e8vre S.a.r.l.",
    "wof:placetype":"venue"
},
  "geometry": {"coordinates":[2.352882,48.77494],"type":"Point"}
}