{
  "type": "Feature",
  "properties": {
    "addr:full":"58, Rte de Nantes, 85000 La Roche sur Yon Pays de Loire",
    "addr:housenumber":"58",
    "addr:postcode":"85000",
    "addr:street":"Rte De Nantes;Roche;Yon",
    "iso:country":"FR",
    "sg:address":"58, Rte de Nantes, 85000 La Roche sur Yon",
    "sg:orig_category":"Non-Classified Establishments",
    "sg:phone":"+33 2 51 36 23 52",
    "sg:province":"Pays de Loire",
    "wof:name":"S.u.o.m.a. S.a. - Soci\u00e9t\u00e9 D'utilisation D'orientation De Mat\u00e9riel Agricole",
    "wof:placetype":"venue"
},
  "geometry": {"coordinates":[-1.42987,46.702049],"type":"Point"}
}