{
  "type": "Feature",
  "properties": {
    "iso:country":"FR",
    "sg:address":"Rn 20 36200 Celon",
    "sg:city":"Celon",
    "sg:classifiers":[
        {
            "category":"Professional",
            "type":"Services"
        }
    ],
    "sg:phone":"+33 2 54 25 33 01",
    "sg:postcode":"36200",
    "sg:province":"Centre",
    "sg:tags":[
        "transport",
        "road"
    ],
    "wof:name":"Autissier Transports Sa",
    "wof:placetype":"venue"
},
  "geometry": {"coordinates":[1.49964,46.519215],"type":"Point"}
}