{
  "type": "Feature",
  "properties": {
    "addr:full":"Zi Du Pont Pannay 4 R Champs Ely\u00e9ses 03500 St Pour\u00e7ain Sur Sioul Ch\u00e2tel-de-Neuvre Auvergne 03500",
    "addr:housenumber":"4 r",
    "addr:postcode":"03500;03500",
    "addr:street":"Zi Du Pont Pannay;Champs Elye\u0301Ses;Cha\u0302Tel-De-Neuvre",
    "iso:country":"FR",
    "sg:address":"Zi Du Pont Pannay 4 R Champs Ely\u00e9ses 03500 St Pour\u00e7ain Sur Sioul",
    "sg:city":"Ch\u00e2tel-de-Neuvre",
    "sg:classifiers":[
        {
            "category":"Manufacturing",
            "subcategory":"Glass & Minerals",
            "type":"Manufacturing & Wholesale Goods"
        }
    ],
    "sg:phone":"+33 4 70 45 70 45",
    "sg:postcode":"03500",
    "sg:province":"Auvergne",
    "sg:tags":[
        "building",
        "material"
    ],
    "wof:name":"Potters Europe Sa",
    "wof:placetype":"venue"
},
  "geometry": {"coordinates":[3.298581,46.308075],"type":"Point"}
}