{
  "type": "Feature",
  "properties": {
    "iso:country":"FR",
    "sg:address":"Av. Emmanuel Pontremoli - ZAC Nice la Plaine 1 - B\u00e2timent F4",
    "sg:city":"Nice",
    "sg:orig_category":"Unclassifiable Establishments",
    "sg:phone":"+33 4 92 29 60 30",
    "sg:postcode":"06200",
    "sg:province":"Provence-Alpes-C\u00f4te d'Azur",
    "wof:name":"S.l.e. S.a.r.l.",
    "wof:placetype":"venue"
},
  "geometry": {"coordinates":[7.215093,43.745003],"type":"Point"}
}