{
  "type": "Feature",
  "properties": {
    "iso:country":"FR",
    "sg:address":"13 Rue Du Perigord 69330 Meyzieu",
    "sg:classifiers":[
        {
            "category":"Manufacturing",
            "subcategory":"Rubber & Plastics",
            "type":"Manufacturing & Wholesale Goods"
        }
    ],
    "sg:phone":"+33 4 78 31 00 22",
    "sg:postcode":"69330",
    "sg:province":"Rhone-Alpes",
    "wof:name":"Etablissements Aubert",
    "wof:placetype":"venue"
},
  "geometry": {"coordinates":[5.021178,45.759712],"type":"Point"}
}