{
  "type": "Feature",
  "properties": {
    "addr:full":"12, Rue Adrien Lomme, 60400 Noyon Picardie",
    "addr:housenumber":"12",
    "addr:postcode":"60400",
    "addr:street":"Rue Adrien",
    "iso:country":"FR",
    "sg:address":"12, Rue Adrien Lomme, 60400 Noyon",
    "sg:orig_category":"Unclassifiable Establishments",
    "sg:phone":"+33 3 44 09 68 68",
    "sg:province":"Picardie",
    "wof:name":"Point P Nord S.a.",
    "wof:placetype":"venue"
},
  "geometry": {"coordinates":[3.022669,49.572285],"type":"Point"}
}