{
  "type": "Feature",
  "properties": {
    "addr:full":"115, Rte de Launaguet, 31500 Toulouse Midi Pyr\u00e9n\u00e9es",
    "addr:housenumber":"115",
    "addr:postcode":"31500",
    "addr:street":"Rte De Launaguet",
    "iso:country":"FR",
    "sg:address":"115, Rte de Launaguet, 31500 Toulouse",
    "sg:orig_category":"Unclassifiable Establishments",
    "sg:phone":"+33 5 61 47 95 86",
    "sg:province":"Midi Pyr\u00e9n\u00e9es",
    "wof:name":"Etablissement Bernad",
    "wof:placetype":"venue"
},
  "geometry": {"coordinates":[1.43907,43.636711],"type":"Point"}
}