{
  "type": "Feature",
  "properties": {
    "iso:country":"FR",
    "sg:address":"Za Le Vivier 85430 Nieul Le Dolent",
    "sg:classifiers":[
        {
            "category":"Manufacturing",
            "subcategory":"Tools & Machinery",
            "type":"Manufacturing & Wholesale Goods"
        }
    ],
    "sg:phone":"+33 2 51 07 91 40",
    "sg:postcode":"85430",
    "sg:province":"Pays de Loire",
    "sg:tags":[
        "environment",
        "equipment",
        "-"
    ],
    "wof:name":"Cp Composites",
    "wof:placetype":"venue"
},
  "geometry": {"coordinates":[-1.510134,46.575214],"type":"Point"}
}