{
  "type": "Feature",
  "properties": {
    "addr:full":"27, Rue des Tilleuls - Espace des Vergers, 78960 Voisins le Bretonneux Ile de France",
    "addr:housenumber":"27",
    "addr:postcode":"78960",
    "addr:street":"Rue Des Tilleuls Espace Des Vergers",
    "iso:country":"FR",
    "sg:address":"27, Rue des Tilleuls - Espace des Vergers, 78960 Voisins le Bretonneux",
    "sg:orig_category":"Non-Classified Establishments",
    "sg:phone":"+33 1 30 64 98 76",
    "sg:province":"Ile de France",
    "wof:name":"Omicron S.a.r.l.",
    "wof:placetype":"venue"
},
  "geometry": {"coordinates":[2.051481,48.758369],"type":"Point"}
}