{
  "type": "Feature",
  "properties": {
    "iso:country":"FR",
    "sg:address":"77, Rue Henri Giffard, 87280 Limoges",
    "sg:orig_category":"Unclassifiable Establishments",
    "sg:phone":"+33 5 55 38 30 19",
    "sg:province":"Limousin",
    "wof:name":"Pergay Salaisons S.a.",
    "wof:placetype":"venue"
},
  "geometry": {"coordinates":[1.264314,45.880154],"type":"Point"}
}