{
  "type": "Feature",
  "properties": {
    "iso:country":"FR",
    "sg:address":"15, Rue Victor Hugo, 69370 Saint Didier au Mont d'Or",
    "sg:orig_category":"Non-Classified Establishments",
    "sg:phone":"+33 4 78 66 81 00",
    "sg:postcode":"69370",
    "sg:province":"Rhone-Alpes",
    "wof:name":"B.j.p.s. S.a.r.l.",
    "wof:placetype":"venue"
},
  "geometry": {"coordinates":[4.794476,45.829563],"type":"Point"}
}