{
  "type": "Feature",
  "properties": {
    "addr:full":"ZI Inova 3000 - All\u00e9e N\u00b02 Thaon les Vosges Lorraine 88150",
    "addr:housenumber":"3000",
    "addr:postcode":"88150",
    "addr:street":"Alle\u0301E N\u00b02",
    "iso:country":"FR",
    "sg:address":"ZI Inova 3000 - All\u00e9e N\u00b02",
    "sg:city":"Thaon les Vosges",
    "sg:orig_category":"Non-Classified Establishments",
    "sg:phone":"+33 3 29 39 45 63",
    "sg:postcode":"88150",
    "sg:province":"Lorraine",
    "wof:name":"Transport Lobisommer S.a.",
    "wof:placetype":"venue"
},
  "geometry": {"coordinates":[6.41948,48.250435],"type":"Point"}
}