{
  "type": "Feature",
  "properties": {
    "iso:country":"FR",
    "sg:address":"N\u00b01 Les Broges 33240 Salignac",
    "sg:city":"Salignac",
    "sg:classifiers":[
        {
            "category":"Home & Garden",
            "subcategory":"Furniture",
            "type":"Retail Goods"
        }
    ],
    "sg:phone":"+33 5 57 43 20 79",
    "sg:postcode":"33240",
    "sg:province":"Aquitaine",
    "sg:tags":[
        "wood"
    ],
    "wof:name":"Sogibois",
    "wof:placetype":"venue"
},
  "geometry": {"coordinates":[-0.333284,44.95092],"type":"Point"}
}