{
  "type": "Feature",
  "properties": {
    "addr:full":"8, Rue Guillaume de Nautonnier, 81100 Castres Midi Pyr\u00e9n\u00e9es",
    "addr:housenumber":"8",
    "addr:postcode":"81100",
    "addr:street":"Rue Guillaume De Nautonnier",
    "iso:country":"FR",
    "sg:address":"8, Rue Guillaume de Nautonnier, 81100 Castres",
    "sg:orig_category":"Non-Classified Establishments",
    "sg:phone":"+33 5 63 62 50 50",
    "sg:province":"Midi Pyr\u00e9n\u00e9es",
    "wof:name":"Frans Maas Sud Transports Internationaux S.n.c.",
    "wof:placetype":"venue"
},
  "geometry": {"coordinates":[2.266462,43.593445],"type":"Point"}
}