{
  "type": "Feature",
  "properties": {
    "addr:full":"2, Rue Aumontzey, 88640 Jussarupt Lorraine",
    "addr:housenumber":"2",
    "addr:postcode":"88640",
    "addr:street":"Rue Aumontzey",
    "iso:country":"FR",
    "sg:address":"2, Rue Aumontzey, 88640 Jussarupt",
    "sg:orig_category":"Unclassifiable Establishments",
    "sg:phone":"+33 3 29 52 69 69",
    "sg:province":"Lorraine",
    "wof:name":"Gaiffe Claude S.a.r.l.",
    "wof:placetype":"venue"
},
  "geometry": {"coordinates":[6.790101,48.145267],"type":"Point"}
}