{
  "type": "Feature",
  "properties": {
    "addr:full":"Zac Des Batterses 01700 Beynost Rhone-Alpes 01700",
    "addr:housenumber":"zac",
    "addr:postcode":"01700;01700",
    "addr:street":"Des Batterses",
    "iso:country":"FR",
    "sg:address":"Zac Des Batterses 01700 Beynost",
    "sg:classifiers":[
        {
            "category":"Travel",
            "subcategory":"Hotels & Motels",
            "type":"Entertainment"
        }
    ],
    "sg:phone":"+33 4 72 88 20 99",
    "sg:postcode":"01700",
    "sg:province":"Rhone-Alpes",
    "sg:tags":[
        "hotels",
        "business",
        "restaurant"
    ],
    "wof:name":"Eurl Djr",
    "wof:placetype":"venue"
},
  "geometry": {"coordinates":[5.002065,45.840061],"type":"Point"}
}