{
  "type": "Feature",
  "properties": {
    "addr:full":"Lieu Dit Les Beaux Jours 71710 Les Bizots Les Bizots Bourgogne 71710",
    "addr:postcode":"71710;71710",
    "addr:street":"Lieu Dit Les;Bizots",
    "iso:country":"FR",
    "sg:address":"Lieu Dit Les Beaux Jours 71710 Les Bizots",
    "sg:city":"Les Bizots",
    "sg:classifiers":[
        {
            "category":"Manufacturing",
            "subcategory":"Jewelry",
            "type":"Manufacturing & Wholesale Goods"
        }
    ],
    "sg:phone":"+33 3 85 55 15 21",
    "sg:postcode":"71710",
    "sg:province":"Bourgogne",
    "sg:tags":[
        "product",
        "miscellaneous",
        "jewellery"
    ],
    "wof:name":"Legros Joaillerie",
    "wof:placetype":"venue"
},
  "geometry": {"coordinates":[4.371505,46.770645],"type":"Point"}
}