{
  "type": "Feature",
  "properties": {
    "iso:country":"FR",
    "sg:address":"Zac Les Portes De L Oise Batiments 6 Et 7 60230 Chambly",
    "sg:classifiers":[
        {
            "category":"Transit Center",
            "subcategory":"Freight",
            "type":"Transportation"
        }
    ],
    "sg:phone":"+33 1 30 28 98 80",
    "sg:postcode":"60230",
    "sg:province":"Picardie",
    "sg:tags":[
        "metallurgy",
        "pipe",
        "metalworking",
        "sheet"
    ],
    "wof:name":"Cosel Societe Anonyme",
    "wof:placetype":"venue"
},
  "geometry": {"coordinates":[2.24453,49.166466],"type":"Point"}
}