{
  "type": "Feature",
  "properties": {
    "iso:country":"FR",
    "sg:address":"57 T Boulevard Lascrosses",
    "sg:city":"Toulouse",
    "sg:classifiers":[
        {
            "category":"Banks & Credit Unions",
            "subcategory":"Financial Services",
            "type":"Services"
        }
    ],
    "sg:phone":"+33 5 62 30 56 56",
    "sg:postcode":"31000",
    "sg:province":"Midi Pyr\u00e9n\u00e9es",
    "sg:tags":[
        "banking",
        "finance",
        "insurance"
    ],
    "wof:name":"Societe D'expertise Comptabilite Controle Conseil (e 3 C)",
    "wof:placetype":"venue"
},
  "geometry": {"coordinates":[1.430785,43.608826],"type":"Point"}
}