{
  "type": "Feature",
  "properties": {
    "iso:country":"FR",
    "sg:address":"4, Rue Fr\u00e9d\u00e9ric Sauvage - ZI Martigues Sud, 13500 Martigues",
    "sg:city":"Artigue",
    "sg:orig_category":"Unclassifiable Establishments",
    "sg:phone":"+33 4 42 07 22 00",
    "sg:postcode":"31110",
    "sg:province":"Midi Pyr\u00e9n\u00e9es",
    "wof:name":"Manpower S.a.s.",
    "wof:placetype":"venue"
},
  "geometry": {"coordinates":[5.055235,43.406536],"type":"Point"}
}