{
  "type": "Feature",
  "properties": {
    "iso:country":"FR",
    "sg:address":"9, Rue Raoul Dautry, 91190 Gif sur Yvette",
    "sg:orig_category":"Non-Classified Establishments",
    "sg:phone":"+33 1 69 07 29 22",
    "sg:postcode":"91190",
    "sg:province":"Ile de France",
    "wof:name":"C.a.d.l.m. S.a.r.l.",
    "wof:placetype":"venue"
},
  "geometry": {"coordinates":[2.137129,48.699062],"type":"Point"}
}