{
  "type": "Feature",
  "properties": {
    "iso:country":"FR",
    "sg:address":"4 Rue De Picardie 92140 Clamart",
    "sg:classifiers":[
        {
            "category":"Bakery",
            "type":"Food & Drink"
        }
    ],
    "sg:phone":"+33 1 46 30 80 16",
    "sg:postcode":"92140",
    "sg:province":"Ile de France",
    "sg:tags":[
        "cake",
        "product",
        "related",
        "bread"
    ],
    "wof:name":"Lesage Christian",
    "wof:placetype":"venue"
},
  "geometry": {"coordinates":[2.245818,48.78558],"type":"Point"}
}