{
  "type": "Feature",
  "properties": {
    "iso:country":"FR",
    "sg:address":"B.P. 166, 17005 La Rochelle Cedex^^15 bis, Rue de l'Ouvrage \u00e0 Cornes, 17000 La Rochelle",
    "sg:orig_category":"Non-Classified Establishments",
    "sg:phone":"+33 5 46 28 02 10",
    "sg:postcode":"17000",
    "sg:province":"Poitou-Charentes",
    "wof:name":"B.n.p. Paris-bas Lease Group",
    "wof:placetype":"venue"
},
  "geometry": {"coordinates":[-1.149421,46.160576],"type":"Point"}
}