{
  "type": "Feature",
  "properties": {
    "iso:country":"FR",
    "sg:address":"188 Allee De Montfermeil 93220 Gagny",
    "sg:classifiers":[
        {
            "category":"Professional",
            "subcategory":"Advertising",
            "type":"Services"
        }
    ],
    "sg:phone":"+33 1 43 81 72 02",
    "sg:postcode":"93220",
    "sg:province":"Ile de France",
    "sg:tags":[
        "communication",
        "medium"
    ],
    "wof:name":"Amd Design (amdm)",
    "wof:placetype":"venue"
},
  "geometry": {"coordinates":[2.53952,48.899361],"type":"Point"}
}