{
  "type": "Feature",
  "properties": {
    "iso:country":"FR",
    "sg:address":"21, Rue Jacques Brel, 38320 Poisat",
    "sg:orig_category":"Non-Classified Establishments",
    "sg:phone":"+33 4 76 24 72 72",
    "sg:postcode":"38320",
    "sg:province":"Rhone-Alpes",
    "wof:name":"Alias S.a.r.l.",
    "wof:placetype":"venue"
},
  "geometry": {"coordinates":[5.75846,45.156132],"type":"Point"}
}