{
  "type": "Feature",
  "properties": {
    "iso:country":"FR",
    "sg:address":"B.P. 96, 41102 Vend\u00f4me C\u00e9dex^^30, Rte de Courtiras, 41100 Vend\u00f4me",
    "sg:city":"Vend\u00f4me",
    "sg:orig_category":"Non-Classified Establishments",
    "sg:phone":"+33 2 54 73 60 00",
    "sg:postcode":"41100",
    "sg:province":"Centre",
    "wof:name":"Polyproc S.a.s.",
    "wof:placetype":"venue"
},
  "geometry": {"coordinates":[1.17829,47.712414],"type":"Point"}
}