{
  "type": "Feature",
  "properties": {
    "iso:country":"FR",
    "sg:address":"ZI de Moulinveau - Saint Jean d'Angely",
    "sg:city":"La Vergne",
    "sg:orig_category":"Unclassifiable Establishments",
    "sg:phone":"+33 5 46 32 24 68",
    "sg:postcode":"17400",
    "sg:province":"Poitou-Charentes",
    "wof:name":"A.m. Polymat S.a.r.l.",
    "wof:placetype":"venue"
},
  "geometry": {"coordinates":[-0.550582,45.964554],"type":"Point"}
}