{
  "type": "Feature",
  "properties": {
    "iso:country":"FR",
    "sg:address":"R DE L'ABBAYE Z I DE JOUX ARNAS NORD 69400 ARNAS",
    "sg:orig_category":"Games and entertainment Horticulture Mechanical Engineering - machines Metals - machinery and equipm",
    "sg:phone":"+33 4 74 62 48 48",
    "sg:postcode":"69400",
    "sg:province":"Rhone-Alpes",
    "wof:name":"Exel Gsa",
    "wof:placetype":"venue"
},
  "geometry": {"coordinates":[4.720333,45.990887],"type":"Point"}
}