{
  "type": "Feature",
  "properties": {
    "addr:full":"24 bd Jean-Pierre Calloch 56100 Lorient Lorient Bretagne 56100",
    "addr:housenumber":"24",
    "addr:postcode":"56100;56100",
    "addr:street":"Bd Jean-Pierre Calloch",
    "iso:country":"FR",
    "sg:address":"24 bd Jean-Pierre Calloch 56100 Lorient",
    "sg:city":"Lorient",
    "sg:classifiers":[
        {
            "category":"Manufacturing",
            "subcategory":"Motor Vehicles & Parts",
            "type":"Manufacturing & Wholesale Goods"
        }
    ],
    "sg:phone":"+33 2 97 37 04 66",
    "sg:postcode":"56100",
    "sg:province":"Bretagne",
    "sg:tags":[
        "precision",
        "mechanic"
    ],
    "wof:name":"Sa Des Ateliers Normand",
    "wof:placetype":"venue"
},
  "geometry": {"coordinates":[-3.366329,47.732311],"type":"Point"}
}