{
  "type": "Feature",
  "properties": {
    "addr:full":"Kerebars 29820 Guilers Guilers Bretagne 29820",
    "addr:postcode":"29820;29820",
    "addr:street":"Kerebars",
    "iso:country":"FR",
    "sg:address":"Kerebars 29820 Guilers",
    "sg:city":"Guilers",
    "sg:classifiers":[
        {
            "category":"Food & Beverages",
            "subcategory":"Groceries & Convenience Stores",
            "type":"Retail Goods"
        }
    ],
    "sg:phone":"+33 2 98 07 54 07",
    "sg:postcode":"29820",
    "sg:province":"Bretagne",
    "sg:tags":[
        "product",
        "related"
    ],
    "wof:name":"Les Maitres Traiteurs Brestois",
    "wof:placetype":"venue"
},
  "geometry": {"coordinates":[-4.576271,48.424911],"type":"Point"}
}