{
  "type": "Feature",
  "properties": {
    "addr:full":"Rue Gustave Eiffel - ZI la Chazotte La Talaudi\u00e8re Rhone-Alpes 42350",
    "addr:postcode":"42350",
    "addr:street":"Rue Gustave Eiffel Zi La Chazotte La;Rhone-Alpes",
    "iso:country":"FR",
    "sg:address":"Rue Gustave Eiffel - ZI la Chazotte",
    "sg:city":"La Talaudi\u00e8re",
    "sg:orig_category":"Non-Classified Establishments",
    "sg:phone":"+33 4 77 53 04 91",
    "sg:postcode":"42350",
    "sg:province":"Rhone-Alpes",
    "wof:name":"M.g.b.f. S.a.r.l. - M\u00e9canique G\u00e9n\u00e9rale Bouillet Fr\u00e8res",
    "wof:placetype":"venue"
},
  "geometry": {"coordinates":[4.434398,45.481918],"type":"Point"}
}