{
  "type": "Feature",
  "properties": {
    "iso:country":"FR",
    "sg:address":"B.P. 74, 42502 Le Chambon Feugerolles C\u00e9dex 02^^31, Rue Honor\u00e9 d'Urf\u00e9, 42500 Le Chambon Feugerolles",
    "sg:orig_category":"Non-Classified Establishments",
    "sg:phone":"+33 4 77 56 43 84",
    "sg:postcode":"42500",
    "sg:province":"Rhone-Alpes",
    "wof:name":"F.p.i. S.a.s. - Fourneyron Packaging International",
    "wof:placetype":"venue"
},
  "geometry": {"coordinates":[4.346466,45.394665],"type":"Point"}
}