{
  "type": "Feature",
  "properties": {
    "addr:full":"B.P. 74, 42502 Le Chambon Feugerolles C\u00e9dex 02^^31, Rue Honor\u00e9 d'Urf\u00e9, 42500 Le Chambon Feugerolles Rhone-Alpes 42500",
    "addr:housenumber":"02 ^ ^ 31",
    "addr:postcode":"42502;42500;42500",
    "addr:street":"B.P. 74;Chambon;Ce\u0301Dex;Rue Honore\u0301 D'Urfe \u0301;Chambon Feugerolles Rhone-Alpes",
    "iso:country":"FR",
    "sg:address":"B.P. 74, 42502 Le Chambon Feugerolles C\u00e9dex 02^^31, Rue Honor\u00e9 d'Urf\u00e9, 42500 Le Chambon Feugerolles",
    "sg:orig_category":"Non-Classified Establishments",
    "sg:phone":"+33 4 77 56 43 84",
    "sg:postcode":"42500",
    "sg:province":"Rhone-Alpes",
    "wof:name":"F.p.i. S.a.s. - Fourneyron Packaging International",
    "wof:placetype":"venue"
},
  "geometry": {"coordinates":[4.346466,45.394665],"type":"Point"}
}