{
  "type": "Feature",
  "properties": {
    "addr:full":"ZI le Bas du Ponte Saint Symphorien d'Ozon Rhone-Alpes 69360",
    "addr:postcode":"69360",
    "addr:street":"Zi Le Bas Du Ponte Saint;D'Ozon Rhone-Alpes",
    "iso:country":"FR",
    "sg:address":"ZI le Bas du Ponte",
    "sg:city":"Saint Symphorien d'Ozon",
    "sg:orig_category":"Non-Classified Establishments",
    "sg:phone":"+33 4 78 02 83 97",
    "sg:postcode":"69360",
    "sg:province":"Rhone-Alpes",
    "wof:name":"Transport Romieu S.a.",
    "wof:placetype":"venue"
},
  "geometry": {"coordinates":[4.85609,45.634979],"type":"Point"}
}