{
  "type": "Feature",
  "properties": {
    "iso:country":"FR",
    "sg:address":"Le Haut S\u00e9vrac 35470 Bain De Bretagne",
    "sg:city":"Bain-de-Bretagne",
    "sg:classifiers":[
        {
            "category":"Personal",
            "subcategory":"Shoe Repair & Shine",
            "type":"Services"
        }
    ],
    "sg:phone":"+33 2 99 43 92 55",
    "sg:postcode":"35470",
    "sg:province":"Bretagne",
    "sg:tags":[
        "product",
        "leather",
        "material",
        "-",
        "miscellaneous",
        "raw"
    ],
    "wof:name":"Marche Au Cuirs De L'ouest Sa",
    "wof:placetype":"venue"
},
  "geometry": {"coordinates":[-1.702499,47.825695],"type":"Point"}
}