{
  "type": "Feature",
  "properties": {
    "iso:country":"FR",
    "sg:address":"18 ter, Rue de Chateaudun, 31000 Toulouse",
    "sg:orig_category":"Unclassifiable Establishments",
    "sg:phone":"+33 5 61 62 99 37",
    "sg:province":"Midi Pyr\u00e9n\u00e9es",
    "wof:name":"S.e.c.a.f. S.a.r.l. - Soci\u00e9t\u00e9 Expertise Comptable Alain Frouvelle",
    "wof:placetype":"venue"
},
  "geometry": {"coordinates":[1.445709,43.614983],"type":"Point"}
}