{
  "type": "Feature",
  "properties": {
    "addr:full":"Rue Lavoisier - ZI Coss\u00e9 le Vivien Pays de Loire 53230",
    "addr:postcode":"53230",
    "addr:street":"Rue Lavoisier Zi Cosse\u0301 Le Vivien",
    "iso:country":"FR",
    "sg:address":"Rue Lavoisier - ZI",
    "sg:city":"Coss\u00e9 le Vivien",
    "sg:orig_category":"Unclassifiable Establishments",
    "sg:phone":"+33 2 43 98 83 60",
    "sg:postcode":"53230",
    "sg:province":"Pays de Loire",
    "wof:name":"Etablissements Heuveline S.a.r.l.",
    "wof:placetype":"venue"
},
  "geometry": {"coordinates":[-0.916009,47.89838],"type":"Point"}
}