{
  "type": "Feature",
  "properties": {
    "iso:country":"FR",
    "sg:address":"Z I Les Grands Jardins 04220 Ste Tulle",
    "sg:classifiers":[
        {
            "category":"Home & Garden",
            "subcategory":"Furniture",
            "type":"Retail Goods"
        }
    ],
    "sg:phone":"+33 4 92 79 79 79",
    "sg:province":"Poitou-Charentes",
    "sg:tags":[
        "household",
        "wood"
    ],
    "wof:name":"Louis Avarello Sarl",
    "wof:placetype":"venue"
},
  "geometry": {"coordinates":[5.76545,43.778259],"type":"Point"}
}