{
  "type": "Feature",
  "properties": {
    "addr:full":"43, Rue du Commandant Rolland, 93350 Le Bourget Ile de France 93350",
    "addr:housenumber":"43",
    "addr:postcode":"93350;93350",
    "addr:street":"Rue Du Commandant Rolland",
    "iso:country":"FR",
    "sg:address":"43, Rue du Commandant Rolland, 93350 Le Bourget",
    "sg:orig_category":"Non-Classified Establishments",
    "sg:phone":"+33 1 48 38 45 45",
    "sg:postcode":"93350",
    "sg:province":"Ile de France",
    "wof:name":"Boon Edam S.a.",
    "wof:placetype":"venue"
},
  "geometry": {"coordinates":[2.431028,48.933052],"type":"Point"}
}