{
  "type": "Feature",
  "properties": {
    "iso:country":"FR",
    "sg:address":"76, Av. des Mimosas, 64700 Hendaye",
    "sg:city":"Hendaye",
    "sg:orig_category":"Unclassifiable Establishments",
    "sg:phone":"+33 5 59 48 88 88",
    "sg:postcode":"64700",
    "sg:province":"Aquitaine",
    "wof:name":"H\u00f4tel Concorde Ibaia Iru S.n.c.",
    "wof:placetype":"venue"
},
  "geometry": {"coordinates":[-1.782343,43.371098],"type":"Point"}
}