{
  "type": "Feature",
  "properties": {
    "iso:country":"FR",
    "sg:address":"Zone Industrielle 45270 Bellegarde",
    "sg:city":"Bellegarde",
    "sg:classifiers":[
        {
            "category":"Shopping",
            "subcategory":"Computers & Home Electronics",
            "type":"Retail Goods"
        }
    ],
    "sg:phone":"+33 2 38 90 41 90",
    "sg:postcode":"45270",
    "sg:province":"Centre",
    "sg:tags":[
        "electronic",
        "module"
    ],
    "wof:name":"Corel Electronique Sa",
    "wof:placetype":"venue"
},
  "geometry": {"coordinates":[2.4431,47.989429],"type":"Point"}
}