{
  "type": "Feature",
  "properties": {
    "addr:full":"Gare Saint Amatre Auxerre Bourgogne 89000",
    "addr:postcode":"89000",
    "addr:street":"Bourgogne",
    "iso:country":"FR",
    "sg:address":"Gare Saint Amatre",
    "sg:city":"Auxerre",
    "sg:orig_category":"Unclassifiable Establishments",
    "sg:phone":"+33 3 86 72 37 00",
    "sg:postcode":"89000",
    "sg:province":"Bourgogne",
    "wof:name":"Pomona S.a.r.l.",
    "wof:placetype":"venue"
},
  "geometry": {"coordinates":[3.567953,47.784241],"type":"Point"}
}