{
  "type": "Feature",
  "properties": {
    "iso:country":"FR",
    "sg:address":"4, Place Louis Lebret, 69008 Lyon",
    "sg:orig_category":"Non-Classified Establishments",
    "sg:phone":"+33 4 72 73 04 26",
    "sg:postcode":"69008",
    "sg:province":"Rhone-Alpes",
    "wof:name":"Compo Relais S.a.r.l.",
    "wof:placetype":"venue"
},
  "geometry": {"coordinates":[4.852794,45.735237],"type":"Point"}
}