{
  "type": "Feature",
  "properties": {
    "addr:full":"La Bitarelle 19800 Gimel les Cascades Limousin",
    "addr:postcode":"19800",
    "addr:street":"Bitarelle",
    "iso:country":"FR",
    "sg:address":"La Bitarelle 19800 Gimel les Cascades",
    "sg:orig_category":"Non-Classified Establishments",
    "sg:phone":"+33 5 55 21 26 54",
    "sg:province":"Limousin",
    "wof:name":"Soci\u00e9t\u00e9 Ch\u00e8ze Et Fils Voyages S.a.r.l.",
    "wof:placetype":"venue"
},
  "geometry": {"coordinates":[1.832819,45.315365],"type":"Point"}
}