{
  "type": "Feature",
  "properties": {
    "addr:full":"74, Rue du Chemin Vert, 95460 Ezanville Ile de France",
    "addr:housenumber":"74",
    "addr:postcode":"95460;ile",
    "addr:street":"Rue Du Chemin Vert",
    "iso:country":"FR",
    "sg:address":"74, Rue du Chemin Vert, 95460 Ezanville",
    "sg:orig_category":"Unclassifiable Establishments",
    "sg:phone":"+33 1 39 91 00 94",
    "sg:province":"Ile de France",
    "wof:name":"C.i.p. S.a. - Cartonnage Industriel Et Publicitaire",
    "wof:placetype":"venue"
},
  "geometry": {"coordinates":[2.356291,49.033909],"type":"Point"}
}