{
  "type": "Feature",
  "properties": {
    "addr:full":"78, Rue Emile Broodcoorens, 44600 Saint Nazaire Pays de Loire",
    "addr:housenumber":"78",
    "addr:postcode":"44600",
    "addr:street":"Rue Emile Broodcoorens;Nazaire",
    "iso:country":"FR",
    "sg:address":"78, Rue Emile Broodcoorens, 44600 Saint Nazaire",
    "sg:orig_category":"Non-Classified Establishments",
    "sg:phone":"+33 2 40 53 60 00",
    "sg:province":"Pays de Loire",
    "wof:name":"Onet Propret\u00e9 S.a.",
    "wof:placetype":"venue"
},
  "geometry": {"coordinates":[-2.253572,47.264179],"type":"Point"}
}