{
  "type": "Feature",
  "properties": {
    "addr:full":"ZA de l'Isle Neuve La Roche de Glun Rhone-Alpes 26600",
    "addr:postcode":"26600",
    "addr:street":"Za De L'Isle Neuve",
    "iso:country":"FR",
    "sg:address":"ZA de l'Isle Neuve",
    "sg:city":"La Roche de Glun",
    "sg:orig_category":"Unclassifiable Establishments",
    "sg:phone":"+33 4 75 84 56 84",
    "sg:postcode":"26600",
    "sg:province":"Rhone-Alpes",
    "wof:name":"Transport Du 45 Emelarall\u00e8le S.a.",
    "wof:placetype":"venue"
},
  "geometry": {"coordinates":[4.847882,45.023754],"type":"Point"}
}