{
  "type": "Feature",
  "properties": {
    "iso:country":"FR",
    "sg:address":"ZI de la Tr\u00e9sorerie",
    "sg:city":"Wimille",
    "sg:orig_category":"Unclassifiable Establishments",
    "sg:phone":"+33 3 21 99 26 26",
    "sg:postcode":"62126",
    "sg:province":"Nord Pas-de-Calais",
    "wof:name":"Flair R\u00e9sine S.a.",
    "wof:placetype":"venue"
},
  "geometry": {"coordinates":[1.631271,50.764091],"type":"Point"}
}