{
  "type": "Feature",
  "properties": {
    "addr:full":"Rue Du Pont L'Abbe 50190 Periers P\u00e9riers Basse Normandie 50190",
    "addr:postcode":"50190;50190",
    "addr:street":"Rue Du Pont L'Abbe",
    "iso:country":"FR",
    "sg:address":"Rue Du Pont L'Abbe 50190 Periers",
    "sg:city":"P\u00e9riers",
    "sg:classifiers":[
        {
            "category":"Farming",
            "subcategory":"Farm & Veterinary Services",
            "type":"Manufacturing & Wholesale Goods"
        }
    ],
    "sg:phone":"+33 2 33 76 55 20",
    "sg:postcode":"50190",
    "sg:province":"Basse Normandie",
    "sg:tags":[
        "food",
        "product",
        "breeding",
        "animal",
        "related"
    ],
    "wof:name":"Societe Cooperative Agricole Et Agro Alimentaire Des Provinc (agralco) Point Vert",
    "wof:placetype":"venue"
},
  "geometry": {"coordinates":[-1.411341,49.18708],"type":"Point"}
}