{
  "type": "Feature",
  "properties": {
    "iso:country":"FR",
    "sg:address":"6, Rue Jacquard, 59280 Armenti\u00e8res",
    "sg:orig_category":"Unclassifiable Establishments",
    "sg:phone":"+33 3 20 48 44 44",
    "sg:province":"Nord Pas-de-Calais",
    "wof:name":"Delannoy Dewailly Entreprise S.a.",
    "wof:placetype":"venue"
},
  "geometry": {"coordinates":[2.877314,50.683926],"type":"Point"}
}