{
  "type": "Feature",
  "properties": {
    "addr:full":"6, Rue Jacquard, 59280 Armenti\u00e8res Nord Pas-de-Calais",
    "addr:housenumber":"6",
    "addr:postcode":"59280",
    "addr:street":"Rue Jacquard",
    "iso:country":"FR",
    "sg:address":"6, Rue Jacquard, 59280 Armenti\u00e8res",
    "sg:orig_category":"Unclassifiable Establishments",
    "sg:phone":"+33 3 20 48 44 44",
    "sg:province":"Nord Pas-de-Calais",
    "wof:name":"Delannoy Dewailly Entreprise S.a.",
    "wof:placetype":"venue"
},
  "geometry": {"coordinates":[2.877314,50.683926],"type":"Point"}
}