{
  "type": "Feature",
  "properties": {
    "addr:full":"8, Av du Comte de Bertier, 57100 Thionville Lorraine",
    "addr:postcode":"57100",
    "addr:street":"Av Du Comte De Bertier",
    "iso:country":"FR",
    "sg:address":"8, Av du Comte de Bertier, 57100 Thionville",
    "sg:orig_category":"Non-Classified Establishments",
    "sg:phone":"+33 3 82 54 37 37",
    "sg:province":"Lorraine",
    "wof:name":"Guenebaut Fr\u00e8res S.a.r.l.",
    "wof:placetype":"venue"
},
  "geometry": {"coordinates":[6.168844,49.367283],"type":"Point"}
}