{
  "type": "Feature",
  "properties": {
    "addr:full":"Zi Jean-Pierre Genin Ld Le Cruzeuil 38260 Nantoin Rhone-Alpes 38260",
    "addr:postcode":"38260;38260",
    "addr:street":"Ld;Rhone-Alpes",
    "iso:country":"FR",
    "sg:address":"Zi Jean-Pierre Genin Ld Le Cruzeuil 38260 Nantoin",
    "sg:classifiers":[
        {
            "category":"Manufacturing",
            "subcategory":"Metals",
            "type":"Manufacturing & Wholesale Goods"
        }
    ],
    "sg:phone":"+33 4 74 54 41 65",
    "sg:postcode":"38260",
    "sg:province":"Rhone-Alpes",
    "sg:tags":[
        "metallurgy",
        "steel",
        "metalworking"
    ],
    "wof:name":"Alutec",
    "wof:placetype":"venue"
},
  "geometry": {"coordinates":[5.269856,45.435501],"type":"Point"}
}