{
  "type": "Feature",
  "properties": {
    "addr:full":"B.P. 183, 88207 Remiremont C\u00e9dex^^36, Rue de la Xav\u00e9e, 88200 Remiremont Lorraine",
    "addr:housenumber":"b.p. 183",
    "addr:postcode":"88207;88200",
    "addr:street":"Rue De La Xave\u0301E",
    "iso:country":"FR",
    "sg:address":"B.P. 183, 88207 Remiremont C\u00e9dex^^36, Rue de la Xav\u00e9e, 88200 Remiremont",
    "sg:orig_category":"Non-Classified Establishments",
    "sg:phone":"+33 3 29 62 46 86",
    "sg:province":"Lorraine",
    "wof:name":"Poignon Georges Et Compagnie S.a.",
    "wof:placetype":"venue"
},
  "geometry": {"coordinates":[6.636039,47.980343],"type":"Point"}
}