{
  "type": "Feature",
  "properties": {
    "iso:country":"FR",
    "sg:address":"Route De Grumesnil 60220 FORMERIE",
    "sg:classifiers":[
        {
            "category":"Home & Garden",
            "subcategory":"Home Furnishings",
            "type":"Retail Goods"
        }
    ],
    "sg:phone":"+33 3 44 04 04 26",
    "sg:postcode":"60220",
    "sg:province":"Picardie",
    "sg:tags":[
        "metal",
        "furniture"
    ],
    "wof:name":"Olivier Corro Mad Sa",
    "wof:placetype":"venue"
},
  "geometry": {"coordinates":[1.724845,49.647381],"type":"Point"}
}