{
  "type": "Feature",
  "properties": {
    "iso:country":"FR",
    "sg:address":"220 Bd De La Villette 75019 Paris",
    "sg:classifiers":[
        {
            "category":"Manufacturing",
            "subcategory":"Tools & Machinery",
            "type":"Manufacturing & Wholesale Goods"
        }
    ],
    "sg:phone":"+33 1 40 36 60 00",
    "sg:postcode":"75019",
    "sg:province":"Ile de France",
    "sg:tags":[
        "metallurgy",
        "metalworking"
    ],
    "wof:name":"Thomas Et Cie",
    "wof:placetype":"venue"
},
  "geometry": {"coordinates":[2.367268,48.884445],"type":"Point"}
}