{
  "type": "Feature",
  "properties": {
    "iso:country":"FR",
    "sg:address":"Chemin Rural Num\u00e9ro 91630 Marolles En Hurepoix",
    "sg:classifiers":[
        {
            "category":"Utilities",
            "subcategory":"Electric",
            "type":"Services"
        }
    ],
    "sg:phone":"+33 1 69 14 85 63",
    "sg:postcode":"91630",
    "sg:province":"Ile de France",
    "sg:tags":[
        "electricity",
        "electronic",
        "electrical",
        "equipment"
    ],
    "wof:name":"Linelec Groupement Pour La Construction De Lignes Electriqu (linelec)",
    "wof:placetype":"venue"
},
  "geometry": {"coordinates":[2.30128,48.561611],"type":"Point"}
}