{
  "type": "Feature",
  "properties": {
    "addr:full":"8, Rue du Ch\u00e2teau, 89420 Vassy Vassy Bourgogne 89420",
    "addr:housenumber":"8",
    "addr:postcode":"89420;89420",
    "addr:street":"Rue Du Cha\u0302Teau",
    "iso:country":"FR",
    "sg:address":"8, Rue du Ch\u00e2teau, 89420 Vassy",
    "sg:city":"Vassy",
    "sg:orig_category":"Non-Classified Establishments",
    "sg:phone":"+33 3 86 32 14 77",
    "sg:postcode":"89420",
    "sg:province":"Bourgogne",
    "wof:name":"Philippe Henrion Cr\u00e9ations",
    "wof:placetype":"venue"
},
  "geometry": {"coordinates":[4.168066,47.570126],"type":"Point"}
}