{
  "type": "Feature",
  "properties": {
    "addr:full":"67, Rue Sylvabelle, 13006 Marseille Poitou-Charentes",
    "addr:housenumber":"67",
    "addr:postcode":"13006",
    "addr:street":"Rue Sylvabelle",
    "iso:country":"FR",
    "sg:address":"67, Rue Sylvabelle, 13006 Marseille",
    "sg:orig_category":"Unclassifiable Establishments",
    "sg:phone":"+33 4 91 33 75 82",
    "sg:province":"Poitou-Charentes",
    "wof:name":"Gauthier",
    "wof:placetype":"venue"
},
  "geometry": {"coordinates":[5.377204,43.288692],"type":"Point"}
}