{
  "type": "Feature",
  "properties": {
    "iso:country":"FR",
    "sg:address":"7, Rue de l'Atome, 67800 Bischheim",
    "sg:city":"Bischheim",
    "sg:orig_category":"Fournitures industrielles Hydrauliques, Accessoires Raccords Raccords hydrauliques Raccords pneumati",
    "sg:phone":"+33 3 88 33 06 13",
    "sg:postcode":"67800",
    "sg:province":"Alsace",
    "wof:name":"Cihal S.a. - Compagnie D'hydraulique D'alsace Lorraine",
    "wof:placetype":"venue"
},
  "geometry": {"coordinates":[7.769752,48.628761],"type":"Point"}
}