{
  "type": "Feature",
  "properties": {
    "addr:full":"1 Boulevard Marechal Leclerc Foug\u00e8res Bretagne 35300",
    "addr:housenumber":"1",
    "addr:postcode":"35300",
    "addr:street":"Boulevard Marechal Leclerc Fouge\u0300Res",
    "iso:country":"FR",
    "sg:address":"1 Boulevard Marechal Leclerc",
    "sg:city":"Foug\u00e8res",
    "sg:classifiers":[
        {
            "category":"Banks & Credit Unions",
            "subcategory":"Financial Services",
            "type":"Services"
        }
    ],
    "sg:phone":"+33 2 99 99 11 28",
    "sg:postcode":"35300",
    "sg:province":"Bretagne",
    "sg:tags":[
        "banking",
        "finance",
        "insurance"
    ],
    "wof:name":"Banque Populaire De L Ouest (bpo)",
    "wof:placetype":"venue"
},
  "geometry": {"coordinates":[-1.200283,48.354572],"type":"Point"}
}