{
  "type": "Feature",
  "properties": {
    "addr:full":"50, Rue Principale, 67290 Petersbach Petersbach Alsace 67290",
    "addr:housenumber":"50",
    "addr:postcode":"67290;67290",
    "addr:street":"Rue Principale",
    "iso:country":"FR",
    "sg:address":"50, Rue Principale, 67290 Petersbach",
    "sg:city":"Petersbach",
    "sg:orig_category":"Unclassifiable Establishments",
    "sg:phone":"+33 3 88 70 45 66",
    "sg:postcode":"67290",
    "sg:province":"Alsace",
    "wof:name":"Carri\u00e8res Reinberger S.a.",
    "wof:placetype":"venue"
},
  "geometry": {"coordinates":[7.26227,48.876034],"type":"Point"}
}