{
  "type": "Feature",
  "properties": {
    "addr:full":"3 impasse des Vergers 93220 Gagny Ile de France",
    "addr:housenumber":"3",
    "addr:postcode":"93220",
    "addr:street":"Impasse Des Vergers",
    "iso:country":"FR",
    "sg:address":"3 impasse des Vergers 93220 Gagny",
    "sg:classifiers":[
        {
            "category":"Utilities",
            "subcategory":"Natural Gas",
            "type":"Services"
        }
    ],
    "sg:phone":"+33 1 43 30 14 26",
    "sg:province":"Ile de France",
    "sg:tags":[
        "plug",
        "connector"
    ],
    "wof:name":"Amphenol Rf Europe",
    "wof:placetype":"venue"
},
  "geometry": {"coordinates":[2.552437,48.879147],"type":"Point"}
}