{
  "type": "Feature",
  "properties": {
    "addr:full":"14, Rue Belle Borne - Zone Fr\u00eat 5, 93290 Tremblay en France Ile de France",
    "addr:housenumber":"14;5",
    "addr:postcode":"93290",
    "addr:street":"Rue Belle Borne;Fre\u0302T",
    "iso:country":"FR",
    "sg:address":"14, Rue Belle Borne - Zone Fr\u00eat 5, 93290 Tremblay en France",
    "sg:orig_category":"Unclassifiable Establishments",
    "sg:phone":"+33 1 48 62 07 81",
    "sg:province":"Ile de France",
    "wof:name":"Cargo Service Center France S.a.r.l.",
    "wof:placetype":"venue"
},
  "geometry": {"coordinates":[2.56727,48.951214],"type":"Point"}
}