{
  "type": "Feature",
  "properties": {
    "addr:full":"B.P. 52, 24203 Sarlat La Caneda C\u00e9dex^^2, Av. Brossard, 24200 Sarlat La Caneda Carsac-Aillac Aquitaine 24200",
    "addr:postcode":"24203;24200;24200",
    "addr:street":"B.P. 52;Av. Brossard",
    "iso:country":"FR",
    "sg:address":"B.P. 52, 24203 Sarlat La Caneda C\u00e9dex^^2, Av. Brossard, 24200 Sarlat La Caneda",
    "sg:city":"Carsac-Aillac",
    "sg:orig_category":"Non-Classified Establishments",
    "sg:phone":"+33 5 53 31 10 10",
    "sg:postcode":"24200",
    "sg:province":"Aquitaine",
    "wof:name":"Limoges Photogravure S.a.",
    "wof:placetype":"venue"
},
  "geometry": {"coordinates":[1.22243,44.829056],"type":"Point"}
}