{
  "type": "Feature",
  "properties": {
    "addr:full":"41, Rue de Mulhouse, 67100 Strasbourg Strasbourg Alsace 67100",
    "addr:housenumber":"41",
    "addr:postcode":"67100;67100",
    "addr:street":"Rue De Mulhouse",
    "iso:country":"FR",
    "sg:address":"41, Rue de Mulhouse, 67100 Strasbourg",
    "sg:city":"Strasbourg",
    "sg:orig_category":"Unclassifiable Establishments",
    "sg:phone":"+33 3 88 44 95 50",
    "sg:postcode":"67100",
    "sg:province":"Alsace",
    "wof:name":"Robelec S.a.r.l.",
    "wof:placetype":"venue"
},
  "geometry": {"coordinates":[7.753035,48.567078],"type":"Point"}
}