{
  "type": "Feature",
  "properties": {
    "iso:country":"FR",
    "sg:address":"11, Av. L\u00e9onard de Vinci - Europarc, 33600 Pessac",
    "sg:city":"Pessac",
    "sg:orig_category":"Unclassifiable Establishments",
    "sg:phone":"+33 5 56 07 07 56",
    "sg:postcode":"33600",
    "sg:province":"Aquitaine",
    "wof:name":"Bdl Syst\u00e8mes S.a.",
    "wof:placetype":"venue"
},
  "geometry": {"coordinates":[-0.654636,44.782734],"type":"Point"}
}