{
  "type": "Feature",
  "properties": {
    "addr:full":"RN 7 Meyreuil Provence-Alpes-C\u00f4te d'Azur 13590",
    "addr:postcode":"13590",
    "addr:street":"Rn 7 Meyreuil",
    "iso:country":"FR",
    "sg:address":"RN 7",
    "sg:city":"Meyreuil",
    "sg:orig_category":"Unclassifiable Establishments",
    "sg:phone":"+33 4 42 12 66 66",
    "sg:postcode":"13590",
    "sg:province":"Provence-Alpes-C\u00f4te d'Azur",
    "wof:name":"La Proven\u00e7ale S.a.",
    "wof:placetype":"venue"
},
  "geometry": {"coordinates":[5.495469,43.485443],"type":"Point"}
}