{
  "type": "Feature",
  "properties": {
    "addr:full":"63, Bd Industriel, 76300 Sotteville l\u00e8s Rouen Haute Normandie",
    "addr:housenumber":"63",
    "addr:postcode":"76300",
    "addr:street":"Bd Industriel;Haute Normandie",
    "iso:country":"FR",
    "sg:address":"63, Bd Industriel, 76300 Sotteville l\u00e8s Rouen",
    "sg:orig_category":"Unclassifiable Establishments",
    "sg:phone":"+33 2 32 91 99 19",
    "sg:province":"Haute Normandie",
    "wof:name":"Taxi-colis Nord Ouest S.a.",
    "wof:placetype":"venue"
},
  "geometry": {"coordinates":[1.110663,49.403942],"type":"Point"}
}