{
  "type": "Feature",
  "properties": {
    "iso:country":"FR",
    "sg:address":"41 Rue Parmentier 92600 Asni\u00e8res Sur Seine",
    "sg:classifiers":[
        {
            "category":"Home & Garden",
            "subcategory":"Furniture",
            "type":"Retail Goods"
        }
    ],
    "sg:phone":"+33 1 47 93 66 91",
    "sg:postcode":"92600",
    "sg:province":"Ile de France",
    "sg:tags":[
        "household",
        "wood"
    ],
    "wof:name":"Rollco Sarl",
    "wof:placetype":"venue"
},
  "geometry": {"coordinates":[2.272227,48.90847],"type":"Point"}
}