{
  "type": "Feature",
  "properties": {
    "iso:country":"FR",
    "sg:address":"6/8, Rue Mar\u00e9chal de Lattre de Tassigny, 59400 Cambrai",
    "sg:orig_category":"Non-Classified Establishments",
    "sg:phone":"+33 3 27 83 68 32",
    "sg:province":"Nord Pas-de-Calais",
    "wof:name":"La Voix Du Nord S.a.",
    "wof:placetype":"venue"
},
  "geometry": {"coordinates":[3.235675,50.174957],"type":"Point"}
}