{
  "type": "Feature",
  "properties": {
    "addr:full":"16, Rue des Ecoles, 25420 Bart Franche Comt\u00e9",
    "addr:housenumber":"16",
    "addr:postcode":"25420",
    "addr:street":"Rue Des Ecoles;Franche Comte\u0301",
    "iso:country":"FR",
    "sg:address":"16, Rue des Ecoles, 25420 Bart",
    "sg:orig_category":"Unclassifiable Establishments",
    "sg:phone":"+33 3 81 90 32 28",
    "sg:province":"Franche Comt\u00e9",
    "wof:name":"Jouffroy S.a.",
    "wof:placetype":"venue"
},
  "geometry": {"coordinates":[6.770011,47.491688],"type":"Point"}
}