{
  "type": "Feature",
  "properties": {
    "addr:full":"B.P. 18, 13771 Fos sur Mer C\u00e9dex^^Rte d'Arles, 13270 Fos sur Mer Provence-Alpes-C\u00f4te d'Azur",
    "addr:postcode":"13771;13270",
    "addr:street":"B.P. 18;D'Arles;Mer",
    "iso:country":"FR",
    "sg:address":"B.P. 18, 13771 Fos sur Mer C\u00e9dex^^Rte d'Arles, 13270 Fos sur Mer",
    "sg:orig_category":"Non-Classified Establishments",
    "sg:phone":"+33 4 42 05 11 04",
    "sg:province":"Provence-Alpes-C\u00f4te d'Azur",
    "wof:name":"Heckett-multiserv Sud S.a.",
    "wof:placetype":"venue"
},
  "geometry": {"coordinates":[4.919865,43.461277],"type":"Point"}
}