{
  "type": "Feature",
  "properties": {
    "addr:full":"24, Av. Gustave Eiffel, 33608 Pessac C\u00e9dex Aquitaine",
    "addr:postcode":"33608",
    "addr:street":"24 Av. Gustave Eiffel",
    "iso:country":"FR",
    "sg:address":"24, Av. Gustave Eiffel, 33608 Pessac C\u00e9dex",
    "sg:orig_category":"Non-Classified Establishments",
    "sg:phone":"+33 5 57 26 30 00",
    "sg:province":"Aquitaine",
    "wof:name":"Thales Syst\u00e8mes A\u00e9roport\u00e9s S.a.",
    "wof:placetype":"venue"
},
  "geometry": {"coordinates":[-0.649042,44.782295],"type":"Point"}
}