{
  "type": "Feature",
  "properties": {
    "addr:full":"29 bd Marinoni; Beaulieu Beaulieu Auvergne 15270",
    "addr:housenumber":"29",
    "addr:postcode":"15270",
    "addr:street":"Bd Marinoni",
    "iso:country":"FR",
    "sg:address":"29 bd Marinoni; Beaulieu",
    "sg:city":"Beaulieu",
    "sg:classifiers":[
        {
            "category":"Banks & Credit Unions",
            "subcategory":"Bank",
            "type":"Services"
        }
    ],
    "sg:phone":"+33 3393011945",
    "sg:postcode":"15270",
    "sg:province":"Auvergne",
    "wof:name":"Cr\u00e9dit Agricole Des Alpes, Maritimes",
    "wof:placetype":"venue"
},
  "geometry": {"coordinates":[-95.80437499999999,47.342918],"type":"Point"}
}