{
  "type": "Feature",
  "properties": {
    "addr:full":"64 Rue De Turenne 75003 Paris Ile de France 75003",
    "addr:housenumber":"64",
    "addr:postcode":"75003;75003",
    "addr:street":"Rue De Turenne",
    "iso:country":"FR",
    "sg:address":"64 Rue De Turenne 75003 Paris",
    "sg:classifiers":[
        {
            "category":"Shopping",
            "subcategory":"Clothing, Apparel, & Fashions",
            "type":"Retail Goods"
        }
    ],
    "sg:phone":"+33 1 42 71 06 95",
    "sg:postcode":"75003",
    "sg:province":"Ile de France",
    "sg:tags":[
        "textile",
        "clothing",
        "clothes"
    ],
    "wof:name":"Creations Jb",
    "wof:placetype":"venue"
},
  "geometry": {"coordinates":[2.364665,48.85957],"type":"Point"}
}