{
  "type": "Feature",
  "properties": {
    "iso:country":"FR",
    "sg:address":"14, Rue des Coudroux, 92500 Rueil Malmaison",
    "sg:orig_category":"Unclassifiable Establishments",
    "sg:phone":"+33 1 47 32 31 88",
    "sg:province":"Ile de France",
    "wof:name":"T.h.s. S.a. - Travaux Haute Seine",
    "wof:placetype":"venue"
},
  "geometry": {"coordinates":[2.179101,48.862644],"type":"Point"}
}