{
  "type": "Feature",
  "properties": {
    "addr:full":"B.P. 70121, 57504 Saint Avold C\u00e9dex^^32, Av Cl\u00e9menceau, 57500 Saint Avold Lorraine",
    "addr:housenumber":"57504",
    "addr:postcode":"57500",
    "addr:street":"Saint Avold;Av Cle\u0301Menceau;Avold",
    "iso:country":"FR",
    "sg:address":"B.P. 70121, 57504 Saint Avold C\u00e9dex^^32, Av Cl\u00e9menceau, 57500 Saint Avold",
    "sg:orig_category":"Non-Classified Establishments",
    "sg:phone":"+33 3 87 91 22 91",
    "sg:province":"Lorraine",
    "wof:name":"Fiduciaire Mosellane S.a.",
    "wof:placetype":"venue"
},
  "geometry": {"coordinates":[6.705505,49.104275],"type":"Point"}
}