{
  "type": "Feature",
  "properties": {
    "addr:full":"Av Pierre De Coubertin 36000 Ch\u00e2teauroux Ch\u00e2teauroux Centre 36000",
    "addr:postcode":"36000;36000",
    "addr:street":"Av Pierre De Coubertin;Cha\u0302Teauroux",
    "iso:country":"FR",
    "sg:address":"Av Pierre De Coubertin 36000 Ch\u00e2teauroux",
    "sg:city":"Ch\u00e2teauroux",
    "sg:classifiers":[
        {
            "category":"Shopping",
            "subcategory":"Computers & Home Electronics",
            "type":"Retail Goods"
        }
    ],
    "sg:phone":"+33 2 54 22 87 76",
    "sg:postcode":"36000",
    "sg:province":"Centre",
    "sg:tags":[
        "electric",
        "electricity",
        "component",
        "equipment",
        "electrical",
        "electronic"
    ],
    "wof:name":"Cge Distribution",
    "wof:placetype":"venue"
},
  "geometry": {"coordinates":[1.722161,46.81163],"type":"Point"}
}