{
  "type": "Feature",
  "properties": {
    "addr:full":"19 Chem Des Coteaux 31780 Castelginest Midi Pyr\u00e9n\u00e9es 31780",
    "addr:housenumber":"19",
    "addr:postcode":"31780;31780",
    "addr:street":"Chem Des Coteaux",
    "iso:country":"FR",
    "sg:address":"19 Chem Des Coteaux 31780 Castelginest",
    "sg:classifiers":[
        {
            "category":"Professional",
            "subcategory":"Engineering",
            "type":"Services"
        }
    ],
    "sg:phone":"+33 5 61 74 15 64",
    "sg:postcode":"31780",
    "sg:province":"Midi Pyr\u00e9n\u00e9es",
    "sg:tags":[
        "machine",
        "-",
        "mechanical"
    ],
    "wof:name":"Sa Rodriguez Et Fils",
    "wof:placetype":"venue"
},
  "geometry": {"coordinates":[1.459135,43.684456],"type":"Point"}
}