{
  "type": "Feature",
  "properties": {
    "addr:full":"La Tuilerie - de Montbron 24360 Bussi\u00e8re Badil Aquitaine 24360",
    "addr:postcode":"24360;24360",
    "addr:street":"La Tuilerie De Montbron",
    "iso:country":"FR",
    "sg:address":"La Tuilerie -",
    "sg:city":"de Montbron 24360 Bussi\u00e8re Badil",
    "sg:classifiers":[
        {
            "category":"Food & Beverages",
            "subcategory":"Fruits & Vegetables",
            "type":"Retail Goods"
        }
    ],
    "sg:phone":"+33 5 53 60 87 00",
    "sg:postcode":"24360",
    "sg:province":"Aquitaine",
    "sg:tags":[
        "frozen",
        "product",
        "related"
    ],
    "wof:name":"Gel Pat",
    "wof:placetype":"venue"
},
  "geometry": {"coordinates":[0.66308,45.591595],"type":"Point"}
}