{
  "type": "Feature",
  "properties": {
    "addr:full":"Lieudit Richagneux 42400 St Chamond Rhone-Alpes 42400",
    "addr:postcode":"42400;42400",
    "addr:street":"Lieudit Richagneux;Rhone-Alpes",
    "iso:country":"FR",
    "sg:address":"Lieudit Richagneux 42400 St Chamond",
    "sg:classifiers":[
        {
            "category":"Shopping",
            "subcategory":"Crafts & Fabrics",
            "type":"Retail Goods"
        }
    ],
    "sg:phone":"+33 4 77 29 22 40",
    "sg:postcode":"42400",
    "sg:province":"Rhone-Alpes",
    "sg:tags":[
        "textile",
        "clothing"
    ],
    "wof:name":"Alpex Protection",
    "wof:placetype":"venue"
},
  "geometry": {"coordinates":[4.522822,45.480812],"type":"Point"}
}