{
  "type": "Feature",
  "properties": {
    "iso:country":"FR",
    "sg:address":"51, Av. de la R\u00e9publique, 92320 Ch\u00e2tillon",
    "sg:orig_category":"Unclassifiable Establishments",
    "sg:phone":"+33 1 40 84 07 77",
    "sg:province":"Ile de France",
    "wof:name":"A.a.e.v. S.a.r.l. - Agence D'am\u00e9nagement D'espaces Verts",
    "wof:placetype":"venue"
},
  "geometry": {"coordinates":[2.294893,48.801704],"type":"Point"}
}