{
  "type": "Feature",
  "properties": {
    "addr:full":"Hautefage 19330 Chameyrat Limousin 19330",
    "addr:postcode":"19330;19330",
    "iso:country":"FR",
    "sg:address":"Hautefage 19330 Chameyrat",
    "sg:classifiers":[
        {
            "category":"Building & Trades",
            "subcategory":"Construction",
            "type":"Services"
        }
    ],
    "sg:phone":"+33 5 55 26 68 02",
    "sg:postcode":"19330",
    "sg:province":"Limousin",
    "sg:tags":[
        "work",
        "public"
    ],
    "wof:name":"Fernandes Et Fils",
    "wof:placetype":"venue"
},
  "geometry": {"coordinates":[1.736921,45.267456],"type":"Point"}
}