{
  "type": "Feature",
  "properties": {
    "iso:country":"FR",
    "sg:address":"30/34, Rue Claude Lorrain, 75016 Paris",
    "sg:orig_category":"Unclassifiable Establishments",
    "sg:phone":"+33 1 46 51 65 65",
    "sg:province":"Ile de France",
    "wof:name":"Image Etudes Conseil S.a.r.l.",
    "wof:placetype":"venue"
},
  "geometry": {"coordinates":[2.260144,48.841564],"type":"Point"}
}