{
  "type": "Feature",
  "properties": {
    "addr:full":"1bis, Av. de la R\u00e9publique, 75011 Paris Ile de France",
    "addr:postcode":"75011",
    "addr:street":"Av. De La Re\u0301Publique",
    "iso:country":"FR",
    "sg:address":"1bis, Av. de la R\u00e9publique, 75011 Paris",
    "sg:orig_category":"Unclassifiable Establishments",
    "sg:phone":"+33 1 49 29 32 00",
    "sg:province":"Ile de France",
    "wof:name":"Air & Cosmos S.a.",
    "wof:placetype":"venue"
},
  "geometry": {"coordinates":[2.366138,48.866951],"type":"Point"}
}