{
  "type": "Feature",
  "properties": {
    "iso:country":"FR",
    "sg:address":"19, Rte de Selles, 41700 Contres",
    "sg:city":"Contres",
    "sg:orig_category":"Unclassifiable Establishments",
    "sg:phone":"+33 2 54 79 59 10",
    "sg:postcode":"41700",
    "sg:province":"Centre",
    "wof:name":"Brenot S.a.r.l.",
    "wof:placetype":"venue"
},
  "geometry": {"coordinates":[1.43519,47.413883],"type":"Point"}
}