{
  "type": "Feature",
  "properties": {
    "addr:full":"Rue Eug\u00e8ne Chevreul - Parc de Magellan Pessac Aquitaine 33600",
    "addr:postcode":"33600",
    "addr:street":"Rue Euge\u0300Ne Chevreul Parc De Magellan",
    "iso:country":"FR",
    "sg:address":"Rue Eug\u00e8ne Chevreul - Parc de Magellan",
    "sg:city":"Pessac",
    "sg:orig_category":"Unclassifiable Establishments",
    "sg:phone":"+33 5 57 26 60 60",
    "sg:postcode":"33600",
    "sg:province":"Aquitaine",
    "wof:name":"Ricoh France Sud Ouest",
    "wof:placetype":"venue"
},
  "geometry": {"coordinates":[-0.664814,44.778065],"type":"Point"}
}