{
  "type": "Feature",
  "properties": {
    "iso:country":"FR",
    "sg:address":"39800 Vaux Sur Poligny",
    "sg:classifiers":[
        {
            "category":"Food & Beverages",
            "subcategory":"Groceries & Convenience Stores",
            "type":"Retail Goods"
        }
    ],
    "sg:phone":"+33 3 84 73 83 83",
    "sg:postcode":"39800",
    "sg:province":"Franche Comt\u00e9",
    "sg:tags":[
        "product",
        "grain",
        "cereal",
        "related"
    ],
    "wof:name":"Etablissements Mignot",
    "wof:placetype":"venue"
},
  "geometry": {"coordinates":[5.723327,46.825829],"type":"Point"}
}