{
  "type": "Feature",
  "properties": {
    "iso:country":"FR",
    "sg:address":"Le Domaine B\u00e2t C2 50220 Ducey",
    "sg:city":"Ducey",
    "sg:classifiers":[
        {
            "category":"Autos & Motor Vehicles",
            "subcategory":"Automobile Sales",
            "type":"Retail Goods"
        }
    ],
    "sg:phone":"+33 2 33 89 38 93",
    "sg:postcode":"50220",
    "sg:province":"Basse Normandie",
    "sg:tags":[
        "equipment",
        "industrial",
        "transport"
    ],
    "wof:name":"Etablissements Jean Chereau",
    "wof:placetype":"venue"
},
  "geometry": {"coordinates":[-1.289544,48.621632],"type":"Point"}
}