{
  "type": "Feature",
  "properties": {
    "addr:full":"1 rue Fructidor 75830 PARIS CEDEX 17 Ile de France",
    "addr:housenumber":"1",
    "addr:postcode":"75830",
    "addr:street":"Rue Fructidor",
    "iso:country":"FR",
    "sg:address":"1 rue Fructidor 75830 PARIS CEDEX 17",
    "sg:classifiers":[
        {
            "category":"Wholesale",
            "subcategory":"Metals & Minerals",
            "type":"Manufacturing & Wholesale Goods"
        }
    ],
    "sg:phone":"+33 1 49 18 40 00",
    "sg:province":"Ile de France",
    "sg:tags":[
        "packaging"
    ],
    "wof:name":"Carnaudmet Albox Sa",
    "wof:placetype":"venue"
},
  "geometry": {"coordinates":[2.30471,48.887321],"type":"Point"}
}