{
  "type": "Feature",
  "properties": {
    "addr:full":"7 All Marcel Proust 87280 Limoges Limousin 87280",
    "addr:housenumber":"7",
    "addr:postcode":"87280;87280",
    "addr:street":"All Marcel Proust",
    "iso:country":"FR",
    "sg:address":"7 All Marcel Proust 87280 Limoges",
    "sg:classifiers":[
        {
            "category":"Professional",
            "subcategory":"Business Services",
            "type":"Services"
        }
    ],
    "sg:phone":"+33 5 55 35 48 48",
    "sg:postcode":"87280",
    "sg:province":"Limousin",
    "sg:tags":[
        "training",
        "advice"
    ],
    "wof:name":"College Anatole France",
    "wof:placetype":"venue"
},
  "geometry": {"coordinates":[1.298561,45.880997],"type":"Point"}
}