{
  "type": "Feature",
  "properties": {
    "iso:country":"FR",
    "sg:address":"Rte du Camp Major CD 2 - Quartier de l'Aum\u00f4ne Vieille",
    "sg:city":"Aubagne",
    "sg:orig_category":"Non-Classified Establishments",
    "sg:phone":"+33 4 42 03 65 65",
    "sg:postcode":"13400",
    "wof:name":"Parqueterie Moderne S.a.r.l.",
    "wof:placetype":"venue"
},
  "geometry": {"coordinates":[5.56359,43.290401],"type":"Point"}
}