{
  "type": "Feature",
  "properties": {
    "iso:country":"FR",
    "sg:address":"12",
    "sg:city":"Jean Jaur\u00e8s 80800 Corbie",
    "sg:classifiers":[
        {
            "category":"Food Court",
            "type":"Food & Drink"
        }
    ],
    "sg:phone":"+33 3 22 48 23 61",
    "sg:postcode":"80800",
    "sg:province":"Picardie",
    "sg:tags":[
        "product",
        "related"
    ],
    "wof:name":"Aromex",
    "wof:placetype":"venue"
},
  "geometry": {"coordinates":[2.50096,49.911346],"type":"Point"}
}