{
  "type": "Feature",
  "properties": {
    "iso:country":"FR",
    "sg:address":"B.P. 89, 55102 Verdun^^Bd de la Citadelle, 55100 Verdun",
    "sg:orig_category":"Non-Classified Establishments",
    "sg:phone":"+33 3 29 86 15 00",
    "sg:province":"Lorraine",
    "wof:name":"Moulet Mat\u00e9riaux S.a.",
    "wof:placetype":"venue"
},
  "geometry": {"coordinates":[5.383225,49.164806],"type":"Point"}
}