{
  "type": "Feature",
  "properties": {
    "addr:full":"B.P. 52, 57250 Moyeuvre Grande^^5, Rue Joffre, 57250 Moyeuvre Grande Lorraine",
    "addr:postcode":"57250;57250",
    "addr:street":"B.P. 52;Rue Joffre;Grande",
    "iso:country":"FR",
    "sg:address":"B.P. 52, 57250 Moyeuvre Grande^^5, Rue Joffre, 57250 Moyeuvre Grande",
    "sg:orig_category":"Non-Classified Establishments",
    "sg:phone":"+33 3 87 58 62 63",
    "sg:province":"Lorraine",
    "wof:name":"Etilor S.a.",
    "wof:placetype":"venue"
},
  "geometry": {"coordinates":[6.045152,49.251892],"type":"Point"}
}