{
  "type": "Feature",
  "properties": {
    "iso:country":"FR",
    "sg:address":"B.P. 72438, 44324 Nantes C\u00e9dex 3^^4, Rue du Ch\u00e2teau de l'Eraudi\u00e8re, 44300 Nantes",
    "sg:orig_category":"Non-Classified Establishments",
    "sg:phone":"+33 2 40 18 52 00",
    "sg:province":"Pays de Loire",
    "wof:name":"Sodifrance T.m.s. S.a. - Technologie Multi Supports",
    "wof:placetype":"venue"
},
  "geometry": {"coordinates":[-1.540981,47.238392],"type":"Point"}
}