{
  "type": "Feature",
  "properties": {
    "addr:full":"12 avenue Lauzier 13008 Marseille Provence-Alpes-C\u00f4te d'Azur",
    "addr:housenumber":"12",
    "addr:postcode":"13008",
    "addr:street":"Avenue Lauzier",
    "iso:country":"FR",
    "sg:address":"12 avenue Lauzier 13008 Marseille",
    "sg:classifiers":[
        {
            "category":"Banks & Credit Unions",
            "subcategory":"Investment Brokerage",
            "type":"Services"
        }
    ],
    "sg:phone":"+33 4 91 73 06 79",
    "sg:province":"Provence-Alpes-C\u00f4te d'Azur",
    "sg:tags":[
        "stoneware",
        "household",
        "use"
    ],
    "wof:name":"Marcel Figu\u00e8re Et Fils S.a.r.l.",
    "wof:placetype":"venue"
},
  "geometry": {"coordinates":[5.373278,43.243778],"type":"Point"}
}