{
  "type": "Feature",
  "properties": {
    "iso:country":"FR",
    "sg:address":"Rte de Fourques - Le Saujean",
    "sg:city":"Beaucaire",
    "sg:orig_category":"Unclassifiable Establishments",
    "sg:phone":"+33 4 90 89 83 49",
    "sg:postcode":"30300",
    "sg:province":"Languedoc-Roussillon",
    "wof:name":"Le Saujean S.a.r.l.",
    "wof:placetype":"venue"
},
  "geometry": {"coordinates":[4.61007,43.69405],"type":"Point"}
}