{
  "type": "Feature",
  "properties": {
    "addr:full":"Site de Marmilhat Lempdes Auvergne 63370",
    "addr:postcode":"63370",
    "iso:country":"FR",
    "sg:address":"Site de Marmilhat",
    "sg:city":"Lempdes",
    "sg:orig_category":"Unclassifiable Establishments",
    "sg:phone":"+33 4 73 14 60 60",
    "sg:postcode":"63370",
    "sg:province":"Auvergne",
    "wof:name":"Geneform S.a.",
    "wof:placetype":"venue"
},
  "geometry": {"coordinates":[3.177015,45.776958],"type":"Point"}
}