{
  "type": "Feature",
  "properties": {
    "iso:country":"FR",
    "sg:address":"4, Rte du Loir, 13250 Saint Chamas",
    "sg:orig_category":"Unclassifiable Establishments",
    "sg:phone":"+33 4 90 50 85 00",
    "sg:province":"Picardie",
    "wof:name":"Marius Bernard S.a.",
    "wof:placetype":"venue"
},
  "geometry": {"coordinates":[5.034913,43.559074],"type":"Point"}
}