{
  "type": "Feature",
  "properties": {
    "addr:full":"58 Avenue Guynemer Marcq En Baroeul Nord Pas-de-Calais 59700",
    "addr:housenumber":"58",
    "addr:postcode":"59700",
    "addr:street":"Avenue Guynemer Marcq;Pas-De-Calais",
    "iso:country":"FR",
    "sg:address":"58 Avenue Guynemer",
    "sg:city":"Marcq En Baroeul",
    "sg:classifiers":[
        {
            "category":"Banks & Credit Unions",
            "subcategory":"Financial Services",
            "type":"Services"
        }
    ],
    "sg:phone":"+33 3 20 72 36 66",
    "sg:postcode":"59700",
    "sg:province":"Nord Pas-de-Calais",
    "sg:tags":[
        "banking",
        "finance",
        "insurance"
    ],
    "wof:name":"Scm Martin Philippe & Theetten Jerome",
    "wof:placetype":"venue"
},
  "geometry": {"coordinates":[3.109165,50.666199],"type":"Point"}
}