{
  "type": "Feature",
  "properties": {
    "addr:full":"22 rue de l'Eglise; Plougastel Midi Pyr\u00e9n\u00e9es",
    "addr:housenumber":"22",
    "addr:street":"Rue De L'Eglise",
    "iso:country":"FR",
    "sg:address":"22 rue de l'Eglise; Plougastel",
    "sg:classifiers":[
        {
            "category":"Banks & Credit Unions",
            "subcategory":"Bank",
            "type":"Services"
        }
    ],
    "sg:phone":"+33 3398403727",
    "sg:province":"Midi Pyr\u00e9n\u00e9es",
    "wof:name":"Cr\u00e9dit Agricole Mutuel",
    "wof:placetype":"venue"
},
  "geometry": {"coordinates":[-4.371437,48.37373],"type":"Point"}
}