{
  "type": "Feature",
  "properties": {
    "iso:country":"FR",
    "sg:address":"Route St Andiol 13440 Cabannes",
    "sg:classifiers":[
        {
            "category":"Professional",
            "type":"Services"
        }
    ],
    "sg:phone":"+33 4 90 95 24 93",
    "sg:province":"Rhone-Alpes",
    "sg:tags":[
        "transport",
        "road"
    ],
    "wof:name":"Vidal Sas",
    "wof:placetype":"venue"
},
  "geometry": {"coordinates":[4.948387,43.853321],"type":"Point"}
}