{
  "type": "Feature",
  "properties": {
    "addr:full":"B.P. 22, 17182 P\u00e9rigny C\u00e9dex^^Rond-Point de la R\u00e9publique, 17180 P\u00e9rigny Poitou-Charentes",
    "addr:postcode":"17182;17180",
    "addr:street":"B.P. 22;Re\u0301Publique",
    "iso:country":"FR",
    "sg:address":"B.P. 22, 17182 P\u00e9rigny C\u00e9dex^^Rond-Point de la R\u00e9publique, 17180 P\u00e9rigny",
    "sg:orig_category":"Non-Classified Establishments",
    "sg:phone":"+33 5 46 45 04 53",
    "sg:province":"Poitou-Charentes",
    "wof:name":"S.r.m.o. S.a.r.l. - Soci\u00e9t\u00e9 De Reconstruction Et R\u00e9paration De Machine-outils",
    "wof:placetype":"venue"
},
  "geometry": {"coordinates":[-1.096665,46.15501],"type":"Point"}
}