{
  "type": "Feature",
  "properties": {
    "iso:country":"FR",
    "sg:address":"1, Cours d'Ormesson, 51000 Ch\u00e2lons en Champagne",
    "sg:orig_category":"Unclassifiable Establishments",
    "sg:phone":"+33 3 26 65 19 62",
    "sg:province":"Champagne",
    "wof:name":"D.r.c.e. - Direction R\u00e9gionale Du Commerce Ext\u00e9rieur",
    "wof:placetype":"venue"
},
  "geometry": {"coordinates":[4.364942,48.952686],"type":"Point"}
}