{
  "type": "Feature",
  "properties": {
    "iso:country":"FR",
    "sg:address":"ZA des Ormeaux",
    "sg:city":"Moulay",
    "sg:orig_category":"Non-Classified Establishments",
    "sg:phone":"+33 2 43 00 40 87",
    "sg:postcode":"53100",
    "sg:province":"Pays de Loire",
    "wof:name":"Letertre S.a.",
    "wof:placetype":"venue"
},
  "geometry": {"coordinates":[-0.625796,48.272095],"type":"Point"}
}