{
  "type": "Feature",
  "properties": {
    "addr:full":"55 Rue Lafayette 01200 Bellegarde Sur Valserine Rhone-Alpes 01200",
    "addr:housenumber":"55",
    "addr:postcode":"01200;01200",
    "addr:street":"Rue Lafayette;Rhone-Alpes",
    "iso:country":"FR",
    "sg:address":"55 Rue Lafayette 01200 Bellegarde Sur Valserine",
    "sg:classifiers":[
        {
            "category":"Manufacturing",
            "subcategory":"Chemicals & Compounds",
            "type":"Manufacturing & Wholesale Goods"
        }
    ],
    "sg:phone":"+33 4 50 48 27 31",
    "sg:postcode":"01200",
    "sg:province":"Rhone-Alpes",
    "sg:tags":[
        "pharmaceutical",
        "energy",
        "chemistry",
        "-",
        "by-product"
    ],
    "wof:name":"La Mure Bianco Produits Petroliers",
    "wof:placetype":"venue"
},
  "geometry": {"coordinates":[5.822705,46.107079],"type":"Point"}
}