{
  "type": "Feature",
  "properties": {
    "iso:country":"FR",
    "sg:address":"20, Av. de Verdun, 94200 Ivry sur Seine",
    "sg:orig_category":"Unclassifiable Establishments",
    "sg:phone":"+33 1 46 70 89 99",
    "sg:province":"Ile de France",
    "wof:name":"Thanh Binh Jeune S.a.r.l.",
    "wof:placetype":"venue"
},
  "geometry": {"coordinates":[2.367727,48.815899],"type":"Point"}
}