{
  "type": "Feature",
  "properties": {
    "iso:country":"FR",
    "sg:address":"7 Avenue Jean Jaur\u00e9s 51120 S\u00e9zanne",
    "sg:classifiers":[
        {
            "category":"Home & Garden",
            "subcategory":"Furniture",
            "type":"Retail Goods"
        }
    ],
    "sg:phone":"+33 3 26 80 61 78",
    "sg:postcode":"51120",
    "sg:province":"Champagne",
    "sg:tags":[
        "household",
        "wood"
    ],
    "wof:name":"Schumer Et Cie Sa",
    "wof:placetype":"venue"
},
  "geometry": {"coordinates":[3.726448,48.716228],"type":"Point"}
}