{
  "type": "Feature",
  "properties": {
    "iso:country":"FR",
    "sg:address":"B.P. 42, 39220 Les Rousses^^Fort des Rousses, 39220 Les Rousses",
    "sg:orig_category":"Non-Classified Establishments",
    "sg:phone":"+33 3 84 60 56 00",
    "sg:postcode":"39220",
    "sg:province":"Franche Comt\u00e9",
    "wof:name":"Comotec S.a.",
    "wof:placetype":"venue"
},
  "geometry": {"coordinates":[6.059062,46.485191],"type":"Point"}
}