{
  "type": "Feature",
  "properties": {
    "iso:country":"FR",
    "sg:address":"Rte D\u00e9partementale 42 Zi Les Troques 69630 Chaponost",
    "sg:classifiers":[
        {
            "category":"Shopping",
            "type":"Retail Goods"
        }
    ],
    "sg:phone":"+33 4 78 86 81 11",
    "sg:province":"Rhone-Alpes",
    "sg:tags":[
        "metallurgy",
        "finished",
        "-",
        "metalworking",
        "metallic"
    ],
    "wof:name":"Ruget Sas",
    "wof:placetype":"venue"
},
  "geometry": {"coordinates":[4.74319,45.710232],"type":"Point"}
}