{
  "type": "Feature",
  "properties": {
    "addr:full":"13, Rue de Turbigo, 75002 Paris Ile de France",
    "addr:housenumber":"13",
    "addr:postcode":"75002",
    "addr:street":"Rue De Turbigo",
    "iso:country":"FR",
    "sg:address":"13, Rue de Turbigo, 75002 Paris",
    "sg:orig_category":"Non-Classified Establishments",
    "sg:phone":"+33 1 53 40 74 31",
    "sg:province":"Ile de France",
    "wof:name":"Firma Diffusion S.a.r.l.",
    "wof:placetype":"venue"
},
  "geometry": {"coordinates":[2.349218,48.86396],"type":"Point"}
}