{
  "type": "Feature",
  "properties": {
    "addr:full":"1 Rue Velpeau P.I. Nord 37110 Ch\u00e2teau Renault Autr\u00e8che Centre 37110",
    "addr:housenumber":"1;autre\u0300che",
    "addr:postcode":"37110;37110",
    "addr:street":"Rue Velpeau P.I. Nord",
    "iso:country":"FR",
    "sg:address":"1 Rue Velpeau P.I. Nord 37110 Ch\u00e2teau Renault",
    "sg:city":"Autr\u00e8che",
    "sg:classifiers":[
        {
            "category":"Manufacturing",
            "subcategory":"Paper Products",
            "type":"Manufacturing & Wholesale Goods"
        }
    ],
    "sg:phone":"+33 2 47 29 82 22",
    "sg:postcode":"37110",
    "sg:province":"Centre",
    "sg:tags":[
        "packaging",
        "material",
        "-",
        "cardboard"
    ],
    "wof:name":"Davoise Productions Cartonnage",
    "wof:placetype":"venue"
},
  "geometry": {"coordinates":[0.99705,47.524975],"type":"Point"}
}