{
  "type": "Feature",
  "properties": {
    "addr:full":"Saint Jory Za de l'Hobit 31790 St Sauveur Midi Pyr\u00e9n\u00e9es 31790",
    "addr:postcode":"31790;pyre\u0301ne\u0301es 31790",
    "addr:street":"Za De L'Hobit;St",
    "iso:country":"FR",
    "sg:address":"Saint Jory Za de l'Hobit 31790 St Sauveur",
    "sg:classifiers":[
        {
            "category":"Manufacturing",
            "subcategory":"Tools & Machinery",
            "type":"Manufacturing & Wholesale Goods"
        }
    ],
    "sg:phone":"+33 5 34 27 03 00",
    "sg:postcode":"31790",
    "sg:province":"Midi Pyr\u00e9n\u00e9es",
    "sg:tags":[
        "hole",
        "drilling",
        "deep"
    ],
    "wof:name":"Sud Distribution Materiel Sas",
    "wof:placetype":"venue"
},
  "geometry": {"coordinates":[1.40003,43.74926],"type":"Point"}
}