{
  "type": "Feature",
  "properties": {
    "iso:country":"FR",
    "sg:address":"91195 Gif sur Yvette C\u00e9dex^^Rte de l'Orme des Merisiers - Immeuble Gemini II",
    "sg:city":"Gif sur Yvette",
    "sg:orig_category":"Non-Classified Establishments",
    "sg:phone":"+33 1 69 35 56 30",
    "sg:postcode":"91190",
    "sg:province":"Ile de France",
    "wof:name":"Albis Plastique France S.a.r.l.",
    "wof:placetype":"venue"
},
  "geometry": {"coordinates":[2.13463,48.708038],"type":"Point"}
}