{
  "type": "Feature",
  "properties": {
    "iso:country":"FR",
    "sg:address":"Les Boulais 35890 Laille",
    "sg:city":"Laill\u00e9",
    "sg:orig_category":"Non-Classified Establishments",
    "sg:phone":"+33 2 99 42 54 57",
    "sg:postcode":"35890",
    "sg:province":"Bretagne",
    "wof:name":"Oct S.a.",
    "wof:placetype":"venue"
},
  "geometry": {"coordinates":[-1.701923,47.957352],"type":"Point"}
}