{
  "type": "Feature",
  "properties": {
    "addr:full":"2 Rue De La Division Leclerc 53200 Gennes Sur Glaize Pays de Loire 53200",
    "addr:housenumber":"2",
    "addr:postcode":"53200;53200",
    "addr:street":"Rue De La Division Leclerc;Glaize",
    "iso:country":"FR",
    "sg:address":"2 Rue De La Division Leclerc 53200 Gennes Sur Glaize",
    "sg:classifiers":[
        {
            "category":"Wholesale",
            "subcategory":"Farm Supplies",
            "type":"Manufacturing & Wholesale Goods"
        }
    ],
    "sg:phone":"+33 2 43 70 90 00",
    "sg:postcode":"53200",
    "sg:province":"Pays de Loire",
    "sg:tags":[
        "-",
        "machine",
        "equipment",
        "engineering",
        "machinery",
        "mechanical",
        "agriculture"
    ],
    "wof:name":"Romet Sas",
    "wof:placetype":"venue"
},
  "geometry": {"coordinates":[-0.614989,47.851959],"type":"Point"}
}