{
  "type": "Feature",
  "properties": {
    "addr:full":"36 avenue de l'Europe 78140 Velizy Villacoublay Ile de France",
    "addr:housenumber":"36",
    "addr:postcode":"78140",
    "addr:street":"Avenue De L'Europe",
    "iso:country":"FR",
    "sg:address":"36 avenue de l'Europe 78140 Velizy Villacoublay",
    "sg:orig_category":"Production Lines, Manufacturing Machines",
    "sg:phone":"+33 1 30 67 72 00",
    "sg:province":"Ile de France",
    "wof:name":"Rockwell Automation S.a.",
    "wof:placetype":"venue"
},
  "geometry": {"coordinates":[2.217197,48.779724],"type":"Point"}
}