{
  "type": "Feature",
  "properties": {
    "addr:full":"16, Rue des Lilas, 27440 Houville En Vexin Haute Normandie",
    "addr:housenumber":"16",
    "addr:postcode":"27440",
    "addr:street":"Rue Des Lilas;Haute Normandie",
    "iso:country":"FR",
    "sg:address":"16, Rue des Lilas, 27440 Houville En Vexin",
    "sg:orig_category":"Non-Classified Establishments",
    "sg:phone":"+33 2 32 54 12 47",
    "sg:province":"Haute Normandie",
    "wof:name":"J. P. Masson S.a.r.l.",
    "wof:placetype":"venue"
},
  "geometry": {"coordinates":[1.353653,49.299824],"type":"Point"}
}