{
  "type": "Feature",
  "properties": {
    "iso:country":"FR",
    "sg:address":"25 av Marcel Aime; Hautmont; 59330",
    "sg:classifiers":[
        {
            "category":"Banks & Credit Unions",
            "subcategory":"Bank",
            "type":"Services"
        }
    ],
    "sg:phone":"+33 27642381",
    "sg:postcode":"59330",
    "sg:province":"Nord Pas-de-Calais",
    "wof:name":"Banque Nationale De Paris",
    "wof:placetype":"venue"
},
  "geometry": {"coordinates":[3.918947,50.251209],"type":"Point"}
}