{
  "type": "Feature",
  "properties": {
    "addr:full":"Le Pont De See 50150 Sourdeval Sourdeval Basse Normandie 50150",
    "addr:postcode":"50150;50150",
    "addr:street":"Le Pont De See",
    "iso:country":"FR",
    "sg:address":"Le Pont De See 50150 Sourdeval",
    "sg:city":"Sourdeval",
    "sg:orig_category":"Food and Related Products Leather - raw materials Leather and Shoes Meats and cooked meat Shoes",
    "sg:phone":"+33 2 33 79 34 80",
    "sg:postcode":"50150",
    "sg:province":"Basse Normandie",
    "wof:name":"Sme Renaud Saveur Sarl",
    "wof:placetype":"venue"
},
  "geometry": {"coordinates":[-0.926847,48.709717],"type":"Point"}
}