{
  "type": "Feature",
  "properties": {
    "iso:country":"FR",
    "sg:address":"1 Rue Abbaye 76960 Notre Dame De Bondeville",
    "sg:classifiers":[
        {
            "category":"Manufacturing",
            "subcategory":"Chemicals & Compounds",
            "type":"Manufacturing & Wholesale Goods"
        }
    ],
    "sg:phone":"+33 2 35 14 34 00",
    "sg:postcode":"76960",
    "sg:province":"Haute Normandie",
    "sg:tags":[
        "pharmaceutical",
        "chemistry"
    ],
    "wof:name":"Sanofi Pharma Industrie",
    "wof:placetype":"venue"
},
  "geometry": {"coordinates":[1.037069,49.502102],"type":"Point"}
}