{
  "type": "Feature",
  "properties": {
    "addr:full":"9, Rte de Beaucaire, 30300 Jonqui\u00e8res Saint Vincent Languedoc-Roussillon",
    "addr:housenumber":"9",
    "addr:postcode":"30300",
    "addr:street":"Rte De Beaucaire",
    "iso:country":"FR",
    "sg:address":"9, Rte de Beaucaire, 30300 Jonqui\u00e8res Saint Vincent",
    "sg:orig_category":"Unclassifiable Establishments",
    "sg:phone":"+33 4 66 74 50 43",
    "sg:province":"Languedoc-Roussillon",
    "wof:name":"Roux G\u00e9rard S.a.r.l.",
    "wof:placetype":"venue"
},
  "geometry": {"coordinates":[4.567424,43.829323],"type":"Point"}
}