{
  "type": "Feature",
  "properties": {
    "addr:full":"61, Av. de Sainte Austreberthe, 62140 Hesdin Nord Pas-de-Calais",
    "addr:postcode":"62140",
    "addr:street":"61 Av. De Sainte Austreberthe",
    "iso:country":"FR",
    "sg:address":"61, Av. de Sainte Austreberthe, 62140 Hesdin",
    "sg:orig_category":"Unclassifiable Establishments",
    "sg:phone":"+33 3 21 86 64 33",
    "sg:province":"Nord Pas-de-Calais",
    "wof:name":"Distri Club M\u00e9dical S.a.",
    "wof:placetype":"venue"
},
  "geometry": {"coordinates":[2.036125,50.371975],"type":"Point"}
}