{
  "type": "Feature",
  "properties": {
    "addr:full":"3, All\u00e9e du Bousquet, 31770 Colomiers Midi Pyr\u00e9n\u00e9es",
    "addr:housenumber":"3",
    "addr:postcode":"31770",
    "addr:street":"Alle\u0301E Du Bousquet",
    "iso:country":"FR",
    "sg:address":"3, All\u00e9e du Bousquet, 31770 Colomiers",
    "sg:orig_category":"Non-Classified Establishments",
    "sg:phone":"+33 5 61 78 11 64",
    "sg:province":"Midi Pyr\u00e9n\u00e9es",
    "wof:name":"Ferrari Industries S.a.r.l.",
    "wof:placetype":"venue"
},
  "geometry": {"coordinates":[1.326157,43.597363],"type":"Point"}
}