{
  "type": "Feature",
  "properties": {
    "addr:full":"B.P. 3 Les Vign\u00e8res^^84300 Les Vign\u00e8res Poitou-Charentes 84300",
    "addr:housenumber":"3",
    "addr:postcode":"84300",
    "addr:street":"B.P.;Les Vigne\u0300Res^^84300 Les Vigne\u0300Res",
    "iso:country":"FR",
    "sg:address":"B.P. 3",
    "sg:city":"Les Vign\u00e8res^^84300 Les Vign\u00e8res",
    "sg:orig_category":"Non-Classified Establishments",
    "sg:phone":"+33 4 90 78 67 67",
    "sg:postcode":"84300",
    "sg:province":"Poitou-Charentes",
    "wof:name":"Guedj Guy S.a.",
    "wof:placetype":"venue"
},
  "geometry": {"coordinates":[5.039415,43.837685],"type":"Point"}
}