{
  "type": "Feature",
  "properties": {
    "iso:country":"FR",
    "sg:address":"B.P. 3",
    "sg:city":"Les Vign\u00e8res^^84300 Les Vign\u00e8res",
    "sg:orig_category":"Non-Classified Establishments",
    "sg:phone":"+33 4 90 78 67 67",
    "sg:postcode":"84300",
    "sg:province":"Poitou-Charentes",
    "wof:name":"Guedj Guy S.a.",
    "wof:placetype":"venue"
},
  "geometry": {"coordinates":[5.039415,43.837685],"type":"Point"}
}