{
  "type": "Feature",
  "properties": {
    "addr:full":"B.P. 44, 54280 Seichamps^^ZAC du Chanois, 54280 Seichamps Lorraine 54280",
    "addr:postcode":"54280;54280;54280",
    "addr:street":"B.P. 44;Chanois",
    "iso:country":"FR",
    "sg:address":"B.P. 44, 54280 Seichamps^^ZAC du Chanois, 54280 Seichamps",
    "sg:orig_category":"Non-Classified Establishments",
    "sg:phone":"+33 3 83 18 50 00",
    "sg:postcode":"54280",
    "sg:province":"Lorraine",
    "wof:name":"Cl\u00e9ment S.a.",
    "wof:placetype":"venue"
},
  "geometry": {"coordinates":[6.255398,48.715652],"type":"Point"}
}