{
  "type": "Feature",
  "properties": {
    "iso:country":"FR",
    "sg:address":"rue Henry Bessemer 85000 La Roche sur Yon",
    "sg:classifiers":[
        {
            "category":"Manufacturing",
            "subcategory":"Motor Vehicles & Parts",
            "type":"Manufacturing & Wholesale Goods"
        }
    ],
    "sg:phone":"+33 2 51 45 47 00",
    "sg:postcode":"85000",
    "sg:province":"Pays de Loire",
    "sg:tags":[
        "packing",
        "handling",
        "robot",
        "unpacking"
    ],
    "wof:name":"Sepro Robotique Sa",
    "wof:placetype":"venue"
},
  "geometry": {"coordinates":[-1.377007,46.699219],"type":"Point"}
}