{
  "type": "Feature",
  "properties": {
    "addr:full":"B.P. 95, 67038 Strasbourg C\u00e9dex^^17, Rue des Fr\u00e8res Lumi\u00e8re, 67000 Strasbourg Strasbourg Alsace 67000",
    "addr:postcode":"67038;67000;67000",
    "addr:street":"B.P. 95;Rue Des Fre\u0300Res Lumie\u0300Re",
    "iso:country":"FR",
    "sg:address":"B.P. 95, 67038 Strasbourg C\u00e9dex^^17, Rue des Fr\u00e8res Lumi\u00e8re, 67000 Strasbourg",
    "sg:city":"Strasbourg",
    "sg:orig_category":"Non-Classified Establishments",
    "sg:phone":"+33 3 90 20 78 50",
    "sg:postcode":"67000",
    "sg:province":"Alsace",
    "wof:name":"Sodap Sobomex S.a.r.l.",
    "wof:placetype":"venue"
},
  "geometry": {"coordinates":[7.73643,48.585079],"type":"Point"}
}