{
  "type": "Feature",
  "properties": {
    "iso:country":"FR",
    "sg:address":"avenue du 10 Ao\u00fbt 12300 DECAZEVILLE",
    "sg:classifiers":[
        {
            "category":"Military Area",
            "subcategory":"Air Force Base",
            "type":"Public Place"
        }
    ],
    "sg:phone":"+33 5 65 63 67 54",
    "sg:province":"Midi Pyr\u00e9n\u00e9es",
    "sg:tags":[
        "iron",
        "pig"
    ],
    "wof:name":"Fonderie Rivi\u00e8re Decazeville S.a.",
    "wof:placetype":"venue"
},
  "geometry": {"coordinates":[2.255207,44.558464],"type":"Point"}
}