{
  "type": "Feature",
  "properties": {
    "addr:full":"All Paul Decauville 26000 Valence Rhone-Alpes 26000",
    "addr:postcode":"26000;26000",
    "addr:street":"Decauville",
    "iso:country":"FR",
    "sg:address":"All Paul Decauville 26000 Valence",
    "sg:classifiers":[
        {
            "category":"Utilities",
            "subcategory":"Electric",
            "type":"Services"
        }
    ],
    "sg:phone":"+33 4 75 81 72 20",
    "sg:postcode":"26000",
    "sg:province":"Rhone-Alpes",
    "sg:tags":[
        "electricity",
        "electronic",
        "electrical",
        "equipment"
    ],
    "wof:name":"Anciens Etablissements Maxence Isnard",
    "wof:placetype":"venue"
},
  "geometry": {"coordinates":[4.888446,44.889946],"type":"Point"}
}