{
  "type": "Feature",
  "properties": {
    "addr:full":"9, Rue du Clos Courtel, 35700 Rennes Rennes Bretagne 35700",
    "addr:housenumber":"9",
    "addr:postcode":"35700;35700",
    "addr:street":"Rue Du Clos Courtel",
    "iso:country":"FR",
    "sg:address":"9, Rue du Clos Courtel, 35700 Rennes",
    "sg:city":"Rennes",
    "sg:orig_category":"Non-Classified Establishments",
    "sg:phone":"+33 2 99 38 33 30",
    "sg:postcode":"35700",
    "sg:province":"Bretagne",
    "wof:name":"C.b.b. D\u00e9veloppement",
    "wof:placetype":"venue"
},
  "geometry": {"coordinates":[-1.628154,48.125244],"type":"Point"}
}