{
  "type": "Feature",
  "properties": {
    "addr:full":"B.P. 49, 68801 Thann C\u00e9dex^^54, Fbg des Vosges, 68800 Thann Thann Alsace 68800",
    "addr:postcode":"68801;68800;68800",
    "addr:street":"B.P. 49;Des Vosges",
    "iso:country":"FR",
    "sg:address":"B.P. 49, 68801 Thann C\u00e9dex^^54, Fbg des Vosges, 68800 Thann",
    "sg:city":"Thann",
    "sg:orig_category":"Non-Classified Establishments",
    "sg:phone":"+33 3 89 37 76 43",
    "sg:postcode":"68800",
    "sg:province":"Alsace",
    "wof:name":"Scheurer Tissus D'ameublement S.a.",
    "wof:placetype":"venue"
},
  "geometry": {"coordinates":[7.10335,47.810196],"type":"Point"}
}