{
  "type": "Feature",
  "properties": {
    "addr:full":"38, Chemin des Petits Marais - Port de Gennevilliers, 92230 Gennevilliers Ile de France",
    "addr:housenumber":"38",
    "addr:postcode":"92230;ile",
    "addr:street":"Chemin Des Petits Marais Port De Gennevilliers",
    "iso:country":"FR",
    "sg:address":"38, Chemin des Petits Marais - Port de Gennevilliers, 92230 Gennevilliers",
    "sg:orig_category":"Unclassifiable Establishments",
    "sg:phone":"+33 1 41 47 99 40",
    "sg:province":"Ile de France",
    "wof:name":"Districhimie S.a.",
    "wof:placetype":"venue"
},
  "geometry": {"coordinates":[2.29447,48.925026],"type":"Point"}
}