{
  "type": "Feature",
  "properties": {
    "addr:full":"40 Rue Xaintrailles 45017 Orl\u00e9ans Orl\u00e9ans Centre 45000",
    "addr:housenumber":"40",
    "addr:postcode":"45017;45000",
    "addr:street":"Rue Xaintrailles",
    "iso:country":"FR",
    "sg:address":"40 Rue Xaintrailles 45017 Orl\u00e9ans",
    "sg:city":"Orl\u00e9ans",
    "sg:classifiers":[
        {
            "category":"Utilities",
            "subcategory":"Electric",
            "type":"Services"
        }
    ],
    "sg:phone":"+33 2 38 62 34 02",
    "sg:postcode":"45000",
    "sg:province":"Centre",
    "sg:tags":[
        "electricity",
        "electronic",
        "electrical",
        "equipment"
    ],
    "wof:name":"Loirelec Sarl",
    "wof:placetype":"venue"
},
  "geometry": {"coordinates":[1.89473,47.906101],"type":"Point"}
}