{
  "type": "Feature",
  "properties": {
    "addr:full":"33, Rue du Chemin de fer, 92160 Antony Ile de France",
    "addr:housenumber":"33",
    "addr:postcode":"92160",
    "addr:street":"Rue Du Chemin De Fer",
    "iso:country":"FR",
    "sg:address":"33, Rue du Chemin de fer, 92160 Antony",
    "sg:orig_category":"Non-Classified Establishments",
    "sg:phone":"+33 1 42 37 85 48",
    "sg:province":"Ile de France",
    "wof:name":"Wendel France Emaceram S.a.r.l.",
    "wof:placetype":"venue"
},
  "geometry": {"coordinates":[2.306395,48.745232],"type":"Point"}
}