{
  "type": "Feature",
  "properties": {
    "addr:full":"36 du Marechal Leclerc BP 10 91200 Athis Mons Ile de France 91200",
    "addr:housenumber":"36;10",
    "addr:postcode":"91200;91200",
    "addr:street":"Du Marechal Leclerc Bp",
    "iso:country":"FR",
    "sg:address":"36",
    "sg:city":"du Marechal Leclerc BP 10 91200 Athis Mons",
    "sg:classifiers":[
        {
            "category":"Shopping",
            "subcategory":"Crafts & Fabrics",
            "type":"Retail Goods"
        }
    ],
    "sg:phone":"+33 1 60 48 40 47",
    "sg:postcode":"91200",
    "sg:province":"Ile de France",
    "sg:tags":[
        "textile",
        "clothing"
    ],
    "wof:name":"Broderie Creation Cornely",
    "wof:placetype":"venue"
},
  "geometry": {"coordinates":[2.372354,48.707203],"type":"Point"}
}