{
  "type": "Feature",
  "properties": {
    "addr:full":"66 rue du G\u00e9n\u00e9ral Leclerc 88190 Golbey Lorraine 88190",
    "addr:housenumber":"66",
    "addr:postcode":"88190;88190",
    "addr:street":"Rue Du Ge\u0301Ne\u0301Ral Leclerc",
    "iso:country":"FR",
    "sg:address":"66 rue du G\u00e9n\u00e9ral Leclerc 88190 Golbey",
    "sg:classifiers":[
        {
            "category":"Education",
            "subcategory":"Special Training",
            "type":"Public Place"
        }
    ],
    "sg:phone":"+33 3 29 34 75 40",
    "sg:postcode":"88190",
    "sg:province":"Lorraine",
    "sg:tags":[
        "bread"
    ],
    "wof:name":"G. Mercier S.a.r.l.",
    "wof:placetype":"venue"
},
  "geometry": {"coordinates":[6.422086,48.190956],"type":"Point"}
}