{
  "type": "Feature",
  "properties": {
    "iso:country":"FR",
    "sg:address":"5 Rue Adolphe Defarge 04100 Manosque",
    "sg:classifiers":[
        {
            "category":"Professional",
            "subcategory":"Printing & Photocopies",
            "type":"Services"
        }
    ],
    "sg:phone":"+33 4 92 72 78 20",
    "sg:province":"Aquitaine",
    "sg:tags":[
        "publishing"
    ],
    "wof:name":"Alpes Edition",
    "wof:placetype":"venue"
},
  "geometry": {"coordinates":[5.782143,43.833023],"type":"Point"}
}