{
  "type": "Feature",
  "properties": {
    "iso:country":"FR",
    "sg:address":"Rue des Carts",
    "sg:city":"Valonne",
    "sg:orig_category":"Non-Classified Establishments",
    "sg:phone":"+33 3 81 93 30 12",
    "sg:postcode":"25190",
    "sg:province":"Franche Comt\u00e9",
    "wof:name":"Corbet Fr\u00e8res S.a.r.l.",
    "wof:placetype":"venue"
},
  "geometry": {"coordinates":[6.661546,47.342842],"type":"Point"}
}