{
  "type": "Feature",
  "properties": {
    "addr:full":"Avenue H De Jouvenel 19130 Objat Limousin 19130",
    "addr:postcode":"19130;19130",
    "addr:street":"Avenue H De Jouvenel",
    "iso:country":"FR",
    "sg:address":"Avenue H De Jouvenel 19130 Objat",
    "sg:classifiers":[
        {
            "category":"Utilities",
            "subcategory":"Electric",
            "type":"Services"
        }
    ],
    "sg:phone":"+33 5 55 25 59 07",
    "sg:postcode":"19130",
    "sg:province":"Limousin",
    "sg:tags":[
        "electricity",
        "raw",
        "energy",
        "material"
    ],
    "wof:name":"Electricite De France (edf)",
    "wof:placetype":"venue"
},
  "geometry": {"coordinates":[1.406945,45.259399],"type":"Point"}
}