{
  "type": "Feature",
  "properties": {
    "iso:country":"FR",
    "sg:address":"10 Rue Auguste Bonamy 60130 St Just En Chauss\u00e9e",
    "sg:classifiers":[
        {
            "category":"Manufacturing",
            "subcategory":"Paper Products",
            "type":"Manufacturing & Wholesale Goods"
        }
    ],
    "sg:phone":"+33 3 44 77 59 00",
    "sg:province":"Picardie",
    "sg:tags":[
        "raw",
        "material",
        "-",
        "cardboard"
    ],
    "wof:name":"Kaysersberg Packaking Sa",
    "wof:placetype":"venue"
},
  "geometry": {"coordinates":[2.434698,49.49884],"type":"Point"}
}