{
  "type": "Feature",
  "properties": {
    "addr:full":"B.P. 47, 68640 Riespach C\u00e9dex^^34, Rue de B\u00e2le, 68640 Riespach Riespach Alsace 68640",
    "addr:postcode":"68640;68640;68640",
    "addr:street":"B.P. 47;Rue De Ba\u0302Le;Riespach",
    "iso:country":"FR",
    "sg:address":"B.P. 47, 68640 Riespach C\u00e9dex^^34, Rue de B\u00e2le, 68640 Riespach",
    "sg:city":"Riespach",
    "sg:orig_category":"Non-Classified Establishments",
    "sg:phone":"+33 3 89 25 82 89",
    "sg:postcode":"68640",
    "sg:province":"Alsace",
    "wof:name":"Dinotec S.a.r.l.",
    "wof:placetype":"venue"
},
  "geometry": {"coordinates":[7.316055,47.550613],"type":"Point"}
}