{
  "type": "Feature",
  "properties": {
    "iso:country":"FR",
    "sg:address":"102, Rue Edouard Vaillant, 93700 Drancy",
    "sg:orig_category":"Non-Classified Establishments",
    "sg:phone":"+33 1 41 60 08 66",
    "sg:province":"Ile de France",
    "wof:name":"Pro.se.de S.a.r.l.",
    "wof:placetype":"venue"
},
  "geometry": {"coordinates":[2.428271,48.926422],"type":"Point"}
}