{
  "type": "Feature",
  "properties": {
    "addr:full":"B.P. 36, 71405 Autun C\u00e9dex^^4, Rue Traversi\u00e8re, 71400 Autun Autun Bourgogne 71400",
    "addr:postcode":"71405;71400;71400",
    "addr:street":"B.P. 36;Rue Traversie\u0300Re",
    "iso:country":"FR",
    "sg:address":"B.P. 36, 71405 Autun C\u00e9dex^^4, Rue Traversi\u00e8re, 71400 Autun",
    "sg:city":"Autun",
    "sg:orig_category":"Non-Classified Establishments",
    "sg:phone":"+33 3 85 86 54 00",
    "sg:postcode":"71400",
    "sg:province":"Bourgogne",
    "wof:name":"Neyrat Autun S.a.",
    "wof:placetype":"venue"
},
  "geometry": {"coordinates":[4.411325,46.902779],"type":"Point"}
}