{
  "type": "Feature",
  "properties": {
    "iso:country":"FR",
    "sg:address":"28, Rue Fran\u00e7ois Premier, 75008 Paris",
    "sg:orig_category":"Unclassifiable Establishments",
    "sg:phone":"+33 1 47 23 11 00",
    "sg:province":"Ile de France",
    "wof:name":"Lagard\u00e8re Active Publicit\u00e9 R\u00e9gion S.n.c.",
    "wof:placetype":"venue"
},
  "geometry": {"coordinates":[2.305528,48.867664],"type":"Point"}
}