{
  "type": "Feature",
  "properties": {
    "addr:full":"ZI Verneuil sur Avre Bourgogne 27135",
    "addr:postcode":"27135",
    "addr:street":"Verneuil;Avre Bourgogne",
    "iso:country":"FR",
    "sg:address":"ZI",
    "sg:city":"Verneuil sur Avre",
    "sg:orig_category":"Unclassifiable Establishments",
    "sg:phone":"+33 2 32 32 01 54",
    "sg:postcode":"27135",
    "sg:province":"Bourgogne",
    "wof:name":"Cooperative Agricole De La R\u00e9gion De Verneuil S.c.a.",
    "wof:placetype":"venue"
},
  "geometry": {"coordinates":[3.869515,46.818153],"type":"Point"}
}