{
  "type": "Feature",
  "properties": {
    "addr:full":"Rn 12 Megaudais 53500 St Pierre Des Landes Pays de Loire",
    "addr:postcode":"53500",
    "addr:street":"Rn 12 Megaudais;St Pierre Des Landes",
    "iso:country":"FR",
    "sg:address":"Rn 12 Megaudais 53500 St Pierre Des Landes",
    "sg:classifiers":[
        {
            "category":"Professional",
            "type":"Services"
        }
    ],
    "sg:phone":"+33 2 43 08 72 00",
    "sg:province":"Pays de Loire",
    "sg:tags":[
        "transport",
        "road"
    ],
    "wof:name":"Ambroise Bouvier Transport Sa",
    "wof:placetype":"venue"
},
  "geometry": {"coordinates":[-0.999719,48.305984],"type":"Point"}
}