{
  "type": "Feature",
  "properties": {
    "addr:full":"5, Rue de la Faisanderie, 67380 Lingolsheim Lingolsheim Alsace 67380",
    "addr:housenumber":"5",
    "addr:postcode":"67380;67380",
    "addr:street":"Rue De La Faisanderie",
    "iso:country":"FR",
    "sg:address":"5, Rue de la Faisanderie, 67380 Lingolsheim",
    "sg:city":"Lingolsheim",
    "sg:orig_category":"Unclassifiable Establishments",
    "sg:phone":"+33 3 88 78 86 50",
    "sg:postcode":"67380",
    "sg:province":"Alsace",
    "wof:name":"Kdp Informatique S.a.r.l.",
    "wof:placetype":"venue"
},
  "geometry": {"coordinates":[7.696438,48.560619],"type":"Point"}
}