{
  "type": "Feature",
  "properties": {
    "addr:full":"B.P. 9, 54121 Vandi\u00e8res^^Z.I., 54121 Vandi\u00e8res Lorraine 54121",
    "addr:housenumber":"9",
    "addr:postcode":"54121;54121;54121",
    "addr:street":"B.P.",
    "iso:country":"FR",
    "sg:address":"B.P. 9, 54121 Vandi\u00e8res^^Z.I., 54121 Vandi\u00e8res",
    "sg:orig_category":"Non-Classified Establishments",
    "sg:phone":"+33 3 83 82 59 00",
    "sg:postcode":"54121",
    "sg:province":"Lorraine",
    "wof:name":"C\u00e9bal S.a.",
    "wof:placetype":"venue"
},
  "geometry": {"coordinates":[6.03689,48.954044],"type":"Point"}
}