{
  "type": "Feature",
  "properties": {
    "addr:full":"176, Av. Charles De Gaulle, 92200 Neuilly sur Seine Ile de France 92200",
    "addr:housenumber":"176",
    "addr:postcode":"92200;92200",
    "addr:street":"Av. Charles De Gaulle",
    "iso:country":"FR",
    "sg:address":"176, Av. Charles De Gaulle, 92200 Neuilly sur Seine",
    "sg:orig_category":"Non-Classified Establishments",
    "sg:phone":"+33 1 47 45 93 00",
    "sg:postcode":"92200",
    "sg:province":"Ile de France",
    "wof:name":"Calvin Klein Cosmetics S.a.",
    "wof:placetype":"venue"
},
  "geometry": {"coordinates":[2.259256,48.885536],"type":"Point"}
}