{
  "type": "Feature",
  "properties": {
    "addr:full":"21, Rue Maynadier, 75019 Paris Ile de France 75019",
    "addr:housenumber":"21",
    "addr:postcode":"75019;75019",
    "addr:street":"Rue Maynadier",
    "iso:country":"FR",
    "sg:address":"21, Rue Maynadier, 75019 Paris",
    "sg:orig_category":"Non-Classified Establishments",
    "sg:phone":"+33 1 42 40 24 86",
    "sg:postcode":"75019",
    "sg:province":"Ile de France",
    "wof:name":"A.c.e.m.a.i. S.a.r.l. - Ascenseurs Cr\u00e9ation Etude Mat\u00e9riel Automatisme In",
    "wof:placetype":"venue"
},
  "geometry": {"coordinates":[2.38385,48.884068],"type":"Point"}
}