{
  "type": "Feature",
  "properties": {
    "addr:full":"Rue Pi\u00e8ronne Bouchain Nord Pas-de-Calais 59111",
    "addr:postcode":"59111",
    "addr:street":"Rue Pie\u0300Ronne Bouchain Nord",
    "iso:country":"FR",
    "sg:address":"Rue Pi\u00e8ronne",
    "sg:city":"Bouchain",
    "sg:orig_category":"Unclassifiable Establishments",
    "sg:phone":"+33 3 27 21 70 30",
    "sg:postcode":"59111",
    "sg:province":"Nord Pas-de-Calais",
    "wof:name":"S.n.c.z. S.a. - Soci\u00e9t\u00e9 Nouvelle Des Couleurs Zinciques",
    "wof:placetype":"venue"
},
  "geometry": {"coordinates":[3.31871,50.282871],"type":"Point"}
}