{
  "type": "Feature",
  "properties": {
    "iso:country":"FR",
    "sg:address":"Rue des Rougeries",
    "sg:city":"Saint Malo",
    "sg:orig_category":"Non-Classified Establishments",
    "sg:phone":"+33 2 99 19 70 70",
    "sg:postcode":"35400",
    "sg:province":"Bretagne",
    "wof:name":"Les Courriers Bretons S.a.",
    "wof:placetype":"venue"
},
  "geometry": {"coordinates":[-1.979491,48.633194],"type":"Point"}
}