{
  "type": "Feature",
  "properties": {
    "iso:country":"FR",
    "sg:address":"Le Bisson 61150 RANES",
    "sg:city":"R\u00e2nes",
    "sg:classifiers":[
        {
            "category":"Manufacturing",
            "subcategory":"Lumber",
            "type":"Manufacturing & Wholesale Goods"
        }
    ],
    "sg:phone":"+33 2 33 39 72 51",
    "sg:postcode":"61150",
    "sg:province":"Basse Normandie",
    "sg:tags":[
        "hardwood",
        "sawmill"
    ],
    "wof:name":"Besson Freres S.a.",
    "wof:placetype":"venue"
},
  "geometry": {"coordinates":[-0.197036,48.638466],"type":"Point"}
}