{
  "type": "Feature",
  "properties": {
    "addr:full":"B.P. 8, 74371 Pringy C\u00e9dex^^520, Rte de Pringy, 74370 Argonay Rhone-Alpes 74370",
    "addr:housenumber":"8",
    "addr:postcode":"74371;74370;74370",
    "addr:street":"B.P.;Rte De Pringy",
    "iso:country":"FR",
    "sg:address":"B.P. 8, 74371 Pringy C\u00e9dex^^520, Rte de Pringy, 74370 Argonay",
    "sg:orig_category":"Non-Classified Establishments",
    "sg:phone":"+33 4 50 27 29 15",
    "sg:postcode":"74370",
    "sg:province":"Rhone-Alpes",
    "wof:name":"Figel S.a.",
    "wof:placetype":"venue"
},
  "geometry": {"coordinates":[6.109395,45.934166],"type":"Point"}
}