{
  "type": "Feature",
  "properties": {
    "iso:country":"FR",
    "sg:address":"28 Rue Des Acacias 93800 Epinay Sur Seine",
    "sg:classifiers":[
        {
            "category":"Manufacturing",
            "subcategory":"Metals",
            "type":"Manufacturing & Wholesale Goods"
        }
    ],
    "sg:phone":"+33 1 48 21 46 38",
    "sg:postcode":"93800",
    "sg:province":"Ile de France",
    "sg:tags":[
        "metallurgy",
        "metalworking",
        "processing"
    ],
    "wof:name":"Oa France",
    "wof:placetype":"venue"
},
  "geometry": {"coordinates":[2.328188,48.94833],"type":"Point"}
}