{
  "type": "Feature",
  "properties": {
    "addr:full":"32 Allee De Tourny 33000 Bordeaux Bordeaux Aquitaine 33000",
    "addr:housenumber":"32",
    "addr:postcode":"33000;33000",
    "addr:street":"Allee De Tourny",
    "iso:country":"FR",
    "sg:address":"32 Allee De Tourny 33000 Bordeaux",
    "sg:city":"Bordeaux",
    "sg:orig_category":"Miscellaneous Products",
    "sg:phone":"+33 5 56 48 26 55",
    "sg:postcode":"33000",
    "sg:province":"Aquitaine",
    "wof:name":"Richard Gouzik Sa",
    "wof:placetype":"venue"
},
  "geometry": {"coordinates":[-0.576645,44.843987],"type":"Point"}
}