{
  "type": "Feature",
  "properties": {
    "iso:country":"FR",
    "sg:address":"10, Rue de la Forge, 68720 Tagolsheim",
    "sg:city":"Tagolsheim",
    "sg:orig_category":"Unclassifiable Establishments",
    "sg:phone":"+33 3 89 25 59 99",
    "sg:postcode":"68720",
    "sg:province":"Alsace",
    "wof:name":"S.a.m.t. D\u00e9veloppement S.a. - Soci\u00e9t\u00e9 Alsacienne De Mat\u00e9riel Textile",
    "wof:placetype":"venue"
},
  "geometry": {"coordinates":[7.266568,47.655277],"type":"Point"}
}