{
  "type": "Feature",
  "properties": {
    "iso:country":"FR",
    "sg:address":"All Treize Femmes 85200 Fontenay Le Comte",
    "sg:classifiers":[
        {
            "category":"Shopping",
            "type":"Retail Goods"
        }
    ],
    "sg:phone":"+33 2 51 53 47 47",
    "sg:postcode":"85200",
    "sg:province":"Pays de Loire",
    "sg:tags":[
        "metallurgy",
        "finished",
        "-",
        "metalworking",
        "metallic"
    ],
    "wof:name":"Societe Vendeenne De Roulements Sas",
    "wof:placetype":"venue"
},
  "geometry": {"coordinates":[-0.779191,46.455822],"type":"Point"}
}