{
  "type": "Feature",
  "properties": {
    "addr:full":"Rue Andr\u00e9 Fj Rieg 51689 Reims Cedex 2 Champagne",
    "addr:postcode":"51689",
    "addr:street":"Rue Andre\u0301 Fj Rieg",
    "iso:country":"FR",
    "sg:address":"Rue Andr\u00e9 Fj Rieg 51689 Reims Cedex 2",
    "sg:classifiers":[
        {
            "category":"Building & Trades",
            "subcategory":"Construction",
            "type":"Services"
        }
    ],
    "sg:phone":"+33 3 26 87 79 50",
    "sg:province":"Champagne",
    "sg:tags":[
        "work",
        "public"
    ],
    "wof:name":"Colas Est",
    "wof:placetype":"venue"
},
  "geometry": {"coordinates":[4.03384,49.25415],"type":"Point"}
}