{
  "type": "Feature",
  "properties": {
    "iso:country":"FR",
    "sg:address":"33 Rue Du 3\u00e8me Zouave 68130 Altkirch",
    "sg:city":"Altkirch",
    "sg:classifiers":[
        {
            "category":"Manufacturing",
            "subcategory":"Metals",
            "type":"Manufacturing & Wholesale Goods"
        }
    ],
    "sg:phone":"+33 3 89 08 96 20",
    "sg:postcode":"68130",
    "sg:province":"Alsace",
    "sg:tags":[
        "pipe",
        "sheet",
        "-",
        "metalworking",
        "metallic",
        "metallurgy",
        "finished"
    ],
    "wof:name":"Bms Tec",
    "wof:placetype":"venue"
},
  "geometry": {"coordinates":[7.257308,47.625961],"type":"Point"}
}