{
  "type": "Feature",
  "properties": {
    "iso:country":"FR",
    "sg:address":"Rte de Chinon",
    "sg:city":"Sainte Maure de Touraine",
    "sg:orig_category":"Unclassifiable Establishments",
    "sg:phone":"+33 2 47 72 37 00",
    "sg:postcode":"37800",
    "sg:province":"Centre",
    "wof:name":"Etablissement Fouasse S.a.r.l.",
    "wof:placetype":"venue"
},
  "geometry": {"coordinates":[0.61336,47.108559],"type":"Point"}
}