{
  "type": "Feature",
  "properties": {
    "addr:full":"14 Chem Moulin De La Bruy\u00e8re BP 17 72250 Challes Pays de Loire 72250",
    "addr:housenumber":"14;17",
    "addr:postcode":"72250 challes;72250",
    "addr:street":"Chem Moulin De La Bruye\u0300Re Bp",
    "iso:country":"FR",
    "sg:address":"14 Chem Moulin De La Bruy\u00e8re BP 17 72250 Challes",
    "sg:classifiers":[
        {
            "category":"Professional",
            "subcategory":"Engineering",
            "type":"Services"
        }
    ],
    "sg:phone":"+33 2 43 86 74 10",
    "sg:postcode":"72250",
    "sg:province":"Pays de Loire",
    "sg:tags":[
        "machine",
        "-",
        "mechanical"
    ],
    "wof:name":"Mt Packaging Sa",
    "wof:placetype":"venue"
},
  "geometry": {"coordinates":[0.412911,47.928593],"type":"Point"}
}