{
  "type": "Feature",
  "properties": {
    "addr:full":"18, Rue de Maubeuge, 75009 Paris Ile de France",
    "addr:housenumber":"18",
    "addr:postcode":"75009",
    "addr:street":"Rue De Maubeuge",
    "iso:country":"FR",
    "sg:address":"18, Rue de Maubeuge, 75009 Paris",
    "sg:orig_category":"Unclassifiable Establishments",
    "sg:phone":"+33 1 48 78 34 01",
    "sg:province":"Ile de France",
    "wof:name":"Laboratoire Du Docteur Dumesny S.a.",
    "wof:placetype":"venue"
},
  "geometry": {"coordinates":[2.342132,48.876923],"type":"Point"}
}