{
  "type": "Feature",
  "properties": {
    "iso:country":"FR",
    "sg:address":"84 Avenue Toulouse 81200 Aussillon",
    "sg:classifiers":[
        {
            "category":"Utilities",
            "subcategory":"Electric",
            "type":"Services"
        }
    ],
    "sg:phone":"+33 5 63 61 14 55",
    "sg:postcode":"81200",
    "sg:province":"Midi Pyr\u00e9n\u00e9es",
    "sg:tags":[
        "electricity",
        "electronic",
        "electrical",
        "equipment"
    ],
    "wof:name":"Meije Pierre Sarl (ets)",
    "wof:placetype":"venue"
},
  "geometry": {"coordinates":[2.355978,43.507202],"type":"Point"}
}