{
  "type": "Feature",
  "properties": {
    "addr:full":"Rue Magellan 31314 Lab\u00e8ge Cedex Languedoc-Roussillon",
    "addr:postcode":"31314;cedex",
    "addr:street":"Rue Magellan",
    "iso:country":"FR",
    "sg:address":"Rue Magellan 31314 Lab\u00e8ge Cedex",
    "sg:classifiers":[
        {
            "category":"Professional",
            "subcategory":"Business Services",
            "type":"Services"
        }
    ],
    "sg:phone":"+33 5 61 00 79 79",
    "sg:province":"Languedoc-Roussillon",
    "sg:tags":[
        "information",
        "advice",
        "technology",
        "software"
    ],
    "wof:name":"Eurogiciel Ingenierie Sa",
    "wof:placetype":"venue"
},
  "geometry": {"coordinates":[1.50224,43.5485],"type":"Point"}
}