{
  "type": "Feature",
  "properties": {
    "addr:full":"4-8 Rue Du Colonel Fabien 51100 Reims Champagne 51100",
    "addr:housenumber":"4-8",
    "addr:postcode":"51100;51100",
    "addr:street":"Rue Du Colonel Fabien",
    "iso:country":"FR",
    "sg:address":"4-8 Rue Du Colonel Fabien 51100 Reims",
    "sg:classifiers":[
        {
            "category":"Autos & Motor Vehicles",
            "subcategory":"Automobile Sales",
            "type":"Retail Goods"
        }
    ],
    "sg:phone":"+33 3 26 50 60 70",
    "sg:postcode":"51100",
    "sg:province":"Champagne",
    "sg:tags":[
        "equipment",
        "motor-cars",
        "transport"
    ],
    "wof:name":"Reanult Reims",
    "wof:placetype":"venue"
},
  "geometry": {"coordinates":[4.018986,49.250103],"type":"Point"}
}