{
  "type": "Feature",
  "properties": {
    "addr:full":"13, Rue Lamartine, 71530 Crissey Crissey Bourgogne 71530",
    "addr:housenumber":"13",
    "addr:postcode":"71530;71530",
    "addr:street":"Rue Lamartine",
    "iso:country":"FR",
    "sg:address":"13, Rue Lamartine, 71530 Crissey",
    "sg:city":"Crissey",
    "sg:orig_category":"Non-Classified Establishments",
    "sg:phone":"+33 3 85 41 93 06",
    "sg:postcode":"71530",
    "sg:province":"Bourgogne",
    "wof:name":"S.e.i. Bourgogne S.a.r.l.",
    "wof:placetype":"venue"
},
  "geometry": {"coordinates":[4.864879,46.810116],"type":"Point"}
}