{
  "type": "Feature",
  "properties": {
    "iso:country":"FR",
    "sg:address":"81, Rue Elis\u00e9e Reclus - Parc des Pivolles, 69153 Decines Charpieu C\u00e9dex",
    "sg:orig_category":"Non-Classified Establishments",
    "sg:phone":"+33 4 72 14 38 38",
    "sg:province":"Rhone-Alpes",
    "wof:name":"Mge Ups Systems S.a.",
    "wof:placetype":"venue"
},
  "geometry": {"coordinates":[4.937022,45.747692],"type":"Point"}
}