{
  "type": "Feature",
  "properties": {
    "addr:full":"Les Trois Ponts 42500 Le Chambon Feugerolles Rhone-Alpes 42500",
    "addr:postcode":"42500;42500",
    "addr:street":"Trois Ponts;Chambon Feugerolles Rhone-Alpes",
    "iso:country":"FR",
    "sg:address":"Les Trois Ponts 42500 Le Chambon Feugerolles",
    "sg:classifiers":[
        {
            "category":"Manufacturing",
            "subcategory":"Tools & Machinery",
            "type":"Manufacturing & Wholesale Goods"
        }
    ],
    "sg:phone":"+33 4 77 61 11 11",
    "sg:postcode":"42500",
    "sg:province":"Rhone-Alpes",
    "sg:tags":[
        "metallurgy",
        "metalworking"
    ],
    "wof:name":"Dofin Sa",
    "wof:placetype":"venue"
},
  "geometry": {"coordinates":[4.29564,45.395432],"type":"Point"}
}