{
  "type": "Feature",
  "properties": {
    "addr:full":"296, Av. Dubauchet, 01400 Ch\u00e2tillon sur Chalaronne Rhone-Alpes",
    "addr:postcode":"01400",
    "addr:street":"296 Av. Dubauchet",
    "iso:country":"FR",
    "sg:address":"296, Av. Dubauchet, 01400 Ch\u00e2tillon sur Chalaronne",
    "sg:orig_category":"Unclassifiable Establishments",
    "sg:phone":"+33 4 74 55 01 41",
    "sg:province":"Rhone-Alpes",
    "wof:name":"Lombard Mat\u00e9riaux S.a.r.l.",
    "wof:placetype":"venue"
},
  "geometry": {"coordinates":[4.951005,46.124565],"type":"Point"}
}