{
  "type": "Feature",
  "properties": {
    "iso:country":"FR",
    "sg:address":"B.P. 5232, 45052 Orl\u00e9ans C\u00e9dex 1^^5, Bd de Quebec, 45000 Orl\u00e9ans",
    "sg:city":"Orl\u00e9ans",
    "sg:orig_category":"Non-Classified Establishments",
    "sg:phone":"+33 2 38 62 41 36",
    "sg:postcode":"45000",
    "sg:province":"Centre",
    "wof:name":"C.n.c. Transport S.a. - Compagnie Nouvelle De Containers",
    "wof:placetype":"venue"
},
  "geometry": {"coordinates":[1.904965,47.901428],"type":"Point"}
}