{
  "type": "Feature",
  "properties": {
    "addr:full":"28/30, Rue Verdi, 06000 Nice Picardie",
    "addr:housenumber":"28 / 30",
    "addr:postcode":"06000",
    "addr:street":"Rue Verdi",
    "iso:country":"FR",
    "sg:address":"28/30, Rue Verdi, 06000 Nice",
    "sg:orig_category":"Unclassifiable Establishments",
    "sg:phone":"+33 4 97 03 29 28",
    "sg:province":"Picardie",
    "wof:name":"Vani.pro. S.a.r.l. - Vanille Et Produits",
    "wof:placetype":"venue"
},
  "geometry": {"coordinates":[7.258762,43.699787],"type":"Point"}
}