{
  "type": "Feature",
  "properties": {
    "addr:full":"21 Av De Verdun Ccal Perrier 74100 Annemasse Rhone-Alpes 74100",
    "addr:housenumber":"ccal",
    "addr:postcode":"74100;74100",
    "addr:street":"21 Av De Verdun;Perrier",
    "iso:country":"FR",
    "sg:address":"21 Av De Verdun Ccal Perrier 74100 Annemasse",
    "sg:classifiers":[
        {
            "category":"Bakery",
            "type":"Food & Drink"
        }
    ],
    "sg:phone":"+33 4 50 37 34 02",
    "sg:postcode":"74100",
    "sg:province":"Rhone-Alpes",
    "sg:tags":[
        "cake",
        "product",
        "related",
        "bread"
    ],
    "wof:name":"Paniere D'annemasse",
    "wof:placetype":"venue"
},
  "geometry": {"coordinates":[6.23712,46.192455],"type":"Point"}
}