{
  "type": "Feature",
  "properties": {
    "addr:full":"10 pl Halles; Tours; 37000 Tours Centre 37000",
    "addr:housenumber":"10",
    "addr:postcode":"37000;37000",
    "addr:street":"Pl Halles",
    "iso:country":"FR",
    "sg:address":"10 pl Halles; Tours; 37000",
    "sg:city":"Tours",
    "sg:classifiers":[
        {
            "category":"Banks & Credit Unions",
            "subcategory":"Bank",
            "type":"Services"
        }
    ],
    "sg:phone":"+33 3347384444",
    "sg:postcode":"37000",
    "sg:province":"Centre",
    "wof:name":"Banque C.i.o.",
    "wof:placetype":"venue"
},
  "geometry": {"coordinates":[0.680183,47.392715],"type":"Point"}
}