{
  "type": "Feature",
  "properties": {
    "addr:full":"7 Bis Decres; Paris Pays de Loire",
    "addr:housenumber":"7 bis",
    "addr:street":"Decres Paris",
    "iso:country":"FR",
    "sg:address":"7 Bis",
    "sg:city":"Decres; Paris",
    "sg:classifiers":[
        {
            "category":"Travel",
            "subcategory":"Travel Agent",
            "type":"Entertainment"
        }
    ],
    "sg:province":"Pays de Loire",
    "wof:name":"En Plein Air",
    "wof:placetype":"venue"
},
  "geometry": {"coordinates":[2.315203,48.833012],"type":"Point"}
}