{
  "type": "Feature",
  "properties": {
    "addr:full":"4, Chemin Bourran - Ch\u00e2teau Smith Haut Lafitte , 33650 Martillac Martillac Aquitaine 33650",
    "addr:housenumber":"4",
    "addr:postcode":"33650;33650",
    "addr:street":"Chemin Bourran Cha\u0302Teau",
    "iso:country":"FR",
    "sg:address":"4, Chemin Bourran - Ch\u00e2teau Smith Haut Lafitte , 33650 Martillac",
    "sg:city":"Martillac",
    "sg:orig_category":"Unclassifiable Establishments",
    "sg:phone":"+33 5 57 83 11 22",
    "sg:postcode":"33650",
    "sg:province":"Aquitaine",
    "wof:name":"D. Cathiard S.a.r.l.",
    "wof:placetype":"venue"
},
  "geometry": {"coordinates":[-0.594689,44.569355],"type":"Point"}
}