{
  "type": "Feature",
  "properties": {
    "addr:full":"B.P. 60122, 44101 Nantes C\u00e9dex 04^^10, Rue Victor Schoelcher - ZI Chevir\u00e9, 44100 Nantes Pays de Loire",
    "addr:housenumber":"04;^ 10",
    "addr:postcode":"44101;44100",
    "addr:street":"^;Rue Victor Schoelcher Zi Chevire\u0301",
    "iso:country":"FR",
    "sg:address":"B.P. 60122, 44101 Nantes C\u00e9dex 04^^10, Rue Victor Schoelcher - ZI Chevir\u00e9, 44100 Nantes",
    "sg:orig_category":"Non-Classified Establishments",
    "sg:phone":"+33 2 51 70 61 00",
    "sg:province":"Pays de Loire",
    "wof:name":"Itecom S.a.",
    "wof:placetype":"venue"
},
  "geometry": {"coordinates":[-1.60436,47.211891],"type":"Point"}
}