{
  "type": "Feature",
  "properties": {
    "iso:country":"FR",
    "sg:address":"Zone Industrielle",
    "sg:city":"Moreuil",
    "sg:orig_category":"Unclassifiable Establishments",
    "sg:phone":"+33 3 22 09 71 14",
    "sg:postcode":"80110",
    "sg:province":"Picardie",
    "wof:name":"Seder S.a.r.l. - Etablissements Rigal",
    "wof:placetype":"venue"
},
  "geometry": {"coordinates":[2.485823,49.774715],"type":"Point"}
}