{
  "type": "Feature",
  "properties": {
    "iso:country":"FR",
    "sg:address":"91, Rte de Ch\u00e2teaurenault, 41000 Blois",
    "sg:city":"Blois",
    "sg:orig_category":"Unclassifiable Establishments",
    "sg:phone":"+33 2 54 50 60 70",
    "sg:postcode":"41000",
    "sg:province":"Centre",
    "wof:name":"Interra Team S.a.s.",
    "wof:placetype":"venue"
},
  "geometry": {"coordinates":[1.30462,47.582901],"type":"Point"}
}