{
  "type": "Feature",
  "properties": {
    "iso:country":"FR",
    "sg:address":"rte Savigny 21420 Aloxe Corton",
    "sg:city":"Aloxe-Corton",
    "sg:classifiers":[
        {
            "category":"Food Court",
            "type":"Food & Drink"
        }
    ],
    "sg:phone":"+33 3 80 25 00 00",
    "sg:postcode":"21420",
    "sg:province":"Bourgogne",
    "sg:tags":[
        "product",
        "related"
    ],
    "wof:name":"Reine Pedauque",
    "wof:placetype":"venue"
},
  "geometry": {"coordinates":[4.825039,47.060619],"type":"Point"}
}