{
  "type": "Feature",
  "properties": {
    "iso:country":"FR",
    "sg:address":"99 rue Albert Barbier 45160 Olivet",
    "sg:city":"Olivet",
    "sg:classifiers":[
        {
            "category":"Building & Trades",
            "subcategory":"Construction",
            "type":"Services"
        }
    ],
    "sg:phone":"+33 2 38 66 35 71",
    "sg:postcode":"45160",
    "sg:province":"Centre",
    "sg:tags":[
        "production",
        "work",
        "mass",
        "sawing"
    ],
    "wof:name":"Etablissements L. Cochain Sa",
    "wof:placetype":"venue"
},
  "geometry": {"coordinates":[1.902182,47.870476],"type":"Point"}
}