{
  "type": "Feature",
  "properties": {
    "addr:full":"B.P. 2, 38330 Montbonnot Saint Martin^^727, Rue Aristide Berg\u00e8s - ZAC de Pr\u00e9 Millet, 38330 Montbonno Rhone-Alpes 38330",
    "addr:housenumber":"2",
    "addr:postcode":"38330;38330;38330",
    "addr:street":"B.P.;Rue Aristide Berge\u0300S Zac De Pre\u0301 Millet;Rhone-Alpes",
    "iso:country":"FR",
    "sg:address":"B.P. 2, 38330 Montbonnot Saint Martin^^727, Rue Aristide Berg\u00e8s - ZAC de Pr\u00e9 Millet, 38330 Montbonno",
    "sg:orig_category":"Non-Classified Establishments",
    "sg:phone":"+33 4 76 52 28 28",
    "sg:postcode":"38330",
    "sg:province":"Rhone-Alpes",
    "wof:name":"Ellipse Industrie S.a.",
    "wof:placetype":"venue"
},
  "geometry": {"coordinates":[-89.038803,36.072281],"type":"Point"}
}