{
  "type": "Feature",
  "properties": {
    "iso:country":"FR",
    "sg:address":"B.P. 2, 38330 Montbonnot Saint Martin^^727, Rue Aristide Berg\u00e8s - ZAC de Pr\u00e9 Millet, 38330 Montbonno",
    "sg:orig_category":"Non-Classified Establishments",
    "sg:phone":"+33 4 76 52 28 28",
    "sg:postcode":"38330",
    "sg:province":"Rhone-Alpes",
    "wof:name":"Ellipse Industrie S.a.",
    "wof:placetype":"venue"
},
  "geometry": {"coordinates":[-89.038803,36.072281],"type":"Point"}
}