{
  "type": "Feature",
  "properties": {
    "addr:full":"3 Rue Du Parc 93150 Le Blanc Mesnil Ile de France",
    "addr:housenumber":"3",
    "addr:postcode":"93150",
    "addr:street":"Rue Du Parc",
    "iso:country":"FR",
    "sg:address":"3 Rue Du Parc 93150 Le Blanc Mesnil",
    "sg:classifiers":[
        {
            "category":"Manufacturing",
            "subcategory":"Printing",
            "type":"Manufacturing & Wholesale Goods"
        }
    ],
    "sg:phone":"+33 1 48 14 21 65",
    "sg:province":"Ile de France",
    "sg:tags":[
        "publishing"
    ],
    "wof:name":"Rotos De L'ile De France",
    "wof:placetype":"venue"
},
  "geometry": {"coordinates":[2.439322,48.937214],"type":"Point"}
}