{
  "type": "Feature",
  "properties": {
    "iso:country":"FR",
    "sg:address":"Za De Kerivan 56500 Naizin",
    "sg:city":"Naizin",
    "sg:classifiers":[
        {
            "category":"Food & Beverages",
            "subcategory":"Groceries & Convenience Stores",
            "type":"Retail Goods"
        }
    ],
    "sg:phone":"+33 2 97 27 43 15",
    "sg:postcode":"56500",
    "sg:province":"Bretagne",
    "sg:tags":[
        "product",
        "related"
    ],
    "wof:name":"Agro Maintenance Systeme (ams)",
    "wof:placetype":"venue"
},
  "geometry": {"coordinates":[-2.831069,47.98856],"type":"Point"}
}