{
  "type": "Feature",
  "properties": {
    "addr:full":"rue Albert Einstein 03100 MONTLUCON Montlu\u00e7on Auvergne 03100",
    "addr:postcode":"03100;03100",
    "addr:street":"Rue Albert Einstein",
    "iso:country":"FR",
    "sg:address":"rue Albert Einstein 03100 MONTLUCON",
    "sg:city":"Montlu\u00e7on",
    "sg:classifiers":[
        {
            "category":"Banks & Credit Unions",
            "subcategory":"Investment Brokerage",
            "type":"Services"
        }
    ],
    "sg:phone":"+33 4 70 06 20 90",
    "sg:postcode":"03100",
    "sg:province":"Auvergne",
    "sg:tags":[
        "casting"
    ],
    "wof:name":"Fonderie L'aluminium Moul\u00e9 Sa",
    "wof:placetype":"venue"
},
  "geometry": {"coordinates":[2.606335,46.349964],"type":"Point"}
}