{
  "type": "Feature",
  "properties": {
    "addr:full":"4, Av. de la Gare, 01100 Bellignat Rhone-Alpes",
    "addr:postcode":"01100",
    "addr:street":"Av. De La Gare",
    "iso:country":"FR",
    "sg:address":"4, Av. de la Gare, 01100 Bellignat",
    "sg:orig_category":"Unclassifiable Establishments",
    "sg:phone":"+33 4 74 73 48 35",
    "sg:province":"Rhone-Alpes",
    "wof:name":"Imprimerie Antoine S.a.r.l.",
    "wof:placetype":"venue"
},
  "geometry": {"coordinates":[5.628731,46.240555],"type":"Point"}
}