{
  "type": "Feature",
  "properties": {
    "addr:full":"1 Place Alexandre Morel 62400 B\u00e9thune Nord Pas-de-Calais 62400",
    "addr:housenumber":"1",
    "addr:postcode":"62400;62400",
    "addr:street":"Place Alexandre Morel",
    "iso:country":"FR",
    "sg:address":"1 Place Alexandre Morel 62400 B\u00e9thune",
    "sg:classifiers":[
        {
            "category":"Wholesale",
            "subcategory":"Medical Equipment & Supplies",
            "type":"Manufacturing & Wholesale Goods"
        }
    ],
    "sg:phone":"+33 3 21 68 12 13",
    "sg:postcode":"62400",
    "sg:province":"Nord Pas-de-Calais",
    "sg:tags":[
        "instrument",
        "health",
        "-",
        "precision"
    ],
    "wof:name":"Centre Medical De Prothese",
    "wof:placetype":"venue"
},
  "geometry": {"coordinates":[2.634979,50.528343],"type":"Point"}
}