{
  "type": "Feature",
  "properties": {
    "iso:country":"FR",
    "sg:address":"B.P. 8290, 95802 Cergy C\u00e9dex^^47, Av. des Genottes - B\u00e2t. le C\u00e9rame, 95000 Cergy",
    "sg:orig_category":"Non-Classified Establishments",
    "sg:phone":"+33 1 34 24 17 17",
    "sg:province":"Ile de France",
    "wof:name":"S\u00e9pal S.a.",
    "wof:placetype":"venue"
},
  "geometry": {"coordinates":[2.07982,49.035198],"type":"Point"}
}