{
  "type": "Feature",
  "properties": {
    "iso:country":"FR",
    "sg:address":"Rue Saint Leonard 53100 Mayenne",
    "sg:classifiers":[
        {
            "category":"Manufacturing",
            "subcategory":"Printing",
            "type":"Manufacturing & Wholesale Goods"
        }
    ],
    "sg:phone":"+33 1 44 76 54 40",
    "sg:province":"Pays de Loire",
    "sg:tags":[
        "publishing"
    ],
    "wof:name":"Jouve",
    "wof:placetype":"venue"
},
  "geometry": {"coordinates":[-0.615186,48.307762],"type":"Point"}
}