{
  "type": "Feature",
  "properties": {
    "addr:full":"24 Rue Montrosier 92200 Neuilly Sur Seine Ile de France 92200",
    "addr:housenumber":"24",
    "addr:postcode":"92200;92200",
    "addr:street":"Rue Montrosier",
    "iso:country":"FR",
    "sg:address":"24 Rue Montrosier 92200 Neuilly Sur Seine",
    "sg:classifiers":[
        {
            "category":"Professional",
            "subcategory":"Advertising",
            "type":"Services"
        }
    ],
    "sg:phone":"+33 1 41 43 07 07",
    "sg:postcode":"92200",
    "sg:province":"Ile de France",
    "sg:tags":[
        "information",
        "medium",
        "communication"
    ],
    "wof:name":"Sonacom",
    "wof:placetype":"venue"
},
  "geometry": {"coordinates":[2.279918,48.880875],"type":"Point"}
}