{
  "type": "Feature",
  "properties": {
    "addr:full":"Impasse des Arts Orval Centre 18200",
    "addr:postcode":"18200",
    "addr:street":"Impasse Des Arts",
    "iso:country":"FR",
    "sg:address":"Impasse des Arts",
    "sg:city":"Orval",
    "sg:orig_category":"Non-Classified Establishments",
    "sg:phone":"+33 2 48 61 54 70",
    "sg:postcode":"18200",
    "sg:province":"Centre",
    "wof:name":"Sofoc S.a.",
    "wof:placetype":"venue"
},
  "geometry": {"coordinates":[2.487324,46.72765],"type":"Point"}
}