{
  "type": "Feature",
  "properties": {
    "iso:country":"FR",
    "sg:address":"B.P. 38, 69741 Genas C\u00e9dex^^39, Rue Ambroise Par\u00e9 - ZI, 69740 Genas",
    "sg:orig_category":"Non-Classified Establishments",
    "sg:phone":"+33 4 72 47 40 00",
    "sg:province":"Rhone-Alpes",
    "wof:name":"T.r.j. S.a. - Transport Rapide Joyau",
    "wof:placetype":"venue"
},
  "geometry": {"coordinates":[5.000308,45.731804],"type":"Point"}
}