{
  "type": "Feature",
  "properties": {
    "iso:country":"FR",
    "sg:address":"350 rue Alfred Nobel 34935 Montpellier",
    "sg:classifiers":[
        {
            "category":"Banks & Credit Unions",
            "subcategory":"Investment Brokerage",
            "type":"Services"
        }
    ],
    "sg:phone":"+33 4 67 99 47 47",
    "sg:province":"Aquitaine",
    "sg:tags":[
        "ovens",
        "industrial",
        "heated",
        "gas",
        "oil-fired",
        "electrically",
        "furnace"
    ],
    "wof:name":"Qualiflow",
    "wof:placetype":"venue"
},
  "geometry": {"coordinates":[3.912016,43.613323],"type":"Point"}
}