{
  "type": "Feature",
  "properties": {
    "addr:full":"1 rue du Ronquet 50590 MONTMARTIN SUR MER Hauteville-sur-Mer Basse Normandie 50590",
    "addr:housenumber":"1",
    "addr:postcode":"50590;50590",
    "addr:street":"Rue Du Ronquet",
    "iso:country":"FR",
    "sg:address":"1 rue du Ronquet 50590 MONTMARTIN SUR MER",
    "sg:city":"Hauteville-sur-Mer",
    "sg:classifiers":[
        {
            "category":"Real Estate",
            "subcategory":"Real Estate Services",
            "type":"Services"
        }
    ],
    "sg:phone":"+33 2 33 76 79 79",
    "sg:postcode":"50590",
    "sg:province":"Basse Normandie",
    "sg:tags":[
        "crustacean",
        "shellfish"
    ],
    "wof:name":"Mar\u00e9e De La Baie Sarl",
    "wof:placetype":"venue"
},
  "geometry": {"coordinates":[-1.520804,48.997654],"type":"Point"}
}