{
  "type": "Feature",
  "properties": {
    "iso:country":"FR",
    "sg:address":"ZI la Garenne",
    "sg:city":"Villeneuve la Guyard",
    "sg:orig_category":"Unclassifiable Establishments",
    "sg:phone":"+33 3 86 66 40 04",
    "sg:postcode":"89340",
    "sg:province":"Bourgogne",
    "wof:name":"Entreprise Petit E.u.r.l.",
    "wof:placetype":"venue"
},
  "geometry": {"coordinates":[3.067805,48.339569],"type":"Point"}
}