{
  "type": "Feature",
  "properties": {
    "iso:country":"FR",
    "sg:address":"16, Av. L\u00e9on Boll\u00e9e, 75013 Paris",
    "sg:orig_category":"Unclassifiable Establishments",
    "sg:phone":"+33 1 45 85 72 37",
    "sg:province":"Ile de France",
    "wof:name":"R.l.d. S.a.r.l.",
    "wof:placetype":"venue"
},
  "geometry": {"coordinates":[2.363183,48.818398],"type":"Point"}
}