{
  "type": "Feature",
  "properties": {
    "iso:country":"FR",
    "sg:address":"12, Rue des Roses, 25200 Montb\u00e9liard",
    "sg:orig_category":"Unclassifiable Establishments",
    "sg:phone":"+33 3 81 91 25 28",
    "sg:province":"Franche Comt\u00e9",
    "wof:name":"Soci\u00e9t\u00e9 Nouvelle Greset Levage S.a.r.l.",
    "wof:placetype":"venue"
},
  "geometry": {"coordinates":[6.779126,47.510384],"type":"Point"}
}