{
  "type": "Feature",
  "properties": {
    "iso:country":"FR",
    "sg:address":"8 Pl Viat Berry 60810 Brasseuse",
    "sg:classifiers":[
        {
            "category":"Home & Garden",
            "subcategory":"Furniture",
            "type":"Retail Goods"
        }
    ],
    "sg:phone":"+33 3 44 54 72 79",
    "sg:province":"Picardie",
    "sg:tags":[
        "wood"
    ],
    "wof:name":"Atelier Du Bois D'ore",
    "wof:placetype":"venue"
},
  "geometry": {"coordinates":[2.680653,49.256493],"type":"Point"}
}