{
  "type": "Feature",
  "properties": {
    "addr:full":"Rue Ondaine 42500 Le Chambon Feugerolles Rhone-Alpes 42500",
    "addr:postcode":"42500;42500",
    "addr:street":"Rue Ondaine;Chambon Feugerolles Rhone-Alpes",
    "iso:country":"FR",
    "sg:address":"Rue Ondaine 42500 Le Chambon Feugerolles",
    "sg:classifiers":[
        {
            "category":"Shopping",
            "subcategory":"Crafts & Fabrics",
            "type":"Retail Goods"
        }
    ],
    "sg:phone":"+33 4 77 40 35 40",
    "sg:postcode":"42500",
    "sg:province":"Rhone-Alpes",
    "sg:tags":[
        "textile",
        "clothing"
    ],
    "wof:name":"Ets Parain Et Lepercke",
    "wof:placetype":"venue"
},
  "geometry": {"coordinates":[4.299319,45.395996],"type":"Point"}
}