{
  "type": "Feature",
  "properties": {
    "addr:full":"14 Rue Industrie 59157 Beauvois En Cambr\u00e9sis Nord Pas-de-Calais 59157",
    "addr:housenumber":"14",
    "addr:postcode":"59157;59157",
    "addr:street":"Rue Industrie;Pas-De-Calais",
    "iso:country":"FR",
    "sg:address":"14 Rue Industrie 59157 Beauvois En Cambr\u00e9sis",
    "sg:classifiers":[
        {
            "category":"Shopping",
            "subcategory":"Crafts & Fabrics",
            "type":"Retail Goods"
        }
    ],
    "sg:phone":"+33 3 27 76 09 09",
    "sg:postcode":"59157",
    "sg:province":"Nord Pas-de-Calais",
    "sg:tags":[
        "textile",
        "clothing"
    ],
    "wof:name":"Duflot Industrie Sa",
    "wof:placetype":"venue"
},
  "geometry": {"coordinates":[3.378151,50.137901],"type":"Point"}
}