{
  "type": "Feature",
  "properties": {
    "addr:full":"2 Rue Du Coll\u00e8ge 35412 St Malo Outre-Mer",
    "addr:housenumber":"2",
    "addr:postcode":"35412",
    "addr:street":"Rue Du Colle\u0300Ge",
    "iso:country":"FR",
    "sg:address":"2 Rue Du Coll\u00e8ge 35412 St Malo",
    "sg:classifiers":[
        {
            "category":"Professional",
            "subcategory":"Business Services",
            "type":"Services"
        }
    ],
    "sg:phone":"+33 2 99 40 74 74",
    "sg:province":"Outre-Mer",
    "sg:tags":[
        "training",
        "advice"
    ],
    "wof:name":"Ass Gestion Institut St Malo Providence",
    "wof:placetype":"venue"
},
  "geometry": {"coordinates":[0.521879,49.129879],"type":"Point"}
}