{
  "type": "Feature",
  "properties": {
    "iso:country":"FR",
    "sg:address":"B.P. 135, 72401 La Fert\u00e9 Bernard C\u00e9dex^^ZI le Joncheray, 72400 La Fert\u00e9 Bernard",
    "sg:orig_category":"Non-Classified Establishments",
    "sg:phone":"+33 2 43 93 07 77",
    "sg:province":"Pays de Loire",
    "wof:name":"Voyages Mauger S.a.r.l.",
    "wof:placetype":"venue"
},
  "geometry": {"coordinates":[0.563782,48.134613],"type":"Point"}
}