{
  "type": "Feature",
  "properties": {
    "addr:full":"B.P. 7, 67210 Obernai^^Rue du G\u00e9n\u00e9ral Leclerc - ZA, 67210 Obernai Obernai Alsace 67210",
    "addr:housenumber":"7",
    "addr:postcode":"67210;67210;67210",
    "addr:street":"B.P.;Ge\u0301Ne\u0301Ral Leclerc Za",
    "iso:country":"FR",
    "sg:address":"B.P. 7, 67210 Obernai^^Rue du G\u00e9n\u00e9ral Leclerc - ZA, 67210 Obernai",
    "sg:city":"Obernai",
    "sg:orig_category":"Non-Classified Establishments",
    "sg:phone":"+33 3 88 47 61 90",
    "sg:postcode":"67210",
    "sg:province":"Alsace",
    "wof:name":"Erhard Menuiserie Eb\u00e9nisterie S.a.",
    "wof:placetype":"venue"
},
  "geometry": {"coordinates":[7.485078,48.46225],"type":"Point"}
}