{
  "type": "Feature",
  "properties": {
    "addr:full":"25 avenue Maurice Chevalier 77330 Ozoir La Ferriere Ile de France",
    "addr:housenumber":"25",
    "addr:postcode":"77330",
    "addr:street":"Avenue Maurice Chevalier",
    "iso:country":"FR",
    "sg:address":"25 avenue Maurice Chevalier 77330 Ozoir La Ferriere",
    "sg:classifiers":[
        {
            "category":"Bars & Pubs",
            "subcategory":"Oxygen Bar",
            "type":"Food & Drink"
        }
    ],
    "sg:phone":"+33 1 60 18 55 40",
    "sg:province":"Ile de France",
    "sg:tags":[
        "soldering",
        "iron"
    ],
    "wof:name":"Cooper Tools Sa",
    "wof:placetype":"venue"
},
  "geometry": {"coordinates":[2.685182,48.767448],"type":"Point"}
}