{
  "type": "Feature",
  "properties": {
    "addr:full":"B.P. 63, 91542 Mennecy C\u00e9dex^^6, Rue de Champoreux, 91540 Mennecy Ile de France",
    "addr:postcode":"91542;91540",
    "addr:street":"B.P. 63;Rue De Champoreux",
    "iso:country":"FR",
    "sg:address":"B.P. 63, 91542 Mennecy C\u00e9dex^^6, Rue de Champoreux, 91540 Mennecy",
    "sg:orig_category":"Non-Classified Establishments",
    "sg:phone":"+33 1 69 90 60 00",
    "sg:province":"Ile de France",
    "wof:name":"Nouvel Automatisme Avenir Informatique S.a.",
    "wof:placetype":"venue"
},
  "geometry": {"coordinates":[2.434665,48.566704],"type":"Point"}
}