{
  "type": "Feature",
  "properties": {
    "addr:full":"41 Rue Lafayette 54320 Max\u00e9ville Lorraine 54320",
    "addr:housenumber":"41",
    "addr:postcode":"54320 maxe\u0301ville;54320",
    "addr:street":"Rue Lafayette",
    "iso:country":"FR",
    "sg:address":"41 Rue Lafayette 54320 Max\u00e9ville",
    "sg:classifiers":[
        {
            "category":"Building & Trades",
            "subcategory":"Electrical",
            "type":"Services"
        }
    ],
    "sg:phone":"+33 3 83 39 38 00",
    "sg:postcode":"54320",
    "sg:province":"Lorraine",
    "sg:tags":[
        "electronic",
        "lighting",
        "equipment"
    ],
    "wof:name":"Eclatec Sa",
    "wof:placetype":"venue"
},
  "geometry": {"coordinates":[6.171721,48.70826],"type":"Point"}
}