{
  "type": "Feature",
  "properties": {
    "iso:country":"FR",
    "sg:address":"56",
    "sg:city":"Nationale 60110 Esches",
    "sg:classifiers":[
        {
            "category":"Professional",
            "subcategory":"Engineering",
            "type":"Services"
        }
    ],
    "sg:phone":"+33 3 44 52 30 00",
    "sg:postcode":"60110",
    "sg:province":"Picardie",
    "sg:tags":[
        "machine",
        "-",
        "environment",
        "equipment",
        "machinery",
        "mechanical"
    ],
    "wof:name":"Cmdp",
    "wof:placetype":"venue"
},
  "geometry": {"coordinates":[2.166569,49.215942],"type":"Point"}
}