{
  "type": "Feature",
  "properties": {
    "iso:country":"FR",
    "sg:address":"6, Rue de l'Amiral Troude, 29200 Brest",
    "sg:city":"Brest",
    "sg:orig_category":"Non-Classified Establishments",
    "sg:phone":"+33 2 98 44 42 13",
    "sg:postcode":"29200",
    "sg:province":"Bretagne",
    "wof:name":"C.r.m. S.a. - Compagnie Radio Maritime",
    "wof:placetype":"venue"
},
  "geometry": {"coordinates":[-4.477128,48.38715],"type":"Point"}
}