{
  "type": "Feature",
  "properties": {
    "addr:full":"51 Rue Jacques Mugnier 68200 Mulhouse Mulhouse Alsace 68200",
    "addr:housenumber":"51",
    "addr:postcode":"68200;68200",
    "addr:street":"Rue Jacques Mugnier",
    "iso:country":"FR",
    "sg:address":"51 Rue Jacques Mugnier 68200 Mulhouse",
    "sg:city":"Mulhouse",
    "sg:classifiers":[
        {
            "category":"Shopping",
            "subcategory":"Computers & Home Electronics",
            "type":"Retail Goods"
        }
    ],
    "sg:phone":"+33 3 89 59 62 20",
    "sg:postcode":"68200",
    "sg:province":"Alsace",
    "sg:tags":[
        "electric",
        "electricity",
        "component",
        "equipment",
        "electrical",
        "electronic"
    ],
    "wof:name":"Stepper Energie France",
    "wof:placetype":"venue"
},
  "geometry": {"coordinates":[7.289908,47.729671],"type":"Point"}
}