{
  "type": "Feature",
  "properties": {
    "addr:full":"10, Rue Ir\u00e8ne Joliot Curie - ZA des Ruires, 38320 Eybens Rhone-Alpes 38320",
    "addr:housenumber":"10",
    "addr:postcode":"38320;38320",
    "addr:street":"Rue Ire\u0300Ne Joliot Curie Za Des Ruires",
    "iso:country":"FR",
    "sg:address":"10, Rue Ir\u00e8ne Joliot Curie - ZA des Ruires, 38320 Eybens",
    "sg:orig_category":"Unclassifiable Establishments",
    "sg:phone":"+33 4 76 14 04 46",
    "sg:postcode":"38320",
    "sg:province":"Rhone-Alpes",
    "wof:name":"Amc Rh\u00f4ne Alpes S.a.r.l.",
    "wof:placetype":"venue"
},
  "geometry": {"coordinates":[5.750275,45.147316],"type":"Point"}
}