{
  "type": "Feature",
  "properties": {
    "iso:country":"FR",
    "sg:address":"52, Rue Appoline - R\u00e9sidence la Roseli\u00e8re, 62280 Saint Martin Boulogne",
    "sg:orig_category":"Unclassifiable Establishments",
    "sg:phone":"+33 3 21 99 04 99",
    "sg:province":"Nord Pas-de-Calais",
    "wof:name":"Freshpack S.a.",
    "wof:placetype":"venue"
},
  "geometry": {"coordinates":[1.615569,50.706192],"type":"Point"}
}