{
  "type": "Feature",
  "properties": {
    "addr:full":"52, Rue Appoline - R\u00e9sidence la Roseli\u00e8re, 62280 Saint Martin Boulogne Nord Pas-de-Calais",
    "addr:housenumber":"52",
    "addr:postcode":"62280",
    "addr:street":"Rue Appoline Re\u0301Sidence La Roselie\u0300Re",
    "iso:country":"FR",
    "sg:address":"52, Rue Appoline - R\u00e9sidence la Roseli\u00e8re, 62280 Saint Martin Boulogne",
    "sg:orig_category":"Unclassifiable Establishments",
    "sg:phone":"+33 3 21 99 04 99",
    "sg:province":"Nord Pas-de-Calais",
    "wof:name":"Freshpack S.a.",
    "wof:placetype":"venue"
},
  "geometry": {"coordinates":[1.615569,50.706192],"type":"Point"}
}