{
  "type": "Feature",
  "properties": {
    "addr:full":"Zi Du Bois De Leuve BP 63 13551 St Martin De Crau Poitou-Charentes",
    "addr:housenumber":"63",
    "addr:postcode":"13551",
    "addr:street":"Zi Du Bois De Leuve Bp;Crau",
    "iso:country":"FR",
    "sg:address":"Zi Du Bois De Leuve BP 63 13551 St Martin De Crau",
    "sg:classifiers":[
        {
            "category":"Shopping",
            "type":"Retail Goods"
        }
    ],
    "sg:phone":"+33 4 90 47 06 37",
    "sg:province":"Poitou-Charentes",
    "sg:tags":[
        "metallurgy",
        "finished",
        "-",
        "metalworking",
        "metallic"
    ],
    "wof:name":"Secomoc",
    "wof:placetype":"venue"
},
  "geometry": {"coordinates":[4.81054,43.638241],"type":"Point"}
}