{
  "type": "Feature",
  "properties": {
    "addr:full":"43, Rue Aristide Briand, 92300 Levallois Perret Ile de France",
    "addr:housenumber":"43",
    "addr:postcode":"92300;ile",
    "addr:street":"Rue Aristide Briand",
    "iso:country":"FR",
    "sg:address":"43, Rue Aristide Briand, 92300 Levallois Perret",
    "sg:orig_category":"Unclassifiable Establishments",
    "sg:phone":"+33 1 49 64 47 00",
    "sg:province":"Ile de France",
    "wof:name":"Communication Et R\u00e9seaux S.a.r.l.",
    "wof:placetype":"venue"
},
  "geometry": {"coordinates":[2.284848,48.891071],"type":"Point"}
}