{
  "type": "Feature",
  "properties": {
    "addr:full":"Av. du Palais des Expositions Perpignan Languedoc-Roussillon 66000",
    "addr:postcode":"66000",
    "addr:street":"Av. Du Palais Des Expositions",
    "iso:country":"FR",
    "sg:address":"Av. du Palais des Expositions",
    "sg:city":"Perpignan",
    "sg:orig_category":"Unclassifiable Establishments",
    "sg:phone":"+33 4 68 52 94 94",
    "sg:postcode":"66000",
    "sg:province":"Languedoc-Roussillon",
    "wof:name":"R\u00e9gie Municipale Des Foires Et Salons",
    "wof:placetype":"venue"
},
  "geometry": {"coordinates":[2.898765,42.706501],"type":"Point"}
}