{
  "type": "Feature",
  "properties": {
    "iso:country":"FR",
    "sg:address":"84300 Les Vign\u00e8res",
    "sg:orig_category":"Unclassifiable Establishments",
    "sg:phone":"+33 4 90 78 67 67",
    "sg:province":"Poitou-Charentes",
    "wof:name":"Guedj Guy S.a.",
    "wof:placetype":"venue"
},
  "geometry": {"coordinates":[5.006315,43.881996],"type":"Point"}
}