{
  "type": "Feature",
  "properties": {
    "iso:country":"FR",
    "sg:address":"108 Vieille Rte De Rosporden 29000 Quimper",
    "sg:city":"Quimper",
    "sg:classifiers":[
        {
            "category":"Professional",
            "subcategory":"Engineering",
            "type":"Services"
        }
    ],
    "sg:phone":"+33 2 98 90 21 24",
    "sg:postcode":"29000",
    "sg:province":"Bretagne",
    "sg:tags":[
        "machine",
        "-",
        "mechanical"
    ],
    "wof:name":"Froid Guyader Sa",
    "wof:placetype":"venue"
},
  "geometry": {"coordinates":[-4.060462,47.987411],"type":"Point"}
}