{
  "type": "Feature",
  "properties": {
    "addr:full":"15, Chemin des Boeufs - ZAC des Bosquets, 95540 M\u00e9ry sur Oise Ile de France",
    "addr:housenumber":"15",
    "addr:postcode":"95540",
    "addr:street":"Chemin Des Boeufs Zac Des Bosquets",
    "iso:country":"FR",
    "sg:address":"15, Chemin des Boeufs - ZAC des Bosquets, 95540 M\u00e9ry sur Oise",
    "sg:orig_category":"Non-Classified Establishments",
    "sg:phone":"+33 1 34 64 89 89",
    "sg:province":"Ile de France",
    "wof:name":"G.t.c. S.a. - Groupement Technique De Construction",
    "wof:placetype":"venue"
},
  "geometry": {"coordinates":[2.185465,49.064209],"type":"Point"}
}