{
  "type": "Feature",
  "properties": {
    "addr:full":"41/43, Rue Constantin Pecqueur, 95150 Taverny Ile de France",
    "addr:housenumber":"41 / 43",
    "addr:postcode":"95150",
    "addr:street":"Rue Constantin Pecqueur",
    "iso:country":"FR",
    "sg:address":"41/43, Rue Constantin Pecqueur, 95150 Taverny",
    "sg:orig_category":"Unclassifiable Establishments",
    "sg:phone":"+33 1 39 95 23 66",
    "sg:province":"Ile de France",
    "wof:name":"A.s.t.e.m. S\u00e9curit\u00e9 S.a.r.l. - Assistance Techniquedes Syst\u00e8mes De S\u00e9curit\u00e9",
    "wof:placetype":"venue"
},
  "geometry": {"coordinates":[2.191837,49.026989],"type":"Point"}
}