{
  "type": "Feature",
  "properties": {
    "iso:country":"FR",
    "sg:address":"Rue G\u00e9rard Philippe 56600 Lanester",
    "sg:city":"Lanester",
    "sg:classifiers":[
        {
            "category":"Professional",
            "type":"Services"
        }
    ],
    "sg:phone":"+33 2 97 76 16 54",
    "sg:postcode":"56600",
    "sg:province":"Bretagne",
    "sg:tags":[
        "transport",
        "road"
    ],
    "wof:name":"Goulias Freres Sae",
    "wof:placetype":"venue"
},
  "geometry": {"coordinates":[-3.361089,47.76886],"type":"Point"}
}