{
  "type": "Feature",
  "properties": {
    "iso:country":"FR",
    "sg:address":"485 Av General Leclerc 59155 Faches Thumesnil",
    "sg:classifiers":[
        {
            "category":"Home & Garden",
            "subcategory":"Furniture",
            "type":"Retail Goods"
        }
    ],
    "sg:phone":"+33 3 20 96 34 10",
    "sg:postcode":"59155",
    "sg:province":"Nord Pas-de-Calais",
    "sg:tags":[
        "household",
        "wood"
    ],
    "wof:name":"Tousalon Sa",
    "wof:placetype":"venue"
},
  "geometry": {"coordinates":[3.087788,50.584869],"type":"Point"}
}