{
  "type": "Feature",
  "properties": {
    "addr:full":"Za La Montgervalaise 2 35520 La Meziere La M\u00e9zi\u00e8re Bretagne 35520",
    "addr:housenumber":"2",
    "addr:postcode":"35520;35520",
    "addr:street":"Za La Montgervalaise;Meziere La Me\u0301Zie\u0300Re Bretagne",
    "iso:country":"FR",
    "sg:address":"Za La Montgervalaise 2 35520 La Meziere",
    "sg:city":"La M\u00e9zi\u00e8re",
    "sg:classifiers":[
        {
            "category":"Shopping",
            "subcategory":"Bicycles & Sporting Goods",
            "type":"Retail Goods"
        }
    ],
    "sg:phone":"+33 2 99 66 40 06",
    "sg:postcode":"35520",
    "sg:province":"Bretagne",
    "sg:tags":[
        "product",
        "sport",
        "miscellaneous"
    ],
    "wof:name":"Sarl Polyform",
    "wof:placetype":"venue"
},
  "geometry": {"coordinates":[-1.734432,48.178051],"type":"Point"}
}