{
  "type": "Feature",
  "properties": {
    "addr:full":"19/21, Place Saint Jacques, 57000 Metz Lorraine",
    "addr:housenumber":"19 / 21",
    "addr:postcode":"57000",
    "addr:street":"Place Saint Jacques",
    "iso:country":"FR",
    "sg:address":"19/21, Place Saint Jacques, 57000 Metz",
    "sg:orig_category":"Unclassifiable Establishments",
    "sg:phone":"+33 3 87 37 75 75",
    "sg:province":"Lorraine",
    "wof:name":"Speedi Rychi Nyon S.a.r.l.",
    "wof:placetype":"venue"
},
  "geometry": {"coordinates":[6.17572,49.118542],"type":"Point"}
}