{
  "type": "Feature",
  "properties": {
    "addr:full":"25 Rue Georges Clemenceau 44150 Ancenis Pays de Loire",
    "addr:housenumber":"25",
    "addr:postcode":"44150",
    "addr:street":"Rue Georges Clemenceau",
    "iso:country":"FR",
    "sg:address":"25 Rue Georges Clemenceau 44150 Ancenis",
    "sg:classifiers":[
        {
            "category":"Professional",
            "subcategory":"Printing & Photocopies",
            "type":"Services"
        }
    ],
    "sg:phone":"+33 2 40 83 04 24",
    "sg:province":"Pays de Loire",
    "sg:tags":[
        "publishing"
    ],
    "wof:name":"Societe Independante De Presse Ancenis",
    "wof:placetype":"venue"
},
  "geometry": {"coordinates":[-1.178241,47.367569],"type":"Point"}
}