{
  "type": "Feature",
  "properties": {
    "iso:country":"FR",
    "sg:address":"La Bou\u00e8re 56200 La Gacilly",
    "sg:city":"La Gacilly",
    "sg:orig_category":"Unclassifiable Establishments",
    "sg:phone":"+33 2 99 08 11 51",
    "sg:postcode":"56200",
    "sg:province":"Bretagne",
    "wof:name":"Etablissements Desnos S.a.r.l.",
    "wof:placetype":"venue"
},
  "geometry": {"coordinates":[-2.128179,47.770393],"type":"Point"}
}