{
  "type": "Feature",
  "properties": {
    "addr:full":"131 Rue Du Bois 59200 Tourcoing Nord Pas-de-Calais 59200",
    "addr:housenumber":"131",
    "addr:postcode":"59200;59200",
    "addr:street":"Rue Du Bois",
    "iso:country":"FR",
    "sg:address":"131 Rue Du Bois 59200 Tourcoing",
    "sg:classifiers":[
        {
            "category":"Home & Garden",
            "subcategory":"Furniture",
            "type":"Retail Goods"
        }
    ],
    "sg:phone":"+33 3 20 28 01 70",
    "sg:postcode":"59200",
    "sg:province":"Nord Pas-de-Calais",
    "sg:tags":[
        "household",
        "wood"
    ],
    "wof:name":"Jacquart Et Fils (marcel) Sa",
    "wof:placetype":"venue"
},
  "geometry": {"coordinates":[3.142011,50.722591],"type":"Point"}
}