{
  "type": "Feature",
  "properties": {
    "iso:country":"FR",
    "sg:address":"Rue du Chapelier - Zone de fr\u00eat 4 - B\u00e2t 3404",
    "sg:city":"Roissy en France",
    "sg:orig_category":"Unclassifiable Establishments",
    "sg:phone":"+33 1 48 16 38 00",
    "sg:postcode":"95700",
    "sg:province":"Ile de France",
    "wof:name":"Daher Et Compagnie S.a.",
    "wof:placetype":"venue"
},
  "geometry": {"coordinates":[2.517005,49.003883],"type":"Point"}
}