{
  "type": "Feature",
  "properties": {
    "addr:full":"Bd de Paris Lillers Nord Pas-de-Calais 62190",
    "addr:postcode":"62190",
    "addr:street":"Bd De Paris Lillers Nord",
    "iso:country":"FR",
    "sg:address":"Bd de Paris",
    "sg:city":"Lillers",
    "sg:orig_category":"Unclassifiable Establishments",
    "sg:phone":"+33 3 21 61 76 76",
    "sg:postcode":"62190",
    "sg:province":"Nord Pas-de-Calais",
    "wof:name":"Philiomel S.a.",
    "wof:placetype":"venue"
},
  "geometry": {"coordinates":[2.479825,50.55983],"type":"Point"}
}