{
  "type": "Feature",
  "properties": {
    "iso:country":"FR",
    "sg:address":"380, Av. Blaise Pascal - ZI, 77550 Moissy Cramayel",
    "sg:orig_category":"Non-Classified Establishments",
    "sg:phone":"+33 1 64 88 94 94",
    "sg:province":"Ile de France",
    "wof:name":"Ohmtronic S.a.r.l.",
    "wof:placetype":"venue"
},
  "geometry": {"coordinates":[2.59017,48.627384],"type":"Point"}
}