{
  "type": "Feature",
  "properties": {
    "addr:full":"Za Les Loges 56420 Plumelec Plumelec Bretagne 56420",
    "addr:postcode":"56420;56420",
    "addr:street":"Za Les Loges",
    "iso:country":"FR",
    "sg:address":"Za Les Loges 56420 Plumelec",
    "sg:city":"Plumelec",
    "sg:classifiers":[
        {
            "category":"Shopping",
            "subcategory":"Crafts & Fabrics",
            "type":"Retail Goods"
        }
    ],
    "sg:phone":"+33 2 97 42 34 78",
    "sg:postcode":"56420",
    "sg:province":"Bretagne",
    "sg:tags":[
        "textile",
        "clothing"
    ],
    "wof:name":"Coax France",
    "wof:placetype":"venue"
},
  "geometry": {"coordinates":[-2.640169,47.83799],"type":"Point"}
}