{
  "type": "Feature",
  "properties": {
    "addr:full":"B.P. 85 Lambersart C\u00e9dex Nord-Pas-de-Calais 59831",
    "addr:postcode":"59831",
    "addr:street":"B.P. 85;Ce\u0301Dex",
    "iso:country":"FR",
    "sg:address":"B.P. 85",
    "sg:city":"Lambersart C\u00e9dex",
    "sg:orig_category":"Non-Classified Establishments",
    "sg:phone":"+33 3 28 38 77 38",
    "sg:postcode":"59831",
    "sg:province":"Nord-Pas-de-Calais",
    "wof:name":"Fid\u00e9ca S.a.",
    "wof:placetype":"venue"
},
  "geometry": {"coordinates":[3.02265,50.64785],"type":"Point"}
}