{
  "type": "Feature",
  "properties": {
    "iso:country":"FR",
    "sg:address":"19 Route Lacanau 33160 Salaunes",
    "sg:city":"Salaunes",
    "sg:classifiers":[
        {
            "category":"Manufacturing",
            "subcategory":"Aerospace",
            "type":"Manufacturing & Wholesale Goods"
        }
    ],
    "sg:phone":"+33 5 56 68 55 00",
    "sg:postcode":"33160",
    "sg:province":"Aquitaine",
    "sg:tags":[
        "equipment",
        "aeronautic",
        "transport",
        "vehicle"
    ],
    "wof:name":"Eads Composites Aquitaine Sa",
    "wof:placetype":"venue"
},
  "geometry": {"coordinates":[-0.825583,44.936947],"type":"Point"}
}