{
  "type": "Feature",
  "properties": {
    "iso:country":"FR",
    "sg:address":"33 Avenue Du Maine 75015 Paris",
    "sg:classifiers":[
        {
            "category":"Professional",
            "subcategory":"Printing & Photocopies",
            "type":"Services"
        }
    ],
    "sg:phone":"+33 1 56 54 12 34",
    "sg:province":"Ile de France",
    "sg:tags":[
        "publishing"
    ],
    "wof:name":"Beaux Arts Magasine Sa",
    "wof:placetype":"venue"
},
  "geometry": {"coordinates":[2.321233,48.842247],"type":"Point"}
}