{
  "type": "Feature",
  "properties": {
    "addr:full":"10, Quai Jean Mermoz, 78400 Chatou Ile de France",
    "addr:housenumber":"10",
    "addr:postcode":"78400",
    "addr:street":"Quai Jean Mermoz;Ile De France",
    "iso:country":"FR",
    "sg:address":"10, Quai Jean Mermoz, 78400 Chatou",
    "sg:orig_category":"Unclassifiable Establishments",
    "sg:phone":"+33 1 30 53 53 00",
    "sg:province":"Ile de France",
    "wof:name":"Terem France S.a.r.l.",
    "wof:placetype":"venue"
},
  "geometry": {"coordinates":[2.158333,48.886051],"type":"Point"}
}