{
  "type": "Feature",
  "properties": {
    "addr:full":"Lieu Dit Les Places 69490 Les Olmes Rhone-Alpes",
    "addr:postcode":"69490",
    "addr:street":"Lieu Dit Les Places;Olmes Rhone-Alpes",
    "iso:country":"FR",
    "sg:address":"Lieu Dit Les Places 69490 Les Olmes",
    "sg:classifiers":[
        {
            "category":"Manufacturing",
            "subcategory":"Printing",
            "type":"Manufacturing & Wholesale Goods"
        }
    ],
    "sg:phone":"+33 4 74 05 74 02",
    "sg:province":"Rhone-Alpes",
    "sg:tags":[
        "publishing"
    ],
    "wof:name":"Opmatis",
    "wof:placetype":"venue"
},
  "geometry": {"coordinates":[4.507927,45.837818],"type":"Point"}
}