{
  "type": "Feature",
  "properties": {
    "iso:country":"FR",
    "sg:address":"102, Av. Philippe Auguste, 75011 Paris",
    "sg:orig_category":"Non-Classified Establishments",
    "sg:phone":"+33 1 43 71 00 97",
    "sg:province":"Ile de France",
    "wof:name":"S.a.p.e.c. S.a. - Soci\u00e9t\u00e9 Audit Prestation Etude Contr\u00f4le",
    "wof:placetype":"venue"
},
  "geometry": {"coordinates":[2.391137,48.856434],"type":"Point"}
}