{
  "type": "Feature",
  "properties": {
    "iso:country":"FR",
    "sg:address":"12/14, Rue Jean Poulmarch, 95100 Argenteuil",
    "sg:orig_category":"Unclassifiable Establishments",
    "sg:phone":"+33 1 30 25 76 20",
    "sg:province":"Ile de France",
    "wof:name":"Seepex France S.a.r.l.",
    "wof:placetype":"venue"
},
  "geometry": {"coordinates":[2.211188,48.956322],"type":"Point"}
}