{
  "type": "Feature",
  "properties": {
    "addr:full":"9 pl Mar\u00e9chal Foch; Lesneven Picardie",
    "addr:housenumber":"9",
    "addr:street":"Pl Mare\u0301Chal Foch",
    "iso:country":"FR",
    "sg:address":"9 pl Mar\u00e9chal Foch; Lesneven",
    "sg:classifiers":[
        {
            "category":"Banks & Credit Unions",
            "subcategory":"Bank",
            "type":"Services"
        }
    ],
    "sg:phone":"+33 3398832280",
    "sg:province":"Picardie",
    "wof:name":"Cr\u00e9dit Lyonnais",
    "wof:placetype":"venue"
},
  "geometry": {"coordinates":[-4.323531,48.572788],"type":"Point"}
}