{
  "type": "Feature",
  "properties": {
    "addr:full":"Zi Claude Bernard 41800 Montoire Sur Le Loir Artins Centre 41800",
    "addr:postcode":"41800;41800",
    "addr:street":"Bernard",
    "iso:country":"FR",
    "sg:address":"Zi Claude Bernard 41800 Montoire Sur Le Loir",
    "sg:city":"Artins",
    "sg:classifiers":[
        {
            "category":"Utilities",
            "subcategory":"Electric",
            "type":"Services"
        }
    ],
    "sg:phone":"+33 2 54 86 50 50",
    "sg:postcode":"41800",
    "sg:province":"Centre",
    "sg:tags":[
        "electricity",
        "electronic",
        "electrical",
        "equipment"
    ],
    "wof:name":"Materligines Sa",
    "wof:placetype":"venue"
},
  "geometry": {"coordinates":[0.862425,47.752869],"type":"Point"}
}