{
  "type": "Feature",
  "properties": {
    "iso:country":"FR",
    "sg:address":"BP 117, 19 rue Romain Desfoss\u00e9es, 29802 Brest Cedex, Dept 29",
    "sg:classifiers":[
        {
            "category":"Banks & Credit Unions",
            "subcategory":"Bank",
            "type":"Services"
        }
    ],
    "sg:phone":"+33 2 98 34 68 80",
    "sg:province":"Bretagne",
    "wof:name":"Banque Commerciale Pour Le Marche De L'entreprise",
    "wof:placetype":"venue"
},
  "geometry": {"coordinates":[-4.48622,48.390228],"type":"Point"}
}