{
  "type": "Feature",
  "properties": {
    "addr:full":"1, Rue Blaise Pascal - Site Technologique Saint Jacques, 54320 Maxeville Lorraine",
    "addr:housenumber":"1",
    "addr:postcode":"54320",
    "addr:street":"Rue Blaise Pascal",
    "iso:country":"FR",
    "sg:address":"1, Rue Blaise Pascal - Site Technologique Saint Jacques, 54320 Maxeville",
    "sg:orig_category":"Non-Classified Establishments",
    "sg:phone":"+33 3 83 95 53 00",
    "sg:province":"Lorraine",
    "wof:name":"R.m.i. S.a. - R\u00e9alisation Micro-electronique Informatique",
    "wof:placetype":"venue"
},
  "geometry": {"coordinates":[6.16249,48.712032],"type":"Point"}
}