{
  "type": "Feature",
  "properties": {
    "iso:country":"FR",
    "sg:address":"B.P. 2, 62112 Corbehem^^Rue de Brebi\u00e8re, 62112 Corbehem",
    "sg:orig_category":"Non-Classified Establishments",
    "sg:phone":"+33 3 27 92 32 82",
    "sg:province":"Nord Pas-de-Calais",
    "wof:name":"Stora Enso Corbehem S.a.",
    "wof:placetype":"venue"
},
  "geometry": {"coordinates":[3.04996,50.335495],"type":"Point"}
}