{
  "type": "Feature",
  "properties": {
    "addr:full":"Rue de la Libert\u00e9 Pertuis Auvergne 84120",
    "addr:postcode":"84120",
    "addr:street":"Rue De La Liberte\u0301",
    "iso:country":"FR",
    "sg:address":"Rue de la Libert\u00e9",
    "sg:city":"Pertuis",
    "sg:orig_category":"Unclassifiable Establishments",
    "sg:phone":"+33 4 90 09 04 09",
    "sg:postcode":"84120",
    "sg:province":"Auvergne",
    "wof:name":"A.i.l. S.a.r.l. - Automatisme Industriel Du Lub\u00e9ron",
    "wof:placetype":"venue"
},
  "geometry": {"coordinates":[5.501485,43.688774],"type":"Point"}
}