{
  "type": "Feature",
  "properties": {
    "iso:country":"FR",
    "sg:address":"66, Rue de Bradford, 59200 Tourcoing",
    "sg:orig_category":"Unclassifiable Establishments",
    "sg:phone":"+33 3 20 68 95 70",
    "sg:province":"Nord Pas-de-Calais",
    "wof:name":"Farm\u00e9tal S.a.",
    "wof:placetype":"venue"
},
  "geometry": {"coordinates":[3.144634,50.715679],"type":"Point"}
}