{
  "type": "Feature",
  "properties": {
    "addr:full":"9bis rue Henri Martin; Paris; 92100 Ile de France 92100",
    "addr:housenumber":"9bis",
    "addr:postcode":"92100 ile;france 92100",
    "addr:street":"Rue Henri Martin",
    "iso:country":"FR",
    "sg:address":"9bis rue Henri Martin; Paris; 92100",
    "sg:classifiers":[
        {
            "category":"Banks & Credit Unions",
            "subcategory":"Bank",
            "type":"Services"
        }
    ],
    "sg:phone":"+33 1 46 94 82 70",
    "sg:postcode":"92100",
    "sg:province":"Ile de France",
    "wof:name":"Barclays Bank Plc",
    "wof:placetype":"venue"
},
  "geometry": {"coordinates":[2.251484,48.837456],"type":"Point"}
}