{
  "type": "Feature",
  "properties": {
    "addr:full":"10 Av De La Grande Arm\u00e9e 75017 Paris Ile de France 75017",
    "addr:postcode":"75017;75017",
    "addr:street":"10 Av De La Grande Arme\u0301E",
    "iso:country":"FR",
    "sg:address":"10 Av De La Grande Arm\u00e9e 75017 Paris",
    "sg:classifiers":[
        {
            "category":"Professional",
            "subcategory":"Advertising",
            "type":"Services"
        }
    ],
    "sg:phone":"+33 1 44 09 82 82",
    "sg:postcode":"75017",
    "sg:province":"Ile de France",
    "sg:tags":[
        "communication",
        "medium"
    ],
    "wof:name":"Grand Public Sarl",
    "wof:placetype":"venue"
},
  "geometry": {"coordinates":[2.292461,48.875038],"type":"Point"}
}