{
  "type": "Feature",
  "properties": {
    "addr:full":"23 ave Jean Jaur\u00e8s; Domont; 95330 Ile de France 95330",
    "addr:postcode":"95330 ile;france 95330",
    "addr:street":"23 Ave Jean Jaure\u0300S",
    "iso:country":"FR",
    "sg:address":"23 ave Jean Jaur\u00e8s; Domont; 95330",
    "sg:classifiers":[
        {
            "category":"Banks & Credit Unions",
            "subcategory":"Bank",
            "type":"Services"
        }
    ],
    "sg:phone":"+33 3339912247",
    "sg:postcode":"95330",
    "sg:province":"Ile de France",
    "wof:name":"Banque Nationale De Paris",
    "wof:placetype":"venue"
},
  "geometry": {"coordinates":[2.334332,49.030895],"type":"Point"}
}