{
  "type": "Feature",
  "properties": {
    "addr:full":"40 rue de Belfort 33000 Bordeaux Bordeaux Aquitaine 33000",
    "addr:housenumber":"40",
    "addr:postcode":"33000;33000",
    "addr:street":"Rue De Belfort",
    "iso:country":"FR",
    "sg:address":"40 rue de Belfort 33000 Bordeaux",
    "sg:city":"Bordeaux",
    "sg:classifiers":[
        {
            "category":"Food & Beverages",
            "subcategory":"Supermarket",
            "type":"Retail Goods"
        }
    ],
    "sg:phone":"+33 5 56 93 69 36",
    "sg:postcode":"33000",
    "sg:province":"Aquitaine",
    "sg:tags":[
        "cask",
        "wine"
    ],
    "wof:name":"Tonneleries De Coreze Sa",
    "wof:placetype":"venue"
},
  "geometry": {"coordinates":[-0.582096,44.835384],"type":"Point"}
}