{
  "type": "Feature",
  "properties": {
    "addr:full":"3274 Avenue Pierroton 33127 St Jean D'Illac Martignas-sur-Jalle Aquitaine 33127",
    "addr:housenumber":"3274;martignas-sur-jalle",
    "addr:postcode":"33127;33127",
    "addr:street":"Avenue Pierroton",
    "iso:country":"FR",
    "sg:address":"3274 Avenue Pierroton 33127 St Jean D'Illac",
    "sg:city":"Martignas-sur-Jalle",
    "sg:classifiers":[
        {
            "category":"Manufacturing",
            "subcategory":"Paper Products",
            "type":"Manufacturing & Wholesale Goods"
        }
    ],
    "sg:phone":"+33 5 57 97 99 00",
    "sg:postcode":"33127",
    "sg:province":"Aquitaine",
    "sg:tags":[
        "packaging",
        "material",
        "-",
        "cardboard"
    ],
    "wof:name":"Smurfit Lembacel Sa",
    "wof:placetype":"venue"
},
  "geometry": {"coordinates":[-0.780016,44.809513],"type":"Point"}
}