{
  "type": "Feature",
  "properties": {
    "iso:country":"FR",
    "sg:address":"Zac Des Grands Camps 46090 Mercu\u00e8s",
    "sg:classifiers":[
        {
            "category":"Banks & Credit Unions",
            "subcategory":"Investment Brokerage",
            "type":"Services"
        }
    ],
    "sg:phone":"+33 5 65 30 39 00",
    "sg:province":"Midi Pyr\u00e9n\u00e9es",
    "sg:tags":[
        "-",
        "transport",
        "related"
    ],
    "wof:name":"Quercy Messagerie Sarl",
    "wof:placetype":"venue"
},
  "geometry": {"coordinates":[1.38588,44.496483],"type":"Point"}
}