{
  "type": "Feature",
  "properties": {
    "addr:full":"Bourg 42540 Croizet sur Gand Rhone-Alpes 42540",
    "addr:postcode":"42540;42540",
    "addr:street":"Bourg;Rhone-Alpes",
    "iso:country":"FR",
    "sg:address":"Bourg 42540 Croizet sur Gand",
    "sg:classifiers":[
        {
            "category":"Shopping",
            "subcategory":"Crafts & Fabrics",
            "type":"Retail Goods"
        }
    ],
    "sg:phone":"+33 4 77 63 22 33",
    "sg:postcode":"42540",
    "sg:province":"Rhone-Alpes",
    "sg:tags":[
        "textile",
        "linen",
        "clothing"
    ],
    "wof:name":"Tissages Recorbet Et Fils (sa)",
    "wof:placetype":"venue"
},
  "geometry": {"coordinates":[4.241717,45.892799],"type":"Point"}
}