{
  "type": "Feature",
  "properties": {
    "iso:country":"FR",
    "sg:address":"22, All\u00e9e de la Verne, 84370 B\u00e9darrides",
    "sg:orig_category":"Non-Classified Establishments",
    "sg:phone":"+33 4 90 33 01 49",
    "sg:province":"Provence-Alpes-C\u00f4te d'Azur",
    "wof:name":"Mac'ani S.a.",
    "wof:placetype":"venue"
},
  "geometry": {"coordinates":[4.898942,44.04538],"type":"Point"}
}