{
  "type": "Feature",
  "properties": {
    "addr:full":"15, Av. Riquet, 11400 Castelnaudary Languedoc-Roussillon",
    "addr:postcode":"11400",
    "addr:street":"15 Av. Riquet",
    "iso:country":"FR",
    "sg:address":"15, Av. Riquet, 11400 Castelnaudary",
    "sg:orig_category":"Unclassifiable Establishments",
    "sg:phone":"+33 4 68 94 01 23",
    "sg:province":"Languedoc-Roussillon",
    "wof:name":"Servieu Houles S.a.r.l.",
    "wof:placetype":"venue"
},
  "geometry": {"coordinates":[1.953128,43.314152],"type":"Point"}
}