{
  "type": "Feature",
  "properties": {
    "iso:country":"FR",
    "sg:address":"La Combe 38300 Meyri\u00e9",
    "sg:orig_category":"Unclassifiable Establishments",
    "sg:phone":"+33 4 74 43 55 40",
    "sg:province":"Rhone-Alpes",
    "wof:name":"A.m.t.i. Altech S.a.r.l.",
    "wof:placetype":"venue"
},
  "geometry": {"coordinates":[5.280851,45.566784],"type":"Point"}
}