{
  "type": "Feature",
  "properties": {
    "iso:country":"FR",
    "sg:address":"Le Cottergt 38380 St Laurent Du Pont",
    "sg:classifiers":[
        {
            "category":"Wholesale",
            "subcategory":"Machinery & Supplies",
            "type":"Manufacturing & Wholesale Goods"
        }
    ],
    "sg:phone":"+33 4 76 55 21 12",
    "sg:postcode":"38380",
    "sg:province":"Rhone-Alpes",
    "sg:tags":[
        "handling",
        "material",
        "-",
        "machine",
        "equipment",
        "engineering",
        "mechanical"
    ],
    "wof:name":"Societe Des Etablissements Galofaro",
    "wof:placetype":"venue"
},
  "geometry": {"coordinates":[5.72527,45.387375],"type":"Point"}
}