{
  "type": "Feature",
  "properties": {
    "addr:full":"2 Rue Du Champ Blanc 42290 SORBIERS Rhone-Alpes 42290",
    "addr:housenumber":"2",
    "addr:postcode":"42290;42290",
    "addr:street":"Rue Du Champ Blanc;Rhone-Alpes",
    "iso:country":"FR",
    "sg:address":"2 Rue Du Champ Blanc 42290 SORBIERS",
    "sg:classifiers":[
        {
            "category":"Food & Beverages",
            "subcategory":"Chocolate",
            "type":"Retail Goods"
        }
    ],
    "sg:phone":"+33 4 77 53 35 39",
    "sg:postcode":"42290",
    "sg:province":"Rhone-Alpes",
    "wof:name":"Chocolaterie Aiguebelle Sarl",
    "wof:placetype":"venue"
},
  "geometry": {"coordinates":[4.448014,45.484367],"type":"Point"}
}