{
  "type": "Feature",
  "properties": {
    "addr:full":"3 Avenue D'Amazonie 91940 Les Ulis Ile de France",
    "addr:housenumber":"3",
    "addr:postcode":"91940",
    "addr:street":"Avenue D'Amazonie",
    "iso:country":"FR",
    "sg:address":"3 Avenue D'Amazonie 91940 Les Ulis",
    "sg:classifiers":[
        {
            "category":"Manufacturing",
            "subcategory":"Printing",
            "type":"Manufacturing & Wholesale Goods"
        }
    ],
    "sg:phone":"+33 1 60 92 23 23",
    "sg:province":"Ile de France",
    "sg:tags":[
        "publishing"
    ],
    "wof:name":"Ets Narboni Sa",
    "wof:placetype":"venue"
},
  "geometry": {"coordinates":[2.196337,48.681561],"type":"Point"}
}