{
  "type": "Feature",
  "properties": {
    "iso:country":"FR",
    "sg:address":"333, Rue du Doyen Georges Chapas, 69009 Lyon",
    "sg:orig_category":"Non-Classified Establishments",
    "sg:phone":"+33 4 78 66 89 80",
    "sg:postcode":"69009",
    "sg:province":"Rhone-Alpes",
    "wof:name":"Dalkia S.a.",
    "wof:placetype":"venue"
},
  "geometry": {"coordinates":[4.800264,45.790649],"type":"Point"}
}