{
  "type": "Feature",
  "properties": {
    "addr:full":"2 B Rue Gambetta 57000 Metz Lorraine 57000",
    "addr:housenumber":"2 b",
    "addr:postcode":"57000;57000",
    "addr:street":"Rue Gambetta",
    "iso:country":"FR",
    "sg:address":"2 B Rue Gambetta 57000 Metz",
    "sg:classifiers":[
        {
            "category":"Travel",
            "subcategory":"Hotels & Motels",
            "type":"Entertainment"
        }
    ],
    "sg:phone":"+33 3 87 55 94 95",
    "sg:postcode":"57000",
    "sg:province":"Lorraine",
    "sg:tags":[
        "hotels",
        "business",
        "restaurant"
    ],
    "wof:name":"Flo Tradition",
    "wof:placetype":"venue"
},
  "geometry": {"coordinates":[6.173305,49.111141],"type":"Point"}
}