{
  "type": "Feature",
  "properties": {
    "addr:full":"25 avenue Marc Sangnier 92390 Villeneuve la Garenne Ile de France 92390",
    "addr:housenumber":"25",
    "addr:postcode":"92390;92390",
    "addr:street":"Avenue Marc Sangnier;Ile;France",
    "iso:country":"FR",
    "sg:address":"25 avenue Marc Sangnier 92390 Villeneuve la Garenne",
    "sg:classifiers":[
        {
            "category":"Home & Garden",
            "subcategory":"Kitchen Supply",
            "type":"Retail Goods"
        }
    ],
    "sg:phone":"+33 1 41 21 41 01",
    "sg:postcode":"92390",
    "sg:province":"Ile de France",
    "sg:tags":[
        "utensil",
        "aluminium",
        "commercial"
    ],
    "wof:name":"Tiroi S.a.",
    "wof:placetype":"venue"
},
  "geometry": {"coordinates":[2.326498,48.928429],"type":"Point"}
}