{
  "type": "Feature",
  "properties": {
    "iso:country":"FR",
    "sg:address":"8",
    "sg:city":"13 27180 Parville",
    "sg:classifiers":[
        {
            "category":"Shopping",
            "subcategory":"Gifts & Souvenirs",
            "type":"Retail Goods"
        }
    ],
    "sg:phone":"+33 2 32 31 69 15",
    "sg:postcode":"27180",
    "sg:province":"Haute Normandie",
    "sg:tags":[
        "product",
        "miscellaneous"
    ],
    "wof:name":"Legabilleux Jean Paul",
    "wof:placetype":"venue"
},
  "geometry": {"coordinates":[1.087645,49.008076],"type":"Point"}
}