{
  "type": "Feature",
  "properties": {
    "addr:full":"Zone de Ch\u00e2teau Rouge M\u00e9sanger R\u00e9gion Pays de la Loire 44151",
    "addr:postcode":"44151",
    "addr:street":"De Cha\u0302Teau Rouge",
    "iso:country":"FR",
    "sg:address":"Zone de Ch\u00e2teau Rouge",
    "sg:city":"M\u00e9sanger",
    "sg:orig_category":"Unclassifiable Establishments",
    "sg:phone":"+33 2 40 96 11 09",
    "sg:postcode":"44151",
    "sg:province":"R\u00e9gion Pays de la Loire",
    "wof:name":"Mecan Outil S.a.",
    "wof:placetype":"venue"
},
  "geometry": {"coordinates":[-1.194484,47.41114],"type":"Point"}
}