{
  "type": "Feature",
  "properties": {
    "addr:full":"91 quai du Pr\u00e9sident Wilson 33130 BEGLES B\u00e8gles Aquitaine 33130",
    "addr:housenumber":"91",
    "addr:postcode":"33130;33130",
    "addr:street":"Quai Du Pre\u0301Sident Wilson",
    "iso:country":"FR",
    "sg:address":"91 quai du Pr\u00e9sident Wilson 33130 BEGLES",
    "sg:city":"B\u00e8gles",
    "sg:classifiers":[
        {
            "category":"Shopping",
            "subcategory":"Stationery & Office Supplies",
            "type":"Retail Goods"
        }
    ],
    "sg:phone":"+33 5 56 49 70 30",
    "sg:postcode":"33130",
    "sg:province":"Aquitaine",
    "wof:name":"Papeteries De Begles Sa",
    "wof:placetype":"venue"
},
  "geometry": {"coordinates":[-0.536445,44.815517],"type":"Point"}
}