{
  "type": "Feature",
  "properties": {
    "iso:country":"FR",
    "sg:address":"15 Rue Des Papetiers 27500 Pont Audemer",
    "sg:classifiers":[
        {
            "category":"Manufacturing",
            "subcategory":"Rubber & Plastics",
            "type":"Manufacturing & Wholesale Goods"
        }
    ],
    "sg:phone":"+33 2 32 56 79 10",
    "sg:province":"Haute Normandie",
    "wof:name":"Sacherie De Pont Audemer Sa",
    "wof:placetype":"venue"
},
  "geometry": {"coordinates":[0.507721,49.357586],"type":"Point"}
}