{
  "type": "Feature",
  "properties": {
    "addr:full":"Rte de Cambounet sur le Sor Soual Midi Pyr\u00e9n\u00e9es 81580",
    "addr:postcode":"81580",
    "addr:street":"Rte De Cambounet Sur Le Sor",
    "iso:country":"FR",
    "sg:address":"Rte de Cambounet sur le Sor",
    "sg:city":"Soual",
    "sg:orig_category":"Unclassifiable Establishments",
    "sg:phone":"+33 5 63 82 50 00",
    "sg:postcode":"81580",
    "sg:province":"Midi Pyr\u00e9n\u00e9es",
    "wof:name":"Pierre Fabre Dermo-cosm\u00e9tique S.a.",
    "wof:placetype":"venue"
},
  "geometry": {"coordinates":[2.145944,43.57],"type":"Point"}
}