{
  "type": "Feature",
  "properties": {
    "addr:full":"Rue des Jonni\u00e8res Bi\u00e8vres Ile de France 91570",
    "addr:postcode":"91570",
    "addr:street":"Rue Des Jonnie\u0300Res;Ile De France",
    "iso:country":"FR",
    "sg:address":"Rue des Jonni\u00e8res",
    "sg:city":"Bi\u00e8vres",
    "sg:orig_category":"Unclassifiable Establishments",
    "sg:phone":"+33 1 69 35 69 12",
    "sg:postcode":"91570",
    "sg:province":"Ile de France",
    "wof:name":"Steria S.a.",
    "wof:placetype":"venue"
},
  "geometry": {"coordinates":[2.215295,48.750504],"type":"Point"}
}