{
  "type": "Feature",
  "properties": {
    "iso:country":"FR",
    "sg:address":"5, Passage des Mauxins, 75009 Paris",
    "sg:orig_category":"Non-Classified Establishments",
    "sg:phone":"+33 1 42 49 01 96",
    "sg:postcode":"75009",
    "sg:province":"Ile de France",
    "wof:name":"Cortesi S.a.",
    "wof:placetype":"venue"
},
  "geometry": {"coordinates":[2.403915,48.877529],"type":"Point"}
}