{
  "type": "Feature",
  "properties": {
    "iso:country":"FR",
    "sg:address":"17, Rue Pasteur, 10230 Mailly le Camp",
    "sg:orig_category":"Unclassifiable Establishments",
    "sg:phone":"+33 3 25 37 30 27",
    "sg:province":"Champagne",
    "wof:name":"Fournier T.p. - Usine Charbonneau",
    "wof:placetype":"venue"
},
  "geometry": {"coordinates":[4.19151,48.667809],"type":"Point"}
}