{
  "type": "Feature",
  "properties": {
    "iso:country":"FR",
    "sg:address":"Chemin de la Forge",
    "sg:city":"Til Ch\u00e2tel",
    "sg:orig_category":"OUTILS \u00c0 MAIN POUR LE B\u00c2TIMENT ET LES TRAVAUX PUBLICS, LE JARDIN ET LA NEIGE GROSSISTE: BTP, JARDINS",
    "sg:phone":"+33 3 80 95 12 55",
    "sg:postcode":"21120",
    "sg:province":"Bourgogne",
    "wof:name":"Perrin S.a.",
    "wof:placetype":"venue"
},
  "geometry": {"coordinates":[5.178221,47.517941],"type":"Point"}
}