{
  "type": "Feature",
  "properties": {
    "addr:full":"5, Quai Solidor, 35400 Saint Malo Saint-Malo Bretagne 35400",
    "addr:housenumber":"5",
    "addr:postcode":"35400;35400",
    "addr:street":"Quai Solidor;Saint-Malo",
    "iso:country":"FR",
    "sg:address":"5, Quai Solidor, 35400 Saint Malo",
    "sg:city":"Saint-Malo",
    "sg:orig_category":"Unclassifiable Establishments",
    "sg:phone":"+33 2 99 81 58 52",
    "sg:postcode":"35400",
    "sg:province":"Bretagne",
    "wof:name":"Les Viviers Malouin S.a.r.l.",
    "wof:placetype":"venue"
},
  "geometry": {"coordinates":[-2.021749,48.634838],"type":"Point"}
}