{
  "type": "Feature",
  "properties": {
    "iso:country":"FR",
    "sg:address":"B.P. 642, 57146 Woippy C\u00e9dex^^1, Rue Saint Vincent, 57140 Woippy",
    "sg:orig_category":"Non-Classified Establishments",
    "sg:phone":"+33 3 87 51 24 24",
    "sg:province":"Lorraine",
    "wof:name":"Malezieux S.a.",
    "wof:placetype":"venue"
},
  "geometry": {"coordinates":[6.150305,49.15131],"type":"Point"}
}