{
  "type": "Feature",
  "properties": {
    "iso:country":"FR",
    "sg:address":"47, Rue Maurice Flandin, 69003 Lyon",
    "sg:orig_category":"Unclassifiable Establishments",
    "sg:phone":"+33 4 37 91 37 00",
    "sg:postcode":"69003",
    "sg:province":"Rhone-Alpes",
    "wof:name":"Kpnqwest Lyon S.a.",
    "wof:placetype":"venue"
},
  "geometry": {"coordinates":[4.862794,45.757648],"type":"Point"}
}