{
  "type": "Feature",
  "properties": {
    "addr:full":"125 Avenue Victor Hugo 75116 Paris Ile de France",
    "addr:housenumber":"125",
    "addr:postcode":"75116",
    "addr:street":"Avenue Victor Hugo",
    "iso:country":"FR",
    "sg:address":"125 Avenue Victor Hugo 75116 Paris",
    "sg:classifiers":[
        {
            "category":"Shopping",
            "subcategory":"Clothing, Apparel, & Fashions",
            "type":"Retail Goods"
        }
    ],
    "sg:phone":"+33 1 47 55 82 81",
    "sg:province":"Ile de France",
    "sg:tags":[
        "textile",
        "clothing",
        "clothes"
    ],
    "wof:name":"Promod",
    "wof:placetype":"venue"
},
  "geometry": {"coordinates":[2.282022,48.868103],"type":"Point"}
}