{
  "type": "Feature",
  "properties": {
    "iso:country":"FR",
    "sg:address":"ZA de Fontgrave",
    "sg:city":"Montboucher sur Jabron",
    "sg:orig_category":"Unclassifiable Establishments",
    "sg:phone":"+33 4 75 90 92 92",
    "sg:postcode":"26740",
    "sg:province":"Rhone-Alpes",
    "wof:name":"M.g.i. S.a. - Michel Girard Industrie",
    "wof:placetype":"venue"
},
  "geometry": {"coordinates":[4.80878,44.554249],"type":"Point"}
}