{
  "type": "Feature",
  "properties": {
    "addr:full":"1 place du Dix Huit Juin 1940 74940 Annecy le Vieux Rhone-Alpes 74940",
    "addr:housenumber":"1",
    "addr:postcode":"74940;74940",
    "addr:street":"Place Du Dix Huit Juin 1940",
    "iso:country":"FR",
    "sg:address":"1 place du Dix Huit Juin 1940 74940 Annecy le Vieux",
    "sg:classifiers":[
        {
            "category":"Communications",
            "subcategory":"Film & Video Production",
            "type":"Services"
        }
    ],
    "sg:phone":"+33 4 50 27 67 33",
    "sg:postcode":"74940",
    "sg:province":"Rhone-Alpes",
    "sg:tags":[
        "photography",
        "digital"
    ],
    "wof:name":"Goodshoot Sarl",
    "wof:placetype":"venue"
},
  "geometry": {"coordinates":[6.145695,45.915424],"type":"Point"}
}