{
  "type": "Feature",
  "properties": {
    "iso:country":"FR",
    "sg:address":"33330 Saint Emilion",
    "sg:city":"Saint-\u00c9tienne-de-Lisse",
    "sg:orig_category":"Unclassifiable Establishments",
    "sg:phone":"+33 5 57 24 70 53",
    "sg:postcode":"33330",
    "sg:province":"Aquitaine",
    "wof:name":"Ch\u00e2teau Cormey Figeac S.c.e.a.",
    "wof:placetype":"venue"
},
  "geometry": {"coordinates":[-0.155229,44.894924],"type":"Point"}
}