{
  "type": "Feature",
  "properties": {
    "addr:full":"B.P. 17, 63270 Vic le Comte^^ZA du Sauzet, 63270 Vic le Comte Buss\u00e9ol Auvergne 63270",
    "addr:postcode":"63270;63270;63270",
    "addr:street":"B.P. 17;Vic Le Comte Busse\u0301Ol",
    "iso:country":"FR",
    "sg:address":"B.P. 17, 63270 Vic le Comte^^ZA du Sauzet, 63270 Vic le Comte",
    "sg:city":"Buss\u00e9ol",
    "sg:orig_category":"Non-Classified Establishments",
    "sg:phone":"+33 4 73 69 16 76",
    "sg:postcode":"63270",
    "sg:province":"Auvergne",
    "wof:name":"Flockage Du Centre S.a.r.l.",
    "wof:placetype":"venue"
},
  "geometry": {"coordinates":[3.254808,45.613323],"type":"Point"}
}