{
  "type": "Feature",
  "properties": {
    "addr:full":"13, Rue des Hautes Rayes, 78700 Conflans Sainte Honorine Ile de France",
    "addr:housenumber":"13",
    "addr:postcode":"78700",
    "addr:street":"Rue Des Hautes Rayes",
    "iso:country":"FR",
    "sg:address":"13, Rue des Hautes Rayes, 78700 Conflans Sainte Honorine",
    "sg:orig_category":"Unclassifiable Establishments",
    "sg:phone":"+33 1 39 19 87 72",
    "sg:province":"Ile de France",
    "wof:name":"Agi-plan S.n.c.",
    "wof:placetype":"venue"
},
  "geometry": {"coordinates":[2.114335,48.99596],"type":"Point"}
}