{
  "type": "Feature",
  "properties": {
    "iso:country":"FR",
    "sg:address":"21 Rue Aristide Briand 69800 St Priest",
    "sg:classifiers":[
        {
            "category":"Manufacturing",
            "subcategory":"Printing",
            "type":"Manufacturing & Wholesale Goods"
        }
    ],
    "sg:phone":"+33 4 78 21 33 11",
    "sg:province":"Rhone-Alpes",
    "sg:tags":[
        "publishing"
    ],
    "wof:name":"V L D Sarl",
    "wof:placetype":"venue"
},
  "geometry": {"coordinates":[4.933651,45.691738],"type":"Point"}
}