{
  "type": "Feature",
  "properties": {
    "iso:country":"FR",
    "sg:address":"91 - 9, Av. Fran\u00e7ois Arago, 92017 Nanterre C\u00e9dex",
    "sg:orig_category":"Non-Classified Establishments",
    "sg:phone":"+33 1 47 29 47 29",
    "sg:province":"\u00cele-de-France",
    "wof:name":"Fininfo S.a.",
    "wof:placetype":"venue"
},
  "geometry": {"coordinates":[2.222812,48.900173],"type":"Point"}
}