{
  "type": "Feature",
  "properties": {
    "addr:full":"2000 Tuilerie Saint Pierre du Mont Aquitaine 40280",
    "addr:housenumber":"2000",
    "addr:postcode":"40280",
    "addr:street":"Tuilerie",
    "iso:country":"FR",
    "sg:address":"2000 Tuilerie",
    "sg:city":"Saint Pierre du Mont",
    "sg:orig_category":"Unclassifiable Establishments",
    "sg:phone":"+33 5 58 06 23 23",
    "sg:postcode":"40280",
    "sg:province":"Aquitaine",
    "wof:name":"Imp Industries S.a.",
    "wof:placetype":"venue"
},
  "geometry": {"coordinates":[-0.495774,43.867458],"type":"Point"}
}