{
  "type": "Feature",
  "properties": {
    "iso:country":"FR",
    "sg:address":"1, Rue du Bois de la Sivrite - Nancy Brabois , 54500 Vandoeuvre l\u00e8s Nancy",
    "sg:orig_category":"Non-Classified Establishments",
    "sg:phone":"+33 3 83 44 19 29",
    "sg:province":"Lorraine",
    "wof:name":"Novelect Lorraine",
    "wof:placetype":"venue"
},
  "geometry": {"coordinates":[6.172675,48.659737],"type":"Point"}
}