{
  "type": "Feature",
  "properties": {
    "addr:full":"82bis, Avenue Cl\u00e9menceau, 25000 Besan\u00e7on Franche Comt\u00e9",
    "addr:housenumber":"82bis",
    "addr:postcode":"25000",
    "addr:street":"Avenue Cle\u0301Menceau;Franche Comte\u0301",
    "iso:country":"FR",
    "sg:address":"82bis, Avenue Cl\u00e9menceau, 25000 Besan\u00e7on",
    "sg:orig_category":"Non-Classified Establishments",
    "sg:phone":"+33 3 81 52 81 21",
    "sg:province":"Franche Comt\u00e9",
    "wof:name":"T.f.c.i. - Thermique Franc Comtoise Installations S.a.",
    "wof:placetype":"venue"
},
  "geometry": {"coordinates":[6.002719,47.236984],"type":"Point"}
}