{
  "type": "Feature",
  "properties": {
    "addr:full":"10, R\u00e9sidence les Ch\u00eanes, 68120 Richwiller Richwiller Alsace 68120",
    "addr:housenumber":"10",
    "addr:postcode":"68120;68120",
    "addr:street":"Re\u0301Sidence Les Che\u0302Nes",
    "iso:country":"FR",
    "sg:address":"10, R\u00e9sidence les Ch\u00eanes, 68120 Richwiller",
    "sg:city":"Richwiller",
    "sg:orig_category":"Non-Classified Establishments",
    "sg:phone":"+33 3 89 50 27 79",
    "sg:postcode":"68120",
    "sg:province":"Alsace",
    "wof:name":"Sat\u00e9co S.a.",
    "wof:placetype":"venue"
},
  "geometry": {"coordinates":[7.26694,47.787621],"type":"Point"}
}