{
  "type": "Feature",
  "properties": {
    "iso:country":"FR",
    "sg:address":"B.P. 2479, 68057 Mulhouse^^13, Rue de Pfastatt, 68057 Mulhouse C\u00e9dex",
    "sg:orig_category":"Non-Classified Establishments",
    "sg:phone":"+33 3 89 32 44 44",
    "sg:province":"Languedoc-Roussillon",
    "wof:name":"D.m.c. S.a.",
    "wof:placetype":"venue"
},
  "geometry": {"coordinates":[7.33886,47.74659],"type":"Point"}
}