{
  "type": "Feature",
  "properties": {
    "addr:full":"Rue Du Bois Bouquin 37110 Ch\u00e2teau-Renault Ch\u00e2teau-Renault Centre 37110",
    "addr:housenumber":"cha\u0302teau-renault",
    "addr:postcode":"37110;37110",
    "addr:street":"Rue Du Bois Bouquin",
    "iso:country":"FR",
    "sg:address":"Rue Du Bois Bouquin 37110 Ch\u00e2teau-Renault",
    "sg:city":"Ch\u00e2teau-Renault",
    "sg:classifiers":[
        {
            "category":"Professional",
            "type":"Services"
        }
    ],
    "sg:phone":"+33 2 47 56 22 59",
    "sg:postcode":"37110",
    "sg:province":"Centre",
    "sg:tags":[
        "transport",
        "road"
    ],
    "wof:name":"Entretien Routier Du Centre Ouest (erco)",
    "wof:placetype":"venue"
},
  "geometry": {"coordinates":[0.895955,47.592129],"type":"Point"}
}