{
  "type": "Feature",
  "properties": {
    "iso:country":"FR",
    "sg:address":"1 Rue Eugene Dechelette 69550 Amplepuis",
    "sg:classifiers":[
        {
            "category":"Shopping",
            "subcategory":"Crafts & Fabrics",
            "type":"Retail Goods"
        }
    ],
    "sg:phone":"+33 4 74 89 44 45",
    "sg:province":"Rhone-Alpes",
    "sg:tags":[
        "textile",
        "clothing"
    ],
    "wof:name":"Danors Industries",
    "wof:placetype":"venue"
},
  "geometry": {"coordinates":[4.32283,45.978706],"type":"Point"}
}