{
  "type": "Feature",
  "properties": {
    "iso:country":"FR",
    "sg:address":"91, Av. Blaise Pascal - ZI la Garrigue, 34170 Castelnau Le Lez",
    "sg:orig_category":"Unclassifiable Establishments",
    "sg:phone":"+33 4 67 72 30 40",
    "sg:province":"Languedoc-Roussillon",
    "wof:name":"Parfor S.a.r.l.",
    "wof:placetype":"venue"
},
  "geometry": {"coordinates":[3.89542,43.633732],"type":"Point"}
}