{
  "type": "Feature",
  "properties": {
    "addr:full":"151 boulevard Danielle Casanova 13014 Marseille Poitou-Charentes",
    "addr:housenumber":"151",
    "addr:postcode":"13014",
    "addr:street":"Boulevard Danielle Casanova",
    "iso:country":"FR",
    "sg:address":"151 boulevard Danielle Casanova 13014 Marseille",
    "sg:classifiers":[
        {
            "category":"Professional",
            "type":"Services"
        }
    ],
    "sg:phone":"+33 4 91 10 16 00",
    "sg:province":"Poitou-Charentes",
    "sg:tags":[
        "transport"
    ],
    "wof:name":"Mory Egl S.a.",
    "wof:placetype":"venue"
},
  "geometry": {"coordinates":[5.374647,43.326775],"type":"Point"}
}