{
  "type": "Feature",
  "properties": {
    "addr:full":"Quartier Kirbon Trets Provence-Alpes-C\u00f4te d'Azur 13530",
    "addr:postcode":"13530",
    "addr:street":"Trets",
    "iso:country":"FR",
    "sg:address":"Quartier Kirbon",
    "sg:city":"Trets",
    "sg:orig_category":"Non-Classified Establishments",
    "sg:phone":"+33 4 42 61 35 15",
    "sg:postcode":"13530",
    "sg:province":"Provence-Alpes-C\u00f4te d'Azur",
    "wof:name":"S.n.c.e. S.a. - Soci\u00e9t\u00e9 Nouvelle Chemisage Entretien",
    "wof:placetype":"venue"
},
  "geometry": {"coordinates":[5.667275,43.41338],"type":"Point"}
}