{
  "type": "Feature",
  "properties": {
    "iso:country":"FR",
    "sg:address":"56 boulevard de la R\u00e9publique 92210 St Cloud",
    "sg:orig_category":"Fish, Frozen",
    "sg:phone":"+33 1 49 11 05 05",
    "sg:postcode":"92210",
    "sg:province":"Ile de France",
    "wof:name":"Eurotrade S.a.r.l.",
    "wof:placetype":"venue"
},
  "geometry": {"coordinates":[2.211471,48.844414],"type":"Point"}
}