{
  "type": "Feature",
  "properties": {
    "addr:full":"34, Rue Brueseau, 75013 Paris Ile de France",
    "addr:housenumber":"34",
    "addr:postcode":"75013",
    "addr:street":"Rue Brueseau",
    "iso:country":"FR",
    "sg:address":"34, Rue Brueseau, 75013 Paris",
    "sg:orig_category":"Unclassifiable Establishments",
    "sg:phone":"+33 1 44 23 20 50",
    "sg:province":"Ile de France",
    "wof:name":"Mondial Net S.a.r.l.",
    "wof:placetype":"venue"
},
  "geometry": {"coordinates":[2.355155,48.832119],"type":"Point"}
}