{
  "type": "Feature",
  "properties": {
    "addr:full":"Domaine De La Vente 61310 Silly En Gouffern Avernes-sous-Exmes Basse Normandie 61310",
    "addr:postcode":"61310;61310",
    "addr:street":"Vente;Basse",
    "iso:country":"FR",
    "sg:address":"Domaine De La Vente 61310 Silly En Gouffern",
    "sg:city":"Avernes-sous-Exmes",
    "sg:classifiers":[
        {
            "category":"Building & Trades",
            "subcategory":"Construction",
            "type":"Services"
        }
    ],
    "sg:phone":"+33 2 33 39 39 70",
    "sg:postcode":"61310",
    "sg:province":"Basse Normandie",
    "sg:tags":[
        "livestock",
        "business",
        "advice",
        "animal",
        "breeding",
        "agriculture"
    ],
    "wof:name":"Haseg",
    "wof:placetype":"venue"
},
  "geometry": {"coordinates":[0.107156,48.738037],"type":"Point"}
}