{
  "type": "Feature",
  "properties": {
    "addr:full":"45 rue Constantinople; Paris; 75008 Ile de France 75008",
    "addr:housenumber":"45",
    "addr:postcode":"75008 ile;france 75008",
    "addr:street":"Rue Constantinople",
    "iso:country":"FR",
    "sg:address":"45 rue Constantinople; Paris; 75008",
    "sg:classifiers":[
        {
            "category":"Banks & Credit Unions",
            "subcategory":"Bank",
            "type":"Services"
        }
    ],
    "sg:phone":"+33 1 45 22 16 56",
    "sg:postcode":"75008",
    "sg:province":"Ile de France",
    "wof:name":"Soci\u00e9t\u00e9 G\u00e9n\u00e9rale",
    "wof:placetype":"venue"
},
  "geometry": {"coordinates":[2.316975,48.881031],"type":"Point"}
}