{
  "type": "Feature",
  "properties": {
    "iso:country":"FR",
    "sg:address":"56 avenue Anatole France 10000 Troyes",
    "sg:classifiers":[
        {
            "category":"Manufacturing",
            "subcategory":"Tools & Machinery",
            "type":"Manufacturing & Wholesale Goods"
        }
    ],
    "sg:phone":"+33 3 25 82 13 89",
    "sg:postcode":"10000",
    "sg:province":"Champagne",
    "sg:tags":[
        "machine",
        "hosiery",
        "knitting",
        "accessory"
    ],
    "wof:name":"Platines Prunier S.a.",
    "wof:placetype":"venue"
},
  "geometry": {"coordinates":[4.070662,48.28233],"type":"Point"}
}