{
  "type": "Feature",
  "properties": {
    "addr:full":"Chemin des Dames Phalsbourg Lorraine 57370",
    "addr:postcode":"57370",
    "addr:street":"Chemin Des Dames Phalsbourg Lorraine",
    "iso:country":"FR",
    "sg:address":"Chemin des Dames",
    "sg:city":"Phalsbourg",
    "sg:orig_category":"Unclassifiable Establishments",
    "sg:phone":"+33 3 87 24 13 91",
    "sg:postcode":"57370",
    "sg:province":"Lorraine",
    "wof:name":"Depalor S.a.s.",
    "wof:placetype":"venue"
},
  "geometry": {"coordinates":[7.26925,48.767765],"type":"Point"}
}