{
  "type": "Feature",
  "properties": {
    "addr:full":"Rue de Verdun - Zone Industrielle Lillers Nord Pas-de-Calais 62190",
    "addr:postcode":"62190",
    "addr:street":"Rue De Verdun;Industrielle Lillers Nord",
    "iso:country":"FR",
    "sg:address":"Rue de Verdun - Zone Industrielle",
    "sg:city":"Lillers",
    "sg:orig_category":"Unclassifiable Establishments",
    "sg:phone":"+33 3 21 61 72 72",
    "sg:postcode":"62190",
    "sg:province":"Nord Pas-de-Calais",
    "wof:name":"Aff\u00fbtage De L'artois S.a.",
    "wof:placetype":"venue"
},
  "geometry": {"coordinates":[2.480824,50.563316],"type":"Point"}
}