{
  "type": "Feature",
  "properties": {
    "addr:full":"4 ter, Rue du Bouloi, 75001 Paris Ile de France",
    "addr:housenumber":"4 ter",
    "addr:postcode":"75001",
    "addr:street":"Rue Du Bouloi",
    "iso:country":"FR",
    "sg:address":"4 ter, Rue du Bouloi, 75001 Paris",
    "sg:orig_category":"Unclassifiable Establishments",
    "sg:phone":"+33 1 40 26 27 10",
    "sg:province":"Ile de France",
    "wof:name":"Journal Des Communes S.a.r.l.",
    "wof:placetype":"venue"
},
  "geometry": {"coordinates":[2.340317,48.863293],"type":"Point"}
}