{
  "type": "Feature",
  "properties": {
    "iso:country":"FR",
    "sg:address":"B.P. 18, 89470 Mon\u00e9teau^^ZI de la Plaine des Iles, 89470 Mon\u00e9teau",
    "sg:city":"Mon\u00e9teau",
    "sg:orig_category":"Non-Classified Establishments",
    "sg:phone":"+33 3 86 94 23 00",
    "sg:postcode":"89470",
    "sg:province":"Bourgogne",
    "wof:name":"Mm Packaging France - Cartonnages Gagnier S.a.",
    "wof:placetype":"venue"
},
  "geometry": {"coordinates":[3.578575,47.85006],"type":"Point"}
}