{
  "type": "Feature",
  "properties": {
    "addr:full":"183, Chemin des Rutys - ZI, 74370 Pringy Rhone-Alpes 74370",
    "addr:housenumber":"183",
    "addr:postcode":"74370;74370",
    "addr:street":"Chemin Des Rutys Zi",
    "iso:country":"FR",
    "sg:address":"183, Chemin des Rutys - ZI, 74370 Pringy",
    "sg:orig_category":"Non-Classified Establishments",
    "sg:phone":"+33 4 50 27 23 22",
    "sg:postcode":"74370",
    "sg:province":"Rhone-Alpes",
    "wof:name":"B.r.m. S.a.r.l. - Brunet R\u00e9alisations M\u00e9caniques",
    "wof:placetype":"venue"
},
  "geometry": {"coordinates":[6.109395,45.934166],"type":"Point"}
}