{
  "type": "Feature",
  "properties": {
    "iso:country":"FR",
    "sg:address":"Rte de Nantes - ZA de Beaupuy",
    "sg:city":"La Roche sur Yon",
    "sg:orig_category":"Unclassifiable Establishments",
    "sg:phone":"+33 2 51 05 31 25",
    "sg:postcode":"85000",
    "sg:province":"Pays de Loire",
    "wof:name":"Sovi Informatique S.a.",
    "wof:placetype":"venue"
},
  "geometry": {"coordinates":[-1.427199,46.67157],"type":"Point"}
}