{
  "type": "Feature",
  "properties": {
    "addr:full":"21 Rue De Villejames 44350 Gu\u00e9rande Pays de Loire",
    "addr:housenumber":"21",
    "addr:postcode":"44350",
    "addr:street":"Rue De Villejames",
    "iso:country":"FR",
    "sg:address":"21 Rue De Villejames 44350 Gu\u00e9rande",
    "sg:classifiers":[
        {
            "category":"Manufacturing",
            "subcategory":"Printing",
            "type":"Manufacturing & Wholesale Goods"
        }
    ],
    "sg:phone":"+33 2 40 15 60 80",
    "sg:province":"Pays de Loire",
    "sg:tags":[
        "publishing"
    ],
    "wof:name":"Westgraphy Sarl",
    "wof:placetype":"venue"
},
  "geometry": {"coordinates":[-2.410737,47.326523],"type":"Point"}
}