{
  "type": "Feature",
  "properties": {
    "iso:country":"FR",
    "sg:address":"41 R Leon Bourgeois 13001 Marseille",
    "sg:classifiers":[
        {
            "category":"Shopping",
            "subcategory":"Hobbies, Toys, & Games",
            "type":"Retail Goods"
        }
    ],
    "sg:phone":"+33 4 91 64 72 92",
    "sg:province":"Poitou-Charentes",
    "sg:tags":[
        "product",
        "miscellaneous",
        "entertainment"
    ],
    "wof:name":"M. Zaouche Didier Santons Didier",
    "wof:placetype":"venue"
},
  "geometry": {"coordinates":[5.392163,43.301956],"type":"Point"}
}