{
  "type": "Feature",
  "properties": {
    "iso:country":"FR",
    "sg:address":"6, Cours Gustave Nadaud, 42000 Saint Etienne",
    "sg:orig_category":"Non-Classified Establishments",
    "sg:phone":"+33 4 77 25 10 22",
    "sg:postcode":"42000",
    "sg:province":"Rhone-Alpes",
    "wof:name":"Acrotecna S.a.",
    "wof:placetype":"venue"
},
  "geometry": {"coordinates":[4.394347,45.435978],"type":"Point"}
}