{
  "type": "Feature",
  "properties": {
    "addr:full":"Rte de Metz Rombas Lorraine 57120",
    "addr:housenumber":"rombas",
    "addr:postcode":"57120",
    "addr:street":"Rte De Metz",
    "iso:country":"FR",
    "sg:address":"Rte de Metz",
    "sg:city":"Rombas",
    "sg:orig_category":"RECHARGEMENT, SOUDURE TIG, MIG, ARC SUBMERG\u00c9, FEUILLARDS, \u00c9LECTRODES ENROB\u00c9ES, ARCAIR, TRAITEMENT TH",
    "sg:phone":"+33 3 87 67 19 31",
    "sg:postcode":"57120",
    "sg:province":"Lorraine",
    "wof:name":"T.s.r.l. Poletti - Technique Soudure Rechargement Lorrain",
    "wof:placetype":"venue"
},
  "geometry": {"coordinates":[6.09932,49.255104],"type":"Point"}
}