{
  "type": "Feature",
  "properties": {
    "iso:country":"FR",
    "sg:address":"ZI de Morcourt",
    "sg:city":"Saint Quentin C\u00e9dex",
    "sg:orig_category":"Unclassifiable Establishments",
    "sg:phone":"+33 3 23 67 82 82",
    "sg:postcode":"02103",
    "sg:province":"Picardie",
    "wof:name":"Mory Team",
    "wof:placetype":"venue"
},
  "geometry": {"coordinates":[3.306302,49.862316],"type":"Point"}
}