{
  "type": "Feature",
  "properties": {
    "iso:country":"FR",
    "sg:address":"18 Rue Jules Vercruysse 95100 Argenteuil",
    "sg:classifiers":[
        {
            "category":"Professional",
            "subcategory":"Advertising",
            "type":"Services"
        }
    ],
    "sg:phone":"+33 1 34 11 74 74",
    "sg:postcode":"95100",
    "sg:province":"Ile de France",
    "sg:tags":[
        "communication",
        "medium"
    ],
    "wof:name":"Desserey",
    "wof:placetype":"venue"
},
  "geometry": {"coordinates":[2.210685,48.954681],"type":"Point"}
}