{
  "type": "Feature",
  "properties": {
    "iso:country":"FR",
    "sg:address":"Za Des Grouettes 91590 Cerny",
    "sg:classifiers":[
        {
            "category":"Utilities",
            "type":"Services"
        }
    ],
    "sg:phone":"+33 1 69 90 71 57",
    "sg:postcode":"91590",
    "sg:province":"Ile de France",
    "sg:tags":[
        "raw",
        "energy",
        "material"
    ],
    "wof:name":"Societe Des Eaux De Melun",
    "wof:placetype":"venue"
},
  "geometry": {"coordinates":[2.325852,48.472534],"type":"Point"}
}