{
  "type": "Feature",
  "properties": {
    "addr:full":"2, Rue du Peu, 41110 Ch\u00e2teauvieux Ch\u00e2teauvieux Centre 41110",
    "addr:housenumber":"2;cha\u0302teauvieux",
    "addr:postcode":"41110;41110",
    "addr:street":"Rue Du Peu",
    "iso:country":"FR",
    "sg:address":"2, Rue du Peu, 41110 Ch\u00e2teauvieux",
    "sg:city":"Ch\u00e2teauvieux",
    "sg:orig_category":"Non-Classified Establishments",
    "sg:phone":"+33 2 54 75 20 07",
    "sg:postcode":"41110",
    "sg:province":"Centre",
    "wof:name":"Malbran S.a.r.l.",
    "wof:placetype":"venue"
},
  "geometry": {"coordinates":[1.387455,47.229576],"type":"Point"}
}