{
  "type": "Feature",
  "properties": {
    "addr:full":"Zi Puy Nardon 85290 Mortagne Sur S\u00e8vres Pays de Loire 85290",
    "addr:postcode":"85290;85290",
    "addr:street":"Mortagne",
    "iso:country":"FR",
    "sg:address":"Zi Puy Nardon 85290 Mortagne Sur S\u00e8vres",
    "sg:classifiers":[
        {
            "category":"Shopping",
            "subcategory":"Computers & Home Electronics",
            "type":"Retail Goods"
        }
    ],
    "sg:phone":"+33 2 51 65 05 39",
    "sg:postcode":"85290",
    "sg:province":"Pays de Loire",
    "sg:tags":[
        "electric",
        "electricity",
        "component",
        "equipment",
        "electrical",
        "electronic"
    ],
    "wof:name":"Chadups Sas",
    "wof:placetype":"venue"
},
  "geometry": {"coordinates":[-111.393677,33.52631],"type":"Point"}
}