{
  "type": "Feature",
  "properties": {
    "iso:country":"FR",
    "sg:address":"route de Montceau 71390 Montagny Les Buxy",
    "sg:city":"Buxy",
    "sg:classifiers":[
        {
            "category":"Mining & Drilling",
            "type":"Manufacturing & Wholesale Goods"
        }
    ],
    "sg:phone":"+33 3 85 92 14 45",
    "sg:postcode":"71390",
    "sg:province":"Bourgogne",
    "sg:tags":[
        "quarry"
    ],
    "wof:name":"Lpb S.a.r.l.",
    "wof:placetype":"venue"
},
  "geometry": {"coordinates":[4.705024,46.6437],"type":"Point"}
}