{
  "type": "Feature",
  "properties": {
    "addr:full":"165 Rue De La Sucrerie 60190 Laneuvilleroy Picardie 60190",
    "addr:housenumber":"165",
    "addr:postcode":"60190;60190",
    "addr:street":"Rue De La Sucrerie;Picardie",
    "iso:country":"FR",
    "sg:address":"165 Rue De La Sucrerie 60190 Laneuvilleroy",
    "sg:classifiers":[
        {
            "category":"Manufacturing",
            "subcategory":"Metals",
            "type":"Manufacturing & Wholesale Goods"
        }
    ],
    "sg:phone":"+33 3 44 51 73 01",
    "sg:postcode":"60190",
    "sg:province":"Picardie",
    "sg:tags":[
        "metallurgy",
        "steel",
        "metalworking"
    ],
    "wof:name":"Jp Arbez Sa",
    "wof:placetype":"venue"
},
  "geometry": {"coordinates":[2.56554,49.490829],"type":"Point"}
}