{
  "type": "Feature",
  "properties": {
    "addr:full":"115 Boulevard De Magenta 75010 Paris Ile de France 75010",
    "addr:housenumber":"115",
    "addr:postcode":"75010;75010",
    "addr:street":"Boulevard De Magenta",
    "iso:country":"FR",
    "sg:address":"115 Boulevard De Magenta 75010 Paris",
    "sg:classifiers":[
        {
            "category":"Shopping",
            "subcategory":"Clothing, Apparel, & Fashions",
            "type":"Retail Goods"
        }
    ],
    "sg:phone":"+33 1 45 26 70 10",
    "sg:postcode":"75010",
    "sg:province":"Ile de France",
    "sg:tags":[
        "textile",
        "clothing",
        "clothes"
    ],
    "wof:name":"Le Vetement Similo",
    "wof:placetype":"venue"
},
  "geometry": {"coordinates":[2.352763,48.879704],"type":"Point"}
}