{
  "type": "Feature",
  "properties": {
    "iso:country":"FR",
    "sg:address":"B.P. 58, 68801 Thann C\u00e9dex^^7, Rue du G\u00e9n\u00e9ral de Gaulle, 68800 Thann",
    "sg:city":"Thann",
    "sg:orig_category":"Non-Classified Establishments",
    "sg:phone":"+33 3 89 37 04 00",
    "sg:postcode":"68800",
    "sg:province":"Alsace",
    "wof:name":"Jacob S.a.",
    "wof:placetype":"venue"
},
  "geometry": {"coordinates":[7.10335,47.810196],"type":"Point"}
}