{
  "type": "Feature",
  "properties": {
    "addr:full":"17 Rue L\u00e9onard De Vinci 92160 Antony Ile de France 92160",
    "addr:housenumber":"17",
    "addr:postcode":"92160;92160",
    "addr:street":"Rue Le\u0301Onard De Vinci",
    "iso:country":"FR",
    "sg:address":"17 Rue L\u00e9onard De Vinci 92160 Antony",
    "sg:classifiers":[
        {
            "category":"Manufacturing",
            "subcategory":"Metals",
            "type":"Manufacturing & Wholesale Goods"
        }
    ],
    "sg:phone":"+33 1 42 37 35 11",
    "sg:postcode":"92160",
    "sg:province":"Ile de France",
    "sg:tags":[
        "metallurgy",
        "metalworking",
        "processing"
    ],
    "wof:name":"Mecaproto Sarl",
    "wof:placetype":"venue"
},
  "geometry": {"coordinates":[2.315484,48.74081],"type":"Point"}
}