{
  "type": "Feature",
  "properties": {
    "iso:country":"FR",
    "sg:address":"23, Place Saint Charles, 45074 Orl\u00e9ans C\u00e9dex 2",
    "sg:city":"Orl\u00e9ans",
    "sg:orig_category":"Non-Classified Establishments",
    "sg:phone":"+33 2 38 25 01 01",
    "sg:postcode":"45000",
    "sg:province":"Centre",
    "wof:name":"Atos Origin. S.a.",
    "wof:placetype":"venue"
},
  "geometry": {"coordinates":[1.91398,47.893879],"type":"Point"}
}