{
  "type": "Feature",
  "properties": {
    "iso:country":"FR",
    "sg:address":"218, Rue de l'Eglise, 60400 Baboeuf",
    "sg:orig_category":"Non-Classified Establishments",
    "sg:phone":"+33 3 44 43 06 17",
    "sg:postcode":"60400",
    "sg:province":"Picardie",
    "wof:name":"Ateliers Du Froid De Picardie S.a.r.l.",
    "wof:placetype":"venue"
},
  "geometry": {"coordinates":[3.01626,49.598675],"type":"Point"}
}