{
  "type": "Feature",
  "properties": {
    "addr:full":"Ch\u00e2teau de Laubade 32110 Sorbets Midi Pyr\u00e9n\u00e9es",
    "addr:postcode":"32110",
    "iso:country":"FR",
    "sg:address":"Ch\u00e2teau de Laubade 32110 Sorbets",
    "sg:orig_category":"Unclassifiable Establishments",
    "sg:phone":"+33 5 62 09 06 02",
    "sg:province":"Midi Pyr\u00e9n\u00e9es",
    "wof:name":"L.e.d.a. S.a. - Laubade Et Domaines Associ\u00e9s",
    "wof:placetype":"venue"
},
  "geometry": {"coordinates":[-0.062689,43.71439],"type":"Point"}
}