{
  "type": "Feature",
  "properties": {
    "addr:full":"19, Rue Navier, 75017 Paris Ile de France",
    "addr:housenumber":"19",
    "addr:postcode":"75017",
    "addr:street":"Rue Navier",
    "iso:country":"FR",
    "sg:address":"19, Rue Navier, 75017 Paris",
    "sg:orig_category":"Unclassifiable Establishments",
    "sg:phone":"+33 1 46 27 30 00",
    "sg:province":"Ile de France",
    "wof:name":"Interface Etudes Conseil & Formation S.a.",
    "wof:placetype":"venue"
},
  "geometry": {"coordinates":[2.326283,48.895535],"type":"Point"}
}