{
  "type": "Feature",
  "properties": {
    "addr:full":"B.P. 50, 78142 V\u00e9lizy Villacoublay Cedex^^1, Rue du Petit Clamart, 78140 V\u00e9lizy Villacoublay Ile de France",
    "addr:postcode":"78142;78140",
    "addr:street":"B.P. 50;Rue Du Petit Clamart",
    "iso:country":"FR",
    "sg:address":"B.P. 50, 78142 V\u00e9lizy Villacoublay Cedex^^1, Rue du Petit Clamart, 78140 V\u00e9lizy Villacoublay",
    "sg:orig_category":"Non-Classified Establishments",
    "sg:phone":"+33 1 46 29 99 60",
    "sg:province":"Ile de France",
    "wof:name":"La Calh\u00e8ne S.a.",
    "wof:placetype":"venue"
},
  "geometry": {"coordinates":[2.18246,48.78503],"type":"Point"}
}