{
  "type": "Feature",
  "properties": {
    "iso:country":"FR",
    "sg:address":"65, Av de P\u00e9rigueux, 67800 Bischheim",
    "sg:city":"Bischheim",
    "sg:orig_category":"Non-Classified Establishments",
    "sg:phone":"+33 3 88 62 40 25",
    "sg:postcode":"67800",
    "sg:province":"Alsace",
    "wof:name":"V. Dia France S.a.r.l.",
    "wof:placetype":"venue"
},
  "geometry": {"coordinates":[7.740452,48.614601],"type":"Point"}
}