{
  "type": "Feature",
  "properties": {
    "iso:country":"FR",
    "sg:address":"La Montagne 26300 Barbi\u00e8res",
    "sg:orig_category":"Non-Classified Establishments",
    "sg:phone":"+33 4 75 47 33 96",
    "sg:postcode":"26300",
    "sg:province":"Rhone-Alpes",
    "wof:name":"S\u00e9r\u00e9fia S.a.r.l.",
    "wof:placetype":"venue"
},
  "geometry": {"coordinates":[5.09157,44.938511],"type":"Point"}
}