{
  "type": "Feature",
  "properties": {
    "iso:country":"FR",
    "sg:address":"B.P. 23, 71170 Chauffailles^^Rte de Charlieu, 71170 Chauffailles",
    "sg:city":"Chauffailles",
    "sg:orig_category":"Non-Classified Establishments",
    "sg:phone":"+33 3 85 26 52 60",
    "sg:postcode":"71170",
    "sg:province":"Bourgogne",
    "wof:name":"Aubonnet S.a.",
    "wof:placetype":"venue"
},
  "geometry": {"coordinates":[4.267355,46.168701],"type":"Point"}
}