{
  "type": "Feature",
  "properties": {
    "iso:country":"FR",
    "sg:address":"122, Av. de Lavaur, 31500 Toulouse",
    "sg:orig_category":"Non-Classified Establishments",
    "sg:phone":"+33 5 61 61 07 07",
    "sg:province":"Midi Pyr\u00e9n\u00e9es",
    "wof:name":"Man S.a.r.l.",
    "wof:placetype":"venue"
},
  "geometry": {"coordinates":[1.46518,43.621887],"type":"Point"}
}