{
  "type": "Feature",
  "properties": {
    "iso:country":"FR",
    "sg:address":"30, Rue des Carnets, 92140 Clamart",
    "sg:orig_category":"Unclassifiable Establishments",
    "sg:phone":"+33 1 46 01 01 01",
    "sg:province":"Ile de France",
    "wof:name":"Jund S.a.",
    "wof:placetype":"venue"
},
  "geometry": {"coordinates":[2.258955,48.78944],"type":"Point"}
}