{
  "type": "Feature",
  "properties": {
    "iso:country":"FR",
    "sg:address":"Av Pierre-Auguste Roiret Parc D'Activites Tourrais 69290 Craponne",
    "sg:classifiers":[
        {
            "category":"Manufacturing",
            "subcategory":"Printing",
            "type":"Manufacturing & Wholesale Goods"
        }
    ],
    "sg:phone":"+33 4 78 57 80 80",
    "sg:postcode":"69290",
    "sg:province":"Rhone-Alpes",
    "sg:tags":[
        "publishing"
    ],
    "wof:name":"Sallaz-grenier",
    "wof:placetype":"venue"
},
  "geometry": {"coordinates":[4.72283,45.747349],"type":"Point"}
}