{
  "type": "Feature",
  "properties": {
    "iso:country":"FR",
    "sg:address":"17 Rue S\u00e9journ\u00e9 94044 Cr\u00e9teil",
    "sg:classifiers":[
        {
            "category":"Shopping",
            "subcategory":"Stationery & Office Supplies",
            "type":"Retail Goods"
        }
    ],
    "sg:phone":"+33 1 43 39 68 38",
    "sg:province":"Pays de Loire",
    "sg:tags":[
        "information",
        "technology",
        "telecommunication",
        "equipment"
    ],
    "wof:name":"Danka France",
    "wof:placetype":"venue"
},
  "geometry": {"coordinates":[2.476097,48.766712],"type":"Point"}
}