{
  "type": "Feature",
  "properties": {
    "addr:full":"13, Rue de Faidherbe, 75011 Paris Ile de France",
    "addr:housenumber":"13",
    "addr:postcode":"75011",
    "addr:street":"Rue De Faidherbe",
    "iso:country":"FR",
    "sg:address":"13, Rue de Faidherbe, 75011 Paris",
    "sg:orig_category":"Non-Classified Establishments",
    "sg:phone":"+33 1 43 70 94 40",
    "sg:province":"Ile de France",
    "wof:name":"Novex S.a.",
    "wof:placetype":"venue"
},
  "geometry": {"coordinates":[2.383544,48.851562],"type":"Point"}
}