{
  "type": "Feature",
  "properties": {
    "addr:full":"20 Rue Du Bourbonnais 03150 Varennes Sur Allier Bouc\u00e9 Auvergne 03150",
    "addr:housenumber":"20",
    "addr:postcode":"03150;03150",
    "addr:street":"Rue Du Bourbonnais",
    "iso:country":"FR",
    "sg:address":"20 Rue Du Bourbonnais 03150 Varennes Sur Allier",
    "sg:city":"Bouc\u00e9",
    "sg:classifiers":[
        {
            "category":"Home & Garden",
            "subcategory":"Furniture",
            "type":"Retail Goods"
        }
    ],
    "sg:phone":"+33 4 70 45 78 68",
    "sg:postcode":"03150",
    "sg:province":"Auvergne",
    "sg:tags":[
        "household",
        "wood"
    ],
    "wof:name":"Moreux De Varennes Production",
    "wof:placetype":"venue"
},
  "geometry": {"coordinates":[3.393613,46.319572],"type":"Point"}
}