{
  "type": "Feature",
  "properties": {
    "addr:full":"2 R De La Vallonnerie 49340 Nuaill\u00e9 Pays de Loire",
    "addr:housenumber":"2",
    "addr:postcode":"49340",
    "addr:street":"R De La Vallonnerie",
    "iso:country":"FR",
    "sg:address":"2 R De La Vallonnerie 49340 Nuaill\u00e9",
    "sg:classifiers":[
        {
            "category":"Professional",
            "type":"Services"
        }
    ],
    "sg:phone":"+33 2 41 62 78 65",
    "sg:province":"Pays de Loire",
    "sg:tags":[
        "transport",
        "road"
    ],
    "wof:name":"Transports Supiot Louis Marie Sarl",
    "wof:placetype":"venue"
},
  "geometry": {"coordinates":[-0.791975,47.093414],"type":"Point"}
}