{
  "type": "Feature",
  "properties": {
    "addr:full":"24, Rue du 4 Septembre, 58600 Fourchambault Fourchambault Bourgogne 58600",
    "addr:housenumber":"24",
    "addr:postcode":"58600;58600",
    "addr:street":"Rue Du 4 Septembre",
    "iso:country":"FR",
    "sg:address":"24, Rue du 4 Septembre, 58600 Fourchambault",
    "sg:city":"Fourchambault",
    "sg:orig_category":"Unclassifiable Establishments",
    "sg:phone":"+33 3 86 90 91 70",
    "sg:postcode":"58600",
    "sg:province":"Bourgogne",
    "wof:name":"G\u00e9n\u00e9rale Collectivit\u00e9s S.a.",
    "wof:placetype":"venue"
},
  "geometry": {"coordinates":[3.084073,47.025333],"type":"Point"}
}