{
  "type": "Feature",
  "properties": {
    "addr:full":"1, Rue de Vieux Berquin, 59190 Hazebrouck Nord Pas-de-Calais 59190",
    "addr:housenumber":"1",
    "addr:postcode":"59190;59190",
    "addr:street":"Rue De Vieux Berquin",
    "iso:country":"FR",
    "sg:address":"1, Rue de Vieux Berquin, 59190 Hazebrouck",
    "sg:orig_category":"Non-Classified Establishments",
    "sg:phone":"+33 3 28 41 87 15",
    "sg:postcode":"59190",
    "sg:province":"Nord Pas-de-Calais",
    "wof:name":"Ateliers Des Flandres S.a.r.l.",
    "wof:placetype":"venue"
},
  "geometry": {"coordinates":[2.577592,50.701351],"type":"Point"}
}