{
  "type": "Feature",
  "properties": {
    "addr:full":"K\u00e9requel Ergu\u00e9 Armel Quimper Bretagne 29000",
    "addr:postcode":"29000",
    "iso:country":"FR",
    "sg:address":"K\u00e9requel Ergu\u00e9 Armel",
    "sg:city":"Quimper",
    "sg:orig_category":"Non-Classified Establishments",
    "sg:phone":"+33 2 98 90 38 53",
    "sg:postcode":"29000",
    "sg:province":"Bretagne",
    "wof:name":"Grandjouan Onys S.a.",
    "wof:placetype":"venue"
},
  "geometry": {"coordinates":[-4.074311,47.987316],"type":"Point"}
}