{
  "type": "Feature",
  "properties": {
    "iso:country":"FR",
    "sg:address":"Zac De Front Vert 3 84130 Le Pontet",
    "sg:city":"Le Pontet",
    "sg:classifiers":[
        {
            "category":"Building & Trades",
            "subcategory":"Electrical",
            "type":"Services"
        }
    ],
    "sg:phone":"+33 4 90 31 14 25",
    "sg:postcode":"73110",
    "sg:province":"Rhone-Alpes",
    "sg:tags":[
        "electronic",
        "lighting",
        "equipment"
    ],
    "wof:name":"Neon Imbert",
    "wof:placetype":"venue"
},
  "geometry": {"coordinates":[4.859935,43.96188],"type":"Point"}
}