{
  "type": "Feature",
  "properties": {
    "addr:full":"R Des Fr\u00e8res Lumi\u00e8re Sud 14126 Mondeville Cedex Alsace",
    "addr:postcode":"14126;cedex",
    "iso:country":"FR",
    "sg:address":"R Des Fr\u00e8res Lumi\u00e8re",
    "sg:city":"Sud 14126 Mondeville Cedex",
    "sg:classifiers":[
        {
            "category":"Autos & Motor Vehicles",
            "subcategory":"Automobile Sales",
            "type":"Retail Goods"
        }
    ],
    "sg:phone":"+33 2 31 83 36 35",
    "sg:province":"Alsace",
    "sg:tags":[
        "equipment",
        "motor-cars",
        "transport"
    ],
    "wof:name":"Bilia Sa",
    "wof:placetype":"venue"
},
  "geometry": {"coordinates":[-0.318344,49.178711],"type":"Point"}
}