{
  "type": "Feature",
  "properties": {
    "addr:full":"Zi La Croisi\u00e8re 84500 Boll\u00e8ne Centre",
    "addr:housenumber":"bolle\u0300ne",
    "addr:postcode":"84500",
    "addr:street":"Zi La Croisie\u0300Re",
    "iso:country":"FR",
    "sg:address":"Zi La Croisi\u00e8re 84500 Boll\u00e8ne",
    "sg:classifiers":[
        {
            "category":"Professional",
            "subcategory":"Engineering",
            "type":"Services"
        }
    ],
    "sg:phone":"+33 4 90 40 50 00",
    "sg:province":"Centre",
    "sg:tags":[
        "machine",
        "-",
        "environment",
        "equipment",
        "machinery",
        "mechanical"
    ],
    "wof:name":"Valoref Sa",
    "wof:placetype":"venue"
},
  "geometry": {"coordinates":[4.748432,44.282192],"type":"Point"}
}