{
  "type": "Feature",
  "properties": {
    "addr:full":"6, Parc des Fontenelles, 78870 Bailly Ile de France 78870",
    "addr:housenumber":"6",
    "addr:postcode":"78870;ile;78870",
    "addr:street":"Parc Des Fontenelles;France",
    "iso:country":"FR",
    "sg:address":"6, Parc des Fontenelles, 78870 Bailly",
    "sg:orig_category":"Non-Classified Establishments",
    "sg:phone":"+33 1 30 80 05 15",
    "sg:postcode":"78870",
    "sg:province":"Ile de France",
    "wof:name":"Acofec S.a.r.l.",
    "wof:placetype":"venue"
},
  "geometry": {"coordinates":[2.079645,48.839886],"type":"Point"}
}