{
  "type": "Feature",
  "properties": {
    "addr:full":"Rte De La Ch\u00e2taigneraie 85120 St Hilaire De Voust Pays de Loire 85120",
    "addr:postcode":"85120;85120",
    "addr:street":"Rte De La Cha\u0302Taigneraie;Voust",
    "iso:country":"FR",
    "sg:address":"Rte De La Ch\u00e2taigneraie 85120 St Hilaire De Voust",
    "sg:classifiers":[
        {
            "category":"Professional",
            "subcategory":"Engineering",
            "type":"Services"
        }
    ],
    "sg:phone":"+33 2 51 53 55 00",
    "sg:postcode":"85120",
    "sg:province":"Pays de Loire",
    "sg:tags":[
        "machine",
        "-",
        "mechanical"
    ],
    "wof:name":"Ets Jc Bouy Sa",
    "wof:placetype":"venue"
},
  "geometry": {"coordinates":[-0.771784,46.573956],"type":"Point"}
}