{
  "type": "Feature",
  "properties": {
    "addr:full":"rue Auguste Sutter 86100 Chatellerault Poitou-Charentes 86100",
    "addr:postcode":"86100;86100",
    "addr:street":"Rue Auguste Sutter",
    "iso:country":"FR",
    "sg:address":"rue Auguste Sutter 86100 Chatellerault",
    "sg:classifiers":[
        {
            "category":"Building & Trades",
            "subcategory":"Landfill",
            "type":"Services"
        }
    ],
    "sg:phone":"+33 5 49 21 09 59",
    "sg:postcode":"86100",
    "sg:province":"Poitou-Charentes",
    "sg:tags":[
        "leather",
        "industry",
        "leatherware"
    ],
    "wof:name":"A.r.c.o. Sa",
    "wof:placetype":"venue"
},
  "geometry": {"coordinates":[0.53882,46.825424],"type":"Point"}
}