{
  "type": "Feature",
  "properties": {
    "addr:full":"11, Rue Charles Robin, 01000 Bourg en Bresse Rhone-Alpes 01000",
    "addr:housenumber":"11",
    "addr:postcode":"01000;01000",
    "addr:street":"Rue Charles Robin;Rhone-Alpes",
    "iso:country":"FR",
    "sg:address":"11, Rue Charles Robin, 01000 Bourg en Bresse",
    "sg:orig_category":"Non-Classified Establishments",
    "sg:phone":"+33 4 74 22 17 90",
    "sg:postcode":"01000",
    "sg:province":"Rhone-Alpes",
    "wof:name":"Entreprise Millot",
    "wof:placetype":"venue"
},
  "geometry": {"coordinates":[5.229833,46.20575],"type":"Point"}
}