{
  "type": "Feature",
  "properties": {
    "addr:full":"B.P. 42100, 57052 Metz C\u00e9dex 2^^7, Rue Teilhard de Chardin, 57050 Metz Lorraine",
    "addr:housenumber":"2 ^ ^ 7",
    "addr:postcode":"57052;57050",
    "addr:street":"Ce\u0301Dex;Rue Teilhard De Chardin",
    "iso:country":"FR",
    "sg:address":"B.P. 42100, 57052 Metz C\u00e9dex 2^^7, Rue Teilhard de Chardin, 57050 Metz",
    "sg:orig_category":"Non-Classified Establishments",
    "sg:phone":"+33 3 87 30 53 53",
    "sg:province":"Lorraine",
    "wof:name":"Sermat S.a.",
    "wof:placetype":"venue"
},
  "geometry": {"coordinates":[6.1251,49.130074],"type":"Point"}
}