{
  "type": "Feature",
  "properties": {
    "addr:full":"B.P. 553, 53205 Az\u00e9 C\u00e9dex^^12, Av. Cassin - Z.I. de Bellitourne, 53200 Az\u00e9 Pays de Loire",
    "addr:housenumber":"b.p. 553",
    "addr:postcode":"53205;53200",
    "addr:street":"Av. Cassin",
    "iso:country":"FR",
    "sg:address":"B.P. 553, 53205 Az\u00e9 C\u00e9dex^^12, Av. Cassin - Z.I. de Bellitourne, 53200 Az\u00e9",
    "sg:orig_category":"Non-Classified Establishments",
    "sg:phone":"+33 2 43 07 15 85",
    "sg:province":"Pays de Loire",
    "wof:name":"Soci\u00e9t\u00e9 Nouvelle Jacquel S.a.r.l.",
    "wof:placetype":"venue"
},
  "geometry": {"coordinates":[-0.638464,47.749775],"type":"Point"}
}