{
  "type": "Feature",
  "properties": {
    "addr:full":"10, Rue Lacu\u00e9e, 75012 Paris Ile de France 75012",
    "addr:housenumber":"10",
    "addr:postcode":"75012;75012",
    "addr:street":"Rue Lacue\u0301E",
    "iso:country":"FR",
    "sg:address":"10, Rue Lacu\u00e9e, 75012 Paris",
    "sg:orig_category":"Non-Classified Establishments",
    "sg:phone":"+33 1 43 45 18 00",
    "sg:postcode":"75012",
    "sg:province":"Ile de France",
    "wof:name":"Architecture Studio Europe S.a.r.l.",
    "wof:placetype":"venue"
},
  "geometry": {"coordinates":[2.369426,48.849476],"type":"Point"}
}