{
  "type": "Feature",
  "properties": {
    "iso:country":"FR",
    "sg:address":"65 rue Pierre Brossolett; Ris Orangis; 91130",
    "sg:classifiers":[
        {
            "category":"Banks & Credit Unions",
            "subcategory":"Bank",
            "type":"Services"
        }
    ],
    "sg:phone":"+33 3369063929",
    "sg:postcode":"91130",
    "sg:province":"Ile de France",
    "wof:name":"Banque Nationale De Paris",
    "wof:placetype":"venue"
},
  "geometry": {"coordinates":[2.409337,48.649307],"type":"Point"}
}