{
  "type": "Feature",
  "properties": {
    "iso:country":"FR",
    "sg:address":"816, Av Poincar\u00e9, 88650 Anould",
    "sg:orig_category":"Unclassifiable Establishments",
    "sg:phone":"+33 3 29 57 11 22",
    "sg:province":"Lorraine",
    "wof:name":"Delot S.a.",
    "wof:placetype":"venue"
},
  "geometry": {"coordinates":[6.944818,48.206818],"type":"Point"}
}