{
  "type": "Feature",
  "properties": {
    "addr:full":"6, Chemin des 3 Villes - ZAE la Saule Madame, 77230 Thieux Ile de France",
    "addr:housenumber":"6",
    "addr:postcode":"77230;ile",
    "addr:street":"Chemin Des 3 Villes Zae La Saule Madame",
    "iso:country":"FR",
    "sg:address":"6, Chemin des 3 Villes - ZAE la Saule Madame, 77230 Thieux",
    "sg:orig_category":"Non-Classified Establishments",
    "sg:phone":"+33 1 60 26 07 26",
    "sg:province":"Ile de France",
    "wof:name":"Stella",
    "wof:placetype":"venue"
},
  "geometry": {"coordinates":[2.665693,49.009327],"type":"Point"}
}