{
  "type": "Feature",
  "properties": {
    "addr:full":"Rue du Saulnois - Parc de l'Observatoire - Immeuble Galil\u00e9e Laxou Lorraine 54523",
    "addr:postcode":"54523",
    "addr:street":"Rue Du Saulnois Parc De L'Observatoire",
    "iso:country":"FR",
    "sg:address":"Rue du Saulnois - Parc de l'Observatoire - Immeuble Galil\u00e9e",
    "sg:city":"Laxou",
    "sg:orig_category":"Unclassifiable Establishments",
    "sg:phone":"+33 3 83 96 65 65",
    "sg:postcode":"54523",
    "sg:province":"Lorraine",
    "wof:name":"Atse S.a.",
    "wof:placetype":"venue"
},
  "geometry": {"coordinates":[6.133258,48.691277],"type":"Point"}
}