{
  "type": "Feature",
  "properties": {
    "iso:country":"FR",
    "sg:address":"B.P. 133, 95505 Gognesse C\u00e9dex^^32, Rue de la Malmaison, 95500 Gonesse",
    "sg:orig_category":"Non-Classified Establishments",
    "sg:phone":"+33 1 39 87 39 87",
    "sg:province":"Ile de France",
    "wof:name":"I.v.g. Europe S.a. - Industrie V\u00e9nitienne Du Caoutchouc",
    "wof:placetype":"venue"
},
  "geometry": {"coordinates":[2.449633,48.986462],"type":"Point"}
}