{
  "type": "Feature",
  "properties": {
    "iso:country":"FR",
    "sg:address":"45 rue de l'Est 92100 Boulogne Billancourt",
    "sg:classifiers":[
        {
            "category":"Shopping",
            "subcategory":"Hobbies, Toys, & Games",
            "type":"Retail Goods"
        }
    ],
    "sg:phone":"+33 1 55 19 54 00",
    "sg:province":"Ile de France",
    "sg:tags":[
        "video"
    ],
    "wof:name":"Vox Diffusion Sarl",
    "wof:placetype":"venue"
},
  "geometry": {"coordinates":[2.244107,48.841747],"type":"Point"}
}