{
  "type": "Feature",
  "properties": {
    "addr:full":"15 quai Jules Guesde 94400 VITRY SUR SEINE Ile de France",
    "addr:housenumber":"15",
    "addr:postcode":"94400",
    "addr:street":"Quai Jules Guesde",
    "iso:country":"FR",
    "sg:address":"15 quai Jules Guesde 94400 VITRY SUR SEINE",
    "sg:orig_category":"Tools, Non-Sparking",
    "sg:phone":"+33 1 46 80 85 97",
    "sg:province":"Ile de France",
    "wof:name":"Andersen Chimie Sa",
    "wof:placetype":"venue"
},
  "geometry": {"coordinates":[2.41907,48.785652],"type":"Point"}
}