{
  "type": "Feature",
  "properties": {
    "addr:full":"Rte De Lyon 63370 Lempdes Lempdes Auvergne 63370",
    "addr:postcode":"63370;63370",
    "addr:street":"Rte De Lyon",
    "iso:country":"FR",
    "sg:address":"Rte De Lyon 63370 Lempdes",
    "sg:city":"Lempdes",
    "sg:classifiers":[
        {
            "category":"Building & Trades",
            "subcategory":"Construction",
            "type":"Services"
        }
    ],
    "sg:phone":"+33 4 73 83 08 55",
    "sg:postcode":"63370",
    "sg:province":"Auvergne",
    "sg:tags":[
        "work",
        "public"
    ],
    "wof:name":"Sacer Sud Est",
    "wof:placetype":"venue"
},
  "geometry": {"coordinates":[3.197355,45.768345],"type":"Point"}
}