{
  "type": "Feature",
  "properties": {
    "addr:full":"6 rue Alain Chartier; Bayeux; 14400 Bayeux Basse Normandie 14400",
    "addr:housenumber":"6",
    "addr:postcode":"14400;14400",
    "addr:street":"Rue Alain Chartier",
    "iso:country":"FR",
    "sg:address":"6 rue Alain Chartier; Bayeux; 14400",
    "sg:city":"Bayeux",
    "sg:classifiers":[
        {
            "category":"Banks & Credit Unions",
            "subcategory":"Bank",
            "type":"Services"
        }
    ],
    "sg:phone":"+33 2 31 21 37 30",
    "sg:postcode":"14400",
    "sg:province":"Basse Normandie",
    "wof:name":"Caisse Regionale De Cr\u00e9dit, Maritime Mutuel Du Finist\u00e8re",
    "wof:placetype":"venue"
},
  "geometry": {"coordinates":[-0.707326,49.278988],"type":"Point"}
}