{
  "type": "Feature",
  "properties": {
    "addr:full":"54, Av. de Nantes, 44116 Vieillevigne Pays de Loire",
    "addr:postcode":"44116",
    "addr:street":"54 Av. De Nantes",
    "iso:country":"FR",
    "sg:address":"54, Av. de Nantes, 44116 Vieillevigne",
    "sg:orig_category":"Unclassifiable Establishments",
    "sg:phone":"+33 2 40 26 57 44",
    "sg:province":"Pays de Loire",
    "wof:name":"Aria S.a.",
    "wof:placetype":"venue"
},
  "geometry": {"coordinates":[-1.439753,46.981155],"type":"Point"}
}