{
  "type": "Feature",
  "properties": {
    "iso:country":"FR",
    "sg:address":"5, Impasse des Tourmalines - Technoparc de l'Aubini\u00e8re, 44300 Nantes",
    "sg:orig_category":"Unclassifiable Establishments",
    "sg:phone":"+33 2 40 18 59 36",
    "sg:province":"Pays de Loire",
    "wof:name":"Apog\u00e9e Communications Nantes S.a.",
    "wof:placetype":"venue"
},
  "geometry": {"coordinates":[-1.495149,47.258614],"type":"Point"}
}