{
  "type": "Feature",
  "properties": {
    "addr:full":"2 rue Robert Keller 10150 PONT STE MARIE Champagne 10150",
    "addr:housenumber":"2",
    "addr:postcode":"10150;10150",
    "addr:street":"Rue Robert Keller;Ste Marie Champagne",
    "iso:country":"FR",
    "sg:address":"2 rue Robert Keller 10150 PONT STE MARIE",
    "sg:classifiers":[
        {
            "category":"Wholesale",
            "subcategory":"Electrical",
            "type":"Manufacturing & Wholesale Goods"
        }
    ],
    "sg:phone":"+33 3 25 76 45 00",
    "sg:postcode":"10150",
    "sg:province":"Champagne",
    "sg:tags":[
        "component"
    ],
    "wof:name":"C.q.e.",
    "wof:placetype":"venue"
},
  "geometry": {"coordinates":[4.108229,48.322769],"type":"Point"}
}