{
  "type": "Feature",
  "properties": {
    "addr:full":"5, Rue Jules Verne - ZAC du Caillou, 69630 Chaponost Rhone-Alpes",
    "addr:housenumber":"5",
    "addr:postcode":"69630",
    "addr:street":"Rue Jules Verne Zac Du Caillou",
    "iso:country":"FR",
    "sg:address":"5, Rue Jules Verne - ZAC du Caillou, 69630 Chaponost",
    "sg:orig_category":"Non-Classified Establishments",
    "sg:phone":"+33 4 78 56 79 90",
    "sg:province":"Rhone-Alpes",
    "wof:name":"I.b.f. S.a.r.l. - Imprimerie Bosc France",
    "wof:placetype":"venue"
},
  "geometry": {"coordinates":[4.74319,45.710232],"type":"Point"}
}