{
  "type": "Feature",
  "properties": {
    "iso:country":"FR",
    "sg:address":"RN 79 - Logis Neuf",
    "sg:city":"Confran\u00e7on",
    "sg:orig_category":"Unclassifiable Establishments",
    "sg:phone":"+33 4 74 25 24 54",
    "sg:postcode":"01310",
    "sg:province":"Rhone-Alpes",
    "wof:name":"G.m.t.c. S.a.r.l. - Gravo Marque Troph\u00e9es Et Groupes",
    "wof:placetype":"venue"
},
  "geometry": {"coordinates":[5.11893,46.232651],"type":"Point"}
}