{
  "type": "Feature",
  "properties": {
    "iso:country":"FR",
    "sg:address":"32 B Route De Montelimar 26110 Nyons",
    "sg:classifiers":[
        {
            "category":"Manufacturing",
            "subcategory":"Chemicals & Compounds",
            "type":"Manufacturing & Wholesale Goods"
        }
    ],
    "sg:phone":"+33 4 75 26 03 94",
    "sg:postcode":"26110",
    "sg:province":"Rhone-Alpes",
    "sg:tags":[
        "pharmaceutical",
        "chemistry",
        "-",
        "by-product"
    ],
    "wof:name":"Socrip",
    "wof:placetype":"venue"
},
  "geometry": {"coordinates":[5.13188,44.362312],"type":"Point"}
}