{
  "type": "Feature",
  "properties": {
    "iso:country":"FR",
    "sg:address":"116, Rue de Verdun, 92800 Puteaux",
    "sg:orig_category":"Unclassifiable Establishments",
    "sg:phone":"+33 1 46 14 80 00",
    "sg:province":"Ile de France",
    "wof:name":"Dalkia Facilities Management S.a.",
    "wof:placetype":"venue"
},
  "geometry": {"coordinates":[2.234445,48.877789],"type":"Point"}
}