{
  "type": "Feature",
  "properties": {
    "addr:full":"6, Rue des Artisans - ZI Sainte Agathe, 57190 Florange Lorraine",
    "addr:housenumber":"6",
    "addr:postcode":"zi;57190",
    "addr:street":"Rue Des Artisans;Agathe",
    "iso:country":"FR",
    "sg:address":"6, Rue des Artisans - ZI Sainte Agathe, 57190 Florange",
    "sg:orig_category":"Unclassifiable Establishments",
    "sg:phone":"+33 3 82 58 57 34",
    "sg:province":"Lorraine",
    "wof:name":"S.l.c.a. S.a. - Lorraine De Construction A\u00e9ronautique",
    "wof:placetype":"venue"
},
  "geometry": {"coordinates":[6.12272,49.327431],"type":"Point"}
}