{
  "type": "Feature",
  "properties": {
    "addr:full":"B.P. 1, 73540 La B\u00e2thie^^Usine d'Arbine, 73540 La B\u00e2thie Rhone-Alpes 73540",
    "addr:housenumber":"1",
    "addr:postcode":"73540;73540;73540",
    "addr:street":"B.P.;D'Arbine;Ba\u0302Thie Rhone-Alpes",
    "iso:country":"FR",
    "sg:address":"B.P. 1, 73540 La B\u00e2thie^^Usine d'Arbine, 73540 La B\u00e2thie",
    "sg:orig_category":"Non-Classified Establishments",
    "sg:phone":"+33 4 79 31 09 50",
    "sg:postcode":"73540",
    "sg:province":"Rhone-Alpes",
    "wof:name":"Pem Abrasifs R\u00e9fractaires S.a.",
    "wof:placetype":"venue"
},
  "geometry": {"coordinates":[6.45153,45.617149],"type":"Point"}
}