{
  "type": "Feature",
  "properties": {
    "iso:country":"FR",
    "sg:address":"2, Rue de Broglie - Synergie Park, 59260 Lezennes",
    "sg:orig_category":"Unclassifiable Establishments",
    "sg:phone":"+33 3 20 34 46 80",
    "sg:province":"Nord Pas-de-Calais",
    "wof:name":"Ren\u00e9 Bonte Ing\u00e9nierie S.a.r.l.",
    "wof:placetype":"venue"
},
  "geometry": {"coordinates":[3.11705,50.614567],"type":"Point"}
}