{
  "type": "Feature",
  "properties": {
    "iso:country":"FR",
    "sg:address":"6 Rue Joseph Cugnot 57200 Sarreguemines",
    "sg:classifiers":[
        {
            "category":"Manufacturing",
            "subcategory":"Wood Products",
            "type":"Manufacturing & Wholesale Goods"
        }
    ],
    "sg:phone":"+33 3 87 95 77 40",
    "sg:postcode":"57200",
    "sg:province":"Lorraine",
    "sg:tags":[
        "household",
        "-",
        "machine",
        "engineering",
        "mechanical",
        "furniture"
    ],
    "wof:name":"Schultz Equipements Sarreguemi Nes",
    "wof:placetype":"venue"
},
  "geometry": {"coordinates":[7.098602,49.108261],"type":"Point"}
}