{
  "type": "Feature",
  "properties": {
    "addr:full":"rue du Vert Bois 59960 Neuville en Ferrain Nord Pas-de-Calais 59960",
    "addr:postcode":"59960;59960",
    "addr:street":"Rue Du Vert Bois",
    "iso:country":"FR",
    "sg:address":"rue du Vert Bois 59960 Neuville en Ferrain",
    "sg:orig_category":"Metal Profile Bending Services",
    "sg:phone":"+33 3 20 28 15 80",
    "sg:postcode":"59960",
    "sg:province":"Nord Pas-de-Calais",
    "wof:name":"B.e.i.m.o. Sarl",
    "wof:placetype":"venue"
},
  "geometry": {"coordinates":[3.169745,50.754875],"type":"Point"}
}