{
  "type": "Feature",
  "properties": {
    "iso:country":"FR",
    "sg:address":"Rue Marechal Foch 64530 Pontacq",
    "sg:city":"Pontacq",
    "sg:classifiers":[
        {
            "category":"Shopping",
            "subcategory":"Luggage & Leather Goods",
            "type":"Retail Goods"
        }
    ],
    "sg:phone":"+33 5 59 53 79 00",
    "sg:postcode":"64530",
    "sg:province":"Aquitaine",
    "sg:tags":[
        "shoe"
    ],
    "wof:name":"Tonon Laburthe Manufacture De Chaussures-tannerie",
    "wof:placetype":"venue"
},
  "geometry": {"coordinates":[-0.109626,43.184105],"type":"Point"}
}