{
  "type": "Feature",
  "properties": {
    "iso:country":"FR",
    "sg:address":"21-35 Chem Du Prieur\u00e9 17024 La Rochelle Cedex 1",
    "sg:classifiers":[
        {
            "category":"Professional",
            "subcategory":"Business Services",
            "type":"Services"
        }
    ],
    "sg:phone":"+33 5 46 00 54 00",
    "sg:province":"Haute Normandie",
    "sg:tags":[
        "body",
        "advice"
    ],
    "wof:name":"Chambre De Commerce Et D Industrie",
    "wof:placetype":"venue"
},
  "geometry": {"coordinates":[-1.149023,46.172436],"type":"Point"}
}