{
  "type": "Feature",
  "properties": {
    "addr:full":"rue de la Gare 26210 EPINOUZE Rhone-Alpes 26210",
    "addr:postcode":"26210;26210",
    "addr:street":"Rue De La Gare;Rhone-Alpes",
    "iso:country":"FR",
    "sg:address":"rue de la Gare 26210 EPINOUZE",
    "sg:classifiers":[
        {
            "category":"Manufacturing",
            "subcategory":"Metals",
            "type":"Manufacturing & Wholesale Goods"
        }
    ],
    "sg:phone":"+33 4 75 31 38 00",
    "sg:postcode":"26210",
    "sg:province":"Rhone-Alpes",
    "sg:tags":[
        "tungsten",
        "carbide",
        "processing"
    ],
    "wof:name":"Sandvik Hard Materials Sa",
    "wof:placetype":"venue"
},
  "geometry": {"coordinates":[4.934375,45.303989],"type":"Point"}
}