{
  "type": "Feature",
  "properties": {
    "addr:full":"150, Rue du Moulin Neuf - ZA, 01570 Feillens Rhone-Alpes",
    "addr:housenumber":"150",
    "addr:postcode":"01570",
    "addr:street":"Rue Du Moulin Neuf Za",
    "iso:country":"FR",
    "sg:address":"150, Rue du Moulin Neuf - ZA, 01570 Feillens",
    "sg:orig_category":"Unclassifiable Establishments",
    "sg:phone":"+33 3 85 30 13 13",
    "sg:province":"Rhone-Alpes",
    "wof:name":"Boudon Favre S.a.",
    "wof:placetype":"venue"
},
  "geometry": {"coordinates":[4.8989,46.345421],"type":"Point"}
}