{
  "type": "Feature",
  "properties": {
    "iso:country":"FR",
    "sg:address":"236 Rue Du Puits Rond 45750 St Pryve St Mesmin",
    "sg:city":"Saint-Pryv\u00e9-Saint-Mesmin",
    "sg:classifiers":[
        {
            "category":"Building & Trades",
            "subcategory":"Construction",
            "type":"Services"
        }
    ],
    "sg:phone":"+33 2 38 66 02 25",
    "sg:postcode":"45750",
    "sg:province":"Centre",
    "sg:tags":[
        "work",
        "public"
    ],
    "wof:name":"Calloux Sa",
    "wof:placetype":"venue"
},
  "geometry": {"coordinates":[-81.423851,39.438179],"type":"Point"}
}