{
  "type": "Feature",
  "properties": {
    "iso:country":"FR",
    "sg:address":"B.P. 49, 71601 Paray le Monial C\u00e9dex^^ZA du Champ Bossu, 71600 Paray le Monial",
    "sg:city":"Varenne-Saint-Germain",
    "sg:orig_category":"Non-Classified Establishments",
    "sg:phone":"+33 3 85 81 95 95",
    "sg:postcode":"71600",
    "sg:province":"Bourgogne",
    "wof:name":"Audio Vid\u00e9o M\u00e9dia S.a.r.l.",
    "wof:placetype":"venue"
},
  "geometry": {"coordinates":[4.127668,46.384384],"type":"Point"}
}