{
  "type": "Feature",
  "properties": {
    "iso:country":"FR",
    "sg:address":"2 Route De Larnage 26600 Tain L Hermitage",
    "sg:classifiers":[
        {
            "category":"Manufacturing",
            "subcategory":"Building Materials",
            "type":"Manufacturing & Wholesale Goods"
        }
    ],
    "sg:phone":"+33 4 75 08 20 76",
    "sg:postcode":"26600",
    "sg:province":"Rhone-Alpes",
    "sg:tags":[
        "glass",
        "ceramic"
    ],
    "wof:name":"Fayol Sa",
    "wof:placetype":"venue"
},
  "geometry": {"coordinates":[4.843445,45.070873],"type":"Point"}
}