{
  "type": "Feature",
  "properties": {
    "iso:country":"FR",
    "sg:address":"B.P. 88, 01220 Divonne les Bains^^ZA Le Cr\u00eat d'Eau, 01220 Divonne les Bains",
    "sg:orig_category":"Non-Classified Establishments",
    "sg:phone":"+33 4 50 20 01 04",
    "sg:postcode":"01220",
    "sg:province":"Rhone-Alpes",
    "wof:name":"Alimentation G\u00e9n\u00e9rale Divonnaise S.a.s.",
    "wof:placetype":"venue"
},
  "geometry": {"coordinates":[6.146092,46.345795],"type":"Point"}
}