{
  "type": "Feature",
  "properties": {
    "iso:country":"FR",
    "sg:address":"26 rue des Solets 94150 Rungis",
    "sg:classifiers":[
        {
            "category":"Airport",
            "subcategory":"General Aviation",
            "type":"Transportation"
        }
    ],
    "sg:phone":"+33 1 45 12 84 84",
    "sg:postcode":"94150",
    "sg:province":"Ile de France",
    "sg:tags":[
        "engine"
    ],
    "wof:name":"E C E Sa",
    "wof:placetype":"venue"
},
  "geometry": {"coordinates":[2.358515,48.744316],"type":"Point"}
}