{
  "type": "Feature",
  "properties": {
    "addr:full":"9, Rue des Usines, 60850 Saint Germer de Fly Picardie",
    "addr:housenumber":"9",
    "addr:postcode":"60850",
    "addr:street":"Rue Des Usines",
    "iso:country":"FR",
    "sg:address":"9, Rue des Usines, 60850 Saint Germer de Fly",
    "sg:orig_category":"Non-Classified Establishments",
    "sg:phone":"+33 3 44 82 81 00",
    "sg:province":"Picardie",
    "wof:name":"Imerys Toiture S.a.s.",
    "wof:placetype":"venue"
},
  "geometry": {"coordinates":[1.800452,49.449165],"type":"Point"}
}