{
  "type": "Feature",
  "properties": {
    "addr:full":"Cd 307 64310 St P\u00e9e Sur Nivelle Sare Aquitaine 64310",
    "addr:housenumber":"cd",
    "addr:postcode":"64310;64310",
    "addr:street":"307",
    "iso:country":"FR",
    "sg:address":"Cd 307 64310 St P\u00e9e Sur Nivelle",
    "sg:city":"Sare",
    "sg:orig_category":"Leather and Shoes Leather goods Miscellaneous Products Sport",
    "sg:phone":"+33 5 59 54 56 70",
    "sg:postcode":"64310",
    "sg:province":"Aquitaine",
    "wof:name":"Creation Jean Vier",
    "wof:placetype":"venue"
},
  "geometry": {"coordinates":[-1.505619,43.29377],"type":"Point"}
}