{
  "type": "Feature",
  "properties": {
    "addr:full":"3, Rue Georges M\u00e9lies, 69680 Chassieu Rhone-Alpes 69680",
    "addr:housenumber":"3",
    "addr:postcode":"69680;69680",
    "addr:street":"Rue Georges Me\u0301Lies",
    "iso:country":"FR",
    "sg:address":"3, Rue Georges M\u00e9lies, 69680 Chassieu",
    "sg:orig_category":"Unclassifiable Establishments",
    "sg:phone":"+33 4 78 90 22 10",
    "sg:postcode":"69680",
    "sg:province":"Rhone-Alpes",
    "wof:name":"Soci\u00e9t\u00e9 Lyonnaise De Photogravure S.a.r.l.",
    "wof:placetype":"venue"
},
  "geometry": {"coordinates":[4.959759,45.73502],"type":"Point"}
}