{
  "type": "Feature",
  "properties": {
    "iso:country":"FR",
    "sg:address":"Centre Commercial; Soyaux; 16800",
    "sg:classifiers":[
        {
            "category":"Banks & Credit Unions",
            "subcategory":"Bank",
            "type":"Services"
        }
    ],
    "sg:phone":"+33 3345955617",
    "sg:postcode":"16800",
    "sg:province":"Poitou-Charentes",
    "wof:name":"Soci\u00e9t\u00e9 G\u00e9n\u00e9rale",
    "wof:placetype":"venue"
},
  "geometry": {"coordinates":[0.204234,45.644039],"type":"Point"}
}