{
  "type": "Feature",
  "properties": {
    "addr:full":"16, Rue Paul Langevin - ZI les Terres Saint Lazare, 91130 Ris Orangis Ile de France",
    "addr:housenumber":"16",
    "addr:postcode":"91130",
    "addr:street":"Rue Paul Langevin Zi Les Terres Saint Lazare",
    "iso:country":"FR",
    "sg:address":"16, Rue Paul Langevin - ZI les Terres Saint Lazare, 91130 Ris Orangis",
    "sg:orig_category":"Non-Classified Establishments",
    "sg:phone":"+33 1 69 06 03 61",
    "sg:province":"Ile de France",
    "wof:name":"Planification Mellot S.a.",
    "wof:placetype":"venue"
},
  "geometry": {"coordinates":[2.409515,48.64957],"type":"Point"}
}