{
  "type": "Feature",
  "properties": {
    "addr:full":"ZI Sud 71380 ST MARCEL Ch\u00e2tenoy-en-Bresse Bourgogne 71380",
    "addr:postcode":"71380;71380",
    "addr:street":"Bourgogne",
    "iso:country":"FR",
    "sg:address":"ZI Sud 71380 ST MARCEL",
    "sg:city":"Ch\u00e2tenoy-en-Bresse",
    "sg:classifiers":[
        {
            "category":"Recreation",
            "subcategory":"Fishing",
            "type":"Entertainment"
        }
    ],
    "sg:phone":"+33 3 85 42 73 33",
    "sg:postcode":"71380",
    "sg:province":"Bourgogne",
    "sg:tags":[
        "equipment"
    ],
    "wof:name":"Articles De P\u00eache Water Queen Sa",
    "wof:placetype":"venue"
},
  "geometry": {"coordinates":[4.890325,46.775509],"type":"Point"}
}