{
  "type": "Feature",
  "properties": {
    "iso:country":"FR",
    "sg:address":"Za 34270 St Mathieu De Tr\u00e9viers",
    "sg:classifiers":[
        {
            "category":"Shopping",
            "type":"Retail Goods"
        }
    ],
    "sg:phone":"+33 4 67 55 21 92",
    "sg:postcode":"34270",
    "sg:province":"Languedoc-Roussillon",
    "sg:tags":[
        "metallurgy",
        "finished",
        "-",
        "metalworking",
        "metallic"
    ],
    "wof:name":"Tesma Sa",
    "wof:placetype":"venue"
},
  "geometry": {"coordinates":[3.85852,43.769829],"type":"Point"}
}