{
  "type": "Feature",
  "properties": {
    "addr:full":"B.P. 5, 71210 Montchanin C\u00e9dex^^6, Rue Charles Avril, 71210 Montchanin Montchanin Bourgogne 71210",
    "addr:housenumber":"5",
    "addr:postcode":"71210;71210;71210",
    "addr:street":"B.P.;Rue Charles Avril",
    "iso:country":"FR",
    "sg:address":"B.P. 5, 71210 Montchanin C\u00e9dex^^6, Rue Charles Avril, 71210 Montchanin",
    "sg:city":"Montchanin",
    "sg:orig_category":"Non-Classified Establishments",
    "sg:phone":"+33 3 85 77 08 50",
    "sg:postcode":"71210",
    "sg:province":"Bourgogne",
    "wof:name":"H.t.d. S.a.r.l. - High Tech Design",
    "wof:placetype":"venue"
},
  "geometry": {"coordinates":[4.463261,46.713284],"type":"Point"}
}