{
  "type": "Feature",
  "properties": {
    "iso:country":"FR",
    "sg:address":"12, Rue du Marais, 44270 Saint M\u00eame le Tenu",
    "sg:orig_category":"Non-Classified Establishments",
    "sg:phone":"+33 2 40 78 52 16",
    "sg:postcode":"44270",
    "sg:province":"Pays de Loire",
    "wof:name":"Bonneau S.a.r.l.",
    "wof:placetype":"venue"
},
  "geometry": {"coordinates":[-1.826296,46.993507],"type":"Point"}
}