{
  "type": "Feature",
  "properties": {
    "addr:full":"Pl De La R\u00e9publique 87000 Limoges Limousin 87000",
    "addr:postcode":"87000;87000",
    "addr:street":"Pl De La Re\u0301Publique",
    "iso:country":"FR",
    "sg:address":"Pl De La R\u00e9publique 87000 Limoges",
    "sg:classifiers":[
        {
            "category":"Banks & Credit Unions",
            "subcategory":"Financial Services",
            "type":"Services"
        }
    ],
    "sg:phone":"+33 5 55 33 62 79",
    "sg:postcode":"87000",
    "sg:province":"Limousin",
    "sg:tags":[
        "banking",
        "insurance",
        "institution",
        "finance"
    ],
    "wof:name":"Cofinoga Services",
    "wof:placetype":"venue"
},
  "geometry": {"coordinates":[1.259505,45.831566],"type":"Point"}
}