{
  "type": "Feature",
  "properties": {
    "addr:full":"ZAC de Villard - Le Charvet Bourg Saint Maurice Rhone-Alpes 73700",
    "addr:postcode":"73700",
    "addr:street":"Zac De Villard Le Charvet",
    "iso:country":"FR",
    "sg:address":"ZAC de Villard - Le Charvet",
    "sg:city":"Bourg Saint Maurice",
    "sg:orig_category":"Non-Classified Establishments",
    "sg:phone":"+33 4 79 41 43 43",
    "sg:postcode":"73700",
    "sg:province":"Rhone-Alpes",
    "wof:name":"Ma\u00ebva Latitudes Les Arcs 1800",
    "wof:placetype":"venue"
},
  "geometry": {"coordinates":[6.770775,45.617996],"type":"Point"}
}