{
  "type": "Feature",
  "properties": {
    "addr:full":"14 Rue Chanay 71700 Tournus Tournus Bourgogne 71700",
    "addr:housenumber":"14",
    "addr:postcode":"71700;71700",
    "addr:street":"Rue Chanay",
    "iso:country":"FR",
    "sg:address":"14 Rue Chanay 71700 Tournus",
    "sg:city":"Tournus",
    "sg:classifiers":[
        {
            "category":"Manufacturing",
            "subcategory":"Chemicals & Compounds",
            "type":"Manufacturing & Wholesale Goods"
        }
    ],
    "sg:phone":"+33 3 85 27 18 00",
    "sg:postcode":"71700",
    "sg:province":"Bourgogne",
    "sg:tags":[
        "pharmaceutical",
        "chemistry",
        "-",
        "by-product"
    ],
    "wof:name":"The Valspar France Corporation Sas",
    "wof:placetype":"venue"
},
  "geometry": {"coordinates":[4.90346,46.555489],"type":"Point"}
}