{
  "type": "Feature",
  "properties": {
    "iso:country":"FR",
    "sg:address":"10 Rue Raymond Poincar\u00e9 92000 Nanterre",
    "sg:classifiers":[
        {
            "category":"Shopping",
            "subcategory":"Computers & Home Electronics",
            "type":"Retail Goods"
        }
    ],
    "sg:phone":"+33 1 47 29 98 99",
    "sg:postcode":"92000",
    "sg:province":"Ile de France",
    "sg:tags":[
        "electronic",
        "electrical",
        "equipment"
    ],
    "wof:name":"Ceet Sarl",
    "wof:placetype":"venue"
},
  "geometry": {"coordinates":[2.191501,48.887703],"type":"Point"}
}