{
  "type": "Feature",
  "properties": {
    "iso:country":"FR",
    "sg:address":"8, Rue Thessalie - ZAC de la B\u00e9rangerais, 44240 La Chapelle sur Erdre",
    "sg:orig_category":"Unclassifiable Establishments",
    "sg:phone":"+33 2 51 12 75 75",
    "sg:province":"Pays de Loire",
    "wof:name":"Goubault Imprimeur S.a.",
    "wof:placetype":"venue"
},
  "geometry": {"coordinates":[-1.536342,47.28133],"type":"Point"}
}