{
  "type": "Feature",
  "properties": {
    "addr:full":"17 Rue Ajols 88560 St Maurice Sur Moselle Lorraine 88560",
    "addr:housenumber":"17",
    "addr:postcode":"88560;88560",
    "addr:street":"Rue Ajols",
    "iso:country":"FR",
    "sg:address":"17 Rue Ajols 88560 St Maurice Sur Moselle",
    "sg:classifiers":[
        {
            "category":"Shopping",
            "subcategory":"Crafts & Fabrics",
            "type":"Retail Goods"
        }
    ],
    "sg:phone":"+33 3 29 25 12 60",
    "sg:postcode":"88560",
    "sg:province":"Lorraine",
    "sg:tags":[
        "textile",
        "clothing"
    ],
    "wof:name":"Ets Leveque",
    "wof:placetype":"venue"
},
  "geometry": {"coordinates":[6.817789,47.856541],"type":"Point"}
}