{
  "type": "Feature",
  "properties": {
    "iso:country":"FR",
    "sg:address":"B.P. 1",
    "sg:city":"Croignon",
    "sg:orig_category":"Non-Classified Establishments",
    "sg:phone":"+33 5 57 97 01 01",
    "sg:postcode":"33750",
    "sg:province":"Aquitaine",
    "wof:name":"B.d.i. S.a.s. - B\u00e9daricienne Doras Industries",
    "wof:placetype":"venue"
},
  "geometry": {"coordinates":[-0.286645,44.817909],"type":"Point"}
}