{
  "type": "Feature",
  "properties": {
    "addr:full":"11 Rue Edouard Branly Zae St Eloi 86000 Poitiers Poitou-Charentes",
    "addr:housenumber":"11",
    "addr:postcode":"86000",
    "addr:street":"Rue Edouard Branly Zae St",
    "iso:country":"FR",
    "sg:address":"11 Rue Edouard Branly Zae St Eloi 86000 Poitiers",
    "sg:classifiers":[
        {
            "category":"Manufacturing",
            "subcategory":"Chemicals & Compounds",
            "type":"Manufacturing & Wholesale Goods"
        }
    ],
    "sg:phone":"+33 5 49 44 23 44",
    "sg:province":"Poitou-Charentes",
    "sg:tags":[
        "pharmaceutical",
        "chemistry",
        "-",
        "by-product"
    ],
    "wof:name":"Cdp Kerlys (cdp)",
    "wof:placetype":"venue"
},
  "geometry": {"coordinates":[0.34169,46.58057],"type":"Point"}
}