{
  "type": "Feature",
  "properties": {
    "addr:full":"Route De Lezan 30140 Bagard Languedoc-Roussillon 30140",
    "addr:postcode":"30140;30140",
    "addr:street":"Route De Lezan",
    "iso:country":"FR",
    "sg:address":"Route De Lezan 30140 Bagard",
    "sg:classifiers":[
        {
            "category":"Shopping",
            "type":"Retail Goods"
        }
    ],
    "sg:phone":"+33 4 66 60 76 45",
    "sg:postcode":"30140",
    "sg:province":"Languedoc-Roussillon",
    "sg:tags":[
        "metallurgy",
        "finished",
        "-",
        "metalworking",
        "metallic"
    ],
    "wof:name":"Ferronnerie Diaz",
    "wof:placetype":"venue"
},
  "geometry": {"coordinates":[4.071717,44.075565],"type":"Point"}
}