{
  "type": "Feature",
  "properties": {
    "iso:country":"FR",
    "sg:address":"18 Rue Bouche Thomas",
    "sg:city":"Angers",
    "sg:classifiers":[
        {
            "category":"Banks & Credit Unions",
            "subcategory":"Financial Services",
            "type":"Services"
        }
    ],
    "sg:phone":"+33 2 41 68 68 10",
    "sg:postcode":"49000",
    "sg:province":"Pays de Loire",
    "sg:tags":[
        "banking",
        "finance",
        "insurance"
    ],
    "wof:name":"Societe De Revision D'expertise De Gestion Et D'organisation (soregor) Soregor",
    "wof:placetype":"venue"
},
  "geometry": {"coordinates":[-0.549419,47.442421],"type":"Point"}
}