{
  "type": "Feature",
  "properties": {
    "addr:full":"7, Chemin du Bel Air - ZI, 33450 Saint Loubes Saint-Loub\u00e8s Aquitaine 33450",
    "addr:housenumber":"7",
    "addr:postcode":"33450;loubes;33450",
    "addr:street":"Chemin Du Bel Air Zi",
    "iso:country":"FR",
    "sg:address":"7, Chemin du Bel Air - ZI, 33450 Saint Loubes",
    "sg:city":"Saint-Loub\u00e8s",
    "sg:orig_category":"Non-Classified Establishments",
    "sg:phone":"+33 5 56 38 91 70",
    "sg:postcode":"33450",
    "sg:province":"Aquitaine",
    "wof:name":"T.r.d. S.a. - Tubes Et Raccords Distribution",
    "wof:placetype":"venue"
},
  "geometry": {"coordinates":[-0.464878,44.897083],"type":"Point"}
}