{
  "type": "Feature",
  "properties": {
    "addr:full":"162, Av. de la Gare, 63800 Cournon d'Auvergne P\u00e9rignat-sur-Allier Auvergne 63800",
    "addr:postcode":"63800;pe\u0301rignat-sur-allier;63800",
    "addr:street":"162 Av. De La Gare",
    "iso:country":"FR",
    "sg:address":"162, Av. de la Gare, 63800 Cournon d'Auvergne",
    "sg:city":"P\u00e9rignat-sur-Allier",
    "sg:orig_category":"Unclassifiable Establishments",
    "sg:phone":"+33 4 73 69 93 40",
    "sg:postcode":"63800",
    "sg:province":"Auvergne",
    "wof:name":"Groko S.a.",
    "wof:placetype":"venue"
},
  "geometry": {"coordinates":[3.168055,45.739147],"type":"Point"}
}