{
  "type": "Feature",
  "properties": {
    "addr:full":"28, R\u00e9sidence Vincennes, 77330 Ozoir la Ferri\u00e8re Ile de France",
    "addr:housenumber":"28",
    "addr:postcode":"77330",
    "addr:street":"Re\u0301Sidence Vincennes",
    "iso:country":"FR",
    "sg:address":"28, R\u00e9sidence Vincennes, 77330 Ozoir la Ferri\u00e8re",
    "sg:orig_category":"Unclassifiable Establishments",
    "sg:phone":"+33 1 64 40 43 31",
    "sg:province":"Ile de France",
    "wof:name":"Oscar Marchandising S.a.r.l.",
    "wof:placetype":"venue"
},
  "geometry": {"coordinates":[2.675714,48.7742],"type":"Point"}
}