{
  "type": "Feature",
  "properties": {
    "addr:full":"18, Rue du Docteur Tardif, 49160 Longu\u00e9 Jumelles Pays de Loire",
    "addr:housenumber":"18",
    "addr:postcode":"49160",
    "addr:street":"Rue Du Docteur Tardif",
    "iso:country":"FR",
    "sg:address":"18, Rue du Docteur Tardif, 49160 Longu\u00e9 Jumelles",
    "sg:orig_category":"Unclassifiable Establishments",
    "sg:phone":"+33 2 41 52 10 65",
    "sg:province":"Pays de Loire",
    "wof:name":"Lemercier Offset",
    "wof:placetype":"venue"
},
  "geometry": {"coordinates":[-0.117094,47.377911],"type":"Point"}
}