{
  "type": "Feature",
  "properties": {
    "iso:country":"FR",
    "sg:address":"10 Rue Marconi Zi 76150 Maromme",
    "sg:classifiers":[
        {
            "category":"Manufacturing",
            "subcategory":"Printing",
            "type":"Manufacturing & Wholesale Goods"
        }
    ],
    "sg:phone":"+33 2 32 82 39 39",
    "sg:province":"Haute Normandie",
    "sg:tags":[
        "publishing"
    ],
    "wof:name":"Imprimerie Gabel",
    "wof:placetype":"venue"
},
  "geometry": {"coordinates":[-97.329231,32.748508],"type":"Point"}
}