{
  "type": "Feature",
  "properties": {
    "addr:full":"10 Rue Marconi Zi 76150 Maromme Haute Normandie",
    "addr:housenumber":"10",
    "addr:postcode":"76150",
    "addr:street":"Rue Marconi Zi;Haute Normandie",
    "iso:country":"FR",
    "sg:address":"10 Rue Marconi Zi 76150 Maromme",
    "sg:classifiers":[
        {
            "category":"Manufacturing",
            "subcategory":"Printing",
            "type":"Manufacturing & Wholesale Goods"
        }
    ],
    "sg:phone":"+33 2 32 82 39 39",
    "sg:province":"Haute Normandie",
    "sg:tags":[
        "publishing"
    ],
    "wof:name":"Imprimerie Gabel",
    "wof:placetype":"venue"
},
  "geometry": {"coordinates":[-97.32923099999999,32.748508],"type":"Point"}
}