{
  "type": "Feature",
  "properties": {
    "addr:full":"5, Rue des Reculettes, 75013 Paris Ile de France",
    "addr:housenumber":"5",
    "addr:postcode":"75013",
    "addr:street":"Rue Des Reculettes",
    "iso:country":"FR",
    "sg:address":"5, Rue des Reculettes, 75013 Paris",
    "sg:orig_category":"Unclassifiable Establishments",
    "sg:phone":"+33 1 45 35 06 06",
    "sg:province":"Ile de France",
    "wof:name":"Msb S.a.r.l.",
    "wof:placetype":"venue"
},
  "geometry": {"coordinates":[2.350583,48.831795],"type":"Point"}
}