{
  "type": "Feature",
  "properties": {
    "addr:full":"B.P. 816, 57148 Woippy C\u00e9dex^^Rte de Vigneulles, 57140 Saulny Lorraine 57140",
    "addr:housenumber":"b.p. 816",
    "addr:postcode":"57148;57140;57140",
    "iso:country":"FR",
    "sg:address":"B.P. 816, 57148 Woippy C\u00e9dex^^Rte de Vigneulles, 57140 Saulny",
    "sg:orig_category":"Non-Classified Establishments",
    "sg:phone":"+33 3 87 31 31 54",
    "sg:postcode":"57140",
    "sg:province":"Lorraine",
    "wof:name":"E.g.o. France S.a.s.",
    "wof:placetype":"venue"
},
  "geometry": {"coordinates":[6.150305,49.15131],"type":"Point"}
}