{
  "type": "Feature",
  "properties": {
    "iso:country":"FR",
    "sg:address":"B.P. 741, 49307 Cholet C\u00e9dex^^ZI de l'Appenti\u00e8re, 49280 Mazi\u00e8res en Mauges",
    "sg:orig_category":"Non-Classified Establishments",
    "sg:phone":"+33 2 41 58 57 13",
    "sg:postcode":"49280",
    "sg:province":"Pays de Loire",
    "wof:name":"Atech S.a.",
    "wof:placetype":"venue"
},
  "geometry": {"coordinates":[-0.799978,47.059746],"type":"Point"}
}