{
  "type": "Feature",
  "properties": {
    "addr:full":"165 route des Pr\u00e9s Rollier 74330 Sillingy Rhone-Alpes",
    "addr:housenumber":"165",
    "addr:postcode":"74330",
    "addr:street":"Route Des Pre\u0301S Rollier",
    "iso:country":"FR",
    "sg:address":"165 route des Pr\u00e9s Rollier 74330 Sillingy",
    "sg:classifiers":[
        {
            "category":"Utilities",
            "subcategory":"Natural Gas",
            "type":"Services"
        }
    ],
    "sg:phone":"+33 4 50 22 53 50",
    "sg:province":"Rhone-Alpes",
    "sg:tags":[
        "mechanics",
        "precision"
    ],
    "wof:name":"Pr\u00e9cim\u00e9casavoy Sarl",
    "wof:placetype":"venue"
},
  "geometry": {"coordinates":[6.070728,45.944241],"type":"Point"}
}