{
  "type": "Feature",
  "properties": {
    "iso:country":"FR",
    "sg:address":"8, Rue Catholique, 62134 Fiefs",
    "sg:orig_category":"Unclassifiable Establishments",
    "sg:phone":"+33 3 21 04 61 70",
    "sg:province":"Nord Pas-de-Calais",
    "wof:name":"Lesaffre E.a.r.l.",
    "wof:placetype":"venue"
},
  "geometry": {"coordinates":[2.317124,50.501019],"type":"Point"}
}