{
  "type": "Feature",
  "properties": {
    "addr:full":"8, Rue Catholique, 62134 Fiefs Nord Pas-de-Calais",
    "addr:housenumber":"8",
    "addr:postcode":"62134",
    "addr:street":"Rue Catholique",
    "iso:country":"FR",
    "sg:address":"8, Rue Catholique, 62134 Fiefs",
    "sg:orig_category":"Unclassifiable Establishments",
    "sg:phone":"+33 3 21 04 61 70",
    "sg:province":"Nord Pas-de-Calais",
    "wof:name":"Lesaffre E.a.r.l.",
    "wof:placetype":"venue"
},
  "geometry": {"coordinates":[2.317124,50.501019],"type":"Point"}
}