{
  "type": "Feature",
  "properties": {
    "iso:country":"FR",
    "sg:address":"Les Baudots - Narcilly les Buxy",
    "sg:city":"Buxy",
    "sg:orig_category":"Non-Classified Establishments",
    "sg:phone":"+33 3 85 78 14 81",
    "sg:postcode":"71390",
    "sg:province":"Bourgogne",
    "wof:name":"Monneret Gonnot S.a.r.l.",
    "wof:placetype":"venue"
},
  "geometry": {"coordinates":[4.705024,46.6437],"type":"Point"}
}