{
  "type": "Feature",
  "properties": {
    "addr:full":"35/37, Bd de la Muette - ZI, 95140 Garges les Gonesse Ile de France",
    "addr:housenumber":"35 / 37",
    "addr:postcode":"95140",
    "addr:street":"Bd De La Muette Zi",
    "iso:country":"FR",
    "sg:address":"35/37, Bd de la Muette - ZI, 95140 Garges les Gonesse",
    "sg:orig_category":"Unclassifiable Establishments",
    "sg:phone":"+33 1 34 45 06 26",
    "sg:province":"Ile de France",
    "wof:name":"E.p.l. S.a.r.l.",
    "wof:placetype":"venue"
},
  "geometry": {"coordinates":[2.39924,48.970955],"type":"Point"}
}