{
  "type": "Feature",
  "properties": {
    "addr:full":"550, Rte de la Gare, 59270 Strazeele Nord Pas-de-Calais 59270",
    "addr:housenumber":"550",
    "addr:postcode":"59270;59270",
    "addr:street":"Rte De La Gare",
    "iso:country":"FR",
    "sg:address":"550, Rte de la Gare, 59270 Strazeele",
    "sg:orig_category":"Non-Classified Establishments",
    "sg:phone":"+33 3 28 42 71 83",
    "sg:postcode":"59270",
    "sg:province":"Nord Pas-de-Calais",
    "wof:name":"Etablissements Catteau Et Compagnie S.a.",
    "wof:placetype":"venue"
},
  "geometry": {"coordinates":[2.632068,50.720066],"type":"Point"}
}