{
  "type": "Feature",
  "properties": {
    "addr:full":"24, Rue du Maine, 49000 Angers Pays de Loire",
    "addr:housenumber":"24",
    "addr:postcode":"49000",
    "addr:street":"Rue Du Maine",
    "iso:country":"FR",
    "sg:address":"24, Rue du Maine, 49000 Angers",
    "sg:orig_category":"Unclassifiable Establishments",
    "sg:phone":"+33 2 41 43 62 18",
    "sg:province":"Pays de Loire",
    "wof:name":"Favry Emballages S.a.",
    "wof:placetype":"venue"
},
  "geometry": {"coordinates":[-0.592339,47.465969],"type":"Point"}
}