{
  "type": "Feature",
  "properties": {
    "iso:country":"FR",
    "sg:address":"ZI du bec",
    "sg:city":"Le Chambon Feugerolles",
    "sg:orig_category":"Non-Classified Establishments",
    "sg:phone":"+33 4 77 40 54 04",
    "sg:postcode":"42500",
    "sg:province":"Rhone-Alpes",
    "wof:name":"Eurodec Industries Europ\u00e9enne De D\u00e9colletage S.a.s.",
    "wof:placetype":"venue"
},
  "geometry": {"coordinates":[4.321885,45.396324],"type":"Point"}
}