{
  "type": "Feature",
  "properties": {
    "addr:full":"8, Rue Robert Fulton - ZI Sud Est - Parc Industriel de la Pompelle, 51100 Reims Champagne",
    "addr:housenumber":"8",
    "addr:postcode":"51100",
    "addr:street":"Rue Robert;Zi Sud Est;Industriel;La Pompelle",
    "iso:country":"FR",
    "sg:address":"8, Rue Robert Fulton - ZI Sud Est - Parc Industriel de la Pompelle, 51100 Reims",
    "sg:orig_category":"Unclassifiable Establishments",
    "sg:phone":"+33 3 26 85 60 96",
    "sg:province":"Champagne",
    "wof:name":"Cartonnages Champenois S.a.",
    "wof:placetype":"venue"
},
  "geometry": {"coordinates":[4.028445,49.26284],"type":"Point"}
}