{
  "type": "Feature",
  "properties": {
    "addr:full":"238 Chem Maguide 40600 Biscarrosse Biscarrosse Aquitaine 40600",
    "addr:housenumber":"238",
    "addr:postcode":"40600;40600",
    "addr:street":"Chem Maguide",
    "iso:country":"FR",
    "sg:address":"238 Chem Maguide 40600 Biscarrosse",
    "sg:city":"Biscarrosse",
    "sg:classifiers":[
        {
            "category":"Autos & Motor Vehicles",
            "subcategory":"Boat Sales",
            "type":"Retail Goods"
        }
    ],
    "sg:phone":"+33 5 58 09 85 85",
    "sg:postcode":"40600",
    "sg:province":"Aquitaine",
    "sg:tags":[
        "equipment",
        "transport"
    ],
    "wof:name":"Charlet Nautic Sa",
    "wof:placetype":"venue"
},
  "geometry": {"coordinates":[-1.200975,44.459053],"type":"Point"}
}