{
  "type": "Feature",
  "properties": {
    "iso:country":"FR",
    "sg:address":"9 Rue Du Moulin A Tan 27660 B\u00e9zu St \u00c9loi",
    "sg:classifiers":[
        {
            "category":"Home & Garden",
            "subcategory":"Furniture",
            "type":"Retail Goods"
        }
    ],
    "sg:phone":"+33 2 32 55 17 72",
    "sg:province":"Haute Normandie",
    "sg:tags":[
        "wood"
    ],
    "wof:name":"Ets Destampes Emballages",
    "wof:placetype":"venue"
},
  "geometry": {"coordinates":[-77.73732800000001,38.558685],"type":"Point"}
}