{
  "type": "Feature",
  "properties": {
    "addr:full":"94150 Rungis Ile de France",
    "addr:postcode":"94150",
    "iso:country":"FR",
    "sg:address":"94150 Rungis",
    "sg:orig_category":"Unclassifiable Establishments",
    "sg:phone":"+33 1 46 87 11 42",
    "sg:province":"Ile de France",
    "wof:name":"I.n.g.e.n. S.a. - International G\u00e9n\u00e9tic Technologies",
    "wof:placetype":"venue"
},
  "geometry": {"coordinates":[2.34984,48.74942],"type":"Point"}
}