{
  "type": "Feature",
  "properties": {
    "addr:full":"Z.I. du Madrillet Saint Etienne du Rouvray Haute Normandie 76800",
    "addr:postcode":"76800",
    "addr:street":"Z.I. Du Madrillet;Haute Normandie",
    "iso:country":"FR",
    "sg:address":"Z.I. du Madrillet",
    "sg:city":"Saint Etienne du Rouvray",
    "sg:orig_category":"Unclassifiable Establishments",
    "sg:phone":"+33 2 35 65 16 43",
    "sg:postcode":"76800",
    "sg:province":"Haute Normandie",
    "wof:name":"Slevmi S.a.",
    "wof:placetype":"venue"
},
  "geometry": {"coordinates":[1.10721,49.379585],"type":"Point"}
}