{
  "type": "Feature",
  "properties": {
    "iso:country":"FR",
    "sg:address":"Bel Air 37110 Ch\u00e2teau Renault",
    "sg:city":"Autr\u00e8che",
    "sg:orig_category":"Unclassifiable Establishments",
    "sg:phone":"+33 2 47 56 20 99",
    "sg:postcode":"37110",
    "sg:province":"Centre",
    "wof:name":"Duchesne S.a.",
    "wof:placetype":"venue"
},
  "geometry": {"coordinates":[0.89883,47.594009],"type":"Point"}
}