{
  "type": "Feature",
  "properties": {
    "addr:full":"Moulin De Pierrotte 19450 Chamboulive Limousin 19450",
    "addr:postcode":"19450;19450",
    "addr:street":"Moulin",
    "iso:country":"FR",
    "sg:address":"Moulin De Pierrotte 19450 Chamboulive",
    "sg:classifiers":[
        {
            "category":"Farming",
            "subcategory":"Farm & Veterinary Services",
            "type":"Manufacturing & Wholesale Goods"
        }
    ],
    "sg:phone":"+33 5 55 21 63 16",
    "sg:postcode":"19450",
    "sg:province":"Limousin",
    "sg:tags":[
        "food",
        "product",
        "breeding",
        "animal",
        "related"
    ],
    "wof:name":"Etablissements Boissy",
    "wof:placetype":"venue"
},
  "geometry": {"coordinates":[1.723628,45.440903],"type":"Point"}
}