{
  "type": "Feature",
  "properties": {
    "addr:full":"54 A Jean Mermoz 06110 Cannet (Le) Midi Pyr\u00e9n\u00e9es",
    "addr:housenumber":"54 a",
    "addr:postcode":"06110",
    "addr:street":"Jean Mermoz",
    "iso:country":"FR",
    "sg:address":"54 A",
    "sg:city":"Jean Mermoz 06110 Cannet (Le)",
    "sg:classifiers":[
        {
            "category":"Manufacturing",
            "subcategory":"Paper Products",
            "type":"Manufacturing & Wholesale Goods"
        }
    ],
    "sg:phone":"+33 4 93 39 37 01",
    "sg:province":"Midi Pyr\u00e9n\u00e9es",
    "sg:tags":[
        "packaging",
        "material",
        "-",
        "cardboard"
    ],
    "wof:name":"Usb - Central Bags Dpt United Stars Bags",
    "wof:placetype":"venue"
},
  "geometry": {"coordinates":[-72.737953,41.73407],"type":"Point"}
}