{
  "type": "Feature",
  "properties": {
    "addr:full":"3 rue Pierre Roche 13004 Marseille Poitou-Charentes",
    "addr:housenumber":"3",
    "addr:postcode":"13004",
    "addr:street":"Rue Pierre Roche",
    "iso:country":"FR",
    "sg:address":"3 rue Pierre Roche 13004 Marseille",
    "sg:classifiers":[
        {
            "category":"Government",
            "subcategory":"Post Office",
            "type":"Public Place"
        }
    ],
    "sg:phone":"+33 4 91 34 50 53",
    "sg:province":"Poitou-Charentes",
    "sg:tags":[
        "switch",
        "wiring",
        "cabinet"
    ],
    "wof:name":"Concept Applic Electrother Sa",
    "wof:placetype":"venue"
},
  "geometry": {"coordinates":[5.401,43.309967],"type":"Point"}
}