{
  "type": "Feature",
  "properties": {
    "addr:full":"ZI Saint Pierre 84500 Boll\u00e8ne Provence-Alpes-C\u00f4te d'Azur",
    "addr:postcode":"84500",
    "addr:street":"Saint Pierre",
    "iso:country":"FR",
    "sg:address":"ZI Saint Pierre 84500 Boll\u00e8ne",
    "sg:classifiers":[
        {
            "category":"Professional",
            "subcategory":"Accounting & Tax Preparation",
            "type":"Services"
        }
    ],
    "sg:phone":"+33 4 90 30 26 27",
    "sg:province":"Provence-Alpes-C\u00f4te d'Azur",
    "sg:tags":[
        "process",
        "solution",
        "automation"
    ],
    "wof:name":"Sirap Industries Sa",
    "wof:placetype":"venue"
},
  "geometry": {"coordinates":[4.748432,44.282192],"type":"Point"}
}