{
  "type": "Feature",
  "properties": {
    "addr:full":"152, Quai de la Souys, 33270 Floirac Floirac Aquitaine 33270",
    "addr:housenumber":"152",
    "addr:postcode":"33270;33270",
    "addr:street":"Quai De La Souys",
    "iso:country":"FR",
    "sg:address":"152, Quai de la Souys, 33270 Floirac",
    "sg:city":"Floirac",
    "sg:orig_category":"Non-Classified Establishments",
    "sg:phone":"+33 5 57 77 54 44",
    "sg:postcode":"33270",
    "sg:province":"Aquitaine",
    "wof:name":"B.s.f. S.a. - Boisson Store Fermeture",
    "wof:placetype":"venue"
},
  "geometry": {"coordinates":[-0.532336,44.821781],"type":"Point"}
}