{
  "type": "Feature",
  "properties": {
    "addr:full":"31 Route De Paris 78550 Bazainville Ile de France 78550",
    "addr:housenumber":"31",
    "addr:postcode":"78550;78550",
    "addr:street":"Route De Paris;Ile De France",
    "iso:country":"FR",
    "sg:address":"31 Route De Paris 78550 Bazainville",
    "sg:classifiers":[
        {
            "category":"Farming",
            "subcategory":"Livestock Farm",
            "type":"Manufacturing & Wholesale Goods"
        }
    ],
    "sg:phone":"+33 1 34 87 69 00",
    "sg:postcode":"78550",
    "sg:province":"Ile de France",
    "sg:tags":[
        "breeding",
        "agriculture",
        "animal"
    ],
    "wof:name":"Mer Et Gastronomie",
    "wof:placetype":"venue"
},
  "geometry": {"coordinates":[1.673374,48.797676],"type":"Point"}
}