{
  "type": "Feature",
  "properties": {
    "addr:full":"8, Rue Henri Pescarolo, 93370 Montfermeil Ile de France 93370",
    "addr:housenumber":"8",
    "addr:postcode":"93370;ile;93370",
    "addr:street":"Rue Henri Pescarolo;France",
    "iso:country":"FR",
    "sg:address":"8, Rue Henri Pescarolo, 93370 Montfermeil",
    "sg:orig_category":"Non-Classified Establishments",
    "sg:phone":"+33 1 43 09 17 26",
    "sg:postcode":"93370",
    "sg:province":"Ile de France",
    "wof:name":"Delta Froid S.a.r.l.",
    "wof:placetype":"venue"
},
  "geometry": {"coordinates":[2.581407,48.903893],"type":"Point"}
}