{
  "type": "Feature",
  "properties": {
    "addr:full":"12 Rue Ste Anne 41000 Blois Blois Centre 41000",
    "addr:housenumber":"12",
    "addr:postcode":"41000;41000",
    "addr:street":"Rue Ste Anne",
    "iso:country":"FR",
    "sg:address":"12 Rue Ste Anne 41000 Blois",
    "sg:city":"Blois",
    "sg:classifiers":[
        {
            "category":"Professional",
            "subcategory":"Business Services",
            "type":"Services"
        }
    ],
    "sg:phone":"+33 2 54 78 49 37",
    "sg:postcode":"41000",
    "sg:province":"Centre",
    "sg:tags":[
        "body",
        "advice"
    ],
    "wof:name":"Association Du Centre Educatif Social Des Mineurs",
    "wof:placetype":"venue"
},
  "geometry": {"coordinates":[1.341128,47.584213],"type":"Point"}
}