{
  "type": "Feature",
  "properties": {
    "addr:full":"14-20 R Marcel Dassault 93141 Bondy Cedex Picardie",
    "addr:housenumber":"14-20",
    "addr:postcode":"93141",
    "addr:street":"R Marcel Dassault",
    "iso:country":"FR",
    "sg:address":"14-20 R Marcel Dassault 93141 Bondy Cedex",
    "sg:classifiers":[
        {
            "category":"Manufacturing",
            "subcategory":"Chemicals & Compounds",
            "type":"Manufacturing & Wholesale Goods"
        }
    ],
    "sg:phone":"+33 1 48 02 73 73",
    "sg:province":"Picardie",
    "sg:tags":[
        "pharmaceutical",
        "chemistry",
        "-",
        "by-product"
    ],
    "wof:name":"Marabu France S A R L",
    "wof:placetype":"venue"
},
  "geometry": {"coordinates":[2.481109,48.888081],"type":"Point"}
}