{
  "type": "Feature",
  "properties": {
    "addr:full":"Domaine de Corbeville Ouest 91400 Orsay Ile de France",
    "addr:postcode":"91400",
    "addr:street":"Ouest;Ile De France",
    "iso:country":"FR",
    "sg:address":"Domaine de Corbeville Ouest 91400 Orsay",
    "sg:orig_category":"Non-Classified Establishments",
    "sg:phone":"+33 1 69 33 69 33",
    "sg:province":"Ile de France",
    "wof:name":"S.g.s. Qualitest Industrie S.a.s.",
    "wof:placetype":"venue"
},
  "geometry": {"coordinates":[2.187755,48.698891],"type":"Point"}
}