{
  "type": "Feature",
  "properties": {
    "addr:full":"B.P. 415, 95005 Cergy C\u00e9dex^^1, Rue de Bretagne - ZI des B\u00e9thunes, 95000 Cergy Ile de France",
    "addr:housenumber":"b.p. 415",
    "addr:postcode":"95005;95000;ile",
    "addr:street":"Rue De Bretagne;Des Be\u0301Thunes",
    "iso:country":"FR",
    "sg:address":"B.P. 415, 95005 Cergy C\u00e9dex^^1, Rue de Bretagne - ZI des B\u00e9thunes, 95000 Cergy",
    "sg:orig_category":"Non-Classified Establishments",
    "sg:phone":"+33 1 34 30 44 44",
    "sg:province":"Ile de France",
    "wof:name":"T.s.e.p. - Techniques Surfaces Electrolytiques De Paris",
    "wof:placetype":"venue"
},
  "geometry": {"coordinates":[2.07982,49.035198],"type":"Point"}
}