{
  "type": "Feature",
  "properties": {
    "addr:full":"158, Av. Francis de Pressenc\u00e9, 69200 V\u00e9nissieux Rhone-Alpes 69200",
    "addr:postcode":"69200;69200",
    "addr:street":"158 Av. Francis De Pressence\u0301",
    "iso:country":"FR",
    "sg:address":"158, Av. Francis de Pressenc\u00e9, 69200 V\u00e9nissieux",
    "sg:orig_category":"Non-Classified Establishments",
    "sg:phone":"+33 4 78 77 96 97",
    "sg:postcode":"69200",
    "sg:province":"Rhone-Alpes",
    "wof:name":"R.e.a. S.a.r.l. - Rh\u00f4ne Equipement Automatismes",
    "wof:placetype":"venue"
},
  "geometry": {"coordinates":[4.86731,45.720879],"type":"Point"}
}