{
  "type": "Feature",
  "properties": {
    "addr:full":"42 Rue Ambroise Croizat 38434 Echirolles Cedex \u00c9chirolles Rhone-Alpes 38130",
    "addr:housenumber":"42",
    "addr:postcode":"38434;38130",
    "addr:street":"Rue Ambroise Croizat",
    "iso:country":"FR",
    "sg:address":"42 Rue Ambroise Croizat 38434 Echirolles Cedex",
    "sg:city":"\u00c9chirolles",
    "sg:classifiers":[
        {
            "category":"Manufacturing",
            "subcategory":"Chemicals & Compounds",
            "type":"Manufacturing & Wholesale Goods"
        }
    ],
    "sg:phone":"+33 4 76 23 39 27",
    "sg:postcode":"38130",
    "sg:province":"Rhone-Alpes",
    "sg:tags":[
        "pharmaceutical",
        "chemistry"
    ],
    "wof:name":"Sodipro Sa",
    "wof:placetype":"venue"
},
  "geometry": {"coordinates":[5.707191,45.158195],"type":"Point"}
}