{
  "type": "Feature",
  "properties": {
    "addr:full":"Za 64170 Artix Artix Aquitaine 64170",
    "addr:postcode":"64170;64170",
    "addr:street":"Za",
    "iso:country":"FR",
    "sg:address":"Za 64170 Artix",
    "sg:city":"Artix",
    "sg:classifiers":[
        {
            "category":"Shopping",
            "subcategory":"Computers & Home Electronics",
            "type":"Retail Goods"
        }
    ],
    "sg:phone":"+33 5 59 83 22 66",
    "sg:postcode":"64170",
    "sg:province":"Aquitaine",
    "sg:tags":[
        "electronic",
        "electrical",
        "equipment"
    ],
    "wof:name":"Ste Exploitation Ets Coustellie Sarl",
    "wof:placetype":"venue"
},
  "geometry": {"coordinates":[-0.538375,43.376938],"type":"Point"}
}