{
  "type": "Feature",
  "properties": {
    "iso:country":"FR",
    "sg:address":"4 Rue Andr\u00e9 Charles Boulle BP 18230 Zi De Malitorne 18230 St Doulchard",
    "sg:city":"Saint-Doulchard",
    "sg:orig_category":"Chemicals and Pharmaceuticals Chemistry - by-products Fabrics and linen Plastics Rubber and Plastics",
    "sg:phone":"+33 2 48 70 39 36",
    "sg:postcode":"18230",
    "sg:province":"Centre",
    "wof:name":"Comptoir Des Peintures Gauthier",
    "wof:placetype":"venue"
},
  "geometry": {"coordinates":[2.35792,47.104084],"type":"Point"}
}