{
  "type": "Feature",
  "properties": {
    "iso:country":"FR",
    "sg:address":"Z.A. les Charpennes",
    "sg:city":"Marlieux",
    "sg:orig_category":"Unclassifiable Establishments",
    "sg:phone":"+33 4 74 42 89 89",
    "sg:postcode":"01240",
    "sg:province":"Rhone-Alpes",
    "wof:name":"Ad\u00e9quat S.a.r.l.",
    "wof:placetype":"venue"
},
  "geometry": {"coordinates":[5.16483,46.100128],"type":"Point"}
}