{
  "type": "Feature",
  "properties": {
    "iso:country":"FR",
    "sg:address":"13 rue De La Perdrix 93290 Tremblay en France",
    "sg:classifiers":[
        {
            "category":"Wholesale",
            "subcategory":"Medical Equipment & Supplies",
            "type":"Manufacturing & Wholesale Goods"
        }
    ],
    "sg:phone":"+33 1 49 90 70 10",
    "sg:postcode":"93290",
    "sg:province":"Ile de France",
    "sg:tags":[
        "heat-protection"
    ],
    "wof:name":"Ste Francaise Approvision Fournitures S.a.",
    "wof:placetype":"venue"
},
  "geometry": {"coordinates":[2.510654,48.977512],"type":"Point"}
}