{
  "type": "Feature",
  "properties": {
    "addr:full":"1 Pl Du 8 Mai 88160 Le Thillot Lorraine 88160",
    "addr:housenumber":"1",
    "addr:postcode":"88160;88160",
    "addr:street":"Pl Du 8 Mai",
    "iso:country":"FR",
    "sg:address":"1 Pl Du 8 Mai 88160 Le Thillot",
    "sg:classifiers":[
        {
            "category":"Bakery",
            "type":"Food & Drink"
        }
    ],
    "sg:phone":"+33 3 29 25 01 40",
    "sg:postcode":"88160",
    "sg:province":"Lorraine",
    "sg:tags":[
        "cake",
        "product",
        "related",
        "bread"
    ],
    "wof:name":"Boulangerie Daval",
    "wof:placetype":"venue"
},
  "geometry": {"coordinates":[6.764995,47.87986],"type":"Point"}
}