{
  "type": "Feature",
  "properties": {
    "iso:country":"FR",
    "sg:address":"6 impasse de l'Ardoise 45170 Neuville aux Bois",
    "sg:city":"Bougy-lez-Neuville",
    "sg:classifiers":[
        {
            "category":"Manufacturing",
            "subcategory":"Motor Vehicles & Parts",
            "type":"Manufacturing & Wholesale Goods"
        }
    ],
    "sg:phone":"+33 1 69 10 15 50",
    "sg:postcode":"45170",
    "sg:province":"Centre",
    "sg:tags":[
        "body",
        "car"
    ],
    "wof:name":"Carrosserie Trouillet Sa",
    "wof:placetype":"venue"
},
  "geometry": {"coordinates":[2.05268,48.068771],"type":"Point"}
}