{
  "type": "Feature",
  "properties": {
    "addr:full":"16 R Joseph Cugnot BP 15 17182 P\u00e9rigny Cedex Ile de France",
    "addr:housenumber":"16;15",
    "addr:postcode":"17182;ile",
    "addr:street":"R Joseph Cugnot Bp",
    "iso:country":"FR",
    "sg:address":"16 R Joseph Cugnot BP 15 17182 P\u00e9rigny Cedex",
    "sg:classifiers":[
        {
            "category":"Autos & Motor Vehicles",
            "subcategory":"Boat Sales",
            "type":"Retail Goods"
        }
    ],
    "sg:phone":"+33 5 46 55 17 31",
    "sg:province":"Ile de France",
    "sg:tags":[
        "equipment",
        "transport"
    ],
    "wof:name":"Amel Chantiers Sa",
    "wof:placetype":"venue"
},
  "geometry": {"coordinates":[-1.104876,46.156612],"type":"Point"}
}