{
  "type": "Feature",
  "properties": {
    "addr:full":"B.P. CS 50904, 08209 Sedan C\u00e9dex^^Rue Dunant, 08140 Bazeilles Champagne",
    "addr:postcode":"08209;08140",
    "addr:street":"B.P. Cs 50904;Dunant",
    "iso:country":"FR",
    "sg:address":"B.P. CS 50904, 08209 Sedan C\u00e9dex^^Rue Dunant, 08140 Bazeilles",
    "sg:orig_category":"Non-Classified Establishments",
    "sg:phone":"+33 3 24 27 03 29",
    "sg:province":"Champagne",
    "wof:name":"Faber S.a.",
    "wof:placetype":"venue"
},
  "geometry": {"coordinates":[5.02497,49.68927],"type":"Point"}
}