{
  "type": "Feature",
  "properties": {
    "iso:country":"FR",
    "sg:address":"94, Av. de Canejan, 33600 Pessac",
    "sg:city":"Pessac",
    "sg:orig_category":"Unclassifiable Establishments",
    "sg:phone":"+33 5 57 89 18 00",
    "sg:postcode":"33600",
    "sg:province":"Aquitaine",
    "wof:name":"A.f.p.a.",
    "wof:placetype":"venue"
},
  "geometry": {"coordinates":[-0.650623,44.790108],"type":"Point"}
}