{
  "type": "Feature",
  "properties": {
    "iso:country":"FR",
    "sg:address":"Zi Av L\u00e9on Jouhaux 33213 Langon Cedex",
    "sg:classifiers":[
        {
            "category":"Manufacturing",
            "subcategory":"Metals",
            "type":"Manufacturing & Wholesale Goods"
        }
    ],
    "sg:phone":"+33 5 56 76 56 56",
    "sg:province":"Aquitaine",
    "sg:tags":[
        "metallurgy",
        "metalworking"
    ],
    "wof:name":"Pmso Sa",
    "wof:placetype":"venue"
},
  "geometry": {"coordinates":[-0.264703,44.547054],"type":"Point"}
}