{
  "type": "Feature",
  "properties": {
    "addr:full":"Plaine Du Gier Vall\u00e9e Du Gi BP 74 69700 Givors Rhone-Alpes 69700",
    "addr:housenumber":"74",
    "addr:postcode":"69700;69700",
    "addr:street":"Plaine;Valle\u0301E Du Gi Bp",
    "iso:country":"FR",
    "sg:address":"Plaine Du Gier",
    "sg:city":"Vall\u00e9e Du Gi BP 74 69700 Givors",
    "sg:classifiers":[
        {
            "category":"Shopping",
            "type":"Retail Goods"
        }
    ],
    "sg:phone":"+33 4 78 07 40 00",
    "sg:postcode":"69700",
    "sg:province":"Rhone-Alpes",
    "sg:tags":[
        "metallurgy",
        "finished",
        "-",
        "metalworking",
        "metallic"
    ],
    "wof:name":"Soci\u00c9t\u00c9 Nouvelle De Moules",
    "wof:placetype":"venue"
},
  "geometry": {"coordinates":[4.715199,45.551682],"type":"Point"}
}