{
  "type": "Feature",
  "properties": {
    "iso:country":"FR",
    "sg:address":"Rte d'Iss\u00e9 - ZI",
    "sg:city":"Ch\u00e2teaubriant",
    "sg:orig_category":"Non-Classified Establishments",
    "sg:phone":"+33 2 40 81 14 41",
    "sg:postcode":"44110",
    "sg:province":"Pays de Loire",
    "wof:name":"U.f.m. S.a. - Unit\u00e9 De Fabrication M\u00e9canique",
    "wof:placetype":"venue"
},
  "geometry": {"coordinates":[-1.491925,47.65461],"type":"Point"}
}