{
  "type": "Feature",
  "properties": {
    "iso:country":"FR",
    "sg:address":"13, L'Aum\u00f4ne, 23300 Saint Agnant de Versillat",
    "sg:orig_category":"Unclassifiable Establishments",
    "sg:phone":"+33 5 55 63 09 62",
    "sg:province":"Limousin",
    "wof:name":"Bourdon S.a.r.l.",
    "wof:placetype":"venue"
},
  "geometry": {"coordinates":[1.50379,46.263699],"type":"Point"}
}