{
  "type": "Feature",
  "properties": {
    "addr:full":"Zone Industrielle Sud Les Aviots Thaon les Vosges Lorraine 88150",
    "addr:postcode":"88150",
    "addr:street":"Zone Industrielle Sud;Aviots",
    "iso:country":"FR",
    "sg:address":"Zone Industrielle Sud Les Aviots",
    "sg:city":"Thaon les Vosges",
    "sg:orig_category":"Non-Classified Establishments",
    "sg:phone":"+33 3 29 31 52 05",
    "sg:postcode":"88150",
    "sg:province":"Lorraine",
    "wof:name":"Atmeca S.a.r.l.",
    "wof:placetype":"venue"
},
  "geometry": {"coordinates":[6.41948,48.250435],"type":"Point"}
}