{
  "type": "Feature",
  "properties": {
    "iso:country":"FR",
    "sg:address":"Rte de Bu",
    "sg:city":"Houdan",
    "sg:orig_category":"Unclassifiable Establishments",
    "sg:phone":"+33 1 30 46 19 00",
    "sg:postcode":"78550",
    "sg:province":"Ile de France",
    "wof:name":"Laboratoire Lact\u00e9ol Du Docteur Boucard S.a.",
    "wof:placetype":"venue"
},
  "geometry": {"coordinates":[1.60191,48.788956],"type":"Point"}
}