{
  "type": "Feature",
  "properties": {
    "iso:country":"FR",
    "sg:address":"Rue Gustave Zed\u00e9",
    "sg:city":"Brest",
    "sg:orig_category":"Non-Classified Establishments",
    "sg:phone":"+33 2 98 41 50 38",
    "sg:postcode":"29200",
    "sg:province":"Bretagne",
    "wof:name":"Bretagne Echafaudage S.a.",
    "wof:placetype":"venue"
},
  "geometry": {"coordinates":[-4.463595,48.422401],"type":"Point"}
}