{
  "type": "Feature",
  "properties": {
    "addr:full":"Rue Bessemer - ZI Sud Le Mans Pays de Loire 72000",
    "addr:postcode":"72000",
    "addr:street":"Rue Bessemer Zi Sud",
    "iso:country":"FR",
    "sg:address":"Rue Bessemer - ZI Sud",
    "sg:city":"Le Mans",
    "sg:orig_category":"Non-Classified Establishments",
    "sg:phone":"+33 2 43 85 58 60",
    "sg:postcode":"72000",
    "sg:province":"Pays de Loire",
    "wof:name":"Etablissements Maillard S.a.s.",
    "wof:placetype":"venue"
},
  "geometry": {"coordinates":[0.197813,48.008095],"type":"Point"}
}