{
  "type": "Feature",
  "properties": {
    "addr:full":"Chemin des Vo\u00fbtes Graulhet Midi Pyr\u00e9n\u00e9es 81300",
    "addr:postcode":"81300",
    "addr:street":"Chemin Des Vou\u0302Tes",
    "iso:country":"FR",
    "sg:address":"Chemin des Vo\u00fbtes",
    "sg:city":"Graulhet",
    "sg:orig_category":"Unclassifiable Establishments",
    "sg:phone":"+33 5 63 42 06 22",
    "sg:postcode":"81300",
    "sg:province":"Midi Pyr\u00e9n\u00e9es",
    "wof:name":"Coop\u00e9rative Agricole Graulhet Lombers",
    "wof:placetype":"venue"
},
  "geometry": {"coordinates":[1.992471,43.767475],"type":"Point"}
}