{
  "type": "Feature",
  "properties": {
    "addr:full":"108, Bd du Midi, 06150 Cannes Provence-Alpes-C\u00f4te d'Azur",
    "addr:housenumber":"108",
    "addr:postcode":"06150",
    "addr:street":"Bd Du Midi",
    "iso:country":"FR",
    "sg:address":"108, Bd du Midi, 06150 Cannes",
    "sg:orig_category":"Unclassifiable Establishments",
    "sg:phone":"+33 4 93 48 74 87",
    "sg:province":"Provence-Alpes-C\u00f4te d'Azur",
    "wof:name":"Varep S.a.",
    "wof:placetype":"venue"
},
  "geometry": {"coordinates":[6.968731,43.556938],"type":"Point"}
}