{
  "type": "Feature",
  "properties": {
    "addr:full":"1 Rue Passerelle 69171 TARARE CEDEX Picardie",
    "addr:housenumber":"1",
    "addr:postcode":"69171",
    "addr:street":"Rue Passerelle",
    "iso:country":"FR",
    "sg:address":"1 Rue Passerelle 69171 TARARE CEDEX",
    "sg:classifiers":[
        {
            "category":"Professional",
            "subcategory":"Art Services",
            "type":"Services"
        }
    ],
    "sg:phone":"+33 4 74 05 02 08",
    "sg:province":"Picardie",
    "sg:tags":[
        "underwear",
        "design"
    ],
    "wof:name":"Defitex Sa",
    "wof:placetype":"venue"
},
  "geometry": {"coordinates":[4.434725,45.894039],"type":"Point"}
}