{
  "type": "Feature",
  "properties": {
    "addr:full":"B.P. 117, 76330 Notre Dame de Gravenchon^^Rue J\u00e9rome Cardan - Parc d'Activit\u00e9s, 76330 Notre Dame de  Haute Normandie",
    "addr:housenumber":"b.p. 117",
    "addr:postcode":"76330;76330",
    "addr:street":"Dame;Cardan;\u0301S;Dame De Haute Normandie",
    "iso:country":"FR",
    "sg:address":"B.P. 117, 76330 Notre Dame de Gravenchon^^Rue J\u00e9rome Cardan - Parc d'Activit\u00e9s, 76330 Notre Dame de ",
    "sg:orig_category":"Non-Classified Establishments",
    "sg:phone":"+33 2 32 84 10 10",
    "sg:province":"Haute Normandie",
    "wof:name":"M.c.i.i. S.a. - Mesure Contr\u00f4le Informatique Industrielle",
    "wof:placetype":"venue"
},
  "geometry": {"coordinates":[0.581916,49.481335],"type":"Point"}
}