{
  "type": "Feature",
  "properties": {
    "addr:full":"B.P. 230, 01602 Tr\u00e9voux C\u00e9dex^^1, Rte de Lyon, 01600 Tr\u00e9voux Rhone-Alpes",
    "addr:housenumber":"b.p. 230",
    "addr:postcode":"01602;01600",
    "addr:street":"Rte De Lyon",
    "iso:country":"FR",
    "sg:address":"B.P. 230, 01602 Tr\u00e9voux C\u00e9dex^^1, Rte de Lyon, 01600 Tr\u00e9voux",
    "sg:orig_category":"Non-Classified Establishments",
    "sg:phone":"+33 4 74 00 13 63",
    "sg:province":"Rhone-Alpes",
    "wof:name":"Langlade Et Picard S.a.",
    "wof:placetype":"venue"
},
  "geometry": {"coordinates":[4.79649,45.94265],"type":"Point"}
}