{
  "type": "Feature",
  "properties": {
    "addr:full":"47 Rue Des Antignans 26110 Nyons Rhone-Alpes 26110",
    "addr:housenumber":"47",
    "addr:postcode":"26110;26110",
    "addr:street":"Rue Des Antignans",
    "iso:country":"FR",
    "sg:address":"47 Rue Des Antignans 26110 Nyons",
    "sg:classifiers":[
        {
            "category":"Home & Garden",
            "subcategory":"Building Materials",
            "type":"Retail Goods"
        }
    ],
    "sg:phone":"+33 4 75 26 01 60",
    "sg:postcode":"26110",
    "sg:province":"Rhone-Alpes",
    "sg:tags":[
        "equipment",
        "energy",
        "-",
        "environment",
        "raw",
        "machinery"
    ],
    "wof:name":"La Generale Des Eaux",
    "wof:placetype":"venue"
},
  "geometry": {"coordinates":[5.133936,44.35574],"type":"Point"}
}