{
  "type": "Feature",
  "properties": {
    "iso:country":"FR",
    "sg:address":"Rue Thales - ZA aux Sorbier",
    "sg:city":"Dannemarie sur Cr\u00eate",
    "sg:orig_category":"Non-Classified Establishments",
    "sg:phone":"+33 3 81 58 61 61",
    "sg:postcode":"25410",
    "sg:province":"Franche Comt\u00e9",
    "wof:name":"A.o.p.b. S.a.r.l. - Atelier D'outillage De Production Beuchey",
    "wof:placetype":"venue"
},
  "geometry": {"coordinates":[5.81099,47.181793],"type":"Point"}
}