{
  "type": "Feature",
  "properties": {
    "iso:country":"FR",
    "sg:address":"61380 Maheru",
    "sg:city":"Mah\u00e9ru",
    "sg:classifiers":[
        {
            "category":"Building & Trades",
            "subcategory":"Construction",
            "type":"Services"
        }
    ],
    "sg:phone":"+33 2 33 34 50 11",
    "sg:postcode":"61380",
    "sg:province":"Basse Normandie",
    "sg:tags":[
        "livestock",
        "business",
        "advice",
        "animal",
        "breeding",
        "agriculture"
    ],
    "wof:name":"Elevage Et Agriculture",
    "wof:placetype":"venue"
},
  "geometry": {"coordinates":[0.432194,48.657192],"type":"Point"}
}