{
  "type": "Feature",
  "properties": {
    "addr:full":"B.P. 19, 67127 Molsheim C\u00e9dex^^30, Rue Amp\u00e8re, 67120 Duttlenheim Molsheim Alsace 67120",
    "addr:postcode":"67127;67120;67120",
    "addr:street":"B.P. 19;Rue Ampe\u0300Re",
    "iso:country":"FR",
    "sg:address":"B.P. 19, 67127 Molsheim C\u00e9dex^^30, Rue Amp\u00e8re, 67120 Duttlenheim",
    "sg:city":"Molsheim",
    "sg:orig_category":"Non-Classified Establishments",
    "sg:phone":"+33 3 88 47 96 00",
    "sg:postcode":"67120",
    "sg:province":"Alsace",
    "wof:name":"Lancier S.a.",
    "wof:placetype":"venue"
},
  "geometry": {"coordinates":[7.490672,48.540382],"type":"Point"}
}