{
  "type": "Feature",
  "properties": {
    "iso:country":"FR",
    "sg:address":"1, Av. du Millac, 33370 Artigues Pr\u00e8s Bordeaux",
    "sg:city":"Artigues-pr\u00e8s-Bordeaux",
    "sg:orig_category":"Unclassifiable Establishments",
    "sg:phone":"+33 5 56 06 00 21",
    "sg:postcode":"33370",
    "sg:province":"Aquitaine",
    "wof:name":"Alexandre Mareuil S.a.r.l.",
    "wof:placetype":"venue"
},
  "geometry": {"coordinates":[-0.501943,44.869434],"type":"Point"}
}