{
  "type": "Feature",
  "properties": {
    "iso:country":"FR",
    "sg:address":"Rte de Varennes",
    "sg:city":"Clermont en Argonne",
    "sg:orig_category":"Non-Classified Establishments",
    "sg:phone":"+33 3 29 88 46 34",
    "sg:postcode":"55120",
    "sg:province":"Lorraine",
    "wof:name":"P\u00e9pini\u00e8res D'argonne",
    "wof:placetype":"venue"
},
  "geometry": {"coordinates":[5.068662,49.110062],"type":"Point"}
}