{
  "type": "Feature",
  "properties": {
    "addr:full":"48, Rue de la R\u00e9publique, 42600 Montbrison Rhone-Alpes",
    "addr:housenumber":"48",
    "addr:postcode":"42600",
    "addr:street":"Rue De La Re\u0301Publique",
    "iso:country":"FR",
    "sg:address":"48, Rue de la R\u00e9publique, 42600 Montbrison",
    "sg:orig_category":"Unclassifiable Establishments",
    "sg:phone":"+33 4 77 96 17 00",
    "sg:province":"Rhone-Alpes",
    "wof:name":"B.m.r.a. S.a.",
    "wof:placetype":"venue"
},
  "geometry": {"coordinates":[4.07572,45.606094],"type":"Point"}
}