{
  "type": "Feature",
  "properties": {
    "addr:full":"All\u00e9e de la Garenne - ZI le Bux\u00e9rioux Ch\u00e2teauroux Centre 36000",
    "addr:postcode":"36000",
    "addr:street":"Alle\u0301E De La Garenne Zi Le Buxe\u0301Rioux Cha\u0302Teauroux",
    "iso:country":"FR",
    "sg:address":"All\u00e9e de la Garenne - ZI le Bux\u00e9rioux",
    "sg:city":"Ch\u00e2teauroux",
    "sg:orig_category":"Unclassifiable Establishments",
    "sg:phone":"+33 2 54 53 67 00",
    "sg:postcode":"36000",
    "sg:province":"Centre",
    "wof:name":"Martin Rondeau S.a.",
    "wof:placetype":"venue"
},
  "geometry": {"coordinates":[1.696558,46.812469],"type":"Point"}
}