{
  "type": "Feature",
  "properties": {
    "iso:country":"FR",
    "sg:address":"22 blvd B\u00e9noni Goullin; Nantes; 44000",
    "sg:classifiers":[
        {
            "category":"Banks & Credit Unions",
            "subcategory":"Bank",
            "type":"Services"
        }
    ],
    "sg:phone":"+33 3340897927",
    "sg:postcode":"44000",
    "sg:province":"Pays de Loire",
    "wof:name":"Caisse Regionale, De Cr\u00e9dit Agricole",
    "wof:placetype":"venue"
},
  "geometry": {"coordinates":[-1.553059,47.218117],"type":"Point"}
}