{
  "type": "Feature",
  "properties": {
    "addr:full":"1 Avenue Gutenberg Za De Larrieu Polis 31120 Portet Sur Garonne Midi Pyr\u00e9n\u00e9es 31120",
    "addr:housenumber":"1",
    "addr:postcode":"31120;31120",
    "addr:street":"Avenue Gutenberg Za De Larrieu",
    "iso:country":"FR",
    "sg:address":"1 Avenue Gutenberg Za De Larrieu Polis 31120 Portet Sur Garonne",
    "sg:classifiers":[
        {
            "category":"Wholesale",
            "subcategory":"Medical Equipment & Supplies",
            "type":"Manufacturing & Wholesale Goods"
        }
    ],
    "sg:phone":"+33 5 62 87 55 66",
    "sg:postcode":"31120",
    "sg:province":"Midi Pyr\u00e9n\u00e9es",
    "sg:tags":[
        "instrument",
        "health",
        "-",
        "precision"
    ],
    "wof:name":"Raymond Valette Dentaire",
    "wof:placetype":"venue"
},
  "geometry": {"coordinates":[1.398561,43.52187],"type":"Point"}
}