{
  "type": "Feature",
  "properties": {
    "addr:full":"8, All\u00e9e du Ch\u00e2teau - ZI du Gassion, 57100 Thionville Lorraine",
    "addr:housenumber":"8",
    "addr:postcode":"57100",
    "addr:street":"Alle\u0301E Du Cha\u0302Teau Zi Du Gassion",
    "iso:country":"FR",
    "sg:address":"8, All\u00e9e du Ch\u00e2teau - ZI du Gassion, 57100 Thionville",
    "sg:orig_category":"Non-Classified Establishments",
    "sg:phone":"+33 3 82 82 87 78",
    "sg:province":"Lorraine",
    "wof:name":"Facen S.a.",
    "wof:placetype":"venue"
},
  "geometry": {"coordinates":[6.158469,49.339546],"type":"Point"}
}