{
  "type": "Feature",
  "properties": {
    "addr:full":"RN 86 Soyons Rhone-Alpes 07130",
    "addr:postcode":"07130",
    "addr:street":"Rn 86;Rhone-Alpes",
    "iso:country":"FR",
    "sg:address":"RN 86",
    "sg:city":"Soyons",
    "sg:orig_category":"Non-Classified Establishments",
    "sg:phone":"+33 4 75 60 91 59",
    "sg:postcode":"07130",
    "sg:province":"Rhone-Alpes",
    "wof:name":"Technigarden S.a.",
    "wof:placetype":"venue"
},
  "geometry": {"coordinates":[4.84198,44.93663],"type":"Point"}
}