{
  "type": "Feature",
  "properties": {
    "addr:full":"3 Rue Du Priaur\u00e9 BP 26 35410 Ch\u00e2teaugiron Ch\u00e2teaugiron Bretagne 35410",
    "addr:housenumber":"3;26",
    "addr:postcode":"35410;35410",
    "addr:street":"Rue Du Priaure\u0301 Bp",
    "iso:country":"FR",
    "sg:address":"3 Rue Du Priaur\u00e9 BP 26 35410 Ch\u00e2teaugiron",
    "sg:city":"Ch\u00e2teaugiron",
    "sg:classifiers":[
        {
            "category":"Professional",
            "subcategory":"Business Services",
            "type":"Services"
        }
    ],
    "sg:phone":"+33 2 99 37 40 23",
    "sg:postcode":"35410",
    "sg:province":"Bretagne",
    "sg:tags":[
        "training",
        "advice"
    ],
    "wof:name":"Ogec",
    "wof:placetype":"venue"
},
  "geometry": {"coordinates":[-1.502135,48.046448],"type":"Point"}
}