{
  "type": "Feature",
  "properties": {
    "addr:full":"B.P. 2, 02250 Marle^^Rue Antoine Laurent Lavoisier - ZI, 02250 Marle Picardie 02250",
    "addr:housenumber":"2",
    "addr:postcode":"02250;02250;02250",
    "addr:street":"B.P.;Antoine Laurent Lavoisier Zi",
    "iso:country":"FR",
    "sg:address":"B.P. 2, 02250 Marle^^Rue Antoine Laurent Lavoisier - ZI, 02250 Marle",
    "sg:orig_category":"Non-Classified Establishments",
    "sg:phone":"+33 3 23 21 71 00",
    "sg:postcode":"02250",
    "sg:province":"Picardie",
    "wof:name":"Bayer Conditionnement S.a.r.l.",
    "wof:placetype":"venue"
},
  "geometry": {"coordinates":[3.77908,49.73595],"type":"Point"}
}