{
  "type": "Feature",
  "properties": {
    "iso:country":"FR",
    "sg:address":"Rn 74 21190 Meursault",
    "sg:city":"Meursault",
    "sg:classifiers":[
        {
            "category":"Building & Trades",
            "subcategory":"Construction",
            "type":"Services"
        }
    ],
    "sg:phone":"+33 3 80 21 69 09",
    "sg:postcode":"21190",
    "sg:province":"Bourgogne",
    "sg:tags":[
        "work",
        "transport",
        "public",
        "road"
    ],
    "wof:name":"Entreprise Hubert Rougeot",
    "wof:placetype":"venue"
},
  "geometry": {"coordinates":[4.775,46.976566],"type":"Point"}
}