{
  "type": "Feature",
  "properties": {
    "addr:full":"42 route Nationale 10 78310 Coignieres Ile de France",
    "addr:housenumber":"42;10",
    "addr:postcode":"78310",
    "addr:street":"Route Nationale;Ile De France",
    "iso:country":"FR",
    "sg:address":"42 route Nationale 10 78310 Coignieres",
    "sg:classifiers":[
        {
            "category":"Utilities",
            "subcategory":"Recycling",
            "type":"Services"
        }
    ],
    "sg:phone":"+33 1 34 82 62 82",
    "sg:province":"Ile de France",
    "sg:tags":[
        "non-ferrous",
        "metal"
    ],
    "wof:name":"Techmet Sa",
    "wof:placetype":"venue"
},
  "geometry": {"coordinates":[1.944855,48.761749],"type":"Point"}
}