{
  "type": "Feature",
  "properties": {
    "addr:full":"30 rue Marcel Paul 76600 Le Havre Haute Normandie",
    "addr:housenumber":"30",
    "addr:postcode":"76600",
    "addr:street":"Rue Marcel Paul",
    "iso:country":"FR",
    "sg:address":"30 rue Marcel Paul 76600 Le Havre",
    "sg:classifiers":[
        {
            "category":"Professional",
            "subcategory":"Employment Agencies",
            "type":"Services"
        }
    ],
    "sg:phone":"+33 2 35 53 06 57",
    "sg:province":"Haute Normandie",
    "sg:tags":[
        "freight",
        "sea"
    ],
    "wof:name":"Rouen Affretement 76 S.a.",
    "wof:placetype":"venue"
},
  "geometry": {"coordinates":[0.145078,49.493217],"type":"Point"}
}