{
  "type": "Feature",
  "properties": {
    "iso:country":"FR",
    "sg:address":"160, Bd Denis Papin, 53000 Laval",
    "sg:orig_category":"Unclassifiable Establishments",
    "sg:phone":"+33 2 43 53 38 66",
    "sg:province":"Pays de Loire",
    "wof:name":"C.e.i.m. - Comptoir Industriel Electro Du Maine",
    "wof:placetype":"venue"
},
  "geometry": {"coordinates":[-0.747435,48.085171],"type":"Point"}
}