{
  "type": "Feature",
  "properties": {
    "addr:full":"5A rue de Picardie 67116 Reichstett Reichstett Alsace 67116",
    "addr:housenumber":"5a",
    "addr:postcode":"67116;67116",
    "addr:street":"Rue De Picardie",
    "iso:country":"FR",
    "sg:address":"5A rue de Picardie 67116 Reichstett",
    "sg:city":"Reichstett",
    "sg:classifiers":[
        {
            "category":"Shopping",
            "subcategory":"Crafts & Fabrics",
            "type":"Retail Goods"
        }
    ],
    "sg:phone":"+33 3 88 20 58 55",
    "sg:postcode":"67116",
    "sg:province":"Alsace",
    "sg:tags":[
        "guillotine",
        "graphic",
        "trade"
    ],
    "wof:name":"Clementz Et Cie Sa",
    "wof:placetype":"venue"
},
  "geometry": {"coordinates":[7.761143,48.642612],"type":"Point"}
}