{
  "type": "Feature",
  "properties": {
    "addr:full":"Le Bourg 87290 Saint Sornin Leulac Limousin",
    "addr:postcode":"87290",
    "addr:street":"Le Bourg",
    "iso:country":"FR",
    "sg:address":"Le Bourg 87290 Saint Sornin Leulac",
    "sg:orig_category":"Unclassifiable Establishments",
    "sg:phone":"+33 5 55 76 20 83",
    "sg:province":"Limousin",
    "wof:name":"Centre 7 S.a.r.l.",
    "wof:placetype":"venue"
},
  "geometry": {"coordinates":[1.30174,46.199242],"type":"Point"}
}