{
  "type": "Feature",
  "properties": {
    "addr:full":"358 Av Paris 79025 Niort Cedex 9 Poitou-Charentes",
    "addr:housenumber":"358",
    "addr:postcode":"79025",
    "addr:street":"Av Paris",
    "iso:country":"FR",
    "sg:address":"358 Av Paris 79025 Niort Cedex 9",
    "sg:classifiers":[
        {
            "category":"Manufacturing",
            "subcategory":"Paper Products",
            "type":"Manufacturing & Wholesale Goods"
        }
    ],
    "sg:phone":"+33 5 49 33 00 68",
    "sg:province":"Poitou-Charentes",
    "sg:tags":[
        "finished",
        "cardboard",
        "-"
    ],
    "wof:name":"Cartorel Leclerc Pelletier Sa",
    "wof:placetype":"venue"
},
  "geometry": {"coordinates":[-0.418678,46.337364],"type":"Point"}
}