{
  "type": "Feature",
  "properties": {
    "iso:country":"FR",
    "sg:address":"1/3, Rue du Colonel Fabien - ZI du Pont Yblon, 93440 Dugny",
    "sg:orig_category":"Unclassifiable Establishments",
    "sg:phone":"+33 1 48 35 91 91",
    "sg:province":"Ile de France",
    "wof:name":"France Transports S.a.",
    "wof:placetype":"venue"
},
  "geometry": {"coordinates":[2.41726,48.955601],"type":"Point"}
}