{
  "type": "Feature",
  "properties": {
    "iso:country":"FR",
    "sg:address":"21 R Louis Lepine Zi Sud Colline 13500 Martigues",
    "sg:city":"Artigue",
    "sg:classifiers":[
        {
            "category":"Building & Trades",
            "subcategory":"Construction",
            "type":"Services"
        }
    ],
    "sg:phone":"+33 4 42 13 02 00",
    "sg:postcode":"31110",
    "sg:province":"Midi Pyr\u00e9n\u00e9es",
    "sg:tags":[
        "work",
        "public"
    ],
    "wof:name":"Sogea Sud Est",
    "wof:placetype":"venue"
},
  "geometry": {"coordinates":[5.055235,43.406536],"type":"Point"}
}