{
  "type": "Feature",
  "properties": {
    "iso:country":"FR",
    "sg:address":"19, Bd du Mar\u00e9chal Juin, 49400 Saumur",
    "sg:orig_category":"Unclassifiable Establishments",
    "sg:phone":"+33 2 41 50 39 13",
    "sg:province":"Pays de Loire",
    "wof:name":"S.p.c.a.",
    "wof:placetype":"venue"
},
  "geometry": {"coordinates":[-0.087524,47.267731],"type":"Point"}
}