{
  "type": "Feature",
  "properties": {
    "addr:full":"Rte de Noyon Coucy le Chateau Auffrique Picardie 02380",
    "addr:postcode":"02380",
    "addr:street":"Rte De Noyon;Picardie",
    "iso:country":"FR",
    "sg:address":"Rte de Noyon",
    "sg:city":"Coucy le Chateau Auffrique",
    "sg:orig_category":"Non-Classified Establishments",
    "sg:phone":"+33 3 23 52 68 00",
    "sg:postcode":"02380",
    "sg:province":"Picardie",
    "wof:name":"U.t.p.m. S.a. - Usinage Et Transformation De Produits M\u00e9tallurgiques",
    "wof:placetype":"venue"
},
  "geometry": {"coordinates":[3.32728,49.517651],"type":"Point"}
}