{
  "type": "Feature",
  "properties": {
    "addr:full":"Rue William Jaubert - La Pouyade Saint M\u00e9dard de Guizi\u00e8res Aquitaine 33230",
    "addr:postcode":"33230",
    "addr:street":"Rue William Jaubert La Pouyade Saint Me\u0301Dard De Guizie\u0300Res",
    "iso:country":"FR",
    "sg:address":"Rue William Jaubert - La Pouyade",
    "sg:city":"Saint M\u00e9dard de Guizi\u00e8res",
    "sg:orig_category":"Unclassifiable Establishments",
    "sg:phone":"+33 5 57 69 61 71",
    "sg:postcode":"33230",
    "sg:province":"Aquitaine",
    "wof:name":"Dudule S.a.",
    "wof:placetype":"venue"
},
  "geometry": {"coordinates":[-0.058893,45.016338],"type":"Point"}
}