{
  "type": "Feature",
  "properties": {
    "iso:country":"FR",
    "sg:address":"109 Av Louis Gallouedec Zi De L'Herveline 45400 Fleury Les Aubrais",
    "sg:city":"Chanteau",
    "sg:classifiers":[
        {
            "category":"Professional",
            "type":"Services"
        }
    ],
    "sg:phone":"+33 2 38 86 09 27",
    "sg:postcode":"45400",
    "sg:province":"Centre",
    "sg:tags":[
        "transport",
        "road"
    ],
    "wof:name":"Abx Logistics",
    "wof:placetype":"venue"
},
  "geometry": {"coordinates":[1.943396,47.940838],"type":"Point"}
}