{
  "type": "Feature",
  "properties": {
    "addr:full":"Usine de Fontrousse Firminy Auvergne 42700",
    "addr:postcode":"42700",
    "iso:country":"FR",
    "sg:address":"Usine de Fontrousse",
    "sg:city":"Firminy",
    "sg:orig_category":"Unclassifiable Establishments",
    "sg:phone":"+33 4 77 40 12 00",
    "sg:postcode":"42700",
    "sg:province":"Auvergne",
    "wof:name":"Autobar Flexible France S.a.s.",
    "wof:placetype":"venue"
},
  "geometry": {"coordinates":[4.278008,45.384243],"type":"Point"}
}