{
  "type": "Feature",
  "properties": {
    "addr:full":"415 R C\u00e9sar Vuarchex 74950 Scionzier Rhone-Alpes 74950",
    "addr:housenumber":"415",
    "addr:postcode":"74950;74950",
    "addr:street":"R Ce\u0301Sar Vuarchex;Rhone-Alpes",
    "iso:country":"FR",
    "sg:address":"415 R C\u00e9sar Vuarchex 74950 Scionzier",
    "sg:classifiers":[
        {
            "category":"Professional",
            "type":"Services"
        }
    ],
    "sg:phone":"+33 4 50 89 50 50",
    "sg:postcode":"74950",
    "sg:province":"Rhone-Alpes",
    "sg:tags":[
        "transport",
        "road"
    ],
    "wof:name":"Gst Sa",
    "wof:placetype":"venue"
},
  "geometry": {"coordinates":[6.552366,46.069248],"type":"Point"}
}