{
  "type": "Feature",
  "properties": {
    "iso:country":"FR",
    "sg:address":"B.P. 50, 77610 Fontenay Tr\u00e9signy C\u00e9dex^^48, Rue de Fr\u00e9gy, 77610 Fontenay Tr\u00e9signy",
    "sg:orig_category":"Non-Classified Establishments",
    "sg:phone":"+33 1 64 42 52 52",
    "sg:province":"Ile de France",
    "wof:name":"Heraeus Sensor Nite France S.a.s.",
    "wof:placetype":"venue"
},
  "geometry": {"coordinates":[2.86665,48.706684],"type":"Point"}
}