{
  "type": "Feature",
  "properties": {
    "iso:country":"FR",
    "sg:address":"127 rue d'Antibes 06400 Cannes",
    "sg:classifiers":[
        {
            "category":"Building & Trades",
            "subcategory":"Equipment Rental",
            "type":"Services"
        }
    ],
    "sg:phone":"+33 4 93 39 23 24",
    "sg:province":"Picardie",
    "sg:tags":[
        "first-aid"
    ],
    "wof:name":"Cr\u00e9ations Jc Delepine C\u00f4te D'azur Sarl",
    "wof:placetype":"venue"
},
  "geometry": {"coordinates":[7.019693,43.552658],"type":"Point"}
}