{
  "type": "Feature",
  "properties": {
    "addr:full":"18, Rue d'Hauteville, 74150 Rumilly Rhone-Alpes",
    "addr:housenumber":"18",
    "addr:postcode":"74150",
    "addr:street":"Rue D'Hauteville",
    "iso:country":"FR",
    "sg:address":"18, Rue d'Hauteville, 74150 Rumilly",
    "sg:orig_category":"Non-Classified Establishments",
    "sg:phone":"+33 4 50 01 44 18",
    "sg:province":"Rhone-Alpes",
    "wof:name":"Adia Int\u00e9rim",
    "wof:placetype":"venue"
},
  "geometry": {"coordinates":[5.97249,45.902981],"type":"Point"}
}