{
  "type": "Feature",
  "properties": {
    "addr:full":"Rte de la Blanche Bailleul Nord Pas-de-Calais 59270",
    "addr:postcode":"59270",
    "addr:street":"Rte De La Blanche Bailleul Nord",
    "iso:country":"FR",
    "sg:address":"Rte de la Blanche",
    "sg:city":"Bailleul",
    "sg:orig_category":"Unclassifiable Establishments",
    "sg:phone":"+33 3 28 42 62 28",
    "sg:postcode":"59270",
    "sg:province":"Nord Pas-de-Calais",
    "wof:name":"Danone S.a.",
    "wof:placetype":"venue"
},
  "geometry": {"coordinates":[2.74213,50.709785],"type":"Point"}
}