{
  "type": "Feature",
  "properties": {
    "addr:full":"1025, Rue Henri Becquerel - Parc Club du Mill\u00e9naire, 34000 Montpellier Languedoc-Roussillon",
    "addr:housenumber":"1025",
    "addr:postcode":"34000",
    "addr:street":"Rue Henri Becquerel Parc Club Du Mille\u0301Naire",
    "iso:country":"FR",
    "sg:address":"1025, Rue Henri Becquerel - Parc Club du Mill\u00e9naire, 34000 Montpellier",
    "sg:orig_category":"Non-Classified Establishments",
    "sg:phone":"+33 4 67 22 13 12",
    "sg:province":"Languedoc-Roussillon",
    "wof:name":"Protection One S.a.",
    "wof:placetype":"venue"
},
  "geometry": {"coordinates":[3.914558,43.609131],"type":"Point"}
}