{
  "type": "Feature",
  "properties": {
    "addr:full":"5 Rue De La Fagatte 54280 Sorneville Lorraine",
    "addr:housenumber":"5",
    "addr:postcode":"54280",
    "addr:street":"Rue De La Fagatte",
    "iso:country":"FR",
    "sg:address":"5 Rue De La Fagatte 54280 Sorneville",
    "sg:classifiers":[
        {
            "category":"Manufacturing",
            "subcategory":"Wood Products",
            "type":"Manufacturing & Wholesale Goods"
        }
    ],
    "sg:phone":"+33 3 83 31 62 02",
    "sg:province":"Lorraine",
    "sg:tags":[
        "professional",
        "furniture"
    ],
    "wof:name":"Mobixyl",
    "wof:placetype":"venue"
},
  "geometry": {"coordinates":[6.421124,48.748112],"type":"Point"}
}