{
  "type": "Feature",
  "properties": {
    "addr:full":"22 Bd De La Lib\u00e9ration 44600 St Nazaire Pays de Loire 44600",
    "addr:housenumber":"22",
    "addr:postcode":"44600 st nazaire;44600",
    "addr:street":"Bd De La Libe\u0301Ration",
    "iso:country":"FR",
    "sg:address":"22 Bd De La Lib\u00e9ration 44600 St Nazaire",
    "sg:classifiers":[
        {
            "category":"Wholesale",
            "subcategory":"Chemicals & Plastics",
            "type":"Manufacturing & Wholesale Goods"
        }
    ],
    "sg:phone":"+33 2 40 22 40 70",
    "sg:postcode":"44600",
    "sg:province":"Pays de Loire",
    "sg:tags":[
        "pharmaceutical",
        "energy",
        "material",
        "-",
        "raw",
        "chemistry",
        "by-product"
    ],
    "wof:name":"Cpo",
    "wof:placetype":"venue"
},
  "geometry": {"coordinates":[-2.205827,47.282425],"type":"Point"}
}