{
  "type": "Feature",
  "properties": {
    "iso:country":"FR",
    "sg:address":"12 rue de la R\u00e9publique; Orl\u00e9ans; 45000",
    "sg:city":"Orl\u00e9ans",
    "sg:classifiers":[
        {
            "category":"Banks & Credit Unions",
            "subcategory":"Bank",
            "type":"Services"
        }
    ],
    "sg:phone":"+33 3338536865",
    "sg:postcode":"45000",
    "sg:province":"Centre",
    "wof:name":"Soci\u00e9t\u00e9 G\u00e9n\u00e9rale",
    "wof:placetype":"venue"
},
  "geometry": {"coordinates":[1.904341,47.903828],"type":"Point"}
}