{
  "type": "Feature",
  "properties": {
    "addr:full":"3, Chemin de la Croix Bris\u00e9e, 92160 Antony Ile de France",
    "addr:housenumber":"3",
    "addr:postcode":"92160",
    "addr:street":"Chemin De La Croix Brise\u0301E",
    "iso:country":"FR",
    "sg:address":"3, Chemin de la Croix Bris\u00e9e, 92160 Antony",
    "sg:orig_category":"Unclassifiable Establishments",
    "sg:phone":"+33 1 40 96 26 26",
    "sg:province":"Ile de France",
    "wof:name":"Beckaert S.a.r.l.",
    "wof:placetype":"venue"
},
  "geometry": {"coordinates":[2.315041,48.732204],"type":"Point"}
}