{
  "type": "Feature",
  "properties": {
    "iso:country":"FR",
    "sg:address":"Rte de l'Orange - ZI des Sablons",
    "sg:city":"Meung sur Loire",
    "sg:orig_category":"Unclassifiable Establishments",
    "sg:phone":"+33 2 38 44 75 75",
    "sg:postcode":"45130",
    "sg:province":"Centre",
    "wof:name":"Chr\u00e9tien S.a.r.l.",
    "wof:placetype":"venue"
},
  "geometry": {"coordinates":[1.709913,47.840733],"type":"Point"}
}