{
  "type": "Feature",
  "properties": {
    "iso:country":"FR",
    "sg:address":"B.P. 60014, 60301 Senlis C\u00e9dex^^CD 924, 60300 Senlis",
    "sg:orig_category":"Non-Classified Establishments",
    "sg:phone":"+33 3 44 67 13 70",
    "sg:province":"Picardie",
    "wof:name":"Sopal S.a.",
    "wof:placetype":"venue"
},
  "geometry": {"coordinates":[2.5857,49.206364],"type":"Point"}
}