{
  "type": "Feature",
  "properties": {
    "addr:full":"B.P. 24, 73201 Albertville C\u00e9dex^^62, Rue de la R\u00e9publique, 73200 Albertville Rhone-Alpes 73200",
    "addr:postcode":"73201;73200;73200",
    "addr:street":"B.P. 24;Rue De La Re\u0301Publique",
    "iso:country":"FR",
    "sg:address":"B.P. 24, 73201 Albertville C\u00e9dex^^62, Rue de la R\u00e9publique, 73200 Albertville",
    "sg:orig_category":"Non-Classified Establishments",
    "sg:phone":"+33 4 79 37 78 81",
    "sg:postcode":"73200",
    "sg:province":"Rhone-Alpes",
    "wof:name":"Banque De Savoie",
    "wof:placetype":"venue"
},
  "geometry": {"coordinates":[6.359874,45.63168],"type":"Point"}
}