{
  "type": "Feature",
  "properties": {
    "iso:country":"FR",
    "sg:address":"route de Verneuil 27160 BRETEUIL SUR ITON",
    "sg:orig_category":"Rounds Of Steel",
    "sg:phone":"+33 2 32 35 64 30",
    "sg:province":"Haute Normandie",
    "wof:name":"Forges Et Laminoirs De Breteuil S.a.",
    "wof:placetype":"venue"
},
  "geometry": {"coordinates":[0.85262,48.788513],"type":"Point"}
}