{
  "type": "Feature",
  "properties": {
    "addr:full":"15, Rue de Tours, 49300 Cholet Pays de Loire",
    "addr:housenumber":"15",
    "addr:postcode":"49300",
    "addr:street":"Rue De Tours",
    "iso:country":"FR",
    "sg:address":"15, Rue de Tours, 49300 Cholet",
    "sg:orig_category":"Unclassifiable Establishments",
    "sg:phone":"+33 2 41 65 94 22",
    "sg:province":"Pays de Loire",
    "wof:name":"S.p.p.f. S.a.",
    "wof:placetype":"venue"
},
  "geometry": {"coordinates":[-0.852551,47.070904],"type":"Point"}
}