{
  "type": "Feature",
  "properties": {
    "iso:country":"FR",
    "sg:address":"B.P. 14",
    "sg:city":"La Chapelle de Guinchay^^Le Bel Avenir 71570 La Chapelle de Guinchay",
    "sg:orig_category":"Non-Classified Establishments",
    "sg:phone":"+33 3 85 36 70 26",
    "sg:postcode":"71570",
    "sg:province":"Bourgogne",
    "wof:name":"Champale S.a.",
    "wof:placetype":"venue"
},
  "geometry": {"coordinates":[4.752783,46.18528],"type":"Point"}
}