{
  "type": "Feature",
  "properties": {
    "iso:country":"FR",
    "sg:address":"B.P. 44, 59260 Hellemmes Lille^^21, Rue Jean Bart, 59260 Hellemmes Lille",
    "sg:orig_category":"Non-Classified Establishments",
    "sg:phone":"+33 3 20 43 36 43",
    "sg:province":"Nord Pas-de-Calais",
    "wof:name":"Tcval S.a.",
    "wof:placetype":"venue"
},
  "geometry": {"coordinates":[3.11705,50.614567],"type":"Point"}
}