{
  "type": "Feature",
  "properties": {
    "iso:country":"FR",
    "sg:address":"B.P. 123, 71005 Macon C\u00e9dex^^16, Rue Bigonnet, 71000 M\u00e2con",
    "sg:city":"Sanc\u00e9",
    "sg:orig_category":"Non-Classified Establishments",
    "sg:phone":"+33 3 85 21 07 60",
    "sg:postcode":"71000",
    "sg:province":"Bourgogne",
    "wof:name":"Forestier S.a.",
    "wof:placetype":"venue"
},
  "geometry": {"coordinates":[4.833055,46.303043],"type":"Point"}
}