{
  "type": "Feature",
  "properties": {
    "addr:full":"8 rue Porte aux; Ch\u00e2teauroux; 36002 Languedoc-Roussillon",
    "addr:housenumber":"8",
    "addr:postcode":"36002",
    "addr:street":"Rue Porte Aux Cha\u0302Teauroux",
    "iso:country":"FR",
    "sg:address":"8 rue Porte aux; Ch\u00e2teauroux; 36002",
    "sg:classifiers":[
        {
            "category":"Banks & Credit Unions",
            "subcategory":"Bank",
            "type":"Services"
        }
    ],
    "sg:phone":"+33 2 54 60 32 32",
    "sg:province":"Languedoc-Roussillon",
    "wof:name":"Cr\u00e9dit Industriel, De L'ouest Sa",
    "wof:placetype":"venue"
},
  "geometry": {"coordinates":[1.696558,46.812469],"type":"Point"}
}