{
  "type": "Feature",
  "properties": {
    "iso:country":"FR",
    "sg:address":"37, Av du G\u00e9n\u00e9ral Leclerc, 10300 La Rivi\u00e8re de Corps",
    "sg:orig_category":"Unclassifiable Establishments",
    "sg:phone":"+33 3 25 78 13 81",
    "sg:province":"Champagne",
    "wof:name":"Genet",
    "wof:placetype":"venue"
},
  "geometry": {"coordinates":[4.056065,48.292885],"type":"Point"}
}