{
  "type": "Feature",
  "properties": {
    "iso:country":"FR",
    "sg:address":"Route Fouesnant 29950 B\u00e9nodet",
    "sg:city":"B\u00e9nodet",
    "sg:classifiers":[
        {
            "category":"Professional",
            "type":"Services"
        }
    ],
    "sg:phone":"+33 2 98 57 19 73",
    "sg:postcode":"29950",
    "sg:province":"Bretagne",
    "sg:tags":[
        "transport",
        "road"
    ],
    "wof:name":"Matelot Sa",
    "wof:placetype":"venue"
},
  "geometry": {"coordinates":[-4.061839,47.876205],"type":"Point"}
}