{
  "type": "Feature",
  "properties": {
    "iso:country":"FR",
    "sg:address":"B.P. 35, 63120 Courpi\u00e8re^^28, Av. Henri Pourat, 63120 Courpi\u00e8re",
    "sg:city":"Courpi\u00e8re",
    "sg:orig_category":"Non-Classified Establishments",
    "sg:phone":"+33 4 73 53 10 77",
    "sg:postcode":"63120",
    "sg:province":"Auvergne",
    "wof:name":"M\u00e9nadier Et Fils S.a.",
    "wof:placetype":"venue"
},
  "geometry": {"coordinates":[3.535275,45.715576],"type":"Point"}
}