{
  "type": "Feature",
  "properties": {
    "iso:country":"FR",
    "sg:address":"B.P. 13, 22610 Pleubian C\u00e9dex^^8, Rue Boisg\u00e9lin, 22610 Pleubian",
    "sg:city":"Pleubian",
    "sg:orig_category":"Non-Classified Establishments",
    "sg:phone":"+33 2 96 22 91 95",
    "sg:postcode":"22610",
    "sg:province":"Bretagne",
    "wof:name":"Soci\u00e9t\u00e9 Des Fils De Mah\u00e9 Louis S.a.",
    "wof:placetype":"venue"
},
  "geometry": {"coordinates":[-3.182846,48.8283],"type":"Point"}
}