{
  "type": "Feature",
  "properties": {
    "addr:full":"B.P. 100, 25461 Etupes C\u00e9dex^^Technoland, 25460 Etupes Franche Comt\u00e9",
    "addr:housenumber":"b.p. 100",
    "addr:postcode":"25461;25460",
    "addr:street":"Ce\u0301Dex^^Technoland;Franche Comte\u0301",
    "iso:country":"FR",
    "sg:address":"B.P. 100, 25461 Etupes C\u00e9dex^^Technoland, 25460 Etupes",
    "sg:orig_category":"Non-Classified Establishments",
    "sg:phone":"+33 3 81 32 61 93",
    "sg:province":"Franche Comt\u00e9",
    "wof:name":"Simonin Michel S.a.r.l.",
    "wof:placetype":"venue"
},
  "geometry": {"coordinates":[6.862814,47.506931],"type":"Point"}
}