{
  "type": "Feature",
  "properties": {
    "addr:full":"B.P. 64, 49427 Saumur C\u00e9dex^^Rue de Chantemerle Bagneux, 49400 Saumur Pays de Loire",
    "addr:postcode":"49427;49400",
    "addr:street":"B.P. 64;Chantemerle",
    "iso:country":"FR",
    "sg:address":"B.P. 64, 49427 Saumur C\u00e9dex^^Rue de Chantemerle Bagneux, 49400 Saumur",
    "sg:orig_category":"Non-Classified Establishments",
    "sg:phone":"+33 2 41 40 44 44",
    "sg:province":"Pays de Loire",
    "wof:name":"France Champignon",
    "wof:placetype":"venue"
},
  "geometry": {"coordinates":[-0.068679,47.2145],"type":"Point"}
}