{
  "type": "Feature",
  "properties": {
    "iso:country":"FR",
    "sg:address":"24 boulevard des Iles 92130 Issy les Moulineaux",
    "sg:classifiers":[
        {
            "category":"Food & Beverages",
            "subcategory":"Specialty",
            "type":"Retail Goods"
        }
    ],
    "sg:phone":"+33 1 46 10 13 00",
    "sg:postcode":"92130",
    "sg:province":"Ile de France",
    "sg:tags":[
        "consulting"
    ],
    "wof:name":"Cie Francaise Gestion Services De Sant\u00e9 Sa",
    "wof:placetype":"venue"
},
  "geometry": {"coordinates":[2.24969,48.822529],"type":"Point"}
}