{
  "type": "Feature",
  "properties": {
    "iso:country":"FR",
    "sg:address":"3 Rue Claude Odde 42000 St Etienne",
    "sg:classifiers":[
        {
            "category":"Professional",
            "subcategory":"Printing & Photocopies",
            "type":"Services"
        }
    ],
    "sg:phone":"+33 4 77 74 33 99",
    "sg:postcode":"42000",
    "sg:province":"Rhone-Alpes",
    "sg:tags":[
        "publishing"
    ],
    "wof:name":"Le Bois National L'officiel Du Bois",
    "wof:placetype":"venue"
},
  "geometry": {"coordinates":[4.382808,45.459339],"type":"Point"}
}