{
  "type": "Feature",
  "properties": {
    "addr:full":"74800 La Roche sur Foron Rhone-Alpes",
    "addr:postcode":"74800",
    "iso:country":"FR",
    "sg:address":"74800 La Roche sur Foron",
    "sg:orig_category":"Unclassifiable Establishments",
    "sg:phone":"+33 4 50 03 22 15",
    "sg:province":"Rhone-Alpes",
    "wof:name":"Lejeune Sa",
    "wof:placetype":"venue"
},
  "geometry": {"coordinates":[6.31217,46.059872],"type":"Point"}
}