{
  "type": "Feature",
  "properties": {
    "addr:full":"B.P. 10442, 95707 Roissy Charles de Gaulle C\u00e9dex^^14, Rue de la Belle Borne - Zone de Fr\u00eat 5 - B\u00e2tim Rhone-Alpes",
    "addr:housenumber":"5",
    "addr:postcode":"95707",
    "addr:street":"Rue De La Belle Borne Zone De Fre\u0302T",
    "iso:country":"FR",
    "sg:address":"B.P. 10442, 95707 Roissy Charles de Gaulle C\u00e9dex^^14, Rue de la Belle Borne - Zone de Fr\u00eat 5 - B\u00e2tim",
    "sg:orig_category":"Non-Classified Establishments",
    "sg:phone":"+33 1 48 16 77 88",
    "sg:province":"Rhone-Alpes",
    "wof:name":"Henry Johnson Sons Et Co Ltd",
    "wof:placetype":"venue"
},
  "geometry": {"coordinates":[-90.72370100000001,39.560822],"type":"Point"}
}