{
  "type": "Feature",
  "properties": {
    "addr:full":"B.P. 719, 55107 Verdun C\u00e9dex^^11, Rue du Pr\u00e9sident Poincar\u00e9, 55100 Verdun Lorraine",
    "addr:housenumber":"b.p. 719",
    "addr:postcode":"55107;55100",
    "addr:street":"Rue Du Pre\u0301Sident Poincare\u0301",
    "iso:country":"FR",
    "sg:address":"B.P. 719, 55107 Verdun C\u00e9dex^^11, Rue du Pr\u00e9sident Poincar\u00e9, 55100 Verdun",
    "sg:orig_category":"Non-Classified Establishments",
    "sg:phone":"+33 3 29 83 44 22",
    "sg:province":"Lorraine",
    "wof:name":"Mairie De Verdun",
    "wof:placetype":"venue"
},
  "geometry": {"coordinates":[5.383225,49.164806],"type":"Point"}
}