{
  "type": "Feature",
  "properties": {
    "iso:country":"FR",
    "sg:address":"22 avenue du G\u00e9n\u00e9ral de Gaulle 91000 EVRY",
    "sg:classifiers":[
        {
            "category":"Utilities",
            "type":"Services"
        }
    ],
    "sg:phone":"+33 1 69 05 59 33",
    "sg:postcode":"91000",
    "sg:province":"Ile de France",
    "sg:tags":[
        "equipment",
        "labeling"
    ],
    "wof:name":"Groupe Sramag S.a.",
    "wof:placetype":"venue"
},
  "geometry": {"coordinates":[2.44693,48.63588],"type":"Point"}
}