{
  "type": "Feature",
  "properties": {
    "iso:country":"FR",
    "sg:address":"322, Av. Charles de Gaulle, 84260 Sarrians",
    "sg:orig_category":"Non-Classified Establishments",
    "sg:phone":"+33 4 90 65 41 15",
    "sg:province":"Basse Normandie",
    "wof:name":"Etablissements Marbaud S.a.r.l.",
    "wof:placetype":"venue"
},
  "geometry": {"coordinates":[4.972981,44.077427],"type":"Point"}
}