{
  "type": "Feature",
  "properties": {
    "iso:country":"FR",
    "sg:address":"La Chanteleuserie 37140 Benais",
    "sg:city":"Benais",
    "sg:orig_category":"Unclassifiable Establishments",
    "sg:phone":"+33 2 47 97 30 20",
    "sg:postcode":"37140",
    "sg:province":"Centre",
    "wof:name":"Boucard Thierry E.a.r.l.",
    "wof:placetype":"venue"
},
  "geometry": {"coordinates":[0.226985,47.299042],"type":"Point"}
}