{
  "type": "Feature",
  "properties": {
    "addr:full":"12 Rue De La Liberation 21400 Chatillon Sur Seine Aisey-sur-Seine Bourgogne 21400",
    "addr:housenumber":"12",
    "addr:postcode":"21400;21400",
    "addr:street":"Rue De La Liberation;Seine;Bourgogne",
    "iso:country":"FR",
    "sg:address":"12 Rue De La Liberation 21400 Chatillon Sur Seine",
    "sg:city":"Aisey-sur-Seine",
    "sg:classifiers":[
        {
            "category":"Professional",
            "subcategory":"Printing & Photocopies",
            "type":"Services"
        }
    ],
    "sg:phone":"+33 3 80 91 08 65",
    "sg:postcode":"21400",
    "sg:province":"Bourgogne",
    "sg:tags":[
        "publishing"
    ],
    "wof:name":"Societe Nouvelle D'imprimerie (sni)",
    "wof:placetype":"venue"
},
  "geometry": {"coordinates":[4.574546,47.862225],"type":"Point"}
}