{
  "type": "Feature",
  "properties": {
    "iso:country":"FR",
    "sg:address":"74, Rue Maryse Basti\u00e9 - ZI de la Lauze, 34430 Saint Jean de V\u00e9das",
    "sg:orig_category":"Unclassifiable Establishments",
    "sg:phone":"+33 4 67 42 89 57",
    "sg:province":"Languedoc-Roussillon",
    "wof:name":"Locamion S.a.",
    "wof:placetype":"venue"
},
  "geometry": {"coordinates":[3.8289,43.575985],"type":"Point"}
}