{
  "type": "Feature",
  "properties": {
    "addr:full":"6, Rue Ernest Cazenave, 64110 Juran\u00e7on Juran\u00e7on Aquitaine 64110",
    "addr:housenumber":"6",
    "addr:postcode":"64110;64110",
    "addr:street":"Rue Ernest Cazenave",
    "iso:country":"FR",
    "sg:address":"6, Rue Ernest Cazenave, 64110 Juran\u00e7on",
    "sg:city":"Juran\u00e7on",
    "sg:orig_category":"Non-Classified Establishments",
    "sg:phone":"+33 5 59 06 55 85",
    "sg:postcode":"64110",
    "sg:province":"Aquitaine",
    "wof:name":"Groupe A.p.r. S.a.",
    "wof:placetype":"venue"
},
  "geometry": {"coordinates":[-0.390128,43.288136],"type":"Point"}
}