{
  "type": "Feature",
  "properties": {
    "iso:country":"FR",
    "sg:address":"101 Zone Industrielle Trusey 88390 Chaumousey",
    "sg:classifiers":[
        {
            "category":"Manufacturing",
            "subcategory":"Metals",
            "type":"Manufacturing & Wholesale Goods"
        }
    ],
    "sg:phone":"+33 3 29 66 85 48",
    "sg:postcode":"88390",
    "sg:province":"Lorraine",
    "sg:tags":[
        "metallurgy",
        "steel",
        "metalworking"
    ],
    "wof:name":"Comesse Soudure (sa)",
    "wof:placetype":"venue"
},
  "geometry": {"coordinates":[6.37188,48.193356],"type":"Point"}
}