{
  "type": "Feature",
  "properties": {
    "addr:full":"Za La Varenne 28200 Marbou\u00e9 Marbou\u00e9 Centre 28200",
    "addr:housenumber":"marboue\u0301",
    "addr:postcode":"28200;28200",
    "addr:street":"Za La Varenne",
    "iso:country":"FR",
    "sg:address":"Za La Varenne 28200 Marbou\u00e9",
    "sg:city":"Marbou\u00e9",
    "sg:classifiers":[
        {
            "category":"Manufacturing",
            "subcategory":"Metals",
            "type":"Manufacturing & Wholesale Goods"
        }
    ],
    "sg:phone":"+33 2 37 94 08 20",
    "sg:postcode":"28200",
    "sg:province":"Centre",
    "sg:tags":[
        "metallurgy",
        "metalworking",
        "processing"
    ],
    "wof:name":"Societe Industrielle Et Commerciale Des Yvelines Sicy Sicy",
    "wof:placetype":"venue"
},
  "geometry": {"coordinates":[1.330185,48.113377],"type":"Point"}
}