{
  "type": "Feature",
  "properties": {
    "iso:country":"FR",
    "sg:address":"557 Rue Andre Le Notre Residence Fontaine Aux Roses 34080 Montpellier",
    "sg:classifiers":[
        {
            "category":"Wholesale",
            "subcategory":"Machinery & Supplies",
            "type":"Manufacturing & Wholesale Goods"
        }
    ],
    "sg:phone":"+33 4 67 10 39 39",
    "sg:postcode":"34080",
    "sg:province":"Languedoc-Roussillon",
    "sg:tags":[
        "handling",
        "material",
        "-",
        "machine",
        "equipment",
        "engineering",
        "mechanical"
    ],
    "wof:name":"Batilift Service",
    "wof:placetype":"venue"
},
  "geometry": {"coordinates":[3.823861,43.614876],"type":"Point"}
}