{
  "type": "Feature",
  "properties": {
    "addr:full":"4, Villa des Numpheas, 75020 Paris Ile de France",
    "addr:housenumber":"4",
    "addr:postcode":"75020",
    "addr:street":"Villa Des Numpheas",
    "iso:country":"FR",
    "sg:address":"4, Villa des Numpheas, 75020 Paris",
    "sg:orig_category":"Unclassifiable Establishments",
    "sg:phone":"+33 1 40 32 49 99",
    "sg:province":"Ile de France",
    "wof:name":"2.g. Graphic S.a.r.l.",
    "wof:placetype":"venue"
},
  "geometry": {"coordinates":[2.399365,48.864849],"type":"Point"}
}