{
  "type": "Feature",
  "properties": {
    "iso:country":"FR",
    "sg:address":"Rue Du Champ De Tir Zi Cambrai- Cantimpre 59400 Cambrai",
    "sg:classifiers":[
        {
            "category":"Building & Trades",
            "subcategory":"Construction",
            "type":"Services"
        }
    ],
    "sg:phone":"+33 3 27 78 12 11",
    "sg:postcode":"59400",
    "sg:province":"Nord Pas-de-Calais",
    "sg:tags":[
        "work",
        "public"
    ],
    "wof:name":"Stpv",
    "wof:placetype":"venue"
},
  "geometry": {"coordinates":[3.23419,50.175018],"type":"Point"}
}