{
  "type": "Feature",
  "properties": {
    "addr:full":"31 Av Luxembourg 51460 L'Epine Champagne 51460",
    "addr:postcode":"51460;51460",
    "addr:street":"31 Av;Champagne",
    "iso:country":"FR",
    "sg:address":"31 Av Luxembourg 51460 L'Epine",
    "sg:classifiers":[
        {
            "category":"Travel",
            "subcategory":"Hotels & Motels",
            "type":"Entertainment"
        }
    ],
    "sg:phone":"+33 3 26 69 30 30",
    "sg:postcode":"51460",
    "sg:province":"Champagne",
    "sg:tags":[
        "hotels",
        "business",
        "restaurant"
    ],
    "wof:name":"Armes De Champagne Sa",
    "wof:placetype":"venue"
},
  "geometry": {"coordinates":[4.470476,48.977581],"type":"Point"}
}