{
  "type": "Feature",
  "properties": {
    "addr:full":"Centre d'Affaires Espace Performance B\u00e2t. M1 Saint Gr\u00e9goire C\u00e9dex Brittany 35769",
    "addr:housenumber":"ba\u0302t",
    "addr:postcode":"35769",
    "iso:country":"FR",
    "sg:address":"Centre d'Affaires Espace Performance B\u00e2t. M1",
    "sg:city":"Saint Gr\u00e9goire C\u00e9dex",
    "sg:orig_category":"Non-Classified Establishments",
    "sg:phone":"+33 2 99 23 45 23",
    "sg:postcode":"35769",
    "sg:province":"Brittany",
    "wof:name":"Syseca S.a.",
    "wof:placetype":"venue"
},
  "geometry": {"coordinates":[-1.68273,48.153191],"type":"Point"}
}