{
  "type": "Feature",
  "properties": {
    "addr:full":"ALLEE DU CLOS DES CHARMES 77090 Collegien Ile de France 77090",
    "addr:postcode":"77090;77090",
    "addr:street":"Allee Du Clos Des Charmes;Ile De France",
    "iso:country":"FR",
    "sg:address":"ALLEE DU CLOS DES CHARMES 77090 Collegien",
    "sg:orig_category":"Magnetic Vane Flow-Meters",
    "sg:phone":"+33 1 60 17 45 54",
    "sg:postcode":"77090",
    "sg:province":"Ile de France",
    "wof:name":"T.a.s. Sarl",
    "wof:placetype":"venue"
},
  "geometry": {"coordinates":[2.674529,48.830166],"type":"Point"}
}