{
  "type": "Feature",
  "properties": {
    "addr:full":"Rue Du Terroir Rue Du Terroir 31140 St Alban Midi Pyr\u00e9n\u00e9es",
    "addr:postcode":"31140",
    "addr:street":"Rue Du;Rue Du Terroir",
    "iso:country":"FR",
    "sg:address":"Rue Du Terroir Rue Du Terroir 31140 St Alban",
    "sg:classifiers":[
        {
            "category":"Manufacturing",
            "subcategory":"Rubber & Plastics",
            "type":"Manufacturing & Wholesale Goods"
        }
    ],
    "sg:phone":"+33 5 61 35 98 04",
    "sg:province":"Midi Pyr\u00e9n\u00e9es",
    "wof:name":"Toulousaine De Rechapage A Froid",
    "wof:placetype":"venue"
},
  "geometry": {"coordinates":[1.429025,43.668308],"type":"Point"}
}