{
  "type": "Feature",
  "properties": {
    "addr:full":"Rue des Champs Saint Marcel Haute Normandie 27950",
    "addr:postcode":"27950",
    "addr:street":"Rue Des Champs Saint;Haute Normandie",
    "iso:country":"FR",
    "sg:address":"Rue des Champs",
    "sg:city":"Saint Marcel",
    "sg:orig_category":"Unclassifiable Establishments",
    "sg:phone":"+33 2 32 51 95 03",
    "sg:postcode":"27950",
    "sg:province":"Haute Normandie",
    "wof:name":"Rastello S.a.",
    "wof:placetype":"venue"
},
  "geometry": {"coordinates":[1.455555,49.100601],"type":"Point"}
}