{
  "type": "Feature",
  "properties": {
    "addr:full":"8 Place De La Fraternit\u00e9 93100 Montreuil Ile de France 93100",
    "addr:housenumber":"8",
    "addr:postcode":"93100;93100",
    "addr:street":"Place De La Fraternite\u0301",
    "iso:country":"FR",
    "sg:address":"8 Place De La Fraternit\u00e9 93100 Montreuil",
    "sg:classifiers":[
        {
            "category":"Home & Garden",
            "subcategory":"Furniture",
            "type":"Retail Goods"
        }
    ],
    "sg:phone":"+33 1 42 87 56 21",
    "sg:postcode":"93100",
    "sg:province":"Ile de France",
    "sg:tags":[
        "household",
        "wood"
    ],
    "wof:name":"Hecquet Meubles Sa",
    "wof:placetype":"venue"
},
  "geometry": {"coordinates":[2.422367,48.856815],"type":"Point"}
}