{
  "type": "Feature",
  "properties": {
    "addr:full":"7 rue Biscornet 75012 Paris Ile de France 75012",
    "addr:housenumber":"7",
    "addr:postcode":"75012;75012",
    "addr:street":"Rue Biscornet",
    "iso:country":"FR",
    "sg:address":"7 rue Biscornet 75012 Paris",
    "sg:classifiers":[
        {
            "category":"Utilities",
            "subcategory":"Natural Gas",
            "type":"Services"
        }
    ],
    "sg:phone":"+33 1 43 42 57 42",
    "sg:postcode":"75012",
    "sg:province":"Ile de France",
    "sg:tags":[
        "turbine"
    ],
    "wof:name":"Turbomach Energie Sa",
    "wof:placetype":"venue"
},
  "geometry": {"coordinates":[2.369623,48.850071],"type":"Point"}
}