{
  "type": "Feature",
  "properties": {
    "addr:full":"5, Rte deTours, 37150 Bl\u00e9r\u00e9 Bl\u00e9r\u00e9 Centre 37150",
    "addr:housenumber":"5",
    "addr:postcode":"37150;37150",
    "addr:street":"Rte Detours",
    "iso:country":"FR",
    "sg:address":"5, Rte deTours, 37150 Bl\u00e9r\u00e9",
    "sg:city":"Bl\u00e9r\u00e9",
    "sg:orig_category":"Unclassifiable Establishments",
    "sg:phone":"+33 2 47 57 89 86",
    "sg:postcode":"37150",
    "sg:province":"Centre",
    "wof:name":"Bodin S.a.",
    "wof:placetype":"venue"
},
  "geometry": {"coordinates":[1.049415,47.247349],"type":"Point"}
}