{
  "type": "Feature",
  "properties": {
    "iso:country":"FR",
    "sg:address":"B.P. 37, 78114 Magny les Hameaux^^6, Rue Am\u00e9d\u00e9e Gordini - Zone de Gomberville, 78114 Magny les Hamea",
    "sg:orig_category":"Non-Classified Establishments",
    "sg:phone":"+33 1 30 23 43 00",
    "sg:postcode":"78114",
    "sg:province":"Ile de France",
    "wof:name":"Argos Arts Graphiques S.a.",
    "wof:placetype":"venue"
},
  "geometry": {"coordinates":[2.103455,48.71944],"type":"Point"}
}