{
  "type": "Feature",
  "properties": {
    "addr:full":"Rte St Martin Bossenay 10350 Marigny Le Ch\u00e2tel Champagne 10350",
    "addr:housenumber":"cha\u0302tel",
    "addr:postcode":"10350;10350",
    "addr:street":"Rte St;Bossenay;Champagne",
    "iso:country":"FR",
    "sg:address":"Rte St Martin Bossenay 10350 Marigny Le Ch\u00e2tel",
    "sg:classifiers":[
        {
            "category":"Farming",
            "subcategory":"Farm & Veterinary Services",
            "type":"Manufacturing & Wholesale Goods"
        }
    ],
    "sg:phone":"+33 3 25 21 61 38",
    "sg:postcode":"10350",
    "sg:province":"Champagne",
    "sg:tags":[
        "food",
        "product",
        "breeding",
        "animal",
        "related"
    ],
    "wof:name":"Coop\u00c9rative Agricole De D\u00c9shydratation",
    "wof:placetype":"venue"
},
  "geometry": {"coordinates":[3.73591,48.403301],"type":"Point"}
}