{
  "type": "Feature",
  "properties": {
    "addr:full":"B.P. 101, 57570 Cattenom^^Rue du Luxembourg, 57570 Cattenom Lorraine",
    "addr:housenumber":"b.p. 101",
    "addr:postcode":"57570;57570",
    "iso:country":"FR",
    "sg:address":"B.P. 101, 57570 Cattenom^^Rue du Luxembourg, 57570 Cattenom",
    "sg:orig_category":"Non-Classified Establishments",
    "sg:phone":"+33 3 82 55 40 11",
    "sg:province":"Lorraine",
    "wof:name":"Sabli\u00e8res De Sentzich S.a.r.l.",
    "wof:placetype":"venue"
},
  "geometry": {"coordinates":[6.23811,49.406609],"type":"Point"}
}