{
  "type": "Feature",
  "properties": {
    "addr:full":"B.P. 315, 92003 Nanterre C\u00e9dex^^11, Av. Fran\u00e7ois Arago, 92000 Nanterre Ile de France",
    "addr:housenumber":"b.p. 315",
    "addr:postcode":"92003;92000",
    "addr:street":"Av. Franc\u0327Ois Arago",
    "iso:country":"FR",
    "sg:address":"B.P. 315, 92003 Nanterre C\u00e9dex^^11, Av. Fran\u00e7ois Arago, 92000 Nanterre",
    "sg:orig_category":"Non-Classified Establishments",
    "sg:phone":"+33 800 07 00 80",
    "sg:province":"Ile de France",
    "wof:name":"Stellram S.a.",
    "wof:placetype":"venue"
},
  "geometry": {"coordinates":[2.194875,48.888084],"type":"Point"}
}