{
  "type": "Feature",
  "properties": {
    "addr:full":"B.P. 57, 80082 Amiens C\u00e9dex 2^^Rue Andr\u00e9 Durouchez - ZI, 80000 Amiens Picardie",
    "addr:postcode":"80082;80000",
    "addr:street":"B.P. 57;Zi",
    "iso:country":"FR",
    "sg:address":"B.P. 57, 80082 Amiens C\u00e9dex 2^^Rue Andr\u00e9 Durouchez - ZI, 80000 Amiens",
    "sg:orig_category":"Non-Classified Establishments",
    "sg:phone":"+33 3 22 54 31 31",
    "sg:province":"Picardie",
    "wof:name":"Gefco Transports S.a.",
    "wof:placetype":"venue"
},
  "geometry": {"coordinates":[2.293165,49.894733],"type":"Point"}
}