{
  "type": "Feature",
  "properties": {
    "addr:full":"9/11, Rue Danton, 42000 Saint Etienne Rhone-Alpes 42000",
    "addr:housenumber":"9 / 11",
    "addr:postcode":"42000;42000",
    "addr:street":"Rue Danton",
    "iso:country":"FR",
    "sg:address":"9/11, Rue Danton, 42000 Saint Etienne",
    "sg:orig_category":"Unclassifiable Establishments",
    "sg:phone":"+33 4 77 32 28 73",
    "sg:postcode":"42000",
    "sg:province":"Rhone-Alpes",
    "wof:name":"Etablissements Bonnassieux P\u00e8re Et Fils S.a.r.l.",
    "wof:placetype":"venue"
},
  "geometry": {"coordinates":[4.366714,45.443703],"type":"Point"}
}