{
  "type": "Feature",
  "properties": {
    "addr:full":"Zi La Couperigne 13127 Vitrolles Centre",
    "addr:postcode":"13127",
    "addr:street":"Zi La Couperigne",
    "iso:country":"FR",
    "sg:address":"Zi La Couperigne 13127 Vitrolles",
    "sg:classifiers":[
        {
            "category":"Professional",
            "subcategory":"Advertising",
            "type":"Services"
        }
    ],
    "sg:phone":"+33 4 42 10 01 01",
    "sg:province":"Centre",
    "sg:tags":[
        "communication",
        "medium"
    ],
    "wof:name":"Promo Inter France Sa",
    "wof:placetype":"venue"
},
  "geometry": {"coordinates":[5.253005,43.449944],"type":"Point"}
}