{
  "type": "Feature",
  "properties": {
    "addr:full":"9, Rue de Cond\u00e9 Bordeaux Cedex 33064",
    "addr:housenumber":"9",
    "addr:postcode":"bordeaux cedex 33064",
    "addr:street":"Rue De Conde\u0301",
    "iso:country":"FR",
    "sg:address":"9, Rue de Cond\u00e9",
    "sg:city":"Bordeaux Cedex",
    "sg:classifiers":[
        {
            "category":"Professional",
            "subcategory":"Computer Services",
            "type":"Services"
        }
    ],
    "sg:postcode":"33064",
    "sg:tags":[
        "mobile",
        "cell-phone"
    ],
    "sg:website":"http://www.roundbox.com",
    "wof:name":"Roundbox",
    "wof:placetype":"venue"
},
  "geometry": {"coordinates":[-0.573256,44.843559],"type":"Point"}
}