{
  "type": "Feature",
  "properties": {
    "iso:country":"FR",
    "sg:address":"2-4 Rue Franklin 69740 Genas",
    "sg:classifiers":[
        {
            "category":"Manufacturing",
            "subcategory":"Tools & Machinery",
            "type":"Manufacturing & Wholesale Goods"
        }
    ],
    "sg:phone":"+33 4 72 47 38 10",
    "sg:postcode":"69740",
    "sg:province":"Rhone-Alpes",
    "sg:tags":[
        "equipment",
        "measurement",
        "-",
        "precision",
        "instrument"
    ],
    "wof:name":"Actaris",
    "wof:placetype":"venue"
},
  "geometry": {"coordinates":[4.994668,45.713802],"type":"Point"}
}