{
  "type": "Feature",
  "properties": {
    "addr:full":"B.P. 2, 83520 Roquebrune sur Argens^^Domaine de Palayson, 83520 Roquebrune sur Argens Provence-Alpes-C\u00f4te d'Azur",
    "addr:housenumber":"2",
    "addr:postcode":"83520;83520",
    "addr:street":"B.P.;Argens",
    "iso:country":"FR",
    "sg:address":"B.P. 2, 83520 Roquebrune sur Argens^^Domaine de Palayson, 83520 Roquebrune sur Argens",
    "sg:orig_category":"Non-Classified Establishments",
    "sg:phone":"+33 4 94 19 55 55",
    "sg:province":"Provence-Alpes-C\u00f4te d'Azur",
    "wof:name":"Scetauroute",
    "wof:placetype":"venue"
},
  "geometry": {"coordinates":[6.64088,43.44437],"type":"Point"}
}