{
  "type": "Feature",
  "properties": {
    "iso:country":"FR",
    "sg:address":"Le Mesnil 14111 Louvigny",
    "sg:city":"Louvigny",
    "sg:classifiers":[
        {
            "category":"Professional",
            "subcategory":"Engineering",
            "type":"Services"
        }
    ],
    "sg:phone":"+33 2 31 29 14 20",
    "sg:postcode":"14111",
    "sg:province":"Basse Normandie",
    "sg:tags":[
        "machine",
        "-",
        "mechanical"
    ],
    "wof:name":"Caen Froid Sa",
    "wof:placetype":"venue"
},
  "geometry": {"coordinates":[-0.407094,49.164059],"type":"Point"}
}