{
  "type": "Feature",
  "properties": {
    "iso:country":"FR",
    "sg:address":"15, Rue du Colonel Fabien, 92160 Antony",
    "sg:orig_category":"Unclassifiable Establishments",
    "sg:phone":"+33 1 46 66 87 86",
    "sg:province":"Ile de France",
    "wof:name":"Desjonqueres Parcs Et Jardins S.a.r.l.",
    "wof:placetype":"venue"
},
  "geometry": {"coordinates":[2.289857,48.753788],"type":"Point"}
}