{
  "type": "Feature",
  "properties": {
    "addr:full":"253, Rte du Bouchet, 74920 Combloux Rhone-Alpes 74920",
    "addr:housenumber":"253",
    "addr:postcode":"74920;74920",
    "addr:street":"Rte Du Bouchet",
    "iso:country":"FR",
    "sg:address":"253, Rte du Bouchet, 74920 Combloux",
    "sg:orig_category":"Unclassifiable Establishments",
    "sg:phone":"+33 4 50 58 61 43",
    "sg:postcode":"74920",
    "sg:province":"Rhone-Alpes",
    "wof:name":"Aux Ducs De Savoie",
    "wof:placetype":"venue"
},
  "geometry": {"coordinates":[6.629635,45.900036],"type":"Point"}
}