{
  "type": "Feature",
  "properties": {
    "iso:country":"FR",
    "sg:address":"55, Quai de Grenelle, 75015 Paris",
    "sg:orig_category":"Unclassifiable Establishments",
    "sg:phone":"+33 1 56 77 10 10",
    "sg:province":"Ile de France",
    "wof:name":"Synetics S.a.",
    "wof:placetype":"venue"
},
  "geometry": {"coordinates":[2.283883,48.850403],"type":"Point"}
}