{
  "type": "Feature",
  "properties": {
    "addr:full":"6 Rue Edouard Branly 45100 Orleans Orl\u00e9ans Centre 45100",
    "addr:housenumber":"6",
    "addr:postcode":"45100;45100",
    "addr:street":"Rue Edouard Branly",
    "iso:country":"FR",
    "sg:address":"6 Rue Edouard Branly 45100 Orleans",
    "sg:city":"Orl\u00e9ans",
    "sg:classifiers":[
        {
            "category":"Utilities",
            "subcategory":"Telephone",
            "type":"Services"
        }
    ],
    "sg:phone":"+33 2 38 41 32 82",
    "sg:postcode":"45100",
    "sg:province":"Centre",
    "sg:tags":[
        "telecommunication"
    ],
    "wof:name":"Compagnie Francaise De Telecommunication (cofratel)",
    "wof:placetype":"venue"
},
  "geometry": {"coordinates":[1.933873,47.833569],"type":"Point"}
}