{
  "type": "Feature",
  "properties": {
    "addr:full":"B.P. 1, 25480 Miserey Salines^^Rue de Vesoul - Lieu dit Planche du Mont , 25480 Miserey Salines Franche Comt\u00e9",
    "addr:housenumber":"1",
    "addr:postcode":"25480;25480",
    "addr:street":"B.P.;Dit Planche Du Mont;Franche Comte\u0301",
    "iso:country":"FR",
    "sg:address":"B.P. 1, 25480 Miserey Salines^^Rue de Vesoul - Lieu dit Planche du Mont , 25480 Miserey Salines",
    "sg:orig_category":"Non-Classified Establishments",
    "sg:phone":"+33 3 81 53 27 76",
    "sg:province":"Franche Comt\u00e9",
    "wof:name":"Obliger S.a.",
    "wof:placetype":"venue"
},
  "geometry": {"coordinates":[5.982078,47.27187],"type":"Point"}
}