{
  "type": "Feature",
  "properties": {
    "iso:country":"FR",
    "sg:address":"7, Rue du T\u00e9, 95700 Roissy en France",
    "sg:orig_category":"Unclassifiable Establishments",
    "sg:phone":"+33 1 48 62 26 55",
    "sg:province":"Ile de France",
    "wof:name":"F.i.r.s.t. S.a.r.l. - Fret International Rapide Service Transit",
    "wof:placetype":"venue"
},
  "geometry": {"coordinates":[2.517005,49.003883],"type":"Point"}
}