{
  "type": "Feature",
  "properties": {
    "addr:full":"Zi La Gaiet\u00e9 69550 Amplepuis Rhone-Alpes",
    "addr:postcode":"69550",
    "addr:street":"Zi La Gaiete\u0301",
    "iso:country":"FR",
    "sg:address":"Zi La Gaiet\u00e9 69550 Amplepuis",
    "sg:classifiers":[
        {
            "category":"Shopping",
            "type":"Retail Goods"
        }
    ],
    "sg:phone":"+33 4 74 89 45 93",
    "sg:province":"Rhone-Alpes",
    "sg:tags":[
        "metallurgy",
        "finished",
        "-",
        "metalworking",
        "metallic"
    ],
    "wof:name":"Soustraitance Industrie & Agricole",
    "wof:placetype":"venue"
},
  "geometry": {"coordinates":[4.33278,45.973209],"type":"Point"}
}