{
  "type": "Feature",
  "properties": {
    "addr:full":"B.P. 8, 77564 Lieusaint C\u00e9dex^^Bd Luxembourg - PA Paris Sud, 77127 Lieusaint Ile de France",
    "addr:housenumber":"8",
    "addr:postcode":"77564;77127;ile",
    "addr:street":"B.P.",
    "iso:country":"FR",
    "sg:address":"B.P. 8, 77564 Lieusaint C\u00e9dex^^Bd Luxembourg - PA Paris Sud, 77127 Lieusaint",
    "sg:orig_category":"Non-Classified Establishments",
    "sg:phone":"+33 1 64 88 05 00",
    "sg:province":"Ile de France",
    "wof:name":"Exapaq Paris Sud S.a.r.l.",
    "wof:placetype":"venue"
},
  "geometry": {"coordinates":[2.551919,48.63187],"type":"Point"}
}