{
  "type": "Feature",
  "properties": {
    "iso:country":"FR",
    "sg:address":"Z I de Bellevue Nord 42440 Noiretable",
    "sg:classifiers":[
        {
            "category":"Social Services",
            "subcategory":"Retirement Home",
            "type":"Services"
        }
    ],
    "sg:phone":"+33 4 77 97 74 75",
    "sg:postcode":"42440",
    "sg:province":"Rhone-Alpes",
    "sg:tags":[
        "cutlery",
        "camping"
    ],
    "wof:name":"Amefa France Sa",
    "wof:placetype":"venue"
},
  "geometry": {"coordinates":[3.74716,45.747978],"type":"Point"}
}