{
  "type": "Feature",
  "properties": {
    "addr:full":"75, Rue de la Roquette, 75011 Paris Ile de France",
    "addr:housenumber":"75",
    "addr:postcode":"75011",
    "addr:street":"Rue De La Roquette",
    "iso:country":"FR",
    "sg:address":"75, Rue de la Roquette, 75011 Paris",
    "sg:orig_category":"Non-Classified Establishments",
    "sg:phone":"+33 1 43 70 84 64",
    "sg:province":"Ile de France",
    "wof:name":"Happlaincourt S.a.r.l.",
    "wof:placetype":"venue"
},
  "geometry": {"coordinates":[2.377293,48.85672],"type":"Point"}
}