{
  "type": "Feature",
  "properties": {
    "addr:full":"11bis route de Gaillac 81500 Lavaur Midi Pyr\u00e9n\u00e9es 81500",
    "addr:housenumber":"11bis",
    "addr:postcode":"81500;81500",
    "addr:street":"Route De Gaillac",
    "iso:country":"FR",
    "sg:address":"11bis route de Gaillac 81500 Lavaur",
    "sg:classifiers":[
        {
            "category":"Food & Beverages",
            "subcategory":"Fruits & Vegetables",
            "type":"Retail Goods"
        }
    ],
    "sg:phone":"+33 5 63 58 01 72",
    "sg:postcode":"81500",
    "sg:province":"Midi Pyr\u00e9n\u00e9es",
    "wof:name":"Fruits Legumes Des Deux Vall\u00e9es Coop",
    "wof:placetype":"venue"
},
  "geometry": {"coordinates":[1.820658,43.705296],"type":"Point"}
}