{
  "type": "Feature",
  "properties": {
    "addr:full":"78, Chemin du Boeuf, 38330 Biviers Rhone-Alpes 38330",
    "addr:housenumber":"78",
    "addr:postcode":"38330;38330",
    "addr:street":"Chemin Du Boeuf;Rhone-Alpes",
    "iso:country":"FR",
    "sg:address":"78, Chemin du Boeuf, 38330 Biviers",
    "sg:orig_category":"Unclassifiable Establishments",
    "sg:phone":"+33 4 76 52 92 92",
    "sg:postcode":"38330",
    "sg:province":"Rhone-Alpes",
    "wof:name":"Allan Et Morisson S.a.",
    "wof:placetype":"venue"
},
  "geometry": {"coordinates":[5.809128,45.233704],"type":"Point"}
}