{
  "type": "Feature",
  "properties": {
    "iso:country":"FR",
    "sg:address":"28 Rue De La Mairie Cap Ferret",
    "sg:city":"Lege Cap Ferret",
    "sg:classifiers":[
        {
            "category":"Banks & Credit Unions",
            "subcategory":"Financial Services",
            "type":"Services"
        }
    ],
    "sg:phone":"+33 5 56 60 47 47",
    "sg:postcode":"33950",
    "sg:province":"Aquitaine",
    "sg:tags":[
        "banking",
        "finance",
        "insurance"
    ],
    "wof:name":"Societe Fiduciaire Nationale D'expertise Comptable Fidexpert (fid)",
    "wof:placetype":"venue"
},
  "geometry": {"coordinates":[-1.146812,44.795296],"type":"Point"}
}