{
  "type": "Feature",
  "properties": {
    "iso:country":"FR",
    "sg:address":"Technoparc du Circuit des 24 Heures",
    "sg:city":"Le Mans",
    "sg:orig_category":"Unclassifiable Establishments",
    "sg:phone":"+33 2 43 21 51 51",
    "sg:postcode":"72000",
    "sg:province":"Pays de Loire",
    "wof:name":"Euro 3 D S.a.",
    "wof:placetype":"venue"
},
  "geometry": {"coordinates":[0.205975,47.956394],"type":"Point"}
}