{
  "type": "Feature",
  "properties": {
    "iso:country":"FR",
    "sg:address":"148 Rue Du Grand Gigognan 84000 Avignon",
    "sg:classifiers":[
        {
            "category":"Utilities",
            "subcategory":"Telephone",
            "type":"Services"
        }
    ],
    "sg:phone":"+33 4 90 85 33 00",
    "sg:province":"Lorraine",
    "sg:tags":[
        "telecommunication"
    ],
    "wof:name":"Sud Telecom Sa",
    "wof:placetype":"venue"
},
  "geometry": {"coordinates":[4.785824,43.933079],"type":"Point"}
}