{
  "type": "Feature",
  "properties": {
    "addr:full":"B.P. 42, 69572 Dardilly C\u00e9dex^^10, Chemin Gorges - Parc d'Affaires, 69570 Dardilly Rhone-Alpes",
    "addr:postcode":"69572;69570",
    "addr:street":"B.P. 42;Chemin Gorges Parc D'Affaires",
    "iso:country":"FR",
    "sg:address":"B.P. 42, 69572 Dardilly C\u00e9dex^^10, Chemin Gorges - Parc d'Affaires, 69570 Dardilly",
    "sg:orig_category":"Non-Classified Establishments",
    "sg:phone":"+33 4 78 35 37 95",
    "sg:province":"Rhone-Alpes",
    "wof:name":"Sterling Fluid Systems France S.a.",
    "wof:placetype":"venue"
},
  "geometry": {"coordinates":[4.765638,45.807957],"type":"Point"}
}