{
  "type": "Feature",
  "properties": {
    "iso:country":"FR",
    "sg:address":"55, Av. Louis Br\u00e9guet - B\u00e2t. 7, 31400 Toulouse",
    "sg:orig_category":"Unclassifiable Establishments",
    "sg:phone":"+33 5 61 33 10 07",
    "sg:province":"Midi Pyr\u00e9n\u00e9es",
    "wof:name":"Image S.a.r.l.",
    "wof:placetype":"venue"
},
  "geometry": {"coordinates":[1.47942,43.57724],"type":"Point"}
}