{
  "type": "Feature",
  "properties": {
    "iso:country":"FR",
    "sg:address":"4 Avenue Marceau",
    "sg:city":"Paris",
    "sg:classifiers":[
        {
            "category":"Banks & Credit Unions",
            "subcategory":"Financial Services",
            "type":"Services"
        }
    ],
    "sg:phone":"+33 1 53 57 31 31",
    "sg:postcode":"75008",
    "sg:province":"Ile de France",
    "sg:tags":[
        "banking",
        "finance",
        "insurance"
    ],
    "wof:name":"La Tete Dans Les Nuages Sarl",
    "wof:placetype":"venue"
},
  "geometry": {"coordinates":[2.300172,48.865383],"type":"Point"}
}