{
  "type": "Feature",
  "properties": {
    "addr:full":"45, Chemin des Bourdettes, 31140 Aucamville Midi Pyr\u00e9n\u00e9es 31140",
    "addr:housenumber":"45",
    "addr:postcode":"31140;31140",
    "addr:street":"Chemin Des Bourdettes",
    "iso:country":"FR",
    "sg:address":"45, Chemin des Bourdettes, 31140 Aucamville",
    "sg:orig_category":"Non-Classified Establishments",
    "sg:phone":"+33 5 61 70 29 66",
    "sg:postcode":"31140",
    "sg:province":"Midi Pyr\u00e9n\u00e9es",
    "wof:name":"Etablissements Carcy S.a.",
    "wof:placetype":"venue"
},
  "geometry": {"coordinates":[1.429702,43.672035],"type":"Point"}
}