{
  "type": "Feature",
  "properties": {
    "iso:country":"FR",
    "sg:address":"2, Rue de Nozay, 44170 Abbaretz",
    "sg:orig_category":"Unclassifiable Establishments",
    "sg:phone":"+33 2 40 87 01 26",
    "sg:province":"Pays de Loire",
    "wof:name":"Etablissement Duquait-seba S.a.",
    "wof:placetype":"venue"
},
  "geometry": {"coordinates":[-1.529044,47.553631],"type":"Point"}
}