{
  "type": "Feature",
  "properties": {
    "iso:country":"FR",
    "sg:address":"7 Rue Des Pyr\u00e9n\u00e9es 68390 Sausheim",
    "sg:city":"Sausheim",
    "sg:classifiers":[
        {
            "category":"Manufacturing",
            "subcategory":"Metals",
            "type":"Manufacturing & Wholesale Goods"
        }
    ],
    "sg:phone":"+33 3 89 61 98 43",
    "sg:postcode":"68390",
    "sg:province":"Alsace",
    "sg:tags":[
        "pipe",
        "sheet",
        "-",
        "metalworking",
        "metallic",
        "metallurgy",
        "finished"
    ],
    "wof:name":"Egtim",
    "wof:placetype":"venue"
},
  "geometry": {"coordinates":[7.389298,47.774429],"type":"Point"}
}