{
  "type": "Feature",
  "properties": {
    "iso:country":"FR",
    "sg:address":"6, Place de l'Homme de Fer, 67000 Strasbourg",
    "sg:city":"Strasbourg",
    "sg:orig_category":"Non-Classified Establishments",
    "sg:phone":"+33 3 88 32 08 00",
    "sg:postcode":"67000",
    "sg:province":"Alsace",
    "wof:name":"Lacour S.a.r.l.",
    "wof:placetype":"venue"
},
  "geometry": {"coordinates":[7.744596,48.583866],"type":"Point"}
}