{
  "type": "Feature",
  "properties": {
    "addr:full":"10, Mont\u00e9e Saint Jean, 73370 Le Bourget du Lac Rhone-Alpes",
    "addr:housenumber":"10",
    "addr:postcode":"73370",
    "addr:street":"Monte\u0301E Saint Jean",
    "iso:country":"FR",
    "sg:address":"10, Mont\u00e9e Saint Jean, 73370 Le Bourget du Lac",
    "sg:orig_category":"Unclassifiable Establishments",
    "sg:phone":"+33 4 79 26 15 91",
    "sg:province":"Rhone-Alpes",
    "wof:name":"P.m.b. Consultants",
    "wof:placetype":"venue"
},
  "geometry": {"coordinates":[5.859883,45.643948],"type":"Point"}
}