{
  "type": "Feature",
  "properties": {
    "iso:country":"FR",
    "sg:address":"B.P. 1",
    "sg:city":"Tiranges",
    "sg:orig_category":"Non-Classified Establishments",
    "sg:phone":"+33 4 71 61 32 51",
    "sg:postcode":"43130",
    "sg:province":"Auvergne",
    "wof:name":"Collange Et Fils S.a.r.l.",
    "wof:placetype":"venue"
},
  "geometry": {"coordinates":[4.03258,45.205246],"type":"Point"}
}