{
  "type": "Feature",
  "properties": {
    "addr:full":"rue Jules Ferry 77173 Chevry Cossigny Ile de France 77173",
    "addr:postcode":"77173;ile;77173",
    "addr:street":"Rue Jules Ferry;France",
    "iso:country":"FR",
    "sg:address":"rue Jules Ferry 77173 Chevry Cossigny",
    "sg:classifiers":[
        {
            "category":"Shopping",
            "subcategory":"Crafts & Fabrics",
            "type":"Retail Goods"
        }
    ],
    "sg:phone":"+33 1 64 05 20 23",
    "sg:postcode":"77173",
    "sg:province":"Ile de France",
    "sg:tags":[
        "brush"
    ],
    "wof:name":"Brosserie Thomas Sa",
    "wof:placetype":"venue"
},
  "geometry": {"coordinates":[2.67069,48.728344],"type":"Point"}
}