{
  "type": "Feature",
  "properties": {
    "addr:full":"B.P. 25, 82030 Montauban C\u00e9dex^^March\u00e9 Gare, 82000 Montauban Midi Pyr\u00e9n\u00e9es 82000",
    "addr:postcode":"82030;82000;82000",
    "addr:street":"B.P. 25;Gare",
    "iso:country":"FR",
    "sg:address":"B.P. 25, 82030 Montauban C\u00e9dex^^March\u00e9 Gare, 82000 Montauban",
    "sg:orig_category":"Non-Classified Establishments",
    "sg:phone":"+33 5 63 03 29 78",
    "sg:postcode":"82000",
    "sg:province":"Midi Pyr\u00e9n\u00e9es",
    "wof:name":"Coop\u00e9rative Sagef",
    "wof:placetype":"venue"
},
  "geometry": {"coordinates":[1.352205,44.016762],"type":"Point"}
}