{
  "type": "Feature",
  "properties": {
    "iso:country":"FR",
    "sg:address":"29 Rue St Marc 22300 Lannion",
    "sg:city":"Lannion",
    "sg:classifiers":[
        {
            "category":"Professional",
            "subcategory":"Engineering",
            "type":"Services"
        }
    ],
    "sg:phone":"+33 2 96 46 68 05",
    "sg:postcode":"22300",
    "sg:province":"Bretagne",
    "sg:tags":[
        "machine",
        "-",
        "mechanical"
    ],
    "wof:name":"Bois Ouest Industrie Sarl",
    "wof:placetype":"venue"
},
  "geometry": {"coordinates":[-3.440852,48.734245],"type":"Point"}
}