{
  "type": "Feature",
  "properties": {
    "iso:country":"FR",
    "sg:address":"B.P. 267, 40106 Dax C\u00e9dex^^Rue des Prairies - ZAC du Sablar, 40100 Dax",
    "sg:city":"Dax",
    "sg:orig_category":"Non-Classified Establishments",
    "sg:phone":"+33 5 58 58 40 58",
    "sg:postcode":"40100",
    "sg:province":"Aquitaine",
    "wof:name":"Saad S.a.",
    "wof:placetype":"venue"
},
  "geometry": {"coordinates":[-1.050939,43.707466],"type":"Point"}
}