{
  "type": "Feature",
  "properties": {
    "iso:country":"FR",
    "sg:address":"4 R Foug\u00e8res 17100 Saintes",
    "sg:classifiers":[
        {
            "category":"Shopping",
            "type":"Retail Goods"
        }
    ],
    "sg:phone":"+33 5 46 93 30 08",
    "sg:postcode":"17100",
    "sg:province":"Poitou-Charentes",
    "sg:tags":[
        "metallurgy",
        "finished",
        "-",
        "metalworking",
        "metallic"
    ],
    "wof:name":"Atelier De Tolerie Saintongeais Sa",
    "wof:placetype":"venue"
},
  "geometry": {"coordinates":[-0.664377,45.742706],"type":"Point"}
}