{
  "type": "Feature",
  "properties": {
    "addr:full":"Rue Tram Pl\u00e9lan le Petit Bretagne 22980",
    "addr:postcode":"22980",
    "addr:street":"Rue Tram Ple\u0301Lan Le Petit Bretagne",
    "iso:country":"FR",
    "sg:address":"Rue Tram",
    "sg:city":"Pl\u00e9lan le Petit",
    "sg:orig_category":"Non-Classified Establishments",
    "sg:phone":"+33 2 96 27 60 32",
    "sg:postcode":"22980",
    "sg:province":"Bretagne",
    "wof:name":"Guigneux S.a.",
    "wof:placetype":"venue"
},
  "geometry": {"coordinates":[-2.216709,48.429989],"type":"Point"}
}