{
  "type": "Feature",
  "properties": {
    "addr:full":"688 R Du Mar\u00e9chal Juin 77000 Vaux Le P\u00e9nil Ile de France 77000",
    "addr:housenumber":"688",
    "addr:postcode":"77000;77000",
    "addr:street":"R Du Mare\u0301Chal Juin",
    "iso:country":"FR",
    "sg:address":"688 R Du Mar\u00e9chal Juin 77000 Vaux Le P\u00e9nil",
    "sg:classifiers":[
        {
            "category":"Manufacturing",
            "subcategory":"Metals",
            "type":"Manufacturing & Wholesale Goods"
        }
    ],
    "sg:phone":"+33 1 64 37 51 32",
    "sg:postcode":"77000",
    "sg:province":"Ile de France",
    "sg:tags":[
        "metallurgy",
        "steel",
        "metalworking"
    ],
    "wof:name":"Ets Brudner Sa",
    "wof:placetype":"venue"
},
  "geometry": {"coordinates":[2.686889,48.537224],"type":"Point"}
}