{
  "type": "Feature",
  "properties": {
    "iso:country":"FR",
    "sg:address":"23, Av. Guynemer, 66000 Perpignan",
    "sg:orig_category":"Non-Classified Establishments",
    "sg:phone":"+33 4 68 66 02 62",
    "sg:postcode":"66000",
    "sg:province":"Languedoc-Roussillon",
    "wof:name":"Centre D' Affaires Europa S.a.r.l.",
    "wof:placetype":"venue"
},
  "geometry": {"coordinates":[2.88743,42.69812],"type":"Point"}
}