{
  "type": "Feature",
  "properties": {
    "addr:full":"Rue De La Plaine 71160 Digoin Digoin Bourgogne 71160",
    "addr:postcode":"71160;71160",
    "addr:street":"Rue De La Plaine",
    "iso:country":"FR",
    "sg:address":"Rue De La Plaine 71160 Digoin",
    "sg:city":"Digoin",
    "sg:classifiers":[
        {
            "category":"Farming",
            "subcategory":"Livestock Farm",
            "type":"Manufacturing & Wholesale Goods"
        }
    ],
    "sg:phone":"+33 3 85 88 59 17",
    "sg:postcode":"71160",
    "sg:province":"Bourgogne",
    "sg:tags":[
        "grain",
        "agriculture",
        "cereal"
    ],
    "wof:name":"Cooperative Agricole Sud Est",
    "wof:placetype":"venue"
},
  "geometry": {"coordinates":[3.9946,46.483845],"type":"Point"}
}