{
  "type": "Feature",
  "properties": {
    "iso:country":"FR",
    "sg:address":"B.P. 12, 35831 Betton C\u00e9dex^^7, Rue des Tisserands - ZA la Forge, 35830 Betton",
    "sg:city":"Betton",
    "sg:orig_category":"Non-Classified Establishments",
    "sg:phone":"+33 2 99 55 88 93",
    "sg:postcode":"35830",
    "sg:province":"Bretagne",
    "wof:name":"G.s.i. E.u.r.l. - Guillard Stockage Industriel",
    "wof:placetype":"venue"
},
  "geometry": {"coordinates":[-1.647044,48.18317],"type":"Point"}
}