{
  "type": "Feature",
  "properties": {
    "addr:full":"14 pl de Verdun; Eybens; 38320 Rhone-Alpes 38320",
    "addr:housenumber":"14",
    "addr:postcode":"38320;38320",
    "addr:street":"Pl De Verdun",
    "iso:country":"FR",
    "sg:address":"14 pl de Verdun; Eybens; 38320",
    "sg:classifiers":[
        {
            "category":"Banks & Credit Unions",
            "subcategory":"Bank",
            "type":"Services"
        }
    ],
    "sg:phone":"+33 3376253029",
    "sg:postcode":"38320",
    "sg:province":"Rhone-Alpes",
    "wof:name":"Soci\u00e9t\u00e9 G\u00e9n\u00e9rale",
    "wof:placetype":"venue"
},
  "geometry": {"coordinates":[5.75159,45.147202],"type":"Point"}
}