{
  "type": "Feature",
  "properties": {
    "addr:full":"B.P. 25, 28231 Epernon C\u00e9dex^^Z.I., 28230 Epernon \u00c9pernon Centre 28230",
    "addr:housenumber":"e\u0301pernon",
    "addr:postcode":"28231;28230;28230",
    "addr:street":"B.P. 25;I.",
    "iso:country":"FR",
    "sg:address":"B.P. 25, 28231 Epernon C\u00e9dex^^Z.I., 28230 Epernon",
    "sg:city":"\u00c9pernon",
    "sg:orig_category":"Non-Classified Establishments",
    "sg:phone":"+33 2 37 18 76 00",
    "sg:postcode":"28230",
    "sg:province":"Centre",
    "wof:name":"F.c. Connectral S.a. - Framatome Connectors Connectral",
    "wof:placetype":"venue"
},
  "geometry": {"coordinates":[1.67713,48.609051],"type":"Point"}
}