{
  "type": "Feature",
  "properties": {
    "iso:country":"FR",
    "sg:address":"rue de la Grande Epine 76800 ST ETIENNE DU ROUVRAY",
    "sg:classifiers":[
        {
            "category":"Wholesale",
            "subcategory":"Auto Parts",
            "type":"Manufacturing & Wholesale Goods"
        }
    ],
    "sg:phone":"+33 2 32 95 91 60",
    "sg:postcode":"76800",
    "sg:province":"Haute Normandie",
    "sg:tags":[
        "automobile",
        "component",
        "structural"
    ],
    "wof:name":"Morisse-nayrat Sa",
    "wof:placetype":"venue"
},
  "geometry": {"coordinates":[1.113628,49.396164],"type":"Point"}
}