{
  "type": "Feature",
  "properties": {
    "addr:full":"1, Place de la R\u00e9publique, 19130 Objat Limousin",
    "addr:housenumber":"1",
    "addr:postcode":"19130",
    "addr:street":"Place De La Re\u0301Publique",
    "iso:country":"FR",
    "sg:address":"1, Place de la R\u00e9publique, 19130 Objat",
    "sg:orig_category":"Unclassifiable Establishments",
    "sg:phone":"+33 5 55 25 27 70",
    "sg:province":"Limousin",
    "wof:name":"B.p.c. - Banque Populaire Du Centre",
    "wof:placetype":"venue"
},
  "geometry": {"coordinates":[1.409001,45.262486],"type":"Point"}
}