{
  "type": "Feature",
  "properties": {
    "iso:country":"FR",
    "sg:address":"20 Rue Emile Zola 73490 La Ravoire",
    "sg:classifiers":[
        {
            "category":"Utilities",
            "subcategory":"Electric",
            "type":"Services"
        }
    ],
    "sg:phone":"+33 4 79 72 76 67",
    "sg:postcode":"73490",
    "sg:province":"Rhone-Alpes",
    "sg:tags":[
        "electricity",
        "electronic",
        "electrical",
        "equipment"
    ],
    "wof:name":"Sotalec Sarl",
    "wof:placetype":"venue"
},
  "geometry": {"coordinates":[5.968932,45.561142],"type":"Point"}
}