{
  "type": "Feature",
  "properties": {
    "addr:full":"13 Rue Chantier Naval 83310 Cogolin Picardie",
    "addr:housenumber":"13",
    "addr:postcode":"83310",
    "addr:street":"Rue Chantier",
    "iso:country":"FR",
    "sg:address":"13 Rue Chantier Naval 83310 Cogolin",
    "sg:classifiers":[
        {
            "category":"Autos & Motor Vehicles",
            "subcategory":"Boat Sales",
            "type":"Retail Goods"
        }
    ],
    "sg:phone":"+33 4 94 43 40 09",
    "sg:province":"Picardie",
    "sg:tags":[
        "equipment",
        "transport"
    ],
    "wof:name":"Perot (agence Maritime Jacques) Sarl",
    "wof:placetype":"venue"
},
  "geometry": {"coordinates":[6.465188,43.207832],"type":"Point"}
}