{
  "type": "Feature",
  "properties": {
    "addr:full":"1900, Chemin de Bounhoure - Rocade Nord, 13090 Aix en Provence Provence-Alpes-C\u00f4te d'Azur",
    "addr:housenumber":"1900",
    "addr:postcode":"13090",
    "addr:street":"Chemin De Bounhoure Rocade Nord;En Provence",
    "iso:country":"FR",
    "sg:address":"1900, Chemin de Bounhoure - Rocade Nord, 13090 Aix en Provence",
    "sg:orig_category":"Unclassifiable Establishments",
    "sg:phone":"+33 4 42 99 20 80",
    "sg:province":"Provence-Alpes-C\u00f4te d'Azur",
    "wof:name":"S.a.t.a.p. S.a. - Soci\u00e9t\u00e9 Aixoise De Transports Alpes-provence",
    "wof:placetype":"venue"
},
  "geometry": {"coordinates":[5.41946,43.55584],"type":"Point"}
}