{
  "type": "Feature",
  "properties": {
    "iso:country":"FR",
    "sg:address":"2 Avenue Du Clos Neuf 45190 Beaugency",
    "sg:city":"Beaugency",
    "sg:classifiers":[
        {
            "category":"Shopping",
            "subcategory":"Gifts & Souvenirs",
            "type":"Retail Goods"
        }
    ],
    "sg:phone":"+33 2 38 44 98 81",
    "sg:postcode":"45190",
    "sg:province":"Centre",
    "sg:tags":[
        "product",
        "miscellaneous"
    ],
    "wof:name":"Des Fontaines Sarl",
    "wof:placetype":"venue"
},
  "geometry": {"coordinates":[1.630985,47.779282],"type":"Point"}
}