{
  "type": "Feature",
  "properties": {
    "addr:full":"11, Av. de l'Ile Brune - ZI les Glairaux, 38120 Saint Egr\u00e8ve Rhone-Alpes 38120",
    "addr:postcode":"38120;38120",
    "addr:street":"11 Av. De L'Ile Brune Zi Les Glairaux;Rhone-Alpes",
    "iso:country":"FR",
    "sg:address":"11, Av. de l'Ile Brune - ZI les Glairaux, 38120 Saint Egr\u00e8ve",
    "sg:orig_category":"Non-Classified Establishments",
    "sg:phone":"+33 4 76 75 25 26",
    "sg:postcode":"38120",
    "sg:province":"Rhone-Alpes",
    "wof:name":"Alpes Denr\u00e9es S.a.s.",
    "wof:placetype":"venue"
},
  "geometry": {"coordinates":[-89.842308,35.12442],"type":"Point"}
}