{
  "type": "Feature",
  "properties": {
    "iso:country":"FR",
    "sg:address":"Les Vincents 42210 Montrond les Bains",
    "sg:orig_category":"Unclassifiable Establishments",
    "sg:phone":"+33 4 72 05 34 95",
    "sg:postcode":"42210",
    "sg:province":"Rhone-Alpes",
    "wof:name":"B\u00e9ton Rhodanien S.a.",
    "wof:placetype":"venue"
},
  "geometry": {"coordinates":[4.230482,45.584427],"type":"Point"}
}