{
  "type": "Feature",
  "properties": {
    "addr:full":"Av. Andr\u00e9 Chausson Maubeuge Nord Pas-de-Calais 59600",
    "addr:postcode":"59600",
    "addr:street":"Av. Andre\u0301 Chausson Maubeuge Nord",
    "iso:country":"FR",
    "sg:address":"Av. Andr\u00e9 Chausson",
    "sg:city":"Maubeuge",
    "sg:orig_category":"Unclassifiable Establishments",
    "sg:phone":"+33 3 27 53 54 55",
    "sg:postcode":"59600",
    "sg:province":"Nord Pas-de-Calais",
    "wof:name":"M.c.a. S.a. - Maubeuge Construction Automobile",
    "wof:placetype":"venue"
},
  "geometry": {"coordinates":[3.914611,50.270714],"type":"Point"}
}