{
  "type": "Feature",
  "properties": {
    "iso:country":"FR",
    "sg:address":"344 avenue Napol\u00e9on Bonaparte 92500 Rueil Malmaison",
    "sg:classifiers":[
        {
            "category":"Autos & Motor Vehicles",
            "subcategory":"Automobile Sales",
            "type":"Retail Goods"
        }
    ],
    "sg:phone":"+33 1 47 32 60 00",
    "sg:province":"Ile de France",
    "sg:tags":[
        "passenger",
        "car"
    ],
    "wof:name":"Ford France S.a.s.",
    "wof:placetype":"venue"
},
  "geometry": {"coordinates":[2.15542,48.869278],"type":"Point"}
}