{
  "type": "Feature",
  "properties": {
    "addr:full":"6 Bd De L'Europe 21800 Quetigny Quetigny Bourgogne 21800",
    "addr:housenumber":"6",
    "addr:postcode":"21800;21800",
    "addr:street":"Bd De L'Europe",
    "iso:country":"FR",
    "sg:address":"6 Bd De L'Europe 21800 Quetigny",
    "sg:city":"Quetigny",
    "sg:classifiers":[
        {
            "category":"Health Services",
            "subcategory":"Medical Lab",
            "type":"Services"
        }
    ],
    "sg:phone":"+33 3 80 48 30 30",
    "sg:postcode":"21800",
    "sg:province":"Bourgogne",
    "sg:tags":[
        "chemical",
        "pharmaceutical",
        "pharmacy"
    ],
    "wof:name":"Sanofi Synthelabo",
    "wof:placetype":"venue"
},
  "geometry": {"coordinates":[5.100317,47.318672],"type":"Point"}
}