{
  "type": "Feature",
  "properties": {
    "addr:full":"Hameau Mercey 70500 Gevigney et Mercey Franche Comt\u00e9 70500",
    "addr:postcode":"70500;70500",
    "addr:street":"Hameau Mercey;Franche Comte\u0301",
    "iso:country":"FR",
    "sg:address":"Hameau Mercey 70500 Gevigney et Mercey",
    "sg:orig_category":"C\u00e2bles \u00e9lectriques D\u00e9coupage-surmoulage synchronis\u00e9s Moulage par injection",
    "sg:phone":"+33 3 84 78 68 00",
    "sg:postcode":"70500",
    "sg:province":"Franche Comt\u00e9",
    "wof:name":"V\u00e9locar S.a.",
    "wof:placetype":"venue"
},
  "geometry": {"coordinates":[5.931748,47.798748],"type":"Point"}
}