{
  "type": "Feature",
  "properties": {
    "addr:full":"12, Av. F\u00e9lix Faure, 06000 Nice Provence-Alpes-C\u00f4te d'Azur",
    "addr:postcode":"06000",
    "addr:street":"12 Av. Fe\u0301Lix Faure",
    "iso:country":"FR",
    "sg:address":"12, Av. F\u00e9lix Faure, 06000 Nice",
    "sg:orig_category":"Unclassifiable Establishments",
    "sg:phone":"+33 4 92 17 53 00",
    "sg:province":"Provence-Alpes-C\u00f4te d'Azur",
    "wof:name":"Aston Golden Tulip",
    "wof:placetype":"venue"
},
  "geometry": {"coordinates":[7.272164,43.698055],"type":"Point"}
}