{
  "type": "Feature",
  "properties": {
    "iso:country":"FR",
    "sg:address":"59171 Hornaing",
    "sg:classifiers":[
        {
            "category":"Utilities",
            "subcategory":"Electric",
            "type":"Services"
        }
    ],
    "sg:phone":"+33 3 27 24 37 60",
    "sg:postcode":"59171",
    "sg:province":"Nord Pas-de-Calais",
    "sg:tags":[
        "electricity",
        "raw",
        "energy",
        "material"
    ],
    "wof:name":"Societe D'electricite Et De Thermique Du Nord Est",
    "wof:placetype":"venue"
},
  "geometry": {"coordinates":[3.33762,50.365253],"type":"Point"}
}