{
  "type": "Feature",
  "properties": {
    "addr:full":"Rue De Faugeras 87280 Limoges Limousin 87280",
    "addr:postcode":"87280;87280",
    "addr:street":"Rue De Faugeras",
    "iso:country":"FR",
    "sg:address":"Rue De Faugeras 87280 Limoges",
    "sg:classifiers":[
        {
            "category":"Professional",
            "subcategory":"Business Services",
            "type":"Services"
        }
    ],
    "sg:phone":"+33 5 55 35 49 50",
    "sg:postcode":"87280",
    "sg:province":"Limousin",
    "sg:tags":[
        "body",
        "advice"
    ],
    "wof:name":"Les Papillons Blancs",
    "wof:placetype":"venue"
},
  "geometry": {"coordinates":[1.292408,45.865875],"type":"Point"}
}