{
  "type": "Feature",
  "properties": {
    "addr:full":"Cite Cazzenave 40260 Lesperon Lesperon Aquitaine 40260",
    "addr:postcode":"40260;40260",
    "addr:street":"Cite Cazzenave",
    "iso:country":"FR",
    "sg:address":"Cite Cazzenave 40260 Lesperon",
    "sg:city":"Lesperon",
    "sg:classifiers":[
        {
            "category":"Manufacturing",
            "subcategory":"Rubber & Plastics",
            "type":"Manufacturing & Wholesale Goods"
        }
    ],
    "sg:phone":"+33 5 58 89 65 51",
    "sg:postcode":"40260",
    "sg:province":"Aquitaine",
    "wof:name":"Aquitaine Sacs Services",
    "wof:placetype":"venue"
},
  "geometry": {"coordinates":[-1.068398,43.872623],"type":"Point"}
}