{
  "type": "Feature",
  "properties": {
    "iso:country":"FR",
    "sg:address":"7, Rue des Usines, 60100 Creil",
    "sg:orig_category":"Unclassifiable Establishments",
    "sg:phone":"+33 3 44 24 09 33",
    "sg:province":"Picardie",
    "wof:name":"S.p.i.m. S.a. - Soci\u00e9t\u00e9 De Prestations Industrielles Et De Montage",
    "wof:placetype":"venue"
},
  "geometry": {"coordinates":[2.463144,49.261494],"type":"Point"}
}