{
  "type": "Feature",
  "properties": {
    "addr:full":"Le Pregay 47800 Allemans du Dropt Moustier Aquitaine 47800",
    "addr:postcode":"47800;47800",
    "iso:country":"FR",
    "sg:address":"Le Pregay 47800 Allemans du Dropt",
    "sg:city":"Moustier",
    "sg:orig_category":"Unclassifiable Establishments",
    "sg:phone":"+33 5 53 20 22 20",
    "sg:postcode":"47800",
    "sg:province":"Aquitaine",
    "wof:name":"Inter Diffusion Fruits Plus S.a.",
    "wof:placetype":"venue"
},
  "geometry": {"coordinates":[0.26897,44.623951],"type":"Point"}
}