{
  "type": "Feature",
  "properties": {
    "iso:country":"FR",
    "sg:address":"Rte des Princes d'Orange",
    "sg:city":"Rasteau",
    "sg:orig_category":"Non-Classified Establishments",
    "sg:phone":"+33 4 90 10 90 10",
    "sg:postcode":"84110",
    "sg:province":"Provence-Alpes-C\u00f4te d'Azur",
    "wof:name":"Caves Des Vignerons De Rasteau",
    "wof:placetype":"venue"
},
  "geometry": {"coordinates":[5.075249,44.252953],"type":"Point"}
}