{
  "type": "Feature",
  "properties": {
    "addr:full":"La Brohini\u00e8re 35360 Montauban De Bretagne Boisgervilly Bretagne 35360",
    "addr:postcode":"35360;boisgervilly;35360",
    "iso:country":"FR",
    "sg:address":"La Brohini\u00e8re 35360 Montauban De Bretagne",
    "sg:city":"Boisgervilly",
    "sg:classifiers":[
        {
            "category":"Professional",
            "type":"Services"
        }
    ],
    "sg:phone":"+33 2 99 06 66 77",
    "sg:postcode":"35360",
    "sg:province":"Bretagne",
    "sg:tags":[
        "transport"
    ],
    "wof:name":"Causse Wallon",
    "wof:placetype":"venue"
},
  "geometry": {"coordinates":[-2.117024,48.215046],"type":"Point"}
}