{
  "type": "Feature",
  "properties": {
    "addr:full":"215, Rue Ren\u00e9 Maire, 39000 Lons le Saunier Franche Comt\u00e9",
    "addr:housenumber":"215",
    "addr:postcode":"39000",
    "addr:street":"Rue Rene\u0301 Maire;Franche Comte\u0301",
    "iso:country":"FR",
    "sg:address":"215, Rue Ren\u00e9 Maire, 39000 Lons le Saunier",
    "sg:orig_category":"Unclassifiable Establishments",
    "sg:phone":"+33 3 84 47 59 59",
    "sg:province":"Franche Comt\u00e9",
    "wof:name":"Skamex France S.a.r.l.",
    "wof:placetype":"venue"
},
  "geometry": {"coordinates":[5.581011,46.684753],"type":"Point"}
}