{
  "type": "Feature",
  "properties": {
    "addr:full":"19 avenue de Fontenille 33360 Carignan de Bordeaux Camblanes-et-Meynac Aquitaine 33360",
    "addr:housenumber":"19",
    "addr:postcode":"33360;33360",
    "addr:street":"Avenue De Fontenille",
    "iso:country":"FR",
    "sg:address":"19 avenue de Fontenille 33360 Carignan de Bordeaux",
    "sg:city":"Camblanes-et-Meynac",
    "sg:classifiers":[
        {
            "category":"Wholesale",
            "subcategory":"Wine & Distilled Alcoholic Beverages",
            "type":"Manufacturing & Wholesale Goods"
        }
    ],
    "sg:phone":"+33 5 56 68 81 82",
    "sg:postcode":"33360",
    "sg:province":"Aquitaine",
    "sg:tags":[
        "french"
    ],
    "wof:name":"Maison Ginestet S.a.",
    "wof:placetype":"venue"
},
  "geometry": {"coordinates":[-0.494849,44.807426],"type":"Point"}
}