{
  "type": "Feature",
  "properties": {
    "addr:full":"B.P. 59, 59550 Landrecies^^Rue de la Pescherie, 59550 Landrecies Nord Pas-de-Calais",
    "addr:postcode":"59550;59550",
    "addr:street":"B.P. 59;Pescherie",
    "iso:country":"FR",
    "sg:address":"B.P. 59, 59550 Landrecies^^Rue de la Pescherie, 59550 Landrecies",
    "sg:orig_category":"Non-Classified Establishments",
    "sg:phone":"+33 3 27 77 74 77",
    "sg:province":"Nord Pas-de-Calais",
    "wof:name":"Nord Sanders S.a.",
    "wof:placetype":"venue"
},
  "geometry": {"coordinates":[3.68928,50.124905],"type":"Point"}
}