{
  "type": "Feature",
  "properties": {
    "addr:full":"33, Rue du Vieil Abreuvoir, 78100 Saint Germain en Laye Ile de France",
    "addr:housenumber":"33",
    "addr:postcode":"78100",
    "addr:street":"Rue Du Vieil Abreuvoir",
    "iso:country":"FR",
    "sg:address":"33, Rue du Vieil Abreuvoir, 78100 Saint Germain en Laye",
    "sg:orig_category":"Unclassifiable Establishments",
    "sg:phone":"+33 1 30 61 67 95",
    "sg:province":"Ile de France",
    "wof:name":"Kingsman S.a.",
    "wof:placetype":"venue"
},
  "geometry": {"coordinates":[2.095238,48.896923],"type":"Point"}
}