{
  "type": "Feature",
  "properties": {
    "addr:full":"23, Rue des Cerisiers - ZI Eglantier - Ce 2818, 91090 Lisses Ile de France",
    "addr:housenumber":"23;2818",
    "addr:postcode":"91090;ile",
    "addr:street":"Rue Des Cerisiers Zi Eglantier Ce",
    "iso:country":"FR",
    "sg:address":"23, Rue des Cerisiers - ZI Eglantier - Ce 2818, 91090 Lisses",
    "sg:orig_category":"Non-Classified Establishments",
    "sg:phone":"+33 1 64 97 70 97",
    "sg:province":"Ile de France",
    "wof:name":"Sf\u00e8re Emballage S.a.",
    "wof:placetype":"venue"
},
  "geometry": {"coordinates":[2.423843,48.597694],"type":"Point"}
}