{
  "type": "Feature",
  "properties": {
    "iso:country":"FR",
    "sg:address":"ZA les Brosses",
    "sg:city":"Lar\u00e7ay",
    "sg:orig_category":"Unclassifiable Establishments",
    "sg:phone":"+33 2 47 27 24 30",
    "sg:postcode":"37270",
    "sg:province":"Centre",
    "wof:name":"Liaume S.a.",
    "wof:placetype":"venue"
},
  "geometry": {"coordinates":[0.77838,47.36808],"type":"Point"}
}