{
  "type": "Feature",
  "properties": {
    "iso:country":"FR",
    "sg:address":"3 Impasse Du Laser 67800 Bischheim",
    "sg:city":"Bischheim",
    "sg:classifiers":[
        {
            "category":"Professional",
            "subcategory":"Advertising",
            "type":"Services"
        }
    ],
    "sg:phone":"+33 3 88 83 55 31",
    "sg:postcode":"67800",
    "sg:province":"Alsace",
    "sg:tags":[
        "communication",
        "medium"
    ],
    "wof:name":"Promo Est Stell Sarl",
    "wof:placetype":"venue"
},
  "geometry": {"coordinates":[7.771948,48.629234],"type":"Point"}
}