{
  "type": "Feature",
  "properties": {
    "addr:full":"ZI Ouest Surg\u00e8res Poitou-Charentes 17700",
    "addr:postcode":"17700",
    "addr:street":"Zi Ouest",
    "iso:country":"FR",
    "sg:address":"ZI Ouest",
    "sg:city":"Surg\u00e8res",
    "sg:orig_category":"Unclassifiable Establishments",
    "sg:phone":"+33 5 46 07 31 20",
    "sg:postcode":"17700",
    "sg:province":"Poitou-Charentes",
    "wof:name":"C.t.l. S.a.r.l. - Chaudronnerie Tuyauterie Launay",
    "wof:placetype":"venue"
},
  "geometry": {"coordinates":[-0.752141,46.105919],"type":"Point"}
}