{
  "type": "Feature",
  "properties": {
    "addr:full":"15 rue Auguste Comte 87280 Limoges Limousin",
    "addr:housenumber":"15",
    "addr:postcode":"87280",
    "addr:street":"Rue Auguste Comte",
    "iso:country":"FR",
    "sg:address":"15 rue Auguste Comte 87280 Limoges",
    "sg:classifiers":[
        {
            "category":"Farming",
            "subcategory":"Farm & Veterinary Services",
            "type":"Manufacturing & Wholesale Goods"
        }
    ],
    "sg:phone":"+33 5 55 04 64 40",
    "sg:province":"Limousin",
    "sg:tags":[
        "herb",
        "product",
        "mixtures"
    ],
    "wof:name":"Longimpex Sa",
    "wof:placetype":"venue"
},
  "geometry": {"coordinates":[1.27087,45.875027],"type":"Point"}
}