{
  "type": "Feature",
  "properties": {
    "addr:full":"14, Av. Louise Michel, 28500 Vernouillet Vernouillet Centre 28500",
    "addr:postcode":"28500;28500",
    "addr:street":"14 Av. Louise Michel;Vernouillet",
    "iso:country":"FR",
    "sg:address":"14, Av. Louise Michel, 28500 Vernouillet",
    "sg:city":"Vernouillet",
    "sg:orig_category":"Unclassifiable Establishments",
    "sg:phone":"+33 2 37 46 05 62",
    "sg:postcode":"28500",
    "sg:province":"Centre",
    "wof:name":"A.m.v. S.a.r.l. - Atelier De M\u00e9canique De Vernouillet",
    "wof:placetype":"venue"
},
  "geometry": {"coordinates":[1.323931,48.731758],"type":"Point"}
}