{
  "type": "Feature",
  "properties": {
    "iso:country":"FR",
    "sg:address":"20, Rue Paul C\u00e9zanne, 69330 Meyzieu",
    "sg:orig_category":"Unclassifiable Establishments",
    "sg:phone":"+33 4 72 02 78 14",
    "sg:province":"Rhone-Alpes",
    "wof:name":"Nouv\u00e9tra S.a.",
    "wof:placetype":"venue"
},
  "geometry": {"coordinates":[4.987543,45.766273],"type":"Point"}
}