{
  "type": "Feature",
  "properties": {
    "iso:country":"FR",
    "sg:address":"B.P. 162, 69512 Vaulx en Velin C\u00e9dex^^34, Rue Louis Saillant, 69120 Vaulx en Velin",
    "sg:orig_category":"Non-Classified Establishments",
    "sg:phone":"+33 4 72 04 63 56",
    "sg:province":"Rhone-Alpes",
    "wof:name":"Socoser S.a.",
    "wof:placetype":"venue"
},
  "geometry": {"coordinates":[4.916895,45.779022],"type":"Point"}
}