{
  "type": "Feature",
  "properties": {
    "addr:full":"Le Bois Launay 61700 Domfront Domfront Basse Normandie 61700",
    "addr:postcode":"61700;61700",
    "addr:street":"Bois Launay",
    "iso:country":"FR",
    "sg:address":"Le Bois Launay 61700 Domfront",
    "sg:city":"Domfront",
    "sg:classifiers":[
        {
            "category":"Utilities",
            "subcategory":"Electric",
            "type":"Services"
        }
    ],
    "sg:phone":"+33 2 33 38 65 22",
    "sg:postcode":"61700",
    "sg:province":"Basse Normandie",
    "sg:tags":[
        "electricity",
        "electronic",
        "electrical",
        "equipment"
    ],
    "wof:name":"Ste Nvelle Marbo Sas",
    "wof:placetype":"venue"
},
  "geometry": {"coordinates":[-0.644869,48.581154],"type":"Point"}
}