{
  "type": "Feature",
  "properties": {
    "iso:country":"FR",
    "sg:address":"B.P. 21, 35960 Le Vivier sur Mer^^Le Port, 35960 Le Vivier sur Mer",
    "sg:city":"Le Vivier-sur-Mer",
    "sg:orig_category":"Non-Classified Establishments",
    "sg:phone":"+33 2 99 48 87 24",
    "sg:postcode":"35960",
    "sg:province":"Bretagne",
    "wof:name":"La Vivi\u00e8re S.a.r.l.",
    "wof:placetype":"venue"
},
  "geometry": {"coordinates":[-1.773474,48.602634],"type":"Point"}
}