{
  "type": "Feature",
  "properties": {
    "iso:country":"FR",
    "sg:address":"67",
    "sg:city":"Jean de la Fontaine; Nogent-sur-Oise Cedex; 60181",
    "sg:classifiers":[
        {
            "category":"Industrial Area",
            "type":"Public Place"
        }
    ],
    "sg:phone":"+33 1 44 66 33 00",
    "sg:province":"Franche Comt\u00e9",
    "sg:tags":[
        "large",
        "private"
    ],
    "wof:name":"Montupet Sa",
    "wof:placetype":"venue"
},
  "geometry": {"coordinates":[-87.975327,41.876934],"type":"Point"}
}