{
  "type": "Feature",
  "properties": {
    "addr:full":"180 Rte Coudreau 33910 St Denis De Pile Bonzac Aquitaine 33910",
    "addr:housenumber":"180",
    "addr:postcode":"33910;33910",
    "addr:street":"Rte Coudreau;Pile",
    "iso:country":"FR",
    "sg:address":"180 Rte Coudreau 33910 St Denis De Pile",
    "sg:city":"Bonzac",
    "sg:classifiers":[
        {
            "category":"Professional",
            "type":"Services"
        }
    ],
    "sg:phone":"+33 5 57 24 38 79",
    "sg:postcode":"33910",
    "sg:province":"Aquitaine",
    "sg:tags":[
        "transport",
        "road"
    ],
    "wof:name":"M A M T A Sarl",
    "wof:placetype":"venue"
},
  "geometry": {"coordinates":[-0.172529,44.964741],"type":"Point"}
}