{
  "type": "Feature",
  "properties": {
    "iso:country":"FR",
    "sg:address":"L'Abbaye",
    "sg:city":"Cruis",
    "sg:orig_category":"Unclassifiable Establishments",
    "sg:phone":"+33 4 92 77 02 02",
    "sg:postcode":"04230",
    "sg:province":"Provence-Alpes-C\u00f4te d'Azur",
    "wof:name":"Micoulin Monique",
    "wof:placetype":"venue"
},
  "geometry": {"coordinates":[5.83591,44.062721],"type":"Point"}
}