{
  "type": "Feature",
  "properties": {
    "iso:country":"FR",
    "sg:address":"ZA",
    "sg:city":"Rioz",
    "sg:orig_category":"Non-Classified Establishments",
    "sg:phone":"+33 3 84 91 88 81",
    "sg:postcode":"70190",
    "sg:province":"Franche Comt\u00e9",
    "wof:name":"Sorima E.u.r.l.",
    "wof:placetype":"venue"
},
  "geometry": {"coordinates":[6.074025,47.424068],"type":"Point"}
}