{
  "type": "Feature",
  "properties": {
    "addr:full":"227, Rue des Marvais - ZI des Lanches, 74300 Thyez Rhone-Alpes 74300",
    "addr:housenumber":"227",
    "addr:postcode":"74300;74300",
    "addr:street":"Rue Des Marvais Zi Des Lanches;Rhone-Alpes",
    "iso:country":"FR",
    "sg:address":"227, Rue des Marvais - ZI des Lanches, 74300 Thyez",
    "sg:orig_category":"Unclassifiable Establishments",
    "sg:phone":"+33 4 50 89 13 79",
    "sg:postcode":"74300",
    "sg:province":"Rhone-Alpes",
    "wof:name":"S.p.i. Energie S.a. - Soci\u00e9t\u00e9 De Production Industrielle D'energie",
    "wof:placetype":"venue"
},
  "geometry": {"coordinates":[6.633185,45.987919],"type":"Point"}
}