{
  "type": "Feature",
  "properties": {
    "addr:full":"1 Compi\u00e8gne 60190 Estr\u00e9es Saint Denis Picardie 60190",
    "addr:housenumber":"1",
    "addr:postcode":"60190;60190",
    "addr:street":"Compie\u0300Gne",
    "iso:country":"FR",
    "sg:address":"1",
    "sg:city":"Compi\u00e8gne 60190 Estr\u00e9es Saint Denis",
    "sg:classifiers":[
        {
            "category":"Transit Center",
            "subcategory":"Freight",
            "type":"Transportation"
        }
    ],
    "sg:phone":"+33 3 44 41 31 31",
    "sg:postcode":"60190",
    "sg:province":"Picardie",
    "sg:tags":[
        "metallurgy",
        "pipe",
        "metalworking",
        "sheet"
    ],
    "wof:name":"Le Plomb Francais",
    "wof:placetype":"venue"
},
  "geometry": {"coordinates":[2.640787,49.430981],"type":"Point"}
}