{
  "type": "Feature",
  "properties": {
    "iso:country":"FR",
    "sg:address":"Rue Denis Papin",
    "sg:city":"Malemort sur Corr\u00e8ze",
    "sg:orig_category":"Unclassifiable Establishments",
    "sg:phone":"+33 5 55 92 21 79",
    "sg:postcode":"19360",
    "sg:province":"Limousin",
    "wof:name":"Etablissements Farge Et Muzergues S.a.",
    "wof:placetype":"venue"
},
  "geometry": {"coordinates":[1.582614,45.177303],"type":"Point"}
}