{
  "type": "Feature",
  "properties": {
    "addr:full":"93 rue de Gassicourt 78200 Mantes la Jolie Ile de France",
    "addr:housenumber":"93",
    "addr:postcode":"78200",
    "addr:street":"Rue De Gassicourt",
    "iso:country":"FR",
    "sg:address":"93 rue de Gassicourt 78200 Mantes la Jolie",
    "sg:classifiers":[
        {
            "category":"Exhibition Hall",
            "type":"Public Place"
        }
    ],
    "sg:phone":"+33 1 30 94 26 51",
    "sg:province":"Ile de France",
    "sg:tags":[
        "screen",
        "printing",
        "precision"
    ],
    "wof:name":"Microcircuit International Sa",
    "wof:placetype":"venue"
},
  "geometry": {"coordinates":[1.705036,48.995106],"type":"Point"}
}