{
  "type": "Feature",
  "properties": {
    "addr:full":"10, Rue des Naudins, 89100 Saligny Saligny Bourgogne 89100",
    "addr:housenumber":"10",
    "addr:postcode":"89100;89100",
    "addr:street":"Rue Des Naudins",
    "iso:country":"FR",
    "sg:address":"10, Rue des Naudins, 89100 Saligny",
    "sg:city":"Saligny",
    "sg:orig_category":"Non-Classified Establishments",
    "sg:phone":"+33 3 86 97 83 51",
    "sg:postcode":"89100",
    "sg:province":"Bourgogne",
    "wof:name":"Soci\u00e9t\u00e9 J.c. Pothin S.a.r.l.",
    "wof:placetype":"venue"
},
  "geometry": {"coordinates":[3.351139,48.215317],"type":"Point"}
}