{
  "type": "Feature",
  "properties": {
    "iso:country":"FR",
    "sg:address":"Zac De Kergaradec 29850 GOUESNOU",
    "sg:city":"Gouesnou",
    "sg:orig_category":"Slaughter-Houses, Abattoirs",
    "sg:phone":"+33 2 98 41 98 33",
    "sg:postcode":"29850",
    "sg:province":"Bretagne",
    "wof:name":"Societe Herve Goar S.a.r.l",
    "wof:placetype":"venue"
},
  "geometry": {"coordinates":[-4.465689,48.44989],"type":"Point"}
}