{
  "type": "Feature",
  "properties": {
    "iso:country":"FR",
    "sg:address":"22 avenue Descartes 94450 Limeil Brevannes",
    "sg:classifiers":[
        {
            "category":"Professional",
            "subcategory":"Testing Lab",
            "type":"Services"
        }
    ],
    "sg:phone":"+33 1 45 10 67 00",
    "sg:postcode":"94450",
    "sg:province":"Ile de France",
    "sg:tags":[
        "laboratory"
    ],
    "wof:name":"Philips France Sa",
    "wof:placetype":"venue"
},
  "geometry": {"coordinates":[2.482419,48.740864],"type":"Point"}
}