{
  "type": "Feature",
  "properties": {
    "iso:country":"FR",
    "sg:address":"21 rue de la Gare 17330 LOULAY",
    "sg:classifiers":[
        {
            "category":"Real Estate",
            "subcategory":"Architect",
            "type":"Services"
        }
    ],
    "sg:phone":"+33 5 46 33 68 00",
    "sg:postcode":"17330",
    "sg:province":"Poitou-Charentes",
    "sg:tags":[
        "use",
        "industrial",
        "plywood"
    ],
    "wof:name":"St\u00e9 Malvaux Sas",
    "wof:placetype":"venue"
},
  "geometry": {"coordinates":[-0.509421,46.044579],"type":"Point"}
}