{
  "type": "Feature",
  "properties": {
    "iso:country":"FR",
    "sg:address":"Rue De La Paix",
    "sg:city":"Laragne Monteglin",
    "sg:classifiers":[
        {
            "category":"Banks & Credit Unions",
            "subcategory":"Financial Services",
            "type":"Services"
        }
    ],
    "sg:phone":"+33 4 92 65 11 44",
    "sg:postcode":"05300",
    "sg:province":"Provence-Alpes-C\u00f4te d'Azur",
    "sg:tags":[
        "banking",
        "finance",
        "insurance"
    ],
    "wof:name":"Credit Agricole Alpes Provence (cap) Agence De Laragne",
    "wof:placetype":"venue"
},
  "geometry": {"coordinates":[5.84117,44.310799],"type":"Point"}
}