{
  "type": "Feature",
  "properties": {
    "addr:full":"Site Industriel Leurette 59820 Gravelines Nord Pas-de-Calais 59820",
    "addr:postcode":"59820;59820",
    "addr:street":"Gravelines Nord",
    "iso:country":"FR",
    "sg:address":"Site Industriel Leurette 59820 Gravelines",
    "sg:classifiers":[
        {
            "category":"Wholesale",
            "subcategory":"Machinery & Supplies",
            "type":"Manufacturing & Wholesale Goods"
        }
    ],
    "sg:phone":"+33 3 28 23 92 69",
    "sg:postcode":"59820",
    "sg:province":"Nord Pas-de-Calais",
    "sg:tags":[
        "handling",
        "material",
        "-",
        "machine",
        "equipment",
        "engineering",
        "mechanical"
    ],
    "wof:name":"Conditionnement Manutention Convoyage (cmc)",
    "wof:placetype":"venue"
},
  "geometry": {"coordinates":[2.13518,50.990211],"type":"Point"}
}