{
  "type": "Feature",
  "properties": {
    "iso:country":"FR",
    "sg:address":"33, Av. des Champs Elys\u00e9es, 75008 Paris",
    "sg:orig_category":"Non-Classified Establishments",
    "sg:phone":"+33 1 42 25 31 92",
    "sg:postcode":"75008",
    "sg:province":"Ile de France",
    "wof:name":"A\u00e9roflot",
    "wof:placetype":"venue"
},
  "geometry": {"coordinates":[2.306706,48.870007],"type":"Point"}
}