{
  "type": "Feature",
  "properties": {
    "iso:country":"FR",
    "sg:address":"Z.I. Arc les Gray",
    "sg:city":"Arc l\u00e8s Gray",
    "sg:orig_category":"Unclassifiable Establishments",
    "sg:phone":"+33 3 84 64 75 00",
    "sg:postcode":"70100",
    "sg:province":"Franche Comt\u00e9",
    "wof:name":"Simu S.a.",
    "wof:placetype":"venue"
},
  "geometry": {"coordinates":[5.514565,47.369511],"type":"Point"}
}