{
  "type": "Feature",
  "properties": {
    "iso:country":"FR",
    "sg:address":"Zi Artois Flandres 62138 Douvrin",
    "sg:classifiers":[
        {
            "category":"Professional",
            "type":"Services"
        }
    ],
    "sg:phone":"+33 3 21 40 29 29",
    "sg:province":"Nord Pas-de-Calais",
    "sg:tags":[
        "transport",
        "road"
    ],
    "wof:name":"Marsy Transports Et Logistique",
    "wof:placetype":"venue"
},
  "geometry": {"coordinates":[2.831475,50.508141],"type":"Point"}
}