{
  "type": "Feature",
  "properties": {
    "addr:full":"240, Rue des Bois Blancs, 59800 Lille Nord Pas-de-Calais",
    "addr:housenumber":"240",
    "addr:postcode":"59800",
    "addr:street":"Rue Des Bois Blancs",
    "iso:country":"FR",
    "sg:address":"240, Rue des Bois Blancs, 59800 Lille",
    "sg:orig_category":"Unclassifiable Establishments",
    "sg:phone":"+33 3 20 09 03 19",
    "sg:province":"Nord Pas-de-Calais",
    "wof:name":"Axc Distribution S.a.",
    "wof:placetype":"venue"
},
  "geometry": {"coordinates":[3.024417,50.630554],"type":"Point"}
}