{
  "type": "Feature",
  "properties": {
    "iso:country":"FR",
    "sg:address":"11, Rue Ernest Chaput - Z.A.E. Capnord, 21000 Dijon",
    "sg:city":"Dijon",
    "sg:orig_category":"Non-Classified Establishments",
    "sg:phone":"+33 3 80 71 36 73",
    "sg:postcode":"21000",
    "sg:province":"Bourgogne",
    "wof:name":"Pion Sylvain S.a.r.l. - Division Jet D\u00e9coup'",
    "wof:placetype":"venue"
},
  "geometry": {"coordinates":[5.06538,47.344532],"type":"Point"}
}