{
  "type": "Feature",
  "properties": {
    "iso:country":"FR",
    "sg:address":"22 Rue Des Joncs Aubigny 77950 Montereau Sur Le Jard",
    "sg:classifiers":[
        {
            "category":"Utilities",
            "subcategory":"Telephone",
            "type":"Services"
        }
    ],
    "sg:phone":"+33 1 64 38 88 44",
    "sg:province":"Ile de France",
    "sg:tags":[
        "telecommunication"
    ],
    "wof:name":"Xr Systems",
    "wof:placetype":"venue"
},
  "geometry": {"coordinates":[2.737446,48.563068],"type":"Point"}
}