{
  "type": "Feature",
  "properties": {
    "iso:country":"FR",
    "sg:address":"225 Route D'Angoul\u00e8me 24000 P\u00e9rigueux",
    "sg:city":"P\u00e9rigueux",
    "sg:classifiers":[
        {
            "category":"Utilities",
            "subcategory":"Electric",
            "type":"Services"
        }
    ],
    "sg:phone":"+33 5 53 35 00 02",
    "sg:postcode":"24000",
    "sg:province":"Aquitaine",
    "sg:tags":[
        "electricity",
        "electronic",
        "electrical",
        "equipment"
    ],
    "wof:name":"Omnium Electrique Du Sud Ouest (oeso)",
    "wof:placetype":"venue"
},
  "geometry": {"coordinates":[0.70664,45.194248],"type":"Point"}
}