{
  "type": "Feature",
  "properties": {
    "iso:country":"FR",
    "sg:address":"B.P. 10, 17510 Villiers Couture^^19, Rte de Cognac, 17510 Villiers Couture",
    "sg:orig_category":"Non-Classified Establishments",
    "sg:phone":"+33 5 46 33 64 22",
    "sg:province":"Poitou-Charentes",
    "wof:name":"Sotrinbois S.a.",
    "wof:placetype":"venue"
},
  "geometry": {"coordinates":[-0.237104,45.974369],"type":"Point"}
}