{
  "type": "Feature",
  "properties": {
    "addr:full":"ZI de la Croisette Vittel Lorraine 88800",
    "addr:postcode":"88800",
    "addr:street":"Zi De La Croisette",
    "iso:country":"FR",
    "sg:address":"ZI de la Croisette",
    "sg:city":"Vittel",
    "sg:orig_category":"Non-Classified Establishments",
    "sg:phone":"+33 3 29 08 16 45",
    "sg:postcode":"88800",
    "sg:province":"Lorraine",
    "wof:name":"M.s.m.i. S.a.r.l.- Machines Sp\u00e9ciales Marquage Industriel",
    "wof:placetype":"venue"
},
  "geometry": {"coordinates":[5.944675,48.202614],"type":"Point"}
}