{
  "type": "Feature",
  "properties": {
    "addr:full":"27/29, Rue de Lyon, 71000 M\u00e2con Sanc\u00e9 Bourgogne 71000",
    "addr:housenumber":"27 / 29",
    "addr:postcode":"71000;71000",
    "addr:street":"Rue De Lyon",
    "iso:country":"FR",
    "sg:address":"27/29, Rue de Lyon, 71000 M\u00e2con",
    "sg:city":"Sanc\u00e9",
    "sg:orig_category":"Unclassifiable Establishments",
    "sg:phone":"+33 3 85 21 95 21",
    "sg:postcode":"71000",
    "sg:province":"Bourgogne",
    "wof:name":"E.m.m. Mencarelli S.a.r.l. - Entreprise M\u00e9canographie M\u00e2connaise Mencarelli",
    "wof:placetype":"venue"
},
  "geometry": {"coordinates":[4.827873,46.300652],"type":"Point"}
}