{
  "type": "Feature",
  "properties": {
    "iso:country":"FR",
    "sg:address":"1355 avenue de Draguignan 83130 La Garde",
    "sg:city":"La Garde",
    "sg:classifiers":[
        {
            "category":"Recreation",
            "subcategory":"Boat Charter",
            "type":"Entertainment"
        }
    ],
    "sg:phone":"+33 4 94 08 68 20",
    "sg:postcode":"38520",
    "sg:province":"Rhone-Alpes",
    "sg:tags":[
        "engine"
    ],
    "wof:name":"Vidal Diffusion Marine Sas",
    "wof:placetype":"venue"
},
  "geometry": {"coordinates":[6.037427,43.143127],"type":"Point"}
}