{
  "type": "Feature",
  "properties": {
    "iso:country":"FR",
    "sg:address":"6 Boulevard John Kennedy 91100 Corbeil Essonnes",
    "sg:classifiers":[
        {
            "category":"Wholesale",
            "subcategory":"Machinery & Supplies",
            "type":"Manufacturing & Wholesale Goods"
        }
    ],
    "sg:phone":"+33 1 64 96 09 76",
    "sg:postcode":"91100",
    "sg:province":"Ile de France",
    "sg:tags":[
        "handling",
        "material",
        "-",
        "machine",
        "equipment",
        "engineering",
        "mechanical"
    ],
    "wof:name":"Amps",
    "wof:placetype":"venue"
},
  "geometry": {"coordinates":[2.477242,48.591045],"type":"Point"}
}