{
  "type": "Feature",
  "properties": {
    "iso:country":"FR",
    "sg:address":"Impasse Lamboy",
    "sg:city":"Caudebec les Elbeuf",
    "sg:orig_category":"Non-Classified Establishments",
    "sg:phone":"+33 2 35 77 21 00",
    "sg:postcode":"76320",
    "sg:province":"Haute Normandie",
    "wof:name":"S.d.t.m. S.a.r.l. - Soci\u00e9t\u00e9 De D\u00e9capage Thermique Et De Maintenance",
    "wof:placetype":"venue"
},
  "geometry": {"coordinates":[1.02345,49.287861],"type":"Point"}
}