{
  "type": "Feature",
  "properties": {
    "addr:full":"109 Avenue De Lyon 63600 Ambert Ambert Auvergne 63600",
    "addr:housenumber":"109",
    "addr:postcode":"63600;63600",
    "addr:street":"Avenue De Lyon",
    "iso:country":"FR",
    "sg:address":"109 Avenue De Lyon 63600 Ambert",
    "sg:city":"Ambert",
    "sg:classifiers":[
        {
            "category":"Manufacturing",
            "subcategory":"Textiles",
            "type":"Manufacturing & Wholesale Goods"
        }
    ],
    "sg:phone":"+33 4 73 82 54 98",
    "sg:postcode":"63600",
    "sg:province":"Auvergne",
    "sg:tags":[
        "printing",
        "clothing",
        "fabric"
    ],
    "wof:name":"Teritex Impression",
    "wof:placetype":"venue"
},
  "geometry": {"coordinates":[3.746087,45.548126],"type":"Point"}
}