{
  "type": "Feature",
  "properties": {
    "addr:full":"9 R Du Centre 88150 Chavelot Lorraine",
    "addr:housenumber":"9",
    "addr:postcode":"88150",
    "addr:street":"R Du Centre",
    "iso:country":"FR",
    "sg:address":"9 R Du Centre 88150 Chavelot",
    "sg:classifiers":[
        {
            "category":"Professional",
            "type":"Services"
        }
    ],
    "sg:phone":"+33 3 29 31 56 87",
    "sg:province":"Lorraine",
    "sg:tags":[
        "transport",
        "road"
    ],
    "wof:name":"Bonvicini Sarl",
    "wof:placetype":"venue"
},
  "geometry": {"coordinates":[6.437909,48.237076],"type":"Point"}
}