{
  "type": "Feature",
  "properties": {
    "addr:full":"23 Boulevard De Plombieres 13003 Marseille Poitou-Charentes",
    "addr:housenumber":"23",
    "addr:postcode":"13003",
    "addr:street":"Boulevard De Plombieres",
    "iso:country":"FR",
    "sg:address":"23 Boulevard De Plombieres 13003 Marseille",
    "sg:classifiers":[
        {
            "category":"Shopping",
            "subcategory":"Clothing, Apparel, & Fashions",
            "type":"Retail Goods"
        }
    ],
    "sg:phone":"+33 4 91 05 85 27",
    "sg:province":"Poitou-Charentes",
    "sg:tags":[
        "textile",
        "clothing",
        "clothes"
    ],
    "wof:name":"Atelier Plus Sports",
    "wof:placetype":"venue"
},
  "geometry": {"coordinates":[5.386634,43.315136],"type":"Point"}
}