{
  "type": "Feature",
  "properties": {
    "addr:full":"rue du Vignoble Franc ZI d'Amphion 74500 Evian les Bains Rhone-Alpes",
    "addr:postcode":"74500",
    "addr:street":"Rue Du Vignoble;Zi D'Amphion",
    "iso:country":"FR",
    "sg:address":"rue du Vignoble Franc ZI d'Amphion 74500 Evian les Bains",
    "sg:classifiers":[
        {
            "category":"Wholesale",
            "subcategory":"Chemicals & Plastics",
            "type":"Manufacturing & Wholesale Goods"
        }
    ],
    "sg:phone":"+33 4 50 71 49 65",
    "sg:province":"Rhone-Alpes",
    "sg:tags":[
        "articles",
        "sterile",
        "disposable"
    ],
    "wof:name":"Mpl S.a.r.l.",
    "wof:placetype":"venue"
},
  "geometry": {"coordinates":[6.588357,46.400627],"type":"Point"}
}