{
  "type": "Feature",
  "properties": {
    "addr:full":"5, Rue Jean Dumas, 24660 Coulounieix Chamiers Coulounieix-Chamiers Aquitaine 24660",
    "addr:housenumber":"5",
    "addr:postcode":"24660;24660",
    "addr:street":"Rue Jean Dumas",
    "iso:country":"FR",
    "sg:address":"5, Rue Jean Dumas, 24660 Coulounieix Chamiers",
    "sg:city":"Coulounieix-Chamiers",
    "sg:orig_category":"Unclassifiable Establishments",
    "sg:phone":"+33 5 53 02 45 50",
    "sg:postcode":"24660",
    "sg:province":"Aquitaine",
    "wof:name":"Coop\u00e8re S.a.",
    "wof:placetype":"venue"
},
  "geometry": {"coordinates":[0.689373,45.185429],"type":"Point"}
}