{
  "type": "Feature",
  "properties": {
    "addr:full":"5, Rue Pierre Corneille, 95500 Gonesse Ile de France",
    "addr:housenumber":"5",
    "addr:postcode":"95500;ile",
    "addr:street":"Rue Pierre Corneille",
    "iso:country":"FR",
    "sg:address":"5, Rue Pierre Corneille, 95500 Gonesse",
    "sg:orig_category":"Unclassifiable Establishments",
    "sg:phone":"+33 1 39 85 11 50",
    "sg:province":"Ile de France",
    "wof:name":"Impex S.a.r.l.",
    "wof:placetype":"venue"
},
  "geometry": {"coordinates":[2.437152,48.984116],"type":"Point"}
}