{
  "type": "Feature",
  "properties": {
    "iso:country":"FR",
    "sg:address":"12-14 Av Industrielle 59520 Marquette Lez Lille",
    "sg:classifiers":[
        {
            "category":"Manufacturing",
            "subcategory":"Tools & Machinery",
            "type":"Manufacturing & Wholesale Goods"
        }
    ],
    "sg:phone":"+33 3 20 42 25 42",
    "sg:postcode":"59520",
    "sg:province":"Nord Pas-de-Calais",
    "sg:tags":[
        "equipment",
        "measurement",
        "-",
        "precision",
        "instrument"
    ],
    "wof:name":"Wateau Sa",
    "wof:placetype":"venue"
},
  "geometry": {"coordinates":[3.054847,50.678043],"type":"Point"}
}