{
  "type": "Feature",
  "properties": {
    "addr:full":"73, Rue Alessandro Volta, 33700 M\u00e9rignac M\u00e9rignac Aquitaine 33700",
    "addr:housenumber":"73",
    "addr:postcode":"33700;33700",
    "addr:street":"Rue Alessandro Volta",
    "iso:country":"FR",
    "sg:address":"73, Rue Alessandro Volta, 33700 M\u00e9rignac",
    "sg:city":"M\u00e9rignac",
    "sg:orig_category":"Non-Classified Establishments",
    "sg:phone":"+33 5 56 13 31 31",
    "sg:postcode":"33700",
    "sg:province":"Aquitaine",
    "wof:name":"Technal S.a.",
    "wof:placetype":"venue"
},
  "geometry": {"coordinates":[-0.676154,44.853756],"type":"Point"}
}