{
  "type": "Feature",
  "properties": {
    "addr:full":"57 Vaneau 75007 PARIS Ile de France",
    "addr:housenumber":"57",
    "addr:postcode":"75007",
    "addr:street":"Vaneau",
    "iso:country":"FR",
    "sg:address":"57",
    "sg:city":"Vaneau 75007 PARIS",
    "sg:classifiers":[
        {
            "category":"Professional",
            "type":"Services"
        }
    ],
    "sg:phone":"+33 1 53 63 02 29",
    "sg:province":"Ile de France",
    "sg:tags":[
        "transport",
        "road"
    ],
    "wof:name":"Speed Courses Master",
    "wof:placetype":"venue"
},
  "geometry": {"coordinates":[2.319881,48.850109],"type":"Point"}
}