{
  "type": "Feature",
  "properties": {
    "iso:country":"FR",
    "sg:address":"La Blanche Tache Zac 80450 Camon",
    "sg:classifiers":[
        {
            "category":"Bakery",
            "type":"Food & Drink"
        }
    ],
    "sg:phone":"+33 3 22 70 15 15",
    "sg:postcode":"80450",
    "sg:province":"Picardie",
    "sg:tags":[
        "cake",
        "product",
        "related",
        "bread"
    ],
    "wof:name":"Touflet Tradition",
    "wof:placetype":"venue"
},
  "geometry": {"coordinates":[2.34342,49.887493],"type":"Point"}
}