{
  "type": "Feature",
  "properties": {
    "addr:full":"3, Rue du Cirque, 75008 Paris Ile de France",
    "addr:housenumber":"3",
    "addr:postcode":"75008",
    "addr:street":"Rue Du Cirque",
    "iso:country":"FR",
    "sg:address":"3, Rue du Cirque, 75008 Paris",
    "sg:orig_category":"Unclassifiable Establishments",
    "sg:phone":"+33 1 42 25 12 73",
    "sg:province":"Ile de France",
    "wof:name":"Alterego S.a.r.l.",
    "wof:placetype":"venue"
},
  "geometry": {"coordinates":[2.313684,48.869919],"type":"Point"}
}