{
  "type": "Feature",
  "properties": {
    "addr:full":"rue Des Etangs ZI 76340 BLANGY SUR BRESLE Haute Normandie 76340",
    "addr:postcode":"76340;76340",
    "addr:street":"Rue Des Etangs Zi;Haute Normandie",
    "iso:country":"FR",
    "sg:address":"rue Des Etangs ZI 76340 BLANGY SUR BRESLE",
    "sg:classifiers":[
        {
            "category":"Manufacturing",
            "subcategory":"Rubber & Plastics",
            "type":"Manufacturing & Wholesale Goods"
        }
    ],
    "sg:phone":"+33 2 35 93 32 33",
    "sg:postcode":"76340",
    "sg:province":"Haute Normandie",
    "sg:tags":[
        "injection",
        "moulding",
        "dy"
    ],
    "wof:name":"Fabrique De Moules Et Injectionplastique S.a.r.l.",
    "wof:placetype":"venue"
},
  "geometry": {"coordinates":[1.593718,49.821468],"type":"Point"}
}