{
  "type": "Feature",
  "properties": {
    "addr:full":"16 Rue Racine 94120 Fontenay Sous Bois Ile de France",
    "addr:housenumber":"16",
    "addr:postcode":"94120",
    "addr:street":"Rue Racine;Bois Ile De France",
    "iso:country":"FR",
    "sg:address":"16 Rue Racine 94120 Fontenay Sous Bois",
    "sg:classifiers":[
        {
            "category":"Professional",
            "type":"Services"
        }
    ],
    "sg:phone":"+33 1 48 76 27 93",
    "sg:province":"Ile de France",
    "sg:tags":[
        "transport",
        "road"
    ],
    "wof:name":"Jurquet Paul",
    "wof:placetype":"venue"
},
  "geometry": {"coordinates":[2.467972,48.857967],"type":"Point"}
}