{
  "type": "Feature",
  "properties": {
    "addr:full":"2, Rue Raoul Follereau, 38180 Seyssins Rhone-Alpes",
    "addr:housenumber":"2",
    "addr:postcode":"38180",
    "addr:street":"Rue Raoul Follereau",
    "iso:country":"FR",
    "sg:address":"2, Rue Raoul Follereau, 38180 Seyssins",
    "sg:orig_category":"Unclassifiable Establishments",
    "sg:phone":"+33 4 76 96 46 54",
    "sg:province":"Rhone-Alpes",
    "wof:name":"Manutention Service Dauphin\u00e9 S.a.",
    "wof:placetype":"venue"
},
  "geometry": {"coordinates":[5.694095,45.163811],"type":"Point"}
}