{
  "type": "Feature",
  "properties": {
    "addr:full":"2 rue Saint Pierre; Roye; 80700 Picardie 80700",
    "addr:housenumber":"2",
    "addr:postcode":"80700;80700",
    "addr:street":"Rue Saint Pierre Roye",
    "iso:country":"FR",
    "sg:address":"2 rue Saint Pierre; Roye; 80700",
    "sg:classifiers":[
        {
            "category":"Banks & Credit Unions",
            "subcategory":"Bank",
            "type":"Services"
        }
    ],
    "sg:phone":"+33 22870058",
    "sg:postcode":"80700",
    "sg:province":"Picardie",
    "wof:name":"Banque Nationale De Paris",
    "wof:placetype":"venue"
},
  "geometry": {"coordinates":[2.790616,49.698421],"type":"Point"}
}