{
  "type": "Feature",
  "properties": {
    "addr:full":"316 Route De Bayonne 31060 Toulouse Cedex 03 Champagne",
    "addr:housenumber":"316",
    "addr:postcode":"31060",
    "addr:street":"Route De Bayonne",
    "iso:country":"FR",
    "sg:address":"316 Route De Bayonne 31060 Toulouse Cedex 03",
    "sg:classifiers":[
        {
            "category":"Manufacturing",
            "subcategory":"Aerospace",
            "type":"Manufacturing & Wholesale Goods"
        }
    ],
    "sg:phone":"+33 5 61 93 55 55",
    "sg:province":"Champagne",
    "sg:tags":[
        "equipment",
        "aeronautic",
        "transport",
        "vehicle"
    ],
    "wof:name":"Airbus France",
    "wof:placetype":"venue"
},
  "geometry": {"coordinates":[1.3724,43.611069],"type":"Point"}
}