{
  "type": "Feature",
  "properties": {
    "iso:country":"FR",
    "sg:address":"Quartier les Carri\u00e8res - ZA les Plaines",
    "sg:city":"Saint Marcel les Valence",
    "sg:orig_category":"Non-Classified Establishments",
    "sg:phone":"+33 4 75 58 88 78",
    "sg:postcode":"26320",
    "sg:province":"Rhone-Alpes",
    "wof:name":"S.t.m.i.",
    "wof:placetype":"venue"
},
  "geometry": {"coordinates":[4.95728,44.971901],"type":"Point"}
}