{
  "type": "Feature",
  "properties": {
    "addr:full":"7, Place Louis le S\u00e9n\u00e9chal, 62250 Marquise Nord Pas-de-Calais",
    "addr:housenumber":"7",
    "addr:postcode":"62250",
    "addr:street":"Place Louis Le Se\u0301Ne\u0301Chal",
    "iso:country":"FR",
    "sg:address":"7, Place Louis le S\u00e9n\u00e9chal, 62250 Marquise",
    "sg:orig_category":"Unclassifiable Establishments",
    "sg:phone":"+33 3 21 87 85 20",
    "sg:province":"Nord Pas-de-Calais",
    "wof:name":"Deschodt S.a.",
    "wof:placetype":"venue"
},
  "geometry": {"coordinates":[1.704325,50.814339],"type":"Point"}
}