{
  "type": "Feature",
  "properties": {
    "addr:full":"17 Rue De Habsheim 68170 Rixheim Rixheim Alsace 68170",
    "addr:housenumber":"17",
    "addr:postcode":"68170;68170",
    "addr:street":"Rue De Habsheim;Rixheim",
    "iso:country":"FR",
    "sg:address":"17 Rue De Habsheim 68170 Rixheim",
    "sg:city":"Rixheim",
    "sg:classifiers":[
        {
            "category":"Professional",
            "subcategory":"Engineering",
            "type":"Services"
        }
    ],
    "sg:phone":"+33 3 89 44 03 25",
    "sg:postcode":"68170",
    "sg:province":"Alsace",
    "sg:tags":[
        "machine",
        "-",
        "mechanical"
    ],
    "wof:name":"Endel",
    "wof:placetype":"venue"
},
  "geometry": {"coordinates":[7.409977,47.747753],"type":"Point"}
}