{
  "type": "Feature",
  "properties": {
    "addr:full":"B.P. 89, 21603 Longvic C\u00e9dex^^6, Bd de Chicago, 21600 Longvic Longvic Bourgogne 21600",
    "addr:postcode":"21603;ce\u0301dex^^6;21600;21600",
    "addr:street":"B.P. 89;Bd De Chicago",
    "iso:country":"FR",
    "sg:address":"B.P. 89, 21603 Longvic C\u00e9dex^^6, Bd de Chicago, 21600 Longvic",
    "sg:city":"Longvic",
    "sg:orig_category":"Non-Classified Establishments",
    "sg:phone":"+33 3 80 65 19 61",
    "sg:postcode":"21600",
    "sg:province":"Bourgogne",
    "wof:name":"C.i.c.o. S.a. - Carrosserie Industrielle De La C\u00f4te D'or",
    "wof:placetype":"venue"
},
  "geometry": {"coordinates":[5.06327,47.286015],"type":"Point"}
}