{
  "type": "Feature",
  "properties": {
    "iso:country":"FR",
    "sg:address":"B.P. 19, 85230 Beauvoir sur Mer^^45, Rue du Port, 85230 Beauvoir sur Mer",
    "sg:orig_category":"Non-Classified Establishments",
    "sg:phone":"+33 2 51 68 70 42",
    "sg:province":"Pays de Loire",
    "wof:name":"Inter Coop Production",
    "wof:placetype":"venue"
},
  "geometry": {"coordinates":[-2.009314,46.87661],"type":"Point"}
}