{
  "type": "Feature",
  "properties": {
    "addr:full":"1/9, Chemin de Chapoly, 69230 Saint Genis Laval Rhone-Alpes",
    "addr:housenumber":"1 / 9",
    "addr:postcode":"69230",
    "addr:street":"Chemin De Chapoly;Genis;Rhone-Alpes",
    "iso:country":"FR",
    "sg:address":"1/9, Chemin de Chapoly, 69230 Saint Genis Laval",
    "sg:orig_category":"Unclassifiable Establishments",
    "sg:phone":"+33 4 78 56 95 60",
    "sg:province":"Rhone-Alpes",
    "wof:name":"Herv\u00e9 Thermique S.a.",
    "wof:placetype":"venue"
},
  "geometry": {"coordinates":[4.79296,45.694736],"type":"Point"}
}