{
  "type": "Feature",
  "properties": {
    "addr:full":"5 rue de Reims; Crozon; 29160 Crozon Bretagne 29160",
    "addr:housenumber":"5",
    "addr:postcode":"29160;29160",
    "addr:street":"Rue De Reims;Bretagne",
    "iso:country":"FR",
    "sg:address":"5 rue de Reims; Crozon; 29160",
    "sg:city":"Crozon",
    "sg:classifiers":[
        {
            "category":"Banks & Credit Unions",
            "subcategory":"Bank",
            "type":"Services"
        }
    ],
    "sg:phone":"+33 3398271379",
    "sg:postcode":"29160",
    "sg:province":"Bretagne",
    "wof:name":"Banque Nationale De Paris",
    "wof:placetype":"venue"
},
  "geometry": {"coordinates":[-4.490067,48.246311],"type":"Point"}
}