{
  "type": "Feature",
  "properties": {
    "addr:full":"La Chezatte 18240 Ste Gemme En Sancerrois Belleville-sur-Loire Centre 18240",
    "addr:postcode":"18240;18240",
    "addr:street":"Gemme",
    "iso:country":"FR",
    "sg:address":"La Chezatte 18240 Ste Gemme En Sancerrois",
    "sg:city":"Belleville-sur-Loire",
    "sg:classifiers":[
        {
            "category":"Food Court",
            "type":"Food & Drink"
        }
    ],
    "sg:phone":"+33 2 48 79 37 14",
    "sg:postcode":"18240",
    "sg:province":"Centre",
    "sg:tags":[
        "product",
        "related"
    ],
    "wof:name":"Domaine De La Chezatte",
    "wof:placetype":"venue"
},
  "geometry": {"coordinates":[2.83047,47.40205],"type":"Point"}
}