{
  "type": "Feature",
  "properties": {
    "iso:country":"FR",
    "sg:address":"3, Av. Didier Daurat, 31400 Toulouse",
    "sg:orig_category":"Unclassifiable Establishments",
    "sg:phone":"+33 5 62 47 49 89",
    "sg:province":"Midi Pyr\u00e9n\u00e9es",
    "wof:name":"Adermip",
    "wof:placetype":"venue"
},
  "geometry": {"coordinates":[1.491024,43.565601],"type":"Point"}
}