{
  "type": "Feature",
  "properties": {
    "addr:full":"18, Rue de la R\u00e9publique, 13400 Aubagne Picardie",
    "addr:housenumber":"18",
    "addr:postcode":"13400",
    "addr:street":"Rue De La Re\u0301Publique",
    "iso:country":"FR",
    "sg:address":"18, Rue de la R\u00e9publique, 13400 Aubagne",
    "sg:orig_category":"Non-Classified Establishments",
    "sg:phone":"+33 4 42 03 04 05",
    "sg:province":"Picardie",
    "wof:name":"C.r.i.t. Int\u00e9rim S.a.",
    "wof:placetype":"venue"
},
  "geometry": {"coordinates":[5.568202,43.292198],"type":"Point"}
}