{
  "type": "Feature",
  "properties": {
    "addr:full":"4 Rue De Clairy 75002 Paris Ile de France 75002",
    "addr:housenumber":"4",
    "addr:postcode":"75002;75002",
    "addr:street":"Rue De Clairy",
    "iso:country":"FR",
    "sg:address":"4 Rue De Clairy 75002 Paris",
    "sg:classifiers":[
        {
            "category":"Shopping",
            "subcategory":"Clothing, Apparel, & Fashions",
            "type":"Retail Goods"
        }
    ],
    "sg:phone":"+33 1 42 36 31 24",
    "sg:postcode":"75002",
    "sg:province":"Ile de France",
    "sg:tags":[
        "textile",
        "clothing",
        "fabric",
        "accessory"
    ],
    "wof:name":"Afritex Sa",
    "wof:placetype":"venue"
},
  "geometry": {"coordinates":[2.34069,48.866241],"type":"Point"}
}