{
  "type": "Feature",
  "properties": {
    "addr:full":"29 Boulevard Haussmann Paris Ile de France 75009",
    "addr:housenumber":"29",
    "addr:postcode":"75009",
    "addr:street":"Boulevard Haussmann",
    "iso:country":"FR",
    "sg:address":"29 Boulevard Haussmann",
    "sg:city":"Paris",
    "sg:classifiers":[
        {
            "category":"Banks & Credit Unions",
            "subcategory":"Financial Services",
            "type":"Services"
        }
    ],
    "sg:phone":"+33 1 42 14 32 68",
    "sg:postcode":"75009",
    "sg:province":"Ile de France",
    "sg:tags":[
        "banking",
        "finance",
        "insurance"
    ],
    "wof:name":"Ste Financiere Credit Bail",
    "wof:placetype":"venue"
},
  "geometry": {"coordinates":[2.332342,48.872936],"type":"Point"}
}