{
  "type": "Feature",
  "properties": {
    "addr:full":"B.P. 45, 69171 Tarare C\u00e9dex^^4, Rue de Thizy, 69170 Tarare Rhone-Alpes 69170",
    "addr:postcode":"69171;69170;69170",
    "addr:street":"B.P. 45;Rue De Thizy",
    "iso:country":"FR",
    "sg:address":"B.P. 45, 69171 Tarare C\u00e9dex^^4, Rue de Thizy, 69170 Tarare",
    "sg:orig_category":"Non-Classified Establishments",
    "sg:phone":"+33 4 74 05 00 00",
    "sg:postcode":"69170",
    "sg:province":"Rhone-Alpes",
    "wof:name":"Chatelard S.a.",
    "wof:placetype":"venue"
},
  "geometry": {"coordinates":[4.402325,45.84494],"type":"Point"}
}