{
  "type": "Feature",
  "properties": {
    "addr:full":"ZA 75011 Paris Ile de France",
    "addr:postcode":"75011",
    "addr:street":"Za",
    "iso:country":"FR",
    "sg:address":"ZA 75011 Paris",
    "sg:classifiers":[
        {
            "category":"Shopping",
            "subcategory":"Clothing, Apparel, & Fashions",
            "type":"Retail Goods"
        }
    ],
    "sg:phone":"+33 1 53 99 95 00",
    "sg:province":"Ile de France",
    "sg:tags":[
        "work",
        "clothes"
    ],
    "wof:name":"Manufacture Btt Hasson Freres Sa",
    "wof:placetype":"venue"
},
  "geometry": {"coordinates":[2.379995,48.857594],"type":"Point"}
}