{
  "type": "Feature",
  "properties": {
    "iso:country":"FR",
    "sg:address":"1, Av. de l'Europe, 95330 Domont",
    "sg:orig_category":"Non-Classified Establishments",
    "sg:phone":"+33 1 39 35 79 08",
    "sg:postcode":"95330",
    "sg:province":"Ile de France",
    "wof:name":"Altec S.a.r.l.",
    "wof:placetype":"venue"
},
  "geometry": {"coordinates":[2.344992,49.027046],"type":"Point"}
}