{
  "type": "Feature",
  "properties": {
    "addr:full":"10 Chem De La Curzeille 74300 Cluses Rhone-Alpes 74300",
    "addr:housenumber":"10",
    "addr:postcode":"74300;74300",
    "addr:street":"Chem De La Curzeille",
    "iso:country":"FR",
    "sg:address":"10 Chem De La Curzeille 74300 Cluses",
    "sg:classifiers":[
        {
            "category":"Manufacturing",
            "subcategory":"Metals",
            "type":"Manufacturing & Wholesale Goods"
        }
    ],
    "sg:phone":"+33 4 50 98 68 73",
    "sg:postcode":"74300",
    "sg:province":"Rhone-Alpes",
    "sg:tags":[
        "metallurgy",
        "metalworking",
        "processing"
    ],
    "wof:name":"Fravidec Sa",
    "wof:placetype":"venue"
},
  "geometry": {"coordinates":[6.58099,46.068909],"type":"Point"}
}