{
  "type": "Feature",
  "properties": {
    "iso:country":"FR",
    "sg:address":"62, Av. Camus, 44000 Nantes",
    "sg:orig_category":"Non-Classified Establishments",
    "sg:phone":"+33 2 51 72 70 30",
    "sg:province":"Pays de Loire",
    "wof:name":"Parsys S.a.",
    "wof:placetype":"venue"
},
  "geometry": {"coordinates":[-1.574838,47.219952],"type":"Point"}
}