{
  "type": "Feature",
  "properties": {
    "addr:full":"2 ave Gabriel Peri; Paris; 92230 Ile de France 92230",
    "addr:postcode":"92230;92230",
    "addr:street":"2 Ave Gabriel Peri Paris;France",
    "iso:country":"FR",
    "sg:address":"2 ave Gabriel Peri; Paris; 92230",
    "sg:classifiers":[
        {
            "category":"Banks & Credit Unions",
            "subcategory":"Bank",
            "type":"Services"
        }
    ],
    "sg:phone":"+33 2 47 93 11 99",
    "sg:postcode":"92230",
    "sg:province":"Ile de France",
    "wof:name":"Banque Commerciale, Du Maroc Sa",
    "wof:placetype":"venue"
},
  "geometry": {"coordinates":[2.29447,48.925026],"type":"Point"}
}