{
  "type": "Feature",
  "properties": {
    "iso:country":"FR",
    "sg:address":"38 Rue Emile Basly 59124 Escaudain",
    "sg:classifiers":[
        {
            "category":"Professional",
            "type":"Services"
        }
    ],
    "sg:phone":"+33 3 27 43 13 38",
    "sg:province":"Nord Pas-de-Calais",
    "sg:tags":[
        "transport",
        "road"
    ],
    "wof:name":"Larousse Sorriaux Marcel",
    "wof:placetype":"venue"
},
  "geometry": {"coordinates":[3.345092,50.332146],"type":"Point"}
}