{
  "type": "Feature",
  "properties": {
    "iso:country":"FR",
    "sg:address":"14, Quai Nicolas Rolin, 21000 Dijon",
    "sg:city":"Dijon",
    "sg:orig_category":"Unclassifiable Establishments",
    "sg:phone":"+33 3 80 58 94 45",
    "sg:postcode":"21000",
    "sg:province":"Bourgogne",
    "wof:name":"Barbier Jean Luc Denis",
    "wof:placetype":"venue"
},
  "geometry": {"coordinates":[5.027397,47.31601],"type":"Point"}
}