{
  "type": "Feature",
  "properties": {
    "addr:full":"1, Rue William Dian, 27620 Gasny Haute Normandie",
    "addr:housenumber":"1",
    "addr:postcode":"27620",
    "addr:street":"Rue William Dian;Haute Normandie",
    "iso:country":"FR",
    "sg:address":"1, Rue William Dian, 27620 Gasny",
    "sg:orig_category":"Unclassifiable Establishments",
    "sg:phone":"+33 2 32 52 15 16",
    "sg:province":"Haute Normandie",
    "wof:name":"Toussaint Denis S.a.r.l.",
    "wof:placetype":"venue"
},
  "geometry": {"coordinates":[1.607753,49.089333],"type":"Point"}
}