{
  "type": "Feature",
  "properties": {
    "iso:country":"FR",
    "sg:address":"Moulin de la Brugerette 48140 Le Malzieu Ville",
    "sg:orig_category":"Non-Classified Establishments",
    "sg:phone":"+33 4 66 42 66 00",
    "sg:postcode":"48140",
    "sg:province":"Languedoc-Roussillon",
    "wof:name":"Boulet Jean-louis S.a.",
    "wof:placetype":"venue"
},
  "geometry": {"coordinates":[3.331721,44.855293],"type":"Point"}
}