{
  "type": "Feature",
  "properties": {
    "addr:full":"Les Cazes 84260 Sarrians Centre",
    "addr:housenumber":"sarrians",
    "addr:postcode":"84260",
    "iso:country":"FR",
    "sg:address":"Les Cazes 84260 Sarrians",
    "sg:classifiers":[
        {
            "category":"Farming",
            "subcategory":"Farm",
            "type":"Manufacturing & Wholesale Goods"
        }
    ],
    "sg:phone":"+33 4 90 65 41 35",
    "sg:province":"Centre",
    "sg:tags":[
        "horticulture",
        "agriculture",
        "livestock"
    ],
    "wof:name":"Se Pepinieres Martin",
    "wof:placetype":"venue"
},
  "geometry": {"coordinates":[4.970184,44.084293],"type":"Point"}
}