{
  "type": "Feature",
  "properties": {
    "iso:country":"FR",
    "sg:address":"18, Rue de la Plaine - Zone Industrielle, 60190 Arsy",
    "sg:orig_category":"Non-Classified Establishments",
    "sg:phone":"+33 3 44 37 36 36",
    "sg:province":"Picardie",
    "wof:name":"Techni Isol S.a.",
    "wof:placetype":"venue"
},
  "geometry": {"coordinates":[2.6372,49.425014],"type":"Point"}
}