{
  "type": "Feature",
  "properties": {
    "addr:full":"1 Avenue Des Cottages 63000 Clermont Ferrand Clermont-Ferrand Auvergne 63000",
    "addr:housenumber":"1",
    "addr:postcode":"63000;63000",
    "addr:street":"Avenue Des Cottages",
    "iso:country":"FR",
    "sg:address":"1 Avenue Des Cottages 63000 Clermont Ferrand",
    "sg:city":"Clermont-Ferrand",
    "sg:classifiers":[
        {
            "category":"Professional",
            "subcategory":"Printing & Photocopies",
            "type":"Services"
        }
    ],
    "sg:phone":"+33 4 73 34 33 01",
    "sg:postcode":"63000",
    "sg:province":"Auvergne",
    "sg:tags":[
        "publishing"
    ],
    "wof:name":"Com 6",
    "wof:placetype":"venue"
},
  "geometry": {"coordinates":[3.080805,45.764889],"type":"Point"}
}