{
  "type": "Feature",
  "properties": {
    "iso:country":"FR",
    "sg:address":"2, All\u00e9e des Eglantines, 31520 Ramonville Saint Agne",
    "sg:orig_category":"Non-Classified Establishments",
    "sg:phone":"+33 5 61 75 65 66",
    "sg:postcode":"31520",
    "sg:province":"Midi Pyr\u00e9n\u00e9es",
    "wof:name":"D\u00e9cora Stores S.a.r.l.",
    "wof:placetype":"venue"
},
  "geometry": {"coordinates":[1.483454,43.537209],"type":"Point"}
}