{
  "type": "Feature",
  "properties": {
    "addr:full":"48 St Julien 13012 Marseille Provence-Alpes-C\u00f4te d'Azur",
    "addr:housenumber":"48",
    "addr:postcode":"13012",
    "addr:street":"St Julien",
    "iso:country":"FR",
    "sg:address":"48",
    "sg:city":"St Julien 13012 Marseille",
    "sg:classifiers":[
        {
            "category":"Professional",
            "type":"Services"
        }
    ],
    "sg:phone":"+33 4 91 49 56 57",
    "sg:province":"Provence-Alpes-C\u00f4te d'Azur",
    "sg:tags":[
        "transport",
        "road"
    ],
    "wof:name":"Dema 82",
    "wof:placetype":"venue"
},
  "geometry": {"coordinates":[5.416606,43.305027],"type":"Point"}
}