{
  "type": "Feature",
  "properties": {
    "iso:country":"FR",
    "sg:address":"150 rue de Marquillies 59000 Lille",
    "sg:classifiers":[
        {
            "category":"Building & Trades",
            "subcategory":"Plumbing",
            "type":"Services"
        }
    ],
    "sg:phone":"+33 3 20 49 05 06",
    "sg:postcode":"59000",
    "sg:province":"Nord Pas-de-Calais",
    "sg:tags":[
        "flow-meters"
    ],
    "wof:name":"Ste Technique Appareil Mesure Industriel Sarl",
    "wof:placetype":"venue"
},
  "geometry": {"coordinates":[3.058574,50.614269],"type":"Point"}
}