{
  "type": "Feature",
  "properties": {
    "addr:full":"10, Rue Manurhin, 68120 Richwiller Richwiller Alsace 68120",
    "addr:housenumber":"10",
    "addr:postcode":"68120;68120",
    "addr:street":"Rue Manurhin",
    "iso:country":"FR",
    "sg:address":"10, Rue Manurhin, 68120 Richwiller",
    "sg:city":"Richwiller",
    "sg:orig_category":"Unclassifiable Establishments",
    "sg:phone":"+33 3 89 57 33 03",
    "sg:postcode":"68120",
    "sg:province":"Alsace",
    "wof:name":"Diamcoupe S.a.",
    "wof:placetype":"venue"
},
  "geometry": {"coordinates":[7.30344,47.787788],"type":"Point"}
}