{
  "type": "Feature",
  "properties": {
    "iso:country":"FR",
    "sg:address":"2 Rue Du Colonel Chambonnet 69500 Bron",
    "sg:classifiers":[
        {
            "category":"Manufacturing",
            "subcategory":"Tools & Machinery",
            "type":"Manufacturing & Wholesale Goods"
        }
    ],
    "sg:phone":"+33 4 72 14 18 80",
    "sg:postcode":"69500",
    "sg:province":"Rhone-Alpes",
    "sg:tags":[
        "equipment",
        "measurement",
        "-",
        "precision",
        "instrument"
    ],
    "wof:name":"Sauter Regulation",
    "wof:placetype":"venue"
},
  "geometry": {"coordinates":[4.924389,45.727745],"type":"Point"}
}