{
  "type": "Feature",
  "properties": {
    "addr:full":"Les Granges 03110 Escurolles Escurolles Auvergne 03110",
    "addr:postcode":"03110;escurolles;03110",
    "addr:street":"Granges",
    "iso:country":"FR",
    "sg:address":"Les Granges 03110 Escurolles",
    "sg:city":"Escurolles",
    "sg:classifiers":[
        {
            "category":"Home & Garden",
            "subcategory":"Furniture",
            "type":"Retail Goods"
        }
    ],
    "sg:phone":"+33 4 70 90 50 11",
    "sg:postcode":"03110",
    "sg:province":"Auvergne",
    "sg:tags":[
        "wood"
    ],
    "wof:name":"Atelier Des Granges",
    "wof:placetype":"venue"
},
  "geometry": {"coordinates":[3.27876,46.129978],"type":"Point"}
}