{
  "type": "Feature",
  "properties": {
    "iso:country":"FR",
    "sg:address":"21 Boulevard De L'Oise 95000 Cergy",
    "sg:classifiers":[
        {
            "category":"Travel",
            "subcategory":"Hotels & Motels",
            "type":"Entertainment"
        }
    ],
    "sg:phone":"+33 1 30 31 93 09",
    "sg:postcode":"95000",
    "sg:province":"Ile de France",
    "sg:tags":[
        "hotels",
        "business",
        "restaurant"
    ],
    "wof:name":"Amc Cergy Sa",
    "wof:placetype":"venue"
},
  "geometry": {"coordinates":[2.09101,49.035709],"type":"Point"}
}