{
  "type": "Feature",
  "properties": {
    "addr:full":"Zi D 06700 St Laurent Du Var Champagne",
    "addr:housenumber":"06700",
    "addr:street":"St Laurent Du Var",
    "iso:country":"FR",
    "sg:address":"Zi D 06700 St Laurent Du Var",
    "sg:classifiers":[
        {
            "category":"Building & Trades",
            "subcategory":"Construction",
            "type":"Services"
        }
    ],
    "sg:phone":"+33 4 93 14 13 13",
    "sg:province":"Champagne",
    "sg:tags":[
        "swimming-pool"
    ],
    "wof:name":"Ste Diffazur Sa",
    "wof:placetype":"venue"
},
  "geometry": {"coordinates":[7.190097,43.673519],"type":"Point"}
}