{
  "type": "Feature",
  "properties": {
    "iso:country":"FR",
    "sg:address":"Place Des Fontaines 13370 Mallemort",
    "sg:city":"Fontain",
    "sg:classifiers":[
        {
            "category":"Sports & Exercise",
            "subcategory":"Tennis Court",
            "type":"Entertainment"
        }
    ],
    "sg:phone":"+33 4 90 57 40 79",
    "sg:postcode":"25660",
    "sg:province":"Franche Comt\u00e9",
    "sg:tags":[
        "banking",
        "game",
        "finance",
        "institution",
        "insurance"
    ],
    "wof:name":"Pont Royal Golf Sarl",
    "wof:placetype":"venue"
},
  "geometry": {"coordinates":[5.181057,43.727749],"type":"Point"}
}