{
  "type": "Feature",
  "properties": {
    "iso:country":"FR",
    "sg:address":"235 Route Des Creuses 74600 Seynod",
    "sg:classifiers":[
        {
            "category":"Utilities",
            "subcategory":"Electric",
            "type":"Services"
        }
    ],
    "sg:phone":"+33 4 50 69 09 14",
    "sg:postcode":"74600",
    "sg:province":"Rhone-Alpes",
    "sg:tags":[
        "electricity",
        "electronic",
        "electrical",
        "equipment"
    ],
    "wof:name":"Alme Sa",
    "wof:placetype":"venue"
},
  "geometry": {"coordinates":[6.081776,45.889404],"type":"Point"}
}