{
  "type": "Feature",
  "properties": {
    "addr:full":"11, Rue Mozard, 38800 Le Pont de Claix Rhone-Alpes 38800",
    "addr:housenumber":"11",
    "addr:postcode":"38800;38800",
    "addr:street":"Rue Mozard;Pont De;Rhone-Alpes",
    "iso:country":"FR",
    "sg:address":"11, Rue Mozard, 38800 Le Pont de Claix",
    "sg:orig_category":"Non-Classified Establishments",
    "sg:phone":"+33 4 76 98 45 27",
    "sg:postcode":"38800",
    "sg:province":"Rhone-Alpes",
    "wof:name":"Elitt S.a.",
    "wof:placetype":"venue"
},
  "geometry": {"coordinates":[5.695372,45.129837],"type":"Point"}
}