{
  "type": "Feature",
  "properties": {
    "addr:full":"B.P. 24, 09120 Varilhes C\u00e9dex^^Parc Technologique Delta Sud, 09120 Varilhes Midi Pyr\u00e9n\u00e9es 09120",
    "addr:postcode":"09120;09120;09120",
    "addr:street":"B.P. 24",
    "iso:country":"FR",
    "sg:address":"B.P. 24, 09120 Varilhes C\u00e9dex^^Parc Technologique Delta Sud, 09120 Varilhes",
    "sg:orig_category":"Non-Classified Establishments",
    "sg:phone":"+33 5 61 67 92 30",
    "sg:postcode":"09120",
    "sg:province":"Midi Pyr\u00e9n\u00e9es",
    "wof:name":"Ari\u00e8ge Expansion",
    "wof:placetype":"venue"
},
  "geometry": {"coordinates":[1.62911,43.04604],"type":"Point"}
}