{
  "type": "Feature",
  "properties": {
    "iso:country":"FR",
    "sg:address":"4 Rue Bobby Sands 44800 St Herblain",
    "sg:classifiers":[
        {
            "category":"Banks & Credit Unions",
            "subcategory":"Investment Brokerage",
            "type":"Services"
        }
    ],
    "sg:phone":"+33 2 40 16 92 40",
    "sg:province":"Pays de Loire",
    "sg:tags":[
        "-",
        "transport",
        "related"
    ],
    "wof:name":"Giraud Transit Sas",
    "wof:placetype":"venue"
},
  "geometry": {"coordinates":[-1.651372,47.233326],"type":"Point"}
}