{
  "type": "Feature",
  "properties": {
    "iso:country":"FR",
    "sg:address":"B.P. 143",
    "sg:city":"Ivry sur Seine C\u00e9dex",
    "sg:orig_category":"Non-Classified Establishments",
    "sg:phone":"+33 1 45 15 11 50",
    "sg:postcode":"94208",
    "sg:province":"Haute Normandie",
    "wof:name":"L.i.r. S.a. - Librairies Imprimeries R\u00e9unies",
    "wof:placetype":"venue"
},
  "geometry": {"coordinates":[2.384885,48.811668],"type":"Point"}
}