{
  "type": "Feature",
  "properties": {
    "iso:country":"FR",
    "sg:address":"130, Rue du Baptistou - ZA Nord, 34980 Saint G\u00e9ly du Fesc",
    "sg:orig_category":"Non-Classified Establishments",
    "sg:phone":"+33 4 67 84 48 00",
    "sg:postcode":"34980",
    "sg:province":"Languedoc-Roussillon",
    "wof:name":"Dataset S.a.",
    "wof:placetype":"venue"
},
  "geometry": {"coordinates":[3.806955,43.69313],"type":"Point"}
}