{
  "type": "Feature",
  "properties": {
    "addr:full":"8 Rue Gustave Eiffel 87410 Le Palais Sur Vienne Limousin",
    "addr:housenumber":"8",
    "addr:postcode":"87410",
    "addr:street":"Rue Gustave Eiffel",
    "iso:country":"FR",
    "sg:address":"8 Rue Gustave Eiffel 87410 Le Palais Sur Vienne",
    "sg:classifiers":[
        {
            "category":"Manufacturing",
            "subcategory":"Printing",
            "type":"Manufacturing & Wholesale Goods"
        }
    ],
    "sg:phone":"+33 5 55 35 10 25",
    "sg:province":"Limousin",
    "sg:tags":[
        "publishing"
    ],
    "wof:name":"Flexogravure Sa",
    "wof:placetype":"venue"
},
  "geometry": {"coordinates":[1.306211,45.873672],"type":"Point"}
}