{
  "type": "Feature",
  "properties": {
    "addr:full":"33, Rue Daru, 75008 Paris Ile de France",
    "addr:housenumber":"33",
    "addr:postcode":"75008",
    "addr:street":"Rue Daru",
    "iso:country":"FR",
    "sg:address":"33, Rue Daru, 75008 Paris",
    "sg:orig_category":"Unclassifiable Establishments",
    "sg:phone":"+33 1 47 66 77 88",
    "sg:province":"Ile de France",
    "wof:name":"A.c.a. S.a. - Auditeurs Conseils Associ\u00e9s",
    "wof:placetype":"venue"
},
  "geometry": {"coordinates":[2.303128,48.878819],"type":"Point"}
}