{
  "type": "Feature",
  "properties": {
    "addr:full":"153 Av Des 16emes Jeux Olympiqu 73200 Albertville Rhone-Alpes",
    "addr:postcode":"73200",
    "addr:street":"153 Av Des 16Emes Jeux Olympiqu",
    "iso:country":"FR",
    "sg:address":"153 Av Des 16emes Jeux Olympiqu 73200 Albertville",
    "sg:classifiers":[
        {
            "category":"Manufacturing",
            "subcategory":"Rubber & Plastics",
            "type":"Manufacturing & Wholesale Goods"
        }
    ],
    "sg:phone":"+33 4 79 31 11 00",
    "sg:province":"Rhone-Alpes",
    "wof:name":"Cebal Sa",
    "wof:placetype":"venue"
},
  "geometry": {"coordinates":[6.359874,45.63168],"type":"Point"}
}