{
  "type": "Feature",
  "properties": {
    "iso:country":"FR",
    "sg:address":"10",
    "sg:city":"Florian 93220 Gagny",
    "sg:orig_category":"Chemicals and Pharmaceuticals Cosmetics Miscellaneous Products",
    "sg:phone":"+33 1 41 53 84 12",
    "sg:postcode":"93220",
    "sg:province":"Ile de France",
    "wof:name":"Lerevenu (ste M.g.)",
    "wof:placetype":"venue"
},
  "geometry": {"coordinates":[2.538805,48.883659],"type":"Point"}
}