{
  "type": "Feature",
  "properties": {
    "addr:full":"ZI Plan du Cumin Les Marches Rhone-Alpes 73800",
    "addr:postcode":"73800",
    "addr:street":"Zi Plan Du Cumin Les;Rhone-Alpes",
    "iso:country":"FR",
    "sg:address":"ZI Plan du Cumin",
    "sg:city":"Les Marches",
    "sg:orig_category":"Non-Classified Establishments",
    "sg:phone":"+33 4 79 28 02 88",
    "sg:postcode":"73800",
    "sg:province":"Rhone-Alpes",
    "wof:name":"M\u00e9tallerie G\u00e9n\u00e9rales Des Marches S.a.r.l.",
    "wof:placetype":"venue"
},
  "geometry": {"coordinates":[6.00053,45.498459],"type":"Point"}
}