{
  "type": "Feature",
  "properties": {
    "addr:full":"B.P. 101, 01303 Belley C\u00e9dex^^ZA de la Pelissi\u00e8re, 01300 Belley Rhone-Alpes 01300",
    "addr:housenumber":"b.p. 101",
    "addr:postcode":"01303;01300;01300",
    "iso:country":"FR",
    "sg:address":"B.P. 101, 01303 Belley C\u00e9dex^^ZA de la Pelissi\u00e8re, 01300 Belley",
    "sg:orig_category":"Non-Classified Establishments",
    "sg:phone":"+33 4 79 81 14 26",
    "sg:postcode":"01300",
    "sg:province":"Rhone-Alpes",
    "wof:name":"U.s.m.o. S.a.",
    "wof:placetype":"venue"
},
  "geometry": {"coordinates":[5.67735,45.734741],"type":"Point"}
}