{
  "type": "Feature",
  "properties": {
    "addr:full":"25 Avenue Gascogne 82500 Beaumont De Lomagne Midi Pyr\u00e9n\u00e9es 82500",
    "addr:housenumber":"25",
    "addr:postcode":"82500;82500",
    "addr:street":"Avenue Gascogne",
    "iso:country":"FR",
    "sg:address":"25 Avenue Gascogne 82500 Beaumont De Lomagne",
    "sg:classifiers":[
        {
            "category":"Farming",
            "subcategory":"Livestock Farm",
            "type":"Manufacturing & Wholesale Goods"
        }
    ],
    "sg:phone":"+33 5 63 02 31 20",
    "sg:postcode":"82500",
    "sg:province":"Midi Pyr\u00e9n\u00e9es",
    "sg:tags":[
        "grain",
        "agriculture",
        "cereal"
    ],
    "wof:name":"Duran Cereales Sa",
    "wof:placetype":"venue"
},
  "geometry": {"coordinates":[1.038505,43.849113],"type":"Point"}
}