{
  "type": "Feature",
  "properties": {
    "addr:full":"RueTorpilleur Siricco Thiers Auvergne 63300",
    "addr:postcode":"63300",
    "iso:country":"FR",
    "sg:address":"RueTorpilleur Siricco",
    "sg:city":"Thiers",
    "sg:orig_category":"Non-Classified Establishments",
    "sg:phone":"+33 4 73 80 63 30",
    "sg:postcode":"63300",
    "sg:province":"Auvergne",
    "wof:name":"Rolland Jean-pierre",
    "wof:placetype":"venue"
},
  "geometry": {"coordinates":[3.510565,45.83902],"type":"Point"}
}