{
  "type": "Feature",
  "properties": {
    "addr:full":"Bd de l'Industrie - ZI Ecouflant Pays de Loire 49000",
    "addr:postcode":"49000",
    "addr:street":"Bd De L'Industrie Zi Ecouflant Pays",
    "iso:country":"FR",
    "sg:address":"Bd de l'Industrie - ZI",
    "sg:city":"Ecouflant",
    "sg:orig_category":"Unclassifiable Establishments",
    "sg:phone":"+33 2 41 43 91 20",
    "sg:postcode":"49000",
    "sg:province":"Pays de Loire",
    "wof:name":"Transports Catroux S.a.",
    "wof:placetype":"venue"
},
  "geometry": {"coordinates":[-0.507665,47.503178],"type":"Point"}
}