{
  "type": "Feature",
  "properties": {
    "iso:country":"FR",
    "sg:address":"3, Rue Paul Painlev\u00e9, 89400 Migennes",
    "sg:city":"Migennes",
    "sg:orig_category":"Unclassifiable Establishments",
    "sg:phone":"+33 3 86 80 21 23",
    "sg:postcode":"89400",
    "sg:province":"Bourgogne",
    "wof:name":"Profil Industrie S.a.",
    "wof:placetype":"venue"
},
  "geometry": {"coordinates":[3.54061,47.970745],"type":"Point"}
}