{
  "type": "Feature",
  "properties": {
    "addr:full":"All\u00e9e des Cabedans Cavaillon Aquitaine 84300",
    "addr:postcode":"84300",
    "addr:street":"Alle\u0301E Des Cabedans",
    "iso:country":"FR",
    "sg:address":"All\u00e9e des Cabedans",
    "sg:city":"Cavaillon",
    "sg:orig_category":"Non-Classified Establishments",
    "sg:phone":"+33 4 90 78 76 76",
    "sg:postcode":"84300",
    "sg:province":"Aquitaine",
    "wof:name":"Aldi",
    "wof:placetype":"venue"
},
  "geometry": {"coordinates":[5.062327,43.828789],"type":"Point"}
}