{
  "type": "Feature",
  "properties": {
    "addr:full":"11, Rue Emile Zola, 38000 Grenoble Rhone-Alpes",
    "addr:housenumber":"11",
    "addr:postcode":"38000",
    "addr:street":"Rue Emile Zola",
    "iso:country":"FR",
    "sg:address":"11, Rue Emile Zola, 38000 Grenoble",
    "sg:orig_category":"Unclassifiable Establishments",
    "sg:phone":"+33 4 76 47 22 03",
    "sg:province":"Rhone-Alpes",
    "wof:name":"G.e.n.e.r.a. S.a.r.l.",
    "wof:placetype":"venue"
},
  "geometry": {"coordinates":[5.730645,45.173855],"type":"Point"}
}