{
  "type": "Feature",
  "properties": {
    "addr:full":"Moulin de Canteret 32270 BLANQUEFORT Midi Pyr\u00e9n\u00e9es 32270",
    "addr:postcode":"32270;32270",
    "addr:street":"Moulin",
    "iso:country":"FR",
    "sg:address":"Moulin de Canteret 32270 BLANQUEFORT",
    "sg:classifiers":[
        {
            "category":"Shopping",
            "subcategory":"Shoes",
            "type":"Retail Goods"
        }
    ],
    "sg:phone":"+33 5 56 95 57 00",
    "sg:postcode":"32270",
    "sg:province":"Midi Pyr\u00e9n\u00e9es",
    "sg:tags":[
        "children's"
    ],
    "wof:name":"Mod'8 Sa",
    "wof:placetype":"venue"
},
  "geometry": {"coordinates":[0.770215,43.61504],"type":"Point"}
}