{
  "type": "Feature",
  "properties": {
    "addr:full":"25 rue Mably Bordeaux 33000",
    "addr:housenumber":"25",
    "addr:postcode":"33000",
    "addr:street":"Rue Mably Bordeaux",
    "iso:country":"FR",
    "sg:address":"25 rue Mably",
    "sg:city":"Bordeaux",
    "sg:classifiers":[
        {
            "category":"Professional",
            "subcategory":"Computer Services",
            "type":"Services"
        }
    ],
    "sg:postcode":"33000",
    "sg:tags":[
        "libcast",
        "podcast",
        "podcasting",
        "rss",
        "feed",
        "rss-feed",
        "broadcast"
    ],
    "sg:website":"http://www.libcast.com",
    "wof:name":"LIBCAST",
    "wof:placetype":"venue"
},
  "geometry": {"coordinates":[-0.577386,44.843843],"type":"Point"}
}