{
  "type": "Feature",
  "properties": {
    "addr:full":"52, Rte de Bretagne, 14760 Bretteville sur Odon Bretteville-sur-Odon Basse Normandie 14760",
    "addr:housenumber":"52",
    "addr:postcode":"14760;14760",
    "addr:street":"Rte De Bretagne",
    "iso:country":"FR",
    "sg:address":"52, Rte de Bretagne, 14760 Bretteville sur Odon",
    "sg:city":"Bretteville-sur-Odon",
    "sg:orig_category":"Non-Classified Establishments",
    "sg:phone":"+33 2 31 75 04 30",
    "sg:postcode":"14760",
    "sg:province":"Basse Normandie",
    "wof:name":"Fotilus S.a.r.l.",
    "wof:placetype":"venue"
},
  "geometry": {"coordinates":[-0.408633,49.168324],"type":"Point"}
}