{
  "type": "Feature",
  "properties": {
    "addr:full":"Ch\u00e2teau de Ligr\u00e9 Ligr\u00e9 Centre 37500",
    "addr:postcode":"37500",
    "iso:country":"FR",
    "sg:address":"Ch\u00e2teau de Ligr\u00e9",
    "sg:city":"Ligr\u00e9",
    "sg:orig_category":"Non-Classified Establishments",
    "sg:phone":"+33 2 47 93 16 70",
    "sg:postcode":"37500",
    "sg:province":"Centre",
    "wof:name":"Ferrand Gatien",
    "wof:placetype":"venue"
},
  "geometry": {"coordinates":[0.19145,47.077888],"type":"Point"}
}