{
  "type": "Feature",
  "properties": {
    "addr:full":"40 R Panhard Et Levassor Des Cettons 78570 Chanteloup Les Vignes Ile de France",
    "addr:housenumber":"40",
    "addr:postcode":"78570 chanteloup",
    "addr:street":"R Panhard Et Levassor Des Cettons",
    "iso:country":"FR",
    "sg:address":"40 R Panhard Et Levassor",
    "sg:city":"Des Cettons 78570 Chanteloup Les Vignes",
    "sg:classifiers":[
        {
            "category":"Autos & Motor Vehicles",
            "subcategory":"Automobile Sales",
            "type":"Retail Goods"
        }
    ],
    "sg:phone":"+33 1 39 27 29 91",
    "sg:province":"Ile de France",
    "sg:tags":[
        "equipment",
        "transport"
    ],
    "wof:name":"Teckart Industries",
    "wof:placetype":"venue"
},
  "geometry": {"coordinates":[2.03067,48.978271],"type":"Point"}
}