{
  "type": "Feature",
  "properties": {
    "addr:full":"5, Rue Terrien Cocherel, 49000 Angers Pays de Loire",
    "addr:housenumber":"5",
    "addr:postcode":"49000",
    "addr:street":"Rue Terrien",
    "iso:country":"FR",
    "sg:address":"5, Rue Terrien Cocherel, 49000 Angers",
    "sg:orig_category":"Unclassifiable Establishments",
    "sg:phone":"+33 2 41 43 78 12",
    "sg:province":"Pays de Loire",
    "wof:name":"Thermic Anjou S.a.",
    "wof:placetype":"venue"
},
  "geometry": {"coordinates":[-0.538014,47.475033],"type":"Point"}
}