{
  "type": "Feature",
  "properties": {
    "iso:country":"FR",
    "sg:address":"23, Rue Nollet, 75017 Paris",
    "sg:orig_category":"Non-Classified Establishments",
    "sg:phone":"+33 1 46 27 18 77",
    "sg:postcode":"75017",
    "sg:province":"Ile de France",
    "wof:name":"Anabole S.a.r.l.",
    "wof:placetype":"venue"
},
  "geometry": {"coordinates":[2.323019,48.88575],"type":"Point"}
}