{
  "type": "Feature",
  "properties": {
    "addr:full":"77615 Marne la Vall\u00e9e C\u00e9dex 3^^33, All\u00e9e du Clos des Charmes - Parc d'Activit\u00e9s les Portes de la For Bourgogne",
    "addr:housenumber":"3 ^ ^ 33",
    "addr:postcode":"77615",
    "addr:street":"Ce\u0301Dex;Alle\u0301E Du Clos Des Charmes Parc D'Activite \u0301S Les",
    "iso:country":"FR",
    "sg:address":"77615 Marne la Vall\u00e9e C\u00e9dex 3^^33, All\u00e9e du Clos des Charmes - Parc d'Activit\u00e9s les Portes de la For",
    "sg:orig_category":"Non-Classified Establishments",
    "sg:phone":"+33 1 64 62 50 50",
    "sg:province":"Bourgogne",
    "wof:name":"77 Express Nord S.a.r.l.",
    "wof:placetype":"venue"
},
  "geometry": {"coordinates":[2.715454,48.864887],"type":"Point"}
}