{
  "type": "Feature",
  "properties": {
    "addr:full":"Ze Les Fougerouses 16430 Balzac Poitou-Charentes 16430",
    "addr:postcode":"16430;16430",
    "addr:street":"Ze;Balzac",
    "iso:country":"FR",
    "sg:address":"Ze Les Fougerouses 16430 Balzac",
    "sg:classifiers":[
        {
            "category":"Wholesale",
            "subcategory":"Medical Equipment & Supplies",
            "type":"Manufacturing & Wholesale Goods"
        }
    ],
    "sg:phone":"+33 5 45 92 77 68",
    "sg:postcode":"16430",
    "sg:province":"Poitou-Charentes",
    "sg:tags":[
        "instrument",
        "health",
        "-",
        "precision"
    ],
    "wof:name":"Bodinaud Christian Sarl",
    "wof:placetype":"venue"
},
  "geometry": {"coordinates":[0.211168,45.691833],"type":"Point"}
}