{
  "type": "Feature",
  "properties": {
    "iso:country":"FR",
    "sg:address":"46/48, Rue Gay Lussac - ZI, 94430 Chennevi\u00e8res sur Marne",
    "sg:orig_category":"Non-Classified Establishments",
    "sg:phone":"+33 1 45 76 48 82",
    "sg:province":"Ile de France",
    "wof:name":"Euro Press S.a.r.l.",
    "wof:placetype":"venue"
},
  "geometry": {"coordinates":[2.53196,48.796413],"type":"Point"}
}