{
  "type": "Feature",
  "properties": {
    "addr:full":"28, Rue Blaise Pascal, 79000 Niort Poitou-Charentes",
    "addr:housenumber":"28",
    "addr:postcode":"79000",
    "addr:street":"Rue Blaise Pascal",
    "iso:country":"FR",
    "sg:address":"28, Rue Blaise Pascal, 79000 Niort",
    "sg:orig_category":"Unclassifiable Establishments",
    "sg:phone":"+33 5 49 06 91 11",
    "sg:province":"Poitou-Charentes",
    "wof:name":"Ates S.a.",
    "wof:placetype":"venue"
},
  "geometry": {"coordinates":[-0.493184,46.314045],"type":"Point"}
}