{
  "type": "Feature",
  "properties": {
    "iso:country":"FR",
    "sg:address":"Place de l'H\u00f4tel de Ville",
    "sg:city":"Compi\u00e8gne",
    "sg:orig_category":"Unclassifiable Establishments",
    "sg:phone":"+33 3 44 40 72 00",
    "sg:postcode":"60200",
    "sg:province":"Picardie",
    "wof:name":"Mairie De Compi\u00e8gne",
    "wof:placetype":"venue"
},
  "geometry": {"coordinates":[2.85486,49.401451],"type":"Point"}
}