{
  "type": "Feature",
  "properties": {
    "addr:full":"Zac De La Gravette 31150 Gratentour Midi Pyr\u00e9n\u00e9es",
    "addr:postcode":"31150",
    "addr:street":"Zac De La",
    "iso:country":"FR",
    "sg:address":"Zac De La Gravette 31150 Gratentour",
    "sg:classifiers":[
        {
            "category":"Manufacturing",
            "subcategory":"Paper Products",
            "type":"Manufacturing & Wholesale Goods"
        }
    ],
    "sg:phone":"+33 5 61 82 56 60",
    "sg:province":"Midi Pyr\u00e9n\u00e9es",
    "sg:tags":[
        "packaging",
        "material",
        "-",
        "cardboard"
    ],
    "wof:name":"Cevi Sarl",
    "wof:placetype":"venue"
},
  "geometry": {"coordinates":[1.4317,43.72184],"type":"Point"}
}