{
  "type": "Feature",
  "properties": {
    "iso:country":"FR",
    "sg:address":"92, Rte de Port la Pierre, 17100 Saint Vaize",
    "sg:orig_category":"Non-Classified Establishments",
    "sg:phone":"+33 5 46 97 18 95",
    "sg:province":"Poitou-Charentes",
    "wof:name":"First Time",
    "wof:placetype":"venue"
},
  "geometry": {"coordinates":[-0.632268,45.811916],"type":"Point"}
}