{
  "type": "Feature",
  "properties": {
    "addr:full":"9 rue de la R\u00e9publique; Avignon; 84000 Picardie",
    "addr:housenumber":"9",
    "addr:postcode":"84000",
    "addr:street":"Rue De La Re\u0301Publique",
    "iso:country":"FR",
    "sg:address":"9 rue de la R\u00e9publique; Avignon; 84000",
    "sg:classifiers":[
        {
            "category":"Banks & Credit Unions",
            "subcategory":"Bank",
            "type":"Services"
        }
    ],
    "sg:phone":"+33 3390829922",
    "sg:province":"Picardie",
    "wof:name":"Soci\u00e9t\u00e9 G\u00e9n\u00e9rale",
    "wof:placetype":"venue"
},
  "geometry": {"coordinates":[4.806042,43.948189],"type":"Point"}
}