{
  "type": "Feature",
  "properties": {
    "iso:country":"FR",
    "sg:address":"8, Rue Bailly, 76400 F\u00e9camp",
    "sg:orig_category":"Unclassifiable Establishments",
    "sg:phone":"+33 2 35 10 38 38",
    "sg:province":"Haute Normandie",
    "wof:name":"Chambre De Commerce Et D'industrie De F\u00e9camp",
    "wof:placetype":"venue"
},
  "geometry": {"coordinates":[0.377538,49.756676],"type":"Point"}
}