{
  "type": "Feature",
  "properties": {
    "addr:full":"3 Rue Anatole De Monzie 44200 Nantes Pays de Loire 44200",
    "addr:housenumber":"3",
    "addr:postcode":"44200;44200",
    "addr:street":"Rue Anatole De Monzie",
    "iso:country":"FR",
    "sg:address":"3 Rue Anatole De Monzie 44200 Nantes",
    "sg:classifiers":[
        {
            "category":"Banks & Credit Unions",
            "subcategory":"Financial Services",
            "type":"Services"
        }
    ],
    "sg:phone":"+33 2 40 47 18 66",
    "sg:postcode":"44200",
    "sg:province":"Pays de Loire",
    "sg:tags":[
        "banking",
        "finance",
        "insurance"
    ],
    "wof:name":"Cabinet Dexpertises Mace Jumel",
    "wof:placetype":"venue"
},
  "geometry": {"coordinates":[-1.542902,47.20274],"type":"Point"}
}