{
  "type": "Feature",
  "properties": {
    "iso:country":"FR",
    "sg:address":"14 quai des Docks 06300 Nice",
    "sg:orig_category":"Bathing Costumes, Bathing Shorts, Bikinis",
    "sg:phone":"+33 4 93 55 61 00",
    "wof:name":"Kaya Line S.a.r.l.",
    "wof:placetype":"venue"
},
  "geometry": {"coordinates":[7.286139,43.696232],"type":"Point"}
}