{
  "type": "Feature",
  "properties": {
    "addr:full":"11, Rue des Porti\u00e8res, 49124 Saint Barth\u00e9l\u00e9my d'Anjou Pays de Loire",
    "addr:housenumber":"11",
    "addr:postcode":"49124;barthe\u0301le\u0301my;pays",
    "addr:street":"Rue Des Portie\u0300Res;D'Anjou",
    "iso:country":"FR",
    "sg:address":"11, Rue des Porti\u00e8res, 49124 Saint Barth\u00e9l\u00e9my d'Anjou",
    "sg:orig_category":"Non-Classified Establishments",
    "sg:phone":"+33 2 41 43 64 64",
    "sg:province":"Pays de Loire",
    "wof:name":"T.f.n.",
    "wof:placetype":"venue"
},
  "geometry": {"coordinates":[-1.334822,47.273693],"type":"Point"}
}