{
  "type": "Feature",
  "properties": {
    "addr:full":"B.P. 100, 18009 Bourges C\u00e9dex^^6, Rte de Guerry, 18000 Bourges Bourges Centre 18000",
    "addr:housenumber":"b.p. 100",
    "addr:postcode":"18009;18000;18000",
    "addr:street":"Rte De Guerry",
    "iso:country":"FR",
    "sg:address":"B.P. 100, 18009 Bourges C\u00e9dex^^6, Rte de Guerry, 18000 Bourges",
    "sg:city":"Bourges",
    "sg:orig_category":"Non-Classified Establishments",
    "sg:phone":"+33 2 48 21 04 78",
    "sg:postcode":"18000",
    "sg:province":"Centre",
    "wof:name":"P.r. 3 S.a.r.l",
    "wof:placetype":"venue"
},
  "geometry": {"coordinates":[2.39293,47.085854],"type":"Point"}
}