{
  "type": "Feature",
  "properties": {
    "iso:country":"FR",
    "sg:address":"30 Chemin Lapujade 31200 Toulouse",
    "sg:classifiers":[
        {
            "category":"Shopping",
            "type":"Retail Goods"
        }
    ],
    "sg:phone":"+33 5 61 48 68 38",
    "sg:postcode":"31200",
    "sg:province":"Midi Pyr\u00e9n\u00e9es",
    "sg:tags":[
        "metallurgy",
        "finished",
        "-",
        "metalworking",
        "metallic"
    ],
    "wof:name":"Societe D'exploitation De L'atelier Paul Larrieu",
    "wof:placetype":"venue"
},
  "geometry": {"coordinates":[1.452737,43.619156],"type":"Point"}
}