{
  "type": "Feature",
  "properties": {
    "addr:full":"3 avenue Condorcet 69626 VILLEURBANNE CEDEX Rhone-Alpes",
    "addr:housenumber":"3",
    "addr:postcode":"69626",
    "addr:street":"Avenue Condorcet",
    "iso:country":"FR",
    "sg:address":"3 avenue Condorcet 69626 VILLEURBANNE CEDEX",
    "sg:classifiers":[
        {
            "category":"Manufacturing",
            "subcategory":"Textiles",
            "type":"Manufacturing & Wholesale Goods"
        }
    ],
    "sg:phone":"+33 4 72 44 44 44",
    "sg:province":"Rhone-Alpes",
    "sg:tags":[
        "use",
        "industrial",
        "yarn"
    ],
    "wof:name":"Acordis France Sas",
    "wof:placetype":"venue"
},
  "geometry": {"coordinates":[4.867084,45.778385],"type":"Point"}
}