{
  "type": "Feature",
  "properties": {
    "iso:country":"FR",
    "sg:address":"B.P. 20053, 60402 Noyon C\u00e9dex^^46, Rue de Paris, 60400 Noyon",
    "sg:orig_category":"Non-Classified Establishments",
    "sg:phone":"+33 3 44 44 26 96",
    "sg:province":"Picardie",
    "wof:name":"S.e.r. S.a. - Soci\u00e9t\u00e9 Electricit\u00e9 R\u00e9gionale Lassigny Et Limitrophes",
    "wof:placetype":"venue"
},
  "geometry": {"coordinates":[3.097817,49.48531],"type":"Point"}
}