{
  "type": "Feature",
  "properties": {
    "addr:full":"81 BD BATAILLE DE STALINGRAD 69100 Villeurbanne Rhone-Alpes 69100",
    "addr:housenumber":"81",
    "addr:postcode":"69100;69100",
    "addr:street":"Bd Bataille De Stalingrad",
    "iso:country":"FR",
    "sg:address":"81 BD BATAILLE DE STALINGRAD 69100 Villeurbanne",
    "sg:classifiers":[
        {
            "category":"Farming",
            "subcategory":"Crops",
            "type":"Manufacturing & Wholesale Goods"
        }
    ],
    "sg:phone":"+33 4 72 43 39 03",
    "sg:postcode":"69100",
    "sg:province":"Rhone-Alpes",
    "sg:tags":[
        "refrigerator",
        "wine"
    ],
    "wof:name":"Fouco-eurocave Sa",
    "wof:placetype":"venue"
},
  "geometry": {"coordinates":[4.85951,45.778709],"type":"Point"}
}