{
  "type": "Feature",
  "properties": {
    "iso:country":"FR",
    "sg:address":"B.P. 225, 35514 Cesson S\u00e9vign\u00e9 C\u00e9dex^^Rue de Bignon - ZI Sud Est, 35510 Cesson S\u00e9vign\u00e9",
    "sg:city":"Cesson-S\u00e9vign\u00e9",
    "sg:orig_category":"Non-Classified Establishments",
    "sg:phone":"+33 2 99 32 08 98",
    "sg:postcode":"35510",
    "sg:province":"Bretagne",
    "wof:name":"Interbovi Bretagne",
    "wof:placetype":"venue"
},
  "geometry": {"coordinates":[-1.604404,48.117016],"type":"Point"}
}