{
  "type": "Feature",
  "properties": {
    "addr:full":"1, Rue du Clos Lointier - Saint Gervais , 95420 Magny en Vexin Ile de France",
    "addr:housenumber":"1",
    "addr:postcode":"95420",
    "addr:street":"Rue Du Clos Lointier;Gervais",
    "iso:country":"FR",
    "sg:address":"1, Rue du Clos Lointier - Saint Gervais , 95420 Magny en Vexin",
    "sg:orig_category":"Unclassifiable Establishments",
    "sg:phone":"+33 1 34 67 02 85",
    "sg:province":"Ile de France",
    "wof:name":"Pouget Parcs Et Jardins S.a.r.l.",
    "wof:placetype":"venue"
},
  "geometry": {"coordinates":[1.786815,49.155235],"type":"Point"}
}