{
  "type": "Feature",
  "properties": {
    "addr:full":"62, Av. de la Grande Arm\u00e9e, 75017 Paris Ile de France",
    "addr:postcode":"75017;france",
    "addr:street":"62 Av. De La Grande Arme\u0301E",
    "iso:country":"FR",
    "sg:address":"62, Av. de la Grande Arm\u00e9e, 75017 Paris",
    "sg:orig_category":"Unclassifiable Establishments",
    "sg:phone":"+33 1 45 74 12 91",
    "sg:province":"Ile de France",
    "wof:name":"C.e.c.i. S.a.r.l. - Comptoir Europ\u00e9en Commecial Et Industriel",
    "wof:placetype":"venue"
},
  "geometry": {"coordinates":[2.286145,48.876968],"type":"Point"}
}