{
  "type": "Feature",
  "properties": {
    "addr:full":"Rte Blanche Scionzier Rhone-Alpes 74950",
    "addr:postcode":"74950",
    "addr:street":"Rte Blanche;Rhone-Alpes",
    "iso:country":"FR",
    "sg:address":"Rte Blanche",
    "sg:city":"Scionzier",
    "sg:orig_category":"Non-Classified Establishments",
    "sg:phone":"+33 4 50 96 46 00",
    "sg:postcode":"74950",
    "sg:province":"Rhone-Alpes",
    "wof:name":"Reynolds European S.a.s.",
    "wof:placetype":"venue"
},
  "geometry": {"coordinates":[6.56523,46.060101],"type":"Point"}
}