{
  "type": "Feature",
  "properties": {
    "iso:country":"FR",
    "sg:address":"126 Quai De La Souys 33100 Bordeaux",
    "sg:city":"Bordeaux",
    "sg:classifiers":[
        {
            "category":"Manufacturing",
            "subcategory":"Chemicals & Compounds",
            "type":"Manufacturing & Wholesale Goods"
        }
    ],
    "sg:phone":"+33 5 56 86 53 04",
    "sg:postcode":"33100",
    "sg:province":"Aquitaine",
    "sg:tags":[
        "pharmaceutical",
        "chemistry"
    ],
    "wof:name":"Laffort Et Cie (produits Oenologiques) Sarl",
    "wof:placetype":"venue"
},
  "geometry": {"coordinates":[-0.539273,44.827904],"type":"Point"}
}