{
  "type": "Feature",
  "properties": {
    "addr:full":"109 Rue De Saint Omer 62310 FRUGES Nord Pas-de-Calais 62310",
    "addr:housenumber":"109",
    "addr:postcode":"62310;62310",
    "addr:street":"Rue De Saint Omer",
    "iso:country":"FR",
    "sg:address":"109 Rue De Saint Omer 62310 FRUGES",
    "sg:classifiers":[
        {
            "category":"Food & Beverages",
            "subcategory":"Meat & Fish",
            "type":"Retail Goods"
        }
    ],
    "sg:phone":"+33 3 21 47 55 55",
    "sg:postcode":"62310",
    "sg:province":"Nord Pas-de-Calais",
    "wof:name":"Etablissements J. M. Macquet Sa",
    "wof:placetype":"venue"
},
  "geometry": {"coordinates":[2.13324,50.520351],"type":"Point"}
}