{
  "type": "Feature",
  "properties": {
    "addr:full":"13 Av Lamartine 13170 Les Pennes Mirabeau Corse",
    "addr:postcode":"13170",
    "addr:street":"13 Av Lamartine",
    "iso:country":"FR",
    "sg:address":"13 Av Lamartine 13170 Les Pennes Mirabeau",
    "sg:classifiers":[
        {
            "category":"Sports & Exercise",
            "subcategory":"Sports Center",
            "type":"Entertainment"
        }
    ],
    "sg:phone":"+33 4 42 02 12 02",
    "sg:province":"Corse",
    "sg:tags":[
        "machine",
        "engineering",
        "-",
        "mechanical"
    ],
    "wof:name":"Equiptec Sa",
    "wof:placetype":"venue"
},
  "geometry": {"coordinates":[5.316214,43.410835],"type":"Point"}
}