{
  "type": "Feature",
  "properties": {
    "iso:country":"FR",
    "sg:address":"Route Nationale 10 40410 Liposthey",
    "sg:city":"Liposthey",
    "sg:classifiers":[
        {
            "category":"Transit Center",
            "subcategory":"Freight",
            "type":"Transportation"
        }
    ],
    "sg:phone":"+33 5 58 82 39 39",
    "sg:postcode":"40410",
    "sg:province":"Aquitaine",
    "sg:tags":[
        "metallurgy",
        "pipe",
        "metalworking",
        "sheet"
    ],
    "wof:name":"Electronique (ste Landaise D) Sarl",
    "wof:placetype":"venue"
},
  "geometry": {"coordinates":[-0.810409,44.269989],"type":"Point"}
}