{
  "type": "Feature",
  "properties": {
    "iso:country":"FR",
    "sg:address":"Ile de la Barthelasse",
    "sg:city":"Avignon",
    "sg:orig_category":"Non-Classified Establishments",
    "sg:phone":"+33 4 90 82 62 29",
    "sg:postcode":"84000",
    "sg:province":"Languedoc-Roussillon",
    "wof:name":"Distillerie Manguin S.a.",
    "wof:placetype":"venue"
},
  "geometry": {"coordinates":[4.817336,43.964222],"type":"Point"}
}