{
  "type": "Feature",
  "properties": {
    "addr:full":"B.P. 3 Rinxent^^62720 Rinxent Nord Pas-de-Calais 62720",
    "addr:postcode":"62720",
    "addr:street":"B.P. 3 Rinxent^^62720 Rinxent Nord",
    "iso:country":"FR",
    "sg:address":"B.P. 3",
    "sg:city":"Rinxent^^62720 Rinxent",
    "sg:orig_category":"Non-Classified Establishments",
    "sg:phone":"+33 3 21 99 53 99",
    "sg:postcode":"62720",
    "sg:province":"Nord Pas-de-Calais",
    "wof:name":"Carri\u00e8res De La Vall\u00e9e Heureuse S.a.",
    "wof:placetype":"venue"
},
  "geometry": {"coordinates":[1.775265,50.798222],"type":"Point"}
}