{
  "type": "Feature",
  "properties": {
    "iso:country":"FR",
    "sg:address":"3 Rue Le Turquie De Longchamp 76100 Rouen",
    "sg:classifiers":[
        {
            "category":"Manufacturing",
            "subcategory":"Chemicals & Compounds",
            "type":"Manufacturing & Wholesale Goods"
        }
    ],
    "sg:phone":"+33 2 35 58 10 00",
    "sg:postcode":"76100",
    "sg:province":"Haute Normandie",
    "sg:tags":[
        "pharmaceutical",
        "energy",
        "chemistry",
        "-",
        "by-product"
    ],
    "wof:name":"Total Fina Elf Lubrifiants",
    "wof:placetype":"venue"
},
  "geometry": {"coordinates":[1.051227,49.43449],"type":"Point"}
}