{
  "type": "Feature",
  "properties": {
    "addr:full":"9 Bis Rue De Didenheim 68200 Mulhouse Mulhouse Alsace 68200",
    "addr:housenumber":"9 bis",
    "addr:postcode":"68200;68200",
    "addr:street":"Rue De Didenheim",
    "iso:country":"FR",
    "sg:address":"9 Bis Rue De Didenheim 68200 Mulhouse",
    "sg:city":"Mulhouse",
    "sg:classifiers":[
        {
            "category":"Farming",
            "subcategory":"Livestock Farm",
            "type":"Manufacturing & Wholesale Goods"
        }
    ],
    "sg:phone":"+33 3 89 43 96 76",
    "sg:postcode":"68200",
    "sg:province":"Alsace",
    "sg:tags":[
        "breeding",
        "agriculture",
        "animal"
    ],
    "wof:name":"Specialites Alimentaires Preparees (sap)",
    "wof:placetype":"venue"
},
  "geometry": {"coordinates":[7.310088,47.743557],"type":"Point"}
}