{
  "type": "Feature",
  "properties": {
    "addr:full":"22, Rue du Cornulier, 44018 Nantes C\u00e9dex 01 R\u00e9gion Pays de la Loire",
    "addr:housenumber":"22;01",
    "addr:postcode":"44018",
    "addr:street":"Rue Du Cornulier;Re\u0301Gion",
    "iso:country":"FR",
    "sg:address":"22, Rue du Cornulier, 44018 Nantes C\u00e9dex 01",
    "sg:orig_category":"Non-Classified Establishments",
    "sg:phone":"+33 2 40 35 04 80",
    "sg:province":"R\u00e9gion Pays de la Loire",
    "wof:name":"J.e.p. S.a.r.l. - Jallais Etude Et Projet",
    "wof:placetype":"venue"
},
  "geometry": {"coordinates":[-1.540323,47.215141],"type":"Point"}
}