{
  "type": "Feature",
  "properties": {
    "iso:country":"FR",
    "sg:address":"9, Rue du Docteur Piquenard - ZI de l'Hippodrome, 29000 Quimper",
    "sg:city":"Quimper",
    "sg:orig_category":"Non-Classified Establishments",
    "sg:phone":"+33 2 98 90 74 74",
    "sg:postcode":"29000",
    "sg:province":"Bretagne",
    "wof:name":"Kdi Rou\u00ebnel S.a.s.",
    "wof:placetype":"venue"
},
  "geometry": {"coordinates":[-4.092478,47.995991],"type":"Point"}
}