{
  "type": "Feature",
  "properties": {
    "addr:full":"9, Rue Clos Reine, 78410 Aubergenville Ile de France",
    "addr:housenumber":"9",
    "addr:postcode":"78410;ile",
    "addr:street":"Rue Clos Reine",
    "iso:country":"FR",
    "sg:address":"9, Rue Clos Reine, 78410 Aubergenville",
    "sg:orig_category":"Unclassifiable Establishments",
    "sg:phone":"+33 1 30 90 57 35",
    "sg:province":"Ile de France",
    "wof:name":"G\u00e9odis Logistics France S.a.",
    "wof:placetype":"venue"
},
  "geometry": {"coordinates":[1.849058,48.967491],"type":"Point"}
}