{
  "type": "Feature",
  "properties": {
    "iso:country":"FR",
    "sg:address":"247, Rue Jean-Jacques Rousseau, 92130 Issy les Moulineaux",
    "sg:orig_category":"Non-Classified Establishments",
    "sg:phone":"+33 1 46 42 11 00",
    "sg:postcode":"92130",
    "sg:province":"Ile de France",
    "wof:name":"Bellatrix S.a.r.l.",
    "wof:placetype":"venue"
},
  "geometry": {"coordinates":[2.254558,48.821892],"type":"Point"}
}