{
  "type": "Feature",
  "properties": {
    "iso:country":"FR",
    "sg:address":"11 Rte Des Gagets 44000 Nantes",
    "sg:classifiers":[
        {
            "category":"Building & Trades",
            "subcategory":"Construction",
            "type":"Services"
        }
    ],
    "sg:phone":"+33 2 51 89 53 53",
    "sg:postcode":"44000",
    "sg:province":"Pays de Loire",
    "sg:tags":[
        "work",
        "public"
    ],
    "wof:name":"Egtp Le Guillou Snc",
    "wof:placetype":"venue"
},
  "geometry": {"coordinates":[-1.553059,47.218117],"type":"Point"}
}