{
  "type": "Feature",
  "properties": {
    "addr:full":"A\u00e9roport de Chavenay Villepreux Ile de France 78450",
    "addr:postcode":"78450",
    "iso:country":"FR",
    "sg:address":"A\u00e9roport de Chavenay",
    "sg:city":"Villepreux",
    "sg:orig_category":"Unclassifiable Establishments",
    "sg:phone":"+33 1 30 56 28 71",
    "sg:postcode":"78450",
    "sg:province":"Ile de France",
    "wof:name":"A.d.p. - A\u00e9roport De Paris",
    "wof:placetype":"venue"
},
  "geometry": {"coordinates":[2.004505,48.830528],"type":"Point"}
}