{
  "type": "Feature",
  "properties": {
    "addr:full":"ZI la Plaine Monthion Rhone-Alpes 73200",
    "addr:postcode":"73200",
    "addr:street":"Zi La Plaine;Rhone-Alpes",
    "iso:country":"FR",
    "sg:address":"ZI la Plaine",
    "sg:city":"Monthion",
    "sg:orig_category":"Non-Classified Establishments",
    "sg:phone":"+33 4 79 32 30 32",
    "sg:postcode":"73200",
    "sg:province":"Rhone-Alpes",
    "wof:name":"Parent Electronique S.a.r.l.",
    "wof:placetype":"venue"
},
  "geometry": {"coordinates":[6.359874,45.63168],"type":"Point"}
}