{
  "type": "Feature",
  "properties": {
    "addr:full":"7 rue Jean Dutilloya Asnieres sur seine 92600",
    "addr:housenumber":"7",
    "addr:postcode":"92600",
    "addr:street":"Rue Jean Dutilloya Asnieres Sur Seine",
    "iso:country":"FR",
    "sg:address":"7 rue Jean Dutilloya",
    "sg:city":"Asnieres sur seine",
    "sg:classifiers":[
        {
            "category":"Professional",
            "subcategory":"Computer Services",
            "type":"Services"
        }
    ],
    "sg:postcode":"92600",
    "sg:tags":[
        "3d",
        "modeling",
        "experience"
    ],
    "sg:website":"http://www.squareclock.com",
    "wof:name":"SquareClock",
    "wof:placetype":"venue"
},
  "geometry": {"coordinates":[2.286042,48.90648],"type":"Point"}
}