{
  "type": "Feature",
  "properties": {
    "addr:full":"Zi 59286 Roost Warendin Nord Pas-de-Calais 59286",
    "addr:postcode":"59286;59286",
    "addr:street":"Zi;Warendin Nord",
    "iso:country":"FR",
    "sg:address":"Zi 59286 Roost Warendin",
    "sg:classifiers":[
        {
            "category":"Manufacturing",
            "subcategory":"Tools & Machinery",
            "type":"Manufacturing & Wholesale Goods"
        }
    ],
    "sg:phone":"+33 3 27 88 10 10",
    "sg:postcode":"59286",
    "sg:province":"Nord Pas-de-Calais",
    "sg:tags":[
        "metallurgy",
        "metalworking"
    ],
    "wof:name":"Leuco Oertli",
    "wof:placetype":"venue"
},
  "geometry": {"coordinates":[3.102545,50.41832],"type":"Point"}
}