{
  "type": "Feature",
  "properties": {
    "addr:full":"Rue Lafayette BP 32 67100 Strasbourg Cedex 1 Strasbourg Alsace 67100",
    "addr:housenumber":"bp 32",
    "addr:postcode":"67100;67100",
    "addr:street":"Rue Lafayette",
    "iso:country":"FR",
    "sg:address":"Rue Lafayette BP 32 67100 Strasbourg Cedex 1",
    "sg:city":"Strasbourg",
    "sg:classifiers":[
        {
            "category":"Shopping",
            "type":"Retail Goods"
        }
    ],
    "sg:phone":"+33 3 88 40 66 61",
    "sg:postcode":"67100",
    "sg:province":"Alsace",
    "sg:tags":[
        "metallurgy",
        "finished",
        "-",
        "metalworking",
        "metallic"
    ],
    "wof:name":"Similor Kugler Sa",
    "wof:placetype":"venue"
},
  "geometry": {"coordinates":[7.76865,48.534969],"type":"Point"}
}