{
  "type": "Feature",
  "properties": {
    "addr:full":"B.P. 40, 77201 Marne la Vall\u00e9e C\u00e9dex 2^^ZI Nord - B\u00e2t. 5, 77200 Torcy Ile de France",
    "addr:housenumber":"5",
    "addr:postcode":"77201;77200;ile",
    "addr:street":"B.P. 40",
    "iso:country":"FR",
    "sg:address":"B.P. 40, 77201 Marne la Vall\u00e9e C\u00e9dex 2^^ZI Nord - B\u00e2t. 5, 77200 Torcy",
    "sg:orig_category":"Non-Classified Establishments",
    "sg:phone":"+33 1 60 17 05 50",
    "sg:province":"Ile de France",
    "wof:name":"L'atelier Du Moulin S.a.r.l.",
    "wof:placetype":"venue"
},
  "geometry": {"coordinates":[2.651845,48.849575],"type":"Point"}
}