{
  "type": "Feature",
  "properties": {
    "iso:country":"FR",
    "sg:address":"17 bis, Rue des Varennes, 45140 Ormes",
    "sg:city":"Ormes",
    "sg:orig_category":"Non-Classified Establishments",
    "sg:phone":"+33 2 38 52 38 52",
    "sg:postcode":"45140",
    "sg:province":"Centre",
    "wof:name":"Esus Bureautique S.a.",
    "wof:placetype":"venue"
},
  "geometry": {"coordinates":[1.831565,47.947346],"type":"Point"}
}