{
  "type": "Feature",
  "properties": {
    "addr:full":"4 rue Rivi\u00e8re 33500 Libourne Libourne Aquitaine 33500",
    "addr:housenumber":"4",
    "addr:postcode":"33500;33500",
    "addr:street":"Rue Rivie\u0300Re",
    "iso:country":"FR",
    "sg:address":"4 rue Rivi\u00e8re 33500 Libourne",
    "sg:city":"Libourne",
    "sg:orig_category":"Hydroponic Plants",
    "sg:phone":"+33 5 57 51 98 39",
    "sg:postcode":"33500",
    "sg:province":"Aquitaine",
    "wof:name":"Kurios Sarl",
    "wof:placetype":"venue"
},
  "geometry": {"coordinates":[-0.240734,44.925678],"type":"Point"}
}