{
  "type": "Feature",
  "properties": {
    "addr:full":"3, Rue Pierre Gourry, 16130 Segonzac Poitou-Charentes",
    "addr:housenumber":"3",
    "addr:postcode":"16130",
    "addr:street":"Rue Pierre Gourry",
    "iso:country":"FR",
    "sg:address":"3, Rue Pierre Gourry, 16130 Segonzac",
    "sg:orig_category":"Non-Classified Establishments",
    "sg:phone":"+33 5 45 83 40 24",
    "sg:province":"Poitou-Charentes",
    "wof:name":"J. Painturaud S.a.r.l.",
    "wof:placetype":"venue"
},
  "geometry": {"coordinates":[-0.222339,45.615665],"type":"Point"}
}