{
  "type": "Feature",
  "properties": {
    "iso:country":"FR",
    "sg:address":"90, Cours Vitton, 69006 Lyon",
    "sg:orig_category":"Non-Classified Establishments",
    "sg:phone":"+33 4 78 52 20 40",
    "sg:province":"Rhone-Alpes",
    "wof:name":"Imprimerie Semoun S.a.",
    "wof:placetype":"venue"
},
  "geometry": {"coordinates":[4.858907,45.769978],"type":"Point"}
}