{
  "type": "Feature",
  "properties": {
    "iso:country":"FR",
    "sg:address":"255, Rue Antoine Burellier, 42153 Riorges",
    "sg:orig_category":"Non-Classified Establishments",
    "sg:phone":"+33 4 77 72 14 11",
    "sg:province":"Rhone-Alpes",
    "wof:name":"Laboure S.a.",
    "wof:placetype":"venue"
},
  "geometry": {"coordinates":[4.054287,46.048981],"type":"Point"}
}