{
  "type": "Feature",
  "properties": {
    "iso:country":"FR",
    "sg:address":"rue Pierre Mend\u00e8s-France 69120 Vaulx en Velin",
    "sg:classifiers":[
        {
            "category":"Banks & Credit Unions",
            "subcategory":"Bureau De Change",
            "type":"Services"
        }
    ],
    "sg:phone":"+33 4 78 80 72 55",
    "sg:postcode":"69120",
    "sg:province":"Rhone-Alpes",
    "sg:tags":[
        "decorative",
        "fibre",
        "made",
        "natural",
        "wall",
        "plaster",
        "linings"
    ],
    "wof:name":"Sidac Diffusion Sa",
    "wof:placetype":"venue"
},
  "geometry": {"coordinates":[4.93572,45.781319],"type":"Point"}
}