{
  "type": "Feature",
  "properties": {
    "iso:country":"FR",
    "sg:address":"2, Rue d'Allemagne, 44330 Nantes",
    "sg:orig_category":"Non-Classified Establishments",
    "sg:phone":"+33 2 40 68 37 80",
    "sg:province":"Pays de Loire",
    "wof:name":"Initial Btb S.a.",
    "wof:placetype":"venue"
},
  "geometry": {"coordinates":[-1.498353,47.254333],"type":"Point"}
}