{
  "type": "Feature",
  "properties": {
    "addr:full":"B.P. 29018, 30971 N\u00eemes C\u00e9dex 9^^41, Rue Andr\u00e9 Le N\u00f4tre, 30000 N\u00eemes Languedoc-Roussillon",
    "addr:housenumber":"^ 41",
    "addr:postcode":"30971;30000",
    "addr:street":"Rue Andre\u0301 Le No\u0302Tre",
    "iso:country":"FR",
    "sg:address":"B.P. 29018, 30971 N\u00eemes C\u00e9dex 9^^41, Rue Andr\u00e9 Le N\u00f4tre, 30000 N\u00eemes",
    "sg:orig_category":"Non-Classified Establishments",
    "sg:phone":"+33 4 66 04 70 47",
    "sg:province":"Languedoc-Roussillon",
    "wof:name":"Starvrac S.a.",
    "wof:placetype":"venue"
},
  "geometry": {"coordinates":[4.36035,43.86256],"type":"Point"}
}