{
  "type": "Feature",
  "properties": {
    "iso:country":"FR",
    "sg:address":"45, Rue Gutenberg - ZI de l'Escudillier, 15000 Aurillac",
    "sg:city":"Aurillac",
    "sg:orig_category":"Non-Classified Establishments",
    "sg:phone":"+33 4 71 48 21 91",
    "sg:postcode":"15000",
    "sg:province":"Auvergne",
    "wof:name":"A.e.e. S.a. - Atelier D'equipement Electrique",
    "wof:placetype":"venue"
},
  "geometry": {"coordinates":[2.422452,44.916969],"type":"Point"}
}