{
  "type": "Feature",
  "properties": {
    "addr:full":"Survaure 42600 Montbrison Rhone-Alpes 42600",
    "addr:postcode":"42600;42600",
    "addr:street":"Survaure",
    "iso:country":"FR",
    "sg:address":"Survaure 42600 Montbrison",
    "sg:classifiers":[
        {
            "category":"Manufacturing",
            "subcategory":"Metals",
            "type":"Manufacturing & Wholesale Goods"
        }
    ],
    "sg:phone":"+33 4 77 58 17 18",
    "sg:postcode":"42600",
    "sg:province":"Rhone-Alpes",
    "sg:tags":[
        "metallurgy",
        "metalworking",
        "processing"
    ],
    "wof:name":"Fairchild Snep Sa",
    "wof:placetype":"venue"
},
  "geometry": {"coordinates":[4.062692,45.617428],"type":"Point"}
}