{
  "type": "Feature",
  "properties": {
    "iso:country":"FR",
    "sg:address":"B.P. 0436, 37004 Tours C\u00e9dex^^45, Av Stendhal, 37000 Tours",
    "sg:city":"Tours",
    "sg:orig_category":"Non-Classified Establishments",
    "sg:phone":"+33 2 47 48 51 23",
    "sg:postcode":"37000",
    "sg:province":"Centre",
    "wof:name":"Edf-gdf Services Touraine",
    "wof:placetype":"venue"
},
  "geometry": {"coordinates":[0.689715,47.390385],"type":"Point"}
}