{
  "type": "Feature",
  "properties": {
    "iso:country":"FR",
    "sg:address":"61 Rue du Ch\u00e2teau d'Eau, 33076 Bordeaux Cedex, Dept 33",
    "sg:city":"Bordeaux",
    "sg:classifiers":[
        {
            "category":"Banks & Credit Unions",
            "subcategory":"Bank",
            "type":"Services"
        }
    ],
    "sg:phone":"+33 5 56 00 15 15",
    "sg:postcode":"33100",
    "sg:province":"Aquitaine",
    "wof:name":"Caisse D'epargne Aquitaine Nord",
    "wof:placetype":"venue"
},
  "geometry": {"coordinates":[-0.52418,44.809174],"type":"Point"}
}