{
  "type": "Feature",
  "properties": {
    "iso:country":"FR",
    "sg:address":"6, Rte du Plessis Bouchet, 44800 Saint Herblain",
    "sg:orig_category":"Unclassifiable Establishments",
    "sg:phone":"+33 2 40 95 02 23",
    "sg:province":"Pays de Loire",
    "wof:name":"Eurom\u00e9canique G\u00e9n\u00e9rale Pr\u00e9cision S.a.r.l.",
    "wof:placetype":"venue"
},
  "geometry": {"coordinates":[-1.639869,47.20208],"type":"Point"}
}