{
  "type": "Feature",
  "properties": {
    "iso:country":"FR",
    "sg:address":"100 Rue Louis Blanc 60160 Montataire",
    "sg:classifiers":[
        {
            "category":"Building & Trades",
            "subcategory":"Electrical",
            "type":"Services"
        }
    ],
    "sg:phone":"+33 3 44 24 79 96",
    "sg:postcode":"60160",
    "sg:province":"Picardie",
    "sg:tags":[
        "electronic",
        "lighting",
        "equipment"
    ],
    "wof:name":"D Light France (dlf)",
    "wof:placetype":"venue"
},
  "geometry": {"coordinates":[2.453715,49.259392],"type":"Point"}
}