{
  "type": "Feature",
  "properties": {
    "addr:full":"Gagne 44700 Orvault Pays de Loire",
    "addr:postcode":"44700",
    "addr:street":"Gagne",
    "iso:country":"FR",
    "sg:address":"Gagne 44700 Orvault",
    "sg:orig_category":"Non-Classified Establishments",
    "sg:phone":"+33 2 40 63 03 24",
    "sg:province":"Pays de Loire",
    "wof:name":"P\u00e9pini\u00e8res Et Jardinerie Blineau S.a.r.l.",
    "wof:placetype":"venue"
},
  "geometry": {"coordinates":[-1.630687,47.280876],"type":"Point"}
}