{
  "type": "Feature",
  "properties": {
    "iso:country":"FR",
    "sg:address":"Prairie de Courr\u00e8jean",
    "sg:city":"Villenave d'Ornon",
    "sg:orig_category":"Unclassifiable Establishments",
    "sg:phone":"+33 5 56 87 78 87",
    "sg:postcode":"33140",
    "sg:province":"Aquitaine",
    "wof:name":"A.f.m. Recyclage S.a.",
    "wof:placetype":"venue"
},
  "geometry": {"coordinates":[-0.568254,44.759846],"type":"Point"}
}