{
  "type": "Feature",
  "properties": {
    "addr:full":"60 Av Du G\u00e9n\u00e9ral De Gaulle 92046 Paris La D\u00e9fense Midi Pyr\u00e9n\u00e9es",
    "addr:postcode":"92046",
    "addr:street":"60 Av Du Ge\u0301Ne\u0301Ral De Gaulle",
    "iso:country":"FR",
    "sg:address":"60 Av Du G\u00e9n\u00e9ral De Gaulle 92046 Paris La D\u00e9fense",
    "sg:classifiers":[
        {
            "category":"Shopping",
            "subcategory":"Luggage & Leather Goods",
            "type":"Retail Goods"
        }
    ],
    "sg:phone":"+33 1 47 76 23 46",
    "sg:province":"Midi Pyr\u00e9n\u00e9es",
    "sg:tags":[
        "shoe"
    ],
    "wof:name":"Multichauss Sa",
    "wof:placetype":"venue"
},
  "geometry": {"coordinates":[2.24119,48.888939],"type":"Point"}
}