{
  "type": "Feature",
  "properties": {
    "iso:country":"FR",
    "sg:address":"863 Rue Gare 59299 Boeschepe",
    "sg:classifiers":[
        {
            "category":"Shopping",
            "subcategory":"Crafts & Fabrics",
            "type":"Retail Goods"
        }
    ],
    "sg:phone":"+33 3 28 49 42 22",
    "sg:postcode":"59299",
    "sg:province":"Nord Pas-de-Calais",
    "sg:tags":[
        "textile",
        "clothing"
    ],
    "wof:name":"Alostery Freres (ets) Sarl",
    "wof:placetype":"venue"
},
  "geometry": {"coordinates":[2.683404,50.804768],"type":"Point"}
}