{
  "type": "Feature",
  "properties": {
    "iso:country":"FR",
    "sg:address":"Chem D\u00e9partemental 934 40120 Pouydesseaux",
    "sg:city":"Pouydesseaux",
    "sg:classifiers":[
        {
            "category":"Home & Garden",
            "subcategory":"Furniture",
            "type":"Retail Goods"
        }
    ],
    "sg:phone":"+33 5 58 93 91 81",
    "sg:postcode":"40120",
    "sg:province":"Aquitaine",
    "sg:tags":[
        "wood"
    ],
    "wof:name":"Etablissements Cazaux Laporte Sarl",
    "wof:placetype":"venue"
},
  "geometry": {"coordinates":[-0.274254,43.9515],"type":"Point"}
}