{
  "type": "Feature",
  "properties": {
    "addr:full":"102, Rue Etienne Dolet, 92245 Malakoff C\u00e9dex Franche Comt\u00e9",
    "addr:housenumber":"102",
    "addr:postcode":"92245",
    "addr:street":"Rue Etienne Dolet;Franche Comte\u0301",
    "iso:country":"FR",
    "sg:address":"102, Rue Etienne Dolet, 92245 Malakoff C\u00e9dex",
    "sg:orig_category":"Non-Classified Establishments",
    "sg:phone":"+33 1 46 73 90 00",
    "sg:province":"Franche Comt\u00e9",
    "wof:name":"Elona S.a.",
    "wof:placetype":"venue"
},
  "geometry": {"coordinates":[2.301122,48.813038],"type":"Point"}
}