{
  "type": "Feature",
  "properties": {
    "addr:full":"3, Rte de Limoges, 23210 Marsac Limousin",
    "addr:housenumber":"3",
    "addr:postcode":"23210",
    "addr:street":"Rte De Limoges",
    "iso:country":"FR",
    "sg:address":"3, Rte de Limoges, 23210 Marsac",
    "sg:orig_category":"Non-Classified Establishments",
    "sg:phone":"+33 5 55 81 50 62",
    "sg:province":"Limousin",
    "wof:name":"Plasti 23 S.a.r.l.",
    "wof:placetype":"venue"
},
  "geometry": {"coordinates":[1.580715,46.091633],"type":"Point"}
}