{
  "type": "Feature",
  "properties": {
    "addr:full":"3 Av St Denis Zi De L'Hippodrome 29000 Quimper Quimper Bretagne 29000",
    "addr:postcode":"29000;29000",
    "addr:street":"Av St Denis Zi De L'Hippodrome",
    "iso:country":"FR",
    "sg:address":"3 Av St Denis Zi De L'Hippodrome 29000 Quimper",
    "sg:city":"Quimper",
    "sg:classifiers":[
        {
            "category":"Building & Trades",
            "subcategory":"Equipment Rental",
            "type":"Services"
        }
    ],
    "sg:phone":"+33 2 98 98 49 21",
    "sg:postcode":"29000",
    "sg:province":"Bretagne",
    "sg:tags":[
        "livestock",
        "animal",
        "-",
        "machinery",
        "cereal",
        "gra",
        "breeding",
        "agriculture"
    ],
    "wof:name":"Cooperative Des Agriculteurs De Bretagne",
    "wof:placetype":"venue"
},
  "geometry": {"coordinates":[-4.079293,47.996113],"type":"Point"}
}