{
  "type": "Feature",
  "properties": {
    "addr:full":"4, Impasse Saint Jean, 25720 Larnod Franche Comt\u00e9",
    "addr:housenumber":"4",
    "addr:postcode":"25720",
    "addr:street":"Impasse Saint Jean;Franche Comte\u0301",
    "iso:country":"FR",
    "sg:address":"4, Impasse Saint Jean, 25720 Larnod",
    "sg:orig_category":"Non-Classified Establishments",
    "sg:phone":"+33 3 81 80 92 75",
    "sg:province":"Franche Comt\u00e9",
    "wof:name":"International Safety Quality Management Services S.a.r.l.",
    "wof:placetype":"venue"
},
  "geometry": {"coordinates":[5.98105,47.191399],"type":"Point"}
}