{
  "type": "Feature",
  "properties": {
    "iso:country":"FR",
    "sg:address":"4, Impasse Saint Jean, 25720 Larnod",
    "sg:orig_category":"Non-Classified Establishments",
    "sg:phone":"+33 3 81 80 92 75",
    "sg:province":"Franche Comt\u00e9",
    "wof:name":"International Safety Quality Management Services S.a.r.l.",
    "wof:placetype":"venue"
},
  "geometry": {"coordinates":[5.98105,47.191399],"type":"Point"}
}