{
  "type": "Feature",
  "properties": {
    "addr:full":"11, Av. du Centre, 78286 Guyancourt C\u00e9dex Ancourt Haute Normandie 76370",
    "addr:postcode":"78286;76370",
    "addr:street":"11 Av. Du Centre;Haute Normandie",
    "iso:country":"FR",
    "sg:address":"11, Av. du Centre, 78286 Guyancourt C\u00e9dex",
    "sg:city":"Ancourt",
    "sg:orig_category":"Non-Classified Establishments",
    "sg:phone":"+33 1 30 48 44 00",
    "sg:postcode":"76370",
    "sg:province":"Haute Normandie",
    "wof:name":"Scetauroute S.a.",
    "wof:placetype":"venue"
},
  "geometry": {"coordinates":[2.048929,48.786575],"type":"Point"}
}