{
  "type": "Feature",
  "properties": {
    "addr:full":"33 Rue Yves Le Caignard 92250 La Garenne Colombes Ile de France",
    "addr:housenumber":"33",
    "addr:postcode":"92250",
    "addr:street":"Rue Yves Le Caignard",
    "iso:country":"FR",
    "sg:address":"33 Rue Yves Le Caignard 92250 La Garenne Colombes",
    "sg:classifiers":[
        {
            "category":"Autos & Motor Vehicles",
            "subcategory":"Automobile Sales",
            "type":"Retail Goods"
        }
    ],
    "sg:phone":"+33 1 47 85 93 57",
    "sg:province":"Ile de France",
    "sg:tags":[
        "equipment",
        "transport"
    ],
    "wof:name":"Synchrosoft",
    "wof:placetype":"venue"
},
  "geometry": {"coordinates":[2.23365,48.907211],"type":"Point"}
}