{
  "type": "Feature",
  "properties": {
    "iso:country":"FR",
    "sg:address":"14 route de Besan\u00e7on ZI La Louvi\u00e8re 25480 Pirey",
    "sg:classifiers":[
        {
            "category":"Manufacturing",
            "subcategory":"Metals",
            "type":"Manufacturing & Wholesale Goods"
        }
    ],
    "sg:phone":"+33 3 81 50 21 67",
    "sg:postcode":"25480",
    "sg:province":"Franche Comt\u00e9",
    "sg:tags":[
        "blanking",
        "dy"
    ],
    "wof:name":"Grosperrin S.a.",
    "wof:placetype":"venue"
},
  "geometry": {"coordinates":[5.982078,47.27187],"type":"Point"}
}