{
  "type": "Feature",
  "properties": {
    "addr:full":"rue Aspirant Buffet 21000 Dijon Dijon Bourgogne 21000",
    "addr:postcode":"21000;21000",
    "addr:street":"Rue Aspirant Buffet",
    "iso:country":"FR",
    "sg:address":"rue Aspirant Buffet 21000 Dijon",
    "sg:city":"Dijon",
    "sg:classifiers":[
        {
            "category":"Food & Beverages",
            "subcategory":"Meat & Fish",
            "type":"Retail Goods"
        }
    ],
    "sg:phone":"+33 3 80 78 78 00",
    "sg:postcode":"21000",
    "sg:province":"Bourgogne",
    "wof:name":"Les Salaisons Dijonnaise S.a.",
    "wof:placetype":"venue"
},
  "geometry": {"coordinates":[5.06191,47.33902],"type":"Point"}
}