{
  "type": "Feature",
  "properties": {
    "iso:country":"FR",
    "sg:address":"Rte de Comine",
    "sg:city":"Quesnoy sur De\u00fble",
    "sg:orig_category":"Non-Classified Establishments",
    "sg:phone":"+33 3 20 39 87 78",
    "sg:postcode":"59890",
    "sg:province":"Nord Pas-de-Calais",
    "wof:name":"Cousin G\u00e9rard Transports S.a.",
    "wof:placetype":"venue"
},
  "geometry": {"coordinates":[3.00305,50.718716],"type":"Point"}
}