{
  "type": "Feature",
  "properties": {
    "addr:full":"12, Rue de la Jalousie, 44900 Sainte Luce sur Loire Outre-Mer",
    "addr:housenumber":"12",
    "addr:postcode":"44900",
    "addr:street":"Rue De La Jalousie",
    "iso:country":"FR",
    "sg:address":"12, Rue de la Jalousie, 44900 Sainte Luce sur Loire",
    "sg:orig_category":"Unclassifiable Establishments",
    "sg:phone":"+33 2 51 13 32 00",
    "sg:province":"Outre-Mer",
    "wof:name":"G.a.b.o.p.l.a. - Groupement D'achats Des Boulangers P\u00e2tissiers De",
    "wof:placetype":"venue"
},
  "geometry": {"coordinates":[-98.38118,29.10928],"type":"Point"}
}