{
  "type": "Feature",
  "properties": {
    "addr:full":"5 Lot De La Fosse Yvon 50440 Beaumont Hague Acqueville Basse Normandie 50440",
    "addr:housenumber":"5",
    "addr:postcode":"50440;50440",
    "addr:street":"Lot De La Fosse Yvon",
    "iso:country":"FR",
    "sg:address":"5 Lot De La Fosse Yvon 50440 Beaumont Hague",
    "sg:city":"Acqueville",
    "sg:classifiers":[
        {
            "category":"Professional",
            "subcategory":"Engineering",
            "type":"Services"
        }
    ],
    "sg:phone":"+33 2 33 53 50 73",
    "sg:postcode":"50440",
    "sg:province":"Basse Normandie",
    "sg:tags":[
        "machine",
        "-",
        "mechanical"
    ],
    "wof:name":"Ets Simon Freres",
    "wof:placetype":"venue"
},
  "geometry": {"coordinates":[-1.779169,49.59861],"type":"Point"}
}