{
  "type": "Feature",
  "properties": {
    "addr:full":"225 quai du Midi 17000 La Rochelle Poitou-Charentes",
    "addr:housenumber":"225",
    "addr:postcode":"17000",
    "addr:street":"Quai Du Midi",
    "iso:country":"FR",
    "sg:address":"225 quai du Midi 17000 La Rochelle",
    "sg:classifiers":[
        {
            "category":"Real Estate",
            "subcategory":"Real Estate Services",
            "type":"Services"
        }
    ],
    "sg:phone":"+33 5 46 41 24 44",
    "sg:province":"Poitou-Charentes",
    "sg:tags":[
        "crustacean",
        "shellfish"
    ],
    "wof:name":"Mareyage Et Armement Rochelais Sarl",
    "wof:placetype":"venue"
},
  "geometry": {"coordinates":[-1.218267,46.14769],"type":"Point"}
}