{
  "type": "Feature",
  "properties": {
    "iso:country":"FR",
    "sg:address":"630 Chemin Noyers 38690 Colombe",
    "sg:classifiers":[
        {
            "category":"Professional",
            "subcategory":"Advertising",
            "type":"Services"
        }
    ],
    "sg:phone":"+33 4 76 55 82 36",
    "sg:postcode":"38690",
    "sg:province":"Rhone-Alpes",
    "sg:tags":[
        "communication",
        "medium"
    ],
    "wof:name":"Burrial Fils Sarl",
    "wof:placetype":"venue"
},
  "geometry": {"coordinates":[5.46277,45.400017],"type":"Point"}
}