{
  "type": "Feature",
  "properties": {
    "iso:country":"FR",
    "sg:address":"89-149 rue de l'Industrie 74330 Epagny",
    "sg:classifiers":[
        {
            "category":"Autos & Motor Vehicles",
            "subcategory":"Recreational Vehicle Sales",
            "type":"Retail Goods"
        }
    ],
    "sg:phone":"+33 4 50 24 20 30",
    "sg:postcode":"74330",
    "sg:province":"Rhone-Alpes",
    "sg:tags":[
        "car",
        "part"
    ],
    "wof:name":"Autodistribution 74 Sas",
    "wof:placetype":"venue"
},
  "geometry": {"coordinates":[6.080035,45.937023],"type":"Point"}
}