{
  "type": "Feature",
  "properties": {
    "addr:full":"Les Ambroises Montceau Les Meaux 77470 Trilport Ile de France 77470",
    "addr:postcode":"77470;77470",
    "addr:street":"Ile De France",
    "iso:country":"FR",
    "sg:address":"Les Ambroises Montceau Les Meaux 77470 Trilport",
    "sg:classifiers":[
        {
            "category":"Shopping",
            "type":"Retail Goods"
        }
    ],
    "sg:phone":"+33 1 64 35 90 68",
    "sg:postcode":"77470",
    "sg:province":"Ile de France",
    "sg:tags":[
        "metallurgy",
        "finished",
        "-",
        "metalworking",
        "metallic"
    ],
    "wof:name":"Serriere Sa",
    "wof:placetype":"venue"
},
  "geometry": {"coordinates":[2.94871,48.957806],"type":"Point"}
}