{
  "type": "Feature",
  "properties": {
    "addr:full":"13, Rue Saint Louis, 93500 Pantin Ile de France",
    "addr:housenumber":"13",
    "addr:postcode":"93500;ile",
    "addr:street":"Rue Saint Louis",
    "iso:country":"FR",
    "sg:address":"13, Rue Saint Louis, 93500 Pantin",
    "sg:orig_category":"Unclassifiable Establishments",
    "sg:phone":"+33 1 48 45 85 24",
    "sg:province":"Ile de France",
    "wof:name":"Mamon S.a.r.l.",
    "wof:placetype":"venue"
},
  "geometry": {"coordinates":[2.418543,48.890678],"type":"Point"}
}