{
  "type": "Feature",
  "properties": {
    "iso:country":"FR",
    "sg:address":"339, Rue J.E. Blanc, 76550 Offranville",
    "sg:orig_category":"Unclassifiable Establishments",
    "sg:phone":"+33 2 32 06 33 33",
    "sg:province":"Haute Normandie",
    "wof:name":"Rousseau S.a.",
    "wof:placetype":"venue"
},
  "geometry": {"coordinates":[1.030699,49.897762],"type":"Point"}
}