{
  "type": "Feature",
  "properties": {
    "iso:country":"FR",
    "sg:address":"B.P. 534, 26005 Valence C\u00e9dex^^44, All\u00e9e Bernard Palissy, 26000 Valence",
    "sg:orig_category":"Non-Classified Establishments",
    "sg:phone":"+33 4 75 81 70 60",
    "sg:province":"Rhone-Alpes",
    "wof:name":"Morel Et Fils S.a.",
    "wof:placetype":"venue"
},
  "geometry": {"coordinates":[4.889246,44.930458],"type":"Point"}
}