{
  "type": "Feature",
  "properties": {
    "iso:country":"FR",
    "sg:address":"Le Bois 2 49500 Nyoiseau",
    "sg:orig_category":"Unclassifiable Establishments",
    "sg:phone":"+33 2 41 92 87 00",
    "sg:province":"Pays de Loire",
    "wof:name":"Sonel S.a.",
    "wof:placetype":"venue"
},
  "geometry": {"coordinates":[-0.927114,47.699375],"type":"Point"}
}