{
  "type": "Feature",
  "properties": {
    "iso:country":"FR",
    "sg:address":"Za Le Perrier 38630 Veyrins Thuellin",
    "sg:classifiers":[
        {
            "category":"Professional",
            "subcategory":"Engineering",
            "type":"Services"
        }
    ],
    "sg:phone":"+33 4 74 33 61 10",
    "sg:postcode":"38630",
    "sg:province":"Rhone-Alpes",
    "sg:tags":[
        "machine",
        "-",
        "mechanical"
    ],
    "wof:name":"Rmis Sa",
    "wof:placetype":"venue"
},
  "geometry": {"coordinates":[5.53878,45.626099],"type":"Point"}
}