{
  "type": "Feature",
  "properties": {
    "addr:full":"1, Chemin des Maisonnettes, 39150 Saint Laurent en Grandvaux Franche Comt\u00e9",
    "addr:housenumber":"1",
    "addr:postcode":"39150",
    "addr:street":"Chemin Des Maisonnettes;Franche Comte\u0301",
    "iso:country":"FR",
    "sg:address":"1, Chemin des Maisonnettes, 39150 Saint Laurent en Grandvaux",
    "sg:orig_category":"Unclassifiable Establishments",
    "sg:phone":"+33 3 84 60 15 65",
    "sg:province":"Franche Comt\u00e9",
    "wof:name":"M.a.j.h.o.r. S.a. - Manufacture Jurassienne D'horlogerie",
    "wof:placetype":"venue"
},
  "geometry": {"coordinates":[5.956609,46.569824],"type":"Point"}
}