{
  "type": "Feature",
  "properties": {
    "addr:full":"37 Rue Des Deportes 88580 Saulcy Sur Meurthe Lorraine 88580",
    "addr:housenumber":"37",
    "addr:postcode":"88580;88580",
    "addr:street":"Rue Des Deportes",
    "iso:country":"FR",
    "sg:address":"37 Rue Des Deportes 88580 Saulcy Sur Meurthe",
    "sg:classifiers":[
        {
            "category":"Autos & Motor Vehicles",
            "subcategory":"Automobile Sales",
            "type":"Retail Goods"
        }
    ],
    "sg:phone":"+33 3 29 50 00 17",
    "sg:postcode":"88580",
    "sg:province":"Lorraine",
    "sg:tags":[
        "equipment",
        "motor-cars",
        "transport"
    ],
    "wof:name":"Carrosserie Girompaire Sarl",
    "wof:placetype":"venue"
},
  "geometry": {"coordinates":[6.962914,48.23695],"type":"Point"}
}