{
  "type": "Feature",
  "properties": {
    "addr:full":"Parc Walibi Aquitaine 47310 Roquefort Roquefort Aquitaine 47310",
    "addr:postcode":"47310;47310",
    "iso:country":"FR",
    "sg:address":"Parc Walibi Aquitaine 47310 Roquefort",
    "sg:city":"Roquefort",
    "sg:classifiers":[
        {
            "category":"Sports & Exercise",
            "subcategory":"Sports Center",
            "type":"Entertainment"
        }
    ],
    "sg:phone":"+33 5 53 96 58 32",
    "sg:postcode":"47310",
    "sg:province":"Aquitaine",
    "sg:tags":[
        "game"
    ],
    "wof:name":"Parc Agen",
    "wof:placetype":"venue"
},
  "geometry": {"coordinates":[0.518632,44.076218],"type":"Point"}
}