{
  "type": "Feature",
  "properties": {
    "iso:country":"FR",
    "sg:address":"B.P. 35",
    "sg:city":"Etoile sur Rh\u00f4ne",
    "sg:orig_category":"Non-Classified Establishments",
    "sg:phone":"+33 4 75 57 89 00",
    "sg:postcode":"26801",
    "sg:province":"Rhone-Alpes",
    "wof:name":"P\u00e2tisserie Pasquier Sud S.a.s.",
    "wof:placetype":"venue"
},
  "geometry": {"coordinates":[4.8962,44.83691],"type":"Point"}
}