{
  "type": "Feature",
  "properties": {
    "addr:full":"Av. de la Gare Nissan lez Enserune Languedoc-Roussillon 34440",
    "addr:postcode":"34440",
    "addr:street":"Av. De La Gare",
    "iso:country":"FR",
    "sg:address":"Av. de la Gare",
    "sg:city":"Nissan lez Enserune",
    "sg:orig_category":"Unclassifiable Establishments",
    "sg:phone":"+33 4 67 37 67 37",
    "sg:postcode":"34440",
    "sg:province":"Languedoc-Roussillon",
    "wof:name":"Soci\u00e9t\u00e9 D'exploitation Des Etablissements Paul Vidal S.a.",
    "wof:placetype":"venue"
},
  "geometry": {"coordinates":[3.122074,43.291641],"type":"Point"}
}