{
  "type": "Feature",
  "properties": {
    "addr:full":"3 R De La R\u00e9publique 30100 Ales Languedoc-Roussillon 30100",
    "addr:housenumber":"3",
    "addr:postcode":"30100;30100",
    "addr:street":"R De La Re\u0301Publique",
    "iso:country":"FR",
    "sg:address":"3 R De La R\u00e9publique 30100 Ales",
    "sg:classifiers":[
        {
            "category":"Banks & Credit Unions",
            "subcategory":"Financial Services",
            "type":"Services"
        }
    ],
    "sg:phone":"+33 4 66 54 24 24",
    "sg:postcode":"30100",
    "sg:province":"Languedoc-Roussillon",
    "sg:tags":[
        "banking",
        "insurance",
        "institution",
        "finance"
    ],
    "wof:name":"Societe Generale (sg)",
    "wof:placetype":"venue"
},
  "geometry": {"coordinates":[4.078123,44.123463],"type":"Point"}
}