{
  "type": "Feature",
  "properties": {
    "iso:country":"FR",
    "sg:address":"12, Rue Jean Jaur\u00e9s - ZI, 69330 Meyzieu",
    "sg:orig_category":"Non-Classified Establishments",
    "sg:phone":"+33 4 72 45 17 70",
    "sg:province":"Rhone-Alpes",
    "wof:name":"Stowe Woodward France S.a.",
    "wof:placetype":"venue"
},
  "geometry": {"coordinates":[5.00581,45.766296],"type":"Point"}
}