{
  "type": "Feature",
  "properties": {
    "iso:country":"FR",
    "sg:address":"28 Rue De L Erboniere 35510 Cesson Sevigne",
    "sg:city":"Cesson-S\u00e9vign\u00e9",
    "sg:classifiers":[
        {
            "category":"Manufacturing",
            "subcategory":"Printing",
            "type":"Manufacturing & Wholesale Goods"
        }
    ],
    "sg:phone":"+33 2 99 26 12 00",
    "sg:postcode":"35510",
    "sg:province":"Bretagne",
    "sg:tags":[
        "publishing"
    ],
    "wof:name":"Scann Image",
    "wof:placetype":"venue"
},
  "geometry": {"coordinates":[-1.623971,48.102806],"type":"Point"}
}