{
  "type": "Feature",
  "properties": {
    "iso:country":"FR",
    "sg:address":"6 Rue Pierre Timbaud 42420 Lorette",
    "sg:classifiers":[
        {
            "category":"Manufacturing",
            "subcategory":"Metals",
            "type":"Manufacturing & Wholesale Goods"
        }
    ],
    "sg:phone":"+33 4 77 73 53 77",
    "sg:postcode":"42420",
    "sg:province":"Rhone-Alpes",
    "sg:tags":[
        "metallurgy",
        "-",
        "metalworking",
        "metallic",
        "machine",
        "engineering",
        "finished",
        "mechanical"
    ],
    "wof:name":"Somev",
    "wof:placetype":"venue"
},
  "geometry": {"coordinates":[4.5735,45.510342],"type":"Point"}
}