{
  "type": "Feature",
  "properties": {
    "addr:full":"35 Rue Maurice Flandin 69436 Lyon Cedex 03 Aquitaine",
    "addr:housenumber":"35",
    "addr:postcode":"69436;cedex 03",
    "addr:street":"Rue Maurice Flandin",
    "iso:country":"FR",
    "sg:address":"35 Rue Maurice Flandin 69436 Lyon Cedex 03",
    "sg:classifiers":[
        {
            "category":"Banks & Credit Unions",
            "subcategory":"Financial Services",
            "type":"Services"
        }
    ],
    "sg:phone":"+33 4 72 91 91 91",
    "sg:province":"Aquitaine",
    "sg:tags":[
        "banking",
        "finance",
        "insurance"
    ],
    "wof:name":"Caisse Regional D'assurance Maladie Rhone-alpes",
    "wof:placetype":"venue"
},
  "geometry": {"coordinates":[4.863023,45.758804],"type":"Point"}
}