{
  "type": "Feature",
  "properties": {
    "addr:full":"4, Place des Noyers, 18220 Rians Rians Centre 18220",
    "addr:housenumber":"4;rians",
    "addr:postcode":"18220;18220",
    "addr:street":"Place Des Noyers",
    "iso:country":"FR",
    "sg:address":"4, Place des Noyers, 18220 Rians",
    "sg:city":"Rians",
    "sg:orig_category":"Non-Classified Establishments",
    "sg:phone":"+33 2 48 66 60 60",
    "sg:postcode":"18220",
    "sg:province":"Centre",
    "wof:name":"Esteve S.a.",
    "wof:placetype":"venue"
},
  "geometry": {"coordinates":[2.613818,47.18417],"type":"Point"}
}