{
  "type": "Feature",
  "properties": {
    "addr:full":"28, Rue de la Rivi\u00e8re, 72230 Arnage Pays de Loire",
    "addr:housenumber":"28",
    "addr:postcode":"72230",
    "addr:street":"Rue De La Rivie\u0300Re",
    "iso:country":"FR",
    "sg:address":"28, Rue de la Rivi\u00e8re, 72230 Arnage",
    "sg:orig_category":"Non-Classified Establishments",
    "sg:phone":"+33 2 43 84 83 20",
    "sg:province":"Pays de Loire",
    "wof:name":"Fiht S.a.r.l.",
    "wof:placetype":"venue"
},
  "geometry": {"coordinates":[0.18128,47.949986],"type":"Point"}
}