{
  "type": "Feature",
  "properties": {
    "addr:full":"2 Rue Jean Baptiste Pigalle Paris Ile de France 75009",
    "addr:housenumber":"2",
    "addr:postcode":"75009",
    "addr:street":"Rue Jean Baptiste Pigalle",
    "iso:country":"FR",
    "sg:address":"2 Rue Jean Baptiste Pigalle",
    "sg:city":"Paris",
    "sg:classifiers":[
        {
            "category":"Banks & Credit Unions",
            "subcategory":"Financial Services",
            "type":"Services"
        }
    ],
    "sg:phone":"+33 1 48 74 54 00",
    "sg:postcode":"75009",
    "sg:province":"Ile de France",
    "sg:tags":[
        "banking",
        "finance",
        "insurance"
    ],
    "wof:name":"Ste Interprofession Artisanale Garantie",
    "wof:placetype":"venue"
},
  "geometry": {"coordinates":[2.332234,48.87796],"type":"Point"}
}