{
  "type": "Feature",
  "properties": {
    "addr:full":"125 Biscarrosse Aquitaine 40600",
    "addr:housenumber":"125",
    "addr:postcode":"40600",
    "iso:country":"FR",
    "sg:address":"125",
    "sg:city":"Biscarrosse",
    "sg:classifiers":[
        {
            "category":"Autos & Motor Vehicles",
            "subcategory":"Boat Sales",
            "type":"Retail Goods"
        }
    ],
    "sg:phone":"+33 5 58 09 85 00",
    "sg:postcode":"40600",
    "sg:province":"Aquitaine",
    "sg:tags":[
        "equipment",
        "transport"
    ],
    "wof:name":"Nautilac",
    "wof:placetype":"venue"
},
  "geometry": {"coordinates":[-1.176318,44.429539],"type":"Point"}
}