{
  "type": "Feature",
  "properties": {
    "iso:country":"FR",
    "sg:address":"7, Av. Bauxite, 13015 Marseille",
    "sg:orig_category":"Non-Classified Establishments",
    "sg:phone":"+33 4 91 09 43 80",
    "sg:province":"Provence-Alpes-C\u00f4te d'Azur",
    "wof:name":"Todd Freinage S.a.",
    "wof:placetype":"venue"
},
  "geometry": {"coordinates":[5.367135,43.339329],"type":"Point"}
}