{
  "type": "Feature",
  "properties": {
    "addr:full":"Rte D'Hauterive La Fournesie 81100 Castres Midi Pyr\u00e9n\u00e9es 81100",
    "addr:postcode":"81100;81100",
    "addr:street":"Rte D'Hauterive La Fournesie",
    "iso:country":"FR",
    "sg:address":"Rte D'Hauterive La Fournesie 81100 Castres",
    "sg:classifiers":[
        {
            "category":"Shopping",
            "subcategory":"Crafts & Fabrics",
            "type":"Retail Goods"
        }
    ],
    "sg:phone":"+33 5 63 72 24 25",
    "sg:postcode":"81100",
    "sg:province":"Midi Pyr\u00e9n\u00e9es",
    "sg:tags":[
        "textile",
        "clothing"
    ],
    "wof:name":"Gilbert Molinier Sa",
    "wof:placetype":"venue"
},
  "geometry": {"coordinates":[2.24809,43.564377],"type":"Point"}
}