{
  "type": "Feature",
  "properties": {
    "addr:full":"51, Rue Amp\u00e8re, 93330 Neuilly sur Marne Ile de France",
    "addr:housenumber":"51",
    "addr:postcode":"93330",
    "addr:street":"Rue Ampe\u0300Re",
    "iso:country":"FR",
    "sg:address":"51, Rue Amp\u00e8re, 93330 Neuilly sur Marne",
    "sg:orig_category":"Non-Classified Establishments",
    "sg:phone":"+33 1 43 00 46 76",
    "sg:province":"Ile de France",
    "wof:name":"Unisida S.a.r.l.",
    "wof:placetype":"venue"
},
  "geometry": {"coordinates":[2.522024,48.869213],"type":"Point"}
}