{
  "type": "Feature",
  "properties": {
    "iso:country":"FR",
    "sg:address":"B.P. 117, 69654 Villefranche sur Sa\u00f4ne C\u00e9dex^^1117, Av. Edouard Herriot, 69400 Villefranche sur Sa\u00f4n",
    "sg:orig_category":"Non-Classified Establishments",
    "sg:phone":"+33 4 74 02 97 50",
    "sg:province":"Rhone-Alpes",
    "wof:name":"H\u00f6gan\u00e4s France S.a.",
    "wof:placetype":"venue"
},
  "geometry": {"coordinates":[4.64756,45.957378],"type":"Point"}
}