{
  "type": "Feature",
  "properties": {
    "addr:full":"6, Rte de Nomfray - ZAE du Levray, 74960 Cran Gevrier Rhone-Alpes 74960",
    "addr:housenumber":"6",
    "addr:postcode":"74960;74960",
    "addr:street":"Rte De Nomfray Zae Du Levray;Rhone-Alpes",
    "iso:country":"FR",
    "sg:address":"6, Rte de Nomfray - ZAE du Levray, 74960 Cran Gevrier",
    "sg:orig_category":"Unclassifiable Establishments",
    "sg:phone":"+33 4 50 69 25 00",
    "sg:postcode":"74960",
    "sg:province":"Rhone-Alpes",
    "wof:name":"Druck S.a.",
    "wof:placetype":"venue"
},
  "geometry": {"coordinates":[6.10647,45.907654],"type":"Point"}
}