{
  "type": "Feature",
  "properties": {
    "iso:country":"FR",
    "sg:address":"23 Rue Romain Rolland 92220 Bagneux",
    "sg:classifiers":[
        {
            "category":"Professional",
            "subcategory":"Engineering",
            "type":"Services"
        }
    ],
    "sg:phone":"+33 1 45 36 17 80",
    "sg:postcode":"92220",
    "sg:province":"Ile de France",
    "sg:tags":[
        "machine",
        "-",
        "environment",
        "equipment",
        "machinery",
        "mechanical"
    ],
    "wof:name":"Axeo",
    "wof:placetype":"venue"
},
  "geometry": {"coordinates":[2.32176,48.802288],"type":"Point"}
}