{
  "type": "Feature",
  "properties": {
    "addr:full":"Z.I. Longpr\u00e9 - D 412 Amiens Picardie 80046",
    "addr:housenumber":"412",
    "addr:postcode":"80046",
    "addr:street":"Z.I. Longpre\u0301 D",
    "iso:country":"FR",
    "sg:address":"Z.I. Longpr\u00e9 - D 412",
    "sg:city":"Amiens",
    "sg:orig_category":"Non-Classified Establishments",
    "sg:phone":"+33 3 22 43 05 77",
    "sg:postcode":"80046",
    "sg:province":"Picardie",
    "wof:name":"Smip S.a.r.l.",
    "wof:placetype":"venue"
},
  "geometry": {"coordinates":[2.30253,49.893959],"type":"Point"}
}