{
  "type": "Feature",
  "properties": {
    "iso:country":"FR",
    "sg:address":"Gorge d'Enfer 69930 Saint Laurent de Chamousset",
    "sg:orig_category":"Non-Classified Establishments",
    "sg:phone":"+33 4 74 26 55 31",
    "sg:postcode":"69930",
    "sg:province":"Rhone-Alpes",
    "wof:name":"Debrun Verch\u00e8re Conseils S.a.",
    "wof:placetype":"venue"
},
  "geometry": {"coordinates":[4.472582,45.735565],"type":"Point"}
}