{
  "type": "Feature",
  "properties": {
    "iso:country":"FR",
    "sg:address":"86 ave Pierre Brossolette; Malakoff; 92240",
    "sg:classifiers":[
        {
            "category":"Banks & Credit Unions",
            "subcategory":"Bank",
            "type":"Services"
        }
    ],
    "sg:phone":"+33 16561121",
    "sg:postcode":"92240",
    "sg:province":"Ile de France",
    "wof:name":"Banque Nationale De Paris",
    "wof:placetype":"venue"
},
  "geometry": {"coordinates":[2.308779,48.818485],"type":"Point"}
}