{
  "type": "Feature",
  "properties": {
    "addr:full":"17, Chemin de la Ferme, 69120 Vaulx en Velin Rhone-Alpes 69120",
    "addr:housenumber":"17",
    "addr:postcode":"69120;69120",
    "addr:street":"Chemin De La Ferme",
    "iso:country":"FR",
    "sg:address":"17, Chemin de la Ferme, 69120 Vaulx en Velin",
    "sg:orig_category":"Unclassifiable Establishments",
    "sg:phone":"+33 4 78 79 91 41",
    "sg:postcode":"69120",
    "sg:province":"Rhone-Alpes",
    "wof:name":"Europe Clean Service S.a.r.l.",
    "wof:placetype":"venue"
},
  "geometry": {"coordinates":[4.914937,45.78616],"type":"Point"}
}