{
  "type": "Feature",
  "properties": {
    "addr:full":"20 Avenue Pdt Salvador Allende Zi Mozinor Porte 22 93106 Montreuil Cedex Haute Normandie",
    "addr:housenumber":"20;22",
    "addr:postcode":"93106",
    "addr:street":"Avenue Pdt Salvador Allende Zi Mozinor Porte",
    "iso:country":"FR",
    "sg:address":"20 Avenue Pdt Salvador Allende Zi Mozinor Porte 22 93106 Montreuil Cedex",
    "sg:classifiers":[
        {
            "category":"Professional",
            "subcategory":"Computer Services",
            "type":"Services"
        }
    ],
    "sg:phone":"+33 1 48 57 33 48",
    "sg:province":"Haute Normandie",
    "sg:tags":[
        "information",
        "technology",
        "software"
    ],
    "wof:name":"Fonctionnel Contemporain Nelco (nelco)",
    "wof:placetype":"venue"
},
  "geometry": {"coordinates":[2.442661,48.864525],"type":"Point"}
}