{
  "type": "Feature",
  "properties": {
    "iso:country":"FR",
    "sg:address":"B.P. 9, 51201 Epernay C\u00e9dex^^11, Rue Marcel Paul, 51200 Epernay",
    "sg:orig_category":"Non-Classified Establishments",
    "sg:phone":"+33 3 26 51 03 23",
    "sg:postcode":"51200",
    "sg:province":"Champagne",
    "wof:name":"Etablissements Madphoto S.a.r.l.",
    "wof:placetype":"venue"
},
  "geometry": {"coordinates":[3.95475,49.045197],"type":"Point"}
}