{
  "type": "Feature",
  "properties": {
    "addr:full":"91 Rue D'Ifs 27160 Breteuil Sur Iton Haute Normandie 27160",
    "addr:housenumber":"91",
    "addr:postcode":"27160;27160",
    "addr:street":"Rue D'Ifs;Haute Normandie",
    "iso:country":"FR",
    "sg:address":"91 Rue D'Ifs 27160 Breteuil Sur Iton",
    "sg:classifiers":[
        {
            "category":"Manufacturing",
            "subcategory":"Metals",
            "type":"Manufacturing & Wholesale Goods"
        }
    ],
    "sg:phone":"+33 2 32 29 74 81",
    "sg:postcode":"27160",
    "sg:province":"Haute Normandie",
    "sg:tags":[
        "metallurgy",
        "metalworking",
        "processing"
    ],
    "wof:name":"Merlet Plastiques",
    "wof:placetype":"venue"
},
  "geometry": {"coordinates":[0.920517,48.833229],"type":"Point"}
}