{
  "type": "Feature",
  "properties": {
    "addr:full":"20 r Argoat; Sizun; 29450 Sizun Bretagne 29450",
    "addr:housenumber":"20",
    "addr:postcode":"29450 sizun;29450",
    "addr:street":"R Argoat",
    "iso:country":"FR",
    "sg:address":"20 r Argoat; Sizun; 29450",
    "sg:city":"Sizun",
    "sg:classifiers":[
        {
            "category":"Banks & Credit Unions",
            "subcategory":"Bank",
            "type":"Services"
        }
    ],
    "sg:phone":"+33 2 98 68 81 53",
    "sg:postcode":"29450",
    "sg:province":"Bretagne",
    "wof:name":"Cr\u00e9dit Agricole Mutuel",
    "wof:placetype":"venue"
},
  "geometry": {"coordinates":[-4.075727,48.40593],"type":"Point"}
}