{
  "type": "Feature",
  "properties": {
    "iso:country":"FR",
    "sg:address":"46 Rue La Fayette 75009 Paris",
    "sg:classifiers":[
        {
            "category":"Manufacturing",
            "subcategory":"Jewelry",
            "type":"Manufacturing & Wholesale Goods"
        }
    ],
    "sg:phone":"+33 1 42 46 63 47",
    "sg:postcode":"75009",
    "sg:province":"Ile de France",
    "sg:tags":[
        "product",
        "miscellaneous",
        "jewellery"
    ],
    "wof:name":"Societe Duchene",
    "wof:placetype":"venue"
},
  "geometry": {"coordinates":[2.340271,48.874775],"type":"Point"}
}