{
  "type": "Feature",
  "properties": {
    "addr:full":"B.P. 834, 50108 Cherbourg C\u00e9dex^^Rue de Tourville - Impasse Leveel, 50100 Cherbourg Cherbourg-Octeville Basse Normandie 50100",
    "addr:housenumber":"b.p. 834",
    "addr:postcode":"50108;50100;50100",
    "addr:street":"Impasse Leveel",
    "iso:country":"FR",
    "sg:address":"B.P. 834, 50108 Cherbourg C\u00e9dex^^Rue de Tourville - Impasse Leveel, 50100 Cherbourg",
    "sg:city":"Cherbourg-Octeville",
    "sg:orig_category":"Non-Classified Establishments",
    "sg:phone":"+33 2 33 44 61 63",
    "sg:postcode":"50100",
    "sg:province":"Basse Normandie",
    "wof:name":"James Walker France S.a.s.",
    "wof:placetype":"venue"
},
  "geometry": {"coordinates":[-1.616124,49.640484],"type":"Point"}
}