{
  "type": "Feature",
  "properties": {
    "iso:country":"FR",
    "sg:address":"Rte De Lingolsheim 67118 Geispolsheim",
    "sg:city":"Geispolsheim",
    "sg:classifiers":[
        {
            "category":"Manufacturing",
            "subcategory":"Metals",
            "type":"Manufacturing & Wholesale Goods"
        }
    ],
    "sg:phone":"+33 3 88 76 06 25",
    "sg:postcode":"67400",
    "sg:province":"Alsace",
    "sg:tags":[
        "metallurgy",
        "steel",
        "metalworking"
    ],
    "wof:name":"Ateliers D'alsace Sarl",
    "wof:placetype":"venue"
},
  "geometry": {"coordinates":[7.68461,48.534336],"type":"Point"}
}