{
  "type": "Feature",
  "properties": {
    "addr:full":"13, Bd Joseph Mar\u00e9chal, 35131 Chartres de Bretagne Chartres-de-Bretagne Bretagne 35131",
    "addr:housenumber":"13",
    "addr:postcode":"35131;35131",
    "addr:street":"Bd Joseph Mare\u0301Chal;Bretagne",
    "iso:country":"FR",
    "sg:address":"13, Bd Joseph Mar\u00e9chal, 35131 Chartres de Bretagne",
    "sg:city":"Chartres-de-Bretagne",
    "sg:orig_category":"Unclassifiable Establishments",
    "sg:phone":"+33 2 99 41 21 25",
    "sg:postcode":"35131",
    "sg:province":"Bretagne",
    "wof:name":"S.e.b.t. S.a.",
    "wof:placetype":"venue"
},
  "geometry": {"coordinates":[-1.703968,48.038025],"type":"Point"}
}