{
  "type": "Feature",
  "properties": {
    "addr:full":"Rue Max Planck Lab\u00e8ge Midi Pyr\u00e9n\u00e9es 31670",
    "addr:postcode":"31670",
    "addr:street":"Rue Max Planck",
    "iso:country":"FR",
    "sg:address":"Rue Max Planck",
    "sg:city":"Lab\u00e8ge",
    "sg:orig_category":"Unclassifiable Establishments",
    "sg:phone":"+33 5 61 39 40 41",
    "sg:postcode":"31670",
    "sg:province":"Midi Pyr\u00e9n\u00e9es",
    "wof:name":"Air Liquide",
    "wof:placetype":"venue"
},
  "geometry": {"coordinates":[1.508089,43.553921],"type":"Point"}
}