{
  "type": "Feature",
  "properties": {
    "iso:country":"FR",
    "sg:address":"Route Petit Fossard 77940 Esmans",
    "sg:classifiers":[
        {
            "category":"Food Court",
            "type":"Food & Drink"
        }
    ],
    "sg:phone":"+33 1 64 32 06 53",
    "sg:postcode":"77940",
    "sg:province":"Ile de France",
    "sg:tags":[
        "product",
        "related"
    ],
    "wof:name":"Magnin Sasdelli Erval",
    "wof:placetype":"venue"
},
  "geometry": {"coordinates":[2.956965,48.360794],"type":"Point"}
}