{
  "type": "Feature",
  "properties": {
    "iso:country":"FR",
    "sg:address":"Rue des Armateurs - ZAC de Pr\u00e9tot",
    "sg:city":"Granville",
    "sg:orig_category":"Unclassifiable Establishments",
    "sg:phone":"+33 2 33 91 20 80",
    "sg:postcode":"50400",
    "sg:province":"Basse Normandie",
    "wof:name":"S.m.i. S.a.r.l. - Sud Manche Informatique",
    "wof:placetype":"venue"
},
  "geometry": {"coordinates":[-1.598484,48.838661],"type":"Point"}
}