{
  "type": "Feature",
  "properties": {
    "addr:full":"ZA Aug\u00e9 Poitou-Charentes 79400",
    "addr:postcode":"79400",
    "addr:street":"Za Auge\u0301",
    "iso:country":"FR",
    "sg:address":"ZA",
    "sg:city":"Aug\u00e9",
    "sg:orig_category":"Non-Classified Establishments",
    "sg:phone":"+33 5 49 05 22 84",
    "sg:postcode":"79400",
    "sg:province":"Poitou-Charentes",
    "wof:name":"Scierie Du Val De S\u00e8vre S.a.r.l.",
    "wof:placetype":"venue"
},
  "geometry": {"coordinates":[-0.231596,46.379642],"type":"Point"}
}