{
  "type": "Feature",
  "properties": {
    "addr:full":"B.P. 1, 61350 Saint Mars d'Egrenne C\u00e9dex^^RN 176, 61350 Saint Mars d'Egrenne \u00c9pinay-le-Comte Basse Normandie 61350",
    "addr:housenumber":"1;176",
    "addr:postcode":"61350;61350;61350",
    "addr:street":"B.P.;E\u0301Pinay-Le-Comte Basse",
    "iso:country":"FR",
    "sg:address":"B.P. 1, 61350 Saint Mars d'Egrenne C\u00e9dex^^RN 176, 61350 Saint Mars d'Egrenne",
    "sg:city":"\u00c9pinay-le-Comte",
    "sg:orig_category":"Non-Classified Establishments",
    "sg:phone":"+33 2 33 30 65 30",
    "sg:postcode":"61350",
    "sg:province":"Basse Normandie",
    "wof:name":"Fa.di.class S.a. - Fabrication Et Distribution De Classement",
    "wof:placetype":"venue"
},
  "geometry": {"coordinates":[-0.72666,48.5606],"type":"Point"}
}