{
  "type": "Feature",
  "properties": {
    "addr:full":"Zi St Cezaire 3987 Avenue Kennedy 30900 N\u00eemes Languedoc-Roussillon 30900",
    "addr:housenumber":"3987",
    "addr:postcode":"30900;30900",
    "addr:street":"Zi St Cezaire;Avenue Kennedy",
    "iso:country":"FR",
    "sg:address":"Zi St Cezaire 3987 Avenue Kennedy 30900 N\u00eemes",
    "sg:orig_category":"Metallurgy and Metalworking Wood and Furniture",
    "sg:phone":"+33 4 66 28 81 81",
    "sg:postcode":"30900",
    "sg:province":"Languedoc-Roussillon",
    "wof:name":"Sarl Nimes Materiaux",
    "wof:placetype":"venue"
},
  "geometry": {"coordinates":[4.309396,43.813297],"type":"Point"}
}