{
  "type": "Feature",
  "properties": {
    "addr:full":"12 pl G\u00e9n\u00e9ral de Gaulle; Antibes; 06600 Pays de Loire",
    "addr:housenumber":"12",
    "addr:postcode":"06600",
    "addr:street":"Pl Ge\u0301Ne\u0301Ral De Gaulle",
    "iso:country":"FR",
    "sg:address":"12 pl G\u00e9n\u00e9ral de Gaulle; Antibes; 06600",
    "sg:classifiers":[
        {
            "category":"Banks & Credit Unions",
            "subcategory":"Bank",
            "type":"Services"
        }
    ],
    "sg:phone":"+33 3393339820",
    "sg:province":"Pays de Loire",
    "wof:name":"Banque Populaire, De La C\u00f4te D'azur",
    "wof:placetype":"venue"
},
  "geometry": {"coordinates":[7.120629,43.58075],"type":"Point"}
}