{
  "type": "Feature",
  "properties": {
    "iso:country":"FR",
    "sg:address":"12 pl G\u00e9n\u00e9ral de Gaulle; Antibes; 06600",
    "sg:classifiers":[
        {
            "category":"Banks & Credit Unions",
            "subcategory":"Bank",
            "type":"Services"
        }
    ],
    "sg:phone":"+33 3393339820",
    "sg:province":"Pays de Loire",
    "wof:name":"Banque Populaire, De La C\u00f4te D'azur",
    "wof:placetype":"venue"
},
  "geometry": {"coordinates":[7.120629,43.58075],"type":"Point"}
}