{
  "type": "Feature",
  "properties": {
    "addr:full":"37130 LANGEAIS Langeais Centre 37130",
    "addr:postcode":"37130;37130",
    "iso:country":"FR",
    "sg:address":"37130 LANGEAIS",
    "sg:city":"Langeais",
    "sg:orig_category":"Glass-Fibre Reinforced Plastic Grp Moulds",
    "sg:phone":"+33 2 47 96 22 22",
    "sg:postcode":"37130",
    "sg:province":"Centre",
    "wof:name":"Doryl S.a.",
    "wof:placetype":"venue"
},
  "geometry": {"coordinates":[0.40836,47.324883],"type":"Point"}
}