{
  "type": "Feature",
  "properties": {
    "addr:full":"Route D'Etusson 79150 Argenton Ch\u00e2teau Poitou-Charentes",
    "addr:postcode":"79150",
    "addr:street":"Route D'Etusson",
    "iso:country":"FR",
    "sg:address":"Route D'Etusson 79150 Argenton Ch\u00e2teau",
    "sg:classifiers":[
        {
            "category":"Manufacturing",
            "subcategory":"Rubber & Plastics",
            "type":"Manufacturing & Wholesale Goods"
        }
    ],
    "sg:phone":"+33 5 49 65 71 79",
    "sg:province":"Poitou-Charentes",
    "wof:name":"Sonac",
    "wof:placetype":"venue"
},
  "geometry": {"coordinates":[-0.51475,47.013962],"type":"Point"}
}