{
  "type": "Feature",
  "properties": {
    "addr:full":"1, Rue Joseph Marie Jacquard, 82000 Montauban Midi Pyr\u00e9n\u00e9es",
    "addr:housenumber":"1",
    "addr:postcode":"82000",
    "addr:street":"Rue Joseph Marie Jacquard",
    "iso:country":"FR",
    "sg:address":"1, Rue Joseph Marie Jacquard, 82000 Montauban",
    "sg:orig_category":"Unclassifiable Establishments",
    "sg:phone":"+33 5 63 66 27 33",
    "sg:province":"Midi Pyr\u00e9n\u00e9es",
    "wof:name":"R.p.p. S.a. - R\u00e9my Paul Pr\u00e9contrainte",
    "wof:placetype":"venue"
},
  "geometry": {"coordinates":[1.362537,44.037884],"type":"Point"}
}