{
  "type": "Feature",
  "properties": {
    "iso:country":"FR",
    "sg:address":"10 Rue Vend\u00e9e 49280 St L\u00e9ger Sous Cholet",
    "sg:classifiers":[
        {
            "category":"Shopping",
            "subcategory":"Luggage & Leather Goods",
            "type":"Retail Goods"
        }
    ],
    "sg:phone":"+33 2 41 56 20 30",
    "sg:postcode":"49280",
    "sg:province":"Pays de Loire",
    "sg:tags":[
        "shoe"
    ],
    "wof:name":"Samson (manufacture De Chaussures H ) Sa",
    "wof:placetype":"venue"
},
  "geometry": {"coordinates":[-0.909258,47.090256],"type":"Point"}
}