{
  "type": "Feature",
  "properties": {
    "addr:full":"B.P. 60090, 68262 Kingersheim C\u00e9dex^^15, Rue de l'Industrie, 68260 Kingersheim Kingersheim Alsace 68260",
    "addr:postcode":"68262;68260;68260",
    "addr:street":"Rue De L'Industrie",
    "iso:country":"FR",
    "sg:address":"B.P. 60090, 68262 Kingersheim C\u00e9dex^^15, Rue de l'Industrie, 68260 Kingersheim",
    "sg:city":"Kingersheim",
    "sg:orig_category":"Non-Classified Establishments",
    "sg:phone":"+33 3 89 57 09 57",
    "sg:postcode":"68260",
    "sg:province":"Alsace",
    "wof:name":"Karm Soci\u00e9t\u00e9 D'application Electro-m\u00e9canique Manutention S.a.",
    "wof:placetype":"venue"
},
  "geometry": {"coordinates":[7.312964,47.786972],"type":"Point"}
}