{
  "type": "Feature",
  "properties": {
    "addr:full":"54 Bis, Av Sarah Bernhardt, 51430 Tinqueux Champagne",
    "addr:housenumber":"54 bis",
    "addr:postcode":"51430",
    "addr:street":"Av Sarah Bernhardt",
    "iso:country":"FR",
    "sg:address":"54 Bis, Av Sarah Bernhardt, 51430 Tinqueux",
    "sg:orig_category":"Non-Classified Establishments",
    "sg:phone":"+33 3 26 50 61 61",
    "sg:province":"Champagne",
    "wof:name":"Leviel S.a.",
    "wof:placetype":"venue"
},
  "geometry": {"coordinates":[3.978149,49.249584],"type":"Point"}
}