{
  "type": "Feature",
  "properties": {
    "addr:full":"30 R Descat 59817 Lesqin",
    "addr:housenumber":"30",
    "addr:postcode":"59817",
    "addr:street":"R Descat",
    "iso:country":"FR",
    "sg:address":"30 R Descat 59817 Lesqin",
    "sg:classifiers":[
        {
            "category":"Banks & Credit Unions",
            "subcategory":"Investment Brokerage",
            "type":"Services"
        }
    ],
    "sg:phone":"+33 3 28 55 08 50",
    "sg:tags":[
        "-",
        "transport",
        "related"
    ],
    "wof:name":"Danzas Sa",
    "wof:placetype":"venue"
},
  "geometry": {"coordinates":[3.11104,50.58828],"type":"Point"}
}