{
  "type": "Feature",
  "properties": {
    "iso:country":"FR",
    "sg:address":"2 rue des Fr\u00e8res Moreau 77380 Combs la Ville",
    "sg:classifiers":[
        {
            "category":"Manufacturing",
            "subcategory":"Chemicals & Compounds",
            "type":"Manufacturing & Wholesale Goods"
        }
    ],
    "sg:phone":"+33 820 35 34 40",
    "sg:province":"Ile de France",
    "sg:tags":[
        "preparation",
        "pastry",
        "system"
    ],
    "wof:name":"Matinox D\u00e9cors Sa",
    "wof:placetype":"venue"
},
  "geometry": {"coordinates":[2.54705,48.6661],"type":"Point"}
}