{
  "type": "Feature",
  "properties": {
    "addr:full":"ZI le Coquet Saint Germain des Foss\u00e9s Auvergne 03260",
    "addr:postcode":"03260",
    "addr:street":"Zi",
    "iso:country":"FR",
    "sg:address":"ZI le Coquet",
    "sg:city":"Saint Germain des Foss\u00e9s",
    "sg:orig_category":"Non-Classified Establishments",
    "sg:phone":"+33 4 70 58 42 00",
    "sg:postcode":"03260",
    "sg:province":"Auvergne",
    "wof:name":"B.s.a.d. S.a. - Bourgoin Soci\u00e9t\u00e9 Anonyme Distribution",
    "wof:placetype":"venue"
},
  "geometry": {"coordinates":[3.43254,46.204044],"type":"Point"}
}