{
  "type": "Feature",
  "properties": {
    "addr:full":"B.P. 117, 74410 Saint Jorioz C\u00e9dex^^ZA les Marais, 74410 Saint Jorioz Rhone-Alpes",
    "addr:housenumber":"b.p. 117",
    "addr:postcode":"74410;74410",
    "addr:street":"Ce\u0301Dex^^Za;Marais",
    "iso:country":"FR",
    "sg:address":"B.P. 117, 74410 Saint Jorioz C\u00e9dex^^ZA les Marais, 74410 Saint Jorioz",
    "sg:orig_category":"Non-Classified Establishments",
    "sg:phone":"+33 4 50 68 63 32",
    "sg:province":"Rhone-Alpes",
    "wof:name":"Soradec S.a.",
    "wof:placetype":"venue"
},
  "geometry": {"coordinates":[6.163775,45.833839],"type":"Point"}
}