{
  "type": "Feature",
  "properties": {
    "addr:full":"B.P. 7410, 38074 Saint Quentin Fallavier C\u00e9dex^^5, Place de l'Europe, 38070 Saint Quentin Fallavier Rhone-Alpes",
    "addr:housenumber":"38074",
    "addr:postcode":"38070",
    "addr:street":"B.P. 7410;Ce\u0301Dex^^5 Place De L'Europe",
    "iso:country":"FR",
    "sg:address":"B.P. 7410, 38074 Saint Quentin Fallavier C\u00e9dex^^5, Place de l'Europe, 38070 Saint Quentin Fallavier",
    "sg:orig_category":"Non-Classified Establishments",
    "sg:phone":"+33 4 74 99 00 10",
    "sg:province":"Rhone-Alpes",
    "wof:name":"Swan S.a.r.l.",
    "wof:placetype":"venue"
},
  "geometry": {"coordinates":[5.11285,45.63916],"type":"Point"}
}