{
  "type": "Feature",
  "properties": {
    "addr:full":"B.P. 10237, 60802 Cr\u00e9py en Valois C\u00e9dex^^Rue Saint Eloi, 60800 Cr\u00e9py en Valois Picardie",
    "addr:housenumber":"60802",
    "addr:postcode":"60800",
    "addr:street":"En;Saint Eloi;En;Picardie",
    "iso:country":"FR",
    "sg:address":"B.P. 10237, 60802 Cr\u00e9py en Valois C\u00e9dex^^Rue Saint Eloi, 60800 Cr\u00e9py en Valois",
    "sg:orig_category":"Non-Classified Establishments",
    "sg:phone":"+33 3 44 87 63 38",
    "sg:province":"Picardie",
    "wof:name":"Texidel Nti S.a.",
    "wof:placetype":"venue"
},
  "geometry": {"coordinates":[2.887172,49.235062],"type":"Point"}
}