{
  "type": "Feature",
  "properties": {
    "iso:country":"FR",
    "sg:address":"6 rue Alfred Kastler 67120 Molsheim",
    "sg:city":"Molsheim",
    "sg:classifiers":[
        {
            "category":"Shopping",
            "subcategory":"Pharmacy",
            "type":"Retail Goods"
        }
    ],
    "sg:phone":"+33 3 88 04 82 82",
    "sg:postcode":"67120",
    "sg:province":"Alsace",
    "sg:tags":[
        "preparation",
        "pharmaceutical"
    ],
    "wof:name":"Promochem Sarl",
    "wof:placetype":"venue"
},
  "geometry": {"coordinates":[7.52159,48.535374],"type":"Point"}
}