{
  "type": "Feature",
  "properties": {
    "addr:full":"26210 Moras En Valloire Rhone-Alpes 26210",
    "addr:postcode":"26210;26210",
    "addr:street":"Moras En Valloire Rhone-Alpes",
    "iso:country":"FR",
    "sg:address":"26210 Moras En Valloire",
    "sg:classifiers":[
        {
            "category":"Farming",
            "subcategory":"Crops",
            "type":"Manufacturing & Wholesale Goods"
        }
    ],
    "sg:phone":"+33 4 75 31 90 52",
    "sg:postcode":"26210",
    "sg:province":"Rhone-Alpes",
    "sg:tags":[
        "horticulture",
        "agriculture",
        "grain",
        "livestock",
        "cereal"
    ],
    "wof:name":"La Dauphinoise",
    "wof:placetype":"venue"
},
  "geometry": {"coordinates":[4.99535,45.290676],"type":"Point"}
}