{
  "type": "Feature",
  "properties": {
    "addr:full":"Zal De L'Epinette 62160 Aix Noulette Nord Pas-de-Calais",
    "addr:postcode":"62160",
    "addr:street":"De L'Epinette",
    "iso:country":"FR",
    "sg:address":"Zal De L'Epinette 62160 Aix Noulette",
    "sg:classifiers":[
        {
            "category":"Professional",
            "type":"Services"
        }
    ],
    "sg:phone":"+33 3 21 72 62 20",
    "sg:province":"Nord Pas-de-Calais",
    "sg:tags":[
        "transport",
        "road"
    ],
    "wof:name":"Trans Artois Frigo Sa",
    "wof:placetype":"venue"
},
  "geometry": {"coordinates":[2.695542,50.443085],"type":"Point"}
}