{
  "type": "Feature",
  "properties": {
    "iso:country":"FR",
    "sg:address":"B.P. 32, 67037 Strasbourg C\u00e9dex 2^^11, Rue Jacob Mayer, 67200 Strasbourg",
    "sg:city":"Strasbourg",
    "sg:orig_category":"Non-Classified Establishments",
    "sg:phone":"+33 3 88 28 44 88",
    "sg:postcode":"67200",
    "sg:province":"Alsace",
    "wof:name":"S.a.e.e. S.a. - Soci\u00e9t\u00e9 Auxiliaire D'entreprises De L'est",
    "wof:placetype":"venue"
},
  "geometry": {"coordinates":[7.71425,48.578671],"type":"Point"}
}