{
  "type": "Feature",
  "properties": {
    "addr:full":"12, Impasse de la Roubine, 33140 Villenave d'Ornon Cadaujac Aquitaine 33140",
    "addr:housenumber":"12",
    "addr:postcode":"33140;33140",
    "addr:street":"Impasse De La Roubine",
    "iso:country":"FR",
    "sg:address":"12, Impasse de la Roubine, 33140 Villenave d'Ornon",
    "sg:city":"Cadaujac",
    "sg:orig_category":"Non-Classified Establishments",
    "sg:phone":"+33 5 56 87 61 87",
    "sg:postcode":"33140",
    "sg:province":"Aquitaine",
    "wof:name":"C.a.l. S.a. - Compagnie Atlantique De Location",
    "wof:placetype":"venue"
},
  "geometry": {"coordinates":[-0.54055,44.782646],"type":"Point"}
}