{
  "type": "Feature",
  "properties": {
    "iso:country":"FR",
    "sg:address":"Rte De Brest 29860 Plabennec",
    "sg:city":"Plabennec",
    "sg:classifiers":[
        {
            "category":"Professional",
            "type":"Services"
        }
    ],
    "sg:phone":"+33 2 98 07 83 80",
    "sg:postcode":"29860",
    "sg:province":"Bretagne",
    "sg:tags":[
        "transport",
        "road"
    ],
    "wof:name":"Transports Pailler Sa",
    "wof:placetype":"venue"
},
  "geometry": {"coordinates":[-4.426449,48.502136],"type":"Point"}
}