{
  "type": "Feature",
  "properties": {
    "addr:full":"ZI de Kerprat Guingamp Bretagne 22200",
    "addr:postcode":"22200",
    "addr:street":"Zi De Kerprat Guingamp Bretagne",
    "iso:country":"FR",
    "sg:address":"ZI de Kerprat",
    "sg:city":"Guingamp",
    "sg:orig_category":"Unclassifiable Establishments",
    "sg:phone":"+33 2 96 40 17 00",
    "sg:postcode":"22200",
    "sg:province":"Bretagne",
    "wof:name":"Conserves Stephan S.a.",
    "wof:placetype":"venue"
},
  "geometry": {"coordinates":[-3.149486,48.562763],"type":"Point"}
}