{
  "type": "Feature",
  "properties": {
    "addr:full":"66 Bd De Paris 16100 Cognac Poitou-Charentes 16100",
    "addr:housenumber":"66",
    "addr:postcode":"16100;16100",
    "addr:street":"Bd De Paris",
    "iso:country":"FR",
    "sg:address":"66 Bd De Paris 16100 Cognac",
    "sg:classifiers":[
        {
            "category":"Food Court",
            "type":"Food & Drink"
        }
    ],
    "sg:phone":"+33 5 45 82 05 88",
    "sg:postcode":"16100",
    "sg:province":"Poitou-Charentes",
    "sg:tags":[
        "product",
        "related"
    ],
    "wof:name":"Larsen Le Cognac Des Vikings",
    "wof:placetype":"venue"
},
  "geometry": {"coordinates":[-0.324647,45.686131],"type":"Point"}
}