{
  "type": "Feature",
  "properties": {
    "iso:country":"FR",
    "sg:address":"Lieu Dit Zone Industrielle Rn 7 58320 Pougues Les Eaux",
    "sg:city":"Germigny-sur-Loire",
    "sg:classifiers":[
        {
            "category":"Home & Garden",
            "subcategory":"Furniture",
            "type":"Retail Goods"
        }
    ],
    "sg:phone":"+33 3 86 68 88 55",
    "sg:postcode":"58320",
    "sg:province":"Bourgogne",
    "sg:tags":[
        "household",
        "wood"
    ],
    "wof:name":"Poterie Georges",
    "wof:placetype":"venue"
},
  "geometry": {"coordinates":[3.100895,47.075207],"type":"Point"}
}