{
  "type": "Feature",
  "properties": {
    "addr:full":"Du Sycala Parc D Activites 46230 Fontanes Midi Pyr\u00e9n\u00e9es 46230",
    "addr:postcode":"46230;46230",
    "addr:street":"Activites",
    "iso:country":"FR",
    "sg:address":"Du Sycala Parc D Activites 46230 Fontanes",
    "sg:classifiers":[
        {
            "category":"Professional",
            "subcategory":"Engineering",
            "type":"Services"
        }
    ],
    "sg:phone":"+33 5 65 21 53 53",
    "sg:postcode":"46230",
    "sg:province":"Midi Pyr\u00e9n\u00e9es",
    "sg:tags":[
        "machine",
        "-",
        "environment",
        "equipment",
        "machinery",
        "mechanical"
    ],
    "wof:name":"Etablissements Boussac",
    "wof:placetype":"venue"
},
  "geometry": {"coordinates":[1.480024,44.346172],"type":"Point"}
}