{
  "type": "Feature",
  "properties": {
    "addr:full":"8, Rue Cl\u00e9menceau, 67300 Schiltigheim Schiltigheim Alsace 67300",
    "addr:housenumber":"8",
    "addr:postcode":"67300;67300",
    "addr:street":"Rue Cle\u0301Menceau",
    "iso:country":"FR",
    "sg:address":"8, Rue Cl\u00e9menceau, 67300 Schiltigheim",
    "sg:city":"Schiltigheim",
    "sg:orig_category":"Unclassifiable Establishments",
    "sg:phone":"+33 3 88 33 25 31",
    "sg:postcode":"67300",
    "sg:province":"Alsace",
    "wof:name":"Miroiterie Wehr S.a.",
    "wof:placetype":"venue"
},
  "geometry": {"coordinates":[7.731516,48.612213],"type":"Point"}
}