{
  "type": "Feature",
  "properties": {
    "addr:full":"431 Rue Ambroise Croizat BP 13 38921 Crolles Cedex Crolles Rhone-Alpes 38190",
    "addr:housenumber":"431;bp 13",
    "addr:postcode":"38921;38190",
    "addr:street":"Rue Ambroise Croizat",
    "iso:country":"FR",
    "sg:address":"431 Rue Ambroise Croizat BP 13 38921 Crolles Cedex",
    "sg:city":"Crolles",
    "sg:classifiers":[
        {
            "category":"Manufacturing",
            "subcategory":"Chemicals & Compounds",
            "type":"Manufacturing & Wholesale Goods"
        }
    ],
    "sg:phone":"+33 4 76 08 00 11",
    "sg:postcode":"38190",
    "sg:province":"Rhone-Alpes",
    "sg:tags":[
        "pharmaceutical",
        "chemistry",
        "-",
        "by-product"
    ],
    "wof:name":"Endeo Nalco France Sas",
    "wof:placetype":"venue"
},
  "geometry": {"coordinates":[5.884878,45.2854],"type":"Point"}
}