{
  "type": "Feature",
  "properties": {
    "iso:country":"FR",
    "sg:address":"26, Rue Andr\u00e9 Amp\u00e8re - ZI Vert Galant, 95310 Saint Ouen l'Aum\u00f4ne",
    "sg:orig_category":"Unclassifiable Establishments",
    "sg:phone":"+33 1 34 64 46 29",
    "sg:province":"Ile de France",
    "wof:name":"Lumox S.a.r.l.",
    "wof:placetype":"venue"
},
  "geometry": {"coordinates":[0.044309,48.325356],"type":"Point"}
}