{
  "type": "Feature",
  "properties": {
    "iso:country":"FR",
    "sg:address":"B.P. 80102, 57281 Maizi\u00e8res les Metz C\u00e9dex^^14, Rue de Malambas - ZI du Malambas, 57210 Hauconcourt",
    "sg:orig_category":"Chaudronnerie m\u00e9tallique Chaudronnerie, T\u00f4lerie Constructions m\u00e9talliques Engineering agro-alimentai",
    "sg:phone":"+33 3 87 51 99 99",
    "sg:postcode":"57210",
    "sg:province":"Lorraine",
    "wof:name":"Somedex S.a.r.l. - Soci\u00e9t\u00e9 Mosellane D'etudes Et D'ex\u00e9cution",
    "wof:placetype":"venue"
},
  "geometry": {"coordinates":[6.16027,49.208511],"type":"Point"}
}