{
  "type": "Feature",
  "properties": {
    "addr:full":"211, Av. Francis Tonner, 06150 Cannes la Bocca Provence-Alpes-C\u00f4te d'Azur",
    "addr:postcode":"06150",
    "addr:street":"211 Av. Francis Tonner;Bocca",
    "iso:country":"FR",
    "sg:address":"211, Av. Francis Tonner, 06150 Cannes la Bocca",
    "sg:orig_category":"Unclassifiable Establishments",
    "sg:phone":"+33 4 92 19 49 49",
    "sg:province":"Provence-Alpes-C\u00f4te d'Azur",
    "wof:name":"Ciffres Bona S.a.",
    "wof:placetype":"venue"
},
  "geometry": {"coordinates":[6.963985,43.549789],"type":"Point"}
}