{
  "type": "Feature",
  "properties": {
    "iso:country":"FR",
    "sg:address":"Le Moulin de l'Habit 50640 Savigny Le Vieux",
    "sg:city":"Buais",
    "sg:classifiers":[
        {
            "category":"Wholesale",
            "subcategory":"Fruits & Vegetables",
            "type":"Manufacturing & Wholesale Goods"
        }
    ],
    "sg:phone":"+33 2 33 49 02 06",
    "sg:postcode":"50640",
    "sg:province":"Basse Normandie",
    "sg:tags":[
        "product",
        "cereal"
    ],
    "wof:name":"Jm Pommereul Eurl",
    "wof:placetype":"venue"
},
  "geometry": {"coordinates":[-1.059775,48.515396],"type":"Point"}
}