{
  "type": "Feature",
  "properties": {
    "addr:full":"1 Rue Eug\u00e8ne Freyssinet BP 80238 35133 Javen\u00e9 Javen\u00e9 Bretagne 35133",
    "addr:housenumber":"1",
    "addr:postcode":"35133;35133",
    "addr:street":"Rue Euge\u0300Ne Freyssinet Bp 80238;Javene\u0301",
    "iso:country":"FR",
    "sg:address":"1 Rue Eug\u00e8ne Freyssinet BP 80238 35133 Javen\u00e9",
    "sg:city":"Javen\u00e9",
    "sg:classifiers":[
        {
            "category":"Shopping",
            "subcategory":"Luggage & Leather Goods",
            "type":"Retail Goods"
        }
    ],
    "sg:phone":"+33 2 99 94 82 96",
    "sg:postcode":"35133",
    "sg:province":"Bretagne",
    "sg:tags":[
        "shoe"
    ],
    "wof:name":"Societe Royer Sa",
    "wof:placetype":"venue"
},
  "geometry": {"coordinates":[-1.177224,48.334244],"type":"Point"}
}