{
  "type": "Feature",
  "properties": {
    "addr:full":"4 chemin des Remises 60411 VERBERIE CEDEX Franche Comt\u00e9",
    "addr:housenumber":"4",
    "addr:postcode":"60411",
    "addr:street":"Chemin Des Remises",
    "iso:country":"FR",
    "sg:address":"4 chemin des Remises 60411 VERBERIE CEDEX",
    "sg:classifiers":[
        {
            "category":"Manufacturing",
            "subcategory":"Motor Vehicles & Parts",
            "type":"Manufacturing & Wholesale Goods"
        }
    ],
    "sg:phone":"+33 3 44 40 54 84",
    "sg:province":"Franche Comt\u00e9",
    "sg:tags":[
        "precision",
        "mechanic"
    ],
    "wof:name":"Erode Sa",
    "wof:placetype":"venue"
},
  "geometry": {"coordinates":[-87.599716,41.51379],"type":"Point"}
}