{
  "type": "Feature",
  "properties": {
    "addr:full":"350, Rue Jean Laville, 71410 Sanvignes les Mines Sanvignes-les-Mines Bourgogne 71410",
    "addr:housenumber":"350",
    "addr:postcode":"71410;71410",
    "addr:street":"Rue Jean Laville;Sanvignes Les;Bourgogne",
    "iso:country":"FR",
    "sg:address":"350, Rue Jean Laville, 71410 Sanvignes les Mines",
    "sg:city":"Sanvignes-les-Mines",
    "sg:orig_category":"Unclassifiable Establishments",
    "sg:phone":"+33 3 85 67 05 10",
    "sg:postcode":"71410",
    "sg:province":"Bourgogne",
    "wof:name":"Caoutchouc Roudot S.a.",
    "wof:placetype":"venue"
},
  "geometry": {"coordinates":[4.288975,46.661499],"type":"Point"}
}