{
  "type": "Feature",
  "properties": {
    "iso:country":"FR",
    "sg:address":"B.P. 2238, 22022 Saint Brieuc C\u00e9dex 1^^69, Rue Chaptal, 22000 Saint Brieuc",
    "sg:city":"Saint-Brieuc",
    "sg:orig_category":"Non-Classified Establishments",
    "sg:phone":"+33 2 96 33 57 64",
    "sg:postcode":"22000",
    "sg:province":"Bretagne",
    "wof:name":"Armor Ing\u00e9nierie S.a.r.l.",
    "wof:placetype":"venue"
},
  "geometry": {"coordinates":[-2.763814,48.515701],"type":"Point"}
}