{
  "type": "Feature",
  "properties": {
    "iso:country":"FR",
    "sg:address":"B.P. 1443, 26014 Valence C\u00e9dex^^230, Av. des Aur\u00e9ats, 26000 Valence",
    "sg:orig_category":"Non-Classified Establishments",
    "sg:phone":"+33 4 75 81 32 00",
    "sg:postcode":"26000",
    "sg:province":"Rhone-Alpes",
    "wof:name":"Charpail S.a.",
    "wof:placetype":"venue"
},
  "geometry": {"coordinates":[4.889246,44.930458],"type":"Point"}
}