{
  "type": "Feature",
  "properties": {
    "addr:full":"19200 Ussel Limousin",
    "addr:postcode":"19200",
    "iso:country":"FR",
    "sg:address":"19200 Ussel",
    "sg:orig_category":"Non-Classified Establishments",
    "sg:phone":"+33 5 55 46 37 00",
    "sg:province":"Limousin",
    "wof:name":"Polyrey S.a.s.",
    "wof:placetype":"venue"
},
  "geometry": {"coordinates":[2.35138,45.54501],"type":"Point"}
}