{
  "type": "Feature",
  "properties": {
    "addr:full":"9 rue Royal; Annecy; 74000 Rhone-Alpes 74000",
    "addr:housenumber":"9",
    "addr:postcode":"74000;74000",
    "addr:street":"Rue Royal",
    "iso:country":"FR",
    "sg:address":"9 rue Royal; Annecy; 74000",
    "sg:classifiers":[
        {
            "category":"Banks & Credit Unions",
            "subcategory":"Bank",
            "type":"Services"
        }
    ],
    "sg:phone":"+33 3350458264",
    "sg:postcode":"74000",
    "sg:province":"Rhone-Alpes",
    "wof:name":"Soci\u00e9t\u00e9 G\u00e9n\u00e9rale",
    "wof:placetype":"venue"
},
  "geometry": {"coordinates":[6.124383,45.900169],"type":"Point"}
}