{
  "type": "Feature",
  "properties": {
    "iso:country":"FR",
    "sg:address":"17, Chemin de Salvetat - ZI en Jacca, 31770 Colomiers",
    "sg:orig_category":"Unclassifiable Establishments",
    "sg:phone":"+33 5 34 55 03 63",
    "sg:province":"Midi Pyr\u00e9n\u00e9es",
    "wof:name":"S.e.r.m.i. S.a.s. - Soci\u00e9t\u00e9 D'etudes Et De R\u00e9alisations M\u00e9caniques Industrielles",
    "wof:placetype":"venue"
},
  "geometry": {"coordinates":[1.33337,43.612431],"type":"Point"}
}