{
  "type": "Feature",
  "properties": {
    "addr:full":"Rue Henni Gourdier Riom Auvergne 63200",
    "addr:postcode":"63200",
    "addr:street":"Rue Henni Gourdier",
    "iso:country":"FR",
    "sg:address":"Rue Henni Gourdier",
    "sg:city":"Riom",
    "sg:orig_category":"Non-Classified Establishments",
    "sg:phone":"+33 4 73 33 49 70",
    "sg:postcode":"63200",
    "sg:province":"Auvergne",
    "wof:name":"Riom Laboratoires Cerm S.a.",
    "wof:placetype":"venue"
},
  "geometry": {"coordinates":[3.123231,45.883553],"type":"Point"}
}