{
  "type": "Feature",
  "properties": {
    "iso:country":"FR",
    "sg:address":"37 Rte St Genis 17500 St Germain De Lusignan",
    "sg:classifiers":[
        {
            "category":"Manufacturing",
            "subcategory":"Printing",
            "type":"Manufacturing & Wholesale Goods"
        }
    ],
    "sg:phone":"+33 5 46 48 31 44",
    "sg:province":"Poitou-Charentes",
    "sg:tags":[
        "publishing"
    ],
    "wof:name":"Luchard Decalcolux Sa",
    "wof:placetype":"venue"
},
  "geometry": {"coordinates":[-0.45334,45.409687],"type":"Point"}
}