{
  "type": "Feature",
  "properties": {
    "addr:full":"ZAC du Muckental Barr Alsace 67140",
    "addr:postcode":"67140",
    "addr:street":"Zac Du Muckental Barr",
    "iso:country":"FR",
    "sg:address":"ZAC du Muckental",
    "sg:city":"Barr",
    "sg:orig_category":"Unclassifiable Establishments",
    "sg:phone":"+33 3 88 58 53 63",
    "sg:postcode":"67140",
    "sg:province":"Alsace",
    "wof:name":"Echamat S.a.r.l.",
    "wof:placetype":"venue"
},
  "geometry": {"coordinates":[7.458762,48.402248],"type":"Point"}
}