{
  "type": "Feature",
  "properties": {
    "addr:full":"4 rue Louis de Broglie 77400 ST THIBAULT DES VIGNES Ile de France",
    "addr:housenumber":"4",
    "addr:postcode":"77400;ile",
    "addr:street":"Rue Louis De Broglie",
    "iso:country":"FR",
    "sg:address":"4 rue Louis de Broglie 77400 ST THIBAULT DES VIGNES",
    "sg:classifiers":[
        {
            "category":"Professional",
            "subcategory":"Engineering",
            "type":"Services"
        }
    ],
    "sg:phone":"+33 1 64 12 49 00",
    "sg:province":"Ile de France",
    "sg:tags":[
        "surface"
    ],
    "wof:name":"Balzers Revetements Sous Vide France Sa",
    "wof:placetype":"venue"
},
  "geometry": {"coordinates":[2.672396,48.863281],"type":"Point"}
}