{
  "type": "Feature",
  "properties": {
    "addr:full":"Zi Oulrich 66400 C\u00e9ret Languedoc-Roussillon",
    "addr:postcode":"66400",
    "iso:country":"FR",
    "sg:address":"Zi Oulrich 66400 C\u00e9ret",
    "sg:classifiers":[
        {
            "category":"Manufacturing",
            "subcategory":"Wood Products",
            "type":"Manufacturing & Wholesale Goods"
        }
    ],
    "sg:phone":"+33 4 68 87 20 20",
    "sg:province":"Languedoc-Roussillon",
    "sg:tags":[
        "furniture"
    ],
    "wof:name":"Sabate Sas",
    "wof:placetype":"venue"
},
  "geometry": {"coordinates":[2.74927,42.485386],"type":"Point"}
}