{
  "type": "Feature",
  "properties": {
    "iso:country":"FR",
    "sg:address":"Imp Des Broderies 78310 Coigni\u00e8res",
    "sg:classifiers":[
        {
            "category":"Manufacturing",
            "subcategory":"Metals",
            "type":"Manufacturing & Wholesale Goods"
        }
    ],
    "sg:phone":"+33 1 30 49 43 50",
    "sg:postcode":"78310",
    "sg:province":"Ile de France",
    "sg:tags":[
        "metallurgy",
        "steel",
        "metalworking"
    ],
    "wof:name":"France Thermique Sarl",
    "wof:placetype":"venue"
},
  "geometry": {"coordinates":[1.91462,48.740437],"type":"Point"}
}