{
  "type": "Feature",
  "properties": {
    "iso:country":"FR",
    "sg:address":"9, Rue des Gen\u00eats, 33450 Saint Loub\u00e8s",
    "sg:city":"Saint-Loub\u00e8s",
    "sg:orig_category":"Unclassifiable Establishments",
    "sg:phone":"+33 5 57 77 31 40",
    "sg:postcode":"33450",
    "sg:province":"Aquitaine",
    "wof:name":"Transports Vaquier S.a.",
    "wof:placetype":"venue"
},
  "geometry": {"coordinates":[-0.454762,44.92012],"type":"Point"}
}