{
  "type": "Feature",
  "properties": {
    "iso:country":"FR",
    "sg:address":"Ld Les Eaux 69210 Bully",
    "sg:classifiers":[
        {
            "category":"Professional",
            "subcategory":"Advertising",
            "type":"Services"
        }
    ],
    "sg:phone":"+33 4 72 56 04 04",
    "sg:postcode":"69210",
    "sg:province":"Rhone-Alpes",
    "sg:tags":[
        "marketing",
        "medium",
        "communication"
    ],
    "wof:name":"Ragtime Tmd",
    "wof:placetype":"venue"
},
  "geometry": {"coordinates":[4.606841,45.7701],"type":"Point"}
}