{
  "type": "Feature",
  "properties": {
    "addr:full":"7 Quai De Rotterdam 68315 Illzach Cedex Rott Alsace 67160",
    "addr:housenumber":"7",
    "addr:postcode":"68315;67160",
    "addr:street":"Quai De Rotterdam",
    "iso:country":"FR",
    "sg:address":"7 Quai De Rotterdam 68315 Illzach Cedex",
    "sg:city":"Rott",
    "sg:classifiers":[
        {
            "category":"Professional",
            "subcategory":"Business Services",
            "type":"Services"
        }
    ],
    "sg:phone":"+33 3 89 63 32 00",
    "sg:postcode":"67160",
    "sg:province":"Alsace",
    "sg:tags":[
        "travel",
        "-",
        "transport",
        "road",
        "air"
    ],
    "wof:name":"Danzas Sa",
    "wof:placetype":"venue"
},
  "geometry": {"coordinates":[7.379068,47.764328],"type":"Point"}
}