{
  "type": "Feature",
  "properties": {
    "addr:full":"ZA Freneuse Ile de France 78840",
    "addr:postcode":"78840",
    "addr:street":"Za Freneuse Ile De France",
    "iso:country":"FR",
    "sg:address":"ZA",
    "sg:city":"Freneuse",
    "sg:orig_category":"Unclassifiable Establishments",
    "sg:phone":"+33 1 30 93 22 32",
    "sg:postcode":"78840",
    "sg:province":"Ile de France",
    "wof:name":"I.m.p.h. S.a.",
    "wof:placetype":"venue"
},
  "geometry": {"coordinates":[1.600769,49.048203],"type":"Point"}
}