{
  "type": "Feature",
  "properties": {
    "addr:full":"10, Av. Pierre Cot, 87350 Panazol Limousin",
    "addr:postcode":"87350",
    "addr:street":"10 Av. Pierre Cot",
    "iso:country":"FR",
    "sg:address":"10, Av. Pierre Cot, 87350 Panazol",
    "sg:orig_category":"Unclassifiable Establishments",
    "sg:phone":"+33 5 55 30 04 84",
    "sg:province":"Limousin",
    "wof:name":"R.m.j. Distribution S.a.r.l.",
    "wof:placetype":"venue"
},
  "geometry": {"coordinates":[1.301242,45.829395],"type":"Point"}
}