{
  "type": "Feature",
  "properties": {
    "addr:full":"Le Vigny 71700 Lacrost Lacrost Bourgogne 71700",
    "addr:postcode":"71700;71700",
    "iso:country":"FR",
    "sg:address":"Le Vigny 71700 Lacrost",
    "sg:city":"Lacrost",
    "sg:orig_category":"Unclassifiable Establishments",
    "sg:phone":"+33 3 85 32 27 00",
    "sg:postcode":"71700",
    "sg:province":"Bourgogne",
    "wof:name":"S.g.o.l. S.a. - Soci\u00e9t\u00e9 G\u00e9n\u00e9rale D'outillage De Lacrost",
    "wof:placetype":"venue"
},
  "geometry": {"coordinates":[4.93188,46.556744],"type":"Point"}
}