{
  "type": "Feature",
  "properties": {
    "addr:full":"ZI Mulhouse Rhin Est Hombourg Alsace 68490",
    "addr:postcode":"68490",
    "addr:street":"Zi;Rhin",
    "iso:country":"FR",
    "sg:address":"ZI Mulhouse Rhin Est",
    "sg:city":"Hombourg",
    "sg:orig_category":"Non-Classified Establishments",
    "sg:phone":"+33 3 89 83 30 30",
    "sg:postcode":"68490",
    "sg:province":"Alsace",
    "wof:name":"Grieshaber France S.a.r.l.",
    "wof:placetype":"venue"
},
  "geometry": {"coordinates":[7.50503,47.759079],"type":"Point"}
}