{
  "type": "Feature",
  "properties": {
    "iso:country":"FR",
    "sg:address":"B.P. 1117",
    "sg:city":"Montlu\u00e7on",
    "sg:orig_category":"Non-Classified Establishments",
    "sg:phone":"+33 4 70 06 22 22",
    "sg:postcode":"03100",
    "sg:province":"Auvergne",
    "wof:name":"Typocentre S.a.",
    "wof:placetype":"venue"
},
  "geometry": {"coordinates":[2.602068,46.338787],"type":"Point"}
}