{
  "type": "Feature",
  "properties": {
    "iso:country":"FR",
    "sg:address":"12, Rue du Bois Chaland - Lisses , 91029 Evry C\u00e9dex",
    "sg:orig_category":"Non-Classified Establishments",
    "sg:phone":"+33 1 64 97 66 41",
    "sg:province":"Midi Pyr\u00e9n\u00e9es",
    "wof:name":"Aveb\u00e9 France S.a.",
    "wof:placetype":"venue"
},
  "geometry": {"coordinates":[2.43072,48.626919],"type":"Point"}
}