{
  "type": "Feature",
  "properties": {
    "addr:full":"50, Rue Capitaine Maillard, 57220 Boulay Moselle Lorraine",
    "addr:housenumber":"50",
    "addr:postcode":"57220",
    "addr:street":"Rue Capitaine Maillard",
    "iso:country":"FR",
    "sg:address":"50, Rue Capitaine Maillard, 57220 Boulay Moselle",
    "sg:orig_category":"Non-Classified Establishments",
    "sg:phone":"+33 3 87 79 20 22",
    "sg:province":"Lorraine",
    "wof:name":"Soci\u00e9t\u00e9 Industrielle De Boulay S.a.",
    "wof:placetype":"venue"
},
  "geometry": {"coordinates":[6.487908,49.180893],"type":"Point"}
}