{
  "type": "Feature",
  "properties": {
    "iso:country":"FR",
    "sg:address":"4, Rue de la Scierie, 67250 Surbourg",
    "sg:city":"Surbourg",
    "sg:orig_category":"Non-Classified Establishments",
    "sg:phone":"+33 3 88 80 66 43",
    "sg:postcode":"67250",
    "sg:province":"Alsace",
    "wof:name":"R.i.m.e.c.o. S.a.r.l.",
    "wof:placetype":"venue"
},
  "geometry": {"coordinates":[7.843419,48.904819],"type":"Point"}
}