{
  "type": "Feature",
  "properties": {
    "addr:full":"B.P. 16, 28312 Janville C\u00e9dex^^Rue Pierre et Marie Curie - ZI, 28310 Janville Janville Centre 28310",
    "addr:postcode":"28312;28310;28310",
    "addr:street":"B.P. 16;Et Marie Curie Zi",
    "iso:country":"FR",
    "sg:address":"B.P. 16, 28312 Janville C\u00e9dex^^Rue Pierre et Marie Curie - ZI, 28310 Janville",
    "sg:city":"Janville",
    "sg:orig_category":"Non-Classified Establishments",
    "sg:phone":"+33 2 37 90 00 17",
    "sg:postcode":"28310",
    "sg:province":"Centre",
    "wof:name":"Bennes Maupu S.a.",
    "wof:placetype":"venue"
},
  "geometry": {"coordinates":[1.93755,48.19762],"type":"Point"}
}