{
  "type": "Feature",
  "properties": {
    "iso:country":"FR",
    "sg:address":"route de la Perri\u00e8re 49400 Chace",
    "sg:classifiers":[
        {
            "category":"Food & Beverages",
            "subcategory":"Fruits & Vegetables",
            "type":"Retail Goods"
        }
    ],
    "sg:phone":"+33 2 41 53 54 00",
    "sg:postcode":"49400",
    "sg:province":"Pays de Loire",
    "sg:tags":[
        "dried"
    ],
    "wof:name":"S.p.a.b. Sa",
    "wof:placetype":"venue"
},
  "geometry": {"coordinates":[-0.068133,47.210464],"type":"Point"}
}