{
  "type": "Feature",
  "properties": {
    "addr:full":"ZI de Chac\u00e9 Saumur Pays de Loire 49400",
    "addr:postcode":"49400",
    "addr:street":"Zi De Chace\u0301 Saumur Pays",
    "iso:country":"FR",
    "sg:address":"ZI de Chac\u00e9",
    "sg:city":"Saumur",
    "sg:orig_category":"Unclassifiable Establishments",
    "sg:phone":"+33 2 41 52 49 62",
    "sg:postcode":"49400",
    "sg:province":"Pays de Loire",
    "wof:name":"Electropoli Production S.a.",
    "wof:placetype":"venue"
},
  "geometry": {"coordinates":[-0.079319,47.259766],"type":"Point"}
}