{
  "type": "Feature",
  "properties": {
    "addr:full":"La Suissi\u00e8re 41250 Neuvy Neuvy Centre 41250",
    "addr:housenumber":"neuvy",
    "addr:postcode":"41250;41250",
    "iso:country":"FR",
    "sg:address":"La Suissi\u00e8re 41250 Neuvy",
    "sg:city":"Neuvy",
    "sg:orig_category":"Unclassifiable Establishments",
    "sg:phone":"+33 2 54 46 42 63",
    "sg:postcode":"41250",
    "sg:province":"Centre",
    "wof:name":"Industrie Du Bois De Neuvy S.a.r.l.",
    "wof:placetype":"venue"
},
  "geometry": {"coordinates":[1.593555,47.566158],"type":"Point"}
}