{
  "type": "Feature",
  "properties": {
    "addr:full":"117 Traverse Bovis 13016 Marseille Poitou-Charentes",
    "addr:housenumber":"117",
    "addr:postcode":"13016",
    "addr:street":"Traverse Bovis",
    "iso:country":"FR",
    "sg:address":"117 Traverse Bovis 13016 Marseille",
    "sg:classifiers":[
        {
            "category":"Manufacturing",
            "subcategory":"Metals",
            "type":"Manufacturing & Wholesale Goods"
        }
    ],
    "sg:phone":"+33 4 91 46 33 31",
    "sg:province":"Poitou-Charentes",
    "sg:tags":[
        "metallurgy",
        "metalworking",
        "processing"
    ],
    "wof:name":"Red Petit Jean",
    "wof:placetype":"venue"
},
  "geometry": {"coordinates":[5.3217,43.364235],"type":"Point"}
}