{
  "type": "Feature",
  "properties": {
    "addr:full":"Chem De Leyran Chazot 33140 Villenave D'Ornon Cadaujac Aquitaine 33140",
    "addr:postcode":"33140;33140",
    "addr:street":"Chem",
    "iso:country":"FR",
    "sg:address":"Chem De Leyran Chazot 33140 Villenave D'Ornon",
    "sg:city":"Cadaujac",
    "sg:classifiers":[
        {
            "category":"Manufacturing",
            "subcategory":"Metals",
            "type":"Manufacturing & Wholesale Goods"
        }
    ],
    "sg:phone":"+33 5 57 96 17 00",
    "sg:postcode":"33140",
    "sg:province":"Aquitaine",
    "sg:tags":[
        "metallurgy",
        "steel",
        "metalworking"
    ],
    "wof:name":"Trefimetaux",
    "wof:placetype":"venue"
},
  "geometry": {"coordinates":[-0.54499,44.7644],"type":"Point"}
}