{
  "type": "Feature",
  "properties": {
    "addr:full":"2, Rue de l'Industrie, 67730 Ch\u00e2tenois Ch\u00e2tenois Alsace 67730",
    "addr:housenumber":"2",
    "addr:postcode":"67730;67730",
    "addr:street":"Rue De L'Industrie",
    "iso:country":"FR",
    "sg:address":"2, Rue de l'Industrie, 67730 Ch\u00e2tenois",
    "sg:city":"Ch\u00e2tenois",
    "sg:orig_category":"Non-Classified Establishments",
    "sg:phone":"+33 3 88 85 05 40",
    "sg:postcode":"67730",
    "sg:province":"Alsace",
    "wof:name":"Jip\u00e9 S.a.",
    "wof:placetype":"venue"
},
  "geometry": {"coordinates":[7.400547,48.276794],"type":"Point"}
}