{
  "type": "Feature",
  "properties": {
    "addr:full":"43 Rue Des Renouill\u00e8res 93285 St Denis Cedex Centre",
    "addr:housenumber":"43",
    "addr:postcode":"93285;denis",
    "addr:street":"Rue Des Renouille\u0300Res",
    "iso:country":"FR",
    "sg:address":"43 Rue Des Renouill\u00e8res 93285 St Denis Cedex",
    "sg:classifiers":[
        {
            "category":"Professional",
            "subcategory":"Advertising",
            "type":"Services"
        }
    ],
    "sg:phone":"+33 1 48 13 13 50",
    "sg:province":"Centre",
    "sg:tags":[
        "information",
        "medium",
        "communication"
    ],
    "wof:name":"Dauphin Groupe Clearchannel",
    "wof:placetype":"venue"
},
  "geometry": {"coordinates":[2.342507,48.916161],"type":"Point"}
}