{
  "type": "Feature",
  "properties": {
    "iso:country":"FR",
    "sg:address":"27, Rue du Bailly, 21000 Dijon",
    "sg:city":"Dijon",
    "sg:orig_category":"Unclassifiable Establishments",
    "sg:phone":"+33 3 80 72 45 37",
    "sg:postcode":"21000",
    "sg:province":"Bourgogne",
    "wof:name":"Desertot S.a.",
    "wof:placetype":"venue"
},
  "geometry": {"coordinates":[5.079916,47.350334],"type":"Point"}
}