{
  "type": "Feature",
  "properties": {
    "iso:country":"FR",
    "sg:address":"Za De La Plaine 87220 Boisseuil",
    "sg:classifiers":[
        {
            "category":"Utilities",
            "subcategory":"Telephone",
            "type":"Services"
        }
    ],
    "sg:phone":"+33 5 55 30 70 03",
    "sg:province":"Limousin",
    "sg:tags":[
        "telecommunication"
    ],
    "wof:name":"Limoges Enseignes Sa",
    "wof:placetype":"venue"
},
  "geometry": {"coordinates":[1.33109,45.769951],"type":"Point"}
}