{
  "type": "Feature",
  "properties": {
    "addr:full":"La Motte Des Justices Zi 79100 Thouars Poitou-Charentes",
    "addr:postcode":"79100",
    "addr:street":"La Motte Des Justices Zi",
    "iso:country":"FR",
    "sg:address":"La Motte Des Justices Zi 79100 Thouars",
    "sg:classifiers":[
        {
            "category":"Manufacturing",
            "subcategory":"Rubber & Plastics",
            "type":"Manufacturing & Wholesale Goods"
        }
    ],
    "sg:phone":"+33 5 49 66 68 56",
    "sg:province":"Poitou-Charentes",
    "sg:tags":[
        "packaging",
        "material",
        "-"
    ],
    "wof:name":"Plastifor",
    "wof:placetype":"venue"
},
  "geometry": {"coordinates":[-0.195199,46.988804],"type":"Point"}
}