{
  "type": "Feature",
  "properties": {
    "addr:full":"18/20, Av. Louis Bl\u00e9riot, 91320 Wissous Ile de France",
    "addr:housenumber":"18 / 20",
    "addr:postcode":"91320;ile",
    "addr:street":"Av. Louis Ble\u0301Riot",
    "iso:country":"FR",
    "sg:address":"18/20, Av. Louis Bl\u00e9riot, 91320 Wissous",
    "sg:orig_category":"Unclassifiable Establishments",
    "sg:phone":"+33 1 49 75 86 00",
    "sg:province":"Ile de France",
    "wof:name":"Dimension Data S.a.",
    "wof:placetype":"venue"
},
  "geometry": {"coordinates":[2.32612,48.731461],"type":"Point"}
}