{
  "type": "Feature",
  "properties": {
    "iso:country":"FR",
    "sg:address":"Rue de la C\u00f4te",
    "sg:city":"Gigny",
    "sg:orig_category":"Non-Classified Establishments",
    "sg:phone":"+33 3 84 85 41 83",
    "sg:postcode":"39320",
    "sg:province":"Franche Comt\u00e9",
    "wof:name":"Grand Ren\u00e9",
    "wof:placetype":"venue"
},
  "geometry": {"coordinates":[5.452781,46.393513],"type":"Point"}
}