{
  "type": "Feature",
  "properties": {
    "addr:full":"9, Place des Fines Herbes, 67210 Obernai Obernai Alsace 67210",
    "addr:housenumber":"9",
    "addr:postcode":"67210;67210",
    "addr:street":"Place Des Fines Herbes",
    "iso:country":"FR",
    "sg:address":"9, Place des Fines Herbes, 67210 Obernai",
    "sg:city":"Obernai",
    "sg:orig_category":"Non-Classified Establishments",
    "sg:phone":"+33 3 88 47 61 61",
    "sg:postcode":"67210",
    "sg:province":"Alsace",
    "wof:name":"Net Service S.a.r.l.",
    "wof:placetype":"venue"
},
  "geometry": {"coordinates":[7.482405,48.461029],"type":"Point"}
}