{
  "type": "Feature",
  "properties": {
    "iso:country":"FR",
    "sg:address":"15, Rue Henri le Ch\u00e2tellier, 66100 Perpignan",
    "sg:orig_category":"Unclassifiable Establishments",
    "sg:phone":"+33 4 68 67 47 20",
    "sg:province":"Languedoc-Roussillon",
    "wof:name":"Cogetec S.a.r.l.",
    "wof:placetype":"venue"
},
  "geometry": {"coordinates":[2.903923,42.690758],"type":"Point"}
}