{
  "type": "Feature",
  "properties": {
    "iso:country":"FR",
    "sg:address":"6, Rue de Haie Pellerine - La Colline , 89100 Villeroy",
    "sg:city":"Villeroy",
    "sg:orig_category":"Non-Classified Establishments",
    "sg:phone":"+33 3 86 88 84 68",
    "sg:postcode":"89100",
    "sg:province":"Bourgogne",
    "wof:name":"Repe Environnement S.a.r.l.",
    "wof:placetype":"venue"
},
  "geometry": {"coordinates":[3.3115,48.150352],"type":"Point"}
}