{
  "type": "Feature",
  "properties": {
    "addr:full":"1 bis, Rue Watterlos, 59115 Leers Nord Pas-de-Calais",
    "addr:housenumber":"1 bis",
    "addr:postcode":"59115",
    "addr:street":"Rue Watterlos",
    "iso:country":"FR",
    "sg:address":"1 bis, Rue Watterlos, 59115 Leers",
    "sg:orig_category":"Non-Classified Establishments",
    "sg:phone":"+33 3 28 33 97 28",
    "sg:province":"Nord Pas-de-Calais",
    "wof:name":"N.m.g.c. S.a.r.l. - Nord Maintenance G\u00e9nie Climatique",
    "wof:placetype":"venue"
},
  "geometry": {"coordinates":[3.244384,50.682144],"type":"Point"}
}