{
  "type": "Feature",
  "properties": {
    "iso:country":"FR",
    "sg:address":"93174 Bagnolet C\u00e9dex^^78, Av. Charles de Gaulle, 93170 Bagnolet",
    "sg:orig_category":"Non-Classified Establishments",
    "sg:phone":"+33 1 49 72 51 00",
    "sg:province":"Ile de France",
    "wof:name":"Nfo Infratest S.a.r.l.",
    "wof:placetype":"venue"
},
  "geometry": {"coordinates":[2.41767,48.868626],"type":"Point"}
}