{
  "type": "Feature",
  "properties": {
    "addr:full":"Rue Denis Papin - ZI d'Arvigny Moissy Cramayel Ile de France 77550",
    "addr:postcode":"77550",
    "addr:street":"Rue Denis Papin Zi D'Arvigny",
    "iso:country":"FR",
    "sg:address":"Rue Denis Papin - ZI d'Arvigny",
    "sg:city":"Moissy Cramayel",
    "sg:orig_category":"Unclassifiable Establishments",
    "sg:phone":"+33 1 64 13 59 42",
    "sg:postcode":"77550",
    "sg:province":"Ile de France",
    "wof:name":"Gefco S.a.",
    "wof:placetype":"venue"
},
  "geometry": {"coordinates":[2.587582,48.611679],"type":"Point"}
}