{
  "type": "Feature",
  "properties": {
    "iso:country":"FR",
    "sg:address":"34 Rue Fontaine 75009 Paris",
    "sg:classifiers":[
        {
            "category":"Travel",
            "subcategory":"Hotels & Motels",
            "type":"Entertainment"
        }
    ],
    "sg:phone":"+33 1 44 63 54 95",
    "sg:postcode":"75009",
    "sg:province":"Ile de France",
    "sg:tags":[
        "hotels",
        "business",
        "restaurant"
    ],
    "wof:name":"Hotel Blanche Fontaine",
    "wof:placetype":"venue"
},
  "geometry": {"coordinates":[2.333503,48.88271],"type":"Point"}
}