{
  "type": "Feature",
  "properties": {
    "iso:country":"FR",
    "sg:address":"A6 Aire De La Chaponne 89420 Sceaux",
    "sg:city":"Sceaux",
    "sg:classifiers":[
        {
            "category":"Travel",
            "subcategory":"Hotels & Motels",
            "type":"Entertainment"
        }
    ],
    "sg:phone":"+33 3 86 32 10 80",
    "sg:postcode":"89420",
    "sg:province":"Bourgogne",
    "sg:tags":[
        "hotels",
        "business",
        "restaurant"
    ],
    "wof:name":"Autogrill Cote France Sa",
    "wof:placetype":"venue"
},
  "geometry": {"coordinates":[4.091625,47.512066],"type":"Point"}
}