{
  "type": "Feature",
  "properties": {
    "addr:full":"B.P. 389, 85303 Challans C\u00e9dex^^2, Rue Saint Fran\u00e7ois, 85300 Challans Pays de Loire 85300",
    "addr:housenumber":"b.p. 389",
    "addr:postcode":"85303;85300;85300",
    "addr:street":"Rue Saint Franc\u0327Ois",
    "iso:country":"FR",
    "sg:address":"B.P. 389, 85303 Challans C\u00e9dex^^2, Rue Saint Fran\u00e7ois, 85300 Challans",
    "sg:orig_category":"Non-Classified Establishments",
    "sg:phone":"+33 2 51 93 11 85",
    "sg:postcode":"85300",
    "sg:province":"Pays de Loire",
    "wof:name":"Briton Et Claude Architecture S.a.r.l.",
    "wof:placetype":"venue"
},
  "geometry": {"coordinates":[-1.879324,46.845879],"type":"Point"}
}