{
  "type": "Feature",
  "properties": {
    "addr:full":"1 Boulevard Jean Jaures 54000 Nancy Lorraine 54000",
    "addr:housenumber":"1",
    "addr:postcode":"54000;54000",
    "addr:street":"Boulevard Jean Jaures",
    "iso:country":"FR",
    "sg:address":"1 Boulevard Jean Jaures 54000 Nancy",
    "sg:classifiers":[
        {
            "category":"Shopping",
            "type":"Retail Goods"
        }
    ],
    "sg:phone":"+33 3 83 40 06 69",
    "sg:postcode":"54000",
    "sg:province":"Lorraine",
    "sg:tags":[
        "metallurgy",
        "finished",
        "-",
        "metalworking",
        "metallic"
    ],
    "wof:name":"Enseignes Charpentier",
    "wof:placetype":"venue"
},
  "geometry": {"coordinates":[6.176906,48.683994],"type":"Point"}
}