{
  "type": "Feature",
  "properties": {
    "iso:country":"FR",
    "sg:address":"153, Rte de Beauge - ZAC de l'Oseraie, 72000 Le Mans",
    "sg:orig_category":"Unclassifiable Establishments",
    "sg:phone":"+33 2 43 39 26 50",
    "sg:province":"Pays de Loire",
    "wof:name":"Cdc Emballage S.a.r.l.",
    "wof:placetype":"venue"
},
  "geometry": {"coordinates":[0.187369,48.003181],"type":"Point"}
}