{
  "type": "Feature",
  "properties": {
    "addr:full":"Zi 80110 Moreuil Picardie 80110",
    "addr:postcode":"80110;80110",
    "addr:street":"Zi",
    "iso:country":"FR",
    "sg:address":"Zi 80110 Moreuil",
    "sg:classifiers":[
        {
            "category":"Shopping",
            "type":"Retail Goods"
        }
    ],
    "sg:phone":"+33 3 22 35 10 08",
    "sg:postcode":"80110",
    "sg:province":"Picardie",
    "sg:tags":[
        "metallurgy",
        "finished",
        "-",
        "metalworking",
        "metallic"
    ],
    "wof:name":"Technique Entretien Maitenance En Industrie Tem Industrie",
    "wof:placetype":"venue"
},
  "geometry": {"coordinates":[2.485823,49.774715],"type":"Point"}
}