{
  "type": "Feature",
  "properties": {
    "iso:country":"FR",
    "sg:address":"27, Rue Jules Verne, 44700 Orvault",
    "sg:orig_category":"Unclassifiable Establishments",
    "sg:phone":"+33 2 40 94 81 82",
    "sg:province":"Pays de Loire",
    "wof:name":"Synetis S.a.s.",
    "wof:placetype":"venue"
},
  "geometry": {"coordinates":[-1.618845,47.252186],"type":"Point"}
}