{
  "type": "Feature",
  "properties": {
    "iso:country":"FR",
    "sg:address":"91191 Gif sur Yvette C\u00e9dex",
    "sg:orig_category":"Non-Classified Establishments",
    "sg:phone":"+33 1 69 08 60 00",
    "sg:province":"Languedoc-Roussillon",
    "wof:name":"C.e.a. De Saclay - Commissariat Energie Atomique",
    "wof:placetype":"venue"
},
  "geometry": {"coordinates":[2.1353,48.702339],"type":"Point"}
}