{
  "type": "Feature",
  "properties": {
    "addr:full":"26, Rue Assalit, 06000 Nice Provence-Alpes-C\u00f4te d'Azur",
    "addr:housenumber":"26",
    "addr:postcode":"06000",
    "addr:street":"Rue Assalit",
    "iso:country":"FR",
    "sg:address":"26, Rue Assalit, 06000 Nice",
    "sg:orig_category":"Unclassifiable Establishments",
    "sg:phone":"+33 4 93 85 44 07",
    "sg:province":"Provence-Alpes-C\u00f4te d'Azur",
    "wof:name":"Agence Inter'anim S.a.",
    "wof:placetype":"venue"
},
  "geometry": {"coordinates":[7.266173,43.705746],"type":"Point"}
}