{
  "type": "Feature",
  "properties": {
    "addr:full":"2 avenue Louis Pasteur 84230 CHATEAUNEUF DU PAPE Midi Pyr\u00e9n\u00e9es",
    "addr:housenumber":"2",
    "addr:postcode":"84230",
    "addr:street":"Avenue Louis Pasteur",
    "iso:country":"FR",
    "sg:address":"2 avenue Louis Pasteur 84230 CHATEAUNEUF DU PAPE",
    "sg:classifiers":[
        {
            "category":"Wholesale",
            "subcategory":"Wine & Distilled Alcoholic Beverages",
            "type":"Manufacturing & Wholesale Goods"
        }
    ],
    "sg:phone":"+33 4 90 83 71 25",
    "sg:province":"Midi Pyr\u00e9n\u00e9es",
    "sg:tags":[
        "french"
    ],
    "wof:name":"Domaine De La Roquette Scea",
    "wof:placetype":"venue"
},
  "geometry": {"coordinates":[4.835261,44.056824],"type":"Point"}
}