{
  "type": "Feature",
  "properties": {
    "addr:full":"253, RN 42 bis - ., 62360 La Capelle l\u00e8s Boulogne Nord Pas-de-Calais",
    "addr:housenumber":"253",
    "addr:postcode":"62360",
    "addr:street":"Rn 42 Bis;La Capelle;Boulogne Nord",
    "iso:country":"FR",
    "sg:address":"253, RN 42 bis - ., 62360 La Capelle l\u00e8s Boulogne",
    "sg:orig_category":"Unclassifiable Establishments",
    "sg:phone":"+33 3 21 83 13 13",
    "sg:province":"Nord Pas-de-Calais",
    "wof:name":"Dispatching France S.a.r.l.",
    "wof:placetype":"venue"
},
  "geometry": {"coordinates":[1.63398,50.677826],"type":"Point"}
}