{
  "type": "Feature",
  "properties": {
    "iso:country":"FR",
    "sg:address":"46 Place Abel Gance 92650 Boulogne",
    "sg:classifiers":[
        {
            "category":"Sports & Exercise",
            "subcategory":"Sports Center",
            "type":"Entertainment"
        }
    ],
    "sg:phone":"+33 1 49 10 20 30",
    "sg:province":"Aquitaine",
    "wof:name":"France Galop",
    "wof:placetype":"venue"
},
  "geometry": {"coordinates":[2.24347,48.83382],"type":"Point"}
}