{
  "type": "Feature",
  "properties": {
    "addr:full":"113 Route Des Argos 74940 Annecy Le Vieux Rhone-Alpes",
    "addr:housenumber":"113",
    "addr:postcode":"74940",
    "addr:street":"Route Des Argos",
    "iso:country":"FR",
    "sg:address":"113 Route Des Argos 74940 Annecy Le Vieux",
    "sg:classifiers":[
        {
            "category":"Manufacturing",
            "subcategory":"Rubber & Plastics",
            "type":"Manufacturing & Wholesale Goods"
        }
    ],
    "sg:phone":"+33 4 50 09 80 50",
    "sg:province":"Rhone-Alpes",
    "wof:name":"Vega Realisations Composites",
    "wof:placetype":"venue"
},
  "geometry": {"coordinates":[6.14277,45.93309],"type":"Point"}
}