{
  "type": "Feature",
  "properties": {
    "iso:country":"FR",
    "sg:address":"70, Chemin de Crau, 13880 V\u00e9laux",
    "sg:orig_category":"Non-Classified Establishments",
    "sg:phone":"+33 4 42 87 92 81",
    "sg:province":"Provence-Alpes-C\u00f4te d'Azur",
    "wof:name":"Rastello",
    "wof:placetype":"venue"
},
  "geometry": {"coordinates":[5.245226,43.526974],"type":"Point"}
}