{
  "type": "Feature",
  "properties": {
    "addr:full":"33, Rue des Perruts, 71160 Digoin Digoin Bourgogne 71160",
    "addr:housenumber":"33",
    "addr:postcode":"71160;71160",
    "addr:street":"Rue Des Perruts",
    "iso:country":"FR",
    "sg:address":"33, Rue des Perruts, 71160 Digoin",
    "sg:city":"Digoin",
    "sg:orig_category":"Non-Classified Establishments",
    "sg:phone":"+33 3 85 53 88 91",
    "sg:postcode":"71160",
    "sg:province":"Bourgogne",
    "wof:name":"Bouhet S.a.",
    "wof:placetype":"venue"
},
  "geometry": {"coordinates":[3.989384,46.475983],"type":"Point"}
}