{
  "type": "Feature",
  "properties": {
    "addr:full":"40 Rue Paul Valery 31200 Toulouse Midi Pyr\u00e9n\u00e9es 31200",
    "addr:housenumber":"40",
    "addr:postcode":"31200;31200",
    "addr:street":"Rue Paul Valery",
    "iso:country":"FR",
    "sg:address":"40 Rue Paul Valery 31200 Toulouse",
    "sg:classifiers":[
        {
            "category":"Farming",
            "subcategory":"Farm",
            "type":"Manufacturing & Wholesale Goods"
        }
    ],
    "sg:phone":"+33 5 61 47 72 08",
    "sg:postcode":"31200",
    "sg:province":"Midi Pyr\u00e9n\u00e9es",
    "sg:tags":[
        "horticulture",
        "agriculture",
        "livestock"
    ],
    "wof:name":"Violin Horticulture Sa",
    "wof:placetype":"venue"
},
  "geometry": {"coordinates":[1.44798,43.636101],"type":"Point"}
}