{
  "type": "Feature",
  "properties": {
    "addr:full":"33 Av Du Docteur Georges Levy Parc Club Moulin A Vent 69200 Venissieux Rhone-Alpes",
    "addr:postcode":"69200",
    "addr:street":"33 Av Du Docteur Georges Levy Parc Club Moulin A Vent",
    "iso:country":"FR",
    "sg:address":"33 Av Du Docteur Georges Levy Parc Club Moulin A Vent 69200 Venissieux",
    "sg:classifiers":[
        {
            "category":"Wholesale",
            "subcategory":"Machinery & Supplies",
            "type":"Manufacturing & Wholesale Goods"
        }
    ],
    "sg:phone":"+33 4 78 00 01 06",
    "sg:province":"Rhone-Alpes",
    "sg:tags":[
        "equipment",
        "-",
        "precision",
        "glass",
        "optical",
        "health",
        "instrument"
    ],
    "wof:name":"Rodenstock France",
    "wof:placetype":"venue"
},
  "geometry": {"coordinates":[4.860519,45.719555],"type":"Point"}
}