{
  "type": "Feature",
  "properties": {
    "addr:full":"27 rue Marcel Merieux 69960 CORBAS Rhone-Alpes 69960",
    "addr:housenumber":"27",
    "addr:postcode":"69960;69960",
    "addr:street":"Rue Marcel Merieux",
    "iso:country":"FR",
    "sg:address":"27 rue Marcel Merieux 69960 CORBAS",
    "sg:classifiers":[
        {
            "category":"Food & Beverages",
            "subcategory":"Meat & Fish",
            "type":"Retail Goods"
        }
    ],
    "sg:phone":"+33 4 78 21 80 80",
    "sg:postcode":"69960",
    "sg:province":"Rhone-Alpes",
    "sg:tags":[
        "export"
    ],
    "wof:name":"Comm Intern Alimentaire Cointa Sa",
    "wof:placetype":"venue"
},
  "geometry": {"coordinates":[4.92227,45.670071],"type":"Point"}
}