{
  "type": "Feature",
  "properties": {
    "iso:country":"FR",
    "sg:address":"zone artisanale le Pansu 38500 La Buisse",
    "sg:classifiers":[
        {
            "category":"Building & Trades",
            "subcategory":"Construction",
            "type":"Services"
        }
    ],
    "sg:phone":"+33 4 76 06 15 15",
    "sg:postcode":"38500",
    "sg:province":"Rhone-Alpes",
    "sg:tags":[
        "scaffold",
        "threaded",
        "connectors"
    ],
    "wof:name":"Sdr Fixations Sa",
    "wof:placetype":"venue"
},
  "geometry": {"coordinates":[5.621252,45.335114],"type":"Point"}
}