{
  "type": "Feature",
  "properties": {
    "iso:country":"FR",
    "sg:address":"avenue des Caniers 13400 Aubagne",
    "sg:classifiers":[
        {
            "category":"Home & Garden",
            "subcategory":"Garden Supply",
            "type":"Retail Goods"
        }
    ],
    "sg:phone":"+33 4 42 82 40 00",
    "sg:tags":[
        "potter's"
    ],
    "wof:name":"Poterie De M\u00e9diterran\u00e9e S.a.r.l.",
    "wof:placetype":"venue"
},
  "geometry": {"coordinates":[5.594322,43.285564],"type":"Point"}
}