{
  "type": "Feature",
  "properties": {
    "addr:full":"1 Sentier De La Montagne D Etre 02380 Coucy Le Chateau Auffrique Picardie 02380",
    "addr:housenumber":"1",
    "addr:postcode":"02380;02380",
    "addr:street":"Sentier De La Montagne D Etre",
    "iso:country":"FR",
    "sg:address":"1 Sentier De La Montagne D Etre 02380 Coucy Le Chateau Auffrique",
    "sg:classifiers":[
        {
            "category":"Farming",
            "subcategory":"Farm & Veterinary Services",
            "type":"Manufacturing & Wholesale Goods"
        }
    ],
    "sg:phone":"+33 3 23 52 70 01",
    "sg:postcode":"02380",
    "sg:province":"Picardie",
    "sg:tags":[
        "advice",
        "agriculture",
        "livestock",
        "business"
    ],
    "wof:name":"Etf Honore",
    "wof:placetype":"venue"
},
  "geometry": {"coordinates":[3.327675,49.522743],"type":"Point"}
}