{
  "type": "Feature",
  "properties": {
    "addr:full":"3 Place Saint Medard Brunoy Ile de France 91800",
    "addr:housenumber":"3",
    "addr:postcode":"91800",
    "addr:street":"Place Saint Medard",
    "iso:country":"FR",
    "sg:address":"3 Place Saint Medard",
    "sg:city":"Brunoy",
    "sg:classifiers":[
        {
            "category":"Banks & Credit Unions",
            "subcategory":"Financial Services",
            "type":"Services"
        }
    ],
    "sg:phone":"+33 1 60 46 88 94",
    "sg:postcode":"91800",
    "sg:province":"Ile de France",
    "sg:tags":[
        "banking",
        "finance",
        "insurance"
    ],
    "wof:name":"Banque Populaire Industrielle Et Commerciale De La Region Su (bics)",
    "wof:placetype":"venue"
},
  "geometry": {"coordinates":[2.502668,48.69791],"type":"Point"}
}