{
  "type": "Feature",
  "properties": {
    "addr:full":"16 Rue Bara 08700 NOUZONVILLE Gespunsart Champagne 08700",
    "addr:housenumber":"16",
    "addr:postcode":"08700;08700",
    "addr:street":"Rue Bara;Champagne",
    "iso:country":"FR",
    "sg:address":"16 Rue Bara 08700 NOUZONVILLE",
    "sg:city":"Gespunsart",
    "sg:classifiers":[
        {
            "category":"Train Station",
            "subcategory":"Rail",
            "type":"Transportation"
        }
    ],
    "sg:phone":"+33 3 24 53 81 12",
    "sg:postcode":"08700",
    "sg:province":"Champagne",
    "sg:tags":[
        "steel",
        "working"
    ],
    "wof:name":"Dombret-becq Sarl",
    "wof:placetype":"venue"
},
  "geometry": {"coordinates":[4.745503,49.816601],"type":"Point"}
}