{
  "type": "Feature",
  "properties": {
    "addr:full":"75 Boulevard Dijon 10800 St Julien Les Villas Champagne 10800",
    "addr:housenumber":"75",
    "addr:postcode":"10800 st julien;10800",
    "addr:street":"Boulevard Dijon;Les Villas",
    "iso:country":"FR",
    "sg:address":"75 Boulevard Dijon 10800 St Julien Les Villas",
    "sg:classifiers":[
        {
            "category":"Shopping",
            "subcategory":"Bicycles & Sporting Goods",
            "type":"Retail Goods"
        }
    ],
    "sg:phone":"+33 3 25 75 57 41",
    "sg:postcode":"10800",
    "sg:province":"Champagne",
    "sg:tags":[
        "product",
        "sport",
        "miscellaneous"
    ],
    "wof:name":"Cabanon Sport Sa",
    "wof:placetype":"venue"
},
  "geometry": {"coordinates":[4.085211,48.27306],"type":"Point"}
}