{
  "type": "Feature",
  "properties": {
    "addr:full":"140 Route De Bischwiller 67300 Schiltigheim Schiltigheim Alsace 67300",
    "addr:housenumber":"140",
    "addr:postcode":"67300;67300",
    "addr:street":"Route De Bischwiller",
    "iso:country":"FR",
    "sg:address":"140 Route De Bischwiller 67300 Schiltigheim",
    "sg:city":"Schiltigheim",
    "sg:classifiers":[
        {
            "category":"Travel",
            "subcategory":"Hotels & Motels",
            "type":"Entertainment"
        }
    ],
    "sg:phone":"+33 3 88 62 33 34",
    "sg:postcode":"67300",
    "sg:province":"Alsace",
    "sg:tags":[
        "hotels",
        "business",
        "restaurant"
    ],
    "wof:name":"Pompes Funebres De Schiltigheim",
    "wof:placetype":"venue"
},
  "geometry": {"coordinates":[7.750365,48.608414],"type":"Point"}
}