{
  "type": "Feature",
  "properties": {
    "addr:full":"Rte Nationale 102 Saint Jean le Centenier Rhone-Alpes 07580",
    "addr:housenumber":"102",
    "addr:postcode":"07580",
    "addr:street":"Rte Nationale;Saint Jean Le;Rhone-Alpes",
    "iso:country":"FR",
    "sg:address":"Rte Nationale 102",
    "sg:city":"Saint Jean le Centenier",
    "sg:orig_category":"Unclassifiable Establishments",
    "sg:phone":"+33 4 75 36 73 27",
    "sg:postcode":"07580",
    "sg:province":"Rhone-Alpes",
    "wof:name":"D.a.g. S.a.r.l. - Distribution Articles Gil",
    "wof:placetype":"venue"
},
  "geometry": {"coordinates":[4.547719,44.607738],"type":"Point"}
}