{
  "type": "Feature",
  "properties": {
    "iso:country":"FR",
    "sg:address":"2 Rue Du Chanoine Collin",
    "sg:city":"Metz",
    "sg:classifiers":[
        {
            "category":"Banks & Credit Unions",
            "subcategory":"Financial Services",
            "type":"Services"
        }
    ],
    "sg:phone":"+33 3 87 18 72 71",
    "sg:postcode":"57000",
    "sg:province":"Lorraine",
    "sg:tags":[
        "banking",
        "finance",
        "insurance"
    ],
    "wof:name":"Banque Populaire De Lorraine Societe Cooperative De Banque (bpl)",
    "wof:placetype":"venue"
},
  "geometry": {"coordinates":[6.176864,49.120407],"type":"Point"}
}