{
  "type": "Feature",
  "properties": {
    "iso:country":"FR",
    "sg:address":"2 Route De La For\u00eat Hameau La Neuville 27400 La Haye Le Comte",
    "sg:classifiers":[
        {
            "category":"Wholesale",
            "subcategory":"Machinery & Supplies",
            "type":"Manufacturing & Wholesale Goods"
        }
    ],
    "sg:phone":"+33 2 32 50 54 45",
    "sg:postcode":"27400",
    "sg:province":"Haute Normandie",
    "sg:tags":[
        "handling",
        "material",
        "-",
        "machine",
        "equipment",
        "engineering",
        "mechanical"
    ],
    "wof:name":"Ploquin Csk Sarl",
    "wof:placetype":"venue"
},
  "geometry": {"coordinates":[1.134962,49.107613],"type":"Point"}
}