{
  "type": "Feature",
  "properties": {
    "addr:full":"ZI La Malterie Montierchaume Centre 36130",
    "addr:postcode":"36130",
    "addr:street":"Zi La Malterie Montierchaume",
    "iso:country":"FR",
    "sg:address":"ZI La Malterie",
    "sg:city":"Montierchaume",
    "sg:orig_category":"Unclassifiable Establishments",
    "sg:phone":"+33 2 54 22 11 44",
    "sg:postcode":"36130",
    "sg:province":"Centre",
    "wof:name":"Maintenance Industrielle S.a.",
    "wof:placetype":"venue"
},
  "geometry": {"coordinates":[1.772713,46.863937],"type":"Point"}
}