{
  "type": "Feature",
  "properties": {
    "iso:country":"FR",
    "sg:address":"13 Place De La Comedie 34000 Montpellier",
    "sg:classifiers":[
        {
            "category":"Professional",
            "subcategory":"Printing & Photocopies",
            "type":"Services"
        }
    ],
    "sg:phone":"+33 4 67 06 77 88",
    "sg:province":"Languedoc-Roussillon",
    "sg:tags":[
        "publishing"
    ],
    "wof:name":"Lettre M",
    "wof:placetype":"venue"
},
  "geometry": {"coordinates":[3.87867,43.60741],"type":"Point"}
}