{
  "type": "Feature",
  "properties": {
    "iso:country":"FR",
    "sg:address":"1 Place Jacquemart; Romans sur Is\u00e8re; 26103",
    "sg:classifiers":[
        {
            "category":"Banks & Credit Unions",
            "subcategory":"Bank",
            "type":"Services"
        }
    ],
    "sg:phone":"+33 4 75 02 20 33",
    "sg:province":"Nord Pas-de-Calais",
    "wof:name":"Banque Rh\u00f4ne-alpes",
    "wof:placetype":"venue"
},
  "geometry": {"coordinates":[5.049843,45.043579],"type":"Point"}
}