{
  "type": "Feature",
  "properties": {
    "iso:country":"FR",
    "sg:address":"B.P. 84001, 44040 Nantes C\u00e9dex 1^^2, Av. Jean-Claude Bonduelle, 44000 Nantes",
    "sg:orig_category":"Non-Classified Establishments",
    "sg:phone":"+33 2 40 12 91 91",
    "sg:postcode":"44000",
    "sg:province":"Pays de Loire",
    "wof:name":"C.i.o. S.a. - Cr\u00e9dit Industriel De L'ouest",
    "wof:placetype":"venue"
},
  "geometry": {"coordinates":[-1.553059,47.218117],"type":"Point"}
}