{
  "type": "Feature",
  "properties": {
    "addr:full":"B.P. 11, 26901 Valence C\u00e9dex 9^^10, Rue Gustave Eiffel, 26000 Valence Rhone-Alpes 26000",
    "addr:housenumber":"9 ^ ^ 10",
    "addr:postcode":"26901;26000;26000",
    "addr:street":"B.P. 11;Ce\u0301Dex;Rue Gustave Eiffel",
    "iso:country":"FR",
    "sg:address":"B.P. 11, 26901 Valence C\u00e9dex 9^^10, Rue Gustave Eiffel, 26000 Valence",
    "sg:orig_category":"Non-Classified Establishments",
    "sg:phone":"+33 4 75 86 18 61",
    "sg:postcode":"26000",
    "sg:province":"Rhone-Alpes",
    "wof:name":"Sermag S.a.r.l.",
    "wof:placetype":"venue"
},
  "geometry": {"coordinates":[4.889246,44.930458],"type":"Point"}
}