{
  "type": "Feature",
  "properties": {
    "addr:full":"Zi Des Dorices 44330 Vallet Pays de Loire 44330",
    "addr:postcode":"44330;44330",
    "addr:street":"Des Dorices",
    "iso:country":"FR",
    "sg:address":"Zi Des Dorices 44330 Vallet",
    "sg:classifiers":[
        {
            "category":"Food & Beverages",
            "subcategory":"Groceries & Convenience Stores",
            "type":"Retail Goods"
        }
    ],
    "sg:phone":"+33 2 40 36 66 66",
    "sg:postcode":"44330",
    "sg:province":"Pays de Loire",
    "sg:tags":[
        "product",
        "grain",
        "cereal",
        "related"
    ],
    "wof:name":"Pharma Sweet",
    "wof:placetype":"venue"
},
  "geometry": {"coordinates":[-1.265219,47.161079],"type":"Point"}
}