{
  "type": "Feature",
  "properties": {
    "iso:country":"FR",
    "sg:address":"Zi 39700 Dampierre",
    "sg:classifiers":[
        {
            "category":"Manufacturing",
            "subcategory":"Rubber & Plastics",
            "type":"Manufacturing & Wholesale Goods"
        }
    ],
    "sg:phone":"+33 3 84 79 42 79",
    "sg:province":"Franche Comt\u00e9",
    "sg:tags":[
        "printing"
    ],
    "wof:name":"Spiranyl Sarl",
    "wof:placetype":"venue"
},
  "geometry": {"coordinates":[5.740925,47.154335],"type":"Point"}
}