{
  "type": "Feature",
  "properties": {
    "iso:country":"FR",
    "sg:address":"Rue Andr\u00e9 Pommery - Z.I.",
    "sg:city":"Breuil le Sec",
    "sg:orig_category":"Unclassifiable Establishments",
    "sg:phone":"+33 3 44 78 28 28",
    "sg:postcode":"60840",
    "sg:province":"Champagne",
    "wof:name":"P.e.m. S.a. - Polyvalente D'electro-m\u00e9canique",
    "wof:placetype":"venue"
},
  "geometry": {"coordinates":[2.450087,49.373474],"type":"Point"}
}