{
  "type": "Feature",
  "properties": {
    "addr:full":"2 Rue Moulin 38160 St Marcellin Rhone-Alpes 38160",
    "addr:housenumber":"2",
    "addr:postcode":"38160;38160",
    "addr:street":"Rue Moulin;Rhone-Alpes",
    "iso:country":"FR",
    "sg:address":"2 Rue Moulin 38160 St Marcellin",
    "sg:classifiers":[
        {
            "category":"Food & Beverages",
            "subcategory":"Dairy",
            "type":"Retail Goods"
        }
    ],
    "sg:phone":"+33 4 76 38 12 13",
    "sg:postcode":"38160",
    "sg:province":"Rhone-Alpes",
    "sg:tags":[
        "product",
        "related"
    ],
    "wof:name":"Fromagerie Veyret Veilleux Sarl",
    "wof:placetype":"venue"
},
  "geometry": {"coordinates":[5.325362,45.15601],"type":"Point"}
}