{
  "type": "Feature",
  "properties": {
    "addr:full":"Le Lintan Za Du Haute Du Bois 56580 Brehan Br\u00e9han Bretagne 56580",
    "addr:postcode":"56580;56580",
    "addr:street":"Za Du Haute Du Bois;Bre\u0301Han",
    "iso:country":"FR",
    "sg:address":"Le Lintan Za Du Haute Du Bois 56580 Brehan",
    "sg:city":"Br\u00e9han",
    "sg:classifiers":[
        {
            "category":"Farming",
            "subcategory":"Farm & Veterinary Services",
            "type":"Manufacturing & Wholesale Goods"
        }
    ],
    "sg:phone":"+33 2 97 38 81 03",
    "sg:postcode":"56580",
    "sg:province":"Bretagne",
    "sg:tags":[
        "food",
        "product",
        "breeding",
        "animal",
        "related"
    ],
    "wof:name":"Olmix",
    "wof:placetype":"venue"
},
  "geometry": {"coordinates":[-2.766409,48.037312],"type":"Point"}
}