{
  "type": "Feature",
  "properties": {
    "addr:full":"Rue Albert Calmette - Usine de Montbr\u00e9sil Castres Midi Pyr\u00e9n\u00e9es 81100",
    "addr:postcode":"81100",
    "addr:street":"Rue Albert Calmette Usine",
    "iso:country":"FR",
    "sg:address":"Rue Albert Calmette - Usine de Montbr\u00e9sil",
    "sg:city":"Castres",
    "sg:orig_category":"Non-Classified Establishments",
    "sg:phone":"+33 5 63 72 65 70",
    "sg:postcode":"81100",
    "sg:province":"Midi Pyr\u00e9n\u00e9es",
    "wof:name":"Borchers France S.a.",
    "wof:placetype":"venue"
},
  "geometry": {"coordinates":[2.257356,43.56094],"type":"Point"}
}