{
  "type": "Feature",
  "properties": {
    "iso:country":"FR",
    "sg:address":"B.P. 95, 17103 Saintes C\u00e9dex^^4, Rue Arc de Triomphe, 17100 Saintes",
    "sg:orig_category":"Non-Classified Establishments",
    "sg:phone":"+33 5 46 74 37 55",
    "sg:postcode":"17100",
    "sg:province":"Poitou-Charentes",
    "wof:name":"L' Eveil Charentais S.a.r.l.",
    "wof:placetype":"venue"
},
  "geometry": {"coordinates":[-0.544339,45.699085],"type":"Point"}
}