{
  "type": "Feature",
  "properties": {
    "iso:country":"FR",
    "sg:address":"153 Avenue du G\u00e9n\u00e9ral Leclerc 54220 MALZEVILLE",
    "sg:classifiers":[
        {
            "category":"Professional",
            "subcategory":"Advertising",
            "type":"Services"
        }
    ],
    "sg:phone":"+33 3 83 21 64 64",
    "sg:postcode":"54220",
    "sg:province":"Lorraine",
    "sg:tags":[
        "agency"
    ],
    "wof:name":"Aire Nouvelle Et Associ\u00e9s Sarl",
    "wof:placetype":"venue"
},
  "geometry": {"coordinates":[6.180658,48.723427],"type":"Point"}
}