{
  "type": "Feature",
  "properties": {
    "iso:country":"FR",
    "sg:address":"7, Rue de la Briquetterie - ZAE Les Fauvettes, 95330 Domont",
    "sg:orig_category":"Unclassifiable Establishments",
    "sg:phone":"+33 1 39 35 16 07",
    "sg:province":"Ile de France",
    "wof:name":"Dasieurope S.a.r.l.",
    "wof:placetype":"venue"
},
  "geometry": {"coordinates":[2.326687,49.026634],"type":"Point"}
}