{
  "type": "Feature",
  "properties": {
    "addr:full":"Rue du Ruisseau Saint Quentin Fallavier C\u00e9dex Rhone-Alpes 38291",
    "addr:postcode":"38291",
    "addr:street":"Rue Du Ruisseau;Rhone-Alpes",
    "iso:country":"FR",
    "sg:address":"Rue du Ruisseau",
    "sg:city":"Saint Quentin Fallavier C\u00e9dex",
    "sg:orig_category":"Non-Classified Establishments",
    "sg:phone":"+33 4 74 99 99 99",
    "sg:postcode":"38291",
    "sg:province":"Rhone-Alpes",
    "wof:name":"Matel Francesa S.a.",
    "wof:placetype":"venue"
},
  "geometry": {"coordinates":[5.096047,45.641567],"type":"Point"}
}