{
  "type": "Feature",
  "properties": {
    "iso:country":"FR",
    "sg:address":"12/14, Bd du G\u00e9n\u00e9ral Leclerc, 93260 Les Lilas",
    "sg:orig_category":"Non-Classified Establishments",
    "sg:phone":"+33 1 43 63 60 60",
    "sg:postcode":"93260",
    "sg:province":"Ile de France",
    "wof:name":"Aviloil S.a.",
    "wof:placetype":"venue"
},
  "geometry": {"coordinates":[2.415765,48.879616],"type":"Point"}
}