{
  "type": "Feature",
  "properties": {
    "addr:full":"B.P. 1427, 13785 Aubagne C\u00e9dex^^ZI des Paluds - P\u00f4le Performance B\u00e2t C2, 13780 Aubagne Provence-Alpes-C\u00f4te d'Azur",
    "addr:housenumber":"ba\u0302t c2",
    "addr:postcode":"13785;13780",
    "addr:street":"B.P. 1427",
    "iso:country":"FR",
    "sg:address":"B.P. 1427, 13785 Aubagne C\u00e9dex^^ZI des Paluds - P\u00f4le Performance B\u00e2t C2, 13780 Aubagne",
    "sg:orig_category":"Non-Classified Establishments",
    "sg:phone":"+33 4 42 84 29 00",
    "sg:province":"Provence-Alpes-C\u00f4te d'Azur",
    "wof:name":"Keybio Laboratoires S.a.r.l.",
    "wof:placetype":"venue"
},
  "geometry": {"coordinates":[5.699832,43.27586],"type":"Point"}
}