{
  "type": "Feature",
  "properties": {
    "addr:full":"27270 La Chapelle Gauthier Haute Normandie 27270",
    "addr:housenumber":"27270",
    "addr:postcode":"27270",
    "addr:street":"La;Haute Normandie",
    "iso:country":"FR",
    "sg:address":"27270 La Chapelle Gauthier",
    "sg:classifiers":[
        {
            "category":"Wholesale",
            "subcategory":"Machinery & Supplies",
            "type":"Manufacturing & Wholesale Goods"
        }
    ],
    "sg:phone":"+33 2 32 43 78 60",
    "sg:postcode":"27270",
    "sg:province":"Haute Normandie",
    "sg:tags":[
        "handling",
        "material",
        "-",
        "machine",
        "equipment",
        "engineering",
        "mechanical"
    ],
    "wof:name":"Etna Fapel Sa.",
    "wof:placetype":"venue"
},
  "geometry": {"coordinates":[0.461005,48.986694],"type":"Point"}
}