{
  "type": "Feature",
  "properties": {
    "iso:country":"FR",
    "sg:address":"Espace Industriel de Beaupr\u00e9 25220 ROCHE LEZ BEAUPRE",
    "sg:classifiers":[
        {
            "category":"Banks & Credit Unions",
            "subcategory":"Investment Brokerage",
            "type":"Services"
        }
    ],
    "sg:phone":"+33 3 81 60 52 40",
    "sg:province":"Franche Comt\u00e9",
    "sg:tags":[
        "process",
        "control",
        "systems",
        "digital"
    ],
    "wof:name":"Societe B.b.e. E.u.r.l",
    "wof:placetype":"venue"
},
  "geometry": {"coordinates":[6.113558,47.275795],"type":"Point"}
}