{
  "type": "Feature",
  "properties": {
    "addr:full":"22 rue Gustave Eiffel 78300 Poissy Ile de France 78300",
    "addr:housenumber":"22",
    "addr:postcode":"78300;ile;78300",
    "addr:street":"Rue Gustave Eiffel;France",
    "iso:country":"FR",
    "sg:address":"22 rue Gustave Eiffel 78300 Poissy",
    "sg:classifiers":[
        {
            "category":"Manufacturing",
            "subcategory":"Motor Vehicles & Parts",
            "type":"Manufacturing & Wholesale Goods"
        }
    ],
    "sg:phone":"+33 13922390",
    "sg:postcode":"78300",
    "sg:province":"Ile de France",
    "sg:tags":[
        "expanding",
        "casting",
        "mortar"
    ],
    "wof:name":"Pagel S.a.",
    "wof:placetype":"venue"
},
  "geometry": {"coordinates":[2.063664,48.946507],"type":"Point"}
}