{
  "type": "Feature",
  "properties": {
    "addr:full":"Rte de Lorient - ZI Vezin le Coquet Bretagne 35132",
    "addr:postcode":"35132",
    "addr:street":"Rte De Lorient Zi Vezin Le Coquet Bretagne",
    "iso:country":"FR",
    "sg:address":"Rte de Lorient - ZI",
    "sg:city":"Vezin le Coquet",
    "sg:orig_category":"Unclassifiable Establishments",
    "sg:phone":"+33 2 99 54 14 44",
    "sg:postcode":"35132",
    "sg:province":"Bretagne",
    "wof:name":"G\u00e9cidic S.a.",
    "wof:placetype":"venue"
},
  "geometry": {"coordinates":[-1.755099,48.119236],"type":"Point"}
}