{
  "type": "Feature",
  "properties": {
    "iso:country":"FR",
    "sg:address":"Rue De L'Egalit\u00e9 69800 St Priest",
    "sg:classifiers":[
        {
            "category":"Professional",
            "subcategory":"Business Services",
            "type":"Services"
        }
    ],
    "sg:phone":"+33 4 78 21 54 05",
    "sg:postcode":"69800",
    "sg:province":"Rhone-Alpes",
    "sg:tags":[
        "training",
        "advice"
    ],
    "wof:name":"Lycee Professionnel Fernand Forest",
    "wof:placetype":"venue"
},
  "geometry": {"coordinates":[4.946621,45.689819],"type":"Point"}
}