{
  "type": "Feature",
  "properties": {
    "addr:full":"310, Rue de la Garonne - ZI de Petite Synthe, 59640 Dunkerque Pays de Loire",
    "addr:housenumber":"310",
    "addr:postcode":"59640",
    "addr:street":"Rue De La Garonne Zi De Petite Synthe",
    "iso:country":"FR",
    "sg:address":"310, Rue de la Garonne - ZI de Petite Synthe, 59640 Dunkerque",
    "sg:orig_category":"Non-Classified Establishments",
    "sg:phone":"+33 3 28 58 72 00",
    "sg:province":"Pays de Loire",
    "wof:name":"Charcuterie Artisanale Des Flandres S.a.",
    "wof:placetype":"venue"
},
  "geometry": {"coordinates":[2.35294,51.022812],"type":"Point"}
}