{
  "type": "Feature",
  "properties": {
    "addr:full":"2, Rue Fresnel - ZA de Marly, 91410 Corbreuse Ile de France",
    "addr:housenumber":"2",
    "addr:postcode":"91410;ile",
    "addr:street":"Rue Fresnel Za De Marly",
    "iso:country":"FR",
    "sg:address":"2, Rue Fresnel - ZA de Marly, 91410 Corbreuse",
    "sg:orig_category":"Unclassifiable Establishments",
    "sg:phone":"+33 1 64 55 15 51",
    "sg:province":"Ile de France",
    "wof:name":"Lord Ing\u00e9nierie S.a.",
    "wof:placetype":"venue"
},
  "geometry": {"coordinates":[2.01121,48.528149],"type":"Point"}
}