{
  "type": "Feature",
  "properties": {
    "addr:full":"67 Rue Du Rempart 59300 Valenciennes Nord Pas-de-Calais 59300",
    "addr:housenumber":"67",
    "addr:postcode":"59300;59300",
    "addr:street":"Rue Du Rempart",
    "iso:country":"FR",
    "sg:address":"67 Rue Du Rempart 59300 Valenciennes",
    "sg:classifiers":[
        {
            "category":"Utilities",
            "subcategory":"Electric",
            "type":"Services"
        }
    ],
    "sg:phone":"+33 3 27 23 23 71",
    "sg:postcode":"59300",
    "sg:province":"Nord Pas-de-Calais",
    "sg:tags":[
        "electricity",
        "raw",
        "energy",
        "material"
    ],
    "wof:name":"Electricite De France (edf)",
    "wof:placetype":"venue"
},
  "geometry": {"coordinates":[3.520513,50.361641],"type":"Point"}
}