{
  "type": "Feature",
  "properties": {
    "addr:full":"B.P. 530, 81206 Mazamet C\u00e9dex^^18, Rue Galibert Pons, 81200 Mazamet Midi Pyr\u00e9n\u00e9es",
    "addr:housenumber":"b.p. 530",
    "addr:postcode":"81206;81200",
    "addr:street":"Rue Galibert Pons",
    "iso:country":"FR",
    "sg:address":"B.P. 530, 81206 Mazamet C\u00e9dex^^18, Rue Galibert Pons, 81200 Mazamet",
    "sg:orig_category":"Non-Classified Establishments",
    "sg:phone":"+33 5 63 97 58 97",
    "sg:province":"Midi Pyr\u00e9n\u00e9es",
    "wof:name":"Midi Provence Service S.a.r.l.",
    "wof:placetype":"venue"
},
  "geometry": {"coordinates":[2.36605,43.460224],"type":"Point"}
}