{
  "type": "Feature",
  "properties": {
    "addr:full":"Actiparc Marseille Est 13821 La Penne Sur Huveaune Poitou-Charentes",
    "addr:postcode":"13821",
    "addr:street":"Actiparc;Huveaune",
    "iso:country":"FR",
    "sg:address":"Actiparc Marseille Est 13821 La Penne Sur Huveaune",
    "sg:classifiers":[
        {
            "category":"Manufacturing",
            "subcategory":"Printing",
            "type":"Manufacturing & Wholesale Goods"
        }
    ],
    "sg:phone":"+33 4 91 87 80 44",
    "sg:province":"Poitou-Charentes",
    "sg:tags":[
        "publishing"
    ],
    "wof:name":"Moore Paragon France",
    "wof:placetype":"venue"
},
  "geometry": {"coordinates":[5.515035,43.282356],"type":"Point"}
}