{
  "type": "Feature",
  "properties": {
    "addr:full":"9, Cours Victor Hugo, 43000 Le Puy en Velay Le Puy-en-Velay Auvergne 43000",
    "addr:housenumber":"9",
    "addr:postcode":"43000;43000",
    "addr:street":"Cours Victor Hugo;Puy En Velay",
    "iso:country":"FR",
    "sg:address":"9, Cours Victor Hugo, 43000 Le Puy en Velay",
    "sg:city":"Le Puy-en-Velay",
    "sg:orig_category":"Unclassifiable Establishments",
    "sg:phone":"+33 4 71 05 80 00",
    "sg:postcode":"43000",
    "sg:province":"Auvergne",
    "wof:name":"E.d.f. Et Gaz De France",
    "wof:placetype":"venue"
},
  "geometry": {"coordinates":[3.884654,45.039005],"type":"Point"}
}