{
  "type": "Feature",
  "properties": {
    "iso:country":"FR",
    "sg:address":"2, Rue du Clos Chalozeau, 28600 Luisant",
    "sg:city":"Luisant",
    "sg:orig_category":"Non-Classified Establishments",
    "sg:phone":"+33 2 37 28 40 74",
    "sg:postcode":"28600",
    "sg:province":"Centre",
    "wof:name":"E.c.e.l.i.",
    "wof:placetype":"venue"
},
  "geometry": {"coordinates":[1.471006,48.424557],"type":"Point"}
}