{
  "type": "Feature",
  "properties": {
    "addr:full":"3 grand rue 67132 SCHIRMECK CEDEX Schirmeck Alsace 67130",
    "addr:housenumber":"3",
    "addr:postcode":"67132;67130",
    "addr:street":"Grand Rue",
    "iso:country":"FR",
    "sg:address":"3 grand rue 67132 SCHIRMECK CEDEX",
    "sg:city":"Schirmeck",
    "sg:classifiers":[
        {
            "category":"Manufacturing",
            "subcategory":"Textiles",
            "type":"Manufacturing & Wholesale Goods"
        }
    ],
    "sg:phone":"+33 3 88 47 44 22",
    "sg:postcode":"67130",
    "sg:province":"Alsace",
    "sg:tags":[
        "natural"
    ],
    "wof:name":"Steinheil Sa",
    "wof:placetype":"venue"
},
  "geometry": {"coordinates":[7.217092,48.477455],"type":"Point"}
}