{
  "type": "Feature",
  "properties": {
    "iso:country":"FR",
    "sg:address":"19, Rue Eug\u00e8ne Hennaff, 69200 V\u00e9nissieux",
    "sg:orig_category":"Unclassifiable Establishments",
    "sg:phone":"+33 4 72 90 19 20",
    "sg:postcode":"69200",
    "sg:province":"Rhone-Alpes",
    "wof:name":"Sautra Dauphin",
    "wof:placetype":"venue"
},
  "geometry": {"coordinates":[4.905285,45.689945],"type":"Point"}
}