{
  "type": "Feature",
  "properties": {
    "addr:full":"13, Rue Rosenwald, 75015 Paris Ile de France",
    "addr:housenumber":"13",
    "addr:postcode":"75015",
    "addr:street":"Rue Rosenwald",
    "iso:country":"FR",
    "sg:address":"13, Rue Rosenwald, 75015 Paris",
    "sg:orig_category":"Non-Classified Establishments",
    "sg:phone":"+33 1 55 76 11 11",
    "sg:province":"Ile de France",
    "wof:name":"Publicorp",
    "wof:placetype":"venue"
},
  "geometry": {"coordinates":[2.306135,48.833263],"type":"Point"}
}