{
  "type": "Feature",
  "properties": {
    "iso:country":"FR",
    "sg:address":"Rte de N\u00eemes - Le Clos Saint Romain",
    "sg:city":"Aimargues",
    "sg:orig_category":"Non-Classified Establishments",
    "sg:phone":"+33 4 66 88 54 46",
    "sg:postcode":"30470",
    "sg:province":"Languedoc-Roussillon",
    "wof:name":"Babcock Wanson S.a.",
    "wof:placetype":"venue"
},
  "geometry": {"coordinates":[4.198167,43.690563],"type":"Point"}
}