{
  "type": "Feature",
  "properties": {
    "addr:full":"place Gutenberg 59175 Templemars Nord Pas-de-Calais 59175",
    "addr:postcode":"59175;59175",
    "addr:street":"Place Gutenberg",
    "iso:country":"FR",
    "sg:address":"place Gutenberg 59175 Templemars",
    "sg:classifiers":[
        {
            "category":"Military Area",
            "subcategory":"Air Force Base",
            "type":"Public Place"
        }
    ],
    "sg:phone":"+33 3 20 60 49 49",
    "sg:postcode":"59175",
    "sg:province":"Nord Pas-de-Calais",
    "sg:tags":[
        "unit",
        "measurement"
    ],
    "wof:name":"S.e.f.r.a.m. Sa",
    "wof:placetype":"venue"
},
  "geometry": {"coordinates":[3.063683,50.564095],"type":"Point"}
}