{
  "type": "Feature",
  "properties": {
    "addr:full":"171, Av. Saint Simond, 73100 Aix les Bains Rhone-Alpes 73100",
    "addr:postcode":"73100;73100",
    "addr:street":"171 Av. Saint Simond",
    "iso:country":"FR",
    "sg:address":"171, Av. Saint Simond, 73100 Aix les Bains",
    "sg:orig_category":"Unclassifiable Establishments",
    "sg:phone":"+33 4 79 61 14 44",
    "sg:postcode":"73100",
    "sg:province":"Rhone-Alpes",
    "wof:name":"Les Fils De Louis Assier S.a.r.l.",
    "wof:placetype":"venue"
},
  "geometry": {"coordinates":[5.915114,45.7075],"type":"Point"}
}