{
  "type": "Feature",
  "properties": {
    "addr:full":"Parc La Plaine De L'Allee Des Com 01150 Blyes Rhone-Alpes",
    "addr:postcode":"01150",
    "addr:street":"La Plaine De L'Allee Des Com",
    "iso:country":"FR",
    "sg:address":"Parc La Plaine De L'Allee Des Com 01150 Blyes",
    "sg:classifiers":[
        {
            "category":"Park",
            "subcategory":"Provincial",
            "type":"Public Place"
        }
    ],
    "sg:phone":"+33 4 74 46 23 60",
    "sg:province":"Rhone-Alpes",
    "sg:tags":[
        "dyer",
        "piece"
    ],
    "wof:name":"Maire Et Compagnie Sa",
    "wof:placetype":"venue"
},
  "geometry": {"coordinates":[5.391374,45.868443],"type":"Point"}
}