{
  "type": "Feature",
  "properties": {
    "addr:full":"140 r de la R\u00e9publique; Belleville sur Sa\u00f4ne; 69220 Rhone-Alpes 69220",
    "addr:housenumber":"140",
    "addr:postcode":"69220;69220",
    "addr:street":"R De La Re\u0301Publique",
    "iso:country":"FR",
    "sg:address":"140 r de la R\u00e9publique; Belleville sur Sa\u00f4ne; 69220",
    "sg:classifiers":[
        {
            "category":"Banks & Credit Unions",
            "subcategory":"Bank",
            "type":"Services"
        }
    ],
    "sg:phone":"+33 4 74 66 07 01",
    "sg:postcode":"69220",
    "sg:province":"Rhone-Alpes",
    "wof:name":"Banque Rh\u00f4ne Alpes",
    "wof:placetype":"venue"
},
  "geometry": {"coordinates":[4.678782,46.0886],"type":"Point"}
}