{
  "type": "Feature",
  "properties": {
    "iso:country":"FR",
    "sg:address":"B.P. 56",
    "sg:city":"Melesse",
    "sg:orig_category":"Non-Classified Establishments",
    "sg:phone":"+33 2 99 13 13 00",
    "sg:postcode":"35520",
    "sg:province":"Bretagne",
    "wof:name":"K\u00e9ramon S.a.",
    "wof:placetype":"venue"
},
  "geometry": {"coordinates":[-1.734432,48.178051],"type":"Point"}
}