{
  "type": "Feature",
  "properties": {
    "addr:full":"B.P. 2428, 31085 Toulouse C\u00e9dex 2^^Impasse Louis de Froidour - ZI de la Glaci\u00e8re, 31200 Toulouse Midi Pyr\u00e9n\u00e9es",
    "addr:postcode":"31085;31200",
    "addr:street":"B.P. 2428;Louis;Zi De La Glacie\u0300Re",
    "iso:country":"FR",
    "sg:address":"B.P. 2428, 31085 Toulouse C\u00e9dex 2^^Impasse Louis de Froidour - ZI de la Glaci\u00e8re, 31200 Toulouse",
    "sg:orig_category":"Non-Classified Establishments",
    "sg:phone":"+33 5 61 13 53 77",
    "sg:province":"Midi Pyr\u00e9n\u00e9es",
    "wof:name":"Ugine France Service S.a.s.",
    "wof:placetype":"venue"
},
  "geometry": {"coordinates":[1.44954,43.639011],"type":"Point"}
}