{
  "type": "Feature",
  "properties": {
    "iso:country":"FR",
    "sg:address":"79 Bd Haussmann",
    "sg:city":"Paris",
    "sg:classifiers":[
        {
            "category":"Banks & Credit Unions",
            "subcategory":"Financial Services",
            "type":"Services"
        }
    ],
    "sg:phone":"+33 1 40 06 43 21",
    "sg:postcode":"75008",
    "sg:province":"Ile de France",
    "sg:tags":[
        "banking",
        "finance",
        "insurance"
    ],
    "wof:name":"Banque Commerciale Pour L'europe Du Nord-eurobank",
    "wof:placetype":"venue"
},
  "geometry": {"coordinates":[2.321805,48.874355],"type":"Point"}
}