{
  "type": "Feature",
  "properties": {
    "addr:full":"1021, Av. de Toulouse, 34000 Montpellier Languedoc-Roussillon",
    "addr:housenumber":"1021",
    "addr:postcode":"34000",
    "addr:street":"Av. De Toulouse",
    "iso:country":"FR",
    "sg:address":"1021, Av. de Toulouse, 34000 Montpellier",
    "sg:orig_category":"Unclassifiable Establishments",
    "sg:phone":"+33 4 67 07 16 00",
    "sg:province":"Languedoc-Roussillon",
    "wof:name":"A.f.p.a.",
    "wof:placetype":"venue"
},
  "geometry": {"coordinates":[3.87609,43.610855],"type":"Point"}
}