{
  "type": "Feature",
  "properties": {
    "iso:country":"FR",
    "sg:address":"3, Rue Jean Monnet - Autoport Alsace, 68390 Sausheim",
    "sg:city":"Sausheim",
    "sg:orig_category":"Unclassifiable Establishments",
    "sg:phone":"+33 3 89 31 39 89",
    "sg:postcode":"68390",
    "sg:province":"Alsace",
    "wof:name":"Streck Transport S.a.r.l.",
    "wof:placetype":"venue"
},
  "geometry": {"coordinates":[7.369807,47.788521],"type":"Point"}
}