{
  "type": "Feature",
  "properties": {
    "addr:full":"1, R Principale Moulin Griesbach, 67580 Mietesheim Mietesheim Alsace 67580",
    "addr:housenumber":"1",
    "addr:postcode":"67580;67580",
    "addr:street":"R Principale Moulin Griesbach;Mietesheim",
    "iso:country":"FR",
    "sg:address":"1, R Principale Moulin Griesbach, 67580 Mietesheim",
    "sg:city":"Mietesheim",
    "sg:orig_category":"Unclassifiable Establishments",
    "sg:phone":"+33 3 88 90 30 14",
    "sg:postcode":"67580",
    "sg:province":"Alsace",
    "wof:name":"Thomenn Et Compagnie S.a.",
    "wof:placetype":"venue"
},
  "geometry": {"coordinates":[7.67937,48.862595],"type":"Point"}
}