{
  "type": "Feature",
  "properties": {
    "addr:full":"r Vann\u00e9e 27210 Saint Maclou Haute Normandie 27210",
    "addr:postcode":"27210;maclou;27210",
    "addr:street":"Haute Normandie",
    "iso:country":"FR",
    "sg:address":"r Vann\u00e9e 27210 Saint Maclou",
    "sg:classifiers":[
        {
            "category":"Professional",
            "subcategory":"Engineering",
            "type":"Services"
        }
    ],
    "sg:phone":"+33 2 32 41 21 95",
    "sg:postcode":"27210",
    "sg:province":"Haute Normandie",
    "sg:tags":[
        "machine",
        "-",
        "mechanical"
    ],
    "wof:name":"Europalettes S.b.f.",
    "wof:placetype":"venue"
},
  "geometry": {"coordinates":[0.404555,49.361004],"type":"Point"}
}