{
  "type": "Feature",
  "properties": {
    "iso:country":"FR",
    "sg:address":"128, Rue de Metz, 57650 Fontoy",
    "sg:orig_category":"Unclassifiable Establishments",
    "sg:phone":"+33 3 82 86 42 42",
    "sg:province":"Lorraine",
    "wof:name":"C.e.p. S.a.r.l.",
    "wof:placetype":"venue"
},
  "geometry": {"coordinates":[6.005165,49.34375],"type":"Point"}
}