{
  "type": "Feature",
  "properties": {
    "addr:full":"55 Rue Du Mole 74800 La Roche Sur Foron Rhone-Alpes",
    "addr:housenumber":"55",
    "addr:postcode":"74800",
    "addr:street":"Rue Du Mole",
    "iso:country":"FR",
    "sg:address":"55 Rue Du Mole 74800 La Roche Sur Foron",
    "sg:classifiers":[
        {
            "category":"Professional",
            "type":"Services"
        }
    ],
    "sg:phone":"+33 4 50 03 49 90",
    "sg:province":"Rhone-Alpes",
    "sg:tags":[
        "transport",
        "road"
    ],
    "wof:name":"Transports Delerce Michel Sarl",
    "wof:placetype":"venue"
},
  "geometry": {"coordinates":[6.303622,46.079033],"type":"Point"}
}