{
  "type": "Feature",
  "properties": {
    "iso:country":"FR",
    "sg:address":"2 Route De Notre Dame Des Mauges 49510 Jallais",
    "sg:classifiers":[
        {
            "category":"Manufacturing",
            "subcategory":"Wood Products",
            "type":"Manufacturing & Wholesale Goods"
        }
    ],
    "sg:phone":"+33 2 41 64 14 72",
    "sg:province":"Pays de Loire",
    "sg:tags":[
        "professional",
        "furniture"
    ],
    "wof:name":"Ste Rene Bidet Meubles Amenagements Interieurs",
    "wof:placetype":"venue"
},
  "geometry": {"coordinates":[-0.854814,47.201897],"type":"Point"}
}