{
  "type": "Feature",
  "properties": {
    "iso:country":"FR",
    "sg:address":"ZI de Felet",
    "sg:city":"Thiers",
    "sg:orig_category":"Unclassifiable Establishments",
    "sg:phone":"+33 4 73 80 34 34",
    "sg:postcode":"63300",
    "sg:province":"Auvergne",
    "wof:name":"S.t.t. L\u00e9onard S.a. - Soci\u00e9t\u00e9 Tiermmoise De Transport",
    "wof:placetype":"venue"
},
  "geometry": {"coordinates":[3.548272,45.855244],"type":"Point"}
}