{
  "type": "Feature",
  "properties": {
    "addr:full":"B.P. 90111, 57201 Sarreguemines C\u00e9dex^^106 A, Rue du Champs de Mars, 57200 Sarreguemines Lorraine",
    "addr:housenumber":"a",
    "addr:postcode":"57201;57200",
    "addr:street":"Rue Du Champs De Mars",
    "iso:country":"FR",
    "sg:address":"B.P. 90111, 57201 Sarreguemines C\u00e9dex^^106 A, Rue du Champs de Mars, 57200 Sarreguemines",
    "sg:orig_category":"Non-Classified Establishments",
    "sg:phone":"+33 3 87 28 33 70",
    "sg:province":"Lorraine",
    "wof:name":"Euragest S.a.r.l.",
    "wof:placetype":"venue"
},
  "geometry": {"coordinates":[7.070569,49.108246],"type":"Point"}
}