{
  "type": "Feature",
  "properties": {
    "addr:full":"4, Rue Plichon, 75011 Paris Ile de France",
    "addr:housenumber":"4",
    "addr:postcode":"75011",
    "addr:street":"Rue Plichon",
    "iso:country":"FR",
    "sg:address":"4, Rue Plichon, 75011 Paris",
    "sg:orig_category":"Non-Classified Establishments",
    "sg:phone":"+33 1 55 28 81 81",
    "sg:province":"Ile de France",
    "wof:name":"Eupro Soft S.a.r.l.",
    "wof:placetype":"venue"
},
  "geometry": {"coordinates":[2.385379,48.862717],"type":"Point"}
}