{
  "type": "Feature",
  "properties": {
    "iso:country":"FR",
    "sg:address":"ZAC de Planuya",
    "sg:city":"Arcangues",
    "sg:orig_category":"Unclassifiable Establishments",
    "sg:phone":"+33 5 59 70 31 31",
    "sg:postcode":"64200",
    "sg:province":"Aquitaine",
    "wof:name":"P.n.p. S.a.r.l.",
    "wof:placetype":"venue"
},
  "geometry": {"coordinates":[-1.519779,43.435661],"type":"Point"}
}