{
  "type": "Feature",
  "properties": {
    "iso:country":"FR",
    "sg:address":"B.P. 31, 67601 S\u00e9lestat C\u00e9dex^^13, Rte du Haut Koenigsbourg, 67600 S\u00e9lestat",
    "sg:city":"S\u00e9lestat",
    "sg:orig_category":"Non-Classified Establishments",
    "sg:phone":"+33 3 88 92 10 34",
    "sg:postcode":"67600",
    "sg:province":"Alsace",
    "wof:name":"Stahl Imprimerie S.a.",
    "wof:placetype":"venue"
},
  "geometry": {"coordinates":[7.452325,48.257805],"type":"Point"}
}