{
  "type": "Feature",
  "properties": {
    "addr:full":"1 Rue De Micy 45380 La Chapelle St Mesmin La Chapelle-Saint-Mesmin Centre 45380",
    "addr:housenumber":"1;chapelle-saint-mesmin",
    "addr:postcode":"45380;45380",
    "addr:street":"Rue De Micy;La Chapelle St",
    "iso:country":"FR",
    "sg:address":"1 Rue De Micy 45380 La Chapelle St Mesmin",
    "sg:city":"La Chapelle-Saint-Mesmin",
    "sg:classifiers":[
        {
            "category":"Professional",
            "subcategory":"Business Services",
            "type":"Services"
        }
    ],
    "sg:phone":"+33 2 38 88 18 69",
    "sg:postcode":"45380",
    "sg:province":"Centre",
    "sg:tags":[
        "training",
        "advice"
    ],
    "wof:name":"Bureau Veritas",
    "wof:placetype":"venue"
},
  "geometry": {"coordinates":[1.852982,47.899586],"type":"Point"}
}