{
  "type": "Feature",
  "properties": {
    "addr:full":"64, Chemin de la Sir\u00e8ne - Vieille Rte de Grasse, 83300 Draguignan Provence-Alpes-C\u00f4te d'Azur",
    "addr:housenumber":"64",
    "addr:postcode":"83300",
    "addr:street":"Chemin De La Sire\u0300Ne Vieille Rte De Grasse",
    "iso:country":"FR",
    "sg:address":"64, Chemin de la Sir\u00e8ne - Vieille Rte de Grasse, 83300 Draguignan",
    "sg:orig_category":"Unclassifiable Establishments",
    "sg:phone":"+33 4 94 68 83 40",
    "sg:province":"Provence-Alpes-C\u00f4te d'Azur",
    "wof:name":"Cr\u00e9ations Henry Jacques S.a.r.l.",
    "wof:placetype":"venue"
},
  "geometry": {"coordinates":[6.463645,43.539795],"type":"Point"}
}