{
  "type": "Feature",
  "properties": {
    "iso:country":"FR",
    "sg:address":"7 Av Des Mauges 49110 Le Pin En Mauges",
    "sg:classifiers":[
        {
            "category":"Shopping",
            "subcategory":"Luggage & Leather Goods",
            "type":"Retail Goods"
        }
    ],
    "sg:phone":"+33 2 41 70 00 17",
    "sg:postcode":"49110",
    "sg:province":"Pays de Loire",
    "sg:tags":[
        "shoe"
    ],
    "wof:name":"La Chaussure Du Pin Sa",
    "wof:placetype":"venue"
},
  "geometry": {"coordinates":[-0.90026,47.252487],"type":"Point"}
}