{
  "type": "Feature",
  "properties": {
    "addr:full":"123 Rue De La Pompe 75116 Paris Ile de France",
    "addr:housenumber":"123",
    "addr:postcode":"75116",
    "addr:street":"Rue De La Pompe",
    "iso:country":"FR",
    "sg:address":"123 Rue De La Pompe 75116 Paris",
    "sg:classifiers":[
        {
            "category":"Professional",
            "subcategory":"Business Services",
            "type":"Services"
        }
    ],
    "sg:phone":"+33 1 45 53 89 36",
    "sg:province":"Ile de France",
    "sg:tags":[
        "training",
        "advice"
    ],
    "wof:name":"Ecole Active Bilingue Lamartine",
    "wof:placetype":"venue"
},
  "geometry": {"coordinates":[2.279639,48.86618],"type":"Point"}
}