{
  "type": "Feature",
  "properties": {
    "iso:country":"FR",
    "sg:address":"2, Rue Victor Noir, 92521 Neuilly sur Seine C\u00e9dex",
    "sg:orig_category":"Non-Classified Establishments",
    "sg:phone":"+33 1 46 43 60 00",
    "sg:province":"Haute Normandie",
    "wof:name":"La Compagnie Des Fromages S.a.s.",
    "wof:placetype":"venue"
},
  "geometry": {"coordinates":[2.266192,48.881226],"type":"Point"}
}