{
  "type": "Feature",
  "properties": {
    "addr:full":"Zone Artisanale 35560 La Fontenelle La Fontenelle Bretagne 35560",
    "addr:postcode":"35560;35560",
    "addr:street":"Zone Artisanale;Fontenelle;Fontenelle",
    "iso:country":"FR",
    "sg:address":"Zone Artisanale 35560 La Fontenelle",
    "sg:city":"La Fontenelle",
    "sg:classifiers":[
        {
            "category":"Food & Beverages",
            "subcategory":"Fruits & Vegetables",
            "type":"Retail Goods"
        }
    ],
    "sg:phone":"+33 2 99 98 32 85",
    "sg:postcode":"35560",
    "sg:province":"Bretagne",
    "sg:tags":[
        "frozen",
        "product",
        "related"
    ],
    "wof:name":"Guerault Yvette",
    "wof:placetype":"venue"
},
  "geometry": {"coordinates":[-1.502958,48.468063],"type":"Point"}
}