{
  "type": "Feature",
  "properties": {
    "iso:country":"FR",
    "sg:address":"10 Rue Croix Marteau 79330 Pierrefitte",
    "sg:classifiers":[
        {
            "category":"Professional",
            "type":"Services"
        }
    ],
    "sg:phone":"+33 5 49 67 62 15",
    "sg:postcode":"79330",
    "sg:province":"Poitou-Charentes",
    "sg:tags":[
        "transport",
        "road"
    ],
    "wof:name":"Sarl Transports Grellier Pere Et Fils",
    "wof:placetype":"venue"
},
  "geometry": {"coordinates":[-0.299632,46.870316],"type":"Point"}
}