{
  "type": "Feature",
  "properties": {
    "iso:country":"FR",
    "sg:address":"4 Rue Charles Cros 95320 St Leu La For\u00eat",
    "sg:classifiers":[
        {
            "category":"Manufacturing",
            "subcategory":"Rubber & Plastics",
            "type":"Manufacturing & Wholesale Goods"
        }
    ],
    "sg:phone":"+33 1 30 40 98 42",
    "sg:province":"Ile de France",
    "wof:name":"Rts France Sa",
    "wof:placetype":"venue"
},
  "geometry": {"coordinates":[2.249553,49.002209],"type":"Point"}
}