{
  "type": "Feature",
  "properties": {
    "iso:country":"FR",
    "sg:address":"12, Av. du Mar\u00e9chal Foch, 31800 Saint Gaudens",
    "sg:orig_category":"Non-Classified Establishments",
    "sg:phone":"+33 5 61 95 96 96",
    "sg:province":"Midi Pyr\u00e9n\u00e9es",
    "wof:name":"Peintures Reca S.a.",
    "wof:placetype":"venue"
},
  "geometry": {"coordinates":[0.719061,43.106232],"type":"Point"}
}