{
  "type": "Feature",
  "properties": {
    "iso:country":"FR",
    "sg:address":"3 Rue De Fos Sur Mer 69007 Lyon",
    "sg:classifiers":[
        {
            "category":"Manufacturing",
            "subcategory":"Metals",
            "type":"Manufacturing & Wholesale Goods"
        }
    ],
    "sg:phone":"+33 4 78 58 62 25",
    "sg:postcode":"69007",
    "sg:province":"Rhone-Alpes",
    "sg:tags":[
        "metallurgy",
        "metalworking",
        "processing"
    ],
    "wof:name":"Entreprise Sartoris Merlin Et Compagnie Sarl",
    "wof:placetype":"venue"
},
  "geometry": {"coordinates":[4.840141,45.724743],"type":"Point"}
}