{
  "type": "Feature",
  "properties": {
    "iso:country":"FR",
    "sg:address":"6 Rue De Lorraine 54120 Baccarat",
    "sg:classifiers":[
        {
            "category":"Shopping",
            "subcategory":"Crafts & Fabrics",
            "type":"Retail Goods"
        }
    ],
    "sg:phone":"+33 3 83 75 10 53",
    "sg:postcode":"54120",
    "sg:province":"Lorraine",
    "sg:tags":[
        "textile",
        "clothing"
    ],
    "wof:name":"Carel Broderies Sarl",
    "wof:placetype":"venue"
},
  "geometry": {"coordinates":[6.734147,48.448292],"type":"Point"}
}