{
  "type": "Feature",
  "properties": {
    "addr:full":"Rte Du Bancillon 69550 St Jean La Bussi\u00e8re Rhone-Alpes",
    "addr:postcode":"69550",
    "addr:street":"Rte Du Bancillon;La Bussie\u0300Re Rhone-Alpes",
    "iso:country":"FR",
    "sg:address":"Rte Du Bancillon 69550 St Jean La Bussi\u00e8re",
    "sg:classifiers":[
        {
            "category":"Farming",
            "subcategory":"Farm & Veterinary Services",
            "type":"Manufacturing & Wholesale Goods"
        }
    ],
    "sg:phone":"+33 4 74 64 20 77",
    "sg:province":"Rhone-Alpes",
    "sg:tags":[
        "food",
        "product",
        "breeding",
        "animal",
        "related"
    ],
    "wof:name":"Garnier Sa",
    "wof:placetype":"venue"
},
  "geometry": {"coordinates":[4.357305,46.004463],"type":"Point"}
}