{
  "type": "Feature",
  "properties": {
    "iso:country":"FR",
    "sg:address":"Ch\u00e2teau de Chambiers 49430 Durtal",
    "sg:classifiers":[
        {
            "category":"Manufacturing",
            "subcategory":"Paper Products",
            "type":"Manufacturing & Wholesale Goods"
        }
    ],
    "sg:phone":"+33 2 41 76 07 31",
    "sg:postcode":"49430",
    "sg:province":"Pays de Loire",
    "sg:tags":[
        "antique"
    ],
    "wof:name":"Materiaux Anciens Sarl",
    "wof:placetype":"venue"
},
  "geometry": {"coordinates":[-0.247129,47.645134],"type":"Point"}
}