{
  "type": "Feature",
  "properties": {
    "iso:country":"FR",
    "sg:address":"7/9, Rue de Montyon, 75009 Paris",
    "sg:orig_category":"Non-Classified Establishments",
    "sg:phone":"+33 1 48 00 08 63",
    "sg:postcode":"75009",
    "sg:province":"Ile de France",
    "wof:name":"Cades S.a.r.l.",
    "wof:placetype":"venue"
},
  "geometry": {"coordinates":[2.344256,48.872894],"type":"Point"}
}