{
  "type": "Feature",
  "properties": {
    "iso:country":"FR",
    "sg:address":"2 rue Pierre-Henri Spaak 68390 Sausheim",
    "sg:city":"Sausheim",
    "sg:orig_category":"Wind Sleeves",
    "sg:phone":"+33 3 89 31 22 31",
    "sg:postcode":"68390",
    "sg:province":"Alsace",
    "wof:name":"Ttl France Sa",
    "wof:placetype":"venue"
},
  "geometry": {"coordinates":[7.38302,47.779068],"type":"Point"}
}