{
  "type": "Feature",
  "properties": {
    "iso:country":"FR",
    "sg:address":"R Victor Delbove 59770 Marly",
    "sg:classifiers":[
        {
            "category":"Wholesale",
            "subcategory":"Medical Equipment & Supplies",
            "type":"Manufacturing & Wholesale Goods"
        }
    ],
    "sg:phone":"+33 3 27 46 96 57",
    "sg:postcode":"59770",
    "sg:province":"Nord Pas-de-Calais",
    "sg:tags":[
        "instrument",
        "health",
        "-",
        "precision"
    ],
    "wof:name":"Hainaut Prothese Sarl",
    "wof:placetype":"venue"
},
  "geometry": {"coordinates":[3.53937,50.352215],"type":"Point"}
}