{
  "type": "Feature",
  "properties": {
    "iso:country":"FR",
    "sg:address":"1 Chemin Des Granges 01800 Meximieux",
    "sg:classifiers":[
        {
            "category":"Manufacturing",
            "subcategory":"Wood Products",
            "type":"Manufacturing & Wholesale Goods"
        }
    ],
    "sg:phone":"+33 4 74 46 76 67",
    "sg:postcode":"01800",
    "sg:province":"Rhone-Alpes",
    "sg:tags":[
        "professional",
        "furniture"
    ],
    "wof:name":"Ebenisterie Cuisine Agencements (eca)",
    "wof:placetype":"venue"
},
  "geometry": {"coordinates":[5.199951,45.90226],"type":"Point"}
}