{
  "type": "Feature",
  "properties": {
    "addr:full":"285 Rue De Rome 83500 La Seyne Sur Mer Languedoc-Roussillon",
    "addr:housenumber":"285",
    "addr:postcode":"83500",
    "addr:street":"Rue De Rome",
    "iso:country":"FR",
    "sg:address":"285 Rue De Rome 83500 La Seyne Sur Mer",
    "sg:classifiers":[
        {
            "category":"Building & Trades",
            "subcategory":"Construction",
            "type":"Services"
        }
    ],
    "sg:phone":"+33 4 94 10 58 94",
    "sg:province":"Languedoc-Roussillon",
    "sg:tags":[
        "livestock",
        "business",
        "advice",
        "animal",
        "breeding",
        "agriculture"
    ],
    "wof:name":"Bio Veto Tests",
    "wof:placetype":"venue"
},
  "geometry": {"coordinates":[5.851098,43.105892],"type":"Point"}
}