{
  "type": "Feature",
  "properties": {
    "addr:full":"ZI de Krafft Erstein Alsace 67150",
    "addr:postcode":"67150",
    "addr:street":"Zi De Krafft",
    "iso:country":"FR",
    "sg:address":"ZI de Krafft",
    "sg:city":"Erstein",
    "sg:orig_category":"Unclassifiable Establishments",
    "sg:phone":"+33 3 88 98 81 80",
    "sg:postcode":"67150",
    "sg:province":"Alsace",
    "wof:name":"Carrosserie Industrielle Kapp S.a.",
    "wof:placetype":"venue"
},
  "geometry": {"coordinates":[7.66295,48.421101],"type":"Point"}
}