{
  "type": "Feature",
  "properties": {
    "addr:full":"81 Avensan Aquitaine 33480",
    "addr:housenumber":"81",
    "addr:postcode":"33480",
    "addr:street":"Avensan Aquitaine",
    "iso:country":"FR",
    "sg:address":"81",
    "sg:city":"Avensan",
    "sg:classifiers":[
        {
            "category":"Home & Garden",
            "subcategory":"Furniture",
            "type":"Retail Goods"
        }
    ],
    "sg:phone":"+33 5 56 58 16 16",
    "sg:postcode":"33480",
    "sg:province":"Aquitaine",
    "sg:tags":[
        "wood"
    ],
    "wof:name":"Eco Pin",
    "wof:placetype":"venue"
},
  "geometry": {"coordinates":[-0.731199,45.045979],"type":"Point"}
}