{
  "type": "Feature",
  "properties": {
    "addr:full":"21 Cours Xavier Arnozan 33082 Bordeaux Cedex Bordeaux Aquitaine 33100",
    "addr:housenumber":"21",
    "addr:postcode":"33082 bordeaux cedex;33100",
    "addr:street":"Cours Xavier Arnozan",
    "iso:country":"FR",
    "sg:address":"21 Cours Xavier Arnozan 33082 Bordeaux Cedex",
    "sg:city":"Bordeaux",
    "sg:classifiers":[
        {
            "category":"Food Court",
            "type":"Food & Drink"
        }
    ],
    "sg:phone":"+33 5 57 81 18 18",
    "sg:postcode":"33100",
    "sg:province":"Aquitaine",
    "sg:tags":[
        "product",
        "related"
    ],
    "wof:name":"Producta Sa",
    "wof:placetype":"venue"
},
  "geometry": {"coordinates":[-0.571949,44.84919],"type":"Point"}
}