{
  "type": "Feature",
  "properties": {
    "iso:country":"FR",
    "sg:address":"B.P. 100, 09300 Lavelanet C\u00e9dex^^44 bis, Rue du Pasteur, 09300 Lavelanet",
    "sg:orig_category":"Non-Classified Establishments",
    "sg:phone":"+33 5 61 01 33 00",
    "sg:postcode":"09300",
    "sg:province":"Midi Pyr\u00e9n\u00e9es",
    "wof:name":"B.p.p.o.a.a.",
    "wof:placetype":"venue"
},
  "geometry": {"coordinates":[1.83825,42.91959],"type":"Point"}
}