{
  "type": "Feature",
  "properties": {
    "addr:full":"1/12, Av. Laennec, 93380 Pierrefitte sur Seine Ile de France",
    "addr:housenumber":"1 / 12",
    "addr:postcode":"93380",
    "addr:street":"Av. Laennec",
    "iso:country":"FR",
    "sg:address":"1/12, Av. Laennec, 93380 Pierrefitte sur Seine",
    "sg:orig_category":"Non-Classified Establishments",
    "sg:phone":"+33 1 49 40 12 20",
    "sg:province":"Ile de France",
    "wof:name":"S\u00e9gula Industries",
    "wof:placetype":"venue"
},
  "geometry": {"coordinates":[2.370885,48.962181],"type":"Point"}
}