{
  "type": "Feature",
  "properties": {
    "iso:country":"FR",
    "sg:address":"22 rue Cugnot 78570 Chanteloup Les Vignes",
    "sg:classifiers":[
        {
            "category":"Organizations",
            "subcategory":"Professional Association",
            "type":"Services"
        }
    ],
    "sg:phone":"+33 1 39 70 85 02",
    "sg:province":"Ile de France",
    "sg:tags":[
        "renovation",
        "system"
    ],
    "wof:name":"Schinasi International Textile Machines Sas",
    "wof:placetype":"venue"
},
  "geometry": {"coordinates":[2.03466,48.967529],"type":"Point"}
}