{
  "type": "Feature",
  "properties": {
    "iso:country":"FR",
    "sg:address":"7, Traverse Valette, 13009 Marseille",
    "sg:orig_category":"Non-Classified Establishments",
    "sg:phone":"+33 4 91 72 29 43",
    "sg:province":"Provence-Alpes-C\u00f4te d'Azur",
    "wof:name":"Sopec S.a.r.l.",
    "wof:placetype":"venue"
},
  "geometry": {"coordinates":[5.404615,43.234024],"type":"Point"}
}