{
  "type": "Feature",
  "properties": {
    "iso:country":"FR",
    "sg:address":"1",
    "sg:city":"Eglise 60300 Apremont",
    "sg:classifiers":[
        {
            "category":"Manufacturing",
            "subcategory":"Paper Products",
            "type":"Manufacturing & Wholesale Goods"
        }
    ],
    "sg:phone":"+33 3 44 28 01 94",
    "sg:province":"Picardie",
    "sg:tags":[
        "packaging",
        "material",
        "-",
        "cardboard"
    ],
    "wof:name":"Bm Cartonage",
    "wof:placetype":"venue"
},
  "geometry": {"coordinates":[2.510859,49.224087],"type":"Point"}
}