{
  "type": "Feature",
  "properties": {
    "addr:full":"Rte Du Plan De La Tour Zac Du Camp Ferrat 83120 Sainte Maxime Languedoc-Roussillon",
    "addr:postcode":"83120",
    "addr:street":"Rte Du Plan De La Tour Zac Du Camp Ferrat;Maxime",
    "iso:country":"FR",
    "sg:address":"Rte Du Plan De La Tour Zac Du Camp Ferrat 83120 Sainte Maxime",
    "sg:classifiers":[
        {
            "category":"Building & Trades",
            "subcategory":"Construction",
            "type":"Services"
        }
    ],
    "sg:phone":"+33 4 94 49 69 70",
    "sg:province":"Languedoc-Roussillon",
    "sg:tags":[
        "work",
        "public"
    ],
    "wof:name":"Profil 06",
    "wof:placetype":"venue"
},
  "geometry": {"coordinates":[6.607347,43.327271],"type":"Point"}
}