{
  "type": "Feature",
  "properties": {
    "iso:country":"FR",
    "sg:address":"12 Boulevard Des Lices 13200 Arles",
    "sg:classifiers":[
        {
            "category":"Professional",
            "subcategory":"Advertising",
            "type":"Services"
        }
    ],
    "sg:phone":"+33 4 90 18 30 00",
    "sg:province":"Centre",
    "sg:tags":[
        "information",
        "medium",
        "communication"
    ],
    "wof:name":"La Provence",
    "wof:placetype":"venue"
},
  "geometry": {"coordinates":[4.627569,43.675381],"type":"Point"}
}