{
  "type": "Feature",
  "properties": {
    "addr:full":"67, Chemin de Cormeilles, 78400 Chatou Ile de France",
    "addr:housenumber":"67",
    "addr:postcode":"78400",
    "addr:street":"Chemin De Cormeilles;Ile De France",
    "iso:country":"FR",
    "sg:address":"67, Chemin de Cormeilles, 78400 Chatou",
    "sg:orig_category":"Unclassifiable Establishments",
    "sg:phone":"+33 1 39 52 33 00",
    "sg:province":"Ile de France",
    "wof:name":"E.l.m. S.a.r.l. - Espace Location Maintenance",
    "wof:placetype":"venue"
},
  "geometry": {"coordinates":[2.13172,48.911762],"type":"Point"}
}