{
  "type": "Feature",
  "properties": {
    "iso:country":"FR",
    "sg:address":"4 Rue Christophe Colomb 27000 Evreux",
    "sg:classifiers":[
        {
            "category":"Food & Beverages",
            "subcategory":"Meat & Fish",
            "type":"Retail Goods"
        }
    ],
    "sg:phone":"+33 2 32 39 33 48",
    "sg:postcode":"27000",
    "sg:province":"Haute Normandie",
    "sg:tags":[
        "preserve",
        "cooked",
        "product",
        "related"
    ],
    "wof:name":"Au Bon Jambon",
    "wof:placetype":"venue"
},
  "geometry": {"coordinates":[1.174425,49.026913],"type":"Point"}
}