{
  "type": "Feature",
  "properties": {
    "iso:country":"FR",
    "sg:address":"7 Rue Roger Favre 16100 Cognac",
    "sg:classifiers":[
        {
            "category":"Professional",
            "subcategory":"Advertising",
            "type":"Services"
        }
    ],
    "sg:phone":"+33 5 45 36 55 00",
    "sg:postcode":"16100",
    "sg:province":"Poitou-Charentes",
    "sg:tags":[
        "medium",
        "communication",
        "-",
        "paper",
        "packa",
        "cardboard"
    ],
    "wof:name":"Valadie Emballages Sas",
    "wof:placetype":"venue"
},
  "geometry": {"coordinates":[-0.33196,45.699879],"type":"Point"}
}