{
  "type": "Feature",
  "properties": {
    "addr:full":"38 Rue Pierre Brossolette 93330 Neuilly Sur Marne Ile de France 93330",
    "addr:housenumber":"38",
    "addr:postcode":"93330;93330",
    "addr:street":"Rue Pierre Brossolette",
    "iso:country":"FR",
    "sg:address":"38 Rue Pierre Brossolette 93330 Neuilly Sur Marne",
    "sg:classifiers":[
        {
            "category":"Shopping",
            "subcategory":"Clothing, Apparel, & Fashions",
            "type":"Retail Goods"
        }
    ],
    "sg:phone":"+33 1 49 44 70 00",
    "sg:postcode":"93330",
    "sg:province":"Ile de France",
    "sg:tags":[
        "textile",
        "clothing",
        "clothes"
    ],
    "wof:name":"Groupe Inicial Btb Sa",
    "wof:placetype":"venue"
},
  "geometry": {"coordinates":[2.533757,48.855988],"type":"Point"}
}