{
  "type": "Feature",
  "properties": {
    "iso:country":"FR",
    "sg:address":"64, Rue des Fonderies - ZAC des Gouchoux Est, 69220 Saint Jean d'Ardi\u00e8res",
    "sg:orig_category":"Non-Classified Establishments",
    "sg:phone":"+33 4 74 69 68 43",
    "sg:postcode":"69220",
    "sg:province":"Rhone-Alpes",
    "wof:name":"M\u00e9canique G\u00e9n\u00e9rale R. P\u00e9pin",
    "wof:placetype":"venue"
},
  "geometry": {"coordinates":[4.732078,46.120586],"type":"Point"}
}