{
  "type": "Feature",
  "properties": {
    "iso:country":"FR",
    "sg:address":"Zone Artisanale 50750 St Samson De Bonfosse",
    "sg:city":"Canisy",
    "sg:classifiers":[
        {
            "category":"Manufacturing",
            "subcategory":"Printing",
            "type":"Manufacturing & Wholesale Goods"
        }
    ],
    "sg:phone":"+33 2 33 55 92 10",
    "sg:postcode":"50750",
    "sg:province":"Basse Normandie",
    "sg:tags":[
        "publishing"
    ],
    "wof:name":"Normandie Fa\u00c7onnage",
    "wof:placetype":"venue"
},
  "geometry": {"coordinates":[-1.128379,49.048546],"type":"Point"}
}