{
  "type": "Feature",
  "properties": {
    "iso:country":"FR",
    "sg:address":"16 Rue Soubise 93400 Saint Ouen",
    "sg:classifiers":[
        {
            "category":"Manufacturing",
            "subcategory":"Printing",
            "type":"Manufacturing & Wholesale Goods"
        }
    ],
    "sg:phone":"+33 1 49 45 64 15",
    "sg:province":"Ile de France",
    "sg:tags":[
        "publishing"
    ],
    "wof:name":"Imprimerie Nouvelle",
    "wof:placetype":"venue"
},
  "geometry": {"coordinates":[2.331867,48.916054],"type":"Point"}
}