{
  "type": "Feature",
  "properties": {
    "addr:full":"Av. de la Gare Saint Langis l\u00e8s Mortagne Basse Normandie 61400",
    "addr:postcode":"61400",
    "addr:street":"Av. De La Gare Saint;Mortagne;Normandie",
    "iso:country":"FR",
    "sg:address":"Av. de la Gare",
    "sg:city":"Saint Langis l\u00e8s Mortagne",
    "sg:orig_category":"Unclassifiable Establishments",
    "sg:phone":"+33 2 33 85 25 25",
    "sg:postcode":"61400",
    "sg:province":"Basse Normandie",
    "wof:name":"S.n.c.o. S.a. - Soci\u00e9t\u00e9 Normande De Carton Ondul\u00e9",
    "wof:placetype":"venue"
},
  "geometry": {"coordinates":[0.548403,48.512131],"type":"Point"}
}