{
  "type": "Feature",
  "properties": {
    "addr:full":"9, Rue S\u00e9bastien La\u00ef, 13014 Marseille Poitou-Charentes",
    "addr:housenumber":"9",
    "addr:postcode":"13014",
    "addr:street":"Rue Se\u0301Bastien Lai\u0308",
    "iso:country":"FR",
    "sg:address":"9, Rue S\u00e9bastien La\u00ef, 13014 Marseille",
    "sg:orig_category":"Unclassifiable Establishments",
    "sg:phone":"+33 4 95 05 30 30",
    "sg:province":"Poitou-Charentes",
    "wof:name":"A.t.e. S.a. - Automatismes Techniques Equipements",
    "wof:placetype":"venue"
},
  "geometry": {"coordinates":[5.379044,43.321438],"type":"Point"}
}