{
  "type": "Feature",
  "properties": {
    "iso:country":"FR",
    "sg:address":"56 Rue Du Vieux Bourg 69126 Brindas",
    "sg:classifiers":[
        {
            "category":"Bakery",
            "type":"Food & Drink"
        }
    ],
    "sg:phone":"+33 4 78 45 13 24",
    "sg:postcode":"69126",
    "sg:province":"Rhone-Alpes",
    "sg:tags":[
        "cake",
        "product",
        "related",
        "bread"
    ],
    "wof:name":"L'epi Du Ble",
    "wof:placetype":"venue"
},
  "geometry": {"coordinates":[4.694152,45.721432],"type":"Point"}
}