{
  "type": "Feature",
  "properties": {
    "iso:country":"FR",
    "sg:address":"4 Rue Dancourt 77300 Fontainebleau",
    "sg:classifiers":[
        {
            "category":"Manufacturing",
            "subcategory":"Printing",
            "type":"Manufacturing & Wholesale Goods"
        }
    ],
    "sg:phone":"+33 1 64 22 24 39",
    "sg:province":"Ile de France",
    "sg:tags":[
        "publishing"
    ],
    "wof:name":"Photolabo Hassler Sarl",
    "wof:placetype":"venue"
},
  "geometry": {"coordinates":[2.707998,48.410522],"type":"Point"}
}