{
  "type": "Feature",
  "properties": {
    "iso:country":"FR",
    "sg:address":"Rue Pierre Curie 08000 Villers Semeuse",
    "sg:city":"Charleville-M\u00e9zi\u00e8res",
    "sg:classifiers":[
        {
            "category":"Professional",
            "type":"Services"
        }
    ],
    "sg:phone":"+33 3 24 37 67 67",
    "sg:postcode":"08000",
    "sg:province":"Champagne",
    "sg:tags":[
        "transport",
        "road"
    ],
    "wof:name":"Transports Delattre Et Fils Sa",
    "wof:placetype":"venue"
},
  "geometry": {"coordinates":[4.752914,49.748631],"type":"Point"}
}