{
  "type": "Feature",
  "properties": {
    "addr:full":"Rue Bertholet 39100 Dole Franche Comt\u00e9",
    "addr:postcode":"39100",
    "addr:street":"Rue Bertholet;Franche Comte\u0301",
    "iso:country":"FR",
    "sg:address":"Rue Bertholet 39100 Dole",
    "sg:classifiers":[
        {
            "category":"Manufacturing",
            "subcategory":"Paper Products",
            "type":"Manufacturing & Wholesale Goods"
        }
    ],
    "sg:phone":"+33 3 84 72 50 71",
    "sg:province":"Franche Comt\u00e9",
    "sg:tags":[
        "finished",
        "cardboard",
        "-"
    ],
    "wof:name":"Ets Protet Sa",
    "wof:placetype":"venue"
},
  "geometry": {"coordinates":[5.499048,47.112896],"type":"Point"}
}