{
  "type": "Feature",
  "properties": {
    "addr:full":"53, Rue Hauteville, 75010 Paris Ile de France 75010",
    "addr:housenumber":"53",
    "addr:postcode":"75010;75010",
    "addr:street":"Rue Hauteville",
    "iso:country":"FR",
    "sg:address":"53, Rue Hauteville, 75010 Paris",
    "sg:orig_category":"Non-Classified Establishments",
    "sg:phone":"+33 1 44 83 70 18",
    "sg:postcode":"75010",
    "sg:province":"Ile de France",
    "wof:name":"A.r.i.s. S.a.r.l. - Assistance R\u00e9seaux Informatiques Syst\u00e8me",
    "wof:placetype":"venue"
},
  "geometry": {"coordinates":[2.350607,48.87466],"type":"Point"}
}