{
  "type": "Feature",
  "properties": {
    "addr:full":"3 Chemin De Ronde 11300 Limoux Languedoc-Roussillon 11300",
    "addr:housenumber":"3",
    "addr:postcode":"11300;11300",
    "addr:street":"Chemin De Ronde",
    "iso:country":"FR",
    "sg:address":"3 Chemin De Ronde 11300 Limoux",
    "sg:classifiers":[
        {
            "category":"Food Court",
            "type":"Food & Drink"
        }
    ],
    "sg:phone":"+33 4 68 31 01 33",
    "sg:postcode":"11300",
    "sg:province":"Languedoc-Roussillon",
    "sg:tags":[
        "product",
        "related"
    ],
    "wof:name":"Maison Guinot",
    "wof:placetype":"venue"
},
  "geometry": {"coordinates":[2.222316,43.051964],"type":"Point"}
}