{
  "type": "Feature",
  "properties": {
    "addr:full":"ZAC de Recouvrance Saintes Poitou-Charentes 17100",
    "addr:postcode":"17100",
    "addr:street":"Zac De Recouvrance",
    "iso:country":"FR",
    "sg:address":"ZAC de Recouvrance",
    "sg:city":"Saintes",
    "sg:orig_category":"Unclassifiable Establishments",
    "sg:phone":"+33 5 46 93 70 70",
    "sg:postcode":"17100",
    "sg:province":"Poitou-Charentes",
    "wof:name":"Cer 17",
    "wof:placetype":"venue"
},
  "geometry": {"coordinates":[-0.632124,45.747147],"type":"Point"}
}