{
  "type": "Feature",
  "properties": {
    "iso:country":"FR",
    "sg:address":"Route Du Rougadou 13531 ST REMY DE PROVENCE CEDEX",
    "sg:classifiers":[
        {
            "category":"Food & Beverages",
            "subcategory":"Fruits & Vegetables",
            "type":"Retail Goods"
        }
    ],
    "sg:phone":"+33 4 90 92 00 58",
    "sg:province":"Nord Pas-de-Calais",
    "wof:name":"Etablissements Lucchesi Sa",
    "wof:placetype":"venue"
},
  "geometry": {"coordinates":[4.8245,43.789043],"type":"Point"}
}