{
  "type": "Feature",
  "properties": {
    "addr:full":"4, Cour Olivier de Clisson, 44000 Nantes Pays de Loire",
    "addr:housenumber":"4",
    "addr:postcode":"44000",
    "addr:street":"Cour Olivier De Clisson",
    "iso:country":"FR",
    "sg:address":"4, Cour Olivier de Clisson, 44000 Nantes",
    "sg:orig_category":"Unclassifiable Establishments",
    "sg:phone":"+33 2 40 47 50 44",
    "sg:province":"Pays de Loire",
    "wof:name":"Balances Saupin S.a.r.l.",
    "wof:placetype":"venue"
},
  "geometry": {"coordinates":[-1.554769,47.213287],"type":"Point"}
}