{
  "type": "Feature",
  "properties": {
    "iso:country":"FR",
    "sg:address":"ZI Sainte Marie des Champs",
    "sg:city":"Yvetot",
    "sg:orig_category":"Unclassifiable Establishments",
    "sg:phone":"+33 2 35 95 96 96",
    "sg:postcode":"76190",
    "sg:province":"Haute Normandie",
    "wof:name":"Nordon Et Compagnie S.a.",
    "wof:placetype":"venue"
},
  "geometry": {"coordinates":[0.75448,49.616741],"type":"Point"}
}