{
  "type": "Feature",
  "properties": {
    "iso:country":"FR",
    "sg:address":"Route De Spay 72700 Allonnes",
    "sg:classifiers":[
        {
            "category":"Manufacturing",
            "subcategory":"Motor Vehicles & Parts",
            "type":"Manufacturing & Wholesale Goods"
        }
    ],
    "sg:phone":"+33 2 43 39 21 50",
    "sg:postcode":"72700",
    "sg:province":"Pays de Loire",
    "sg:tags":[
        "engine",
        "machine",
        "engineering",
        "-",
        "mechanical"
    ],
    "wof:name":"Moteurs Leroy Somer",
    "wof:placetype":"venue"
},
  "geometry": {"coordinates":[0.159155,47.942692],"type":"Point"}
}