{
  "type": "Feature",
  "properties": {
    "iso:country":"FR",
    "sg:address":"7 Rue Denis Papin 94854 Ivry Sur Seine Cede",
    "sg:classifiers":[
        {
            "category":"Manufacturing",
            "subcategory":"Tools & Machinery",
            "type":"Manufacturing & Wholesale Goods"
        }
    ],
    "sg:phone":"+33 1 46 72 56 20",
    "sg:province":"Franche Comt\u00e9",
    "sg:tags":[
        "equipment",
        "measurement",
        "-",
        "precision",
        "instrument"
    ],
    "wof:name":"Sade Compagnie Generale De Travaux D'hydraulique",
    "wof:placetype":"venue"
},
  "geometry": {"coordinates":[2.37467,48.807781],"type":"Point"}
}