{
  "type": "Feature",
  "properties": {
    "iso:country":"FR",
    "sg:address":"6, Rue Barth\u00e9l\u00e9my Thimonier - C.E. Nord, 01000 Bourg en Bresse",
    "sg:orig_category":"Unclassifiable Establishments",
    "sg:phone":"+33 4 74 23 34 51",
    "sg:postcode":"01000",
    "sg:province":"Rhone-Alpes",
    "wof:name":"Carrier Transicold France S.a.",
    "wof:placetype":"venue"
},
  "geometry": {"coordinates":[5.221494,46.218323],"type":"Point"}
}