{
  "type": "Feature",
  "properties": {
    "addr:full":"Rue de la Pommeraye Saint Laurent du Mottay Pays de Loire 49410",
    "addr:postcode":"49410",
    "addr:street":"Rue De La Pommeraye",
    "iso:country":"FR",
    "sg:address":"Rue de la Pommeraye",
    "sg:city":"Saint Laurent du Mottay",
    "sg:orig_category":"Unclassifiable Establishments",
    "sg:phone":"+33 2 41 78 53 62",
    "sg:postcode":"49410",
    "sg:province":"Pays de Loire",
    "wof:name":"Socap S.a.",
    "wof:placetype":"venue"
},
  "geometry": {"coordinates":[-0.927774,47.320755],"type":"Point"}
}