{
  "type": "Feature",
  "properties": {
    "iso:country":"FR",
    "sg:address":"632, Rue de Malitorne - ZI, 18230 Saint Doulchard",
    "sg:city":"Saint-Doulchard",
    "sg:orig_category":"Unclassifiable Establishments",
    "sg:phone":"+33 2 48 70 15 38",
    "sg:postcode":"18230",
    "sg:province":"Centre",
    "wof:name":"Berry - Froid S.a.r.l.",
    "wof:placetype":"venue"
},
  "geometry": {"coordinates":[2.35792,47.104084],"type":"Point"}
}