{
  "type": "Feature",
  "properties": {
    "iso:country":"FR",
    "sg:address":"5, Rue Cugnot, 66000 Perpignan",
    "sg:orig_category":"Non-Classified Establishments",
    "sg:phone":"+33 4 68 55 55 11",
    "sg:postcode":"66000",
    "sg:province":"Languedoc-Roussillon",
    "wof:name":"C.e.b.t.p. S.a. - Centre D'expertise Du B\u00e2timent Et Des Travaux Publics",
    "wof:placetype":"venue"
},
  "geometry": {"coordinates":[2.871629,42.696388],"type":"Point"}
}