{
  "type": "Feature",
  "properties": {
    "iso:country":"FR",
    "sg:address":"146 avenue des Etats-Unis 31200 Toulouse",
    "sg:classifiers":[
        {
            "category":"Food & Beverages",
            "subcategory":"Fruits & Vegetables",
            "type":"Retail Goods"
        }
    ],
    "sg:phone":"+33 5 61 13 30 00",
    "sg:postcode":"31200",
    "sg:province":"Midi Pyr\u00e9n\u00e9es",
    "wof:name":"Eugenie Fruits S.a.r.l.",
    "wof:placetype":"venue"
},
  "geometry": {"coordinates":[1.430138,43.637642],"type":"Point"}
}