{
  "type": "Feature",
  "properties": {
    "addr:full":"33 rue des Vanesses 93420 Villepinte Ile de France",
    "addr:housenumber":"33",
    "addr:postcode":"93420",
    "addr:street":"Rue Des Vanesses;Ile De France",
    "iso:country":"FR",
    "sg:address":"33 rue des Vanesses 93420 Villepinte",
    "sg:classifiers":[
        {
            "category":"Military Area",
            "subcategory":"Air Force Base",
            "type":"Public Place"
        }
    ],
    "sg:phone":"+33 1 49 38 04 67",
    "sg:province":"Ile de France",
    "sg:tags":[
        "system",
        "integration"
    ],
    "wof:name":"Infodis S.a.",
    "wof:placetype":"venue"
},
  "geometry": {"coordinates":[2.505738,48.974586],"type":"Point"}
}