{
  "type": "Feature",
  "properties": {
    "addr:full":"19/23, Bd des Varennes, 51700 Dormans Champagne",
    "addr:housenumber":"19 / 23",
    "addr:postcode":"51700",
    "addr:street":"Bd Des Varennes",
    "iso:country":"FR",
    "sg:address":"19/23, Bd des Varennes, 51700 Dormans",
    "sg:orig_category":"Non-Classified Establishments",
    "sg:phone":"+33 3 26 58 21 61",
    "sg:province":"Champagne",
    "wof:name":"Soci\u00e9t\u00e9 Des Etablissements Rennepont S.a.r.l.",
    "wof:placetype":"venue"
},
  "geometry": {"coordinates":[3.642336,49.079063],"type":"Point"}
}