{
  "type": "Feature",
  "properties": {
    "iso:country":"FR",
    "sg:address":"B.P. 39",
    "sg:city":"Andilly",
    "sg:orig_category":"Non-Classified Establishments",
    "sg:phone":"+33 1 30 10 60 20",
    "sg:postcode":"95580",
    "sg:province":"Ile de France",
    "wof:name":"Straub S.a.",
    "wof:placetype":"venue"
},
  "geometry": {"coordinates":[2.29798,49.004433],"type":"Point"}
}