{
  "type": "Feature",
  "properties": {
    "iso:country":"FR",
    "sg:address":"Route De Bordeaux 33112 St Laurent Medoc",
    "sg:city":"Saint-Laurent-M\u00e9doc",
    "sg:classifiers":[
        {
            "category":"Farming",
            "subcategory":"Farm & Veterinary Services",
            "type":"Manufacturing & Wholesale Goods"
        }
    ],
    "sg:phone":"+33 5 56 59 46 91",
    "sg:postcode":"33112",
    "sg:province":"Aquitaine",
    "sg:tags":[
        "advice",
        "agriculture",
        "livestock",
        "business"
    ],
    "wof:name":"Generation Bois",
    "wof:placetype":"venue"
},
  "geometry": {"coordinates":[-0.821959,45.150249],"type":"Point"}
}