{
  "type": "Feature",
  "properties": {
    "iso:country":"FR",
    "sg:address":"Rue des Fr\u00e8res Morane - Fief du Roy",
    "sg:city":"Ch\u00e2teaubernard",
    "sg:orig_category":"Non-Classified Establishments",
    "sg:phone":"+33 5 45 35 46 02",
    "sg:postcode":"16100",
    "sg:province":"Poitou-Charentes",
    "wof:name":"Prestations Du Fief S.a.r.l.",
    "wof:placetype":"venue"
},
  "geometry": {"coordinates":[-0.313384,45.67149],"type":"Point"}
}