{
  "type": "Feature",
  "properties": {
    "addr:full":"318 rue Mar\u00e9chal Foch 42153 Riorges Rhone-Alpes 42153",
    "addr:housenumber":"318",
    "addr:postcode":"42153;42153",
    "addr:street":"Rue Mare\u0301Chal Foch;Rhone-Alpes",
    "iso:country":"FR",
    "sg:address":"318 rue Mar\u00e9chal Foch 42153 Riorges",
    "sg:orig_category":"Ladies' Knitwear",
    "sg:phone":"+33 4 77 70 57 77",
    "sg:postcode":"42153",
    "sg:province":"Rhone-Alpes",
    "wof:name":"Paul Rhodamel Sa",
    "wof:placetype":"venue"
},
  "geometry": {"coordinates":[4.048648,46.039829],"type":"Point"}
}