{
  "type": "Feature",
  "properties": {
    "iso:country":"FR",
    "sg:address":"24, Rue de la Gare, 78370 Plaisir",
    "sg:orig_category":"Unclassifiable Establishments",
    "sg:phone":"+33 1 30 79 22 35",
    "sg:province":"Ile de France",
    "wof:name":"A.g.n. Partners S.a.",
    "wof:placetype":"venue"
},
  "geometry": {"coordinates":[1.943418,48.829304],"type":"Point"}
}