{
  "type": "Feature",
  "properties": {
    "addr:full":"41, Rue Jean Jaur\u00e8s - Zone Industrielle, 10600 La Chapelle Saint Luc Champagne",
    "addr:housenumber":"41",
    "addr:postcode":"10600",
    "addr:street":"Rue Jean Jaure\u0300S Zone Industrielle",
    "iso:country":"FR",
    "sg:address":"41, Rue Jean Jaur\u00e8s - Zone Industrielle, 10600 La Chapelle Saint Luc",
    "sg:orig_category":"Unclassifiable Establishments",
    "sg:phone":"+33 800 87 78 77",
    "sg:province":"Champagne",
    "wof:name":"U.p.s. Transports S.a.",
    "wof:placetype":"venue"
},
  "geometry": {"coordinates":[4.032522,48.314156],"type":"Point"}
}