{
  "type": "Feature",
  "properties": {
    "iso:country":"FR",
    "sg:address":"41, Rue Jean Jaur\u00e8s - Zone Industrielle, 10600 La Chapelle Saint Luc",
    "sg:orig_category":"Unclassifiable Establishments",
    "sg:phone":"+33 800 87 78 77",
    "sg:province":"Champagne",
    "wof:name":"U.p.s. Transports S.a.",
    "wof:placetype":"venue"
},
  "geometry": {"coordinates":[4.032522,48.314156],"type":"Point"}
}