{
  "type": "Feature",
  "properties": {
    "addr:full":"Pard d'Activit\u00e9s Porte Sud Pont Saint Esprit Languedoc-Roussillon 30130",
    "addr:postcode":"30130",
    "addr:street":"Saint",
    "iso:country":"FR",
    "sg:address":"Pard d'Activit\u00e9s Porte Sud",
    "sg:city":"Pont Saint Esprit",
    "sg:orig_category":"Unclassifiable Establishments",
    "sg:phone":"+33 4 66 39 61 40",
    "sg:postcode":"30130",
    "sg:province":"Languedoc-Roussillon",
    "wof:name":"M.a.t.i. 30 S.a.r.l. - M\u00e9canique Assistance Technique Industrielle",
    "wof:placetype":"venue"
},
  "geometry": {"coordinates":[4.639614,44.242882],"type":"Point"}
}