{
  "type": "Feature",
  "properties": {
    "iso:country":"FR",
    "sg:address":"53, Rue du G\u00e9n\u00e9ral Metman, 57070 Metz",
    "sg:orig_category":"Non-Classified Establishments",
    "sg:phone":"+33 3 87 74 16 83",
    "sg:province":"Lorraine",
    "wof:name":"Wiedemann Jasalu S.a.",
    "wof:placetype":"venue"
},
  "geometry": {"coordinates":[6.211894,49.12019],"type":"Point"}
}