{
  "type": "Feature",
  "properties": {
    "addr:full":"24, Av. de la Sardagne, 74300 Cluses Rhone-Alpes",
    "addr:postcode":"74300",
    "addr:street":"24 Av. De La Sardagne",
    "iso:country":"FR",
    "sg:address":"24, Av. de la Sardagne, 74300 Cluses",
    "sg:orig_category":"Non-Classified Establishments",
    "sg:phone":"+33 4 50 98 24 18",
    "sg:province":"Rhone-Alpes",
    "wof:name":"Rectification Forestier Andr\u00e9",
    "wof:placetype":"venue"
},
  "geometry": {"coordinates":[6.564173,46.069813],"type":"Point"}
}