{
  "type": "Feature",
  "properties": {
    "addr:full":"9, Rue de la Mairie, 28500 Saulni\u00e8res Saulni\u00e8res Centre 28500",
    "addr:housenumber":"9;saulnie\u0300res",
    "addr:postcode":"28500;28500",
    "addr:street":"Rue De La Mairie",
    "iso:country":"FR",
    "sg:address":"9, Rue de la Mairie, 28500 Saulni\u00e8res",
    "sg:city":"Saulni\u00e8res",
    "sg:orig_category":"Unclassifiable Establishments",
    "sg:phone":"+33 2 37 38 65 00",
    "sg:postcode":"28500",
    "sg:province":"Centre",
    "wof:name":"Fonderie Technique De Saulni\u00e8re S.a.r.l.",
    "wof:placetype":"venue"
},
  "geometry": {"coordinates":[1.274287,48.658222],"type":"Point"}
}