{
  "type": "Feature",
  "properties": {
    "addr:full":"B.P. 1, 49123 Champtoc\u00e9 sur Loire C\u00e9dex^^Rte de Montjean, 49123 Champtoc\u00e9 sur Loire Pays de Loire",
    "addr:housenumber":"1",
    "addr:postcode":"49123;49123",
    "addr:street":"B.P.;Champtoce\u0301;Loire",
    "iso:country":"FR",
    "sg:address":"B.P. 1, 49123 Champtoc\u00e9 sur Loire C\u00e9dex^^Rte de Montjean, 49123 Champtoc\u00e9 sur Loire",
    "sg:orig_category":"Non-Classified Establishments",
    "sg:phone":"+33 2 41 22 90 00",
    "sg:province":"Pays de Loire",
    "wof:name":"P.c.m. - Pompes Compresseurs M\u00e9canique",
    "wof:placetype":"venue"
},
  "geometry": {"coordinates":[-0.922474,47.404785],"type":"Point"}
}