{
  "type": "Feature",
  "properties": {
    "iso:country":"FR",
    "sg:address":"13, Rue de Belfort, 35000 Rennes",
    "sg:city":"Rennes",
    "sg:orig_category":"Unclassifiable Establishments",
    "sg:phone":"+33 2 99 36 28 29",
    "sg:postcode":"35000",
    "sg:province":"Bretagne",
    "wof:name":"Centre De Tarification Pharmaceutique S.a.",
    "wof:placetype":"venue"
},
  "geometry": {"coordinates":[-1.667139,48.111111],"type":"Point"}
}