{
  "type": "Feature",
  "properties": {
    "addr:full":"Rue Albert Camus 59540 Caudry Nord Pas-de-Calais 59540",
    "addr:postcode":"59540;59540",
    "addr:street":"Rue Albert Camus",
    "iso:country":"FR",
    "sg:address":"Rue Albert Camus 59540 Caudry",
    "sg:classifiers":[
        {
            "category":"Travel",
            "subcategory":"Hotels & Motels",
            "type":"Entertainment"
        }
    ],
    "sg:phone":"+33 3 27 85 47 72",
    "sg:postcode":"59540",
    "sg:province":"Nord Pas-de-Calais",
    "sg:tags":[
        "hotels",
        "business",
        "restaurant"
    ],
    "wof:name":"Avenance",
    "wof:placetype":"venue"
},
  "geometry": {"coordinates":[3.417603,50.128712],"type":"Point"}
}