{
  "type": "Feature",
  "properties": {
    "iso:country":"FR",
    "sg:address":"34 Rue Clarisse 59320 Haubourdin",
    "sg:classifiers":[
        {
            "category":"Shopping",
            "subcategory":"Clothing, Apparel, & Fashions",
            "type":"Retail Goods"
        }
    ],
    "sg:phone":"+33 3 20 07 30 83",
    "sg:postcode":"59320",
    "sg:province":"Nord Pas-de-Calais",
    "sg:tags":[
        "textile",
        "clothing",
        "clothes"
    ],
    "wof:name":"Rohart Marie",
    "wof:placetype":"venue"
},
  "geometry": {"coordinates":[2.98103,50.612339],"type":"Point"}
}