{
  "type": "Feature",
  "properties": {
    "iso:country":"FR",
    "sg:address":"B.P. 9268, 95078 Cergy Pontoise C\u00e9dex^^Av. de la Mare - ZA des B\u00e9thunes, 95310 Saint Ouen l'Aum\u00f4ne",
    "sg:orig_category":"Non-Classified Establishments",
    "sg:phone":"+33 1 34 64 94 95",
    "sg:province":"Ile de France",
    "wof:name":"P.i.e. S.a.r.l. - Pr\u00e9sence International Ev\u00e8nement",
    "wof:placetype":"venue"
},
  "geometry": {"coordinates":[3.183886,48.91972],"type":"Point"}
}