{
  "type": "Feature",
  "properties": {
    "addr:full":"258 Rue Pierre De Roubaix 59100 Roubaix Nord Pas-de-Calais 59100",
    "addr:housenumber":"258",
    "addr:postcode":"59100;59100",
    "addr:street":"Rue Pierre De Roubaix",
    "iso:country":"FR",
    "sg:address":"258 Rue Pierre De Roubaix 59100 Roubaix",
    "sg:classifiers":[
        {
            "category":"Manufacturing",
            "subcategory":"Metals",
            "type":"Manufacturing & Wholesale Goods"
        }
    ],
    "sg:phone":"+33 3 20 75 82 88",
    "sg:postcode":"59100",
    "sg:province":"Nord Pas-de-Calais",
    "sg:tags":[
        "metallurgy",
        "steel",
        "metalworking"
    ],
    "wof:name":"Hw Sa",
    "wof:placetype":"venue"
},
  "geometry": {"coordinates":[3.191082,50.685982],"type":"Point"}
}