{
  "type": "Feature",
  "properties": {
    "addr:full":"24 Rue De Belfort 94700 Maisons Alfort Ile de France 94700",
    "addr:housenumber":"24",
    "addr:postcode":"94700;94700",
    "addr:street":"Rue De Belfort",
    "iso:country":"FR",
    "sg:address":"24 Rue De Belfort 94700 Maisons Alfort",
    "sg:classifiers":[
        {
            "category":"Manufacturing",
            "subcategory":"Metals",
            "type":"Manufacturing & Wholesale Goods"
        }
    ],
    "sg:phone":"+33 1 43 75 32 33",
    "sg:postcode":"94700",
    "sg:province":"Ile de France",
    "sg:tags":[
        "-",
        "machine",
        "equipment",
        "engineering",
        "machinery",
        "mechanical"
    ],
    "wof:name":"La Scie Industrielle Groux",
    "wof:placetype":"venue"
},
  "geometry": {"coordinates":[2.436844,48.793251],"type":"Point"}
}