{
  "type": "Feature",
  "properties": {
    "iso:country":"FR",
    "sg:address":"B.P. 44, 56190 Arzal C\u00e9dex^^ZA de la Corne du Cerf, 56190 Arzal",
    "sg:city":"Arzal",
    "sg:orig_category":"Non-Classified Establishments",
    "sg:phone":"+33 2 97 45 07 07",
    "sg:postcode":"56190",
    "sg:province":"Bretagne",
    "wof:name":"S.m.a. S.a. - Soci\u00e9t\u00e9 De Mat\u00e9riel Alimentaire",
    "wof:placetype":"venue"
},
  "geometry": {"coordinates":[-2.379094,47.50161],"type":"Point"}
}