{
  "type": "Feature",
  "properties": {
    "iso:country":"FR",
    "sg:address":"1 r Francois Cadoret; Riec sur B\u00e9lon; 29340",
    "sg:city":"Riec-sur-Belon",
    "sg:classifiers":[
        {
            "category":"Banks & Credit Unions",
            "subcategory":"Bank",
            "type":"Services"
        }
    ],
    "sg:phone":"+33 2 98 06 92 53",
    "sg:postcode":"29340",
    "sg:province":"Bretagne",
    "wof:name":"Cr\u00e9dit Mutuel De Bretagne",
    "wof:placetype":"venue"
},
  "geometry": {"coordinates":[-3.693285,47.843105],"type":"Point"}
}