{
  "type": "Feature",
  "properties": {
    "addr:full":"240 rue de Rivoli; Paris; 75009 Ile de France 75009",
    "addr:housenumber":"240",
    "addr:postcode":"75009 ile;france 75009",
    "addr:street":"Rue De Rivoli",
    "iso:country":"FR",
    "sg:address":"240 rue de Rivoli; Paris; 75009",
    "sg:classifiers":[
        {
            "category":"Banks & Credit Unions",
            "subcategory":"Bank",
            "type":"Services"
        }
    ],
    "sg:phone":"+33 1 42 60 38 81",
    "sg:postcode":"75009",
    "sg:province":"Ile de France",
    "wof:name":"Banca D'italia",
    "wof:placetype":"venue"
},
  "geometry": {"coordinates":[2.325872,48.865887],"type":"Point"}
}