{
  "type": "Feature",
  "properties": {
    "iso:country":"FR",
    "sg:address":"B.P. 2154, 31200 Toulouse C\u00e9dex^^30, Av. de Fondeyre, 31200 Toulouse",
    "sg:orig_category":"Non-Classified Establishments",
    "sg:phone":"+33 5 61 13 57 11",
    "sg:province":"Midi Pyr\u00e9n\u00e9es",
    "wof:name":"S.t.c.m. S.a. - Soci\u00e9t\u00e9 Traitement Chimique M\u00e9taux",
    "wof:placetype":"venue"
},
  "geometry": {"coordinates":[1.44954,43.639011],"type":"Point"}
}