{
  "type": "Feature",
  "properties": {
    "iso:country":"FR",
    "sg:address":"44 B Rue Du Chemin Vert 78610 Le Perray En Yvelines",
    "sg:classifiers":[
        {
            "category":"Home & Garden",
            "subcategory":"Furniture",
            "type":"Retail Goods"
        }
    ],
    "sg:phone":"+33 1 34 84 25 50",
    "sg:postcode":"78610",
    "sg:province":"Ile de France",
    "sg:tags":[
        "professional",
        "household",
        "wood"
    ],
    "wof:name":"Sarl Mg",
    "wof:placetype":"venue"
},
  "geometry": {"coordinates":[1.857338,48.702976],"type":"Point"}
}