{
  "type": "Feature",
  "properties": {
    "iso:country":"FR",
    "sg:address":"B.P. 70439, 57105 Thionville C\u00e9dex^^50, Rte de la Digue, 57100 Thionville",
    "sg:orig_category":"Non-Classified Establishments",
    "sg:phone":"+33 3 82 88 62 62",
    "sg:province":"Lorraine",
    "wof:name":"S.a.d. S.a. - Soci\u00e9t\u00e9 D'application Diesel",
    "wof:placetype":"venue"
},
  "geometry": {"coordinates":[6.16909,49.357601],"type":"Point"}
}