{
  "type": "Feature",
  "properties": {
    "addr:full":"55, Rue B\u00e9rard, 01500 Amb\u00e9rieu en Bugey Rhone-Alpes 01500",
    "addr:housenumber":"55",
    "addr:postcode":"01500;01500",
    "addr:street":"Rue Be\u0301Rard",
    "iso:country":"FR",
    "sg:address":"55, Rue B\u00e9rard, 01500 Amb\u00e9rieu en Bugey",
    "sg:orig_category":"Unclassifiable Establishments",
    "sg:phone":"+33 4 74 38 41 54",
    "sg:postcode":"01500",
    "sg:province":"Rhone-Alpes",
    "wof:name":"B.p.f.c.m.a. S.a. - Banque Populaire De Franche-comt\u00e9, Du M\u00e2connais Et De L'ain",
    "wof:placetype":"venue"
},
  "geometry": {"coordinates":[5.342773,45.970695],"type":"Point"}
}