{
  "type": "Feature",
  "properties": {
    "iso:country":"FR",
    "sg:address":"8, Rue du March\u00e9, 67000 Strasbourg",
    "sg:city":"Strasbourg",
    "sg:orig_category":"Non-Classified Establishments",
    "sg:phone":"+33 3 88 32 22 65",
    "sg:postcode":"67000",
    "sg:province":"Alsace",
    "wof:name":"Coelis S.a.",
    "wof:placetype":"venue"
},
  "geometry": {"coordinates":[7.743262,48.584534],"type":"Point"}
}