{
  "type": "Feature",
  "properties": {
    "iso:country":"FR",
    "sg:address":"122 Avenue Des Champs Elysees 75008 Paris",
    "sg:classifiers":[
        {
            "category":"Professional",
            "subcategory":"Printing & Photocopies",
            "type":"Services"
        }
    ],
    "sg:phone":"+33 1 56 88 88 88",
    "sg:province":"Ile de France",
    "sg:tags":[
        "publishing"
    ],
    "wof:name":"Studio Magazine",
    "wof:placetype":"venue"
},
  "geometry": {"coordinates":[2.299896,48.872292],"type":"Point"}
}