{
  "type": "Feature",
  "properties": {
    "addr:full":"20 RUE CLAUDE BERNARD 78310 MAUREPAS Ile de France 78310",
    "addr:housenumber":"20",
    "addr:postcode":"78310;ile;78310",
    "addr:street":"Rue Claude Bernard;France",
    "iso:country":"FR",
    "sg:address":"20 RUE CLAUDE BERNARD 78310 MAUREPAS",
    "sg:classifiers":[
        {
            "category":"Manufacturing",
            "subcategory":"Metals",
            "type":"Manufacturing & Wholesale Goods"
        }
    ],
    "sg:phone":"+33 1 30 49 29 29",
    "sg:postcode":"78310",
    "sg:province":"Ile de France",
    "sg:tags":[
        "alloy",
        "aluminium"
    ],
    "wof:name":"Ampco M\u00e9tal France Sa",
    "wof:placetype":"venue"
},
  "geometry": {"coordinates":[1.925081,48.761768],"type":"Point"}
}