{
  "type": "Feature",
  "properties": {
    "addr:full":"Le Folu Zi Des 2 B 82370 La Bastide Saint Pierre Midi Pyr\u00e9n\u00e9es",
    "addr:housenumber":"b",
    "addr:postcode":"82370",
    "addr:street":"Des 2",
    "iso:country":"FR",
    "sg:address":"Le Folu Zi Des 2 B 82370 La Bastide Saint Pierre",
    "sg:classifiers":[
        {
            "category":"Manufacturing",
            "subcategory":"Rubber & Plastics",
            "type":"Manufacturing & Wholesale Goods"
        }
    ],
    "sg:phone":"+33 5 63 25 12 02",
    "sg:province":"Midi Pyr\u00e9n\u00e9es",
    "wof:name":"Saliens Industrie",
    "wof:placetype":"venue"
},
  "geometry": {"coordinates":[-100.36507400000001,44.377945],"type":"Point"}
}