{
  "type": "Feature",
  "properties": {
    "addr:full":"4075 Rue Lys 62840 Sailly Sur La Lys Nord Pas-de-Calais 62840",
    "addr:housenumber":"4075",
    "addr:postcode":"62840;62840",
    "addr:street":"Rue Lys",
    "iso:country":"FR",
    "sg:address":"4075 Rue Lys 62840 Sailly Sur La Lys",
    "sg:classifiers":[
        {
            "category":"Manufacturing",
            "subcategory":"Textiles",
            "type":"Manufacturing & Wholesale Goods"
        }
    ],
    "sg:phone":"+33 3 21 63 16 16",
    "sg:postcode":"62840",
    "sg:province":"Nord Pas-de-Calais",
    "sg:tags":[
        "printing",
        "clothing",
        "fabric"
    ],
    "wof:name":"Sonolys Sarl",
    "wof:placetype":"venue"
},
  "geometry": {"coordinates":[2.786013,50.661915],"type":"Point"}
}