{
  "type": "Feature",
  "properties": {
    "addr:full":"38, Rue des Jeuneurs, 75081 Paris C\u00e9dex 2 Haute Normandie",
    "addr:housenumber":"38;2",
    "addr:postcode":"75081",
    "addr:street":"Rue Des Jeuneurs;Haute Normandie",
    "iso:country":"FR",
    "sg:address":"38, Rue des Jeuneurs, 75081 Paris C\u00e9dex 2",
    "sg:orig_category":"Non-Classified Establishments",
    "sg:phone":"+33 1 44 76 64 00",
    "sg:province":"Haute Normandie",
    "wof:name":"Rousseau S.a.",
    "wof:placetype":"venue"
},
  "geometry": {"coordinates":[2.344115,48.869812],"type":"Point"}
}