{
  "type": "Feature",
  "properties": {
    "addr:full":"1483, Rte de Paris, 76520 Franqueville Saint Pierre Haute Normandie",
    "addr:housenumber":"1483",
    "addr:postcode":"76520",
    "addr:street":"Rte De Paris",
    "iso:country":"FR",
    "sg:address":"1483, Rte de Paris, 76520 Franqueville Saint Pierre",
    "sg:orig_category":"Unclassifiable Establishments",
    "sg:phone":"+33 2 35 80 20 50",
    "sg:province":"Haute Normandie",
    "wof:name":"Duex S.a.r.l.",
    "wof:placetype":"venue"
},
  "geometry": {"coordinates":[1.159325,49.402714],"type":"Point"}
}