{
  "type": "Feature",
  "properties": {
    "iso:country":"FR",
    "sg:address":"ZA du Caintin",
    "sg:city":"La Ricamarie",
    "sg:orig_category":"Unclassifiable Establishments",
    "sg:phone":"+33 4 77 59 91 92",
    "sg:postcode":"42150",
    "sg:province":"Rhone-Alpes",
    "wof:name":"Ferrapie Transport Affr\u00eatement S.a.",
    "wof:placetype":"venue"
},
  "geometry": {"coordinates":[4.36615,45.40406],"type":"Point"}
}