{
  "type": "Feature",
  "properties": {
    "addr:full":"98, Rue Louis Amp\u00e8re - ZI Les Chanoux, 93330 Neuilly sur Marne Ile de France",
    "addr:housenumber":"98",
    "addr:postcode":"93330",
    "addr:street":"Rue Louis Ampe\u0300Re Zi Les Chanoux",
    "iso:country":"FR",
    "sg:address":"98, Rue Louis Amp\u00e8re - ZI Les Chanoux, 93330 Neuilly sur Marne",
    "sg:orig_category":"Unclassifiable Establishments",
    "sg:phone":"+33 1 49 44 88 10",
    "sg:province":"Ile de France",
    "wof:name":"A.m.f. S.a.",
    "wof:placetype":"venue"
},
  "geometry": {"coordinates":[2.52871,48.857376],"type":"Point"}
}