{
  "type": "Feature",
  "properties": {
    "iso:country":"FR",
    "sg:address":"29, Rue du Mar\u00e9chal Foch, 78000 Versailles",
    "sg:orig_category":"Unclassifiable Establishments",
    "sg:phone":"+33 1 39 07 48 00",
    "sg:province":"Ile de France",
    "wof:name":"A.3.x.x. S.a.",
    "wof:placetype":"venue"
},
  "geometry": {"coordinates":[2.132364,48.807556],"type":"Point"}
}