{
  "type": "Feature",
  "properties": {
    "iso:country":"FR",
    "sg:address":"21, Rue de l'Industrie - ZI, 67720 Hoerdt",
    "sg:city":"Hoerdt",
    "sg:orig_category":"Unclassifiable Establishments",
    "sg:phone":"+33 3 88 69 20 02",
    "sg:postcode":"67720",
    "sg:province":"Alsace",
    "wof:name":"Julie Guerlande S.a.",
    "wof:placetype":"venue"
},
  "geometry": {"coordinates":[7.795894,48.676208],"type":"Point"}
}