{
  "type": "Feature",
  "properties": {
    "addr:full":"89, Rue du Gouverneur G\u00e9n\u00e9ral Ebou\u00e9, 92130 Issy les Moulineaux Ile de France",
    "addr:housenumber":"89",
    "addr:postcode":"92130",
    "addr:street":"Rue Du Gouverneur Ge\u0301Ne\u0301Ral Eboue\u0301",
    "iso:country":"FR",
    "sg:address":"89, Rue du Gouverneur G\u00e9n\u00e9ral Ebou\u00e9, 92130 Issy les Moulineaux",
    "sg:orig_category":"Unclassifiable Establishments",
    "sg:phone":"+33 1 46 29 37 00",
    "sg:province":"Ile de France",
    "wof:name":"I.f. S.a. - Imagerie Fran\u00e7aise",
    "wof:placetype":"venue"
},
  "geometry": {"coordinates":[2.264567,48.824329],"type":"Point"}
}