{
  "type": "Feature",
  "properties": {
    "addr:full":"69191 Saint Fons C\u00e9dex^^Av. Ramboz - Usine de Belle Etoile Saint Fons Rhone-Alpes 69190",
    "addr:housenumber":"69191",
    "addr:postcode":"69190",
    "addr:street":"Saint Fons Ce\u0301Dex^^Av Ramboz Usine De Belle Etoile Saint Fons Rhone-Alpes",
    "iso:country":"FR",
    "sg:address":"69191 Saint Fons C\u00e9dex^^Av. Ramboz - Usine de Belle Etoile",
    "sg:city":"Saint Fons",
    "sg:orig_category":"Non-Classified Establishments",
    "sg:phone":"+33 4 72 73 95 00",
    "sg:postcode":"69190",
    "sg:province":"Rhone-Alpes",
    "wof:name":"Rhodia Polyamide Interm\u00e9diaire S.a.",
    "wof:placetype":"venue"
},
  "geometry": {"coordinates":[4.843304,45.694775],"type":"Point"}
}