{
  "type": "Feature",
  "properties": {
    "addr:full":"Fontan 31370 B\u00e9rat Midi Pyr\u00e9n\u00e9es",
    "addr:postcode":"31370",
    "iso:country":"FR",
    "sg:address":"Fontan 31370 B\u00e9rat",
    "sg:orig_category":"Unclassifiable Establishments",
    "sg:phone":"+33 5 61 91 04 24",
    "sg:province":"Midi Pyr\u00e9n\u00e9es",
    "wof:name":"B.e.c. S.n.c. - Boyer Et Cazelles",
    "wof:placetype":"venue"
},
  "geometry": {"coordinates":[1.182842,43.381313],"type":"Point"}
}