{
  "type": "Feature",
  "properties": {
    "addr:full":"B.P. 2047, 76040 Rouen C\u00e9dex^^99, Rue Louis Poterat, 76100 Rouen Haute Normandie",
    "addr:housenumber":"2047",
    "addr:postcode":"76040;76100",
    "addr:street":"B.P.;Rue Louis Poterat;Haute Normandie",
    "iso:country":"FR",
    "sg:address":"B.P. 2047, 76040 Rouen C\u00e9dex^^99, Rue Louis Poterat, 76100 Rouen",
    "sg:orig_category":"Non-Classified Establishments",
    "sg:phone":"+33 2 35 58 46 46",
    "sg:province":"Haute Normandie",
    "wof:name":"Groupe Normand D'electricite S.a.",
    "wof:placetype":"venue"
},
  "geometry": {"coordinates":[1.0879,49.433601],"type":"Point"}
}