{
  "type": "Feature",
  "properties": {
    "iso:country":"FR",
    "sg:address":"132, Impasse de Gourette, 64121 Serres Castet",
    "sg:city":"Montardon",
    "sg:orig_category":"Non-Classified Establishments",
    "sg:phone":"+33 5 59 33 10 01",
    "sg:postcode":"64121",
    "sg:province":"Aquitaine",
    "wof:name":"D.k. Welding S.a.r.l.",
    "wof:placetype":"venue"
},
  "geometry": {"coordinates":[-0.384767,43.366264],"type":"Point"}
}