{
  "type": "Feature",
  "properties": {
    "addr:full":"B.P. 39, 63801 Cournon d'Auvergne^^2, Rue Manzat - ZI, 63800 Cournon d'Auvergne P\u00e9rignat-sur-Allier Auvergne 63800",
    "addr:housenumber":"^ 2",
    "addr:postcode":"63801;^;63800;pe\u0301rignat-sur-allier;63800",
    "addr:street":"B.P. 39;D'Auvergne;Rue Manzat Zi",
    "iso:country":"FR",
    "sg:address":"B.P. 39, 63801 Cournon d'Auvergne^^2, Rue Manzat - ZI, 63800 Cournon d'Auvergne",
    "sg:city":"P\u00e9rignat-sur-Allier",
    "sg:orig_category":"Non-Classified Establishments",
    "sg:phone":"+33 4 73 84 76 11",
    "sg:postcode":"63800",
    "sg:province":"Auvergne",
    "wof:name":"Coop\u00e9rative Agricole Du Puy De D\u00f4me-domagri",
    "wof:placetype":"venue"
},
  "geometry": {"coordinates":[3.204957,45.7477],"type":"Point"}
}