{
  "type": "Feature",
  "properties": {
    "addr:full":"B.P. 23903, 44339 Nantes C\u00e9dex 3^^4, Rue de la Raini\u00e8re - Parc Club du Parray, 44000 Nantes Pays de Loire",
    "addr:housenumber":"3;^ 4",
    "addr:postcode":"44339;44000",
    "addr:street":"^;Rue De La Rainie\u0300Re Parc Club Du Parray",
    "iso:country":"FR",
    "sg:address":"B.P. 23903, 44339 Nantes C\u00e9dex 3^^4, Rue de la Raini\u00e8re - Parc Club du Parray, 44000 Nantes",
    "sg:orig_category":"Non-Classified Establishments",
    "sg:phone":"+33 2 51 89 76 50",
    "sg:province":"Pays de Loire",
    "wof:name":"S.d.r.c. France S.a.",
    "wof:placetype":"venue"
},
  "geometry": {"coordinates":[-1.553059,47.218117],"type":"Point"}
}