{
  "type": "Feature",
  "properties": {
    "addr:full":"ZI le Sylvain Sanary sur Mer Centre 83110",
    "addr:postcode":"83110",
    "addr:street":"Zi Le Sylvain Sanary",
    "iso:country":"FR",
    "sg:address":"ZI le Sylvain",
    "sg:city":"Sanary sur Mer",
    "sg:orig_category":"Unclassifiable Establishments",
    "sg:phone":"+33 4 94 74 01 18",
    "sg:postcode":"83110",
    "sg:province":"Centre",
    "wof:name":"Apex Sarl",
    "wof:placetype":"venue"
},
  "geometry": {"coordinates":[5.80096,43.117786],"type":"Point"}
}