{
  "type": "Feature",
  "properties": {
    "addr:full":"B.P. 298 Epernay C\u00e9dex^^Les Forges 51200 Epernay Champagne 51209",
    "addr:housenumber":"b.p. 298",
    "addr:postcode":"51200;51209",
    "addr:street":"Ce\u0301Dex^^Les Forges;Champagne",
    "iso:country":"FR",
    "sg:address":"B.P. 298",
    "sg:city":"Epernay C\u00e9dex^^Les Forges 51200 Epernay",
    "sg:orig_category":"Vinicole et/ou viticole, Mat\u00e9riel",
    "sg:phone":"+33 3 26 58 79 79",
    "sg:postcode":"51209",
    "sg:province":"Champagne",
    "wof:name":"Valentin Thi\u00e9rion S.a.r.l.",
    "wof:placetype":"venue"
},
  "geometry": {"coordinates":[3.95475,49.045197],"type":"Point"}
}