{
  "type": "Feature",
  "properties": {
    "iso:country":"FR",
    "sg:address":"Z.I. Beaufeu",
    "sg:city":"Ro\u00e9z\u00e9 sur Sarthe",
    "sg:orig_category":"Non-Classified Establishments",
    "sg:phone":"+33 2 43 77 35 05",
    "sg:postcode":"72210",
    "sg:province":"Pays de Loire",
    "wof:name":"Soci\u00e9t\u00e9 Maine-emballages S.a.",
    "wof:placetype":"venue"
},
  "geometry": {"coordinates":[0.067595,47.895176],"type":"Point"}
}