{
  "type": "Feature",
  "properties": {
    "iso:country":"FR",
    "sg:address":"8/10, Rue Henri Estier, 56100 Lorient",
    "sg:city":"Lorient",
    "sg:orig_category":"Non-Classified Establishments",
    "sg:phone":"+33 2 97 37 32 44",
    "sg:postcode":"56100",
    "sg:province":"Bretagne",
    "wof:name":"N.i.o. S.a.r.l. - Soci\u00e9t\u00e9 Navale Industrielle Ouest",
    "wof:placetype":"venue"
},
  "geometry": {"coordinates":[-3.365211,47.732891],"type":"Point"}
}