{
  "type": "Feature",
  "properties": {
    "iso:country":"FR",
    "sg:address":"Rue Des Chasseurs A Pieds 59570 La Longueville",
    "sg:classifiers":[
        {
            "category":"Manufacturing",
            "subcategory":"Metals",
            "type":"Manufacturing & Wholesale Goods"
        }
    ],
    "sg:phone":"+33 3 27 65 32 00",
    "sg:postcode":"59570",
    "sg:province":"Nord Pas-de-Calais",
    "sg:tags":[
        "-",
        "machine",
        "equipment",
        "engineering",
        "machinery",
        "mechanical"
    ],
    "wof:name":"Sambre Alu Sa",
    "wof:placetype":"venue"
},
  "geometry": {"coordinates":[3.876915,50.284294],"type":"Point"}
}