{
  "type": "Feature",
  "properties": {
    "addr:full":"37 avenue Marceau 92400 Courbevoie Ile de France 92400",
    "addr:housenumber":"37",
    "addr:postcode":"92400;92400",
    "addr:street":"Avenue Marceau",
    "iso:country":"FR",
    "sg:address":"37 avenue Marceau 92400 Courbevoie",
    "sg:classifiers":[
        {
            "category":"Utilities",
            "subcategory":"Water",
            "type":"Services"
        }
    ],
    "sg:phone":"+33 1 41 88 15 15",
    "sg:postcode":"92400",
    "sg:province":"Ile de France",
    "sg:tags":[
        "acid",
        "amino"
    ],
    "wof:name":"Rexim S.a.",
    "wof:placetype":"venue"
},
  "geometry": {"coordinates":[2.245286,48.899849],"type":"Point"}
}