{
  "type": "Feature",
  "properties": {
    "iso:country":"FR",
    "sg:address":"2, Rue Louis Lachenal, 69740 Genas",
    "sg:orig_category":"Unclassifiable Establishments",
    "sg:phone":"+33 4 72 22 93 72",
    "sg:postcode":"69740",
    "sg:province":"Rhone-Alpes",
    "wof:name":"S.a.f. S.a. - Soudure Autog\u00e8ne Fran\u00e7aise",
    "wof:placetype":"venue"
},
  "geometry": {"coordinates":[4.98876,45.718052],"type":"Point"}
}