{
  "type": "Feature",
  "properties": {
    "addr:full":"2, Rue Louis Lachenal, 69740 Genas Rhone-Alpes 69740",
    "addr:housenumber":"2",
    "addr:postcode":"69740;69740",
    "addr:street":"Rue Louis Lachenal",
    "iso:country":"FR",
    "sg:address":"2, Rue Louis Lachenal, 69740 Genas",
    "sg:orig_category":"Unclassifiable Establishments",
    "sg:phone":"+33 4 72 22 93 72",
    "sg:postcode":"69740",
    "sg:province":"Rhone-Alpes",
    "wof:name":"S.a.f. S.a. - Soudure Autog\u00e8ne Fran\u00e7aise",
    "wof:placetype":"venue"
},
  "geometry": {"coordinates":[4.98876,45.718052],"type":"Point"}
}