{
  "type": "Feature",
  "properties": {
    "iso:country":"FR",
    "sg:address":"1, Place de la Coupole - Tour Framatome, 92084 Paris la D\u00e9fense",
    "sg:orig_category":"Non-Classified Establishments",
    "sg:phone":"+33 1 47 96 05 05",
    "sg:province":"Midi Pyr\u00e9n\u00e9es",
    "wof:name":"C.m.c. S.a. - Conduite Et Management Pour Le Changement",
    "wof:placetype":"venue"
},
  "geometry": {"coordinates":[2.24119,48.888939],"type":"Point"}
}