{
  "type": "Feature",
  "properties": {
    "addr:full":"94 avenue de Clichy 75017 Paris Ile de France",
    "addr:housenumber":"94",
    "addr:postcode":"75017",
    "addr:street":"Avenue De Clichy",
    "iso:country":"FR",
    "sg:address":"94 avenue de Clichy 75017 Paris",
    "sg:classifiers":[
        {
            "category":"Shopping",
            "subcategory":"Hobbies, Toys, & Games",
            "type":"Retail Goods"
        }
    ],
    "sg:phone":"+33 1 42 63 41 08",
    "sg:province":"Ile de France",
    "sg:tags":[
        "video"
    ],
    "wof:name":"Ste Parisienne D'exportation Sarl",
    "wof:placetype":"venue"
},
  "geometry": {"coordinates":[2.323177,48.889034],"type":"Point"}
}