{
  "type": "Feature",
  "properties": {
    "addr:full":"Impasse du Moulin Roye Picardie 80700",
    "addr:postcode":"80700",
    "addr:street":"Impasse Du Moulin;Picardie",
    "iso:country":"FR",
    "sg:address":"Impasse du Moulin",
    "sg:city":"Roye",
    "sg:orig_category":"Unclassifiable Establishments",
    "sg:phone":"+33 3 22 87 13 95",
    "sg:postcode":"80700",
    "sg:province":"Picardie",
    "wof:name":"Gaudefroy S.a.r.l.",
    "wof:placetype":"venue"
},
  "geometry": {"coordinates":[2.775632,49.704849],"type":"Point"}
}