{
  "type": "Feature",
  "properties": {
    "iso:country":"FR",
    "sg:address":"Lincel La Plaine 04870 St Michel L Observatoire",
    "sg:city":"Plaine",
    "sg:classifiers":[
        {
            "category":"Farming",
            "subcategory":"Farm & Veterinary Services",
            "type":"Manufacturing & Wholesale Goods"
        }
    ],
    "sg:phone":"+33 4 92 76 68 74",
    "sg:postcode":"67420",
    "sg:province":"Alsace",
    "sg:tags":[
        "advice",
        "agriculture",
        "livestock",
        "business"
    ],
    "wof:name":"La Forestiere",
    "wof:placetype":"venue"
},
  "geometry": {"coordinates":[5.722711,43.908947],"type":"Point"}
}