{
  "type": "Feature",
  "properties": {
    "iso:country":"FR",
    "sg:address":"39, Rue du Saule Trapu, 91300 Massy",
    "sg:orig_category":"Unclassifiable Establishments",
    "sg:phone":"+33 1 69 75 86 20",
    "sg:province":"Ile de France",
    "wof:name":"G.e. Fanuc Automation France S.a.",
    "wof:placetype":"venue"
},
  "geometry": {"coordinates":[2.30347,48.730751],"type":"Point"}
}