{
  "type": "Feature",
  "properties": {
    "iso:country":"FR",
    "sg:address":"43, Av. de Vigon, 40200 Mimizan",
    "sg:city":"Mimizan",
    "sg:orig_category":"Unclassifiable Establishments",
    "sg:phone":"+33 5 58 09 01 81",
    "sg:postcode":"40200",
    "sg:province":"Aquitaine",
    "wof:name":"Soci\u00e9t\u00e9 Lavie Et Fils S.a.r.l.",
    "wof:placetype":"venue"
},
  "geometry": {"coordinates":[-1.232762,44.208134],"type":"Point"}
}