{
  "type": "Feature",
  "properties": {
    "addr:full":"539, Av. du Cateau, 59400 Cambrai Nord Pas-de-Calais",
    "addr:postcode":"59400",
    "addr:street":"539 Av. Du Cateau",
    "iso:country":"FR",
    "sg:address":"539, Av. du Cateau, 59400 Cambrai",
    "sg:orig_category":"Unclassifiable Establishments",
    "sg:phone":"+33 3 27 73 53 11",
    "sg:province":"Nord Pas-de-Calais",
    "wof:name":"Engrenages Et R\u00e9ducteurs Messian Durand S.a.",
    "wof:placetype":"venue"
},
  "geometry": {"coordinates":[3.255555,50.171974],"type":"Point"}
}