{
  "type": "Feature",
  "properties": {
    "addr:full":"7 bis, Rue Paul Langevin, 95220 Herblay Ile de France",
    "addr:housenumber":"7 bis",
    "addr:postcode":"95220;ile",
    "addr:street":"Rue Paul Langevin",
    "iso:country":"FR",
    "sg:address":"7 bis, Rue Paul Langevin, 95220 Herblay",
    "sg:orig_category":"Unclassifiable Establishments",
    "sg:phone":"+33 1 34 50 98 99",
    "sg:province":"Ile de France",
    "wof:name":"P.p.p.l. S.a.",
    "wof:placetype":"venue"
},
  "geometry": {"coordinates":[2.171085,49.004143],"type":"Point"}
}