{
  "type": "Feature",
  "properties": {
    "addr:full":"7 Rue Du Lieutenant Audras 69160 Tassin La Demi Lune Rhone-Alpes 69160",
    "addr:housenumber":"7",
    "addr:postcode":"69160;69160",
    "addr:street":"Rue Du Lieutenant Audras",
    "iso:country":"FR",
    "sg:address":"7 Rue Du Lieutenant Audras 69160 Tassin La Demi Lune",
    "sg:classifiers":[
        {
            "category":"Professional",
            "subcategory":"Business Services",
            "type":"Services"
        }
    ],
    "sg:phone":"+33 4 78 34 07 51",
    "sg:postcode":"69160",
    "sg:province":"Rhone-Alpes",
    "sg:tags":[
        "training",
        "advice"
    ],
    "wof:name":"Institut St Joseph",
    "wof:placetype":"venue"
},
  "geometry": {"coordinates":[4.75801,45.759922],"type":"Point"}
}