{
  "type": "Feature",
  "properties": {
    "iso:country":"FR",
    "sg:address":"7 Rue Du Lieutenant Audras 69160 Tassin La Demi Lune",
    "sg:classifiers":[
        {
            "category":"Professional",
            "subcategory":"Business Services",
            "type":"Services"
        }
    ],
    "sg:phone":"+33 4 78 34 07 51",
    "sg:postcode":"69160",
    "sg:province":"Rhone-Alpes",
    "sg:tags":[
        "training",
        "advice"
    ],
    "wof:name":"Institut St Joseph",
    "wof:placetype":"venue"
},
  "geometry": {"coordinates":[4.75801,45.759922],"type":"Point"}
}