{
  "type": "Feature",
  "properties": {
    "addr:full":"29 Rte Mardichamp BP 7 88650 St L\u00e9onard Lorraine 88650",
    "addr:housenumber":"29;7",
    "addr:postcode":"88650;88650",
    "addr:street":"Rte Mardichamp Bp",
    "iso:country":"FR",
    "sg:address":"29 Rte Mardichamp BP 7 88650 St L\u00e9onard",
    "sg:classifiers":[
        {
            "category":"Manufacturing",
            "subcategory":"Metals",
            "type":"Manufacturing & Wholesale Goods"
        }
    ],
    "sg:phone":"+33 3 29 50 01 44",
    "sg:postcode":"88650",
    "sg:province":"Lorraine",
    "sg:tags":[
        "-",
        "machine",
        "equipment",
        "engineering",
        "machinery",
        "mechanical"
    ],
    "wof:name":"Sifo Sogecom Sa",
    "wof:placetype":"venue"
},
  "geometry": {"coordinates":[6.960614,48.220234],"type":"Point"}
}