{
  "type": "Feature",
  "properties": {
    "addr:full":"4 Av Foch 62390 Auxi Le Chateau Nord Pas-de-Calais 62390",
    "addr:postcode":"62390;62390",
    "addr:street":"Av Foch;Chateau Nord",
    "iso:country":"FR",
    "sg:address":"4 Av Foch 62390 Auxi Le Chateau",
    "sg:classifiers":[
        {
            "category":"Government",
            "subcategory":"Department Of Motor Vehicles",
            "type":"Public Place"
        }
    ],
    "sg:phone":"+33 3 21 04 00 11",
    "sg:postcode":"62390",
    "sg:province":"Nord Pas-de-Calais",
    "sg:tags":[
        "equipment",
        "industrial",
        "transport",
        "motor-cars"
    ],
    "wof:name":"Aubecq Auxi",
    "wof:placetype":"venue"
},
  "geometry": {"coordinates":[2.128906,50.228878],"type":"Point"}
}