{
  "type": "Feature",
  "properties": {
    "addr:full":"18 Bd De La Tour Maubourg 75007 Paris Ile de France 75007",
    "addr:housenumber":"18",
    "addr:postcode":"75007;75007",
    "addr:street":"Bd De La Tour Maubourg",
    "iso:country":"FR",
    "sg:address":"18 Bd De La Tour Maubourg 75007 Paris",
    "sg:classifiers":[
        {
            "category":"Farming",
            "subcategory":"Livestock Farm",
            "type":"Manufacturing & Wholesale Goods"
        }
    ],
    "sg:phone":"+33 1 44 11 32 32",
    "sg:postcode":"75007",
    "sg:province":"Ile de France",
    "sg:tags":[
        "breeding",
        "agriculture",
        "animal"
    ],
    "wof:name":"Restaurant Petrossian Sa",
    "wof:placetype":"venue"
},
  "geometry": {"coordinates":[2.310056,48.861313],"type":"Point"}
}