{
  "type": "Feature",
  "properties": {
    "addr:full":"ZI la Croix Cadeau Avrill\u00e9 Pays de Loire 49240",
    "addr:postcode":"49240",
    "addr:street":"Zi La Croix Cadeau",
    "iso:country":"FR",
    "sg:address":"ZI la Croix Cadeau",
    "sg:city":"Avrill\u00e9",
    "sg:orig_category":"Unclassifiable Establishments",
    "sg:phone":"+33 2 41 34 26 14",
    "sg:postcode":"49240",
    "sg:province":"Pays de Loire",
    "wof:name":"Seba S.a.r.l.",
    "wof:placetype":"venue"
},
  "geometry": {"coordinates":[-0.587263,47.504822],"type":"Point"}
}