{
  "type": "Feature",
  "properties": {
    "iso:country":"FR",
    "sg:address":"ZI Champs \u00e0 la Perdrix",
    "sg:city":"Semur en Auxois",
    "sg:orig_category":"Non-Classified Establishments",
    "sg:phone":"+33 3 80 97 43 80",
    "sg:postcode":"21140",
    "sg:province":"Bourgogne",
    "wof:name":"S\u00e9ca France S.a.r.l.",
    "wof:placetype":"venue"
},
  "geometry": {"coordinates":[4.33685,47.491798],"type":"Point"}
}