{
  "type": "Feature",
  "properties": {
    "addr:full":"5 Rue de la Vall\u00e9e 08120 BOGNY SUR MEUSE Bogny-sur-Meuse Champagne 08120",
    "addr:housenumber":"5",
    "addr:postcode":"08120;08120",
    "addr:street":"Rue De La Valle\u0301E;Bogny;Meuse;Champagne",
    "iso:country":"FR",
    "sg:address":"5 Rue de la Vall\u00e9e 08120 BOGNY SUR MEUSE",
    "sg:city":"Bogny-sur-Meuse",
    "sg:classifiers":[
        {
            "category":"Professional",
            "type":"Services"
        }
    ],
    "sg:phone":"+33 3 24 52 65 40",
    "sg:postcode":"08120",
    "sg:province":"Champagne",
    "sg:tags":[
        "transport"
    ],
    "wof:name":"Blin Albert Et Cie Sa",
    "wof:placetype":"venue"
},
  "geometry": {"coordinates":[4.76065,49.858601],"type":"Point"}
}