{
  "type": "Feature",
  "properties": {
    "addr:full":"Avenue Joseph Szydlowski 64510 Bordes Cedex Bordes Aquitaine 64510",
    "addr:postcode":"64510;64510",
    "addr:street":"Avenue Joseph Szydlowski",
    "iso:country":"FR",
    "sg:address":"Avenue Joseph Szydlowski 64510 Bordes Cedex",
    "sg:city":"Bordes",
    "sg:classifiers":[
        {
            "category":"Manufacturing",
            "subcategory":"Aerospace",
            "type":"Manufacturing & Wholesale Goods"
        }
    ],
    "sg:phone":"+33 5 59 12 50 00",
    "sg:postcode":"64510",
    "sg:province":"Aquitaine",
    "sg:tags":[
        "equipment",
        "aeronautic",
        "transport",
        "vehicle"
    ],
    "wof:name":"Turbomeca",
    "wof:placetype":"venue"
},
  "geometry": {"coordinates":[-0.287119,43.241196],"type":"Point"}
}