{
  "type": "Feature",
  "properties": {
    "addr:full":"RN 9 Chirac Languedoc-Roussillon 48100",
    "addr:postcode":"48100",
    "addr:street":"Rn 9",
    "iso:country":"FR",
    "sg:address":"RN 9",
    "sg:city":"Chirac",
    "sg:orig_category":"Non-Classified Establishments",
    "sg:phone":"+33 4 66 32 77 15",
    "sg:postcode":"48100",
    "sg:province":"Languedoc-Roussillon",
    "wof:name":"M.f.b. S.a.r.l.",
    "wof:placetype":"venue"
},
  "geometry": {"coordinates":[3.278586,44.508331],"type":"Point"}
}