{
  "type": "Feature",
  "properties": {
    "iso:country":"FR",
    "sg:address":"64, Rue Jean Jaur\u00e8s, 59770 Marly",
    "sg:orig_category":"Unclassifiable Establishments",
    "sg:phone":"+33 3 27 20 29 50",
    "sg:province":"Nord Pas-de-Calais",
    "wof:name":"Quinet S.a.",
    "wof:placetype":"venue"
},
  "geometry": {"coordinates":[3.545151,50.344337],"type":"Point"}
}