{
  "type": "Feature",
  "properties": {
    "iso:country":"FR",
    "sg:address":"Chaville",
    "sg:city":"92",
    "sg:classifiers":[
        {
            "category":"Banks & Credit Unions",
            "subcategory":"Bank",
            "type":"Services"
        }
    ],
    "sg:province":"Alsace",
    "wof:name":"Grenadier Holdings Limited",
    "wof:placetype":"venue"
},
  "geometry": {"coordinates":[2.18971,48.809811],"type":"Point"}
}