{
  "type": "Feature",
  "properties": {
    "addr:full":"B.P. 10180, 35183 Dinard C\u00e9dex^^55, Bd Jules Verger, 35180 Dinard Bretagne",
    "addr:housenumber":"10180",
    "addr:postcode":"35183;ce\u0301dex^^55;35180",
    "addr:street":"Jules Verger",
    "iso:country":"FR",
    "sg:address":"B.P. 10180, 35183 Dinard C\u00e9dex^^55, Bd Jules Verger, 35180 Dinard",
    "sg:orig_category":"Non-Classified Establishments",
    "sg:phone":"+33 2 99 16 51 00",
    "sg:province":"Bretagne",
    "wof:name":"Agriplas S.a.",
    "wof:placetype":"venue"
},
  "geometry": {"coordinates":[-2.05315,48.635181],"type":"Point"}
}