{
  "type": "Feature",
  "properties": {
    "iso:country":"FR",
    "sg:address":"157, Av. des D\u00e9port\u00e9s, 41260 La Chauss\u00e9e Saint Victor",
    "sg:city":"La Chauss\u00e9e-Saint-Victor",
    "sg:orig_category":"Unclassifiable Establishments",
    "sg:phone":"+33 2 54 74 16 67",
    "sg:postcode":"41260",
    "sg:province":"Centre",
    "wof:name":"Soci\u00e9t\u00e9 D'exploitation Des Etablissements Lacroute S.a.",
    "wof:placetype":"venue"
},
  "geometry": {"coordinates":[1.34991,47.602676],"type":"Point"}
}