{
  "type": "Feature",
  "properties": {
    "iso:country":"FR",
    "sg:address":"590 rue Auguste Roiret 69290 Craponne",
    "sg:orig_category":"Do-It-Yourself Kits For Heating Systems",
    "sg:phone":"+33 4 78 57 84 84",
    "sg:postcode":"69290",
    "sg:province":"Rhone-Alpes",
    "wof:name":"Rgs-diffusion Sa",
    "wof:placetype":"venue"
},
  "geometry": {"coordinates":[4.741527,45.752468],"type":"Point"}
}