{
  "type": "Feature",
  "properties": {
    "addr:full":"B.P. 102, 74604 Seynod C\u00e9dex^^16, Chemin de la Croix, 74600 Seynod Rhone-Alpes 74600",
    "addr:housenumber":"b.p. 102",
    "addr:postcode":"74604;74600;74600",
    "addr:street":"Chemin De La Croix",
    "iso:country":"FR",
    "sg:address":"B.P. 102, 74604 Seynod C\u00e9dex^^16, Chemin de la Croix, 74600 Seynod",
    "sg:orig_category":"Non-Classified Establishments",
    "sg:phone":"+33 4 50 69 12 15",
    "sg:postcode":"74600",
    "sg:province":"Rhone-Alpes",
    "wof:name":"Bigey S.a.r.l.",
    "wof:placetype":"venue"
},
  "geometry": {"coordinates":[6.100926,45.888924],"type":"Point"}
}