{
  "type": "Feature",
  "properties": {
    "iso:country":"FR",
    "sg:address":"14bis, Rue Duquesne, 62840 Fleurbaix",
    "sg:orig_category":"Unclassifiable Establishments",
    "sg:phone":"+33 3 21 64 64 10",
    "sg:province":"Nord Pas-de-Calais",
    "wof:name":"O.r.m.e. S.a.r.l.",
    "wof:placetype":"venue"
},
  "geometry": {"coordinates":[2.82416,50.646358],"type":"Point"}
}