{
  "type": "Feature",
  "properties": {
    "addr:full":"B.P. 565, 59308 Valenciennes C\u00e9dex^^Parc d'Activit\u00e9s du Mont Houy, 59308 Aulnoy lez Valenciennes Ile de France",
    "addr:housenumber":"b.p. 565",
    "addr:postcode":"59308;59308",
    "addr:street":"Houy",
    "iso:country":"FR",
    "sg:address":"B.P. 565, 59308 Valenciennes C\u00e9dex^^Parc d'Activit\u00e9s du Mont Houy, 59308 Aulnoy lez Valenciennes",
    "sg:orig_category":"Non-Classified Establishments",
    "sg:phone":"+33 3 27 33 68 55",
    "sg:province":"Ile de France",
    "wof:name":"Finand Autocars S.a.",
    "wof:placetype":"venue"
},
  "geometry": {"coordinates":[3.52349,50.357632],"type":"Point"}
}