{
  "type": "Feature",
  "properties": {
    "addr:full":"14 rue Jean Jaur\u00e8s 54320 Maxeville Lorraine",
    "addr:housenumber":"14",
    "addr:postcode":"54320",
    "addr:street":"Rue Jean Jaure\u0300S",
    "iso:country":"FR",
    "sg:address":"14 rue Jean Jaur\u00e8s 54320 Maxeville",
    "sg:classifiers":[
        {
            "category":"Retail",
            "subcategory":"Repair Shop",
            "type":"Services"
        }
    ],
    "sg:phone":"+33 3 83 35 62 89",
    "sg:province":"Lorraine",
    "sg:tags":[
        "sharpening",
        "workshop",
        "saw"
    ],
    "wof:name":"Safi-est Sarl",
    "wof:placetype":"venue"
},
  "geometry": {"coordinates":[6.169018,48.710407],"type":"Point"}
}