{
  "type": "Feature",
  "properties": {
    "iso:country":"FR",
    "sg:address":"55 ave Kl\u00e9ber; Paris; 75770",
    "sg:classifiers":[
        {
            "category":"Banks & Credit Unions",
            "subcategory":"Bank",
            "type":"Services"
        }
    ],
    "sg:phone":"+33 1 44 05 50 00",
    "sg:province":"Ile de France",
    "wof:name":"Banque Des Echanges, Internationaux",
    "wof:placetype":"venue"
},
  "geometry": {"coordinates":[2.290266,48.867008],"type":"Point"}
}