{
  "type": "Feature",
  "properties": {
    "iso:country":"FR",
    "sg:address":"33, Rue de Sartrouville - ZAC des C\u00f4tes d'Auty, 92700 Colombes",
    "sg:orig_category":"Unclassifiable Establishments",
    "sg:phone":"+33 1 47 60 23 93",
    "sg:province":"Ile de France",
    "wof:name":"Cary Michel",
    "wof:placetype":"venue"
},
  "geometry": {"coordinates":[2.228061,48.916939],"type":"Point"}
}