{
  "type": "Feature",
  "properties": {
    "iso:country":"FR",
    "sg:address":"rue Pierre Dravet 13011 Marseille",
    "sg:orig_category":"Lead Working",
    "sg:phone":"+33 4 91 87 60 00",
    "sg:province":"Poitou-Charentes",
    "wof:name":"D'huart Industrie Sa",
    "wof:placetype":"venue"
},
  "geometry": {"coordinates":[5.462205,43.288891],"type":"Point"}
}