{
  "type": "Feature",
  "properties": {
    "addr:full":"ZI le Peleu Montmerle sur Sa\u00f4ne Rhone-Alpes 01090",
    "addr:postcode":"01090",
    "addr:street":"Zi Le",
    "iso:country":"FR",
    "sg:address":"ZI le Peleu",
    "sg:city":"Montmerle sur Sa\u00f4ne",
    "sg:orig_category":"Unclassifiable Establishments",
    "sg:phone":"+33 4 74 06 15 20",
    "sg:postcode":"01090",
    "sg:province":"Rhone-Alpes",
    "wof:name":"Ts1 S.a.",
    "wof:placetype":"venue"
},
  "geometry": {"coordinates":[4.75763,46.080986],"type":"Point"}
}