{
  "type": "Feature",
  "properties": {
    "addr:full":"32, Rue Longue des Capucins, 13001 Marseille Provence-Alpes-C\u00f4te d'Azur",
    "addr:housenumber":"32",
    "addr:postcode":"13001",
    "addr:street":"Rue Longue Des Capucins",
    "iso:country":"FR",
    "sg:address":"32, Rue Longue des Capucins, 13001 Marseille",
    "sg:orig_category":"Unclassifiable Establishments",
    "sg:phone":"+33 4 91 90 09 79",
    "sg:province":"Provence-Alpes-C\u00f4te d'Azur",
    "wof:name":"U.t.p. S.a. - Union Textile Phoc\u00e9enne",
    "wof:placetype":"venue"
},
  "geometry": {"coordinates":[5.379347,43.297714],"type":"Point"}
}