{
  "type": "Feature",
  "properties": {
    "addr:full":"route de pont-Aven 29380 Bannalec Bannalec Bretagne 29380",
    "addr:postcode":"29380;29380",
    "addr:street":"Route De Pont-Aven;Bannalec",
    "iso:country":"FR",
    "sg:address":"route de pont-Aven 29380 Bannalec",
    "sg:city":"Bannalec",
    "sg:classifiers":[
        {
            "category":"Food & Beverages",
            "subcategory":"Meat & Fish",
            "type":"Retail Goods"
        }
    ],
    "sg:phone":"+33 2 98 39 44 60",
    "sg:postcode":"29380",
    "sg:province":"Bretagne",
    "sg:tags":[
        "product"
    ],
    "wof:name":"St\u00e9 Industrielle Et Commerciale Du Ster-goz S.a.",
    "wof:placetype":"venue"
},
  "geometry": {"coordinates":[-3.707869,47.926762],"type":"Point"}
}