{
  "type": "Feature",
  "properties": {
    "iso:country":"FR",
    "sg:address":"261",
    "sg:city":"Jacquard 71000 M\u00e2con",
    "sg:classifiers":[
        {
            "category":"Professional",
            "subcategory":"Engineering",
            "type":"Services"
        }
    ],
    "sg:phone":"+33 3 85 29 22 11",
    "sg:postcode":"71000",
    "sg:province":"Bourgogne",
    "sg:tags":[
        "machine",
        "-",
        "mechanical"
    ],
    "wof:name":"Lvi (lavage Vehicules Industriels)",
    "wof:placetype":"venue"
},
  "geometry": {"coordinates":[4.808563,46.280434],"type":"Point"}
}