{
  "type": "Feature",
  "properties": {
    "iso:country":"FR",
    "sg:address":"8, Rue de Nancy, 93800 Epinay sur Seine",
    "sg:orig_category":"Non-Classified Establishments",
    "sg:phone":"+33 1 48 41 42 43",
    "sg:province":"Ile de France",
    "wof:name":"Titres Cin\u00e9 Color A.d. S.a.",
    "wof:placetype":"venue"
},
  "geometry": {"coordinates":[2.30006,48.956547],"type":"Point"}
}