{
  "type": "Feature",
  "properties": {
    "addr:full":"Bd du Pr\u00e9sident Kennedy Tarbes Midi Pyr\u00e9n\u00e9es 65000",
    "addr:postcode":"65000",
    "addr:street":"Bd Du Pre\u0301Sident Kennedy",
    "iso:country":"FR",
    "sg:address":"Bd du Pr\u00e9sident Kennedy",
    "sg:city":"Tarbes",
    "sg:orig_category":"Unclassifiable Establishments",
    "sg:phone":"+33 5 62 44 14 55",
    "sg:postcode":"65000",
    "sg:province":"Midi Pyr\u00e9n\u00e9es",
    "wof:name":"Soci\u00e9t\u00e9 D'equipement De Bureau Services S.a.r.l.",
    "wof:placetype":"venue"
},
  "geometry": {"coordinates":[0.085435,43.219311],"type":"Point"}
}