{
  "type": "Feature",
  "properties": {
    "iso:country":"FR",
    "sg:address":"Z I De Montgivray Lieu Dit Les Vare 36400 MONTGIVRAY",
    "sg:city":"Montgivray",
    "sg:classifiers":[
        {
            "category":"Manufacturing",
            "subcategory":"Lumber",
            "type":"Manufacturing & Wholesale Goods"
        }
    ],
    "sg:phone":"+33 2 54 48 22 42",
    "sg:postcode":"36400",
    "sg:province":"Centre",
    "sg:tags":[
        "hardwood",
        "sawmill"
    ],
    "wof:name":"Ste Ageorges Freres Sa",
    "wof:placetype":"venue"
},
  "geometry": {"coordinates":[1.938385,46.541531],"type":"Point"}
}