{
  "type": "Feature",
  "properties": {
    "iso:country":"FR",
    "sg:address":"17, Rue Saulnier, 75009 Paris",
    "sg:orig_category":"Unclassifiable Establishments",
    "sg:phone":"+33 1 48 01 20 00",
    "sg:province":"Ile de France",
    "wof:name":"Gab Robins Francexpert S.a.",
    "wof:placetype":"venue"
},
  "geometry": {"coordinates":[2.344192,48.875298],"type":"Point"}
}