{
  "type": "Feature",
  "properties": {
    "iso:country":"FR",
    "sg:address":"55, Av. Joffre, 93800 Epinay sur Seine",
    "sg:orig_category":"Unclassifiable Establishments",
    "sg:phone":"+33 1 48 41 36 25",
    "sg:province":"Ile de France",
    "wof:name":"Cine Dia S.a.",
    "wof:placetype":"venue"
},
  "geometry": {"coordinates":[2.297184,48.960598],"type":"Point"}
}