{
  "type": "Feature",
  "properties": {
    "iso:country":"FR",
    "sg:address":"Av Grosse Ch\u00eane 95610 Oragny Sur Oise",
    "sg:classifiers":[
        {
            "category":"Utilities",
            "subcategory":"Telephone",
            "type":"Services"
        }
    ],
    "sg:phone":"+33 1 34 30 50 50",
    "sg:province":"Ile de France",
    "sg:tags":[
        "telecommunication"
    ],
    "wof:name":"Sagem Sa",
    "wof:placetype":"venue"
},
  "geometry": {"coordinates":[-121.26763200000001,38.692612],"type":"Point"}
}