{
  "type": "Feature",
  "properties": {
    "addr:full":"B.P. 7, 18390 Saint Germain du Puy C\u00e9dex^^Rte de la Charit\u00e9, 18390 Saint Germain du Puy Saint-Germain-du-Puy Centre 18390",
    "addr:housenumber":"7",
    "addr:postcode":"18390;18390;18390",
    "addr:street":"B.P.;Germain;Charite\u0301;Germain",
    "iso:country":"FR",
    "sg:address":"B.P. 7, 18390 Saint Germain du Puy C\u00e9dex^^Rte de la Charit\u00e9, 18390 Saint Germain du Puy",
    "sg:city":"Saint-Germain-du-Puy",
    "sg:orig_category":"Non-Classified Establishments",
    "sg:phone":"+33 2 48 68 35 00",
    "sg:postcode":"18390",
    "sg:province":"Centre",
    "wof:name":"Saint Herblain P.a.m. S.a.",
    "wof:placetype":"venue"
},
  "geometry": {"coordinates":[2.441083,47.096149],"type":"Point"}
}