{
  "type": "Feature",
  "properties": {
    "iso:country":"FR",
    "sg:address":"16, Impasse des Jades - Technoparc de l'Aubini\u00e8re, 44000 Nantes",
    "sg:orig_category":"Unclassifiable Establishments",
    "sg:phone":"+33 2 51 89 18 00",
    "sg:province":"Pays de Loire",
    "wof:name":"Rockwell Automation S.a.",
    "wof:placetype":"venue"
},
  "geometry": {"coordinates":[-1.567257,47.229397],"type":"Point"}
}