{
  "type": "Feature",
  "properties": {
    "iso:country":"FR",
    "sg:address":"Bourg 24250 Saint Martial de Nabirat",
    "sg:city":"Nabirat",
    "sg:classifiers":[
        {
            "category":"Shopping",
            "type":"Retail Goods"
        }
    ],
    "sg:phone":"+33 5 65 24 50 59",
    "sg:postcode":"24250",
    "sg:province":"Aquitaine",
    "sg:tags":[
        "metallurgy",
        "finished",
        "-",
        "metalworking",
        "metallic"
    ],
    "wof:name":"Berus",
    "wof:placetype":"venue"
},
  "geometry": {"coordinates":[1.227576,44.831924],"type":"Point"}
}