{
  "type": "Feature",
  "properties": {
    "addr:full":"Chemin de la Rotonde - ZI de la Cassine 94 Chamb\u00e9ry Rhone-Alpes 73000",
    "addr:housenumber":"94",
    "addr:postcode":"73000",
    "addr:street":"Chemin De La Rotonde Zi De La Cassine",
    "iso:country":"FR",
    "sg:address":"Chemin de la Rotonde - ZI de la Cassine 94",
    "sg:city":"Chamb\u00e9ry",
    "sg:orig_category":"Unclassifiable Establishments",
    "sg:phone":"+33 4 79 69 53 63",
    "sg:postcode":"73000",
    "sg:province":"Rhone-Alpes",
    "wof:name":"Four Et Cl\u00e9ment S.a.",
    "wof:placetype":"venue"
},
  "geometry": {"coordinates":[5.90839,45.538151],"type":"Point"}
}