{
  "type": "Feature",
  "properties": {
    "iso:country":"FR",
    "sg:address":"B.P. 9, 14540 Bourgu\u00e9bus C\u00e9dex^^Bd de l'Europe - ZI, 14540 Bourgu\u00e9bus",
    "sg:city":"Bourgu\u00e9bus",
    "sg:orig_category":"Non-Classified Establishments",
    "sg:phone":"+33 2 31 27 94 00",
    "sg:postcode":"14540",
    "sg:province":"Basse Normandie",
    "wof:name":"Soci\u00e9t\u00e9 Des Transports Lemonier S.a.r.l.",
    "wof:placetype":"venue"
},
  "geometry": {"coordinates":[-0.29966,49.12394],"type":"Point"}
}