{
  "type": "Feature",
  "properties": {
    "addr:full":"50 Rue De Curembourg 45404 Fleury Les Aubrais Centre",
    "addr:housenumber":"50",
    "addr:postcode":"45404",
    "addr:street":"Rue De Curembourg",
    "iso:country":"FR",
    "sg:address":"50 Rue De Curembourg 45404 Fleury Les Aubrais",
    "sg:classifiers":[
        {
            "category":"Professional",
            "subcategory":"Business Services",
            "type":"Services"
        }
    ],
    "sg:phone":"+33 2 38 65 48 80",
    "sg:province":"Centre",
    "sg:tags":[
        "body",
        "advice"
    ],
    "wof:name":"Familles Rurales Fed Depart Du Loiret",
    "wof:placetype":"venue"
},
  "geometry": {"coordinates":[1.92652,47.942791],"type":"Point"}
}