{
  "type": "Feature",
  "properties": {
    "iso:country":"FR",
    "sg:address":"41 Rue Lamartine 06000 Nice",
    "sg:classifiers":[
        {
            "category":"Travel",
            "subcategory":"Hotels & Motels",
            "type":"Entertainment"
        }
    ],
    "sg:phone":"+33 4 93 62 14 43",
    "sg:province":"Corse",
    "sg:tags":[
        "hotels",
        "business",
        "restaurant"
    ],
    "wof:name":"Hotel Alexandra Sa",
    "wof:placetype":"venue"
},
  "geometry": {"coordinates":[7.26695,43.705078],"type":"Point"}
}