{
  "type": "Feature",
  "properties": {
    "iso:country":"FR",
    "sg:address":"71 Bd G\u00e9n\u00e9ral De Gaulle 06230 St Jean Cap Ferrat",
    "sg:classifiers":[
        {
            "category":"Travel",
            "subcategory":"Hotels & Motels",
            "type":"Entertainment"
        }
    ],
    "sg:phone":"+33 4 93 76 50 50",
    "sg:province":"Languedoc-Roussillon",
    "sg:tags":[
        "hotels",
        "business",
        "restaurant"
    ],
    "wof:name":"Union Hoteliere Du Cap",
    "wof:placetype":"venue"
},
  "geometry": {"coordinates":[7.330657,43.677361],"type":"Point"}
}