{
  "type": "Feature",
  "properties": {
    "iso:country":"FR",
    "sg:address":"rue de Lucelle 68300 ST LOUIS",
    "sg:city":"Saint-Louis",
    "sg:classifiers":[
        {
            "category":"Home & Garden",
            "subcategory":"Household Appliances",
            "type":"Retail Goods"
        }
    ],
    "sg:phone":"+33 3 89 70 48 00",
    "sg:postcode":"68300",
    "sg:province":"Alsace",
    "sg:tags":[
        "electric"
    ],
    "wof:name":"Cice Sa",
    "wof:placetype":"venue"
},
  "geometry": {"coordinates":[7.567145,47.581669],"type":"Point"}
}