{
  "type": "Feature",
  "properties": {
    "iso:country":"FR",
    "sg:address":"125 Rue Pasteur 59370 Mons En Baroeul",
    "sg:classifiers":[
        {
            "category":"Manufacturing",
            "subcategory":"Printing",
            "type":"Manufacturing & Wholesale Goods"
        }
    ],
    "sg:phone":"+33 3 20 04 20 19",
    "sg:province":"Nord Pas-de-Calais",
    "sg:tags":[
        "publishing"
    ],
    "wof:name":"Vigne Impressions Sa",
    "wof:placetype":"venue"
},
  "geometry": {"coordinates":[3.10327,50.649769],"type":"Point"}
}