{
  "type": "Feature",
  "properties": {
    "iso:country":"FR",
    "sg:address":"4 boulevard de Beauregard 21600 Longvic",
    "sg:city":"Longvic",
    "sg:classifiers":[
        {
            "category":"Wholesale",
            "subcategory":"Fruits & Vegetables",
            "type":"Manufacturing & Wholesale Goods"
        }
    ],
    "sg:phone":"+33 3 80 69 21 21",
    "sg:postcode":"21600",
    "sg:province":"Bourgogne",
    "sg:tags":[
        "product",
        "cereal"
    ],
    "wof:name":"Union Cooperative Agricole Bourgogne Cereales",
    "wof:placetype":"venue"
},
  "geometry": {"coordinates":[5.052162,47.279133],"type":"Point"}
}