{
  "type": "Feature",
  "properties": {
    "iso:country":"FR",
    "sg:address":"6, Av Foch, 57730 Folschviller",
    "sg:orig_category":"Installateur: Travaux \u00e9lectriques instrumentation, automatismes et petite tuyauterie",
    "sg:phone":"+33 3 87 92 10 28",
    "sg:postcode":"57730",
    "sg:province":"Lorraine",
    "wof:name":"S.e.r.e.t.r.a. S.a.r.l. - Soci\u00e9t\u00e9 D'etudes R\u00e9alisations Electrique Tuyauterie R\u00e9gulation Automatisme",
    "wof:placetype":"venue"
},
  "geometry": {"coordinates":[6.686688,49.070847],"type":"Point"}
}