{
  "type": "Feature",
  "properties": {
    "addr:full":"79 Rue Maxime Gorki 93700 Drancy Ile de France 93700",
    "addr:housenumber":"79",
    "addr:postcode":"93700;ile;93700",
    "addr:street":"Rue Maxime Gorki;France",
    "iso:country":"FR",
    "sg:address":"79 Rue Maxime Gorki 93700 Drancy",
    "sg:classifiers":[
        {
            "category":"Food & Beverages",
            "subcategory":"Groceries & Convenience Stores",
            "type":"Retail Goods"
        }
    ],
    "sg:phone":"+33 1 48 32 22 03",
    "sg:postcode":"93700",
    "sg:province":"Ile de France",
    "sg:tags":[
        "product",
        "related"
    ],
    "wof:name":"Dumond Traiteur Sa",
    "wof:placetype":"venue"
},
  "geometry": {"coordinates":[2.443556,48.926834],"type":"Point"}
}