{
  "type": "Feature",
  "properties": {
    "iso:country":"FR",
    "sg:address":"Z I Artel Lieu-Dit Artel Est 82100 CASTELFERRUS",
    "sg:classifiers":[
        {
            "category":"Wholesale",
            "subcategory":"Electrical",
            "type":"Manufacturing & Wholesale Goods"
        }
    ],
    "sg:phone":"+33 5 63 32 41 47",
    "sg:province":"Midi Pyr\u00e9n\u00e9es",
    "sg:tags":[
        "units",
        "generating",
        "generator",
        "emergency",
        "power"
    ],
    "wof:name":"Electro Diesel Distribution Sarl",
    "wof:placetype":"venue"
},
  "geometry": {"coordinates":[1.109529,43.941746],"type":"Point"}
}