{
  "type": "Feature",
  "properties": {
    "addr:full":"8, Bd Magenta, 75010 Paris Ile de France",
    "addr:housenumber":"8",
    "addr:postcode":"75010",
    "addr:street":"Bd Magenta",
    "iso:country":"FR",
    "sg:address":"8, Bd Magenta, 75010 Paris",
    "sg:orig_category":"Unclassifiable Establishments",
    "sg:phone":"+33 1 53 38 57 00",
    "sg:province":"Ile de France",
    "wof:name":"N.e.s. Conseil S.a.r.l.",
    "wof:placetype":"venue"
},
  "geometry": {"coordinates":[2.36277,48.86898],"type":"Point"}
}