{
  "type": "Feature",
  "properties": {
    "addr:full":"Rue Lazare Carnot - ZI Nord Alen\u00e7on Basse Normandie 61000",
    "addr:postcode":"61000",
    "addr:street":"Rue Lazare Carnot Zi Nord;Basse",
    "iso:country":"FR",
    "sg:address":"Rue Lazare Carnot - ZI Nord",
    "sg:city":"Alen\u00e7on",
    "sg:orig_category":"Non-Classified Establishments",
    "sg:phone":"+33 2 33 29 15 61",
    "sg:postcode":"61000",
    "sg:province":"Basse Normandie",
    "wof:name":"Garczynski Traploir",
    "wof:placetype":"venue"
},
  "geometry": {"coordinates":[0.083175,48.430626],"type":"Point"}
}