{
  "type": "Feature",
  "properties": {
    "addr:full":"5, Rue de Seichamps, 54425 Pulnoy Lorraine",
    "addr:housenumber":"5",
    "addr:postcode":"54425",
    "addr:street":"Rue De Seichamps",
    "iso:country":"FR",
    "sg:address":"5, Rue de Seichamps, 54425 Pulnoy",
    "sg:orig_category":"Unclassifiable Establishments",
    "sg:phone":"+33 3 83 29 54 39",
    "sg:province":"Lorraine",
    "wof:name":"Laboratoires S\u00e9robiologiques S.a.",
    "wof:placetype":"venue"
},
  "geometry": {"coordinates":[6.260024,48.703495],"type":"Point"}
}