{
  "type": "Feature",
  "properties": {
    "iso:country":"FR",
    "sg:address":"B.P. 26, 80101 Abbeville C\u00e9dex^^12, Rue de la Tannerie, 80100 Abbeville",
    "sg:orig_category":"Non-Classified Establishments",
    "sg:phone":"+33 3 22 24 55 77",
    "sg:postcode":"80100",
    "sg:province":"Picardie",
    "wof:name":"Dubois S.a.",
    "wof:placetype":"venue"
},
  "geometry": {"coordinates":[1.83483,50.105034],"type":"Point"}
}