{
  "type": "Feature",
  "properties": {
    "iso:country":"FR",
    "sg:address":"6, Rue des B'Helsinki, 90000 Belfort",
    "sg:orig_category":"Non-Classified Establishments",
    "sg:phone":"+33 3 84 36 60 20",
    "sg:postcode":"90000",
    "sg:province":"Franche Comt\u00e9",
    "wof:name":"A.e.2.i. S.a.s. - Automastisme Electrotechnique Informatique Industriel",
    "wof:placetype":"venue"
},
  "geometry": {"coordinates":[6.835969,47.635429],"type":"Point"}
}