{
  "type": "Feature",
  "properties": {
    "iso:country":"FR",
    "sg:address":"7 avenue de Bel Air 69100 Villeurbanne",
    "sg:classifiers":[
        {
            "category":"Bus Stop",
            "subcategory":"None",
            "type":"Transportation"
        }
    ],
    "sg:phone":"+33 4 72 35 57 00",
    "sg:province":"Rhone-Alpes",
    "sg:tags":[
        "disc",
        "brake"
    ],
    "wof:name":"Messier-bugatti Sa",
    "wof:placetype":"venue"
},
  "geometry": {"coordinates":[4.911123,45.757721],"type":"Point"}
}