{
  "type": "Feature",
  "properties": {
    "addr:full":"27, Chemin des Chaus, 33610 Cestas Cestas Aquitaine 33610",
    "addr:housenumber":"27",
    "addr:postcode":"33610;33610",
    "addr:street":"Chemin Des Chaus",
    "iso:country":"FR",
    "sg:address":"27, Chemin des Chaus, 33610 Cestas",
    "sg:city":"Cestas",
    "sg:orig_category":"Non-Classified Establishments",
    "sg:phone":"+33 5 56 21 56 05",
    "sg:postcode":"33610",
    "sg:province":"Aquitaine",
    "wof:name":"Cabinet Alain Sussan S.a.r.l.",
    "wof:placetype":"venue"
},
  "geometry": {"coordinates":[-0.702453,44.721989],"type":"Point"}
}