{
  "type": "Feature",
  "properties": {
    "iso:country":"FR",
    "sg:address":"Place de l'Eglise",
    "sg:city":"Bouille Loretz",
    "sg:orig_category":"Unclassifiable Establishments",
    "sg:phone":"+33 5 49 67 04 61",
    "sg:postcode":"79290",
    "sg:province":"Poitou-Charentes",
    "wof:name":"Soci\u00e9t\u00e9 D'exploitation Des Voyages Rousselot S.a.",
    "wof:placetype":"venue"
},
  "geometry": {"coordinates":[-0.27309,47.079411],"type":"Point"}
}