{
  "type": "Feature",
  "properties": {
    "iso:country":"FR",
    "sg:address":"5, Rue Jean Menesson, 80100 Abbeville",
    "sg:orig_category":"Unclassifiable Establishments",
    "sg:phone":"+33 3 22 25 45 70",
    "sg:province":"Picardie",
    "wof:name":"B\u00e9ghin-say S.a. - Sucrerie D'abbeville",
    "wof:placetype":"venue"
},
  "geometry": {"coordinates":[1.827895,50.116676],"type":"Point"}
}