{
  "type": "Feature",
  "properties": {
    "addr:full":"B.P. 5, 60860 Saint Omer en Chauss\u00e9e^^Rte du Moulin, 60860 Saint Omer en Chauss\u00e9e Picardie",
    "addr:housenumber":"5",
    "addr:postcode":"60860;60860",
    "addr:street":"B.P.;Moulin;Chausse\u0301E Picardie",
    "iso:country":"FR",
    "sg:address":"B.P. 5, 60860 Saint Omer en Chauss\u00e9e^^Rte du Moulin, 60860 Saint Omer en Chauss\u00e9e",
    "sg:orig_category":"Non-Classified Establishments",
    "sg:phone":"+33 3 44 84 50 36",
    "sg:province":"Picardie",
    "wof:name":"Ventm\u00e9ca S.a.",
    "wof:placetype":"venue"
},
  "geometry": {"coordinates":[2.029483,49.547749],"type":"Point"}
}