{
  "type": "Feature",
  "properties": {
    "addr:full":"Saint-Ange; \u00c9toile-sur-Rh\u00f4ne; 26800 Rhone-Alpes",
    "addr:postcode":"26800",
    "iso:country":"FR",
    "sg:address":"Saint-Ange; \u00c9toile-sur-Rh\u00f4ne; 26800",
    "sg:classifiers":[
        {
            "category":"Industrial Area",
            "type":"Public Place"
        }
    ],
    "sg:phone":"+33 4 75 75 26 00",
    "sg:province":"Rhone-Alpes",
    "sg:tags":[
        "large",
        "private"
    ],
    "wof:name":"Icbt Groupe Sa",
    "wof:placetype":"venue"
},
  "geometry": {"coordinates":[4.907647,44.794395],"type":"Point"}
}