{
  "type": "Feature",
  "properties": {
    "addr:full":"5 Rue Mond\u00e9tour 91320 Wissous Ile de France 91320",
    "addr:housenumber":"5",
    "addr:postcode":"91320;ile;91320",
    "addr:street":"Rue Monde\u0301Tour;France",
    "iso:country":"FR",
    "sg:address":"5 Rue Mond\u00e9tour 91320 Wissous",
    "sg:classifiers":[
        {
            "category":"Communications",
            "type":"Services"
        }
    ],
    "sg:phone":"+33 1 60 13 50 50",
    "sg:postcode":"91320",
    "sg:province":"Ile de France",
    "sg:tags":[
        "advice",
        "interpretation",
        "translation",
        "business"
    ],
    "wof:name":"Btcs France Sarl",
    "wof:placetype":"venue"
},
  "geometry": {"coordinates":[2.326423,48.72987],"type":"Point"}
}