{
  "type": "Feature",
  "properties": {
    "iso:country":"FR",
    "sg:address":"Rue Maurice Ravel - Z.I. de Croupillac",
    "sg:city":"Al\u00e8s C\u00e9dex",
    "sg:orig_category":"Unclassifiable Establishments",
    "sg:phone":"+33 4 66 78 41 41",
    "sg:postcode":"30319",
    "sg:province":"Languedoc-Roussillon",
    "wof:name":"Merlin G\u00e9rin Al\u00e8s S.a.",
    "wof:placetype":"venue"
},
  "geometry": {"coordinates":[4.07903,44.127399],"type":"Point"}
}