{
  "type": "Feature",
  "properties": {
    "iso:country":"FR",
    "sg:address":"107 pl de l'H\u00f4tel de Ville; Chambly; 60230",
    "sg:classifiers":[
        {
            "category":"Banks & Credit Unions",
            "subcategory":"Bank",
            "type":"Services"
        }
    ],
    "sg:phone":"+33 3334705460",
    "sg:postcode":"60230",
    "sg:province":"Picardie",
    "wof:name":"Banque Nationale De Paris",
    "wof:placetype":"venue"
},
  "geometry": {"coordinates":[2.24606,49.174332],"type":"Point"}
}