{
  "type": "Feature",
  "properties": {
    "iso:country":"FR",
    "sg:address":"1 rue Gabriel P\u00e9ri; Bastia; 20200",
    "sg:classifiers":[
        {
            "category":"Banks & Credit Unions",
            "subcategory":"Bank",
            "type":"Services"
        }
    ],
    "sg:phone":"+33 3395311863",
    "sg:postcode":"20200",
    "sg:province":"Corse",
    "wof:name":"Sovac",
    "wof:placetype":"venue"
},
  "geometry": {"coordinates":[9.449266,42.701614],"type":"Point"}
}