{
  "type": "Feature",
  "properties": {
    "iso:country":"FR",
    "sg:address":"119 Rue Camille Pelletan 79104 Thouars Cedex",
    "sg:classifiers":[
        {
            "category":"Food & Beverages",
            "subcategory":"Meat & Fish",
            "type":"Retail Goods"
        }
    ],
    "sg:phone":"+33 5 49 66 00 51",
    "sg:province":"Poitou-Charentes",
    "sg:tags":[
        "preserve",
        "cooked",
        "product",
        "related"
    ],
    "wof:name":"Samco Alimentaire Sa",
    "wof:placetype":"venue"
},
  "geometry": {"coordinates":[-0.226385,46.984989],"type":"Point"}
}