{
  "type": "Feature",
  "properties": {
    "iso:country":"FR",
    "sg:address":"Zone Artisanale 73800 Les Marches",
    "sg:classifiers":[
        {
            "category":"Shopping",
            "type":"Retail Goods"
        }
    ],
    "sg:phone":"+33 4 79 28 16 52",
    "sg:postcode":"73800",
    "sg:province":"Rhone-Alpes",
    "sg:tags":[
        "metallurgy",
        "finished",
        "-",
        "metalworking",
        "metallic"
    ],
    "wof:name":"Bma France",
    "wof:placetype":"venue"
},
  "geometry": {"coordinates":[6.00053,45.498459],"type":"Point"}
}