{
  "type": "Feature",
  "properties": {
    "addr:full":"63 Av Marcel Lacassagne 82240 Septfonds Midi Pyr\u00e9n\u00e9es 82240",
    "addr:postcode":"82240;82240",
    "addr:street":"63 Av Marcel Lacassagne",
    "iso:country":"FR",
    "sg:address":"63 Av Marcel Lacassagne 82240 Septfonds",
    "sg:classifiers":[
        {
            "category":"Manufacturing",
            "subcategory":"Textiles",
            "type":"Manufacturing & Wholesale Goods"
        }
    ],
    "sg:phone":"+33 5 63 64 91 47",
    "sg:postcode":"82240",
    "sg:province":"Midi Pyr\u00e9n\u00e9es",
    "sg:tags":[
        "clothing",
        "accessory"
    ],
    "wof:name":"Coustilleres Sa",
    "wof:placetype":"venue"
},
  "geometry": {"coordinates":[1.607453,44.173782],"type":"Point"}
}