{
  "type": "Feature",
  "properties": {
    "iso:country":"FR",
    "sg:address":"55, Rue Jules Verne, 63100 Clermont Ferrand",
    "sg:city":"Clermont-Ferrand",
    "sg:orig_category":"Unclassifiable Establishments",
    "sg:phone":"+33 4 73 98 89 88",
    "sg:postcode":"63100",
    "sg:province":"Auvergne",
    "wof:name":"Etablissement Etellin S.a.",
    "wof:placetype":"venue"
},
  "geometry": {"coordinates":[3.137742,45.787144],"type":"Point"}
}