{
  "type": "Feature",
  "properties": {
    "iso:country":"FR",
    "sg:address":"47480 Pont du Casse",
    "sg:city":"Bajamont",
    "sg:orig_category":"Unclassifiable Establishments",
    "sg:phone":"+33 5 53 69 36 30",
    "sg:postcode":"47480",
    "sg:province":"Aquitaine",
    "wof:name":"De Sangosse S.a.",
    "wof:placetype":"venue"
},
  "geometry": {"coordinates":[0.680915,44.231335],"type":"Point"}
}