{
  "type": "Feature",
  "properties": {
    "addr:full":"52 Bis Rue Lafitte 75009 Paris Ile de France 75009",
    "addr:housenumber":"52 bis",
    "addr:postcode":"75009;75009",
    "addr:street":"Rue Lafitte",
    "iso:country":"FR",
    "sg:address":"52 Bis Rue Lafitte 75009 Paris",
    "sg:classifiers":[
        {
            "category":"Banks & Credit Unions",
            "subcategory":"Financial Services",
            "type":"Services"
        }
    ],
    "sg:phone":"+33 1 49 70 13 70",
    "sg:postcode":"75009",
    "sg:province":"Ile de France",
    "sg:tags":[
        "banking",
        "insurance",
        "institution",
        "finance"
    ],
    "wof:name":"Banque De Chine",
    "wof:placetype":"venue"
},
  "geometry": {"coordinates":[2.338724,48.875378],"type":"Point"}
}