{
  "type": "Feature",
  "properties": {
    "iso:country":"FR",
    "sg:address":"Rte Du Bassin Carnot 14600 Honfleur",
    "sg:city":"Honfleur",
    "sg:classifiers":[
        {
            "category":"Home & Garden",
            "subcategory":"Furniture",
            "type":"Retail Goods"
        }
    ],
    "sg:phone":"+33 2 31 81 65 65",
    "sg:postcode":"14600",
    "sg:province":"Basse Normandie",
    "sg:tags":[
        "wood"
    ],
    "wof:name":"Pb Et M Ile De France Nord",
    "wof:placetype":"venue"
},
  "geometry": {"coordinates":[0.246048,49.416077],"type":"Point"}
}