{
  "type": "Feature",
  "properties": {
    "iso:country":"FR",
    "sg:address":"B.P. 131, 71600 Hautefond^^ZA, 71600 Hautefond",
    "sg:city":"Hautefond",
    "sg:orig_category":"Non-Classified Establishments",
    "sg:phone":"+33 3 85 81 48 08",
    "sg:postcode":"71600",
    "sg:province":"Bourgogne",
    "wof:name":"Vitrage Isolant Technique S.a.",
    "wof:placetype":"venue"
},
  "geometry": {"coordinates":[4.127668,46.384384],"type":"Point"}
}