{
  "type": "Feature",
  "properties": {
    "addr:full":"Chemin des Cendres Steenvoorde Nord Pas-de-Calais 59114",
    "addr:postcode":"59114",
    "addr:street":"Chemin Des Cendres Steenvoorde Nord",
    "iso:country":"FR",
    "sg:address":"Chemin des Cendres",
    "sg:city":"Steenvoorde",
    "sg:orig_category":"Unclassifiable Establishments",
    "sg:phone":"+33 3 28 43 84 38",
    "sg:postcode":"59114",
    "sg:province":"Nord Pas-de-Calais",
    "wof:name":"Frigo A 25 S.a.",
    "wof:placetype":"venue"
},
  "geometry": {"coordinates":[2.583874,50.813236],"type":"Point"}
}