{
  "type": "Feature",
  "properties": {
    "iso:country":"FR",
    "sg:address":"Rue Du Causse 81090 Lagarrigue",
    "sg:classifiers":[
        {
            "category":"Shopping",
            "subcategory":"Crafts & Fabrics",
            "type":"Retail Goods"
        }
    ],
    "sg:phone":"+33 5 63 35 09 25",
    "sg:postcode":"81090",
    "sg:province":"Midi Pyr\u00e9n\u00e9es",
    "sg:tags":[
        "textile",
        "clothing"
    ],
    "wof:name":"Tissage Du Causse Sa",
    "wof:placetype":"venue"
},
  "geometry": {"coordinates":[2.272327,43.575443],"type":"Point"}
}