{
  "type": "Feature",
  "properties": {
    "addr:full":"1737 route du Conihout 76480 Jumieges Haute Normandie 76480",
    "addr:housenumber":"1737",
    "addr:postcode":"76480;76480",
    "addr:street":"Route Du Conihout;Haute Normandie",
    "iso:country":"FR",
    "sg:address":"1737 route du Conihout 76480 Jumieges",
    "sg:classifiers":[
        {
            "category":"Home & Garden",
            "subcategory":"Hardware",
            "type":"Retail Goods"
        }
    ],
    "sg:phone":"+33 2 35 05 33 15",
    "sg:postcode":"76480",
    "sg:province":"Haute Normandie",
    "sg:tags":[
        "equipment"
    ],
    "wof:name":"Bdr Brouettes Distribution Rapide Sarl",
    "wof:placetype":"venue"
},
  "geometry": {"coordinates":[0.836808,49.39608],"type":"Point"}
}