{
  "type": "Feature",
  "properties": {
    "iso:country":"FR",
    "sg:address":"Rue de Buchelay - ZI",
    "sg:city":"Mantes la Jolie",
    "sg:orig_category":"Unclassifiable Establishments",
    "sg:phone":"+33 1 30 94 10 35",
    "sg:postcode":"78200",
    "sg:province":"Ile de France",
    "wof:name":"Soci\u00e9t\u00e9 D'exploitation Dupetit S.a.r.l.",
    "wof:placetype":"venue"
},
  "geometry": {"coordinates":[1.714715,48.989491],"type":"Point"}
}