{
  "type": "Feature",
  "properties": {
    "iso:country":"FR",
    "sg:address":"Rte de Draillant",
    "sg:city":"Perrignier",
    "sg:orig_category":"Unclassifiable Establishments",
    "sg:phone":"+33 4 50 72 42 76",
    "sg:postcode":"74550",
    "sg:province":"Rhone-Alpes",
    "wof:name":"E.t.d.e. S.a.",
    "wof:placetype":"venue"
},
  "geometry": {"coordinates":[6.442996,46.30439],"type":"Point"}
}