{
  "type": "Feature",
  "properties": {
    "addr:full":"63 place Bernard du Bois 13001 Marseille Poitou-Charentes",
    "addr:housenumber":"63",
    "addr:postcode":"13001",
    "addr:street":"Place Bernard Du Bois",
    "iso:country":"FR",
    "sg:address":"63 place Bernard du Bois 13001 Marseille",
    "sg:classifiers":[
        {
            "category":"Travel",
            "subcategory":"Travel Agent",
            "type":"Entertainment"
        }
    ],
    "sg:phone":"+33 4 91 90 11 18",
    "sg:province":"Poitou-Charentes",
    "sg:tags":[
        "incentive"
    ],
    "wof:name":"Saint Charles Voyages Sa",
    "wof:placetype":"venue"
},
  "geometry": {"coordinates":[5.379475,43.302101],"type":"Point"}
}