{
  "type": "Feature",
  "properties": {
    "addr:full":"19 rue Eug\u00e8ne H\u00e9naff 94400 Vitry sur Seine Ile de France",
    "addr:housenumber":"19",
    "addr:postcode":"94400",
    "addr:street":"Rue Euge\u0300Ne He\u0301Naff",
    "iso:country":"FR",
    "sg:address":"19 rue Eug\u00e8ne H\u00e9naff 94400 Vitry sur Seine",
    "sg:classifiers":[
        {
            "category":"Coffee & Tea",
            "type":"Food & Drink"
        }
    ],
    "sg:phone":"+33 1 45 73 69 40",
    "sg:province":"Ile de France",
    "sg:tags":[
        "roasted"
    ],
    "wof:name":"Caf\u00e9s Suavor Sa",
    "wof:placetype":"venue"
},
  "geometry": {"coordinates":[2.412307,48.793373],"type":"Point"}
}