{
  "type": "Feature",
  "properties": {
    "addr:full":"Min Avignon Bat O 84000 Avignon",
    "addr:postcode":"84000",
    "iso:country":"FR",
    "sg:address":"Min Avignon Bat O 84000 Avignon",
    "sg:classifiers":[
        {
            "category":"Farming",
            "subcategory":"Livestock Farm",
            "type":"Manufacturing & Wholesale Goods"
        }
    ],
    "sg:phone":"+33 4 90 88 40 67",
    "sg:tags":[
        "agriculture"
    ],
    "wof:name":"Avon (sa)",
    "wof:placetype":"venue"
},
  "geometry": {"coordinates":[4.806015,43.948753],"type":"Point"}
}