{
  "type": "Feature",
  "properties": {
    "iso:country":"FR",
    "sg:address":"Rue du Camp de P\u00e9ran 22960 PLEDRAN",
    "sg:city":"Pl\u00e9dran",
    "sg:classifiers":[
        {
            "category":"Communications",
            "subcategory":"Film & Video Production",
            "type":"Services"
        }
    ],
    "sg:phone":"+33 2 96 71 00 98",
    "sg:postcode":"22960",
    "sg:province":"Bretagne",
    "sg:tags":[
        "wooden",
        "articles",
        "mass"
    ],
    "wof:name":"Tournerie D' Armor Sa",
    "wof:placetype":"venue"
},
  "geometry": {"coordinates":[-2.774194,48.464802],"type":"Point"}
}