{
  "type": "Feature",
  "properties": {
    "iso:country":"FR",
    "sg:address":"81200 Caucali\u00e8res",
    "sg:orig_category":"Unclassifiable Establishments",
    "sg:phone":"+33 5 63 61 17 67",
    "sg:province":"Midi Pyr\u00e9n\u00e9es",
    "wof:name":"Tissus De La Montagne Noire S.a.r.l.",
    "wof:placetype":"venue"
},
  "geometry": {"coordinates":[2.31307,43.521305],"type":"Point"}
}