{
  "type": "Feature",
  "properties": {
    "addr:full":"2 RUE DE L AUBRAC 94150 Rungis Ile de France 94150",
    "addr:housenumber":"2",
    "addr:postcode":"94150;94150",
    "addr:street":"Rue De L Aubrac",
    "iso:country":"FR",
    "sg:address":"2 RUE DE L AUBRAC 94150 Rungis",
    "sg:classifiers":[
        {
            "category":"Food & Beverages",
            "subcategory":"Meat & Fish",
            "type":"Retail Goods"
        }
    ],
    "sg:phone":"+33 1 46 86 41 31",
    "sg:postcode":"94150",
    "sg:province":"Ile de France",
    "wof:name":"Approval Sa",
    "wof:placetype":"venue"
},
  "geometry": {"coordinates":[2.365559,48.757164],"type":"Point"}
}