{
  "type": "Feature",
  "properties": {
    "addr:full":"202, Chemin D\u00e9partemental, 52260 Rolampont Champagne",
    "addr:housenumber":"202",
    "addr:postcode":"52260",
    "addr:street":"Chemin De\u0301Partemental",
    "iso:country":"FR",
    "sg:address":"202, Chemin D\u00e9partemental, 52260 Rolampont",
    "sg:orig_category":"Non-Classified Establishments",
    "sg:phone":"+33 3 25 84 70 53",
    "sg:province":"Champagne",
    "wof:name":"Floriot-vistot Hubert S.a.r.l.",
    "wof:placetype":"venue"
},
  "geometry": {"coordinates":[5.28544,47.948673],"type":"Point"}
}