{
  "type": "Feature",
  "properties": {
    "addr:full":"18210 St Pierre Les Etieux Bannegon Centre 18210",
    "addr:housenumber":"18210;bannegon",
    "addr:postcode":"18210",
    "addr:street":"St Pierre Les",
    "iso:country":"FR",
    "sg:address":"18210 St Pierre Les Etieux",
    "sg:city":"Bannegon",
    "sg:classifiers":[
        {
            "category":"Home & Garden",
            "subcategory":"Furniture",
            "type":"Retail Goods"
        }
    ],
    "sg:phone":"+33 2 48 60 75 22",
    "sg:postcode":"18210",
    "sg:province":"Centre",
    "sg:tags":[
        "wood"
    ],
    "wof:name":"Centre Bois Massif",
    "wof:placetype":"venue"
},
  "geometry": {"coordinates":[2.621389,46.733032],"type":"Point"}
}