{
  "type": "Feature",
  "properties": {
    "addr:full":"12, Rue Jean Joly, 41000 Blois Blois Centre 41000",
    "addr:housenumber":"12",
    "addr:postcode":"41000;41000",
    "addr:street":"Rue Jean Joly",
    "iso:country":"FR",
    "sg:address":"12, Rue Jean Joly, 41000 Blois",
    "sg:city":"Blois",
    "sg:orig_category":"Non-Classified Establishments",
    "sg:phone":"+33 2 54 55 80 00",
    "sg:postcode":"41000",
    "sg:province":"Centre",
    "wof:name":"Coop\u00e9rative Agricole Foresti\u00e8re Sylviculteurs Du Loir Et Cher S.c.a.",
    "wof:placetype":"venue"
},
  "geometry": {"coordinates":[1.327696,47.596542],"type":"Point"}
}