{
  "type": "Feature",
  "properties": {
    "addr:full":"ZI Billom Auvergne 63160",
    "addr:postcode":"63160",
    "addr:street":"Billom",
    "iso:country":"FR",
    "sg:address":"ZI",
    "sg:city":"Billom",
    "sg:orig_category":"Non-Classified Establishments",
    "sg:phone":"+33 4 73 73 42 12",
    "sg:postcode":"63160",
    "sg:province":"Auvergne",
    "wof:name":"A.m.h. S.a.",
    "wof:placetype":"venue"
},
  "geometry": {"coordinates":[3.41201,45.677967],"type":"Point"}
}