{
  "type": "Feature",
  "properties": {
    "addr:full":"17, Place Soult, 81100 Castres Midi Pyr\u00e9n\u00e9es",
    "addr:housenumber":"17",
    "addr:postcode":"81100",
    "addr:street":"Place Soult",
    "iso:country":"FR",
    "sg:address":"17, Place Soult, 81100 Castres",
    "sg:orig_category":"Non-Classified Establishments",
    "sg:phone":"+33 5 63 62 57 57",
    "sg:province":"Midi Pyr\u00e9n\u00e9es",
    "wof:name":"Soci\u00e9t\u00e9 Des Cars Ren\u00e9 Thorel S.a.r.l.",
    "wof:placetype":"venue"
},
  "geometry": {"coordinates":[2.246278,43.604301],"type":"Point"}
}