{
  "type": "Feature",
  "properties": {
    "addr:full":"3, Rue du Maconnais - ZI la Petite Montagne Sud, 91000 Evry Ile de France",
    "addr:housenumber":"3",
    "addr:postcode":"91000",
    "addr:street":"Rue Du Maconnais Zi La Petite Montagne Sud",
    "iso:country":"FR",
    "sg:address":"3, Rue du Maconnais - ZI la Petite Montagne Sud, 91000 Evry",
    "sg:orig_category":"Unclassifiable Establishments",
    "sg:phone":"+33 1 64 97 08 07",
    "sg:province":"Ile de France",
    "wof:name":"Everlite Concept S.a.",
    "wof:placetype":"venue"
},
  "geometry": {"coordinates":[2.4293,48.624664],"type":"Point"}
}