{
  "type": "Feature",
  "properties": {
    "addr:full":"6, Av. Marcel Langer, 31400 Toulouse Midi Pyr\u00e9n\u00e9es",
    "addr:postcode":"31400",
    "addr:street":"Av. Marcel Langer",
    "iso:country":"FR",
    "sg:address":"6, Av. Marcel Langer, 31400 Toulouse",
    "sg:orig_category":"Unclassifiable Establishments",
    "sg:phone":"+33 5 34 31 92 92",
    "sg:province":"Midi Pyr\u00e9n\u00e9es",
    "wof:name":"D.d.b. The Way S.a.",
    "wof:placetype":"venue"
},
  "geometry": {"coordinates":[1.449483,43.58186],"type":"Point"}
}