{
  "type": "Feature",
  "properties": {
    "iso:country":"FR",
    "sg:address":"16, Rue du Docteur Nancel Penard, 33000 Bordeaux",
    "sg:city":"Bordeaux",
    "sg:orig_category":"Unclassifiable Establishments",
    "sg:phone":"+33 5 56 43 19 65",
    "sg:postcode":"33000",
    "sg:province":"Aquitaine",
    "wof:name":"Pano Boutique S.a.r.l.",
    "wof:placetype":"venue"
},
  "geometry": {"coordinates":[-0.580959,44.839867],"type":"Point"}
}