{
  "type": "Feature",
  "properties": {
    "addr:full":"Le Chene Vert Za 35650 Le Rheu Le Rheu Bretagne 35650",
    "addr:postcode":"35650;35650",
    "addr:street":"Za;Rheu",
    "iso:country":"FR",
    "sg:address":"Le Chene Vert Za 35650 Le Rheu",
    "sg:city":"Le Rheu",
    "sg:classifiers":[
        {
            "category":"Utilities",
            "subcategory":"Electric",
            "type":"Services"
        }
    ],
    "sg:phone":"+33 2 99 14 55 30",
    "sg:postcode":"35650",
    "sg:province":"Bretagne",
    "sg:tags":[
        "electricity",
        "electronic",
        "electrical",
        "equipment"
    ],
    "wof:name":"Cimlec Industrie",
    "wof:placetype":"venue"
},
  "geometry": {"coordinates":[-1.775371,48.080837],"type":"Point"}
}