{
  "type": "Feature",
  "properties": {
    "iso:country":"FR",
    "sg:address":"Zi 25870 Devecey",
    "sg:classifiers":[
        {
            "category":"Manufacturing",
            "subcategory":"Metals",
            "type":"Manufacturing & Wholesale Goods"
        }
    ],
    "sg:phone":"+33 3 81 56 81 08",
    "sg:postcode":"25870",
    "sg:province":"Franche Comt\u00e9",
    "sg:tags":[
        "metallurgy",
        "steel",
        "metalworking"
    ],
    "wof:name":"Brocard Roux Et Compagnie Sa",
    "wof:placetype":"venue"
},
  "geometry": {"coordinates":[6.006115,47.308216],"type":"Point"}
}