{
  "type": "Feature",
  "properties": {
    "iso:country":"FR",
    "sg:address":"9 Rue Pasteur 49450 St Macaire En Mauges",
    "sg:classifiers":[
        {
            "category":"Banks & Credit Unions",
            "subcategory":"Investment Brokerage",
            "type":"Services"
        }
    ],
    "sg:phone":"+33 2 41 49 07 50",
    "sg:province":"Pays de Loire",
    "sg:tags":[
        "-",
        "transport",
        "related"
    ],
    "wof:name":"Drouet Sarl",
    "wof:placetype":"venue"
},
  "geometry": {"coordinates":[-0.994504,47.122128],"type":"Point"}
}