{
  "type": "Feature",
  "properties": {
    "addr:full":"B.P. 8, 33640 Beautiran^^5, Rue Balambits - ZI, 33640 Beautiran Beautiran Aquitaine 33640",
    "addr:housenumber":"8",
    "addr:postcode":"33640;33640;33640",
    "addr:street":"B.P.;Rue Balambits Zi",
    "iso:country":"FR",
    "sg:address":"B.P. 8, 33640 Beautiran^^5, Rue Balambits - ZI, 33640 Beautiran",
    "sg:city":"Beautiran",
    "sg:orig_category":"Non-Classified Establishments",
    "sg:phone":"+33 5 56 67 40 40",
    "sg:postcode":"33640",
    "sg:province":"Aquitaine",
    "wof:name":"Dal'alu S.a.",
    "wof:placetype":"venue"
},
  "geometry": {"coordinates":[-0.402069,44.679958],"type":"Point"}
}