{
  "type": "Feature",
  "properties": {
    "iso:country":"FR",
    "sg:address":"228, RN, 74300 Magland",
    "sg:orig_category":"Non-Classified Establishments",
    "sg:phone":"+33 4 50 34 72 67",
    "sg:province":"Rhone-Alpes",
    "wof:name":"Th\u00e9venet Roch S.a.r.l.",
    "wof:placetype":"venue"
},
  "geometry": {"coordinates":[6.633185,45.987919],"type":"Point"}
}