{
  "type": "Feature",
  "properties": {
    "iso:country":"FR",
    "sg:address":"ZI Couffouleux",
    "sg:city":"Rabastens",
    "sg:orig_category":"Non-Classified Establishments",
    "sg:phone":"+33 5 63 33 73 62",
    "sg:postcode":"81800",
    "sg:province":"Midi Pyr\u00e9n\u00e9es",
    "wof:name":"Soci\u00e9t\u00e9 Nouvelle France V\u00eat. S.a.r.l.",
    "wof:placetype":"venue"
},
  "geometry": {"coordinates":[1.724625,43.822037],"type":"Point"}
}