{
  "type": "Feature",
  "properties": {
    "iso:country":"FR",
    "sg:address":"11 Villa Riberolle 75020 Paris",
    "sg:classifiers":[
        {
            "category":"Manufacturing",
            "subcategory":"Rubber & Plastics",
            "type":"Manufacturing & Wholesale Goods"
        }
    ],
    "sg:phone":"+33 1 43 70 33 53",
    "sg:province":"Ile de France",
    "wof:name":"Societe Industrielle De Moulage Et De Materiel Electrique Simme (simme)",
    "wof:placetype":"venue"
},
  "geometry": {"coordinates":[2.39664,48.857796],"type":"Point"}
}