{
  "type": "Feature",
  "properties": {
    "addr:full":"Rue de l'Eclipse Cergy Ile de France 95800",
    "addr:postcode":"95800",
    "addr:street":"Rue De L'Eclipse;Ile De France",
    "iso:country":"FR",
    "sg:address":"Rue de l'Eclipse",
    "sg:city":"Cergy",
    "sg:orig_category":"Unclassifiable Establishments",
    "sg:phone":"+33 1 34 25 41 11",
    "sg:postcode":"95800",
    "sg:province":"Ile de France",
    "wof:name":"C'vert Paysage S.a.r.l.",
    "wof:placetype":"venue"
},
  "geometry": {"coordinates":[2.035575,49.050365],"type":"Point"}
}