{
  "type": "Feature",
  "properties": {
    "iso:country":"FR",
    "sg:address":"rue de Maurapan 25870 Chatillon Le Duc",
    "sg:classifiers":[
        {
            "category":"Home & Garden",
            "subcategory":"Garden Supply",
            "type":"Retail Goods"
        }
    ],
    "sg:phone":"+33 3 81 47 91 20",
    "sg:province":"Franche Comt\u00e9",
    "sg:tags":[
        "plant",
        "power"
    ],
    "wof:name":"Elec-comtois S.a.",
    "wof:placetype":"venue"
},
  "geometry": {"coordinates":[5.998459,47.293747],"type":"Point"}
}