{
  "type": "Feature",
  "properties": {
    "addr:full":"16, Rue de la Dorini\u00e8re, 17600 Corme Royal Poitou-Charentes",
    "addr:housenumber":"16",
    "addr:postcode":"17600",
    "addr:street":"Rue De La Dorinie\u0300Re;Corme Royal",
    "iso:country":"FR",
    "sg:address":"16, Rue de la Dorini\u00e8re, 17600 Corme Royal",
    "sg:orig_category":"Non-Classified Establishments",
    "sg:phone":"+33 5 46 92 32 32",
    "sg:province":"Poitou-Charentes",
    "wof:name":"P\u00e9pini\u00e8res De Corme Royal S.a.r.l.",
    "wof:placetype":"venue"
},
  "geometry": {"coordinates":[-0.822375,45.740627],"type":"Point"}
}