{
  "type": "Feature",
  "properties": {
    "iso:country":"FR",
    "sg:address":"8 Rue De Marle 02250 Tavaux Et Ponts\u00e9ricourt",
    "sg:orig_category":"Miscellaneous Products",
    "sg:phone":"+33 3 23 20 03 43",
    "sg:postcode":"02250",
    "sg:province":"Picardie",
    "wof:name":"Ets D. Richet",
    "wof:placetype":"venue"
},
  "geometry": {"coordinates":[3.898471,49.730885],"type":"Point"}
}