{
  "type": "Feature",
  "properties": {
    "addr:full":"B.P. 19, 84601 Valr\u00e9as C\u00e9dex^^10, Rte de Grillon, 84600 Valr\u00e9as Languedoc-Roussillon",
    "addr:postcode":"84601;84600",
    "addr:street":"B.P. 19;Rte De Grillon",
    "iso:country":"FR",
    "sg:address":"B.P. 19, 84601 Valr\u00e9as C\u00e9dex^^10, Rte de Grillon, 84600 Valr\u00e9as",
    "sg:orig_category":"Non-Classified Establishments",
    "sg:phone":"+33 4 90 35 04 94",
    "sg:province":"Languedoc-Roussillon",
    "wof:name":"Cartonnage Faure S.a.",
    "wof:placetype":"venue"
},
  "geometry": {"coordinates":[4.911945,44.359257],"type":"Point"}
}