{
  "type": "Feature",
  "properties": {
    "addr:full":"265 Bd Charles Martel Pa Bois Rigaul 62210 Avion Nord Pas-de-Calais 62210",
    "addr:housenumber":"265",
    "addr:postcode":"62210;62210",
    "addr:street":"Bd Charles Martel;Rigaul",
    "iso:country":"FR",
    "sg:address":"265 Bd Charles Martel Pa Bois Rigaul 62210 Avion",
    "sg:classifiers":[
        {
            "category":"Building & Trades",
            "subcategory":"Construction",
            "type":"Services"
        }
    ],
    "sg:phone":"+33 3 21 43 40 00",
    "sg:postcode":"62210",
    "sg:province":"Nord Pas-de-Calais",
    "sg:tags":[
        "work",
        "public"
    ],
    "wof:name":"Ramery B\u00c2timent Sa",
    "wof:placetype":"venue"
},
  "geometry": {"coordinates":[2.83327,50.413349],"type":"Point"}
}