{
  "type": "Feature",
  "properties": {
    "addr:full":"2 Rue Cavenne 69007 Lyon Rhone-Alpes 69007",
    "addr:housenumber":"2",
    "addr:postcode":"69007;69007",
    "addr:street":"Rue Cavenne",
    "iso:country":"FR",
    "sg:address":"2 Rue Cavenne 69007 Lyon",
    "sg:classifiers":[
        {
            "category":"Home & Garden",
            "subcategory":"Furniture",
            "type":"Retail Goods"
        }
    ],
    "sg:phone":"+33 4 72 73 31 82",
    "sg:postcode":"69007",
    "sg:province":"Rhone-Alpes",
    "sg:tags":[
        "household",
        "wood"
    ],
    "wof:name":"Lyon Visa Service Sarl",
    "wof:placetype":"venue"
},
  "geometry": {"coordinates":[4.839702,45.754429],"type":"Point"}
}