{
  "type": "Feature",
  "properties": {
    "iso:country":"FR",
    "sg:address":"12, Rte de Vend\u00f4me, 41800 Les Roches l'Ev\u00eaque",
    "sg:city":"Artins",
    "sg:orig_category":"Unclassifiable Establishments",
    "sg:phone":"+33 2 54 86 41 41",
    "sg:postcode":"41800",
    "sg:province":"Centre",
    "wof:name":"Champignonni\u00e8res Des Roches S.a.",
    "wof:placetype":"venue"
},
  "geometry": {"coordinates":[0.89664,47.786388],"type":"Point"}
}