{
  "type": "Feature",
  "properties": {
    "addr:full":"10 Rue Vauban Bordeaux Aquitaine 33000",
    "addr:housenumber":"10",
    "addr:postcode":"33000",
    "addr:street":"Rue Vauban",
    "iso:country":"FR",
    "sg:address":"10 Rue Vauban",
    "sg:city":"Bordeaux",
    "sg:classifiers":[
        {
            "category":"Banks & Credit Unions",
            "subcategory":"Financial Services",
            "type":"Services"
        }
    ],
    "sg:phone":"+33 5 56 01 94 00",
    "sg:postcode":"33000",
    "sg:province":"Aquitaine",
    "sg:tags":[
        "banking",
        "finance",
        "insurance"
    ],
    "wof:name":"Banque De Laquitaine",
    "wof:placetype":"venue"
},
  "geometry": {"coordinates":[-0.573836,44.847729],"type":"Point"}
}