{
  "type": "Feature",
  "properties": {
    "iso:country":"FR",
    "sg:address":"51 R Bellevue 42308 Roanne Cedex",
    "sg:classifiers":[
        {
            "category":"Real Estate",
            "subcategory":"Surveying",
            "type":"Services"
        }
    ],
    "sg:phone":"+33 4 77 72 35 99",
    "sg:province":"Rhone-Alpes",
    "sg:tags":[
        "leather",
        "raw",
        "material",
        "-",
        "shoe"
    ],
    "wof:name":"Fortier Beaulieu Sas",
    "wof:placetype":"venue"
},
  "geometry": {"coordinates":[4.061351,46.02964],"type":"Point"}
}