{
  "type": "Feature",
  "properties": {
    "addr:full":"1165 Rte Des Alpes 38260 St Hilaire De La C\u00f4te Rhone-Alpes",
    "addr:housenumber":"1165",
    "addr:postcode":"38260",
    "addr:street":"Rte Des Alpes;La Co\u0302Te Rhone-Alpes",
    "iso:country":"FR",
    "sg:address":"1165 Rte Des Alpes 38260 St Hilaire De La C\u00f4te",
    "sg:classifiers":[
        {
            "category":"Manufacturing",
            "subcategory":"Paper Products",
            "type":"Manufacturing & Wholesale Goods"
        }
    ],
    "sg:phone":"+33 4 74 54 60 65",
    "sg:province":"Rhone-Alpes",
    "sg:tags":[
        "packaging",
        "material",
        "-",
        "cardboard"
    ],
    "wof:name":"Tubilaire",
    "wof:placetype":"venue"
},
  "geometry": {"coordinates":[5.314012,45.390892],"type":"Point"}
}