{
  "type": "Feature",
  "properties": {
    "addr:full":"73 Cs Richard Viton 69003 Lyon Rhone-Alpes 69003",
    "addr:housenumber":"cs",
    "addr:postcode":"69003;69003",
    "iso:country":"FR",
    "sg:address":"73 Cs Richard Viton 69003 Lyon",
    "sg:classifiers":[
        {
            "category":"Wholesale",
            "subcategory":"Medical Equipment & Supplies",
            "type":"Manufacturing & Wholesale Goods"
        }
    ],
    "sg:phone":"+33 4 78 53 28 79",
    "sg:postcode":"69003",
    "sg:province":"Rhone-Alpes",
    "sg:tags":[
        "instrument",
        "health",
        "-",
        "precision"
    ],
    "wof:name":"Laboratoire Alfonsi Alain",
    "wof:placetype":"venue"
},
  "geometry": {"coordinates":[4.893129,45.75341],"type":"Point"}
}