{
  "type": "Feature",
  "properties": {
    "addr:full":"ZI de Frimont La R\u00e9ole C\u00e9dex Aquitaine 33191",
    "addr:postcode":"re\u0301ole;33191",
    "addr:street":"Zi De Frimont La",
    "iso:country":"FR",
    "sg:address":"ZI de Frimont",
    "sg:city":"La R\u00e9ole C\u00e9dex",
    "sg:orig_category":"Non-Classified Establishments",
    "sg:phone":"+33 5 56 61 00 59",
    "sg:postcode":"33191",
    "sg:province":"Aquitaine",
    "wof:name":"Maumy Impression S.a.",
    "wof:placetype":"venue"
},
  "geometry": {"coordinates":[-0.054466,44.583031],"type":"Point"}
}