{
  "type": "Feature",
  "properties": {
    "addr:full":"B.P. 11, 26760 Beaumont les Valence^^Rte de Valence - Quartier les Chirons, 26760 Beaumont les Valen Rhone-Alpes 26760",
    "addr:postcode":"26760;26760;26760",
    "addr:street":"B.P. 11;Valence;Les Chirons",
    "iso:country":"FR",
    "sg:address":"B.P. 11, 26760 Beaumont les Valence^^Rte de Valence - Quartier les Chirons, 26760 Beaumont les Valen",
    "sg:orig_category":"Non-Classified Establishments",
    "sg:phone":"+33 4 75 59 73 32",
    "sg:postcode":"26760",
    "sg:province":"Rhone-Alpes",
    "wof:name":"Socma S.a.",
    "wof:placetype":"venue"
},
  "geometry": {"coordinates":[4.94163,44.860664],"type":"Point"}
}