{
  "type": "Feature",
  "properties": {
    "addr:full":"2 Rue Des Vignes 39240 Arinthod Franche Comt\u00e9 39240",
    "addr:housenumber":"2",
    "addr:postcode":"39240;39240",
    "addr:street":"Rue Des Vignes;Franche Comte\u0301",
    "iso:country":"FR",
    "sg:address":"2 Rue Des Vignes 39240 Arinthod",
    "sg:orig_category":"Environment - machinery and equipment Mechanical Engineering - machines Road transport Transport ser",
    "sg:phone":"+33 3 84 48 00 01",
    "sg:postcode":"39240",
    "sg:province":"Franche Comt\u00e9",
    "wof:name":"Besson Transports Sarl",
    "wof:placetype":"venue"
},
  "geometry": {"coordinates":[5.567696,46.389774],"type":"Point"}
}