{
  "type": "Feature",
  "properties": {
    "iso:country":"FR",
    "sg:address":"B.P. 235, 89004 Auxerre C\u00e9dex^^63, Av Jean Mermoz, 89000 Auxerre",
    "sg:city":"Auxerre",
    "sg:orig_category":"Non-Classified Establishments",
    "sg:phone":"+33 3 86 94 41 00",
    "sg:postcode":"89000",
    "sg:province":"Bourgogne",
    "wof:name":"B.p.f. S.a. - Bourgogne Produits Frais",
    "wof:placetype":"venue"
},
  "geometry": {"coordinates":[3.569305,47.796051],"type":"Point"}
}