{
  "type": "Feature",
  "properties": {
    "iso:country":"FR",
    "sg:address":"32, Rue Saint Lazare, 95290 L'Isle Adam",
    "sg:orig_category":"Unclassifiable Establishments",
    "sg:phone":"+33 1 34 69 39 22",
    "sg:province":"Ile de France",
    "wof:name":"Publi Typo S.a.r.l.",
    "wof:placetype":"venue"
},
  "geometry": {"coordinates":[2.217418,49.109917],"type":"Point"}
}