{
  "type": "Feature",
  "properties": {
    "iso:country":"FR",
    "sg:address":"2, Rue du Comey, 88220 Uzemain",
    "sg:orig_category":"Non-Classified Establishments",
    "sg:phone":"+33 3 29 30 85 40",
    "sg:province":"Lorraine",
    "wof:name":"Toda S.a.r.l.",
    "wof:placetype":"venue"
},
  "geometry": {"coordinates":[6.337308,48.103081],"type":"Point"}
}