{
  "type": "Feature",
  "properties": {
    "iso:country":"FR",
    "sg:address":"Z A Nord Du Val De Moder 67350 Niedermodern",
    "sg:city":"Niedermodern",
    "sg:classifiers":[
        {
            "category":"Manufacturing",
            "subcategory":"Paper Products",
            "type":"Manufacturing & Wholesale Goods"
        }
    ],
    "sg:phone":"+33 3 88 05 50 40",
    "sg:postcode":"67350",
    "sg:province":"Alsace",
    "sg:tags":[
        "finished",
        "cardboard",
        "-"
    ],
    "wof:name":"Alsace Techniques Etiquetage (ate)",
    "wof:placetype":"venue"
},
  "geometry": {"coordinates":[7.60881,48.844219],"type":"Point"}
}