{
  "type": "Feature",
  "properties": {
    "addr:full":"11 Av Villiers 77580 Cr\u00e8cy La Chapelle Ile de France 77580",
    "addr:postcode":"77580;77580",
    "addr:street":"11 Av",
    "iso:country":"FR",
    "sg:address":"11 Av Villiers 77580 Cr\u00e8cy La Chapelle",
    "sg:classifiers":[
        {
            "category":"Manufacturing",
            "subcategory":"Wood Products",
            "type":"Manufacturing & Wholesale Goods"
        }
    ],
    "sg:phone":"+33 1 64 63 83 72",
    "sg:postcode":"77580",
    "sg:province":"Ile de France",
    "sg:tags":[
        "machine",
        "engineering",
        "furniture",
        "-",
        "mechanical"
    ],
    "wof:name":"Roeser De Laubriere Noel Snc",
    "wof:placetype":"venue"
},
  "geometry": {"coordinates":[2.905439,48.858459],"type":"Point"}
}