{
  "type": "Feature",
  "properties": {
    "addr:full":"29, Rue Fondary, 75015 Paris Ile de France",
    "addr:housenumber":"29",
    "addr:postcode":"75015",
    "addr:street":"Rue Fondary",
    "iso:country":"FR",
    "sg:address":"29, Rue Fondary, 75015 Paris",
    "sg:orig_category":"Unclassifiable Establishments",
    "sg:phone":"+33 1 45 18 87 37",
    "sg:province":"Ile de France",
    "wof:name":"Apocole S.a.r.l.",
    "wof:placetype":"venue"
},
  "geometry": {"coordinates":[2.293196,48.848232],"type":"Point"}
}