{
  "type": "Feature",
  "properties": {
    "addr:full":"Zi Monay 71210 St Eus\u00e8be Torcy Bourgogne 71210",
    "addr:postcode":"71210;71210",
    "iso:country":"FR",
    "sg:address":"Zi Monay 71210 St Eus\u00e8be",
    "sg:city":"Torcy",
    "sg:classifiers":[
        {
            "category":"Manufacturing",
            "subcategory":"Paper Products",
            "type":"Manufacturing & Wholesale Goods"
        }
    ],
    "sg:phone":"+33 3 85 73 09 00",
    "sg:postcode":"71210",
    "sg:province":"Bourgogne",
    "sg:tags":[
        "packaging",
        "material",
        "-",
        "cardboard"
    ],
    "wof:name":"Cartonnages Francais Lilp Sa - Lgr",
    "wof:placetype":"venue"
},
  "geometry": {"coordinates":[4.463261,46.713284],"type":"Point"}
}