{
  "type": "Feature",
  "properties": {
    "iso:country":"FR",
    "sg:address":"138 Avenue De Provence 84300 Cavaillon",
    "sg:classifiers":[
        {
            "category":"Wholesale",
            "subcategory":"Medical Equipment & Supplies",
            "type":"Manufacturing & Wholesale Goods"
        }
    ],
    "sg:phone":"+33 4 90 71 22 43",
    "sg:province":"Languedoc-Roussillon",
    "sg:tags":[
        "instrument",
        "health",
        "-",
        "precision"
    ],
    "wof:name":"Dental Creation",
    "wof:placetype":"venue"
},
  "geometry": {"coordinates":[5.036439,43.831226],"type":"Point"}
}