{
  "type": "Feature",
  "properties": {
    "addr:full":"la Gare SNCF 03300 Cusset Cusset Auvergne 03300",
    "addr:postcode":"03300;03300",
    "iso:country":"FR",
    "sg:address":"la Gare SNCF 03300 Cusset",
    "sg:city":"Cusset",
    "sg:classifiers":[
        {
            "category":"Manufacturing",
            "subcategory":"Building Materials",
            "type":"Manufacturing & Wholesale Goods"
        }
    ],
    "sg:phone":"+33 4 70 31 84 66",
    "sg:postcode":"03300",
    "sg:province":"Auvergne",
    "sg:tags":[
        "reutilization",
        "residual"
    ],
    "wof:name":"Sorece Sa",
    "wof:placetype":"venue"
},
  "geometry": {"coordinates":[3.47831,46.14436],"type":"Point"}
}