{
  "type": "Feature",
  "properties": {
    "addr:full":"Quai Baptistin Pin 83980 Le Lavandou Franche Comt\u00e9",
    "addr:postcode":"83980",
    "addr:street":"Quai Baptistin Pin;Franche Comte\u0301",
    "iso:country":"FR",
    "sg:address":"Quai Baptistin Pin 83980 Le Lavandou",
    "sg:classifiers":[
        {
            "category":"Autos & Motor Vehicles",
            "subcategory":"Boat Sales",
            "type":"Retail Goods"
        }
    ],
    "sg:phone":"+33 4 94 64 91 10",
    "sg:province":"Franche Comt\u00e9",
    "sg:tags":[
        "equipment",
        "transport"
    ],
    "wof:name":"Euroyachting",
    "wof:placetype":"venue"
},
  "geometry": {"coordinates":[6.373424,43.138039],"type":"Point"}
}