{
  "type": "Feature",
  "properties": {
    "iso:country":"FR",
    "sg:address":"112 Rue Loubon 13003 Marseille",
    "sg:classifiers":[
        {
            "category":"Manufacturing",
            "subcategory":"Jewelry",
            "type":"Manufacturing & Wholesale Goods"
        }
    ],
    "sg:phone":"+33 4 91 64 64 28",
    "sg:province":"Poitou-Charentes",
    "sg:tags":[
        "product",
        "miscellaneous",
        "jewellery"
    ],
    "wof:name":"Provence Fonderie Sarl",
    "wof:placetype":"venue"
},
  "geometry": {"coordinates":[5.383197,43.312729],"type":"Point"}
}