{
  "type": "Feature",
  "properties": {
    "addr:full":"10 La Presle 03170 Doyet Doyet Auvergne 03170",
    "addr:housenumber":"10",
    "addr:postcode":"03170;doyet;03170",
    "addr:street":"La Presle",
    "iso:country":"FR",
    "sg:address":"10 La Presle 03170 Doyet",
    "sg:city":"Doyet",
    "sg:classifiers":[
        {
            "category":"Manufacturing",
            "subcategory":"Glass & Minerals",
            "type":"Manufacturing & Wholesale Goods"
        }
    ],
    "sg:phone":"+33 4 70 07 70 05",
    "sg:postcode":"03170",
    "sg:province":"Auvergne",
    "sg:tags":[
        "building",
        "material"
    ],
    "wof:name":"La Fran\u00c7aise Des Tuiles Et Briques Sarl",
    "wof:placetype":"venue"
},
  "geometry": {"coordinates":[2.819459,46.34911],"type":"Point"}
}