{
  "type": "Feature",
  "properties": {
    "addr:full":"8-10 rue de Buzenval 75020 Paris Ile de France 75020",
    "addr:housenumber":"8-10",
    "addr:postcode":"75020;75020",
    "addr:street":"Rue De Buzenval",
    "iso:country":"FR",
    "sg:address":"8-10 rue de Buzenval 75020 Paris",
    "sg:classifiers":[
        {
            "category":"Wholesale",
            "subcategory":"Metals & Minerals",
            "type":"Manufacturing & Wholesale Goods"
        }
    ],
    "sg:phone":"+33 1 43 73 63 63",
    "sg:postcode":"75020",
    "sg:province":"Ile de France",
    "sg:tags":[
        "articles",
        "industrial"
    ],
    "wof:name":"Gehelle Sa",
    "wof:placetype":"venue"
},
  "geometry": {"coordinates":[2.402315,48.850243],"type":"Point"}
}