{
  "type": "Feature",
  "properties": {
    "iso:country":"FR",
    "sg:address":"33 chemin de la Croix 13270 Fos Sur Mer",
    "sg:classifiers":[
        {
            "category":"Autos & Motor Vehicles",
            "subcategory":"Fuel & Gas Station",
            "type":"Retail Goods"
        }
    ],
    "sg:phone":"+33 4 42 05 57 95",
    "sg:province":"Franche Comt\u00e9",
    "sg:tags":[
        "oil",
        "boreholes",
        "geological",
        "formation",
        "analysis",
        "hydrogeological"
    ],
    "wof:name":"Pib International Sarl",
    "wof:placetype":"venue"
},
  "geometry": {"coordinates":[4.945918,43.433716],"type":"Point"}
}