{
  "type": "Feature",
  "properties": {
    "addr:full":"av Francis M\u00e8ano; Puyloubier Picardie",
    "addr:street":"Av Francis Me\u0300Ano",
    "iso:country":"FR",
    "sg:address":"av Francis M\u00e8ano; Puyloubier",
    "sg:classifiers":[
        {
            "category":"Banks & Credit Unions",
            "subcategory":"Bank",
            "type":"Services"
        }
    ],
    "sg:phone":"+33 3342663162",
    "sg:province":"Picardie",
    "wof:name":"Cr\u00e9dit Agricole",
    "wof:placetype":"venue"
},
  "geometry": {"coordinates":[5.675764,43.525154],"type":"Point"}
}