{
  "type": "Feature",
  "properties": {
    "iso:country":"FR",
    "sg:address":"19, Rue Pierre Loti, 92340 Bourg la Reine",
    "sg:orig_category":"Non-Classified Establishments",
    "sg:phone":"+33 1 46 60 06 06",
    "sg:province":"Ile de France",
    "wof:name":"I.i.f. S.a.r.l. - Instititut International Du Fromage",
    "wof:placetype":"venue"
},
  "geometry": {"coordinates":[2.311494,48.783081],"type":"Point"}
}