{
  "type": "Feature",
  "properties": {
    "addr:full":"64 Boulevard Stanislas Girardin Centre Commercial Bruyeres 76140 Le Petit Quevilly Haute Normandie 76140",
    "addr:housenumber":"64",
    "addr:postcode":"76140;76140",
    "addr:street":"Boulevard Stanislas Girardin Centre;Le Petit Quevilly Haute Normandie",
    "iso:country":"FR",
    "sg:address":"64 Boulevard Stanislas Girardin Centre Commercial Bruyeres 76140 Le Petit Quevilly",
    "sg:classifiers":[
        {
            "category":"Building & Trades",
            "subcategory":"Electrical",
            "type":"Services"
        }
    ],
    "sg:phone":"+33 2 35 69 74 74",
    "sg:postcode":"76140",
    "sg:province":"Haute Normandie",
    "sg:tags":[
        "electronic",
        "lighting",
        "equipment"
    ],
    "wof:name":"Thorn Europhane",
    "wof:placetype":"venue"
},
  "geometry": {"coordinates":[1.06335,49.41679],"type":"Point"}
}