{
  "type": "Feature",
  "properties": {
    "addr:full":"Les Simonni\u00e8res 49125 Tierc\u00e9 Pays de Loire",
    "addr:postcode":"49125",
    "addr:street":"Simonnie\u0300Res",
    "iso:country":"FR",
    "sg:address":"Les Simonni\u00e8res 49125 Tierc\u00e9",
    "sg:orig_category":"Unclassifiable Establishments",
    "sg:phone":"+33 2 41 42 64 36",
    "sg:province":"Pays de Loire",
    "wof:name":"Robert S.a.",
    "wof:placetype":"venue"
},
  "geometry": {"coordinates":[-0.423424,47.623402],"type":"Point"}
}