{
  "type": "Feature",
  "properties": {
    "addr:full":"20 Rte Aumale 80290 Poix De Picardie Picardie",
    "addr:housenumber":"20",
    "addr:postcode":"80290",
    "addr:street":"Rte Aumale;Picardie",
    "iso:country":"FR",
    "sg:address":"20 Rte Aumale 80290 Poix De Picardie",
    "sg:classifiers":[
        {
            "category":"Manufacturing",
            "subcategory":"Paper Products",
            "type":"Manufacturing & Wholesale Goods"
        }
    ],
    "sg:phone":"+33 3 22 90 38 20",
    "sg:province":"Picardie",
    "sg:tags":[
        "raw",
        "material",
        "-",
        "cardboard"
    ],
    "wof:name":"Emin Leydier Emballages Sa",
    "wof:placetype":"venue"
},
  "geometry": {"coordinates":[1.972615,49.781948],"type":"Point"}
}