{
  "type": "Feature",
  "properties": {
    "addr:full":"41bis, Rue de la R\u00e9publique, 76700 Harfleur Haute Normandie",
    "addr:housenumber":"41bis",
    "addr:postcode":"76700",
    "addr:street":"Rue De La Re\u0301Publique;Haute Normandie",
    "iso:country":"FR",
    "sg:address":"41bis, Rue de la R\u00e9publique, 76700 Harfleur",
    "sg:orig_category":"Unclassifiable Establishments",
    "sg:phone":"+33 2 35 45 83 83",
    "sg:province":"Haute Normandie",
    "wof:name":"Iris S.a.r.l.",
    "wof:placetype":"venue"
},
  "geometry": {"coordinates":[0.198608,49.507103],"type":"Point"}
}