{
  "type": "Feature",
  "properties": {
    "addr:full":"L'Aguillou 81800 Coufouleux Midi Pyr\u00e9n\u00e9es",
    "addr:postcode":"81800",
    "addr:street":"L'Aguillou",
    "iso:country":"FR",
    "sg:address":"L'Aguillou 81800 Coufouleux",
    "sg:classifiers":[
        {
            "category":"Professional",
            "type":"Services"
        }
    ],
    "sg:phone":"+33 5 63 33 81 42",
    "sg:province":"Midi Pyr\u00e9n\u00e9es",
    "sg:tags":[
        "transport",
        "road"
    ],
    "wof:name":"Rivet-muratet Sa",
    "wof:placetype":"venue"
},
  "geometry": {"coordinates":[1.746863,43.811581],"type":"Point"}
}