{
  "type": "Feature",
  "properties": {
    "iso:country":"FR",
    "sg:address":"5 place de la R\u00e9publique 64100 Bayonne",
    "sg:city":"Bayonne",
    "sg:classifiers":[
        {
            "category":"Social Services",
            "subcategory":"Adult Care",
            "type":"Services"
        }
    ],
    "sg:phone":"+33 5 59 55 45 64",
    "sg:postcode":"64100",
    "sg:province":"Aquitaine",
    "sg:tags":[
        "consulting",
        "management",
        "corporate"
    ],
    "wof:name":"Negometal Sarl",
    "wof:placetype":"venue"
},
  "geometry": {"coordinates":[-1.470549,43.495251],"type":"Point"}
}