{
  "type": "Feature",
  "properties": {
    "addr:full":"4, Rue du 11 Novembre 1918, 31150 Brugui\u00e8res Midi Pyr\u00e9n\u00e9es",
    "addr:housenumber":"4",
    "addr:postcode":"31150",
    "addr:street":"Rue Du 11 Novembre 1918",
    "iso:country":"FR",
    "sg:address":"4, Rue du 11 Novembre 1918, 31150 Brugui\u00e8res",
    "sg:orig_category":"Non-Classified Establishments",
    "sg:phone":"+33 5 61 82 92 59",
    "sg:province":"Midi Pyr\u00e9n\u00e9es",
    "wof:name":"Sat\u00e9co S.a.",
    "wof:placetype":"venue"
},
  "geometry": {"coordinates":[1.414575,43.722233],"type":"Point"}
}