{
  "type": "Feature",
  "properties": {
    "iso:country":"FR",
    "sg:address":"120 all\u00e9e des Erables 95700 ROISSY EN FRANCE",
    "sg:classifiers":[
        {
            "category":"Manufacturing",
            "subcategory":"Rubber & Plastics",
            "type":"Manufacturing & Wholesale Goods"
        }
    ],
    "sg:phone":"+33 1 49 89 07 97",
    "sg:province":"Ile de France",
    "sg:tags":[
        "coating"
    ],
    "wof:name":"Societe D'etudes Et Methodes Des Matieres Plastiques S.a.",
    "wof:placetype":"venue"
},
  "geometry": {"coordinates":[2.517005,49.003883],"type":"Point"}
}