{
  "type": "Feature",
  "properties": {
    "addr:full":"607, Bd Jean Moulin, 83700 Saint Rapha\u00ebl Basse Normandie",
    "addr:housenumber":"607",
    "addr:postcode":"83700",
    "addr:street":"Bd Jean Moulin",
    "iso:country":"FR",
    "sg:address":"607, Bd Jean Moulin, 83700 Saint Rapha\u00ebl",
    "sg:orig_category":"Non-Classified Establishments",
    "sg:phone":"+33 4 94 95 13 44",
    "sg:province":"Basse Normandie",
    "wof:name":"Deschamps P\u00e8re Et Fils",
    "wof:placetype":"venue"
},
  "geometry": {"coordinates":[6.781273,43.427914],"type":"Point"}
}