{
  "type": "Feature",
  "properties": {
    "iso:country":"FR",
    "sg:address":"8, Av. du Cinq Mars, 95100 Argenteuil",
    "sg:orig_category":"Non-Classified Establishments",
    "sg:phone":"+33 1 39 61 14 29",
    "sg:postcode":"95100",
    "sg:province":"Ile de France",
    "wof:name":"Alcor Sarrazin Industrie S.a.r.l.",
    "wof:placetype":"venue"
},
  "geometry": {"coordinates":[2.230585,48.936508],"type":"Point"}
}