{
  "type": "Feature",
  "properties": {
    "iso:country":"FR",
    "sg:address":"Rte de la Feri\u00e8re",
    "sg:city":"La Merlati\u00e8re",
    "sg:orig_category":"Unclassifiable Establishments",
    "sg:phone":"+33 2 51 40 52 16",
    "sg:postcode":"85140",
    "sg:province":"Pays de Loire",
    "wof:name":"D.n.l. S.a. - Diffusion National Du Livre",
    "wof:placetype":"venue"
},
  "geometry": {"coordinates":[-1.303629,46.765949],"type":"Point"}
}