{
  "type": "Feature",
  "properties": {
    "addr:full":"5 Rue Du Sompre 88700 Bult Lorraine 88700",
    "addr:housenumber":"5",
    "addr:postcode":"88700;88700",
    "addr:street":"Rue Du Sompre",
    "iso:country":"FR",
    "sg:address":"5 Rue Du Sompre 88700 Bult",
    "sg:classifiers":[
        {
            "category":"Farming",
            "subcategory":"Farm & Veterinary Services",
            "type":"Manufacturing & Wholesale Goods"
        }
    ],
    "sg:phone":"+33 3 29 65 71 42",
    "sg:postcode":"88700",
    "sg:province":"Lorraine",
    "sg:tags":[
        "advice",
        "agriculture",
        "livestock",
        "business"
    ],
    "wof:name":"Bois Et Travaux",
    "wof:placetype":"venue"
},
  "geometry": {"coordinates":[6.60995,48.293781],"type":"Point"}
}