{
  "type": "Feature",
  "properties": {
    "iso:country":"FR",
    "sg:address":"38, Rue de la Commune de Paris, 93300 Aubervilliers",
    "sg:orig_category":"Non-Classified Establishments",
    "sg:phone":"+33 1 48 33 66 79",
    "sg:postcode":"93300",
    "sg:province":"Ile de France",
    "wof:name":"Escoube Impressions S.a.r.l.",
    "wof:placetype":"venue"
},
  "geometry": {"coordinates":[2.38048,48.911129],"type":"Point"}
}