{
  "type": "Feature",
  "properties": {
    "addr:full":"B.P. 20192, 57005 Metz C\u00e9dex 1^^5, Av. Joffre, 57000 Metz Lorraine 57000",
    "addr:housenumber":"1 ^ ^ 5",
    "addr:postcode":"57005;57000;57000",
    "addr:street":"Ce\u0301Dex;Av. Joffre",
    "iso:country":"FR",
    "sg:address":"B.P. 20192, 57005 Metz C\u00e9dex 1^^5, Av. Joffre, 57000 Metz",
    "sg:orig_category":"Non-Classified Establishments",
    "sg:phone":"+33 3 87 65 53 68",
    "sg:postcode":"57000",
    "sg:province":"Lorraine",
    "wof:name":"B.g.l. Bail S.a.",
    "wof:placetype":"venue"
},
  "geometry": {"coordinates":[6.183995,49.07645],"type":"Point"}
}