{
  "type": "Feature",
  "properties": {
    "addr:full":"32, Rue Mollien, 62100 Calais Nord Pas-de-Calais",
    "addr:housenumber":"32",
    "addr:postcode":"62100",
    "addr:street":"Rue Mollien;Calais;Pas-De-Calais",
    "iso:country":"FR",
    "sg:address":"32, Rue Mollien, 62100 Calais",
    "sg:orig_category":"Unclassifiable Establishments",
    "sg:phone":"+33 3 21 96 52 14",
    "sg:province":"Nord Pas-de-Calais",
    "wof:name":"B\u00e2timent Am\u00e9nagement Construction S.a.r.l.",
    "wof:placetype":"venue"
},
  "geometry": {"coordinates":[1.860368,50.954769],"type":"Point"}
}