{
  "type": "Feature",
  "properties": {
    "iso:country":"FR",
    "sg:address":"10, Av. de la R\u00e9publique, 92130 Issy les Moulineaux",
    "sg:orig_category":"Unclassifiable Establishments",
    "sg:phone":"+33 1 46 44 69 40",
    "sg:province":"Ile de France",
    "wof:name":"Cotelec S.a.",
    "wof:placetype":"venue"
},
  "geometry": {"coordinates":[2.273387,48.82666],"type":"Point"}
}