{
  "type": "Feature",
  "properties": {
    "addr:full":"Rte De Grenoble Ld Le Bon 38510 Vezeronce Curtin Rhone-Alpes 38510",
    "addr:postcode":"38510;38510",
    "addr:street":"Rte De Grenoble Ld Le Bon",
    "iso:country":"FR",
    "sg:address":"Rte De Grenoble Ld Le Bon 38510 Vezeronce Curtin",
    "sg:orig_category":"Agriculture and Livestock Chemicals and Pharmaceuticals Horticulture",
    "sg:phone":"+33 4 74 80 05 35",
    "sg:postcode":"38510",
    "sg:province":"Rhone-Alpes",
    "wof:name":"Alpha",
    "wof:placetype":"venue"
},
  "geometry": {"coordinates":[5.475785,45.635395],"type":"Point"}
}