{
  "type": "Feature",
  "properties": {
    "addr:full":"47, Rue Saint Just, 94200 Ivry sur Seine Ile de France",
    "addr:housenumber":"47",
    "addr:postcode":"94200",
    "addr:street":"Rue Saint Just",
    "iso:country":"FR",
    "sg:address":"47, Rue Saint Just, 94200 Ivry sur Seine",
    "sg:orig_category":"Non-Classified Establishments",
    "sg:phone":"+33 1 46 58 98 99",
    "sg:province":"Ile de France",
    "wof:name":"Vientiane Distribution S.a.r.l.",
    "wof:placetype":"venue"
},
  "geometry": {"coordinates":[2.386959,48.809372],"type":"Point"}
}