{
  "type": "Feature",
  "properties": {
    "addr:full":"37, Rue Lafayette, 75009 Paris Ile de France",
    "addr:housenumber":"37",
    "addr:postcode":"75009",
    "addr:street":"Rue Lafayette",
    "iso:country":"FR",
    "sg:address":"37, Rue Lafayette, 75009 Paris",
    "sg:orig_category":"Non-Classified Establishments",
    "sg:phone":"+33 1 55 07 97 50",
    "sg:province":"Ile de France",
    "wof:name":"Netpartage S.a.",
    "wof:placetype":"venue"
},
  "geometry": {"coordinates":[2.340605,48.87368],"type":"Point"}
}