{
  "type": "Feature",
  "properties": {
    "iso:country":"FR",
    "sg:address":"15, Rue du Ch\u00e2teau, 50250 La Haye du Puits",
    "sg:city":"Neuville-en-Beaumont",
    "sg:orig_category":"Non-Classified Establishments",
    "sg:phone":"+33 2 33 46 03 01",
    "sg:postcode":"50250",
    "sg:province":"Basse Normandie",
    "wof:name":"Soci\u00e9t\u00e9 D'exploitation Etablissement Armand Laurent S.a.r.l.",
    "wof:placetype":"venue"
},
  "geometry": {"coordinates":[-1.544662,49.293854],"type":"Point"}
}