{
  "type": "Feature",
  "properties": {
    "addr:full":"B.P. 97, 95101 Argenteuil C\u00e9dex^^56, Rte de Pontoise, 95100 Argenteuil Ile de France",
    "addr:postcode":"95101;95100;ile",
    "addr:street":"B.P. 97;Rte De Pontoise",
    "iso:country":"FR",
    "sg:address":"B.P. 97, 95101 Argenteuil C\u00e9dex^^56, Rte de Pontoise, 95100 Argenteuil",
    "sg:orig_category":"Non-Classified Establishments",
    "sg:phone":"+33 1 39 82 46 03",
    "sg:province":"Ile de France",
    "wof:name":"M\u00e9co Concept Soreve S.a.",
    "wof:placetype":"venue"
},
  "geometry": {"coordinates":[2.245075,48.942097],"type":"Point"}
}