{
  "type": "Feature",
  "properties": {
    "addr:full":"91 Av De La 1e Division Blind Mulhouse Alsace 68100",
    "addr:postcode":"68100",
    "addr:street":"91 Av De La 1E Division Blind Mulhouse",
    "iso:country":"FR",
    "sg:address":"91 Av De La 1e Division Blind",
    "sg:city":"Mulhouse",
    "sg:classifiers":[
        {
            "category":"Banks & Credit Unions",
            "subcategory":"Financial Services",
            "type":"Services"
        }
    ],
    "sg:phone":"+33 3 89 65 52 65",
    "sg:postcode":"68100",
    "sg:province":"Alsace",
    "sg:tags":[
        "banking",
        "finance",
        "insurance"
    ],
    "wof:name":"Zuber Laederich",
    "wof:placetype":"venue"
},
  "geometry": {"coordinates":[7.345023,47.732677],"type":"Point"}
}