{
  "type": "Feature",
  "properties": {
    "iso:country":"FR",
    "sg:address":"Le Grand Plan",
    "sg:city":"Ollioules",
    "sg:orig_category":"Unclassifiable Establishments",
    "sg:phone":"+33 4 94 63 04 84",
    "sg:postcode":"83190",
    "sg:province":"Provence-Alpes-C\u00f4te d'Azur",
    "wof:name":"M.a.r.c.a. S.a.r.l. - Manufacture D'anches Et Roseaux De La C\u00f4te D'azur",
    "wof:placetype":"venue"
},
  "geometry": {"coordinates":[5.841364,43.123634],"type":"Point"}
}