{
  "type": "Feature",
  "properties": {
    "iso:country":"FR",
    "sg:address":"1, Rue Albert Einstein, 77420 Champs sur Marne",
    "sg:orig_category":"Non-Classified Establishments",
    "sg:phone":"+33 1 64 61 86 50",
    "sg:province":"Ile de France",
    "wof:name":"No\u00e9matics S.a.r.l.",
    "wof:placetype":"venue"
},
  "geometry": {"coordinates":[2.585612,48.837643],"type":"Point"}
}