{
  "type": "Feature",
  "properties": {
    "iso:country":"FR",
    "sg:address":"ZA les Granges Hautes",
    "sg:city":"Auxonne",
    "sg:orig_category":"Unclassifiable Establishments",
    "sg:phone":"+33 3 80 48 16 80",
    "sg:postcode":"21130",
    "sg:province":"Bourgogne",
    "wof:name":"C.2.b. Magnets S.a.",
    "wof:placetype":"venue"
},
  "geometry": {"coordinates":[5.389957,47.19239],"type":"Point"}
}