{
  "type": "Feature",
  "properties": {
    "addr:full":"45, Bd Vincent Auriol, 75013 Paris Ile de France 75013",
    "addr:housenumber":"45",
    "addr:postcode":"75013;75013",
    "addr:street":"Bd Vincent Auriol",
    "iso:country":"FR",
    "sg:address":"45, Bd Vincent Auriol, 75013 Paris",
    "sg:orig_category":"Non-Classified Establishments",
    "sg:phone":"+33 1 44 24 08 09",
    "sg:postcode":"75013",
    "sg:province":"Ile de France",
    "wof:name":"Cicad Consultants S.a.r.l.",
    "wof:placetype":"venue"
},
  "geometry": {"coordinates":[2.369933,48.835308],"type":"Point"}
}