{
  "type": "Feature",
  "properties": {
    "iso:country":"FR",
    "sg:address":"9, Chauss\u00e9e Jules C\u00e9sar - Evolic 333, 95520 Osny",
    "sg:orig_category":"Unclassifiable Establishments",
    "sg:phone":"+33 1 34 41 67 90",
    "sg:province":"Ile de France",
    "wof:name":"Menrad S.a.",
    "wof:placetype":"venue"
},
  "geometry": {"coordinates":[2.064945,49.064018],"type":"Point"}
}