{
  "type": "Feature",
  "properties": {
    "iso:country":"FR",
    "sg:address":"B.P. 7, 38231 Pont de Ch\u00e9ruy C\u00e9dex^^ZI de Chavanoz, 38230 Pont de Ch\u00e9ruy",
    "sg:orig_category":"Non-Classified Establishments",
    "sg:phone":"+33 4 72 46 16 26",
    "sg:postcode":"38230",
    "sg:province":"Rhone-Alpes",
    "wof:name":"Erard S.a.",
    "wof:placetype":"venue"
},
  "geometry": {"coordinates":[5.160112,45.745178],"type":"Point"}
}