{
  "type": "Feature",
  "properties": {
    "iso:country":"FR",
    "sg:address":"79 av Alfred Anatole Th\u00e9venet 51530 Magenta",
    "sg:classifiers":[
        {
            "category":"Manufacturing",
            "subcategory":"Chemicals & Compounds",
            "type":"Manufacturing & Wholesale Goods"
        }
    ],
    "sg:phone":"+33 3 26 51 56 45",
    "sg:province":"Aquitaine",
    "sg:tags":[
        "base"
    ],
    "wof:name":"Sofralab Sa",
    "wof:placetype":"venue"
},
  "geometry": {"coordinates":[3.965193,49.053314],"type":"Point"}
}