{
  "type": "Feature",
  "properties": {
    "iso:country":"FR",
    "sg:address":"6 Rue De Chambray 37300 Joue Les Tours",
    "sg:city":"Jou\u00e9-l\u00e8s-Tours",
    "sg:orig_category":"Miscellaneous Products Motor-cars Sport Vehicles and Transport Equipment",
    "sg:phone":"+33 2 47 80 26 00",
    "sg:postcode":"37300",
    "sg:province":"Centre",
    "wof:name":"Aerazur",
    "wof:placetype":"venue"
},
  "geometry": {"coordinates":[0.673532,47.354023],"type":"Point"}
}