{
  "type": "Feature",
  "properties": {
    "addr:full":"Rte des 4 Saisons - ZA de Fontevieille - B\u00e2t 1 Allauch Midi Pyr\u00e9n\u00e9es 13190",
    "addr:housenumber":"1",
    "addr:postcode":"13190",
    "addr:street":"Rte Des 4 Saisons Za De Fontevieille Ba\u0302T",
    "iso:country":"FR",
    "sg:address":"Rte des 4 Saisons - ZA de Fontevieille - B\u00e2t 1",
    "sg:city":"Allauch",
    "sg:orig_category":"Unclassifiable Establishments",
    "sg:phone":"+33 4 91 07 72 07",
    "sg:postcode":"13190",
    "sg:province":"Midi Pyr\u00e9n\u00e9es",
    "wof:name":"Clean City Mach Electronic Group S.a.r.l.",
    "wof:placetype":"venue"
},
  "geometry": {"coordinates":[5.488955,43.330566],"type":"Point"}
}