{
  "type": "Feature",
  "properties": {
    "iso:country":"FR",
    "sg:address":"Avenue Des Aureats 26000 Valence",
    "sg:classifiers":[
        {
            "category":"Manufacturing",
            "subcategory":"Building Materials",
            "type":"Manufacturing & Wholesale Goods"
        }
    ],
    "sg:phone":"+33 4 75 44 06 90",
    "sg:postcode":"26000",
    "sg:province":"Rhone-Alpes",
    "sg:tags":[
        "glass",
        "ceramic"
    ],
    "wof:name":"Depot Services Carrelages",
    "wof:placetype":"venue"
},
  "geometry": {"coordinates":[4.884193,44.900108],"type":"Point"}
}