{
  "type": "Feature",
  "properties": {
    "addr:full":"13, Rue du H\u00e9ron, 67300 Schiltigheim Schiltigheim Alsace 67300",
    "addr:housenumber":"13",
    "addr:postcode":"67300;67300",
    "addr:street":"Rue Du He\u0301Ron",
    "iso:country":"FR",
    "sg:address":"13, Rue du H\u00e9ron, 67300 Schiltigheim",
    "sg:city":"Schiltigheim",
    "sg:orig_category":"Non-Classified Establishments",
    "sg:phone":"+33 3 88 62 24 25",
    "sg:postcode":"67300",
    "sg:province":"Alsace",
    "wof:name":"Leica Geosystem Topo Center",
    "wof:placetype":"venue"
},
  "geometry": {"coordinates":[7.770149,48.62093],"type":"Point"}
}