{
  "type": "Feature",
  "properties": {
    "addr:full":"Place des Moines Langogne Languedoc-Roussillon 48300",
    "addr:postcode":"48300",
    "addr:street":"Place",
    "iso:country":"FR",
    "sg:address":"Place des Moines",
    "sg:city":"Langogne",
    "sg:orig_category":"Unclassifiable Establishments",
    "sg:phone":"+33 4 66 69 26 27",
    "sg:postcode":"48300",
    "sg:province":"Languedoc-Roussillon",
    "wof:name":"S.s.i. Loz\u00e8re Informatique S.a.r.l.",
    "wof:placetype":"venue"
},
  "geometry": {"coordinates":[3.854964,44.726955],"type":"Point"}
}