{
  "type": "Feature",
  "properties": {
    "iso:country":"FR",
    "sg:address":"58 Av Du Mar\u00e9chal Foch 86100 Ch\u00e2tellerault",
    "sg:classifiers":[
        {
            "category":"Wholesale",
            "subcategory":"Medical Equipment & Supplies",
            "type":"Manufacturing & Wholesale Goods"
        }
    ],
    "sg:phone":"+33 5 49 21 09 76",
    "sg:postcode":"86100",
    "sg:province":"Poitou-Charentes",
    "sg:tags":[
        "instrument",
        "health",
        "-",
        "precision"
    ],
    "wof:name":"Cabinet De Radiologie Des Docteurs Abbadie Michel Pallado Gilles Rabi",
    "wof:placetype":"venue"
},
  "geometry": {"coordinates":[0.555474,46.820518],"type":"Point"}
}