{
  "type": "Feature",
  "properties": {
    "addr:full":"81660 Pont de Larn Midi Pyr\u00e9n\u00e9es",
    "addr:postcode":"81660",
    "iso:country":"FR",
    "sg:address":"81660 Pont de Larn",
    "sg:orig_category":"Unclassifiable Establishments",
    "sg:phone":"+33 5 63 61 08 23",
    "sg:province":"Midi Pyr\u00e9n\u00e9es",
    "wof:name":"Delainage Des Calmettes S.a.r.l.",
    "wof:placetype":"venue"
},
  "geometry": {"coordinates":[2.405188,43.503761],"type":"Point"}
}