{
  "type": "Feature",
  "properties": {
    "addr:full":"43 Rue Bayern 75017 Paris Ile de France 75017",
    "addr:housenumber":"43",
    "addr:postcode":"75017;75017",
    "addr:street":"Rue Bayern",
    "iso:country":"FR",
    "sg:address":"43 Rue Bayern 75017 Paris",
    "sg:classifiers":[
        {
            "category":"Government",
            "subcategory":"Department Of Motor Vehicles",
            "type":"Public Place"
        }
    ],
    "sg:phone":"+33 1 40 55 20 20",
    "sg:postcode":"75017",
    "sg:province":"Ile de France",
    "sg:tags":[
        "engine",
        "motor-cars",
        "-",
        "machine",
        "equipment",
        "engineering",
        "part",
        "mechanical",
        "transport"
    ],
    "wof:name":"Valeo Sa",
    "wof:placetype":"venue"
},
  "geometry": {"coordinates":[2.318885,48.883629],"type":"Point"}
}