{
  "type": "Feature",
  "properties": {
    "iso:country":"FR",
    "sg:address":"33, Av. des Fr\u00e8res Montgolfier, 69680 Chassieu",
    "sg:orig_category":"Non-Classified Establishments",
    "sg:phone":"+33 4 78 90 04 94",
    "sg:postcode":"69680",
    "sg:province":"Rhone-Alpes",
    "wof:name":"Alliedsignal Aftermarket Europe Honywelle",
    "wof:placetype":"venue"
},
  "geometry": {"coordinates":[4.971809,45.724163],"type":"Point"}
}