{
  "type": "Feature",
  "properties": {
    "addr:full":"62 Av Des Champs Elys\u00e9es 75008 Paris Ile de France 75008",
    "addr:postcode":"75008;75008",
    "addr:street":"62 Av Des Champs Elyse\u0301Es",
    "iso:country":"FR",
    "sg:address":"62 Av Des Champs Elys\u00e9es 75008 Paris",
    "sg:classifiers":[
        {
            "category":"Travel",
            "subcategory":"Hotels & Motels",
            "type":"Entertainment"
        }
    ],
    "sg:phone":"+33 1 45 63 06 06",
    "sg:postcode":"75008",
    "sg:province":"Ile de France",
    "sg:tags":[
        "hotels",
        "business",
        "restaurant"
    ],
    "wof:name":"Restaurant Quick",
    "wof:placetype":"venue"
},
  "geometry": {"coordinates":[2.305221,48.870636],"type":"Point"}
}