{
  "type": "Feature",
  "properties": {
    "addr:full":"1 rue Doct.Michel; L'Arbresle Picardie",
    "addr:housenumber":"1",
    "addr:street":"Rue Doct.Michel",
    "iso:country":"FR",
    "sg:address":"1 rue Doct.Michel; L'Arbresle",
    "sg:classifiers":[
        {
            "category":"Banks & Credit Unions",
            "subcategory":"Bank",
            "type":"Services"
        }
    ],
    "sg:phone":"+33 3374011283",
    "sg:province":"Picardie",
    "wof:name":"Societ\u00e9 G\u00e9n\u00e9rale",
    "wof:placetype":"venue"
},
  "geometry": {"coordinates":[4.615032,45.83659],"type":"Point"}
}