{
  "type": "Feature",
  "properties": {
    "addr:full":"21 Bd Jean Mermoz 13700 Marignane Centre",
    "addr:housenumber":"21",
    "addr:postcode":"13700",
    "addr:street":"Bd Jean Mermoz",
    "iso:country":"FR",
    "sg:address":"21 Bd Jean Mermoz 13700 Marignane",
    "sg:classifiers":[
        {
            "category":"Banks & Credit Unions",
            "subcategory":"Financial Services",
            "type":"Services"
        }
    ],
    "sg:phone":"+33 4 42 31 72 72",
    "sg:province":"Centre",
    "sg:tags":[
        "banking",
        "insurance",
        "institution",
        "finance"
    ],
    "wof:name":"Credit Lyonnais",
    "wof:placetype":"venue"
},
  "geometry": {"coordinates":[5.214114,43.417881],"type":"Point"}
}