{
  "type": "Feature",
  "properties": {
    "addr:full":"79 All De Beauregard BP 188 07104 Annonay Cedex Annonay Rhone-Alpes 07100",
    "addr:housenumber":"79;188",
    "addr:postcode":"07104;07100",
    "addr:street":"All De Beauregard Bp",
    "iso:country":"FR",
    "sg:address":"79 All De Beauregard BP 188 07104 Annonay Cedex",
    "sg:city":"Annonay",
    "sg:classifiers":[
        {
            "category":"Building & Trades",
            "subcategory":"Electrical",
            "type":"Services"
        }
    ],
    "sg:phone":"+33 4 75 67 61 55",
    "sg:postcode":"07100",
    "sg:province":"Rhone-Alpes",
    "sg:tags":[
        "electronic",
        "lighting",
        "equipment"
    ],
    "wof:name":"J Grenot Sa",
    "wof:placetype":"venue"
},
  "geometry": {"coordinates":[4.659016,45.256001],"type":"Point"}
}