{
  "type": "Feature",
  "properties": {
    "addr:full":"ZA Nueil les Aubiers Poitou-Charentes 79250",
    "addr:postcode":"79250",
    "addr:street":"Za Nueil Les Aubiers",
    "iso:country":"FR",
    "sg:address":"ZA",
    "sg:city":"Nueil les Aubiers",
    "sg:orig_category":"Non-Classified Establishments",
    "sg:phone":"+33 5 49 65 42 15",
    "sg:postcode":"79250",
    "sg:province":"Poitou-Charentes",
    "wof:name":"S.m.m. S.a.",
    "wof:placetype":"venue"
},
  "geometry": {"coordinates":[-0.590424,46.95528],"type":"Point"}
}