{
  "type": "Feature",
  "properties": {
    "iso:country":"FR",
    "sg:address":"1, Rue de Crucy, 44944 Nantes C\u00e9dex 09^^1, Rue Crucy, 44900 Nantes",
    "sg:orig_category":"Non-Classified Establishments",
    "sg:phone":"+33 2 40 99 25 25",
    "sg:province":"R\u00e9gion Pays de la Loire",
    "wof:name":"O.f.u.p. S.a. - Office Universitaire De Presse",
    "wof:placetype":"venue"
},
  "geometry": {"coordinates":[-1.54947,47.219791],"type":"Point"}
}