{
  "type": "Feature",
  "properties": {
    "iso:country":"FR",
    "sg:address":"B.P. 15, 35801 Dinard C\u00e9dex^^2, Rue Gramme, 35800 Dinard",
    "sg:city":"Dinard",
    "sg:orig_category":"Non-Classified Establishments",
    "sg:phone":"+33 2 99 16 35 33",
    "sg:postcode":"35800",
    "sg:province":"Bretagne",
    "wof:name":"Harbour Investissement S.a.r.l.",
    "wof:placetype":"venue"
},
  "geometry": {"coordinates":[-2.136755,48.624207],"type":"Point"}
}