{
  "type": "Feature",
  "properties": {
    "addr:full":"37, Rue Marboeuf, 75008 Paris Ile de France",
    "addr:housenumber":"37",
    "addr:postcode":"75008",
    "addr:street":"Rue Marboeuf",
    "iso:country":"FR",
    "sg:address":"37, Rue Marboeuf, 75008 Paris",
    "sg:orig_category":"Non-Classified Establishments",
    "sg:phone":"+33 1 56 43 43 43",
    "sg:province":"Ile de France",
    "wof:name":"Mincitude Di\u00e9t\u00e9tique France S.a.r.l.",
    "wof:placetype":"venue"
},
  "geometry": {"coordinates":[2.305424,48.869816],"type":"Point"}
}