{
  "type": "Feature",
  "properties": {
    "addr:full":"27, Rue des Petits Foss\u00e9s, 61200 Argentan Argentan Basse Normandie 61200",
    "addr:housenumber":"27",
    "addr:postcode":"61200;61200",
    "addr:street":"Rue Des Petits Fosse\u0301S",
    "iso:country":"FR",
    "sg:address":"27, Rue des Petits Foss\u00e9s, 61200 Argentan",
    "sg:city":"Argentan",
    "sg:orig_category":"Non-Classified Establishments",
    "sg:phone":"+33 2 33 67 09 11",
    "sg:postcode":"61200",
    "sg:province":"Basse Normandie",
    "wof:name":"P.r.o.",
    "wof:placetype":"venue"
},
  "geometry": {"coordinates":[-0.018735,48.749561],"type":"Point"}
}