{
  "type": "Feature",
  "properties": {
    "iso:country":"FR",
    "sg:address":"28, Rue de la Convention, 93120 La Courneuve",
    "sg:orig_category":"Non-Classified Establishments",
    "sg:phone":"+33 1 48 36 00 11",
    "sg:province":"Ile de France",
    "wof:name":"S.c.m.m.s.c. S.a.r.l. - Soci\u00e9t\u00e9 De Construction Menuiserie M\u00e9tallique Ser",
    "wof:placetype":"venue"
},
  "geometry": {"coordinates":[2.388273,48.928562],"type":"Point"}
}