{
  "type": "Feature",
  "properties": {
    "iso:country":"FR",
    "sg:address":"6 Avenue De L'Atlantique Za De Courtaboeuf 91955 Les Ulis Cedex",
    "sg:classifiers":[
        {
            "category":"Shopping",
            "subcategory":"Computers & Home Electronics",
            "type":"Retail Goods"
        }
    ],
    "sg:phone":"+33 1 69 07 70 71",
    "sg:province":"Aquitaine",
    "sg:tags":[
        "equipment",
        "electrical",
        "component",
        "electric",
        "electronic"
    ],
    "wof:name":"Systronic S.a.",
    "wof:placetype":"venue"
},
  "geometry": {"coordinates":[2.19902,48.680809],"type":"Point"}
}