{
  "type": "Feature",
  "properties": {
    "addr:full":"22 Rue Jean Baptiste Potin 92130 Issy Les Moulineaux Ile de France 92130",
    "addr:housenumber":"22",
    "addr:postcode":"92130;92130",
    "addr:street":"Rue Jean Baptiste Potin",
    "iso:country":"FR",
    "sg:address":"22 Rue Jean Baptiste Potin 92130 Issy Les Moulineaux",
    "sg:classifiers":[
        {
            "category":"Manufacturing",
            "subcategory":"Metals",
            "type":"Manufacturing & Wholesale Goods"
        }
    ],
    "sg:phone":"+33 1 46 45 09 74",
    "sg:postcode":"92130",
    "sg:province":"Ile de France",
    "sg:tags":[
        "-",
        "machine",
        "equipment",
        "engineering",
        "machinery",
        "mechanical"
    ],
    "wof:name":"Societe A Breton",
    "wof:placetype":"venue"
},
  "geometry": {"coordinates":[2.28039,48.819572],"type":"Point"}
}