{
  "type": "Feature",
  "properties": {
    "iso:country":"FR",
    "sg:address":"4 Rue Frantz Toussaint 64110 Juran\u00e7on",
    "sg:city":"Juran\u00e7on",
    "sg:classifiers":[
        {
            "category":"Wholesale",
            "subcategory":"Meat",
            "type":"Manufacturing & Wholesale Goods"
        }
    ],
    "sg:phone":"+33 5 59 06 22 43",
    "sg:postcode":"64110",
    "sg:province":"Aquitaine",
    "sg:tags":[
        "food",
        "cooked",
        "product",
        "related"
    ],
    "wof:name":"Ste D Exploitation Fromagerie D Ossau Sarl",
    "wof:placetype":"venue"
},
  "geometry": {"coordinates":[-0.385785,43.287136],"type":"Point"}
}