{
  "type": "Feature",
  "properties": {
    "addr:full":"RN 97 - A57 Sortie N\u00b08 Sollies Pont Midi Pyr\u00e9n\u00e9es 83210",
    "addr:housenumber":"a57;n\u00b08",
    "addr:postcode":"83210",
    "addr:street":"Rn 97;Sollies Pont Midi Pyre\u0301Ne\u0301Es",
    "iso:country":"FR",
    "sg:address":"RN 97 - A57 Sortie N\u00b08",
    "sg:city":"Sollies Pont",
    "sg:orig_category":"Unclassifiable Establishments",
    "sg:phone":"+33 4 94 28 92 32",
    "sg:postcode":"83210",
    "sg:province":"Midi Pyr\u00e9n\u00e9es",
    "wof:name":"Mat\u00e9riaux Du Soleil Sa",
    "wof:placetype":"venue"
},
  "geometry": {"coordinates":[6.042811,43.166992],"type":"Point"}
}