{
  "type": "Feature",
  "properties": {
    "addr:full":"B.P. 248, 49002 Angers C\u00e9dex^^7, Av. Jean Jox\u00e9, 49000 Angers Pays de Loire",
    "addr:housenumber":"b.p. 248",
    "addr:postcode":"49002;49000",
    "addr:street":"Av. Jean Joxe\u0301",
    "iso:country":"FR",
    "sg:address":"B.P. 248, 49002 Angers C\u00e9dex^^7, Av. Jean Jox\u00e9, 49000 Angers",
    "sg:orig_category":"Non-Classified Establishments",
    "sg:phone":"+33 2 51 14 28 10",
    "sg:province":"Pays de Loire",
    "wof:name":"Gastronome S.a.",
    "wof:placetype":"venue"
},
  "geometry": {"coordinates":[-0.56339,47.46315],"type":"Point"}
}