{
  "type": "Feature",
  "properties": {
    "iso:country":"FR",
    "sg:address":"82 cours Carnot; Salon de Provence; 13300",
    "sg:classifiers":[
        {
            "category":"Banks & Credit Unions",
            "subcategory":"Bank",
            "type":"Services"
        }
    ],
    "sg:phone":"+33 3390562017",
    "sg:province":"Outre-Mer",
    "wof:name":"Banque Nationale De Paris",
    "wof:placetype":"venue"
},
  "geometry": {"coordinates":[5.095999,43.640968],"type":"Point"}
}