{
  "type": "Feature",
  "properties": {
    "iso:country":"FR",
    "sg:address":"87, Av. des Aygalades, 13015 Marseille",
    "sg:orig_category":"Unclassifiable Establishments",
    "sg:phone":"+33 4 91 61 58 00",
    "sg:province":"Midi Pyr\u00e9n\u00e9es",
    "wof:name":"Snef S.a.",
    "wof:placetype":"venue"
},
  "geometry": {"coordinates":[5.36684,43.337742],"type":"Point"}
}