{
  "type": "Feature",
  "properties": {
    "addr:full":"Rte De Paris Parc D'Activit\u00e9s De La Garenne 76220 Gournay En Bray Haute Normandie 76220",
    "addr:postcode":"76220;76220",
    "addr:street":"Rte De Paris Parc D'Activite \u0301S De La Garenne;Haute Normandie",
    "iso:country":"FR",
    "sg:address":"Rte De Paris Parc D'Activit\u00e9s De La Garenne 76220 Gournay En Bray",
    "sg:classifiers":[
        {
            "category":"Professional",
            "subcategory":"Engineering",
            "type":"Services"
        }
    ],
    "sg:phone":"+33 2 35 90 21 08",
    "sg:postcode":"76220",
    "sg:province":"Haute Normandie",
    "sg:tags":[
        "machine",
        "-",
        "mechanical"
    ],
    "wof:name":"Unifiltr",
    "wof:placetype":"venue"
},
  "geometry": {"coordinates":[1.724604,49.470741],"type":"Point"}
}