{
  "type": "Feature",
  "properties": {
    "addr:full":"7 Rue Du Taillefer 38600 Fontaine Rhone-Alpes 38600",
    "addr:housenumber":"7",
    "addr:postcode":"38600;38600",
    "addr:street":"Rue Du Taillefer",
    "iso:country":"FR",
    "sg:address":"7 Rue Du Taillefer 38600 Fontaine",
    "sg:classifiers":[
        {
            "category":"Professional",
            "subcategory":"Advertising",
            "type":"Services"
        }
    ],
    "sg:phone":"+33 4 76 26 06 08",
    "sg:postcode":"38600",
    "sg:province":"Rhone-Alpes",
    "sg:tags":[
        "information",
        "medium",
        "communication"
    ],
    "wof:name":"Dauphine Color Sa",
    "wof:placetype":"venue"
},
  "geometry": {"coordinates":[5.693119,45.192009],"type":"Point"}
}