{
  "type": "Feature",
  "properties": {
    "addr:full":"6 Rue Etienne Dolet 69170 Tarare Rhone-Alpes 69170",
    "addr:housenumber":"6",
    "addr:postcode":"69170;69170",
    "addr:street":"Rue Etienne Dolet",
    "iso:country":"FR",
    "sg:address":"6 Rue Etienne Dolet 69170 Tarare",
    "sg:classifiers":[
        {
            "category":"Shopping",
            "subcategory":"Stationery & Office Supplies",
            "type":"Retail Goods"
        }
    ],
    "sg:phone":"+33 4 74 05 03 26",
    "sg:postcode":"69170",
    "sg:province":"Rhone-Alpes",
    "sg:tags":[
        "information",
        "technology",
        "telecommunication",
        "equipment"
    ],
    "wof:name":"Burotec Sa",
    "wof:placetype":"venue"
},
  "geometry": {"coordinates":[4.436645,45.895237],"type":"Point"}
}