{
  "type": "Feature",
  "properties": {
    "addr:full":"13 Rue Gabriel Dumoulin 27300 Bernay Haute Normandie 27300",
    "addr:housenumber":"13",
    "addr:postcode":"27300;27300",
    "addr:street":"Rue Gabriel Dumoulin;Haute Normandie",
    "iso:country":"FR",
    "sg:address":"13 Rue Gabriel Dumoulin 27300 Bernay",
    "sg:classifiers":[
        {
            "category":"Utilities",
            "subcategory":"Electric",
            "type":"Services"
        }
    ],
    "sg:phone":"+33 810 02 60 27",
    "sg:postcode":"27300",
    "sg:province":"Haute Normandie",
    "sg:tags":[
        "electricity",
        "raw",
        "energy",
        "material"
    ],
    "wof:name":"Electricite De France (edf)",
    "wof:placetype":"venue"
},
  "geometry": {"coordinates":[0.607821,49.094009],"type":"Point"}
}