{
  "type": "Feature",
  "properties": {
    "addr:full":"2, Rue Julien Neveu, 35530 Noyal sur Vilaine Br\u00e9c\u00e9 Bretagne 35530",
    "addr:housenumber":"2",
    "addr:postcode":"35530;bre\u0301ce\u0301;35530",
    "addr:street":"Rue Julien Neveu",
    "iso:country":"FR",
    "sg:address":"2, Rue Julien Neveu, 35530 Noyal sur Vilaine",
    "sg:city":"Br\u00e9c\u00e9",
    "sg:orig_category":"Non-Classified Establishments",
    "sg:phone":"+33 2 99 04 11 04",
    "sg:postcode":"35530",
    "sg:province":"Bretagne",
    "wof:name":"Sojasun Technologies S.a.",
    "wof:placetype":"venue"
},
  "geometry": {"coordinates":[-1.525555,48.114506],"type":"Point"}
}