{
  "type": "Feature",
  "properties": {
    "addr:full":"B.P. 143, 13675 Aubagne C\u00e9dex^^8, Av. des Templiers - Parc d'Activit\u00e9 Napollon, 13670 Aubagne Languedoc-Roussillon",
    "addr:housenumber":"b.p. 143",
    "addr:postcode":"13675;13670",
    "addr:street":"Av. Des Templiers Parc D'Activite \u0301 Napollon",
    "iso:country":"FR",
    "sg:address":"B.P. 143, 13675 Aubagne C\u00e9dex^^8, Av. des Templiers - Parc d'Activit\u00e9 Napollon, 13670 Aubagne",
    "sg:orig_category":"Non-Classified Establishments",
    "sg:phone":"+33 4 42 18 72 22",
    "sg:province":"Languedoc-Roussillon",
    "wof:name":"C.r.e.a.p. S.a.r.l. - Cr\u00e9ation Etiquette Adh\u00e9sive Prestige",
    "wof:placetype":"venue"
},
  "geometry": {"coordinates":[5.57028,43.293251],"type":"Point"}
}