{
  "type": "Feature",
  "properties": {
    "addr:full":"B.P. 12, 57175 Gandrange^^70, Rue Louis Jost, 57175 Gandrange Lorraine 57175",
    "addr:postcode":"57175;57175;57175",
    "addr:street":"B.P. 12;Rue Louis Jost",
    "iso:country":"FR",
    "sg:address":"B.P. 12, 57175 Gandrange^^70, Rue Louis Jost, 57175 Gandrange",
    "sg:orig_category":"Non-Classified Establishments",
    "sg:phone":"+33 3 87 67 18 03",
    "sg:postcode":"57175",
    "sg:province":"Lorraine",
    "wof:name":"Arthur Kull S.a. - M.co.m\u00e9tal",
    "wof:placetype":"venue"
},
  "geometry": {"coordinates":[6.125325,49.270489],"type":"Point"}
}