{
  "type": "Feature",
  "properties": {
    "addr:full":"10, Rue des Prairies, 75020 Paris Ile de France",
    "addr:housenumber":"10",
    "addr:postcode":"75020",
    "addr:street":"Rue Des Prairies",
    "iso:country":"FR",
    "sg:address":"10, Rue des Prairies, 75020 Paris",
    "sg:orig_category":"Unclassifiable Establishments",
    "sg:phone":"+33 1 40 33 73 37",
    "sg:province":"Ile de France",
    "wof:name":"Quadratin S.a.",
    "wof:placetype":"venue"
},
  "geometry": {"coordinates":[2.404512,48.861656],"type":"Point"}
}