{
  "type": "Feature",
  "properties": {
    "iso:country":"FR",
    "sg:address":"1, Av. Pierre Grenier, 92100 Boulogne Billancourt",
    "sg:orig_category":"Unclassifiable Establishments",
    "sg:phone":"+33 1 46 21 77 44",
    "sg:province":"Ile de France",
    "wof:name":"Sos Emballage S.a.",
    "wof:placetype":"venue"
},
  "geometry": {"coordinates":[2.248391,48.825653],"type":"Point"}
}