{
  "type": "Feature",
  "properties": {
    "addr:full":"ZA Eckenbach Saint Hippolyte Alsace 68590",
    "addr:postcode":"68590",
    "addr:street":"Za Eckenbach Saint Hippolyte Alsace",
    "iso:country":"FR",
    "sg:address":"ZA Eckenbach",
    "sg:city":"Saint Hippolyte",
    "sg:orig_category":"Unclassifiable Establishments",
    "sg:phone":"+33 3 89 73 00 14",
    "sg:postcode":"68590",
    "sg:province":"Alsace",
    "wof:name":"Vins D'alsace Jean Biecher Et Fils S.a.",
    "wof:placetype":"venue"
},
  "geometry": {"coordinates":[7.365417,48.230247],"type":"Point"}
}