{
  "type": "Feature",
  "properties": {
    "addr:full":"10 pl de la Lib\u00e9ration; Nyons; 26110 Rhone-Alpes 26110",
    "addr:housenumber":"10",
    "addr:postcode":"26110;26110",
    "addr:street":"Pl De La Libe\u0301Ration",
    "iso:country":"FR",
    "sg:address":"10 pl de la Lib\u00e9ration; Nyons; 26110",
    "sg:classifiers":[
        {
            "category":"Banks & Credit Unions",
            "subcategory":"Bank",
            "type":"Services"
        }
    ],
    "sg:phone":"+33 3375261300",
    "sg:postcode":"26110",
    "sg:province":"Rhone-Alpes",
    "wof:name":"Soci\u00e9t\u00e9 Marseillaise De Cr\u00e9dit",
    "wof:placetype":"venue"
},
  "geometry": {"coordinates":[5.139003,44.360489],"type":"Point"}
}