{
  "type": "Feature",
  "properties": {
    "addr:full":"B.P. 20, 33530 Bassens C\u00e9dex^^Av. Bellerive des Moines, 33530 Bassens Bassens Aquitaine 33530",
    "addr:postcode":"33530;33530;33530",
    "addr:street":"B.P. 20",
    "iso:country":"FR",
    "sg:address":"B.P. 20, 33530 Bassens C\u00e9dex^^Av. Bellerive des Moines, 33530 Bassens",
    "sg:city":"Bassens",
    "sg:orig_category":"Non-Classified Establishments",
    "sg:phone":"+33 5 57 77 49 50",
    "sg:postcode":"33530",
    "sg:province":"Aquitaine",
    "wof:name":"Sea Invest France S.a.",
    "wof:placetype":"venue"
},
  "geometry": {"coordinates":[-0.516629,44.900097],"type":"Point"}
}