{
  "type": "Feature",
  "properties": {
    "iso:country":"FR",
    "sg:address":"18, Rue Robert Fulton - ZI Z.E, 51100 Reims",
    "sg:orig_category":"Non-Classified Establishments",
    "sg:phone":"+33 3 26 05 00 48",
    "sg:province":"Champagne",
    "wof:name":"Technique Du B\u00e2timent S.a.r.l.",
    "wof:placetype":"venue"
},
  "geometry": {"coordinates":[4.028445,49.26284],"type":"Point"}
}