{
  "type": "Feature",
  "properties": {
    "addr:full":"B.P. 36, 54120 Baccarat^^30, Rue du 20\u00e8me Bataillon, 54120 Baccarat Lorraine",
    "addr:postcode":"54120;54120",
    "addr:street":"B.P. 36;Rue Du 20E\u0300Me Bataillon",
    "iso:country":"FR",
    "sg:address":"B.P. 36, 54120 Baccarat^^30, Rue du 20\u00e8me Bataillon, 54120 Baccarat",
    "sg:orig_category":"Non-Classified Establishments",
    "sg:phone":"+33 3 83 75 18 18",
    "sg:province":"Lorraine",
    "wof:name":"Europ\u00e9enne De Galvanisation S.a.",
    "wof:placetype":"venue"
},
  "geometry": {"coordinates":[6.74019,48.450111],"type":"Point"}
}