{
  "type": "Feature",
  "properties": {
    "iso:country":"FR",
    "sg:address":"75",
    "sg:city":"Georges Cl\u00e9menceau 34500 B\u00e9ziers",
    "sg:classifiers":[
        {
            "category":"Professional",
            "type":"Services"
        }
    ],
    "sg:phone":"+33 4 67 31 28 31",
    "sg:province":"Languedoc-Roussillon",
    "sg:tags":[
        "transport",
        "road"
    ],
    "wof:name":"Roc'eclerc Biterroise Du Funeraire Franchise Independant",
    "wof:placetype":"venue"
},
  "geometry": {"coordinates":[3.21933,43.347961],"type":"Point"}
}