{
  "type": "Feature",
  "properties": {
    "addr:full":"2 Dix Toises 78117 Ch\u00e2teaufort Ile de France 78117",
    "addr:housenumber":"2",
    "addr:postcode":"78117;ile;78117",
    "addr:street":"Dix Toises;France",
    "iso:country":"FR",
    "sg:address":"2",
    "sg:city":"Dix Toises 78117 Ch\u00e2teaufort",
    "sg:classifiers":[
        {
            "category":"Manufacturing",
            "subcategory":"Tools & Machinery",
            "type":"Manufacturing & Wholesale Goods"
        }
    ],
    "sg:phone":"+33 1 39 56 76 40",
    "sg:postcode":"78117",
    "sg:province":"Ile de France",
    "sg:tags":[
        "equipment",
        "measurement",
        "-",
        "precision",
        "instrument"
    ],
    "wof:name":"Asco Instruments",
    "wof:placetype":"venue"
},
  "geometry": {"coordinates":[2.089832,48.740353],"type":"Point"}
}