{
  "type": "Feature",
  "properties": {
    "addr:full":"Usine des Chazelles Saint Eloy les Mines Auvergne 63700",
    "addr:postcode":"63700",
    "addr:street":"Saint Eloy Les Mines",
    "iso:country":"FR",
    "sg:address":"Usine des Chazelles",
    "sg:city":"Saint Eloy les Mines",
    "sg:orig_category":"Non-Classified Establishments",
    "sg:phone":"+33 4 73 85 00 44",
    "sg:postcode":"63700",
    "sg:province":"Auvergne",
    "wof:name":"Sautereau Industrie S.a.r.l.",
    "wof:placetype":"venue"
},
  "geometry": {"coordinates":[2.83358,46.162521],"type":"Point"}
}