{
  "type": "Feature",
  "properties": {
    "iso:country":"FR",
    "sg:address":"11 a rue Kl\u00e9ber; Schiltigheim; 67300",
    "sg:city":"Schiltigheim",
    "sg:classifiers":[
        {
            "category":"Banks & Credit Unions",
            "subcategory":"Bank",
            "type":"Services"
        }
    ],
    "sg:phone":"+33 3388837261",
    "sg:postcode":"67300",
    "sg:province":"Alsace",
    "wof:name":"Banque Populaire De La Region Econo",
    "wof:placetype":"venue"
},
  "geometry": {"coordinates":[7.733909,48.607922],"type":"Point"}
}