{
  "type": "Feature",
  "properties": {
    "addr:full":"ZI Auterive Midi Pyr\u00e9n\u00e9es 31190",
    "addr:postcode":"31190",
    "iso:country":"FR",
    "sg:address":"ZI",
    "sg:city":"Auterive",
    "sg:orig_category":"Unclassifiable Establishments",
    "sg:phone":"+33 5 61 50 62 33",
    "sg:postcode":"31190",
    "sg:province":"Midi Pyr\u00e9n\u00e9es",
    "wof:name":"Simalux S.a.",
    "wof:placetype":"venue"
},
  "geometry": {"coordinates":[1.40004,43.297123],"type":"Point"}
}