{
  "type": "Feature",
  "properties": {
    "iso:country":"FR",
    "sg:address":"13, Cour Blaise Pascal, 91000 Evry",
    "sg:orig_category":"Unclassifiable Establishments",
    "sg:phone":"+33 1 60 77 15 62",
    "sg:province":"Ile de France",
    "wof:name":"Randstad Interim",
    "wof:placetype":"venue"
},
  "geometry": {"coordinates":[2.430595,48.627266],"type":"Point"}
}