{
  "type": "Feature",
  "properties": {
    "iso:country":"FR",
    "sg:address":"6, Av. Tissonvilliers, 95400 Villiers le Bel",
    "sg:orig_category":"Unclassifiable Establishments",
    "sg:phone":"+33 1 39 33 01 01",
    "sg:province":"Ile de France",
    "wof:name":"Imprimerie R. Ras S.a.",
    "wof:placetype":"venue"
},
  "geometry": {"coordinates":[2.389553,49.000652],"type":"Point"}
}