{
  "type": "Feature",
  "properties": {
    "addr:full":"Ch\u00e2teau Villars 33141 Saillans Saillans Aquitaine 33141",
    "addr:postcode":"33141;33141",
    "iso:country":"FR",
    "sg:address":"Ch\u00e2teau Villars 33141 Saillans",
    "sg:city":"Saillans",
    "sg:orig_category":"Non-Classified Establishments",
    "sg:phone":"+33 5 57 84 32 17",
    "sg:postcode":"33141",
    "sg:province":"Aquitaine",
    "wof:name":"Gaudrie Et Fils S.c.e.a.",
    "wof:placetype":"venue"
},
  "geometry": {"coordinates":[-0.267619,44.964275],"type":"Point"}
}