{
  "type": "Feature",
  "properties": {
    "iso:country":"FR",
    "sg:address":"Le Tremblot 08190 VILLERS DEVANT LE THOUR",
    "sg:city":"Aire",
    "sg:classifiers":[
        {
            "category":"Wholesale",
            "subcategory":"Fruits & Vegetables",
            "type":"Manufacturing & Wholesale Goods"
        }
    ],
    "sg:phone":"+33 3 24 72 99 51",
    "sg:postcode":"08190",
    "sg:province":"Champagne",
    "sg:tags":[
        "product",
        "cereal"
    ],
    "wof:name":"France Agricole De Champagne Sarl",
    "wof:placetype":"venue"
},
  "geometry": {"coordinates":[4.05168,49.498909],"type":"Point"}
}