{
  "type": "Feature",
  "properties": {
    "addr:full":"Domaine de Palayson Roquebrune sur Argens Provence-Alpes-C\u00f4te d'Azur 83520",
    "addr:postcode":"83520",
    "addr:street":"Roquebrune;Argens",
    "iso:country":"FR",
    "sg:address":"Domaine de Palayson",
    "sg:city":"Roquebrune sur Argens",
    "sg:orig_category":"Unclassifiable Establishments",
    "sg:phone":"+33 4 94 19 55 55",
    "sg:postcode":"83520",
    "sg:province":"Provence-Alpes-C\u00f4te d'Azur",
    "wof:name":"Scetauroute",
    "wof:placetype":"venue"
},
  "geometry": {"coordinates":[6.61083,43.485798],"type":"Point"}
}