{
  "type": "Feature",
  "properties": {
    "iso:country":"FR",
    "sg:address":"B.P. 422, 59464 Lomme C\u00e9dex^^Rue Lavoisier, 59160 Lomme",
    "sg:orig_category":"Non-Classified Establishments",
    "sg:phone":"+33 3 20 00 18 88",
    "sg:province":"Nord Pas-de-Calais",
    "wof:name":"Richard Et Compagnie S.a.",
    "wof:placetype":"venue"
},
  "geometry": {"coordinates":[2.961047,50.643799],"type":"Point"}
}