{
  "type": "Feature",
  "properties": {
    "addr:full":"Pagezou 81600 T\u00e9cou Midi Pyr\u00e9n\u00e9es 81600",
    "addr:postcode":"81600;81600",
    "addr:street":"Pagezou",
    "iso:country":"FR",
    "sg:address":"Pagezou 81600 T\u00e9cou",
    "sg:classifiers":[
        {
            "category":"Food Court",
            "type":"Food & Drink"
        }
    ],
    "sg:phone":"+33 5 63 33 00 80",
    "sg:postcode":"81600",
    "sg:province":"Midi Pyr\u00e9n\u00e9es",
    "sg:tags":[
        "product",
        "related"
    ],
    "wof:name":"Cave De T\u00c9cou",
    "wof:placetype":"venue"
},
  "geometry": {"coordinates":[1.938874,43.847916],"type":"Point"}
}