{
  "type": "Feature",
  "properties": {
    "iso:country":"FR",
    "sg:address":"60/62, Bd de la Mission Marchand, 92400 Courbevoie",
    "sg:orig_category":"Non-Classified Establishments",
    "sg:phone":"+33 1 46 67 77 00",
    "sg:postcode":"92400",
    "sg:province":"Ile de France",
    "wof:name":"D.t.c. Consultants S.a.",
    "wof:placetype":"venue"
},
  "geometry": {"coordinates":[2.240138,48.899193],"type":"Point"}
}