{
  "type": "Feature",
  "properties": {
    "addr:full":"34 Allee Du Closeau Zi Nord Des Richardets 93160 Noisy Le Grand Ile de France",
    "addr:housenumber":"34",
    "addr:postcode":"93160",
    "addr:street":"Allee Du Closeau Zi Nord Des Richardets",
    "iso:country":"FR",
    "sg:address":"34 Allee Du Closeau Zi Nord Des Richardets 93160 Noisy Le Grand",
    "sg:classifiers":[
        {
            "category":"Wholesale",
            "subcategory":"Machinery & Supplies",
            "type":"Manufacturing & Wholesale Goods"
        }
    ],
    "sg:phone":"+33 1 43 04 58 83",
    "sg:province":"Ile de France",
    "sg:tags":[
        "equipment",
        "precision"
    ],
    "wof:name":"Bt International",
    "wof:placetype":"venue"
},
  "geometry": {"coordinates":[2.553644,48.848892],"type":"Point"}
}