{
  "type": "Feature",
  "properties": {
    "iso:country":"FR",
    "sg:address":"3, Av. Alsace Lorraine, 42600 Montbrison",
    "sg:orig_category":"Unclassifiable Establishments",
    "sg:phone":"+33 4 77 58 85 02",
    "sg:postcode":"42600",
    "sg:province":"Rhone-Alpes",
    "wof:name":"Productions Graphics S.a.r.l.",
    "wof:placetype":"venue"
},
  "geometry": {"coordinates":[4.069351,45.604385],"type":"Point"}
}