{
  "type": "Feature",
  "properties": {
    "addr:full":"14, Rue Jacques Bizeray, 41500 Mer Mer Centre 41500",
    "addr:housenumber":"14",
    "addr:postcode":"41500;41500",
    "addr:street":"Rue Jacques Bizeray",
    "iso:country":"FR",
    "sg:address":"14, Rue Jacques Bizeray, 41500 Mer",
    "sg:city":"Mer",
    "sg:orig_category":"Unclassifiable Establishments",
    "sg:phone":"+33 2 54 81 23 50",
    "sg:postcode":"41500",
    "sg:province":"Centre",
    "wof:name":"Bois Du Val De Loire S.a.r.l.",
    "wof:placetype":"venue"
},
  "geometry": {"coordinates":[1.504673,47.703178],"type":"Point"}
}