{
  "type": "Feature",
  "properties": {
    "addr:full":"105 Rue Olivier De Serres 75015 Paris Ile de France 75015",
    "addr:housenumber":"105",
    "addr:postcode":"75015;75015",
    "addr:street":"Rue Olivier De Serres",
    "iso:country":"FR",
    "sg:address":"105 Rue Olivier De Serres 75015 Paris",
    "sg:classifiers":[
        {
            "category":"Professional",
            "subcategory":"Engineering",
            "type":"Services"
        }
    ],
    "sg:phone":"+33 1 48 28 21 80",
    "sg:postcode":"75015",
    "sg:province":"Ile de France",
    "sg:tags":[
        "machine",
        "-",
        "mechanical"
    ],
    "wof:name":"Etablissements Marchand Pernot",
    "wof:placetype":"venue"
},
  "geometry": {"coordinates":[2.293022,48.831478],"type":"Point"}
}