{
  "type": "Feature",
  "properties": {
    "addr:full":"Rte De Rouelles 76700 Harfleur Haute Normandie 76700",
    "addr:postcode":"76700;76700",
    "addr:street":"Rte De Rouelles;Haute Normandie",
    "iso:country":"FR",
    "sg:address":"Rte De Rouelles 76700 Harfleur",
    "sg:orig_category":"Finished goods - metallic Goods handling - material and equipment Mechanical Engineering - machines ",
    "sg:phone":"+33 2 35 47 39 44",
    "sg:postcode":"76700",
    "sg:province":"Haute Normandie",
    "wof:name":"Ste D'exploitation Demaret Freres-sedf",
    "wof:placetype":"venue"
},
  "geometry": {"coordinates":[0.193405,49.519176],"type":"Point"}
}