{
  "type": "Feature",
  "properties": {
    "addr:full":"Av. Jolliot Curie Bill\u00e8re Aquitaine 64140",
    "addr:postcode":"64140",
    "addr:street":"Av. Jolliot Curie",
    "iso:country":"FR",
    "sg:address":"Av. Jolliot Curie",
    "sg:city":"Bill\u00e8re",
    "sg:orig_category":"Non-Classified Establishments",
    "sg:phone":"+33 5 59 92 35 51",
    "sg:postcode":"64140",
    "sg:province":"Aquitaine",
    "wof:name":"M.i. Drilling Fluids International Bv",
    "wof:placetype":"venue"
},
  "geometry": {"coordinates":[-0.413078,43.317261],"type":"Point"}
}