{
  "type": "Feature",
  "properties": {
    "iso:country":"FR",
    "sg:address":"All\u00e9e Ecusson",
    "sg:city":"Saint Pierre Montlimart",
    "sg:orig_category":"Unclassifiable Establishments",
    "sg:phone":"+33 2 41 30 00 55",
    "sg:postcode":"49110",
    "sg:province":"Pays de Loire",
    "wof:name":"Etablissements Peign\u00e9 S.a.r.l.",
    "wof:placetype":"venue"
},
  "geometry": {"coordinates":[-1.042257,47.264469],"type":"Point"}
}