{
  "type": "Feature",
  "properties": {
    "addr:full":"9 Chem De La Justice 44300 Nantes Pays de Loire 44300",
    "addr:housenumber":"9",
    "addr:postcode":"44300;44300",
    "addr:street":"Chem De La Justice",
    "iso:country":"FR",
    "sg:address":"9 Chem De La Justice 44300 Nantes",
    "sg:classifiers":[
        {
            "category":"Manufacturing",
            "subcategory":"Tools & Machinery",
            "type":"Manufacturing & Wholesale Goods"
        }
    ],
    "sg:phone":"+33 2 40 16 01 90",
    "sg:postcode":"44300",
    "sg:province":"Pays de Loire",
    "sg:tags":[
        "environment",
        "equipment",
        "-"
    ],
    "wof:name":"Sa Briand",
    "wof:placetype":"venue"
},
  "geometry": {"coordinates":[-1.588604,47.268227],"type":"Point"}
}