{
  "type": "Feature",
  "properties": {
    "addr:full":"Zi De Noisel BP 24 77423 Marne La Vall\u00e9e Cedex 2 Midi Pyr\u00e9n\u00e9es",
    "addr:housenumber":"24;2",
    "addr:postcode":"77423",
    "addr:street":"Zi De Noisel Bp;Cedex",
    "iso:country":"FR",
    "sg:address":"Zi De Noisel BP 24 77423 Marne La Vall\u00e9e Cedex 2",
    "sg:classifiers":[
        {
            "category":"Wholesale",
            "subcategory":"Drugs",
            "type":"Manufacturing & Wholesale Goods"
        }
    ],
    "sg:phone":"+33 1 60 37 50 00",
    "sg:province":"Midi Pyr\u00e9n\u00e9es",
    "sg:tags":[
        "chemical",
        "pharmaceutical"
    ],
    "wof:name":"Aps Cothal Sa",
    "wof:placetype":"venue"
},
  "geometry": {"coordinates":[2.306422,48.822132],"type":"Point"}
}