{
  "type": "Feature",
  "properties": {
    "iso:country":"FR",
    "sg:address":"3, Rue Jean Mermoz, 93297 Tremblay en France C\u00e9dex",
    "sg:orig_category":"Non-Classified Establishments",
    "sg:phone":"+33 1 49 96 33 31",
    "sg:province":"Aquitaine",
    "wof:name":"S.i.m.o.p. S.a.r.l. - Soci\u00e9t\u00e9 Industrielle D' Optique Et De Pr\u00e9cision",
    "wof:placetype":"venue"
},
  "geometry": {"coordinates":[2.567334,48.966873],"type":"Point"}
}