{
  "type": "Feature",
  "properties": {
    "addr:full":"58, Place Henri Loritz, 54000 Nancy Lorraine",
    "addr:housenumber":"58",
    "addr:postcode":"54000",
    "addr:street":"Place Henri Loritz",
    "iso:country":"FR",
    "sg:address":"58, Place Henri Loritz, 54000 Nancy",
    "sg:orig_category":"Non-Classified Establishments",
    "sg:phone":"+33 3 83 32 04 20",
    "sg:province":"Lorraine",
    "wof:name":"Lbi Systems S.a.r.l.",
    "wof:placetype":"venue"
},
  "geometry": {"coordinates":[6.19507,48.685635],"type":"Point"}
}