{
  "type": "Feature",
  "properties": {
    "addr:full":"B.P. 1033, 84097 Avignon C\u00e9dex 9^^610, Rue du Grand Gigognan - ZI de Courtine, 84000 Avignon Lorraine",
    "addr:housenumber":"1033;9 ^ ^ 610",
    "addr:postcode":"84097;84000",
    "addr:street":"B.P.;Ce\u0301Dex;Rue Du Grand Gigognan Zi De Courtine",
    "iso:country":"FR",
    "sg:address":"B.P. 1033, 84097 Avignon C\u00e9dex 9^^610, Rue du Grand Gigognan - ZI de Courtine, 84000 Avignon",
    "sg:orig_category":"Non-Classified Establishments",
    "sg:phone":"+33 4 90 16 54 54",
    "sg:province":"Lorraine",
    "wof:name":"C.o.g.i.x. S.a.",
    "wof:placetype":"venue"
},
  "geometry": {"coordinates":[4.806015,43.948753],"type":"Point"}
}