{
  "type": "Feature",
  "properties": {
    "addr:full":"3, All\u00e9e de Rigny Uss\u00e9, 37170 Chambray l\u00e8s Tours Chambray-l\u00e8s-Tours Centre 37170",
    "addr:housenumber":"3",
    "addr:postcode":"37170;37170",
    "addr:street":"Alle\u0301E De Rigny Usse\u0301",
    "iso:country":"FR",
    "sg:address":"3, All\u00e9e de Rigny Uss\u00e9, 37170 Chambray l\u00e8s Tours",
    "sg:city":"Chambray-l\u00e8s-Tours",
    "sg:orig_category":"Unclassifiable Establishments",
    "sg:phone":"+33 2 47 27 85 55",
    "sg:postcode":"37170",
    "sg:province":"Centre",
    "wof:name":"Solog S.a.r.l.",
    "wof:placetype":"venue"
},
  "geometry": {"coordinates":[0.737128,47.337276],"type":"Point"}
}