{
  "type": "Feature",
  "properties": {
    "addr:full":"Za De Camparian 33870 Vayres Vayres Aquitaine 33870",
    "addr:postcode":"33870;33870",
    "addr:street":"Za De Camparian",
    "iso:country":"FR",
    "sg:address":"Za De Camparian 33870 Vayres",
    "sg:city":"Vayres",
    "sg:classifiers":[
        {
            "category":"Professional",
            "subcategory":"Engineering",
            "type":"Services"
        }
    ],
    "sg:phone":"+33 5 57 74 73 37",
    "sg:postcode":"33870",
    "sg:province":"Aquitaine",
    "sg:tags":[
        "machine",
        "-",
        "mechanical"
    ],
    "wof:name":"Aquitaine Technique Vinicole Industriel Sa",
    "wof:placetype":"venue"
},
  "geometry": {"coordinates":[-0.316485,44.897472],"type":"Point"}
}