{
  "type": "Feature",
  "properties": {
    "iso:country":"FR",
    "sg:address":"Les Turins 26300 Besayes",
    "sg:classifiers":[
        {
            "category":"Utilities",
            "subcategory":"Electric",
            "type":"Services"
        }
    ],
    "sg:phone":"+33 4 75 47 47 65",
    "sg:postcode":"26300",
    "sg:province":"Rhone-Alpes",
    "sg:tags":[
        "electricity",
        "electronic",
        "electrical",
        "equipment"
    ],
    "wof:name":"Societe Dromoise De Travaux",
    "wof:placetype":"venue"
},
  "geometry": {"coordinates":[5.062446,44.962818],"type":"Point"}
}