{
  "type": "Feature",
  "properties": {
    "addr:full":"Rue de l'Orme G\u00e2teau - ZA les Champs Sablons Semoy Centre 45400",
    "addr:postcode":"45400",
    "addr:street":"Rue De L'Orme;Za Les Champs Sablons Semoy",
    "iso:country":"FR",
    "sg:address":"Rue de l'Orme G\u00e2teau - ZA les Champs Sablons",
    "sg:city":"Semoy",
    "sg:orig_category":"Unclassifiable Establishments",
    "sg:phone":"+33 2 38 84 41 42",
    "sg:postcode":"45400",
    "sg:province":"Centre",
    "wof:name":"Publigraphie S.a.r.l.",
    "wof:placetype":"venue"
},
  "geometry": {"coordinates":[1.893539,47.929756],"type":"Point"}
}