{
  "type": "Feature",
  "properties": {
    "addr:full":"3 La Cour Charette 45650 St Jean Le Blanc Saint-Jean-le-Blanc Centre 45650",
    "addr:housenumber":"3",
    "addr:postcode":"45650;45650",
    "addr:street":"La Cour Charette;Jean Le;Saint-Jean-Le-Blanc",
    "iso:country":"FR",
    "sg:address":"3 La Cour Charette 45650 St Jean Le Blanc",
    "sg:city":"Saint-Jean-le-Blanc",
    "sg:classifiers":[
        {
            "category":"Farming",
            "subcategory":"Farm",
            "type":"Manufacturing & Wholesale Goods"
        }
    ],
    "sg:phone":"+33 2 38 66 37 93",
    "sg:postcode":"45650",
    "sg:province":"Centre",
    "sg:tags":[
        "horticulture",
        "agriculture",
        "livestock"
    ],
    "wof:name":"Pepinieres Travers",
    "wof:placetype":"venue"
},
  "geometry": {"coordinates":[1.920372,47.880882],"type":"Point"}
}