{
  "type": "Feature",
  "properties": {
    "addr:full":"2 Rue De Pr\u00e9 Tillon Champfleuri 38300 Bourgoin Jallieu Rhone-Alpes",
    "addr:housenumber":"2",
    "addr:postcode":"38300",
    "addr:street":"Rue De Pre\u0301 Tillon Champfleuri",
    "iso:country":"FR",
    "sg:address":"2 Rue De Pr\u00e9 Tillon Champfleuri 38300 Bourgoin Jallieu",
    "sg:classifiers":[
        {
            "category":"Manufacturing",
            "subcategory":"Printing",
            "type":"Manufacturing & Wholesale Goods"
        }
    ],
    "sg:phone":"+33 4 74 43 68 70",
    "sg:province":"Rhone-Alpes",
    "sg:tags":[
        "publishing"
    ],
    "wof:name":"Lembourg Sa",
    "wof:placetype":"venue"
},
  "geometry": {"coordinates":[5.30075,45.4981],"type":"Point"}
}