{
  "type": "Feature",
  "properties": {
    "addr:full":"1 Place des Mineurs; Giromagny; 90200 Franche Comt\u00e9 90200",
    "addr:housenumber":"1",
    "addr:postcode":"90200;90200",
    "addr:street":"Place Des Mineurs;Comte\u0301",
    "iso:country":"FR",
    "sg:address":"1 Place des Mineurs; Giromagny; 90200",
    "sg:classifiers":[
        {
            "category":"Banks & Credit Unions",
            "subcategory":"Bank",
            "type":"Services"
        }
    ],
    "sg:phone":"+33 3 84 27 13 10",
    "sg:postcode":"90200",
    "sg:province":"Franche Comt\u00e9",
    "wof:name":"Cr\u00e9dit Industriel D'alsace, Et De Lorraine Sa",
    "wof:placetype":"venue"
},
  "geometry": {"coordinates":[6.82686,47.74131],"type":"Point"}
}