{
  "type": "Feature",
  "properties": {
    "addr:full":"B.P. 05, 49071 Beaucouz\u00e9^^Rue de la Claie, 49070 Beaucouz\u00e9 Pays de Loire",
    "addr:postcode":"49071;49070",
    "addr:street":"B.P. 05;Claie",
    "iso:country":"FR",
    "sg:address":"B.P. 05, 49071 Beaucouz\u00e9^^Rue de la Claie, 49070 Beaucouz\u00e9",
    "sg:orig_category":"Non-Classified Establishments",
    "sg:phone":"+33 2 41 72 10 40",
    "sg:province":"Pays de Loire",
    "wof:name":"Sipect S.a.",
    "wof:placetype":"venue"
},
  "geometry": {"coordinates":[-0.658364,47.45779],"type":"Point"}
}