{
  "type": "Feature",
  "properties": {
    "addr:full":"B.P. 144, 74303 Cluses C\u00e9dex^^4, Rue de Lyc\u00e9e, 74300 Cluses Rhone-Alpes 74300",
    "addr:housenumber":"b.p. 144",
    "addr:postcode":"74303;74300;74300",
    "addr:street":"Rue De Lyce\u0301E",
    "iso:country":"FR",
    "sg:address":"B.P. 144, 74303 Cluses C\u00e9dex^^4, Rue de Lyc\u00e9e, 74300 Cluses",
    "sg:orig_category":"Non-Classified Establishments",
    "sg:phone":"+33 4 50 98 01 52",
    "sg:postcode":"74300",
    "sg:province":"Rhone-Alpes",
    "wof:name":"Donche Gay S.a.",
    "wof:placetype":"venue"
},
  "geometry": {"coordinates":[6.633185,45.987919],"type":"Point"}
}