{
  "type": "Feature",
  "properties": {
    "iso:country":"FR",
    "sg:address":"B.P. 29, 77251 Brie Comte Robert C\u00e9dex^^51, Rte de Chevry, 77250 Brie Comte Robert",
    "sg:orig_category":"Non-Classified Establishments",
    "sg:phone":"+33 1 64 05 40 22",
    "sg:postcode":"77250",
    "sg:province":"Ile de France",
    "wof:name":"Dumo S.a.",
    "wof:placetype":"venue"
},
  "geometry": {"coordinates":[2.814518,48.372993],"type":"Point"}
}