{
  "type": "Feature",
  "properties": {
    "addr:full":"40, Rue de la Libert\u00e9, 41110 Pouill\u00e9 Pouill\u00e9 Centre 41110",
    "addr:housenumber":"40;pouille\u0301",
    "addr:postcode":"41110;41110",
    "addr:street":"Rue De La Liberte\u0301",
    "iso:country":"FR",
    "sg:address":"40, Rue de la Libert\u00e9, 41110 Pouill\u00e9",
    "sg:city":"Pouill\u00e9",
    "sg:orig_category":"Non-Classified Establishments",
    "sg:phone":"+33 2 54 71 44 25",
    "sg:postcode":"41110",
    "sg:province":"Centre",
    "wof:name":"Delaunay Jacques",
    "wof:placetype":"venue"
},
  "geometry": {"coordinates":[1.288745,47.317955],"type":"Point"}
}