{
  "type": "Feature",
  "properties": {
    "iso:country":"FR",
    "sg:address":"Rue Brancion",
    "sg:city":"Tournus",
    "sg:classifiers":[
        {
            "category":"Banks & Credit Unions",
            "subcategory":"Financial Services",
            "type":"Services"
        }
    ],
    "sg:phone":"+33 3 85 51 74 57",
    "sg:postcode":"71700",
    "sg:province":"Bourgogne",
    "sg:tags":[
        "banking",
        "finance",
        "insurance"
    ],
    "wof:name":"Societe D'expertise Comptable M Michaud Sarl Secmi Sarl (secmi)",
    "wof:placetype":"venue"
},
  "geometry": {"coordinates":[4.90919,46.563576],"type":"Point"}
}