{
  "type": "Feature",
  "properties": {
    "addr:full":"3 Avenue Jules Janin 75016 Paris Ile de France 75016",
    "addr:housenumber":"3",
    "addr:postcode":"75016;75016",
    "addr:street":"Avenue Jules Janin",
    "iso:country":"FR",
    "sg:address":"3 Avenue Jules Janin 75016 Paris",
    "sg:classifiers":[
        {
            "category":"Professional",
            "subcategory":"Advertising",
            "type":"Services"
        }
    ],
    "sg:phone":"+33 1 45 03 10 50",
    "sg:postcode":"75016",
    "sg:province":"Ile de France",
    "sg:tags":[
        "information",
        "medium",
        "communication"
    ],
    "wof:name":"Audioprod Sas",
    "wof:placetype":"venue"
},
  "geometry": {"coordinates":[2.275218,48.859871],"type":"Point"}
}