{
  "type": "Feature",
  "properties": {
    "addr:full":"25, Chemin des Fr\u00e8res Lumi\u00e8re, 69800 Saint Priest Rhone-Alpes 69800",
    "addr:housenumber":"25",
    "addr:postcode":"69800;69800",
    "addr:street":"Chemin Des Fre\u0300Res Lumie\u0300Re;Priest Rhone-Alpes",
    "iso:country":"FR",
    "sg:address":"25, Chemin des Fr\u00e8res Lumi\u00e8re, 69800 Saint Priest",
    "sg:orig_category":"Unclassifiable Establishments",
    "sg:phone":"+33 4 72 23 11 83",
    "sg:postcode":"69800",
    "sg:province":"Rhone-Alpes",
    "wof:name":"Ipel S.a.",
    "wof:placetype":"venue"
},
  "geometry": {"coordinates":[4.949169,45.69054],"type":"Point"}
}