{
  "type": "Feature",
  "properties": {
    "addr:full":"13 Rue Emile Decorps 69100 Villeurbanne Rhone-Alpes 69100",
    "addr:housenumber":"13",
    "addr:postcode":"69100;69100",
    "addr:street":"Rue Emile Decorps",
    "iso:country":"FR",
    "sg:address":"13 Rue Emile Decorps 69100 Villeurbanne",
    "sg:classifiers":[
        {
            "category":"Professional",
            "subcategory":"Computer Services",
            "type":"Services"
        }
    ],
    "sg:phone":"+33 4 72 01 82 60",
    "sg:postcode":"69100",
    "sg:province":"Rhone-Alpes",
    "sg:tags":[
        "information",
        "technology",
        "software"
    ],
    "wof:name":"L E E Lyon Equipement Electronique Sarl",
    "wof:placetype":"venue"
},
  "geometry": {"coordinates":[4.900031,45.758495],"type":"Point"}
}