{
  "type": "Feature",
  "properties": {
    "addr:full":"Rue Chataigniers 45140 Ormes Ormes Centre 45140",
    "addr:postcode":"45140;45140",
    "addr:street":"Rue Chataigniers",
    "iso:country":"FR",
    "sg:address":"Rue Chataigniers 45140 Ormes",
    "sg:city":"Ormes",
    "sg:classifiers":[
        {
            "category":"Wholesale",
            "subcategory":"Farm Supplies",
            "type":"Manufacturing & Wholesale Goods"
        }
    ],
    "sg:phone":"+33 2 38 65 06 00",
    "sg:postcode":"45140",
    "sg:province":"Centre",
    "sg:tags":[
        "-",
        "machine",
        "equipment",
        "engineering",
        "machinery",
        "mechanical",
        "agriculture"
    ],
    "wof:name":"Honda Europe Power Equipement Sarl",
    "wof:placetype":"venue"
},
  "geometry": {"coordinates":[1.842963,47.951694],"type":"Point"}
}