{
  "type": "Feature",
  "properties": {
    "addr:full":"Rue Marcel Le Mignot 76700 Gonfreville L'Orcher Haute Normandie 76700",
    "addr:postcode":"76700;l'orcher;76700",
    "addr:street":"Rue Marcel Le Mignot;Haute Normandie",
    "iso:country":"FR",
    "sg:address":"Rue Marcel Le Mignot 76700 Gonfreville L'Orcher",
    "sg:classifiers":[
        {
            "category":"Manufacturing",
            "subcategory":"Tools & Machinery",
            "type":"Manufacturing & Wholesale Goods"
        }
    ],
    "sg:phone":"+33 2 35 24 04 01",
    "sg:postcode":"76700",
    "sg:province":"Haute Normandie",
    "sg:tags":[
        "metallurgy",
        "metalworking"
    ],
    "wof:name":"Regis Location",
    "wof:placetype":"venue"
},
  "geometry": {"coordinates":[0.23025,49.498188],"type":"Point"}
}