{
  "type": "Feature",
  "properties": {
    "addr:full":"4 Camiran Aquitaine 33190",
    "addr:housenumber":"4",
    "addr:postcode":"33190",
    "addr:street":"Camiran Aquitaine",
    "iso:country":"FR",
    "sg:address":"4",
    "sg:city":"Camiran",
    "sg:classifiers":[
        {
            "category":"Farming",
            "subcategory":"Farm",
            "type":"Manufacturing & Wholesale Goods"
        }
    ],
    "sg:phone":"+33 5 56 61 58 20",
    "sg:postcode":"33190",
    "sg:province":"Aquitaine",
    "sg:tags":[
        "horticulture",
        "agriculture",
        "livestock"
    ],
    "wof:name":"Bouges (sarl)",
    "wof:placetype":"venue"
},
  "geometry": {"coordinates":[-0.012771,44.516201],"type":"Point"}
}