{
  "type": "Feature",
  "properties": {
    "addr:full":"Village 21520 Beuxhaulles Sur Aube Bissey-la-C\u00f4te Bourgogne 21520",
    "addr:housenumber":"21520",
    "addr:postcode":"21520",
    "addr:street":"Beuxhaulles;Bourgogne",
    "iso:country":"FR",
    "sg:address":"Village 21520 Beuxhaulles Sur Aube",
    "sg:city":"Bissey-la-C\u00f4te",
    "sg:classifiers":[
        {
            "category":"Home & Garden",
            "subcategory":"Furniture",
            "type":"Retail Goods"
        }
    ],
    "sg:phone":"+33 3 80 93 50 84",
    "sg:postcode":"21520",
    "sg:province":"Bourgogne",
    "sg:tags":[
        "wood"
    ],
    "wof:name":"Ets Pianetti Sarl",
    "wof:placetype":"venue"
},
  "geometry": {"coordinates":[4.733185,47.914364],"type":"Point"}
}