{
  "type": "Feature",
  "properties": {
    "iso:country":"FR",
    "sg:address":"B.P. 129, 60761 Montataire C\u00e9dex^^5, Av de la Lib\u00e9ration, 60761 Montataire",
    "sg:orig_category":"Non-Classified Establishments",
    "sg:phone":"+33 3 44 61 57 00",
    "sg:province":"Champagne",
    "wof:name":"Still & Saxby S.a.r.l.",
    "wof:placetype":"venue"
},
  "geometry": {"coordinates":[2.41041,49.258701],"type":"Point"}
}