{
  "type": "Feature",
  "properties": {
    "addr:full":"Chemin de Memorin Gastins Ile de France 77370",
    "addr:postcode":"77370",
    "addr:street":"Chemin De Memorin",
    "iso:country":"FR",
    "sg:address":"Chemin de Memorin",
    "sg:city":"Gastins",
    "sg:orig_category":"Unclassifiable Establishments",
    "sg:phone":"+33 1 64 60 90 34",
    "sg:postcode":"77370",
    "sg:province":"Ile de France",
    "wof:name":"Le Cartonnage Industriel S.a.",
    "wof:placetype":"venue"
},
  "geometry": {"coordinates":[3.02755,48.629475],"type":"Point"}
}