{
  "type": "Feature",
  "properties": {
    "addr:full":"B.P. 519, 42007 Saint Etienne C\u00e9dex 1^^10, Rue Scheurer Kestner, 42000 Saint Etienne Rhone-Alpes",
    "addr:housenumber":"b.p. 519;1 ^ ^ 10",
    "addr:postcode":"42007;42000",
    "addr:street":"Ce\u0301Dex;Rue Scheurer Kestner",
    "iso:country":"FR",
    "sg:address":"B.P. 519, 42007 Saint Etienne C\u00e9dex 1^^10, Rue Scheurer Kestner, 42000 Saint Etienne",
    "sg:orig_category":"Non-Classified Establishments",
    "sg:phone":"+33 4 77 92 82 42",
    "sg:province":"Rhone-Alpes",
    "wof:name":"S.c.m. S.a. - St\u00e9phanoise De Construction M\u00e9canique",
    "wof:placetype":"venue"
},
  "geometry": {"coordinates":[4.391551,45.453495],"type":"Point"}
}