{
  "type": "Feature",
  "properties": {
    "iso:country":"FR",
    "sg:address":"31 Av Dr\u00e9o 83170 Brignoles",
    "sg:classifiers":[
        {
            "category":"Bakery",
            "type":"Food & Drink"
        }
    ],
    "sg:phone":"+33 4 94 69 22 83",
    "sg:province":"Centre",
    "sg:tags":[
        "cake",
        "product",
        "related",
        "bread"
    ],
    "wof:name":"Lafitau Freres Sarl",
    "wof:placetype":"venue"
},
  "geometry": {"coordinates":[6.068429,43.405876],"type":"Point"}
}