{
  "type": "Feature",
  "properties": {
    "iso:country":"FR",
    "sg:address":"Av. Joseph Cu\u00e8gnot - ZI Saint Joseph",
    "sg:city":"Manosque",
    "sg:orig_category":"Unclassifiable Establishments",
    "sg:phone":"+33 4 92 87 36 03",
    "sg:postcode":"04100",
    "sg:province":"Provence-Alpes-C\u00f4te d'Azur",
    "wof:name":"A.g.e.i. S.a. - Approvisionnement G\u00e9n\u00e9ral En Electricit\u00e9 Industri",
    "wof:placetype":"venue"
},
  "geometry": {"coordinates":[5.785752,43.832085],"type":"Point"}
}