{
  "type": "Feature",
  "properties": {
    "addr:full":"3 Rue Joubert 49100 Angers Pays de Loire 49100",
    "addr:housenumber":"3",
    "addr:postcode":"49100;49100",
    "addr:street":"Rue Joubert",
    "iso:country":"FR",
    "sg:address":"3 Rue Joubert 49100 Angers",
    "sg:classifiers":[
        {
            "category":"Professional",
            "subcategory":"Business Services",
            "type":"Services"
        }
    ],
    "sg:phone":"+33 2 41 24 17 70",
    "sg:postcode":"49100",
    "sg:province":"Pays de Loire",
    "sg:tags":[
        "training",
        "advice"
    ],
    "wof:name":"Institution Jeanne D'arc Ecoles Maternelle Et Primaire, Colleges Et Lycees",
    "wof:placetype":"venue"
},
  "geometry": {"coordinates":[-0.544816,47.472549],"type":"Point"}
}