{
  "type": "Feature",
  "properties": {
    "addr:full":"65 avenue Villars 59300 Valenciennes Nord Pas-de-Calais",
    "addr:housenumber":"65",
    "addr:postcode":"59300",
    "addr:street":"Avenue Villars",
    "iso:country":"FR",
    "sg:address":"65 avenue Villars 59300 Valenciennes",
    "sg:classifiers":[
        {
            "category":"Communications",
            "subcategory":"Film & Video Production",
            "type":"Services"
        }
    ],
    "sg:phone":"+33 3 27 21 59 00",
    "sg:province":"Nord Pas-de-Calais",
    "sg:tags":[
        "medical",
        "use",
        "scanner",
        "equipment"
    ],
    "wof:name":"Select Europ Produit Sante Appareil Medical S.a.r.l.",
    "wof:placetype":"venue"
},
  "geometry": {"coordinates":[3.505972,50.357101],"type":"Point"}
}