{
  "type": "Feature",
  "properties": {
    "addr:full":"47 Avenue Camille Prost 39000 Lons Le Saunier Franche Comt\u00e9 39000",
    "addr:housenumber":"47",
    "addr:postcode":"39000;franche comte\u0301 39000",
    "addr:street":"Avenue Camille Prost",
    "iso:country":"FR",
    "sg:address":"47 Avenue Camille Prost 39000 Lons Le Saunier",
    "sg:classifiers":[
        {
            "category":"Autos & Motor Vehicles",
            "subcategory":"Automobile Sales",
            "type":"Retail Goods"
        }
    ],
    "sg:phone":"+33 3 84 35 66 66",
    "sg:postcode":"39000",
    "sg:province":"Franche Comt\u00e9",
    "sg:tags":[
        "equipment",
        "motor-cars",
        "transport"
    ],
    "wof:name":"Soreca Tourisme Sa",
    "wof:placetype":"venue"
},
  "geometry": {"coordinates":[5.568649,46.671467],"type":"Point"}
}