{
  "type": "Feature",
  "properties": {
    "addr:full":"36 Boulevard Lazare Carnot Toulouse Midi Pyr\u00e9n\u00e9es 31000",
    "addr:housenumber":"36",
    "addr:postcode":"31000",
    "addr:street":"Boulevard Lazare Carnot",
    "iso:country":"FR",
    "sg:address":"36 Boulevard Lazare Carnot",
    "sg:city":"Toulouse",
    "sg:classifiers":[
        {
            "category":"Banks & Credit Unions",
            "subcategory":"Financial Services",
            "type":"Services"
        }
    ],
    "sg:phone":"+33 5 62 73 53 03",
    "sg:postcode":"31000",
    "sg:province":"Midi Pyr\u00e9n\u00e9es",
    "sg:tags":[
        "banking",
        "finance",
        "insurance"
    ],
    "wof:name":"Cetelem",
    "wof:placetype":"venue"
},
  "geometry": {"coordinates":[1.450855,43.604004],"type":"Point"}
}