{
  "type": "Feature",
  "properties": {
    "iso:country":"FR",
    "sg:address":"148-150 Av Ren\u00e9 Morin 91420 Morangis",
    "sg:classifiers":[
        {
            "category":"Wholesale",
            "subcategory":"Meat",
            "type":"Manufacturing & Wholesale Goods"
        }
    ],
    "sg:phone":"+33 1 69 79 15 20",
    "sg:postcode":"91420",
    "sg:province":"Ile de France",
    "sg:tags":[
        "food",
        "cooked",
        "product",
        "related"
    ],
    "wof:name":"Chedeville Charcuterie De Paris",
    "wof:placetype":"venue"
},
  "geometry": {"coordinates":[2.32146,48.693501],"type":"Point"}
}