{
  "type": "Feature",
  "properties": {
    "iso:country":"FR",
    "sg:address":"Lacapelette 46100 Figeac",
    "sg:orig_category":"Non-Classified Establishments",
    "sg:phone":"+33 5 65 50 05 99",
    "sg:province":"Midi Pyr\u00e9n\u00e9es",
    "wof:name":"Transports Roux Et Fils S.a.r.l.",
    "wof:placetype":"venue"
},
  "geometry": {"coordinates":[2.024565,44.560276],"type":"Point"}
}