{
  "type": "Feature",
  "properties": {
    "addr:full":"B.P. 71, 38110 La Tour du Pin^^31, Rue Pierre Vincendon, 38110 La Tour du Pin Rhone-Alpes",
    "addr:postcode":"38110;38110",
    "addr:street":"B.P. 71;Rue Pierre Vincendon",
    "iso:country":"FR",
    "sg:address":"B.P. 71, 38110 La Tour du Pin^^31, Rue Pierre Vincendon, 38110 La Tour du Pin",
    "sg:orig_category":"Non-Classified Establishments",
    "sg:phone":"+33 4 74 97 13 11",
    "sg:province":"Rhone-Alpes",
    "wof:name":"Muller Tube Pneumatique S.a.r.l.",
    "wof:placetype":"venue"
},
  "geometry": {"coordinates":[5.454585,45.52478],"type":"Point"}
}