{
  "type": "Feature",
  "properties": {
    "addr:full":"24 All Des Peupliers 54180 Hellicourt Lorraine 54180",
    "addr:housenumber":"24",
    "addr:postcode":"54180;54180",
    "addr:street":"All Des Peupliers",
    "iso:country":"FR",
    "sg:address":"24 All Des Peupliers 54180 Hellicourt",
    "sg:classifiers":[
        {
            "category":"Wholesale",
            "subcategory":"Chemicals & Plastics",
            "type":"Manufacturing & Wholesale Goods"
        }
    ],
    "sg:phone":"+33 3 83 51 17 50",
    "sg:postcode":"54180",
    "sg:province":"Lorraine",
    "sg:tags":[
        "pharmaceutical",
        "cardboard",
        "-",
        "fini",
        "paper",
        "chemistry",
        "by-product"
    ],
    "wof:name":"Comptoir Lorraine Alsace De Peinture Et De Papiers Peints Sa",
    "wof:placetype":"venue"
},
  "geometry": {"coordinates":[6.176609,48.647343],"type":"Point"}
}