{
  "type": "Feature",
  "properties": {
    "iso:country":"FR",
    "sg:address":"B.P. 262, 95615 Cergy Pontoise C\u00e9dex^^35/37, Av. du Gros Ch\u00eane - Parc d'Activit\u00e9 des Bellevues, 9517",
    "sg:orig_category":"Non-Classified Establishments",
    "sg:phone":"+33 1 34 40 15 80",
    "sg:province":"Diekirch",
    "wof:name":"Imi Corn\u00e9lius France S.a.",
    "wof:placetype":"venue"
},
  "geometry": {"coordinates":[5.927232,49.971825],"type":"Point"}
}