{
  "type": "Feature",
  "properties": {
    "addr:full":"6, Rue de Bretagne, 38070 Saint Quentin Fallavier Rhone-Alpes 38070",
    "addr:housenumber":"6",
    "addr:postcode":"38070;38070",
    "addr:street":"Rue De Bretagne",
    "iso:country":"FR",
    "sg:address":"6, Rue de Bretagne, 38070 Saint Quentin Fallavier",
    "sg:orig_category":"Unclassifiable Establishments",
    "sg:phone":"+33 4 74 94 45 77",
    "sg:postcode":"38070",
    "sg:province":"Rhone-Alpes",
    "wof:name":"Adecco Travail Temporaire",
    "wof:placetype":"venue"
},
  "geometry": {"coordinates":[5.114107,45.642502],"type":"Point"}
}