{
  "type": "Feature",
  "properties": {
    "addr:full":"100 R Des Foug\u00e8res 69009 Lyon Rhone-Alpes 69009",
    "addr:housenumber":"100",
    "addr:postcode":"69009;69009",
    "addr:street":"R Des Fouge\u0300Res",
    "iso:country":"FR",
    "sg:address":"100 R Des Foug\u00e8res 69009 Lyon",
    "sg:classifiers":[
        {
            "category":"Professional",
            "subcategory":"Computer Services",
            "type":"Services"
        }
    ],
    "sg:phone":"+33 4 78 47 50 85",
    "sg:postcode":"69009",
    "sg:province":"Rhone-Alpes",
    "sg:tags":[
        "information",
        "technology",
        "software"
    ],
    "wof:name":"Sofft Industries Sa",
    "wof:placetype":"venue"
},
  "geometry": {"coordinates":[4.794985,45.779652],"type":"Point"}
}