{
  "type": "Feature",
  "properties": {
    "iso:country":"FR",
    "sg:address":"B.P. 16, 76520 Boos^^Rte de Paris, 76520 Franqueville Saint Pierre",
    "sg:orig_category":"Non-Classified Establishments",
    "sg:phone":"+33 2 35 79 46 46",
    "sg:postcode":"76520",
    "sg:province":"Haute Normandie",
    "wof:name":"Carrier Transicold Europe S.a.",
    "wof:placetype":"venue"
},
  "geometry": {"coordinates":[1.172807,49.399475],"type":"Point"}
}