{
  "type": "Feature",
  "properties": {
    "addr:full":"ZA Froideconche Franche Comt\u00e9 70300",
    "addr:postcode":"70300",
    "addr:street":"Za Froideconche Franche Comte\u0301",
    "iso:country":"FR",
    "sg:address":"ZA",
    "sg:city":"Froideconche",
    "sg:orig_category":"Unclassifiable Establishments",
    "sg:phone":"+33 3 84 40 12 04",
    "sg:postcode":"70300",
    "sg:province":"Franche Comt\u00e9",
    "wof:name":"Poupinet S.a.",
    "wof:placetype":"venue"
},
  "geometry": {"coordinates":[6.3795,47.819172],"type":"Point"}
}