{
  "type": "Feature",
  "properties": {
    "iso:country":"FR",
    "sg:address":"273, Rue Saint Denis, 75002 Paris",
    "sg:orig_category":"Non-Classified Establishments",
    "sg:phone":"+33 1 40 26 30 98",
    "sg:province":"Ile de France",
    "wof:name":"S.e.m. Biscote S.a.",
    "wof:placetype":"venue"
},
  "geometry": {"coordinates":[2.35188,48.868622],"type":"Point"}
}