{
  "type": "Feature",
  "properties": {
    "addr:full":"41, Bd Vauban, 59046 Lille C\u00e9dex Nord-Pas-de-Calais",
    "addr:housenumber":"41",
    "addr:postcode":"59046",
    "addr:street":"Bd Vauban;Ce\u0301Dex",
    "iso:country":"FR",
    "sg:address":"41, Bd Vauban, 59046 Lille C\u00e9dex",
    "sg:orig_category":"Non-Classified Establishments",
    "sg:phone":"+33 3 20 30 85 29",
    "sg:province":"Nord-Pas-de-Calais",
    "wof:name":"Gesti",
    "wof:placetype":"venue"
},
  "geometry": {"coordinates":[3.04853,50.634045],"type":"Point"}
}