{
  "type": "Feature",
  "properties": {
    "addr:full":"12, Rue de la C\u00e9si\u00e8re - Bureau de chantier, 74600 Seynod Rhone-Alpes",
    "addr:housenumber":"12",
    "addr:postcode":"74600",
    "addr:street":"Rue De La Ce\u0301Sie\u0300Re",
    "iso:country":"FR",
    "sg:address":"12, Rue de la C\u00e9si\u00e8re - Bureau de chantier, 74600 Seynod",
    "sg:orig_category":"Non-Classified Establishments",
    "sg:phone":"+33 4 50 52 37 44",
    "sg:province":"Rhone-Alpes",
    "wof:name":"Sdel Savoie Leman S.a.s.",
    "wof:placetype":"venue"
},
  "geometry": {"coordinates":[6.100926,45.888924],"type":"Point"}
}