{
  "type": "Feature",
  "properties": {
    "iso:country":"FR",
    "sg:address":"54, Rue de la Chapelle, 74460 Marnaz",
    "sg:orig_category":"Unclassifiable Establishments",
    "sg:phone":"+33 4 50 98 35 46",
    "sg:postcode":"74460",
    "sg:province":"Rhone-Alpes",
    "wof:name":"Paul L\u00e9ger Et Fils S.a.r.l.",
    "wof:placetype":"venue"
},
  "geometry": {"coordinates":[6.525448,46.059307],"type":"Point"}
}