{
  "type": "Feature",
  "properties": {
    "addr:full":"84, Quai Claude Le Lorrain, 54000 Nancy Lorraine",
    "addr:housenumber":"84",
    "addr:postcode":"54000",
    "addr:street":"Quai Claude Le Lorrain",
    "iso:country":"FR",
    "sg:address":"84, Quai Claude Le Lorrain, 54000 Nancy",
    "sg:orig_category":"Unclassifiable Establishments",
    "sg:phone":"+33 3 83 35 48 86",
    "sg:province":"Lorraine",
    "wof:name":"Socotec S.a.",
    "wof:placetype":"venue"
},
  "geometry": {"coordinates":[6.170377,48.698051],"type":"Point"}
}