{
  "type": "Feature",
  "properties": {
    "addr:full":"Rue des Nobles Tauves Auvergne 63690",
    "addr:postcode":"63690",
    "addr:street":"Rue Des Nobles",
    "iso:country":"FR",
    "sg:address":"Rue des Nobles",
    "sg:city":"Tauves",
    "sg:orig_category":"Non-Classified Establishments",
    "sg:phone":"+33 4 73 21 10 48",
    "sg:postcode":"63690",
    "sg:province":"Auvergne",
    "wof:name":"Entreprise Lemonnier S.a.r.l.",
    "wof:placetype":"venue"
},
  "geometry": {"coordinates":[2.622405,45.5602],"type":"Point"}
}