{
  "type": "Feature",
  "properties": {
    "iso:country":"FR",
    "sg:address":"Ccal Carrefour 91620 La Ville Du Bois",
    "sg:classifiers":[
        {
            "category":"Professional",
            "subcategory":"Advertising",
            "type":"Services"
        }
    ],
    "sg:phone":"+33 1 64 49 73 34",
    "sg:postcode":"91620",
    "sg:province":"Ile de France",
    "sg:tags":[
        "information",
        "medium",
        "communication"
    ],
    "wof:name":"Photo Express",
    "wof:placetype":"venue"
},
  "geometry": {"coordinates":[2.242235,48.66037],"type":"Point"}
}