{
  "type": "Feature",
  "properties": {
    "iso:country":"FR",
    "sg:address":"Les Cafourches 24350 La Chapelle Gonaguet",
    "sg:city":"Bussac",
    "sg:classifiers":[
        {
            "category":"Professional",
            "type":"Services"
        }
    ],
    "sg:phone":"+33 5 53 03 54 62",
    "sg:postcode":"24350",
    "sg:province":"Aquitaine",
    "sg:tags":[
        "transport",
        "road"
    ],
    "wof:name":"Translait Laroche Sarl",
    "wof:placetype":"venue"
},
  "geometry": {"coordinates":[0.613307,45.23288],"type":"Point"}
}