{
  "type": "Feature",
  "properties": {
    "iso:country":"FR",
    "sg:address":"RN 90 - Zone d'Am\u00e9nagement Concert\u00e9 Expo Sud",
    "sg:city":"Orl\u00e9ans",
    "sg:orig_category":"Unclassifiable Establishments",
    "sg:phone":"+33 2 38 51 07 07",
    "sg:postcode":"45100",
    "sg:province":"Centre",
    "wof:name":"Kiloutou S.a.",
    "wof:placetype":"venue"
},
  "geometry": {"coordinates":[1.93345,47.854561],"type":"Point"}
}