{
  "type": "Feature",
  "properties": {
    "addr:full":"15, Rue Vladimir Jankelevitch, 77184 Emerainville Ile de France 77184",
    "addr:housenumber":"15",
    "addr:postcode":"77184;77184",
    "addr:street":"Rue Vladimir Jankelevitch;Ile De France",
    "iso:country":"FR",
    "sg:address":"15, Rue Vladimir Jankelevitch, 77184 Emerainville",
    "sg:orig_category":"Non-Classified Establishments",
    "sg:phone":"+33 1 64 61 66 66",
    "sg:postcode":"77184",
    "sg:province":"Ile de France",
    "wof:name":"Bio Advance S.a.r.l.",
    "wof:placetype":"venue"
},
  "geometry": {"coordinates":[2.586215,48.829113],"type":"Point"}
}