{
  "type": "Feature",
  "properties": {
    "iso:country":"FR",
    "sg:address":"Z.A.C. Le Rambonneau",
    "sg:city":"Poulainville",
    "sg:orig_category":"Non-Classified Establishments",
    "sg:phone":"+33 3 22 43 17 49",
    "sg:postcode":"80260",
    "sg:province":"Picardie",
    "wof:name":"Rog\u00e9e Raymond",
    "wof:placetype":"venue"
},
  "geometry": {"coordinates":[2.309245,49.944965],"type":"Point"}
}