{
  "type": "Feature",
  "properties": {
    "iso:country":"FR",
    "sg:address":"191 rue des 5 Voies 59200 Tourcoing",
    "sg:classifiers":[
        {
            "category":"Manufacturing",
            "subcategory":"Textiles",
            "type":"Manufacturing & Wholesale Goods"
        }
    ],
    "sg:phone":"+33 3 20 11 64 64",
    "sg:province":"Nord Pas-de-Calais",
    "sg:tags":[
        "used",
        "machines"
    ],
    "wof:name":"Thibeau Sa",
    "wof:placetype":"venue"
},
  "geometry": {"coordinates":[3.169004,50.711456],"type":"Point"}
}