{
  "type": "Feature",
  "properties": {
    "addr:full":"76 route des Creuses 74960 CRAN GEVRIER Rhone-Alpes 74960",
    "addr:housenumber":"76",
    "addr:postcode":"74960;74960",
    "addr:street":"Route Des Creuses;Rhone-Alpes",
    "iso:country":"FR",
    "sg:address":"76 route des Creuses 74960 CRAN GEVRIER",
    "sg:classifiers":[
        {
            "category":"Home & Garden",
            "subcategory":"Furniture",
            "type":"Retail Goods"
        }
    ],
    "sg:phone":"+33 4 50 69 33 51",
    "sg:postcode":"74960",
    "sg:province":"Rhone-Alpes",
    "wof:name":"Adm Sas",
    "wof:placetype":"venue"
},
  "geometry": {"coordinates":[6.089161,45.891407],"type":"Point"}
}