{
  "type": "Feature",
  "properties": {
    "addr:full":"B.P. 411, 80004 Amiens C\u00e9dex^^19, Rue Masclef, 80000 Amiens Picardie",
    "addr:housenumber":"b.p. 411",
    "addr:postcode":"80004;80000",
    "addr:street":"Rue Masclef",
    "iso:country":"FR",
    "sg:address":"B.P. 411, 80004 Amiens C\u00e9dex^^19, Rue Masclef, 80000 Amiens",
    "sg:orig_category":"Non-Classified Establishments",
    "sg:phone":"+33 3 22 71 31 61",
    "sg:province":"Picardie",
    "wof:name":"G.c.p. S.a. - G\u00e9nie Civil De Picardie",
    "wof:placetype":"venue"
},
  "geometry": {"coordinates":[2.293165,49.894733],"type":"Point"}
}