{
  "type": "Feature",
  "properties": {
    "iso:country":"FR",
    "sg:address":"57 Bis Boulevard B\u00e9ranger",
    "sg:city":"Tours",
    "sg:classifiers":[
        {
            "category":"Banks & Credit Unions",
            "subcategory":"Financial Services",
            "type":"Services"
        }
    ],
    "sg:phone":"+33 2 47 05 80 05",
    "sg:postcode":"37000",
    "sg:province":"Centre",
    "sg:tags":[
        "banking",
        "finance",
        "insurance"
    ],
    "wof:name":"San Valeri Organisation Sarl",
    "wof:placetype":"venue"
},
  "geometry": {"coordinates":[0.679762,47.389252],"type":"Point"}
}