{
  "type": "Feature",
  "properties": {
    "iso:country":"FR",
    "sg:address":"B.P. 923, 60009 Beauvais C\u00e9dex^^10, Chauss\u00e9e Feldtrappe, 60000 Beauvais",
    "sg:orig_category":"Non-Classified Establishments",
    "sg:phone":"+33 3 44 06 37 00",
    "sg:province":"Picardie",
    "wof:name":"Viskase S.a.",
    "wof:placetype":"venue"
},
  "geometry": {"coordinates":[2.08322,49.429558],"type":"Point"}
}