{
  "type": "Feature",
  "properties": {
    "addr:full":"19, Place du Groupe Scolaire, 63250 Chabreloche Chabreloche Auvergne 63250",
    "addr:housenumber":"19",
    "addr:postcode":"63250;chabreloche;63250",
    "addr:street":"Place Du Groupe Scolaire",
    "iso:country":"FR",
    "sg:address":"19, Place du Groupe Scolaire, 63250 Chabreloche",
    "sg:city":"Chabreloche",
    "sg:orig_category":"Non-Classified Establishments",
    "sg:phone":"+33 4 73 94 27 29",
    "sg:postcode":"63250",
    "sg:province":"Auvergne",
    "wof:name":"Regnaud S.a.r.l.",
    "wof:placetype":"venue"
},
  "geometry": {"coordinates":[3.694637,45.877975],"type":"Point"}
}