{
  "type": "Feature",
  "properties": {
    "iso:country":"FR",
    "sg:address":"12 Rue Nicolas Robert 93600 Aulnay Sous Bois",
    "sg:classifiers":[
        {
            "category":"Professional",
            "subcategory":"Engineering",
            "type":"Services"
        }
    ],
    "sg:phone":"+33 1 48 19 96 96",
    "sg:postcode":"93600",
    "sg:province":"Ile de France",
    "sg:tags":[
        "machine",
        "-",
        "mechanical"
    ],
    "wof:name":"Rogat Industries Sa",
    "wof:placetype":"venue"
},
  "geometry": {"coordinates":[2.487611,48.945076],"type":"Point"}
}