{
  "type": "Feature",
  "properties": {
    "addr:full":"13/15, Bd de la Madeleine, 75001 Paris Ile de France",
    "addr:housenumber":"13 / 15",
    "addr:postcode":"75001;france",
    "addr:street":"Bd De La Madeleine",
    "iso:country":"FR",
    "sg:address":"13/15, Bd de la Madeleine, 75001 Paris",
    "sg:orig_category":"Unclassifiable Establishments",
    "sg:phone":"+33 1 44 55 52 03",
    "sg:province":"Ile de France",
    "wof:name":"Quantas Airways S.a.",
    "wof:placetype":"venue"
},
  "geometry": {"coordinates":[2.326352,48.869602],"type":"Point"}
}