{
  "type": "Feature",
  "properties": {
    "addr:full":"34 Sully 45730 Saint Beno\u00eet sur Loire Centre",
    "addr:housenumber":"34",
    "addr:postcode":"45730",
    "addr:street":"Sully;Benoi\u0302T",
    "iso:country":"FR",
    "sg:address":"34",
    "sg:city":"Sully 45730 Saint Beno\u00eet sur Loire",
    "sg:classifiers":[
        {
            "category":"Manufacturing",
            "subcategory":"Rubber & Plastics",
            "type":"Manufacturing & Wholesale Goods"
        }
    ],
    "sg:phone":"+33 2 38 35 77 77",
    "sg:province":"Centre",
    "sg:tags":[
        "packaging",
        "material",
        "-"
    ],
    "wof:name":"J.p.b. Emballage",
    "wof:placetype":"venue"
},
  "geometry": {"coordinates":[2.30255,47.813129],"type":"Point"}
}