{
  "type": "Feature",
  "properties": {
    "iso:country":"FR",
    "sg:address":"B.P. 1217, 78202 Mantes la Jolie C\u00e9dex^^28, Bd Roger Salengro, 78711 Mantes la Ville",
    "sg:city":"Vill\u00e9",
    "sg:orig_category":"Non-Classified Establishments",
    "sg:phone":"+33 1 34 77 72 00",
    "sg:postcode":"67220",
    "sg:province":"Alsace",
    "wof:name":"Sulzen Pompes France S.a.s.",
    "wof:placetype":"venue"
},
  "geometry": {"coordinates":[1.71416,48.977772],"type":"Point"}
}