{
  "type": "Feature",
  "properties": {
    "iso:country":"FR",
    "sg:address":"40 Av Du Pr\u00e9sident Jf Kenndy 33700 M\u00e9rignac",
    "sg:city":"M\u00e9rignac",
    "sg:classifiers":[
        {
            "category":"Manufacturing",
            "subcategory":"Chemicals & Compounds",
            "type":"Manufacturing & Wholesale Goods"
        }
    ],
    "sg:phone":"+33 5 56 34 88 34",
    "sg:postcode":"33700",
    "sg:province":"Aquitaine",
    "sg:tags":[
        "pharmaceutical",
        "chemistry"
    ],
    "wof:name":"Chem Industries Sa",
    "wof:placetype":"venue"
},
  "geometry": {"coordinates":[-0.64762,44.841808],"type":"Point"}
}