{
  "type": "Feature",
  "properties": {
    "addr:full":"Rte d'Herbeauvilliers Amponville Ile de France 77760",
    "addr:postcode":"77760",
    "addr:street":"Rte D'Herbeauvilliers",
    "iso:country":"FR",
    "sg:address":"Rte d'Herbeauvilliers",
    "sg:city":"Amponville",
    "sg:orig_category":"Unclassifiable Establishments",
    "sg:phone":"+33 1 64 24 34 91",
    "sg:postcode":"77760",
    "sg:province":"Ile de France",
    "wof:name":"Pr\u00e9cision-profils S.a.",
    "wof:placetype":"venue"
},
  "geometry": {"coordinates":[2.47475,48.282089],"type":"Point"}
}