{
  "type": "Feature",
  "properties": {
    "addr:full":"B.P. 317, 17013 La Rochelle C\u00e9dex^^6, Rue Eug\u00e8ne Thomas - B\u00e2t. B 1er Etage, 17000 La Rochelle Poitou-Charentes",
    "addr:housenumber":"b.p. 317;ba\u0302t;1er",
    "addr:postcode":"17013;b;etage 17000",
    "addr:street":"Rue Euge\u0300Ne Thomas",
    "iso:country":"FR",
    "sg:address":"B.P. 317, 17013 La Rochelle C\u00e9dex^^6, Rue Eug\u00e8ne Thomas - B\u00e2t. B 1er Etage, 17000 La Rochelle",
    "sg:orig_category":"Non-Classified Establishments",
    "sg:phone":"+33 5 46 41 28 33",
    "sg:province":"Poitou-Charentes",
    "wof:name":"M.h.r. Industrie S.a.",
    "wof:placetype":"venue"
},
  "geometry": {"coordinates":[-1.151639,46.159435],"type":"Point"}
}