{
  "type": "Feature",
  "properties": {
    "addr:full":"122 Av Des Pyr\u00e9n\u00e9es 33140 Villenave D'Ornon Cadaujac Aquitaine 33140",
    "addr:postcode":"33140;33140",
    "addr:street":"122 Av Des Pyre\u0301Ne\u0301Es",
    "iso:country":"FR",
    "sg:address":"122 Av Des Pyr\u00e9n\u00e9es 33140 Villenave D'Ornon",
    "sg:city":"Cadaujac",
    "sg:classifiers":[
        {
            "category":"Professional",
            "subcategory":"Engineering",
            "type":"Services"
        }
    ],
    "sg:phone":"+33 5 56 87 71 30",
    "sg:postcode":"33140",
    "sg:province":"Aquitaine",
    "sg:tags":[
        "machine",
        "-",
        "mechanical"
    ],
    "wof:name":"Zhendre",
    "wof:placetype":"venue"
},
  "geometry": {"coordinates":[-0.561607,44.76527],"type":"Point"}
}