{
  "type": "Feature",
  "properties": {
    "addr:full":"Rue de la Warenne Les Ayvelles Champagne 08000",
    "addr:housenumber":"ayvelles",
    "addr:postcode":"08000",
    "addr:street":"Rue De La Warenne Les;Champagne",
    "iso:country":"FR",
    "sg:address":"Rue de la Warenne",
    "sg:city":"Les Ayvelles",
    "sg:orig_category":"Non-Classified Establishments",
    "sg:phone":"+33 3 24 37 31 36",
    "sg:postcode":"08000",
    "sg:province":"Champagne",
    "wof:name":"E.g.i.e. S.a.",
    "wof:placetype":"venue"
},
  "geometry": {"coordinates":[4.759065,49.721489],"type":"Point"}
}