{
  "type": "Feature",
  "properties": {
    "addr:full":"535 rue Pierre Simon Laplace 13090 Aix En Provence Nord Pas-de-Calais",
    "addr:housenumber":"535",
    "addr:postcode":"13090",
    "addr:street":"Rue Pierre Simon Laplace;En Provence Nord",
    "iso:country":"FR",
    "sg:address":"535 rue Pierre Simon Laplace 13090 Aix En Provence",
    "sg:classifiers":[
        {
            "category":"Shopping",
            "subcategory":"Beauty & Cosmetics",
            "type":"Retail Goods"
        }
    ],
    "sg:phone":"+33 4 42 24 56 24",
    "sg:province":"Nord Pas-de-Calais",
    "sg:tags":[
        "natural"
    ],
    "wof:name":"Laboratoires Phytomedica S.a.r.l.",
    "wof:placetype":"venue"
},
  "geometry": {"coordinates":[5.378635,43.476055],"type":"Point"}
}