{
  "type": "Feature",
  "properties": {
    "addr:full":"Parc des Activit\u00e9s la Pommeraie 50640 LE TEILLEUL Le Teilleul Basse Normandie 50640",
    "addr:postcode":"50640;50640",
    "addr:street":"Parc;La Pommeraie",
    "iso:country":"FR",
    "sg:address":"Parc des Activit\u00e9s la Pommeraie 50640 LE TEILLEUL",
    "sg:city":"Le Teilleul",
    "sg:classifiers":[
        {
            "category":"Retail",
            "subcategory":"Laundry & Dry Cleaning",
            "type":"Services"
        }
    ],
    "sg:phone":"+33 2 33 79 35 46",
    "sg:postcode":"50640",
    "sg:province":"Basse Normandie",
    "sg:tags":[
        "cider"
    ],
    "wof:name":"Cidrerie Volcler Sas",
    "wof:placetype":"venue"
},
  "geometry": {"coordinates":[-0.900381,48.50687],"type":"Point"}
}