{
  "type": "Feature",
  "properties": {
    "iso:country":"FR",
    "sg:address":"Zi Artois Flandres Zone C 62138 Billy Berclau",
    "sg:classifiers":[
        {
            "category":"Professional",
            "subcategory":"Engineering",
            "type":"Services"
        }
    ],
    "sg:phone":"+33 3 21 79 49 90",
    "sg:postcode":"62138",
    "sg:province":"Nord Pas-de-Calais",
    "sg:tags":[
        "machine",
        "-",
        "mechanical"
    ],
    "wof:name":"Lbcc Systemes Et Productique",
    "wof:placetype":"venue"
},
  "geometry": {"coordinates":[2.87091,50.521229],"type":"Point"}
}