{
  "type": "Feature",
  "properties": {
    "iso:country":"FR",
    "sg:address":"All\u00e9e du Pr\u00e9 du Roy",
    "sg:city":"Saint Prest",
    "sg:orig_category":"Non-Classified Establishments",
    "sg:phone":"+33 2 37 22 27 27",
    "sg:postcode":"28300",
    "sg:province":"Centre",
    "wof:name":"Le Manoir Des Pr\u00e9s Du Roy",
    "wof:placetype":"venue"
},
  "geometry": {"coordinates":[1.538541,48.501774],"type":"Point"}
}