{
  "type": "Feature",
  "properties": {
    "iso:country":"FR",
    "sg:address":"100 Avenue Du General Leclerc Zone De L Ourcq 93500 Pantin",
    "sg:classifiers":[
        {
            "category":"Shopping",
            "subcategory":"Clothing, Apparel, & Fashions",
            "type":"Retail Goods"
        }
    ],
    "sg:phone":"+33 1 44 88 28 82",
    "sg:postcode":"93500",
    "sg:province":"Ile de France",
    "sg:tags":[
        "textile",
        "clothing",
        "clothes"
    ],
    "wof:name":"Sundy",
    "wof:placetype":"venue"
},
  "geometry": {"coordinates":[2.40168,48.89658],"type":"Point"}
}