{
  "type": "Feature",
  "properties": {
    "iso:country":"FR",
    "sg:address":"Quartier de Fourchon - Mas de V\u00e9ran",
    "sg:city":"Arles",
    "sg:orig_category":"Non-Classified Establishments",
    "sg:phone":"+33 4 90 18 49 49",
    "sg:postcode":"13200",
    "sg:province":"Provence-Alpes-C\u00f4te d'Azur",
    "wof:name":"Ma\u00ebva Latitudes Camargue",
    "wof:placetype":"venue"
},
  "geometry": {"coordinates":[4.644145,43.656925],"type":"Point"}
}