{
  "type": "Feature",
  "properties": {
    "iso:country":"FR",
    "sg:address":"70 Rue Montgrand",
    "sg:city":"Marseille",
    "sg:classifiers":[
        {
            "category":"Banks & Credit Unions",
            "subcategory":"Financial Services",
            "type":"Services"
        }
    ],
    "sg:phone":"+33 4 91 33 58 20",
    "sg:postcode":"13006",
    "sg:province":"Provence-Alpes-C\u00f4te d'Azur",
    "sg:tags":[
        "banking",
        "finance",
        "insurance"
    ],
    "wof:name":"Alain Vidal-naquet Norbert Morant Ass",
    "wof:placetype":"venue"
},
  "geometry": {"coordinates":[5.375668,43.291172],"type":"Point"}
}