{
  "type": "Feature",
  "properties": {
    "addr:full":"R De La Lissoni\u00e8re 27210 St Maclou Haute Normandie",
    "addr:postcode":"27210",
    "addr:street":"Haute Normandie",
    "iso:country":"FR",
    "sg:address":"R De La Lissoni\u00e8re 27210 St Maclou",
    "sg:classifiers":[
        {
            "category":"Professional",
            "type":"Services"
        }
    ],
    "sg:phone":"+33 2 32 41 26 10",
    "sg:province":"Haute Normandie",
    "sg:tags":[
        "transport",
        "road"
    ],
    "wof:name":"Beaucamp Sas",
    "wof:placetype":"venue"
},
  "geometry": {"coordinates":[0.41129,49.356339],"type":"Point"}
}