{
  "type": "Feature",
  "properties": {
    "iso:country":"FR",
    "sg:address":"132, Bd de Strasbourg, 76600 Le Havre",
    "sg:orig_category":"Non-Classified Establishments",
    "sg:phone":"+33 2 35 42 24 32",
    "sg:province":"Haute Normandie",
    "wof:name":"Imprimerie Havraise Deshayes Et Compagnie S.a.r.l.",
    "wof:placetype":"venue"
},
  "geometry": {"coordinates":[0.11459,49.492741],"type":"Point"}
}