{
  "type": "Feature",
  "properties": {
    "addr:full":"12, Av. Marie Amp\u00e8re - Immeuble le Triptyque, 77420 Champs sur Marne Ile de France",
    "addr:postcode":"77420",
    "addr:street":"12 Av. Marie Ampe\u0300Re Immeuble Le Triptyque",
    "iso:country":"FR",
    "sg:address":"12, Av. Marie Amp\u00e8re - Immeuble le Triptyque, 77420 Champs sur Marne",
    "sg:orig_category":"Non-Classified Establishments",
    "sg:phone":"+33 1 64 73 55 55",
    "sg:province":"Ile de France",
    "wof:name":"Foseco S.a.",
    "wof:placetype":"venue"
},
  "geometry": {"coordinates":[2.583029,48.843952],"type":"Point"}
}