{
  "type": "Feature",
  "properties": {
    "iso:country":"FR",
    "sg:address":"Route St Affrique 12380 St Sernin Sur Rance",
    "sg:orig_category":"Agriculture - machinery and equipment Animals and breeding Mechanical Engineering - machines Packagi",
    "sg:phone":"+33 5 65 99 62 40",
    "sg:postcode":"12380",
    "sg:province":"Midi Pyr\u00e9n\u00e9es",
    "wof:name":"Faf Sa",
    "wof:placetype":"venue"
},
  "geometry": {"coordinates":[2.612938,43.882774],"type":"Point"}
}