{
  "type": "Feature",
  "properties": {
    "addr:full":"B.P. 55, 01190 Pont de Vaux C\u00e9dex^^Rte de Fleurville, 01190 Pont de Vaux Rhone-Alpes",
    "addr:postcode":"01190;01190",
    "addr:street":"B.P. 55;Fleurville;Rhone-Alpes",
    "iso:country":"FR",
    "sg:address":"B.P. 55, 01190 Pont de Vaux C\u00e9dex^^Rte de Fleurville, 01190 Pont de Vaux",
    "sg:orig_category":"Non-Classified Establishments",
    "sg:phone":"+33 3 85 51 59 01",
    "sg:province":"Rhone-Alpes",
    "wof:name":"Guillot Industrie S.a.",
    "wof:placetype":"venue"
},
  "geometry": {"coordinates":[4.959331,46.43729],"type":"Point"}
}