{
  "type": "Feature",
  "properties": {
    "addr:full":"67, Rue de l'Aqueduc, 30000 N\u00eemes Languedoc-Roussillon",
    "addr:housenumber":"67",
    "addr:postcode":"30000",
    "addr:street":"Rue De L'Aqueduc",
    "iso:country":"FR",
    "sg:address":"67, Rue de l'Aqueduc, 30000 N\u00eemes",
    "sg:orig_category":"Unclassifiable Establishments",
    "sg:phone":"+33 4 66 29 15 91",
    "sg:province":"Languedoc-Roussillon",
    "wof:name":"Martin Richard",
    "wof:placetype":"venue"
},
  "geometry": {"coordinates":[4.354665,43.829823],"type":"Point"}
}