{
  "type": "Feature",
  "properties": {
    "addr:full":"12 Rue Porte D'Etampes 78730 Rochefort En Yvelines Ile de France 78730",
    "addr:housenumber":"12",
    "addr:postcode":"78730;78730",
    "addr:street":"Rue Porte D'Etampes",
    "iso:country":"FR",
    "sg:address":"12 Rue Porte D'Etampes 78730 Rochefort En Yvelines",
    "sg:classifiers":[
        {
            "category":"Farming",
            "subcategory":"Crops",
            "type":"Manufacturing & Wholesale Goods"
        }
    ],
    "sg:phone":"+33 1 30 41 48 25",
    "sg:postcode":"78730",
    "sg:province":"Ile de France",
    "sg:tags":[
        "vegetable",
        "fruit",
        "agriculture",
        "livestock"
    ],
    "wof:name":"France Food",
    "wof:placetype":"venue"
},
  "geometry": {"coordinates":[1.988815,48.583935],"type":"Point"}
}