{
  "type": "Feature",
  "properties": {
    "addr:full":"Rue des Bonnetiers - ZI Sainte M\u00e9n\u00e9hould Champagne 51800",
    "addr:postcode":"51800",
    "addr:street":"Rue Des Bonnetiers Zi Sainte Me\u0301Ne\u0301Hould Champagne",
    "iso:country":"FR",
    "sg:address":"Rue des Bonnetiers - ZI",
    "sg:city":"Sainte M\u00e9n\u00e9hould",
    "sg:orig_category":"COUVERTURE ET ACCESSOIRES Distributeur: Quincailleries, fournitures industrielles chauffage sanitair",
    "sg:phone":"+33 3 26 60 84 01",
    "sg:postcode":"51800",
    "sg:province":"Champagne",
    "wof:name":"Virrion S.a.",
    "wof:placetype":"venue"
},
  "geometry": {"coordinates":[-80.127045,39.512737],"type":"Point"}
}