{
  "type": "Feature",
  "properties": {
    "iso:country":"FR",
    "sg:address":"Rue Tristan Corbi\u00e8re 56500 Locmin\u00e9",
    "sg:city":"Locmin\u00e9",
    "sg:classifiers":[
        {
            "category":"Bakery",
            "type":"Food & Drink"
        }
    ],
    "sg:phone":"+33 2 97 60 02 01",
    "sg:postcode":"56500",
    "sg:province":"Bretagne",
    "sg:tags":[
        "cake",
        "product",
        "related",
        "bread"
    ],
    "wof:name":"Gaillard Patissiers Sa",
    "wof:placetype":"venue"
},
  "geometry": {"coordinates":[-2.837182,47.884819],"type":"Point"}
}