{
  "type": "Feature",
  "properties": {
    "addr:full":"B.P. 10, 59188 Saint Vaast en Cambr\u00e9sis^^13, Rue Jean Jaur\u00e9s, 59188 Saint Vaast en Cambr\u00e9sis Nord Pas-de-Calais",
    "addr:postcode":"59188;59188",
    "addr:street":"B.P. 10;Rue Jean Jaure\u0301S",
    "iso:country":"FR",
    "sg:address":"B.P. 10, 59188 Saint Vaast en Cambr\u00e9sis^^13, Rue Jean Jaur\u00e9s, 59188 Saint Vaast en Cambr\u00e9sis",
    "sg:orig_category":"Non-Classified Establishments",
    "sg:phone":"+33 3 27 37 14 22",
    "sg:province":"Nord Pas-de-Calais",
    "wof:name":"Leduc Duez S.a.r.l.",
    "wof:placetype":"venue"
},
  "geometry": {"coordinates":[3.421592,50.192177],"type":"Point"}
}