{
  "type": "Feature",
  "properties": {
    "addr:full":"301 rue de Lille 59223 Roncq Nord Pas-de-Calais 59223",
    "addr:housenumber":"301",
    "addr:postcode":"59223;59223",
    "addr:street":"Rue De Lille",
    "iso:country":"FR",
    "sg:address":"301 rue de Lille 59223 Roncq",
    "sg:classifiers":[
        {
            "category":"Banks & Credit Unions",
            "subcategory":"Investment Brokerage",
            "type":"Services"
        }
    ],
    "sg:phone":"+33 3 20 46 28 28",
    "sg:postcode":"59223",
    "sg:province":"Nord Pas-de-Calais",
    "sg:tags":[
        "accessory",
        "high-fashion"
    ],
    "wof:name":"Daniel Latour S.a.r.l.",
    "wof:placetype":"venue"
},
  "geometry": {"coordinates":[3.117482,50.743378],"type":"Point"}
}