{
  "type": "Feature",
  "properties": {
    "addr:full":"B.P. 246, 91944 Courtaboeuf C\u00e9dex^^27, Av. de la Baltique, 91940 Les Ulis Ile de France",
    "addr:housenumber":"b.p. 246",
    "addr:postcode":"91944;91940",
    "addr:street":"Av. De La Baltique",
    "iso:country":"FR",
    "sg:address":"B.P. 246, 91944 Courtaboeuf C\u00e9dex^^27, Av. de la Baltique, 91940 Les Ulis",
    "sg:orig_category":"Non-Classified Establishments",
    "sg:phone":"+33 1 69 59 87 00",
    "sg:province":"Ile de France",
    "wof:name":"Nilfisk Advance S.a.",
    "wof:placetype":"venue"
},
  "geometry": {"coordinates":[2.169475,48.68161],"type":"Point"}
}