{
  "type": "Feature",
  "properties": {
    "addr:full":"18, Rue de la Raini\u00e8re - Parc Club du Perray - B\u00e2t. P 9, 44339 Nantes C\u00e9dex 3 Champagne",
    "addr:housenumber":"18;ba\u0302t p 9;3",
    "addr:postcode":"44339",
    "addr:street":"Rue De La Rainie\u0300Re Parc Club Du Perray",
    "iso:country":"FR",
    "sg:address":"18, Rue de la Raini\u00e8re - Parc Club du Perray - B\u00e2t. P 9, 44339 Nantes C\u00e9dex 3",
    "sg:orig_category":"Non-Classified Establishments",
    "sg:phone":"+33 2 51 89 71 71",
    "sg:province":"Champagne",
    "wof:name":"Elona S.a.",
    "wof:placetype":"venue"
},
  "geometry": {"coordinates":[-1.507803,47.247631],"type":"Point"}
}