{
  "type": "Feature",
  "properties": {
    "addr:full":"La Rippe des Monts 71470 Romenay Romenay Bourgogne 71470",
    "addr:postcode":"71470;71470",
    "addr:street":"La;Des Monts",
    "iso:country":"FR",
    "sg:address":"La Rippe des Monts 71470 Romenay",
    "sg:city":"Romenay",
    "sg:orig_category":"Non-Classified Establishments",
    "sg:phone":"+33 3 85 40 30 98",
    "sg:postcode":"71470",
    "sg:province":"Bourgogne",
    "wof:name":"Etablissements Roger Donguy S.a.r.l.",
    "wof:placetype":"venue"
},
  "geometry": {"coordinates":[5.116135,46.517204],"type":"Point"}
}