{
  "type": "Feature",
  "properties": {
    "iso:country":"FR",
    "sg:address":"14 Av De Colmar 68100 Mulhouse",
    "sg:city":"Mulhouse",
    "sg:classifiers":[
        {
            "category":"Home & Garden",
            "subcategory":"Furniture",
            "type":"Retail Goods"
        }
    ],
    "sg:phone":"+33 3 89 62 36 36",
    "sg:postcode":"68100",
    "sg:province":"Alsace",
    "sg:tags":[
        "professional",
        "household",
        "wood"
    ],
    "wof:name":"Mobilier Europeen",
    "wof:placetype":"venue"
},
  "geometry": {"coordinates":[7.338458,47.751125],"type":"Point"}
}