{
  "type": "Feature",
  "properties": {
    "iso:country":"FR",
    "sg:address":"84 rue Fran\u00e7ois Herbo 59310 Orchies",
    "sg:orig_category":"Roasters For Coffee, Cocoa, Grain, Malt Coffee, Chicory, Peanuts",
    "sg:phone":"+33 3 20 64 48 50",
    "sg:province":"Nord Pas-de-Calais",
    "wof:name":"Leroux Sa",
    "wof:placetype":"venue"
},
  "geometry": {"coordinates":[3.24645,50.47781],"type":"Point"}
}