{
  "type": "Feature",
  "properties": {
    "addr:full":"39-41 Av Paul Claude Les Champs Elys\u00e9es 91000 Evry Ile de France 91000",
    "addr:housenumber":"39-41",
    "addr:postcode":"91000;91000",
    "addr:street":"Av Paul Claude Les;Elyse\u0301Es",
    "iso:country":"FR",
    "sg:address":"39-41 Av Paul Claude Les Champs Elys\u00e9es 91000 Evry",
    "sg:classifiers":[
        {
            "category":"Professional",
            "subcategory":"Advertising",
            "type":"Services"
        }
    ],
    "sg:phone":"+33 1 64 97 02 02",
    "sg:postcode":"91000",
    "sg:province":"Ile de France",
    "sg:tags":[
        "information",
        "medium",
        "communication"
    ],
    "wof:name":"Comareg Bonjour Sa",
    "wof:placetype":"venue"
},
  "geometry": {"coordinates":[2.4293,48.624664],"type":"Point"}
}