{
  "type": "Feature",
  "properties": {
    "iso:country":"FR",
    "sg:address":"Le Mesnil Roux 76360 Barentin",
    "sg:classifiers":[
        {
            "category":"Manufacturing",
            "subcategory":"Metals",
            "type":"Manufacturing & Wholesale Goods"
        }
    ],
    "sg:phone":"+33 2 32 94 50 80",
    "sg:postcode":"76360",
    "sg:province":"Haute Normandie",
    "sg:tags":[
        "-",
        "machine",
        "equipment",
        "engineering",
        "machinery",
        "mechanical"
    ],
    "wof:name":"Tolerie Ganaye Industrielle (tgi)",
    "wof:placetype":"venue"
},
  "geometry": {"coordinates":[0.966315,49.535774],"type":"Point"}
}