{
  "type": "Feature",
  "properties": {
    "iso:country":"FR",
    "sg:address":"10, Rue du Danemark, 44470 Carquefou",
    "sg:orig_category":"Non-Classified Establishments",
    "sg:phone":"+33 2 40 30 04 77",
    "sg:province":"Pays de Loire",
    "wof:name":"Ouest Injection S.a.",
    "wof:placetype":"venue"
},
  "geometry": {"coordinates":[-1.498586,47.26115],"type":"Point"}
}