{
  "type": "Feature",
  "properties": {
    "addr:full":"16 Place Vendome 75001 Paris Ile de France 75001",
    "addr:housenumber":"16",
    "addr:postcode":"75001;75001",
    "addr:street":"Place Vendome",
    "iso:country":"FR",
    "sg:address":"16 Place Vendome 75001 Paris",
    "sg:classifiers":[
        {
            "category":"Professional",
            "subcategory":"Engineering",
            "type":"Services"
        }
    ],
    "sg:phone":"+33 1 42 60 04 10",
    "sg:postcode":"75001",
    "sg:province":"Ile de France",
    "sg:tags":[
        "machine",
        "-",
        "mechanical"
    ],
    "wof:name":"Laboratoires Garnier Paris",
    "wof:placetype":"venue"
},
  "geometry": {"coordinates":[2.330015,48.867035],"type":"Point"}
}