{
  "type": "Feature",
  "properties": {
    "addr:full":"33, Rue de Kingersheim, 68120 Richwiller Richwiller Alsace 68120",
    "addr:housenumber":"33",
    "addr:postcode":"68120;68120",
    "addr:street":"Rue De Kingersheim",
    "iso:country":"FR",
    "sg:address":"33, Rue de Kingersheim, 68120 Richwiller",
    "sg:city":"Richwiller",
    "sg:orig_category":"Unclassifiable Establishments",
    "sg:phone":"+33 3 89 50 03 93",
    "sg:postcode":"68120",
    "sg:province":"Alsace",
    "wof:name":"Klein Roland S.a.r.l.",
    "wof:placetype":"venue"
},
  "geometry": {"coordinates":[7.303924,47.788223],"type":"Point"}
}