{
  "type": "Feature",
  "properties": {
    "iso:country":"FR",
    "sg:address":"Rte de Verthier",
    "sg:city":"Doussard",
    "sg:orig_category":"Non-Classified Establishments",
    "sg:phone":"+33 4 50 44 35 09",
    "sg:postcode":"74210",
    "sg:province":"Rhone-Alpes",
    "wof:name":"M.g.c.m. S.a.r.l. - M\u00e9canique G\u00e9n\u00e9rale Carcasses De Moules",
    "wof:placetype":"venue"
},
  "geometry": {"coordinates":[6.231179,45.783512],"type":"Point"}
}