{
  "type": "Feature",
  "properties": {
    "addr:full":"180, Rue du Rond d'Eau - ZI la Saussaye, 45590 Saint Cyr en Val Saint-Cyr-en-Val Centre 45590",
    "addr:housenumber":"180",
    "addr:postcode":"45590;45590",
    "addr:street":"Rue Du Rond D'Eau Zi La Saussaye;Cyr En Val Saint-Cyr-En-Val",
    "iso:country":"FR",
    "sg:address":"180, Rue du Rond d'Eau - ZI la Saussaye, 45590 Saint Cyr en Val",
    "sg:city":"Saint-Cyr-en-Val",
    "sg:orig_category":"Unclassifiable Establishments",
    "sg:phone":"+33 2 38 69 38 00",
    "sg:postcode":"45590",
    "sg:province":"Centre",
    "wof:name":"Robot Christian",
    "wof:placetype":"venue"
},
  "geometry": {"coordinates":[1.953982,47.808144],"type":"Point"}
}