{
  "type": "Feature",
  "properties": {
    "iso:country":"FR",
    "sg:address":"5, Rue de l'Abb\u00e9 Gr\u00e9goire, 57000 Metz",
    "sg:orig_category":"Unclassifiable Establishments",
    "sg:phone":"+33 3 87 34 60 00",
    "sg:province":"Lorraine",
    "wof:name":"Les Courriers Mosellans S.a.",
    "wof:placetype":"venue"
},
  "geometry": {"coordinates":[6.171657,49.147312],"type":"Point"}
}