{
  "type": "Feature",
  "properties": {
    "addr:full":"Rue Claude Morel Louhans Bourgogne 71500",
    "addr:postcode":"71500",
    "addr:street":"Rue Claude Morel;Bourgogne",
    "iso:country":"FR",
    "sg:address":"Rue Claude Morel",
    "sg:city":"Louhans",
    "sg:orig_category":"Non-Classified Establishments",
    "sg:phone":"+33 3 85 75 10 23",
    "sg:postcode":"71500",
    "sg:province":"Bourgogne",
    "wof:name":"Kdi Bresse Hardy S.a.s.",
    "wof:placetype":"venue"
},
  "geometry": {"coordinates":[5.227815,46.63036],"type":"Point"}
}