{
  "type": "Feature",
  "properties": {
    "addr:full":"B.P. 223, 91160 Longjumeau Cedex^^59, Rue Saint Sauveur - Ballainvilliers , 91160 Longjumeau Ile de France",
    "addr:housenumber":"b.p. 223",
    "addr:postcode":"91160;91160;ile",
    "addr:street":"Rue Saint Sauveur",
    "iso:country":"FR",
    "sg:address":"B.P. 223, 91160 Longjumeau Cedex^^59, Rue Saint Sauveur - Ballainvilliers , 91160 Longjumeau",
    "sg:orig_category":"Non-Classified Establishments",
    "sg:phone":"+33 1 69 79 35 35",
    "sg:province":"Ile de France",
    "wof:name":"Sn Les Ma\u00e7ons De L'essonne S.a.",
    "wof:placetype":"venue"
},
  "geometry": {"coordinates":[2.29005,48.691734],"type":"Point"}
}