{
  "type": "Feature",
  "properties": {
    "iso:country":"FR",
    "sg:address":"B.P. 5, 70300 Froideconche^^Zone Industrielle Les Noyes, 70300 Froideconche",
    "sg:orig_category":"Non-Classified Establishments",
    "sg:phone":"+33 3 84 93 93 00",
    "sg:province":"Franche Comt\u00e9",
    "wof:name":"Transports Luxoviens S.a.",
    "wof:placetype":"venue"
},
  "geometry": {"coordinates":[6.3795,47.819172],"type":"Point"}
}