{
  "type": "Feature",
  "properties": {
    "iso:country":"FR",
    "sg:address":"rue des Transitaires 68300 ST LOUIS",
    "sg:city":"Saint-Louis",
    "sg:classifiers":[
        {
            "category":"Professional",
            "subcategory":"Employment Agencies",
            "type":"Services"
        }
    ],
    "sg:phone":"+33 3 89 67 21 23",
    "sg:postcode":"68300",
    "sg:province":"Alsace",
    "sg:tags":[
        "cargo"
    ],
    "wof:name":"Roba France Sarl",
    "wof:placetype":"venue"
},
  "geometry": {"coordinates":[7.565345,47.579266],"type":"Point"}
}