{
  "type": "Feature",
  "properties": {
    "addr:full":"971, Rue du Debout, 59310 Faumont Nord Pas-de-Calais",
    "addr:housenumber":"971",
    "addr:postcode":"59310",
    "addr:street":"Rue Du Debout",
    "iso:country":"FR",
    "sg:address":"971, Rue du Debout, 59310 Faumont",
    "sg:orig_category":"Unclassifiable Establishments",
    "sg:phone":"+33 3 20 92 17 67",
    "sg:province":"Nord Pas-de-Calais",
    "wof:name":"Lagache S.a.r.l.",
    "wof:placetype":"venue"
},
  "geometry": {"coordinates":[3.123289,50.450558],"type":"Point"}
}