{
  "type": "Feature",
  "properties": {
    "addr:full":"Rue G\u00e9rard de Nerval Othis Ile de France 77280",
    "addr:postcode":"77280",
    "addr:street":"Rue Ge\u0301Rard De Nerval",
    "iso:country":"FR",
    "sg:address":"Rue G\u00e9rard de Nerval",
    "sg:city":"Othis",
    "sg:orig_category":"Non-Classified Establishments",
    "sg:phone":"+33 1 60 03 02 27",
    "sg:postcode":"77280",
    "sg:province":"Ile de France",
    "wof:name":"Soci\u00e9t\u00e9 Robert Etienne S.a.r.l.",
    "wof:placetype":"venue"
},
  "geometry": {"coordinates":[2.675464,49.073444],"type":"Point"}
}