{
  "type": "Feature",
  "properties": {
    "iso:country":"FR",
    "sg:address":"3, Chemin Ch\u00eane, 78490 Galluis",
    "sg:orig_category":"Non-Classified Establishments",
    "sg:phone":"+33 1 34 57 04 50",
    "sg:province":"Ile de France",
    "wof:name":"R. Et D. Industries S.a.r.l.",
    "wof:placetype":"venue"
},
  "geometry": {"coordinates":[1.797418,48.796551],"type":"Point"}
}