{
  "type": "Feature",
  "properties": {
    "iso:country":"FR",
    "sg:address":"ZI n\u00b01",
    "sg:city":"L'Aigle",
    "sg:orig_category":"Unclassifiable Establishments",
    "sg:phone":"+33 2 33 84 34 99",
    "sg:postcode":"61300",
    "sg:province":"Basse Normandie",
    "wof:name":"Usine Plastohm S.a.",
    "wof:placetype":"venue"
},
  "geometry": {"coordinates":[0.64151,48.73592],"type":"Point"}
}