{
  "type": "Feature",
  "properties": {
    "iso:country":"FR",
    "sg:address":"20, Bd de la Lib\u00e9ration - B\u00e2t D - Villa Alexandra, 06230 Saint Jean Cap Ferrat",
    "sg:orig_category":"Unclassifiable Establishments",
    "sg:phone":"+33 4 93 76 82 52",
    "sg:province":"Provence-Alpes-C\u00f4te d'Azur",
    "wof:name":"Platinium Services Party S.a.r.l.",
    "wof:placetype":"venue"
},
  "geometry": {"coordinates":[7.330624,43.689892],"type":"Point"}
}