{
  "type": "Feature",
  "properties": {
    "addr:full":"Rte de Meulan Limay Ile de France 78520",
    "addr:postcode":"78520",
    "addr:street":"Rte De Meulan;Ile De France",
    "iso:country":"FR",
    "sg:address":"Rte de Meulan",
    "sg:city":"Limay",
    "sg:orig_category":"Unclassifiable Establishments",
    "sg:phone":"+33 1 30 98 36 80",
    "sg:postcode":"78520",
    "sg:province":"Ile de France",
    "wof:name":"B.d.i. S.a.s. - B\u00e9daricienne Doras Industries",
    "wof:placetype":"venue"
},
  "geometry": {"coordinates":[1.754482,48.991142],"type":"Point"}
}