{
  "type": "Feature",
  "properties": {
    "iso:country":"FR",
    "sg:address":"Route Nationale 34 77120 Mouroux",
    "sg:classifiers":[
        {
            "category":"Manufacturing",
            "subcategory":"Tools & Machinery",
            "type":"Manufacturing & Wholesale Goods"
        }
    ],
    "sg:phone":"+33 1 64 03 29 37",
    "sg:postcode":"77120",
    "sg:province":"Ile de France",
    "sg:tags":[
        "metallurgy",
        "metalworking"
    ],
    "wof:name":"Dupont G Sarl",
    "wof:placetype":"venue"
},
  "geometry": {"coordinates":[3.13013,48.742996],"type":"Point"}
}