{
  "type": "Feature",
  "properties": {
    "addr:full":"7 rue Ren\u00e9 Coty 21000 Dijon Dijon Bourgogne 21000",
    "addr:housenumber":"7",
    "addr:postcode":"21000;21000",
    "addr:street":"Rue Rene\u0301 Coty",
    "iso:country":"FR",
    "sg:address":"7 rue Ren\u00e9 Coty 21000 Dijon",
    "sg:city":"Dijon",
    "sg:classifiers":[
        {
            "category":"Wholesale",
            "subcategory":"Meat",
            "type":"Manufacturing & Wholesale Goods"
        }
    ],
    "sg:phone":"+33 3 80 66 51 43",
    "sg:postcode":"21000",
    "sg:province":"Bourgogne",
    "sg:tags":[
        "sausage",
        "casing",
        "natural"
    ],
    "wof:name":"Les Boyaux Francais S.a.",
    "wof:placetype":"venue"
},
  "geometry": {"coordinates":[5.06411,47.300091],"type":"Point"}
}