{
  "type": "Feature",
  "properties": {
    "iso:country":"FR",
    "sg:address":"Rue Gustave Eiffel 49500 Segre",
    "sg:classifiers":[
        {
            "category":"Professional",
            "subcategory":"Engineering",
            "type":"Services"
        }
    ],
    "sg:phone":"+33 2 41 92 80 87",
    "sg:postcode":"49500",
    "sg:province":"Pays de Loire",
    "sg:tags":[
        "machine",
        "-",
        "mechanical"
    ],
    "wof:name":"Segre Mecanique Precision Sarl",
    "wof:placetype":"venue"
},
  "geometry": {"coordinates":[-0.866512,47.69735],"type":"Point"}
}