{
  "type": "Feature",
  "properties": {
    "addr:full":"3, Rue L\u00e9on Fournier, 38130 Echirolles Rhone-Alpes",
    "addr:housenumber":"3",
    "addr:postcode":"38130",
    "addr:street":"Rue Le\u0301On Fournier",
    "iso:country":"FR",
    "sg:address":"3, Rue L\u00e9on Fournier, 38130 Echirolles",
    "sg:orig_category":"Unclassifiable Establishments",
    "sg:phone":"+33 4 76 23 30 90",
    "sg:province":"Rhone-Alpes",
    "wof:name":"Modloc Mbtp S.a.",
    "wof:placetype":"venue"
},
  "geometry": {"coordinates":[5.710534,45.158314],"type":"Point"}
}