{
  "type": "Feature",
  "properties": {
    "addr:full":"39320 Gigny Franche Comt\u00e9",
    "addr:postcode":"39320",
    "addr:street":"Franche Comte\u0301",
    "iso:country":"FR",
    "sg:address":"39320 Gigny",
    "sg:classifiers":[
        {
            "category":"Manufacturing",
            "subcategory":"Wood Products",
            "type":"Manufacturing & Wholesale Goods"
        }
    ],
    "sg:phone":"+33 3 84 85 43 12",
    "sg:province":"Franche Comt\u00e9",
    "sg:tags":[
        "furniture"
    ],
    "wof:name":"Corsetti Sarl",
    "wof:placetype":"venue"
},
  "geometry": {"coordinates":[5.460248,46.452141],"type":"Point"}
}