{
  "type": "Feature",
  "properties": {
    "addr:full":"B.P. 1233, 45002 Orl\u00e9ans C\u00e9dex 1^^12, Rue du Grenier \u00e0 Sel, 45000 Orl\u00e9ans Orl\u00e9ans Centre 45000",
    "addr:housenumber":"1233;^ 12",
    "addr:postcode":"45002;45000;45000",
    "addr:street":"B.P.;Rue Du Grenier A\u0300 Sel",
    "iso:country":"FR",
    "sg:address":"B.P. 1233, 45002 Orl\u00e9ans C\u00e9dex 1^^12, Rue du Grenier \u00e0 Sel, 45000 Orl\u00e9ans",
    "sg:city":"Orl\u00e9ans",
    "sg:orig_category":"Non-Classified Establishments",
    "sg:phone":"+33 2 38 52 17 73",
    "sg:postcode":"45000",
    "sg:province":"Centre",
    "wof:name":"Energia S.a.",
    "wof:placetype":"venue"
},
  "geometry": {"coordinates":[1.904965,47.901428],"type":"Point"}
}