{
  "type": "Feature",
  "properties": {
    "addr:full":"Av de l'Europe - C.I.T. Roncq Nord Pas-de-Calais 59223",
    "addr:postcode":"59223",
    "addr:street":"Av De L'Europe C.I.T.",
    "iso:country":"FR",
    "sg:address":"Av de l'Europe - C.I.T.",
    "sg:city":"Roncq",
    "sg:orig_category":"Unclassifiable Establishments",
    "sg:phone":"+33 3 20 94 01 36",
    "sg:postcode":"59223",
    "sg:province":"Nord Pas-de-Calais",
    "wof:name":"E.s.e.m. S.a.r.l. - Entreprise De Services Express Et Messageries",
    "wof:placetype":"venue"
},
  "geometry": {"coordinates":[2.481493,48.891426],"type":"Point"}
}