{
  "type": "Feature",
  "properties": {
    "iso:country":"FR",
    "sg:address":"T\u00e9l\u00e9cabine C\u00f4te 2000 38250 Villard De Lans",
    "sg:classifiers":[
        {
            "category":"Sports & Exercise",
            "subcategory":"Sports Center",
            "type":"Entertainment"
        }
    ],
    "sg:phone":"+33 4 76 94 50 50",
    "sg:postcode":"38250",
    "sg:province":"Rhone-Alpes",
    "sg:tags":[
        "machine",
        "engineering",
        "-",
        "mechanical"
    ],
    "wof:name":"Ste D'equipement De Villard Et De Correncon Sa",
    "wof:placetype":"venue"
},
  "geometry": {"coordinates":[5.545742,45.055138],"type":"Point"}
}