{
  "type": "Feature",
  "properties": {
    "addr:full":"53 Rue De Dion Bouton 87021 Limoges Cedex 9 Centre",
    "addr:housenumber":"53;9",
    "addr:postcode":"87021",
    "addr:street":"Rue De Dion Bouton",
    "iso:country":"FR",
    "sg:address":"53 Rue De Dion Bouton 87021 Limoges Cedex 9",
    "sg:classifiers":[
        {
            "category":"Health Services",
            "subcategory":"Medical Lab",
            "type":"Services"
        }
    ],
    "sg:phone":"+33 5 55 04 63 00",
    "sg:province":"Centre",
    "sg:tags":[
        "chemical",
        "pharmaceutical",
        "pharmacy"
    ],
    "wof:name":"Federa",
    "wof:placetype":"venue"
},
  "geometry": {"coordinates":[1.268996,45.882484],"type":"Point"}
}