{
  "type": "Feature",
  "properties": {
    "addr:full":"Les Landes 87400 Champnetery Limousin",
    "addr:postcode":"87400",
    "addr:street":"Landes",
    "iso:country":"FR",
    "sg:address":"Les Landes 87400 Champnetery",
    "sg:orig_category":"Unclassifiable Establishments",
    "sg:phone":"+33 5 55 56 06 60",
    "sg:province":"Limousin",
    "wof:name":"Vergne G\u00e9rard",
    "wof:placetype":"venue"
},
  "geometry": {"coordinates":[1.543018,45.826382],"type":"Point"}
}