{
  "type": "Feature",
  "properties": {
    "addr:full":"Rue de Famards Lesquin Nord Pas-de-Calais 59810",
    "addr:postcode":"59810",
    "addr:street":"Rue De Famards Lesquin Nord",
    "iso:country":"FR",
    "sg:address":"Rue de Famards",
    "sg:city":"Lesquin",
    "sg:orig_category":"Non-Classified Establishments",
    "sg:phone":"+33 3 20 18 02 80",
    "sg:postcode":"59810",
    "sg:province":"Nord Pas-de-Calais",
    "wof:name":"Matman Kon\u00e9cranes S.a.",
    "wof:placetype":"venue"
},
  "geometry": {"coordinates":[3.11003,50.588009],"type":"Point"}
}