{
  "type": "Feature",
  "properties": {
    "addr:full":"B.P. 122, 43100 Brioude^^Av. d'Auvergne, 43100 Brioude Brioude Auvergne 43100",
    "addr:housenumber":"b.p. 122",
    "addr:postcode":"43100;43100;brioude;43100",
    "addr:street":"D'Auvergne",
    "iso:country":"FR",
    "sg:address":"B.P. 122, 43100 Brioude^^Av. d'Auvergne, 43100 Brioude",
    "sg:city":"Brioude",
    "sg:orig_category":"Non-Classified Establishments",
    "sg:phone":"+33 4 71 74 92 51",
    "sg:postcode":"43100",
    "sg:province":"Auvergne",
    "wof:name":"B.t.s. S.a. - Brivadoise De Traitement De Surface",
    "wof:placetype":"venue"
},
  "geometry": {"coordinates":[3.420518,45.311161],"type":"Point"}
}