{
  "type": "Feature",
  "properties": {
    "addr:full":"ZA les L\u00e9g\u00e8res Vimy Nord Pas-de-Calais 62580",
    "addr:postcode":"62580",
    "addr:street":"Za Les Le\u0301Ge\u0300Res Vimy Nord",
    "iso:country":"FR",
    "sg:address":"ZA les L\u00e9g\u00e8res",
    "sg:city":"Vimy",
    "sg:orig_category":"Non-Classified Establishments",
    "sg:phone":"+33 3 21 60 63 00",
    "sg:postcode":"62580",
    "sg:province":"Nord Pas-de-Calais",
    "wof:name":"So.vi.mo. S.a. - Soci\u00e9t\u00e9 Vimoise D'ovoproduits",
    "wof:placetype":"venue"
},
  "geometry": {"coordinates":[2.813412,50.371101],"type":"Point"}
}