{
  "type": "Feature",
  "properties": {
    "iso:country":"FR",
    "sg:address":"10BIS rue Saint-Eus\u00e8be 69425 LYON CEDEX 03",
    "sg:classifiers":[
        {
            "category":"Industrial Area",
            "type":"Public Place"
        }
    ],
    "sg:phone":"+33 4 72 68 15 00",
    "sg:province":"Haute Normandie",
    "sg:tags":[
        "engraving"
    ],
    "wof:name":"Keller-dorian Graveurs Sa",
    "wof:placetype":"venue"
},
  "geometry": {"coordinates":[4.873173,45.757069],"type":"Point"}
}