{
  "type": "Feature",
  "properties": {
    "addr:full":"20 Rue De La Promenade 68040 Ingersheim Ingersheim Alsace 68040",
    "addr:housenumber":"20",
    "addr:postcode":"68040;68040",
    "addr:street":"Rue De La Promenade",
    "iso:country":"FR",
    "sg:address":"20 Rue De La Promenade 68040 Ingersheim",
    "sg:city":"Ingersheim",
    "sg:classifiers":[
        {
            "category":"Professional",
            "subcategory":"Engineering",
            "type":"Services"
        }
    ],
    "sg:phone":"+33 3 89 27 05 63",
    "sg:postcode":"68040",
    "sg:province":"Alsace",
    "sg:tags":[
        "machine",
        "-",
        "mechanical"
    ],
    "wof:name":"Froid Service Joseph Haeffele Et Fils",
    "wof:placetype":"venue"
},
  "geometry": {"coordinates":[7.301067,48.094498],"type":"Point"}
}