{
  "type": "Feature",
  "properties": {
    "iso:country":"FR",
    "sg:address":"2 pl Dossen; Morlaix",
    "sg:classifiers":[
        {
            "category":"Banks & Credit Unions",
            "subcategory":"Bank",
            "type":"Services"
        }
    ],
    "sg:phone":"+33 3398886471",
    "sg:province":"Nord Pas-de-Calais",
    "wof:name":"Banque Populaire De L'ouest",
    "wof:placetype":"venue"
},
  "geometry": {"coordinates":[-3.826259,48.577026],"type":"Point"}
}