{
  "type": "Feature",
  "properties": {
    "iso:country":"FR",
    "sg:address":"38 Rue Voltaire 92800 Puteaux",
    "sg:classifiers":[
        {
            "category":"Professional",
            "subcategory":"Printing & Photocopies",
            "type":"Services"
        }
    ],
    "sg:phone":"+33 1 47 28 00 15",
    "sg:province":"Ile de France",
    "sg:tags":[
        "publishing"
    ],
    "wof:name":"Happy Music",
    "wof:placetype":"venue"
},
  "geometry": {"coordinates":[2.241729,48.879276],"type":"Point"}
}