{
  "type": "Feature",
  "properties": {
    "addr:full":"1 rue Paul Cezanne 91420 Morangis Ile de France 91420",
    "addr:housenumber":"1",
    "addr:postcode":"91420;ile;91420",
    "addr:street":"Rue Paul Cezanne;France",
    "iso:country":"FR",
    "sg:address":"1 rue Paul Cezanne 91420 Morangis",
    "sg:classifiers":[
        {
            "category":"Military Area",
            "subcategory":"Air Force Base",
            "type":"Public Place"
        }
    ],
    "sg:phone":"+33 1 64 54 22 21",
    "sg:postcode":"91420",
    "sg:province":"Ile de France",
    "sg:tags":[
        "window",
        "skylight",
        "dormer"
    ],
    "wof:name":"Ste Velux France Sa",
    "wof:placetype":"venue"
},
  "geometry": {"coordinates":[2.338363,48.692844],"type":"Point"}
}