{
  "type": "Feature",
  "properties": {
    "iso:country":"FR",
    "sg:address":"Rue Des Marchandises 30660 Gallargues Le Montueux",
    "sg:classifiers":[
        {
            "category":"Manufacturing",
            "subcategory":"Paper Products",
            "type":"Manufacturing & Wholesale Goods"
        }
    ],
    "sg:phone":"+33 4 66 35 90 90",
    "sg:province":"Languedoc-Roussillon",
    "sg:tags":[
        "raw",
        "material",
        "-",
        "cardboard"
    ],
    "wof:name":"Smurfit Socar Socar Sud",
    "wof:placetype":"venue"
},
  "geometry": {"coordinates":[4.172856,43.716206],"type":"Point"}
}