{
  "type": "Feature",
  "properties": {
    "addr:full":"Rue Alain Gerbault Vannes Bretagne 56000",
    "addr:postcode":"56000",
    "addr:street":"Rue Alain Gerbault Vannes Bretagne",
    "iso:country":"FR",
    "sg:address":"Rue Alain Gerbault",
    "sg:city":"Vannes",
    "sg:orig_category":"Unclassifiable Establishments",
    "sg:phone":"+33 2 97 47 97 40",
    "sg:postcode":"56000",
    "sg:province":"Bretagne",
    "wof:name":"Risso S.a.",
    "wof:placetype":"venue"
},
  "geometry": {"coordinates":[-2.731383,47.665348],"type":"Point"}
}