{
  "type": "Feature",
  "properties": {
    "iso:country":"FR",
    "sg:address":"15 Rue Du Louvre 75001 Paris",
    "sg:classifiers":[
        {
            "category":"Manufacturing",
            "subcategory":"Building Materials",
            "type":"Manufacturing & Wholesale Goods"
        }
    ],
    "sg:phone":"+33 1 42 36 80 60",
    "sg:postcode":"75001",
    "sg:province":"Ile de France",
    "sg:tags":[
        "glass",
        "ceramic"
    ],
    "wof:name":"Verrerie Des Halles Sarl",
    "wof:placetype":"venue"
},
  "geometry": {"coordinates":[2.341971,48.863522],"type":"Point"}
}