{
  "type": "Feature",
  "properties": {
    "addr:full":"60, Rue de la D\u00e9viation, 93000 Bobigny Ile de France",
    "addr:housenumber":"60",
    "addr:postcode":"93000;ile",
    "addr:street":"Rue De La De\u0301Viation",
    "iso:country":"FR",
    "sg:address":"60, Rue de la D\u00e9viation, 93000 Bobigny",
    "sg:orig_category":"Unclassifiable Establishments",
    "sg:phone":"+33 1 48 45 52 00",
    "sg:province":"Ile de France",
    "wof:name":"A.m.i.c. S.a.r.l.",
    "wof:placetype":"venue"
},
  "geometry": {"coordinates":[2.435535,48.905048],"type":"Point"}
}