{
  "type": "Feature",
  "properties": {
    "iso:country":"FR",
    "sg:address":"12, Rue Ren\u00e9 Cassin - Zone Resurgat 2, 62230 Outreau",
    "sg:orig_category":"Non-Classified Establishments",
    "sg:phone":"+33 3 21 31 52 71",
    "sg:postcode":"62230",
    "sg:province":"Nord Pas-de-Calais",
    "wof:name":"Demouselle S.a.r.l.",
    "wof:placetype":"venue"
},
  "geometry": {"coordinates":[1.596139,50.703754],"type":"Point"}
}