{
  "type": "Feature",
  "properties": {
    "addr:full":"24 rue Jean Jaur\u00e8s 18500 FOECY Fo\u00ebcy Centre 18500",
    "addr:housenumber":"24;foe\u0308cy",
    "addr:postcode":"18500;18500",
    "addr:street":"Rue Jean Jaure\u0300S",
    "iso:country":"FR",
    "sg:address":"24 rue Jean Jaur\u00e8s 18500 FOECY",
    "sg:city":"Fo\u00ebcy",
    "sg:classifiers":[
        {
            "category":"Manufacturing",
            "subcategory":"Tools & Machinery",
            "type":"Manufacturing & Wholesale Goods"
        }
    ],
    "sg:phone":"+33 2 48 51 01 84",
    "sg:postcode":"18500",
    "sg:province":"Centre",
    "sg:tags":[
        "special"
    ],
    "wof:name":"R.t.o. S.a.",
    "wof:placetype":"venue"
},
  "geometry": {"coordinates":[2.152461,47.186127],"type":"Point"}
}