{
  "type": "Feature",
  "properties": {
    "iso:country":"FR",
    "sg:address":"ZI Bois de Leuze",
    "sg:city":"Saint Martin de Crau",
    "sg:orig_category":"Unclassifiable Establishments",
    "sg:phone":"+33 4 90 47 21 52",
    "sg:postcode":"13310",
    "sg:province":"Poitou-Charentes",
    "wof:name":"R\u00e9g\u00e9 Plastique S.a.",
    "wof:placetype":"venue"
},
  "geometry": {"coordinates":[4.809945,43.638184],"type":"Point"}
}