{
  "type": "Feature",
  "properties": {
    "addr:full":"370 R De Bas 88140 La Vacheresse La Rouillie Lorraine",
    "addr:housenumber":"370",
    "addr:postcode":"88140",
    "addr:street":"R De Bas;Vacheresse;Rouillie",
    "iso:country":"FR",
    "sg:address":"370 R De Bas 88140 La Vacheresse La Rouillie",
    "sg:classifiers":[
        {
            "category":"Home & Garden",
            "subcategory":"Furniture",
            "type":"Retail Goods"
        }
    ],
    "sg:phone":"+33 3 29 07 22 12",
    "sg:province":"Lorraine",
    "sg:tags":[
        "wood"
    ],
    "wof:name":"Tournerie Dutheil Sa",
    "wof:placetype":"venue"
},
  "geometry": {"coordinates":[5.787991,48.149231],"type":"Point"}
}