{
  "type": "Feature",
  "properties": {
    "iso:country":"FR",
    "sg:address":"104 Av Jean Jaur\u00e8s 93320 Les Pavillons Sous Bois",
    "sg:classifiers":[
        {
            "category":"Home & Garden",
            "subcategory":"Furniture",
            "type":"Retail Goods"
        }
    ],
    "sg:phone":"+33 1 48 50 05 60",
    "sg:province":"Ile de France",
    "sg:tags":[
        "wood"
    ],
    "wof:name":"Agencement General Du Bois",
    "wof:placetype":"venue"
},
  "geometry": {"coordinates":[2.503384,48.904583],"type":"Point"}
}