{
  "type": "Feature",
  "properties": {
    "iso:country":"FR",
    "sg:address":"12 rue de l'Abbaye 76960 NOTRE DAME DE BONDEVILLE",
    "sg:classifiers":[
        {
            "category":"Sports & Exercise",
            "subcategory":"Climbing Gym",
            "type":"Entertainment"
        }
    ],
    "sg:phone":"+33 2 32 82 38 80",
    "sg:province":"Haute Normandie",
    "sg:tags":[
        "dyer",
        "yarn"
    ],
    "wof:name":"Gresland Sa",
    "wof:placetype":"venue"
},
  "geometry": {"coordinates":[1.044799,49.488457],"type":"Point"}
}