{
  "type": "Feature",
  "properties": {
    "iso:country":"FR",
    "sg:address":"Chef de Baie",
    "sg:city":"La Rochelle C\u00e9dex 1",
    "sg:orig_category":"Non-Classified Establishments",
    "sg:phone":"+33 5 46 41 02 46",
    "sg:postcode":"17045",
    "sg:province":"Poitou-Charentes",
    "wof:name":"Rabateau S.a.r.l.",
    "wof:placetype":"venue"
},
  "geometry": {"coordinates":[-1.199259,46.153996],"type":"Point"}
}