{
  "type": "Feature",
  "properties": {
    "iso:country":"FR",
    "sg:address":"945, Av. Pic de Bertagne - Zone de la Plaine de Jouques, 13420 G\u00e9menos",
    "sg:city":"Plaine",
    "sg:orig_category":"Unclassifiable Establishments",
    "sg:phone":"+33 4 42 32 05 27",
    "sg:postcode":"67420",
    "sg:province":"Alsace",
    "wof:name":"Cejip S\u00e9curit\u00e9 E.u.r.l.",
    "wof:placetype":"venue"
},
  "geometry": {"coordinates":[5.627487,43.294132],"type":"Point"}
}