{
  "type": "Feature",
  "properties": {
    "iso:country":"FR",
    "sg:address":"1, Chemin des Peupliers, 81600 Gaillac",
    "sg:orig_category":"Unclassifiable Establishments",
    "sg:phone":"+33 5 63 57 20 86",
    "sg:province":"Midi Pyr\u00e9n\u00e9es",
    "wof:name":"Sodifri S.a. - Soci\u00e9t\u00e9 De Distribution Frigorifique",
    "wof:placetype":"venue"
},
  "geometry": {"coordinates":[1.899029,43.909428],"type":"Point"}
}