{
  "type": "Feature",
  "properties": {
    "addr:full":"Za Ville 43220 Duni\u00e8res Duni\u00e8res Auvergne 43220",
    "addr:postcode":"43220;dunie\u0300res;43220",
    "addr:street":"Za Ville",
    "iso:country":"FR",
    "sg:address":"Za Ville 43220 Duni\u00e8res",
    "sg:city":"Duni\u00e8res",
    "sg:classifiers":[
        {
            "category":"Home & Garden",
            "subcategory":"Furniture",
            "type":"Retail Goods"
        }
    ],
    "sg:phone":"+33 4 71 61 70 00",
    "sg:postcode":"43220",
    "sg:province":"Auvergne",
    "sg:tags":[
        "wood"
    ],
    "wof:name":"Moulin Sa",
    "wof:placetype":"venue"
},
  "geometry": {"coordinates":[4.343615,45.216541],"type":"Point"}
}