{
  "type": "Feature",
  "properties": {
    "iso:country":"FR",
    "sg:address":"Quartier l'Ibac",
    "sg:city":"Roquebilli\u00e8re",
    "sg:orig_category":"Unclassifiable Establishments",
    "sg:phone":"+33 4 93 03 50 79",
    "sg:postcode":"06450",
    "sg:province":"Provence-Alpes-C\u00f4te d'Azur",
    "wof:name":"Plomberie Corona S.a.r.l.",
    "wof:placetype":"venue"
},
  "geometry": {"coordinates":[7.270738,43.944927],"type":"Point"}
}