{
  "type": "Feature",
  "properties": {
    "addr:full":"Lotissement Plein Soleil 13080 Luynes Champagne",
    "addr:postcode":"13080",
    "addr:street":"Lotissement Plein Soleil",
    "iso:country":"FR",
    "sg:address":"Lotissement Plein Soleil 13080 Luynes",
    "sg:classifiers":[
        {
            "category":"Banks & Credit Unions",
            "subcategory":"Financial Services",
            "type":"Services"
        }
    ],
    "sg:phone":"+33 4 42 16 07 00",
    "sg:province":"Champagne",
    "sg:tags":[
        "banking",
        "insurance",
        "institution",
        "finance"
    ],
    "wof:name":"Sogea Sud Est Snc",
    "wof:placetype":"venue"
},
  "geometry": {"coordinates":[5.41954,43.484966],"type":"Point"}
}