{
  "type": "Feature",
  "properties": {
    "addr:full":"B.P. 6, 38280 Villette d'Anthon^^21, Rue des Emeraudes - ZI, 38280 Villette d'Anthon Rhone-Alpes 38280",
    "addr:housenumber":"6;^ 21",
    "addr:postcode":"38280;^;38280;38280",
    "addr:street":"B.P.;Rue Des Emeraudes Zi;Rhone-Alpes",
    "iso:country":"FR",
    "sg:address":"B.P. 6, 38280 Villette d'Anthon^^21, Rue des Emeraudes - ZI, 38280 Villette d'Anthon",
    "sg:orig_category":"Non-Classified Establishments",
    "sg:phone":"+33 4 72 02 42 77",
    "sg:postcode":"38280",
    "sg:province":"Rhone-Alpes",
    "wof:name":"Lyon D'or 2002 S.a.r.l.",
    "wof:placetype":"venue"
},
  "geometry": {"coordinates":[5.166468,45.791191],"type":"Point"}
}