{
  "type": "Feature",
  "properties": {
    "addr:full":"B.P. 29, 09401 Tarascon sur Ari\u00e8ge C\u00e9dex^^Usine Calypso de Sabart, 09400 Tarascon sur Ari\u00e8ge Midi Pyr\u00e9n\u00e9es 09400",
    "addr:postcode":"09401;09400 tarascon sur;pyre\u0301ne\u0301es 09400",
    "addr:street":"B.P. 29",
    "iso:country":"FR",
    "sg:address":"B.P. 29, 09401 Tarascon sur Ari\u00e8ge C\u00e9dex^^Usine Calypso de Sabart, 09400 Tarascon sur Ari\u00e8ge",
    "sg:orig_category":"Non-Classified Establishments",
    "sg:phone":"+33 5 61 02 40 00",
    "sg:postcode":"09400",
    "sg:province":"Midi Pyr\u00e9n\u00e9es",
    "wof:name":"Aluminium Pechiney S.a.",
    "wof:placetype":"venue"
},
  "geometry": {"coordinates":[1.590551,42.85318],"type":"Point"}
}