{
  "type": "Feature",
  "properties": {
    "addr:full":"2477 rte Grasse; Antibes Rhone-Alpes",
    "addr:housenumber":"2477",
    "addr:street":"Rte Grasse;Rhone-Alpes",
    "iso:country":"FR",
    "sg:address":"2477 rte Grasse; Antibes",
    "sg:classifiers":[
        {
            "category":"Banks & Credit Unions",
            "subcategory":"Bank",
            "type":"Services"
        }
    ],
    "sg:phone":"+33 3393745220",
    "sg:province":"Rhone-Alpes",
    "wof:name":"Lyonnaise De Banque",
    "wof:placetype":"venue"
},
  "geometry": {"coordinates":[7.085101,43.600471],"type":"Point"}
}