{
  "type": "Feature",
  "properties": {
    "addr:full":"24, Rue Dronin, 54000 Nancy Lorraine",
    "addr:housenumber":"24",
    "addr:postcode":"54000",
    "addr:street":"Rue Dronin",
    "iso:country":"FR",
    "sg:address":"24, Rue Dronin, 54000 Nancy",
    "sg:orig_category":"Non-Classified Establishments",
    "sg:phone":"+33 3 83 35 29 40",
    "sg:province":"Lorraine",
    "wof:name":"Grav'est",
    "wof:placetype":"venue"
},
  "geometry": {"coordinates":[6.18901,48.690632],"type":"Point"}
}