{
  "type": "Feature",
  "properties": {
    "addr:full":"89380 Appoigny Appoigny Bourgogne 89380",
    "addr:postcode":"89380;89380",
    "iso:country":"FR",
    "sg:address":"89380 Appoigny",
    "sg:city":"Appoigny",
    "sg:orig_category":"Non-Classified Establishments",
    "sg:phone":"+33 3 86 48 31 89",
    "sg:postcode":"89380",
    "sg:province":"Bourgogne",
    "wof:name":"A\u00e9roport D'auxerre Branches",
    "wof:placetype":"venue"
},
  "geometry": {"coordinates":[3.52076,47.866859],"type":"Point"}
}