{
  "type": "Feature",
  "properties": {
    "iso:country":"FR",
    "sg:address":"32 rue de l'Ermitage 78000 Versailles",
    "sg:classifiers":[
        {
            "category":"Banks & Credit Unions",
            "subcategory":"Investment Brokerage",
            "type":"Services"
        }
    ],
    "sg:phone":"+33 1 39 23 96 70",
    "sg:province":"Ile de France",
    "sg:tags":[
        "pneumatic",
        "apparatus"
    ],
    "wof:name":"P\u00e9trom\u00e9talic Sa",
    "wof:placetype":"venue"
},
  "geometry": {"coordinates":[2.121336,48.816402],"type":"Point"}
}