{
  "type": "Feature",
  "properties": {
    "addr:full":"7 Grande Rue Verte 78610 Le Perray En Yvelines Ile de France 78610",
    "addr:housenumber":"7",
    "addr:postcode":"78610;78610",
    "addr:street":"Grande Rue Verte",
    "iso:country":"FR",
    "sg:address":"7 Grande Rue Verte 78610 Le Perray En Yvelines",
    "sg:classifiers":[
        {
            "category":"Autos & Motor Vehicles",
            "subcategory":"Automobile Sales",
            "type":"Retail Goods"
        }
    ],
    "sg:phone":"+33 1 34 84 90 24",
    "sg:postcode":"78610",
    "sg:province":"Ile de France",
    "sg:tags":[
        "equipment",
        "motor-cars",
        "transport"
    ],
    "wof:name":"Almatic Sa",
    "wof:placetype":"venue"
},
  "geometry": {"coordinates":[1.842248,48.689419],"type":"Point"}
}