{
  "type": "Feature",
  "properties": {
    "addr:full":"12 Rue Bl\u00e9riot 49300 Cholet Pays de Loire 49300",
    "addr:housenumber":"12",
    "addr:postcode":"49300;49300",
    "addr:street":"Rue Ble\u0301Riot",
    "iso:country":"FR",
    "sg:address":"12 Rue Bl\u00e9riot 49300 Cholet",
    "sg:classifiers":[
        {
            "category":"Utilities",
            "type":"Services"
        }
    ],
    "sg:phone":"+33 2 41 29 14 59",
    "sg:postcode":"49300",
    "sg:province":"Pays de Loire",
    "sg:tags":[
        "road",
        "transport",
        "air"
    ],
    "wof:name":"Dusolier Sa",
    "wof:placetype":"venue"
},
  "geometry": {"coordinates":[-0.87243,47.070641],"type":"Point"}
}