{
  "type": "Feature",
  "properties": {
    "iso:country":"FR",
    "sg:address":"11, Rue du Pied Sec, 72100 Le Mans",
    "sg:orig_category":"Non-Classified Establishments",
    "sg:phone":"+33 2 43 16 04 70",
    "sg:province":"Pays de Loire",
    "wof:name":"Serma Industrie S.a.s.",
    "wof:placetype":"venue"
},
  "geometry": {"coordinates":[0.206161,47.982872],"type":"Point"}
}