{
  "type": "Feature",
  "properties": {
    "iso:country":"FR",
    "sg:address":"6, Av. Charles de Gaulle, 78150 Le Chesnay",
    "sg:orig_category":"Non-Classified Establishments",
    "sg:phone":"+33 1 39 55 31 54",
    "sg:province":"Ile de France",
    "wof:name":"J.p.a. Engineering S.a.r.l.",
    "wof:placetype":"venue"
},
  "geometry": {"coordinates":[2.115254,48.829239],"type":"Point"}
}