{
  "type": "Feature",
  "properties": {
    "addr:full":"B.P. 21, 59331 Tourcoing C\u00e9dex^^11, Rue de Ch\u00e2lons, 59200 Tourcoing Nord Pas-de-Calais",
    "addr:postcode":"59331;59200",
    "addr:street":"B.P. 21;Rue De Cha\u0302Lons",
    "iso:country":"FR",
    "sg:address":"B.P. 21, 59331 Tourcoing C\u00e9dex^^11, Rue de Ch\u00e2lons, 59200 Tourcoing",
    "sg:orig_category":"Non-Classified Establishments",
    "sg:phone":"+33 3 20 26 61 27",
    "sg:province":"Nord Pas-de-Calais",
    "wof:name":"Worex S.n.c.",
    "wof:placetype":"venue"
},
  "geometry": {"coordinates":[3.159375,50.722389],"type":"Point"}
}