{
  "type": "Feature",
  "properties": {
    "addr:full":"97 Rue Monge Paris Ile de France 75005",
    "addr:housenumber":"97",
    "addr:postcode":"75005",
    "addr:street":"Rue Monge",
    "iso:country":"FR",
    "sg:address":"97 Rue Monge",
    "sg:city":"Paris",
    "sg:classifiers":[
        {
            "category":"Banks & Credit Unions",
            "subcategory":"Financial Services",
            "type":"Services"
        }
    ],
    "sg:phone":"+33 1 43 36 76 00",
    "sg:postcode":"75005",
    "sg:province":"Ile de France",
    "sg:tags":[
        "banking",
        "finance",
        "insurance"
    ],
    "wof:name":"A C O J F Mechin Assistance Conseil Organisation Sa",
    "wof:placetype":"venue"
},
  "geometry": {"coordinates":[2.352115,48.841148],"type":"Point"}
}