{
  "type": "Feature",
  "properties": {
    "addr:full":"15, Rte de Limoges, 23300 La Souterraine Limousin",
    "addr:housenumber":"15",
    "addr:postcode":"23300",
    "addr:street":"Rte De Limoges",
    "iso:country":"FR",
    "sg:address":"15, Rte de Limoges, 23300 La Souterraine",
    "sg:orig_category":"Unclassifiable Establishments",
    "sg:phone":"+33 5 55 63 72 45",
    "sg:province":"Limousin",
    "wof:name":"Carrefour Du Bois Limousin S.a.r.l.",
    "wof:placetype":"venue"
},
  "geometry": {"coordinates":[1.483282,46.233696],"type":"Point"}
}