{
  "type": "Feature",
  "properties": {
    "addr:full":"Av. Louis Rossel - ZI de la Pointe du Diable Plouzan\u00e9 Bretagne 29280",
    "addr:postcode":"29280",
    "addr:street":"Av. Louis Rossel Zi De La Pointe Du Diable;Bretagne",
    "iso:country":"FR",
    "sg:address":"Av. Louis Rossel - ZI de la Pointe du Diable",
    "sg:city":"Plouzan\u00e9",
    "sg:orig_category":"Non-Classified Establishments",
    "sg:phone":"+33 2 98 49 25 50",
    "sg:postcode":"29280",
    "sg:province":"Bretagne",
    "wof:name":"Brest T\u00f4lerie S.a.",
    "wof:placetype":"venue"
},
  "geometry": {"coordinates":[-4.622545,48.38055],"type":"Point"}
}