{
  "type": "Feature",
  "properties": {
    "addr:full":"Route De Nantes 85000 La Roche Sur Yon Pays de Loire 85000",
    "addr:postcode":"85000;85000",
    "addr:street":"Route De Nantes;Roche;Yon",
    "iso:country":"FR",
    "sg:address":"Route De Nantes 85000 La Roche Sur Yon",
    "sg:classifiers":[
        {
            "category":"Autos & Motor Vehicles",
            "subcategory":"Automobile Sales",
            "type":"Retail Goods"
        }
    ],
    "sg:phone":"+33 2 51 37 36 27",
    "sg:postcode":"85000",
    "sg:province":"Pays de Loire",
    "sg:tags":[
        "equipment",
        "motor-cars",
        "transport"
    ],
    "wof:name":"Garage Napoleon Sa",
    "wof:placetype":"venue"
},
  "geometry": {"coordinates":[-1.429674,46.702045],"type":"Point"}
}