{
  "type": "Feature",
  "properties": {
    "addr:full":"18 bis, Rue de Villiers, 92200 Levallois Perret Ile de France",
    "addr:housenumber":"18 bis",
    "addr:postcode":"92200;ile",
    "addr:street":"Rue De Villiers",
    "iso:country":"FR",
    "sg:address":"18 bis, Rue de Villiers, 92200 Levallois Perret",
    "sg:orig_category":"Unclassifiable Establishments",
    "sg:phone":"+33 1 46 39 49 00",
    "sg:province":"Ile de France",
    "wof:name":"C\u00e9rium S.a.r.l.",
    "wof:placetype":"venue"
},
  "geometry": {"coordinates":[2.2823,48.887897],"type":"Point"}
}