{
  "type": "Feature",
  "properties": {
    "addr:full":"1 bis, Rue Maysonnabe, 64200 Biarritz Biarritz Aquitaine 64200",
    "addr:housenumber":"1 bis",
    "addr:postcode":"64200;64200",
    "addr:street":"Rue Maysonnabe",
    "iso:country":"FR",
    "sg:address":"1 bis, Rue Maysonnabe, 64200 Biarritz",
    "sg:city":"Biarritz",
    "sg:orig_category":"Non-Classified Establishments",
    "sg:phone":"+33 5 59 23 11 70",
    "sg:postcode":"64200",
    "sg:province":"Aquitaine",
    "wof:name":"T.b.b. S.a.r.l. - Teinturerie Blanchisserie Biarrotte",
    "wof:placetype":"venue"
},
  "geometry": {"coordinates":[-1.546668,43.469002],"type":"Point"}
}