{
  "type": "Feature",
  "properties": {
    "addr:full":"Z I D En Toulze 81580 CAMBOUNET SUR LE SOR Midi Pyr\u00e9n\u00e9es",
    "addr:postcode":"81580",
    "addr:street":"Z I D;Cambounet Sur Le Sor Midi",
    "iso:country":"FR",
    "sg:address":"Z I D En Toulze 81580 CAMBOUNET SUR LE SOR",
    "sg:classifiers":[
        {
            "category":"Landmark",
            "subcategory":"Monument",
            "type":"Public Place"
        }
    ],
    "sg:phone":"+33 5 63 74 81 31",
    "sg:province":"Midi Pyr\u00e9n\u00e9es",
    "sg:tags":[
        "sepulchral"
    ],
    "wof:name":"Claude Dourel Sas",
    "wof:placetype":"venue"
},
  "geometry": {"coordinates":[2.11659,43.55587],"type":"Point"}
}