{
  "type": "Feature",
  "properties": {
    "iso:country":"FR",
    "sg:address":"30, Av. Mirabeau, 13220 Ch\u00e2teauneuf les Martigues",
    "sg:city":"Artigue",
    "sg:orig_category":"Unclassifiable Establishments",
    "sg:phone":"+33 4 42 81 08 72",
    "sg:postcode":"31110",
    "sg:province":"Midi Pyr\u00e9n\u00e9es",
    "wof:name":"Poujaud S.a.",
    "wof:placetype":"venue"
},
  "geometry": {"coordinates":[5.109292,43.398243],"type":"Point"}
}