{
  "type": "Feature",
  "properties": {
    "iso:country":"FR",
    "sg:address":"Rte de Plouray",
    "sg:city":"Saint Tugdual",
    "sg:orig_category":"Unclassifiable Establishments",
    "sg:phone":"+33 2 97 39 41 02",
    "sg:postcode":"56540",
    "sg:province":"Bretagne",
    "wof:name":"Biscuits Revolt S.a.",
    "wof:placetype":"venue"
},
  "geometry": {"coordinates":[-3.319536,48.007076],"type":"Point"}
}