{
  "type": "Feature",
  "properties": {
    "iso:country":"FR",
    "sg:address":"B.P. 149, 88304 Neufch\u00e2teau C\u00e9dex^^76, Av de la Division Leclerc, 88300 Neufch\u00e2teau",
    "sg:orig_category":"Non-Classified Establishments",
    "sg:phone":"+33 3 29 94 15 86",
    "sg:province":"Lorraine",
    "wof:name":"Sadap S.a.",
    "wof:placetype":"venue"
},
  "geometry": {"coordinates":[5.69254,48.358501],"type":"Point"}
}