{
  "type": "Feature",
  "properties": {
    "iso:country":"FR",
    "sg:address":"4 faubourg Remiremont 88204 Remiremont",
    "sg:classifiers":[
        {
            "category":"Professional",
            "subcategory":"Advertising",
            "type":"Services"
        }
    ],
    "sg:phone":"+33 3 29 62 52 72",
    "sg:province":"Centre",
    "sg:tags":[
        "boxes",
        "cardboard",
        "individual"
    ],
    "wof:name":"Gr\u00e9goire Sa",
    "wof:placetype":"venue"
},
  "geometry": {"coordinates":[6.589865,48.017303],"type":"Point"}
}