{
  "type": "Feature",
  "properties": {
    "iso:country":"FR",
    "sg:address":"1, Rue d'Illiers, 45000 Orl\u00e9ans",
    "sg:city":"Orl\u00e9ans",
    "sg:orig_category":"Non-Classified Establishments",
    "sg:phone":"+33 2 38 81 11 55",
    "sg:postcode":"45000",
    "sg:province":"Centre",
    "wof:name":"Club Med Voyages",
    "wof:placetype":"venue"
},
  "geometry": {"coordinates":[1.900093,47.902557],"type":"Point"}
}