{
  "type": "Feature",
  "properties": {
    "addr:full":"1 bis, Chemin des Gorges, 69570 Dardilly Rhone-Alpes",
    "addr:housenumber":"1 bis",
    "addr:postcode":"69570",
    "addr:street":"Chemin Des Gorges",
    "iso:country":"FR",
    "sg:address":"1 bis, Chemin des Gorges, 69570 Dardilly",
    "sg:orig_category":"Unclassifiable Establishments",
    "sg:phone":"+33 4 72 52 30 20",
    "sg:province":"Rhone-Alpes",
    "wof:name":"Iss Abilis S.a.s.",
    "wof:placetype":"venue"
},
  "geometry": {"coordinates":[4.76499,45.807533],"type":"Point"}
}