{
  "type": "Feature",
  "properties": {
    "addr:full":"4, Rue Paul Langevin - ZA Paul Bert, 62300 Lens Nord Pas-de-Calais",
    "addr:housenumber":"4",
    "addr:postcode":"62300",
    "addr:street":"Rue Paul Langevin Za Paul Bert",
    "iso:country":"FR",
    "sg:address":"4, Rue Paul Langevin - ZA Paul Bert, 62300 Lens",
    "sg:orig_category":"Non-Classified Establishments",
    "sg:phone":"+33 3 21 43 26 26",
    "sg:province":"Nord Pas-de-Calais",
    "wof:name":"S.g.e.e. S.a. - Soci\u00e9t\u00e9 G\u00e9n\u00e9rale D'equipement Electrique",
    "wof:placetype":"venue"
},
  "geometry": {"coordinates":[2.83296,50.42934],"type":"Point"}
}