{
  "type": "Feature",
  "properties": {
    "addr:full":"115, Av. Charles de Gaulle, 81600 Gaillac Midi Pyr\u00e9n\u00e9es 81600",
    "addr:postcode":"81600;81600",
    "addr:street":"115 Av. Charles De Gaulle",
    "iso:country":"FR",
    "sg:address":"115, Av. Charles de Gaulle, 81600 Gaillac",
    "sg:orig_category":"Non-Classified Establishments",
    "sg:phone":"+33 5 63 81 21 71",
    "sg:postcode":"81600",
    "sg:province":"Midi Pyr\u00e9n\u00e9es",
    "wof:name":"Etablissements Jacques Vigne S.a.",
    "wof:placetype":"venue"
},
  "geometry": {"coordinates":[1.91727,43.908821],"type":"Point"}
}