{
  "type": "Feature",
  "properties": {
    "addr:full":"ZI Jules Verne BP 55 70400 H\u00e9ricourt Franche Comt\u00e9 70400",
    "addr:postcode":"70400;70400",
    "addr:street":"Jules;Bp 55;Franche Comte\u0301",
    "iso:country":"FR",
    "sg:address":"ZI",
    "sg:city":"Jules Verne BP 55 70400 H\u00e9ricourt",
    "sg:classifiers":[
        {
            "category":"Manufacturing",
            "subcategory":"Metals",
            "type":"Manufacturing & Wholesale Goods"
        }
    ],
    "sg:phone":"+33 3 84 56 88 06",
    "sg:postcode":"70400",
    "sg:province":"Franche Comt\u00e9",
    "sg:tags":[
        "metallurgy",
        "metalworking",
        "processing"
    ],
    "wof:name":"Devillers Oxycoupage",
    "wof:placetype":"venue"
},
  "geometry": {"coordinates":[6.754775,47.574718],"type":"Point"}
}