{
  "type": "Feature",
  "properties": {
    "addr:full":"3, Rue Jacquard - ZI de Tr\u00e9pillot, 25000 Besan\u00e7on Franche Comt\u00e9 25000",
    "addr:housenumber":"3",
    "addr:postcode":"25000;25000",
    "addr:street":"Rue Jacquard Zi De Tre\u0301Pillot;Franche Comte\u0301",
    "iso:country":"FR",
    "sg:address":"3, Rue Jacquard - ZI de Tr\u00e9pillot, 25000 Besan\u00e7on",
    "sg:orig_category":"Non-Classified Establishments",
    "sg:phone":"+33 3 81 47 04 04",
    "sg:postcode":"25000",
    "sg:province":"Franche Comt\u00e9",
    "wof:name":"Afodis S.a.r.l.",
    "wof:placetype":"venue"
},
  "geometry": {"coordinates":[6.025686,47.242317],"type":"Point"}
}