{
  "type": "Feature",
  "properties": {
    "iso:country":"FR",
    "sg:address":"26, Rue des Osiers - ZI des Marais, 78310 Coigni\u00e8res",
    "sg:orig_category":"Unclassifiable Establishments",
    "sg:phone":"+33 1 30 49 26 26",
    "sg:province":"Ile de France",
    "wof:name":"Diabolo Manus S.n.c.",
    "wof:placetype":"venue"
},
  "geometry": {"coordinates":[1.944855,48.761749],"type":"Point"}
}