{
  "type": "Feature",
  "properties": {
    "iso:country":"FR",
    "sg:address":"325, Rte des Colloges, 74300 Magland",
    "sg:orig_category":"Unclassifiable Establishments",
    "sg:phone":"+33 4 50 58 21 21",
    "sg:postcode":"74300",
    "sg:province":"Rhone-Alpes",
    "wof:name":"Delem S.a.r.l.",
    "wof:placetype":"venue"
},
  "geometry": {"coordinates":[6.631491,45.991371],"type":"Point"}
}