{
  "type": "Feature",
  "properties": {
    "iso:country":"FR",
    "sg:address":"16 rue Amp\u00e8re 95300 Pontoise",
    "sg:classifiers":[
        {
            "category":"Building & Trades",
            "subcategory":"Plumbing",
            "type":"Services"
        }
    ],
    "sg:phone":"+33 1 34 20 01 37",
    "sg:postcode":"95300",
    "sg:province":"Ile de France",
    "sg:tags":[
        "dehumidification"
    ],
    "wof:name":"Cbk S.a.r.l.",
    "wof:placetype":"venue"
},
  "geometry": {"coordinates":[2.075141,49.046612],"type":"Point"}
}