{
  "type": "Feature",
  "properties": {
    "iso:country":"FR",
    "sg:address":"Zi Rue Des Amusoirs 62350 St Venant",
    "sg:classifiers":[
        {
            "category":"Home & Garden",
            "subcategory":"Furniture",
            "type":"Retail Goods"
        }
    ],
    "sg:phone":"+33 3 21 63 17 77",
    "sg:postcode":"62350",
    "sg:province":"Nord Pas-de-Calais",
    "sg:tags":[
        "household",
        "wood"
    ],
    "wof:name":"Fabec",
    "wof:placetype":"venue"
},
  "geometry": {"coordinates":[2.55135,50.623798],"type":"Point"}
}