{
  "type": "Feature",
  "properties": {
    "iso:country":"FR",
    "sg:address":"Quai du Mas d'Hours",
    "sg:city":"Al\u00e8s",
    "sg:orig_category":"Non-Classified Establishments",
    "sg:phone":"+33 4 66 86 34 62",
    "sg:postcode":"30100",
    "sg:province":"Languedoc-Roussillon",
    "wof:name":"Somatran S.a.",
    "wof:placetype":"venue"
},
  "geometry": {"coordinates":[4.093499,44.120155],"type":"Point"}
}