{
  "type": "Feature",
  "properties": {
    "iso:country":"FR",
    "sg:address":"101, Rue Jean-Jaur\u00e8s, 80520 Woincourt",
    "sg:orig_category":"Unclassifiable Establishments",
    "sg:phone":"+33 3 22 30 63 30",
    "sg:province":"Picardie",
    "wof:name":"M.o.p.m. S.a.r.l.",
    "wof:placetype":"venue"
},
  "geometry": {"coordinates":[1.53597,50.060684],"type":"Point"}
}