{
  "type": "Feature",
  "properties": {
    "addr:full":"67, Mail Barth\u00e9l\u00e9my Thimonnier, 77185 Lognes Ile de France",
    "addr:housenumber":"67",
    "addr:postcode":"77185;ile",
    "addr:street":"Mail Barthe\u0301Le\u0301My Thimonnier",
    "iso:country":"FR",
    "sg:address":"67, Mail Barth\u00e9l\u00e9my Thimonnier, 77185 Lognes",
    "sg:orig_category":"Unclassifiable Establishments",
    "sg:phone":"+33 1 60 17 09 50",
    "sg:province":"Ile de France",
    "wof:name":"Sprimag France S.a.r.l.",
    "wof:placetype":"venue"
},
  "geometry": {"coordinates":[2.628189,48.839626],"type":"Point"}
}