{
  "type": "Feature",
  "properties": {
    "iso:country":"FR",
    "sg:address":"B.P. 14, 38430 Moirans^^Av. Joseph Trabbia - ZA de la Pichati\u00e8re, 38430 Moirans",
    "sg:orig_category":"Non-Classified Establishments",
    "sg:phone":"+33 4 76 35 55 97",
    "sg:postcode":"38430",
    "sg:province":"Rhone-Alpes",
    "wof:name":"Diplex S.a.r.l.",
    "wof:placetype":"venue"
},
  "geometry": {"coordinates":[5.554805,45.327175],"type":"Point"}
}