{
  "type": "Feature",
  "properties": {
    "iso:country":"FR",
    "sg:address":"1 Rue Mal Joffre 54150 Briey",
    "sg:classifiers":[
        {
            "category":"Professional",
            "subcategory":"Printing & Photocopies",
            "type":"Services"
        }
    ],
    "sg:phone":"+33 3 82 47 11 30",
    "sg:province":"Lorraine",
    "sg:tags":[
        "publishing"
    ],
    "wof:name":"Le Republicain Lorrain (rl)",
    "wof:placetype":"venue"
},
  "geometry": {"coordinates":[5.937522,49.248146],"type":"Point"}
}