{
  "type": "Feature",
  "properties": {
    "iso:country":"FR",
    "sg:address":"10, Rue Georges Besse - ZI Br\u00e9zet Est, 63017 Clermont Ferrand C\u00e9dex 2",
    "sg:orig_category":"Non-Classified Establishments",
    "sg:phone":"+33 4 73 98 82 82",
    "sg:province":"Auvergne",
    "wof:name":"Centre Roulement S.a.",
    "wof:placetype":"venue"
},
  "geometry": {"coordinates":[3.08515,45.778461],"type":"Point"}
}