{
  "type": "Feature",
  "properties": {
    "addr:full":"80, Av. des Buttes de Co\u00ebsnes - B\u00e2t. Gallium, 35700 Rennes Rennes Bretagne 35700",
    "addr:housenumber":"ba\u0302t",
    "addr:postcode":"35700;35700",
    "addr:street":"80 Av. Des Buttes De Coe\u0308Snes",
    "iso:country":"FR",
    "sg:address":"80, Av. des Buttes de Co\u00ebsnes - B\u00e2t. Gallium, 35700 Rennes",
    "sg:city":"Rennes",
    "sg:orig_category":"Non-Classified Establishments",
    "sg:phone":"+33 2 23 25 03 30",
    "sg:postcode":"35700",
    "sg:province":"Bretagne",
    "wof:name":"Quartz Data T\u00e9l\u00e9com S.a.",
    "wof:placetype":"venue"
},
  "geometry": {"coordinates":[-1.632003,48.125603],"type":"Point"}
}