{
  "type": "Feature",
  "properties": {
    "iso:country":"FR",
    "sg:address":"B.P. 69",
    "sg:city":"Boissy Saint L\u00e9ger C\u00e9dex",
    "sg:orig_category":"Non-Classified Establishments",
    "sg:phone":"+33 825 88 80 01",
    "sg:postcode":"94472",
    "sg:province":"Poitou-Charentes",
    "wof:name":"Endress & Hauser S.a.",
    "wof:placetype":"venue"
},
  "geometry": {"coordinates":[2.510725,48.75145],"type":"Point"}
}