{
  "type": "Feature",
  "properties": {
    "addr:full":"29, Rue de la For\u00eat, 54350 Mont Saint Martin Lorraine",
    "addr:housenumber":"29",
    "addr:postcode":"54350",
    "addr:street":"Rue De La Fore\u0302T;Martin",
    "iso:country":"FR",
    "sg:address":"29, Rue de la For\u00eat, 54350 Mont Saint Martin",
    "sg:orig_category":"Non-Classified Establishments",
    "sg:phone":"+33 3 82 25 65 59",
    "sg:province":"Lorraine",
    "wof:name":"Eur-imprim S.a.r.l.",
    "wof:placetype":"venue"
},
  "geometry": {"coordinates":[5.763363,49.534588],"type":"Point"}
}