{
  "type": "Feature",
  "properties": {
    "addr:full":"Pont Palais 42110 Feurs Rhone-Alpes 42110",
    "addr:postcode":"42110;42110",
    "iso:country":"FR",
    "sg:address":"Pont Palais 42110 Feurs",
    "sg:classifiers":[
        {
            "category":"Professional",
            "subcategory":"Business Services",
            "type":"Services"
        }
    ],
    "sg:phone":"+33 4 77 26 21 14",
    "sg:postcode":"42110",
    "sg:province":"Rhone-Alpes",
    "sg:tags":[
        "body",
        "advice"
    ],
    "wof:name":"Mjc Maison De La Culture Ass",
    "wof:placetype":"venue"
},
  "geometry": {"coordinates":[4.223765,45.744545],"type":"Point"}
}