{
  "type": "Feature",
  "properties": {
    "iso:country":"FR",
    "sg:address":"Le Ch\u00e2teau Fere 02130 F\u00e8re En Tardenois",
    "sg:classifiers":[
        {
            "category":"Travel",
            "subcategory":"Hotels & Motels",
            "type":"Entertainment"
        }
    ],
    "sg:phone":"+33 3 23 82 21 13",
    "sg:postcode":"02130",
    "sg:province":"Picardie",
    "sg:tags":[
        "hotels",
        "business",
        "restaurant"
    ],
    "wof:name":"Hostellerie Du Chateau De Fere Sa",
    "wof:placetype":"venue"
},
  "geometry": {"coordinates":[3.530253,49.223614],"type":"Point"}
}