{
  "type": "Feature",
  "properties": {
    "addr:full":"5 rue Paul Louis Courier 77100 Meaux Ile de France 77100",
    "addr:housenumber":"5",
    "addr:postcode":"77100;ile;77100",
    "addr:street":"Rue Paul Louis Courier;France",
    "iso:country":"FR",
    "sg:address":"5 rue Paul Louis Courier 77100 Meaux",
    "sg:classifiers":[
        {
            "category":"Professional",
            "subcategory":"Engineering",
            "type":"Services"
        }
    ],
    "sg:phone":"+33 1 60 09 01 72",
    "sg:postcode":"77100",
    "sg:province":"Ile de France",
    "sg:tags":[
        "machine",
        "steel"
    ],
    "wof:name":"Ste Commerciale Appareil Mecaniques Sarl",
    "wof:placetype":"venue"
},
  "geometry": {"coordinates":[2.90142,48.949982],"type":"Point"}
}