{
  "type": "Feature",
  "properties": {
    "iso:country":"FR",
    "sg:address":"B.P. 25, 01400 Chatillon sur Chalaronne C\u00e9dex^^Av. Foch, 01400 Chatillon sur Chalaronne",
    "sg:orig_category":"Non-Classified Establishments",
    "sg:phone":"+33 4 74 45 54 42",
    "sg:province":"Rhone-Alpes",
    "wof:name":"Solvay Pharma S.a.",
    "wof:placetype":"venue"
},
  "geometry": {"coordinates":[4.99054,46.134781],"type":"Point"}
}