{
  "type": "Feature",
  "properties": {
    "addr:full":"Rue du Coteau - ZI Ouest Heillecourt Lorraine 54180",
    "addr:postcode":"54180",
    "addr:street":"Rue Du Coteau Zi Ouest",
    "iso:country":"FR",
    "sg:address":"Rue du Coteau - ZI Ouest",
    "sg:city":"Heillecourt",
    "sg:orig_category":"Non-Classified Establishments",
    "sg:phone":"+33 3 83 56 16 83",
    "sg:postcode":"54180",
    "sg:province":"Lorraine",
    "wof:name":"Loxam S.a.",
    "wof:placetype":"venue"
},
  "geometry": {"coordinates":[6.194192,48.653137],"type":"Point"}
}