{
  "type": "Feature",
  "properties": {
    "iso:country":"FR",
    "sg:address":"582 Avenue Des Paluds Zi Les Paluds Lot 168 13400 Aubagne",
    "sg:classifiers":[
        {
            "category":"Home & Garden",
            "subcategory":"Furniture",
            "type":"Retail Goods"
        }
    ],
    "sg:phone":"+33 4 42 70 95 65",
    "sg:tags":[
        "household",
        "wood"
    ],
    "wof:name":"Santons D'art De Provence",
    "wof:placetype":"venue"
},
  "geometry": {"coordinates":[5.5687,43.292141],"type":"Point"}
}