{
  "type": "Feature",
  "properties": {
    "addr:full":"74460 MARNAZ Rhone-Alpes 74460",
    "addr:postcode":"74460;74460",
    "addr:street":"Rhone-Alpes",
    "iso:country":"FR",
    "sg:address":"74460 MARNAZ",
    "sg:classifiers":[
        {
            "category":"Building & Trades",
            "subcategory":"Construction",
            "type":"Services"
        }
    ],
    "sg:phone":"+33 4 50 89 38 00",
    "sg:postcode":"74460",
    "sg:province":"Rhone-Alpes",
    "sg:tags":[
        "turning",
        "vertical"
    ],
    "wof:name":"Bontaz Centre Sa",
    "wof:placetype":"venue"
},
  "geometry": {"coordinates":[6.52688,46.06094],"type":"Point"}
}