{
  "type": "Feature",
  "properties": {
    "iso:country":"FR",
    "sg:address":"2 Chem Du Bois St Paul BP 899 25025 Besan\u00e7on Cedex",
    "sg:city":"Besan\u00e7on",
    "sg:classifiers":[
        {
            "category":"Professional",
            "subcategory":"Business Services",
            "type":"Services"
        }
    ],
    "sg:phone":"+33 3 81 61 34 34",
    "sg:postcode":"25000",
    "sg:province":"Franche Comt\u00e9",
    "sg:tags":[
        "training",
        "advice"
    ],
    "wof:name":"College Clairs Soleils",
    "wof:placetype":"venue"
},
  "geometry": {"coordinates":[6.05893,47.252171],"type":"Point"}
}