{
  "type": "Feature",
  "properties": {
    "iso:country":"FR",
    "sg:address":"112 Av Daumesnil 75012 Paris",
    "sg:classifiers":[
        {
            "category":"Professional",
            "subcategory":"Engineering",
            "type":"Services"
        }
    ],
    "sg:phone":"+33 1 44 74 37 37",
    "sg:postcode":"75012",
    "sg:province":"Ile de France",
    "sg:tags":[
        "machine",
        "-",
        "mechanical"
    ],
    "wof:name":"Loueurs De France Btp Sa",
    "wof:placetype":"venue"
},
  "geometry": {"coordinates":[2.384651,48.842609],"type":"Point"}
}