{
  "type": "Feature",
  "properties": {
    "iso:country":"FR",
    "sg:address":"ZA de la Gu\u00e9rini\u00e8re",
    "sg:city":"La Gu\u00e9rini\u00e8re",
    "sg:orig_category":"Unclassifiable Establishments",
    "sg:phone":"+33 2 51 39 85 19",
    "sg:postcode":"85680",
    "sg:province":"Pays de Loire",
    "wof:name":"J.k. S.a.",
    "wof:placetype":"venue"
},
  "geometry": {"coordinates":[-2.237751,46.967464],"type":"Point"}
}