{
  "type": "Feature",
  "properties": {
    "iso:country":"FR",
    "sg:address":"B.P. 13, 76133 Epouville^^RD 32, 76133 Epouville",
    "sg:orig_category":"Non-Classified Establishments",
    "sg:phone":"+33 2 35 30 26 35",
    "sg:province":"Haute Normandie",
    "wof:name":"Martin - Calais S.a.",
    "wof:placetype":"venue"
},
  "geometry": {"coordinates":[0.2558,49.56546],"type":"Point"}
}