{
  "type": "Feature",
  "properties": {
    "addr:full":"70/76, Rue Jean Jacques Rousseau, 78800 Houilles Ile de France 78800",
    "addr:housenumber":"70 / 76",
    "addr:postcode":"78800;ile;78800",
    "addr:street":"Rue Jean Jacques Rousseau;France",
    "iso:country":"FR",
    "sg:address":"70/76, Rue Jean Jacques Rousseau, 78800 Houilles",
    "sg:orig_category":"Non-Classified Establishments",
    "sg:phone":"+33 1 39 68 19 67",
    "sg:postcode":"78800",
    "sg:province":"Ile de France",
    "wof:name":"Cahors S.a.",
    "wof:placetype":"venue"
},
  "geometry": {"coordinates":[2.182606,48.917774],"type":"Point"}
}