{
  "type": "Feature",
  "properties": {
    "addr:full":"Rte D'Epinal 70210 Vauvillers Franche Comt\u00e9 70210",
    "addr:postcode":"70210;70210",
    "addr:street":"Rte D'Epinal;Franche Comte\u0301",
    "iso:country":"FR",
    "sg:address":"Rte D'Epinal 70210 Vauvillers",
    "sg:classifiers":[
        {
            "category":"Farming",
            "subcategory":"Farm & Veterinary Services",
            "type":"Manufacturing & Wholesale Goods"
        }
    ],
    "sg:phone":"+33 3 84 92 88 48",
    "sg:postcode":"70210",
    "sg:province":"Franche Comt\u00e9",
    "sg:tags":[
        "food",
        "product",
        "breeding",
        "animal",
        "related"
    ],
    "wof:name":"Sarl Cofathim",
    "wof:placetype":"venue"
},
  "geometry": {"coordinates":[6.128354,47.957848],"type":"Point"}
}