{
  "type": "Feature",
  "properties": {
    "addr:full":"Minist\u00e8re Saint Augustin-P\u00f4le 19 Nice C\u00e9dex 3 Basse Normandie 06296",
    "addr:housenumber":"19;3",
    "addr:postcode":"06296",
    "addr:street":"Ce\u0301Dex",
    "iso:country":"FR",
    "sg:address":"Minist\u00e8re Saint Augustin-P\u00f4le 19",
    "sg:city":"Nice C\u00e9dex 3",
    "sg:orig_category":"Non-Classified Establishments",
    "sg:phone":"+33 4 93 21 00 78",
    "sg:postcode":"06296",
    "sg:province":"Basse Normandie",
    "wof:name":"Cosmar International S.a.r.l.",
    "wof:placetype":"venue"
},
  "geometry": {"coordinates":[7.26627,43.703388],"type":"Point"}
}