{
  "type": "Feature",
  "properties": {
    "addr:full":"ZI Nord - Les Aigais Brignais Rhone-Alpes 69530",
    "addr:postcode":"69530",
    "addr:street":"Zi Nord Les Aigais;Rhone-Alpes",
    "iso:country":"FR",
    "sg:address":"ZI Nord - Les Aigais",
    "sg:city":"Brignais",
    "sg:orig_category":"Unclassifiable Establishments",
    "sg:phone":"+33 4 72 31 50 00",
    "sg:postcode":"69530",
    "sg:province":"Rhone-Alpes",
    "wof:name":"S.g.p.f. Prestafroid Nord S.a.",
    "wof:placetype":"venue"
},
  "geometry": {"coordinates":[4.753949,45.674034],"type":"Point"}
}