{
  "type": "Feature",
  "properties": {
    "iso:country":"FR",
    "sg:address":"R \u00e0 Laurent de Lavoisier 45500 Gien",
    "sg:city":"Gien",
    "sg:orig_category":"Ecg Suction Electrodes",
    "sg:phone":"+33 2 38 29 80 80",
    "sg:postcode":"45500",
    "sg:province":"Centre",
    "wof:name":"Aupem Sefli Sa",
    "wof:placetype":"venue"
},
  "geometry": {"coordinates":[2.628379,47.703911],"type":"Point"}
}