{
  "type": "Feature",
  "properties": {
    "iso:country":"FR",
    "sg:address":"5 rue de la Mou\u00e9e 57070 Metz",
    "sg:classifiers":[
        {
            "category":"Utilities",
            "subcategory":"Recycling",
            "type":"Services"
        }
    ],
    "sg:phone":"+33 3 87 75 70 70",
    "sg:postcode":"57070",
    "sg:province":"Lorraine",
    "sg:tags":[
        "metal"
    ],
    "wof:name":"Etablissements Marchal Sa",
    "wof:placetype":"venue"
},
  "geometry": {"coordinates":[6.247745,49.107891],"type":"Point"}
}