{
  "type": "Feature",
  "properties": {
    "iso:country":"FR",
    "sg:address":"59 Boulevard Raspail 75006 Paris",
    "sg:classifiers":[
        {
            "category":"Shopping",
            "subcategory":"Clothing, Apparel, & Fashions",
            "type":"Retail Goods"
        }
    ],
    "sg:phone":"+33 1 45 48 22 63",
    "sg:postcode":"75006",
    "sg:province":"Ile de France",
    "sg:tags":[
        "clothes"
    ],
    "wof:name":"Germain Jean",
    "wof:placetype":"venue"
},
  "geometry": {"coordinates":[2.327716,48.849567],"type":"Point"}
}