{
  "type": "Feature",
  "properties": {
    "addr:full":"12, Rue de Castellane, 75008 Paris Ile de France",
    "addr:housenumber":"12",
    "addr:postcode":"75008",
    "addr:street":"Rue De Castellane",
    "iso:country":"FR",
    "sg:address":"12, Rue de Castellane, 75008 Paris",
    "sg:orig_category":"Unclassifiable Establishments",
    "sg:phone":"+33 1 43 12 50 50",
    "sg:province":"Ile de France",
    "wof:name":"Audisoft Consultants S.a.s.",
    "wof:placetype":"venue"
},
  "geometry": {"coordinates":[2.324514,48.872574],"type":"Point"}
}