{
  "type": "Feature",
  "properties": {
    "addr:full":"4, Rue Blacas, 06000 Nice Picardie",
    "addr:housenumber":"4",
    "addr:postcode":"06000",
    "addr:street":"Rue Blacas",
    "iso:country":"FR",
    "sg:address":"4, Rue Blacas, 06000 Nice",
    "sg:orig_category":"Non-Classified Establishments",
    "sg:phone":"+33 4 93 13 05 00",
    "sg:province":"Picardie",
    "wof:name":"E.a.r. France S.a.s.",
    "wof:placetype":"venue"
},
  "geometry": {"coordinates":[7.270685,43.700123],"type":"Point"}
}