{
  "type": "Feature",
  "properties": {
    "addr:full":"2/4, Rue de Tr\u00e9vise, 75009 Paris Ile de France 75009",
    "addr:housenumber":"2 / 4",
    "addr:postcode":"75009;75009",
    "addr:street":"Rue De Tre\u0301Vise",
    "iso:country":"FR",
    "sg:address":"2/4, Rue de Tr\u00e9vise, 75009 Paris",
    "sg:orig_category":"Non-Classified Establishments",
    "sg:phone":"+33 1 42 46 21 53",
    "sg:postcode":"75009",
    "sg:province":"Ile de France",
    "wof:name":"E.m.c.t. S.a.r.l. - Euro Market Cohen Textiles",
    "wof:placetype":"venue"
},
  "geometry": {"coordinates":[2.345129,48.872574],"type":"Point"}
}