{
  "type": "Feature",
  "properties": {
    "addr:full":"32 Boulevard Gambetta 38000 Grenoble Rhone-Alpes 38000",
    "addr:housenumber":"32",
    "addr:postcode":"38000;38000",
    "addr:street":"Boulevard Gambetta",
    "iso:country":"FR",
    "sg:address":"32 Boulevard Gambetta 38000 Grenoble",
    "sg:classifiers":[
        {
            "category":"Manufacturing",
            "subcategory":"Textiles",
            "type":"Manufacturing & Wholesale Goods"
        }
    ],
    "sg:phone":"+33 4 76 46 56 60",
    "sg:postcode":"38000",
    "sg:province":"Rhone-Alpes",
    "sg:tags":[
        "clothing",
        "accessory"
    ],
    "wof:name":"S Notturno",
    "wof:placetype":"venue"
},
  "geometry": {"coordinates":[5.724627,45.185837],"type":"Point"}
}