{
  "type": "Feature",
  "properties": {
    "iso:country":"FR",
    "sg:address":"340 Rue Des Bruyeres Pa Orl\u00e9ans Sologne 45075 Orl\u00e9ans Cedex 2",
    "sg:classifiers":[
        {
            "category":"Building & Trades",
            "subcategory":"Construction",
            "type":"Services"
        }
    ],
    "sg:phone":"+33 2 38 63 25 56",
    "sg:province":"Lorraine",
    "sg:tags":[
        "work",
        "public"
    ],
    "wof:name":"Eurovia Centre Loire",
    "wof:placetype":"venue"
},
  "geometry": {"coordinates":[1.90398,47.90139],"type":"Point"}
}