{
  "type": "Feature",
  "properties": {
    "iso:country":"FR",
    "sg:address":"B.P. 6",
    "sg:city":"Sauveterre la L\u00e9mance C\u00e9dex^^Le Martinet 47500 Sauveterre la L\u00e9mance",
    "sg:orig_category":"Non-Classified Establishments",
    "sg:phone":"+33 5 53 40 63 15",
    "sg:postcode":"47500",
    "sg:province":"Aquitaine",
    "wof:name":"Les Chaux Du P\u00e9rigord S.a.",
    "wof:placetype":"venue"
},
  "geometry": {"coordinates":[0.984485,44.469021],"type":"Point"}
}