{
  "type": "Feature",
  "properties": {
    "addr:full":"4 Rue Du Lurin 69650 St Germain Au Mont D Or Rhone-Alpes 69650",
    "addr:housenumber":"4",
    "addr:postcode":"69650;69650",
    "addr:street":"Rue Du Lurin;Au Mont D;Rhone-Alpes",
    "iso:country":"FR",
    "sg:address":"4 Rue Du Lurin 69650 St Germain Au Mont D Or",
    "sg:classifiers":[
        {
            "category":"Shopping",
            "subcategory":"Clothing, Apparel, & Fashions",
            "type":"Retail Goods"
        }
    ],
    "sg:phone":"+33 4 78 91 37 75",
    "sg:postcode":"69650",
    "sg:province":"Rhone-Alpes",
    "sg:tags":[
        "textile",
        "clothing",
        "clothes"
    ],
    "wof:name":"Louise Della",
    "wof:placetype":"venue"
},
  "geometry": {"coordinates":[4.804755,45.877144],"type":"Point"}
}