{
  "type": "Feature",
  "properties": {
    "iso:country":"FR",
    "sg:address":"B.P. 85, 13425 Marseille C\u00e9dex 12^^53, Rue Gaston de Flotte - Parc d'Activit\u00e9s des Fa\u00efenciers, 13012",
    "sg:orig_category":"Non-Classified Establishments",
    "sg:phone":"+33 4 91 89 90 00",
    "sg:province":"Poitou-Charentes",
    "wof:name":"Somaf S.a.r.l.",
    "wof:placetype":"venue"
},
  "geometry": {"coordinates":[5.429799,43.298958],"type":"Point"}
}