{
  "type": "Feature",
  "properties": {
    "addr:full":"Rue Thomas Edison Espace Le Trefle 33610 Canejan Can\u00e9jan Aquitaine 33610",
    "addr:housenumber":"espace",
    "addr:postcode":"33610;33610",
    "addr:street":"Rue Thomas Edison",
    "iso:country":"FR",
    "sg:address":"Rue Thomas Edison Espace Le Trefle 33610 Canejan",
    "sg:city":"Can\u00e9jan",
    "sg:classifiers":[
        {
            "category":"Professional",
            "subcategory":"Printing & Photocopies",
            "type":"Services"
        }
    ],
    "sg:phone":"+33 5 57 26 68 68",
    "sg:postcode":"33610",
    "sg:province":"Aquitaine",
    "sg:tags":[
        "publishing"
    ],
    "wof:name":"Educatic",
    "wof:placetype":"venue"
},
  "geometry": {"coordinates":[-0.685714,44.741707],"type":"Point"}
}