{
  "type": "Feature",
  "properties": {
    "addr:full":"18 Imp De La Papeterie 10800 St Julien Les Villas Champagne 10800",
    "addr:housenumber":"18",
    "addr:postcode":"10800 st julien;10800",
    "addr:street":"Imp De La Papeterie;Les Villas",
    "iso:country":"FR",
    "sg:address":"18 Imp De La Papeterie 10800 St Julien Les Villas",
    "sg:classifiers":[
        {
            "category":"Shopping",
            "subcategory":"Clothing, Apparel, & Fashions",
            "type":"Retail Goods"
        }
    ],
    "sg:phone":"+33 3 25 82 15 53",
    "sg:postcode":"10800",
    "sg:province":"Champagne",
    "sg:tags":[
        "textile",
        "clothing",
        "clothes"
    ],
    "wof:name":"Ste Textiles De Champagne Sa",
    "wof:placetype":"venue"
},
  "geometry": {"coordinates":[4.09477,48.282291],"type":"Point"}
}