{
  "type": "Feature",
  "properties": {
    "iso:country":"FR",
    "sg:address":"556 route de Toulouse; Bordeaux; 33140",
    "sg:city":"Cadaujac",
    "sg:classifiers":[
        {
            "category":"Banks & Credit Unions",
            "subcategory":"Bank",
            "type":"Services"
        }
    ],
    "sg:phone":"+33 3356871518",
    "sg:postcode":"33140",
    "sg:province":"Aquitaine",
    "wof:name":"Cr\u00e9dit Agricole De La Gironde",
    "wof:placetype":"venue"
},
  "geometry": {"coordinates":[-0.570844,44.783916],"type":"Point"}
}