{
  "type": "Feature",
  "properties": {
    "addr:full":"Route De Teteghem 59380 Coudekerque Village Nord Pas-de-Calais 59380",
    "addr:postcode":"59380;59380",
    "addr:street":"Route De Teteghem;Coudekerque Village Nord",
    "iso:country":"FR",
    "sg:address":"Route De Teteghem 59380 Coudekerque Village",
    "sg:classifiers":[
        {
            "category":"Shopping",
            "type":"Retail Goods"
        }
    ],
    "sg:phone":"+33 3 28 61 05 48",
    "sg:postcode":"59380",
    "sg:province":"Nord Pas-de-Calais",
    "sg:tags":[
        "metallurgy",
        "finished",
        "-",
        "metalworking",
        "metallic"
    ],
    "wof:name":"Ste Industrielle Technique Dunkerquoise Eurl Sarl",
    "wof:placetype":"venue"
},
  "geometry": {"coordinates":[2.493145,50.976814],"type":"Point"}
}