{
  "type": "Feature",
  "properties": {
    "addr:full":"70150 Chenevrey et Morogne Franche Comt\u00e9",
    "addr:postcode":"70150",
    "addr:street":"Franche Comte\u0301",
    "iso:country":"FR",
    "sg:address":"70150 Chenevrey et Morogne",
    "sg:orig_category":"Non-Classified Establishments",
    "sg:phone":"+33 3 84 31 72 22",
    "sg:province":"Franche Comt\u00e9",
    "wof:name":"Haute Sa\u00f4ne Boissons S.a.r.l.",
    "wof:placetype":"venue"
},
  "geometry": {"coordinates":[5.741105,47.281078],"type":"Point"}
}