{
  "type": "Feature",
  "properties": {
    "iso:country":"FR",
    "sg:address":"123 Rue De La Republique",
    "sg:city":"Luc\u00e9",
    "sg:classifiers":[
        {
            "category":"Banks & Credit Unions",
            "subcategory":"Financial Services",
            "type":"Services"
        }
    ],
    "sg:phone":"+33 2 37 90 80 00",
    "sg:postcode":"28110",
    "sg:province":"Centre",
    "sg:tags":[
        "banking",
        "finance",
        "insurance"
    ],
    "wof:name":"Fiduciaire Technique Et Comptable De L'ouest (fiteco)",
    "wof:placetype":"venue"
},
  "geometry": {"coordinates":[1.455304,48.438328],"type":"Point"}
}