{
  "type": "Feature",
  "properties": {
    "iso:country":"FR",
    "sg:address":"Route Artix BP 80 64150 Nogueres",
    "sg:city":"Nogu\u00e8res",
    "sg:classifiers":[
        {
            "category":"Health Services",
            "subcategory":"Medical Lab",
            "type":"Services"
        }
    ],
    "sg:phone":"+33 5 59 60 92 92",
    "sg:postcode":"64150",
    "sg:province":"Aquitaine",
    "sg:tags":[
        "chemical",
        "pharmaceutical",
        "pharmacy"
    ],
    "wof:name":"Calliope Sa",
    "wof:placetype":"venue"
},
  "geometry": {"coordinates":[-0.61819,43.354855],"type":"Point"}
}