{
  "type": "Feature",
  "properties": {
    "iso:country":"FR",
    "sg:address":"Avenue Du Parc 95011 Cergy",
    "sg:classifiers":[
        {
            "category":"Professional",
            "subcategory":"Business Services",
            "type":"Services"
        }
    ],
    "sg:phone":"+33 1 34 25 10 10",
    "sg:province":"Ile de France",
    "sg:tags":[
        "training",
        "advice"
    ],
    "wof:name":"Ecole Internationale Des Sciences Du Traitment Des Informations",
    "wof:placetype":"venue"
},
  "geometry": {"coordinates":[2.07333,49.033215],"type":"Point"}
}