{
  "type": "Feature",
  "properties": {
    "iso:country":"FR",
    "sg:address":"B.P. 322, 12103 Millau C\u00e9dex^^ZI, 12100 Saint Georges de Luzen\u00e7on",
    "sg:orig_category":"Non-Classified Establishments",
    "sg:phone":"+33 5 65 62 40 40",
    "sg:postcode":"12100",
    "sg:province":"Midi Pyr\u00e9n\u00e9es",
    "wof:name":"Cros Et Delmas S.a.r.l.",
    "wof:placetype":"venue"
},
  "geometry": {"coordinates":[2.98414,44.063969],"type":"Point"}
}