{
  "type": "Feature",
  "properties": {
    "addr:full":"80 Rue De La R\u00e9publique 80610 St Ouen Picardie",
    "addr:housenumber":"80",
    "addr:postcode":"80610",
    "addr:street":"Rue De La Re\u0301Publique;St",
    "iso:country":"FR",
    "sg:address":"80 Rue De La R\u00e9publique 80610 St Ouen",
    "sg:classifiers":[
        {
            "category":"Manufacturing",
            "subcategory":"Rubber & Plastics",
            "type":"Manufacturing & Wholesale Goods"
        }
    ],
    "sg:phone":"+33 3 22 39 44 44",
    "sg:province":"Picardie",
    "wof:name":"Trioplanex France Sa",
    "wof:placetype":"venue"
},
  "geometry": {"coordinates":[2.11752,50.041538],"type":"Point"}
}