{
  "type": "Feature",
  "properties": {
    "addr:full":"5 Avenue Lionel Terray 69881 Meyzieu Champagne",
    "addr:housenumber":"5",
    "addr:postcode":"69881",
    "addr:street":"Avenue Lionel Terray",
    "iso:country":"FR",
    "sg:address":"5 Avenue Lionel Terray 69881 Meyzieu",
    "sg:classifiers":[
        {
            "category":"Manufacturing",
            "subcategory":"Chemicals & Compounds",
            "type":"Manufacturing & Wholesale Goods"
        }
    ],
    "sg:phone":"+33 4 72 45 03 50",
    "sg:province":"Champagne",
    "sg:tags":[
        "pharmaceutical",
        "chemistry",
        "-",
        "by-product"
    ],
    "wof:name":"Ceri Revetements Techniques Sa",
    "wof:placetype":"venue"
},
  "geometry": {"coordinates":[5.027063,45.770672],"type":"Point"}
}