{
  "type": "Feature",
  "properties": {
    "iso:country":"FR",
    "sg:address":"7 Rue De Camas 02480 JUSSY",
    "sg:classifiers":[
        {
            "category":"Banks & Credit Unions",
            "subcategory":"Atm",
            "type":"Services"
        }
    ],
    "sg:phone":"+33 3 23 63 60 60",
    "sg:postcode":"02480",
    "sg:province":"Picardie",
    "sg:tags":[
        "carrier",
        "airlines",
        "air-freight"
    ],
    "wof:name":"Heli Interventions S.a.r.l",
    "wof:placetype":"venue"
},
  "geometry": {"coordinates":[3.23103,49.722439],"type":"Point"}
}