{
  "type": "Feature",
  "properties": {
    "iso:country":"FR",
    "sg:address":"35, Rue de la Motte, 93308 Aubervilliers C\u00e9dex",
    "sg:orig_category":"Non-Classified Establishments",
    "sg:phone":"+33 1 41 94 17 40",
    "sg:province":"Basse Normandie",
    "wof:name":"Signode France S.a.s.",
    "wof:placetype":"venue"
},
  "geometry": {"coordinates":[2.396433,48.910255],"type":"Point"}
}