{
  "type": "Feature",
  "properties": {
    "iso:country":"FR",
    "sg:address":"2 pl de l'Eglise; Loudeac; 22600",
    "sg:city":"Loud\u00e9ac",
    "sg:classifiers":[
        {
            "category":"Banks & Credit Unions",
            "subcategory":"Bank",
            "type":"Services"
        }
    ],
    "sg:phone":"+33 3396280405",
    "sg:postcode":"22600",
    "sg:province":"Bretagne",
    "wof:name":"Soci\u00e9t\u00e9 G\u00e9n\u00e9rale",
    "wof:placetype":"venue"
},
  "geometry": {"coordinates":[-2.7543,48.176136],"type":"Point"}
}