{
  "type": "Feature",
  "properties": {
    "iso:country":"FR",
    "sg:address":"50, Rue Ferrer, 59210 Coudekerque Branche",
    "sg:orig_category":"Non-Classified Establishments",
    "sg:phone":"+33 3 28 29 24 27",
    "sg:postcode":"59210",
    "sg:province":"Nord Pas-de-Calais",
    "wof:name":"C.e.t. 2 I. S.a.r.l. - Conception Etudes Techniques Ing\u00e9nierie Innovation",
    "wof:placetype":"venue"
},
  "geometry": {"coordinates":[2.370277,51.018951],"type":"Point"}
}