{
  "type": "Feature",
  "properties": {
    "iso:country":"FR",
    "sg:address":"21, Rue de la Pradelle, 63190 Lezoux",
    "sg:city":"Lezoux",
    "sg:orig_category":"Unclassifiable Establishments",
    "sg:phone":"+33 4 73 73 11 62",
    "sg:postcode":"63190",
    "sg:province":"Auvergne",
    "wof:name":"Appia Auvergne S.n.c.",
    "wof:placetype":"venue"
},
  "geometry": {"coordinates":[3.387223,45.828003],"type":"Point"}
}