{
  "type": "Feature",
  "properties": {
    "addr:full":"B.P. 7, 51470 Moncetz Longevas^^23, Rue Royale, 51470 Moncetz Longevas Champagne 51470",
    "addr:housenumber":"7",
    "addr:postcode":"51470;51470;51470",
    "addr:street":"B.P.;Rue Royale;Champagne",
    "iso:country":"FR",
    "sg:address":"B.P. 7, 51470 Moncetz Longevas^^23, Rue Royale, 51470 Moncetz Longevas",
    "sg:orig_category":"Assainissement du sol Canalisations d'eau et/ou conduites de gaz D\u00e9molition Terrassement Travaux pub",
    "sg:phone":"+33 3 26 67 52 82",
    "sg:postcode":"51470",
    "sg:province":"Champagne",
    "wof:name":"Boituzat S.a.",
    "wof:placetype":"venue"
},
  "geometry": {"coordinates":[4.384128,48.954563],"type":"Point"}
}