{
  "type": "Feature",
  "properties": {
    "addr:full":"94 Av Du G\u00e9n\u00e9ral Leclerc 69300 Caluire Et Cuire Rhone-Alpes 69300",
    "addr:postcode":"69300;69300",
    "addr:street":"94 Av Du Ge\u0301Ne\u0301Ral Leclerc",
    "iso:country":"FR",
    "sg:address":"94 Av Du G\u00e9n\u00e9ral Leclerc 69300 Caluire Et Cuire",
    "sg:classifiers":[
        {
            "category":"Manufacturing",
            "subcategory":"Metals",
            "type":"Manufacturing & Wholesale Goods"
        }
    ],
    "sg:phone":"+33 4 78 23 55 59",
    "sg:postcode":"69300",
    "sg:province":"Rhone-Alpes",
    "sg:tags":[
        "metallurgy",
        "metalworking",
        "processing"
    ],
    "wof:name":"Bonitempo Sa",
    "wof:placetype":"venue"
},
  "geometry": {"coordinates":[4.866097,45.805489],"type":"Point"}
}