{
  "type": "Feature",
  "properties": {
    "addr:full":"75 Rue De Nantes 44360 Le Temple De Bretagne Pays de Loire 44360",
    "addr:housenumber":"75",
    "addr:postcode":"44360;44360",
    "addr:street":"Rue De Nantes",
    "iso:country":"FR",
    "sg:address":"75 Rue De Nantes 44360 Le Temple De Bretagne",
    "sg:classifiers":[
        {
            "category":"Wholesale",
            "subcategory":"Machinery & Supplies",
            "type":"Manufacturing & Wholesale Goods"
        }
    ],
    "sg:phone":"+33 2 40 57 02 83",
    "sg:postcode":"44360",
    "sg:province":"Pays de Loire",
    "sg:tags":[
        "handling",
        "material",
        "-",
        "machine",
        "equipment",
        "engineering",
        "mechanical"
    ],
    "wof:name":"Sarl Sillon Levage",
    "wof:placetype":"venue"
},
  "geometry": {"coordinates":[-1.781545,47.321312],"type":"Point"}
}