{
  "type": "Feature",
  "properties": {
    "addr:full":"23, Rue Claude Chappe - ZAC de l'Aqueduc de l'Avre, 78370 Plaisir Ile de France 78370",
    "addr:housenumber":"23",
    "addr:postcode":"78370;78370",
    "addr:street":"Rue Claude Chappe Zac De L'Aqueduc De L'Avre",
    "iso:country":"FR",
    "sg:address":"23, Rue Claude Chappe - ZAC de l'Aqueduc de l'Avre, 78370 Plaisir",
    "sg:orig_category":"Non-Classified Establishments",
    "sg:phone":"+33 1 30 55 84 00",
    "sg:postcode":"78370",
    "sg:province":"Ile de France",
    "wof:name":"Cablelec S.a.",
    "wof:placetype":"venue"
},
  "geometry": {"coordinates":[1.961071,48.82188],"type":"Point"}
}