{
  "type": "Feature",
  "properties": {
    "addr:full":"22 Av Des Nations, Villepinte B\u00e2t Le Raspail, Paris Nord 2 95958 Roissy Cdg Cedex Vill\u00e9 Alsace 67220",
    "addr:housenumber":"ba\u0302t;2",
    "addr:postcode":"95958;67220",
    "addr:street":"22 Av Des Nations",
    "iso:country":"FR",
    "sg:address":"22 Av Des Nations, Villepinte B\u00e2t Le Raspail, Paris Nord 2 95958 Roissy Cdg Cedex",
    "sg:city":"Vill\u00e9",
    "sg:classifiers":[
        {
            "category":"Shopping",
            "subcategory":"Pharmacy",
            "type":"Retail Goods"
        }
    ],
    "sg:phone":"+33 1 49 90 72 72",
    "sg:postcode":"67220",
    "sg:province":"Alsace",
    "sg:tags":[
        "chemical",
        "pharmaceutical",
        "chemistry",
        "-",
        "by-product"
    ],
    "wof:name":"Dow France",
    "wof:placetype":"venue"
},
  "geometry": {"coordinates":[2.51524,49.004028],"type":"Point"}
}