{
  "type": "Feature",
  "properties": {
    "addr:full":"20, Rte de Lyons la For\u00eat, 76000 Rouen Haute Normandie 76000",
    "addr:housenumber":"20",
    "addr:postcode":"76000;76000",
    "addr:street":"Rte De Lyons La Fore\u0302T;Haute Normandie",
    "iso:country":"FR",
    "sg:address":"20, Rte de Lyons la For\u00eat, 76000 Rouen",
    "sg:orig_category":"Non-Classified Establishments",
    "sg:phone":"+33 2 35 08 20 95",
    "sg:postcode":"76000",
    "sg:province":"Haute Normandie",
    "wof:name":"Bignard S.a.",
    "wof:placetype":"venue"
},
  "geometry": {"coordinates":[1.12145,49.436729],"type":"Point"}
}