{
  "type": "Feature",
  "properties": {
    "addr:full":"6 R Thomas Edison Zi Des Tilleroy 25050 Besan\u00e7on Besan\u00e7on Franche Comt\u00e9 25000",
    "addr:housenumber":"6",
    "addr:postcode":"25050;25000",
    "addr:street":"R Thomas Edison Zi Des Tilleroy;Franche Comte\u0301",
    "iso:country":"FR",
    "sg:address":"6 R Thomas Edison Zi Des Tilleroy 25050 Besan\u00e7on",
    "sg:city":"Besan\u00e7on",
    "sg:classifiers":[
        {
            "category":"Manufacturing",
            "subcategory":"Metals",
            "type":"Manufacturing & Wholesale Goods"
        }
    ],
    "sg:phone":"+33 3 81 48 42 90",
    "sg:postcode":"25000",
    "sg:province":"Franche Comt\u00e9",
    "sg:tags":[
        "-",
        "machine",
        "equipment",
        "engineering",
        "machinery",
        "mechanical"
    ],
    "wof:name":"Somica Sa",
    "wof:placetype":"venue"
},
  "geometry": {"coordinates":[6.02091,47.239639],"type":"Point"}
}