{
  "type": "Feature",
  "properties": {
    "addr:full":"78 Gramme 59200 Tourcoing Nord Pas-de-Calais 59200",
    "addr:housenumber":"78",
    "addr:postcode":"59200;59200",
    "addr:street":"Gramme",
    "iso:country":"FR",
    "sg:address":"78",
    "sg:city":"Gramme 59200 Tourcoing",
    "sg:classifiers":[
        {
            "category":"Shopping",
            "type":"Retail Goods"
        }
    ],
    "sg:phone":"+33 3 20 28 11 11",
    "sg:postcode":"59200",
    "sg:province":"Nord Pas-de-Calais",
    "sg:tags":[
        "metallurgy",
        "finished",
        "-",
        "metalworking",
        "metallic"
    ],
    "wof:name":"Mareel Le Serrurier",
    "wof:placetype":"venue"
},
  "geometry": {"coordinates":[3.16861,50.736992],"type":"Point"}
}