{
  "type": "Feature",
  "properties": {
    "addr:full":"26, Rue d'Agen, 68000 Colmar Colmar Alsace 68000",
    "addr:housenumber":"26",
    "addr:postcode":"68000;68000",
    "addr:street":"Rue D'Agen",
    "iso:country":"FR",
    "sg:address":"26, Rue d'Agen, 68000 Colmar",
    "sg:city":"Colmar",
    "sg:orig_category":"Unclassifiable Establishments",
    "sg:phone":"+33 3 89 23 09 15",
    "sg:postcode":"68000",
    "sg:province":"Alsace",
    "wof:name":"Sabreco S.a. - Soci\u00e9t\u00e9 D'achat Des Bouchers De La R\u00e9gion De Colmar",
    "wof:placetype":"venue"
},
  "geometry": {"coordinates":[7.351405,48.086105],"type":"Point"}
}