{
  "type": "Feature",
  "properties": {
    "addr:full":"11, Rue de Vitry - Immeuble le Delta, 93512 Montreuil C\u00e9dex Haute Normandie",
    "addr:housenumber":"11;immeuble",
    "addr:postcode":"93512",
    "addr:street":"Rue De Vitry;Haute Normandie",
    "iso:country":"FR",
    "sg:address":"11, Rue de Vitry - Immeuble le Delta, 93512 Montreuil C\u00e9dex",
    "sg:orig_category":"Non-Classified Establishments",
    "sg:phone":"+33 1 48 18 68 00",
    "sg:province":"Haute Normandie",
    "wof:name":"Emergences",
    "wof:placetype":"venue"
},
  "geometry": {"coordinates":[2.445578,48.860565],"type":"Point"}
}