{
  "type": "Feature",
  "properties": {
    "addr:full":"7, Place Saint Eloi, 79700 Rorthais Poitou-Charentes 79700",
    "addr:housenumber":"7",
    "addr:postcode":"79700;79700",
    "addr:street":"Place Saint Eloi;Rorthais",
    "iso:country":"FR",
    "sg:address":"7, Place Saint Eloi, 79700 Rorthais",
    "sg:orig_category":"Unclassifiable Establishments",
    "sg:phone":"+33 5 49 81 46 48",
    "sg:postcode":"79700",
    "sg:province":"Poitou-Charentes",
    "wof:name":"Loiseau Et Compagnie S.a.r.l.",
    "wof:placetype":"venue"
},
  "geometry": {"coordinates":[-0.706989,46.916214],"type":"Point"}
}