{
  "type": "Feature",
  "properties": {
    "addr:full":"Rte de Janz\u00e9 Janz\u00e9 Bretagne 35150",
    "addr:postcode":"35150",
    "addr:street":"Rte De Janze\u0301 Janze\u0301 Bretagne",
    "iso:country":"FR",
    "sg:address":"Rte de Janz\u00e9",
    "sg:city":"Janz\u00e9",
    "sg:orig_category":"Non-Classified Establishments",
    "sg:phone":"+33 2 99 44 00 49",
    "sg:postcode":"35150",
    "sg:province":"Bretagne",
    "wof:name":"Etablissements Henry Lecomte S.a.",
    "wof:placetype":"venue"
},
  "geometry": {"coordinates":[-1.586419,47.97781],"type":"Point"}
}