{
  "type": "Feature",
  "properties": {
    "addr:full":"ZA le R\u00e9mourin B\u00e9darrides Provence-Alpes-C\u00f4te d'Azur 84370",
    "addr:postcode":"84370",
    "addr:street":"Za Le Re\u0301Mourin Be\u0301Darrides",
    "iso:country":"FR",
    "sg:address":"ZA le R\u00e9mourin",
    "sg:city":"B\u00e9darrides",
    "sg:orig_category":"Non-Classified Establishments",
    "sg:phone":"+33 4 90 33 20 90",
    "sg:postcode":"84370",
    "sg:province":"Provence-Alpes-C\u00f4te d'Azur",
    "wof:name":"Co - Loc S.a.r.l.",
    "wof:placetype":"venue"
},
  "geometry": {"coordinates":[4.89808,44.040989],"type":"Point"}
}