{
  "type": "Feature",
  "properties": {
    "iso:country":"FR",
    "sg:address":"1, Rue Boinville, 78790 Arnouville les Mantes",
    "sg:orig_category":"Unclassifiable Establishments",
    "sg:phone":"+33 1 30 42 61 61",
    "sg:province":"Ile de France",
    "wof:name":"Duport S.a.",
    "wof:placetype":"venue"
},
  "geometry": {"coordinates":[1.6806,48.892555],"type":"Point"}
}