{
  "type": "Feature",
  "properties": {
    "addr:full":"Avenue Du Teleport BP 20125 Pacifica Tel 4 Imm Antares 86360 Chasseneuil Du Poitou Corse 20125",
    "addr:housenumber":"imm",
    "addr:postcode":"20125;86360;20125",
    "addr:street":"Avenue Du Teleport Bp;Tel;Antares",
    "iso:country":"FR",
    "sg:address":"Avenue Du Teleport BP 20125 Pacifica Tel 4 Imm Antares 86360 Chasseneuil Du Poitou",
    "sg:classifiers":[
        {
            "category":"Banks & Credit Unions",
            "subcategory":"Financial Services",
            "type":"Services"
        }
    ],
    "sg:phone":"+33 5 49 49 09 49",
    "sg:postcode":"20125",
    "sg:province":"Corse",
    "sg:tags":[
        "banking",
        "finance",
        "insurance"
    ],
    "wof:name":"Societe D'indemnisations Regionales Du Credit Agricole",
    "wof:placetype":"venue"
},
  "geometry": {"coordinates":[0.37477,46.650494],"type":"Point"}
}