{
  "type": "Feature",
  "properties": {
    "addr:full":"10 Rue Du Sable 67110 Gundershoffen Gundershoffen Alsace 67110",
    "addr:housenumber":"10",
    "addr:postcode":"67110;67110",
    "addr:street":"Rue Du Sable;Gundershoffen",
    "iso:country":"FR",
    "sg:address":"10 Rue Du Sable 67110 Gundershoffen",
    "sg:city":"Gundershoffen",
    "sg:classifiers":[
        {
            "category":"Manufacturing",
            "subcategory":"Metals",
            "type":"Manufacturing & Wholesale Goods"
        }
    ],
    "sg:phone":"+33 3 88 72 90 29",
    "sg:postcode":"67110",
    "sg:province":"Alsace",
    "sg:tags":[
        "metallurgy",
        "steel",
        "metalworking"
    ],
    "wof:name":"Gerard Schweyer Sarl",
    "wof:placetype":"venue"
},
  "geometry": {"coordinates":[7.662325,48.904762],"type":"Point"}
}