{
  "type": "Feature",
  "properties": {
    "iso:country":"FR",
    "sg:address":"Quai Trichet 35400 St Malo",
    "sg:city":"Saint-Malo",
    "sg:classifiers":[
        {
            "category":"Ice Cream",
            "type":"Food & Drink"
        }
    ],
    "sg:phone":"+33 2 99 19 10 10",
    "sg:postcode":"35400",
    "sg:province":"Bretagne",
    "sg:tags":[
        "preserve",
        "product",
        "livestock",
        "frozen",
        "related",
        "animal",
        "breeding",
        "agriculture"
    ],
    "wof:name":"P\u00cacheries Et Viviers La C\u00d4te D'emeraude Sarl",
    "wof:placetype":"venue"
},
  "geometry": {"coordinates":[-2.018371,48.641422],"type":"Point"}
}