{
  "type": "Feature",
  "properties": {
    "iso:country":"FR",
    "sg:address":"1 Rue Charles Croiz\u00e9 35740 Pac\u00e9",
    "sg:city":"Pac\u00e9",
    "sg:classifiers":[
        {
            "category":"Shopping",
            "type":"Retail Goods"
        }
    ],
    "sg:phone":"+33 2 99 60 63 58",
    "sg:postcode":"35740",
    "sg:province":"Bretagne",
    "sg:tags":[
        "metallurgy",
        "finished",
        "-",
        "metalworking",
        "metallic"
    ],
    "wof:name":"Bst Charrier",
    "wof:placetype":"venue"
},
  "geometry": {"coordinates":[-1.766166,48.147827],"type":"Point"}
}