{
  "type": "Feature",
  "properties": {
    "iso:country":"FR",
    "sg:address":"32 Rue Sorgentino 06300 Nice",
    "sg:classifiers":[
        {
            "category":"Government",
            "subcategory":"Fire Station",
            "type":"Public Place"
        }
    ],
    "sg:phone":"+33 4 93 55 26 26",
    "sg:province":"Picardie",
    "sg:tags":[
        "electric",
        "electricity",
        "component",
        "equipment",
        "lighting",
        "electrical",
        "electronic"
    ],
    "wof:name":"Comptoir Electrique Francais",
    "wof:placetype":"venue"
},
  "geometry": {"coordinates":[7.292025,43.711823],"type":"Point"}
}