{
  "type": "Feature",
  "properties": {
    "iso:country":"FR",
    "sg:address":"B.P. 69, 93104 Montreuil C\u00e9dex^^63, Rue Beaumarchais, 93100 Montreuil",
    "sg:orig_category":"Non-Classified Establishments",
    "sg:phone":"+33 1 48 18 51 00",
    "sg:province":"Ile de France",
    "wof:name":"Norton Desmarquest S.a.",
    "wof:placetype":"venue"
},
  "geometry": {"coordinates":[2.442661,48.864525],"type":"Point"}
}