{
  "type": "Feature",
  "properties": {
    "addr:full":"3, Av. de l'Orme Fourchu - ZI, 84000 Avignon Provence-Alpes-C\u00f4te d'Azur",
    "addr:postcode":"84000",
    "addr:street":"Av. De L'Orme;Zi",
    "iso:country":"FR",
    "sg:address":"3, Av. de l'Orme Fourchu - ZI, 84000 Avignon",
    "sg:orig_category":"Non-Classified Establishments",
    "sg:phone":"+33 4 90 87 57 02",
    "sg:province":"Provence-Alpes-C\u00f4te d'Azur",
    "wof:name":"Montel Sud S.a.",
    "wof:placetype":"venue"
},
  "geometry": {"coordinates":[4.835001,43.940262],"type":"Point"}
}