{
  "type": "Feature",
  "properties": {
    "iso:country":"FR",
    "sg:address":"33 Av De Lugo 94600 Choisy Le Roi",
    "sg:classifiers":[
        {
            "category":"Shopping",
            "subcategory":"Computers & Home Electronics",
            "type":"Retail Goods"
        }
    ],
    "sg:phone":"+33 1 43 91 62 02",
    "sg:postcode":"94600",
    "sg:province":"Ile de France",
    "sg:tags":[
        "electronic",
        "electrical",
        "equipment"
    ],
    "wof:name":"Serfa",
    "wof:placetype":"venue"
},
  "geometry": {"coordinates":[2.409177,48.770538],"type":"Point"}
}