{
  "type": "Feature",
  "properties": {
    "iso:country":"FR",
    "sg:address":"4 Rue Piroux",
    "sg:city":"Nancy",
    "sg:classifiers":[
        {
            "category":"Banks & Credit Unions",
            "subcategory":"Financial Services",
            "type":"Services"
        }
    ],
    "sg:phone":"+33 3 83 32 93 93",
    "sg:postcode":"54000",
    "sg:province":"Lorraine",
    "sg:tags":[
        "banking",
        "finance",
        "insurance"
    ],
    "wof:name":"Sofico France",
    "wof:placetype":"venue"
},
  "geometry": {"coordinates":[6.17425,48.690536],"type":"Point"}
}