{
  "type": "Feature",
  "properties": {
    "iso:country":"FR",
    "sg:address":"68, Rue de Turbigo, 75003 Paris",
    "sg:orig_category":"Unclassifiable Establishments",
    "sg:phone":"+33 1 44 54 90 68",
    "sg:province":"Ile de France",
    "wof:name":"Goldriver S.a",
    "wof:placetype":"venue"
},
  "geometry": {"coordinates":[2.35955,48.866077],"type":"Point"}
}