{
  "type": "Feature",
  "properties": {
    "iso:country":"FR",
    "sg:address":"3, Rue du Stand, 10700 Arcis sur Aube",
    "sg:orig_category":"SERRURERIE, M\u00c9TALLERIE chaudronnerie acier inox constructions m\u00e9talliques m\u00e9cano-soudure poin\u00e7onnage",
    "sg:phone":"+33 3 25 37 07 06",
    "sg:province":"Champagne",
    "wof:name":"Collet Pascal",
    "wof:placetype":"venue"
},
  "geometry": {"coordinates":[4.158239,48.532112],"type":"Point"}
}