{
  "type": "Feature",
  "properties": {
    "addr:full":"Route D Agonac Cap Blanc 24750 Champcevinel Champcevinel Aquitaine 24750",
    "addr:postcode":"24750;24750",
    "addr:street":"Route D;Blanc",
    "iso:country":"FR",
    "sg:address":"Route D Agonac Cap Blanc 24750 Champcevinel",
    "sg:city":"Champcevinel",
    "sg:classifiers":[
        {
            "category":"Manufacturing",
            "subcategory":"Wood Products",
            "type":"Manufacturing & Wholesale Goods"
        }
    ],
    "sg:phone":"+33 5 53 45 60 10",
    "sg:postcode":"24750",
    "sg:province":"Aquitaine",
    "sg:tags":[
        "professional",
        "furniture"
    ],
    "wof:name":"Aquitaine Agencements",
    "wof:placetype":"venue"
},
  "geometry": {"coordinates":[0.789735,45.09977],"type":"Point"}
}