{
  "type": "Feature",
  "properties": {
    "addr:full":"105, Rue de la Vincourt, 59246 Mons en P\u00e9v\u00e8le Nord Pas-de-Calais",
    "addr:housenumber":"105",
    "addr:postcode":"59246",
    "addr:street":"Rue De La Vincourt",
    "iso:country":"FR",
    "sg:address":"105, Rue de la Vincourt, 59246 Mons en P\u00e9v\u00e8le",
    "sg:orig_category":"Non-Classified Establishments",
    "sg:phone":"+33 3 20 59 21 50",
    "sg:province":"Nord Pas-de-Calais",
    "wof:name":"J. Bernard S.a.",
    "wof:placetype":"venue"
},
  "geometry": {"coordinates":[3.121494,50.485592],"type":"Point"}
}