{
  "type": "Feature",
  "properties": {
    "addr:full":"14, Rue de l'Industrie - ZI de la Courbi\u00e8re, 49450 Saint Macaire en Mauges Pays de Loire",
    "addr:housenumber":"14",
    "addr:postcode":"49450",
    "addr:street":"Rue De L'Industrie Zi De La Courbie\u0300Re;Mauges",
    "iso:country":"FR",
    "sg:address":"14, Rue de l'Industrie - ZI de la Courbi\u00e8re, 49450 Saint Macaire en Mauges",
    "sg:orig_category":"Non-Classified Establishments",
    "sg:phone":"+33 2 41 49 17 30",
    "sg:province":"Pays de Loire",
    "wof:name":"P.a.b. S.a.",
    "wof:placetype":"venue"
},
  "geometry": {"coordinates":[-0.976353,47.119495],"type":"Point"}
}