{
  "type": "Feature",
  "properties": {
    "iso:country":"FR",
    "sg:address":"PA Cambrai Cantimpr\u00e9",
    "sg:city":"Cambrai",
    "sg:orig_category":"Unclassifiable Establishments",
    "sg:phone":"+33 3 27 81 23 84",
    "sg:postcode":"59400",
    "sg:province":"Nord Pas-de-Calais",
    "wof:name":"Normand Construction S.a.r.l.",
    "wof:placetype":"venue"
},
  "geometry": {"coordinates":[3.207297,50.176643],"type":"Point"}
}