{
  "type": "Feature",
  "properties": {
    "addr:full":"71, Rue Gabriel P\u00e9rri, 95240 Cormeilles en Parisis Ile de France",
    "addr:housenumber":"71",
    "addr:postcode":"95240;ile",
    "addr:street":"Rue Gabriel Pe\u0301Rri",
    "iso:country":"FR",
    "sg:address":"71, Rue Gabriel P\u00e9rri, 95240 Cormeilles en Parisis",
    "sg:orig_category":"Unclassifiable Establishments",
    "sg:phone":"+33 1 30 26 35 20",
    "sg:province":"Ile de France",
    "wof:name":"Bosquet S.a.",
    "wof:placetype":"venue"
},
  "geometry": {"coordinates":[2.202676,48.975094],"type":"Point"}
}