{
  "type": "Feature",
  "properties": {
    "addr:full":"6 bis, Rue des Prairies, 75020 Paris Ile de France",
    "addr:housenumber":"6 bis",
    "addr:postcode":"75020",
    "addr:street":"Rue Des Prairies",
    "iso:country":"FR",
    "sg:address":"6 bis, Rue des Prairies, 75020 Paris",
    "sg:orig_category":"Unclassifiable Establishments",
    "sg:phone":"+33 1 44 62 87 30",
    "sg:province":"Ile de France",
    "wof:name":"Kam\u00e9dia Informatique S.a.r.l.",
    "wof:placetype":"venue"
},
  "geometry": {"coordinates":[2.404736,48.861332],"type":"Point"}
}