{
  "type": "Feature",
  "properties": {
    "addr:full":"Rue Jean Chaptal - ZAC de la Chartreuse Castres Midi Pyr\u00e9n\u00e9es 81100",
    "addr:postcode":"81100",
    "addr:street":"Rue Jean Chaptal Zac De La Chartreuse",
    "iso:country":"FR",
    "sg:address":"Rue Jean Chaptal - ZAC de la Chartreuse",
    "sg:city":"Castres",
    "sg:orig_category":"Unclassifiable Establishments",
    "sg:phone":"+33 5 63 59 10 77",
    "sg:postcode":"81100",
    "sg:province":"Midi Pyr\u00e9n\u00e9es",
    "wof:name":"C\u00e9d\u00e9o S.a.",
    "wof:placetype":"venue"
},
  "geometry": {"coordinates":[2.257356,43.56094],"type":"Point"}
}