{
  "type": "Feature",
  "properties": {
    "iso:country":"FR",
    "sg:address":"244 Av De Dunkerque 59130 Lambersart",
    "sg:classifiers":[
        {
            "category":"Professional",
            "subcategory":"Business Services",
            "type":"Services"
        }
    ],
    "sg:phone":"+33 3 20 08 15 50",
    "sg:postcode":"59130",
    "sg:province":"Nord Pas-de-Calais",
    "sg:tags":[
        "training",
        "advice"
    ],
    "wof:name":"Assoc Gestion Ctre Scolaire Sainte Union",
    "wof:placetype":"venue"
},
  "geometry": {"coordinates":[3.025666,50.636757],"type":"Point"}
}