{
  "type": "Feature",
  "properties": {
    "addr:full":"57, Rue de Rennes, 44119 Treilli\u00e8res Pays de Loire",
    "addr:housenumber":"57",
    "addr:postcode":"44119",
    "addr:street":"Rue De Rennes",
    "iso:country":"FR",
    "sg:address":"57, Rue de Rennes, 44119 Treilli\u00e8res",
    "sg:orig_category":"Non-Classified Establishments",
    "sg:phone":"+33 2 40 94 60 69",
    "sg:province":"Pays de Loire",
    "wof:name":"Eurovoirie",
    "wof:placetype":"venue"
},
  "geometry": {"coordinates":[-1.614774,47.322891],"type":"Point"}
}