{
  "type": "Feature",
  "properties": {
    "iso:country":"FR",
    "sg:address":"9 Rue Des Chaudronniers Zi 88190 Golbey",
    "sg:classifiers":[
        {
            "category":"Farming",
            "subcategory":"Crops",
            "type":"Manufacturing & Wholesale Goods"
        }
    ],
    "sg:phone":"+33 3 29 34 81 34",
    "sg:postcode":"88190",
    "sg:province":"Lorraine",
    "sg:tags":[
        "vegetable",
        "fruit",
        "agriculture",
        "livestock"
    ],
    "wof:name":"La Forestiere Du Champignon",
    "wof:placetype":"venue"
},
  "geometry": {"coordinates":[6.438855,48.197556],"type":"Point"}
}