{
  "type": "Feature",
  "properties": {
    "iso:country":"FR",
    "sg:address":"102 Rue D'Epluches 95310 St Ouen L'Aumone",
    "sg:classifiers":[
        {
            "category":"Marine",
            "type":"Transportation"
        }
    ],
    "sg:phone":"+33 1 34 48 83 83",
    "sg:province":"Ile de France",
    "sg:tags":[
        "transport",
        "sea"
    ],
    "wof:name":"Armat Sarl",
    "wof:placetype":"venue"
},
  "geometry": {"coordinates":[2.097719,49.028938],"type":"Point"}
}