{
  "type": "Feature",
  "properties": {
    "addr:full":"Hameau Le Moulin Longuet 76360 Villers Ecalles Haute Normandie 76360",
    "addr:postcode":"76360;76360",
    "addr:street":"Hameau Le Moulin Longuet;Haute Normandie",
    "iso:country":"FR",
    "sg:address":"Hameau Le Moulin Longuet 76360 Villers Ecalles",
    "sg:classifiers":[
        {
            "category":"Utilities",
            "subcategory":"Natural Gas",
            "type":"Services"
        }
    ],
    "sg:phone":"+33 2 35 91 25 69",
    "sg:postcode":"76360",
    "sg:province":"Haute Normandie",
    "sg:tags":[
        "blended",
        "flax",
        "yarn"
    ],
    "wof:name":"Etablissements Bidault Sa",
    "wof:placetype":"venue"
},
  "geometry": {"coordinates":[0.953649,49.545403],"type":"Point"}
}