{
  "type": "Feature",
  "properties": {
    "iso:country":"FR",
    "sg:address":"29, Rue Jules Michelet, 01100 Oyonnax",
    "sg:orig_category":"Unclassifiable Establishments",
    "sg:phone":"+33 4 74 73 64 19",
    "sg:postcode":"01100",
    "sg:province":"Rhone-Alpes",
    "wof:name":"Albis Plastique France S.a.",
    "wof:placetype":"venue"
},
  "geometry": {"coordinates":[5.652381,46.260445],"type":"Point"}
}