{
  "type": "Feature",
  "properties": {
    "iso:country":"FR",
    "sg:address":"ZI du Chaffaut",
    "sg:city":"Bouguenais",
    "sg:orig_category":"Unclassifiable Establishments",
    "sg:phone":"+33 2 40 75 56 49",
    "sg:postcode":"44340",
    "sg:province":"Pays de Loire",
    "wof:name":"Lemasson E.u.r.l.",
    "wof:placetype":"venue"
},
  "geometry": {"coordinates":[-1.623469,47.179531],"type":"Point"}
}