{
  "type": "Feature",
  "properties": {
    "addr:full":"21, Rue du Parc, 68700 Cernay Cernay Alsace 68700",
    "addr:housenumber":"21",
    "addr:postcode":"68700;68700",
    "addr:street":"Rue Du Parc",
    "iso:country":"FR",
    "sg:address":"21, Rue du Parc, 68700 Cernay",
    "sg:city":"Cernay",
    "sg:orig_category":"Non-Classified Establishments",
    "sg:phone":"+33 3 89 63 33 63",
    "sg:postcode":"68700",
    "sg:province":"Alsace",
    "wof:name":"Fernand Schlienger Et Fils S.a.",
    "wof:placetype":"venue"
},
  "geometry": {"coordinates":[7.175107,47.802814],"type":"Point"}
}