{
  "type": "Feature",
  "properties": {
    "iso:country":"FR",
    "sg:address":"5 boulevard Saint-Jean",
    "sg:city":"Beauvais",
    "sg:classifiers":[
        {
            "category":"Professional",
            "subcategory":"Computer Services",
            "type":"Services"
        }
    ],
    "sg:postcode":"60000",
    "sg:tags":[
        "web-development-website-backup-remote-backup-training-ecommerce-cms-joomla-oscommerce-anti-spam-spam-filter"
    ],
    "sg:website":"http://www.sitescom.eu",
    "wof:name":"Sitescom",
    "wof:placetype":"venue"
},
  "geometry": {"coordinates":[2.075503,49.428636],"type":"Point"}
}