{
  "type": "Feature",
  "properties": {
    "addr:full":"Zi De Coursan 11110 Coursan Languedoc-Roussillon",
    "addr:postcode":"11110",
    "addr:street":"Zi De Coursan",
    "iso:country":"FR",
    "sg:address":"Zi De Coursan 11110 Coursan",
    "sg:classifiers":[
        {
            "category":"Manufacturing",
            "subcategory":"Rubber & Plastics",
            "type":"Manufacturing & Wholesale Goods"
        }
    ],
    "sg:phone":"+33 4 68 33 79 05",
    "sg:province":"Languedoc-Roussillon",
    "sg:tags":[
        "packaging",
        "material",
        "-"
    ],
    "wof:name":"Mamor Sud",
    "wof:placetype":"venue"
},
  "geometry": {"coordinates":[3.05693,43.233913],"type":"Point"}
}