{
  "type": "Feature",
  "properties": {
    "iso:country":"FR",
    "sg:address":"114 Av Charles De Gaulle 92542 Neuilly Sur Seine",
    "sg:classifiers":[
        {
            "category":"Food Court",
            "type":"Food & Drink"
        }
    ],
    "sg:phone":"+33 1 49 75 21 90",
    "sg:province":"Haute Normandie",
    "sg:tags":[
        "related",
        "product",
        "miscellaneous",
        "gift"
    ],
    "wof:name":"Dfa",
    "wof:placetype":"venue"
},
  "geometry": {"coordinates":[2.268223,48.882702],"type":"Point"}
}