{
  "type": "Feature",
  "properties": {
    "iso:country":"FR",
    "sg:address":"4 Pl De La R\u00e9publique 62300 Lens",
    "sg:classifiers":[
        {
            "category":"Professional",
            "subcategory":"Engineering",
            "type":"Services"
        }
    ],
    "sg:phone":"+33 3 21 28 04 08",
    "sg:postcode":"62300",
    "sg:province":"Nord Pas-de-Calais",
    "sg:tags":[
        "machine",
        "-",
        "mechanical"
    ],
    "wof:name":"Mecatol (sa)",
    "wof:placetype":"venue"
},
  "geometry": {"coordinates":[2.831219,50.427502],"type":"Point"}
}