{
  "type": "Feature",
  "properties": {
    "iso:country":"FR",
    "sg:address":"6, avenue Raymond Poincar\u00e9, BP 419.16; Paris; 75769",
    "sg:classifiers":[
        {
            "category":"Industrial Area",
            "type":"Public Place"
        }
    ],
    "sg:phone":"+33 1 53 70 19 00",
    "sg:province":"Ile-de-France",
    "sg:tags":[
        "large",
        "private"
    ],
    "wof:name":"Carrefour Sa",
    "wof:placetype":"venue"
},
  "geometry": {"coordinates":[2.26286,48.857079],"type":"Point"}
}