{
  "type": "Feature",
  "properties": {
    "addr:full":"11, Rue de Malte, 75011 Paris Ile de France 75011",
    "addr:housenumber":"11",
    "addr:postcode":"75011;75011",
    "addr:street":"Rue De Malte",
    "iso:country":"FR",
    "sg:address":"11, Rue de Malte, 75011 Paris",
    "sg:orig_category":"Non-Classified Establishments",
    "sg:phone":"+33 1 43 55 37 85",
    "sg:postcode":"75011",
    "sg:province":"Ile de France",
    "wof:name":"Cutty Sark S.a.",
    "wof:placetype":"venue"
},
  "geometry": {"coordinates":[2.368742,48.8638],"type":"Point"}
}