{
  "type": "Feature",
  "properties": {
    "addr:full":"Z.I. d'Alissas 07210 Alissas Rhone-Alpes 07210",
    "addr:postcode":"07210;07210",
    "addr:street":"Z.I. D'Alissas;Rhone-Alpes",
    "iso:country":"FR",
    "sg:address":"Z.I. d'Alissas 07210 Alissas",
    "sg:classifiers":[
        {
            "category":"Manufacturing",
            "subcategory":"Wood Products",
            "type":"Manufacturing & Wholesale Goods"
        }
    ],
    "sg:phone":"+33 4 75 64 52 10",
    "sg:postcode":"07210",
    "sg:province":"Rhone-Alpes",
    "sg:tags":[
        "insulating",
        "high-temperature"
    ],
    "wof:name":"Piral Sa",
    "wof:placetype":"venue"
},
  "geometry": {"coordinates":[4.615669,44.71629],"type":"Point"}
}