{
  "type": "Feature",
  "properties": {
    "addr:full":"8 Rue Pierre De Coubertin Auray Bretagne 56400",
    "addr:housenumber":"8",
    "addr:postcode":"56400",
    "addr:street":"Rue Pierre De Coubertin Auray Bretagne",
    "iso:country":"FR",
    "sg:address":"8 Rue Pierre De Coubertin",
    "sg:city":"Auray",
    "sg:classifiers":[
        {
            "category":"Banks & Credit Unions",
            "subcategory":"Financial Services",
            "type":"Services"
        }
    ],
    "sg:phone":"+33 2 97 24 23 80",
    "sg:postcode":"56400",
    "sg:province":"Bretagne",
    "sg:tags":[
        "banking",
        "finance",
        "insurance"
    ],
    "wof:name":"Sobrecomo 56 Sarl",
    "wof:placetype":"venue"
},
  "geometry": {"coordinates":[-2.986899,47.675507],"type":"Point"}
}