{
  "type": "Feature",
  "properties": {
    "addr:full":"20 avenue d'Auvergne 23000 GUERET Limousin 23000",
    "addr:housenumber":"20",
    "addr:postcode":"23000;23000",
    "addr:street":"Avenue D'Auvergne",
    "iso:country":"FR",
    "sg:address":"20 avenue d'Auvergne 23000 GUERET",
    "sg:classifiers":[
        {
            "category":"Utilities",
            "subcategory":"Natural Gas",
            "type":"Services"
        }
    ],
    "sg:phone":"+33 5 55 41 14 60",
    "sg:postcode":"23000",
    "sg:province":"Limousin",
    "sg:tags":[
        "fertilizer",
        "biological"
    ],
    "wof:name":"Agricreuse Sca",
    "wof:placetype":"venue"
},
  "geometry": {"coordinates":[1.886904,46.165859],"type":"Point"}
}