{
  "type": "Feature",
  "properties": {
    "iso:country":"FR",
    "sg:address":"93, Av. de la Paix - ZI, 41700 Contres",
    "sg:city":"Contres",
    "sg:orig_category":"Unclassifiable Establishments",
    "sg:phone":"+33 2 54 79 06 33",
    "sg:postcode":"41700",
    "sg:province":"Centre",
    "wof:name":"Wintersteiger S.a.r.l.",
    "wof:placetype":"venue"
},
  "geometry": {"coordinates":[1.47907,47.344543],"type":"Point"}
}