{
  "type": "Feature",
  "properties": {
    "addr:full":"26, Rue des Marchais - ZI, 45140 Saint Jean de la Ruelle Ingr\u00e9 Centre 45140",
    "addr:housenumber":"26",
    "addr:postcode":"45140;45140",
    "addr:street":"Rue Des Marchais Zi;La Ruelle Ingre\u0301",
    "iso:country":"FR",
    "sg:address":"26, Rue des Marchais - ZI, 45140 Saint Jean de la Ruelle",
    "sg:city":"Ingr\u00e9",
    "sg:orig_category":"Non-Classified Establishments",
    "sg:phone":"+33 2 38 61 72 22",
    "sg:postcode":"45140",
    "sg:province":"Centre",
    "wof:name":"Orl\u00e9ans Laser S.a.",
    "wof:placetype":"venue"
},
  "geometry": {"coordinates":[1.8745,47.912949],"type":"Point"}
}