{
  "type": "Feature",
  "properties": {
    "addr:full":"14, Rue de la Cretagne, 21110 Rouvres en Plaine Soirans Bourgogne 21110",
    "addr:housenumber":"14",
    "addr:postcode":"21110;21110",
    "addr:street":"Rue De La Cretagne;Plaine",
    "iso:country":"FR",
    "sg:address":"14, Rue de la Cretagne, 21110 Rouvres en Plaine",
    "sg:city":"Soirans",
    "sg:orig_category":"Non-Classified Establishments",
    "sg:phone":"+33 3 80 79 15 00",
    "sg:postcode":"21110",
    "sg:province":"Bourgogne",
    "wof:name":"Gringos Productions S.a.r.l.",
    "wof:placetype":"venue"
},
  "geometry": {"coordinates":[5.141139,47.240921],"type":"Point"}
}