{
  "type": "Feature",
  "properties": {
    "addr:full":"38, Rue des Blancs Manteaux, 75004 Paris Ile de France",
    "addr:housenumber":"38",
    "addr:postcode":"75004",
    "addr:street":"Rue Des Blancs Manteaux",
    "iso:country":"FR",
    "sg:address":"38, Rue des Blancs Manteaux, 75004 Paris",
    "sg:orig_category":"Unclassifiable Establishments",
    "sg:phone":"+33 1 40 27 91 95",
    "sg:province":"Ile de France",
    "wof:name":"Selling Attitude S.a.",
    "wof:placetype":"venue"
},
  "geometry": {"coordinates":[2.355285,48.859802],"type":"Point"}
}