{
  "type": "Feature",
  "properties": {
    "iso:country":"FR",
    "sg:address":"Chemin d'Enrobert",
    "sg:city":"Gimont",
    "sg:orig_category":"Unclassifiable Establishments",
    "sg:phone":"+33 5 62 67 92 30",
    "sg:postcode":"32200",
    "sg:province":"Midi Pyr\u00e9n\u00e9es",
    "wof:name":"Par\u00e9ra S.a.",
    "wof:placetype":"venue"
},
  "geometry": {"coordinates":[0.878801,43.631039],"type":"Point"}
}