{
  "type": "Feature",
  "properties": {
    "iso:country":"FR",
    "sg:address":"avenue du Fond de Vaux 95310 ST OUEN L AUMONE",
    "sg:classifiers":[
        {
            "category":"Professional",
            "type":"Services"
        }
    ],
    "sg:phone":"+33 1 30 37 30 00",
    "sg:province":"Ile de France",
    "sg:tags":[
        "transport"
    ],
    "wof:name":"H\u00e9li-inter",
    "wof:placetype":"venue"
},
  "geometry": {"coordinates":[-120.396912,38.051048],"type":"Point"}
}