{
  "type": "Feature",
  "properties": {
    "addr:full":"6 Chemin De Bastillac Zi Bastillac Nord 65000 Tarbes Midi Pyr\u00e9n\u00e9es 65000",
    "addr:housenumber":"6",
    "addr:postcode":"65000;65000",
    "addr:street":"Chemin De Bastillac Zi Bastillac Nord",
    "iso:country":"FR",
    "sg:address":"6 Chemin De Bastillac Zi Bastillac Nord 65000 Tarbes",
    "sg:classifiers":[
        {
            "category":"Wholesale",
            "subcategory":"Meat",
            "type":"Manufacturing & Wholesale Goods"
        }
    ],
    "sg:phone":"+33 5 62 51 34 34",
    "sg:postcode":"65000",
    "sg:province":"Midi Pyr\u00e9n\u00e9es",
    "sg:tags":[
        "food",
        "cooked",
        "product",
        "related"
    ],
    "wof:name":"Sa Salaisons De L'adour",
    "wof:placetype":"venue"
},
  "geometry": {"coordinates":[0.073125,43.230011],"type":"Point"}
}