{
  "type": "Feature",
  "properties": {
    "addr:full":"8 Rte De Troyes A\u00e9rodrome De Dijon-Darois 21121 Darois Darois Bourgogne 21121",
    "addr:housenumber":"8",
    "addr:postcode":"21121;21121",
    "addr:street":"Rte De Troyes",
    "iso:country":"FR",
    "sg:address":"8 Rte De Troyes A\u00e9rodrome De Dijon-Darois 21121 Darois",
    "sg:city":"Darois",
    "sg:classifiers":[
        {
            "category":"Manufacturing",
            "subcategory":"Aerospace",
            "type":"Manufacturing & Wholesale Goods"
        }
    ],
    "sg:phone":"+33 3 80 35 68 00",
    "sg:postcode":"21121",
    "sg:province":"Bourgogne",
    "sg:tags":[
        "equipment",
        "aeronautic",
        "transport",
        "vehicle"
    ],
    "wof:name":"Cosmos Sa",
    "wof:placetype":"venue"
},
  "geometry": {"coordinates":[5.02013,47.339851],"type":"Point"}
}