{
  "type": "Feature",
  "properties": {
    "addr:full":"51 Rue Louis Bleriot Z I Eurochannel 76370 Dieppe Haute Normandie 76370",
    "addr:housenumber":"51",
    "addr:postcode":"76370;76370",
    "addr:street":"Rue Louis Bleriot Z I Eurochannel",
    "iso:country":"FR",
    "sg:address":"51 Rue Louis Bleriot Z I Eurochannel 76370 Dieppe",
    "sg:classifiers":[
        {
            "category":"Shopping",
            "type":"Retail Goods"
        }
    ],
    "sg:phone":"+33 2 35 06 06 70",
    "sg:postcode":"76370",
    "sg:province":"Haute Normandie",
    "sg:tags":[
        "metallurgy",
        "finished",
        "-",
        "metalworking",
        "metallic"
    ],
    "wof:name":"Camfo (cameo)",
    "wof:placetype":"venue"
},
  "geometry": {"coordinates":[1.093,49.904709],"type":"Point"}
}