{
  "type": "Feature",
  "properties": {
    "addr:full":"rte de Quillan Saint Paul de Fenouillet Languedoc-Roussillon 66220",
    "addr:postcode":"66220",
    "addr:street":"Rte De Quillan;Fenouillet",
    "iso:country":"FR",
    "sg:address":"rte de Quillan",
    "sg:city":"Saint Paul de Fenouillet",
    "sg:orig_category":"Unclassifiable Establishments",
    "sg:phone":"+33 4 68 59 01 53",
    "sg:postcode":"66220",
    "sg:province":"Languedoc-Roussillon",
    "wof:name":"Etablissements Sapa S.a.r.l.",
    "wof:placetype":"venue"
},
  "geometry": {"coordinates":[2.505204,42.810398],"type":"Point"}
}