{
  "type": "Feature",
  "properties": {
    "iso:country":"FR",
    "sg:address":"rue du Levant 76590 Torcy Le Petit",
    "sg:classifiers":[
        {
            "category":"Utilities",
            "subcategory":"Natural Gas",
            "type":"Services"
        }
    ],
    "sg:phone":"+33 2 35 04 69 15",
    "sg:postcode":"76590",
    "sg:province":"Haute Normandie",
    "sg:tags":[
        "vent",
        "mat",
        "fume",
        "filter",
        "extraction",
        "filters",
        "hood",
        "greasy"
    ],
    "wof:name":"Saftair Industries S.a.",
    "wof:placetype":"venue"
},
  "geometry": {"coordinates":[1.176685,49.814556],"type":"Point"}
}