{
  "type": "Feature",
  "properties": {
    "addr:full":"Le Charpenay Parc d'Activit\u00e9s 69210 Lentilly Rhone-Alpes 69210",
    "addr:postcode":"69210;69210",
    "addr:street":"\u0301S;Rhone-Alpes",
    "iso:country":"FR",
    "sg:address":"Le Charpenay Parc d'Activit\u00e9s 69210 Lentilly",
    "sg:classifiers":[
        {
            "category":"Banks & Credit Unions",
            "subcategory":"Investment Brokerage",
            "type":"Services"
        }
    ],
    "sg:phone":"+33 4 74 01 73 72",
    "sg:postcode":"69210",
    "sg:province":"Rhone-Alpes",
    "sg:tags":[
        "equipment",
        "industrial",
        "refrigeration"
    ],
    "wof:name":"Froid Installat Depannage Entret Climati Sarl",
    "wof:placetype":"venue"
},
  "geometry": {"coordinates":[4.665969,45.816906],"type":"Point"}
}