{
  "type": "Feature",
  "properties": {
    "addr:full":"10 Rue Des Pierres Missigault 28630 Barjouville Barjouville Centre 28630",
    "addr:housenumber":"10",
    "addr:postcode":"28630;28630",
    "addr:street":"Rue Des Pierres Missigault",
    "iso:country":"FR",
    "sg:address":"10 Rue Des Pierres Missigault 28630 Barjouville",
    "sg:city":"Barjouville",
    "sg:classifiers":[
        {
            "category":"Shopping",
            "subcategory":"Gifts & Souvenirs",
            "type":"Retail Goods"
        }
    ],
    "sg:phone":"+33 2 37 34 37 57",
    "sg:postcode":"28630",
    "sg:province":"Centre",
    "sg:tags":[
        "product",
        "miscellaneous"
    ],
    "wof:name":"La Lettre Beauceronne",
    "wof:placetype":"venue"
},
  "geometry": {"coordinates":[1.472205,48.415043],"type":"Point"}
}