{
  "type": "Feature",
  "properties": {
    "iso:country":"FR",
    "sg:address":"B.P. 9, 59360 Le Cateau Cambr\u00e9sis^^ZI, 59360 Le Cateau Cambr\u00e9sis",
    "sg:orig_category":"Non-Classified Establishments",
    "sg:phone":"+33 3 27 84 23 38",
    "sg:province":"Nord Pas-de-Calais",
    "wof:name":"S.a.s.a. S.a. - Soci\u00e9t\u00e9 D'application Des Silicones Alimentaires",
    "wof:placetype":"venue"
},
  "geometry": {"coordinates":[3.543052,50.105213],"type":"Point"}
}