{
  "type": "Feature",
  "properties": {
    "iso:country":"FR",
    "sg:address":"19 Av Albert Einstein 93150 Le Blanc Mesnil",
    "sg:classifiers":[
        {
            "category":"Professional",
            "subcategory":"Engineering",
            "type":"Services"
        }
    ],
    "sg:phone":"+33 1 48 65 90 40",
    "sg:postcode":"93150",
    "sg:province":"Ile de France",
    "sg:tags":[
        "machine",
        "-",
        "mechanical"
    ],
    "wof:name":"Meca Rectif Sa",
    "wof:placetype":"venue"
},
  "geometry": {"coordinates":[2.47481,48.942562],"type":"Point"}
}