{
  "type": "Feature",
  "properties": {
    "addr:full":"Av. Pierre Pflimlin Sausheim Alsace 68390",
    "addr:postcode":"68390",
    "addr:street":"Av. Pierre Pflimlin",
    "iso:country":"FR",
    "sg:address":"Av. Pierre Pflimlin",
    "sg:city":"Sausheim",
    "sg:orig_category":"Non-Classified Establishments",
    "sg:phone":"+33 3 89 61 84 63",
    "sg:postcode":"68390",
    "sg:province":"Alsace",
    "wof:name":"Buro S.a.r.l.",
    "wof:placetype":"venue"
},
  "geometry": {"coordinates":[7.380565,47.778824],"type":"Point"}
}