{
  "type": "Feature",
  "properties": {
    "iso:country":"FR",
    "sg:address":"91, Rue R\u00e9aumur, 75002 Paris",
    "sg:orig_category":"Non-Classified Establishments",
    "sg:phone":"+33 1 40 26 42 99",
    "sg:province":"Ile de France",
    "wof:name":"Philippe Matignon France S.a.",
    "wof:placetype":"venue"
},
  "geometry": {"coordinates":[2.346719,48.867325],"type":"Point"}
}