{
  "type": "Feature",
  "properties": {
    "addr:full":"Rte Des Granges 01470 Briord Rhone-Alpes 01470",
    "addr:postcode":"01470;01470",
    "addr:street":"Rte Des Granges;Rhone-Alpes",
    "iso:country":"FR",
    "sg:address":"Rte Des Granges 01470 Briord",
    "sg:classifiers":[
        {
            "category":"Home & Garden",
            "subcategory":"Furniture",
            "type":"Retail Goods"
        }
    ],
    "sg:phone":"+33 4 74 36 18 49",
    "sg:postcode":"01470",
    "sg:province":"Rhone-Alpes",
    "sg:tags":[
        "household",
        "wood"
    ],
    "wof:name":"Cinna Sa",
    "wof:placetype":"venue"
},
  "geometry": {"coordinates":[5.46698,45.797981],"type":"Point"}
}