{
  "type": "Feature",
  "properties": {
    "addr:full":"6 Rue De Boigne 73000 Chambery Rhone-Alpes 73000",
    "addr:housenumber":"6",
    "addr:postcode":"73000;73000",
    "addr:street":"Rue De Boigne",
    "iso:country":"FR",
    "sg:address":"6 Rue De Boigne 73000 Chambery",
    "sg:classifiers":[
        {
            "category":"Shopping",
            "subcategory":"Clothing, Apparel, & Fashions",
            "type":"Retail Goods"
        }
    ],
    "sg:phone":"+33 4 79 85 42 93",
    "sg:postcode":"73000",
    "sg:province":"Rhone-Alpes",
    "sg:tags":[
        "textile",
        "clothing",
        "clothes"
    ],
    "wof:name":"Promod",
    "wof:placetype":"venue"
},
  "geometry": {"coordinates":[5.921547,45.566017],"type":"Point"}
}