{
  "type": "Feature",
  "properties": {
    "addr:full":"10, Rte de Molineuf, 41190 Orchaise Orchaise Centre 41190",
    "addr:housenumber":"10;orchaise",
    "addr:postcode":"41190;41190",
    "addr:street":"Rte De Molineuf",
    "iso:country":"FR",
    "sg:address":"10, Rte de Molineuf, 41190 Orchaise",
    "sg:city":"Orchaise",
    "sg:orig_category":"Unclassifiable Establishments",
    "sg:phone":"+33 2 54 70 05 34",
    "sg:postcode":"41190",
    "sg:province":"Centre",
    "wof:name":"Boutet Jean-louis",
    "wof:placetype":"venue"
},
  "geometry": {"coordinates":[1.202824,47.585766],"type":"Point"}
}