{
  "type": "Feature",
  "properties": {
    "addr:full":"5 Rue Du Prof Philippe Maupas Centre Ccal Chambray Ii 37170 Chambray Les Tours Chambray-l\u00e8s-Tours Centre 37170",
    "addr:housenumber":"5",
    "addr:postcode":"37170;tours;37170",
    "addr:street":"Rue Du Prof Philippe Maupas;Ccal Chambray Ii",
    "iso:country":"FR",
    "sg:address":"5 Rue Du Prof Philippe Maupas Centre Ccal Chambray Ii 37170 Chambray Les Tours",
    "sg:city":"Chambray-l\u00e8s-Tours",
    "sg:classifiers":[
        {
            "category":"Farming",
            "subcategory":"Farm",
            "type":"Manufacturing & Wholesale Goods"
        }
    ],
    "sg:phone":"+33 2 47 28 11 62",
    "sg:postcode":"37170",
    "sg:province":"Centre",
    "sg:tags":[
        "horticulture",
        "agriculture",
        "livestock"
    ],
    "wof:name":"Etablissements Horticoles Georges Truffaut (ehgt)",
    "wof:placetype":"venue"
},
  "geometry": {"coordinates":[0.71327,47.33884],"type":"Point"}
}