{
  "type": "Feature",
  "properties": {
    "addr:full":"4, Rue des Fontaines - Z.I., 59880 Saint Saulve Nord Pas-de-Calais",
    "addr:housenumber":"4",
    "addr:postcode":"59880;saulve",
    "addr:street":"Rue Des Fontaines;Pas-De-Calais",
    "iso:country":"FR",
    "sg:address":"4, Rue des Fontaines - Z.I., 59880 Saint Saulve",
    "sg:orig_category":"Unclassifiable Establishments",
    "sg:phone":"+33 3 27 47 00 04",
    "sg:province":"Nord Pas-de-Calais",
    "wof:name":"Bobinage Du Hainaut, Mirland Et Di Giovanni S.a.r.l.",
    "wof:placetype":"venue"
},
  "geometry": {"coordinates":[3.552555,50.369625],"type":"Point"}
}