{
  "type": "Feature",
  "properties": {
    "iso:country":"FR",
    "sg:address":"35, Rue Godot de Mauroy, 75009 Paris",
    "sg:orig_category":"Non-Classified Establishments",
    "sg:phone":"+33 1 44 71 07 07",
    "sg:postcode":"75009",
    "sg:province":"Ile de France",
    "wof:name":"Axon Airlines S.a.",
    "wof:placetype":"venue"
},
  "geometry": {"coordinates":[2.327155,48.872131],"type":"Point"}
}