{
  "type": "Feature",
  "properties": {
    "iso:country":"FR",
    "sg:address":"Le Bourg 01340 Marsonnas",
    "sg:orig_category":"Unclassifiable Establishments",
    "sg:phone":"+33 4 74 51 14 58",
    "sg:province":"Rhone-Alpes",
    "wof:name":"Entreprise Geray Jean-claude",
    "wof:placetype":"venue"
},
  "geometry": {"coordinates":[5.06841,46.336647],"type":"Point"}
}