{
  "type": "Feature",
  "properties": {
    "addr:full":"2 Chemin Rivet 33450 St Loub\u00e9s Cedex Saint-Loub\u00e8s Aquitaine 33450",
    "addr:housenumber":"2",
    "addr:postcode":"33450;loube\u0301s cedex;33450",
    "addr:street":"Chemin Rivet",
    "iso:country":"FR",
    "sg:address":"2 Chemin Rivet 33450 St Loub\u00e9s Cedex",
    "sg:city":"Saint-Loub\u00e8s",
    "sg:classifiers":[
        {
            "category":"Food Court",
            "type":"Food & Drink"
        }
    ],
    "sg:phone":"+33 5 57 97 07 20",
    "sg:postcode":"33450",
    "sg:province":"Aquitaine",
    "sg:tags":[
        "product",
        "related"
    ],
    "wof:name":"Grands Vins De Gironde San (gvg)",
    "wof:placetype":"venue"
},
  "geometry": {"coordinates":[-0.437015,44.924831],"type":"Point"}
}