{
  "type": "Feature",
  "properties": {
    "addr:full":"12 Avenue Beguines; Cergy \u00cele-de-France",
    "addr:housenumber":"12",
    "addr:street":"Avenue Beguines Cergy",
    "iso:country":"FR",
    "sg:address":"12 Avenue",
    "sg:city":"Beguines; Cergy",
    "sg:classifiers":[
        {
            "category":"Travel",
            "subcategory":"Travel Agent",
            "type":"Entertainment"
        }
    ],
    "sg:province":"\u00cele-de-France",
    "wof:name":"Lastminute.com /degriftour",
    "wof:placetype":"venue"
},
  "geometry": {"coordinates":[2.034892,49.050751],"type":"Point"}
}