{
  "type": "Feature",
  "properties": {
    "addr:full":"641 Avenue Des 4 Marronniers 74800 St Pierre En Faucigny Rhone-Alpes 74800",
    "addr:housenumber":"641",
    "addr:postcode":"74800;rhone-alpes 74800",
    "addr:street":"Avenue Des 4 Marronniers;Pierre En Faucigny",
    "iso:country":"FR",
    "sg:address":"641 Avenue Des 4 Marronniers 74800 St Pierre En Faucigny",
    "sg:classifiers":[
        {
            "category":"Professional",
            "subcategory":"Engineering",
            "type":"Services"
        }
    ],
    "sg:phone":"+33 4 50 25 01 76",
    "sg:postcode":"74800",
    "sg:province":"Rhone-Alpes",
    "sg:tags":[
        "machine",
        "-",
        "mechanical"
    ],
    "wof:name":"Euro Scies Rhone Alpes",
    "wof:placetype":"venue"
},
  "geometry": {"coordinates":[6.355976,46.063183],"type":"Point"}
}