{
  "type": "Feature",
  "properties": {
    "addr:full":"128, Av. de Lattre de Tassigny, 77400 Lagny sur Marne Ile de France",
    "addr:postcode":"77400",
    "addr:street":"128 Av. De Lattre De Tassigny",
    "iso:country":"FR",
    "sg:address":"128, Av. de Lattre de Tassigny, 77400 Lagny sur Marne",
    "sg:orig_category":"Unclassifiable Establishments",
    "sg:phone":"+33 1 60 07 82 00",
    "sg:province":"Ile de France",
    "wof:name":"Sodis S.a.",
    "wof:placetype":"venue"
},
  "geometry": {"coordinates":[2.685993,48.877361],"type":"Point"}
}