{
  "type": "Feature",
  "properties": {
    "iso:country":"FR",
    "sg:address":"74, Rue Notre Dame des Pr\u00e9s, 10120 Saint Andr\u00e9 les Vergers",
    "sg:orig_category":"Unclassifiable Establishments",
    "sg:phone":"+33 3 25 45 18 18",
    "sg:province":"Champagne",
    "wof:name":"A.d.g. S.a. - Agencement D\u00e9coration G\u00e9n\u00e9rale",
    "wof:placetype":"venue"
},
  "geometry": {"coordinates":[4.045618,48.288166],"type":"Point"}
}