{
  "type": "Feature",
  "properties": {
    "addr:full":"Cit\u00e9 Bata Moussey Lorraine 57770",
    "addr:postcode":"57770",
    "addr:street":"Cite\u0301 Bata",
    "iso:country":"FR",
    "sg:address":"Cit\u00e9 Bata",
    "sg:city":"Moussey",
    "sg:orig_category":"Unclassifiable Establishments",
    "sg:phone":"+33 3 87 24 50 00",
    "sg:postcode":"57770",
    "sg:province":"Lorraine",
    "wof:name":"Bata Hellocourt S.a.",
    "wof:placetype":"venue"
},
  "geometry": {"coordinates":[6.782645,48.673447],"type":"Point"}
}