{
  "type": "Feature",
  "properties": {
    "iso:country":"FR",
    "sg:address":"33760 LADAUX",
    "sg:city":"Ladaux",
    "sg:classifiers":[
        {
            "category":"Wholesale",
            "subcategory":"Wine & Distilled Alcoholic Beverages",
            "type":"Manufacturing & Wholesale Goods"
        }
    ],
    "sg:phone":"+33 5 57 34 54 00",
    "sg:postcode":"33760",
    "sg:province":"Aquitaine",
    "sg:tags":[
        "french"
    ],
    "wof:name":"Vignoble Ducourt Scea",
    "wof:placetype":"venue"
},
  "geometry": {"coordinates":[-0.24395,44.700226],"type":"Point"}
}