{
  "type": "Feature",
  "properties": {
    "addr:full":"Les Chaussins 05230 Chorges Chaussin Franche Comt\u00e9 39120",
    "addr:postcode":"05230;39120",
    "addr:street":"Chaussins;Franche Comte\u0301",
    "iso:country":"FR",
    "sg:address":"Les Chaussins 05230 Chorges",
    "sg:city":"Chaussin",
    "sg:classifiers":[
        {
            "category":"Farming",
            "subcategory":"Livestock Farm",
            "type":"Manufacturing & Wholesale Goods"
        }
    ],
    "sg:phone":"+33 4 92 50 66 99",
    "sg:postcode":"39120",
    "sg:province":"Franche Comt\u00e9",
    "sg:tags":[
        "breeding",
        "agriculture",
        "animal"
    ],
    "wof:name":"Gaec Gaudy",
    "wof:placetype":"venue"
},
  "geometry": {"coordinates":[6.266561,44.529663],"type":"Point"}
}