{
  "type": "Feature",
  "properties": {
    "addr:full":"42 route de Brignais 69230 ST GENIS LAVAL Rhone-Alpes",
    "addr:housenumber":"42",
    "addr:postcode":"69230",
    "addr:street":"Route De Brignais;Genis;Rhone-Alpes",
    "iso:country":"FR",
    "sg:address":"42 route de Brignais 69230 ST GENIS LAVAL",
    "sg:classifiers":[
        {
            "category":"Manufacturing",
            "subcategory":"Building Materials",
            "type":"Manufacturing & Wholesale Goods"
        }
    ],
    "sg:phone":"+33 4 78 56 19 07",
    "sg:province":"Rhone-Alpes",
    "sg:tags":[
        "sealing",
        "terrace",
        "balcony"
    ],
    "wof:name":"Merle Sarl",
    "wof:placetype":"venue"
},
  "geometry": {"coordinates":[4.77116,45.710381],"type":"Point"}
}