{
  "type": "Feature",
  "properties": {
    "iso:country":"FR",
    "sg:address":"B.P. 1, 68580 Seppois le Bas^^11, Rue d'Altkirch, 68580 Seppois le Bas",
    "sg:city":"Mooslargue",
    "sg:orig_category":"Non-Classified Establishments",
    "sg:phone":"+33 3 89 08 91 20",
    "sg:postcode":"68580",
    "sg:province":"Alsace",
    "wof:name":"Janoplast S.a.",
    "wof:placetype":"venue"
},
  "geometry": {"coordinates":[7.17645,47.540295],"type":"Point"}
}