{
  "type": "Feature",
  "properties": {
    "addr:full":"B.P. 4, 29180 Locronan^^Rte de Douarnenez, 29180 Locronan Locronan Bretagne 29180",
    "addr:housenumber":"4",
    "addr:postcode":"29180;29180;29180",
    "addr:street":"B.P.",
    "iso:country":"FR",
    "sg:address":"B.P. 4, 29180 Locronan^^Rte de Douarnenez, 29180 Locronan",
    "sg:city":"Locronan",
    "sg:orig_category":"Non-Classified Establishments",
    "sg:phone":"+33 2 98 91 73 01",
    "sg:postcode":"29180",
    "sg:province":"Bretagne",
    "wof:name":"Cadiou Industrie S.a.",
    "wof:placetype":"venue"
},
  "geometry": {"coordinates":[-4.206064,48.042675],"type":"Point"}
}