{
  "type": "Feature",
  "properties": {
    "addr:full":"33 rue des Jardins 68000 Colmar Colmar Alsace 68000",
    "addr:housenumber":"33",
    "addr:postcode":"68000;68000",
    "addr:street":"Rue Des Jardins",
    "iso:country":"FR",
    "sg:address":"33 rue des Jardins 68000 Colmar",
    "sg:city":"Colmar",
    "sg:classifiers":[
        {
            "category":"Communications",
            "subcategory":"Film & Video Production",
            "type":"Services"
        }
    ],
    "sg:phone":"+33 3 89 23 73 84",
    "sg:postcode":"68000",
    "sg:province":"Alsace",
    "sg:tags":[
        "material",
        "audio-visual"
    ],
    "wof:name":"Sandvale S.a.",
    "wof:placetype":"venue"
},
  "geometry": {"coordinates":[7.372675,48.076275],"type":"Point"}
}