{
  "type": "Feature",
  "properties": {
    "addr:full":"27 ter, Rue du Progr\u00e8s, 93107 Montreuil C\u00e9dex Haute Normandie",
    "addr:housenumber":"27 ter",
    "addr:postcode":"93107",
    "addr:street":"Rue Du Progre\u0300S;Haute Normandie",
    "iso:country":"FR",
    "sg:address":"27 ter, Rue du Progr\u00e8s, 93107 Montreuil C\u00e9dex",
    "sg:orig_category":"Non-Classified Establishments",
    "sg:phone":"+33 1 48 57 36 36",
    "sg:province":"Haute Normandie",
    "wof:name":"F.s.p. S.a.r.l. - France S\u00e9curit\u00e9 Protect",
    "wof:placetype":"venue"
},
  "geometry": {"coordinates":[2.421302,48.851845],"type":"Point"}
}