{
  "type": "Feature",
  "properties": {
    "iso:country":"FR",
    "sg:address":"Lieu Dit Le Haut Bois 28330 La Bazoche Gouet",
    "sg:city":"Authon-du-Perche",
    "sg:classifiers":[
        {
            "category":"Wholesale",
            "subcategory":"Meat",
            "type":"Manufacturing & Wholesale Goods"
        }
    ],
    "sg:phone":"+33 2 37 49 35 73",
    "sg:postcode":"28330",
    "sg:province":"Centre",
    "sg:tags":[
        "food",
        "cooked",
        "product",
        "related"
    ],
    "wof:name":"Boudet Jean Paul",
    "wof:placetype":"venue"
},
  "geometry": {"coordinates":[0.94485,48.148952],"type":"Point"}
}