{
  "type": "Feature",
  "properties": {
    "addr:full":"1, Rue de Baquet, 08800 Thilay Deville Champagne 08800",
    "addr:housenumber":"1",
    "addr:postcode":"08800;08800",
    "addr:street":"Rue De Baquet;Champagne",
    "iso:country":"FR",
    "sg:address":"1, Rue de Baquet, 08800 Thilay",
    "sg:city":"Deville",
    "sg:orig_category":"BRIDES, \u00c9TRIERS, FIXATIONS DIVERSES, BOULONNERIE, FERRONNERIE, FILETAGE ET MISE EN FORME DE RONDS SE",
    "sg:phone":"+33 3 24 32 80 50",
    "sg:postcode":"08800",
    "sg:province":"Champagne",
    "wof:name":"Davreux Noizet S.a.r.l.",
    "wof:placetype":"venue"
},
  "geometry": {"coordinates":[4.80829,49.874889],"type":"Point"}
}