{
  "type": "Feature",
  "properties": {
    "iso:country":"FR",
    "sg:address":"59, Av. de la Fert\u00e9 Milon, 02600 Villers Cotter\u00eats",
    "sg:orig_category":"Unclassifiable Establishments",
    "sg:phone":"+33 3 23 96 13 06",
    "sg:province":"Picardie",
    "wof:name":"Chauvin Paul Anciens Etablissements S.a.",
    "wof:placetype":"venue"
},
  "geometry": {"coordinates":[3.095671,49.25071],"type":"Point"}
}