{
  "type": "Feature",
  "properties": {
    "addr:full":"Zone Garolor 57365 Ennery Lorraine",
    "addr:postcode":"57365",
    "addr:street":"Zone Garolor",
    "iso:country":"FR",
    "sg:address":"Zone Garolor 57365 Ennery",
    "sg:classifiers":[
        {
            "category":"Professional",
            "type":"Services"
        }
    ],
    "sg:phone":"+33 3 87 73 87 78",
    "sg:province":"Lorraine",
    "sg:tags":[
        "transport",
        "road"
    ],
    "wof:name":"Panalpina Transports Internationaux",
    "wof:placetype":"venue"
},
  "geometry": {"coordinates":[6.234967,49.206741],"type":"Point"}
}