{
  "type": "Feature",
  "properties": {
    "addr:full":"190, Rte de Valence, 38210 Vourey Rhone-Alpes",
    "addr:housenumber":"190",
    "addr:postcode":"38210",
    "addr:street":"Rte De Valence",
    "iso:country":"FR",
    "sg:address":"190, Rte de Valence, 38210 Vourey",
    "sg:orig_category":"Unclassifiable Establishments",
    "sg:phone":"+33 4 76 07 05 38",
    "sg:province":"Rhone-Alpes",
    "wof:name":"Vourey Plastiques S.a.",
    "wof:placetype":"venue"
},
  "geometry": {"coordinates":[5.518871,45.317921],"type":"Point"}
}