{
  "type": "Feature",
  "properties": {
    "addr:full":"1, Rue de l'Is\u00e8re, 38950 Saint Martin le Vinoux Rhone-Alpes 38950",
    "addr:housenumber":"1",
    "addr:postcode":"38950;38950",
    "addr:street":"Rue De L'Ise \u0300Re;Martin Le;Rhone-Alpes",
    "iso:country":"FR",
    "sg:address":"1, Rue de l'Is\u00e8re, 38950 Saint Martin le Vinoux",
    "sg:orig_category":"Non-Classified Establishments",
    "sg:phone":"+33 4 76 75 49 94",
    "sg:postcode":"38950",
    "sg:province":"Rhone-Alpes",
    "wof:name":"Act'is\u00e8re S.a.s.",
    "wof:placetype":"venue"
},
  "geometry": {"coordinates":[5.71678,45.201351],"type":"Point"}
}