{
  "type": "Feature",
  "properties": {
    "addr:full":"B.P. 2, 69881 Meyzieu C\u00e9dex^^19, Rue Honor\u00e9 de Balzac, 69330 Meyzieu Rhone-Alpes 69330",
    "addr:housenumber":"2",
    "addr:postcode":"69881;69330;69330",
    "addr:street":"B.P.;Rue Honore\u0301 De Balzac",
    "iso:country":"FR",
    "sg:address":"B.P. 2, 69881 Meyzieu C\u00e9dex^^19, Rue Honor\u00e9 de Balzac, 69330 Meyzieu",
    "sg:orig_category":"Non-Classified Establishments",
    "sg:phone":"+33 4 78 31 02 70",
    "sg:postcode":"69330",
    "sg:province":"Rhone-Alpes",
    "wof:name":"Sorotec S.a.r.l.",
    "wof:placetype":"venue"
},
  "geometry": {"coordinates":[5.00581,45.766296],"type":"Point"}
}