{
  "type": "Feature",
  "properties": {
    "addr:full":"Launay 76780 Argueil Haute Normandie 76780",
    "addr:postcode":"76780;76780",
    "addr:street":"Launay;Haute Normandie",
    "iso:country":"FR",
    "sg:address":"Launay 76780 Argueil",
    "sg:classifiers":[
        {
            "category":"Home & Garden",
            "subcategory":"Furniture",
            "type":"Retail Goods"
        }
    ],
    "sg:phone":"+33 2 32 89 97 00",
    "sg:postcode":"76780",
    "sg:province":"Haute Normandie",
    "sg:tags":[
        "household",
        "wood"
    ],
    "wof:name":"Meubles Lejeune",
    "wof:placetype":"venue"
},
  "geometry": {"coordinates":[1.49601,49.529129],"type":"Point"}
}