{
  "type": "Feature",
  "properties": {
    "addr:full":"Au Bourg Lagupie Aquitaine 47180",
    "addr:postcode":"47180",
    "iso:country":"FR",
    "sg:address":"Au Bourg",
    "sg:city":"Lagupie",
    "sg:orig_category":"Non-Classified Establishments",
    "sg:phone":"+33 5 53 94 22 54",
    "sg:postcode":"47180",
    "sg:province":"Aquitaine",
    "wof:name":"Gava Industrie S.a.r.l.",
    "wof:placetype":"venue"
},
  "geometry": {"coordinates":[0.116616,44.557217],"type":"Point"}
}