{
  "type": "Feature",
  "properties": {
    "iso:country":"FR",
    "sg:address":"180, Av. du Panorama, 72000 Le Mans",
    "sg:orig_category":"Unclassifiable Establishments",
    "sg:phone":"+33 2 43 40 22 00",
    "sg:province":"Pays de Loire",
    "wof:name":"Colitel S.a.",
    "wof:placetype":"venue"
},
  "geometry": {"coordinates":[0.21123,47.960655],"type":"Point"}
}