{
  "type": "Feature",
  "properties": {
    "iso:country":"FR",
    "sg:address":"Rue Parmentier 85110 Chantonnay",
    "sg:classifiers":[
        {
            "category":"Professional",
            "type":"Services"
        }
    ],
    "sg:phone":"+33 2 51 46 80 12",
    "sg:province":"Pays de Loire",
    "sg:tags":[
        "transport",
        "road"
    ],
    "wof:name":"Groupe Abx",
    "wof:placetype":"venue"
},
  "geometry": {"coordinates":[-1.064644,46.69112],"type":"Point"}
}