{
  "type": "Feature",
  "properties": {
    "addr:full":"48, Rue Barth\u00e9l\u00e9my Gautier, 17800 Pons Poitou-Charentes",
    "addr:housenumber":"48",
    "addr:postcode":"17800",
    "addr:street":"Rue Barthe\u0301Le\u0301My Gautier",
    "iso:country":"FR",
    "sg:address":"48, Rue Barth\u00e9l\u00e9my Gautier, 17800 Pons",
    "sg:orig_category":"Non-Classified Establishments",
    "sg:phone":"+33 5 46 96 14 44",
    "sg:province":"Poitou-Charentes",
    "wof:name":"Sobeca - Soci\u00e9t\u00e9 Beaujolaise Canalisation",
    "wof:placetype":"venue"
},
  "geometry": {"coordinates":[-0.59809,45.51733],"type":"Point"}
}