{
  "type": "Feature",
  "properties": {
    "addr:full":"15 rue de la Branche 71230 ST VALLIER Saint-Romain-sous-Gourdon Bourgogne 71230",
    "addr:housenumber":"15",
    "addr:postcode":"71230;71230",
    "addr:street":"Rue De La Branche",
    "iso:country":"FR",
    "sg:address":"15 rue de la Branche 71230 ST VALLIER",
    "sg:city":"Saint-Romain-sous-Gourdon",
    "sg:classifiers":[
        {
            "category":"Building & Trades",
            "subcategory":"Pest Control",
            "type":"Services"
        }
    ],
    "sg:phone":"+33 3 85 69 07 50",
    "sg:postcode":"71230",
    "sg:province":"Bourgogne",
    "sg:tags":[
        "brand",
        "image"
    ],
    "wof:name":"Assistance Et Gestion A L Exportation S.a.r.l",
    "wof:placetype":"venue"
},
  "geometry": {"coordinates":[4.34046,46.64624],"type":"Point"}
}