{
  "type": "Feature",
  "properties": {
    "iso:country":"FR",
    "sg:address":"1, Rue Mansard, 83100 Toulon",
    "sg:orig_category":"Unclassifiable Establishments",
    "sg:phone":"+33 4 98 00 13 00",
    "sg:province":"Bourgogne",
    "wof:name":"Imprimerie Marim S.a.r.l.",
    "wof:placetype":"venue"
},
  "geometry": {"coordinates":[5.968749,43.125607],"type":"Point"}
}