{
  "type": "Feature",
  "properties": {
    "iso:country":"FR",
    "sg:address":"Rue du Commerce - Zone Industrielle",
    "sg:city":"Fegersheim",
    "sg:orig_category":"Unclassifiable Establishments",
    "sg:phone":"+33 3 88 64 02 00",
    "sg:postcode":"67640",
    "sg:province":"Alsace",
    "wof:name":"Kernst S.a.",
    "wof:placetype":"venue"
},
  "geometry": {"coordinates":[7.679595,48.489704],"type":"Point"}
}