{
  "type": "Feature",
  "properties": {
    "addr:full":"Le Four a Chaux 69380 Marcilly d'Azergues Rhone-Alpes 69380",
    "addr:postcode":"69380;69380",
    "addr:street":"Chaux;Rhone-Alpes",
    "iso:country":"FR",
    "sg:address":"Le Four a Chaux 69380 Marcilly d'Azergues",
    "sg:classifiers":[
        {
            "category":"Food & Beverages",
            "subcategory":"Fruits & Vegetables",
            "type":"Retail Goods"
        }
    ],
    "sg:phone":"+33 4 78 43 62 61",
    "sg:postcode":"69380",
    "sg:province":"Rhone-Alpes",
    "wof:name":"Les Vergers Des Monts D'or S.a.r.l.",
    "wof:placetype":"venue"
},
  "geometry": {"coordinates":[4.72745,45.871712],"type":"Point"}
}