{
  "type": "Feature",
  "properties": {
    "iso:country":"FR",
    "sg:address":"Parc d'Activit\u00e9s les 4 Routes, 35390 Grand Fougeray C\u00e9dex^^Parc d'Activit\u00e9s les 4 Routes, 35390 Gran",
    "sg:city":"Grand-Fougeray",
    "sg:orig_category":"Non-Classified Establishments",
    "sg:phone":"+33 2 99 08 48 59",
    "sg:postcode":"35390",
    "sg:province":"Bretagne",
    "wof:name":"Lodi S.a.",
    "wof:placetype":"venue"
},
  "geometry": {"coordinates":[-1.822934,47.723373],"type":"Point"}
}