{
  "type": "Feature",
  "properties": {
    "iso:country":"FR",
    "sg:address":"75, Rue Jules Guesde, 92532 Levallois Perret C\u00e9dex",
    "sg:orig_category":"Non-Classified Establishments",
    "sg:phone":"+33 1 41 27 92 93",
    "sg:province":"Languedoc-Roussillon",
    "wof:name":"Aspitec S.a.r.l.",
    "wof:placetype":"venue"
},
  "geometry": {"coordinates":[2.290717,48.895149],"type":"Point"}
}