{
  "type": "Feature",
  "properties": {
    "iso:country":"FR",
    "sg:address":"12, Rue Joliot Curie, 37550 Saint Avertin",
    "sg:city":"Saint-Avertin",
    "sg:orig_category":"Unclassifiable Establishments",
    "sg:phone":"+33 2 47 28 39 47",
    "sg:postcode":"37550",
    "sg:province":"Centre",
    "wof:name":"Tecm\u00e9ca S.a.r.l.",
    "wof:placetype":"venue"
},
  "geometry": {"coordinates":[0.732937,47.346638],"type":"Point"}
}