{
  "type": "Feature",
  "properties": {
    "addr:full":"2 rue de la Pature 78420 Carrieres Sur Seine Ile de France 78420",
    "addr:housenumber":"2",
    "addr:postcode":"78420;78420",
    "addr:street":"Rue De La Pature;Carrieres;Seine;France",
    "iso:country":"FR",
    "sg:address":"2 rue de la Pature 78420 Carrieres Sur Seine",
    "sg:classifiers":[
        {
            "category":"Banks & Credit Unions",
            "subcategory":"Investment Brokerage",
            "type":"Services"
        }
    ],
    "sg:phone":"+33 1 30 86 66 66",
    "sg:postcode":"78420",
    "sg:province":"Ile de France",
    "sg:tags":[
        "filter",
        "hydraulic"
    ],
    "wof:name":"Le Bozec Filtration Et Systemes Sa",
    "wof:placetype":"venue"
},
  "geometry": {"coordinates":[2.19641,48.915291],"type":"Point"}
}