{
  "type": "Feature",
  "properties": {
    "iso:country":"FR",
    "sg:address":"12 Avenue De La Division Leclerc 92160 Antony",
    "sg:classifiers":[
        {
            "category":"Banks & Credit Unions",
            "subcategory":"Bureau De Change",
            "type":"Services"
        }
    ],
    "sg:phone":"+33 1 46 66 02 60",
    "sg:postcode":"92160",
    "sg:province":"Ile de France",
    "sg:tags":[
        "leather",
        "good",
        "shoe"
    ],
    "wof:name":"Chaussures Deshays",
    "wof:placetype":"venue"
},
  "geometry": {"coordinates":[2.3046,48.752178],"type":"Point"}
}