{
  "type": "Feature",
  "properties": {
    "iso:country":"FR",
    "sg:address":"14 Rue Moli\u00e8re 09300 Lavelanet",
    "sg:classifiers":[
        {
            "category":"Shopping",
            "subcategory":"Crafts & Fabrics",
            "type":"Retail Goods"
        }
    ],
    "sg:phone":"+33 5 61 01 15 81",
    "sg:postcode":"09300",
    "sg:province":"Midi Pyr\u00e9n\u00e9es",
    "sg:tags":[
        "textile",
        "clothing"
    ],
    "wof:name":"Ets Roger Canals Textiles Sarl",
    "wof:placetype":"venue"
},
  "geometry": {"coordinates":[1.839012,42.931007],"type":"Point"}
}