{
  "type": "Feature",
  "properties": {
    "iso:country":"FR",
    "sg:address":"2208 Rte De Grasse 06600 Antibes",
    "sg:classifiers":[
        {
            "category":"Shopping",
            "subcategory":"Hobbies, Toys, & Games",
            "type":"Retail Goods"
        }
    ],
    "sg:phone":"+33 4 93 74 17 63",
    "sg:province":"Rhone-Alpes",
    "sg:tags":[
        "product",
        "miscellaneous",
        "entertainment"
    ],
    "wof:name":"Giftoys Sa",
    "wof:placetype":"venue"
},
  "geometry": {"coordinates":[7.087384,43.598824],"type":"Point"}
}