{
  "type": "Feature",
  "properties": {
    "iso:country":"FR",
    "sg:address":"16 bis",
    "sg:city":"Sextius; Aix en Provence",
    "sg:classifiers":[
        {
            "category":"Banks & Credit Unions",
            "subcategory":"Bank",
            "type":"Services"
        }
    ],
    "sg:phone":"+33 3342160050",
    "sg:province":"Nord Pas-de-Calais",
    "wof:name":"Cr\u00e9dit Du Nord",
    "wof:placetype":"venue"
},
  "geometry": {"coordinates":[5.443545,43.528641],"type":"Point"}
}