{
  "type": "Feature",
  "properties": {
    "addr:full":"Espace le Triangle Vienne C\u00e9dex Bretagne 38216",
    "addr:postcode":"38216",
    "addr:street":"Ce\u0301Dex",
    "iso:country":"FR",
    "sg:address":"Espace le Triangle",
    "sg:city":"Vienne C\u00e9dex",
    "sg:orig_category":"Non-Classified Establishments",
    "sg:phone":"+33 4 74 53 00 28",
    "sg:postcode":"38216",
    "sg:province":"Bretagne",
    "wof:name":"Imprimerie De La Tour S.a.",
    "wof:placetype":"venue"
},
  "geometry": {"coordinates":[4.87828,45.52422],"type":"Point"}
}