{
  "type": "Feature",
  "properties": {
    "iso:country":"FR",
    "sg:address":"B.P. 6",
    "sg:city":"Vivy C\u00e9dex^^Le Ciron 49680 Vivy",
    "sg:orig_category":"Non-Classified Establishments",
    "sg:phone":"+33 2 41 52 51 71",
    "sg:postcode":"49680",
    "sg:province":"Pays de Loire",
    "wof:name":"Terreaux De France Falienor S.a.",
    "wof:placetype":"venue"
},
  "geometry": {"coordinates":[-0.057519,47.327534],"type":"Point"}
}