{
  "type": "Feature",
  "properties": {
    "iso:country":"FR",
    "sg:address":"8 Chem De G\u00e9nas 69800 St Priest",
    "sg:classifiers":[
        {
            "category":"Shopping",
            "subcategory":"Computers & Home Electronics",
            "type":"Retail Goods"
        }
    ],
    "sg:phone":"+33 4 78 90 32 88",
    "sg:postcode":"69800",
    "sg:province":"Rhone-Alpes",
    "sg:tags":[
        "electronic",
        "electrical",
        "equipment"
    ],
    "wof:name":"Cel (constructions Electriques Lyonnaises)",
    "wof:placetype":"venue"
},
  "geometry": {"coordinates":[4.970898,45.719868],"type":"Point"}
}