{
  "type": "Feature",
  "properties": {
    "iso:country":"FR",
    "sg:address":"Grand Moulinet 33500 Pomerol",
    "sg:city":"Pomerol",
    "sg:orig_category":"Unclassifiable Establishments",
    "sg:phone":"+33 5 57 51 10 41",
    "sg:postcode":"33500",
    "sg:province":"Aquitaine",
    "wof:name":"Garde Jean-marie",
    "wof:placetype":"venue"
},
  "geometry": {"coordinates":[-0.223674,44.934345],"type":"Point"}
}