{
  "type": "Feature",
  "properties": {
    "addr:full":"B.P. 7 Sarbazan Aquitaine 40120",
    "addr:postcode":"40120",
    "addr:street":"B.P. 7 Sarbazan",
    "iso:country":"FR",
    "sg:address":"B.P. 7",
    "sg:city":"Sarbazan",
    "sg:orig_category":"Non-Classified Establishments",
    "sg:phone":"+33 5 58 45 53 04",
    "sg:postcode":"40120",
    "sg:province":"Aquitaine",
    "wof:name":"Galvalandes S.a.",
    "wof:placetype":"venue"
},
  "geometry": {"coordinates":[-0.274254,43.9515],"type":"Point"}
}