{
  "type": "Feature",
  "properties": {
    "iso:country":"FR",
    "sg:address":"Rue Santos Dumont Zin D Arsonval 86102 Chatellerault Cedex",
    "sg:classifiers":[
        {
            "category":"Wholesale",
            "subcategory":"Medical Equipment & Supplies",
            "type":"Manufacturing & Wholesale Goods"
        }
    ],
    "sg:phone":"+33 5 49 20 01 01",
    "sg:province":"Poitou-Charentes",
    "sg:tags":[
        "instrument",
        "health",
        "-",
        "precision"
    ],
    "wof:name":"Tricotage Elastique Et Medical Societe Anonyme (tem)",
    "wof:placetype":"venue"
},
  "geometry": {"coordinates":[0.54494,46.819901],"type":"Point"}
}