{
  "type": "Feature",
  "properties": {
    "iso:country":"FR",
    "sg:address":"25/27, Rue Andr\u00e9 Citro\u00ebn, 95130 Franconville",
    "sg:orig_category":"Unclassifiable Establishments",
    "sg:phone":"+33 1 30 72 47 23",
    "sg:province":"Ile de France",
    "wof:name":"Etablissements Ren\u00e9 Elbhar S.a.r.l.",
    "wof:placetype":"venue"
},
  "geometry": {"coordinates":[2.210145,48.989754],"type":"Point"}
}