{
  "type": "Feature",
  "properties": {
    "addr:full":"ZI Beaurains Nord Pas-de-Calais 62217",
    "addr:postcode":"62217",
    "addr:street":"Pas-De-Calais",
    "iso:country":"FR",
    "sg:address":"ZI",
    "sg:city":"Beaurains",
    "sg:orig_category":"Non-Classified Establishments",
    "sg:phone":"+33 3 21 73 27 70",
    "sg:postcode":"62217",
    "sg:province":"Nord Pas-de-Calais",
    "wof:name":"Gaudry Serge S.a.",
    "wof:placetype":"venue"
},
  "geometry": {"coordinates":[2.757345,50.273754],"type":"Point"}
}