{
  "type": "Feature",
  "properties": {
    "iso:country":"FR",
    "sg:address":"B.P. 117, 47400 Tonneins C\u00e9dex^^Place de la Manufacture, 47400 Tonneins",
    "sg:city":"Tonneins",
    "sg:orig_category":"Non-Classified Establishments",
    "sg:phone":"+33 5 53 88 33 20",
    "sg:postcode":"47400",
    "sg:province":"Aquitaine",
    "wof:name":"Altadis",
    "wof:placetype":"venue"
},
  "geometry": {"coordinates":[0.319993,44.345749],"type":"Point"}
}