{
  "type": "Feature",
  "properties": {
    "iso:country":"FR",
    "sg:address":"Rue Du Saut Du Li\u00e8vre Zi 77130 Montereau Fault Yonne",
    "sg:classifiers":[
        {
            "category":"Building & Trades",
            "subcategory":"Construction",
            "type":"Services"
        }
    ],
    "sg:phone":"+33 1 64 32 81 40",
    "sg:postcode":"77130",
    "sg:province":"Ile de France",
    "sg:tags":[
        "work",
        "public"
    ],
    "wof:name":"Etpi (entreprise De Travaux Publics Et Industriels)",
    "wof:placetype":"venue"
},
  "geometry": {"coordinates":[2.891333,48.303902],"type":"Point"}
}