{
  "type": "Feature",
  "properties": {
    "iso:country":"FR",
    "sg:address":"ZI 85390 Chavagnes Les Redoux",
    "sg:orig_category":"Special Cases",
    "sg:phone":"+33 2 51 93 11 64",
    "sg:province":"Pays de Loire",
    "wof:name":"So.ve.ce Sa",
    "wof:placetype":"venue"
},
  "geometry": {"coordinates":[-0.805454,46.644264],"type":"Point"}
}