{
  "type": "Feature",
  "properties": {
    "addr:full":"152 Av Des Champs Elys\u00e9es 75008 Paris Ile de France 75008",
    "addr:postcode":"75008;75008",
    "addr:street":"152 Av Des Champs Elyse\u0301Es",
    "iso:country":"FR",
    "sg:address":"152 Av Des Champs Elys\u00e9es 75008 Paris",
    "sg:classifiers":[
        {
            "category":"Banks & Credit Unions",
            "subcategory":"Investment Brokerage",
            "type":"Services"
        }
    ],
    "sg:phone":"+33 1 44 13 44 13",
    "sg:postcode":"75008",
    "sg:province":"Ile de France",
    "sg:tags":[
        "product",
        "finance",
        "food",
        "drink",
        "related",
        "institution",
        "banking",
        "insurance"
    ],
    "wof:name":"Cointreau Sa",
    "wof:placetype":"venue"
},
  "geometry": {"coordinates":[2.297585,48.873089],"type":"Point"}
}