{
  "type": "Feature",
  "properties": {
    "addr:full":"Rue du Pr\u00e9sident Kennedy Notre Dame de Gravenchon Haute Normandie 76330",
    "addr:postcode":"76330",
    "addr:street":"Rue Du Pre\u0301Sident Kennedy Notre",
    "iso:country":"FR",
    "sg:address":"Rue du Pr\u00e9sident Kennedy",
    "sg:city":"Notre Dame de Gravenchon",
    "sg:orig_category":"Non-Classified Establishments",
    "sg:phone":"+33 2 35 39 53 53",
    "sg:postcode":"76330",
    "sg:province":"Haute Normandie",
    "wof:name":"Soci\u00e9t\u00e9 Nouvelle De Transports Industriels S.a.",
    "wof:placetype":"venue"
},
  "geometry": {"coordinates":[0.556896,49.483383],"type":"Point"}
}