{
  "type": "Feature",
  "properties": {
    "iso:country":"FR",
    "sg:address":"2, Rue Jean Baptiste Dumaire - Parc Industriel Sud - ZI Edison, 57200 Sarreguemines",
    "sg:orig_category":"Unclassifiable Establishments",
    "sg:phone":"+33 3 87 95 34 99",
    "sg:province":"Lorraine",
    "wof:name":"B.o.a. Technology S.a.r.l.",
    "wof:placetype":"venue"
},
  "geometry": {"coordinates":[7.093455,49.102795],"type":"Point"}
}