{
  "type": "Feature",
  "properties": {
    "iso:country":"FR",
    "sg:address":"ZI du Solier",
    "sg:city":"Duni\u00e8res",
    "sg:orig_category":"Unclassifiable Establishments",
    "sg:phone":"+33 4 71 66 82 44",
    "sg:postcode":"43220",
    "sg:province":"Auvergne",
    "wof:name":"Moulinage Du Solier S.a.r.l.",
    "wof:placetype":"venue"
},
  "geometry": {"coordinates":[4.343615,45.216541],"type":"Point"}
}