{
  "type": "Feature",
  "properties": {
    "addr:full":"Boisthorel 61270 RAI Rai Basse Normandie 61270",
    "addr:postcode":"61270;61270",
    "addr:street":"Boisthorel",
    "iso:country":"FR",
    "sg:address":"Boisthorel 61270 RAI",
    "sg:city":"Rai",
    "sg:classifiers":[
        {
            "category":"Shopping",
            "subcategory":"Crafts & Fabrics",
            "type":"Retail Goods"
        }
    ],
    "sg:phone":"+33 2 33 84 11 80",
    "sg:postcode":"61270",
    "sg:province":"Basse Normandie",
    "sg:tags":[
        "synthetic",
        "fabrics",
        "plastic"
    ],
    "wof:name":"Rai-tilli\u00e8res Sas",
    "wof:placetype":"venue"
},
  "geometry": {"coordinates":[0.572107,48.749886],"type":"Point"}
}