{
  "type": "Feature",
  "properties": {
    "iso:country":"FR",
    "sg:address":"All\u00e9e des 5 Chemins",
    "sg:city":"Briouze",
    "sg:orig_category":"Unclassifiable Establishments",
    "sg:phone":"+33 2 33 65 29 22",
    "sg:postcode":"61220",
    "sg:province":"Basse Normandie",
    "wof:name":"Amcap S.a.r.l.",
    "wof:placetype":"venue"
},
  "geometry": {"coordinates":[-0.456955,48.649422],"type":"Point"}
}