{
  "type": "Feature",
  "properties": {
    "addr:full":"All\u00e9e des 5 Chemins Briouze Basse Normandie 61220",
    "addr:postcode":"61220",
    "addr:street":"Alle\u0301E Des 5 Chemins;Basse",
    "iso:country":"FR",
    "sg:address":"All\u00e9e des 5 Chemins",
    "sg:city":"Briouze",
    "sg:orig_category":"Unclassifiable Establishments",
    "sg:phone":"+33 2 33 65 29 22",
    "sg:postcode":"61220",
    "sg:province":"Basse Normandie",
    "wof:name":"Amcap S.a.r.l.",
    "wof:placetype":"venue"
},
  "geometry": {"coordinates":[-0.456955,48.649422],"type":"Point"}
}