{
  "type": "Feature",
  "properties": {
    "iso:country":"FR",
    "sg:address":"168, Rte de Paris, 76240 Le Mesnil Esnard",
    "sg:orig_category":"EMBALLAGES POUR L'ALIMENTATION ET LES INDUSTRIES TRANSFORMATION DE PAPIER PARAFFIN\u00c9 d\u00e9coupe \u00e0 fa\u00e7on ",
    "sg:phone":"+33 2 35 80 15 11",
    "sg:postcode":"76240",
    "sg:province":"Haute Normandie",
    "wof:name":"D\u00e9catoire S.a.r.l.",
    "wof:placetype":"venue"
},
  "geometry": {"coordinates":[1.134787,49.415588],"type":"Point"}
}