{
  "type": "Feature",
  "properties": {
    "addr:full":"5, Av. Gutenberg - ZA Pariwest, 78310 Maurepas Ile de France",
    "addr:postcode":"78310;ile",
    "addr:street":"Av. Gutenberg Za Pariwest",
    "iso:country":"FR",
    "sg:address":"5, Av. Gutenberg - ZA Pariwest, 78310 Maurepas",
    "sg:orig_category":"Unclassifiable Establishments",
    "sg:phone":"+33 1 34 82 77 40",
    "sg:province":"Ile de France",
    "wof:name":"Groupe Adage S.a.",
    "wof:placetype":"venue"
},
  "geometry": {"coordinates":[1.944855,48.761749],"type":"Point"}
}