{
  "type": "Feature",
  "properties": {
    "addr:full":"Caphar 79250 les Aubiers Poitou-Charentes",
    "addr:postcode":"79250",
    "addr:street":"Caphar;Aubiers",
    "iso:country":"FR",
    "sg:address":"Caphar 79250 les Aubiers",
    "sg:orig_category":"Unclassifiable Establishments",
    "sg:phone":"+33 5 49 65 63 55",
    "sg:province":"Poitou-Charentes",
    "wof:name":"O.n.i. S.a.r.l. - Ouest N\u00e9goce International",
    "wof:placetype":"venue"
},
  "geometry": {"coordinates":[-0.591334,46.951263],"type":"Point"}
}