{
  "type": "Feature",
  "properties": {
    "addr:full":"50, Rue Bernard Palissy - ZAL du Grand Mont, 62750 Loos en Gohelle Nord Pas-de-Calais",
    "addr:housenumber":"50",
    "addr:postcode":"62750",
    "addr:street":"Rue Bernard Palissy;Du Grand Mont",
    "iso:country":"FR",
    "sg:address":"50, Rue Bernard Palissy - ZAL du Grand Mont, 62750 Loos en Gohelle",
    "sg:orig_category":"Unclassifiable Establishments",
    "sg:phone":"+33 3 21 69 80 10",
    "sg:province":"Nord Pas-de-Calais",
    "wof:name":"C.b.s. S.a. - Claude Benet Serigraphie",
    "wof:placetype":"venue"
},
  "geometry": {"coordinates":[2.798195,50.449741],"type":"Point"}
}