{
  "type": "Feature",
  "properties": {
    "addr:full":"12200 Morlhon le Haut Midi Pyr\u00e9n\u00e9es",
    "addr:housenumber":"12200",
    "addr:street":"Morlhon",
    "iso:country":"FR",
    "sg:address":"12200 Morlhon le Haut",
    "sg:orig_category":"Unclassifiable Establishments",
    "sg:phone":"+33 5 65 29 95 88",
    "sg:province":"Midi Pyr\u00e9n\u00e9es",
    "wof:name":"Altec S.a.",
    "wof:placetype":"venue"
},
  "geometry": {"coordinates":[2.062735,44.324635],"type":"Point"}
}