{
  "type": "Feature",
  "properties": {
    "iso:country":"FR",
    "sg:address":"2, Lotissement le Vieux Fr\u00eane, 34570 Montarnaud",
    "sg:orig_category":"Non-Classified Establishments",
    "sg:phone":"+33 4 67 47 19 99",
    "sg:postcode":"34570",
    "sg:province":"Languedoc-Roussillon",
    "wof:name":"Cabinet Jean Vasquez S.a.r.l.",
    "wof:placetype":"venue"
},
  "geometry": {"coordinates":[3.75978,43.583614],"type":"Point"}
}