{
  "type": "Feature",
  "properties": {
    "addr:full":"43 rue G\u00e9n\u00e9ral de Gaulle; Bernay Champagne",
    "addr:housenumber":"43",
    "addr:street":"Rue Ge\u0301Ne\u0301Ral De Gaulle",
    "iso:country":"FR",
    "sg:address":"43 rue G\u00e9n\u00e9ral de Gaulle; Bernay",
    "sg:classifiers":[
        {
            "category":"Banks & Credit Unions",
            "subcategory":"Bank",
            "type":"Services"
        }
    ],
    "sg:phone":"+33 32435103",
    "sg:province":"Champagne",
    "wof:name":"Cr\u00e9dit Mutuel",
    "wof:placetype":"venue"
},
  "geometry": {"coordinates":[0.594909,49.089352],"type":"Point"}
}