{
  "type": "Feature",
  "properties": {
    "addr:full":"Vers la fabrique 01430 MAILLAT Rhone-Alpes 01430",
    "addr:postcode":"01430;01430",
    "addr:street":"Vers La Fabrique",
    "iso:country":"FR",
    "sg:address":"Vers la fabrique 01430 MAILLAT",
    "sg:classifiers":[
        {
            "category":"Manufacturing",
            "subcategory":"Rubber & Plastics",
            "type":"Manufacturing & Wholesale Goods"
        }
    ],
    "sg:phone":"+33 4 74 75 70 70",
    "sg:postcode":"01430",
    "sg:province":"Rhone-Alpes",
    "sg:tags":[
        "packaging",
        "mean"
    ],
    "wof:name":"Form'ain Sa",
    "wof:placetype":"venue"
},
  "geometry": {"coordinates":[5.5448,46.098789],"type":"Point"}
}