{
  "type": "Feature",
  "properties": {
    "iso:country":"FR",
    "sg:address":"B.P. 16, 01580 Izernore C\u00e9dex^^La Mode, 01580 Izernore",
    "sg:orig_category":"Non-Classified Establishments",
    "sg:phone":"+33 4 74 76 90 76",
    "sg:postcode":"01580",
    "sg:province":"Rhone-Alpes",
    "wof:name":"C.u.d.i. S.a.r.l.",
    "wof:placetype":"venue"
},
  "geometry": {"coordinates":[5.54865,46.236309],"type":"Point"}
}