{
  "type": "Feature",
  "properties": {
    "addr:full":"Rte de Br\u00e9duire Villard de Lans Rhone-Alpes 38250",
    "addr:postcode":"38250",
    "addr:street":"Rte De Bre\u0301Duire;Rhone-Alpes",
    "iso:country":"FR",
    "sg:address":"Rte de Br\u00e9duire",
    "sg:city":"Villard de Lans",
    "sg:orig_category":"Unclassifiable Establishments",
    "sg:phone":"+33 4 76 95 58 32",
    "sg:postcode":"38250",
    "sg:province":"Rhone-Alpes",
    "wof:name":"Entreprise Bonnard E.u.r.l.",
    "wof:placetype":"venue"
},
  "geometry": {"coordinates":[5.546885,45.07341],"type":"Point"}
}