{
  "type": "Feature",
  "properties": {
    "addr:full":"83, Rue de la P\u00e2le, 25230 Seloncourt Franche Comt\u00e9",
    "addr:housenumber":"83",
    "addr:postcode":"25230",
    "addr:street":"Rue De La Pa\u0302Le;Franche Comte\u0301",
    "iso:country":"FR",
    "sg:address":"83, Rue de la P\u00e2le, 25230 Seloncourt",
    "sg:orig_category":"Unclassifiable Establishments",
    "sg:phone":"+33 3 81 36 33 40",
    "sg:province":"Franche Comt\u00e9",
    "wof:name":"Sigeb S.a.",
    "wof:placetype":"venue"
},
  "geometry": {"coordinates":[6.85134,47.466614],"type":"Point"}
}