{
  "type": "Feature",
  "properties": {
    "addr:full":"434 R Des Sarazins Zi Les Fourmis 74130 Bonneville Rhone-Alpes 74130",
    "addr:housenumber":"434",
    "addr:postcode":"74130;74130",
    "addr:street":"R Des Sarazins Zi Les Fourmis",
    "iso:country":"FR",
    "sg:address":"434 R Des Sarazins Zi Les Fourmis 74130 Bonneville",
    "sg:classifiers":[
        {
            "category":"Manufacturing",
            "subcategory":"Rubber & Plastics",
            "type":"Manufacturing & Wholesale Goods"
        }
    ],
    "sg:phone":"+33 4 50 97 43 33",
    "sg:postcode":"74130",
    "sg:province":"Rhone-Alpes",
    "sg:tags":[
        "packaging",
        "material",
        "-"
    ],
    "wof:name":"M. Cetinkaya Hasan Hcp",
    "wof:placetype":"venue"
},
  "geometry": {"coordinates":[6.388322,45.95652],"type":"Point"}
}