{
  "type": "Feature",
  "properties": {
    "iso:country":"FR",
    "sg:address":"ZAC les Dineux",
    "sg:city":"Tr\u00e9meur",
    "sg:orig_category":"Non-Classified Establishments",
    "sg:phone":"+33 2 96 84 65 55",
    "sg:postcode":"22250",
    "sg:province":"Bretagne",
    "wof:name":"Itek S.a.",
    "wof:placetype":"venue"
},
  "geometry": {"coordinates":[-2.263419,48.347321],"type":"Point"}
}