{
  "type": "Feature",
  "properties": {
    "addr:full":"191 rue France; Nice Aquitaine",
    "addr:housenumber":"191",
    "addr:street":"Rue France",
    "iso:country":"FR",
    "sg:address":"191 rue France; Nice",
    "sg:classifiers":[
        {
            "category":"Banks & Credit Unions",
            "subcategory":"Bank",
            "type":"Services"
        }
    ],
    "sg:phone":"+33 3393375200",
    "sg:province":"Aquitaine",
    "wof:name":"Cr\u00e9dit Lyonnais, Agence Magnan",
    "wof:placetype":"venue"
},
  "geometry": {"coordinates":[7.24565,43.691391],"type":"Point"}
}