{
  "type": "Feature",
  "properties": {
    "iso:country":"FR",
    "sg:address":"quai Jean Jaur\u00e8s 07800 LA VOULTE SUR RHONE",
    "sg:classifiers":[
        {
            "category":"Professional",
            "subcategory":"Engineering",
            "type":"Services"
        }
    ],
    "sg:phone":"+33 4 75 85 13 13",
    "sg:postcode":"07800",
    "sg:province":"Rhone-Alpes",
    "sg:tags":[
        "process",
        "control",
        "technology"
    ],
    "wof:name":"Euro C\u00e2blage Sa",
    "wof:placetype":"venue"
},
  "geometry": {"coordinates":[4.790153,44.807415],"type":"Point"}
}