{
  "type": "Feature",
  "properties": {
    "iso:country":"FR",
    "sg:address":"Les Plots 07380 Prades",
    "sg:classifiers":[
        {
            "category":"Professional",
            "subcategory":"Engineering",
            "type":"Services"
        }
    ],
    "sg:phone":"+33 4 75 94 31 75",
    "sg:postcode":"07380",
    "sg:province":"Rhone-Alpes",
    "sg:tags":[
        "machine",
        "-",
        "environment",
        "equipment",
        "machinery",
        "mechanical"
    ],
    "wof:name":"Societe D'exploitation Des Etablissements Plancher",
    "wof:placetype":"venue"
},
  "geometry": {"coordinates":[4.320925,44.644325],"type":"Point"}
}