{
  "type": "Feature",
  "properties": {
    "addr:full":"B.P. 26, 13728 Marignane C\u00e9dex^^A\u00e9roport Marseille Provence, 13700 Marignane Poitou-Charentes",
    "addr:postcode":"13728;13700",
    "addr:street":"B.P. 26;Ce\u0301Dex^^Ae\u0301Roport",
    "iso:country":"FR",
    "sg:address":"B.P. 26, 13728 Marignane C\u00e9dex^^A\u00e9roport Marseille Provence, 13700 Marignane",
    "sg:orig_category":"Non-Classified Establishments",
    "sg:phone":"+33 4 42 14 26 13",
    "sg:province":"Poitou-Charentes",
    "wof:name":"Olympic Airways",
    "wof:placetype":"venue"
},
  "geometry": {"coordinates":[5.21421,43.418041],"type":"Point"}
}