{
  "type": "Feature",
  "properties": {
    "iso:country":"FR",
    "sg:address":"24 Ch De Vauldy 10000 Troyes",
    "sg:classifiers":[
        {
            "category":"Food & Beverages",
            "subcategory":"Groceries & Convenience Stores",
            "type":"Retail Goods"
        }
    ],
    "sg:phone":"+33 3 25 71 19 19",
    "sg:postcode":"10000",
    "sg:province":"Champagne",
    "sg:tags":[
        "product",
        "grain",
        "cereal",
        "related"
    ],
    "wof:name":"Inter Meunerie Sa",
    "wof:placetype":"venue"
},
  "geometry": {"coordinates":[4.074345,48.297874],"type":"Point"}
}