{
  "type": "Feature",
  "properties": {
    "iso:country":"FR",
    "sg:address":"262 rue du Faubourg Saint Honore; PARIS; 75008",
    "sg:classifiers":[
        {
            "category":"Shopping",
            "subcategory":"Computers & Home Electronics",
            "type":"Retail Goods"
        }
    ],
    "sg:phone":"+33 1 53 89 11 00",
    "sg:postcode":"75008",
    "sg:province":"Ile de France",
    "sg:tags":[
        "chamber",
        "commerce"
    ],
    "wof:name":"Chambre De Commerce Franco-americaine",
    "wof:placetype":"venue"
},
  "geometry": {"coordinates":[2.299868,48.877399],"type":"Point"}
}