{
  "type": "Feature",
  "properties": {
    "iso:country":"FR",
    "sg:address":"23 Rue De Mulhouse 90000 Belfort",
    "sg:classifiers":[
        {
            "category":"Professional",
            "subcategory":"Business Services",
            "type":"Services"
        }
    ],
    "sg:phone":"+33 3 84 22 08 08",
    "sg:postcode":"90000",
    "sg:province":"Franche Comt\u00e9",
    "sg:tags":[
        "body",
        "advice"
    ],
    "wof:name":"Femmes Actives Association",
    "wof:placetype":"venue"
},
  "geometry": {"coordinates":[6.853319,47.642879],"type":"Point"}
}