{
  "type": "Feature",
  "properties": {
    "addr:full":"39 Rte Dole 39120 Le Deschaux Franche Comt\u00e9 39120",
    "addr:housenumber":"39",
    "addr:postcode":"39120;39120",
    "addr:street":"Rte Dole;Franche Comte\u0301",
    "iso:country":"FR",
    "sg:address":"39 Rte Dole 39120 Le Deschaux",
    "sg:orig_category":"Drinks Food and Related Products Wood Wood and Furniture",
    "sg:phone":"+33 3 84 71 51 00",
    "sg:postcode":"39120",
    "sg:province":"Franche Comt\u00e9",
    "wof:name":"Etablissements Prost-magnin Pere Et Fils Sarl",
    "wof:placetype":"venue"
},
  "geometry": {"coordinates":[5.502217,46.95253],"type":"Point"}
}