{
  "type": "Feature",
  "properties": {
    "addr:full":"17, Rue C\u00e9sar Bertholon, 42800 Rive de Gier Rhone-Alpes",
    "addr:housenumber":"17",
    "addr:postcode":"42800",
    "addr:street":"Rue Ce\u0301Sar Bertholon;Rhone-Alpes",
    "iso:country":"FR",
    "sg:address":"17, Rue C\u00e9sar Bertholon, 42800 Rive de Gier",
    "sg:orig_category":"Non-Classified Establishments",
    "sg:phone":"+33 4 77 75 04 65",
    "sg:province":"Rhone-Alpes",
    "wof:name":"A.m.e. S.a. - Atelier De M\u00e9canique D'egarande",
    "wof:placetype":"venue"
},
  "geometry": {"coordinates":[4.610043,45.522762],"type":"Point"}
}