{
  "type": "Feature",
  "properties": {
    "addr:full":"6 Rue Des Bateliers 57950 Montigny Les Metz Ile de France",
    "addr:housenumber":"6",
    "addr:postcode":"57950",
    "addr:street":"Rue Des Bateliers",
    "iso:country":"FR",
    "sg:address":"6 Rue Des Bateliers 57950 Montigny Les Metz",
    "sg:classifiers":[
        {
            "category":"Shopping",
            "subcategory":"Computers & Home Electronics",
            "type":"Retail Goods"
        }
    ],
    "sg:phone":"+33 3 87 65 72 15",
    "sg:province":"Ile de France",
    "sg:tags":[
        "electronic",
        "electrical",
        "equipment"
    ],
    "wof:name":"Sa Sofiferm",
    "wof:placetype":"venue"
},
  "geometry": {"coordinates":[6.148067,49.107635],"type":"Point"}
}