{
  "type": "Feature",
  "properties": {
    "iso:country":"FR",
    "sg:address":"1 Rte St Am\u00e9 Za Champs De L'Etraye 88120 Cleurie",
    "sg:classifiers":[
        {
            "category":"Shopping",
            "subcategory":"Computers & Home Electronics",
            "type":"Retail Goods"
        }
    ],
    "sg:phone":"+33 3 29 28 88 88",
    "sg:postcode":"88120",
    "sg:province":"Lorraine",
    "sg:tags":[
        "equipment",
        "electrical",
        "component",
        "electric",
        "electronic"
    ],
    "wof:name":"Sa Enrulec",
    "wof:placetype":"venue"
},
  "geometry": {"coordinates":[-6.273302,53.351116],"type":"Point"}
}