{
  "type": "Feature",
  "properties": {
    "iso:country":"FR",
    "sg:address":"698, Av. March\u00e9 Gare, 34000 Montpellier",
    "sg:orig_category":"Unclassifiable Establishments",
    "sg:phone":"+33 4 67 06 00 67",
    "sg:province":"Languedoc-Roussillon",
    "wof:name":"Kent Marine Equipement S.a.",
    "wof:placetype":"venue"
},
  "geometry": {"coordinates":[3.87609,43.610855],"type":"Point"}
}