{
  "type": "Feature",
  "properties": {
    "iso:country":"FR",
    "sg:address":"565, Rue Marcellin Berthelot - P.A. les Milles - Le Mercure A, 13851 Aix en Provence C\u00e9dex 3",
    "sg:orig_category":"Non-Classified Establishments",
    "sg:phone":"+33 4 42 90 05 47",
    "sg:province":"Nord Pas-de-Calais",
    "wof:name":"Upsilog S.a.r.l.",
    "wof:placetype":"venue"
},
  "geometry": {"coordinates":[5.4542,43.52494],"type":"Point"}
}