{
  "type": "Feature",
  "properties": {
    "addr:full":"114, Rte de Saint Emilion, 33500 Libourne Libourne Aquitaine 33500",
    "addr:housenumber":"114",
    "addr:postcode":"33500;33500",
    "addr:street":"Rte De Saint Emilion",
    "iso:country":"FR",
    "sg:address":"114, Rte de Saint Emilion, 33500 Libourne",
    "sg:city":"Libourne",
    "sg:orig_category":"Non-Classified Establishments",
    "sg:phone":"+33 5 57 55 39 60",
    "sg:postcode":"33500",
    "sg:province":"Aquitaine",
    "wof:name":"Chassagnoux Et Fils S.a.",
    "wof:placetype":"venue"
},
  "geometry": {"coordinates":[-0.223909,44.912575],"type":"Point"}
}