{
  "type": "Feature",
  "properties": {
    "addr:full":"37, Chemin des Pivolles, 69150 D\u00e9cines Charpieu Rhone-Alpes 69150",
    "addr:housenumber":"37",
    "addr:postcode":"69150;69150",
    "addr:street":"Chemin Des Pivolles;Rhone-Alpes",
    "iso:country":"FR",
    "sg:address":"37, Chemin des Pivolles, 69150 D\u00e9cines Charpieu",
    "sg:orig_category":"Unclassifiable Establishments",
    "sg:phone":"+33 4 72 37 82 15",
    "sg:postcode":"69150",
    "sg:province":"Rhone-Alpes",
    "wof:name":"Soci\u00e9t\u00e9 M.p.m.p. S.a.r.l.",
    "wof:placetype":"venue"
},
  "geometry": {"coordinates":[4.940263,45.753765],"type":"Point"}
}