{
  "type": "Feature",
  "properties": {
    "iso:country":"FR",
    "sg:address":"123 Avenue Barth\u00e9l\u00e9my Buyer",
    "sg:city":"Lyon",
    "sg:classifiers":[
        {
            "category":"Banks & Credit Unions",
            "subcategory":"Financial Services",
            "type":"Services"
        }
    ],
    "sg:phone":"+33 4 72 57 25 25",
    "sg:postcode":"69005",
    "sg:province":"Rhone-Alpes",
    "sg:tags":[
        "banking",
        "finance",
        "insurance"
    ],
    "wof:name":"Cegid Sa",
    "wof:placetype":"venue"
},
  "geometry": {"coordinates":[4.800347,45.76313],"type":"Point"}
}