{
  "type": "Feature",
  "properties": {
    "iso:country":"FR",
    "sg:address":"10, Rue du Grenier \u00e0 Sel - ZI du Quai, 28210 Nogent le Roi",
    "sg:city":"Br\u00e9champs",
    "sg:orig_category":"Unclassifiable Establishments",
    "sg:phone":"+33 2 37 38 03 30",
    "sg:postcode":"28210",
    "sg:province":"Centre",
    "wof:name":"Cosinus S.a.r.l.",
    "wof:placetype":"venue"
},
  "geometry": {"coordinates":[1.52835,48.648594],"type":"Point"}
}