{
  "type": "Feature",
  "properties": {
    "addr:full":"Zone D'Activit\u00e9 Robert 43140 St Didier En Velay Saint-Didier-en-Velay Auvergne 43140",
    "addr:postcode":"43140;43140",
    "addr:street":"Zone",
    "iso:country":"FR",
    "sg:address":"Zone D'Activit\u00e9 Robert 43140 St Didier En Velay",
    "sg:city":"Saint-Didier-en-Velay",
    "sg:classifiers":[
        {
            "category":"Manufacturing",
            "subcategory":"Textiles",
            "type":"Manufacturing & Wholesale Goods"
        }
    ],
    "sg:phone":"+33 4 71 61 02 91",
    "sg:postcode":"43140",
    "sg:province":"Auvergne",
    "sg:tags":[
        "clothing",
        "accessory"
    ],
    "wof:name":"Peyrache",
    "wof:placetype":"venue"
},
  "geometry": {"coordinates":[4.27581,45.303429],"type":"Point"}
}