{
  "type": "Feature",
  "properties": {
    "addr:full":"2 Bis Chemin Des Eyrolles 60460 Blaincourt Les Pr\u00e8cy Picardie 60460",
    "addr:housenumber":"2 bis",
    "addr:postcode":"60460;60460",
    "addr:street":"Chemin Des Eyrolles",
    "iso:country":"FR",
    "sg:address":"2 Bis Chemin Des Eyrolles 60460 Blaincourt Les Pr\u00e8cy",
    "sg:orig_category":"Miscellaneous Products",
    "sg:phone":"+33 3 44 27 10 54",
    "sg:postcode":"60460",
    "sg:province":"Picardie",
    "wof:name":"Max Martine Bureautique Sarl",
    "wof:placetype":"venue"
},
  "geometry": {"coordinates":[2.360113,49.220753],"type":"Point"}
}