{
  "type": "Feature",
  "properties": {
    "iso:country":"FR",
    "sg:address":"Avenue Gaston Phoebus Usine Beyrede 65410 Beyrede Jumet",
    "sg:classifiers":[
        {
            "category":"Manufacturing",
            "subcategory":"Chemicals & Compounds",
            "type":"Manufacturing & Wholesale Goods"
        }
    ],
    "sg:phone":"+33 5 62 98 70 70",
    "sg:postcode":"65410",
    "sg:province":"Midi Pyr\u00e9n\u00e9es",
    "sg:tags":[
        "pharmaceutical",
        "chemistry",
        "-",
        "by-product"
    ],
    "wof:name":"Pem Abrasifs Refractaires",
    "wof:placetype":"venue"
},
  "geometry": {"coordinates":[0.37705,42.966358],"type":"Point"}
}