{
  "type": "Feature",
  "properties": {
    "iso:country":"FR",
    "sg:address":"ZI Vrillonerie",
    "sg:city":"Chambray l\u00e8s Tours",
    "sg:orig_category":"Unclassifiable Establishments",
    "sg:phone":"+33 2 47 27 28 27",
    "sg:postcode":"37170",
    "sg:province":"Centre",
    "wof:name":"Laboratoires Bioph\u00e9lia S.a.",
    "wof:placetype":"venue"
},
  "geometry": {"coordinates":[0.71327,47.33884],"type":"Point"}
}