{
  "type": "Feature",
  "properties": {
    "iso:country":"FR",
    "sg:address":"67 Rue Arago 93400 St Ouen",
    "sg:classifiers":[
        {
            "category":"Manufacturing",
            "subcategory":"Rubber & Plastics",
            "type":"Manufacturing & Wholesale Goods"
        }
    ],
    "sg:phone":"+33 1 49 18 40 00",
    "sg:postcode":"93400",
    "sg:province":"Ile de France",
    "sg:tags":[
        "packaging",
        "material",
        "-",
        "metalworking",
        "metallic",
        "metallurgy",
        "finished",
        "plast"
    ],
    "wof:name":"Risdon Sa",
    "wof:placetype":"venue"
},
  "geometry": {"coordinates":[2.3238,48.902706],"type":"Point"}
}