{
  "type": "Feature",
  "properties": {
    "addr:full":"B.P. 60178 Mor\u00e9ac Bretagne 56500",
    "addr:postcode":"60178 more\u0301ac;56500",
    "iso:country":"FR",
    "sg:address":"B.P. 60178",
    "sg:city":"Mor\u00e9ac",
    "sg:orig_category":"Non-Classified Establishments",
    "sg:phone":"+33 2 97 54 66 01",
    "sg:postcode":"56500",
    "sg:province":"Bretagne",
    "wof:name":"Bernard S.a.",
    "wof:placetype":"venue"
},
  "geometry": {"coordinates":[-2.870512,47.839455],"type":"Point"}
}