{
  "type": "Feature",
  "properties": {
    "iso:country":"FR",
    "sg:address":"110 boulevard Saint-Germain 75006 Paris",
    "sg:orig_category":"Boys' Clothing",
    "sg:phone":"+33 1 56 24 86 37",
    "sg:postcode":"75006",
    "sg:province":"Ile de France",
    "wof:name":"Carbone International Sa",
    "wof:placetype":"venue"
},
  "geometry": {"coordinates":[2.341647,48.851891],"type":"Point"}
}