{
  "type": "Feature",
  "properties": {
    "addr:full":"Les Chatelets 22440 Ploufragan Ploufragan Bretagne 22440",
    "addr:postcode":"22440;22440",
    "iso:country":"FR",
    "sg:address":"Les Chatelets 22440 Ploufragan",
    "sg:city":"Ploufragan",
    "sg:classifiers":[
        {
            "category":"Manufacturing",
            "subcategory":"Chemicals & Compounds",
            "type":"Manufacturing & Wholesale Goods"
        }
    ],
    "sg:phone":"+33 2 96 94 18 63",
    "sg:postcode":"22440",
    "sg:province":"Bretagne",
    "sg:tags":[
        "pharmaceutical",
        "chemistry",
        "-",
        "by-product"
    ],
    "wof:name":"Cooperative Des Agriculteurs De Bretagne",
    "wof:placetype":"venue"
},
  "geometry": {"coordinates":[-2.797303,48.468601],"type":"Point"}
}