{
  "type": "Feature",
  "properties": {
    "iso:country":"FR",
    "sg:address":"Rte De Pernes 84450 St Saturnin Les Avignon",
    "sg:classifiers":[
        {
            "category":"Manufacturing",
            "subcategory":"Glass & Minerals",
            "type":"Manufacturing & Wholesale Goods"
        }
    ],
    "sg:phone":"+33 4 90 22 20 26",
    "sg:province":"Aquitaine",
    "sg:tags":[
        "building",
        "material"
    ],
    "wof:name":"Beton De France Sud Est",
    "wof:placetype":"venue"
},
  "geometry": {"coordinates":[4.927346,43.964954],"type":"Point"}
}