{
  "type": "Feature",
  "properties": {
    "addr:full":"Quartier Saint Ruff Valence Rhone-Alpes 26000",
    "addr:postcode":"26000",
    "addr:street":"Ruff;Rhone-Alpes",
    "iso:country":"FR",
    "sg:address":"Quartier Saint Ruff",
    "sg:city":"Valence",
    "sg:orig_category":"Unclassifiable Establishments",
    "sg:phone":"+33 4 75 56 92 15",
    "sg:postcode":"26000",
    "sg:province":"Rhone-Alpes",
    "wof:name":"Des Rieux S.a.s.",
    "wof:placetype":"venue"
},
  "geometry": {"coordinates":[4.889726,44.93391],"type":"Point"}
}