{
  "type": "Feature",
  "properties": {
    "iso:country":"FR",
    "sg:address":"4 Mont\u00e9e De Gezon Zi Sud 39260 Moirans En Montagne",
    "sg:classifiers":[
        {
            "category":"Manufacturing",
            "subcategory":"Metals",
            "type":"Manufacturing & Wholesale Goods"
        }
    ],
    "sg:phone":"+33 3 84 42 01 28",
    "sg:postcode":"39260",
    "sg:province":"Franche Comt\u00e9",
    "sg:tags":[
        "processing",
        "-",
        "metalworking",
        "metallic",
        "metallurgy",
        "finished"
    ],
    "wof:name":"Etablissements Verpillat",
    "wof:placetype":"venue"
},
  "geometry": {"coordinates":[5.7253,46.42524],"type":"Point"}
}