{
  "type": "Feature",
  "properties": {
    "addr:full":"Rte du Lude Arnage Pays de Loire 72230",
    "addr:postcode":"72230",
    "addr:street":"Rte Du Lude",
    "iso:country":"FR",
    "sg:address":"Rte du Lude",
    "sg:city":"Arnage",
    "sg:orig_category":"Unclassifiable Establishments",
    "sg:phone":"+33 2 43 21 80 80",
    "sg:postcode":"72230",
    "sg:province":"Pays de Loire",
    "wof:name":"Le Segment A.b. S.a.",
    "wof:placetype":"venue"
},
  "geometry": {"coordinates":[0.189885,47.91011],"type":"Point"}
}