{
  "type": "Feature",
  "properties": {
    "addr:full":"Za 90150 Lagrange Franche Comt\u00e9 90150",
    "addr:postcode":"90150;90150",
    "addr:street":"Za;Franche Comte\u0301",
    "iso:country":"FR",
    "sg:address":"Za 90150 Lagrange",
    "sg:classifiers":[
        {
            "category":"Professional",
            "subcategory":"Engineering",
            "type":"Services"
        }
    ],
    "sg:phone":"+33 3 84 23 84 01",
    "sg:postcode":"90150",
    "sg:province":"Franche Comt\u00e9",
    "sg:tags":[
        "machine",
        "-",
        "mechanical"
    ],
    "wof:name":"Sarl Farque",
    "wof:placetype":"venue"
},
  "geometry": {"coordinates":[6.942255,47.670254],"type":"Point"}
}