{
  "type": "Feature",
  "properties": {
    "addr:full":"4, Rue Louis Massotte, 78530 Buc Ile de France 78530",
    "addr:housenumber":"4",
    "addr:postcode":"78530;ile;78530",
    "addr:street":"Rue Louis Massotte;France",
    "iso:country":"FR",
    "sg:address":"4, Rue Louis Massotte, 78530 Buc",
    "sg:orig_category":"Non-Classified Establishments",
    "sg:phone":"+33 1 39 20 10 10",
    "sg:postcode":"78530",
    "sg:province":"Ile de France",
    "wof:name":"A.d.n.t. S.a.r.l. - Assistance D\u00e9veloppement Nouvelles Technologies",
    "wof:placetype":"venue"
},
  "geometry": {"coordinates":[2.127045,48.773296],"type":"Point"}
}