{
  "type": "Feature",
  "properties": {
    "iso:country":"FR",
    "sg:address":"31, Rue du G\u00e9n\u00e9ral Rascas, 57220 Boulay Moselle",
    "sg:orig_category":"Non-Classified Establishments",
    "sg:phone":"+33 3 87 79 31 69",
    "sg:province":"Lorraine",
    "wof:name":"Rath S.a.r.l.",
    "wof:placetype":"venue"
},
  "geometry": {"coordinates":[6.468805,49.176491],"type":"Point"}
}