{
  "type": "Feature",
  "properties": {
    "addr:full":"106, Rue Georges Cl\u00e9menceau, 76210 Bolbec Haute Normandie",
    "addr:housenumber":"106",
    "addr:postcode":"76210",
    "addr:street":"Rue Georges Cle\u0301Menceau;Haute Normandie",
    "iso:country":"FR",
    "sg:address":"106, Rue Georges Cl\u00e9menceau, 76210 Bolbec",
    "sg:orig_category":"Non-Classified Establishments",
    "sg:phone":"+33 2 35 31 00 93",
    "sg:province":"Haute Normandie",
    "wof:name":"Mutuelle Coop\u00e9rative Artisanale D'abattage S.a.",
    "wof:placetype":"venue"
},
  "geometry": {"coordinates":[0.463948,49.564365],"type":"Point"}
}