{
  "type": "Feature",
  "properties": {
    "addr:full":"Monte Ruffin 38630 Les Aveni\u00e8res Rhone-Alpes 38630",
    "addr:postcode":"38630;38630",
    "addr:street":"Monte Ruffin;Avenie\u0300Res Rhone-Alpes",
    "iso:country":"FR",
    "sg:address":"Monte Ruffin 38630 Les Aveni\u00e8res",
    "sg:orig_category":"Unclassifiable Establishments",
    "sg:phone":"+33 4 74 33 96 85",
    "sg:postcode":"38630",
    "sg:province":"Rhone-Alpes",
    "wof:name":"Catcel S.a.r.l.",
    "wof:placetype":"venue"
},
  "geometry": {"coordinates":[5.56585,45.640476],"type":"Point"}
}