{
  "type": "Feature",
  "properties": {
    "addr:full":"104, Chemin des Grands Moulins, 69400 Gleiz\u00e9 Rhone-Alpes",
    "addr:housenumber":"104",
    "addr:postcode":"69400",
    "addr:street":"Chemin Des Grands Moulins",
    "iso:country":"FR",
    "sg:address":"104, Chemin des Grands Moulins, 69400 Gleiz\u00e9",
    "sg:orig_category":"Unclassifiable Establishments",
    "sg:phone":"+33 4 74 68 30 43",
    "sg:province":"Rhone-Alpes",
    "wof:name":"Schneiderlin S.a.r.l.",
    "wof:placetype":"venue"
},
  "geometry": {"coordinates":[4.707301,45.989063],"type":"Point"}
}