{
  "type": "Feature",
  "properties": {
    "iso:country":"FR",
    "sg:address":"Zac La Prade 33650 St Medard D Eyrans",
    "sg:city":"Cabanac-et-Villagrains",
    "sg:classifiers":[
        {
            "category":"Wholesale",
            "subcategory":"Meat",
            "type":"Manufacturing & Wholesale Goods"
        }
    ],
    "sg:phone":"+33 5 57 97 03 30",
    "sg:postcode":"33650",
    "sg:province":"Aquitaine",
    "sg:tags":[
        "food",
        "cooked",
        "product",
        "related"
    ],
    "wof:name":"Sa Lou Gascoun",
    "wof:placetype":"venue"
},
  "geometry": {"coordinates":[-0.508946,44.717876],"type":"Point"}
}