{
  "type": "Feature",
  "properties": {
    "addr:full":"14 Bd Rocheplatte 45058 Orl\u00e9ans Cedex 1 Orl\u00e9ans Centre 45000",
    "addr:housenumber":"14",
    "addr:postcode":"45058;45000",
    "addr:street":"Bd Rocheplatte",
    "iso:country":"FR",
    "sg:address":"14 Bd Rocheplatte 45058 Orl\u00e9ans Cedex 1",
    "sg:city":"Orl\u00e9ans",
    "sg:classifiers":[
        {
            "category":"Banks & Credit Unions",
            "subcategory":"Financial Services",
            "type":"Services"
        }
    ],
    "sg:phone":"+33 2 38 78 18 16",
    "sg:postcode":"45000",
    "sg:province":"Centre",
    "sg:tags":[
        "banking",
        "finance",
        "insurance"
    ],
    "wof:name":"Centre Capital Developpement Sa",
    "wof:placetype":"venue"
},
  "geometry": {"coordinates":[1.90398,47.90139],"type":"Point"}
}