{
  "type": "Feature",
  "properties": {
    "addr:full":"19 Rue Du Vercors Zi De La Chauvetiere 42000 St Etienne Rhone-Alpes 42000",
    "addr:housenumber":"19",
    "addr:postcode":"42000;42000",
    "addr:street":"Rue Du Vercors Zi De La Chauvetiere",
    "iso:country":"FR",
    "sg:address":"19 Rue Du Vercors Zi De La Chauvetiere 42000 St Etienne",
    "sg:classifiers":[
        {
            "category":"Manufacturing",
            "subcategory":"Tools & Machinery",
            "type":"Manufacturing & Wholesale Goods"
        }
    ],
    "sg:phone":"+33 4 77 81 45 56",
    "sg:postcode":"42000",
    "sg:province":"Rhone-Alpes",
    "sg:tags":[
        "environment",
        "equipment",
        "-"
    ],
    "wof:name":"Planchet Epuration Societe Anonyme",
    "wof:placetype":"venue"
},
  "geometry": {"coordinates":[4.387921,45.439053],"type":"Point"}
}