{
  "type": "Feature",
  "properties": {
    "iso:country":"FR",
    "sg:address":"146, Av. des Etats Unis - Min Magasias 14 et 16, 31200 Toulouse",
    "sg:orig_category":"Unclassifiable Establishments",
    "sg:phone":"+33 5 61 47 21 59",
    "sg:province":"Midi Pyr\u00e9n\u00e9es",
    "wof:name":"Favarel Francis S.a.",
    "wof:placetype":"venue"
},
  "geometry": {"coordinates":[1.44954,43.639011],"type":"Point"}
}