{
  "type": "Feature",
  "properties": {
    "addr:full":"B.P. 2725, 03207 Vichy C\u00e9dex^^Rue du Sergent Georges Bourdeaux - ZI Vichy Rhue, 03300 Creuzier le Vi Cusset Auvergne 03300",
    "addr:postcode":"03207;03300;03300",
    "addr:street":"B.P. 2725;Zi;Rhue;Creuzier Le Vi",
    "iso:country":"FR",
    "sg:address":"B.P. 2725, 03207 Vichy C\u00e9dex^^Rue du Sergent Georges Bourdeaux - ZI Vichy Rhue, 03300 Creuzier le Vi",
    "sg:city":"Cusset",
    "sg:orig_category":"Non-Classified Establishments",
    "sg:phone":"+33 4 70 30 15 85",
    "sg:postcode":"03300",
    "sg:province":"Auvergne",
    "wof:name":"Th\u00e9venet S.a.",
    "wof:placetype":"venue"
},
  "geometry": {"coordinates":[3.47831,46.14436],"type":"Point"}
}