{
  "type": "Feature",
  "properties": {
    "iso:country":"FR",
    "sg:address":"12, Rue du Stade, 25200 Grand Charmont",
    "sg:orig_category":"Unclassifiable Establishments",
    "sg:phone":"+33 3 81 32 28 65",
    "sg:province":"Franche Comt\u00e9",
    "wof:name":"Fermetures Jeannin S.a.r.l.",
    "wof:placetype":"venue"
},
  "geometry": {"coordinates":[6.821196,47.52858],"type":"Point"}
}