{
  "type": "Feature",
  "properties": {
    "addr:full":"CD 42 - Beauversan Saint Genis Laval Rhone-Alpes 69230",
    "addr:postcode":"69230",
    "addr:street":"Cd 42 Beauversan Saint Genis;Rhone-Alpes",
    "iso:country":"FR",
    "sg:address":"CD 42 - Beauversan",
    "sg:city":"Saint Genis Laval",
    "sg:orig_category":"Unclassifiable Establishments",
    "sg:phone":"+33 4 78 56 99 99",
    "sg:postcode":"69230",
    "sg:province":"Rhone-Alpes",
    "wof:name":"Transport Pi\u00e9gay Fr\u00e8res S.a.",
    "wof:placetype":"venue"
},
  "geometry": {"coordinates":[4.79296,45.694736],"type":"Point"}
}