{
  "type": "Feature",
  "properties": {
    "iso:country":"FR",
    "sg:address":"Kerlann 56550 Belz",
    "sg:city":"Belz",
    "sg:classifiers":[
        {
            "category":"Food & Beverages",
            "subcategory":"Fruits & Vegetables",
            "type":"Retail Goods"
        }
    ],
    "sg:phone":"+33 2 97 55 32 22",
    "sg:postcode":"56550",
    "sg:province":"Bretagne",
    "sg:tags":[
        "preserve",
        "product",
        "related"
    ],
    "wof:name":"Conserverie Lorcy J-m Sa",
    "wof:placetype":"venue"
},
  "geometry": {"coordinates":[-3.173517,47.676033],"type":"Point"}
}