{
  "type": "Feature",
  "properties": {
    "addr:full":"29 Rue Gasparin Lyon Rhone-Alpes 69002",
    "addr:housenumber":"29",
    "addr:postcode":"69002",
    "addr:street":"Rue Gasparin;Rhone-Alpes",
    "iso:country":"FR",
    "sg:address":"29 Rue Gasparin",
    "sg:city":"Lyon",
    "sg:classifiers":[
        {
            "category":"Banks & Credit Unions",
            "subcategory":"Financial Services",
            "type":"Services"
        }
    ],
    "sg:phone":"+33 4 78 37 03 17",
    "sg:postcode":"69002",
    "sg:province":"Rhone-Alpes",
    "sg:tags":[
        "banking",
        "finance",
        "insurance"
    ],
    "wof:name":"Bignon & Lebray",
    "wof:placetype":"venue"
},
  "geometry": {"coordinates":[4.83331,45.758324],"type":"Point"}
}