{
  "type": "Feature",
  "properties": {
    "iso:country":"FR",
    "sg:address":"ZA le R\u00e9seau",
    "sg:city":"Andard",
    "sg:orig_category":"Unclassifiable Establishments",
    "sg:phone":"+33 2 41 54 99 99",
    "sg:postcode":"49800",
    "sg:province":"Pays de Loire",
    "wof:name":"Lex Manutention S.a.",
    "wof:placetype":"venue"
},
  "geometry": {"coordinates":[-0.399599,47.456196],"type":"Point"}
}