{
  "type": "Feature",
  "properties": {
    "iso:country":"FR",
    "sg:address":"22, Rue Andr\u00e9 Potelle, 80300 Albert",
    "sg:orig_category":"Unclassifiable Establishments",
    "sg:phone":"+33 3 22 75 04 95",
    "sg:province":"Picardie",
    "wof:name":"Albert Maille S.a.r.l.",
    "wof:placetype":"venue"
},
  "geometry": {"coordinates":[2.645392,49.999031],"type":"Point"}
}