{
  "type": "Feature",
  "properties": {
    "iso:country":"FR",
    "sg:address":"21 Rue Jean Charcot Zi 26100 Romans Sur Isere",
    "sg:classifiers":[
        {
            "category":"Professional",
            "subcategory":"Printing & Photocopies",
            "type":"Services"
        }
    ],
    "sg:phone":"+33 4 75 02 15 25",
    "sg:postcode":"26100",
    "sg:province":"Rhone-Alpes",
    "sg:tags":[
        "publishing"
    ],
    "wof:name":"Societe Edifice",
    "wof:placetype":"venue"
},
  "geometry": {"coordinates":[5.049637,45.045036],"type":"Point"}
}