{
  "type": "Feature",
  "properties": {
    "addr:full":"180, Rue Cl\u00e9ment Ader, 42153 Riorges Rhone-Alpes 42153",
    "addr:housenumber":"180",
    "addr:postcode":"42153;42153",
    "addr:street":"Rue Cle\u0301Ment Ader;Rhone-Alpes",
    "iso:country":"FR",
    "sg:address":"180, Rue Cl\u00e9ment Ader, 42153 Riorges",
    "sg:orig_category":"Unclassifiable Establishments",
    "sg:phone":"+33 4 77 67 83 83",
    "sg:postcode":"42153",
    "sg:province":"Rhone-Alpes",
    "wof:name":"Terre De Couleurs S.a.",
    "wof:placetype":"venue"
},
  "geometry": {"coordinates":[4.04546,46.060394],"type":"Point"}
}