{
  "type": "Feature",
  "properties": {
    "addr:full":"Magny 69240 Saint Vincent de Reins Rhone-Alpes",
    "addr:postcode":"69240",
    "addr:street":"Rhone-Alpes",
    "iso:country":"FR",
    "sg:address":"Magny 69240 Saint Vincent de Reins",
    "sg:orig_category":"Unclassifiable Establishments",
    "sg:phone":"+33 4 74 89 67 67",
    "sg:province":"Rhone-Alpes",
    "wof:name":"M.g. S.a. - Muguet Grisard",
    "wof:placetype":"venue"
},
  "geometry": {"coordinates":[4.39618,46.052979],"type":"Point"}
}