{
  "type": "Feature",
  "properties": {
    "addr:full":"Rue du Chemin Blanc Champlan Ile de France 91160",
    "addr:postcode":"91160",
    "addr:street":"Rue Du Chemin Blanc;Ile De France",
    "iso:country":"FR",
    "sg:address":"Rue du Chemin Blanc",
    "sg:city":"Champlan",
    "sg:orig_category":"Unclassifiable Establishments",
    "sg:phone":"+33 1 69 79 14 14",
    "sg:postcode":"91160",
    "sg:province":"Ile de France",
    "wof:name":"C.a.e. S.a. - C\u00e2blage Antenne Electronique",
    "wof:placetype":"venue"
},
  "geometry": {"coordinates":[2.29005,48.691734],"type":"Point"}
}