{
  "type": "Feature",
  "properties": {
    "iso:country":"FR",
    "sg:address":"128 Rte Du Polygone 67100 Strasbourg",
    "sg:city":"Strasbourg",
    "sg:classifiers":[
        {
            "category":"Professional",
            "subcategory":"Business Services",
            "type":"Services"
        }
    ],
    "sg:phone":"+33 3 88 31 97 50",
    "sg:postcode":"67100",
    "sg:province":"Alsace",
    "sg:tags":[
        "training",
        "advice"
    ],
    "wof:name":"Ecole Libre Sainte Anne",
    "wof:placetype":"venue"
},
  "geometry": {"coordinates":[7.761167,48.563671],"type":"Point"}
}