{
  "type": "Feature",
  "properties": {
    "iso:country":"FR",
    "sg:address":"Maillard 01400 Ch\u00e2tillon Sur Chalaronne",
    "sg:classifiers":[
        {
            "category":"Utilities",
            "subcategory":"Electric",
            "type":"Services"
        }
    ],
    "sg:phone":"+33 4 74 55 30 76",
    "sg:postcode":"01400",
    "sg:province":"Rhone-Alpes",
    "sg:tags":[
        "electricity",
        "electronic",
        "electrical",
        "equipment"
    ],
    "wof:name":"Sercate",
    "wof:placetype":"venue"
},
  "geometry": {"coordinates":[4.94928,46.11776],"type":"Point"}
}