{
  "type": "Feature",
  "properties": {
    "iso:country":"FR",
    "sg:address":"10 Rue Du Paradis 45144 St Jean De La Ruelle",
    "sg:classifiers":[
        {
            "category":"Manufacturing",
            "subcategory":"Motor Vehicles & Parts",
            "type":"Manufacturing & Wholesale Goods"
        }
    ],
    "sg:phone":"+33 2 38 72 30 00",
    "sg:province":"Picardie",
    "sg:tags":[
        "motor-cars",
        "tran",
        "-",
        "machine",
        "equipment",
        "engineering",
        "machinery",
        "mechanical",
        "agriculture"
    ],
    "wof:name":"John Deere",
    "wof:placetype":"venue"
},
  "geometry": {"coordinates":[1.823606,47.940861],"type":"Point"}
}