{
  "type": "Feature",
  "properties": {
    "addr:full":"20 Rue De La Cit\u00e9 Saint Gobain 31150 Fenouillet Midi Pyr\u00e9n\u00e9es 31150",
    "addr:housenumber":"20",
    "addr:postcode":"31150;31150",
    "addr:street":"Rue De La Cite\u0301 Saint Gobain",
    "iso:country":"FR",
    "sg:address":"20 Rue De La Cit\u00e9 Saint Gobain 31150 Fenouillet",
    "sg:classifiers":[
        {
            "category":"Building & Trades",
            "subcategory":"Construction",
            "type":"Services"
        }
    ],
    "sg:phone":"+33 5 61 70 37 20",
    "sg:postcode":"31150",
    "sg:province":"Midi Pyr\u00e9n\u00e9es",
    "sg:tags":[
        "work",
        "public"
    ],
    "wof:name":"Societe Garonne Ariege Travaux Publics Sogatrap Sogatrap",
    "wof:placetype":"venue"
},
  "geometry": {"coordinates":[1.40833,43.67601],"type":"Point"}
}