{
  "type": "Feature",
  "properties": {
    "addr:full":"B.P. 2, 71960 Priss\u00e9^^Rue de la Fontaine, 71960 Priss\u00e9 Priss\u00e9 Bourgogne 71960",
    "addr:housenumber":"2",
    "addr:postcode":"71960;71960;71960",
    "addr:street":"B.P.;La Fontaine",
    "iso:country":"FR",
    "sg:address":"B.P. 2, 71960 Priss\u00e9^^Rue de la Fontaine, 71960 Priss\u00e9",
    "sg:city":"Priss\u00e9",
    "sg:orig_category":"Non-Classified Establishments",
    "sg:phone":"+33 3 85 32 26 85",
    "sg:postcode":"71960",
    "sg:province":"Bourgogne",
    "wof:name":"Carrara Et Fils S.a.",
    "wof:placetype":"venue"
},
  "geometry": {"coordinates":[4.740233,46.290405],"type":"Point"}
}