{
  "type": "Feature",
  "properties": {
    "iso:country":"FR",
    "sg:address":"ZI Les Ecorces 88250 La Bresse",
    "sg:classifiers":[
        {
            "category":"Manufacturing",
            "subcategory":"Wood Products",
            "type":"Manufacturing & Wholesale Goods"
        }
    ],
    "sg:phone":"+33 3 29 25 53 11",
    "sg:postcode":"88250",
    "sg:province":"Lorraine",
    "sg:tags":[
        "lumber"
    ],
    "wof:name":"Les Zelles Sa",
    "wof:placetype":"venue"
},
  "geometry": {"coordinates":[6.87512,48.003704],"type":"Point"}
}