{
  "type": "Feature",
  "properties": {
    "iso:country":"FR",
    "sg:address":"86 blvd Cimiez; Nice",
    "sg:classifiers":[
        {
            "category":"Banks & Credit Unions",
            "subcategory":"Bank",
            "type":"Services"
        }
    ],
    "sg:phone":"+33 3393813232",
    "wof:name":"Banque Nationale De Paris",
    "wof:placetype":"venue"
},
  "geometry": {"coordinates":[7.278493,43.70145],"type":"Point"}
}