{
  "type": "Feature",
  "properties": {
    "iso:country":"FR",
    "sg:address":"B.P. 39, 74131 Bonneville C\u00e9dex^^399, Av. Roche Parnale - ZI la Motte Longue, 74130 Bonneville",
    "sg:orig_category":"Non-Classified Establishments",
    "sg:phone":"+33 4 50 25 65 34",
    "sg:postcode":"74130",
    "sg:province":"Rhone-Alpes",
    "wof:name":"Index France Sarl",
    "wof:placetype":"venue"
},
  "geometry": {"coordinates":[6.388322,45.95652],"type":"Point"}
}