{
  "type": "Feature",
  "properties": {
    "addr:full":"Ch\u00e2teau des Laurets 33570 Puisseguin Puisseguin Aquitaine 33570",
    "addr:postcode":"33570;33570",
    "iso:country":"FR",
    "sg:address":"Ch\u00e2teau des Laurets 33570 Puisseguin",
    "sg:city":"Puisseguin",
    "sg:orig_category":"Non-Classified Establishments",
    "sg:phone":"+33 5 57 74 63 40",
    "sg:postcode":"33570",
    "sg:province":"Aquitaine",
    "wof:name":"Ch\u00e2teau Des Laurets S.a.s.",
    "wof:placetype":"venue"
},
  "geometry": {"coordinates":[-0.078879,44.918182],"type":"Point"}
}