{
  "type": "Feature",
  "properties": {
    "addr:full":"43, Rue Patou, 59800 Lille Nord Pas-de-Calais",
    "addr:housenumber":"43",
    "addr:postcode":"59800",
    "addr:street":"Rue Patou",
    "iso:country":"FR",
    "sg:address":"43, Rue Patou, 59800 Lille",
    "sg:orig_category":"Unclassifiable Establishments",
    "sg:phone":"+33 3 20 42 00 45",
    "sg:province":"Nord Pas-de-Calais",
    "wof:name":"Roche Dubar Et Associ\u00e9s S.a.",
    "wof:placetype":"venue"
},
  "geometry": {"coordinates":[3.050671,50.634735],"type":"Point"}
}