{
  "type": "Feature",
  "properties": {
    "addr:full":"1 Rue Des Pres Meles Za Du Champ Mulon 35230 St Erblon Bourgbarr\u00e9 Bretagne 35230",
    "addr:housenumber":"1",
    "addr:postcode":"35230;35230",
    "addr:street":"Rue Des Pres;Za Du Champ Mulon",
    "iso:country":"FR",
    "sg:address":"1 Rue Des Pres Meles Za Du Champ Mulon 35230 St Erblon",
    "sg:city":"Bourgbarr\u00e9",
    "sg:classifiers":[
        {
            "category":"Shopping",
            "type":"Retail Goods"
        }
    ],
    "sg:phone":"+33 2 99 52 39 91",
    "sg:postcode":"35230",
    "sg:province":"Bretagne",
    "sg:tags":[
        "metallurgy",
        "finished",
        "-",
        "metalworking",
        "metallic"
    ],
    "wof:name":"Ouest Roues",
    "wof:placetype":"venue"
},
  "geometry": {"coordinates":[-1.615554,47.99485],"type":"Point"}
}