{
  "type": "Feature",
  "properties": {
    "addr:full":"La Grusti\u00e8re 44170 Nozay Pays de Loire 44170",
    "addr:postcode":"44170;44170",
    "iso:country":"FR",
    "sg:address":"La Grusti\u00e8re 44170 Nozay",
    "sg:classifiers":[
        {
            "category":"Building & Trades",
            "subcategory":"Construction",
            "type":"Services"
        }
    ],
    "sg:phone":"+33 2 40 79 43 57",
    "sg:postcode":"44170",
    "sg:province":"Pays de Loire",
    "sg:tags":[
        "work",
        "public"
    ],
    "wof:name":"Mahe",
    "wof:placetype":"venue"
},
  "geometry": {"coordinates":[-1.637064,47.565735],"type":"Point"}
}