{
  "type": "Feature",
  "properties": {
    "addr:full":"351, Rue de la Castelle, 34070 Montpellier Languedoc-Roussillon",
    "addr:housenumber":"351",
    "addr:postcode":"34070",
    "addr:street":"Rue De La Castelle",
    "iso:country":"FR",
    "sg:address":"351, Rue de la Castelle, 34070 Montpellier",
    "sg:orig_category":"Unclassifiable Establishments",
    "sg:phone":"+33 4 99 52 86 86",
    "sg:province":"Languedoc-Roussillon",
    "wof:name":"Soci\u00e9t\u00e9 M\u00e9diterran\u00e9enne De Nettoiement S.a.",
    "wof:placetype":"venue"
},
  "geometry": {"coordinates":[3.86941,43.58411],"type":"Point"}
}