{
  "type": "Feature",
  "properties": {
    "addr:full":"B.P. 6 Luc C\u00e9dex^^La Primaube 12450 Luc Midi Pyr\u00e9n\u00e9es 12450",
    "addr:housenumber":"6",
    "addr:postcode":"luc;12450;12450",
    "addr:street":"B.P.;Primaube",
    "iso:country":"FR",
    "sg:address":"B.P. 6",
    "sg:city":"Luc C\u00e9dex^^La Primaube 12450 Luc",
    "sg:orig_category":"Non-Classified Establishments",
    "sg:phone":"+33 5 65 71 40 04",
    "sg:postcode":"12450",
    "sg:province":"Midi Pyr\u00e9n\u00e9es",
    "wof:name":"Transports Beteille S.a.",
    "wof:placetype":"venue"
},
  "geometry": {"coordinates":[2.544625,44.245583],"type":"Point"}
}