{
  "type": "Feature",
  "properties": {
    "iso:country":"FR",
    "sg:address":"2, Rue Ch\u00eane Lass\u00e9, 44800 Saint Herblain",
    "sg:orig_category":"Unclassifiable Establishments",
    "sg:phone":"+33 2 40 92 32 50",
    "sg:province":"Pays de Loire",
    "wof:name":"Chupin Emballage S.a.",
    "wof:placetype":"venue"
},
  "geometry": {"coordinates":[-1.641676,47.229076],"type":"Point"}
}