{
  "type": "Feature",
  "properties": {
    "iso:country":"FR",
    "sg:address":"10, Av. Newton, 92350 Le Plessis Robinson",
    "sg:orig_category":"Non-Classified Establishments",
    "sg:phone":"+33 1 46 01 24 10",
    "sg:province":"Ile de France",
    "wof:name":"F.c. International S.a.",
    "wof:placetype":"venue"
},
  "geometry": {"coordinates":[2.244414,48.779224],"type":"Point"}
}