{
  "type": "Feature",
  "properties": {
    "iso:country":"FR",
    "sg:address":"Route De Nomeny Manoncourt Sur Seille 54610 Belleau",
    "sg:classifiers":[
        {
            "category":"Utilities",
            "subcategory":"Telephone",
            "type":"Services"
        }
    ],
    "sg:phone":"+33 3 83 31 33 08",
    "sg:province":"Lorraine",
    "sg:tags":[
        "telecommunication"
    ],
    "wof:name":"Societe Vosgienne De Telephone Svt",
    "wof:placetype":"venue"
},
  "geometry": {"coordinates":[6.197409,48.876556],"type":"Point"}
}