{
  "type": "Feature",
  "properties": {
    "iso:country":"FR",
    "sg:address":"15340 Mourjou",
    "sg:city":"Mourjou",
    "sg:classifiers":[
        {
            "category":"Health Services",
            "subcategory":"Podiatrist",
            "type":"Services"
        }
    ],
    "sg:phone":"+33 4 71 49 94 74",
    "sg:postcode":"15340",
    "sg:province":"Auvergne",
    "sg:tags":[
        "instrument",
        "measurement",
        "-",
        "precision",
        "equipment"
    ],
    "wof:name":"Interlab",
    "wof:placetype":"venue"
},
  "geometry": {"coordinates":[2.330688,44.692364],"type":"Point"}
}