{
  "type": "Feature",
  "properties": {
    "addr:full":"31 all\u00e9e de Chartres; Bordeaux; 33000 Bordeaux Aquitaine 33000",
    "addr:housenumber":"31",
    "addr:postcode":"33000;33000",
    "addr:street":"Alle\u0301E De Chartres",
    "iso:country":"FR",
    "sg:address":"31 all\u00e9e de Chartres; Bordeaux; 33000",
    "sg:city":"Bordeaux",
    "sg:classifiers":[
        {
            "category":"Banks & Credit Unions",
            "subcategory":"Bank",
            "type":"Services"
        }
    ],
    "sg:phone":"+33 3356909323",
    "sg:postcode":"33000",
    "sg:province":"Aquitaine",
    "wof:name":"Sovac",
    "wof:placetype":"venue"
},
  "geometry": {"coordinates":[-0.573732,44.847298],"type":"Point"}
}