{
  "type": "Feature",
  "properties": {
    "iso:country":"FR",
    "sg:address":"ZA les Grands Champs Sud",
    "sg:city":"Viry",
    "sg:orig_category":"Non-Classified Establishments",
    "sg:phone":"+33 4 50 04 84 04",
    "sg:postcode":"74580",
    "sg:province":"Rhone-Alpes",
    "wof:name":"Alp T.p. E.u.r.l.",
    "wof:placetype":"venue"
},
  "geometry": {"coordinates":[6.037754,46.117142],"type":"Point"}
}