{
  "type": "Feature",
  "properties": {
    "addr:full":"28 rue Fernand Pelloutier 92110 Clichy Ile de France 92110",
    "addr:housenumber":"28",
    "addr:postcode":"92110;92110",
    "addr:street":"Rue Fernand Pelloutier;Ile De France",
    "iso:country":"FR",
    "sg:address":"28 rue Fernand Pelloutier 92110 Clichy",
    "sg:classifiers":[
        {
            "category":"Bars & Pubs",
            "subcategory":"Nightclub",
            "type":"Food & Drink"
        }
    ],
    "sg:phone":"+33 1 47 15 54 54",
    "sg:postcode":"92110",
    "sg:province":"Ile de France",
    "sg:tags":[
        "lamp",
        "halogen",
        "illuminant"
    ],
    "wof:name":"Orbitec Sa",
    "wof:placetype":"venue"
},
  "geometry": {"coordinates":[2.30014,48.903652],"type":"Point"}
}