{
  "type": "Feature",
  "properties": {
    "iso:country":"FR",
    "sg:address":"35, Faubourg de Nantes, 35130 La Guerche de Bretagne",
    "sg:city":"Availles-sur-Seiche",
    "sg:orig_category":"Non-Classified Establishments",
    "sg:phone":"+33 2 99 96 32 10",
    "sg:postcode":"35130",
    "sg:province":"Bretagne",
    "wof:name":"Transports D\u00e9sert S.a.",
    "wof:placetype":"venue"
},
  "geometry": {"coordinates":[-1.231827,47.936081],"type":"Point"}
}