{
  "type": "Feature",
  "properties": {
    "addr:full":"22, Rue des Landelles, 35510 Cesson S\u00e9vign\u00e9 Cesson-S\u00e9vign\u00e9 Bretagne 35510",
    "addr:housenumber":"22",
    "addr:postcode":"35510;se\u0301vigne\u0301 cesson-se\u0301vigne\u0301;35510",
    "addr:street":"Rue Des Landelles",
    "iso:country":"FR",
    "sg:address":"22, Rue des Landelles, 35510 Cesson S\u00e9vign\u00e9",
    "sg:city":"Cesson-S\u00e9vign\u00e9",
    "sg:orig_category":"Non-Classified Establishments",
    "sg:phone":"+33 2 99 50 47 07",
    "sg:postcode":"35510",
    "sg:province":"Bretagne",
    "wof:name":"Atal S.a.",
    "wof:placetype":"venue"
},
  "geometry": {"coordinates":[-1.626425,48.10194],"type":"Point"}
}