{
  "type": "Feature",
  "properties": {
    "iso:country":"FR",
    "sg:address":"22, Rue des Landelles, 35510 Cesson S\u00e9vign\u00e9",
    "sg:city":"Cesson-S\u00e9vign\u00e9",
    "sg:orig_category":"Non-Classified Establishments",
    "sg:phone":"+33 2 99 50 47 07",
    "sg:postcode":"35510",
    "sg:province":"Bretagne",
    "wof:name":"Atal S.a.",
    "wof:placetype":"venue"
},
  "geometry": {"coordinates":[-1.626425,48.10194],"type":"Point"}
}