{
  "type": "Feature",
  "properties": {
    "iso:country":"FR",
    "sg:address":"86 Rue Jean Bertin Parc D Activite De L Eigue 69100 Villeurbanne",
    "sg:classifiers":[
        {
            "category":"Wholesale",
            "subcategory":"Machinery & Supplies",
            "type":"Manufacturing & Wholesale Goods"
        }
    ],
    "sg:phone":"+33 4 78 26 53 62",
    "sg:postcode":"69100",
    "sg:province":"Rhone-Alpes",
    "sg:tags":[
        "equipment",
        "precision"
    ],
    "wof:name":"Oldham",
    "wof:placetype":"venue"
},
  "geometry": {"coordinates":[4.917555,45.759575],"type":"Point"}
}