{
  "type": "Feature",
  "properties": {
    "iso:country":"FR",
    "sg:address":"Allee Louis Breguet Zac Les Merisiers 93420 Villepinte",
    "sg:classifiers":[
        {
            "category":"Professional",
            "subcategory":"Engineering",
            "type":"Services"
        }
    ],
    "sg:phone":"+33 1 48 60 11 70",
    "sg:postcode":"93420",
    "sg:province":"Ile de France",
    "sg:tags":[
        "machine",
        "-",
        "mechanical"
    ],
    "wof:name":"La Main D'oeuvre Mecanique",
    "wof:placetype":"venue"
},
  "geometry": {"coordinates":[2.53979,48.955807],"type":"Point"}
}