{
  "type": "Feature",
  "properties": {
    "addr:full":"91020 Evry C\u00e9dex^^1, All\u00e9e de la Chartreuse, 91000 Evry Ile de France",
    "addr:postcode":"91020;91000",
    "addr:street":"Alle\u0301E De La Chartreuse",
    "iso:country":"FR",
    "sg:address":"91020 Evry C\u00e9dex^^1, All\u00e9e de la Chartreuse, 91000 Evry",
    "sg:orig_category":"Non-Classified Establishments",
    "sg:phone":"+33 1 60 91 42 49",
    "sg:province":"Ile de France",
    "wof:name":"Tracor Europe S.a.s.",
    "wof:placetype":"venue"
},
  "geometry": {"coordinates":[2.4293,48.624664],"type":"Point"}
}