{
  "type": "Feature",
  "properties": {
    "iso:country":"FR",
    "sg:address":"21 Bd Marius Vivier Merle 69003 Lyon",
    "sg:classifiers":[
        {
            "category":"Professional",
            "subcategory":"Business Services",
            "type":"Services"
        }
    ],
    "sg:phone":"+33 4 72 13 37 10",
    "sg:postcode":"69003",
    "sg:province":"Rhone-Alpes",
    "sg:tags":[
        "information",
        "advice",
        "technology",
        "software"
    ],
    "wof:name":"Steria Sa",
    "wof:placetype":"venue"
},
  "geometry": {"coordinates":[4.859186,45.7616],"type":"Point"}
}