{
  "type": "Feature",
  "properties": {
    "iso:country":"FR",
    "sg:address":"80, Rue de Cl\u00e9ry, 95830 Fr\u00e9m\u00e9court",
    "sg:orig_category":"Non-Classified Establishments",
    "sg:phone":"+33 1 34 66 64 43",
    "sg:postcode":"95830",
    "sg:province":"Ile de France",
    "wof:name":"Asch Industrie S.a.r.l.",
    "wof:placetype":"venue"
},
  "geometry": {"coordinates":[1.994089,49.121368],"type":"Point"}
}