{
  "type": "Feature",
  "properties": {
    "iso:country":"FR",
    "sg:address":"16, Bd Kennedy, 95110 Sannois",
    "sg:orig_category":"Non-Classified Establishments",
    "sg:phone":"+33 1 30 25 82 82",
    "sg:province":"Ile de France",
    "wof:name":"Imprimerie M\u00e9tais S.a",
    "wof:placetype":"venue"
},
  "geometry": {"coordinates":[2.25625,48.97221],"type":"Point"}
}