{
  "type": "Feature",
  "properties": {
    "iso:country":"FR",
    "sg:address":"B.P. 9162, 69263 Lyon C\u00e9dex 9^^52, Rue Joann\u00e8s Carret, 69009 Lyon",
    "sg:orig_category":"Non-Classified Establishments",
    "sg:phone":"+33 4 72 53 14 00",
    "sg:province":"Rhone-Alpes",
    "wof:name":"S.c.r. Ma\u00e7on S.a.",
    "wof:placetype":"venue"
},
  "geometry": {"coordinates":[4.805335,45.774105],"type":"Point"}
}