{
  "type": "Feature",
  "properties": {
    "iso:country":"FR",
    "sg:address":"Route De La Trappe 61380 Soligny La Trappe",
    "sg:city":"Sainte-C\u00e9ronne-l\u00e8s-Mortagne",
    "sg:classifiers":[
        {
            "category":"Shopping",
            "subcategory":"Clothing, Apparel, & Fashions",
            "type":"Retail Goods"
        }
    ],
    "sg:phone":"+33 2 33 34 50 17",
    "sg:postcode":"61380",
    "sg:province":"Basse Normandie",
    "sg:tags":[
        "textile",
        "clothing",
        "clothes"
    ],
    "wof:name":"Eurl Charles Andrea",
    "wof:placetype":"venue"
},
  "geometry": {"coordinates":[0.532155,48.568153],"type":"Point"}
}