{
  "type": "Feature",
  "properties": {
    "iso:country":"FR",
    "sg:address":"8, Rue Traversi\u00e8re, 95000 Cergy",
    "sg:orig_category":"Non-Classified Establishments",
    "sg:phone":"+33 1 34 25 54 54",
    "sg:province":"Ile de France",
    "wof:name":"Prosilog S.a.r.l.",
    "wof:placetype":"venue"
},
  "geometry": {"coordinates":[2.076668,49.037174],"type":"Point"}
}