{
  "type": "Feature",
  "properties": {
    "addr:full":"14 rue du Quatre Septembre, 75002 Paris, Dept 75 Ile de France 75002",
    "addr:housenumber":"14;75",
    "addr:postcode":"75002;75002",
    "addr:street":"Rue Du Quatre Septembre;Ile De France",
    "iso:country":"FR",
    "sg:address":"14 rue du Quatre Septembre, 75002 Paris, Dept 75",
    "sg:classifiers":[
        {
            "category":"Banks & Credit Unions",
            "subcategory":"Bank",
            "type":"Services"
        }
    ],
    "sg:postcode":"75002",
    "sg:province":"Ile de France",
    "wof:name":"Credit D'equipement Des Pme",
    "wof:placetype":"venue"
},
  "geometry": {"coordinates":[2.337003,48.869617],"type":"Point"}
}