{
  "type": "Feature",
  "properties": {
    "iso:country":"FR",
    "sg:address":"22A, Rte d'Altkirch, 68720 Illfurth",
    "sg:city":"Illfurth",
    "sg:orig_category":"Unclassifiable Establishments",
    "sg:phone":"+33 3 89 25 48 43",
    "sg:postcode":"68720",
    "sg:province":"Alsace",
    "wof:name":"Lingelser Menuiserie S.a.r.l.",
    "wof:placetype":"venue"
},
  "geometry": {"coordinates":[7.264944,47.670765],"type":"Point"}
}