{
  "type": "Feature",
  "properties": {
    "iso:country":"FR",
    "sg:address":"Bourdassou 09140 Soueix Rogalle",
    "sg:orig_category":"Non-Classified Establishments",
    "sg:phone":"+33 5 61 66 82 82",
    "sg:postcode":"09140",
    "sg:province":"Midi Pyr\u00e9n\u00e9es",
    "wof:name":"Chamoley",
    "wof:placetype":"venue"
},
  "geometry": {"coordinates":[1.23528,42.840607],"type":"Point"}
}