{
  "type": "Feature",
  "properties": {
    "addr:full":"B.P. 29, 47250 Bon Encontre^^ZI de la Ville, 47240 Bon Encontre Bon-Encontre Aquitaine 47240",
    "addr:postcode":"47250;47240;47240",
    "addr:street":"B.P. 29;Bon",
    "iso:country":"FR",
    "sg:address":"B.P. 29, 47250 Bon Encontre^^ZI de la Ville, 47240 Bon Encontre",
    "sg:city":"Bon-Encontre",
    "sg:orig_category":"Non-Classified Establishments",
    "sg:phone":"+33 5 53 77 33 20",
    "sg:postcode":"47240",
    "sg:province":"Aquitaine",
    "wof:name":"Laffaye Et Begu\u00e9 S.a.",
    "wof:placetype":"venue"
},
  "geometry": {"coordinates":[0.698695,44.16959],"type":"Point"}
}