{
  "type": "Feature",
  "properties": {
    "iso:country":"FR",
    "sg:address":"563, Chemin de Beauregard, 13100 Aix en Provence",
    "sg:orig_category":"Non-Classified Establishments",
    "sg:phone":"+33 4 42 23 17 14",
    "sg:province":"Nord Pas-de-Calais",
    "wof:name":"Jacques Croce",
    "wof:placetype":"venue"
},
  "geometry": {"coordinates":[5.467257,43.536823],"type":"Point"}
}