{
  "type": "Feature",
  "properties": {
    "addr:full":"10, Rue de Brotterode - ZI, 38950 Saint Martin le Vinoux Rhone-Alpes 38950",
    "addr:housenumber":"10;38950",
    "addr:postcode":"38950",
    "addr:street":"Rue De Brotterode Zi;Martin Le;Rhone-Alpes",
    "iso:country":"FR",
    "sg:address":"10, Rue de Brotterode - ZI, 38950 Saint Martin le Vinoux",
    "sg:orig_category":"Unclassifiable Establishments",
    "sg:phone":"+33 4 76 75 66 45",
    "sg:postcode":"38950",
    "sg:province":"Rhone-Alpes",
    "wof:name":"R.i.d.e.c. S.a. - Repr\u00e9sentation Industrielle Distribution Des Emba",
    "wof:placetype":"venue"
},
  "geometry": {"coordinates":[5.716783,45.201359],"type":"Point"}
}