{
  "type": "Feature",
  "properties": {
    "addr:full":"7, Rue du Canal, 93420 Villepinte Ile de France",
    "addr:housenumber":"7",
    "addr:postcode":"93420",
    "addr:street":"Rue Du Canal;Ile De France",
    "iso:country":"FR",
    "sg:address":"7, Rue du Canal, 93420 Villepinte",
    "sg:orig_category":"Unclassifiable Establishments",
    "sg:phone":"+33 1 48 63 01 01",
    "sg:province":"Ile de France",
    "wof:name":"Trafag S.a.r.l.",
    "wof:placetype":"venue"
},
  "geometry": {"coordinates":[2.513245,48.975056],"type":"Point"}
}