{
  "type": "Feature",
  "properties": {
    "addr:full":"31, Bd des Etines, 42120 Le Coteau Rhone-Alpes",
    "addr:housenumber":"31",
    "addr:postcode":"42120",
    "addr:street":"Bd Des Etines;Rhone-Alpes",
    "iso:country":"FR",
    "sg:address":"31, Bd des Etines, 42120 Le Coteau",
    "sg:orig_category":"Unclassifiable Establishments",
    "sg:phone":"+33 4 77 67 14 44",
    "sg:province":"Rhone-Alpes",
    "wof:name":"Etablissements Desbenoit S.a.",
    "wof:placetype":"venue"
},
  "geometry": {"coordinates":[4.091705,46.022202],"type":"Point"}
}