{
  "type": "Feature",
  "properties": {
    "addr:full":"Rte de Pomerols Florensac Languedoc-Roussillon 34510",
    "addr:postcode":"34510",
    "addr:street":"Rte De Pomerols",
    "iso:country":"FR",
    "sg:address":"Rte de Pomerols",
    "sg:city":"Florensac",
    "sg:orig_category":"Unclassifiable Establishments",
    "sg:phone":"+33 4 67 77 00 36",
    "sg:postcode":"34510",
    "sg:province":"Languedoc-Roussillon",
    "wof:name":"Magne S.a.",
    "wof:placetype":"venue"
},
  "geometry": {"coordinates":[3.47136,43.3848],"type":"Point"}
}