{
  "type": "Feature",
  "properties": {
    "iso:country":"FR",
    "sg:address":"Quartier les Levades",
    "sg:city":"Rognac",
    "sg:orig_category":"Non-Classified Establishments",
    "sg:phone":"+33 4 42 87 05 18",
    "sg:postcode":"13340",
    "sg:province":"Provence-Alpes-C\u00f4te d'Azur",
    "wof:name":"A.d.f.t.e. S.a.r.l.",
    "wof:placetype":"venue"
},
  "geometry": {"coordinates":[5.229803,43.48933],"type":"Point"}
}