{
  "type": "Feature",
  "properties": {
    "iso:country":"FR",
    "sg:address":"9 Rue Sorbon 51370 St Brice Courcelles",
    "sg:orig_category":"Miscellaneous Products",
    "sg:phone":"+33 3 26 87 17 34",
    "sg:postcode":"51370",
    "sg:province":"Champagne",
    "wof:name":"Nicopack Emballage Sa",
    "wof:placetype":"venue"
},
  "geometry": {"coordinates":[3.99056,49.267254],"type":"Point"}
}