{
  "type": "Feature",
  "properties": {
    "addr:full":"B.P. 23, 86440 Migne Auxances C\u00e9dex^^Rte de Saumur - ZAC, 86440 Migne Auxances Poitou-Charentes 86440",
    "addr:postcode":"86440;86440;86440",
    "addr:street":"B.P. 23;Zac;Auxances",
    "iso:country":"FR",
    "sg:address":"B.P. 23, 86440 Migne Auxances C\u00e9dex^^Rte de Saumur - ZAC, 86440 Migne Auxances",
    "sg:orig_category":"Non-Classified Establishments",
    "sg:phone":"+33 5 49 51 64 64",
    "sg:postcode":"86440",
    "sg:province":"Poitou-Charentes",
    "wof:name":"Dauphin Communication S.a.",
    "wof:placetype":"venue"
},
  "geometry": {"coordinates":[0.311651,46.626766],"type":"Point"}
}