{
  "type": "Feature",
  "properties": {
    "iso:country":"FR",
    "sg:address":"2269",
    "sg:city":"Lou Mistraou 83230 Bormes les Mimosas",
    "sg:classifiers":[
        {
            "category":"Shopping",
            "subcategory":"Pharmacy",
            "type":"Retail Goods"
        }
    ],
    "sg:phone":"+33 4 94 01 59 00",
    "sg:province":"Champagne",
    "sg:tags":[
        "chemical",
        "pharmaceutical",
        "cosmetic"
    ],
    "wof:name":"Savonnerie De Bormes",
    "wof:placetype":"venue"
},
  "geometry": {"coordinates":[6.333717,43.142117],"type":"Point"}
}