{
  "type": "Feature",
  "properties": {
    "addr:full":"Lieu-Dit La Maillerie 16600 TOUVRE Poitou-Charentes 16600",
    "addr:postcode":"16600;16600",
    "addr:street":"Lieu-Dit La Maillerie",
    "iso:country":"FR",
    "sg:address":"Lieu-Dit La Maillerie 16600 TOUVRE",
    "sg:orig_category":"Caoutchouc",
    "sg:phone":"+33 5 45 68 41 88",
    "sg:postcode":"16600",
    "sg:province":"Poitou-Charentes",
    "wof:name":"Ste Indust Diverses Applic Caoutchouc Sidiac Sa",
    "wof:placetype":"venue"
},
  "geometry": {"coordinates":[0.245592,45.664047],"type":"Point"}
}