{
  "type": "Feature",
  "properties": {
    "iso:country":"FR",
    "sg:address":"55 r Georges Cl\u00e9menceau; Cours",
    "sg:classifiers":[
        {
            "category":"Banks & Credit Unions",
            "subcategory":"Bank",
            "type":"Services"
        }
    ],
    "sg:phone":"+33 3374897151",
    "sg:province":"Midi Pyr\u00e9n\u00e9es",
    "wof:name":"Cr\u00e9dit Lyonnais",
    "wof:placetype":"venue"
},
  "geometry": {"coordinates":[-71.58110000000001,44.783298],"type":"Point"}
}