{
  "type": "Feature",
  "properties": {
    "addr:full":"4195, Av. de Bordeaux Saint Jean d'Illac, 33127 Saint Jean d'Illac Martignas-sur-Jalle Aquitaine 33127",
    "addr:housenumber":"4195",
    "addr:postcode":"33127;33127",
    "addr:street":"Av. De Bordeaux Saint Jean D'Illac",
    "iso:country":"FR",
    "sg:address":"4195, Av. de Bordeaux Saint Jean d'Illac, 33127 Saint Jean d'Illac",
    "sg:city":"Martignas-sur-Jalle",
    "sg:orig_category":"Unclassifiable Establishments",
    "sg:phone":"+33 5 57 92 16 80",
    "sg:postcode":"33127",
    "sg:province":"Aquitaine",
    "wof:name":"S.e.r.t.a. S.a. - Soci\u00e9t\u00e9 D'etudes Et R\u00e9alisations Techniques D'aqu",
    "wof:placetype":"venue"
},
  "geometry": {"coordinates":[-0.77956,44.811649],"type":"Point"}
}