{
  "type": "Feature",
  "properties": {
    "iso:country":"FR",
    "sg:address":"43 Rue De La Lib\u00e9ration 57870 Troisfontaines",
    "sg:classifiers":[
        {
            "category":"Manufacturing",
            "subcategory":"Glass & Minerals",
            "type":"Manufacturing & Wholesale Goods"
        }
    ],
    "sg:phone":"+33 3 87 23 10 11",
    "sg:postcode":"57870",
    "sg:province":"Lorraine",
    "sg:tags":[
        "building",
        "material"
    ],
    "wof:name":"Schott Vtf Sarl",
    "wof:placetype":"venue"
},
  "geometry": {"coordinates":[7.122313,48.674927],"type":"Point"}
}