{
  "type": "Feature",
  "properties": {
    "addr:full":"B.P. 39, 91322 Wissous C\u00e9dex^^56, Rue Victor Baloche, 91320 Wissous Ile de France",
    "addr:postcode":"91322;91320;ile",
    "addr:street":"B.P. 39;Rue Victor Baloche",
    "iso:country":"FR",
    "sg:address":"B.P. 39, 91322 Wissous C\u00e9dex^^56, Rue Victor Baloche, 91320 Wissous",
    "sg:orig_category":"Non-Classified Establishments",
    "sg:phone":"+33 1 69 20 00 83",
    "sg:province":"Ile de France",
    "wof:name":"Exocat S.a.r.l.",
    "wof:placetype":"venue"
},
  "geometry": {"coordinates":[2.32612,48.731461],"type":"Point"}
}