{
  "type": "Feature",
  "properties": {
    "iso:country":"FR",
    "sg:address":"24, Rue Lavoisier - ZA Belle Aire, 17440 Aytr\u00e9",
    "sg:orig_category":"Non-Classified Establishments",
    "sg:phone":"+33 5 46 07 44 40",
    "sg:province":"Poitou-Charentes",
    "wof:name":"K.e.p. France S.a.",
    "wof:placetype":"venue"
},
  "geometry": {"coordinates":[-1.113492,46.133381],"type":"Point"}
}