{
  "type": "Feature",
  "properties": {
    "addr:full":"chemin du petit Pr\u00e9s 79270 Le Vanneau Irleau Poitou-Charentes 79270",
    "addr:postcode":"79270;79270",
    "addr:street":"Chemin Du Petit Pre\u0301S;Vanneau Irleau",
    "iso:country":"FR",
    "sg:address":"chemin du petit Pr\u00e9s 79270 Le Vanneau Irleau",
    "sg:classifiers":[
        {
            "category":"Manufacturing",
            "subcategory":"Motor Vehicles & Parts",
            "type":"Manufacturing & Wholesale Goods"
        }
    ],
    "sg:phone":"+33 5 49 35 00 61",
    "sg:postcode":"79270",
    "sg:province":"Poitou-Charentes",
    "sg:tags":[
        "construction",
        "board",
        "plywood"
    ],
    "wof:name":"Ets A. Math\u00e9 Sa",
    "wof:placetype":"venue"
},
  "geometry": {"coordinates":[-0.586446,46.205681],"type":"Point"}
}