{
  "type": "Feature",
  "properties": {
    "addr:full":"6 Aubuisson 31000 Toulouse Midi Pyr\u00e9n\u00e9es",
    "addr:housenumber":"6",
    "addr:postcode":"31000",
    "addr:street":"Aubuisson",
    "iso:country":"FR",
    "sg:address":"6",
    "sg:city":"Aubuisson 31000 Toulouse",
    "sg:classifiers":[
        {
            "category":"Manufacturing",
            "subcategory":"Printing",
            "type":"Manufacturing & Wholesale Goods"
        }
    ],
    "sg:phone":"+33 5 62 73 40 50",
    "sg:province":"Midi Pyr\u00e9n\u00e9es",
    "sg:tags":[
        "publishing"
    ],
    "wof:name":"Copie Minute",
    "wof:placetype":"venue"
},
  "geometry": {"coordinates":[1.451191,43.603851],"type":"Point"}
}