{
  "type": "Feature",
  "properties": {
    "iso:country":"FR",
    "sg:address":"ZI",
    "sg:city":"Pringy",
    "sg:orig_category":"Unclassifiable Establishments",
    "sg:phone":"+33 4 50 66 96 22",
    "sg:postcode":"74370",
    "sg:province":"Rhone-Alpes",
    "wof:name":"Varilec S.a.",
    "wof:placetype":"venue"
},
  "geometry": {"coordinates":[6.109395,45.934166],"type":"Point"}
}