{
  "type": "Feature",
  "properties": {
    "addr:full":"11 Rue Du Rond Point 74960 Cran Gevrier Rhone-Alpes 74960",
    "addr:housenumber":"11",
    "addr:postcode":"74960;74960",
    "addr:street":"Rue Du Rond Point;Rhone-Alpes",
    "iso:country":"FR",
    "sg:address":"11 Rue Du Rond Point 74960 Cran Gevrier",
    "sg:classifiers":[
        {
            "category":"Manufacturing",
            "subcategory":"Metals",
            "type":"Manufacturing & Wholesale Goods"
        }
    ],
    "sg:phone":"+33 4 50 45 19 44",
    "sg:postcode":"74960",
    "sg:province":"Rhone-Alpes",
    "sg:tags":[
        "metallurgy",
        "metalworking",
        "processing"
    ],
    "wof:name":"Sodep Site 3 Souzy",
    "wof:placetype":"venue"
},
  "geometry": {"coordinates":[6.111287,45.897007],"type":"Point"}
}