{
  "type": "Feature",
  "properties": {
    "iso:country":"FR",
    "sg:address":"12, Rue de la Sandlach, 67500 Haguenau",
    "sg:city":"Haguenau",
    "sg:orig_category":"Non-Classified Establishments",
    "sg:phone":"+33 3 88 90 53 60",
    "sg:postcode":"67500",
    "sg:province":"Alsace",
    "wof:name":"Trumpf Machines S.a.r.l.",
    "wof:placetype":"venue"
},
  "geometry": {"coordinates":[7.75968,48.831936],"type":"Point"}
}