{
  "type": "Feature",
  "properties": {
    "addr:full":"B.P. 73, 10003 Troyes C\u00e9dex^^113, Rue Edmond Fariat, 10000 Troyes Champagne",
    "addr:postcode":"10003;10000",
    "addr:street":"B.P. 73;Rue Edmond Fariat",
    "iso:country":"FR",
    "sg:address":"B.P. 73, 10003 Troyes C\u00e9dex^^113, Rue Edmond Fariat, 10000 Troyes",
    "sg:orig_category":"Non-Classified Establishments",
    "sg:phone":"+33 3 25 82 90 00",
    "sg:province":"Champagne",
    "wof:name":"Royal Moto France S.a.",
    "wof:placetype":"venue"
},
  "geometry": {"coordinates":[4.074345,48.297874],"type":"Point"}
}