{
  "type": "Feature",
  "properties": {
    "addr:full":"34 Route De Longjumeau Village D'Entreprise 91380 Chilly Mazarin Ile de France 91380",
    "addr:housenumber":"34",
    "addr:postcode":"91380;91380",
    "addr:street":"Route De Longjumeau Village D'Entreprise;Ile De France",
    "iso:country":"FR",
    "sg:address":"34 Route De Longjumeau Village D'Entreprise 91380 Chilly Mazarin",
    "sg:classifiers":[
        {
            "category":"Professional",
            "subcategory":"Engineering",
            "type":"Services"
        }
    ],
    "sg:phone":"+33 1 69 10 17 75",
    "sg:postcode":"91380",
    "sg:province":"Ile de France",
    "sg:tags":[
        "machine",
        "-",
        "mechanical"
    ],
    "wof:name":"Manuli Sonatra",
    "wof:placetype":"venue"
},
  "geometry": {"coordinates":[2.296633,48.704918],"type":"Point"}
}