{
  "type": "Feature",
  "properties": {
    "iso:country":"FR",
    "sg:address":"97 Boulevard St Michel 91150 Etampes",
    "sg:classifiers":[
        {
            "category":"Professional",
            "type":"Services"
        }
    ],
    "sg:phone":"+33 1 64 94 13 85",
    "sg:province":"Ile de France",
    "sg:tags":[
        "transport",
        "road"
    ],
    "wof:name":"Ambulances Saint Gilles",
    "wof:placetype":"venue"
},
  "geometry": {"coordinates":[2.170553,48.446827],"type":"Point"}
}