{
  "type": "Feature",
  "properties": {
    "addr:full":"101 blvd G\u00e9n\u00e9ral de Gaulle; Hendaye; 64700 Hendaye Aquitaine 64700",
    "addr:housenumber":"101",
    "addr:postcode":"64700;64700",
    "addr:street":"Blvd Ge\u0301Ne\u0301Ral De Gaulle",
    "iso:country":"FR",
    "sg:address":"101 blvd G\u00e9n\u00e9ral de Gaulle; Hendaye; 64700",
    "sg:city":"Hendaye",
    "sg:classifiers":[
        {
            "category":"Banks & Credit Unions",
            "subcategory":"Bank",
            "type":"Services"
        }
    ],
    "sg:phone":"+33 5 59 20 79 70",
    "sg:postcode":"64700",
    "sg:province":"Aquitaine",
    "wof:name":"Banque Franco, Portugaise Sa",
    "wof:placetype":"venue"
},
  "geometry": {"coordinates":[-1.781504,43.352589],"type":"Point"}
}