{
  "type": "Feature",
  "properties": {
    "iso:country":"FR",
    "sg:address":"410 Route De Thones Cites D Entreprises 74210 Faverges",
    "sg:classifiers":[
        {
            "category":"Manufacturing",
            "subcategory":"Tools & Machinery",
            "type":"Manufacturing & Wholesale Goods"
        }
    ],
    "sg:phone":"+33 4 50 32 58 90",
    "sg:province":"Rhone-Alpes",
    "sg:tags":[
        "metallurgy",
        "metalworking"
    ],
    "wof:name":"A N C A",
    "wof:placetype":"venue"
},
  "geometry": {"coordinates":[6.299244,45.724998],"type":"Point"}
}