{
  "type": "Feature",
  "properties": {
    "iso:country":"FR",
    "sg:address":"Rue des Coop\u00e9rateurs",
    "sg:city":"Denain",
    "sg:orig_category":"Unclassifiable Establishments",
    "sg:phone":"+33 3 27 23 50 50",
    "sg:postcode":"59220",
    "sg:province":"Nord Pas-de-Calais",
    "wof:name":"Sada Et Compagnie S.a.",
    "wof:placetype":"venue"
},
  "geometry": {"coordinates":[3.389829,50.335659],"type":"Point"}
}