{
  "type": "Feature",
  "properties": {
    "iso:country":"FR",
    "sg:address":"3, Rue des Longs Pr\u00e9s, 92100 Boulogne Billancourt",
    "sg:orig_category":"Unclassifiable Establishments",
    "sg:phone":"+33 1 47 61 91 61",
    "sg:province":"Ile de France",
    "wof:name":"Arts Affaires S.a.r.l.",
    "wof:placetype":"venue"
},
  "geometry": {"coordinates":[2.246377,48.832905],"type":"Point"}
}