{
  "type": "Feature",
  "properties": {
    "iso:country":"FR",
    "sg:address":"16, Rue Joseph Bertolo, 01200 Bellegarde sur Valserine",
    "sg:orig_category":"Unclassifiable Establishments",
    "sg:phone":"+33 4 50 48 23 44",
    "sg:province":"Rhone-Alpes",
    "wof:name":"Entreprise Marbrerie Bianchi Olivier Puech S.a.r.l.",
    "wof:placetype":"venue"
},
  "geometry": {"coordinates":[5.825243,46.10894],"type":"Point"}
}