{
  "type": "Feature",
  "properties": {
    "iso:country":"FR",
    "sg:address":"B.P. 201, 13156 Tarascon C\u00e9dex^^Parc d'Activit\u00e9 de Laurade, 13103 Saint Etienne du Gr\u00e9s",
    "sg:orig_category":"Non-Classified Establishments",
    "sg:phone":"+33 4 90 18 70 00",
    "sg:province":"Midi Pyr\u00e9n\u00e9es",
    "wof:name":"Arbex S.a.",
    "wof:placetype":"venue"
},
  "geometry": {"coordinates":[4.391736,45.449642],"type":"Point"}
}