{
  "type": "Feature",
  "properties": {
    "iso:country":"FR",
    "sg:address":"4, Quai Sable, 67150 Erstein",
    "sg:city":"Erstein",
    "sg:orig_category":"Non-Classified Establishments",
    "sg:phone":"+33 3 88 98 17 43",
    "sg:postcode":"67150",
    "sg:province":"Alsace",
    "wof:name":"G.t.s. S.a.r.l. - Gousset T\u00e9l\u00e9communications Services",
    "wof:placetype":"venue"
},
  "geometry": {"coordinates":[7.66449,48.423077],"type":"Point"}
}