{
  "type": "Feature",
  "properties": {
    "addr:full":"29 Av Du 45\u00e8me Parall\u00e8le 26600 Pont De L'Is\u00e8re Rhone-Alpes 26600",
    "addr:postcode":"26600;26600",
    "addr:street":"29 Av Du 45E\u0300Me Paralle\u0300Le;Rhone-Alpes",
    "iso:country":"FR",
    "sg:address":"29 Av Du 45\u00e8me Parall\u00e8le 26600 Pont De L'Is\u00e8re",
    "sg:classifiers":[
        {
            "category":"Travel",
            "subcategory":"Hotels & Motels",
            "type":"Entertainment"
        }
    ],
    "sg:phone":"+33 4 75 84 60 09",
    "sg:postcode":"26600",
    "sg:province":"Rhone-Alpes",
    "sg:tags":[
        "hotels",
        "business",
        "restaurant"
    ],
    "wof:name":"Michel Chabran Sa",
    "wof:placetype":"venue"
},
  "geometry": {"coordinates":[4.869987,45.00835],"type":"Point"}
}