{
  "type": "Feature",
  "properties": {
    "iso:country":"FR",
    "sg:address":"2BIS rue Nicolas Houel 75005 Paris",
    "sg:classifiers":[
        {
            "category":"Building & Trades",
            "subcategory":"Construction",
            "type":"Services"
        }
    ],
    "sg:phone":"+33 1 44 08 87 50",
    "sg:postcode":"75005",
    "sg:province":"Ile de France",
    "sg:tags":[
        "consulting",
        "management",
        "commercial",
        "operation"
    ],
    "wof:name":"B C M W Sa",
    "wof:placetype":"venue"
},
  "geometry": {"coordinates":[2.363033,48.842007],"type":"Point"}
}