{
  "type": "Feature",
  "properties": {
    "addr:full":"Ch\u00e2teau Belon Saint Morillon Aquitaine 33650",
    "addr:postcode":"33650",
    "addr:street":"Saint",
    "iso:country":"FR",
    "sg:address":"Ch\u00e2teau Belon",
    "sg:city":"Saint Morillon",
    "sg:orig_category":"Unclassifiable Establishments",
    "sg:phone":"+33 5 56 20 30 35",
    "sg:postcode":"33650",
    "sg:province":"Aquitaine",
    "wof:name":"Vignobles Depiot - Ch\u00e2teau Belon S.c.e.a.",
    "wof:placetype":"venue"
},
  "geometry": {"coordinates":[-0.532935,44.646469],"type":"Point"}
}