{
  "type": "Feature",
  "properties": {
    "addr:full":"Rue De St Martin 62120 Aire Sur La Lys Nord Pas-de-Calais",
    "addr:postcode":"62120",
    "addr:street":"Rue De St Martin;Aire;La Lys Nord",
    "iso:country":"FR",
    "sg:address":"Rue De St Martin 62120 Aire Sur La Lys",
    "sg:classifiers":[
        {
            "category":"Professional",
            "type":"Services"
        }
    ],
    "sg:phone":"+33 3 21 38 45 99",
    "sg:province":"Nord Pas-de-Calais",
    "sg:tags":[
        "transport",
        "road"
    ],
    "wof:name":"Transports Carette Sa",
    "wof:placetype":"venue"
},
  "geometry": {"coordinates":[2.393883,50.647457],"type":"Point"}
}