{
  "type": "Feature",
  "properties": {
    "addr:full":"rue du Wachen, 67002 Strasbourg, Dept 67 Strasbourg Alsace 67000",
    "addr:housenumber":"67",
    "addr:postcode":"67002;67000",
    "addr:street":"Rue Du Wachen;Strasbourg",
    "iso:country":"FR",
    "sg:address":"rue du Wachen, 67002 Strasbourg, Dept 67",
    "sg:city":"Strasbourg",
    "sg:classifiers":[
        {
            "category":"Banks & Credit Unions",
            "subcategory":"Bank",
            "type":"Services"
        }
    ],
    "sg:postcode":"67000",
    "sg:province":"Alsace",
    "wof:name":"Caisse F\u00e9d\u00e9rale Du Cm Centre Est Europe",
    "wof:placetype":"venue"
},
  "geometry": {"coordinates":[7.754222,48.600304],"type":"Point"}
}