{
  "type": "Feature",
  "properties": {
    "addr:full":"12-14 Rond Point des; Paris; 75008 Ile de France 75008",
    "addr:housenumber":"12-14",
    "addr:postcode":"75008;75008",
    "addr:street":"Rond Point Des Paris;France",
    "iso:country":"FR",
    "sg:address":"12-14 Rond Point des; Paris; 75008",
    "sg:classifiers":[
        {
            "category":"Banks & Credit Unions",
            "subcategory":"Bank",
            "type":"Services"
        }
    ],
    "sg:phone":"+33 1 45 50 90 00",
    "sg:postcode":"75008",
    "sg:province":"Ile de France",
    "wof:name":"Banque Saint Dominique, Natexis Groupe",
    "wof:placetype":"venue"
},
  "geometry": {"coordinates":[2.34121,48.856926],"type":"Point"}
}