{
  "type": "Feature",
  "properties": {
    "iso:country":"FR",
    "sg:address":"rue Jean Louis Guiot 67220 Neuve Eglise",
    "sg:city":"Alb\u00e9",
    "sg:classifiers":[
        {
            "category":"Banks & Credit Unions",
            "subcategory":"Financial Services",
            "type":"Services"
        }
    ],
    "sg:phone":"+33 3 88 58 98 93",
    "sg:postcode":"67220",
    "sg:province":"Alsace",
    "sg:tags":[
        "card",
        "smart"
    ],
    "wof:name":"Larisys Sarl",
    "wof:placetype":"venue"
},
  "geometry": {"coordinates":[7.317296,48.336048],"type":"Point"}
}