{
  "type": "Feature",
  "properties": {
    "iso:country":"FR",
    "sg:address":"ZA La Nouvelle Energie",
    "sg:city":"Comines",
    "sg:orig_category":"Unclassifiable Establishments",
    "sg:phone":"+33 3 20 39 05 55",
    "sg:postcode":"59560",
    "sg:province":"Nord Pas-de-Calais",
    "wof:name":"Schoutteten Georges Et Fils S.a.r.l.",
    "wof:placetype":"venue"
},
  "geometry": {"coordinates":[3.006479,50.764984],"type":"Point"}
}