{
  "type": "Feature",
  "properties": {
    "addr:full":"9, Rue des Millesoupes, 78126 Aulnay sur Mauldre Ile de France",
    "addr:housenumber":"9",
    "addr:postcode":"78126",
    "addr:street":"Rue Des Millesoupes",
    "iso:country":"FR",
    "sg:address":"9, Rue des Millesoupes, 78126 Aulnay sur Mauldre",
    "sg:orig_category":"Non-Classified Establishments",
    "sg:phone":"+33 1 34 75 84 43",
    "sg:province":"Ile de France",
    "wof:name":"S\u00e9rigraphie D\u00e9cor S.a.r.l.",
    "wof:placetype":"venue"
},
  "geometry": {"coordinates":[1.844214,48.929054],"type":"Point"}
}