{
  "type": "Feature",
  "properties": {
    "addr:full":"3, Rue Saint Lubin, 41000 Blois Blois Centre 41000",
    "addr:housenumber":"3",
    "addr:postcode":"41000;41000",
    "addr:street":"Rue Saint",
    "iso:country":"FR",
    "sg:address":"3, Rue Saint Lubin, 41000 Blois",
    "sg:city":"Blois",
    "sg:orig_category":"Unclassifiable Establishments",
    "sg:phone":"+33 2 54 78 40 30",
    "sg:postcode":"41000",
    "sg:province":"Centre",
    "wof:name":"Institut De L'audition Du Val De Loire S.a.r.l.",
    "wof:placetype":"venue"
},
  "geometry": {"coordinates":[1.33272,47.585491],"type":"Point"}
}