{
  "type": "Feature",
  "properties": {
    "iso:country":"FR",
    "sg:address":"Rue Du Pre Brenot Zac Valentin 25870 Chatillon Le Duc",
    "sg:classifiers":[
        {
            "category":"Wholesale",
            "subcategory":"Machinery & Supplies",
            "type":"Manufacturing & Wholesale Goods"
        }
    ],
    "sg:phone":"+33 3 81 50 05 94",
    "sg:province":"Franche Comt\u00e9",
    "sg:tags":[
        "equipment",
        "equipement",
        "precision",
        "timekeeping"
    ],
    "wof:name":"Seram",
    "wof:placetype":"venue"
},
  "geometry": {"coordinates":[6.006115,47.308216],"type":"Point"}
}