{
  "type": "Feature",
  "properties": {
    "iso:country":"FR",
    "sg:address":"Chemin des Aissi\u00e8res",
    "sg:city":"Saint Brisson sur Loire",
    "sg:orig_category":"Unclassifiable Establishments",
    "sg:phone":"+33 2 38 36 71 05",
    "sg:postcode":"45500",
    "sg:province":"Centre",
    "wof:name":"Arem S.a.",
    "wof:placetype":"venue"
},
  "geometry": {"coordinates":[2.604419,47.598969],"type":"Point"}
}