{
  "type": "Feature",
  "properties": {
    "iso:country":"FR",
    "sg:address":"27 ave de Jura; Ferney Voltaire",
    "sg:classifiers":[
        {
            "category":"Banks & Credit Unions",
            "subcategory":"Bank",
            "type":"Services"
        }
    ],
    "sg:phone":"+33 3350405546",
    "sg:province":"Champagne",
    "wof:name":"Banque Nationale De Paris",
    "wof:placetype":"venue"
},
  "geometry": {"coordinates":[6.105805,46.259869],"type":"Point"}
}