{
  "type": "Feature",
  "properties": {
    "iso:country":"FR",
    "sg:address":"B.P. 44, 95112 Sannois C\u00e9dex^^21, Rue du Docteur Emile Roux, 95110 Sannois",
    "sg:orig_category":"Non-Classified Establishments",
    "sg:phone":"+33 1 30 25 81 81",
    "sg:province":"Ile de France",
    "wof:name":"Stple S.n.c. - Soci\u00e9t\u00e9 De Travaux Publics L'essor",
    "wof:placetype":"venue"
},
  "geometry": {"coordinates":[2.25625,48.97221],"type":"Point"}
}