{
  "type": "Feature",
  "properties": {
    "iso:country":"FR",
    "sg:address":"1, Bd Malvoisine, 77185 Lognes",
    "sg:orig_category":"Unclassifiable Establishments",
    "sg:phone":"+33 1 64 80 54 49",
    "sg:province":"Ile de France",
    "wof:name":"Retravailler Ile De France",
    "wof:placetype":"venue"
},
  "geometry": {"coordinates":[2.630642,48.840748],"type":"Point"}
}