{
  "type": "Feature",
  "properties": {
    "iso:country":"FR",
    "sg:address":"B.P. 250, 94576 Rungis C\u00e9dex^^516, Rue de la Tour, 94550 Chevilly Larue",
    "sg:orig_category":"Non-Classified Establishments",
    "sg:phone":"+33 1 46 86 66 88",
    "sg:province":"Ile de France",
    "wof:name":"Inter Agro S.a.r.l.",
    "wof:placetype":"venue"
},
  "geometry": {"coordinates":[2.35062,48.770672],"type":"Point"}
}