{
  "type": "Feature",
  "properties": {
    "iso:country":"FR",
    "sg:address":"155 Quai Aulagnier 92600 Asni\u00e8res Sur Seine",
    "sg:classifiers":[
        {
            "category":"Professional",
            "subcategory":"Engineering",
            "type":"Services"
        }
    ],
    "sg:phone":"+33 1 47 93 39 52",
    "sg:postcode":"92600",
    "sg:province":"Ile de France",
    "sg:tags":[
        "machine",
        "-",
        "mechanical"
    ],
    "wof:name":"Erom See",
    "wof:placetype":"venue"
},
  "geometry": {"coordinates":[2.298733,48.911469],"type":"Point"}
}