{
  "type": "Feature",
  "properties": {
    "iso:country":"FR",
    "sg:address":"Rue Henri Barbuse",
    "sg:city":"Marpent",
    "sg:orig_category":"Unclassifiable Establishments",
    "sg:phone":"+33 3 27 68 68 00",
    "sg:postcode":"59164",
    "sg:province":"Nord Pas-de-Calais",
    "wof:name":"M.c.h. S.a.r.l. - M\u00e9canique Chaudronnerie Hydraulique Et Maintenance Industrielle",
    "wof:placetype":"venue"
},
  "geometry": {"coordinates":[4.07724,50.293968],"type":"Point"}
}