{
  "type": "Feature",
  "properties": {
    "addr:full":"6, Rue Brillat Savarin - Magasin la Vall\u00e9e d'eau, 01160 Pont d'Ain Rhone-Alpes",
    "addr:housenumber":"6",
    "addr:postcode":"01160",
    "addr:street":"Rue Brillat Savarin Magasin La;D'Eau;D'Ain Rhone-Alpes",
    "iso:country":"FR",
    "sg:address":"6, Rue Brillat Savarin - Magasin la Vall\u00e9e d'eau, 01160 Pont d'Ain",
    "sg:orig_category":"Unclassifiable Establishments",
    "sg:phone":"+33 4 74 39 15 35",
    "sg:province":"Rhone-Alpes",
    "wof:name":"Entreprise Bouilloud Jean",
    "wof:placetype":"venue"
},
  "geometry": {"coordinates":[5.607583,45.973366],"type":"Point"}
}