{
  "type": "Feature",
  "properties": {
    "addr:full":"Bd Fran\u00e7ois Arago - Les Colonnes Blanches Chauray Poitou-Charentes 79180",
    "addr:postcode":"79180",
    "addr:street":"Bd Franc\u0327Ois Arago;Blanches",
    "iso:country":"FR",
    "sg:address":"Bd Fran\u00e7ois Arago - Les Colonnes Blanches",
    "sg:city":"Chauray",
    "sg:orig_category":"Unclassifiable Establishments",
    "sg:phone":"+33 5 49 17 39 00",
    "sg:postcode":"79180",
    "sg:province":"Poitou-Charentes",
    "wof:name":"Scriba S.a.",
    "wof:placetype":"venue"
},
  "geometry": {"coordinates":[-0.372754,46.361385],"type":"Point"}
}