{
  "type": "Feature",
  "properties": {
    "addr:full":"Zone Artisanale Du Puynardon 85290 Mortagne Sur Sevre Pays de Loire 85290",
    "addr:postcode":"85290;sur sevre;85290",
    "addr:street":"Zone Artisanale Du Puynardon",
    "iso:country":"FR",
    "sg:address":"Zone Artisanale Du Puynardon 85290 Mortagne Sur Sevre",
    "sg:classifiers":[
        {
            "category":"Shopping",
            "subcategory":"Crafts & Fabrics",
            "type":"Retail Goods"
        }
    ],
    "sg:phone":"+33 2 51 65 04 44",
    "sg:postcode":"85290",
    "sg:province":"Pays de Loire",
    "sg:tags":[
        "textile",
        "linen",
        "clothing"
    ],
    "wof:name":"Clc Sarl",
    "wof:placetype":"venue"
},
  "geometry": {"coordinates":[-0.953982,46.994831],"type":"Point"}
}