{
  "type": "Feature",
  "properties": {
    "iso:country":"FR",
    "sg:address":"Za De Penprat 29600 Ste-S\u00e8ve",
    "sg:city":"Morlaix",
    "sg:classifiers":[
        {
            "category":"Building & Trades",
            "subcategory":"Construction",
            "type":"Services"
        }
    ],
    "sg:phone":"+33 2 98 88 73 26",
    "sg:postcode":"29600",
    "sg:province":"Bretagne",
    "sg:tags":[
        "work",
        "public"
    ],
    "wof:name":"Francois Beuzit",
    "wof:placetype":"venue"
},
  "geometry": {"coordinates":[-3.874559,48.556625],"type":"Point"}
}