{
  "type": "Feature",
  "properties": {
    "iso:country":"FR",
    "sg:address":"Domaine de la Plaine",
    "sg:city":"Saint Julien de Peyrolas",
    "sg:orig_category":"Unclassifiable Establishments",
    "sg:phone":"+33 4 66 82 18 12",
    "sg:postcode":"30760",
    "sg:province":"Languedoc-Roussillon",
    "wof:name":"Production Rieu S.a.r.l.",
    "wof:placetype":"venue"
},
  "geometry": {"coordinates":[4.56502,44.291088],"type":"Point"}
}