{
  "type": "Feature",
  "properties": {
    "iso:country":"FR",
    "sg:address":"3, Rue de la Grande Ourse, 95800 Cergy",
    "sg:orig_category":"Unclassifiable Establishments",
    "sg:phone":"+33 1 30 75 11 11",
    "sg:province":"Ile de France",
    "wof:name":"Time Designa S.a.",
    "wof:placetype":"venue"
},
  "geometry": {"coordinates":[2.029746,49.052937],"type":"Point"}
}