{
  "type": "Feature",
  "properties": {
    "iso:country":"FR",
    "sg:address":"176/178, Rue Montmartre, 75002 Paris",
    "sg:orig_category":"Unclassifiable Establishments",
    "sg:phone":"+33 1 42 36 04 26",
    "sg:province":"Ile de France",
    "wof:name":"T\u00e9l\u00e9 France Vid\u00e9o Club S.a.",
    "wof:placetype":"venue"
},
  "geometry": {"coordinates":[2.34321,48.871204],"type":"Point"}
}