{
  "type": "Feature",
  "properties": {
    "iso:country":"FR",
    "sg:address":"15, Rue T\u00e9xier Gallas, 28150 Voves",
    "sg:city":"Voves",
    "sg:orig_category":"Non-Classified Establishments",
    "sg:phone":"+33 2 37 99 15 15",
    "sg:postcode":"28150",
    "sg:province":"Centre",
    "wof:name":"Au Quai Fleuri",
    "wof:placetype":"venue"
},
  "geometry": {"coordinates":[1.629337,48.277519],"type":"Point"}
}