{
  "type": "Feature",
  "properties": {
    "addr:full":"Chanliau Za Bois De Chanliau 71200 Le Creusot Le Creusot Bourgogne 71200",
    "addr:postcode":"71200;71200",
    "addr:street":"Za Bois De Chanliau",
    "iso:country":"FR",
    "sg:address":"Chanliau Za Bois De Chanliau 71200 Le Creusot",
    "sg:city":"Le Creusot",
    "sg:classifiers":[
        {
            "category":"Building & Trades",
            "subcategory":"Construction",
            "type":"Services"
        }
    ],
    "sg:phone":"+33 3 85 56 23 93",
    "sg:postcode":"71200",
    "sg:province":"Bourgogne",
    "sg:tags":[
        "work",
        "public"
    ],
    "wof:name":"Pbp",
    "wof:placetype":"venue"
},
  "geometry": {"coordinates":[4.421295,46.806164],"type":"Point"}
}