{
  "type": "Feature",
  "properties": {
    "iso:country":"FR",
    "sg:address":"Rue de la R\u00e9publique - ZA",
    "sg:city":"Salom\u00e9",
    "sg:orig_category":"Unclassifiable Establishments",
    "sg:phone":"+33 3 28 55 11 80",
    "sg:postcode":"59496",
    "sg:province":"Nord Pas-de-Calais",
    "wof:name":"Sofilac S.a.",
    "wof:placetype":"venue"
},
  "geometry": {"coordinates":[2.840488,50.536152],"type":"Point"}
}