{
  "type": "Feature",
  "properties": {
    "addr:full":"Zi Rte De Domfort BP 64 61100 Flers Flers Basse Normandie 61100",
    "addr:housenumber":"64",
    "addr:postcode":"61100;61100",
    "addr:street":"Rte De Domfort Bp",
    "iso:country":"FR",
    "sg:address":"Zi Rte De Domfort BP 64 61100 Flers",
    "sg:city":"Flers",
    "sg:classifiers":[
        {
            "category":"Professional",
            "type":"Services"
        }
    ],
    "sg:phone":"+33 2 33 64 64 33",
    "sg:postcode":"61100",
    "sg:province":"Basse Normandie",
    "sg:tags":[
        "transport",
        "road"
    ],
    "wof:name":"Transport Noyon",
    "wof:placetype":"venue"
},
  "geometry": {"coordinates":[-0.568314,48.748585],"type":"Point"}
}