{
  "type": "Feature",
  "properties": {
    "addr:full":"11 Rue Pierre Blanche 91630 Cheptainville Ile de France 91630",
    "addr:housenumber":"11",
    "addr:postcode":"91630;91630",
    "addr:street":"Rue Pierre Blanche;Ile De France",
    "iso:country":"FR",
    "sg:address":"11 Rue Pierre Blanche 91630 Cheptainville",
    "sg:classifiers":[
        {
            "category":"Manufacturing",
            "subcategory":"Chemicals & Compounds",
            "type":"Manufacturing & Wholesale Goods"
        }
    ],
    "sg:phone":"+33 1 69 14 10 70",
    "sg:postcode":"91630",
    "sg:province":"Ile de France",
    "sg:tags":[
        "pharmaceutical",
        "chemistry",
        "-",
        "by-product"
    ],
    "wof:name":"Nordin (societe Des Freres) Sarl",
    "wof:placetype":"venue"
},
  "geometry": {"coordinates":[2.286312,48.556942],"type":"Point"}
}