{
  "type": "Feature",
  "properties": {
    "iso:country":"FR",
    "sg:address":"B.P. 1017, 51685 Reims C\u00e9dex 2^^2, Rue Cl\u00e9ment Ader, 51100 Reims",
    "sg:orig_category":"Non-Classified Establishments",
    "sg:phone":"+33 3 26 78 62 60",
    "sg:postcode":"51100",
    "sg:province":"Champagne",
    "wof:name":"C\u00e9r\u00e9com France S.a.",
    "wof:placetype":"venue"
},
  "geometry": {"coordinates":[4.028445,49.26284],"type":"Point"}
}