{
  "type": "Feature",
  "properties": {
    "addr:full":"31, Av. du Parc de l'Horloge - Z.I., 59840 P\u00e9renchies Nord Pas-de-Calais 59840",
    "addr:postcode":"59840;59840",
    "addr:street":"31 Av. Du Parc De L'Horloge",
    "iso:country":"FR",
    "sg:address":"31, Av. du Parc de l'Horloge - Z.I., 59840 P\u00e9renchies",
    "sg:orig_category":"Non-Classified Establishments",
    "sg:phone":"+33 3 20 08 63 18",
    "sg:postcode":"59840",
    "sg:province":"Nord Pas-de-Calais",
    "wof:name":"C.v.i. S.a. - Carlier V\u00e9hicules Industriels",
    "wof:placetype":"venue"
},
  "geometry": {"coordinates":[2.970818,50.665268],"type":"Point"}
}