{
  "type": "Feature",
  "properties": {
    "addr:full":"12 Pl St Am\u00e2tre 89000 Auxerre Auxerre Bourgogne 89000",
    "addr:housenumber":"12",
    "addr:postcode":"89000;89000",
    "addr:street":"Pl St Ama\u0302Tre",
    "iso:country":"FR",
    "sg:address":"12 Pl St Am\u00e2tre 89000 Auxerre",
    "sg:city":"Auxerre",
    "sg:classifiers":[
        {
            "category":"Utilities",
            "subcategory":"Telephone",
            "type":"Services"
        }
    ],
    "sg:phone":"+33 3 86 72 90 00",
    "sg:postcode":"89000",
    "sg:province":"Bourgogne",
    "sg:tags":[
        "telecommunication"
    ],
    "wof:name":"Yonne Copie Sa",
    "wof:placetype":"venue"
},
  "geometry": {"coordinates":[3.576409,47.787716],"type":"Point"}
}