{
  "type": "Feature",
  "properties": {
    "addr:full":"6 Rue Victor Hugo 71000 M\u00e2con Sanc\u00e9 Bourgogne 71000",
    "addr:housenumber":"6",
    "addr:postcode":"71000;71000",
    "addr:street":"Rue Victor Hugo",
    "iso:country":"FR",
    "sg:address":"6 Rue Victor Hugo 71000 M\u00e2con",
    "sg:city":"Sanc\u00e9",
    "sg:classifiers":[
        {
            "category":"Travel",
            "subcategory":"Hotels & Motels",
            "type":"Entertainment"
        }
    ],
    "sg:phone":"+33 3 85 21 10 23",
    "sg:postcode":"71000",
    "sg:province":"Bourgogne",
    "sg:tags":[
        "hotels",
        "business",
        "restaurant"
    ],
    "wof:name":"Grand Hotel Bourgogne",
    "wof:placetype":"venue"
},
  "geometry": {"coordinates":[4.828985,46.30611],"type":"Point"}
}