{
  "type": "Feature",
  "properties": {
    "iso:country":"FR",
    "sg:address":"Parc Nord",
    "sg:city":"Metz Tessy",
    "sg:orig_category":"Unclassifiable Establishments",
    "sg:phone":"+33 4 50 66 91 91",
    "sg:postcode":"74370",
    "sg:province":"Rhone-Alpes",
    "wof:name":"Robotic S.a.",
    "wof:placetype":"venue"
},
  "geometry": {"coordinates":[6.114765,45.939877],"type":"Point"}
}