{
  "type": "Feature",
  "properties": {
    "iso:country":"FR",
    "sg:address":"B.P. 16, 68550 Saint Amarin^^28, Rue du Mar\u00e9chal Joffre, 68550 Saint Amarin",
    "sg:city":"Malmerspach",
    "sg:orig_category":"Non-Classified Establishments",
    "sg:phone":"+33 3 89 82 11 34",
    "sg:postcode":"68550",
    "sg:province":"Alsace",
    "wof:name":"Charpente Scierie Naviliat Sarl",
    "wof:placetype":"venue"
},
  "geometry": {"coordinates":[7.031865,47.873653],"type":"Point"}
}