{
  "type": "Feature",
  "properties": {
    "addr:full":"52 Rue St Martin 62120 Aire Sur La Lys Nord Pas-de-Calais",
    "addr:housenumber":"52",
    "addr:postcode":"62120",
    "addr:street":"Rue St Martin;Aire;La Lys Nord",
    "iso:country":"FR",
    "sg:address":"52 Rue St Martin 62120 Aire Sur La Lys",
    "sg:classifiers":[
        {
            "category":"Professional",
            "type":"Services"
        }
    ],
    "sg:phone":"+33 3 21 38 10 33",
    "sg:province":"Nord Pas-de-Calais",
    "sg:tags":[
        "transport",
        "road"
    ],
    "wof:name":"Transports Hannoir Sarl",
    "wof:placetype":"venue"
},
  "geometry": {"coordinates":[2.393885,50.646488],"type":"Point"}
}