{
  "type": "Feature",
  "properties": {
    "iso:country":"FR",
    "sg:address":"B.P. 10",
    "sg:city":"Fos sur Mer C\u00e9dex",
    "sg:orig_category":"Non-Classified Establishments",
    "sg:phone":"+33 4 42 05 11 00",
    "sg:postcode":"13771",
    "sg:province":"Midi Pyr\u00e9n\u00e9es",
    "wof:name":"Eiffel S.a.",
    "wof:placetype":"venue"
},
  "geometry": {"coordinates":[4.94456,43.437721],"type":"Point"}
}