{
  "type": "Feature",
  "properties": {
    "iso:country":"FR",
    "sg:address":"20, Bd Eug\u00e8ne D\u00e9ruelle - Le Britannia C, 69432 Lyon C\u00e9dex 03",
    "sg:orig_category":"Non-Classified Establishments",
    "sg:phone":"+33 4 72 84 91 91",
    "sg:province":"Haute Normandie",
    "wof:name":"Infopole S.a.",
    "wof:placetype":"venue"
},
  "geometry": {"coordinates":[4.86843,45.751369],"type":"Point"}
}