{
  "type": "Feature",
  "properties": {
    "addr:full":"Immeuble Le Palafour Tignes Rhone-Alpes 73320",
    "addr:postcode":"73320",
    "addr:street":"Rhone-Alpes",
    "iso:country":"FR",
    "sg:address":"Immeuble Le Palafour",
    "sg:city":"Tignes",
    "sg:orig_category":"Non-Classified Establishments",
    "sg:phone":"+33 4 79 06 31 61",
    "sg:postcode":"73320",
    "sg:province":"Rhone-Alpes",
    "wof:name":"Idex Synergie Alpes S.a.",
    "wof:placetype":"venue"
},
  "geometry": {"coordinates":[6.908405,45.470901],"type":"Point"}
}