{
  "type": "Feature",
  "properties": {
    "addr:full":"B.P. 96, 76403 F\u00e9camp C\u00e9dex^^Chemin de Briqueville, 76400 F\u00e9camp Haute Normandie",
    "addr:postcode":"76403;76400",
    "addr:street":"B.P. 96;Haute Normandie",
    "iso:country":"FR",
    "sg:address":"B.P. 96, 76403 F\u00e9camp C\u00e9dex^^Chemin de Briqueville, 76400 F\u00e9camp",
    "sg:orig_category":"Non-Classified Establishments",
    "sg:phone":"+33 2 35 28 05 62",
    "sg:province":"Haute Normandie",
    "wof:name":"S.c.s.j. - Scieries Et Chantiers Saint Jacques S.a.",
    "wof:placetype":"venue"
},
  "geometry": {"coordinates":[0.34733,49.69891],"type":"Point"}
}