{
  "type": "Feature",
  "properties": {
    "iso:country":"FR",
    "sg:address":"route de Thennes 80110 Moreuil",
    "sg:classifiers":[
        {
            "category":"Home & Garden",
            "subcategory":"Home Furnishings",
            "type":"Retail Goods"
        }
    ],
    "sg:phone":"+33 3 22 35 32 32",
    "sg:province":"Picardie",
    "sg:tags":[
        "wallpaper"
    ],
    "wof:name":"Ugepa Sa",
    "wof:placetype":"venue"
},
  "geometry": {"coordinates":[2.47051,49.784069],"type":"Point"}
}