{
  "type": "Feature",
  "properties": {
    "addr:full":"104, Av. Franklin Roosevelt, 69120 Vaulx en Velin Rhone-Alpes",
    "addr:postcode":"69120",
    "addr:street":"104 Av. Franklin Roosevelt",
    "iso:country":"FR",
    "sg:address":"104, Av. Franklin Roosevelt, 69120 Vaulx en Velin",
    "sg:orig_category":"Unclassifiable Establishments",
    "sg:phone":"+33 4 72 05 60 60",
    "sg:province":"Rhone-Alpes",
    "wof:name":"D.u.l. S.a. - Droguerie Union Lyonnaise",
    "wof:placetype":"venue"
},
  "geometry": {"coordinates":[4.936026,45.758232],"type":"Point"}
}