{
  "type": "Feature",
  "properties": {
    "iso:country":"FR",
    "sg:address":"14, Rue Denis Papin, 51100 Reims",
    "sg:orig_category":"Chaudronnerie aluminium Chaudronnerie en acier inoxydable Cintrage D\u00e9coupage au plasma Maintenance e",
    "sg:phone":"+33 3 26 03 97 40",
    "sg:postcode":"51100",
    "sg:province":"Champagne",
    "wof:name":"M.r.i. Industrie S.a.r.l.",
    "wof:placetype":"venue"
},
  "geometry": {"coordinates":[4.072021,49.271412],"type":"Point"}
}