{
  "type": "Feature",
  "properties": {
    "iso:country":"FR",
    "sg:address":"Lavade 11700 Fontcouverte",
    "sg:classifiers":[
        {
            "category":"Wholesale",
            "subcategory":"Machinery & Supplies",
            "type":"Manufacturing & Wholesale Goods"
        }
    ],
    "sg:phone":"+33 4 68 43 92 11",
    "sg:province":"Languedoc-Roussillon",
    "sg:tags":[
        "equipment",
        "precision"
    ],
    "wof:name":"Midi Electronique Alarme Protection (mea Protection)",
    "wof:placetype":"venue"
},
  "geometry": {"coordinates":[2.684459,43.170296],"type":"Point"}
}