{
  "type": "Feature",
  "properties": {
    "iso:country":"FR",
    "sg:address":"6, Av de la D\u00e9couverte, 21000 Dijon",
    "sg:city":"Dijon",
    "sg:orig_category":"Unclassifiable Establishments",
    "sg:phone":"+33 3 80 77 35 35",
    "sg:postcode":"21000",
    "sg:province":"Bourgogne",
    "wof:name":"France 3 S.a.",
    "wof:placetype":"venue"
},
  "geometry": {"coordinates":[5.043917,47.355808],"type":"Point"}
}