{
  "type": "Feature",
  "properties": {
    "addr:full":"1, Rue de Saint Malo, 67100 Strasbourg Strasbourg Alsace 67100",
    "addr:housenumber":"1",
    "addr:postcode":"67100;67100",
    "addr:street":"Rue De Saint Malo",
    "iso:country":"FR",
    "sg:address":"1, Rue de Saint Malo, 67100 Strasbourg",
    "sg:city":"Strasbourg",
    "sg:orig_category":"Unclassifiable Establishments",
    "sg:phone":"+33 3 88 79 22 20",
    "sg:postcode":"67100",
    "sg:province":"Alsace",
    "wof:name":"Glasseurop S.a.",
    "wof:placetype":"venue"
},
  "geometry": {"coordinates":[7.793443,48.543861],"type":"Point"}
}