{
  "type": "Feature",
  "properties": {
    "addr:full":"Zi La Saulaie 49700 Dou\u00e9 La Fontaine Pays de Loire 49700",
    "addr:postcode":"49700;49700",
    "addr:street":"Zi La Saulaie;La Fontaine Pays",
    "iso:country":"FR",
    "sg:address":"Zi La Saulaie 49700 Dou\u00e9 La Fontaine",
    "sg:classifiers":[
        {
            "category":"Food Court",
            "type":"Food & Drink"
        }
    ],
    "sg:phone":"+33 2 41 59 26 26",
    "sg:postcode":"49700",
    "sg:province":"Pays de Loire",
    "sg:tags":[
        "product",
        "related"
    ],
    "wof:name":"Tradival Sa",
    "wof:placetype":"venue"
},
  "geometry": {"coordinates":[-0.275044,47.197166],"type":"Point"}
}