{
  "type": "Feature",
  "properties": {
    "iso:country":"FR",
    "sg:address":"Rte De Bussy 18130 Dun Sur Auron",
    "sg:city":"Bussy",
    "sg:classifiers":[
        {
            "category":"Personal",
            "subcategory":"Shoe Repair & Shine",
            "type":"Services"
        }
    ],
    "sg:phone":"+33 2 48 66 69 69",
    "sg:postcode":"18130",
    "sg:province":"Centre",
    "sg:tags":[
        "leather",
        "textile",
        "clothing",
        "clothes"
    ],
    "wof:name":"Le Chameau Sa",
    "wof:placetype":"venue"
},
  "geometry": {"coordinates":[2.581315,46.88752],"type":"Point"}
}