{
  "type": "Feature",
  "properties": {
    "addr:full":"44 rue des Vinaigriers 75010 Paris Ile de France 75010",
    "addr:housenumber":"44",
    "addr:postcode":"75010;75010",
    "addr:street":"Rue Des Vinaigriers",
    "iso:country":"FR",
    "sg:address":"44 rue des Vinaigriers 75010 Paris",
    "sg:orig_category":"Furskins",
    "sg:phone":"+33 1 42 08 94 04",
    "sg:postcode":"75010",
    "sg:province":"Ile de France",
    "wof:name":"Ste Guiard Diffuson S.a.r.l.",
    "wof:placetype":"venue"
},
  "geometry": {"coordinates":[2.361025,48.873287],"type":"Point"}
}