{
  "type": "Feature",
  "properties": {
    "addr:full":"B.P. 114, 30102 Al\u00e8s C\u00e9dex^^112, Rue Andr\u00e9 Boulle, 30100 Al\u00e8s Languedoc-Roussillon",
    "addr:housenumber":"b.p. 114",
    "addr:postcode":"30102;30100",
    "addr:street":"Rue Andre\u0301 Boulle",
    "iso:country":"FR",
    "sg:address":"B.P. 114, 30102 Al\u00e8s C\u00e9dex^^112, Rue Andr\u00e9 Boulle, 30100 Al\u00e8s",
    "sg:orig_category":"Non-Classified Establishments",
    "sg:phone":"+33 4 66 86 29 32",
    "sg:province":"Languedoc-Roussillon",
    "wof:name":"La Cheville Al\u00e9sienne Euroviandes S.a.",
    "wof:placetype":"venue"
},
  "geometry": {"coordinates":[4.082515,44.121254],"type":"Point"}
}