{
  "type": "Feature",
  "properties": {
    "iso:country":"FR",
    "sg:address":"39, Rte de Forstheim, 67500 Haguenau",
    "sg:city":"Haguenau",
    "sg:orig_category":"Unclassifiable Establishments",
    "sg:phone":"+33 3 88 73 20 15",
    "sg:postcode":"67500",
    "sg:province":"Alsace",
    "wof:name":"Beck S.a.r.l.",
    "wof:placetype":"venue"
},
  "geometry": {"coordinates":[7.787353,48.824589],"type":"Point"}
}