{
  "type": "Feature",
  "properties": {
    "addr:full":"7, Alfred Parent, 47600 N\u00e9rac N\u00e9rac Aquitaine 47600",
    "addr:housenumber":"7",
    "addr:postcode":"47600;47600",
    "addr:street":"Alfred Parent",
    "iso:country":"FR",
    "sg:address":"7, Alfred Parent, 47600 N\u00e9rac",
    "sg:city":"N\u00e9rac",
    "sg:orig_category":"Unclassifiable Establishments",
    "sg:phone":"+33 5 53 65 48 15",
    "sg:postcode":"47600",
    "sg:province":"Aquitaine",
    "wof:name":"Babcock Wanson",
    "wof:placetype":"venue"
},
  "geometry": {"coordinates":[0.33782,44.130657],"type":"Point"}
}