{
  "type": "Feature",
  "properties": {
    "iso:country":"FR",
    "sg:address":"Rue des Gravi\u00e8res - Zone Industrielle Nord",
    "sg:city":"Brumath",
    "sg:orig_category":"Non-Classified Establishments",
    "sg:phone":"+33 3 90 29 12 20",
    "sg:postcode":"67170",
    "sg:province":"Alsace",
    "wof:name":"Sophipain S.a.r.l.",
    "wof:placetype":"venue"
},
  "geometry": {"coordinates":[7.710455,48.730267],"type":"Point"}
}