{
  "type": "Feature",
  "properties": {
    "addr:full":"142-144 rte Nationale; Noeux les Mines; 62290 Nord Pas-de-Calais 62290",
    "addr:housenumber":"142-144",
    "addr:postcode":"62290;62290",
    "addr:street":"Rte Nationale Noeux Les Mines",
    "iso:country":"FR",
    "sg:address":"142-144 rte Nationale; Noeux les Mines; 62290",
    "sg:classifiers":[
        {
            "category":"Banks & Credit Unions",
            "subcategory":"Bank",
            "type":"Services"
        }
    ],
    "sg:phone":"+33 21263753",
    "sg:postcode":"62290",
    "sg:province":"Nord Pas-de-Calais",
    "wof:name":"Soci\u00e9t\u00e9 G\u00e9n\u00e9rale",
    "wof:placetype":"venue"
},
  "geometry": {"coordinates":[2.661913,50.480907],"type":"Point"}
}