{
  "type": "Feature",
  "properties": {
    "addr:full":"863, Chemin de la Malauti\u00e8re, 84701 Sorgues C\u00e9dex Franche Comt\u00e9",
    "addr:housenumber":"863",
    "addr:postcode":"84701",
    "addr:street":"Chemin De La Malautie\u0300Re;Franche Comte\u0301",
    "iso:country":"FR",
    "sg:address":"863, Chemin de la Malauti\u00e8re, 84701 Sorgues C\u00e9dex",
    "sg:orig_category":"Non-Classified Establishments",
    "sg:phone":"+33 4 90 39 21 27",
    "sg:province":"Franche Comt\u00e9",
    "wof:name":"Bas E.u.r.l.",
    "wof:placetype":"venue"
},
  "geometry": {"coordinates":[4.867294,44.031204],"type":"Point"}
}