{
  "type": "Feature",
  "properties": {
    "addr:full":"1 rue Des Corroyes 78730 ST ARNOULT EN YVELINES Ile de France",
    "addr:housenumber":"1",
    "addr:postcode":"78730",
    "addr:street":"Rue Des Corroyes",
    "iso:country":"FR",
    "sg:address":"1 rue Des Corroyes 78730 ST ARNOULT EN YVELINES",
    "sg:classifiers":[
        {
            "category":"Manufacturing",
            "subcategory":"Metals",
            "type":"Manufacturing & Wholesale Goods"
        }
    ],
    "sg:phone":"+33 1 30 41 27 63",
    "sg:province":"Ile de France",
    "sg:tags":[
        "sheet",
        "thin",
        "working"
    ],
    "wof:name":"Lhotellier S.a.",
    "wof:placetype":"venue"
},
  "geometry": {"coordinates":[1.9347,48.562698],"type":"Point"}
}