{
  "type": "Feature",
  "properties": {
    "addr:full":"B.P. 8, 26320 Saint Marcel les Valence^^ZA Mathias, 26320 Saint Marcel les Valence Rhone-Alpes",
    "addr:housenumber":"8",
    "addr:postcode":"26320;26320",
    "addr:street":"B.P.;Marcel Les;Mathias;Marcel Les",
    "iso:country":"FR",
    "sg:address":"B.P. 8, 26320 Saint Marcel les Valence^^ZA Mathias, 26320 Saint Marcel les Valence",
    "sg:orig_category":"Non-Classified Establishments",
    "sg:phone":"+33 4 75 85 71 11",
    "sg:province":"Rhone-Alpes",
    "wof:name":"Papeterie Estour Emballage S.a.",
    "wof:placetype":"venue"
},
  "geometry": {"coordinates":[4.969534,44.98045],"type":"Point"}
}