{
  "type": "Feature",
  "properties": {
    "addr:full":"3, Bd Sampi\u00e9ro, 20000 Ajaccio Corse",
    "addr:housenumber":"3",
    "addr:postcode":"20000",
    "addr:street":"Bd Sampie\u0301Ro",
    "iso:country":"FR",
    "sg:address":"3, Bd Sampi\u00e9ro, 20000 Ajaccio",
    "sg:orig_category":"Unclassifiable Establishments",
    "sg:phone":"+33 4 95 21 60 04",
    "sg:province":"Corse",
    "wof:name":"P\u00e9triconi S.a.r.l.",
    "wof:placetype":"venue"
},
  "geometry": {"coordinates":[8.738816,41.924538],"type":"Point"}
}