{
  "type": "Feature",
  "properties": {
    "addr:full":"4, H\u00e9rault de Seichelles, 75017 Paris Ile de France",
    "addr:housenumber":"4",
    "addr:postcode":"75017",
    "addr:street":"He\u0301Rault De Seichelles",
    "iso:country":"FR",
    "sg:address":"4, H\u00e9rault de Seichelles, 75017 Paris",
    "sg:orig_category":"Unclassifiable Establishments",
    "sg:phone":"+33 1 58 61 50 00",
    "sg:province":"Ile de France",
    "wof:name":"C.g.p.p. S.a. - Compagnie Des Gaz De P\u00e9trole Primagaz S.a.",
    "wof:placetype":"venue"
},
  "geometry": {"coordinates":[2.320443,48.900719],"type":"Point"}
}