{
  "type": "Feature",
  "properties": {
    "addr:full":"15 pl de la R\u00e9publique; Caen; 14000 Caen Basse Normandie 14000",
    "addr:housenumber":"15",
    "addr:postcode":"14000;14000",
    "addr:street":"Pl De La Re\u0301Publique",
    "iso:country":"FR",
    "sg:address":"15 pl de la R\u00e9publique; Caen; 14000",
    "sg:city":"Caen",
    "sg:classifiers":[
        {
            "category":"Banks & Credit Unions",
            "subcategory":"Bank",
            "type":"Services"
        }
    ],
    "sg:phone":"+33 31838183",
    "sg:postcode":"14000",
    "sg:province":"Basse Normandie",
    "wof:name":"Banque Nationale De Paris",
    "wof:placetype":"venue"
},
  "geometry": {"coordinates":[-0.36303,49.181019],"type":"Point"}
}