{
  "type": "Feature",
  "properties": {
    "iso:country":"FR",
    "sg:address":"B.P. 3",
    "sg:city":"Languidic",
    "sg:orig_category":"Non-Classified Establishments",
    "sg:phone":"+33 2 97 85 90 43",
    "sg:postcode":"56440",
    "sg:province":"Bretagne",
    "wof:name":"Unicopa Volailles S.a.",
    "wof:placetype":"venue"
},
  "geometry": {"coordinates":[-3.162875,47.78611],"type":"Point"}
}