{
  "type": "Feature",
  "properties": {
    "addr:full":"1, Rue des Entrepreneurs, 93400 Saint Ouen Ile de France",
    "addr:housenumber":"1",
    "addr:postcode":"93400;ile",
    "addr:street":"Rue Des Entrepreneurs",
    "iso:country":"FR",
    "sg:address":"1, Rue des Entrepreneurs, 93400 Saint Ouen",
    "sg:orig_category":"Non-Classified Establishments",
    "sg:phone":"+33 1 40 11 44 44",
    "sg:province":"Ile de France",
    "wof:name":"Job Pratique Magazine S.a.r.l.",
    "wof:placetype":"venue"
},
  "geometry": {"coordinates":[2.340995,48.907871],"type":"Point"}
}