{
  "type": "Feature",
  "properties": {
    "iso:country":"FR",
    "sg:address":"14, Rue du Moulin - ZI, 31280 Dr\u00e9mil Lafage",
    "sg:orig_category":"Non-Classified Establishments",
    "sg:phone":"+33 5 61 83 93 41",
    "sg:province":"Midi Pyr\u00e9n\u00e9es",
    "wof:name":"T.b.a. S.a.s. - Technique Des B\u00e9tons All\u00e9g\u00e9s",
    "wof:placetype":"venue"
},
  "geometry": {"coordinates":[1.603065,43.597385],"type":"Point"}
}