{
  "type": "Feature",
  "properties": {
    "addr:full":"29 Rue de Monceau, Paris, Dept 75 Ile de France",
    "addr:housenumber":"29;75",
    "addr:street":"Rue De Monceau;Ile De France",
    "iso:country":"FR",
    "sg:address":"29 Rue de Monceau, Paris, Dept 75",
    "sg:classifiers":[
        {
            "category":"Banks & Credit Unions",
            "subcategory":"Bank",
            "type":"Services"
        }
    ],
    "sg:province":"Ile de France",
    "wof:name":"Sicomax Sa",
    "wof:placetype":"venue"
},
  "geometry": {"coordinates":[2.308694,48.876926],"type":"Point"}
}