{
  "type": "Feature",
  "properties": {
    "addr:full":"9 Rue De Saurupt 54000 Nancy Lorraine",
    "addr:housenumber":"9",
    "addr:postcode":"54000",
    "addr:street":"Rue De Saurupt",
    "iso:country":"FR",
    "sg:address":"9 Rue De Saurupt 54000 Nancy",
    "sg:classifiers":[
        {
            "category":"Manufacturing",
            "subcategory":"Printing",
            "type":"Manufacturing & Wholesale Goods"
        }
    ],
    "sg:phone":"+33 3 83 55 38 41",
    "sg:province":"Lorraine",
    "sg:tags":[
        "publishing"
    ],
    "wof:name":"Marc Et Fils (sa)",
    "wof:placetype":"venue"
},
  "geometry": {"coordinates":[6.185062,48.681431],"type":"Point"}
}