{
  "type": "Feature",
  "properties": {
    "iso:country":"FR",
    "sg:address":"6, Rue Eug\u00e8ne Freyssinet, 94045 Cr\u00e9teil C\u00e9dex",
    "sg:orig_category":"Non-Classified Establishments",
    "sg:phone":"+33 1 43 39 63 63",
    "sg:province":"Pays de Loire",
    "wof:name":"Dauphin S.a.",
    "wof:placetype":"venue"
},
  "geometry": {"coordinates":[2.47249,48.762962],"type":"Point"}
}