{
  "type": "Feature",
  "properties": {
    "addr:full":"39 R De Nantes 30162 Foug\u00e8res Cedex Lorraine",
    "addr:housenumber":"39",
    "addr:postcode":"30162",
    "addr:street":"R De Nantes",
    "iso:country":"FR",
    "sg:address":"39 R De Nantes 30162 Foug\u00e8res Cedex",
    "sg:classifiers":[
        {
            "category":"Professional",
            "subcategory":"Printing & Photocopies",
            "type":"Services"
        }
    ],
    "sg:phone":"+33 2 99 99 12 15",
    "sg:province":"Lorraine",
    "sg:tags":[
        "publishing"
    ],
    "wof:name":"Chronique Editions",
    "wof:placetype":"venue"
},
  "geometry": {"coordinates":[-1.202858,48.34853],"type":"Point"}
}