{
  "type": "Feature",
  "properties": {
    "addr:full":"28, Bd Gay Lussac, 13014 Marseille Poitou-Charentes",
    "addr:housenumber":"28",
    "addr:postcode":"13014",
    "addr:street":"Bd Gay Lussac",
    "iso:country":"FR",
    "sg:address":"28, Bd Gay Lussac, 13014 Marseille",
    "sg:orig_category":"Non-Classified Establishments",
    "sg:phone":"+33 4 91 63 01 03",
    "sg:province":"Poitou-Charentes",
    "wof:name":"Dormex S.a.",
    "wof:placetype":"venue"
},
  "geometry": {"coordinates":[5.374873,43.334869],"type":"Point"}
}