{
  "type": "Feature",
  "properties": {
    "addr:full":"1284, Rue de Gautray - ZI la Saussaye - PA. Orl\u00e9ans Sologne, 45075 Orl\u00e9ans C\u00e9dex 2 Champagne",
    "addr:housenumber":"1284",
    "addr:postcode":"saussaye pa.;sologne 45075",
    "addr:street":"Rue De Gautray Zi",
    "iso:country":"FR",
    "sg:address":"1284, Rue de Gautray - ZI la Saussaye - PA. Orl\u00e9ans Sologne, 45075 Orl\u00e9ans C\u00e9dex 2",
    "sg:orig_category":"Non-Classified Establishments",
    "sg:phone":"+33 2 38 69 72 30",
    "sg:province":"Champagne",
    "wof:name":"Fabrica S.a.",
    "wof:placetype":"venue"
},
  "geometry": {"coordinates":[1.90398,47.90139],"type":"Point"}
}