{
  "type": "Feature",
  "properties": {
    "addr:full":"26 Rue Jaques Louvel Tessier 75010 Paris Ile de France 75010",
    "addr:housenumber":"26",
    "addr:postcode":"75010;75010",
    "addr:street":"Rue Jaques Louvel Tessier",
    "iso:country":"FR",
    "sg:address":"26 Rue Jaques Louvel Tessier 75010 Paris",
    "sg:classifiers":[
        {
            "category":"Shopping",
            "subcategory":"Clothing, Apparel, & Fashions",
            "type":"Retail Goods"
        }
    ],
    "sg:phone":"+33 1 42 45 33 72",
    "sg:postcode":"75010",
    "sg:province":"Ile de France",
    "sg:tags":[
        "textile",
        "clothing",
        "clothes"
    ],
    "wof:name":"M P S P Creation Diffusion",
    "wof:placetype":"venue"
},
  "geometry": {"coordinates":[2.370595,48.871239],"type":"Point"}
}