{
  "type": "Feature",
  "properties": {
    "iso:country":"FR",
    "sg:address":"Chemin de l'Industrie",
    "sg:city":"Carbonne",
    "sg:orig_category":"Non-Classified Establishments",
    "sg:phone":"+33 5 61 87 00 33",
    "sg:postcode":"31390",
    "sg:province":"Midi Pyr\u00e9n\u00e9es",
    "wof:name":"Soci\u00e9t\u00e9 Carbonne Mat\u00e9riaux S.a.r.l.",
    "wof:placetype":"venue"
},
  "geometry": {"coordinates":[1.216437,43.301723],"type":"Point"}
}