{
  "type": "Feature",
  "properties": {
    "addr:full":"5, Rue Blanqu\u00e9, 01100 Oyonnax Rhone-Alpes",
    "addr:housenumber":"5",
    "addr:postcode":"01100",
    "addr:street":"Rue Blanque\u0301",
    "iso:country":"FR",
    "sg:address":"5, Rue Blanqu\u00e9, 01100 Oyonnax",
    "sg:orig_category":"Non-Classified Establishments",
    "sg:phone":"+33 4 74 73 02 03",
    "sg:province":"Rhone-Alpes",
    "wof:name":"Servy",
    "wof:placetype":"venue"
},
  "geometry": {"coordinates":[5.658318,46.264549],"type":"Point"}
}