{
  "type": "Feature",
  "properties": {
    "iso:country":"FR",
    "sg:address":"6 rue des Serruriers 57070 Metz",
    "sg:classifiers":[
        {
            "category":"Manufacturing",
            "subcategory":"Rubber & Plastics",
            "type":"Manufacturing & Wholesale Goods"
        }
    ],
    "sg:phone":"+33 3 87 76 32 32",
    "sg:province":"Lorraine",
    "sg:tags":[
        "material"
    ],
    "wof:name":"Fimic Dispelor Sa",
    "wof:placetype":"venue"
},
  "geometry": {"coordinates":[6.240681,49.117306],"type":"Point"}
}