{
  "type": "Feature",
  "properties": {
    "iso:country":"FR",
    "sg:address":"10, Av. Cl\u00e9menceau, 25000 Besan\u00e7on",
    "sg:orig_category":"Non-Classified Establishments",
    "sg:phone":"+33 3 81 82 14 71",
    "sg:province":"Franche Comt\u00e9",
    "wof:name":"Web Confiance",
    "wof:placetype":"venue"
},
  "geometry": {"coordinates":[6.013929,47.241192],"type":"Point"}
}