{
  "type": "Feature",
  "properties": {
    "iso:country":"FR",
    "sg:address":"28/32, Av. Victor Hugo, 75783 Paris C\u00e9dex 16",
    "sg:orig_category":"Non-Classified Establishments",
    "sg:phone":"+33 1 40 67 80 00",
    "sg:province":"Ile de France",
    "wof:name":"Beaut\u00e9 Prestige International S.a.",
    "wof:placetype":"venue"
},
  "geometry": {"coordinates":[2.290444,48.871971],"type":"Point"}
}