{
  "type": "Feature",
  "properties": {
    "addr:full":"B.P. 97, 67403 Illkirch C\u00e9dex^^18, Rue Joseph Marie Jacquard - Zone Industrielle Sud, 67400 Illkirch Geispolsheim Alsace 67400",
    "addr:postcode":"67403;67400;67400",
    "addr:street":"B.P. 97;Rue Joseph Marie Jacquard Zone Industrielle Sud",
    "iso:country":"FR",
    "sg:address":"B.P. 97, 67403 Illkirch C\u00e9dex^^18, Rue Joseph Marie Jacquard - Zone Industrielle Sud, 67400 Illkirch",
    "sg:city":"Geispolsheim",
    "sg:orig_category":"Non-Classified Establishments",
    "sg:phone":"+33 3 88 66 07 00",
    "sg:postcode":"67400",
    "sg:province":"Alsace",
    "wof:name":"Lehmann Et Compagnie S.a.",
    "wof:placetype":"venue"
},
  "geometry": {"coordinates":[7.73041,48.521969],"type":"Point"}
}