{
  "type": "Feature",
  "properties": {
    "addr:full":"22 Quai Carnot 92210 St Cloud Ile de France 92210",
    "addr:housenumber":"22",
    "addr:postcode":"92210;92210",
    "addr:street":"Quai Carnot",
    "iso:country":"FR",
    "sg:address":"22 Quai Carnot 92210 St Cloud",
    "sg:classifiers":[
        {
            "category":"Shopping",
            "subcategory":"Stationery & Office Supplies",
            "type":"Retail Goods"
        }
    ],
    "sg:phone":"+33 1 47 11 14 22",
    "sg:postcode":"92210",
    "sg:province":"Ile de France",
    "sg:tags":[
        "information",
        "technology",
        "telecommunication",
        "equipment"
    ],
    "wof:name":"Oce Facility Services",
    "wof:placetype":"venue"
},
  "geometry": {"coordinates":[2.223329,48.845402],"type":"Point"}
}