{
  "type": "Feature",
  "properties": {
    "addr:full":"B.P. 12, 79210 Mauz\u00e9 sur le Mignon C\u00e9dex^^179, Grande Rue, 79210 Mauz\u00e9 sur le Mignon Poitou-Charentes",
    "addr:postcode":"79210;79210",
    "addr:street":"B.P. 12;Ce\u0301Dex^^179 Grande Rue",
    "iso:country":"FR",
    "sg:address":"B.P. 12, 79210 Mauz\u00e9 sur le Mignon C\u00e9dex^^179, Grande Rue, 79210 Mauz\u00e9 sur le Mignon",
    "sg:orig_category":"Non-Classified Establishments",
    "sg:phone":"+33 5 49 26 30 58",
    "sg:province":"Poitou-Charentes",
    "wof:name":"Pierre Gu\u00e9rin S.a.",
    "wof:placetype":"venue"
},
  "geometry": {"coordinates":[-0.606155,46.143532],"type":"Point"}
}