{
  "type": "Feature",
  "properties": {
    "iso:country":"FR",
    "sg:address":"Technoparc Futura",
    "sg:city":"B\u00e9thune",
    "sg:orig_category":"Unclassifiable Establishments",
    "sg:phone":"+33 3 21 68 65 00",
    "sg:postcode":"62400",
    "sg:province":"Nord Pas-de-Calais",
    "wof:name":"Distribution Technique Industrie S.a.",
    "wof:placetype":"venue"
},
  "geometry": {"coordinates":[2.63787,50.530472],"type":"Point"}
}