{
  "type": "Feature",
  "properties": {
    "iso:country":"FR",
    "sg:address":"B.P. 241, 06292 Nice C\u00e9dex^^457, Promenade des Anglais, 06200 Nice",
    "sg:orig_category":"Non-Classified Establishments",
    "sg:phone":"+33 4 93 21 52 00",
    "sg:province":"Midi Pyr\u00e9n\u00e9es",
    "wof:name":"B.p.c.a. - Banque Populaire C\u00f4te D'azur",
    "wof:placetype":"venue"
},
  "geometry": {"coordinates":[7.215093,43.745003],"type":"Point"}
}