{
  "type": "Feature",
  "properties": {
    "addr:full":"58, Rue Beaubourg - 13, 75003 Paris Ile de France",
    "addr:housenumber":"58;13",
    "addr:postcode":"75003",
    "addr:street":"Rue Beaubourg",
    "iso:country":"FR",
    "sg:address":"58, Rue Beaubourg - 13, 75003 Paris",
    "sg:orig_category":"Non-Classified Establishments",
    "sg:phone":"+33 1 42 72 75 74",
    "sg:province":"Ile de France",
    "wof:name":"Saphir France S.a.",
    "wof:placetype":"venue"
},
  "geometry": {"coordinates":[2.36455,48.864704],"type":"Point"}
}