{
  "type": "Feature",
  "properties": {
    "iso:country":"FR",
    "sg:address":"140, Av. Paul Doumer, 92508 Rueil Malmaison C\u00e9dex",
    "sg:orig_category":"Non-Classified Establishments",
    "sg:phone":"+33 1 41 39 99 99",
    "sg:province":"\u00cele-de-France",
    "wof:name":"S\u00f6dra France S.a.",
    "wof:placetype":"venue"
},
  "geometry": {"coordinates":[2.181875,48.880512],"type":"Point"}
}