{
  "type": "Feature",
  "properties": {
    "iso:country":"FR",
    "sg:address":"Rue Andr\u00e9 Duronchez",
    "sg:city":"Amiens",
    "sg:orig_category":"Unclassifiable Establishments",
    "sg:phone":"+33 3 22 54 27 54",
    "sg:postcode":"80000",
    "sg:province":"Picardie",
    "wof:name":"A.t.x. S.a.",
    "wof:placetype":"venue"
},
  "geometry": {"coordinates":[2.291708,49.878712],"type":"Point"}
}