{
  "type": "Feature",
  "properties": {
    "addr:full":"Les Chenes Verts 26600 PONT DE L ISERE Rhone-Alpes 26600",
    "addr:postcode":"26600;26600",
    "addr:street":"L;Rhone-Alpes",
    "iso:country":"FR",
    "sg:address":"Les Chenes Verts 26600 PONT DE L ISERE",
    "sg:classifiers":[
        {
            "category":"Wholesale",
            "subcategory":"Wine & Distilled Alcoholic Beverages",
            "type":"Manufacturing & Wholesale Goods"
        }
    ],
    "sg:phone":"+33 4 75 84 67 52",
    "sg:postcode":"26600",
    "sg:province":"Rhone-Alpes",
    "sg:tags":[
        "french"
    ],
    "wof:name":"Alain Graillot Sarl",
    "wof:placetype":"venue"
},
  "geometry": {"coordinates":[4.869976,45.008339],"type":"Point"}
}