{
  "type": "Feature",
  "properties": {
    "iso:country":"FR",
    "sg:address":"Domaien De La Vallongue 13810 Eygalieres",
    "sg:classifiers":[
        {
            "category":"Food Court",
            "type":"Food & Drink"
        }
    ],
    "sg:phone":"+33 4 90 95 91 70",
    "sg:province":"Midi Pyr\u00e9n\u00e9es",
    "sg:tags":[
        "product",
        "related"
    ],
    "wof:name":"Mme Cohn Cavalier Paul Domaine De La Vallongue",
    "wof:placetype":"venue"
},
  "geometry": {"coordinates":[4.950015,43.760689],"type":"Point"}
}