{
  "type": "Feature",
  "properties": {
    "iso:country":"FR",
    "sg:address":"2 Rue Labauche 08200 Sedan",
    "sg:classifiers":[
        {
            "category":"Manufacturing",
            "subcategory":"Metals",
            "type":"Manufacturing & Wholesale Goods"
        }
    ],
    "sg:phone":"+33 3 24 29 40 49",
    "sg:postcode":"08200",
    "sg:province":"Champagne",
    "sg:tags":[
        "metallurgy",
        "metalworking",
        "processing"
    ],
    "wof:name":"Aldem",
    "wof:placetype":"venue"
},
  "geometry": {"coordinates":[4.932027,49.702652],"type":"Point"}
}