{
  "type": "Feature",
  "properties": {
    "addr:full":"12, Rue Barbedette, 17440 Aytr\u00e9 Poitou-Charentes 17440",
    "addr:housenumber":"12",
    "addr:postcode":"17440;17440",
    "addr:street":"Rue Barbedette",
    "iso:country":"FR",
    "sg:address":"12, Rue Barbedette, 17440 Aytr\u00e9",
    "sg:orig_category":"Non-Classified Establishments",
    "sg:phone":"+33 5 46 44 27 21",
    "sg:postcode":"17440",
    "sg:province":"Poitou-Charentes",
    "wof:name":"Abakx M.p.r. S.a.",
    "wof:placetype":"venue"
},
  "geometry": {"coordinates":[-1.116992,46.132095],"type":"Point"}
}