{
  "type": "Feature",
  "properties": {
    "addr:full":"3, Chemin des Iles, 78610 Le Perray en Yvelines Ile de France 78610",
    "addr:housenumber":"3",
    "addr:postcode":"78610;78610",
    "addr:street":"Chemin Des Iles",
    "iso:country":"FR",
    "sg:address":"3, Chemin des Iles, 78610 Le Perray en Yvelines",
    "sg:orig_category":"Non-Classified Establishments",
    "sg:phone":"+33 1 34 84 27 23",
    "sg:postcode":"78610",
    "sg:province":"Ile de France",
    "wof:name":"Doka France S.a.",
    "wof:placetype":"venue"
},
  "geometry": {"coordinates":[1.857858,48.701599],"type":"Point"}
}