{
  "type": "Feature",
  "properties": {
    "addr:full":"Cours Camille Pelletan; Grans; 13450 Midi Pyr\u00e9n\u00e9es",
    "addr:postcode":"13450",
    "addr:street":"Cours Camille Pelletan",
    "iso:country":"FR",
    "sg:address":"Cours Camille Pelletan; Grans; 13450",
    "sg:classifiers":[
        {
            "category":"Banks & Credit Unions",
            "subcategory":"Bank",
            "type":"Services"
        }
    ],
    "sg:phone":"+33 4 90 55 97 32",
    "sg:province":"Midi Pyr\u00e9n\u00e9es",
    "wof:name":"Cr\u00e9dit Agricole",
    "wof:placetype":"venue"
},
  "geometry": {"coordinates":[5.063394,43.606434],"type":"Point"}
}