{
  "type": "Feature",
  "properties": {
    "iso:country":"FR",
    "sg:address":"La Grande Vall\u00e9e 53150 Montsers",
    "sg:classifiers":[
        {
            "category":"Professional",
            "type":"Services"
        }
    ],
    "sg:phone":"+33 2 43 02 22 90",
    "sg:province":"Pays de Loire",
    "sg:tags":[
        "transport",
        "road"
    ],
    "wof:name":"Morin Transports Michel Sarl",
    "wof:placetype":"venue"
},
  "geometry": {"coordinates":[-0.519726,48.098911],"type":"Point"}
}