{
  "type": "Feature",
  "properties": {
    "iso:country":"FR",
    "sg:address":"All Des G\u00e9om\u00e8tres 06700 St Laurent Du Var",
    "sg:classifiers":[
        {
            "category":"Professional",
            "subcategory":"Printing & Photocopies",
            "type":"Services"
        }
    ],
    "sg:phone":"+33 4 92 12 57 57",
    "sg:province":"Champagne",
    "sg:tags":[
        "publishing"
    ],
    "wof:name":"Panini France Sa",
    "wof:placetype":"venue"
},
  "geometry": {"coordinates":[7.181616,43.701958],"type":"Point"}
}