{
  "type": "Feature",
  "properties": {
    "addr:full":"Z I La Canurie 50250 LA HAYE DU PUITS Neuville-en-Beaumont Basse Normandie 50250",
    "addr:postcode":"50250;50250",
    "addr:street":"Z I La Canurie;Basse",
    "iso:country":"FR",
    "sg:address":"Z I La Canurie 50250 LA HAYE DU PUITS",
    "sg:city":"Neuville-en-Beaumont",
    "sg:classifiers":[
        {
            "category":"Manufacturing",
            "subcategory":"Printing",
            "type":"Manufacturing & Wholesale Goods"
        }
    ],
    "sg:phone":"+33 2 33 07 33 07",
    "sg:postcode":"50250",
    "sg:province":"Basse Normandie",
    "sg:tags":[
        "house",
        "book"
    ],
    "wof:name":"Cauchard Impressions S.a.",
    "wof:placetype":"venue"
},
  "geometry": {"coordinates":[-1.519254,49.272572],"type":"Point"}
}