{
  "type": "Feature",
  "properties": {
    "iso:country":"FR",
    "sg:address":"70, Bd du Mar\u00e9chal Paul - Immeuble le Modulor, 44800 Saint Herblain",
    "sg:orig_category":"Non-Classified Establishments",
    "sg:phone":"+33 2 51 78 66 52",
    "sg:province":"Pays de Loire",
    "wof:name":"Silog S.a.",
    "wof:placetype":"venue"
},
  "geometry": {"coordinates":[-1.628529,47.237419],"type":"Point"}
}