{
  "type": "Feature",
  "properties": {
    "addr:full":"70, Bd du Mar\u00e9chal Paul - Immeuble le Modulor, 44800 Saint Herblain Pays de Loire",
    "addr:housenumber":"70",
    "addr:postcode":"44800",
    "addr:street":"Bd Du Mare\u0301Chal Paul Immeuble Le Modulor;Herblain",
    "iso:country":"FR",
    "sg:address":"70, Bd du Mar\u00e9chal Paul - Immeuble le Modulor, 44800 Saint Herblain",
    "sg:orig_category":"Non-Classified Establishments",
    "sg:phone":"+33 2 51 78 66 52",
    "sg:province":"Pays de Loire",
    "wof:name":"Silog S.a.",
    "wof:placetype":"venue"
},
  "geometry": {"coordinates":[-1.628529,47.237419],"type":"Point"}
}