{
  "type": "Feature",
  "properties": {
    "iso:country":"FR",
    "sg:address":"RN 538 - Mas des Alpilles",
    "sg:city":"Lamanon",
    "sg:orig_category":"Non-Classified Establishments",
    "sg:phone":"+33 4 90 59 54 44",
    "sg:postcode":"13113",
    "sg:province":"Provence-Alpes-C\u00f4te d'Azur",
    "wof:name":"P\u00e9pini\u00e8res Sintes S.a.r.l.",
    "wof:placetype":"venue"
},
  "geometry": {"coordinates":[5.08669,43.701965],"type":"Point"}
}