{
  "type": "Feature",
  "properties": {
    "addr:full":"30 Rue De Paris 93130 Noisy Le Sec Ile de France 93130",
    "addr:housenumber":"30",
    "addr:postcode":"93130;93130",
    "addr:street":"Rue De Paris",
    "iso:country":"FR",
    "sg:address":"30 Rue De Paris 93130 Noisy Le Sec",
    "sg:classifiers":[
        {
            "category":"Government",
            "subcategory":"Department Of Motor Vehicles",
            "type":"Public Place"
        }
    ],
    "sg:phone":"+33 1 48 40 40 64",
    "sg:postcode":"93130",
    "sg:province":"Ile de France",
    "sg:tags":[
        "equipment",
        "industrial",
        "transport",
        "motor-cars"
    ],
    "wof:name":"Pellier Rn3 Sa",
    "wof:placetype":"venue"
},
  "geometry": {"coordinates":[2.444737,48.898834],"type":"Point"}
}