{
  "type": "Feature",
  "properties": {
    "addr:full":"4 Four; Barbentane Rhone-Alpes",
    "addr:housenumber":"4",
    "addr:street":"Four Barbentane Rhone-Alpes",
    "iso:country":"FR",
    "sg:address":"4",
    "sg:city":"Four; Barbentane",
    "sg:classifiers":[
        {
            "category":"Banks & Credit Unions",
            "subcategory":"Bank",
            "type":"Services"
        }
    ],
    "sg:phone":"+33 3390955129",
    "sg:province":"Rhone-Alpes",
    "wof:name":"Cr\u00e9dit Agricole",
    "wof:placetype":"venue"
},
  "geometry": {"coordinates":[4.747351,43.899155],"type":"Point"}
}