{
  "type": "Feature",
  "properties": {
    "addr:full":"Le Vieux Village 34980 Murles Languedoc-Roussillon",
    "addr:postcode":"34980",
    "addr:street":"Murles",
    "iso:country":"FR",
    "sg:address":"Le Vieux Village 34980 Murles",
    "sg:orig_category":"Unclassifiable Establishments",
    "sg:phone":"+33 4 67 84 40 87",
    "sg:province":"Languedoc-Roussillon",
    "wof:name":"Paradise Am\u00e9nagements S.a.r.l.",
    "wof:placetype":"venue"
},
  "geometry": {"coordinates":[3.806955,43.69313],"type":"Point"}
}