{
  "type": "Feature",
  "properties": {
    "addr:full":"170, Rte Zand Put Houck, 59670 Winnezeele Nord Pas-de-Calais",
    "addr:housenumber":"170",
    "addr:postcode":"59670",
    "addr:street":"Rte Zand Put Houck",
    "iso:country":"FR",
    "sg:address":"170, Rte Zand Put Houck, 59670 Winnezeele",
    "sg:orig_category":"Unclassifiable Establishments",
    "sg:phone":"+33 3 28 42 97 42",
    "sg:province":"Nord Pas-de-Calais",
    "wof:name":"Sotraveer S.a.",
    "wof:placetype":"venue"
},
  "geometry": {"coordinates":[2.572463,50.839809],"type":"Point"}
}