{
  "type": "Feature",
  "properties": {
    "iso:country":"FR",
    "sg:address":"170, Rte Zand Put Houck, 59670 Winnezeele",
    "sg:orig_category":"Unclassifiable Establishments",
    "sg:phone":"+33 3 28 42 97 42",
    "sg:province":"Nord Pas-de-Calais",
    "wof:name":"Sotraveer S.a.",
    "wof:placetype":"venue"
},
  "geometry": {"coordinates":[2.572463,50.839809],"type":"Point"}
}