{
  "type": "Feature",
  "properties": {
    "iso:country":"FR",
    "sg:address":"B.P. 18, 95151 Taverny C\u00e9dex^^38/40, Av. des Ch\u00e2taigniers - ZAE Les Ch\u00e2taigniers, 95150 Taverny",
    "sg:orig_category":"Non-Classified Establishments",
    "sg:phone":"+33 1 39 32 06 00",
    "sg:postcode":"95150",
    "sg:province":"Ile de France",
    "wof:name":"A.g. Laser S.a.r.l.",
    "wof:placetype":"venue"
},
  "geometry": {"coordinates":[2.22329,49.026966],"type":"Point"}
}