{
  "type": "Feature",
  "properties": {
    "addr:full":"20 Rue Delaroche 62100 Calais Nord Pas-de-Calais 62100",
    "addr:housenumber":"20",
    "addr:postcode":"62100;62100",
    "addr:street":"Rue Delaroche;Calais;Pas-De-Calais",
    "iso:country":"FR",
    "sg:address":"20 Rue Delaroche 62100 Calais",
    "sg:classifiers":[
        {
            "category":"Shopping",
            "subcategory":"Crafts & Fabrics",
            "type":"Retail Goods"
        }
    ],
    "sg:phone":"+33 3 21 36 28 32",
    "sg:postcode":"62100",
    "sg:province":"Nord Pas-de-Calais",
    "sg:tags":[
        "textile",
        "clothing"
    ],
    "wof:name":"Dentelle Sophie Hallette",
    "wof:placetype":"venue"
},
  "geometry": {"coordinates":[1.86757,50.946751],"type":"Point"}
}