{
  "type": "Feature",
  "properties": {
    "addr:full":"8, Rue du Sentier, 75080 Paris C\u00e9dex 02 Ile de France",
    "addr:housenumber":"8;02",
    "addr:postcode":"75080",
    "addr:street":"Rue Du Sentier;Ile De France",
    "iso:country":"FR",
    "sg:address":"8, Rue du Sentier, 75080 Paris C\u00e9dex 02",
    "sg:orig_category":"Non-Classified Establishments",
    "sg:phone":"+33 1 53 43 91 46",
    "sg:province":"Ile de France",
    "wof:name":"Creuters France",
    "wof:placetype":"venue"
},
  "geometry": {"coordinates":[2.345785,48.868378],"type":"Point"}
}