{
  "type": "Feature",
  "properties": {
    "iso:country":"FR",
    "sg:address":"Les Pr\u00e9s 83570 Entrecasteaux",
    "sg:orig_category":"Unclassifiable Establishments",
    "sg:phone":"+33 4 94 04 42 68",
    "sg:province":"Provence-Alpes-C\u00f4te d'Azur",
    "wof:name":"Coop\u00e9rative Vinicole D'entrecasteaux S.c.a.",
    "wof:placetype":"venue"
},
  "geometry": {"coordinates":[6.239084,43.519924],"type":"Point"}
}