{
  "type": "Feature",
  "properties": {
    "addr:full":"Kerluandre 29300 Tremeven Tr\u00e9m\u00e9ven Bretagne 29300",
    "addr:postcode":"29300;29300",
    "addr:street":"Kerluandre;Tre\u0301Me\u0301Ven",
    "iso:country":"FR",
    "sg:address":"Kerluandre 29300 Tremeven",
    "sg:city":"Tr\u00e9m\u00e9ven",
    "sg:classifiers":[
        {
            "category":"Bakery",
            "type":"Food & Drink"
        }
    ],
    "sg:phone":"+33 2 98 39 35 58",
    "sg:postcode":"29300",
    "sg:province":"Bretagne",
    "sg:tags":[
        "cake",
        "product",
        "related",
        "bread"
    ],
    "wof:name":"La Tremevenoise",
    "wof:placetype":"venue"
},
  "geometry": {"coordinates":[-3.536259,47.879677],"type":"Point"}
}