{
  "type": "Feature",
  "properties": {
    "addr:full":"6, Av. du Mar\u00e9chal Foch, 31800 Saint Gaudens Midi Pyr\u00e9n\u00e9es",
    "addr:postcode":"31800",
    "addr:street":"Av. Du Mare\u0301Chal Foch",
    "iso:country":"FR",
    "sg:address":"6, Av. du Mar\u00e9chal Foch, 31800 Saint Gaudens",
    "sg:orig_category":"Non-Classified Establishments",
    "sg:phone":"+33 5 61 95 45 75",
    "sg:province":"Midi Pyr\u00e9n\u00e9es",
    "wof:name":"S.o.c. - Services Occasionnels Commingeois",
    "wof:placetype":"venue"
},
  "geometry": {"coordinates":[0.7198,43.10648],"type":"Point"}
}