{
  "type": "Feature",
  "properties": {
    "iso:country":"FR",
    "sg:address":"59, Rue des Mathurins, 75008 Paris",
    "sg:orig_category":"Unclassifiable Establishments",
    "sg:phone":"+33 1 42 66 50 51",
    "sg:province":"Ile de France",
    "wof:name":"Axel Assistance S.a.",
    "wof:placetype":"venue"
},
  "geometry": {"coordinates":[2.321314,48.873333],"type":"Point"}
}