{
  "type": "Feature",
  "properties": {
    "iso:country":"FR",
    "sg:address":"B.P. 42, 26301 Bourg de P\u00e9age C\u00e9dex^^All\u00e9e du Lyonnais - ZI, 26300 Bourg de P\u00e9age",
    "sg:orig_category":"Non-Classified Establishments",
    "sg:phone":"+33 4 75 70 41 03",
    "sg:province":"Rhone-Alpes",
    "wof:name":"Maurens Et Scopont S.a.r.l.",
    "wof:placetype":"venue"
},
  "geometry": {"coordinates":[5.09157,44.938511],"type":"Point"}
}