{
  "type": "Feature",
  "properties": {
    "iso:country":"FR",
    "sg:address":"9, Rue du Corps Franc Pommies, 46300 Gourdon",
    "sg:orig_category":"Non-Classified Establishments",
    "sg:phone":"+33 5 65 27 08 28",
    "sg:postcode":"46300",
    "sg:province":"Midi Pyr\u00e9n\u00e9es",
    "wof:name":"Bouriane Solidarit\u00e9",
    "wof:placetype":"venue"
},
  "geometry": {"coordinates":[1.383628,44.737171],"type":"Point"}
}