{
  "type": "Feature",
  "properties": {
    "addr:full":"La Courtoiserie 27270 Saint Jean du Thenney Haute Normandie",
    "addr:postcode":"27270",
    "addr:street":"Saint Jean Du Thenney Haute Normandie",
    "iso:country":"FR",
    "sg:address":"La Courtoiserie 27270 Saint Jean du Thenney",
    "sg:orig_category":"Non-Classified Establishments",
    "sg:phone":"+33 2 32 44 65 16",
    "sg:province":"Haute Normandie",
    "wof:name":"Morel Emmanuel",
    "wof:placetype":"venue"
},
  "geometry": {"coordinates":[0.461225,49.01228],"type":"Point"}
}