{
  "type": "Feature",
  "properties": {
    "addr:full":"Gournac Z Artisanale De Laure 09700 SAVERDUN Midi Pyr\u00e9n\u00e9es",
    "addr:postcode":"09700",
    "iso:country":"FR",
    "sg:address":"Gournac Z Artisanale De Laure 09700 SAVERDUN",
    "sg:classifiers":[
        {
            "category":"Home & Garden",
            "subcategory":"Hardware",
            "type":"Retail Goods"
        }
    ],
    "sg:phone":"+33 5 61 60 31 80",
    "sg:province":"Midi Pyr\u00e9n\u00e9es",
    "sg:tags":[
        "tarpaulin"
    ],
    "wof:name":"Ste Des Toiles Et Baches Gournac Sa",
    "wof:placetype":"venue"
},
  "geometry": {"coordinates":[1.5882,43.211658],"type":"Point"}
}