{
  "type": "Feature",
  "properties": {
    "iso:country":"FR",
    "sg:address":"10 Rue St Exup\u00e9ry",
    "sg:city":"Lorient",
    "sg:classifiers":[
        {
            "category":"Autos & Motor Vehicles",
            "subcategory":"Fuel & Gas Station",
            "type":"Retail Goods"
        }
    ],
    "sg:phone":"+33 2 97 37 25 87",
    "sg:postcode":"56100",
    "sg:province":"Bretagne",
    "sg:tags":[
        "engine",
        "-",
        "machine",
        "equipment",
        "engineering",
        "part",
        "electrical",
        "mechanical",
        "electronic"
    ],
    "wof:name":"Rgbb Sa",
    "wof:placetype":"venue"
},
  "geometry": {"coordinates":[-3.365181,47.748108],"type":"Point"}
}