{
  "type": "Feature",
  "properties": {
    "addr:full":"25, Rue Falgui\u00e8re, 75015 Paris Ile de France",
    "addr:housenumber":"25",
    "addr:postcode":"75015",
    "addr:street":"Rue Falguie\u0300Re",
    "iso:country":"FR",
    "sg:address":"25, Rue Falgui\u00e8re, 75015 Paris",
    "sg:orig_category":"Unclassifiable Establishments",
    "sg:phone":"+33 1 43 35 30 30",
    "sg:province":"Ile de France",
    "wof:name":"Dialectic S.a.",
    "wof:placetype":"venue"
},
  "geometry": {"coordinates":[2.316539,48.842808],"type":"Point"}
}