{
  "type": "Feature",
  "properties": {
    "addr:full":"16000 Angoul\u00eame Poitou-Charentes",
    "addr:postcode":"16000",
    "iso:country":"FR",
    "sg:address":"16000 Angoul\u00eame",
    "sg:orig_category":"Unclassifiable Establishments",
    "sg:phone":"+33 5 45 23 39 39",
    "sg:province":"Poitou-Charentes",
    "wof:name":"Lafarge Ciments S.a.",
    "wof:placetype":"venue"
},
  "geometry": {"coordinates":[0.14514,45.645672],"type":"Point"}
}