{
  "type": "Feature",
  "properties": {
    "addr:full":"9, Rue de la Garance, 67240 Bischwiller Bischwiller Alsace 67240",
    "addr:housenumber":"9",
    "addr:postcode":"67240;67240",
    "addr:street":"Rue De La Garance",
    "iso:country":"FR",
    "sg:address":"9, Rue de la Garance, 67240 Bischwiller",
    "sg:city":"Bischwiller",
    "sg:orig_category":"Non-Classified Establishments",
    "sg:phone":"+33 3 88 06 41 90",
    "sg:postcode":"67240",
    "sg:province":"Alsace",
    "wof:name":"Moscherosch Teinturerie S.a.",
    "wof:placetype":"venue"
},
  "geometry": {"coordinates":[7.861127,48.760868],"type":"Point"}
}