{
  "type": "Feature",
  "properties": {
    "iso:country":"FR",
    "sg:address":"261 Rte De St Michel 18000 Bourges",
    "sg:city":"Bourges",
    "sg:classifiers":[
        {
            "category":"Professional",
            "subcategory":"Business Services",
            "type":"Services"
        }
    ],
    "sg:phone":"+33 2 48 65 31 93",
    "sg:postcode":"18000",
    "sg:province":"Centre",
    "sg:tags":[
        "body",
        "advice"
    ],
    "wof:name":"Association D'entraide Berruyere",
    "wof:placetype":"venue"
},
  "geometry": {"coordinates":[2.423229,47.103962],"type":"Point"}
}