{
  "type": "Feature",
  "properties": {
    "addr:full":"B.P. 1, 38330 Montbonnot Saint Martin^^195, Rue Lavoisier, 38330 Montbonnot Saint Martin Rhone-Alpes 38330",
    "addr:housenumber":"1",
    "addr:postcode":"38330;38330;38330",
    "addr:street":"B.P.;Rue Lavoisier;Rhone-Alpes",
    "iso:country":"FR",
    "sg:address":"B.P. 1, 38330 Montbonnot Saint Martin^^195, Rue Lavoisier, 38330 Montbonnot Saint Martin",
    "sg:orig_category":"Non-Classified Establishments",
    "sg:phone":"+33 4 76 41 66 48",
    "sg:postcode":"38330",
    "sg:province":"Rhone-Alpes",
    "wof:name":"Groupe Silicomp S.a.",
    "wof:placetype":"venue"
},
  "geometry": {"coordinates":[5.81127,45.217968],"type":"Point"}
}