{
  "type": "Feature",
  "properties": {
    "addr:full":"1 All Des Mouettes Du Rivage Z.I. La Fray\u00e8re 06150 Cannes La Bocca Champagne",
    "addr:housenumber":"1",
    "addr:postcode":"06150",
    "addr:street":"All Des Mouettes Du Rivage Z.I. La Fraye\u0300Re",
    "iso:country":"FR",
    "sg:address":"1 All Des Mouettes",
    "sg:city":"Du Rivage Z.I. La Fray\u00e8re 06150 Cannes La Bocca",
    "sg:classifiers":[
        {
            "category":"Autos & Motor Vehicles",
            "subcategory":"Boat Sales",
            "type":"Retail Goods"
        }
    ],
    "sg:phone":"+33 4 93 48 12 11",
    "sg:province":"Champagne",
    "sg:tags":[
        "equipment",
        "transport"
    ],
    "wof:name":"Elvstrom-sobstade",
    "wof:placetype":"venue"
},
  "geometry": {"coordinates":[6.968731,43.556938],"type":"Point"}
}