{
  "type": "Feature",
  "properties": {
    "addr:full":"21 rue Parmentier 42100 ST ETIENNE Rhone-Alpes 42100",
    "addr:housenumber":"21",
    "addr:postcode":"42100;42100",
    "addr:street":"Rue Parmentier",
    "iso:country":"FR",
    "sg:address":"21 rue Parmentier 42100 ST ETIENNE",
    "sg:classifiers":[
        {
            "category":"Wholesale",
            "subcategory":"Construction Materials",
            "type":"Manufacturing & Wholesale Goods"
        }
    ],
    "sg:phone":"+33 4 77 81 24 66",
    "sg:postcode":"42100",
    "sg:province":"Rhone-Alpes",
    "sg:tags":[
        "cloth",
        "dye"
    ],
    "wof:name":"Servitex Sa",
    "wof:placetype":"venue"
},
  "geometry": {"coordinates":[4.399648,45.417336],"type":"Point"}
}