{
  "type": "Feature",
  "properties": {
    "addr:full":"93, Rue Nationale, 62151 Burbure Nord Pas-de-Calais",
    "addr:housenumber":"93",
    "addr:postcode":"62151",
    "addr:street":"Rue Nationale",
    "iso:country":"FR",
    "sg:address":"93, Rue Nationale, 62151 Burbure",
    "sg:orig_category":"Unclassifiable Establishments",
    "sg:phone":"+33 3 21 64 59 89",
    "sg:province":"Nord Pas-de-Calais",
    "wof:name":"Savio Vincent S.a.r.l.",
    "wof:placetype":"venue"
},
  "geometry": {"coordinates":[2.45696,50.524082],"type":"Point"}
}