{
  "type": "Feature",
  "properties": {
    "iso:country":"FR",
    "sg:address":"3, Rue Jean de Becker R\u00e9my, 27940 Aubevoye",
    "sg:orig_category":"Unclassifiable Establishments",
    "sg:phone":"+33 2 32 53 04 85",
    "sg:province":"Haute Normandie",
    "wof:name":"D.k. Plast S.a.r.l.",
    "wof:placetype":"venue"
},
  "geometry": {"coordinates":[1.352132,49.175915],"type":"Point"}
}