{
  "type": "Feature",
  "properties": {
    "iso:country":"FR",
    "sg:address":"Zi 02700 Condren",
    "sg:classifiers":[
        {
            "category":"Manufacturing",
            "subcategory":"Glass & Minerals",
            "type":"Manufacturing & Wholesale Goods"
        }
    ],
    "sg:phone":"+33 3 23 57 81 81",
    "sg:postcode":"02700",
    "sg:province":"Picardie",
    "sg:tags":[
        "building",
        "material"
    ],
    "wof:name":"St Gobain Produits Industriels Sas",
    "wof:placetype":"venue"
},
  "geometry": {"coordinates":[3.293201,49.653469],"type":"Point"}
}