{
  "type": "Feature",
  "properties": {
    "addr:full":"29 rue Nationale; Pontivy; 56300 Pontivy Bretagne 56300",
    "addr:housenumber":"29",
    "addr:postcode":"56300;56300",
    "addr:street":"Rue Nationale;Bretagne",
    "iso:country":"FR",
    "sg:address":"29 rue Nationale; Pontivy; 56300",
    "sg:city":"Pontivy",
    "sg:classifiers":[
        {
            "category":"Banks & Credit Unions",
            "subcategory":"Bank",
            "type":"Services"
        }
    ],
    "sg:phone":"+33 3397250005",
    "sg:postcode":"56300",
    "sg:province":"Bretagne",
    "wof:name":"Soci\u00e9t\u00e9 G\u00e9n\u00e9rale",
    "wof:placetype":"venue"
},
  "geometry": {"coordinates":[-2.965434,48.066536],"type":"Point"}
}