{
  "type": "Feature",
  "properties": {
    "addr:full":"17, Rte d'Obernai, 67530 Boersch Boersch Alsace 67530",
    "addr:housenumber":"17",
    "addr:postcode":"67530;67530",
    "addr:street":"Rte D'Obernai;Boersch",
    "iso:country":"FR",
    "sg:address":"17, Rte d'Obernai, 67530 Boersch",
    "sg:city":"Boersch",
    "sg:orig_category":"Unclassifiable Establishments",
    "sg:phone":"+33 3 88 95 81 40",
    "sg:postcode":"67530",
    "sg:province":"Alsace",
    "wof:name":"Tr\u00e9boma S.a.r.l.",
    "wof:placetype":"venue"
},
  "geometry": {"coordinates":[7.43994,48.475769],"type":"Point"}
}