{
  "type": "Feature",
  "properties": {
    "iso:country":"FR",
    "sg:address":"15, Rue Aristide Berges, 38320 Eybens",
    "sg:orig_category":"Unclassifiable Establishments",
    "sg:phone":"+33 4 76 62 96 96",
    "sg:postcode":"38320",
    "sg:province":"Rhone-Alpes",
    "wof:name":"Air Liquide Electronics Systems S.a.",
    "wof:placetype":"venue"
},
  "geometry": {"coordinates":[5.74409,45.147739],"type":"Point"}
}