{
  "type": "Feature",
  "properties": {
    "iso:country":"FR",
    "sg:address":"B.P. 29, 06211 Mandelieu C\u00e9dex^^131, Av. du Mar\u00e9chal Lyautey - ZA la Proven\u00e7ale, 06210 Mandelieu la ",
    "sg:orig_category":"Non-Classified Establishments",
    "sg:phone":"+33 4 93 48 16 16",
    "sg:province":"Haute Normandie",
    "wof:name":"Angelini S.a.",
    "wof:placetype":"venue"
},
  "geometry": {"coordinates":[6.93623,43.542488],"type":"Point"}
}