{
  "type": "Feature",
  "properties": {
    "addr:full":"24 rue Chartraine; Evreux; 27000 Haute Normandie 27000",
    "addr:housenumber":"24",
    "addr:postcode":"27000;27000",
    "addr:street":"Rue Chartraine;Normandie",
    "iso:country":"FR",
    "sg:address":"24 rue Chartraine; Evreux; 27000",
    "sg:classifiers":[
        {
            "category":"Banks & Credit Unions",
            "subcategory":"Bank",
            "type":"Services"
        }
    ],
    "sg:phone":"+33 32314700",
    "sg:postcode":"27000",
    "sg:province":"Haute Normandie",
    "wof:name":"Soci\u00e9t\u00e9 G\u00e9n\u00e9rale",
    "wof:placetype":"venue"
},
  "geometry": {"coordinates":[1.148188,49.025166],"type":"Point"}
}