{
  "type": "Feature",
  "properties": {
    "addr:full":"2, All\u00e9e de la Tramontane, 30133 Les Angles Languedoc-Roussillon",
    "addr:housenumber":"2",
    "addr:postcode":"30133 les angles",
    "addr:street":"Alle\u0301E De La Tramontane",
    "iso:country":"FR",
    "sg:address":"2, All\u00e9e de la Tramontane, 30133 Les Angles",
    "sg:orig_category":"Unclassifiable Establishments",
    "sg:phone":"+33 4 90 15 16 32",
    "sg:province":"Languedoc-Roussillon",
    "wof:name":"I.m.c. S.a. - Industrialise Modulaire Cartoux",
    "wof:placetype":"venue"
},
  "geometry": {"coordinates":[4.75516,43.957733],"type":"Point"}
}