{
  "type": "Feature",
  "properties": {
    "addr:full":"Rte De Montr\u00e9al 11000 Carcassonne Languedoc-Roussillon 11000",
    "addr:postcode":"11000;11000",
    "addr:street":"Rte De Montre\u0301Al",
    "iso:country":"FR",
    "sg:address":"Rte De Montr\u00e9al 11000 Carcassonne",
    "sg:classifiers":[
        {
            "category":"Shopping",
            "subcategory":"Hobbies, Toys, & Games",
            "type":"Retail Goods"
        }
    ],
    "sg:phone":"+33 4 68 25 38 16",
    "sg:postcode":"11000",
    "sg:province":"Languedoc-Roussillon",
    "sg:tags":[
        "product",
        "miscellaneous",
        "entertainment"
    ],
    "wof:name":"Majar Sa",
    "wof:placetype":"venue"
},
  "geometry": {"coordinates":[2.306378,43.188465],"type":"Point"}
}