{
  "type": "Feature",
  "properties": {
    "addr:full":"Pl Du Ch\u00e2teau 59559 Comines Ch\u00e2teau Bourgogne 71250",
    "addr:postcode":"59559;71250",
    "addr:street":"Pl Du Cha\u0302Teau",
    "iso:country":"FR",
    "sg:address":"Pl Du Ch\u00e2teau 59559 Comines",
    "sg:city":"Ch\u00e2teau",
    "sg:classifiers":[
        {
            "category":"Bakery",
            "type":"Food & Drink"
        }
    ],
    "sg:phone":"+33 3 20 39 34 37",
    "sg:postcode":"71250",
    "sg:province":"Bourgogne",
    "sg:tags":[
        "cake",
        "product",
        "related",
        "bread"
    ],
    "wof:name":"Lotus Bakeries France",
    "wof:placetype":"venue"
},
  "geometry": {"coordinates":[3.009853,50.766502],"type":"Point"}
}