{
  "type": "Feature",
  "properties": {
    "iso:country":"FR",
    "sg:address":"20, Rue de Loz\u00e8re, 91400 Orsay",
    "sg:orig_category":"Non-Classified Establishments",
    "sg:phone":"+33 1 60 10 05 74",
    "sg:province":"Ile de France",
    "wof:name":"T.i.m. S.a.r.l. - Techniques Industrielles De Maintenance",
    "wof:placetype":"venue"
},
  "geometry": {"coordinates":[2.194401,48.704559],"type":"Point"}
}