{
  "type": "Feature",
  "properties": {
    "addr:full":"177 R Des Capucines 51100 Reims Champagne 51100",
    "addr:housenumber":"177",
    "addr:postcode":"51100;51100",
    "addr:street":"R Des Capucines",
    "iso:country":"FR",
    "sg:address":"177 R Des Capucines 51100 Reims",
    "sg:classifiers":[
        {
            "category":"Professional",
            "subcategory":"Business Services",
            "type":"Services"
        }
    ],
    "sg:phone":"+33 3 26 85 23 65",
    "sg:postcode":"51100",
    "sg:province":"Champagne",
    "sg:tags":[
        "training",
        "advice"
    ],
    "wof:name":"Lycee St Joseph",
    "wof:placetype":"venue"
},
  "geometry": {"coordinates":[4.033797,49.247734],"type":"Point"}
}