{
  "type": "Feature",
  "properties": {
    "iso:country":"FR",
    "sg:address":"Saint L\u00e9ger de Peyre 48100 Marvejols",
    "sg:orig_category":"Non-Classified Establishments",
    "sg:phone":"+33 4 66 32 10 84",
    "sg:postcode":"48100",
    "sg:province":"Languedoc-Roussillon",
    "wof:name":"Bonnet G\u00e9rard S.a.",
    "wof:placetype":"venue"
},
  "geometry": {"coordinates":[3.284801,44.568432],"type":"Point"}
}