{
  "type": "Feature",
  "properties": {
    "addr:full":"Zac Les Marli\u00e8res 59710 Avelin Nord Pas-de-Calais 59710",
    "addr:postcode":"59710;59710",
    "addr:street":"Zac Les Marlie\u0300Res",
    "iso:country":"FR",
    "sg:address":"Zac Les Marli\u00e8res 59710 Avelin",
    "sg:classifiers":[
        {
            "category":"Professional",
            "subcategory":"Engineering",
            "type":"Services"
        }
    ],
    "sg:phone":"+33 3 20 62 95 62",
    "sg:postcode":"59710",
    "sg:province":"Nord Pas-de-Calais",
    "sg:tags":[
        "machine",
        "-",
        "mechanical"
    ],
    "wof:name":"Facultatieve Technologies",
    "wof:placetype":"venue"
},
  "geometry": {"coordinates":[3.080295,50.53793],"type":"Point"}
}