{
  "type": "Feature",
  "properties": {
    "addr:full":"195 rue Jean Jaures Toulon 83000",
    "addr:housenumber":"195",
    "addr:postcode":"83000",
    "addr:street":"Rue Jean Jaures",
    "iso:country":"FR",
    "sg:address":"195 rue Jean Jaures",
    "sg:city":"Toulon",
    "sg:classifiers":[
        {
            "category":"Professional",
            "subcategory":"Computer Services",
            "type":"Services"
        }
    ],
    "sg:postcode":"83000",
    "sg:tags":[
        "emob",
        "elearning",
        "video",
        "screencast",
        "screencasting",
        "tutorial"
    ],
    "sg:website":"http://formationvideo.emob.fr",
    "wof:name":"EMOB",
    "wof:placetype":"venue"
},
  "geometry": {"coordinates":[5.929313,43.124351],"type":"Point"}
}