{
  "type": "Feature",
  "properties": {
    "addr:full":"89 rue Carnot 92300 Levallois Perret Ile de France",
    "addr:housenumber":"89",
    "addr:postcode":"92300;ile",
    "addr:street":"Rue Carnot",
    "iso:country":"FR",
    "sg:address":"89 rue Carnot 92300 Levallois Perret",
    "sg:classifiers":[
        {
            "category":"Professional",
            "subcategory":"Art Services",
            "type":"Services"
        }
    ],
    "sg:phone":"+33 1 41 49 00 20",
    "sg:province":"Ile de France",
    "sg:tags":[
        "photo",
        "series"
    ],
    "wof:name":"Magenta Sarl",
    "wof:placetype":"venue"
},
  "geometry": {"coordinates":[2.284523,48.893875],"type":"Point"}
}