{
  "type": "Feature",
  "properties": {
    "addr:full":"75384 Paris C\u00e9dex 08^^22/30, Av. Wagram, 75008 Paris Ile de France 75008",
    "addr:housenumber":"08;^ 22 / 30",
    "addr:postcode":"75384;75008;75008",
    "addr:street":"^;Av. Wagram",
    "iso:country":"FR",
    "sg:address":"75384 Paris C\u00e9dex 08^^22/30, Av. Wagram, 75008 Paris",
    "sg:orig_category":"Non-Classified Establishments",
    "sg:phone":"+33 1 40 42 22 22",
    "sg:postcode":"75008",
    "sg:province":"Ile de France",
    "wof:name":"E.d.f. -electricit\u00e9 De France",
    "wof:placetype":"venue"
},
  "geometry": {"coordinates":[2.34121,48.856926],"type":"Point"}
}