{
  "type": "Feature",
  "properties": {
    "addr:full":"1, Rue du Mar\u00e9chal Leclerc, 38130 Echirolles Rhone-Alpes 38130",
    "addr:housenumber":"1",
    "addr:postcode":"38130;38130",
    "addr:street":"Rue Du Mare\u0301Chal Leclerc;Rhone-Alpes",
    "iso:country":"FR",
    "sg:address":"1, Rue du Mar\u00e9chal Leclerc, 38130 Echirolles",
    "sg:orig_category":"Unclassifiable Establishments",
    "sg:phone":"+33 4 76 33 00 55",
    "sg:postcode":"38130",
    "sg:province":"Rhone-Alpes",
    "wof:name":"Afficom S.a.r.l.",
    "wof:placetype":"venue"
},
  "geometry": {"coordinates":[5.711671,45.137432],"type":"Point"}
}