{
  "type": "Feature",
  "properties": {
    "addr:full":"3 Rue Jean Mermoz 93297 Tremblay En France Cedex Aquitaine",
    "addr:housenumber":"3",
    "addr:postcode":"93297",
    "addr:street":"Rue Jean Mermoz",
    "iso:country":"FR",
    "sg:address":"3 Rue Jean Mermoz 93297 Tremblay En France Cedex",
    "sg:classifiers":[
        {
            "category":"Manufacturing",
            "subcategory":"Metals",
            "type":"Manufacturing & Wholesale Goods"
        }
    ],
    "sg:phone":"+33 1 49 63 86 39",
    "sg:province":"Aquitaine",
    "sg:tags":[
        "metallurgy",
        "metalworking",
        "processing"
    ],
    "wof:name":"Ste Industrielle De Meca D'optique Et De Precision Simop (simop)",
    "wof:placetype":"venue"
},
  "geometry": {"coordinates":[2.567334,48.966873],"type":"Point"}
}