{
  "type": "Feature",
  "properties": {
    "iso:country":"FR",
    "sg:address":"81 Av Du Pdt Kennedy 87000 Limoges",
    "sg:classifiers":[
        {
            "category":"Building & Trades",
            "subcategory":"Construction",
            "type":"Services"
        }
    ],
    "sg:phone":"+33 5 55 30 91 00",
    "sg:postcode":"87000",
    "sg:province":"Limousin",
    "sg:tags":[
        "work",
        "public"
    ],
    "wof:name":"Eurovia Management Snc",
    "wof:placetype":"venue"
},
  "geometry": {"coordinates":[1.281215,45.805038],"type":"Point"}
}