{
  "type": "Feature",
  "properties": {
    "addr:full":"ZA la Bouissonade Lagrave Midi Pyr\u00e9n\u00e9es 81150",
    "addr:postcode":"81150",
    "addr:street":"Za La Bouissonade Lagrave",
    "iso:country":"FR",
    "sg:address":"ZA la Bouissonade",
    "sg:city":"Lagrave",
    "sg:orig_category":"Unclassifiable Establishments",
    "sg:phone":"+33 5 63 57 72 00",
    "sg:postcode":"81150",
    "sg:province":"Midi Pyr\u00e9n\u00e9es",
    "wof:name":"Verts Loisirs",
    "wof:placetype":"venue"
},
  "geometry": {"coordinates":[1.991842,43.898067],"type":"Point"}
}