{
  "type": "Feature",
  "properties": {
    "addr:full":"2 boulevard du Mar\u00e9chal Juin 65000 Tarbes Midi Pyr\u00e9n\u00e9es 65000",
    "addr:housenumber":"2",
    "addr:postcode":"65000;65000",
    "addr:street":"Boulevard Du Mare\u0301Chal Juin",
    "iso:country":"FR",
    "sg:address":"2 boulevard du Mar\u00e9chal Juin 65000 Tarbes",
    "sg:classifiers":[
        {
            "category":"Manufacturing",
            "subcategory":"Printing",
            "type":"Manufacturing & Wholesale Goods"
        }
    ],
    "sg:phone":"+33 5 62 34 07 77",
    "sg:postcode":"65000",
    "sg:province":"Midi Pyr\u00e9n\u00e9es",
    "sg:tags":[
        "house",
        "book"
    ],
    "wof:name":"Conseil Imprim S.a.",
    "wof:placetype":"venue"
},
  "geometry": {"coordinates":[0.061979,43.239567],"type":"Point"}
}