{
  "type": "Feature",
  "properties": {
    "addr:full":"ZI de Kergr\u00e9 Ploumagoar Bretagne 22970",
    "addr:postcode":"22970",
    "addr:street":"Zi De Kergre\u0301 Ploumagoar Bretagne",
    "iso:country":"FR",
    "sg:address":"ZI de Kergr\u00e9",
    "sg:city":"Ploumagoar",
    "sg:orig_category":"Non-Classified Establishments",
    "sg:phone":"+33 2 96 37 06 15",
    "sg:postcode":"22970",
    "sg:province":"Bretagne",
    "wof:name":"Gu\u00e9zet S.a.r.l.",
    "wof:placetype":"venue"
},
  "geometry": {"coordinates":[-3.13226,48.54538],"type":"Point"}
}