{
  "type": "Feature",
  "properties": {
    "iso:country":"FR",
    "sg:address":"Le Moulin De Goudou 24170 St Pompont",
    "sg:city":"Belv\u00e8s",
    "sg:classifiers":[
        {
            "category":"Farming",
            "subcategory":"Livestock Farm",
            "type":"Manufacturing & Wholesale Goods"
        }
    ],
    "sg:phone":"+33 5 53 28 47 21",
    "sg:postcode":"24170",
    "sg:province":"Aquitaine",
    "sg:tags":[
        "grain",
        "agriculture",
        "cereal"
    ],
    "wof:name":"Etablissements Bouyssou Sa",
    "wof:placetype":"venue"
},
  "geometry": {"coordinates":[1.14745,44.725121],"type":"Point"}
}