{
  "type": "Feature",
  "properties": {
    "iso:country":"FR",
    "sg:address":"1 Cs Du G\u00e9n\u00e9ral De Gaulle 33170 Gradignan",
    "sg:city":"Gradignan",
    "sg:classifiers":[
        {
            "category":"Professional",
            "subcategory":"Business Services",
            "type":"Services"
        }
    ],
    "sg:phone":"+33 5 57 35 07 07",
    "sg:postcode":"33170",
    "sg:province":"Aquitaine",
    "sg:tags":[
        "training",
        "advice"
    ],
    "wof:name":"Ecole Nationale D'ing\u00c9nieur Des Travaux Agricoles (enita)",
    "wof:placetype":"venue"
},
  "geometry": {"coordinates":[-0.606969,44.783211],"type":"Point"}
}