{
  "type": "Feature",
  "properties": {
    "addr:full":"10, Chemin de la Maladi\u00e8re - ZI de l'Argenti\u00e8re, 38360 Sassenage Rhone-Alpes 38360",
    "addr:housenumber":"10",
    "addr:postcode":"38360;38360",
    "addr:street":"Chemin De La Maladie\u0300Re Zi De L'Argentie \u0300Re",
    "iso:country":"FR",
    "sg:address":"10, Chemin de la Maladi\u00e8re - ZI de l'Argenti\u00e8re, 38360 Sassenage",
    "sg:orig_category":"Non-Classified Establishments",
    "sg:phone":"+33 4 76 26 41 46",
    "sg:postcode":"38360",
    "sg:province":"Rhone-Alpes",
    "wof:name":"C.m.b. S.a.r.l. - Constructions M\u00e9caniques Buissonnet",
    "wof:placetype":"venue"
},
  "geometry": {"coordinates":[5.671662,45.199844],"type":"Point"}
}