{
  "type": "Feature",
  "properties": {
    "iso:country":"FR",
    "sg:address":"Rue de la Laiterie",
    "sg:city":"Verton",
    "sg:orig_category":"Unclassifiable Establishments",
    "sg:phone":"+33 3 21 84 34 34",
    "sg:postcode":"62180",
    "sg:province":"Nord Pas-de-Calais",
    "wof:name":"Nutrilac S.a.",
    "wof:placetype":"venue"
},
  "geometry": {"coordinates":[1.64909,50.408051],"type":"Point"}
}