{
  "type": "Feature",
  "properties": {
    "iso:country":"FR",
    "sg:address":"17, Av. Jacques Cartier, 44800 Saint Herblain",
    "sg:orig_category":"Non-Classified Establishments",
    "sg:phone":"+33 2 40 92 05 86",
    "sg:province":"Pays de Loire",
    "wof:name":"Le Chaudron Magique S.a.r.l.",
    "wof:placetype":"venue"
},
  "geometry": {"coordinates":[-1.635505,47.226055],"type":"Point"}
}