{
  "type": "Feature",
  "properties": {
    "iso:country":"FR",
    "sg:address":"8 Rue Europe 59540 Caudry",
    "sg:classifiers":[
        {
            "category":"Shopping",
            "subcategory":"Crafts & Fabrics",
            "type":"Retail Goods"
        }
    ],
    "sg:phone":"+33 3 27 85 37 12",
    "sg:postcode":"59540",
    "sg:province":"Nord Pas-de-Calais",
    "sg:tags":[
        "textile",
        "clothing"
    ],
    "wof:name":"Velysam Coloredo",
    "wof:placetype":"venue"
},
  "geometry": {"coordinates":[3.421943,50.112427],"type":"Point"}
}