{
  "type": "Feature",
  "properties": {
    "addr:full":"Le Saubenard 14400 Blay Blay Basse Normandie 14400",
    "addr:postcode":"14400;14400",
    "iso:country":"FR",
    "sg:address":"Le Saubenard 14400 Blay",
    "sg:city":"Blay",
    "sg:orig_category":"Non-Classified Establishments",
    "sg:phone":"+33 2 31 92 74 74",
    "sg:postcode":"14400",
    "sg:province":"Basse Normandie",
    "wof:name":"Ylem S.a.r.l.",
    "wof:placetype":"venue"
},
  "geometry": {"coordinates":[-0.636232,49.223503],"type":"Point"}
}