{
  "type": "Feature",
  "properties": {
    "addr:full":"Zone Artisanale St Vincent 73190 Challes Les Eaux Rhone-Alpes 73190",
    "addr:postcode":"73190;73190",
    "addr:street":"Zone Artisanale St",
    "iso:country":"FR",
    "sg:address":"Zone Artisanale St Vincent 73190 Challes Les Eaux",
    "sg:classifiers":[
        {
            "category":"Home & Garden",
            "subcategory":"Furniture",
            "type":"Retail Goods"
        }
    ],
    "sg:phone":"+33 4 79 72 85 31",
    "sg:postcode":"73190",
    "sg:province":"Rhone-Alpes",
    "sg:tags":[
        "household",
        "wood"
    ],
    "wof:name":"Norma",
    "wof:placetype":"venue"
},
  "geometry": {"coordinates":[5.982985,45.548054],"type":"Point"}
}