{
  "type": "Feature",
  "properties": {
    "addr:full":"ZA Marlhes Rhone-Alpes 42660",
    "addr:postcode":"42660",
    "addr:street":"Za Marlhes Rhone-Alpes",
    "iso:country":"FR",
    "sg:address":"ZA",
    "sg:city":"Marlhes",
    "sg:orig_category":"Non-Classified Establishments",
    "sg:phone":"+33 4 77 51 84 63",
    "sg:postcode":"42660",
    "sg:province":"Rhone-Alpes",
    "wof:name":"Le Foie Gras Marlhes S.a.r.l.",
    "wof:placetype":"venue"
},
  "geometry": {"coordinates":[4.394324,45.283489],"type":"Point"}
}