{
  "type": "Feature",
  "properties": {
    "addr:full":"B.P. 4, 45410 Artenay C\u00e9dex^^20, Rue de la Gare, 45410 Artenay Artenay Centre 45410",
    "addr:housenumber":"4;artenay",
    "addr:postcode":"45410;45410;45410",
    "addr:street":"B.P.;Rue De La Gare",
    "iso:country":"FR",
    "sg:address":"B.P. 4, 45410 Artenay C\u00e9dex^^20, Rue de la Gare, 45410 Artenay",
    "sg:city":"Artenay",
    "sg:orig_category":"Non-Classified Establishments",
    "sg:phone":"+33 2 38 52 31 10",
    "sg:postcode":"45410",
    "sg:province":"Centre",
    "wof:name":"Lecureur S.a.",
    "wof:placetype":"venue"
},
  "geometry": {"coordinates":[1.880494,48.082932],"type":"Point"}
}