{
  "type": "Feature",
  "properties": {
    "iso:country":"FR",
    "sg:address":"2, Bd de la Lib\u00e9ration - Urbaparc 1 B\u00e2t. G, 93200 Saint Denis",
    "sg:orig_category":"Non-Classified Establishments",
    "sg:phone":"+33 1 48 09 22 23",
    "sg:province":"Ile de France",
    "wof:name":"Mensys S.a.",
    "wof:placetype":"venue"
},
  "geometry": {"coordinates":[2.35497,48.938454],"type":"Point"}
}