{
  "type": "Feature",
  "properties": {
    "addr:full":"rue Charles Boulle 19360 MALEMORT SUR CORREZE Limousin 19360",
    "addr:postcode":"19360;19360",
    "addr:street":"Rue Charles Boulle",
    "iso:country":"FR",
    "sg:address":"rue Charles Boulle 19360 MALEMORT SUR CORREZE",
    "sg:classifiers":[
        {
            "category":"Food & Beverages",
            "subcategory":"Bakery",
            "type":"Retail Goods"
        }
    ],
    "sg:phone":"+33 5 55 92 36 70",
    "sg:postcode":"19360",
    "sg:province":"Limousin",
    "sg:tags":[
        "long-keeping",
        "pastry"
    ],
    "wof:name":"Lachaise S.a.",
    "wof:placetype":"venue"
},
  "geometry": {"coordinates":[1.563173,45.164104],"type":"Point"}
}