{
  "type": "Feature",
  "properties": {
    "iso:country":"FR",
    "sg:address":"36, Rue de la Cerisaie, 51100 Reims",
    "sg:orig_category":"Non-Classified Establishments",
    "sg:phone":"+33 3 26 85 65 17",
    "sg:postcode":"51100",
    "sg:province":"Champagne",
    "wof:name":"A.f.r. La M\u00e9ridienne",
    "wof:placetype":"venue"
},
  "geometry": {"coordinates":[4.069086,49.227921],"type":"Point"}
}