{
  "type": "Feature",
  "properties": {
    "addr:full":"166, Av. Jean Lagarrique, 76530 Grand Couronne Haute Normandie",
    "addr:housenumber":"76530",
    "addr:street":"166 Av. Jean Lagarrique;Grand Couronne Haute Normandie",
    "iso:country":"FR",
    "sg:address":"166, Av. Jean Lagarrique, 76530 Grand Couronne",
    "sg:orig_category":"Unclassifiable Establishments",
    "sg:phone":"+33 2 35 67 62 62",
    "sg:province":"Haute Normandie",
    "wof:name":"Ati - Qualiflex S.a.",
    "wof:placetype":"venue"
},
  "geometry": {"coordinates":[1.01728,49.342522],"type":"Point"}
}