{
  "type": "Feature",
  "properties": {
    "addr:full":"101 Rue Combattants Afn 36260 Reuilly Reuilly Centre 36260",
    "addr:housenumber":"101",
    "addr:postcode":"36260;36260",
    "addr:street":"Rue Combattants Afn",
    "iso:country":"FR",
    "sg:address":"101 Rue Combattants Afn 36260 Reuilly",
    "sg:city":"Reuilly",
    "sg:classifiers":[
        {
            "category":"Professional",
            "type":"Services"
        }
    ],
    "sg:phone":"+33 2 54 49 22 50",
    "sg:postcode":"36260",
    "sg:province":"Centre",
    "sg:tags":[
        "transport",
        "road"
    ],
    "wof:name":"Van De Walle Pierre Sa",
    "wof:placetype":"venue"
},
  "geometry": {"coordinates":[2.029824,47.082237],"type":"Point"}
}