{
  "type": "Feature",
  "properties": {
    "addr:full":"63 Grand Rue 68240 Freland Fr\u00e9land Alsace 68240",
    "addr:housenumber":"63",
    "addr:postcode":"68240;68240",
    "addr:street":"Grand Rue",
    "iso:country":"FR",
    "sg:address":"63 Grand Rue 68240 Freland",
    "sg:city":"Fr\u00e9land",
    "sg:classifiers":[
        {
            "category":"Wholesale",
            "subcategory":"Auto Parts",
            "type":"Manufacturing & Wholesale Goods"
        }
    ],
    "sg:phone":"+33 3 89 71 92 78",
    "sg:postcode":"68240",
    "sg:province":"Alsace",
    "sg:tags":[
        "wheel",
        "car",
        "alloy",
        "rims"
    ],
    "wof:name":"A.m.m. Sa",
    "wof:placetype":"venue"
},
  "geometry": {"coordinates":[7.19224,48.171509],"type":"Point"}
}