{
  "type": "Feature",
  "properties": {
    "addr:full":"Rte d'Esbarres - Zone Industrielle Brazey en Plaine Bourgogne 21470",
    "addr:postcode":"21470",
    "addr:street":"Rte D'Esbarres Zone Industrielle Brazey En Plaine Bourgogne",
    "iso:country":"FR",
    "sg:address":"Rte d'Esbarres - Zone Industrielle",
    "sg:city":"Brazey en Plaine",
    "sg:orig_category":"Unclassifiable Establishments",
    "sg:phone":"+33 3 80 29 91 40",
    "sg:postcode":"21470",
    "sg:province":"Bourgogne",
    "wof:name":"C.i.t.m.s. S.a.",
    "wof:placetype":"venue"
},
  "geometry": {"coordinates":[5.21622,47.132481],"type":"Point"}
}