{
  "type": "Feature",
  "properties": {
    "addr:full":"Za 73800 Les Marches Rhone-Alpes 73800",
    "addr:postcode":"73800;73800",
    "addr:street":"Za",
    "iso:country":"FR",
    "sg:address":"Za 73800 Les Marches",
    "sg:classifiers":[
        {
            "category":"Food Court",
            "type":"Food & Drink"
        }
    ],
    "sg:phone":"+33 4 79 28 11 45",
    "sg:postcode":"73800",
    "sg:province":"Rhone-Alpes",
    "sg:tags":[
        "product",
        "related"
    ],
    "wof:name":"Caves Jean Perrier Et Fils Sa",
    "wof:placetype":"venue"
},
  "geometry": {"coordinates":[6.038695,45.448456],"type":"Point"}
}