{
  "type": "Feature",
  "properties": {
    "iso:country":"FR",
    "sg:address":"123 Parc D'Activit\u00e9 De L'Argile 2 Voie K 06370 Mouans Sartoux",
    "sg:classifiers":[
        {
            "category":"Manufacturing",
            "subcategory":"Paper Products",
            "type":"Manufacturing & Wholesale Goods"
        }
    ],
    "sg:phone":"+33 4 92 92 14 91",
    "sg:province":"Provence-Alpes-C\u00f4te d'Azur",
    "sg:tags":[
        "finished",
        "cardboard",
        "-"
    ],
    "wof:name":"Gravic-roll",
    "wof:placetype":"venue"
},
  "geometry": {"coordinates":[6.951678,43.610916],"type":"Point"}
}