{
  "type": "Feature",
  "properties": {
    "iso:country":"FR",
    "sg:address":"69 route de Saint Omer 59670 Cassel",
    "sg:orig_category":"Bolts, Galvanized",
    "sg:phone":"+33 3 28 42 93 13",
    "sg:postcode":"59670",
    "sg:province":"Nord Pas-de-Calais",
    "wof:name":"Cathelain Sa",
    "wof:placetype":"venue"
},
  "geometry": {"coordinates":[2.46686,50.800022],"type":"Point"}
}