{
  "type": "Feature",
  "properties": {
    "iso:country":"FR",
    "sg:address":"2, Rte de Glisy, 80440 Boves",
    "sg:orig_category":"Unclassifiable Establishments",
    "sg:phone":"+33 3 22 35 34 20",
    "sg:province":"Picardie",
    "wof:name":"Sogex S.a. - Soci\u00e9t\u00e9 G\u00e9n\u00e9rale D'extrusion",
    "wof:placetype":"venue"
},
  "geometry": {"coordinates":[2.397098,49.84996],"type":"Point"}
}