{
  "type": "Feature",
  "properties": {
    "addr:full":"134 Chemin De La Pertuade 83140 Six Fours Les Plages Midi Pyr\u00e9n\u00e9es",
    "addr:housenumber":"134",
    "addr:postcode":"83140",
    "addr:street":"Chemin De La Pertuade;Fours Les Plages",
    "iso:country":"FR",
    "sg:address":"134 Chemin De La Pertuade 83140 Six Fours Les Plages",
    "sg:classifiers":[
        {
            "category":"Shopping",
            "type":"Retail Goods"
        }
    ],
    "sg:phone":"+33 4 94 34 83 83",
    "sg:province":"Midi Pyr\u00e9n\u00e9es",
    "sg:tags":[
        "metallurgy",
        "finished",
        "-",
        "metalworking",
        "metallic"
    ],
    "wof:name":"Entrepose Navibord",
    "wof:placetype":"venue"
},
  "geometry": {"coordinates":[5.837306,43.109089],"type":"Point"}
}