{
  "type": "Feature",
  "properties": {
    "addr:full":"47, Rue du Port de l'Homme, 33360 Latresne Latresne Aquitaine 33360",
    "addr:housenumber":"47",
    "addr:postcode":"33360;33360",
    "addr:street":"Rue Du Port De L'Homme",
    "iso:country":"FR",
    "sg:address":"47, Rue du Port de l'Homme, 33360 Latresne",
    "sg:city":"Latresne",
    "sg:orig_category":"Non-Classified Establishments",
    "sg:phone":"+33 5 57 97 00 75",
    "sg:postcode":"33360",
    "sg:province":"Aquitaine",
    "wof:name":"Fillon Fauconnet S.a.",
    "wof:placetype":"venue"
},
  "geometry": {"coordinates":[-0.4964,44.784229],"type":"Point"}
}