{
  "type": "Feature",
  "properties": {
    "iso:country":"FR",
    "sg:address":"47, Rue du Port de l'Homme, 33360 Latresne",
    "sg:city":"Latresne",
    "sg:orig_category":"Non-Classified Establishments",
    "sg:phone":"+33 5 57 97 00 75",
    "sg:postcode":"33360",
    "sg:province":"Aquitaine",
    "wof:name":"Fillon Fauconnet S.a.",
    "wof:placetype":"venue"
},
  "geometry": {"coordinates":[-0.4964,44.784229],"type":"Point"}
}