{
  "type": "Feature",
  "properties": {
    "iso:country":"FR",
    "sg:address":"B.P. Centra 407, 94616 Rungis C\u00e9dex^^40, Rue du S\u00e9minaire, 94550 Chevilly Larue",
    "sg:orig_category":"Non-Classified Establishments",
    "sg:phone":"+33 1 46 87 25 08",
    "sg:province":"Ile de France",
    "wof:name":"Hubco S.a.",
    "wof:placetype":"venue"
},
  "geometry": {"coordinates":[2.35062,48.770672],"type":"Point"}
}