{
  "type": "Feature",
  "properties": {
    "iso:country":"FR",
    "sg:address":"ZI",
    "sg:city":"Boussac",
    "sg:orig_category":"Unclassifiable Establishments",
    "sg:phone":"+33 5 55 82 70 00",
    "sg:postcode":"23600",
    "sg:province":"Limousin",
    "wof:name":"Gibard S.a.",
    "wof:placetype":"venue"
},
  "geometry": {"coordinates":[2.248463,46.271877],"type":"Point"}
}