{
  "type": "Feature",
  "properties": {
    "iso:country":"FR",
    "sg:address":"38, Rue de Li\u00e8ge, 75008 Paris",
    "sg:orig_category":"Non-Classified Establishments",
    "sg:phone":"+33 1 44 69 44 25",
    "sg:province":"Ile de France",
    "wof:name":"Par S On France S.a.",
    "wof:placetype":"venue"
},
  "geometry": {"coordinates":[2.324298,48.879307],"type":"Point"}
}