{
  "type": "Feature",
  "properties": {
    "addr:full":"43 Rue Adolphe Thiers 62200 Boulogne Sur Mer Nord Pas-de-Calais 62200",
    "addr:housenumber":"43",
    "addr:postcode":"62200;62200",
    "addr:street":"Rue Adolphe Thiers;Sur Mer Nord",
    "iso:country":"FR",
    "sg:address":"43 Rue Adolphe Thiers 62200 Boulogne Sur Mer",
    "sg:classifiers":[
        {
            "category":"Food & Beverages",
            "subcategory":"Dairy",
            "type":"Retail Goods"
        }
    ],
    "sg:phone":"+33 3 21 31 94 74",
    "sg:postcode":"62200",
    "sg:province":"Nord Pas-de-Calais",
    "sg:tags":[
        "product",
        "related"
    ],
    "wof:name":"Philippe Olivier Sa",
    "wof:placetype":"venue"
},
  "geometry": {"coordinates":[1.605296,50.724026],"type":"Point"}
}