{
  "type": "Feature",
  "properties": {
    "iso:country":"FR",
    "sg:address":"chemin de Bellepeyre 13170 Les Pennes Mirabeau",
    "sg:orig_category":"Measuring Instruments, Mobile",
    "sg:phone":"+33 4 42 02 60 44",
    "sg:province":"Franche Comt\u00e9",
    "wof:name":"Concept Etude Realisation Systeme Automa S.a.r.l.",
    "wof:placetype":"venue"
},
  "geometry": {"coordinates":[5.332865,43.413269],"type":"Point"}
}