{
  "type": "Feature",
  "properties": {
    "iso:country":"FR",
    "sg:address":"5 All Des Quatre Lejeune Zac De Gourvily 29000 Quimper",
    "sg:city":"Quimper",
    "sg:classifiers":[
        {
            "category":"Manufacturing",
            "subcategory":"Glass & Minerals",
            "type":"Manufacturing & Wholesale Goods"
        }
    ],
    "sg:phone":"+33 2 98 64 10 10",
    "sg:postcode":"29000",
    "sg:province":"Bretagne",
    "sg:tags":[
        "building",
        "material"
    ],
    "wof:name":"Miroiteries De L'ouest Armorique",
    "wof:placetype":"venue"
},
  "geometry": {"coordinates":[-4.084568,48.016068],"type":"Point"}
}