{
  "type": "Feature",
  "properties": {
    "iso:country":"FR",
    "sg:address":"46, Sente du Pr\u00e9, 95320 Saint Leu la For\u00eat",
    "sg:orig_category":"Non-Classified Establishments",
    "sg:phone":"+33 1 39 95 07 03",
    "sg:postcode":"95320",
    "sg:province":"Ile de France",
    "wof:name":"C.e.a. S.a. - Compagnie Europ\u00e9enne D'ascenseurs",
    "wof:placetype":"venue"
},
  "geometry": {"coordinates":[2.246911,49.011173],"type":"Point"}
}