{
  "type": "Feature",
  "properties": {
    "addr:full":"7, Rue Teilhard de Chardin - ZI Metz deux Fontaine, 57000 Metz Lorraine",
    "addr:housenumber":"7",
    "addr:postcode":"57000",
    "addr:street":"Rue Teilhard De Chardin Zi;Fontaine",
    "iso:country":"FR",
    "sg:address":"7, Rue Teilhard de Chardin - ZI Metz deux Fontaine, 57000 Metz",
    "sg:orig_category":"Unclassifiable Establishments",
    "sg:phone":"+33 3 87 30 53 53",
    "sg:province":"Lorraine",
    "wof:name":"Manuloc S.a.",
    "wof:placetype":"venue"
},
  "geometry": {"coordinates":[6.183995,49.07645],"type":"Point"}
}