{
  "type": "Feature",
  "properties": {
    "addr:full":"Locmenven 29410 Guiclan Guiclan Bretagne 29410",
    "addr:postcode":"29410;29410",
    "addr:street":"Locmenven;Guiclan",
    "iso:country":"FR",
    "sg:address":"Locmenven 29410 Guiclan",
    "sg:city":"Guiclan",
    "sg:classifiers":[
        {
            "category":"Farming",
            "subcategory":"Livestock Farm",
            "type":"Manufacturing & Wholesale Goods"
        }
    ],
    "sg:phone":"+33 2 98 79 62 35",
    "sg:postcode":"29410",
    "sg:province":"Bretagne",
    "sg:tags":[
        "breeding",
        "agriculture",
        "animal"
    ],
    "wof:name":"Etablissement Tanguy",
    "wof:placetype":"venue"
},
  "geometry": {"coordinates":[-3.967484,48.530521],"type":"Point"}
}