{
  "type": "Feature",
  "properties": {
    "iso:country":"FR",
    "sg:address":"Avenue Jean Bonnefont 36100 Issoudun",
    "sg:city":"Issoudun",
    "sg:classifiers":[
        {
            "category":"Professional",
            "subcategory":"Engineering",
            "type":"Services"
        }
    ],
    "sg:phone":"+33 2 54 21 41 03",
    "sg:postcode":"36100",
    "sg:province":"Centre",
    "sg:tags":[
        "machine",
        "-",
        "mechanical"
    ],
    "wof:name":"Mtp Industries Sa",
    "wof:placetype":"venue"
},
  "geometry": {"coordinates":[1.993595,46.955082],"type":"Point"}
}