{
  "type": "Feature",
  "properties": {
    "addr:full":"15, R.N. Aubonne, 74140 Douvaine Rhone-Alpes 74140",
    "addr:housenumber":"15",
    "addr:postcode":"74140;74140",
    "addr:street":"R.N. Aubonne",
    "iso:country":"FR",
    "sg:address":"15, R.N. Aubonne, 74140 Douvaine",
    "sg:orig_category":"Unclassifiable Establishments",
    "sg:phone":"+33 4 50 94 01 46",
    "sg:postcode":"74140",
    "sg:province":"Rhone-Alpes",
    "wof:name":"Dumont Fr\u00e8res S.a.",
    "wof:placetype":"venue"
},
  "geometry": {"coordinates":[6.314533,46.228855],"type":"Point"}
}