{
  "type": "Feature",
  "properties": {
    "iso:country":"FR",
    "sg:address":"Rue Gustave Eiffel",
    "sg:city":"Tournan en Brie",
    "sg:orig_category":"Unclassifiable Establishments",
    "sg:phone":"+33 1 64 42 54 43",
    "sg:postcode":"77220",
    "sg:province":"Ile de France",
    "wof:name":"Liebherr-france",
    "wof:placetype":"venue"
},
  "geometry": {"coordinates":[2.776505,48.736198],"type":"Point"}
}