{
  "type": "Feature",
  "properties": {
    "addr:full":"56, Rue Cl\u00e9menceau, 54640 Tucquegnieux Lorraine",
    "addr:housenumber":"56",
    "addr:postcode":"54640",
    "addr:street":"Rue Cle\u0301Menceau",
    "iso:country":"FR",
    "sg:address":"56, Rue Cl\u00e9menceau, 54640 Tucquegnieux",
    "sg:orig_category":"Unclassifiable Establishments",
    "sg:phone":"+33 3 82 21 36 05",
    "sg:province":"Lorraine",
    "wof:name":"Savia S.a.r.l.",
    "wof:placetype":"venue"
},
  "geometry": {"coordinates":[5.903167,49.312984],"type":"Point"}
}