{
  "type": "Feature",
  "properties": {
    "addr:full":"2 Rue De Pitoys Les Arches N 4 Maignon 64600 Anglet Anglet Aquitaine 64600",
    "addr:housenumber":"2;4",
    "addr:postcode":"64600;64600",
    "addr:street":"Rue De Pitoys Les;N;Maignon",
    "iso:country":"FR",
    "sg:address":"2 Rue De Pitoys Les Arches N 4 Maignon 64600 Anglet",
    "sg:city":"Anglet",
    "sg:classifiers":[
        {
            "category":"Wholesale",
            "subcategory":"Medical Equipment & Supplies",
            "type":"Manufacturing & Wholesale Goods"
        }
    ],
    "sg:phone":"+33 5 59 31 42 84",
    "sg:postcode":"64600",
    "sg:province":"Aquitaine",
    "sg:tags":[
        "instrument",
        "health",
        "-",
        "precision"
    ],
    "wof:name":"Ortho Dynamic Sarl",
    "wof:placetype":"venue"
},
  "geometry": {"coordinates":[-1.514707,43.481705],"type":"Point"}
}