{
  "type": "Feature",
  "properties": {
    "addr:full":"ZI Ch\u00e2teau Renard Centre 45220",
    "addr:postcode":"45220",
    "iso:country":"FR",
    "sg:address":"ZI",
    "sg:city":"Ch\u00e2teau Renard",
    "sg:orig_category":"Non-Classified Establishments",
    "sg:phone":"+33 2 38 95 23 82",
    "sg:postcode":"45220",
    "sg:province":"Centre",
    "wof:name":"S.n.f.c. S.a.r.l.",
    "wof:placetype":"venue"
},
  "geometry": {"coordinates":[-84.520218,39.147369],"type":"Point"}
}