{
  "type": "Feature",
  "properties": {
    "addr:full":"Le Bourg 63250 Viscomtat Viscomtat Auvergne 63250",
    "addr:postcode":"63250;viscomtat;63250",
    "addr:street":"Le Bourg",
    "iso:country":"FR",
    "sg:address":"Le Bourg 63250 Viscomtat",
    "sg:city":"Viscomtat",
    "sg:orig_category":"Miscellaneous Products",
    "sg:phone":"+33 4 73 51 91 91",
    "sg:postcode":"63250",
    "sg:province":"Auvergne",
    "wof:name":"Dubost Colas Pradel Sarl",
    "wof:placetype":"venue"
},
  "geometry": {"coordinates":[3.704752,45.82304],"type":"Point"}
}