{
  "type": "Feature",
  "properties": {
    "iso:country":"FR",
    "sg:address":"Av. Albert Einstein",
    "sg:city":"Montpellier",
    "sg:orig_category":"Unclassifiable Establishments",
    "sg:phone":"+33 4 67 15 76 10",
    "sg:postcode":"34000",
    "sg:province":"Languedoc-Roussillon",
    "wof:name":"S.p.i. Infra S.a.",
    "wof:placetype":"venue"
},
  "geometry": {"coordinates":[3.918,43.611046],"type":"Point"}
}