{
  "type": "Feature",
  "properties": {
    "iso:country":"FR",
    "sg:address":"ZA des Vigneaux",
    "sg:city":"Chabris",
    "sg:orig_category":"Non-Classified Establishments",
    "sg:phone":"+33 2 54 40 00 60",
    "sg:postcode":"36210",
    "sg:province":"Centre",
    "wof:name":"Lebert Paysage Environnement S.a.r.l.",
    "wof:placetype":"venue"
},
  "geometry": {"coordinates":[1.653815,47.254814],"type":"Point"}
}