{
  "type": "Feature",
  "properties": {
    "iso:country":"FR",
    "sg:address":"Rue du Presbyt\u00e8re",
    "sg:city":"Seyches",
    "sg:orig_category":"Unclassifiable Establishments",
    "sg:phone":"+33 5 53 83 75 30",
    "sg:postcode":"47350",
    "sg:province":"Aquitaine",
    "wof:name":"A.e.i.m.s.a.r.l.",
    "wof:placetype":"venue"
},
  "geometry": {"coordinates":[0.30672,44.550724],"type":"Point"}
}