{
  "type": "Feature",
  "properties": {
    "iso:country":"FR",
    "sg:address":"16, Rue Pasteur, 94450 Limeil Br\u00e9vannes",
    "sg:orig_category":"Unclassifiable Establishments",
    "sg:phone":"+33 1 56 73 21 00",
    "sg:province":"Ile de France",
    "wof:name":"Quillery Environnement Urbain S.n.c.",
    "wof:placetype":"venue"
},
  "geometry": {"coordinates":[2.477141,48.745277],"type":"Point"}
}