{
  "type": "Feature",
  "properties": {
    "addr:full":"390, Rue Claude Nicolas Ledoux, 13854 Aix en Provence C\u00e9dex 03 Nord Pas-de-Calais",
    "addr:housenumber":"390;03",
    "addr:postcode":"13854",
    "addr:street":"Rue Claude Nicolas Ledoux;Ce\u0301Dex",
    "iso:country":"FR",
    "sg:address":"390, Rue Claude Nicolas Ledoux, 13854 Aix en Provence C\u00e9dex 03",
    "sg:orig_category":"Non-Classified Establishments",
    "sg:phone":"+33 4 42 97 96 00",
    "sg:province":"Nord Pas-de-Calais",
    "wof:name":"Azur Conception S.a.",
    "wof:placetype":"venue"
},
  "geometry": {"coordinates":[5.387038,43.48119],"type":"Point"}
}