{
  "type": "Feature",
  "properties": {
    "iso:country":"FR",
    "sg:address":"2, Place de la Lib\u00e9ration, 93380 Pierrefitte sur Seine",
    "sg:orig_category":"Unclassifiable Establishments",
    "sg:phone":"+33 1 48 26 57 10",
    "sg:province":"Ile de France",
    "wof:name":"Agica S.a.r.l.",
    "wof:placetype":"venue"
},
  "geometry": {"coordinates":[2.360269,48.964005],"type":"Point"}
}