{
  "type": "Feature",
  "properties": {
    "addr:full":"2/4, Rue Jean Baptiste Huet, 78350 Jouy en Josas Ile de France",
    "addr:housenumber":"2 / 4",
    "addr:postcode":"78350",
    "addr:street":"Rue Jean Baptiste Huet",
    "iso:country":"FR",
    "sg:address":"2/4, Rue Jean Baptiste Huet, 78350 Jouy en Josas",
    "sg:orig_category":"Unclassifiable Establishments",
    "sg:phone":"+33 1 34 88 50 90",
    "sg:province":"Ile de France",
    "wof:name":"Prisme S.a.",
    "wof:placetype":"venue"
},
  "geometry": {"coordinates":[2.16847,48.780697],"type":"Point"}
}