{
  "type": "Feature",
  "properties": {
    "iso:country":"FR",
    "sg:address":"44 rue Louis Barthou; Pau; 64000",
    "sg:city":"Pau",
    "sg:classifiers":[
        {
            "category":"Banks & Credit Unions",
            "subcategory":"Bank",
            "type":"Services"
        }
    ],
    "sg:phone":"+33 3359277700",
    "sg:postcode":"64000",
    "sg:province":"Aquitaine",
    "wof:name":"Banque Courtois Sa",
    "wof:placetype":"venue"
},
  "geometry": {"coordinates":[-0.370272,43.294632],"type":"Point"}
}