{
  "type": "Feature",
  "properties": {
    "iso:country":"FR",
    "sg:address":"1, Chemin du Moulin de la Ram\u00e9e, 44550 Montoir de Bretagne",
    "sg:orig_category":"Non-Classified Establishments",
    "sg:phone":"+33 2 40 45 44 44",
    "sg:province":"Pays de Loire",
    "wof:name":"S.n.a.b. S.a.r.l. - Soci\u00e9t\u00e9 Nouvelle Des Ateliers Du Brivet",
    "wof:placetype":"venue"
},
  "geometry": {"coordinates":[-2.177519,47.308414],"type":"Point"}
}