{
  "type": "Feature",
  "properties": {
    "iso:country":"FR",
    "sg:address":"6, Rte de Colmar, 67600 S\u00e9lestat",
    "sg:city":"S\u00e9lestat",
    "sg:orig_category":"Unclassifiable Establishments",
    "sg:phone":"+33 3 88 58 05 80",
    "sg:postcode":"67600",
    "sg:province":"Alsace",
    "wof:name":"Dromson S.a.",
    "wof:placetype":"venue"
},
  "geometry": {"coordinates":[7.444347,48.258209],"type":"Point"}
}