{
  "type": "Feature",
  "properties": {
    "addr:full":"B.P. 99, 61303 L'Aigle C\u00e9dex^^1, Rte de Crislai, 61300 L'Aigle Chandai Basse Normandie 61300",
    "addr:postcode":"61303;61300;61300",
    "addr:street":"B.P. 99;Rte De Crislai",
    "iso:country":"FR",
    "sg:address":"B.P. 99, 61303 L'Aigle C\u00e9dex^^1, Rte de Crislai, 61300 L'Aigle",
    "sg:city":"Chandai",
    "sg:orig_category":"Non-Classified Establishments",
    "sg:phone":"+33 2 33 84 34 00",
    "sg:postcode":"61300",
    "sg:province":"Basse Normandie",
    "wof:name":"Usiphar S.a.",
    "wof:placetype":"venue"
},
  "geometry": {"coordinates":[0.738917,48.751774],"type":"Point"}
}