{
  "type": "Feature",
  "properties": {
    "iso:country":"FR",
    "sg:address":"92 Rue Des Alpes 26000 Valence",
    "sg:classifiers":[
        {
            "category":"Shopping",
            "subcategory":"Clothing, Apparel, & Fashions",
            "type":"Retail Goods"
        }
    ],
    "sg:phone":"+33 4 75 43 30 21",
    "sg:postcode":"26000",
    "sg:province":"Rhone-Alpes",
    "sg:tags":[
        "textile",
        "clothing",
        "clothes"
    ],
    "wof:name":"Euromaille Sarl",
    "wof:placetype":"venue"
},
  "geometry": {"coordinates":[4.900101,44.926739],"type":"Point"}
}