{
  "type": "Feature",
  "properties": {
    "addr:full":"21 R Du Pr\u00e9sident Poincar\u00e9 59140 Dunkerque Nord Pas-de-Calais 59140",
    "addr:housenumber":"21",
    "addr:postcode":"59140;59140",
    "addr:street":"R Du Pre\u0301Sident Poincare\u0301",
    "iso:country":"FR",
    "sg:address":"21 R Du Pr\u00e9sident Poincar\u00e9 59140 Dunkerque",
    "sg:classifiers":[
        {
            "category":"Wholesale",
            "subcategory":"Meat",
            "type":"Manufacturing & Wholesale Goods"
        }
    ],
    "sg:phone":"+33 3 28 66 91 47",
    "sg:postcode":"59140",
    "sg:province":"Nord Pas-de-Calais",
    "sg:tags":[
        "food",
        "cooked",
        "product",
        "related"
    ],
    "wof:name":"Boucherie Jean Bart",
    "wof:placetype":"venue"
},
  "geometry": {"coordinates":[2.379118,51.035332],"type":"Point"}
}