{
  "type": "Feature",
  "properties": {
    "addr:full":"Zi Borde Rouge 82200 Moissac Midi Pyr\u00e9n\u00e9es 82200",
    "addr:postcode":"82200;82200",
    "addr:street":"Zi Borde Rouge",
    "iso:country":"FR",
    "sg:address":"Zi Borde Rouge 82200 Moissac",
    "sg:classifiers":[
        {
            "category":"Farming",
            "subcategory":"Crops",
            "type":"Manufacturing & Wholesale Goods"
        }
    ],
    "sg:phone":"+33 5 63 04 15 64",
    "sg:postcode":"82200",
    "sg:province":"Midi Pyr\u00e9n\u00e9es",
    "sg:tags":[
        "vegetable",
        "fruit",
        "agriculture",
        "livestock"
    ],
    "wof:name":"Boyer Sa",
    "wof:placetype":"venue"
},
  "geometry": {"coordinates":[1.08214,44.103298],"type":"Point"}
}