{
  "type": "Feature",
  "properties": {
    "iso:country":"FR",
    "sg:address":"Allee Des Ingenieurs Actimart 3 Pa Les Milles 13851 Aix En Provence",
    "sg:classifiers":[
        {
            "category":"Government",
            "subcategory":"Fire Station",
            "type":"Public Place"
        }
    ],
    "sg:phone":"+33 4 42 39 79 41",
    "sg:province":"Nord Pas-de-Calais",
    "sg:tags":[
        "electric",
        "electricity",
        "component",
        "equipment",
        "lighting",
        "electrical",
        "electronic"
    ],
    "wof:name":"Cge Distribution",
    "wof:placetype":"venue"
},
  "geometry": {"coordinates":[5.44625,43.526409],"type":"Point"}
}