{
  "type": "Feature",
  "properties": {
    "addr:full":"3, Av. Edouard Herriot, 69400 Limas Rhone-Alpes",
    "addr:postcode":"69400",
    "addr:street":"Av. Edouard Herriot",
    "iso:country":"FR",
    "sg:address":"3, Av. Edouard Herriot, 69400 Limas",
    "sg:orig_category":"Unclassifiable Establishments",
    "sg:phone":"+33 4 74 09 40 80",
    "sg:province":"Rhone-Alpes",
    "wof:name":"Vildis Aldis Sud Est Deux S.a.",
    "wof:placetype":"venue"
},
  "geometry": {"coordinates":[4.7249,45.978291],"type":"Point"}
}