{
  "type": "Feature",
  "properties": {
    "iso:country":"FR",
    "sg:address":"B.P. 202, 73276 Albertville^^356, Chemin des Bauges, 73200 Gilly sur Is\u00e8re",
    "sg:orig_category":"Non-Classified Establishments",
    "sg:phone":"+33 4 79 37 82 45",
    "sg:postcode":"73200",
    "sg:province":"Rhone-Alpes",
    "wof:name":"Art",
    "wof:placetype":"venue"
},
  "geometry": {"coordinates":[6.359874,45.63168],"type":"Point"}
}