{
  "type": "Feature",
  "properties": {
    "iso:country":"FR",
    "sg:address":"B.P. 19",
    "sg:city":"Tr\u00e9flaou\u00e9nan",
    "sg:orig_category":"Non-Classified Establishments",
    "sg:phone":"+33 2 98 29 53 65",
    "sg:postcode":"29440",
    "sg:province":"Bretagne",
    "wof:name":"Hygiadis S.a.",
    "wof:placetype":"venue"
},
  "geometry": {"coordinates":[-4.182647,48.547588],"type":"Point"}
}