{
  "type": "Feature",
  "properties": {
    "addr:full":"B.P. 119, 91144 Les Ulis C\u00e9dex^^9, Av. de Scandinavie - ZI de Courtaboeuf, 91140 Villebon sur Yvette Ile de France",
    "addr:housenumber":"b.p. 119",
    "addr:postcode":"91144;91140",
    "addr:street":"Av. De Scandinavie Zi De Courtaboeuf",
    "iso:country":"FR",
    "sg:address":"B.P. 119, 91144 Les Ulis C\u00e9dex^^9, Av. de Scandinavie - ZI de Courtaboeuf, 91140 Villebon sur Yvette",
    "sg:orig_category":"Non-Classified Establishments",
    "sg:phone":"+33 1 69 18 81 90",
    "sg:province":"Ile de France",
    "wof:name":"Supra S.a.",
    "wof:placetype":"venue"
},
  "geometry": {"coordinates":[2.227225,48.700069],"type":"Point"}
}