{
  "type": "Feature",
  "properties": {
    "iso:country":"FR",
    "sg:address":"Rn 7 BP 95 84130 Le Pontet",
    "sg:city":"Le Pontet",
    "sg:classifiers":[
        {
            "category":"Professional",
            "subcategory":"Engineering",
            "type":"Services"
        }
    ],
    "sg:phone":"+33 4 90 32 90 30",
    "sg:postcode":"73110",
    "sg:province":"Rhone-Alpes",
    "sg:tags":[
        "machine",
        "-",
        "mechanical"
    ],
    "wof:name":"Groupement Petrolier Du Pontet",
    "wof:placetype":"venue"
},
  "geometry": {"coordinates":[4.859935,43.96188],"type":"Point"}
}