{
  "type": "Feature",
  "properties": {
    "iso:country":"FR",
    "sg:address":"9 cours Mar\u00e9chal Leclerc; Leognan; 33850",
    "sg:city":"L\u00e9ognan",
    "sg:classifiers":[
        {
            "category":"Banks & Credit Unions",
            "subcategory":"Bank",
            "type":"Services"
        }
    ],
    "sg:phone":"+33 5 56 64 76 76",
    "sg:postcode":"33850",
    "sg:province":"Aquitaine",
    "wof:name":"Soci\u00e9t\u00e9 Bordelaise Cic",
    "wof:placetype":"venue"
},
  "geometry": {"coordinates":[-0.600948,44.728771],"type":"Point"}
}