{
  "type": "Feature",
  "properties": {
    "iso:country":"FR",
    "sg:address":"Combe De Veyle Nord 01750 Replonges",
    "sg:classifiers":[
        {
            "category":"Professional",
            "type":"Services"
        }
    ],
    "sg:phone":"+33 3 85 31 10 61",
    "sg:province":"Picardie",
    "sg:tags":[
        "transport",
        "road"
    ],
    "wof:name":"Ste Demenagement Prudent Sarl",
    "wof:placetype":"venue"
},
  "geometry": {"coordinates":[4.86986,46.293884],"type":"Point"}
}