{
  "type": "Feature",
  "properties": {
    "iso:country":"FR",
    "sg:address":"Zi 62575 Blendecques",
    "sg:classifiers":[
        {
            "category":"Shopping",
            "type":"Retail Goods"
        }
    ],
    "sg:phone":"+33 3 21 98 77 44",
    "sg:postcode":"62575",
    "sg:province":"Nord Pas-de-Calais",
    "sg:tags":[
        "metallurgy",
        "finished",
        "-",
        "metalworking",
        "metallic"
    ],
    "wof:name":"Cfc (cie Francaise De Chaudronnerie)",
    "wof:placetype":"venue"
},
  "geometry": {"coordinates":[2.27307,50.715118],"type":"Point"}
}