{
  "type": "Feature",
  "properties": {
    "iso:country":"FR",
    "sg:address":"92, Rue des Ors, 79000 Niort",
    "sg:orig_category":"Non-Classified Establishments",
    "sg:phone":"+33 5 49 24 16 17",
    "sg:province":"Poitou-Charentes",
    "wof:name":"Finergie S.a.",
    "wof:placetype":"venue"
},
  "geometry": {"coordinates":[-0.420739,46.330929],"type":"Point"}
}