{
  "type": "Feature",
  "properties": {
    "iso:country":"FR",
    "sg:address":"62 Rue Du Grand Perne Au Vieux Soldat 59560 Comines",
    "sg:classifiers":[
        {
            "category":"Farming",
            "subcategory":"Crops",
            "type":"Manufacturing & Wholesale Goods"
        }
    ],
    "sg:phone":"+33 3 20 39 84 82",
    "sg:postcode":"59560",
    "sg:province":"Nord Pas-de-Calais",
    "sg:tags":[
        "vegetable",
        "fruit",
        "agriculture",
        "livestock"
    ],
    "wof:name":"Sarl Cinq Ge",
    "wof:placetype":"venue"
},
  "geometry": {"coordinates":[3.019316,50.730637],"type":"Point"}
}