{
  "type": "Feature",
  "properties": {
    "addr:full":"B.P. 107, 59416 Anzin C\u00e9dex^^76, Rue Jean Jaur\u00e8s, 59410 Anzin Nord Pas-de-Calais",
    "addr:housenumber":"b.p. 107",
    "addr:postcode":"59416;59410",
    "addr:street":"Rue Jean Jaure\u0300S",
    "iso:country":"FR",
    "sg:address":"B.P. 107, 59416 Anzin C\u00e9dex^^76, Rue Jean Jaur\u00e8s, 59410 Anzin",
    "sg:orig_category":"Non-Classified Establishments",
    "sg:phone":"+33 3 27 45 35 00",
    "sg:province":"Nord Pas-de-Calais",
    "wof:name":"Famacom S.a.",
    "wof:placetype":"venue"
},
  "geometry": {"coordinates":[3.503465,50.370636],"type":"Point"}
}