{
  "type": "Feature",
  "properties": {
    "addr:full":"95, Rue des Grives, 38920 Crolles Crolles Rhone-Alpes 38190",
    "addr:housenumber":"95",
    "addr:postcode":"38920;38190",
    "addr:street":"Rue Des Grives",
    "iso:country":"FR",
    "sg:address":"95, Rue des Grives, 38920 Crolles",
    "sg:city":"Crolles",
    "sg:orig_category":"Unclassifiable Establishments",
    "sg:phone":"+33 4 76 92 07 00",
    "sg:postcode":"38190",
    "sg:province":"Rhone-Alpes",
    "wof:name":"Catalcad S.a.r.l.",
    "wof:placetype":"venue"
},
  "geometry": {"coordinates":[5.89174,45.272163],"type":"Point"}
}