{
  "type": "Feature",
  "properties": {
    "addr:full":"Rte des Saintiers - ZAE les Grands Pr\u00e9s Sevrier Rhone-Alpes 74320",
    "addr:postcode":"74320",
    "addr:street":"Rte Des Saintiers Zae Les",
    "iso:country":"FR",
    "sg:address":"Rte des Saintiers - ZAE les Grands Pr\u00e9s",
    "sg:city":"Sevrier",
    "sg:orig_category":"Unclassifiable Establishments",
    "sg:phone":"+33 4 50 52 47 91",
    "sg:postcode":"74320",
    "sg:province":"Rhone-Alpes",
    "wof:name":"D. N. L. S.a.r.l. - Diffusion National Du Livre",
    "wof:placetype":"venue"
},
  "geometry": {"coordinates":[6.14032,45.86393],"type":"Point"}
}