{
  "type": "Feature",
  "properties": {
    "iso:country":"FR",
    "sg:address":"B.P. 1003, 68050 Mulhouse C\u00e9dex^^2, Rue de Bretagne, 68390 Sausheim",
    "sg:city":"Sausheim",
    "sg:orig_category":"Non-Classified Establishments",
    "sg:phone":"+33 3 89 61 99 00",
    "sg:postcode":"68390",
    "sg:province":"Alsace",
    "wof:name":"S.m.e.b. S.a. - Soci\u00e9t\u00e9 De Maintenance Et D'equipements Bureautique",
    "wof:placetype":"venue"
},
  "geometry": {"coordinates":[7.369807,47.788521],"type":"Point"}
}