{
  "type": "Feature",
  "properties": {
    "iso:country":"FR",
    "sg:address":"6, Impasse du Levant, 45390 La Neuville sur Essonne",
    "sg:city":"Aulnay-la-Rivi\u00e8re",
    "sg:orig_category":"Non-Classified Establishments",
    "sg:phone":"+33 2 38 34 28 28",
    "sg:postcode":"45390",
    "sg:province":"Centre",
    "wof:name":"S.c.m.m. Helinox S.a. - Soci\u00e9t\u00e9 De Construction M\u00e9tallique M\u00e9canique",
    "wof:placetype":"venue"
},
  "geometry": {"coordinates":[2.37678,48.187759],"type":"Point"}
}