{
  "type": "Feature",
  "properties": {
    "addr:full":"Boulevard Petite Mer 43770 Chadrac Chadrac Auvergne 43770",
    "addr:postcode":"43770;chadrac;43770",
    "addr:street":"Boulevard Petite Mer",
    "iso:country":"FR",
    "sg:address":"Boulevard Petite Mer 43770 Chadrac",
    "sg:city":"Chadrac",
    "sg:classifiers":[
        {
            "category":"Real Estate",
            "subcategory":"Surveying",
            "type":"Services"
        }
    ],
    "sg:phone":"+33 4 71 09 60 44",
    "sg:postcode":"43770",
    "sg:province":"Auvergne",
    "sg:tags":[
        "leather",
        "raw",
        "material",
        "-",
        "shoe"
    ],
    "wof:name":"Tanneries Du Puy Sa",
    "wof:placetype":"venue"
},
  "geometry": {"coordinates":[3.907278,45.064564],"type":"Point"}
}