{
  "type": "Feature",
  "properties": {
    "addr:full":"11, Rue Gaston Cornavin, 94200 Ivry sur Seine Ile de France",
    "addr:housenumber":"11",
    "addr:postcode":"94200",
    "addr:street":"Rue Gaston Cornavin",
    "iso:country":"FR",
    "sg:address":"11, Rue Gaston Cornavin, 94200 Ivry sur Seine",
    "sg:orig_category":"Unclassifiable Establishments",
    "sg:phone":"+33 1 49 60 12 99",
    "sg:province":"Ile de France",
    "wof:name":"Avenir Jardins S.a.r.l.",
    "wof:placetype":"venue"
},
  "geometry": {"coordinates":[2.381395,48.809826],"type":"Point"}
}