{
  "type": "Feature",
  "properties": {
    "addr:full":"170-174 Av Du Gal Sarrail 51000 Ch\u00e2lons-En-Champagne Champagne 51000",
    "addr:postcode":"51000;51000",
    "addr:street":"Av Du Gal Sarrail;Champagne",
    "iso:country":"FR",
    "sg:address":"170-174 Av Du Gal Sarrail 51000 Ch\u00e2lons-En-Champagne",
    "sg:classifiers":[
        {
            "category":"Autos & Motor Vehicles",
            "subcategory":"Automobile Sales",
            "type":"Retail Goods"
        }
    ],
    "sg:phone":"+33 3 26 21 46 46",
    "sg:postcode":"51000",
    "sg:province":"Champagne",
    "sg:tags":[
        "equipment",
        "motor-cars",
        "transport"
    ],
    "wof:name":"Garage Guyot Et Fils Sa",
    "wof:placetype":"venue"
},
  "geometry": {"coordinates":[4.360652,48.971947],"type":"Point"}
}