{
  "type": "Feature",
  "properties": {
    "addr:full":"Boulevard Pierre Lefaucheux - ZI Sud 72100 Le Mans Pays de Loire 72100",
    "addr:postcode":"72100;72100",
    "addr:street":"Boulevard Pierre Lefaucheux Zi Sud",
    "iso:country":"FR",
    "sg:address":"Boulevard Pierre Lefaucheux - ZI Sud 72100 Le Mans",
    "sg:classifiers":[
        {
            "category":"Utilities",
            "subcategory":"Electric",
            "type":"Services"
        }
    ],
    "sg:phone":"+33 2 43 61 45 45",
    "sg:postcode":"72100",
    "sg:province":"Pays de Loire",
    "sg:tags":[
        "automotive",
        "equipment"
    ],
    "wof:name":"Ckb - Carrier Kheops Bac S.a.",
    "wof:placetype":"venue"
},
  "geometry": {"coordinates":[4.29189,46.374798],"type":"Point"}
}