{
  "type": "Feature",
  "properties": {
    "iso:country":"FR",
    "sg:address":"34 Rue De Ruffi 13003 Marseille",
    "sg:classifiers":[
        {
            "category":"Transit Center",
            "subcategory":"Freight",
            "type":"Transportation"
        }
    ],
    "sg:phone":"+33 4 91 50 11 19",
    "sg:province":"Poitou-Charentes",
    "sg:tags":[
        "metallurgy",
        "pipe",
        "metalworking",
        "sheet"
    ],
    "wof:name":"Tcim Sn",
    "wof:placetype":"venue"
},
  "geometry": {"coordinates":[5.371905,43.311016],"type":"Point"}
}