{
  "type": "Feature",
  "properties": {
    "addr:full":"8 Villa Guizot 75017 Paris Ile de France 75017",
    "addr:housenumber":"8",
    "addr:postcode":"75017;75017",
    "addr:street":"Villa Guizot",
    "iso:country":"FR",
    "sg:address":"8 Villa Guizot 75017 Paris",
    "sg:classifiers":[
        {
            "category":"Professional",
            "subcategory":"Computer Services",
            "type":"Services"
        }
    ],
    "sg:phone":"+33 1 45 72 97 97",
    "sg:postcode":"75017",
    "sg:province":"Ile de France",
    "sg:tags":[
        "information",
        "technology",
        "software"
    ],
    "wof:name":"Topsys Sarl",
    "wof:placetype":"venue"
},
  "geometry": {"coordinates":[2.291321,48.877316],"type":"Point"}
}