{
  "type": "Feature",
  "properties": {
    "iso:country":"FR",
    "sg:address":"Zi La P\u00ealti\u00e8re 35130 Moutiers",
    "sg:city":"Moutiers",
    "sg:classifiers":[
        {
            "category":"Shopping",
            "subcategory":"Computers & Home Electronics",
            "type":"Retail Goods"
        }
    ],
    "sg:phone":"+33 2 99 96 12 12",
    "sg:postcode":"35130",
    "sg:province":"Bretagne",
    "sg:tags":[
        "equipment",
        "electrical",
        "component",
        "electric",
        "electronic"
    ],
    "wof:name":"Lithos Sa",
    "wof:placetype":"venue"
},
  "geometry": {"coordinates":[-1.212949,47.967243],"type":"Point"}
}