{
  "type": "Feature",
  "properties": {
    "iso:country":"FR",
    "sg:address":"39 Rue Jacquemart 26100 Romans Sur Is\u00e8re",
    "sg:classifiers":[
        {
            "category":"Bakery",
            "type":"Food & Drink"
        }
    ],
    "sg:phone":"+33 4 75 02 32 29",
    "sg:postcode":"26100",
    "sg:province":"Rhone-Alpes",
    "sg:tags":[
        "cake",
        "product",
        "related",
        "bread"
    ],
    "wof:name":"Patisserie Mourier",
    "wof:placetype":"venue"
},
  "geometry": {"coordinates":[5.048737,45.047001],"type":"Point"}
}