{
  "type": "Feature",
  "properties": {
    "addr:full":"4 Rue De La Fontaine 77114 Gouaix Ile de France",
    "addr:housenumber":"4",
    "addr:postcode":"77114",
    "addr:street":"Rue De La Fontaine;Ile De France",
    "iso:country":"FR",
    "sg:address":"4 Rue De La Fontaine 77114 Gouaix",
    "sg:classifiers":[
        {
            "category":"Manufacturing",
            "subcategory":"Rubber & Plastics",
            "type":"Manufacturing & Wholesale Goods"
        }
    ],
    "sg:phone":"+33 1 64 00 79 91",
    "sg:province":"Ile de France",
    "wof:name":"Gouaix Plastiques",
    "wof:placetype":"venue"
},
  "geometry": {"coordinates":[3.293873,48.488747],"type":"Point"}
}