{
  "type": "Feature",
  "properties": {
    "addr:full":"4 Av Windsor 06400 Cannes Midi Pyr\u00e9n\u00e9es",
    "addr:postcode":"06400",
    "addr:street":"Av Windsor",
    "iso:country":"FR",
    "sg:address":"4 Av Windsor 06400 Cannes",
    "sg:classifiers":[
        {
            "category":"Professional",
            "subcategory":"Business Services",
            "type":"Services"
        }
    ],
    "sg:phone":"+33 4 92 18 85 55",
    "sg:province":"Midi Pyr\u00e9n\u00e9es",
    "sg:tags":[
        "training",
        "advice"
    ],
    "wof:name":"Ogec Sainte Marie",
    "wof:placetype":"venue"
},
  "geometry": {"coordinates":[7.030495,43.552876],"type":"Point"}
}