{
  "type": "Feature",
  "properties": {
    "addr:full":"42 route d'Avignon 84300 Cavaillon Provence-Alpes-C\u00f4te d'Azur",
    "addr:housenumber":"42",
    "addr:postcode":"84300",
    "addr:street":"Route D'Avignon",
    "iso:country":"FR",
    "sg:address":"42 route d'Avignon 84300 Cavaillon",
    "sg:classifiers":[
        {
            "category":"Building & Trades",
            "subcategory":"Locksmith",
            "type":"Services"
        }
    ],
    "sg:phone":"+33 4 90 78 45 00",
    "sg:province":"Provence-Alpes-C\u00f4te d'Azur",
    "sg:tags":[
        "frozen",
        "transport",
        "refrigerated"
    ],
    "wof:name":"T.c. Sa",
    "wof:placetype":"venue"
},
  "geometry": {"coordinates":[5.04855,43.84869],"type":"Point"}
}