{
  "type": "Feature",
  "properties": {
    "addr:full":"94 Rue Lauriston 75116 Paris Rhone-Alpes",
    "addr:housenumber":"94",
    "addr:postcode":"75116",
    "addr:street":"Rue Lauriston",
    "iso:country":"FR",
    "sg:address":"94 Rue Lauriston 75116 Paris",
    "sg:classifiers":[
        {
            "category":"Autos & Motor Vehicles",
            "subcategory":"Automobile Sales",
            "type":"Retail Goods"
        }
    ],
    "sg:phone":"+33 1 44 05 33 97",
    "sg:province":"Rhone-Alpes",
    "sg:tags":[
        "equipment",
        "motor-cars",
        "transport"
    ],
    "wof:name":"Snac Bmw",
    "wof:placetype":"venue"
},
  "geometry": {"coordinates":[2.287328,48.867043],"type":"Point"}
}