{
  "type": "Feature",
  "properties": {
    "iso:country":"FR",
    "sg:address":"669 Chemin Du Littoral Anse Saumaty 13016 Marseille",
    "sg:classifiers":[
        {
            "category":"Airport",
            "type":"Transportation"
        }
    ],
    "sg:phone":"+33 4 91 03 50 50",
    "sg:province":"Rhone-Alpes",
    "sg:tags":[
        "transport",
        "air"
    ],
    "wof:name":"Ducros Euroexpress",
    "wof:placetype":"venue"
},
  "geometry": {"coordinates":[5.321475,43.362785],"type":"Point"}
}