{
  "type": "Feature",
  "properties": {
    "addr:full":"85 Rue Saint-Lazare Paris Ile de France 75009",
    "addr:housenumber":"85",
    "addr:postcode":"75009",
    "addr:street":"Rue Saint-Lazare",
    "iso:country":"FR",
    "sg:address":"85 Rue Saint-Lazare",
    "sg:city":"Paris",
    "sg:classifiers":[
        {
            "category":"Banks & Credit Unions",
            "subcategory":"Financial Services",
            "type":"Services"
        }
    ],
    "sg:phone":"+33 1 49 70 18 18",
    "sg:postcode":"75009",
    "sg:province":"Ile de France",
    "sg:tags":[
        "banking",
        "finance",
        "insurance"
    ],
    "wof:name":"Fortis",
    "wof:placetype":"venue"
},
  "geometry": {"coordinates":[2.330089,48.875847],"type":"Point"}
}