{
  "type": "Feature",
  "properties": {
    "addr:full":"B.P. 41, 49170 Saint Germain des Pr\u00e9s C\u00e9dex C^^Rte de Saint Augustin, 49170 Saint Germain des Pr\u00e9s Pays de Loire",
    "addr:postcode":"49170;49170",
    "addr:street":"B.P. 41;Germain Des Pre\u0301S Ce\u0301Dex;De Saint Augustin;Germain Des Pre\u0301S",
    "iso:country":"FR",
    "sg:address":"B.P. 41, 49170 Saint Germain des Pr\u00e9s C\u00e9dex C^^Rte de Saint Augustin, 49170 Saint Germain des Pr\u00e9s",
    "sg:orig_category":"Non-Classified Establishments",
    "sg:phone":"+33 2 41 39 98 80",
    "sg:province":"Pays de Loire",
    "wof:name":"Soci\u00e9t\u00e9 Germanoprataine De Poudres.a.r.l.",
    "wof:placetype":"venue"
},
  "geometry": {"coordinates":[-0.79533,47.459358],"type":"Point"}
}