{
  "type": "Feature",
  "properties": {
    "addr:full":"12 Cours Louis Lumiere 94306 Vincennes Cedex Midi Pyr\u00e9n\u00e9es",
    "addr:housenumber":"12",
    "addr:postcode":"94306",
    "addr:street":"Cours Louis Lumiere",
    "iso:country":"FR",
    "sg:address":"12 Cours Louis Lumiere 94306 Vincennes Cedex",
    "sg:classifiers":[
        {
            "category":"Food & Beverages",
            "subcategory":"Dairy",
            "type":"Retail Goods"
        }
    ],
    "sg:phone":"+33 1 41 93 88 00",
    "sg:province":"Midi Pyr\u00e9n\u00e9es",
    "sg:tags":[
        "product",
        "related"
    ],
    "wof:name":"Fromageries Bel",
    "wof:placetype":"venue"
},
  "geometry": {"coordinates":[2.428771,48.843552],"type":"Point"}
}