{
  "type": "Feature",
  "properties": {
    "iso:country":"FR",
    "sg:address":"Rue des Maillys",
    "sg:city":"Essey l\u00e8s Nancy",
    "sg:orig_category":"Non-Classified Establishments",
    "sg:phone":"+33 3 83 29 25 53",
    "sg:postcode":"54270",
    "sg:province":"Lorraine",
    "wof:name":"Vulca Pneus S.a.r.l.",
    "wof:placetype":"venue"
},
  "geometry": {"coordinates":[6.24858,48.706699],"type":"Point"}
}