{
  "type": "Feature",
  "properties": {
    "addr:full":"Saint Martin 83400 Hyeres Basse Normandie",
    "addr:postcode":"83400",
    "addr:street":"Saint Martin;Basse Normandie",
    "iso:country":"FR",
    "sg:address":"Saint Martin 83400 Hyeres",
    "sg:classifiers":[
        {
            "category":"Farming",
            "subcategory":"Farm",
            "type":"Manufacturing & Wholesale Goods"
        }
    ],
    "sg:phone":"+33 4 94 12 41 90",
    "sg:province":"Basse Normandie",
    "sg:tags":[
        "horticulture",
        "agriculture",
        "livestock"
    ],
    "wof:name":"Rampp France",
    "wof:placetype":"venue"
},
  "geometry": {"coordinates":[6.119875,43.112801],"type":"Point"}
}