{
  "type": "Feature",
  "properties": {
    "iso:country":"FR",
    "sg:address":"15, Av. du Pont de Tasset, 74960 Meythet",
    "sg:orig_category":"Unclassifiable Establishments",
    "sg:phone":"+33 4 50 67 69 36",
    "sg:province":"Rhone-Alpes",
    "wof:name":"Blanc Yves",
    "wof:placetype":"venue"
},
  "geometry": {"coordinates":[6.098698,45.911812],"type":"Point"}
}