{
  "type": "Feature",
  "properties": {
    "addr:full":"B.P. 30, 67701 Saverne C\u00e9dex^^10, Rue du Zornhoff, 67700 Saverne Saverne Alsace 67700",
    "addr:postcode":"67701;67700;67700",
    "addr:street":"B.P. 30;Rue Du Zornhoff",
    "iso:country":"FR",
    "sg:address":"B.P. 30, 67701 Saverne C\u00e9dex^^10, Rue du Zornhoff, 67700 Saverne",
    "sg:city":"Saverne",
    "sg:orig_category":"Non-Classified Establishments",
    "sg:phone":"+33 3 88 71 63 00",
    "sg:postcode":"67700",
    "sg:province":"Alsace",
    "wof:name":"S.a.i.t. Mining S.a.",
    "wof:placetype":"venue"
},
  "geometry": {"coordinates":[7.366026,48.739471],"type":"Point"}
}