{
  "type": "Feature",
  "properties": {
    "iso:country":"FR",
    "sg:address":"9 av Sadi Carnot; Mont de Marsan",
    "sg:classifiers":[
        {
            "category":"Banks & Credit Unions",
            "subcategory":"Bank",
            "type":"Services"
        }
    ],
    "sg:phone":"+33 3358751633",
    "sg:province":"Poitou-Charentes",
    "wof:name":"Cr\u00e9dit Mutuel",
    "wof:placetype":"venue"
},
  "geometry": {"coordinates":[-0.500138,43.887833],"type":"Point"}
}