{
  "type": "Feature",
  "properties": {
    "iso:country":"FR",
    "sg:address":"6, Rue L\u00e9on Blum - ZI du Ch\u00e2teau de l'Ile, 69320 Feyzin",
    "sg:orig_category":"Unclassifiable Establishments",
    "sg:phone":"+33 4 72 89 32 32",
    "sg:postcode":"69320",
    "sg:province":"Rhone-Alpes",
    "wof:name":"L.d.g. S.a. - Lyon Distribution Gaz",
    "wof:placetype":"venue"
},
  "geometry": {"coordinates":[4.856056,45.677654],"type":"Point"}
}