{
  "type": "Feature",
  "properties": {
    "addr:full":"B.P. 186, 59544 Caudry C\u00e9dex^^Av. Henri Lefebvre, 59540 Caudry Nord Pas-de-Calais",
    "addr:housenumber":"b.p. 186",
    "addr:postcode":"59544;59540",
    "addr:street":"Henri Lefebvre",
    "iso:country":"FR",
    "sg:address":"B.P. 186, 59544 Caudry C\u00e9dex^^Av. Henri Lefebvre, 59540 Caudry",
    "sg:orig_category":"Non-Classified Establishments",
    "sg:phone":"+33 3 27 85 22 61",
    "sg:province":"Nord Pas-de-Calais",
    "wof:name":"Rousseau S.a.",
    "wof:placetype":"venue"
},
  "geometry": {"coordinates":[3.41236,50.124474],"type":"Point"}
}