{
  "type": "Feature",
  "properties": {
    "iso:country":"FR",
    "sg:address":"35, Rue Grillet, 03400 Yzeure",
    "sg:city":"Yzeure",
    "sg:orig_category":"Unclassifiable Establishments",
    "sg:phone":"+33 4 70 44 01 38",
    "sg:postcode":"03400",
    "sg:province":"Auvergne",
    "wof:name":"S.r.a. Savac S.a.",
    "wof:placetype":"venue"
},
  "geometry": {"coordinates":[3.353778,46.570457],"type":"Point"}
}