{
  "type": "Feature",
  "properties": {
    "iso:country":"FR",
    "sg:address":"4, Rue de l'Orme, 28140 Dambron",
    "sg:city":"Dambron",
    "sg:orig_category":"Unclassifiable Establishments",
    "sg:phone":"+33 2 38 80 07 78",
    "sg:postcode":"28140",
    "sg:province":"Centre",
    "wof:name":"Saunier Et Fils S.a.r.l.",
    "wof:placetype":"venue"
},
  "geometry": {"coordinates":[1.872267,48.113796],"type":"Point"}
}