{
  "type": "Feature",
  "properties": {
    "addr:full":"Rue Edouard Branly - ZA la Buzeni\u00e8re Les Herbiers Pays de Loire 85500",
    "addr:postcode":"85500",
    "addr:street":"Rue Edouard Branly Za La Buzenie\u0300Re",
    "iso:country":"FR",
    "sg:address":"Rue Edouard Branly - ZA la Buzeni\u00e8re",
    "sg:city":"Les Herbiers",
    "sg:orig_category":"Unclassifiable Establishments",
    "sg:phone":"+33 2 51 64 99 88",
    "sg:postcode":"85500",
    "sg:province":"Pays de Loire",
    "wof:name":"C.e.i.m. S.a. - Comptoir Electrique Industriel Du Maine",
    "wof:placetype":"venue"
},
  "geometry": {"coordinates":[-1.019829,46.815769],"type":"Point"}
}