{
  "type": "Feature",
  "properties": {
    "iso:country":"FR",
    "sg:address":"Le Nuzeret BP 14 71440 St Vincent En Bresse",
    "sg:city":"Lessard-en-Bresse",
    "sg:classifiers":[
        {
            "category":"Manufacturing",
            "subcategory":"Chemicals & Compounds",
            "type":"Manufacturing & Wholesale Goods"
        }
    ],
    "sg:phone":"+33 3 85 76 54 66",
    "sg:postcode":"71440",
    "sg:province":"Bourgogne",
    "sg:tags":[
        "pharmaceutical",
        "chemistry",
        "-",
        "by-product"
    ],
    "wof:name":"Cellande Sa",
    "wof:placetype":"venue"
},
  "geometry": {"coordinates":[5.045917,46.681728],"type":"Point"}
}