{
  "type": "Feature",
  "properties": {
    "iso:country":"FR",
    "sg:address":"parc Activit\u00e9s Logis Neuf 69780 Toussieu",
    "sg:classifiers":[
        {
            "category":"Exhibition Hall",
            "type":"Public Place"
        }
    ],
    "sg:phone":"+33 4 72 48 03 63",
    "sg:postcode":"69780",
    "sg:province":"Rhone-Alpes",
    "sg:tags":[
        "equipping",
        "sale",
        "room",
        "show"
    ],
    "wof:name":"X - Po Sa",
    "wof:placetype":"venue"
},
  "geometry": {"coordinates":[4.988005,45.662899],"type":"Point"}
}