{
  "type": "Feature",
  "properties": {
    "addr:full":"Route St Quentin 30700 St Victor Des Oules Languedoc-Roussillon 30700",
    "addr:postcode":"30700;30700",
    "addr:street":"Route St;Des Oules",
    "iso:country":"FR",
    "sg:address":"Route St Quentin 30700 St Victor Des Oules",
    "sg:classifiers":[
        {
            "category":"Shopping",
            "type":"Retail Goods"
        }
    ],
    "sg:phone":"+33 4 66 22 20 09",
    "sg:postcode":"30700",
    "sg:province":"Languedoc-Roussillon",
    "sg:tags":[
        "metallurgy",
        "finished",
        "-",
        "metalworking",
        "metallic"
    ],
    "wof:name":"Acma (ste D'exploitation Des Ets)",
    "wof:placetype":"venue"
},
  "geometry": {"coordinates":[4.440003,44.047153],"type":"Point"}
}