{
  "type": "Feature",
  "properties": {
    "addr:full":"Za Lebreyres 43400 Le Chambon Sur Lignon Le Chambon-sur-Lignon Auvergne 43400",
    "addr:housenumber":"lignon",
    "addr:postcode":"43400;43400",
    "addr:street":"Za Lebreyres;Chambon;Chambon-Sur-Lignon",
    "iso:country":"FR",
    "sg:address":"Za Lebreyres 43400 Le Chambon Sur Lignon",
    "sg:city":"Le Chambon-sur-Lignon",
    "sg:orig_category":"Health - equipments and instruments Jewellery Miscellaneous Products Optical equipments and instrume",
    "sg:phone":"+33 4 71 65 74 50",
    "sg:postcode":"43400",
    "sg:province":"Auvergne",
    "wof:name":"Slam",
    "wof:placetype":"venue"
},
  "geometry": {"coordinates":[4.302683,45.060493],"type":"Point"}
}