{
  "type": "Feature",
  "properties": {
    "iso:country":"FR",
    "sg:address":"Quergarabat Zac De L'Hermitage 29200 Brest",
    "sg:city":"Brest",
    "sg:classifiers":[
        {
            "category":"Government",
            "subcategory":"Department Of Motor Vehicles",
            "type":"Public Place"
        }
    ],
    "sg:phone":"+33 2 98 41 64 84",
    "sg:postcode":"29200",
    "sg:province":"Bretagne",
    "sg:tags":[
        "equipment",
        "industrial",
        "transport",
        "motor-cars"
    ],
    "wof:name":"Fichou Maxauto",
    "wof:placetype":"venue"
},
  "geometry": {"coordinates":[-4.467803,48.42704],"type":"Point"}
}