{
  "type": "Feature",
  "properties": {
    "addr:full":"Rte de Rosel Saint Contest Basse Normandie 14000",
    "addr:postcode":"14000",
    "addr:street":"Rte De Rosel",
    "iso:country":"FR",
    "sg:address":"Rte de Rosel",
    "sg:city":"Saint Contest",
    "sg:orig_category":"Non-Classified Establishments",
    "sg:phone":"+33 2 31 44 56 19",
    "sg:postcode":"14000",
    "sg:province":"Basse Normandie",
    "wof:name":"Soci\u00e9t\u00e9 Paysag\u00e8re De L'ouest S.a.r.l.",
    "wof:placetype":"venue"
},
  "geometry": {"coordinates":[-0.36111,49.184361],"type":"Point"}
}