{
  "type": "Feature",
  "properties": {
    "iso:country":"FR",
    "sg:address":"Lieudit Les Dodoux Zone Industrielle 26190 St Jean En Royans",
    "sg:classifiers":[
        {
            "category":"Manufacturing",
            "subcategory":"Tools & Machinery",
            "type":"Manufacturing & Wholesale Goods"
        }
    ],
    "sg:phone":"+33 4 75 48 61 79",
    "sg:postcode":"26190",
    "sg:province":"Rhone-Alpes",
    "sg:tags":[
        "metallurgy",
        "metalworking"
    ],
    "wof:name":"Etablissements Brun Freres",
    "wof:placetype":"venue"
},
  "geometry": {"coordinates":[5.182355,44.886749],"type":"Point"}
}