{
  "type": "Feature",
  "properties": {
    "addr:full":"41 Rue De La Garenne 92310 S\u00e8vres Ile de France 92310",
    "addr:housenumber":"41",
    "addr:postcode":"92310;92310",
    "addr:street":"Rue De La Garenne",
    "iso:country":"FR",
    "sg:address":"41 Rue De La Garenne 92310 S\u00e8vres",
    "sg:classifiers":[
        {
            "category":"Professional",
            "subcategory":"Business Services",
            "type":"Services"
        }
    ],
    "sg:phone":"+33 1 41 14 16 18",
    "sg:postcode":"92310",
    "sg:province":"Ile de France",
    "sg:tags":[
        "body",
        "training",
        "advice"
    ],
    "wof:name":"Association Nationale Pour La Formation Automobile",
    "wof:placetype":"venue"
},
  "geometry": {"coordinates":[2.21235,48.813435],"type":"Point"}
}