{
  "type": "Feature",
  "properties": {
    "addr:full":"B.P. 23, 45140 Saint Jean de la Ruelle C\u00e9dex^^Rue Henri Dunant, 45140 Ingr\u00e9 Ingr\u00e9 Centre 45140",
    "addr:postcode":"45140;45140;45140",
    "addr:street":"B.P. 23;La Ruelle Ce\u0301Dex^^Rue Henri Dunant",
    "iso:country":"FR",
    "sg:address":"B.P. 23, 45140 Saint Jean de la Ruelle C\u00e9dex^^Rue Henri Dunant, 45140 Ingr\u00e9",
    "sg:city":"Ingr\u00e9",
    "sg:orig_category":"Non-Classified Establishments",
    "sg:phone":"+33 2 38 88 22 82",
    "sg:postcode":"45140",
    "sg:province":"Centre",
    "wof:name":"Mory Team S.a.",
    "wof:placetype":"venue"
},
  "geometry": {"coordinates":[1.8745,47.912949],"type":"Point"}
}