{
  "type": "Feature",
  "properties": {
    "addr:full":"2 blvd de Chaney; Montreuil; 93199 Haute Normandie",
    "addr:housenumber":"2",
    "addr:postcode":"93199",
    "addr:street":"Blvd De Chaney",
    "iso:country":"FR",
    "sg:address":"2 blvd de Chaney; Montreuil; 93199",
    "sg:classifiers":[
        {
            "category":"Banks & Credit Unions",
            "subcategory":"Bank",
            "type":"Services"
        }
    ],
    "sg:phone":"+33 18586800",
    "sg:province":"Haute Normandie",
    "wof:name":"Banque Worms",
    "wof:placetype":"venue"
},
  "geometry": {"coordinates":[1.67767,49.176891],"type":"Point"}
}