{
  "type": "Feature",
  "properties": {
    "addr:full":"B.P. 44, 62310 Fruges^^52, Rue du Fort du Rietz, 62310 Fruges Nord Pas-de-Calais",
    "addr:postcode":"62310;62310",
    "addr:street":"B.P. 44;Rue Du Fort Du Rietz",
    "iso:country":"FR",
    "sg:address":"B.P. 44, 62310 Fruges^^52, Rue du Fort du Rietz, 62310 Fruges",
    "sg:orig_category":"Non-Classified Establishments",
    "sg:phone":"+33 3 21 04 41 86",
    "sg:province":"Nord Pas-de-Calais",
    "wof:name":"Merlier Cars S.a.",
    "wof:placetype":"venue"
},
  "geometry": {"coordinates":[2.134399,50.514503],"type":"Point"}
}