{
  "type": "Feature",
  "properties": {
    "addr:full":"21 Rue Marcellin Berthelot 86000 Poitiers Poitou-Charentes",
    "addr:housenumber":"21",
    "addr:postcode":"86000",
    "addr:street":"Rue Marcellin Berthelot",
    "iso:country":"FR",
    "sg:address":"21 Rue Marcellin Berthelot 86000 Poitiers",
    "sg:classifiers":[
        {
            "category":"Manufacturing",
            "subcategory":"Rubber & Plastics",
            "type":"Manufacturing & Wholesale Goods"
        }
    ],
    "sg:phone":"+33 5 49 50 38 00",
    "sg:province":"Poitou-Charentes",
    "wof:name":"Manufacture Fran\u00c7aise Des Pneumatiques Michelin",
    "wof:placetype":"venue"
},
  "geometry": {"coordinates":[0.33149,46.608269],"type":"Point"}
}