{
  "type": "Feature",
  "properties": {
    "iso:country":"FR",
    "sg:address":"Rue de Jud\u00e9e",
    "sg:city":"Les Landes Genusson",
    "sg:orig_category":"Unclassifiable Establishments",
    "sg:phone":"+33 2 51 91 67 00",
    "sg:postcode":"85130",
    "sg:province":"Pays de Loire",
    "wof:name":"Marchand E.a.r.l.",
    "wof:placetype":"venue"
},
  "geometry": {"coordinates":[-1.117903,46.964584],"type":"Point"}
}