{
  "type": "Feature",
  "properties": {
    "addr:full":"46 Avenue Roussillon 63170 Aubi\u00e8re Aubi\u00e8re Auvergne 63170",
    "addr:housenumber":"46",
    "addr:postcode":"63170;63170",
    "addr:street":"Avenue",
    "iso:country":"FR",
    "sg:address":"46 Avenue Roussillon 63170 Aubi\u00e8re",
    "sg:city":"Aubi\u00e8re",
    "sg:classifiers":[
        {
            "category":"Autos & Motor Vehicles",
            "subcategory":"Automobile Sales",
            "type":"Retail Goods"
        }
    ],
    "sg:phone":"+33 4 73 26 33 90",
    "sg:postcode":"63170",
    "sg:province":"Auvergne",
    "sg:tags":[
        "equipment",
        "industrial",
        "transport"
    ],
    "wof:name":"Sevi 63 Sa",
    "wof:placetype":"venue"
},
  "geometry": {"coordinates":[3.13383,45.749699],"type":"Point"}
}