{
  "type": "Feature",
  "properties": {
    "iso:country":"FR",
    "sg:address":"March\u00e9 Gare St C\u00e9saire 30900 N\u00eemes",
    "sg:classifiers":[
        {
            "category":"Banks & Credit Unions",
            "subcategory":"Financial Services",
            "type":"Services"
        }
    ],
    "sg:phone":"+33 4 66 04 86 86",
    "sg:postcode":"30900",
    "sg:province":"Languedoc-Roussillon",
    "sg:tags":[
        "banking",
        "insurance",
        "institution",
        "finance"
    ],
    "wof:name":"Promocash",
    "wof:placetype":"venue"
},
  "geometry": {"coordinates":[4.327705,43.817001],"type":"Point"}
}