{
  "type": "Feature",
  "properties": {
    "iso:country":"FR",
    "sg:address":"74/76, Rue du Temple, 75003 Paris",
    "sg:orig_category":"Non-Classified Establishments",
    "sg:phone":"+33 1 53 01 70 00",
    "sg:province":"Ile de France",
    "wof:name":"Gyl Bagages S.a.",
    "wof:placetype":"venue"
},
  "geometry": {"coordinates":[2.356718,48.861504],"type":"Point"}
}