{
  "type": "Feature",
  "properties": {
    "iso:country":"FR",
    "sg:address":"6, Rue du 5 Septembre 1914, 77165 Saint Soupplets",
    "sg:orig_category":"Non-Classified Establishments",
    "sg:phone":"+33 1 60 01 53 72",
    "sg:province":"Ile de France",
    "wof:name":"Seca S.a.",
    "wof:placetype":"venue"
},
  "geometry": {"coordinates":[2.800452,49.035004],"type":"Point"}
}