{
  "type": "Feature",
  "properties": {
    "addr:full":"102, Rue de la Fontaine, 75016 Paris Ile de France",
    "addr:housenumber":"102",
    "addr:postcode":"75016",
    "addr:street":"Rue De La Fontaine",
    "iso:country":"FR",
    "sg:address":"102, Rue de la Fontaine, 75016 Paris",
    "sg:orig_category":"Unclassifiable Establishments",
    "sg:phone":"+33 1 45 20 27 91",
    "sg:province":"Ile de France",
    "wof:name":"Cogistem S.a.r.l.",
    "wof:placetype":"venue"
},
  "geometry": {"coordinates":[2.267212,48.849468],"type":"Point"}
}