{
  "type": "Feature",
  "properties": {
    "iso:country":"FR",
    "sg:address":"31, Rue de la Vertonne - ZI Parc de la Vertonne, 44120 Vertou",
    "sg:orig_category":"Non-Classified Establishments",
    "sg:phone":"+33 2 40 03 13 30",
    "sg:postcode":"44120",
    "sg:province":"Pays de Loire",
    "wof:name":"Calpeda Pompes S.a.",
    "wof:placetype":"venue"
},
  "geometry": {"coordinates":[-1.468059,47.137573],"type":"Point"}
}