{
  "type": "Feature",
  "properties": {
    "addr:full":"268, Chemin de Sainte Marthe, 13014 Marseille Provence-Alpes-C\u00f4te d'Azur",
    "addr:housenumber":"268",
    "addr:postcode":"13014",
    "addr:street":"Chemin De Sainte Marthe",
    "iso:country":"FR",
    "sg:address":"268, Chemin de Sainte Marthe, 13014 Marseille",
    "sg:orig_category":"Non-Classified Establishments",
    "sg:phone":"+33 4 91 02 83 07",
    "sg:province":"Provence-Alpes-C\u00f4te d'Azur",
    "wof:name":"L.b.l. M\u00e9diterrann\u00e9e S.a.",
    "wof:placetype":"venue"
},
  "geometry": {"coordinates":[5.390523,43.332981],"type":"Point"}
}