{
  "type": "Feature",
  "properties": {
    "addr:full":"21, Rue de la Mairie, 02420 Aubencheul aux Bois Picardie",
    "addr:housenumber":"21",
    "addr:postcode":"02420",
    "addr:street":"Rue De La Mairie;Aux Bois Picardie",
    "iso:country":"FR",
    "sg:address":"21, Rue de la Mairie, 02420 Aubencheul aux Bois",
    "sg:orig_category":"Non-Classified Establishments",
    "sg:phone":"+33 3 23 66 22 57",
    "sg:province":"Picardie",
    "wof:name":"Soci\u00e9t\u00e9 D'exploitation Des Etablissements Gervais Cotter\u00eat S.a.r.l.",
    "wof:placetype":"venue"
},
  "geometry": {"coordinates":[3.24773,49.97208],"type":"Point"}
}