{
  "type": "Feature",
  "properties": {
    "iso:country":"FR",
    "sg:address":"24 Av Jean Moulin 90110 Rougement Le Ch\u00e2teau",
    "sg:classifiers":[
        {
            "category":"Transit Center",
            "subcategory":"Freight",
            "type":"Transportation"
        }
    ],
    "sg:phone":"+33 3 84 46 62 80",
    "sg:postcode":"90110",
    "sg:province":"Franche Comt\u00e9",
    "sg:tags":[
        "metallurgy",
        "pipe",
        "metalworking",
        "sheet"
    ],
    "wof:name":"Filiac",
    "wof:placetype":"venue"
},
  "geometry": {"coordinates":[-96.835457,43.446461],"type":"Point"}
}