{
  "type": "Feature",
  "properties": {
    "iso:country":"FR",
    "sg:address":"7, All\u00e9e de la Providence, 86000 Poitiers",
    "sg:orig_category":"Non-Classified Establishments",
    "sg:phone":"+33 5 49 30 09 50",
    "sg:postcode":"86000",
    "sg:province":"Poitou-Charentes",
    "wof:name":"Sph\u00e8re",
    "wof:placetype":"venue"
},
  "geometry": {"coordinates":[0.3677,46.562851],"type":"Point"}
}