{
  "type": "Feature",
  "properties": {
    "addr:full":"7, Rue des Fr\u00e8res Lumi\u00e8re, 45800 Saint Jean de Braye Combleux Centre 45800",
    "addr:housenumber":"7;combleux",
    "addr:postcode":"45800;45800",
    "addr:street":"Rue Des Fre\u0300Res Lumie\u0300Re",
    "iso:country":"FR",
    "sg:address":"7, Rue des Fr\u00e8res Lumi\u00e8re, 45800 Saint Jean de Braye",
    "sg:city":"Combleux",
    "sg:orig_category":"Non-Classified Establishments",
    "sg:phone":"+33 2 38 72 69 50",
    "sg:postcode":"45800",
    "sg:province":"Centre",
    "wof:name":"Etablissement Bati France",
    "wof:placetype":"venue"
},
  "geometry": {"coordinates":[1.946344,47.918022],"type":"Point"}
}