{
  "type": "Feature",
  "properties": {
    "addr:full":"8, Chemin des Trois Moulins, 33390 Saint Martin Lacaussade Berson Aquitaine 33390",
    "addr:housenumber":"8",
    "addr:postcode":"33390;33390",
    "addr:street":"Chemin Des Trois Moulins",
    "iso:country":"FR",
    "sg:address":"8, Chemin des Trois Moulins, 33390 Saint Martin Lacaussade",
    "sg:city":"Berson",
    "sg:orig_category":"Unclassifiable Establishments",
    "sg:phone":"+33 5 57 42 90 93",
    "sg:postcode":"33390",
    "sg:province":"Aquitaine",
    "wof:name":"Montaut Thierry E.u.r.l.",
    "wof:placetype":"venue"
},
  "geometry": {"coordinates":[-0.64003,45.1488],"type":"Point"}
}