{
  "type": "Feature",
  "properties": {
    "addr:full":"Zone D'Emploi La Touche 16560 Anais Poitou-Charentes 16560",
    "addr:postcode":"16560;16560",
    "iso:country":"FR",
    "sg:address":"Zone D'Emploi La Touche 16560 Anais",
    "sg:classifiers":[
        {
            "category":"Professional",
            "subcategory":"Engineering",
            "type":"Services"
        }
    ],
    "sg:phone":"+33 5 45 20 65 50",
    "sg:postcode":"16560",
    "sg:province":"Poitou-Charentes",
    "sg:tags":[
        "machine",
        "-",
        "mechanical"
    ],
    "wof:name":"Somc",
    "wof:placetype":"venue"
},
  "geometry": {"coordinates":[0.20944,45.774029],"type":"Point"}
}