{
  "type": "Feature",
  "properties": {
    "iso:country":"FR",
    "sg:address":"1 Pl De La Trinit\u00e9 35064 Rennes Cedex",
    "sg:city":"La Trinit\u00e9",
    "sg:classifiers":[
        {
            "category":"Banks & Credit Unions",
            "subcategory":"Financial Services",
            "type":"Services"
        }
    ],
    "sg:phone":"+33 2 99 29 79 79",
    "sg:postcode":"50800",
    "sg:province":"Basse Normandie",
    "sg:tags":[
        "banking",
        "insurance",
        "institution",
        "finance"
    ],
    "wof:name":"Banque Populaire De L Ouest",
    "wof:placetype":"venue"
},
  "geometry": {"coordinates":[-1.683241,48.112385],"type":"Point"}
}