{
  "type": "Feature",
  "properties": {
    "iso:country":"FR",
    "sg:address":"4, Square Rosny Ain\u00e9, 75013 Paris",
    "sg:orig_category":"Non-Classified Establishments",
    "sg:phone":"+33 1 45 81 63 69",
    "sg:postcode":"75013",
    "sg:province":"Ile de France",
    "wof:name":"Dife S.a.",
    "wof:placetype":"venue"
},
  "geometry": {"coordinates":[2.358963,48.817619],"type":"Point"}
}