{
  "type": "Feature",
  "properties": {
    "iso:country":"FR",
    "sg:address":"B.P. 343, 74008 Annecy C\u00e9dex^^4, Rue du Radar, 74000 Annecy",
    "sg:orig_category":"Non-Classified Establishments",
    "sg:phone":"+33 4 50 67 99 50",
    "sg:postcode":"74000",
    "sg:province":"Rhone-Alpes",
    "wof:name":"S.i.c.n. S.a. - Soci\u00e9t\u00e9 Industrielle De Combustible Nucl\u00e9aire",
    "wof:placetype":"venue"
},
  "geometry": {"coordinates":[6.128832,45.898781],"type":"Point"}
}