{
  "type": "Feature",
  "properties": {
    "iso:country":"FR",
    "sg:address":"Z Activite 62840 Sailly sur la Lys",
    "sg:classifiers":[
        {
            "category":"Government",
            "subcategory":"Office",
            "type":"Public Place"
        }
    ],
    "sg:phone":"+33 3 21 26 61 41",
    "sg:postcode":"62840",
    "sg:province":"Nord Pas-de-Calais",
    "sg:tags":[
        "building",
        "industrial",
        "equipping",
        "furnishing"
    ],
    "wof:name":"Produits Avicoles Lillois S.a.",
    "wof:placetype":"venue"
},
  "geometry": {"coordinates":[2.772065,50.626614],"type":"Point"}
}