{
  "type": "Feature",
  "properties": {
    "iso:country":"FR",
    "sg:address":"5, Avenue de Saintignon, 54400 Longwy",
    "sg:orig_category":"Non-Classified Establishments",
    "sg:phone":"+33 3 82 24 40 58",
    "sg:postcode":"54400",
    "sg:province":"Lorraine",
    "wof:name":"C.c.i. Meurthe Et Moselle",
    "wof:placetype":"venue"
},
  "geometry": {"coordinates":[5.768301,49.515633],"type":"Point"}
}