{
  "type": "Feature",
  "properties": {
    "addr:full":"11, Rue Blaise Pascal, 18100 Vierzon Vierzon Centre 18100",
    "addr:housenumber":"11;vierzon",
    "addr:postcode":"18100;18100",
    "addr:street":"Rue Blaise Pascal",
    "iso:country":"FR",
    "sg:address":"11, Rue Blaise Pascal, 18100 Vierzon",
    "sg:city":"Vierzon",
    "sg:orig_category":"Non-Classified Establishments",
    "sg:phone":"+33 2 48 75 04 55",
    "sg:postcode":"18100",
    "sg:province":"Centre",
    "wof:name":"Soci\u00e9t\u00e9 D' Exploitation Des Etablissements De Pooter S.a.r.l.",
    "wof:placetype":"venue"
},
  "geometry": {"coordinates":[2.075009,47.216789],"type":"Point"}
}