{
  "type": "Feature",
  "properties": {
    "addr:full":"692, Av. du G\u00e9n\u00e9ral de Gaulle, 01300 Belley Rhone-Alpes",
    "addr:postcode":"01300",
    "addr:street":"692 Av. Du Ge\u0301Ne\u0301Ral De Gaulle",
    "iso:country":"FR",
    "sg:address":"692, Av. du G\u00e9n\u00e9ral de Gaulle, 01300 Belley",
    "sg:orig_category":"Unclassifiable Establishments",
    "sg:phone":"+33 4 79 42 30 30",
    "sg:province":"Rhone-Alpes",
    "wof:name":"Le Tanneur Et Compagnie S.a.",
    "wof:placetype":"venue"
},
  "geometry": {"coordinates":[5.69818,45.758339],"type":"Point"}
}