{
  "type": "Feature",
  "properties": {
    "addr:full":"La Bougri\u00e8re 44980 Ste Luce Sur Loire Pays de Loire 44980",
    "addr:postcode":"44980;44980",
    "addr:street":"Luce;Loire",
    "iso:country":"FR",
    "sg:address":"La Bougri\u00e8re 44980 Ste Luce Sur Loire",
    "sg:classifiers":[
        {
            "category":"Shopping",
            "subcategory":"Crafts & Fabrics",
            "type":"Retail Goods"
        }
    ],
    "sg:phone":"+33 2 40 25 85 59",
    "sg:postcode":"44980",
    "sg:province":"Pays de Loire",
    "sg:tags":[
        "textile",
        "clothing"
    ],
    "wof:name":"Technostor",
    "wof:placetype":"venue"
},
  "geometry": {"coordinates":[-1.475059,47.260941],"type":"Point"}
}