{
  "type": "Feature",
  "properties": {
    "addr:full":"Moulin De Bures 76660 Bures En Bray Haute Normandie 76660",
    "addr:postcode":"76660;76660",
    "addr:street":"Moulin De Bures;Haute Normandie",
    "iso:country":"FR",
    "sg:address":"Moulin De Bures 76660 Bures En Bray",
    "sg:classifiers":[
        {
            "category":"Farming",
            "subcategory":"Farm & Veterinary Services",
            "type":"Manufacturing & Wholesale Goods"
        }
    ],
    "sg:phone":"+33 2 32 97 41 22",
    "sg:postcode":"76660",
    "sg:province":"Haute Normandie",
    "sg:tags":[
        "food",
        "product",
        "breeding",
        "animal",
        "related"
    ],
    "wof:name":"Prevital Normandie",
    "wof:placetype":"venue"
},
  "geometry": {"coordinates":[1.4025,49.832535],"type":"Point"}
}