{
  "type": "Feature",
  "properties": {
    "iso:country":"FR",
    "sg:address":"43, Rue Corneille - B\u00e2t. C, 31100 Toulouse",
    "sg:orig_category":"Unclassifiable Establishments",
    "sg:phone":"+33 5 61 43 68 80",
    "sg:province":"Midi Pyr\u00e9n\u00e9es",
    "wof:name":"A.c.g. S.a.r.l. - Audit Et Contr\u00f4le De Gestion",
    "wof:placetype":"venue"
},
  "geometry": {"coordinates":[1.411166,43.592339],"type":"Point"}
}