{
  "type": "Feature",
  "properties": {
    "iso:country":"FR",
    "sg:address":"12, Rte de Pontoise - la Bonneville, 95540 M\u00e9ry sur Oise",
    "sg:orig_category":"Non-Classified Establishments",
    "sg:phone":"+33 1 34 64 82 38",
    "sg:postcode":"95540",
    "sg:province":"Ile de France",
    "wof:name":"D\u00e9m\u00e9nagement Transport Gardes Meubles Grie S.a.r.l.",
    "wof:placetype":"venue"
},
  "geometry": {"coordinates":[2.185465,49.064209],"type":"Point"}
}