{
  "type": "Feature",
  "properties": {
    "iso:country":"FR",
    "sg:address":"24 B Rue Des Landelles 35135 Chantepie",
    "sg:city":"Chantepie",
    "sg:classifiers":[
        {
            "category":"Manufacturing",
            "subcategory":"Rubber & Plastics",
            "type":"Manufacturing & Wholesale Goods"
        }
    ],
    "sg:phone":"+33 2 99 41 03 10",
    "sg:postcode":"35135",
    "sg:province":"Bretagne",
    "wof:name":"Goodyear France",
    "wof:placetype":"venue"
},
  "geometry": {"coordinates":[-1.623301,48.099728],"type":"Point"}
}