{
  "type": "Feature",
  "properties": {
    "iso:country":"FR",
    "sg:address":"Kerdelant 29430 Ploun\u00e9vez Lochrist",
    "sg:city":"Lanhouarneau",
    "sg:orig_category":"Non-Classified Establishments",
    "sg:phone":"+33 2 98 61 67 68",
    "sg:postcode":"29430",
    "sg:province":"Bretagne",
    "wof:name":"Fruits D'amor S.a.r.l.",
    "wof:placetype":"venue"
},
  "geometry": {"coordinates":[-4.214894,48.63916],"type":"Point"}
}