{
  "type": "Feature",
  "properties": {
    "addr:full":"Rte de Thizy Grandris Rhone-Alpes 69870",
    "addr:postcode":"69870",
    "addr:street":"Rte De Thizy;Rhone-Alpes",
    "iso:country":"FR",
    "sg:address":"Rte de Thizy",
    "sg:city":"Grandris",
    "sg:orig_category":"Non-Classified Establishments",
    "sg:phone":"+33 4 74 60 10 53",
    "sg:postcode":"69870",
    "sg:province":"Rhone-Alpes",
    "wof:name":"Rivaton Georges Robert",
    "wof:placetype":"venue"
},
  "geometry": {"coordinates":[4.474476,46.036133],"type":"Point"}
}