{
  "type": "Feature",
  "properties": {
    "addr:full":"B.P. 21, 69141 Rillieux la Pape C\u00e9dex^^404, Av. du Champ de Lierre, 69140 Rillieux la Pape Rhone-Alpes 69140",
    "addr:postcode":"69141;69140;69140",
    "addr:street":"B.P. 21;Av. Du Champ De Lierre",
    "iso:country":"FR",
    "sg:address":"B.P. 21, 69141 Rillieux la Pape C\u00e9dex^^404, Av. du Champ de Lierre, 69140 Rillieux la Pape",
    "sg:orig_category":"Non-Classified Establishments",
    "sg:phone":"+33 4 72 01 81 50",
    "sg:postcode":"69140",
    "sg:province":"Rhone-Alpes",
    "wof:name":"Gemavil Prolians S.a.",
    "wof:placetype":"venue"
},
  "geometry": {"coordinates":[4.897105,45.820801],"type":"Point"}
}