{
  "type": "Feature",
  "properties": {
    "iso:country":"FR",
    "sg:address":"9 rue Blaise Pascal 92200 Neuilly sur Seine",
    "sg:classifiers":[
        {
            "category":"Professional",
            "subcategory":"Advertising",
            "type":"Services"
        }
    ],
    "sg:phone":"+33 1 55 62 62 62",
    "sg:postcode":"92200",
    "sg:province":"Ile de France",
    "sg:tags":[
        "agency"
    ],
    "wof:name":"D'arcy Masius Benton & Bowles S.a.",
    "wof:placetype":"venue"
},
  "geometry": {"coordinates":[2.257701,48.886589],"type":"Point"}
}