{
  "type": "Feature",
  "properties": {
    "addr:full":"4, Bd de la Rade, 56100 Lorient Lorient Bretagne 56100",
    "addr:housenumber":"4",
    "addr:postcode":"56100;56100",
    "addr:street":"Bd De La Rade",
    "iso:country":"FR",
    "sg:address":"4, Bd de la Rade, 56100 Lorient",
    "sg:city":"Lorient",
    "sg:orig_category":"Unclassifiable Establishments",
    "sg:phone":"+33 2 97 21 17 89",
    "sg:postcode":"56100",
    "sg:province":"Bretagne",
    "wof:name":"Cobral S.a.r.l.",
    "wof:placetype":"venue"
},
  "geometry": {"coordinates":[-3.358344,47.741749],"type":"Point"}
}