{
  "type": "Feature",
  "properties": {
    "addr:full":"Pr\u00e9 La Grande Chauss\u00e9e 76530 Moulineaux Haute Normandie 76530",
    "addr:postcode":"76530;76530",
    "addr:street":"Pre\u0301 La;Chausse\u0301E;Haute Normandie",
    "iso:country":"FR",
    "sg:address":"Pr\u00e9 La Grande Chauss\u00e9e 76530 Moulineaux",
    "sg:classifiers":[
        {
            "category":"Food & Beverages",
            "subcategory":"Dairy",
            "type":"Retail Goods"
        }
    ],
    "sg:phone":"+33 2 35 18 29 10",
    "sg:postcode":"76530",
    "sg:province":"Haute Normandie",
    "sg:tags":[
        "product",
        "related"
    ],
    "wof:name":"Novandie",
    "wof:placetype":"venue"
},
  "geometry": {"coordinates":[1.00869,49.357891],"type":"Point"}
}