{
  "type": "Feature",
  "properties": {
    "addr:full":"3 avenue Nagelmackers 78450 Villepreux Ile de France",
    "addr:housenumber":"3",
    "addr:postcode":"78450;ile",
    "addr:street":"Avenue Nagelmackers",
    "iso:country":"FR",
    "sg:address":"3 avenue Nagelmackers 78450 Villepreux",
    "sg:classifiers":[
        {
            "category":"Professional",
            "subcategory":"Testing Lab",
            "type":"Services"
        }
    ],
    "sg:phone":"+33 1 30 80 81 82",
    "sg:province":"Ile de France",
    "sg:tags":[
        "aeronautical",
        "material",
        "non-destructive"
    ],
    "wof:name":"Babb Co Sa",
    "wof:placetype":"venue"
},
  "geometry": {"coordinates":[2.00259,48.819183],"type":"Point"}
}