{
  "type": "Feature",
  "properties": {
    "addr:full":"Bourg 35560 Rimou Rimou Bretagne 35560",
    "addr:postcode":"35560;35560",
    "addr:street":"Bourg;Rimou",
    "iso:country":"FR",
    "sg:address":"Bourg 35560 Rimou",
    "sg:city":"Rimou",
    "sg:classifiers":[
        {
            "category":"Home & Garden",
            "subcategory":"Furniture",
            "type":"Retail Goods"
        }
    ],
    "sg:phone":"+33 2 99 98 23 23",
    "sg:postcode":"35560",
    "sg:province":"Bretagne",
    "sg:tags":[
        "wood"
    ],
    "wof:name":"Scierie Roussel Sarl",
    "wof:placetype":"venue"
},
  "geometry": {"coordinates":[-1.570554,48.368214],"type":"Point"}
}