{
  "type": "Feature",
  "properties": {
    "addr:full":"Voie n\u00b01 - Immeuble le Strat\u00e8ge Lab\u00e8ge Midi Pyr\u00e9n\u00e9es 31670",
    "addr:postcode":"31670",
    "addr:street":"Voie N\u00b01 Immeuble Le Strate\u0300Ge",
    "iso:country":"FR",
    "sg:address":"Voie n\u00b01 - Immeuble le Strat\u00e8ge",
    "sg:city":"Lab\u00e8ge",
    "sg:orig_category":"Unclassifiable Establishments",
    "sg:phone":"+33 5 61 39 77 41",
    "sg:postcode":"31670",
    "sg:province":"Midi Pyr\u00e9n\u00e9es",
    "wof:name":"Esri France S.a.",
    "wof:placetype":"venue"
},
  "geometry": {"coordinates":[1.527111,43.529713],"type":"Point"}
}