{
  "type": "Feature",
  "properties": {
    "iso:country":"FR",
    "sg:address":"Zi Du Bompas 49120 Chemill\u00e9",
    "sg:classifiers":[
        {
            "category":"Professional",
            "subcategory":"Engineering",
            "type":"Services"
        }
    ],
    "sg:phone":"+33 2 41 30 55 08",
    "sg:postcode":"49120",
    "sg:province":"Pays de Loire",
    "sg:tags":[
        "machine",
        "-",
        "mechanical"
    ],
    "wof:name":"Alla France",
    "wof:placetype":"venue"
},
  "geometry": {"coordinates":[-0.730529,47.212543],"type":"Point"}
}