{
  "type": "Feature",
  "properties": {
    "iso:country":"FR",
    "sg:address":"44, Rue Ferrandi\u00e8re, 69002 Lyon",
    "sg:orig_category":"Unclassifiable Establishments",
    "sg:phone":"+33 4 78 92 94 53",
    "sg:postcode":"69002",
    "sg:province":"Rhone-Alpes",
    "wof:name":"Excellence Financi\u00e8re Cr\u00e9dit Et Gestion S.a.r.l.",
    "wof:placetype":"venue"
},
  "geometry": {"coordinates":[4.83727,45.762043],"type":"Point"}
}