{
  "type": "Feature",
  "properties": {
    "addr:full":"435, Rue Denis Papin, 59147 Gondecourt Nord Pas-de-Calais 59147",
    "addr:housenumber":"435",
    "addr:postcode":"59147;59147",
    "addr:street":"Rue Denis Papin",
    "iso:country":"FR",
    "sg:address":"435, Rue Denis Papin, 59147 Gondecourt",
    "sg:orig_category":"CONDITIONNEMENT ET VENTE GAZ INDUSTRIEL OXYG\u00c8NE, AC\u00c9TYL\u00c8NE, ARGON, STARGON, GOLDMIX, H\u00c9LISTAR, HYDRO",
    "sg:phone":"+33 3 20 62 00 70",
    "sg:postcode":"59147",
    "sg:province":"Nord Pas-de-Calais",
    "wof:name":"Praxair S.a. - Agence R\u00e9gion Nord",
    "wof:placetype":"venue"
},
  "geometry": {"coordinates":[2.968892,50.560608],"type":"Point"}
}