{
  "type": "Feature",
  "properties": {
    "addr:full":"B.P. 23, 77313 Marne la Vall\u00e9e C\u00e9dex 2^^Av. Spinoza, 77184 Emerainville Ile de France",
    "addr:postcode":"77313;77184",
    "addr:street":"B.P. 23;Spinoza;Ile De France",
    "iso:country":"FR",
    "sg:address":"B.P. 23, 77313 Marne la Vall\u00e9e C\u00e9dex 2^^Av. Spinoza, 77184 Emerainville",
    "sg:orig_category":"Non-Classified Establishments",
    "sg:phone":"+33 1 60 95 88 88",
    "sg:province":"Ile de France",
    "wof:name":"France Gift S.a.",
    "wof:placetype":"venue"
},
  "geometry": {"coordinates":[2.622175,48.811619],"type":"Point"}
}