{
  "type": "Feature",
  "properties": {
    "iso:country":"FR",
    "sg:address":"23 pl Vend\u00f4me; Paris; 75001",
    "sg:classifiers":[
        {
            "category":"Banks & Credit Unions",
            "subcategory":"Bank",
            "type":"Services"
        }
    ],
    "sg:phone":"+33 1 42 61 32 33",
    "sg:postcode":"75001",
    "sg:province":"Ile de France",
    "wof:name":"The Nippon Credit, Bank Ltd",
    "wof:placetype":"venue"
},
  "geometry": {"coordinates":[2.329738,48.868057],"type":"Point"}
}