{
  "type": "Feature",
  "properties": {
    "addr:full":"23 pl Vend\u00f4me; Paris; 75001 Ile de France 75001",
    "addr:housenumber":"23",
    "addr:postcode":"75001 ile;france 75001",
    "addr:street":"Pl Vendo\u0302Me",
    "iso:country":"FR",
    "sg:address":"23 pl Vend\u00f4me; Paris; 75001",
    "sg:classifiers":[
        {
            "category":"Banks & Credit Unions",
            "subcategory":"Bank",
            "type":"Services"
        }
    ],
    "sg:phone":"+33 1 42 61 32 33",
    "sg:postcode":"75001",
    "sg:province":"Ile de France",
    "wof:name":"The Nippon Credit, Bank Ltd",
    "wof:placetype":"venue"
},
  "geometry": {"coordinates":[2.329738,48.868057],"type":"Point"}
}