{
  "type": "Feature",
  "properties": {
    "addr:full":"B.P. 3013, 68061 Mulhouse C\u00e9dex^^21, Rue Jean Mieg, 68100 Mulhouse Mulhouse Alsace 68100",
    "addr:postcode":"68061;68100;68100",
    "addr:street":"B.P. 3013;Rue Jean Mieg",
    "iso:country":"FR",
    "sg:address":"B.P. 3013, 68061 Mulhouse C\u00e9dex^^21, Rue Jean Mieg, 68100 Mulhouse",
    "sg:city":"Mulhouse",
    "sg:orig_category":"Non-Classified Establishments",
    "sg:phone":"+33 3 89 36 83 83",
    "sg:postcode":"68100",
    "sg:province":"Alsace",
    "wof:name":"Eurex Alsace S.a.",
    "wof:placetype":"venue"
},
  "geometry": {"coordinates":[7.34365,47.751709],"type":"Point"}
}