{
  "type": "Feature",
  "properties": {
    "iso:country":"FR",
    "sg:address":"13 rue Albert Louppe; Carantec",
    "sg:city":"Alb\u00e9",
    "sg:classifiers":[
        {
            "category":"Banks & Credit Unions",
            "subcategory":"Bank",
            "type":"Services"
        }
    ],
    "sg:phone":"+33 3398670166",
    "sg:postcode":"67220",
    "sg:province":"Alsace",
    "wof:name":"Cr\u00e9dit Agricole Mutuel, (c.a.m)",
    "wof:placetype":"venue"
},
  "geometry": {"coordinates":[-3.914107,48.667194],"type":"Point"}
}