{
  "type": "Feature",
  "properties": {
    "addr:full":"B.P. 62008, 62060 Arras C\u00e9dex 9^^Zone Industrielle Artoipole, 62118 Monchy le Preux Nord Pas-de-Calais 62118",
    "addr:postcode":"62060;62118;62118",
    "addr:street":"9^^Zone;Artoipole;Preux Nord",
    "iso:country":"FR",
    "sg:address":"B.P. 62008, 62060 Arras C\u00e9dex 9^^Zone Industrielle Artoipole, 62118 Monchy le Preux",
    "sg:orig_category":"Non-Classified Establishments",
    "sg:phone":"+33 3 21 50 48 49",
    "sg:postcode":"62118",
    "sg:province":"Nord Pas-de-Calais",
    "wof:name":"Desmazi\u00e8res Artois Bapaume S.a.",
    "wof:placetype":"venue"
},
  "geometry": {"coordinates":[2.94502,50.310165],"type":"Point"}
}