{
  "type": "Feature",
  "properties": {
    "iso:country":"FR",
    "sg:address":"2, Rue Capricorne, 94150 Rungis",
    "sg:orig_category":"Non-Classified Establishments",
    "sg:phone":"+33 1 41 80 31 80",
    "sg:province":"Ile de France",
    "wof:name":"Lasermatic S.a.",
    "wof:placetype":"venue"
},
  "geometry": {"coordinates":[2.358325,48.744129],"type":"Point"}
}