{
  "type": "Feature",
  "properties": {
    "iso:country":"FR",
    "sg:address":"Garonor Tour D",
    "sg:city":"Aulnay sous Bois",
    "sg:orig_category":"Unclassifiable Establishments",
    "sg:phone":"+33 1 48 62 81 75",
    "sg:postcode":"93620",
    "sg:province":"Pays de Loire",
    "wof:name":"Avia Partener Cargo S.a.s.",
    "wof:placetype":"venue"
},
  "geometry": {"coordinates":[2.472009,48.962227],"type":"Point"}
}