{
  "type": "Feature",
  "properties": {
    "iso:country":"FR",
    "sg:address":"Zac Mas De Grille 34430 St Jean De Vedas",
    "sg:classifiers":[
        {
            "category":"Professional",
            "subcategory":"Engineering",
            "type":"Services"
        }
    ],
    "sg:phone":"+33 825 30 06 00",
    "sg:postcode":"34430",
    "sg:province":"Languedoc-Roussillon",
    "sg:tags":[
        "machine",
        "-",
        "mechanical"
    ],
    "wof:name":"Sas Auzet",
    "wof:placetype":"venue"
},
  "geometry": {"coordinates":[3.8289,43.575985],"type":"Point"}
}