{
  "type": "Feature",
  "properties": {
    "addr:full":"38 Avenue Orgeval 91360 Villemoisson Sur Orge Ile de France",
    "addr:housenumber":"38",
    "addr:postcode":"91360",
    "addr:street":"Avenue",
    "iso:country":"FR",
    "sg:address":"38 Avenue Orgeval 91360 Villemoisson Sur Orge",
    "sg:classifiers":[
        {
            "category":"Manufacturing",
            "subcategory":"Printing",
            "type":"Manufacturing & Wholesale Goods"
        }
    ],
    "sg:phone":"+33 1 69 51 51 11",
    "sg:province":"Ile de France",
    "sg:tags":[
        "publishing"
    ],
    "wof:name":"Diamand Graphic Sarl",
    "wof:placetype":"venue"
},
  "geometry": {"coordinates":[2.335892,48.656986],"type":"Point"}
}