{
  "type": "Feature",
  "properties": {
    "addr:full":"Rte d'Avignon Entraigues sur la Sorgue Provence-Alpes-C\u00f4te d'Azur 84320",
    "addr:postcode":"84320",
    "addr:street":"Rte D'Avignon Entraigues;La Sorgue",
    "iso:country":"FR",
    "sg:address":"Rte d'Avignon",
    "sg:city":"Entraigues sur la Sorgue",
    "sg:orig_category":"Unclassifiable Establishments",
    "sg:phone":"+33 4 90 83 18 64",
    "sg:postcode":"84320",
    "sg:province":"Provence-Alpes-C\u00f4te d'Azur",
    "wof:name":"Stores Moliner S.a.",
    "wof:placetype":"venue"
},
  "geometry": {"coordinates":[4.919942,43.999863],"type":"Point"}
}