{
  "type": "Feature",
  "properties": {
    "addr:full":"B.P. 293, 78053 Saint Quentin en Yvelines C\u00e9dex^^4, Rue des Charmes - Zone d'Activit\u00e9s du Buisson de Bourgogne",
    "addr:housenumber":"b.p. 293",
    "addr:postcode":"78053",
    "addr:street":"Rue Des Charmes Zone D'Activite \u0301S Du Buisson De",
    "iso:country":"FR",
    "sg:address":"B.P. 293, 78053 Saint Quentin en Yvelines C\u00e9dex^^4, Rue des Charmes - Zone d'Activit\u00e9s du Buisson de",
    "sg:orig_category":"Non-Classified Establishments",
    "sg:phone":"+33 1 30 16 23 23",
    "sg:province":"Bourgogne",
    "wof:name":"Culligan France S.a.",
    "wof:placetype":"venue"
},
  "geometry": {"coordinates":[2.044,48.786594],"type":"Point"}
}