{
  "type": "Feature",
  "properties": {
    "addr:full":"Cauchire 33720 Budos Budos Aquitaine 33720",
    "addr:postcode":"33720;33720",
    "addr:street":"Cauchire",
    "iso:country":"FR",
    "sg:address":"Cauchire 33720 Budos",
    "sg:city":"Budos",
    "sg:orig_category":"Unclassifiable Establishments",
    "sg:phone":"+33 5 56 62 43 45",
    "sg:postcode":"33720",
    "sg:province":"Aquitaine",
    "wof:name":"Zausa Yannick",
    "wof:placetype":"venue"
},
  "geometry": {"coordinates":[-0.392974,44.548531],"type":"Point"}
}