{
  "type": "Feature",
  "properties": {
    "iso:country":"FR",
    "sg:address":"215, Av. Georges Cl\u00e9menceau - Le Cl\u00e9menceau II, 92024 Nanterre C\u00e9dex",
    "sg:orig_category":"Non-Classified Establishments",
    "sg:phone":"+33 1 41 37 67 67",
    "sg:province":"\u00cele-de-France",
    "wof:name":"Infocom Informatique S.a.",
    "wof:placetype":"venue"
},
  "geometry": {"coordinates":[2.208,48.896141],"type":"Point"}
}