{
  "type": "Feature",
  "properties": {
    "iso:country":"FR",
    "sg:address":"Zi Point Sud 65260 Soulom",
    "sg:classifiers":[
        {
            "category":"Shopping",
            "subcategory":"Bicycles & Sporting Goods",
            "type":"Retail Goods"
        }
    ],
    "sg:phone":"+33 5 62 92 20 18",
    "sg:postcode":"65260",
    "sg:province":"Midi Pyr\u00e9n\u00e9es",
    "sg:tags":[
        "product",
        "sport",
        "miscellaneous"
    ],
    "wof:name":"Nervures Sarl",
    "wof:placetype":"venue"
},
  "geometry": {"coordinates":[-0.074254,42.956646],"type":"Point"}
}