{
  "type": "Feature",
  "properties": {
    "addr:full":"28 Rue Aum\u00f4nerie 79600 Airvault Poitou-Charentes",
    "addr:housenumber":"28",
    "addr:postcode":"79600",
    "addr:street":"Rue Aumo\u0302Nerie",
    "iso:country":"FR",
    "sg:address":"28 Rue Aum\u00f4nerie 79600 Airvault",
    "sg:classifiers":[
        {
            "category":"Professional",
            "type":"Services"
        }
    ],
    "sg:phone":"+33 5 49 64 71 25",
    "sg:province":"Poitou-Charentes",
    "sg:tags":[
        "transport",
        "road"
    ],
    "wof:name":"Pierre Larricq Sa",
    "wof:placetype":"venue"
},
  "geometry": {"coordinates":[-0.133769,46.82048],"type":"Point"}
}