{
  "type": "Feature",
  "properties": {
    "addr:full":"9 Rue D Alsace 71500 Louhans Louhans Bourgogne 71500",
    "addr:housenumber":"9",
    "addr:postcode":"71500;71500",
    "addr:street":"Rue D",
    "iso:country":"FR",
    "sg:address":"9 Rue D Alsace 71500 Louhans",
    "sg:city":"Louhans",
    "sg:classifiers":[
        {
            "category":"Professional",
            "subcategory":"Printing & Photocopies",
            "type":"Services"
        }
    ],
    "sg:phone":"+33 3 85 75 22 49",
    "sg:postcode":"71500",
    "sg:province":"Bourgogne",
    "sg:tags":[
        "publishing"
    ],
    "wof:name":"Les Journaux De Saone Et Loire (jsl)",
    "wof:placetype":"venue"
},
  "geometry": {"coordinates":[5.226603,46.630165],"type":"Point"}
}