{
  "type": "Feature",
  "properties": {
    "iso:country":"FR",
    "sg:address":"12 Rue De L Industrie 51350 Cormontreuil",
    "sg:classifiers":[
        {
            "category":"Autos & Motor Vehicles",
            "subcategory":"Automobile Sales",
            "type":"Retail Goods"
        }
    ],
    "sg:phone":"+33 3 26 50 32 42",
    "sg:postcode":"51350",
    "sg:province":"Champagne",
    "sg:tags":[
        "equipment",
        "industrial",
        "transport"
    ],
    "wof:name":"General Trailers France (gt)",
    "wof:placetype":"venue"
},
  "geometry": {"coordinates":[4.06747,49.217365],"type":"Point"}
}