{
  "type": "Feature",
  "properties": {
    "addr:full":"ZI Saint Eloi Nevers Bourgogne 58000",
    "addr:postcode":"58000",
    "addr:street":"Saint Eloi;Bourgogne",
    "iso:country":"FR",
    "sg:address":"ZI Saint Eloi",
    "sg:city":"Nevers",
    "sg:orig_category":"Unclassifiable Establishments",
    "sg:phone":"+33 3 86 60 65 65",
    "sg:postcode":"58000",
    "sg:province":"Bourgogne",
    "wof:name":"Facom S.a.",
    "wof:placetype":"venue"
},
  "geometry": {"coordinates":[3.15725,46.988964],"type":"Point"}
}