{
  "type": "Feature",
  "properties": {
    "iso:country":"FR",
    "sg:address":"chemin de la Poulvarel 30210 SERNHAC",
    "sg:classifiers":[
        {
            "category":"Manufacturing",
            "subcategory":"Textiles",
            "type":"Manufacturing & Wholesale Goods"
        }
    ],
    "sg:phone":"+33 4 66 37 08 20",
    "sg:postcode":"30210",
    "sg:province":"Languedoc-Roussillon",
    "sg:tags":[
        "non-woven",
        "industrial",
        "fabric",
        "processing"
    ],
    "wof:name":"Sirtex S.a.r.l.",
    "wof:placetype":"venue"
},
  "geometry": {"coordinates":[4.551335,43.910404],"type":"Point"}
}