{
  "type": "Feature",
  "properties": {
    "iso:country":"FR",
    "sg:address":"30 chemin Du Bois Des Arpents 78860 ST NOM LA BRETECHE",
    "sg:classifiers":[
        {
            "category":"Health Services",
            "subcategory":"Medical Lab",
            "type":"Services"
        }
    ],
    "sg:phone":"+33 1 30 56 64 01",
    "sg:postcode":"78860",
    "sg:province":"Ile de France",
    "sg:tags":[
        "laboratory",
        "accessory"
    ],
    "wof:name":"Interlab S.a.r.l.",
    "wof:placetype":"venue"
},
  "geometry": {"coordinates":[2.014141,48.870396],"type":"Point"}
}