{
  "type": "Feature",
  "properties": {
    "iso:country":"FR",
    "sg:address":"487 rue H\u00e9l\u00e8ne Boucher 34130 Mauguio",
    "sg:classifiers":[
        {
            "category":"Bars & Pubs",
            "subcategory":"Hookah Bar",
            "type":"Food & Drink"
        }
    ],
    "sg:phone":"+33 4 67 83 63 38",
    "sg:postcode":"34130",
    "sg:province":"Languedoc-Roussillon",
    "sg:tags":[
        "tub",
        "massage",
        "bath"
    ],
    "wof:name":"B.d.h. Sarl",
    "wof:placetype":"venue"
},
  "geometry": {"coordinates":[3.941062,43.58424],"type":"Point"}
}