{
  "type": "Feature",
  "properties": {
    "iso:country":"FR",
    "sg:address":"37110 CHATEAU RENAULT",
    "sg:city":"Autr\u00e8che",
    "sg:classifiers":[
        {
            "category":"Banks & Credit Unions",
            "subcategory":"Investment Brokerage",
            "type":"Services"
        }
    ],
    "sg:phone":"+33 2 47 29 86 60",
    "sg:postcode":"37110",
    "sg:province":"Centre",
    "sg:tags":[
        "accessory",
        "high-fashion"
    ],
    "wof:name":"Maurice Boinet S.a.",
    "wof:placetype":"venue"
},
  "geometry": {"coordinates":[0.91292,47.59214],"type":"Point"}
}