{
  "type": "Feature",
  "properties": {
    "addr:full":"38, Rue Anatole France, 92594 Levallois Perret C\u00e9dex Aquitaine",
    "addr:housenumber":"38",
    "addr:postcode":"92594",
    "addr:street":"Rue Anatole France",
    "iso:country":"FR",
    "sg:address":"38, Rue Anatole France, 92594 Levallois Perret C\u00e9dex",
    "sg:orig_category":"Non-Classified Establishments",
    "sg:phone":"+33 1 41 49 09 09",
    "sg:province":"Aquitaine",
    "wof:name":"Business Soft S.a.",
    "wof:placetype":"venue"
},
  "geometry": {"coordinates":[2.287076,48.89011],"type":"Point"}
}