{
  "type": "Feature",
  "properties": {
    "addr:full":"3, Rue Remblai - Zone de Fret 3, 93290 Tremblay en France Ile de France",
    "addr:housenumber":"3;3",
    "addr:postcode":"93290",
    "addr:street":"Rue Remblai Zone De Fret",
    "iso:country":"FR",
    "sg:address":"3, Rue Remblai - Zone de Fret 3, 93290 Tremblay en France",
    "sg:orig_category":"Unclassifiable Establishments",
    "sg:phone":"+33 1 49 19 10 10",
    "sg:province":"Ile de France",
    "wof:name":"Scac Air Service S.a.",
    "wof:placetype":"venue"
},
  "geometry": {"coordinates":[2.56727,48.951214],"type":"Point"}
}