{
  "type": "Feature",
  "properties": {
    "iso:country":"FR",
    "sg:address":"4 Rue De Charenton 94140 Alfortville",
    "sg:classifiers":[
        {
            "category":"Professional",
            "subcategory":"Advertising",
            "type":"Services"
        }
    ],
    "sg:phone":"+33 1 45 18 71 00",
    "sg:postcode":"94140",
    "sg:province":"Ile de France",
    "sg:tags":[
        "marketing",
        "medium",
        "communication"
    ],
    "wof:name":"Phone City European Research Center Sarl",
    "wof:placetype":"venue"
},
  "geometry": {"coordinates":[2.411725,48.814114],"type":"Point"}
}