{
  "type": "Feature",
  "properties": {
    "addr:full":"B.P. 23, 59510 Hem^^280, Rue Jules Guesde, 59510 Hem Nord Pas-de-Calais",
    "addr:postcode":"59510;59510",
    "addr:street":"B.P. 23;Rue Jules Guesde",
    "iso:country":"FR",
    "sg:address":"B.P. 23, 59510 Hem^^280, Rue Jules Guesde, 59510 Hem",
    "sg:orig_category":"Non-Classified Establishments",
    "sg:phone":"+33 3 20 75 65 07",
    "sg:province":"Nord Pas-de-Calais",
    "wof:name":"Modern D\u00e9cor S.a.",
    "wof:placetype":"venue"
},
  "geometry": {"coordinates":[3.184105,50.653839],"type":"Point"}
}