{
  "type": "Feature",
  "properties": {
    "iso:country":"FR",
    "sg:address":"Av. de la Mer - Espace Imbert",
    "sg:city":"P\u00e9rols",
    "sg:orig_category":"Unclassifiable Establishments",
    "sg:phone":"+33 4 66 68 76 87",
    "sg:postcode":"34470",
    "sg:province":"Languedoc-Roussillon",
    "wof:name":"S.m.b. S.a.",
    "wof:placetype":"venue"
},
  "geometry": {"coordinates":[3.95078,43.562229],"type":"Point"}
}