{
  "type": "Feature",
  "properties": {
    "addr:full":"4, All\u00e9e du 1er Mai 1945 - ZAC Paris Est, 77183 Croissy Beaubourg Ile de France",
    "addr:housenumber":"4",
    "addr:postcode":"77183",
    "addr:street":"Alle\u0301E Du 1Er Mai 1945 Zac",
    "iso:country":"FR",
    "sg:address":"4, All\u00e9e du 1er Mai 1945 - ZAC Paris Est, 77183 Croissy Beaubourg",
    "sg:orig_category":"Non-Classified Establishments",
    "sg:phone":"+33 1 60 95 45 10",
    "sg:province":"Ile de France",
    "wof:name":"Transports Graveleau S.a.",
    "wof:placetype":"venue"
},
  "geometry": {"coordinates":[2.636174,48.824478],"type":"Point"}
}