{
  "type": "Feature",
  "properties": {
    "iso:country":"FR",
    "sg:address":"3 bis, Bd de l'Industrie, 35730 Pleurtuit",
    "sg:city":"Pleurtuit",
    "sg:orig_category":"Unclassifiable Establishments",
    "sg:phone":"+33 2 99 41 43 46",
    "sg:postcode":"35730",
    "sg:province":"Bretagne",
    "wof:name":"Entreprise Marc S.a.",
    "wof:placetype":"venue"
},
  "geometry": {"coordinates":[-2.058573,48.572117],"type":"Point"}
}