{
  "type": "Feature",
  "properties": {
    "iso:country":"FR",
    "sg:address":"Belle Vue 85110 Ste Cecile",
    "sg:classifiers":[
        {
            "category":"Wholesale",
            "subcategory":"Farm Supplies",
            "type":"Manufacturing & Wholesale Goods"
        }
    ],
    "sg:phone":"+33 2 51 48 51 51",
    "sg:postcode":"85110",
    "sg:province":"Pays de Loire",
    "sg:tags":[
        "-",
        "machine",
        "equipment",
        "engineering",
        "machinery",
        "mechanical",
        "agriculture"
    ],
    "wof:name":"Rabaud Sa",
    "wof:placetype":"venue"
},
  "geometry": {"coordinates":[-1.099997,46.738289],"type":"Point"}
}