{
  "type": "Feature",
  "properties": {
    "addr:full":"Violet 11160 Rieux Minervois Languedoc-Roussillon",
    "addr:postcode":"11160",
    "addr:street":"Violet",
    "iso:country":"FR",
    "sg:address":"Violet 11160 Rieux Minervois",
    "sg:orig_category":"Non-Classified Establishments",
    "sg:phone":"+33 4 68 78 22 14",
    "sg:province":"Languedoc-Roussillon",
    "wof:name":"Les Celliers Jean D'alibert S.a.",
    "wof:placetype":"venue"
},
  "geometry": {"coordinates":[2.586085,43.282204],"type":"Point"}
}