{
  "type": "Feature",
  "properties": {
    "iso:country":"FR",
    "sg:address":"5 Bis Rue Ladres 36100 Issoudun",
    "sg:city":"Issoudun",
    "sg:classifiers":[
        {
            "category":"Shopping",
            "subcategory":"Clothing, Apparel, & Fashions",
            "type":"Retail Goods"
        }
    ],
    "sg:phone":"+33 2 54 21 04 15",
    "sg:postcode":"36100",
    "sg:province":"Centre",
    "sg:tags":[
        "textile",
        "clothing",
        "clothes"
    ],
    "wof:name":"Manufacture Issoudunoise De Confection",
    "wof:placetype":"venue"
},
  "geometry": {"coordinates":[1.99898,46.946312],"type":"Point"}
}