{
  "type": "Feature",
  "properties": {
    "iso:country":"FR",
    "sg:address":"Parc Technologique des Fontaines",
    "sg:city":"Bernin",
    "sg:orig_category":"Non-Classified Establishments",
    "sg:phone":"+33 4 76 92 75 00",
    "sg:postcode":"38190",
    "sg:province":"Rhone-Alpes",
    "wof:name":"Soitec S.a. - Silicon On Insulator Technologie",
    "wof:placetype":"venue"
},
  "geometry": {"coordinates":[5.866393,45.269234],"type":"Point"}
}