{
  "type": "Feature",
  "properties": {
    "iso:country":"FR",
    "sg:address":"Zi Maladonnes 26700 Pierrelatte",
    "sg:classifiers":[
        {
            "category":"Wholesale",
            "subcategory":"Metals & Minerals",
            "type":"Manufacturing & Wholesale Goods"
        }
    ],
    "sg:phone":"+33 4 75 04 25 91",
    "sg:postcode":"26700",
    "sg:province":"Rhone-Alpes",
    "sg:tags":[
        "steel",
        "metallurgy",
        "tool",
        "metalworking"
    ],
    "wof:name":"Rozier Aime (quincaillerie) Sa",
    "wof:placetype":"venue"
},
  "geometry": {"coordinates":[4.69703,44.375584],"type":"Point"}
}