{
  "type": "Feature",
  "properties": {
    "addr:full":"Rue du Donjon Thionville Lorraine 57100",
    "addr:postcode":"57100",
    "addr:street":"Rue Du Donjon",
    "iso:country":"FR",
    "sg:address":"Rue du Donjon",
    "sg:city":"Thionville",
    "sg:orig_category":"Unclassifiable Establishments",
    "sg:phone":"+33 3 82 59 60 70",
    "sg:postcode":"57100",
    "sg:province":"Lorraine",
    "wof:name":"C.a.t. A.p.e.i. De Thionville",
    "wof:placetype":"venue"
},
  "geometry": {"coordinates":[6.091375,49.364601],"type":"Point"}
}