{
  "type": "Feature",
  "properties": {
    "iso:country":"FR",
    "sg:address":"17 Rue Des Ecoles 25560 Courvi\u00e8res",
    "sg:classifiers":[
        {
            "category":"Manufacturing",
            "subcategory":"Wood Products",
            "type":"Manufacturing & Wholesale Goods"
        }
    ],
    "sg:phone":"+33 3 81 49 38 51",
    "sg:province":"Franche Comt\u00e9",
    "sg:tags":[
        "furniture"
    ],
    "wof:name":"Scierie Regnaud Sarl",
    "wof:placetype":"venue"
},
  "geometry": {"coordinates":[6.109284,46.869221],"type":"Point"}
}