{
  "type": "Feature",
  "properties": {
    "addr:full":"131 Av Georges Pompidou 19100 Brive La Gaillarde Limousin 19100",
    "addr:postcode":"19100;19100",
    "addr:street":"131 Av Georges Pompidou",
    "iso:country":"FR",
    "sg:address":"131 Av Georges Pompidou 19100 Brive La Gaillarde",
    "sg:classifiers":[
        {
            "category":"Bakery",
            "type":"Food & Drink"
        }
    ],
    "sg:phone":"+33 5 55 24 09 14",
    "sg:postcode":"19100",
    "sg:province":"Limousin",
    "sg:tags":[
        "cake",
        "product",
        "related",
        "bread"
    ],
    "wof:name":"Le Pain Campagnard",
    "wof:placetype":"venue"
},
  "geometry": {"coordinates":[1.553213,45.158058],"type":"Point"}
}