{
  "type": "Feature",
  "properties": {
    "iso:country":"FR",
    "sg:address":"37 Rue Jules Guesde 59160 Lomme",
    "sg:classifiers":[
        {
            "category":"Home & Garden",
            "subcategory":"Furniture",
            "type":"Retail Goods"
        }
    ],
    "sg:phone":"+33 3 20 00 70 00",
    "sg:province":"Nord Pas-de-Calais",
    "sg:tags":[
        "wood"
    ],
    "wof:name":"Sarl Euro Pvc",
    "wof:placetype":"venue"
},
  "geometry": {"coordinates":[2.998337,50.645493],"type":"Point"}
}