{
  "type": "Feature",
  "properties": {
    "iso:country":"FR",
    "sg:address":"41 Avenue Jean Jaures 46200 SOUILLAC",
    "sg:classifiers":[
        {
            "category":"Utilities",
            "subcategory":"Water",
            "type":"Services"
        }
    ],
    "sg:phone":"+33 5 65 32 78 16",
    "sg:postcode":"46200",
    "sg:province":"Midi Pyr\u00e9n\u00e9es",
    "sg:tags":[
        "waters",
        "natural",
        "mineral"
    ],
    "wof:name":"Distillerie Louis Roque S.a.",
    "wof:placetype":"venue"
},
  "geometry": {"coordinates":[1.473338,44.899376],"type":"Point"}
}