{
  "type": "Feature",
  "properties": {
    "iso:country":"FR",
    "sg:address":"5 Boulevard Pierre Lecoq La Novatheque",
    "sg:city":"Cholet",
    "sg:classifiers":[
        {
            "category":"Banks & Credit Unions",
            "subcategory":"Financial Services",
            "type":"Services"
        }
    ],
    "sg:phone":"+33 2 41 75 20 50",
    "sg:postcode":"49300",
    "sg:province":"Pays de Loire",
    "sg:tags":[
        "banking",
        "finance",
        "insurance"
    ],
    "wof:name":"Societe Fiduciaire D'expertise Comptable De Gestion Et De Re (socogere)",
    "wof:placetype":"venue"
},
  "geometry": {"coordinates":[-0.892689,46.99659],"type":"Point"}
}