{
  "type": "Feature",
  "properties": {
    "iso:country":"FR",
    "sg:address":"81660 Bout du Pont de Larn",
    "sg:orig_category":"Non-Classified Establishments",
    "sg:phone":"+33 5 63 98 68 29",
    "sg:province":"Midi Pyr\u00e9n\u00e9es",
    "wof:name":"Soprefil S.a.r.l.",
    "wof:placetype":"venue"
},
  "geometry": {"coordinates":[2.406587,43.502777],"type":"Point"}
}