{
  "type": "Feature",
  "properties": {
    "iso:country":"FR",
    "sg:address":"16250 Jurignac",
    "sg:orig_category":"Unclassifiable Establishments",
    "sg:phone":"+33 5 45 64 99 38",
    "sg:province":"Poitou-Charentes",
    "wof:name":"P.s.a. S.a. - Piveteau Services Agricoles",
    "wof:placetype":"venue"
},
  "geometry": {"coordinates":[-0.039234,45.534401],"type":"Point"}
}