{
  "type": "Feature",
  "properties": {
    "iso:country":"FR",
    "sg:address":"25 bis, Av. du Petit Parc, 94306 Vincennes C\u00e9dex",
    "sg:orig_category":"Non-Classified Establishments",
    "sg:phone":"+33 2 37 28 28 08",
    "sg:province":"Ile-de-France",
    "wof:name":"Wescho Int\u00e9rieur S.a.r.l.",
    "wof:placetype":"venue"
},
  "geometry": {"coordinates":[2.42851,48.843449],"type":"Point"}
}