{
  "type": "Feature",
  "properties": {
    "addr:full":"8, Rue de la Mare, 50200 Coutances Coutances Basse Normandie 50200",
    "addr:housenumber":"8",
    "addr:postcode":"50200;50200",
    "addr:street":"Rue De La Mare",
    "iso:country":"FR",
    "sg:address":"8, Rue de la Mare, 50200 Coutances",
    "sg:city":"Coutances",
    "sg:orig_category":"Non-Classified Establishments",
    "sg:phone":"+33 2 33 45 31 94",
    "sg:postcode":"50200",
    "sg:province":"Basse Normandie",
    "wof:name":"Imprimerie Garlan S.a.r.l.",
    "wof:placetype":"venue"
},
  "geometry": {"coordinates":[-1.430163,49.060356],"type":"Point"}
}