{
  "type": "Feature",
  "properties": {
    "iso:country":"FR",
    "sg:address":"Rue de Dion Bouton",
    "sg:city":"Limoges",
    "sg:orig_category":"Non-Classified Establishments",
    "sg:phone":"+33 5 55 37 70 39",
    "sg:postcode":"87280",
    "sg:province":"Limousin",
    "wof:name":"S.c.r. Leblond S.n.c.",
    "wof:placetype":"venue"
},
  "geometry": {"coordinates":[1.27495,45.883949],"type":"Point"}
}