{
  "type": "Feature",
  "properties": {
    "addr:full":"110 Av Du M\u00f4le 74460 Marnaz Rhone-Alpes 74460",
    "addr:housenumber":"110",
    "addr:postcode":"74460;74460",
    "addr:street":"Av Du Mo\u0302Le;Rhone-Alpes",
    "iso:country":"FR",
    "sg:address":"110 Av Du M\u00f4le 74460 Marnaz",
    "sg:classifiers":[
        {
            "category":"Manufacturing",
            "subcategory":"Metals",
            "type":"Manufacturing & Wholesale Goods"
        }
    ],
    "sg:phone":"+33 4 50 98 32 66",
    "sg:postcode":"74460",
    "sg:province":"Rhone-Alpes",
    "sg:tags":[
        "-",
        "machine",
        "equipment",
        "engineering",
        "machinery",
        "mechanical"
    ],
    "wof:name":"Technicoutils Sa",
    "wof:placetype":"venue"
},
  "geometry": {"coordinates":[6.527375,46.072041],"type":"Point"}
}