{
  "type": "Feature",
  "properties": {
    "addr:full":"71 Avenue Jean Jaures 72500 Chateau Du Loir Pays de Loire 72500",
    "addr:housenumber":"71",
    "addr:postcode":"72500;72500",
    "addr:street":"Avenue Jean Jaures;Chateau Du Loir",
    "iso:country":"FR",
    "sg:address":"71 Avenue Jean Jaures 72500 Chateau Du Loir",
    "sg:classifiers":[
        {
            "category":"Wholesale",
            "subcategory":"Farm Supplies",
            "type":"Manufacturing & Wholesale Goods"
        }
    ],
    "sg:phone":"+33 2 43 44 00 94",
    "sg:postcode":"72500",
    "sg:province":"Pays de Loire",
    "sg:tags":[
        "-",
        "machine",
        "equipment",
        "engineering",
        "machinery",
        "mechanical",
        "agriculture"
    ],
    "wof:name":"Societe Rolland Chateau Du Loir Src",
    "wof:placetype":"venue"
},
  "geometry": {"coordinates":[0.41715,47.693699],"type":"Point"}
}