{
  "type": "Feature",
  "properties": {
    "iso:country":"FR",
    "sg:address":"380, Bd Charles de Gaulle, 37540 Saint Cyr sur Loire",
    "sg:city":"Saint-Cyr-sur-Loire",
    "sg:orig_category":"Unclassifiable Establishments",
    "sg:phone":"+33 2 47 54 55 98",
    "sg:postcode":"37540",
    "sg:province":"Centre",
    "wof:name":"Isogard S.a.s.",
    "wof:placetype":"venue"
},
  "geometry": {"coordinates":[0.646828,47.429165],"type":"Point"}
}