{
  "type": "Feature",
  "properties": {
    "addr:full":"4 Quai D'Aval 60100 Creil Picardie 60100",
    "addr:housenumber":"4",
    "addr:postcode":"60100;60100",
    "addr:street":"Quai D'Aval",
    "iso:country":"FR",
    "sg:address":"4 Quai D'Aval 60100 Creil",
    "sg:classifiers":[
        {
            "category":"Professional",
            "subcategory":"Engineering",
            "type":"Services"
        }
    ],
    "sg:phone":"+33 3 44 55 21 99",
    "sg:postcode":"60100",
    "sg:province":"Picardie",
    "sg:tags":[
        "machine",
        "-",
        "mechanical"
    ],
    "wof:name":"Domoservices Maintenance",
    "wof:placetype":"venue"
},
  "geometry": {"coordinates":[2.462603,49.256817],"type":"Point"}
}