{
  "type": "Feature",
  "properties": {
    "addr:full":"ZA les Beluzes Pouilly sous Charlieu Rhone-Alpes 42720",
    "addr:postcode":"42720",
    "addr:street":"Za Les Beluzes",
    "iso:country":"FR",
    "sg:address":"ZA les Beluzes",
    "sg:city":"Pouilly sous Charlieu",
    "sg:orig_category":"Non-Classified Establishments",
    "sg:phone":"+33 4 77 69 30 00",
    "sg:postcode":"42720",
    "sg:province":"Rhone-Alpes",
    "wof:name":"Soci\u00e9t\u00e9 De Val De Seille S.a.",
    "wof:placetype":"venue"
},
  "geometry": {"coordinates":[4.1084,46.145191],"type":"Point"}
}