{
  "type": "Feature",
  "properties": {
    "iso:country":"FR",
    "sg:address":"Champ Des H\u00e2tes 58200 St Loup",
    "sg:city":"Cosne-Cours-sur-Loire",
    "sg:classifiers":[
        {
            "category":"Wholesale",
            "subcategory":"Farm Supplies",
            "type":"Manufacturing & Wholesale Goods"
        }
    ],
    "sg:phone":"+33 3 86 26 24 49",
    "sg:postcode":"58200",
    "sg:province":"Bourgogne",
    "sg:tags":[
        "-",
        "machine",
        "equipment",
        "engineering",
        "machinery",
        "mechanical",
        "agriculture"
    ],
    "wof:name":"Poirier Sa",
    "wof:placetype":"venue"
},
  "geometry": {"coordinates":[2.901115,47.369862],"type":"Point"}
}