{
  "type": "Feature",
  "properties": {
    "iso:country":"FR",
    "sg:address":"41",
    "sg:city":"Anatole France 83700 Saint Rapha\u00ebl",
    "sg:classifiers":[
        {
            "category":"Professional",
            "type":"Services"
        }
    ],
    "sg:phone":"+33 4 94 95 00 12",
    "sg:province":"Aquitaine",
    "sg:tags":[
        "transport",
        "road"
    ],
    "wof:name":"Demeco Demenagement Porre Adherent",
    "wof:placetype":"venue"
},
  "geometry": {"coordinates":[6.77048,43.424522],"type":"Point"}
}