{
  "type": "Feature",
  "properties": {
    "iso:country":"FR",
    "sg:address":"R Jean Mln Imm Le Vaillant Lotissement A 2 93350 Le Bourget",
    "sg:classifiers":[
        {
            "category":"Professional",
            "subcategory":"Engineering",
            "type":"Services"
        }
    ],
    "sg:phone":"+33 1 43 11 22 57",
    "sg:postcode":"93350",
    "sg:province":"Ile de France",
    "sg:tags":[
        "machine",
        "-",
        "mechanical"
    ],
    "wof:name":"Froid Service 95",
    "wof:placetype":"venue"
},
  "geometry": {"coordinates":[2.43559,48.936787],"type":"Point"}
}