{
  "type": "Feature",
  "properties": {
    "iso:country":"FR",
    "sg:address":"6, Av. de Fondeyre, 31200 Toulouse",
    "sg:orig_category":"Non-Classified Establishments",
    "sg:phone":"+33 5 62 72 41 00",
    "sg:province":"Midi Pyr\u00e9n\u00e9es",
    "wof:name":"Laussuy Messagerie.",
    "wof:placetype":"venue"
},
  "geometry": {"coordinates":[1.427662,43.642616],"type":"Point"}
}