{
  "type": "Feature",
  "properties": {
    "addr:full":"45 bis rue du General de Gaulle 59225 Clary Nord Pas-de-Calais 59225",
    "addr:housenumber":"45 bis",
    "addr:postcode":"59225;59225",
    "addr:street":"Rue Du General De Gaulle;Clary Nord",
    "iso:country":"FR",
    "sg:address":"45 bis rue du General de Gaulle 59225 Clary",
    "sg:classifiers":[
        {
            "category":"Professional",
            "subcategory":"Printing & Photocopies",
            "type":"Services"
        }
    ],
    "sg:phone":"+33 3 27 85 16 54",
    "sg:postcode":"59225",
    "sg:province":"Nord Pas-de-Calais",
    "sg:tags":[
        "embroidery"
    ],
    "wof:name":"Clarbrod Sarl",
    "wof:placetype":"venue"
},
  "geometry": {"coordinates":[3.39853,50.071377],"type":"Point"}
}