{
  "type": "Feature",
  "properties": {
    "addr:full":"Chemin du Ch\u00eane Vert - ZAC de la Bourgade Lab\u00e8ge Midi Pyr\u00e9n\u00e9es 31670",
    "addr:postcode":"31670",
    "addr:street":"Chemin Du Che\u0302Ne Vert Zac De La Bourgade",
    "iso:country":"FR",
    "sg:address":"Chemin du Ch\u00eane Vert - ZAC de la Bourgade",
    "sg:city":"Lab\u00e8ge",
    "sg:orig_category":"Unclassifiable Establishments",
    "sg:phone":"+33 5 61 00 71 71",
    "sg:postcode":"31670",
    "sg:province":"Midi Pyr\u00e9n\u00e9es",
    "wof:name":"Biovector Th\u00e9rapeutics S.a.",
    "wof:placetype":"venue"
},
  "geometry": {"coordinates":[1.527111,43.529713],"type":"Point"}
}