{
  "type": "Feature",
  "properties": {
    "addr:full":"B.P. 41, 44220 Cou\u00ebron C\u00e9dex^^ZA la Tour \u00e0 Plomb, 44220 Cou\u00ebron Pays de Loire",
    "addr:postcode":"44220;44220",
    "addr:street":"B.P. 41",
    "iso:country":"FR",
    "sg:address":"B.P. 41, 44220 Cou\u00ebron C\u00e9dex^^ZA la Tour \u00e0 Plomb, 44220 Cou\u00ebron",
    "sg:orig_category":"Non-Classified Establishments",
    "sg:phone":"+33 2 40 38 38 28",
    "sg:province":"Pays de Loire",
    "wof:name":"S.a.c.m.o. S.a.",
    "wof:placetype":"venue"
},
  "geometry": {"coordinates":[-1.727234,47.210861],"type":"Point"}
}