{
  "type": "Feature",
  "properties": {
    "addr:full":"B.P. 4 Sourzac Aquitaine 24400",
    "addr:postcode":"24400",
    "addr:street":"B.P. 4 Sourzac",
    "iso:country":"FR",
    "sg:address":"B.P. 4",
    "sg:city":"Sourzac",
    "sg:orig_category":"Non-Classified Establishments",
    "sg:phone":"+33 5 53 81 01 84",
    "sg:postcode":"24400",
    "sg:province":"Aquitaine",
    "wof:name":"Meubles Ranouil S.a.r.l.",
    "wof:placetype":"venue"
},
  "geometry": {"coordinates":[0.426855,44.981491],"type":"Point"}
}