{
  "type": "Feature",
  "properties": {
    "addr:full":"101 Rue De Geilles 01100 Oyonnax Rhone-Alpes",
    "addr:housenumber":"101",
    "addr:postcode":"01100",
    "addr:street":"Rue De Geilles",
    "iso:country":"FR",
    "sg:address":"101 Rue De Geilles 01100 Oyonnax",
    "sg:classifiers":[
        {
            "category":"Manufacturing",
            "subcategory":"Rubber & Plastics",
            "type":"Manufacturing & Wholesale Goods"
        }
    ],
    "sg:phone":"+33 4 74 73 59 76",
    "sg:province":"Rhone-Alpes",
    "wof:name":"Etablissements Patrice Tabourin",
    "wof:placetype":"venue"
},
  "geometry": {"coordinates":[5.667267,46.240448],"type":"Point"}
}