{
  "type": "Feature",
  "properties": {
    "iso:country":"FR",
    "sg:address":"B.P. 47, 35410 Ch\u00e2teaugiron C\u00e9dex^^1, Rue des Tisserands - ZA Sainte Croix, 35410 Ch\u00e2teaugiron",
    "sg:city":"Ch\u00e2teaugiron",
    "sg:orig_category":"Non-Classified Establishments",
    "sg:phone":"+33 2 99 37 62 00",
    "sg:postcode":"35410",
    "sg:province":"Bretagne",
    "wof:name":"E.a.i. S.a.r.l. - Euro Air Instruments",
    "wof:placetype":"venue"
},
  "geometry": {"coordinates":[-1.499349,48.032745],"type":"Point"}
}