{
  "type": "Feature",
  "properties": {
    "addr:full":"1, Rue de la Vo\u00fbte du Ch\u00e2teau, 41000 Blois Blois Centre 41000",
    "addr:housenumber":"1",
    "addr:postcode":"41000;41000",
    "addr:street":"Rue De La Vou\u0302Te Du Cha\u0302Teau",
    "iso:country":"FR",
    "sg:address":"1, Rue de la Vo\u00fbte du Ch\u00e2teau, 41000 Blois",
    "sg:city":"Blois",
    "sg:orig_category":"Non-Classified Establishments",
    "sg:phone":"+33 2 54 78 04 43",
    "sg:postcode":"41000",
    "sg:province":"Centre",
    "wof:name":"Soci\u00e9t\u00e9 D'exploitation Des T\u00e2pisseries Langlois S.a.",
    "wof:placetype":"venue"
},
  "geometry": {"coordinates":[1.33061,47.586048],"type":"Point"}
}