{
  "type": "Feature",
  "properties": {
    "iso:country":"FR",
    "sg:address":"15, Rue Albert 1er, 42000 Saint Etienne",
    "sg:orig_category":"Non-Classified Establishments",
    "sg:phone":"+33 4 77 79 72 39",
    "sg:province":"Rhone-Alpes",
    "wof:name":"Tigra S.a.r.l.",
    "wof:placetype":"venue"
},
  "geometry": {"coordinates":[4.381638,45.449512],"type":"Point"}
}