{
  "type": "Feature",
  "properties": {
    "addr:full":"3 Bourse 75002 Paris Ile de France",
    "addr:housenumber":"3",
    "addr:postcode":"75002",
    "addr:street":"Bourse",
    "iso:country":"FR",
    "sg:address":"3",
    "sg:city":"Bourse 75002 Paris",
    "sg:classifiers":[
        {
            "category":"Utilities",
            "subcategory":"Telephone",
            "type":"Services"
        }
    ],
    "sg:phone":"+33 1 49 27 04 65",
    "sg:province":"Ile de France",
    "sg:tags":[
        "telecommunication"
    ],
    "wof:name":"Fileas",
    "wof:placetype":"venue"
},
  "geometry": {"coordinates":[2.339849,48.869289],"type":"Point"}
}