{
  "type": "Feature",
  "properties": {
    "addr:full":"38334 Saint Ismier C\u00e9dex^^176, Rue Lavoisier, 38330 Montbonnot Saint Martin Rhone-Alpes 38330",
    "addr:housenumber":"38334",
    "addr:postcode":"38330;38330",
    "addr:street":"Rue Lavoisier;Rhone-Alpes",
    "iso:country":"FR",
    "sg:address":"38334 Saint Ismier C\u00e9dex^^176, Rue Lavoisier, 38330 Montbonnot Saint Martin",
    "sg:orig_category":"Non-Classified Establishments",
    "sg:phone":"+33 4 76 41 44 00",
    "sg:postcode":"38330",
    "sg:province":"Rhone-Alpes",
    "wof:name":"Jay Sensors S.a.",
    "wof:placetype":"venue"
},
  "geometry": {"coordinates":[5.81127,45.217968],"type":"Point"}
}