{
  "type": "Feature",
  "properties": {
    "addr:full":"la Rivi\u00e8re - Soultrac Autoire Midi Pyr\u00e9n\u00e9es 46400",
    "addr:postcode":"46400",
    "iso:country":"FR",
    "sg:address":"la Rivi\u00e8re - Soultrac",
    "sg:city":"Autoire",
    "sg:orig_category":"Unclassifiable Establishments",
    "sg:phone":"+33 5 65 38 12 57",
    "sg:postcode":"46400",
    "sg:province":"Midi Pyr\u00e9n\u00e9es",
    "wof:name":"Jammes F. S.a.r.l.",
    "wof:placetype":"venue"
},
  "geometry": {"coordinates":[1.835101,44.868973],"type":"Point"}
}