{
  "type": "Feature",
  "properties": {
    "addr:full":"37 Avenue Baraduc 63140 Ch\u00e2telguyon Ch\u00e2telguyon Auvergne 63140",
    "addr:housenumber":"37",
    "addr:postcode":"63140;63140",
    "addr:street":"Avenue Baraduc",
    "iso:country":"FR",
    "sg:address":"37 Avenue Baraduc 63140 Ch\u00e2telguyon",
    "sg:city":"Ch\u00e2telguyon",
    "sg:classifiers":[
        {
            "category":"Travel",
            "subcategory":"Hotels & Motels",
            "type":"Entertainment"
        }
    ],
    "sg:phone":"+33 4 73 86 02 71",
    "sg:postcode":"63140",
    "sg:province":"Auvergne",
    "sg:tags":[
        "hotels",
        "business",
        "restaurant"
    ],
    "wof:name":"Hotel De L'univers Sarl",
    "wof:placetype":"venue"
},
  "geometry": {"coordinates":[3.064505,45.919525],"type":"Point"}
}