{
  "type": "Feature",
  "properties": {
    "iso:country":"FR",
    "sg:address":"23 Cd De Bethune Z.I. Du Petit Pacault 59660 Merville",
    "sg:classifiers":[
        {
            "category":"Food & Beverages",
            "subcategory":"Groceries & Convenience Stores",
            "type":"Retail Goods"
        }
    ],
    "sg:phone":"+33 3 28 42 94 94",
    "sg:postcode":"59660",
    "sg:province":"Nord Pas-de-Calais",
    "sg:tags":[
        "product",
        "related"
    ],
    "wof:name":"Clabo Conseil France",
    "wof:placetype":"venue"
},
  "geometry": {"coordinates":[2.64101,50.642799],"type":"Point"}
}