{
  "type": "Feature",
  "properties": {
    "iso:country":"FR",
    "sg:address":"47, Rue de Lorraine, 88190 Golbey",
    "sg:orig_category":"Non-Classified Establishments",
    "sg:phone":"+33 3 29 34 36 65",
    "sg:postcode":"88190",
    "sg:province":"Lorraine",
    "wof:name":"Ateliers D'epinal S.a.r.l.",
    "wof:placetype":"venue"
},
  "geometry": {"coordinates":[6.439194,48.201527],"type":"Point"}
}