{
  "type": "Feature",
  "properties": {
    "addr:full":"11 Rte Industrielle 68320 Kunheim Kunheim Alsace 68320",
    "addr:housenumber":"11",
    "addr:postcode":"68320;68320",
    "addr:street":"Rte Industrielle",
    "iso:country":"FR",
    "sg:address":"11 Rte Industrielle 68320 Kunheim",
    "sg:city":"Kunheim",
    "sg:classifiers":[
        {
            "category":"Manufacturing",
            "subcategory":"Paper Products",
            "type":"Manufacturing & Wholesale Goods"
        }
    ],
    "sg:phone":"+33 3 89 72 24 00",
    "sg:postcode":"68320",
    "sg:province":"Alsace",
    "sg:tags":[
        "raw",
        "material",
        "-",
        "cardboard"
    ],
    "wof:name":"Kaysersberg Packaging Sca",
    "wof:placetype":"venue"
},
  "geometry": {"coordinates":[7.42541,48.110287],"type":"Point"}
}