{
  "type": "Feature",
  "properties": {
    "addr:full":"Centre d'Activit\u00e9s du Haut Pont Saint Omer Nord Pas-de-Calais 62500",
    "addr:postcode":"62500",
    "addr:street":"Saint Omer Nord",
    "iso:country":"FR",
    "sg:address":"Centre d'Activit\u00e9s du Haut Pont",
    "sg:city":"Saint Omer",
    "sg:orig_category":"Non-Classified Establishments",
    "sg:phone":"+33 3 21 98 11 02",
    "sg:postcode":"62500",
    "sg:province":"Nord Pas-de-Calais",
    "wof:name":"Sameco S.a.",
    "wof:placetype":"venue"
},
  "geometry": {"coordinates":[3.156055,48.239918],"type":"Point"}
}