{
  "type": "Feature",
  "properties": {
    "iso:country":"FR",
    "sg:address":"32370 Espas",
    "sg:orig_category":"Unclassifiable Establishments",
    "sg:phone":"+33 5 62 08 54 96",
    "sg:province":"Midi Pyr\u00e9n\u00e9es",
    "wof:name":"Ferme De Lacoste - Marfaing Robert E.u.r.l.",
    "wof:placetype":"venue"
},
  "geometry": {"coordinates":[0.070954,43.78117],"type":"Point"}
}