{
  "type": "Feature",
  "properties": {
    "iso:country":"FR",
    "sg:address":"11 avenue des Chenes 06610 LA GAUDE",
    "sg:classifiers":[
        {
            "category":"Shopping",
            "subcategory":"Computers & Home Electronics",
            "type":"Retail Goods"
        }
    ],
    "sg:phone":"+33 4 93 73 25 00",
    "sg:tags":[
        "hardware",
        "appraisal",
        "damage",
        "analysis"
    ],
    "wof:name":"Cosch Sarl",
    "wof:placetype":"venue"
},
  "geometry": {"coordinates":[7.154352,43.722301],"type":"Point"}
}