{
  "type": "Feature",
  "properties": {
    "addr:full":"ZI les Grands Bois La S\u00e9guini\u00e8re Pays de Loire 49280",
    "addr:postcode":"49280",
    "addr:street":"Zi Les Grands Bois La",
    "iso:country":"FR",
    "sg:address":"ZI les Grands Bois",
    "sg:city":"La S\u00e9guini\u00e8re",
    "sg:orig_category":"Unclassifiable Establishments",
    "sg:phone":"+33 2 41 56 24 08",
    "sg:postcode":"49280",
    "sg:province":"Pays de Loire",
    "wof:name":"T.b.s. S.a.",
    "wof:placetype":"venue"
},
  "geometry": {"coordinates":[-0.936754,47.060074],"type":"Point"}
}