{
  "type": "Feature",
  "properties": {
    "iso:country":"FR",
    "sg:address":"Chef Lieu 74390 Ch\u00e2tel",
    "sg:classifiers":[
        {
            "category":"Travel",
            "subcategory":"Hotels & Motels",
            "type":"Entertainment"
        }
    ],
    "sg:phone":"+33 4 50 73 24 12",
    "sg:postcode":"74390",
    "sg:province":"Rhone-Alpes",
    "sg:tags":[
        "hotels",
        "business",
        "restaurant"
    ],
    "wof:name":"Hotel Macchi Sarl",
    "wof:placetype":"venue"
},
  "geometry": {"coordinates":[6.840885,46.268005],"type":"Point"}
}