{
  "type": "Feature",
  "properties": {
    "addr:full":"Rte d'Ermolsheim Molsheim Alsace 67120",
    "addr:postcode":"67120",
    "addr:street":"Rte D'Ermolsheim Molsheim",
    "iso:country":"FR",
    "sg:address":"Rte d'Ermolsheim",
    "sg:city":"Molsheim",
    "sg:orig_category":"Unclassifiable Establishments",
    "sg:phone":"+33 3 88 38 87 87",
    "sg:postcode":"67120",
    "sg:province":"Alsace",
    "wof:name":"Actis S.a.r.l.",
    "wof:placetype":"venue"
},
  "geometry": {"coordinates":[7.53769,48.544296],"type":"Point"}
}