{
  "type": "Feature",
  "properties": {
    "addr:full":"Av. du Parc Floral - H\u00f4tel des Entreprises Orl\u00e9ans C\u00e9dex 02 Picardie 45072",
    "addr:housenumber":"02",
    "addr:postcode":"orle\u0301ans;45072",
    "addr:street":"Av. Du Parc;Ce\u0301Dex;Picardie",
    "iso:country":"FR",
    "sg:address":"Av. du Parc Floral - H\u00f4tel des Entreprises",
    "sg:city":"Orl\u00e9ans C\u00e9dex 02",
    "sg:orig_category":"Non-Classified Establishments",
    "sg:phone":"+33 2 38 63 63 69",
    "sg:postcode":"45072",
    "sg:province":"Picardie",
    "wof:name":"B.r.e.u.i.l. Consultants S.a.",
    "wof:placetype":"venue"
},
  "geometry": {"coordinates":[1.90398,47.90139],"type":"Point"}
}