{
  "type": "Feature",
  "properties": {
    "addr:full":"ZA Peyrat le Ch\u00e2teau Limousin 87470",
    "addr:postcode":"87470",
    "addr:street":"Za Peyrat",
    "iso:country":"FR",
    "sg:address":"ZA",
    "sg:city":"Peyrat le Ch\u00e2teau",
    "sg:orig_category":"Unclassifiable Establishments",
    "sg:phone":"+33 5 55 69 40 22",
    "sg:postcode":"87470",
    "sg:province":"Limousin",
    "wof:name":"Portiso S.a.",
    "wof:placetype":"venue"
},
  "geometry": {"coordinates":[1.7729,45.815159],"type":"Point"}
}