{
  "type": "Feature",
  "properties": {
    "addr:full":"ZI le Pressoir Vert Semoy Centre 45400",
    "addr:postcode":"semoy;45400",
    "addr:street":"Zi Le",
    "iso:country":"FR",
    "sg:address":"ZI le Pressoir Vert",
    "sg:city":"Semoy",
    "sg:orig_category":"Non-Classified Establishments",
    "sg:phone":"+33 2 38 61 81 00",
    "sg:postcode":"45400",
    "sg:province":"Centre",
    "wof:name":"Morton S.a.s.",
    "wof:placetype":"venue"
},
  "geometry": {"coordinates":[1.949125,47.932152],"type":"Point"}
}