{
  "type": "Feature",
  "properties": {
    "addr:full":"B.P. 19, 60360 Viefvillers^^19, Rte de Rouen, 60360 Viefvillers Picardie",
    "addr:postcode":"60360;60360",
    "addr:street":"B.P. 19;Rte De Rouen",
    "iso:country":"FR",
    "sg:address":"B.P. 19, 60360 Viefvillers^^19, Rte de Rouen, 60360 Viefvillers",
    "sg:orig_category":"Non-Classified Establishments",
    "sg:phone":"+33 3 44 46 40 40",
    "sg:province":"Picardie",
    "wof:name":"Transports Leraille S.a.r.l.",
    "wof:placetype":"venue"
},
  "geometry": {"coordinates":[2.076715,49.607101],"type":"Point"}
}