{
  "type": "Feature",
  "properties": {
    "addr:full":"15 Rue Louis Armand 95600 Eaubonne Ile de France 95600",
    "addr:housenumber":"15",
    "addr:postcode":"95600;95600",
    "addr:street":"Rue Louis Armand",
    "iso:country":"FR",
    "sg:address":"15 Rue Louis Armand 95600 Eaubonne",
    "sg:classifiers":[
        {
            "category":"Manufacturing",
            "subcategory":"Metals",
            "type":"Manufacturing & Wholesale Goods"
        }
    ],
    "sg:phone":"+33 1 34 16 11 43",
    "sg:postcode":"95600",
    "sg:province":"Ile de France",
    "sg:tags":[
        "metallurgy",
        "steel",
        "metalworking"
    ],
    "wof:name":"Aluza Sa",
    "wof:placetype":"venue"
},
  "geometry": {"coordinates":[2.278009,49.003429],"type":"Point"}
}