{
  "type": "Feature",
  "properties": {
    "iso:country":"FR",
    "sg:address":"23, Rte d'Etrembi\u00e8res, 74100 Annemasse",
    "sg:orig_category":"Unclassifiable Establishments",
    "sg:phone":"+33 4 50 92 63 37",
    "sg:province":"Rhone-Alpes",
    "wof:name":"Protecno S.a.r.l.",
    "wof:placetype":"venue"
},
  "geometry": {"coordinates":[6.232299,46.187965],"type":"Point"}
}