{
  "type": "Feature",
  "properties": {
    "addr:full":"Route De Mauleon 79700 St Amand Sur Sevre Poitou-Charentes 79700",
    "addr:postcode":"79700;79700",
    "addr:street":"Route De Mauleon;Sevre",
    "iso:country":"FR",
    "sg:address":"Route De Mauleon 79700 St Amand Sur Sevre",
    "sg:classifiers":[
        {
            "category":"Autos & Motor Vehicles",
            "subcategory":"Boat Sales",
            "type":"Retail Goods"
        }
    ],
    "sg:phone":"+33 5 49 81 65 81",
    "sg:postcode":"79700",
    "sg:province":"Poitou-Charentes",
    "sg:tags":[
        "equipment",
        "transport"
    ],
    "wof:name":"3p Industrie",
    "wof:placetype":"venue"
},
  "geometry": {"coordinates":[-0.795684,46.869335],"type":"Point"}
}