{
  "type": "Feature",
  "properties": {
    "addr:full":"27, Rue de l'Avenir - ZI de Revoison, 69740 Genas Rhone-Alpes 69740",
    "addr:housenumber":"27",
    "addr:postcode":"69740;69740",
    "addr:street":"Rue De L'Avenir Zi De Revoison",
    "iso:country":"FR",
    "sg:address":"27, Rue de l'Avenir - ZI de Revoison, 69740 Genas",
    "sg:orig_category":"Unclassifiable Establishments",
    "sg:phone":"+33 4 72 47 02 11",
    "sg:postcode":"69740",
    "sg:province":"Rhone-Alpes",
    "wof:name":"Irpem France S.a.r.l.",
    "wof:placetype":"venue"
},
  "geometry": {"coordinates":[4.984198,45.723469],"type":"Point"}
}