{
  "type": "Feature",
  "properties": {
    "iso:country":"FR",
    "sg:address":"3 Rue Denis Papin 67403 Illkirch",
    "sg:classifiers":[
        {
            "category":"Manufacturing",
            "subcategory":"Tools & Machinery",
            "type":"Manufacturing & Wholesale Goods"
        }
    ],
    "sg:phone":"+33 3 88 55 29 00",
    "sg:province":"Franche Comt\u00e9",
    "sg:tags":[
        "equipment",
        "measurement",
        "-",
        "precision",
        "instrument"
    ],
    "wof:name":"Ivo Industries Sas",
    "wof:placetype":"venue"
},
  "geometry": {"coordinates":[7.71108,48.529339],"type":"Point"}
}