{
  "type": "Feature",
  "properties": {
    "iso:country":"FR",
    "sg:address":"8 Rue Karl Marx 02420 Nauroy",
    "sg:classifiers":[
        {
            "category":"Shopping",
            "subcategory":"Clothing, Apparel, & Fashions",
            "type":"Retail Goods"
        }
    ],
    "sg:phone":"+33 3 23 09 56 55",
    "sg:postcode":"02420",
    "sg:province":"Picardie",
    "sg:tags":[
        "textile",
        "clothing",
        "clothes"
    ],
    "wof:name":"Bellicourt Confection Sarl",
    "wof:placetype":"venue"
},
  "geometry": {"coordinates":[3.25718,49.94928],"type":"Point"}
}