{
  "type": "Feature",
  "properties": {
    "iso:country":"FR",
    "sg:address":"6, Bd Eiffel, 21600 Longvic",
    "sg:city":"Longvic",
    "sg:orig_category":"Unclassifiable Establishments",
    "sg:phone":"+33 3 80 65 42 00",
    "sg:postcode":"21600",
    "sg:province":"Bourgogne",
    "wof:name":"Ets Malatier",
    "wof:placetype":"venue"
},
  "geometry": {"coordinates":[5.057165,47.277538],"type":"Point"}
}