{
  "type": "Feature",
  "properties": {
    "iso:country":"FR",
    "sg:address":"B.P. 166",
    "sg:city":"Brest C\u00e9dex 9",
    "sg:orig_category":"Non-Classified Establishments",
    "sg:phone":"+33 2 98 42 14 44",
    "sg:postcode":"29803",
    "sg:province":"Brittany",
    "wof:name":"Propriet Appareil Vapeur Electrique Ouest S.a.",
    "wof:placetype":"venue"
},
  "geometry": {"coordinates":[-4.48622,48.390228],"type":"Point"}
}