{
  "type": "Feature",
  "properties": {
    "iso:country":"FR",
    "sg:address":"62 Rue Beaubourg 75003 Paris",
    "sg:classifiers":[
        {
            "category":"Professional",
            "subcategory":"Computer Services",
            "type":"Services"
        }
    ],
    "sg:phone":"+33 1 44 78 28 28",
    "sg:postcode":"75003",
    "sg:province":"Ile de France",
    "sg:tags":[
        "information",
        "technology",
        "software"
    ],
    "wof:name":"Semmit",
    "wof:placetype":"venue"
},
  "geometry": {"coordinates":[2.354764,48.863297],"type":"Point"}
}