{
  "type": "Feature",
  "properties": {
    "iso:country":"FR",
    "sg:address":"Rte De La Marana 20600 Furiani",
    "sg:classifiers":[
        {
            "category":"Food Court",
            "type":"Food & Drink"
        }
    ],
    "sg:phone":"+33 4 95 30 14 70",
    "sg:postcode":"20600",
    "sg:province":"Corse",
    "sg:tags":[
        "product",
        "related"
    ],
    "wof:name":"Brasserie Pietra",
    "wof:placetype":"venue"
},
  "geometry": {"coordinates":[9.415856,42.658413],"type":"Point"}
}