{
  "type": "Feature",
  "properties": {
    "addr:full":"45 Bd Marcel Pagnol Le Plan De Grasse 06130 Grasse Rhone-Alpes",
    "addr:housenumber":"45",
    "addr:postcode":"06130",
    "addr:street":"Bd Marcel Pagnol;Plan De Grasse",
    "iso:country":"FR",
    "sg:address":"45 Bd Marcel Pagnol Le Plan De Grasse 06130 Grasse",
    "sg:classifiers":[
        {
            "category":"Manufacturing",
            "subcategory":"Chemicals & Compounds",
            "type":"Manufacturing & Wholesale Goods"
        }
    ],
    "sg:phone":"+33 4 93 09 33 50",
    "sg:province":"Rhone-Alpes",
    "sg:tags":[
        "pharmaceutical",
        "chemistry",
        "-",
        "by-product"
    ],
    "wof:name":"Haarmann Et Reimer Sa",
    "wof:placetype":"venue"
},
  "geometry": {"coordinates":[6.931648,43.649738],"type":"Point"}
}