{
  "type": "Feature",
  "properties": {
    "iso:country":"FR",
    "sg:address":"1960 Av Fran\u00e7ois Mitterrand 62730 Marck",
    "sg:classifiers":[
        {
            "category":"Building & Trades",
            "subcategory":"Construction",
            "type":"Services"
        }
    ],
    "sg:phone":"+33 3 21 82 95 62",
    "sg:postcode":"62730",
    "sg:province":"Nord Pas-de-Calais",
    "sg:tags":[
        "work",
        "public"
    ],
    "wof:name":"Lianne Yves Sarl",
    "wof:placetype":"venue"
},
  "geometry": {"coordinates":[1.975904,50.951897],"type":"Point"}
}