{
  "type": "Feature",
  "properties": {
    "iso:country":"FR",
    "sg:address":"147, Bd Thiers, 16000 Angoul\u00eame",
    "sg:orig_category":"Unclassifiable Establishments",
    "sg:phone":"+33 5 45 37 00 90",
    "sg:province":"Poitou-Charentes",
    "wof:name":"Hydris Multum\u00e9dia S.a.r.l.",
    "wof:placetype":"venue"
},
  "geometry": {"coordinates":[0.17357,45.649448],"type":"Point"}
}