{
  "type": "Feature",
  "properties": {
    "addr:full":"25, Lot. Bonneverte, 01330 Amb\u00e9rieux en Dombes Rhone-Alpes 01330",
    "addr:housenumber":"25",
    "addr:postcode":"01330;01330",
    "addr:street":"Lot. Bonneverte;Rhone-Alpes",
    "iso:country":"FR",
    "sg:address":"25, Lot. Bonneverte, 01330 Amb\u00e9rieux en Dombes",
    "sg:orig_category":"Non-Classified Establishments",
    "sg:phone":"+33 4 74 00 85 50",
    "sg:postcode":"01330",
    "sg:province":"Rhone-Alpes",
    "wof:name":"Entreprise Moretton Albert",
    "wof:placetype":"venue"
},
  "geometry": {"coordinates":[5.01121,46.002338],"type":"Point"}
}