{
  "type": "Feature",
  "properties": {
    "iso:country":"FR",
    "sg:address":"38, Rue Marceau, 92000 Nanterre",
    "sg:orig_category":"Non-Classified Establishments",
    "sg:phone":"+33 1 47 21 52 41",
    "sg:province":"Ile de France",
    "wof:name":"S.a.m.t. Industrie S.a.",
    "wof:placetype":"venue"
},
  "geometry": {"coordinates":[2.19166,48.901958],"type":"Point"}
}