{
  "type": "Feature",
  "properties": {
    "addr:full":"2 rue la Fayette 25000 Besancon Franche Comt\u00e9",
    "addr:housenumber":"2",
    "addr:postcode":"25000",
    "addr:street":"Rue La Fayette;Franche Comte\u0301",
    "iso:country":"FR",
    "sg:address":"2 rue la Fayette 25000 Besancon",
    "sg:classifiers":[
        {
            "category":"Utilities",
            "subcategory":"Electric",
            "type":"Services"
        }
    ],
    "sg:phone":"+33 3 81 54 54 54",
    "sg:province":"Franche Comt\u00e9",
    "sg:tags":[
        "plug",
        "connectors",
        "customized"
    ],
    "wof:name":"F.c.i. Besancon S.a.",
    "wof:placetype":"venue"
},
  "geometry": {"coordinates":[5.967467,47.217049],"type":"Point"}
}