{
  "type": "Feature",
  "properties": {
    "addr:full":"21, Rue Gustave Delory, 42000 Saint Etienne Rhone-Alpes 42000",
    "addr:housenumber":"21",
    "addr:postcode":"42000;42000",
    "addr:street":"Rue Gustave Delory",
    "iso:country":"FR",
    "sg:address":"21, Rue Gustave Delory, 42000 Saint Etienne",
    "sg:orig_category":"Non-Classified Establishments",
    "sg:phone":"+33 4 77 79 13 14",
    "sg:postcode":"42000",
    "sg:province":"Rhone-Alpes",
    "wof:name":"B.m.r.a. S.a. - Bois Mat\u00e9riaux Rh\u00f4ne Alpes",
    "wof:placetype":"venue"
},
  "geometry": {"coordinates":[4.402171,45.462231],"type":"Point"}
}