{
  "type": "Feature",
  "properties": {
    "iso:country":"FR",
    "sg:address":"ZI des Champs de la Pierre - Espace Leaders",
    "sg:city":"Alby sur Ch\u00e9ran",
    "sg:orig_category":"Unclassifiable Establishments",
    "sg:phone":"+33 4 50 68 32 32",
    "sg:postcode":"74540",
    "sg:province":"Rhone-Alpes",
    "wof:name":"D.a.s. - Distribution Automatique Service",
    "wof:placetype":"venue"
},
  "geometry": {"coordinates":[6.022001,45.817081],"type":"Point"}
}