{
  "type": "Feature",
  "properties": {
    "addr:full":"70, Av. Jean Jaur\u00e8s, 69007 Lyon Rhone-Alpes 69007",
    "addr:postcode":"69007;69007",
    "addr:street":"70 Av. Jean Jaure\u0300S",
    "iso:country":"FR",
    "sg:address":"70, Av. Jean Jaur\u00e8s, 69007 Lyon",
    "sg:orig_category":"Unclassifiable Establishments",
    "sg:phone":"+33 4 78 58 95 80",
    "sg:postcode":"69007",
    "sg:province":"Rhone-Alpes",
    "wof:name":"Adia B.t.p. S.a.",
    "wof:placetype":"venue"
},
  "geometry": {"coordinates":[4.843273,45.747948],"type":"Point"}
}