{
  "type": "Feature",
  "properties": {
    "addr:full":"B.P. 413, 87011 Limoges C\u00e9dex^^22, Rue Jean Jaur\u00e8s, 87000 Limoges Limousin",
    "addr:housenumber":"b.p. 413",
    "addr:postcode":"87011;87000",
    "addr:street":"Rue Jean Jaure\u0300S",
    "iso:country":"FR",
    "sg:address":"B.P. 413, 87011 Limoges C\u00e9dex^^22, Rue Jean Jaur\u00e8s, 87000 Limoges",
    "sg:orig_category":"Non-Classified Establishments",
    "sg:phone":"+33 5 55 33 07 01",
    "sg:province":"Limousin",
    "wof:name":"Sacerp S.a. - Soci\u00e9t\u00e9 Commerciale Exploitation R\u00e9gies Publicita",
    "wof:placetype":"venue"
},
  "geometry": {"coordinates":[1.26201,45.828785],"type":"Point"}
}