{
  "type": "Feature",
  "properties": {
    "addr:full":"35, Rue Maubeuge, 75009 Paris Ile de France 75009",
    "addr:housenumber":"35",
    "addr:postcode":"75009;75009",
    "addr:street":"Rue Maubeuge",
    "iso:country":"FR",
    "sg:address":"35, Rue Maubeuge, 75009 Paris",
    "sg:orig_category":"Non-Classified Establishments",
    "sg:phone":"+33 1 44 63 52 00",
    "sg:postcode":"75009",
    "sg:province":"Ile de France",
    "wof:name":"Cavrois S.a.",
    "wof:placetype":"venue"
},
  "geometry": {"coordinates":[2.345343,48.87859],"type":"Point"}
}