{
  "type": "Feature",
  "properties": {
    "iso:country":"FR",
    "sg:address":"B.P. 131, 84133 Le Pontet C\u00e9dex^^Rue de la Verdette, 84130 Le Pontet",
    "sg:city":"Le Pontet",
    "sg:orig_category":"Non-Classified Establishments",
    "sg:phone":"+33 4 90 32 66 19",
    "sg:postcode":"73110",
    "sg:province":"Rhone-Alpes",
    "wof:name":"Deltisol S.a.",
    "wof:placetype":"venue"
},
  "geometry": {"coordinates":[4.859935,43.96188],"type":"Point"}
}