{
  "type": "Feature",
  "properties": {
    "iso:country":"FR",
    "sg:address":"1 Av De La Garonne 59640 Dunkerque",
    "sg:classifiers":[
        {
            "category":"Professional",
            "type":"Services"
        }
    ],
    "sg:phone":"+33 3 28 26 74 39",
    "sg:province":"Pays de Loire",
    "sg:tags":[
        "transport",
        "road"
    ],
    "wof:name":"Transports De Peauw Sa",
    "wof:placetype":"venue"
},
  "geometry": {"coordinates":[2.33191,51.004211],"type":"Point"}
}