{
  "type": "Feature",
  "properties": {
    "iso:country":"FR",
    "sg:address":"B.P. 1459, 30017 N\u00eemes C\u00e9dex^^257, Ancienne Route d'Avignon, 30000 N\u00eemes",
    "sg:orig_category":"Non-Classified Establishments",
    "sg:phone":"+33 4 66 02 22 22",
    "sg:province":"Languedoc-Roussillon",
    "wof:name":"Fermatec S.a.",
    "wof:placetype":"venue"
},
  "geometry": {"coordinates":[4.419136,43.856777],"type":"Point"}
}