{
  "type": "Feature",
  "properties": {
    "iso:country":"FR",
    "sg:address":"Parc Artisanal De Ste Consorce",
    "sg:city":"G7 BP 97 69280 Ste Consorce",
    "sg:classifiers":[
        {
            "category":"Shopping",
            "subcategory":"Clothing, Apparel, & Fashions",
            "type":"Retail Goods"
        }
    ],
    "sg:phone":"+33 4 37 22 50 30",
    "sg:postcode":"69280",
    "sg:province":"Rhone-Alpes",
    "sg:tags":[
        "clothes"
    ],
    "wof:name":"Cortex Sa",
    "wof:placetype":"venue"
},
  "geometry": {"coordinates":[4.69055,45.776863],"type":"Point"}
}