{
  "type": "Feature",
  "properties": {
    "iso:country":"FR",
    "sg:address":"10, Av. des Granitiers - ZA de la Grande Chauss\u00e9e, 49370 Becon les Granits",
    "sg:orig_category":"Unclassifiable Establishments",
    "sg:phone":"+33 2 41 77 04 40",
    "sg:province":"Pays de Loire",
    "wof:name":"Coremat E.u.r.l.",
    "wof:placetype":"venue"
},
  "geometry": {"coordinates":[-0.892846,47.463634],"type":"Point"}
}