{
  "type": "Feature",
  "properties": {
    "iso:country":"FR",
    "sg:address":"17, Rue Bel Air, 69800 Saint Priest",
    "sg:orig_category":"Non-Classified Establishments",
    "sg:phone":"+33 4 78 20 06 43",
    "sg:postcode":"69800",
    "sg:province":"Rhone-Alpes",
    "wof:name":"Eile Rh\u00f4ne Alpes S.a.",
    "wof:placetype":"venue"
},
  "geometry": {"coordinates":[4.947216,45.691723],"type":"Point"}
}