{
  "type": "Feature",
  "properties": {
    "addr:full":"11 Rue Des Buttes 21000 Dijon Dijon Bourgogne 21000",
    "addr:housenumber":"11",
    "addr:postcode":"21000;21000",
    "addr:street":"Rue Des Buttes",
    "iso:country":"FR",
    "sg:address":"11 Rue Des Buttes 21000 Dijon",
    "sg:city":"Dijon",
    "sg:classifiers":[
        {
            "category":"Wholesale",
            "subcategory":"Medical Equipment & Supplies",
            "type":"Manufacturing & Wholesale Goods"
        }
    ],
    "sg:phone":"+33 3 80 78 42 00",
    "sg:postcode":"21000",
    "sg:province":"Bourgogne",
    "sg:tags":[
        "instrument",
        "health",
        "-",
        "precision"
    ],
    "wof:name":"Etablissements Proteor",
    "wof:placetype":"venue"
},
  "geometry": {"coordinates":[5.040772,47.331596],"type":"Point"}
}