{
  "type": "Feature",
  "properties": {
    "iso:country":"FR",
    "sg:address":"50 Avenue Des Champs Elys\u00e9es 75008 Paris",
    "sg:classifiers":[
        {
            "category":"Professional",
            "subcategory":"Advertising",
            "type":"Services"
        }
    ],
    "sg:phone":"+33 1 45 63 33 44",
    "sg:postcode":"75008",
    "sg:province":"Ile de France",
    "sg:tags":[
        "information",
        "medium",
        "communication"
    ],
    "wof:name":"International Press Syndicate",
    "wof:placetype":"venue"
},
  "geometry": {"coordinates":[2.306555,48.870205],"type":"Point"}
}