{
  "type": "Feature",
  "properties": {
    "addr:full":"19, Av. Henri Barbusse, 47300 Villeneuve sur Lot Villeneuve-sur-Lot Aquitaine 47300",
    "addr:postcode":"47300;47300",
    "addr:street":"19 Av. Henri Barbusse;Lot",
    "iso:country":"FR",
    "sg:address":"19, Av. Henri Barbusse, 47300 Villeneuve sur Lot",
    "sg:city":"Villeneuve-sur-Lot",
    "sg:orig_category":"Unclassifiable Establishments",
    "sg:phone":"+33 5 53 70 56 72",
    "sg:postcode":"47300",
    "sg:province":"Aquitaine",
    "wof:name":"Etablissements Arthur Castagn\u00e9 S.a.",
    "wof:placetype":"venue"
},
  "geometry": {"coordinates":[0.708895,44.39991],"type":"Point"}
}