{
  "type": "Feature",
  "properties": {
    "addr:full":"140 rue Mauljean 52130 Wassy Champagne 52130",
    "addr:housenumber":"140",
    "addr:postcode":"52130;52130",
    "addr:street":"Rue Mauljean;Champagne",
    "iso:country":"FR",
    "sg:address":"140 rue Mauljean 52130 Wassy",
    "sg:classifiers":[
        {
            "category":"Banks & Credit Unions",
            "subcategory":"Investment Brokerage",
            "type":"Services"
        }
    ],
    "sg:phone":"+33 3 25 56 73 73",
    "sg:postcode":"52130",
    "sg:province":"Champagne",
    "sg:tags":[
        "casting"
    ],
    "wof:name":"G.h.m. Sa",
    "wof:placetype":"venue"
},
  "geometry": {"coordinates":[4.956017,48.493938],"type":"Point"}
}