{
  "type": "Feature",
  "properties": {
    "iso:country":"FR",
    "sg:address":"1180, Rte des Dolines, 06560 Valbonne",
    "sg:orig_category":"Unclassifiable Establishments",
    "sg:phone":"+33 4 92 94 33 91",
    "sg:province":"Rhone-Alpes",
    "wof:name":"Atsat-tas France E.u.r.l.",
    "wof:placetype":"venue"
},
  "geometry": {"coordinates":[7.039239,43.62521],"type":"Point"}
}