{
  "type": "Feature",
  "properties": {
    "iso:country":"FR",
    "sg:address":"18 Rue Moulin 62123 Berles Au Bois",
    "sg:classifiers":[
        {
            "category":"Professional",
            "type":"Services"
        }
    ],
    "sg:phone":"+33 3 21 07 46 16",
    "sg:province":"Nord Pas-de-Calais",
    "sg:tags":[
        "transport",
        "road"
    ],
    "wof:name":"Tpf Sarl",
    "wof:placetype":"venue"
},
  "geometry": {"coordinates":[2.62446,50.201271],"type":"Point"}
}