{
  "type": "Feature",
  "properties": {
    "iso:country":"FR",
    "sg:address":"8, Rue des Maronneirs - Le Charmois , 28190 Saint Germain le Gaillard",
    "sg:city":"Billancelles",
    "sg:orig_category":"Non-Classified Establishments",
    "sg:phone":"+33 2 37 23 73 04",
    "sg:postcode":"28190",
    "sg:province":"Centre",
    "wof:name":"Levillain Espaces Verts S.a.r.l.",
    "wof:placetype":"venue"
},
  "geometry": {"coordinates":[1.20829,48.391891],"type":"Point"}
}