{
  "type": "Feature",
  "properties": {
    "addr:full":"11 Rue Poitou 94150 Rungis Ile de France 94150",
    "addr:housenumber":"11",
    "addr:postcode":"94150;94150",
    "addr:street":"Rue Poitou",
    "iso:country":"FR",
    "sg:address":"11 Rue Poitou 94150 Rungis",
    "sg:classifiers":[
        {
            "category":"Farming",
            "subcategory":"Crops",
            "type":"Manufacturing & Wholesale Goods"
        }
    ],
    "sg:phone":"+33 1 46 87 31 06",
    "sg:postcode":"94150",
    "sg:province":"Ile de France",
    "sg:tags":[
        "vegetable",
        "fruit",
        "agriculture",
        "livestock"
    ],
    "wof:name":"Gb Tex (ste) Sarl",
    "wof:placetype":"venue"
},
  "geometry": {"coordinates":[2.361155,48.757225],"type":"Point"}
}