{
  "type": "Feature",
  "properties": {
    "iso:country":"FR",
    "sg:address":"1510, Av. du Stade - ZI les Valignons, 74460 Marnaz",
    "sg:orig_category":"Non-Classified Establishments",
    "sg:phone":"+33 4 50 98 23 53",
    "sg:postcode":"74460",
    "sg:province":"Rhone-Alpes",
    "wof:name":"Claret Jean-paul Fraisage S.a.",
    "wof:placetype":"venue"
},
  "geometry": {"coordinates":[6.52688,46.06094],"type":"Point"}
}