{
  "type": "Feature",
  "properties": {
    "addr:full":"Rue De L Alouette Zone Activites Economique 62210 Avion Nord Pas-de-Calais 62210",
    "addr:postcode":"62210;62210",
    "addr:street":"Rue De L Alouette;Activites Economique",
    "iso:country":"FR",
    "sg:address":"Rue De L Alouette Zone Activites Economique 62210 Avion",
    "sg:classifiers":[
        {
            "category":"Farming",
            "subcategory":"Livestock Farm",
            "type":"Manufacturing & Wholesale Goods"
        }
    ],
    "sg:phone":"+33 3 21 28 15 40",
    "sg:postcode":"62210",
    "sg:province":"Nord Pas-de-Calais",
    "sg:tags":[
        "agriculture"
    ],
    "wof:name":"Societe D'exploitation Agricole Zaffani",
    "wof:placetype":"venue"
},
  "geometry": {"coordinates":[2.83327,50.413349],"type":"Point"}
}