{
  "type": "Feature",
  "properties": {
    "iso:country":"FR",
    "sg:address":"B.P. 176, 13774 Fos sur Mer C\u00e9dex^^Site de Sollac Lot 9 1er \u00e9tage, 13770 Fos sur Mer",
    "sg:orig_category":"Non-Classified Establishments",
    "sg:phone":"+33 4 42 05 82 02",
    "sg:province":"Midi Pyr\u00e9n\u00e9es",
    "wof:name":"Riss Transport S.a.",
    "wof:placetype":"venue"
},
  "geometry": {"coordinates":[5.485145,43.599094],"type":"Point"}
}