{
  "type": "Feature",
  "properties": {
    "iso:country":"FR",
    "sg:address":"B.P. 6",
    "sg:city":"Tonneins",
    "sg:orig_category":"Non-Classified Establishments",
    "sg:phone":"+33 5 53 79 18 20",
    "sg:postcode":"47400",
    "sg:province":"Aquitaine",
    "wof:name":"Sogecofa S.a.",
    "wof:placetype":"venue"
},
  "geometry": {"coordinates":[0.319993,44.345749],"type":"Point"}
}