{
  "type": "Feature",
  "properties": {
    "iso:country":"FR",
    "sg:address":"29, Rue de l'Avenir, 38150 Chanas",
    "sg:orig_category":"Non-Classified Establishments",
    "sg:phone":"+33 4 74 79 32 94",
    "sg:postcode":"38150",
    "sg:province":"Rhone-Alpes",
    "wof:name":"A.c.2d. Isolation S.a.r.l.",
    "wof:placetype":"venue"
},
  "geometry": {"coordinates":[4.815685,45.314663],"type":"Point"}
}