{
  "type": "Feature",
  "properties": {
    "iso:country":"FR",
    "sg:address":"46, Rue Proudhon, 75012 Paris",
    "sg:orig_category":"Unclassifiable Establishments",
    "sg:phone":"+33 1 43 45 14 23",
    "sg:province":"Ile de France",
    "wof:name":"Europ Froid S.a.r.l.",
    "wof:placetype":"venue"
},
  "geometry": {"coordinates":[2.390504,48.837013],"type":"Point"}
}