{
  "type": "Feature",
  "properties": {
    "iso:country":"FR",
    "sg:address":"ZAE des Ecricrolles",
    "sg:city":"Groslay",
    "sg:orig_category":"Unclassifiable Establishments",
    "sg:phone":"+33 1 39 84 26 63",
    "sg:postcode":"95410",
    "sg:province":"Ile de France",
    "wof:name":"Atelier M\u00e9canique De Deuil S.a.",
    "wof:placetype":"venue"
},
  "geometry": {"coordinates":[2.358945,48.988194],"type":"Point"}
}