{
  "type": "Feature",
  "properties": {
    "addr:full":"B.P. 34, 76680 Saint Sa\u00ebns^^Z.I. des Aulnaies, 76680 Saint Sa\u00ebns Haute Normandie",
    "addr:postcode":"76680;76680;sae\u0308ns",
    "addr:street":"B.P. 34;Aulnaies;Haute Normandie",
    "iso:country":"FR",
    "sg:address":"B.P. 34, 76680 Saint Sa\u00ebns^^Z.I. des Aulnaies, 76680 Saint Sa\u00ebns",
    "sg:orig_category":"Non-Classified Establishments",
    "sg:phone":"+33 2 35 34 51 65",
    "sg:province":"Haute Normandie",
    "wof:name":"Nicole S.a.r.l.",
    "wof:placetype":"venue"
},
  "geometry": {"coordinates":[1.233175,49.70686],"type":"Point"}
}