{
  "type": "Feature",
  "properties": {
    "iso:country":"FR",
    "sg:address":"23, Rue Isaac Newton - ZAC de Chanteloup - B\u00e2t D2, 93600 Aulnay sous Bois",
    "sg:orig_category":"Unclassifiable Establishments",
    "sg:phone":"+33 1 48 19 97 30",
    "sg:province":"Ile de France",
    "wof:name":"M\u00e9capi\u00e8ces S.a.r.l.",
    "wof:placetype":"venue"
},
  "geometry": {"coordinates":[2.49124,48.927509],"type":"Point"}
}