{
  "type": "Feature",
  "properties": {
    "iso:country":"FR",
    "sg:address":"B.P. 5, 51140 Muizon^^ZI de Muizon, 51140 Muizon",
    "sg:orig_category":"Non-Classified Establishments",
    "sg:phone":"+33 3 26 02 99 48",
    "sg:postcode":"51140",
    "sg:province":"Champagne",
    "wof:name":"C.i.c.a. S.a.r.l. - Chaudronnerie Industrielle De Champagne-ardennes",
    "wof:placetype":"venue"
},
  "geometry": {"coordinates":[3.889085,49.275993],"type":"Point"}
}