{
  "type": "Feature",
  "properties": {
    "addr:full":"2, Rue du Paul Rohmer - Actipark les Poteries 1, 67200 Strasbourg Strasbourg Alsace 67200",
    "addr:housenumber":"2;1",
    "addr:postcode":"67200;67200",
    "addr:street":"Rue Du Paul Rohmer Actipark Les Poteries",
    "iso:country":"FR",
    "sg:address":"2, Rue du Paul Rohmer - Actipark les Poteries 1, 67200 Strasbourg",
    "sg:city":"Strasbourg",
    "sg:orig_category":"Non-Classified Establishments",
    "sg:phone":"+33 3 90 20 46 71",
    "sg:postcode":"67200",
    "sg:province":"Alsace",
    "wof:name":"Ferrures Et Patines S.a.r.l.",
    "wof:placetype":"venue"
},
  "geometry": {"coordinates":[7.71425,48.578671],"type":"Point"}
}