{
  "type": "Feature",
  "properties": {
    "iso:country":"FR",
    "sg:address":"Zone Ciale De Bellevue",
    "sg:city":"Caudan",
    "sg:classifiers":[
        {
            "category":"Manufacturing",
            "subcategory":"Metals",
            "type":"Manufacturing & Wholesale Goods"
        }
    ],
    "sg:phone":"+33 2 97 84 32 32",
    "sg:postcode":"56850",
    "sg:province":"Bretagne",
    "sg:tags":[
        "metallurgy",
        "metalworking",
        "processing"
    ],
    "wof:name":"Kerpont Industrie",
    "wof:placetype":"venue"
},
  "geometry": {"coordinates":[-3.340384,47.810596],"type":"Point"}
}