{
  "type": "Feature",
  "properties": {
    "addr:full":"B.P. 15, 25420 Voujeaucourt^^ZAC La Cray, 25420 Voujeaucourt Franche Comt\u00e9",
    "addr:postcode":"25420;25420",
    "addr:street":"B.P. 15;Franche Comte\u0301",
    "iso:country":"FR",
    "sg:address":"B.P. 15, 25420 Voujeaucourt^^ZAC La Cray, 25420 Voujeaucourt",
    "sg:orig_category":"Non-Classified Establishments",
    "sg:phone":"+33 3 81 98 20 20",
    "sg:province":"Franche Comt\u00e9",
    "wof:name":"S.t.2 M. S.a.r.l. - Services Techniques M\u00e9canique Et Maintenance",
    "wof:placetype":"venue"
},
  "geometry": {"coordinates":[6.765181,47.473015],"type":"Point"}
}