{
  "type": "Feature",
  "properties": {
    "iso:country":"FR",
    "sg:address":"54, Av de la Gironde, 59640 Dunkerque",
    "sg:orig_category":"Unclassifiable Establishments",
    "sg:phone":"+33 3 28 64 64 74",
    "sg:province":"Nord-Pas-de-Calais",
    "wof:name":"Eurolevage S.a.r.l.",
    "wof:placetype":"venue"
},
  "geometry": {"coordinates":[2.33319,51.004398],"type":"Point"}
}