{
  "type": "Feature",
  "properties": {
    "addr:full":"3 Rue Beaumarchais 93100 Montreuil Ile de France 93100",
    "addr:housenumber":"3",
    "addr:postcode":"93100;93100",
    "addr:street":"Rue Beaumarchais",
    "iso:country":"FR",
    "sg:address":"3 Rue Beaumarchais 93100 Montreuil",
    "sg:classifiers":[
        {
            "category":"Shopping",
            "subcategory":"Stationery & Office Supplies",
            "type":"Retail Goods"
        }
    ],
    "sg:phone":"+33 1 48 70 85 85",
    "sg:postcode":"93100",
    "sg:province":"Ile de France",
    "sg:tags":[
        "information",
        "technology",
        "telecommunication",
        "equipment"
    ],
    "wof:name":"Nagler Megras",
    "wof:placetype":"venue"
},
  "geometry": {"coordinates":[2.431704,48.856968],"type":"Point"}
}