{
  "type": "Feature",
  "properties": {
    "addr:full":"Rue des Chalets Lure Franche Comt\u00e9 70200",
    "addr:postcode":"70200",
    "addr:street":"Rue Des Chalets;Franche Comte\u0301",
    "iso:country":"FR",
    "sg:address":"Rue des Chalets",
    "sg:city":"Lure",
    "sg:orig_category":"Unclassifiable Establishments",
    "sg:phone":"+33 3 84 30 01 01",
    "sg:postcode":"70200",
    "sg:province":"Franche Comt\u00e9",
    "wof:name":"Gillot Voyages S.a.r.l.",
    "wof:placetype":"venue"
},
  "geometry": {"coordinates":[6.512995,47.68235],"type":"Point"}
}