{
  "type": "Feature",
  "properties": {
    "addr:full":"72-74 blvd Mar\u00e9chal Foch; Angers; 49000 Pays de Loire 49000",
    "addr:housenumber":"72-74",
    "addr:postcode":"49000;49000",
    "addr:street":"Blvd Mare\u0301Chal Foch",
    "iso:country":"FR",
    "sg:address":"72-74 blvd Mar\u00e9chal Foch; Angers; 49000",
    "sg:classifiers":[
        {
            "category":"Banks & Credit Unions",
            "subcategory":"Bank",
            "type":"Services"
        }
    ],
    "sg:phone":"+33 3341473276",
    "sg:postcode":"49000",
    "sg:province":"Pays de Loire",
    "wof:name":"Cr\u00e9dit Commercial De France (ccf)",
    "wof:placetype":"venue"
},
  "geometry": {"coordinates":[-0.608607,47.458508],"type":"Point"}
}