{
  "type": "Feature",
  "properties": {
    "addr:full":"10, Rue Saint Tropez, 56000 Vannes Vannes Bretagne 56000",
    "addr:housenumber":"10",
    "addr:postcode":"56000;56000",
    "addr:street":"Rue Saint Tropez",
    "iso:country":"FR",
    "sg:address":"10, Rue Saint Tropez, 56000 Vannes",
    "sg:city":"Vannes",
    "sg:orig_category":"Unclassifiable Establishments",
    "sg:phone":"+33 2 97 01 59 91",
    "sg:postcode":"56000",
    "sg:province":"Bretagne",
    "wof:name":"Soci\u00e9t\u00e9 Espace Et D\u00e9veloppements S.a.",
    "wof:placetype":"venue"
},
  "geometry": {"coordinates":[-2.750013,47.657688],"type":"Point"}
}