{
  "type": "Feature",
  "properties": {
    "addr:full":"2A l\u00e9e Andr\u00e9 Barrois 08310 JUNIVILLE Alincourt Champagne 08310",
    "addr:housenumber":"2a",
    "addr:postcode":"08310;08310",
    "addr:street":"Le\u0301E Andre\u0301 Barrois;Champagne",
    "iso:country":"FR",
    "sg:address":"2A l\u00e9e Andr\u00e9 Barrois 08310 JUNIVILLE",
    "sg:city":"Alincourt",
    "sg:classifiers":[
        {
            "category":"Wholesale",
            "subcategory":"Fruits & Vegetables",
            "type":"Manufacturing & Wholesale Goods"
        }
    ],
    "sg:phone":"+33 3 24 39 50 70",
    "sg:postcode":"08310",
    "sg:province":"Champagne",
    "sg:tags":[
        "product",
        "cereal"
    ],
    "wof:name":"Coop Agricol Transform Conservation Vent",
    "wof:placetype":"venue"
},
  "geometry": {"coordinates":[4.455027,49.354725],"type":"Point"}
}