{
  "type": "Feature",
  "properties": {
    "iso:country":"FR",
    "sg:address":"49, Rue de Normandie, 80220 Gamaches",
    "sg:orig_category":"Unclassifiable Establishments",
    "sg:phone":"+33 3 22 60 30 30",
    "sg:province":"Picardie",
    "wof:name":"S.e.e. Millancourt Et Nicolas S.a. - Adh\u00e9rant Gedimat",
    "wof:placetype":"venue"
},
  "geometry": {"coordinates":[1.551735,49.984234],"type":"Point"}
}