{
  "type": "Feature",
  "properties": {
    "addr:full":"Immeuble La Fayette 2-3, place des Vosges, La D\u00e9fense 5; Courbevoie; 92400 Ile de France",
    "addr:housenumber":"2-3;5",
    "addr:postcode":"92400 ile",
    "addr:street":"Fayette;Place Des Vosges La De\u0301Fense",
    "iso:country":"FR",
    "sg:address":"Immeuble La Fayette 2-3, place des Vosges, La D\u00e9fense 5; Courbevoie; 92400",
    "sg:classifiers":[
        {
            "category":"Industrial Area",
            "type":"Public Place"
        }
    ],
    "sg:phone":"+33 1 46 91 54 00",
    "sg:province":"Ile de France",
    "sg:tags":[
        "large",
        "private"
    ],
    "wof:name":"Le Carbone-lorraine",
    "wof:placetype":"venue"
},
  "geometry": {"coordinates":[2.25645,48.895908],"type":"Point"}
}