{
  "type": "Feature",
  "properties": {
    "addr:full":"13 Rue Rolette 27190 Portes Haute Normandie 27190",
    "addr:housenumber":"13",
    "addr:postcode":"27190;27190",
    "addr:street":"Rue Rolette;Haute Normandie",
    "iso:country":"FR",
    "sg:address":"13 Rue Rolette 27190 Portes",
    "sg:classifiers":[
        {
            "category":"Shopping",
            "type":"Retail Goods"
        }
    ],
    "sg:phone":"+33 2 32 30 10 72",
    "sg:postcode":"27190",
    "sg:province":"Haute Normandie",
    "sg:tags":[
        "metallurgy",
        "finished",
        "-",
        "metalworking",
        "metallic"
    ],
    "wof:name":"Mecalynox",
    "wof:placetype":"venue"
},
  "geometry": {"coordinates":[0.951876,49.030117],"type":"Point"}
}