{
  "type": "Feature",
  "properties": {
    "iso:country":"FR",
    "sg:address":"70 avenue Jean Chatelet 18500 MEHUN SUR YEVRE",
    "sg:city":"Marmagne",
    "sg:classifiers":[
        {
            "category":"Manufacturing",
            "subcategory":"Pottery",
            "type":"Manufacturing & Wholesale Goods"
        }
    ],
    "sg:phone":"+33 2 48 57 32 09",
    "sg:postcode":"18500",
    "sg:province":"Centre",
    "sg:tags":[
        "decorative",
        "porcelain"
    ],
    "wof:name":"France Porcelaine S.a.",
    "wof:placetype":"venue"
},
  "geometry": {"coordinates":[2.216024,47.149628],"type":"Point"}
}