{
  "type": "Feature",
  "properties": {
    "iso:country":"FR",
    "sg:address":"Zac De La Haute Rive BP 18 59553 Cuincy",
    "sg:classifiers":[
        {
            "category":"Building & Trades",
            "subcategory":"Electrical",
            "type":"Services"
        }
    ],
    "sg:phone":"+33 3 27 90 88 88",
    "sg:postcode":"59553",
    "sg:province":"Nord Pas-de-Calais",
    "sg:tags":[
        "electronic",
        "lighting",
        "equipment"
    ],
    "wof:name":"Neon Pub Enseignes Sarl",
    "wof:placetype":"venue"
},
  "geometry": {"coordinates":[3.04381,50.382118],"type":"Point"}
}