{
  "type": "Feature",
  "properties": {
    "addr:full":"90, Av. du G\u00e9n\u00e9ral de Gaulle, 92230 Gennevilliers Ile de France",
    "addr:postcode":"92230;ile",
    "addr:street":"90 Av. Du Ge\u0301Ne\u0301Ral De Gaulle",
    "iso:country":"FR",
    "sg:address":"90, Av. du G\u00e9n\u00e9ral de Gaulle, 92230 Gennevilliers",
    "sg:orig_category":"Non-Classified Establishments",
    "sg:phone":"+33 1 47 98 52 20",
    "sg:province":"Ile de France",
    "wof:name":"Soci\u00e9t\u00e9 Thomet S.a.",
    "wof:placetype":"venue"
},
  "geometry": {"coordinates":[2.314796,48.933804],"type":"Point"}
}