{
  "type": "Feature",
  "properties": {
    "addr:full":"1430 Rue Berthelot 59721 Denain Cedex Auvergne",
    "addr:housenumber":"1430",
    "addr:postcode":"59721;cedex",
    "addr:street":"Rue Berthelot",
    "iso:country":"FR",
    "sg:address":"1430 Rue Berthelot 59721 Denain Cedex",
    "sg:classifiers":[
        {
            "category":"Manufacturing",
            "subcategory":"Chemicals & Compounds",
            "type":"Manufacturing & Wholesale Goods"
        }
    ],
    "sg:phone":"+33 3 27 14 55 00",
    "sg:province":"Auvergne",
    "sg:tags":[
        "pharmaceutical",
        "chemistry",
        "-",
        "by-product"
    ],
    "wof:name":"Air Liquide (l)",
    "wof:placetype":"venue"
},
  "geometry": {"coordinates":[3.375043,50.345253],"type":"Point"}
}