{
  "type": "Feature",
  "properties": {
    "iso:country":"FR",
    "sg:address":"209, Chemin de la Conche, 01700 Beynost",
    "sg:orig_category":"Unclassifiable Establishments",
    "sg:phone":"+33 4 72 88 20 19",
    "sg:province":"Rhone-Alpes",
    "wof:name":"Crozet Eric",
    "wof:placetype":"venue"
},
  "geometry": {"coordinates":[4.993475,45.840279],"type":"Point"}
}