{
  "type": "Feature",
  "properties": {
    "iso:country":"FR",
    "sg:address":"Rue Chapelet - ZA la N\u00e9gresse",
    "sg:city":"Biarritz",
    "sg:orig_category":"Non-Classified Establishments",
    "sg:phone":"+33 5 59 41 71 71",
    "sg:postcode":"64200",
    "sg:province":"Aquitaine",
    "wof:name":"Soci\u00e9t\u00e9 Nouvelle F\u00e9ralu C\u00f4te Basque S.a.r.l.",
    "wof:placetype":"venue"
},
  "geometry": {"coordinates":[-1.558793,43.482571],"type":"Point"}
}