{
  "type": "Feature",
  "properties": {
    "addr:full":"3, Rue Mirabeau, 59420 Mouvaux Nord Pas-de-Calais",
    "addr:housenumber":"3",
    "addr:postcode":"59420",
    "addr:street":"Rue Mirabeau",
    "iso:country":"FR",
    "sg:address":"3, Rue Mirabeau, 59420 Mouvaux",
    "sg:orig_category":"Unclassifiable Establishments",
    "sg:phone":"+33 3 20 27 25 25",
    "sg:province":"Nord Pas-de-Calais",
    "wof:name":"Kali Communication S.a.r.l.",
    "wof:placetype":"venue"
},
  "geometry": {"coordinates":[3.13428,50.701954],"type":"Point"}
}