{
  "type": "Feature",
  "properties": {
    "addr:full":"Rue L\u00e9o Lagrange La Sentinelle Nord Pas-de-Calais 59174",
    "addr:postcode":"59174",
    "addr:street":"Rue Le\u0301O Lagrange La;Nord",
    "iso:country":"FR",
    "sg:address":"Rue L\u00e9o Lagrange",
    "sg:city":"La Sentinelle",
    "sg:orig_category":"Unclassifiable Establishments",
    "sg:phone":"+33 3 27 21 23 00",
    "sg:postcode":"59174",
    "sg:province":"Nord Pas-de-Calais",
    "wof:name":"S.i.s.c. S.a. - Soci\u00e9t\u00e9 Industrielle De Saint-christophe",
    "wof:placetype":"venue"
},
  "geometry": {"coordinates":[3.472945,50.352646],"type":"Point"}
}