{
  "type": "Feature",
  "properties": {
    "addr:full":"316bis, Av. des Olives, 13013 Marseille Poitou-Charentes",
    "addr:postcode":"13013",
    "addr:street":"Av. Des Olives",
    "iso:country":"FR",
    "sg:address":"316bis, Av. des Olives, 13013 Marseille",
    "sg:orig_category":"Non-Classified Establishments",
    "sg:phone":"+33 4 91 66 23 13",
    "sg:province":"Poitou-Charentes",
    "wof:name":"Carri\u00e8res De Fondacle S.a.",
    "wof:placetype":"venue"
},
  "geometry": {"coordinates":[5.44836,43.323189],"type":"Point"}
}