{
  "type": "Feature",
  "properties": {
    "addr:full":"1, Rue Bauderon de Senec\u00e9, 71000 M\u00e2con Sanc\u00e9 Bourgogne 71000",
    "addr:housenumber":"1",
    "addr:postcode":"71000;71000",
    "addr:street":"Rue Bauderon De Senece\u0301",
    "iso:country":"FR",
    "sg:address":"1, Rue Bauderon de Senec\u00e9, 71000 M\u00e2con",
    "sg:city":"Sanc\u00e9",
    "sg:orig_category":"Unclassifiable Establishments",
    "sg:phone":"+33 3 85 22 96 22",
    "sg:postcode":"71000",
    "sg:province":"Bourgogne",
    "wof:name":"Atecmaa S.a.r.l.",
    "wof:placetype":"venue"
},
  "geometry": {"coordinates":[4.832726,46.306973],"type":"Point"}
}