{
  "type": "Feature",
  "properties": {
    "iso:country":"FR",
    "sg:address":"7 Rue Ladrie",
    "sg:city":"De La Pilaterie 59290 Wasquehal",
    "sg:classifiers":[
        {
            "category":"Manufacturing",
            "subcategory":"Paper Products",
            "type":"Manufacturing & Wholesale Goods"
        }
    ],
    "sg:phone":"+33 3 28 33 05 50",
    "sg:province":"Nord Pas-de-Calais",
    "sg:tags":[
        "raw",
        "material",
        "-",
        "cardboard"
    ],
    "wof:name":"Papeteries R & P Blanquart",
    "wof:placetype":"venue"
},
  "geometry": {"coordinates":[3.132085,50.669395],"type":"Point"}
}