{
  "type": "Feature",
  "properties": {
    "addr:full":"1 Rue Eugene Ravanat 38320 Eybens Rhone-Alpes 38320",
    "addr:housenumber":"1",
    "addr:postcode":"38320;38320",
    "addr:street":"Rue Eugene Ravanat",
    "iso:country":"FR",
    "sg:address":"1 Rue Eugene Ravanat 38320 Eybens",
    "sg:classifiers":[
        {
            "category":"Building & Trades",
            "subcategory":"Construction",
            "type":"Services"
        }
    ],
    "sg:phone":"+33 4 76 25 31 54",
    "sg:postcode":"38320",
    "sg:province":"Rhone-Alpes",
    "sg:tags":[
        "work",
        "public"
    ],
    "wof:name":"Fileppi",
    "wof:placetype":"venue"
},
  "geometry": {"coordinates":[5.745339,45.157776],"type":"Point"}
}