{
  "type": "Feature",
  "properties": {
    "iso:country":"FR",
    "sg:address":"20 Avenue De Grande Bretagne 66000 Perpignan",
    "sg:classifiers":[
        {
            "category":"Professional",
            "subcategory":"Business Services",
            "type":"Services"
        }
    ],
    "sg:phone":"+33 4 68 34 07 83",
    "sg:postcode":"66000",
    "sg:province":"Languedoc-Roussillon",
    "sg:tags":[
        "industrial",
        "advice",
        "motor-cars",
        "equipment",
        "vehicle",
        "transport"
    ],
    "wof:name":"Garage Alart Sa",
    "wof:placetype":"venue"
},
  "geometry": {"coordinates":[2.881225,42.699142],"type":"Point"}
}