{
  "type": "Feature",
  "properties": {
    "iso:country":"FR",
    "sg:address":"Centre Commercial Barne; Cabris; 13480",
    "sg:classifiers":[
        {
            "category":"Banks & Credit Unions",
            "subcategory":"Bank",
            "type":"Services"
        }
    ],
    "sg:phone":"+33 3342028548",
    "sg:province":"Midi Pyr\u00e9n\u00e9es",
    "wof:name":"Soci\u00e9t\u00e9 G\u00e9n\u00e9rale",
    "wof:placetype":"venue"
},
  "geometry": {"coordinates":[-75.373589,42.92643],"type":"Point"}
}