{
  "type": "Feature",
  "properties": {
    "iso:country":"FR",
    "sg:address":"Zi Chef De Baie Rue De Qu\u00e9bec 17000 La Rochelle",
    "sg:classifiers":[
        {
            "category":"Wholesale",
            "subcategory":"Machinery & Supplies",
            "type":"Manufacturing & Wholesale Goods"
        }
    ],
    "sg:phone":"+33 5 46 42 84 36",
    "sg:postcode":"17000",
    "sg:province":"Poitou-Charentes",
    "sg:tags":[
        "handling",
        "material",
        "-",
        "machine",
        "equipment",
        "engineering",
        "mechanical"
    ],
    "wof:name":"Otis",
    "wof:placetype":"venue"
},
  "geometry": {"coordinates":[-1.151639,46.159435],"type":"Point"}
}