{
  "type": "Feature",
  "properties": {
    "addr:full":"438, Bd Jean Moulin, 49400 Saumur Pays de Loire",
    "addr:housenumber":"438",
    "addr:postcode":"49400",
    "addr:street":"Bd Jean Moulin",
    "iso:country":"FR",
    "sg:address":"438, Bd Jean Moulin, 49400 Saumur",
    "sg:orig_category":"Unclassifiable Establishments",
    "sg:phone":"+33 2 41 40 22 30",
    "sg:province":"Pays de Loire",
    "wof:name":"Verdier Joseph S.a.",
    "wof:placetype":"venue"
},
  "geometry": {"coordinates":[-0.070488,47.237194],"type":"Point"}
}