{
  "type": "Feature",
  "properties": {
    "iso:country":"FR",
    "sg:address":"24, Rue Emile Zola, 39300 Champagnole",
    "sg:orig_category":"Unclassifiable Establishments",
    "sg:phone":"+33 3 84 52 14 75",
    "sg:province":"Franche Comt\u00e9",
    "wof:name":"Poiret Et Fils S.a.r.l.",
    "wof:placetype":"venue"
},
  "geometry": {"coordinates":[5.92488,46.739792],"type":"Point"}
}