{
  "type": "Feature",
  "properties": {
    "addr:full":"24, Rue Emile Zola, 39300 Champagnole Franche Comt\u00e9",
    "addr:housenumber":"24",
    "addr:postcode":"39300",
    "addr:street":"Rue Emile Zola;Franche Comte\u0301",
    "iso:country":"FR",
    "sg:address":"24, Rue Emile Zola, 39300 Champagnole",
    "sg:orig_category":"Unclassifiable Establishments",
    "sg:phone":"+33 3 84 52 14 75",
    "sg:province":"Franche Comt\u00e9",
    "wof:name":"Poiret Et Fils S.a.r.l.",
    "wof:placetype":"venue"
},
  "geometry": {"coordinates":[5.92488,46.739792],"type":"Point"}
}