{
  "type": "Feature",
  "properties": {
    "iso:country":"FR",
    "sg:address":"4, Rue Oscar Momeris, 72500 Vouvray sur Loir",
    "sg:orig_category":"Non-Classified Establishments",
    "sg:phone":"+33 2 43 44 14 01",
    "sg:postcode":"72500",
    "sg:province":"Pays de Loire",
    "wof:name":"Bechtet S.a.",
    "wof:placetype":"venue"
},
  "geometry": {"coordinates":[0.452638,47.688572],"type":"Point"}
}