{
  "type": "Feature",
  "properties": {
    "addr:full":"Chemin D\u00e9partemental n3 Longueville sur Scie Haute Normandie 76590",
    "addr:housenumber":"n3",
    "addr:postcode":"76590",
    "addr:street":"Chemin De\u0301Partemental;Haute Normandie",
    "iso:country":"FR",
    "sg:address":"Chemin D\u00e9partemental n3",
    "sg:city":"Longueville sur Scie",
    "sg:orig_category":"Non-Classified Establishments",
    "sg:phone":"+33 2 35 85 07 12",
    "sg:postcode":"76590",
    "sg:province":"Haute Normandie",
    "wof:name":"S.l.f. S.a.r.l. - Soci\u00e9t\u00e9 Longuevillaise De Fabrications",
    "wof:placetype":"venue"
},
  "geometry": {"coordinates":[1.10931,49.791386],"type":"Point"}
}