{
  "type": "Feature",
  "properties": {
    "addr:full":"5, Rue L\u00e9on Blum, 91120 Palaiseau Ile de France",
    "addr:housenumber":"5",
    "addr:postcode":"91120;ile",
    "addr:street":"Rue Le\u0301On Blum",
    "iso:country":"FR",
    "sg:address":"5, Rue L\u00e9on Blum, 91120 Palaiseau",
    "sg:orig_category":"Non-Classified Establishments",
    "sg:phone":"+33 1 69 19 44 00",
    "sg:province":"Ile de France",
    "wof:name":"Unaxis S.a.",
    "wof:placetype":"venue"
},
  "geometry": {"coordinates":[2.25354,48.712276],"type":"Point"}
}