{
  "type": "Feature",
  "properties": {
    "addr:full":"41 Rue Edouard Dallas Ancien R Du Docteur Guini 65600 Semeac Midi Pyr\u00e9n\u00e9es 65600",
    "addr:housenumber":"41",
    "addr:postcode":"65600;65600",
    "addr:street":"Rue Edouard",
    "iso:country":"FR",
    "sg:address":"41 Rue Edouard Dallas Ancien R Du Docteur Guini 65600 Semeac",
    "sg:classifiers":[
        {
            "category":"Manufacturing",
            "subcategory":"Tools & Machinery",
            "type":"Manufacturing & Wholesale Goods"
        }
    ],
    "sg:phone":"+33 5 62 44 26 25",
    "sg:postcode":"65600",
    "sg:province":"Midi Pyr\u00e9n\u00e9es",
    "sg:tags":[
        "metallurgy",
        "metalworking"
    ],
    "wof:name":"Bernard Pages",
    "wof:placetype":"venue"
},
  "geometry": {"coordinates":[0.104826,43.228313],"type":"Point"}
}