{
  "type": "Feature",
  "properties": {
    "iso:country":"FR",
    "sg:address":"pl G\u00e9n\u00e9ral de Gaulle; Ploudalmezeau",
    "sg:classifiers":[
        {
            "category":"Banks & Credit Unions",
            "subcategory":"Bank",
            "type":"Services"
        }
    ],
    "sg:phone":"+33 3398481460",
    "sg:province":"Pays de Loire",
    "wof:name":"Cr\u00e9dit Agricole Mutuel",
    "wof:placetype":"venue"
},
  "geometry": {"coordinates":[-4.660329,48.541996],"type":"Point"}
}