{
  "type": "Feature",
  "properties": {
    "iso:country":"FR",
    "sg:address":"27 avenue Auguste Verola 06200 Nice",
    "sg:classifiers":[
        {
            "category":"Professional",
            "subcategory":"Advertising",
            "type":"Services"
        }
    ],
    "sg:phone":"+33 4 92 29 57 80",
    "sg:province":"Ile de France",
    "sg:tags":[
        "gift"
    ],
    "wof:name":"Coup De Poing S.a.",
    "wof:placetype":"venue"
},
  "geometry": {"coordinates":[7.188408,43.710228],"type":"Point"}
}