{
  "type": "Feature",
  "properties": {
    "iso:country":"FR",
    "sg:address":"9, Rue de la Mare Blanche - ZI de Noisiel, 77186 Noisiel",
    "sg:orig_category":"Unclassifiable Establishments",
    "sg:phone":"+33 1 60 37 26 10",
    "sg:province":"Ile de France",
    "wof:name":"S.f.d.e. S.c.a.",
    "wof:placetype":"venue"
},
  "geometry": {"coordinates":[2.628145,48.854988],"type":"Point"}
}