{
  "type": "Feature",
  "properties": {
    "addr:full":"32, Av. Valioud, 69110 Sainte Foy les Lyon Rhone-Alpes 69110",
    "addr:postcode":"69110;69110",
    "addr:street":"32 Av. Valioud;Foy Les;Rhone-Alpes",
    "iso:country":"FR",
    "sg:address":"32, Av. Valioud, 69110 Sainte Foy les Lyon",
    "sg:orig_category":"Non-Classified Establishments",
    "sg:phone":"+33 4 78 25 21 25",
    "sg:postcode":"69110",
    "sg:province":"Rhone-Alpes",
    "wof:name":"A.m.c. Marketing Op\u00e9rationnel S.a.",
    "wof:placetype":"venue"
},
  "geometry": {"coordinates":[4.810616,45.746208],"type":"Point"}
}