{
  "type": "Feature",
  "properties": {
    "iso:country":"FR",
    "sg:address":"268 avenue du Pr\u00e9sident Wilson 93210 LA PLAINE ST DENIS",
    "sg:city":"Plaine",
    "sg:classifiers":[
        {
            "category":"Autos & Motor Vehicles",
            "subcategory":"Auto Supplies",
            "type":"Retail Goods"
        }
    ],
    "sg:phone":"+33 1 49 46 71 71",
    "sg:postcode":"67420",
    "sg:province":"Alsace",
    "sg:tags":[
        "automobile",
        "painting"
    ],
    "wof:name":"Akzo Nobel Industrial Coatings S.a.",
    "wof:placetype":"venue"
},
  "geometry": {"coordinates":[2.357995,48.91898],"type":"Point"}
}