{
  "type": "Feature",
  "properties": {
    "addr:full":"2 Avenue Gabrielle 93330 Neuilly Sur Marne Ile de France 93330",
    "addr:housenumber":"2",
    "addr:postcode":"93330;93330",
    "addr:street":"Avenue Gabrielle",
    "iso:country":"FR",
    "sg:address":"2 Avenue Gabrielle 93330 Neuilly Sur Marne",
    "sg:classifiers":[
        {
            "category":"Manufacturing",
            "subcategory":"Metals",
            "type":"Manufacturing & Wholesale Goods"
        }
    ],
    "sg:phone":"+33 1 43 81 77 12",
    "sg:postcode":"93330",
    "sg:province":"Ile de France",
    "sg:tags":[
        "metallurgy",
        "metalworking",
        "processing"
    ],
    "wof:name":"Adim Application Decorative Industrielle Metallerie",
    "wof:placetype":"venue"
},
  "geometry": {"coordinates":[2.525765,48.875355],"type":"Point"}
}