{
  "type": "Feature",
  "properties": {
    "iso:country":"FR",
    "sg:address":"12, Rue de la Pompadour, 94470 Boissy saint L\u00e9ger",
    "sg:orig_category":"Unclassifiable Establishments",
    "sg:phone":"+33 1 56 73 14 60",
    "sg:province":"Ile de France",
    "wof:name":"Distri Elec S.a.",
    "wof:placetype":"venue"
},
  "geometry": {"coordinates":[2.498333,48.761181],"type":"Point"}
}