{
  "type": "Feature",
  "properties": {
    "addr:full":"6 Rue Du Vignolle 95200 Sarcelles Ile de France 95200",
    "addr:housenumber":"6",
    "addr:postcode":"95200;ile;95200",
    "addr:street":"Rue Du Vignolle;France",
    "iso:country":"FR",
    "sg:address":"6 Rue Du Vignolle 95200 Sarcelles",
    "sg:classifiers":[
        {
            "category":"Autos & Motor Vehicles",
            "subcategory":"Automobile Sales",
            "type":"Retail Goods"
        }
    ],
    "sg:phone":"+33 1 39 92 62 00",
    "sg:postcode":"95200",
    "sg:province":"Ile de France",
    "sg:tags":[
        "equipment",
        "industrial",
        "transport"
    ],
    "wof:name":"Evobus France Sas",
    "wof:placetype":"venue"
},
  "geometry": {"coordinates":[2.386917,48.988686],"type":"Point"}
}