{
  "type": "Feature",
  "properties": {
    "addr:full":"5 rue Rousselet 33710 ST TROJAN Bayon-sur-Gironde Aquitaine 33710",
    "addr:housenumber":"5",
    "addr:postcode":"33710;33710",
    "addr:street":"Rue Rousselet",
    "iso:country":"FR",
    "sg:address":"5 rue Rousselet 33710 ST TROJAN",
    "sg:city":"Bayon-sur-Gironde",
    "sg:classifiers":[
        {
            "category":"Wholesale",
            "subcategory":"Wine & Distilled Alcoholic Beverages",
            "type":"Manufacturing & Wholesale Goods"
        }
    ],
    "sg:phone":"+33 5 57 64 32 18",
    "sg:postcode":"33710",
    "sg:province":"Aquitaine",
    "sg:tags":[
        "french"
    ],
    "wof:name":"Ch\u00e2teau De Rousselet E.a.r.l",
    "wof:placetype":"venue"
},
  "geometry": {"coordinates":[-0.582674,45.086285],"type":"Point"}
}