{
  "type": "Feature",
  "properties": {
    "addr:full":"Rue de la Grosne M\u00e2con Bourgogne 71000",
    "addr:postcode":"71000",
    "addr:street":"Rue De La Grosne;Bourgogne",
    "iso:country":"FR",
    "sg:address":"Rue de la Grosne",
    "sg:city":"M\u00e2con",
    "sg:orig_category":"Unclassifiable Establishments",
    "sg:phone":"+33 3 85 29 61 00",
    "sg:postcode":"71000",
    "sg:province":"Bourgogne",
    "wof:name":"Transports Alain\u00e9 S.a.",
    "wof:placetype":"venue"
},
  "geometry": {"coordinates":[4.818374,46.286152],"type":"Point"}
}