{
  "type": "Feature",
  "properties": {
    "addr:full":"5566 / 67, 55556 lkhljhlkjgbkljvb^^5566 / 67, 99999 lkhljhlkjgbkljvb",
    "addr:housenumber":"5566 / 67;67",
    "addr:postcode":"55556;99999",
    "iso:country":"FR",
    "sg:address":"5566 / 67, 55556 lkhljhlkjgbkljvb^^5566 / 67, 99999 lkhljhlkjgbkljvb",
    "sg:orig_category":"Non-Classified Establishments",
    "sg:phone":"+33 1233445555",
    "wof:name":"Thierry Decoutre - Rutger",
    "wof:placetype":"venue"
},
  "geometry": {"coordinates":[-93.914993,44.7836],"type":"Point"}
}