{
  "type": "Feature",
  "properties": {
    "addr:full":"2, Rue Alexandre Hugot, 10500 Brienne la Vieille Champagne",
    "addr:housenumber":"2",
    "addr:postcode":"10500",
    "addr:street":"Rue Alexandre Hugot;Vieille Champagne",
    "iso:country":"FR",
    "sg:address":"2, Rue Alexandre Hugot, 10500 Brienne la Vieille",
    "sg:orig_category":"Non-Classified Establishments",
    "sg:phone":"+33 3 25 92 84 17",
    "sg:province":"Champagne",
    "wof:name":"Vautrin S.a.r.l.",
    "wof:placetype":"venue"
},
  "geometry": {"coordinates":[4.53125,48.370281],"type":"Point"}
}