{
  "type": "Feature",
  "properties": {
    "iso:country":"FR",
    "sg:address":"Rue des Fournels",
    "sg:city":"Lunel",
    "sg:orig_category":"Unclassifiable Establishments",
    "sg:phone":"+33 4 67 83 51 60",
    "sg:postcode":"34400",
    "sg:province":"Languedoc-Roussillon",
    "wof:name":"Foraco S.a.",
    "wof:placetype":"venue"
},
  "geometry": {"coordinates":[4.108795,43.679749],"type":"Point"}
}