{
  "type": "Feature",
  "properties": {
    "iso:country":"FR",
    "sg:address":"1023 Avenue Du Mar\u00e9chal Foch 40990 Saint Paul Les Dax",
    "sg:city":"Angoum\u00e9",
    "sg:classifiers":[
        {
            "category":"Banks & Credit Unions",
            "subcategory":"Financial Services",
            "type":"Services"
        }
    ],
    "sg:phone":"+33 5 58 91 95 70",
    "sg:postcode":"40990",
    "sg:province":"Aquitaine",
    "sg:tags":[
        "banking",
        "finance",
        "insurance"
    ],
    "wof:name":"Eurisk",
    "wof:placetype":"venue"
},
  "geometry": {"coordinates":[-1.049491,43.732391],"type":"Point"}
}