{
  "type": "Feature",
  "properties": {
    "addr:full":"55, Rue du Mollaret - ZI les Chesnes, 38070 Saint Quentin Fallavier Rhone-Alpes 38070",
    "addr:housenumber":"55",
    "addr:postcode":"38070;38070",
    "addr:street":"Rue Du Mollaret Zi Les Chesnes",
    "iso:country":"FR",
    "sg:address":"55, Rue du Mollaret - ZI les Chesnes, 38070 Saint Quentin Fallavier",
    "sg:orig_category":"Non-Classified Establishments",
    "sg:phone":"+33 4 74 94 32 32",
    "sg:postcode":"38070",
    "sg:province":"Rhone-Alpes",
    "wof:name":"A.d. S.a.",
    "wof:placetype":"venue"
},
  "geometry": {"coordinates":[5.11081,45.632595],"type":"Point"}
}