{
  "type": "Feature",
  "properties": {
    "iso:country":"FR",
    "sg:address":"13 bd Rabatau; Marseille",
    "sg:classifiers":[
        {
            "category":"Banks & Credit Unions",
            "subcategory":"Bank",
            "type":"Services"
        }
    ],
    "sg:phone":"+33 3391174104",
    "sg:province":"Poitou-Charentes",
    "wof:name":"Sovac",
    "wof:placetype":"venue"
},
  "geometry": {"coordinates":[5.392273,43.273289],"type":"Point"}
}