{
  "type": "Feature",
  "properties": {
    "iso:country":"FR",
    "sg:address":"463, Rue Pierre et Marie Curie - ZI Ludres, 54710 Ludres",
    "sg:orig_category":"Non-Classified Establishments",
    "sg:phone":"+33 3 83 26 19 69",
    "sg:postcode":"54710",
    "sg:province":"Lorraine",
    "wof:name":"A.c.2m. S.a.r.l.",
    "wof:placetype":"venue"
},
  "geometry": {"coordinates":[6.161059,48.621563],"type":"Point"}
}