{
  "type": "Feature",
  "properties": {
    "addr:full":"66, Av. de Landshut, 60200 Compi\u00e8gne Picardie",
    "addr:postcode":"60200",
    "addr:street":"66 Av. De Landshut",
    "iso:country":"FR",
    "sg:address":"66, Av. de Landshut, 60200 Compi\u00e8gne",
    "sg:orig_category":"Unclassifiable Establishments",
    "sg:phone":"+33 3 44 23 45 96",
    "sg:province":"Picardie",
    "wof:name":"Dynal Biotech France S.a.",
    "wof:placetype":"venue"
},
  "geometry": {"coordinates":[2.796509,49.402233],"type":"Point"}
}