{
  "type": "Feature",
  "properties": {
    "iso:country":"FR",
    "sg:address":"41 bis, Av. de l'Europe, 78140 V\u00e9lizy Villacoublay",
    "sg:orig_category":"Unclassifiable Establishments",
    "sg:phone":"+33 1 34 63 09 40",
    "sg:province":"Ile de France",
    "wof:name":"Xircom France S.a.r.l.",
    "wof:placetype":"venue"
},
  "geometry": {"coordinates":[2.217197,48.779724],"type":"Point"}
}