{
  "type": "Feature",
  "properties": {
    "addr:full":"20, Rue Berbier du Mets, 75013 Paris Ile de France",
    "addr:housenumber":"20",
    "addr:postcode":"75013",
    "addr:street":"Rue Berbier Du Mets",
    "iso:country":"FR",
    "sg:address":"20, Rue Berbier du Mets, 75013 Paris",
    "sg:orig_category":"Unclassifiable Establishments",
    "sg:phone":"+33 1 44 08 49 00",
    "sg:province":"Ile de France",
    "wof:name":"Librairie Vuibert S.a.",
    "wof:placetype":"venue"
},
  "geometry": {"coordinates":[2.350419,48.835415],"type":"Point"}
}