{
  "type": "Feature",
  "properties": {
    "iso:country":"FR",
    "sg:address":"47 Rue Louis Blanc 92984 Paris La D\u00e9fense Cedex",
    "sg:classifiers":[
        {
            "category":"Professional",
            "subcategory":"Printing & Photocopies",
            "type":"Services"
        }
    ],
    "sg:phone":"+33 1 41 16 49 00",
    "sg:province":"Midi Pyr\u00e9n\u00e9es",
    "sg:tags":[
        "publishing"
    ],
    "wof:name":"Euredit Sa",
    "wof:placetype":"venue"
},
  "geometry": {"coordinates":[2.24119,48.888939],"type":"Point"}
}