{
  "type": "Feature",
  "properties": {
    "iso:country":"FR",
    "sg:address":"54 Rte Torigni 50890 Cond\u00e9 Sur Vire",
    "sg:city":"Cond\u00e9-sur-Vire",
    "sg:classifiers":[
        {
            "category":"Transit Center",
            "subcategory":"Freight",
            "type":"Transportation"
        }
    ],
    "sg:phone":"+33 2 33 57 67 47",
    "sg:postcode":"50890",
    "sg:province":"Basse Normandie",
    "sg:tags":[
        "metallurgy",
        "pipe",
        "metalworking",
        "sheet"
    ],
    "wof:name":"T E A M Sarl",
    "wof:placetype":"venue"
},
  "geometry": {"coordinates":[-0.998027,49.046772],"type":"Point"}
}