{
  "type": "Feature",
  "properties": {
    "addr:full":"10 Rue Charles Et Rene Auffray 92110 Clichy Ile de France",
    "addr:housenumber":"10",
    "addr:postcode":"92110",
    "addr:street":"Rue Charles Et Rene Auffray;Ile De France",
    "iso:country":"FR",
    "sg:address":"10 Rue Charles Et Rene Auffray 92110 Clichy",
    "sg:classifiers":[
        {
            "category":"Utilities",
            "subcategory":"Telephone",
            "type":"Services"
        }
    ],
    "sg:phone":"+33 1 41 40 84 40",
    "sg:province":"Ile de France",
    "sg:tags":[
        "telecommunication"
    ],
    "wof:name":"Axetel",
    "wof:placetype":"venue"
},
  "geometry": {"coordinates":[2.304313,48.902012],"type":"Point"}
}