{
  "type": "Feature",
  "properties": {
    "iso:country":"FR",
    "sg:address":"6, Rue de la Durance, 67100 Strasbourg",
    "sg:city":"Strasbourg",
    "sg:orig_category":"Unclassifiable Establishments",
    "sg:phone":"+33 3 88 79 71 00",
    "sg:postcode":"67100",
    "sg:province":"Alsace",
    "wof:name":"Pfaudler Werke S.a.r.l.",
    "wof:placetype":"venue"
},
  "geometry": {"coordinates":[7.733907,48.55204],"type":"Point"}
}