{
  "type": "Feature",
  "properties": {
    "addr:full":"3, Rue de Gail, 67210 Obernai Obernai Alsace 67210",
    "addr:housenumber":"3",
    "addr:postcode":"67210;67210",
    "addr:street":"Rue De Gail",
    "iso:country":"FR",
    "sg:address":"3, Rue de Gail, 67210 Obernai",
    "sg:city":"Obernai",
    "sg:orig_category":"Unclassifiable Establishments",
    "sg:phone":"+33 3 88 95 07 00",
    "sg:postcode":"67210",
    "sg:province":"Alsace",
    "wof:name":"A La Cour D'alsace",
    "wof:placetype":"venue"
},
  "geometry": {"coordinates":[7.479495,48.461506],"type":"Point"}
}