{
  "type": "Feature",
  "properties": {
    "addr:full":"Route De Cholet 85290 Mortagne Sur Sevre Pays de Loire 85290",
    "addr:postcode":"85290;sur sevre;85290",
    "addr:street":"Route De Cholet",
    "iso:country":"FR",
    "sg:address":"Route De Cholet 85290 Mortagne Sur Sevre",
    "sg:classifiers":[
        {
            "category":"Farming",
            "subcategory":"Farm",
            "type":"Manufacturing & Wholesale Goods"
        }
    ],
    "sg:phone":"+33 2 51 65 07 30",
    "sg:postcode":"85290",
    "sg:province":"Pays de Loire",
    "sg:tags":[
        "horticulture",
        "agriculture",
        "livestock"
    ],
    "wof:name":"Les Pepinieres De Mortagne Sa Ripaud",
    "wof:placetype":"venue"
},
  "geometry": {"coordinates":[-0.945369,46.996353],"type":"Point"}
}