{
  "type": "Feature",
  "properties": {
    "addr:full":"Zi Des Six Bottes 45190 Tavers Tavers Centre 45190",
    "addr:postcode":"45190;45190",
    "addr:street":"Des Six Bottes;Tavers",
    "iso:country":"FR",
    "sg:address":"Zi Des Six Bottes 45190 Tavers",
    "sg:city":"Tavers",
    "sg:classifiers":[
        {
            "category":"Shopping",
            "subcategory":"Hobbies, Toys, & Games",
            "type":"Retail Goods"
        }
    ],
    "sg:phone":"+33 2 38 46 33 00",
    "sg:postcode":"45190",
    "sg:province":"Centre",
    "sg:tags":[
        "product",
        "miscellaneous",
        "entertainment"
    ],
    "wof:name":"Plisson",
    "wof:placetype":"venue"
},
  "geometry": {"coordinates":[1.606415,47.763771],"type":"Point"}
}