{
  "type": "Feature",
  "properties": {
    "iso:country":"FR",
    "sg:address":"rue du Kemmel 59280 Armenti\u00e8res",
    "sg:classifiers":[
        {
            "category":"Autos & Motor Vehicles",
            "subcategory":"Fuel & Gas Station",
            "type":"Retail Goods"
        }
    ],
    "sg:phone":"+33 3 20 10 59 00",
    "sg:postcode":"59280",
    "sg:province":"Nord Pas-de-Calais",
    "sg:tags":[
        "appliance",
        "heating"
    ],
    "wof:name":"Solaronics Sa",
    "wof:placetype":"venue"
},
  "geometry": {"coordinates":[2.875385,50.691284],"type":"Point"}
}