{
  "type": "Feature",
  "properties": {
    "addr:full":"5, Bd Flandret, 75116 Paris Ile de France",
    "addr:housenumber":"5",
    "addr:postcode":"75116",
    "addr:street":"Bd Flandret",
    "iso:country":"FR",
    "sg:address":"5, Bd Flandret, 75116 Paris",
    "sg:orig_category":"Non-Classified Establishments",
    "sg:phone":"+33 1 45 04 80 21",
    "sg:province":"Ile de France",
    "wof:name":"E.c.n. S.a.r.l. - Edition Charles N\u00e9giar",
    "wof:placetype":"venue"
},
  "geometry": {"coordinates":[2.271668,48.864677],"type":"Point"}
}