{
  "type": "Feature",
  "properties": {
    "addr:full":"6 Rue Marsoulan 75012 Paris Ile de France 75012",
    "addr:housenumber":"6",
    "addr:postcode":"75012;75012",
    "addr:street":"Rue Marsoulan",
    "iso:country":"FR",
    "sg:address":"6 Rue Marsoulan 75012 Paris",
    "sg:classifiers":[
        {
            "category":"Retail",
            "subcategory":"Event Space",
            "type":"Services"
        }
    ],
    "sg:phone":"+33 1 43 43 33 13",
    "sg:postcode":"75012",
    "sg:province":"Ile de France",
    "sg:tags":[
        "product",
        "transport",
        "road",
        "miscellaneous"
    ],
    "wof:name":"Pompes Funebres Dulac Sa",
    "wof:placetype":"venue"
},
  "geometry": {"coordinates":[2.403009,48.845356],"type":"Point"}
}