{
  "type": "Feature",
  "properties": {
    "iso:country":"FR",
    "sg:address":"route de Fatines 72470 Champagne",
    "sg:classifiers":[
        {
            "category":"Social Services",
            "subcategory":"Retirement Home",
            "type":"Services"
        }
    ],
    "sg:phone":"+33 2 43 89 20 00",
    "sg:postcode":"72470",
    "sg:province":"Pays de Loire",
    "sg:tags":[
        "slipper",
        "house"
    ],
    "wof:name":"Etablissement Plastigom Sa",
    "wof:placetype":"venue"
},
  "geometry": {"coordinates":[0.39876,48.017715],"type":"Point"}
}