{
  "type": "Feature",
  "properties": {
    "addr:full":"36 Rue Scheffer BP 121 Trocad\u00e9ro 75116 Paris Cedex Midi Pyr\u00e9n\u00e9es",
    "addr:housenumber":"36;121",
    "addr:postcode":"75116",
    "addr:street":"Rue Scheffer Bp;Trocade\u0301Ro",
    "iso:country":"FR",
    "sg:address":"36 Rue Scheffer BP 121 Trocad\u00e9ro 75116 Paris Cedex",
    "sg:classifiers":[
        {
            "category":"Banks & Credit Unions",
            "subcategory":"Financial Services",
            "type":"Services"
        }
    ],
    "sg:phone":"+33 1 44 05 04 45",
    "sg:province":"Midi Pyr\u00e9n\u00e9es",
    "sg:tags":[
        "banking",
        "insurance",
        "institution",
        "finance"
    ],
    "wof:name":"Societe Financiere De Ma Seine Omega Recouvrement Sarl",
    "wof:placetype":"venue"
},
  "geometry": {"coordinates":[2.274115,48.864906],"type":"Point"}
}