{
  "type": "Feature",
  "properties": {
    "addr:full":"B.P. 1, 54470 Thiaucourt R\u00e9gni\u00e8ville^^7, Rte de Pont \u00e0 Mousson, 54470 Thiaucourt R\u00e9gni\u00e8ville Lorraine 54470",
    "addr:housenumber":"1",
    "addr:postcode":"54470;54470;54470",
    "addr:street":"B.P.;Rte De Pont A\u0300 Mousson;Re\u0301Gnie\u0300Ville Lorraine",
    "iso:country":"FR",
    "sg:address":"B.P. 1, 54470 Thiaucourt R\u00e9gni\u00e8ville^^7, Rte de Pont \u00e0 Mousson, 54470 Thiaucourt R\u00e9gni\u00e8ville",
    "sg:orig_category":"Non-Classified Establishments",
    "sg:phone":"+33 3 83 81 90 17",
    "sg:postcode":"54470",
    "sg:province":"Lorraine",
    "wof:name":"E.d.c. Protection S.a.",
    "wof:placetype":"venue"
},
  "geometry": {"coordinates":[5.862805,48.955154],"type":"Point"}
}