{
  "type": "Feature",
  "properties": {
    "addr:full":"1903, Av. Jacques Cartier - La Fr\u00e9gate, 44811 Saint Herblain C\u00e9dex Nord Pas-de-Calais",
    "addr:housenumber":"1903",
    "addr:postcode":"44811",
    "addr:street":"Av. Jacques Cartier La Fre\u0301Gate",
    "iso:country":"FR",
    "sg:address":"1903, Av. Jacques Cartier - La Fr\u00e9gate, 44811 Saint Herblain C\u00e9dex",
    "sg:orig_category":"Non-Classified Establishments",
    "sg:phone":"+33 2 47 25 35 35",
    "sg:province":"Nord Pas-de-Calais",
    "wof:name":"I.p.l. S.a.r.l. - Informatique Pays De Loire",
    "wof:placetype":"venue"
},
  "geometry": {"coordinates":[-1.636816,47.222179],"type":"Point"}
}