{
  "type": "Feature",
  "properties": {
    "iso:country":"FR",
    "sg:address":"avenue Chateaubriand 22500 Paimpol",
    "sg:city":"Paimpol",
    "sg:classifiers":[
        {
            "category":"Food & Beverages",
            "subcategory":"Fruits & Vegetables",
            "type":"Retail Goods"
        }
    ],
    "sg:phone":"+33 2 96 20 80 40",
    "sg:postcode":"22500",
    "sg:province":"Bretagne",
    "wof:name":"St\u00e9 Exploitation Libouban S.a.r.l.",
    "wof:placetype":"venue"
},
  "geometry": {"coordinates":[-3.043884,48.778053],"type":"Point"}
}