{
  "type": "Feature",
  "properties": {
    "iso:country":"FR",
    "sg:address":"73 Rue Gabriel Peri 42100 St Etienne",
    "sg:classifiers":[
        {
            "category":"Wholesale",
            "subcategory":"Machinery & Supplies",
            "type":"Manufacturing & Wholesale Goods"
        }
    ],
    "sg:phone":"+33 4 77 95 72 17",
    "sg:postcode":"42100",
    "sg:province":"Rhone-Alpes",
    "sg:tags":[
        "handling",
        "material",
        "-",
        "machine",
        "equipment",
        "engineering",
        "mechanical"
    ],
    "wof:name":"Societe Francaise Des Ascenseurs Kone",
    "wof:placetype":"venue"
},
  "geometry": {"coordinates":[4.385647,45.410816],"type":"Point"}
}