{
  "type": "Feature",
  "properties": {
    "addr:full":"25 Rue Bennefray 49140 Villeveque Pays de Loire",
    "addr:housenumber":"25",
    "addr:postcode":"49140",
    "addr:street":"Rue Bennefray;Villeveque",
    "iso:country":"FR",
    "sg:address":"25 Rue Bennefray 49140 Villeveque",
    "sg:classifiers":[
        {
            "category":"Manufacturing",
            "subcategory":"Rubber & Plastics",
            "type":"Manufacturing & Wholesale Goods"
        }
    ],
    "sg:phone":"+33 2 41 76 82 00",
    "sg:province":"Pays de Loire",
    "wof:name":"Outinov",
    "wof:placetype":"venue"
},
  "geometry": {"coordinates":[-0.430228,47.523178],"type":"Point"}
}