{
  "type": "Feature",
  "properties": {
    "iso:country":"FR",
    "sg:address":"Route D'Ocqu\u00e8rre Zi 77440 Lizy Sur Ourcq",
    "sg:classifiers":[
        {
            "category":"Manufacturing",
            "subcategory":"Metals",
            "type":"Manufacturing & Wholesale Goods"
        }
    ],
    "sg:phone":"+33 1 60 01 80 89",
    "sg:postcode":"77440",
    "sg:province":"Ile de France",
    "sg:tags":[
        "pipe",
        "sheet",
        "-",
        "metalworking",
        "metallic",
        "metallurgy",
        "finished"
    ],
    "wof:name":"Ets C. Basle",
    "wof:placetype":"venue"
},
  "geometry": {"coordinates":[3.01993,49.025009],"type":"Point"}
}