{
  "type": "Feature",
  "properties": {
    "addr:full":"ZI Sud Le Teil Rhone-Alpes 07400",
    "addr:postcode":"07400",
    "iso:country":"FR",
    "sg:address":"ZI Sud",
    "sg:city":"Le Teil",
    "sg:orig_category":"Unclassifiable Establishments",
    "sg:phone":"+33 4 75 49 27 39",
    "sg:postcode":"07400",
    "sg:province":"Rhone-Alpes",
    "wof:name":"Cartonnages Girard S.a.",
    "wof:placetype":"venue"
},
  "geometry": {"coordinates":[4.682274,44.549747],"type":"Point"}
}