{
  "type": "Feature",
  "properties": {
    "addr:full":"7 Pasquier 75008 PARIS Ile de France",
    "addr:housenumber":"7",
    "addr:postcode":"75008",
    "addr:street":"Pasquier",
    "iso:country":"FR",
    "sg:address":"7",
    "sg:city":"Pasquier 75008 PARIS",
    "sg:classifiers":[
        {
            "category":"Wholesale",
            "subcategory":"Machinery & Supplies",
            "type":"Manufacturing & Wholesale Goods"
        }
    ],
    "sg:phone":"+33 1 49 24 93 04",
    "sg:province":"Ile de France",
    "sg:tags":[
        "equipment",
        "precision"
    ],
    "wof:name":"Oxygen",
    "wof:placetype":"venue"
},
  "geometry": {"coordinates":[2.322957,48.871845],"type":"Point"}
}