{
  "type": "Feature",
  "properties": {
    "addr:full":"B.P. 15, 57480 Sierck les Bains^^44, Rue du Moulin, 57480 Sierck les Bains Lorraine 57480",
    "addr:postcode":"57480;57480;57480",
    "addr:street":"B.P. 15;Rue Du Moulin",
    "iso:country":"FR",
    "sg:address":"B.P. 15, 57480 Sierck les Bains^^44, Rue du Moulin, 57480 Sierck les Bains",
    "sg:orig_category":"Non-Classified Establishments",
    "sg:phone":"+33 3 82 83 22 65",
    "sg:postcode":"57480",
    "sg:province":"Lorraine",
    "wof:name":"Agepharm S.a.",
    "wof:placetype":"venue"
},
  "geometry": {"coordinates":[6.361142,49.440037],"type":"Point"}
}