{
  "type": "Feature",
  "properties": {
    "addr:full":"Rue Emile Basly 62820 Libercourt Nord Pas-de-Calais 62820",
    "addr:postcode":"62820;62820",
    "addr:street":"Rue Emile Basly",
    "iso:country":"FR",
    "sg:address":"Rue Emile Basly 62820 Libercourt",
    "sg:classifiers":[
        {
            "category":"Shopping",
            "type":"Retail Goods"
        }
    ],
    "sg:phone":"+33 3 21 37 13 55",
    "sg:postcode":"62820",
    "sg:province":"Nord Pas-de-Calais",
    "sg:tags":[
        "metallurgy",
        "finished",
        "-",
        "metalworking",
        "metallic"
    ],
    "wof:name":"Ets Haze Sa",
    "wof:placetype":"venue"
},
  "geometry": {"coordinates":[3.011428,50.473156],"type":"Point"}
}