{
  "type": "Feature",
  "properties": {
    "iso:country":"FR",
    "sg:address":"63220 Dore l'Eglise",
    "sg:city":"Arlanc",
    "sg:orig_category":"Non-Classified Establishments",
    "sg:phone":"+33 4 73 95 00 32",
    "sg:postcode":"63220",
    "sg:province":"Auvergne",
    "wof:name":"Etablissements Raz Et Ses Fils S.a.r.l.",
    "wof:placetype":"venue"
},
  "geometry": {"coordinates":[-104.03125799999999,47.917019],"type":"Point"}
}