{
  "type": "Feature",
  "properties": {
    "iso:country":"FR",
    "sg:address":"38 Av Des Champs Elys\u00e9es 75008 Paris",
    "sg:classifiers":[
        {
            "category":"Professional",
            "subcategory":"Business Services",
            "type":"Services"
        }
    ],
    "sg:phone":"+33 1 40 69 50 50",
    "sg:postcode":"75008",
    "sg:province":"Ile de France",
    "sg:tags":[
        "travel",
        "-",
        "transport",
        "air"
    ],
    "wof:name":"Varig Lignes Aerennes Br\u00c9siliennes",
    "wof:placetype":"venue"
},
  "geometry": {"coordinates":[2.307582,48.86998],"type":"Point"}
}