{
  "type": "Feature",
  "properties": {
    "iso:country":"FR",
    "sg:address":"35 Av Raymond Poincar\u00e9 75116 Paris",
    "sg:classifiers":[
        {
            "category":"Travel",
            "subcategory":"Hotels & Motels",
            "type":"Entertainment"
        }
    ],
    "sg:phone":"+33 1 53 70 09 09",
    "sg:province":"Champagne",
    "sg:tags":[
        "hotels",
        "business",
        "restaurant"
    ],
    "wof:name":"Hotel Au Palais De Chaillot",
    "wof:placetype":"venue"
},
  "geometry": {"coordinates":[2.286107,48.865902],"type":"Point"}
}