{
  "type": "Feature",
  "properties": {
    "iso:country":"FR",
    "sg:address":"31 Quai Du Rancy 94388 Bonneuil Sur Marne Cedex",
    "sg:classifiers":[
        {
            "category":"Professional",
            "subcategory":"Engineering",
            "type":"Services"
        }
    ],
    "sg:phone":"+33 1 41 94 54 54",
    "sg:province":"Rhone-Alpes",
    "sg:tags":[
        "machine",
        "-",
        "mechanical"
    ],
    "wof:name":"Ciat",
    "wof:placetype":"venue"
},
  "geometry": {"coordinates":[2.48475,48.777966],"type":"Point"}
}