{
  "type": "Feature",
  "properties": {
    "addr:full":"Rte de Guillon L'Isle sur Serein Bourgogne 89440",
    "addr:postcode":"89440",
    "addr:street":"Rte De Guillon",
    "iso:country":"FR",
    "sg:address":"Rte de Guillon",
    "sg:city":"L'Isle sur Serein",
    "sg:orig_category":"Unclassifiable Establishments",
    "sg:phone":"+33 3 86 33 83 33",
    "sg:postcode":"89440",
    "sg:province":"Bourgogne",
    "wof:name":"Billiat Et Compagnie S.a.r.l.",
    "wof:placetype":"venue"
},
  "geometry": {"coordinates":[3.994646,47.603165],"type":"Point"}
}