{
  "type": "Feature",
  "properties": {
    "addr:full":"239, Rte de Muret - Le Sirius B\u00e2t. B, 31100 Toulouse Midi Pyr\u00e9n\u00e9es",
    "addr:housenumber":"239",
    "addr:postcode":"31100",
    "addr:street":"Rte De Muret Le",
    "iso:country":"FR",
    "sg:address":"239, Rte de Muret - Le Sirius B\u00e2t. B, 31100 Toulouse",
    "sg:orig_category":"Unclassifiable Establishments",
    "sg:phone":"+33 5 61 43 48 00",
    "sg:province":"Midi Pyr\u00e9n\u00e9es",
    "wof:name":"Cerberus S\u00e9curit\u00e9 S.a.",
    "wof:placetype":"venue"
},
  "geometry": {"coordinates":[1.39859,43.56786],"type":"Point"}
}