{
  "type": "Feature",
  "properties": {
    "addr:full":"22 Rue Meynadier 06400 Cannes Rhone-Alpes",
    "addr:housenumber":"22",
    "addr:postcode":"06400",
    "addr:street":"Rue Meynadier",
    "iso:country":"FR",
    "sg:address":"22 Rue Meynadier 06400 Cannes",
    "sg:classifiers":[
        {
            "category":"Food & Beverages",
            "subcategory":"Dairy",
            "type":"Retail Goods"
        }
    ],
    "sg:phone":"+33 4 93 39 63 68",
    "sg:province":"Rhone-Alpes",
    "sg:tags":[
        "product",
        "related"
    ],
    "wof:name":"Ceneri Fromager Sarl",
    "wof:placetype":"venue"
},
  "geometry": {"coordinates":[7.014634,43.552788],"type":"Point"}
}