{
  "type": "Feature",
  "properties": {
    "addr:full":"54 Rue Ernest Macarez 59300 Valenciennes Nord Pas-de-Calais 59300",
    "addr:housenumber":"54",
    "addr:postcode":"59300;59300",
    "addr:street":"Rue Ernest Macarez",
    "iso:country":"FR",
    "sg:address":"54 Rue Ernest Macarez 59300 Valenciennes",
    "sg:classifiers":[
        {
            "category":"Social Services",
            "subcategory":"Job Training",
            "type":"Services"
        }
    ],
    "sg:phone":"+33 3 27 47 38 94",
    "sg:postcode":"59300",
    "sg:province":"Nord Pas-de-Calais",
    "sg:tags":[
        "good",
        "business",
        "advice",
        "-",
        "metalworking",
        "metallic",
        "metallurgy",
        "finished"
    ],
    "wof:name":"Nord Travaux Industries",
    "wof:placetype":"venue"
},
  "geometry": {"coordinates":[3.53655,50.372581],"type":"Point"}
}