{
  "type": "Feature",
  "properties": {
    "addr:full":"61, Rue Daguerre, 75014 Paris Ile de France 75014",
    "addr:housenumber":"61",
    "addr:postcode":"75014;75014",
    "addr:street":"Rue Daguerre",
    "iso:country":"FR",
    "sg:address":"61, Rue Daguerre, 75014 Paris",
    "sg:orig_category":"Non-Classified Establishments",
    "sg:phone":"+33 1 43 21 56 63",
    "sg:postcode":"75014",
    "sg:province":"Ile de France",
    "wof:name":"Essais 80 S.a.r.l.",
    "wof:placetype":"venue"
},
  "geometry": {"coordinates":[2.326451,48.835052],"type":"Point"}
}