{
  "type": "Feature",
  "properties": {
    "iso:country":"FR",
    "sg:address":"Rue Gabriel Benier - Bouviers",
    "sg:city":"Guyancourt",
    "sg:orig_category":"Non-Classified Establishments",
    "sg:phone":"+33 1 30 43 71 07",
    "sg:postcode":"78280",
    "sg:province":"Ile de France",
    "wof:name":"Exploitation Transports Mentre S.a.",
    "wof:placetype":"venue"
},
  "geometry": {"coordinates":[2.065967,48.780781],"type":"Point"}
}