{
  "type": "Feature",
  "properties": {
    "iso:country":"FR",
    "sg:address":"43 Rue S\u00e9bastien Bottin BP 1 54115 Favi\u00e8res",
    "sg:classifiers":[
        {
            "category":"Home & Garden",
            "subcategory":"Furniture",
            "type":"Retail Goods"
        }
    ],
    "sg:phone":"+33 3 83 15 28 40",
    "sg:province":"Lorraine",
    "sg:tags":[
        "wood"
    ],
    "wof:name":"Ets Thanry Sa",
    "wof:placetype":"venue"
},
  "geometry": {"coordinates":[5.946814,48.463928],"type":"Point"}
}