{
  "type": "Feature",
  "properties": {
    "addr:full":"6 Rue Louis De Broglie Dijon Bourgogne 21000",
    "addr:housenumber":"6",
    "addr:postcode":"21000",
    "addr:street":"Rue Louis De Broglie;Bourgogne",
    "iso:country":"FR",
    "sg:address":"6 Rue Louis De Broglie",
    "sg:city":"Dijon",
    "sg:classifiers":[
        {
            "category":"Banks & Credit Unions",
            "subcategory":"Financial Services",
            "type":"Services"
        }
    ],
    "sg:phone":"+33 3 80 78 84 80",
    "sg:postcode":"21000",
    "sg:province":"Bourgogne",
    "sg:tags":[
        "banking",
        "finance",
        "insurance"
    ],
    "wof:name":"Societe Fiduciaire Nationale D'expertise Comptable Fidexpert (fid)",
    "wof:placetype":"venue"
},
  "geometry": {"coordinates":[5.041119,47.356449],"type":"Point"}
}