{
  "type": "Feature",
  "properties": {
    "iso:country":"FR",
    "sg:address":"Le Croisy 44700 Orvault",
    "sg:classifiers":[
        {
            "category":"Autos & Motor Vehicles",
            "subcategory":"Automobile Sales",
            "type":"Retail Goods"
        }
    ],
    "sg:phone":"+33 2 40 16 81 81",
    "sg:postcode":"44700",
    "sg:province":"Pays de Loire",
    "sg:tags":[
        "equipment",
        "motor-cars",
        "transport"
    ],
    "wof:name":"Paris Maine Sa",
    "wof:placetype":"venue"
},
  "geometry": {"coordinates":[-1.623129,47.270981],"type":"Point"}
}