{
  "type": "Feature",
  "properties": {
    "addr:full":"9 rue de Poitou 75003 Paris Ile de France",
    "addr:housenumber":"9",
    "addr:postcode":"75003",
    "addr:street":"Rue De Poitou",
    "iso:country":"FR",
    "sg:address":"9 rue de Poitou 75003 Paris",
    "sg:classifiers":[
        {
            "category":"Manufacturing",
            "subcategory":"Rubber & Plastics",
            "type":"Manufacturing & Wholesale Goods"
        }
    ],
    "sg:phone":"+33 1 42 71 23 45",
    "sg:province":"Ile de France",
    "sg:tags":[
        "material"
    ],
    "wof:name":"3a Weber Outils Fournitures Ind. Sa",
    "wof:placetype":"venue"
},
  "geometry": {"coordinates":[2.363847,48.861271],"type":"Point"}
}