{
  "type": "Feature",
  "properties": {
    "iso:country":"FR",
    "sg:address":"B.P. 3, 67151 Erstein C\u00e9dex^^35, Rue Mal de Lattre de Tassigny, 67150 Erstein",
    "sg:city":"Erstein",
    "sg:orig_category":"Non-Classified Establishments",
    "sg:phone":"+33 3 88 59 89 59",
    "sg:postcode":"67150",
    "sg:province":"Alsace",
    "wof:name":"Firn S.a.r.l.",
    "wof:placetype":"venue"
},
  "geometry": {"coordinates":[7.66295,48.421101],"type":"Point"}
}