{
  "type": "Feature",
  "properties": {
    "iso:country":"FR",
    "sg:address":"3bis, Rue du G\u00e9n\u00e9ral Leclerc, 44100 Nantes",
    "sg:orig_category":"Unclassifiable Establishments",
    "sg:phone":"+33 2 40 35 60 00",
    "sg:province":"Pays de Loire",
    "wof:name":"Baumont & Associ\u00e9s S.a.r.l.",
    "wof:placetype":"venue"
},
  "geometry": {"coordinates":[-1.594446,47.218517],"type":"Point"}
}