{
  "type": "Feature",
  "properties": {
    "iso:country":"FR",
    "sg:address":"25 Rue Desrame 76620 Le Havre",
    "sg:city":"Le Havre",
    "sg:classifiers":[
        {
            "category":"Wholesale",
            "subcategory":"Medical Equipment & Supplies",
            "type":"Manufacturing & Wholesale Goods"
        }
    ],
    "sg:phone":"+33 2 35 46 01 07",
    "sg:postcode":"76600",
    "sg:province":"Haute Normandie",
    "sg:tags":[
        "instrument",
        "health",
        "-",
        "precision"
    ],
    "wof:name":"Bouette Dentaire",
    "wof:placetype":"venue"
},
  "geometry": {"coordinates":[0.099965,49.518211],"type":"Point"}
}