{
  "type": "Feature",
  "properties": {
    "addr:full":"33, Rue Piretins, 95110 Sannois Ile de France",
    "addr:housenumber":"33",
    "addr:postcode":"95110;ile",
    "addr:street":"Rue Piretins",
    "iso:country":"FR",
    "sg:address":"33, Rue Piretins, 95110 Sannois",
    "sg:orig_category":"Non-Classified Establishments",
    "sg:phone":"+33 1 39 80 65 20",
    "sg:province":"Ile de France",
    "wof:name":"Graphic Conseils S.a.s.",
    "wof:placetype":"venue"
},
  "geometry": {"coordinates":[2.252156,48.973068],"type":"Point"}
}