{
  "type": "Feature",
  "properties": {
    "iso:country":"FR",
    "sg:address":"125 Av Du Douard Zi Les Paluds Sud Lot 23 13400 Aubagne",
    "sg:classifiers":[
        {
            "category":"Manufacturing",
            "subcategory":"Rubber & Plastics",
            "type":"Manufacturing & Wholesale Goods"
        }
    ],
    "sg:phone":"+33 4 42 82 10 10",
    "wof:name":"Frans Bonhomme",
    "wof:placetype":"venue"
},
  "geometry": {"coordinates":[5.5687,43.292141],"type":"Point"}
}