{
  "type": "Feature",
  "properties": {
    "addr:full":"6, Rue Van Gogh, 93360 Neuilly Plaisance Ile de France 93360",
    "addr:housenumber":"6",
    "addr:postcode":"93360;93360",
    "addr:street":"Rue Van Gogh;Ile De France",
    "iso:country":"FR",
    "sg:address":"6, Rue Van Gogh, 93360 Neuilly Plaisance",
    "sg:orig_category":"Non-Classified Establishments",
    "sg:phone":"+33 1 49 44 25 50",
    "sg:postcode":"93360",
    "sg:province":"Ile de France",
    "wof:name":"Connexion S.a.",
    "wof:placetype":"venue"
},
  "geometry": {"coordinates":[2.516313,48.852322],"type":"Point"}
}