{
  "type": "Feature",
  "properties": {
    "addr:full":"38 Avenue De La Gde Marine Zi 84800 L Isle Sur La Sorgue Limousin",
    "addr:housenumber":"38",
    "addr:postcode":"84800",
    "addr:street":"Avenue De La Gde Marine Zi;Isle;La",
    "iso:country":"FR",
    "sg:address":"38 Avenue De La Gde Marine Zi 84800 L Isle Sur La Sorgue",
    "sg:classifiers":[
        {
            "category":"Autos & Motor Vehicles",
            "subcategory":"Automobile Sales",
            "type":"Retail Goods"
        }
    ],
    "sg:phone":"+33 4 90 20 61 77",
    "sg:province":"Limousin",
    "sg:tags":[
        "equipment",
        "motor-cars",
        "transport"
    ],
    "wof:name":"Guilhot Catalin",
    "wof:placetype":"venue"
},
  "geometry": {"coordinates":[5.053315,43.918144],"type":"Point"}
}