{
  "type": "Feature",
  "properties": {
    "addr:full":"22 Grande Rue; Guitres Haute Normandie",
    "addr:housenumber":"22",
    "addr:street":"Grande Rue Guitres Haute Normandie",
    "iso:country":"FR",
    "sg:address":"22 Grande Rue; Guitres",
    "sg:classifiers":[
        {
            "category":"Banks & Credit Unions",
            "subcategory":"Bank",
            "type":"Services"
        }
    ],
    "sg:phone":"+33 3357564440",
    "sg:province":"Haute Normandie",
    "wof:name":"Cr\u00e9dit Agricole Mutuel, Du Libournais",
    "wof:placetype":"venue"
},
  "geometry": {"coordinates":[-0.186515,45.040565],"type":"Point"}
}