{
  "type": "Feature",
  "properties": {
    "addr:full":"Za La Crau 13670 St Andiol",
    "addr:postcode":"13670",
    "addr:street":"Za La Crau",
    "iso:country":"FR",
    "sg:address":"Za La Crau 13670 St Andiol",
    "sg:orig_category":"Agriculture and Livestock Chemicals and Pharmaceuticals Chemistry - by-products Fruits and vegetable",
    "sg:phone":"+33 4 90 90 23 23",
    "wof:name":"Xeda International Sa",
    "wof:placetype":"venue"
},
  "geometry": {"coordinates":[4.94301,43.836479],"type":"Point"}
}