{
  "type": "Feature",
  "properties": {
    "iso:country":"FR",
    "sg:address":"1, Av. L\u00e9onard de Vinci, 33600 Pessac",
    "sg:city":"Pessac",
    "sg:orig_category":"Unclassifiable Establishments",
    "sg:phone":"+33 5 57 26 37 37",
    "sg:postcode":"33600",
    "sg:province":"Aquitaine",
    "wof:name":"O.d.i.m.a. S.a.r.l. - Organisation D\u00e9veloppement Informatique M\u00e9thode Assistance",
    "wof:placetype":"venue"
},
  "geometry": {"coordinates":[-0.653171,44.783344],"type":"Point"}
}