{
  "type": "Feature",
  "properties": {
    "iso:country":"FR",
    "sg:address":"ZI les Favi\u00e8res",
    "sg:city":"Lissieu",
    "sg:orig_category":"Unclassifiable Establishments",
    "sg:phone":"+33 4 72 54 99 99",
    "sg:postcode":"69380",
    "sg:province":"Rhone-Alpes",
    "wof:name":"Hysys Service S.a.",
    "wof:placetype":"venue"
},
  "geometry": {"coordinates":[4.742365,45.865833],"type":"Point"}
}