{
  "type": "Feature",
  "properties": {
    "iso:country":"FR",
    "sg:address":"16, Rue du Stade, 57415 Montbronn",
    "sg:orig_category":"Unclassifiable Establishments",
    "sg:phone":"+33 3 87 96 34 50",
    "sg:province":"Lorraine",
    "wof:name":"Philipp Et Fils Transports S.a.r.l.",
    "wof:placetype":"venue"
},
  "geometry": {"coordinates":[7.28991,48.989323],"type":"Point"}
}