{
  "type": "Feature",
  "properties": {
    "addr:full":"43 Grande Rue De La Coupee Bureau 71850 Charnay Les Macon Bourgogne 71850",
    "addr:housenumber":"43",
    "addr:postcode":"71850;71850",
    "addr:street":"Grande Rue De La Coupee Bureau",
    "iso:country":"FR",
    "sg:address":"43 Grande Rue De La Coupee Bureau",
    "sg:city":"71850 Charnay Les Macon",
    "sg:classifiers":[
        {
            "category":"Banks & Credit Unions",
            "subcategory":"Financial Services",
            "type":"Services"
        }
    ],
    "sg:phone":"+33 3 85 32 84 60",
    "sg:postcode":"71850",
    "sg:province":"Bourgogne",
    "sg:tags":[
        "banking",
        "finance",
        "insurance"
    ],
    "wof:name":"Caisse Regionale Credit Agricole Mutuel Centre Est (crcamce) Credit Agricole Centre Est",
    "wof:placetype":"venue"
},
  "geometry": {"coordinates":[4.811808,46.308296],"type":"Point"}
}