{
  "type": "Feature",
  "properties": {
    "iso:country":"FR",
    "sg:address":"6, Chemin des Terres - La Matassine , 73370 Le Bourget du Lac",
    "sg:orig_category":"Non-Classified Establishments",
    "sg:phone":"+33 4 79 25 39 30",
    "sg:postcode":"73370",
    "sg:province":"Rhone-Alpes",
    "wof:name":"Aertecnic S.a.r.l.",
    "wof:placetype":"venue"
},
  "geometry": {"coordinates":[5.86225,45.643875],"type":"Point"}
}