{
  "type": "Feature",
  "properties": {
    "addr:full":"Coat Conq 29900 Concarneau Concarneau Bretagne 29900",
    "addr:postcode":"29900;29900",
    "addr:street":"Coat Conq",
    "iso:country":"FR",
    "sg:address":"Coat Conq 29900 Concarneau",
    "sg:city":"Concarneau",
    "sg:classifiers":[
        {
            "category":"Farming",
            "subcategory":"Farm",
            "type":"Manufacturing & Wholesale Goods"
        }
    ],
    "sg:phone":"+33 2 98 97 24 92",
    "sg:postcode":"29900",
    "sg:province":"Bretagne",
    "sg:tags":[
        "horticulture",
        "agriculture",
        "livestock"
    ],
    "wof:name":"Coop\u00c9rative Des Agriculteurs De Bretagne",
    "wof:placetype":"venue"
},
  "geometry": {"coordinates":[-3.896915,47.929485],"type":"Point"}
}