{
  "type": "Feature",
  "properties": {
    "iso:country":"FR",
    "sg:address":"Rue Maurice Ravel - La Cogne",
    "sg:city":"La Chapelle sur Erdre",
    "sg:orig_category":"Non-Classified Establishments",
    "sg:phone":"+33 2 40 72 00 73",
    "sg:postcode":"44240",
    "sg:province":"Pays de Loire",
    "wof:name":"Grelier S.a.r.l.",
    "wof:placetype":"venue"
},
  "geometry": {"coordinates":[-1.55739,47.288681],"type":"Point"}
}