{
  "type": "Feature",
  "properties": {
    "addr:full":"32, Rue de la R\u00e9publique, 80000 Amiens Picardie 80000",
    "addr:housenumber":"32",
    "addr:postcode":"80000;80000",
    "addr:street":"Rue De La Re\u0301Publique",
    "iso:country":"FR",
    "sg:address":"32, Rue de la R\u00e9publique, 80000 Amiens",
    "sg:orig_category":"Non-Classified Establishments",
    "sg:phone":"+33 3 22 91 28 57",
    "sg:postcode":"80000",
    "sg:province":"Picardie",
    "wof:name":"B.r.l. Bienvenu Jean S.a.",
    "wof:placetype":"venue"
},
  "geometry": {"coordinates":[2.296558,49.891525],"type":"Point"}
}