{
  "type": "Feature",
  "properties": {
    "addr:full":"Escudier Nord 19270 Donzenac Limousin 19270",
    "addr:postcode":"19270;19270",
    "addr:street":"Escudier",
    "iso:country":"FR",
    "sg:address":"Escudier Nord 19270 Donzenac",
    "sg:orig_category":"Miscellaneous Products",
    "sg:phone":"+33 5 55 85 62 11",
    "sg:postcode":"19270",
    "sg:province":"Limousin",
    "wof:name":"Fisa Pac Fournitures Indles De Services Automatiques Packaging",
    "wof:placetype":"venue"
},
  "geometry": {"coordinates":[1.50646,45.189976],"type":"Point"}
}