{
  "type": "Feature",
  "properties": {
    "addr:full":"Traverse Gaston De Flotte Parc Activites Faienciers 13012 Marseille Poitou-Charentes",
    "addr:postcode":"13012",
    "addr:street":"Traverse Gaston De Flotte Parc Activites Faienciers",
    "iso:country":"FR",
    "sg:address":"Traverse Gaston De Flotte Parc Activites Faienciers 13012 Marseille",
    "sg:classifiers":[
        {
            "category":"Professional",
            "subcategory":"Engineering",
            "type":"Services"
        }
    ],
    "sg:phone":"+33 4 91 89 90 91",
    "sg:province":"Poitou-Charentes",
    "sg:tags":[
        "machine",
        "-",
        "mechanical"
    ],
    "wof:name":"Refrigeration Industrielle Et Commerciale (ric)",
    "wof:placetype":"venue"
},
  "geometry": {"coordinates":[5.427532,43.296833],"type":"Point"}
}