{
  "type": "Feature",
  "properties": {
    "iso:country":"FR",
    "sg:address":"8 B Avenue De Buffon 45100 Orleans",
    "sg:city":"Orl\u00e9ans",
    "sg:classifiers":[
        {
            "category":"Health Services",
            "subcategory":"Medical Lab",
            "type":"Services"
        }
    ],
    "sg:phone":"+33 2 38 49 36 66",
    "sg:postcode":"45100",
    "sg:province":"Centre",
    "sg:tags":[
        "chemical",
        "pharmaceutical",
        "pharmacy"
    ],
    "wof:name":"Ocp Repartition",
    "wof:placetype":"venue"
},
  "geometry": {"coordinates":[1.941975,47.822613],"type":"Point"}
}