{
  "type": "Feature",
  "properties": {
    "iso:country":"FR",
    "sg:address":"B.P. 92, 83181 Six Fours les Plages^^131, Av. de Lattre de Tassigny - Les G\u00e9meaux , 83140 Six Fours ",
    "sg:city":"Assigny",
    "sg:orig_category":"Non-Classified Establishments",
    "sg:phone":"+33 4 94 34 34 34",
    "sg:postcode":"18260",
    "sg:province":"Centre",
    "wof:name":"A. T. E. C. I. Ing\u00e9nierie S. A. - Assistance Technique D'etudes Et De Conceptions Industrielles",
    "wof:placetype":"venue"
},
  "geometry": {"coordinates":[-0.628503,45.173199],"type":"Point"}
}