{
  "type": "Feature",
  "properties": {
    "iso:country":"FR",
    "sg:address":"Parc des Aliz\u00e9s II",
    "sg:city":"Sandouville",
    "sg:orig_category":"Unclassifiable Establishments",
    "sg:phone":"+33 2 32 79 25 40",
    "sg:postcode":"76430",
    "sg:province":"Haute Normandie",
    "wof:name":"Onet Propret\u00e9 S.a.",
    "wof:placetype":"venue"
},
  "geometry": {"coordinates":[0.288194,49.494537],"type":"Point"}
}