{
  "type": "Feature",
  "properties": {
    "addr:full":"rue du Port 33120 Arcachon Arcachon Aquitaine 33120",
    "addr:postcode":"33120;33120",
    "addr:street":"Rue Du Port",
    "iso:country":"FR",
    "sg:address":"rue du Port 33120 Arcachon",
    "sg:city":"Arcachon",
    "sg:classifiers":[
        {
            "category":"Food & Beverages",
            "subcategory":"Meat & Fish",
            "type":"Retail Goods"
        }
    ],
    "sg:phone":"+33 5 57 72 29 67",
    "sg:postcode":"33120",
    "sg:province":"Aquitaine",
    "sg:tags":[
        "fresh"
    ],
    "wof:name":"Arca-coop Sa",
    "wof:placetype":"venue"
},
  "geometry": {"coordinates":[-1.147664,44.657295],"type":"Point"}
}