{
  "type": "Feature",
  "properties": {
    "addr:full":"La Batteuse 01130 Lalleyriat Rhone-Alpes 01130",
    "addr:postcode":"01130;01130",
    "addr:street":"Rhone-Alpes",
    "iso:country":"FR",
    "sg:address":"La Batteuse 01130 Lalleyriat",
    "sg:classifiers":[
        {
            "category":"Home & Garden",
            "subcategory":"Furniture",
            "type":"Retail Goods"
        }
    ],
    "sg:phone":"+33 4 74 75 30 84",
    "sg:postcode":"01130",
    "sg:province":"Rhone-Alpes",
    "sg:tags":[
        "wood"
    ],
    "wof:name":"Vion Dury Sarl",
    "wof:placetype":"venue"
},
  "geometry": {"coordinates":[5.696632,46.19223],"type":"Point"}
}