{
  "type": "Feature",
  "properties": {
    "iso:country":"FR",
    "sg:address":"146 Rue De Fontenay 94300 Vincennes",
    "sg:classifiers":[
        {
            "category":"Manufacturing",
            "subcategory":"Chemicals & Compounds",
            "type":"Manufacturing & Wholesale Goods"
        }
    ],
    "sg:phone":"+33 1 43 98 18 18",
    "sg:postcode":"94300",
    "sg:province":"Ile de France",
    "sg:tags":[
        "pharmaceutical",
        "chemistry",
        "-",
        "by-product"
    ],
    "wof:name":"Marionnaud Espaces",
    "wof:placetype":"venue"
},
  "geometry": {"coordinates":[2.436049,48.848537],"type":"Point"}
}