{
  "type": "Feature",
  "properties": {
    "addr:full":"63 Rue Du Faubourg Saint-Lazare 59600 Maubeuge Nord Pas-de-Calais",
    "addr:housenumber":"63",
    "addr:postcode":"59600",
    "addr:street":"Rue Du Faubourg Saint-Lazare",
    "iso:country":"FR",
    "sg:address":"63 Rue Du Faubourg Saint-Lazare 59600 Maubeuge",
    "sg:classifiers":[
        {
            "category":"Professional",
            "type":"Services"
        }
    ],
    "sg:phone":"+33 3 27 62 17 16",
    "sg:province":"Nord Pas-de-Calais",
    "sg:tags":[
        "transport",
        "road"
    ],
    "wof:name":"Somatra",
    "wof:placetype":"venue"
},
  "geometry": {"coordinates":[3.960048,50.280293],"type":"Point"}
}