{
  "type": "Feature",
  "properties": {
    "iso:country":"FR",
    "sg:address":"Rte d'Olmet",
    "sg:city":"Augerolles",
    "sg:orig_category":"Unclassifiable Establishments",
    "sg:phone":"+33 4 73 53 51 49",
    "sg:postcode":"63930",
    "sg:province":"Auvergne",
    "wof:name":"Gouttesolard Bois S.a.",
    "wof:placetype":"venue"
},
  "geometry": {"coordinates":[3.62047,45.72414],"type":"Point"}
}