{
  "type": "Feature",
  "properties": {
    "iso:country":"FR",
    "sg:address":"222/224, Rue Louis Auguste Blanqui, 93140 Bondy",
    "sg:orig_category":"Unclassifiable Establishments",
    "sg:phone":"+33 1 48 49 97 00",
    "sg:province":"Ile de France",
    "wof:name":"Silium S.a.",
    "wof:placetype":"venue"
},
  "geometry": {"coordinates":[2.497162,48.896328],"type":"Point"}
}