{
  "type": "Feature",
  "properties": {
    "iso:country":"FR",
    "sg:address":"Le Ch\u00eane des Perri\u00e8res",
    "sg:city":"Fay de Bretagne",
    "sg:orig_category":"Unclassifiable Establishments",
    "sg:phone":"+33 2 40 92 31 12",
    "sg:postcode":"44130",
    "sg:province":"Pays de Loire",
    "wof:name":"Franguy S.a.r.l.",
    "wof:placetype":"venue"
},
  "geometry": {"coordinates":[-1.766288,47.356403],"type":"Point"}
}