{
  "type": "Feature",
  "properties": {
    "iso:country":"FR",
    "sg:address":"22 Av Marcel Dassault Zi De Larnay 86580 Biard",
    "sg:classifiers":[
        {
            "category":"Building & Trades",
            "subcategory":"Construction",
            "type":"Services"
        }
    ],
    "sg:phone":"+33 5 49 58 65 75",
    "sg:postcode":"86580",
    "sg:province":"Poitou-Charentes",
    "sg:tags":[
        "work",
        "public"
    ],
    "wof:name":"Sacer Atlantique",
    "wof:placetype":"venue"
},
  "geometry": {"coordinates":[0.27321,46.575256],"type":"Point"}
}