{
  "type": "Feature",
  "properties": {
    "addr:full":"76 bis, Rte de Nevers, 58180 Marzy Marzy Bourgogne 58180",
    "addr:housenumber":"76 bis",
    "addr:postcode":"58180;58180",
    "addr:street":"Rte De Nevers",
    "iso:country":"FR",
    "sg:address":"76 bis, Rte de Nevers, 58180 Marzy",
    "sg:city":"Marzy",
    "sg:orig_category":"Non-Classified Establishments",
    "sg:phone":"+33 3 86 58 83 85",
    "sg:postcode":"58180",
    "sg:province":"Bourgogne",
    "wof:name":"Mgp Prieur S.a.r.l.",
    "wof:placetype":"venue"
},
  "geometry": {"coordinates":[3.088412,47.012135],"type":"Point"}
}