{
  "type": "Feature",
  "properties": {
    "iso:country":"FR",
    "sg:address":"14 Rue De La R\u00e9publique 57240 Knutange",
    "sg:classifiers":[
        {
            "category":"Bakery",
            "type":"Food & Drink"
        }
    ],
    "sg:phone":"+33 3 82 85 82 25",
    "sg:postcode":"57240",
    "sg:province":"Lorraine",
    "sg:tags":[
        "cake",
        "product",
        "related",
        "bread"
    ],
    "wof:name":"Sarl Le Fournil De Stan",
    "wof:placetype":"venue"
},
  "geometry": {"coordinates":[6.044648,49.338261],"type":"Point"}
}