{
  "type": "Feature",
  "properties": {
    "addr:full":"B.P. 62 L'Arbresle C\u00e9dex^^La Martini\u00e8re 69210 Bully Rhone-Alpes 69592",
    "addr:postcode":"69210;69592",
    "addr:street":"B.P. 62;Ce\u0301Dex^^La Martinie\u0300Re",
    "iso:country":"FR",
    "sg:address":"B.P. 62",
    "sg:city":"L'Arbresle C\u00e9dex^^La Martini\u00e8re 69210 Bully",
    "sg:orig_category":"Non-Classified Establishments",
    "sg:phone":"+33 4 74 01 65 90",
    "sg:postcode":"69592",
    "sg:province":"Rhone-Alpes",
    "wof:name":"Les Vignerons De La Cave Bully",
    "wof:placetype":"venue"
},
  "geometry": {"coordinates":[4.611003,45.85099],"type":"Point"}
}