{
  "type": "Feature",
  "properties": {
    "addr:full":"B.P. 174, 47005 Agen C\u00e9dex^^Rue de Pechabout, 47000 Agen Agen Aquitaine 47000",
    "addr:housenumber":"b.p. 174",
    "addr:postcode":"47005;47000;47000",
    "iso:country":"FR",
    "sg:address":"B.P. 174, 47005 Agen C\u00e9dex^^Rue de Pechabout, 47000 Agen",
    "sg:city":"Agen",
    "sg:orig_category":"Non-Classified Establishments",
    "sg:phone":"+33 5 53 77 90 00",
    "sg:postcode":"47000",
    "sg:province":"Aquitaine",
    "wof:name":"Centre Gestion Economique Rurale Du Lot Et Garonne",
    "wof:placetype":"venue"
},
  "geometry": {"coordinates":[0.62061,44.205109],"type":"Point"}
}