{
  "type": "Feature",
  "properties": {
    "addr:full":"295 R du Pr Paul Milliez 94500 Champigny sur Marne Ile de France",
    "addr:housenumber":"295",
    "addr:postcode":"94500",
    "addr:street":"R Du Pr Paul Milliez",
    "iso:country":"FR",
    "sg:address":"295 R du Pr Paul Milliez 94500 Champigny sur Marne",
    "sg:classifiers":[
        {
            "category":"Wholesale",
            "subcategory":"Machinery & Supplies",
            "type":"Manufacturing & Wholesale Goods"
        }
    ],
    "sg:phone":"+33 1 41 77 62 00",
    "sg:province":"Ile de France",
    "sg:tags":[
        "industry",
        "workshop"
    ],
    "wof:name":"Fors France S.a.",
    "wof:placetype":"venue"
},
  "geometry": {"coordinates":[2.534934,48.81509],"type":"Point"}
}