{
  "type": "Feature",
  "properties": {
    "addr:full":"28/30, Av. Edouard Vaillant, 93500 Pantin Ile de France",
    "addr:housenumber":"28 / 30",
    "addr:postcode":"93500;ile",
    "addr:street":"Av. Edouard Vaillant",
    "iso:country":"FR",
    "sg:address":"28/30, Av. Edouard Vaillant, 93500 Pantin",
    "sg:orig_category":"Non-Classified Establishments",
    "sg:phone":"+33 1 41 83 63 63",
    "sg:province":"Ile de France",
    "wof:name":"L.d.i. S.a.r.l. - La D\u00e9coupe Industrielle",
    "wof:placetype":"venue"
},
  "geometry": {"coordinates":[2.395745,48.900154],"type":"Point"}
}