{
  "type": "Feature",
  "properties": {
    "iso:country":"FR",
    "sg:address":"33, Rue Faidherbe, 59410 Anzin",
    "sg:orig_category":"Non-Classified Establishments",
    "sg:phone":"+33 3 27 21 50 50",
    "sg:province":"Nord Pas-de-Calais",
    "wof:name":"Gaz Service S.a.r.l.",
    "wof:placetype":"venue"
},
  "geometry": {"coordinates":[3.502881,50.368778],"type":"Point"}
}