{
  "type": "Feature",
  "properties": {
    "iso:country":"FR",
    "sg:address":"3 Rue Alexandre Dumas 93400 St Ouen",
    "sg:classifiers":[
        {
            "category":"Autos & Motor Vehicles",
            "subcategory":"Automobile Sales",
            "type":"Retail Goods"
        }
    ],
    "sg:phone":"+33 1 40 11 75 48",
    "sg:postcode":"93400",
    "sg:province":"Ile de France",
    "sg:tags":[
        "equipment",
        "motor-cars",
        "transport"
    ],
    "wof:name":"Societe Par Actions Simplifiee Marais",
    "wof:placetype":"venue"
},
  "geometry": {"coordinates":[2.327335,48.90543],"type":"Point"}
}