{
  "type": "Feature",
  "properties": {
    "addr:full":"18, bd Louis Seguin, 92707 Colombes C\u00e9dex \u00cele-de-France",
    "addr:housenumber":"18",
    "addr:postcode":"92707",
    "addr:street":"Bd Louis Seguin;Ce\u0301Dex",
    "iso:country":"FR",
    "sg:address":"18, bd Louis Seguin, 92707 Colombes C\u00e9dex",
    "sg:orig_category":"Unclassifiable Establishments",
    "sg:phone":"+33 1 41 30 50 10",
    "sg:province":"\u00cele-de-France",
    "wof:name":"Hispano Suiza S.a.r.l.",
    "wof:placetype":"venue"
},
  "geometry": {"coordinates":[2.248452,48.933865],"type":"Point"}
}