{
  "type": "Feature",
  "properties": {
    "iso:country":"FR",
    "sg:address":"B.P. 149, 84304 Cavaillon C\u00e9dex^^Rte de l'Isle sur Sorgue, 84300 Cavaillon",
    "sg:orig_category":"Non-Classified Establishments",
    "sg:phone":"+33 4 90 71 69 33",
    "sg:province":"Provence-Alpes-C\u00f4te d'Azur",
    "wof:name":"L'electricit\u00e9 Fran\u00e7aise S.a.r.l.",
    "wof:placetype":"venue"
},
  "geometry": {"coordinates":[5.04855,43.84869],"type":"Point"}
}