{
  "type": "Feature",
  "properties": {
    "iso:country":"FR",
    "sg:address":"92643 Boulogne Billancourt C\u00e9dex^^126, Rue Galli\u00e9na, 92100 Boulogne Billancourt",
    "sg:orig_category":"Non-Classified Establishments",
    "sg:phone":"+33 1 69 82 60 60",
    "sg:province":"Ile de France",
    "wof:name":"Hewlett Packard France S.a.s.",
    "wof:placetype":"venue"
},
  "geometry": {"coordinates":[2.24102,48.835155],"type":"Point"}
}