{
  "type": "Feature",
  "properties": {
    "iso:country":"FR",
    "sg:address":"5, Rte de Stains, 94380 Bonneuil sur Marne",
    "sg:orig_category":"Unclassifiable Establishments",
    "sg:phone":"+33 1 43 77 28 04",
    "sg:province":"Ile de France",
    "wof:name":"Spiro France S.a.",
    "wof:placetype":"venue"
},
  "geometry": {"coordinates":[2.493952,48.781803],"type":"Point"}
}