{
  "type": "Feature",
  "properties": {
    "addr:full":"252, Av Henri Dunant, 54700 Pont \u00e0 Mousson Lorraine",
    "addr:postcode":"54700",
    "addr:street":"252 Av Henri Dunant",
    "iso:country":"FR",
    "sg:address":"252, Av Henri Dunant, 54700 Pont \u00e0 Mousson",
    "sg:orig_category":"Unclassifiable Establishments",
    "sg:phone":"+33 3 83 82 15 95",
    "sg:province":"Lorraine",
    "wof:name":"Trentin Armand",
    "wof:placetype":"venue"
},
  "geometry": {"coordinates":[6.05625,48.919613],"type":"Point"}
}