{
  "type": "Feature",
  "properties": {
    "iso:country":"FR",
    "sg:address":"11, Av. Karl Marx, 69120 Vaulx en Velin",
    "sg:orig_category":"Unclassifiable Establishments",
    "sg:phone":"+33 4 37 45 03 78",
    "sg:postcode":"69120",
    "sg:province":"Rhone-Alpes",
    "wof:name":"J.p.f. Machines-outils S.a.r.l.",
    "wof:placetype":"venue"
},
  "geometry": {"coordinates":[4.937609,45.776543],"type":"Point"}
}