{
  "type": "Feature",
  "properties": {
    "addr:full":"Rue Rosa Luxembourg Eragny Ile de France 95610",
    "addr:postcode":"95610",
    "addr:street":"Rue Rosa Luxembourg Eragny Ile De France",
    "iso:country":"FR",
    "sg:address":"Rue Rosa Luxembourg",
    "sg:city":"Eragny",
    "sg:orig_category":"Non-Classified Establishments",
    "sg:phone":"+33 1 34 02 40 40",
    "sg:postcode":"95610",
    "sg:province":"Ile de France",
    "wof:name":"Spectro France S.a.r.l.",
    "wof:placetype":"venue"
},
  "geometry": {"coordinates":[2.106449,49.026134],"type":"Point"}
}