{
  "type": "Feature",
  "properties": {
    "iso:country":"FR",
    "sg:address":"155, Rue du Docteur Bauer - Energy park 3, 93400 Saint Ouen",
    "sg:orig_category":"Non-Classified Establishments",
    "sg:phone":"+33 1 49 18 16 40",
    "sg:postcode":"93400",
    "sg:province":"Ile de France",
    "wof:name":"Commend France S.a.r.l.",
    "wof:placetype":"venue"
},
  "geometry": {"coordinates":[2.333555,48.911171],"type":"Point"}
}