{
  "type": "Feature",
  "properties": {
    "iso:country":"FR",
    "sg:address":"B.P. 1, 67290 Petersbach^^50, Rue Principale, 67290 Petersbach",
    "sg:city":"Petersbach",
    "sg:orig_category":"Non-Classified Establishments",
    "sg:phone":"+33 3 88 70 45 66",
    "sg:postcode":"67290",
    "sg:province":"Alsace",
    "wof:name":"Carri\u00e8res Reinberger S.a.",
    "wof:placetype":"venue"
},
  "geometry": {"coordinates":[7.38129,48.91753],"type":"Point"}
}