{
  "type": "Feature",
  "properties": {
    "addr:full":"RN 7 - Rte d'Aix Brignoles Nord Pas-de-Calais 83170",
    "addr:postcode":"83170",
    "addr:street":"Rn 7 Rte D'Aix Brignoles Nord",
    "iso:country":"FR",
    "sg:address":"RN 7 - Rte d'Aix",
    "sg:city":"Brignoles",
    "sg:orig_category":"Non-Classified Establishments",
    "sg:phone":"+33 4 94 37 08 08",
    "sg:postcode":"83170",
    "sg:province":"Nord Pas-de-Calais",
    "wof:name":"Blanc Et Rochebois S.a.",
    "wof:placetype":"venue"
},
  "geometry": {"coordinates":[6.00598,43.396832],"type":"Point"}
}