{
  "type": "Feature",
  "properties": {
    "addr:full":"13 R De La Poudri\u00e8re 13090 Aix En Provence Nord Pas-de-Calais",
    "addr:housenumber":"13",
    "addr:postcode":"13090",
    "addr:street":"R De La Poudrie\u0300Re;En Provence Nord",
    "iso:country":"FR",
    "sg:address":"13 R De La Poudri\u00e8re 13090 Aix En Provence",
    "sg:classifiers":[
        {
            "category":"Professional",
            "subcategory":"Business Services",
            "type":"Services"
        }
    ],
    "sg:phone":"+33 4 42 59 14 02",
    "sg:province":"Nord Pas-de-Calais",
    "sg:tags":[
        "training",
        "advice"
    ],
    "wof:name":"Ass Bac 2000",
    "wof:placetype":"venue"
},
  "geometry": {"coordinates":[5.4453,43.520981],"type":"Point"}
}