{
  "type": "Feature",
  "properties": {
    "iso:country":"FR",
    "sg:address":"39, Rue Saint-Livier, 57000 Metz",
    "sg:orig_category":"Unclassifiable Establishments",
    "sg:phone":"+33 3 87 62 28 00",
    "sg:province":"Lorraine",
    "wof:name":"Compagnie Fran\u00e7aise Assistance Technique S.a.",
    "wof:placetype":"venue"
},
  "geometry": {"coordinates":[6.174464,49.100422],"type":"Point"}
}