{
  "type": "Feature",
  "properties": {
    "addr:full":"32, rue du Commerce, 51350 Cormontreuil Champagne",
    "addr:housenumber":"32",
    "addr:postcode":"51350",
    "addr:street":"Rue Du Commerce",
    "iso:country":"FR",
    "sg:address":"32, rue du Commerce, 51350 Cormontreuil",
    "sg:orig_category":"Unclassifiable Establishments",
    "sg:phone":"+33 3 26 82 89 89",
    "sg:province":"Champagne",
    "wof:name":"Rem Isol S.a.",
    "wof:placetype":"venue"
},
  "geometry": {"coordinates":[4.06664,49.214504],"type":"Point"}
}