{
  "type": "Feature",
  "properties": {
    "addr:full":"Bd Jean Monnet Zi 49360 Maul\u00e9vrier Pays de Loire",
    "addr:postcode":"49360",
    "addr:street":"Bd Jean Monnet Zi",
    "iso:country":"FR",
    "sg:address":"Bd Jean Monnet Zi 49360 Maul\u00e9vrier",
    "sg:classifiers":[
        {
            "category":"Manufacturing",
            "subcategory":"Rubber & Plastics",
            "type":"Manufacturing & Wholesale Goods"
        }
    ],
    "sg:phone":"+33 2 41 55 00 92",
    "sg:province":"Pays de Loire",
    "wof:name":"Plastil France Sa",
    "wof:placetype":"venue"
},
  "geometry": {"coordinates":[-0.641124,46.999599],"type":"Point"}
}