{
  "type": "Feature",
  "properties": {
    "addr:full":"10/12, Av. Charles de Gaulle, 77340 Pontault Combault Ile de France",
    "addr:housenumber":"10 / 12",
    "addr:postcode":"77340",
    "addr:street":"Av. Charles De Gaulle",
    "iso:country":"FR",
    "sg:address":"10/12, Av. Charles de Gaulle, 77340 Pontault Combault",
    "sg:orig_category":"Non-Classified Establishments",
    "sg:phone":"+33 825 00 02 15",
    "sg:province":"Ile de France",
    "wof:name":"Texacad S.a.r.l.",
    "wof:placetype":"venue"
},
  "geometry": {"coordinates":[2.617165,48.804703],"type":"Point"}
}