{
  "type": "Feature",
  "properties": {
    "addr:full":"ZA le Haut Coin Aigrefeuille sur Maine Pays de Loire 44140",
    "addr:postcode":"44140",
    "addr:street":"Za;Aigrefeuille;Maine",
    "iso:country":"FR",
    "sg:address":"ZA le Haut Coin",
    "sg:city":"Aigrefeuille sur Maine",
    "sg:orig_category":"Non-Classified Establishments",
    "sg:phone":"+33 2 40 33 57 33",
    "sg:postcode":"44140",
    "sg:province":"Pays de Loire",
    "wof:name":"T.d.p. S.a. - Techniques De Plasturgie",
    "wof:placetype":"venue"
},
  "geometry": {"coordinates":[-1.399704,47.07658],"type":"Point"}
}