{
  "type": "Feature",
  "properties": {
    "iso:country":"FR",
    "sg:address":"Rue Colombier Zi La Boistardiere 37530 Charge",
    "sg:city":"Charg\u00e9",
    "sg:classifiers":[
        {
            "category":"Travel",
            "subcategory":"Hotels & Motels",
            "type":"Entertainment"
        }
    ],
    "sg:phone":"+33 2 47 30 60 00",
    "sg:postcode":"37530",
    "sg:province":"Centre",
    "sg:tags":[
        "hotels",
        "business",
        "restaurant"
    ],
    "wof:name":"Etablissements Bontemps",
    "wof:placetype":"venue"
},
  "geometry": {"coordinates":[1.05566,47.409721],"type":"Point"}
}