{
  "type": "Feature",
  "properties": {
    "addr:full":"98 RUE ALBERT VANDERHAGHEN 59320 Haubourdin Nord Pas-de-Calais 59320",
    "addr:housenumber":"98",
    "addr:postcode":"59320;59320",
    "addr:street":"Rue Albert Vanderhaghen",
    "iso:country":"FR",
    "sg:address":"98 RUE ALBERT VANDERHAGHEN 59320 Haubourdin",
    "sg:classifiers":[
        {
            "category":"Wholesale",
            "subcategory":"Wine & Distilled Alcoholic Beverages",
            "type":"Manufacturing & Wholesale Goods"
        }
    ],
    "sg:phone":"+33 3 20 10 41 41",
    "sg:postcode":"59320",
    "sg:province":"Nord Pas-de-Calais",
    "sg:tags":[
        "french"
    ],
    "wof:name":"Ets Cuvelier Fauvarque Sa",
    "wof:placetype":"venue"
},
  "geometry": {"coordinates":[2.974775,50.612129],"type":"Point"}
}