{
  "type": "Feature",
  "properties": {
    "addr:full":"Z I Du Moulin 69490 PONTCHARRA SUR TURDINE Rhone-Alpes",
    "addr:postcode":"69490",
    "addr:street":"Z I Du Moulin",
    "iso:country":"FR",
    "sg:address":"Z I Du Moulin 69490 PONTCHARRA SUR TURDINE",
    "sg:classifiers":[
        {
            "category":"Professional",
            "subcategory":"Printing & Photocopies",
            "type":"Services"
        }
    ],
    "sg:phone":"+33 4 74 05 77 06",
    "sg:province":"Rhone-Alpes",
    "sg:tags":[
        "offset"
    ],
    "wof:name":"Imprimerie Rechagnieux Offset Sa",
    "wof:placetype":"venue"
},
  "geometry": {"coordinates":[4.507927,45.837818],"type":"Point"}
}