{
  "type": "Feature",
  "properties": {
    "addr:full":"46 rue du Moulin 57430 Sarralbe Lorraine 57430",
    "addr:housenumber":"46",
    "addr:postcode":"57430;57430",
    "addr:street":"Rue Du Moulin",
    "iso:country":"FR",
    "sg:address":"46 rue du Moulin 57430 Sarralbe",
    "sg:classifiers":[
        {
            "category":"Professional",
            "subcategory":"Accounting & Tax Preparation",
            "type":"Services"
        }
    ],
    "sg:phone":"+33 3 87 97 80 11",
    "sg:postcode":"57430",
    "sg:province":"Lorraine",
    "sg:tags":[
        "mixed",
        "feed"
    ],
    "wof:name":"Dubach Paul Et Cie Sa",
    "wof:placetype":"venue"
},
  "geometry": {"coordinates":[7.031264,48.999672],"type":"Point"}
}