{
  "type": "Feature",
  "properties": {
    "addr:full":"203, Rue des Fr\u00e8res Thibault, 77190 Dammarie les Lys Ile de France 77190",
    "addr:housenumber":"203",
    "addr:postcode":"77190;77190",
    "addr:street":"Rue Des Fre\u0300Res Thibault",
    "iso:country":"FR",
    "sg:address":"203, Rue des Fr\u00e8res Thibault, 77190 Dammarie les Lys",
    "sg:orig_category":"Non-Classified Establishments",
    "sg:phone":"+33 1 64 39 54 30",
    "sg:postcode":"77190",
    "sg:province":"Ile de France",
    "wof:name":"Contre Jour S.a.",
    "wof:placetype":"venue"
},
  "geometry": {"coordinates":[2.642214,48.530071],"type":"Point"}
}