{
  "type": "Feature",
  "properties": {
    "addr:full":"Rte de Menandon Pontoise Ile de France 95300",
    "addr:postcode":"95300",
    "addr:street":"Rte De Menandon;Ile De France",
    "iso:country":"FR",
    "sg:address":"Rte de Menandon",
    "sg:city":"Pontoise",
    "sg:orig_category":"Non-Classified Establishments",
    "sg:phone":"+33 1 34 22 91 91",
    "sg:postcode":"95300",
    "sg:province":"Ile de France",
    "wof:name":"F\u00e9d\u00e9ral Mogul Sintered Products S.a.s.",
    "wof:placetype":"venue"
},
  "geometry": {"coordinates":[2.0826,49.047874],"type":"Point"}
}