{
  "type": "Feature",
  "properties": {
    "addr:full":"6, Rue du B\u00e9al - ZI Sud, 38400 Saint Martin d'H\u00e8res Rhone-Alpes",
    "addr:housenumber":"6",
    "addr:postcode":"38400",
    "addr:street":"Rue Du Be\u0301Al Zi Sud",
    "iso:country":"FR",
    "sg:address":"6, Rue du B\u00e9al - ZI Sud, 38400 Saint Martin d'H\u00e8res",
    "sg:orig_category":"Non-Classified Establishments",
    "sg:phone":"+33 4 76 25 42 83",
    "sg:province":"Rhone-Alpes",
    "wof:name":"Onyx Auvergne Rh\u00f4ne Alpes",
    "wof:placetype":"venue"
},
  "geometry": {"coordinates":[5.756404,45.162926],"type":"Point"}
}