{
  "type": "Feature",
  "properties": {
    "addr:full":"1040 Rte Du Cateau 59400 Awoingt Nord Pas-de-Calais 59400",
    "addr:housenumber":"1040",
    "addr:postcode":"59400;59400",
    "addr:street":"Rte Du Cateau",
    "iso:country":"FR",
    "sg:address":"1040 Rte Du Cateau 59400 Awoingt",
    "sg:classifiers":[
        {
            "category":"Food & Beverages",
            "subcategory":"Dairy",
            "type":"Retail Goods"
        }
    ],
    "sg:phone":"+33 3 27 78 77 21",
    "sg:postcode":"59400",
    "sg:province":"Nord Pas-de-Calais",
    "sg:tags":[
        "product",
        "related"
    ],
    "wof:name":"Sully",
    "wof:placetype":"venue"
},
  "geometry": {"coordinates":[3.284775,50.163231],"type":"Point"}
}