{
  "type": "Feature",
  "properties": {
    "addr:full":"B.P. 4 Labastide Saint Pierre^^82370 Labastide Saint Pierre Midi Pyr\u00e9n\u00e9es 82370",
    "addr:postcode":"82370",
    "addr:street":"B.P. 4 Labastide Saint Pierre^^82370",
    "iso:country":"FR",
    "sg:address":"B.P. 4",
    "sg:city":"Labastide Saint Pierre^^82370 Labastide Saint Pierre",
    "sg:orig_category":"Non-Classified Establishments",
    "sg:phone":"+33 5 63 25 12 12",
    "sg:postcode":"82370",
    "sg:province":"Midi Pyr\u00e9n\u00e9es",
    "wof:name":"Saliens Industries S.a.",
    "wof:placetype":"venue"
},
  "geometry": {"coordinates":[1.36731,43.918789],"type":"Point"}
}