{
  "type": "Feature",
  "properties": {
    "addr:full":"121 Avenue Maurice Thorez 94207 Ivry Sur Seine Cedex Aquitaine",
    "addr:housenumber":"121",
    "addr:postcode":"94207",
    "addr:street":"Avenue Maurice Thorez",
    "iso:country":"FR",
    "sg:address":"121 Avenue Maurice Thorez 94207 Ivry Sur Seine Cedex",
    "sg:classifiers":[
        {
            "category":"Utilities",
            "subcategory":"Electric",
            "type":"Services"
        }
    ],
    "sg:phone":"+33 1 45 15 29 30",
    "sg:province":"Aquitaine",
    "sg:tags":[
        "electricity",
        "electronic",
        "electrical",
        "equipment"
    ],
    "wof:name":"Electricite Travaux Techniques Sa",
    "wof:placetype":"venue"
},
  "geometry": {"coordinates":[2.377828,48.815594],"type":"Point"}
}