{
  "type": "Feature",
  "properties": {
    "iso:country":"FR",
    "sg:address":"9, Rue Saint Martin - Centre Culturel de Rencontre, 54700 Pont \u00e0 Mousson",
    "sg:orig_category":"Unclassifiable Establishments",
    "sg:phone":"+33 3 83 81 10 32",
    "sg:province":"Lorraine",
    "wof:name":"Abbaye Des Pr\u00e9montr\u00e9s",
    "wof:placetype":"venue"
},
  "geometry": {"coordinates":[6.054945,48.902954],"type":"Point"}
}