{
  "type": "Feature",
  "properties": {
    "addr:full":"29 Rue Marceau 94200 Ivry Sur Seine Ile de France",
    "addr:housenumber":"29",
    "addr:postcode":"94200",
    "addr:street":"Rue Marceau",
    "iso:country":"FR",
    "sg:address":"29 Rue Marceau 94200 Ivry Sur Seine",
    "sg:classifiers":[
        {
            "category":"Manufacturing",
            "subcategory":"Printing",
            "type":"Manufacturing & Wholesale Goods"
        }
    ],
    "sg:phone":"+33 1 45 15 00 61",
    "sg:province":"Ile de France",
    "sg:tags":[
        "publishing"
    ],
    "wof:name":"Corlet Imprimeur Sa",
    "wof:placetype":"venue"
},
  "geometry": {"coordinates":[2.379054,48.819126],"type":"Point"}
}