{
  "type": "Feature",
  "properties": {
    "addr:full":"Za St Jean De L' Arnouze 11880 Carcassonne Aquitaine",
    "addr:postcode":"11880",
    "addr:street":"Za St;De L ' Arnouze",
    "iso:country":"FR",
    "sg:address":"Za St Jean De L' Arnouze 11880 Carcassonne",
    "sg:classifiers":[
        {
            "category":"Autos & Motor Vehicles",
            "subcategory":"Automobile Sales",
            "type":"Retail Goods"
        }
    ],
    "sg:phone":"+33 4 68 47 70 00",
    "sg:province":"Aquitaine",
    "sg:tags":[
        "equipment",
        "motor-cars",
        "transport"
    ],
    "wof:name":"Sa Auto Cite",
    "wof:placetype":"venue"
},
  "geometry": {"coordinates":[2.321975,43.211536],"type":"Point"}
}