{
  "type": "Feature",
  "properties": {
    "iso:country":"FR",
    "sg:address":"175, Rte de Vienne, 69008 Lyon",
    "sg:orig_category":"Unclassifiable Establishments",
    "sg:phone":"+33 4 78 00 36 36",
    "sg:province":"Rhone-Alpes",
    "wof:name":"P\u00e9rimat S.a.r.l.",
    "wof:placetype":"venue"
},
  "geometry": {"coordinates":[4.853613,45.733353],"type":"Point"}
}