{
  "type": "Feature",
  "properties": {
    "iso:country":"FR",
    "sg:address":"Lieu Dit La Croix Des Riaux 44530 St Gildas Des Bois",
    "sg:classifiers":[
        {
            "category":"Farming",
            "subcategory":"Farm",
            "type":"Manufacturing & Wholesale Goods"
        }
    ],
    "sg:phone":"+33 2 40 91 88 00",
    "sg:postcode":"44530",
    "sg:province":"Pays de Loire",
    "sg:tags":[
        "horticulture",
        "agriculture",
        "livestock"
    ],
    "wof:name":"Etablissements Poupard (ste Ets Poupard)",
    "wof:placetype":"venue"
},
  "geometry": {"coordinates":[-2.049879,47.489651],"type":"Point"}
}