{
  "type": "Feature",
  "properties": {
    "iso:country":"FR",
    "sg:address":"1, Bd Vivier Merle, 69443 Lyon C\u00e9dex 03",
    "sg:orig_category":"Non-Classified Establishments",
    "sg:phone":"+33 4 72 13 31 41",
    "sg:province":"Rhone-Alpes",
    "wof:name":"L.r.q.a. France S.a. - Lloyd's Register Quality Assurance France",
    "wof:placetype":"venue"
},
  "geometry": {"coordinates":[4.86843,45.751369],"type":"Point"}
}