{
  "type": "Feature",
  "properties": {
    "iso:country":"FR",
    "sg:address":"8, Rue du G\u00e9n\u00e9ral de Gaulle - Parc d'Orsay, 91400 Orsay",
    "sg:orig_category":"Unclassifiable Establishments",
    "sg:phone":"+33 1 64 86 18 00",
    "sg:province":"Ile de France",
    "wof:name":"G\u00e9om\u00e9ga S.a.r.l.",
    "wof:placetype":"venue"
},
  "geometry": {"coordinates":[2.186025,48.682358],"type":"Point"}
}