{
  "type": "Feature",
  "properties": {
    "addr:full":"B.P. 231, 06287 Nice C\u00e9dex 3^^208, Rte de Grenoble, 06200 Nice Provence-Alpes-C\u00f4te d'Azur",
    "addr:housenumber":"b.p. 231;3 ^ ^ 208",
    "addr:postcode":"06287;06200",
    "addr:street":"Ce\u0301Dex;Rte De Grenoble",
    "iso:country":"FR",
    "sg:address":"B.P. 231, 06287 Nice C\u00e9dex 3^^208, Rte de Grenoble, 06200 Nice",
    "sg:orig_category":"Non-Classified Establishments",
    "sg:phone":"+33 4 93 18 70 00",
    "sg:province":"Provence-Alpes-C\u00f4te d'Azur",
    "wof:name":"Eurosud S.a.",
    "wof:placetype":"venue"
},
  "geometry": {"coordinates":[7.215093,43.745003],"type":"Point"}
}