{
  "type": "Feature",
  "properties": {
    "addr:full":"12 Rue Charles Fourier 75647 Paris Cedex 13 Rhone-Alpes",
    "addr:housenumber":"12",
    "addr:postcode":"75647;13 rhone-alpes",
    "addr:street":"Rue Charles Fourier",
    "iso:country":"FR",
    "sg:address":"12 Rue Charles Fourier 75647 Paris Cedex 13",
    "sg:classifiers":[
        {
            "category":"Professional",
            "subcategory":"Advertising",
            "type":"Services"
        }
    ],
    "sg:phone":"+33 1 55 76 40 10",
    "sg:province":"Rhone-Alpes",
    "sg:tags":[
        "marketing",
        "medium",
        "communication"
    ],
    "wof:name":"Teleperformance France",
    "wof:placetype":"venue"
},
  "geometry": {"coordinates":[2.352167,48.824757],"type":"Point"}
}