{
  "type": "Feature",
  "properties": {
    "iso:country":"FR",
    "sg:address":"Avenue Industrie 09190 Lorp Sentaraille",
    "sg:classifiers":[
        {
            "category":"Professional",
            "type":"Services"
        }
    ],
    "sg:phone":"+33 5 61 66 27 56",
    "sg:province":"Midi Pyr\u00e9n\u00e9es",
    "sg:tags":[
        "transport",
        "road"
    ],
    "wof:name":"Transports Innocent Freres Snc",
    "wof:placetype":"venue"
},
  "geometry": {"coordinates":[1.102422,43.024712],"type":"Point"}
}