{
  "type": "Feature",
  "properties": {
    "addr:full":"18 av Meilleur Ouvrier France 33700 MERIGNAC M\u00e9rignac Aquitaine 33700",
    "addr:postcode":"33700;33700",
    "addr:street":"18 Av Meilleur Ouvrier",
    "iso:country":"FR",
    "sg:address":"18 av Meilleur Ouvrier France 33700 MERIGNAC",
    "sg:city":"M\u00e9rignac",
    "sg:classifiers":[
        {
            "category":"Wholesale",
            "subcategory":"Home Furnishings",
            "type":"Manufacturing & Wholesale Goods"
        }
    ],
    "sg:phone":"+33 5 56 34 23 08",
    "sg:postcode":"33700",
    "sg:province":"Aquitaine",
    "sg:tags":[
        "house",
        "paint"
    ],
    "wof:name":"Unikalo S.a.",
    "wof:placetype":"venue"
},
  "geometry": {"coordinates":[-0.669038,44.836151],"type":"Point"}
}