{
  "type": "Feature",
  "properties": {
    "iso:country":"FR",
    "sg:address":"B.P. 323, 95526 Cergy Pontoise C\u00e9dex^^12, Rue des Beaux Soleils, 95520 Osny",
    "sg:orig_category":"Non-Classified Establishments",
    "sg:phone":"+33 1 30 38 23 49",
    "sg:postcode":"95520",
    "sg:province":"Ile de France",
    "wof:name":"Cma Cermeca S.a.",
    "wof:placetype":"venue"
},
  "geometry": {"coordinates":[2.064945,49.064018],"type":"Point"}
}