{
  "type": "Feature",
  "properties": {
    "iso:country":"FR",
    "sg:address":"Rue Madame De S\u00e9vign\u00e9 56430 Mauron",
    "sg:city":"Mauron",
    "sg:classifiers":[
        {
            "category":"Professional",
            "subcategory":"Business Services",
            "type":"Services"
        }
    ],
    "sg:phone":"+33 2 97 22 95 38",
    "sg:postcode":"56430",
    "sg:province":"Bretagne",
    "sg:tags":[
        "training",
        "advice"
    ],
    "wof:name":"College Madame De Sevigne",
    "wof:placetype":"venue"
},
  "geometry": {"coordinates":[-2.291578,48.076366],"type":"Point"}
}