{
  "type": "Feature",
  "properties": {
    "addr:full":"9/11, Rue Alphonse de Neuville, 75017 Paris Ile de France",
    "addr:housenumber":"9 / 11",
    "addr:postcode":"75017",
    "addr:street":"Rue Alphonse De Neuville",
    "iso:country":"FR",
    "sg:address":"9/11, Rue Alphonse de Neuville, 75017 Paris",
    "sg:orig_category":"Unclassifiable Establishments",
    "sg:phone":"+33 1 40 53 02 02",
    "sg:province":"Ile de France",
    "wof:name":"Lonsdale Design S.a.",
    "wof:placetype":"venue"
},
  "geometry": {"coordinates":[2.30243,48.885712],"type":"Point"}
}