{
  "type": "Feature",
  "properties": {
    "addr:full":"74 Rue Du Marechal Leclerc 50400 Granville Granville Basse Normandie 50400",
    "addr:housenumber":"74",
    "addr:postcode":"50400;50400",
    "addr:street":"Rue Du Marechal Leclerc",
    "iso:country":"FR",
    "sg:address":"74 Rue Du Marechal Leclerc 50400 Granville",
    "sg:city":"Granville",
    "sg:classifiers":[
        {
            "category":"Wholesale",
            "subcategory":"Medical Equipment & Supplies",
            "type":"Manufacturing & Wholesale Goods"
        }
    ],
    "sg:phone":"+33 2 33 50 03 34",
    "sg:postcode":"50400",
    "sg:province":"Basse Normandie",
    "sg:tags":[
        "instrument",
        "health",
        "-",
        "precision"
    ],
    "wof:name":"Laboratoire Thierry Loquet",
    "wof:placetype":"venue"
},
  "geometry": {"coordinates":[-1.585824,48.837849],"type":"Point"}
}