{
  "type": "Feature",
  "properties": {
    "iso:country":"FR",
    "sg:address":"61 rue Thibaud 75014 Paris",
    "sg:orig_category":"Embossed, Pressed And Stamped Articles Of Cardboard, Paper, Plastics, Fibrous And Composite Material",
    "sg:phone":"+33 1 43 57 31 34",
    "sg:postcode":"75014",
    "sg:province":"Ile de France",
    "wof:name":"Sacophane Sa",
    "wof:placetype":"venue"
},
  "geometry": {"coordinates":[2.3259,48.830219],"type":"Point"}
}