{
  "type": "Feature",
  "properties": {
    "addr:full":"La Lagade 81500 Banni\u00e8res Midi Pyr\u00e9n\u00e9es 81500",
    "addr:postcode":"81500;81500",
    "addr:street":"Lagade",
    "iso:country":"FR",
    "sg:address":"La Lagade 81500 Banni\u00e8res",
    "sg:orig_category":"Non-Classified Establishments",
    "sg:phone":"+33 5 63 58 71 05",
    "sg:postcode":"81500",
    "sg:province":"Midi Pyr\u00e9n\u00e9es",
    "wof:name":"Bernardi Isolation S.a.r.l.",
    "wof:placetype":"venue"
},
  "geometry": {"coordinates":[1.785927,43.599144],"type":"Point"}
}