{
  "type": "Feature",
  "properties": {
    "iso:country":"FR",
    "sg:address":"42 Rue Paul Sabatier 71530 Crissey",
    "sg:city":"Crissey",
    "sg:classifiers":[
        {
            "category":"Autos & Motor Vehicles",
            "subcategory":"Automobile Sales",
            "type":"Retail Goods"
        }
    ],
    "sg:phone":"+33 3 85 47 27 00",
    "sg:postcode":"71530",
    "sg:province":"Bourgogne",
    "sg:tags":[
        "equipment",
        "transport"
    ],
    "wof:name":"Gidi Production Sa",
    "wof:placetype":"venue"
},
  "geometry": {"coordinates":[4.8642,46.823811],"type":"Point"}
}