{
  "type": "Feature",
  "properties": {
    "addr:full":"Rte de Montville Malaunay Haute Normandie 76770",
    "addr:postcode":"76770",
    "addr:street":"Rte De Montville;Haute Normandie",
    "iso:country":"FR",
    "sg:address":"Rte de Montville",
    "sg:city":"Malaunay",
    "sg:orig_category":"Unclassifiable Establishments",
    "sg:phone":"+33 2 35 75 80 30",
    "sg:postcode":"76770",
    "sg:province":"Haute Normandie",
    "wof:name":"Logitra S.a.r.l.",
    "wof:placetype":"venue"
},
  "geometry": {"coordinates":[1.04732,49.528343],"type":"Point"}
}