{
  "type": "Feature",
  "properties": {
    "addr:full":"rue des Vosges 57430 Sarralbe Lorraine 57430",
    "addr:postcode":"57430;57430",
    "addr:street":"Rue Des Vosges",
    "iso:country":"FR",
    "sg:address":"rue des Vosges 57430 Sarralbe",
    "sg:classifiers":[
        {
            "category":"Structure",
            "subcategory":"Office Building",
            "type":"Public Place"
        }
    ],
    "sg:phone":"+33 3 87 97 02 20",
    "sg:postcode":"57430",
    "sg:province":"Lorraine",
    "sg:tags":[
        "industrial",
        "assembly"
    ],
    "wof:name":"Est Industries Sa",
    "wof:placetype":"venue"
},
  "geometry": {"coordinates":[7.021735,48.979935],"type":"Point"}
}