{
  "type": "Feature",
  "properties": {
    "addr:full":"12 Avenue De La Paix 54400 Longwy Lorraine 54400",
    "addr:housenumber":"12",
    "addr:postcode":"54400;54400",
    "addr:street":"Avenue De La Paix",
    "iso:country":"FR",
    "sg:address":"12 Avenue De La Paix 54400 Longwy",
    "sg:classifiers":[
        {
            "category":"Shopping",
            "subcategory":"Bicycles & Sporting Goods",
            "type":"Retail Goods"
        }
    ],
    "sg:phone":"+33 3 82 23 17 10",
    "sg:postcode":"54400",
    "sg:province":"Lorraine",
    "sg:tags":[
        "product",
        "sport",
        "miscellaneous"
    ],
    "wof:name":"Etablissements Jan Sports Sa",
    "wof:placetype":"venue"
},
  "geometry": {"coordinates":[5.76045,49.513931],"type":"Point"}
}