{
  "type": "Feature",
  "properties": {
    "iso:country":"FR",
    "sg:address":"B.P. 262, 42301 Roanne C\u00e9dex^^6, Rue Gilbertes, 42300 Roanne",
    "sg:orig_category":"Non-Classified Establishments",
    "sg:phone":"+33 4 77 72 91 11",
    "sg:postcode":"42300",
    "sg:province":"Rhone-Alpes",
    "wof:name":"Fiduciaire D'expertise Comptable S.a.",
    "wof:placetype":"venue"
},
  "geometry": {"coordinates":[4.040056,45.992947],"type":"Point"}
}