{
  "type": "Feature",
  "properties": {
    "iso:country":"FR",
    "sg:address":"B.P. 115, 89400 Migennes^^32, Rte des Gauzys - Zone Industrielle de Bel Air, 89400 Migennes",
    "sg:city":"Migennes",
    "sg:orig_category":"Non-Classified Establishments",
    "sg:phone":"+33 3 86 47 82 82",
    "sg:postcode":"89400",
    "sg:province":"Bourgogne",
    "wof:name":"Auxerroise De Cartonnages S.a.",
    "wof:placetype":"venue"
},
  "geometry": {"coordinates":[3.51162,47.963699],"type":"Point"}
}