{
  "type": "Feature",
  "properties": {
    "addr:full":"Quartier Lestordri\u00e8res BP 37 26300 Bourg De P\u00e9age Rhone-Alpes 26300",
    "addr:housenumber":"bp 37",
    "addr:postcode":"26300;26300",
    "addr:street":"Rhone-Alpes",
    "iso:country":"FR",
    "sg:address":"Quartier Lestordri\u00e8res BP 37 26300 Bourg De P\u00e9age",
    "sg:classifiers":[
        {
            "category":"Shopping",
            "type":"Retail Goods"
        }
    ],
    "sg:phone":"+33 4 75 70 23 85",
    "sg:postcode":"26300",
    "sg:province":"Rhone-Alpes",
    "sg:tags":[
        "metallurgy",
        "finished",
        "-",
        "metalworking",
        "metallic"
    ],
    "wof:name":"Bourguignon Sarl",
    "wof:placetype":"venue"
},
  "geometry": {"coordinates":[5.09157,44.938511],"type":"Point"}
}