{
  "type": "Feature",
  "properties": {
    "iso:country":"FR",
    "sg:address":"21 boulevard Kraemer 13014 Marseille",
    "sg:classifiers":[
        {
            "category":"Manufacturing",
            "subcategory":"Textiles",
            "type":"Manufacturing & Wholesale Goods"
        }
    ],
    "sg:phone":"+33 4 91 63 30 63",
    "sg:province":"Poitou-Charentes",
    "sg:tags":[
        "natural"
    ],
    "wof:name":"Madeco Sarl",
    "wof:placetype":"venue"
},
  "geometry": {"coordinates":[5.382845,43.321106],"type":"Point"}
}