{
  "type": "Feature",
  "properties": {
    "iso:country":"FR",
    "sg:address":"B.P. 845, 50108 Cherbourg C\u00e9dex^^44, Rue Leledier, 50100 Cherbourg",
    "sg:city":"Cherbourg-Octeville",
    "sg:orig_category":"Non-Classified Establishments",
    "sg:phone":"+33 2 33 87 55 00",
    "sg:postcode":"50100",
    "sg:province":"Basse Normandie",
    "wof:name":"Soccoma S.a.",
    "wof:placetype":"venue"
},
  "geometry": {"coordinates":[-1.616124,49.640484],"type":"Point"}
}