{
  "type": "Feature",
  "properties": {
    "addr:full":"370 Rue Alfred Krug 54000 Nancy Lorraine 54000",
    "addr:housenumber":"370",
    "addr:postcode":"54000;54000",
    "addr:street":"Rue Alfred Krug",
    "iso:country":"FR",
    "sg:address":"370 Rue Alfred Krug 54000 Nancy",
    "sg:classifiers":[
        {
            "category":"Professional",
            "subcategory":"Engineering",
            "type":"Services"
        }
    ],
    "sg:phone":"+33 3 83 32 16 05",
    "sg:postcode":"54000",
    "sg:province":"Lorraine",
    "sg:tags":[
        "machine",
        "-",
        "mechanical"
    ],
    "wof:name":"Gautier Moulron Sa",
    "wof:placetype":"venue"
},
  "geometry": {"coordinates":[6.20658,48.682869],"type":"Point"}
}