{
  "type": "Feature",
  "properties": {
    "iso:country":"FR",
    "sg:address":"B.P. 305, 26208 Mont\u00e9limar C\u00e9dex^^Quartier du Petit P\u00e9lican, 26200 Mont\u00e9limar",
    "sg:orig_category":"Non-Classified Establishments",
    "sg:phone":"+33 4 75 00 83 00",
    "sg:postcode":"26200",
    "sg:province":"Rhone-Alpes",
    "wof:name":"Entrepose",
    "wof:placetype":"venue"
},
  "geometry": {"coordinates":[4.74916,44.555592],"type":"Point"}
}