{
  "type": "Feature",
  "properties": {
    "addr:full":"2 Rue Gambetta 10350 Marigny Le Ch\u00e2tel Champagne",
    "addr:housenumber":"2;cha\u0302tel",
    "addr:postcode":"10350",
    "addr:street":"Rue Gambetta",
    "iso:country":"FR",
    "sg:address":"2 Rue Gambetta 10350 Marigny Le Ch\u00e2tel",
    "sg:classifiers":[
        {
            "category":"Professional",
            "subcategory":"Printing & Photocopies",
            "type":"Services"
        }
    ],
    "sg:phone":"+33 3 25 21 80 60",
    "sg:province":"Champagne",
    "sg:tags":[
        "publishing"
    ],
    "wof:name":"Stpp (ste De Traitement Des Produits De Presse) Sarl",
    "wof:placetype":"venue"
},
  "geometry": {"coordinates":[3.72995,48.40543],"type":"Point"}
}