{
  "type": "Feature",
  "properties": {
    "iso:country":"FR",
    "sg:address":"B.P. 3323, 27033 Evreux C\u00e9dex^^Rue de Toulouse Lautrec - Clos de Vironvay, 27000 Evreux",
    "sg:orig_category":"Non-Classified Establishments",
    "sg:phone":"+33 2 32 28 14 00",
    "sg:province":"Haute Normandie",
    "wof:name":"Flash Graphic S.a.r.l.",
    "wof:placetype":"venue"
},
  "geometry": {"coordinates":[1.150283,49.027546],"type":"Point"}
}