{
  "type": "Feature",
  "properties": {
    "iso:country":"FR",
    "sg:address":"66 rue Henri Barbusse 93200 ST DENIS",
    "sg:classifiers":[
        {
            "category":"Shopping",
            "subcategory":"Beauty & Cosmetics",
            "type":"Retail Goods"
        }
    ],
    "sg:phone":"+33 1 42 35 14 14",
    "sg:postcode":"93200",
    "sg:province":"Ile de France",
    "sg:tags":[
        "natural"
    ],
    "wof:name":"Soteix Sarl",
    "wof:placetype":"venue"
},
  "geometry": {"coordinates":[2.372364,48.942577],"type":"Point"}
}