{
  "type": "Feature",
  "properties": {
    "addr:full":"Route Gibraltar 64120 St Palais M\u00e9harin Aquitaine 64120",
    "addr:housenumber":"64120",
    "addr:postcode":"64120",
    "addr:street":"Route Gibraltar",
    "iso:country":"FR",
    "sg:address":"Route Gibraltar 64120 St Palais",
    "sg:city":"M\u00e9harin",
    "sg:classifiers":[
        {
            "category":"Professional",
            "type":"Services"
        }
    ],
    "sg:phone":"+33 5 59 65 96 88",
    "sg:postcode":"64120",
    "sg:province":"Aquitaine",
    "sg:tags":[
        "transport",
        "road"
    ],
    "wof:name":"Saint Palais Sarl",
    "wof:placetype":"venue"
},
  "geometry": {"coordinates":[-1.035034,43.323109],"type":"Point"}
}