{
  "type": "Feature",
  "properties": {
    "addr:full":"L'Epine 74450 Saint Jean de Sixt Rhone-Alpes",
    "addr:postcode":"74450",
    "addr:street":"L'Epine;Rhone-Alpes",
    "iso:country":"FR",
    "sg:address":"L'Epine 74450 Saint Jean de Sixt",
    "sg:orig_category":"Unclassifiable Establishments",
    "sg:phone":"+33 4 50 02 34 17",
    "sg:province":"Rhone-Alpes",
    "wof:name":"Goy Marcel S.a.",
    "wof:placetype":"venue"
},
  "geometry": {"coordinates":[6.418622,45.913353],"type":"Point"}
}