{
  "type": "Feature",
  "properties": {
    "iso:country":"FR",
    "sg:address":"5 Bd Fontainebleau 91550 Paray Vieille Poste",
    "sg:classifiers":[
        {
            "category":"Autos & Motor Vehicles",
            "subcategory":"Automobile Sales",
            "type":"Retail Goods"
        }
    ],
    "sg:phone":"+33 1 60 48 78 40",
    "sg:postcode":"91550",
    "sg:province":"Ile de France",
    "sg:tags":[
        "equipment",
        "motor-cars",
        "transport"
    ],
    "wof:name":"Belle Etoile Automobile Sa",
    "wof:placetype":"venue"
},
  "geometry": {"coordinates":[2.371318,48.707752],"type":"Point"}
}