{
  "type": "Feature",
  "properties": {
    "iso:country":"FR",
    "sg:address":"6, Rue des Entrepreneurs, 78450 Villepreux",
    "sg:orig_category":"Unclassifiable Establishments",
    "sg:phone":"+33 1 30 56 40 05",
    "sg:province":"Ile de France",
    "wof:name":"Apur Energie S.a.r.l. - Application Pour Utilisation Rationel De L'energie",
    "wof:placetype":"venue"
},
  "geometry": {"coordinates":[2.006738,48.81813],"type":"Point"}
}