{
  "type": "Feature",
  "properties": {
    "addr:full":"274, Bd Cl\u00e9menceau, 59700 Marcq en Baroeul Nord Pas-de-Calais",
    "addr:housenumber":"274",
    "addr:postcode":"59700",
    "addr:street":"Bd Cle\u0301Menceau;En Baroeul Nord",
    "iso:country":"FR",
    "sg:address":"274, Bd Cl\u00e9menceau, 59700 Marcq en Baroeul",
    "sg:orig_category":"Unclassifiable Establishments",
    "sg:phone":"+33 3 20 98 05 45",
    "sg:province":"Nord Pas-de-Calais",
    "wof:name":"Hfr Interd\u00e9co Publicit\u00e9 S.n.c.",
    "wof:placetype":"venue"
},
  "geometry": {"coordinates":[3.0994,50.659653],"type":"Point"}
}