{
  "type": "Feature",
  "properties": {
    "addr:full":"18 Rue De Vaucanson 69150 D\u00e9cines Charpieu Rhone-Alpes",
    "addr:housenumber":"18",
    "addr:postcode":"69150",
    "addr:street":"Rue De Vaucanson",
    "iso:country":"FR",
    "sg:address":"18 Rue De Vaucanson 69150 D\u00e9cines Charpieu",
    "sg:classifiers":[
        {
            "category":"Manufacturing",
            "subcategory":"Rubber & Plastics",
            "type":"Manufacturing & Wholesale Goods"
        }
    ],
    "sg:phone":"+33 4 72 14 55 55",
    "sg:province":"Rhone-Alpes",
    "wof:name":"Capsules Scheide Sarl",
    "wof:placetype":"venue"
},
  "geometry": {"coordinates":[4.93671,45.753281],"type":"Point"}
}