{
  "type": "Feature",
  "properties": {
    "iso:country":"FR",
    "sg:address":"chemin des Patureaux 49400 Saumur",
    "sg:classifiers":[
        {
            "category":"Social Services",
            "subcategory":"Job Training",
            "type":"Services"
        }
    ],
    "sg:phone":"+33 2 41 67 71 31",
    "sg:province":"Pays de Loire",
    "sg:tags":[
        "machine",
        "pressure",
        "welding"
    ],
    "wof:name":"Languepin Soudage S.a.r.l.",
    "wof:placetype":"venue"
},
  "geometry": {"coordinates":[-0.055192,47.281574],"type":"Point"}
}