{
  "type": "Feature",
  "properties": {
    "addr:full":"11, Rue de la Libert\u00e9, 92150 Suresnes Ile de France",
    "addr:housenumber":"11",
    "addr:postcode":"92150;ile",
    "addr:street":"Rue De La Liberte\u0301",
    "iso:country":"FR",
    "sg:address":"11, Rue de la Libert\u00e9, 92150 Suresnes",
    "sg:orig_category":"Non-Classified Establishments",
    "sg:phone":"+33 1 42 04 53 12",
    "sg:province":"Ile de France",
    "wof:name":"Fabric Action",
    "wof:placetype":"venue"
},
  "geometry": {"coordinates":[2.222573,48.87632],"type":"Point"}
}