{
  "type": "Feature",
  "properties": {
    "addr:full":"117, Rue Pasteur, 01500 Ambutrix Rhone-Alpes 01500",
    "addr:housenumber":"117",
    "addr:postcode":"01500;01500",
    "addr:street":"Rue Pasteur;Rhone-Alpes",
    "iso:country":"FR",
    "sg:address":"117, Rue Pasteur, 01500 Ambutrix",
    "sg:orig_category":"Non-Classified Establishments",
    "sg:phone":"+33 4 74 38 43 47",
    "sg:postcode":"01500",
    "sg:province":"Rhone-Alpes",
    "wof:name":"Entreprise Piromalli Jean-pierre",
    "wof:placetype":"venue"
},
  "geometry": {"coordinates":[5.33117,45.943169],"type":"Point"}
}