{
  "type": "Feature",
  "properties": {
    "addr:full":"35 Rue De La Demi Lune 61000 Alencon Alen\u00e7on Basse Normandie 61000",
    "addr:housenumber":"35",
    "addr:postcode":"61000;61000",
    "addr:street":"Rue De La Demi Lune",
    "iso:country":"FR",
    "sg:address":"35 Rue De La Demi Lune 61000 Alencon",
    "sg:city":"Alen\u00e7on",
    "sg:classifiers":[
        {
            "category":"Manufacturing",
            "subcategory":"Wood Products",
            "type":"Manufacturing & Wholesale Goods"
        }
    ],
    "sg:phone":"+33 2 33 26 06 24",
    "sg:postcode":"61000",
    "sg:province":"Basse Normandie",
    "sg:tags":[
        "furniture"
    ],
    "wof:name":"Coulon Bernard",
    "wof:placetype":"venue"
},
  "geometry": {"coordinates":[0.089037,48.433868],"type":"Point"}
}