{
  "type": "Feature",
  "properties": {
    "addr:full":"12 bis, Rue du Grand Logis, 13770 Venelles Lorraine",
    "addr:housenumber":"12 bis",
    "addr:postcode":"13770",
    "addr:street":"Rue Du Grand Logis",
    "iso:country":"FR",
    "sg:address":"12 bis, Rue du Grand Logis, 13770 Venelles",
    "sg:orig_category":"Unclassifiable Establishments",
    "sg:phone":"+33 4 42 54 19 33",
    "sg:province":"Lorraine",
    "wof:name":"Solabel S.a.r.l.",
    "wof:placetype":"venue"
},
  "geometry": {"coordinates":[5.485067,43.600578],"type":"Point"}
}