{
  "type": "Feature",
  "properties": {
    "iso:country":"FR",
    "sg:address":"B.P. 26, 67190 Gresswiller^^2, Rue Gutenberg, 67190 Gresswiller",
    "sg:city":"Gresswiller",
    "sg:orig_category":"Non-Classified Establishments",
    "sg:phone":"+33 3 88 48 78 48",
    "sg:postcode":"67190",
    "sg:province":"Alsace",
    "wof:name":"Girold Julien Imprimerie S.a.",
    "wof:placetype":"venue"
},
  "geometry": {"coordinates":[7.450435,48.539268],"type":"Point"}
}