{
  "type": "Feature",
  "properties": {
    "iso:country":"FR",
    "sg:address":"17, Av Jean Jaur\u00e8s, 89000 Auxerre",
    "sg:city":"Auxerre",
    "sg:orig_category":"Unclassifiable Establishments",
    "sg:phone":"+33 3 86 46 86 87",
    "sg:postcode":"89000",
    "sg:province":"Bourgogne",
    "wof:name":"A.p.f. Industrie",
    "wof:placetype":"venue"
},
  "geometry": {"coordinates":[3.579577,47.798237],"type":"Point"}
}