{
  "type": "Feature",
  "properties": {
    "addr:full":"Caquet Echallon Rhone-Alpes 01130",
    "addr:postcode":"01130",
    "addr:street":"Rhone-Alpes",
    "iso:country":"FR",
    "sg:address":"Caquet",
    "sg:city":"Echallon",
    "sg:orig_category":"Non-Classified Establishments",
    "sg:phone":"+33 4 74 76 42 24",
    "sg:postcode":"01130",
    "sg:province":"Rhone-Alpes",
    "wof:name":"Joux S.a.r.l.",
    "wof:placetype":"venue"
},
  "geometry": {"coordinates":[5.741794,46.20668],"type":"Point"}
}