{
  "type": "Feature",
  "properties": {
    "iso:country":"FR",
    "sg:address":"Lassoubs 34330 La Salvetat Sur Agout",
    "sg:classifiers":[
        {
            "category":"Food Court",
            "type":"Food & Drink"
        }
    ],
    "sg:phone":"+33 4 67 97 58 05",
    "sg:postcode":"34330",
    "sg:province":"Languedoc-Roussillon",
    "sg:tags":[
        "product",
        "related"
    ],
    "wof:name":"Eaux Minerales D'evian",
    "wof:placetype":"venue"
},
  "geometry": {"coordinates":[2.689426,43.550789],"type":"Point"}
}