{
  "type": "Feature",
  "properties": {
    "addr:full":"49 Grand Rue 67430 Diemeringen Diemeringen Alsace 67430",
    "addr:housenumber":"49",
    "addr:postcode":"67430;67430",
    "addr:street":"Grand Rue",
    "iso:country":"FR",
    "sg:address":"49 Grand Rue 67430 Diemeringen",
    "sg:city":"Diemeringen",
    "sg:classifiers":[
        {
            "category":"Bakery",
            "type":"Food & Drink"
        }
    ],
    "sg:phone":"+33 3 88 00 02 24",
    "sg:postcode":"67430",
    "sg:province":"Alsace",
    "sg:tags":[
        "cake",
        "product",
        "related",
        "bread"
    ],
    "wof:name":"Boulangerie Patisserie Salon De The Eby",
    "wof:placetype":"venue"
},
  "geometry": {"coordinates":[7.18668,48.939781],"type":"Point"}
}