{
  "type": "Feature",
  "properties": {
    "addr:full":"169, Av Francis Tonner, 06150 Cannes la Bocca Provence-Alpes-C\u00f4te d'Azur",
    "addr:postcode":"06150",
    "addr:street":"169 Av Francis Tonner;Bocca",
    "iso:country":"FR",
    "sg:address":"169, Av Francis Tonner, 06150 Cannes la Bocca",
    "sg:orig_category":"Unclassifiable Establishments",
    "sg:phone":"+33 4 93 47 16 13",
    "sg:province":"Provence-Alpes-C\u00f4te d'Azur",
    "wof:name":"Belisa S.a.",
    "wof:placetype":"venue"
},
  "geometry": {"coordinates":[6.96919,43.549751],"type":"Point"}
}