{
  "type": "Feature",
  "properties": {
    "addr:full":"449, Av Jean Moulin - ZAC du Camp du Roy, 60880 Jaux Picardie",
    "addr:postcode":"60880",
    "addr:street":"449 Av Jean Moulin Zac Du Camp Du Roy",
    "iso:country":"FR",
    "sg:address":"449, Av Jean Moulin - ZAC du Camp du Roy, 60880 Jaux",
    "sg:orig_category":"Unclassifiable Establishments",
    "sg:phone":"+33 3 44 90 66 00",
    "sg:province":"Picardie",
    "wof:name":"Daniel S.a.",
    "wof:placetype":"venue"
},
  "geometry": {"coordinates":[2.776811,49.389362],"type":"Point"}
}