{
  "type": "Feature",
  "properties": {
    "addr:full":"av Louis Vigo 66310 Estagel Languedoc-Roussillon 66310",
    "addr:postcode":"66310;66310",
    "addr:street":"Av Louis Vigo",
    "iso:country":"FR",
    "sg:address":"av Louis Vigo 66310 Estagel",
    "sg:classifiers":[
        {
            "category":"Food Court",
            "type":"Food & Drink"
        }
    ],
    "sg:phone":"+33 4 68 29 00 45",
    "sg:postcode":"66310",
    "sg:province":"Languedoc-Roussillon",
    "sg:tags":[
        "product",
        "related"
    ],
    "wof:name":"Les Vignerons Des Cotes D'agly",
    "wof:placetype":"venue"
},
  "geometry": {"coordinates":[2.698795,42.776196],"type":"Point"}
}