{
  "type": "Feature",
  "properties": {
    "addr:full":"Av. de la R\u00e9publique Gu\u00e9ret Limousin 23000",
    "addr:postcode":"23000",
    "addr:street":"Av. De La Re\u0301Publique",
    "iso:country":"FR",
    "sg:address":"Av. de la R\u00e9publique",
    "sg:city":"Gu\u00e9ret",
    "sg:orig_category":"Unclassifiable Establishments",
    "sg:phone":"+33 5 55 51 96 60",
    "sg:postcode":"23000",
    "sg:province":"Limousin",
    "wof:name":"C.c.i. De La Creuse",
    "wof:placetype":"venue"
},
  "geometry": {"coordinates":[1.871975,46.169456],"type":"Point"}
}