{
  "type": "Feature",
  "properties": {
    "iso:country":"FR",
    "sg:address":"123 Bd St Symphorien 57050 Longeville Les Metz",
    "sg:classifiers":[
        {
            "category":"Manufacturing",
            "subcategory":"Wood Products",
            "type":"Manufacturing & Wholesale Goods"
        }
    ],
    "sg:phone":"+33 3 87 66 60 25",
    "sg:province":"Lorraine",
    "sg:tags":[
        "furniture"
    ],
    "wof:name":"R Flucklinger",
    "wof:placetype":"venue"
},
  "geometry": {"coordinates":[6.149667,49.116386],"type":"Point"}
}