{
  "type": "Feature",
  "properties": {
    "iso:country":"FR",
    "sg:address":"207 marche de Saumaty 13016 Marseille",
    "sg:classifiers":[
        {
            "category":"Food & Beverages",
            "subcategory":"Meat & Fish",
            "type":"Retail Goods"
        }
    ],
    "sg:phone":"+33 4 91 46 28 48",
    "sg:province":"Poitou-Charentes",
    "sg:tags":[
        "fresh"
    ],
    "wof:name":"Badouix Fr\u00e8res Mareyeur Sa",
    "wof:placetype":"venue"
},
  "geometry": {"coordinates":[5.321475,43.362785],"type":"Point"}
}