{
  "type": "Feature",
  "properties": {
    "addr:full":"2, Av. du Premier Mai, 91127 Palaiseau \u00cele-de-France",
    "addr:postcode":"91127",
    "addr:street":"Av. Du Premier Mai",
    "iso:country":"FR",
    "sg:address":"2, Av. du Premier Mai, 91127 Palaiseau",
    "sg:orig_category":"Non-Classified Establishments",
    "sg:phone":"+33 1 69 93 66 63",
    "sg:province":"\u00cele-de-France",
    "wof:name":"Siporex S.a.",
    "wof:placetype":"venue"
},
  "geometry": {"coordinates":[2.257045,48.713245],"type":"Point"}
}