{
  "type": "Feature",
  "properties": {
    "iso:country":"FR",
    "sg:address":"43, Bd Barb\u00e8s, 75880 Paris C\u00e9dex 18",
    "sg:orig_category":"Non-Classified Establishments",
    "sg:phone":"+33 1 49 25 26 27",
    "sg:province":"Ile-de-France",
    "wof:name":"Soci\u00e9t\u00e9 Publiprint",
    "wof:placetype":"venue"
},
  "geometry": {"coordinates":[2.349359,48.888515],"type":"Point"}
}