{
  "type": "Feature",
  "properties": {
    "addr:full":"438, Rue de Vaudricourt, 62700 Bruay la Buissi\u00e8re Nord Pas-de-Calais",
    "addr:housenumber":"438",
    "addr:postcode":"62700",
    "addr:street":"Rue De Vaudricourt",
    "iso:country":"FR",
    "sg:address":"438, Rue de Vaudricourt, 62700 Bruay la Buissi\u00e8re",
    "sg:orig_category":"Non-Classified Establishments",
    "sg:phone":"+33 3 21 62 67 94",
    "sg:province":"Nord Pas-de-Calais",
    "wof:name":"Eurocam' S.a.r.l.",
    "wof:placetype":"venue"
},
  "geometry": {"coordinates":[2.57438,50.489437],"type":"Point"}
}