{
  "type": "Feature",
  "properties": {
    "addr:full":"42 Avenue Camille Pujol 31079 Toulouse Cedex Midi Pyr\u00e9n\u00e9es",
    "addr:housenumber":"42",
    "addr:postcode":"31079",
    "addr:street":"Avenue Camille Pujol",
    "iso:country":"FR",
    "sg:address":"42 Avenue Camille Pujol 31079 Toulouse Cedex",
    "sg:classifiers":[
        {
            "category":"Professional",
            "subcategory":"Business Services",
            "type":"Services"
        }
    ],
    "sg:phone":"+33 5 62 47 48 49",
    "sg:province":"Midi Pyr\u00e9n\u00e9es",
    "sg:tags":[
        "training",
        "advice"
    ],
    "wof:name":"Caousou Coll\u00c8ge Et Lyc\u00c9e",
    "wof:placetype":"venue"
},
  "geometry": {"coordinates":[1.462242,43.600769],"type":"Point"}
}