{
  "type": "Feature",
  "properties": {
    "addr:full":"10, Rue Marboeuf, 75008 Paris Ile de France",
    "addr:housenumber":"10",
    "addr:postcode":"75008",
    "addr:street":"Rue Marboeuf",
    "iso:country":"FR",
    "sg:address":"10, Rue Marboeuf, 75008 Paris",
    "sg:orig_category":"Non-Classified Establishments",
    "sg:phone":"+33 1 53 67 81 90",
    "sg:province":"Ile de France",
    "wof:name":"Jean-claude Biguine S.a.",
    "wof:placetype":"venue"
},
  "geometry": {"coordinates":[2.302623,48.867603],"type":"Point"}
}