{
  "type": "Feature",
  "properties": {
    "addr:full":"3 Rue De Haguenau 67620 Soufflenheim Soufflenheim Alsace 67620",
    "addr:housenumber":"3",
    "addr:postcode":"67620;67620",
    "addr:street":"Rue De Haguenau",
    "iso:country":"FR",
    "sg:address":"3 Rue De Haguenau 67620 Soufflenheim",
    "sg:city":"Soufflenheim",
    "sg:classifiers":[
        {
            "category":"Home & Garden",
            "subcategory":"Furniture",
            "type":"Retail Goods"
        }
    ],
    "sg:phone":"+33 3 88 86 61 21",
    "sg:postcode":"67620",
    "sg:province":"Alsace",
    "sg:tags":[
        "household",
        "wood"
    ],
    "wof:name":"Societe D'exploitation Poterie Friedmann Ignace",
    "wof:placetype":"venue"
},
  "geometry": {"coordinates":[7.958012,48.8297],"type":"Point"}
}