{
  "type": "Feature",
  "properties": {
    "iso:country":"FR",
    "sg:address":"Zi Rte De Francouville 28630 Sours",
    "sg:city":"Sours",
    "sg:classifiers":[
        {
            "category":"Manufacturing",
            "subcategory":"Metals",
            "type":"Manufacturing & Wholesale Goods"
        }
    ],
    "sg:phone":"+33 2 37 25 94 94",
    "sg:postcode":"28630",
    "sg:province":"Centre",
    "sg:tags":[
        "metallurgy",
        "steel",
        "metalworking"
    ],
    "wof:name":"Biezanek Noyautage",
    "wof:placetype":"venue"
},
  "geometry": {"coordinates":[1.598,48.41227],"type":"Point"}
}