{
  "type": "Feature",
  "properties": {
    "iso:country":"FR",
    "sg:address":"6, Rue Maurice Loewy, 75014 Paris",
    "sg:orig_category":"Non-Classified Establishments",
    "sg:phone":"+33 1 43 20 00 18",
    "sg:province":"Ile de France",
    "wof:name":"Leyre Et Compagnie S.a.r.l.",
    "wof:placetype":"venue"
},
  "geometry": {"coordinates":[2.33367,48.826939],"type":"Point"}
}