{
  "type": "Feature",
  "properties": {
    "iso:country":"FR",
    "sg:address":"3 Rte De Chevigny 21130 Auxonne",
    "sg:city":"Auxonne",
    "sg:classifiers":[
        {
            "category":"Food & Beverages",
            "subcategory":"Fruits & Vegetables",
            "type":"Retail Goods"
        }
    ],
    "sg:phone":"+33 3 80 77 47 47",
    "sg:postcode":"21130",
    "sg:province":"Bourgogne",
    "sg:tags":[
        "preserve",
        "product",
        "related"
    ],
    "wof:name":"Ste De Transformation De Legumes",
    "wof:placetype":"venue"
},
  "geometry": {"coordinates":[5.394947,47.193642],"type":"Point"}
}