{
  "type": "Feature",
  "properties": {
    "addr:full":"Av. de la Noix de Grenoble Vinay Rhone-Alpes 38470",
    "addr:postcode":"38470",
    "addr:street":"Av. De La Noix De Grenoble Vinay Rhone-Alpes",
    "iso:country":"FR",
    "sg:address":"Av. de la Noix de Grenoble",
    "sg:city":"Vinay",
    "sg:orig_category":"Non-Classified Establishments",
    "sg:phone":"+33 4 76 36 80 33",
    "sg:postcode":"38470",
    "sg:province":"Rhone-Alpes",
    "wof:name":"Coopenoix - Euronoix",
    "wof:placetype":"venue"
},
  "geometry": {"coordinates":[5.419325,45.211876],"type":"Point"}
}