{
  "type": "Feature",
  "properties": {
    "iso:country":"FR",
    "sg:address":"Av Paul Mairat",
    "sg:city":"Mansle",
    "sg:orig_category":"Non-Classified Establishments",
    "sg:phone":"+33 5 45 22 20 05",
    "sg:postcode":"16230",
    "sg:province":"Poitou-Charentes",
    "wof:name":"Cars Thorin S.a.r.l.",
    "wof:placetype":"venue"
},
  "geometry": {"coordinates":[0.171355,45.872566],"type":"Point"}
}