{
  "type": "Feature",
  "properties": {
    "iso:country":"FR",
    "sg:address":"20 Allee Des Bruyeres Croix Sainte 13500 Martigues",
    "sg:city":"Artigue",
    "sg:classifiers":[
        {
            "category":"Transit Center",
            "subcategory":"Freight",
            "type":"Transportation"
        }
    ],
    "sg:phone":"+33 4 42 80 24 76",
    "sg:postcode":"31110",
    "sg:province":"Midi Pyr\u00e9n\u00e9es",
    "sg:tags":[
        "metallurgy",
        "pipe",
        "metalworking",
        "sheet"
    ],
    "wof:name":"Societe D'etudes De Realisations Industrielles Et De Maintenance (eti Maintenance)",
    "wof:placetype":"venue"
},
  "geometry": {"coordinates":[5.055235,43.406536],"type":"Point"}
}