{
  "type": "Feature",
  "properties": {
    "iso:country":"FR",
    "sg:address":"6 Rue Ren\u00e9 Cassin 42500 Le Chambon Feugerolles",
    "sg:classifiers":[
        {
            "category":"Shopping",
            "subcategory":"Crafts & Fabrics",
            "type":"Retail Goods"
        }
    ],
    "sg:phone":"+33 4 77 40 18 90",
    "sg:postcode":"42500",
    "sg:province":"Rhone-Alpes",
    "sg:tags":[
        "textile",
        "clothing"
    ],
    "wof:name":"Fourneyron Sa (paul)",
    "wof:placetype":"venue"
},
  "geometry": {"coordinates":[4.335085,45.395805],"type":"Point"}
}