{
  "type": "Feature",
  "properties": {
    "addr:full":"Rue de la Varenne Pezou Centre 41100",
    "addr:postcode":"41100",
    "addr:street":"Rue De La",
    "iso:country":"FR",
    "sg:address":"Rue de la Varenne",
    "sg:city":"Pezou",
    "sg:orig_category":"Non-Classified Establishments",
    "sg:phone":"+33 2 54 23 60 48",
    "sg:postcode":"41100",
    "sg:province":"Centre",
    "wof:name":"Lisle Agri Service S.a.r.l.",
    "wof:placetype":"venue"
},
  "geometry": {"coordinates":[1.13478,47.86385],"type":"Point"}
}