{
  "type": "Feature",
  "properties": {
    "iso:country":"FR",
    "sg:address":"293, Rue de la For\u00eat, 26000 Valence",
    "sg:orig_category":"Non-Classified Establishments",
    "sg:phone":"+33 4 75 43 24 92",
    "sg:province":"Rhone-Alpes",
    "wof:name":"S.r.c.c. S.a. - Soci\u00e9t\u00e9 Rodannienne De Collecte Et Compostage",
    "wof:placetype":"venue"
},
  "geometry": {"coordinates":[4.92505,44.917358],"type":"Point"}
}