{
  "type": "Feature",
  "properties": {
    "iso:country":"FR",
    "sg:address":"10 rue du Bois Casseau 77210 Samoreau",
    "sg:classifiers":[
        {
            "category":"Home & Garden",
            "subcategory":"Household Appliances",
            "type":"Retail Goods"
        }
    ],
    "sg:phone":"+33 1 60 74 95 20",
    "sg:province":"Ile de France",
    "sg:tags":[
        "mixing",
        "stirring"
    ],
    "wof:name":"Robin Industries Sa",
    "wof:placetype":"venue"
},
  "geometry": {"coordinates":[2.764461,48.424995],"type":"Point"}
}