{
  "type": "Feature",
  "properties": {
    "addr:full":"2 Rue De La Carnoy 59130 Lambersart Nord Pas-de-Calais",
    "addr:housenumber":"2",
    "addr:postcode":"59130",
    "addr:street":"Rue De La Carnoy",
    "iso:country":"FR",
    "sg:address":"2 Rue De La Carnoy 59130 Lambersart",
    "sg:classifiers":[
        {
            "category":"Professional",
            "subcategory":"Printing & Photocopies",
            "type":"Services"
        }
    ],
    "sg:phone":"+33 3 20 17 17 17",
    "sg:province":"Nord Pas-de-Calais",
    "sg:tags":[
        "publishing"
    ],
    "wof:name":"La Voix Du Nord",
    "wof:placetype":"venue"
},
  "geometry": {"coordinates":[3.022211,50.651146],"type":"Point"}
}