{
  "type": "Feature",
  "properties": {
    "iso:country":"FR",
    "sg:address":"17, Rue Lamartine, 39400 Morez",
    "sg:orig_category":"D\u00e9graissage par ultrasons Polissage Polissage des m\u00e9taux",
    "sg:phone":"+33 3 84 33 46 71",
    "sg:postcode":"39400",
    "sg:province":"Franche Comt\u00e9",
    "wof:name":"N.p.m. S.a.r.l.",
    "wof:placetype":"venue"
},
  "geometry": {"coordinates":[6.021375,46.52182],"type":"Point"}
}