{
  "type": "Feature",
  "properties": {
    "addr:full":"B.P. 95, 59028 Lille C\u00e9dex^^32, Rue de l'Arc, 59800 Lille Nord Pas-de-Calais",
    "addr:postcode":"59028;59800",
    "addr:street":"B.P. 95;Rue De L'Arc",
    "iso:country":"FR",
    "sg:address":"B.P. 95, 59028 Lille C\u00e9dex^^32, Rue de l'Arc, 59800 Lille",
    "sg:orig_category":"Non-Classified Establishments",
    "sg:phone":"+33 3 20 57 15 57",
    "sg:province":"Nord Pas-de-Calais",
    "wof:name":"Jarimex S.a.r.l.",
    "wof:placetype":"venue"
},
  "geometry": {"coordinates":[3.089117,50.605724],"type":"Point"}
}