{
  "type": "Feature",
  "properties": {
    "iso:country":"FR",
    "sg:address":"4, Rue de l'Arsenal, 63100 Clermont Ferrand",
    "sg:city":"Clermont-Ferrand",
    "sg:orig_category":"Unclassifiable Establishments",
    "sg:phone":"+33 4 73 14 14 14",
    "sg:postcode":"63100",
    "sg:province":"Auvergne",
    "wof:name":"J.l.b. Technologies S.a.",
    "wof:placetype":"venue"
},
  "geometry": {"coordinates":[3.131068,45.796963],"type":"Point"}
}