{
  "type": "Feature",
  "properties": {
    "iso:country":"FR",
    "sg:address":"63190 Saint Jean d'Heurs",
    "sg:city":"Moissat",
    "sg:orig_category":"Unclassifiable Establishments",
    "sg:phone":"+33 4 73 73 14 95",
    "sg:postcode":"63190",
    "sg:province":"Auvergne",
    "wof:name":"Kita Chrome S.a.",
    "wof:placetype":"venue"
},
  "geometry": {"coordinates":[-90.268326,38.560898],"type":"Point"}
}