{
  "type": "Feature",
  "properties": {
    "iso:country":"FR",
    "sg:address":"Rn 9 11510 Fitou",
    "sg:classifiers":[
        {
            "category":"Food Court",
            "type":"Food & Drink"
        }
    ],
    "sg:phone":"+33 4 68 45 71 41",
    "sg:postcode":"11510",
    "sg:province":"Languedoc-Roussillon",
    "sg:tags":[
        "product",
        "related"
    ],
    "wof:name":"Cave Cooperative De Fitou",
    "wof:placetype":"venue"
},
  "geometry": {"coordinates":[2.982601,42.894505],"type":"Point"}
}