{
  "type": "Feature",
  "properties": {
    "iso:country":"FR",
    "sg:address":"B.P. 558, 77332 Meaux C\u00e9dex^^11, Rue des Fr\u00e8res Lumi\u00e8re - ZI Nord, 77100 Meaux",
    "sg:orig_category":"Non-Classified Establishments",
    "sg:phone":"+33 1 64 34 12 45",
    "sg:province":"Ile de France",
    "wof:name":"Jade Sa",
    "wof:placetype":"venue"
},
  "geometry": {"coordinates":[2.883054,48.959351],"type":"Point"}
}