{
  "type": "Feature",
  "properties": {
    "addr:full":"Rue de la M\u00e9tallurgie Colombelles Basse Normandie 14460",
    "addr:postcode":"14460",
    "addr:street":"Rue De La Me\u0301Tallurgie;Basse",
    "iso:country":"FR",
    "sg:address":"Rue de la M\u00e9tallurgie",
    "sg:city":"Colombelles",
    "sg:orig_category":"Non-Classified Establishments",
    "sg:phone":"+33 2 31 72 81 00",
    "sg:postcode":"14460",
    "sg:province":"Basse Normandie",
    "wof:name":"Quadrat S.a.",
    "wof:placetype":"venue"
},
  "geometry": {"coordinates":[-0.292761,49.197254],"type":"Point"}
}