{
  "type": "Feature",
  "properties": {
    "addr:full":"111, Chemin du Puits Germain - Carreau de la Mine , 13119 Saint Savournin Provence-Alpes-C\u00f4te d'Azur",
    "addr:housenumber":"111;13119",
    "addr:street":"Chemin Du Puits Germain Carreau De La Mine;Savournin",
    "iso:country":"FR",
    "sg:address":"111, Chemin du Puits Germain - Carreau de la Mine , 13119 Saint Savournin",
    "sg:orig_category":"Unclassifiable Establishments",
    "sg:phone":"+33 4 42 04 63 95",
    "sg:province":"Provence-Alpes-C\u00f4te d'Azur",
    "wof:name":"M\u00e9casud S.a.r.l.",
    "wof:placetype":"venue"
},
  "geometry": {"coordinates":[5.528105,43.405949],"type":"Point"}
}