{
  "type": "Feature",
  "properties": {
    "addr:full":"29/31, Bd de Brandenbourg, 94200 Ivry sur Seine Ile de France",
    "addr:housenumber":"29 / 31",
    "addr:postcode":"94200",
    "addr:street":"Bd De Brandenbourg",
    "iso:country":"FR",
    "sg:address":"29/31, Bd de Brandenbourg, 94200 Ivry sur Seine",
    "sg:orig_category":"Non-Classified Establishments",
    "sg:phone":"+33 1 45 15 03 50",
    "sg:province":"Ile de France",
    "wof:name":"Le Portugal Des Saveurs S.a.",
    "wof:placetype":"venue"
},
  "geometry": {"coordinates":[2.398895,48.814335],"type":"Point"}
}