{
  "type": "Feature",
  "properties": {
    "iso:country":"FR",
    "sg:address":"32 Rue De Paradis 75010 Paris",
    "sg:classifiers":[
        {
            "category":"Real Estate",
            "subcategory":"Surveying",
            "type":"Services"
        }
    ],
    "sg:phone":"+33 1 42 46 76 22",
    "sg:postcode":"75010",
    "sg:province":"Ile de France",
    "sg:tags":[
        "leather",
        "raw",
        "material",
        "-",
        "shoe"
    ],
    "wof:name":"Sprung Freres (ets) Sa",
    "wof:placetype":"venue"
},
  "geometry": {"coordinates":[2.351798,48.875305],"type":"Point"}
}