{
  "type": "Feature",
  "properties": {
    "addr:full":"83 Av De La Grande Arm\u00e9e 75782 Paris Cedex 16 Haute Normandie",
    "addr:postcode":"75782",
    "addr:street":"83 Av De La Grande Arme\u0301E",
    "iso:country":"FR",
    "sg:address":"83 Av De La Grande Arm\u00e9e 75782 Paris Cedex 16",
    "sg:classifiers":[
        {
            "category":"Food & Beverages",
            "subcategory":"Fruits & Vegetables",
            "type":"Retail Goods"
        }
    ],
    "sg:phone":"+33 1 40 66 22 22",
    "sg:province":"Haute Normandie",
    "sg:tags":[
        "agriculture",
        "grain",
        "livestock",
        "cereal"
    ],
    "wof:name":"Meodis",
    "wof:placetype":"venue"
},
  "geometry": {"coordinates":[2.284428,48.876724],"type":"Point"}
}