{
  "type": "Feature",
  "properties": {
    "iso:country":"FR",
    "sg:address":"4, Av. des Tilleuls, 77000 Melun",
    "sg:orig_category":"Non-Classified Establishments",
    "sg:phone":"+33 1 64 37 13 13",
    "sg:postcode":"77000",
    "sg:province":"Ile de France",
    "wof:name":"Edex Val De Seine S.a.r.l.",
    "wof:placetype":"venue"
},
  "geometry": {"coordinates":[2.654439,48.530163],"type":"Point"}
}