{
  "type": "Feature",
  "properties": {
    "iso:country":"FR",
    "sg:address":"83860 Nans les Pins",
    "sg:city":"Les Pins",
    "sg:orig_category":"Unclassifiable Establishments",
    "sg:phone":"+33 4 94 78 90 59",
    "sg:postcode":"16260",
    "sg:province":"Poitou-Charentes",
    "wof:name":"Le Tigre S.a.",
    "wof:placetype":"venue"
},
  "geometry": {"coordinates":[5.783497,43.370277],"type":"Point"}
}