{
  "type": "Feature",
  "properties": {
    "iso:country":"FR",
    "sg:address":"5, Rue du Point du Jour, 21800 Chevigny Saint Sauveur",
    "sg:city":"Neuilly-l\u00e8s-Dijon",
    "sg:orig_category":"Non-Classified Establishments",
    "sg:phone":"+33 3 80 46 57 10",
    "sg:postcode":"21800",
    "sg:province":"Bourgogne",
    "wof:name":"Sofistock S.a.",
    "wof:placetype":"venue"
},
  "geometry": {"coordinates":[5.144442,47.297604],"type":"Point"}
}