{
  "type": "Feature",
  "properties": {
    "iso:country":"FR",
    "sg:address":"28, Rue Jean Bertin - Technoparc des Hautes Faventines, 26000 Valence",
    "sg:orig_category":"Unclassifiable Establishments",
    "sg:phone":"+33 4 75 56 89 49",
    "sg:province":"Rhone-Alpes",
    "wof:name":"A.t.e. S.a.r.l. - Atelier Test Electronique",
    "wof:placetype":"venue"
},
  "geometry": {"coordinates":[4.889246,44.930458],"type":"Point"}
}