{
  "type": "Feature",
  "properties": {
    "addr:full":"6 rue Victor Lafuma 26140 ANNEYRON Rhone-Alpes 26140",
    "addr:housenumber":"6",
    "addr:postcode":"26140;26140",
    "addr:street":"Rue Victor Lafuma;Rhone-Alpes",
    "iso:country":"FR",
    "sg:address":"6 rue Victor Lafuma 26140 ANNEYRON",
    "sg:classifiers":[
        {
            "category":"Government",
            "subcategory":"Post Office",
            "type":"Public Place"
        }
    ],
    "sg:phone":"+33 4 75 31 31 31",
    "sg:postcode":"26140",
    "sg:province":"Rhone-Alpes",
    "sg:tags":[
        "camping",
        "furniture"
    ],
    "wof:name":"Lafuma S.a.",
    "wof:placetype":"venue"
},
  "geometry": {"coordinates":[4.875925,45.27076],"type":"Point"}
}