{
  "type": "Feature",
  "properties": {
    "iso:country":"FR",
    "sg:address":"6 rue Victor Lafuma 26140 ANNEYRON",
    "sg:classifiers":[
        {
            "category":"Government",
            "subcategory":"Post Office",
            "type":"Public Place"
        }
    ],
    "sg:phone":"+33 4 75 31 31 31",
    "sg:postcode":"26140",
    "sg:province":"Rhone-Alpes",
    "sg:tags":[
        "camping",
        "furniture"
    ],
    "wof:name":"Lafuma S.a.",
    "wof:placetype":"venue"
},
  "geometry": {"coordinates":[4.875925,45.27076],"type":"Point"}
}