{
  "type": "Feature",
  "properties": {
    "iso:country":"FR",
    "sg:address":"Rue Des Terrasses 74960 Cran Gevrier",
    "sg:classifiers":[
        {
            "category":"Manufacturing",
            "subcategory":"Rubber & Plastics",
            "type":"Manufacturing & Wholesale Goods"
        }
    ],
    "sg:phone":"+33 4 50 67 52 81",
    "sg:postcode":"74960",
    "sg:province":"Rhone-Alpes",
    "sg:tags":[
        "packaging",
        "material",
        "-"
    ],
    "wof:name":"Rexam",
    "wof:placetype":"venue"
},
  "geometry": {"coordinates":[6.10581,45.914009],"type":"Point"}
}