{
  "type": "Feature",
  "properties": {
    "addr:full":"B.P. 10, 69131 Ecully C\u00e9dex^^26 ter, Chemin des Hautes Bruy\u00e8res, 69130 Ecully Rhone-Alpes 69130",
    "addr:postcode":"69131;ce\u0301dex^^26;69130;69130",
    "addr:street":"B.P. 10;Chemin Des Hautes Bruye\u0300Res;Rhone-Alpes",
    "iso:country":"FR",
    "sg:address":"B.P. 10, 69131 Ecully C\u00e9dex^^26 ter, Chemin des Hautes Bruy\u00e8res, 69130 Ecully",
    "sg:orig_category":"Non-Classified Establishments",
    "sg:phone":"+33 4 78 33 49 26",
    "sg:postcode":"69130",
    "sg:province":"Rhone-Alpes",
    "wof:name":"Roland Starace",
    "wof:placetype":"venue"
},
  "geometry": {"coordinates":[4.778336,45.7747],"type":"Point"}
}