{
  "type": "Feature",
  "properties": {
    "addr:full":"32, Rue du G\u00e9n\u00e9ral de Gaulle, 62223 Saint Nicolas Nord Pas-de-Calais",
    "addr:housenumber":"32",
    "addr:postcode":"62223",
    "addr:street":"Rue Du Ge\u0301Ne\u0301Ral De Gaulle;Nicolas Nord",
    "iso:country":"FR",
    "sg:address":"32, Rue du G\u00e9n\u00e9ral de Gaulle, 62223 Saint Nicolas",
    "sg:orig_category":"Unclassifiable Establishments",
    "sg:phone":"+33 3 21 48 49 57",
    "sg:province":"Nord Pas-de-Calais",
    "wof:name":"Color'way S.a.",
    "wof:placetype":"venue"
},
  "geometry": {"coordinates":[2.782454,50.303368],"type":"Point"}
}