{
  "type": "Feature",
  "properties": {
    "addr:full":"26 pl Pierre Orus; Castillon la Bataille Still Alsace 67190",
    "addr:housenumber":"26",
    "addr:postcode":"67190",
    "addr:street":"Pl Pierre Orus",
    "iso:country":"FR",
    "sg:address":"26 pl Pierre Orus; Castillon la Bataille",
    "sg:city":"Still",
    "sg:classifiers":[
        {
            "category":"Banks & Credit Unions",
            "subcategory":"Bank",
            "type":"Services"
        }
    ],
    "sg:phone":"+33 3357401146",
    "sg:postcode":"67190",
    "sg:province":"Alsace",
    "wof:name":"Banque National De Paris",
    "wof:placetype":"venue"
},
  "geometry": {"coordinates":[-0.042579,44.854099],"type":"Point"}
}