{
  "type": "Feature",
  "properties": {
    "addr:full":"47 R L\u00e9o Lagrange BP 54 93130 Noisy Le Sec Ile de France 93130",
    "addr:housenumber":"47;bp 54",
    "addr:postcode":"93130;93130",
    "addr:street":"R Le\u0301O Lagrange",
    "iso:country":"FR",
    "sg:address":"47 R L\u00e9o Lagrange BP 54 93130 Noisy Le Sec",
    "sg:classifiers":[
        {
            "category":"Manufacturing",
            "subcategory":"Tools & Machinery",
            "type":"Manufacturing & Wholesale Goods"
        }
    ],
    "sg:phone":"+33 1 48 10 32 35",
    "sg:postcode":"93130",
    "sg:province":"Ile de France",
    "sg:tags":[
        "metallurgy",
        "metalworking"
    ],
    "wof:name":"Chaland Et Fils Sa",
    "wof:placetype":"venue"
},
  "geometry": {"coordinates":[2.445971,48.892979],"type":"Point"}
}