{
  "type": "Feature",
  "properties": {
    "iso:country":"FR",
    "sg:address":"34, Rue Gaston Lauriau, 93100 Montreuil",
    "sg:orig_category":"Unclassifiable Establishments",
    "sg:phone":"+33 1 48 58 45 00",
    "sg:province":"Ile de France",
    "wof:name":"Replicart S.a.r.l.",
    "wof:placetype":"venue"
},
  "geometry": {"coordinates":[2.445386,48.859627],"type":"Point"}
}