{
  "type": "Feature",
  "properties": {
    "addr:full":"26, Rue Agen, 68000 Colmar Colmar Alsace 68000",
    "addr:housenumber":"26",
    "addr:postcode":"68000;68000",
    "addr:street":"Rue Agen",
    "iso:country":"FR",
    "sg:address":"26, Rue Agen, 68000 Colmar",
    "sg:city":"Colmar",
    "sg:orig_category":"Unclassifiable Establishments",
    "sg:phone":"+33 3 89 41 41 48",
    "sg:postcode":"68000",
    "sg:province":"Alsace",
    "wof:name":"Bogivo S.a.",
    "wof:placetype":"venue"
},
  "geometry": {"coordinates":[7.353803,48.085793],"type":"Point"}
}