{
  "type": "Feature",
  "properties": {
    "addr:full":"B.P. 58, 33032 Bordeaux C\u00e9dex^^1, Rue d'Armagnac, 33000 Bordeaux Bordeaux Aquitaine 33000",
    "addr:postcode":"33032;33000;33000",
    "addr:street":"B.P. 58;Rue D'Armagnac",
    "iso:country":"FR",
    "sg:address":"B.P. 58, 33032 Bordeaux C\u00e9dex^^1, Rue d'Armagnac, 33000 Bordeaux",
    "sg:city":"Bordeaux",
    "sg:orig_category":"Non-Classified Establishments",
    "sg:phone":"+33 5 56 49 20 26",
    "sg:postcode":"33000",
    "sg:province":"Aquitaine",
    "wof:name":"Chantarella S.a.",
    "wof:placetype":"venue"
},
  "geometry": {"coordinates":[-0.550018,44.820869],"type":"Point"}
}