{
  "type": "Feature",
  "properties": {
    "iso:country":"FR",
    "sg:address":"St Just 81570 Semalens",
    "sg:classifiers":[
        {
            "category":"Farming",
            "subcategory":"Livestock Farm",
            "type":"Manufacturing & Wholesale Goods"
        }
    ],
    "sg:phone":"+33 5 63 70 40 34",
    "sg:postcode":"81570",
    "sg:province":"Midi Pyr\u00e9n\u00e9es",
    "sg:tags":[
        "breeding",
        "agriculture",
        "animal"
    ],
    "wof:name":"Sarl Smp",
    "wof:placetype":"venue"
},
  "geometry": {"coordinates":[2.098156,43.613331],"type":"Point"}
}