{
  "type": "Feature",
  "properties": {
    "iso:country":"FR",
    "sg:address":"Zone D'Activit\u00e9 Rte De Chang\u00e9 53240 St Jean Sur Mayenne",
    "sg:classifiers":[
        {
            "category":"Professional",
            "subcategory":"Engineering",
            "type":"Services"
        }
    ],
    "sg:phone":"+33 2 43 37 62 63",
    "sg:postcode":"53240",
    "sg:province":"Pays de Loire",
    "sg:tags":[
        "machine",
        "-",
        "mechanical"
    ],
    "wof:name":"Courteille Outillage Sarl",
    "wof:placetype":"venue"
},
  "geometry": {"coordinates":[-0.7512,48.131062],"type":"Point"}
}