{
  "type": "Feature",
  "properties": {
    "iso:country":"FR",
    "sg:address":"A\u00e9rodrome de Lognes",
    "sg:city":"Lognes",
    "sg:orig_category":"Unclassifiable Establishments",
    "sg:phone":"+33 1 60 17 08 08",
    "sg:postcode":"77185",
    "sg:province":"Ile de France",
    "wof:name":"Gertis S.a.r.l.",
    "wof:placetype":"venue"
},
  "geometry": {"coordinates":[2.6324,48.837631],"type":"Point"}
}