{
  "type": "Feature",
  "properties": {
    "iso:country":"FR",
    "sg:address":"Hameau De Buisson 21550 LADOIX SERRIGNY",
    "sg:city":"Ladoix-Serrigny",
    "sg:classifiers":[
        {
            "category":"Wholesale",
            "subcategory":"Wine & Distilled Alcoholic Beverages",
            "type":"Manufacturing & Wholesale Goods"
        }
    ],
    "sg:phone":"+33 3 80 26 41 94",
    "sg:postcode":"21550",
    "sg:province":"Bourgogne",
    "sg:tags":[
        "french"
    ],
    "wof:name":"Gaston Et Pierre Ravaut Earl",
    "wof:placetype":"venue"
},
  "geometry": {"coordinates":[4.885925,47.08028],"type":"Point"}
}