{
  "type": "Feature",
  "properties": {
    "addr:full":"Rte du Creusot Saint Gengoux le National Bourgogne 71460",
    "addr:postcode":"71460",
    "addr:street":"Rte Du Creusot Saint Gengoux Le;Bourgogne",
    "iso:country":"FR",
    "sg:address":"Rte du Creusot",
    "sg:city":"Saint Gengoux le National",
    "sg:orig_category":"Unclassifiable Establishments",
    "sg:phone":"+33 3 85 92 60 16",
    "sg:postcode":"71460",
    "sg:province":"Bourgogne",
    "wof:name":"G\u00e9rard Mouchet",
    "wof:placetype":"venue"
},
  "geometry": {"coordinates":[4.659516,46.619331],"type":"Point"}
}