{
  "type": "Feature",
  "properties": {
    "iso:country":"FR",
    "sg:address":"2 Quai Kl\u00e9ber",
    "sg:city":"Strasbourg",
    "sg:classifiers":[
        {
            "category":"Banks & Credit Unions",
            "subcategory":"Financial Services",
            "type":"Services"
        }
    ],
    "sg:phone":"+33 3 88 52 58 20",
    "sg:postcode":"67000",
    "sg:province":"Alsace",
    "sg:tags":[
        "banking",
        "finance",
        "insurance"
    ],
    "wof:name":"Gie Serv Comm Caisse Epargne Als Lorrain Sa",
    "wof:placetype":"venue"
},
  "geometry": {"coordinates":[7.741387,48.585049],"type":"Point"}
}