{
  "type": "Feature",
  "properties": {
    "addr:full":"74930 Reignier Rhone-Alpes",
    "addr:postcode":"74930",
    "iso:country":"FR",
    "sg:address":"74930 Reignier",
    "sg:orig_category":"Unclassifiable Establishments",
    "sg:phone":"+33 4 50 43 40 52",
    "sg:province":"Rhone-Alpes",
    "wof:name":"Bornand Fr\u00e8res S.a.",
    "wof:placetype":"venue"
},
  "geometry": {"coordinates":[6.267778,46.132328],"type":"Point"}
}