{
  "type": "Feature",
  "properties": {
    "iso:country":"FR",
    "sg:address":"Rue du Trousset - ZI",
    "sg:city":"Saint Jean de Braye",
    "sg:orig_category":"Unclassifiable Establishments",
    "sg:phone":"+33 2 38 70 98 00",
    "sg:postcode":"45800",
    "sg:province":"Centre",
    "wof:name":"Soulier S.a",
    "wof:placetype":"venue"
},
  "geometry": {"coordinates":[1.96818,47.912338],"type":"Point"}
}