{
  "type": "Feature",
  "properties": {
    "addr:full":"Chemin Ormissets Oiry Champagne 51530",
    "addr:postcode":"51530",
    "addr:street":"Chemin Ormissets;Champagne",
    "iso:country":"FR",
    "sg:address":"Chemin Ormissets",
    "sg:city":"Oiry",
    "sg:orig_category":"Non-Classified Establishments",
    "sg:phone":"+33 3 26 51 16 61",
    "sg:postcode":"51530",
    "sg:province":"Champagne",
    "wof:name":"Villeroy Et Boch S.a.s.",
    "wof:placetype":"venue"
},
  "geometry": {"coordinates":[4.03973,49.012005],"type":"Point"}
}