{
  "type": "Feature",
  "properties": {
    "addr:full":"120, Chemin de la Rotonde, 73000 Chamb\u00e9ry Rhone-Alpes 73000",
    "addr:housenumber":"120",
    "addr:postcode":"73000;73000",
    "addr:street":"Chemin De La Rotonde",
    "iso:country":"FR",
    "sg:address":"120, Chemin de la Rotonde, 73000 Chamb\u00e9ry",
    "sg:orig_category":"Non-Classified Establishments",
    "sg:phone":"+33 4 79 62 29 17",
    "sg:postcode":"73000",
    "sg:province":"Rhone-Alpes",
    "wof:name":"Chaudronnerie Berlioz S.a.r.l.",
    "wof:placetype":"venue"
},
  "geometry": {"coordinates":[5.920413,45.574734],"type":"Point"}
}