{
  "type": "Feature",
  "properties": {
    "addr:full":"B.P. 517, 81204 Mazamet C\u00e9dex^^31, Bd Soult, 81200 Mazamet Midi Pyr\u00e9n\u00e9es",
    "addr:housenumber":"b.p. 517",
    "addr:postcode":"81204;ce\u0301dex^^31;81200",
    "addr:street":"Soult",
    "iso:country":"FR",
    "sg:address":"B.P. 517, 81204 Mazamet C\u00e9dex^^31, Bd Soult, 81200 Mazamet",
    "sg:orig_category":"Non-Classified Establishments",
    "sg:phone":"+33 5 63 61 37 44",
    "sg:province":"Midi Pyr\u00e9n\u00e9es",
    "wof:name":"France Contentieux S.a.r.l.",
    "wof:placetype":"venue"
},
  "geometry": {"coordinates":[2.36605,43.460224],"type":"Point"}
}