{
  "type": "Feature",
  "properties": {
    "iso:country":"FR",
    "sg:address":"B.P. 517, 81204 Mazamet C\u00e9dex^^31, Bd Soult, 81200 Mazamet",
    "sg:orig_category":"Non-Classified Establishments",
    "sg:phone":"+33 5 63 61 37 44",
    "sg:province":"Midi Pyr\u00e9n\u00e9es",
    "wof:name":"France Contentieux S.a.r.l.",
    "wof:placetype":"venue"
},
  "geometry": {"coordinates":[2.36605,43.460224],"type":"Point"}
}