{
  "type": "Feature",
  "properties": {
    "addr:full":"All\u00e9e du Moulin Pinard - ZI Nord Limoges Limousin 87000",
    "addr:postcode":"87000",
    "addr:street":"Alle\u0301E Du Moulin Pinard Zi Nord",
    "iso:country":"FR",
    "sg:address":"All\u00e9e du Moulin Pinard - ZI Nord",
    "sg:city":"Limoges",
    "sg:orig_category":"Unclassifiable Establishments",
    "sg:phone":"+33 5 55 38 87 60",
    "sg:postcode":"87000",
    "sg:province":"Limousin",
    "wof:name":"S\u00e9dia - Groupe T.x.c.o.m. S.a.",
    "wof:placetype":"venue"
},
  "geometry": {"coordinates":[1.26201,45.828785],"type":"Point"}
}