{
  "type": "Feature",
  "properties": {
    "addr:full":"165 chemin de Font de Cine 06220 VALLAURIS Rhone-Alpes",
    "addr:housenumber":"165",
    "addr:postcode":"06220",
    "addr:street":"Chemin De Font De Cine",
    "iso:country":"FR",
    "sg:address":"165 chemin de Font de Cine 06220 VALLAURIS",
    "sg:orig_category":"Stoneware, Acid-Proof",
    "sg:phone":"+33 4 92 96 98 02",
    "sg:province":"Rhone-Alpes",
    "wof:name":"La Poterie D'amelie S.a.",
    "wof:placetype":"venue"
},
  "geometry": {"coordinates":[7.056951,43.593555],"type":"Point"}
}