{
  "type": "Feature",
  "properties": {
    "iso:country":"FR",
    "sg:address":"6, Rue des Forgerons - ZI, 77200 Torcy",
    "sg:orig_category":"Unclassifiable Establishments",
    "sg:phone":"+33 1 60 05 75 75",
    "sg:province":"Ile de France",
    "wof:name":"Coldis",
    "wof:placetype":"venue"
},
  "geometry": {"coordinates":[2.651845,48.849575],"type":"Point"}
}