{
  "type": "Feature",
  "properties": {
    "iso:country":"FR",
    "sg:address":"B.P. 23, 69513 Vaulx en Velin C\u00e9dex^^35, Rte de genas, 69120 Vaulx en Velin",
    "sg:orig_category":"Non-Classified Establishments",
    "sg:phone":"+33 4 72 14 16 90",
    "sg:postcode":"69120",
    "sg:province":"Rhone-Alpes",
    "wof:name":"Jb Bonnfond Environnement S.a.",
    "wof:placetype":"venue"
},
  "geometry": {"coordinates":[4.916895,45.779022],"type":"Point"}
}