{
  "type": "Feature",
  "properties": {
    "addr:full":"13, Rue d'Alembert, 38000 Grenoble Rhone-Alpes",
    "addr:housenumber":"13",
    "addr:postcode":"38000",
    "addr:street":"Rue D'Alembert",
    "iso:country":"FR",
    "sg:address":"13, Rue d'Alembert, 38000 Grenoble",
    "sg:orig_category":"Unclassifiable Establishments",
    "sg:phone":"+33 4 76 70 64 77",
    "sg:province":"Rhone-Alpes",
    "wof:name":"Coheris S.a. - Agence Grenoble",
    "wof:placetype":"venue"
},
  "geometry": {"coordinates":[5.711162,45.186981],"type":"Point"}
}