{
  "type": "Feature",
  "properties": {
    "addr:full":"1, Place de la M\u00e9diterran\u00e9e, 95200 Sarcelles Ile de France 95200",
    "addr:housenumber":"1",
    "addr:postcode":"95200;ile;95200",
    "addr:street":"Place De La Me\u0301Diterrane\u0301E;France",
    "iso:country":"FR",
    "sg:address":"1, Place de la M\u00e9diterran\u00e9e, 95200 Sarcelles",
    "sg:orig_category":"Non-Classified Establishments",
    "sg:phone":"+33 1 34 38 29 18",
    "sg:postcode":"95200",
    "sg:province":"Ile de France",
    "wof:name":"Certplus S.a.",
    "wof:placetype":"venue"
},
  "geometry": {"coordinates":[2.375945,48.977345],"type":"Point"}
}