{
  "type": "Feature",
  "properties": {
    "addr:full":"Place De Verdun 07320 St Agreve Rhone-Alpes 07320",
    "addr:postcode":"07320;07320",
    "addr:street":"Place De Verdun;Rhone-Alpes",
    "iso:country":"FR",
    "sg:address":"Place De Verdun 07320 St Agreve",
    "sg:classifiers":[
        {
            "category":"Wholesale",
            "subcategory":"Meat",
            "type":"Manufacturing & Wholesale Goods"
        }
    ],
    "sg:phone":"+33 4 75 30 14 22",
    "sg:postcode":"07320",
    "sg:province":"Rhone-Alpes",
    "sg:tags":[
        "food",
        "cooked",
        "product",
        "related"
    ],
    "wof:name":"Teyssier Salaisons",
    "wof:placetype":"venue"
},
  "geometry": {"coordinates":[4.394685,45.010124],"type":"Point"}
}