{
  "type": "Feature",
  "properties": {
    "addr:full":"Rte de Buzan\u00e7ais - Usine des Gaillards Saint Gaultier Centre 36800",
    "addr:postcode":"36800",
    "addr:street":"Rte De Buzanc\u0327Ais Usine Des Gaillards Saint Gaultier",
    "iso:country":"FR",
    "sg:address":"Rte de Buzan\u00e7ais - Usine des Gaillards",
    "sg:city":"Saint Gaultier",
    "sg:orig_category":"Unclassifiable Establishments",
    "sg:phone":"+33 2 54 47 02 04",
    "sg:postcode":"36800",
    "sg:province":"Centre",
    "wof:name":"Etablissement Bonargent-goyon S.a.",
    "wof:placetype":"venue"
},
  "geometry": {"coordinates":[1.39243,46.5415],"type":"Point"}
}