{
  "type": "Feature",
  "properties": {
    "iso:country":"FR",
    "sg:address":"478 Rue Louis R\u00e9my 39570 Messia Sur Sorne",
    "sg:classifiers":[
        {
            "category":"Professional",
            "type":"Services"
        }
    ],
    "sg:phone":"+33 3 84 24 11 78",
    "sg:province":"Franche Comt\u00e9",
    "sg:tags":[
        "transport",
        "road"
    ],
    "wof:name":"Trafic Route",
    "wof:placetype":"venue"
},
  "geometry": {"coordinates":[5.516002,46.599735],"type":"Point"}
}