{
  "type": "Feature",
  "properties": {
    "addr:full":"1, Rue Blaise Pascal - Parc d'Activit\u00e9s Pissaloup, 78190 Trappes Ile de France 78190",
    "addr:housenumber":"1",
    "addr:postcode":"78190;ile;78190",
    "addr:street":"Rue Blaise Pascal Parc D'Activite \u0301S Pissaloup;France",
    "iso:country":"FR",
    "sg:address":"1, Rue Blaise Pascal - Parc d'Activit\u00e9s Pissaloup, 78190 Trappes",
    "sg:orig_category":"Non-Classified Establishments",
    "sg:phone":"+33 1 30 68 18 68",
    "sg:postcode":"78190",
    "sg:province":"Ile de France",
    "wof:name":"C.c.l. Informatique S.a. - Conseil Conception De Logiciel",
    "wof:placetype":"venue"
},
  "geometry": {"coordinates":[1.980023,48.792847],"type":"Point"}
}