{
  "type": "Feature",
  "properties": {
    "iso:country":"FR",
    "sg:address":"B.P. 69, 10302 Sainte Savine C\u00e9dex^^1, Av du G\u00e9n\u00e9ral Leclerc, 10300 Sainte Savine",
    "sg:orig_category":"Non-Classified Establishments",
    "sg:phone":"+33 3 25 79 20 10",
    "sg:postcode":"10300",
    "sg:province":"Champagne",
    "wof:name":"Buror S.a.",
    "wof:placetype":"venue"
},
  "geometry": {"coordinates":[4.056065,48.292885],"type":"Point"}
}