{
  "type": "Feature",
  "properties": {
    "addr:full":"7 Rue Jean Louis Calderon Zi Est 69120 Vaulx En Velin Rhone-Alpes 69120",
    "addr:housenumber":"7",
    "addr:postcode":"69120;69120",
    "addr:street":"Rue Jean Louis Calderon Zi Est",
    "iso:country":"FR",
    "sg:address":"7 Rue Jean Louis Calderon Zi Est 69120 Vaulx En Velin",
    "sg:classifiers":[
        {
            "category":"Farming",
            "subcategory":"Farm & Veterinary Services",
            "type":"Manufacturing & Wholesale Goods"
        }
    ],
    "sg:phone":"+33 4 78 80 06 96",
    "sg:postcode":"69120",
    "sg:province":"Rhone-Alpes",
    "sg:tags":[
        "advice",
        "agriculture",
        "livestock",
        "business"
    ],
    "wof:name":"Ag Outils Coupants",
    "wof:placetype":"venue"
},
  "geometry": {"coordinates":[4.916895,45.779022],"type":"Point"}
}