{
  "type": "Feature",
  "properties": {
    "addr:full":"22 Rue Concorde 88100 St Die Des Vosges Lorraine 88100",
    "addr:housenumber":"22",
    "addr:postcode":"88100 st;88100",
    "addr:street":"Rue Concorde;Des Vosges",
    "iso:country":"FR",
    "sg:address":"22 Rue Concorde 88100 St Die Des Vosges",
    "sg:classifiers":[
        {
            "category":"Manufacturing",
            "subcategory":"Jewelry",
            "type":"Manufacturing & Wholesale Goods"
        }
    ],
    "sg:phone":"+33 3 29 55 08 13",
    "sg:postcode":"88100",
    "sg:province":"Lorraine",
    "sg:tags":[
        "product",
        "miscellaneous",
        "jewellery"
    ],
    "wof:name":"Adb",
    "wof:placetype":"venue"
},
  "geometry": {"coordinates":[6.951378,48.286572],"type":"Point"}
}