{
  "type": "Feature",
  "properties": {
    "iso:country":"FR",
    "sg:address":"B.P. 542, 77295 Mitry Mory C\u00e9dex^^1, Rue Isaac Newton - ZI Mitry Compans, 77290 Mitry Mory",
    "sg:orig_category":"Non-Classified Establishments",
    "sg:phone":"+33 1 64 67 70 23",
    "sg:postcode":"77290",
    "sg:province":"Ile de France",
    "wof:name":"C\u00e9sab Carreli El\u00e9vatori",
    "wof:placetype":"venue"
},
  "geometry": {"coordinates":[2.619585,48.984165],"type":"Point"}
}