{
  "type": "Feature",
  "properties": {
    "addr:full":"Zone Industrielle Gudmont Villiers Champagne 52320",
    "addr:postcode":"52320",
    "addr:street":"Zone Industrielle Gudmont",
    "iso:country":"FR",
    "sg:address":"Zone Industrielle",
    "sg:city":"Gudmont Villiers",
    "sg:orig_category":"Non-Classified Establishments",
    "sg:phone":"+33 3 25 94 70 58",
    "sg:postcode":"52320",
    "sg:province":"Champagne",
    "wof:name":"La Scierie De Gudmont S.a.",
    "wof:placetype":"venue"
},
  "geometry": {"coordinates":[5.137225,48.343327],"type":"Point"}
}