{
  "type": "Feature",
  "properties": {
    "addr:full":"48, Impasse de Vormy, 74300 Magland Rhone-Alpes 74300",
    "addr:housenumber":"48",
    "addr:postcode":"74300;74300",
    "addr:street":"Impasse De Vormy",
    "iso:country":"FR",
    "sg:address":"48, Impasse de Vormy, 74300 Magland",
    "sg:orig_category":"Non-Classified Establishments",
    "sg:phone":"+33 4 50 34 71 84",
    "sg:postcode":"74300",
    "sg:province":"Rhone-Alpes",
    "wof:name":"Etablissement Bastard Fils",
    "wof:placetype":"venue"
},
  "geometry": {"coordinates":[6.633185,45.987919],"type":"Point"}
}