{
  "type": "Feature",
  "properties": {
    "iso:country":"FR",
    "sg:address":"2 Rue De K\u00e9r\u00e9lie 29200 Brest",
    "sg:city":"Brest",
    "sg:classifiers":[
        {
            "category":"Shopping",
            "subcategory":"Computers & Home Electronics",
            "type":"Retail Goods"
        }
    ],
    "sg:phone":"+33 2 98 47 41 41",
    "sg:postcode":"29200",
    "sg:province":"Bretagne",
    "sg:tags":[
        "electronic",
        "electrical",
        "equipment"
    ],
    "wof:name":"Solemco Da Sa",
    "wof:placetype":"venue"
},
  "geometry": {"coordinates":[-4.491583,48.410339],"type":"Point"}
}