{
  "type": "Feature",
  "properties": {
    "addr:full":"3, Rte de Strasbourg, 67550 Vendenheim Vendenheim Alsace 67550",
    "addr:housenumber":"3",
    "addr:postcode":"67550;67550",
    "addr:street":"Rte De Strasbourg",
    "iso:country":"FR",
    "sg:address":"3, Rte de Strasbourg, 67550 Vendenheim",
    "sg:city":"Vendenheim",
    "sg:orig_category":"Non-Classified Establishments",
    "sg:phone":"+33 3 88 69 35 74",
    "sg:postcode":"67550",
    "sg:province":"Alsace",
    "wof:name":"Institut De Soudure",
    "wof:placetype":"venue"
},
  "geometry": {"coordinates":[7.719523,48.666023],"type":"Point"}
}