{
  "type": "Feature",
  "properties": {
    "iso:country":"FR",
    "sg:address":"10, Rue Bodin, 49400 Saumur",
    "sg:orig_category":"Unclassifiable Establishments",
    "sg:phone":"+33 2 41 38 23 96",
    "sg:province":"Pays de Loire",
    "wof:name":"S.p.i.a. Ressources Humaines",
    "wof:placetype":"venue"
},
  "geometry": {"coordinates":[-0.079975,47.257023],"type":"Point"}
}