{
  "type": "Feature",
  "properties": {
    "iso:country":"FR",
    "sg:address":"29, Rue du Pont d'Arcole, 60000 Beauvais",
    "sg:orig_category":"Unclassifiable Establishments",
    "sg:phone":"+33 3 44 02 40 21",
    "sg:province":"Picardie",
    "wof:name":"Miller Graohics S.a.",
    "wof:placetype":"venue"
},
  "geometry": {"coordinates":[2.087665,49.425838],"type":"Point"}
}