{
  "type": "Feature",
  "properties": {
    "addr:full":"415, Rue de la Poste, 01200 Ch\u00e2tillon en Michaille Rhone-Alpes",
    "addr:housenumber":"415",
    "addr:postcode":"01200",
    "addr:street":"Rue De La Poste;Rhone-Alpes",
    "iso:country":"FR",
    "sg:address":"415, Rue de la Poste, 01200 Ch\u00e2tillon en Michaille",
    "sg:orig_category":"Unclassifiable Establishments",
    "sg:phone":"+33 4 50 56 69 00",
    "sg:province":"Rhone-Alpes",
    "wof:name":"Famy Et Compagnie S.a.r.l.",
    "wof:placetype":"venue"
},
  "geometry": {"coordinates":[5.796391,46.139084],"type":"Point"}
}