{
  "type": "Feature",
  "properties": {
    "iso:country":"FR",
    "sg:address":"B.P. 374, 69960 Corbas^^8, Rue du Dauphin\u00e9, 69960 Corbas",
    "sg:orig_category":"Non-Classified Establishments",
    "sg:phone":"+33 4 72 21 25 75",
    "sg:province":"Rhone-Alpes",
    "wof:name":"Gerland Lyon S.n.c.",
    "wof:placetype":"venue"
},
  "geometry": {"coordinates":[4.898495,45.670914],"type":"Point"}
}