{
  "type": "Feature",
  "properties": {
    "addr:full":"1 Boulevard John Kennedy Immeuble L'Espadon Voilier Perpignan Languedoc-Roussillon 66000",
    "addr:housenumber":"1",
    "addr:postcode":"66000",
    "addr:street":"Boulevard John Kennedy;Voilier",
    "iso:country":"FR",
    "sg:address":"1 Boulevard John Kennedy Immeuble L'Espadon Voilier",
    "sg:city":"Perpignan",
    "sg:classifiers":[
        {
            "category":"Banks & Credit Unions",
            "subcategory":"Financial Services",
            "type":"Services"
        }
    ],
    "sg:phone":"+33 4 68 66 43 80",
    "sg:postcode":"66000",
    "sg:province":"Languedoc-Roussillon",
    "sg:tags":[
        "banking",
        "finance",
        "insurance"
    ],
    "wof:name":"Societe Fiduciaire Nationale Juridique Et Fiscale Fiducial (sofiral)",
    "wof:placetype":"venue"
},
  "geometry": {"coordinates":[2.901774,42.690598],"type":"Point"}
}