{
  "type": "Feature",
  "properties": {
    "addr:full":"Route de Doullens - Zone Industrielle Abbeville Picardie 80100",
    "addr:postcode":"80100",
    "addr:street":"Route De Doullens Zone Industrielle;Picardie",
    "iso:country":"FR",
    "sg:address":"Route de Doullens - Zone Industrielle",
    "sg:city":"Abbeville",
    "sg:orig_category":"Unclassifiable Establishments",
    "sg:phone":"+33 3 22 24 26 64",
    "sg:postcode":"80100",
    "sg:province":"Picardie",
    "wof:name":"Bailleul T.p. S.n.c.",
    "wof:placetype":"venue"
},
  "geometry": {"coordinates":[1.83483,50.105034],"type":"Point"}
}