{
  "type": "Feature",
  "properties": {
    "addr:full":"Usine Des Caillots 58302 Decize Cedex Bourgogne",
    "addr:postcode":"58302",
    "iso:country":"FR",
    "sg:address":"Usine Des Caillots 58302 Decize Cedex",
    "sg:classifiers":[
        {
            "category":"Manufacturing",
            "subcategory":"Rubber & Plastics",
            "type":"Manufacturing & Wholesale Goods"
        }
    ],
    "sg:phone":"+33 3 86 77 32 32",
    "sg:province":"Bourgogne",
    "wof:name":"Michelin Avs",
    "wof:placetype":"venue"
},
  "geometry": {"coordinates":[3.458527,46.828903],"type":"Point"}
}