{
  "type": "Feature",
  "properties": {
    "addr:full":"27 Rue Vernet 75008 Paris Ile de France 75008",
    "addr:housenumber":"27",
    "addr:postcode":"75008;75008",
    "addr:street":"Rue Vernet",
    "iso:country":"FR",
    "sg:address":"27 Rue Vernet 75008 Paris",
    "sg:classifiers":[
        {
            "category":"Professional",
            "subcategory":"Business Services",
            "type":"Services"
        }
    ],
    "sg:phone":"+33 1 56 62 26 00",
    "sg:postcode":"75008",
    "sg:province":"Ile de France",
    "sg:tags":[
        "training",
        "advice"
    ],
    "wof:name":"Jenebel Francoise Morice",
    "wof:placetype":"venue"
},
  "geometry": {"coordinates":[2.297555,48.871983],"type":"Point"}
}