{
  "type": "Feature",
  "properties": {
    "iso:country":"FR",
    "sg:address":"76, Rue Marceau, 76600 Le Havre",
    "sg:orig_category":"Unclassifiable Establishments",
    "sg:phone":"+33 2 35 26 50 33",
    "sg:province":"Haute Normandie",
    "wof:name":"Snef S.a.",
    "wof:placetype":"venue"
},
  "geometry": {"coordinates":[0.134649,49.489376],"type":"Point"}
}