{
  "type": "Feature",
  "properties": {
    "addr:full":"205 Rue Jean Jaur\u00e8s Zi St Florent 79000 Niort Poitou-Charentes 79000",
    "addr:housenumber":"205",
    "addr:postcode":"79000;79000",
    "addr:street":"Rue Jean Jaure\u0300S Zi St",
    "iso:country":"FR",
    "sg:address":"205 Rue Jean Jaur\u00e8s Zi St Florent 79000 Niort",
    "sg:classifiers":[
        {
            "category":"Manufacturing",
            "subcategory":"Paper Products",
            "type":"Manufacturing & Wholesale Goods"
        }
    ],
    "sg:phone":"+33 5 49 73 46 46",
    "sg:postcode":"79000",
    "sg:province":"Poitou-Charentes",
    "sg:tags":[
        "pharmaceutical",
        "-",
        "plastic",
        "rubber",
        "chemical",
        "chemistry",
        "by-product"
    ],
    "wof:name":"Wogegal Sa",
    "wof:placetype":"venue"
},
  "geometry": {"coordinates":[-0.504137,46.298],"type":"Point"}
}