{
  "type": "Feature",
  "properties": {
    "iso:country":"FR",
    "sg:address":"RUE DES FORTS 59960 Neuville en Ferrain",
    "sg:classifiers":[
        {
            "category":"Home & Garden",
            "subcategory":"Carpets & Floor Coverings",
            "type":"Retail Goods"
        }
    ],
    "sg:phone":"+33 3 20 69 35 35",
    "sg:province":"Nord Pas-de-Calais",
    "sg:tags":[
        "blind",
        "roller"
    ],
    "wof:name":"Hunter Douglas Fabrications Sa",
    "wof:placetype":"venue"
},
  "geometry": {"coordinates":[3.162775,50.751797],"type":"Point"}
}