{
  "type": "Feature",
  "properties": {
    "addr:full":"223, Rue Nationale, 59800 Lille Nord Pas-de-Calais",
    "addr:housenumber":"223",
    "addr:postcode":"59800",
    "addr:street":"Rue Nationale",
    "iso:country":"FR",
    "sg:address":"223, Rue Nationale, 59800 Lille",
    "sg:orig_category":"Non-Classified Establishments",
    "sg:phone":"+33 3 20 54 60 63",
    "sg:province":"Nord Pas-de-Calais",
    "wof:name":"Gravina Salvatore",
    "wof:placetype":"venue"
},
  "geometry": {"coordinates":[3.049234,50.631191],"type":"Point"}
}