{
  "type": "Feature",
  "properties": {
    "addr:full":"197, Grand Sud Avenue, 37170 Chambray les Tours Chambray-l\u00e8s-Tours Centre 37170",
    "addr:housenumber":"197",
    "addr:postcode":"37170;37170",
    "addr:street":"Grand Sud Avenue",
    "iso:country":"FR",
    "sg:address":"197, Grand Sud Avenue, 37170 Chambray les Tours",
    "sg:city":"Chambray-l\u00e8s-Tours",
    "sg:orig_category":"Unclassifiable Establishments",
    "sg:phone":"+33 2 47 28 63 40",
    "sg:postcode":"37170",
    "sg:province":"Centre",
    "wof:name":"S.t.a S.a.",
    "wof:placetype":"venue"
},
  "geometry": {"coordinates":[0.71327,47.33884],"type":"Point"}
}