{
  "type": "Feature",
  "properties": {
    "addr:full":"ZI les Clairs Ch\u00eanes Chavigny Lorraine 54230",
    "addr:postcode":"54230",
    "addr:street":"Zi Les Clairs Che\u0302Nes",
    "iso:country":"FR",
    "sg:address":"ZI les Clairs Ch\u00eanes",
    "sg:city":"Chavigny",
    "sg:orig_category":"Non-Classified Establishments",
    "sg:phone":"+33 3 83 44 68 00",
    "sg:postcode":"54230",
    "sg:province":"Lorraine",
    "wof:name":"Macchia S.a.",
    "wof:placetype":"venue"
},
  "geometry": {"coordinates":[6.124944,48.629288],"type":"Point"}
}