{
  "type": "Feature",
  "properties": {
    "iso:country":"FR",
    "sg:address":"4 avenue Hoche 75286 Paris CEDEX",
    "sg:classifiers":[
        {
            "category":"Shopping",
            "subcategory":"Clothing, Apparel, & Fashions",
            "type":"Retail Goods"
        }
    ],
    "sg:phone":"+33 1 47 63 11 40",
    "sg:province":"Ile de France",
    "sg:tags":[
        "blouse",
        "ladies'",
        "dress"
    ],
    "wof:name":"S.i.p.c. Daniel Hechter Sa",
    "wof:placetype":"venue"
},
  "geometry": {"coordinates":[2.303875,48.877754],"type":"Point"}
}