{
  "type": "Feature",
  "properties": {
    "addr:full":"14, rue Joseph Cugnot, 51430 Tinqueux Champagne",
    "addr:housenumber":"14",
    "addr:postcode":"51430",
    "addr:street":"Rue Joseph Cugnot",
    "iso:country":"FR",
    "sg:address":"14, rue Joseph Cugnot, 51430 Tinqueux",
    "sg:orig_category":"Unclassifiable Establishments",
    "sg:phone":"+33 3 26 79 12 12",
    "sg:province":"Champagne",
    "wof:name":"Demepool Bertrand S.a.",
    "wof:placetype":"venue"
},
  "geometry": {"coordinates":[3.985039,49.24015],"type":"Point"}
}