{
  "type": "Feature",
  "properties": {
    "addr:full":"25 Rte De P\u00e9ronne 80200 Buire Courcelles Picardie 80200",
    "addr:housenumber":"25",
    "addr:postcode":"80200;80200",
    "addr:street":"Rte De Pe\u0301Ronne",
    "iso:country":"FR",
    "sg:address":"25 Rte De P\u00e9ronne 80200 Buire Courcelles",
    "sg:classifiers":[
        {
            "category":"Autos & Motor Vehicles",
            "subcategory":"Automobile Sales",
            "type":"Retail Goods"
        }
    ],
    "sg:phone":"+33 3 22 83 07 77",
    "sg:postcode":"80200",
    "sg:province":"Picardie",
    "sg:tags":[
        "equipment",
        "motor-cars",
        "transport"
    ],
    "wof:name":"Delcar Industries",
    "wof:placetype":"venue"
},
  "geometry": {"coordinates":[2.935345,49.929661],"type":"Point"}
}