{
  "type": "Feature",
  "properties": {
    "iso:country":"FR",
    "sg:address":"Quai George V",
    "sg:city":"Le Havre",
    "sg:orig_category":"Unclassifiable Establishments",
    "sg:phone":"+33 2 35 19 83 04",
    "sg:postcode":"76600",
    "sg:province":"Haute Normandie",
    "wof:name":"Watson Brown S.a.",
    "wof:placetype":"venue"
},
  "geometry": {"coordinates":[0.11076,49.490952],"type":"Point"}
}