{
  "type": "Feature",
  "properties": {
    "iso:country":"FR",
    "sg:address":"La Tuilerie 14270 BIEVILLE QUETIEVILLE",
    "sg:city":"Cesny-aux-Vignes-Ou\u00e9zy",
    "sg:orig_category":"Polyvinyl Chloride Pvc Shrink Films",
    "sg:phone":"+33 2 31 20 58 90",
    "sg:postcode":"14270",
    "sg:province":"Basse Normandie",
    "wof:name":"Travyl S.a.",
    "wof:placetype":"venue"
},
  "geometry": {"coordinates":[-0.050049,49.096085],"type":"Point"}
}