{
  "type": "Feature",
  "properties": {
    "addr:full":"chemin Grande Communication 17 59470 WORMHOUT Nord Pas-de-Calais 59470",
    "addr:housenumber":"17",
    "addr:postcode":"59470;59470",
    "addr:street":"Chemin Grande Communication",
    "iso:country":"FR",
    "sg:address":"chemin Grande Communication 17 59470 WORMHOUT",
    "sg:classifiers":[
        {
            "category":"Communications",
            "subcategory":"Film & Video Production",
            "type":"Services"
        }
    ],
    "sg:phone":"+33 3 28 65 77 77",
    "sg:postcode":"59470",
    "sg:province":"Nord Pas-de-Calais",
    "sg:tags":[
        "industrial"
    ],
    "wof:name":"Sofilma Sa",
    "wof:placetype":"venue"
},
  "geometry": {"coordinates":[2.468422,50.882675],"type":"Point"}
}