{
  "type": "Feature",
  "properties": {
    "addr:full":"Rue Denis Papin 71100 Chalon Sur Sa\u00f4ne Chalon-sur-Sa\u00f4ne Bourgogne 71100",
    "addr:postcode":"71100;71100",
    "addr:street":"Rue Denis Papin",
    "iso:country":"FR",
    "sg:address":"Rue Denis Papin 71100 Chalon Sur Sa\u00f4ne",
    "sg:city":"Chalon-sur-Sa\u00f4ne",
    "sg:classifiers":[
        {
            "category":"Manufacturing",
            "subcategory":"Rubber & Plastics",
            "type":"Manufacturing & Wholesale Goods"
        }
    ],
    "sg:phone":"+33 3 85 97 12 00",
    "sg:postcode":"71100",
    "sg:province":"Bourgogne",
    "wof:name":"Metroplast Sa",
    "wof:placetype":"venue"
},
  "geometry": {"coordinates":[4.873455,46.787991],"type":"Point"}
}