{
  "type": "Feature",
  "properties": {
    "addr:full":"185, Av. de Senigallia, 89100 Sens Sens Bourgogne 89100",
    "addr:housenumber":"185",
    "addr:postcode":"89100;89100",
    "addr:street":"Av. De Senigallia",
    "iso:country":"FR",
    "sg:address":"185, Av. de Senigallia, 89100 Sens",
    "sg:city":"Sens",
    "sg:orig_category":"Unclassifiable Establishments",
    "sg:phone":"+33 3 86 83 73 83",
    "sg:postcode":"89100",
    "sg:province":"Bourgogne",
    "wof:name":"Senostores S.a.r.l.",
    "wof:placetype":"venue"
},
  "geometry": {"coordinates":[3.28715,48.184498],"type":"Point"}
}