{
  "type": "Feature",
  "properties": {
    "iso:country":"FR",
    "sg:address":"355 Avenue D'Italie 74300 Cluses",
    "sg:classifiers":[
        {
            "category":"Professional",
            "type":"Services"
        }
    ],
    "sg:phone":"+33 4 50 98 71 11",
    "sg:province":"Rhone-Alpes",
    "sg:tags":[
        "-",
        "related",
        "road",
        "transport"
    ],
    "wof:name":"Sotracom Sa",
    "wof:placetype":"venue"
},
  "geometry": {"coordinates":[6.595942,46.048561],"type":"Point"}
}