{
  "type": "Feature",
  "properties": {
    "addr:full":"20, Grande Rue, 74300 Cluses Rhone-Alpes 74300",
    "addr:housenumber":"20",
    "addr:postcode":"74300;74300",
    "addr:street":"Grande Rue",
    "iso:country":"FR",
    "sg:address":"20, Grande Rue, 74300 Cluses",
    "sg:orig_category":"Non-Classified Establishments",
    "sg:phone":"+33 820 33 79 30",
    "sg:postcode":"74300",
    "sg:province":"Rhone-Alpes",
    "wof:name":"B.p.s. - Banque Populaire De Cluzes",
    "wof:placetype":"venue"
},
  "geometry": {"coordinates":[6.580366,46.060703],"type":"Point"}
}