{
  "type": "Feature",
  "properties": {
    "addr:full":"2 Rue Turgot 27150 Etr\u00e9pagny Haute Normandie",
    "addr:housenumber":"2",
    "addr:postcode":"27150",
    "addr:street":"Rue Turgot;Haute Normandie",
    "iso:country":"FR",
    "sg:address":"2 Rue Turgot 27150 Etr\u00e9pagny",
    "sg:classifiers":[
        {
            "category":"Manufacturing",
            "subcategory":"Rubber & Plastics",
            "type":"Manufacturing & Wholesale Goods"
        }
    ],
    "sg:phone":"+33 2 32 27 65 00",
    "sg:province":"Haute Normandie",
    "wof:name":"Paulstra Snc",
    "wof:placetype":"venue"
},
  "geometry": {"coordinates":[1.613266,49.30637],"type":"Point"}
}