{
  "type": "Feature",
  "properties": {
    "iso:country":"FR",
    "sg:address":"Rue De Paris Parc Activites Industrielles C 77515 Faremoutiers",
    "sg:classifiers":[
        {
            "category":"Manufacturing",
            "subcategory":"Rubber & Plastics",
            "type":"Manufacturing & Wholesale Goods"
        }
    ],
    "sg:phone":"+33 1 64 04 24 14",
    "sg:province":"Ile de France",
    "wof:name":"Plastiques Grm",
    "wof:placetype":"venue"
},
  "geometry": {"coordinates":[2.988971,48.800442],"type":"Point"}
}