{
  "type": "Feature",
  "properties": {
    "iso:country":"FR",
    "sg:address":"303, Rue du Congo, 59420 Mouvaux",
    "sg:orig_category":"Unclassifiable Establishments",
    "sg:phone":"+33 3 20 70 55 07",
    "sg:province":"Nord Pas-de-Calais",
    "wof:name":"Claeys P\u00e8re Et Fils S.a.r.l.",
    "wof:placetype":"venue"
},
  "geometry": {"coordinates":[3.151768,50.70166],"type":"Point"}
}