{
  "type": "Feature",
  "properties": {
    "iso:country":"FR",
    "sg:address":"2, Rue Marcel Daussault - ZI, 33260 La Teste de Buch",
    "sg:city":"Teste-de-Buch",
    "sg:orig_category":"Unclassifiable Establishments",
    "sg:phone":"+33 5 56 54 73 73",
    "sg:postcode":"33260",
    "sg:province":"Aquitaine",
    "wof:name":"Arcachon Primeurs S.a.r.l.",
    "wof:placetype":"venue"
},
  "geometry": {"coordinates":[-1.145227,44.632915],"type":"Point"}
}