{
  "type": "Feature",
  "properties": {
    "iso:country":"FR",
    "sg:address":"Zi Du Canal Des Soeurs 17300 Rochefort",
    "sg:classifiers":[
        {
            "category":"Manufacturing",
            "subcategory":"Metals",
            "type":"Manufacturing & Wholesale Goods"
        }
    ],
    "sg:phone":"+33 5 46 88 03 76",
    "sg:postcode":"17300",
    "sg:province":"Poitou-Charentes",
    "sg:tags":[
        "-",
        "machine",
        "equipment",
        "engineering",
        "machinery",
        "mechanical"
    ],
    "wof:name":"Alu Creation 17",
    "wof:placetype":"venue"
},
  "geometry": {"coordinates":[-0.958704,45.934818],"type":"Point"}
}