{
  "type": "Feature",
  "properties": {
    "iso:country":"FR",
    "sg:address":"7, Rue de Roquebilli\u00e8re, 06300 Nice",
    "sg:city":"Billi\u00e8re",
    "sg:orig_category":"Non-Classified Establishments",
    "sg:phone":"+33 4 93 56 94 00",
    "sg:postcode":"31110",
    "sg:province":"Midi Pyr\u00e9n\u00e9es",
    "wof:name":"A.g.e.i. S.a. - Approvisionnement G\u00e9n\u00e9ral Electricit\u00e9 Industriel",
    "wof:placetype":"venue"
},
  "geometry": {"coordinates":[7.289423,43.71471],"type":"Point"}
}