{
  "type": "Feature",
  "properties": {
    "iso:country":"FR",
    "sg:address":"20 Petite Rue 55320 Ancemont",
    "sg:classifiers":[
        {
            "category":"Home & Garden",
            "subcategory":"Furniture",
            "type":"Retail Goods"
        }
    ],
    "sg:phone":"+33 3 29 87 74 00",
    "sg:postcode":"55320",
    "sg:province":"Lorraine",
    "sg:tags":[
        "household",
        "wood"
    ],
    "wof:name":"Anthea",
    "wof:placetype":"venue"
},
  "geometry": {"coordinates":[5.408875,49.068935],"type":"Point"}
}