{
  "type": "Feature",
  "properties": {
    "iso:country":"FR",
    "sg:address":"B.P. 142, 67303 Schiltigheim C\u00e9dex^^2, Av de la 2\u00e8me Division Blind\u00e9e, 67300 Schiltigheim",
    "sg:city":"Schiltigheim",
    "sg:orig_category":"Non-Classified Establishments",
    "sg:phone":"+33 3 88 19 13 00",
    "sg:postcode":"67300",
    "sg:province":"Alsace",
    "wof:name":"Istra I.n. S.a.",
    "wof:placetype":"venue"
},
  "geometry": {"coordinates":[7.748565,48.605949],"type":"Point"}
}