{
  "type": "Feature",
  "properties": {
    "iso:country":"FR",
    "sg:address":"Pl Ir\u00e8ne Joliot Curie Z A Des Couleurs 26000 Valence",
    "sg:classifiers":[
        {
            "category":"Professional",
            "subcategory":"Advertising",
            "type":"Services"
        }
    ],
    "sg:phone":"+33 4 75 43 23 05",
    "sg:postcode":"26000",
    "sg:province":"Rhone-Alpes",
    "sg:tags":[
        "information",
        "medium",
        "communication"
    ],
    "wof:name":"Avenir France",
    "wof:placetype":"venue"
},
  "geometry": {"coordinates":[4.928179,44.949085],"type":"Point"}
}