{
  "type": "Feature",
  "properties": {
    "addr:full":"65 avenue Victor Hugo 69160 Tassin La Demi Lune Rhone-Alpes 69160",
    "addr:housenumber":"65",
    "addr:postcode":"69160;69160",
    "addr:street":"Avenue Victor Hugo",
    "iso:country":"FR",
    "sg:address":"65 avenue Victor Hugo 69160 Tassin La Demi Lune",
    "sg:classifiers":[
        {
            "category":"Social Services",
            "subcategory":"Adult Care",
            "type":"Services"
        }
    ],
    "sg:phone":"+33 4 72 38 35 40",
    "sg:postcode":"69160",
    "sg:province":"Rhone-Alpes",
    "sg:tags":[
        "consulting",
        "management",
        "corporate"
    ],
    "wof:name":"Jnb Developpement S.a.",
    "wof:placetype":"venue"
},
  "geometry": {"coordinates":[4.783006,45.765129],"type":"Point"}
}