{
  "type": "Feature",
  "properties": {
    "iso:country":"FR",
    "sg:address":"za Lucinges 01370 Treffort Cuisiat",
    "sg:classifiers":[
        {
            "category":"Banks & Credit Unions",
            "subcategory":"Investment Brokerage",
            "type":"Services"
        }
    ],
    "sg:phone":"+33 4 74 42 36 65",
    "sg:postcode":"01370",
    "sg:province":"Rhone-Alpes",
    "sg:tags":[
        "-",
        "transport",
        "related"
    ],
    "wof:name":"Messagerie Bressane",
    "wof:placetype":"venue"
},
  "geometry": {"coordinates":[5.367818,46.269913],"type":"Point"}
}