{
  "type": "Feature",
  "properties": {
    "addr:full":"B.P. 106, 94513 Rungis C\u00e9dex^^18, Rue de Villeneuve, 94150 Rungis Ile de France 94150",
    "addr:housenumber":"b.p. 106",
    "addr:postcode":"94513;94150;94150",
    "addr:street":"Rue De Villeneuve",
    "iso:country":"FR",
    "sg:address":"B.P. 106, 94513 Rungis C\u00e9dex^^18, Rue de Villeneuve, 94150 Rungis",
    "sg:orig_category":"Non-Classified Establishments",
    "sg:phone":"+33 1 46 86 76 76",
    "sg:postcode":"94150",
    "sg:province":"Ile de France",
    "wof:name":"Compas S.a.",
    "wof:placetype":"venue"
},
  "geometry": {"coordinates":[2.35142,48.74918],"type":"Point"}
}