{
  "type": "Feature",
  "properties": {
    "iso:country":"FR",
    "sg:address":"B.P. 55, 74152 Rumilly C\u00e9dex^^9, Rue de l'industrie, 74150 Rumilly",
    "sg:orig_category":"Non-Classified Establishments",
    "sg:phone":"+33 4 50 01 10 01",
    "sg:province":"Rhone-Alpes",
    "wof:name":"B. C. S. S.a.s. - Etablissement Beaud Challes Solap",
    "wof:placetype":"venue"
},
  "geometry": {"coordinates":[5.947772,45.864349],"type":"Point"}
}