{
  "type": "Feature",
  "properties": {
    "iso:country":"FR",
    "sg:address":"9, Rue Alexandre Fleming, 49066 Angers C\u00e9dex 01",
    "sg:orig_category":"Non-Classified Establishments",
    "sg:phone":"+33 2 41 73 89 00",
    "sg:province":"Pays de la Loire",
    "wof:name":"L10 Communication S.a.",
    "wof:placetype":"venue"
},
  "geometry": {"coordinates":[-0.604342,47.477577],"type":"Point"}
}