{
  "type": "Feature",
  "properties": {
    "addr:full":"Za Hauts De Cou\u00ebron BP 28 44220 Cou\u00ebron Pays de Loire",
    "addr:housenumber":"28",
    "addr:postcode":"44220",
    "addr:street":"Za Hauts De Coue\u0308Ron Bp",
    "iso:country":"FR",
    "sg:address":"Za Hauts De Cou\u00ebron BP 28 44220 Cou\u00ebron",
    "sg:classifiers":[
        {
            "category":"Manufacturing",
            "subcategory":"Printing",
            "type":"Manufacturing & Wholesale Goods"
        }
    ],
    "sg:phone":"+33 2 40 38 00 71",
    "sg:province":"Pays de Loire",
    "sg:tags":[
        "publishing"
    ],
    "wof:name":"Simedit Imprimeur",
    "wof:placetype":"venue"
},
  "geometry": {"coordinates":[-1.727234,47.210861],"type":"Point"}
}