{
  "type": "Feature",
  "properties": {
    "addr:full":"1 Rue Du Parc 90600 Grandvillars Franche Comt\u00e9 90600",
    "addr:housenumber":"1",
    "addr:postcode":"90600;90600",
    "addr:street":"Rue Du Parc;Franche Comte\u0301",
    "iso:country":"FR",
    "sg:address":"1 Rue Du Parc 90600 Grandvillars",
    "sg:classifiers":[
        {
            "category":"Manufacturing",
            "subcategory":"Metals",
            "type":"Manufacturing & Wholesale Goods"
        }
    ],
    "sg:phone":"+33 3 84 57 30 00",
    "sg:postcode":"90600",
    "sg:province":"Franche Comt\u00e9",
    "sg:tags":[
        "metallurgy",
        "metalworking",
        "processing"
    ],
    "wof:name":"Former Sa",
    "wof:placetype":"venue"
},
  "geometry": {"coordinates":[6.9688,47.539146],"type":"Point"}
}