{
  "type": "Feature",
  "properties": {
    "addr:full":"B.P. 17, 59246 Mons en P\u00e9v\u00e8le^^49, Rue la P\u00e9trie, 59246 Mons en P\u00e9v\u00e8le Nord Pas-de-Calais 59246",
    "addr:postcode":"59246;59246;59246",
    "addr:street":"B.P. 17;Rue La Pe\u0301Trie;Pas-De-Calais",
    "iso:country":"FR",
    "sg:address":"B.P. 17, 59246 Mons en P\u00e9v\u00e8le^^49, Rue la P\u00e9trie, 59246 Mons en P\u00e9v\u00e8le",
    "sg:orig_category":"Maintenance sur sites M\u00e9canique g\u00e9n\u00e9rale R\u00e9vision et/ou r\u00e9paration de pompes Vannes de r\u00e9gulation",
    "sg:phone":"+33 3 20 86 55 29",
    "sg:postcode":"59246",
    "sg:province":"Nord Pas-de-Calais",
    "wof:name":"P\u00e9v\u00e8le M\u00e9canique S.a.r.l.",
    "wof:placetype":"venue"
},
  "geometry": {"coordinates":[3.10085,50.479244],"type":"Point"}
}