{
  "type": "Feature",
  "properties": {
    "addr:full":"387, Rue des Champs, 76230 Bois Guillaume Haute Normandie",
    "addr:housenumber":"387",
    "addr:postcode":"76230",
    "addr:street":"Rue Des Champs;Haute Normandie",
    "iso:country":"FR",
    "sg:address":"387, Rue des Champs, 76230 Bois Guillaume",
    "sg:orig_category":"Unclassifiable Establishments",
    "sg:phone":"+33 2 35 59 49 39",
    "sg:province":"Haute Normandie",
    "wof:name":"Bureau D'etudes Techniques Sogeti S.a.",
    "wof:placetype":"venue"
},
  "geometry": {"coordinates":[1.112285,49.469482],"type":"Point"}
}