{
  "type": "Feature",
  "properties": {
    "iso:country":"FR",
    "sg:address":"13680 Lan\u00e7on Provence",
    "sg:city":"Lan\u00e7on",
    "sg:orig_category":"Unclassifiable Establishments",
    "sg:phone":"+33 4 90 42 83 41",
    "sg:postcode":"08250",
    "sg:province":"Champagne",
    "wof:name":"E.g.c. S.a.r.l. - Entreprise G\u00e9n\u00e9rale De Chaudronnerie",
    "wof:placetype":"venue"
},
  "geometry": {"coordinates":[5.12418,43.590092],"type":"Point"}
}