{
  "type": "Feature",
  "properties": {
    "addr:full":"1579, Av. Joliot Curie - ZI Saint C\u00e9saire, 30900 N\u00eemes Languedoc-Roussillon",
    "addr:housenumber":"1579",
    "addr:postcode":"30900",
    "addr:street":"Av. Joliot Curie Zi Saint Ce\u0301Saire",
    "iso:country":"FR",
    "sg:address":"1579, Av. Joliot Curie - ZI Saint C\u00e9saire, 30900 N\u00eemes",
    "sg:orig_category":"Unclassifiable Establishments",
    "sg:phone":"+33 4 66 64 00 02",
    "sg:province":"Languedoc-Roussillon",
    "wof:name":"M.c.m. S.a. - M\u00e9ridionale De Constructions M\u00e9talliques",
    "wof:placetype":"venue"
},
  "geometry": {"coordinates":[4.356115,43.830025],"type":"Point"}
}