{
  "type": "Feature",
  "properties": {
    "addr:full":"80200 Flaucourt Picardie",
    "addr:postcode":"80200",
    "iso:country":"FR",
    "sg:address":"80200 Flaucourt",
    "sg:orig_category":"Unclassifiable Establishments",
    "sg:phone":"+33 3 22 83 55 83",
    "sg:province":"Picardie",
    "wof:name":"Bonduelle Grand Public S.a.",
    "wof:placetype":"venue"
},
  "geometry": {"coordinates":[2.866116,49.909279],"type":"Point"}
}