{
  "type": "Feature",
  "properties": {
    "addr:full":"B.P. 3410 Rodez C\u00e9dex^^Le Puech 12000 Rodez Midi Pyr\u00e9n\u00e9es 12000",
    "addr:postcode":"3410;12000;12000",
    "addr:street":"B.P.;Puech",
    "iso:country":"FR",
    "sg:address":"B.P. 3410",
    "sg:city":"Rodez C\u00e9dex^^Le Puech 12000 Rodez",
    "sg:orig_category":"Non-Classified Establishments",
    "sg:phone":"+33 5 65 77 65 00",
    "sg:postcode":"12000",
    "sg:province":"Midi Pyr\u00e9n\u00e9es",
    "wof:name":"Alstom Entreprise S.a.",
    "wof:placetype":"venue"
},
  "geometry": {"coordinates":[2.57289,44.349735],"type":"Point"}
}