{
  "type": "Feature",
  "properties": {
    "iso:country":"FR",
    "sg:address":"4 pl Gabriel Peri; Paris; 92270",
    "sg:classifiers":[
        {
            "category":"Banks & Credit Unions",
            "subcategory":"Bank",
            "type":"Services"
        }
    ],
    "sg:phone":"+33 1 42 42 42 81",
    "sg:postcode":"92270",
    "sg:province":"Ile de France",
    "wof:name":"Bred, Banque Populaire",
    "wof:placetype":"venue"
},
  "geometry": {"coordinates":[2.26742,48.913509],"type":"Point"}
}