{
  "type": "Feature",
  "properties": {
    "iso:country":"FR",
    "sg:address":"ZI du Launay 22800 ST BRANDAN",
    "sg:city":"Cohiniac",
    "sg:classifiers":[
        {
            "category":"Government",
            "subcategory":"Customs House",
            "type":"Public Place"
        }
    ],
    "sg:phone":"+33 2 96 79 62 00",
    "sg:postcode":"22800",
    "sg:province":"Bretagne",
    "sg:tags":[
        "caravan",
        "folding"
    ],
    "wof:name":"Autostar S.a.",
    "wof:placetype":"venue"
},
  "geometry": {"coordinates":[-2.8699,48.38998],"type":"Point"}
}