{
  "type": "Feature",
  "properties": {
    "iso:country":"FR",
    "sg:address":"26, Av. Charles Bedaux, 37000 Tours",
    "sg:city":"Tours",
    "sg:orig_category":"Non-Classified Establishments",
    "sg:phone":"+33 2 47 39 44 72",
    "sg:postcode":"37000",
    "sg:province":"Centre",
    "wof:name":"Graphi Compo S.a.r.l.",
    "wof:placetype":"venue"
},
  "geometry": {"coordinates":[0.671864,47.376537],"type":"Point"}
}