{
  "type": "Feature",
  "properties": {
    "iso:country":"FR",
    "sg:address":"178, Chemin Vial, 01310 Polliat",
    "sg:orig_category":"Non-Classified Establishments",
    "sg:phone":"+33 4 74 30 42 43",
    "sg:province":"Rhone-Alpes",
    "wof:name":"Roux & Gondrand S.a.r.l.",
    "wof:placetype":"venue"
},
  "geometry": {"coordinates":[5.15904,46.235565],"type":"Point"}
}