{
  "type": "Feature",
  "properties": {
    "iso:country":"FR",
    "sg:address":"40, Av. de Flandre, 59491 Villeneuve d'Ascq",
    "sg:orig_category":"Non-Classified Establishments",
    "sg:phone":"+33 3 28 33 07 83",
    "sg:province":"Nord Pas-de-Calais",
    "wof:name":"G.s.f. Conseil S.a.r.l.",
    "wof:placetype":"venue"
},
  "geometry": {"coordinates":[2.361394,49.27264],"type":"Point"}
}