{
  "type": "Feature",
  "properties": {
    "addr:full":"Za Des Poupettes 91580 Villeneuve Sur Auvers Ile de France",
    "addr:postcode":"91580",
    "addr:street":"Za Des Poupettes",
    "iso:country":"FR",
    "sg:address":"Za Des Poupettes 91580 Villeneuve Sur Auvers",
    "sg:classifiers":[
        {
            "category":"Professional",
            "type":"Services"
        }
    ],
    "sg:phone":"+33 1 69 92 28 38",
    "sg:province":"Ile de France",
    "sg:tags":[
        "transport",
        "road"
    ],
    "wof:name":"Transports Jbf Euroval Sarl",
    "wof:placetype":"venue"
},
  "geometry": {"coordinates":[2.247426,48.475388],"type":"Point"}
}