{
  "type": "Feature",
  "properties": {
    "addr:full":"Rue des Artisans Cond\u00e9 sur Sarthe Basse Normandie 61250",
    "addr:postcode":"61250",
    "addr:street":"Rue Des Artisans Conde\u0301;Sarthe Basse",
    "iso:country":"FR",
    "sg:address":"Rue des Artisans",
    "sg:city":"Cond\u00e9 sur Sarthe",
    "sg:orig_category":"Non-Classified Establishments",
    "sg:phone":"+33 2 33 32 25 05",
    "sg:postcode":"61250",
    "sg:province":"Basse Normandie",
    "wof:name":"C.e.m.i.p. S.a. - Conception Essais Moules Industries Mati\u00e8res Plas",
    "wof:placetype":"venue"
},
  "geometry": {"coordinates":[0.060475,48.430786],"type":"Point"}
}