{
  "type": "Feature",
  "properties": {
    "iso:country":"FR",
    "sg:address":"21 Rue Du Parc 68700 Cernay",
    "sg:city":"Cernay",
    "sg:classifiers":[
        {
            "category":"Home & Garden",
            "subcategory":"Furniture",
            "type":"Retail Goods"
        }
    ],
    "sg:phone":"+33 3 89 35 64 30",
    "sg:postcode":"68700",
    "sg:province":"Alsace",
    "sg:tags":[
        "household",
        "wood"
    ],
    "wof:name":"Mts Productions",
    "wof:placetype":"venue"
},
  "geometry": {"coordinates":[7.175107,47.802814],"type":"Point"}
}