{
  "type": "Feature",
  "properties": {
    "addr:full":"34 rue Casimir P\u00e9rier 69002 Lyon Rhone-Alpes 69002",
    "addr:housenumber":"34",
    "addr:postcode":"69002;69002",
    "addr:street":"Rue Casimir Pe\u0301Rier",
    "iso:country":"FR",
    "sg:address":"34 rue Casimir P\u00e9rier 69002 Lyon",
    "sg:classifiers":[
        {
            "category":"Food & Beverages",
            "subcategory":"Fruits & Vegetables",
            "type":"Retail Goods"
        }
    ],
    "sg:phone":"+33 4 78 42 54 00",
    "sg:postcode":"69002",
    "sg:province":"Rhone-Alpes",
    "wof:name":"Etablissements Frutas Sanchez Sarl",
    "wof:placetype":"venue"
},
  "geometry": {"coordinates":[4.828975,45.759399],"type":"Point"}
}