{
  "type": "Feature",
  "properties": {
    "iso:country":"FR",
    "sg:address":"5, Rue des Marmouzets, 51100 Reims",
    "sg:orig_category":"Unclassifiable Establishments",
    "sg:phone":"+33 3 26 50 62 50",
    "sg:province":"Champagne",
    "wof:name":"C.c.i. De Reims - Chambre De Commerce Et D'industrie De Reims Et D'epernay",
    "wof:placetype":"venue"
},
  "geometry": {"coordinates":[4.03678,49.256058],"type":"Point"}
}