{
  "type": "Feature",
  "properties": {
    "addr:full":"56, Rue de Dole, 25000 Besan\u00e7on Franche Comt\u00e9",
    "addr:housenumber":"56",
    "addr:postcode":"25000",
    "addr:street":"Rue De Dole;Franche Comte\u0301",
    "iso:country":"FR",
    "sg:address":"56, Rue de Dole, 25000 Besan\u00e7on",
    "sg:orig_category":"Non-Classified Establishments",
    "sg:phone":"+33 3 81 52 45 63",
    "sg:province":"Franche Comt\u00e9",
    "wof:name":"S.a.c.r.e.m.b. S.a.",
    "wof:placetype":"venue"
},
  "geometry": {"coordinates":[6.007256,47.234074],"type":"Point"}
}