{
  "type": "Feature",
  "properties": {
    "addr:full":"74, Rte de Savigny, 21200 Beaune Beaune Bourgogne 21200",
    "addr:housenumber":"74",
    "addr:postcode":"21200;21200",
    "addr:street":"Rte De Savigny",
    "iso:country":"FR",
    "sg:address":"74, Rte de Savigny, 21200 Beaune",
    "sg:city":"Beaune",
    "sg:orig_category":"Unclassifiable Establishments",
    "sg:phone":"+33 3 80 24 85 85",
    "sg:postcode":"21200",
    "sg:province":"Bourgogne",
    "wof:name":"Thomson Csf Passive Components S.a.",
    "wof:placetype":"venue"
},
  "geometry": {"coordinates":[4.840502,47.03957],"type":"Point"}
}