{
  "type": "Feature",
  "properties": {
    "iso:country":"FR",
    "sg:address":"2, Rue des Gonnes, 49800 Andard",
    "sg:orig_category":"Non-Classified Establishments",
    "sg:phone":"+33 2 41 54 98 88",
    "sg:postcode":"49800",
    "sg:province":"Pays de Loire",
    "wof:name":"Anjou Irrigation S.a.r.l.",
    "wof:placetype":"venue"
},
  "geometry": {"coordinates":[-0.382562,47.466213],"type":"Point"}
}