{
  "type": "Feature",
  "properties": {
    "addr:full":"Le Bourg 16150 Exideuil Poitou-Charentes",
    "addr:postcode":"16150",
    "addr:street":"Le Bourg",
    "iso:country":"FR",
    "sg:address":"Le Bourg 16150 Exideuil",
    "sg:classifiers":[
        {
            "category":"Communications",
            "subcategory":"Newspaper",
            "type":"Services"
        }
    ],
    "sg:phone":"+33 5 45 71 83 83",
    "sg:province":"Poitou-Charentes",
    "sg:tags":[
        "material",
        "-",
        "packaging",
        "raw",
        "paper",
        "cardboard"
    ],
    "wof:name":"Sofpo Emballages Sa",
    "wof:placetype":"venue"
},
  "geometry": {"coordinates":[0.740556,45.825764],"type":"Point"}
}