{
  "type": "Feature",
  "properties": {
    "iso:country":"FR",
    "sg:address":"172, Rue Alfred de Qu\u00e9ant, 92000 Nanterre",
    "sg:orig_category":"Non-Classified Establishments",
    "sg:phone":"+33 1 47 84 62 50",
    "sg:postcode":"92000",
    "sg:province":"Ile de France",
    "wof:name":"D\u00e9m\u00e9nagements Durand S.a.r.l.",
    "wof:placetype":"venue"
},
  "geometry": {"coordinates":[2.226014,48.909454],"type":"Point"}
}