{
  "type": "Feature",
  "properties": {
    "addr:full":"125 125 \u00e0 Fontainebleau 127 94276 Kremlin Bic\u00eatre (Le) ced Franche Comt\u00e9",
    "addr:housenumber":"125 a\u0300;127",
    "addr:postcode":"94276",
    "addr:street":"Fontainebleau;Bice\u0302Tre Le;Franche Comte\u0301",
    "iso:country":"FR",
    "sg:address":"125 125 \u00e0",
    "sg:city":"Fontainebleau 127 94276 Kremlin Bic\u00eatre (Le) ced",
    "sg:classifiers":[
        {
            "category":"Manufacturing",
            "subcategory":"Chemicals & Compounds",
            "type":"Manufacturing & Wholesale Goods"
        }
    ],
    "sg:phone":"+33 1 46 72 30 95",
    "sg:province":"Franche Comt\u00e9",
    "sg:tags":[
        "pharmaceutical",
        "chemistry",
        "-",
        "by-product"
    ],
    "wof:name":"Onip",
    "wof:placetype":"venue"
},
  "geometry": {"coordinates":[-92.52522999999999,41.213619],"type":"Point"}
}