{
  "type": "Feature",
  "properties": {
    "addr:full":"5, Rue des Molarets, 01590 Dortan Rhone-Alpes 01590",
    "addr:housenumber":"5",
    "addr:postcode":"01590;01590",
    "addr:street":"Rue Des Molarets",
    "iso:country":"FR",
    "sg:address":"5, Rue des Molarets, 01590 Dortan",
    "sg:orig_category":"Unclassifiable Establishments",
    "sg:phone":"+33 4 74 77 73 43",
    "sg:postcode":"01590",
    "sg:province":"Rhone-Alpes",
    "wof:name":"Entreprise Marcel Picod",
    "wof:placetype":"venue"
},
  "geometry": {"coordinates":[5.651253,46.317097],"type":"Point"}
}