{
  "type": "Feature",
  "properties": {
    "iso:country":"FR",
    "sg:address":"ZAC de Grezailles Rigoulet",
    "sg:city":"Bo\u00e9",
    "sg:orig_category":"Unclassifiable Establishments",
    "sg:phone":"+33 5 53 96 47 05",
    "sg:postcode":"47550",
    "sg:province":"Aquitaine",
    "wof:name":"T.f.e.",
    "wof:placetype":"venue"
},
  "geometry": {"coordinates":[0.626876,44.160385],"type":"Point"}
}