{
  "type": "Feature",
  "properties": {
    "addr:full":"26, Rue Montmarlet Mont\u00e9mafroy, 02470 Dammard Picardie",
    "addr:housenumber":"26",
    "addr:postcode":"02470",
    "addr:street":"Rue Montmarlet Monte\u0301Mafroy",
    "iso:country":"FR",
    "sg:address":"26, Rue Montmarlet Mont\u00e9mafroy, 02470 Dammard",
    "sg:orig_category":"Non-Classified Establishments",
    "sg:phone":"+33 3 23 71 01 75",
    "sg:province":"Picardie",
    "wof:name":"G. Tournant S.a.r.l.",
    "wof:placetype":"venue"
},
  "geometry": {"coordinates":[3.25989,49.16806],"type":"Point"}
}