{
  "type": "Feature",
  "properties": {
    "iso:country":"FR",
    "sg:address":"Champ Trentenier 07800 Charmes Sur Rh\u00f4ne",
    "sg:classifiers":[
        {
            "category":"Food & Beverages",
            "subcategory":"Fruits & Vegetables",
            "type":"Retail Goods"
        }
    ],
    "sg:phone":"+33 4 75 60 90 90",
    "sg:postcode":"07800",
    "sg:province":"Rhone-Alpes",
    "sg:tags":[
        "preserve",
        "frozen",
        "product",
        "related"
    ],
    "wof:name":"Oxaves Sa",
    "wof:placetype":"venue"
},
  "geometry": {"coordinates":[4.788699,44.833321],"type":"Point"}
}