{
  "type": "Feature",
  "properties": {
    "addr:full":"11 Boulevard De La Paix Reims Champagne 51100",
    "addr:housenumber":"11",
    "addr:postcode":"51100",
    "addr:street":"Boulevard De La Paix;Champagne",
    "iso:country":"FR",
    "sg:address":"11 Boulevard De La Paix",
    "sg:city":"Reims",
    "sg:classifiers":[
        {
            "category":"Banks & Credit Unions",
            "subcategory":"Financial Services",
            "type":"Services"
        }
    ],
    "sg:phone":"+33 3 26 87 77 99",
    "sg:postcode":"51100",
    "sg:province":"Champagne",
    "sg:tags":[
        "banking",
        "finance",
        "insurance"
    ],
    "wof:name":"Credit Lyonnais Sa",
    "wof:placetype":"venue"
},
  "geometry": {"coordinates":[4.040558,49.255375],"type":"Point"}
}