{
  "type": "Feature",
  "properties": {
    "iso:country":"FR",
    "sg:address":"107 Chem Val Fleuri 06800 Cagnes Sur Mer",
    "sg:classifiers":[
        {
            "category":"Bakery",
            "type":"Food & Drink"
        }
    ],
    "sg:phone":"+33 4 93 31 67 48",
    "sg:province":"Haute Normandie",
    "sg:tags":[
        "cake",
        "product",
        "related",
        "bread"
    ],
    "wof:name":"Paindor Nice Sarl",
    "wof:placetype":"venue"
},
  "geometry": {"coordinates":[7.165118,43.669529],"type":"Point"}
}