{
  "type": "Feature",
  "properties": {
    "addr:full":"Quartier Coudoulet Orange Centre 84100",
    "addr:postcode":"84100",
    "addr:street":"Quartier",
    "iso:country":"FR",
    "sg:address":"Quartier Coudoulet",
    "sg:city":"Orange",
    "sg:orig_category":"Unclassifiable Establishments",
    "sg:phone":"+33 4 90 70 88 35",
    "sg:postcode":"84100",
    "sg:province":"Centre",
    "wof:name":"Capelli",
    "wof:placetype":"venue"
},
  "geometry": {"coordinates":[4.825505,44.120861],"type":"Point"}
}