{
  "type": "Feature",
  "properties": {
    "iso:country":"FR",
    "sg:address":"110, Cours Tolsto\u00ef, 69100 Villeurbanne",
    "sg:orig_category":"Non-Classified Establishments",
    "sg:phone":"+33 4 78 68 74 75",
    "sg:province":"Rhone-Alpes",
    "wof:name":"S.e.t. Jacoulot S.a.r.l.",
    "wof:placetype":"venue"
},
  "geometry": {"coordinates":[4.880071,45.762047],"type":"Point"}
}