{
  "type": "Feature",
  "properties": {
    "addr:full":"11 place Maisonnat; Fontaine; 38601 Fontain Franche Comt\u00e9 25660",
    "addr:housenumber":"11",
    "addr:postcode":"38601;25660",
    "addr:street":"Place Maisonnat Fontaine;Franche Comte\u0301",
    "iso:country":"FR",
    "sg:address":"11 place Maisonnat; Fontaine; 38601",
    "sg:city":"Fontain",
    "sg:classifiers":[
        {
            "category":"Banks & Credit Unions",
            "subcategory":"Bank",
            "type":"Services"
        }
    ],
    "sg:phone":"+33 4 76 26 42 13",
    "sg:postcode":"25660",
    "sg:province":"Franche Comt\u00e9",
    "wof:name":"Banque Rh\u00f4ne Alpes",
    "wof:placetype":"venue"
},
  "geometry": {"coordinates":[5.687735,45.191673],"type":"Point"}
}