{
  "type": "Feature",
  "properties": {
    "iso:country":"FR",
    "sg:address":"zi Grands Bois 49280 Saint L\u00e9ger sous Cholet",
    "sg:classifiers":[
        {
            "category":"Shopping",
            "subcategory":"Computers & Home Electronics",
            "type":"Retail Goods"
        }
    ],
    "sg:phone":"+33 2 41 56 28 13",
    "sg:postcode":"49280",
    "sg:province":"Pays de Loire",
    "sg:tags":[
        "equipment",
        "electrical",
        "component",
        "electric",
        "electronic"
    ],
    "wof:name":"Cesl",
    "wof:placetype":"venue"
},
  "geometry": {"coordinates":[-0.909529,47.094292],"type":"Point"}
}