{
  "type": "Feature",
  "properties": {
    "iso:country":"FR",
    "sg:address":"B.P. 604, 74500 Evian les Bains^^1040, Rte de la Dranse, 74500 Amphion les Bains",
    "sg:orig_category":"Non-Classified Establishments",
    "sg:phone":"+33 4 50 70 00 05",
    "sg:province":"Rhone-Alpes",
    "wof:name":"Sagradranse S.a.",
    "wof:placetype":"venue"
},
  "geometry": {"coordinates":[6.64146,46.330173],"type":"Point"}
}