{
  "type": "Feature",
  "properties": {
    "iso:country":"FR",
    "sg:address":"B.P. 116, 07131 Saint P\u00e9ray C\u00e9dex^^Rte de N\u00eemes, 07130 Saint P\u00e9ray",
    "sg:orig_category":"Non-Classified Establishments",
    "sg:phone":"+33 4 75 40 44 44",
    "sg:postcode":"07130",
    "sg:province":"Rhone-Alpes",
    "wof:name":"Fruitcoop Fra\u00eecheur",
    "wof:placetype":"venue"
},
  "geometry": {"coordinates":[4.84198,44.93663],"type":"Point"}
}