{
  "type": "Feature",
  "properties": {
    "iso:country":"FR",
    "sg:address":"2 rue Stephenson; Montigny le Bretonneux; 78181",
    "sg:classifiers":[
        {
            "category":"Banks & Credit Unions",
            "subcategory":"Bank",
            "type":"Services"
        }
    ],
    "sg:phone":"+33 30440606",
    "sg:province":"Midi Pyr\u00e9n\u00e9es",
    "wof:name":"Cr\u00e9dit Industriel Et, Commercial De Paris",
    "wof:placetype":"venue"
},
  "geometry": {"coordinates":[2.04854,48.786541],"type":"Point"}
}