{
  "type": "Feature",
  "properties": {
    "addr:full":"B.P. 159, 70003 Vesoul C\u00e9dex^^9, Av du Lac, 70000 Vesoul Franche Comt\u00e9",
    "addr:housenumber":"b.p. 159",
    "addr:postcode":"70003;70000",
    "addr:street":"Av Du Lac;Franche Comte\u0301",
    "iso:country":"FR",
    "sg:address":"B.P. 159, 70003 Vesoul C\u00e9dex^^9, Av du Lac, 70000 Vesoul",
    "sg:orig_category":"Non-Classified Establishments",
    "sg:phone":"+33 3 84 96 81 00",
    "sg:province":"Franche Comt\u00e9",
    "wof:name":"S.i.c.a.e. De Ray Cendrecourt S.a.",
    "wof:placetype":"venue"
},
  "geometry": {"coordinates":[6.034054,47.524078],"type":"Point"}
}