{
  "type": "Feature",
  "properties": {
    "iso:country":"FR",
    "sg:address":"B.P. 159, 70003 Vesoul C\u00e9dex^^9, Av du Lac, 70000 Vesoul",
    "sg:orig_category":"Non-Classified Establishments",
    "sg:phone":"+33 3 84 96 81 00",
    "sg:province":"Franche Comt\u00e9",
    "wof:name":"S.i.c.a.e. De Ray Cendrecourt S.a.",
    "wof:placetype":"venue"
},
  "geometry": {"coordinates":[6.034054,47.524078],"type":"Point"}
}