{
  "type": "Feature",
  "properties": {
    "addr:full":"Route Charpenay 69210 Lentilly Rhone-Alpes 69210",
    "addr:postcode":"69210;69210",
    "addr:street":"Route Charpenay;Rhone-Alpes",
    "iso:country":"FR",
    "sg:address":"Route Charpenay 69210 Lentilly",
    "sg:classifiers":[
        {
            "category":"Manufacturing",
            "subcategory":"Jewelry",
            "type":"Manufacturing & Wholesale Goods"
        }
    ],
    "sg:phone":"+33 4 74 01 89 89",
    "sg:postcode":"69210",
    "sg:province":"Rhone-Alpes",
    "sg:tags":[
        "product",
        "miscellaneous",
        "jewellery"
    ],
    "wof:name":"Charles Perroud Sa",
    "wof:placetype":"venue"
},
  "geometry": {"coordinates":[4.665988,45.816891],"type":"Point"}
}