{
  "type": "Feature",
  "properties": {
    "addr:full":"46 Av Villarceau 25042 Besan\u00e7on Bourgogne",
    "addr:postcode":"25042",
    "addr:street":"46 Av Villarceau",
    "iso:country":"FR",
    "sg:address":"46 Av Villarceau 25042 Besan\u00e7on",
    "sg:classifiers":[
        {
            "category":"Professional",
            "subcategory":"Business Services",
            "type":"Services"
        }
    ],
    "sg:phone":"+33 3 81 25 25 45",
    "sg:province":"Bourgogne",
    "sg:tags":[
        "body",
        "advice"
    ],
    "wof:name":"Chambre De Commerce Et D'industrie Du Doubs",
    "wof:placetype":"venue"
},
  "geometry": {"coordinates":[6.02091,47.239639],"type":"Point"}
}