{
  "type": "Feature",
  "properties": {
    "iso:country":"FR",
    "sg:address":"2, Rue du Mar\u00e9chal Joffre, 37000 Tours",
    "sg:city":"Tours",
    "sg:orig_category":"Non-Classified Establishments",
    "sg:phone":"+33 2 47 41 20 20",
    "sg:postcode":"37000",
    "sg:province":"Centre",
    "wof:name":"Roy S.a.",
    "wof:placetype":"venue"
},
  "geometry": {"coordinates":[0.686855,47.394573],"type":"Point"}
}