{
  "type": "Feature",
  "properties": {
    "addr:full":"46, Rue du Champreux, 91540 Mennecy Ile de France",
    "addr:housenumber":"46",
    "addr:postcode":"91540",
    "addr:street":"Rue Du Champreux",
    "iso:country":"FR",
    "sg:address":"46, Rue du Champreux, 91540 Mennecy",
    "sg:orig_category":"Unclassifiable Establishments",
    "sg:phone":"+33 1 69 90 63 70",
    "sg:province":"Ile de France",
    "wof:name":"H.b.m. France S.a.s.",
    "wof:placetype":"venue"
},
  "geometry": {"coordinates":[2.429869,48.557865],"type":"Point"}
}