{
  "type": "Feature",
  "properties": {
    "addr:full":"La Haute Vern\u00e9e 01960 P\u00e9ronnas Rhone-Alpes",
    "addr:postcode":"01960",
    "addr:street":"Verne\u0301E",
    "iso:country":"FR",
    "sg:address":"La Haute Vern\u00e9e 01960 P\u00e9ronnas",
    "sg:orig_category":"Unclassifiable Establishments",
    "sg:phone":"+33 4 74 21 27 81",
    "sg:province":"Rhone-Alpes",
    "wof:name":"Etablissements Jacques Niel Et Fils S.a.r.l.",
    "wof:placetype":"venue"
},
  "geometry": {"coordinates":[5.180992,46.169678],"type":"Point"}
}