{
  "type": "Feature",
  "properties": {
    "addr:full":"10 All Des Erables BP 50 Parc D'Activit\u00e9s R\u00e9publique Carnot 69632 V\u00e9nissieux Cedex Haute Normandie",
    "addr:housenumber":"10;50",
    "addr:postcode":"69632",
    "addr:street":"All Des Erables Bp;Parc D'Activite \u0301S Re\u0301Publique Carnot",
    "iso:country":"FR",
    "sg:address":"10 All Des Erables BP 50 Parc D'Activit\u00e9s R\u00e9publique Carnot 69632 V\u00e9nissieux Cedex",
    "sg:classifiers":[
        {
            "category":"Shopping",
            "type":"Retail Goods"
        }
    ],
    "sg:phone":"+33 4 78 70 84 88",
    "sg:province":"Haute Normandie",
    "sg:tags":[
        "metallurgy",
        "finished",
        "-",
        "metalworking",
        "metallic"
    ],
    "wof:name":"Roulement Service",
    "wof:placetype":"venue"
},
  "geometry": {"coordinates":[4.880816,45.702873],"type":"Point"}
}