{
  "type": "Feature",
  "properties": {
    "iso:country":"FR",
    "sg:address":"104 Rue Joseph Vernet 84000 Avignon",
    "sg:classifiers":[
        {
            "category":"Wholesale",
            "subcategory":"Medical Equipment & Supplies",
            "type":"Manufacturing & Wholesale Goods"
        }
    ],
    "sg:phone":"+33 4 90 82 19 74",
    "sg:province":"Picardie",
    "sg:tags":[
        "instrument",
        "health",
        "-",
        "precision"
    ],
    "wof:name":"Laboratoire De Correction Auditive D'avignon",
    "wof:placetype":"venue"
},
  "geometry": {"coordinates":[4.804729,43.945217],"type":"Point"}
}