{
  "type": "Feature",
  "properties": {
    "addr:full":"Vorzelas 42480 La Fouillouse Rhone-Alpes 42480",
    "addr:postcode":"42480;42480",
    "addr:street":"Vorzelas",
    "iso:country":"FR",
    "sg:address":"Vorzelas 42480 La Fouillouse",
    "sg:orig_category":"Unclassifiable Establishments",
    "sg:phone":"+33 4 77 30 15 97",
    "sg:postcode":"42480",
    "sg:province":"Rhone-Alpes",
    "wof:name":"Transports Bayard S.a.",
    "wof:placetype":"venue"
},
  "geometry": {"coordinates":[4.301087,45.515182],"type":"Point"}
}