{
  "type": "Feature",
  "properties": {
    "iso:country":"FR",
    "sg:address":"201 Rue Victor Hugo 37540 St Cyr Sur Loire",
    "sg:city":"Saint-Cyr-sur-Loire",
    "sg:classifiers":[
        {
            "category":"Professional",
            "subcategory":"Business Services",
            "type":"Services"
        }
    ],
    "sg:phone":"+33 2 47 54 10 37",
    "sg:postcode":"37540",
    "sg:province":"Centre",
    "sg:tags":[
        "training",
        "advice"
    ],
    "wof:name":"College Henri Bergson",
    "wof:placetype":"venue"
},
  "geometry": {"coordinates":[0.66761,47.410881],"type":"Point"}
}