{
  "type": "Feature",
  "properties": {
    "addr:full":"14, Rue de Marcq-en-Baroeul, 59290 Wasquehal Nord Pas-de-Calais",
    "addr:housenumber":"14",
    "addr:postcode":"59290",
    "addr:street":"Rue De Marcq-En-Baroeul",
    "iso:country":"FR",
    "sg:address":"14, Rue de Marcq-en-Baroeul, 59290 Wasquehal",
    "sg:orig_category":"Unclassifiable Establishments",
    "sg:phone":"+33 3 20 89 11 84",
    "sg:province":"Nord Pas-de-Calais",
    "wof:name":"Sapro S.a.",
    "wof:placetype":"venue"
},
  "geometry": {"coordinates":[3.122716,50.670513],"type":"Point"}
}