{
  "type": "Feature",
  "properties": {
    "addr:full":"La Boursidi\u00e8re Pr\u00e9-Normandie 92357 Le Plessis Robinson Centre",
    "addr:postcode":"92357",
    "addr:street":"Pre\u0301-Normandie;Plessis Robinson",
    "iso:country":"FR",
    "sg:address":"La Boursidi\u00e8re Pr\u00e9-Normandie 92357 Le Plessis Robinson",
    "sg:classifiers":[
        {
            "category":"Professional",
            "subcategory":"Engineering",
            "type":"Services"
        }
    ],
    "sg:phone":"+33 1 46 01 32 32",
    "sg:province":"Centre",
    "sg:tags":[
        "machine",
        "-",
        "mechanical"
    ],
    "wof:name":"Porges Sa",
    "wof:placetype":"venue"
},
  "geometry": {"coordinates":[2.259315,48.779976],"type":"Point"}
}