{
  "type": "Feature",
  "properties": {
    "addr:full":"6 Avenue Louis Martin 35400 St Malo Saint-Malo Bretagne 35400",
    "addr:housenumber":"6",
    "addr:postcode":"35400;35400",
    "addr:street":"Avenue Louis Martin;Saint-Malo Bretagne",
    "iso:country":"FR",
    "sg:address":"6 Avenue Louis Martin 35400 St Malo",
    "sg:city":"Saint-Malo",
    "sg:classifiers":[
        {
            "category":"Autos & Motor Vehicles",
            "subcategory":"Boat Sales",
            "type":"Retail Goods"
        }
    ],
    "sg:phone":"+33 2 99 20 37 77",
    "sg:postcode":"35400",
    "sg:province":"Bretagne",
    "sg:tags":[
        "equipment",
        "transport"
    ],
    "wof:name":"Chantier Naval Etoile Marine",
    "wof:placetype":"venue"
},
  "geometry": {"coordinates":[-2.010164,48.647804],"type":"Point"}
}