{
  "type": "Feature",
  "properties": {
    "iso:country":"FR",
    "sg:address":"29, Rue du Calvaire - Lieu dit Le Cailloit , 59132 Glageon",
    "sg:orig_category":"Non-Classified Establishments",
    "sg:phone":"+33 3 27 56 15 15",
    "sg:province":"Nord Pas-de-Calais",
    "wof:name":"Groupement Des Carri\u00e8res De L'avesnois S.a.r.l.",
    "wof:placetype":"venue"
},
  "geometry": {"coordinates":[4.10237,50.05798],"type":"Point"}
}