{
  "type": "Feature",
  "properties": {
    "iso:country":"FR",
    "sg:address":"B.P. 39",
    "sg:city":"Saint Florent sur Cher",
    "sg:orig_category":"Non-Classified Establishments",
    "sg:phone":"+33 2 48 55 11 06",
    "sg:postcode":"18400",
    "sg:province":"Centre",
    "wof:name":"Entreprise Lecomte S.a.",
    "wof:placetype":"venue"
},
  "geometry": {"coordinates":[2.244945,46.992325],"type":"Point"}
}