{
  "type": "Feature",
  "properties": {
    "addr:full":"16, Rue Pierre Brossolette - Wall Street Building, 76052 Le Havre C\u00e9dex Centre",
    "addr:housenumber":"16",
    "addr:postcode":"76052",
    "addr:street":"Rue Pierre Brossolette Wall",
    "iso:country":"FR",
    "sg:address":"16, Rue Pierre Brossolette - Wall Street Building, 76052 Le Havre C\u00e9dex",
    "sg:orig_category":"Non-Classified Establishments",
    "sg:phone":"+33 2 32 74 93 80",
    "sg:province":"Centre",
    "wof:name":"K\u00fcnhe & Nagel S.a.",
    "wof:placetype":"venue"
},
  "geometry": {"coordinates":[0.13231,49.498619],"type":"Point"}
}