{
  "type": "Feature",
  "properties": {
    "iso:country":"FR",
    "sg:address":"B.P. 94, 74311 Cluses^^177, Av. des M\u00e9l\u00e8zes, 74300 Thyez",
    "sg:orig_category":"Non-Classified Establishments",
    "sg:phone":"+33 4 50 98 96 71",
    "sg:postcode":"74300",
    "sg:province":"Rhone-Alpes",
    "wof:name":"H.f. S\u00e9curit\u00e9 S.a.",
    "wof:placetype":"venue"
},
  "geometry": {"coordinates":[6.633185,45.987919],"type":"Point"}
}