{
  "type": "Feature",
  "properties": {
    "addr:full":"B.P. 4, 66502 Prades^^Bd de la Gare, 66500 Prades Languedoc-Roussillon",
    "addr:housenumber":"4",
    "addr:postcode":"66502;66500",
    "addr:street":"B.P.;La Gare",
    "iso:country":"FR",
    "sg:address":"B.P. 4, 66502 Prades^^Bd de la Gare, 66500 Prades",
    "sg:orig_category":"Non-Classified Establishments",
    "sg:phone":"+33 4 68 96 49 47",
    "sg:province":"Languedoc-Roussillon",
    "wof:name":"Po Instrumentation S.a.",
    "wof:placetype":"venue"
},
  "geometry": {"coordinates":[2.418326,42.615593],"type":"Point"}
}