{
  "type": "Feature",
  "properties": {
    "iso:country":"FR",
    "sg:address":"23 R Dom Vaissette 34000 Montpellier",
    "sg:classifiers":[
        {
            "category":"Professional",
            "subcategory":"Business Services",
            "type":"Services"
        }
    ],
    "sg:phone":"+33 4 67 92 19 91",
    "sg:postcode":"34000",
    "sg:province":"Languedoc-Roussillon",
    "sg:tags":[
        "training",
        "advice"
    ],
    "wof:name":"Alis\u00c9",
    "wof:placetype":"venue"
},
  "geometry": {"coordinates":[3.872947,43.604912],"type":"Point"}
}