{
  "type": "Feature",
  "properties": {
    "iso:country":"FR",
    "sg:address":"7, Rue Francis Combe, 95000 Cergy",
    "sg:orig_category":"Unclassifiable Establishments",
    "sg:phone":"+33 1 34 20 14 00",
    "sg:province":"Ile de France",
    "wof:name":"S.p.s. S.a. - Soci\u00e9t\u00e9 De Prestations De Service",
    "wof:placetype":"venue"
},
  "geometry": {"coordinates":[2.071591,49.044369],"type":"Point"}
}