{
  "type": "Feature",
  "properties": {
    "addr:full":"Manfle 16230 St Groux Poitou-Charentes 16230",
    "addr:postcode":"16230;16230",
    "addr:street":"Manfle;Groux",
    "iso:country":"FR",
    "sg:address":"Manfle 16230 St Groux",
    "sg:classifiers":[
        {
            "category":"Utilities",
            "subcategory":"Electric",
            "type":"Services"
        }
    ],
    "sg:phone":"+33 5 45 38 56 56",
    "sg:postcode":"16230",
    "sg:province":"Poitou-Charentes",
    "sg:tags":[
        "electricity",
        "electronic",
        "electrical",
        "equipment"
    ],
    "wof:name":"Moteurs Leroy Somer",
    "wof:placetype":"venue"
},
  "geometry": {"coordinates":[0.31836,45.833389],"type":"Point"}
}