{
  "type": "Feature",
  "properties": {
    "addr:full":"7 Rue Des Biches 74112 Ville La Grande Vill\u00e9 Alsace 67220",
    "addr:housenumber":"7",
    "addr:postcode":"74112;67220",
    "addr:street":"Rue Des Biches;Grande",
    "iso:country":"FR",
    "sg:address":"7 Rue Des Biches 74112 Ville La Grande",
    "sg:city":"Vill\u00e9",
    "sg:classifiers":[
        {
            "category":"Manufacturing",
            "subcategory":"Metals",
            "type":"Manufacturing & Wholesale Goods"
        }
    ],
    "sg:phone":"+33 4 50 84 11 22",
    "sg:postcode":"67220",
    "sg:province":"Alsace",
    "sg:tags":[
        "metallurgy",
        "metalworking"
    ],
    "wof:name":"Tuthill Coupleurs Gromele",
    "wof:placetype":"venue"
},
  "geometry": {"coordinates":[-118.09594,45.329544],"type":"Point"}
}