{
  "type": "Feature",
  "properties": {
    "iso:country":"FR",
    "sg:address":"1 R Des Seigneurs 68960 Willer",
    "sg:city":"Willer",
    "sg:classifiers":[
        {
            "category":"Shopping",
            "subcategory":"Hobbies, Toys, & Games",
            "type":"Retail Goods"
        }
    ],
    "sg:phone":"+33 3 89 07 85 92",
    "sg:postcode":"68960",
    "sg:province":"Alsace",
    "sg:tags":[
        "product",
        "miscellaneous",
        "entertainment"
    ],
    "wof:name":"Manufacture D'orgues Guerriers Sarl",
    "wof:placetype":"venue"
},
  "geometry": {"coordinates":[7.323355,47.584148],"type":"Point"}
}