{
  "type": "Feature",
  "properties": {
    "iso:country":"FR",
    "sg:address":"Parc Industriel De Furst 57730 Folschviller",
    "sg:classifiers":[
        {
            "category":"Building & Trades",
            "subcategory":"Landscaping Services",
            "type":"Services"
        }
    ],
    "sg:phone":"+33 3 87 92 46 17",
    "sg:postcode":"57730",
    "sg:province":"Lorraine",
    "sg:tags":[
        "business",
        "advice",
        "processing",
        "metal",
        "metallurgy",
        "metalworking"
    ],
    "wof:name":"Soudure Montage Entretien Sme",
    "wof:placetype":"venue"
},
  "geometry": {"coordinates":[6.68588,49.07077],"type":"Point"}
}