{
  "type": "Feature",
  "properties": {
    "addr:full":"74550 Perrignier Rhone-Alpes 74550",
    "addr:postcode":"74550;74550",
    "addr:street":"Rhone-Alpes",
    "iso:country":"FR",
    "sg:address":"74550 Perrignier",
    "sg:classifiers":[
        {
            "category":"Food & Beverages",
            "subcategory":"Groceries & Convenience Stores",
            "type":"Retail Goods"
        }
    ],
    "sg:phone":"+33 4 50 72 40 06",
    "sg:postcode":"74550",
    "sg:province":"Rhone-Alpes",
    "sg:tags":[
        "product",
        "grain",
        "cereal",
        "related"
    ],
    "wof:name":"Minoterie J Jeandin Et Fils",
    "wof:placetype":"venue"
},
  "geometry": {"coordinates":[6.442996,46.30439],"type":"Point"}
}