{
  "type": "Feature",
  "properties": {
    "iso:country":"FR",
    "sg:address":"2",
    "sg:city":"Nantes; Savenay",
    "sg:classifiers":[
        {
            "category":"Banks & Credit Unions",
            "subcategory":"Bank",
            "type":"Services"
        }
    ],
    "sg:phone":"+33 3340569140",
    "sg:province":"Basse Normandie",
    "wof:name":"Banque Cio",
    "wof:placetype":"venue"
},
  "geometry": {"coordinates":[-1.942882,47.360046],"type":"Point"}
}