{
  "type": "Feature",
  "properties": {
    "addr:full":"48, Av. de la R\u00e9publique, 78500 Sartrouville Ile de France",
    "addr:postcode":"78500;ile",
    "addr:street":"48 Av. De La Re\u0301Publique",
    "iso:country":"FR",
    "sg:address":"48, Av. de la R\u00e9publique, 78500 Sartrouville",
    "sg:orig_category":"Non-Classified Establishments",
    "sg:phone":"+33 1 30 90 11 74",
    "sg:province":"Ile de France",
    "wof:name":"Kepler S.a.r.l.",
    "wof:placetype":"venue"
},
  "geometry": {"coordinates":[2.154716,48.936485],"type":"Point"}
}