{
  "type": "Feature",
  "properties": {
    "iso:country":"FR",
    "sg:address":"185, Rue des Artisans, 01310 Buellas",
    "sg:orig_category":"Unclassifiable Establishments",
    "sg:phone":"+33 4 74 24 29 29",
    "sg:province":"Rhone-Alpes",
    "wof:name":"Bourg Offset S.a.",
    "wof:placetype":"venue"
},
  "geometry": {"coordinates":[5.150777,46.195042],"type":"Point"}
}