{
  "type": "Feature",
  "properties": {
    "addr:full":"Rte de Ch\u00e2lons-en-Champagne Montmirail Champagne 51210",
    "addr:postcode":"51210",
    "addr:street":"Rte De Cha\u0302Lons-En-Champagne",
    "iso:country":"FR",
    "sg:address":"Rte de Ch\u00e2lons-en-Champagne",
    "sg:city":"Montmirail",
    "sg:orig_category":"Non-Classified Establishments",
    "sg:phone":"+33 3 26 81 70 00",
    "sg:postcode":"51210",
    "sg:province":"Champagne",
    "wof:name":"Axon C\u00e2ble S.a.",
    "wof:placetype":"venue"
},
  "geometry": {"coordinates":[3.50046,48.78986],"type":"Point"}
}