{
  "type": "Feature",
  "properties": {
    "iso:country":"FR",
    "sg:address":"4 avenue Morane Saulnier 78140 VELIZY VILLACOUBLAY",
    "sg:classifiers":[
        {
            "category":"Manufacturing",
            "subcategory":"Motor Vehicles & Parts",
            "type":"Manufacturing & Wholesale Goods"
        }
    ],
    "sg:phone":"+33 1 34 58 03 03",
    "sg:postcode":"78140",
    "sg:province":"Ile de France",
    "sg:tags":[
        "heavy",
        "screw",
        "bolt"
    ],
    "wof:name":"Nedschroef Sa",
    "wof:placetype":"venue"
},
  "geometry": {"coordinates":[2.209564,48.781105],"type":"Point"}
}