{
  "type": "Feature",
  "properties": {
    "addr:full":"Parc d'Activit\u00e9s Nord n\u00b02 Tresses Aquitaine 33370",
    "addr:postcode":"33370",
    "iso:country":"FR",
    "sg:address":"Parc d'Activit\u00e9s Nord n\u00b02",
    "sg:city":"Tresses",
    "sg:orig_category":"Unclassifiable Establishments",
    "sg:phone":"+33 5 56 68 35 62",
    "sg:postcode":"33370",
    "sg:province":"Aquitaine",
    "wof:name":"S.e.v.a.c.r.e.m. S.a. - Soci\u00e9t\u00e9 D'etude Et De Valorisation De La Cr\u00e8merie",
    "wof:placetype":"venue"
},
  "geometry": {"coordinates":[-0.46358,44.84832],"type":"Point"}
}