{
  "type": "Feature",
  "properties": {
    "addr:full":"B.P. 7164, 95056 Saint Ouen l' Aum\u00f4ne C\u00e9dex^^6, Rue de la Treatte, 95310 Saint Ouen l' Aum\u00f4ne Ile de France",
    "addr:postcode":"95056;95310",
    "addr:street":"B.P. 7164;Ouen L ' Aumo\u0302Ne;Rue De La Treatte;Ouen L ' Aumo\u0302Ne Ile De France",
    "iso:country":"FR",
    "sg:address":"B.P. 7164, 95056 Saint Ouen l' Aum\u00f4ne C\u00e9dex^^6, Rue de la Treatte, 95310 Saint Ouen l' Aum\u00f4ne",
    "sg:orig_category":"Non-Classified Establishments",
    "sg:phone":"+33 1 30 37 73 74",
    "sg:province":"Ile de France",
    "wof:name":"Mecaloc T.p. S.a.",
    "wof:placetype":"venue"
},
  "geometry": {"coordinates":[5.098155,43.781731],"type":"Point"}
}