{
  "type": "Feature",
  "properties": {
    "iso:country":"FR",
    "sg:address":"8 rue Rameau 78000 Versailles",
    "sg:classifiers":[
        {
            "category":"Communications",
            "type":"Services"
        }
    ],
    "sg:phone":"+33 1 39 24 88 55",
    "sg:province":"Ile de France",
    "sg:tags":[
        "translation"
    ],
    "wof:name":"Cg Traduction Et Interpr\u00e9tation",
    "wof:placetype":"venue"
},
  "geometry": {"coordinates":[2.130883,48.807636],"type":"Point"}
}