{
  "type": "Feature",
  "properties": {
    "iso:country":"FR",
    "sg:address":"2 Aeroport Charles de Gaulle 93290 Tremblay en France",
    "sg:classifiers":[
        {
            "category":"Airport",
            "type":"Transportation"
        }
    ],
    "sg:phone":"+33 1 48 62 81 75",
    "sg:postcode":"93290",
    "sg:province":"Ile de France",
    "sg:tags":[
        "air-freight",
        "forwarders"
    ],
    "wof:name":"Aviapartner Cargo Sas",
    "wof:placetype":"venue"
},
  "geometry": {"coordinates":[2.56727,48.951214],"type":"Point"}
}