{
  "type": "Feature",
  "properties": {
    "addr:full":"12 Av Jean Bart 78960 Voisin Le Bretonneux Ile de France 78960",
    "addr:postcode":"78960;78960",
    "addr:street":"12 Av Jean Bart;Voisin Le Bretonneux Ile De France",
    "iso:country":"FR",
    "sg:address":"12 Av Jean Bart 78960 Voisin Le Bretonneux",
    "sg:classifiers":[
        {
            "category":"Health Services",
            "subcategory":"Optometrist",
            "type":"Services"
        }
    ],
    "sg:phone":"+33 1 30 12 06 80",
    "sg:postcode":"78960",
    "sg:province":"Ile de France",
    "sg:tags":[
        "instrument",
        "optical",
        "-",
        "precision",
        "equipment"
    ],
    "wof:name":"Melles Griot Industrie",
    "wof:placetype":"venue"
},
  "geometry": {"coordinates":[-96.91423,30.05592],"type":"Point"}
}