{
  "type": "Feature",
  "properties": {
    "iso:country":"FR",
    "sg:address":"19, Av. de Norv\u00e8ge - Les Fjords , 91940 Les Ulis",
    "sg:orig_category":"Non-Classified Establishments",
    "sg:phone":"+33 1 69 29 81 20",
    "sg:province":"Ile de France",
    "wof:name":"Lambert Alcyon S.a.",
    "wof:placetype":"venue"
},
  "geometry": {"coordinates":[2.169475,48.68161],"type":"Point"}
}