{
  "type": "Feature",
  "properties": {
    "addr:full":"14bis, Rue de Verdun, 52290 Eclaron Braucourt Sainte Livi\u00e8re Champagne",
    "addr:housenumber":"14bis",
    "addr:postcode":"52290",
    "addr:street":"Rue De Verdun",
    "iso:country":"FR",
    "sg:address":"14bis, Rue de Verdun, 52290 Eclaron Braucourt Sainte Livi\u00e8re",
    "sg:orig_category":"Unclassifiable Establishments",
    "sg:phone":"+33 3 25 04 16 68",
    "sg:province":"Champagne",
    "wof:name":"Orparc Paysagiste S.a.r.l.",
    "wof:placetype":"venue"
},
  "geometry": {"coordinates":[4.873882,48.598171],"type":"Point"}
}