{
  "type": "Feature",
  "properties": {
    "addr:full":"Av. de Versailles Rungis C\u00e9dex Corse 94664",
    "addr:postcode":"94664",
    "addr:street":"Av. De Versailles",
    "iso:country":"FR",
    "sg:address":"Av. de Versailles",
    "sg:city":"Rungis C\u00e9dex",
    "sg:orig_category":"Non-Classified Establishments",
    "sg:phone":"+33 1 41 80 30 80",
    "sg:postcode":"94664",
    "sg:province":"Corse",
    "wof:name":"Danone France",
    "wof:placetype":"venue"
},
  "geometry": {"coordinates":[2.35294,48.754734],"type":"Point"}
}