{
  "type": "Feature",
  "properties": {
    "addr:full":"16, Rue Ir\u00e8ne Joliot Curie - Parc Industriel des Ruires, 38320 Eybens Rhone-Alpes 38320",
    "addr:housenumber":"16",
    "addr:postcode":"38320;38320",
    "addr:street":"Rue Ire\u0300Ne Joliot Curie;Ruires",
    "iso:country":"FR",
    "sg:address":"16, Rue Ir\u00e8ne Joliot Curie - Parc Industriel des Ruires, 38320 Eybens",
    "sg:orig_category":"Unclassifiable Establishments",
    "sg:phone":"+33 4 76 62 00 02",
    "sg:postcode":"38320",
    "sg:province":"Rhone-Alpes",
    "wof:name":"E.q.m. S.a.r.l. - European Quality Management",
    "wof:placetype":"venue"
},
  "geometry": {"coordinates":[5.736241,45.149448],"type":"Point"}
}