{
  "type": "Feature",
  "properties": {
    "addr:full":"22, Quai Gallieni SURESNES Cedex 92158 ",
    "addr:housenumber":"22",
    "addr:postcode":"92158",
    "addr:street":"Quai Gallieni",
    "iso:country":"FR",
    "sg:address":"22, Quai Gallieni",
    "sg:city":"SURESNES Cedex",
    "sg:classifiers":[
        {
            "category":"Professional",
            "subcategory":"Computer Services",
            "type":"Services"
        }
    ],
    "sg:postcode":"92158 ",
    "sg:website":"http://www.verio.com",
    "wof:name":"Verio",
    "wof:placetype":"venue"
},
  "geometry": {"coordinates":[2.23063,48.869458],"type":"Point"}
}