{
  "type": "Feature",
  "properties": {
    "iso:country":"FR",
    "sg:address":"Parc de Montigny",
    "sg:city":"Maxilly sur L\u00e9man",
    "sg:orig_category":"Non-Classified Establishments",
    "sg:phone":"+33 4 50 70 74 74",
    "sg:postcode":"74500",
    "sg:province":"Rhone-Alpes",
    "wof:name":"Actini S.a.",
    "wof:placetype":"venue"
},
  "geometry": {"coordinates":[6.62509,46.393333],"type":"Point"}
}