{
  "type": "Feature",
  "properties": {
    "iso:country":"FR",
    "sg:address":"528 Route D'Etampes 91150 Bri\u00e8res Les Scell\u00e9s",
    "sg:classifiers":[
        {
            "category":"Manufacturing",
            "subcategory":"Tools & Machinery",
            "type":"Manufacturing & Wholesale Goods"
        }
    ],
    "sg:phone":"+33 1 64 94 24 54",
    "sg:postcode":"91150",
    "sg:province":"Ile de France",
    "sg:tags":[
        "metallurgy",
        "metalworking"
    ],
    "wof:name":"Larrue Sa",
    "wof:placetype":"venue"
},
  "geometry": {"coordinates":[2.13848,48.457619],"type":"Point"}
}