{
  "type": "Feature",
  "properties": {
    "iso:country":"FR",
    "sg:address":"2 Rue De Lattre De Tassigny 25390 Orchamps Vennes",
    "sg:classifiers":[
        {
            "category":"Food & Beverages",
            "subcategory":"Meat & Fish",
            "type":"Retail Goods"
        }
    ],
    "sg:phone":"+33 3 81 67 68 69",
    "sg:postcode":"25390",
    "sg:province":"Franche Comt\u00e9",
    "sg:tags":[
        "preserve",
        "cooked",
        "product",
        "related"
    ],
    "wof:name":"Maison Noel Myotte",
    "wof:placetype":"venue"
},
  "geometry": {"coordinates":[6.525345,47.130424],"type":"Point"}
}