{
  "type": "Feature",
  "properties": {
    "addr:full":"Rue des Champs Pacaud Nevers Bourgogne 58000",
    "addr:postcode":"58000",
    "addr:street":"Rue Des Champs Pacaud;Bourgogne",
    "iso:country":"FR",
    "sg:address":"Rue des Champs Pacaud",
    "sg:city":"Nevers",
    "sg:orig_category":"Unclassifiable Establishments",
    "sg:phone":"+33 3 86 21 65 00",
    "sg:postcode":"58000",
    "sg:province":"Bourgogne",
    "wof:name":"Philips France - Division Philips Eclairage",
    "wof:placetype":"venue"
},
  "geometry": {"coordinates":[3.188545,46.994473],"type":"Point"}
}