{
  "type": "Feature",
  "properties": {
    "addr:full":"Rte de Valr\u00e9as Taulignan Rhone-Alpes 26770",
    "addr:postcode":"26770",
    "addr:street":"Rte De Valre\u0301As;Rhone-Alpes",
    "iso:country":"FR",
    "sg:address":"Rte de Valr\u00e9as",
    "sg:city":"Taulignan",
    "sg:orig_category":"Non-Classified Establishments",
    "sg:phone":"+33 4 75 53 61 39",
    "sg:postcode":"26770",
    "sg:province":"Rhone-Alpes",
    "wof:name":"Pascal Mat\u00e9riaux Et Occasions S.a.r.l.",
    "wof:placetype":"venue"
},
  "geometry": {"coordinates":[5.043869,44.39809],"type":"Point"}
}