{
  "type": "Feature",
  "properties": {
    "addr:full":"La Pontchonniere Zone Industrielle 69210 Savigny Rhone-Alpes",
    "addr:postcode":"69210",
    "addr:street":"Zone Industrielle",
    "iso:country":"FR",
    "sg:address":"La Pontchonniere Zone Industrielle 69210 Savigny",
    "sg:classifiers":[
        {
            "category":"Manufacturing",
            "subcategory":"Rubber & Plastics",
            "type":"Manufacturing & Wholesale Goods"
        }
    ],
    "sg:phone":"+33 4 74 01 33 02",
    "sg:province":"Rhone-Alpes",
    "sg:tags":[
        "packaging",
        "material",
        "-"
    ],
    "wof:name":"Polidou",
    "wof:placetype":"venue"
},
  "geometry": {"coordinates":[4.606841,45.7701],"type":"Point"}
}