{
  "type": "Feature",
  "properties": {
    "addr:full":"B.P. 60, 74301 Cluses C\u00e9dex^^47, All\u00e9e du Mont Blanc, 74300 Cluses Rhone-Alpes 74300",
    "addr:postcode":"74301;74300;74300",
    "addr:street":"B.P. 60;Alle\u0301E Du Mont Blanc",
    "iso:country":"FR",
    "sg:address":"B.P. 60, 74301 Cluses C\u00e9dex^^47, All\u00e9e du Mont Blanc, 74300 Cluses",
    "sg:orig_category":"Non-Classified Establishments",
    "sg:phone":"+33 4 50 89 25 70",
    "sg:postcode":"74300",
    "sg:province":"Rhone-Alpes",
    "wof:name":"T.2.s. S.a. - Traitement De Surfaces",
    "wof:placetype":"venue"
},
  "geometry": {"coordinates":[6.633185,45.987919],"type":"Point"}
}