{
  "type": "Feature",
  "properties": {
    "addr:full":"71 Avenue Jean Mermoz 69008 Lyon Rhone-Alpes 69008",
    "addr:housenumber":"71",
    "addr:postcode":"69008;69008",
    "addr:street":"Avenue Jean Mermoz",
    "iso:country":"FR",
    "sg:address":"71 Avenue Jean Mermoz 69008 Lyon",
    "sg:classifiers":[
        {
            "category":"Manufacturing",
            "subcategory":"Rubber & Plastics",
            "type":"Manufacturing & Wholesale Goods"
        }
    ],
    "sg:phone":"+33 4 78 78 82 82",
    "sg:postcode":"69008",
    "sg:province":"Rhone-Alpes",
    "wof:name":"Metifiot Sa",
    "wof:placetype":"venue"
},
  "geometry": {"coordinates":[4.87761,45.733749],"type":"Point"}
}