{
  "type": "Feature",
  "properties": {
    "iso:country":"FR",
    "sg:address":"68, Rue de la R\u00e9publique, 69002 Lyon",
    "sg:orig_category":"Unclassifiable Establishments",
    "sg:phone":"+33 4 72 41 17 25",
    "sg:postcode":"69002",
    "sg:province":"Rhone-Alpes",
    "wof:name":"O.f.i.c.e. Organisation S.a.",
    "wof:placetype":"venue"
},
  "geometry": {"coordinates":[4.834206,45.758228],"type":"Point"}
}