{
  "type": "Feature",
  "properties": {
    "iso:country":"FR",
    "sg:address":"Le Bourg 71800 Baudemont",
    "sg:city":"Baudemont",
    "sg:orig_category":"Unclassifiable Establishments",
    "sg:phone":"+33 3 85 28 29 57",
    "sg:postcode":"71800",
    "sg:province":"Bourgogne",
    "wof:name":"Etudes Constructions Bonnetain Maringue S.a.r.l.",
    "wof:placetype":"venue"
},
  "geometry": {"coordinates":[4.279969,46.302181],"type":"Point"}
}