{
  "type": "Feature",
  "properties": {
    "addr:full":"27/29, Rue de l'Union, 78600 Maisons Laffitte Ile de France 78600",
    "addr:housenumber":"27 / 29",
    "addr:postcode":"78600 maisons laffitte ile;france 78600",
    "addr:street":"Rue De L'Union",
    "iso:country":"FR",
    "sg:address":"27/29, Rue de l'Union, 78600 Maisons Laffitte",
    "sg:orig_category":"Non-Classified Establishments",
    "sg:phone":"+33 1 39 62 57 21",
    "sg:postcode":"78600",
    "sg:province":"Ile de France",
    "wof:name":"A.p.f. S.a.r.l. - Atelier Polissage Fa\u00e7onnage",
    "wof:placetype":"venue"
},
  "geometry": {"coordinates":[2.136181,48.948914],"type":"Point"}
}