{
  "type": "Feature",
  "properties": {
    "iso:country":"FR",
    "sg:address":"B.P. 16",
    "sg:city":"Saint Rambert d'Albon^^Mallegarde 26210 Saint Sorlin en Valloire",
    "sg:orig_category":"Non-Classified Establishments",
    "sg:phone":"+33 4 75 31 74 05",
    "sg:postcode":"26140",
    "sg:province":"Rhone-Alpes",
    "wof:name":"Cheddite France S.a.",
    "wof:placetype":"venue"
},
  "geometry": {"coordinates":[4.935108,45.268082],"type":"Point"}
}