{
  "type": "Feature",
  "properties": {
    "iso:country":"FR",
    "sg:address":"3, Bd de l'Europe - Tour de l'Europe, 68100 Mulhouse",
    "sg:city":"Mulhouse",
    "sg:orig_category":"Unclassifiable Establishments",
    "sg:phone":"+33 3 89 56 02 62",
    "sg:postcode":"68100",
    "sg:province":"Alsace",
    "wof:name":"Le Comptoir Du Temps S.a.r.l.",
    "wof:placetype":"venue"
},
  "geometry": {"coordinates":[7.349008,47.746971],"type":"Point"}
}