{
  "type": "Feature",
  "properties": {
    "addr:full":"B.P. 349000, 13799 Aix en Provence C\u00e9dex 3^^770, Av. Guillibert de la Lauzi\u00e8re, 13700 Aix en Provenc Pays de Loire",
    "addr:housenumber":"349000;3 ^ ^ 770",
    "addr:postcode":"13799;13700",
    "addr:street":"Ce\u0301Dex;Av. Guillibert De La Lauzie\u0300Re;Provenc",
    "iso:country":"FR",
    "sg:address":"B.P. 349000, 13799 Aix en Provence C\u00e9dex 3^^770, Av. Guillibert de la Lauzi\u00e8re, 13700 Aix en Provenc",
    "sg:orig_category":"Non-Classified Establishments",
    "sg:phone":"+33 4 42 16 61 00",
    "sg:province":"Pays de Loire",
    "wof:name":"Polysius S.a.",
    "wof:placetype":"venue"
},
  "geometry": {"coordinates":[5.21421,43.418041],"type":"Point"}
}