{
  "type": "Feature",
  "properties": {
    "addr:full":"91, Av. de Colmar, 67100 Strasbourg Strasbourg Alsace 67100",
    "addr:postcode":"67100;67100",
    "addr:street":"91 Av. De Colmar",
    "iso:country":"FR",
    "sg:address":"91, Av. de Colmar, 67100 Strasbourg",
    "sg:city":"Strasbourg",
    "sg:orig_category":"Non-Classified Establishments",
    "sg:phone":"+33 3 88 84 58 80",
    "sg:postcode":"67100",
    "sg:province":"Alsace",
    "wof:name":"Hirstel Jacques G\u00e9rard",
    "wof:placetype":"venue"
},
  "geometry": {"coordinates":[7.752036,48.568256],"type":"Point"}
}