{
  "type": "Feature",
  "properties": {
    "addr:full":"7, Rue du Paquis, 54115 Aboncourt Lorraine",
    "addr:housenumber":"7",
    "addr:postcode":"54115",
    "addr:street":"Rue Du Paquis",
    "iso:country":"FR",
    "sg:address":"7, Rue du Paquis, 54115 Aboncourt",
    "sg:orig_category":"Non-Classified Establishments",
    "sg:phone":"+33 3 83 52 31 40",
    "sg:province":"Lorraine",
    "wof:name":"S.l.t.p. S.a.r.l. - Soci\u00e9t\u00e9 De Location De Travaux Publics",
    "wof:placetype":"venue"
},
  "geometry": {"coordinates":[5.969197,48.356331],"type":"Point"}
}