{
  "type": "Feature",
  "properties": {
    "addr:full":"B.P. 25, 38530 Pontcharra^^131, Rue du Bac, 38530 Pontcharra Rhone-Alpes 38530",
    "addr:postcode":"38530;38530;38530",
    "addr:street":"B.P. 25;Rue Du Bac;Rhone-Alpes",
    "iso:country":"FR",
    "sg:address":"B.P. 25, 38530 Pontcharra^^131, Rue du Bac, 38530 Pontcharra",
    "sg:orig_category":"Non-Classified Establishments",
    "sg:phone":"+33 4 76 97 65 44",
    "sg:postcode":"38530",
    "sg:province":"Rhone-Alpes",
    "wof:name":"Etablissements Girod Henri S.a.",
    "wof:placetype":"venue"
},
  "geometry": {"coordinates":[6.024777,45.431976],"type":"Point"}
}