{
  "type": "Feature",
  "properties": {
    "addr:full":"17 Rue De L'Abron 03400 St Edmond Toulon-sur-Allier Auvergne 03400",
    "addr:housenumber":"17",
    "addr:postcode":"03400;03400",
    "addr:street":"Rue De L'Abron",
    "iso:country":"FR",
    "sg:address":"17 Rue De L'Abron 03400 St Edmond",
    "sg:city":"Toulon-sur-Allier",
    "sg:classifiers":[
        {
            "category":"Professional",
            "subcategory":"Engineering",
            "type":"Services"
        }
    ],
    "sg:phone":"+33 4 70 43 82 19",
    "sg:postcode":"03400",
    "sg:province":"Auvergne",
    "sg:tags":[
        "machine",
        "-",
        "mechanical"
    ],
    "wof:name":"Imb",
    "wof:placetype":"venue"
},
  "geometry": {"coordinates":[-99.821831,39.625801],"type":"Point"}
}