{
  "type": "Feature",
  "properties": {
    "iso:country":"FR",
    "sg:address":"Rte Nationale",
    "sg:city":"Villeneuve de Berg",
    "sg:orig_category":"Unclassifiable Establishments",
    "sg:phone":"+33 4 75 94 80 30",
    "sg:postcode":"07170",
    "sg:province":"Rhone-Alpes",
    "wof:name":"C.s.a. S.a.r.l. - Compagnie Des Sacs Et Accessoires",
    "wof:placetype":"venue"
},
  "geometry": {"coordinates":[4.50118,44.557049],"type":"Point"}
}