{
  "type": "Feature",
  "properties": {
    "addr:full":"387, Rue Vaugirard, 75015 Paris Ile de France",
    "addr:housenumber":"387",
    "addr:postcode":"75015",
    "addr:street":"Rue Vaugirard",
    "iso:country":"FR",
    "sg:address":"387, Rue Vaugirard, 75015 Paris",
    "sg:orig_category":"Unclassifiable Establishments",
    "sg:phone":"+33 1 53 68 08 88",
    "sg:province":"Ile de France",
    "wof:name":"Vaysse S.a.",
    "wof:placetype":"venue"
},
  "geometry": {"coordinates":[2.292675,48.835346],"type":"Point"}
}