{
  "type": "Feature",
  "properties": {
    "iso:country":"FR",
    "sg:address":"54 Rue Pigalle 75009 Paris",
    "sg:classifiers":[
        {
            "category":"Manufacturing",
            "subcategory":"Wood Products",
            "type":"Manufacturing & Wholesale Goods"
        }
    ],
    "sg:phone":"+33 1 42 85 39 00",
    "sg:province":"Ile de France",
    "sg:tags":[
        "professional",
        "furniture"
    ],
    "wof:name":"Fort Comptoirs",
    "wof:placetype":"venue"
},
  "geometry": {"coordinates":[2.340605,48.87368],"type":"Point"}
}