{
  "type": "Feature",
  "properties": {
    "iso:country":"FR",
    "sg:address":"559, Rte de Bandole, 83270 Saint Cyr sur Mer",
    "sg:orig_category":"Non-Classified Establishments",
    "sg:phone":"+33 4 94 29 39 39",
    "sg:province":"Provence-Alpes-C\u00f4te d'Azur",
    "wof:name":"Golf De Fr\u00e9gate S.n.c.",
    "wof:placetype":"venue"
},
  "geometry": {"coordinates":[5.71089,43.180401],"type":"Point"}
}