{
  "type": "Feature",
  "properties": {
    "addr:full":"7, Bd Eiffel, 21600 Longvic Longvic Bourgogne 21600",
    "addr:housenumber":"7",
    "addr:postcode":"21600;21600",
    "addr:street":"Bd Eiffel",
    "iso:country":"FR",
    "sg:address":"7, Bd Eiffel, 21600 Longvic",
    "sg:city":"Longvic",
    "sg:orig_category":"Non-Classified Establishments",
    "sg:phone":"+33 3 80 68 05 50",
    "sg:postcode":"21600",
    "sg:province":"Bourgogne",
    "wof:name":"R.t.s.m. S.a.r.l. - R\u00e9mond Traitement De Surface Des M\u00e9taux",
    "wof:placetype":"venue"
},
  "geometry": {"coordinates":[5.054429,47.278969],"type":"Point"}
}