{
  "type": "Feature",
  "properties": {
    "addr:full":"36, Rue Guersant, 75017 Paris Ile de France 75017",
    "addr:housenumber":"36",
    "addr:postcode":"75017;75017",
    "addr:street":"Rue Guersant",
    "iso:country":"FR",
    "sg:address":"36, Rue Guersant, 75017 Paris",
    "sg:orig_category":"Non-Classified Establishments",
    "sg:phone":"+33 1 53 81 82 20",
    "sg:postcode":"75017",
    "sg:province":"Ile de France",
    "wof:name":"Ceren G.i.e.",
    "wof:placetype":"venue"
},
  "geometry": {"coordinates":[2.288767,48.882107],"type":"Point"}
}