{
  "type": "Feature",
  "properties": {
    "addr:full":"59, Av du Danemark, 37000 Tours Tours Centre 37000",
    "addr:postcode":"37000;37000",
    "addr:street":"59 Av Du Danemark",
    "iso:country":"FR",
    "sg:address":"59, Av du Danemark, 37000 Tours",
    "sg:city":"Tours",
    "sg:orig_category":"Unclassifiable Establishments",
    "sg:phone":"+33 2 47 88 31 31",
    "sg:postcode":"37000",
    "sg:province":"Centre",
    "wof:name":"Ensival Moret Kestner S.a.",
    "wof:placetype":"venue"
},
  "geometry": {"coordinates":[0.679507,47.429996],"type":"Point"}
}