{
  "type": "Feature",
  "properties": {
    "addr:full":"16/18, Cours Suchet, 69002 Lyon Rhone-Alpes 69002",
    "addr:housenumber":"16 / 18",
    "addr:postcode":"69002;69002",
    "addr:street":"Cours Suchet",
    "iso:country":"FR",
    "sg:address":"16/18, Cours Suchet, 69002 Lyon",
    "sg:orig_category":"Unclassifiable Establishments",
    "sg:phone":"+33 4 72 56 16 16",
    "sg:postcode":"69002",
    "sg:province":"Rhone-Alpes",
    "wof:name":"Groupe Oxyde S.a.r.l.",
    "wof:placetype":"venue"
},
  "geometry": {"coordinates":[4.821538,45.747677],"type":"Point"}
}