{
  "type": "Feature",
  "properties": {
    "iso:country":"FR",
    "sg:address":"13, Rue Alexandre Charpentier, 75017 Paris",
    "sg:orig_category":"Non-Classified Establishments",
    "sg:phone":"+33 1 45 72 44 21",
    "sg:postcode":"75017",
    "sg:province":"Ile de France",
    "wof:name":"Agora",
    "wof:placetype":"venue"
},
  "geometry": {"coordinates":[2.287734,48.884174],"type":"Point"}
}