{
  "type": "Feature",
  "properties": {
    "addr:full":"B.P. 39, 47800 Miramont de Guyenne C\u00e9dex^^ZI de Favard, 47800 Miramont de Guyenne Moustier Aquitaine 47800",
    "addr:postcode":"47800;47800;47800",
    "addr:street":"B.P. 39",
    "iso:country":"FR",
    "sg:address":"B.P. 39, 47800 Miramont de Guyenne C\u00e9dex^^ZI de Favard, 47800 Miramont de Guyenne",
    "sg:city":"Moustier",
    "sg:orig_category":"Non-Classified Establishments",
    "sg:phone":"+33 5 53 93 20 36",
    "sg:postcode":"47800",
    "sg:province":"Aquitaine",
    "wof:name":"Maille 2000 S.a.",
    "wof:placetype":"venue"
},
  "geometry": {"coordinates":[0.419595,44.551861],"type":"Point"}
}