{
  "type": "Feature",
  "properties": {
    "addr:full":"Jardins et Fond d'Effry 02500 Effry Picardie",
    "addr:postcode":"02500",
    "addr:street":"D'Effry",
    "iso:country":"FR",
    "sg:address":"Jardins et Fond d'Effry 02500 Effry",
    "sg:orig_category":"Non-Classified Establishments",
    "sg:phone":"+33 3 23 97 47 35",
    "sg:province":"Picardie",
    "wof:name":"Tecnitol S.a.",
    "wof:placetype":"venue"
},
  "geometry": {"coordinates":[3.98312,49.926048],"type":"Point"}
}