{
  "type": "Feature",
  "properties": {
    "iso:country":"FR",
    "sg:address":"11 Bis Rue 19 Mars 1962 59129 Avesnes Les Aubert",
    "sg:classifiers":[
        {
            "category":"Manufacturing",
            "subcategory":"Paper Products",
            "type":"Manufacturing & Wholesale Goods"
        }
    ],
    "sg:phone":"+33 3 27 37 15 42",
    "sg:province":"Nord Pas-de-Calais",
    "sg:tags":[
        "packaging",
        "material",
        "-",
        "cardboard"
    ],
    "wof:name":"Cartonnages Du Cambresis Sa",
    "wof:placetype":"venue"
},
  "geometry": {"coordinates":[3.369708,50.199219],"type":"Point"}
}