{
  "type": "Feature",
  "properties": {
    "iso:country":"FR",
    "sg:address":"1172 Route Enco De Botte 13190 Allauch",
    "sg:classifiers":[
        {
            "category":"Shopping",
            "subcategory":"Clothing, Apparel, & Fashions",
            "type":"Retail Goods"
        }
    ],
    "sg:phone":"+33 4 91 68 39 23",
    "sg:province":"Midi Pyr\u00e9n\u00e9es",
    "sg:tags":[
        "textile",
        "clothing",
        "clothes"
    ],
    "wof:name":"Sarl Barre",
    "wof:placetype":"venue"
},
  "geometry": {"coordinates":[5.47338,43.318859],"type":"Point"}
}