{
  "type": "Feature",
  "properties": {
    "addr:full":"Saint Justin Zi Montreuil Sud 62170 Ecuires Nord Pas-de-Calais 62170",
    "addr:postcode":"62170;62170",
    "addr:street":"Ecuires Nord",
    "iso:country":"FR",
    "sg:address":"Saint Justin Zi Montreuil Sud 62170 Ecuires",
    "sg:classifiers":[
        {
            "category":"Professional",
            "subcategory":"Engineering",
            "type":"Services"
        }
    ],
    "sg:phone":"+33 3 21 90 02 60",
    "sg:postcode":"62170",
    "sg:province":"Nord Pas-de-Calais",
    "sg:tags":[
        "machine",
        "-",
        "mechanical"
    ],
    "wof:name":"Ducrocq Industries",
    "wof:placetype":"venue"
},
  "geometry": {"coordinates":[1.73439,50.384281],"type":"Point"}
}