{
  "type": "Feature",
  "properties": {
    "addr:full":"372 rue Saint Honor\u00e9, 92059 Paris La D\u00e9fense, Dept 92 Midi Pyr\u00e9n\u00e9es",
    "addr:housenumber":"372;92",
    "addr:postcode":"92059",
    "addr:street":"Rue Saint Honore\u0301",
    "iso:country":"FR",
    "sg:address":"372 rue Saint Honor\u00e9, 92059 Paris La D\u00e9fense, Dept 92",
    "sg:classifiers":[
        {
            "category":"Banks & Credit Unions",
            "subcategory":"Bank",
            "type":"Services"
        }
    ],
    "sg:phone":"+33 1 55 35 86 42",
    "sg:province":"Midi Pyr\u00e9n\u00e9es",
    "wof:name":"Uap Banque",
    "wof:placetype":"venue"
},
  "geometry": {"coordinates":[2.327013,48.867336],"type":"Point"}
}