{
  "type": "Feature",
  "properties": {
    "iso:country":"FR",
    "sg:address":"Maison St Michel 56320 Priziac",
    "sg:city":"Priziac",
    "sg:classifiers":[
        {
            "category":"Professional",
            "subcategory":"Business Services",
            "type":"Services"
        }
    ],
    "sg:phone":"+33 2 97 23 93 28",
    "sg:postcode":"56320",
    "sg:province":"Bretagne",
    "sg:tags":[
        "training",
        "advice"
    ],
    "wof:name":"Orphelins Apprentis Dauteuil",
    "wof:placetype":"venue"
},
  "geometry": {"coordinates":[-3.431906,48.102428],"type":"Point"}
}