{
  "type": "Feature",
  "properties": {
    "iso:country":"FR",
    "sg:address":"52 Rue De La M\u00e9dit\u00e9rran\u00e9e",
    "sg:city":"Montpellier",
    "sg:classifiers":[
        {
            "category":"Banks & Credit Unions",
            "subcategory":"Financial Services",
            "type":"Services"
        }
    ],
    "sg:phone":"+33 4 67 20 61 02",
    "sg:postcode":"34000",
    "sg:province":"Languedoc-Roussillon",
    "sg:tags":[
        "banking",
        "finance",
        "insurance"
    ],
    "wof:name":"Assedic Languedoc Roussillon Cevennes",
    "wof:placetype":"venue"
},
  "geometry": {"coordinates":[3.87609,43.610855],"type":"Point"}
}