{
  "type": "Feature",
  "properties": {
    "addr:full":"Rue Juliot Curie Hendaye Aquitaine 64700",
    "addr:postcode":"64700",
    "addr:street":"Rue Juliot Curie",
    "iso:country":"FR",
    "sg:address":"Rue Juliot Curie",
    "sg:city":"Hendaye",
    "sg:orig_category":"Non-Classified Establishments",
    "sg:phone":"+33 5 59 20 74 85",
    "sg:postcode":"64700",
    "sg:province":"Aquitaine",
    "wof:name":"Etablissement Julia",
    "wof:placetype":"venue"
},
  "geometry": {"coordinates":[-1.782101,43.351421],"type":"Point"}
}