{
  "type": "Feature",
  "properties": {
    "iso:country":"FR",
    "sg:address":"B.P. 238, 45202 Montargis C\u00e9dex^^Rue Gustave Nourry, 45120 Ch\u00e2lette sur Loing",
    "sg:city":"Cepoy",
    "sg:orig_category":"Non-Classified Establishments",
    "sg:phone":"+33 2 38 87 50 00",
    "sg:postcode":"45120",
    "sg:province":"Centre",
    "wof:name":"Hutchinson S.n.c.",
    "wof:placetype":"venue"
},
  "geometry": {"coordinates":[2.731191,48.014793],"type":"Point"}
}