{
  "type": "Feature",
  "properties": {
    "iso:country":"FR",
    "sg:address":"Rue Denis Papin Za La Buzeniere 85500 Les Herbiers",
    "sg:classifiers":[
        {
            "category":"Manufacturing",
            "subcategory":"Metals",
            "type":"Manufacturing & Wholesale Goods"
        }
    ],
    "sg:phone":"+33 2 51 66 94 56",
    "sg:postcode":"85500",
    "sg:province":"Pays de Loire",
    "sg:tags":[
        "-",
        "machine",
        "equipment",
        "engineering",
        "machinery",
        "mechanical"
    ],
    "wof:name":"Ouest Affutage",
    "wof:placetype":"venue"
},
  "geometry": {"coordinates":[-1.019829,46.815769],"type":"Point"}
}