{
  "type": "Feature",
  "properties": {
    "iso:country":"FR",
    "sg:address":"106 Rue De S\u00e8vres",
    "sg:city":"Paris",
    "sg:classifiers":[
        {
            "category":"Banks & Credit Unions",
            "subcategory":"Financial Services",
            "type":"Services"
        }
    ],
    "sg:phone":"+33 1 47 34 54 03",
    "sg:postcode":"75015",
    "sg:province":"Ile de France",
    "sg:tags":[
        "banking",
        "finance",
        "insurance"
    ],
    "wof:name":"Fiduciar Dexpertise Comptable Pour Le Commerce Et Lndustrie",
    "wof:placetype":"venue"
},
  "geometry": {"coordinates":[2.312825,48.845791],"type":"Point"}
}