{
  "type": "Feature",
  "properties": {
    "iso:country":"FR",
    "sg:address":"B.P. 54, 51160 Ay^^2, Rue Jules Lobet, 51160 Ay",
    "sg:orig_category":"Non-Classified Establishments",
    "sg:phone":"+33 3 26 55 43 05",
    "sg:postcode":"51160",
    "sg:province":"Champagne",
    "wof:name":"Champagne Jean-pierre Husson",
    "wof:placetype":"venue"
},
  "geometry": {"coordinates":[4.010445,49.052212],"type":"Point"}
}