{
  "type": "Feature",
  "properties": {
    "addr:full":"Rue Hippolyte Lucas Zac De Mivoie 35136 St Jacques De La Lande Saint-Jacques-de-la-Lande Bretagne 35136",
    "addr:postcode":"35136;35136",
    "addr:street":"Rue Hippolyte Lucas Zac De Mivoie;St Jacques De La Lande Saint-Jacques-De-La-Lande Bretagne",
    "iso:country":"FR",
    "sg:address":"Rue Hippolyte Lucas Zac De Mivoie 35136 St Jacques De La Lande",
    "sg:city":"Saint-Jacques-de-la-Lande",
    "sg:classifiers":[
        {
            "category":"Professional",
            "subcategory":"Engineering",
            "type":"Services"
        }
    ],
    "sg:phone":"+33 2 99 31 38 78",
    "sg:postcode":"35136",
    "sg:province":"Bretagne",
    "sg:tags":[
        "machine",
        "-",
        "mechanical"
    ],
    "wof:name":"Le Fournil De Mivoie",
    "wof:placetype":"venue"
},
  "geometry": {"coordinates":[-1.701114,48.066277],"type":"Point"}
}