{
  "type": "Feature",
  "properties": {
    "iso:country":"FR",
    "sg:address":"323 R Pasteur 39220 Les Rousses",
    "sg:classifiers":[
        {
            "category":"Travel",
            "subcategory":"Hotels & Motels",
            "type":"Entertainment"
        }
    ],
    "sg:phone":"+33 3 84 60 01 45",
    "sg:postcode":"39220",
    "sg:province":"Franche Comt\u00e9",
    "sg:tags":[
        "hotels",
        "business",
        "restaurant"
    ],
    "wof:name":"Hotel Et Restaurant De France Sa",
    "wof:placetype":"venue"
},
  "geometry": {"coordinates":[6.06029,46.484249],"type":"Point"}
}