{
  "type": "Feature",
  "properties": {
    "addr:full":"11, Av. Descartes, 92350 Le Plessis Robinson Ile de France",
    "addr:postcode":"92350",
    "addr:street":"11 Av. Descartes",
    "iso:country":"FR",
    "sg:address":"11, Av. Descartes, 92350 Le Plessis Robinson",
    "sg:orig_category":"Unclassifiable Establishments",
    "sg:phone":"+33 1 46 31 50 27",
    "sg:province":"Ile de France",
    "wof:name":"Goetz S.a.",
    "wof:placetype":"venue"
},
  "geometry": {"coordinates":[2.243904,48.776974],"type":"Point"}
}