{
  "type": "Feature",
  "properties": {
    "addr:full":"29, Rue Marcel Dassault, 93140 Bondy Ile de France",
    "addr:housenumber":"29",
    "addr:postcode":"93140",
    "addr:street":"Rue Marcel Dassault",
    "iso:country":"FR",
    "sg:address":"29, Rue Marcel Dassault, 93140 Bondy",
    "sg:orig_category":"Unclassifiable Establishments",
    "sg:phone":"+33 1 48 02 23 98",
    "sg:province":"Ile de France",
    "wof:name":"Imprim Etic S.a.",
    "wof:placetype":"venue"
},
  "geometry": {"coordinates":[2.481547,48.888374],"type":"Point"}
}