{
  "type": "Feature",
  "properties": {
    "addr:full":"3, Rue de Citeaux, 75012 Paris Ile de France",
    "addr:housenumber":"3",
    "addr:postcode":"75012",
    "addr:street":"Rue De Citeaux",
    "iso:country":"FR",
    "sg:address":"3, Rue de Citeaux, 75012 Paris",
    "sg:orig_category":"Unclassifiable Establishments",
    "sg:phone":"+33 1 56 95 49 49",
    "sg:province":"Ile de France",
    "wof:name":"Asr International S.a.r.l.",
    "wof:placetype":"venue"
},
  "geometry": {"coordinates":[2.379664,48.846851],"type":"Point"}
}