{
  "type": "Feature",
  "properties": {
    "iso:country":"FR",
    "sg:address":"18 Route Mousseaux 78760 Jouars Pontchartrain",
    "sg:classifiers":[
        {
            "category":"Manufacturing",
            "subcategory":"Glass & Minerals",
            "type":"Manufacturing & Wholesale Goods"
        }
    ],
    "sg:phone":"+33 1 34 87 85 36",
    "sg:postcode":"78760",
    "sg:province":"Ile de France",
    "sg:tags":[
        "building",
        "material"
    ],
    "wof:name":"Miroiterie Des Yvelines Sa",
    "wof:placetype":"venue"
},
  "geometry": {"coordinates":[1.896227,48.7854],"type":"Point"}
}