{
  "type": "Feature",
  "properties": {
    "iso:country":"FR",
    "sg:address":"av du Professeur Fl\u00e9ming 33610 Cestas",
    "sg:city":"Cestas",
    "sg:classifiers":[
        {
            "category":"Shopping",
            "subcategory":"Baby Store",
            "type":"Retail Goods"
        }
    ],
    "sg:phone":"+33 5 57 96 56 56",
    "sg:postcode":"33610",
    "sg:province":"Aquitaine",
    "sg:tags":[
        "food",
        "children's",
        "foods"
    ],
    "wof:name":"Vitagermine",
    "wof:placetype":"venue"
},
  "geometry": {"coordinates":[-0.701504,44.776314],"type":"Point"}
}