{
  "type": "Feature",
  "properties": {
    "iso:country":"FR",
    "sg:address":"7 Imp St Amand 94500 Champigny Sur Marne",
    "sg:classifiers":[
        {
            "category":"Manufacturing",
            "subcategory":"Printing",
            "type":"Manufacturing & Wholesale Goods"
        }
    ],
    "sg:phone":"+33 1 45 16 13 50",
    "sg:province":"Ile de France",
    "sg:tags":[
        "publishing"
    ],
    "wof:name":"Graphitec Sa",
    "wof:placetype":"venue"
},
  "geometry": {"coordinates":[2.49665,48.82259],"type":"Point"}
}