{
  "type": "Feature",
  "properties": {
    "iso:country":"FR",
    "sg:address":"5, Rue Jean Menans - Parc des Buttes Chaumont, 75019 Paris",
    "sg:orig_category":"Unclassifiable Establishments",
    "sg:phone":"+33 1 53 72 83 00",
    "sg:province":"Ile de France",
    "wof:name":"A.p.c. S.a.r.l. - Actualit\u00e9s Paie Conseil",
    "wof:placetype":"venue"
},
  "geometry": {"coordinates":[2.379391,48.88081],"type":"Point"}
}