{
  "type": "Feature",
  "properties": {
    "addr:full":"ZA de Maubec Maubec Rhone-Alpes 38300",
    "addr:postcode":"38300",
    "addr:street":"Za De Maubec;Rhone-Alpes",
    "iso:country":"FR",
    "sg:address":"ZA de Maubec",
    "sg:city":"Maubec",
    "sg:orig_category":"Unclassifiable Establishments",
    "sg:phone":"+33 4 74 93 71 55",
    "sg:postcode":"38300",
    "sg:province":"Rhone-Alpes",
    "wof:name":"Multipapiers S.a.r.l.",
    "wof:placetype":"venue"
},
  "geometry": {"coordinates":[5.26464,45.567654],"type":"Point"}
}