{
  "type": "Feature",
  "properties": {
    "addr:full":"108, Rue du Mont \u00e0 Leux, 59150 Wattrelos Nord Pas-de-Calais",
    "addr:housenumber":"108",
    "addr:postcode":"59150",
    "addr:street":"Rue Du Mont A\u0300 Leux",
    "iso:country":"FR",
    "sg:address":"108, Rue du Mont \u00e0 Leux, 59150 Wattrelos",
    "sg:orig_category":"Unclassifiable Establishments",
    "sg:phone":"+33 3 20 01 07 60",
    "sg:province":"Nord Pas-de-Calais",
    "wof:name":"Sion Paul Et Fils S.a.",
    "wof:placetype":"venue"
},
  "geometry": {"coordinates":[3.184174,50.71748],"type":"Point"}
}