{
  "type": "Feature",
  "properties": {
    "iso:country":"FR",
    "sg:address":"Zac Des Grands Clos 37420 AVOINE",
    "sg:city":"Avoine",
    "sg:classifiers":[
        {
            "category":"Manufacturing",
            "subcategory":"Wood Products",
            "type":"Manufacturing & Wholesale Goods"
        }
    ],
    "sg:phone":"+33 2 47 58 86 10",
    "sg:postcode":"37420",
    "sg:province":"Centre",
    "sg:tags":[
        "technical",
        "drying"
    ],
    "wof:name":"Chene De France S.a.r.l.",
    "wof:placetype":"venue"
},
  "geometry": {"coordinates":[0.181698,47.206543],"type":"Point"}
}