{
  "type": "Feature",
  "properties": {
    "iso:country":"FR",
    "sg:address":"10, Rue Alexandre, 08000 Charleville M\u00e9zi\u00e8res",
    "sg:city":"Charleville-M\u00e9zi\u00e8res",
    "sg:orig_category":"Non-Classified Establishments",
    "sg:phone":"+33 3 24 59 37 38",
    "sg:postcode":"08000",
    "sg:province":"Champagne",
    "wof:name":"Imprimerie Saingery",
    "wof:placetype":"venue"
},
  "geometry": {"coordinates":[4.725851,49.770641],"type":"Point"}
}