{
  "type": "Feature",
  "properties": {
    "iso:country":"FR",
    "sg:address":"1 Rue De La Galoch\u00e8re 38400 St Martin D'H\u00e8res",
    "sg:classifiers":[
        {
            "category":"Professional",
            "subcategory":"Engineering",
            "type":"Services"
        }
    ],
    "sg:phone":"+33 4 76 62 96 47",
    "sg:postcode":"38400",
    "sg:province":"Rhone-Alpes",
    "sg:tags":[
        "metallurgy",
        "metal",
        "processing",
        "-",
        "machine",
        "metalworking",
        "machinery",
        "mechanical"
    ],
    "wof:name":"Fac Traitement De Surface Sarl",
    "wof:placetype":"venue"
},
  "geometry": {"coordinates":[5.776862,45.177216],"type":"Point"}
}