{
  "type": "Feature",
  "properties": {
    "addr:full":"41-43 rue de la Finarie 81200 MAZAMET Midi Pyr\u00e9n\u00e9es 81200",
    "addr:housenumber":"41-43",
    "addr:postcode":"81200;81200",
    "addr:street":"Rue De La Finarie",
    "iso:country":"FR",
    "sg:address":"41-43 rue de la Finarie 81200 MAZAMET",
    "sg:classifiers":[
        {
            "category":"Personal",
            "subcategory":"Tanning Parlor",
            "type":"Services"
        }
    ],
    "sg:phone":"+33 5 63 98 92 16",
    "sg:postcode":"81200",
    "sg:province":"Midi Pyr\u00e9n\u00e9es",
    "sg:tags":[
        "hide"
    ],
    "wof:name":"Ets Azais Fernand Et Cie S.a.r.l.",
    "wof:placetype":"venue"
},
  "geometry": {"coordinates":[2.37998,43.492699],"type":"Point"}
}