{
  "type": "Feature",
  "properties": {
    "addr:full":"RD 996 - ZA de Malaval Marboz Rhone-Alpes 01851",
    "addr:postcode":"01851",
    "addr:street":"Rd 996 Za De Malaval;Rhone-Alpes",
    "iso:country":"FR",
    "sg:address":"RD 996 - ZA de Malaval",
    "sg:city":"Marboz",
    "sg:orig_category":"Unclassifiable Establishments",
    "sg:phone":"+33 4 74 51 00 63",
    "sg:postcode":"01851",
    "sg:province":"Rhone-Alpes",
    "wof:name":"Simi S.a.r.l.",
    "wof:placetype":"venue"
},
  "geometry": {"coordinates":[5.244505,46.322487],"type":"Point"}
}