{
  "type": "Feature",
  "properties": {
    "iso:country":"FR",
    "sg:address":"43 Rue De Richelieu 75001 Paris",
    "sg:classifiers":[
        {
            "category":"Professional",
            "subcategory":"Advertising",
            "type":"Services"
        }
    ],
    "sg:phone":"+33 1 42 60 28 04",
    "sg:postcode":"75001",
    "sg:province":"Ile de France",
    "sg:tags":[
        "information",
        "medium",
        "communication"
    ],
    "wof:name":"Groupe France Mutuelle Sa",
    "wof:placetype":"venue"
},
  "geometry": {"coordinates":[2.3369,48.865986],"type":"Point"}
}