{
  "type": "Feature",
  "properties": {
    "addr:full":"4, Rue du Commerce, 68260 Kingersheim Kingersheim Alsace 68260",
    "addr:housenumber":"4",
    "addr:postcode":"68260;68260",
    "addr:street":"Rue Du Commerce",
    "iso:country":"FR",
    "sg:address":"4, Rue du Commerce, 68260 Kingersheim",
    "sg:city":"Kingersheim",
    "sg:orig_category":"Unclassifiable Establishments",
    "sg:phone":"+33 3 89 57 08 08",
    "sg:postcode":"68260",
    "sg:province":"Alsace",
    "wof:name":"Produits S\u00e9lectionn\u00e9s S.a.",
    "wof:placetype":"venue"
},
  "geometry": {"coordinates":[7.313935,47.793758],"type":"Point"}
}