{
  "type": "Feature",
  "properties": {
    "iso:country":"FR",
    "sg:address":"25 Rue Jeanne D'Arc 52115 St Dizier",
    "sg:classifiers":[
        {
            "category":"Shopping",
            "type":"Retail Goods"
        }
    ],
    "sg:phone":"+33 3 25 56 54 36",
    "sg:province":"Bourgogne",
    "sg:tags":[
        "metallurgy",
        "finished",
        "-",
        "metalworking",
        "metallic"
    ],
    "wof:name":"Ste Nouvelle D'exploitation Renot",
    "wof:placetype":"venue"
},
  "geometry": {"coordinates":[4.944951,48.645309],"type":"Point"}
}