{
  "type": "Feature",
  "properties": {
    "addr:full":"Zi Beaune-Vignolles 21200 Beaune Beaune Bourgogne 21200",
    "addr:postcode":"21200;21200",
    "iso:country":"FR",
    "sg:address":"Zi Beaune-Vignolles 21200 Beaune",
    "sg:city":"Beaune",
    "sg:classifiers":[
        {
            "category":"Manufacturing",
            "subcategory":"Wood Products",
            "type":"Manufacturing & Wholesale Goods"
        }
    ],
    "sg:phone":"+33 3 80 25 92 60",
    "sg:postcode":"21200",
    "sg:province":"Bourgogne",
    "sg:tags":[
        "furniture"
    ],
    "wof:name":"Sa Tonnellerie Billon",
    "wof:placetype":"venue"
},
  "geometry": {"coordinates":[4.835545,47.019245],"type":"Point"}
}