{
  "type": "Feature",
  "properties": {
    "addr:full":"20, Rue Bernard Palissy, 45800 Saint Jean de Braye Combleux Centre 45800",
    "addr:housenumber":"20;combleux",
    "addr:postcode":"45800;45800",
    "addr:street":"Rue Bernard Palissy",
    "iso:country":"FR",
    "sg:address":"20, Rue Bernard Palissy, 45800 Saint Jean de Braye",
    "sg:city":"Combleux",
    "sg:orig_category":"Unclassifiable Establishments",
    "sg:phone":"+33 2 38 79 75 50",
    "sg:postcode":"45800",
    "sg:province":"Centre",
    "wof:name":"Rineau S.a.",
    "wof:placetype":"venue"
},
  "geometry": {"coordinates":[1.944111,47.914776],"type":"Point"}
}