{
  "type": "Feature",
  "properties": {
    "addr:full":"272, Rue des Vingt Toises, 38950 Saint Martin le Vinoux Rhone-Alpes 38950",
    "addr:housenumber":"272",
    "addr:postcode":"38950;38950",
    "addr:street":"Rue Des Vingt Toises;Martin Le;Rhone-Alpes",
    "iso:country":"FR",
    "sg:address":"272, Rue des Vingt Toises, 38950 Saint Martin le Vinoux",
    "sg:orig_category":"Non-Classified Establishments",
    "sg:phone":"+33 4 76 56 18 18",
    "sg:postcode":"38950",
    "sg:province":"Rhone-Alpes",
    "wof:name":"Rural Services",
    "wof:placetype":"venue"
},
  "geometry": {"coordinates":[5.687757,45.213043],"type":"Point"}
}