{
  "type": "Feature",
  "properties": {
    "addr:full":"Avenue Sinibaldi 87130 Ch\u00e2teauneuf La For\u00eat Limousin 87130",
    "addr:postcode":"87130;87130",
    "addr:street":"Avenue Sinibaldi;La Fore\u0302T Limousin",
    "iso:country":"FR",
    "sg:address":"Avenue Sinibaldi 87130 Ch\u00e2teauneuf La For\u00eat",
    "sg:classifiers":[
        {
            "category":"Military Area",
            "subcategory":"Air Force Base",
            "type":"Public Place"
        }
    ],
    "sg:phone":"+33 5 55 69 32 53",
    "sg:postcode":"87130",
    "sg:province":"Limousin",
    "sg:tags":[
        "good",
        "material",
        "-",
        "machine",
        "equipment",
        "engineering",
        "handling",
        "transport",
        "mechanical",
        "road"
    ],
    "wof:name":"Sa Faye",
    "wof:placetype":"venue"
},
  "geometry": {"coordinates":[1.603045,45.71283],"type":"Point"}
}