{
  "type": "Feature",
  "properties": {
    "iso:country":"FR",
    "sg:address":"38 Bis, Place de l'Eglise, 35850 Romill\u00e9",
    "sg:city":"Romill\u00e9",
    "sg:orig_category":"Non-Classified Establishments",
    "sg:phone":"+33 2 99 68 23 23",
    "sg:postcode":"35850",
    "sg:province":"Bretagne",
    "wof:name":"Presta Breizh S.a.",
    "wof:placetype":"venue"
},
  "geometry": {"coordinates":[-1.790026,48.220993],"type":"Point"}
}