{
  "type": "Feature",
  "properties": {
    "addr:full":"22, Bd Anatole France, 06340 La Trinit\u00e9 Provence-Alpes-C\u00f4te d'Azur",
    "addr:housenumber":"22",
    "addr:postcode":"06340",
    "addr:street":"Bd Anatole France;Trinite\u0301",
    "iso:country":"FR",
    "sg:address":"22, Bd Anatole France, 06340 La Trinit\u00e9",
    "sg:orig_category":"Unclassifiable Establishments",
    "sg:phone":"+33 4 93 54 82 60",
    "sg:province":"Provence-Alpes-C\u00f4te d'Azur",
    "wof:name":"Syd\u00e9ric S.a.",
    "wof:placetype":"venue"
},
  "geometry": {"coordinates":[7.310466,43.743832],"type":"Point"}
}