{
  "type": "Feature",
  "properties": {
    "addr:full":"B.P. 1007, 01101 Oyonnax C\u00e9dex^^15, Chemin du Grand Moulin - Usine du Grand Moulin , 01100 Oyonnax Rhone-Alpes 01100",
    "addr:postcode":"01101;01100;01100",
    "addr:street":"B.P. 1007;Chemin Du Grand Moulin Usine Du Grand Moulin",
    "iso:country":"FR",
    "sg:address":"B.P. 1007, 01101 Oyonnax C\u00e9dex^^15, Chemin du Grand Moulin - Usine du Grand Moulin , 01100 Oyonnax",
    "sg:orig_category":"Non-Classified Establishments",
    "sg:phone":"+33 4 74 77 46 22",
    "sg:postcode":"01100",
    "sg:province":"Rhone-Alpes",
    "wof:name":"D\u00e9coracet S.a.r.l.",
    "wof:placetype":"venue"
},
  "geometry": {"coordinates":[5.64405,46.24968],"type":"Point"}
}