{
  "type": "Feature",
  "properties": {
    "iso:country":"FR",
    "sg:address":"9 rue Albert Einstein 77420 Champs sur Marne",
    "sg:classifiers":[
        {
            "category":"Shopping",
            "subcategory":"Computers & Home Electronics",
            "type":"Retail Goods"
        }
    ],
    "sg:phone":"+33 1 64 68 30 00",
    "sg:postcode":"77420",
    "sg:province":"Ile de France",
    "sg:tags":[
        "client-server",
        "software"
    ],
    "wof:name":"E.m.c. Sa",
    "wof:placetype":"venue"
},
  "geometry": {"coordinates":[2.585909,48.836773],"type":"Point"}
}