{
  "type": "Feature",
  "properties": {
    "addr:full":"43, Rue du Saule Trapu - ZA du Moulin, 91300 Massy Ile de France",
    "addr:housenumber":"43",
    "addr:postcode":"91300",
    "addr:street":"Rue Du Saule Trapu Za Du Moulin;Massy Ile De France",
    "iso:country":"FR",
    "sg:address":"43, Rue du Saule Trapu - ZA du Moulin, 91300 Massy",
    "sg:orig_category":"Unclassifiable Establishments",
    "sg:phone":"+33 1 69 93 83 60",
    "sg:province":"Ile de France",
    "wof:name":"Createch Industrie S.a.",
    "wof:placetype":"venue"
},
  "geometry": {"coordinates":[2.27325,48.730282],"type":"Point"}
}