{
  "type": "Feature",
  "properties": {
    "addr:full":"Rte Ch\u00e2teau La Valli\u00e8re 37360 Neuill\u00e9 Pont Pierre Beaumont-la-Ronce Centre 37360",
    "addr:postcode":"37360;37360",
    "addr:street":"Rte Cha\u0302Teau La Vallie\u0300Re",
    "iso:country":"FR",
    "sg:address":"Rte Ch\u00e2teau La Valli\u00e8re 37360 Neuill\u00e9 Pont Pierre",
    "sg:city":"Beaumont-la-Ronce",
    "sg:classifiers":[
        {
            "category":"Manufacturing",
            "subcategory":"Printing",
            "type":"Manufacturing & Wholesale Goods"
        }
    ],
    "sg:phone":"+33 2 47 29 77 88",
    "sg:postcode":"37360",
    "sg:province":"Centre",
    "sg:tags":[
        "publishing"
    ],
    "wof:name":"Faconnage 37 Sa",
    "wof:placetype":"venue"
},
  "geometry": {"coordinates":[0.54306,47.485722],"type":"Point"}
}