{
  "type": "Feature",
  "properties": {
    "iso:country":"FR",
    "sg:address":"13-15, rue des Entrepreneurs, 91560 Crosne",
    "sg:orig_category":"Unclassifiable Establishments",
    "sg:phone":"+33 1 69 49 79 78",
    "sg:province":"Ile de France",
    "wof:name":"Mecaflex S.a.r.l.",
    "wof:placetype":"venue"
},
  "geometry": {"coordinates":[2.472887,48.725037],"type":"Point"}
}