{
  "type": "Feature",
  "properties": {
    "addr:full":"17, Passage du Caire, 75002 Paris Ile de France 75002",
    "addr:housenumber":"17",
    "addr:postcode":"75002;75002",
    "addr:street":"Passage Du Caire",
    "iso:country":"FR",
    "sg:address":"17, Passage du Caire, 75002 Paris",
    "sg:orig_category":"Non-Classified Establishments",
    "sg:phone":"+33 1 42 21 17 36",
    "sg:postcode":"75002",
    "sg:province":"Ile de France",
    "wof:name":"Clip Art Eurexa S.a.",
    "wof:placetype":"venue"
},
  "geometry": {"coordinates":[2.351451,48.867332],"type":"Point"}
}