{
  "type": "Feature",
  "properties": {
    "addr:full":"16 Rue De L'Atome Zi 67800 Bischheim Bischheim Alsace 67800",
    "addr:housenumber":"16",
    "addr:postcode":"67800;67800",
    "addr:street":"Rue De L'Atome Zi",
    "iso:country":"FR",
    "sg:address":"16 Rue De L'Atome Zi 67800 Bischheim",
    "sg:city":"Bischheim",
    "sg:classifiers":[
        {
            "category":"Manufacturing",
            "subcategory":"Rubber & Plastics",
            "type":"Manufacturing & Wholesale Goods"
        }
    ],
    "sg:phone":"+33 3 88 81 18 14",
    "sg:postcode":"67800",
    "sg:province":"Alsace",
    "sg:tags":[
        "textile",
        "linen",
        "clothing",
        "fabric"
    ],
    "wof:name":"Revetements Hess Et Fils",
    "wof:placetype":"venue"
},
  "geometry": {"coordinates":[7.769752,48.628761],"type":"Point"}
}