{
  "type": "Feature",
  "properties": {
    "addr:full":"58, Rue Monsieur le Prince, 75006 Paris Ile de France",
    "addr:housenumber":"58",
    "addr:postcode":"75006",
    "addr:street":"Rue Monsieur Le Prince",
    "iso:country":"FR",
    "sg:address":"58, Rue Monsieur le Prince, 75006 Paris",
    "sg:orig_category":"Unclassifiable Establishments",
    "sg:phone":"+33 1 53 73 74 75",
    "sg:province":"Ile de France",
    "wof:name":"Vasconi Ing\u00e9nierie Et Architecture S.a.r.l.",
    "wof:placetype":"venue"
},
  "geometry": {"coordinates":[2.340625,48.848061],"type":"Point"}
}