{
  "type": "Feature",
  "properties": {
    "addr:full":"3, Rue Ettore Bugatti, 67500 Haguenau Haguenau Alsace 67500",
    "addr:housenumber":"3",
    "addr:postcode":"67500;67500",
    "addr:street":"Rue Ettore Bugatti",
    "iso:country":"FR",
    "sg:address":"3, Rue Ettore Bugatti, 67500 Haguenau",
    "sg:city":"Haguenau",
    "sg:orig_category":"Unclassifiable Establishments",
    "sg:phone":"+33 3 88 05 42 20",
    "sg:postcode":"67500",
    "sg:province":"Alsace",
    "wof:name":"Sapo S.a. - Soci\u00e9t\u00e9 Alsacienne De Polym\u00e8res",
    "wof:placetype":"venue"
},
  "geometry": {"coordinates":[7.800516,48.797577],"type":"Point"}
}