{
  "type": "Feature",
  "properties": {
    "iso:country":"FR",
    "sg:address":"72, Rue Pierre Curie, 78130 Les Mureaux",
    "sg:orig_category":"Unclassifiable Establishments",
    "sg:phone":"+33 1 30 04 15 50",
    "sg:province":"Ile de France",
    "wof:name":"Fieldflex Europe S.a.s.",
    "wof:placetype":"venue"
},
  "geometry": {"coordinates":[1.926568,48.994553],"type":"Point"}
}