{
  "type": "Feature",
  "properties": {
    "addr:full":"10, Rue de la Prairie, 69100 Villeurbanne Rhone-Alpes 69100",
    "addr:housenumber":"10",
    "addr:postcode":"69100;69100",
    "addr:street":"Rue De La Prairie",
    "iso:country":"FR",
    "sg:address":"10, Rue de la Prairie, 69100 Villeurbanne",
    "sg:orig_category":"Unclassifiable Establishments",
    "sg:phone":"+33 4 72 04 51 83",
    "sg:postcode":"69100",
    "sg:province":"Rhone-Alpes",
    "wof:name":"H.i.m. France",
    "wof:placetype":"venue"
},
  "geometry": {"coordinates":[4.899517,45.783054],"type":"Point"}
}