{
  "type": "Feature",
  "properties": {
    "addr:full":"9 rue Champcevrais 89350 CHAMPIGNELLES Champignelles Bourgogne 89350",
    "addr:housenumber":"9",
    "addr:postcode":"89350;89350",
    "addr:street":"Rue Champcevrais",
    "iso:country":"FR",
    "sg:address":"9 rue Champcevrais 89350 CHAMPIGNELLES",
    "sg:city":"Champignelles",
    "sg:classifiers":[
        {
            "category":"Manufacturing",
            "subcategory":"Rubber & Plastics",
            "type":"Manufacturing & Wholesale Goods"
        }
    ],
    "sg:phone":"+33 3 86 45 10 23",
    "sg:postcode":"89350",
    "sg:province":"Bourgogne",
    "sg:tags":[
        "processing"
    ],
    "wof:name":"Rial Plastics S.a.",
    "wof:placetype":"venue"
},
  "geometry": {"coordinates":[3.065272,47.778347],"type":"Point"}
}