{
  "type": "Feature",
  "properties": {
    "iso:country":"FR",
    "sg:address":"Peissonnel 83550 VIDAUBAN",
    "sg:classifiers":[
        {
            "category":"Wholesale",
            "subcategory":"Wine & Distilled Alcoholic Beverages",
            "type":"Manufacturing & Wholesale Goods"
        }
    ],
    "sg:phone":"+33 4 94 73 03 12",
    "sg:province":"Champagne",
    "sg:tags":[
        "french"
    ],
    "wof:name":"Domaine Feraud Peissonnel Sev",
    "wof:placetype":"venue"
},
  "geometry": {"coordinates":[6.43862,43.39035],"type":"Point"}
}