{
  "type": "Feature",
  "properties": {
    "iso:country":"FR",
    "sg:address":"rue du 8 Mai 25490 FESCHES LE CHATEL",
    "sg:orig_category":"Pre-Wall Installation Elements, Sanitary",
    "sg:phone":"+33 3 81 93 01 65",
    "sg:province":"Franche Comt\u00e9",
    "wof:name":"Transvaal Gres Sa",
    "wof:placetype":"venue"
},
  "geometry": {"coordinates":[6.913402,47.521957],"type":"Point"}
}