{
  "type": "Feature",
  "properties": {
    "addr:full":"Av. des Aur\u00e9ats Valence Midi Pyr\u00e9n\u00e9es 26000",
    "addr:postcode":"26000",
    "addr:street":"Av. Des Aure\u0301Ats",
    "iso:country":"FR",
    "sg:address":"Av. des Aur\u00e9ats",
    "sg:city":"Valence",
    "sg:orig_category":"Non-Classified Establishments",
    "sg:phone":"+33 4 75 81 71 71",
    "sg:postcode":"26000",
    "sg:province":"Midi Pyr\u00e9n\u00e9es",
    "wof:name":"T.f.e. - Transport Frigorifique Europ\u00e9en.",
    "wof:placetype":"venue"
},
  "geometry": {"coordinates":[4.884193,44.900108],"type":"Point"}
}