{
  "type": "Feature",
  "properties": {
    "iso:country":"FR",
    "sg:address":"67, Av A Th\u00e9venet, 51200 Epernay",
    "sg:orig_category":"Unclassifiable Establishments",
    "sg:phone":"+33 3 26 53 35 00",
    "sg:province":"Champagne",
    "wof:name":"Isoroy Contre-plaqu\u00e9 S.a.",
    "wof:placetype":"venue"
},
  "geometry": {"coordinates":[3.95475,49.045197],"type":"Point"}
}