{
  "type": "Feature",
  "properties": {
    "iso:country":"FR",
    "sg:address":"1 Chemin De Lou Tribail Za Auguste 3 N 1 Ter 33610 Cestas",
    "sg:city":"Cestas",
    "sg:classifiers":[
        {
            "category":"Home & Garden",
            "subcategory":"Furniture",
            "type":"Retail Goods"
        }
    ],
    "sg:phone":"+33 5 57 97 34 34",
    "sg:postcode":"33610",
    "sg:province":"Aquitaine",
    "sg:tags":[
        "wood"
    ],
    "wof:name":"Bureau Central De Securite France (bcs France)",
    "wof:placetype":"venue"
},
  "geometry": {"coordinates":[-0.685714,44.741707],"type":"Point"}
}