{
  "type": "Feature",
  "properties": {
    "iso:country":"FR",
    "sg:address":"A\u00e9rodrome",
    "sg:city":"Villiers le Sec",
    "sg:orig_category":"Non-Classified Establishments",
    "sg:phone":"+33 3 25 35 06 00",
    "sg:postcode":"52000",
    "sg:province":"Champagne",
    "wof:name":"S.m.a.o. S.a.r.l. - Soci\u00e9t\u00e9 Marnaise Aff\u00fbtage Et Outillage",
    "wof:placetype":"venue"
},
  "geometry": {"coordinates":[5.135536,48.110767],"type":"Point"}
}