{
  "type": "Feature",
  "properties": {
    "iso:country":"FR",
    "sg:address":"18, Av. de la Gare, 74100 Annemasse",
    "sg:orig_category":"Unclassifiable Establishments",
    "sg:phone":"+33 820 33 79 17",
    "sg:postcode":"74100",
    "sg:province":"Rhone-Alpes",
    "wof:name":"Banque Populaire Des Alpes S.a.",
    "wof:placetype":"venue"
},
  "geometry": {"coordinates":[6.23419,46.194942],"type":"Point"}
}