{
  "type": "Feature",
  "properties": {
    "iso:country":"FR",
    "sg:address":"rue Raymond Derain 59700 Marcq en Baroeul",
    "sg:classifiers":[
        {
            "category":"Manufacturing",
            "subcategory":"Motor Vehicles & Parts",
            "type":"Manufacturing & Wholesale Goods"
        }
    ],
    "sg:phone":"+33 3 20 72 03 67",
    "sg:province":"Nord Pas-de-Calais",
    "sg:tags":[
        "precision",
        "mechanic"
    ],
    "wof:name":"A.c.m.m. Sa",
    "wof:placetype":"venue"
},
  "geometry": {"coordinates":[3.090635,50.675758],"type":"Point"}
}