{
  "type": "Feature",
  "properties": {
    "iso:country":"FR",
    "sg:address":"5111 111 67470 SELTZ",
    "sg:city":"Seltz",
    "sg:orig_category":"Furniture, General",
    "sg:phone":"+33 3 88 05 55 50",
    "sg:postcode":"67470",
    "sg:province":"Alsace",
    "wof:name":"Inter Link Sa",
    "wof:placetype":"venue"
},
  "geometry": {"coordinates":[8.103833,48.894581],"type":"Point"}
}