{
  "type": "Feature",
  "properties": {
    "iso:country":"FR",
    "sg:address":"11, Rue Baudin, 94207 Ivry sur Seine C\u00e9dex",
    "sg:orig_category":"Non-Classified Establishments",
    "sg:phone":"+33 1 49 87 88 88",
    "sg:province":"Bretagne",
    "wof:name":"Coprex S.a.",
    "wof:placetype":"venue"
},
  "geometry": {"coordinates":[2.374187,48.817169],"type":"Point"}
}