{
  "type": "Feature",
  "properties": {
    "iso:country":"FR",
    "sg:address":"10 Rue Amp\u00e9re Zi 77109 Meaux Cedex",
    "sg:classifiers":[
        {
            "category":"Transit Center",
            "subcategory":"Freight",
            "type":"Transportation"
        }
    ],
    "sg:phone":"+33 1 64 33 25 51",
    "sg:province":"Ile de France",
    "sg:tags":[
        "metallurgy",
        "pipe",
        "metalworking",
        "sheet"
    ],
    "wof:name":"Bujon Sa",
    "wof:placetype":"venue"
},
  "geometry": {"coordinates":[2.883054,48.959351],"type":"Point"}
}