{
  "type": "Feature",
  "properties": {
    "iso:country":"FR",
    "sg:address":"31 rue Jean Wenger-Valentin, 67000 Strasbourg, Dept 67",
    "sg:city":"Strasbourg",
    "sg:classifiers":[
        {
            "category":"Banks & Credit Unions",
            "subcategory":"Bank",
            "type":"Services"
        }
    ],
    "sg:postcode":"67000",
    "sg:province":"Alsace",
    "wof:name":"Cial Finance",
    "wof:placetype":"venue"
},
  "geometry": {"coordinates":[7.761679,48.599293],"type":"Point"}
}