{
  "type": "Feature",
  "properties": {
    "addr:full":"B.P. 522 M\u00e2con C\u00e9dex Haute Normandie 71010",
    "addr:housenumber":"b.p. 522",
    "addr:postcode":"71010",
    "addr:street":"Haute Normandie",
    "iso:country":"FR",
    "sg:address":"B.P. 522",
    "sg:city":"M\u00e2con C\u00e9dex",
    "sg:orig_category":"Non-Classified Establishments",
    "sg:phone":"+33 3 85 29 55 29",
    "sg:postcode":"71010",
    "sg:province":"Haute Normandie",
    "wof:name":"S\u00e9pasal S.a.r.l.",
    "wof:placetype":"venue"
},
  "geometry": {"coordinates":[4.78461,46.310059],"type":"Point"}
}