{
  "type": "Feature",
  "properties": {
    "addr:full":"Place Neyrand BP 12 42420 Lorette Rhone-Alpes 42420",
    "addr:housenumber":"12",
    "addr:postcode":"42420;42420",
    "addr:street":"Place Neyrand Bp",
    "iso:country":"FR",
    "sg:address":"Place Neyrand BP 12 42420 Lorette",
    "sg:classifiers":[
        {
            "category":"Manufacturing",
            "subcategory":"Metals",
            "type":"Manufacturing & Wholesale Goods"
        }
    ],
    "sg:phone":"+33 4 77 73 24 75",
    "sg:postcode":"42420",
    "sg:province":"Rhone-Alpes",
    "sg:tags":[
        "metallurgy",
        "metalworking",
        "processing"
    ],
    "wof:name":"Beniere Et Perrin (anciens Etablissements) Sa",
    "wof:placetype":"venue"
},
  "geometry": {"coordinates":[4.581775,45.515259],"type":"Point"}
}