{
  "type": "Feature",
  "properties": {
    "addr:full":"52 Boulevard De La Federation 13004 Marseille Poitou-Charentes",
    "addr:housenumber":"52",
    "addr:postcode":"13004",
    "addr:street":"Boulevard De La Federation",
    "iso:country":"FR",
    "sg:address":"52 Boulevard De La Federation 13004 Marseille",
    "sg:classifiers":[
        {
            "category":"Manufacturing",
            "subcategory":"Jewelry",
            "type":"Manufacturing & Wholesale Goods"
        }
    ],
    "sg:phone":"+33 4 91 85 12 80",
    "sg:province":"Poitou-Charentes",
    "sg:tags":[
        "product",
        "miscellaneous",
        "jewellery"
    ],
    "wof:name":"Barone",
    "wof:placetype":"venue"
},
  "geometry": {"coordinates":[5.403286,43.312626],"type":"Point"}
}