{
  "type": "Feature",
  "properties": {
    "iso:country":"FR",
    "sg:address":"6, Rte Nationale, 89290 Champs sur Yonne",
    "sg:city":"Augy",
    "sg:orig_category":"Unclassifiable Establishments",
    "sg:phone":"+33 3 86 53 52 00",
    "sg:postcode":"89290",
    "sg:province":"Bourgogne",
    "wof:name":"Nicolas Industrie S.a.",
    "wof:placetype":"venue"
},
  "geometry": {"coordinates":[3.636858,47.806263],"type":"Point"}
}