{
  "type": "Feature",
  "properties": {
    "iso:country":"FR",
    "sg:address":"16 Av Su\u00e8de 14110 Cond\u00e9 Sur Noireau",
    "sg:city":"Saint-Denis-de-M\u00e9r\u00e9",
    "sg:classifiers":[
        {
            "category":"Manufacturing",
            "subcategory":"Printing",
            "type":"Manufacturing & Wholesale Goods"
        }
    ],
    "sg:phone":"+33 2 31 69 04 26",
    "sg:postcode":"14110",
    "sg:province":"Basse Normandie",
    "sg:tags":[
        "publishing"
    ],
    "wof:name":"Anquetil Sa",
    "wof:placetype":"venue"
},
  "geometry": {"coordinates":[-0.561975,48.843037],"type":"Point"}
}