{
  "type": "Feature",
  "properties": {
    "iso:country":"FR",
    "sg:address":"Moulin D Hyeres 22160 Carnoet",
    "sg:city":"Carno\u00ebt",
    "sg:classifiers":[
        {
            "category":"Farming",
            "subcategory":"Farm & Veterinary Services",
            "type":"Manufacturing & Wholesale Goods"
        }
    ],
    "sg:phone":"+33 2 96 21 59 21",
    "sg:postcode":"22160",
    "sg:province":"Bretagne",
    "sg:tags":[
        "food",
        "product",
        "breeding",
        "animal",
        "related"
    ],
    "wof:name":"Moulin D'hyeres Societe Anonyme",
    "wof:placetype":"venue"
},
  "geometry": {"coordinates":[-3.486047,48.347546],"type":"Point"}
}