{
  "type": "Feature",
  "properties": {
    "addr:full":"Rue Alfred Cattel Amiens Picardie 80000",
    "addr:postcode":"80000",
    "addr:street":"Rue Alfred Cattel",
    "iso:country":"FR",
    "sg:address":"Rue Alfred Cattel",
    "sg:city":"Amiens",
    "sg:orig_category":"Non-Classified Establishments",
    "sg:phone":"+33 3 22 52 40 00",
    "sg:postcode":"80000",
    "sg:province":"Picardie",
    "wof:name":"Loxam S.a.",
    "wof:placetype":"venue"
},
  "geometry": {"coordinates":[2.275935,49.905994],"type":"Point"}
}