{
  "type": "Feature",
  "properties": {
    "addr:full":"Route de Roinville 28700 AUNAY SOUS AUNEAU Roinville Centre 28700",
    "addr:postcode":"28700;28700",
    "addr:street":"Route De Roinville",
    "iso:country":"FR",
    "sg:address":"Route de Roinville 28700 AUNAY SOUS AUNEAU",
    "sg:city":"Roinville",
    "sg:classifiers":[
        {
            "category":"Manufacturing",
            "subcategory":"Rubber & Plastics",
            "type":"Manufacturing & Wholesale Goods"
        }
    ],
    "sg:phone":"+33 2 37 91 77 00",
    "sg:postcode":"28700",
    "sg:province":"Centre",
    "sg:tags":[
        "article"
    ],
    "wof:name":"Polarcup France S.a.",
    "wof:placetype":"venue"
},
  "geometry": {"coordinates":[1.910886,48.354084],"type":"Point"}
}