{
  "type": "Feature",
  "properties": {
    "addr:full":"40 boulevard Jules Durand 76600 Le Havre Haute Normandie",
    "addr:housenumber":"40",
    "addr:postcode":"76600",
    "addr:street":"Boulevard Jules Durand",
    "iso:country":"FR",
    "sg:address":"40 boulevard Jules Durand 76600 Le Havre",
    "sg:classifiers":[
        {
            "category":"Manufacturing",
            "subcategory":"Building Materials",
            "type":"Manufacturing & Wholesale Goods"
        }
    ],
    "sg:phone":"+33 2 35 53 49 99",
    "sg:province":"Haute Normandie",
    "sg:tags":[
        "processing",
        "special"
    ],
    "wof:name":"Trefileries Et Cableries Du Havre S.a.",
    "wof:placetype":"venue"
},
  "geometry": {"coordinates":[0.152738,49.488781],"type":"Point"}
}