{
  "type": "Feature",
  "properties": {
    "addr:full":"Champ S\u00e8che Sud 89250 Chemilly sur Yonne Beaumont Bourgogne 89250",
    "addr:postcode":"89250;89250",
    "addr:street":"Champ Se\u0300Che Sud;Bourgogne",
    "iso:country":"FR",
    "sg:address":"Champ S\u00e8che Sud 89250 Chemilly sur Yonne",
    "sg:city":"Beaumont",
    "sg:orig_category":"Non-Classified Establishments",
    "sg:phone":"+33 3 86 98 25 00",
    "sg:postcode":"89250",
    "sg:province":"Bourgogne",
    "wof:name":"Ceb Bourgogne S.a.",
    "wof:placetype":"venue"
},
  "geometry": {"coordinates":[3.560498,47.866913],"type":"Point"}
}