{
  "type": "Feature",
  "properties": {
    "addr:full":"ZI Les Herbues Pagny sur Meuse Lorraine 55190",
    "addr:postcode":"55190",
    "addr:street":"Zi Les Herbues Pagny Sur Meuse Lorraine",
    "iso:country":"FR",
    "sg:address":"ZI Les Herbues",
    "sg:city":"Pagny sur Meuse",
    "sg:orig_category":"Unclassifiable Establishments",
    "sg:phone":"+33 3 29 90 65 38",
    "sg:postcode":"55190",
    "sg:province":"Lorraine",
    "wof:name":"A.c.m.g. S.a. - Atelier De Construction M\u00e9canique G\u00e9n\u00e9rale",
    "wof:placetype":"venue"
},
  "geometry": {"coordinates":[5.716705,48.688316],"type":"Point"}
}