{
  "type": "Feature",
  "properties": {
    "iso:country":"FR",
    "sg:address":"115, Rue Paul Gidon - ZI de l'Etrier, 73290 La Motte Servolex",
    "sg:orig_category":"Unclassifiable Establishments",
    "sg:phone":"+33 4 79 96 72 00",
    "sg:postcode":"73290",
    "sg:province":"Rhone-Alpes",
    "wof:name":"Syst\u00e8me U - Centrale R\u00e9gionale Est",
    "wof:placetype":"venue"
},
  "geometry": {"coordinates":[5.885132,45.597885],"type":"Point"}
}