{
  "type": "Feature",
  "properties": {
    "addr:full":"ZI Le Pont Frontenex Rhone-Alpes 73460",
    "addr:postcode":"73460",
    "addr:street":"Zi Le Pont Frontenex Rhone-Alpes",
    "iso:country":"FR",
    "sg:address":"ZI Le Pont",
    "sg:city":"Frontenex",
    "sg:orig_category":"Unclassifiable Establishments",
    "sg:phone":"+33 4 79 31 48 09",
    "sg:postcode":"73460",
    "sg:province":"Rhone-Alpes",
    "wof:name":"Soci\u00e9t\u00e9 Nouvelle Des Transports Cornu S.a.",
    "wof:placetype":"venue"
},
  "geometry": {"coordinates":[6.310965,45.635201],"type":"Point"}
}