{
  "type": "Feature",
  "properties": {
    "addr:full":"129 avenue Daumesnil 75012 Paris Ile de France 75012",
    "addr:housenumber":"129",
    "addr:postcode":"75012;75012",
    "addr:street":"Avenue Daumesnil",
    "iso:country":"FR",
    "sg:address":"129 avenue Daumesnil 75012 Paris",
    "sg:classifiers":[
        {
            "category":"Banks & Credit Unions",
            "subcategory":"Investment Brokerage",
            "type":"Services"
        }
    ],
    "sg:phone":"+33 1 53 33 82 00",
    "sg:postcode":"75012",
    "sg:province":"Ile de France",
    "sg:tags":[
        "accessory",
        "high-fashion"
    ],
    "wof:name":"Jean Charles Brosseau Licences Sa",
    "wof:placetype":"venue"
},
  "geometry": {"coordinates":[2.381816,48.844311],"type":"Point"}
}