{
  "type": "Feature",
  "properties": {
    "iso:country":"FR",
    "sg:address":"54bis, Rue Malherbe, 76600 Le Havre",
    "sg:orig_category":"Non-Classified Establishments",
    "sg:phone":"+33 2 35 24 23 84",
    "sg:postcode":"76600",
    "sg:province":"Haute Normandie",
    "wof:name":"Electro-force S.a.",
    "wof:placetype":"venue"
},
  "geometry": {"coordinates":[0.139752,49.499359],"type":"Point"}
}