{
  "type": "Feature",
  "properties": {
    "addr:full":"248, Av. Franklin Roosevelt, 69120 Vaulx en Velin Rhone-Alpes 69120",
    "addr:postcode":"69120;69120",
    "addr:street":"248 Av. Franklin Roosevelt",
    "iso:country":"FR",
    "sg:address":"248, Av. Franklin Roosevelt, 69120 Vaulx en Velin",
    "sg:orig_category":"Non-Classified Establishments",
    "sg:phone":"+33 4 72 15 99 56",
    "sg:postcode":"69120",
    "sg:province":"Rhone-Alpes",
    "wof:name":"A.f.t. I.f.t.i.m.",
    "wof:placetype":"venue"
},
  "geometry": {"coordinates":[4.93393,45.749599],"type":"Point"}
}