{
  "type": "Feature",
  "properties": {
    "addr:full":"Rte de L\u00e9ognan - Immeuble Topaze Villenave d'Ornon Aquitaine 33140",
    "addr:postcode":"33140",
    "addr:street":"Rte De Le\u0301Ognan",
    "iso:country":"FR",
    "sg:address":"Rte de L\u00e9ognan - Immeuble Topaze",
    "sg:city":"Villenave d'Ornon",
    "sg:orig_category":"Unclassifiable Establishments",
    "sg:phone":"+33 5 56 87 92 12",
    "sg:postcode":"33140",
    "sg:province":"Aquitaine",
    "wof:name":"G\u00e9fran Coreci S.a.",
    "wof:placetype":"venue"
},
  "geometry": {"coordinates":[-0.577072,44.772278],"type":"Point"}
}