{
  "type": "Feature",
  "properties": {
    "iso:country":"FR",
    "sg:address":"20 chauss\u00e9e de Bertinval 60260 Lamorlaye",
    "sg:orig_category":"Food, Vegetarian",
    "sg:phone":"+33 3 44 21 11 20",
    "sg:postcode":"60260",
    "sg:province":"Picardie",
    "wof:name":"Cbh S.a.r.l.",
    "wof:placetype":"venue"
},
  "geometry": {"coordinates":[2.428689,49.149574],"type":"Point"}
}