{
  "type": "Feature",
  "properties": {
    "iso:country":"FR",
    "sg:address":"80, Rte de Geilles, 01100 Oyonnax",
    "sg:orig_category":"Unclassifiable Establishments",
    "sg:phone":"+33 4 74 77 35 89",
    "sg:postcode":"01100",
    "sg:province":"Rhone-Alpes",
    "wof:name":"M.c.m. D\u00e9cor S.a.r.l.",
    "wof:placetype":"venue"
},
  "geometry": {"coordinates":[5.65999,46.247959],"type":"Point"}
}