{
  "type": "Feature",
  "properties": {
    "addr:full":"place des Bremondi\u00e8res 07130 ST PERAY Rhone-Alpes 07130",
    "addr:postcode":"07130;07130",
    "addr:street":"Place Des Bremondie\u0300Res;Rhone-Alpes",
    "iso:country":"FR",
    "sg:address":"place des Bremondi\u00e8res 07130 ST PERAY",
    "sg:classifiers":[
        {
            "category":"Manufacturing",
            "subcategory":"Textiles",
            "type":"Manufacturing & Wholesale Goods"
        }
    ],
    "sg:phone":"+33 4 75 81 67 00",
    "sg:postcode":"07130",
    "sg:province":"Rhone-Alpes",
    "sg:tags":[
        "natural"
    ],
    "wof:name":"Rhonetex Sa",
    "wof:placetype":"venue"
},
  "geometry": {"coordinates":[4.847423,44.948055],"type":"Point"}
}