{
  "type": "Feature",
  "properties": {
    "iso:country":"FR",
    "sg:address":"43 rue Raspail 92300 Levallois Perret",
    "sg:classifiers":[
        {
            "category":"Professional",
            "subcategory":"Employment Agencies",
            "type":"Services"
        }
    ],
    "sg:phone":"+33 1 55 21 07 00",
    "sg:postcode":"92300",
    "sg:province":"Ile de France",
    "sg:tags":[
        "import"
    ],
    "wof:name":"Commerce Et Technologie Internationale Sarl",
    "wof:placetype":"venue"
},
  "geometry": {"coordinates":[2.291584,48.897919],"type":"Point"}
}