{
  "type": "Feature",
  "properties": {
    "iso:country":"FR",
    "sg:address":"41 Bd Convention 19110 Bort Les Orgues",
    "sg:classifiers":[
        {
            "category":"Professional",
            "type":"Services"
        }
    ],
    "sg:phone":"+33 5 55 96 06 81",
    "sg:province":"Limousin",
    "sg:tags":[
        "transport"
    ],
    "wof:name":"Cheriex Transports Sarl",
    "wof:placetype":"venue"
},
  "geometry": {"coordinates":[2.494737,45.401314],"type":"Point"}
}