{
  "type": "Feature",
  "properties": {
    "addr:full":"Trezelan 22140 Begard B\u00e9gard Bretagne 22140",
    "addr:postcode":"22140;22140",
    "addr:street":"Trezelan;Be\u0301Gard",
    "iso:country":"FR",
    "sg:address":"Trezelan 22140 Begard",
    "sg:city":"B\u00e9gard",
    "sg:classifiers":[
        {
            "category":"Manufacturing",
            "subcategory":"Rubber & Plastics",
            "type":"Manufacturing & Wholesale Goods"
        }
    ],
    "sg:phone":"+33 2 96 45 30 54",
    "sg:postcode":"22140",
    "sg:province":"Bretagne",
    "wof:name":"Brigant Polyester",
    "wof:placetype":"venue"
},
  "geometry": {"coordinates":[-3.2571,48.649799],"type":"Point"}
}