{
  "type": "Feature",
  "properties": {
    "addr:full":"B.P. 779, 42951 Saint Etienne C\u00e9dex 9^^26, Rue de la T\u00e9l\u00e9matique, 42000 Saint Etienne Rhone-Alpes 42000",
    "addr:housenumber":"b.p. 779;9 ^ ^ 26",
    "addr:postcode":"42951;42000;42000",
    "addr:street":"Ce\u0301Dex;Rue De La Te\u0301Le\u0301Matique",
    "iso:country":"FR",
    "sg:address":"B.P. 779, 42951 Saint Etienne C\u00e9dex 9^^26, Rue de la T\u00e9l\u00e9matique, 42000 Saint Etienne",
    "sg:orig_category":"Non-Classified Establishments",
    "sg:phone":"+33 4 77 92 27 92",
    "sg:postcode":"42000",
    "sg:province":"Rhone-Alpes",
    "wof:name":"S.e.e.e. S.a. - Soci\u00e9t\u00e9 D' Etudes Et D'entreprises Electriques",
    "wof:placetype":"venue"
},
  "geometry": {"coordinates":[4.394358,45.456036],"type":"Point"}
}