{
  "type": "Feature",
  "properties": {
    "addr:full":"1, Rte Langeac - Le Moulin , 43230 Paulhaguet Paulhaguet Auvergne 43230",
    "addr:housenumber":"1",
    "addr:postcode":"43230;paulhaguet;43230",
    "addr:street":"Rte Langeac Le Moulin",
    "iso:country":"FR",
    "sg:address":"1, Rte Langeac - Le Moulin , 43230 Paulhaguet",
    "sg:city":"Paulhaguet",
    "sg:orig_category":"Non-Classified Establishments",
    "sg:phone":"+33 4 71 76 62 22",
    "sg:postcode":"43230",
    "sg:province":"Auvergne",
    "wof:name":"S.h.e.m. S.a.r.l. - Soci\u00e9t\u00e9 Hydro Electrique Des Moulins",
    "wof:placetype":"venue"
},
  "geometry": {"coordinates":[3.62377,45.139496],"type":"Point"}
}