{
  "type": "Feature",
  "properties": {
    "addr:full":"58, Rue Jean Jaur\u00e8s, 08700 Nouzonville Gespunsart Champagne 08700",
    "addr:housenumber":"58",
    "addr:postcode":"08700;08700",
    "addr:street":"Rue Jean Jaure\u0300S;Champagne",
    "iso:country":"FR",
    "sg:address":"58, Rue Jean Jaur\u00e8s, 08700 Nouzonville",
    "sg:city":"Gespunsart",
    "sg:orig_category":"Non-Classified Establishments",
    "sg:phone":"+33 3 24 53 81 14",
    "sg:postcode":"08700",
    "sg:province":"Champagne",
    "wof:name":"Duban Et Boisseau S.a.r.l.",
    "wof:placetype":"venue"
},
  "geometry": {"coordinates":[4.75116,49.814201],"type":"Point"}
}