{
  "type": "Feature",
  "properties": {
    "iso:country":"FR",
    "sg:address":"27, Rue des Marais, 72000 Le Mans",
    "sg:orig_category":"Unclassifiable Establishments",
    "sg:phone":"+33 2 43 50 05 90",
    "sg:province":"Pays de Loire",
    "wof:name":"Variant Consultants S.a.",
    "wof:placetype":"venue"
},
  "geometry": {"coordinates":[0.212832,47.994251],"type":"Point"}
}