{
  "type": "Feature",
  "properties": {
    "addr:full":"Les Quatre Chemins 19130 Saint Aulaire Limousin",
    "addr:postcode":"19130",
    "addr:street":"Quatre Chemins",
    "iso:country":"FR",
    "sg:address":"Les Quatre Chemins 19130 Saint Aulaire",
    "sg:orig_category":"Unclassifiable Establishments",
    "sg:phone":"+33 5 55 25 29 30",
    "sg:province":"Limousin",
    "wof:name":"Perlim G.i.e.",
    "wof:placetype":"venue"
},
  "geometry": {"coordinates":[1.39654,45.24889],"type":"Point"}
}