{
  "type": "Feature",
  "properties": {
    "addr:full":"RN 9 - Rte de Perpignan Narbonne Languedoc-Roussillon 11100",
    "addr:postcode":"11100",
    "addr:street":"Rn 9 Rte De Perpignan",
    "iso:country":"FR",
    "sg:address":"RN 9 - Rte de Perpignan",
    "sg:city":"Narbonne",
    "sg:orig_category":"Non-Classified Establishments",
    "sg:phone":"+33 4 68 41 68 68",
    "sg:postcode":"11100",
    "sg:province":"Languedoc-Roussillon",
    "wof:name":"Menuiseries Gr\u00e9goire",
    "wof:placetype":"venue"
},
  "geometry": {"coordinates":[2.953635,43.119781],"type":"Point"}
}