{
  "type": "Feature",
  "properties": {
    "iso:country":"FR",
    "sg:address":"B.P. 202, 91801 Brunoy C\u00e9dex^^118, Av. du G\u00e9n\u00e9ral Leclerc, 91800 Brunoy",
    "sg:orig_category":"Non-Classified Establishments",
    "sg:phone":"+33 1 60 46 31 11",
    "sg:province":"Ile de France",
    "wof:name":"Soci\u00e9t\u00e9 Dufour S.a.",
    "wof:placetype":"venue"
},
  "geometry": {"coordinates":[2.504703,48.698208],"type":"Point"}
}