{
  "type": "Feature",
  "properties": {
    "addr:full":"B.P. 10034, 57801 Freyming Merlebach C\u00e9dex^^25, Rue Nationale, 57800 Freyming Merlebach Lorraine 57800",
    "addr:housenumber":"10034",
    "addr:postcode":"57801;57800;57800",
    "addr:street":"Rue Nationale",
    "iso:country":"FR",
    "sg:address":"B.P. 10034, 57801 Freyming Merlebach C\u00e9dex^^25, Rue Nationale, 57800 Freyming Merlebach",
    "sg:orig_category":"Non-Classified Establishments",
    "sg:phone":"+33 3 87 81 60 23",
    "sg:postcode":"57800",
    "sg:province":"Lorraine",
    "wof:name":"Durol France S.a.r.l.",
    "wof:placetype":"venue"
},
  "geometry": {"coordinates":[6.793515,49.143681],"type":"Point"}
}