{
  "type": "Feature",
  "properties": {
    "iso:country":"FR",
    "sg:address":"route de Bergerac 33220 Pineuilh",
    "sg:city":"Pineuilh",
    "sg:classifiers":[
        {
            "category":"Wholesale",
            "subcategory":"Wine & Distilled Alcoholic Beverages",
            "type":"Manufacturing & Wholesale Goods"
        }
    ],
    "sg:phone":"+33 5 57 46 03 71",
    "sg:postcode":"33220",
    "sg:province":"Aquitaine",
    "sg:tags":[
        "french"
    ],
    "wof:name":"Groupement Viticulteurs De Guyenne Sa",
    "wof:placetype":"venue"
},
  "geometry": {"coordinates":[0.23075,44.842228],"type":"Point"}
}