{
  "type": "Feature",
  "properties": {
    "addr:full":"2, Rue de l'Egalit\u00e9 - ZA des Garennes, 74960 Meythet Rhone-Alpes 74960",
    "addr:housenumber":"2",
    "addr:postcode":"74960;74960",
    "addr:street":"Rue De L'Egalite;Za Des Garennes",
    "iso:country":"FR",
    "sg:address":"2, Rue de l'Egalit\u00e9 - ZA des Garennes, 74960 Meythet",
    "sg:orig_category":"Unclassifiable Establishments",
    "sg:phone":"+33 4 50 22 33 44",
    "sg:postcode":"74960",
    "sg:province":"Rhone-Alpes",
    "wof:name":"D.s.t. S.a. - Distribution Service Transmission",
    "wof:placetype":"venue"
},
  "geometry": {"coordinates":[6.097254,45.914307],"type":"Point"}
}