{
  "type": "Feature",
  "properties": {
    "iso:country":"FR",
    "sg:address":"Zone Horticole",
    "sg:city":"Tierc\u00e9",
    "sg:orig_category":"Non-Classified Establishments",
    "sg:phone":"+33 2 41 42 12 00",
    "sg:postcode":"49125",
    "sg:province":"Pays de Loire",
    "wof:name":"Isafloral S.a.",
    "wof:placetype":"venue"
},
  "geometry": {"coordinates":[-0.468399,47.615028],"type":"Point"}
}