{
  "type": "Feature",
  "properties": {
    "iso:country":"FR",
    "sg:address":"42, Rue du Professeur Paul Miller, 94500 Champigny sur Marne",
    "sg:orig_category":"Non-Classified Establishments",
    "sg:phone":"+33 1 45 16 62 00",
    "sg:province":"Ile de France",
    "wof:name":"Morand Industrie S.a.",
    "wof:placetype":"venue"
},
  "geometry": {"coordinates":[2.534934,48.81509],"type":"Point"}
}