{
  "type": "Feature",
  "properties": {
    "addr:full":"Rue des Fromentaux Saint Amand Montrond Centre 18200",
    "addr:postcode":"18200",
    "addr:street":"Rue Des Fromentaux",
    "iso:country":"FR",
    "sg:address":"Rue des Fromentaux",
    "sg:city":"Saint Amand Montrond",
    "sg:orig_category":"Unclassifiable Establishments",
    "sg:phone":"+33 2 48 96 46 61",
    "sg:postcode":"18200",
    "sg:province":"Centre",
    "wof:name":"Cartonnages Franche S.a.r.l.",
    "wof:placetype":"venue"
},
  "geometry": {"coordinates":[2.514194,46.718891],"type":"Point"}
}