{
  "type": "Feature",
  "properties": {
    "addr:full":"Rte De Cholet 85620 Rocheservi\u00e8re Pays de Loire 85620",
    "addr:postcode":"85620;85620",
    "addr:street":"Rte De Cholet",
    "iso:country":"FR",
    "sg:address":"Rte De Cholet 85620 Rocheservi\u00e8re",
    "sg:classifiers":[
        {
            "category":"Professional",
            "subcategory":"Engineering",
            "type":"Services"
        }
    ],
    "sg:phone":"+33 2 51 31 03 03",
    "sg:postcode":"85620",
    "sg:province":"Pays de Loire",
    "sg:tags":[
        "electric",
        "-",
        "component",
        "machine",
        "mechanical",
        "electronic"
    ],
    "wof:name":"Europlacer Industries Sa",
    "wof:placetype":"venue"
},
  "geometry": {"coordinates":[-1.513304,46.939156],"type":"Point"}
}