{
  "type": "Feature",
  "properties": {
    "iso:country":"FR",
    "sg:address":"Rte de Langres",
    "sg:city":"Chaumont",
    "sg:orig_category":"Non-Classified Establishments",
    "sg:phone":"+33 3 25 03 80 44",
    "sg:postcode":"52000",
    "sg:province":"Champagne",
    "wof:name":"Coud\u00e8re Etablissements S.a.",
    "wof:placetype":"venue"
},
  "geometry": {"coordinates":[5.14777,48.087399],"type":"Point"}
}