{
  "type": "Feature",
  "properties": {
    "addr:full":"B.P. 54, 02200 Villeneuve Saint Germain^^Rue Jean Mermoz - ZAC des Etomelles, 02200 Villeneuve Saint Picardie",
    "addr:postcode":"02200;02200",
    "addr:street":"B.P. 54;Zac Des Etomelles",
    "iso:country":"FR",
    "sg:address":"B.P. 54, 02200 Villeneuve Saint Germain^^Rue Jean Mermoz - ZAC des Etomelles, 02200 Villeneuve Saint",
    "sg:orig_category":"Non-Classified Establishments",
    "sg:phone":"+33 3 23 73 83 83",
    "sg:province":"Picardie",
    "wof:name":"Magetrans S.a.",
    "wof:placetype":"venue"
},
  "geometry": {"coordinates":[3.341099,49.371037],"type":"Point"}
}