{
  "type": "Feature",
  "properties": {
    "addr:full":"38490 Les Abrets Rhone-Alpes 38490",
    "addr:postcode":"38490;38490",
    "addr:street":"Rhone-Alpes",
    "iso:country":"FR",
    "sg:address":"38490 Les Abrets",
    "sg:orig_category":"Unclassifiable Establishments",
    "sg:phone":"+33 4 76 32 14 44",
    "sg:postcode":"38490",
    "sg:province":"Rhone-Alpes",
    "wof:name":"Bourgeat S.a.",
    "wof:placetype":"venue"
},
  "geometry": {"coordinates":[5.584947,45.53738],"type":"Point"}
}