{
  "type": "Feature",
  "properties": {
    "addr:full":"37, Rte du Rhin, 67100 Strasbourg Strasbourg Alsace 67100",
    "addr:housenumber":"37",
    "addr:postcode":"67100;67100",
    "addr:street":"Rte Du Rhin",
    "iso:country":"FR",
    "sg:address":"37, Rte du Rhin, 67100 Strasbourg",
    "sg:city":"Strasbourg",
    "sg:orig_category":"Unclassifiable Establishments",
    "sg:phone":"+33 3 88 84 90 88",
    "sg:postcode":"67100",
    "sg:province":"Alsace",
    "wof:name":"Etablissements Siehr S.a.s.",
    "wof:placetype":"venue"
},
  "geometry": {"coordinates":[7.772939,48.57135],"type":"Point"}
}