{
  "type": "Feature",
  "properties": {
    "iso:country":"FR",
    "sg:address":"28 rue Aim\u00e9 Treboulon 34660 Cournonterral",
    "sg:classifiers":[
        {
            "category":"Insurance",
            "subcategory":"Insurance Agent",
            "type":"Services"
        }
    ],
    "sg:phone":"+33 4 67 85 33 04",
    "sg:postcode":"34660",
    "sg:province":"Languedoc-Roussillon",
    "sg:tags":[
        "instrument",
        "dental"
    ],
    "wof:name":"Realisation Develop Industriel Medical S.a.r.l.",
    "wof:placetype":"venue"
},
  "geometry": {"coordinates":[3.715002,43.557625],"type":"Point"}
}