{
  "type": "Feature",
  "properties": {
    "addr:full":"98, Rue Gabriel P\u00e9ri, 94120 Fontenay sous Bois Ile de France",
    "addr:housenumber":"98",
    "addr:postcode":"94120",
    "addr:street":"Rue Gabriel Pe\u0301Ri;Bois Ile De France",
    "iso:country":"FR",
    "sg:address":"98, Rue Gabriel P\u00e9ri, 94120 Fontenay sous Bois",
    "sg:orig_category":"Unclassifiable Establishments",
    "sg:phone":"+33 1 42 33 21 28",
    "sg:province":"Ile de France",
    "wof:name":"F.t.f. S.a.",
    "wof:placetype":"venue"
},
  "geometry": {"coordinates":[2.45114,48.853996],"type":"Point"}
}