{
  "type": "Feature",
  "properties": {
    "addr:full":"70, Av. du G\u00e9n\u00e9ral de Gaulle, 92800 Puteaux Ile de France",
    "addr:postcode":"92800",
    "addr:street":"70 Av. Du Ge\u0301Ne\u0301Ral De Gaulle",
    "iso:country":"FR",
    "sg:address":"70, Av. du G\u00e9n\u00e9ral de Gaulle, 92800 Puteaux",
    "sg:orig_category":"Non-Classified Establishments",
    "sg:phone":"+33 1 46 96 96 00",
    "sg:province":"Ile de France",
    "wof:name":"France Clariant Lsm S.a.",
    "wof:placetype":"venue"
},
  "geometry": {"coordinates":[2.232046,48.887566],"type":"Point"}
}