{
  "type": "Feature",
  "properties": {
    "iso:country":"FR",
    "sg:address":"19 Rue De La Tremoille 75008 Paris",
    "sg:classifiers":[
        {
            "category":"Autos & Motor Vehicles",
            "subcategory":"Automobile Sales",
            "type":"Retail Goods"
        }
    ],
    "sg:phone":"+33 1 44 49 64 64",
    "sg:postcode":"75008",
    "sg:province":"Ile de France",
    "sg:tags":[
        "equipment",
        "motor-cars",
        "transport"
    ],
    "wof:name":"Societe Immobiliere De L'ouest",
    "wof:placetype":"venue"
},
  "geometry": {"coordinates":[2.304117,48.867886],"type":"Point"}
}