{
  "type": "Feature",
  "properties": {
    "iso:country":"FR",
    "sg:address":"74, Rue S\u00e9bil\u00e9, 09300 Lavelanet",
    "sg:orig_category":"Non-Classified Establishments",
    "sg:phone":"+33 5 61 01 00 79",
    "sg:province":"Midi Pyr\u00e9n\u00e9es",
    "wof:name":"Imprimerie Du Noisetier S.a.",
    "wof:placetype":"venue"
},
  "geometry": {"coordinates":[1.850905,42.935581],"type":"Point"}
}