{
  "type": "Feature",
  "properties": {
    "iso:country":"FR",
    "sg:address":"B.P. 125, 38403 Saint Martin d'H\u00e8res C\u00e9dex^^70, Rue Champ Roman, 38400 Saint Martin d'H\u00e8res",
    "sg:orig_category":"Non-Classified Establishments",
    "sg:phone":"+33 4 76 42 74 87",
    "sg:postcode":"38400",
    "sg:province":"Rhone-Alpes",
    "wof:name":"Alpes M\u00e9taux S.a.r.l.",
    "wof:placetype":"venue"
},
  "geometry": {"coordinates":[5.77712,45.183945],"type":"Point"}
}