{
  "type": "Feature",
  "properties": {
    "iso:country":"FR",
    "sg:address":"3, All\u00e9e Hector Berlioz, 95130 Franconville",
    "sg:orig_category":"Non-Classified Establishments",
    "sg:phone":"+33 1 34 14 96 64",
    "sg:postcode":"95130",
    "sg:province":"Ile de France",
    "wof:name":"Apim Informatique S.a.r.l.",
    "wof:placetype":"venue"
},
  "geometry": {"coordinates":[2.23118,48.986416],"type":"Point"}
}