{
  "type": "Feature",
  "properties": {
    "addr:full":"B.P. 302, 49303 Cholet C\u00e9dex^^64, Rue Alphonse Darmaillarcq, 49300 Cholet Pays de Loire",
    "addr:housenumber":"b.p. 302",
    "addr:postcode":"49303;49300",
    "addr:street":"Rue Alphonse Darmaillarcq",
    "iso:country":"FR",
    "sg:address":"B.P. 302, 49303 Cholet C\u00e9dex^^64, Rue Alphonse Darmaillarcq, 49300 Cholet",
    "sg:orig_category":"Non-Classified Establishments",
    "sg:phone":"+33 2 41 65 26 13",
    "sg:province":"Pays de Loire",
    "wof:name":"Photogravure Choletaise S.a.r.l.",
    "wof:placetype":"venue"
},
  "geometry": {"coordinates":[-0.892689,46.99659],"type":"Point"}
}