{
  "type": "Feature",
  "properties": {
    "iso:country":"FR",
    "sg:address":"18 Rue De L'Ecluse Chette",
    "sg:city":"Coutances",
    "sg:classifiers":[
        {
            "category":"Banks & Credit Unions",
            "subcategory":"Financial Services",
            "type":"Services"
        }
    ],
    "sg:phone":"+33 2 33 07 69 92",
    "sg:postcode":"50200",
    "sg:province":"Basse Normandie",
    "sg:tags":[
        "banking",
        "finance",
        "insurance"
    ],
    "wof:name":"Societe Fiduciaire Nationale D'expertise Comptable Fidexpert (fid)",
    "wof:placetype":"venue"
},
  "geometry": {"coordinates":[-1.45646,49.06229],"type":"Point"}
}