{
  "type": "Feature",
  "properties": {
    "addr:full":"14 R G\u00e9n\u00e9ral Foy 42000 St Etienne Rhone-Alpes 42000",
    "addr:housenumber":"14",
    "addr:postcode":"42000;42000",
    "addr:street":"R Ge\u0301Ne\u0301Ral Foy",
    "iso:country":"FR",
    "sg:address":"14 R G\u00e9n\u00e9ral Foy 42000 St Etienne",
    "sg:classifiers":[
        {
            "category":"Professional",
            "subcategory":"Advertising",
            "type":"Services"
        }
    ],
    "sg:phone":"+33 4 77 49 03 26",
    "sg:postcode":"42000",
    "sg:province":"Rhone-Alpes",
    "sg:tags":[
        "marketing",
        "medium",
        "communication"
    ],
    "wof:name":"Regicom Plus Contact",
    "wof:placetype":"venue"
},
  "geometry": {"coordinates":[4.387674,45.437077],"type":"Point"}
}