{
  "type": "Feature",
  "properties": {
    "iso:country":"FR",
    "sg:address":"B.P. 10026, 60104 Creil C\u00e9dex^^2, Rue Thomas Edison, 60180 Nogent sur Oise",
    "sg:orig_category":"Non-Classified Establishments",
    "sg:phone":"+33 3 44 55 88 00",
    "sg:postcode":"60180",
    "sg:province":"Picardie",
    "wof:name":"Disfruits S.a.",
    "wof:placetype":"venue"
},
  "geometry": {"coordinates":[2.46198,49.278976],"type":"Point"}
}