{
  "type": "Feature",
  "properties": {
    "addr:full":"1, Av. de Gameville, 31650 Saint Orens de Gameville Midi Pyr\u00e9n\u00e9es",
    "addr:postcode":"31650",
    "addr:street":"Av. De Gameville",
    "iso:country":"FR",
    "sg:address":"1, Av. de Gameville, 31650 Saint Orens de Gameville",
    "sg:orig_category":"Non-Classified Establishments",
    "sg:phone":"+33 5 61 00 63 20",
    "sg:province":"Midi Pyr\u00e9n\u00e9es",
    "wof:name":"S\u00e9curmatique S.a.r.l.",
    "wof:placetype":"venue"
},
  "geometry": {"coordinates":[1.53061,43.555958],"type":"Point"}
}