{
  "type": "Feature",
  "properties": {
    "addr:full":"Rte de Bressuire - Les Champs de l'Etang Viennay Poitou-Charentes 79200",
    "addr:postcode":"79200",
    "addr:street":"Rte De Bressuire Les Champs De L'Etang Viennay",
    "iso:country":"FR",
    "sg:address":"Rte de Bressuire - Les Champs de l'Etang",
    "sg:city":"Viennay",
    "sg:orig_category":"Unclassifiable Establishments",
    "sg:phone":"+33 5 49 95 11 99",
    "sg:postcode":"79200",
    "sg:province":"Poitou-Charentes",
    "wof:name":"Teldis Porc S.i.c.a.",
    "wof:placetype":"venue"
},
  "geometry": {"coordinates":[-0.259472,46.674606],"type":"Point"}
}