{
  "type": "Feature",
  "properties": {
    "addr:full":"100 Bis Avenue Charles De Gaulle 77169 Boissy Le Ch\u00e2tel Ile de France",
    "addr:housenumber":"100 bis",
    "addr:postcode":"77169;le;ile",
    "addr:street":"Avenue Charles De Gaulle;Boissy;De France",
    "iso:country":"FR",
    "sg:address":"100 Bis Avenue Charles De Gaulle 77169 Boissy Le Ch\u00e2tel",
    "sg:classifiers":[
        {
            "category":"Wholesale",
            "subcategory":"Machinery & Supplies",
            "type":"Manufacturing & Wholesale Goods"
        }
    ],
    "sg:phone":"+33 1 64 03 87 08",
    "sg:province":"Ile de France",
    "sg:tags":[
        "equipment",
        "optical",
        "precision",
        "instrument"
    ],
    "wof:name":"Atl France",
    "wof:placetype":"venue"
},
  "geometry": {"coordinates":[3.118677,48.817463],"type":"Point"}
}