{
  "type": "Feature",
  "properties": {
    "addr:full":"25, Rue Louis Legrand, 75002 Paris Ile de France 75002",
    "addr:housenumber":"25",
    "addr:postcode":"75002;75002",
    "addr:street":"Rue Louis Legrand",
    "iso:country":"FR",
    "sg:address":"25, Rue Louis Legrand, 75002 Paris",
    "sg:orig_category":"Non-Classified Establishments",
    "sg:phone":"+33 1 40 22 00 89",
    "sg:postcode":"75002",
    "sg:province":"Ile de France",
    "wof:name":"Beijaflore Center S.a.",
    "wof:placetype":"venue"
},
  "geometry": {"coordinates":[2.333946,48.870598],"type":"Point"}
}