{
  "type": "Feature",
  "properties": {
    "addr:full":"11 rue Pastourelle 75003 Paris Ile de France 75003",
    "addr:housenumber":"11",
    "addr:postcode":"75003;75003",
    "addr:street":"Rue Pastourelle",
    "iso:country":"FR",
    "sg:address":"11 rue Pastourelle 75003 Paris",
    "sg:classifiers":[
        {
            "category":"Shopping",
            "subcategory":"Jewelry",
            "type":"Retail Goods"
        }
    ],
    "sg:phone":"+33 1 42 77 91 48",
    "sg:postcode":"75003",
    "sg:province":"Ile de France",
    "sg:tags":[
        "jewellery",
        "gold"
    ],
    "wof:name":"Ste Orfevrerie Daniel Cregut Sa",
    "wof:placetype":"venue"
},
  "geometry": {"coordinates":[2.360567,48.862026],"type":"Point"}
}