{
  "type": "Feature",
  "properties": {
    "addr:full":"560 Rue Jean Chazy 69400 Villefranche Sur Sa\u00f4ne Rhone-Alpes 69400",
    "addr:housenumber":"560",
    "addr:postcode":"69400;69400",
    "addr:street":"Rue Jean Chazy;Rhone-Alpes",
    "iso:country":"FR",
    "sg:address":"560 Rue Jean Chazy 69400 Villefranche Sur Sa\u00f4ne",
    "sg:classifiers":[
        {
            "category":"Manufacturing",
            "subcategory":"Rubber & Plastics",
            "type":"Manufacturing & Wholesale Goods"
        }
    ],
    "sg:phone":"+33 4 74 02 73 20",
    "sg:postcode":"69400",
    "sg:province":"Rhone-Alpes",
    "wof:name":"S.b.t.n. - Partner Plast",
    "wof:placetype":"venue"
},
  "geometry": {"coordinates":[4.74592,45.985161],"type":"Point"}
}