{
  "type": "Feature",
  "properties": {
    "addr:full":"42 All Du Closeau 93160 Noisy Le Grand Ile de France 93160",
    "addr:housenumber":"42",
    "addr:postcode":"93160;93160",
    "addr:street":"All Du Closeau",
    "iso:country":"FR",
    "sg:address":"42 All Du Closeau 93160 Noisy Le Grand",
    "sg:classifiers":[
        {
            "category":"Shopping",
            "type":"Retail Goods"
        }
    ],
    "sg:phone":"+33 1 43 03 75 05",
    "sg:postcode":"93160",
    "sg:province":"Ile de France",
    "sg:tags":[
        "metallurgy",
        "finished",
        "-",
        "metalworking",
        "metallic"
    ],
    "wof:name":"Us Refrigeration Controls Sa",
    "wof:placetype":"venue"
},
  "geometry": {"coordinates":[2.5685,48.836853],"type":"Point"}
}