{
  "type": "Feature",
  "properties": {
    "iso:country":"FR",
    "sg:address":"4 Rue De Verdun Quartier Rebeuval 88300 Neufchateau",
    "sg:classifiers":[
        {
            "category":"Home & Garden",
            "subcategory":"Furniture",
            "type":"Retail Goods"
        }
    ],
    "sg:phone":"+33 3 29 06 09 36",
    "sg:postcode":"88300",
    "sg:province":"Lorraine",
    "sg:tags":[
        "household",
        "wood"
    ],
    "wof:name":"Atelier Du Meuble",
    "wof:placetype":"venue"
},
  "geometry": {"coordinates":[5.69254,48.358501],"type":"Point"}
}