{
  "type": "Feature",
  "properties": {
    "addr:full":"49, Av. de la Gare, 91470 Limours Ile de France 91470",
    "addr:postcode":"91470;91470",
    "addr:street":"49 Av. De La Gare",
    "iso:country":"FR",
    "sg:address":"49, Av. de la Gare, 91470 Limours",
    "sg:orig_category":"Non-Classified Establishments",
    "sg:phone":"+33 1 64 91 00 00",
    "sg:postcode":"91470",
    "sg:province":"Ile de France",
    "wof:name":"Cablisi S.a.r.l.",
    "wof:placetype":"venue"
},
  "geometry": {"coordinates":[2.069928,48.64426],"type":"Point"}
}