{
  "type": "Feature",
  "properties": {
    "addr:full":"18, Rue des Canadiens, 14290 Orbec Orbec Basse Normandie 14290",
    "addr:housenumber":"18",
    "addr:postcode":"14290;14290",
    "addr:street":"Rue Des Canadiens",
    "iso:country":"FR",
    "sg:address":"18, Rue des Canadiens, 14290 Orbec",
    "sg:city":"Orbec",
    "sg:orig_category":"Non-Classified Establishments",
    "sg:phone":"+33 2 31 32 73 97",
    "sg:postcode":"14290",
    "sg:province":"Basse Normandie",
    "wof:name":"U.m.o. S.a.r.l. - Usine M\u00e9tallurgie D'orbec",
    "wof:placetype":"venue"
},
  "geometry": {"coordinates":[0.404244,49.02203],"type":"Point"}
}