{
  "type": "Feature",
  "properties": {
    "iso:country":"FR",
    "sg:address":"547 Rue De La Bergeresse",
    "sg:city":"Des Aulnaies 45160 Olivet",
    "sg:classifiers":[
        {
            "category":"Manufacturing",
            "subcategory":"Printing",
            "type":"Manufacturing & Wholesale Goods"
        }
    ],
    "sg:phone":"+33 2 38 63 63 64",
    "sg:province":"Centre",
    "sg:tags":[
        "publishing"
    ],
    "wof:name":"Db Technique Sa",
    "wof:placetype":"venue"
},
  "geometry": {"coordinates":[1.875266,47.778763],"type":"Point"}
}