{
  "type": "Feature",
  "properties": {
    "iso:country":"FR",
    "sg:address":"16, Bd Gali\u00e9ni, 92230 Gennevilliers",
    "sg:orig_category":"Unclassifiable Establishments",
    "sg:phone":"+33 1 47 90 06 39",
    "sg:province":"Ile de France",
    "wof:name":"C.p.c. S.a. - Compagnie Parisienne Des C\u00e2bles Et Appareils \u00e9le",
    "wof:placetype":"venue"
},
  "geometry": {"coordinates":[2.32452,48.924358],"type":"Point"}
}