{
  "type": "Feature",
  "properties": {
    "iso:country":"FR",
    "sg:address":"5, Rue Barth\u00e9l\u00e9my Thimonnier, 66200 Elne",
    "sg:orig_category":"Non-Classified Establishments",
    "sg:phone":"+33 4 68 37 92 38",
    "sg:province":"Languedoc-Roussillon",
    "wof:name":"Le Tech Emballages S.a.r.l.",
    "wof:placetype":"venue"
},
  "geometry": {"coordinates":[2.982696,42.606895],"type":"Point"}
}