{
  "type": "Feature",
  "properties": {
    "addr:full":"B.P. 20 Chang\u00e9^^Les H\u00eatres 53810 Chang\u00e9 Pays de Loire 53810",
    "addr:postcode":"53810;53810",
    "addr:street":"B.P. 20 Change\u0301^^Les He\u0302Tres",
    "iso:country":"FR",
    "sg:address":"B.P. 20",
    "sg:city":"Chang\u00e9^^Les H\u00eatres 53810 Chang\u00e9",
    "sg:orig_category":"Non-Classified Establishments",
    "sg:phone":"+33 2 43 59 60 10",
    "sg:postcode":"53810",
    "sg:province":"Pays de Loire",
    "wof:name":"S\u00e9ch\u00e9 Transports S.a.r.l.",
    "wof:placetype":"venue"
},
  "geometry": {"coordinates":[-0.789729,48.099052],"type":"Point"}
}