{
  "type": "Feature",
  "properties": {
    "addr:full":"14, Rue Thibault, 52220 Montier en Der Champagne",
    "addr:housenumber":"14",
    "addr:postcode":"52220",
    "addr:street":"Rue Thibault",
    "iso:country":"FR",
    "sg:address":"14, Rue Thibault, 52220 Montier en Der",
    "sg:orig_category":"Unclassifiable Establishments",
    "sg:phone":"+33 3 25 04 21 92",
    "sg:province":"Champagne",
    "wof:name":"Menuiserie Eb\u00e9nisterie Dervoise S.a.r.l.",
    "wof:placetype":"venue"
},
  "geometry": {"coordinates":[4.77181,48.476257],"type":"Point"}
}