{
  "type": "Feature",
  "properties": {
    "iso:country":"FR",
    "sg:address":"5BIS avenue Charles Bras 77184 Emerainville",
    "sg:orig_category":"Fittings, Valves",
    "sg:phone":"+33 1 64 61 65 12",
    "sg:postcode":"77184",
    "sg:province":"Ile de France",
    "wof:name":"Assistance Diffusion Industrielle S.a.r.l.",
    "wof:placetype":"venue"
},
  "geometry": {"coordinates":[2.594965,48.827469],"type":"Point"}
}