{
  "type": "Feature",
  "properties": {
    "addr:full":"5BIS avenue Charles Bras 77184 Emerainville Ile de France 77184",
    "addr:housenumber":"5bis",
    "addr:postcode":"77184;77184",
    "addr:street":"Avenue Charles Bras;Ile De France",
    "iso:country":"FR",
    "sg:address":"5BIS avenue Charles Bras 77184 Emerainville",
    "sg:orig_category":"Fittings, Valves",
    "sg:phone":"+33 1 64 61 65 12",
    "sg:postcode":"77184",
    "sg:province":"Ile de France",
    "wof:name":"Assistance Diffusion Industrielle S.a.r.l.",
    "wof:placetype":"venue"
},
  "geometry": {"coordinates":[2.594965,48.827469],"type":"Point"}
}