{
  "type": "Feature",
  "properties": {
    "addr:full":"B.P. 40647, 57011 Metz C\u00e9dex^^6, Rue de M\u00e9ric, 57000 Metz Lorraine 57000",
    "addr:housenumber":"57011",
    "addr:postcode":"57000;57000",
    "addr:street":"Rue De Me\u0301Ric",
    "iso:country":"FR",
    "sg:address":"B.P. 40647, 57011 Metz C\u00e9dex^^6, Rue de M\u00e9ric, 57000 Metz",
    "sg:orig_category":"Non-Classified Establishments",
    "sg:phone":"+33 3 87 31 81 60",
    "sg:postcode":"57000",
    "sg:province":"Lorraine",
    "wof:name":"C.e.r.i. Antirouille S.a.",
    "wof:placetype":"venue"
},
  "geometry": {"coordinates":[6.183995,49.07645],"type":"Point"}
}