{
  "type": "Feature",
  "properties": {
    "addr:full":"25 Franklin D. Roosevelt; Paris; 75008 Ile de France",
    "addr:housenumber":"25",
    "addr:postcode":"75008 ile",
    "addr:street":"Franklin D. Roosevelt",
    "iso:country":"FR",
    "sg:address":"25",
    "sg:city":"Franklin D. Roosevelt; Paris; 75008",
    "sg:classifiers":[
        {
            "category":"Industrial Area",
            "type":"Public Place"
        }
    ],
    "sg:phone":"+33 1 56 88 78 00",
    "sg:province":"Ile de France",
    "sg:tags":[
        "large",
        "private"
    ],
    "wof:name":"Worms & Cie",
    "wof:placetype":"venue"
},
  "geometry": {"coordinates":[2.309877,48.867012],"type":"Point"}
}