{
  "type": "Feature",
  "properties": {
    "iso:country":"FR",
    "sg:address":"23, Rue Fran\u00e7ois Jacob, 92842 Rueil Malmaison",
    "sg:orig_category":"Non-Classified Establishments",
    "sg:phone":"+33 1 41 96 54 00",
    "sg:province":"Picardie",
    "wof:name":"Fralib S.a.",
    "wof:placetype":"venue"
},
  "geometry": {"coordinates":[3.979421,49.515598],"type":"Point"}
}