{
  "type": "Feature",
  "properties": {
    "addr:full":"Rte D'Orthez 40700 Hagetmau Hagetmau Aquitaine 40700",
    "addr:postcode":"40700;40700",
    "addr:street":"Rte D'Orthez",
    "iso:country":"FR",
    "sg:address":"Rte D'Orthez 40700 Hagetmau",
    "sg:city":"Hagetmau",
    "sg:classifiers":[
        {
            "category":"Home & Garden",
            "subcategory":"Furniture",
            "type":"Retail Goods"
        }
    ],
    "sg:phone":"+33 5 58 79 58 91",
    "sg:postcode":"40700",
    "sg:province":"Aquitaine",
    "sg:tags":[
        "household",
        "wood"
    ],
    "wof:name":"Le Meuble Chalossais",
    "wof:placetype":"venue"
},
  "geometry": {"coordinates":[-0.677991,43.546185],"type":"Point"}
}