{
  "type": "Feature",
  "properties": {
    "iso:country":"FR",
    "sg:address":"82, Rue Jean-Pierre Timbaud, 92400 Courbevoie",
    "sg:orig_category":"Unclassifiable Establishments",
    "sg:phone":"+33 1 46 91 07 77",
    "sg:province":"Ile de France",
    "wof:name":"Overdrive Manuia S.a.",
    "wof:placetype":"venue"
},
  "geometry": {"coordinates":[2.249637,48.900394],"type":"Point"}
}