{
  "type": "Feature",
  "properties": {
    "iso:country":"FR",
    "sg:address":"33126 La Riviere",
    "sg:city":"La Rivi\u00e8re",
    "sg:classifiers":[
        {
            "category":"Wholesale",
            "subcategory":"Machinery & Supplies",
            "type":"Manufacturing & Wholesale Goods"
        }
    ],
    "sg:phone":"+33 5 57 55 56 78",
    "sg:postcode":"33126",
    "sg:province":"Aquitaine",
    "sg:tags":[
        "handling",
        "material",
        "-",
        "machine",
        "equipment",
        "engineering",
        "mechanical"
    ],
    "wof:name":"Richard Sa",
    "wof:placetype":"venue"
},
  "geometry": {"coordinates":[-0.313384,44.936924],"type":"Point"}
}