{
  "type": "Feature",
  "properties": {
    "iso:country":"FR",
    "sg:address":"60 B Rue Jules Michelet 01100 Oyonnax",
    "sg:classifiers":[
        {
            "category":"Manufacturing",
            "subcategory":"Rubber & Plastics",
            "type":"Manufacturing & Wholesale Goods"
        }
    ],
    "sg:phone":"+33 4 74 77 28 14",
    "sg:province":"Rhone-Alpes",
    "wof:name":"Etablissements Cecchini",
    "wof:placetype":"venue"
},
  "geometry": {"coordinates":[5.650889,46.261166],"type":"Point"}
}