{
  "type": "Feature",
  "properties": {
    "addr:full":"136 Chemin De Chapicolle 38330 Montbonnot St Martin Rhone-Alpes 38330",
    "addr:housenumber":"136",
    "addr:postcode":"38330;38330",
    "addr:street":"Chemin De Chapicolle;Montbonnot;Rhone-Alpes",
    "iso:country":"FR",
    "sg:address":"136 Chemin De Chapicolle 38330 Montbonnot St Martin",
    "sg:classifiers":[
        {
            "category":"Health Services",
            "subcategory":"Medical Lab",
            "type":"Services"
        }
    ],
    "sg:phone":"+33 4 76 52 18 28",
    "sg:postcode":"38330",
    "sg:province":"Rhone-Alpes",
    "sg:tags":[
        "chemical",
        "pharmaceutical",
        "pharmacy"
    ],
    "wof:name":"Stabyl",
    "wof:placetype":"venue"
},
  "geometry": {"coordinates":[5.813837,45.234955],"type":"Point"}
}