{
  "type": "Feature",
  "properties": {
    "addr:full":"B.P. 28, 13541 Gardanne C\u00e9dex^^ZI la Palun, 13540 Gardanne Provence-Alpes-C\u00f4te d'Azur",
    "addr:postcode":"13541;13540",
    "addr:street":"B.P. 28",
    "iso:country":"FR",
    "sg:address":"B.P. 28, 13541 Gardanne C\u00e9dex^^ZI la Palun, 13540 Gardanne",
    "sg:orig_category":"Non-Classified Establishments",
    "sg:phone":"+33 4 42 58 37 22",
    "sg:province":"Provence-Alpes-C\u00f4te d'Azur",
    "wof:name":"Les Bois Jullier S.a.",
    "wof:placetype":"venue"
},
  "geometry": {"coordinates":[5.421925,43.582729],"type":"Point"}
}