{
  "type": "Feature",
  "properties": {
    "addr:full":"2, Av. M\u00e9sarmes, 93140 Bondy Ile de France 93140",
    "addr:postcode":"93140;93140",
    "addr:street":"Av. Me\u0301Sarmes",
    "iso:country":"FR",
    "sg:address":"2, Av. M\u00e9sarmes, 93140 Bondy",
    "sg:orig_category":"Non-Classified Establishments",
    "sg:phone":"+33 1 48 48 45 87",
    "sg:postcode":"93140",
    "sg:province":"Ile de France",
    "wof:name":"Elyo S.a.",
    "wof:placetype":"venue"
},
  "geometry": {"coordinates":[2.483328,48.908329],"type":"Point"}
}