{
  "type": "Feature",
  "properties": {
    "addr:full":"B.P. 329, 59026 Lille C\u00e9dex^^16, Place du G\u00e9n\u00e9ral de Gaulle, 59800 Lille Nord Pas-de-Calais",
    "addr:housenumber":"b.p. 329",
    "addr:postcode":"59026;59800",
    "addr:street":"Place Du Ge\u0301Ne\u0301Ral De Gaulle",
    "iso:country":"FR",
    "sg:address":"B.P. 329, 59026 Lille C\u00e9dex^^16, Place du G\u00e9n\u00e9ral de Gaulle, 59800 Lille",
    "sg:orig_category":"Non-Classified Establishments",
    "sg:phone":"+33 3 20 12 33 00",
    "sg:province":"Nord Pas-de-Calais",
    "wof:name":"Transeurope Pologne Consulting S.a.r.l.",
    "wof:placetype":"venue"
},
  "geometry": {"coordinates":[3.08024,50.636189],"type":"Point"}
}