{
  "type": "Feature",
  "properties": {
    "iso:country":"FR",
    "sg:address":"9, Chemin du Parc, 95480 Pierrelaye",
    "sg:orig_category":"Non-Classified Establishments",
    "sg:phone":"+33 1 30 40 77 77",
    "sg:postcode":"95480",
    "sg:province":"Ile de France",
    "wof:name":"Champagnat Groupe Trans. Al S.a.s.",
    "wof:placetype":"venue"
},
  "geometry": {"coordinates":[2.175188,49.017662],"type":"Point"}
}