{
  "type": "Feature",
  "properties": {
    "addr:full":"rue du Pr\u00e9 Magne 69126 Brindas Rhone-Alpes 69126",
    "addr:postcode":"69126;69126",
    "addr:street":"Rue Du Pre\u0301 Magne",
    "iso:country":"FR",
    "sg:address":"rue du Pr\u00e9 Magne 69126 Brindas",
    "sg:classifiers":[
        {
            "category":"Structure",
            "subcategory":"Office Building",
            "type":"Public Place"
        }
    ],
    "sg:phone":"+33 4 78 87 91 82",
    "sg:postcode":"69126",
    "sg:province":"Rhone-Alpes",
    "sg:tags":[
        "industrial",
        "assembly"
    ],
    "wof:name":"Maintenance Instrumentation Regulation Industrielle Scoop",
    "wof:placetype":"venue"
},
  "geometry": {"coordinates":[4.697782,45.718861],"type":"Point"}
}