{
  "type": "Feature",
  "properties": {
    "addr:full":"23 Rue Linois 75015 Paris Ile de France",
    "addr:housenumber":"23",
    "addr:postcode":"75015",
    "addr:street":"Rue Linois",
    "iso:country":"FR",
    "sg:address":"23 Rue Linois 75015 Paris",
    "sg:classifiers":[
        {
            "category":"Professional",
            "subcategory":"Printing & Photocopies",
            "type":"Services"
        }
    ],
    "sg:phone":"+33 1 71 72 45 00",
    "sg:province":"Ile de France",
    "sg:tags":[
        "publishing"
    ],
    "wof:name":"Editions Scientifiques Et Medicales Elsevier Esme (esme)",
    "wof:placetype":"venue"
},
  "geometry": {"coordinates":[2.283569,48.84819],"type":"Point"}
}