{
  "type": "Feature",
  "properties": {
    "addr:full":"5 Rue Du Grand Veymont Zac De Comboire 38130 Echirolles Rhone-Alpes",
    "addr:housenumber":"5",
    "addr:postcode":"38130",
    "addr:street":"Rue Du Grand Veymont Zac De Comboire",
    "iso:country":"FR",
    "sg:address":"5 Rue Du Grand Veymont Zac De Comboire 38130 Echirolles",
    "sg:classifiers":[
        {
            "category":"Professional",
            "subcategory":"Printing & Photocopies",
            "type":"Services"
        }
    ],
    "sg:phone":"+33 4 76 40 20 20",
    "sg:province":"Rhone-Alpes",
    "sg:tags":[
        "publishing"
    ],
    "wof:name":"Editions Didier Richard",
    "wof:placetype":"venue"
},
  "geometry": {"coordinates":[5.7194,45.149536],"type":"Point"}
}