{
  "type": "Feature",
  "properties": {
    "iso:country":"FR",
    "sg:address":"B.P. 53460, 67456 Mundolsheim C\u00e9dex^^4, Rue de l'Industrie, 67116 Reichstett",
    "sg:city":"Reichstett",
    "sg:orig_category":"Non-Classified Establishments",
    "sg:phone":"+33 3 88 18 08 28",
    "sg:postcode":"67116",
    "sg:province":"Alsace",
    "wof:name":"S.v.i. S.a. - Strasbourg V\u00e9hicules Industrie",
    "wof:placetype":"venue"
},
  "geometry": {"coordinates":[7.761792,48.646458],"type":"Point"}
}