{
  "type": "Feature",
  "properties": {
    "iso:country":"FR",
    "sg:address":"5 rue Aristide Berges 82000 Montauban",
    "sg:classifiers":[
        {
            "category":"Banks & Credit Unions",
            "subcategory":"Investment Brokerage",
            "type":"Services"
        }
    ],
    "sg:phone":"+33 5 63 63 75 34",
    "sg:postcode":"82000",
    "sg:province":"Midi Pyr\u00e9n\u00e9es",
    "sg:tags":[
        "aeronautics",
        "accessory"
    ],
    "wof:name":"Normaero S.a.",
    "wof:placetype":"venue"
},
  "geometry": {"coordinates":[1.360819,44.039089],"type":"Point"}
}