{
  "type": "Feature",
  "properties": {
    "iso:country":"FR",
    "sg:address":"La Haute Limougere 37230 FONDETTES",
    "sg:city":"Fondettes",
    "sg:classifiers":[
        {
            "category":"Arts & Performance",
            "subcategory":"Music",
            "type":"Entertainment"
        }
    ],
    "sg:phone":"+33 2 47 49 43 43",
    "sg:postcode":"37230",
    "sg:province":"Centre",
    "sg:tags":[
        "journal",
        "magazine"
    ],
    "wof:name":"Editions Van De Velde S.a.r.l.",
    "wof:placetype":"venue"
},
  "geometry": {"coordinates":[0.622701,47.409626],"type":"Point"}
}