{
  "type": "Feature",
  "properties": {
    "addr:full":"Rue du Bourg Trois Palis Poitou-Charentes 16730",
    "addr:postcode":"16730",
    "addr:street":"Rue Du Bourg Trois Palis",
    "iso:country":"FR",
    "sg:address":"Rue du Bourg",
    "sg:city":"Trois Palis",
    "sg:orig_category":"Non-Classified Establishments",
    "sg:phone":"+33 5 45 91 05 21",
    "sg:postcode":"16730",
    "sg:province":"Poitou-Charentes",
    "wof:name":"Chocolaterie Letuffe S.a.r.l.",
    "wof:placetype":"venue"
},
  "geometry": {"coordinates":[0.055445,45.640057],"type":"Point"}
}