{
  "type": "Feature",
  "properties": {
    "addr:full":"481 Avenue Des Voirons 74800 La Roche Sur Foron Rhone-Alpes",
    "addr:housenumber":"481",
    "addr:postcode":"74800",
    "addr:street":"Avenue Des Voirons",
    "iso:country":"FR",
    "sg:address":"481 Avenue Des Voirons 74800 La Roche Sur Foron",
    "sg:classifiers":[
        {
            "category":"Manufacturing",
            "subcategory":"Rubber & Plastics",
            "type":"Manufacturing & Wholesale Goods"
        }
    ],
    "sg:phone":"+33 4 50 25 17 00",
    "sg:province":"Rhone-Alpes",
    "wof:name":"Decoplast Sa",
    "wof:placetype":"venue"
},
  "geometry": {"coordinates":[6.295745,46.078442],"type":"Point"}
}