{
  "type": "Feature",
  "properties": {
    "addr:full":"264 Av Mend\u00e9s France 83500 La Seyne Sur Mer Aquitaine",
    "addr:postcode":"83500",
    "addr:street":"264 Av Mende\u0301S France",
    "iso:country":"FR",
    "sg:address":"264 Av Mend\u00e9s France 83500 La Seyne Sur Mer",
    "sg:classifiers":[
        {
            "category":"Wholesale",
            "subcategory":"Machinery & Supplies",
            "type":"Manufacturing & Wholesale Goods"
        }
    ],
    "sg:phone":"+33 4 94 94 88 01",
    "sg:province":"Aquitaine",
    "sg:tags":[
        "publishing",
        "-",
        "machine",
        "engineering",
        "printing",
        "mechanical"
    ],
    "wof:name":"Ste De Reprographie Mirog Sarl",
    "wof:placetype":"venue"
},
  "geometry": {"coordinates":[5.874446,43.109447],"type":"Point"}
}