{
  "type": "Feature",
  "properties": {
    "iso:country":"FR",
    "sg:address":"Rue 11 Novembre 21190 Meursault",
    "sg:city":"Meursault",
    "sg:classifiers":[
        {
            "category":"Food Court",
            "type":"Food & Drink"
        }
    ],
    "sg:phone":"+33 3 80 21 22 72",
    "sg:postcode":"21190",
    "sg:province":"Bourgogne",
    "sg:tags":[
        "product",
        "related"
    ],
    "wof:name":"Domaine Bernard Delagrange Et Fils Sarl",
    "wof:placetype":"venue"
},
  "geometry": {"coordinates":[4.76818,46.981419],"type":"Point"}
}