{
  "type": "Feature",
  "properties": {
    "addr:full":"21, Rue du Rocher, 75008 Paris Ile de France",
    "addr:housenumber":"21",
    "addr:postcode":"75008",
    "addr:street":"Rue Du Rocher",
    "iso:country":"FR",
    "sg:address":"21, Rue du Rocher, 75008 Paris",
    "sg:orig_category":"Unclassifiable Establishments",
    "sg:phone":"+33 1 53 42 54 54",
    "sg:province":"Ile de France",
    "wof:name":"Novatrans S.a.",
    "wof:placetype":"venue"
},
  "geometry": {"coordinates":[2.322135,48.876213],"type":"Point"}
}