{
  "type": "Feature",
  "properties": {
    "addr:full":"12 blvd Frederic Mistral; Narbonne; 11108 Midi Pyr\u00e9n\u00e9es",
    "addr:postcode":"11108",
    "addr:street":"12 Blvd",
    "iso:country":"FR",
    "sg:address":"12 blvd Frederic Mistral; Narbonne; 11108",
    "sg:classifiers":[
        {
            "category":"Banks & Credit Unions",
            "subcategory":"Bank",
            "type":"Services"
        }
    ],
    "sg:phone":"+33 4 68 32 48 31",
    "sg:province":"Midi Pyr\u00e9n\u00e9es",
    "wof:name":"Banque De France",
    "wof:placetype":"venue"
},
  "geometry": {"coordinates":[3.001343,43.185543],"type":"Point"}
}