{
  "type": "Feature",
  "properties": {
    "addr:full":"6 Rue Fernand Pelloutier 69200 V\u00e9nissieux Rhone-Alpes 69200",
    "addr:housenumber":"6",
    "addr:postcode":"69200;69200",
    "addr:street":"Rue Fernand Pelloutier",
    "iso:country":"FR",
    "sg:address":"6 Rue Fernand Pelloutier 69200 V\u00e9nissieux",
    "sg:classifiers":[
        {
            "category":"Manufacturing",
            "subcategory":"Metals",
            "type":"Manufacturing & Wholesale Goods"
        }
    ],
    "sg:phone":"+33 4 72 51 51 42",
    "sg:postcode":"69200",
    "sg:province":"Rhone-Alpes",
    "sg:tags":[
        "metallurgy",
        "steel",
        "metalworking"
    ],
    "wof:name":"Tabourin Et Bezile Sa",
    "wof:placetype":"venue"
},
  "geometry": {"coordinates":[4.900579,45.690624],"type":"Point"}
}