{
  "type": "Feature",
  "properties": {
    "addr:full":"23, Av Michoneau, 62000 Arras Nord Pas-de-Calais",
    "addr:postcode":"62000",
    "addr:street":"23 Av Michoneau",
    "iso:country":"FR",
    "sg:address":"23, Av Michoneau, 62000 Arras",
    "sg:orig_category":"Non-Classified Establishments",
    "sg:phone":"+33 3 21 55 48 59",
    "sg:province":"Nord Pas-de-Calais",
    "wof:name":"Thueux S.a.r.l.",
    "wof:placetype":"venue"
},
  "geometry": {"coordinates":[2.782741,50.295837],"type":"Point"}
}