{
  "type": "Feature",
  "properties": {
    "iso:country":"FR",
    "sg:address":"99 Avenue Gabriel Peri",
    "sg:city":"St Ouen",
    "sg:classifiers":[
        {
            "category":"Banks & Credit Unions",
            "subcategory":"Financial Services",
            "type":"Services"
        }
    ],
    "sg:phone":"+33 1 40 11 12 12",
    "sg:postcode":"93400",
    "sg:province":"Ile de France",
    "sg:tags":[
        "banking",
        "finance",
        "insurance"
    ],
    "wof:name":"Credit Du Nord",
    "wof:placetype":"venue"
},
  "geometry": {"coordinates":[2.331322,48.903984],"type":"Point"}
}