{
  "type": "Feature",
  "properties": {
    "iso:country":"FR",
    "sg:address":"4, Rue Rigord, 13007 Marseille",
    "sg:orig_category":"Non-Classified Establishments",
    "sg:phone":"+33 4 91 54 04 40",
    "sg:province":"Poitou-Charentes",
    "wof:name":"Gestion Synth\u00e8se S.a.r.l.",
    "wof:placetype":"venue"
},
  "geometry": {"coordinates":[5.36068,43.283264],"type":"Point"}
}