{
  "type": "Feature",
  "properties": {
    "addr:full":"Rue de Creil - Val d'Aunette Senlis Picardie 60300",
    "addr:postcode":"60300",
    "addr:street":"Rue De Creil Val D'Aunette",
    "iso:country":"FR",
    "sg:address":"Rue de Creil - Val d'Aunette",
    "sg:city":"Senlis",
    "sg:orig_category":"Unclassifiable Establishments",
    "sg:phone":"+33 3 44 63 84 00",
    "sg:postcode":"60300",
    "sg:province":"Picardie",
    "wof:name":"Socotec S.a.",
    "wof:placetype":"venue"
},
  "geometry": {"coordinates":[2.62101,49.187401],"type":"Point"}
}