{
  "type": "Feature",
  "properties": {
    "iso:country":"FR",
    "sg:address":"B.P. 83, 67020 Strasbourg C\u00e9dex^^10, Rue de Saint Nazaire, 67100 Strasbourg",
    "sg:city":"Strasbourg",
    "sg:orig_category":"Aluminium, Barres d' Aluminium, Demi-produits en Menuiserie aluminium T\u00f4lerie en aluminium",
    "sg:phone":"+33 3 88 79 10 00",
    "sg:postcode":"67100",
    "sg:province":"Alsace",
    "wof:name":"Groupe Rc System Aleurope",
    "wof:placetype":"venue"
},
  "geometry": {"coordinates":[7.76865,48.534969],"type":"Point"}
}