{
  "type": "Feature",
  "properties": {
    "addr:full":"avenue de Flore 95500 Le Thillay Ile de France",
    "addr:postcode":"95500",
    "addr:street":"Avenue De Flore",
    "iso:country":"FR",
    "sg:address":"avenue de Flore 95500 Le Thillay",
    "sg:classifiers":[
        {
            "category":"Wholesale",
            "subcategory":"Metals & Minerals",
            "type":"Manufacturing & Wholesale Goods"
        }
    ],
    "sg:phone":"+33 1 39 92 81 16",
    "sg:province":"Ile de France",
    "sg:tags":[
        "alloy",
        "tin"
    ],
    "wof:name":"Etain Soudure",
    "wof:placetype":"venue"
},
  "geometry": {"coordinates":[2.48032,48.997589],"type":"Point"}
}