{
  "type": "Feature",
  "properties": {
    "addr:full":"16, Av. de Belgique, 08700 La Grandville Gespunsart Champagne 08700",
    "addr:postcode":"08700;08700",
    "addr:street":"16 Av. De Belgique;Champagne",
    "iso:country":"FR",
    "sg:address":"16, Av. de Belgique, 08700 La Grandville",
    "sg:city":"Gespunsart",
    "sg:orig_category":"Non-Classified Establishments",
    "sg:phone":"+33 3 24 37 72 17",
    "sg:postcode":"08700",
    "sg:province":"Champagne",
    "wof:name":"Sassi S.a.r.l.",
    "wof:placetype":"venue"
},
  "geometry": {"coordinates":[4.797022,49.780605],"type":"Point"}
}