{
  "type": "Feature",
  "properties": {
    "addr:full":"18 Quai Paimpolais; Ile de Sein Paimpol Bretagne 22500",
    "addr:housenumber":"18",
    "addr:postcode":"22500",
    "addr:street":"Quai Paimpolais Ile De Sein Paimpol Bretagne",
    "iso:country":"FR",
    "sg:address":"18 Quai Paimpolais; Ile de Sein",
    "sg:city":"Paimpol",
    "sg:classifiers":[
        {
            "category":"Banks & Credit Unions",
            "subcategory":"Bank",
            "type":"Services"
        }
    ],
    "sg:phone":"+33 3398709025",
    "sg:postcode":"22500",
    "sg:province":"Bretagne",
    "wof:name":"Cr\u00e9dit Agricole Mutuel",
    "wof:placetype":"venue"
},
  "geometry": {"coordinates":[-4.854337,48.037876],"type":"Point"}
}