{
  "type": "Feature",
  "properties": {
    "addr:full":"Rte de Vitry - Pont SNCF Reims Champagne 51100",
    "addr:postcode":"51100",
    "addr:street":"Rte De Vitry Pont Sncf;Champagne",
    "iso:country":"FR",
    "sg:address":"Rte de Vitry - Pont SNCF",
    "sg:city":"Reims",
    "sg:orig_category":"Non-Classified Establishments",
    "sg:phone":"+33 3 26 89 08 48",
    "sg:postcode":"51100",
    "sg:province":"Champagne",
    "wof:name":"Sodiceram S.a.r.l.",
    "wof:placetype":"venue"
},
  "geometry": {"coordinates":[4.028445,49.26284],"type":"Point"}
}