{
  "type": "Feature",
  "properties": {
    "addr:full":"B.P. 21, 35530 Noyal sur Vilaine^^Rte de Paris, 35530 Noyal sur Vilaine Br\u00e9c\u00e9 Bretagne 35530",
    "addr:postcode":"35530;35530;35530",
    "addr:street":"B.P. 21;Noyal;Bre\u0301Ce\u0301 Bretagne",
    "iso:country":"FR",
    "sg:address":"B.P. 21, 35530 Noyal sur Vilaine^^Rte de Paris, 35530 Noyal sur Vilaine",
    "sg:city":"Br\u00e9c\u00e9",
    "sg:orig_category":"Non-Classified Establishments",
    "sg:phone":"+33 2 99 04 12 12",
    "sg:postcode":"35530",
    "sg:province":"Bretagne",
    "wof:name":"Team Ouest S.a.",
    "wof:placetype":"venue"
},
  "geometry": {"coordinates":[-1.521279,48.110287],"type":"Point"}
}