{
  "type": "Feature",
  "properties": {
    "iso:country":"FR",
    "sg:address":"7, Rue Bouret, 75019 Paris",
    "sg:orig_category":"Non-Classified Establishments",
    "sg:phone":"+33 1 42 08 76 96",
    "sg:postcode":"75019",
    "sg:province":"Ile de France",
    "wof:name":"A.c.m.i. S.a. - Ateliers De Construction De Moules Industriels",
    "wof:placetype":"venue"
},
  "geometry": {"coordinates":[2.375617,48.880783],"type":"Point"}
}