{
  "type": "Feature",
  "properties": {
    "iso:country":"FR",
    "sg:address":"1 Rue De Haarlem 59200 Tourcoing",
    "sg:classifiers":[
        {
            "category":"Autos & Motor Vehicles",
            "subcategory":"Automobile Sales",
            "type":"Retail Goods"
        }
    ],
    "sg:phone":"+33 3 20 28 10 10",
    "sg:province":"Nord Pas-de-Calais",
    "sg:tags":[
        "equipment",
        "transport"
    ],
    "wof:name":"Manubob Industrie",
    "wof:placetype":"venue"
},
  "geometry": {"coordinates":[3.132923,50.719635],"type":"Point"}
}