{
  "type": "Feature",
  "properties": {
    "addr:full":"69, Rue de Paris, 92110 Clichy Ile de France",
    "addr:housenumber":"69",
    "addr:postcode":"92110",
    "addr:street":"Rue De Paris;Ile De France",
    "iso:country":"FR",
    "sg:address":"69, Rue de Paris, 92110 Clichy",
    "sg:orig_category":"Non-Classified Establishments",
    "sg:phone":"+33 1 47 31 98 63",
    "sg:province":"Ile de France",
    "wof:name":"Star Auto Export S.a.r.l.",
    "wof:placetype":"venue"
},
  "geometry": {"coordinates":[2.304452,48.900043],"type":"Point"}
}