{
  "type": "Feature",
  "properties": {
    "addr:full":"B.P. 19 Saint Rambert d'Albon C\u00e9dex^^26140 Anneyron Rhone-Alpes 26140",
    "addr:housenumber":"19",
    "addr:postcode":"26140",
    "addr:street":"B.P.;Saint Rambert D'Albon Ce\u0301Dex^^26140;Rhone-Alpes",
    "iso:country":"FR",
    "sg:address":"B.P. 19",
    "sg:city":"Saint Rambert d'Albon C\u00e9dex^^26140 Anneyron",
    "sg:orig_category":"Non-Classified Establishments",
    "sg:phone":"+33 4 75 31 66 66",
    "sg:postcode":"26140",
    "sg:province":"Rhone-Alpes",
    "wof:name":"Rodet Loisirs S.a.",
    "wof:placetype":"venue"
},
  "geometry": {"coordinates":[4.866955,45.249264],"type":"Point"}
}