{
  "type": "Feature",
  "properties": {
    "addr:full":"Grands Pr\u00e9s des Vouards 74140 Saint Cergues Rhone-Alpes 74140",
    "addr:postcode":"74140 saint cergues rhone-alpes 74140",
    "iso:country":"FR",
    "sg:address":"Grands Pr\u00e9s des Vouards 74140 Saint Cergues",
    "sg:orig_category":"Unclassifiable Establishments",
    "sg:phone":"+33 4 50 43 51 01",
    "sg:postcode":"74140",
    "sg:province":"Rhone-Alpes",
    "wof:name":"Rocland Rh\u00f4ne Alpes S.a.s.",
    "wof:placetype":"venue"
},
  "geometry": {"coordinates":[6.314533,46.228855],"type":"Point"}
}