{
  "type": "Feature",
  "properties": {
    "addr:full":"B.P. 127, 44703 Orvault C\u00e9dex^^15, Av. de la Jeunesse, 44700 Orvault Pays de Loire 44700",
    "addr:housenumber":"b.p. 127",
    "addr:postcode":"44703;44700;44700",
    "addr:street":"Av. De La Jeunesse",
    "iso:country":"FR",
    "sg:address":"B.P. 127, 44703 Orvault C\u00e9dex^^15, Av. de la Jeunesse, 44700 Orvault",
    "sg:orig_category":"Non-Classified Establishments",
    "sg:phone":"+33 2 40 67 05 00",
    "sg:postcode":"44700",
    "sg:province":"Pays de Loire",
    "wof:name":"Caisse D'epargne Pays De La Loire",
    "wof:placetype":"venue"
},
  "geometry": {"coordinates":[-1.623129,47.270981],"type":"Point"}
}