{
  "type": "Feature",
  "properties": {
    "addr:full":"Zi La Gane Lachaud 19140 Uzerche Limousin",
    "addr:postcode":"19140",
    "addr:street":"Zi La Gane Lachaud",
    "iso:country":"FR",
    "sg:address":"Zi La Gane Lachaud 19140 Uzerche",
    "sg:classifiers":[
        {
            "category":"Manufacturing",
            "subcategory":"Paper Products",
            "type":"Manufacturing & Wholesale Goods"
        }
    ],
    "sg:phone":"+33 5 55 73 25 01",
    "sg:province":"Limousin",
    "sg:tags":[
        "raw",
        "material",
        "-",
        "cardboard"
    ],
    "wof:name":"Smurfit Uzerche",
    "wof:placetype":"venue"
},
  "geometry": {"coordinates":[1.56594,45.426266],"type":"Point"}
}