{
  "type": "Feature",
  "properties": {
    "addr:full":"928, Av. du G\u00e9n\u00e9ral de Gaulle, 14200 H\u00e9rouville Saint Clair H\u00e9rouville-Saint-Clair Basse Normandie 14200",
    "addr:housenumber":"928",
    "addr:postcode":"14200;14200",
    "addr:street":"Av. Du Ge\u0301Ne\u0301Ral De Gaulle;Clair;Basse",
    "iso:country":"FR",
    "sg:address":"928, Av. du G\u00e9n\u00e9ral de Gaulle, 14200 H\u00e9rouville Saint Clair",
    "sg:city":"H\u00e9rouville-Saint-Clair",
    "sg:orig_category":"Unclassifiable Establishments",
    "sg:phone":"+33 2 31 47 15 15",
    "sg:postcode":"14200",
    "sg:province":"Basse Normandie",
    "wof:name":"Laboratoires Gilbert S.a.",
    "wof:placetype":"venue"
},
  "geometry": {"coordinates":[-0.34539,49.209435],"type":"Point"}
}