{
  "type": "Feature",
  "properties": {
    "addr:full":"155 Rue Amp\u00e8re 36000 Chateauroux Ch\u00e2teauroux Centre 36000",
    "addr:housenumber":"155",
    "addr:postcode":"36000;36000",
    "addr:street":"Rue Ampe\u0300Re;Cha\u0302Teauroux",
    "iso:country":"FR",
    "sg:address":"155 Rue Amp\u00e8re 36000 Chateauroux",
    "sg:city":"Ch\u00e2teauroux",
    "sg:classifiers":[
        {
            "category":"Professional",
            "subcategory":"Engineering",
            "type":"Services"
        }
    ],
    "sg:phone":"+33 2 54 27 03 04",
    "sg:postcode":"36000",
    "sg:province":"Centre",
    "sg:tags":[
        "machine",
        "-",
        "mechanical"
    ],
    "wof:name":"Brossette Bti",
    "wof:placetype":"venue"
},
  "geometry": {"coordinates":[1.720826,46.813492],"type":"Point"}
}