{
  "type": "Feature",
  "properties": {
    "addr:full":"73 Bd Joffre 17000 La Rochelle Cedex Poitou-Charentes 17000",
    "addr:housenumber":"73",
    "addr:postcode":"17000;17000",
    "addr:street":"Bd Joffre",
    "iso:country":"FR",
    "sg:address":"73 Bd Joffre 17000 La Rochelle Cedex",
    "sg:classifiers":[
        {
            "category":"Food Court",
            "type":"Food & Drink"
        }
    ],
    "sg:phone":"+33 5 46 27 16 12",
    "sg:postcode":"17000",
    "sg:province":"Poitou-Charentes",
    "sg:tags":[
        "product",
        "related"
    ],
    "wof:name":"Elidis Boissons Services",
    "wof:placetype":"venue"
},
  "geometry": {"coordinates":[-1.142241,46.157578],"type":"Point"}
}