{
  "type": "Feature",
  "properties": {
    "addr:full":"158, Rue de Lille, 59200 Tourcoing Nord Pas-de-Calais",
    "addr:housenumber":"158",
    "addr:postcode":"59200",
    "addr:street":"Rue De Lille",
    "iso:country":"FR",
    "sg:address":"158, Rue de Lille, 59200 Tourcoing",
    "sg:orig_category":"Unclassifiable Establishments",
    "sg:phone":"+33 3 20 26 66 30",
    "sg:province":"Nord Pas-de-Calais",
    "wof:name":"Dhalluin Tourcoing S.a.",
    "wof:placetype":"venue"
},
  "geometry": {"coordinates":[3.148401,50.723293],"type":"Point"}
}