{
  "type": "Feature",
  "properties": {
    "addr:full":"4, Rue de Mayotte - ZAC de Courtaboeuf, 91955 Courtaboeuf C\u00e9dex Champagne",
    "addr:housenumber":"4",
    "addr:postcode":"91955",
    "addr:street":"Rue De Mayotte Zac De Courtaboeuf",
    "iso:country":"FR",
    "sg:address":"4, Rue de Mayotte - ZAC de Courtaboeuf, 91955 Courtaboeuf C\u00e9dex",
    "sg:orig_category":"Non-Classified Establishments",
    "sg:phone":"+33 1 60 92 38 10",
    "sg:province":"Champagne",
    "wof:name":"D.m.a.e.e. S.a. - Distribution Et Montage D'accessoires Electroniqu",
    "wof:placetype":"venue"
},
  "geometry": {"coordinates":[-1.163661,44.388096],"type":"Point"}
}