{
  "type": "Feature",
  "properties": {
    "addr:full":"Rue de la Vieille Poste - PIT de la Pompignane - B\u00e2t. T2 Montpellier C\u00e9dex 1 Aquitaine 34055",
    "addr:housenumber":"t2;1",
    "addr:postcode":"34055",
    "addr:street":"Rue De La;Ce\u0301Dex",
    "iso:country":"FR",
    "sg:address":"Rue de la Vieille Poste - PIT de la Pompignane - B\u00e2t. T2",
    "sg:city":"Montpellier C\u00e9dex 1",
    "sg:orig_category":"Non-Classified Establishments",
    "sg:phone":"+33 4 67 99 61 95",
    "sg:postcode":"34055",
    "sg:province":"Aquitaine",
    "wof:name":"A2c S.a.r.l.",
    "wof:placetype":"venue"
},
  "geometry": {"coordinates":[3.87927,43.608528],"type":"Point"}
}