{
  "type": "Feature",
  "properties": {
    "addr:full":"92 Vall\u00e9e 76600 Havre (Le) Haute Normandie 76600",
    "addr:housenumber":"92",
    "addr:postcode":"76600;76600",
    "addr:street":"Valle\u0301E;Haute",
    "iso:country":"FR",
    "sg:address":"92",
    "sg:city":"Vall\u00e9e 76600 Havre (Le)",
    "sg:classifiers":[
        {
            "category":"Shopping",
            "type":"Retail Goods"
        }
    ],
    "sg:phone":"+33 2 35 24 03 03",
    "sg:postcode":"76600",
    "sg:province":"Haute Normandie",
    "sg:tags":[
        "metallurgy",
        "finished",
        "-",
        "metalworking",
        "metallic"
    ],
    "wof:name":"Cis Services",
    "wof:placetype":"venue"
},
  "geometry": {"coordinates":[0.154389,49.49456],"type":"Point"}
}