{
  "type": "Feature",
  "properties": {
    "addr:full":"3, Rue Descartes - Parc d'Activit\u00e9s de Treilli\u00e8res, 44119 Treilli\u00e8res Pays de Loire",
    "addr:housenumber":"3",
    "addr:postcode":"44119",
    "addr:street":"Rue Descartes Parc D'Activite \u0301S De Treillie\u0300Res",
    "iso:country":"FR",
    "sg:address":"3, Rue Descartes - Parc d'Activit\u00e9s de Treilli\u00e8res, 44119 Treilli\u00e8res",
    "sg:orig_category":"Unclassifiable Establishments",
    "sg:phone":"+33 2 28 01 25 25",
    "sg:province":"Pays de Loire",
    "wof:name":"Airflux B.p.l. S.a.",
    "wof:placetype":"venue"
},
  "geometry": {"coordinates":[-1.589245,47.277042],"type":"Point"}
}