{
  "type": "Feature",
  "properties": {
    "addr:full":"Av. des Carri\u00e8res - ZI la Plaine du Caire Roquefort la Bedoule Alsace 13830",
    "addr:postcode":"13830",
    "addr:street":"Av. Des Carrie\u0300Res Zi La Plaine Du Caire;La Bedoule",
    "iso:country":"FR",
    "sg:address":"Av. des Carri\u00e8res - ZI la Plaine du Caire",
    "sg:city":"Roquefort la Bedoule",
    "sg:orig_category":"Non-Classified Establishments",
    "sg:phone":"+33 4 42 73 10 18",
    "sg:postcode":"13830",
    "sg:province":"Alsace",
    "wof:name":"S.b.r. Construction S.a.r.l.",
    "wof:placetype":"venue"
},
  "geometry": {"coordinates":[5.589952,43.247658],"type":"Point"}
}