{
  "type": "Feature",
  "properties": {
    "addr:full":"B.P. 46, 44142 Ch\u00e2teaubriant C\u00e9dex^^8, Rue Michel Grimaud, 44140 Ch\u00e2teaubriant Pays de Loire 44140",
    "addr:postcode":"44142;44140;44140",
    "addr:street":"B.P. 46;Rue Michel Grimaud",
    "iso:country":"FR",
    "sg:address":"B.P. 46, 44142 Ch\u00e2teaubriant C\u00e9dex^^8, Rue Michel Grimaud, 44140 Ch\u00e2teaubriant",
    "sg:orig_category":"Non-Classified Establishments",
    "sg:phone":"+33 2 40 81 21 85",
    "sg:postcode":"44140",
    "sg:province":"Pays de Loire",
    "wof:name":"Caisse D'epargne Pr\u00e9voyance Pays De Loire",
    "wof:placetype":"venue"
},
  "geometry": {"coordinates":[-1.426909,47.009285],"type":"Point"}
}