{
  "type": "Feature",
  "properties": {
    "iso:country":"FR",
    "sg:address":"B.P. 10, 29610 Plouigneau^^ZI de Kerbriand, 29610 Plouigneau",
    "sg:city":"Plouigneau",
    "sg:orig_category":"Non-Classified Establishments",
    "sg:phone":"+33 2 98 79 81 00",
    "sg:postcode":"29610",
    "sg:province":"Bretagne",
    "wof:name":"Agrimages S.a.r.l.",
    "wof:placetype":"venue"
},
  "geometry": {"coordinates":[-3.651184,48.565731],"type":"Point"}
}