{
  "type": "Feature",
  "properties": {
    "iso:country":"FR",
    "sg:address":"Les Abattoirs",
    "sg:city":"Lubersac",
    "sg:orig_category":"Unclassifiable Establishments",
    "sg:phone":"+33 5 55 73 52 74",
    "sg:postcode":"19210",
    "sg:province":"Limousin",
    "wof:name":"Ducloux S.a.",
    "wof:placetype":"venue"
},
  "geometry": {"coordinates":[1.450631,45.431385],"type":"Point"}
}