{
  "type": "Feature",
  "properties": {
    "addr:full":"46, Av. du Mar\u00e9chal Leclerc, 71300 Montceau les Mines Saint-Berain-sous-Sanvignes Bourgogne 71300",
    "addr:postcode":"71300;71300",
    "addr:street":"46 Av. Du Mare\u0301Chal Leclerc;Bourgogne",
    "iso:country":"FR",
    "sg:address":"46, Av. du Mar\u00e9chal Leclerc, 71300 Montceau les Mines",
    "sg:city":"Saint-Berain-sous-Sanvignes",
    "sg:orig_category":"Unclassifiable Establishments",
    "sg:phone":"+33 3 85 57 30 66",
    "sg:postcode":"71300",
    "sg:province":"Bourgogne",
    "wof:name":"Badet S.a.",
    "wof:placetype":"venue"
},
  "geometry": {"coordinates":[4.370453,46.681412],"type":"Point"}
}