{
  "type": "Feature",
  "properties": {
    "addr:full":"rue Amp\u00e8re 81000 Albi Midi Pyr\u00e9n\u00e9es 81000",
    "addr:postcode":"81000;81000",
    "addr:street":"Rue Ampe\u0300Re",
    "iso:country":"FR",
    "sg:address":"rue Amp\u00e8re 81000 Albi",
    "sg:classifiers":[
        {
            "category":"Food & Beverages",
            "subcategory":"Specialty",
            "type":"Retail Goods"
        }
    ],
    "sg:phone":"+33 5 63 46 02 24",
    "sg:postcode":"81000",
    "sg:province":"Midi Pyr\u00e9n\u00e9es",
    "sg:tags":[
        "supplement",
        "additive"
    ],
    "wof:name":"Tsi S.a.r.l.",
    "wof:placetype":"venue"
},
  "geometry": {"coordinates":[2.194719,43.926815],"type":"Point"}
}