{
  "type": "Feature",
  "properties": {
    "iso:country":"FR",
    "sg:address":"14 pl Eug\u00e8ne Forest; Plouguin; 29830",
    "sg:city":"Plouguin",
    "sg:classifiers":[
        {
            "category":"Banks & Credit Unions",
            "subcategory":"Bank",
            "type":"Services"
        }
    ],
    "sg:phone":"+33 2 98 89 26 79",
    "sg:postcode":"29830",
    "sg:province":"Bretagne",
    "wof:name":"Cr\u00e9dit Mutuel De Bretagne",
    "wof:placetype":"venue"
},
  "geometry": {"coordinates":[-4.598405,48.525349],"type":"Point"}
}