{
  "type": "Feature",
  "properties": {
    "addr:full":"27, Rue de la Carri\u00e8re, 35000 Rennes Rennes Bretagne 35000",
    "addr:housenumber":"27",
    "addr:postcode":"35000;35000",
    "addr:street":"Rue De La Carrie\u0300Re",
    "iso:country":"FR",
    "sg:address":"27, Rue de la Carri\u00e8re, 35000 Rennes",
    "sg:city":"Rennes",
    "sg:orig_category":"Unclassifiable Establishments",
    "sg:phone":"+33 2 99 59 22 78",
    "sg:postcode":"35000",
    "sg:province":"Bretagne",
    "wof:name":"Jean Et Volailles Tradition S.a.",
    "wof:placetype":"venue"
},
  "geometry": {"coordinates":[-1.700162,48.109287],"type":"Point"}
}