{
  "type": "Feature",
  "properties": {
    "addr:full":"B.P. 5, 24610 Villefranche de Lonchat^^Cave du Vigneron Gurson en P\u00e9rigord, 24610 Carsac de Gurson Carsac-de-Gurson Aquitaine 24610",
    "addr:housenumber":"5",
    "addr:postcode":"24610;24610;24610",
    "addr:street":"B.P.",
    "iso:country":"FR",
    "sg:address":"B.P. 5, 24610 Villefranche de Lonchat^^Cave du Vigneron Gurson en P\u00e9rigord, 24610 Carsac de Gurson",
    "sg:city":"Carsac-de-Gurson",
    "sg:orig_category":"Non-Classified Establishments",
    "sg:phone":"+33 5 53 82 81 50",
    "sg:postcode":"24610",
    "sg:province":"Aquitaine",
    "wof:name":"La Grappe De Gurson",
    "wof:placetype":"venue"
},
  "geometry": {"coordinates":[0.183472,44.908039],"type":"Point"}
}