{
  "type": "Feature",
  "properties": {
    "addr:full":"41, Rue de la Scierie, 88800 Vittel Lorraine",
    "addr:housenumber":"41",
    "addr:postcode":"88800",
    "addr:street":"Rue De La Scierie",
    "iso:country":"FR",
    "sg:address":"41, Rue de la Scierie, 88800 Vittel",
    "sg:orig_category":"Unclassifiable Establishments",
    "sg:phone":"+33 3 83 15 20 00",
    "sg:province":"Lorraine",
    "wof:name":"Arnould Gaston S.a.",
    "wof:placetype":"venue"
},
  "geometry": {"coordinates":[5.9599,48.200096],"type":"Point"}
}