{
  "type": "Feature",
  "properties": {
    "addr:full":"51 Av Jean Jaur\u00e8s 92120 Montrouge Ile de France 92120",
    "addr:postcode":"92120;92120",
    "addr:street":"51 Av Jean Jaure\u0300S",
    "iso:country":"FR",
    "sg:address":"51 Av Jean Jaur\u00e8s 92120 Montrouge",
    "sg:classifiers":[
        {
            "category":"Shopping",
            "subcategory":"Computers & Home Electronics",
            "type":"Retail Goods"
        }
    ],
    "sg:phone":"+33 1 46 00 61 11",
    "sg:postcode":"92120",
    "sg:province":"Ile de France",
    "sg:tags":[
        "electronic",
        "electrical",
        "equipment"
    ],
    "wof:name":"Alsthom Sa",
    "wof:placetype":"venue"
},
  "geometry": {"coordinates":[2.31439,48.816887],"type":"Point"}
}