{
  "type": "Feature",
  "properties": {
    "addr:full":"34965 Montpellier C\u00e9dex 2^^16, Bd d'Orient - R\u00e9sidence Am\u00e9thyste, 34000 Montpellier Languedoc-Roussillon 34000",
    "addr:housenumber":"2 ^ ^ 16;d'orient re\u0301sidence",
    "addr:postcode":"34965;34000;34000",
    "addr:street":"Ce\u0301Dex;Bd;Ame\u0301Thyste",
    "iso:country":"FR",
    "sg:address":"34965 Montpellier C\u00e9dex 2^^16, Bd d'Orient - R\u00e9sidence Am\u00e9thyste, 34000 Montpellier",
    "sg:orig_category":"Non-Classified Establishments",
    "sg:phone":"+33 4 67 65 01 82",
    "sg:postcode":"34000",
    "sg:province":"Languedoc-Roussillon",
    "wof:name":"Adhara Informatique S.a.",
    "wof:placetype":"venue"
},
  "geometry": {"coordinates":[3.89005,43.6035],"type":"Point"}
}