{
  "type": "Feature",
  "properties": {
    "addr:full":"B.P. 50905, 95922 Roissy CDG C\u00e9dex^^22, Av. des Nations - Paris Nord II - B\u00e2t. Le Rimbaud, 93420 Vil Ile de France 93420",
    "addr:housenumber":"ba\u0302t",
    "addr:postcode":"95922;93420;93420",
    "addr:street":"Av. Des Nations Paris;Vil Ile De France",
    "iso:country":"FR",
    "sg:address":"B.P. 50905, 95922 Roissy CDG C\u00e9dex^^22, Av. des Nations - Paris Nord II - B\u00e2t. Le Rimbaud, 93420 Vil",
    "sg:orig_category":"Non-Classified Establishments",
    "sg:phone":"+33 1 49 89 84 00",
    "sg:postcode":"93420",
    "sg:province":"Ile de France",
    "wof:name":"Downe Egberts Coffee Systems France S.n.c.",
    "wof:placetype":"venue"
},
  "geometry": {"coordinates":[2.53979,48.955807],"type":"Point"}
}