{
  "type": "Feature",
  "properties": {
    "addr:full":"100, Rte de Versailles, 78163 Marly le Roi \u00cele-de-France",
    "addr:housenumber":"100",
    "addr:postcode":"78163",
    "addr:street":"Rte De Versailles",
    "iso:country":"FR",
    "sg:address":"100, Rte de Versailles, 78163 Marly le Roi",
    "sg:orig_category":"Non-Classified Establishments",
    "sg:phone":"+33 1 39 17 80 00",
    "sg:province":"\u00cele-de-France",
    "wof:name":"Laboratoire Glaxo Smitch Cline S.a.s.",
    "wof:placetype":"venue"
},
  "geometry": {"coordinates":[2.10316,48.872021],"type":"Point"}
}