{
  "type": "Feature",
  "properties": {
    "iso:country":"FR",
    "sg:address":"130, Rue du Vernois, 25700 Valentigney",
    "sg:orig_category":"Unclassifiable Establishments",
    "sg:phone":"+33 3 81 36 12 12",
    "sg:province":"Franche Comt\u00e9",
    "wof:name":"Transports Vecatel S.a.",
    "wof:placetype":"venue"
},
  "geometry": {"coordinates":[6.833936,47.451809],"type":"Point"}
}