{
  "type": "Feature",
  "properties": {
    "addr:full":"Rue De Tumulus 64121 Serres Castet Montardon Aquitaine 64121",
    "addr:postcode":"64121;64121",
    "addr:street":"Rue De Tumulus",
    "iso:country":"FR",
    "sg:address":"Rue De Tumulus 64121 Serres Castet",
    "sg:city":"Montardon",
    "sg:classifiers":[
        {
            "category":"Shopping",
            "subcategory":"Clothing, Apparel, & Fashions",
            "type":"Retail Goods"
        }
    ],
    "sg:phone":"+33 5 59 33 20 19",
    "sg:postcode":"64121",
    "sg:province":"Aquitaine",
    "sg:tags":[
        "textile",
        "clothing",
        "clothes"
    ],
    "wof:name":"Jaero Sa",
    "wof:placetype":"venue"
},
  "geometry": {"coordinates":[-0.382634,43.374271],"type":"Point"}
}