{
  "type": "Feature",
  "properties": {
    "addr:full":"ZA La Pagerie Moncetz Longevas Champagne 51470",
    "addr:postcode":"51470",
    "addr:street":"Za La;Champagne",
    "iso:country":"FR",
    "sg:address":"ZA La Pagerie",
    "sg:city":"Moncetz Longevas",
    "sg:orig_category":"Certifi\u00e9e Qualibat 2002 TRAVAUX DE PEINTURE INDUSTRIELLE, ANTI CORROSION, SABLAGE, M\u00c9TALLISATION, RE",
    "sg:phone":"+33 3 26 66 46 40",
    "sg:postcode":"51470",
    "sg:province":"Champagne",
    "wof:name":"Mb Industrie S.a.",
    "wof:placetype":"venue"
},
  "geometry": {"coordinates":[4.427427,48.90823],"type":"Point"}
}