{
  "type": "Feature",
  "properties": {
    "addr:full":"9 Allee Jean Prouve 92110 Clichy Ile de France",
    "addr:housenumber":"9",
    "addr:postcode":"92110",
    "addr:street":"Allee Jean Prouve;Ile De France",
    "iso:country":"FR",
    "sg:address":"9 Allee Jean Prouve 92110 Clichy",
    "sg:classifiers":[
        {
            "category":"Professional",
            "subcategory":"Printing & Photocopies",
            "type":"Services"
        }
    ],
    "sg:phone":"+33 1 41 40 33 33",
    "sg:province":"Ile de France",
    "sg:tags":[
        "publishing"
    ],
    "wof:name":"Societe Les Editions Lariviere",
    "wof:placetype":"venue"
},
  "geometry": {"coordinates":[2.318361,48.906513],"type":"Point"}
}