{
  "type": "Feature",
  "properties": {
    "iso:country":"FR",
    "sg:address":"51 Avenue Du Perigord 33370 Artigues Pres Bordeaux",
    "sg:city":"Artigues-pr\u00e8s-Bordeaux",
    "sg:classifiers":[
        {
            "category":"Wholesale",
            "subcategory":"Medical Equipment & Supplies",
            "type":"Manufacturing & Wholesale Goods"
        }
    ],
    "sg:phone":"+33 5 57 34 11 11",
    "sg:postcode":"33370",
    "sg:province":"Aquitaine",
    "sg:tags":[
        "instrument",
        "health",
        "-",
        "precision"
    ],
    "wof:name":"Actuel Dentaire Sarl",
    "wof:placetype":"venue"
},
  "geometry": {"coordinates":[-0.473618,44.865353],"type":"Point"}
}