{
  "type": "Feature",
  "properties": {
    "addr:full":"Rue Jean Monnet - ZA de Lazare Colombelles Basse Normandie 14460",
    "addr:postcode":"14460",
    "addr:street":"Rue Jean Monnet Za De Lazare Colombelles Basse",
    "iso:country":"FR",
    "sg:address":"Rue Jean Monnet - ZA de Lazare",
    "sg:city":"Colombelles",
    "sg:orig_category":"Unclassifiable Establishments",
    "sg:phone":"+33 2 31 78 84 80",
    "sg:postcode":"14460",
    "sg:province":"Basse Normandie",
    "wof:name":"S.t.a.b. S.a.r.l.",
    "wof:placetype":"venue"
},
  "geometry": {"coordinates":[-0.297164,49.204124],"type":"Point"}
}