{
  "type": "Feature",
  "properties": {
    "addr:full":"2, Av Joseph Lazare, 34500 B\u00e9ziers Languedoc-Roussillon",
    "addr:postcode":"34500",
    "addr:street":"Av Joseph Lazare",
    "iso:country":"FR",
    "sg:address":"2, Av Joseph Lazare, 34500 B\u00e9ziers",
    "sg:orig_category":"Non-Classified Establishments",
    "sg:phone":"+33 4 67 62 80 00",
    "sg:province":"Languedoc-Roussillon",
    "wof:name":"Hydraulique Mhavip S.a.r.l.",
    "wof:placetype":"venue"
},
  "geometry": {"coordinates":[3.222433,43.334084],"type":"Point"}
}