{
  "type": "Feature",
  "properties": {
    "iso:country":"FR",
    "sg:address":"Parc Haye 4 All Aub\u00e9pines 54840 Velaine En Haye",
    "sg:orig_category":"Miscellaneous Products",
    "sg:phone":"+33 3 83 23 26 66",
    "sg:postcode":"54840",
    "sg:province":"Lorraine",
    "wof:name":"Publi Cadeaux",
    "wof:placetype":"venue"
},
  "geometry": {"coordinates":[6.055453,48.696339],"type":"Point"}
}