{
  "type": "Feature",
  "properties": {
    "addr:full":"455 Promenade Des Anglais Nice Provence-Alpes-C\u00f4te d'Azur 06200",
    "addr:housenumber":"455",
    "addr:postcode":"06200",
    "addr:street":"Promenade Des Anglais",
    "iso:country":"FR",
    "sg:address":"455 Promenade Des Anglais",
    "sg:city":"Nice",
    "sg:classifiers":[
        {
            "category":"Banks & Credit Unions",
            "subcategory":"Financial Services",
            "type":"Services"
        }
    ],
    "sg:phone":"+33 4 92 29 49 29",
    "sg:postcode":"06200",
    "sg:province":"Provence-Alpes-C\u00f4te d'Azur",
    "sg:tags":[
        "banking",
        "finance",
        "insurance"
    ],
    "wof:name":"Ernst",
    "wof:placetype":"venue"
},
  "geometry": {"coordinates":[7.215069,43.667114],"type":"Point"}
}