{
  "type": "Feature",
  "properties": {
    "addr:full":"10, Rue Hoche, 71200 Le Creusot Le Creusot Bourgogne 71200",
    "addr:housenumber":"10",
    "addr:postcode":"71200;71200",
    "addr:street":"Rue Hoche",
    "iso:country":"FR",
    "sg:address":"10, Rue Hoche, 71200 Le Creusot",
    "sg:city":"Le Creusot",
    "sg:orig_category":"Non-Classified Establishments",
    "sg:phone":"+33 3 85 80 49 76",
    "sg:postcode":"71200",
    "sg:province":"Bourgogne",
    "wof:name":"C.s.t.n. S.a.r.l. - Creusot Soudure Tuyauterie Nucl\u00e9aire",
    "wof:placetype":"venue"
},
  "geometry": {"coordinates":[4.444182,46.799915],"type":"Point"}
}