{
  "type": "Feature",
  "properties": {
    "iso:country":"FR",
    "sg:address":"Rte d'Ablemont",
    "sg:city":"Bacqueville en Caux",
    "sg:orig_category":"Non-Classified Establishments",
    "sg:phone":"+33 2 35 83 26 69",
    "sg:postcode":"76730",
    "sg:province":"Haute Normandie",
    "wof:name":"Rubalin Normandie S.i.c.a.",
    "wof:placetype":"venue"
},
  "geometry": {"coordinates":[1.00077,49.808079],"type":"Point"}
}