{
  "type": "Feature",
  "properties": {
    "addr:full":"2 Rue Rabelais BP 819 41008 Blois Centre",
    "addr:housenumber":"2;819",
    "addr:postcode":"41008",
    "addr:street":"Rue Rabelais Bp",
    "iso:country":"FR",
    "sg:address":"2 Rue Rabelais BP 819 41008 Blois",
    "sg:classifiers":[
        {
            "category":"Professional",
            "subcategory":"Business Services",
            "type":"Services"
        }
    ],
    "sg:phone":"+33 2 54 52 26 20",
    "sg:province":"Centre",
    "sg:tags":[
        "training",
        "advice"
    ],
    "wof:name":"College Francois Rabelais",
    "wof:placetype":"venue"
},
  "geometry": {"coordinates":[1.331433,47.586849],"type":"Point"}
}