{
  "type": "Feature",
  "properties": {
    "iso:country":"FR",
    "sg:address":"Rte D'Annecy 73100 Gr\u00e9sy Sur Aix",
    "sg:classifiers":[
        {
            "category":"Manufacturing",
            "subcategory":"Rubber & Plastics",
            "type":"Manufacturing & Wholesale Goods"
        }
    ],
    "sg:phone":"+33 4 79 34 85 00",
    "sg:postcode":"73100",
    "sg:province":"Rhone-Alpes",
    "wof:name":"Applications Industrielles Rhone-alpes Sarl",
    "wof:placetype":"venue"
},
  "geometry": {"coordinates":[5.911885,45.695866],"type":"Point"}
}