{
  "type": "Feature",
  "properties": {
    "addr:full":"B.P. 215, 56402 Auray C\u00e9dex^^K\u00e9riquellan, 56400 Brech Brech Bretagne 56400",
    "addr:housenumber":"b.p. 215",
    "addr:postcode":"56402;56400;56400",
    "addr:street":"Brech",
    "iso:country":"FR",
    "sg:address":"B.P. 215, 56402 Auray C\u00e9dex^^K\u00e9riquellan, 56400 Brech",
    "sg:city":"Brech",
    "sg:orig_category":"Non-Classified Establishments",
    "sg:phone":"+33 2 97 24 07 40",
    "sg:postcode":"56400",
    "sg:province":"Bretagne",
    "wof:name":"Elidis Auray S.a.",
    "wof:placetype":"venue"
},
  "geometry": {"coordinates":[-2.949126,47.63744],"type":"Point"}
}