{
  "type": "Feature",
  "properties": {
    "addr:full":"clos Saint-Landelin 68250 Rouffach Rouffach Alsace 68250",
    "addr:postcode":"68250;68250",
    "addr:street":"Clos",
    "iso:country":"FR",
    "sg:address":"clos Saint-Landelin 68250 Rouffach",
    "sg:city":"Rouffach",
    "sg:classifiers":[
        {
            "category":"Wholesale",
            "subcategory":"Wine & Distilled Alcoholic Beverages",
            "type":"Manufacturing & Wholesale Goods"
        }
    ],
    "sg:phone":"+33 3 89 78 58 00",
    "sg:postcode":"68250",
    "sg:province":"Alsace",
    "sg:tags":[
        "french"
    ],
    "wof:name":"Vignobles Ren\u00e9 Mur\u00e9 Sarl",
    "wof:placetype":"venue"
},
  "geometry": {"coordinates":[7.296965,47.959679],"type":"Point"}
}