{
  "type": "Feature",
  "properties": {
    "iso:country":"FR",
    "sg:address":"4 rte Lesneven; Plouider",
    "sg:classifiers":[
        {
            "category":"Banks & Credit Unions",
            "subcategory":"Bank",
            "type":"Services"
        }
    ],
    "sg:phone":"+33 3398254714",
    "sg:province":"Picardie",
    "wof:name":"Cr\u00e9dit Mutuel De Bretagne",
    "wof:placetype":"venue"
},
  "geometry": {"coordinates":[-4.299575,48.607876],"type":"Point"}
}