{
  "type": "Feature",
  "properties": {
    "addr:full":"14, 1\u00e8re Avenue - ZI des Estroublancs, 13127 Vitrolles Provence-Alpes-C\u00f4te d'Azur",
    "addr:housenumber":"14",
    "addr:postcode":"13127",
    "addr:street":"1E\u0300Re Avenue Zi Des Estroublancs",
    "iso:country":"FR",
    "sg:address":"14, 1\u00e8re Avenue - ZI des Estroublancs, 13127 Vitrolles",
    "sg:orig_category":"Unclassifiable Establishments",
    "sg:phone":"+33 4 42 15 96 50",
    "sg:province":"Provence-Alpes-C\u00f4te d'Azur",
    "wof:name":"E.i.g.c. S.n.c.",
    "wof:placetype":"venue"
},
  "geometry": {"coordinates":[5.241435,43.438313],"type":"Point"}
}