{
  "type": "Feature",
  "properties": {
    "iso:country":"FR",
    "sg:address":"4, Rue du Congo, 75012 Paris",
    "sg:orig_category":"Non-Classified Establishments",
    "sg:phone":"+33 1 47 42 31 33",
    "sg:province":"Ile de France",
    "wof:name":"Synercom S.a.",
    "wof:placetype":"venue"
},
  "geometry": {"coordinates":[2.386398,48.841217],"type":"Point"}
}