{
  "type": "Feature",
  "properties": {
    "iso:country":"FR",
    "sg:address":"Rte De Chalons 51210 Montmirail",
    "sg:classifiers":[
        {
            "category":"Utilities",
            "subcategory":"Electric",
            "type":"Services"
        }
    ],
    "sg:phone":"+33 3 26 81 70 00",
    "sg:postcode":"51210",
    "sg:province":"Champagne",
    "sg:tags":[
        "electricity",
        "electronic",
        "electrical",
        "equipment"
    ],
    "wof:name":"Axon Cable Sa",
    "wof:placetype":"venue"
},
  "geometry": {"coordinates":[3.5402,48.870331],"type":"Point"}
}