{
  "type": "Feature",
  "properties": {
    "addr:full":"16, Av. Victor Hugo, 81300 Graulhet Midi Pyr\u00e9n\u00e9es",
    "addr:postcode":"81300",
    "addr:street":"16 Av. Victor Hugo",
    "iso:country":"FR",
    "sg:address":"16, Av. Victor Hugo, 81300 Graulhet",
    "sg:orig_category":"Unclassifiable Establishments",
    "sg:phone":"+33 5 63 34 42 90",
    "sg:province":"Midi Pyr\u00e9n\u00e9es",
    "wof:name":"M.r.l.f. S.a.r.l. - Montage R\u00e9alisation Laine France",
    "wof:placetype":"venue"
},
  "geometry": {"coordinates":[1.990014,43.759926],"type":"Point"}
}