{
  "type": "Feature",
  "properties": {
    "addr:full":"B.P. 58, 08120 Bogny sur Meuse^^Rue Victor Hugo - ZI, 08120 Bogny sur Meuse Bogny-sur-Meuse Champagne 08120",
    "addr:postcode":"08120;08120;08120",
    "addr:street":"B.P. 58;Bogny;Meuse^^Rue;Hugo Zi;Bogny;Meuse;Champagne",
    "iso:country":"FR",
    "sg:address":"B.P. 58, 08120 Bogny sur Meuse^^Rue Victor Hugo - ZI, 08120 Bogny sur Meuse",
    "sg:city":"Bogny-sur-Meuse",
    "sg:orig_category":"Non-Classified Establishments",
    "sg:phone":"+33 3 24 53 61 40",
    "sg:postcode":"08120",
    "sg:province":"Champagne",
    "wof:name":"Carameaux A.t.c.b. S.a. - Ateliers De T\u00f4lerie Chaudronnerie De Bogny",
    "wof:placetype":"venue"
},
  "geometry": {"coordinates":[4.75985,49.85899],"type":"Point"}
}