{
  "type": "Feature",
  "properties": {
    "addr:full":"ZI de Lissandre Cenon Aquitaine 33150",
    "addr:postcode":"33150",
    "addr:street":"Zi De Lissandre",
    "iso:country":"FR",
    "sg:address":"ZI de Lissandre",
    "sg:city":"Cenon",
    "sg:orig_category":"Unclassifiable Establishments",
    "sg:phone":"+33 5 56 40 09 88",
    "sg:postcode":"33150",
    "sg:province":"Aquitaine",
    "wof:name":"M.b.c. S.a.r.l. - Manufacture Bordelaise De Caoutchouc",
    "wof:placetype":"venue"
},
  "geometry": {"coordinates":[-0.530473,44.858353],"type":"Point"}
}