{
  "type": "Feature",
  "properties": {
    "iso:country":"FR",
    "sg:address":"B.P. 353, 76503 Elbeuf C\u00e9dex^^209, Av F\u00e9lix Faure, 76320 Caudebec les Elbeuf",
    "sg:orig_category":"Non-Classified Establishments",
    "sg:phone":"+33 2 35 81 03 94",
    "sg:province":"Haute Normandie",
    "wof:name":"S.m.e.r.p. S.a.r.l. - Soci\u00e9t\u00e9 Moderne Etude R\u00e9alisation Et Prestation Moretti-hervieux S.a.r.l.",
    "wof:placetype":"venue"
},
  "geometry": {"coordinates":[1.01608,49.283875],"type":"Point"}
}