{
  "type": "Feature",
  "properties": {
    "iso:country":"FR",
    "sg:address":"4, Rue Wencker, 67000 Strasbourg",
    "sg:city":"Strasbourg",
    "sg:orig_category":"Unclassifiable Establishments",
    "sg:phone":"+33 3 88 25 88 00",
    "sg:postcode":"67000",
    "sg:province":"Alsace",
    "wof:name":"Dornbusch France S.a.r.l.",
    "wof:placetype":"venue"
},
  "geometry": {"coordinates":[7.757589,48.5854],"type":"Point"}
}