{
  "type": "Feature",
  "properties": {
    "iso:country":"FR",
    "sg:address":"All\u00e9e des Bruy\u00e8res",
    "sg:city":"Biganos",
    "sg:orig_category":"Unclassifiable Establishments",
    "sg:phone":"+33 5 56 26 79 17",
    "sg:postcode":"33380",
    "sg:province":"Aquitaine",
    "wof:name":"E.2.m S.a. - Etudes M\u00e9thodes Maintenance",
    "wof:placetype":"venue"
},
  "geometry": {"coordinates":[-0.965424,44.63969],"type":"Point"}
}