{
  "type": "Feature",
  "properties": {
    "addr:full":"Village 30500 Poteli\u00e8res Languedoc-Roussillon 30500",
    "addr:postcode":"30500;30500",
    "addr:street":"Potelie\u0300Res",
    "iso:country":"FR",
    "sg:address":"Village 30500 Poteli\u00e8res",
    "sg:classifiers":[
        {
            "category":"Wholesale",
            "subcategory":"Farm Supplies",
            "type":"Manufacturing & Wholesale Goods"
        }
    ],
    "sg:phone":"+33 4 66 24 81 81",
    "sg:postcode":"30500",
    "sg:province":"Languedoc-Roussillon",
    "sg:tags":[
        "-",
        "machine",
        "equipment",
        "engineering",
        "machinery",
        "mechanical",
        "agriculture"
    ],
    "wof:name":"Ets Gard Sarl",
    "wof:placetype":"venue"
},
  "geometry": {"coordinates":[4.220085,44.186352],"type":"Point"}
}