{
  "type": "Feature",
  "properties": {
    "addr:full":"79 R du Docteur Jacques Touati 95340 Persan Ile de France",
    "addr:housenumber":"79",
    "addr:postcode":"95340;ile",
    "addr:street":"R Du Docteur Jacques Touati",
    "iso:country":"FR",
    "sg:address":"79 R du Docteur Jacques Touati 95340 Persan",
    "sg:classifiers":[
        {
            "category":"Banks & Credit Unions",
            "subcategory":"Bureau De Change",
            "type":"Services"
        }
    ],
    "sg:phone":"+33 1 34 70 02 35",
    "sg:province":"Ile de France",
    "sg:tags":[
        "steel",
        "stainless",
        "plant",
        "construction",
        "boiler"
    ],
    "wof:name":"Perinox Sarl",
    "wof:placetype":"venue"
},
  "geometry": {"coordinates":[2.292446,49.151878],"type":"Point"}
}