{
  "type": "Feature",
  "properties": {
    "addr:full":"avenue de l'Europe 49450 ST MACAIRE EN MAUGES Pays de Loire 49450",
    "addr:postcode":"49450;49450",
    "addr:street":"Avenue De L'Europe;Mauges",
    "iso:country":"FR",
    "sg:address":"avenue de l'Europe 49450 ST MACAIRE EN MAUGES",
    "sg:orig_category":"Ladies' Shoes",
    "sg:phone":"+33 2 41 49 77 00",
    "sg:postcode":"49450",
    "sg:province":"Pays de Loire",
    "wof:name":"Cbc Shoes Sas",
    "wof:placetype":"venue"
},
  "geometry": {"coordinates":[-0.988359,47.115822],"type":"Point"}
}