{
  "type": "Feature",
  "properties": {
    "addr:full":"B.P. 64, 42125 Le Coteau C\u00e9dex^^27, Bd Charles de Gaulle, 42120 Le Coteau Rhone-Alpes",
    "addr:postcode":"42125;42120",
    "addr:street":"B.P. 64;Ce\u0301Dex^^27 Bd Charles De Gaulle;Rhone-Alpes",
    "iso:country":"FR",
    "sg:address":"B.P. 64, 42125 Le Coteau C\u00e9dex^^27, Bd Charles de Gaulle, 42120 Le Coteau",
    "sg:orig_category":"Non-Classified Establishments",
    "sg:phone":"+33 4 77 67 26 88",
    "sg:province":"Rhone-Alpes",
    "wof:name":"R.b.i. S.a.",
    "wof:placetype":"venue"
},
  "geometry": {"coordinates":[4.09834,45.991081],"type":"Point"}
}