{
  "type": "Feature",
  "properties": {
    "addr:full":"62/64, Av. Fran\u00e7ois Verdier, 81030 Albi C\u00e9dex 9 Midi-Pyr\u00e9n\u00e9es",
    "addr:housenumber":"62 / 64;9",
    "addr:postcode":"81030",
    "addr:street":"Av. Franc\u0327Ois Verdier;Ce\u0301Dex",
    "iso:country":"FR",
    "sg:address":"62/64, Av. Fran\u00e7ois Verdier, 81030 Albi C\u00e9dex 9",
    "sg:orig_category":"Non-Classified Establishments",
    "sg:phone":"+33 5 63 38 08 44",
    "sg:province":"Midi-Pyr\u00e9n\u00e9es",
    "wof:name":"Sud-ouest M\u00e9dical S.a.",
    "wof:placetype":"venue"
},
  "geometry": {"coordinates":[2.135373,43.919834],"type":"Point"}
}