{
  "type": "Feature",
  "properties": {
    "addr:full":"73 Bis Traverse De La Gaye 13009 Marseille Poitou-Charentes",
    "addr:housenumber":"73 bis",
    "addr:postcode":"13009",
    "addr:street":"Traverse De La Gaye",
    "iso:country":"FR",
    "sg:address":"73 Bis Traverse De La Gaye 13009 Marseille",
    "sg:classifiers":[
        {
            "category":"Professional",
            "subcategory":"Printing & Photocopies",
            "type":"Services"
        }
    ],
    "sg:phone":"+33 4 91 75 30 30",
    "sg:province":"Poitou-Charentes",
    "sg:tags":[
        "paper",
        "raw",
        "material",
        "-",
        "cardboard"
    ],
    "wof:name":"Provence Pelliculage",
    "wof:placetype":"venue"
},
  "geometry": {"coordinates":[5.408587,43.257393],"type":"Point"}
}