{
  "type": "Feature",
  "properties": {
    "iso:country":"FR",
    "sg:address":"29 rue Georges Clemenceau; Carcassonne",
    "sg:classifiers":[
        {
            "category":"Banks & Credit Unions",
            "subcategory":"Bank",
            "type":"Services"
        }
    ],
    "sg:phone":"+33 3368257244",
    "sg:province":"Aquitaine",
    "wof:name":"Soci\u00e9t\u00e9 Marseillaise De Cr\u00e9dit",
    "wof:placetype":"venue"
},
  "geometry": {"coordinates":[-82.990898,37.139431],"type":"Point"}
}