{
  "type": "Feature",
  "properties": {
    "addr:full":"Rue du Gay Chalezeule Franche Comt\u00e9 25220",
    "addr:postcode":"25220",
    "addr:street":"Rue Du Gay;Franche Comte\u0301",
    "iso:country":"FR",
    "sg:address":"Rue du Gay",
    "sg:city":"Chalezeule",
    "sg:orig_category":"Unclassifiable Establishments",
    "sg:phone":"+33 3 81 80 01 62",
    "sg:postcode":"25220",
    "sg:province":"Franche Comt\u00e9",
    "wof:name":"Bureau Cetel S.a.r.l.",
    "wof:placetype":"venue"
},
  "geometry": {"coordinates":[6.05758,47.265549],"type":"Point"}
}