{
  "type": "Feature",
  "properties": {
    "addr:full":"23 R Des Tondeurs La Neuvillette 51100 Reims Champagne 51100",
    "addr:housenumber":"23",
    "addr:postcode":"51100;51100",
    "addr:street":"R Des Tondeurs La Neuvillette",
    "iso:country":"FR",
    "sg:address":"23 R Des Tondeurs La Neuvillette 51100 Reims",
    "sg:classifiers":[
        {
            "category":"Manufacturing",
            "subcategory":"Glass & Minerals",
            "type":"Manufacturing & Wholesale Goods"
        }
    ],
    "sg:phone":"+33 3 26 09 24 76",
    "sg:postcode":"51100",
    "sg:province":"Champagne",
    "sg:tags":[
        "building",
        "material"
    ],
    "wof:name":"Miroiterie Berger",
    "wof:placetype":"venue"
},
  "geometry": {"coordinates":[4.024687,49.268242],"type":"Point"}
}