{
  "type": "Feature",
  "properties": {
    "addr:full":"22 Rue Georges Cl\u00e9menceau 59374 Loos Aquitaine",
    "addr:housenumber":"22",
    "addr:postcode":"59374",
    "addr:street":"Rue Georges Cle\u0301Menceau",
    "iso:country":"FR",
    "sg:address":"22 Rue Georges Cl\u00e9menceau 59374 Loos",
    "sg:classifiers":[
        {
            "category":"Shopping",
            "subcategory":"Pharmacy",
            "type":"Retail Goods"
        }
    ],
    "sg:phone":"+33 3 20 22 58 58",
    "sg:province":"Aquitaine",
    "sg:tags":[
        "chemical",
        "pharmaceutical",
        "chemistry",
        "-",
        "by-product"
    ],
    "wof:name":"Produits Chimiques De Loos Sa",
    "wof:placetype":"venue"
},
  "geometry": {"coordinates":[3.011113,50.614388],"type":"Point"}
}