{
  "type": "Feature",
  "properties": {
    "addr:full":"20 Quai Du Lazaret 13002 Marseille Provence-Alpes-C\u00f4te d'Azur",
    "addr:housenumber":"20",
    "addr:postcode":"13002",
    "addr:street":"Quai Du Lazaret",
    "iso:country":"FR",
    "sg:address":"20 Quai Du Lazaret 13002 Marseille",
    "sg:classifiers":[
        {
            "category":"Marine",
            "type":"Transportation"
        }
    ],
    "sg:phone":"+33 4 91 13 16 16",
    "sg:province":"Provence-Alpes-C\u00f4te d'Azur",
    "sg:tags":[
        "transport",
        "sea"
    ],
    "wof:name":"Smi",
    "wof:placetype":"venue"
},
  "geometry": {"coordinates":[5.37001,43.296101],"type":"Point"}
}