{
  "type": "Feature",
  "properties": {
    "iso:country":"FR",
    "sg:address":"9 Rue Du Grand D\u00f4me Za Courtaboeuf 91951 Courtabouef Cedex",
    "sg:classifiers":[
        {
            "category":"Utilities",
            "subcategory":"Electric",
            "type":"Services"
        }
    ],
    "sg:phone":"+33 1 69 29 35 10",
    "sg:province":"Aquitaine",
    "sg:tags":[
        "electricity",
        "electronic",
        "electrical",
        "equipment"
    ],
    "wof:name":"Ste Azenn Sa",
    "wof:placetype":"venue"
},
  "geometry": {"coordinates":[-117.10536999999999,32.67194],"type":"Point"}
}