{
  "type": "Feature",
  "properties": {
    "iso:country":"FR",
    "sg:address":"34 Rue Des Clercs 57000 Metz",
    "sg:classifiers":[
        {
            "category":"Bakery",
            "type":"Food & Drink"
        }
    ],
    "sg:phone":"+33 3 87 75 12 93",
    "sg:postcode":"57000",
    "sg:province":"Lorraine",
    "sg:tags":[
        "cake",
        "product",
        "related",
        "bread"
    ],
    "wof:name":"Malaman",
    "wof:placetype":"venue"
},
  "geometry": {"coordinates":[6.173222,49.116592],"type":"Point"}
}