{
  "type": "Feature",
  "properties": {
    "iso:country":"FR",
    "sg:address":"9, All\u00e9e des Bouleaux - ZI de Courtine, 84000 Avignon",
    "sg:orig_category":"Non-Classified Establishments",
    "sg:phone":"+33 4 90 27 57 57",
    "sg:province":"Centre",
    "wof:name":"Quadrio S.a.r.l.",
    "wof:placetype":"venue"
},
  "geometry": {"coordinates":[4.806015,43.948753],"type":"Point"}
}