{
  "type": "Feature",
  "properties": {
    "addr:full":"1 Rue De La Papeterie 68230 Turckheim Turckheim Alsace 68230",
    "addr:housenumber":"1",
    "addr:postcode":"68230;68230",
    "addr:street":"Rue De La Papeterie",
    "iso:country":"FR",
    "sg:address":"1 Rue De La Papeterie 68230 Turckheim",
    "sg:city":"Turckheim",
    "sg:classifiers":[
        {
            "category":"Manufacturing",
            "subcategory":"Paper Products",
            "type":"Manufacturing & Wholesale Goods"
        }
    ],
    "sg:phone":"+33 3 89 27 05 50",
    "sg:postcode":"68230",
    "sg:province":"Alsace",
    "sg:tags":[
        "raw",
        "material",
        "-",
        "cardboard"
    ],
    "wof:name":"Matussiere Et Forest Sa (papeteries)",
    "wof:placetype":"venue"
},
  "geometry": {"coordinates":[7.278857,48.083893],"type":"Point"}
}