{
  "type": "Feature",
  "properties": {
    "addr:full":"16 Avenue De Friedland Paris Ile de France 75008",
    "addr:housenumber":"16",
    "addr:postcode":"75008",
    "addr:street":"Avenue De Friedland",
    "iso:country":"FR",
    "sg:address":"16 Avenue De Friedland",
    "sg:city":"Paris",
    "sg:classifiers":[
        {
            "category":"Banks & Credit Unions",
            "subcategory":"Financial Services",
            "type":"Services"
        }
    ],
    "sg:phone":"+33 1 45 62 86 11",
    "sg:postcode":"75008",
    "sg:province":"Ile de France",
    "sg:tags":[
        "banking",
        "finance",
        "insurance"
    ],
    "wof:name":"Tregouet Pigot & Associ\u00c9s",
    "wof:placetype":"venue"
},
  "geometry": {"coordinates":[2.301132,48.874432],"type":"Point"}
}