{
  "type": "Feature",
  "properties": {
    "addr:full":"B.P. 414, 51689 Reims C\u00e9dex 2^^24, Rue Robert Fulton - ZA Farman Sud, 51100 Reims Champagne",
    "addr:housenumber":"b.p. 414;2 ^ ^ 24",
    "addr:postcode":"51689;51100",
    "addr:street":"Ce\u0301Dex;Rue Robert;Farman Sud",
    "iso:country":"FR",
    "sg:address":"B.P. 414, 51689 Reims C\u00e9dex 2^^24, Rue Robert Fulton - ZA Farman Sud, 51100 Reims",
    "sg:orig_category":"Non-Classified Establishments",
    "sg:phone":"+33 3 26 79 31 31",
    "sg:province":"Champagne",
    "wof:name":"Still & Saxby S.a.r.l.",
    "wof:placetype":"venue"
},
  "geometry": {"coordinates":[4.028445,49.26284],"type":"Point"}
}