{
  "type": "Feature",
  "properties": {
    "iso:country":"FR",
    "sg:address":"58 Rue Du Faubourg Poissonniere 75010 Paris",
    "sg:classifiers":[
        {
            "category":"Manufacturing",
            "subcategory":"Textiles",
            "type":"Manufacturing & Wholesale Goods"
        }
    ],
    "sg:phone":"+33 1 47 70 47 73",
    "sg:postcode":"75010",
    "sg:province":"Ile de France",
    "sg:tags":[
        "linen",
        "clothing",
        "fabric"
    ],
    "wof:name":"Linge Au Coeur",
    "wof:placetype":"venue"
},
  "geometry": {"coordinates":[2.348321,48.875202],"type":"Point"}
}