{
  "type": "Feature",
  "properties": {
    "iso:country":"FR",
    "sg:address":"B.P. 35, 68170 Rixheim^^82, Rue de Mulhouse, 68170 Rixheim",
    "sg:city":"Rixheim",
    "sg:orig_category":"Non-Classified Establishments",
    "sg:phone":"+33 3 89 44 17 14",
    "sg:postcode":"68170",
    "sg:province":"Alsace",
    "wof:name":"Sarmac S.a.",
    "wof:placetype":"venue"
},
  "geometry": {"coordinates":[7.397395,47.744122],"type":"Point"}
}