{
  "type": "Feature",
  "properties": {
    "iso:country":"FR",
    "sg:address":"2, Bd de Ch\u00e2tillon - Zone Portuaire, 62200 Boulogne sur Mer",
    "sg:orig_category":"Unclassifiable Establishments",
    "sg:phone":"+33 3 21 30 56 00",
    "sg:province":"Nord Pas-de-Calais",
    "wof:name":"Socarenam S.a.",
    "wof:placetype":"venue"
},
  "geometry": {"coordinates":[1.615514,50.727444],"type":"Point"}
}