{
  "type": "Feature",
  "properties": {
    "addr:full":"31-32 de Dion Bouton; Puteaux Cedex; 92811 Centre",
    "addr:housenumber":"31-32",
    "addr:postcode":"92811",
    "addr:street":"De Dion Bouton",
    "iso:country":"FR",
    "sg:address":"31-32",
    "sg:city":"de Dion Bouton; Puteaux Cedex; 92811",
    "sg:classifiers":[
        {
            "category":"Industrial Area",
            "type":"Public Place"
        }
    ],
    "sg:phone":"+33 1 46 96 44 33",
    "sg:province":"Centre",
    "sg:tags":[
        "large",
        "private"
    ],
    "wof:name":"Bollor\u00e9",
    "wof:placetype":"venue"
},
  "geometry": {"coordinates":[2.23768,48.883331],"type":"Point"}
}