{
  "type": "Feature",
  "properties": {
    "addr:full":"RN 113 - Quartier le Repos Les Pennes Mirabeau Midi Pyr\u00e9n\u00e9es 13170",
    "addr:postcode":"13170",
    "addr:street":"Rn 113",
    "iso:country":"FR",
    "sg:address":"RN 113 - Quartier le Repos",
    "sg:city":"Les Pennes Mirabeau",
    "sg:orig_category":"Unclassifiable Establishments",
    "sg:phone":"+33 4 42 02 67 83",
    "sg:postcode":"13170",
    "sg:province":"Midi Pyr\u00e9n\u00e9es",
    "wof:name":"E.m.r.j. D\u00e9mo S.a.r.l.",
    "wof:placetype":"venue"
},
  "geometry": {"coordinates":[5.316214,43.410835],"type":"Point"}
}