{
  "type": "Feature",
  "properties": {
    "iso:country":"FR",
    "sg:address":"116, Rte de Montpellier, 30540 Milhaud",
    "sg:orig_category":"Non-Classified Establishments",
    "sg:phone":"+33 4 66 74 61 61",
    "sg:province":"Languedoc-Roussillon",
    "wof:name":"Locavert S.a.",
    "wof:placetype":"venue"
},
  "geometry": {"coordinates":[4.301833,43.786179],"type":"Point"}
}