{
  "type": "Feature",
  "properties": {
    "iso:country":"FR",
    "sg:address":"Rue de la Tuilerie",
    "sg:city":"Rouffach",
    "sg:orig_category":"Non-Classified Establishments",
    "sg:phone":"+33 3 89 49 62 13",
    "sg:postcode":"68250",
    "sg:province":"Alsace",
    "wof:name":"Tuileries Sturm S.a.",
    "wof:placetype":"venue"
},
  "geometry": {"coordinates":[7.293095,47.952278],"type":"Point"}
}