{
  "type": "Feature",
  "properties": {
    "addr:full":"480 Av Des Pr\u00e9s D'Ar\u00e8nes 34000 Montpellier Languedoc-Roussillon 34000",
    "addr:housenumber":"480",
    "addr:postcode":"34000;34000",
    "addr:street":"Av Des Pre\u0301S D'Are \u0300Nes",
    "iso:country":"FR",
    "sg:address":"480 Av Des Pr\u00e9s D'Ar\u00e8nes 34000 Montpellier",
    "sg:classifiers":[
        {
            "category":"Manufacturing",
            "subcategory":"Aerospace",
            "type":"Manufacturing & Wholesale Goods"
        }
    ],
    "sg:phone":"+33 4 67 12 66 00",
    "sg:postcode":"34000",
    "sg:province":"Languedoc-Roussillon",
    "sg:tags":[
        "equipment",
        "aeronautic",
        "transport",
        "vehicle"
    ],
    "wof:name":"Tld Europe Sas",
    "wof:placetype":"venue"
},
  "geometry": {"coordinates":[3.891268,43.609718],"type":"Point"}
}