{
  "type": "Feature",
  "properties": {
    "iso:country":"FR",
    "sg:address":"ZA le Pr\u00e9 du Milieu",
    "sg:city":"Bas en Basset",
    "sg:orig_category":"Unclassifiable Establishments",
    "sg:phone":"+33 4 71 66 71 83",
    "sg:postcode":"43210",
    "sg:province":"Auvergne",
    "wof:name":"Entreprise Michalon S.a.r.l.",
    "wof:placetype":"venue"
},
  "geometry": {"coordinates":[4.110865,45.31274],"type":"Point"}
}