{
  "type": "Feature",
  "properties": {
    "addr:full":"2 Rue De La Roquette Cour De Mai Passage Du Che 75011 Paris Ile de France",
    "addr:housenumber":"2",
    "addr:postcode":"75011",
    "addr:street":"Rue De La Roquette Cour De Mai Passage Du Che",
    "iso:country":"FR",
    "sg:address":"2 Rue De La Roquette Cour De Mai Passage Du Che 75011 Paris",
    "sg:classifiers":[
        {
            "category":"Professional",
            "subcategory":"Printing & Photocopies",
            "type":"Services"
        }
    ],
    "sg:phone":"+33 1 53 36 10 90",
    "sg:province":"Ile de France",
    "sg:tags":[
        "publishing"
    ],
    "wof:name":"Mosaique Sarl",
    "wof:placetype":"venue"
},
  "geometry": {"coordinates":[2.379995,48.857594],"type":"Point"}
}