{
  "type": "Feature",
  "properties": {
    "addr:full":"B.P. 149 Olivet Centre 45160",
    "addr:housenumber":"b.p. 149",
    "addr:postcode":"45160",
    "addr:street":"Olivet Centre",
    "iso:country":"FR",
    "sg:address":"B.P. 149",
    "sg:city":"Olivet",
    "sg:orig_category":"Non-Classified Establishments",
    "sg:phone":"+33 2 38 25 26 40",
    "sg:postcode":"45160",
    "sg:province":"Centre",
    "wof:name":"A.f.p.a.",
    "wof:placetype":"venue"
},
  "geometry": {"coordinates":[1.875266,47.778763],"type":"Point"}
}