{
  "type": "Feature",
  "properties": {
    "iso:country":"FR",
    "sg:address":"14, Rue Vieux Porche, 41120 Les Montils",
    "sg:city":"Les Montils",
    "sg:orig_category":"Non-Classified Establishments",
    "sg:phone":"+33 2 54 44 04 06",
    "sg:postcode":"41120",
    "sg:province":"Centre",
    "wof:name":"Michel Dupret",
    "wof:placetype":"venue"
},
  "geometry": {"coordinates":[1.295413,47.495094],"type":"Point"}
}