{
  "type": "Feature",
  "properties": {
    "addr:full":"68, Cours de Verdun, 01100 Oyonnax Rhone-Alpes 01100",
    "addr:housenumber":"68",
    "addr:postcode":"01100;01100",
    "addr:street":"Cours De Verdun",
    "iso:country":"FR",
    "sg:address":"68, Cours de Verdun, 01100 Oyonnax",
    "sg:orig_category":"Non-Classified Establishments",
    "sg:phone":"+33 4 74 73 82 76",
    "sg:postcode":"01100",
    "sg:province":"Rhone-Alpes",
    "wof:name":"Etablissement C.c.f. France Chauffage S.a.r.l. - Etablissement Chauffage Climatisation Froid France ",
    "wof:placetype":"venue"
},
  "geometry": {"coordinates":[5.650851,46.263599],"type":"Point"}
}