{
  "type": "Feature",
  "properties": {
    "iso:country":"FR",
    "sg:address":"62, Av du G\u00e9n\u00e9ral Leclerc, 54700 Pont \u00e0 Mousson",
    "sg:orig_category":"Unclassifiable Establishments",
    "sg:phone":"+33 3 83 82 10 41",
    "sg:province":"Lorraine",
    "wof:name":"Publi-cr\u00e9ation",
    "wof:placetype":"venue"
},
  "geometry": {"coordinates":[6.0616,48.909973],"type":"Point"}
}