{
  "type": "Feature",
  "properties": {
    "iso:country":"FR",
    "sg:address":"B.P. 41, 49181 Saint Barth\u00e9l\u00e9my d'Anjou C\u00e9dex^^Rue du Bois Rinier - ZI, 49124 Saint Barth\u00e9l\u00e9my d'Anj",
    "sg:orig_category":"Non-Classified Establishments",
    "sg:phone":"+33 2 41 31 17 00",
    "sg:province":"Pays de Loire",
    "wof:name":"Fixator S.a.",
    "wof:placetype":"venue"
},
  "geometry": {"coordinates":[-1.334822,47.273693],"type":"Point"}
}