{
  "type": "Feature",
  "properties": {
    "addr:full":"B.P. 41, 49181 Saint Barth\u00e9l\u00e9my d'Anjou C\u00e9dex^^Rue du Bois Rinier - ZI, 49124 Saint Barth\u00e9l\u00e9my d'Anj Pays de Loire",
    "addr:postcode":"49181;barthe\u0301le\u0301my;49124",
    "addr:street":"B.P. 41;Ce\u0301Dex^^Rue;Zi;Barthe\u0301Le\u0301My D'Anj",
    "iso:country":"FR",
    "sg:address":"B.P. 41, 49181 Saint Barth\u00e9l\u00e9my d'Anjou C\u00e9dex^^Rue du Bois Rinier - ZI, 49124 Saint Barth\u00e9l\u00e9my d'Anj",
    "sg:orig_category":"Non-Classified Establishments",
    "sg:phone":"+33 2 41 31 17 00",
    "sg:province":"Pays de Loire",
    "wof:name":"Fixator S.a.",
    "wof:placetype":"venue"
},
  "geometry": {"coordinates":[-1.334822,47.273693],"type":"Point"}
}