{
  "type": "Feature",
  "properties": {
    "addr:full":"1 Ave Robert Schuman; Epinal; 88000 Lorraine 88000",
    "addr:postcode":"88000;88000",
    "addr:street":"1 Ave Robert Schuman",
    "iso:country":"FR",
    "sg:address":"1 Ave Robert Schuman; Epinal; 88000",
    "sg:classifiers":[
        {
            "category":"Banks & Credit Unions",
            "subcategory":"Bank",
            "type":"Services"
        }
    ],
    "sg:phone":"+33 29314667",
    "sg:postcode":"88000",
    "sg:province":"Lorraine",
    "wof:name":"Cr\u00e9dit Mutuel",
    "wof:placetype":"venue"
},
  "geometry": {"coordinates":[6.45534,48.179707],"type":"Point"}
}