{
  "type": "Feature",
  "properties": {
    "iso:country":"FR",
    "sg:address":"Min de Brienne",
    "sg:city":"Bordeaux",
    "sg:orig_category":"Unclassifiable Establishments",
    "sg:phone":"+33 5 57 35 02 72",
    "sg:postcode":"33800",
    "sg:province":"Aquitaine",
    "wof:name":"Espana Et Fils S.a.",
    "wof:placetype":"venue"
},
  "geometry": {"coordinates":[-0.543007,44.822979],"type":"Point"}
}