{
  "type": "Feature",
  "properties": {
    "addr:full":"44 Rue Charles De Gaulle 42300 Roanne Rhone-Alpes 42300",
    "addr:housenumber":"44",
    "addr:postcode":"42300;42300",
    "addr:street":"Rue Charles De Gaulle;Rhone-Alpes",
    "iso:country":"FR",
    "sg:address":"44 Rue Charles De Gaulle 42300 Roanne",
    "sg:classifiers":[
        {
            "category":"Professional",
            "subcategory":"Advertising",
            "type":"Services"
        }
    ],
    "sg:phone":"+33 4 77 70 80 37",
    "sg:postcode":"42300",
    "sg:province":"Rhone-Alpes",
    "sg:tags":[
        "information",
        "medium",
        "communication"
    ],
    "wof:name":"Photo Cine Perrin Sa",
    "wof:placetype":"venue"
},
  "geometry": {"coordinates":[4.071675,46.038067],"type":"Point"}
}