{
  "type": "Feature",
  "properties": {
    "addr:full":"ZAE les P\u00e9rouses Rumilly Nord Pas-de-Calais 74150",
    "addr:postcode":"74150",
    "addr:street":"Zae;Pas-De-Calais",
    "iso:country":"FR",
    "sg:address":"ZAE les P\u00e9rouses",
    "sg:city":"Rumilly",
    "sg:orig_category":"Unclassifiable Establishments",
    "sg:phone":"+33 4 50 64 60 82",
    "sg:postcode":"74150",
    "sg:province":"Nord Pas-de-Calais",
    "wof:name":"C.s.f. Inox S.a.r.l.",
    "wof:placetype":"venue"
},
  "geometry": {"coordinates":[5.96494,45.848652],"type":"Point"}
}