{
  "type": "Feature",
  "properties": {
    "iso:country":"FR",
    "sg:address":"Route Bras 83143 Le Val",
    "sg:classifiers":[
        {
            "category":"Autos & Motor Vehicles",
            "subcategory":"Automobile Sales",
            "type":"Retail Goods"
        }
    ],
    "sg:phone":"+33 4 94 86 47 46",
    "sg:tags":[
        "equipment",
        "industrial",
        "transport"
    ],
    "wof:name":"Bennes Guillaume Sa",
    "wof:placetype":"venue"
},
  "geometry": {"coordinates":[6.020921,43.442333],"type":"Point"}
}