{
  "type": "Feature",
  "properties": {
    "addr:full":"Rte de Saubrigues Saubrigues Aquitaine 40230",
    "addr:postcode":"40230",
    "addr:street":"Rte De Saubrigues",
    "iso:country":"FR",
    "sg:address":"Rte de Saubrigues",
    "sg:city":"Saubrigues",
    "sg:orig_category":"Non-Classified Establishments",
    "sg:phone":"+33 5 58 41 86 00",
    "sg:postcode":"40230",
    "sg:province":"Aquitaine",
    "wof:name":"Scierie Nicolas S.a.",
    "wof:placetype":"venue"
},
  "geometry": {"coordinates":[-1.370948,43.627762],"type":"Point"}
}