{
  "type": "Feature",
  "properties": {
    "addr:full":"177 Rue Garibaldi Lyon Rhone-Alpes 69003",
    "addr:housenumber":"177",
    "addr:postcode":"69003",
    "addr:street":"Rue Garibaldi;Rhone-Alpes",
    "iso:country":"FR",
    "sg:address":"177 Rue Garibaldi",
    "sg:city":"Lyon",
    "sg:classifiers":[
        {
            "category":"Banks & Credit Unions",
            "subcategory":"Financial Services",
            "type":"Services"
        }
    ],
    "sg:phone":"+33 4 72 84 77 77",
    "sg:postcode":"69003",
    "sg:province":"Rhone-Alpes",
    "sg:tags":[
        "banking",
        "finance",
        "insurance"
    ],
    "wof:name":"Banque Sanpaolo",
    "wof:placetype":"venue"
},
  "geometry": {"coordinates":[4.852541,45.759937],"type":"Point"}
}