{
  "type": "Feature",
  "properties": {
    "addr:full":"ZA des Petits Primeaux Le Pallet Pays de Loire 44330",
    "addr:postcode":"44330",
    "addr:street":"Za Des Petits Primeaux Le Pallet Pays",
    "iso:country":"FR",
    "sg:address":"ZA des Petits Primeaux",
    "sg:city":"Le Pallet",
    "sg:orig_category":"Unclassifiable Establishments",
    "sg:phone":"+33 2 40 80 44 88",
    "sg:postcode":"44330",
    "sg:province":"Pays de Loire",
    "wof:name":"Ad\u00e9com-act Mail S.a.r.l.",
    "wof:placetype":"venue"
},
  "geometry": {"coordinates":[-1.339546,47.140858],"type":"Point"}
}