{
  "type": "Feature",
  "properties": {
    "addr:full":"400, Rue du Docteur Jean-Michel - Lyc\u00e9e J. Michel, 39015 Lons le Saunier Franche-Comt\u00e9",
    "addr:housenumber":"400",
    "addr:postcode":"jean-michel;39015",
    "addr:street":"Rue Du Docteur;Saunier",
    "iso:country":"FR",
    "sg:address":"400, Rue du Docteur Jean-Michel - Lyc\u00e9e J. Michel, 39015 Lons le Saunier",
    "sg:orig_category":"Non-Classified Establishments",
    "sg:phone":"+33 3 84 35 26 10",
    "sg:province":"Franche-Comt\u00e9",
    "wof:name":"Gr\u00e9ta De Lons/champagnole",
    "wof:placetype":"venue"
},
  "geometry": {"coordinates":[5.55178,46.674065],"type":"Point"}
}