{
  "type": "Feature",
  "properties": {
    "addr:full":"48, Rue Waldeck Rousseau, 94400 Vitry sur Seine Ile de France",
    "addr:housenumber":"48",
    "addr:postcode":"94400",
    "addr:street":"Rue Waldeck Rousseau",
    "iso:country":"FR",
    "sg:address":"48, Rue Waldeck Rousseau, 94400 Vitry sur Seine",
    "sg:orig_category":"Unclassifiable Establishments",
    "sg:phone":"+33 1 46 80 14 18",
    "sg:province":"Ile de France",
    "wof:name":"C.a.s.a. - Comptoir D'appareils Pour Soudure Autog\u00e8ne",
    "wof:placetype":"venue"
},
  "geometry": {"coordinates":[2.409116,48.801094],"type":"Point"}
}