{
  "type": "Feature",
  "properties": {
    "addr:full":"580 avenue de l'Industrie 66000 Perpignan Languedoc-Roussillon 66000",
    "addr:housenumber":"580",
    "addr:postcode":"66000;66000",
    "addr:street":"Avenue De L'Industrie",
    "iso:country":"FR",
    "sg:address":"580 avenue de l'Industrie 66000 Perpignan",
    "sg:classifiers":[
        {
            "category":"Education",
            "subcategory":"Special Training",
            "type":"Public Place"
        }
    ],
    "sg:phone":"+33 4 68 38 41 41",
    "sg:postcode":"66000",
    "sg:province":"Languedoc-Roussillon",
    "sg:tags":[
        "bread"
    ],
    "wof:name":"Les Pains Du Sud S.a.",
    "wof:placetype":"venue"
},
  "geometry": {"coordinates":[2.901249,42.731579],"type":"Point"}
}