{
  "type": "Feature",
  "properties": {
    "iso:country":"FR",
    "sg:address":"12, Rue Jean Jaur\u00e8s - Immeuble Plein Jour, 92800 Puteaux",
    "sg:orig_category":"Non-Classified Establishments",
    "sg:phone":"+33 1 47 67 76 76",
    "sg:province":"Ile de France",
    "wof:name":"Lanier",
    "wof:placetype":"venue"
},
  "geometry": {"coordinates":[2.249337,48.885345],"type":"Point"}
}