{
  "type": "Feature",
  "properties": {
    "iso:country":"FR",
    "sg:address":"Chemin de Monthuchet",
    "sg:city":"Saulx les Chartreux",
    "sg:orig_category":"Non-Classified Establishments",
    "sg:phone":"+33 1 64 48 84 95",
    "sg:postcode":"91160",
    "sg:province":"Ile de France",
    "wof:name":"Solignac F.f.c. S.a.r.l.",
    "wof:placetype":"venue"
},
  "geometry": {"coordinates":[2.276735,48.693642],"type":"Point"}
}