{
  "type": "Feature",
  "properties": {
    "addr:full":"B.P. 1, 88410 Bleurville^^3, Rte Nonville, 88410 Bleurville Lorraine",
    "addr:housenumber":"1",
    "addr:postcode":"88410;88410",
    "addr:street":"B.P.;Rte Nonville",
    "iso:country":"FR",
    "sg:address":"B.P. 1, 88410 Bleurville^^3, Rte Nonville, 88410 Bleurville",
    "sg:orig_category":"Non-Classified Establishments",
    "sg:phone":"+33 3 29 09 02 64",
    "sg:province":"Lorraine",
    "wof:name":"Sebeler S.a.",
    "wof:placetype":"venue"
},
  "geometry": {"coordinates":[6.035722,48.03231],"type":"Point"}
}