{
  "type": "Feature",
  "properties": {
    "iso:country":"FR",
    "sg:address":"B.P. 475, 75366 Paris C\u00e9dex 08^^58, Rue de Monceau, 75008 Paris",
    "sg:orig_category":"Non-Classified Establishments",
    "sg:phone":"+33 1 53 83 95 20",
    "sg:province":"Ile de France",
    "wof:name":"Maison De L'autriche S.a.r.l.",
    "wof:placetype":"venue"
},
  "geometry": {"coordinates":[2.34121,48.856926],"type":"Point"}
}