{
  "type": "Feature",
  "properties": {
    "addr:full":"Rue Jospeh Nivet - Centre Artisanal Saint Laurent de Cerdans Languedoc-Roussillon 66260",
    "addr:postcode":"66260",
    "addr:street":"Rue Jospeh Nivet Centre Artisanal",
    "iso:country":"FR",
    "sg:address":"Rue Jospeh Nivet - Centre Artisanal",
    "sg:city":"Saint Laurent de Cerdans",
    "sg:orig_category":"Non-Classified Establishments",
    "sg:phone":"+33 4 68 39 57 57",
    "sg:postcode":"66260",
    "sg:province":"Languedoc-Roussillon",
    "wof:name":"Vallespir Sandales S.a.r.l.",
    "wof:placetype":"venue"
},
  "geometry": {"coordinates":[2.611821,42.386539],"type":"Point"}
}