{
  "type": "Feature",
  "properties": {
    "iso:country":"FR",
    "sg:address":"Puymaret 19360 Malemort Sur Corr\u00eaze",
    "sg:classifiers":[
        {
            "category":"Autos & Motor Vehicles",
            "subcategory":"Automobile Sales",
            "type":"Retail Goods"
        }
    ],
    "sg:phone":"+33 5 55 92 03 04",
    "sg:postcode":"19360",
    "sg:province":"Limousin",
    "sg:tags":[
        "equipment",
        "motor-cars",
        "transport"
    ],
    "wof:name":"Sas Garage Noel Perrier",
    "wof:placetype":"venue"
},
  "geometry": {"coordinates":[-75.87367999999999,39.783821],"type":"Point"}
}