{
  "type": "Feature",
  "properties": {
    "iso:country":"FR",
    "sg:address":"14, Quai de la R\u00e9publique, 60200 Compi\u00e8gne",
    "sg:orig_category":"Non-Classified Establishments",
    "sg:phone":"+33 3 44 83 24 94",
    "sg:province":"Picardie",
    "wof:name":"S\u00e9curitas France S.a.",
    "wof:placetype":"venue"
},
  "geometry": {"coordinates":[2.822855,49.420811],"type":"Point"}
}