{
  "type": "Feature",
  "properties": {
    "addr:full":"Col St Jean 04140 Montclar Aquitaine",
    "addr:postcode":"04140",
    "addr:street":"Col St Jean",
    "iso:country":"FR",
    "sg:address":"Col St Jean 04140 Montclar",
    "sg:classifiers":[
        {
            "category":"Food Court",
            "type":"Food & Drink"
        }
    ],
    "sg:phone":"+33 4 92 35 09 66",
    "sg:province":"Aquitaine",
    "sg:tags":[
        "product",
        "related"
    ],
    "wof:name":"Sources Du Col St Jean",
    "wof:placetype":"venue"
},
  "geometry": {"coordinates":[6.351005,44.41526],"type":"Point"}
}