{
  "type": "Feature",
  "properties": {
    "addr:full":"291, Rte de Rouquairol, 30900 N\u00eemes Languedoc-Roussillon",
    "addr:housenumber":"291",
    "addr:postcode":"30900",
    "addr:street":"Rte De Rouquairol",
    "iso:country":"FR",
    "sg:address":"291, Rte de Rouquairol, 30900 N\u00eemes",
    "sg:orig_category":"Non-Classified Establishments",
    "sg:phone":"+33 4 66 29 85 29",
    "sg:province":"Languedoc-Roussillon",
    "wof:name":"Manuli Sonatra S.a.",
    "wof:placetype":"venue"
},
  "geometry": {"coordinates":[4.331474,43.814034],"type":"Point"}
}