{
  "type": "Feature",
  "properties": {
    "addr:full":"8, Rue Saint Antoine, 93100 Montreuil Ile de France",
    "addr:housenumber":"8",
    "addr:postcode":"93100",
    "addr:street":"Rue Saint Antoine",
    "iso:country":"FR",
    "sg:address":"8, Rue Saint Antoine, 93100 Montreuil",
    "sg:orig_category":"Unclassifiable Establishments",
    "sg:phone":"+33 1 48 58 29 18",
    "sg:province":"Ile de France",
    "wof:name":"Baranco S.a.r.l.",
    "wof:placetype":"venue"
},
  "geometry": {"coordinates":[2.454284,48.864868],"type":"Point"}
}