{
  "type": "Feature",
  "properties": {
    "iso:country":"FR",
    "sg:address":"47 Rue Charles Heller 94405 Vitry Sur Seine Cedex",
    "sg:classifiers":[
        {
            "category":"Food & Beverages",
            "subcategory":"Groceries & Convenience Stores",
            "type":"Retail Goods"
        }
    ],
    "sg:phone":"+33 1 47 18 30 30",
    "sg:province":"Picardie",
    "sg:tags":[
        "product",
        "related"
    ],
    "wof:name":"Ulysse Sa",
    "wof:placetype":"venue"
},
  "geometry": {"coordinates":[2.410745,48.791168],"type":"Point"}
}