{
  "type": "Feature",
  "properties": {
    "iso:country":"FR",
    "sg:address":"ham Moulin 25300 Cluse et Mijoux (La)",
    "sg:classifiers":[
        {
            "category":"Professional",
            "type":"Services"
        }
    ],
    "sg:phone":"+33 3 81 69 45 15",
    "sg:province":"Franche Comt\u00e9",
    "sg:tags":[
        "transport",
        "road"
    ],
    "wof:name":"Ambulances Du Haut Doubs",
    "wof:placetype":"venue"
},
  "geometry": {"coordinates":[6.352208,46.904282],"type":"Point"}
}