{
  "type": "Feature",
  "properties": {
    "addr:full":"Route Nationale - Le Bourg Cour Saint Maurice Franche Comt\u00e9 25380",
    "addr:postcode":"25380",
    "addr:street":"Route Nationale Le Bourg Cour Saint;Franche Comte\u0301",
    "iso:country":"FR",
    "sg:address":"Route Nationale - Le Bourg",
    "sg:city":"Cour Saint Maurice",
    "sg:orig_category":"Unclassifiable Establishments",
    "sg:phone":"+33 3 81 44 32 45",
    "sg:postcode":"25380",
    "sg:province":"Franche Comt\u00e9",
    "wof:name":"Filisetti Scierie S.a.",
    "wof:placetype":"venue"
},
  "geometry": {"coordinates":[6.70346,47.25721],"type":"Point"}
}