{
  "type": "Feature",
  "properties": {
    "iso:country":"FR",
    "sg:address":"Montplaisir 40700 Hagetmau",
    "sg:city":"Hagetmau",
    "sg:orig_category":"Non-Classified Establishments",
    "sg:phone":"+33 5 58 79 56 50",
    "sg:postcode":"40700",
    "sg:province":"Aquitaine",
    "wof:name":"Pab Sud Ouest S.a.",
    "wof:placetype":"venue"
},
  "geometry": {"coordinates":[-0.624728,43.552284],"type":"Point"}
}