{
  "type": "Feature",
  "properties": {
    "iso:country":"FR",
    "sg:address":"Z A Les Chenes 85250 Chavagnes En Paillers",
    "sg:classifiers":[
        {
            "category":"Wholesale",
            "subcategory":"Machinery & Supplies",
            "type":"Manufacturing & Wholesale Goods"
        }
    ],
    "sg:phone":"+33 2 51 42 36 42",
    "sg:postcode":"85250",
    "sg:province":"Pays de Loire",
    "sg:tags":[
        "handling",
        "material",
        "-",
        "machine",
        "equipment",
        "engineering",
        "mechanical"
    ],
    "wof:name":"Alfatec",
    "wof:placetype":"venue"
},
  "geometry": {"coordinates":[-1.122949,46.825233],"type":"Point"}
}