{
  "type": "Feature",
  "properties": {
    "addr:full":"Rue Soudan 02540 Fontenelle En Brie Picardie",
    "addr:postcode":"02540",
    "addr:street":"Rue Soudan",
    "iso:country":"FR",
    "sg:address":"Rue Soudan 02540 Fontenelle En Brie",
    "sg:classifiers":[
        {
            "category":"Professional",
            "type":"Services"
        }
    ],
    "sg:phone":"+33 3 23 69 46 59",
    "sg:province":"Picardie",
    "sg:tags":[
        "transport",
        "road"
    ],
    "wof:name":"Transports Diximus Sarl",
    "wof:placetype":"venue"
},
  "geometry": {"coordinates":[3.4769,48.918896],"type":"Point"}
}