{
  "type": "Feature",
  "properties": {
    "addr:full":"Dom Du Bosquet 30220 Aigues Mortes Languedoc-Roussillon 30220",
    "addr:postcode":"30220;30220",
    "iso:country":"FR",
    "sg:address":"Dom Du Bosquet 30220 Aigues Mortes",
    "sg:classifiers":[
        {
            "category":"Food Court",
            "type":"Food & Drink"
        }
    ],
    "sg:phone":"+33 4 66 53 60 80",
    "sg:postcode":"30220",
    "sg:province":"Languedoc-Roussillon",
    "sg:tags":[
        "product",
        "related"
    ],
    "wof:name":"Domaines Listel",
    "wof:placetype":"venue"
},
  "geometry": {"coordinates":[4.2053,43.565914],"type":"Point"}
}