{
  "type": "Feature",
  "properties": {
    "addr:full":"38, Rue Nationale, 69480 Anse Rhone-Alpes",
    "addr:housenumber":"38",
    "addr:postcode":"69480",
    "addr:street":"Rue Nationale",
    "iso:country":"FR",
    "sg:address":"38, Rue Nationale, 69480 Anse",
    "sg:orig_category":"Non-Classified Establishments",
    "sg:phone":"+33 4 74 09 92 50",
    "sg:province":"Rhone-Alpes",
    "wof:name":"R.a.s. S.a. - Rh\u00f4ne Alpes Services",
    "wof:placetype":"venue"
},
  "geometry": {"coordinates":[4.718958,45.936905],"type":"Point"}
}