{
  "type": "Feature",
  "properties": {
    "addr:full":"Za Bellevue 29170 Pleuven Pleuven Bretagne 29170",
    "addr:postcode":"29170;29170",
    "addr:street":"Za Bellevue",
    "iso:country":"FR",
    "sg:address":"Za Bellevue 29170 Pleuven",
    "sg:city":"Pleuven",
    "sg:classifiers":[
        {
            "category":"Professional",
            "subcategory":"Engineering",
            "type":"Services"
        }
    ],
    "sg:phone":"+33 2 98 51 72 85",
    "sg:postcode":"29170",
    "sg:province":"Bretagne",
    "sg:tags":[
        "machine",
        "-",
        "mechanical"
    ],
    "wof:name":"Irador Sarl",
    "wof:placetype":"venue"
},
  "geometry": {"coordinates":[-4.044222,47.90662],"type":"Point"}
}