{
  "type": "Feature",
  "properties": {
    "iso:country":"FR",
    "sg:address":"7, Rue du Parc de Clagny, 78000 Versailles",
    "sg:orig_category":"Unclassifiable Establishments",
    "sg:phone":"+33 1 30 97 07 07",
    "sg:province":"Ile de France",
    "wof:name":"Wellx T\u00e9l\u00e9com S.a.s.",
    "wof:placetype":"venue"
},
  "geometry": {"coordinates":[2.139969,48.80962],"type":"Point"}
}