{
  "type": "Feature",
  "properties": {
    "addr:full":"Z.I. Chevreuil Ressons sur Matz Picardie 60490",
    "addr:postcode":"60490",
    "addr:street":"Z.I. Chevreuil Ressons Sur Matz Picardie",
    "iso:country":"FR",
    "sg:address":"Z.I. Chevreuil",
    "sg:city":"Ressons sur Matz",
    "sg:orig_category":"Unclassifiable Establishments",
    "sg:phone":"+33 3 44 42 35 39",
    "sg:postcode":"60490",
    "sg:province":"Picardie",
    "wof:name":"Beaudoin Fr\u00e8res S.n.c.",
    "wof:placetype":"venue"
},
  "geometry": {"coordinates":[2.747872,49.544872],"type":"Point"}
}