{
  "type": "Feature",
  "properties": {
    "iso:country":"FR",
    "sg:address":"40, Bd Louis Blanc, 69400 Villefranche sur Sa\u00f4ne",
    "sg:orig_category":"Unclassifiable Establishments",
    "sg:phone":"+33 4 74 78 70 55",
    "sg:province":"Rhone-Alpes",
    "wof:name":"I.f.r.a. Rh\u00f4ne - Institut Formation Rh\u00f4ne Alpes",
    "wof:placetype":"venue"
},
  "geometry": {"coordinates":[4.72145,45.990334],"type":"Point"}
}