{
  "type": "Feature",
  "properties": {
    "addr:full":"58, Chemin de Villedieu, 07100 Annonay Rhone-Alpes",
    "addr:housenumber":"58",
    "addr:postcode":"07100",
    "addr:street":"Chemin De Villedieu",
    "iso:country":"FR",
    "sg:address":"58, Chemin de Villedieu, 07100 Annonay",
    "sg:orig_category":"Non-Classified Establishments",
    "sg:phone":"+33 4 75 32 40 20",
    "sg:province":"Rhone-Alpes",
    "wof:name":"S.e.p.r.",
    "wof:placetype":"venue"
},
  "geometry": {"coordinates":[4.689215,45.247719],"type":"Point"}
}