{
  "type": "Feature",
  "properties": {
    "iso:country":"FR",
    "sg:address":"31 Et 33 Av Gambetta 46200 Souillac",
    "sg:classifiers":[
        {
            "category":"Banks & Credit Unions",
            "subcategory":"Financial Services",
            "type":"Services"
        }
    ],
    "sg:phone":"+33 5 65 27 55 60",
    "sg:postcode":"46200",
    "sg:province":"Midi Pyr\u00e9n\u00e9es",
    "sg:tags":[
        "banking",
        "insurance",
        "institution",
        "finance"
    ],
    "wof:name":"Banque Populaire Du Quercy Et De L'agenais",
    "wof:placetype":"venue"
},
  "geometry": {"coordinates":[1.55895,44.84621],"type":"Point"}
}