{
  "type": "Feature",
  "properties": {
    "iso:country":"FR",
    "sg:address":"2 rue Jacques Daguerre 92500 Rueil Malmaison",
    "sg:classifiers":[
        {
            "category":"Military Area",
            "subcategory":"Army Base",
            "type":"Public Place"
        }
    ],
    "sg:phone":"+33 1 41 96 64 00",
    "sg:postcode":"92500",
    "sg:province":"Ile de France",
    "sg:tags":[
        "chem"
    ],
    "wof:name":"Unilever International Paris S.a.",
    "wof:placetype":"venue"
},
  "geometry": {"coordinates":[2.168869,48.888577],"type":"Point"}
}