{
  "type": "Feature",
  "properties": {
    "iso:country":"FR",
    "sg:address":"B.P. 63102, 14103 Lisieux C\u00e9dex^^Rue Edouard Branly - ZI Nord Est, 14100 Hermival les Vaux",
    "sg:city":"Lisieux",
    "sg:orig_category":"Non-Classified Establishments",
    "sg:phone":"+33 2 31 62 05 44",
    "sg:postcode":"14100",
    "sg:province":"Basse Normandie",
    "wof:name":"Imprimerie Loiseleur S.a.r.l.",
    "wof:placetype":"venue"
},
  "geometry": {"coordinates":[0.189525,49.074329],"type":"Point"}
}