{
  "type": "Feature",
  "properties": {
    "iso:country":"FR",
    "sg:address":"33210 Sauternes",
    "sg:city":"Sauternes",
    "sg:orig_category":"Unclassifiable Establishments",
    "sg:phone":"+33 5 56 76 60 17",
    "sg:postcode":"33210",
    "sg:province":"Aquitaine",
    "wof:name":"Grands Domaines Du Ciron",
    "wof:placetype":"venue"
},
  "geometry": {"coordinates":[-0.342564,44.531319],"type":"Point"}
}