{
  "type": "Feature",
  "properties": {
    "iso:country":"FR",
    "sg:address":"28, Av. du Mar\u00e9chal Foch, 92260 Fontenay aux Roses",
    "sg:orig_category":"Unclassifiable Establishments",
    "sg:phone":"+33 1 41 87 08 25",
    "sg:province":"Ile de France",
    "wof:name":"Vargus Hanita France",
    "wof:placetype":"venue"
},
  "geometry": {"coordinates":[2.298621,48.792427],"type":"Point"}
}