{
  "type": "Feature",
  "properties": {
    "iso:country":"FR",
    "sg:address":"B.P. 11, 69542 Champagne au Mont d'Or C\u00e9dex^^Rue du Ch\u00e2teau d'Eau - ZAC Ouest, 69540 Champagne au Mo",
    "sg:orig_category":"Non-Classified Establishments",
    "sg:phone":"+33 4 78 35 56 56",
    "sg:postcode":"69540",
    "sg:province":"Rhone-Alpes",
    "wof:name":"Gerland Pariot Guillotte S.a.",
    "wof:placetype":"venue"
},
  "geometry": {"coordinates":[-92.43665300000001,38.304611],"type":"Point"}
}