{
  "type": "Feature",
  "properties": {
    "iso:country":"FR",
    "sg:address":"B.P. 598, 77005 Melun C\u00e9dex^^319, Rue Saint Just - Z.I. de Vaux le Penil, 77000 Melun",
    "sg:orig_category":"Non-Classified Establishments",
    "sg:phone":"+33 1 64 37 86 79",
    "sg:postcode":"77000",
    "sg:province":"Ile de France",
    "wof:name":"Entreprise Hanny S.a. Entreprise Hanny S.a.",
    "wof:placetype":"venue"
},
  "geometry": {"coordinates":[2.664085,48.539577],"type":"Point"}
}