{
  "type": "Feature",
  "properties": {
    "addr:full":"55 cours Georges Clemenceau; Bordeaux Bordeaux Aquitaine 33100",
    "addr:housenumber":"55",
    "addr:postcode":"33100",
    "addr:street":"Cours Georges Clemenceau",
    "iso:country":"FR",
    "sg:address":"55 cours Georges Clemenceau; Bordeaux",
    "sg:city":"Bordeaux",
    "sg:classifiers":[
        {
            "category":"Banks & Credit Unions",
            "subcategory":"Bank",
            "type":"Services"
        }
    ],
    "sg:phone":"+33 3356513313",
    "sg:postcode":"33100",
    "sg:province":"Aquitaine",
    "wof:name":"Banque G\u00e9n\u00e9rale Du Commerce",
    "wof:placetype":"venue"
},
  "geometry": {"coordinates":[-0.578742,44.8442],"type":"Point"}
}