{
  "type": "Feature",
  "properties": {
    "addr:full":"5 R des Remparts St-Jacques 66000 Perpignan Languedoc-Roussillon 66000",
    "addr:housenumber":"5",
    "addr:postcode":"66000;66000",
    "addr:street":"R Des Remparts St-Jacques",
    "iso:country":"FR",
    "sg:address":"5 R des Remparts St-Jacques 66000 Perpignan",
    "sg:classifiers":[
        {
            "category":"Building & Trades",
            "subcategory":"Construction",
            "type":"Services"
        }
    ],
    "sg:phone":"+33 4 68 50 05 25",
    "sg:postcode":"66000",
    "sg:province":"Languedoc-Roussillon",
    "sg:tags":[
        "tool",
        "cutting"
    ],
    "wof:name":"Libervit Sarl",
    "wof:placetype":"venue"
},
  "geometry": {"coordinates":[2.901929,42.696808],"type":"Point"}
}