{
  "type": "Feature",
  "properties": {
    "iso:country":"FR",
    "sg:address":"22, Bd du Docteur Veillet, 21000 Dijon",
    "sg:city":"Dijon",
    "sg:orig_category":"Unclassifiable Establishments",
    "sg:phone":"+33 3 80 78 90 55",
    "sg:postcode":"21000",
    "sg:province":"Bourgogne",
    "wof:name":"S.r.p.",
    "wof:placetype":"venue"
},
  "geometry": {"coordinates":[5.053328,47.353298],"type":"Point"}
}