{
  "type": "Feature",
  "properties": {
    "iso:country":"FR",
    "sg:address":"22 Rue Des Entrepreneurs 86000 Poitiers",
    "sg:classifiers":[
        {
            "category":"Shopping",
            "subcategory":"Computers & Home Electronics",
            "type":"Retail Goods"
        }
    ],
    "sg:phone":"+33 5 49 55 93 73",
    "sg:province":"Poitou-Charentes",
    "sg:tags":[
        "electric",
        "electricity",
        "component",
        "equipment",
        "electrical",
        "electronic"
    ],
    "wof:name":"Cge Distribution",
    "wof:placetype":"venue"
},
  "geometry": {"coordinates":[0.345601,46.616829],"type":"Point"}
}