{
  "type": "Feature",
  "properties": {
    "addr:full":"65, Rte des Ch\u00e8vres, 01570 Feillens Rhone-Alpes 01570",
    "addr:housenumber":"65",
    "addr:postcode":"01570;01570",
    "addr:street":"Rte Des Che\u0300Vres;Rhone-Alpes",
    "iso:country":"FR",
    "sg:address":"65, Rte des Ch\u00e8vres, 01570 Feillens",
    "sg:orig_category":"Unclassifiable Establishments",
    "sg:phone":"+33 3 85 30 04 27",
    "sg:postcode":"01570",
    "sg:province":"Rhone-Alpes",
    "wof:name":"Entreprise Vaissaud Marc",
    "wof:placetype":"venue"
},
  "geometry": {"coordinates":[4.89095,46.339874],"type":"Point"}
}