{
  "type": "Feature",
  "properties": {
    "addr:full":"Lot Z I Baleone 20167 AFA Corse 20167",
    "addr:postcode":"20167;20167",
    "addr:street":"Z I Baleone",
    "iso:country":"FR",
    "sg:address":"Lot Z I Baleone 20167 AFA",
    "sg:classifiers":[
        {
            "category":"Utilities",
            "subcategory":"Natural Gas",
            "type":"Services"
        }
    ],
    "sg:phone":"+33 4 95 22 27 07",
    "sg:postcode":"20167",
    "sg:province":"Corse",
    "wof:name":"Ste Corse Gaz S.a.r.l.",
    "wof:placetype":"venue"
},
  "geometry": {"coordinates":[8.668294,41.959526],"type":"Point"}
}