{
  "type": "Feature",
  "properties": {
    "iso:country":"FR",
    "sg:address":"Rue D'Islande 91971 Courtaboeuf",
    "sg:orig_category":"Fabrics Metallurgy and Metalworking Plastics Rubber and Plastics Textiles and Clothing Tools",
    "sg:phone":"+33 1 69 18 38 00",
    "sg:province":"Haute Normandie",
    "wof:name":"Freudenberg Sa",
    "wof:placetype":"venue"
},
  "geometry": {"coordinates":[-19.02116,64.963943],"type":"Point"}
}