{
  "type": "Feature",
  "properties": {
    "iso:country":"FR",
    "sg:address":"Les Pierrelles BP 98 26241 Saint Vallier",
    "sg:city":"Allier",
    "sg:classifiers":[
        {
            "category":"Airport",
            "type":"Transportation"
        }
    ],
    "sg:phone":"+33 4 75 23 25 26",
    "sg:postcode":"65360",
    "sg:province":"Midi Pyr\u00e9n\u00e9es",
    "sg:tags":[
        "transport",
        "air"
    ],
    "wof:name":"Groupe Norbert Dentressangle Si\u00d4ge Social",
    "wof:placetype":"venue"
},
  "geometry": {"coordinates":[2.035775,45.906776],"type":"Point"}
}