{
  "type": "Feature",
  "properties": {
    "addr:full":"Les Collines de l'Arche - Immeuble Op\u00e9ra 2 Courbevoie C\u00e9dex California 92057",
    "addr:housenumber":"2",
    "addr:postcode":"92057",
    "iso:country":"FR",
    "sg:address":"Les Collines de l'Arche - Immeuble Op\u00e9ra 2",
    "sg:city":"Courbevoie C\u00e9dex",
    "sg:orig_category":"Non-Classified Establishments",
    "sg:phone":"+33 1 49 07 22 22",
    "sg:postcode":"92057",
    "sg:province":"California",
    "wof:name":"Systems Union France S.a.r.l.",
    "wof:placetype":"venue"
},
  "geometry": {"coordinates":[-117.286034,33.25243],"type":"Point"}
}