{
  "type": "Feature",
  "properties": {
    "iso:country":"FR",
    "sg:address":"ZI 2",
    "sg:city":"Rouvignies",
    "sg:orig_category":"Unclassifiable Establishments",
    "sg:phone":"+33 3 27 21 18 50",
    "sg:postcode":"59220",
    "sg:province":"Nord Pas-de-Calais",
    "wof:name":"Petiau Pierre S.a.r.l.",
    "wof:placetype":"venue"
},
  "geometry": {"coordinates":[3.39305,50.326897],"type":"Point"}
}