{
  "type": "Feature",
  "properties": {
    "addr:full":"146 avenue du M\u00f4le 74460 MARNAZ Rhone-Alpes",
    "addr:housenumber":"146",
    "addr:postcode":"74460",
    "addr:street":"Avenue Du Mo\u0302Le",
    "iso:country":"FR",
    "sg:address":"146 avenue du M\u00f4le 74460 MARNAZ",
    "sg:classifiers":[
        {
            "category":"Wholesale",
            "subcategory":"Auto Parts",
            "type":"Manufacturing & Wholesale Goods"
        }
    ],
    "sg:phone":"+33 4 50 98 67 05",
    "sg:province":"Rhone-Alpes",
    "sg:tags":[
        "turned",
        "precision"
    ],
    "wof:name":"Briffaz Albert Et Cie Sa",
    "wof:placetype":"venue"
},
  "geometry": {"coordinates":[6.527002,46.072029],"type":"Point"}
}