{
  "type": "Feature",
  "properties": {
    "iso:country":"FR",
    "sg:address":"Av. du Cerisier Noir",
    "sg:city":"Naintr\u00e9",
    "sg:orig_category":"Non-Classified Establishments",
    "sg:phone":"+33 5 49 90 28 30",
    "sg:postcode":"86530",
    "sg:province":"Poitou-Charentes",
    "wof:name":"Editions M\u00e9gastar S.a.",
    "wof:placetype":"venue"
},
  "geometry": {"coordinates":[0.484104,46.756695],"type":"Point"}
}