{
  "type": "Feature",
  "properties": {
    "addr:full":"6 B Rue Rene Cassin La Patte D Oie D Herblay 95220 Herblay Ile de France 95220",
    "addr:housenumber":"6 b",
    "addr:postcode":"95220;ile;95220",
    "addr:street":"Rue Rene Cassin;France",
    "iso:country":"FR",
    "sg:address":"6 B Rue Rene Cassin La Patte D Oie D Herblay 95220 Herblay",
    "sg:classifiers":[
        {
            "category":"Transit Center",
            "subcategory":"Freight",
            "type":"Transportation"
        }
    ],
    "sg:phone":"+33 1 39 78 63 42",
    "sg:postcode":"95220",
    "sg:province":"Ile de France",
    "sg:tags":[
        "metallurgy",
        "pipe",
        "metalworking",
        "sheet"
    ],
    "wof:name":"Technicable",
    "wof:placetype":"venue"
},
  "geometry": {"coordinates":[2.163532,48.989609],"type":"Point"}
}