{
  "type": "Feature",
  "properties": {
    "iso:country":"FR",
    "sg:address":"Route De Bapaume 80300 Albert",
    "sg:classifiers":[
        {
            "category":"Manufacturing",
            "subcategory":"Metals",
            "type":"Manufacturing & Wholesale Goods"
        }
    ],
    "sg:phone":"+33 3 22 74 43 24",
    "sg:postcode":"80300",
    "sg:province":"Picardie",
    "sg:tags":[
        "-",
        "machine",
        "equipment",
        "engineering",
        "machinery",
        "mechanical"
    ],
    "wof:name":"Forest Line Albert",
    "wof:placetype":"venue"
},
  "geometry": {"coordinates":[2.671451,50.01038],"type":"Point"}
}