{
  "type": "Feature",
  "properties": {
    "addr:full":"B.P. 90, 69882 Meyzieu C\u00e9dex^^27, Rue Jules Vall\u00e9s, 69330 Meyzieu Rhone-Alpes 69330",
    "addr:postcode":"69882;69330;69330",
    "addr:street":"B.P. 90;Rue Jules Valle\u0301S",
    "iso:country":"FR",
    "sg:address":"B.P. 90, 69882 Meyzieu C\u00e9dex^^27, Rue Jules Vall\u00e9s, 69330 Meyzieu",
    "sg:orig_category":"Non-Classified Establishments",
    "sg:phone":"+33 4 78 04 10 95",
    "sg:postcode":"69330",
    "sg:province":"Rhone-Alpes",
    "wof:name":"Ares Conseil D'entreprise S.a.r.l.",
    "wof:placetype":"venue"
},
  "geometry": {"coordinates":[5.00581,45.766296],"type":"Point"}
}