{
  "type": "Feature",
  "properties": {
    "addr:full":"B.P. 12 Lagny le Sec Picardie 60330",
    "addr:postcode":"60330",
    "addr:street":"B.P. 12 Lagny Le Sec Picardie",
    "iso:country":"FR",
    "sg:address":"B.P. 12",
    "sg:city":"Lagny le Sec",
    "sg:orig_category":"Non-Classified Establishments",
    "sg:phone":"+33 3 44 60 65 00",
    "sg:postcode":"60330",
    "sg:province":"Picardie",
    "wof:name":"T.n.t. Logistique France S.a.",
    "wof:placetype":"venue"
},
  "geometry": {"coordinates":[2.746227,49.088638],"type":"Point"}
}