{
  "type": "Feature",
  "properties": {
    "addr:full":"Fontrousse 42703 Firminy Midi Pyr\u00e9n\u00e9es",
    "addr:postcode":"42703",
    "addr:street":"Fontrousse",
    "iso:country":"FR",
    "sg:address":"Fontrousse 42703 Firminy",
    "sg:classifiers":[
        {
            "category":"Manufacturing",
            "subcategory":"Rubber & Plastics",
            "type":"Manufacturing & Wholesale Goods"
        }
    ],
    "sg:phone":"+33 4 77 40 12 00",
    "sg:province":"Midi Pyr\u00e9n\u00e9es",
    "wof:name":"Autobar Flexible France Sas",
    "wof:placetype":"venue"
},
  "geometry": {"coordinates":[4.278008,45.384243],"type":"Point"}
}