{
  "type": "Feature",
  "properties": {
    "iso:country":"FR",
    "sg:address":"64 Rue De La Joliette 13002 Marseille",
    "sg:classifiers":[
        {
            "category":"Banks & Credit Unions",
            "subcategory":"Investment Brokerage",
            "type":"Services"
        }
    ],
    "sg:phone":"+33 4 91 56 58 70",
    "sg:province":"Provence-Alpes-C\u00f4te d'Azur",
    "sg:tags":[
        "-",
        "transport",
        "related"
    ],
    "wof:name":"Joliette Transit International Sa",
    "wof:placetype":"venue"
},
  "geometry": {"coordinates":[5.370365,43.302967],"type":"Point"}
}