{
  "type": "Feature",
  "properties": {
    "iso:country":"FR",
    "sg:address":"6, Rue de l'Energie - ZAE Sud, 67210 Obernai",
    "sg:city":"Obernai",
    "sg:orig_category":"Unclassifiable Establishments",
    "sg:phone":"+33 3 88 95 56 50",
    "sg:postcode":"67210",
    "sg:province":"Alsace",
    "wof:name":"Boitembal S.a.r.l.",
    "wof:placetype":"venue"
},
  "geometry": {"coordinates":[7.494401,48.453373],"type":"Point"}
}