{
  "type": "Feature",
  "properties": {
    "iso:country":"FR",
    "sg:address":"46 Avenue Charles De Gaulle 81100 Castres",
    "sg:classifiers":[
        {
            "category":"Utilities",
            "subcategory":"Electric",
            "type":"Services"
        }
    ],
    "sg:phone":"+33 810 13 39 23",
    "sg:postcode":"81100",
    "sg:province":"Midi Pyr\u00e9n\u00e9es",
    "sg:tags":[
        "electricity",
        "raw",
        "energy",
        "material"
    ],
    "wof:name":"Electricite De France (edf)",
    "wof:placetype":"venue"
},
  "geometry": {"coordinates":[2.252701,43.60112],"type":"Point"}
}