{
  "type": "Feature",
  "properties": {
    "iso:country":"FR",
    "sg:address":"boulevard Gustave Roch 44200 Nantes",
    "sg:classifiers":[
        {
            "category":"Food & Beverages",
            "subcategory":"Fruits & Vegetables",
            "type":"Retail Goods"
        }
    ],
    "sg:phone":"+33 2 40 47 17 74",
    "sg:postcode":"44200",
    "sg:province":"Pays de Loire",
    "wof:name":"Bouyer Et Guindon Sa",
    "wof:placetype":"venue"
},
  "geometry": {"coordinates":[-1.547734,47.205116],"type":"Point"}
}