{
  "type": "Feature",
  "properties": {
    "iso:country":"FR",
    "sg:address":"Rue De Buffon 45063 Orl\u00e9ans Cedex 2",
    "sg:classifiers":[
        {
            "category":"Utilities",
            "type":"Services"
        }
    ],
    "sg:phone":"+33 2 38 51 73 73",
    "sg:province":"Centre",
    "sg:tags":[
        "raw",
        "energy",
        "material"
    ],
    "wof:name":"Agence De L'eau Loire-bretagne",
    "wof:placetype":"venue"
},
  "geometry": {"coordinates":[1.94651,47.820415],"type":"Point"}
}