{
  "type": "Feature",
  "properties": {
    "addr:full":"60, Rue Auguste Perret - Parc technologique Europarc, 94043 Cr\u00e9teil C\u00e9dex Pays de Loire",
    "addr:housenumber":"60",
    "addr:postcode":"94043;ce\u0301dex",
    "addr:street":"Rue Auguste Perret",
    "iso:country":"FR",
    "sg:address":"60, Rue Auguste Perret - Parc technologique Europarc, 94043 Cr\u00e9teil C\u00e9dex",
    "sg:orig_category":"Non-Classified Establishments",
    "sg:phone":"+33 1 43 99 12 02",
    "sg:province":"Pays de Loire",
    "wof:name":"Epson Engineering France S.a.",
    "wof:placetype":"venue"
},
  "geometry": {"coordinates":[2.473915,48.764835],"type":"Point"}
}