{
  "type": "Feature",
  "properties": {
    "addr:full":"Vaubrault 37210 Chan\u00e7ay Chan\u00e7ay Centre 37210",
    "addr:housenumber":"chanc\u0327ay",
    "addr:postcode":"37210;37210",
    "addr:street":"Vaubrault",
    "iso:country":"FR",
    "sg:address":"Vaubrault 37210 Chan\u00e7ay",
    "sg:city":"Chan\u00e7ay",
    "sg:orig_category":"Non-Classified Establishments",
    "sg:phone":"+33 2 47 52 93 16",
    "sg:postcode":"37210",
    "sg:province":"Centre",
    "wof:name":"Serpot S.a.",
    "wof:placetype":"venue"
},
  "geometry": {"coordinates":[0.914735,47.448383],"type":"Point"}
}