{
  "type": "Feature",
  "properties": {
    "addr:full":"120, Place Camille Prost, 39300 Champagnole Franche Comt\u00e9",
    "addr:housenumber":"120",
    "addr:postcode":"39300",
    "addr:street":"Place Camille Prost;Franche Comte\u0301",
    "iso:country":"FR",
    "sg:address":"120, Place Camille Prost, 39300 Champagnole",
    "sg:orig_category":"Unclassifiable Establishments",
    "sg:phone":"+33 3 84 53 13 53",
    "sg:province":"Franche Comt\u00e9",
    "wof:name":"Bugada Bernard Et Compagnie S.a.",
    "wof:placetype":"venue"
},
  "geometry": {"coordinates":[5.908725,46.747513],"type":"Point"}
}