{
  "type": "Feature",
  "properties": {
    "addr:full":"Aux Brousses 24300 Javerlhac et la Chapelle Saint Ro La Chapelle-Montmoreau Aquitaine 24300",
    "addr:postcode":"24300;24300",
    "addr:street":"La;Saint Ro La Chapelle-Montmoreau",
    "iso:country":"FR",
    "sg:address":"Aux Brousses 24300 Javerlhac et la Chapelle Saint Ro",
    "sg:city":"La Chapelle-Montmoreau",
    "sg:orig_category":"Non-Classified Establishments",
    "sg:phone":"+33 5 53 56 34 03",
    "sg:postcode":"24300",
    "sg:province":"Aquitaine",
    "wof:name":"P\u00e9pini\u00e8res Deschamps Christian E.a.r.l.",
    "wof:placetype":"venue"
},
  "geometry": {"coordinates":[0.55877,45.55434],"type":"Point"}
}