{
  "type": "Feature",
  "properties": {
    "addr:full":"B.P. 16 Saint Pierre d'Albigny C\u00e9dex Rhone-Alpes 73250",
    "addr:housenumber":"16",
    "addr:postcode":"73250",
    "addr:street":"B.P.",
    "iso:country":"FR",
    "sg:address":"B.P. 16",
    "sg:city":"Saint Pierre d'Albigny C\u00e9dex",
    "sg:orig_category":"Non-Classified Establishments",
    "sg:phone":"+33 4 79 28 50 04",
    "sg:postcode":"73250",
    "sg:province":"Rhone-Alpes",
    "wof:name":"Sampa-helios S.a.",
    "wof:placetype":"venue"
},
  "geometry": {"coordinates":[6.14549,45.564381],"type":"Point"}
}