{
  "type": "Feature",
  "properties": {
    "iso:country":"FR",
    "sg:address":"5 cours Ferdinand de Lesseps 92500 Rueil Malmaison",
    "sg:classifiers":[
        {
            "category":"Structure",
            "subcategory":"Shopping Mall",
            "type":"Public Place"
        }
    ],
    "sg:phone":"+33 1 47 16 47 00",
    "sg:province":"Ile de France",
    "sg:tags":[
        "steel",
        "frame"
    ],
    "wof:name":"Campenon Bernard S.a.",
    "wof:placetype":"venue"
},
  "geometry": {"coordinates":[2.16558,48.889004],"type":"Point"}
}