{
  "type": "Feature",
  "properties": {
    "iso:country":"FR",
    "sg:address":"Pl De La Fontaine 70210 Selles",
    "sg:classifiers":[
        {
            "category":"Food & Beverages",
            "subcategory":"Dairy",
            "type":"Retail Goods"
        }
    ],
    "sg:phone":"+33 3 84 92 42 44",
    "sg:postcode":"70210",
    "sg:province":"Franche Comt\u00e9",
    "sg:tags":[
        "product",
        "related"
    ],
    "wof:name":"Fromagerie Roussey Sa",
    "wof:placetype":"venue"
},
  "geometry": {"coordinates":[6.08936,47.962273],"type":"Point"}
}