{
  "type": "Feature",
  "properties": {
    "addr:full":"RN 8 - Quartier Quiez Ollioules Midi Pyr\u00e9n\u00e9es 83190",
    "addr:postcode":"83190",
    "addr:street":"Rn 8 Quartier Quiez",
    "iso:country":"FR",
    "sg:address":"RN 8 - Quartier Quiez",
    "sg:city":"Ollioules",
    "sg:orig_category":"Non-Classified Establishments",
    "sg:phone":"+33 4 94 09 08 95",
    "sg:postcode":"83190",
    "sg:province":"Midi Pyr\u00e9n\u00e9es",
    "wof:name":"Capricorne Propret\u00e9 S.a.",
    "wof:placetype":"venue"
},
  "geometry": {"coordinates":[5.87611,43.129589],"type":"Point"}
}