{
  "type": "Feature",
  "properties": {
    "iso:country":"FR",
    "sg:address":"Rue Hans Geiger",
    "sg:city":"Arras",
    "sg:orig_category":"Unclassifiable Establishments",
    "sg:phone":"+33 3 21 60 91 60",
    "sg:postcode":"62000",
    "sg:province":"Nord Pas-de-Calais",
    "wof:name":"Rabot Dutilleul S.a.",
    "wof:placetype":"venue"
},
  "geometry": {"coordinates":[2.805078,50.288284],"type":"Point"}
}