{
  "type": "Feature",
  "properties": {
    "iso:country":"FR",
    "sg:address":"190, Bd des Ambassadeurs, 95220 Herblay",
    "sg:orig_category":"Unclassifiable Establishments",
    "sg:phone":"+33 1 34 50 83 73",
    "sg:province":"Ile de France",
    "wof:name":"Net Garden S.a.r.l.",
    "wof:placetype":"venue"
},
  "geometry": {"coordinates":[2.1642,48.997166],"type":"Point"}
}