{
  "type": "Feature",
  "properties": {
    "addr:full":"107, Av. de la Prospective, 18000 Bourges Bourges Centre 18000",
    "addr:postcode":"18000;18000",
    "addr:street":"107 Av. De La Prospective",
    "iso:country":"FR",
    "sg:address":"107, Av. de la Prospective, 18000 Bourges",
    "sg:city":"Bourges",
    "sg:orig_category":"Unclassifiable Establishments",
    "sg:phone":"+33 2 48 23 74 74",
    "sg:postcode":"18000",
    "sg:province":"Centre",
    "wof:name":"Etablissement Colom Alberti S.a.",
    "wof:placetype":"venue"
},
  "geometry": {"coordinates":[2.394577,47.106628],"type":"Point"}
}