{
  "type": "Feature",
  "properties": {
    "addr:full":"B.P. 521, 81107 Castres C\u00e9dex^^ZI de M\u00e9lou, 81100 Castres Midi Pyr\u00e9n\u00e9es 81100",
    "addr:housenumber":"b.p. 521",
    "addr:postcode":"81107;81100;81100",
    "addr:street":"Me\u0301Lou",
    "iso:country":"FR",
    "sg:address":"B.P. 521, 81107 Castres C\u00e9dex^^ZI de M\u00e9lou, 81100 Castres",
    "sg:orig_category":"Non-Classified Establishments",
    "sg:phone":"+33 5 63 59 31 30",
    "sg:postcode":"81100",
    "sg:province":"Midi Pyr\u00e9n\u00e9es",
    "wof:name":"C.3.l. S.n.c.",
    "wof:placetype":"venue"
},
  "geometry": {"coordinates":[2.257356,43.56094],"type":"Point"}
}