{
  "type": "Feature",
  "properties": {
    "iso:country":"FR",
    "sg:address":"Les Usines 73240 Gresin",
    "sg:orig_category":"Non-Classified Establishments",
    "sg:phone":"+33 4 76 31 65 79",
    "sg:postcode":"73240",
    "sg:province":"Rhone-Alpes",
    "wof:name":"R.e.s. S.a. - Rev\u00eatement Electrolytique Savoisien",
    "wof:placetype":"venue"
},
  "geometry": {"coordinates":[5.652775,45.605461],"type":"Point"}
}