{
  "type": "Feature",
  "properties": {
    "addr:full":"B.P. 224, 60802 Cr\u00e9py en Valois C\u00e9dex^^Rue du Bois de Tillet, 60800 Cr\u00e9py en Valois Picardie",
    "addr:housenumber":"b.p. 224",
    "addr:postcode":"60802;60800 cre\u0301py en",
    "addr:street":"En;Bois De Tillet",
    "iso:country":"FR",
    "sg:address":"B.P. 224, 60802 Cr\u00e9py en Valois C\u00e9dex^^Rue du Bois de Tillet, 60800 Cr\u00e9py en Valois",
    "sg:orig_category":"Non-Classified Establishments",
    "sg:phone":"+33 3 44 94 42 00",
    "sg:province":"Picardie",
    "wof:name":"F.m. Logistic S.a.",
    "wof:placetype":"venue"
},
  "geometry": {"coordinates":[2.887172,49.235062],"type":"Point"}
}