{
  "type": "Feature",
  "properties": {
    "addr:full":"1572, Rue Achille P\u00e9r\u00e8s - ZI Petite Synthe, 59640 Dunkerque Nord-Pas-de-Calais",
    "addr:housenumber":"1572",
    "addr:postcode":"59640",
    "addr:street":"Rue Achille Pe\u0301Re\u0300S Zi Petite Synthe",
    "iso:country":"FR",
    "sg:address":"1572, Rue Achille P\u00e9r\u00e8s - ZI Petite Synthe, 59640 Dunkerque",
    "sg:orig_category":"Non-Classified Establishments",
    "sg:phone":"+33 3 28 25 02 43",
    "sg:province":"Nord-Pas-de-Calais",
    "wof:name":"S.m.s.m. S.a.r.l. - Soci\u00e9t\u00e9 Maritime De Soudure Et De Montage",
    "wof:placetype":"venue"
},
  "geometry": {"coordinates":[2.35294,51.022812],"type":"Point"}
}