{
  "type": "Feature",
  "properties": {
    "iso:country":"FR",
    "sg:address":"2 Rue Marcel Dassault 94510 La Queue En Brie",
    "sg:classifiers":[
        {
            "category":"Manufacturing",
            "subcategory":"Motor Vehicles & Parts",
            "type":"Manufacturing & Wholesale Goods"
        }
    ],
    "sg:phone":"+33 1 45 93 05 25",
    "sg:postcode":"94510",
    "sg:province":"Ile de France",
    "sg:tags":[
        "engine",
        "machine",
        "engineering",
        "-",
        "mechanical"
    ],
    "wof:name":"Ste Nouvelle De Transmissions Sa",
    "wof:placetype":"venue"
},
  "geometry": {"coordinates":[2.573948,48.779305],"type":"Point"}
}