{
  "type": "Feature",
  "properties": {
    "addr:full":"1 Rue Louis Pasteur 67160 Wissembourg Wissembourg Alsace 67160",
    "addr:housenumber":"1",
    "addr:postcode":"67160;67160",
    "addr:street":"Rue Louis Pasteur",
    "iso:country":"FR",
    "sg:address":"1 Rue Louis Pasteur 67160 Wissembourg",
    "sg:city":"Wissembourg",
    "sg:classifiers":[
        {
            "category":"Shopping",
            "subcategory":"Computers & Home Electronics",
            "type":"Retail Goods"
        }
    ],
    "sg:phone":"+33 3 88 05 38 50",
    "sg:postcode":"67160",
    "sg:province":"Alsace",
    "sg:tags":[
        "equipment",
        "electrical",
        "component",
        "electric",
        "electronic"
    ],
    "wof:name":"Dbk France",
    "wof:placetype":"venue"
},
  "geometry": {"coordinates":[7.962788,49.022675],"type":"Point"}
}