{
  "type": "Feature",
  "properties": {
    "addr:full":"Rue Gutenberg - ZI de la Bergerie La S\u00e9guini\u00e8re Pays de Loire 49280",
    "addr:postcode":"49280",
    "addr:street":"Rue Gutenberg Zi De La Bergerie",
    "iso:country":"FR",
    "sg:address":"Rue Gutenberg - ZI de la Bergerie",
    "sg:city":"La S\u00e9guini\u00e8re",
    "sg:orig_category":"Unclassifiable Establishments",
    "sg:phone":"+33 2 41 56 99 77",
    "sg:postcode":"49280",
    "sg:province":"Pays de Loire",
    "wof:name":"Equ'inox 49 S.a.r.l.",
    "wof:placetype":"venue"
},
  "geometry": {"coordinates":[-0.849369,47.005348],"type":"Point"}
}