{
  "type": "Feature",
  "properties": {
    "addr:full":"11, Rue de la Madeleine, 33170 Gradignan Gradignan Aquitaine 33170",
    "addr:housenumber":"11",
    "addr:postcode":"33170;33170",
    "addr:street":"Rue De La Madeleine",
    "iso:country":"FR",
    "sg:address":"11, Rue de la Madeleine, 33170 Gradignan",
    "sg:city":"Gradignan",
    "sg:orig_category":"Non-Classified Establishments",
    "sg:phone":"+33 5 56 75 33 62",
    "sg:postcode":"33170",
    "sg:province":"Aquitaine",
    "wof:name":"Genlis Cosm\u00e9tiques S.a.",
    "wof:placetype":"venue"
},
  "geometry": {"coordinates":[-0.637079,44.77562],"type":"Point"}
}