{
  "type": "Feature",
  "properties": {
    "addr:full":"20, Rue de Royon, 92310 S\u00e8vres Ile de France",
    "addr:housenumber":"20",
    "addr:postcode":"92310",
    "addr:street":"Rue De Royon",
    "iso:country":"FR",
    "sg:address":"20, Rue de Royon, 92310 S\u00e8vres",
    "sg:orig_category":"Unclassifiable Establishments",
    "sg:phone":"+33 1 41 14 43 16",
    "sg:province":"Ile de France",
    "wof:name":"Geser S.a.r.l.",
    "wof:placetype":"venue"
},
  "geometry": {"coordinates":[2.2269,48.825821],"type":"Point"}
}