{
  "type": "Feature",
  "properties": {
    "iso:country":"FR",
    "sg:address":"2, Rue de Toufflers, 59390 Lys lez Lannoy",
    "sg:orig_category":"Unclassifiable Establishments",
    "sg:phone":"+33 3 20 89 43 13",
    "sg:province":"Nord Pas-de-Calais",
    "wof:name":"Provaal S.a.",
    "wof:placetype":"venue"
},
  "geometry": {"coordinates":[3.22795,50.673069],"type":"Point"}
}