{
  "type": "Feature",
  "properties": {
    "addr:full":"26 Rue Dupouy 59140 Dunkerque Nord Pas-de-Calais 59140",
    "addr:housenumber":"26",
    "addr:postcode":"59140;59140",
    "addr:street":"Rue Dupouy",
    "iso:country":"FR",
    "sg:address":"26 Rue Dupouy 59140 Dunkerque",
    "sg:classifiers":[
        {
            "category":"Professional",
            "subcategory":"Advertising",
            "type":"Services"
        }
    ],
    "sg:phone":"+33 3 28 23 52 35",
    "sg:postcode":"59140",
    "sg:province":"Nord Pas-de-Calais",
    "sg:tags":[
        "information",
        "medium",
        "communication"
    ],
    "wof:name":"Fun Radio Europe 2",
    "wof:placetype":"venue"
},
  "geometry": {"coordinates":[2.378707,51.033363],"type":"Point"}
}