{
  "type": "Feature",
  "properties": {
    "addr:full":"22 rue de Palestro Paris 75002",
    "addr:housenumber":"22",
    "addr:postcode":"75002",
    "addr:street":"Rue De Palestro",
    "iso:country":"FR",
    "sg:address":"22 rue de Palestro",
    "sg:city":"Paris",
    "sg:classifiers":[
        {
            "category":"Professional",
            "subcategory":"Advertising",
            "type":"Services"
        }
    ],
    "sg:postcode":"75002",
    "sg:tags":[
        "e-commerce",
        "search-marketing",
        "sem",
        "seo",
        "magento",
        "web",
        "ecommerce",
        "web-design",
        "web-development"
    ],
    "sg:website":"http://www.baobaz.com",
    "wof:name":"Baobaz",
    "wof:placetype":"venue"
},
  "geometry": {"coordinates":[2.351824,48.865996],"type":"Point"}
}