{
  "type": "Feature",
  "properties": {
    "addr:full":"23 R des Lieutenants Chauveau 71100 CHALON SUR SAONE Chalon-sur-Sa\u00f4ne Bourgogne 71100",
    "addr:housenumber":"23",
    "addr:postcode":"71100;71100",
    "addr:street":"R Des Lieutenants Chauveau",
    "iso:country":"FR",
    "sg:address":"23 R des Lieutenants Chauveau 71100 CHALON SUR SAONE",
    "sg:city":"Chalon-sur-Sa\u00f4ne",
    "sg:orig_category":"Uniform Caps",
    "sg:phone":"+33 3 85 97 04 00",
    "sg:postcode":"71100",
    "sg:province":"Bourgogne",
    "wof:name":"Etablissements Joly-chamoin Sa",
    "wof:placetype":"venue"
},
  "geometry": {"coordinates":[4.840235,46.781052],"type":"Point"}
}