{
  "type": "Feature",
  "properties": {
    "addr:full":"all\u00e9e du Poirier 49000 Angers Pays de Loire 49000",
    "addr:postcode":"49000;49000",
    "addr:street":"Alle\u0301E Du Poirier",
    "iso:country":"FR",
    "sg:address":"all\u00e9e du Poirier 49000 Angers",
    "sg:classifiers":[
        {
            "category":"Social Services",
            "subcategory":"Child Care",
            "type":"Services"
        }
    ],
    "sg:phone":"+33 2 41 31 17 50",
    "sg:postcode":"49000",
    "sg:province":"Pays de Loire",
    "sg:tags":[
        "baby",
        "product"
    ],
    "wof:name":"Plasti Temple Sa",
    "wof:placetype":"venue"
},
  "geometry": {"coordinates":[-0.528566,47.449669],"type":"Point"}
}