{
  "type": "Feature",
  "properties": {
    "addr:full":"74 Rue Andre Ampere Ji Jarlard 81000 Albi Midi Pyr\u00e9n\u00e9es",
    "addr:housenumber":"74",
    "addr:postcode":"81000",
    "addr:street":"Rue Andre Ampere;Jarlard",
    "iso:country":"FR",
    "sg:address":"74 Rue Andre Ampere Ji Jarlard 81000 Albi",
    "sg:classifiers":[
        {
            "category":"Real Estate",
            "subcategory":"Architect",
            "type":"Services"
        }
    ],
    "sg:phone":"+33 5 63 77 83 83",
    "sg:province":"Midi Pyr\u00e9n\u00e9es",
    "sg:tags":[
        "textile",
        "clothing"
    ],
    "wof:name":"School Rag",
    "wof:placetype":"venue"
},
  "geometry": {"coordinates":[2.192571,43.926327],"type":"Point"}
}