{
  "type": "Feature",
  "properties": {
    "iso:country":"FR",
    "sg:address":"Rte de Philippeville - ZI Ouest",
    "sg:city":"Givet",
    "sg:orig_category":"Non-Classified Establishments",
    "sg:phone":"+33 3 24 40 42 85",
    "sg:postcode":"08600",
    "sg:province":"Champagne",
    "wof:name":"Isopac S.a.",
    "wof:placetype":"venue"
},
  "geometry": {"coordinates":[4.82085,50.134769],"type":"Point"}
}