{
  "type": "Feature",
  "properties": {
    "iso:country":"FR",
    "sg:address":"110 Bd Du Midi 06150 Cannes La Bocca",
    "sg:classifiers":[
        {
            "category":"Autos & Motor Vehicles",
            "subcategory":"Boat Sales",
            "type":"Retail Goods"
        }
    ],
    "sg:phone":"+33 4 93 47 12 62",
    "sg:tags":[
        "equipment",
        "transport"
    ],
    "wof:name":"Elco International",
    "wof:placetype":"venue"
},
  "geometry": {"coordinates":[6.987438,43.548744],"type":"Point"}
}