{
  "type": "Feature",
  "properties": {
    "iso:country":"FR",
    "sg:address":"52800 Mandres la C\u00f4te",
    "sg:orig_category":"Unclassifiable Establishments",
    "sg:phone":"+33 3 25 31 81 54",
    "sg:province":"Champagne",
    "wof:name":"M\u00e9cadis S.a.r.l.",
    "wof:placetype":"venue"
},
  "geometry": {"coordinates":[5.336336,48.063053],"type":"Point"}
}