{
  "type": "Feature",
  "properties": {
    "addr:full":"10, Rue du 8 Mai 1945, 72540 Lou\u00e9 Pays de Loire",
    "addr:housenumber":"10",
    "addr:postcode":"72540",
    "addr:street":"Rue Du 8 Mai 1945",
    "iso:country":"FR",
    "sg:address":"10, Rue du 8 Mai 1945, 72540 Lou\u00e9",
    "sg:orig_category":"Unclassifiable Establishments",
    "sg:phone":"+33 2 43 88 40 62",
    "sg:province":"Pays de Loire",
    "wof:name":"Etablissement Gautier S.a.r.l.",
    "wof:placetype":"venue"
},
  "geometry": {"coordinates":[-0.152191,47.998451],"type":"Point"}
}