{
  "type": "Feature",
  "properties": {
    "addr:full":"5 rue Tilly 14400 Bayeux Bayeux Basse Normandie 14400",
    "addr:housenumber":"5",
    "addr:postcode":"14400;14400",
    "addr:street":"Rue Tilly",
    "iso:country":"FR",
    "sg:address":"5 rue Tilly 14400 Bayeux",
    "sg:city":"Bayeux",
    "sg:classifiers":[
        {
            "category":"Bus Stop",
            "subcategory":"None",
            "type":"Transportation"
        }
    ],
    "sg:phone":"+33 2 31 92 83 12",
    "sg:postcode":"14400",
    "sg:province":"Basse Normandie",
    "sg:tags":[
        "period",
        "furniture"
    ],
    "wof:name":"Meubles Production S.a.r.l.",
    "wof:placetype":"venue"
},
  "geometry": {"coordinates":[-0.696789,49.269451],"type":"Point"}
}