{
  "type": "Feature",
  "properties": {
    "addr:full":"18 Rue Aux Juifs Sancerre Centre 18300",
    "addr:housenumber":"18",
    "addr:postcode":"18300",
    "addr:street":"Rue Aux Juifs Sancerre",
    "iso:country":"FR",
    "sg:address":"18 Rue Aux Juifs",
    "sg:city":"Sancerre",
    "sg:classifiers":[
        {
            "category":"Banks & Credit Unions",
            "subcategory":"Financial Services",
            "type":"Services"
        }
    ],
    "sg:phone":"+33 2 48 54 19 29",
    "sg:postcode":"18300",
    "sg:province":"Centre",
    "sg:tags":[
        "banking",
        "finance",
        "insurance"
    ],
    "wof:name":"Cogep Groupe D'experts Comptables Et De Commissaires Au",
    "wof:placetype":"venue"
},
  "geometry": {"coordinates":[2.839107,47.332031],"type":"Point"}
}