{
  "type": "Feature",
  "properties": {
    "addr:full":"58 Av Marchinal De Lattre De Tassigny 39100 Dole Franche Comt\u00e9",
    "addr:postcode":"39100",
    "addr:street":"58 Av Marchinal De Lattre De Tassigny;Franche Comte\u0301",
    "iso:country":"FR",
    "sg:address":"58 Av Marchinal De Lattre De Tassigny 39100 Dole",
    "sg:classifiers":[
        {
            "category":"Manufacturing",
            "subcategory":"Printing",
            "type":"Manufacturing & Wholesale Goods"
        }
    ],
    "sg:phone":"+33 3 84 70 80 90",
    "sg:province":"Franche Comt\u00e9",
    "sg:tags":[
        "publishing"
    ],
    "wof:name":"Lig Soci\u00c9t\u00c9 D'ingeni\u00c8re Graphique Sa",
    "wof:placetype":"venue"
},
  "geometry": {"coordinates":[5.499573,47.108734],"type":"Point"}
}