{
  "type": "Feature",
  "properties": {
    "addr:full":"Lieu-Dit Bois Granger 26240 La Motte De Galaure Rhone-Alpes 26240",
    "addr:postcode":"26240;26240",
    "addr:street":"Lieu-Dit Bois Granger;Rhone-Alpes",
    "iso:country":"FR",
    "sg:address":"Lieu-Dit Bois Granger 26240 La Motte De Galaure",
    "sg:classifiers":[
        {
            "category":"Building & Trades",
            "subcategory":"Construction",
            "type":"Services"
        }
    ],
    "sg:phone":"+33 4 75 68 40 24",
    "sg:postcode":"26240",
    "sg:province":"Rhone-Alpes",
    "sg:tags":[
        "work",
        "public"
    ],
    "wof:name":"Beolet Et Fils",
    "wof:placetype":"venue"
},
  "geometry": {"coordinates":[4.836268,45.159122],"type":"Point"}
}