{
  "type": "Feature",
  "properties": {
    "iso:country":"FR",
    "sg:address":"28 Rue Montrosier 92200 Neuilly Sur Seine",
    "sg:classifiers":[
        {
            "category":"Home & Garden",
            "subcategory":"Furniture",
            "type":"Retail Goods"
        }
    ],
    "sg:phone":"+33 1 43 04 90 80",
    "sg:postcode":"92200",
    "sg:province":"Ile de France",
    "sg:tags":[
        "household",
        "wood"
    ],
    "wof:name":"Tecteur Sanibloc",
    "wof:placetype":"venue"
},
  "geometry": {"coordinates":[2.27983,48.881123],"type":"Point"}
}