{
  "type": "Feature",
  "properties": {
    "addr:full":"74 rue Maurice Flandin 69003 Lyon Rhone-Alpes 69003",
    "addr:housenumber":"74",
    "addr:postcode":"69003;69003",
    "addr:street":"Rue Maurice Flandin",
    "iso:country":"FR",
    "sg:address":"74 rue Maurice Flandin 69003 Lyon",
    "sg:classifiers":[
        {
            "category":"Professional",
            "subcategory":"Business Services",
            "type":"Services"
        }
    ],
    "sg:phone":"+33 4 72 36 02 20",
    "sg:postcode":"69003",
    "sg:province":"Rhone-Alpes",
    "sg:tags":[
        "data"
    ],
    "wof:name":"Medial Sa",
    "wof:placetype":"venue"
},
  "geometry": {"coordinates":[4.862468,45.757919],"type":"Point"}
}