{
  "type": "Feature",
  "properties": {
    "addr:full":"26 Rue Du Chalet 92600 Asni\u00e8res Sur Seine Ile de France",
    "addr:housenumber":"26",
    "addr:postcode":"92600",
    "addr:street":"Rue Du Chalet",
    "iso:country":"FR",
    "sg:address":"26 Rue Du Chalet 92600 Asni\u00e8res Sur Seine",
    "sg:classifiers":[
        {
            "category":"Utilities",
            "subcategory":"Telephone",
            "type":"Services"
        }
    ],
    "sg:phone":"+33 1 47 93 10 43",
    "sg:province":"Ile de France",
    "sg:tags":[
        "telecommunication"
    ],
    "wof:name":"Transmissions Electriques Sa",
    "wof:placetype":"venue"
},
  "geometry": {"coordinates":[2.275049,48.914619],"type":"Point"}
}