{
  "type": "Feature",
  "properties": {
    "addr:full":"95, Rte de Montpellier, 34200 S\u00e8te Languedoc-Roussillon",
    "addr:housenumber":"95",
    "addr:postcode":"34200",
    "addr:street":"Rte De Montpellier",
    "iso:country":"FR",
    "sg:address":"95, Rte de Montpellier, 34200 S\u00e8te",
    "sg:orig_category":"Unclassifiable Establishments",
    "sg:phone":"+33 4 67 51 60 30",
    "sg:province":"Languedoc-Roussillon",
    "wof:name":"A.g.a. M\u00e9dical",
    "wof:placetype":"venue"
},
  "geometry": {"coordinates":[3.69633,43.399052],"type":"Point"}
}