{
  "type": "Feature",
  "properties": {
    "iso:country":"FR",
    "sg:address":"Chemin des Voieries",
    "sg:city":"Leuville sur Orge",
    "sg:orig_category":"Unclassifiable Establishments",
    "sg:phone":"+33 1 60 84 10 31",
    "sg:postcode":"91310",
    "sg:province":"Ile de France",
    "wof:name":"Soci\u00e9t\u00e9 Caudron Fr\u00e8res S.a.r.l.",
    "wof:placetype":"venue"
},
  "geometry": {"coordinates":[2.274446,48.618793],"type":"Point"}
}