{
  "type": "Feature",
  "properties": {
    "addr:full":"12 ave de Laumi\u00e8re; Paris; 75019 Ile de France 75019",
    "addr:postcode":"75019 ile;france 75019",
    "addr:street":"12 Ave De Laumie\u0300Re",
    "iso:country":"FR",
    "sg:address":"12 ave de Laumi\u00e8re; Paris; 75019",
    "sg:classifiers":[
        {
            "category":"Banks & Credit Unions",
            "subcategory":"Bank",
            "type":"Services"
        }
    ],
    "sg:phone":"+33 1 44 52 10 20",
    "sg:postcode":"75019",
    "sg:province":"Ile de France",
    "wof:name":"Soci\u00e9t\u00e9 G\u00e9n\u00e9rale",
    "wof:placetype":"venue"
},
  "geometry": {"coordinates":[2.380979,48.883602],"type":"Point"}
}