{
  "type": "Feature",
  "properties": {
    "iso:country":"FR",
    "sg:address":"Moulin Court 38630 Veyrins Thuellin",
    "sg:classifiers":[
        {
            "category":"Manufacturing",
            "subcategory":"Paper Products",
            "type":"Manufacturing & Wholesale Goods"
        }
    ],
    "sg:phone":"+33 4 74 33 63 63",
    "sg:province":"Rhone-Alpes",
    "sg:tags":[
        "raw",
        "material",
        "-",
        "cardboard"
    ],
    "wof:name":"Emballages Veyrinois Sarl",
    "wof:placetype":"venue"
},
  "geometry": {"coordinates":[5.562497,45.635681],"type":"Point"}
}