{
  "type": "Feature",
  "properties": {
    "addr:full":"B.P. 10430, 57954 Montigny l\u00e8s Metz C\u00e9dex^^296, Rue de Pont \u00e0 Mousson, 57950 Montigny l\u00e8s Metz Champagne 10430",
    "addr:housenumber":"10430",
    "addr:postcode":"57954;57950;10430",
    "addr:street":"Rue De Pont A\u0300 Mousson",
    "iso:country":"FR",
    "sg:address":"B.P. 10430, 57954 Montigny l\u00e8s Metz C\u00e9dex^^296, Rue de Pont \u00e0 Mousson, 57950 Montigny l\u00e8s Metz",
    "sg:orig_category":"Non-Classified Establishments",
    "sg:phone":"+33 3 87 66 40 22",
    "sg:postcode":"10430",
    "sg:province":"Champagne",
    "wof:name":"Editions Le Lorrain S.a.",
    "wof:placetype":"venue"
},
  "geometry": {"coordinates":[6.15241,49.099918],"type":"Point"}
}