{
  "type": "Feature",
  "properties": {
    "addr:full":"B.P. 39, 83401 Hy\u00e8res C\u00e9dex^^Quartier de la Villette, 83400 Hy\u00e8res Vill\u00e9 Alsace 67220",
    "addr:postcode":"83401;83400;67220",
    "addr:street":"B.P. 39;La Villette",
    "iso:country":"FR",
    "sg:address":"B.P. 39, 83401 Hy\u00e8res C\u00e9dex^^Quartier de la Villette, 83400 Hy\u00e8res",
    "sg:city":"Vill\u00e9",
    "sg:orig_category":"Non-Classified Establishments",
    "sg:phone":"+33 4 94 12 31 31",
    "sg:postcode":"67220",
    "sg:province":"Alsace",
    "wof:name":"Savco S.a.",
    "wof:placetype":"venue"
},
  "geometry": {"coordinates":[6.155135,43.029346],"type":"Point"}
}