{
  "type": "Feature",
  "properties": {
    "addr:full":"Zone Industrielle Henri Paul 71210 Montchanin Montchanin Bourgogne 71210",
    "addr:postcode":"71210;71210",
    "addr:street":"Zone Industrielle Henri Paul",
    "iso:country":"FR",
    "sg:address":"Zone Industrielle Henri Paul 71210 Montchanin",
    "sg:city":"Montchanin",
    "sg:classifiers":[
        {
            "category":"Transit Center",
            "subcategory":"Freight",
            "type":"Transportation"
        }
    ],
    "sg:phone":"+33 3 85 77 90 10",
    "sg:postcode":"71210",
    "sg:province":"Bourgogne",
    "sg:tags":[
        "metallurgy",
        "pipe",
        "metalworking",
        "sheet"
    ],
    "wof:name":"Tancarville",
    "wof:placetype":"venue"
},
  "geometry": {"coordinates":[4.46917,46.748814],"type":"Point"}
}