{
  "type": "Feature",
  "properties": {
    "iso:country":"FR",
    "sg:address":"Chassin 01540 Vonnas",
    "sg:orig_category":"Unclassifiable Establishments",
    "sg:phone":"+33 4 74 50 00 08",
    "sg:postcode":"01540",
    "sg:province":"Rhone-Alpes",
    "wof:name":"Entreprise Mignot Patrick",
    "wof:placetype":"venue"
},
  "geometry": {"coordinates":[4.994515,46.199165],"type":"Point"}
}