{
  "type": "Feature",
  "properties": {
    "addr:full":"29 rue du Mar\u00e9chal; Alen\u00e7on; 61000 Alen\u00e7on Basse Normandie 61000",
    "addr:housenumber":"29",
    "addr:postcode":"61000;61000",
    "addr:street":"Rue Du Mare\u0301Chal Alenc\u0327On",
    "iso:country":"FR",
    "sg:address":"29 rue du Mar\u00e9chal; Alen\u00e7on; 61000",
    "sg:city":"Alen\u00e7on",
    "sg:classifiers":[
        {
            "category":"Banks & Credit Unions",
            "subcategory":"Bank",
            "type":"Services"
        }
    ],
    "sg:phone":"+33 3333266967",
    "sg:postcode":"61000",
    "sg:province":"Basse Normandie",
    "wof:name":"Cr\u00e9dit Foncier De France",
    "wof:placetype":"venue"
},
  "geometry": {"coordinates":[0.083175,48.430626],"type":"Point"}
}