{
  "type": "Feature",
  "properties": {
    "iso:country":"FR",
    "sg:address":"Voie C - ZI Ouest",
    "sg:city":"Surg\u00e8res",
    "sg:orig_category":"Unclassifiable Establishments",
    "sg:phone":"+33 5 46 07 04 85",
    "sg:postcode":"17700",
    "sg:province":"Poitou-Charentes",
    "wof:name":"Villeneau S.a.r.l.",
    "wof:placetype":"venue"
},
  "geometry": {"coordinates":[-0.690955,46.052395],"type":"Point"}
}