{
  "type": "Feature",
  "properties": {
    "addr:full":"15 rue Voltaire 38200 Vienne Rhone-Alpes 38200",
    "addr:housenumber":"15",
    "addr:postcode":"38200;38200",
    "addr:street":"Rue Voltaire",
    "iso:country":"FR",
    "sg:address":"15 rue Voltaire 38200 Vienne",
    "sg:classifiers":[
        {
            "category":"Wholesale",
            "subcategory":"Medical Equipment & Supplies",
            "type":"Manufacturing & Wholesale Goods"
        }
    ],
    "sg:phone":"+33 4 74 85 42 85",
    "sg:postcode":"38200",
    "sg:province":"Rhone-Alpes",
    "wof:name":"Vienne M\u00e9dical S.a.r.l.",
    "wof:placetype":"venue"
},
  "geometry": {"coordinates":[4.87305,45.522812],"type":"Point"}
}