{
  "type": "Feature",
  "properties": {
    "iso:country":"FR",
    "sg:address":"4, Rue Aristide Berges, 38080 L'Isle d'Abeau",
    "sg:orig_category":"Unclassifiable Establishments",
    "sg:phone":"+33 4 74 27 59 30",
    "sg:postcode":"38080",
    "sg:province":"Rhone-Alpes",
    "wof:name":"V.p.i. S.a. - Vicat Produits Industriels",
    "wof:placetype":"venue"
},
  "geometry": {"coordinates":[-89.478561,36.259331],"type":"Point"}
}