{
  "type": "Feature",
  "properties": {
    "addr:full":"5, Av. Joliot Curie, 17180 P\u00e9rigny Poitou-Charentes 17180",
    "addr:postcode":"17180;17180",
    "addr:street":"Av. Joliot Curie",
    "iso:country":"FR",
    "sg:address":"5, Av. Joliot Curie, 17180 P\u00e9rigny",
    "sg:orig_category":"Non-Classified Establishments",
    "sg:phone":"+33 5 46 44 20 16",
    "sg:postcode":"17180",
    "sg:province":"Poitou-Charentes",
    "wof:name":"Apprelec S.a.",
    "wof:placetype":"venue"
},
  "geometry": {"coordinates":[-1.107134,46.157475],"type":"Point"}
}