{
  "type": "Feature",
  "properties": {
    "addr:full":"B.P. 49, 40001 Mont de Marsan C\u00e9dex^^430, Rue Monge - ZA de P\u00e9m\u00e9gan, 40000 Mont de Marsan Mont-de-Marsan Aquitaine 40000",
    "addr:postcode":"40001;40000;40000",
    "addr:street":"B.P. 49;Rue Monge Za De Pe\u0301Me\u0301Gan",
    "iso:country":"FR",
    "sg:address":"B.P. 49, 40001 Mont de Marsan C\u00e9dex^^430, Rue Monge - ZA de P\u00e9m\u00e9gan, 40000 Mont de Marsan",
    "sg:city":"Mont-de-Marsan",
    "sg:orig_category":"Non-Classified Establishments",
    "sg:phone":"+33 5 58 05 55 55",
    "sg:postcode":"40000",
    "sg:province":"Aquitaine",
    "wof:name":"Scalandes S.a.",
    "wof:placetype":"venue"
},
  "geometry": {"coordinates":[-0.498939,43.889503],"type":"Point"}
}