{
  "type": "Feature",
  "properties": {
    "addr:full":"14 Rue Mal Leclerc 60157 Elioncourt Ste Marguerite Picardie",
    "addr:housenumber":"14",
    "addr:postcode":"60157",
    "addr:street":"Rue Mal Leclerc;Marguerite Picardie",
    "iso:country":"FR",
    "sg:address":"14 Rue Mal Leclerc 60157 Elioncourt Ste Marguerite",
    "sg:classifiers":[
        {
            "category":"Professional",
            "type":"Services"
        }
    ],
    "sg:phone":"+33 3 44 96 00 31",
    "sg:province":"Picardie",
    "sg:tags":[
        "transport",
        "road"
    ],
    "wof:name":"Guy Lefebvre Sa",
    "wof:placetype":"venue"
},
  "geometry": {"coordinates":[-91.677902,29.876461],"type":"Point"}
}