{
  "type": "Feature",
  "properties": {
    "iso:country":"FR",
    "sg:address":"13 A Avenue De La Republique 68000 Colmar",
    "sg:city":"Colmar",
    "sg:classifiers":[
        {
            "category":"Utilities",
            "subcategory":"Electric",
            "type":"Services"
        }
    ],
    "sg:phone":"+33 3 89 41 32 29",
    "sg:postcode":"68000",
    "sg:province":"Alsace",
    "sg:tags":[
        "electricity",
        "electronic",
        "electrical",
        "equipment"
    ],
    "wof:name":"Elyo Nord Est Districhaleur",
    "wof:placetype":"venue"
},
  "geometry": {"coordinates":[7.349257,48.0732],"type":"Point"}
}