{
  "type": "Feature",
  "properties": {
    "iso:country":"FR",
    "sg:address":"10 Rue Louis Blanc 69200 V\u00e9nissieux",
    "sg:classifiers":[
        {
            "category":"Professional",
            "subcategory":"Business Services",
            "type":"Services"
        }
    ],
    "sg:phone":"+33 4 72 78 81 00",
    "sg:province":"Rhone-Alpes",
    "sg:tags":[
        "body",
        "advice"
    ],
    "wof:name":"Majo",
    "wof:placetype":"venue"
},
  "geometry": {"coordinates":[4.880099,45.720573],"type":"Point"}
}