{
  "type": "Feature",
  "properties": {
    "iso:country":"FR",
    "sg:address":"Quartier Plessier 68130 Altkirch",
    "sg:city":"Altkirch",
    "sg:classifiers":[
        {
            "category":"Wholesale",
            "subcategory":"Machinery & Supplies",
            "type":"Manufacturing & Wholesale Goods"
        }
    ],
    "sg:phone":"+33 3 89 08 90 12",
    "sg:postcode":"68130",
    "sg:province":"Alsace",
    "sg:tags":[
        "handling",
        "material",
        "-",
        "machine",
        "equipment",
        "engineering",
        "mechanical"
    ],
    "wof:name":"Rotzinger France Sa",
    "wof:placetype":"venue"
},
  "geometry": {"coordinates":[7.24009,47.625919],"type":"Point"}
}