{
  "type": "Feature",
  "properties": {
    "iso:country":"FR",
    "sg:address":"Chateau Du Roncemay 89110 Chassy",
    "sg:city":"Chassy",
    "sg:classifiers":[
        {
            "category":"Food & Beverages",
            "subcategory":"Fruits & Vegetables",
            "type":"Retail Goods"
        }
    ],
    "sg:phone":"+33 3 86 73 50 50",
    "sg:postcode":"89110",
    "sg:province":"Bourgogne",
    "sg:tags":[
        "preserve",
        "product",
        "related"
    ],
    "wof:name":"Les Confitures Domaine De Roncemay",
    "wof:placetype":"venue"
},
  "geometry": {"coordinates":[3.332646,47.799889],"type":"Point"}
}