{
  "type": "Feature",
  "properties": {
    "addr:full":"71480 Varennes Saint Sauveur Champagnat Bourgogne 71480",
    "addr:postcode":"71480;71480",
    "addr:street":"Bourgogne",
    "iso:country":"FR",
    "sg:address":"71480 Varennes Saint Sauveur",
    "sg:city":"Champagnat",
    "sg:orig_category":"Non-Classified Establishments",
    "sg:phone":"+33 3 85 76 33 50",
    "sg:postcode":"71480",
    "sg:province":"Bourgogne",
    "wof:name":"U.c.r. Les Laiteries Bressanes",
    "wof:placetype":"venue"
},
  "geometry": {"coordinates":[5.244185,46.484756],"type":"Point"}
}