{
  "type": "Feature",
  "properties": {
    "iso:country":"FR",
    "sg:address":"1 Rue De Su\u00e8de 37100 Tours",
    "sg:city":"Tours",
    "sg:classifiers":[
        {
            "category":"Manufacturing",
            "subcategory":"Chemicals & Compounds",
            "type":"Manufacturing & Wholesale Goods"
        }
    ],
    "sg:phone":"+33 2 47 54 44 54",
    "sg:postcode":"37100",
    "sg:province":"Centre",
    "sg:tags":[
        "pharmaceutical",
        "chemistry",
        "-",
        "by-product"
    ],
    "wof:name":"Mainguet Sas",
    "wof:placetype":"venue"
},
  "geometry": {"coordinates":[0.697591,47.435886],"type":"Point"}
}