{
  "type": "Feature",
  "properties": {
    "addr:full":"20 Rue De Lyon 71000 M\u00e2con Sanc\u00e9 Bourgogne 71000",
    "addr:housenumber":"20",
    "addr:postcode":"71000;71000",
    "addr:street":"Rue De Lyon",
    "iso:country":"FR",
    "sg:address":"20 Rue De Lyon 71000 M\u00e2con",
    "sg:city":"Sanc\u00e9",
    "sg:classifiers":[
        {
            "category":"Professional",
            "type":"Services"
        }
    ],
    "sg:phone":"+33 3 85 39 01 70",
    "sg:postcode":"71000",
    "sg:province":"Bourgogne",
    "sg:tags":[
        "transport",
        "road"
    ],
    "wof:name":"Demenagements Dupont Bedu",
    "wof:placetype":"venue"
},
  "geometry": {"coordinates":[4.829416,46.301888],"type":"Point"}
}