{
  "type": "Feature",
  "properties": {
    "addr:full":"Zi St Ren\u00e9 59287 Guesnain Nord Pas-de-Calais 59287",
    "addr:postcode":"59287;59287",
    "addr:street":"Zi St Rene\u0301",
    "iso:country":"FR",
    "sg:address":"Zi St Ren\u00e9 59287 Guesnain",
    "sg:classifiers":[
        {
            "category":"Building & Trades",
            "subcategory":"Pest Control",
            "type":"Services"
        }
    ],
    "sg:phone":"+33 3 27 87 25 25",
    "sg:postcode":"59287",
    "sg:province":"Nord Pas-de-Calais",
    "sg:tags":[
        "metallurgy",
        "sheet",
        "-",
        "metalworking",
        "pipe",
        "engineering",
        "machine",
        "mechanical"
    ],
    "wof:name":"Motif Sarl",
    "wof:placetype":"venue"
},
  "geometry": {"coordinates":[3.14886,50.352917],"type":"Point"}
}