{
  "type": "Feature",
  "properties": {
    "addr:full":"route d'Aubusson 61100 St Georges Des Groseillers Aubusson Basse Normandie 61100",
    "addr:postcode":"61100;61100",
    "addr:street":"Route D'Aubusson;Des Groseillers;Basse",
    "iso:country":"FR",
    "sg:address":"route d'Aubusson 61100 St Georges Des Groseillers",
    "sg:city":"Aubusson",
    "sg:classifiers":[
        {
            "category":"Manufacturing",
            "subcategory":"Rubber & Plastics",
            "type":"Manufacturing & Wholesale Goods"
        }
    ],
    "sg:phone":"+33 2 33 98 19 80",
    "sg:postcode":"61100",
    "sg:province":"Basse Normandie",
    "sg:tags":[
        "technical",
        "parts"
    ],
    "wof:name":"P.v.o. Snc",
    "wof:placetype":"venue"
},
  "geometry": {"coordinates":[-0.55205,48.784061],"type":"Point"}
}