{
  "type": "Feature",
  "properties": {
    "addr:full":"Rue d'Italie - Le quart Saint Jean de Maurienne Rhone-Alpes 73300",
    "addr:postcode":"73300",
    "addr:street":"Rue D'Italie Le Quart Saint Jean De Maurienne Rhone-Alpes",
    "iso:country":"FR",
    "sg:address":"Rue d'Italie - Le quart",
    "sg:city":"Saint Jean de Maurienne",
    "sg:orig_category":"Unclassifiable Establishments",
    "sg:phone":"+33 4 79 83 20 24",
    "sg:postcode":"73300",
    "sg:province":"Rhone-Alpes",
    "wof:name":"S.a.c.e.r. Sud Est S.a.",
    "wof:placetype":"venue"
},
  "geometry": {"coordinates":[6.3436,45.278198],"type":"Point"}
}