{
  "type": "Feature",
  "properties": {
    "iso:country":"FR",
    "sg:address":"Rue d'Italie - Le quart",
    "sg:city":"Saint Jean de Maurienne",
    "sg:orig_category":"Unclassifiable Establishments",
    "sg:phone":"+33 4 79 83 20 24",
    "sg:postcode":"73300",
    "sg:province":"Rhone-Alpes",
    "wof:name":"S.a.c.e.r. Sud Est S.a.",
    "wof:placetype":"venue"
},
  "geometry": {"coordinates":[6.3436,45.278198],"type":"Point"}
}