{
  "type": "Feature",
  "properties": {
    "iso:country":"FR",
    "sg:address":"23, Rue des Poiriers - ZI Sainte Apolline, 78370 Plaisir",
    "sg:orig_category":"Non-Classified Establishments",
    "sg:phone":"+33 1 30 79 18 28",
    "sg:province":"Ile de France",
    "wof:name":"Waid S.a.",
    "wof:placetype":"venue"
},
  "geometry": {"coordinates":[1.949255,48.816689],"type":"Point"}
}