{
  "type": "Feature",
  "properties": {
    "addr:full":"32, Rue Andr\u00e9 Dessaux, 45400 Fleury les Aubrais Chanteau Centre 45400",
    "addr:housenumber":"32",
    "addr:postcode":"45400;45400",
    "addr:street":"Rue Andre\u0301 Dessaux;Aubrais",
    "iso:country":"FR",
    "sg:address":"32, Rue Andr\u00e9 Dessaux, 45400 Fleury les Aubrais",
    "sg:city":"Chanteau",
    "sg:orig_category":"Unclassifiable Establishments",
    "sg:phone":"+33 2 38 43 18 19",
    "sg:postcode":"45400",
    "sg:province":"Centre",
    "wof:name":"C.o.m.e.t. S.a.s. - Compagnie Orl\u00e9anaise De Mat\u00e9riel Electrique Et Thermique",
    "wof:placetype":"venue"
},
  "geometry": {"coordinates":[1.897051,47.931557],"type":"Point"}
}