{
  "type": "Feature",
  "properties": {
    "iso:country":"FR",
    "sg:address":"7, Av. Henri Beaudelet, 77330 Ozoir la Ferri\u00e8re",
    "sg:orig_category":"Non-Classified Establishments",
    "sg:phone":"+33 1 64 40 42 01",
    "sg:postcode":"77330",
    "sg:province":"Ile de France",
    "wof:name":"Constructions Electriques Le Cosinus S.a.",
    "wof:placetype":"venue"
},
  "geometry": {"coordinates":[2.692318,48.765518],"type":"Point"}
}