{
  "type": "Feature",
  "properties": {
    "addr:full":"B.P. 97, 40800 Aire sur l'Adour^^Rte de Bordeaux - Cap de la Coste , 40800 Aire sur l'Adour Duhort-Bachen Aquitaine 40800",
    "addr:postcode":"40800;40800;40800",
    "addr:street":"B.P. 97;Aire;Coste;Aire",
    "iso:country":"FR",
    "sg:address":"B.P. 97, 40800 Aire sur l'Adour^^Rte de Bordeaux - Cap de la Coste , 40800 Aire sur l'Adour",
    "sg:city":"Duhort-Bachen",
    "sg:orig_category":"Non-Classified Establishments",
    "sg:phone":"+33 5 58 71 66 77",
    "sg:postcode":"40800",
    "sg:province":"Aquitaine",
    "wof:name":"Biscuits Poult S.a.",
    "wof:placetype":"venue"
},
  "geometry": {"coordinates":[-0.265104,43.725365],"type":"Point"}
}