{
  "type": "Feature",
  "properties": {
    "addr:full":"217, Av. de la Gare, 84210 Pernes les Fontaines Provence-Alpes-C\u00f4te d'Azur",
    "addr:postcode":"84210",
    "addr:street":"217 Av. De La Gare;Les Fontaines",
    "iso:country":"FR",
    "sg:address":"217, Av. de la Gare, 84210 Pernes les Fontaines",
    "sg:orig_category":"Unclassifiable Establishments",
    "sg:phone":"+33 4 90 61 50 92",
    "sg:province":"Provence-Alpes-C\u00f4te d'Azur",
    "wof:name":"Luxacor S.a.r.l.",
    "wof:placetype":"venue"
},
  "geometry": {"coordinates":[5.051935,43.998718],"type":"Point"}
}