{
  "type": "Feature",
  "properties": {
    "iso:country":"FR",
    "sg:address":"Bd Ferdinand de Lesseps - Zone Industrielle",
    "sg:city":"H\u00e9nin Beaumont",
    "sg:orig_category":"Non-Classified Establishments",
    "sg:phone":"+33 3 21 69 88 88",
    "sg:postcode":"62110",
    "sg:province":"Nord Pas-de-Calais",
    "wof:name":"Exel Logistics S.a.",
    "wof:placetype":"venue"
},
  "geometry": {"coordinates":[2.961701,50.403736],"type":"Point"}
}