{
  "type": "Feature",
  "properties": {
    "iso:country":"FR",
    "sg:address":"1144, Av Eloi Ducom, 40000 Mont de Marsan",
    "sg:city":"Mont-de-Marsan",
    "sg:orig_category":"Unclassifiable Establishments",
    "sg:phone":"+33 5 58 06 50 50",
    "sg:postcode":"40000",
    "sg:province":"Aquitaine",
    "wof:name":"Etablissement H.philippon S.a.",
    "wof:placetype":"venue"
},
  "geometry": {"coordinates":[-0.482631,43.891308],"type":"Point"}
}