{
  "type": "Feature",
  "properties": {
    "addr:full":"3, Rue des 3 Fourchettes, 08600 Givet Charnois Champagne 08600",
    "addr:housenumber":"3",
    "addr:postcode":"08600;08600",
    "addr:street":"Rue Des 3 Fourchettes;Champagne",
    "iso:country":"FR",
    "sg:address":"3, Rue des 3 Fourchettes, 08600 Givet",
    "sg:city":"Charnois",
    "sg:orig_category":"Unclassifiable Establishments",
    "sg:phone":"+33 3 24 42 08 31",
    "sg:postcode":"08600",
    "sg:province":"Champagne",
    "wof:name":"M\u00e9tal Industriel De Givet S.a.r.l.",
    "wof:placetype":"venue"
},
  "geometry": {"coordinates":[4.820043,50.142197],"type":"Point"}
}