{
  "type": "Feature",
  "properties": {
    "iso:country":"FR",
    "sg:address":"Zi Champigny",
    "sg:city":"Richelieu",
    "sg:classifiers":[
        {
            "category":"Home & Garden",
            "subcategory":"Furniture",
            "type":"Retail Goods"
        }
    ],
    "sg:phone":"+33 2 47 58 25 00",
    "sg:postcode":"37120",
    "sg:province":"Centre",
    "sg:tags":[
        "household",
        "wood"
    ],
    "wof:name":"Art Et Meubles De France",
    "wof:placetype":"venue"
},
  "geometry": {"coordinates":[0.324045,47.01247],"type":"Point"}
}