{
  "type": "Feature",
  "properties": {
    "addr:full":"80, Rue des Martyrs, 76500 Elbeuf Haute Normandie",
    "addr:housenumber":"80",
    "addr:postcode":"76500",
    "addr:street":"Rue Des Martyrs;Haute Normandie",
    "iso:country":"FR",
    "sg:address":"80, Rue des Martyrs, 76500 Elbeuf",
    "sg:orig_category":"Unclassifiable Establishments",
    "sg:phone":"+33 2 32 96 51 35",
    "sg:province":"Haute Normandie",
    "wof:name":"Fidelb S.a.",
    "wof:placetype":"venue"
},
  "geometry": {"coordinates":[1.003578,49.290054],"type":"Point"}
}