{
  "type": "Feature",
  "properties": {
    "addr:full":"Rue Antoine de Lavoisier - ZA de Cr\u00e9hange Cr\u00e9hange Lorraine 57690",
    "addr:postcode":"57690",
    "addr:street":"Rue Antoine De Lavoisier Za De Cre\u0301Hange Cre\u0301Hange Lorraine",
    "iso:country":"FR",
    "sg:address":"Rue Antoine de Lavoisier - ZA de Cr\u00e9hange",
    "sg:city":"Cr\u00e9hange",
    "sg:orig_category":"Cl\u00f4tures et/ou grillages Glissi\u00e8res de s\u00e9curit\u00e9 Serrurerie et/ou m\u00e9tallerie",
    "sg:phone":"+33 3 87 91 49 40",
    "sg:postcode":"57690",
    "sg:province":"Lorraine",
    "wof:name":"S.m.f. S.a.r.l. - Serrurerie M\u00e9tallerie Ferronnerie",
    "wof:placetype":"venue"
},
  "geometry": {"coordinates":[6.58013,49.062054],"type":"Point"}
}