{
  "type": "Feature",
  "properties": {
    "iso:country":"FR",
    "sg:address":"Chem Du Polygone Zac De Castellamare 13250 Saint Chamas",
    "sg:classifiers":[
        {
            "category":"Transit Center",
            "subcategory":"Freight",
            "type":"Transportation"
        }
    ],
    "sg:phone":"+33 4 90 50 29 29",
    "sg:province":"Midi Pyr\u00e9n\u00e9es",
    "sg:tags":[
        "metallurgy",
        "pipe",
        "metalworking",
        "sheet"
    ],
    "wof:name":"Societe D'armartures Manna Et Thirion",
    "wof:placetype":"venue"
},
  "geometry": {"coordinates":[5.032915,43.550137],"type":"Point"}
}