{
  "type": "Feature",
  "properties": {
    "addr:full":"La Nerolle 16130 Segonzac Poitou-Charentes 16130",
    "addr:postcode":"16130;16130",
    "iso:country":"FR",
    "sg:address":"La Nerolle 16130 Segonzac",
    "sg:classifiers":[
        {
            "category":"Food Court",
            "type":"Food & Drink"
        }
    ],
    "sg:phone":"+33 5 45 83 31 11",
    "sg:postcode":"16130",
    "sg:province":"Poitou-Charentes",
    "sg:tags":[
        "product",
        "related"
    ],
    "wof:name":"Camus La Grande Marque (camus)",
    "wof:placetype":"venue"
},
  "geometry": {"coordinates":[-0.21148,45.63662],"type":"Point"}
}