{
  "type": "Feature",
  "properties": {
    "addr:full":"Rn 13 41260 La Chauss\u00e9e St Victor La Chauss\u00e9e-Saint-Victor Centre 41260",
    "addr:housenumber":"41260;chausse\u0301e-saint-victor",
    "addr:postcode":"41260",
    "addr:street":"Rn 13;Chausse\u0301E St;La",
    "iso:country":"FR",
    "sg:address":"Rn 13 41260 La Chauss\u00e9e St Victor",
    "sg:city":"La Chauss\u00e9e-Saint-Victor",
    "sg:classifiers":[
        {
            "category":"Travel",
            "subcategory":"Hotels & Motels",
            "type":"Entertainment"
        }
    ],
    "sg:phone":"+33 2 54 74 80 01",
    "sg:postcode":"41260",
    "sg:province":"Centre",
    "sg:tags":[
        "hotels",
        "business",
        "restaurant"
    ],
    "wof:name":"Buffalo Grill",
    "wof:placetype":"venue"
},
  "geometry": {"coordinates":[1.36532,47.613747],"type":"Point"}
}