{
  "type": "Feature",
  "properties": {
    "iso:country":"FR",
    "sg:address":"Rn 13 41260 La Chauss\u00e9e St Victor",
    "sg:city":"La Chauss\u00e9e-Saint-Victor",
    "sg:classifiers":[
        {
            "category":"Travel",
            "subcategory":"Hotels & Motels",
            "type":"Entertainment"
        }
    ],
    "sg:phone":"+33 2 54 74 80 01",
    "sg:postcode":"41260",
    "sg:province":"Centre",
    "sg:tags":[
        "hotels",
        "business",
        "restaurant"
    ],
    "wof:name":"Buffalo Grill",
    "wof:placetype":"venue"
},
  "geometry": {"coordinates":[1.36532,47.613747],"type":"Point"}
}