{
  "type": "Feature",
  "properties": {
    "iso:country":"FR",
    "sg:address":"144 Rue des Bosn\u00e9es 74460 MARNAZ",
    "sg:classifiers":[
        {
            "category":"Building & Trades",
            "subcategory":"Plumbing",
            "type":"Services"
        }
    ],
    "sg:phone":"+33 4 50 98 35 29",
    "sg:postcode":"74460",
    "sg:province":"Rhone-Alpes",
    "sg:tags":[
        "cropping",
        "tool"
    ],
    "wof:name":"Billardy Sa",
    "wof:placetype":"venue"
},
  "geometry": {"coordinates":[6.531699,46.061703],"type":"Point"}
}