{
  "type": "Feature",
  "properties": {
    "iso:country":"FR",
    "sg:address":"65 Rte De P\u00e9rigueux 87170 Isle",
    "sg:classifiers":[
        {
            "category":"Manufacturing",
            "subcategory":"Musical Instruments",
            "type":"Manufacturing & Wholesale Goods"
        }
    ],
    "sg:phone":"+33 5 55 39 01 94",
    "sg:postcode":"87170",
    "sg:province":"Limousin",
    "sg:tags":[
        "leather",
        "equipment",
        "health",
        "-",
        "shoe"
    ],
    "wof:name":"Hervy Tannerie Megisserie Sa",
    "wof:placetype":"venue"
},
  "geometry": {"coordinates":[1.224534,45.79652],"type":"Point"}
}