{
  "type": "Feature",
  "properties": {
    "iso:country":"FR",
    "sg:address":"B.P. 53, 94290 Villeneuve le Roi^^20 bis, Quai Marcel Cachin, 94290 Villeneuve le Roi",
    "sg:orig_category":"Non-Classified Establishments",
    "sg:phone":"+33 1 45 97 40 41",
    "sg:province":"Ile de France",
    "wof:name":"S.u.r.a. S.a. - Soci\u00e9t\u00e9 Pour L'utilisation Rationelle Des Abrasifs",
    "wof:placetype":"venue"
},
  "geometry": {"coordinates":[2.405535,48.733829],"type":"Point"}
}