{
  "type": "Feature",
  "properties": {
    "iso:country":"FR",
    "sg:address":"52 Av De Villeneuve 66870 Perpignan Cedex",
    "sg:city":"Vill\u00e9",
    "sg:classifiers":[
        {
            "category":"Professional",
            "subcategory":"Advertising",
            "type":"Services"
        }
    ],
    "sg:phone":"+33 4 68 50 07 63",
    "sg:postcode":"67220",
    "sg:province":"Alsace",
    "sg:tags":[
        "information",
        "medium",
        "communication"
    ],
    "wof:name":"Bibliotheque Universitaire",
    "wof:placetype":"venue"
},
  "geometry": {"coordinates":[2.902525,42.680782],"type":"Point"}
}