{
  "type": "Feature",
  "properties": {
    "addr:full":"Lamarzelle Figeac 33330 Saint Emilion Saint-\u00c9tienne-de-Lisse Aquitaine 33330",
    "addr:postcode":"33330;33330",
    "iso:country":"FR",
    "sg:address":"Lamarzelle Figeac 33330 Saint Emilion",
    "sg:city":"Saint-\u00c9tienne-de-Lisse",
    "sg:orig_category":"Unclassifiable Establishments",
    "sg:phone":"+33 5 57 24 71 43",
    "sg:postcode":"33330",
    "sg:province":"Aquitaine",
    "wof:name":"Ch\u00e2teau Grand Barrail Marzelle Figeac S.c.e.a.",
    "wof:placetype":"venue"
},
  "geometry": {"coordinates":[-0.148079,44.848289],"type":"Point"}
}