{
  "type": "Feature",
  "properties": {
    "addr:full":"B.P. 119 Thiers Auvergne 63300",
    "addr:housenumber":"b.p. 119",
    "addr:postcode":"63300",
    "addr:street":"Thiers",
    "iso:country":"FR",
    "sg:address":"B.P. 119",
    "sg:city":"Thiers",
    "sg:orig_category":"Non-Classified Establishments",
    "sg:phone":"+33 4 73 80 41 76",
    "sg:postcode":"63300",
    "sg:province":"Auvergne",
    "wof:name":"Therias Et L'econome S.a.",
    "wof:placetype":"venue"
},
  "geometry": {"coordinates":[3.563396,45.82058],"type":"Point"}
}