{
  "type": "Feature",
  "properties": {
    "iso:country":"FR",
    "sg:address":"Place de la Mairie",
    "sg:city":"Puimisson",
    "sg:orig_category":"Unclassifiable Establishments",
    "sg:phone":"+33 4 67 36 09 67",
    "sg:postcode":"34480",
    "sg:province":"Languedoc-Roussillon",
    "wof:name":"C\u00f4teaux De Bassac S.c.e.a.",
    "wof:placetype":"venue"
},
  "geometry": {"coordinates":[3.206155,43.439281],"type":"Point"}
}