{
  "type": "Feature",
  "properties": {
    "addr:full":"8 pl Eglise; Blanquefort Midi Pyr\u00e9n\u00e9es",
    "addr:housenumber":"8",
    "addr:street":"Pl Eglise",
    "iso:country":"FR",
    "sg:address":"8 pl Eglise; Blanquefort",
    "sg:classifiers":[
        {
            "category":"Banks & Credit Unions",
            "subcategory":"Bank",
            "type":"Services"
        }
    ],
    "sg:phone":"+33 3356351001",
    "sg:province":"Midi Pyr\u00e9n\u00e9es",
    "wof:name":"Cr\u00e9dit Agricole",
    "wof:placetype":"venue"
},
  "geometry": {"coordinates":[-0.645514,44.92728],"type":"Point"}
}