{
  "type": "Feature",
  "properties": {
    "addr:full":"Tron\u00e7ais 03360 Saint Bonnet Tron\u00e7ais Ainay-le-Ch\u00e2teau Auvergne 03360",
    "addr:postcode":"03360;03360",
    "addr:street":"Tronc\u0327Ais",
    "iso:country":"FR",
    "sg:address":"Tron\u00e7ais 03360 Saint Bonnet Tron\u00e7ais",
    "sg:city":"Ainay-le-Ch\u00e2teau",
    "sg:orig_category":"Unclassifiable Establishments",
    "sg:phone":"+33 4 70 06 16 17",
    "sg:postcode":"03360",
    "sg:province":"Auvergne",
    "wof:name":"Tron\u00e7ais S.a.",
    "wof:placetype":"venue"
},
  "geometry": {"coordinates":[2.695606,46.660866],"type":"Point"}
}