{
  "type": "Feature",
  "properties": {
    "iso:country":"FR",
    "sg:address":"Chauvign\u00e9 49610 Moz\u00e9 sur Louet",
    "sg:orig_category":"Non-Classified Establishments",
    "sg:phone":"+33 2 41 78 72 13",
    "sg:province":"Pays de Loire",
    "wof:name":"Richou G.a.e.c.",
    "wof:placetype":"venue"
},
  "geometry": {"coordinates":[-0.584654,47.374836],"type":"Point"}
}