{
  "type": "Feature",
  "properties": {
    "iso:country":"FR",
    "sg:address":"Zac Les Ingres 36000 Ch\u00e2teauroux",
    "sg:city":"Ch\u00e2teauroux",
    "sg:classifiers":[
        {
            "category":"Manufacturing",
            "subcategory":"Leather Goods",
            "type":"Manufacturing & Wholesale Goods"
        }
    ],
    "sg:phone":"+33 2 54 34 21 15",
    "sg:postcode":"36000",
    "sg:province":"Centre",
    "sg:tags":[
        "shoe"
    ],
    "wof:name":"Maquin G\u00c9rard Sas",
    "wof:placetype":"venue"
},
  "geometry": {"coordinates":[1.696558,46.812469],"type":"Point"}
}