{
  "type": "Feature",
  "properties": {
    "addr:full":"180, Av. Eug\u00e8ne Avin\u00e9e - Parc Eurasant\u00e9, 59120 Loos Nord Pas-de-Calais",
    "addr:housenumber":"180",
    "addr:postcode":"59120",
    "addr:street":"Av. Euge\u0300Ne Avine\u0301E Parc Eurasante\u0301",
    "iso:country":"FR",
    "sg:address":"180, Av. Eug\u00e8ne Avin\u00e9e - Parc Eurasant\u00e9, 59120 Loos",
    "sg:orig_category":"Unclassifiable Establishments",
    "sg:phone":"+33 3 20 16 83 00",
    "sg:province":"Nord Pas-de-Calais",
    "wof:name":"Cognitis S.a.",
    "wof:placetype":"venue"
},
  "geometry": {"coordinates":[3.030761,50.606922],"type":"Point"}
}