{
  "type": "Feature",
  "properties": {
    "addr:full":"45058 Orl\u00e9ans C\u00e9dex 1^^2, Av. de la Lib\u00e9ration, 45000 Orl\u00e9ans Orl\u00e9ans Centre 45000",
    "addr:housenumber":"^",
    "addr:postcode":"45058;45000;45000",
    "addr:street":"Av. De La Libe\u0301Ration",
    "iso:country":"FR",
    "sg:address":"45058 Orl\u00e9ans C\u00e9dex 1^^2, Av. de la Lib\u00e9ration, 45000 Orl\u00e9ans",
    "sg:city":"Orl\u00e9ans",
    "sg:orig_category":"Non-Classified Establishments",
    "sg:phone":"+33 2 38 22 86 87",
    "sg:postcode":"45000",
    "sg:province":"Centre",
    "wof:name":"A.f.p.a.",
    "wof:placetype":"venue"
},
  "geometry": {"coordinates":[1.904965,47.901428],"type":"Point"}
}