{
  "type": "Feature",
  "properties": {
    "addr:full":"Z.I. du Breuil Saint Florent sur Cher Centre 18400",
    "addr:housenumber":"cher",
    "addr:postcode":"18400",
    "addr:street":"Z.I. Du Breuil Saint Florent Sur",
    "iso:country":"FR",
    "sg:address":"Z.I. du Breuil",
    "sg:city":"Saint Florent sur Cher",
    "sg:orig_category":"Unclassifiable Establishments",
    "sg:phone":"+33 2 48 55 67 30",
    "sg:postcode":"18400",
    "sg:province":"Centre",
    "wof:name":"Megalit S.a.",
    "wof:placetype":"venue"
},
  "geometry": {"coordinates":[2.244945,46.992325],"type":"Point"}
}