{
  "type": "Feature",
  "properties": {
    "addr:full":"38 Rue Georges Caldray 56000 Vannes Vannes Bretagne 56000",
    "addr:housenumber":"38",
    "addr:postcode":"56000;56000",
    "addr:street":"Rue Georges Caldray",
    "iso:country":"FR",
    "sg:address":"38 Rue Georges Caldray 56000 Vannes",
    "sg:city":"Vannes",
    "sg:classifiers":[
        {
            "category":"Utilities",
            "subcategory":"Electric",
            "type":"Services"
        }
    ],
    "sg:phone":"+33 810 51 50 57",
    "sg:postcode":"56000",
    "sg:province":"Bretagne",
    "sg:tags":[
        "electricity",
        "raw",
        "energy",
        "material"
    ],
    "wof:name":"Electricite De France (edf)",
    "wof:placetype":"venue"
},
  "geometry": {"coordinates":[-2.776399,47.664719],"type":"Point"}
}