{
  "type": "Feature",
  "properties": {
    "addr:full":"22, Rte d' Orl\u00e9ans, 91310 Montlh\u00e9ry Ile de France",
    "addr:housenumber":"22",
    "addr:postcode":"91310;ile",
    "addr:street":"Rte D ' Orle\u0301Ans",
    "iso:country":"FR",
    "sg:address":"22, Rte d' Orl\u00e9ans, 91310 Montlh\u00e9ry",
    "sg:orig_category":"Unclassifiable Establishments",
    "sg:phone":"+33 1 69 01 01 37",
    "sg:province":"Ile de France",
    "wof:name":"B.i.c.s.",
    "wof:placetype":"venue"
},
  "geometry": {"coordinates":[2.268209,48.639591],"type":"Point"}
}