{
  "type": "Feature",
  "properties": {
    "iso:country":"FR",
    "sg:address":"B.P. 96, 83079 Toulon C\u00e9dex 9^^901, Av. Alphonse Louall\u00e9 - ZI Toulon Est - Centre Coudon, 83000 Toul",
    "sg:orig_category":"Non-Classified Establishments",
    "sg:phone":"+33 4 94 14 77 88",
    "sg:province":"Provence-Alpes-C\u00f4te d'Azur",
    "wof:name":"G\u00e9otec S.a.",
    "wof:placetype":"venue"
},
  "geometry": {"coordinates":[5.930305,43.125324],"type":"Point"}
}