{
  "type": "Feature",
  "properties": {
    "iso:country":"FR",
    "sg:address":"B.P. 11",
    "sg:city":"Grandvillars^^Site des Forges 90600 Grandvillars",
    "sg:orig_category":"Non-Classified Establishments",
    "sg:phone":"+33 3 84 23 59 37",
    "sg:postcode":"90600",
    "sg:province":"Franche Comt\u00e9",
    "wof:name":"M\u00e9casem S.a.",
    "wof:placetype":"venue"
},
  "geometry": {"coordinates":[6.9688,47.539146],"type":"Point"}
}