{
  "type": "Feature",
  "properties": {
    "iso:country":"FR",
    "sg:address":"boulevard Cassanyes 66140 Canet en Roussillon",
    "sg:classifiers":[
        {
            "category":"Food & Beverages",
            "subcategory":"Meat & Fish",
            "type":"Retail Goods"
        }
    ],
    "sg:phone":"+33 4 68 80 44 15",
    "sg:postcode":"66140",
    "sg:province":"Languedoc-Roussillon",
    "sg:tags":[
        "fresh"
    ],
    "wof:name":"Canet Maree Sarl",
    "wof:placetype":"venue"
},
  "geometry": {"coordinates":[3.035775,42.700279],"type":"Point"}
}