{
  "type": "Feature",
  "properties": {
    "addr:full":"Pont Des Samsons 69430 Quinci\u00e9 En Beaujolais Rhone-Alpes 69430",
    "addr:postcode":"69430;69430",
    "addr:street":"Pont Des Samsons;Rhone-Alpes",
    "iso:country":"FR",
    "sg:address":"Pont Des Samsons 69430 Quinci\u00e9 En Beaujolais",
    "sg:classifiers":[
        {
            "category":"Food Court",
            "type":"Food & Drink"
        }
    ],
    "sg:phone":"+33 4 74 69 09 20",
    "sg:postcode":"69430",
    "sg:province":"Rhone-Alpes",
    "sg:tags":[
        "product",
        "related"
    ],
    "wof:name":"Cellier Des Samsons Sa",
    "wof:placetype":"venue"
},
  "geometry": {"coordinates":[4.62833,46.113716],"type":"Point"}
}