{
  "type": "Feature",
  "properties": {
    "addr:full":"2040, Chemin Saint Bernard - Lotissement Fogliani, 06220 Vallauris Rhone-Alpes",
    "addr:housenumber":"2040",
    "addr:postcode":"06220",
    "addr:street":"Chemin Saint Bernard Lotissement Fogliani",
    "iso:country":"FR",
    "sg:address":"2040, Chemin Saint Bernard - Lotissement Fogliani, 06220 Vallauris",
    "sg:orig_category":"Non-Classified Establishments",
    "sg:phone":"+33 4 92 96 98 21",
    "sg:province":"Rhone-Alpes",
    "wof:name":"S.g.m.e. S.a.r.l. - Soci\u00e9t\u00e9 G\u00e9n\u00e9rale De Mat\u00e9riels Electroniques",
    "wof:placetype":"venue"
},
  "geometry": {"coordinates":[7.060788,43.573296],"type":"Point"}
}