{
  "type": "Feature",
  "properties": {
    "iso:country":"FR",
    "sg:address":"B.P. 5, 89460 Bazarnes^^40, Rte de Vezelay, 89460 Bazarnes",
    "sg:city":"Bazarnes",
    "sg:orig_category":"Non-Classified Establishments",
    "sg:phone":"+33 3 86 42 59 00",
    "sg:postcode":"89460",
    "sg:province":"Bourgogne",
    "wof:name":"Provib S.a.",
    "wof:placetype":"venue"
},
  "geometry": {"coordinates":[3.690575,47.681236],"type":"Point"}
}