{
  "type": "Feature",
  "properties": {
    "addr:full":"B.P. 6, 02407 Ch\u00e2teau Thierry C\u00e9dex^^Rue de la Plaine - Zone Industrielle, 02400 Ch\u00e2teau Thierry Picardie 02400",
    "addr:housenumber":"6",
    "addr:postcode":"02407;02400;02400",
    "addr:street":"B.P.;Plaine Zone Industrielle",
    "iso:country":"FR",
    "sg:address":"B.P. 6, 02407 Ch\u00e2teau Thierry C\u00e9dex^^Rue de la Plaine - Zone Industrielle, 02400 Ch\u00e2teau Thierry",
    "sg:orig_category":"Non-Classified Establishments",
    "sg:phone":"+33 3 23 83 82 00",
    "sg:postcode":"02400",
    "sg:province":"Picardie",
    "wof:name":"Cifra S.a. - Calandrage Industriel Fran\u00e7ais",
    "wof:placetype":"venue"
},
  "geometry": {"coordinates":[3.39314,49.05019],"type":"Point"}
}