{
  "type": "Feature",
  "properties": {
    "iso:country":"FR",
    "sg:address":"Route de l'Hippodrome 72140 LE GREZ",
    "sg:classifiers":[
        {
            "category":"Arena",
            "subcategory":"Horse Racetrack",
            "type":"Entertainment"
        }
    ],
    "sg:phone":"+33 2 43 20 12 90",
    "sg:postcode":"72140",
    "sg:province":"Pays de Loire",
    "sg:tags":[
        "trailer"
    ],
    "wof:name":"Lesage Sarl",
    "wof:placetype":"venue"
},
  "geometry": {"coordinates":[-0.202647,48.157921],"type":"Point"}
}