{
  "type": "Feature",
  "properties": {
    "iso:country":"FR",
    "sg:address":"ZA",
    "sg:city":"Saint Germain de Princay",
    "sg:orig_category":"Unclassifiable Establishments",
    "sg:phone":"+33 2 51 94 49 64",
    "sg:postcode":"85110",
    "sg:province":"Pays de Loire",
    "wof:name":"Clairval S.a.",
    "wof:placetype":"venue"
},
  "geometry": {"coordinates":[-0.963094,46.642857],"type":"Point"}
}