{
  "type": "Feature",
  "properties": {
    "addr:full":"368 Chemin Du Mont Rivel 39300 Champagnole Franche Comt\u00e9 39300",
    "addr:housenumber":"368",
    "addr:postcode":"39300;39300",
    "addr:street":"Chemin Du Mont Rivel;Franche Comte\u0301",
    "iso:country":"FR",
    "sg:address":"368 Chemin Du Mont Rivel 39300 Champagnole",
    "sg:classifiers":[
        {
            "category":"Home & Garden",
            "subcategory":"Furniture",
            "type":"Retail Goods"
        }
    ],
    "sg:phone":"+33 3 84 52 13 26",
    "sg:postcode":"39300",
    "sg:province":"Franche Comt\u00e9",
    "sg:tags":[
        "household",
        "wood"
    ],
    "wof:name":"Artica Sarl",
    "wof:placetype":"venue"
},
  "geometry": {"coordinates":[5.911338,46.753193],"type":"Point"}
}