{
  "type": "Feature",
  "properties": {
    "addr:full":"8, Rue du 8 Mai 1945, 80150 Vitz sur Authie Picardie",
    "addr:housenumber":"8",
    "addr:postcode":"80150",
    "addr:street":"Rue Du 8 Mai 1945",
    "iso:country":"FR",
    "sg:address":"8, Rue du 8 Mai 1945, 80150 Vitz sur Authie",
    "sg:orig_category":"Non-Classified Establishments",
    "sg:phone":"+33 3 22 29 20 41",
    "sg:province":"Picardie",
    "wof:name":"Qualivia S.a.",
    "wof:placetype":"venue"
},
  "geometry": {"coordinates":[2.063881,50.251987],"type":"Point"}
}