{
  "type": "Feature",
  "properties": {
    "addr:full":"ZA de Loguellou Pencran Bretagne 29800",
    "addr:postcode":"29800",
    "addr:street":"Za De Loguellou Pencran Bretagne",
    "iso:country":"FR",
    "sg:address":"ZA de Loguellou",
    "sg:city":"Pencran",
    "sg:orig_category":"Unclassifiable Establishments",
    "sg:phone":"+33 2 98 85 13 25",
    "sg:postcode":"29800",
    "sg:province":"Bretagne",
    "wof:name":"Jaffredou S.a.r.l.",
    "wof:placetype":"venue"
},
  "geometry": {"coordinates":[-4.234044,48.437721],"type":"Point"}
}