{
  "type": "Feature",
  "properties": {
    "iso:country":"FR",
    "sg:address":"29, Rue Roger Salengro, 69310 Pierre B\u00e9nite",
    "sg:orig_category":"Non-Classified Establishments",
    "sg:phone":"+33 4 78 50 42 03",
    "sg:postcode":"69310",
    "sg:province":"Rhone-Alpes",
    "wof:name":"Art Et Technique Du Nettoyage Atn S.a.r.l.",
    "wof:placetype":"venue"
},
  "geometry": {"coordinates":[4.821325,45.706825],"type":"Point"}
}