{
  "type": "Feature",
  "properties": {
    "iso:country":"FR",
    "sg:address":"Bonnatrait 74140 Sciez",
    "sg:classifiers":[
        {
            "category":"Professional",
            "subcategory":"Computer Services",
            "type":"Services"
        }
    ],
    "sg:phone":"+33 4 50 72 39 82",
    "sg:postcode":"74140",
    "sg:province":"Rhone-Alpes",
    "sg:tags":[
        "digital"
    ],
    "wof:name":"Dynamad S.a.r.l.",
    "wof:placetype":"venue"
},
  "geometry": {"coordinates":[6.392765,46.334465],"type":"Point"}
}