{
  "type": "Feature",
  "properties": {
    "addr:full":"5 pl de l'Etoile; Aubergenville; 78410 Ile de France 78410",
    "addr:housenumber":"5",
    "addr:postcode":"78410 ile;france 78410",
    "addr:street":"Pl De L'Etoile",
    "iso:country":"FR",
    "sg:address":"5 pl de l'Etoile; Aubergenville; 78410",
    "sg:classifiers":[
        {
            "category":"Banks & Credit Unions",
            "subcategory":"Bank",
            "type":"Services"
        }
    ],
    "sg:phone":"+33 30957980",
    "sg:postcode":"78410",
    "sg:province":"Ile de France",
    "wof:name":"Banque Nationale De Paris",
    "wof:placetype":"venue"
},
  "geometry": {"coordinates":[1.871581,48.963394],"type":"Point"}
}