{
  "type": "Feature",
  "properties": {
    "iso:country":"FR",
    "sg:address":"39, Av. Carnot, 91300 Massy",
    "sg:orig_category":"Unclassifiable Establishments",
    "sg:phone":"+33 1 69 32 11 20",
    "sg:province":"Ile de France",
    "wof:name":"Rent Car Acara S.a.",
    "wof:placetype":"venue"
},
  "geometry": {"coordinates":[2.260741,48.724613],"type":"Point"}
}