{
  "type": "Feature",
  "properties": {
    "iso:country":"FR",
    "sg:address":"12 av M de Robespierre 94400 Vitry Sur Seine",
    "sg:classifiers":[
        {
            "category":"Train Station",
            "subcategory":"Light Rail",
            "type":"Transportation"
        }
    ],
    "sg:phone":"+33 1 46 81 58 10",
    "sg:province":"Ile de France",
    "sg:tags":[
        "sensor"
    ],
    "wof:name":"J2p Instrumentation S.a.r.l.",
    "wof:placetype":"venue"
},
  "geometry": {"coordinates":[2.387491,48.790703],"type":"Point"}
}