{
  "type": "Feature",
  "properties": {
    "iso:country":"FR",
    "sg:address":"ZI Combe de Veyle",
    "sg:city":"Replonges",
    "sg:orig_category":"Unclassifiable Establishments",
    "sg:phone":"+33 3 85 31 12 10",
    "sg:postcode":"01750",
    "sg:province":"Rhone-Alpes",
    "wof:name":"Cryl S.a.s.",
    "wof:placetype":"venue"
},
  "geometry": {"coordinates":[4.872405,46.301384],"type":"Point"}
}