{
  "type": "Feature",
  "properties": {
    "iso:country":"FR",
    "sg:address":"Zac De Nicopolis Rn7 83172 Brignoles",
    "sg:classifiers":[
        {
            "category":"Shopping",
            "subcategory":"Computers & Home Electronics",
            "type":"Retail Goods"
        }
    ],
    "sg:phone":"+33 4 94 69 56 78",
    "sg:province":"Centre",
    "sg:tags":[
        "information",
        "peripheral",
        "-",
        "technology"
    ],
    "wof:name":"Vitte",
    "wof:placetype":"venue"
},
  "geometry": {"coordinates":[6.065544,43.406113],"type":"Point"}
}