{
  "type": "Feature",
  "properties": {
    "addr:full":"7 Chemin Du Barrail 47310 Brax Brax Aquitaine 47310",
    "addr:housenumber":"7",
    "addr:postcode":"47310;47310",
    "addr:street":"Chemin Du Barrail",
    "iso:country":"FR",
    "sg:address":"7 Chemin Du Barrail 47310 Brax",
    "sg:city":"Brax",
    "sg:classifiers":[
        {
            "category":"Autos & Motor Vehicles",
            "subcategory":"Automobile Sales",
            "type":"Retail Goods"
        }
    ],
    "sg:phone":"+33 5 53 98 38 50",
    "sg:postcode":"47310",
    "sg:province":"Aquitaine",
    "sg:tags":[
        "equipment",
        "motor-cars",
        "transport"
    ],
    "wof:name":"Carrosserie D'aquitaine Et Midi Pyrenees Camp (camp)",
    "wof:placetype":"venue"
},
  "geometry": {"coordinates":[0.570734,44.197025],"type":"Point"}
}