{
  "type": "Feature",
  "properties": {
    "iso:country":"FR",
    "sg:address":"3, Enclos des B\u00e9n\u00e9dictins, 18000 Bourges",
    "sg:city":"Bourges",
    "sg:orig_category":"Unclassifiable Establishments",
    "sg:phone":"+33 2 48 23 01 10",
    "sg:postcode":"18000",
    "sg:province":"Centre",
    "wof:name":"Tessiot D\u00e9m\u00e9nagement S.a.r.l.",
    "wof:placetype":"venue"
},
  "geometry": {"coordinates":[2.385842,47.087128],"type":"Point"}
}