{
  "type": "Feature",
  "properties": {
    "iso:country":"FR",
    "sg:address":"28 Rue De La Courbe 88162 Le Thillot Cedex",
    "sg:city":"La Courbe",
    "sg:classifiers":[
        {
            "category":"Home & Garden",
            "subcategory":"Furniture",
            "type":"Retail Goods"
        }
    ],
    "sg:phone":"+33 3 29 25 20 04",
    "sg:postcode":"61150",
    "sg:province":"Basse Normandie",
    "sg:tags":[
        "household",
        "wood"
    ],
    "wof:name":"Martival Sa",
    "wof:placetype":"venue"
},
  "geometry": {"coordinates":[6.754938,47.879932],"type":"Point"}
}