{
  "type": "Feature",
  "properties": {
    "iso:country":"FR",
    "sg:address":"Rue Eperon Dor\u00e9 - ZI de la Bihardais",
    "sg:city":"Bruz",
    "sg:orig_category":"Unclassifiable Establishments",
    "sg:phone":"+33 2 99 52 75 52",
    "sg:postcode":"35170",
    "sg:province":"Bretagne",
    "wof:name":"Plastic System International",
    "wof:placetype":"venue"
},
  "geometry": {"coordinates":[-1.773184,48.006374],"type":"Point"}
}