{
  "type": "Feature",
  "properties": {
    "iso:country":"FR",
    "sg:address":"48 Rue De L Ermitage 93100 Montreuil",
    "sg:classifiers":[
        {
            "category":"Professional",
            "subcategory":"Engineering",
            "type":"Services"
        }
    ],
    "sg:phone":"+33 1 48 70 06 07",
    "sg:postcode":"93100",
    "sg:province":"Ile de France",
    "sg:tags":[
        "machine",
        "-",
        "mechanical"
    ],
    "wof:name":"Cif Inox",
    "wof:placetype":"venue"
},
  "geometry": {"coordinates":[2.452584,48.869652],"type":"Point"}
}