{
  "type": "Feature",
  "properties": {
    "addr:full":"20 Rue De La Citadelle 85150 St Georges De Pointindoux Pays de Loire 85150",
    "addr:housenumber":"20",
    "addr:postcode":"85150;85150",
    "addr:street":"Rue De La Citadelle;Pointindoux",
    "iso:country":"FR",
    "sg:address":"20 Rue De La Citadelle 85150 St Georges De Pointindoux",
    "sg:orig_category":"Miscellaneous Products",
    "sg:phone":"+33 2 51 38 61 47",
    "sg:postcode":"85150",
    "sg:province":"Pays de Loire",
    "wof:name":"Perocheau J Jacques Funeraire Batiment",
    "wof:placetype":"venue"
},
  "geometry": {"coordinates":[-1.623434,46.644169],"type":"Point"}
}