{
  "type": "Feature",
  "properties": {
    "iso:country":"FR",
    "sg:address":"ZA du Vimeu Industriel",
    "sg:city":"Feuqui\u00e8res en Vimeu",
    "sg:orig_category":"SOUS-TRAITANCE INDUSTRIELLE",
    "sg:phone":"+33 3 22 61 26 12",
    "sg:postcode":"80210",
    "sg:province":"Picardie",
    "wof:name":"Devismes S.a.",
    "wof:placetype":"venue"
},
  "geometry": {"coordinates":[1.604313,50.06144],"type":"Point"}
}