{
  "type": "Feature",
  "properties": {
    "addr:full":"12, Av. Marie Talet, 49000 Angers Pays de Loire",
    "addr:postcode":"49000",
    "addr:street":"12 Av. Marie Talet",
    "iso:country":"FR",
    "sg:address":"12, Av. Marie Talet, 49000 Angers",
    "sg:orig_category":"Unclassifiable Establishments",
    "sg:phone":"+33 2 41 73 87 73",
    "sg:province":"Pays de Loire",
    "wof:name":"Brochard Et Gaudichet S.n.c.",
    "wof:placetype":"venue"
},
  "geometry": {"coordinates":[-0.547682,47.476368],"type":"Point"}
}