{
  "type": "Feature",
  "properties": {
    "addr:full":"150 Avenue Joseph Kessel 78960 Voisins Le Bretonneux Ile de France 78960",
    "addr:housenumber":"150",
    "addr:postcode":"78960;78960",
    "addr:street":"Avenue Joseph Kessel",
    "iso:country":"FR",
    "sg:address":"150 Avenue Joseph Kessel 78960 Voisins Le Bretonneux",
    "sg:classifiers":[
        {
            "category":"Shopping",
            "subcategory":"Computers & Home Electronics",
            "type":"Retail Goods"
        }
    ],
    "sg:phone":"+33 1 39 30 19 00",
    "sg:postcode":"78960",
    "sg:province":"Ile de France",
    "sg:tags":[
        "equipment",
        "electrical",
        "component",
        "electric",
        "electronic"
    ],
    "wof:name":"Maxim France Sarl",
    "wof:placetype":"venue"
},
  "geometry": {"coordinates":[2.058564,48.765423],"type":"Point"}
}