{
  "type": "Feature",
  "properties": {
    "addr:full":"27, Rte D\u00e9partementale - Z.I., 88510 Eloyes Lorraine",
    "addr:housenumber":"27",
    "addr:postcode":"88510",
    "addr:street":"Rte De\u0301Partementale Z.I.",
    "iso:country":"FR",
    "sg:address":"27, Rte D\u00e9partementale - Z.I., 88510 Eloyes",
    "sg:orig_category":"Unclassifiable Establishments",
    "sg:phone":"+33 6 07 03 48 45",
    "sg:province":"Lorraine",
    "wof:name":"Loca Bennes S.a.r.l.",
    "wof:placetype":"venue"
},
  "geometry": {"coordinates":[6.610609,48.093906],"type":"Point"}
}