{
  "type": "Feature",
  "properties": {
    "iso:country":"FR",
    "sg:address":"19 rue des Balanciers 57100 Thionville",
    "sg:classifiers":[
        {
            "category":"Personal",
            "subcategory":"Beauty Salon",
            "type":"Services"
        }
    ],
    "sg:phone":"+33 3 82 53 25 29",
    "sg:postcode":"57100",
    "sg:province":"Lorraine",
    "sg:tags":[
        "hair",
        "shampoo"
    ],
    "wof:name":"Sopret S.a.r.l.",
    "wof:placetype":"venue"
},
  "geometry": {"coordinates":[6.171096,49.370499],"type":"Point"}
}