{
  "type": "Feature",
  "properties": {
    "iso:country":"FR",
    "sg:address":"ZA du Tertre",
    "sg:city":"Pellouailles les Vignes",
    "sg:orig_category":"Unclassifiable Establishments",
    "sg:phone":"+33 2 41 76 47 12",
    "sg:postcode":"49112",
    "sg:province":"Pays de Loire",
    "wof:name":"Strader S.a.",
    "wof:placetype":"venue"
},
  "geometry": {"coordinates":[-0.440534,47.521824],"type":"Point"}
}