{
  "type": "Feature",
  "properties": {
    "addr:full":"23 Bis Rue Du Bignon Zi Sud Est 35574 Chantepie Cedex Chantepie Bretagne 35135",
    "addr:housenumber":"23 bis",
    "addr:postcode":"35574;cedex chantepie;35135",
    "addr:street":"Rue Du Bignon Zi Sud Est",
    "iso:country":"FR",
    "sg:address":"23 Bis Rue Du Bignon Zi Sud Est 35574 Chantepie Cedex",
    "sg:city":"Chantepie",
    "sg:orig_category":"Audio-visual Business advice and other services Telecommunications",
    "sg:phone":"+33 2 99 26 60 00",
    "sg:postcode":"35135",
    "sg:province":"Bretagne",
    "wof:name":"Alcatel Reseaux D'entreprises",
    "wof:placetype":"venue"
},
  "geometry": {"coordinates":[-1.61886,48.088348],"type":"Point"}
}