{
  "type": "Feature",
  "properties": {
    "iso:country":"FR",
    "sg:address":"3 Rue Carnot 71300 Montceau Les Mines",
    "sg:city":"Saint-Berain-sous-Sanvignes",
    "sg:classifiers":[
        {
            "category":"Professional",
            "subcategory":"Printing & Photocopies",
            "type":"Services"
        }
    ],
    "sg:phone":"+33 3 85 57 04 61",
    "sg:postcode":"71300",
    "sg:province":"Bourgogne",
    "sg:tags":[
        "publishing"
    ],
    "wof:name":"Les Journaux De Saone Et Loire (jsl)",
    "wof:placetype":"venue"
},
  "geometry": {"coordinates":[4.364109,46.674835],"type":"Point"}
}