{
  "type": "Feature",
  "properties": {
    "addr:full":"40 boulevard de Dunkerque 13002 Marseille Poitou-Charentes",
    "addr:housenumber":"40",
    "addr:postcode":"13002",
    "addr:street":"Boulevard De Dunkerque",
    "iso:country":"FR",
    "sg:address":"40 boulevard de Dunkerque 13002 Marseille",
    "sg:classifiers":[
        {
            "category":"Professional",
            "type":"Services"
        }
    ],
    "sg:phone":"+33 4 91 13 18 00",
    "sg:province":"Poitou-Charentes",
    "sg:tags":[
        "transport"
    ],
    "wof:name":"P.o. Nedlloyd S.a.",
    "wof:placetype":"venue"
},
  "geometry": {"coordinates":[5.368016,43.307137],"type":"Point"}
}