{
  "type": "Feature",
  "properties": {
    "iso:country":"FR",
    "sg:address":"Parc Baboin",
    "sg:city":"La Voulte sur Rh\u00f4ne",
    "sg:orig_category":"Unclassifiable Establishments",
    "sg:phone":"+33 4 75 62 40 37",
    "sg:postcode":"07800",
    "sg:province":"Rhone-Alpes",
    "wof:name":"Cim\u00e9ca S.a.",
    "wof:placetype":"venue"
},
  "geometry": {"coordinates":[4.778902,44.802254],"type":"Point"}
}