{
  "type": "Feature",
  "properties": {
    "addr:full":"2, Rue du Vallon, 94440 Marolles en Brie Ile de France",
    "addr:housenumber":"2",
    "addr:postcode":"94440",
    "addr:street":"Rue Du Vallon",
    "iso:country":"FR",
    "sg:address":"2, Rue du Vallon, 94440 Marolles en Brie",
    "sg:orig_category":"Unclassifiable Establishments",
    "sg:phone":"+33 1 45 10 79 04",
    "sg:province":"Ile de France",
    "wof:name":"Jeambrun Automation S.a.",
    "wof:placetype":"venue"
},
  "geometry": {"coordinates":[2.538601,48.726952],"type":"Point"}
}