{
  "type": "Feature",
  "properties": {
    "addr:full":"ZI Secteur B - Lot 1 Saint Laurent du Var Champagne 06700",
    "addr:housenumber":"lot 1",
    "addr:postcode":"06700",
    "addr:street":"Zi;Var Champagne",
    "iso:country":"FR",
    "sg:address":"ZI Secteur B - Lot 1",
    "sg:city":"Saint Laurent du Var",
    "sg:orig_category":"Unclassifiable Establishments",
    "sg:phone":"+33 4 92 12 59 00",
    "sg:postcode":"06700",
    "sg:province":"Champagne",
    "wof:name":"D.h.l Worlwide Express S.a.",
    "wof:placetype":"venue"
},
  "geometry": {"coordinates":[7.183398,43.684536],"type":"Point"}
}