{
  "type": "Feature",
  "properties": {
    "addr:full":"9, Rue d'Alen\u00e7on, 14100 Lisieux Lisieux Basse Normandie 14100",
    "addr:housenumber":"9",
    "addr:postcode":"14100;14100",
    "addr:street":"Rue D'Alenc \u0327On",
    "iso:country":"FR",
    "sg:address":"9, Rue d'Alen\u00e7on, 14100 Lisieux",
    "sg:city":"Lisieux",
    "sg:orig_category":"Unclassifiable Establishments",
    "sg:phone":"+33 2 31 62 72 17",
    "sg:postcode":"14100",
    "sg:province":"Basse Normandie",
    "wof:name":"C.r.i.t. Int\u00e9rim S.a.",
    "wof:placetype":"venue"
},
  "geometry": {"coordinates":[0.227379,49.141808],"type":"Point"}
}