{
  "type": "Feature",
  "properties": {
    "addr:full":", 16120 CHATEAUNEUF SUR CHARENTE CHATEAUNEUF SUR CHARENTE Poitou-Charentes 16120",
    "addr:postcode":"16120;16120",
    "iso:country":"FR",
    "sg:address":", 16120 CHATEAUNEUF SUR CHARENTE",
    "sg:city":"CHATEAUNEUF SUR CHARENTE",
    "sg:classifiers":[
        {
            "category":"Manufacturing",
            "subcategory":"Wood Products",
            "type":"Manufacturing & Wholesale Goods"
        }
    ],
    "sg:phone":"+33 5 45 62 53 77",
    "sg:postcode":"16120",
    "sg:province":"Poitou-Charentes",
    "sg:tags":[
        "made",
        "door",
        "panel"
    ],
    "wof:name":"Vallin S.a.",
    "wof:placetype":"venue"
},
  "geometry": {"coordinates":[-0.051824,45.598511],"type":"Point"}
}