{
  "type": "Feature",
  "properties": {
    "addr:full":"11 Rue Ernest Renan 92190 Meudon Ile de France 92190",
    "addr:housenumber":"11",
    "addr:postcode":"92190;92190",
    "addr:street":"Rue Ernest Renan",
    "iso:country":"FR",
    "sg:address":"11 Rue Ernest Renan 92190 Meudon",
    "sg:classifiers":[
        {
            "category":"Professional",
            "subcategory":"Business Services",
            "type":"Services"
        }
    ],
    "sg:phone":"+33 1 46 26 99 88",
    "sg:postcode":"92190",
    "sg:province":"Ile de France",
    "sg:tags":[
        "training",
        "advice"
    ],
    "wof:name":"Association La Source",
    "wof:placetype":"venue"
},
  "geometry": {"coordinates":[2.227112,48.818928],"type":"Point"}
}