{
  "type": "Feature",
  "properties": {
    "addr:full":"105, Av de Cal\u00e8s, 12100 Millau Midi Pyr\u00e9n\u00e9es",
    "addr:postcode":"12100",
    "addr:street":"105 Av De Cale\u0300S",
    "iso:country":"FR",
    "sg:address":"105, Av de Cal\u00e8s, 12100 Millau",
    "sg:orig_category":"Unclassifiable Establishments",
    "sg:phone":"+33 5 65 60 07 55",
    "sg:province":"Midi Pyr\u00e9n\u00e9es",
    "wof:name":"Modern'gant S.a.r.l.",
    "wof:placetype":"venue"
},
  "geometry": {"coordinates":[3.072111,44.093781],"type":"Point"}
}