{
  "type": "Feature",
  "properties": {
    "iso:country":"FR",
    "sg:address":"La Teinture 47200 Montpouillan",
    "sg:city":"Montpouillan",
    "sg:classifiers":[
        {
            "category":"Utilities",
            "type":"Services"
        }
    ],
    "sg:phone":"+33 5 53 89 89 50",
    "sg:postcode":"47200",
    "sg:province":"Aquitaine",
    "sg:tags":[
        "raw",
        "energy",
        "material"
    ],
    "wof:name":"Alvea",
    "wof:placetype":"venue"
},
  "geometry": {"coordinates":[0.119415,44.464588],"type":"Point"}
}