{
  "type": "Feature",
  "properties": {
    "addr:full":"266, Av. Daumesnil - Sofradem, 75012 Paris Ile de France",
    "addr:postcode":"75012",
    "addr:street":"266 Av. Daumesnil Sofradem",
    "iso:country":"FR",
    "sg:address":"266, Av. Daumesnil - Sofradem, 75012 Paris",
    "sg:orig_category":"Non-Classified Establishments",
    "sg:phone":"+33 1 60 44 29 70",
    "sg:province":"Ile de France",
    "wof:name":"G.p.m.g. 21 S.a.r.l. - Gestion Des Performances De Fonction Maintenance Globale",
    "wof:placetype":"venue"
},
  "geometry": {"coordinates":[2.389295,48.841045],"type":"Point"}
}