{
  "type": "Feature",
  "properties": {
    "iso:country":"FR",
    "sg:address":"B.P. 6, 07700 Bourg Saint And\u00e9ol C\u00e9dex^^Rte de Saint Rem\u00e8ze - Le Haut Derbousset, 07700 Bourg Saint ",
    "sg:orig_category":"Non-Classified Establishments",
    "sg:phone":"+33 4 75 54 45 45",
    "sg:province":"Rhone-Alpes",
    "wof:name":"Schadroff S.a.",
    "wof:placetype":"venue"
},
  "geometry": {"coordinates":[4.64433,44.371861],"type":"Point"}
}