{
  "type": "Feature",
  "properties": {
    "addr:full":"Grande Rue 70140 Sauvigney Les Pesmes Franche Comt\u00e9",
    "addr:postcode":"70140",
    "addr:street":"Grande Rue;Franche Comte\u0301",
    "iso:country":"FR",
    "sg:address":"Grande Rue 70140 Sauvigney Les Pesmes",
    "sg:classifiers":[
        {
            "category":"Home & Garden",
            "subcategory":"Furniture",
            "type":"Retail Goods"
        }
    ],
    "sg:phone":"+33 3 84 31 26 60",
    "sg:province":"Franche Comt\u00e9",
    "sg:tags":[
        "wood"
    ],
    "wof:name":"Ste Franc Comptoise De Tournerie",
    "wof:placetype":"venue"
},
  "geometry": {"coordinates":[5.567486,47.297955],"type":"Point"}
}