{
  "type": "Feature",
  "properties": {
    "addr:full":"La Vigne 61250 Radon Radon Basse Normandie 61250",
    "addr:postcode":"61250;61250",
    "addr:street":"Vigne",
    "iso:country":"FR",
    "sg:address":"La Vigne 61250 Radon",
    "sg:city":"Radon",
    "sg:orig_category":"Unclassifiable Establishments",
    "sg:phone":"+33 2 33 28 11 64",
    "sg:postcode":"61250",
    "sg:province":"Basse Normandie",
    "wof:name":"Delangle Paysage S.a.r.l.",
    "wof:placetype":"venue"
},
  "geometry": {"coordinates":[0.074856,48.488918],"type":"Point"}
}