{
  "type": "Feature",
  "properties": {
    "addr:full":"6 Bd Agutte Sembat BP 186 38004 Grenoble Grenoble Rhone-Alpes 38100",
    "addr:housenumber":"6;bp 186",
    "addr:postcode":"38004;38100",
    "addr:street":"Bd Agutte Sembat",
    "iso:country":"FR",
    "sg:address":"6 Bd Agutte Sembat BP 186 38004 Grenoble",
    "sg:city":"Grenoble",
    "sg:classifiers":[
        {
            "category":"Manufacturing",
            "subcategory":"Chemicals & Compounds",
            "type":"Manufacturing & Wholesale Goods"
        }
    ],
    "sg:phone":"+33 4 76 12 17 40",
    "sg:postcode":"38100",
    "sg:province":"Rhone-Alpes",
    "sg:tags":[
        "pharmaceutical",
        "chemistry"
    ],
    "wof:name":"Stearinerie Dubois Fils",
    "wof:placetype":"venue"
},
  "geometry": {"coordinates":[5.725773,45.18853],"type":"Point"}
}