{
  "type": "Feature",
  "properties": {
    "iso:country":"FR",
    "sg:address":"B.P. 15, 59193 Erquinghem Lys^^1411, Rue de l'Alloeu, 59193 Erquinghem Lys",
    "sg:orig_category":"Non-Classified Establishments",
    "sg:phone":"+33 3 20 77 90 91",
    "sg:postcode":"59193",
    "sg:province":"Nord Pas-de-Calais",
    "wof:name":"Costenoble Jean-louis",
    "wof:placetype":"venue"
},
  "geometry": {"coordinates":[2.833447,50.674976],"type":"Point"}
}