{
  "type": "Feature",
  "properties": {
    "addr:full":"A\u00e9roport Paris Orly Orly Fr\u00eat 725 94310 Orly Ile de France",
    "addr:housenumber":"725",
    "addr:postcode":"94310",
    "addr:street":"Ile De France",
    "iso:country":"FR",
    "sg:address":"A\u00e9roport Paris Orly Orly Fr\u00eat 725 94310 Orly",
    "sg:classifiers":[
        {
            "category":"Banks & Credit Unions",
            "subcategory":"Investment Brokerage",
            "type":"Services"
        }
    ],
    "sg:phone":"+33 1 45 60 81 54",
    "sg:province":"Ile de France",
    "sg:tags":[
        "-",
        "transport",
        "related"
    ],
    "wof:name":"Moiroud Sa",
    "wof:placetype":"venue"
},
  "geometry": {"coordinates":[2.40138,48.743031],"type":"Point"}
}