{
  "type": "Feature",
  "properties": {
    "addr:full":"13 Rue Georges Auric 75019 Paris Ile de France 75019",
    "addr:housenumber":"13",
    "addr:postcode":"75019;75019",
    "addr:street":"Rue Georges Auric",
    "iso:country":"FR",
    "sg:address":"13 Rue Georges Auric 75019 Paris",
    "sg:classifiers":[
        {
            "category":"Health Services",
            "subcategory":"Medical Lab",
            "type":"Services"
        }
    ],
    "sg:phone":"+33 1 44 52 32 32",
    "sg:postcode":"75019",
    "sg:province":"Ile de France",
    "sg:tags":[
        "chemical",
        "pharmaceutical",
        "pharmacy"
    ],
    "wof:name":"Laboratoires Dolisos",
    "wof:placetype":"venue"
},
  "geometry": {"coordinates":[2.385513,48.885029],"type":"Point"}
}