{
  "type": "Feature",
  "properties": {
    "iso:country":"FR",
    "sg:address":"4, Rue de la St\u00e9rie - Le Quintet, 75116 Paris C\u00e9dex",
    "sg:orig_category":"Non-Classified Establishments",
    "sg:phone":"+33 1 53 70 71 72",
    "sg:province":"\u00cele-de-France",
    "wof:name":"Gti Software S.a.",
    "wof:placetype":"venue"
},
  "geometry": {"coordinates":[2.274115,48.864906],"type":"Point"}
}