{
  "type": "Feature",
  "properties": {
    "iso:country":"FR",
    "sg:address":"365, Rte de Saint Germain, 78424 Carri\u00e8res sur Seine C\u00e9dex",
    "sg:orig_category":"Non-Classified Establishments",
    "sg:phone":"+33 1 30 86 60 00",
    "sg:province":"\u00cele-de-France",
    "wof:name":"Minolta France S.a.",
    "wof:placetype":"venue"
},
  "geometry": {"coordinates":[2.165287,48.910954],"type":"Point"}
}