{
  "type": "Feature",
  "properties": {
    "iso:country":"FR",
    "sg:address":"28/32, Rue Jacques Ibert, 75858 Paris C\u00e9dex 17",
    "sg:orig_category":"Non-Classified Establishments",
    "sg:phone":"+33 1 40 89 76 00",
    "sg:province":"Nord Pas-de-Calais",
    "wof:name":"Elida Faberg\u00e9 S.a.",
    "wof:placetype":"venue"
},
  "geometry": {"coordinates":[2.28776,48.88755],"type":"Point"}
}