{
  "type": "Feature",
  "properties": {
    "iso:country":"FR",
    "sg:address":"406, Rue Albert Bailly, 59290 Wasquehal",
    "sg:orig_category":"Non-Classified Establishments",
    "sg:phone":"+33 3 20 98 55 04",
    "sg:province":"Nord Pas-de-Calais",
    "wof:name":"Promotel S.a.",
    "wof:placetype":"venue"
},
  "geometry": {"coordinates":[3.11747,50.68943],"type":"Point"}
}