{
  "type": "Feature",
  "properties": {
    "iso:country":"FR",
    "sg:address":"B.P. 120, 59202 Tourcoing C\u00e9dex^^105, Rue de Rotterdam, 59200 Tourcoing",
    "sg:orig_category":"Non-Classified Establishments",
    "sg:phone":"+33 3 20 69 11 11",
    "sg:postcode":"59200",
    "sg:province":"Nord Pas-de-Calais",
    "wof:name":"Dumortier P. Fr\u00e8res S.a.",
    "wof:placetype":"venue"
},
  "geometry": {"coordinates":[3.159375,50.722389],"type":"Point"}
}