{
  "type": "Feature",
  "properties": {
    "addr:full":"Rue Nationale 36400 La Chatre La Ch\u00e2tre Centre 36400",
    "addr:housenumber":"cha\u0302tre",
    "addr:postcode":"36400;36400",
    "addr:street":"Rue Nationale",
    "iso:country":"FR",
    "sg:address":"Rue Nationale 36400 La Chatre",
    "sg:city":"La Ch\u00e2tre",
    "sg:classifiers":[
        {
            "category":"Wholesale",
            "subcategory":"Machinery & Supplies",
            "type":"Manufacturing & Wholesale Goods"
        }
    ],
    "sg:phone":"+33 2 54 06 06 30",
    "sg:postcode":"36400",
    "sg:province":"Centre",
    "sg:tags":[
        "-",
        "machine",
        "equipment",
        "engineering",
        "animal",
        "mechanical",
        "breeding",
        "agriculture"
    ],
    "wof:name":"Satene Sarl",
    "wof:placetype":"venue"
},
  "geometry": {"coordinates":[1.989015,46.58461],"type":"Point"}
}