{
  "type": "Feature",
  "properties": {
    "addr:full":"Rte du Lac Mourenx Aquitaine 64150",
    "addr:postcode":"64150",
    "addr:street":"Rte Du Lac",
    "iso:country":"FR",
    "sg:address":"Rte du Lac",
    "sg:city":"Mourenx",
    "sg:orig_category":"Unclassifiable Establishments",
    "sg:phone":"+33 5 59 60 79 00",
    "sg:postcode":"64150",
    "sg:province":"Aquitaine",
    "wof:name":"Sylachim",
    "wof:placetype":"venue"
},
  "geometry": {"coordinates":[-0.602939,43.378117],"type":"Point"}
}