{
  "type": "Feature",
  "properties": {
    "iso:country":"FR",
    "sg:address":"Ave Jean Jaur\u00e8s Centre; Montfermeil; 93370",
    "sg:classifiers":[
        {
            "category":"Banks & Credit Unions",
            "subcategory":"Bank",
            "type":"Services"
        }
    ],
    "sg:phone":"+33 13305744",
    "sg:postcode":"93370",
    "sg:province":"Ile de France",
    "wof:name":"Banque Nationale De Paris",
    "wof:placetype":"venue"
},
  "geometry": {"coordinates":[2.546925,48.898827],"type":"Point"}
}