{
  "type": "Feature",
  "properties": {
    "addr:full":"11, Rue de Cambrai, 75019 Paris Ile de France",
    "addr:housenumber":"11",
    "addr:postcode":"75019",
    "addr:street":"Rue De Cambrai",
    "iso:country":"FR",
    "sg:address":"11, Rue de Cambrai, 75019 Paris",
    "sg:orig_category":"Unclassifiable Establishments",
    "sg:phone":"+33 1 40 35 83 13",
    "sg:province":"Ile de France",
    "wof:name":"Eurosab S.a.r.l.",
    "wof:placetype":"venue"
},
  "geometry": {"coordinates":[2.377907,48.89473],"type":"Point"}
}