{
  "type": "Feature",
  "properties": {
    "addr:full":"B.P. 7, 38601 Fontaine C\u00e9dex^^49/51, Bd Paul Langevin, 38600 Fontaine Rhone-Alpes 38600",
    "addr:housenumber":"7",
    "addr:postcode":"38601;51;38600;38600",
    "addr:street":"B.P.;Bd Paul Langevin",
    "iso:country":"FR",
    "sg:address":"B.P. 7, 38601 Fontaine C\u00e9dex^^49/51, Bd Paul Langevin, 38600 Fontaine",
    "sg:orig_category":"Non-Classified Establishments",
    "sg:phone":"+33 4 76 85 95 00",
    "sg:postcode":"38600",
    "sg:province":"Rhone-Alpes",
    "wof:name":"Bouvier Darling S.a.",
    "wof:placetype":"venue"
},
  "geometry": {"coordinates":[5.687735,45.191673],"type":"Point"}
}