{
  "type": "Feature",
  "properties": {
    "addr:full":"84 B Rue Martyrs La Resistance 51000 Chalons En Champagne Champagne 51000",
    "addr:housenumber":"84 b",
    "addr:postcode":"51000;51000",
    "addr:street":"Rue Martyrs La Resistance",
    "iso:country":"FR",
    "sg:address":"84 B Rue Martyrs La Resistance 51000 Chalons En Champagne",
    "sg:classifiers":[
        {
            "category":"Shopping",
            "subcategory":"Clothing, Apparel, & Fashions",
            "type":"Retail Goods"
        }
    ],
    "sg:phone":"+33 3 26 21 45 19",
    "sg:postcode":"51000",
    "sg:province":"Champagne",
    "sg:tags":[
        "textile",
        "clothing",
        "clothes"
    ],
    "wof:name":"Saint Loup Confection",
    "wof:placetype":"venue"
},
  "geometry": {"coordinates":[4.369045,48.95929],"type":"Point"}
}