{
  "type": "Feature",
  "properties": {
    "addr:full":"ZI Saint Christophe Digne les Bains Provence-Alpes-C\u00f4te d'Azur 04000",
    "addr:postcode":"04000",
    "addr:street":"Christophe Digne Les Bains",
    "iso:country":"FR",
    "sg:address":"ZI Saint Christophe",
    "sg:city":"Digne les Bains",
    "sg:orig_category":"Unclassifiable Establishments",
    "sg:phone":"+33 4 92 32 25 57",
    "sg:postcode":"04000",
    "sg:province":"Provence-Alpes-C\u00f4te d'Azur",
    "wof:name":"Arc En Ciel S.a.r.l.",
    "wof:placetype":"venue"
},
  "geometry": {"coordinates":[6.235892,44.093357],"type":"Point"}
}