{
  "type": "Feature",
  "properties": {
    "addr:full":"17, Rue Manurhin, 68120 Richwiller Richwiller Alsace 68120",
    "addr:housenumber":"17",
    "addr:postcode":"68120;68120",
    "addr:street":"Rue Manurhin",
    "iso:country":"FR",
    "sg:address":"17, Rue Manurhin, 68120 Richwiller",
    "sg:city":"Richwiller",
    "sg:orig_category":"Unclassifiable Establishments",
    "sg:phone":"+33 3 89 50 55 10",
    "sg:postcode":"68120",
    "sg:province":"Alsace",
    "wof:name":"V.h.m. S.a.",
    "wof:placetype":"venue"
},
  "geometry": {"coordinates":[7.299179,47.786987],"type":"Point"}
}