{
  "type": "Feature",
  "properties": {
    "addr:full":"2, Place Viala, 34060 Montpellier Aquitaine",
    "addr:housenumber":"2",
    "addr:postcode":"34060",
    "addr:street":"Place Viala",
    "iso:country":"FR",
    "sg:address":"2, Place Viala, 34060 Montpellier",
    "sg:orig_category":"Unclassifiable Establishments",
    "sg:phone":"+33 4 99 61 22 00",
    "sg:province":"Aquitaine",
    "wof:name":"I.n.r.a. - Institut National De Recherches Agronomiques",
    "wof:placetype":"venue"
},
  "geometry": {"coordinates":[3.890701,43.617615],"type":"Point"}
}