{
  "type": "Feature",
  "properties": {
    "iso:country":"FR",
    "sg:address":"Av Martyres De La R\u00e9sistance 47200 Marmande",
    "sg:city":"Marmande",
    "sg:classifiers":[
        {
            "category":"Farming",
            "subcategory":"Livestock Farm",
            "type":"Manufacturing & Wholesale Goods"
        }
    ],
    "sg:phone":"+33 5 53 64 25 74",
    "sg:postcode":"47200",
    "sg:province":"Aquitaine",
    "sg:tags":[
        "agriculture"
    ],
    "wof:name":"Areil Fruitaprim",
    "wof:placetype":"venue"
},
  "geometry": {"coordinates":[0.15862,44.51553],"type":"Point"}
}