{
  "type": "Feature",
  "properties": {
    "addr:full":"Le Champ Lain 21190 Tailly Tailly Bourgogne 21190",
    "addr:postcode":"21190;21190",
    "addr:street":"Champ Lain",
    "iso:country":"FR",
    "sg:address":"Le Champ Lain 21190 Tailly",
    "sg:city":"Tailly",
    "sg:orig_category":"Unclassifiable Establishments",
    "sg:phone":"+33 3 80 26 89 99",
    "sg:postcode":"21190",
    "sg:province":"Bourgogne",
    "wof:name":"Pma M\u00e9cano-soudure S.a.r.l.",
    "wof:placetype":"venue"
},
  "geometry": {"coordinates":[4.775,46.976566],"type":"Point"}
}