{
  "type": "Feature",
  "properties": {
    "iso:country":"FR",
    "sg:address":"16/24, Rue Cabanis - 12 Villa de Lourcine, 75014 Paris",
    "sg:orig_category":"Unclassifiable Establishments",
    "sg:phone":"+33 1 53 62 75 75",
    "sg:province":"Ile de France",
    "wof:name":"O.r.t. S.a.",
    "wof:placetype":"venue"
},
  "geometry": {"coordinates":[2.32515,48.832199],"type":"Point"}
}