{
  "type": "Feature",
  "properties": {
    "addr:full":"225 rue Saint-Pierre 13012 Marseille Saint-Pierre Alsace 67140",
    "addr:housenumber":"225",
    "addr:postcode":"13012;67140",
    "addr:street":"Rue Saint-Pierre",
    "iso:country":"FR",
    "sg:address":"225 rue Saint-Pierre 13012 Marseille",
    "sg:city":"Saint-Pierre",
    "sg:classifiers":[
        {
            "category":"Shopping",
            "subcategory":"Jewelry",
            "type":"Retail Goods"
        }
    ],
    "sg:phone":"+33 4 91 18 40 91",
    "sg:postcode":"67140",
    "sg:province":"Alsace",
    "sg:tags":[
        "watch"
    ],
    "wof:name":"Etablissement C. Beuchat S.a.",
    "wof:placetype":"venue"
},
  "geometry": {"coordinates":[5.414999,43.29184],"type":"Point"}
}