{
  "type": "Feature",
  "properties": {
    "iso:country":"FR",
    "sg:address":"5, Impasse Rameau, 44220 Cou\u00ebron",
    "sg:orig_category":"Unclassifiable Establishments",
    "sg:phone":"+33 2 40 85 45 00",
    "sg:province":"Pays de Loire",
    "wof:name":"C.b.i. S.a.r.l. - Commerce Et Business International",
    "wof:placetype":"venue"
},
  "geometry": {"coordinates":[-1.727234,47.210861],"type":"Point"}
}