{
  "type": "Feature",
  "properties": {
    "addr:full":"13 Rue Abbe Salvetti 06000 Nice Picardie",
    "addr:housenumber":"13",
    "addr:postcode":"06000",
    "addr:street":"Rue Abbe Salvetti",
    "iso:country":"FR",
    "sg:address":"13 Rue Abbe Salvetti 06000 Nice",
    "sg:classifiers":[
        {
            "category":"Food & Beverages",
            "subcategory":"Groceries & Convenience Stores",
            "type":"Retail Goods"
        }
    ],
    "sg:phone":"+33 4 93 89 53 23",
    "sg:province":"Picardie",
    "sg:tags":[
        "product",
        "related"
    ],
    "wof:name":"La Raiola",
    "wof:placetype":"venue"
},
  "geometry": {"coordinates":[7.292932,43.703587],"type":"Point"}
}