{
  "type": "Feature",
  "properties": {
    "addr:full":"12 Rue Des Chaufourniers 75019 Paris Ile de France",
    "addr:housenumber":"12",
    "addr:postcode":"75019",
    "addr:street":"Rue Des Chaufourniers",
    "iso:country":"FR",
    "sg:address":"12 Rue Des Chaufourniers 75019 Paris",
    "sg:orig_category":"Plastics Printing Printing and Publishing Rubber and Plastics",
    "sg:phone":"+33 1 42 02 03 95",
    "sg:province":"Ile de France",
    "wof:name":"Ste De Marquage Industriel Sarl",
    "wof:placetype":"venue"
},
  "geometry": {"coordinates":[2.372449,48.878353],"type":"Point"}
}