{
  "type": "Feature",
  "properties": {
    "iso:country":"FR",
    "sg:address":"63 avenue de Villiers; 75017 Paris",
    "sg:classifiers":[
        {
            "category":"Industrial Area",
            "type":"Public Place"
        }
    ],
    "sg:phone":"+33 1 56 98 29 29",
    "sg:province":"Ile de France",
    "sg:tags":[
        "large",
        "private"
    ],
    "wof:name":"Synerdeal Ltd.",
    "wof:placetype":"venue"
},
  "geometry": {"coordinates":[2.305436,48.88353],"type":"Point"}
}