{
  "type": "Feature",
  "properties": {
    "iso:country":"FR",
    "sg:address":"19, Rue du Mal Oudinot, 54000 Nancy",
    "sg:orig_category":"Unclassifiable Establishments",
    "sg:phone":"+33 3 83 51 78 76",
    "sg:province":"Lorraine",
    "wof:name":"Bousch Alain S.a.r.l.",
    "wof:placetype":"venue"
},
  "geometry": {"coordinates":[6.185814,48.676926],"type":"Point"}
}