{
  "type": "Feature",
  "properties": {
    "iso:country":"FR",
    "sg:address":"672 Av Du 15\u00e8me Corps 83200 Toulon",
    "sg:classifiers":[
        {
            "category":"Shopping",
            "subcategory":"Hobbies, Toys, & Games",
            "type":"Retail Goods"
        }
    ],
    "sg:phone":"+33 4 94 24 14 10",
    "sg:province":"Rhone-Alpes",
    "sg:tags":[
        "product",
        "miscellaneous",
        "entertainment"
    ],
    "wof:name":"Comptoir Varois De L'automatique Sa",
    "wof:placetype":"venue"
},
  "geometry": {"coordinates":[5.914734,43.128471],"type":"Point"}
}