{
  "type": "Feature",
  "properties": {
    "iso:country":"FR",
    "sg:address":"72 Rte Grotteaux 41250 Mont Pr\u00e8s Chambord",
    "sg:city":"Chambord",
    "sg:classifiers":[
        {
            "category":"Home & Garden",
            "subcategory":"Furniture",
            "type":"Retail Goods"
        }
    ],
    "sg:phone":"+33 2 54 70 70 30",
    "sg:postcode":"41250",
    "sg:province":"Centre",
    "sg:tags":[
        "wood"
    ],
    "wof:name":"Blanvillain Sa",
    "wof:placetype":"venue"
},
  "geometry": {"coordinates":[1.450145,47.564636],"type":"Point"}
}