{
  "type": "Feature",
  "properties": {
    "addr:full":"7, Rue du Canton, 88200 Remiremont Lorraine",
    "addr:housenumber":"7",
    "addr:postcode":"88200",
    "addr:street":"Rue Du Canton",
    "iso:country":"FR",
    "sg:address":"7, Rue du Canton, 88200 Remiremont",
    "sg:orig_category":"Unclassifiable Establishments",
    "sg:phone":"+33 3 29 23 19 20",
    "sg:province":"Lorraine",
    "wof:name":"S.v.c. Production Vid\u00e9o S.a.r.l.",
    "wof:placetype":"venue"
},
  "geometry": {"coordinates":[6.588308,48.018974],"type":"Point"}
}