{
  "type": "Feature",
  "properties": {
    "addr:full":"2 A Avenue De Northwich Dole Franche Comt\u00e9 39100",
    "addr:housenumber":"2 a",
    "addr:postcode":"39100",
    "addr:street":"Avenue De Northwich;Franche Comte\u0301",
    "iso:country":"FR",
    "sg:address":"2 A Avenue De Northwich",
    "sg:city":"Dole",
    "sg:classifiers":[
        {
            "category":"Banks & Credit Unions",
            "subcategory":"Financial Services",
            "type":"Services"
        }
    ],
    "sg:phone":"+33 3 84 82 04 87",
    "sg:postcode":"39100",
    "sg:province":"Franche Comt\u00e9",
    "sg:tags":[
        "banking",
        "finance",
        "insurance"
    ],
    "wof:name":"Societe Fiduciaire Nationale D'expertise Comptable Fidexpert (fid)",
    "wof:placetype":"venue"
},
  "geometry": {"coordinates":[5.497039,47.095181],"type":"Point"}
}