{
  "type": "Feature",
  "properties": {
    "iso:country":"FR",
    "sg:address":"ZA le Poteau 47800 Roumagne",
    "sg:city":"Roumagne",
    "sg:classifiers":[
        {
            "category":"Professional",
            "subcategory":"Engineering",
            "type":"Services"
        }
    ],
    "sg:phone":"+33 5 53 93 30 10",
    "sg:postcode":"47800",
    "sg:province":"Aquitaine",
    "sg:tags":[
        "machine",
        "-",
        "mechanical"
    ],
    "wof:name":"A.d.i.t.e.c",
    "wof:placetype":"venue"
},
  "geometry": {"coordinates":[0.33744,44.619091],"type":"Point"}
}