{
  "type": "Feature",
  "properties": {
    "addr:full":"B.P. 7, 39260 Moirans en Montagne^^ZI Sud, 39260 Moirans en Montagne Franche Comt\u00e9 39260",
    "addr:housenumber":"7",
    "addr:postcode":"39260;39260;39260",
    "addr:street":"B.P.;Sud;Franche Comte\u0301",
    "iso:country":"FR",
    "sg:address":"B.P. 7, 39260 Moirans en Montagne^^ZI Sud, 39260 Moirans en Montagne",
    "sg:orig_category":"Non-Classified Establishments",
    "sg:phone":"+33 3 84 42 36 81",
    "sg:postcode":"39260",
    "sg:province":"Franche Comt\u00e9",
    "wof:name":"Bourbon Communication S.a.",
    "wof:placetype":"venue"
},
  "geometry": {"coordinates":[5.7253,46.42524],"type":"Point"}
}