{
  "type": "Feature",
  "properties": {
    "addr:full":"P\u00f4le d'Activit\u00e9 d'Aix les Milles Aix en Provence Provence-Alpes-C\u00f4te d'Azur 13790",
    "addr:postcode":"13790",
    "iso:country":"FR",
    "sg:address":"P\u00f4le d'Activit\u00e9 d'Aix les Milles",
    "sg:city":"Aix en Provence",
    "sg:orig_category":"Unclassifiable Establishments",
    "sg:phone":"+33 4 42 60 46 00",
    "sg:postcode":"13790",
    "sg:province":"Provence-Alpes-C\u00f4te d'Azur",
    "wof:name":"Bertin Technologies S.a.",
    "wof:placetype":"venue"
},
  "geometry": {"coordinates":[5.44625,43.526409],"type":"Point"}
}