{
  "type": "Feature",
  "properties": {
    "addr:full":"3, Av. Ozane - ZI Limay Porcheville, 78440 Gargenville Ile de France 78440",
    "addr:postcode":"78440;78440",
    "addr:street":"Av. Ozane Zi;Ile De France",
    "iso:country":"FR",
    "sg:address":"3, Av. Ozane - ZI Limay Porcheville, 78440 Gargenville",
    "sg:orig_category":"Non-Classified Establishments",
    "sg:phone":"+33 1 30 98 26 26",
    "sg:postcode":"78440",
    "sg:province":"Ile de France",
    "wof:name":"Aga S.a.",
    "wof:placetype":"venue"
},
  "geometry": {"coordinates":[1.81015,48.989475],"type":"Point"}
}