{
  "type": "Feature",
  "properties": {
    "iso:country":"FR",
    "sg:address":"3/5, Rue de la Breuchilli\u00e8re, 21000 Dijon",
    "sg:city":"Dijon",
    "sg:orig_category":"Unclassifiable Establishments",
    "sg:phone":"+33 3 80 72 68 82",
    "sg:postcode":"21000",
    "sg:province":"Bourgogne",
    "wof:name":"5 A.t.a.",
    "wof:placetype":"venue"
},
  "geometry": {"coordinates":[5.074279,47.34547],"type":"Point"}
}