{
  "type": "Feature",
  "properties": {
    "iso:country":"FR",
    "sg:address":"500, Rue L\u00e9on Blum, 34965 Montpellier C\u00e9dex 2",
    "sg:orig_category":"Non-Classified Establishments",
    "sg:phone":"+33 4 67 15 39 15",
    "sg:province":"Aquitaine",
    "wof:name":"R.c.a. S.a.r.l. - Rivi\u00e8re Consult Associ\u00e9s",
    "wof:placetype":"venue"
},
  "geometry": {"coordinates":[3.87927,43.608528],"type":"Point"}
}