{
  "type": "Feature",
  "properties": {
    "iso:country":"FR",
    "sg:address":"Route de Thil 01704 MIRIBEL CEDEX",
    "sg:city":"Miribel",
    "sg:classifiers":[
        {
            "category":"Utilities",
            "subcategory":"Cable",
            "type":"Services"
        }
    ],
    "sg:phone":"+33 4 78 55 15 72",
    "sg:postcode":"01700",
    "sg:province":"Rhone-Alpes",
    "sg:tags":[
        "lead-covered"
    ],
    "wof:name":"C\u00e2blerie E. Charbonnet Sa",
    "wof:placetype":"venue"
},
  "geometry": {"coordinates":[4.953455,45.824306],"type":"Point"}
}