{
  "type": "Feature",
  "properties": {
    "iso:country":"FR",
    "sg:address":"13 Avenue De La Republique 51190 Le Mesnil Sur Oger",
    "sg:classifiers":[
        {
            "category":"Food Court",
            "type":"Food & Drink"
        }
    ],
    "sg:phone":"+33 3 26 57 52 14",
    "sg:postcode":"51190",
    "sg:province":"Champagne",
    "sg:tags":[
        "product",
        "related"
    ],
    "wof:name":"Sa Champagne Pertois Moriset",
    "wof:placetype":"venue"
},
  "geometry": {"coordinates":[4.026507,48.948566],"type":"Point"}
}