{
  "type": "Feature",
  "properties": {
    "addr:full":"19, Av. Jean L\u00e9gers, 78150 Le Chesnay Ile de France 78150",
    "addr:postcode":"78150;78150",
    "addr:street":"19 Av. Jean Le\u0301Gers",
    "iso:country":"FR",
    "sg:address":"19, Av. Jean L\u00e9gers, 78150 Le Chesnay",
    "sg:orig_category":"Non-Classified Establishments",
    "sg:phone":"+33 1 39 43 35 43",
    "sg:postcode":"78150",
    "sg:province":"Ile de France",
    "wof:name":"Cayroll Ingetex S.a.r.l.",
    "wof:placetype":"venue"
},
  "geometry": {"coordinates":[2.127977,48.833305],"type":"Point"}
}