{
  "type": "Feature",
  "properties": {
    "addr:full":"19 blvd du Roi Jerome; Ajaccio; 20000 Corse 20000",
    "addr:postcode":"20000;20000",
    "addr:street":"19 Blvd Du Roi",
    "iso:country":"FR",
    "sg:address":"19 blvd du Roi Jerome; Ajaccio; 20000",
    "sg:classifiers":[
        {
            "category":"Banks & Credit Unions",
            "subcategory":"Bank",
            "type":"Services"
        }
    ],
    "sg:phone":"+33 3395210013",
    "sg:postcode":"20000",
    "sg:province":"Corse",
    "wof:name":"Banque Worms",
    "wof:placetype":"venue"
},
  "geometry": {"coordinates":[8.739228,41.921864],"type":"Point"}
}