{
  "type": "Feature",
  "properties": {
    "addr:full":"4, Rue Maurice Caunes - ZAC Montblanc, 31200 Toulouse Midi Pyr\u00e9n\u00e9es",
    "addr:housenumber":"4",
    "addr:postcode":"31200",
    "addr:street":"Rue Maurice Caunes Zac Montblanc",
    "iso:country":"FR",
    "sg:address":"4, Rue Maurice Caunes - ZAC Montblanc, 31200 Toulouse",
    "sg:orig_category":"Non-Classified Establishments",
    "sg:phone":"+33 5 61 26 29 16",
    "sg:province":"Midi Pyr\u00e9n\u00e9es",
    "wof:name":"S.t.p.a. S.a. - Soci\u00e9t\u00e9 Toulouse Peintures Accessoires",
    "wof:placetype":"venue"
},
  "geometry": {"coordinates":[1.471523,43.640053],"type":"Point"}
}