{
  "type": "Feature",
  "properties": {
    "addr:full":"Rue Gallil\u00e9e BP 640 29552 Quimper Cedex 9 Aquitaine",
    "addr:housenumber":"640",
    "addr:postcode":"29552",
    "addr:street":"Rue Gallile\u0301E Bp",
    "iso:country":"FR",
    "sg:address":"Rue Gallil\u00e9e BP 640 29552 Quimper Cedex 9",
    "sg:classifiers":[
        {
            "category":"Wholesale",
            "subcategory":"Meat",
            "type":"Manufacturing & Wholesale Goods"
        }
    ],
    "sg:phone":"+33 2 98 66 63 90",
    "sg:province":"Aquitaine",
    "sg:tags":[
        "food",
        "cooked",
        "product",
        "related"
    ],
    "wof:name":"Jean D'erguet Sa",
    "wof:placetype":"venue"
},
  "geometry": {"coordinates":[-4.09986,47.99593],"type":"Point"}
}