{
  "type": "Feature",
  "properties": {
    "addr:full":"86, Rue David d'Angers, 49130 Les Ponts de C\u00e9 Pays de Loire",
    "addr:housenumber":"86",
    "addr:postcode":"49130",
    "addr:street":"Rue David D'Angers;Ponts De Ce\u0301",
    "iso:country":"FR",
    "sg:address":"86, Rue David d'Angers, 49130 Les Ponts de C\u00e9",
    "sg:orig_category":"Unclassifiable Establishments",
    "sg:phone":"+33 2 41 44 89 89",
    "sg:province":"Pays de Loire",
    "wof:name":"Grangeray S.a.",
    "wof:placetype":"venue"
},
  "geometry": {"coordinates":[-0.530618,47.435043],"type":"Point"}
}