{
  "type": "Feature",
  "properties": {
    "addr:full":"2 Av Du G\u00e9n\u00e9ral Malleret Joinville 94110 Arcueil Ile de France 94110",
    "addr:postcode":"94110;ile;94110",
    "addr:street":"Av Du Ge\u0301Ne\u0301Ral Malleret Joinville;France",
    "iso:country":"FR",
    "sg:address":"2 Av Du G\u00e9n\u00e9ral Malleret Joinville 94110 Arcueil",
    "sg:classifiers":[
        {
            "category":"Professional",
            "subcategory":"Business Services",
            "type":"Services"
        }
    ],
    "sg:phone":"+33 1 47 40 70 00",
    "sg:postcode":"94110",
    "sg:province":"Ile de France",
    "sg:tags":[
        "body",
        "advice"
    ],
    "wof:name":"Institut National De Recherche Sur Les Transports Et Leur Securite",
    "wof:placetype":"venue"
},
  "geometry": {"coordinates":[2.343491,48.804302],"type":"Point"}
}