{
  "type": "Feature",
  "properties": {
    "addr:full":"Bd Des Bretonni\u00e8res Zi 49181 St Barth\u00e9l\u00e9my D'Anjou Rhone-Alpes",
    "addr:postcode":"49181",
    "addr:street":"Bd Des Bretonnie\u0300Res Zi;Rhone-Alpes",
    "iso:country":"FR",
    "sg:address":"Bd Des Bretonni\u00e8res Zi 49181 St Barth\u00e9l\u00e9my D'Anjou",
    "sg:classifiers":[
        {
            "category":"Shopping",
            "subcategory":"Crafts & Fabrics",
            "type":"Retail Goods"
        }
    ],
    "sg:phone":"+33 2 41 21 31 31",
    "sg:province":"Rhone-Alpes",
    "sg:tags":[
        "textile",
        "clothing"
    ],
    "wof:name":"Carpenter France",
    "wof:placetype":"venue"
},
  "geometry": {"coordinates":[-0.507701,47.477131],"type":"Point"}
}