{
  "type": "Feature",
  "properties": {
    "iso:country":"FR",
    "sg:address":"Les Tronquats 33480 Ste Helene",
    "sg:city":"Avensan",
    "sg:classifiers":[
        {
            "category":"Farming",
            "subcategory":"Farm & Veterinary Services",
            "type":"Manufacturing & Wholesale Goods"
        }
    ],
    "sg:phone":"+33 5 56 58 57 12",
    "sg:postcode":"33480",
    "sg:province":"Aquitaine",
    "sg:tags":[
        "advice",
        "agriculture",
        "livestock",
        "business"
    ],
    "wof:name":"Etablissements Seguin Sa",
    "wof:placetype":"venue"
},
  "geometry": {"coordinates":[-0.916289,44.958344],"type":"Point"}
}