{
  "type": "Feature",
  "properties": {
    "addr:full":"2, Vladimir Jankelevitch, 77184 Emerainville Ile de France",
    "addr:housenumber":"2",
    "addr:postcode":"77184",
    "addr:street":"Vladimir Jankelevitch;Ile De France",
    "iso:country":"FR",
    "sg:address":"2, Vladimir Jankelevitch, 77184 Emerainville",
    "sg:orig_category":"Unclassifiable Establishments",
    "sg:phone":"+33 1 64 73 10 40",
    "sg:province":"Ile de France",
    "wof:name":"Claircom S.a.",
    "wof:placetype":"venue"
},
  "geometry": {"coordinates":[2.587715,48.82766],"type":"Point"}
}