{
  "type": "Feature",
  "properties": {
    "iso:country":"FR",
    "sg:address":"La Chaise 47450 Colayrac St Cirq",
    "sg:city":"Colayrac-Saint-Cirq",
    "sg:classifiers":[
        {
            "category":"Manufacturing",
            "subcategory":"Metals",
            "type":"Manufacturing & Wholesale Goods"
        }
    ],
    "sg:phone":"+33 5 53 87 55 45",
    "sg:postcode":"47450",
    "sg:province":"Aquitaine",
    "sg:tags":[
        "-",
        "machine",
        "equipment",
        "engineering",
        "machinery",
        "mechanical"
    ],
    "wof:name":"Garrigues Sa",
    "wof:placetype":"venue"
},
  "geometry": {"coordinates":[0.571873,44.224022],"type":"Point"}
}