{
  "type": "Feature",
  "properties": {
    "addr:full":"La Palud Rudolf Diesel 83600 Fr\u00e9jus Rhone-Alpes",
    "addr:postcode":"83600",
    "addr:street":"La;Diesel",
    "iso:country":"FR",
    "sg:address":"La Palud",
    "sg:city":"Rudolf Diesel 83600 Fr\u00e9jus",
    "sg:classifiers":[
        {
            "category":"Professional",
            "subcategory":"Advertising",
            "type":"Services"
        }
    ],
    "sg:phone":"+33 4 94 53 78 63",
    "sg:province":"Rhone-Alpes",
    "sg:tags":[
        "marketing",
        "medium",
        "communication"
    ],
    "wof:name":"Adrexo",
    "wof:placetype":"venue"
},
  "geometry": {"coordinates":[6.718305,43.442287],"type":"Point"}
}