{
  "type": "Feature",
  "properties": {
    "addr:full":"9/13, Rue Traversi\u00e8re, 94513 Rungis C\u00e9dex \u00cele-de-France",
    "addr:housenumber":"9 / 13",
    "addr:postcode":"94513",
    "addr:street":"Rue Traversie\u0300Re;Ce\u0301Dex",
    "iso:country":"FR",
    "sg:address":"9/13, Rue Traversi\u00e8re, 94513 Rungis C\u00e9dex",
    "sg:orig_category":"Non-Classified Establishments",
    "sg:phone":"+33 1 41 28 30 00",
    "sg:province":"\u00cele-de-France",
    "wof:name":"Osiatis France S.a.",
    "wof:placetype":"venue"
},
  "geometry": {"coordinates":[2.35232,48.746799],"type":"Point"}
}