{
  "type": "Feature",
  "properties": {
    "addr:full":"122, Rue de la Zone Industrielle, 40110 Morcenx Morcenx Aquitaine 40110",
    "addr:housenumber":"122",
    "addr:postcode":"40110;40110",
    "addr:street":"Rue De La Zone Industrielle",
    "iso:country":"FR",
    "sg:address":"122, Rue de la Zone Industrielle, 40110 Morcenx",
    "sg:city":"Morcenx",
    "sg:orig_category":"Non-Classified Establishments",
    "sg:phone":"+33 5 58 04 17 09",
    "sg:postcode":"40110",
    "sg:province":"Aquitaine",
    "wof:name":"Durand B\u00e9ton S.a.r.l.",
    "wof:placetype":"venue"
},
  "geometry": {"coordinates":[-0.761829,43.957363],"type":"Point"}
}