{
  "type": "Feature",
  "properties": {
    "addr:full":"Bareyrou 24750 Boulazac Boulazac Aquitaine 24750",
    "addr:postcode":"24750;24750",
    "addr:street":"Bareyrou",
    "iso:country":"FR",
    "sg:address":"Bareyrou 24750 Boulazac",
    "sg:city":"Boulazac",
    "sg:classifiers":[
        {
            "category":"Professional",
            "subcategory":"Advertising",
            "type":"Services"
        }
    ],
    "sg:phone":"+33 5 53 03 93 41",
    "sg:postcode":"24750",
    "sg:province":"Aquitaine",
    "sg:tags":[
        "information",
        "medium",
        "communication"
    ],
    "wof:name":"Avenir France",
    "wof:placetype":"venue"
},
  "geometry": {"coordinates":[0.784734,45.185307],"type":"Point"}
}