{
  "type": "Feature",
  "properties": {
    "addr:full":"13 Rte Industrielle De La Hardt 67120 Molsheim Molsheim Alsace 67120",
    "addr:housenumber":"13",
    "addr:postcode":"67120;67120",
    "addr:street":"Rte Industrielle De La Hardt",
    "iso:country":"FR",
    "sg:address":"13 Rte Industrielle De La Hardt 67120 Molsheim",
    "sg:city":"Molsheim",
    "sg:classifiers":[
        {
            "category":"Building & Trades",
            "subcategory":"Construction",
            "type":"Services"
        }
    ],
    "sg:phone":"+33 3 88 47 99 19",
    "sg:postcode":"67120",
    "sg:province":"Alsace",
    "sg:tags":[
        "work",
        "public"
    ],
    "wof:name":"Eurovia Alsace Franche Comte",
    "wof:placetype":"venue"
},
  "geometry": {"coordinates":[7.510742,48.538307],"type":"Point"}
}