{
  "type": "Feature",
  "properties": {
    "addr:full":"route Nationale 59270 Fletre Nord Pas-de-Calais 59270",
    "addr:postcode":"59270;59270",
    "addr:street":"Route Nationale;Fletre Nord",
    "iso:country":"FR",
    "sg:address":"route Nationale 59270 Fletre",
    "sg:classifiers":[
        {
            "category":"Manufacturing",
            "subcategory":"Metals",
            "type":"Manufacturing & Wholesale Goods"
        }
    ],
    "sg:phone":"+33 3 28 40 13 51",
    "sg:postcode":"59270",
    "sg:province":"Nord Pas-de-Calais",
    "sg:tags":[
        "alloy",
        "construction",
        "lightweight"
    ],
    "wof:name":"Etablissement Benault Sa",
    "wof:placetype":"venue"
},
  "geometry": {"coordinates":[2.646433,50.75341],"type":"Point"}
}