{
  "type": "Feature",
  "properties": {
    "iso:country":"FR",
    "sg:address":"50 Av Gal De Gaulle 66170 Nefiach",
    "sg:classifiers":[
        {
            "category":"Farming",
            "subcategory":"Crops",
            "type":"Manufacturing & Wholesale Goods"
        }
    ],
    "sg:phone":"+33 4 68 57 18 79",
    "sg:postcode":"66170",
    "sg:province":"Languedoc-Roussillon",
    "sg:tags":[
        "vegetable",
        "fruit",
        "agriculture",
        "livestock"
    ],
    "wof:name":"Chassagnac",
    "wof:placetype":"venue"
},
  "geometry": {"coordinates":[2.6669,42.692856],"type":"Point"}
}