{
  "type": "Feature",
  "properties": {
    "iso:country":"FR",
    "sg:address":"ZI de Kerjean",
    "sg:city":"le Relecq Kerhuon",
    "sg:orig_category":"Non-Classified Establishments",
    "sg:phone":"+33 2 98 30 54 61",
    "sg:postcode":"29480",
    "sg:province":"Bretagne",
    "wof:name":"Electro Standard S.a.",
    "wof:placetype":"venue"
},
  "geometry": {"coordinates":[-4.398229,48.408016],"type":"Point"}
}