{
  "type": "Feature",
  "properties": {
    "iso:country":"FR",
    "sg:address":"Chef Lieu 74370 Villaz",
    "sg:orig_category":"Non-Classified Establishments",
    "sg:phone":"+33 4 50 22 45 83",
    "sg:postcode":"74370",
    "sg:province":"Rhone-Alpes",
    "wof:name":"Entreprise Peron S.a.r.l.",
    "wof:placetype":"venue"
},
  "geometry": {"coordinates":[6.109395,45.934166],"type":"Point"}
}