{
  "type": "Feature",
  "properties": {
    "iso:country":"FR",
    "sg:address":"27 Av Gay-Lussac 81300 Graulhet",
    "sg:classifiers":[
        {
            "category":"Manufacturing",
            "subcategory":"Leather Goods",
            "type":"Manufacturing & Wholesale Goods"
        }
    ],
    "sg:phone":"+33 5 63 34 79 26",
    "sg:postcode":"81300",
    "sg:province":"Midi Pyr\u00e9n\u00e9es",
    "sg:tags":[
        "shoe"
    ],
    "wof:name":"Jean Louis Four\u00c8s Sarl",
    "wof:placetype":"venue"
},
  "geometry": {"coordinates":[1.99129,43.772102],"type":"Point"}
}