{
  "type": "Feature",
  "properties": {
    "addr:full":"B.P. 35, 70102 Velet C\u00e9dex^^Rte Aubigney la Chapelle, 70100 Velet Franche Comt\u00e9",
    "addr:postcode":"70102;70100",
    "addr:street":"B.P. 35;Franche Comte\u0301",
    "iso:country":"FR",
    "sg:address":"B.P. 35, 70102 Velet C\u00e9dex^^Rte Aubigney la Chapelle, 70100 Velet",
    "sg:orig_category":"Non-Classified Establishments",
    "sg:phone":"+33 3 84 65 48 66",
    "sg:province":"Franche Comt\u00e9",
    "wof:name":"G.s.m. Secteur Bourgogne Franche Comt\u00e9 S.a.",
    "wof:placetype":"venue"
},
  "geometry": {"coordinates":[5.514565,47.369511],"type":"Point"}
}