{
  "type": "Feature",
  "properties": {
    "addr:full":"40, Rue Alfred Lef\u00e8vre, 14320 Saint Andr\u00e9 sur Orne Clinchamps-sur-Orne Basse Normandie 14320",
    "addr:housenumber":"40",
    "addr:postcode":"14320;14320",
    "addr:street":"Rue Alfred Lefe\u0300Vre;Andre\u0301;Clinchamps-Sur-Orne Basse",
    "iso:country":"FR",
    "sg:address":"40, Rue Alfred Lef\u00e8vre, 14320 Saint Andr\u00e9 sur Orne",
    "sg:city":"Clinchamps-sur-Orne",
    "sg:orig_category":"Non-Classified Establishments",
    "sg:phone":"+33 2 31 79 11 00",
    "sg:postcode":"14320",
    "sg:province":"Basse Normandie",
    "wof:name":"Bureau D'etudes Gehan E.u.r.l.",
    "wof:placetype":"venue"
},
  "geometry": {"coordinates":[-0.375011,49.121128],"type":"Point"}
}