{
  "type": "Feature",
  "properties": {
    "addr:full":"Rue des Bambous Brignon Languedoc-Roussillon 30190",
    "addr:postcode":"30190",
    "addr:street":"Rue Des Bambous",
    "iso:country":"FR",
    "sg:address":"Rue des Bambous",
    "sg:city":"Brignon",
    "sg:orig_category":"Non-Classified Establishments",
    "sg:phone":"+33 4 66 83 24 32",
    "sg:postcode":"30190",
    "sg:province":"Languedoc-Roussillon",
    "wof:name":"Brunel Et Compagnie S.a.r.l.",
    "wof:placetype":"venue"
},
  "geometry": {"coordinates":[4.216521,43.987659],"type":"Point"}
}