{
  "type": "Feature",
  "properties": {
    "iso:country":"FR",
    "sg:address":"Le Fonteneau 38440 Moidieu Detourbe",
    "sg:classifiers":[
        {
            "category":"Farming",
            "subcategory":"Farm & Veterinary Services",
            "type":"Manufacturing & Wholesale Goods"
        }
    ],
    "sg:phone":"+33 4 74 58 17 82",
    "sg:postcode":"38440",
    "sg:province":"Rhone-Alpes",
    "sg:tags":[
        "advice",
        "agriculture",
        "livestock",
        "business"
    ],
    "wof:name":"Etablissements Terry",
    "wof:placetype":"venue"
},
  "geometry": {"coordinates":[5.181732,45.457729],"type":"Point"}
}