{
  "type": "Feature",
  "properties": {
    "iso:country":"FR",
    "sg:address":"ZI du Bois Joly Sud",
    "sg:city":"Les Herbiers",
    "sg:orig_category":"Unclassifiable Establishments",
    "sg:phone":"+33 2 51 64 81 41",
    "sg:postcode":"85500",
    "sg:province":"Pays de Loire",
    "wof:name":"Vend\u00e9e Plastique S.a.",
    "wof:placetype":"venue"
},
  "geometry": {"coordinates":[-1.015364,46.871265],"type":"Point"}
}