{
  "type": "Feature",
  "properties": {
    "addr:full":"3 Rue Bouchet 69100 Villeurbanne Rhone-Alpes 69100",
    "addr:housenumber":"3",
    "addr:postcode":"69100;69100",
    "addr:street":"Rue Bouchet",
    "iso:country":"FR",
    "sg:address":"3 Rue Bouchet 69100 Villeurbanne",
    "sg:classifiers":[
        {
            "category":"Shopping",
            "subcategory":"Crafts & Fabrics",
            "type":"Retail Goods"
        }
    ],
    "sg:phone":"+33 4 72 35 97 36",
    "sg:postcode":"69100",
    "sg:province":"Rhone-Alpes",
    "sg:tags":[
        "textile",
        "clothing"
    ],
    "wof:name":"Style Abm",
    "wof:placetype":"venue"
},
  "geometry": {"coordinates":[4.889621,45.755821],"type":"Point"}
}