{
  "type": "Feature",
  "properties": {
    "addr:full":"21, Rte Nationale, 62580 Th\u00e9lus Nord Pas-de-Calais 62580",
    "addr:housenumber":"21",
    "addr:postcode":"62580;62580",
    "addr:street":"Rte Nationale",
    "iso:country":"FR",
    "sg:address":"21, Rte Nationale, 62580 Th\u00e9lus",
    "sg:orig_category":"Non-Classified Establishments",
    "sg:phone":"+33 3 21 55 42 30",
    "sg:postcode":"62580",
    "sg:province":"Nord Pas-de-Calais",
    "wof:name":"Cauwet Michel",
    "wof:placetype":"venue"
},
  "geometry": {"coordinates":[2.793675,50.36351],"type":"Point"}
}