{
  "type": "Feature",
  "properties": {
    "addr:full":"5, Bd de l'Oise - Immeuble le Rond Point, 95031 Cergy C\u00e9dex Ile de France",
    "addr:housenumber":"5;immeuble",
    "addr:postcode":"95031",
    "addr:street":"Bd De L'Oise;Rond Point",
    "iso:country":"FR",
    "sg:address":"5, Bd de l'Oise - Immeuble le Rond Point, 95031 Cergy C\u00e9dex",
    "sg:orig_category":"Non-Classified Establishments",
    "sg:phone":"+33 1 34 20 16 00",
    "sg:province":"Ile de France",
    "wof:name":"Civitas S.a.",
    "wof:placetype":"venue"
},
  "geometry": {"coordinates":[2.03861,49.052551],"type":"Point"}
}