{
  "type": "Feature",
  "properties": {
    "iso:country":"FR",
    "sg:address":"38/40, Rue Salvador Allende, 93800 Epinay sur Seine",
    "sg:orig_category":"Non-Classified Establishments",
    "sg:phone":"+33 1 49 71 54 54",
    "sg:province":"Ile de France",
    "wof:name":"La Francilienne De Services S.a.r.l.",
    "wof:placetype":"venue"
},
  "geometry": {"coordinates":[2.309507,48.956875],"type":"Point"}
}