{
  "type": "Feature",
  "properties": {
    "addr:full":"8 route de Soufflenheim 67660 BETSCHDORF Betschdorf Alsace 67660",
    "addr:housenumber":"8",
    "addr:postcode":"67660;67660",
    "addr:street":"Route De Soufflenheim",
    "iso:country":"FR",
    "sg:address":"8 route de Soufflenheim 67660 BETSCHDORF",
    "sg:city":"Betschdorf",
    "sg:classifiers":[
        {
            "category":"Shopping",
            "subcategory":"Discount & Variety Stores",
            "type":"Retail Goods"
        }
    ],
    "sg:phone":"+33 3 88 54 44 16",
    "sg:postcode":"67660",
    "sg:province":"Alsace",
    "sg:tags":[
        "type",
        "ceramics"
    ],
    "wof:name":"Paga Sarl",
    "wof:placetype":"venue"
},
  "geometry": {"coordinates":[7.92163,48.887009],"type":"Point"}
}