{
  "type": "Feature",
  "properties": {
    "addr:full":"R\u00e9sidence Pauline Bonaparte Ajaccio Corse 20000",
    "addr:postcode":"20000",
    "addr:street":"Corse",
    "iso:country":"FR",
    "sg:address":"R\u00e9sidence Pauline Bonaparte",
    "sg:city":"Ajaccio",
    "sg:orig_category":"Unclassifiable Establishments",
    "sg:phone":"+33 4 95 22 07 64",
    "sg:postcode":"20000",
    "sg:province":"Corse",
    "wof:name":"E.g.a. S.a.r.l -electricit\u00e9 G\u00e9n\u00e9rale D'ajaccio",
    "wof:placetype":"venue"
},
  "geometry": {"coordinates":[8.73839,41.918453],"type":"Point"}
}