{
  "type": "Feature",
  "properties": {
    "addr:full":"35, Av. de Saxe, 69006 Lyon Rhone-Alpes 69006",
    "addr:postcode":"69006;69006",
    "addr:street":"35 Av. De Saxe",
    "iso:country":"FR",
    "sg:address":"35, Av. de Saxe, 69006 Lyon",
    "sg:orig_category":"Unclassifiable Establishments",
    "sg:phone":"+33 4 78 52 51 01",
    "sg:postcode":"69006",
    "sg:province":"Rhone-Alpes",
    "wof:name":"Fran\u00e7ois S.a.r.l.",
    "wof:placetype":"venue"
},
  "geometry": {"coordinates":[4.849785,45.769245],"type":"Point"}
}