{
  "type": "Feature",
  "properties": {
    "addr:full":"La Morandi\u00e8re 35220 Saint Jean sur Vilaine Ch\u00e2teaubourg Bretagne 35220",
    "addr:postcode":"35220;35220",
    "iso:country":"FR",
    "sg:address":"La Morandi\u00e8re 35220 Saint Jean sur Vilaine",
    "sg:city":"Ch\u00e2teaubourg",
    "sg:orig_category":"Unclassifiable Establishments",
    "sg:phone":"+33 2 99 00 83 83",
    "sg:postcode":"35220",
    "sg:province":"Bretagne",
    "wof:name":"Socah Division Pneumatiques S.a.",
    "wof:placetype":"venue"
},
  "geometry": {"coordinates":[-1.34994,48.120049],"type":"Point"}
}