{
  "type": "Feature",
  "properties": {
    "iso:country":"FR",
    "sg:address":"RN 147 - Les Petites Buff\u00e9teries",
    "sg:city":"Saint Barth\u00e9l\u00e9my d'Anjou",
    "sg:orig_category":"Unclassifiable Establishments",
    "sg:phone":"+33 2 41 18 85 85",
    "sg:postcode":"49124",
    "sg:province":"Pays de Loire",
    "wof:name":"Provost S.a.",
    "wof:placetype":"venue"
},
  "geometry": {"coordinates":[-1.334822,47.273693],"type":"Point"}
}