{
  "type": "Feature",
  "properties": {
    "addr:full":"4 B Rue De L Eglise 28150 Villeneuve St Nicolas Allonnes Centre 28150",
    "addr:housenumber":"4 b",
    "addr:postcode":"28150;28150",
    "addr:street":"Rue De L Eglise;St Nicolas Allonnes",
    "iso:country":"FR",
    "sg:address":"4 B Rue De L Eglise 28150 Villeneuve St Nicolas",
    "sg:city":"Allonnes",
    "sg:classifiers":[
        {
            "category":"Manufacturing",
            "subcategory":"Building Materials",
            "type":"Manufacturing & Wholesale Goods"
        }
    ],
    "sg:phone":"+33 2 37 99 16 11",
    "sg:postcode":"28150",
    "sg:province":"Centre",
    "sg:tags":[
        "glass",
        "ceramic"
    ],
    "wof:name":"Art'stone",
    "wof:placetype":"venue"
},
  "geometry": {"coordinates":[1.565594,48.287403],"type":"Point"}
}