{
  "type": "Feature",
  "properties": {
    "addr:full":"14, Bd Montmartre, 75009 Paris Ile de France",
    "addr:housenumber":"14",
    "addr:postcode":"75009",
    "addr:street":"Bd Montmartre",
    "iso:country":"FR",
    "sg:address":"14, Bd Montmartre, 75009 Paris",
    "sg:orig_category":"Non-Classified Establishments",
    "sg:phone":"+33 1 53 34 15 35",
    "sg:province":"Ile de France",
    "wof:name":"Kaleido S.a.r.l.",
    "wof:placetype":"venue"
},
  "geometry": {"coordinates":[2.341321,48.871922],"type":"Point"}
}