{
  "type": "Feature",
  "properties": {
    "addr:full":"B.P. Cidex 118, 33083 Bordeaux C\u00e9dex^^Av. du Docteur Schinazy, 33300 Bordeaux Bordeaux Aquitaine 33300",
    "addr:housenumber":"118",
    "addr:postcode":"33083;33300;33300",
    "iso:country":"FR",
    "sg:address":"B.P. Cidex 118, 33083 Bordeaux C\u00e9dex^^Av. du Docteur Schinazy, 33300 Bordeaux",
    "sg:city":"Bordeaux",
    "sg:orig_category":"Non-Classified Establishments",
    "sg:phone":"+33 5 56 43 54 00",
    "sg:postcode":"33300",
    "sg:province":"Aquitaine",
    "wof:name":"E.i. Aquitaine Nord Travaux S.n.c.",
    "wof:placetype":"venue"
},
  "geometry": {"coordinates":[-0.56244,44.87672],"type":"Point"}
}