{
  "type": "Feature",
  "properties": {
    "iso:country":"FR",
    "sg:address":"Toul Carosse Zone Artisanale 56400 Auray",
    "sg:city":"Auray",
    "sg:classifiers":[
        {
            "category":"Manufacturing",
            "subcategory":"Glass & Minerals",
            "type":"Manufacturing & Wholesale Goods"
        }
    ],
    "sg:phone":"+33 2 97 56 51 26",
    "sg:postcode":"56400",
    "sg:province":"Bretagne",
    "sg:tags":[
        "building",
        "material"
    ],
    "wof:name":"Miroiteries Services",
    "wof:placetype":"venue"
},
  "geometry": {"coordinates":[-2.949126,47.63744],"type":"Point"}
}