{
  "type": "Feature",
  "properties": {
    "iso:country":"FR",
    "sg:address":"14, Rue de la fonderie, 45000 Orl\u00e9ans C\u00e9dex 2",
    "sg:city":"Orl\u00e9ans",
    "sg:orig_category":"Non-Classified Establishments",
    "sg:phone":"+33 2 38 56 86 86",
    "sg:postcode":"45000",
    "sg:province":"Centre",
    "wof:name":"S.e.e.e. S.a. - Soci\u00e9t\u00e9 D'etude Entreprise Electrique",
    "wof:placetype":"venue"
},
  "geometry": {"coordinates":[1.919338,47.868282],"type":"Point"}
}