{
  "type": "Feature",
  "properties": {
    "addr:full":"Rue Paul Vaillant Couturier Thiant Nord Pas-de-Calais 59224",
    "addr:postcode":"59224",
    "addr:street":"Rue Paul Vaillant Couturier Thiant Nord",
    "iso:country":"FR",
    "sg:address":"Rue Paul Vaillant Couturier",
    "sg:city":"Thiant",
    "sg:orig_category":"Unclassifiable Establishments",
    "sg:phone":"+33 3 27 19 34 00",
    "sg:postcode":"59224",
    "sg:province":"Nord Pas-de-Calais",
    "wof:name":"Eternit S.a.",
    "wof:placetype":"venue"
},
  "geometry": {"coordinates":[3.44633,50.309849],"type":"Point"}
}