{
  "type": "Feature",
  "properties": {
    "addr:full":"6 parc Ariane 78280 Guyancourt Ile de France",
    "addr:housenumber":"6",
    "addr:postcode":"78280;ile",
    "addr:street":"Parc Ariane",
    "iso:country":"FR",
    "sg:address":"6 parc Ariane 78280 Guyancourt",
    "sg:orig_category":"Power Supply Sub-Assemblies And Modules",
    "sg:phone":"+33 1 34 52 18 30",
    "sg:province":"Ile de France",
    "wof:name":"Vicor France",
    "wof:placetype":"venue"
},
  "geometry": {"coordinates":[2.059555,48.78788],"type":"Point"}
}