{
  "type": "Feature",
  "properties": {
    "addr:full":"Rue Sadi Carnot Haubourdin Nord Pas-de-Calais 59320",
    "addr:postcode":"59320",
    "addr:street":"Rue Sadi Carnot",
    "iso:country":"FR",
    "sg:address":"Rue Sadi Carnot",
    "sg:city":"Haubourdin",
    "sg:orig_category":"Unclassifiable Establishments",
    "sg:phone":"+33 3 20 08 01 50",
    "sg:postcode":"59320",
    "sg:province":"Nord Pas-de-Calais",
    "wof:name":"Offset Feuilles Du Nord S.a.",
    "wof:placetype":"venue"
},
  "geometry": {"coordinates":[3.000455,50.612171],"type":"Point"}
}