{
  "type": "Feature",
  "properties": {
    "addr:full":"Rte de Woerth Soultz sous For\u00eats Alsace 67250",
    "addr:postcode":"67250",
    "addr:street":"Rte De Woerth;Fore\u0302Ts",
    "iso:country":"FR",
    "sg:address":"Rte de Woerth",
    "sg:city":"Soultz sous For\u00eats",
    "sg:orig_category":"Unclassifiable Establishments",
    "sg:phone":"+33 3 88 63 35 00",
    "sg:postcode":"67250",
    "sg:province":"Alsace",
    "wof:name":"C.e.f.a. S.a.",
    "wof:placetype":"venue"
},
  "geometry": {"coordinates":[7.88268,48.937824],"type":"Point"}
}