{
  "type": "Feature",
  "properties": {
    "iso:country":"FR",
    "sg:address":"Rue de la Tuilerie",
    "sg:city":"Pouan les Vall\u00e9es",
    "sg:orig_category":"Non-Classified Establishments",
    "sg:phone":"+33 3 25 37 71 35",
    "sg:postcode":"10700",
    "sg:province":"Champagne",
    "wof:name":"F\u00e9ron Daniel S.a.",
    "wof:placetype":"venue"
},
  "geometry": {"coordinates":[4.0604,48.543026],"type":"Point"}
}