{
  "type": "Feature",
  "properties": {
    "addr:full":"25 Rue Des Artisans 86200 Loudun Poitou-Charentes 86200",
    "addr:housenumber":"25",
    "addr:postcode":"86200;86200",
    "addr:street":"Rue Des Artisans",
    "iso:country":"FR",
    "sg:address":"25 Rue Des Artisans 86200 Loudun",
    "sg:classifiers":[
        {
            "category":"Professional",
            "type":"Services"
        }
    ],
    "sg:phone":"+33 5 49 98 33 26",
    "sg:postcode":"86200",
    "sg:province":"Poitou-Charentes",
    "sg:tags":[
        "transport",
        "road"
    ],
    "wof:name":"Transports Chauveau Sa",
    "wof:placetype":"venue"
},
  "geometry": {"coordinates":[0.07834,47.004444],"type":"Point"}
}