{
  "type": "Feature",
  "properties": {
    "iso:country":"FR",
    "sg:address":"Rue Rabelais 72200 La Fleche",
    "sg:classifiers":[
        {
            "category":"Manufacturing",
            "subcategory":"Paper Products",
            "type":"Manufacturing & Wholesale Goods"
        }
    ],
    "sg:phone":"+33 2 43 45 87 68",
    "sg:province":"Pays de Loire",
    "sg:tags":[
        "raw",
        "material",
        "-",
        "cardboard"
    ],
    "wof:name":"Cartonnerie Des Pays De Loire",
    "wof:placetype":"venue"
},
  "geometry": {"coordinates":[-0.091484,47.699539],"type":"Point"}
}