{
  "type": "Feature",
  "properties": {
    "iso:country":"FR",
    "sg:address":"98bis, Rue des Grandes Filles de Dieu, 28000 Chartres",
    "sg:city":"Chartres",
    "sg:orig_category":"Unclassifiable Establishments",
    "sg:phone":"+33 2 37 36 21 13",
    "sg:postcode":"28000",
    "sg:province":"Centre",
    "wof:name":"Cresphonte",
    "wof:placetype":"venue"
},
  "geometry": {"coordinates":[1.494669,48.456059],"type":"Point"}
}