{
  "type": "Feature",
  "properties": {
    "addr:full":"9 Rue La Bruy\u00e8re 75009 Paris Ile de France 75009",
    "addr:housenumber":"9",
    "addr:postcode":"75009;75009",
    "addr:street":"Rue La Bruye\u0300Re",
    "iso:country":"FR",
    "sg:address":"9 Rue La Bruy\u00e8re 75009 Paris",
    "sg:classifiers":[
        {
            "category":"Professional",
            "subcategory":"Business Services",
            "type":"Services"
        }
    ],
    "sg:phone":"+33 1 42 85 45 28",
    "sg:postcode":"75009",
    "sg:province":"Ile de France",
    "sg:tags":[
        "body",
        "advice"
    ],
    "wof:name":"Ariam Idf",
    "wof:placetype":"venue"
},
  "geometry": {"coordinates":[2.335977,48.878925],"type":"Point"}
}