{
  "type": "Feature",
  "properties": {
    "iso:country":"FR",
    "sg:address":"La Mothe 81240 Rouairoux",
    "sg:classifiers":[
        {
            "category":"Farming",
            "subcategory":"Farm",
            "type":"Manufacturing & Wholesale Goods"
        }
    ],
    "sg:phone":"+33 5 63 98 42 08",
    "sg:postcode":"81240",
    "sg:province":"Midi Pyr\u00e9n\u00e9es",
    "sg:tags":[
        "horticulture",
        "agriculture",
        "livestock"
    ],
    "wof:name":"Phalippou Frayssinet Sa",
    "wof:placetype":"venue"
},
  "geometry": {"coordinates":[2.594614,43.472103],"type":"Point"}
}