{
  "type": "Feature",
  "properties": {
    "iso:country":"FR",
    "sg:address":"44 rue Jean Jaur\u00e8s 17700 Surgeres",
    "sg:classifiers":[
        {
            "category":"Wholesale",
            "subcategory":"Plants",
            "type":"Manufacturing & Wholesale Goods"
        }
    ],
    "sg:phone":"+33 5 46 07 60 00",
    "sg:postcode":"17700",
    "sg:province":"Poitou-Charentes",
    "sg:tags":[
        "plants",
        "dairy",
        "turnkey"
    ],
    "wof:name":"Ucc Coop.",
    "wof:placetype":"venue"
},
  "geometry": {"coordinates":[-0.7531,46.112152],"type":"Point"}
}