{
  "type": "Feature",
  "properties": {
    "addr:full":"Zone Agricole de la Garnerie Saint Hilaire de Clisson Pays de Loire 44190",
    "addr:postcode":"44190",
    "addr:street":"Garnerie",
    "iso:country":"FR",
    "sg:address":"Zone Agricole de la Garnerie",
    "sg:city":"Saint Hilaire de Clisson",
    "sg:orig_category":"Unclassifiable Establishments",
    "sg:phone":"+33 2 40 03 97 84",
    "sg:postcode":"44190",
    "sg:province":"Pays de Loire",
    "wof:name":"A.n.m. S.a. - Ateliers Nantais De Maroquinerie",
    "wof:placetype":"venue"
},
  "geometry": {"coordinates":[-1.309111,47.062561],"type":"Point"}
}