{
  "type": "Feature",
  "properties": {
    "addr:full":"139, Bd Baille, 13005 Marseille Provence-Alpes-C\u00f4te d'Azur",
    "addr:housenumber":"139",
    "addr:postcode":"13005",
    "addr:street":"Bd Baille",
    "iso:country":"FR",
    "sg:address":"139, Bd Baille, 13005 Marseille",
    "sg:orig_category":"Unclassifiable Establishments",
    "sg:phone":"+33 4 91 48 20 21",
    "sg:province":"Provence-Alpes-C\u00f4te d'Azur",
    "wof:name":"S.m.t.t. S.a.r.l.",
    "wof:placetype":"venue"
},
  "geometry": {"coordinates":[5.39287,43.288471],"type":"Point"}
}