{
  "type": "Feature",
  "properties": {
    "iso:country":"FR",
    "sg:address":"Aeropole Sud Lorraine Rue De Bourgo 88500 Domvallier",
    "sg:orig_category":"Slaughter-Houses, Abattoirs",
    "sg:phone":"+33 3 29 38 29 38",
    "sg:province":"Lorraine",
    "wof:name":"Ste Industrielle Commerciale De L Est Scea",
    "wof:placetype":"venue"
},
  "geometry": {"coordinates":[6.133115,48.30014],"type":"Point"}
}