{
  "type": "Feature",
  "properties": {
    "addr:full":"8, Quai Paul Riquet, 34200 S\u00e8te Languedoc-Roussillon",
    "addr:housenumber":"8",
    "addr:postcode":"34200",
    "addr:street":"Quai Paul Riquet",
    "iso:country":"FR",
    "sg:address":"8, Quai Paul Riquet, 34200 S\u00e8te",
    "sg:orig_category":"Unclassifiable Establishments",
    "sg:phone":"+33 4 67 48 63 16",
    "sg:province":"Languedoc-Roussillon",
    "wof:name":"L\u00e9opold Suquet S.a.",
    "wof:placetype":"venue"
},
  "geometry": {"coordinates":[3.702525,43.41024],"type":"Point"}
}