{
  "type": "Feature",
  "properties": {
    "addr:full":"4 Rue Abadie 65000 Tarbes Midi Pyr\u00e9n\u00e9es",
    "addr:housenumber":"4",
    "addr:postcode":"65000",
    "addr:street":"Rue Abadie",
    "iso:country":"FR",
    "sg:address":"4 Rue Abadie 65000 Tarbes",
    "sg:classifiers":[
        {
            "category":"Professional",
            "type":"Services"
        }
    ],
    "sg:phone":"+33 5 62 34 76 69",
    "sg:province":"Midi Pyr\u00e9n\u00e9es",
    "sg:tags":[
        "transport",
        "road"
    ],
    "wof:name":"Ste Autobus Littoral Toulonnais Salt",
    "wof:placetype":"venue"
},
  "geometry": {"coordinates":[0.071394,43.239044],"type":"Point"}
}