{
  "type": "Feature",
  "properties": {
    "iso:country":"FR",
    "sg:address":"Lieu-Dit Plaine De Bories 81500 Lavaur",
    "sg:classifiers":[
        {
            "category":"Banks & Credit Unions",
            "subcategory":"Investment Brokerage",
            "type":"Services"
        }
    ],
    "sg:phone":"+33 5 63 58 01 49",
    "sg:postcode":"81500",
    "sg:province":"Midi Pyr\u00e9n\u00e9es",
    "sg:tags":[
        "decoration",
        "project"
    ],
    "wof:name":"Sael Decors Sa",
    "wof:placetype":"venue"
},
  "geometry": {"coordinates":[1.84443,43.682781],"type":"Point"}
}