{
  "type": "Feature",
  "properties": {
    "iso:country":"FR",
    "sg:address":"BP 540, Immeuble Atlantique Montparnasse - Nord Pont, 7 Place Des 5 Martyrs du Lyc\u00e9e Buffon, 75725 P",
    "sg:classifiers":[
        {
            "category":"Banks & Credit Unions",
            "subcategory":"Bank",
            "type":"Services"
        }
    ],
    "sg:phone":"+33 1 58 40 33 66",
    "sg:province":"Rhone-Alpes",
    "wof:name":"Caisse Nationale Des Caisses D'epargne Et De Prevoyance",
    "wof:placetype":"venue"
},
  "geometry": {"coordinates":[3.84692,50.221619],"type":"Point"}
}