{
  "type": "Feature",
  "properties": {
    "iso:country":"FR",
    "sg:address":"4, Rue Marivaux, 80000 Amiens",
    "sg:orig_category":"Unclassifiable Establishments",
    "sg:phone":"+33 3 22 44 28 31",
    "sg:province":"Picardie",
    "wof:name":"Denis Jean-marie S.a.",
    "wof:placetype":"venue"
},
  "geometry": {"coordinates":[2.325815,49.909489],"type":"Point"}
}