{
  "type": "Feature",
  "properties": {
    "addr:full":"Zi Site Mira De Gayan 65320 Bord\u00e8res Sur L'Echez Midi Pyr\u00e9n\u00e9es 65320",
    "addr:postcode":"65320;65320",
    "iso:country":"FR",
    "sg:address":"Zi Site Mira",
    "sg:city":"De Gayan 65320 Bord\u00e8res Sur L'Echez",
    "sg:classifiers":[
        {
            "category":"Transit Center",
            "subcategory":"Freight",
            "type":"Transportation"
        }
    ],
    "sg:phone":"+33 5 62 37 01 25",
    "sg:postcode":"65320",
    "sg:province":"Midi Pyr\u00e9n\u00e9es",
    "sg:tags":[
        "metallurgy",
        "pipe",
        "metalworking",
        "sheet"
    ],
    "wof:name":"Industron Europe Sarl",
    "wof:placetype":"venue"
},
  "geometry": {"coordinates":[0.059049,43.272099],"type":"Point"}
}