{
  "type": "Feature",
  "properties": {
    "iso:country":"FR",
    "sg:address":"B.P. 35, 77551 Moissy Cramayel C\u00e9dex^^70, Av. Albert Einstein - ZI de Roissy, 77550 Moissy Cramayel",
    "sg:orig_category":"Non-Classified Establishments",
    "sg:phone":"+33 1 64 88 20 10",
    "sg:province":"Ile de France",
    "wof:name":"Same Deutz Fahr France S.a.",
    "wof:placetype":"venue"
},
  "geometry": {"coordinates":[2.59017,48.627384],"type":"Point"}
}