{
  "type": "Feature",
  "properties": {
    "addr:full":"B.P. 191000, 13795 Aix en Provence C\u00e9dex 03^^350, Rue Gustave Eiffel, 13100 Aix en Provence Limousin",
    "addr:housenumber":"191000;03 ^ ^ 350",
    "addr:postcode":"13795;13100",
    "addr:street":"Ce\u0301Dex;Rue Gustave Eiffel",
    "iso:country":"FR",
    "sg:address":"B.P. 191000, 13795 Aix en Provence C\u00e9dex 03^^350, Rue Gustave Eiffel, 13100 Aix en Provence",
    "sg:orig_category":"Non-Classified Establishments",
    "sg:phone":"+33 4 42 39 34 10",
    "sg:province":"Limousin",
    "wof:name":"S.n.c.i. S.a. - Soci\u00e9t\u00e9 N\u00e9goce International",
    "wof:placetype":"venue"
},
  "geometry": {"coordinates":[5.49167,43.509033],"type":"Point"}
}