{
  "type": "Feature",
  "properties": {
    "addr:full":"24, Rue du Feu, 67370 Truchtersheim Truchtersheim Alsace 67370",
    "addr:housenumber":"24",
    "addr:postcode":"67370;67370",
    "addr:street":"Rue Du Feu",
    "iso:country":"FR",
    "sg:address":"24, Rue du Feu, 67370 Truchtersheim",
    "sg:city":"Truchtersheim",
    "sg:orig_category":"Unclassifiable Establishments",
    "sg:phone":"+33 3 90 29 65 64",
    "sg:postcode":"67370",
    "sg:province":"Alsace",
    "wof:name":"Philipps S.a.r.l.",
    "wof:placetype":"venue"
},
  "geometry": {"coordinates":[7.60507,48.662151],"type":"Point"}
}