{
  "type": "Feature",
  "properties": {
    "addr:full":"8, rue des Combottes, 25700 Valentigney Franche Comt\u00e9",
    "addr:housenumber":"8",
    "addr:postcode":"25700",
    "addr:street":"Rue Des Combottes;Franche Comte\u0301",
    "iso:country":"FR",
    "sg:address":"8, rue des Combottes, 25700 Valentigney",
    "sg:orig_category":"Unclassifiable Establishments",
    "sg:phone":"+33 3 81 35 54 55",
    "sg:province":"Franche Comt\u00e9",
    "wof:name":"Futurelec S.a.r.l.",
    "wof:placetype":"venue"
},
  "geometry": {"coordinates":[6.82853,47.483749],"type":"Point"}
}