{
  "type": "Feature",
  "properties": {
    "addr:full":"60, Rue Pierre S\u00e9nard, 92323 Ch\u00e2tillon C\u00e9dex Ch\u00e2tillon Ile de France 92320",
    "addr:housenumber":"60",
    "addr:postcode":"92323;92320",
    "addr:street":"Rue Pierre Se\u0301Nard",
    "iso:country":"FR",
    "sg:address":"60, Rue Pierre S\u00e9nard, 92323 Ch\u00e2tillon C\u00e9dex",
    "sg:city":"Ch\u00e2tillon",
    "sg:orig_category":"Non-Classified Establishments",
    "sg:phone":"+33 1 41 48 56 78",
    "sg:postcode":"92320",
    "sg:province":"Ile de France",
    "wof:name":"Cofratel I.d.f. S.a.",
    "wof:placetype":"venue"
},
  "geometry": {"coordinates":[2.28984,48.799801],"type":"Point"}
}