{
  "type": "Feature",
  "properties": {
    "addr:full":"9, Villa Pierre Ginier, 75018 Paris Ile de France",
    "addr:housenumber":"9",
    "addr:postcode":"75018",
    "addr:street":"Villa Pierre Ginier",
    "iso:country":"FR",
    "sg:address":"9, Villa Pierre Ginier, 75018 Paris",
    "sg:orig_category":"Non-Classified Establishments",
    "sg:phone":"+33 1 43 87 85 59",
    "sg:province":"Ile de France",
    "wof:name":"Guyenne Papiers S.a.",
    "wof:placetype":"venue"
},
  "geometry": {"coordinates":[2.326675,48.887394],"type":"Point"}
}