{
  "type": "Feature",
  "properties": {
    "iso:country":"FR",
    "sg:address":"route de Beaumont 27300 Menneval",
    "sg:classifiers":[
        {
            "category":"Manufacturing",
            "subcategory":"Tools & Machinery",
            "type":"Manufacturing & Wholesale Goods"
        }
    ],
    "sg:phone":"+33 2 32 43 70 00",
    "sg:province":"Haute Normandie",
    "sg:tags":[
        "fitting",
        "cock"
    ],
    "wof:name":"Soci\u00e9t\u00e9 Nouvelle Champion Sa",
    "wof:placetype":"venue"
},
  "geometry": {"coordinates":[0.609685,49.0956],"type":"Point"}
}