{
  "type": "Feature",
  "properties": {
    "iso:country":"FR",
    "sg:address":"6, Chemin du Clos Portier, 14250 Audrieu",
    "sg:city":"Audrieu",
    "sg:orig_category":"Unclassifiable Establishments",
    "sg:phone":"+33 2 31 80 46 34",
    "sg:postcode":"14250",
    "sg:province":"Basse Normandie",
    "wof:name":"S.r.t.p. S.a.r.l.",
    "wof:placetype":"venue"
},
  "geometry": {"coordinates":[-0.599129,49.199009],"type":"Point"}
}