{
  "type": "Feature",
  "properties": {
    "addr:full":"Chemin de Sury Warcq Champagne 08000",
    "addr:postcode":"08000",
    "addr:street":"Chemin De Sury",
    "iso:country":"FR",
    "sg:address":"Chemin de Sury",
    "sg:city":"Warcq",
    "sg:orig_category":"Unclassifiable Establishments",
    "sg:phone":"+33 3 24 59 63 50",
    "sg:postcode":"08000",
    "sg:province":"Champagne",
    "wof:name":"Gilbert S.a.",
    "wof:placetype":"venue"
},
  "geometry": {"coordinates":[4.663647,49.768665],"type":"Point"}
}