{
  "type": "Feature",
  "properties": {
    "addr:full":"12, Bd Pierre Renaudet, 65000 Tarbes Midi Pyr\u00e9n\u00e9es",
    "addr:housenumber":"12",
    "addr:postcode":"65000",
    "addr:street":"Bd Pierre Renaudet",
    "iso:country":"FR",
    "sg:address":"12, Bd Pierre Renaudet, 65000 Tarbes",
    "sg:orig_category":"Unclassifiable Establishments",
    "sg:phone":"+33 5 62 38 62 62",
    "sg:province":"Midi Pyr\u00e9n\u00e9es",
    "wof:name":"Giat Industries S.a.",
    "wof:placetype":"venue"
},
  "geometry": {"coordinates":[0.053004,43.224606],"type":"Point"}
}