{
  "type": "Feature",
  "properties": {
    "iso:country":"FR",
    "sg:address":"11, Rue Henri Farman - ZI des Petits Ponts, 93297 Tremblay en France C\u00e9dex",
    "sg:orig_category":"Non-Classified Establishments",
    "sg:phone":"+33 1 48 60 21 21",
    "sg:province":"Aquitaine",
    "wof:name":"T.g.l. S.a.r.l. - Technom\u00e9tal Guidage Lin\u00e9aire",
    "wof:placetype":"venue"
},
  "geometry": {"coordinates":[2.56727,48.951214],"type":"Point"}
}