{
  "type": "Feature",
  "properties": {
    "iso:country":"FR",
    "sg:address":"1, Rue de la Mare Neuve - Parc du Bois Briard, 91080 Courcouronnes",
    "sg:orig_category":"Unclassifiable Establishments",
    "sg:phone":"+33 1 69 36 86 00",
    "sg:province":"Ile de France",
    "wof:name":"Academie Accor S.n.c.",
    "wof:placetype":"venue"
},
  "geometry": {"coordinates":[2.425511,48.616367],"type":"Point"}
}