{
  "type": "Feature",
  "properties": {
    "addr:full":"B.P. 185, 76410 Sotteville sous le Val^^4, Rue Jean Sibelius, 76410 Sotteville sous le Val Haute Normandie",
    "addr:housenumber":"b.p. 185",
    "addr:postcode":"76410;76410",
    "addr:street":"Sous Le;Rue Jean Sibelius;Sous Le Val Haute Normandie",
    "iso:country":"FR",
    "sg:address":"B.P. 185, 76410 Sotteville sous le Val^^4, Rue Jean Sibelius, 76410 Sotteville sous le Val",
    "sg:orig_category":"Non-Classified Establishments",
    "sg:phone":"+33 2 32 96 07 47",
    "sg:province":"Haute Normandie",
    "wof:name":"P.v.g. France S.a.r.l.",
    "wof:placetype":"venue"
},
  "geometry": {"coordinates":[1.016645,49.303566],"type":"Point"}
}