{
  "type": "Feature",
  "properties": {
    "addr:full":"Rte Vill\u00e8s Blais Pornichet Pays de Loire 44380",
    "addr:postcode":"44380",
    "addr:street":"Rte Ville\u0300S Blais",
    "iso:country":"FR",
    "sg:address":"Rte Vill\u00e8s Blais",
    "sg:city":"Pornichet",
    "sg:orig_category":"Unclassifiable Establishments",
    "sg:phone":"+33 2 40 61 07 02",
    "sg:postcode":"44380",
    "sg:province":"Pays de Loire",
    "wof:name":"Brake France Service S.a.s.",
    "wof:placetype":"venue"
},
  "geometry": {"coordinates":[-2.298176,47.262787],"type":"Point"}
}