{
  "type": "Feature",
  "properties": {
    "iso:country":"FR",
    "sg:address":"B.P. 26, 35310 Mordelles^^ZA de Cossinade, 35310 Saint Thurial",
    "sg:city":"Mordelles",
    "sg:orig_category":"Non-Classified Establishments",
    "sg:phone":"+33 2 99 85 31 31",
    "sg:postcode":"35310",
    "sg:province":"Bretagne",
    "wof:name":"Buhmann France Image S.a.",
    "wof:placetype":"venue"
},
  "geometry": {"coordinates":[-1.930143,48.030022],"type":"Point"}
}