{
  "type": "Feature",
  "properties": {
    "addr:full":"Rue Edouard Branly - Parc d'Activit\u00e9s de Pissaloup - B\u00e2t. Herm\u00e8s II Trappes Ile de France 78190",
    "addr:housenumber":"ba\u0302t",
    "addr:postcode":"78190",
    "addr:street":"Rue Edouard Branly Parc D'Activite \u0301S De Pissaloup",
    "iso:country":"FR",
    "sg:address":"Rue Edouard Branly - Parc d'Activit\u00e9s de Pissaloup - B\u00e2t. Herm\u00e8s II",
    "sg:city":"Trappes",
    "sg:orig_category":"Non-Classified Establishments",
    "sg:phone":"+33 1 30 68 81 50",
    "sg:postcode":"78190",
    "sg:province":"Ile de France",
    "wof:name":"Tecan France S.a.",
    "wof:placetype":"venue"
},
  "geometry": {"coordinates":[1.98275,48.793591],"type":"Point"}
}