{
  "type": "Feature",
  "properties": {
    "addr:full":"Zone D Activite La Fontain 49330 Champigne Pays de Loire",
    "addr:postcode":"49330",
    "addr:street":"La Fontain;Champigne",
    "iso:country":"FR",
    "sg:address":"Zone D Activite La Fontain 49330 Champigne",
    "sg:classifiers":[
        {
            "category":"Home & Garden",
            "subcategory":"Furniture",
            "type":"Retail Goods"
        }
    ],
    "sg:phone":"+33 2 41 42 01 80",
    "sg:province":"Pays de Loire",
    "sg:tags":[
        "wood"
    ],
    "wof:name":"Etablissements Margot",
    "wof:placetype":"venue"
},
  "geometry": {"coordinates":[-0.570718,47.667068],"type":"Point"}
}