{
  "type": "Feature",
  "properties": {
    "addr:full":"B.P. 11, 01160 Pont d'Ain C\u00e9dex^^ZI Le Blanchon, 01160 Pont d'Ain Rhone-Alpes",
    "addr:postcode":"01160;01160",
    "addr:street":"B.P. 11;D'Ain Ce\u0301Dex^^Zi Le Blanchon;D'Ain Rhone-Alpes",
    "iso:country":"FR",
    "sg:address":"B.P. 11, 01160 Pont d'Ain C\u00e9dex^^ZI Le Blanchon, 01160 Pont d'Ain",
    "sg:orig_category":"Non-Classified Establishments",
    "sg:phone":"+33 4 74 39 14 44",
    "sg:province":"Rhone-Alpes",
    "wof:name":"Michaud S.a.",
    "wof:placetype":"venue"
},
  "geometry": {"coordinates":[5.3206,46.06266],"type":"Point"}
}