{
  "type": "Feature",
  "properties": {
    "iso:country":"FR",
    "sg:address":"3",
    "sg:city":"Vimoutiers",
    "sg:classifiers":[
        {
            "category":"Shopping",
            "subcategory":"Bicycles & Sporting Goods",
            "type":"Retail Goods"
        }
    ],
    "sg:phone":"+33 2 33 39 07 04",
    "sg:postcode":"61120",
    "sg:province":"Basse Normandie",
    "sg:tags":[
        "product",
        "sport",
        "miscellaneous"
    ],
    "wof:name":"Ring Verseron",
    "wof:placetype":"venue"
},
  "geometry": {"coordinates":[0.197715,48.935654],"type":"Point"}
}