{
  "type": "Feature",
  "properties": {
    "addr:full":"7, Rue du Foss\u00e9 Blanc, 92230 Gennevilliers Ile de France",
    "addr:housenumber":"7",
    "addr:postcode":"92230;ile",
    "addr:street":"Rue Du Fosse\u0301 Blanc",
    "iso:country":"FR",
    "sg:address":"7, Rue du Foss\u00e9 Blanc, 92230 Gennevilliers",
    "sg:orig_category":"Non-Classified Establishments",
    "sg:phone":"+33 1 41 32 27 00",
    "sg:province":"Ile de France",
    "wof:name":"Th\u00e9sis S.a.",
    "wof:placetype":"venue"
},
  "geometry": {"coordinates":[2.306201,48.922695],"type":"Point"}
}