{
  "type": "Feature",
  "properties": {
    "iso:country":"FR",
    "sg:address":"Bd Stalingrad - Gare Nord Immeuble Parking SNCF",
    "sg:city":"Nantes",
    "sg:orig_category":"Non-Classified Establishments",
    "sg:phone":"+33 2 40 29 05 10",
    "sg:postcode":"44000",
    "sg:province":"Pays de Loire",
    "wof:name":"Europcar S.a.",
    "wof:placetype":"venue"
},
  "geometry": {"coordinates":[-1.532709,47.219746],"type":"Point"}
}