{
  "type": "Feature",
  "properties": {
    "addr:full":"Rte Lescun Lescun Aquitaine 64490",
    "addr:postcode":"64490",
    "addr:street":"Rte Lescun",
    "iso:country":"FR",
    "sg:address":"Rte Lescun",
    "sg:city":"Lescun",
    "sg:orig_category":"Unclassifiable Establishments",
    "sg:phone":"+33 5 59 88 20 00",
    "sg:postcode":"64490",
    "sg:province":"Aquitaine",
    "wof:name":"Toyal Europe S.a.",
    "wof:placetype":"venue"
},
  "geometry": {"coordinates":[-0.554219,42.87114],"type":"Point"}
}