{
  "type": "Feature",
  "properties": {
    "addr:full":"77 rue Samuel Morse 34000 Montpellier Languedoc-Roussillon 34000",
    "addr:housenumber":"77",
    "addr:postcode":"34000;34000",
    "addr:street":"Rue Samuel Morse",
    "iso:country":"FR",
    "sg:address":"77 rue Samuel Morse 34000 Montpellier",
    "sg:orig_category":"Cad/Cam Software",
    "sg:phone":"+33 4 99 52 43 00",
    "sg:postcode":"34000",
    "sg:province":"Languedoc-Roussillon",
    "wof:name":"Palm Computing Europe S.a.r.l.",
    "wof:placetype":"venue"
},
  "geometry": {"coordinates":[3.914221,43.606724],"type":"Point"}
}