{
  "type": "Feature",
  "properties": {
    "addr:full":"12, Rue Ren\u00e9 Cassin, 71380 Saint Marcel Ch\u00e2tenoy-en-Bresse Bourgogne 71380",
    "addr:housenumber":"12",
    "addr:postcode":"71380;71380",
    "addr:street":"Rue Rene\u0301 Cassin;Marcel",
    "iso:country":"FR",
    "sg:address":"12, Rue Ren\u00e9 Cassin, 71380 Saint Marcel",
    "sg:city":"Ch\u00e2tenoy-en-Bresse",
    "sg:orig_category":"Unclassifiable Establishments",
    "sg:phone":"+33 3 85 97 52 02",
    "sg:postcode":"71380",
    "sg:province":"Bourgogne",
    "wof:name":"Aubry C.r. S.a.",
    "wof:placetype":"venue"
},
  "geometry": {"coordinates":[4.868186,46.77243],"type":"Point"}
}