{
  "type": "Feature",
  "properties": {
    "iso:country":"FR",
    "sg:address":"5, Av. Albert 1er, 06230 Villefranche sur Mer",
    "sg:city":"Alb\u00e9",
    "sg:orig_category":"Unclassifiable Establishments",
    "sg:phone":"+33 4 93 01 93 72",
    "sg:postcode":"67220",
    "sg:province":"Alsace",
    "wof:name":"M\u00e9diatype S.a.r.l.",
    "wof:placetype":"venue"
},
  "geometry": {"coordinates":[7.308862,43.7033],"type":"Point"}
}