{
  "type": "Feature",
  "properties": {
    "iso:country":"FR",
    "sg:address":"33 rue de l'Industrie 76120 Le Grand Quevilly",
    "sg:classifiers":[
        {
            "category":"Wholesale",
            "subcategory":"Vending Machines",
            "type":"Manufacturing & Wholesale Goods"
        }
    ],
    "sg:phone":"+33 2 35 68 27 22",
    "sg:province":"Haute Normandie",
    "sg:tags":[
        "engineering",
        "special",
        "mechanical"
    ],
    "wof:name":"Remsi S.a.",
    "wof:placetype":"venue"
},
  "geometry": {"coordinates":[1.046985,49.423759],"type":"Point"}
}