{
  "type": "Feature",
  "properties": {
    "addr:full":"Rte du March\u00e9 de la Fraise Vergt Aquitaine 24380",
    "addr:postcode":"24380",
    "addr:street":"Rte Du Marche\u0301 De La Fraise",
    "iso:country":"FR",
    "sg:address":"Rte du March\u00e9 de la Fraise",
    "sg:city":"Vergt",
    "sg:orig_category":"Unclassifiable Establishments",
    "sg:phone":"+33 5 53 03 81 00",
    "sg:postcode":"24380",
    "sg:province":"Aquitaine",
    "wof:name":"Socave S.a.",
    "wof:placetype":"venue"
},
  "geometry": {"coordinates":[0.722844,45.030548],"type":"Point"}
}