{
  "type": "Feature",
  "properties": {
    "iso:country":"FR",
    "sg:address":"Rue du Cap Horn",
    "sg:city":"Saint Herblain",
    "sg:orig_category":"Unclassifiable Establishments",
    "sg:phone":"+33 2 40 63 13 98",
    "sg:postcode":"44800",
    "sg:province":"Pays de Loire",
    "wof:name":"Vezin S.n.c.",
    "wof:placetype":"venue"
},
  "geometry": {"coordinates":[-1.656068,47.236706],"type":"Point"}
}