{
  "type": "Feature",
  "properties": {
    "addr:full":"12 Rue Nicolas No\u00ebl 54460 Liverdun Lorraine 54460",
    "addr:housenumber":"12",
    "addr:postcode":"54460;54460",
    "addr:street":"Rue Nicolas Noe\u0308L",
    "iso:country":"FR",
    "sg:address":"12 Rue Nicolas No\u00ebl 54460 Liverdun",
    "sg:classifiers":[
        {
            "category":"Manufacturing",
            "subcategory":"Metals",
            "type":"Manufacturing & Wholesale Goods"
        }
    ],
    "sg:phone":"+33 3 83 24 51 98",
    "sg:postcode":"54460",
    "sg:province":"Lorraine",
    "sg:tags":[
        "metallurgy",
        "metalworking"
    ],
    "wof:name":"Saint Gobain Pam",
    "wof:placetype":"venue"
},
  "geometry": {"coordinates":[6.06675,48.74876],"type":"Point"}
}