{
  "type": "Feature",
  "properties": {
    "addr:full":"5-7 R Sinclair 94044 Cr\u00e9teil Cedex Pays de Loire",
    "addr:housenumber":"5-7",
    "addr:postcode":"94044;cedex pays",
    "addr:street":"R Sinclair",
    "iso:country":"FR",
    "sg:address":"5-7 R Sinclair 94044 Cr\u00e9teil Cedex",
    "sg:classifiers":[
        {
            "category":"Professional",
            "subcategory":"Engineering",
            "type":"Services"
        }
    ],
    "sg:phone":"+33 1 43 99 15 00",
    "sg:province":"Pays de Loire",
    "sg:tags":[
        "machine",
        "-",
        "mechanical"
    ],
    "wof:name":"Hanrot Sa",
    "wof:placetype":"venue"
},
  "geometry": {"coordinates":[2.47468,48.768242],"type":"Point"}
}