{
  "type": "Feature",
  "properties": {
    "addr:full":"Rue Andr\u00e9 Durouchez - Espace Industriel d'Amiens Nord - Village PMI Amiens Picardie 80000",
    "addr:postcode":"80000",
    "addr:street":"Rue Andre\u0301 Durouchez Espace Industriel D'Amiens Nord Village",
    "iso:country":"FR",
    "sg:address":"Rue Andr\u00e9 Durouchez - Espace Industriel d'Amiens Nord - Village PMI",
    "sg:city":"Amiens",
    "sg:orig_category":"Unclassifiable Establishments",
    "sg:phone":"+33 3 22 54 27 27",
    "sg:postcode":"80000",
    "sg:province":"Picardie",
    "wof:name":"Euromur S.a.",
    "wof:placetype":"venue"
},
  "geometry": {"coordinates":[2.30023,49.895584],"type":"Point"}
}