{
  "type": "Feature",
  "properties": {
    "addr:full":"12 Av De Paris 42300 Roanne Rhone-Alpes 42300",
    "addr:postcode":"42300;42300",
    "addr:street":"12 Av De Paris;Rhone-Alpes",
    "iso:country":"FR",
    "sg:address":"12 Av De Paris 42300 Roanne",
    "sg:classifiers":[
        {
            "category":"Professional",
            "subcategory":"Business Services",
            "type":"Services"
        }
    ],
    "sg:phone":"+33 4 77 23 67 00",
    "sg:postcode":"42300",
    "sg:province":"Rhone-Alpes",
    "sg:tags":[
        "body",
        "advice"
    ],
    "wof:name":"Comite Roannais De Vacances",
    "wof:placetype":"venue"
},
  "geometry": {"coordinates":[4.072045,46.043297],"type":"Point"}
}