{
  "type": "Feature",
  "properties": {
    "iso:country":"FR",
    "sg:address":"10, Place Bougainville, 13020 Marseille",
    "sg:city":"Vill\u00e9",
    "sg:orig_category":"Unclassifiable Establishments",
    "sg:phone":"+33 4 91 50 94 74",
    "sg:postcode":"67220",
    "sg:province":"Alsace",
    "wof:name":"C.s.a. S.a. - Compagnie Stn Alimentaire",
    "wof:placetype":"venue"
},
  "geometry": {"coordinates":[5.36802,43.319229],"type":"Point"}
}