{
  "type": "Feature",
  "properties": {
    "iso:country":"FR",
    "sg:address":"Ripotier Haut 07200 Aubenas",
    "sg:classifiers":[
        {
            "category":"Manufacturing",
            "subcategory":"Printing",
            "type":"Manufacturing & Wholesale Goods"
        }
    ],
    "sg:phone":"+33 4 75 35 33 65",
    "sg:postcode":"07200",
    "sg:province":"Rhone-Alpes",
    "sg:tags":[
        "publishing"
    ],
    "wof:name":"Lienhart Et Cie Imprimerie",
    "wof:placetype":"venue"
},
  "geometry": {"coordinates":[4.399589,44.606449],"type":"Point"}
}