{
  "type": "Feature",
  "properties": {
    "iso:country":"FR",
    "sg:address":"15 A, Rue Forlen, 67118 Geispolsheim",
    "sg:city":"Geispolsheim",
    "sg:orig_category":"Non-Classified Establishments",
    "sg:phone":"+33 3 88 55 36 55",
    "sg:postcode":"67400",
    "sg:province":"Alsace",
    "wof:name":"Compagnie Centrale Sicli S.a.",
    "wof:placetype":"venue"
},
  "geometry": {"coordinates":[7.683125,48.536072],"type":"Point"}
}