{
  "type": "Feature",
  "properties": {
    "iso:country":"FR",
    "sg:address":"A\u00e9rodrome Avignon Caumont",
    "sg:city":"Montfavet",
    "sg:orig_category":"Unclassifiable Establishments",
    "sg:phone":"+33 4 90 33 36 58",
    "sg:postcode":"84140",
    "sg:province":"Provence-Alpes-C\u00f4te d'Azur",
    "wof:name":"Delta Aviation S.a.",
    "wof:placetype":"venue"
},
  "geometry": {"coordinates":[4.87188,43.935669],"type":"Point"}
}