{
  "type": "Feature",
  "properties": {
    "addr:full":"ZI Av g\u00e9n\u00e9ral de Gaulle 89130 Toucy Toucy Bourgogne 89130",
    "addr:postcode":"89130;89130",
    "addr:street":"Zi Av Ge\u0301Ne\u0301Ral De Gaulle",
    "iso:country":"FR",
    "sg:address":"ZI Av g\u00e9n\u00e9ral de Gaulle 89130 Toucy",
    "sg:city":"Toucy",
    "sg:classifiers":[
        {
            "category":"Professional",
            "subcategory":"Engineering",
            "type":"Services"
        }
    ],
    "sg:phone":"+33 3 86 44 06 06",
    "sg:postcode":"89130",
    "sg:province":"Bourgogne",
    "sg:tags":[
        "machine",
        "-",
        "mechanical"
    ],
    "wof:name":"Technitrace",
    "wof:placetype":"venue"
},
  "geometry": {"coordinates":[3.296364,47.734806],"type":"Point"}
}