{
  "type": "Feature",
  "properties": {
    "iso:country":"FR",
    "sg:address":"14, Rue Andr\u00e9 Clou, 31094 Toulouse C\u00e9dex",
    "sg:orig_category":"Non-Classified Establishments",
    "sg:phone":"+33 5 62 20 65 40",
    "sg:province":"Picardie",
    "wof:name":"C.g.e. Distribution S.a.",
    "wof:placetype":"venue"
},
  "geometry": {"coordinates":[1.407878,43.548901],"type":"Point"}
}