{
  "type": "Feature",
  "properties": {
    "addr:full":"40 bis, Chemin Lavarin, 84000 Avignon Franche Comt\u00e9",
    "addr:housenumber":"40 bis",
    "addr:postcode":"84000",
    "addr:street":"Chemin Lavarin;Franche Comte\u0301",
    "iso:country":"FR",
    "sg:address":"40 bis, Chemin Lavarin, 84000 Avignon",
    "sg:orig_category":"Non-Classified Establishments",
    "sg:phone":"+33 4 90 88 41 66",
    "sg:province":"Franche Comt\u00e9",
    "wof:name":"A.g.e.i. - Approvisionnement G\u00e9n\u00e9ral Electrique Industrielle",
    "wof:placetype":"venue"
},
  "geometry": {"coordinates":[4.804656,43.929829],"type":"Point"}
}