{
  "type": "Feature",
  "properties": {
    "addr:full":"Rte de Caen Cabourg Basse Normandie 14390",
    "addr:postcode":"14390",
    "addr:street":"Rte De Caen;Basse",
    "iso:country":"FR",
    "sg:address":"Rte de Caen",
    "sg:city":"Cabourg",
    "sg:orig_category":"Unclassifiable Establishments",
    "sg:phone":"+33 2 31 91 25 42",
    "sg:postcode":"14390",
    "sg:province":"Basse Normandie",
    "wof:name":"Scop Houchard S.a.",
    "wof:placetype":"venue"
},
  "geometry": {"coordinates":[-0.134764,49.283508],"type":"Point"}
}