{
  "type": "Feature",
  "properties": {
    "addr:full":"1, All\u00e9e de Saint Cloud, 54600 Villers l\u00e8s Nancy Lorraine",
    "addr:housenumber":"1",
    "addr:postcode":"54600",
    "addr:street":"Alle\u0301E De Saint Cloud",
    "iso:country":"FR",
    "sg:address":"1, All\u00e9e de Saint Cloud, 54600 Villers l\u00e8s Nancy",
    "sg:orig_category":"Unclassifiable Establishments",
    "sg:phone":"+33 3 83 44 01 41",
    "sg:province":"Lorraine",
    "wof:name":"T.n.i. S.a. - Techniques Nouvelles Informatique",
    "wof:placetype":"venue"
},
  "geometry": {"coordinates":[6.133809,48.656376],"type":"Point"}
}