{
  "type": "Feature",
  "properties": {
    "iso:country":"FR",
    "sg:address":"170, Rue du Mar\u00e9chal Leclerc, 33130 B\u00e8gles",
    "sg:city":"B\u00e8gles",
    "sg:orig_category":"Non-Classified Establishments",
    "sg:phone":"+33 5 56 85 07 23",
    "sg:postcode":"33130",
    "sg:province":"Aquitaine",
    "wof:name":"France Tambour S.a.",
    "wof:placetype":"venue"
},
  "geometry": {"coordinates":[-0.540126,44.814198],"type":"Point"}
}