{
  "type": "Feature",
  "properties": {
    "addr:full":"1 Place Victor Hugo 31000 Toulouse Midi Pyr\u00e9n\u00e9es 31000",
    "addr:housenumber":"1",
    "addr:postcode":"31000;31000",
    "addr:street":"Place Victor Hugo",
    "iso:country":"FR",
    "sg:address":"1 Place Victor Hugo 31000 Toulouse",
    "sg:classifiers":[
        {
            "category":"Shopping",
            "subcategory":"Bicycles & Sporting Goods",
            "type":"Retail Goods"
        }
    ],
    "sg:phone":"+33 5 61 21 54 57",
    "sg:postcode":"31000",
    "sg:province":"Midi Pyr\u00e9n\u00e9es",
    "sg:tags":[
        "product",
        "sport",
        "miscellaneous"
    ],
    "wof:name":"Sa Sls Igloo Sport Intersport",
    "wof:placetype":"venue"
},
  "geometry": {"coordinates":[1.446766,43.607277],"type":"Point"}
}