{
  "type": "Feature",
  "properties": {
    "addr:full":"Tours 11 Jean; Indre; 37 Pays de Loire",
    "addr:housenumber":"11;37",
    "addr:street":"Jean Indre",
    "iso:country":"FR",
    "sg:address":"Tours 11",
    "sg:city":"Jean; Indre; 37",
    "sg:classifiers":[
        {
            "category":"Banks & Credit Unions",
            "subcategory":"Bank",
            "type":"Services"
        }
    ],
    "sg:phone":"+33 3347209751",
    "sg:province":"Pays de Loire",
    "wof:name":"Cr\u00e9dit Commercial De France",
    "wof:placetype":"venue"
},
  "geometry": {"coordinates":[1.995748,46.947117],"type":"Point"}
}