{
  "type": "Feature",
  "properties": {
    "iso:country":"FR",
    "sg:address":"11 Rue Des Freres Lumiere 72650 La Chapelle St Aubin",
    "sg:classifiers":[
        {
            "category":"Utilities",
            "subcategory":"Telephone",
            "type":"Services"
        }
    ],
    "sg:phone":"+33 2 43 28 64 36",
    "sg:province":"Pays de Loire",
    "sg:tags":[
        "telecommunication"
    ],
    "wof:name":"Sarl Atelier Chiron",
    "wof:placetype":"venue"
},
  "geometry": {"coordinates":[0.174791,48.025009],"type":"Point"}
}