{
  "type": "Feature",
  "properties": {
    "iso:country":"FR",
    "sg:address":"Maison Grigt",
    "sg:city":"Sauvelade",
    "sg:orig_category":"Unclassifiable Establishments",
    "sg:phone":"+33 5 59 67 30 66",
    "sg:postcode":"64150",
    "sg:province":"Aquitaine",
    "wof:name":"Marmagne Alain S.a.r.l.",
    "wof:placetype":"venue"
},
  "geometry": {"coordinates":[-0.61819,43.354855],"type":"Point"}
}