{
  "type": "Feature",
  "properties": {
    "iso:country":"FR",
    "sg:address":"201, Rue Gustave Eiffel - ZI de Gr\u00e9zan, 30000 N\u00eemes",
    "sg:orig_category":"Unclassifiable Establishments",
    "sg:phone":"+33 4 66 27 53 93",
    "sg:province":"Languedoc-Roussillon",
    "wof:name":"S.e.m.i.c. S.a.r.l. - Soci\u00e9t\u00e9 D'equipement M\u00e9canique Pour L'industrie De La Chaussure",
    "wof:placetype":"venue"
},
  "geometry": {"coordinates":[4.36035,43.86256],"type":"Point"}
}