{
  "type": "Feature",
  "properties": {
    "iso:country":"FR",
    "sg:address":"B.P. 139, 42600 Montbrison C\u00e9dex^^ZI de Vaure, 42600 Montbrison",
    "sg:orig_category":"Non-Classified Establishments",
    "sg:phone":"+33 4 77 58 00 22",
    "sg:postcode":"42600",
    "sg:province":"Rhone-Alpes",
    "wof:name":"U.f.f.o.p. S.a. - Union Fran\u00e7aise De Fabrication D'outillage De Pr\u00e9",
    "wof:placetype":"venue"
},
  "geometry": {"coordinates":[3.996271,45.571075],"type":"Point"}
}