{
  "type": "Feature",
  "properties": {
    "addr:full":"13, Rue de Rambouillet, 75012 Paris Ile de France 75012",
    "addr:housenumber":"13",
    "addr:postcode":"75012;75012",
    "addr:street":"Rue De Rambouillet",
    "iso:country":"FR",
    "sg:address":"13, Rue de Rambouillet, 75012 Paris",
    "sg:orig_category":"Non-Classified Establishments",
    "sg:phone":"+33 1 43 07 70 00",
    "sg:postcode":"75012",
    "sg:province":"Ile de France",
    "wof:name":"Agilos Sarl",
    "wof:placetype":"venue"
},
  "geometry": {"coordinates":[2.380381,48.843998],"type":"Point"}
}