{
  "type": "Feature",
  "properties": {
    "iso:country":"FR",
    "sg:address":"B.P. 7",
    "sg:city":"Monthou sur Cher",
    "sg:orig_category":"Non-Classified Establishments",
    "sg:phone":"+33 2 54 71 50 42",
    "sg:postcode":"41400",
    "sg:province":"Centre",
    "wof:name":"M.c.f. S.a.r.l. - Manufacture Case Flight",
    "wof:placetype":"venue"
},
  "geometry": {"coordinates":[1.294545,47.346161],"type":"Point"}
}