{
  "type": "Feature",
  "properties": {
    "addr:full":"Rue Du Marais Zac Des Puits D Ordet 73190 Challes Les Eaux Rhone-Alpes 73190",
    "addr:postcode":"73190;73190",
    "addr:street":"Rue Du Marais Zac Des Puits D Ordet",
    "iso:country":"FR",
    "sg:address":"Rue Du Marais Zac Des Puits D Ordet 73190 Challes Les Eaux",
    "sg:classifiers":[
        {
            "category":"Professional",
            "subcategory":"Engineering",
            "type":"Services"
        }
    ],
    "sg:phone":"+33 4 79 72 95 47",
    "sg:postcode":"73190",
    "sg:province":"Rhone-Alpes",
    "sg:tags":[
        "machine",
        "-",
        "mechanical"
    ],
    "wof:name":"Elsy",
    "wof:placetype":"venue"
},
  "geometry": {"coordinates":[5.959457,45.513103],"type":"Point"}
}