{
  "type": "Feature",
  "properties": {
    "addr:full":"Rte de Sottevast - ZA d'Armanville Valognes Basse Normandie 50700",
    "addr:postcode":"50700",
    "addr:street":"Rte De Sottevast Za D'Armanville;Basse",
    "iso:country":"FR",
    "sg:address":"Rte de Sottevast - ZA d'Armanville",
    "sg:city":"Valognes",
    "sg:orig_category":"Unclassifiable Establishments",
    "sg:phone":"+33 2 33 40 31 23",
    "sg:postcode":"50700",
    "sg:province":"Basse Normandie",
    "wof:name":"A.f.c.o. S.a.r.l. - Aciers Et Fers Du Cotentin",
    "wof:placetype":"venue"
},
  "geometry": {"coordinates":[-1.46848,49.508759],"type":"Point"}
}