{
  "type": "Feature",
  "properties": {
    "iso:country":"FR",
    "sg:address":"B.P. 21203, 44312 Nantes C\u00e9dex 03^^359, Rte de Ste Luce - Le Petit Ch\u00e2telier, 44300 Nantes",
    "sg:orig_category":"Non-Classified Establishments",
    "sg:phone":"+33 2 51 89 14 22",
    "sg:province":"Pays de Loire",
    "wof:name":"Hobart S.a.",
    "wof:placetype":"venue"
},
  "geometry": {"coordinates":[-1.5359,47.25631],"type":"Point"}
}