{
  "type": "Feature",
  "properties": {
    "addr:full":"18 Rue Hoche Issy Les Moulineaux Ile de France 92130",
    "addr:housenumber":"18",
    "addr:postcode":"92130",
    "addr:street":"Rue Hoche",
    "iso:country":"FR",
    "sg:address":"18 Rue Hoche",
    "sg:city":"Issy Les Moulineaux",
    "sg:classifiers":[
        {
            "category":"Banks & Credit Unions",
            "subcategory":"Financial Services",
            "type":"Services"
        }
    ],
    "sg:phone":"+33 1 41 90 18 18",
    "sg:postcode":"92130",
    "sg:province":"Ile de France",
    "sg:tags":[
        "banking",
        "finance",
        "insurance"
    ],
    "wof:name":"Sodecorg Sa",
    "wof:placetype":"venue"
},
  "geometry": {"coordinates":[2.271351,48.824886],"type":"Point"}
}