{
  "type": "Feature",
  "properties": {
    "addr:full":"1 G\u00e9n\u00e9al de Gaulle Cedex 92074 Paris La D\u00e9fense Midi Pyr\u00e9n\u00e9es",
    "addr:housenumber":"1",
    "addr:postcode":"92074",
    "addr:street":"Ge\u0301Ne\u0301Al De Gaulle",
    "iso:country":"FR",
    "sg:address":"1",
    "sg:city":"G\u00e9n\u00e9al de Gaulle Cedex 92074 Paris La D\u00e9fense",
    "sg:classifiers":[
        {
            "category":"Banks & Credit Unions",
            "subcategory":"Financial Services",
            "type":"Services"
        }
    ],
    "sg:phone":"+33 1 46 98 70 00",
    "sg:province":"Midi Pyr\u00e9n\u00e9es",
    "sg:tags":[
        "banking",
        "finance",
        "insurance"
    ],
    "wof:name":"Scor",
    "wof:placetype":"venue"
},
  "geometry": {"coordinates":[2.24119,48.888939],"type":"Point"}
}