{
  "type": "Feature",
  "properties": {
    "addr:full":"3, Rue de Saint Senoch, 75017 Paris Ile de France 75017",
    "addr:housenumber":"3",
    "addr:postcode":"75017;75017",
    "addr:street":"Rue De Saint Senoch",
    "iso:country":"FR",
    "sg:address":"3, Rue de Saint Senoch, 75017 Paris",
    "sg:orig_category":"Non-Classified Establishments",
    "sg:phone":"+33 1 42 27 22 92",
    "sg:postcode":"75017",
    "sg:province":"Ile de France",
    "wof:name":"Ecrire S.a.r.l.",
    "wof:placetype":"venue"
},
  "geometry": {"coordinates":[2.292943,48.881489],"type":"Point"}
}