{
  "type": "Feature",
  "properties": {
    "iso:country":"FR",
    "sg:address":"1 Rue Du Bief 25500 Morteau",
    "sg:classifiers":[
        {
            "category":"Manufacturing",
            "subcategory":"Jewelry",
            "type":"Manufacturing & Wholesale Goods"
        }
    ],
    "sg:phone":"+33 3 81 67 30 66",
    "sg:postcode":"25500",
    "sg:province":"Franche Comt\u00e9",
    "sg:tags":[
        "product",
        "miscellaneous",
        "jewellery"
    ],
    "wof:name":"Montres Pequignet Sa",
    "wof:placetype":"venue"
},
  "geometry": {"coordinates":[6.615364,47.057674],"type":"Point"}
}