{
  "type": "Feature",
  "properties": {
    "addr:full":"21, Bd Joseph Girod, 63000 Clermont Ferrand Clermont-Ferrand Auvergne 63000",
    "addr:housenumber":"21",
    "addr:postcode":"63000;63000",
    "addr:street":"Bd Joseph Girod",
    "iso:country":"FR",
    "sg:address":"21, Bd Joseph Girod, 63000 Clermont Ferrand",
    "sg:city":"Clermont-Ferrand",
    "sg:orig_category":"Unclassifiable Establishments",
    "sg:phone":"+33 4 73 34 12 34",
    "sg:postcode":"63000",
    "sg:province":"Auvergne",
    "wof:name":"C.e.g.e.x. S.a.r.l. - Centre De Gestion Et D'expertise Comptable",
    "wof:placetype":"venue"
},
  "geometry": {"coordinates":[3.084126,45.76606],"type":"Point"}
}