{
  "type": "Feature",
  "properties": {
    "iso:country":"FR",
    "sg:address":"Pont St Thomas Saint Rene 22120 Hillion",
    "sg:city":"Hillion",
    "sg:classifiers":[
        {
            "category":"Shopping",
            "type":"Retail Goods"
        }
    ],
    "sg:phone":"+33 2 96 63 90 06",
    "sg:postcode":"22120",
    "sg:province":"Bretagne",
    "sg:tags":[
        "metallurgy",
        "finished",
        "-",
        "metalworking",
        "metallic"
    ],
    "wof:name":"Btp Armatures",
    "wof:placetype":"venue"
},
  "geometry": {"coordinates":[-2.636549,48.482815],"type":"Point"}
}