{
  "type": "Feature",
  "properties": {
    "iso:country":"FR",
    "sg:address":"B.P. 188, 67405 Illkirch C\u00e9dex^^Bd S\u00e9bastien Brandt - Parc d'Innovation, 67400 Illkirch Graffenstade",
    "sg:city":"Geispolsheim",
    "sg:orig_category":"Non-Classified Establishments",
    "sg:phone":"+33 3 88 66 67 24",
    "sg:postcode":"67400",
    "sg:province":"Alsace",
    "wof:name":"Avantec S.a.r.l.",
    "wof:placetype":"venue"
},
  "geometry": {"coordinates":[7.727581,48.545532],"type":"Point"}
}