{
  "type": "Feature",
  "properties": {
    "iso:country":"FR",
    "sg:address":"67 Rue Martre",
    "sg:city":"Clichy",
    "sg:classifiers":[
        {
            "category":"Banks & Credit Unions",
            "subcategory":"Financial Services",
            "type":"Services"
        }
    ],
    "sg:phone":"+33 1 41 06 15 00",
    "sg:postcode":"92110",
    "sg:province":"Ile de France",
    "sg:tags":[
        "banking",
        "finance",
        "insurance"
    ],
    "wof:name":"Agence Nationale Pour Les Cheques Vacances",
    "wof:placetype":"venue"
},
  "geometry": {"coordinates":[2.30586,48.903126],"type":"Point"}
}