{
  "type": "Feature",
  "properties": {
    "iso:country":"FR",
    "sg:address":"4, Rue des Colonnes, 75082 Paris C\u00e9dex 2",
    "sg:orig_category":"Non-Classified Establishments",
    "sg:phone":"+33 1 55 04 52 00",
    "sg:province":"\u00cele-de-France",
    "wof:name":"Questel-orbit S.a.",
    "wof:placetype":"venue"
},
  "geometry": {"coordinates":[2.339647,48.869347],"type":"Point"}
}