{
  "type": "Feature",
  "properties": {
    "addr:full":"4, Rue des Colonnes, 75082 Paris C\u00e9dex 2 \u00cele-de-France",
    "addr:housenumber":"4",
    "addr:postcode":"75082",
    "addr:street":"Rue Des Colonnes",
    "iso:country":"FR",
    "sg:address":"4, Rue des Colonnes, 75082 Paris C\u00e9dex 2",
    "sg:orig_category":"Non-Classified Establishments",
    "sg:phone":"+33 1 55 04 52 00",
    "sg:province":"\u00cele-de-France",
    "wof:name":"Questel-orbit S.a.",
    "wof:placetype":"venue"
},
  "geometry": {"coordinates":[2.339647,48.869347],"type":"Point"}
}