{
  "type": "Feature",
  "properties": {
    "addr:full":"Rue Jean Monnet - ZI du Parquet Saint Jean de Maurienne Rhone-Alpes 73300",
    "addr:postcode":"73300",
    "addr:street":"Rue Jean Monnet Zi Du Parquet Saint Jean De Maurienne Rhone-Alpes",
    "iso:country":"FR",
    "sg:address":"Rue Jean Monnet - ZI du Parquet",
    "sg:city":"Saint Jean de Maurienne",
    "sg:orig_category":"Unclassifiable Establishments",
    "sg:phone":"+33 4 79 64 30 45",
    "sg:postcode":"73300",
    "sg:province":"Rhone-Alpes",
    "wof:name":"Brun Nettoyage S.a.",
    "wof:placetype":"venue"
},
  "geometry": {"coordinates":[6.3601,45.270611],"type":"Point"}
}