{
  "type": "Feature",
  "properties": {
    "addr:full":"65 Rue Jean Jaur\u00e8s BP 102 26802 Portes L\u00e8s Valence Champagne",
    "addr:housenumber":"65;102",
    "addr:postcode":"26802",
    "addr:street":"Rue Jean Jaure\u0300S Bp",
    "iso:country":"FR",
    "sg:address":"65 Rue Jean Jaur\u00e8s BP 102 26802 Portes L\u00e8s Valence",
    "sg:classifiers":[
        {
            "category":"Food & Beverages",
            "subcategory":"Fruits & Vegetables",
            "type":"Retail Goods"
        }
    ],
    "sg:phone":"+33 4 75 57 41 00",
    "sg:province":"Champagne",
    "sg:tags":[
        "preserve",
        "product",
        "related"
    ],
    "wof:name":"Hero France Sa",
    "wof:placetype":"venue"
},
  "geometry": {"coordinates":[4.876899,44.874504],"type":"Point"}
}