{
  "type": "Feature",
  "properties": {
    "iso:country":"FR",
    "sg:address":"route de Richerenches 84600 Valreas",
    "sg:classifiers":[
        {
            "category":"Personal",
            "subcategory":"Shoe Repair & Shine",
            "type":"Services"
        }
    ],
    "sg:phone":"+33 4 90 28 56 00",
    "sg:province":"Basse Normandie",
    "sg:tags":[
        "injection",
        "moulding",
        "plastic"
    ],
    "wof:name":"Ervaf Sa",
    "wof:placetype":"venue"
},
  "geometry": {"coordinates":[4.970619,44.382553],"type":"Point"}
}