{
  "type": "Feature",
  "properties": {
    "addr:full":"189 Boulevard De La Valbarelle 13011 Marseille Poitou-Charentes",
    "addr:housenumber":"189",
    "addr:postcode":"13011",
    "addr:street":"Boulevard De La Valbarelle",
    "iso:country":"FR",
    "sg:address":"189 Boulevard De La Valbarelle 13011 Marseille",
    "sg:classifiers":[
        {
            "category":"Autos & Motor Vehicles",
            "subcategory":"Automobile Sales",
            "type":"Retail Goods"
        }
    ],
    "sg:phone":"+33 4 91 87 61 61",
    "sg:province":"Poitou-Charentes",
    "sg:tags":[
        "equipment",
        "industrial",
        "transport"
    ],
    "wof:name":"Coder Constructeur Sa",
    "wof:placetype":"venue"
},
  "geometry": {"coordinates":[5.437165,43.289322],"type":"Point"}
}