{
  "type": "Feature",
  "properties": {
    "addr:full":"27 \u00e0 33 Grand Place; Arras; 62000 Nord Pas-de-Calais 62000",
    "addr:housenumber":"27 a\u0300 33",
    "addr:postcode":"62000;62000",
    "addr:street":"Grand Place",
    "iso:country":"FR",
    "sg:address":"27 \u00e0 33 Grand Place; Arras; 62000",
    "sg:classifiers":[
        {
            "category":"Banks & Credit Unions",
            "subcategory":"Bank",
            "type":"Services"
        }
    ],
    "sg:phone":"+33 21077575",
    "sg:postcode":"62000",
    "sg:province":"Nord Pas-de-Calais",
    "wof:name":"Cr\u00e9dit Agricole, Du Pas-de-calais",
    "wof:placetype":"venue"
},
  "geometry": {"coordinates":[2.779836,50.292278],"type":"Point"}
}