{
  "type": "Feature",
  "properties": {
    "addr:full":"4 M\u00e9tiers 49130 Sainte Gemmes sur Loire Pays de Loire 49130",
    "addr:housenumber":"4",
    "addr:postcode":"49130;49130",
    "addr:street":"Me\u0301Tiers;Gemmes;Loire",
    "iso:country":"FR",
    "sg:address":"4",
    "sg:city":"M\u00e9tiers 49130 Sainte Gemmes sur Loire",
    "sg:classifiers":[
        {
            "category":"Wholesale",
            "subcategory":"Medical Equipment & Supplies",
            "type":"Manufacturing & Wholesale Goods"
        }
    ],
    "sg:phone":"+33 2 41 66 20 88",
    "sg:postcode":"49130",
    "sg:province":"Pays de Loire",
    "sg:tags":[
        "instrument",
        "health",
        "-",
        "precision"
    ],
    "wof:name":"Cidelec",
    "wof:placetype":"venue"
},
  "geometry": {"coordinates":[-0.56494,47.424984],"type":"Point"}
}