{
  "type": "Feature",
  "properties": {
    "addr:full":"44 Rue Lamarck 75018 Paris Ile de France 75018",
    "addr:housenumber":"44",
    "addr:postcode":"75018;75018",
    "addr:street":"Rue Lamarck",
    "iso:country":"FR",
    "sg:address":"44 Rue Lamarck 75018 Paris",
    "sg:classifiers":[
        {
            "category":"Professional",
            "subcategory":"Engineering",
            "type":"Services"
        }
    ],
    "sg:phone":"+33 1 42 57 11 25",
    "sg:postcode":"75018",
    "sg:province":"Ile de France",
    "sg:tags":[
        "machine",
        "-",
        "mechanical"
    ],
    "wof:name":"Zehnder Sas",
    "wof:placetype":"venue"
},
  "geometry": {"coordinates":[2.34291,48.889229],"type":"Point"}
}