{
  "type": "Feature",
  "properties": {
    "addr:full":"13 Rue Lamartine 13500 Martigues Provence-Alpes-C\u00f4te d'Azur",
    "addr:housenumber":"13",
    "addr:postcode":"13500",
    "addr:street":"Rue Lamartine",
    "iso:country":"FR",
    "sg:address":"13 Rue Lamartine 13500 Martigues",
    "sg:classifiers":[
        {
            "category":"Professional",
            "subcategory":"Printing & Photocopies",
            "type":"Services"
        }
    ],
    "sg:phone":"+33 4 42 07 20 33",
    "sg:province":"Provence-Alpes-C\u00f4te d'Azur",
    "sg:tags":[
        "publishing"
    ],
    "wof:name":"Regicom",
    "wof:placetype":"venue"
},
  "geometry": {"coordinates":[5.055254,43.40313],"type":"Point"}
}