{
  "type": "Feature",
  "properties": {
    "addr:full":"2, Rue Maladrie, 88210 Hurbache Lorraine",
    "addr:housenumber":"2",
    "addr:postcode":"88210",
    "addr:street":"Rue Maladrie",
    "iso:country":"FR",
    "sg:address":"2, Rue Maladrie, 88210 Hurbache",
    "sg:orig_category":"Unclassifiable Establishments",
    "sg:phone":"+33 3 29 58 97 53",
    "sg:province":"Lorraine",
    "wof:name":"Maurice G\u00e9rard Et Fils S.a.r.l.",
    "wof:placetype":"venue"
},
  "geometry": {"coordinates":[6.932147,48.34914],"type":"Point"}
}