{
  "type": "Feature",
  "properties": {
    "addr:full":"ZA Nurieux Volognat Rhone-Alpes 01460",
    "addr:postcode":"01460",
    "addr:street":"Za;Rhone-Alpes",
    "iso:country":"FR",
    "sg:address":"ZA",
    "sg:city":"Nurieux Volognat",
    "sg:orig_category":"Non-Classified Establishments",
    "sg:phone":"+33 4 74 76 21 76",
    "sg:postcode":"01460",
    "sg:province":"Rhone-Alpes",
    "wof:name":"Heyr Moules S.a.r.l.",
    "wof:placetype":"venue"
},
  "geometry": {"coordinates":[5.55338,46.177399],"type":"Point"}
}