{
  "type": "Feature",
  "properties": {
    "iso:country":"FR",
    "sg:address":"B.P. 50291, 95958 Roissy Charles de Gaulle^^22, Av. des Nations - B\u00e2t. le Raspail, 93420 Villepinte",
    "sg:orig_category":"Non-Classified Establishments",
    "sg:phone":"+33 1 49 89 72 00",
    "sg:postcode":"93420",
    "sg:province":"Ile de France",
    "wof:name":"Datacard S.a.",
    "wof:placetype":"venue"
},
  "geometry": {"coordinates":[2.53979,48.955807],"type":"Point"}
}