{
  "type": "Feature",
  "properties": {
    "iso:country":"FR",
    "sg:address":"Lieu Dit Gres 12220 Galgan",
    "sg:classifiers":[
        {
            "category":"Manufacturing",
            "subcategory":"Wood Products",
            "type":"Manufacturing & Wholesale Goods"
        }
    ],
    "sg:phone":"+33 5 65 80 40 46",
    "sg:province":"Midi Pyr\u00e9n\u00e9es",
    "sg:tags":[
        "furniture"
    ],
    "wof:name":"Sc 12",
    "wof:placetype":"venue"
},
  "geometry": {"coordinates":[2.190295,44.523407],"type":"Point"}
}