{
  "type": "Feature",
  "properties": {
    "iso:country":"FR",
    "sg:address":"47 Rue Eug\u00e8ne Berthoud 93400 St Ouen",
    "sg:classifiers":[
        {
            "category":"Home & Garden",
            "subcategory":"Furniture",
            "type":"Retail Goods"
        }
    ],
    "sg:phone":"+33 1 49 48 13 60",
    "sg:province":"Ile de France",
    "sg:tags":[
        "wood"
    ],
    "wof:name":"Marotte Et Cie Sa",
    "wof:placetype":"venue"
},
  "geometry": {"coordinates":[2.347687,48.90543],"type":"Point"}
}