{
  "type": "Feature",
  "properties": {
    "iso:country":"FR",
    "sg:address":"11 bis, Rue de Nantes, 44140 La Planche",
    "sg:orig_category":"Unclassifiable Establishments",
    "sg:phone":"+33 2 40 31 94 01",
    "sg:province":"Pays de Loire",
    "wof:name":"Sud Loire Confection S.a.",
    "wof:placetype":"venue"
},
  "geometry": {"coordinates":[-1.435424,47.016773],"type":"Point"}
}