{
  "type": "Feature",
  "properties": {
    "iso:country":"FR",
    "sg:address":"Zi Du Ch\u00eane Maillard",
    "sg:city":"Saran",
    "sg:classifiers":[
        {
            "category":"Professional",
            "subcategory":"Computer Services",
            "type":"Services"
        }
    ],
    "sg:phone":"+33 2 38 73 50 12",
    "sg:postcode":"45770",
    "sg:province":"Centre",
    "sg:tags":[
        "information",
        "technology",
        "software"
    ],
    "wof:name":"Mikros Groupe Aspheria Sa",
    "wof:placetype":"venue"
},
  "geometry": {"coordinates":[1.90868,47.948238],"type":"Point"}
}