{
  "type": "Feature",
  "properties": {
    "iso:country":"FR",
    "sg:address":"2, Rue de la Tour des Dames, 75009 Paris",
    "sg:orig_category":"Unclassifiable Establishments",
    "sg:phone":"+33 1 48 78 82 82",
    "sg:province":"Ile de France",
    "wof:name":"Sonepar Distribution",
    "wof:placetype":"venue"
},
  "geometry": {"coordinates":[2.333981,48.877872],"type":"Point"}
}