{
  "type": "Feature",
  "properties": {
    "addr:full":"Parc des Platanes; BP 185; ANNONAY; 07104 CEDEX Annonay Rhone-Alpes 07100",
    "addr:housenumber":"185",
    "addr:postcode":"07104 cedex;07100",
    "addr:street":"Parc Des Platanes Bp",
    "iso:country":"FR",
    "sg:address":"Parc des Platanes; BP 185; ANNONAY; 07104 CEDEX",
    "sg:city":"Annonay",
    "sg:classifiers":[
        {
            "category":"Shopping",
            "subcategory":"Computers & Home Electronics",
            "type":"Retail Goods"
        }
    ],
    "sg:phone":"+33 4 75 69 27 27",
    "sg:postcode":"07100",
    "sg:province":"Rhone-Alpes",
    "sg:tags":[
        "chamber",
        "commerce"
    ],
    "wof:name":"La Chambre De Commerce Et D'industrie D'annonay",
    "wof:placetype":"venue"
},
  "geometry": {"coordinates":[4.66843,45.240349],"type":"Point"}
}