{
  "type": "Feature",
  "properties": {
    "addr:full":"7, Rue du Champ aux Pr\u00eatres - ZAE Cap Nord, 21000 Dijon Dijon Bourgogne 21000",
    "addr:housenumber":"7",
    "addr:postcode":"21000;21000",
    "addr:street":"Rue Du Champ Aux Pre\u0302Tres Zae Cap Nord",
    "iso:country":"FR",
    "sg:address":"7, Rue du Champ aux Pr\u00eatres - ZAE Cap Nord, 21000 Dijon",
    "sg:city":"Dijon",
    "sg:orig_category":"Unclassifiable Establishments",
    "sg:phone":"+33 3 80 73 44 25",
    "sg:postcode":"21000",
    "sg:province":"Bourgogne",
    "wof:name":"Acrem S.a.",
    "wof:placetype":"venue"
},
  "geometry": {"coordinates":[5.075567,47.344116],"type":"Point"}
}