{
  "type": "Feature",
  "properties": {
    "addr:full":"Au Dessus Des Lisses Zi 02140 Vervins Picardie 02140",
    "addr:postcode":"02140;02140",
    "addr:street":"Au Dessus Des Lisses Zi;Picardie",
    "iso:country":"FR",
    "sg:address":"Au Dessus Des Lisses Zi 02140 Vervins",
    "sg:classifiers":[
        {
            "category":"Professional",
            "subcategory":"Engineering",
            "type":"Services"
        }
    ],
    "sg:phone":"+33 3 23 98 87 18",
    "sg:postcode":"02140",
    "sg:province":"Picardie",
    "sg:tags":[
        "machine",
        "-",
        "mechanical"
    ],
    "wof:name":"Quadra Nord",
    "wof:placetype":"venue"
},
  "geometry": {"coordinates":[3.91817,49.828499],"type":"Point"}
}