{
  "type": "Feature",
  "properties": {
    "addr:full":"Les Baraques 42610 Saint Romain le Puy Rhone-Alpes",
    "addr:postcode":"42610",
    "addr:street":"Baraques;Romain Le",
    "iso:country":"FR",
    "sg:address":"Les Baraques 42610 Saint Romain le Puy",
    "sg:orig_category":"Unclassifiable Establishments",
    "sg:phone":"+33 4 77 76 61 36",
    "sg:province":"Rhone-Alpes",
    "wof:name":"Soreca S.a.",
    "wof:placetype":"venue"
},
  "geometry": {"coordinates":[4.1317,45.570114],"type":"Point"}
}