{
  "type": "Feature",
  "properties": {
    "addr:full":"44, Rue Maurice de Broglie, 93605 Aulnay sous Bois C\u00e9dex Champagne",
    "addr:housenumber":"44",
    "addr:postcode":"93605",
    "addr:street":"Rue Maurice De Broglie",
    "iso:country":"FR",
    "sg:address":"44, Rue Maurice de Broglie, 93605 Aulnay sous Bois C\u00e9dex",
    "sg:orig_category":"Non-Classified Establishments",
    "sg:phone":"+33 1 48 66 07 17",
    "sg:province":"Champagne",
    "wof:name":"D.c.m. Friesland S.a.r.l.",
    "wof:placetype":"venue"
},
  "geometry": {"coordinates":[2.48245,48.946171],"type":"Point"}
}