{
  "type": "Feature",
  "properties": {
    "iso:country":"FR",
    "sg:address":"32 Av De L'Europe Energie I 78140 Velizy Villacoublay",
    "sg:classifiers":[
        {
            "category":"Home & Garden",
            "subcategory":"Furniture",
            "type":"Retail Goods"
        }
    ],
    "sg:phone":"+33 1 39 45 67 50",
    "sg:province":"Ile de France",
    "sg:tags":[
        "wood"
    ],
    "wof:name":"Polyrey",
    "wof:placetype":"venue"
},
  "geometry": {"coordinates":[2.19556,48.783909],"type":"Point"}
}