{
  "type": "Feature",
  "properties": {
    "iso:country":"FR",
    "sg:address":"85300 Challans",
    "sg:orig_category":"Unclassifiable Establishments",
    "sg:phone":"+33 2 51 93 13 21",
    "sg:province":"Pays de Loire",
    "wof:name":"Constructions M\u00e9talliques Arnaudeau S.a.",
    "wof:placetype":"venue"
},
  "geometry": {"coordinates":[-1.88051,46.839779],"type":"Point"}
}