{
  "type": "Feature",
  "properties": {
    "iso:country":"FR",
    "sg:address":"B.P. 23, 31771 Colomiers C\u00e9dex^^12, Chemin Garrabot - Z.I. en Jacca, 31770 Colomiers",
    "sg:orig_category":"Non-Classified Establishments",
    "sg:phone":"+33 5 61 15 93 00",
    "sg:province":"Midi Pyr\u00e9n\u00e9es",
    "wof:name":"Razel-ducler Rogard S.a.",
    "wof:placetype":"venue"
},
  "geometry": {"coordinates":[1.33337,43.612431],"type":"Point"}
}