{
  "type": "Feature",
  "properties": {
    "addr:full":"B.P. 55 Pons C\u00e9dex^^Goutrolles 17800 Pons Poitou-Charentes 17800",
    "addr:postcode":"17800;17800",
    "addr:street":"B.P. 55 Pons Ce\u0301Dex^^Goutrolles",
    "iso:country":"FR",
    "sg:address":"B.P. 55",
    "sg:city":"Pons C\u00e9dex^^Goutrolles 17800 Pons",
    "sg:orig_category":"Non-Classified Establishments",
    "sg:phone":"+33 5 46 94 08 69",
    "sg:postcode":"17800",
    "sg:province":"Poitou-Charentes",
    "wof:name":"Soci\u00e9t\u00e9 Renaud S.a.",
    "wof:placetype":"venue"
},
  "geometry": {"coordinates":[-0.59809,45.51733],"type":"Point"}
}