{
  "type": "Feature",
  "properties": {
    "iso:country":"FR",
    "sg:address":"14 Rue Voltaire 94290 Villeneuve Le Roi",
    "sg:classifiers":[
        {
            "category":"Professional",
            "type":"Services"
        }
    ],
    "sg:phone":"+33 1 49 61 13 13",
    "sg:province":"Ile de France",
    "sg:tags":[
        "transport",
        "road"
    ],
    "wof:name":"Bousquet Pere Et Fils",
    "wof:placetype":"venue"
},
  "geometry": {"coordinates":[2.412912,48.728703],"type":"Point"}
}