{
  "type": "Feature",
  "properties": {
    "iso:country":"FR",
    "sg:address":"1, Rue de la Ferme du Presbyt\u00e8re, 77330 Ozoir la Ferri\u00e8re",
    "sg:orig_category":"Non-Classified Establishments",
    "sg:phone":"+33 1 60 02 95 00",
    "sg:postcode":"77330",
    "sg:province":"Ile de France",
    "wof:name":"Claz S.a.",
    "wof:placetype":"venue"
},
  "geometry": {"coordinates":[2.664284,48.762295],"type":"Point"}
}