{
  "type": "Feature",
  "properties": {
    "addr:full":"21, Rue de l'Industrie, 63300 Thiers Thiers Auvergne 63300",
    "addr:housenumber":"21",
    "addr:postcode":"63300;63300",
    "addr:street":"Rue De L'Industrie",
    "iso:country":"FR",
    "sg:address":"21, Rue de l'Industrie, 63300 Thiers",
    "sg:city":"Thiers",
    "sg:orig_category":"Unclassifiable Establishments",
    "sg:phone":"+33 4 73 51 67 00",
    "sg:postcode":"63300",
    "sg:province":"Auvergne",
    "wof:name":"Compagnie D'etudes Et Plastiques S.a.",
    "wof:placetype":"venue"
},
  "geometry": {"coordinates":[3.555439,45.861668],"type":"Point"}
}