{
  "type": "Feature",
  "properties": {
    "iso:country":"FR",
    "sg:address":"21, Rue de l'Industrie, 63300 Thiers",
    "sg:city":"Thiers",
    "sg:orig_category":"Unclassifiable Establishments",
    "sg:phone":"+33 4 73 51 67 00",
    "sg:postcode":"63300",
    "sg:province":"Auvergne",
    "wof:name":"Compagnie D'etudes Et Plastiques S.a.",
    "wof:placetype":"venue"
},
  "geometry": {"coordinates":[3.555439,45.861668],"type":"Point"}
}