{
  "type": "Feature",
  "properties": {
    "addr:full":"Kerjoly 29430 Plouescat Plouescat Bretagne 29430",
    "addr:postcode":"29430;plouescat;29430",
    "addr:street":"Kerjoly",
    "iso:country":"FR",
    "sg:address":"Kerjoly 29430 Plouescat",
    "sg:city":"Plouescat",
    "sg:classifiers":[
        {
            "category":"Manufacturing",
            "subcategory":"Food",
            "type":"Manufacturing & Wholesale Goods"
        }
    ],
    "sg:phone":"+33 2 98 69 84 45",
    "sg:postcode":"29430",
    "sg:province":"Bretagne",
    "sg:tags":[
        "preserve",
        "product",
        "related"
    ],
    "wof:name":"Brossier Joel",
    "wof:placetype":"venue"
},
  "geometry": {"coordinates":[-4.17841,48.662148],"type":"Point"}
}