{
  "type": "Feature",
  "properties": {
    "addr:full":"11, Rte de Nonancourt, 27810 Marcilly sur Eure Haute Normandie",
    "addr:housenumber":"11",
    "addr:postcode":"27810",
    "addr:street":"Rte De Nonancourt;Haute Normandie",
    "iso:country":"FR",
    "sg:address":"11, Rte de Nonancourt, 27810 Marcilly sur Eure",
    "sg:orig_category":"Non-Classified Establishments",
    "sg:phone":"+33 2 37 62 52 40",
    "sg:province":"Haute Normandie",
    "wof:name":"Perfect Circle Europe S.a.",
    "wof:placetype":"venue"
},
  "geometry": {"coordinates":[1.346705,48.825539],"type":"Point"}
}