{
  "type": "Feature",
  "properties": {
    "addr:full":"7, Rue de Strasbourg, 77400 Lagny sur Marne Ile de France",
    "addr:housenumber":"7",
    "addr:postcode":"77400",
    "addr:street":"Rue De Strasbourg",
    "iso:country":"FR",
    "sg:address":"7, Rue de Strasbourg, 77400 Lagny sur Marne",
    "sg:orig_category":"Unclassifiable Establishments",
    "sg:phone":"+33 1 64 30 36 05",
    "sg:province":"Ile de France",
    "wof:name":"Gaillat S.n.f. S.a.r.l. - Soci\u00e9t\u00e9 Nouvelle Fran\u00e7ois",
    "wof:placetype":"venue"
},
  "geometry": {"coordinates":[2.691539,48.879242],"type":"Point"}
}