{
  "type": "Feature",
  "properties": {
    "iso:country":"FR",
    "sg:address":"46, Rue Breteuil, 13006 Marseille",
    "sg:orig_category":"Unclassifiable Establishments",
    "sg:phone":"+33 4 91 37 16 00",
    "sg:province":"Poitou-Charentes",
    "wof:name":"Tempier Et Fils S.a.",
    "wof:placetype":"venue"
},
  "geometry": {"coordinates":[5.376213,43.289047],"type":"Point"}
}