{
  "type": "Feature",
  "properties": {
    "addr:full":"59, Rte de M\u00e9r\u00e9ville, 91690 Saclas Ile de France",
    "addr:housenumber":"59",
    "addr:postcode":"91690;ile",
    "addr:street":"Rte De Me\u0301Re\u0301Ville",
    "iso:country":"FR",
    "sg:address":"59, Rte de M\u00e9r\u00e9ville, 91690 Saclas",
    "sg:orig_category":"Unclassifiable Establishments",
    "sg:phone":"+33 1 64 94 07 44",
    "sg:province":"Ile de France",
    "wof:name":"Soci\u00e9t\u00e9 Samson S.a.r.l.",
    "wof:placetype":"venue"
},
  "geometry": {"coordinates":[2.113887,48.348274],"type":"Point"}
}