{
  "type": "Feature",
  "properties": {
    "addr:full":"34 Rue Principale 57570 Puttelange Les Thionville Lorraine 57570",
    "addr:housenumber":"34",
    "addr:postcode":"57570;57570",
    "addr:street":"Rue Principale;Puttelange",
    "iso:country":"FR",
    "sg:address":"34 Rue Principale 57570 Puttelange Les Thionville",
    "sg:classifiers":[
        {
            "category":"Manufacturing",
            "subcategory":"Metals",
            "type":"Manufacturing & Wholesale Goods"
        }
    ],
    "sg:phone":"+33 3 82 51 20 17",
    "sg:postcode":"57570",
    "sg:province":"Lorraine",
    "sg:tags":[
        "metallurgy",
        "metalworking"
    ],
    "wof:name":"Travaux Industriels Lorrains Trainlor",
    "wof:placetype":"venue"
},
  "geometry": {"coordinates":[6.237612,49.491512],"type":"Point"}
}