{
  "type": "Feature",
  "properties": {
    "addr:full":"6 rte K\u00e9rogan; Quimper Aquitaine",
    "addr:housenumber":"6",
    "addr:street":"Rte Ke\u0301Rogan",
    "iso:country":"FR",
    "sg:address":"6 rte K\u00e9rogan; Quimper",
    "sg:classifiers":[
        {
            "category":"Banks & Credit Unions",
            "subcategory":"Bank",
            "type":"Services"
        }
    ],
    "sg:phone":"+33 3398520610",
    "sg:province":"Aquitaine",
    "wof:name":"Cr\u00e9dit Agricole Mutuel, Agence Entreprises",
    "wof:placetype":"venue"
},
  "geometry": {"coordinates":[-4.096228,47.973183],"type":"Point"}
}