{
  "type": "Feature",
  "properties": {
    "addr:full":"Z I de Montbertrand 38230 CHARVIEU CHAVAGNEUX Rhone-Alpes 38230",
    "addr:postcode":"38230;38230",
    "addr:street":"Z I De Montbertrand;Rhone-Alpes",
    "iso:country":"FR",
    "sg:address":"Z I de Montbertrand 38230 CHARVIEU CHAVAGNEUX",
    "sg:orig_category":"Fruits, Dried",
    "sg:phone":"+33 4 37 42 70 00",
    "sg:postcode":"38230",
    "sg:province":"Rhone-Alpes",
    "wof:name":"Benoit Snc",
    "wof:placetype":"venue"
},
  "geometry": {"coordinates":[5.160112,45.745178],"type":"Point"}
}