{
  "type": "Feature",
  "properties": {
    "iso:country":"FR",
    "sg:address":"Av De La Vall\u00e9e D'Ossau 64121 Serres Castet",
    "sg:city":"Montardon",
    "sg:classifiers":[
        {
            "category":"Professional",
            "subcategory":"Engineering",
            "type":"Services"
        }
    ],
    "sg:phone":"+33 5 59 33 78 44",
    "sg:postcode":"64121",
    "sg:province":"Aquitaine",
    "sg:tags":[
        "machine",
        "-",
        "mechanical"
    ],
    "wof:name":"Societe Europeenne De Mecanique Societe Nouvelle Societe Europeenne Demecanique",
    "wof:placetype":"venue"
},
  "geometry": {"coordinates":[-0.3603,43.37347],"type":"Point"}
}