{
  "type": "Feature",
  "properties": {
    "iso:country":"FR",
    "sg:address":"21 Rue Fontgieve; Clermont Ferrand; 63000",
    "sg:city":"Clermont-Ferrand",
    "sg:classifiers":[
        {
            "category":"Banks & Credit Unions",
            "subcategory":"Bank",
            "type":"Services"
        }
    ],
    "sg:phone":"+33 4 73 37 20 22",
    "sg:postcode":"63000",
    "sg:province":"Auvergne",
    "wof:name":"Banque Franco, Portugaise Sa",
    "wof:placetype":"venue"
},
  "geometry": {"coordinates":[3.080574,45.780701],"type":"Point"}
}