{
  "type": "Feature",
  "properties": {
    "addr:full":"4, Rue Fr\u00e9d\u00e9rick Passy, 69100 Villeurbanne Rhone-Alpes 69100",
    "addr:housenumber":"4",
    "addr:postcode":"69100;69100",
    "addr:street":"Rue Fre\u0301De\u0301Rick",
    "iso:country":"FR",
    "sg:address":"4, Rue Fr\u00e9d\u00e9rick Passy, 69100 Villeurbanne",
    "sg:orig_category":"Unclassifiable Establishments",
    "sg:phone":"+33 4 72 65 91 91",
    "sg:postcode":"69100",
    "sg:province":"Rhone-Alpes",
    "wof:name":"E.m.g. S.a.r.l. - Electro Mechanic Games",
    "wof:placetype":"venue"
},
  "geometry": {"coordinates":[4.875555,45.760681],"type":"Point"}
}