{
  "type": "Feature",
  "properties": {
    "addr:full":"Rue Des Pommiers 39100 Gevry Franche Comt\u00e9 39100",
    "addr:postcode":"39100;39100",
    "addr:street":"Rue Des Pommiers;Franche Comte\u0301",
    "iso:country":"FR",
    "sg:address":"Rue Des Pommiers 39100 Gevry",
    "sg:classifiers":[
        {
            "category":"Manufacturing",
            "subcategory":"Aerospace",
            "type":"Manufacturing & Wholesale Goods"
        }
    ],
    "sg:phone":"+33 3 84 71 01 99",
    "sg:postcode":"39100",
    "sg:province":"Franche Comt\u00e9",
    "sg:tags":[
        "equipment",
        "aeronautic",
        "transport",
        "vehicle"
    ],
    "wof:name":"Jolliet Electronique- Radiomaster",
    "wof:placetype":"venue"
},
  "geometry": {"coordinates":[5.440367,47.038807],"type":"Point"}
}