{
  "type": "Feature",
  "properties": {
    "addr:full":"2, Rte du Wahlweg - Z.I., 68310 Wittelsheim Wittelsheim Alsace 68310",
    "addr:housenumber":"2",
    "addr:postcode":"68310;68310",
    "addr:street":"Rte Du Wahlweg",
    "iso:country":"FR",
    "sg:address":"2, Rte du Wahlweg - Z.I., 68310 Wittelsheim",
    "sg:city":"Wittelsheim",
    "sg:orig_category":"Non-Classified Establishments",
    "sg:phone":"+33 3 89 55 14 36",
    "sg:postcode":"68310",
    "sg:province":"Alsace",
    "wof:name":"S.n.i.g. Est S.n.c.",
    "wof:placetype":"venue"
},
  "geometry": {"coordinates":[7.240633,47.810478],"type":"Point"}
}