{
  "type": "Feature",
  "properties": {
    "addr:full":"Z.I. de Labeillye 38780 PONT EVEQUE Rhone-Alpes",
    "addr:postcode":"38780",
    "addr:street":"Z.I.;Pont Eveque Rhone-Alpes",
    "iso:country":"FR",
    "sg:address":"Z.I. de Labeillye 38780 PONT EVEQUE",
    "sg:classifiers":[
        {
            "category":"Banks & Credit Unions",
            "subcategory":"Investment Brokerage",
            "type":"Services"
        }
    ],
    "sg:phone":"+33 4 74 16 11 00",
    "sg:province":"Rhone-Alpes",
    "sg:tags":[
        "packaging",
        "polypropylene",
        "pp"
    ],
    "wof:name":"Primasacs S.a.",
    "wof:placetype":"venue"
},
  "geometry": {"coordinates":[4.999713,45.473324],"type":"Point"}
}