{
  "type": "Feature",
  "properties": {
    "addr:full":"B.P. 6, 08140 Douzy^^Rte Francheval, 08140 Douzy Champagne",
    "addr:housenumber":"6",
    "addr:postcode":"08140;08140",
    "addr:street":"B.P.",
    "iso:country":"FR",
    "sg:address":"B.P. 6, 08140 Douzy^^Rte Francheval, 08140 Douzy",
    "sg:orig_category":"Non-Classified Establishments",
    "sg:phone":"+33 3 24 26 30 98",
    "sg:province":"Champagne",
    "wof:name":"Forges De Magne S.a.",
    "wof:placetype":"venue"
},
  "geometry": {"coordinates":[5.02497,49.68927],"type":"Point"}
}