{
  "type": "Feature",
  "properties": {
    "iso:country":"FR",
    "sg:address":"ZAC des Bamardes",
    "sg:city":"Valdahon",
    "sg:orig_category":"Unclassifiable Establishments",
    "sg:phone":"+33 3 81 56 34 34",
    "sg:postcode":"25800",
    "sg:province":"Franche Comt\u00e9",
    "wof:name":"Les Eleveurs De La Chevillotte",
    "wof:placetype":"venue"
},
  "geometry": {"coordinates":[6.346255,47.147182],"type":"Point"}
}