{
  "type": "Feature",
  "properties": {
    "iso:country":"FR",
    "sg:address":"99 Rue De Talant 21000 Dijon",
    "sg:city":"Dijon",
    "sg:classifiers":[
        {
            "category":"Professional",
            "subcategory":"Business Services",
            "type":"Services"
        }
    ],
    "sg:phone":"+33 3 80 58 33 43",
    "sg:postcode":"21000",
    "sg:province":"Bourgogne",
    "sg:tags":[
        "training",
        "advice"
    ],
    "wof:name":"Nouvelle Assoc Educat Populai St-benigne",
    "wof:placetype":"venue"
},
  "geometry": {"coordinates":[5.016266,47.330688],"type":"Point"}
}