{
  "type": "Feature",
  "properties": {
    "iso:country":"FR",
    "sg:address":"6 Rue Barb\u00e8s 92305 Levallois Perret",
    "sg:classifiers":[
        {
            "category":"Manufacturing",
            "subcategory":"Chemicals & Compounds",
            "type":"Manufacturing & Wholesale Goods"
        }
    ],
    "sg:phone":"+33 1 41 34 14 00",
    "sg:province":"Limousin",
    "sg:tags":[
        "pharmaceutical",
        "chemistry"
    ],
    "wof:name":"Protex International",
    "wof:placetype":"venue"
},
  "geometry": {"coordinates":[2.280933,48.889862],"type":"Point"}
}