{
  "type": "Feature",
  "properties": {
    "addr:full":"22, Rue Th\u00e9ron de Montaug\u00e9 - ZI, 31200 Toulouse Midi Pyr\u00e9n\u00e9es 31200",
    "addr:housenumber":"22",
    "addr:postcode":"31200;31200",
    "addr:street":"Rue The\u0301Ron De Montauge\u0301 Zi",
    "iso:country":"FR",
    "sg:address":"22, Rue Th\u00e9ron de Montaug\u00e9 - ZI, 31200 Toulouse",
    "sg:orig_category":"Non-Classified Establishments",
    "sg:phone":"+33 5 61 48 73 11",
    "sg:postcode":"31200",
    "sg:province":"Midi Pyr\u00e9n\u00e9es",
    "wof:name":"Elemotac S.a.",
    "wof:placetype":"venue"
},
  "geometry": {"coordinates":[1.48376,43.635216],"type":"Point"}
}