{
  "type": "Feature",
  "properties": {
    "iso:country":"FR",
    "sg:address":"31, Bd des Saulniers, 35370 Argentr\u00e9 du Plessis",
    "sg:city":"Argentr\u00e9-du-Plessis",
    "sg:orig_category":"Non-Classified Establishments",
    "sg:phone":"+33 2 99 96 60 47",
    "sg:postcode":"35370",
    "sg:province":"Bretagne",
    "wof:name":"Sicoma Menuiserie S.a.s.",
    "wof:placetype":"venue"
},
  "geometry": {"coordinates":[-1.163008,48.056709],"type":"Point"}
}