{
  "type": "Feature",
  "properties": {
    "addr:full":"Grande Rue Gy Franche Comt\u00e9 70700",
    "addr:postcode":"70700",
    "addr:street":"Grande Rue Gy Franche Comte\u0301",
    "iso:country":"FR",
    "sg:address":"Grande Rue",
    "sg:city":"Gy",
    "sg:orig_category":"Non-Classified Establishments",
    "sg:phone":"+33 3 84 32 86 22",
    "sg:postcode":"70700",
    "sg:province":"Franche Comt\u00e9",
    "wof:name":"Imprimerie Du Ch\u00e2teau S.a.r.l.",
    "wof:placetype":"venue"
},
  "geometry": {"coordinates":[5.80929,47.404018],"type":"Point"}
}