{
  "type": "Feature",
  "properties": {
    "iso:country":"FR",
    "sg:address":"B.P. 1213, 68012 Colmar C\u00e9dex^^7, Rue Pierre Curie - Zone Industrielle Nord, 68000 Colmar",
    "sg:city":"Colmar",
    "sg:orig_category":"Non-Classified Establishments",
    "sg:phone":"+33 3 89 23 05 75",
    "sg:postcode":"68000",
    "sg:province":"Alsace",
    "wof:name":"Eglinsdoerfer Pfohl S.a.",
    "wof:placetype":"venue"
},
  "geometry": {"coordinates":[7.363583,48.081985],"type":"Point"}
}