{
  "type": "Feature",
  "properties": {
    "addr:full":"Av. de la M\u00e9rindole - ZI de la Grand'Colle Port de Bouc Centre 13110",
    "addr:postcode":"13110",
    "addr:street":"Av. De La Me\u0301Rindole Zi De La Grand'Colle Port De Bouc",
    "iso:country":"FR",
    "sg:address":"Av. de la M\u00e9rindole - ZI de la Grand'Colle",
    "sg:city":"Port de Bouc",
    "sg:orig_category":"Non-Classified Establishments",
    "sg:phone":"+33 4 42 40 19 50",
    "sg:postcode":"13110",
    "sg:province":"Centre",
    "wof:name":"B\u00e9c\u00e9ma",
    "wof:placetype":"venue"
},
  "geometry": {"coordinates":[4.99928,43.42075],"type":"Point"}
}