{
  "type": "Feature",
  "properties": {
    "iso:country":"FR",
    "sg:address":"B.P. 523, 77465 Lagny sur Marne C\u00e9dex^^57, Rue Jacquard, 77400 Lagny sur Marne",
    "sg:orig_category":"Non-Classified Establishments",
    "sg:phone":"+33 1 64 30 91 36",
    "sg:province":"Ile de France",
    "wof:name":"Woodhead S.a.",
    "wof:placetype":"venue"
},
  "geometry": {"coordinates":[2.701485,48.87775],"type":"Point"}
}