{
  "type": "Feature",
  "properties": {
    "iso:country":"FR",
    "sg:address":"75 rue de Gerland 69007 Lyon",
    "sg:classifiers":[
        {
            "category":"Professional",
            "subcategory":"Employment Agencies",
            "type":"Services"
        }
    ],
    "sg:phone":"+33 4 72 71 91 48",
    "sg:postcode":"69007",
    "sg:province":"Rhone-Alpes",
    "sg:tags":[
        "silk",
        "neckerchief"
    ],
    "wof:name":"Maison Jean Minodier Sarl",
    "wof:placetype":"venue"
},
  "geometry": {"coordinates":[4.839916,45.737625],"type":"Point"}
}