{
  "type": "Feature",
  "properties": {
    "addr:full":"22, Rue de Cornulier, 44000 Nantes Pays de Loire",
    "addr:housenumber":"22",
    "addr:postcode":"44000",
    "addr:street":"Rue De Cornulier",
    "iso:country":"FR",
    "sg:address":"22, Rue de Cornulier, 44000 Nantes",
    "sg:orig_category":"Unclassifiable Establishments",
    "sg:phone":"+33 2 40 35 02 00",
    "sg:province":"Pays de Loire",
    "wof:name":"Jallais S.a.",
    "wof:placetype":"venue"
},
  "geometry": {"coordinates":[-1.540323,47.215141],"type":"Point"}
}