{
  "type": "Feature",
  "properties": {
    "iso:country":"FR",
    "sg:address":"9 avenue de Friedland 75008 Paris",
    "sg:classifiers":[
        {
            "category":"Building & Trades",
            "subcategory":"Electrical",
            "type":"Services"
        }
    ],
    "sg:phone":"+33 1 58 36 44 80",
    "sg:postcode":"75008",
    "sg:province":"Ile de France",
    "sg:tags":[
        "industry",
        "promotion"
    ],
    "wof:name":"Centre Fran\u00e7ais De L'electricit\u00e9",
    "wof:placetype":"venue"
},
  "geometry": {"coordinates":[2.303974,48.87447],"type":"Point"}
}