{
  "type": "Feature",
  "properties": {
    "addr:full":"10 Rue Sigmund Freud 69512 Vaulx En Velin Cedex Haute Normandie",
    "addr:housenumber":"10",
    "addr:postcode":"69512",
    "addr:street":"Rue Sigmund Freud",
    "iso:country":"FR",
    "sg:address":"10 Rue Sigmund Freud 69512 Vaulx En Velin Cedex",
    "sg:classifiers":[
        {
            "category":"Manufacturing",
            "subcategory":"Wood Products",
            "type":"Manufacturing & Wholesale Goods"
        }
    ],
    "sg:phone":"+33 4 72 04 58 55",
    "sg:province":"Haute Normandie",
    "sg:tags":[
        "furniture"
    ],
    "wof:name":"Psa Amenagement",
    "wof:placetype":"venue"
},
  "geometry": {"coordinates":[4.926787,45.773037],"type":"Point"}
}