{
  "type": "Feature",
  "properties": {
    "addr:full":"ZI de Monplaisir Pont Ev\u00eaque Rhone-Alpes 38780",
    "addr:postcode":"38780",
    "addr:street":"Zi De Monplaisir Pont Eve\u0302Que Rhone-Alpes",
    "iso:country":"FR",
    "sg:address":"ZI de Monplaisir",
    "sg:city":"Pont Ev\u00eaque",
    "sg:orig_category":"Unclassifiable Establishments",
    "sg:phone":"+33 4 74 57 20 00",
    "sg:postcode":"38780",
    "sg:province":"Rhone-Alpes",
    "wof:name":"R.2.r. S.a.",
    "wof:placetype":"venue"
},
  "geometry": {"coordinates":[4.911707,45.530884],"type":"Point"}
}