{
  "type": "Feature",
  "properties": {
    "addr:full":"416 rue du G\u00e9n\u00e9ral Andrea 01100 Arbent Rhone-Alpes 01100",
    "addr:housenumber":"416",
    "addr:postcode":"01100;01100",
    "addr:street":"Rue Du Ge\u0301Ne\u0301Ral Andrea;Rhone-Alpes",
    "iso:country":"FR",
    "sg:address":"416 rue du G\u00e9n\u00e9ral Andrea 01100 Arbent",
    "sg:classifiers":[
        {
            "category":"Manufacturing",
            "subcategory":"Wood Products",
            "type":"Manufacturing & Wholesale Goods"
        }
    ],
    "sg:phone":"+33 4 74 77 22 13",
    "sg:postcode":"01100",
    "sg:province":"Rhone-Alpes",
    "sg:tags":[
        "pallet",
        "made"
    ],
    "wof:name":"Richpal Sarl",
    "wof:placetype":"venue"
},
  "geometry": {"coordinates":[5.67727,46.292881],"type":"Point"}
}