{
  "type": "Feature",
  "properties": {
    "iso:country":"FR",
    "sg:address":"17 ave Gambetta; Bourgoin Jallieu; 38300",
    "sg:classifiers":[
        {
            "category":"Banks & Credit Unions",
            "subcategory":"Bank",
            "type":"Services"
        }
    ],
    "sg:phone":"+33 3374930309",
    "sg:postcode":"38300",
    "sg:province":"Rhone-Alpes",
    "wof:name":"Soci\u00e9t\u00e9 G\u00e9n\u00e9rale",
    "wof:placetype":"venue"
},
  "geometry": {"coordinates":[5.272967,45.586449],"type":"Point"}
}