{
  "type": "Feature",
  "properties": {
    "iso:country":"FR",
    "sg:address":"Chateau Angelus 33330 St Emilion",
    "sg:city":"Saint-\u00c9tienne-de-Lisse",
    "sg:classifiers":[
        {
            "category":"Food Court",
            "type":"Food & Drink"
        }
    ],
    "sg:phone":"+33 5 57 24 71 39",
    "sg:postcode":"33330",
    "sg:province":"Aquitaine",
    "sg:tags":[
        "product",
        "related"
    ],
    "wof:name":"Chateau Angelus Sa",
    "wof:placetype":"venue"
},
  "geometry": {"coordinates":[-0.156634,44.892399],"type":"Point"}
}