{
  "type": "Feature",
  "properties": {
    "iso:country":"FR",
    "sg:address":"Rue Du 11 Novembre 28210 Nogent Le Roi",
    "sg:city":"Br\u00e9champs",
    "sg:classifiers":[
        {
            "category":"Professional",
            "subcategory":"Business Services",
            "type":"Services"
        }
    ],
    "sg:phone":"+33 2 37 51 45 32",
    "sg:postcode":"28210",
    "sg:province":"Centre",
    "sg:tags":[
        "training",
        "advice"
    ],
    "wof:name":"College Jean Moulin",
    "wof:placetype":"venue"
},
  "geometry": {"coordinates":[1.518435,48.645241],"type":"Point"}
}