{
  "type": "Feature",
  "properties": {
    "iso:country":"FR",
    "sg:address":"19 Quai De Juillet 14000 Caen",
    "sg:city":"Caen",
    "sg:classifiers":[
        {
            "category":"Professional",
            "subcategory":"Printing & Photocopies",
            "type":"Services"
        }
    ],
    "sg:phone":"+33 2 31 70 88 18",
    "sg:postcode":"14000",
    "sg:province":"Basse Normandie",
    "sg:tags":[
        "publishing"
    ],
    "wof:name":"Societe Agricole D'edition Et De Communication De Normandie (saecno)",
    "wof:placetype":"venue"
},
  "geometry": {"coordinates":[-0.354286,49.178158],"type":"Point"}
}