{
  "type": "Feature",
  "properties": {
    "addr:full":"B.P. 14, 62801 Li\u00e9vin C\u00e9dex^^Rue Jacob - Zone Industrielle, 62800 Li\u00e9vin Nord Pas-de-Calais",
    "addr:postcode":"62801;62800",
    "addr:street":"B.P. 14;Jacob Zone Industrielle",
    "iso:country":"FR",
    "sg:address":"B.P. 14, 62801 Li\u00e9vin C\u00e9dex^^Rue Jacob - Zone Industrielle, 62800 Li\u00e9vin",
    "sg:orig_category":"Non-Classified Establishments",
    "sg:phone":"+33 3 21 72 76 40",
    "sg:province":"Nord Pas-de-Calais",
    "wof:name":"S.m.a. S.a.r.l. - Serrurerie M\u00e9tallerie De L'artois",
    "wof:placetype":"venue"
},
  "geometry": {"coordinates":[2.779565,50.4216],"type":"Point"}
}