{
  "type": "Feature",
  "properties": {
    "iso:country":"FR",
    "sg:address":"84, Rte de Strasbourg, 67500 Haguenau",
    "sg:city":"Haguenau",
    "sg:orig_category":"Unclassifiable Establishments",
    "sg:phone":"+33 3 88 07 15 50",
    "sg:postcode":"67500",
    "sg:province":"Alsace",
    "wof:name":"European Rail Software Applications S.a.r.l.",
    "wof:placetype":"venue"
},
  "geometry": {"coordinates":[7.773247,48.805321],"type":"Point"}
}