{
  "type": "Feature",
  "properties": {
    "iso:country":"FR",
    "sg:address":"ZA du Stiletto",
    "sg:city":"Ajaccio",
    "sg:orig_category":"Unclassifiable Establishments",
    "sg:phone":"+33 4 95 23 73 73",
    "sg:postcode":"20090",
    "sg:province":"Corse",
    "wof:name":"C.i.m. S.a. - Concept Informatique M\u00e9diterran\u00e9en",
    "wof:placetype":"venue"
},
  "geometry": {"coordinates":[8.781228,41.952419],"type":"Point"}
}