{
  "type": "Feature",
  "properties": {
    "iso:country":"FR",
    "sg:address":"Rue Lecien Perriaux 21200 Beaune",
    "sg:city":"Beaune",
    "sg:classifiers":[
        {
            "category":"Home & Garden",
            "subcategory":"Furniture",
            "type":"Retail Goods"
        }
    ],
    "sg:phone":"+33 3 80 25 92 55",
    "sg:postcode":"21200",
    "sg:province":"Bourgogne",
    "sg:tags":[
        "wood"
    ],
    "wof:name":"Tonnelleries De Bourgogne Sarl",
    "wof:placetype":"venue"
},
  "geometry": {"coordinates":[4.86171,47.02388],"type":"Point"}
}