{
  "type": "Feature",
  "properties": {
    "addr:full":"15 Bd De Beaubourg Beaubourg 77421 Marne La Vall\u00e9e Cedex 2 \u00cele-de-France",
    "addr:housenumber":"15",
    "addr:postcode":"77421",
    "addr:street":"Bd De Beaubourg Beaubourg;Cedex",
    "iso:country":"FR",
    "sg:address":"15 Bd De Beaubourg",
    "sg:city":"Beaubourg 77421 Marne La Vall\u00e9e Cedex 2",
    "sg:classifiers":[
        {
            "category":"Professional",
            "type":"Services"
        }
    ],
    "sg:phone":"+33 1 64 62 53 00",
    "sg:province":"\u00cele-de-France",
    "sg:tags":[
        "transport",
        "road"
    ],
    "wof:name":"Danzas Fashion",
    "wof:placetype":"venue"
},
  "geometry": {"coordinates":[2.647897,48.828018],"type":"Point"}
}