{
  "type": "Feature",
  "properties": {
    "iso:country":"FR",
    "sg:address":"rue Andr\u00e9 Fruchard 54320 Maxeville",
    "sg:classifiers":[
        {
            "category":"Retail",
            "subcategory":"Car Wash",
            "type":"Services"
        }
    ],
    "sg:phone":"+33 3 83 37 03 57",
    "sg:province":"Lorraine",
    "sg:tags":[
        "transportation",
        "special"
    ],
    "wof:name":"M.k.t.s. Sa",
    "wof:placetype":"venue"
},
  "geometry": {"coordinates":[6.16942,48.712425],"type":"Point"}
}