{
  "type": "Feature",
  "properties": {
    "addr:full":"102, Rue R\u00e9aumur, 75002 Paris Ile de France",
    "addr:housenumber":"102",
    "addr:postcode":"75002",
    "addr:street":"Rue Re\u0301Aumur",
    "iso:country":"FR",
    "sg:address":"102, Rue R\u00e9aumur, 75002 Paris",
    "sg:orig_category":"Unclassifiable Establishments",
    "sg:phone":"+33 1 42 33 72 42",
    "sg:province":"Ile de France",
    "wof:name":"Ann Taylor S.a.",
    "wof:placetype":"venue"
},
  "geometry": {"coordinates":[2.348226,48.867245],"type":"Point"}
}