{
  "type": "Feature",
  "properties": {
    "iso:country":"FR",
    "sg:address":"74 Avenue De La Division Leclerc 93350 Le Bourget",
    "sg:classifiers":[
        {
            "category":"Bakery",
            "type":"Food & Drink"
        }
    ],
    "sg:phone":"+33 1 48 37 36 27",
    "sg:postcode":"93350",
    "sg:province":"Ile de France",
    "sg:tags":[
        "cake",
        "product",
        "related",
        "bread"
    ],
    "wof:name":"Guillerme Roger",
    "wof:placetype":"venue"
},
  "geometry": {"coordinates":[2.427199,48.935989],"type":"Point"}
}