{
  "type": "Feature",
  "properties": {
    "addr:full":"ZI 80000 Amiens Picardie 80000",
    "addr:postcode":"80000;80000",
    "addr:street":"Zi",
    "iso:country":"FR",
    "sg:address":"ZI 80000 Amiens",
    "sg:classifiers":[
        {
            "category":"Building & Trades",
            "subcategory":"Cleaning & Sanitation",
            "type":"Services"
        }
    ],
    "sg:phone":"+33 3 22 67 31 31",
    "sg:postcode":"80000",
    "sg:province":"Picardie",
    "sg:tags":[
        "hazardous",
        "waste",
        "treatment"
    ],
    "wof:name":"Fls Miljo Sa",
    "wof:placetype":"venue"
},
  "geometry": {"coordinates":[2.293165,49.894733],"type":"Point"}
}