{
  "type": "Feature",
  "properties": {
    "addr:full":"Rue Cl\u00e9ment Ader Saint Ouen Centre 41100",
    "addr:postcode":"41100",
    "addr:street":"Rue Cle\u0301Ment Ader Saint",
    "iso:country":"FR",
    "sg:address":"Rue Cl\u00e9ment Ader",
    "sg:city":"Saint Ouen",
    "sg:orig_category":"Unclassifiable Establishments",
    "sg:phone":"+33 2 54 73 37 50",
    "sg:postcode":"41100",
    "sg:province":"Centre",
    "wof:name":"Crois\u00e9es Alu S.a.",
    "wof:placetype":"venue"
},
  "geometry": {"coordinates":[1.087235,47.811134],"type":"Point"}
}