{
  "type": "Feature",
  "properties": {
    "iso:country":"FR",
    "sg:address":"2, Rue Andr\u00e9 Citro\u00ebn - Z.A. Moulin Marcill\u00e9, 49137 Les Ponts de C\u00e9 C\u00e9dex",
    "sg:orig_category":"Unclassifiable Establishments",
    "sg:phone":"+33 2 41 69 10 00",
    "sg:province":"Bourgogne",
    "wof:name":"C.a.a. - S.a. - Compagnie Autoroute Anjou",
    "wof:placetype":"venue"
},
  "geometry": {"coordinates":[-0.500473,47.433521],"type":"Point"}
}