{
  "type": "Feature",
  "properties": {
    "addr:full":"4, Rue Pascal - ZI Mi-Plaine, 69680 Chassieu Rhone-Alpes 69680",
    "addr:housenumber":"4",
    "addr:postcode":"69680;69680",
    "addr:street":"Rue Pascal Zi Mi-Plaine",
    "iso:country":"FR",
    "sg:address":"4, Rue Pascal - ZI Mi-Plaine, 69680 Chassieu",
    "sg:orig_category":"Non-Classified Establishments",
    "sg:phone":"+33 4 78 40 67 95",
    "sg:postcode":"69680",
    "sg:province":"Rhone-Alpes",
    "wof:name":"Manupi\u00e8ce S.a.",
    "wof:placetype":"venue"
},
  "geometry": {"coordinates":[4.972185,45.743477],"type":"Point"}
}