{
  "type": "Feature",
  "properties": {
    "addr:full":"Route Digoin 71130 Gueugnon Gueugnon Bourgogne 71130",
    "addr:postcode":"71130;71130",
    "addr:street":"Route Digoin",
    "iso:country":"FR",
    "sg:address":"Route Digoin 71130 Gueugnon",
    "sg:city":"Gueugnon",
    "sg:classifiers":[
        {
            "category":"Autos & Motor Vehicles",
            "subcategory":"Automobile Sales",
            "type":"Retail Goods"
        }
    ],
    "sg:phone":"+33 3 85 85 06 02",
    "sg:postcode":"71130",
    "sg:province":"Bourgogne",
    "sg:tags":[
        "equipment",
        "motor-cars",
        "transport"
    ],
    "wof:name":"Ets Milli-difusion Automobile Charollais Sa",
    "wof:placetype":"venue"
},
  "geometry": {"coordinates":[4.063795,46.586281],"type":"Point"}
}