{
  "type": "Feature",
  "properties": {
    "iso:country":"FR",
    "sg:address":"Centre Commercial de Saint Bonnet",
    "sg:city":"Villefontaine",
    "sg:orig_category":"Unclassifiable Establishments",
    "sg:phone":"+33 4 74 96 48 80",
    "sg:postcode":"38090",
    "sg:province":"Rhone-Alpes",
    "wof:name":"Faure Tourisme",
    "wof:placetype":"venue"
},
  "geometry": {"coordinates":[5.14945,45.615166],"type":"Point"}
}