{
  "type": "Feature",
  "properties": {
    "iso:country":"FR",
    "sg:address":"5, Chemin Carrosse - ZI Montaudran, 31400 Toulouse",
    "sg:orig_category":"Unclassifiable Establishments",
    "sg:phone":"+33 5 61 36 06 60",
    "sg:province":"Midi Pyr\u00e9n\u00e9es",
    "wof:name":"Kdi M\u00e9tal Barbier Besson S.a.s.",
    "wof:placetype":"venue"
},
  "geometry": {"coordinates":[1.4579,43.57795],"type":"Point"}
}