{
  "type": "Feature",
  "properties": {
    "addr:full":"Rte de Mondavezan - ZA Martres Tolosane Midi Pyr\u00e9n\u00e9es 31220",
    "addr:postcode":"31220",
    "addr:street":"Rte De Mondavezan Za Martres Tolosane",
    "iso:country":"FR",
    "sg:address":"Rte de Mondavezan - ZA",
    "sg:city":"Martres Tolosane",
    "sg:orig_category":"Unclassifiable Establishments",
    "sg:phone":"+33 5 61 90 82 60",
    "sg:postcode":"31220",
    "sg:province":"Midi Pyr\u00e9n\u00e9es",
    "wof:name":"Innopsys S.a.",
    "wof:placetype":"venue"
},
  "geometry": {"coordinates":[1.14288,43.155048],"type":"Point"}
}