{
  "type": "Feature",
  "properties": {
    "addr:full":"4, Rue de Pressy, 74300 Cluses Rhone-Alpes 74300",
    "addr:housenumber":"4",
    "addr:postcode":"74300;74300",
    "addr:street":"Rue De Pressy",
    "iso:country":"FR",
    "sg:address":"4, Rue de Pressy, 74300 Cluses",
    "sg:orig_category":"Unclassifiable Establishments",
    "sg:phone":"+33 4 50 98 10 00",
    "sg:postcode":"74300",
    "sg:province":"Rhone-Alpes",
    "wof:name":"D.a.m.a. S.a. - D\u00e9colletage Automatique Et M\u00e9canique D'appareillage",
    "wof:placetype":"venue"
},
  "geometry": {"coordinates":[6.558063,46.079094],"type":"Point"}
}