{
  "type": "Feature",
  "properties": {
    "addr:full":"10 Rue Du President Herriot Nantes Pays de Loire 44000",
    "addr:housenumber":"10",
    "addr:postcode":"44000",
    "addr:street":"Rue Du President Herriot",
    "iso:country":"FR",
    "sg:address":"10 Rue Du President Herriot",
    "sg:city":"Nantes",
    "sg:classifiers":[
        {
            "category":"Banks & Credit Unions",
            "subcategory":"Financial Services",
            "type":"Services"
        }
    ],
    "sg:phone":"+33 2 40 89 79 29",
    "sg:postcode":"44000",
    "sg:province":"Pays de Loire",
    "sg:tags":[
        "banking",
        "finance",
        "insurance"
    ],
    "wof:name":"Hommes Strategie Droit Esnst Et Young Hsd Ernst Et Young",
    "wof:placetype":"venue"
},
  "geometry": {"coordinates":[-1.560554,47.218807],"type":"Point"}
}