{
  "type": "Feature",
  "properties": {
    "iso:country":"FR",
    "sg:address":"Rue Du Remoulaire 13300 Salon De Provence",
    "sg:classifiers":[
        {
            "category":"Banks & Credit Unions",
            "subcategory":"Investment Brokerage",
            "type":"Services"
        }
    ],
    "sg:phone":"+33 4 90 17 27 00",
    "sg:province":"Provence-Alpes-C\u00f4te d'Azur",
    "sg:tags":[
        "-",
        "transport",
        "related"
    ],
    "wof:name":"Nexia Froid",
    "wof:placetype":"venue"
},
  "geometry": {"coordinates":[5.092364,43.630066],"type":"Point"}
}