{
  "type": "Feature",
  "properties": {
    "addr:full":"91023 Evry C\u00e9dex^^20/22, Rue du Marquis des Raies - Le Canal , 91080 Courcouronnes Ile de France 91080",
    "addr:housenumber":"22",
    "addr:postcode":"91023;91080;91080",
    "addr:street":"Rue Du Marquis Des Raies Le Canal",
    "iso:country":"FR",
    "sg:address":"91023 Evry C\u00e9dex^^20/22, Rue du Marquis des Raies - Le Canal , 91080 Courcouronnes",
    "sg:orig_category":"Non-Classified Establishments",
    "sg:phone":"+33 1 60 78 84 84",
    "sg:postcode":"91080",
    "sg:province":"Ile de France",
    "wof:name":"Arbres Et Paysages S.a.",
    "wof:placetype":"venue"
},
  "geometry": {"coordinates":[2.410883,48.618111],"type":"Point"}
}