{
  "type": "Feature",
  "properties": {
    "iso:country":"FR",
    "sg:address":"17 boulevard de l'Industrie 31170 Tournefeuille",
    "sg:classifiers":[
        {
            "category":"Structure",
            "subcategory":"Building",
            "type":"Public Place"
        }
    ],
    "sg:phone":"+33 5 61 15 11 22",
    "sg:province":"Midi Pyr\u00e9n\u00e9es",
    "sg:tags":[
        "roof"
    ],
    "wof:name":"Innovation Partners S.a.r.l.",
    "wof:placetype":"venue"
},
  "geometry": {"coordinates":[1.311151,43.588341],"type":"Point"}
}