{
  "type": "Feature",
  "properties": {
    "addr:full":"31, Rue Amp\u00e8re - ZI Est, 54710 Ludres Lorraine",
    "addr:housenumber":"31",
    "addr:postcode":"54710",
    "addr:street":"Rue Ampe\u0300Re Zi Est",
    "iso:country":"FR",
    "sg:address":"31, Rue Amp\u00e8re - ZI Est, 54710 Ludres",
    "sg:orig_category":"Unclassifiable Establishments",
    "sg:phone":"+33 3 83 26 16 60",
    "sg:province":"Lorraine",
    "wof:name":"Imatec",
    "wof:placetype":"venue"
},
  "geometry": {"coordinates":[6.161059,48.621563],"type":"Point"}
}