{
  "type": "Feature",
  "properties": {
    "iso:country":"FR",
    "sg:address":"Av. de la R\u00e9sistance",
    "sg:city":"Les Quatre Routes du Lot",
    "sg:orig_category":"Non-Classified Establishments",
    "sg:phone":"+33 5 65 32 11 67",
    "sg:postcode":"46110",
    "sg:province":"Midi Pyr\u00e9n\u00e9es",
    "wof:name":"Point P S.a.",
    "wof:placetype":"venue"
},
  "geometry": {"coordinates":[1.653004,44.994877],"type":"Point"}
}