{
  "type": "Feature",
  "properties": {
    "iso:country":"FR",
    "sg:address":"93 Rue Des 4 Eglises",
    "sg:city":"Nancy",
    "sg:classifiers":[
        {
            "category":"Banks & Credit Unions",
            "subcategory":"Financial Services",
            "type":"Services"
        }
    ],
    "sg:phone":"+33 3 83 85 03 40",
    "sg:postcode":"54000",
    "sg:province":"Lorraine",
    "sg:tags":[
        "banking",
        "finance",
        "insurance"
    ],
    "wof:name":"Societe Fiduciaire Nationale Juridique Et Fiscale Fiducial (sofiral)",
    "wof:placetype":"venue"
},
  "geometry": {"coordinates":[6.186039,48.684296],"type":"Point"}
}