{
  "type": "Feature",
  "properties": {
    "addr:full":"Rn 10 86370 Vivonne Poitou-Charentes 86370",
    "addr:postcode":"86370;86370",
    "addr:street":"Rn 10;Vivonne",
    "iso:country":"FR",
    "sg:address":"Rn 10 86370 Vivonne",
    "sg:classifiers":[
        {
            "category":"Autos & Motor Vehicles",
            "subcategory":"Automobile Sales",
            "type":"Retail Goods"
        }
    ],
    "sg:phone":"+33 5 49 43 25 12",
    "sg:postcode":"86370",
    "sg:province":"Poitou-Charentes",
    "sg:tags":[
        "equipment",
        "industrial",
        "transport"
    ],
    "wof:name":"Vivonnemarrel Bennes",
    "wof:placetype":"venue"
},
  "geometry": {"coordinates":[0.314755,46.41745],"type":"Point"}
}