{
  "type": "Feature",
  "properties": {
    "iso:country":"FR",
    "sg:address":"13 Rue Lavoisier 45140 Ingr\u00e9",
    "sg:city":"Ingr\u00e9",
    "sg:classifiers":[
        {
            "category":"Utilities",
            "subcategory":"Electric",
            "type":"Services"
        }
    ],
    "sg:phone":"+33 2 38 22 33 77",
    "sg:postcode":"45140",
    "sg:province":"Centre",
    "sg:tags":[
        "electricity",
        "electronic",
        "electrical",
        "equipment"
    ],
    "wof:name":"Comet Sas",
    "wof:placetype":"venue"
},
  "geometry": {"coordinates":[1.854514,47.903801],"type":"Point"}
}