{
  "type": "Feature",
  "properties": {
    "addr:full":"7 Rue Roger Aubry 51100 Reims Champagne 51100",
    "addr:housenumber":"7",
    "addr:postcode":"51100;51100",
    "addr:street":"Rue Roger Aubry",
    "iso:country":"FR",
    "sg:address":"7 Rue Roger Aubry 51100 Reims",
    "sg:orig_category":"Miscellaneous Products",
    "sg:phone":"+33 3 26 06 31 04",
    "sg:postcode":"51100",
    "sg:province":"Champagne",
    "wof:name":"Pompes Funebres Generale Est Sa",
    "wof:placetype":"venue"
},
  "geometry": {"coordinates":[4.025006,49.227367],"type":"Point"}
}