{
  "type": "Feature",
  "properties": {
    "addr:full":"9, Rue des Fr\u00e8res Lumi\u00e8re, 67201 Eckbolsheim Eckbolsheim Alsace 67201",
    "addr:housenumber":"9",
    "addr:postcode":"67201;67201",
    "addr:street":"Rue Des Fre\u0300Res Lumie\u0300Re",
    "iso:country":"FR",
    "sg:address":"9, Rue des Fr\u00e8res Lumi\u00e8re, 67201 Eckbolsheim",
    "sg:city":"Eckbolsheim",
    "sg:orig_category":"Unclassifiable Establishments",
    "sg:phone":"+33 3 88 76 50 51",
    "sg:postcode":"67201",
    "sg:province":"Alsace",
    "wof:name":"D.g.s. S.a.r.l.",
    "wof:placetype":"venue"
},
  "geometry": {"coordinates":[7.686251,48.587257],"type":"Point"}
}