{
  "type": "Feature",
  "properties": {
    "addr:full":"2 rue de Lorraine; Beaune; 21204 Bourgogne",
    "addr:housenumber":"2",
    "addr:postcode":"21204",
    "addr:street":"Rue De Lorraine",
    "iso:country":"FR",
    "sg:address":"2 rue de Lorraine; Beaune; 21204",
    "sg:classifiers":[
        {
            "category":"Banks & Credit Unions",
            "subcategory":"Bank",
            "type":"Services"
        }
    ],
    "sg:phone":"+33 3 80 22 25 34",
    "sg:province":"Bourgogne",
    "wof:name":"Banque Rh\u00f4ne Alpes",
    "wof:placetype":"venue"
},
  "geometry": {"coordinates":[4.83869,47.024548],"type":"Point"}
}