{
  "type": "Feature",
  "properties": {
    "addr:full":"Zone Industrielle Ouest 76700 Rogerville Haute Normandie 76700",
    "addr:postcode":"76700;76700",
    "addr:street":"Zone Industrielle Ouest;Haute Normandie",
    "iso:country":"FR",
    "sg:address":"Zone Industrielle Ouest 76700 Rogerville",
    "sg:classifiers":[
        {
            "category":"Manufacturing",
            "subcategory":"Metals",
            "type":"Manufacturing & Wholesale Goods"
        }
    ],
    "sg:phone":"+33 2 35 47 90 32",
    "sg:postcode":"76700",
    "sg:province":"Haute Normandie",
    "sg:tags":[
        "pipe",
        "sheet",
        "-",
        "metalworking",
        "metallic",
        "metallurgy",
        "finished"
    ],
    "wof:name":"Boccard",
    "wof:placetype":"venue"
},
  "geometry": {"coordinates":[0.267375,49.503597],"type":"Point"}
}