{
  "type": "Feature",
  "properties": {
    "addr:full":"Chemin de la Voyette Pernant Picardie 02200",
    "addr:postcode":"02200",
    "addr:street":"Chemin De La Voyette;Picardie",
    "iso:country":"FR",
    "sg:address":"Chemin de la Voyette",
    "sg:city":"Pernant",
    "sg:orig_category":"Unclassifiable Establishments",
    "sg:phone":"+33 3 23 73 00 22",
    "sg:postcode":"02200",
    "sg:province":"Picardie",
    "wof:name":"T.k.i. S.a.r.l. - Trans Kam International",
    "wof:placetype":"venue"
},
  "geometry": {"coordinates":[3.243368,49.385475],"type":"Point"}
}