{
  "type": "Feature",
  "properties": {
    "addr:full":"ZI Les Niollets Douvaine Rhone-Alpes 74140",
    "addr:postcode":"74140",
    "addr:street":"Zi Les Niollets;Rhone-Alpes",
    "iso:country":"FR",
    "sg:address":"ZI Les Niollets",
    "sg:city":"Douvaine",
    "sg:orig_category":"Non-Classified Establishments",
    "sg:phone":"+33 4 50 35 46 80",
    "sg:postcode":"74140",
    "sg:province":"Rhone-Alpes",
    "wof:name":"Soci\u00e9t\u00e9 Chablaisienne De Distribution S.a.s.",
    "wof:placetype":"venue"
},
  "geometry": {"coordinates":[6.302328,46.306038],"type":"Point"}
}