{
  "type": "Feature",
  "properties": {
    "iso:country":"FR",
    "sg:address":"92053 Paris la D\u00e9fense C\u00e9dex^^2, Place de la D\u00e9fense, 92800 Puteaux",
    "sg:orig_category":"Non-Classified Establishments",
    "sg:phone":"+33 1 49 07 21 60",
    "sg:postcode":"92800",
    "sg:province":"Ile de France",
    "wof:name":"E.a.c. Corporation Ingenico S.a.",
    "wof:placetype":"venue"
},
  "geometry": {"coordinates":[2.23944,48.884205],"type":"Point"}
}