{
  "type": "Feature",
  "properties": {
    "addr:full":"43, Chemin des Simons, 73100 Aix les Bains Rhone-Alpes",
    "addr:housenumber":"43",
    "addr:postcode":"73100",
    "addr:street":"Chemin Des Simons",
    "iso:country":"FR",
    "sg:address":"43, Chemin des Simons, 73100 Aix les Bains",
    "sg:orig_category":"Unclassifiable Establishments",
    "sg:phone":"+33 4 79 35 48 63",
    "sg:province":"Rhone-Alpes",
    "wof:name":"C.a.t. De Chantemerle",
    "wof:placetype":"venue"
},
  "geometry": {"coordinates":[5.92448,45.696514],"type":"Point"}
}