{
  "type": "Feature",
  "properties": {
    "addr:full":"4, Rue de la Grenouill\u00e8re, 89190 Chigy Chigy Bourgogne 89190",
    "addr:housenumber":"4",
    "addr:postcode":"89190;89190",
    "addr:street":"Rue De La Grenouille\u0300Re",
    "iso:country":"FR",
    "sg:address":"4, Rue de la Grenouill\u00e8re, 89190 Chigy",
    "sg:city":"Chigy",
    "sg:orig_category":"Non-Classified Establishments",
    "sg:phone":"+33 3 86 86 75 13",
    "sg:postcode":"89190",
    "sg:province":"Bourgogne",
    "wof:name":"Exploitation Foresti\u00e8re",
    "wof:placetype":"venue"
},
  "geometry": {"coordinates":[3.473551,48.201027],"type":"Point"}
}