{
  "type": "Feature",
  "properties": {
    "iso:country":"FR",
    "sg:address":"6, Cit\u00e9 Joly, 75011 Paris",
    "sg:orig_category":"Non-Classified Establishments",
    "sg:phone":"+33 1 47 00 93 11",
    "sg:province":"Ile de France",
    "wof:name":"Photogravure Topag S.a.r.l.",
    "wof:placetype":"venue"
},
  "geometry": {"coordinates":[2.383322,48.862232],"type":"Point"}
}