{
  "type": "Feature",
  "properties": {
    "addr:full":"23, Rue Saint Michel, 69007 Lyon Rhone-Alpes 69007",
    "addr:housenumber":"23",
    "addr:postcode":"69007;69007",
    "addr:street":"Rue Saint Michel",
    "iso:country":"FR",
    "sg:address":"23, Rue Saint Michel, 69007 Lyon",
    "sg:orig_category":"Unclassifiable Establishments",
    "sg:phone":"+33 4 72 71 03 79",
    "sg:postcode":"69007",
    "sg:province":"Rhone-Alpes",
    "wof:name":"G.r.e.b.e. S.a.r.l.",
    "wof:placetype":"venue"
},
  "geometry": {"coordinates":[4.844777,45.752323],"type":"Point"}
}