{
  "type": "Feature",
  "properties": {
    "addr:full":"8 R De Dole 69007 Lyon Rhone-Alpes",
    "addr:housenumber":"8",
    "addr:postcode":"69007",
    "addr:street":"R De Dole",
    "iso:country":"FR",
    "sg:address":"8 R De Dole 69007 Lyon",
    "sg:classifiers":[
        {
            "category":"Professional",
            "type":"Services"
        }
    ],
    "sg:phone":"+33 4 72 73 10 77",
    "sg:province":"Rhone-Alpes",
    "sg:tags":[
        "transport"
    ],
    "wof:name":"Ups",
    "wof:placetype":"venue"
},
  "geometry": {"coordinates":[4.836131,45.723537],"type":"Point"}
}