{
  "type": "Feature",
  "properties": {
    "iso:country":"FR",
    "sg:address":"54, Rue la Fayette, 75009 Paris",
    "sg:orig_category":"Unclassifiable Establishments",
    "sg:phone":"+33 1 44 83 10 00",
    "sg:province":"Ile de France",
    "wof:name":"Discofone S.a.",
    "wof:placetype":"venue"
},
  "geometry": {"coordinates":[2.342009,48.875256],"type":"Point"}
}