{
  "type": "Feature",
  "properties": {
    "iso:country":"FR",
    "sg:address":"R De La P\u00eacherie 61260 Le Theil",
    "sg:city":"Le Theil",
    "sg:classifiers":[
        {
            "category":"Manufacturing",
            "subcategory":"Metals",
            "type":"Manufacturing & Wholesale Goods"
        }
    ],
    "sg:phone":"+33 2 37 53 73 00",
    "sg:postcode":"61260",
    "sg:province":"Basse Normandie",
    "sg:tags":[
        "metallurgy",
        "metalworking",
        "processing"
    ],
    "wof:name":"Sofedit",
    "wof:placetype":"venue"
},
  "geometry": {"coordinates":[0.684809,48.261532],"type":"Point"}
}