{
  "type": "Feature",
  "properties": {
    "addr:full":"Rte De Libourne 33330 St Emilion Saint-\u00c9tienne-de-Lisse Aquitaine 33330",
    "addr:postcode":"33330;33330",
    "addr:street":"Rte De Libourne",
    "iso:country":"FR",
    "sg:address":"Rte De Libourne 33330 St Emilion",
    "sg:city":"Saint-\u00c9tienne-de-Lisse",
    "sg:classifiers":[
        {
            "category":"Travel",
            "subcategory":"Hotels & Motels",
            "type":"Entertainment"
        }
    ],
    "sg:phone":"+33 5 57 55 37 00",
    "sg:postcode":"33330",
    "sg:province":"Aquitaine",
    "sg:tags":[
        "hotels",
        "business",
        "restaurant"
    ],
    "wof:name":"Gross Hotels Sa",
    "wof:placetype":"venue"
},
  "geometry": {"coordinates":[-0.148079,44.848289],"type":"Point"}
}