{
  "type": "Feature",
  "properties": {
    "iso:country":"FR",
    "sg:address":"113, Bd Pierre Brossolette, 02000 Laon",
    "sg:orig_category":"Unclassifiable Establishments",
    "sg:phone":"+33 3 23 79 26 69",
    "sg:province":"Picardie",
    "wof:name":"Socotec S.a.",
    "wof:placetype":"venue"
},
  "geometry": {"coordinates":[3.617556,49.569218],"type":"Point"}
}