{
  "type": "Feature",
  "properties": {
    "iso:country":"FR",
    "sg:address":"B.P. 1130, 03103 Montlu\u00e7on C\u00e9dex^^36, Rue St\u00e9phane Servant, 03100 Montlu\u00e7on",
    "sg:city":"Montlu\u00e7on",
    "sg:orig_category":"Non-Classified Establishments",
    "sg:phone":"+33 4 70 28 12 24",
    "sg:postcode":"03100",
    "sg:province":"Auvergne",
    "wof:name":"Maison Rousseau P\u00e8re Et Fils S.a.",
    "wof:placetype":"venue"
},
  "geometry": {"coordinates":[2.59568,46.343418],"type":"Point"}
}