{
  "type": "Feature",
  "properties": {
    "addr:full":"424 Av Du Roi 06250 Mougins",
    "addr:postcode":"06250",
    "addr:street":"424 Av Du Roi",
    "iso:country":"FR",
    "sg:address":"424 Av Du Roi 06250 Mougins",
    "sg:classifiers":[
        {
            "category":"Travel",
            "subcategory":"Hotels & Motels",
            "type":"Entertainment"
        }
    ],
    "sg:phone":"+33 4 92 92 49 69",
    "sg:tags":[
        "hotels",
        "game",
        "sport",
        "business",
        "restaurant"
    ],
    "wof:name":"Ste En Participation Royal Mougins",
    "wof:placetype":"venue"
},
  "geometry": {"coordinates":[6.967929,43.593834],"type":"Point"}
}