{
  "type": "Feature",
  "properties": {
    "iso:country":"FR",
    "sg:address":"25 avenue de Champagne 51200 Epernay",
    "sg:classifiers":[
        {
            "category":"Food & Beverages",
            "subcategory":"Liquor & Beverages",
            "type":"Retail Goods"
        }
    ],
    "sg:phone":"+33 3 26 59 71 52",
    "sg:postcode":"51200",
    "sg:province":"Champagne",
    "sg:tags":[
        "champagne"
    ],
    "wof:name":"Cooper Vini De Mancy - Champagne Esterlin",
    "wof:placetype":"venue"
},
  "geometry": {"coordinates":[3.95942,49.043266],"type":"Point"}
}