{
  "type": "Feature",
  "properties": {
    "addr:full":"avenue de Milan 66000 Perpignan Languedoc-Roussillon 66000",
    "addr:postcode":"66000;66000",
    "addr:street":"Avenue De Milan",
    "iso:country":"FR",
    "sg:address":"avenue de Milan 66000 Perpignan",
    "sg:orig_category":"Fresh Vegetables, Lettuces, And Potatoes",
    "sg:phone":"+33 4 68 56 88 56",
    "sg:postcode":"66000",
    "sg:province":"Languedoc-Roussillon",
    "wof:name":"Agrofel Sa",
    "wof:placetype":"venue"
},
  "geometry": {"coordinates":[2.852565,42.69091],"type":"Point"}
}