{
  "type": "Feature",
  "properties": {
    "addr:full":"1, Rte Houssi\u00e8re, 88430 Corcieux Lorraine 88430",
    "addr:housenumber":"1",
    "addr:postcode":"88430;88430",
    "addr:street":"Rte Houssie\u0300Re",
    "iso:country":"FR",
    "sg:address":"1, Rte Houssi\u00e8re, 88430 Corcieux",
    "sg:orig_category":"Non-Classified Establishments",
    "sg:phone":"+33 3 29 50 65 11",
    "sg:postcode":"88430",
    "sg:province":"Lorraine",
    "wof:name":"Coop\u00e9rative Agricole En Commun Et D'approvisionnement",
    "wof:placetype":"venue"
},
  "geometry": {"coordinates":[6.88129,48.173882],"type":"Point"}
}