{
  "type": "Feature",
  "properties": {
    "iso:country":"FR",
    "sg:address":"1 Rue Fauvettes 85290 Mortagne Sur S\u00eavre",
    "sg:classifiers":[
        {
            "category":"Manufacturing",
            "subcategory":"Textiles",
            "type":"Manufacturing & Wholesale Goods"
        }
    ],
    "sg:phone":"+33 2 51 65 09 06",
    "sg:postcode":"85290",
    "sg:province":"Pays de Loire",
    "sg:tags":[
        "clothing",
        "accessory"
    ],
    "wof:name":"Freydberg Sa",
    "wof:placetype":"venue"
},
  "geometry": {"coordinates":[-111.393677,33.52631],"type":"Point"}
}