{
  "type": "Feature",
  "properties": {
    "addr:full":"B.P. 19, 69510 Soucieu en Jarrest C\u00e9dex^^Rue Louis Bastien, 69510 Soucieu en Jarrest Rhone-Alpes",
    "addr:postcode":"69510;69510",
    "addr:street":"B.P. 19;Bastien",
    "iso:country":"FR",
    "sg:address":"B.P. 19, 69510 Soucieu en Jarrest C\u00e9dex^^Rue Louis Bastien, 69510 Soucieu en Jarrest",
    "sg:orig_category":"Non-Classified Establishments",
    "sg:phone":"+33 4 72 31 06 49",
    "sg:province":"Rhone-Alpes",
    "wof:name":"Cobaltix S.a.",
    "wof:placetype":"venue"
},
  "geometry": {"coordinates":[4.63232,45.660503],"type":"Point"}
}