{
  "type": "Feature",
  "properties": {
    "iso:country":"FR",
    "sg:address":"ZA La Bourdonnais",
    "sg:city":"La M\u00e9zi\u00e8re",
    "sg:orig_category":"Unclassifiable Establishments",
    "sg:phone":"+33 2 99 66 59 69",
    "sg:postcode":"35520",
    "sg:province":"Bretagne",
    "wof:name":"Eraf S.a.",
    "wof:placetype":"venue"
},
  "geometry": {"coordinates":[-1.754379,48.219215],"type":"Point"}
}