{
  "type": "Feature",
  "properties": {
    "iso:country":"FR",
    "sg:address":"1 Bd Salvador Allende 44187 Nantes Cedex 4",
    "sg:classifiers":[
        {
            "category":"Professional",
            "subcategory":"Business Services",
            "type":"Services"
        }
    ],
    "sg:phone":"+33 2 40 69 63 27",
    "sg:province":"Midi Pyr\u00e9n\u00e9es",
    "sg:tags":[
        "body",
        "advice"
    ],
    "wof:name":"Univaloire Ass",
    "wof:placetype":"venue"
},
  "geometry": {"coordinates":[-1.573509,47.206718],"type":"Point"}
}