{
  "type": "Feature",
  "properties": {
    "iso:country":"FR",
    "sg:address":"B.P. 12, 66670 Bages C\u00e9dex^^Chemin Saint Jean, 66670 Bages",
    "sg:orig_category":"Non-Classified Establishments",
    "sg:phone":"+33 4 68 21 61 95",
    "sg:province":"Languedoc-Roussillon",
    "wof:name":"Laboratoire J.p.llopart Et Compagnie S.a.r.l.",
    "wof:placetype":"venue"
},
  "geometry": {"coordinates":[2.893224,42.605865],"type":"Point"}
}