{
  "type": "Feature",
  "properties": {
    "addr:full":"1960 Route De Frans 69400 Villefranche Sur Saone Rhone-Alpes 69400",
    "addr:housenumber":"1960",
    "addr:postcode":"69400;69400",
    "addr:street":"Route De Frans",
    "iso:country":"FR",
    "sg:address":"1960 Route De Frans 69400 Villefranche Sur Saone",
    "sg:classifiers":[
        {
            "category":"Professional",
            "subcategory":"Engineering",
            "type":"Services"
        }
    ],
    "sg:phone":"+33 4 74 62 30 63",
    "sg:postcode":"69400",
    "sg:province":"Rhone-Alpes",
    "sg:tags":[
        "machine",
        "-",
        "mechanical"
    ],
    "wof:name":"Printland",
    "wof:placetype":"venue"
},
  "geometry": {"coordinates":[4.746517,45.983746],"type":"Point"}
}