{
  "type": "Feature",
  "properties": {
    "iso:country":"FR",
    "sg:address":"13 R Berthelot 89800 Chablis",
    "sg:city":"Chablis",
    "sg:classifiers":[
        {
            "category":"Food Court",
            "type":"Food & Drink"
        }
    ],
    "sg:phone":"+33 3 86 42 12 63",
    "sg:postcode":"89800",
    "sg:province":"Bourgogne",
    "sg:tags":[
        "product",
        "related"
    ],
    "wof:name":"Earl Sarl",
    "wof:placetype":"venue"
},
  "geometry": {"coordinates":[3.797514,47.811752],"type":"Point"}
}