{
  "type": "Feature",
  "properties": {
    "iso:country":"FR",
    "sg:address":"ZI Sud",
    "sg:city":"Brian\u00e7on C\u00e9dex",
    "sg:orig_category":"Non-Classified Establishments",
    "sg:phone":"+33 4 92 21 04 31",
    "sg:postcode":"05103",
    "sg:province":"Provence-Alpes-C\u00f4te d'Azur",
    "wof:name":"Mass\u00e9 Et Fils S.a.r.l.",
    "wof:placetype":"venue"
},
  "geometry": {"coordinates":[6.635696,44.896965],"type":"Point"}
}