{
  "type": "Feature",
  "properties": {
    "iso:country":"FR",
    "sg:address":"34, Rue Winston Churchill, 59100 Roubaix",
    "sg:orig_category":"Unclassifiable Establishments",
    "sg:phone":"+33 3 20 20 78 78",
    "sg:province":"Nord Pas-de-Calais",
    "wof:name":"Distrifac S.a.",
    "wof:placetype":"venue"
},
  "geometry": {"coordinates":[3.180799,50.688908],"type":"Point"}
}