{
  "type": "Feature",
  "properties": {
    "addr:full":"34, Rue Winston Churchill, 59100 Roubaix Nord Pas-de-Calais",
    "addr:housenumber":"34",
    "addr:postcode":"59100",
    "addr:street":"Rue Winston Churchill",
    "iso:country":"FR",
    "sg:address":"34, Rue Winston Churchill, 59100 Roubaix",
    "sg:orig_category":"Unclassifiable Establishments",
    "sg:phone":"+33 3 20 20 78 78",
    "sg:province":"Nord Pas-de-Calais",
    "wof:name":"Distrifac S.a.",
    "wof:placetype":"venue"
},
  "geometry": {"coordinates":[3.180799,50.688908],"type":"Point"}
}