{
  "type": "Feature",
  "properties": {
    "iso:country":"FR",
    "sg:address":"19, Rue du Bois Galon, 94120 Fontenay sous Bois",
    "sg:orig_category":"Unclassifiable Establishments",
    "sg:phone":"+33 1 49 74 70 00",
    "sg:province":"Ile de France",
    "wof:name":"Omrom Electronics S.a.r.l.",
    "wof:placetype":"venue"
},
  "geometry": {"coordinates":[2.492981,48.859306],"type":"Point"}
}