{
  "type": "Feature",
  "properties": {
    "addr:full":"67 Rue R\u00e9aumur 75002 Paris Ile de France 75002",
    "addr:housenumber":"67",
    "addr:postcode":"75002;75002",
    "addr:street":"Rue Re\u0301Aumur",
    "iso:country":"FR",
    "sg:address":"67 Rue R\u00e9aumur 75002 Paris",
    "sg:classifiers":[
        {
            "category":"Shopping",
            "subcategory":"Clothing, Apparel, & Fashions",
            "type":"Retail Goods"
        }
    ],
    "sg:phone":"+33 1 42 33 67 46",
    "sg:postcode":"75002",
    "sg:province":"Ile de France",
    "sg:tags":[
        "textile",
        "clothing",
        "clothes"
    ],
    "wof:name":"Shimmy",
    "wof:placetype":"venue"
},
  "geometry": {"coordinates":[2.350062,48.866512],"type":"Point"}
}