{
  "type": "Feature",
  "properties": {
    "addr:full":"2 Rue Drelon Residence Isabelle 63000 Clermont Ferrand Clermont-Ferrand Auvergne 63000",
    "addr:housenumber":"2",
    "addr:postcode":"63000;63000",
    "addr:street":"Rue Drelon;Isabelle",
    "iso:country":"FR",
    "sg:address":"2 Rue Drelon Residence Isabelle 63000 Clermont Ferrand",
    "sg:city":"Clermont-Ferrand",
    "sg:classifiers":[
        {
            "category":"Professional",
            "subcategory":"Printing & Photocopies",
            "type":"Services"
        }
    ],
    "sg:phone":"+33 4 73 35 36 20",
    "sg:postcode":"63000",
    "sg:province":"Auvergne",
    "sg:tags":[
        "publishing"
    ],
    "wof:name":"Auvergne Agricole Communication (auvacom)",
    "wof:placetype":"venue"
},
  "geometry": {"coordinates":[3.080687,45.771744],"type":"Point"}
}