{
  "type": "Feature",
  "properties": {
    "addr:full":"6 R De Paris 62300 Lens Nord Pas-de-Calais 62300",
    "addr:housenumber":"6",
    "addr:postcode":"62300;62300",
    "addr:street":"R De Paris",
    "iso:country":"FR",
    "sg:address":"6 R De Paris 62300 Lens",
    "sg:classifiers":[
        {
            "category":"Shopping",
            "subcategory":"Clothing, Apparel, & Fashions",
            "type":"Retail Goods"
        }
    ],
    "sg:phone":"+33 3 21 42 33 00",
    "sg:postcode":"62300",
    "sg:province":"Nord Pas-de-Calais",
    "sg:tags":[
        "textile",
        "clothing",
        "clothes"
    ],
    "wof:name":"New Man Sarl",
    "wof:placetype":"venue"
},
  "geometry": {"coordinates":[2.830549,50.428776],"type":"Point"}
}