{
  "type": "Feature",
  "properties": {
    "addr:full":"Z Artisanale Du Launay 29600 ST MARTIN DES CHAMPS Morlaix Bretagne 29600",
    "addr:postcode":"29600;29600",
    "addr:street":"Launay",
    "iso:country":"FR",
    "sg:address":"Z Artisanale Du Launay 29600 ST MARTIN DES CHAMPS",
    "sg:city":"Morlaix",
    "sg:classifiers":[
        {
            "category":"Arena",
            "subcategory":"Sports Club",
            "type":"Entertainment"
        }
    ],
    "sg:phone":"+33 2 98 88 67 90",
    "sg:postcode":"29600",
    "sg:province":"Bretagne",
    "sg:tags":[
        "game",
        "wood"
    ],
    "wof:name":"Loisirs Nouveaux Sarl",
    "wof:placetype":"venue"
},
  "geometry": {"coordinates":[-3.856472,48.570778],"type":"Point"}
}