{
  "type": "Feature",
  "properties": {
    "iso:country":"FR",
    "sg:address":"102 Cours Lafayette 69003 Lyon",
    "sg:classifiers":[
        {
            "category":"Wholesale",
            "subcategory":"Meat",
            "type":"Manufacturing & Wholesale Goods"
        }
    ],
    "sg:phone":"+33 4 78 62 32 25",
    "sg:postcode":"69003",
    "sg:province":"Rhone-Alpes",
    "sg:tags":[
        "food",
        "cooked",
        "product",
        "related"
    ],
    "wof:name":"Gast Sa",
    "wof:placetype":"venue"
},
  "geometry": {"coordinates":[4.850236,45.763519],"type":"Point"}
}