{
  "type": "Feature",
  "properties": {
    "iso:country":"FR",
    "sg:address":"64 Route St-Lo 50570 Marigny",
    "sg:city":"Marigny",
    "sg:classifiers":[
        {
            "category":"Shopping",
            "subcategory":"Clothing, Apparel, & Fashions",
            "type":"Retail Goods"
        }
    ],
    "sg:phone":"+33 2 33 56 61 62",
    "sg:postcode":"50570",
    "sg:province":"Basse Normandie",
    "sg:tags":[
        "household",
        "textile",
        "wood",
        "clothes",
        "clothing",
        "furniture"
    ],
    "wof:name":"Magasins Bleus",
    "wof:placetype":"venue"
},
  "geometry": {"coordinates":[-1.221389,49.09597],"type":"Point"}
}