{
  "type": "Feature",
  "properties": {
    "addr:full":"Z.A. des Champy Couchey Bourgogne 21160",
    "addr:postcode":"21160",
    "addr:street":"Z.A. Des Champy",
    "iso:country":"FR",
    "sg:address":"Z.A. des Champy",
    "sg:city":"Couchey",
    "sg:orig_category":"Non-Classified Establishments",
    "sg:phone":"+33 3 80 52 30 28",
    "sg:postcode":"21160",
    "sg:province":"Bourgogne",
    "wof:name":"Rousseau P\u00e8re Et Fils S.a.r.l.",
    "wof:placetype":"venue"
},
  "geometry": {"coordinates":[4.987744,47.269951],"type":"Point"}
}