{
  "type": "Feature",
  "properties": {
    "iso:country":"FR",
    "sg:address":"29 Rue Bonaparte 75006 Paris",
    "sg:classifiers":[
        {
            "category":"Manufacturing",
            "subcategory":"Paper Products",
            "type":"Manufacturing & Wholesale Goods"
        }
    ],
    "sg:phone":"+33 1 53 10 39 50",
    "sg:province":"Ile de France",
    "sg:tags":[
        "finished",
        "cardboard",
        "-"
    ],
    "wof:name":"Nobilis",
    "wof:placetype":"venue"
},
  "geometry": {"coordinates":[2.333966,48.85503],"type":"Point"}
}