{
  "type": "Feature",
  "properties": {
    "addr:full":"Lot Industriel Benoit Fourneyron 42160 Andr\u00e9zieux Boutheon Rhone-Alpes 42160",
    "addr:postcode":"42160;42160",
    "addr:street":"Rhone-Alpes",
    "iso:country":"FR",
    "sg:address":"Lot Industriel",
    "sg:city":"Benoit Fourneyron 42160 Andr\u00e9zieux Boutheon",
    "sg:classifiers":[
        {
            "category":"Manufacturing",
            "subcategory":"Metals",
            "type":"Manufacturing & Wholesale Goods"
        }
    ],
    "sg:phone":"+33 4 77 55 48 88",
    "sg:postcode":"42160",
    "sg:province":"Rhone-Alpes",
    "sg:tags":[
        "-",
        "machine",
        "equipment",
        "engineering",
        "machinery",
        "mechanical"
    ],
    "wof:name":"Durancon Patrick Sa",
    "wof:placetype":"venue"
},
  "geometry": {"coordinates":[4.278859,45.521114],"type":"Point"}
}