{
  "type": "Feature",
  "properties": {
    "iso:country":"FR",
    "sg:address":"20-22 Rue De Flandre 93290 Tremblay En France",
    "sg:classifiers":[
        {
            "category":"Wholesale",
            "subcategory":"Medical Equipment & Supplies",
            "type":"Manufacturing & Wholesale Goods"
        }
    ],
    "sg:phone":"+33 1 49 63 14 13",
    "sg:postcode":"93290",
    "sg:province":"Ile de France",
    "sg:tags":[
        "instrument",
        "health",
        "-",
        "precision"
    ],
    "wof:name":"Art Dent Sarl",
    "wof:placetype":"venue"
},
  "geometry": {"coordinates":[2.571968,48.942036],"type":"Point"}
}