{
  "type": "Feature",
  "properties": {
    "addr:full":"1965 Chem De Trespeau 30100 Al\u00e8s Languedoc-Roussillon 30100",
    "addr:housenumber":"1965",
    "addr:postcode":"30100;30100",
    "addr:street":"Chem De Trespeau",
    "iso:country":"FR",
    "sg:address":"1965 Chem De Trespeau 30100 Al\u00e8s",
    "sg:classifiers":[
        {
            "category":"Autos & Motor Vehicles",
            "subcategory":"Automobile Sales",
            "type":"Retail Goods"
        }
    ],
    "sg:phone":"+33 4 66 86 50 15",
    "sg:postcode":"30100",
    "sg:province":"Languedoc-Roussillon",
    "sg:tags":[
        "equipment",
        "motor-cars",
        "transport"
    ],
    "wof:name":"Alpha Karting Sarl",
    "wof:placetype":"venue"
},
  "geometry": {"coordinates":[4.110821,44.117069],"type":"Point"}
}