{
  "type": "Feature",
  "properties": {
    "addr:full":"Rue Jules Guesde - ZI du bas Pontet Saint Symphorien d'Ozon Rhone-Alpes 69360",
    "addr:postcode":"69360",
    "addr:street":"Rue Jules Guesde Zi Du Bas;Rhone-Alpes",
    "iso:country":"FR",
    "sg:address":"Rue Jules Guesde - ZI du bas Pontet",
    "sg:city":"Saint Symphorien d'Ozon",
    "sg:orig_category":"Unclassifiable Establishments",
    "sg:phone":"+33 4 78 02 92 93",
    "sg:postcode":"69360",
    "sg:province":"Rhone-Alpes",
    "wof:name":"Merlin Tuyauterie Chaudronnerie Montage S.a.",
    "wof:placetype":"venue"
},
  "geometry": {"coordinates":[4.85609,45.634979],"type":"Point"}
}