{
  "type": "Feature",
  "properties": {
    "iso:country":"FR",
    "sg:address":"Rue Leconte de Lisle",
    "sg:city":"Saint Gaudens",
    "sg:orig_category":"Non-Classified Establishments",
    "sg:phone":"+33 5 61 89 35 98",
    "sg:postcode":"31800",
    "sg:province":"Midi Pyr\u00e9n\u00e9es",
    "wof:name":"B.v.c. S.a. - B\u00e9tail Viandes Du Comminge",
    "wof:placetype":"venue"
},
  "geometry": {"coordinates":[0.723251,43.050159],"type":"Point"}
}