{
  "type": "Feature",
  "properties": {
    "addr:full":"58 Chemin De Saint Hippolyte 81100 Castres Midi Pyr\u00e9n\u00e9es",
    "addr:housenumber":"58",
    "addr:postcode":"81100",
    "addr:street":"Chemin De Saint Hippolyte",
    "iso:country":"FR",
    "sg:address":"58 Chemin De Saint Hippolyte 81100 Castres",
    "sg:classifiers":[
        {
            "category":"Manufacturing",
            "subcategory":"Paper Products",
            "type":"Manufacturing & Wholesale Goods"
        }
    ],
    "sg:phone":"+33 5 63 35 82 59",
    "sg:province":"Midi Pyr\u00e9n\u00e9es",
    "sg:tags":[
        "packaging",
        "material",
        "-",
        "cardboard"
    ],
    "wof:name":"Etablissements Pierre Blanc",
    "wof:placetype":"venue"
},
  "geometry": {"coordinates":[2.264606,43.598732],"type":"Point"}
}