{
  "type": "Feature",
  "properties": {
    "addr:full":"429 Rue Ernest Renan 62940 Haillicourt Nord Pas-de-Calais",
    "addr:housenumber":"429",
    "addr:postcode":"62940",
    "addr:street":"Rue Ernest Renan",
    "iso:country":"FR",
    "sg:address":"429 Rue Ernest Renan 62940 Haillicourt",
    "sg:classifiers":[
        {
            "category":"Professional",
            "type":"Services"
        }
    ],
    "sg:phone":"+33 3 21 52 03 32",
    "sg:province":"Nord Pas-de-Calais",
    "sg:tags":[
        "transport",
        "road"
    ],
    "wof:name":"Horen Freres Sa",
    "wof:placetype":"venue"
},
  "geometry": {"coordinates":[2.58304,50.469952],"type":"Point"}
}