{
  "type": "Feature",
  "properties": {
    "iso:country":"FR",
    "sg:address":"Zi Thionville Nord Est Usine De Basse Ham 57974 Yutz Cedex",
    "sg:city":"Vill\u00e9",
    "sg:classifiers":[
        {
            "category":"Manufacturing",
            "subcategory":"Motor Vehicles & Parts",
            "type":"Manufacturing & Wholesale Goods"
        }
    ],
    "sg:phone":"+33 3 82 55 93 93",
    "sg:postcode":"67220",
    "sg:province":"Alsace",
    "sg:tags":[
        "engine",
        "machine",
        "engineering",
        "-",
        "mechanical"
    ],
    "wof:name":"Societe Mosellane De Pistons",
    "wof:placetype":"venue"
},
  "geometry": {"coordinates":[6.1873,49.35741],"type":"Point"}
}