{
  "type": "Feature",
  "properties": {
    "addr:full":"157 Rue De La Mini\u00e8re BP 105 78531 Buc Cedex \u00cele-de-France",
    "addr:housenumber":"157;105",
    "addr:postcode":"78531;cedex",
    "addr:street":"Rue De La Minie\u0300Re Bp",
    "iso:country":"FR",
    "sg:address":"157 Rue De La Mini\u00e8re BP 105 78531 Buc Cedex",
    "sg:classifiers":[
        {
            "category":"Utilities",
            "subcategory":"Telephone",
            "type":"Services"
        }
    ],
    "sg:phone":"+33 1 39 67 47 00",
    "sg:province":"\u00cele-de-France",
    "sg:tags":[
        "telecommunication"
    ],
    "wof:name":"Universit\u00c9 Cooperation",
    "wof:placetype":"venue"
},
  "geometry": {"coordinates":[2.10703,48.770721],"type":"Point"}
}