{
  "type": "Feature",
  "properties": {
    "addr:full":"Impasse des C\u00f4teaux - Zone Industrielle Muizon Champagne 51140",
    "addr:postcode":"51140",
    "addr:street":"Impasse Des Co\u0302Teaux;Industrielle;Champagne",
    "iso:country":"FR",
    "sg:address":"Impasse des C\u00f4teaux - Zone Industrielle",
    "sg:city":"Muizon",
    "sg:orig_category":"Unclassifiable Establishments",
    "sg:phone":"+33 3 26 02 98 12",
    "sg:postcode":"51140",
    "sg:province":"Champagne",
    "wof:name":"B.n.e. S.a. - Blanchisserie Du Nord Est",
    "wof:placetype":"venue"
},
  "geometry": {"coordinates":[3.889085,49.275993],"type":"Point"}
}