{
  "type": "Feature",
  "properties": {
    "iso:country":"FR",
    "sg:address":"ZI 75218 PARIS CEDEX 16",
    "sg:classifiers":[
        {
            "category":"Transit Center",
            "subcategory":"Freight",
            "type":"Transportation"
        }
    ],
    "sg:phone":"+33 1 56 28 20 00",
    "sg:province":"\u00cele-de-France",
    "sg:tags":[
        "packaging",
        "special"
    ],
    "wof:name":"Pechiney Sa",
    "wof:placetype":"venue"
},
  "geometry": {"coordinates":[2.26286,48.857079],"type":"Point"}
}