{
  "type": "Feature",
  "properties": {
    "addr:full":"17, Rue Georges Sand, 94405 Vitry sur Seine C\u00e9dex Sand Alsace 67230",
    "addr:housenumber":"17",
    "addr:postcode":"94405;67230",
    "addr:street":"Rue Georges Sand",
    "iso:country":"FR",
    "sg:address":"17, Rue Georges Sand, 94405 Vitry sur Seine C\u00e9dex",
    "sg:city":"Sand",
    "sg:orig_category":"Non-Classified Establishments",
    "sg:phone":"+33 1 46 82 93 93",
    "sg:postcode":"67230",
    "sg:province":"Alsace",
    "wof:name":"Agri Fuseau S.a.r.l.",
    "wof:placetype":"venue"
},
  "geometry": {"coordinates":[2.388125,48.789055],"type":"Point"}
}