{
  "type": "Feature",
  "properties": {
    "addr:full":"9, Chauss\u00e9e Jules C\u00e9sar - ZI des Beaux Soleils, 95520 Osny Ile de France",
    "addr:housenumber":"9",
    "addr:postcode":"95520",
    "addr:street":"Chausse\u0301E Jules Ce\u0301Sar Zi Des Beaux Soleils;Ile De France",
    "iso:country":"FR",
    "sg:address":"9, Chauss\u00e9e Jules C\u00e9sar - ZI des Beaux Soleils, 95520 Osny",
    "sg:orig_category":"Unclassifiable Establishments",
    "sg:phone":"+33 1 30 30 09 35",
    "sg:province":"Ile de France",
    "wof:name":"C.r.i. S.a. - Cr\u00e9ation Relation Impression",
    "wof:placetype":"venue"
},
  "geometry": {"coordinates":[2.064945,49.064018],"type":"Point"}
}