{
  "type": "Feature",
  "properties": {
    "iso:country":"FR",
    "sg:address":"Rue Andr\u00e9 Durouchez Zi Nord 80046 Amiens",
    "sg:classifiers":[
        {
            "category":"Autos & Motor Vehicles",
            "subcategory":"Automobile Sales",
            "type":"Retail Goods"
        }
    ],
    "sg:phone":"+33 3 22 67 35 00",
    "sg:province":"Picardie",
    "sg:tags":[
        "equipment",
        "transport"
    ],
    "wof:name":"Sab Wabco Sa",
    "wof:placetype":"venue"
},
  "geometry": {"coordinates":[2.30253,49.893959],"type":"Point"}
}