{
  "type": "Feature",
  "properties": {
    "addr:full":"B.P. 33, 57170 Ch\u00e2teau Salins^^Av des Saulniers - Zone Industrielle, 57170 Ch\u00e2teau Salins Lorraine",
    "addr:postcode":"57170;57170",
    "addr:street":"B.P. 33;Zone Industrielle",
    "iso:country":"FR",
    "sg:address":"B.P. 33, 57170 Ch\u00e2teau Salins^^Av des Saulniers - Zone Industrielle, 57170 Ch\u00e2teau Salins",
    "sg:orig_category":"Non-Classified Establishments",
    "sg:phone":"+33 3 87 05 11 47",
    "sg:province":"Lorraine",
    "wof:name":"Gf Moselle S.a.",
    "wof:placetype":"venue"
},
  "geometry": {"coordinates":[6.50647,48.819954],"type":"Point"}
}