{
  "type": "Feature",
  "properties": {
    "addr:full":"10 Avenue Foch Lille Nord Pas-de-Calais 59000",
    "addr:housenumber":"10",
    "addr:postcode":"59000",
    "addr:street":"Avenue Foch Lille Nord",
    "iso:country":"FR",
    "sg:address":"10 Avenue Foch",
    "sg:city":"Lille",
    "sg:classifiers":[
        {
            "category":"Banks & Credit Unions",
            "subcategory":"Financial Services",
            "type":"Services"
        }
    ],
    "sg:phone":"+33 3 20 63 70 00",
    "sg:postcode":"59000",
    "sg:province":"Nord Pas-de-Calais",
    "sg:tags":[
        "banking",
        "finance",
        "insurance"
    ],
    "wof:name":"Caisse Regionale De Credit Agricole Mutuel Du Nord (crcamn) Credit Agricole",
    "wof:placetype":"venue"
},
  "geometry": {"coordinates":[3.057381,50.635986],"type":"Point"}
}