{
  "type": "Feature",
  "properties": {
    "iso:country":"FR",
    "sg:address":"23, Rue Nelson Mandela, 34000 Montpellier",
    "sg:orig_category":"Non-Classified Establishments",
    "sg:phone":"+33 4 67 27 59 00",
    "sg:province":"Languedoc-Roussillon",
    "wof:name":"Ingerop Sud-ouest S.a.",
    "wof:placetype":"venue"
},
  "geometry": {"coordinates":[3.879571,43.582001],"type":"Point"}
}