{
  "type": "Feature",
  "properties": {
    "addr:full":"B.P. 16 Nontron Aquitaine 24300",
    "addr:postcode":"24300",
    "addr:street":"B.P. 16",
    "iso:country":"FR",
    "sg:address":"B.P. 16",
    "sg:city":"Nontron",
    "sg:orig_category":"Non-Classified Establishments",
    "sg:phone":"+33 5 53 56 34 90",
    "sg:postcode":"24300",
    "sg:province":"Aquitaine",
    "wof:name":"Laboratoire Du Bain S.a.",
    "wof:placetype":"venue"
},
  "geometry": {"coordinates":[0.585917,45.505871],"type":"Point"}
}