{
  "type": "Feature",
  "properties": {
    "iso:country":"FR",
    "sg:address":"39 bis, Louis Bouquet, 62840 Fleurbaix",
    "sg:orig_category":"Non-Classified Establishments",
    "sg:phone":"+33 3 21 65 41 73",
    "sg:postcode":"62840",
    "sg:province":"Nord Pas-de-Calais",
    "wof:name":"E.r.m. Electronique E.u.r.l.",
    "wof:placetype":"venue"
},
  "geometry": {"coordinates":[2.833408,50.650608],"type":"Point"}
}