{
  "type": "Feature",
  "properties": {
    "addr:full":"95-97, Av. Victor Hugo, 92500 Rueil Malmaison Ile de France",
    "addr:housenumber":"95-97",
    "addr:postcode":"92500",
    "addr:street":"Av. Victor Hugo",
    "iso:country":"FR",
    "sg:address":"95-97, Av. Victor Hugo, 92500 Rueil Malmaison",
    "sg:orig_category":"Unclassifiable Establishments",
    "sg:phone":"+33 1 47 10 08 00",
    "sg:province":"Ile de France",
    "wof:name":"Entreprise Quelin S.a.",
    "wof:placetype":"venue"
},
  "geometry": {"coordinates":[2.174999,48.886177],"type":"Point"}
}