{
  "type": "Feature",
  "properties": {
    "addr:full":"Zi De Craye 25110 Autechaux Franche Comt\u00e9 25110",
    "addr:postcode":"25110;25110",
    "addr:street":"Zi De Craye;Franche Comte\u0301",
    "iso:country":"FR",
    "sg:address":"Zi De Craye 25110 Autechaux",
    "sg:classifiers":[
        {
            "category":"Manufacturing",
            "subcategory":"Metals",
            "type":"Manufacturing & Wholesale Goods"
        }
    ],
    "sg:phone":"+33 3 81 84 39 20",
    "sg:postcode":"25110",
    "sg:province":"Franche Comt\u00e9",
    "sg:tags":[
        "metallurgy",
        "steel",
        "metalworking"
    ],
    "wof:name":"Mecanique Baumoise De Precision",
    "wof:placetype":"venue"
},
  "geometry": {"coordinates":[6.38379,47.377895],"type":"Point"}
}