{
  "type": "Feature",
  "properties": {
    "iso:country":"FR",
    "sg:address":"81, Cours Edouard Vaillantt, 33000 Bordeaux",
    "sg:city":"Bordeaux",
    "sg:orig_category":"Unclassifiable Establishments",
    "sg:phone":"+33 5 57 19 37 37",
    "sg:postcode":"33000",
    "sg:province":"Aquitaine",
    "wof:name":"Aquiro S.a.r.l.",
    "wof:placetype":"venue"
},
  "geometry": {"coordinates":[-0.559366,44.862007],"type":"Point"}
}