{
  "type": "Feature",
  "properties": {
    "addr:full":"B.P. 7024, 95050 Cergy Pontoise C\u00e9dex^^1/3, Rue des Fortes Terres, 95310 Saint Ouen l'Aum\u00f4ne Ile de France",
    "addr:housenumber":"3",
    "addr:postcode":"95050;95310",
    "addr:street":"B.P. 7024;Rue Des Fortes Terres",
    "iso:country":"FR",
    "sg:address":"B.P. 7024, 95050 Cergy Pontoise C\u00e9dex^^1/3, Rue des Fortes Terres, 95310 Saint Ouen l'Aum\u00f4ne",
    "sg:orig_category":"Non-Classified Establishments",
    "sg:phone":"+33 1 34 32 68 68",
    "sg:province":"Ile de France",
    "wof:name":"S.l.p.m. S.a.",
    "wof:placetype":"venue"
},
  "geometry": {"coordinates":[3.183886,48.91972],"type":"Point"}
}