{
  "type": "Feature",
  "properties": {
    "iso:country":"FR",
    "sg:address":"46230 Belfort du Quercy",
    "sg:orig_category":"Non-Classified Establishments",
    "sg:phone":"+33 5 65 31 60 21",
    "sg:province":"Midi Pyr\u00e9n\u00e9es",
    "wof:name":"Silvestre S.a.",
    "wof:placetype":"venue"
},
  "geometry": {"coordinates":[1.543695,44.269619],"type":"Point"}
}