{
  "type": "Feature",
  "properties": {
    "iso:country":"FR",
    "sg:address":"B.P. 10, 49280 Saint Christophe du Bois^^Zone Agricole du Parc, 49280 Saint Christophe du Bois",
    "sg:orig_category":"Non-Classified Establishments",
    "sg:phone":"+33 2 41 56 24 24",
    "sg:province":"Pays de Loire",
    "wof:name":"Transports Raud S.a.r.l.",
    "wof:placetype":"venue"
},
  "geometry": {"coordinates":[-0.899868,47.054268],"type":"Point"}
}