{
  "type": "Feature",
  "properties": {
    "addr:full":"1 Grand Route Le Peux 79140 Le Pin Poitou-Charentes 79140",
    "addr:housenumber":"1",
    "addr:postcode":"79140;79140",
    "addr:street":"Grand Route Le Peux;Pin",
    "iso:country":"FR",
    "sg:address":"1 Grand Route Le Peux 79140 Le Pin",
    "sg:classifiers":[
        {
            "category":"Shopping",
            "subcategory":"Clothing, Apparel, & Fashions",
            "type":"Retail Goods"
        }
    ],
    "sg:phone":"+33 5 49 81 06 46",
    "sg:postcode":"79140",
    "sg:province":"Poitou-Charentes",
    "sg:tags":[
        "textile",
        "clothing",
        "clothes"
    ],
    "wof:name":"Duret Ets J Sarl",
    "wof:placetype":"venue"
},
  "geometry": {"coordinates":[-0.684999,46.808239],"type":"Point"}
}