{
  "type": "Feature",
  "properties": {
    "addr:full":"46, Rue de Cambrai, 62000 Arras Nord Pas-de-Calais",
    "addr:housenumber":"46",
    "addr:postcode":"62000",
    "addr:street":"Rue De Cambrai",
    "iso:country":"FR",
    "sg:address":"46, Rue de Cambrai, 62000 Arras",
    "sg:orig_category":"Unclassifiable Establishments",
    "sg:phone":"+33 3 21 73 26 36",
    "sg:province":"Nord Pas-de-Calais",
    "wof:name":"Delaplace Et Compagnie Fermetures S.a.",
    "wof:placetype":"venue"
},
  "geometry": {"coordinates":[2.793567,50.28495],"type":"Point"}
}