{
  "type": "Feature",
  "properties": {
    "addr:full":"8 Rue Sebastien Lehr 88100 St Di\u00e9 Lorraine 88100",
    "addr:housenumber":"8",
    "addr:postcode":"88100;88100",
    "addr:street":"Rue Sebastien Lehr",
    "iso:country":"FR",
    "sg:address":"8 Rue Sebastien Lehr 88100 St Di\u00e9",
    "sg:classifiers":[
        {
            "category":"Shopping",
            "type":"Retail Goods"
        }
    ],
    "sg:phone":"+33 3 29 52 20 20",
    "sg:postcode":"88100",
    "sg:province":"Lorraine",
    "sg:tags":[
        "metallurgy",
        "finished",
        "-",
        "metalworking",
        "metallic"
    ],
    "wof:name":"Arvin Meritor France",
    "wof:placetype":"venue"
},
  "geometry": {"coordinates":[6.89995,48.249744],"type":"Point"}
}