{
  "type": "Feature",
  "properties": {
    "addr:full":"16, Rue du Pont Lafleur, 91670 Angerville Ile de France",
    "addr:housenumber":"16",
    "addr:postcode":"91670;ile",
    "addr:street":"Rue Du Pont Lafleur",
    "iso:country":"FR",
    "sg:address":"16, Rue du Pont Lafleur, 91670 Angerville",
    "sg:orig_category":"Unclassifiable Establishments",
    "sg:phone":"+33 1 64 95 20 13",
    "sg:province":"Ile de France",
    "wof:name":"Etablissements W. Doyen S.a.",
    "wof:placetype":"venue"
},
  "geometry": {"coordinates":[2.002631,48.319145],"type":"Point"}
}