{
  "type": "Feature",
  "properties": {
    "iso:country":"FR",
    "sg:address":"B.P. 3123, 27031 Evreux C\u00e9dex^^Rte Melleville - Chemin D\u00e9partemental 28, 27930 Angerville la Campagn",
    "sg:orig_category":"Non-Classified Establishments",
    "sg:phone":"+33 2 32 23 08 08",
    "sg:postcode":"27930",
    "sg:province":"Haute Normandie",
    "wof:name":"Baziret Transports S.a.",
    "wof:placetype":"venue"
},
  "geometry": {"coordinates":[1.17113,48.963875],"type":"Point"}
}