{
  "type": "Feature",
  "properties": {
    "iso:country":"FR",
    "sg:address":"Rte de Castelnaudary",
    "sg:city":"Revel",
    "sg:orig_category":"Non-Classified Establishments",
    "sg:phone":"+33 5 61 83 53 14",
    "sg:postcode":"31250",
    "sg:province":"Midi Pyr\u00e9n\u00e9es",
    "wof:name":"Autogaz S.a.r.l.",
    "wof:placetype":"venue"
},
  "geometry": {"coordinates":[1.97298,43.450016],"type":"Point"}
}