{
  "type": "Feature",
  "properties": {
    "addr:full":"2, Rue Edisson - ZI de la Butte, 91620 Nozay Ile de France",
    "addr:housenumber":"2",
    "addr:postcode":"91620;ile",
    "addr:street":"Rue Edisson Zi De La Butte",
    "iso:country":"FR",
    "sg:address":"2, Rue Edisson - ZI de la Butte, 91620 Nozay",
    "sg:orig_category":"Unclassifiable Establishments",
    "sg:phone":"+33 1 69 01 64 80",
    "sg:province":"Ile de France",
    "wof:name":"Batelect S.a.r.l.",
    "wof:placetype":"venue"
},
  "geometry": {"coordinates":[2.242235,48.66037],"type":"Point"}
}