{
  "type": "Feature",
  "properties": {
    "addr:full":"Bd Emile Cazelles Saint Gilles Languedoc-Roussillon 30800",
    "addr:postcode":"30800",
    "addr:street":"Bd Emile Cazelles Saint Gilles",
    "iso:country":"FR",
    "sg:address":"Bd Emile Cazelles",
    "sg:city":"Saint Gilles",
    "sg:orig_category":"Non-Classified Establishments",
    "sg:phone":"+33 4 66 87 32 16",
    "sg:postcode":"30800",
    "sg:province":"Languedoc-Roussillon",
    "wof:name":"S.g.b.m. S.a.r.l. - Saint Gilles Bois Et Mat\u00e9riaux",
    "wof:placetype":"venue"
},
  "geometry": {"coordinates":[4.43385,43.674801],"type":"Point"}
}