{
  "type": "Feature",
  "properties": {
    "addr:full":"29 rue Beno\u00eet Malon 92800 Puteaux Ile de France 92800",
    "addr:housenumber":"29",
    "addr:postcode":"92800;92800",
    "addr:street":"Rue Benoi\u0302T Malon",
    "iso:country":"FR",
    "sg:address":"29 rue Beno\u00eet Malon 92800 Puteaux",
    "sg:orig_category":"Engravings, Technical",
    "sg:phone":"+33 1 47 72 12 78",
    "sg:postcode":"92800",
    "sg:province":"Ile de France",
    "wof:name":"Ats Poirier S.a.r.l.",
    "wof:placetype":"venue"
},
  "geometry": {"coordinates":[2.241424,48.880215],"type":"Point"}
}