{
  "type": "Feature",
  "properties": {
    "addr:full":"B.P. 7, 49370 B\u00e9con les Granits^^10, Av. des Granitiers - ZA de la Grande Chauss\u00e9e, 49370 B\u00e9con les  Pays de Loire 49370",
    "addr:housenumber":"7",
    "addr:postcode":"49370;49370;49370",
    "addr:street":"B.P.;Av. Des Granitiers Za De La Grande Chausse\u0301E;Les Pays",
    "iso:country":"FR",
    "sg:address":"B.P. 7, 49370 B\u00e9con les Granits^^10, Av. des Granitiers - ZA de la Grande Chauss\u00e9e, 49370 B\u00e9con les ",
    "sg:orig_category":"Non-Classified Establishments",
    "sg:phone":"+33 2 41 77 04 40",
    "sg:postcode":"49370",
    "sg:province":"Pays de Loire",
    "wof:name":"Coremat E.u.r.l.",
    "wof:placetype":"venue"
},
  "geometry": {"coordinates":[-7.120802,43.345642],"type":"Point"}
}