{
  "type": "Feature",
  "properties": {
    "addr:full":"61, Bd de la Couronne Champagne, 08000 Charleville M\u00e9zi\u00e8res Charleville-M\u00e9zi\u00e8res Champagne 08000",
    "addr:housenumber":"61",
    "addr:postcode":"08000;08000",
    "addr:street":"Bd De La Couronne Champagne",
    "iso:country":"FR",
    "sg:address":"61, Bd de la Couronne Champagne, 08000 Charleville M\u00e9zi\u00e8res",
    "sg:city":"Charleville-M\u00e9zi\u00e8res",
    "sg:orig_category":"M\u00c9CANO-SOUDURE D\u00c9COUPAGE AU LASER 3 KW - 4000 X 2000 chaudronnerie t\u00f4lerie moyenne, cisaillage, plia",
    "sg:phone":"+33 3 24 57 05 17",
    "sg:postcode":"08000",
    "sg:province":"Champagne",
    "wof:name":"S.i.m.a. S.a.",
    "wof:placetype":"venue"
},
  "geometry": {"coordinates":[4.71225,49.756302],"type":"Point"}
}