{
  "type": "Feature",
  "properties": {
    "addr:full":"13, Place Beno\u00eet Cr\u00e9pu, 69005 Lyon Rhone-Alpes",
    "addr:housenumber":"13",
    "addr:postcode":"69005",
    "addr:street":"Place Benoi\u0302T Cre\u0301Pu",
    "iso:country":"FR",
    "sg:address":"13, Place Beno\u00eet Cr\u00e9pu, 69005 Lyon",
    "sg:orig_category":"Unclassifiable Establishments",
    "sg:phone":"+33 4 78 37 18 93",
    "sg:province":"Rhone-Alpes",
    "wof:name":"Tilsitt Communication S.a.r.l.",
    "wof:placetype":"venue"
},
  "geometry": {"coordinates":[4.825672,45.758015],"type":"Point"}
}