{
  "type": "Feature",
  "properties": {
    "addr:full":"7 Rue Froide Fontaine 49600 Beaupreau Pays de Loire 49600",
    "addr:housenumber":"7",
    "addr:postcode":"49600;49600",
    "addr:street":"Rue Froide Fontaine;Beaupreau",
    "iso:country":"FR",
    "sg:address":"7 Rue Froide Fontaine 49600 Beaupreau",
    "sg:classifiers":[
        {
            "category":"Shopping",
            "subcategory":"Luggage & Leather Goods",
            "type":"Retail Goods"
        }
    ],
    "sg:phone":"+33 2 41 63 01 45",
    "sg:postcode":"49600",
    "sg:province":"Pays de Loire",
    "sg:tags":[
        "shoe"
    ],
    "wof:name":"Bopy Humeau Beaupreau Sas",
    "wof:placetype":"venue"
},
  "geometry": {"coordinates":[-0.99724,47.201294],"type":"Point"}
}