{
  "type": "Feature",
  "properties": {
    "addr:full":"3, Petite Rue de la Course, 67000 Strasbourg Strasbourg Alsace 67000",
    "addr:housenumber":"3",
    "addr:postcode":"67000;67000",
    "addr:street":"Petite Rue De La Course",
    "iso:country":"FR",
    "sg:address":"3, Petite Rue de la Course, 67000 Strasbourg",
    "sg:city":"Strasbourg",
    "sg:orig_category":"Unclassifiable Establishments",
    "sg:phone":"+33 3 88 22 77 77",
    "sg:postcode":"67000",
    "sg:province":"Alsace",
    "wof:name":"Tempor S.a.r.l.",
    "wof:placetype":"venue"
},
  "geometry": {"coordinates":[7.735518,48.582649],"type":"Point"}
}