{
  "type": "Feature",
  "properties": {
    "iso:country":"FR",
    "sg:address":"B.P. 3, 81210 Lacrouzette^^10, Chemin de la Clayrie, 81210 Lacrouzette",
    "sg:orig_category":"Non-Classified Establishments",
    "sg:phone":"+33 5 63 82 11 36",
    "sg:province":"Midi Pyr\u00e9n\u00e9es",
    "wof:name":"Maffre Transports S.a.",
    "wof:placetype":"venue"
},
  "geometry": {"coordinates":[2.339068,43.662106],"type":"Point"}
}