{
  "type": "Feature",
  "properties": {
    "addr:full":"350, Rte du Nord, 82000 Montauban Midi Pyr\u00e9n\u00e9es",
    "addr:housenumber":"350",
    "addr:postcode":"82000",
    "addr:street":"Rte Du Nord",
    "iso:country":"FR",
    "sg:address":"350, Rte du Nord, 82000 Montauban",
    "sg:orig_category":"Unclassifiable Establishments",
    "sg:phone":"+33 5 63 03 12 62",
    "sg:province":"Midi Pyr\u00e9n\u00e9es",
    "wof:name":"Etablissements Salsi S.a.r.l.",
    "wof:placetype":"venue"
},
  "geometry": {"coordinates":[1.38621,44.042061],"type":"Point"}
}