{
  "type": "Feature",
  "properties": {
    "addr:full":"28 Rue De La Fougere 88150 Chavelot Lorraine 88150",
    "addr:housenumber":"28",
    "addr:postcode":"88150;88150",
    "addr:street":"Rue De La Fougere",
    "iso:country":"FR",
    "sg:address":"28 Rue De La Fougere 88150 Chavelot",
    "sg:classifiers":[
        {
            "category":"Shopping",
            "subcategory":"Computers & Home Electronics",
            "type":"Retail Goods"
        }
    ],
    "sg:phone":"+33 3 29 34 65 44",
    "sg:postcode":"88150",
    "sg:province":"Lorraine",
    "sg:tags":[
        "electric",
        "electricity",
        "component",
        "equipment",
        "electrical",
        "electronic"
    ],
    "wof:name":"Jad'electronique Plus",
    "wof:placetype":"venue"
},
  "geometry": {"coordinates":[6.430884,48.228531],"type":"Point"}
}