{
  "type": "Feature",
  "properties": {
    "addr:full":"34, Rue Ambroise Croizat, 60160 Montataire Picardie 60160",
    "addr:housenumber":"34",
    "addr:postcode":"60160;60160",
    "addr:street":"Rue Ambroise Croizat;Picardie",
    "iso:country":"FR",
    "sg:address":"34, Rue Ambroise Croizat, 60160 Montataire",
    "sg:orig_category":"Non-Classified Establishments",
    "sg:phone":"+33 3 44 61 78 00",
    "sg:postcode":"60160",
    "sg:province":"Picardie",
    "wof:name":"Ducros Services Rapides S.a.",
    "wof:placetype":"venue"
},
  "geometry": {"coordinates":[2.434553,49.251209],"type":"Point"}
}