{
  "type": "Feature",
  "properties": {
    "addr:full":"12, Chemin du G\u00e9nie, 74000 Annecy le Vieux Rhone-Alpes 74000",
    "addr:housenumber":"12",
    "addr:postcode":"74000;74000",
    "addr:street":"Chemin Du Ge\u0301Nie",
    "iso:country":"FR",
    "sg:address":"12, Chemin du G\u00e9nie, 74000 Annecy le Vieux",
    "sg:orig_category":"Non-Classified Establishments",
    "sg:phone":"+33 4 50 57 06 73",
    "sg:postcode":"74000",
    "sg:province":"Rhone-Alpes",
    "wof:name":"Bello Joseph & Fils S.a.r.l.",
    "wof:placetype":"venue"
},
  "geometry": {"coordinates":[6.128832,45.898781],"type":"Point"}
}