{
  "type": "Feature",
  "properties": {
    "addr:full":"Av. Emile de Villeneuve Castres Midi Pyr\u00e9n\u00e9es 81100",
    "addr:postcode":"81100",
    "addr:street":"Av. Emile De Villeneuve",
    "iso:country":"FR",
    "sg:address":"Av. Emile de Villeneuve",
    "sg:city":"Castres",
    "sg:orig_category":"Unclassifiable Establishments",
    "sg:phone":"+33 5 63 35 74 48",
    "sg:postcode":"81100",
    "sg:province":"Midi Pyr\u00e9n\u00e9es",
    "wof:name":"Anciens Etablissements F. Hardouin S.a.r.l.",
    "wof:placetype":"venue"
},
  "geometry": {"coordinates":[2.24355,43.60186],"type":"Point"}
}