{
  "type": "Feature",
  "properties": {
    "iso:country":"FR",
    "sg:address":"19 Avenue Bagnell 64110 Juran\u00e7on",
    "sg:city":"Juran\u00e7on",
    "sg:classifiers":[
        {
            "category":"Home & Garden",
            "subcategory":"Furniture",
            "type":"Retail Goods"
        }
    ],
    "sg:phone":"+33 5 59 06 25 22",
    "sg:postcode":"64110",
    "sg:province":"Aquitaine",
    "sg:tags":[
        "professional",
        "household",
        "wood"
    ],
    "wof:name":"Serem",
    "wof:placetype":"venue"
},
  "geometry": {"coordinates":[-0.389086,43.280441],"type":"Point"}
}