{
  "type": "Feature",
  "properties": {
    "addr:full":"76, Rue du Dauphin\u00e9, 69960 Corbas Rhone-Alpes 69960",
    "addr:housenumber":"76",
    "addr:postcode":"69960;69960",
    "addr:street":"Rue Du Dauphine\u0301",
    "iso:country":"FR",
    "sg:address":"76, Rue du Dauphin\u00e9, 69960 Corbas",
    "sg:orig_category":"Non-Classified Establishments",
    "sg:phone":"+33 4 72 50 55 78",
    "sg:postcode":"69960",
    "sg:province":"Rhone-Alpes",
    "wof:name":"Apave Agence Corbas S.a.",
    "wof:placetype":"venue"
},
  "geometry": {"coordinates":[4.91093,45.685265],"type":"Point"}
}