{
  "type": "Feature",
  "properties": {
    "addr:full":"Av. du Campon - Central Buro Le Cannet Provence-Alpes-C\u00f4te d'Azur 06110",
    "addr:postcode":"06110",
    "addr:street":"Av. Du Campon Central;Cannet",
    "iso:country":"FR",
    "sg:address":"Av. du Campon - Central Buro",
    "sg:city":"Le Cannet",
    "sg:orig_category":"Non-Classified Establishments",
    "sg:phone":"+33 4 92 18 92 00",
    "sg:postcode":"06110",
    "sg:province":"Provence-Alpes-C\u00f4te d'Azur",
    "wof:name":"M.c.s. S.a. - Micro Computer Services Cannes",
    "wof:placetype":"venue"
},
  "geometry": {"coordinates":[7.00241,43.570782],"type":"Point"}
}