{
  "type": "Feature",
  "properties": {
    "iso:country":"FR",
    "sg:address":"32, Rue Boussingault, 75013 Paris",
    "sg:orig_category":"Non-Classified Establishments",
    "sg:phone":"+33 1 58 40 80 00",
    "sg:postcode":"75013",
    "sg:province":"Ile de France",
    "wof:name":"Axicare S.a.",
    "wof:placetype":"venue"
},
  "geometry": {"coordinates":[2.344191,48.824593],"type":"Point"}
}