{
  "type": "Feature",
  "properties": {
    "iso:country":"FR",
    "sg:address":"3 rue Yves de Kergu\u00e9len 56400 Auray",
    "sg:city":"Auray",
    "sg:classifiers":[
        {
            "category":"Social Services",
            "subcategory":"Child Care",
            "type":"Services"
        }
    ],
    "sg:phone":"+33 2 97 24 11 66",
    "sg:postcode":"56400",
    "sg:province":"Bretagne",
    "sg:tags":[
        "baby",
        "product"
    ],
    "wof:name":"Thermobaby Sa",
    "wof:placetype":"venue"
},
  "geometry": {"coordinates":[-3.003343,47.66338],"type":"Point"}
}