{
  "type": "Feature",
  "properties": {
    "addr:full":"B.P. 17, 08350 Donchery^^9, Rue Georges Cl\u00e9menceau, 08350 Donchery Vrigne-Meuse Champagne 08350",
    "addr:postcode":"08350;08350;08350",
    "addr:street":"B.P. 17;Rue Georges Cle\u0301Menceau;Champagne",
    "iso:country":"FR",
    "sg:address":"B.P. 17, 08350 Donchery^^9, Rue Georges Cl\u00e9menceau, 08350 Donchery",
    "sg:city":"Vrigne-Meuse",
    "sg:orig_category":"Non-Classified Establishments",
    "sg:phone":"+33 3 24 27 78 40",
    "sg:postcode":"08350",
    "sg:province":"Champagne",
    "wof:name":"Euromold S.a.",
    "wof:placetype":"venue"
},
  "geometry": {"coordinates":[4.88706,49.692299],"type":"Point"}
}