{
  "type": "Feature",
  "properties": {
    "addr:full":"6, Av de la R\u00e9publique, 51190 Le Mesnil sur Oger Champagne 51190",
    "addr:postcode":"51190;51190",
    "addr:street":"Av De La Re\u0301Publique;Mesnil;Oger Champagne",
    "iso:country":"FR",
    "sg:address":"6, Av de la R\u00e9publique, 51190 Le Mesnil sur Oger",
    "sg:orig_category":"Non-Classified Establishments",
    "sg:phone":"+33 3 26 57 52 29",
    "sg:postcode":"51190",
    "sg:province":"Champagne",
    "wof:name":"Champagne Andr\u00e9 Jacquart Et Fils",
    "wof:placetype":"venue"
},
  "geometry": {"coordinates":[4.026507,48.948566],"type":"Point"}
}