{
  "type": "Feature",
  "properties": {
    "iso:country":"FR",
    "sg:address":"B.P. 14, 12300 Decazeville^^ZI Combal, 12300 Decazeville",
    "sg:orig_category":"Non-Classified Establishments",
    "sg:phone":"+33 5 65 43 42 10",
    "sg:province":"Midi Pyr\u00e9n\u00e9es",
    "wof:name":"Mti S.a. - M\u00e9canique Et Travaux Industriels",
    "wof:placetype":"venue"
},
  "geometry": {"coordinates":[2.307615,44.541191],"type":"Point"}
}