{
  "type": "Feature",
  "properties": {
    "iso:country":"FR",
    "sg:address":"B.P. 97, 69280 Marcy l'Etoile^^Parc d'Activit\u00e9s Sainte Consorce - B\u00e2t. G7, 69280 Marcy l'Etoile",
    "sg:orig_category":"Non-Classified Establishments",
    "sg:phone":"+33 4 37 22 50 30",
    "sg:postcode":"69280",
    "sg:province":"Rhone-Alpes",
    "wof:name":"Cortex S.a.",
    "wof:placetype":"venue"
},
  "geometry": {"coordinates":[2.02819,50.033714],"type":"Point"}
}