{
  "type": "Feature",
  "properties": {
    "addr:full":"Le Bourg 21510 Moitron Moitron Bourgogne 21510",
    "addr:postcode":"21510;21510",
    "addr:street":"Le Bourg",
    "iso:country":"FR",
    "sg:address":"Le Bourg 21510 Moitron",
    "sg:city":"Moitron",
    "sg:orig_category":"Unclassifiable Establishments",
    "sg:phone":"+33 3 80 93 98 90",
    "sg:postcode":"21510",
    "sg:province":"Bourgogne",
    "wof:name":"Logarithme S.a.r.l.",
    "wof:placetype":"venue"
},
  "geometry": {"coordinates":[4.731865,47.664902],"type":"Point"}
}