{
  "type": "Feature",
  "properties": {
    "addr:full":"A\u00e9roport Nice C\u00f4te d'Azur - Gare de Fr\u00eat Nice C\u00e9dex 3 Provence-Alpes-C\u00f4te d'Azur 06281",
    "addr:postcode":"06281",
    "iso:country":"FR",
    "sg:address":"A\u00e9roport Nice C\u00f4te d'Azur - Gare de Fr\u00eat",
    "sg:city":"Nice C\u00e9dex 3",
    "sg:orig_category":"Non-Classified Establishments",
    "sg:phone":"+33 4 93 21 35 53",
    "sg:postcode":"06281",
    "sg:province":"Provence-Alpes-C\u00f4te d'Azur",
    "wof:name":"S.c.a.c. S.a.",
    "wof:placetype":"venue"
},
  "geometry": {"coordinates":[7.267039,43.734467],"type":"Point"}
}