{
  "type": "Feature",
  "properties": {
    "addr:full":"Av Augustin Grangeon BP 135 83990 Saint-Tropez Centre",
    "addr:housenumber":"135",
    "addr:postcode":"83990",
    "addr:street":"Av Augustin Grangeon Bp;Saint-Tropez Centre",
    "iso:country":"FR",
    "sg:address":"Av Augustin Grangeon BP 135 83990 Saint-Tropez",
    "sg:classifiers":[
        {
            "category":"Travel",
            "subcategory":"Hotels & Motels",
            "type":"Entertainment"
        }
    ],
    "sg:phone":"+33 4 94 97 28 28",
    "sg:province":"Centre",
    "sg:tags":[
        "hotels",
        "business",
        "restaurant"
    ],
    "wof:name":"Saint-tropez Hotel Des Lices Sa",
    "wof:placetype":"venue"
},
  "geometry": {"coordinates":[6.6405,43.269733],"type":"Point"}
}