{
  "type": "Feature",
  "properties": {
    "iso:country":"FR",
    "sg:address":"18 rue du 4 Septembre; Aix en Provence; 13611",
    "sg:classifiers":[
        {
            "category":"Banks & Credit Unions",
            "subcategory":"Bank",
            "type":"Services"
        }
    ],
    "sg:phone":"+33 3342385764",
    "sg:province":"Nord Pas-de-Calais",
    "wof:name":"Banque De France",
    "wof:placetype":"venue"
},
  "geometry": {"coordinates":[5.450064,43.525513],"type":"Point"}
}