{
  "type": "Feature",
  "properties": {
    "addr:full":"8, Rue Faulx, 88230 Fraize Lorraine",
    "addr:housenumber":"8",
    "addr:postcode":"88230",
    "addr:street":"Rue Faulx",
    "iso:country":"FR",
    "sg:address":"8, Rue Faulx, 88230 Fraize",
    "sg:orig_category":"Unclassifiable Establishments",
    "sg:phone":"+33 3 29 52 76 07",
    "sg:province":"Lorraine",
    "wof:name":"Logistic Systems S.a.r.l.",
    "wof:placetype":"venue"
},
  "geometry": {"coordinates":[7.011323,48.178623],"type":"Point"}
}