{
  "type": "Feature",
  "properties": {
    "addr:full":"B.P. 5, 19600 Saint Pantal\u00e9on de Larche C\u00e9dex^^ZA de Vermeil, 19600 Saint Pantal\u00e9on de Larche Limousin",
    "addr:housenumber":"5",
    "addr:postcode":"19600;19600 saint",
    "addr:street":"B.P.",
    "iso:country":"FR",
    "sg:address":"B.P. 5, 19600 Saint Pantal\u00e9on de Larche C\u00e9dex^^ZA de Vermeil, 19600 Saint Pantal\u00e9on de Larche",
    "sg:orig_category":"Non-Classified Establishments",
    "sg:phone":"+33 5 55 85 35 38",
    "sg:province":"Limousin",
    "wof:name":"Sanz S.a.",
    "wof:placetype":"venue"
},
  "geometry": {"coordinates":[1.44653,45.140591],"type":"Point"}
}