{
  "type": "Feature",
  "properties": {
    "addr:full":"2, Rte de Champagne, 69130 Ecully Rhone-Alpes 69130",
    "addr:housenumber":"2",
    "addr:postcode":"69130;69130",
    "addr:street":"Rte De Champagne;Rhone-Alpes",
    "iso:country":"FR",
    "sg:address":"2, Rte de Champagne, 69130 Ecully",
    "sg:orig_category":"Unclassifiable Establishments",
    "sg:phone":"+33 4 72 18 08 08",
    "sg:postcode":"69130",
    "sg:province":"Rhone-Alpes",
    "wof:name":"A.p. Consultants S.a.",
    "wof:placetype":"venue"
},
  "geometry": {"coordinates":[4.78166,45.78373],"type":"Point"}
}