{
  "type": "Feature",
  "properties": {
    "iso:country":"FR",
    "sg:address":"51, Rue de Saint Fuscien, 60210 Grandvilliers",
    "sg:orig_category":"Unclassifiable Establishments",
    "sg:phone":"+33 3 44 46 53 54",
    "sg:province":"Picardie",
    "wof:name":"Sinet Imprimerie S.a.",
    "wof:placetype":"venue"
},
  "geometry": {"coordinates":[1.941287,49.660347],"type":"Point"}
}