{
  "type": "Feature",
  "properties": {
    "addr:full":"20, Bd Louis Seguin, 92700 Colombes Ile de France",
    "addr:housenumber":"20",
    "addr:postcode":"92700;ile",
    "addr:street":"Bd Louis Seguin",
    "iso:country":"FR",
    "sg:address":"20, Bd Louis Seguin, 92700 Colombes",
    "sg:orig_category":"Unclassifiable Establishments",
    "sg:phone":"+33 1 46 52 23 78",
    "sg:province":"Ile de France",
    "wof:name":"S.e.m.m.b - Soci\u00e9t\u00e9 D'exploitation Des Mat\u00e9riels Martin Bake",
    "wof:placetype":"venue"
},
  "geometry": {"coordinates":[2.248452,48.933865],"type":"Point"}
}