{
  "type": "Feature",
  "properties": {
    "addr:full":"3, Rue de la Blanchardi\u00e8re, 49300 Cholet Pays de Loire",
    "addr:housenumber":"3",
    "addr:postcode":"49300",
    "addr:street":"Rue De La Blanchardie\u0300Re",
    "iso:country":"FR",
    "sg:address":"3, Rue de la Blanchardi\u00e8re, 49300 Cholet",
    "sg:orig_category":"Unclassifiable Establishments",
    "sg:phone":"+33 2 41 62 47 58",
    "sg:province":"Pays de Loire",
    "wof:name":"Unib\u00e9ton",
    "wof:placetype":"venue"
},
  "geometry": {"coordinates":[-0.844466,47.067829],"type":"Point"}
}