{
  "type": "Feature",
  "properties": {
    "iso:country":"FR",
    "sg:address":"1 Rue De Chatillon 92170 Vanves",
    "sg:classifiers":[
        {
            "category":"Professional",
            "subcategory":"Printing & Photocopies",
            "type":"Services"
        }
    ],
    "sg:phone":"+33 1 58 88 00 10",
    "sg:province":"Ile de France",
    "sg:tags":[
        "publishing"
    ],
    "wof:name":"Regie Generale D'annuaires (rga)",
    "wof:placetype":"venue"
},
  "geometry": {"coordinates":[2.284093,48.817791],"type":"Point"}
}