{
  "type": "Feature",
  "properties": {
    "addr:full":"3 avenue des Cypres 53950 Louverne Pays de Loire 53950",
    "addr:housenumber":"3",
    "addr:postcode":"53950;53950",
    "addr:street":"Avenue Des Cypres;Louverne",
    "iso:country":"FR",
    "sg:address":"3 avenue des Cypres 53950 Louverne",
    "sg:classifiers":[
        {
            "category":"Animal Shelter",
            "type":"Public Place"
        }
    ],
    "sg:phone":"+33 2 43 37 87 47",
    "sg:postcode":"53950",
    "sg:province":"Pays de Loire",
    "sg:tags":[
        "feed",
        "flavouring"
    ],
    "wof:name":"Lallemand Animal Nutrition Sa",
    "wof:placetype":"venue"
},
  "geometry": {"coordinates":[-0.712945,48.126522],"type":"Point"}
}