{
  "type": "Feature",
  "properties": {
    "addr:full":"B.P. 243, 56602 Lanester C\u00e9dex^^237, Rue Amp\u00e8re - ZI Kerpont, 56600 Lanester Lanester Bretagne 56600",
    "addr:housenumber":"b.p. 243",
    "addr:postcode":"56602;56600;56600",
    "addr:street":"Rue Ampe\u0300Re Zi Kerpont",
    "iso:country":"FR",
    "sg:address":"B.P. 243, 56602 Lanester C\u00e9dex^^237, Rue Amp\u00e8re - ZI Kerpont, 56600 Lanester",
    "sg:city":"Lanester",
    "sg:orig_category":"Non-Classified Establishments",
    "sg:phone":"+33 2 97 81 20 04",
    "sg:postcode":"56600",
    "sg:province":"Bretagne",
    "wof:name":"La Biscuiterie De Kerpont S.a.",
    "wof:placetype":"venue"
},
  "geometry": {"coordinates":[-3.345244,47.76532],"type":"Point"}
}