{
  "type": "Feature",
  "properties": {
    "addr:full":"50, Av. Gaston Cabannes, 33270 Floirac Floirac Aquitaine 33270",
    "addr:postcode":"33270;33270",
    "addr:street":"50 Av. Gaston Cabannes",
    "iso:country":"FR",
    "sg:address":"50, Av. Gaston Cabannes, 33270 Floirac",
    "sg:city":"Floirac",
    "sg:orig_category":"Unclassifiable Establishments",
    "sg:phone":"+33 5 56 86 36 19",
    "sg:postcode":"33270",
    "sg:province":"Aquitaine",
    "wof:name":"Kichim S.a.",
    "wof:placetype":"venue"
},
  "geometry": {"coordinates":[-0.523477,44.828587],"type":"Point"}
}