{
  "type": "Feature",
  "properties": {
    "iso:country":"FR",
    "sg:address":"K\u00e9rouel 29910 Tr\u00e9gunc",
    "sg:city":"Tr\u00e9gunc",
    "sg:orig_category":"Unclassifiable Establishments",
    "sg:phone":"+33 2 98 97 63 82",
    "sg:postcode":"29910",
    "sg:province":"Bretagne",
    "wof:name":"Les Gourmandises De Fanny S.a.",
    "wof:placetype":"venue"
},
  "geometry": {"coordinates":[-3.863847,47.855946],"type":"Point"}
}