{
  "type": "Feature",
  "properties": {
    "addr:full":"1300 R Antoine De Saint Exupery 44150 Ancenis Pays de Loire 44150",
    "addr:housenumber":"1300",
    "addr:postcode":"44150;44150",
    "addr:street":"R Antoine De Saint Exupery",
    "iso:country":"FR",
    "sg:address":"1300 R Antoine De Saint Exupery 44150 Ancenis",
    "sg:classifiers":[
        {
            "category":"Banks & Credit Unions",
            "subcategory":"Investment Brokerage",
            "type":"Services"
        }
    ],
    "sg:phone":"+33 2 51 14 51 44",
    "sg:postcode":"44150",
    "sg:province":"Pays de Loire",
    "sg:tags":[
        "lift",
        "truck"
    ],
    "wof:name":"Toyota Industrial Equipment Europe Sarl",
    "wof:placetype":"venue"
},
  "geometry": {"coordinates":[-1.188637,47.409878],"type":"Point"}
}