{
  "type": "Feature",
  "properties": {
    "addr:full":"9 ter, Rue Carnot, 94270 Le Kremlin Bic\u00eatre Ile de France 94270",
    "addr:housenumber":"9 ter",
    "addr:postcode":"94270;94270",
    "addr:street":"Rue Carnot",
    "iso:country":"FR",
    "sg:address":"9 ter, Rue Carnot, 94270 Le Kremlin Bic\u00eatre",
    "sg:orig_category":"Non-Classified Establishments",
    "sg:phone":"+33 1 45 15 12 00",
    "sg:postcode":"94270",
    "sg:province":"Ile de France",
    "wof:name":"Bic\u00eatre Communication S.a.r.l.",
    "wof:placetype":"venue"
},
  "geometry": {"coordinates":[2.364113,48.80957],"type":"Point"}
}