{
  "type": "Feature",
  "properties": {
    "addr:full":"48, Av. Charles de Gaulle, 84130 Le Pontet Le Pontet Rhone-Alpes 73110",
    "addr:postcode":"84130;73110",
    "addr:street":"48 Av. Charles De Gaulle;Rhone-Alpes",
    "iso:country":"FR",
    "sg:address":"48, Av. Charles de Gaulle, 84130 Le Pontet",
    "sg:city":"Le Pontet",
    "sg:orig_category":"Unclassifiable Establishments",
    "sg:phone":"+33 4 90 32 51 91",
    "sg:postcode":"73110",
    "sg:province":"Rhone-Alpes",
    "wof:name":"C.r.i.t. Int\u00e9rim S.a.",
    "wof:placetype":"venue"
},
  "geometry": {"coordinates":[4.847159,43.956581],"type":"Point"}
}