{
  "type": "Feature",
  "properties": {
    "iso:country":"FR",
    "sg:address":"Route De Serigne 85201 FONTENAY LE COMTE",
    "sg:classifiers":[
        {
            "category":"Bars & Pubs",
            "subcategory":"Sports Bar",
            "type":"Food & Drink"
        }
    ],
    "sg:phone":"+33 2 51 69 40 55",
    "sg:province":"Champagne",
    "sg:tags":[
        "graining"
    ],
    "wof:name":"Etablissements Leduc Et Lubot Sas",
    "wof:placetype":"venue"
},
  "geometry": {"coordinates":[-0.817386,46.478714],"type":"Point"}
}