{
  "type": "Feature",
  "properties": {
    "addr:full":"2 all\u00e9e Roland Garros 93360 Neuilly Plaisance Ile de France 93360",
    "addr:housenumber":"2",
    "addr:postcode":"93360;93360",
    "addr:street":"Alle\u0301E Roland Garros;Ile De France",
    "iso:country":"FR",
    "sg:address":"2 all\u00e9e Roland Garros 93360 Neuilly Plaisance",
    "sg:classifiers":[
        {
            "category":"Food & Beverages",
            "subcategory":"Bakery",
            "type":"Retail Goods"
        }
    ],
    "sg:phone":"+33 1 43 09 87 00",
    "sg:postcode":"93360",
    "sg:province":"Ile de France",
    "sg:tags":[
        "articles",
        "edible",
        "also",
        "baker",
        "decoration",
        "confectioner"
    ],
    "wof:name":"Etablissements Lelievre Sa",
    "wof:placetype":"venue"
},
  "geometry": {"coordinates":[2.516919,48.864677],"type":"Point"}
}