{
  "type": "Feature",
  "properties": {
    "iso:country":"FR",
    "sg:address":"B.P. 2, 68240 Sigolsheim^^17, Rue du Vieux Moulin, 68240 Sigolsheim",
    "sg:city":"Sigolsheim",
    "sg:orig_category":"Non-Classified Establishments",
    "sg:phone":"+33 3 89 78 25 11",
    "sg:postcode":"68240",
    "sg:province":"Alsace",
    "wof:name":"Romann Distillerie S.a.",
    "wof:placetype":"venue"
},
  "geometry": {"coordinates":[7.19303,48.170895],"type":"Point"}
}