{
  "type": "Feature",
  "properties": {
    "iso:country":"FR",
    "sg:address":"Melun Senart; Tigery; 91250",
    "sg:classifiers":[
        {
            "category":"Banks & Credit Unions",
            "subcategory":"Bank",
            "type":"Services"
        }
    ],
    "sg:phone":"+33 1 60 90 70 89",
    "sg:postcode":"91250",
    "sg:province":"Ile de France",
    "wof:name":"Soci\u00e9t\u00e9 G\u00e9n\u00e9rale",
    "wof:placetype":"venue"
},
  "geometry": {"coordinates":[2.50729,48.639343],"type":"Point"}
}