{
  "type": "Feature",
  "properties": {
    "addr:full":"13, Rue des Grands Mortiers - ZI, 37700 Saint Pierre des Corps La Ville-aux-Dames Centre 37700",
    "addr:housenumber":"13",
    "addr:postcode":"37700;37700",
    "addr:street":"Rue Des Grands Mortiers Zi;Des Corps La",
    "iso:country":"FR",
    "sg:address":"13, Rue des Grands Mortiers - ZI, 37700 Saint Pierre des Corps",
    "sg:city":"La Ville-aux-Dames",
    "sg:orig_category":"Unclassifiable Establishments",
    "sg:phone":"+33 825 31 32 33",
    "sg:postcode":"37700",
    "sg:province":"Centre",
    "wof:name":"Lagallais Bouchard",
    "wof:placetype":"venue"
},
  "geometry": {"coordinates":[0.718755,47.389648],"type":"Point"}
}