{
  "type": "Feature",
  "properties": {
    "addr:full":"1, Chemin de la Bourrellerie, 18100 Th\u00e9nioux Th\u00e9nioux Centre 18100",
    "addr:housenumber":"1;the\u0301nioux",
    "addr:postcode":"18100;18100",
    "addr:street":"Chemin De La Bourrellerie",
    "iso:country":"FR",
    "sg:address":"1, Chemin de la Bourrellerie, 18100 Th\u00e9nioux",
    "sg:city":"Th\u00e9nioux",
    "sg:orig_category":"Unclassifiable Establishments",
    "sg:phone":"+33 2 48 52 93 70",
    "sg:postcode":"18100",
    "sg:province":"Centre",
    "wof:name":"J.b.i. S.a.",
    "wof:placetype":"venue"
},
  "geometry": {"coordinates":[1.940519,47.255005],"type":"Point"}
}