{
  "type": "Feature",
  "properties": {
    "iso:country":"FR",
    "sg:address":"Rte de Cunlhat",
    "sg:city":"Fournols",
    "sg:orig_category":"Non-Classified Establishments",
    "sg:phone":"+33 4 73 72 10 27",
    "sg:postcode":"63980",
    "sg:province":"Auvergne",
    "wof:name":"Fromagerie Du Livradois S.a.",
    "wof:placetype":"venue"
},
  "geometry": {"coordinates":[3.5867,45.518494],"type":"Point"}
}