{
  "type": "Feature",
  "properties": {
    "iso:country":"FR",
    "sg:address":"19 avenue Michelet 93400 ST OUEN",
    "sg:classifiers":[
        {
            "category":"Community Center",
            "subcategory":"Youth",
            "type":"Public Place"
        }
    ],
    "sg:phone":"+33 1 49 45 48 00",
    "sg:province":"Ile de France",
    "sg:tags":[
        "specialities",
        "spirit",
        "foreign"
    ],
    "wof:name":"Bacardi Martini France Sa",
    "wof:placetype":"venue"
},
  "geometry": {"coordinates":[2.34433,48.912296],"type":"Point"}
}