{
  "type": "Feature",
  "properties": {
    "addr:full":"Rte de Cholet - ZA la Lande Toutlemonde Pays de Loire 49360",
    "addr:postcode":"49360",
    "addr:street":"Rte De Cholet Za La;Toutlemonde",
    "iso:country":"FR",
    "sg:address":"Rte de Cholet - ZA la Lande",
    "sg:city":"Toutlemonde",
    "sg:orig_category":"Non-Classified Establishments",
    "sg:phone":"+33 2 41 55 02 08",
    "sg:postcode":"49360",
    "sg:province":"Pays de Loire",
    "wof:name":"Grolleau P\u00e8re Et Fils S.a.r.l.",
    "wof:placetype":"venue"
},
  "geometry": {"coordinates":[-0.641124,46.999599],"type":"Point"}
}