{
  "type": "Feature",
  "properties": {
    "addr:full":"79B, Av. du G\u00e9n\u00e9ral Leclerc, 93500 Pantin Ile de France 93500",
    "addr:postcode":"93500;ile;93500",
    "addr:street":"Av. Du Ge\u0301Ne\u0301Ral Leclerc;France",
    "iso:country":"FR",
    "sg:address":"79B, Av. du G\u00e9n\u00e9ral Leclerc, 93500 Pantin",
    "sg:orig_category":"Non-Classified Establishments",
    "sg:phone":"+33 1 41 71 30 22",
    "sg:postcode":"93500",
    "sg:province":"Ile de France",
    "wof:name":"Carmine S.a.r.l.",
    "wof:placetype":"venue"
},
  "geometry": {"coordinates":[2.401324,48.896446],"type":"Point"}
}