{
  "type": "Feature",
  "properties": {
    "addr:full":"28, Rue Sainte Ad\u00e9la\u00efde, 78000 Versailles Ile de France 78000",
    "addr:housenumber":"28",
    "addr:postcode":"78000;78000",
    "addr:street":"Rue Sainte Ade\u0301Lai\u0308De",
    "iso:country":"FR",
    "sg:address":"28, Rue Sainte Ad\u00e9la\u00efde, 78000 Versailles",
    "sg:orig_category":"Non-Classified Establishments",
    "sg:phone":"+33 1 30 21 89 17",
    "sg:postcode":"78000",
    "sg:province":"Ile de France",
    "wof:name":"Coryent Conseil",
    "wof:placetype":"venue"
},
  "geometry": {"coordinates":[2.130776,48.812271],"type":"Point"}
}