{
  "type": "Feature",
  "properties": {
    "addr:full":"B.P. 45596, 34071 Montpellier C\u00e9dex 3^^639, Av. du March\u00e9 Gare - ZI, 34000 Montpellier Languedoc-Roussillon",
    "addr:housenumber":"3 ^ ^ 639",
    "addr:postcode":"34071;34000",
    "addr:street":"Ce\u0301Dex;Av. Du Marche\u0301 Gare Zi",
    "iso:country":"FR",
    "sg:address":"B.P. 45596, 34071 Montpellier C\u00e9dex 3^^639, Av. du March\u00e9 Gare - ZI, 34000 Montpellier",
    "sg:orig_category":"Non-Classified Establishments",
    "sg:phone":"+33 4 67 92 09 11",
    "sg:province":"Languedoc-Roussillon",
    "wof:name":"Richardson Fr\u00e8res S.a.",
    "wof:placetype":"venue"
},
  "geometry": {"coordinates":[3.87609,43.610855],"type":"Point"}
}