{
  "type": "Feature",
  "properties": {
    "iso:country":"FR",
    "sg:address":"B.P. 67, 63016 Clermont Ferrand^^ZI du Br\u00e9zet, 63000 Clermont Ferrand",
    "sg:city":"Clermont-Ferrand",
    "sg:orig_category":"Non-Classified Establishments",
    "sg:phone":"+33 4 73 14 31 35",
    "sg:postcode":"63000",
    "sg:province":"Auvergne",
    "wof:name":"Transauto Stur S.a.",
    "wof:placetype":"venue"
},
  "geometry": {"coordinates":[3.08183,45.777618],"type":"Point"}
}