{
  "type": "Feature",
  "properties": {
    "addr:full":"Rue Edouard Branly 78190 Trappes Ile de France 78190",
    "addr:postcode":"78190;ile;78190",
    "addr:street":"Rue Edouard Branly;France",
    "iso:country":"FR",
    "sg:address":"Rue Edouard Branly 78190 Trappes",
    "sg:classifiers":[
        {
            "category":"Health Services",
            "subcategory":"Medical Lab",
            "type":"Services"
        }
    ],
    "sg:phone":"+33 1 30 68 42 42",
    "sg:postcode":"78190",
    "sg:province":"Ile de France",
    "sg:tags":[
        "chemical",
        "pharmaceutical",
        "pharmacy"
    ],
    "wof:name":"Boiron Sa",
    "wof:placetype":"venue"
},
  "geometry": {"coordinates":[1.982724,48.793587],"type":"Point"}
}