{
  "type": "Feature",
  "properties": {
    "iso:country":"FR",
    "sg:address":"75, Rue de la R\u00e9publique, 76140 Le Petit Quevilly",
    "sg:orig_category":"Unclassifiable Establishments",
    "sg:phone":"+33 2 35 72 52 22",
    "sg:province":"Haute Normandie",
    "wof:name":"Br\u00e9ard Communication S.a.",
    "wof:placetype":"venue"
},
  "geometry": {"coordinates":[1.047051,49.423649],"type":"Point"}
}