{
  "type": "Feature",
  "properties": {
    "iso:country":"FR",
    "sg:address":"13 Rue Des Pres 68920 Wettolsheim",
    "sg:city":"Wettolsheim",
    "sg:classifiers":[
        {
            "category":"Home & Garden",
            "subcategory":"Furniture",
            "type":"Retail Goods"
        }
    ],
    "sg:phone":"+33 3 89 80 32 64",
    "sg:postcode":"68920",
    "sg:province":"Alsace",
    "sg:tags":[
        "wood"
    ],
    "wof:name":"Etablissements Soell",
    "wof:placetype":"venue"
},
  "geometry": {"coordinates":[7.302416,48.055134],"type":"Point"}
}