{
  "type": "Feature",
  "properties": {
    "addr:full":"43 blvd Gambetta; Poissy; 78300 Ile de France 78300",
    "addr:postcode":"78300 ile;france 78300",
    "addr:street":"43 Blvd Gambetta",
    "iso:country":"FR",
    "sg:address":"43 blvd Gambetta; Poissy; 78300",
    "sg:classifiers":[
        {
            "category":"Banks & Credit Unions",
            "subcategory":"Bank",
            "type":"Services"
        }
    ],
    "sg:phone":"+33 30742440",
    "sg:postcode":"78300",
    "sg:province":"Ile de France",
    "wof:name":"Banque Nationale De Paris",
    "wof:placetype":"venue"
},
  "geometry": {"coordinates":[2.047005,48.930431],"type":"Point"}
}