{
  "type": "Feature",
  "properties": {
    "iso:country":"FR",
    "sg:address":"10, Les Priviers, 37130 Ligni\u00e8res de Touraine",
    "sg:city":"Br\u00e9h\u00e9mont",
    "sg:orig_category":"Unclassifiable Establishments",
    "sg:phone":"+33 2 47 96 85 37",
    "sg:postcode":"37130",
    "sg:province":"Centre",
    "wof:name":"T. Besard",
    "wof:placetype":"venue"
},
  "geometry": {"coordinates":[0.394412,47.28867],"type":"Point"}
}