{
  "type": "Feature",
  "properties": {
    "iso:country":"FR",
    "sg:address":"9 Rue De La Monnaie 37000 Tours",
    "sg:city":"Tours",
    "sg:classifiers":[
        {
            "category":"Professional",
            "subcategory":"Printing & Photocopies",
            "type":"Services"
        }
    ],
    "sg:phone":"+33 2 47 70 60 00",
    "sg:postcode":"37000",
    "sg:province":"Centre",
    "sg:tags":[
        "publishing"
    ],
    "wof:name":"Mcm Presse (mcm)",
    "wof:placetype":"venue"
},
  "geometry": {"coordinates":[0.683431,47.394505],"type":"Point"}
}