{
  "type": "Feature",
  "properties": {
    "iso:country":"FR",
    "sg:address":"Parc Innovation Bretagne Sud",
    "sg:city":"Vannes C\u00e9dex",
    "sg:orig_category":"Non-Classified Establishments",
    "sg:phone":"+33 2 97 47 06 00",
    "sg:postcode":"56038",
    "sg:province":"Franche Comt\u00e9",
    "wof:name":"Archimex S.a.",
    "wof:placetype":"venue"
},
  "geometry": {"coordinates":[-2.75967,47.65736],"type":"Point"}
}