{
  "type": "Feature",
  "properties": {
    "iso:country":"FR",
    "sg:address":"6 Bis Rue Amp\u00e8re 51000 Chalons En Champagne",
    "sg:classifiers":[
        {
            "category":"Building & Trades",
            "subcategory":"Construction",
            "type":"Services"
        }
    ],
    "sg:phone":"+33 3 26 64 00 22",
    "sg:postcode":"51000",
    "sg:province":"Champagne",
    "sg:tags":[
        "work",
        "public"
    ],
    "wof:name":"Nord Est Tp",
    "wof:placetype":"venue"
},
  "geometry": {"coordinates":[4.353151,48.972698],"type":"Point"}
}