{
  "type": "Feature",
  "properties": {
    "addr:full":"10, rue Fructidor - Immeuble le Colis\u00e9e 2, 75017 Paris Ile de France",
    "addr:housenumber":"10;immeuble;2",
    "addr:postcode":"75017",
    "addr:street":"Rue Fructidor",
    "iso:country":"FR",
    "sg:address":"10, rue Fructidor - Immeuble le Colis\u00e9e 2, 75017 Paris",
    "sg:orig_category":"Non-Classified Establishments",
    "sg:phone":"+33 1 41 66 21 21",
    "sg:province":"Ile de France",
    "wof:name":"Sage Saari",
    "wof:placetype":"venue"
},
  "geometry": {"coordinates":[2.32719,48.900814],"type":"Point"}
}