{
  "type": "Feature",
  "properties": {
    "addr:full":"22, Rue Gambetta, 51150 Bouzy Champagne",
    "addr:housenumber":"22",
    "addr:postcode":"51150",
    "addr:street":"Rue Gambetta",
    "iso:country":"FR",
    "sg:address":"22, Rue Gambetta, 51150 Bouzy",
    "sg:orig_category":"Unclassifiable Establishments",
    "sg:phone":"+33 3 26 59 50 50",
    "sg:province":"Champagne",
    "wof:name":"Bmt Vignobles S.a.",
    "wof:placetype":"venue"
},
  "geometry": {"coordinates":[4.146201,49.078411],"type":"Point"}
}