{
  "type": "Feature",
  "properties": {
    "addr:full":"36 Bis Av Des Pr\u00e9s Le Roi 18230 St Doulchard Saint-Doulchard Centre 18230",
    "addr:housenumber":"36 bis;saint-doulchard",
    "addr:postcode":"18230 st doulchard;18230",
    "addr:street":"Av Des Pre\u0301S",
    "iso:country":"FR",
    "sg:address":"36 Bis Av Des Pr\u00e9s Le Roi 18230 St Doulchard",
    "sg:city":"Saint-Doulchard",
    "sg:classifiers":[
        {
            "category":"Professional",
            "type":"Services"
        }
    ],
    "sg:phone":"+33 2 48 24 09 79",
    "sg:postcode":"18230",
    "sg:province":"Centre",
    "sg:tags":[
        "transport",
        "road"
    ],
    "wof:name":"Transports Houdray Sa",
    "wof:placetype":"venue"
},
  "geometry": {"coordinates":[2.387188,47.093548],"type":"Point"}
}