{
  "type": "Feature",
  "properties": {
    "addr:full":"45/47, Bd de Pr\u00e9 Pommier - ZI Champfleuri, 38300 Bourgoin Jallieu Rhone-Alpes",
    "addr:housenumber":"45 / 47",
    "addr:postcode":"38300",
    "addr:street":"Bd De Pre\u0301 Pommier Zi Champfleuri",
    "iso:country":"FR",
    "sg:address":"45/47, Bd de Pr\u00e9 Pommier - ZI Champfleuri, 38300 Bourgoin Jallieu",
    "sg:orig_category":"Unclassifiable Establishments",
    "sg:phone":"+33 4 74 43 59 30",
    "sg:province":"Rhone-Alpes",
    "wof:name":"Plast Moul S.a.",
    "wof:placetype":"venue"
},
  "geometry": {"coordinates":[5.30075,45.4981],"type":"Point"}
}