{
  "type": "Feature",
  "properties": {
    "addr:full":"Rue de Longu\u00e9 - ZI Les Rosiers sur Loire Pays de Loire 49350",
    "addr:postcode":"49350",
    "addr:street":"Rue De Longue\u0301 Zi Les Rosiers;Loire",
    "iso:country":"FR",
    "sg:address":"Rue de Longu\u00e9 - ZI",
    "sg:city":"Les Rosiers sur Loire",
    "sg:orig_category":"Non-Classified Establishments",
    "sg:phone":"+33 2 41 51 86 66",
    "sg:postcode":"49350",
    "sg:province":"Pays de Loire",
    "wof:name":"Ouest Embal S.a.r.l.",
    "wof:placetype":"venue"
},
  "geometry": {"coordinates":[-0.255384,47.287113],"type":"Point"}
}