{
  "type": "Feature",
  "properties": {
    "iso:country":"FR",
    "sg:address":"127, Rte de Vertou, 44200 Nantes",
    "sg:orig_category":"Unclassifiable Establishments",
    "sg:phone":"+33 2 40 03 33 53",
    "sg:province":"Pays de Loire",
    "wof:name":"Plasprent",
    "wof:placetype":"venue"
},
  "geometry": {"coordinates":[-1.528125,47.186855],"type":"Point"}
}