{
  "type": "Feature",
  "properties": {
    "addr:full":"6, Rue de Boston, 38000 Grenoble Rhone-Alpes 38000",
    "addr:housenumber":"6",
    "addr:postcode":"38000;38000",
    "addr:street":"Rue De Boston",
    "iso:country":"FR",
    "sg:address":"6, Rue de Boston, 38000 Grenoble",
    "sg:orig_category":"Non-Classified Establishments",
    "sg:phone":"+33 4 76 49 00 80",
    "sg:postcode":"38000",
    "sg:province":"Rhone-Alpes",
    "wof:name":"Passeport Formation S.a.",
    "wof:placetype":"venue"
},
  "geometry": {"coordinates":[5.713201,45.184246],"type":"Point"}
}