{
  "type": "Feature",
  "properties": {
    "addr:full":"B.P. 30163, 60401 Noyon C\u00e9dex^^16, Rue de la Poterne, 60400 Noyon Picardie",
    "addr:postcode":"60401;60400",
    "addr:street":"Rue De La Poterne",
    "iso:country":"FR",
    "sg:address":"B.P. 30163, 60401 Noyon C\u00e9dex^^16, Rue de la Poterne, 60400 Noyon",
    "sg:orig_category":"Non-Classified Establishments",
    "sg:phone":"+33 3 44 93 35 00",
    "sg:province":"Picardie",
    "wof:name":"Rigida S.a.",
    "wof:placetype":"venue"
},
  "geometry": {"coordinates":[3.097817,49.48531],"type":"Point"}
}