{
  "type": "Feature",
  "properties": {
    "addr:full":"186, Rue du Rh\u00f4ne - Parc d'Activit\u00e9s les Jourdies, 74800 Saint Pierre en Faucigny Rhone-Alpes",
    "addr:housenumber":"186",
    "addr:postcode":"74800",
    "addr:street":"Rue Du Rho\u0302Ne Parc D'Activite \u0301S Les Jourdies",
    "iso:country":"FR",
    "sg:address":"186, Rue du Rh\u00f4ne - Parc d'Activit\u00e9s les Jourdies, 74800 Saint Pierre en Faucigny",
    "sg:orig_category":"Unclassifiable Establishments",
    "sg:phone":"+33 4 50 03 87 00",
    "sg:province":"Rhone-Alpes",
    "wof:name":"Geroudet",
    "wof:placetype":"venue"
},
  "geometry": {"coordinates":[6.379533,46.07299],"type":"Point"}
}