{
  "type": "Feature",
  "properties": {
    "iso:country":"FR",
    "sg:address":"K\u00e9risole 29300 Quimperl\u00e9",
    "sg:city":"Quimperl\u00e9",
    "sg:classifiers":[
        {
            "category":"Manufacturing",
            "subcategory":"Paper Products",
            "type":"Manufacturing & Wholesale Goods"
        }
    ],
    "sg:phone":"+33 2 98 06 20 00",
    "sg:postcode":"29300",
    "sg:province":"Bretagne",
    "sg:tags":[
        "raw",
        "material",
        "-",
        "cardboard"
    ],
    "wof:name":"Papeteries De Mauduit (sa)",
    "wof:placetype":"venue"
},
  "geometry": {"coordinates":[-3.461656,47.859921],"type":"Point"}
}