{
  "type": "Feature",
  "properties": {
    "iso:country":"FR",
    "sg:address":"B.P. 42",
    "sg:city":"Gennevilliers C\u00e9dex",
    "sg:orig_category":"Non-Classified Establishments",
    "sg:phone":"+33 1 47 33 20 50",
    "sg:postcode":"92234",
    "sg:province":"Ile de France",
    "wof:name":"Airofiltre S.a.",
    "wof:placetype":"venue"
},
  "geometry": {"coordinates":[2.29447,48.925026],"type":"Point"}
}