{
  "type": "Feature",
  "properties": {
    "addr:full":"B.P. 71, 78340 Les Clayes sous Bois C\u00e9dex^^CD 161 - ZI le Ch\u00eane Sorcier, 78340 Les Clayes sous Bois Ile de France",
    "addr:housenumber":"161",
    "addr:postcode":"78340;78340",
    "addr:street":"B.P. 71;Zi Le;Sorcier",
    "iso:country":"FR",
    "sg:address":"B.P. 71, 78340 Les Clayes sous Bois C\u00e9dex^^CD 161 - ZI le Ch\u00eane Sorcier, 78340 Les Clayes sous Bois",
    "sg:orig_category":"Non-Classified Establishments",
    "sg:phone":"+33 1 30 79 69 99",
    "sg:province":"Ile de France",
    "wof:name":"Laboratoires Vitarmonyl S.a.r.l.",
    "wof:placetype":"venue"
},
  "geometry": {"coordinates":[1.970759,48.825859],"type":"Point"}
}