{
  "type": "Feature",
  "properties": {
    "iso:country":"FR",
    "sg:address":"Long\u00e8ve 86130 Dissay",
    "sg:orig_category":"Unclassifiable Establishments",
    "sg:phone":"+33 5 49 62 60 00",
    "sg:province":"Poitou-Charentes",
    "wof:name":"Eurial Poitouraine S.a.s.",
    "wof:placetype":"venue"
},
  "geometry": {"coordinates":[0.422095,46.720711],"type":"Point"}
}