{
  "type": "Feature",
  "properties": {
    "iso:country":"FR",
    "sg:address":"14 blvd du G\u00e9n\u00e9ral de Gaulle; Cusset; 3300",
    "sg:classifiers":[
        {
            "category":"Banks & Credit Unions",
            "subcategory":"Bank",
            "type":"Services"
        }
    ],
    "sg:phone":"+33 3370310448",
    "sg:province":"Auvergne",
    "wof:name":"Banque Populaire, Du Massif Central",
    "wof:placetype":"venue"
},
  "geometry": {"coordinates":[3.47831,46.14436],"type":"Point"}
}