{
  "type": "Feature",
  "properties": {
    "addr:full":"200 R De L'Arbre De La Garde 12160 Baraqueville Midi Pyr\u00e9n\u00e9es 12160",
    "addr:housenumber":"200",
    "addr:postcode":"12160;12160",
    "addr:street":"R De L'Arbre De La Garde",
    "iso:country":"FR",
    "sg:address":"200 R De L'Arbre De La Garde 12160 Baraqueville",
    "sg:classifiers":[
        {
            "category":"Farming",
            "subcategory":"Livestock Farm",
            "type":"Manufacturing & Wholesale Goods"
        }
    ],
    "sg:phone":"+33 5 65 70 15 80",
    "sg:postcode":"12160",
    "sg:province":"Midi Pyr\u00e9n\u00e9es",
    "sg:tags":[
        "breeding",
        "agriculture",
        "animal"
    ],
    "wof:name":"Lenfant Jean-jacques Sarl",
    "wof:placetype":"venue"
},
  "geometry": {"coordinates":[2.429766,44.276924],"type":"Point"}
}