{
  "type": "Feature",
  "properties": {
    "addr:full":"69 Rue Du Jardin Public 33000 Bordeaux Bordeaux Aquitaine 33000",
    "addr:housenumber":"69",
    "addr:postcode":"33000;33000",
    "addr:street":"Rue Du Jardin Public",
    "iso:country":"FR",
    "sg:address":"69 Rue Du Jardin Public 33000 Bordeaux",
    "sg:city":"Bordeaux",
    "sg:classifiers":[
        {
            "category":"Wholesale",
            "subcategory":"Machinery & Supplies",
            "type":"Manufacturing & Wholesale Goods"
        }
    ],
    "sg:phone":"+33 5 56 00 61 10",
    "sg:postcode":"33000",
    "sg:province":"Aquitaine",
    "sg:tags":[
        "equipment",
        "optical",
        "precision",
        "instrument"
    ],
    "wof:name":"Aquitaine Repro Sarl",
    "wof:placetype":"venue"
},
  "geometry": {"coordinates":[-0.575355,44.853012],"type":"Point"}
}