{
  "type": "Feature",
  "properties": {
    "addr:full":"Les Gravasses 12200 Villefranche De Rouergue Midi Pyr\u00e9n\u00e9es 12200",
    "addr:postcode":"12200;12200",
    "iso:country":"FR",
    "sg:address":"Les Gravasses 12200 Villefranche De Rouergue",
    "sg:classifiers":[
        {
            "category":"Food & Beverages",
            "subcategory":"Dairy",
            "type":"Retail Goods"
        }
    ],
    "sg:phone":"+33 5 65 65 13 70",
    "sg:postcode":"12200",
    "sg:province":"Midi Pyr\u00e9n\u00e9es",
    "sg:tags":[
        "product",
        "related"
    ],
    "wof:name":"La Compagnie Des Fromages Fromagerie Soulie",
    "wof:placetype":"venue"
},
  "geometry": {"coordinates":[2.02078,44.336014],"type":"Point"}
}