{
  "type": "Feature",
  "properties": {
    "iso:country":"FR",
    "sg:address":"1, Rue des Vergers, 69760 Limonest",
    "sg:orig_category":"Non-Classified Establishments",
    "sg:phone":"+33 4 78 66 64 64",
    "sg:postcode":"69760",
    "sg:province":"Rhone-Alpes",
    "wof:name":"Power S\u00e9curit\u00e9 Priv\u00e9 S.a.",
    "wof:placetype":"venue"
},
  "geometry": {"coordinates":[4.77387,45.807426],"type":"Point"}
}