{
  "type": "Feature",
  "properties": {
    "addr:full":"Chemin de P\u00e9rad\u00e8re Castelnau d'Estr\u00e9tefonds Midi Pyr\u00e9n\u00e9es 31620",
    "addr:postcode":"31620",
    "addr:street":"Chemin De Pe\u0301Rade\u0300Re Castelnau",
    "iso:country":"FR",
    "sg:address":"Chemin de P\u00e9rad\u00e8re",
    "sg:city":"Castelnau d'Estr\u00e9tefonds",
    "sg:orig_category":"Non-Classified Establishments",
    "sg:phone":"+33 5 61 35 15 64",
    "sg:postcode":"31620",
    "sg:province":"Midi Pyr\u00e9n\u00e9es",
    "wof:name":"C.t.i. S.a. - Centre Toulousain De Mat\u00e9riel",
    "wof:placetype":"venue"
},
  "geometry": {"coordinates":[1.356939,43.776867],"type":"Point"}
}