{
  "type": "Feature",
  "properties": {
    "iso:country":"FR",
    "sg:address":"Rue Vincent Van Gogh 76290 Montivilliers",
    "sg:classifiers":[
        {
            "category":"Banks & Credit Unions",
            "subcategory":"Investment Brokerage",
            "type":"Services"
        }
    ],
    "sg:phone":"+33 2 32 79 63 63",
    "sg:province":"Haute Normandie",
    "sg:tags":[
        "-",
        "transport",
        "related"
    ],
    "wof:name":"Challenge International Services Sa",
    "wof:placetype":"venue"
},
  "geometry": {"coordinates":[0.164917,49.554478],"type":"Point"}
}