{
  "type": "Feature",
  "properties": {
    "addr:full":"541, Rue d'Anhiers, 59500 Douai Nord Pas-de-Calais",
    "addr:housenumber":"541",
    "addr:postcode":"59500",
    "addr:street":"Rue D'Anhiers",
    "iso:country":"FR",
    "sg:address":"541, Rue d'Anhiers, 59500 Douai",
    "sg:orig_category":"Unclassifiable Establishments",
    "sg:phone":"+33 3 27 88 54 00",
    "sg:province":"Nord Pas-de-Calais",
    "wof:name":"Constru S.a.",
    "wof:placetype":"venue"
},
  "geometry": {"coordinates":[3.128845,50.398602],"type":"Point"}
}