{
  "type": "Feature",
  "properties": {
    "addr:full":"245, Rue du Nizerand, 69400 Villefranche sur Sa\u00f4ne Rhone-Alpes",
    "addr:housenumber":"245",
    "addr:postcode":"69400",
    "addr:street":"Rue Du Nizerand",
    "iso:country":"FR",
    "sg:address":"245, Rue du Nizerand, 69400 Villefranche sur Sa\u00f4ne",
    "sg:orig_category":"Unclassifiable Establishments",
    "sg:phone":"+33 4 74 65 71 90",
    "sg:province":"Rhone-Alpes",
    "wof:name":"Lafont Logistique S.a.",
    "wof:placetype":"venue"
},
  "geometry": {"coordinates":[4.70928,45.999519],"type":"Point"}
}