{
  "type": "Feature",
  "properties": {
    "iso:country":"FR",
    "sg:address":"125, Av Edouard Herriot, 39300 Champagnole",
    "sg:orig_category":"Unclassifiable Establishments",
    "sg:phone":"+33 3 84 53 11 54",
    "sg:province":"Franche Comt\u00e9",
    "wof:name":"39 Express S.n.c.",
    "wof:placetype":"venue"
},
  "geometry": {"coordinates":[5.892762,46.751205],"type":"Point"}
}