{
  "type": "Feature",
  "properties": {
    "addr:full":"B.P. 38, 20611 Bastia C\u00e9dex^^RN 193 - L'Arinella , 20600 Bastia Corse",
    "addr:housenumber":"193",
    "addr:postcode":"20611;20600",
    "addr:street":"B.P. 38;Ce\u0301Dex^^Rn",
    "iso:country":"FR",
    "sg:address":"B.P. 38, 20611 Bastia C\u00e9dex^^RN 193 - L'Arinella , 20600 Bastia",
    "sg:orig_category":"Non-Classified Establishments",
    "sg:phone":"+33 4 95 33 36 06",
    "sg:province":"Corse",
    "wof:name":"Tamburini S.a.r.l.",
    "wof:placetype":"venue"
},
  "geometry": {"coordinates":[9.42128,42.666969],"type":"Point"}
}