{
  "type": "Feature",
  "properties": {
    "addr:full":"10 Rue Des Freres Montgolfier 21300 Chenove Chen\u00f4ve Bourgogne 21300",
    "addr:housenumber":"10",
    "addr:postcode":"21300;21300",
    "addr:street":"Rue Des Freres Montgolfier",
    "iso:country":"FR",
    "sg:address":"10 Rue Des Freres Montgolfier 21300 Chenove",
    "sg:city":"Chen\u00f4ve",
    "sg:classifiers":[
        {
            "category":"Bakery",
            "type":"Food & Drink"
        }
    ],
    "sg:phone":"+33 3 80 52 82 18",
    "sg:postcode":"21300",
    "sg:province":"Bourgogne",
    "sg:tags":[
        "cake",
        "product",
        "related",
        "bread"
    ],
    "wof:name":"Panidor Atelier De Patisserie",
    "wof:placetype":"venue"
},
  "geometry": {"coordinates":[5.020925,47.294155],"type":"Point"}
}