{
  "type": "Feature",
  "properties": {
    "addr:full":"37 rue G\u00e9n\u00e9ral de Gaulle; Capbreton Capbreton Aquitaine 40130",
    "addr:housenumber":"37",
    "addr:postcode":"40130",
    "addr:street":"Rue Ge\u0301Ne\u0301Ral De Gaulle",
    "iso:country":"FR",
    "sg:address":"37 rue G\u00e9n\u00e9ral de Gaulle; Capbreton",
    "sg:city":"Capbreton",
    "sg:classifiers":[
        {
            "category":"Banks & Credit Unions",
            "subcategory":"Bank",
            "type":"Services"
        }
    ],
    "sg:phone":"+33 3358721348",
    "sg:postcode":"40130",
    "sg:province":"Aquitaine",
    "wof:name":"Soci\u00e9t\u00e9 G\u00e9n\u00e9rale",
    "wof:placetype":"venue"
},
  "geometry": {"coordinates":[-1.432296,43.642029],"type":"Point"}
}