{
  "type": "Feature",
  "properties": {
    "iso:country":"FR",
    "sg:address":"B.P. 28, 56204 La Gacilly C\u00e9dex^^ZI de la Croix des Archers, 56200 La Gacilly",
    "sg:city":"La Gacilly",
    "sg:orig_category":"Non-Classified Establishments",
    "sg:phone":"+33 2 99 08 22 18",
    "sg:postcode":"56200",
    "sg:province":"Bretagne",
    "wof:name":"Transports Morand S.a.r.l.",
    "wof:placetype":"venue"
},
  "geometry": {"coordinates":[-2.132382,47.727661],"type":"Point"}
}