{
  "type": "Feature",
  "properties": {
    "addr:full":"133/135, Rue Bataille, 69008 Lyon Rhone-Alpes 69008",
    "addr:housenumber":"133 / 135",
    "addr:postcode":"69008;69008",
    "addr:street":"Rue Bataille",
    "iso:country":"FR",
    "sg:address":"133/135, Rue Bataille, 69008 Lyon",
    "sg:orig_category":"Unclassifiable Establishments",
    "sg:phone":"+33 4 72 78 80 48",
    "sg:postcode":"69008",
    "sg:province":"Rhone-Alpes",
    "wof:name":"S.k.f. France S.a.",
    "wof:placetype":"venue"
},
  "geometry": {"coordinates":[4.872945,45.735241],"type":"Point"}
}