{
  "type": "Feature",
  "properties": {
    "iso:country":"FR",
    "sg:address":"B.P. 7, 38160 Saint Romans^^RN 532 - ZI Beauvoir en Royans, 38160 Saint Romans",
    "sg:orig_category":"Non-Classified Establishments",
    "sg:phone":"+33 4 76 38 08 44",
    "sg:province":"Rhone-Alpes",
    "wof:name":"Sti Plastics S.a.",
    "wof:placetype":"venue"
},
  "geometry": {"coordinates":[5.336171,45.131378],"type":"Point"}
}