{
  "type": "Feature",
  "properties": {
    "iso:country":"FR",
    "sg:address":"ZI",
    "sg:city":"Chambon sur Voueize",
    "sg:orig_category":"Unclassifiable Establishments",
    "sg:phone":"+33 5 55 82 11 06",
    "sg:postcode":"23170",
    "sg:province":"Limousin",
    "wof:name":"Carrosserie Dhume S.a.",
    "wof:placetype":"venue"
},
  "geometry": {"coordinates":[2.346211,46.139374],"type":"Point"}
}