{
  "type": "Feature",
  "properties": {
    "addr:full":"18 Bd D'Alsace Lorraine 51350 Cormontreuil Champagne 51350",
    "addr:housenumber":"18",
    "addr:postcode":"51350;51350",
    "addr:street":"Bd D'Alsace Lorraine;Champagne",
    "iso:country":"FR",
    "sg:address":"18 Bd D'Alsace Lorraine 51350 Cormontreuil",
    "sg:classifiers":[
        {
            "category":"Government",
            "subcategory":"Department Of Motor Vehicles",
            "type":"Public Place"
        }
    ],
    "sg:phone":"+33 3 26 08 63 68",
    "sg:postcode":"51350",
    "sg:province":"Champagne",
    "sg:tags":[
        "equipment",
        "industrial",
        "transport",
        "motor-cars"
    ],
    "wof:name":"Sa Pwa",
    "wof:placetype":"venue"
},
  "geometry": {"coordinates":[4.05217,49.216499],"type":"Point"}
}