{
  "type": "Feature",
  "properties": {
    "iso:country":"FR",
    "sg:address":"B.P. 21, 54560 Beuvillers^^Rte d'Audun le Roman, 54560 Beuvillers",
    "sg:orig_category":"Non-Classified Establishments",
    "sg:phone":"+33 3 82 21 60 36",
    "sg:province":"Lorraine",
    "wof:name":"Lef\u00e8vre R. Et G. S.a.",
    "wof:placetype":"venue"
},
  "geometry": {"coordinates":[5.88836,49.366329],"type":"Point"}
}