{
  "type": "Feature",
  "properties": {
    "addr:full":"B.P. 90159, 86961 Chasseneuil Poitou C\u00e9dex^^Rue Thomas Edison, 86360 Chasseneuil du Poitou Poitou-Charentes",
    "addr:housenumber":"86961",
    "addr:postcode":"86360",
    "addr:street":"Thomas Edison",
    "iso:country":"FR",
    "sg:address":"B.P. 90159, 86961 Chasseneuil Poitou C\u00e9dex^^Rue Thomas Edison, 86360 Chasseneuil du Poitou",
    "sg:orig_category":"Non-Classified Establishments",
    "sg:phone":"+33 5 49 49 44 44",
    "sg:province":"Poitou-Charentes",
    "wof:name":"Union Poitou Anjou S.a.",
    "wof:placetype":"venue"
},
  "geometry": {"coordinates":[0.37477,46.650494],"type":"Point"}
}