{
  "type": "Feature",
  "properties": {
    "addr:full":"Bd Winston Churchill, 37041 Tours C\u00e9dex^^Bd Winston Churchill, 37000 Tours Tours Centre 37000",
    "addr:postcode":"37041;37000;37000",
    "addr:street":"Bd Winston Churchill;Winston Churchill",
    "iso:country":"FR",
    "sg:address":"Bd Winston Churchill, 37041 Tours C\u00e9dex^^Bd Winston Churchill, 37000 Tours",
    "sg:city":"Tours",
    "sg:orig_category":"Non-Classified Establishments",
    "sg:phone":"+33 2 47 39 81 00",
    "sg:postcode":"37000",
    "sg:province":"Centre",
    "wof:name":"C.r.c.a.m",
    "wof:placetype":"venue"
},
  "geometry": {"coordinates":[0.689715,47.390385],"type":"Point"}
}