{
  "type": "Feature",
  "properties": {
    "iso:country":"FR",
    "sg:address":"1 rue de la Marie; Lampaul Plouarzel; 29810",
    "sg:city":"Plouarzel",
    "sg:classifiers":[
        {
            "category":"Banks & Credit Unions",
            "subcategory":"Bank",
            "type":"Services"
        }
    ],
    "sg:phone":"+33 2 98 84 04 83",
    "sg:postcode":"29810",
    "sg:province":"Bretagne",
    "wof:name":"Caisse Regionale De Cr\u00e9dit, Maritime Mutuel Du Finist\u00e8re",
    "wof:placetype":"venue"
},
  "geometry": {"coordinates":[-4.76055,48.44775],"type":"Point"}
}