{
  "type": "Feature",
  "properties": {
    "iso:country":"FR",
    "sg:address":"Les Ouvas 74210 Doussard",
    "sg:orig_category":"Unclassifiable Establishments",
    "sg:phone":"+33 4 50 44 31 12",
    "sg:province":"Rhone-Alpes",
    "wof:name":"A.l.m.o. S.a. - Alpes Machines Outil",
    "wof:placetype":"venue"
},
  "geometry": {"coordinates":[6.223055,45.777744],"type":"Point"}
}