{
  "type": "Feature",
  "properties": {
    "addr:full":"20 Rue Eug\u00e8ne Henaff 69200 V\u00e9nissieux Rhone-Alpes",
    "addr:housenumber":"20",
    "addr:postcode":"69200",
    "addr:street":"Rue Euge\u0300Ne Henaff",
    "iso:country":"FR",
    "sg:address":"20 Rue Eug\u00e8ne Henaff 69200 V\u00e9nissieux",
    "sg:classifiers":[
        {
            "category":"Home & Garden",
            "subcategory":"Furniture",
            "type":"Retail Goods"
        }
    ],
    "sg:phone":"+33 4 72 21 28 28",
    "sg:province":"Rhone-Alpes",
    "sg:tags":[
        "household",
        "wood"
    ],
    "wof:name":"Ceanothe Holding",
    "wof:placetype":"venue"
},
  "geometry": {"coordinates":[4.899375,45.687191],"type":"Point"}
}