{
  "type": "Feature",
  "properties": {
    "addr:full":"B.P. 416, 76805 Saint Etienne du Rouvray C\u00e9dex^^Rue du Buissonnet, 76800 Saint Etienne du Rouvray Haute Normandie",
    "addr:housenumber":"b.p. 416",
    "addr:postcode":"76805;76800",
    "addr:street":"Buissonnet;Haute Normandie",
    "iso:country":"FR",
    "sg:address":"B.P. 416, 76805 Saint Etienne du Rouvray C\u00e9dex^^Rue du Buissonnet, 76800 Saint Etienne du Rouvray",
    "sg:orig_category":"Non-Classified Establishments",
    "sg:phone":"+33 2 32 95 90 00",
    "sg:province":"Haute Normandie",
    "wof:name":"S.n.m.s. S.a.r.l. - Soci\u00e9t\u00e9 Normande Malissard Services",
    "wof:placetype":"venue"
},
  "geometry": {"coordinates":[1.112756,49.389599],"type":"Point"}
}