{
  "type": "Feature",
  "properties": {
    "addr:full":"Cite Industrielle 44680 CHEMERE Pays de Loire",
    "addr:postcode":"44680",
    "addr:street":"Cite Industrielle;Chemere",
    "iso:country":"FR",
    "sg:address":"Cite Industrielle 44680 CHEMERE",
    "sg:classifiers":[
        {
            "category":"Communications",
            "subcategory":"Television Station",
            "type":"Services"
        }
    ],
    "sg:phone":"+33 2 40 21 31 30",
    "sg:province":"Pays de Loire",
    "sg:tags":[
        "shower",
        "cabinet"
    ],
    "wof:name":"Aquaproduction Sa",
    "wof:placetype":"venue"
},
  "geometry": {"coordinates":[-1.914548,47.122234],"type":"Point"}
}