{
  "type": "Feature",
  "properties": {
    "addr:full":"40 Avenue De La Liberation 57160 Chatel St Germain Lorraine 57160",
    "addr:housenumber":"40",
    "addr:postcode":"57160;57160",
    "addr:street":"Avenue De La Liberation;Chatel St;Lorraine",
    "iso:country":"FR",
    "sg:address":"40 Avenue De La Liberation 57160 Chatel St Germain",
    "sg:classifiers":[
        {
            "category":"Professional",
            "subcategory":"Computer Services",
            "type":"Services"
        }
    ],
    "sg:phone":"+33 3 87 65 98 80",
    "sg:postcode":"57160",
    "sg:province":"Lorraine",
    "sg:tags":[
        "information",
        "technology",
        "software"
    ],
    "wof:name":"Crisalid",
    "wof:placetype":"venue"
},
  "geometry": {"coordinates":[6.100188,49.109619],"type":"Point"}
}