{
  "type": "Feature",
  "properties": {
    "iso:country":"FR",
    "sg:address":"1, Rue Pierre Josse - ZI des Bordes, 91070 Bondoufle",
    "sg:orig_category":"Unclassifiable Establishments",
    "sg:phone":"+33 1 60 86 89 70",
    "sg:province":"Ile de France",
    "wof:name":"C.d.p. France S.a.s. - Cardo Door Production",
    "wof:placetype":"venue"
},
  "geometry": {"coordinates":[2.379516,48.615681],"type":"Point"}
}