{
  "type": "Feature",
  "properties": {
    "addr:full":"35 Rue Denis Cordonnier 76620 Le Havre Rhone-Alpes",
    "addr:housenumber":"35",
    "addr:postcode":"76620",
    "addr:street":"Rue Denis Cordonnier",
    "iso:country":"FR",
    "sg:address":"35 Rue Denis Cordonnier 76620 Le Havre",
    "sg:classifiers":[
        {
            "category":"Bakery",
            "type":"Food & Drink"
        }
    ],
    "sg:phone":"+33 2 35 44 05 30",
    "sg:province":"Rhone-Alpes",
    "sg:tags":[
        "cake",
        "product",
        "related",
        "bread"
    ],
    "wof:name":"Thomelin (ets Roger)",
    "wof:placetype":"venue"
},
  "geometry": {"coordinates":[0.100645,49.522018],"type":"Point"}
}