{
  "type": "Feature",
  "properties": {
    "addr:full":"Route Nationale 60590 Trie Chateau Picardie 60590",
    "addr:postcode":"60590;60590",
    "addr:street":"Route Nationale;Chateau Picardie",
    "iso:country":"FR",
    "sg:address":"Route Nationale 60590 Trie Chateau",
    "sg:classifiers":[
        {
            "category":"Manufacturing",
            "subcategory":"Metals",
            "type":"Manufacturing & Wholesale Goods"
        }
    ],
    "sg:phone":"+33 3 44 49 74 71",
    "sg:postcode":"60590",
    "sg:province":"Picardie",
    "sg:tags":[
        "-",
        "machine",
        "equipment",
        "engineering",
        "machinery",
        "mechanical"
    ],
    "wof:name":"Metalesca",
    "wof:placetype":"venue"
},
  "geometry": {"coordinates":[1.82357,49.283527],"type":"Point"}
}