{
  "type": "Feature",
  "properties": {
    "addr:full":"Rte De Craon 53800 Renaz\u00e9 Pays de Loire 53800",
    "addr:postcode":"53800;53800",
    "addr:street":"Rte De Craon",
    "iso:country":"FR",
    "sg:address":"Rte De Craon 53800 Renaz\u00e9",
    "sg:classifiers":[
        {
            "category":"Building & Trades",
            "subcategory":"Construction",
            "type":"Services"
        }
    ],
    "sg:phone":"+33 2 43 06 40 76",
    "sg:postcode":"53800",
    "sg:province":"Pays de Loire",
    "sg:tags":[
        "work",
        "public"
    ],
    "wof:name":"Ste De Travaux Et D'amenagement Regionaux",
    "wof:placetype":"venue"
},
  "geometry": {"coordinates":[-1.053819,47.798168],"type":"Point"}
}