{
  "type": "Feature",
  "properties": {
    "addr:full":"25 Avenue De L Enclos 31120 Portet Sur Garonne Midi Pyr\u00e9n\u00e9es 31120",
    "addr:housenumber":"25",
    "addr:postcode":"31120;31120",
    "addr:street":"Avenue De L Enclos",
    "iso:country":"FR",
    "sg:address":"25 Avenue De L Enclos 31120 Portet Sur Garonne",
    "sg:classifiers":[
        {
            "category":"Shopping",
            "subcategory":"Crafts & Fabrics",
            "type":"Retail Goods"
        }
    ],
    "sg:phone":"+33 5 61 72 35 32",
    "sg:postcode":"31120",
    "sg:province":"Midi Pyr\u00e9n\u00e9es",
    "sg:tags":[
        "textile",
        "clothing"
    ],
    "wof:name":"Tissus Plus",
    "wof:placetype":"venue"
},
  "geometry": {"coordinates":[1.397865,43.535461],"type":"Point"}
}