{
  "type": "Feature",
  "properties": {
    "addr:full":"Rue Louis Bl\u00e9riot Cholet Pays de Loire 49300",
    "addr:postcode":"49300",
    "addr:street":"Rue Louis Ble\u0301Riot",
    "iso:country":"FR",
    "sg:address":"Rue Louis Bl\u00e9riot",
    "sg:city":"Cholet",
    "sg:orig_category":"Unclassifiable Establishments",
    "sg:phone":"+33 2 41 58 67 44",
    "sg:postcode":"49300",
    "sg:province":"Pays de Loire",
    "wof:name":"Locamion",
    "wof:placetype":"venue"
},
  "geometry": {"coordinates":[-0.872568,47.070499],"type":"Point"}
}