{
  "type": "Feature",
  "properties": {
    "iso:country":"FR",
    "sg:address":"8 Quai Duguay Trouin 35000 Rennes",
    "sg:city":"Rennes",
    "sg:classifiers":[
        {
            "category":"Sports & Exercise",
            "subcategory":"Sports Center",
            "type":"Entertainment"
        }
    ],
    "sg:phone":"+33 2 99 31 53 22",
    "sg:postcode":"35000",
    "sg:province":"Bretagne",
    "sg:tags":[
        "game"
    ],
    "wof:name":"Cinema Gaumont Programmes Et Horaires",
    "wof:placetype":"venue"
},
  "geometry": {"coordinates":[-1.680803,48.110298],"type":"Point"}
}