{
  "type": "Feature",
  "properties": {
    "addr:full":"5 bis, Rue Bel Air - ZI Nantes Carquefou, 44570 Carquefou Pays de Loire",
    "addr:housenumber":"5 bis",
    "addr:postcode":"44570",
    "addr:street":"Rue Bel Air Zi",
    "iso:country":"FR",
    "sg:address":"5 bis, Rue Bel Air - ZI Nantes Carquefou, 44570 Carquefou",
    "sg:orig_category":"Non-Classified Establishments",
    "sg:phone":"+33 2 28 23 08 00",
    "sg:province":"Pays de Loire",
    "wof:name":"Everest Vit France S.a.",
    "wof:placetype":"venue"
},
  "geometry": {"coordinates":[-2.187869,47.317436],"type":"Point"}
}