{
  "type": "Feature",
  "properties": {
    "iso:country":"FR",
    "sg:address":"41 Bis Rue Aristide Briand 39570 Montmorot",
    "sg:classifiers":[
        {
            "category":"Health Services",
            "subcategory":"Optometrist",
            "type":"Services"
        }
    ],
    "sg:phone":"+33 3 84 47 80 80",
    "sg:postcode":"39570",
    "sg:province":"Franche Comt\u00e9",
    "sg:tags":[
        "instrument",
        "optical",
        "-",
        "precision",
        "equipment"
    ],
    "wof:name":"Prost Boucle Sa",
    "wof:placetype":"venue"
},
  "geometry": {"coordinates":[5.535219,46.673878],"type":"Point"}
}