{
  "type": "Feature",
  "properties": {
    "addr:full":"64-66 rue des Mauges 49620 La Pommeraye Pays de Loire 49620",
    "addr:housenumber":"64-66",
    "addr:postcode":"49620;49620",
    "addr:street":"Rue Des Mauges;Pommeraye",
    "iso:country":"FR",
    "sg:address":"64-66 rue des Mauges 49620 La Pommeraye",
    "sg:classifiers":[
        {
            "category":"Building & Trades",
            "subcategory":"Equipment Rental",
            "type":"Services"
        }
    ],
    "sg:phone":"+33 2 41 72 13 60",
    "sg:postcode":"49620",
    "sg:province":"Pays de Loire",
    "sg:tags":[
        "first-aid"
    ],
    "wof:name":"Thema Sarl",
    "wof:placetype":"venue"
},
  "geometry": {"coordinates":[-0.856648,47.349854],"type":"Point"}
}