{
  "type": "Feature",
  "properties": {
    "iso:country":"FR",
    "sg:address":"4, Cours de Verdun, 33470 Gujan Mestras",
    "sg:city":"Gujan-Mestras",
    "sg:orig_category":"Non-Classified Establishments",
    "sg:phone":"+33 5 56 22 31 70",
    "sg:postcode":"33470",
    "sg:province":"Aquitaine",
    "wof:name":"B.p.s.o.",
    "wof:placetype":"venue"
},
  "geometry": {"coordinates":[-1.072899,44.635929],"type":"Point"}
}