{
  "type": "Feature",
  "properties": {
    "addr:full":"Rue Jean Monnet - ZI d'Etrich\u00e9 Segr\u00e9 Pays de Loire 49500",
    "addr:postcode":"49500",
    "addr:street":"Rue Jean Monnet Zi D'Etriche \u0301",
    "iso:country":"FR",
    "sg:address":"Rue Jean Monnet - ZI d'Etrich\u00e9",
    "sg:city":"Segr\u00e9",
    "sg:orig_category":"Non-Classified Establishments",
    "sg:phone":"+33 2 41 92 21 78",
    "sg:postcode":"49500",
    "sg:province":"Pays de Loire",
    "wof:name":"Soci\u00e9t\u00e9 Nouvelle Mercure Segreen E.u.r.l.",
    "wof:placetype":"venue"
},
  "geometry": {"coordinates":[-0.86016,47.693108],"type":"Point"}
}