{
  "type": "Feature",
  "properties": {
    "addr:full":"B.P. 1, 67036 Strasbourg C\u00e9dex^^189, Rte de Schirmeck, 67200 Strasbourg Strasbourg Alsace 67200",
    "addr:housenumber":"1",
    "addr:postcode":"67036;67200;67200",
    "addr:street":"B.P.;Rte De Schirmeck",
    "iso:country":"FR",
    "sg:address":"B.P. 1, 67036 Strasbourg C\u00e9dex^^189, Rte de Schirmeck, 67200 Strasbourg",
    "sg:city":"Strasbourg",
    "sg:orig_category":"Non-Classified Establishments",
    "sg:phone":"+33 3 88 67 46 22",
    "sg:postcode":"67200",
    "sg:province":"Alsace",
    "wof:name":"Frank S.a.",
    "wof:placetype":"venue"
},
  "geometry": {"coordinates":[7.71425,48.578671],"type":"Point"}
}