{
  "type": "Feature",
  "properties": {
    "addr:full":"5 Quai De France 76172 Rouen Aquitaine",
    "addr:housenumber":"5",
    "addr:postcode":"76172",
    "addr:street":"Quai De France",
    "iso:country":"FR",
    "sg:address":"5 Quai De France 76172 Rouen",
    "sg:classifiers":[
        {
            "category":"Autos & Motor Vehicles",
            "subcategory":"Automobile Sales",
            "type":"Retail Goods"
        }
    ],
    "sg:phone":"+33 2 35 63 55 55",
    "sg:province":"Aquitaine",
    "sg:tags":[
        "equipment",
        "industrial",
        "transport"
    ],
    "wof:name":"Bilia Trucks De Normandie",
    "wof:placetype":"venue"
},
  "geometry": {"coordinates":[1.06528,49.439644],"type":"Point"}
}