{
  "type": "Feature",
  "properties": {
    "iso:country":"FR",
    "sg:address":"2, Rue Jean Lamour, 54519 Vandoeuvre l\u00e8s Nancy C\u00e9dex",
    "sg:orig_category":"Non-Classified Establishments",
    "sg:phone":"+33 3 83 68 20 11",
    "sg:province":"Aquitaine",
    "wof:name":"Esstin Industrie",
    "wof:placetype":"venue"
},
  "geometry": {"coordinates":[6.188594,48.660156],"type":"Point"}
}