{
  "type": "Feature",
  "properties": {
    "iso:country":"FR",
    "sg:address":"305, Bd de L\u00e9ry - ZI les Playes, 83140 Six Fours les Plages",
    "sg:orig_category":"Non-Classified Establishments",
    "sg:phone":"+33 4 94 10 56 00",
    "sg:province":"Provence-Alpes-C\u00f4te d'Azur",
    "wof:name":"Soci\u00e9t\u00e9 Dim\u00e9o S.a.",
    "wof:placetype":"venue"
},
  "geometry": {"coordinates":[5.842716,43.093311],"type":"Point"}
}