{
  "type": "Feature",
  "properties": {
    "addr:full":"Cri\u00e9e 29100 Douarnenez Douarnenez Bretagne 29100",
    "addr:postcode":"29100;29100",
    "addr:street":"Crie\u0301E",
    "iso:country":"FR",
    "sg:address":"Cri\u00e9e 29100 Douarnenez",
    "sg:city":"Douarnenez",
    "sg:classifiers":[
        {
            "category":"Farming",
            "subcategory":"Livestock Farm",
            "type":"Manufacturing & Wholesale Goods"
        }
    ],
    "sg:phone":"+33 2 98 92 47 54",
    "sg:postcode":"29100",
    "sg:province":"Bretagne",
    "sg:tags":[
        "breeding",
        "agriculture",
        "animal"
    ],
    "wof:name":"Quideau Et Compagnie (sa)",
    "wof:placetype":"venue"
},
  "geometry": {"coordinates":[-4.349964,48.101341],"type":"Point"}
}