{
  "type": "Feature",
  "properties": {
    "addr:full":"10, Av. du Qu\u00e9bec - B\u00e2t. F3 - Immeuble Apis Technology, 91140 Villebon sur Yvette Ile de France",
    "addr:housenumber":"f3",
    "addr:postcode":"ba\u0302t;immeuble;91140",
    "addr:street":"10 Av. Du Que\u0301Bec;Technology",
    "iso:country":"FR",
    "sg:address":"10, Av. du Qu\u00e9bec - B\u00e2t. F3 - Immeuble Apis Technology, 91140 Villebon sur Yvette",
    "sg:orig_category":"Unclassifiable Establishments",
    "sg:phone":"+33 1 64 58 88 47",
    "sg:province":"Ile de France",
    "wof:name":"Uniwell France S.a.",
    "wof:placetype":"venue"
},
  "geometry": {"coordinates":[2.210402,48.687927],"type":"Point"}
}