{
  "type": "Feature",
  "properties": {
    "iso:country":"FR",
    "sg:address":"3, Rue Lavoisier, 27700 Les Andelys",
    "sg:orig_category":"Unclassifiable Establishments",
    "sg:phone":"+33 2 32 54 02 68",
    "sg:province":"Haute Normandie",
    "wof:name":"Le Barbier S.a.",
    "wof:placetype":"venue"
},
  "geometry": {"coordinates":[1.463625,49.195496],"type":"Point"}
}