{
  "type": "Feature",
  "properties": {
    "iso:country":"FR",
    "sg:address":"47, All\u00e9e des Impressionnistes, 93420 Villepinte",
    "sg:orig_category":"Unclassifiable Establishments",
    "sg:phone":"+33 1 49 38 83 00",
    "sg:province":"Ile de France",
    "wof:name":"Spicers France S.a.",
    "wof:placetype":"venue"
},
  "geometry": {"coordinates":[2.511515,48.973953],"type":"Point"}
}