{
  "type": "Feature",
  "properties": {
    "addr:full":"54, Rue du Gaz, 62100 Calais Nord Pas-de-Calais",
    "addr:housenumber":"54",
    "addr:postcode":"62100",
    "addr:street":"Rue Du Gaz;Calais;Pas-De-Calais",
    "iso:country":"FR",
    "sg:address":"54, Rue du Gaz, 62100 Calais",
    "sg:orig_category":"Unclassifiable Establishments",
    "sg:phone":"+33 3 21 46 01 01",
    "sg:province":"Nord Pas-de-Calais",
    "wof:name":"Localinge R.l.s.t., S.a.",
    "wof:placetype":"venue"
},
  "geometry": {"coordinates":[1.85305,50.953079],"type":"Point"}
}