{
  "type": "Feature",
  "properties": {
    "iso:country":"FR",
    "sg:address":"8 Rue Proudhon",
    "sg:city":"La Plaine St Denis",
    "sg:classifiers":[
        {
            "category":"Banks & Credit Unions",
            "subcategory":"Financial Services",
            "type":"Services"
        }
    ],
    "sg:phone":"+33 1 49 17 04 95",
    "sg:postcode":"93210",
    "sg:province":"Alsace",
    "sg:tags":[
        "banking",
        "finance",
        "insurance"
    ],
    "wof:name":"Scds Jdl",
    "wof:placetype":"venue"
},
  "geometry": {"coordinates":[2.359111,48.906391],"type":"Point"}
}