{
  "type": "Feature",
  "properties": {
    "addr:full":"Zone Commerciale d'Englos Sequedin Nord Pas-de-Calais 59320",
    "addr:postcode":"59320",
    "addr:street":"Zone Commerciale;Pas-De-Calais",
    "iso:country":"FR",
    "sg:address":"Zone Commerciale d'Englos",
    "sg:city":"Sequedin",
    "sg:orig_category":"Non-Classified Establishments",
    "sg:phone":"+33 3 20 00 94 20",
    "sg:postcode":"59320",
    "sg:province":"Nord Pas-de-Calais",
    "wof:name":"Perig\u00e9e Informatique S.a.r.l.",
    "wof:placetype":"venue"
},
  "geometry": {"coordinates":[2.971652,50.613201],"type":"Point"}
}