{
  "type": "Feature",
  "properties": {
    "iso:country":"FR",
    "sg:address":"30, Rue de la Fabrique, 68530 Buhl",
    "sg:city":"Buhl",
    "sg:orig_category":"Unclassifiable Establishments",
    "sg:phone":"+33 3 89 76 66 29",
    "sg:postcode":"68530",
    "sg:province":"Alsace",
    "wof:name":"Biscuiterie Wermelinger S.a.r.l.",
    "wof:placetype":"venue"
},
  "geometry": {"coordinates":[7.193951,47.92384],"type":"Point"}
}