{
  "type": "Feature",
  "properties": {
    "addr:full":"B.P. 01, 56326 Lorient C\u00e9dex^^73, Av. de la Perri\u00e8re, 56100 Lorient Lorient Bretagne 56100",
    "addr:postcode":"56326;56100;56100",
    "addr:street":"B.P. 01;Av. De La Perrie\u0300Re",
    "iso:country":"FR",
    "sg:address":"B.P. 01, 56326 Lorient C\u00e9dex^^73, Av. de la Perri\u00e8re, 56100 Lorient",
    "sg:city":"Lorient",
    "sg:orig_category":"Non-Classified Establishments",
    "sg:phone":"+33 2 97 87 94 14",
    "sg:postcode":"56100",
    "sg:province":"Bretagne",
    "wof:name":"Seastem S.a.",
    "wof:placetype":"venue"
},
  "geometry": {"coordinates":[-3.365181,47.748108],"type":"Point"}
}