{
  "type": "Feature",
  "properties": {
    "addr:full":"B.P. 1269, 25005 Besan\u00e7on C\u00e9dex^^21bis, Rue Alain Savary - TEMIS - Technopole Microtechnique et Scie Besan\u00e7on Franche Comt\u00e9 25000",
    "addr:postcode":"25005;25000",
    "addr:street":"B.P. 1269;Rue Alain Savary Temis;Franche Comte\u0301",
    "iso:country":"FR",
    "sg:address":"B.P. 1269, 25005 Besan\u00e7on C\u00e9dex^^21bis, Rue Alain Savary - TEMIS - Technopole Microtechnique et Scie",
    "sg:city":"Besan\u00e7on",
    "sg:orig_category":"Non-Classified Establishments",
    "sg:phone":"+33 3 81 41 65 00",
    "sg:postcode":"25000",
    "sg:province":"Franche Comt\u00e9",
    "wof:name":"D.r.i.r.e. - Direction R\u00e9gionale De L'industrie De La Recherche Et De L'environnement",
    "wof:placetype":"venue"
},
  "geometry": {"coordinates":[6.02091,47.239639],"type":"Point"}
}