{
  "type": "Feature",
  "properties": {
    "iso:country":"FR",
    "sg:address":"9, Rue Charles Fourier, 91011 Evry C\u00e9dex",
    "sg:orig_category":"Non-Classified Establishments",
    "sg:phone":"+33 1 60 76 40 40",
    "sg:province":"Ile de France",
    "wof:name":"Groupe Des Ecoles Des T\u00e9l\u00e9communications",
    "wof:placetype":"venue"
},
  "geometry": {"coordinates":[2.44432,48.623569],"type":"Point"}
}