{
  "type": "Feature",
  "properties": {
    "iso:country":"FR",
    "sg:address":"Rte du Bassin N\u00b01 - ZA - B\u00e2t. A9",
    "sg:city":"Gennevilliers C\u00e9dex",
    "sg:orig_category":"Non-Classified Establishments",
    "sg:phone":"+33 1 41 21 00 11",
    "sg:postcode":"92631",
    "sg:province":"Ile de France",
    "wof:name":"Adipak Ile De France S.a.",
    "wof:placetype":"venue"
},
  "geometry": {"coordinates":[2.265135,48.93763],"type":"Point"}
}