{
  "type": "Feature",
  "properties": {
    "addr:full":"Rte du Bassin N\u00b01 - ZA - B\u00e2t. A9 Gennevilliers C\u00e9dex Ile de France 92631",
    "addr:housenumber":"ba\u0302t a9",
    "addr:postcode":"n\u00b01;92631",
    "addr:street":"Rte Du Bassin;Za",
    "iso:country":"FR",
    "sg:address":"Rte du Bassin N\u00b01 - ZA - B\u00e2t. A9",
    "sg:city":"Gennevilliers C\u00e9dex",
    "sg:orig_category":"Non-Classified Establishments",
    "sg:phone":"+33 1 41 21 00 11",
    "sg:postcode":"92631",
    "sg:province":"Ile de France",
    "wof:name":"Adipak Ile De France S.a.",
    "wof:placetype":"venue"
},
  "geometry": {"coordinates":[2.265135,48.93763],"type":"Point"}
}