{
  "type": "Feature",
  "properties": {
    "iso:country":"FR",
    "sg:address":"Fief Des Quatre Chevaliers 17180 Perigny",
    "sg:classifiers":[
        {
            "category":"Autos & Motor Vehicles",
            "subcategory":"Boat Sales",
            "type":"Retail Goods"
        }
    ],
    "sg:phone":"+33 5 46 44 10 86",
    "sg:postcode":"17180",
    "sg:province":"Poitou-Charentes",
    "sg:tags":[
        "equipment",
        "transport"
    ],
    "wof:name":"Locwind",
    "wof:placetype":"venue"
},
  "geometry": {"coordinates":[-1.111506,46.164742],"type":"Point"}
}