{
  "type": "Feature",
  "properties": {
    "addr:full":"5, Rue des Champs, 78260 Ach\u00e8res Ile de France",
    "addr:housenumber":"5",
    "addr:postcode":"78260;ile",
    "addr:street":"Rue Des Champs",
    "iso:country":"FR",
    "sg:address":"5, Rue des Champs, 78260 Ach\u00e8res",
    "sg:orig_category":"Unclassifiable Establishments",
    "sg:phone":"+33 1 39 11 42 45",
    "sg:province":"Ile de France",
    "wof:name":"Gacec S.a.",
    "wof:placetype":"venue"
},
  "geometry": {"coordinates":[2.065633,48.957779],"type":"Point"}
}