{
  "type": "Feature",
  "properties": {
    "iso:country":"FR",
    "sg:address":"15/17, 4\u00e8me Rue - ZI des Estroublancs, 13127 Vitrolles",
    "sg:orig_category":"Unclassifiable Establishments",
    "sg:phone":"+33 4 42 10 54 00",
    "sg:province":"Provence-Alpes-C\u00f4te d'Azur",
    "wof:name":"Vital S.a.",
    "wof:placetype":"venue"
},
  "geometry": {"coordinates":[5.242467,43.424721],"type":"Point"}
}