{
  "type": "Feature",
  "properties": {
    "addr:full":"B.P. 12, 45331 Malesherbes C\u00e9dex^^Rte d'Etampes, 45330 Malesherbes Coudray Centre 45330",
    "addr:housenumber":"coudray",
    "addr:postcode":"45331;45330;45330",
    "addr:street":"B.P. 12;D'Etampes",
    "iso:country":"FR",
    "sg:address":"B.P. 12, 45331 Malesherbes C\u00e9dex^^Rte d'Etampes, 45330 Malesherbes",
    "sg:city":"Coudray",
    "sg:orig_category":"Non-Classified Establishments",
    "sg:phone":"+33 2 38 32 34 34",
    "sg:postcode":"45330",
    "sg:province":"Centre",
    "wof:name":"Maury Imprimeur S.a.",
    "wof:placetype":"venue"
},
  "geometry": {"coordinates":[2.34765,48.28389],"type":"Point"}
}