{
  "type": "Feature",
  "properties": {
    "addr:full":"7 Rue Aude 92210 St Cloud Ile de France",
    "addr:housenumber":"7",
    "addr:postcode":"92210",
    "addr:street":"Rue Aude",
    "iso:country":"FR",
    "sg:address":"7 Rue Aude 92210 St Cloud",
    "sg:classifiers":[
        {
            "category":"Professional",
            "subcategory":"Printing & Photocopies",
            "type":"Services"
        }
    ],
    "sg:phone":"+33 1 41 12 90 90",
    "sg:province":"Ile de France",
    "sg:tags":[
        "publishing"
    ],
    "wof:name":"Kapagama",
    "wof:placetype":"venue"
},
  "geometry": {"coordinates":[2.22154,48.842731],"type":"Point"}
}