{
  "type": "Feature",
  "properties": {
    "addr:full":"20 Rue Louis Armand Zae St Leu 95130 Le Plessis Bouchard Ile de France 95130",
    "addr:housenumber":"20",
    "addr:postcode":"95130;ile;95130",
    "addr:street":"Rue Louis Armand Zae;France",
    "iso:country":"FR",
    "sg:address":"20 Rue Louis Armand Zae St Leu 95130 Le Plessis Bouchard",
    "sg:classifiers":[
        {
            "category":"Wholesale",
            "subcategory":"Medical Equipment & Supplies",
            "type":"Manufacturing & Wholesale Goods"
        }
    ],
    "sg:phone":"+33 1 34 15 60 00",
    "sg:postcode":"95130",
    "sg:province":"Ile de France",
    "sg:tags":[
        "instrument",
        "health",
        "-",
        "precision"
    ],
    "wof:name":"Laboratoire Bernard Et Associes",
    "wof:placetype":"venue"
},
  "geometry": {"coordinates":[2.23118,48.986416],"type":"Point"}
}