{
  "type": "Feature",
  "properties": {
    "addr:full":"8, Av des Fr\u00e8res Montgolfier, 69680 Chassieu Rhone-Alpes",
    "addr:postcode":"69680",
    "addr:street":"Av Des Fre\u0300Res Montgolfier",
    "iso:country":"FR",
    "sg:address":"8, Av des Fr\u00e8res Montgolfier, 69680 Chassieu",
    "sg:orig_category":"Non-Classified Establishments",
    "sg:phone":"+33 4 78 40 19 56",
    "sg:province":"Rhone-Alpes",
    "wof:name":"V.s.r. Pro Cd S.a.",
    "wof:placetype":"venue"
},
  "geometry": {"coordinates":[4.965738,45.726841],"type":"Point"}
}