{
  "type": "Feature",
  "properties": {
    "addr:full":"157 rue de la R\u00e9publique; Guebwiller; 68501 Guebwiller Alsace 68500",
    "addr:housenumber":"157",
    "addr:postcode":"68501;68500",
    "addr:street":"Rue De La Re\u0301Publique",
    "iso:country":"FR",
    "sg:address":"157 rue de la R\u00e9publique; Guebwiller; 68501",
    "sg:city":"Guebwiller",
    "sg:classifiers":[
        {
            "category":"Banks & Credit Unions",
            "subcategory":"Bank",
            "type":"Services"
        }
    ],
    "sg:phone":"+33 3 89 74 67 30",
    "sg:postcode":"68500",
    "sg:province":"Alsace",
    "wof:name":"Cr\u00e9dit Industriel D'alsace, Et De Lorraine Sa",
    "wof:placetype":"venue"
},
  "geometry": {"coordinates":[7.208264,47.911938],"type":"Point"}
}