{
  "type": "Feature",
  "properties": {
    "iso:country":"FR",
    "sg:address":"Rue Jacquard - ZI du Phare",
    "sg:city":"M\u00e9rignac",
    "sg:orig_category":"Non-Classified Establishments",
    "sg:phone":"+33 5 56 34 34 80",
    "sg:postcode":"33700",
    "sg:province":"Aquitaine",
    "wof:name":"Sermat",
    "wof:placetype":"venue"
},
  "geometry": {"coordinates":[-0.64762,44.841808],"type":"Point"}
}