{
  "type": "Feature",
  "properties": {
    "iso:country":"FR",
    "sg:address":"B.P. 49, 44611 Saint Nazaire C\u00e9dex^^168, Rue Henri Gautier, 44600 Saint Nazaire",
    "sg:orig_category":"Non-Classified Establishments",
    "sg:phone":"+33 2 40 22 22 18",
    "sg:province":"Pays de Loire",
    "wof:name":"Outils Dock David S.a.",
    "wof:placetype":"venue"
},
  "geometry": {"coordinates":[-2.278494,47.240322],"type":"Point"}
}