{
  "type": "Feature",
  "properties": {
    "addr:full":"10, Rue de Pouy, 75013 Paris Ile de France 75013",
    "addr:housenumber":"10",
    "addr:postcode":"75013;75013",
    "addr:street":"Rue De Pouy",
    "iso:country":"FR",
    "sg:address":"10, Rue de Pouy, 75013 Paris",
    "sg:orig_category":"Non-Classified Establishments",
    "sg:phone":"+33 1 45 80 37 37",
    "sg:postcode":"75013",
    "sg:province":"Ile de France",
    "wof:name":"Eggo Conseils S.a.r.l.",
    "wof:placetype":"venue"
},
  "geometry": {"coordinates":[2.350716,48.827213],"type":"Point"}
}