{
  "type": "Feature",
  "properties": {
    "addr:full":"10, Rue Marcel Sallenave, 94854 Ivry sur Seine Pays de Loire",
    "addr:housenumber":"10",
    "addr:postcode":"94854",
    "addr:street":"Rue Marcel Sallenave;Seine",
    "iso:country":"FR",
    "sg:address":"10, Rue Marcel Sallenave, 94854 Ivry sur Seine",
    "sg:orig_category":"Non-Classified Establishments",
    "sg:phone":"+33 1 46 70 18 88",
    "sg:province":"Pays de Loire",
    "wof:name":"A.e.e. S.a. - Abacus Equipment Electronic",
    "wof:placetype":"venue"
},
  "geometry": {"coordinates":[4.376615,48.114494],"type":"Point"}
}