{
  "type": "Feature",
  "properties": {
    "addr:full":"85 av Edouard Millaud; Craponne Craponne Rhone-Alpes 69290",
    "addr:postcode":"69290",
    "addr:street":"85 Av Edouard Millaud",
    "iso:country":"FR",
    "sg:address":"85 av Edouard Millaud; Craponne",
    "sg:city":"Craponne",
    "sg:classifiers":[
        {
            "category":"Banks & Credit Unions",
            "subcategory":"Bank",
            "type":"Services"
        }
    ],
    "sg:phone":"+33 3378571468",
    "sg:postcode":"69290",
    "sg:province":"Rhone-Alpes",
    "wof:name":"Cr\u00e9dit Agricole Du Sud Est",
    "wof:placetype":"venue"
},
  "geometry": {"coordinates":[4.724964,45.747227],"type":"Point"}
}