{
  "type": "Feature",
  "properties": {
    "iso:country":"FR",
    "sg:address":"9 R Henri Dagallier 38100 Grenoble",
    "sg:classifiers":[
        {
            "category":"Manufacturing",
            "subcategory":"Printing",
            "type":"Manufacturing & Wholesale Goods"
        }
    ],
    "sg:phone":"+33 4 76 22 29 09",
    "sg:province":"Rhone-Alpes",
    "sg:tags":[
        "publishing"
    ],
    "wof:name":"Imprimerie De Murcia Sarl",
    "wof:placetype":"venue"
},
  "geometry": {"coordinates":[5.707515,45.160156],"type":"Point"}
}