{
  "type": "Feature",
  "properties": {
    "addr:full":"12, Rue Sakharov, 76130 Mont Saint Aignan Haute Normandie",
    "addr:housenumber":"12",
    "addr:postcode":"76130",
    "addr:street":"Rue Sakharov",
    "iso:country":"FR",
    "sg:address":"12, Rue Sakharov, 76130 Mont Saint Aignan",
    "sg:orig_category":"Unclassifiable Establishments",
    "sg:phone":"+33 2 35 12 20 30",
    "sg:province":"Haute Normandie",
    "wof:name":"Otis S.a.",
    "wof:placetype":"venue"
},
  "geometry": {"coordinates":[1.070859,49.46204],"type":"Point"}
}