{
  "type": "Feature",
  "properties": {
    "iso:country":"FR",
    "sg:address":"1, Place des Etats Unis, 94150 Rungis",
    "sg:orig_category":"Unclassifiable Establishments",
    "sg:phone":"+33 1 49 78 35 00",
    "sg:province":"Ile de France",
    "wof:name":"S\u00e9lisa S.a.",
    "wof:placetype":"venue"
},
  "geometry": {"coordinates":[2.355927,48.747971],"type":"Point"}
}