{
  "type": "Feature",
  "properties": {
    "addr:full":"14, Rue du Printemps, 75017 Paris Ile de France",
    "addr:housenumber":"14",
    "addr:postcode":"75017",
    "addr:street":"Rue Du Printemps",
    "iso:country":"FR",
    "sg:address":"14, Rue du Printemps, 75017 Paris",
    "sg:orig_category":"Unclassifiable Establishments",
    "sg:phone":"+33 1 44 29 60 00",
    "sg:province":"Ile de France",
    "wof:name":"Rep\u00e8res S.a.",
    "wof:placetype":"venue"
},
  "geometry": {"coordinates":[2.309505,48.887085],"type":"Point"}
}