{
  "type": "Feature",
  "properties": {
    "addr:full":"Au Canal Zi 42320 La Grand Croix Rhone-Alpes 42320",
    "addr:postcode":"42320;42320",
    "addr:street":"Zi;Grand Croix Rhone-Alpes",
    "iso:country":"FR",
    "sg:address":"Au Canal Zi 42320 La Grand Croix",
    "sg:classifiers":[
        {
            "category":"Home & Garden",
            "subcategory":"Furniture",
            "type":"Retail Goods"
        }
    ],
    "sg:phone":"+33 4 77 73 27 40",
    "sg:postcode":"42320",
    "sg:province":"Rhone-Alpes",
    "sg:tags":[
        "wood"
    ],
    "wof:name":"Emballages Font",
    "wof:placetype":"venue"
},
  "geometry": {"coordinates":[4.597547,45.493946],"type":"Point"}
}