{
  "type": "Feature",
  "properties": {
    "addr:full":"Rue Des Boutons D'Or 85130 La Gaubreti\u00e8re Pays de Loire 85130",
    "addr:postcode":"85130;85130",
    "addr:street":"Rue Des Boutons D'Or;Gaubretie\u0300Re",
    "iso:country":"FR",
    "sg:address":"Rue Des Boutons D'Or 85130 La Gaubreti\u00e8re",
    "sg:classifiers":[
        {
            "category":"Shopping",
            "subcategory":"Luggage & Leather Goods",
            "type":"Retail Goods"
        }
    ],
    "sg:phone":"+33 2 51 66 36 36",
    "sg:postcode":"85130",
    "sg:province":"Pays de Loire",
    "sg:tags":[
        "shoe"
    ],
    "wof:name":"Rautureau Apple Shoes Sa",
    "wof:placetype":"venue"
},
  "geometry": {"coordinates":[-1.068081,46.94392],"type":"Point"}
}