{
  "type": "Feature",
  "properties": {
    "iso:country":"FR",
    "sg:address":"B.P. 717, 92007 Nanterre C\u00e9dex^^78/82, Rue Alfred Dequeant, 92000 Nanterre",
    "sg:orig_category":"Non-Classified Establishments",
    "sg:phone":"+33 1 41 19 52 52",
    "sg:province":"Ile de France",
    "wof:name":"Schunk Electrographite S.a.s.",
    "wof:placetype":"venue"
},
  "geometry": {"coordinates":[2.194875,48.888084],"type":"Point"}
}