{
  "type": "Feature",
  "properties": {
    "iso:country":"FR",
    "sg:address":"5",
    "sg:city":"Descartes - ZI BP 5 cedex 95331 Domont",
    "sg:classifiers":[
        {
            "category":"Manufacturing",
            "subcategory":"Printing",
            "type":"Manufacturing & Wholesale Goods"
        }
    ],
    "sg:phone":"+33 1 39 91 56 71",
    "sg:province":"Centre",
    "sg:tags":[
        "publishing"
    ],
    "wof:name":"Bma Serigraphie",
    "wof:placetype":"venue"
},
  "geometry": {"coordinates":[2.326687,49.026634],"type":"Point"}
}