{
  "type": "Feature",
  "properties": {
    "addr:full":"14 Place D'Armes Toulon Bourgogne 83000",
    "addr:housenumber":"14",
    "addr:postcode":"83000",
    "addr:street":"Place D'Armes",
    "iso:country":"FR",
    "sg:address":"14 Place D'Armes",
    "sg:city":"Toulon",
    "sg:classifiers":[
        {
            "category":"Banks & Credit Unions",
            "subcategory":"Financial Services",
            "type":"Services"
        }
    ],
    "sg:phone":"+33 4 94 18 57 00",
    "sg:postcode":"83000",
    "sg:province":"Bourgogne",
    "sg:tags":[
        "banking",
        "finance",
        "insurance"
    ],
    "wof:name":"Societe Generale",
    "wof:placetype":"venue"
},
  "geometry": {"coordinates":[5.929801,43.123276],"type":"Point"}
}