{
  "type": "Feature",
  "properties": {
    "addr:full":"26, Rue Georges Guynemer, 63500 Issoire Issoire Auvergne 63500",
    "addr:housenumber":"26",
    "addr:postcode":"63500;63500",
    "addr:street":"Rue Georges Guynemer",
    "iso:country":"FR",
    "sg:address":"26, Rue Georges Guynemer, 63500 Issoire",
    "sg:city":"Issoire",
    "sg:orig_category":"Unclassifiable Establishments",
    "sg:phone":"+33 4 73 89 59 41",
    "sg:postcode":"63500",
    "sg:province":"Auvergne",
    "wof:name":"Auvernett S.a.r.l.",
    "wof:placetype":"venue"
},
  "geometry": {"coordinates":[3.234368,45.545067],"type":"Point"}
}