{
  "type": "Feature",
  "properties": {
    "iso:country":"FR",
    "sg:address":"3, Av. Gustave Eiffel, 28630 Gellainville",
    "sg:city":"Gellainville",
    "sg:orig_category":"Unclassifiable Establishments",
    "sg:phone":"+33 2 37 28 77 22",
    "sg:postcode":"28630",
    "sg:province":"Centre",
    "wof:name":"Sofrigel S.a.",
    "wof:placetype":"venue"
},
  "geometry": {"coordinates":[1.51966,48.427258],"type":"Point"}
}