{
  "type": "Feature",
  "properties": {
    "addr:full":"19, Place Moli\u00e8re, 49000 Angers Pays de Loire",
    "addr:housenumber":"19",
    "addr:postcode":"49000",
    "addr:street":"Place Molie\u0300Re",
    "iso:country":"FR",
    "sg:address":"19, Place Moli\u00e8re, 49000 Angers",
    "sg:orig_category":"Non-Classified Establishments",
    "sg:phone":"+33 2 41 87 91 91",
    "sg:province":"Pays de Loire",
    "wof:name":"Ordi Soft S.a.r.l.",
    "wof:placetype":"venue"
},
  "geometry": {"coordinates":[-0.555255,47.473793],"type":"Point"}
}