{
  "type": "Feature",
  "properties": {
    "addr:full":"17 rue Dupetit Thouars 75003 Paris Ile de France 75003",
    "addr:housenumber":"17",
    "addr:postcode":"75003;75003",
    "addr:street":"Rue Dupetit Thouars",
    "iso:country":"FR",
    "sg:address":"17 rue Dupetit Thouars 75003 Paris",
    "sg:classifiers":[
        {
            "category":"Real Estate",
            "subcategory":"Real Estate Operator",
            "type":"Services"
        }
    ],
    "sg:phone":"+33 1 49 96 60 60",
    "sg:postcode":"75003",
    "sg:province":"Ile de France",
    "sg:tags":[
        "application",
        "asp",
        "provider"
    ],
    "wof:name":"Ferrari-technotrans S.a.",
    "wof:placetype":"venue"
},
  "geometry": {"coordinates":[2.361202,48.865555],"type":"Point"}
}