{
  "type": "Feature",
  "properties": {
    "iso:country":"FR",
    "sg:address":"Zac Du Puy St Martin 74160 St Julien En Genevois",
    "sg:classifiers":[
        {
            "category":"Professional",
            "type":"Services"
        }
    ],
    "sg:phone":"+33 4 50 35 05 32",
    "sg:postcode":"74160",
    "sg:province":"Rhone-Alpes",
    "sg:tags":[
        "transport",
        "road"
    ],
    "wof:name":"Danzas Sa",
    "wof:placetype":"venue"
},
  "geometry": {"coordinates":[6.083075,46.141129],"type":"Point"}
}