{
  "type": "Feature",
  "properties": {
    "iso:country":"FR",
    "sg:address":"09310 Aston",
    "sg:classifiers":[
        {
            "category":"Utilities",
            "subcategory":"Electric",
            "type":"Services"
        }
    ],
    "sg:phone":"+33 5 61 64 77 29",
    "sg:postcode":"09310",
    "sg:province":"Midi Pyr\u00e9n\u00e9es",
    "sg:tags":[
        "electricity",
        "raw",
        "energy",
        "material"
    ],
    "wof:name":"Electricite De France (edf)",
    "wof:placetype":"venue"
},
  "geometry": {"coordinates":[1.674366,42.775761],"type":"Point"}
}