{
  "type": "Feature",
  "properties": {
    "addr:full":"85, Rue Chevalier, 33000 Bordeaux Bordeaux Aquitaine 33000",
    "addr:housenumber":"85",
    "addr:postcode":"33000;33000",
    "addr:street":"Rue Chevalier",
    "iso:country":"FR",
    "sg:address":"85, Rue Chevalier, 33000 Bordeaux",
    "sg:city":"Bordeaux",
    "sg:orig_category":"Unclassifiable Establishments",
    "sg:phone":"+33 5 56 51 23 23",
    "sg:postcode":"33000",
    "sg:province":"Aquitaine",
    "wof:name":"T.p. Sud Ouest S.a. - T\u00e9l\u00e9 Performance",
    "wof:placetype":"venue"
},
  "geometry": {"coordinates":[-0.596018,44.844391],"type":"Point"}
}