{
  "type": "Feature",
  "properties": {
    "iso:country":"FR",
    "sg:address":"167, Rue des Douets - ZI Tours Nord, 37100 Tours",
    "sg:city":"Tours",
    "sg:orig_category":"Non-Classified Establishments",
    "sg:phone":"+33 2 47 88 07 88",
    "sg:postcode":"37100",
    "sg:province":"Centre",
    "wof:name":"Fluidair",
    "wof:placetype":"venue"
},
  "geometry": {"coordinates":[0.69944,47.418121],"type":"Point"}
}