{
  "type": "Feature",
  "properties": {
    "addr:full":"B.P. 549, 59060 Roubaix C\u00e9dex 1^^64, Bd de Cambrai, 59100 Roubaix Nord Pas-de-Calais",
    "addr:housenumber":"b.p. 549;1;^ 64",
    "addr:postcode":"59060;59100",
    "addr:street":"^;Bd De Cambrai",
    "iso:country":"FR",
    "sg:address":"B.P. 549, 59060 Roubaix C\u00e9dex 1^^64, Bd de Cambrai, 59100 Roubaix",
    "sg:orig_category":"Non-Classified Establishments",
    "sg:phone":"+33 3 20 45 50 00",
    "sg:province":"Nord Pas-de-Calais",
    "wof:name":"Ibm France S.a.",
    "wof:placetype":"venue"
},
  "geometry": {"coordinates":[3.1752,50.691704],"type":"Point"}
}