{
  "type": "Feature",
  "properties": {
    "addr:full":"7, All\u00e9e des Atlantes - Parc les Propyl\u00e9es, 28000 Chartres Chartres Centre 28000",
    "addr:housenumber":"7",
    "addr:postcode":"28000;28000",
    "addr:street":"Alle\u0301E Des Atlantes Parc Les Propyle\u0301Es",
    "iso:country":"FR",
    "sg:address":"7, All\u00e9e des Atlantes - Parc les Propyl\u00e9es, 28000 Chartres",
    "sg:city":"Chartres",
    "sg:orig_category":"Unclassifiable Establishments",
    "sg:phone":"+33 2 37 88 09 00",
    "sg:postcode":"28000",
    "sg:province":"Centre",
    "wof:name":"I.s.t.a. G.e. Capital I.t.s.",
    "wof:placetype":"venue"
},
  "geometry": {"coordinates":[1.529195,48.4548],"type":"Point"}
}