{
  "type": "Feature",
  "properties": {
    "addr:full":"B.P. 33, 28240 La Loupe^^14, Rue de l'Eglise, 28240 La Loupe La Loupe Centre 28240",
    "addr:postcode":"28240;28240;28240",
    "addr:street":"B.P. 33;Rue De L'Eglise;La",
    "iso:country":"FR",
    "sg:address":"B.P. 33, 28240 La Loupe^^14, Rue de l'Eglise, 28240 La Loupe",
    "sg:city":"La Loupe",
    "sg:orig_category":"Non-Classified Establishments",
    "sg:phone":"+33 2 37 81 15 47",
    "sg:postcode":"28240",
    "sg:province":"Centre",
    "wof:name":"Souris Verte S.a.r.l.",
    "wof:placetype":"venue"
},
  "geometry": {"coordinates":[1.013616,48.471107],"type":"Point"}
}