{
  "type": "Feature",
  "properties": {
    "addr:full":"B.P. 3303, 54014 Nancy C\u00e9dex^^58 ter, Rue de Metz, 54000 Nancy Lorraine 54000",
    "addr:housenumber":"3303",
    "addr:postcode":"54014;54000;54000",
    "addr:street":"B.P.;Rue De Metz",
    "iso:country":"FR",
    "sg:address":"B.P. 3303, 54014 Nancy C\u00e9dex^^58 ter, Rue de Metz, 54000 Nancy",
    "sg:orig_category":"Non-Classified Establishments",
    "sg:phone":"+33 3 83 35 47 45",
    "sg:postcode":"54000",
    "sg:province":"Lorraine",
    "wof:name":"Arvier S.a.",
    "wof:placetype":"venue"
},
  "geometry": {"coordinates":[6.183405,48.689548],"type":"Point"}
}