{
  "type": "Feature",
  "properties": {
    "addr:full":"112, Rue du Faubourg Saint Honor\u00e9, 75008 Paris Ile de France",
    "addr:housenumber":"112",
    "addr:postcode":"75008",
    "addr:street":"Rue Du Faubourg Saint Honore\u0301",
    "iso:country":"FR",
    "sg:address":"112, Rue du Faubourg Saint Honor\u00e9, 75008 Paris",
    "sg:orig_category":"Unclassifiable Establishments",
    "sg:phone":"+33 1 53 43 43 00",
    "sg:province":"Ile de France",
    "wof:name":"H\u00f4tel Le Bristol",
    "wof:placetype":"venue"
},
  "geometry": {"coordinates":[2.314744,48.871727],"type":"Point"}
}