{
  "type": "Feature",
  "properties": {
    "iso:country":"FR",
    "sg:address":"20, Le Bourg, 67420 Bourg Bruche",
    "sg:city":"Bourg-Bruche",
    "sg:orig_category":"Unclassifiable Establishments",
    "sg:phone":"+33 3 88 97 75 11",
    "sg:postcode":"67420",
    "sg:province":"Alsace",
    "wof:name":"Reliure Magar",
    "wof:placetype":"venue"
},
  "geometry": {"coordinates":[7.13184,48.363773],"type":"Point"}
}