{
  "type": "Feature",
  "properties": {
    "addr:full":"Grande Rue 50530 Sartilly Sartilly Basse Normandie 50530",
    "addr:postcode":"50530;50530",
    "addr:street":"Grande Rue",
    "iso:country":"FR",
    "sg:address":"Grande Rue 50530 Sartilly",
    "sg:city":"Sartilly",
    "sg:classifiers":[
        {
            "category":"Home & Garden",
            "subcategory":"Furniture",
            "type":"Retail Goods"
        }
    ],
    "sg:phone":"+33 2 33 48 81 55",
    "sg:postcode":"50530",
    "sg:province":"Basse Normandie",
    "sg:tags":[
        "wood"
    ],
    "wof:name":"Societe Lorin (henne)",
    "wof:placetype":"venue"
},
  "geometry": {"coordinates":[-1.457904,48.753399],"type":"Point"}
}