{
  "type": "Feature",
  "properties": {
    "iso:country":"FR",
    "sg:address":"ZA la Gare",
    "sg:city":"La S\u00e9auve sur Sem\u00e8ne",
    "sg:orig_category":"Non-Classified Establishments",
    "sg:phone":"+33 4 71 60 01 71",
    "sg:postcode":"43140",
    "sg:province":"Auvergne",
    "wof:name":"Jolivet Et Compagnie S.a.",
    "wof:placetype":"venue"
},
  "geometry": {"coordinates":[4.25757,45.2957],"type":"Point"}
}