{
  "type": "Feature",
  "properties": {
    "addr:full":"5 Rue Guerbette 93220 Gagny Ile de France",
    "addr:housenumber":"5",
    "addr:postcode":"93220",
    "addr:street":"Rue Guerbette",
    "iso:country":"FR",
    "sg:address":"5 Rue Guerbette 93220 Gagny",
    "sg:classifiers":[
        {
            "category":"Professional",
            "type":"Services"
        }
    ],
    "sg:phone":"+33 1 43 02 51 33",
    "sg:province":"Ile de France",
    "sg:tags":[
        "transport",
        "road"
    ],
    "wof:name":"Tcgm",
    "wof:placetype":"venue"
},
  "geometry": {"coordinates":[2.525639,48.884426],"type":"Point"}
}