{
  "type": "Feature",
  "properties": {
    "iso:country":"FR",
    "sg:address":"2, Place Richelieu, 85400 Lu\u00e7on",
    "sg:orig_category":"Unclassifiable Establishments",
    "sg:phone":"+33 2 51 56 11 48",
    "sg:province":"Pays de Loire",
    "wof:name":"H. Vrignaud Fils S.a.",
    "wof:placetype":"venue"
},
  "geometry": {"coordinates":[-1.175959,46.45697],"type":"Point"}
}