{
  "type": "Feature",
  "properties": {
    "addr:full":"La Bougenti\u00e8re 49430 Montign\u00e9 l\u00e8s Rairies Pays de Loire",
    "addr:postcode":"49430",
    "addr:street":"Rairies",
    "iso:country":"FR",
    "sg:address":"La Bougenti\u00e8re 49430 Montign\u00e9 l\u00e8s Rairies",
    "sg:orig_category":"Non-Classified Establishments",
    "sg:phone":"+33 2 41 32 50 22",
    "sg:province":"Pays de Loire",
    "wof:name":"Ferme De La Table Au Roy S.c.e.a.",
    "wof:placetype":"venue"
},
  "geometry": {"coordinates":[-0.217984,47.619884],"type":"Point"}
}