{
  "type": "Feature",
  "properties": {
    "iso:country":"FR",
    "sg:address":"B.P. 9, 72440 Bouloire C\u00e9dex^^Rue de la Petite Charmoie - ZI, 72440 Bouloire",
    "sg:orig_category":"Non-Classified Establishments",
    "sg:phone":"+33 2 43 63 13 00",
    "sg:province":"Pays de Loire",
    "wof:name":"Lionce Industries S.a.r.l.",
    "wof:placetype":"venue"
},
  "geometry": {"coordinates":[0.57452,47.903477],"type":"Point"}
}