{
  "type": "Feature",
  "properties": {
    "addr:full":"Cours National; Graveson Midi Pyr\u00e9n\u00e9es",
    "addr:street":"Cours National",
    "iso:country":"FR",
    "sg:address":"Cours National; Graveson",
    "sg:classifiers":[
        {
            "category":"Banks & Credit Unions",
            "subcategory":"Bank",
            "type":"Services"
        }
    ],
    "sg:phone":"+33 3390957062",
    "sg:province":"Midi Pyr\u00e9n\u00e9es",
    "wof:name":"Cr\u00e9dit Agricole",
    "wof:placetype":"venue"
},
  "geometry": {"coordinates":[4.773093,43.850876],"type":"Point"}
}