{
  "type": "Feature",
  "properties": {
    "addr:full":"12, Rue des Sarcelles, 67300 Schiltigheim Schiltigheim Alsace 67300",
    "addr:housenumber":"12",
    "addr:postcode":"67300;67300",
    "addr:street":"Rue Des Sarcelles",
    "iso:country":"FR",
    "sg:address":"12, Rue des Sarcelles, 67300 Schiltigheim",
    "sg:city":"Schiltigheim",
    "sg:orig_category":"Non-Classified Establishments",
    "sg:phone":"+33 3 88 62 50 00",
    "sg:postcode":"67300",
    "sg:province":"Alsace",
    "wof:name":"L.p.c.r. S.a. - Les Produits Chimiques De La Robertsau",
    "wof:placetype":"venue"
},
  "geometry": {"coordinates":[7.774262,48.620216],"type":"Point"}
}