{
  "type": "Feature",
  "properties": {
    "iso:country":"FR",
    "sg:address":"130, Rue Tah\u00e8re, 92210 Saint Cloud",
    "sg:orig_category":"Unclassifiable Establishments",
    "sg:phone":"+33 1 47 71 82 84",
    "sg:province":"Ile de France",
    "wof:name":"Balac S.a.",
    "wof:placetype":"venue"
},
  "geometry": {"coordinates":[2.202718,48.846863],"type":"Point"}
}