{
  "type": "Feature",
  "properties": {
    "iso:country":"FR",
    "sg:address":"B.P. 30421, 44204 Nantes C\u00e9dex 02^^Quai Wilson, 44200 Nantes",
    "sg:orig_category":"Non-Classified Establishments",
    "sg:phone":"+33 2 40 89 74 33",
    "sg:postcode":"44200",
    "sg:province":"Pays de Loire",
    "wof:name":"Armor Travaux Maritimes S.n.c.",
    "wof:placetype":"venue"
},
  "geometry": {"coordinates":[-1.55206,47.199429],"type":"Point"}
}