{
  "type": "Feature",
  "properties": {
    "iso:country":"FR",
    "sg:address":"10, Place de la Libert\u00e9, 83000 Toulon",
    "sg:orig_category":"Unclassifiable Establishments",
    "sg:phone":"+33 4 94 91 85 58",
    "sg:province":"Provence-Alpes-C\u00f4te d'Azur",
    "wof:name":"Ab'sys S.a.r.l.",
    "wof:placetype":"venue"
},
  "geometry": {"coordinates":[5.931446,43.125828],"type":"Point"}
}