{
  "type": "Feature",
  "properties": {
    "iso:country":"FR",
    "sg:address":"18, Rue des Vignes, 31780 Castelginest",
    "sg:orig_category":"Unclassifiable Establishments",
    "sg:phone":"+33 5 61 70 94 94",
    "sg:province":"Midi Pyr\u00e9n\u00e9es",
    "wof:name":"L.m.d.i. S.a. - Logistique Manutention D\u00e9velop Industrie",
    "wof:placetype":"venue"
},
  "geometry": {"coordinates":[1.438399,43.693298],"type":"Point"}
}