{
  "type": "Feature",
  "properties": {
    "iso:country":"FR",
    "sg:address":"3 Rue Offenbach 26000 Valence",
    "sg:classifiers":[
        {
            "category":"Professional",
            "subcategory":"Engineering",
            "type":"Services"
        }
    ],
    "sg:phone":"+33 4 75 78 52 45",
    "sg:postcode":"26000",
    "sg:province":"Rhone-Alpes",
    "sg:tags":[
        "machine",
        "-",
        "mechanical"
    ],
    "wof:name":"Ertm S.a.",
    "wof:placetype":"venue"
},
  "geometry": {"coordinates":[4.889246,44.930458],"type":"Point"}
}