{
  "type": "Feature",
  "properties": {
    "iso:country":"FR",
    "sg:address":"Les Berthiers - la Moynerie 58150 Saint Andelain",
    "sg:city":"Garchy",
    "sg:orig_category":"Non-Classified Establishments",
    "sg:phone":"+33 3 86 39 14 72",
    "sg:postcode":"58150",
    "sg:province":"Bourgogne",
    "wof:name":"Michel Redde Et Fils S.a.",
    "wof:placetype":"venue"
},
  "geometry": {"coordinates":[3.071695,47.263222],"type":"Point"}
}