{
  "type": "Feature",
  "properties": {
    "iso:country":"FR",
    "sg:address":"5, Rue de l'Houmaille - ZI de Chevir\u00e9, 44340 Bouguenais",
    "sg:orig_category":"Unclassifiable Establishments",
    "sg:phone":"+33 2 51 11 20 00",
    "sg:province":"Pays de Loire",
    "wof:name":"Pinault Centre Ouest S.n.c.",
    "wof:placetype":"venue"
},
  "geometry": {"coordinates":[-1.599109,47.190739],"type":"Point"}
}