{
  "type": "Feature",
  "properties": {
    "iso:country":"FR",
    "sg:address":"Av Chardonnet 35000 Rennes",
    "sg:city":"Rennes",
    "sg:classifiers":[
        {
            "category":"Banks & Credit Unions",
            "subcategory":"Investment Brokerage",
            "type":"Services"
        }
    ],
    "sg:phone":"+33 2 99 27 61 00",
    "sg:postcode":"35000",
    "sg:province":"Bretagne",
    "sg:tags":[
        "-",
        "transport",
        "related"
    ],
    "wof:name":"Conteneurs (compagnie Nouvelle De) Sa",
    "wof:placetype":"venue"
},
  "geometry": {"coordinates":[-1.648109,48.106987],"type":"Point"}
}