{
  "type": "Feature",
  "properties": {
    "addr:full":"6 bis, Bd des Manouvriers, 53810 Chang\u00e9 Pays de Loire",
    "addr:housenumber":"6 bis",
    "addr:postcode":"53810",
    "addr:street":"Bd Des Manouvriers",
    "iso:country":"FR",
    "sg:address":"6 bis, Bd des Manouvriers, 53810 Chang\u00e9",
    "sg:orig_category":"Unclassifiable Establishments",
    "sg:phone":"+33 2 43 53 39 56",
    "sg:province":"Pays de Loire",
    "wof:name":"I.s.r. Informatique S.a.r.l.",
    "wof:placetype":"venue"
},
  "geometry": {"coordinates":[-0.777169,48.096828],"type":"Point"}
}