{
  "type": "Feature",
  "properties": {
    "addr:full":"152, Av. de Malakoff - Tour Vend\u00f4me, 75116 Paris Ile-de-France",
    "addr:postcode":"75116",
    "addr:street":"152 Av. De Malakoff Tour Vendo\u0302Me",
    "iso:country":"FR",
    "sg:address":"152, Av. de Malakoff - Tour Vend\u00f4me, 75116 Paris",
    "sg:orig_category":"Non-Classified Establishments",
    "sg:phone":"+33 1 44 17 66 65",
    "sg:province":"Ile-de-France",
    "wof:name":"Etablissements Soules Et Compagnie S.a.",
    "wof:placetype":"venue"
},
  "geometry": {"coordinates":[2.283851,48.876385],"type":"Point"}
}