{
  "type": "Feature",
  "properties": {
    "addr:full":"34, Rue Etienne Dolet, 08120 Bogny sur Meuse Bogny-sur-Meuse Champagne 08120",
    "addr:housenumber":"34",
    "addr:postcode":"08120;08120",
    "addr:street":"Rue Etienne Dolet;Bogny;Meuse;Champagne",
    "iso:country":"FR",
    "sg:address":"34, Rue Etienne Dolet, 08120 Bogny sur Meuse",
    "sg:city":"Bogny-sur-Meuse",
    "sg:orig_category":"BOULONNERIE, VISSERIE",
    "sg:phone":"+33 3 24 32 14 39",
    "sg:postcode":"08120",
    "sg:province":"Champagne",
    "wof:name":"Dauvin Fils Boulonnerie S.a.",
    "wof:placetype":"venue"
},
  "geometry": {"coordinates":[4.76716,49.848049],"type":"Point"}
}