{
  "type": "Feature",
  "properties": {
    "addr:full":"Av Ch\u00e2teaubriand 22500 Paimpol Paimpol Bretagne 22500",
    "addr:postcode":"22500;22500",
    "addr:street":"Av Cha\u0302Teaubriand",
    "iso:country":"FR",
    "sg:address":"Av Ch\u00e2teaubriand 22500 Paimpol",
    "sg:city":"Paimpol",
    "sg:classifiers":[
        {
            "category":"Farming",
            "subcategory":"Farm",
            "type":"Manufacturing & Wholesale Goods"
        }
    ],
    "sg:phone":"+33 2 96 20 86 48",
    "sg:postcode":"22500",
    "sg:province":"Bretagne",
    "sg:tags":[
        "horticulture",
        "agriculture",
        "livestock"
    ],
    "wof:name":"Gamm Vert Sica Du Gouessant Franchise",
    "wof:placetype":"venue"
},
  "geometry": {"coordinates":[-3.043884,48.778053],"type":"Point"}
}