{
  "type": "Feature",
  "properties": {
    "addr:full":"Chemin des Meuniers Willems Nord Pas-de-Calais 59780",
    "addr:postcode":"59780",
    "addr:street":"Chemin Des Meuniers Willems Nord",
    "iso:country":"FR",
    "sg:address":"Chemin des Meuniers",
    "sg:city":"Willems",
    "sg:orig_category":"Unclassifiable Establishments",
    "sg:phone":"+33 3 28 37 01 01",
    "sg:postcode":"59780",
    "sg:province":"Nord Pas-de-Calais",
    "wof:name":"Tiberghien Fils S.a.r.l.",
    "wof:placetype":"venue"
},
  "geometry": {"coordinates":[3.244115,50.632343],"type":"Point"}
}