{
  "type": "Feature",
  "properties": {
    "addr:full":"Bureaux de Rosny 2 Rosny sous Bois C\u00e9dex Poitou-Charentes 93118",
    "addr:housenumber":"2",
    "addr:postcode":"93118",
    "addr:street":"Bureaux;Rosny;Ce\u0301Dex",
    "iso:country":"FR",
    "sg:address":"Bureaux de Rosny 2",
    "sg:city":"Rosny sous Bois C\u00e9dex",
    "sg:orig_category":"Non-Classified Establishments",
    "sg:phone":"+33 1 49 35 21 21",
    "sg:postcode":"93118",
    "sg:province":"Poitou-Charentes",
    "wof:name":"Kellogg's P.a. S.a.",
    "wof:placetype":"venue"
},
  "geometry": {"coordinates":[2.485155,48.872375],"type":"Point"}
}