{
  "type": "Feature",
  "properties": {
    "addr:full":"5 bis, Rue Chauvelot, 75015 Paris Ile de France",
    "addr:housenumber":"5 bis",
    "addr:postcode":"75015",
    "addr:street":"Rue Chauvelot",
    "iso:country":"FR",
    "sg:address":"5 bis, Rue Chauvelot, 75015 Paris",
    "sg:orig_category":"Non-Classified Establishments",
    "sg:phone":"+33 1 48 56 14 07",
    "sg:province":"Ile de France",
    "wof:name":"Hippo Distribution S.a.r.l.",
    "wof:placetype":"venue"
},
  "geometry": {"coordinates":[2.302365,48.829357],"type":"Point"}
}