{
  "type": "Feature",
  "properties": {
    "iso:country":"FR",
    "sg:address":"5, Rue de Sable, 72140 Sill\u00e9 le Guillaume",
    "sg:orig_category":"Unclassifiable Establishments",
    "sg:phone":"+33 2 43 20 10 16",
    "sg:province":"Pays de Loire",
    "wof:name":"Kdi Chartier S.a.s.",
    "wof:placetype":"venue"
},
  "geometry": {"coordinates":[-0.13376,48.181004],"type":"Point"}
}