{
  "type": "Feature",
  "properties": {
    "addr:full":"1, Rue de Ch\u00e2lon sur Sa\u00f4ne, 69007 Lyon Rhone-Alpes 69007",
    "addr:housenumber":"1",
    "addr:postcode":"69007;69007",
    "addr:street":"Rue De Cha\u0302Lon;Sao\u0302Ne",
    "iso:country":"FR",
    "sg:address":"1, Rue de Ch\u00e2lon sur Sa\u00f4ne, 69007 Lyon",
    "sg:orig_category":"Non-Classified Establishments",
    "sg:phone":"+33 4 78 72 65 53",
    "sg:postcode":"69007",
    "sg:province":"Rhone-Alpes",
    "wof:name":"C.n.r. S.a. - Compagnie Nationale Du Rh\u00f4ne",
    "wof:placetype":"venue"
},
  "geometry": {"coordinates":[4.832334,45.721729],"type":"Point"}
}