{
  "type": "Feature",
  "properties": {
    "iso:country":"FR",
    "sg:address":"12, Rue Bl\u00e9riot, 49300 Cholet",
    "sg:orig_category":"Unclassifiable Establishments",
    "sg:phone":"+33 2 41 58 02 34",
    "sg:province":"Pays de Loire",
    "wof:name":"M.s.c. S.a.r.l.",
    "wof:placetype":"venue"
},
  "geometry": {"coordinates":[-0.87243,47.070641],"type":"Point"}
}