{
  "type": "Feature",
  "properties": {
    "iso:country":"FR",
    "sg:address":"Rue de l'Abb\u00e9 Pierre Nachin",
    "sg:city":"Vitrey sur Mance",
    "sg:orig_category":"Unclassifiable Establishments",
    "sg:phone":"+33 3 84 68 53 67",
    "sg:postcode":"70500",
    "sg:province":"Franche Comt\u00e9",
    "wof:name":"Castellani S.a.r.l.",
    "wof:placetype":"venue"
},
  "geometry": {"coordinates":[5.76091,47.814072],"type":"Point"}
}