{
  "type": "Feature",
  "properties": {
    "addr:full":"Zi De Bellevue 22200 St Agathon Squiffiec Bretagne 22200",
    "addr:postcode":"22200;squiffiec;22200",
    "addr:street":"Zi De Bellevue",
    "iso:country":"FR",
    "sg:address":"Zi De Bellevue 22200 St Agathon",
    "sg:city":"Squiffiec",
    "sg:classifiers":[
        {
            "category":"Wholesale",
            "subcategory":"Meat",
            "type":"Manufacturing & Wholesale Goods"
        }
    ],
    "sg:phone":"+33 2 96 11 97 97",
    "sg:postcode":"22200",
    "sg:province":"Bretagne",
    "sg:tags":[
        "food",
        "cooked",
        "product",
        "related"
    ],
    "wof:name":"La Maison Des Gourmets",
    "wof:placetype":"venue"
},
  "geometry": {"coordinates":[-3.104819,48.559273],"type":"Point"}
}