{
  "type": "Feature",
  "properties": {
    "iso:country":"FR",
    "sg:address":"Zone Industrielle Biopole Lotissement Biopole 32500 Fleurance",
    "sg:classifiers":[
        {
            "category":"Food & Beverages",
            "subcategory":"Fruits & Vegetables",
            "type":"Retail Goods"
        }
    ],
    "sg:phone":"+33 5 62 64 04 12",
    "sg:postcode":"32500",
    "sg:province":"Midi Pyr\u00e9n\u00e9es",
    "sg:tags":[
        "frozen",
        "product",
        "related"
    ],
    "wof:name":"Artegel",
    "wof:placetype":"venue"
},
  "geometry": {"coordinates":[0.659451,43.850388],"type":"Point"}
}