{
  "type": "Feature",
  "properties": {
    "iso:country":"FR",
    "sg:address":"2 Rue Emile Mathis 67150 Erstein",
    "sg:city":"Erstein",
    "sg:classifiers":[
        {
            "category":"Professional",
            "subcategory":"Engineering",
            "type":"Services"
        }
    ],
    "sg:phone":"+33 3 88 98 60 84",
    "sg:postcode":"67150",
    "sg:province":"Alsace",
    "sg:tags":[
        "machine",
        "-",
        "mechanical"
    ],
    "wof:name":"Erstein Engrenages Sarl",
    "wof:placetype":"venue"
},
  "geometry": {"coordinates":[7.634065,48.421822],"type":"Point"}
}