{
  "type": "Feature",
  "properties": {
    "addr:full":"55, Bd de la R\u00e9publique, 13100 Aix en Provence Nord Pas-de-Calais",
    "addr:housenumber":"55",
    "addr:postcode":"13100",
    "addr:street":"Bd De La Re\u0301Publique;En Provence Nord",
    "iso:country":"FR",
    "sg:address":"55, Bd de la R\u00e9publique, 13100 Aix en Provence",
    "sg:orig_category":"Unclassifiable Establishments",
    "sg:phone":"+33 4 42 27 83 00",
    "sg:province":"Nord Pas-de-Calais",
    "wof:name":"Locauvar",
    "wof:placetype":"venue"
},
  "geometry": {"coordinates":[5.440182,43.528759],"type":"Point"}
}