{
  "type": "Feature",
  "properties": {
    "addr:full":"2 Rue Des Gardes 91370 Verri\u00e8res Le Buisson Ile de France 91370",
    "addr:housenumber":"2",
    "addr:postcode":"91370;91370",
    "addr:street":"Rue Des Gardes",
    "iso:country":"FR",
    "sg:address":"2 Rue Des Gardes 91370 Verri\u00e8res Le Buisson",
    "sg:classifiers":[
        {
            "category":"Manufacturing",
            "subcategory":"Wood Products",
            "type":"Manufacturing & Wholesale Goods"
        }
    ],
    "sg:phone":"+33 1 69 53 69 53",
    "sg:postcode":"91370",
    "sg:province":"Ile de France",
    "sg:tags":[
        "printing",
        "miscellaneous",
        "publishing"
    ],
    "wof:name":"Depiesse Sa",
    "wof:placetype":"venue"
},
  "geometry": {"coordinates":[2.28196,48.744991],"type":"Point"}
}