{
  "type": "Feature",
  "properties": {
    "addr:full":"2, Chemin des Romains, 57730 Lachambre Lorraine",
    "addr:housenumber":"2",
    "addr:postcode":"57730",
    "addr:street":"Chemin Des Romains",
    "iso:country":"FR",
    "sg:address":"2, Chemin des Romains, 57730 Lachambre",
    "sg:orig_category":"Unclassifiable Establishments",
    "sg:phone":"+33 3 87 00 36 50",
    "sg:province":"Lorraine",
    "wof:name":"Servifroid S.a.r.l.",
    "wof:placetype":"venue"
},
  "geometry": {"coordinates":[6.728431,49.088413],"type":"Point"}
}