{
  "type": "Feature",
  "properties": {
    "addr:full":"B.P. 6, 71590 Gergy^^Rue du Pr\u00e9 de la Mare - Z.A. du Bourg, 71590 Gergy Gergy Bourgogne 71590",
    "addr:housenumber":"6",
    "addr:postcode":"71590;71590;71590",
    "addr:street":"B.P.;Du Pre\u0301 De La Mare Z.A. Du Bourg",
    "iso:country":"FR",
    "sg:address":"B.P. 6, 71590 Gergy^^Rue du Pr\u00e9 de la Mare - Z.A. du Bourg, 71590 Gergy",
    "sg:city":"Gergy",
    "sg:orig_category":"Non-Classified Establishments",
    "sg:phone":"+33 3 85 98 98 98",
    "sg:postcode":"71590",
    "sg:province":"Bourgogne",
    "wof:name":"A\u00e9rom\u00e9tal S.a.",
    "wof:placetype":"venue"
},
  "geometry": {"coordinates":[4.94654,46.877941],"type":"Point"}
}