{
  "type": "Feature",
  "properties": {
    "iso:country":"FR",
    "sg:address":"Grande Rue 25360 Naisey Les Granges",
    "sg:classifiers":[
        {
            "category":"Farming",
            "subcategory":"Farm & Veterinary Services",
            "type":"Manufacturing & Wholesale Goods"
        }
    ],
    "sg:phone":"+33 3 81 55 23 35",
    "sg:postcode":"25360",
    "sg:province":"Franche Comt\u00e9",
    "sg:tags":[
        "advice",
        "agriculture",
        "livestock",
        "business"
    ],
    "wof:name":"Sarl Sapolin Freres",
    "wof:placetype":"venue"
},
  "geometry": {"coordinates":[6.239843,47.21323],"type":"Point"}
}