{
  "type": "Feature",
  "properties": {
    "iso:country":"FR",
    "sg:address":"80, Rue du 29 Juillet, 62100 Calais",
    "sg:orig_category":"Unclassifiable Establishments",
    "sg:phone":"+33 3 21 46 73 73",
    "sg:province":"Nord Pas-de-Calais",
    "wof:name":"Crystal, S.a.",
    "wof:placetype":"venue"
},
  "geometry": {"coordinates":[1.847608,50.943726],"type":"Point"}
}