{
  "type": "Feature",
  "properties": {
    "addr:full":"Les Petites Yvelines - Les Br\u00e9viaires Le Perray en Yvelines Ile de France 78610",
    "addr:housenumber":"bre\u0301viaires",
    "addr:postcode":"78610",
    "addr:street":"Les;Yvelines Les",
    "iso:country":"FR",
    "sg:address":"Les Petites Yvelines - Les Br\u00e9viaires",
    "sg:city":"Le Perray en Yvelines",
    "sg:orig_category":"Unclassifiable Establishments",
    "sg:phone":"+33 1 34 84 10 22",
    "sg:postcode":"78610",
    "sg:province":"Ile de France",
    "wof:name":"Jardins & For\u00eats S.a.r.l.",
    "wof:placetype":"venue"
},
  "geometry": {"coordinates":[1.854045,48.694569],"type":"Point"}
}