{
  "type": "Feature",
  "properties": {
    "addr:full":"12, Rue du Parc, 41150 Onzain Onzain Centre 41150",
    "addr:housenumber":"12;onzain",
    "addr:postcode":"41150;41150",
    "addr:street":"Rue Du Parc",
    "iso:country":"FR",
    "sg:address":"12, Rue du Parc, 41150 Onzain",
    "sg:city":"Onzain",
    "sg:orig_category":"Non-Classified Establishments",
    "sg:phone":"+33 2 54 20 71 05",
    "sg:postcode":"41150",
    "sg:province":"Centre",
    "wof:name":"Lenoir Et Compagnie S.a.r.l.",
    "wof:placetype":"venue"
},
  "geometry": {"coordinates":[1.176655,47.499577],"type":"Point"}
}