{
  "type": "Feature",
  "properties": {
    "iso:country":"FR",
    "sg:address":"B.P. 3, 80500 Rollot^^55, Rue Haute, 80500 Rollot",
    "sg:orig_category":"Non-Classified Establishments",
    "sg:phone":"+33 3 22 78 28 93",
    "sg:postcode":"80500",
    "sg:province":"Picardie",
    "wof:name":"Condi Film S.a. - Soci\u00e9t\u00e9 Industrielle Des Produits Condi Film",
    "wof:placetype":"venue"
},
  "geometry": {"coordinates":[2.571364,49.647224],"type":"Point"}
}