{
  "type": "Feature",
  "properties": {
    "addr:full":"135 Bd S\u00e9bastopol 75002 Paris Ile de France 75002",
    "addr:housenumber":"135",
    "addr:postcode":"75002;75002",
    "addr:street":"Bd Se\u0301Bastopol",
    "iso:country":"FR",
    "sg:address":"135 Bd S\u00e9bastopol 75002 Paris",
    "sg:classifiers":[
        {
            "category":"Shopping",
            "subcategory":"Clothing, Apparel, & Fashions",
            "type":"Retail Goods"
        }
    ],
    "sg:phone":"+33 1 42 33 05 69",
    "sg:postcode":"75002",
    "sg:province":"Ile de France",
    "sg:tags":[
        "textile",
        "clothing",
        "clothes"
    ],
    "wof:name":"Jerry Mod",
    "wof:placetype":"venue"
},
  "geometry": {"coordinates":[2.353618,48.86832],"type":"Point"}
}