{
  "type": "Feature",
  "properties": {
    "iso:country":"FR",
    "sg:address":"1, Av. Marcel Dassault, 93360 Neuilly Plaisance",
    "sg:orig_category":"Unclassifiable Establishments",
    "sg:phone":"+33 1 43 09 91 39",
    "sg:province":"Ile de France",
    "wof:name":"Schatz France S.a.r.l.",
    "wof:placetype":"venue"
},
  "geometry": {"coordinates":[2.516377,48.864525],"type":"Point"}
}