{
  "type": "Feature",
  "properties": {
    "iso:country":"FR",
    "sg:address":"Za Beau Soleil 44680 Ste Pazanne",
    "sg:classifiers":[
        {
            "category":"Manufacturing",
            "subcategory":"Textiles",
            "type":"Manufacturing & Wholesale Goods"
        }
    ],
    "sg:phone":"+33 2 40 02 41 38",
    "sg:postcode":"44680",
    "sg:province":"Pays de Loire",
    "sg:tags":[
        "clothing",
        "accessory"
    ],
    "wof:name":"Balsan Sa",
    "wof:placetype":"venue"
},
  "geometry": {"coordinates":[-1.812382,47.10154],"type":"Point"}
}