{
  "type": "Feature",
  "properties": {
    "addr:full":"28, Av. de Messine, 75008 Paris Ile de France",
    "addr:postcode":"75008",
    "addr:street":"28 Av. De Messine",
    "iso:country":"FR",
    "sg:address":"28, Av. de Messine, 75008 Paris",
    "sg:orig_category":"Non-Classified Establishments",
    "sg:phone":"+33 1 56 88 38 28",
    "sg:province":"Ile de France",
    "wof:name":"M\u00e9dia Prisme S.a.",
    "wof:placetype":"venue"
},
  "geometry": {"coordinates":[2.312046,48.876965],"type":"Point"}
}