{
  "type": "Feature",
  "properties": {
    "addr:full":"113, Rue du 1er Mars 1943, 69100 Villeurbanne Rhone-Alpes 69100",
    "addr:housenumber":"113",
    "addr:postcode":"69100;69100",
    "addr:street":"Rue Du 1Er Mars 1943",
    "iso:country":"FR",
    "sg:address":"113, Rue du 1er Mars 1943, 69100 Villeurbanne",
    "sg:orig_category":"Unclassifiable Establishments",
    "sg:phone":"+33 4 72 33 00 62",
    "sg:postcode":"69100",
    "sg:province":"Rhone-Alpes",
    "wof:name":"C.s.t. France S.a.",
    "wof:placetype":"venue"
},
  "geometry": {"coordinates":[4.889318,45.761791],"type":"Point"}
}