{
  "type": "Feature",
  "properties": {
    "addr:full":"10, Rue Treillard, 75008 Paris Ile de France",
    "addr:housenumber":"10",
    "addr:postcode":"75008",
    "addr:street":"Rue Treillard",
    "iso:country":"FR",
    "sg:address":"10, Rue Treillard, 75008 Paris",
    "sg:orig_category":"Unclassifiable Establishments",
    "sg:phone":"+33 800 06 22 22",
    "sg:province":"Ile de France",
    "wof:name":"Nabab S.a.",
    "wof:placetype":"venue"
},
  "geometry": {"coordinates":[2.314488,48.877171],"type":"Point"}
}