{
  "type": "Feature",
  "properties": {
    "addr:full":"1 Grande Rue; Brunoy; 91800 Ile de France 91800",
    "addr:housenumber":"1",
    "addr:postcode":"91800;91800",
    "addr:street":"Grande Rue Brunoy;France",
    "iso:country":"FR",
    "sg:address":"1 Grande Rue; Brunoy; 91800",
    "sg:classifiers":[
        {
            "category":"Banks & Credit Unions",
            "subcategory":"Bank",
            "type":"Services"
        }
    ],
    "sg:phone":"+33 3360460971",
    "sg:postcode":"91800",
    "sg:province":"Ile de France",
    "wof:name":"Banque Nationale De Paris",
    "wof:placetype":"venue"
},
  "geometry": {"coordinates":[2.503528,48.697952],"type":"Point"}
}