{
  "type": "Feature",
  "properties": {
    "iso:country":"FR",
    "sg:address":"Rue Jean Marie Birrien 29520 Ch\u00e2teauneuf Du Faou",
    "sg:city":"Ch\u00e2teauneuf-du-Faou",
    "sg:classifiers":[
        {
            "category":"Wholesale",
            "subcategory":"Machinery & Supplies",
            "type":"Manufacturing & Wholesale Goods"
        }
    ],
    "sg:phone":"+33 2 98 81 73 66",
    "sg:postcode":"29520",
    "sg:province":"Bretagne",
    "sg:tags":[
        "-",
        "machine",
        "equipment",
        "engineering",
        "animal",
        "mechanical",
        "breeding",
        "agriculture"
    ],
    "wof:name":"Etablissements Andre Goeffic Sa",
    "wof:placetype":"venue"
},
  "geometry": {"coordinates":[-3.819959,48.189507],"type":"Point"}
}