{
  "type": "Feature",
  "properties": {
    "iso:country":"FR",
    "sg:address":"7 Bis R Galli\u00e9ni 76600 Le Havre",
    "sg:classifiers":[
        {
            "category":"Banks & Credit Unions",
            "subcategory":"Bank",
            "type":"Services"
        }
    ],
    "sg:phone":"+33 2 35 21 10 21",
    "sg:province":"Haute Normandie",
    "sg:tags":[
        "sea",
        "transport",
        "road"
    ],
    "wof:name":"Norsram Sa",
    "wof:placetype":"venue"
},
  "geometry": {"coordinates":[0.114265,49.493496],"type":"Point"}
}