{
  "type": "Feature",
  "properties": {
    "addr:full":"7, Rue des B\u00e9n\u00e9dictines, 57950 Montigny l\u00e8s Metz Ile de France",
    "addr:housenumber":"7",
    "addr:postcode":"57950",
    "addr:street":"Rue Des Be\u0301Ne\u0301Dictines",
    "iso:country":"FR",
    "sg:address":"7, Rue des B\u00e9n\u00e9dictines, 57950 Montigny l\u00e8s Metz",
    "sg:orig_category":"Non-Classified Establishments",
    "sg:phone":"+33 3 87 36 92 58",
    "sg:province":"Ile de France",
    "wof:name":"Allo Nettoyage S.a.r.l.",
    "wof:placetype":"venue"
},
  "geometry": {"coordinates":[6.162668,49.090263],"type":"Point"}
}