{
  "type": "Feature",
  "properties": {
    "addr:full":"Bonneuil Verrines sous Celles 79370 Celles sur Belle Poitou-Charentes",
    "addr:postcode":"79370",
    "addr:street":"Sous Celles;Belle",
    "iso:country":"FR",
    "sg:address":"Bonneuil Verrines sous Celles 79370 Celles sur Belle",
    "sg:orig_category":"Unclassifiable Establishments",
    "sg:phone":"+33 5 49 32 97 97",
    "sg:province":"Poitou-Charentes",
    "wof:name":"Bonmort S.a.",
    "wof:placetype":"venue"
},
  "geometry": {"coordinates":[-0.2398,46.24556],"type":"Point"}
}