{
  "type": "Feature",
  "properties": {
    "addr:full":"64 Bis Rue De Mon\u00e7eau 75008 Paris Ile de France 75008",
    "addr:housenumber":"64 bis",
    "addr:postcode":"75008;75008",
    "addr:street":"Rue De Monc\u0327Eau",
    "iso:country":"FR",
    "sg:address":"64 Bis Rue De Mon\u00e7eau 75008 Paris",
    "sg:classifiers":[
        {
            "category":"Banks & Credit Unions",
            "subcategory":"Financial Services",
            "type":"Services"
        }
    ],
    "sg:phone":"+33 1 40 76 85 00",
    "sg:postcode":"75008",
    "sg:province":"Ile de France",
    "sg:tags":[
        "banking",
        "finance",
        "insurance"
    ],
    "wof:name":"Groupe Vezelay",
    "wof:placetype":"venue"
},
  "geometry": {"coordinates":[2.313229,48.87875],"type":"Point"}
}