{
  "type": "Feature",
  "properties": {
    "iso:country":"FR",
    "sg:address":"B.P. 136, 74303 Cluses C\u00e9dex^^65, Av. d'Italie, 74300 Cluses",
    "sg:orig_category":"Non-Classified Establishments",
    "sg:phone":"+33 4 50 98 88 00",
    "sg:postcode":"74300",
    "sg:province":"Rhone-Alpes",
    "wof:name":"Dexa S.a.",
    "wof:placetype":"venue"
},
  "geometry": {"coordinates":[6.595942,46.048561],"type":"Point"}
}