{
  "type": "Feature",
  "properties": {
    "iso:country":"FR",
    "sg:address":"ZA les Tannes Basses 34800 CLERMONT L HERAULT",
    "sg:classifiers":[
        {
            "category":"Professional",
            "subcategory":"Printing & Photocopies",
            "type":"Services"
        }
    ],
    "sg:phone":"+33 4 67 96 01 78",
    "sg:province":"Languedoc-Roussillon",
    "sg:tags":[
        "offset"
    ],
    "wof:name":"Chalaguier S.a.",
    "wof:placetype":"venue"
},
  "geometry": {"coordinates":[3.43383,43.626785],"type":"Point"}
}