{
  "type": "Feature",
  "properties": {
    "iso:country":"FR",
    "sg:address":"Zone Industrielle",
    "sg:city":"Ottmarsheim",
    "sg:orig_category":"Unclassifiable Establishments",
    "sg:phone":"+33 3 89 83 20 62",
    "sg:postcode":"68490",
    "sg:province":"Alsace",
    "wof:name":"S.a.r. S.a. - Service Acier Rh\u00e9nan",
    "wof:placetype":"venue"
},
  "geometry": {"coordinates":[7.506465,47.78661],"type":"Point"}
}