{
  "type": "Feature",
  "properties": {
    "iso:country":"FR",
    "sg:address":"17, Rue de la Cornouaille, 44300 Nantes",
    "sg:orig_category":"Unclassifiable Establishments",
    "sg:phone":"+33 2 51 89 16 16",
    "sg:province":"Pays de Loire",
    "wof:name":"Danfoss S.a.r.l.",
    "wof:placetype":"venue"
},
  "geometry": {"coordinates":[-1.535923,47.242386],"type":"Point"}
}