{
  "type": "Feature",
  "properties": {
    "iso:country":"FR",
    "sg:address":"Acti Club B\u00e2timent E 13400 Aubagne",
    "sg:classifiers":[
        {
            "category":"Utilities",
            "subcategory":"Mobile Phone",
            "type":"Services"
        }
    ],
    "sg:phone":"+33 4 91 19 11 60",
    "sg:tags":[
        "telecommunication",
        "audio-visual"
    ],
    "wof:name":"Societe D'organisation De Faconnes Et De Transformes (soft) Mussetta",
    "wof:placetype":"venue"
},
  "geometry": {"coordinates":[5.5687,43.292141],"type":"Point"}
}