{
  "type": "Feature",
  "properties": {
    "iso:country":"FR",
    "sg:address":"2, Rue des Pionniers, 67120 Duttlenheim",
    "sg:city":"Duttlenheim",
    "sg:orig_category":"Non-Classified Establishments",
    "sg:phone":"+33 3 88 47 97 17",
    "sg:postcode":"67120",
    "sg:province":"Alsace",
    "wof:name":"J.p.e. Engel S.a.r.l.",
    "wof:placetype":"venue"
},
  "geometry": {"coordinates":[7.57313,48.540241],"type":"Point"}
}