{
  "type": "Feature",
  "properties": {
    "addr:full":"Avenue Jean Moulin 84500 Bollene Centre",
    "addr:postcode":"84500",
    "addr:street":"Avenue Jean Moulin;Bollene",
    "iso:country":"FR",
    "sg:address":"Avenue Jean Moulin 84500 Bollene",
    "sg:classifiers":[
        {
            "category":"Manufacturing",
            "subcategory":"Tools & Machinery",
            "type":"Manufacturing & Wholesale Goods"
        }
    ],
    "sg:phone":"+33 4 90 30 46 60",
    "sg:province":"Centre",
    "sg:tags":[
        "metallurgy",
        "metalworking"
    ],
    "wof:name":"Bricorama France",
    "wof:placetype":"venue"
},
  "geometry": {"coordinates":[4.752475,44.28928],"type":"Point"}
}