{
  "type": "Feature",
  "properties": {
    "addr:full":"Rue Du Poire Sur Vie 85190 AIZENAY Pays de Loire",
    "addr:postcode":"85190",
    "addr:street":"Rue Du Poire Sur Vie",
    "iso:country":"FR",
    "sg:address":"Rue Du Poire Sur Vie 85190 AIZENAY",
    "sg:orig_category":"Sheet Protectors",
    "sg:phone":"+33 2 51 45 51 45",
    "sg:province":"Pays de Loire",
    "wof:name":"Cougnaud S.a.",
    "wof:placetype":"venue"
},
  "geometry": {"coordinates":[-1.610729,46.676075],"type":"Point"}
}