{
  "type": "Feature",
  "properties": {
    "iso:country":"FR",
    "sg:address":"5 Z.A du Hillans 64990 St Pierre d'Irube",
    "sg:city":"Lahonce",
    "sg:classifiers":[
        {
            "category":"Manufacturing",
            "subcategory":"Glass & Minerals",
            "type":"Manufacturing & Wholesale Goods"
        }
    ],
    "sg:phone":"+33 5 59 44 29 40",
    "sg:postcode":"64990",
    "sg:province":"Aquitaine",
    "sg:tags":[
        "frame"
    ],
    "wof:name":"Globex Sa",
    "wof:placetype":"venue"
},
  "geometry": {"coordinates":[-1.44966,43.466114],"type":"Point"}
}