{
  "type": "Feature",
  "properties": {
    "addr:full":"10, Rue Colbert, 03400 Yzeure Yzeure Auvergne 03400",
    "addr:housenumber":"10",
    "addr:postcode":"03400;03400",
    "addr:street":"Rue Colbert",
    "iso:country":"FR",
    "sg:address":"10, Rue Colbert, 03400 Yzeure",
    "sg:city":"Yzeure",
    "sg:orig_category":"Unclassifiable Establishments",
    "sg:phone":"+33 4 70 48 21 60",
    "sg:postcode":"03400",
    "sg:province":"Auvergne",
    "wof:name":"Scacentre S.a.",
    "wof:placetype":"venue"
},
  "geometry": {"coordinates":[3.357431,46.542732],"type":"Point"}
}