{
  "type": "Feature",
  "properties": {
    "addr:full":"Zac Sanital Technoforum 86100 Ch\u00e2tellerault Poitou-Charentes 86100",
    "addr:postcode":"86100;86100",
    "addr:street":"Zac Sanital Technoforum",
    "iso:country":"FR",
    "sg:address":"Zac Sanital Technoforum 86100 Ch\u00e2tellerault",
    "sg:classifiers":[
        {
            "category":"Utilities",
            "subcategory":"Electric",
            "type":"Services"
        }
    ],
    "sg:phone":"+33 5 49 20 22 22",
    "sg:postcode":"86100",
    "sg:province":"Poitou-Charentes",
    "sg:tags":[
        "electricity",
        "raw",
        "energy",
        "material"
    ],
    "wof:name":"Clemessy",
    "wof:placetype":"venue"
},
  "geometry": {"coordinates":[0.54494,46.819901],"type":"Point"}
}