{
  "type": "Feature",
  "properties": {
    "iso:country":"FR",
    "sg:address":"Quai De La Cabaude 85100 Les Sables D Olonne",
    "sg:classifiers":[
        {
            "category":"Autos & Motor Vehicles",
            "subcategory":"Boat Sales",
            "type":"Retail Goods"
        }
    ],
    "sg:phone":"+33 2 51 23 86 43",
    "sg:postcode":"85100",
    "sg:province":"Pays de Loire",
    "sg:tags":[
        "equipment",
        "transport"
    ],
    "wof:name":"Sarl Littoral Maintenance 85",
    "wof:placetype":"venue"
},
  "geometry": {"coordinates":[-1.792039,46.497334],"type":"Point"}
}