{
  "type": "Feature",
  "properties": {
    "addr:full":"21, Rue Gustave Eiffel, 13010 Marseille Provence-Alpes-C\u00f4te d'Azur",
    "addr:housenumber":"21",
    "addr:postcode":"13010",
    "addr:street":"Rue Gustave Eiffel",
    "iso:country":"FR",
    "sg:address":"21, Rue Gustave Eiffel, 13010 Marseille",
    "sg:orig_category":"Unclassifiable Establishments",
    "sg:phone":"+33 4 91 79 78 28",
    "sg:province":"Provence-Alpes-C\u00f4te d'Azur",
    "wof:name":"S.p.a.p.a. S.a. - Soci\u00e9t\u00e9 De Pavage Et Des Asphaltes De Paris",
    "wof:placetype":"venue"
},
  "geometry": {"coordinates":[5.406299,43.274307],"type":"Point"}
}