{
  "type": "Feature",
  "properties": {
    "addr:full":"21, Rue Ren\u00e9 Froissard, 89100 Saint Martin du Tertre Villeroy Bourgogne 89100",
    "addr:housenumber":"21",
    "addr:postcode":"89100;89100",
    "addr:street":"Rue Rene\u0301 Froissard",
    "iso:country":"FR",
    "sg:address":"21, Rue Ren\u00e9 Froissard, 89100 Saint Martin du Tertre",
    "sg:city":"Villeroy",
    "sg:orig_category":"Non-Classified Establishments",
    "sg:phone":"+33 3 86 64 13 01",
    "sg:postcode":"89100",
    "sg:province":"Bourgogne",
    "wof:name":"Soci\u00e9t\u00e9 A.p.c.i. S.a.r.l.- Am\u00e9nagement Plafond Cloison Isolation",
    "wof:placetype":"venue"
},
  "geometry": {"coordinates":[3.262404,48.216927],"type":"Point"}
}