{
  "type": "Feature",
  "properties": {
    "addr:full":"B.P. 20, 13191 Marseille C\u00e9dex 20^^51, Bd Longchamp, 13020 Marseille Poitou-Charentes",
    "addr:housenumber":"20 ^ ^ 51",
    "addr:postcode":"13191;13020",
    "addr:street":"B.P. 20;Ce\u0301Dex;Bd Longchamp",
    "iso:country":"FR",
    "sg:address":"B.P. 20, 13191 Marseille C\u00e9dex 20^^51, Bd Longchamp, 13020 Marseille",
    "sg:orig_category":"Non-Classified Establishments",
    "sg:phone":"+33 4 91 95 90 23",
    "sg:province":"Poitou-Charentes",
    "wof:name":"S.i.c.t.i.a. S.a. - Soci\u00e9t\u00e9 Industrielle Et Commerciale Pour Le Trait",
    "wof:placetype":"venue"
},
  "geometry": {"coordinates":[5.38078,43.311352],"type":"Point"}
}