{
  "type": "Feature",
  "properties": {
    "addr:full":"34 RUE DE BRETAGNE 94550 Chevilly Larue Ile de France 94550",
    "addr:housenumber":"34",
    "addr:postcode":"94550;94550",
    "addr:street":"Rue De Bretagne",
    "iso:country":"FR",
    "sg:address":"34 RUE DE BRETAGNE 94550 Chevilly Larue",
    "sg:classifiers":[
        {
            "category":"Food & Beverages",
            "subcategory":"Fruits & Vegetables",
            "type":"Retail Goods"
        }
    ],
    "sg:phone":"+33 1 46 87 22 40",
    "sg:postcode":"94550",
    "sg:province":"Ile de France",
    "wof:name":"Primeurope Import & Export Sarl",
    "wof:placetype":"venue"
},
  "geometry": {"coordinates":[2.361862,48.774403],"type":"Point"}
}