{
  "type": "Feature",
  "properties": {
    "iso:country":"FR",
    "sg:address":"9 Av Matignon 75008 Paris",
    "sg:classifiers":[
        {
            "category":"Shopping",
            "subcategory":"Clothing, Apparel, & Fashions",
            "type":"Retail Goods"
        }
    ],
    "sg:phone":"+33 1 53 89 23 00",
    "sg:postcode":"75008",
    "sg:province":"Ile de France",
    "sg:tags":[
        "textile",
        "clothing",
        "clothes"
    ],
    "wof:name":"Gap France Sa",
    "wof:placetype":"venue"
},
  "geometry": {"coordinates":[2.311929,48.869961],"type":"Point"}
}