{
  "type": "Feature",
  "properties": {
    "iso:country":"FR",
    "sg:address":"80",
    "sg:city":"Saint Exup\u00e9ry; Montbonnot-Saint-Martin; F-38330",
    "sg:classifiers":[
        {
            "category":"Industrial Area",
            "type":"Public Place"
        }
    ],
    "sg:phone":"+33 4 76 04 37 00",
    "sg:province":"Rhone-Alpes",
    "sg:tags":[
        "large",
        "private"
    ],
    "wof:name":"Volubill Sa",
    "wof:placetype":"venue"
},
  "geometry": {"coordinates":[5.807172,45.219383],"type":"Point"}
}