{
  "type": "Feature",
  "properties": {
    "addr:full":"40, Rue de l'Intendance, 33000 Bordeaux Bordeaux Aquitaine 33000",
    "addr:housenumber":"40",
    "addr:postcode":"33000;33000",
    "addr:street":"Rue De L'Intendance",
    "iso:country":"FR",
    "sg:address":"40, Rue de l'Intendance, 33000 Bordeaux",
    "sg:city":"Bordeaux",
    "sg:orig_category":"Unclassifiable Establishments",
    "sg:phone":"+33 5 56 51 36 93",
    "sg:postcode":"33000",
    "sg:province":"Aquitaine",
    "wof:name":"Club Inter Entreprises S.a.r.l.",
    "wof:placetype":"venue"
},
  "geometry": {"coordinates":[-0.577846,44.842014],"type":"Point"}
}