{
  "type": "Feature",
  "properties": {
    "iso:country":"FR",
    "sg:address":"37, Av. Grand Cl\u00e9ment, 69120 Vaulx en Velin",
    "sg:orig_category":"Unclassifiable Establishments",
    "sg:phone":"+33 4 78 79 22 66",
    "sg:province":"Rhone-Alpes",
    "wof:name":"C.l.a. E.u.r.l. - Compagnie Lyonnaise D'aluminium",
    "wof:placetype":"venue"
},
  "geometry": {"coordinates":[4.910933,45.769493],"type":"Point"}
}