{
  "type": "Feature",
  "properties": {
    "iso:country":"FR",
    "sg:address":"3, Rue des Avoiries - ZA, 22100 Saint Samson sur Rance",
    "sg:city":"Dinan",
    "sg:orig_category":"Unclassifiable Establishments",
    "sg:phone":"+33 2 96 87 60 60",
    "sg:postcode":"22100",
    "sg:province":"Bretagne",
    "wof:name":"Brake France Service S.a.s.",
    "wof:placetype":"venue"
},
  "geometry": {"coordinates":[-2.064859,48.390835],"type":"Point"}
}