{
  "type": "Feature",
  "properties": {
    "addr:full":"55, Av. de Paris, 86530 Naintr\u00e9 Poitou-Charentes",
    "addr:postcode":"86530",
    "addr:street":"55 Av. De Paris",
    "iso:country":"FR",
    "sg:address":"55, Av. de Paris, 86530 Naintr\u00e9",
    "sg:orig_category":"Non-Classified Establishments",
    "sg:phone":"+33 5 49 20 27 27",
    "sg:province":"Poitou-Charentes",
    "wof:name":"S\u00e9ma Plus",
    "wof:placetype":"venue"
},
  "geometry": {"coordinates":[0.49987,46.766605],"type":"Point"}
}