{
  "type": "Feature",
  "properties": {
    "iso:country":"FR",
    "sg:address":"ZA le Vernet",
    "sg:city":"Vertolaye",
    "sg:orig_category":"Non-Classified Establishments",
    "sg:phone":"+33 4 73 95 27 37",
    "sg:postcode":"63480",
    "sg:province":"Auvergne",
    "wof:name":"Blix S.a.r.l.",
    "wof:placetype":"venue"
},
  "geometry": {"coordinates":[3.710925,45.650814],"type":"Point"}
}