{
  "type": "Feature",
  "properties": {
    "addr:full":"B.P. 312, 80003 Amiens C\u00e9dex^^Rue de Poulainville - Zone Industrielle, 80000 Amiens Picardie 80000",
    "addr:housenumber":"b.p. 312",
    "addr:postcode":"80003;80000;80000",
    "addr:street":"Zone Industrielle",
    "iso:country":"FR",
    "sg:address":"B.P. 312, 80003 Amiens C\u00e9dex^^Rue de Poulainville - Zone Industrielle, 80000 Amiens",
    "sg:orig_category":"Non-Classified Establishments",
    "sg:phone":"+33 3 22 43 76 22",
    "sg:postcode":"80000",
    "sg:province":"Picardie",
    "wof:name":"C.g.e. Distribution S.a.",
    "wof:placetype":"venue"
},
  "geometry": {"coordinates":[2.293165,49.894733],"type":"Point"}
}