{
  "type": "Feature",
  "properties": {
    "iso:country":"FR",
    "sg:address":"83 Rue Fran\u00e7ois Appert 62200 Boulogne Sur Mer",
    "sg:classifiers":[
        {
            "category":"Manufacturing",
            "subcategory":"Metals",
            "type":"Manufacturing & Wholesale Goods"
        }
    ],
    "sg:phone":"+33 3 21 83 86 66",
    "sg:postcode":"62200",
    "sg:province":"Nord Pas-de-Calais",
    "sg:tags":[
        "-",
        "machine",
        "equipment",
        "engineering",
        "machinery",
        "mechanical"
    ],
    "wof:name":"Kayac Sa",
    "wof:placetype":"venue"
},
  "geometry": {"coordinates":[1.615514,50.727444],"type":"Point"}
}