{
  "type": "Feature",
  "properties": {
    "iso:country":"FR",
    "sg:address":"23, Rue Jean Jaur\u00e8s, 59800 Lille",
    "sg:orig_category":"Non-Classified Establishments",
    "sg:phone":"+33 3 20 52 10 10",
    "sg:postcode":"59800",
    "sg:province":"Nord Pas-de-Calais",
    "wof:name":"2.d. Signal\u00e9tique S.a.r.l.",
    "wof:placetype":"venue"
},
  "geometry": {"coordinates":[3.018311,50.636597],"type":"Point"}
}