{
  "type": "Feature",
  "properties": {
    "iso:country":"FR",
    "sg:address":"La Vern\u00e8de 30390 Aramon",
    "sg:orig_category":"Unclassifiable Establishments",
    "sg:phone":"+33 4 66 57 49 87",
    "sg:province":"Languedoc-Roussillon",
    "wof:name":"Rijk Zwaan France S.a.r.l.",
    "wof:placetype":"venue"
},
  "geometry": {"coordinates":[4.67997,43.891102],"type":"Point"}
}