{
  "type": "Feature",
  "properties": {
    "iso:country":"FR",
    "sg:address":"Rue Newton BP 3000 17030 La Rochelle",
    "sg:city":"La Rochelle",
    "sg:classifiers":[
        {
            "category":"Professional",
            "subcategory":"Printing & Photocopies",
            "type":"Services"
        }
    ],
    "sg:phone":"+33 5 46 34 77 88",
    "sg:postcode":"17000",
    "sg:province":"Poitou-Charentes",
    "sg:tags":[
        "publishing"
    ],
    "wof:name":"Editions Rupella Sarl",
    "wof:placetype":"venue"
},
  "geometry": {"coordinates":[-1.15283,46.161812],"type":"Point"}
}