{
  "type": "Feature",
  "properties": {
    "iso:country":"FR",
    "sg:address":"6 Rue Du Louis D'Or",
    "sg:city":"Rennes",
    "sg:classifiers":[
        {
            "category":"Banks & Credit Unions",
            "subcategory":"Financial Services",
            "type":"Services"
        }
    ],
    "sg:phone":"+33 2 99 67 93 62",
    "sg:postcode":"35000",
    "sg:province":"Bretagne",
    "sg:tags":[
        "banking",
        "finance",
        "insurance"
    ],
    "wof:name":"Comptafrance",
    "wof:placetype":"venue"
},
  "geometry": {"coordinates":[-1.686993,48.113674],"type":"Point"}
}