{
  "type": "Feature",
  "properties": {
    "addr:full":"Le Porchon 42480 La Fouillouse Rhone-Alpes",
    "addr:postcode":"42480",
    "iso:country":"FR",
    "sg:address":"Le Porchon 42480 La Fouillouse",
    "sg:orig_category":"Unclassifiable Establishments",
    "sg:phone":"+33 4 77 92 27 57",
    "sg:province":"Rhone-Alpes",
    "wof:name":"Etablissements Jean Eychenn\u00e9 S.a.",
    "wof:placetype":"venue"
},
  "geometry": {"coordinates":[4.341327,45.484085],"type":"Point"}
}