{
  "type": "Feature",
  "properties": {
    "addr:full":"1, Place Occitan - Le Sully, 31000 Toulouse Midi Pyr\u00e9n\u00e9es",
    "addr:housenumber":"1",
    "addr:postcode":"31000",
    "addr:street":"Place Occitan Le Sully",
    "iso:country":"FR",
    "sg:address":"1, Place Occitan - Le Sully, 31000 Toulouse",
    "sg:orig_category":"Unclassifiable Establishments",
    "sg:phone":"+33 5 61 00 31 61",
    "sg:province":"Midi Pyr\u00e9n\u00e9es",
    "wof:name":"Control Data France S.a.",
    "wof:placetype":"venue"
},
  "geometry": {"coordinates":[1.44869,43.60574],"type":"Point"}
}