{
  "type": "Feature",
  "properties": {
    "addr:full":"130 Rue D'Antibes 06400 Cannes Picardie",
    "addr:housenumber":"130",
    "addr:postcode":"06400",
    "addr:street":"Rue D'Antibes",
    "iso:country":"FR",
    "sg:address":"130 Rue D'Antibes 06400 Cannes",
    "sg:classifiers":[
        {
            "category":"Banks & Credit Unions",
            "subcategory":"Financial Services",
            "type":"Services"
        }
    ],
    "sg:phone":"+33 4 93 99 45 45",
    "sg:province":"Picardie",
    "sg:tags":[
        "banking",
        "insurance",
        "institution",
        "finance"
    ],
    "wof:name":"Danske Bank International Sa",
    "wof:placetype":"venue"
},
  "geometry": {"coordinates":[7.019693,43.552658],"type":"Point"}
}