{
  "type": "Feature",
  "properties": {
    "addr:full":"87, Av de la Victoire, 02480 Jussy Picardie",
    "addr:postcode":"02480",
    "addr:street":"87 Av De La Victoire",
    "iso:country":"FR",
    "sg:address":"87, Av de la Victoire, 02480 Jussy",
    "sg:orig_category":"Non-Classified Establishments",
    "sg:phone":"+33 3 23 63 58 00",
    "sg:province":"Picardie",
    "wof:name":"Lu P\u00e2tisserie S.a.",
    "wof:placetype":"venue"
},
  "geometry": {"coordinates":[3.24539,49.73362],"type":"Point"}
}