{
  "type": "Feature",
  "properties": {
    "iso:country":"FR",
    "sg:address":"route de Noves 84310 Morieres Les Avignon",
    "sg:classifiers":[
        {
            "category":"Shopping",
            "subcategory":"Computers & Home Electronics",
            "type":"Retail Goods"
        }
    ],
    "sg:phone":"+33 4 90 33 40 40",
    "sg:province":"Provence-Alpes-C\u00f4te d'Azur",
    "sg:tags":[
        "industrial",
        "power"
    ],
    "wof:name":"S.p.e.c. Sa",
    "wof:placetype":"venue"
},
  "geometry": {"coordinates":[4.906263,43.931175],"type":"Point"}
}