{
  "type": "Feature",
  "properties": {
    "addr:full":"22, Rue de l'Ouche Buron, 44300 Nantes Pays de Loire",
    "addr:housenumber":"22",
    "addr:postcode":"44300",
    "addr:street":"Rue De L'Ouche Buron",
    "iso:country":"FR",
    "sg:address":"22, Rue de l'Ouche Buron, 44300 Nantes",
    "sg:orig_category":"Unclassifiable Establishments",
    "sg:phone":"+33 2 51 13 21 51",
    "sg:province":"Pays de Loire",
    "wof:name":"A.f.p.t Atlantique S.a.",
    "wof:placetype":"venue"
},
  "geometry": {"coordinates":[-1.5359,47.25631],"type":"Point"}
}