{
  "type": "Feature",
  "properties": {
    "iso:country":"FR",
    "sg:address":"157-159 Rte De Doullens 80100 Abbeville",
    "sg:classifiers":[
        {
            "category":"Shopping",
            "type":"Retail Goods"
        }
    ],
    "sg:phone":"+33 3 22 25 44 00",
    "sg:postcode":"80100",
    "sg:province":"Picardie",
    "sg:tags":[
        "metallurgy",
        "finished",
        "-",
        "metalworking",
        "metallic"
    ],
    "wof:name":"Valeo Securite Habitacle",
    "wof:placetype":"venue"
},
  "geometry": {"coordinates":[1.858631,50.109352],"type":"Point"}
}