{
  "type": "Feature",
  "properties": {
    "addr:full":"63 Rue De L'Ile Napol\u00e9on 68170 Rixheim Rixheim Alsace 68170",
    "addr:housenumber":"63",
    "addr:postcode":"68170;68170",
    "addr:street":"Rue De L'Ile Napole\u0301On;Rixheim",
    "iso:country":"FR",
    "sg:address":"63 Rue De L'Ile Napol\u00e9on 68170 Rixheim",
    "sg:city":"Rixheim",
    "sg:classifiers":[
        {
            "category":"Banks & Credit Unions",
            "subcategory":"Investment Brokerage",
            "type":"Services"
        }
    ],
    "sg:phone":"+33 3 89 44 47 48",
    "sg:postcode":"68170",
    "sg:province":"Alsace",
    "sg:tags":[
        "-",
        "transport",
        "related"
    ],
    "wof:name":"Sateg Sa",
    "wof:placetype":"venue"
},
  "geometry": {"coordinates":[7.407369,47.750523],"type":"Point"}
}