{
  "type": "Feature",
  "properties": {
    "addr:full":"Route De Guise 02100 Harly Picardie 02100",
    "addr:postcode":"02100;02100",
    "addr:street":"Route De Guise;Picardie",
    "iso:country":"FR",
    "sg:address":"Route De Guise 02100 Harly",
    "sg:classifiers":[
        {
            "category":"Wholesale",
            "subcategory":"Farm Supplies",
            "type":"Manufacturing & Wholesale Goods"
        }
    ],
    "sg:phone":"+33 3 23 50 31 10",
    "sg:postcode":"02100",
    "sg:province":"Picardie",
    "sg:tags":[
        "-",
        "machine",
        "equipment",
        "engineering",
        "machinery",
        "mechanical",
        "agriculture"
    ],
    "wof:name":"Etablissements Lefevre Et Fils",
    "wof:placetype":"venue"
},
  "geometry": {"coordinates":[3.347185,49.844204],"type":"Point"}
}