{
  "type": "Feature",
  "properties": {
    "addr:full":"Ch\u00e2teau De Gilly 21640 Gilly Les Citeaux Flagey-Ech\u00e9zeaux Bourgogne 21640",
    "addr:postcode":"21640;21640",
    "iso:country":"FR",
    "sg:address":"Ch\u00e2teau De Gilly 21640 Gilly Les Citeaux",
    "sg:city":"Flagey-Ech\u00e9zeaux",
    "sg:classifiers":[
        {
            "category":"Travel",
            "subcategory":"Hotels & Motels",
            "type":"Entertainment"
        }
    ],
    "sg:phone":"+33 3 80 62 89 98",
    "sg:postcode":"21640",
    "sg:province":"Bourgogne",
    "sg:tags":[
        "hotels",
        "business",
        "restaurant"
    ],
    "wof:name":"Chateau De Gilly",
    "wof:placetype":"venue"
},
  "geometry": {"coordinates":[4.985598,47.171673],"type":"Point"}
}