{
  "type": "Feature",
  "properties": {
    "addr:full":"Voie Romaine Maizi\u00e8res l\u00e8s Metz Lorraine 57280",
    "addr:postcode":"57280",
    "addr:street":"Voie Romaine",
    "iso:country":"FR",
    "sg:address":"Voie Romaine",
    "sg:city":"Maizi\u00e8res l\u00e8s Metz",
    "sg:orig_category":"Unclassifiable Establishments",
    "sg:phone":"+33 3 87 70 40 00",
    "sg:postcode":"57280",
    "sg:province":"Lorraine",
    "wof:name":"I.r.s.i.d. S.a. - Institut De Recherches De La Sid\u00e9rurgie Fran\u00e7aise",
    "wof:placetype":"venue"
},
  "geometry": {"coordinates":[6.14834,49.209595],"type":"Point"}
}