{
  "type": "Feature",
  "properties": {
    "addr:full":"B.P. 2538, 68058 Mulhouse C\u00e9dex^^16, Rue de Hirtzbach, 68200 Mulhouse Mulhouse Alsace 68200",
    "addr:housenumber":"2538",
    "addr:postcode":"68058;68200;mulhouse;68200",
    "addr:street":"B.P.;Rue De Hirtzbach",
    "iso:country":"FR",
    "sg:address":"B.P. 2538, 68058 Mulhouse C\u00e9dex^^16, Rue de Hirtzbach, 68200 Mulhouse",
    "sg:city":"Mulhouse",
    "sg:orig_category":"Non-Classified Establishments",
    "sg:phone":"+33 3 89 59 67 50",
    "sg:postcode":"68200",
    "sg:province":"Alsace",
    "wof:name":"Lesage Pr\u00e9fabrication S.a.",
    "wof:placetype":"venue"
},
  "geometry": {"coordinates":[7.31201,47.75547],"type":"Point"}
}