{
  "type": "Feature",
  "properties": {
    "addr:full":"9, Rue des Cigognes, 67140 Barr Barr Alsace 67140",
    "addr:housenumber":"9",
    "addr:postcode":"67140;67140",
    "addr:street":"Rue Des Cigognes;Barr",
    "iso:country":"FR",
    "sg:address":"9, Rue des Cigognes, 67140 Barr",
    "sg:city":"Barr",
    "sg:orig_category":"Non-Classified Establishments",
    "sg:phone":"+33 3 88 58 52 40",
    "sg:postcode":"67140",
    "sg:province":"Alsace",
    "wof:name":"Simplast S.a.r.l.",
    "wof:placetype":"venue"
},
  "geometry": {"coordinates":[7.451191,48.408234],"type":"Point"}
}