{
  "type": "Feature",
  "properties": {
    "addr:full":"25\u00e0 29 rue du Cuivre 77176 Savigny le Temple Ile de France 77176",
    "addr:housenumber":"29",
    "addr:postcode":"77176;77176",
    "addr:street":"25A\u0300;Rue Du Cuivre;Ile;France",
    "iso:country":"FR",
    "sg:address":"25\u00e0 29 rue du Cuivre 77176 Savigny le Temple",
    "sg:orig_category":"Cable Printing Rollers",
    "sg:phone":"+33 1 64 10 50 50",
    "sg:postcode":"77176",
    "sg:province":"Ile de France",
    "wof:name":"B\u00f6ttcher France Sarl",
    "wof:placetype":"venue"
},
  "geometry": {"coordinates":[2.591134,48.589397],"type":"Point"}
}