{
  "type": "Feature",
  "properties": {
    "iso:country":"FR",
    "sg:address":"Place Eglise",
    "sg:city":"Fleurie",
    "sg:classifiers":[
        {
            "category":"Banks & Credit Unions",
            "subcategory":"Financial Services",
            "type":"Services"
        }
    ],
    "sg:phone":"+33 4 74 04 17 70",
    "sg:postcode":"69820",
    "sg:province":"Rhone-Alpes",
    "sg:tags":[
        "banking",
        "finance",
        "insurance"
    ],
    "wof:name":"Centre De Gestion Agri Bilan Conseil",
    "wof:placetype":"venue"
},
  "geometry": {"coordinates":[4.696968,46.192356],"type":"Point"}
}