{
  "type": "Feature",
  "properties": {
    "addr:full":"80 Rue Des Prussiens 88410 Monthureux-Sur-Sa\u00f4ne Lorraine",
    "addr:housenumber":"80",
    "addr:postcode":"88410",
    "addr:street":"Rue Des Prussiens",
    "iso:country":"FR",
    "sg:address":"80 Rue Des Prussiens 88410 Monthureux-Sur-Sa\u00f4ne",
    "sg:classifiers":[
        {
            "category":"Home & Garden",
            "subcategory":"Furniture",
            "type":"Retail Goods"
        }
    ],
    "sg:phone":"+33 3 29 09 91 24",
    "sg:province":"Lorraine",
    "sg:tags":[
        "wood"
    ],
    "wof:name":"Merrain Internatonal Sarl",
    "wof:placetype":"venue"
},
  "geometry": {"coordinates":[5.985742,48.03331],"type":"Point"}
}