{
  "type": "Feature",
  "properties": {
    "addr:full":"33/39, Bd Robert Schuman, 93190 Livry Gargan Ile de France",
    "addr:housenumber":"33 / 39",
    "addr:postcode":"93190",
    "addr:street":"Bd Robert Schuman",
    "iso:country":"FR",
    "sg:address":"33/39, Bd Robert Schuman, 93190 Livry Gargan",
    "sg:orig_category":"Non-Classified Establishments",
    "sg:phone":"+33 1 49 36 90 00",
    "sg:province":"Ile de France",
    "wof:name":"Pro Consultant Greyf's S.a.",
    "wof:placetype":"venue"
},
  "geometry": {"coordinates":[2.549224,48.928261],"type":"Point"}
}