{
  "type": "Feature",
  "properties": {
    "addr:full":"1 Goyaux 33860 Reignac Reignac Aquitaine 33860",
    "addr:housenumber":"1",
    "addr:postcode":"33860;33860",
    "addr:street":"Goyaux",
    "iso:country":"FR",
    "sg:address":"1 Goyaux 33860 Reignac",
    "sg:city":"Reignac",
    "sg:classifiers":[
        {
            "category":"Professional",
            "type":"Services"
        }
    ],
    "sg:phone":"+33 5 57 32 43 92",
    "sg:postcode":"33860",
    "sg:province":"Aquitaine",
    "sg:tags":[
        "transport",
        "road"
    ],
    "wof:name":"Transports Chiche Sarl",
    "wof:placetype":"venue"
},
  "geometry": {"coordinates":[-0.507802,45.233929],"type":"Point"}
}