{
  "type": "Feature",
  "properties": {
    "iso:country":"FR",
    "sg:address":"10, Impasse du Grand Jardin - ZAC de la Moinerie, 35400 Saint Malo",
    "sg:city":"Saint-Malo",
    "sg:orig_category":"Unclassifiable Establishments",
    "sg:phone":"+33 2 99 19 98 98",
    "sg:postcode":"35400",
    "sg:province":"Bretagne",
    "wof:name":"Cache Cache S.a.",
    "wof:placetype":"venue"
},
  "geometry": {"coordinates":[-2.003669,48.604897],"type":"Point"}
}