{
  "type": "Feature",
  "properties": {
    "iso:country":"FR",
    "sg:address":"21, Av. Germaine, 59110 La Madeleine",
    "sg:orig_category":"Non-Classified Establishments",
    "sg:phone":"+33 3 20 55 89 69",
    "sg:province":"Nord Pas-de-Calais",
    "wof:name":"Shogun S.a.r.l.",
    "wof:placetype":"venue"
},
  "geometry": {"coordinates":[3.075093,50.647484],"type":"Point"}
}