{
  "type": "Feature",
  "properties": {
    "iso:country":"FR",
    "sg:address":"B.P. 2, 92315 S\u00e8vres C\u00e9dex^^5, Rue Carles Vernet, 92310 S\u00e8vres",
    "sg:orig_category":"Non-Classified Establishments",
    "sg:phone":"+33 1 46 23 79 00",
    "sg:postcode":"92310",
    "sg:province":"Ile de France",
    "wof:name":"A2m",
    "wof:placetype":"venue"
},
  "geometry": {"coordinates":[2.212127,48.824337],"type":"Point"}
}