{
  "type": "Feature",
  "properties": {
    "iso:country":"FR",
    "sg:address":"24, Rue du G\u00e9n\u00e9ral de Rascas, 57220 Boulay Moselle",
    "sg:orig_category":"Unclassifiable Establishments",
    "sg:phone":"+33 3 87 57 43 44",
    "sg:province":"Lorraine",
    "wof:name":"M\u00e9tallit S.a.r.l.",
    "wof:placetype":"venue"
},
  "geometry": {"coordinates":[6.4788,49.180439],"type":"Point"}
}