{
  "type": "Feature",
  "properties": {
    "iso:country":"FR",
    "sg:address":"Rue Weber Prolong\u00e9e",
    "sg:city":"Troyes",
    "sg:orig_category":"Unclassifiable Establishments",
    "sg:phone":"+33 3 25 76 24 00",
    "sg:postcode":"10000",
    "sg:province":"Champagne",
    "wof:name":"Appia S.a.",
    "wof:placetype":"venue"
},
  "geometry": {"coordinates":[4.091796,48.295872],"type":"Point"}
}