{
  "type": "Feature",
  "properties": {
    "addr:full":"B.P. 143, 71306 Montceau les Mines C\u00e9dex^^ZA Sainte Elisabeth, 71300 Montceau les Mines Saint-Berain-sous-Sanvignes Bourgogne 71300",
    "addr:housenumber":"b.p. 143",
    "addr:postcode":"71306;71300;71300",
    "addr:street":"Sainte Elisabeth;Bourgogne",
    "iso:country":"FR",
    "sg:address":"B.P. 143, 71306 Montceau les Mines C\u00e9dex^^ZA Sainte Elisabeth, 71300 Montceau les Mines",
    "sg:city":"Saint-Berain-sous-Sanvignes",
    "sg:orig_category":"Non-Classified Establishments",
    "sg:phone":"+33 3 85 69 04 40",
    "sg:postcode":"71300",
    "sg:province":"Bourgogne",
    "wof:name":"S.i.a.p. R\u00e9servoirs S.a.",
    "wof:placetype":"venue"
},
  "geometry": {"coordinates":[4.366535,46.690456],"type":"Point"}
}