{
  "type": "Feature",
  "properties": {
    "addr:full":"15, Rue Pierre S\u00e9mard, 69700 Givors Rhone-Alpes 69700",
    "addr:housenumber":"15",
    "addr:postcode":"69700;69700",
    "addr:street":"Rue Pierre Se\u0301Mard",
    "iso:country":"FR",
    "sg:address":"15, Rue Pierre S\u00e9mard, 69700 Givors",
    "sg:orig_category":"Unclassifiable Establishments",
    "sg:phone":"+33 4 72 49 21 30",
    "sg:postcode":"69700",
    "sg:province":"Rhone-Alpes",
    "wof:name":"Cl\u00e9men\u00e7on S.a.r.l.",
    "wof:placetype":"venue"
},
  "geometry": {"coordinates":[4.768428,45.585445],"type":"Point"}
}