{
  "type": "Feature",
  "properties": {
    "iso:country":"FR",
    "sg:address":"1 Quai Herve Rielle; Le Croisic",
    "sg:city":"Le Croisic",
    "sg:classifiers":[
        {
            "category":"Banks & Credit Unions",
            "subcategory":"Bank",
            "type":"Services"
        }
    ],
    "sg:phone":"+33 3340230252",
    "sg:postcode":"44490",
    "sg:province":"Pays de Loire",
    "wof:name":"Cr\u00e9dit Lyonnais",
    "wof:placetype":"venue"
},
  "geometry": {"coordinates":[-2.508933,47.292583],"type":"Point"}
}