{
  "type": "Feature",
  "properties": {
    "addr:full":"ZONE INDUSTRIELLE Reichstett Alsace 67116",
    "addr:postcode":"67116",
    "addr:street":"Zone Industrielle",
    "iso:country":"FR",
    "sg:address":"ZONE INDUSTRIELLE",
    "sg:city":"Reichstett",
    "sg:classifiers":[
        {
            "category":"Transit Center",
            "subcategory":"Freight",
            "type":"Transportation"
        }
    ],
    "sg:phone":"+33 3 88 18 19 20",
    "sg:postcode":"67116",
    "sg:province":"Alsace",
    "sg:tags":[
        "metallurgy",
        "pipe",
        "metalworking",
        "sheet"
    ],
    "wof:name":"Mat-hydro",
    "wof:placetype":"venue"
},
  "geometry": {"coordinates":[7.763275,48.644394],"type":"Point"}
}