{
  "type": "Feature",
  "properties": {
    "addr:full":"16, Rue du Mouzon - ZI Champ le Boeuf, 54520 Laxou Lorraine",
    "addr:housenumber":"16",
    "addr:postcode":"54520",
    "addr:street":"Rue Du Mouzon Zi Champ Le Boeuf",
    "iso:country":"FR",
    "sg:address":"16, Rue du Mouzon - ZI Champ le Boeuf, 54520 Laxou",
    "sg:orig_category":"Unclassifiable Establishments",
    "sg:phone":"+33 3 83 98 41 41",
    "sg:province":"Lorraine",
    "wof:name":"Via Location France Provinces S.a.",
    "wof:placetype":"venue"
},
  "geometry": {"coordinates":[6.15226,48.68528],"type":"Point"}
}