{
  "type": "Feature",
  "properties": {
    "iso:country":"FR",
    "sg:address":"9 Avenue Jean Pierre Timbaud 78190 Trappes",
    "sg:classifiers":[
        {
            "category":"Autos & Motor Vehicles",
            "subcategory":"Automobile Sales",
            "type":"Retail Goods"
        }
    ],
    "sg:phone":"+33 1 30 13 95 95",
    "sg:postcode":"78190",
    "sg:province":"Ile de France",
    "sg:tags":[
        "equipment",
        "industrial",
        "transport"
    ],
    "wof:name":"Garage Ares Mercedes Sarl",
    "wof:placetype":"venue"
},
  "geometry": {"coordinates":[1.972404,48.783642],"type":"Point"}
}