{
  "type": "Feature",
  "properties": {
    "iso:country":"FR",
    "sg:address":"La Boige",
    "sg:city":"Moulin Neuf",
    "sg:orig_category":"Unclassifiable Establishments",
    "sg:phone":"+33 5 53 80 84 85",
    "sg:postcode":"24700",
    "sg:province":"Aquitaine",
    "wof:name":"S.i.n.p.a. S.a.",
    "wof:placetype":"venue"
},
  "geometry": {"coordinates":[0.052366,45.009632],"type":"Point"}
}