{
  "type": "Feature",
  "properties": {
    "iso:country":"FR",
    "sg:address":"73, Rue Prunier, 33000 Bordeaux",
    "sg:city":"Bordeaux",
    "sg:orig_category":"Unclassifiable Establishments",
    "sg:phone":"+33 5 56 39 43 76",
    "sg:postcode":"33000",
    "sg:province":"Aquitaine",
    "wof:name":"Plastiluz",
    "wof:placetype":"venue"
},
  "geometry": {"coordinates":[-0.57281,44.859016],"type":"Point"}
}