{
  "type": "Feature",
  "properties": {
    "addr:full":"Gouillasse 33430 Le Nizan Le Nizan Aquitaine 33430",
    "addr:housenumber":"nizan;nizan",
    "addr:postcode":"33430;33430",
    "addr:street":"Gouillasse",
    "iso:country":"FR",
    "sg:address":"Gouillasse 33430 Le Nizan",
    "sg:city":"Le Nizan",
    "sg:orig_category":"Non-Classified Establishments",
    "sg:phone":"+33 5 56 25 09 55",
    "sg:postcode":"33430",
    "sg:province":"Aquitaine",
    "wof:name":"Soci\u00e9t\u00e9 Louis Sarraute Et Fils S.a.",
    "wof:placetype":"venue"
},
  "geometry": {"coordinates":[-0.254911,44.376896],"type":"Point"}
}