{
  "type": "Feature",
  "properties": {
    "addr:full":"B.P. 209, 87222 Feytiat C\u00e9dex^^Rue Marthe Dutheil - Parc d'Activit\u00e9s du Ponteix, 87220 Feytiat Limousin",
    "addr:housenumber":"b.p. 209",
    "addr:postcode":"87222;87220",
    "iso:country":"FR",
    "sg:address":"B.P. 209, 87222 Feytiat C\u00e9dex^^Rue Marthe Dutheil - Parc d'Activit\u00e9s du Ponteix, 87220 Feytiat",
    "sg:orig_category":"Non-Classified Establishments",
    "sg:phone":"+33 5 55 30 23 67",
    "sg:province":"Limousin",
    "wof:name":"J. M\u00e9rigous S.a.r.l.",
    "wof:placetype":"venue"
},
  "geometry": {"coordinates":[1.298609,45.807583],"type":"Point"}
}