{
  "type": "Feature",
  "properties": {
    "iso:country":"FR",
    "sg:address":"4 Rue Paul Emile Victor 80136 Rivery",
    "sg:classifiers":[
        {
            "category":"Autos & Motor Vehicles",
            "subcategory":"Automobile Sales",
            "type":"Retail Goods"
        }
    ],
    "sg:phone":"+33 3 22 70 27 00",
    "sg:postcode":"80136",
    "sg:province":"Picardie",
    "sg:tags":[
        "equipment",
        "motor-cars",
        "transport"
    ],
    "wof:name":"Sa Pruvost",
    "wof:placetype":"venue"
},
  "geometry": {"coordinates":[2.338111,49.914513],"type":"Point"}
}