{
  "type": "Feature",
  "properties": {
    "addr:full":"6 Av De La Lib\u00e9ration 42000 St Etienne Rhone-Alpes 42000",
    "addr:postcode":"42000;42000",
    "addr:street":"Av De La Libe\u0301Ration",
    "iso:country":"FR",
    "sg:address":"6 Av De La Lib\u00e9ration 42000 St Etienne",
    "sg:classifiers":[
        {
            "category":"Shopping",
            "subcategory":"Clothing, Apparel, & Fashions",
            "type":"Retail Goods"
        }
    ],
    "sg:phone":"+33 4 77 32 70 70",
    "sg:postcode":"42000",
    "sg:province":"Rhone-Alpes",
    "sg:tags":[
        "textile",
        "clothing",
        "clothes"
    ],
    "wof:name":"Tadduni Sa",
    "wof:placetype":"venue"
},
  "geometry": {"coordinates":[4.390122,45.436916],"type":"Point"}
}