{
  "type": "Feature",
  "properties": {
    "addr:full":"13, Av. Louis Renault, 44800 Saint Herblain Pays de Loire",
    "addr:postcode":"44800",
    "addr:street":"13 Av. Louis Renault;Herblain",
    "iso:country":"FR",
    "sg:address":"13, Av. Louis Renault, 44800 Saint Herblain",
    "sg:orig_category":"Unclassifiable Establishments",
    "sg:phone":"+33 2 40 63 06 13",
    "sg:province":"Pays de Loire",
    "wof:name":"Technal S.a.",
    "wof:placetype":"venue"
},
  "geometry": {"coordinates":[-1.645614,47.25687],"type":"Point"}
}