{
  "type": "Feature",
  "properties": {
    "iso:country":"FR",
    "sg:address":"18 Av Montmirail 02400 Nogentel",
    "sg:classifiers":[
        {
            "category":"Professional",
            "type":"Services"
        }
    ],
    "sg:phone":"+33 3 23 69 16 23",
    "sg:province":"Picardie",
    "sg:tags":[
        "transport",
        "road"
    ],
    "wof:name":"Entreprise Generale Des Transports Castel Bernard",
    "wof:placetype":"venue"
},
  "geometry": {"coordinates":[3.409375,49.027737],"type":"Point"}
}