{
  "type": "Feature",
  "properties": {
    "addr:full":"14, Rue du Clos Barrois, 60183 Nogent sur Oise C\u00e9dex Picardie",
    "addr:housenumber":"14",
    "addr:postcode":"60183",
    "addr:street":"Rue Du Clos Barrois",
    "iso:country":"FR",
    "sg:address":"14, Rue du Clos Barrois, 60183 Nogent sur Oise C\u00e9dex",
    "sg:orig_category":"Non-Classified Establishments",
    "sg:phone":"+33 3 44 55 36 82",
    "sg:province":"Picardie",
    "wof:name":"Eurand France S.a.",
    "wof:placetype":"venue"
},
  "geometry": {"coordinates":[2.48803,49.27327],"type":"Point"}
}