{
  "type": "Feature",
  "properties": {
    "iso:country":"FR",
    "sg:address":"Les Vallots 18410 Argent sur Sauldre",
    "sg:city":"Argent-sur-Sauldre",
    "sg:orig_category":"Unclassifiable Establishments",
    "sg:phone":"+33 2 48 73 33 07",
    "sg:postcode":"18410",
    "sg:province":"Centre",
    "wof:name":"Roby S.a.r.l.",
    "wof:placetype":"venue"
},
  "geometry": {"coordinates":[2.466235,47.555321],"type":"Point"}
}