{
  "type": "Feature",
  "properties": {
    "iso:country":"FR",
    "sg:address":"121, Rue Jules Fuzelier, 08700 Nouzonville",
    "sg:city":"Gespunsart",
    "sg:orig_category":"PI\u00c8CES DE M\u00c9CANIQUE DE PR\u00c9CISION SUR PLANS DANS LES DOMAINES FERROVIAIRE, AGRICULTURE, INDUSTRIEL Us",
    "sg:phone":"+33 3 24 52 89 00",
    "sg:postcode":"08700",
    "sg:province":"Champagne",
    "wof:name":"U.m.g.a. S.a.r.l. - Usinage M\u00e9canique G\u00e9n\u00e9rale Ardennaise",
    "wof:placetype":"venue"
},
  "geometry": {"coordinates":[4.747922,49.82296],"type":"Point"}
}