{
  "type": "Feature",
  "properties": {
    "addr:full":"12 Route Oye Et Pallet 25160 La Plan\u00e9e Franche Comt\u00e9",
    "addr:housenumber":"12",
    "addr:postcode":"25160",
    "addr:street":"Route Oye Et Pallet;Franche Comte\u0301",
    "iso:country":"FR",
    "sg:address":"12 Route Oye Et Pallet 25160 La Plan\u00e9e",
    "sg:classifiers":[
        {
            "category":"Manufacturing",
            "subcategory":"Wood Products",
            "type":"Manufacturing & Wholesale Goods"
        }
    ],
    "sg:phone":"+33 3 81 69 63 31",
    "sg:province":"Franche Comt\u00e9",
    "sg:tags":[
        "furniture"
    ],
    "wof:name":"Scierie Laresche Sarl",
    "wof:placetype":"venue"
},
  "geometry": {"coordinates":[6.2853,46.8433],"type":"Point"}
}