{
  "type": "Feature",
  "properties": {
    "iso:country":"FR",
    "sg:address":"23 R Des Veyettes BP 40727 35063 Rennes Cedex",
    "sg:classifiers":[
        {
            "category":"Manufacturing",
            "subcategory":"Printing",
            "type":"Manufacturing & Wholesale Goods"
        }
    ],
    "sg:phone":"+33 2 99 86 71 86",
    "sg:province":"Bretagne",
    "sg:tags":[
        "publishing"
    ],
    "wof:name":"Media Graphic",
    "wof:placetype":"venue"
},
  "geometry": {"coordinates":[-1.629703,48.096333],"type":"Point"}
}