{
  "type": "Feature",
  "properties": {
    "addr:full":"7, Rte de Joinville, 88350 Liffol le Grand Lorraine",
    "addr:housenumber":"7",
    "addr:postcode":"88350",
    "addr:street":"Rte De Joinville;Grand",
    "iso:country":"FR",
    "sg:address":"7, Rte de Joinville, 88350 Liffol le Grand",
    "sg:orig_category":"Unclassifiable Establishments",
    "sg:phone":"+33 3 29 06 62 40",
    "sg:province":"Lorraine",
    "wof:name":"Counot Blandin S.a.",
    "wof:placetype":"venue"
},
  "geometry": {"coordinates":[5.57056,48.326614],"type":"Point"}
}