{
  "type": "Feature",
  "properties": {
    "addr:full":"4, Rue Joseph Cugnot, 60000 Beauvais Picardie",
    "addr:housenumber":"4",
    "addr:postcode":"60000",
    "addr:street":"Rue Joseph Cugnot",
    "iso:country":"FR",
    "sg:address":"4, Rue Joseph Cugnot, 60000 Beauvais",
    "sg:orig_category":"Unclassifiable Establishments",
    "sg:phone":"+33 3 44 05 61 67",
    "sg:province":"Picardie",
    "wof:name":"Loxam S.a.",
    "wof:placetype":"venue"
},
  "geometry": {"coordinates":[2.117158,49.423183],"type":"Point"}
}