{
  "type": "Feature",
  "properties": {
    "iso:country":"FR",
    "sg:address":"Rue Gay Lussac 59494 Petite For\u00eat",
    "sg:classifiers":[
        {
            "category":"Travel",
            "subcategory":"Hotels & Motels",
            "type":"Entertainment"
        }
    ],
    "sg:phone":"+33 3 27 45 36 55",
    "sg:postcode":"59494",
    "sg:province":"Nord Pas-de-Calais",
    "sg:tags":[
        "hotels",
        "business",
        "restaurant"
    ],
    "wof:name":"Buffalo Grill",
    "wof:placetype":"venue"
},
  "geometry": {"coordinates":[3.472609,50.376865],"type":"Point"}
}