{
  "type": "Feature",
  "properties": {
    "addr:full":"B.P. 45, 25461 Etupes C\u00e9dex^^Technoland, 25460 Etupes Franche Comt\u00e9 25460",
    "addr:postcode":"25461;25460;25460",
    "addr:street":"B.P. 45;Ce\u0301Dex^^Technoland;Franche Comte\u0301",
    "iso:country":"FR",
    "sg:address":"B.P. 45, 25461 Etupes C\u00e9dex^^Technoland, 25460 Etupes",
    "sg:orig_category":"Non-Classified Establishments",
    "sg:phone":"+33 3 81 32 55 00",
    "sg:postcode":"25460",
    "sg:province":"Franche Comt\u00e9",
    "wof:name":"Delphi Packard Electric Systems S.a.",
    "wof:placetype":"venue"
},
  "geometry": {"coordinates":[6.862814,47.506931],"type":"Point"}
}