{
  "type": "Feature",
  "properties": {
    "addr:full":"11cit\u00e9 Louis Beguerie 64130 Maul\u00e9on Soule Ainharp Aquitaine 64130",
    "addr:postcode":"64130;64130",
    "iso:country":"FR",
    "sg:address":"11cit\u00e9 Louis Beguerie 64130 Maul\u00e9on Soule",
    "sg:city":"Ainharp",
    "sg:classifiers":[
        {
            "category":"Shopping",
            "subcategory":"Crafts & Fabrics",
            "type":"Retail Goods"
        }
    ],
    "sg:phone":"+33 5 59 28 11 91",
    "sg:postcode":"64130",
    "sg:province":"Aquitaine",
    "sg:tags":[
        "textile",
        "clothing"
    ],
    "wof:name":"Tissages Du Saison Sa",
    "wof:placetype":"venue"
},
  "geometry": {"coordinates":[-0.933393,43.148788],"type":"Point"}
}