{
  "type": "Feature",
  "properties": {
    "addr:full":"La Chandelle 36350 LUANT Luant Centre 36350",
    "addr:postcode":"36350;36350",
    "iso:country":"FR",
    "sg:address":"La Chandelle 36350 LUANT",
    "sg:city":"Luant",
    "sg:classifiers":[
        {
            "category":"Education",
            "subcategory":"School",
            "type":"Public Place"
        }
    ],
    "sg:phone":"+33 2 54 36 55 55",
    "sg:postcode":"36350",
    "sg:province":"Centre",
    "sg:tags":[
        "breeding",
        "livestock",
        "cattle"
    ],
    "wof:name":"Cooper Agricole Betail Viande De L Indre Coop.",
    "wof:placetype":"venue"
},
  "geometry": {"coordinates":[1.602196,46.735023],"type":"Point"}
}