{
  "type": "Feature",
  "properties": {
    "addr:full":"23 Voie Romaine 21110 Genlis Genlis Bourgogne 21110",
    "addr:housenumber":"23",
    "addr:postcode":"21110;21110",
    "addr:street":"Voie Romaine",
    "iso:country":"FR",
    "sg:address":"23 Voie Romaine 21110 Genlis",
    "sg:city":"Genlis",
    "sg:classifiers":[
        {
            "category":"Manufacturing",
            "subcategory":"Chemicals & Compounds",
            "type":"Manufacturing & Wholesale Goods"
        }
    ],
    "sg:phone":"+33 3 80 47 62 00",
    "sg:postcode":"21110",
    "sg:province":"Bourgogne",
    "sg:tags":[
        "pharmaceutical",
        "chemistry",
        "-",
        "by-product"
    ],
    "wof:name":"Euridep Sa",
    "wof:placetype":"venue"
},
  "geometry": {"coordinates":[5.22542,47.242451],"type":"Point"}
}