{
  "type": "Feature",
  "properties": {
    "addr:full":"1, All\u00e9e de la Providence, 86000 Poitiers Poitou-Charentes",
    "addr:housenumber":"1",
    "addr:postcode":"86000",
    "addr:street":"Alle\u0301E De La Providence",
    "iso:country":"FR",
    "sg:address":"1, All\u00e9e de la Providence, 86000 Poitiers",
    "sg:orig_category":"Unclassifiable Establishments",
    "sg:phone":"+33 5 49 45 20 20",
    "sg:province":"Poitou-Charentes",
    "wof:name":"Editions Chrysis S.a.",
    "wof:placetype":"venue"
},
  "geometry": {"coordinates":[0.3677,46.562851],"type":"Point"}
}