{
  "type": "Feature",
  "properties": {
    "addr:full":"22-24, Rue Bauer, 57600 Forbach Lorraine",
    "addr:housenumber":"22-24",
    "addr:postcode":"57600",
    "addr:street":"Rue Bauer",
    "iso:country":"FR",
    "sg:address":"22-24, Rue Bauer, 57600 Forbach",
    "sg:orig_category":"Unclassifiable Establishments",
    "sg:phone":"+33 3 87 88 41 95",
    "sg:province":"Lorraine",
    "wof:name":"Pibia Constructions S.a.r.l.",
    "wof:placetype":"venue"
},
  "geometry": {"coordinates":[6.896394,49.186989],"type":"Point"}
}