{
  "type": "Feature",
  "properties": {
    "addr:full":"18 Rue Andr\u00e9 Dupont Ccal Carrefour 30900 N\u00eemes Languedoc-Roussillon 30900",
    "addr:housenumber":"18",
    "addr:postcode":"30900;30900",
    "addr:street":"Rue Andre\u0301 Dupont Ccal",
    "iso:country":"FR",
    "sg:address":"18 Rue Andr\u00e9 Dupont Ccal Carrefour 30900 N\u00eemes",
    "sg:classifiers":[
        {
            "category":"Travel",
            "subcategory":"Hotels & Motels",
            "type":"Entertainment"
        }
    ],
    "sg:phone":"+33 4 66 38 15 52",
    "sg:postcode":"30900",
    "sg:province":"Languedoc-Roussillon",
    "sg:tags":[
        "hotels",
        "business",
        "restaurant"
    ],
    "wof:name":"Phenix Richelieu",
    "wof:placetype":"venue"
},
  "geometry": {"coordinates":[4.356115,43.830025],"type":"Point"}
}