{
  "type": "Feature",
  "properties": {
    "iso:country":"FR",
    "sg:address":"Rte de Vandi\u00e8res",
    "sg:city":"Pont \u00e0 Mousson",
    "sg:orig_category":"Non-Classified Establishments",
    "sg:phone":"+33 3 83 81 21 16",
    "sg:postcode":"54700",
    "sg:province":"Lorraine",
    "wof:name":"Real 54 S.a.r.l.",
    "wof:placetype":"venue"
},
  "geometry": {"coordinates":[6.039221,48.91951],"type":"Point"}
}