{
  "type": "Feature",
  "properties": {
    "iso:country":"FR",
    "sg:address":"Rue de la Vigne - ZI Ouest",
    "sg:city":"Carpiquet",
    "sg:orig_category":"Non-Classified Establishments",
    "sg:phone":"+33 2 31 71 29 90",
    "sg:postcode":"14650",
    "sg:province":"Basse Normandie",
    "wof:name":"Initial Btb S.a.",
    "wof:placetype":"venue"
},
  "geometry": {"coordinates":[-0.443854,49.183708],"type":"Point"}
}