{
  "type": "Feature",
  "properties": {
    "iso:country":"FR",
    "sg:address":"75 Rue Emile Zola 62300 Lens",
    "sg:classifiers":[
        {
            "category":"Professional",
            "subcategory":"Business Services",
            "type":"Services"
        }
    ],
    "sg:phone":"+33 3 21 14 72 47",
    "sg:postcode":"62300",
    "sg:province":"Nord Pas-de-Calais",
    "sg:tags":[
        "training",
        "advice"
    ],
    "wof:name":"College Prive Sainte Ide",
    "wof:placetype":"venue"
},
  "geometry": {"coordinates":[2.831713,50.434113],"type":"Point"}
}