{
  "type": "Feature",
  "properties": {
    "addr:full":"30, Rue de la Rodaie, 37140 Saint Nicolas de Bourgueil Bourgueil Centre 37140",
    "addr:housenumber":"30",
    "addr:postcode":"37140;37140",
    "addr:street":"Rue De La Rodaie;Nicolas De Bourgueil Bourgueil",
    "iso:country":"FR",
    "sg:address":"30, Rue de la Rodaie, 37140 Saint Nicolas de Bourgueil",
    "sg:city":"Bourgueil",
    "sg:orig_category":"Unclassifiable Establishments",
    "sg:phone":"+33 2 47 97 77 74",
    "sg:postcode":"37140",
    "sg:province":"Centre",
    "wof:name":"Domaine De La Chopini\u00e8re Du Roy E.a.r.l.",
    "wof:placetype":"venue"
},
  "geometry": {"coordinates":[0.129144,47.281307],"type":"Point"}
}