{
  "type": "Feature",
  "properties": {
    "addr:full":"40 Rue De Panicale 78320 La Verriere Ile de France",
    "addr:housenumber":"40",
    "addr:postcode":"78320",
    "addr:street":"Rue De Panicale",
    "iso:country":"FR",
    "sg:address":"40 Rue De Panicale 78320 La Verriere",
    "sg:classifiers":[
        {
            "category":"Manufacturing",
            "subcategory":"Rubber & Plastics",
            "type":"Manufacturing & Wholesale Goods"
        }
    ],
    "sg:phone":"+33 1 30 66 30 99",
    "sg:province":"Ile de France",
    "wof:name":"Color Matrix Europe Ltd",
    "wof:placetype":"venue"
},
  "geometry": {"coordinates":[1.946786,48.75779],"type":"Point"}
}