{
  "type": "Feature",
  "properties": {
    "addr:full":"6 Quimper Bretagne 29000",
    "addr:housenumber":"6",
    "addr:postcode":"29000",
    "addr:street":"Quimper Bretagne",
    "iso:country":"FR",
    "sg:address":"6",
    "sg:city":"Quimper",
    "sg:classifiers":[
        {
            "category":"Professional",
            "type":"Services"
        }
    ],
    "sg:phone":"+33 2 98 64 04 60",
    "sg:postcode":"29000",
    "sg:province":"Bretagne",
    "sg:tags":[
        "transport",
        "road"
    ],
    "wof:name":"Alexis Bertholom",
    "wof:placetype":"venue"
},
  "geometry": {"coordinates":[-4.073266,47.980137],"type":"Point"}
}