{
  "type": "Feature",
  "properties": {
    "iso:country":"FR",
    "sg:address":"2 avenue Alphand 94160 St Mand\u00e9",
    "sg:classifiers":[
        {
            "category":"Professional",
            "subcategory":"Business Services",
            "type":"Services"
        }
    ],
    "sg:phone":"+33 1 48 08 65 24",
    "sg:postcode":"94160",
    "sg:province":"Ile de France",
    "sg:tags":[
        "data"
    ],
    "wof:name":"Logic Systems S.a.r.l.",
    "wof:placetype":"venue"
},
  "geometry": {"coordinates":[2.413925,48.839478],"type":"Point"}
}