{
  "type": "Feature",
  "properties": {
    "iso:country":"FR",
    "sg:address":"8 Rue Du Caire 1er Etage 75002 Paris",
    "sg:classifiers":[
        {
            "category":"Shopping",
            "subcategory":"Clothing, Apparel, & Fashions",
            "type":"Retail Goods"
        }
    ],
    "sg:phone":"+33 1 42 36 89 74",
    "sg:postcode":"75002",
    "sg:province":"Ile de France",
    "sg:tags":[
        "textile",
        "clothing",
        "clothes"
    ],
    "wof:name":"Anitsa",
    "wof:placetype":"venue"
},
  "geometry": {"coordinates":[2.352358,48.867317],"type":"Point"}
}