{
  "type": "Feature",
  "properties": {
    "addr:full":"105, Bd de Strasbourg, 76600 Le Havre Haute Normandie",
    "addr:housenumber":"105",
    "addr:postcode":"76600",
    "addr:street":"Bd De Strasbourg",
    "iso:country":"FR",
    "sg:address":"105, Bd de Strasbourg, 76600 Le Havre",
    "sg:orig_category":"Non-Classified Establishments",
    "sg:phone":"+33 2 35 22 46 92",
    "sg:province":"Haute Normandie",
    "wof:name":"Scoqi S.a.r.l.",
    "wof:placetype":"venue"
},
  "geometry": {"coordinates":[0.114644,49.492947],"type":"Point"}
}