{
  "type": "Feature",
  "properties": {
    "addr:full":"Chem De La Moselle BP 1043 57162 Moulin Les Metz Cedex Nord Pas-de-Calais",
    "addr:housenumber":"1043",
    "addr:postcode":"57162;les metz cedex nord",
    "addr:street":"Chem De La Moselle Bp;Moulin",
    "iso:country":"FR",
    "sg:address":"Chem De La Moselle BP 1043 57162 Moulin Les Metz Cedex",
    "sg:classifiers":[
        {
            "category":"Building & Trades",
            "subcategory":"Construction",
            "type":"Services"
        }
    ],
    "sg:phone":"+33 3 87 60 48 96",
    "sg:province":"Nord Pas-de-Calais",
    "sg:tags":[
        "work",
        "public"
    ],
    "wof:name":"Appia Metz",
    "wof:placetype":"venue"
},
  "geometry": {"coordinates":[6.105118,49.103085],"type":"Point"}
}