{
  "type": "Feature",
  "properties": {
    "iso:country":"FR",
    "sg:address":"6, Rue V\u00e9ja - ZI La Belle Etoile, 44470 Carquefou",
    "sg:orig_category":"Unclassifiable Establishments",
    "sg:phone":"+33 2 40 68 80 80",
    "sg:province":"Pays de Loire",
    "wof:name":"Transports Jean Devay S.a.r.l.",
    "wof:placetype":"venue"
},
  "geometry": {"coordinates":[-1.440899,47.266781],"type":"Point"}
}