{
  "type": "Feature",
  "properties": {
    "iso:country":"FR",
    "sg:address":"45",
    "sg:city":"St Martin 79390 Th\u00e9nezay",
    "sg:classifiers":[
        {
            "category":"Home & Garden",
            "subcategory":"Furniture",
            "type":"Retail Goods"
        }
    ],
    "sg:phone":"+33 5 49 63 01 64",
    "sg:province":"Poitou-Charentes",
    "sg:tags":[
        "wood"
    ],
    "wof:name":"Tib (transform.indus Du Bois)",
    "wof:placetype":"venue"
},
  "geometry": {"coordinates":[-0.027264,46.72086],"type":"Point"}
}