{
  "type": "Feature",
  "properties": {
    "addr:full":"Rue De La Garde 44335 Nantes Cedex 3 La Garde Rhone-Alpes 38520",
    "addr:postcode":"44335;38520",
    "addr:street":"Rue De La Garde;Garde Rhone-Alpes",
    "iso:country":"FR",
    "sg:address":"Rue De La Garde 44335 Nantes Cedex 3",
    "sg:city":"La Garde",
    "sg:orig_category":"Agriculture and Livestock Clothing accessories Horticulture Textiles and Clothing",
    "sg:phone":"+33 2 40 18 44 22",
    "sg:postcode":"38520",
    "sg:province":"Rhone-Alpes",
    "wof:name":"Renaud Sa",
    "wof:placetype":"venue"
},
  "geometry": {"coordinates":[-1.508607,47.255428],"type":"Point"}
}