{
  "type": "Feature",
  "properties": {
    "addr:full":"B.P. 15, 62161 Maroeuil^^5, Rue des Champs, 62161 Maroeuil Nord Pas-de-Calais 62161",
    "addr:postcode":"62161;62161;62161",
    "addr:street":"B.P. 15;Rue Des Champs",
    "iso:country":"FR",
    "sg:address":"B.P. 15, 62161 Maroeuil^^5, Rue des Champs, 62161 Maroeuil",
    "sg:orig_category":"Non-Classified Establishments",
    "sg:phone":"+33 3 21 50 58 00",
    "sg:postcode":"62161",
    "sg:province":"Nord Pas-de-Calais",
    "wof:name":"Corsain S.a.",
    "wof:placetype":"venue"
},
  "geometry": {"coordinates":[2.687328,50.306469],"type":"Point"}
}