{
  "type": "Feature",
  "properties": {
    "addr:full":"Rte De La Brosse 77164 Ferri\u00e8res En Brie Ile de France 77164",
    "addr:postcode":"77164;77164",
    "addr:street":"Rte De La Brosse",
    "iso:country":"FR",
    "sg:address":"Rte De La Brosse 77164 Ferri\u00e8res En Brie",
    "sg:classifiers":[
        {
            "category":"Professional",
            "subcategory":"Engineering",
            "type":"Services"
        }
    ],
    "sg:phone":"+33 1 64 76 70 70",
    "sg:postcode":"77164",
    "sg:province":"Ile de France",
    "sg:tags":[
        "machine",
        "-",
        "mechanical"
    ],
    "wof:name":"Verdun Ets",
    "wof:placetype":"venue"
},
  "geometry": {"coordinates":[2.691414,48.825504],"type":"Point"}
}