{
  "type": "Feature",
  "properties": {
    "iso:country":"FR",
    "sg:address":"B.P. 34",
    "sg:city":"Vallet",
    "sg:orig_category":"Non-Classified Establishments",
    "sg:phone":"+33 2 40 33 99 94",
    "sg:postcode":"44330",
    "sg:province":"Pays de Loire",
    "wof:name":"Michel Bahuaud S.a.r.l.",
    "wof:placetype":"venue"
},
  "geometry": {"coordinates":[-1.265219,47.161079],"type":"Point"}
}