{
  "type": "Feature",
  "properties": {
    "addr:full":"16 rue Etienne Rognon 69007 Lyon Rhone-Alpes",
    "addr:housenumber":"16",
    "addr:postcode":"69007",
    "addr:street":"Rue Etienne Rognon",
    "iso:country":"FR",
    "sg:address":"16 rue Etienne Rognon 69007 Lyon",
    "sg:classifiers":[
        {
            "category":"Banks & Credit Unions",
            "subcategory":"Investment Brokerage",
            "type":"Services"
        }
    ],
    "sg:phone":"+33 4 37 37 84 90",
    "sg:province":"Rhone-Alpes",
    "sg:tags":[
        "picture",
        "frame",
        "moulding"
    ],
    "wof:name":"Senelar Larson Juhl S.a.",
    "wof:placetype":"venue"
},
  "geometry": {"coordinates":[4.834907,45.746323],"type":"Point"}
}