{
  "type": "Feature",
  "properties": {
    "addr:full":"B.P. 62303, 44323 Nantes C\u00e9dex 03^^Rue Pierre Adolphe Bobierre - Atlanp\u00f4le la G\u00e9raudi\u00e8re, 44320 Nant Pays de Loire 44320",
    "addr:postcode":"44323;atlanpo\u0302le;44320;44320",
    "addr:street":"La Ge\u0301Raudie\u0300Re;Nant Pays",
    "iso:country":"FR",
    "sg:address":"B.P. 62303, 44323 Nantes C\u00e9dex 03^^Rue Pierre Adolphe Bobierre - Atlanp\u00f4le la G\u00e9raudi\u00e8re, 44320 Nant",
    "sg:orig_category":"Non-Classified Establishments",
    "sg:phone":"+33 2 51 77 68 00",
    "sg:postcode":"44320",
    "sg:province":"Pays de Loire",
    "wof:name":"Adriant S.a.",
    "wof:placetype":"venue"
},
  "geometry": {"coordinates":[-1.939712,47.114998],"type":"Point"}
}