{
  "type": "Feature",
  "properties": {
    "iso:country":"FR",
    "sg:address":"18, Rue des Chasseurs \u00e0 Pied, 59570 La Longueville",
    "sg:orig_category":"Unclassifiable Establishments",
    "sg:phone":"+33 3 27 62 15 76",
    "sg:province":"Nord Pas-de-Calais",
    "wof:name":"Lorban Et Compagnie S.a.",
    "wof:placetype":"venue"
},
  "geometry": {"coordinates":[3.870645,50.284813],"type":"Point"}
}