{
  "type": "Feature",
  "properties": {
    "iso:country":"FR",
    "sg:address":"PAE les Combaruches",
    "sg:city":"Aix les Bains",
    "sg:orig_category":"Non-Classified Establishments",
    "sg:phone":"+33 4 79 34 35 36",
    "sg:postcode":"73100",
    "sg:province":"Rhone-Alpes",
    "wof:name":"Clipsol S.a.",
    "wof:placetype":"venue"
},
  "geometry": {"coordinates":[5.899685,45.672455],"type":"Point"}
}