{
  "type": "Feature",
  "properties": {
    "iso:country":"FR",
    "sg:address":"23, Av. Aristide Briand, 79200 Parthenay",
    "sg:orig_category":"Unclassifiable Establishments",
    "sg:phone":"+33 5 49 64 48 22",
    "sg:postcode":"79200",
    "sg:province":"Poitou-Charentes",
    "wof:name":"A.d.c. S.a. - Ateliers De La Chainette",
    "wof:placetype":"venue"
},
  "geometry": {"coordinates":[-0.236569,46.646095],"type":"Point"}
}