{
  "type": "Feature",
  "properties": {
    "iso:country":"FR",
    "sg:address":"4 Boulevard De L Industrie",
    "sg:city":"De Pahin 31170 Tournefeuille",
    "sg:classifiers":[
        {
            "category":"Shopping",
            "type":"Retail Goods"
        }
    ],
    "sg:phone":"+33 5 61 78 27 03",
    "sg:postcode":"31170",
    "sg:province":"Midi Pyr\u00e9n\u00e9es",
    "sg:tags":[
        "metallurgy",
        "finished",
        "-",
        "metalworking",
        "metallic"
    ],
    "wof:name":"Carr\u00c9 Sa",
    "wof:placetype":"venue"
},
  "geometry": {"coordinates":[1.342895,43.584095],"type":"Point"}
}