{
  "type": "Feature",
  "properties": {
    "iso:country":"FR",
    "sg:address":"82, Rue du Montmurier, 38540 Grenay",
    "sg:orig_category":"Unclassifiable Establishments",
    "sg:phone":"+33 4 74 94 02 30",
    "sg:province":"Rhone-Alpes",
    "wof:name":"R.e.m.t. S.a.r.l. - R\u00e9alisation Etudes M\u00e9caniques Et Techniques",
    "wof:placetype":"venue"
},
  "geometry": {"coordinates":[5.09427,45.664413],"type":"Point"}
}