{
  "type": "Feature",
  "properties": {
    "addr:full":"46, Rue de la R\u00e9publique, 30500 Saint Ambroix Languedoc-Roussillon",
    "addr:housenumber":"46",
    "addr:postcode":"30500;ambroix",
    "addr:street":"Rue De La Re\u0301Publique",
    "iso:country":"FR",
    "sg:address":"46, Rue de la R\u00e9publique, 30500 Saint Ambroix",
    "sg:orig_category":"Non-Classified Establishments",
    "sg:phone":"+33 4 66 24 00 26",
    "sg:province":"Languedoc-Roussillon",
    "wof:name":"Soci\u00e9t\u00e9 Exploitation Samnet S.a.r.l.",
    "wof:placetype":"venue"
},
  "geometry": {"coordinates":[4.203219,44.258385],"type":"Point"}
}