{
  "type": "Feature",
  "properties": {
    "addr:full":"ZI Nord - La B\u00e9lardi\u00e8re Dissay Poitou-Charentes 86130",
    "addr:postcode":"86130",
    "addr:street":"Zi Nord La Be\u0301Lardie\u0300Re Dissay",
    "iso:country":"FR",
    "sg:address":"ZI Nord - La B\u00e9lardi\u00e8re",
    "sg:city":"Dissay",
    "sg:orig_category":"Unclassifiable Establishments",
    "sg:phone":"+33 5 49 62 74 00",
    "sg:postcode":"86130",
    "sg:province":"Poitou-Charentes",
    "wof:name":"Transports Paulus Guillot S.a.",
    "wof:placetype":"venue"
},
  "geometry": {"coordinates":[0.428726,46.698917],"type":"Point"}
}