{
  "type": "Feature",
  "properties": {
    "addr:full":"52, Rue Lucien Coupet, 36100 Issoudun Issoudun Centre 36100",
    "addr:housenumber":"52",
    "addr:postcode":"36100;36100",
    "addr:street":"Rue Lucien Coupet",
    "iso:country":"FR",
    "sg:address":"52, Rue Lucien Coupet, 36100 Issoudun",
    "sg:city":"Issoudun",
    "sg:orig_category":"Unclassifiable Establishments",
    "sg:phone":"+33 2 54 21 27 50",
    "sg:postcode":"36100",
    "sg:province":"Centre",
    "wof:name":"Socom\u00e9tub S.a.r.l.",
    "wof:placetype":"venue"
},
  "geometry": {"coordinates":[1.983356,46.937801],"type":"Point"}
}