{
  "type": "Feature",
  "properties": {
    "addr:full":"Avenue Du President Coty 21400 CHARREY SUR SEINE Aisey-sur-Seine Bourgogne 21400",
    "addr:postcode":"21400;21400",
    "addr:street":"Avenue Du President Coty;Seine;Bourgogne",
    "iso:country":"FR",
    "sg:address":"Avenue Du President Coty 21400 CHARREY SUR SEINE",
    "sg:city":"Aisey-sur-Seine",
    "sg:orig_category":"Adhesive Tape Dispensers, Automatic",
    "sg:phone":"+33 3 80 91 11 35",
    "sg:postcode":"21400",
    "sg:province":"Bourgogne",
    "wof:name":"Etablissements Fernand Brugere Sa",
    "wof:placetype":"venue"
},
  "geometry": {"coordinates":[4.464557,47.731129],"type":"Point"}
}