{
  "type": "Feature",
  "properties": {
    "iso:country":"FR",
    "sg:address":"Rte Broglie - La Grande Malouve",
    "sg:city":"Bernay",
    "sg:orig_category":"Unclassifiable Establishments",
    "sg:phone":"+33 2 32 43 26 93",
    "sg:postcode":"27300",
    "sg:province":"Haute Normandie",
    "wof:name":"Girard S.a.",
    "wof:placetype":"venue"
},
  "geometry": {"coordinates":[0.57964,49.066216],"type":"Point"}
}