{
  "type": "Feature",
  "properties": {
    "iso:country":"FR",
    "sg:address":"2 rue d'Allemagne 68310 Wittelsheim",
    "sg:city":"Wittelsheim",
    "sg:orig_category":"Peripheral Equipment For Screen Printing",
    "sg:phone":"+33 3 89 57 70 11",
    "sg:postcode":"68310",
    "sg:province":"Alsace",
    "wof:name":"Sorim Sarl",
    "wof:placetype":"venue"
},
  "geometry": {"coordinates":[7.22461,47.773651],"type":"Point"}
}