{
  "type": "Feature",
  "properties": {
    "addr:full":"1, Mont\u00e9e Georges Kubler, 69004 Lyon Rhone-Alpes 69004",
    "addr:housenumber":"1",
    "addr:postcode":"69004;69004",
    "addr:street":"Monte\u0301E Georges Kubler",
    "iso:country":"FR",
    "sg:address":"1, Mont\u00e9e Georges Kubler, 69004 Lyon",
    "sg:orig_category":"Unclassifiable Establishments",
    "sg:phone":"+33 4 37 85 12 12",
    "sg:postcode":"69004",
    "sg:province":"Rhone-Alpes",
    "wof:name":"Jeannot S.a.",
    "wof:placetype":"venue"
},
  "geometry": {"coordinates":[4.834812,45.780598],"type":"Point"}
}