{
  "type": "Feature",
  "properties": {
    "iso:country":"FR",
    "sg:address":"57, Rue Jean Jaur\u00e8s, 37210 Vernou sur Brenne",
    "sg:city":"Chan\u00e7ay",
    "sg:orig_category":"Unclassifiable Establishments",
    "sg:phone":"+33 2 47 52 02 38",
    "sg:postcode":"37210",
    "sg:province":"Centre",
    "wof:name":"G. Champion G.a.e.c.",
    "wof:placetype":"venue"
},
  "geometry": {"coordinates":[0.84108,47.453579],"type":"Point"}
}