{
  "type": "Feature",
  "properties": {
    "addr:full":"57, Rue Jean Jaur\u00e8s, 37210 Vernou sur Brenne Chan\u00e7ay Centre 37210",
    "addr:housenumber":"57;chanc\u0327ay",
    "addr:postcode":"37210;37210",
    "addr:street":"Rue Jean Jaure\u0300S",
    "iso:country":"FR",
    "sg:address":"57, Rue Jean Jaur\u00e8s, 37210 Vernou sur Brenne",
    "sg:city":"Chan\u00e7ay",
    "sg:orig_category":"Unclassifiable Establishments",
    "sg:phone":"+33 2 47 52 02 38",
    "sg:postcode":"37210",
    "sg:province":"Centre",
    "wof:name":"G. Champion G.a.e.c.",
    "wof:placetype":"venue"
},
  "geometry": {"coordinates":[0.84108,47.453579],"type":"Point"}
}