{
  "type": "Feature",
  "properties": {
    "addr:full":"9 Rue Amp\u00e8re 71000 M\u00e2con Sanc\u00e9 Bourgogne 71000",
    "addr:housenumber":"9",
    "addr:postcode":"71000;71000",
    "addr:street":"Rue Ampe\u0300Re",
    "iso:country":"FR",
    "sg:address":"9 Rue Amp\u00e8re 71000 M\u00e2con",
    "sg:city":"Sanc\u00e9",
    "sg:classifiers":[
        {
            "category":"Manufacturing",
            "subcategory":"Tools & Machinery",
            "type":"Manufacturing & Wholesale Goods"
        }
    ],
    "sg:phone":"+33 3 85 29 39 00",
    "sg:postcode":"71000",
    "sg:province":"Bourgogne",
    "sg:tags":[
        "equipment",
        "measurement",
        "-",
        "precision",
        "instrument"
    ],
    "wof:name":"Actaris",
    "wof:placetype":"venue"
},
  "geometry": {"coordinates":[4.804219,46.293304],"type":"Point"}
}