{
  "type": "Feature",
  "properties": {
    "iso:country":"FR",
    "sg:address":"ZI",
    "sg:city":"Gellainville",
    "sg:orig_category":"Non-Classified Establishments",
    "sg:phone":"+33 2 37 88 33 33",
    "sg:postcode":"28630",
    "sg:province":"Centre",
    "wof:name":"Senteria Parfums S.a.r.l.",
    "wof:placetype":"venue"
},
  "geometry": {"coordinates":[1.49045,48.429531],"type":"Point"}
}