{
  "type": "Feature",
  "properties": {
    "addr:full":"117A, Rte des Romains, 67200 Strasbourg Strasbourg Alsace 67200",
    "addr:housenumber":"117a",
    "addr:postcode":"67200;67200",
    "addr:street":"Rte Des Romains",
    "iso:country":"FR",
    "sg:address":"117A, Rte des Romains, 67200 Strasbourg",
    "sg:city":"Strasbourg",
    "sg:orig_category":"Unclassifiable Establishments",
    "sg:phone":"+33 3 88 28 80 80",
    "sg:postcode":"67200",
    "sg:province":"Alsace",
    "wof:name":"Atac S.a.",
    "wof:placetype":"venue"
},
  "geometry": {"coordinates":[7.706925,48.578121],"type":"Point"}
}