{
  "type": "Feature",
  "properties": {
    "addr:full":"Plessis 27560 Noards Haute Normandie 27560",
    "addr:postcode":"27560;27560",
    "addr:street":"Plessis;Haute Normandie",
    "iso:country":"FR",
    "sg:address":"Plessis 27560 Noards",
    "sg:classifiers":[
        {
            "category":"Food & Beverages",
            "subcategory":"Dairy",
            "type":"Retail Goods"
        }
    ],
    "sg:phone":"+33 2 32 20 27 27",
    "sg:postcode":"27560",
    "sg:province":"Haute Normandie",
    "sg:tags":[
        "product",
        "related"
    ],
    "wof:name":"Fromagerie Du Plessis Sas",
    "wof:placetype":"venue"
},
  "geometry": {"coordinates":[0.5686,49.195526],"type":"Point"}
}