{
  "type": "Feature",
  "properties": {
    "iso:country":"FR",
    "sg:address":"17 Rue Du F\u00e2ches Zi B 59790 Ronchin",
    "sg:classifiers":[
        {
            "category":"Utilities",
            "subcategory":"Telephone",
            "type":"Services"
        }
    ],
    "sg:phone":"+33 3 20 62 13 50",
    "sg:province":"Nord Pas-de-Calais",
    "sg:tags":[
        "telecommunication"
    ],
    "wof:name":"Japel",
    "wof:placetype":"venue"
},
  "geometry": {"coordinates":[3.07743,50.605816],"type":"Point"}
}