{
  "type": "Feature",
  "properties": {
    "addr:full":"6, Rue L\u00e9opold Bellan, 94360 Bry sur Marne Ile de France",
    "addr:housenumber":"6",
    "addr:postcode":"94360",
    "addr:street":"Rue Le\u0301Opold Bellan",
    "iso:country":"FR",
    "sg:address":"6, Rue L\u00e9opold Bellan, 94360 Bry sur Marne",
    "sg:orig_category":"Non-Classified Establishments",
    "sg:phone":"+33 1 47 06 04 00",
    "sg:province":"Ile de France",
    "wof:name":"Spring S.a.r.l.",
    "wof:placetype":"venue"
},
  "geometry": {"coordinates":[2.520146,48.837982],"type":"Point"}
}