{
  "type": "Feature",
  "properties": {
    "iso:country":"FR",
    "sg:address":"45 rue Charles de Gaulle 88160 Le Thillot",
    "sg:classifiers":[
        {
            "category":"Shopping",
            "subcategory":"Crafts & Fabrics",
            "type":"Retail Goods"
        }
    ],
    "sg:phone":"+33 3 29 25 00 19",
    "sg:postcode":"88160",
    "sg:province":"Lorraine",
    "sg:tags":[
        "cloth"
    ],
    "wof:name":"Malima S.a.r.l",
    "wof:placetype":"venue"
},
  "geometry": {"coordinates":[6.76787,47.878098],"type":"Point"}
}