{
  "type": "Feature",
  "properties": {
    "addr:full":"5, Rue des Suisses, 75014 Paris Ile de France",
    "addr:housenumber":"5",
    "addr:postcode":"75014",
    "addr:street":"Rue Des Suisses",
    "iso:country":"FR",
    "sg:address":"5, Rue des Suisses, 75014 Paris",
    "sg:orig_category":"Unclassifiable Establishments",
    "sg:phone":"+33 1 40 44 04 56",
    "sg:province":"Ile de France",
    "wof:name":"A. Burodafer S.a.r.l.",
    "wof:placetype":"venue"
},
  "geometry": {"coordinates":[2.314307,48.830681],"type":"Point"}
}