{
  "type": "Feature",
  "properties": {
    "iso:country":"FR",
    "sg:address":"30 B Rue Archange",
    "sg:city":"Orsay",
    "sg:classifiers":[
        {
            "category":"Banks & Credit Unions",
            "subcategory":"Financial Services",
            "type":"Services"
        }
    ],
    "sg:phone":"+33 1 64 46 25 48",
    "sg:postcode":"91400",
    "sg:province":"Ile de France",
    "sg:tags":[
        "banking",
        "finance",
        "insurance"
    ],
    "wof:name":"Societe Nanceienne Varin Bernier (snvb)",
    "wof:placetype":"venue"
},
  "geometry": {"coordinates":[2.184827,48.696926],"type":"Point"}
}