{
  "type": "Feature",
  "properties": {
    "addr:full":"15 Quai Des Belges 38300 Bourgoin Jallieu Rhone-Alpes 38300",
    "addr:housenumber":"15",
    "addr:postcode":"38300;38300",
    "addr:street":"Quai Des Belges;Rhone-Alpes",
    "iso:country":"FR",
    "sg:address":"15 Quai Des Belges 38300 Bourgoin Jallieu",
    "sg:classifiers":[
        {
            "category":"Professional",
            "subcategory":"Engineering",
            "type":"Services"
        }
    ],
    "sg:phone":"+33 4 74 93 30 15",
    "sg:postcode":"38300",
    "sg:province":"Rhone-Alpes",
    "sg:tags":[
        "machine",
        "-",
        "mechanical"
    ],
    "wof:name":"Lahes",
    "wof:placetype":"venue"
},
  "geometry": {"coordinates":[5.282848,45.5942],"type":"Point"}
}