{
  "type": "Feature",
  "properties": {
    "addr:full":"Rue Le Tintoret Zac Vall\u00e9e St Ladre 80080 Amiens Amiens Picardie 80000",
    "addr:postcode":"80080 amiens;80000",
    "addr:street":"Rue Le Tintoret Zac Valle\u0301E St Ladre",
    "iso:country":"FR",
    "sg:address":"Rue Le Tintoret Zac Vall\u00e9e St Ladre 80080 Amiens",
    "sg:city":"Amiens",
    "sg:classifiers":[
        {
            "category":"Shopping",
            "subcategory":"Clothing, Apparel, & Fashions",
            "type":"Retail Goods"
        }
    ],
    "sg:phone":"+33 3 22 54 66 66",
    "sg:postcode":"80000",
    "sg:province":"Picardie",
    "sg:tags":[
        "textile",
        "clothing",
        "clothes"
    ],
    "wof:name":"Lee Cooper France",
    "wof:placetype":"venue"
},
  "geometry": {"coordinates":[2.2913,49.924992],"type":"Point"}
}