{
  "type": "Feature",
  "properties": {
    "addr:full":"20, Rue du Mal de Lattre de Tassigny, 49440 Cand\u00e9 Pays de Loire 49440",
    "addr:housenumber":"20",
    "addr:postcode":"49440;49440",
    "addr:street":"Rue Du Mal De Lattre De Tassigny",
    "iso:country":"FR",
    "sg:address":"20, Rue du Mal de Lattre de Tassigny, 49440 Cand\u00e9",
    "sg:orig_category":"Non-Classified Establishments",
    "sg:phone":"+33 2 41 92 01 85",
    "sg:postcode":"49440",
    "sg:province":"Pays de Loire",
    "wof:name":"Croix Fils S.a.",
    "wof:placetype":"venue"
},
  "geometry": {"coordinates":[-0.983694,47.511105],"type":"Point"}
}