{
  "type": "Feature",
  "properties": {
    "addr:full":"30, Rte de Dieppe, 76960 Notre Dame de Bondeville Haute Normandie 76960",
    "addr:housenumber":"30",
    "addr:postcode":"76960;76960",
    "addr:street":"Rte De Dieppe;Dame",
    "iso:country":"FR",
    "sg:address":"30, Rte de Dieppe, 76960 Notre Dame de Bondeville",
    "sg:orig_category":"Non-Classified Establishments",
    "sg:phone":"+33 2 35 75 49 36",
    "sg:postcode":"76960",
    "sg:province":"Haute Normandie",
    "wof:name":"Doubet Automatisme E.u.r.l.",
    "wof:placetype":"venue"
},
  "geometry": {"coordinates":[1.048354,49.486263],"type":"Point"}
}