{
  "type": "Feature",
  "properties": {
    "addr:full":"Usine D Estarac 31360 BOUSSENS Midi Pyr\u00e9n\u00e9es 31360",
    "addr:postcode":"31360;31360",
    "iso:country":"FR",
    "sg:address":"Usine D Estarac 31360 BOUSSENS",
    "sg:classifiers":[
        {
            "category":"Manufacturing",
            "subcategory":"Chemicals & Compounds",
            "type":"Manufacturing & Wholesale Goods"
        }
    ],
    "sg:phone":"+33 5 61 98 43 60",
    "sg:postcode":"31360",
    "sg:province":"Midi Pyr\u00e9n\u00e9es",
    "sg:tags":[
        "base"
    ],
    "wof:name":"Cognis France Sa",
    "wof:placetype":"venue"
},
  "geometry": {"coordinates":[0.866359,43.108395],"type":"Point"}
}