{
  "type": "Feature",
  "properties": {
    "addr:full":"Av. Charles Bedaux - ZI de Menneton Tours Centre 37000",
    "addr:postcode":"37000",
    "addr:street":"Av. Charles Bedaux Zi De Menneton",
    "iso:country":"FR",
    "sg:address":"Av. Charles Bedaux - ZI de Menneton",
    "sg:city":"Tours",
    "sg:orig_category":"Unclassifiable Establishments",
    "sg:phone":"+33 2 47 76 45 45",
    "sg:postcode":"37000",
    "sg:province":"Centre",
    "wof:name":"Atac S.a.",
    "wof:placetype":"venue"
},
  "geometry": {"coordinates":[0.689715,47.390385],"type":"Point"}
}