{
  "type": "Feature",
  "properties": {
    "addr:full":"Av. de Vanel Privas Rhone-Alpes 07000",
    "addr:postcode":"07000",
    "addr:street":"Av. De Vanel Privas Rhone-Alpes",
    "iso:country":"FR",
    "sg:address":"Av. de Vanel",
    "sg:city":"Privas",
    "sg:orig_category":"Unclassifiable Establishments",
    "sg:phone":"+33 4 75 64 30 66",
    "sg:postcode":"07000",
    "sg:province":"Rhone-Alpes",
    "wof:name":"La Chaumette",
    "wof:placetype":"venue"
},
  "geometry": {"coordinates":[4.604285,44.736053],"type":"Point"}
}