{
  "type": "Feature",
  "properties": {
    "addr:full":"B.P. 70, 69513 Vaulx en Velin C\u00e9dex^^118, av. Franklin Roosevelt, 69120 Vaulx en Velin Rhone-Alpes 69120",
    "addr:postcode":"69513;69120;69120",
    "addr:street":"B.P. 70;Av. Franklin Roosevelt",
    "iso:country":"FR",
    "sg:address":"B.P. 70, 69513 Vaulx en Velin C\u00e9dex^^118, av. Franklin Roosevelt, 69120 Vaulx en Velin",
    "sg:orig_category":"Non-Classified Establishments",
    "sg:phone":"+33 4 72 05 46 50",
    "sg:postcode":"69120",
    "sg:province":"Rhone-Alpes",
    "wof:name":"Revol Et Sonier S.a.",
    "wof:placetype":"venue"
},
  "geometry": {"coordinates":[4.916895,45.779022],"type":"Point"}
}