{
  "type": "Feature",
  "properties": {
    "iso:country":"FR",
    "sg:address":"229, Rte de Taninges - ZI de Borly, 74380 Cranves Sales",
    "sg:orig_category":"Unclassifiable Establishments",
    "sg:phone":"+33 4 50 36 75 35",
    "sg:province":"Rhone-Alpes",
    "wof:name":"Coadec S.a.r.l.",
    "wof:placetype":"venue"
},
  "geometry": {"coordinates":[6.291592,46.186501],"type":"Point"}
}