{
  "type": "Feature",
  "properties": {
    "iso:country":"FR",
    "sg:address":"B.P. 203, 76304 Sotteville l\u00e8s Rouen C\u00e9dex^^9, Rue Lavoisier - ZI, 76300 Sotteville l\u00e8s Rouen",
    "sg:orig_category":"Non-Classified Establishments",
    "sg:phone":"+33 2 35 64 26 00",
    "sg:province":"Haute Normandie",
    "wof:name":"Tecniroc S.a.r.l.",
    "wof:placetype":"venue"
},
  "geometry": {"coordinates":[1.089274,49.414249],"type":"Point"}
}