{
  "type": "Feature",
  "properties": {
    "addr:full":"3 Quai du Commdt l'Herminier; Pornic Aquitaine",
    "addr:housenumber":"3",
    "addr:street":"Quai Du Commdt L'Herminier",
    "iso:country":"FR",
    "sg:address":"3 Quai du Commdt l'Herminier; Pornic",
    "sg:classifiers":[
        {
            "category":"Banks & Credit Unions",
            "subcategory":"Bank",
            "type":"Services"
        }
    ],
    "sg:phone":"+33 4 08 20 08 59",
    "sg:province":"Aquitaine",
    "wof:name":"Cr\u00e9dit Agricole Mutuel",
    "wof:placetype":"venue"
},
  "geometry": {"coordinates":[-2.100336,47.114239],"type":"Point"}
}