{
  "type": "Feature",
  "properties": {
    "iso:country":"FR",
    "sg:address":"ZA",
    "sg:city":"Caylus",
    "sg:orig_category":"Unclassifiable Establishments",
    "sg:phone":"+33 5 63 67 05 20",
    "sg:postcode":"82160",
    "sg:province":"Midi Pyr\u00e9n\u00e9es",
    "wof:name":"Constructions M\u00e9talliques Miramond S.a.s.",
    "wof:placetype":"venue"
},
  "geometry": {"coordinates":[1.829266,44.195793],"type":"Point"}
}