{
  "type": "Feature",
  "properties": {
    "addr:full":"ZA Parc C'Hastel Fouesnant Bretagne 29170",
    "addr:postcode":"29170",
    "addr:street":"Za Parc C'Hastel;Bretagne",
    "iso:country":"FR",
    "sg:address":"ZA Parc C'Hastel",
    "sg:city":"Fouesnant",
    "sg:orig_category":"Non-Classified Establishments",
    "sg:phone":"+33 2 98 56 19 40",
    "sg:postcode":"29170",
    "sg:province":"Bretagne",
    "wof:name":"S.m.i.s.",
    "wof:placetype":"venue"
},
  "geometry": {"coordinates":[-4.01156,47.894421],"type":"Point"}
}