{
  "type": "Feature",
  "properties": {
    "iso:country":"FR",
    "sg:address":"Zone Industrielle",
    "sg:city":"Carpiquet",
    "sg:orig_category":"Unclassifiable Establishments",
    "sg:phone":"+33 2 31 26 12 34",
    "sg:postcode":"14650",
    "sg:province":"Basse Normandie",
    "wof:name":"Amidis Nord France S.a.s.",
    "wof:placetype":"venue"
},
  "geometry": {"coordinates":[-0.443854,49.183708],"type":"Point"}
}