{
  "type": "Feature",
  "properties": {
    "addr:full":"81, Av. de l'Europe - ZAC de l'Anjoly, 13127 Vitrolles Haute Normandie",
    "addr:postcode":"13127",
    "addr:street":"81 Av. De L'Europe Zac De L'Anjoly;Haute Normandie",
    "iso:country":"FR",
    "sg:address":"81, Av. de l'Europe - ZAC de l'Anjoly, 13127 Vitrolles",
    "sg:orig_category":"Non-Classified Establishments",
    "sg:phone":"+33 4 42 46 19 19",
    "sg:province":"Haute Normandie",
    "wof:name":"Offset 2000 S.a.r.l.",
    "wof:placetype":"venue"
},
  "geometry": {"coordinates":[5.26554,43.450859],"type":"Point"}
}