{
  "type": "Feature",
  "properties": {
    "iso:country":"FR",
    "sg:address":"54 Bis Av D'Orl\u00e9ans 18230 Saint Doulchard",
    "sg:city":"Saint-Doulchard",
    "sg:classifiers":[
        {
            "category":"Travel",
            "subcategory":"Hotels & Motels",
            "type":"Entertainment"
        }
    ],
    "sg:phone":"+33 2 48 70 31 73",
    "sg:postcode":"18230",
    "sg:province":"Centre",
    "sg:tags":[
        "hotels",
        "business",
        "restaurant"
    ],
    "wof:name":"France Restauration Rapide Pat A Pain",
    "wof:placetype":"venue"
},
  "geometry": {"coordinates":[2.378836,47.105812],"type":"Point"}
}