{
  "type": "Feature",
  "properties": {
    "addr:full":"1 Bis Gustave Eiffel 49300 Cholet Pays de Loire 49300",
    "addr:housenumber":"1 bis",
    "addr:postcode":"49300;49300",
    "addr:street":"Gustave Eiffel",
    "iso:country":"FR",
    "sg:address":"1 Bis Gustave Eiffel 49300 Cholet",
    "sg:classifiers":[
        {
            "category":"Professional",
            "subcategory":"Advertising",
            "type":"Services"
        }
    ],
    "sg:phone":"+33 2 41 58 55 26",
    "sg:postcode":"49300",
    "sg:province":"Pays de Loire",
    "sg:tags":[
        "marketing",
        "medium",
        "communication"
    ],
    "wof:name":"Adrexo",
    "wof:placetype":"venue"
},
  "geometry": {"coordinates":[-0.850809,47.064526],"type":"Point"}
}