{
  "type": "Feature",
  "properties": {
    "addr:full":"25 Chemin De Pouvourville 31400 Toulouse Midi Pyr\u00e9n\u00e9es 31400",
    "addr:housenumber":"25",
    "addr:postcode":"31400;31400",
    "addr:street":"Chemin De Pouvourville",
    "iso:country":"FR",
    "sg:address":"25 Chemin De Pouvourville 31400 Toulouse",
    "sg:classifiers":[
        {
            "category":"Government",
            "subcategory":"Department Of Motor Vehicles",
            "type":"Public Place"
        }
    ],
    "sg:phone":"+33 5 61 17 61 61",
    "sg:postcode":"31400",
    "sg:province":"Midi Pyr\u00e9n\u00e9es",
    "sg:tags":[
        "equipment",
        "industrial",
        "transport",
        "motor-cars"
    ],
    "wof:name":"Actia",
    "wof:placetype":"venue"
},
  "geometry": {"coordinates":[1.454685,43.548481],"type":"Point"}
}