{
  "type": "Feature",
  "properties": {
    "addr:full":"Rue de la Sonde Donchery Champagne 08350",
    "addr:postcode":"08350",
    "addr:street":"Rue De La;Champagne",
    "iso:country":"FR",
    "sg:address":"Rue de la Sonde",
    "sg:city":"Donchery",
    "sg:orig_category":"FONDERIE",
    "sg:phone":"+33 3 24 27 71 71",
    "sg:postcode":"08350",
    "sg:province":"Champagne",
    "wof:name":"Invicta S.a.",
    "wof:placetype":"venue"
},
  "geometry": {"coordinates":[4.872138,49.691349],"type":"Point"}
}