{
  "type": "Feature",
  "properties": {
    "addr:full":"Route Tonnerre 89600 St Florentin Ch\u00e9u Bourgogne 89600",
    "addr:postcode":"89600;89600",
    "addr:street":"Route Tonnerre",
    "iso:country":"FR",
    "sg:address":"Route Tonnerre 89600 St Florentin",
    "sg:city":"Ch\u00e9u",
    "sg:classifiers":[
        {
            "category":"Government",
            "subcategory":"Department Of Motor Vehicles",
            "type":"Public Place"
        }
    ],
    "sg:phone":"+33 3 86 35 02 14",
    "sg:postcode":"89600",
    "sg:province":"Bourgogne",
    "sg:tags":[
        "equipment",
        "industrial",
        "transport",
        "motor-cars"
    ],
    "wof:name":"Ets Dujon Sa",
    "wof:placetype":"venue"
},
  "geometry": {"coordinates":[3.72972,48.002575],"type":"Point"}
}