{
  "type": "Feature",
  "properties": {
    "iso:country":"FR",
    "sg:address":"ZI",
    "sg:city":"Susville",
    "sg:orig_category":"Non-Classified Establishments",
    "sg:phone":"+33 4 76 81 07 04",
    "sg:postcode":"38350",
    "sg:province":"Rhone-Alpes",
    "wof:name":"S.n.i.a. S.a.r.l. - Soci\u00e9t\u00e9 Nouvelle Is\u00e8re Alp.",
    "wof:placetype":"venue"
},
  "geometry": {"coordinates":[5.733722,44.872341],"type":"Point"}
}