{
  "type": "Feature",
  "properties": {
    "iso:country":"FR",
    "sg:address":"Rte de Limoux",
    "sg:city":"Bram",
    "sg:orig_category":"Unclassifiable Establishments",
    "sg:phone":"+33 4 68 76 70 60",
    "sg:postcode":"11150",
    "sg:province":"Languedoc-Roussillon",
    "wof:name":"Bio Plan\u00e8te S.a.r.l.",
    "wof:placetype":"venue"
},
  "geometry": {"coordinates":[2.038485,43.220734],"type":"Point"}
}