{
  "type": "Feature",
  "properties": {
    "iso:country":"FR",
    "sg:address":"30, Av. du 19 Mars 1962, 17500 Jonzac",
    "sg:orig_category":"Unclassifiable Establishments",
    "sg:phone":"+33 5 46 48 35 05",
    "sg:province":"Poitou-Charentes",
    "wof:name":"Euromaster France S.n.c.",
    "wof:placetype":"venue"
},
  "geometry": {"coordinates":[-0.443894,45.43932],"type":"Point"}
}