{
  "type": "Feature",
  "properties": {
    "addr:full":"10/14, Av. du G\u00e9n\u00e9ral Leclerc, 78230 Le Pecq Ile de France",
    "addr:housenumber":"10 / 14",
    "addr:postcode":"78230",
    "addr:street":"Av. Du Ge\u0301Ne\u0301Ral Leclerc",
    "iso:country":"FR",
    "sg:address":"10/14, Av. du G\u00e9n\u00e9ral Leclerc, 78230 Le Pecq",
    "sg:orig_category":"Unclassifiable Establishments",
    "sg:phone":"+33 1 39 16 34 00",
    "sg:province":"Ile de France",
    "wof:name":"Toner Services F.r. S.a.r.l.",
    "wof:placetype":"venue"
},
  "geometry": {"coordinates":[2.09858,48.886902],"type":"Point"}
}