{
  "type": "Feature",
  "properties": {
    "iso:country":"FR",
    "sg:address":"88 Rue L\u00e9on Blum 02830 St Michel",
    "sg:classifiers":[
        {
            "category":"Government",
            "subcategory":"Department Of Motor Vehicles",
            "type":"Public Place"
        }
    ],
    "sg:phone":"+33 3 23 58 86 00",
    "sg:postcode":"02830",
    "sg:province":"Picardie",
    "sg:tags":[
        "equipment",
        "industrial",
        "transport",
        "motor-cars"
    ],
    "wof:name":"Compagnie Industrielle De Laisne Sarl",
    "wof:placetype":"venue"
},
  "geometry": {"coordinates":[4.13307,49.917599],"type":"Point"}
}