{
  "type": "Feature",
  "properties": {
    "addr:full":"1, Rue de l'Etoile du Matin, 44600 Saint Nazaire Pays de Loire",
    "addr:housenumber":"1",
    "addr:postcode":"44600",
    "addr:street":"Rue De L'Etoile Du Matin;Nazaire",
    "iso:country":"FR",
    "sg:address":"1, Rue de l'Etoile du Matin, 44600 Saint Nazaire",
    "sg:orig_category":"Unclassifiable Establishments",
    "sg:phone":"+33 2 40 53 08 08",
    "sg:province":"Pays de Loire",
    "wof:name":"Polygone S.a.",
    "wof:placetype":"venue"
},
  "geometry": {"coordinates":[-2.273627,47.260258],"type":"Point"}
}