{
  "type": "Feature",
  "properties": {
    "addr:full":"Parc les Algorithmes Saint Aubin Ile de France 91190",
    "addr:postcode":"91190",
    "addr:street":"Saint",
    "iso:country":"FR",
    "sg:address":"Parc les Algorithmes",
    "sg:city":"Saint Aubin",
    "sg:orig_category":"Unclassifiable Establishments",
    "sg:phone":"+33 1 69 35 37 60",
    "sg:postcode":"91190",
    "sg:province":"Ile de France",
    "wof:name":"Keeboo France S.a.r.l.",
    "wof:placetype":"venue"
},
  "geometry": {"coordinates":[2.151245,48.70945],"type":"Point"}
}