{
  "type": "Feature",
  "properties": {
    "iso:country":"FR",
    "sg:address":"Rue Jean Queillau Marche Des Arnavaux 712 13323 Marseille Cedex 14",
    "sg:classifiers":[
        {
            "category":"Professional",
            "subcategory":"Engineering",
            "type":"Services"
        }
    ],
    "sg:phone":"+33 4 91 21 42 14",
    "sg:province":"Poitou-Charentes",
    "sg:tags":[
        "machine",
        "-",
        "environment",
        "equipment",
        "machinery",
        "mechanical"
    ],
    "wof:name":"Gammaster Provence",
    "wof:placetype":"venue"
},
  "geometry": {"coordinates":[5.39137,43.340919],"type":"Point"}
}