{
  "type": "Feature",
  "properties": {
    "iso:country":"FR",
    "sg:address":"Parc d'Activit\u00e9 du Gaillec",
    "sg:city":"Ploemeur",
    "sg:orig_category":"Unclassifiable Establishments",
    "sg:phone":"+33 2 97 83 56 06",
    "sg:postcode":"56270",
    "sg:province":"Bretagne",
    "wof:name":"Soci\u00e9t\u00e9 D'etude Et De D\u00e9veloppement De La Productique S.a.",
    "wof:placetype":"venue"
},
  "geometry": {"coordinates":[-3.44665,47.73111],"type":"Point"}
}