{
  "type": "Feature",
  "properties": {
    "addr:full":"28 A, Rue Edouard Branly, 68000 Colmar Colmar Alsace 68000",
    "addr:housenumber":"28 a",
    "addr:postcode":"68000;68000",
    "addr:street":"Rue Edouard Branly",
    "iso:country":"FR",
    "sg:address":"28 A, Rue Edouard Branly, 68000 Colmar",
    "sg:city":"Colmar",
    "sg:orig_category":"Unclassifiable Establishments",
    "sg:phone":"+33 3 89 23 86 50",
    "sg:postcode":"68000",
    "sg:province":"Alsace",
    "wof:name":"Eurameca S.a.",
    "wof:placetype":"venue"
},
  "geometry": {"coordinates":[7.380306,48.094769],"type":"Point"}
}