{
  "type": "Feature",
  "properties": {
    "addr:full":"B.P. 79, 59302 Valenciennes C\u00e9dex^^8, Rue du Petit Bruxelles, 59300 Valenciennes Nord Pas-de-Calais",
    "addr:postcode":"59302;59300",
    "addr:street":"B.P. 79;Rue Du Petit Bruxelles",
    "iso:country":"FR",
    "sg:address":"B.P. 79, 59302 Valenciennes C\u00e9dex^^8, Rue du Petit Bruxelles, 59300 Valenciennes",
    "sg:orig_category":"Non-Classified Establishments",
    "sg:phone":"+33 3 27 20 09 09",
    "sg:province":"Nord Pas-de-Calais",
    "wof:name":"Soufflet Alimentaire S.a.",
    "wof:placetype":"venue"
},
  "geometry": {"coordinates":[3.524105,50.358494],"type":"Point"}
}