{
  "type": "Feature",
  "properties": {
    "iso:country":"FR",
    "sg:address":"12, Rue Jean Monnet - Parc d'Activit\u00e9, 67200 Strasbourg",
    "sg:city":"Strasbourg",
    "sg:orig_category":"Unclassifiable Establishments",
    "sg:phone":"+33 3 88 76 57 04",
    "sg:postcode":"67200",
    "sg:province":"Alsace",
    "wof:name":"Rhin Climatisation S.a.",
    "wof:placetype":"venue"
},
  "geometry": {"coordinates":[7.758282,48.605492],"type":"Point"}
}