{
  "type": "Feature",
  "properties": {
    "addr:full":"B.P. 113, 27501 Pont Audemer C\u00e9dex^^8, Rue du 8 Mai 1945, 27500 Pont Audemer Haute Normandie",
    "addr:housenumber":"b.p. 113",
    "addr:postcode":"27501;27500",
    "addr:street":"Audemer;Rue Du 8 Mai 1945;Audemer Haute Normandie",
    "iso:country":"FR",
    "sg:address":"B.P. 113, 27501 Pont Audemer C\u00e9dex^^8, Rue du 8 Mai 1945, 27500 Pont Audemer",
    "sg:orig_category":"Non-Classified Establishments",
    "sg:phone":"+33 2 32 41 13 21",
    "sg:province":"Haute Normandie",
    "wof:name":"Nor-stick S.a.",
    "wof:placetype":"venue"
},
  "geometry": {"coordinates":[0.5067,49.300587],"type":"Point"}
}