{
  "type": "Feature",
  "properties": {
    "addr:full":"Zi De Plaisance 16300 Barbezieux St Hilaire Poitou-Charentes",
    "addr:postcode":"16300",
    "addr:street":"Zi De Plaisance;St Hilaire",
    "iso:country":"FR",
    "sg:address":"Zi De Plaisance 16300 Barbezieux St Hilaire",
    "sg:classifiers":[
        {
            "category":"Manufacturing",
            "subcategory":"Rubber & Plastics",
            "type":"Manufacturing & Wholesale Goods"
        }
    ],
    "sg:phone":"+33 5 45 78 09 22",
    "sg:province":"Poitou-Charentes",
    "sg:tags":[
        "packaging",
        "material",
        "-"
    ],
    "wof:name":"Plastiques Venthenat",
    "wof:placetype":"venue"
},
  "geometry": {"coordinates":[-0.155134,45.47094],"type":"Point"}
}