{
  "type": "Feature",
  "properties": {
    "addr:full":"115 boulevard de Paris 83200 Toulon Centre",
    "addr:housenumber":"115",
    "addr:postcode":"83200",
    "addr:street":"Boulevard De Paris",
    "iso:country":"FR",
    "sg:address":"115 boulevard de Paris 83200 Toulon",
    "sg:classifiers":[
        {
            "category":"Building & Trades",
            "subcategory":"Electrical",
            "type":"Services"
        }
    ],
    "sg:phone":"+33 4 94 89 96 00",
    "sg:province":"Centre",
    "sg:tags":[
        "commerce",
        "mining",
        "chain",
        "industry",
        "accessory",
        "forestry",
        "shipbuilding"
    ],
    "wof:name":"Roulement Service Sa",
    "wof:placetype":"venue"
},
  "geometry": {"coordinates":[5.908446,43.129967],"type":"Point"}
}