{
  "type": "Feature",
  "properties": {
    "addr:full":"B.P. 57000, 13792 Aix en Provence C\u00e9dex 03^^140, Rue Georges Claude, 13790 Aix en Provence Lorraine",
    "addr:housenumber":"13792;03 ^ ^ 140",
    "addr:postcode":"13790",
    "addr:street":"Ce\u0301Dex;Rue Georges Claude",
    "iso:country":"FR",
    "sg:address":"B.P. 57000, 13792 Aix en Provence C\u00e9dex 03^^140, Rue Georges Claude, 13790 Aix en Provence",
    "sg:orig_category":"Non-Classified Establishments",
    "sg:phone":"+33 4 42 39 34 40",
    "sg:province":"Lorraine",
    "wof:name":"Jean Lefebvre M\u00e9diterran\u00e9e S.a.",
    "wof:placetype":"venue"
},
  "geometry": {"coordinates":[5.63957,43.446781],"type":"Point"}
}