{
  "type": "Feature",
  "properties": {
    "iso:country":"FR",
    "sg:address":"Av. de Verdun",
    "sg:city":"Flers",
    "sg:orig_category":"Unclassifiable Establishments",
    "sg:phone":"+33 2 33 65 83 22",
    "sg:postcode":"61100",
    "sg:province":"Basse Normandie",
    "wof:name":"Lecois S.a.r.l.",
    "wof:placetype":"venue"
},
  "geometry": {"coordinates":[-0.55883,48.74485],"type":"Point"}
}