{
  "type": "Feature",
  "properties": {
    "iso:country":"FR",
    "sg:address":"21 rue Georges Cl\u00e9menceau; La Bernerie",
    "sg:classifiers":[
        {
            "category":"Banks & Credit Unions",
            "subcategory":"Bank",
            "type":"Services"
        }
    ],
    "sg:phone":"+33 3340827603",
    "sg:province":"Bretagne",
    "wof:name":"Caisse R\u00e9gionale De Cr\u00e9dit, Agricole Mutuel",
    "wof:placetype":"venue"
},
  "geometry": {"coordinates":[-2.041457,47.084057],"type":"Point"}
}