{
  "type": "Feature",
  "properties": {
    "iso:country":"FR",
    "sg:address":"B.P. 523, 78535 Buc C\u00e9dex^^153, Rue de Fourny, 78530 Buc",
    "sg:orig_category":"Non-Classified Establishments",
    "sg:phone":"+33 1 30 83 92 92",
    "sg:province":"Ile de France",
    "wof:name":"Soci\u00e9t\u00e9 Matech Electronique S.a.",
    "wof:placetype":"venue"
},
  "geometry": {"coordinates":[2.126343,48.774464],"type":"Point"}
}