{
  "type": "Feature",
  "properties": {
    "addr:full":"1, Rte de Mardyck - PAE du Pont de Spycker, 59380 Spycker Nord Pas-de-Calais",
    "addr:housenumber":"1",
    "addr:postcode":"59380",
    "addr:street":"Rte De Mardyck Pae Du;De Spycker",
    "iso:country":"FR",
    "sg:address":"1, Rte de Mardyck - PAE du Pont de Spycker, 59380 Spycker",
    "sg:orig_category":"Unclassifiable Establishments",
    "sg:phone":"+33 3 28 28 90 00",
    "sg:province":"Nord Pas-de-Calais",
    "wof:name":"Schoonberg S.a.",
    "wof:placetype":"venue"
},
  "geometry": {"coordinates":[2.493145,50.976814],"type":"Point"}
}