{
  "type": "Feature",
  "properties": {
    "addr:full":"Rte de Bellevue Vorey Auvergne 43800",
    "addr:postcode":"43800",
    "addr:street":"Rte De Bellevue Vorey",
    "iso:country":"FR",
    "sg:address":"Rte de Bellevue",
    "sg:city":"Vorey",
    "sg:orig_category":"Unclassifiable Establishments",
    "sg:phone":"+33 4 71 03 40 46",
    "sg:postcode":"43800",
    "sg:province":"Auvergne",
    "wof:name":"S.p.c.v. S.a. - Silicones Plastiques Caoutchouc Vor\u00e9ziens",
    "wof:placetype":"venue"
},
  "geometry": {"coordinates":[3.967025,45.099289],"type":"Point"}
}