{
  "type": "Feature",
  "properties": {
    "addr:full":"Rte de Sill\u00e9 Voutr\u00e9 Pays de Loire 53600",
    "addr:postcode":"53600",
    "addr:street":"Rte De Sille\u0301 Voutre\u0301 Pays",
    "iso:country":"FR",
    "sg:address":"Rte de Sill\u00e9",
    "sg:city":"Voutr\u00e9",
    "sg:orig_category":"Non-Classified Establishments",
    "sg:phone":"+33 2 43 01 53 00",
    "sg:postcode":"53600",
    "sg:province":"Pays de Loire",
    "wof:name":"Soci\u00e9t\u00e9 Des Carri\u00e8res De Voutr\u00e9 S.a.",
    "wof:placetype":"venue"
},
  "geometry": {"coordinates":[-0.432901,48.132961],"type":"Point"}
}