{
  "type": "Feature",
  "properties": {
    "addr:full":"ZA de l'Ile Neuve 26600 La Roche de Glun Rhone-Alpes 26600",
    "addr:postcode":"26600;26600",
    "addr:street":"Za De L'Ile Neuve",
    "iso:country":"FR",
    "sg:address":"ZA de l'Ile Neuve 26600 La Roche de Glun",
    "sg:classifiers":[
        {
            "category":"Utilities",
            "subcategory":"Electric",
            "type":"Services"
        }
    ],
    "sg:phone":"+33 4 75 84 56 83",
    "sg:postcode":"26600",
    "sg:province":"Rhone-Alpes",
    "sg:tags":[
        "drive"
    ],
    "wof:name":"S.o.t.e.l.i.c. S.a.r.l.",
    "wof:placetype":"venue"
},
  "geometry": {"coordinates":[4.84854,45.01276],"type":"Point"}
}