{
  "type": "Feature",
  "properties": {
    "iso:country":"FR",
    "sg:address":"18 Rue Des Alli\u00e8res 43110 Aurec Sur Loire",
    "sg:city":"Aurec-sur-Loire",
    "sg:classifiers":[
        {
            "category":"Health Services",
            "subcategory":"Medical Lab",
            "type":"Services"
        }
    ],
    "sg:phone":"+33 4 77 35 45 76",
    "sg:postcode":"43110",
    "sg:province":"Auvergne",
    "sg:tags":[
        "chemical",
        "pharmaceutical",
        "pharmacy"
    ],
    "wof:name":"Phymed",
    "wof:placetype":"venue"
},
  "geometry": {"coordinates":[4.20126,45.3685],"type":"Point"}
}