{
  "type": "Feature",
  "properties": {
    "iso:country":"FR",
    "sg:address":"Za La Mare Aux Loups 27240 Damville",
    "sg:classifiers":[
        {
            "category":"Manufacturing",
            "subcategory":"Leather Goods",
            "type":"Manufacturing & Wholesale Goods"
        }
    ],
    "sg:phone":"+33 2 32 34 41 32",
    "sg:postcode":"27240",
    "sg:province":"Haute Normandie",
    "sg:tags":[
        "shoe"
    ],
    "wof:name":"Maroquinerie Suzanne",
    "wof:placetype":"venue"
},
  "geometry": {"coordinates":[1.074465,48.870255],"type":"Point"}
}