{
  "type": "Feature",
  "properties": {
    "addr:full":"76 Ch Du Sillon 35400 St Malo Saint-Malo Bretagne 35400",
    "addr:housenumber":"76",
    "addr:postcode":"35400;35400",
    "addr:street":"Ch Du Sillon;Saint-Malo Bretagne",
    "iso:country":"FR",
    "sg:address":"76 Ch Du Sillon 35400 St Malo",
    "sg:city":"Saint-Malo",
    "sg:classifiers":[
        {
            "category":"Travel",
            "subcategory":"Hotels & Motels",
            "type":"Entertainment"
        }
    ],
    "sg:phone":"+33 2 99 40 36 36",
    "sg:postcode":"35400",
    "sg:province":"Bretagne",
    "sg:tags":[
        "hotels",
        "business",
        "restaurant"
    ],
    "wof:name":"Hotel Mascotte",
    "wof:placetype":"venue"
},
  "geometry": {"coordinates":[-2.008545,48.654316],"type":"Point"}
}