{
  "type": "Feature",
  "properties": {
    "addr:full":"52, Rue Frohnacker, 67250 Soultz sous For\u00eats Aschbach Alsace 67250",
    "addr:housenumber":"52",
    "addr:postcode":"67250;67250",
    "addr:street":"Rue Frohnacker;Fore\u0302Ts Aschbach",
    "iso:country":"FR",
    "sg:address":"52, Rue Frohnacker, 67250 Soultz sous For\u00eats",
    "sg:city":"Aschbach",
    "sg:orig_category":"AFF\u00dbTAGE INDUSTRIEL N\u00c9GOCIANT: N\u00c9GOCE DE LAMES DE TRON\u00c7ONNAGE POUR ACIER",
    "sg:phone":"+33 3 88 80 41 52",
    "sg:postcode":"67250",
    "sg:province":"Alsace",
    "wof:name":"Zyto S.a.r.l.",
    "wof:placetype":"venue"
},
  "geometry": {"coordinates":[7.88944,48.935421],"type":"Point"}
}