{
  "type": "Feature",
  "properties": {
    "iso:country":"FR",
    "sg:address":"La Plaine 11390 Cuxac Cabard\u00e8s",
    "sg:classifiers":[
        {
            "category":"Manufacturing",
            "subcategory":"Chemicals & Compounds",
            "type":"Manufacturing & Wholesale Goods"
        }
    ],
    "sg:phone":"+33 4 68 26 57 08",
    "sg:postcode":"11390",
    "sg:province":"Languedoc-Roussillon",
    "sg:tags":[
        "pharmaceutical",
        "chemistry",
        "-",
        "by-product"
    ],
    "wof:name":"Titanite Sa",
    "wof:placetype":"venue"
},
  "geometry": {"coordinates":[2.281543,43.369141],"type":"Point"}
}