{
  "type": "Feature",
  "properties": {
    "iso:country":"FR",
    "sg:address":"B.P. 6810, 87068 Limoges C\u00e9dex^^5, All\u00e9e Skylab - Parc Esther, 87000 Limoges",
    "sg:orig_category":"Non-Classified Establishments",
    "sg:phone":"+33 5 55 37 04 90",
    "sg:province":"Limousin",
    "wof:name":"Sorevi S.a.",
    "wof:placetype":"venue"
},
  "geometry": {"coordinates":[1.26201,45.828785],"type":"Point"}
}