{
  "type": "Feature",
  "properties": {
    "iso:country":"FR",
    "sg:address":"1 Rue Gustave Courbet 56017 Vannes Cedex",
    "sg:classifiers":[
        {
            "category":"Professional",
            "subcategory":"Business Services",
            "type":"Services"
        }
    ],
    "sg:phone":"+33 2 97 63 28 54",
    "sg:province":"Franche Comt\u00e9",
    "sg:tags":[
        "training",
        "advice"
    ],
    "wof:name":"College Antoine De Saint Exupery",
    "wof:placetype":"venue"
},
  "geometry": {"coordinates":[-2.770913,47.675491],"type":"Point"}
}