{
  "type": "Feature",
  "properties": {
    "iso:country":"FR",
    "sg:address":"6, Rue du Poilu, 02390 Origny Sainte Beno\u00eete",
    "sg:orig_category":"Unclassifiable Establishments",
    "sg:phone":"+33 3 23 09 73 53",
    "sg:province":"Picardie",
    "wof:name":"Rouche Poyart S.a.r.l.",
    "wof:placetype":"venue"
},
  "geometry": {"coordinates":[3.489285,49.837132],"type":"Point"}
}