{
  "type": "Feature",
  "properties": {
    "addr:full":"57, Rue Savoie, 69170 Tarare Rhone-Alpes 69170",
    "addr:housenumber":"57",
    "addr:postcode":"69170;69170",
    "addr:street":"Rue Savoie",
    "iso:country":"FR",
    "sg:address":"57, Rue Savoie, 69170 Tarare",
    "sg:orig_category":"Non-Classified Establishments",
    "sg:phone":"+33 4 74 63 18 85",
    "sg:postcode":"69170",
    "sg:province":"Rhone-Alpes",
    "wof:name":"Amalvy Roland",
    "wof:placetype":"venue"
},
  "geometry": {"coordinates":[4.435448,45.892422],"type":"Point"}
}