{
  "type": "Feature",
  "properties": {
    "iso:country":"FR",
    "sg:address":"B.P. 4, 07700 Bourg Saint And\u00e9ol^^Quartier Les Mures, 07700 Bourg Saint And\u00e9ol",
    "sg:orig_category":"Non-Classified Establishments",
    "sg:phone":"+33 4 75 54 77 22",
    "sg:province":"Rhone-Alpes",
    "wof:name":"S.l.d.b. S.a. - Salavert Les Domaines Bernard",
    "wof:placetype":"venue"
},
  "geometry": {"coordinates":[4.64433,44.371861],"type":"Point"}
}