{
  "type": "Feature",
  "properties": {
    "iso:country":"FR",
    "sg:address":"Rue Emile Deshaies",
    "sg:city":"Louvign\u00e9 du D\u00e9sert",
    "sg:orig_category":"Unclassifiable Establishments",
    "sg:phone":"+33 2 99 98 02 70",
    "sg:postcode":"35420",
    "sg:province":"Bretagne",
    "wof:name":"Guyomarc'h Pays D'ouest S.n.c.",
    "wof:placetype":"venue"
},
  "geometry": {"coordinates":[-1.131254,48.483131],"type":"Point"}
}