{
  "type": "Feature",
  "properties": {
    "iso:country":"FR",
    "sg:address":"149 Rue De Grenelle 75007 Paris",
    "sg:classifiers":[
        {
            "category":"Professional",
            "subcategory":"Business Services",
            "type":"Services"
        }
    ],
    "sg:phone":"+33 1 40 62 89 89",
    "sg:postcode":"75007",
    "sg:province":"Ile de France",
    "sg:tags":[
        "body",
        "advice"
    ],
    "wof:name":"Gic",
    "wof:placetype":"venue"
},
  "geometry": {"coordinates":[2.307899,48.857891],"type":"Point"}
}