{
  "type": "Feature",
  "properties": {
    "iso:country":"FR",
    "sg:address":"B.P. 510, 19106 Brive la Gaillarde C\u00e9dex^^Av. Adrien Allard, 19106 Brive la Gaillarde",
    "sg:city":"Gaillard",
    "sg:orig_category":"Non-Classified Establishments",
    "sg:phone":"+33 5 55 87 90 21",
    "sg:postcode":"74240",
    "sg:province":"Rhone-Alpes",
    "wof:name":"Allard S.a.",
    "wof:placetype":"venue"
},
  "geometry": {"coordinates":[0.85753,49.836731],"type":"Point"}
}