{
  "type": "Feature",
  "properties": {
    "iso:country":"FR",
    "sg:address":"9, Rue de la Chauss\u00e9e Romaine - ZA Lavall\u00e9e, 02100 Saint Quentin",
    "sg:orig_category":"Unclassifiable Establishments",
    "sg:phone":"+33 3 23 06 24 25",
    "sg:province":"Picardie",
    "wof:name":"Apegelec Industries S.a.",
    "wof:placetype":"venue"
},
  "geometry": {"coordinates":[3.291399,49.850842],"type":"Point"}
}