{
  "type": "Feature",
  "properties": {
    "iso:country":"FR",
    "sg:address":"38 Rue Pierre Lat\u00e9co\u00e8re 26000 Valence",
    "sg:classifiers":[
        {
            "category":"Professional",
            "subcategory":"Engineering",
            "type":"Services"
        }
    ],
    "sg:phone":"+33 4 75 56 07 07",
    "sg:postcode":"26000",
    "sg:province":"Rhone-Alpes",
    "sg:tags":[
        "machine",
        "-",
        "mechanical"
    ],
    "wof:name":"Entreprise Sallee",
    "wof:placetype":"venue"
},
  "geometry": {"coordinates":[4.922186,44.923409],"type":"Point"}
}