{
  "type": "Feature",
  "properties": {
    "addr:full":"185bis, Rue Victor Hugo, 59100 Roubaix Nord Pas-de-Calais",
    "addr:housenumber":"185bis",
    "addr:postcode":"59100",
    "addr:street":"Rue Victor Hugo",
    "iso:country":"FR",
    "sg:address":"185bis, Rue Victor Hugo, 59100 Roubaix",
    "sg:orig_category":"Unclassifiable Establishments",
    "sg:phone":"+33 3 20 82 34 51",
    "sg:province":"Nord Pas-de-Calais",
    "wof:name":"Lecomte S.a.",
    "wof:placetype":"venue"
},
  "geometry": {"coordinates":[3.198446,50.685646],"type":"Point"}
}