{
  "type": "Feature",
  "properties": {
    "addr:full":"18, Chemin du Parc, 31150 Brugui\u00e8res Midi Pyr\u00e9n\u00e9es",
    "addr:housenumber":"18",
    "addr:postcode":"31150",
    "addr:street":"Chemin Du Parc",
    "iso:country":"FR",
    "sg:address":"18, Chemin du Parc, 31150 Brugui\u00e8res",
    "sg:orig_category":"Non-Classified Establishments",
    "sg:phone":"+33 5 56 47 93 62",
    "sg:province":"Midi Pyr\u00e9n\u00e9es",
    "wof:name":"Recall Syndarchives",
    "wof:placetype":"venue"
},
  "geometry": {"coordinates":[1.395013,43.714703],"type":"Point"}
}