{
  "type": "Feature",
  "properties": {
    "addr:full":"Rue de M\u00e2con 01090 MONTMERLE SUR SAONE Rhone-Alpes 01090",
    "addr:postcode":"01090;01090",
    "addr:street":"Rue De Ma\u0302Con",
    "iso:country":"FR",
    "sg:address":"Rue de M\u00e2con 01090 MONTMERLE SUR SAONE",
    "sg:classifiers":[
        {
            "category":"Professional",
            "subcategory":"Advertising",
            "type":"Services"
        }
    ],
    "sg:phone":"+33 4 74 69 31 21",
    "sg:postcode":"01090",
    "sg:province":"Rhone-Alpes",
    "sg:tags":[
        "article",
        "plastic"
    ],
    "wof:name":"S.i.p. Sarl",
    "wof:placetype":"venue"
},
  "geometry": {"coordinates":[4.753212,46.084641],"type":"Point"}
}