{
  "type": "Feature",
  "properties": {
    "addr:full":"33 Rue B\u00e9zot 75014 Paris Ile de France",
    "addr:housenumber":"33",
    "addr:postcode":"75014",
    "addr:street":"Rue Be\u0301Zot",
    "iso:country":"FR",
    "sg:address":"33 Rue B\u00e9zot 75014 Paris",
    "sg:classifiers":[
        {
            "category":"Utilities",
            "subcategory":"Telephone",
            "type":"Services"
        }
    ],
    "sg:phone":"+33 1 43 27 54 34",
    "sg:province":"Ile de France",
    "sg:tags":[
        "telecommunication"
    ],
    "wof:name":"Sodivel Sarl",
    "wof:placetype":"venue"
},
  "geometry": {"coordinates":[2.329857,48.828766],"type":"Point"}
}