{
  "type": "Feature",
  "properties": {
    "iso:country":"FR",
    "sg:address":"B.P. 618, 57146 Woippy C\u00e9dex^^34, Rte de Thionville, 57140 Woippy",
    "sg:orig_category":"Non-Classified Establishments",
    "sg:phone":"+33 3 87 31 02 66",
    "sg:postcode":"57140",
    "sg:province":"Lorraine",
    "wof:name":"Cedeo S.a.",
    "wof:placetype":"venue"
},
  "geometry": {"coordinates":[6.150305,49.15131],"type":"Point"}
}