{
  "type": "Feature",
  "properties": {
    "addr:full":"B.P. 7024, 69342 Lyon C\u00e9dex 7^^6, Rue d'Avignon - Port Herriot, 69007 Lyon Rhone-Alpes 69007",
    "addr:housenumber":"69342;7 ^ ^ 6",
    "addr:postcode":"69007;69007",
    "addr:street":"B.P. 7024;Ce\u0301Dex;Rue D'Avignon Port Herriot",
    "iso:country":"FR",
    "sg:address":"B.P. 7024, 69342 Lyon C\u00e9dex 7^^6, Rue d'Avignon - Port Herriot, 69007 Lyon",
    "sg:orig_category":"Non-Classified Establishments",
    "sg:phone":"+33 4 78 58 24 24",
    "sg:postcode":"69007",
    "sg:province":"Rhone-Alpes",
    "wof:name":"E.m.2.s. S.a.",
    "wof:placetype":"venue"
},
  "geometry": {"coordinates":[4.829679,45.714104],"type":"Point"}
}