{
  "type": "Feature",
  "properties": {
    "iso:country":"FR",
    "sg:address":"Les Fontaines Douces 58260 La Machine",
    "sg:city":"La Machine",
    "sg:orig_category":"Non-Classified Establishments",
    "sg:phone":"+33 3 86 50 82 12",
    "sg:postcode":"58260",
    "sg:province":"Bourgogne",
    "wof:name":"Cascade France S.a.r.l.",
    "wof:placetype":"venue"
},
  "geometry": {"coordinates":[3.465241,46.889523],"type":"Point"}
}