{
  "type": "Feature",
  "properties": {
    "iso:country":"FR",
    "sg:address":"4, Rue de Belfort, 68990 Heimsbrunn",
    "sg:city":"Heimsbrunn",
    "sg:orig_category":"Unclassifiable Establishments",
    "sg:phone":"+33 3 89 81 90 50",
    "sg:postcode":"68990",
    "sg:province":"Alsace",
    "wof:name":"Serafini S.a.r.l.",
    "wof:placetype":"venue"
},
  "geometry": {"coordinates":[7.227383,47.72887],"type":"Point"}
}