{
  "type": "Feature",
  "properties": {
    "addr:full":"B.P. 20, 77590 Bois le Roi C\u00e9dex^^Rue des Peupliers - ZA, 77590 Bois le Roi Ile de France 77590",
    "addr:postcode":"77590;77590;77590",
    "addr:street":"B.P. 20;Bois Le Roi Ce\u0301Dex^^Rue Des Peupliers Za;Bois Le Roi Ile De France",
    "iso:country":"FR",
    "sg:address":"B.P. 20, 77590 Bois le Roi C\u00e9dex^^Rue des Peupliers - ZA, 77590 Bois le Roi",
    "sg:orig_category":"Non-Classified Establishments",
    "sg:phone":"+33 1 60 69 54 09",
    "sg:postcode":"77590",
    "sg:province":"Ile de France",
    "wof:name":"Etablissements Barot S.a.r.l.",
    "wof:placetype":"venue"
},
  "geometry": {"coordinates":[2.702982,48.462391],"type":"Point"}
}