{
  "type": "Feature",
  "properties": {
    "iso:country":"FR",
    "sg:address":"49, Chemin Chapelle Saint Antoine, 95300 Ennery",
    "sg:orig_category":"Non-Classified Establishments",
    "sg:phone":"+33 1 30 31 30 45",
    "sg:province":"Ile de France",
    "wof:name":"S.i.d.a.c. S.a.r.l. - Soci\u00e9t\u00e9 Industrielle Pour Le D\u00e9veloppement De L'anti-pollution Et De La Chimie",
    "wof:placetype":"venue"
},
  "geometry": {"coordinates":[2.112366,49.067108],"type":"Point"}
}