{
  "type": "Feature",
  "properties": {
    "iso:country":"FR",
    "sg:address":"All\u00e9e Yves Stourdze",
    "sg:city":"Clapiers",
    "sg:orig_category":"Unclassifiable Establishments",
    "sg:phone":"+33 4 67 14 44 44",
    "sg:postcode":"34830",
    "sg:province":"Languedoc-Roussillon",
    "wof:name":"Institut De L'audiovisuel Des T\u00e9l\u00e9communications En Europe",
    "wof:placetype":"venue"
},
  "geometry": {"coordinates":[3.896502,43.649994],"type":"Point"}
}