{
  "type": "Feature",
  "properties": {
    "iso:country":"FR",
    "sg:address":"La Cri\u00e9e 44420 La Turballe",
    "sg:orig_category":"Non-Classified Establishments",
    "sg:phone":"+33 2 40 23 38 90",
    "sg:province":"Pays de Loire",
    "wof:name":"Scoma Production",
    "wof:placetype":"venue"
},
  "geometry": {"coordinates":[-2.512269,47.348259],"type":"Point"}
}