{
  "type": "Feature",
  "properties": {
    "addr:full":"B.P. 1028, 78202 Mantes la Jolie C\u00e9dex^^All\u00e9e des Maronniers, 78200 Mantes la Jolie Ile de France 78200",
    "addr:postcode":"78202;78200;france 78200",
    "addr:street":"B.P. 1028",
    "iso:country":"FR",
    "sg:address":"B.P. 1028, 78202 Mantes la Jolie C\u00e9dex^^All\u00e9e des Maronniers, 78200 Mantes la Jolie",
    "sg:orig_category":"Non-Classified Establishments",
    "sg:phone":"+33 1 34 79 40 00",
    "sg:postcode":"78200",
    "sg:province":"Ile de France",
    "wof:name":"Dunlopillo S.a.",
    "wof:placetype":"venue"
},
  "geometry": {"coordinates":[1.714715,48.989491],"type":"Point"}
}