{
  "type": "Feature",
  "properties": {
    "addr:full":"4, Rue du Clos Saint Yon, 76530 Grand Couronne Haute Normandie",
    "addr:housenumber":"4;76530",
    "addr:street":"Rue Du Clos Saint Yon;Grand Couronne Haute Normandie",
    "iso:country":"FR",
    "sg:address":"4, Rue du Clos Saint Yon, 76530 Grand Couronne",
    "sg:orig_category":"Unclassifiable Establishments",
    "sg:phone":"+33 2 35 69 06 12",
    "sg:province":"Haute Normandie",
    "wof:name":"Sojep S.a.r.l.",
    "wof:placetype":"venue"
},
  "geometry": {"coordinates":[1.019018,49.341064],"type":"Point"}
}