{
  "type": "Feature",
  "properties": {
    "addr:full":"53, Rue Edmond Rostand, 02100 Saint Quentin Picardie",
    "addr:housenumber":"53",
    "addr:postcode":"02100",
    "addr:street":"Rue Edmond Rostand",
    "iso:country":"FR",
    "sg:address":"53, Rue Edmond Rostand, 02100 Saint Quentin",
    "sg:orig_category":"Non-Classified Establishments",
    "sg:phone":"+33 3 23 08 16 30",
    "sg:province":"Picardie",
    "wof:name":"M3c Courtois S.a.r.l.",
    "wof:placetype":"venue"
},
  "geometry": {"coordinates":[3.291962,49.855923],"type":"Point"}
}