{
  "type": "Feature",
  "properties": {
    "iso:country":"FR",
    "sg:address":"57 Rue Principale 67310 Traenheim",
    "sg:city":"Traenheim",
    "sg:classifiers":[
        {
            "category":"Food Court",
            "type":"Food & Drink"
        }
    ],
    "sg:phone":"+33 3 88 50 38 07",
    "sg:postcode":"67310",
    "sg:province":"Alsace",
    "sg:tags":[
        "product",
        "related"
    ],
    "wof:name":"Societe A Responsabilite Limitee Jus De Fruits Rothgerber",
    "wof:placetype":"venue"
},
  "geometry": {"coordinates":[7.466493,48.594765],"type":"Point"}
}