{
  "type": "Feature",
  "properties": {
    "addr:full":"2 rue Jean Bertin 26000 Valence Rhone-Alpes 26000",
    "addr:housenumber":"2",
    "addr:postcode":"26000;26000",
    "addr:street":"Rue Jean Bertin",
    "iso:country":"FR",
    "sg:address":"2 rue Jean Bertin 26000 Valence",
    "sg:orig_category":"Fittings, Valves",
    "sg:phone":"+33 4 75 82 07 07",
    "sg:postcode":"26000",
    "sg:province":"Rhone-Alpes",
    "wof:name":"Robinetterie Industrielle Valentinoise S.a.",
    "wof:placetype":"venue"
},
  "geometry": {"coordinates":[4.9138,44.914783],"type":"Point"}
}