{
  "type": "Feature",
  "properties": {
    "iso:country":"FR",
    "sg:address":"Route D Orleans 45600 Sully Sur Loire",
    "sg:city":"Guilly",
    "sg:classifiers":[
        {
            "category":"Manufacturing",
            "subcategory":"Rubber & Plastics",
            "type":"Manufacturing & Wholesale Goods"
        }
    ],
    "sg:phone":"+33 2 38 37 71 20",
    "sg:postcode":"45600",
    "sg:province":"Centre",
    "wof:name":"Wavin",
    "wof:placetype":"venue"
},
  "geometry": {"coordinates":[2.33401,47.685894],"type":"Point"}
}