{
  "type": "Feature",
  "properties": {
    "addr:full":"B.P. 4, 60401 Noyon C\u00e9dex^^5, Place de la R\u00e9publique, 60400 Noyon Picardie",
    "addr:housenumber":"4",
    "addr:postcode":"60401;60400",
    "addr:street":"B.P.;Ce\u0301Dex^^5 Place De La Re\u0301Publique",
    "iso:country":"FR",
    "sg:address":"B.P. 4, 60401 Noyon C\u00e9dex^^5, Place de la R\u00e9publique, 60400 Noyon",
    "sg:orig_category":"Non-Classified Establishments",
    "sg:phone":"+33 3 44 44 26 51",
    "sg:province":"Picardie",
    "wof:name":"Van Brabant Francis S.a.r.l.",
    "wof:placetype":"venue"
},
  "geometry": {"coordinates":[3.097817,49.48531],"type":"Point"}
}