{
  "type": "Feature",
  "properties": {
    "addr:full":"29, Rue Gay Lussac, 94120 Fontenay sous Bois Ile de France",
    "addr:housenumber":"29",
    "addr:postcode":"94120",
    "addr:street":"Rue Gay Lussac;Bois Ile De France",
    "iso:country":"FR",
    "sg:address":"29, Rue Gay Lussac, 94120 Fontenay sous Bois",
    "sg:orig_category":"Non-Classified Establishments",
    "sg:phone":"+33 1 48 75 17 17",
    "sg:province":"Ile de France",
    "wof:name":"S.i.d.e.s. S.a.r.l. - Soci\u00e9t\u00e9 Internationale De Diffusion Edition Scientifique",
    "wof:placetype":"venue"
},
  "geometry": {"coordinates":[2.469829,48.852852],"type":"Point"}
}