{
  "type": "Feature",
  "properties": {
    "iso:country":"FR",
    "sg:address":"58, Bd Gustave Roch, 44200 Nantes",
    "sg:orig_category":"Non-Classified Establishments",
    "sg:phone":"+33 2 40 08 01 70",
    "sg:province":"Pays de Loire",
    "wof:name":"Soci\u00e9t\u00e9 Nouvelle Scavo S.a.",
    "wof:placetype":"venue"
},
  "geometry": {"coordinates":[-1.555667,47.200958],"type":"Point"}
}