{
  "type": "Feature",
  "properties": {
    "iso:country":"FR",
    "sg:address":"12B, Rue de Ham, 57880 Ham sous Varsberg",
    "sg:orig_category":"Calorifugeage D\u00e9poussi\u00e9rage, Installations de D\u00e9poussi\u00e9reurs D\u00e9senfumage, Etudes et r\u00e9alisations de ",
    "sg:phone":"+33 3 87 93 71 11",
    "sg:postcode":"57880",
    "sg:province":"Lorraine",
    "wof:name":"Isocap S.a.r.l.",
    "wof:placetype":"venue"
},
  "geometry": {"coordinates":[6.662978,49.191956],"type":"Point"}
}