{
  "type": "Feature",
  "properties": {
    "addr:full":"B.P. 40, 75782 Paris C\u00e9dex 16^^61, Rue des Belles Feuilles, 75016 Paris Ile de France",
    "addr:housenumber":"16;^ 61",
    "addr:postcode":"75782;75016",
    "addr:street":"B.P. 40;^;Rue Des Belles Feuilles",
    "iso:country":"FR",
    "sg:address":"B.P. 40, 75782 Paris C\u00e9dex 16^^61, Rue des Belles Feuilles, 75016 Paris",
    "sg:orig_category":"Non-Classified Establishments",
    "sg:phone":"+33 1 44 34 11 11",
    "sg:province":"Ile de France",
    "wof:name":"Lafarge S.a.",
    "wof:placetype":"venue"
},
  "geometry": {"coordinates":[2.25657,48.857079],"type":"Point"}
}