{
  "type": "Feature",
  "properties": {
    "addr:full":"3, Rue de l'Angle, 67370 Dingsheim Dingsheim Alsace 67370",
    "addr:housenumber":"3",
    "addr:postcode":"67370;67370",
    "addr:street":"Rue De L'Angle",
    "iso:country":"FR",
    "sg:address":"3, Rue de l'Angle, 67370 Dingsheim",
    "sg:city":"Dingsheim",
    "sg:orig_category":"Unclassifiable Establishments",
    "sg:phone":"+33 3 88 56 20 59",
    "sg:postcode":"67370",
    "sg:province":"Alsace",
    "wof:name":"Wagner Publicit\u00e9 S.a.r.l.",
    "wof:placetype":"venue"
},
  "geometry": {"coordinates":[7.668889,48.630009],"type":"Point"}
}