{
  "type": "Feature",
  "properties": {
    "iso:country":"FR",
    "sg:address":"Quartier Bas 39270 Plaisia",
    "sg:classifiers":[
        {
            "category":"Manufacturing",
            "subcategory":"Metals",
            "type":"Manufacturing & Wholesale Goods"
        }
    ],
    "sg:phone":"+33 3 84 25 41 68",
    "sg:postcode":"39270",
    "sg:province":"Franche Comt\u00e9",
    "sg:tags":[
        "metallurgy",
        "metalworking",
        "processing"
    ],
    "wof:name":"Societe D'exploitation Des Etablissements Chevassu",
    "wof:placetype":"venue"
},
  "geometry": {"coordinates":[5.610467,46.52206],"type":"Point"}
}