{
  "type": "Feature",
  "properties": {
    "addr:full":"2 Rue Maccarani 06000 Nice Picardie",
    "addr:housenumber":"2",
    "addr:postcode":"06000",
    "addr:street":"Rue Maccarani",
    "iso:country":"FR",
    "sg:address":"2 Rue Maccarani 06000 Nice",
    "sg:classifiers":[
        {
            "category":"Food & Beverages",
            "subcategory":"Groceries & Convenience Stores",
            "type":"Retail Goods"
        }
    ],
    "sg:phone":"+33 4 93 87 61 86",
    "sg:province":"Picardie",
    "sg:tags":[
        "product",
        "related"
    ],
    "wof:name":"Calluaud Traiteur Sarl",
    "wof:placetype":"venue"
},
  "geometry": {"coordinates":[7.265184,43.697136],"type":"Point"}
}