{
  "type": "Feature",
  "properties": {
    "iso:country":"FR",
    "sg:address":"8, Rue Charles Brifaut, 21000 Dijon",
    "sg:city":"Dijon",
    "sg:orig_category":"Unclassifiable Establishments",
    "sg:phone":"+33 3 80 43 00 89",
    "sg:postcode":"21000",
    "sg:province":"Bourgogne",
    "wof:name":"Espace Graphique S.a.r.l.",
    "wof:placetype":"venue"
},
  "geometry": {"coordinates":[5.027419,47.325184],"type":"Point"}
}