{
  "type": "Feature",
  "properties": {
    "addr:full":"184 rue du G\u00e9n\u00e9ral; La Madeleine; 59110 Nord Pas-de-Calais 59110",
    "addr:housenumber":"184",
    "addr:postcode":"59110;59110",
    "addr:street":"Rue Du Ge\u0301Ne\u0301Ral La Madeleine",
    "iso:country":"FR",
    "sg:address":"184 rue du G\u00e9n\u00e9ral; La Madeleine; 59110",
    "sg:classifiers":[
        {
            "category":"Banks & Credit Unions",
            "subcategory":"Bank",
            "type":"Services"
        }
    ],
    "sg:phone":"+33 20554247",
    "sg:postcode":"59110",
    "sg:province":"Nord Pas-de-Calais",
    "wof:name":"Soci\u00e9t\u00e9 G\u00e9n\u00e9rale",
    "wof:placetype":"venue"
},
  "geometry": {"coordinates":[3.073995,50.655983],"type":"Point"}
}