{
  "type": "Feature",
  "properties": {
    "iso:country":"FR",
    "sg:address":"Zi Quest Rue Des Fr\u00e8res Chappe 72201 La Fl\u00e8che Cedex",
    "sg:city":"La Fl\u00e8che",
    "sg:classifiers":[
        {
            "category":"Professional",
            "subcategory":"Engineering",
            "type":"Services"
        }
    ],
    "sg:phone":"+33 2 43 45 98 13",
    "sg:postcode":"72200",
    "sg:province":"Pays de Loire",
    "sg:tags":[
        "machine",
        "-",
        "mechanical"
    ],
    "wof:name":"Mecanique De Precision Des Pays De Loire Sa",
    "wof:placetype":"venue"
},
  "geometry": {"coordinates":[-0.104549,47.708538],"type":"Point"}
}