{
  "type": "Feature",
  "properties": {
    "iso:country":"FR",
    "sg:address":"1, All\u00e9e des Peupliers, 33270 Floirac",
    "sg:city":"Floirac",
    "sg:orig_category":"Unclassifiable Establishments",
    "sg:phone":"+33 5 56 86 94 80",
    "sg:postcode":"33270",
    "sg:province":"Aquitaine",
    "wof:name":"Taxy S.a.",
    "wof:placetype":"venue"
},
  "geometry": {"coordinates":[-0.542349,44.840858],"type":"Point"}
}