{
  "type": "Feature",
  "properties": {
    "addr:full":"B.P. 112, 92203 Neuilly sur Seine C\u00e9dex^^175, Av. Achille P\u00e9retti, 92200 Neuilly sur Seine Ile de France 92200",
    "addr:housenumber":"b.p. 112",
    "addr:postcode":"92203;92200;92200",
    "addr:street":"Av. Achille Pe\u0301Retti",
    "iso:country":"FR",
    "sg:address":"B.P. 112, 92203 Neuilly sur Seine C\u00e9dex^^175, Av. Achille P\u00e9retti, 92200 Neuilly sur Seine",
    "sg:orig_category":"Non-Classified Establishments",
    "sg:phone":"+33 1 46 24 84 01",
    "sg:postcode":"92200",
    "sg:province":"Ile de France",
    "wof:name":"C.e.n. S.a.",
    "wof:placetype":"venue"
},
  "geometry": {"coordinates":[2.26934,48.884377],"type":"Point"}
}