{
  "type": "Feature",
  "properties": {
    "addr:full":"112 rue R\u00e9aumur 75002 Paris Ile de France 75002",
    "addr:housenumber":"112",
    "addr:postcode":"75002;75002",
    "addr:street":"Rue Re\u0301Aumur",
    "iso:country":"FR",
    "sg:address":"112 rue R\u00e9aumur 75002 Paris",
    "sg:classifiers":[
        {
            "category":"Shopping",
            "subcategory":"Clothing, Apparel, & Fashions",
            "type":"Retail Goods"
        }
    ],
    "sg:phone":"+33 1 40 41 06 31",
    "sg:postcode":"75002",
    "sg:province":"Ile de France",
    "sg:tags":[
        "blouse",
        "ladies'",
        "dress"
    ],
    "wof:name":"Teenflo S.a.",
    "wof:placetype":"venue"
},
  "geometry": {"coordinates":[2.345915,48.867805],"type":"Point"}
}