{
  "type": "Feature",
  "properties": {
    "addr:full":"B.P. 108, 37301 Jou\u00e9 l\u00e8s Tours C\u00e9dex^^Place Fran\u00e7ois Mitt\u00e9rand, 37300 Jou\u00e9 l\u00e8s Tours Jou\u00e9-l\u00e8s-Tours Centre 37300",
    "addr:housenumber":"b.p. 108",
    "addr:postcode":"37301;37300;37300",
    "iso:country":"FR",
    "sg:address":"B.P. 108, 37301 Jou\u00e9 l\u00e8s Tours C\u00e9dex^^Place Fran\u00e7ois Mitt\u00e9rand, 37300 Jou\u00e9 l\u00e8s Tours",
    "sg:city":"Jou\u00e9-l\u00e8s-Tours",
    "sg:orig_category":"Non-Classified Establishments",
    "sg:phone":"+33 2 47 39 70 00",
    "sg:postcode":"37300",
    "sg:province":"Centre",
    "wof:name":"Mairie De Jou\u00e9 Les Tours",
    "wof:placetype":"venue"
},
  "geometry": {"coordinates":[0.662555,47.350945],"type":"Point"}
}