{
  "type": "Feature",
  "properties": {
    "iso:country":"FR",
    "sg:address":"Rue Blaise Pascal 10430 Rosi\u00e8res Pr\u00e9s Troyes",
    "sg:classifiers":[
        {
            "category":"Professional",
            "type":"Services"
        }
    ],
    "sg:phone":"+33 3 25 75 22 14",
    "sg:province":"Champagne",
    "sg:tags":[
        "-",
        "related",
        "road",
        "transport"
    ],
    "wof:name":"Brie Translocadem Sarl",
    "wof:placetype":"venue"
},
  "geometry": {"coordinates":[4.046185,48.262245],"type":"Point"}
}