{
  "type": "Feature",
  "properties": {
    "addr:full":"40, Rue Roland Garros - Mas de Figui\u00e8res , 34130 Mauguio Languedoc-Roussillon",
    "addr:housenumber":"40",
    "addr:postcode":"34130",
    "addr:street":"Rue Roland Garros",
    "iso:country":"FR",
    "sg:address":"40, Rue Roland Garros - Mas de Figui\u00e8res , 34130 Mauguio",
    "sg:orig_category":"Unclassifiable Establishments",
    "sg:phone":"+33 4 67 20 10 77",
    "sg:province":"Languedoc-Roussillon",
    "wof:name":"C.r.p.i. S.a.s.",
    "wof:placetype":"venue"
},
  "geometry": {"coordinates":[4.0079,43.617867],"type":"Point"}
}