{
  "type": "Feature",
  "properties": {
    "iso:country":"FR",
    "sg:address":"10, Av de la Lib\u00e9ration - Rte de Reims, 55000 Fains V\u00e9el",
    "sg:orig_category":"Unclassifiable Establishments",
    "sg:phone":"+33 3 29 45 43 43",
    "sg:province":"Lorraine",
    "wof:name":"Pergent Peinture S.a.r.l.",
    "wof:placetype":"venue"
},
  "geometry": {"coordinates":[5.084741,48.685223],"type":"Point"}
}