{
  "type": "Feature",
  "properties": {
    "iso:country":"FR",
    "sg:address":"42 Rue Vaucanson 69150 Decines Charpieu",
    "sg:classifiers":[
        {
            "category":"Professional",
            "subcategory":"Engineering",
            "type":"Services"
        }
    ],
    "sg:phone":"+33 4 72 37 02 00",
    "sg:postcode":"69150",
    "sg:province":"Rhone-Alpes",
    "sg:tags":[
        "machine",
        "-",
        "mechanical"
    ],
    "wof:name":"Vmi",
    "wof:placetype":"venue"
},
  "geometry": {"coordinates":[4.940136,45.753487],"type":"Point"}
}