{
  "type": "Feature",
  "properties": {
    "iso:country":"FR",
    "sg:address":"ZA",
    "sg:city":"Notre Dame de Monts",
    "sg:orig_category":"Unclassifiable Establishments",
    "sg:phone":"+33 2 51 58 45 03",
    "sg:postcode":"85690",
    "sg:province":"Pays de Loire",
    "wof:name":"Gastromer S.a.",
    "wof:placetype":"venue"
},
  "geometry": {"coordinates":[-2.131849,46.828014],"type":"Point"}
}