{
  "type": "Feature",
  "properties": {
    "addr:full":"Rue Martel - ZA Ramerupt Champagne 10240",
    "addr:postcode":"10240",
    "addr:street":"Rue Martel Za Ramerupt Champagne",
    "iso:country":"FR",
    "sg:address":"Rue Martel - ZA",
    "sg:city":"Ramerupt",
    "sg:orig_category":"Unclassifiable Establishments",
    "sg:phone":"+33 3 25 37 64 06",
    "sg:postcode":"10240",
    "sg:province":"Champagne",
    "wof:name":"Imprimerie De La Halle E.u.r.l.",
    "wof:placetype":"venue"
},
  "geometry": {"coordinates":[4.29195,48.519314],"type":"Point"}
}