{
  "type": "Feature",
  "properties": {
    "iso:country":"FR",
    "sg:address":"7, Quai Saint Nicolas, 67000 Strasbourg",
    "sg:city":"Strasbourg",
    "sg:orig_category":"Unclassifiable Establishments",
    "sg:phone":"+33 3 88 60 28 61",
    "sg:postcode":"67000",
    "sg:province":"Alsace",
    "wof:name":"Breton Alain Dominique Marcel",
    "wof:placetype":"venue"
},
  "geometry": {"coordinates":[7.748019,48.579117],"type":"Point"}
}