{
  "type": "Feature",
  "properties": {
    "addr:full":"Zi 68490 Hombourg Hombourg Alsace 68490",
    "addr:postcode":"68490;68490",
    "addr:street":"Zi",
    "iso:country":"FR",
    "sg:address":"Zi 68490 Hombourg",
    "sg:city":"Hombourg",
    "sg:classifiers":[
        {
            "category":"Shopping",
            "subcategory":"Computers & Home Electronics",
            "type":"Retail Goods"
        }
    ],
    "sg:phone":"+33 3 89 26 07 44",
    "sg:postcode":"68490",
    "sg:province":"Alsace",
    "sg:tags":[
        "electric",
        "electricity",
        "component",
        "equipment",
        "electrical",
        "electronic"
    ],
    "wof:name":"Kaefer Wanner",
    "wof:placetype":"venue"
},
  "geometry": {"coordinates":[7.506465,47.78661],"type":"Point"}
}