{
  "type": "Feature",
  "properties": {
    "addr:full":"All Charles Victor Naudin Templiers Sophia Antipolis 06410 Biot Midi Pyr\u00e9n\u00e9es",
    "addr:postcode":"06410",
    "iso:country":"FR",
    "sg:address":"All Charles Victor Naudin Templiers Sophia Antipolis 06410 Biot",
    "sg:classifiers":[
        {
            "category":"Utilities",
            "subcategory":"Electric",
            "type":"Services"
        }
    ],
    "sg:phone":"+33 4 92 38 88 20",
    "sg:province":"Midi Pyr\u00e9n\u00e9es",
    "sg:tags":[
        "electricity",
        "electronic",
        "electrical",
        "equipment"
    ],
    "wof:name":"Dsf Technologies",
    "wof:placetype":"venue"
},
  "geometry": {"coordinates":[7.08509,43.626709],"type":"Point"}
}