{
  "type": "Feature",
  "properties": {
    "addr:full":"Centre Commercial Belle Epine - Tour Europe 106 Thiais C\u00e9dex \u00cele-de-France 94532",
    "addr:housenumber":"106",
    "addr:postcode":"94532",
    "addr:street":"Ce\u0301Dex",
    "iso:country":"FR",
    "sg:address":"Centre Commercial Belle Epine - Tour Europe 106",
    "sg:city":"Thiais C\u00e9dex",
    "sg:orig_category":"Non-Classified Establishments",
    "sg:phone":"+33 1 41 80 01 41",
    "sg:postcode":"94532",
    "sg:province":"\u00cele-de-France",
    "wof:name":"Giuseppe Citterio France S.a.",
    "wof:placetype":"venue"
},
  "geometry": {"coordinates":[2.39276,48.765701],"type":"Point"}
}