{
  "type": "Feature",
  "properties": {
    "addr:full":"Zi Les Grouets 41100 St Ouen Lisle Centre 41100",
    "addr:postcode":"41100;41100",
    "addr:street":"Zi Les Grouets;St;Lisle",
    "iso:country":"FR",
    "sg:address":"Zi Les Grouets 41100 St Ouen",
    "sg:city":"Lisle",
    "sg:classifiers":[
        {
            "category":"Home & Garden",
            "subcategory":"Furniture",
            "type":"Retail Goods"
        }
    ],
    "sg:phone":"+33 2 54 77 56 56",
    "sg:postcode":"41100",
    "sg:province":"Centre",
    "sg:tags":[
        "household",
        "wood"
    ],
    "wof:name":"Neves Industrie",
    "wof:placetype":"venue"
},
  "geometry": {"coordinates":[1.081308,47.809818],"type":"Point"}
}