{
  "type": "Feature",
  "properties": {
    "iso:country":"FR",
    "sg:address":"3, Rue de Lardy - Le Petit Mesnil , 91850 Bouray sur Juine",
    "sg:orig_category":"Non-Classified Establishments",
    "sg:phone":"+33 1 60 82 78 78",
    "sg:province":"Ile de France",
    "wof:name":"R.a.g.t. Semences S.a.",
    "wof:placetype":"venue"
},
  "geometry": {"coordinates":[2.298276,48.520473],"type":"Point"}
}