{
  "type": "Feature",
  "properties": {
    "iso:country":"FR",
    "sg:address":"4 rue de la Marne 34370 CAZOULS LES BEZIERS",
    "sg:classifiers":[
        {
            "category":"Wholesale",
            "subcategory":"Metals & Minerals",
            "type":"Manufacturing & Wholesale Goods"
        }
    ],
    "sg:phone":"+33 4 67 93 60 47",
    "sg:province":"Languedoc-Roussillon",
    "sg:tags":[
        "steel",
        "stainless",
        "tub",
        "vat"
    ],
    "wof:name":"Julien Viticulture S.a.",
    "wof:placetype":"venue"
},
  "geometry": {"coordinates":[3.105529,43.392406],"type":"Point"}
}