{
  "type": "Feature",
  "properties": {
    "addr:full":"17 bis, Av. Stalingrad, 78190 Trappes Ile de France",
    "addr:housenumber":"17 bis",
    "addr:postcode":"78190;ile",
    "addr:street":"Av. Stalingrad",
    "iso:country":"FR",
    "sg:address":"17 bis, Av. Stalingrad, 78190 Trappes",
    "sg:orig_category":"Non-Classified Establishments",
    "sg:phone":"+33 1 30 66 04 36",
    "sg:province":"Ile de France",
    "wof:name":"Toute La Signalisation S.a.r.l.",
    "wof:placetype":"venue"
},
  "geometry": {"coordinates":[2.001022,48.777634],"type":"Point"}
}