{
  "type": "Feature",
  "properties": {
    "iso:country":"FR",
    "sg:address":"8, Rue Louis le Bourhis, 29000 Quimper",
    "sg:city":"Quimper",
    "sg:orig_category":"Unclassifiable Establishments",
    "sg:phone":"+33 2 98 52 81 44",
    "sg:postcode":"29000",
    "sg:province":"Bretagne",
    "wof:name":"Piscicultures De Bretagne S.a.",
    "wof:placetype":"venue"
},
  "geometry": {"coordinates":[-4.032349,47.983444],"type":"Point"}
}