{
  "type": "Feature",
  "properties": {
    "addr:full":"26 avenue de la Lib\u00e9ration 69330 Meyzieu Rhone-Alpes",
    "addr:housenumber":"26",
    "addr:postcode":"69330",
    "addr:street":"Avenue De La Libe\u0301Ration",
    "iso:country":"FR",
    "sg:address":"26 avenue de la Lib\u00e9ration 69330 Meyzieu",
    "sg:classifiers":[
        {
            "category":"Autos & Motor Vehicles",
            "subcategory":"Boat Sales",
            "type":"Retail Goods"
        }
    ],
    "sg:phone":"+33 4 78 31 59 89",
    "sg:province":"Rhone-Alpes",
    "sg:tags":[
        "machine",
        "beverage",
        "vending",
        "dispensing"
    ],
    "wof:name":"Ste Stephanexpress Sa",
    "wof:placetype":"venue"
},
  "geometry": {"coordinates":[4.999854,45.773506],"type":"Point"}
}