{
  "type": "Feature",
  "properties": {
    "addr:full":"118 Rue Du G\u00e9n\u00e9ral Leclerc Franconville La Garenne Ile de France 95130",
    "addr:housenumber":"118",
    "addr:postcode":"95130",
    "addr:street":"Rue Du Ge\u0301Ne\u0301Ral Leclerc;La;Ile;France",
    "iso:country":"FR",
    "sg:address":"118 Rue Du G\u00e9n\u00e9ral Leclerc",
    "sg:city":"Franconville La Garenne",
    "sg:classifiers":[
        {
            "category":"Banks & Credit Unions",
            "subcategory":"Financial Services",
            "type":"Services"
        }
    ],
    "sg:phone":"+33 1 30 72 70 90",
    "sg:postcode":"95130",
    "sg:province":"Ile de France",
    "sg:tags":[
        "banking",
        "finance",
        "insurance"
    ],
    "wof:name":"Compagnie Fiduciaire Francilienne Sa",
    "wof:placetype":"venue"
},
  "geometry": {"coordinates":[2.235405,49.001438],"type":"Point"}
}