{
  "type": "Feature",
  "properties": {
    "iso:country":"FR",
    "sg:address":"19, Rue Thales de Milet, 72000 Le Mans",
    "sg:orig_category":"Non-Classified Establishments",
    "sg:phone":"+33 2 43 39 48 76",
    "sg:postcode":"72000",
    "sg:province":"Pays de Loire",
    "wof:name":"E.m.e.s. S.a.s.",
    "wof:placetype":"venue"
},
  "geometry": {"coordinates":[0.159933,48.0191],"type":"Point"}
}