{
  "type": "Feature",
  "properties": {
    "iso:country":"FR",
    "sg:address":"Bd des Bassins de Radoub - .",
    "sg:city":"Marseille",
    "sg:orig_category":"Non-Classified Establishments",
    "sg:phone":"+33 4 91 11 61 24",
    "sg:postcode":"13002",
    "sg:province":"Poitou-Charentes",
    "wof:name":"S.o.g.e.r.i.c. S.a.r.l. - Soci\u00e9t\u00e9 De Gestion Repr\u00e9sentation Et Diffusion Industrielle Et Commerciale",
    "wof:placetype":"venue"
},
  "geometry": {"coordinates":[5.36197,43.320309],"type":"Point"}
}