{
  "type": "Feature",
  "properties": {
    "iso:country":"FR",
    "sg:address":"33126 La Rivi\u00e8re",
    "sg:city":"La Rivi\u00e8re",
    "sg:orig_category":"Unclassifiable Establishments",
    "sg:phone":"+33 5 57 55 56 56",
    "sg:postcode":"33126",
    "sg:province":"Aquitaine",
    "wof:name":"Ch\u00e2teau De La Rivi\u00e8re S.a.",
    "wof:placetype":"venue"
},
  "geometry": {"coordinates":[-0.313384,44.936924],"type":"Point"}
}