{
  "type": "Feature",
  "properties": {
    "addr:full":"ZA Les Brandeaux Puymoyen Poitou-Charentes 16400",
    "addr:postcode":"16400",
    "addr:street":"Za Les;Puymoyen",
    "iso:country":"FR",
    "sg:address":"ZA Les Brandeaux",
    "sg:city":"Puymoyen",
    "sg:orig_category":"Non-Classified Establishments",
    "sg:phone":"+33 5 45 65 34 62",
    "sg:postcode":"16400",
    "sg:province":"Poitou-Charentes",
    "wof:name":"E.s.a.t.e.c. S.a. - Etudes Services Automatismes Techniques Emballages Conditionnements",
    "wof:placetype":"venue"
},
  "geometry": {"coordinates":[0.18004,45.614738],"type":"Point"}
}