{
  "type": "Feature",
  "properties": {
    "addr:full":"B.P. 8, 89380 Appoigny^^10, Chemin de Pougy, 89380 Appoigny Appoigny Bourgogne 89380",
    "addr:housenumber":"8",
    "addr:postcode":"89380;89380;89380",
    "addr:street":"B.P.;Chemin De Pougy",
    "iso:country":"FR",
    "sg:address":"B.P. 8, 89380 Appoigny^^10, Chemin de Pougy, 89380 Appoigny",
    "sg:city":"Appoigny",
    "sg:orig_category":"Non-Classified Establishments",
    "sg:phone":"+33 3 86 53 59 00",
    "sg:postcode":"89380",
    "sg:province":"Bourgogne",
    "wof:name":"Amora Maille S.a.",
    "wof:placetype":"venue"
},
  "geometry": {"coordinates":[3.52591,47.877048],"type":"Point"}
}