{
  "type": "Feature",
  "properties": {
    "iso:country":"FR",
    "sg:address":"56, Rue Notre Dame de Nazareth, 75003 Paris",
    "sg:orig_category":"Non-Classified Establishments",
    "sg:phone":"+33 1 42 78 18 00",
    "sg:province":"Ile de France",
    "wof:name":"Nazareth Fournitures S.a.",
    "wof:placetype":"venue"
},
  "geometry": {"coordinates":[2.357331,48.867722],"type":"Point"}
}