{
  "type": "Feature",
  "properties": {
    "addr:full":"9 Av Hoche 75008 Paris Ile de France 75008",
    "addr:postcode":"75008;75008",
    "addr:street":"Av Hoche",
    "iso:country":"FR",
    "sg:address":"9 Av Hoche 75008 Paris",
    "sg:classifiers":[
        {
            "category":"Professional",
            "subcategory":"Business Services",
            "type":"Services"
        }
    ],
    "sg:phone":"+33 1 45 63 08 23",
    "sg:postcode":"75008",
    "sg:province":"Ile de France",
    "sg:tags":[
        "advice",
        "clothes"
    ],
    "wof:name":"Karin Models",
    "wof:placetype":"venue"
},
  "geometry": {"coordinates":[2.304459,48.877457],"type":"Point"}
}