{
  "type": "Feature",
  "properties": {
    "iso:country":"FR",
    "sg:address":"27 Avenue Maurice Chevalier 77330 Ozoir La Ferri\u00e8re",
    "sg:classifiers":[
        {
            "category":"Autos & Motor Vehicles",
            "subcategory":"Automobile Sales",
            "type":"Retail Goods"
        }
    ],
    "sg:phone":"+33 1 64 40 05 88",
    "sg:province":"Ile de France",
    "sg:tags":[
        "equipment",
        "transport"
    ],
    "wof:name":"Pleintube Jl Jouvin Sa",
    "wof:placetype":"venue"
},
  "geometry": {"coordinates":[2.686447,48.767845],"type":"Point"}
}