{
  "type": "Feature",
  "properties": {
    "addr:full":"135 Rue De La Vincenderie 86000 Poitiers Poitou-Charentes",
    "addr:housenumber":"135",
    "addr:postcode":"86000",
    "addr:street":"Rue De La Vincenderie",
    "iso:country":"FR",
    "sg:address":"135 Rue De La Vincenderie 86000 Poitiers",
    "sg:classifiers":[
        {
            "category":"Manufacturing",
            "subcategory":"Chemicals & Compounds",
            "type":"Manufacturing & Wholesale Goods"
        }
    ],
    "sg:phone":"+33 5 49 45 60 09",
    "sg:province":"Poitou-Charentes",
    "sg:tags":[
        "pharmaceutical",
        "chemistry",
        "-",
        "by-product"
    ],
    "wof:name":"Les Usines De La Vincenderie",
    "wof:placetype":"venue"
},
  "geometry": {"coordinates":[0.34031,46.592869],"type":"Point"}
}