{
  "type": "Feature",
  "properties": {
    "iso:country":"FR",
    "sg:address":"Moulin Paradou",
    "sg:city":"Brassac",
    "sg:orig_category":"Unclassifiable Establishments",
    "sg:phone":"+33 5 63 74 03 26",
    "sg:postcode":"81260",
    "sg:province":"Midi Pyr\u00e9n\u00e9es",
    "wof:name":"Etablissements Veaute Olivier S.a.r.l.",
    "wof:placetype":"venue"
},
  "geometry": {"coordinates":[2.492796,43.633369],"type":"Point"}
}