{
  "type": "Feature",
  "properties": {
    "addr:full":"RN 8 Ollioules 83190",
    "addr:postcode":"83190",
    "addr:street":"Rn 8",
    "iso:country":"FR",
    "sg:address":"RN 8",
    "sg:city":"Ollioules",
    "sg:orig_category":"Unclassifiable Establishments",
    "sg:phone":"+33 4 94 63 10 34",
    "sg:postcode":"83190",
    "wof:name":"Entreprise B\u00e9neventi S.a.r.l.",
    "wof:placetype":"venue"
},
  "geometry": {"coordinates":[5.84722,43.137573],"type":"Point"}
}