{
  "type": "Feature",
  "properties": {
    "addr:full":"Rte de Kermelin Saint Av\u00e9 Bretagne 56890",
    "addr:postcode":"56890",
    "addr:street":"Rte De Kermelin Saint Ave\u0301 Bretagne",
    "iso:country":"FR",
    "sg:address":"Rte de Kermelin",
    "sg:city":"Saint Av\u00e9",
    "sg:orig_category":"Non-Classified Establishments",
    "sg:phone":"+33 2 97 60 74 22",
    "sg:postcode":"56890",
    "sg:province":"Bretagne",
    "wof:name":"Etablissements Guedo S.a.r.l.",
    "wof:placetype":"venue"
},
  "geometry": {"coordinates":[-2.740259,47.678532],"type":"Point"}
}