{
  "type": "Feature",
  "properties": {
    "addr:full":"ZI Nord - Pr\u00e9 Viboud La Rochette Rhone-Alpes 73110",
    "addr:postcode":"73110",
    "addr:street":"Zi Nord Pre\u0301 Viboud La",
    "iso:country":"FR",
    "sg:address":"ZI Nord - Pr\u00e9 Viboud",
    "sg:city":"La Rochette",
    "sg:orig_category":"Non-Classified Establishments",
    "sg:phone":"+33 4 79 25 74 05",
    "sg:postcode":"73110",
    "sg:province":"Rhone-Alpes",
    "wof:name":"Charlet-moser S.a.",
    "wof:placetype":"venue"
},
  "geometry": {"coordinates":[6.116625,45.463394],"type":"Point"}
}