{
  "type": "Feature",
  "properties": {
    "iso:country":"FR",
    "sg:address":"1, Av. du Capitaine Anjot, 74960 Cran Gevrier",
    "sg:orig_category":"Non-Classified Establishments",
    "sg:phone":"+33 4 50 52 06 42",
    "sg:postcode":"74960",
    "sg:province":"Rhone-Alpes",
    "wof:name":"Ateliers Du Thiou",
    "wof:placetype":"venue"
},
  "geometry": {"coordinates":[6.091535,45.895828],"type":"Point"}
}