{
  "type": "Feature",
  "properties": {
    "addr:full":"1, Square Franklin, 78180 Montigny le Bretonneux Ile de France",
    "addr:housenumber":"1",
    "addr:postcode":"78180",
    "addr:street":"Square Franklin",
    "iso:country":"FR",
    "sg:address":"1, Square Franklin, 78180 Montigny le Bretonneux",
    "sg:orig_category":"Non-Classified Establishments",
    "sg:phone":"+33 1 39 30 53 00",
    "sg:province":"Ile de France",
    "wof:name":"Thermo Opteck S.a.r.l.",
    "wof:placetype":"venue"
},
  "geometry": {"coordinates":[2.039737,48.77018],"type":"Point"}
}