{
  "type": "Feature",
  "properties": {
    "iso:country":"FR",
    "sg:address":"140, Rue Larevelli\u00e8re, 49100 Angers",
    "sg:orig_category":"Unclassifiable Establishments",
    "sg:phone":"+33 2 41 43 18 80",
    "sg:province":"Pays de Loire",
    "wof:name":"Sadac Marolleau S.a.",
    "wof:placetype":"venue"
},
  "geometry": {"coordinates":[-0.527354,47.471184],"type":"Point"}
}