{
  "type": "Feature",
  "properties": {
    "addr:full":"Rte Nationale Marconnelle Nord Pas-de-Calais 62140",
    "addr:postcode":"62140",
    "addr:street":"Rte Nationale Marconnelle Nord",
    "iso:country":"FR",
    "sg:address":"Rte Nationale",
    "sg:city":"Marconnelle",
    "sg:orig_category":"Unclassifiable Establishments",
    "sg:phone":"+33 3 21 06 77 11",
    "sg:postcode":"62140",
    "sg:province":"Nord Pas-de-Calais",
    "wof:name":"Sucreries Du Marquenterre S.a.",
    "wof:placetype":"venue"
},
  "geometry": {"coordinates":[2.009226,50.375629],"type":"Point"}
}