{
  "type": "Feature",
  "properties": {
    "iso:country":"FR",
    "sg:address":"B.P. 985, 60009 Beauvais C\u00e9dex^^Av Descartes, 60000 Beauvais",
    "sg:orig_category":"Non-Classified Establishments",
    "sg:phone":"+33 3 44 05 40 35",
    "sg:province":"Picardie",
    "wof:name":"Paris Caramels S.a.",
    "wof:placetype":"venue"
},
  "geometry": {"coordinates":[2.08322,49.429558],"type":"Point"}
}