{
  "type": "Feature",
  "properties": {
    "iso:country":"FR",
    "sg:address":"12, Rue Sainte Anne, 67100 Strasbourg",
    "sg:city":"Strasbourg",
    "sg:orig_category":"Unclassifiable Establishments",
    "sg:phone":"+33 3 88 44 11 99",
    "sg:postcode":"67100",
    "sg:province":"Alsace",
    "wof:name":"Contrast' S.a.r.l.",
    "wof:placetype":"venue"
},
  "geometry": {"coordinates":[7.757046,48.563808],"type":"Point"}
}