{
  "type": "Feature",
  "properties": {
    "iso:country":"FR",
    "sg:address":"917, Rue de l'Horlogerie, 62400 B\u00e9thune",
    "sg:orig_category":"Unclassifiable Establishments",
    "sg:phone":"+33 3 21 64 54 68",
    "sg:province":"Nord Pas-de-Calais",
    "wof:name":"Soci\u00e9t\u00e9 Nouvelle Equi-test Pesage S.a.r.l.",
    "wof:placetype":"venue"
},
  "geometry": {"coordinates":[2.645554,50.523384],"type":"Point"}
}