{
  "type": "Feature",
  "properties": {
    "addr:full":"B.P. 1244, 31047 Toulouse C\u00e9dex^^7, Rue Paul Mespl\u00e9 - Parc Technologique de Basso Cambo, 31100 Toulo Midi Pyr\u00e9n\u00e9es",
    "addr:postcode":"31047;31100",
    "addr:street":"B.P. 1244;Rue Paul Mesple\u0301 Parc Technologique De Basso Cambo",
    "iso:country":"FR",
    "sg:address":"B.P. 1244, 31047 Toulouse C\u00e9dex^^7, Rue Paul Mespl\u00e9 - Parc Technologique de Basso Cambo, 31100 Toulo",
    "sg:orig_category":"Non-Classified Establishments",
    "sg:phone":"+33 5 62 14 38 10",
    "sg:province":"Midi Pyr\u00e9n\u00e9es",
    "wof:name":"I.d.e.e.f. S.a.r.l. - Institut De D\u00e9veloppement Et D'etudes De Formation",
    "wof:placetype":"venue"
},
  "geometry": {"coordinates":[1.44301,43.604359],"type":"Point"}
}