{
  "type": "Feature",
  "properties": {
    "addr:full":"Pl Du 8 Mai 65120 Luz St Sauveur Midi Pyr\u00e9n\u00e9es 65120",
    "addr:postcode":"65120;65120",
    "addr:street":"Pl Du 8 Mai;Luz St;Midi",
    "iso:country":"FR",
    "sg:address":"Pl Du 8 Mai 65120 Luz St Sauveur",
    "sg:classifiers":[
        {
            "category":"Sports & Exercise",
            "subcategory":"Sports Center",
            "type":"Entertainment"
        }
    ],
    "sg:phone":"+33 5 62 92 80 58",
    "sg:postcode":"65120",
    "sg:province":"Midi Pyr\u00e9n\u00e9es",
    "sg:tags":[
        "game"
    ],
    "wof:name":"Regie Des Sports D Hiver De Luz Ardiden",
    "wof:placetype":"venue"
},
  "geometry": {"coordinates":[-0.002624,42.873314],"type":"Point"}
}