{
  "type": "Feature",
  "properties": {
    "iso:country":"FR",
    "sg:address":"33, Rue Pierre Curie, 60110 M\u00e9ru",
    "sg:orig_category":"Non-Classified Establishments",
    "sg:phone":"+33 3 44 22 27 12",
    "sg:postcode":"60110",
    "sg:province":"Picardie",
    "wof:name":"Cousin S.a.r.l.",
    "wof:placetype":"venue"
},
  "geometry": {"coordinates":[2.131707,49.242332],"type":"Point"}
}