{
  "type": "Feature",
  "properties": {
    "addr:full":"105 Avenue Paul Marcellin 69120 Vaulx En Velin Rhone-Alpes 69120",
    "addr:housenumber":"105",
    "addr:postcode":"69120;69120",
    "addr:street":"Avenue Paul Marcellin",
    "iso:country":"FR",
    "sg:address":"105 Avenue Paul Marcellin 69120 Vaulx En Velin",
    "sg:classifiers":[
        {
            "category":"Manufacturing",
            "subcategory":"Printing",
            "type":"Manufacturing & Wholesale Goods"
        }
    ],
    "sg:phone":"+33 4 72 04 73 73",
    "sg:postcode":"69120",
    "sg:province":"Rhone-Alpes",
    "sg:tags":[
        "publishing"
    ],
    "wof:name":"Fayolle Pole Graphique Global",
    "wof:placetype":"venue"
},
  "geometry": {"coordinates":[4.930769,45.778389],"type":"Point"}
}