{
  "type": "Feature",
  "properties": {
    "iso:country":"FR",
    "sg:address":"B.P. 37, 49140 Seiches sur le Loir^^Zone Artisanale les Mulotti\u00e8res, 49140 Seiches sur le Loir",
    "sg:orig_category":"Non-Classified Establishments",
    "sg:phone":"+33 2 41 21 14 00",
    "sg:province":"Pays de Loire",
    "wof:name":"I.g.r.e.c.a. S.a.",
    "wof:placetype":"venue"
},
  "geometry": {"coordinates":[-0.317761,47.499454],"type":"Point"}
}