{
  "type": "Feature",
  "properties": {
    "addr:full":"Rte de Bastia - Quartier la Poretta Porto Vecchio Corse 20137",
    "addr:postcode":"20137",
    "addr:street":"Rte De Bastia",
    "iso:country":"FR",
    "sg:address":"Rte de Bastia - Quartier la Poretta",
    "sg:city":"Porto Vecchio",
    "sg:orig_category":"Non-Classified Establishments",
    "sg:phone":"+33 4 95 70 08 31",
    "sg:postcode":"20137",
    "sg:province":"Corse",
    "wof:name":"E.t.m. S.a. - Ettori Tadd\u00e9i Mosconi",
    "wof:placetype":"venue"
},
  "geometry": {"coordinates":[9.27852,41.592529],"type":"Point"}
}