{
  "type": "Feature",
  "properties": {
    "addr:full":"23, Rue Delpont, 31700 Blagnac Midi Pyr\u00e9n\u00e9es",
    "addr:housenumber":"23",
    "addr:postcode":"31700",
    "addr:street":"Rue Delpont",
    "iso:country":"FR",
    "sg:address":"23, Rue Delpont, 31700 Blagnac",
    "sg:orig_category":"Unclassifiable Establishments",
    "sg:phone":"+33 5 61 71 55 93",
    "sg:province":"Midi Pyr\u00e9n\u00e9es",
    "wof:name":"Cogilog S.a.r.l.",
    "wof:placetype":"venue"
},
  "geometry": {"coordinates":[1.396383,43.631748],"type":"Point"}
}