{
  "type": "Feature",
  "properties": {
    "addr:full":"45, Rue du Point Central, 59200 Tourcoing Nord Pas-de-Calais",
    "addr:housenumber":"45",
    "addr:postcode":"59200",
    "addr:street":"Rue Du Point",
    "iso:country":"FR",
    "sg:address":"45, Rue du Point Central, 59200 Tourcoing",
    "sg:orig_category":"Unclassifiable Establishments",
    "sg:phone":"+33 3 20 26 40 13",
    "sg:province":"Nord Pas-de-Calais",
    "wof:name":"Serteco S.a.r.l. - Services Technico-commerciaux",
    "wof:placetype":"venue"
},
  "geometry": {"coordinates":[3.157839,50.707741],"type":"Point"}
}