{
  "type": "Feature",
  "properties": {
    "addr:full":"2 pl Jean Jaur\u00e8s; Merignac Champagne",
    "addr:housenumber":"2",
    "addr:street":"Pl Jean Jaure\u0300S",
    "iso:country":"FR",
    "sg:address":"2 pl Jean Jaur\u00e8s; Merignac",
    "sg:classifiers":[
        {
            "category":"Banks & Credit Unions",
            "subcategory":"Bank",
            "type":"Services"
        }
    ],
    "sg:phone":"+33 3356976757",
    "sg:province":"Champagne",
    "wof:name":"Banque National De Paris",
    "wof:placetype":"venue"
},
  "geometry": {"coordinates":[-0.64431,44.851288],"type":"Point"}
}