{
  "type": "Feature",
  "properties": {
    "iso:country":"FR",
    "sg:address":"6, Rue Jacques Bujault, 79300 Bressuire",
    "sg:orig_category":"Unclassifiable Establishments",
    "sg:phone":"+33 5 49 72 90 00",
    "sg:postcode":"79300",
    "sg:province":"Poitou-Charentes",
    "wof:name":"La Nouvelle R\u00e9publique Du Centre Ouest S.a.",
    "wof:placetype":"venue"
},
  "geometry": {"coordinates":[-0.491811,46.842045],"type":"Point"}
}