{
  "type": "Feature",
  "properties": {
    "iso:country":"FR",
    "sg:address":"91181 Wissous C\u00e9dex^^4, All\u00e9e du Commandant Mouchotte - Orlytech, 91550 Paray Vieille Poste",
    "sg:orig_category":"Non-Classified Establishments",
    "sg:phone":"+33 1 45 12 02 20",
    "sg:province":"Ile de France",
    "wof:name":"Kyocera S.a.",
    "wof:placetype":"venue"
},
  "geometry": {"coordinates":[2.36467,48.71294],"type":"Point"}
}