{
  "type": "Feature",
  "properties": {
    "iso:country":"FR",
    "sg:address":"B.P. 335, 91958 Courtaboeuf C\u00e9dex^^2, Av. du Pacific - ZAC de Courtaboeuf, 91940 Les Ulis",
    "sg:orig_category":"Non-Classified Establishments",
    "sg:phone":"+33 1 69 86 25 25",
    "sg:province":"Ile de France",
    "wof:name":"Sayag S.a.",
    "wof:placetype":"venue"
},
  "geometry": {"coordinates":[2.169475,48.68161],"type":"Point"}
}