{
  "type": "Feature",
  "properties": {
    "addr:full":"B.P. 7 Saint Ju\u00e9ry Midi Pyr\u00e9n\u00e9es 81160",
    "addr:housenumber":"7",
    "addr:postcode":"81160",
    "addr:street":"B.P.;Saint Jue\u0301Ry Midi Pyre\u0301Ne\u0301Es",
    "iso:country":"FR",
    "sg:address":"B.P. 7",
    "sg:city":"Saint Ju\u00e9ry",
    "sg:orig_category":"Non-Classified Establishments",
    "sg:phone":"+33 5 63 78 12 00",
    "sg:postcode":"81160",
    "sg:province":"Midi Pyr\u00e9n\u00e9es",
    "wof:name":"F.c.t. S.a. - Flow Control Technologies",
    "wof:placetype":"venue"
},
  "geometry": {"coordinates":[2.210815,43.949654],"type":"Point"}
}