{
  "type": "Feature",
  "properties": {
    "iso:country":"FR",
    "sg:address":"1, Rue de Berri, 75008 Paris",
    "sg:orig_category":"Unclassifiable Establishments",
    "sg:phone":"+33 1 42 25 10 63",
    "sg:province":"Ile de France",
    "wof:name":"M\u00e9dia Car S.a.",
    "wof:placetype":"venue"
},
  "geometry": {"coordinates":[2.302523,48.871716],"type":"Point"}
}