{
  "type": "Feature",
  "properties": {
    "iso:country":"FR",
    "sg:address":"39, Rue des Petits Champs, 75001 Paris",
    "sg:orig_category":"Non-Classified Establishments",
    "sg:phone":"+33 1 42 97 42 97",
    "sg:province":"Ile de France",
    "wof:name":"Soci\u00e9t\u00e9 Chanson Et Compagnie S.a.",
    "wof:placetype":"venue"
},
  "geometry": {"coordinates":[2.336147,48.866772],"type":"Point"}
}