{
  "type": "Feature",
  "properties": {
    "addr:full":"51, Rue du Boccage, 79440 Courlay Poitou-Charentes 79440",
    "addr:housenumber":"51",
    "addr:postcode":"79440;79440",
    "addr:street":"Rue Du Boccage",
    "iso:country":"FR",
    "sg:address":"51, Rue du Boccage, 79440 Courlay",
    "sg:orig_category":"Unclassifiable Establishments",
    "sg:phone":"+33 5 49 72 31 19",
    "sg:postcode":"79440",
    "sg:province":"Poitou-Charentes",
    "wof:name":"C.2.s. S.a. - Confection Des Deux-s\u00e8vres",
    "wof:placetype":"venue"
},
  "geometry": {"coordinates":[-0.549326,46.776928],"type":"Point"}
}