{
  "type": "Feature",
  "properties": {
    "addr:full":"210 avenue Georges Cl\u00e9menceau 92000 Nanterre Ile de France 92000",
    "addr:housenumber":"210",
    "addr:postcode":"92000;92000",
    "addr:street":"Avenue Georges Cle\u0301Menceau",
    "iso:country":"FR",
    "sg:address":"210 avenue Georges Cl\u00e9menceau 92000 Nanterre",
    "sg:classifiers":[
        {
            "category":"Home & Garden",
            "subcategory":"Furniture",
            "type":"Retail Goods"
        }
    ],
    "sg:phone":"+33 1 41 18 01 49",
    "sg:postcode":"92000",
    "sg:province":"Ile de France",
    "sg:tags":[
        "designer"
    ],
    "wof:name":"Collectivia Sa",
    "wof:placetype":"venue"
},
  "geometry": {"coordinates":[2.214743,48.88586],"type":"Point"}
}