{
  "type": "Feature",
  "properties": {
    "addr:full":"2 R Le Corbosier BP 174 Goussainville Ile de France 95190",
    "addr:housenumber":"2;174",
    "addr:postcode":"95190",
    "addr:street":"R Le Corbosier Bp",
    "iso:country":"FR",
    "sg:address":"2 R Le Corbosier BP 174",
    "sg:city":"Goussainville",
    "sg:classifiers":[
        {
            "category":"Banks & Credit Unions",
            "subcategory":"Financial Services",
            "type":"Services"
        }
    ],
    "sg:phone":"+33 1 39 88 19 99",
    "sg:postcode":"95190",
    "sg:province":"Ile de France",
    "sg:tags":[
        "banking",
        "finance",
        "insurance"
    ],
    "wof:name":"Assistance Mondial Protection Securite",
    "wof:placetype":"venue"
},
  "geometry": {"coordinates":[2.463859,49.020412],"type":"Point"}
}