{
  "type": "Feature",
  "properties": {
    "addr:full":"Rue Marcel Henaux 59000 Lille Nord Pas-de-Calais 59000",
    "addr:postcode":"59000;59000",
    "addr:street":"Rue Marcel Henaux",
    "iso:country":"FR",
    "sg:address":"Rue Marcel Henaux 59000 Lille",
    "sg:classifiers":[
        {
            "category":"Professional",
            "subcategory":"Engineering",
            "type":"Services"
        }
    ],
    "sg:phone":"+33 3 28 54 00 80",
    "sg:postcode":"59000",
    "sg:province":"Nord Pas-de-Calais",
    "sg:tags":[
        "machine",
        "-",
        "mechanical"
    ],
    "wof:name":"Diffus'air Service",
    "wof:placetype":"venue"
},
  "geometry": {"coordinates":[3.06058,50.614201],"type":"Point"}
}