{
  "type": "Feature",
  "properties": {
    "addr:full":"2, Rue Lyautey, 75016 Paris Ile de France",
    "addr:housenumber":"2",
    "addr:postcode":"75016",
    "addr:street":"Rue Lyautey",
    "iso:country":"FR",
    "sg:address":"2, Rue Lyautey, 75016 Paris",
    "sg:orig_category":"Non-Classified Establishments",
    "sg:phone":"+33 1 45 27 07 54",
    "sg:province":"Ile de France",
    "wof:name":"G\u00e9n\u00e9cos S.a.",
    "wof:placetype":"venue"
},
  "geometry": {"coordinates":[2.281939,48.856716],"type":"Point"}
}