{
  "type": "Feature",
  "properties": {
    "iso:country":"FR",
    "sg:address":"7 pl Eglise; Tregunc",
    "sg:city":"Tr\u00e9gunc",
    "sg:classifiers":[
        {
            "category":"Banks & Credit Unions",
            "subcategory":"Bank",
            "type":"Services"
        }
    ],
    "sg:phone":"+33 3398976351",
    "sg:postcode":"29910",
    "sg:province":"Bretagne",
    "wof:name":"Cr\u00e9dit Agricole Mutuel",
    "wof:placetype":"venue"
},
  "geometry": {"coordinates":[-3.85211,47.855282],"type":"Point"}
}