{
  "type": "Feature",
  "properties": {
    "iso:country":"FR",
    "sg:address":"ZI du Rhin",
    "sg:city":"Guidel",
    "sg:orig_category":"Unclassifiable Establishments",
    "sg:phone":"+33 2 97 65 97 98",
    "sg:postcode":"56520",
    "sg:province":"Bretagne",
    "wof:name":"Sibjet Technologies S.n.c.",
    "wof:placetype":"venue"
},
  "geometry": {"coordinates":[-3.489289,47.790478],"type":"Point"}
}