{
  "type": "Feature",
  "properties": {
    "addr:full":"Av. de la Touloubre - Lotissement du Midi - Puyricard Aix en Provence Nord Pas-de-Calais 13000",
    "addr:postcode":"13000",
    "addr:street":"Av. De La Touloubre Lotissement Du Midi;Pas-De-Calais",
    "iso:country":"FR",
    "sg:address":"Av. de la Touloubre - Lotissement du Midi - Puyricard",
    "sg:city":"Aix en Provence",
    "sg:orig_category":"Non-Classified Establishments",
    "sg:phone":"+33 4 42 92 26 27",
    "sg:postcode":"13000",
    "sg:province":"Nord Pas-de-Calais",
    "wof:name":"E.r.c.e.m.",
    "wof:placetype":"venue"
},
  "geometry": {"coordinates":[5.42192,43.582729],"type":"Point"}
}