{
  "type": "Feature",
  "properties": {
    "iso:country":"FR",
    "sg:address":"ZI",
    "sg:city":"Neufch\u00e2tel en Bray",
    "sg:orig_category":"Unclassifiable Establishments",
    "sg:phone":"+33 2 35 93 21 17",
    "sg:postcode":"76270",
    "sg:province":"Haute Normandie",
    "wof:name":"Bruno Frete Publicit\u00e9 S.a.s.",
    "wof:placetype":"venue"
},
  "geometry": {"coordinates":[1.43525,49.726658],"type":"Point"}
}