{
  "type": "Feature",
  "properties": {
    "addr:full":"83 Exelmans 75016 Paris Ile de France 75016",
    "addr:housenumber":"83",
    "addr:postcode":"75016;75016",
    "addr:street":"Exelmans",
    "iso:country":"FR",
    "sg:address":"83",
    "sg:city":"Exelmans 75016 Paris",
    "sg:classifiers":[
        {
            "category":"Manufacturing",
            "subcategory":"Chemicals & Compounds",
            "type":"Manufacturing & Wholesale Goods"
        }
    ],
    "sg:phone":"+33 1 40 71 20 60",
    "sg:postcode":"75016",
    "sg:province":"Ile de France",
    "sg:tags":[
        "pharmaceutical",
        "cosmetic"
    ],
    "wof:name":"Annick Goutal Parfums",
    "wof:placetype":"venue"
},
  "geometry": {"coordinates":[2.258861,48.843784],"type":"Point"}
}