{
  "type": "Feature",
  "properties": {
    "iso:country":"FR",
    "sg:address":"ZI des Glaires",
    "sg:city":"Pontamafrey Montpascal",
    "sg:orig_category":"Non-Classified Establishments",
    "sg:phone":"+33 4 79 83 40 38",
    "sg:postcode":"73300",
    "sg:province":"Rhone-Alpes",
    "wof:name":"Bianco Produits P\u00e9troliers S.a.",
    "wof:placetype":"venue"
},
  "geometry": {"coordinates":[6.341076,45.311859],"type":"Point"}
}