{
  "type": "Feature",
  "properties": {
    "addr:full":"260 R De La Gare 44370 Varades Pays de Loire",
    "addr:housenumber":"260",
    "addr:postcode":"44370",
    "addr:street":"R De La Gare",
    "iso:country":"FR",
    "sg:address":"260 R De La Gare 44370 Varades",
    "sg:classifiers":[
        {
            "category":"Professional",
            "type":"Services"
        }
    ],
    "sg:phone":"+33 2 40 98 34 07",
    "sg:province":"Pays de Loire",
    "sg:tags":[
        "transport",
        "road"
    ],
    "wof:name":"Poiron Rene",
    "wof:placetype":"venue"
},
  "geometry": {"coordinates":[-1.023569,47.3755],"type":"Point"}
}