{
  "type": "Feature",
  "properties": {
    "addr:full":"11, Rue de la M\u00e9tallurgie - ZI, 44470 Carquefou Pays de Loire 44470",
    "addr:housenumber":"11",
    "addr:postcode":"44470;44470",
    "addr:street":"Rue De La Me\u0301Tallurgie Zi",
    "iso:country":"FR",
    "sg:address":"11, Rue de la M\u00e9tallurgie - ZI, 44470 Carquefou",
    "sg:orig_category":"Non-Classified Establishments",
    "sg:phone":"+33 2 40 25 22 25",
    "sg:postcode":"44470",
    "sg:province":"Pays de Loire",
    "wof:name":"Elidis Boisson Services S.a.s.",
    "wof:placetype":"venue"
},
  "geometry": {"coordinates":[-1.440899,47.266781],"type":"Point"}
}