{
  "type": "Feature",
  "properties": {
    "addr:full":"Rue De La Lib\u00e9ration 59242 Genech Nord Pas-de-Calais 59242",
    "addr:postcode":"59242;59242",
    "addr:street":"Rue De La Libe\u0301Ration",
    "iso:country":"FR",
    "sg:address":"Rue De La Lib\u00e9ration 59242 Genech",
    "sg:classifiers":[
        {
            "category":"Professional",
            "subcategory":"Business Services",
            "type":"Services"
        }
    ],
    "sg:phone":"+33 3 20 84 57 08",
    "sg:postcode":"59242",
    "sg:province":"Nord Pas-de-Calais",
    "sg:tags":[
        "training",
        "advice"
    ],
    "wof:name":"Institut De Genech",
    "wof:placetype":"venue"
},
  "geometry": {"coordinates":[3.22135,50.530811],"type":"Point"}
}