{
  "type": "Feature",
  "properties": {
    "addr:full":"22, Rue des Tuileries - ZA, 67460 Souffelweyersheim Souffelweyersheim Alsace 67460",
    "addr:housenumber":"22",
    "addr:postcode":"67460;67460",
    "addr:street":"Rue Des Tuileries Za",
    "iso:country":"FR",
    "sg:address":"22, Rue des Tuileries - ZA, 67460 Souffelweyersheim",
    "sg:city":"Souffelweyersheim",
    "sg:orig_category":"Non-Classified Establishments",
    "sg:phone":"+33 3 88 20 08 84",
    "sg:postcode":"67460",
    "sg:province":"Alsace",
    "wof:name":"Facen S.a.",
    "wof:placetype":"venue"
},
  "geometry": {"coordinates":[7.74147,48.635509],"type":"Point"}
}