{
  "type": "Feature",
  "properties": {
    "addr:full":"48 Rue De Richelieu Paris Ile de France 75001",
    "addr:housenumber":"48",
    "addr:postcode":"75001",
    "addr:street":"Rue De Richelieu",
    "iso:country":"FR",
    "sg:address":"48 Rue De Richelieu",
    "sg:city":"Paris",
    "sg:classifiers":[
        {
            "category":"Banks & Credit Unions",
            "subcategory":"Financial Services",
            "type":"Services"
        }
    ],
    "sg:phone":"+33 1 42 60 05 05",
    "sg:postcode":"75001",
    "sg:province":"Ile de France",
    "sg:tags":[
        "banking",
        "finance",
        "insurance"
    ],
    "wof:name":"Centre D Etude Des Energies Et Therapies De Demain",
    "wof:placetype":"venue"
},
  "geometry": {"coordinates":[2.337256,48.866055],"type":"Point"}
}