{
  "type": "Feature",
  "properties": {
    "addr:full":"5 rue Jacques Monod 54250 Champigneulles Lorraine 54250",
    "addr:housenumber":"5",
    "addr:postcode":"54250;54250",
    "addr:street":"Rue Jacques Monod",
    "iso:country":"FR",
    "sg:address":"5 rue Jacques Monod 54250 Champigneulles",
    "sg:classifiers":[
        {
            "category":"Manufacturing",
            "subcategory":"Glass & Minerals",
            "type":"Manufacturing & Wholesale Goods"
        }
    ],
    "sg:phone":"+33 3 83 31 24 24",
    "sg:postcode":"54250",
    "sg:province":"Lorraine",
    "sg:tags":[
        "chemical",
        "consulting"
    ],
    "wof:name":"Separex Sa",
    "wof:placetype":"venue"
},
  "geometry": {"coordinates":[6.15747,48.740242],"type":"Point"}
}