{
  "type": "Feature",
  "properties": {
    "addr:full":"30 Rue Jules Beraud 04400 Barcelonnette Limousin",
    "addr:housenumber":"30",
    "addr:postcode":"04400",
    "addr:street":"Rue Jules Beraud",
    "iso:country":"FR",
    "sg:address":"30 Rue Jules Beraud 04400 Barcelonnette",
    "sg:classifiers":[
        {
            "category":"Manufacturing",
            "subcategory":"Chemicals & Compounds",
            "type":"Manufacturing & Wholesale Goods"
        }
    ],
    "sg:phone":"+33 4 92 81 01 39",
    "sg:province":"Limousin",
    "sg:tags":[
        "pharmaceutical",
        "energy",
        "chemistry",
        "-",
        "by-product"
    ],
    "wof:name":"Charvet",
    "wof:placetype":"venue"
},
  "geometry": {"coordinates":[6.650615,44.386532],"type":"Point"}
}