{
  "type": "Feature",
  "properties": {
    "addr:full":"105 rue de la R\u00e9publique; Fontenay le Comte; 85203 Champagne",
    "addr:housenumber":"105",
    "addr:postcode":"85203",
    "addr:street":"Rue De La Re\u0301Publique;Le Comte",
    "iso:country":"FR",
    "sg:address":"105 rue de la R\u00e9publique; Fontenay le Comte; 85203",
    "sg:classifiers":[
        {
            "category":"Banks & Credit Unions",
            "subcategory":"Bank",
            "type":"Services"
        }
    ],
    "sg:phone":"+33 2 51 51 18 51",
    "sg:province":"Champagne",
    "wof:name":"Banque De France",
    "wof:placetype":"venue"
},
  "geometry": {"coordinates":[-0.797388,46.463402],"type":"Point"}
}