{
  "type": "Feature",
  "properties": {
    "iso:country":"FR",
    "sg:address":"83, Bd Louis Armand, 53940 Saint Berthevin",
    "sg:orig_category":"Unclassifiable Establishments",
    "sg:phone":"+33 2 43 69 21 03",
    "sg:province":"Pays de Loire",
    "wof:name":"Imprimierie Madiot S.a.",
    "wof:placetype":"venue"
},
  "geometry": {"coordinates":[-0.809704,48.066231],"type":"Point"}
}