{
  "type": "Feature",
  "properties": {
    "addr:full":"85, Av. des Nations - ZI Parinord 2, 93420 Villepinte Ile de France",
    "addr:housenumber":"2",
    "addr:postcode":"93420",
    "addr:street":"85 Av. Des Nations Zi Parinord;Ile De France",
    "iso:country":"FR",
    "sg:address":"85, Av. des Nations - ZI Parinord 2, 93420 Villepinte",
    "sg:orig_category":"Unclassifiable Establishments",
    "sg:phone":"+33 825 33 14 00",
    "sg:province":"Ile de France",
    "wof:name":"Avon S.a.",
    "wof:placetype":"venue"
},
  "geometry": {"coordinates":[2.53979,48.955807],"type":"Point"}
}