{
  "type": "Feature",
  "properties": {
    "iso:country":"FR",
    "sg:address":"118 Rue De Bercy 75012 Paris",
    "sg:classifiers":[
        {
            "category":"Professional",
            "subcategory":"Advertising",
            "type":"Services"
        }
    ],
    "sg:phone":"+33 1 43 43 44 29",
    "sg:postcode":"75012",
    "sg:province":"Ile de France",
    "sg:tags":[
        "information",
        "medium",
        "communication"
    ],
    "wof:name":"Tv Bercy",
    "wof:placetype":"venue"
},
  "geometry": {"coordinates":[2.37992,48.839809],"type":"Point"}
}