{
  "type": "Feature",
  "properties": {
    "iso:country":"FR",
    "sg:address":"Place du 11 Novembre 1918",
    "sg:city":"Pouilly en Auxois",
    "sg:orig_category":"Unclassifiable Establishments",
    "sg:phone":"+33 3 80 90 81 78",
    "sg:postcode":"21320",
    "sg:province":"Bourgogne",
    "wof:name":"Caisse D'epargne De Bourgogne - Agence Pouilly-en-auxois",
    "wof:placetype":"venue"
},
  "geometry": {"coordinates":[4.555975,47.26255],"type":"Point"}
}