{
  "type": "Feature",
  "properties": {
    "iso:country":"FR",
    "sg:address":"114, Bd de l4\u00e8me Embouchure, 31200 Toulouse",
    "sg:orig_category":"Unclassifiable Establishments",
    "sg:phone":"+33 5 61 26 54 00",
    "sg:province":"Midi Pyr\u00e9n\u00e9es",
    "wof:name":"Guiraud Fr\u00e8re S.a.",
    "wof:placetype":"venue"
},
  "geometry": {"coordinates":[1.44954,43.639011],"type":"Point"}
}