{
  "type": "Feature",
  "properties": {
    "addr:full":"Rue de l'Egalit\u00e9 S\u00e9rignan Languedoc-Roussillon 34410",
    "addr:postcode":"34410",
    "addr:street":"Rue De L'Egalite \u0301 Se\u0301Rignan",
    "iso:country":"FR",
    "sg:address":"Rue de l'Egalit\u00e9",
    "sg:city":"S\u00e9rignan",
    "sg:orig_category":"Unclassifiable Establishments",
    "sg:phone":"+33 4 67 32 06 94",
    "sg:postcode":"34410",
    "sg:province":"Languedoc-Roussillon",
    "wof:name":"Megnint Mat\u00e9riaux S.a.r.l.",
    "wof:placetype":"venue"
},
  "geometry": {"coordinates":[3.283871,43.280586],"type":"Point"}
}