{
  "type": "Feature",
  "properties": {
    "addr:full":"34 Av De Bobigny Zi Le Terminal 93135 Noisy Le Sec Cedex Bobigny Ile de France 93000",
    "addr:postcode":"93135;93000",
    "addr:street":"34 Av De Bobigny Zi Le",
    "iso:country":"FR",
    "sg:address":"34 Av De Bobigny Zi Le Terminal 93135 Noisy Le Sec Cedex",
    "sg:city":"Bobigny",
    "sg:classifiers":[
        {
            "category":"Manufacturing",
            "subcategory":"Tools & Machinery",
            "type":"Manufacturing & Wholesale Goods"
        }
    ],
    "sg:phone":"+33 1 48 44 44 59",
    "sg:postcode":"93000",
    "sg:province":"Ile de France",
    "sg:tags":[
        "metallurgy",
        "-",
        "metalworking",
        "machine",
        "engineering",
        "mechanical"
    ],
    "wof:name":"Lc Constructeurs Sarl",
    "wof:placetype":"venue"
},
  "geometry": {"coordinates":[2.45075,48.889885],"type":"Point"}
}