{
  "type": "Feature",
  "properties": {
    "addr:full":"255 Rte Mittelhausbergen; Strasbourg; 67000 Strasbourg Alsace 67000",
    "addr:housenumber":"255",
    "addr:postcode":"67000;67000",
    "addr:street":"Rte Mittelhausbergen",
    "iso:country":"FR",
    "sg:address":"255 Rte Mittelhausbergen; Strasbourg; 67000",
    "sg:city":"Strasbourg",
    "sg:classifiers":[
        {
            "category":"Banks & Credit Unions",
            "subcategory":"Bank",
            "type":"Services"
        }
    ],
    "sg:phone":"+33 3388268138",
    "sg:postcode":"67000",
    "sg:province":"Alsace",
    "wof:name":"Sogenal, Soci\u00e9t\u00e9 G\u00e9n\u00e9rale Alsacienne",
    "wof:placetype":"venue"
},
  "geometry": {"coordinates":[7.73643,48.585079],"type":"Point"}
}