{
  "type": "Feature",
  "properties": {
    "addr:full":"102 Av Tolosane 31520 Ramonville St Agne Midi Pyr\u00e9n\u00e9es 31520",
    "addr:postcode":"31520;31520",
    "addr:street":"102 Av Tolosane;Ramonville St",
    "iso:country":"FR",
    "sg:address":"102 Av Tolosane 31520 Ramonville St Agne",
    "sg:classifiers":[
        {
            "category":"Travel",
            "subcategory":"Hotels & Motels",
            "type":"Entertainment"
        }
    ],
    "sg:phone":"+33 5 61 73 20 75",
    "sg:postcode":"31520",
    "sg:province":"Midi Pyr\u00e9n\u00e9es",
    "sg:tags":[
        "hotels",
        "business",
        "restaurant"
    ],
    "wof:name":"Chaumiere Sarl",
    "wof:placetype":"venue"
},
  "geometry": {"coordinates":[1.480021,43.539425],"type":"Point"}
}