{
  "type": "Feature",
  "properties": {
    "addr:full":"RN 98 - For\u00eat du Dom Bormes les Mimosas Provence-Alpes-C\u00f4te d'Azur 83230",
    "addr:postcode":"83230",
    "addr:street":"Rn 98 Fore\u0302T Du Dom Bormes Les Mimosas",
    "iso:country":"FR",
    "sg:address":"RN 98 - For\u00eat du Dom",
    "sg:city":"Bormes les Mimosas",
    "sg:orig_category":"Non-Classified Establishments",
    "sg:phone":"+33 4 94 71 18 52",
    "sg:postcode":"83230",
    "sg:province":"Provence-Alpes-C\u00f4te d'Azur",
    "wof:name":"Le Noyer E.a.r.l.",
    "wof:placetype":"venue"
},
  "geometry": {"coordinates":[6.337109,43.178749],"type":"Point"}
}