{
  "type": "Feature",
  "properties": {
    "iso:country":"FR",
    "sg:address":"39, Rue Santos Dumont, 75015 Paris",
    "sg:orig_category":"Non-Classified Establishments",
    "sg:phone":"+33 1 45 31 13 36",
    "sg:province":"Ile de France",
    "wof:name":"Soci\u00e9t\u00e9 Porphyre S.a.r.l.",
    "wof:placetype":"venue"
},
  "geometry": {"coordinates":[2.304441,48.832489],"type":"Point"}
}