{
  "type": "Feature",
  "properties": {
    "iso:country":"FR",
    "sg:address":"7 Rue Rene Dalloz 39260 Moirans En Montagne",
    "sg:classifiers":[
        {
            "category":"Manufacturing",
            "subcategory":"Rubber & Plastics",
            "type":"Manufacturing & Wholesale Goods"
        }
    ],
    "sg:phone":"+33 3 84 42 35 71",
    "sg:province":"Franche Comt\u00e9",
    "wof:name":"Millet 04",
    "wof:placetype":"venue"
},
  "geometry": {"coordinates":[5.725578,46.423073],"type":"Point"}
}