{
  "type": "Feature",
  "properties": {
    "addr:full":"7, Rue Alexandre Dumas, 38100 Grenoble Rhone-Alpes 38100",
    "addr:housenumber":"7",
    "addr:postcode":"38100;38100",
    "addr:street":"Rue Alexandre Dumas",
    "iso:country":"FR",
    "sg:address":"7, Rue Alexandre Dumas, 38100 Grenoble",
    "sg:orig_category":"Unclassifiable Establishments",
    "sg:phone":"+33 4 76 96 38 73",
    "sg:postcode":"38100",
    "sg:province":"Rhone-Alpes",
    "wof:name":"Entreprise N\u00e9ri",
    "wof:placetype":"venue"
},
  "geometry": {"coordinates":[5.709255,45.177807],"type":"Point"}
}