{
  "type": "Feature",
  "properties": {
    "iso:country":"FR",
    "sg:address":"B.P. 230, 42333 Roanne C\u00e9dex^^84, Rue de Charlieu, 42300 Roanne",
    "sg:orig_category":"Non-Classified Establishments",
    "sg:phone":"+33 4 77 71 17 14",
    "sg:postcode":"42300",
    "sg:province":"Rhone-Alpes",
    "wof:name":"Atelier Roannais De Maroquinerie S.a.r.l.",
    "wof:placetype":"venue"
},
  "geometry": {"coordinates":[4.040056,45.992947],"type":"Point"}
}