{
  "type": "Feature",
  "properties": {
    "iso:country":"FR",
    "sg:address":"22, Rue de la Convention, 41300 Salbris",
    "sg:city":"Salbris",
    "sg:orig_category":"Unclassifiable Establishments",
    "sg:phone":"+33 2 54 94 67 67",
    "sg:postcode":"41300",
    "sg:province":"Centre",
    "wof:name":"Standis S.a.",
    "wof:placetype":"venue"
},
  "geometry": {"coordinates":[2.047792,47.422119],"type":"Point"}
}