{
  "type": "Feature",
  "properties": {
    "iso:country":"FR",
    "sg:address":"45, Rue Jacquard - ZI 2, 27000 Evreux",
    "sg:orig_category":"Unclassifiable Establishments",
    "sg:phone":"+33 2 32 23 10 01",
    "sg:province":"Haute Normandie",
    "wof:name":"Feuvrais S.a.",
    "wof:placetype":"venue"
},
  "geometry": {"coordinates":[1.150283,49.027546],"type":"Point"}
}