{
  "type": "Feature",
  "properties": {
    "iso:country":"FR",
    "sg:address":"6, Rue Michel Chasles, 75012 Paris",
    "sg:orig_category":"Unclassifiable Establishments",
    "sg:phone":"+33 1 46 28 79 61",
    "sg:province":"Ile de France",
    "wof:name":"Dic T.p.a. S.a. - Dic Tout Par L'aimant",
    "wof:placetype":"venue"
},
  "geometry": {"coordinates":[2.374059,48.846504],"type":"Point"}
}