{
  "type": "Feature",
  "properties": {
    "iso:country":"FR",
    "sg:address":"28 Rue De La Victoire 93150 Le Blanc Mesnil",
    "sg:classifiers":[
        {
            "category":"Shopping",
            "type":"Retail Goods"
        }
    ],
    "sg:phone":"+33 1 48 65 21 38",
    "sg:postcode":"93150",
    "sg:province":"Ile de France",
    "sg:tags":[
        "metallurgy",
        "finished",
        "-",
        "metalworking",
        "metallic"
    ],
    "wof:name":"Seft",
    "wof:placetype":"venue"
},
  "geometry": {"coordinates":[2.446555,48.9398],"type":"Point"}
}