{
  "type": "Feature",
  "properties": {
    "iso:country":"FR",
    "sg:address":"Rue Du Fauge Zi Les Paluds Ii 13400 Aubagne",
    "sg:classifiers":[
        {
            "category":"Home & Garden",
            "subcategory":"Furniture",
            "type":"Retail Goods"
        }
    ],
    "sg:phone":"+33 4 42 70 22 46",
    "sg:province":"Champagne",
    "sg:tags":[
        "household",
        "wood"
    ],
    "wof:name":"Kristina Cuisines",
    "wof:placetype":"venue"
},
  "geometry": {"coordinates":[5.5687,43.292141],"type":"Point"}
}