{
  "type": "Feature",
  "properties": {
    "addr:full":"La Noe Bel air 44330 Vallet Pays de Loire 44330",
    "addr:postcode":"44330;44330",
    "addr:street":"Air",
    "iso:country":"FR",
    "sg:address":"La Noe Bel air 44330 Vallet",
    "sg:orig_category":"Non-Classified Establishments",
    "sg:phone":"+33 2 40 33 92 72",
    "sg:postcode":"44330",
    "sg:province":"Pays de Loire",
    "wof:name":"Comte De Malestroit E.a.r.l.",
    "wof:placetype":"venue"
},
  "geometry": {"coordinates":[-1.286009,47.178974],"type":"Point"}
}