{
  "type": "Feature",
  "properties": {
    "addr:full":"68 boulevard Lazer 13010 Marseille Poitou-Charentes",
    "addr:housenumber":"68",
    "addr:postcode":"13010",
    "addr:street":"Boulevard",
    "iso:country":"FR",
    "sg:address":"68 boulevard Lazer 13010 Marseille",
    "sg:classifiers":[
        {
            "category":"Bars & Pubs",
            "type":"Food & Drink"
        }
    ],
    "sg:phone":"+33 4 91 94 02 70",
    "sg:province":"Poitou-Charentes",
    "sg:tags":[
        "glue",
        "label",
        "wet"
    ],
    "wof:name":"Ste Etiquetages Rapides S.a.r.l.",
    "wof:placetype":"venue"
},
  "geometry": {"coordinates":[5.403096,43.281818],"type":"Point"}
}