{
  "type": "Feature",
  "properties": {
    "addr:full":"B.P. 11 Macau Aquitaine 33460",
    "addr:postcode":"33460",
    "addr:street":"B.P. 11 Macau",
    "iso:country":"FR",
    "sg:address":"B.P. 11",
    "sg:city":"Macau",
    "sg:orig_category":"Non-Classified Establishments",
    "sg:phone":"+33 5 57 88 07 64",
    "sg:postcode":"33460",
    "sg:province":"Aquitaine",
    "wof:name":"Ambrosia S.a.r.l.",
    "wof:placetype":"venue"
},
  "geometry": {"coordinates":[-0.712874,44.964851],"type":"Point"}
}