{
  "type": "Feature",
  "properties": {
    "addr:full":"57, Bd Vivier Merle, 69003 Lyon Rhone-Alpes 69003",
    "addr:housenumber":"57",
    "addr:postcode":"69003;69003",
    "addr:street":"Bd Vivier",
    "iso:country":"FR",
    "sg:address":"57, Bd Vivier Merle, 69003 Lyon",
    "sg:orig_category":"Non-Classified Establishments",
    "sg:phone":"+33 4 37 91 37 37",
    "sg:postcode":"69003",
    "sg:province":"Rhone-Alpes",
    "wof:name":"Ageca",
    "wof:placetype":"venue"
},
  "geometry": {"coordinates":[4.84978,45.760479],"type":"Point"}
}