{
  "type": "Feature",
  "properties": {
    "addr:full":"B.P. 5209, 31079 Toulouse C\u00e9dex 5^^9, Rue Marengo, 31500 Toulouse Midi Pyr\u00e9n\u00e9es",
    "addr:housenumber":"5;^ 9",
    "addr:postcode":"31079;31500",
    "addr:street":"B.P. 5209;^;Rue Marengo",
    "iso:country":"FR",
    "sg:address":"B.P. 5209, 31079 Toulouse C\u00e9dex 5^^9, Rue Marengo, 31500 Toulouse",
    "sg:orig_category":"Non-Classified Establishments",
    "sg:phone":"+33 5 61 10 10 00",
    "sg:province":"Midi Pyr\u00e9n\u00e9es",
    "wof:name":"S.n.c.f. - Soci\u00e9t\u00e9 Nationale De Chemins De Fer Fran\u00e7ais",
    "wof:placetype":"venue"
},
  "geometry": {"coordinates":[1.47517,43.60207],"type":"Point"}
}