{
  "type": "Feature",
  "properties": {
    "addr:full":"26, Av. de Verdun, 42000 Saint Etienne Rhone-Alpes",
    "addr:postcode":"42000",
    "addr:street":"26 Av. De Verdun",
    "iso:country":"FR",
    "sg:address":"26, Av. de Verdun, 42000 Saint Etienne",
    "sg:orig_category":"Non-Classified Establishments",
    "sg:phone":"+33 4 77 93 53 36",
    "sg:province":"Rhone-Alpes",
    "wof:name":"Ficc Audit S.a.r.l.",
    "wof:placetype":"venue"
},
  "geometry": {"coordinates":[4.377446,45.466312],"type":"Point"}
}