{
  "type": "Feature",
  "properties": {
    "addr:full":"B.P. 97, 25702 Valentigney C\u00e9dex^^1, Rue de la Lib\u00e9ration - ZI les Rives du Doubs, 25700 Valentigney Franche Comt\u00e9",
    "addr:postcode":"25702;25700",
    "addr:street":"B.P. 97;Rue De La Libe\u0301Ration Zi Les Rives Du Doubs;Franche Comte\u0301",
    "iso:country":"FR",
    "sg:address":"B.P. 97, 25702 Valentigney C\u00e9dex^^1, Rue de la Lib\u00e9ration - ZI les Rives du Doubs, 25700 Valentigney",
    "sg:orig_category":"Non-Classified Establishments",
    "sg:phone":"+33 3 81 34 13 35",
    "sg:province":"Franche Comt\u00e9",
    "wof:name":"Jean-paul Martini S.a.r.l.",
    "wof:placetype":"venue"
},
  "geometry": {"coordinates":[6.837825,47.464218],"type":"Point"}
}