{
  "type": "Feature",
  "properties": {
    "addr:full":"ZI Mouguerre Mouguerre Aquitaine 64990",
    "addr:postcode":"64990",
    "iso:country":"FR",
    "sg:address":"ZI Mouguerre",
    "sg:city":"Mouguerre",
    "sg:orig_category":"Non-Classified Establishments",
    "sg:phone":"+33 5 59 31 86 98",
    "sg:postcode":"64990",
    "sg:province":"Aquitaine",
    "wof:name":"Sicom S.a. - Soci\u00e9t\u00e9 Internationale Constructions M\u00e9caniques",
    "wof:placetype":"venue"
},
  "geometry": {"coordinates":[-1.417994,43.467365],"type":"Point"}
}