{
  "type": "Feature",
  "properties": {
    "addr:full":"19, Rue Jean Mace, 29200 Brest Brest Bretagne 29200",
    "addr:housenumber":"19",
    "addr:postcode":"29200;29200",
    "addr:street":"Rue Jean Mace",
    "iso:country":"FR",
    "sg:address":"19, Rue Jean Mace, 29200 Brest",
    "sg:city":"Brest",
    "sg:orig_category":"Non-Classified Establishments",
    "sg:phone":"+33 2 98 46 66 21",
    "sg:postcode":"29200",
    "sg:province":"Bretagne",
    "wof:name":"R\u00e9gie Networks Ouest S.a.",
    "wof:placetype":"venue"
},
  "geometry": {"coordinates":[-4.487404,48.386536],"type":"Point"}
}