{
  "type": "Feature",
  "properties": {
    "iso:country":"FR",
    "sg:address":"B.P. 24, 77170 Brie Comte Robert^^Rte de Ferolles, 77170 Brie Comte Robert",
    "sg:orig_category":"Non-Classified Establishments",
    "sg:phone":"+33 1 60 62 51 60",
    "sg:postcode":"77170",
    "sg:province":"Ile de France",
    "wof:name":"A.i.e. S.a. - Aries Industries Emboutissage",
    "wof:placetype":"venue"
},
  "geometry": {"coordinates":[2.612735,48.691845],"type":"Point"}
}