{
  "type": "Feature",
  "properties": {
    "iso:country":"FR",
    "sg:address":"B.P. 70411",
    "sg:city":"Rennes C\u00e9dex 7",
    "sg:orig_category":"Non-Classified Establishments",
    "sg:phone":"+33 2 99 25 55 00",
    "sg:postcode":"35704",
    "sg:province":"Bretagne",
    "wof:name":"Legris S.a.",
    "wof:placetype":"venue"
},
  "geometry": {"coordinates":[-1.67777,48.111721],"type":"Point"}
}