{
  "type": "Feature",
  "properties": {
    "addr:full":"6, Rue de Dinan - Immeuble le Saint Louis, 35000 Rennes Rennes Bretagne 35000",
    "addr:housenumber":"6;immeuble",
    "addr:postcode":"35000;35000",
    "addr:street":"Rue De Dinan",
    "iso:country":"FR",
    "sg:address":"6, Rue de Dinan - Immeuble le Saint Louis, 35000 Rennes",
    "sg:city":"Rennes",
    "sg:orig_category":"Unclassifiable Establishments",
    "sg:phone":"+33 2 99 30 04 04",
    "sg:postcode":"35000",
    "sg:province":"Bretagne",
    "wof:name":"Soci\u00e9t\u00e9 Alsacienne D'aluminium",
    "wof:placetype":"venue"
},
  "geometry": {"coordinates":[-1.685065,48.113693],"type":"Point"}
}