{
  "type": "Feature",
  "properties": {
    "iso:country":"FR",
    "sg:address":"6, Rue de Dinan - Immeuble le Saint Louis, 35000 Rennes",
    "sg:city":"Rennes",
    "sg:orig_category":"Unclassifiable Establishments",
    "sg:phone":"+33 2 99 30 04 04",
    "sg:postcode":"35000",
    "sg:province":"Bretagne",
    "wof:name":"Soci\u00e9t\u00e9 Alsacienne D'aluminium",
    "wof:placetype":"venue"
},
  "geometry": {"coordinates":[-1.685065,48.113693],"type":"Point"}
}