{
  "type": "Feature",
  "properties": {
    "addr:full":"4, Rue Jean Mac\u00e9, 93200 Saint Denis Ile de France",
    "addr:housenumber":"4",
    "addr:postcode":"93200",
    "addr:street":"Rue Jean Mace\u0301",
    "iso:country":"FR",
    "sg:address":"4, Rue Jean Mac\u00e9, 93200 Saint Denis",
    "sg:orig_category":"Unclassifiable Establishments",
    "sg:phone":"+33 1 42 43 60 59",
    "sg:province":"Ile de France",
    "wof:name":"M\u00e9canique Travaux Publics S.a.r.l.",
    "wof:placetype":"venue"
},
  "geometry": {"coordinates":[2.36368,48.929462],"type":"Point"}
}