{
  "type": "Feature",
  "properties": {
    "iso:country":"FR",
    "sg:address":"13, Rue des Battants, 31140 Saint Alban",
    "sg:orig_category":"Unclassifiable Establishments",
    "sg:phone":"+33 5 61 35 40 40",
    "sg:province":"Midi Pyr\u00e9n\u00e9es",
    "wof:name":"Sodiscol S.a.",
    "wof:placetype":"venue"
},
  "geometry": {"coordinates":[1.401089,43.697968],"type":"Point"}
}