{
  "type": "Feature",
  "properties": {
    "iso:country":"FR",
    "sg:address":"11, Rue de l'Industrie - ZI, 43110 Aurec sur Loire",
    "sg:city":"Aurec-sur-Loire",
    "sg:orig_category":"Non-Classified Establishments",
    "sg:phone":"+33 4 77 35 20 21",
    "sg:postcode":"43110",
    "sg:province":"Auvergne",
    "wof:name":"Interep S.a.",
    "wof:placetype":"venue"
},
  "geometry": {"coordinates":[4.200365,45.371178],"type":"Point"}
}