{
  "type": "Feature",
  "properties": {
    "addr:full":"41 Rue Du Four 75006 Paris Ile de France 75006",
    "addr:housenumber":"41",
    "addr:postcode":"75006;75006",
    "addr:street":"Rue Du Four",
    "iso:country":"FR",
    "sg:address":"41 Rue Du Four 75006 Paris",
    "sg:classifiers":[
        {
            "category":"Manufacturing",
            "subcategory":"Leather Goods",
            "type":"Manufacturing & Wholesale Goods"
        }
    ],
    "sg:phone":"+33 1 45 49 24 15",
    "sg:postcode":"75006",
    "sg:province":"Ile de France",
    "sg:tags":[
        "shoe"
    ],
    "wof:name":"La Bagagerie Service Presse Sa",
    "wof:placetype":"venue"
},
  "geometry": {"coordinates":[2.33254,48.85244],"type":"Point"}
}