{
  "type": "Feature",
  "properties": {
    "iso:country":"FR",
    "sg:address":"15, Rue Jean Poulmarch - ZAC du Chemin Vert, 95106 Argenteuil C\u00e9dex",
    "sg:orig_category":"Non-Classified Establishments",
    "sg:phone":"+33 1 39 98 02 34",
    "sg:province":"Ile-de-France",
    "wof:name":"Polet S.a.",
    "wof:placetype":"venue"
},
  "geometry": {"coordinates":[2.245075,48.942097],"type":"Point"}
}