{
  "type": "Feature",
  "properties": {
    "addr:full":"571, Av. de Croupillac, 30100 Al\u00e8s Languedoc-Roussillon",
    "addr:postcode":"30100",
    "addr:street":"571 Av. De Croupillac",
    "iso:country":"FR",
    "sg:address":"571, Av. de Croupillac, 30100 Al\u00e8s",
    "sg:orig_category":"Unclassifiable Establishments",
    "sg:phone":"+33 4 66 86 46 50",
    "sg:province":"Languedoc-Roussillon",
    "wof:name":"G\u00e9om\u00e9tal S.a.r.l.",
    "wof:placetype":"venue"
},
  "geometry": {"coordinates":[4.10537,44.13266],"type":"Point"}
}