{
  "type": "Feature",
  "properties": {
    "iso:country":"FR",
    "sg:address":"MAURY 66460 MAURY",
    "sg:classifiers":[
        {
            "category":"Wholesale",
            "subcategory":"Wine & Distilled Alcoholic Beverages",
            "type":"Manufacturing & Wholesale Goods"
        }
    ],
    "sg:phone":"+33 4 68 29 01 02",
    "sg:postcode":"66460",
    "sg:province":"Languedoc-Roussillon",
    "sg:tags":[
        "french"
    ],
    "wof:name":"Domaine Du Mas Amiel Sc",
    "wof:placetype":"venue"
},
  "geometry": {"coordinates":[2.593269,42.809971],"type":"Point"}
}