{
  "type": "Feature",
  "properties": {
    "addr:full":"1, Rue Castelbon de Beauxhotes, 34500 B\u00e9ziers Languedoc-Roussillon",
    "addr:housenumber":"1",
    "addr:postcode":"34500",
    "addr:street":"Rue Castelbon De Beauxhotes",
    "iso:country":"FR",
    "sg:address":"1, Rue Castelbon de Beauxhotes, 34500 B\u00e9ziers",
    "sg:orig_category":"Unclassifiable Establishments",
    "sg:phone":"+33 4 67 31 37 72",
    "sg:province":"Languedoc-Roussillon",
    "wof:name":"C.g.d.e. Distribution",
    "wof:placetype":"venue"
},
  "geometry": {"coordinates":[3.228054,43.343475],"type":"Point"}
}