{
  "type": "Feature",
  "properties": {
    "addr:full":"12, Rue F\u00e9lix Faure, 44100 Nantes Pays de Loire",
    "addr:housenumber":"12",
    "addr:postcode":"44100",
    "addr:street":"Rue Fe\u0301Lix Faure",
    "iso:country":"FR",
    "sg:address":"12, Rue F\u00e9lix Faure, 44100 Nantes",
    "sg:orig_category":"Unclassifiable Establishments",
    "sg:phone":"+33 2 40 67 44 44",
    "sg:province":"Pays de Loire",
    "wof:name":"H\u00e9lio Nantes S.a.",
    "wof:placetype":"venue"
},
  "geometry": {"coordinates":[-1.569511,47.228378],"type":"Point"}
}