{
  "type": "Feature",
  "properties": {
    "addr:full":"Tour Facto Paris La Defense Cedex Midi Pyr\u00e9n\u00e9es 92988",
    "addr:postcode":"defense;92988",
    "iso:country":"FR",
    "sg:address":"Tour Facto",
    "sg:city":"Paris La Defense Cedex",
    "sg:classifiers":[
        {
            "category":"Banks & Credit Unions",
            "subcategory":"Financial Services",
            "type":"Services"
        }
    ],
    "sg:phone":"+33 1 46 35 74 00",
    "sg:postcode":"92988",
    "sg:province":"Midi Pyr\u00e9n\u00e9es",
    "sg:tags":[
        "banking",
        "finance",
        "insurance"
    ],
    "wof:name":"Facto Cic",
    "wof:placetype":"venue"
},
  "geometry": {"coordinates":[2.24119,48.888939],"type":"Point"}
}