{
  "type": "Feature",
  "properties": {
    "addr:full":"106 ave Felix Faure; Paris; 75015 Ile de France 75015",
    "addr:housenumber":"106",
    "addr:postcode":"75015 ile;france 75015",
    "addr:street":"Ave Felix Faure",
    "iso:country":"FR",
    "sg:address":"106 ave Felix Faure; Paris; 75015",
    "sg:classifiers":[
        {
            "category":"Banks & Credit Unions",
            "subcategory":"Bank",
            "type":"Services"
        }
    ],
    "sg:phone":"+33 1 45 54 10 13",
    "sg:postcode":"75015",
    "sg:province":"Ile de France",
    "wof:name":"Soci\u00e9t\u00e9 G\u00e9n\u00e9rale",
    "wof:placetype":"venue"
},
  "geometry": {"coordinates":[2.281668,48.838718],"type":"Point"}
}