{
  "type": "Feature",
  "properties": {
    "addr:full":"B.P. 50352, 95942 Roissy C\u00e9dex^^13, Rue de la Perdrix, 93290 Tremblay en France Ile de France 93290",
    "addr:postcode":"95942;93290;93290",
    "addr:street":"Rue De La Perdrix",
    "iso:country":"FR",
    "sg:address":"B.P. 50352, 95942 Roissy C\u00e9dex^^13, Rue de la Perdrix, 93290 Tremblay en France",
    "sg:orig_category":"Non-Classified Establishments",
    "sg:phone":"+33 1 48 63 00 77",
    "sg:postcode":"93290",
    "sg:province":"Ile de France",
    "wof:name":"Artelux France S.a.",
    "wof:placetype":"venue"
},
  "geometry": {"coordinates":[2.56727,48.951214],"type":"Point"}
}