{
  "type": "Feature",
  "properties": {
    "addr:full":"12, Rue Maurice Fonvieille, 31000 Toulouse Midi Pyr\u00e9n\u00e9es 31000",
    "addr:housenumber":"12",
    "addr:postcode":"31000;31000",
    "addr:street":"Rue Maurice Fonvieille",
    "iso:country":"FR",
    "sg:address":"12, Rue Maurice Fonvieille, 31000 Toulouse",
    "sg:orig_category":"Non-Classified Establishments",
    "sg:phone":"+33 5 61 23 78 00",
    "sg:postcode":"31000",
    "sg:province":"Midi Pyr\u00e9n\u00e9es",
    "wof:name":"Business Conseil",
    "wof:placetype":"venue"
},
  "geometry": {"coordinates":[1.44908,43.603901],"type":"Point"}
}