{
  "type": "Feature",
  "properties": {
    "iso:country":"FR",
    "sg:address":"Arc 1800",
    "sg:city":"Administratif 73700 Bourg St Maurice",
    "sg:classifiers":[
        {
            "category":"Sports & Exercise",
            "subcategory":"Sports Center",
            "type":"Entertainment"
        }
    ],
    "sg:phone":"+33 4 79 04 24 04",
    "sg:postcode":"73700",
    "sg:province":"Rhone-Alpes",
    "sg:tags":[
        "machine",
        "engineering",
        "-",
        "mechanical"
    ],
    "wof:name":"Ste Les Montagnes De L Arc",
    "wof:placetype":"venue"
},
  "geometry": {"coordinates":[6.714042,45.582619],"type":"Point"}
}