{
  "type": "Feature",
  "properties": {
    "addr:full":"19 Rue Pierre Dupont 42300 Roanne Rhone-Alpes 42300",
    "addr:housenumber":"19",
    "addr:postcode":"42300;42300",
    "addr:street":"Rue Pierre Dupont;Rhone-Alpes",
    "iso:country":"FR",
    "sg:address":"19 Rue Pierre Dupont 42300 Roanne",
    "sg:classifiers":[
        {
            "category":"Shopping",
            "subcategory":"Clothing, Apparel, & Fashions",
            "type":"Retail Goods"
        }
    ],
    "sg:phone":"+33 4 77 71 03 99",
    "sg:postcode":"42300",
    "sg:province":"Rhone-Alpes",
    "sg:tags":[
        "textile",
        "clothing",
        "clothes"
    ],
    "wof:name":"Tornare Denise",
    "wof:placetype":"venue"
},
  "geometry": {"coordinates":[4.066484,46.048336],"type":"Point"}
}