{
  "type": "Feature",
  "properties": {
    "addr:full":"81/83, Rue Vauvenargues, 75018 Paris Ile de France 75018",
    "addr:housenumber":"81 / 83",
    "addr:postcode":"75018;75018",
    "addr:street":"Rue Vauvenargues",
    "iso:country":"FR",
    "sg:address":"81/83, Rue Vauvenargues, 75018 Paris",
    "sg:orig_category":"Non-Classified Establishments",
    "sg:phone":"+33 1 53 06 61 21",
    "sg:postcode":"75018",
    "sg:province":"Ile de France",
    "wof:name":"D\u00e9m\u00e9nagement Am\u00e9nagement Conse S.a.r.l.",
    "wof:placetype":"venue"
},
  "geometry": {"coordinates":[2.32951,48.897137],"type":"Point"}
}