{
  "type": "Feature",
  "properties": {
    "addr:full":"1225, Rue Blaise Pascal, 39000 Lons le Saunier Franche Comt\u00e9",
    "addr:housenumber":"1225",
    "addr:postcode":"39000",
    "addr:street":"Rue Blaise Pascal;Franche Comte\u0301",
    "iso:country":"FR",
    "sg:address":"1225, Rue Blaise Pascal, 39000 Lons le Saunier",
    "sg:orig_category":"Non-Classified Establishments",
    "sg:phone":"+33 3 84 24 46 40",
    "sg:province":"Franche Comt\u00e9",
    "wof:name":"Martin S.a.r.l.",
    "wof:placetype":"venue"
},
  "geometry": {"coordinates":[5.574289,46.682499],"type":"Point"}
}