{
  "type": "Feature",
  "properties": {
    "addr:full":"6, chemin de Palamans - Z.I., 39270 Orgelet Franche Comt\u00e9",
    "addr:housenumber":"6",
    "addr:postcode":"39270",
    "addr:street":"Chemin De Palamans Z.I.;Franche Comte\u0301",
    "iso:country":"FR",
    "sg:address":"6, chemin de Palamans - Z.I., 39270 Orgelet",
    "sg:orig_category":"Non-Classified Establishments",
    "sg:phone":"+33 3 84 87 18 00",
    "sg:province":"Franche Comt\u00e9",
    "wof:name":"V.p.i. S.a. - Verchere Plastiques Industriels",
    "wof:placetype":"venue"
},
  "geometry": {"coordinates":[5.610467,46.52206],"type":"Point"}
}