{
  "type": "Feature",
  "properties": {
    "addr:full":"14 Boulevard Georges Leygues 47300 Villeneuve Sur Lot Villeneuve-sur-Lot Aquitaine 47300",
    "addr:housenumber":"14",
    "addr:postcode":"47300;47300",
    "addr:street":"Boulevard Georges Leygues;Lot",
    "iso:country":"FR",
    "sg:address":"14 Boulevard Georges Leygues 47300 Villeneuve Sur Lot",
    "sg:city":"Villeneuve-sur-Lot",
    "sg:classifiers":[
        {
            "category":"Professional",
            "subcategory":"Printing & Photocopies",
            "type":"Services"
        }
    ],
    "sg:phone":"+33 5 53 70 89 66",
    "sg:postcode":"47300",
    "sg:province":"Aquitaine",
    "sg:tags":[
        "publishing"
    ],
    "wof:name":"La Depeche Et Le Petit Toulousain",
    "wof:placetype":"venue"
},
  "geometry": {"coordinates":[0.70678,44.408909],"type":"Point"}
}