{
  "type": "Feature",
  "properties": {
    "iso:country":"FR",
    "sg:address":"B.P. 10, 31908 Toulouse C\u00e9dex^^11, Bd L\u00e9opold Escande, 31000 Toulouse",
    "sg:orig_category":"Non-Classified Establishments",
    "sg:phone":"+33 5 61 62 44 24",
    "sg:postcode":"31000",
    "sg:province":"Midi Pyr\u00e9n\u00e9es",
    "wof:name":"Calfeutral E.u.r.l.",
    "wof:placetype":"venue"
},
  "geometry": {"coordinates":[1.44869,43.60574],"type":"Point"}
}