{
  "type": "Feature",
  "properties": {
    "addr:full":"Les C\u00f4teaux d'Albret 33540 Mesterrieux Mesterrieux Aquitaine 33540",
    "addr:postcode":"33540;33540",
    "iso:country":"FR",
    "sg:address":"Les C\u00f4teaux d'Albret 33540 Mesterrieux",
    "sg:city":"Mesterrieux",
    "sg:orig_category":"Non-Classified Establishments",
    "sg:phone":"+33 5 56 71 41 07",
    "sg:postcode":"33540",
    "sg:province":"Aquitaine",
    "wof:name":"Cave Coop\u00e9rative Les C\u00f4teaux D'albret",
    "wof:placetype":"venue"
},
  "geometry": {"coordinates":[-0.01558,44.647041],"type":"Point"}
}