{
  "type": "Feature",
  "properties": {
    "addr:full":"56, Bd du Bon Secours, 13014 Marseille Provence-Alpes-C\u00f4te d'Azur",
    "addr:housenumber":"56",
    "addr:postcode":"13014",
    "addr:street":"Bd Du Bon Secours",
    "iso:country":"FR",
    "sg:address":"56, Bd du Bon Secours, 13014 Marseille",
    "sg:orig_category":"Unclassifiable Establishments",
    "sg:phone":"+33 4 91 58 20 38",
    "sg:province":"Provence-Alpes-C\u00f4te d'Azur",
    "wof:name":"International Trade And Transit S.a.r.l.",
    "wof:placetype":"venue"
},
  "geometry": {"coordinates":[5.3817,43.320019],"type":"Point"}
}