{
  "type": "Feature",
  "properties": {
    "iso:country":"FR",
    "sg:address":"56, Bd du Bon Secours, 13014 Marseille",
    "sg:orig_category":"Unclassifiable Establishments",
    "sg:phone":"+33 4 91 58 20 38",
    "sg:province":"Provence-Alpes-C\u00f4te d'Azur",
    "wof:name":"International Trade And Transit S.a.r.l.",
    "wof:placetype":"venue"
},
  "geometry": {"coordinates":[5.3817,43.320019],"type":"Point"}
}