{
  "type": "Feature",
  "properties": {
    "addr:full":"88 Ave du G\u00e9n\u00e9ral Leclerc; Bordeaux; 33200 Bordeaux Aquitaine 33200",
    "addr:postcode":"33200;33200",
    "addr:street":"88 Ave Du Ge\u0301Ne\u0301Ral Leclerc",
    "iso:country":"FR",
    "sg:address":"88 Ave du G\u00e9n\u00e9ral Leclerc; Bordeaux; 33200",
    "sg:city":"Bordeaux",
    "sg:classifiers":[
        {
            "category":"Banks & Credit Unions",
            "subcategory":"Bank",
            "type":"Services"
        }
    ],
    "sg:phone":"+33 5 56 08 00 01",
    "sg:postcode":"33200",
    "sg:province":"Aquitaine",
    "wof:name":"Cr\u00e9dit Lyonnais Sa",
    "wof:placetype":"venue"
},
  "geometry": {"coordinates":[-0.610379,44.853569],"type":"Point"}
}