{
  "type": "Feature",
  "properties": {
    "addr:full":"10, Impasse des Lavandi\u00e8res, 14220 Thury Harcourt Barbery Basse Normandie 14220",
    "addr:housenumber":"10",
    "addr:postcode":"14220;14220",
    "addr:street":"Impasse Des Lavandie\u0300Res",
    "iso:country":"FR",
    "sg:address":"10, Impasse des Lavandi\u00e8res, 14220 Thury Harcourt",
    "sg:city":"Barbery",
    "sg:orig_category":"Unclassifiable Establishments",
    "sg:phone":"+33 2 31 79 70 15",
    "sg:postcode":"14220",
    "sg:province":"Basse Normandie",
    "wof:name":"Emaillerie Normande S.a.r.l.",
    "wof:placetype":"venue"
},
  "geometry": {"coordinates":[-0.482026,48.988503],"type":"Point"}
}