{
  "type": "Feature",
  "properties": {
    "addr:full":"14, Rue de la Cellophane, 78711 Mantes la Ville Vill\u00e9 Alsace 67220",
    "addr:housenumber":"14",
    "addr:postcode":"78711;67220",
    "addr:street":"Rue De La Cellophane",
    "iso:country":"FR",
    "sg:address":"14, Rue de la Cellophane, 78711 Mantes la Ville",
    "sg:city":"Vill\u00e9",
    "sg:orig_category":"Unclassifiable Establishments",
    "sg:phone":"+33 1 30 92 52 52",
    "sg:postcode":"67220",
    "sg:province":"Alsace",
    "wof:name":"Omni - M\u00e9tal Service S.a.",
    "wof:placetype":"venue"
},
  "geometry": {"coordinates":[1.725112,48.980488],"type":"Point"}
}