{
  "type": "Feature",
  "properties": {
    "addr:full":"5 All Joseph Bumb 67500 Haguenau Haguenau Alsace 67500",
    "addr:housenumber":"5",
    "addr:postcode":"67500;67500",
    "addr:street":"All Joseph Bumb",
    "iso:country":"FR",
    "sg:address":"5 All Joseph Bumb 67500 Haguenau",
    "sg:city":"Haguenau",
    "sg:classifiers":[
        {
            "category":"Professional",
            "type":"Services"
        }
    ],
    "sg:phone":"+33 3 88 73 00 98",
    "sg:postcode":"67500",
    "sg:province":"Alsace",
    "sg:tags":[
        "transport",
        "road"
    ],
    "wof:name":"Haguenau Transports Sa",
    "wof:placetype":"venue"
},
  "geometry": {"coordinates":[7.759416,48.829037],"type":"Point"}
}