{
  "type": "Feature",
  "properties": {
    "addr:full":"8 rue Royale; Paris; 75008 Ile de France 75008",
    "addr:housenumber":"8",
    "addr:postcode":"75008 ile;france 75008",
    "addr:street":"Rue Royale",
    "iso:country":"FR",
    "sg:address":"8 rue Royale; Paris; 75008",
    "sg:classifiers":[
        {
            "category":"Banks & Credit Unions",
            "subcategory":"Bank",
            "type":"Services"
        }
    ],
    "sg:phone":"+33 1 42 96 61 08",
    "sg:postcode":"75008",
    "sg:province":"Ile de France",
    "wof:name":"Cassa Di Risparmio, Di Genova E Imperia",
    "wof:placetype":"venue"
},
  "geometry": {"coordinates":[2.322751,48.867485],"type":"Point"}
}