{
  "type": "Feature",
  "properties": {
    "addr:full":"18 Rue De La Fontaine Au Roi 75011 Paris Ile de France 75011",
    "addr:housenumber":"18",
    "addr:postcode":"75011;75011",
    "addr:street":"Rue De La Fontaine Au Roi",
    "iso:country":"FR",
    "sg:address":"18 Rue De La Fontaine Au Roi 75011 Paris",
    "sg:classifiers":[
        {
            "category":"Shopping",
            "subcategory":"Hobbies, Toys, & Games",
            "type":"Retail Goods"
        }
    ],
    "sg:phone":"+33 1 49 23 87 40",
    "sg:postcode":"75011",
    "sg:province":"Ile de France",
    "sg:tags":[
        "product",
        "miscellaneous",
        "entertainment"
    ],
    "wof:name":"Selmer Et Cie",
    "wof:placetype":"venue"
},
  "geometry": {"coordinates":[2.370292,48.868279],"type":"Point"}
}