{
  "type": "Feature",
  "properties": {
    "iso:country":"FR",
    "sg:address":"Rte d'Etreux",
    "sg:city":"Venerolles",
    "sg:orig_category":"Non-Classified Establishments",
    "sg:phone":"+33 3 23 60 60 02",
    "sg:postcode":"02510",
    "sg:province":"Picardie",
    "wof:name":"Bouvart Anciens Etablissements S.a.",
    "wof:placetype":"venue"
},
  "geometry": {"coordinates":[3.65712,49.995529],"type":"Point"}
}