{
  "type": "Feature",
  "properties": {
    "addr:full":"2 Rue Gutemberg 77440 Lizy Sur Ourcq Ile de France 77440",
    "addr:housenumber":"2",
    "addr:postcode":"77440;77440",
    "addr:street":"Rue Gutemberg",
    "iso:country":"FR",
    "sg:address":"2 Rue Gutemberg 77440 Lizy Sur Ourcq",
    "sg:classifiers":[
        {
            "category":"Manufacturing",
            "subcategory":"Metals",
            "type":"Manufacturing & Wholesale Goods"
        }
    ],
    "sg:phone":"+33 1 60 01 89 00",
    "sg:postcode":"77440",
    "sg:province":"Ile de France",
    "sg:tags":[
        "metallurgy",
        "-",
        "metalworking",
        "metallic",
        "machine",
        "engineering",
        "finished",
        "mechanical"
    ],
    "wof:name":"Ets Bariot",
    "wof:placetype":"venue"
},
  "geometry": {"coordinates":[3.023166,49.027592],"type":"Point"}
}