{
  "type": "Feature",
  "properties": {
    "iso:country":"FR",
    "sg:address":"ZA Le Moulin",
    "sg:city":"Bellignat",
    "sg:orig_category":"Non-Classified Establishments",
    "sg:phone":"+33 4 74 73 55 27",
    "sg:postcode":"01810",
    "sg:province":"Rhone-Alpes",
    "wof:name":"Huca Proto S.a.",
    "wof:placetype":"venue"
},
  "geometry": {"coordinates":[-71.166031,42.649849],"type":"Point"}
}