{
  "type": "Feature",
  "properties": {
    "addr:full":"14, Rue JB Colbert - ZI Ouest, 10600 La Chapelle Saint Luc Champagne",
    "addr:housenumber":"14",
    "addr:postcode":"10600",
    "addr:street":"Rue Jb Colbert Zi Ouest",
    "iso:country":"FR",
    "sg:address":"14, Rue JB Colbert - ZI Ouest, 10600 La Chapelle Saint Luc",
    "sg:orig_category":"Unclassifiable Establishments",
    "sg:phone":"+33 3 25 79 33 23",
    "sg:province":"Champagne",
    "wof:name":"Collin Etanch\u00e9it\u00e9 S.a.r.l.",
    "wof:placetype":"venue"
},
  "geometry": {"coordinates":[4.04779,48.311729],"type":"Point"}
}