{
  "type": "Feature",
  "properties": {
    "addr:full":"5 Allee Des Chataigners 19360 Malemort Sur Correze Limousin 19360",
    "addr:housenumber":"5",
    "addr:postcode":"19360;19360",
    "addr:street":"Allee Des Chataigners",
    "iso:country":"FR",
    "sg:address":"5 Allee Des Chataigners 19360 Malemort Sur Correze",
    "sg:classifiers":[
        {
            "category":"Manufacturing",
            "subcategory":"Tools & Machinery",
            "type":"Manufacturing & Wholesale Goods"
        }
    ],
    "sg:phone":"+33 5 55 92 05 34",
    "sg:postcode":"19360",
    "sg:province":"Limousin",
    "sg:tags":[
        "equipment",
        "measurement",
        "-",
        "precision",
        "instrument"
    ],
    "wof:name":"Antignac Sarl",
    "wof:placetype":"venue"
},
  "geometry": {"coordinates":[1.5838,45.176723],"type":"Point"}
}