{
  "type": "Feature",
  "properties": {
    "iso:country":"FR",
    "sg:address":"10, Av Victor Pilhes, 09400 Tarascon sur Ari\u00e8ge",
    "sg:orig_category":"Unclassifiable Establishments",
    "sg:phone":"+33 5 61 05 88 05",
    "sg:province":"Midi Pyr\u00e9n\u00e9es",
    "wof:name":"B.p.p.o.a.a.",
    "wof:placetype":"venue"
},
  "geometry": {"coordinates":[1.60349,42.851376],"type":"Point"}
}