{
  "type": "Feature",
  "properties": {
    "iso:country":"FR",
    "sg:address":"85 Av Victor Hugo 92563 Rueil Malmaison",
    "sg:classifiers":[
        {
            "category":"Manufacturing",
            "subcategory":"Chemicals & Compounds",
            "type":"Manufacturing & Wholesale Goods"
        }
    ],
    "sg:phone":"+33 1 47 10 10 50",
    "sg:province":"Picardie",
    "sg:tags":[
        "pharmaceutical",
        "energy",
        "chemistry",
        "-",
        "by-product"
    ],
    "wof:name":"Caldeo Sa",
    "wof:placetype":"venue"
},
  "geometry": {"coordinates":[2.17561,48.88596],"type":"Point"}
}