{
  "type": "Feature",
  "properties": {
    "iso:country":"FR",
    "sg:address":"15 Rue Paul Bert 75011 Paris",
    "sg:orig_category":"Miscellaneous Products",
    "sg:phone":"+33 1 43 71 77 79",
    "sg:postcode":"75011",
    "sg:province":"Ile de France",
    "wof:name":"Rocher Riocreux Le Couturier De La Reliure",
    "wof:placetype":"venue"
},
  "geometry": {"coordinates":[2.384519,48.852119],"type":"Point"}
}