{
  "type": "Feature",
  "properties": {
    "iso:country":"FR",
    "sg:address":"32 rue Parisis; Dreux; 28101",
    "sg:classifiers":[
        {
            "category":"Banks & Credit Unions",
            "subcategory":"Bank",
            "type":"Services"
        }
    ],
    "sg:phone":"+33 2 37 46 00 90",
    "sg:province":"Centre",
    "wof:name":"Banque De France",
    "wof:placetype":"venue"
},
  "geometry": {"coordinates":[1.366823,48.737724],"type":"Point"}
}