{
  "type": "Feature",
  "properties": {
    "iso:country":"FR",
    "sg:address":"ZI la Ville",
    "sg:city":"Bon Encontre",
    "sg:orig_category":"Unclassifiable Establishments",
    "sg:phone":"+33 5 53 77 42 42",
    "sg:postcode":"47240",
    "sg:province":"Aquitaine",
    "wof:name":"Caruelle Nicolas S.a.",
    "wof:placetype":"venue"
},
  "geometry": {"coordinates":[0.668345,44.186184],"type":"Point"}
}