{
  "type": "Feature",
  "properties": {
    "addr:full":"Rue De La Gaudree Zi De La Gaudree 91410 Dourdan Ile de France 91410",
    "addr:postcode":"91410;ile;91410",
    "addr:street":"Rue De La Gaudree Zi De La Gaudree;France",
    "iso:country":"FR",
    "sg:address":"Rue De La Gaudree Zi De La Gaudree 91410 Dourdan",
    "sg:classifiers":[
        {
            "category":"Manufacturing",
            "subcategory":"Rubber & Plastics",
            "type":"Manufacturing & Wholesale Goods"
        }
    ],
    "sg:phone":"+33 1 64 59 56 80",
    "sg:postcode":"91410",
    "sg:province":"Ile de France",
    "sg:tags":[
        "metallurgy",
        "finished",
        "-",
        "metalworking",
        "metallic"
    ],
    "wof:name":"Rouxel Sa",
    "wof:placetype":"venue"
},
  "geometry": {"coordinates":[2.01121,48.528149],"type":"Point"}
}