{
  "type": "Feature",
  "properties": {
    "iso:country":"FR",
    "sg:address":"A\u00e9rodrome d'Auxerre Branches",
    "sg:city":"Appoigny",
    "sg:orig_category":"Unclassifiable Establishments",
    "sg:phone":"+33 3 86 48 20 22",
    "sg:postcode":"89380",
    "sg:province":"Bourgogne",
    "wof:name":"Bayo S.a.r.l.",
    "wof:placetype":"venue"
},
  "geometry": {"coordinates":[3.52197,47.877018],"type":"Point"}
}