{
  "type": "Feature",
  "properties": {
    "iso:country":"FR",
    "sg:address":"30 Rue Condorcet 95157 Taverny",
    "sg:city":"Condorcet",
    "sg:classifiers":[
        {
            "category":"Manufacturing",
            "subcategory":"Tools & Machinery",
            "type":"Manufacturing & Wholesale Goods"
        }
    ],
    "sg:phone":"+33 1 34 18 33 22",
    "sg:postcode":"26110",
    "sg:province":"Rhone-Alpes",
    "sg:tags":[
        "equipment",
        "measurement",
        "-",
        "precision",
        "instrument"
    ],
    "wof:name":"Gazfio Sa",
    "wof:placetype":"venue"
},
  "geometry": {"coordinates":[2.189701,49.028191],"type":"Point"}
}