{
  "type": "Feature",
  "properties": {
    "addr:full":"57, Bd Vivier Merle, 69429 Lyon C\u00e9dex Rhone-Alpes",
    "addr:housenumber":"57",
    "addr:postcode":"69429",
    "addr:street":"Bd Vivier",
    "iso:country":"FR",
    "sg:address":"57, Bd Vivier Merle, 69429 Lyon C\u00e9dex",
    "sg:orig_category":"Non-Classified Establishments",
    "sg:phone":"+33 4 72 68 98 17",
    "sg:province":"Rhone-Alpes",
    "wof:name":"Lufthansa",
    "wof:placetype":"venue"
},
  "geometry": {"coordinates":[4.86843,45.751369],"type":"Point"}
}