{
  "type": "Feature",
  "properties": {
    "addr:full":"B.P. 7415, 38074 Saint Quentin Fallavier C\u00e9dex^^3, Rue de la Haye - Parc d'Affaires Silic, 38070 Sai Rhone-Alpes 38070",
    "addr:housenumber":"38074",
    "addr:postcode":"38070;38070",
    "addr:street":"B.P. 7415;Rue De La Haye Parc D'Affaires Silic",
    "iso:country":"FR",
    "sg:address":"B.P. 7415, 38074 Saint Quentin Fallavier C\u00e9dex^^3, Rue de la Haye - Parc d'Affaires Silic, 38070 Sai",
    "sg:orig_category":"Non-Classified Establishments",
    "sg:phone":"+33 4 74 94 62 60",
    "sg:postcode":"38070",
    "sg:province":"Rhone-Alpes",
    "wof:name":"Spigraph Images S.a.",
    "wof:placetype":"venue"
},
  "geometry": {"coordinates":[5.101862,45.656334],"type":"Point"}
}