{
  "type": "Feature",
  "properties": {
    "addr:full":"157 Bd Haussmann 75803 Paris Cedex 08 Ile de France",
    "addr:housenumber":"157",
    "addr:postcode":"75803",
    "addr:street":"Bd Haussmann;Ile De France",
    "iso:country":"FR",
    "sg:address":"157 Bd Haussmann 75803 Paris Cedex 08",
    "sg:classifiers":[
        {
            "category":"Banks & Credit Unions",
            "subcategory":"Financial Services",
            "type":"Services"
        }
    ],
    "sg:phone":"+33 1 53 53 23 23",
    "sg:province":"Ile de France",
    "sg:tags":[
        "banking",
        "insurance",
        "institution",
        "finance"
    ],
    "wof:name":"Banque Finama",
    "wof:placetype":"venue"
},
  "geometry": {"coordinates":[2.309261,48.874969],"type":"Point"}
}