{
  "type": "Feature",
  "properties": {
    "addr:full":"9 /11 Rue George Enesco 94008 Creteil Cedex Pays de Loire",
    "addr:housenumber":"9 / 11",
    "addr:postcode":"94008 creteil cedex pays",
    "addr:street":"Rue George Enesco",
    "iso:country":"FR",
    "sg:address":"9 /11 Rue George Enesco 94008 Creteil Cedex",
    "sg:classifiers":[
        {
            "category":"Professional",
            "subcategory":"Computer Services",
            "type":"Services"
        }
    ],
    "sg:phone":"+33 1 43 99 22 49",
    "sg:province":"Pays de Loire",
    "sg:tags":[
        "information",
        "technology",
        "software"
    ],
    "wof:name":"Visualsoft Sa",
    "wof:placetype":"venue"
},
  "geometry": {"coordinates":[2.447267,48.796803],"type":"Point"}
}