{
  "type": "Feature",
  "properties": {
    "addr:full":"21, Rue L\u00e9on Geffroy, 94400 Vitry sur Seine Ile de France",
    "addr:housenumber":"21",
    "addr:postcode":"94400",
    "addr:street":"Rue Le\u0301On Geffroy",
    "iso:country":"FR",
    "sg:address":"21, Rue L\u00e9on Geffroy, 94400 Vitry sur Seine",
    "sg:orig_category":"Unclassifiable Establishments",
    "sg:phone":"+33 1 46 82 05 05",
    "sg:province":"Ile de France",
    "wof:name":"W.p.i. S.a. - William Pitters International La Guilde Du Vin",
    "wof:placetype":"venue"
},
  "geometry": {"coordinates":[2.408843,48.776279],"type":"Point"}
}