{
  "type": "Feature",
  "properties": {
    "iso:country":"FR",
    "sg:address":"B.P. 17, 74131 Bonneville C\u00e9dex^^105, Rue des Sancelles - ZI des Bordets, 74130 Bonneville",
    "sg:orig_category":"Non-Classified Establishments",
    "sg:phone":"+33 4 50 97 09 56",
    "sg:postcode":"74130",
    "sg:province":"Rhone-Alpes",
    "wof:name":"Faucigny Viandes Perier S.a.",
    "wof:placetype":"venue"
},
  "geometry": {"coordinates":[6.388322,45.95652],"type":"Point"}
}