{
  "type": "Feature",
  "properties": {
    "iso:country":"FR",
    "sg:address":"32",
    "sg:city":"Lices; Arles",
    "sg:classifiers":[
        {
            "category":"Banks & Credit Unions",
            "subcategory":"Bank",
            "type":"Services"
        }
    ],
    "sg:phone":"+33 3390935320",
    "wof:name":"Banque Populaire, Provencale Et Corse",
    "wof:placetype":"venue"
},
  "geometry": {"coordinates":[-84.198135,32.118336],"type":"Point"}
}