{
  "type": "Feature",
  "properties": {
    "addr:full":"90 Rue Des Sources 69230 St Genis Laval Rhone-Alpes 69230",
    "addr:housenumber":"90",
    "addr:postcode":"69230;69230",
    "addr:street":"Rue Des Sources;Genis;Rhone-Alpes",
    "iso:country":"FR",
    "sg:address":"90 Rue Des Sources 69230 St Genis Laval",
    "sg:classifiers":[
        {
            "category":"Building & Trades",
            "subcategory":"Construction",
            "type":"Services"
        }
    ],
    "sg:phone":"+33 4 72 66 35 20",
    "sg:postcode":"69230",
    "sg:province":"Rhone-Alpes",
    "sg:tags":[
        "work",
        "public"
    ],
    "wof:name":"Gerland Lyon Snc",
    "wof:placetype":"venue"
},
  "geometry": {"coordinates":[4.814538,45.692211],"type":"Point"}
}