{
  "type": "Feature",
  "properties": {
    "addr:full":"49, Rue de l'Eglise, 68480 Fislis Fislis Alsace 68480",
    "addr:housenumber":"49",
    "addr:postcode":"68480;68480",
    "addr:street":"Rue De L'Eglise;Fislis",
    "iso:country":"FR",
    "sg:address":"49, Rue de l'Eglise, 68480 Fislis",
    "sg:city":"Fislis",
    "sg:orig_category":"Unclassifiable Establishments",
    "sg:phone":"+33 3 89 40 71 23",
    "sg:postcode":"68480",
    "sg:province":"Alsace",
    "wof:name":"Heinis Et Fils Carrosserie S.a.r.l.",
    "wof:placetype":"venue"
},
  "geometry": {"coordinates":[7.381973,47.50499],"type":"Point"}
}