{
  "type": "Feature",
  "properties": {
    "addr:full":"B.P. 134, 76051 Le Havre C\u00e9dex^^Zone Industrielle Portuaire, 76600 Le Havre Haute Normandie",
    "addr:housenumber":"b.p. 134",
    "addr:postcode":"76051;76600",
    "addr:street":"Portuaire",
    "iso:country":"FR",
    "sg:address":"B.P. 134, 76051 Le Havre C\u00e9dex^^Zone Industrielle Portuaire, 76600 Le Havre",
    "sg:orig_category":"Non-Classified Establishments",
    "sg:phone":"+33 2 32 72 15 15",
    "sg:province":"Haute Normandie",
    "wof:name":"Renault S.a.",
    "wof:placetype":"venue"
},
  "geometry": {"coordinates":[0.101405,49.493511],"type":"Point"}
}