{
  "type": "Feature",
  "properties": {
    "iso:country":"FR",
    "sg:address":"1, Rue Chemin de Fer, 93000 Bobigny",
    "sg:orig_category":"Unclassifiable Establishments",
    "sg:phone":"+33 1 48 32 80 80",
    "sg:province":"Ile de France",
    "wof:name":"Distribution Bois Et Menuiseries S.a.r.l.",
    "wof:placetype":"venue"
},
  "geometry": {"coordinates":[2.42892,48.911572],"type":"Point"}
}