{
  "type": "Feature",
  "properties": {
    "iso:country":"FR",
    "sg:address":"59, Rue de la R\u00e9publique, 76240 Bonsecours",
    "sg:orig_category":"Unclassifiable Establishments",
    "sg:phone":"+33 2 35 89 26 51",
    "sg:province":"Haute Normandie",
    "wof:name":"I.b.l. Graphique S.a.",
    "wof:placetype":"venue"
},
  "geometry": {"coordinates":[1.112363,49.427406],"type":"Point"}
}