{
  "type": "Feature",
  "properties": {
    "addr:full":"ZI de la Tr\u00e9sorerie Wimille Nord Pas-de-Calais 62126",
    "addr:postcode":"62126",
    "addr:street":"Zi De La Tre\u0301Sorerie Wimille Nord",
    "iso:country":"FR",
    "sg:address":"ZI de la Tr\u00e9sorerie",
    "sg:city":"Wimille",
    "sg:orig_category":"Unclassifiable Establishments",
    "sg:phone":"+33 3 21 87 56 99",
    "sg:postcode":"62126",
    "sg:province":"Nord Pas-de-Calais",
    "wof:name":"Les Entr\u00e9es De La Mer S.a.",
    "wof:placetype":"venue"
},
  "geometry": {"coordinates":[1.631271,50.764091],"type":"Point"}
}