{
  "type": "Feature",
  "properties": {
    "addr:full":"1, rue Emile Verhague, 27380 Fleury sur Andelle Haute Normandie",
    "addr:housenumber":"1",
    "addr:postcode":"27380",
    "addr:street":"Rue Emile Verhague;Andelle Haute Normandie",
    "iso:country":"FR",
    "sg:address":"1, rue Emile Verhague, 27380 Fleury sur Andelle",
    "sg:orig_category":"Unclassifiable Establishments",
    "sg:phone":"+33 2 32 49 49 36",
    "sg:province":"Haute Normandie",
    "wof:name":"Lenud Jean-marie",
    "wof:placetype":"venue"
},
  "geometry": {"coordinates":[1.356642,49.360863],"type":"Point"}
}