{
  "type": "Feature",
  "properties": {
    "iso:country":"FR",
    "sg:address":"Z.A. Lacombe 83690 Salernes",
    "sg:classifiers":[
        {
            "category":"Deli",
            "type":"Food & Drink"
        }
    ],
    "sg:phone":"+33 4 94 70 60 68",
    "sg:province":"Basse Normandie",
    "sg:tags":[
        "delicatessen"
    ],
    "wof:name":"Soleillou Sa",
    "wof:placetype":"venue"
},
  "geometry": {"coordinates":[6.234065,43.563431],"type":"Point"}
}