{
  "type": "Feature",
  "properties": {
    "iso:country":"FR",
    "sg:address":"23, Rte du Mortier Vannerie, 44120 Vertou",
    "sg:orig_category":"Unclassifiable Establishments",
    "sg:phone":"+33 2 51 79 40 00",
    "sg:province":"Pays de Loire",
    "wof:name":"O.c.p. R\u00e9partition",
    "wof:placetype":"venue"
},
  "geometry": {"coordinates":[-1.496129,47.184689],"type":"Point"}
}