{
  "type": "Feature",
  "properties": {
    "addr:full":"B.P. 85, 69280 Marcy l'Etoile^^Parc d'Activit\u00e9s de Sainte Consorce, 69280 Marcy l'Etoile Rhone-Alpes 69280",
    "addr:postcode":"69280;69280;69280",
    "addr:street":"B.P. 85",
    "iso:country":"FR",
    "sg:address":"B.P. 85, 69280 Marcy l'Etoile^^Parc d'Activit\u00e9s de Sainte Consorce, 69280 Marcy l'Etoile",
    "sg:orig_category":"Non-Classified Establishments",
    "sg:phone":"+33 4 78 87 40 67",
    "sg:postcode":"69280",
    "sg:province":"Rhone-Alpes",
    "wof:name":"Coriex S.a.",
    "wof:placetype":"venue"
},
  "geometry": {"coordinates":[2.02819,50.033714],"type":"Point"}
}