{
  "type": "Feature",
  "properties": {
    "iso:country":"FR",
    "sg:address":"25 quai Gabriel Peri; Tulle; 19000",
    "sg:classifiers":[
        {
            "category":"Banks & Credit Unions",
            "subcategory":"Bank",
            "type":"Services"
        }
    ],
    "sg:phone":"+33 5 55 26 22 84",
    "sg:postcode":"19000",
    "sg:province":"Limousin",
    "wof:name":"Banque Tarneaud",
    "wof:placetype":"venue"
},
  "geometry": {"coordinates":[1.767295,45.263268],"type":"Point"}
}