{
  "type": "Feature",
  "properties": {
    "addr:full":"2, Place du Concert, 59800 Lille Nord Pas-de-Calais 59800",
    "addr:housenumber":"2",
    "addr:postcode":"59800;59800",
    "addr:street":"Place Du Concert",
    "iso:country":"FR",
    "sg:address":"2, Place du Concert, 59800 Lille",
    "sg:orig_category":"Non-Classified Establishments",
    "sg:phone":"+33 3 20 13 10 60",
    "sg:postcode":"59800",
    "sg:province":"Nord Pas-de-Calais",
    "wof:name":"Archimed S.a.",
    "wof:placetype":"venue"
},
  "geometry": {"coordinates":[3.061702,50.641994],"type":"Point"}
}