{
  "type": "Feature",
  "properties": {
    "iso:country":"FR",
    "sg:address":"Rte de Bagnols - ZI",
    "sg:city":"Pont Saint Esprit",
    "sg:orig_category":"Unclassifiable Establishments",
    "sg:phone":"+33 4 66 39 08 88",
    "sg:postcode":"30130",
    "sg:province":"Languedoc-Roussillon",
    "wof:name":"Chambouleyron S.a.",
    "wof:placetype":"venue"
},
  "geometry": {"coordinates":[4.6225,44.22781],"type":"Point"}
}