{
  "type": "Feature",
  "properties": {
    "addr:full":"2, Rue du Mar\u00e9chal Joffre, 68510 Sierentz Sierentz Alsace 68510",
    "addr:housenumber":"2",
    "addr:postcode":"68510;68510",
    "addr:street":"Rue Du Mare\u0301Chal Joffre",
    "iso:country":"FR",
    "sg:address":"2, Rue du Mar\u00e9chal Joffre, 68510 Sierentz",
    "sg:city":"Sierentz",
    "sg:orig_category":"Unclassifiable Establishments",
    "sg:phone":"+33 3 89 83 91 61",
    "sg:postcode":"68510",
    "sg:province":"Alsace",
    "wof:name":"Mobil Elasto France S.a.r.l.",
    "wof:placetype":"venue"
},
  "geometry": {"coordinates":[7.457786,47.654411],"type":"Point"}
}