{
  "type": "Feature",
  "properties": {
    "addr:full":"3 Rue Paul Mazy 94200 Ivry Sur Seine Ile de France 94200",
    "addr:housenumber":"3",
    "addr:postcode":"94200;94200",
    "addr:street":"Rue Paul Mazy;France",
    "iso:country":"FR",
    "sg:address":"3 Rue Paul Mazy 94200 Ivry Sur Seine",
    "sg:classifiers":[
        {
            "category":"Shopping",
            "subcategory":"Computers & Home Electronics",
            "type":"Retail Goods"
        }
    ],
    "sg:phone":"+33 1 46 72 29 93",
    "sg:postcode":"94200",
    "sg:province":"Ile de France",
    "sg:tags":[
        "equipment",
        "household",
        "electrical",
        "appliance",
        "electronic"
    ],
    "wof:name":"Distribution Ile De France Sa",
    "wof:placetype":"venue"
},
  "geometry": {"coordinates":[2.384761,48.817932],"type":"Point"}
}