{
  "type": "Feature",
  "properties": {
    "addr:full":"10, Rue Pierre Salmon, 51430 Bezannes Champagne",
    "addr:housenumber":"10",
    "addr:postcode":"51430",
    "addr:street":"Rue Pierre Salmon",
    "iso:country":"FR",
    "sg:address":"10, Rue Pierre Salmon, 51430 Bezannes",
    "sg:orig_category":"Unclassifiable Establishments",
    "sg:phone":"+33 3 26 36 40 40",
    "sg:province":"Champagne",
    "wof:name":"Oxalis Champagne S.a.",
    "wof:placetype":"venue"
},
  "geometry": {"coordinates":[3.990152,49.218266],"type":"Point"}
}