{
  "type": "Feature",
  "properties": {
    "addr:full":"Place Ch\u00e2teaubriand Saint Malo Bretagne 35400",
    "addr:postcode":"35400",
    "addr:street":"Place Cha\u0302Teaubriand Saint Malo Bretagne",
    "iso:country":"FR",
    "sg:address":"Place Ch\u00e2teaubriand",
    "sg:city":"Saint Malo",
    "sg:orig_category":"Unclassifiable Establishments",
    "sg:phone":"+33 2 99 56 66 52",
    "sg:postcode":"35400",
    "sg:province":"Bretagne",
    "wof:name":"H\u00f4tel France Et Ch\u00e2teaubriand",
    "wof:placetype":"venue"
},
  "geometry": {"coordinates":[-2.023634,48.650902],"type":"Point"}
}