{
  "type": "Feature",
  "properties": {
    "iso:country":"FR",
    "sg:address":"Parc d'activit\u00e9 Orl\u00e9ans Sologne 45075 ORLEANS",
    "sg:classifiers":[
        {
            "category":"Autos & Motor Vehicles",
            "subcategory":"Motorcycle Sales",
            "type":"Retail Goods"
        }
    ],
    "sg:phone":"+33 2 38 69 29 01",
    "sg:province":"Centre",
    "sg:tags":[
        "polypropylene",
        "pp",
        "bag"
    ],
    "wof:name":"Valembal Sa",
    "wof:placetype":"venue"
},
  "geometry": {"coordinates":[1.912453,47.871941],"type":"Point"}
}