{
  "type": "Feature",
  "properties": {
    "iso:country":"FR",
    "sg:address":"1000, Rue du Mar\u00e9chal Juin - ZI, 77000 Vaux le P\u00e9nil",
    "sg:orig_category":"Non-Classified Establishments",
    "sg:phone":"+33 1 64 10 23 43",
    "sg:province":"Ile de France",
    "wof:name":"S.e.r.e.c. S.a. - Soci\u00e9t\u00e9 D'etudes Et R\u00e9alisation D'etiquettes En Continu",
    "wof:placetype":"venue"
},
  "geometry": {"coordinates":[2.664085,48.539577],"type":"Point"}
}