{
  "type": "Feature",
  "properties": {
    "iso:country":"FR",
    "sg:address":"Rue Saint Joseph; Lesneven",
    "sg:classifiers":[
        {
            "category":"Banks & Credit Unions",
            "subcategory":"Bank",
            "type":"Services"
        }
    ],
    "sg:phone":"+33 3398832922",
    "sg:province":"Picardie",
    "wof:name":"Cr\u00e9dit Mutuel De Bretagne",
    "wof:placetype":"venue"
},
  "geometry": {"coordinates":[-4.321516,48.571541],"type":"Point"}
}