{
  "type": "Feature",
  "properties": {
    "addr:full":"154, Rue Guynemer, 34130 Mauguio Languedoc-Roussillon",
    "addr:housenumber":"154",
    "addr:postcode":"34130",
    "addr:street":"Rue Guynemer",
    "iso:country":"FR",
    "sg:address":"154, Rue Guynemer, 34130 Mauguio",
    "sg:orig_category":"Non-Classified Establishments",
    "sg:phone":"+33 4 67 20 45 00",
    "sg:province":"Languedoc-Roussillon",
    "wof:name":"Marketing Distribution S.a.",
    "wof:placetype":"venue"
},
  "geometry": {"coordinates":[3.939015,43.584595],"type":"Point"}
}