{
  "type": "Feature",
  "properties": {
    "addr:full":"50, Av. Jean Baptiste le Bas, 59100 Roubaix Nord Pas-de-Calais",
    "addr:postcode":"59100",
    "addr:street":"50 Av. Jean Baptiste Le Bas",
    "iso:country":"FR",
    "sg:address":"50, Av. Jean Baptiste le Bas, 59100 Roubaix",
    "sg:orig_category":"Unclassifiable Establishments",
    "sg:phone":"+33 3 20 69 19 00",
    "sg:province":"Nord Pas-de-Calais",
    "wof:name":"Adistar S.n.c.",
    "wof:placetype":"venue"
},
  "geometry": {"coordinates":[3.170656,50.692795],"type":"Point"}
}