{
  "type": "Feature",
  "properties": {
    "iso:country":"FR",
    "sg:address":"B.P. 15, 12170 Saint Jean Delnous C\u00e9dex^^Av d'Albi, 12170 Saint Jean Delnous",
    "sg:orig_category":"Non-Classified Establishments",
    "sg:phone":"+33 5 65 74 02 16",
    "sg:postcode":"12170",
    "sg:province":"Midi Pyr\u00e9n\u00e9es",
    "wof:name":"E.a.r. S.a.",
    "wof:placetype":"venue"
},
  "geometry": {"coordinates":[2.520637,44.037281],"type":"Point"}
}