{
  "type": "Feature",
  "properties": {
    "iso:country":"FR",
    "sg:address":"73 Rue R\u00e9aumur 75002 Paris",
    "sg:classifiers":[
        {
            "category":"Shopping",
            "subcategory":"Clothing, Apparel, & Fashions",
            "type":"Retail Goods"
        }
    ],
    "sg:phone":"+33 1 45 08 48 12",
    "sg:postcode":"75002",
    "sg:province":"Ile de France",
    "sg:tags":[
        "textile",
        "clothing",
        "clothes"
    ],
    "wof:name":"Segeco Sa",
    "wof:placetype":"venue"
},
  "geometry": {"coordinates":[2.349569,48.866608],"type":"Point"}
}