{
  "type": "Feature",
  "properties": {
    "addr:full":"35, Av. du chalet, 93360 Neuilly Plaisance Ile de France",
    "addr:postcode":"93360",
    "addr:street":"35 Av. Du Chalet;Ile De France",
    "iso:country":"FR",
    "sg:address":"35, Av. du chalet, 93360 Neuilly Plaisance",
    "sg:orig_category":"Unclassifiable Establishments",
    "sg:phone":"+33 1 43 00 98 98",
    "sg:province":"Ile de France",
    "wof:name":"Aspasia Bui Kim Khue S.a.r.l.",
    "wof:placetype":"venue"
},
  "geometry": {"coordinates":[2.501405,48.85976],"type":"Point"}
}