{
  "type": "Feature",
  "properties": {
    "addr:full":"100, Rue de Courcelles, 75017 Paris Ile de France",
    "addr:housenumber":"100",
    "addr:postcode":"75017",
    "addr:street":"Rue De Courcelles",
    "iso:country":"FR",
    "sg:address":"100, Rue de Courcelles, 75017 Paris",
    "sg:orig_category":"Unclassifiable Establishments",
    "sg:phone":"+33 1 44 01 90 00",
    "sg:province":"Ile de France",
    "wof:name":"Cgu Courtage S.a.",
    "wof:placetype":"venue"
},
  "geometry": {"coordinates":[2.302927,48.879555],"type":"Point"}
}