{
  "type": "Feature",
  "properties": {
    "iso:country":"FR",
    "sg:address":"B.P. 804, 53008 Laval C\u00e9dex^^2 bis, Rue Ambroise Par\u00e9, 53000 Laval",
    "sg:orig_category":"Non-Classified Establishments",
    "sg:phone":"+33 2 43 59 73 30",
    "sg:province":"Pays de Loire",
    "wof:name":"Techn\u00e9 Conseil S.a.r.l.",
    "wof:placetype":"venue"
},
  "geometry": {"coordinates":[-0.756451,48.036293],"type":"Point"}
}