{
  "type": "Feature",
  "properties": {
    "addr:full":"Rue de la Vall\u00e9e d'Ossau - Z.I. Serres Castet Aquitaine 64121",
    "addr:postcode":"64121",
    "addr:street":"Rue De La Valle\u0301E;Z.I.",
    "iso:country":"FR",
    "sg:address":"Rue de la Vall\u00e9e d'Ossau - Z.I.",
    "sg:city":"Serres Castet",
    "sg:orig_category":"Non-Classified Establishments",
    "sg:phone":"+33 5 59 33 16 06",
    "sg:postcode":"64121",
    "sg:province":"Aquitaine",
    "wof:name":"Screg Sud Ouest",
    "wof:placetype":"venue"
},
  "geometry": {"coordinates":[-0.3603,43.37347],"type":"Point"}
}