{
  "type": "Feature",
  "properties": {
    "iso:country":"FR",
    "sg:address":"14, Rue de L\u00fcbeck, 75116 Paris",
    "sg:orig_category":"Non-Classified Establishments",
    "sg:phone":"+33 1 56 26 59 60",
    "sg:province":"Ile de France",
    "wof:name":"Batenborch International S.a.",
    "wof:placetype":"venue"
},
  "geometry": {"coordinates":[2.292847,48.865967],"type":"Point"}
}