{
  "type": "Feature",
  "properties": {
    "addr:full":"avenue Barberin Laurade 13103 ST ETIENNE DU GRES Midi Pyr\u00e9n\u00e9es",
    "addr:postcode":"13103",
    "addr:street":"Avenue Barberin Laurade",
    "iso:country":"FR",
    "sg:address":"avenue Barberin Laurade 13103 ST ETIENNE DU GRES",
    "sg:classifiers":[
        {
            "category":"Manufacturing",
            "subcategory":"Printing",
            "type":"Manufacturing & Wholesale Goods"
        }
    ],
    "sg:phone":"+33 4 90 49 19 19",
    "sg:province":"Midi Pyr\u00e9n\u00e9es",
    "sg:tags":[
        "machine",
        "transfer",
        "fabric"
    ],
    "wof:name":"S.a.i.t. Les Olivades S.a.",
    "wof:placetype":"venue"
},
  "geometry": {"coordinates":[4.718431,43.785587],"type":"Point"}
}