{
  "type": "Feature",
  "properties": {
    "addr:full":"17770 Saint C\u00e9saire Poitou-Charentes 17770",
    "addr:housenumber":"17770",
    "addr:postcode":"17770",
    "addr:street":"Saint Ce\u0301Saire",
    "iso:country":"FR",
    "sg:address":"17770 Saint C\u00e9saire",
    "sg:orig_category":"Unclassifiable Establishments",
    "sg:phone":"+33 5 46 91 56 00",
    "sg:postcode":"17770",
    "sg:province":"Poitou-Charentes",
    "wof:name":"Sifraco Sa",
    "wof:placetype":"venue"
},
  "geometry": {"coordinates":[-0.506504,45.753639],"type":"Point"}
}