{
  "type": "Feature",
  "properties": {
    "addr:full":"82, Av Boufflers, 59130 Lambersart Nord Pas-de-Calais",
    "addr:postcode":"59130",
    "addr:street":"82 Av Boufflers",
    "iso:country":"FR",
    "sg:address":"82, Av Boufflers, 59130 Lambersart",
    "sg:orig_category":"Unclassifiable Establishments",
    "sg:phone":"+33 3 20 09 23 23",
    "sg:province":"Nord Pas-de-Calais",
    "wof:name":"M.e.p.s. - Maintenance Entretien Prestations De Services S.a.",
    "wof:placetype":"venue"
},
  "geometry": {"coordinates":[3.01881,50.643044],"type":"Point"}
}