{
  "type": "Feature",
  "properties": {
    "addr:full":"80, Rue Nationale, 56300 Pontivy Pontivy Bretagne 56300",
    "addr:housenumber":"80",
    "addr:postcode":"56300;56300",
    "addr:street":"Rue Nationale;Pontivy",
    "iso:country":"FR",
    "sg:address":"80, Rue Nationale, 56300 Pontivy",
    "sg:city":"Pontivy",
    "sg:orig_category":"Non-Classified Establishments",
    "sg:phone":"+33 2 97 25 94 94",
    "sg:postcode":"56300",
    "sg:province":"Bretagne",
    "wof:name":"C.c.i. Du Morbihan",
    "wof:placetype":"venue"
},
  "geometry": {"coordinates":[-2.966553,48.064213],"type":"Point"}
}