{
  "type": "Feature",
  "properties": {
    "addr:full":"Av. d'Ordiget - ZI Villefranche de Rouergue Midi Pyr\u00e9n\u00e9es 12200",
    "addr:postcode":"12200",
    "addr:street":"Av. D'Ordiget Zi",
    "iso:country":"FR",
    "sg:address":"Av. d'Ordiget - ZI",
    "sg:city":"Villefranche de Rouergue",
    "sg:orig_category":"Unclassifiable Establishments",
    "sg:phone":"+33 5 65 65 13 70",
    "sg:postcode":"12200",
    "sg:province":"Midi Pyr\u00e9n\u00e9es",
    "wof:name":"La Compagnie Des Fromages S.a.s.",
    "wof:placetype":"venue"
},
  "geometry": {"coordinates":[2.032,44.332211],"type":"Point"}
}