{
  "type": "Feature",
  "properties": {
    "addr:full":"99, Rue Pierre Benoit, 40000 Mont de Marsan Mont-de-Marsan Aquitaine 40000",
    "addr:housenumber":"99",
    "addr:postcode":"40000;40000",
    "addr:street":"Rue Pierre Benoit",
    "iso:country":"FR",
    "sg:address":"99, Rue Pierre Benoit, 40000 Mont de Marsan",
    "sg:city":"Mont-de-Marsan",
    "sg:orig_category":"Unclassifiable Establishments",
    "sg:phone":"+33 5 58 05 66 06",
    "sg:postcode":"40000",
    "sg:province":"Aquitaine",
    "wof:name":"R.d.t.l. - R\u00e9gie D\u00e9partementale De Transports Des Landes",
    "wof:placetype":"venue"
},
  "geometry": {"coordinates":[-0.511887,43.897961],"type":"Point"}
}