{
  "type": "Feature",
  "properties": {
    "addr:full":"2, Rue de la Halte, 45770 Saran Saran Centre 45770",
    "addr:housenumber":"2",
    "addr:postcode":"45770;45770",
    "addr:street":"Rue De La Halte",
    "iso:country":"FR",
    "sg:address":"2, Rue de la Halte, 45770 Saran",
    "sg:city":"Saran",
    "sg:orig_category":"Unclassifiable Establishments",
    "sg:phone":"+33 2 38 79 44 02",
    "sg:postcode":"45770",
    "sg:province":"Centre",
    "wof:name":"Alliance M\u00e9dia S.a.",
    "wof:placetype":"venue"
},
  "geometry": {"coordinates":[1.912057,47.952244],"type":"Point"}
}