{
  "type": "Feature",
  "properties": {
    "iso:country":"FR",
    "sg:address":"26 Avenue De Thi\u00e8s",
    "sg:city":"Caen",
    "sg:classifiers":[
        {
            "category":"Banks & Credit Unions",
            "subcategory":"Financial Services",
            "type":"Services"
        }
    ],
    "sg:phone":"+33 2 31 46 72 72",
    "sg:postcode":"14000",
    "sg:province":"Basse Normandie",
    "sg:tags":[
        "banking",
        "finance",
        "insurance"
    ],
    "wof:name":"So Fi Com Ste Fiduciaire Comptable Sa",
    "wof:placetype":"venue"
},
  "geometry": {"coordinates":[-0.361595,49.198658],"type":"Point"}
}