{
  "type": "Feature",
  "properties": {
    "iso:country":"FR",
    "sg:address":"46 Rue Des Colibris 40100 Dax",
    "sg:city":"Dax",
    "sg:classifiers":[
        {
            "category":"Wholesale",
            "subcategory":"Medical Equipment & Supplies",
            "type":"Manufacturing & Wholesale Goods"
        }
    ],
    "sg:phone":"+33 5 58 74 43 80",
    "sg:postcode":"40100",
    "sg:province":"Aquitaine",
    "sg:tags":[
        "instrument",
        "health",
        "-",
        "precision"
    ],
    "wof:name":"Sarl Lafargue Jean Louis",
    "wof:placetype":"venue"
},
  "geometry": {"coordinates":[-1.04134,43.705162],"type":"Point"}
}