{
  "type": "Feature",
  "properties": {
    "addr:full":"67 Bis Av Gambetta 94700 Maisons Alfort Ile de France",
    "addr:housenumber":"67 bis",
    "addr:postcode":"94700",
    "addr:street":"Av Gambetta",
    "iso:country":"FR",
    "sg:address":"67 Bis Av Gambetta 94700 Maisons Alfort",
    "sg:classifiers":[
        {
            "category":"Manufacturing",
            "subcategory":"Printing",
            "type":"Manufacturing & Wholesale Goods"
        }
    ],
    "sg:phone":"+33 1 43 76 61 21",
    "sg:province":"Ile de France",
    "sg:tags":[
        "publishing"
    ],
    "wof:name":"Societe Nouvelle H.b. Graphic",
    "wof:placetype":"venue"
},
  "geometry": {"coordinates":[2.442126,48.810104],"type":"Point"}
}