{
  "type": "Feature",
  "properties": {
    "addr:full":"Rte Nationale 152 - ZI de Tavers Tavers Centre 45190",
    "addr:postcode":"152;45190",
    "addr:street":"Rte Nationale;Zi De Tavers Tavers",
    "iso:country":"FR",
    "sg:address":"Rte Nationale 152 - ZI de Tavers",
    "sg:city":"Tavers",
    "sg:orig_category":"Non-Classified Establishments",
    "sg:phone":"+33 2 38 44 01 08",
    "sg:postcode":"45190",
    "sg:province":"Centre",
    "wof:name":"T.u.p. S.a. - Tavers Usinage De Pr\u00e9cision",
    "wof:placetype":"venue"
},
  "geometry": {"coordinates":[1.630985,47.779282],"type":"Point"}
}