{
  "type": "Feature",
  "properties": {
    "addr:full":"112, Rue de la Croix Nivert, 75015 Paris Ile de France",
    "addr:housenumber":"112",
    "addr:postcode":"75015",
    "addr:street":"Rue De La Croix Nivert",
    "iso:country":"FR",
    "sg:address":"112, Rue de la Croix Nivert, 75015 Paris",
    "sg:orig_category":"Non-Classified Establishments",
    "sg:phone":"+33 1 48 28 49 29",
    "sg:province":"Ile de France",
    "wof:name":"Sidec S.a.r.l.",
    "wof:placetype":"venue"
},
  "geometry": {"coordinates":[2.294425,48.842644],"type":"Point"}
}