{
  "type": "Feature",
  "properties": {
    "iso:country":"FR",
    "sg:address":"Z.A. des Pr\u00e9s Mouchets",
    "sg:city":"Les Fins",
    "sg:orig_category":"Outillages pour bijoutiers Outillages pour horlogers",
    "sg:phone":"+33 3 81 67 18 28",
    "sg:postcode":"25500",
    "sg:province":"Franche Comt\u00e9",
    "wof:name":"Lerrac Outillage S.a.r.l.",
    "wof:placetype":"venue"
},
  "geometry": {"coordinates":[6.636594,47.085358],"type":"Point"}
}