{
  "type": "Feature",
  "properties": {
    "iso:country":"FR",
    "sg:address":"33, Place Saint Louis, 57000 Metz",
    "sg:orig_category":"Non-Classified Establishments",
    "sg:phone":"+33 3 87 36 64 81",
    "sg:postcode":"57000",
    "sg:province":"Lorraine",
    "wof:name":"Daytona S.a.s.",
    "wof:placetype":"venue"
},
  "geometry": {"coordinates":[6.178612,49.116432],"type":"Point"}
}