{
  "type": "Feature",
  "properties": {
    "addr:full":"B.P. 7, 33560 Carbon Blanc C\u00e9dex^^ZI de la Moulure, 33560 Carbon Blanc Carbon-Blanc Aquitaine 33560",
    "addr:housenumber":"7",
    "addr:postcode":"33560;33560;33560",
    "addr:street":"B.P.;Blanc;Blanc",
    "iso:country":"FR",
    "sg:address":"B.P. 7, 33560 Carbon Blanc C\u00e9dex^^ZI de la Moulure, 33560 Carbon Blanc",
    "sg:city":"Carbon-Blanc",
    "sg:orig_category":"Non-Classified Establishments",
    "sg:phone":"+33 5 57 80 83 33",
    "sg:postcode":"33560",
    "sg:province":"Aquitaine",
    "wof:name":"Danel S.a.",
    "wof:placetype":"venue"
},
  "geometry": {"coordinates":[-0.473724,44.908085],"type":"Point"}
}