{
  "type": "Feature",
  "properties": {
    "iso:country":"FR",
    "sg:address":"2, Rue Choiseul, 75002 Paris",
    "sg:orig_category":"Unclassifiable Establishments",
    "sg:phone":"+33 1 42 86 18 18",
    "sg:province":"Ile de France",
    "wof:name":"Cr\u00e9dit Agricole Indosuez Cheuvreux Gestion Sa",
    "wof:placetype":"venue"
},
  "geometry": {"coordinates":[2.336095,48.868996],"type":"Point"}
}