{
  "type": "Feature",
  "properties": {
    "addr:full":"ZI de la Charmotte Anjoutey Franche Comt\u00e9 90170",
    "addr:postcode":"90170",
    "addr:street":"Zi De La Charmotte;Franche Comte\u0301",
    "iso:country":"FR",
    "sg:address":"ZI de la Charmotte",
    "sg:city":"Anjoutey",
    "sg:orig_category":"Unclassifiable Establishments",
    "sg:phone":"+33 3 84 54 68 24",
    "sg:postcode":"90170",
    "sg:province":"Franche Comt\u00e9",
    "wof:name":"Hydro G\u00e9otechnique Est S.a.r.l.",
    "wof:placetype":"venue"
},
  "geometry": {"coordinates":[6.93056,47.702919],"type":"Point"}
}