{
  "type": "Feature",
  "properties": {
    "iso:country":"FR",
    "sg:address":"B.P. 69, 69567 Saint Genis Laval C\u00e9dex^^9, RueJules Guesdes, 69230 Saint Genis Laval",
    "sg:orig_category":"Non-Classified Establishments",
    "sg:phone":"+33 4 78 51 57 41",
    "sg:postcode":"69230",
    "sg:province":"Rhone-Alpes",
    "wof:name":"Ter Beke France S.a.",
    "wof:placetype":"venue"
},
  "geometry": {"coordinates":[4.79287,45.692242],"type":"Point"}
}