{
  "type": "Feature",
  "properties": {
    "addr:full":"Chemin de Lirac Roquemaure Languedoc-Roussillon 30150",
    "addr:postcode":"30150",
    "addr:street":"Chemin De Lirac Roquemaure",
    "iso:country":"FR",
    "sg:address":"Chemin de Lirac",
    "sg:city":"Roquemaure",
    "sg:orig_category":"Non-Classified Establishments",
    "sg:phone":"+33 4 66 82 82 59",
    "sg:postcode":"30150",
    "sg:province":"Languedoc-Roussillon",
    "wof:name":"Brunel Fr\u00e8res S.a.r.l. - Ch\u00e2teau Saint Roch",
    "wof:placetype":"venue"
},
  "geometry": {"coordinates":[4.756821,44.051453],"type":"Point"}
}