{
  "type": "Feature",
  "properties": {
    "addr:full":"30, Rue de l'Ail, 67000 Strasbourg Strasbourg Alsace 67000",
    "addr:housenumber":"30",
    "addr:postcode":"67000;67000",
    "addr:street":"Rue De L'Ail",
    "iso:country":"FR",
    "sg:address":"30, Rue de l'Ail, 67000 Strasbourg",
    "sg:city":"Strasbourg",
    "sg:orig_category":"Non-Classified Establishments",
    "sg:phone":"+33 3 88 32 63 46",
    "sg:postcode":"67000",
    "sg:province":"Alsace",
    "wof:name":"Galerie K S.a.",
    "wof:placetype":"venue"
},
  "geometry": {"coordinates":[7.749171,48.580048],"type":"Point"}
}