{
  "type": "Feature",
  "properties": {
    "addr:full":"137 Av De Conthe 15000 Aurillac Aurillac Auvergne 15000",
    "addr:postcode":"15000;15000",
    "addr:street":"137 Av De Conthe",
    "iso:country":"FR",
    "sg:address":"137 Av De Conthe 15000 Aurillac",
    "sg:city":"Aurillac",
    "sg:classifiers":[
        {
            "category":"Manufacturing",
            "subcategory":"Printing",
            "type":"Manufacturing & Wholesale Goods"
        }
    ],
    "sg:phone":"+33 4 71 63 44 60",
    "sg:postcode":"15000",
    "sg:province":"Auvergne",
    "sg:tags":[
        "publishing"
    ],
    "wof:name":"Union Sociale De La Haute Auvergne Imprimerie Moderne Usha Imprimerie Moderne",
    "wof:placetype":"venue"
},
  "geometry": {"coordinates":[2.421576,44.910702],"type":"Point"}
}