{
  "type": "Feature",
  "properties": {
    "iso:country":"FR",
    "sg:address":"B.P. 4, 01960 P\u00e9ronnas C\u00e9dex^^All\u00e9e du Thioudet - Espace Pro Monternoz, 01960 P\u00e9ronnas",
    "sg:orig_category":"Non-Classified Establishments",
    "sg:phone":"+33 4 74 32 14 60",
    "sg:postcode":"01960",
    "sg:province":"Rhone-Alpes",
    "wof:name":"C\u00e9g\u00e9lec Sa",
    "wof:placetype":"venue"
},
  "geometry": {"coordinates":[5.1892,46.161331],"type":"Point"}
}