{
  "type": "Feature",
  "properties": {
    "iso:country":"FR",
    "sg:address":"10, Rue de la Gare, 38600 Fontaine",
    "sg:orig_category":"Unclassifiable Establishments",
    "sg:phone":"+33 4 76 26 48 83",
    "sg:province":"Rhone-Alpes",
    "wof:name":"Le Lane Xang S.a.r.l.",
    "wof:placetype":"venue"
},
  "geometry": {"coordinates":[5.687735,45.191673],"type":"Point"}
}