{
  "type": "Feature",
  "properties": {
    "addr:full":"22 Rue De L Arc De Triomphe 75017 Paris Ile de France 75017",
    "addr:housenumber":"22",
    "addr:postcode":"75017;75017",
    "addr:street":"Rue De L Arc De Triomphe",
    "iso:country":"FR",
    "sg:address":"22 Rue De L Arc De Triomphe 75017 Paris",
    "sg:classifiers":[
        {
            "category":"Food & Beverages",
            "subcategory":"Groceries & Convenience Stores",
            "type":"Retail Goods"
        }
    ],
    "sg:phone":"+33 1 43 22 88 28",
    "sg:postcode":"75017",
    "sg:province":"Ile de France",
    "sg:tags":[
        "product",
        "related"
    ],
    "wof:name":"Sole Mio",
    "wof:placetype":"venue"
},
  "geometry": {"coordinates":[2.293698,48.877228],"type":"Point"}
}