{
  "type": "Feature",
  "properties": {
    "iso:country":"FR",
    "sg:address":"Trianon 41270 Drou\u00e9",
    "sg:city":"Drou\u00e9",
    "sg:orig_category":"Non-Classified Establishments",
    "sg:phone":"+33 2 54 89 40 40",
    "sg:postcode":"41270",
    "sg:province":"Centre",
    "wof:name":"Etablissements Servais S.a.",
    "wof:placetype":"venue"
},
  "geometry": {"coordinates":[1.071641,48.043743],"type":"Point"}
}