{
  "type": "Feature",
  "properties": {
    "iso:country":"FR",
    "sg:address":"Rue E. Vitriat - ZI la Palun",
    "sg:city":"Gardanne",
    "sg:orig_category":"Non-Classified Establishments",
    "sg:phone":"+33 4 42 58 02 20",
    "sg:postcode":"13120",
    "sg:province":"Basse Normandie",
    "wof:name":"Knauf Technique B\u00e9ton",
    "wof:placetype":"venue"
},
  "geometry": {"coordinates":[5.47062,43.454971],"type":"Point"}
}