{
  "type": "Feature",
  "properties": {
    "iso:country":"FR",
    "sg:address":"34 Ter boulevard Ornano 93200 St Denis",
    "sg:classifiers":[
        {
            "category":"Building & Trades",
            "subcategory":"Locksmith",
            "type":"Services"
        }
    ],
    "sg:phone":"+33 1 48 20 20 00",
    "sg:province":"Ile de France",
    "sg:tags":[
        "software"
    ],
    "wof:name":"Gercop Sa",
    "wof:placetype":"venue"
},
  "geometry": {"coordinates":[2.344,48.915447],"type":"Point"}
}