{
  "type": "Feature",
  "properties": {
    "iso:country":"FR",
    "sg:address":"188, Rue Pierre Joigneaux, 92250 La Garenne Colombes",
    "sg:orig_category":"Non-Classified Establishments",
    "sg:phone":"+33 1 47 60 86 92",
    "sg:province":"Ile de France",
    "wof:name":"Girardin Packaging S.a.r.l.",
    "wof:placetype":"venue"
},
  "geometry": {"coordinates":[2.255009,48.911293],"type":"Point"}
}