{
  "type": "Feature",
  "properties": {
    "addr:full":"7 all\u00e9e de La Fontaine 93340 Le Raincy Ile de France",
    "addr:housenumber":"7",
    "addr:postcode":"93340",
    "addr:street":"Alle\u0301E De La Fontaine",
    "iso:country":"FR",
    "sg:address":"7 all\u00e9e de La Fontaine 93340 Le Raincy",
    "sg:classifiers":[
        {
            "category":"Professional",
            "subcategory":"Accounting & Tax Preparation",
            "type":"Services"
        }
    ],
    "sg:phone":"+33 1 43 02 22 55",
    "sg:province":"Ile de France",
    "sg:tags":[
        "agency",
        "purchasing",
        "enterprise"
    ],
    "wof:name":"Id Lease Sa",
    "wof:placetype":"venue"
},
  "geometry": {"coordinates":[2.513822,48.892895],"type":"Point"}
}