{
  "type": "Feature",
  "properties": {
    "addr:full":"B.P. 20725, 60207 Compi\u00e8gne C\u00e9dex 2^^1, Rue Jeanne d'Arc, 60200 Compi\u00e8gne Picardie",
    "addr:housenumber":"2;^ 1",
    "addr:postcode":"60207;60200",
    "addr:street":"^;Rue Jeanne D'Arc",
    "iso:country":"FR",
    "sg:address":"B.P. 20725, 60207 Compi\u00e8gne C\u00e9dex 2^^1, Rue Jeanne d'Arc, 60200 Compi\u00e8gne",
    "sg:orig_category":"Non-Classified Establishments",
    "sg:phone":"+33 3 44 86 26 26",
    "sg:province":"Picardie",
    "wof:name":"U.f.b. Locabail",
    "wof:placetype":"venue"
},
  "geometry": {"coordinates":[2.822872,49.417477],"type":"Point"}
}