{
  "type": "Feature",
  "properties": {
    "iso:country":"FR",
    "sg:address":"75710 Paris C\u00e9dex 15^^91, Bd Pasteur, 75015 Paris",
    "sg:orig_category":"Non-Classified Establishments",
    "sg:phone":"+33 1 43 23 52 02",
    "sg:postcode":"75015",
    "sg:province":"Ile de France",
    "wof:name":"C.n.c.a. S.a.- Caisse Nationale De Cr\u00e9dit Agricole",
    "wof:placetype":"venue"
},
  "geometry": {"coordinates":[2.299265,48.841057],"type":"Point"}
}