{
  "type": "Feature",
  "properties": {
    "iso:country":"FR",
    "sg:address":"5, Rue Valmy, 51100 Reims",
    "sg:orig_category":"Unclassifiable Establishments",
    "sg:phone":"+33 3 26 40 66 41",
    "sg:province":"Champagne",
    "wof:name":"T.v.m. Productions Alimentaires S.a.",
    "wof:placetype":"venue"
},
  "geometry": {"coordinates":[4.034007,49.266174],"type":"Point"}
}