{
  "type": "Feature",
  "properties": {
    "addr:full":"52 R L\u00e9onard Samie 87000 Limoges Limousin 87000",
    "addr:housenumber":"52",
    "addr:postcode":"87000;87000",
    "addr:street":"R Le\u0301Onard Samie",
    "iso:country":"FR",
    "sg:address":"52 R L\u00e9onard Samie 87000 Limoges",
    "sg:classifiers":[
        {
            "category":"Manufacturing",
            "subcategory":"Metals",
            "type":"Manufacturing & Wholesale Goods"
        }
    ],
    "sg:phone":"+33 5 55 30 69 34",
    "sg:postcode":"87000",
    "sg:province":"Limousin",
    "sg:tags":[
        "metallurgy",
        "metalworking",
        "processing"
    ],
    "wof:name":"Ets Leonard Sarl",
    "wof:placetype":"venue"
},
  "geometry": {"coordinates":[1.273992,45.802906],"type":"Point"}
}