{
  "type": "Feature",
  "properties": {
    "addr:full":"B.P. 9 Le Cateau Cambr\u00e9sis Nord Pas-de-Calais 59360",
    "addr:postcode":"59360",
    "addr:street":"B.P. 9 Le Cateau Cambre\u0301Sis Nord",
    "iso:country":"FR",
    "sg:address":"B.P. 9",
    "sg:city":"Le Cateau Cambr\u00e9sis",
    "sg:orig_category":"Non-Classified Establishments",
    "sg:phone":"+33 3 27 77 52 00",
    "sg:postcode":"59360",
    "sg:province":"Nord Pas-de-Calais",
    "wof:name":"G\u00e9n\u00e9ral Coating - D\u00e9partement Tr\u00e9fil'alu S.a.",
    "wof:placetype":"venue"
},
  "geometry": {"coordinates":[3.543052,50.105213],"type":"Point"}
}