{
  "type": "Feature",
  "properties": {
    "addr:full":"B.P. 442, 59814 Lesquin C\u00e9dex^^Centre Routier Transports, 59810 Lesquin Nord Pas-de-Calais",
    "addr:housenumber":"b.p. 442",
    "addr:postcode":"59814;transports 59810",
    "iso:country":"FR",
    "sg:address":"B.P. 442, 59814 Lesquin C\u00e9dex^^Centre Routier Transports, 59810 Lesquin",
    "sg:orig_category":"Non-Classified Establishments",
    "sg:phone":"+33 3 20 87 94 40",
    "sg:province":"Nord Pas-de-Calais",
    "wof:name":"Sapanord Les Professionnels Automobiles Du Nord De La France S.a.",
    "wof:placetype":"venue"
},
  "geometry": {"coordinates":[3.11003,50.588009],"type":"Point"}
}