{
  "type": "Feature",
  "properties": {
    "addr:full":"1, Rue Thomas Edison, 91090 Lisses Ile de France",
    "addr:housenumber":"1",
    "addr:postcode":"91090;ile",
    "addr:street":"Rue Thomas Edison",
    "iso:country":"FR",
    "sg:address":"1, Rue Thomas Edison, 91090 Lisses",
    "sg:orig_category":"Unclassifiable Establishments",
    "sg:phone":"+33 1 69 11 33 33",
    "sg:province":"Ile de France",
    "wof:name":"Exel Logistics Textiles S.a.",
    "wof:placetype":"venue"
},
  "geometry": {"coordinates":[2.446355,48.607021],"type":"Point"}
}