{
  "type": "Feature",
  "properties": {
    "iso:country":"FR",
    "sg:address":"Rte d'Anduze",
    "sg:city":"L\u00e9dignan",
    "sg:orig_category":"Unclassifiable Establishments",
    "sg:phone":"+33 4 66 83 40 91",
    "sg:postcode":"30350",
    "sg:province":"Languedoc-Roussillon",
    "wof:name":"Agence Rocani\u00e8re S.a.r.l.",
    "wof:placetype":"venue"
},
  "geometry": {"coordinates":[4.049153,44.013023],"type":"Point"}
}