{
  "type": "Feature",
  "properties": {
    "addr:full":"72 Rue Caroline Follet 80160 Conty Picardie 80160",
    "addr:housenumber":"72",
    "addr:postcode":"80160;80160",
    "addr:street":"Rue Caroline Follet",
    "iso:country":"FR",
    "sg:address":"72 Rue Caroline Follet 80160 Conty",
    "sg:classifiers":[
        {
            "category":"Professional",
            "subcategory":"Engineering",
            "type":"Services"
        }
    ],
    "sg:phone":"+33 3 22 41 30 89",
    "sg:postcode":"80160",
    "sg:province":"Picardie",
    "sg:tags":[
        "machine",
        "-",
        "environment",
        "equipment",
        "machinery",
        "mechanical"
    ],
    "wof:name":"Orchidee Sas",
    "wof:placetype":"venue"
},
  "geometry": {"coordinates":[2.151125,49.73653],"type":"Point"}
}