{
  "type": "Feature",
  "properties": {
    "addr:full":"Rue de Laubette - Z.A. des Deux Rivi\u00e8res Rouen C\u00e9dex Basse Normandie 76012",
    "addr:postcode":"76012",
    "addr:street":"Rue De Laubette Z.A. Des Deux Rivie\u0300Res",
    "iso:country":"FR",
    "sg:address":"Rue de Laubette - Z.A. des Deux Rivi\u00e8res",
    "sg:city":"Rouen C\u00e9dex",
    "sg:orig_category":"Non-Classified Establishments",
    "sg:phone":"+33 2 32 12 38 00",
    "sg:postcode":"76012",
    "sg:province":"Basse Normandie",
    "wof:name":"C\u00e9d\u00e9o S.a.",
    "wof:placetype":"venue"
},
  "geometry": {"coordinates":[1.10154,49.443089],"type":"Point"}
}