{
  "type": "Feature",
  "properties": {
    "addr:full":"Chemin de Saint Fons Taulignan Rhone-Alpes 26770",
    "addr:postcode":"26770",
    "addr:street":"Chemin De Saint Fons Taulignan Rhone-Alpes",
    "iso:country":"FR",
    "sg:address":"Chemin de Saint Fons",
    "sg:city":"Taulignan",
    "sg:orig_category":"Unclassifiable Establishments",
    "sg:phone":"+33 4 75 53 55 36",
    "sg:postcode":"26770",
    "sg:province":"Rhone-Alpes",
    "wof:name":"Etablissements Charpenel Et Maury S.a.r.l.",
    "wof:placetype":"venue"
},
  "geometry": {"coordinates":[5.043869,44.39809],"type":"Point"}
}