{
  "type": "Feature",
  "properties": {
    "addr:full":"76 Rue Henri Barbusse 59129 Avesnes Les Aubert Nord Pas-de-Calais 59129",
    "addr:housenumber":"76",
    "addr:postcode":"59129;59129",
    "addr:street":"Rue Henri Barbusse;Pas-De-Calais",
    "iso:country":"FR",
    "sg:address":"76 Rue Henri Barbusse 59129 Avesnes Les Aubert",
    "sg:classifiers":[
        {
            "category":"Home & Garden",
            "subcategory":"Furniture",
            "type":"Retail Goods"
        }
    ],
    "sg:phone":"+33 3 27 37 66 66",
    "sg:postcode":"59129",
    "sg:province":"Nord Pas-de-Calais",
    "sg:tags":[
        "household",
        "wood"
    ],
    "wof:name":"Sfm",
    "wof:placetype":"venue"
},
  "geometry": {"coordinates":[3.386607,50.196106],"type":"Point"}
}