{
  "type": "Feature",
  "properties": {
    "iso:country":"FR",
    "sg:address":"76 Rue Henri Barbusse 59129 Avesnes Les Aubert",
    "sg:classifiers":[
        {
            "category":"Home & Garden",
            "subcategory":"Furniture",
            "type":"Retail Goods"
        }
    ],
    "sg:phone":"+33 3 27 37 66 66",
    "sg:postcode":"59129",
    "sg:province":"Nord Pas-de-Calais",
    "sg:tags":[
        "household",
        "wood"
    ],
    "wof:name":"Sfm",
    "wof:placetype":"venue"
},
  "geometry": {"coordinates":[3.386607,50.196106],"type":"Point"}
}