{
  "type": "Feature",
  "properties": {
    "iso:country":"FR",
    "sg:address":"187 rue Fondaud\u00e8ge; Bordeaux; 33000",
    "sg:city":"Bordeaux",
    "sg:classifiers":[
        {
            "category":"Banks & Credit Unions",
            "subcategory":"Bank",
            "type":"Services"
        }
    ],
    "sg:phone":"+33 3356818863",
    "sg:postcode":"33000",
    "sg:province":"Aquitaine",
    "wof:name":"Banque Populaire Du Sud-ouest",
    "wof:placetype":"venue"
},
  "geometry": {"coordinates":[-0.584745,44.849667],"type":"Point"}
}