{
  "type": "Feature",
  "properties": {
    "addr:full":"28, Quai Gailleton, 69002 Lyon Rhone-Alpes",
    "addr:housenumber":"28",
    "addr:postcode":"69002",
    "addr:street":"Quai Gailleton",
    "iso:country":"FR",
    "sg:address":"28, Quai Gailleton, 69002 Lyon",
    "sg:orig_category":"Unclassifiable Establishments",
    "sg:phone":"+33 4 78 38 00 17",
    "sg:province":"Rhone-Alpes",
    "wof:name":"Bnp Lease S.a.",
    "wof:placetype":"venue"
},
  "geometry": {"coordinates":[4.828975,45.759399],"type":"Point"}
}