{
  "type": "Feature",
  "properties": {
    "addr:full":"14, Av. de Verdun, 72200 La Fl\u00e8che Pays de Loire 72200",
    "addr:postcode":"72200;72200",
    "addr:street":"14 Av. De Verdun;Fle\u0300Che",
    "iso:country":"FR",
    "sg:address":"14, Av. de Verdun, 72200 La Fl\u00e8che",
    "sg:orig_category":"Non-Classified Establishments",
    "sg:phone":"+33 2 43 94 04 14",
    "sg:postcode":"72200",
    "sg:province":"Pays de Loire",
    "wof:name":"Etablissement Patrick Masson D\u00e9co Renov S.a.r.l.",
    "wof:placetype":"venue"
},
  "geometry": {"coordinates":[-0.097179,47.695889],"type":"Point"}
}