{
  "type": "Feature",
  "properties": {
    "addr:full":"530, Av. du Stade, 74950 Scionzier Rhone-Alpes",
    "addr:postcode":"74950",
    "addr:street":"530 Av. Du Stade",
    "iso:country":"FR",
    "sg:address":"530, Av. du Stade, 74950 Scionzier",
    "sg:orig_category":"Non-Classified Establishments",
    "sg:phone":"+33 4 50 96 14 23",
    "sg:province":"Rhone-Alpes",
    "wof:name":"Outimat S.a.s.",
    "wof:placetype":"venue"
},
  "geometry": {"coordinates":[6.556756,46.062504],"type":"Point"}
}