{
  "type": "Feature",
  "properties": {
    "iso:country":"FR",
    "sg:address":"44110 CHATEAUBRIANT",
    "sg:classifiers":[
        {
            "category":"Manufacturing",
            "subcategory":"Rubber & Plastics",
            "type":"Manufacturing & Wholesale Goods"
        }
    ],
    "sg:phone":"+33 2 40 81 14 41",
    "sg:postcode":"44110",
    "sg:province":"Pays de Loire",
    "sg:tags":[
        "injection",
        "moulding",
        "dy"
    ],
    "wof:name":"U.f.m. Sa",
    "wof:placetype":"venue"
},
  "geometry": {"coordinates":[-1.37553,47.711731],"type":"Point"}
}