{
  "type": "Feature",
  "properties": {
    "addr:full":"rue de la Gare 08140 BAZEILLES Champagne 08140",
    "addr:postcode":"08140;08140",
    "addr:street":"Rue De La Gare;Champagne",
    "iso:country":"FR",
    "sg:address":"rue de la Gare 08140 BAZEILLES",
    "sg:classifiers":[
        {
            "category":"Utilities",
            "subcategory":"Cable",
            "type":"Services"
        }
    ],
    "sg:phone":"+33 3 24 27 10 69",
    "sg:postcode":"08140",
    "sg:province":"Champagne",
    "sg:tags":[
        "forestry"
    ],
    "wof:name":"Reitz S.a.r.l.",
    "wof:placetype":"venue"
},
  "geometry": {"coordinates":[4.98409,49.671581],"type":"Point"}
}