{
  "type": "Feature",
  "properties": {
    "addr:full":"6, Rue des Charons, 31700 Blagnac Midi Pyr\u00e9n\u00e9es",
    "addr:housenumber":"6",
    "addr:postcode":"31700",
    "addr:street":"Rue Des Charons",
    "iso:country":"FR",
    "sg:address":"6, Rue des Charons, 31700 Blagnac",
    "sg:orig_category":"Unclassifiable Establishments",
    "sg:phone":"+33 5 61 71 04 80",
    "sg:province":"Midi Pyr\u00e9n\u00e9es",
    "wof:name":"G.h.m. Gesthotel S.a.",
    "wof:placetype":"venue"
},
  "geometry": {"coordinates":[1.381947,43.646122],"type":"Point"}
}