{
  "type": "Feature",
  "properties": {
    "iso:country":"FR",
    "sg:address":"26, Rue Pag\u00e8s, 92150 Suresnes",
    "sg:orig_category":"Non-Classified Establishments",
    "sg:phone":"+33 1 42 04 30 92",
    "sg:province":"Ile de France",
    "wof:name":"Stimlive S.a.r.l.",
    "wof:placetype":"venue"
},
  "geometry": {"coordinates":[2.229846,48.872185],"type":"Point"}
}