{
  "type": "Feature",
  "properties": {
    "addr:full":"37, Av. Eug\u00e9nie Cotton, 69120 Vaulx en Velin Rhone-Alpes 69120",
    "addr:postcode":"69120;69120",
    "addr:street":"37 Av. Euge\u0301Nie Cotton",
    "iso:country":"FR",
    "sg:address":"37, Av. Eug\u00e9nie Cotton, 69120 Vaulx en Velin",
    "sg:orig_category":"Unclassifiable Establishments",
    "sg:phone":"+33 4 78 80 41 08",
    "sg:postcode":"69120",
    "sg:province":"Rhone-Alpes",
    "wof:name":"Cor\u00e9vis Industries S.a.r.l.",
    "wof:placetype":"venue"
},
  "geometry": {"coordinates":[4.923801,45.771328],"type":"Point"}
}