{
  "type": "Feature",
  "properties": {
    "iso:country":"FR",
    "sg:address":"15, Rue Layni-Laroche, 49000 Angers",
    "sg:orig_category":"Non-Classified Establishments",
    "sg:phone":"+33 2 41 88 52 88",
    "sg:postcode":"49000",
    "sg:province":"Pays de Loire",
    "wof:name":"Bi - Eau S.a.r.l.",
    "wof:placetype":"venue"
},
  "geometry": {"coordinates":[-0.541929,47.462856],"type":"Point"}
}