{
  "type": "Feature",
  "properties": {
    "addr:full":"ZA de la Grave Carros Provence-Alpes-C\u00f4te d'Azur 06510",
    "addr:postcode":"06510",
    "addr:street":"Za De La Grave Carros",
    "iso:country":"FR",
    "sg:address":"ZA de la Grave",
    "sg:city":"Carros",
    "sg:orig_category":"Unclassifiable Establishments",
    "sg:phone":"+33 4 92 08 20 40",
    "sg:postcode":"06510",
    "sg:province":"Provence-Alpes-C\u00f4te d'Azur",
    "wof:name":"Snaf Routes S.a.",
    "wof:placetype":"venue"
},
  "geometry": {"coordinates":[7.191765,43.766804],"type":"Point"}
}