{
  "type": "Feature",
  "properties": {
    "iso:country":"FR",
    "sg:address":"27 Av Du Mal Joffre 94290 Villeneuve Le Roi",
    "sg:classifiers":[
        {
            "category":"Manufacturing",
            "subcategory":"Metals",
            "type":"Manufacturing & Wholesale Goods"
        }
    ],
    "sg:phone":"+33 1 45 97 13 50",
    "sg:postcode":"94290",
    "sg:province":"Ile de France",
    "sg:tags":[
        "metallurgy",
        "metalworking",
        "processing"
    ],
    "wof:name":"Nouailhac Gilles Sarl",
    "wof:placetype":"venue"
},
  "geometry": {"coordinates":[2.417932,48.73328],"type":"Point"}
}