{
  "type": "Feature",
  "properties": {
    "addr:full":"30 rue des Grandes Berges 77130 Montereau Fault Yonne Ile de France",
    "addr:housenumber":"30",
    "addr:postcode":"77130",
    "addr:street":"Rue Des Grandes Berges",
    "iso:country":"FR",
    "sg:address":"30 rue des Grandes Berges 77130 Montereau Fault Yonne",
    "sg:classifiers":[
        {
            "category":"Wholesale",
            "subcategory":"Farm Supplies",
            "type":"Manufacturing & Wholesale Goods"
        }
    ],
    "sg:phone":"+33 1 64 70 42 00",
    "sg:province":"Ile de France",
    "sg:tags":[
        "agricultural",
        "part",
        "spare",
        "machinery",
        "accessory"
    ],
    "wof:name":"Kuhn-nodet Sa",
    "wof:placetype":"venue"
},
  "geometry": {"coordinates":[2.95716,48.392288],"type":"Point"}
}