{
  "type": "Feature",
  "properties": {
    "addr:full":"28, Chemin du Petit Bois, 69130 Ecully Rhone-Alpes 69130",
    "addr:housenumber":"28",
    "addr:postcode":"69130;69130",
    "addr:street":"Chemin Du Petit Bois;Rhone-Alpes",
    "iso:country":"FR",
    "sg:address":"28, Chemin du Petit Bois, 69130 Ecully",
    "sg:orig_category":"Unclassifiable Establishments",
    "sg:phone":"+33 4 72 86 65 65",
    "sg:postcode":"69130",
    "sg:province":"Rhone-Alpes",
    "wof:name":"Vibratec S.a.",
    "wof:placetype":"venue"
},
  "geometry": {"coordinates":[4.762356,45.783138],"type":"Point"}
}