{
  "type": "Feature",
  "properties": {
    "addr:full":"59, Av des Vosges, 67000 Strasbourg Strasbourg Alsace 67000",
    "addr:postcode":"67000;67000",
    "addr:street":"59 Av Des Vosges",
    "iso:country":"FR",
    "sg:address":"59, Av des Vosges, 67000 Strasbourg",
    "sg:city":"Strasbourg",
    "sg:orig_category":"Unclassifiable Establishments",
    "sg:phone":"+33 3 88 35 06 57",
    "sg:postcode":"67000",
    "sg:province":"Alsace",
    "wof:name":"Roch Laboratoire S.a.r.l.",
    "wof:placetype":"venue"
},
  "geometry": {"coordinates":[7.74921,48.59013],"type":"Point"}
}