{
  "type": "Feature",
  "properties": {
    "addr:full":"21, Rue de Villeneuve, 02200 Soissons Picardie",
    "addr:housenumber":"21",
    "addr:postcode":"02200",
    "addr:street":"Rue De Villeneuve",
    "iso:country":"FR",
    "sg:address":"21, Rue de Villeneuve, 02200 Soissons",
    "sg:orig_category":"Non-Classified Establishments",
    "sg:phone":"+33 3 23 53 20 52",
    "sg:province":"Picardie",
    "wof:name":"M.a.g. S.a. - M\u00e9canique Agricole G\u00e9n\u00e9rale",
    "wof:placetype":"venue"
},
  "geometry": {"coordinates":[3.342375,49.372185],"type":"Point"}
}