{
  "type": "Feature",
  "properties": {
    "addr:full":"118/122, Av. Berlioz, 93230 Romainville Ile de France",
    "addr:housenumber":"118 / 122",
    "addr:postcode":"93230;ile",
    "addr:street":"Av. Berlioz",
    "iso:country":"FR",
    "sg:address":"118/122, Av. Berlioz, 93230 Romainville",
    "sg:orig_category":"Unclassifiable Establishments",
    "sg:phone":"+33 1 49 88 87 33",
    "sg:province":"Ile de France",
    "wof:name":"Joker S.a.r.l.",
    "wof:placetype":"venue"
},
  "geometry": {"coordinates":[2.439158,48.871952],"type":"Point"}
}