{
  "type": "Feature",
  "properties": {
    "addr:full":"15 Rue Des Ajoncs Zi De La Lande 33451 St Loub\u00e9s Cedex Haute Normandie",
    "addr:housenumber":"15",
    "addr:postcode":"33451;loube\u0301s cedex",
    "addr:street":"Rue Des Ajoncs Zi De La Lande",
    "iso:country":"FR",
    "sg:address":"15 Rue Des Ajoncs Zi De La Lande 33451 St Loub\u00e9s Cedex",
    "sg:classifiers":[
        {
            "category":"Shopping",
            "type":"Retail Goods"
        }
    ],
    "sg:phone":"+33 5 56 38 80 93",
    "sg:province":"Haute Normandie",
    "sg:tags":[
        "metallurgy",
        "finished",
        "-",
        "metalworking",
        "metallic"
    ],
    "wof:name":"Massias Entreprise Sarl",
    "wof:placetype":"venue"
},
  "geometry": {"coordinates":[-0.429024,44.91724],"type":"Point"}
}