{
  "type": "Feature",
  "properties": {
    "iso:country":"FR",
    "sg:address":"Rue Pr\u00e9 Comtal - Z.A.C. des Gravanches",
    "sg:city":"Clermont Ferrand",
    "sg:orig_category":"Unclassifiable Establishments",
    "sg:phone":"+33 4 73 25 84 70",
    "sg:postcode":"63100",
    "sg:province":"Auvergne",
    "wof:name":"C.e.r.p. Lorraine S.a. - Coop\u00e9rative Expansion Et R\u00e9partition Pharmaceutique",
    "wof:placetype":"venue"
},
  "geometry": {"coordinates":[2.09017,43.151814],"type":"Point"}
}