{
  "type": "Feature",
  "properties": {
    "iso:country":"FR",
    "sg:address":"180, Chemin du Stade - Thol , 01160 Neuville sur Ain",
    "sg:orig_category":"Non-Classified Establishments",
    "sg:phone":"+33 4 74 37 70 93",
    "sg:province":"Rhone-Alpes",
    "wof:name":"Capuano Jean",
    "wof:placetype":"venue"
},
  "geometry": {"coordinates":[5.327073,46.067696],"type":"Point"}
}