{
  "type": "Feature",
  "properties": {
    "addr:full":"180, Chemin du Stade - Thol , 01160 Neuville sur Ain Rhone-Alpes",
    "addr:housenumber":"180",
    "addr:postcode":"01160",
    "addr:street":"Chemin Du Stade Thol",
    "iso:country":"FR",
    "sg:address":"180, Chemin du Stade - Thol , 01160 Neuville sur Ain",
    "sg:orig_category":"Non-Classified Establishments",
    "sg:phone":"+33 4 74 37 70 93",
    "sg:province":"Rhone-Alpes",
    "wof:name":"Capuano Jean",
    "wof:placetype":"venue"
},
  "geometry": {"coordinates":[5.327073,46.067696],"type":"Point"}
}