{
  "type": "Feature",
  "properties": {
    "iso:country":"FR",
    "sg:address":"17 bis, Place des Reflets, 92077 Paris la D\u00e9fence C\u00e9dex",
    "sg:orig_category":"Non-Classified Establishments",
    "sg:phone":"+33 1 42 91 33 30",
    "sg:province":"\u00cele-de-France",
    "wof:name":"Tecnitas S.a.",
    "wof:placetype":"venue"
},
  "geometry": {"coordinates":[2.208,48.896141],"type":"Point"}
}