{
  "type": "Feature",
  "properties": {
    "iso:country":"FR",
    "sg:address":"1, Rue des Arquebusiers, 67000 Strasbourg",
    "sg:city":"Strasbourg",
    "sg:orig_category":"Unclassifiable Establishments",
    "sg:phone":"+33 3 88 15 33 60",
    "sg:postcode":"67000",
    "sg:province":"Alsace",
    "wof:name":"C.g.p. S.a. - Compagnie G\u00e9n\u00e9rale De Pr\u00e9voyance",
    "wof:placetype":"venue"
},
  "geometry": {"coordinates":[7.75897,48.590439],"type":"Point"}
}