{
  "type": "Feature",
  "properties": {
    "iso:country":"FR",
    "sg:address":"rue de l'Esplanade Nord 25220 Thise",
    "sg:classifiers":[
        {
            "category":"Manufacturing",
            "subcategory":"Rubber & Plastics",
            "type":"Manufacturing & Wholesale Goods"
        }
    ],
    "sg:phone":"+33 3 81 47 91 70",
    "sg:province":"Franche Comt\u00e9",
    "sg:tags":[
        "packaging",
        "mean"
    ],
    "wof:name":"Plastiform S.a.r.l.",
    "wof:placetype":"venue"
},
  "geometry": {"coordinates":[6.065125,47.272957],"type":"Point"}
}