{
  "type": "Feature",
  "properties": {
    "addr:full":"Peysales D'En Bas BP 2 Rte D'Espagne 09000 Foix Midi Pyr\u00e9n\u00e9es 09000",
    "addr:housenumber":"2",
    "addr:postcode":"09000;09000",
    "addr:street":"Rte D'Espagne",
    "iso:country":"FR",
    "sg:address":"Peysales D'En Bas BP 2 Rte D'Espagne 09000 Foix",
    "sg:classifiers":[
        {
            "category":"Banks & Credit Unions",
            "subcategory":"Investment Brokerage",
            "type":"Services"
        }
    ],
    "sg:phone":"+33 5 34 09 86 40",
    "sg:postcode":"09000",
    "sg:province":"Midi Pyr\u00e9n\u00e9es",
    "sg:tags":[
        "finance",
        "institution",
        "banking",
        "road",
        "insurance",
        "transport"
    ],
    "wof:name":"Valiance Fiduciaire Sa",
    "wof:placetype":"venue"
},
  "geometry": {"coordinates":[1.626488,42.948082],"type":"Point"}
}