{
  "type": "Feature",
  "properties": {
    "addr:full":"1 avenue Albert Calmette 59910 Bondues Nord Pas-de-Calais 59910",
    "addr:housenumber":"1",
    "addr:postcode":"59910;59910",
    "addr:street":"Avenue Albert Calmette",
    "iso:country":"FR",
    "sg:address":"1 avenue Albert Calmette 59910 Bondues",
    "sg:classifiers":[
        {
            "category":"Government",
            "subcategory":"Post Office",
            "type":"Public Place"
        }
    ],
    "sg:phone":"+33 3 20 28 98 38",
    "sg:postcode":"59910",
    "sg:province":"Nord Pas-de-Calais",
    "sg:tags":[
        "dress",
        "leisure"
    ],
    "wof:name":"Sahinler Sa",
    "wof:placetype":"venue"
},
  "geometry": {"coordinates":[3.128828,50.717396],"type":"Point"}
}