{
  "type": "Feature",
  "properties": {
    "iso:country":"FR",
    "sg:address":"Lotissement Des Pontots 64600 Anglet",
    "sg:city":"Anglet",
    "sg:classifiers":[
        {
            "category":"Manufacturing",
            "subcategory":"Rubber & Plastics",
            "type":"Manufacturing & Wholesale Goods"
        }
    ],
    "sg:phone":"+33 5 59 58 04 90",
    "sg:postcode":"64600",
    "sg:province":"Aquitaine",
    "wof:name":"Produits Metallurgiques Du Sud Ouest (pum Sa)",
    "wof:placetype":"venue"
},
  "geometry": {"coordinates":[-1.498519,43.493923],"type":"Point"}
}