{
  "type": "Feature",
  "properties": {
    "addr:full":"8 rue Colette 45230 CHATILLON COLIGNY Adon Centre 45230",
    "addr:housenumber":"8",
    "addr:postcode":"45230;45230",
    "addr:street":"Rue Colette",
    "iso:country":"FR",
    "sg:address":"8 rue Colette 45230 CHATILLON COLIGNY",
    "sg:city":"Adon",
    "sg:classifiers":[
        {
            "category":"Real Estate",
            "subcategory":"Real Estate Agent",
            "type":"Services"
        }
    ],
    "sg:phone":"+33 2 38 92 53 17",
    "sg:postcode":"45230",
    "sg:province":"Centre",
    "sg:tags":[
        "sample",
        "collection"
    ],
    "wof:name":"Brachot Pierre Sa",
    "wof:placetype":"venue"
},
  "geometry": {"coordinates":[2.848495,47.827351],"type":"Point"}
}