{
  "type": "Feature",
  "properties": {
    "addr:full":"Quartier la Confrerie Le Puy Sainte R\u00e9parade Provence-Alpes-C\u00f4te d'Azur 13610",
    "addr:postcode":"13610",
    "addr:street":"Quartier La Confrerie Le",
    "iso:country":"FR",
    "sg:address":"Quartier la Confrerie",
    "sg:city":"Le Puy Sainte R\u00e9parade",
    "sg:orig_category":"Unclassifiable Establishments",
    "sg:phone":"+33 4 42 33 86 00",
    "sg:postcode":"13610",
    "sg:province":"Provence-Alpes-C\u00f4te d'Azur",
    "wof:name":"Mors Technologie S.a.",
    "wof:placetype":"venue"
},
  "geometry": {"coordinates":[5.434375,43.662586],"type":"Point"}
}