{
  "type": "Feature",
  "properties": {
    "addr:full":"750, Av. du Docteur Jean Bru, 47000 Agen Agen Aquitaine 47000",
    "addr:housenumber":"750",
    "addr:postcode":"47000;47000",
    "addr:street":"Av. Du Docteur Jean Bru",
    "iso:country":"FR",
    "sg:address":"750, Av. du Docteur Jean Bru, 47000 Agen",
    "sg:city":"Agen",
    "sg:orig_category":"Unclassifiable Establishments",
    "sg:phone":"+33 5 53 77 03 00",
    "sg:postcode":"47000",
    "sg:province":"Aquitaine",
    "wof:name":"Imprimerie Moderne S.a.",
    "wof:placetype":"venue"
},
  "geometry": {"coordinates":[0.616189,44.193474],"type":"Point"}
}