{
  "type": "Feature",
  "properties": {
    "addr:full":"ZA Les Croisettes 80132 Huchenneville Picardie 80132",
    "addr:postcode":"80132;80132",
    "addr:street":"Za Les Croisettes;Picardie",
    "iso:country":"FR",
    "sg:address":"ZA Les Croisettes 80132 Huchenneville",
    "sg:classifiers":[
        {
            "category":"Shopping",
            "type":"Retail Goods"
        }
    ],
    "sg:phone":"+33 3 22 24 58 04",
    "sg:postcode":"80132",
    "sg:province":"Picardie",
    "sg:tags":[
        "metallurgy",
        "finished",
        "-",
        "metalworking",
        "metallic"
    ],
    "wof:name":"Tmcs",
    "wof:placetype":"venue"
},
  "geometry": {"coordinates":[1.79947,50.050785],"type":"Point"}
}