{
  "type": "Feature",
  "properties": {
    "addr:full":"B.P. 119, 28404 Nogent le Rotrou C\u00e9dex^^ZA de l'Huisne, 28400 Nogent le Rotrou Brunelles Centre 28400",
    "addr:housenumber":"b.p. 119",
    "addr:postcode":"28404;28400;28400",
    "iso:country":"FR",
    "sg:address":"B.P. 119, 28404 Nogent le Rotrou C\u00e9dex^^ZA de l'Huisne, 28400 Nogent le Rotrou",
    "sg:city":"Brunelles",
    "sg:orig_category":"Non-Classified Establishments",
    "sg:phone":"+33 2 37 53 54 20",
    "sg:postcode":"28400",
    "sg:province":"Centre",
    "wof:name":"I.m.p. S.a.r.l. - Imprimerie Peau",
    "wof:placetype":"venue"
},
  "geometry": {"coordinates":[0.808511,48.318604],"type":"Point"}
}