{
  "type": "Feature",
  "properties": {
    "addr:full":"1 Rue Eug\u00e8ne Varlin Les Dorides 44100 Nantes Pays de Loire 44100",
    "addr:housenumber":"1",
    "addr:postcode":"44100;44100",
    "addr:street":"Rue Euge\u0300Ne Varlin Les Dorides",
    "iso:country":"FR",
    "sg:address":"1 Rue Eug\u00e8ne Varlin Les Dorides 44100 Nantes",
    "sg:classifiers":[
        {
            "category":"Shopping",
            "subcategory":"Stationery & Office Supplies",
            "type":"Retail Goods"
        }
    ],
    "sg:phone":"+33 2 40 69 00 07",
    "sg:postcode":"44100",
    "sg:province":"Pays de Loire",
    "sg:tags":[
        "information",
        "technology",
        "telecommunication",
        "equipment"
    ],
    "wof:name":"Danka France",
    "wof:placetype":"venue"
},
  "geometry": {"coordinates":[-1.573119,47.207394],"type":"Point"}
}