{
  "type": "Feature",
  "properties": {
    "addr:full":"9 avenue Jacques Auneau 44300 Nantes Pays de Loire 44300",
    "addr:housenumber":"9",
    "addr:postcode":"44300;44300",
    "addr:street":"Avenue Jacques Auneau",
    "iso:country":"FR",
    "sg:address":"9 avenue Jacques Auneau 44300 Nantes",
    "sg:classifiers":[
        {
            "category":"Professional",
            "subcategory":"Business Services",
            "type":"Services"
        }
    ],
    "sg:phone":"+33 2 40 52 18 41",
    "sg:postcode":"44300",
    "sg:province":"Pays de Loire",
    "sg:tags":[
        "high-precision",
        "mechanic"
    ],
    "wof:name":"Sovecop Sarl",
    "wof:placetype":"venue"
},
  "geometry": {"coordinates":[-1.525742,47.23661],"type":"Point"}
}