{
  "type": "Feature",
  "properties": {
    "addr:full":"Zone Industrielle des Aulnaies Saint Sa\u00ebns Haute Normandie 76680",
    "addr:postcode":"76680",
    "addr:street":"Zone Industrielle Des Aulnaies Saint Sae\u0308Ns Haute Normandie",
    "iso:country":"FR",
    "sg:address":"Zone Industrielle des Aulnaies",
    "sg:city":"Saint Sa\u00ebns",
    "sg:orig_category":"Non-Classified Establishments",
    "sg:phone":"+33 2 35 32 69 65",
    "sg:postcode":"76680",
    "sg:province":"Haute Normandie",
    "wof:name":"Gamatex S.a.r.l.",
    "wof:placetype":"venue"
},
  "geometry": {"coordinates":[1.28323,49.67276],"type":"Point"}
}