{
  "type": "Feature",
  "properties": {
    "iso:country":"FR",
    "sg:address":"57, Rue de Franche Comt\u00e9, 21760 Lamarche sur Sa\u00f4ne",
    "sg:city":"Lamarche-sur-Sa\u00f4ne",
    "sg:orig_category":"Unclassifiable Establishments",
    "sg:phone":"+33 3 80 77 11 00",
    "sg:postcode":"21760",
    "sg:province":"Bourgogne",
    "wof:name":"Sopemi S.a.r.l.",
    "wof:placetype":"venue"
},
  "geometry": {"coordinates":[5.388216,47.281223],"type":"Point"}
}