{
  "type": "Feature",
  "properties": {
    "iso:country":"FR",
    "sg:address":"B.P. 3, 17182 P\u00e9rigny C\u00e9dex^^Av. Louis Lumi\u00e8re - ZI de P\u00e9rigny, 17180 P\u00e9rigny",
    "sg:orig_category":"Non-Classified Establishments",
    "sg:phone":"+33 5 46 51 78 00",
    "sg:postcode":"17180",
    "sg:province":"Poitou-Charentes",
    "wof:name":"Etablissements Lh\u00e9riteau Et Compagnie S.a.s.",
    "wof:placetype":"venue"
},
  "geometry": {"coordinates":[-1.096665,46.15501],"type":"Point"}
}