{
  "type": "Feature",
  "properties": {
    "addr:full":"10, Rue de l'Industrie, 49120 La Tourlandry Pays de Loire",
    "addr:housenumber":"10",
    "addr:postcode":"49120",
    "addr:street":"Rue De L'Industrie;Tourlandry",
    "iso:country":"FR",
    "sg:address":"10, Rue de l'Industrie, 49120 La Tourlandry",
    "sg:orig_category":"Unclassifiable Establishments",
    "sg:phone":"+33 2 41 65 44 77",
    "sg:province":"Pays de Loire",
    "wof:name":"Chaussures Cuir Michigan S.a.r.l.",
    "wof:placetype":"venue"
},
  "geometry": {"coordinates":[-0.698547,47.144096],"type":"Point"}
}