{
  "type": "Feature",
  "properties": {
    "addr:full":"69 chemin Neuf 69780 Toussieu Rhone-Alpes 69780",
    "addr:housenumber":"69",
    "addr:postcode":"69780;69780",
    "addr:street":"Chemin Neuf;Rhone-Alpes",
    "iso:country":"FR",
    "sg:address":"69 chemin Neuf 69780 Toussieu",
    "sg:classifiers":[
        {
            "category":"Home & Garden",
            "subcategory":"Furniture",
            "type":"Retail Goods"
        }
    ],
    "sg:phone":"+33 4 72 48 03 63",
    "sg:postcode":"69780",
    "sg:province":"Rhone-Alpes",
    "sg:tags":[
        "living",
        "room"
    ],
    "wof:name":"Xpo Sas",
    "wof:placetype":"venue"
},
  "geometry": {"coordinates":[4.992358,45.66317],"type":"Point"}
}