{
  "type": "Feature",
  "properties": {
    "addr:full":"9, Rue aux Ours, 75003 Paris Ile de France",
    "addr:housenumber":"9",
    "addr:postcode":"75003",
    "addr:street":"Rue Aux Ours",
    "iso:country":"FR",
    "sg:address":"9, Rue aux Ours, 75003 Paris",
    "sg:orig_category":"Non-Classified Establishments",
    "sg:phone":"+33 1 44 54 32 90",
    "sg:province":"Ile de France",
    "wof:name":"Gyoza M\u00e9dia S.a.r.l.",
    "wof:placetype":"venue"
},
  "geometry": {"coordinates":[2.351961,48.863018],"type":"Point"}
}