{
  "type": "Feature",
  "properties": {
    "addr:full":"Traon Elorn 29800 Landerneau Landerneau Bretagne 29800",
    "addr:postcode":"29800;29800",
    "addr:street":"Elorn",
    "iso:country":"FR",
    "sg:address":"Traon Elorn 29800 Landerneau",
    "sg:city":"Landerneau",
    "sg:orig_category":"Business advice and other services Clothes Household goods Wood and Furniture",
    "sg:phone":"+33 2 98 21 57 75",
    "sg:postcode":"29800",
    "sg:province":"Bretagne",
    "wof:name":"Societe Fabrication Meubles Guy Le Bihan",
    "wof:placetype":"venue"
},
  "geometry": {"coordinates":[-4.228497,48.400295],"type":"Point"}
}