{
  "type": "Feature",
  "properties": {
    "iso:country":"FR",
    "sg:address":"Av de l'Ermitage - Zone Industrielle 4",
    "sg:city":"Saint Laurent Blangy",
    "sg:orig_category":"Unclassifiable Establishments",
    "sg:phone":"+33 3 21 60 44 44",
    "sg:postcode":"62223",
    "sg:province":"Nord Pas-de-Calais",
    "wof:name":"Bossu Cuvelier S.a.",
    "wof:placetype":"venue"
},
  "geometry": {"coordinates":[2.719059,50.281082],"type":"Point"}
}