{
  "type": "Feature",
  "properties": {
    "addr:full":"42-44 Rue Panicale 78320 La Verri\u00e8re Ile de France",
    "addr:housenumber":"42-44",
    "addr:postcode":"78320",
    "addr:street":"Rue Panicale",
    "iso:country":"FR",
    "sg:address":"42-44 Rue Panicale 78320 La Verri\u00e8re",
    "sg:classifiers":[
        {
            "category":"Utilities",
            "subcategory":"Telephone",
            "type":"Services"
        }
    ],
    "sg:phone":"+33 1 30 62 30 30",
    "sg:province":"Ile de France",
    "sg:tags":[
        "telecommunication"
    ],
    "wof:name":"Mic Data Sa",
    "wof:placetype":"venue"
},
  "geometry": {"coordinates":[1.946236,48.757343],"type":"Point"}
}