{
  "type": "Feature",
  "properties": {
    "addr:full":"B.P. 116, 41203 Romorantin Lanthenay C\u00e9dex^^Rte de Blois - ZI de la Grange, 41200 Romorantin Lanthen Villefranche-sur-Cher Centre 41200",
    "addr:housenumber":"b.p. 116",
    "addr:postcode":"41203;41200;41200",
    "addr:street":"La Grange",
    "iso:country":"FR",
    "sg:address":"B.P. 116, 41203 Romorantin Lanthenay C\u00e9dex^^Rte de Blois - ZI de la Grange, 41200 Romorantin Lanthen",
    "sg:city":"Villefranche-sur-Cher",
    "sg:orig_category":"Non-Classified Establishments",
    "sg:phone":"+33 2 54 94 12 50",
    "sg:postcode":"41200",
    "sg:province":"Centre",
    "wof:name":"Etablissements Charbonnier S.a.",
    "wof:placetype":"venue"
},
  "geometry": {"coordinates":[1.76969,47.294876],"type":"Point"}
}