{
  "type": "Feature",
  "properties": {
    "iso:country":"FR",
    "sg:address":"1 pl Gu\u00e9pin; Savenay; 44260",
    "sg:classifiers":[
        {
            "category":"Banks & Credit Unions",
            "subcategory":"Bank",
            "type":"Services"
        }
    ],
    "sg:phone":"+33 3340569010",
    "sg:postcode":"44260",
    "sg:province":"Pays de Loire",
    "wof:name":"Caisse Regionale De Cr\u00e9dit Agricole",
    "wof:placetype":"venue"
},
  "geometry": {"coordinates":[-1.943378,47.359905],"type":"Point"}
}