{
  "type": "Feature",
  "properties": {
    "iso:country":"FR",
    "sg:address":"117-119 Av Paul Marcellin BP 1 69511 Vaulx En Velin Cedex",
    "sg:classifiers":[
        {
            "category":"Wholesale",
            "subcategory":"Farm Supplies",
            "type":"Manufacturing & Wholesale Goods"
        }
    ],
    "sg:phone":"+33 4 78 79 48 48",
    "sg:province":"Pays de Loire",
    "sg:tags":[
        "-",
        "machine",
        "equipment",
        "engineering",
        "machinery",
        "mechanical",
        "agriculture"
    ],
    "wof:name":"Blount France Sa",
    "wof:placetype":"venue"
},
  "geometry": {"coordinates":[4.930886,45.778141],"type":"Point"}
}