{
  "type": "Feature",
  "properties": {
    "iso:country":"FR",
    "sg:address":"12, Rue Vincent Auriol - ZI Nord, 64000 Pau",
    "sg:city":"Pau",
    "sg:orig_category":"Non-Classified Establishments",
    "sg:phone":"+33 5 59 02 52 09",
    "sg:postcode":"64000",
    "sg:province":"Aquitaine",
    "wof:name":"M\u00e9canique De Pr\u00e9cision I Toulouse Et Compagnie S.a.",
    "wof:placetype":"venue"
},
  "geometry": {"coordinates":[-0.374294,43.296558],"type":"Point"}
}