{
  "type": "Feature",
  "properties": {
    "addr:full":"Rue de la Julienne - ZI Le Coudray Montceaux Ile de France 91830",
    "addr:postcode":"91830",
    "addr:street":"Rue De La Julienne Zi;Coudray;Ile De France",
    "iso:country":"FR",
    "sg:address":"Rue de la Julienne - ZI",
    "sg:city":"Le Coudray Montceaux",
    "sg:orig_category":"Non-Classified Establishments",
    "sg:phone":"+33 1 64 93 83 98",
    "sg:postcode":"91830",
    "sg:province":"Ile de France",
    "wof:name":"Serm S.a.",
    "wof:placetype":"venue"
},
  "geometry": {"coordinates":[2.485505,48.565704],"type":"Point"}
}