{
  "type": "Feature",
  "properties": {
    "iso:country":"FR",
    "sg:address":"13 Rue Jean Moulin 59128 Flers En Escrebieux",
    "sg:classifiers":[
        {
            "category":"Home & Garden",
            "subcategory":"Home Furnishings",
            "type":"Retail Goods"
        }
    ],
    "sg:phone":"+33 3 27 90 82 40",
    "sg:postcode":"59128",
    "sg:province":"Nord Pas-de-Calais",
    "sg:tags":[
        "household",
        "appliance",
        "equipment",
        "wood",
        "electrical",
        "electronic",
        "furniture"
    ],
    "wof:name":"Ets Destexhe",
    "wof:placetype":"venue"
},
  "geometry": {"coordinates":[3.045467,50.403728],"type":"Point"}
}