{
  "type": "Feature",
  "properties": {
    "iso:country":"FR",
    "sg:address":"5 Rue Du Closeau 71640 Mercurey",
    "sg:city":"Mercurey",
    "sg:classifiers":[
        {
            "category":"Food Court",
            "type":"Food & Drink"
        }
    ],
    "sg:phone":"+33 3 85 45 29 29",
    "sg:postcode":"71640",
    "sg:province":"Bourgogne",
    "sg:tags":[
        "product",
        "related"
    ],
    "wof:name":"Caves Du Val D' Or Sarl",
    "wof:placetype":"venue"
},
  "geometry": {"coordinates":[4.734548,46.833981],"type":"Point"}
}