{
  "type": "Feature",
  "properties": {
    "addr:full":"1 Rue De Verdun 57120 PIERREVILLERS Lorraine",
    "addr:housenumber":"1",
    "addr:postcode":"57120",
    "addr:street":"Rue De Verdun",
    "iso:country":"FR",
    "sg:address":"1 Rue De Verdun 57120 PIERREVILLERS",
    "sg:orig_category":"Soya Bean Meal",
    "sg:phone":"+33 3 87 67 61 61",
    "sg:province":"Lorraine",
    "wof:name":"Heng Sieng Sa",
    "wof:placetype":"venue"
},
  "geometry": {"coordinates":[6.110904,49.22863],"type":"Point"}
}