{
  "type": "Feature",
  "properties": {
    "iso:country":"FR",
    "sg:address":"10 Rue De La Mairie 53440 La Bazoge Montpincon",
    "sg:classifiers":[
        {
            "category":"Wholesale",
            "subcategory":"Farm Supplies",
            "type":"Manufacturing & Wholesale Goods"
        }
    ],
    "sg:phone":"+33 2 43 04 12 67",
    "sg:postcode":"53440",
    "sg:province":"Pays de Loire",
    "sg:tags":[
        "-",
        "machine",
        "equipment",
        "engineering",
        "machinery",
        "mechanical",
        "agriculture"
    ],
    "wof:name":"Adaf Somatherm",
    "wof:placetype":"venue"
},
  "geometry": {"coordinates":[-0.571163,48.27961],"type":"Point"}
}