{
  "type": "Feature",
  "properties": {
    "addr:full":"65300 Lannemezan Midi Pyr\u00e9n\u00e9es",
    "addr:postcode":"65300",
    "iso:country":"FR",
    "sg:address":"65300 Lannemezan",
    "sg:orig_category":"Unclassifiable Establishments",
    "sg:phone":"+33 5 62 40 63 06",
    "sg:province":"Midi Pyr\u00e9n\u00e9es",
    "wof:name":"Elf Atochem - Usine De Lannemezan S.a.",
    "wof:placetype":"venue"
},
  "geometry": {"coordinates":[0.39478,43.142029],"type":"Point"}
}