{
  "type": "Feature",
  "properties": {
    "iso:country":"FR",
    "sg:address":"1027 Av Du Docteur Lef\u00e8vre BP 27 06271 Villeneuve Loubet",
    "sg:city":"Vill\u00e9",
    "sg:classifiers":[
        {
            "category":"Professional",
            "subcategory":"Computer Services",
            "type":"Services"
        }
    ],
    "sg:phone":"+33 4 92 02 45 45",
    "sg:postcode":"67220",
    "sg:province":"Alsace",
    "sg:tags":[
        "information",
        "technology",
        "software"
    ],
    "wof:name":"Studiel",
    "wof:placetype":"venue"
},
  "geometry": {"coordinates":[7.12296,43.657749],"type":"Point"}
}