{
  "type": "Feature",
  "properties": {
    "iso:country":"FR",
    "sg:address":"371 Rue De L Albanne Z I De L Albanne 73490 La Ravoire",
    "sg:classifiers":[
        {
            "category":"Shopping",
            "type":"Retail Goods"
        }
    ],
    "sg:phone":"+33 4 79 71 66 30",
    "sg:postcode":"73490",
    "sg:province":"Rhone-Alpes",
    "sg:tags":[
        "metallurgy",
        "finished",
        "-",
        "metalworking",
        "metallic"
    ],
    "wof:name":"Cofamolds Industries",
    "wof:placetype":"venue"
},
  "geometry": {"coordinates":[5.961922,45.55677],"type":"Point"}
}