{
  "type": "Feature",
  "properties": {
    "iso:country":"FR",
    "sg:address":"Le Bourg 33460 Arcins",
    "sg:city":"Arcins",
    "sg:orig_category":"Unclassifiable Establishments",
    "sg:phone":"+33 5 56 59 04 93",
    "sg:postcode":"33460",
    "sg:province":"Aquitaine",
    "wof:name":"Bernardini S.a.",
    "wof:placetype":"venue"
},
  "geometry": {"coordinates":[-0.712874,44.964851],"type":"Point"}
}