{
  "type": "Feature",
  "properties": {
    "addr:full":"ZI Chemin Gillard Dagneux Rhone-Alpes 01120",
    "addr:postcode":"01120",
    "addr:street":"Chemin Gillard;Rhone-Alpes",
    "iso:country":"FR",
    "sg:address":"ZI Chemin Gillard",
    "sg:city":"Dagneux",
    "sg:orig_category":"Non-Classified Establishments",
    "sg:phone":"+33 4 78 06 33 21",
    "sg:postcode":"01120",
    "sg:province":"Rhone-Alpes",
    "wof:name":"A.m.o.b. S.a.r.l. - Agencement Mobilier",
    "wof:placetype":"venue"
},
  "geometry": {"coordinates":[5.074815,45.850704],"type":"Point"}
}