{
  "type": "Feature",
  "properties": {
    "addr:full":"4/8, All\u00e9e de Maison Rouge, 87410 Le Palais sur Vienne Limousin",
    "addr:housenumber":"4 / 8",
    "addr:postcode":"87410",
    "addr:street":"Alle\u0301E De Maison Rouge",
    "iso:country":"FR",
    "sg:address":"4/8, All\u00e9e de Maison Rouge, 87410 Le Palais sur Vienne",
    "sg:orig_category":"Unclassifiable Establishments",
    "sg:phone":"+33 5 55 33 86 50",
    "sg:province":"Limousin",
    "wof:name":"S.a.d. S.a. - Soci\u00e9t\u00e9 D'agences Et De Diffusion",
    "wof:placetype":"venue"
},
  "geometry": {"coordinates":[1.305783,45.853329],"type":"Point"}
}