{
  "type": "Feature",
  "properties": {
    "iso:country":"FR",
    "sg:address":"Rue Pasteur 81990 Puygouzon",
    "sg:classifiers":[
        {
            "category":"Manufacturing",
            "subcategory":"Rubber & Plastics",
            "type":"Manufacturing & Wholesale Goods"
        }
    ],
    "sg:phone":"+33 5 63 38 10 18",
    "sg:province":"Midi Pyr\u00e9n\u00e9es",
    "wof:name":"Frans Bonhomme",
    "wof:placetype":"venue"
},
  "geometry": {"coordinates":[2.162053,43.892517],"type":"Point"}
}