{
  "type": "Feature",
  "properties": {
    "iso:country":"FR",
    "sg:address":"B.P. 29, 59112 Carnin^^Rte de Camphin, 59112 Carnin",
    "sg:orig_category":"Non-Classified Establishments",
    "sg:phone":"+33 3 20 90 72 72",
    "sg:province":"Nord Pas-de-Calais",
    "wof:name":"Fonderie Fran\u00e7aise Du Chauffage S.a.",
    "wof:placetype":"venue"
},
  "geometry": {"coordinates":[2.931675,50.529125],"type":"Point"}
}