{
  "type": "Feature",
  "properties": {
    "addr:full":"200 Rte De Sarves 74370 Metz Tessy Rhone-Alpes",
    "addr:housenumber":"200",
    "addr:postcode":"74370",
    "addr:street":"Rte De Sarves",
    "iso:country":"FR",
    "sg:address":"200 Rte De Sarves 74370 Metz Tessy",
    "sg:classifiers":[
        {
            "category":"Manufacturing",
            "subcategory":"Rubber & Plastics",
            "type":"Manufacturing & Wholesale Goods"
        }
    ],
    "sg:phone":"+33 4 50 27 34 50",
    "sg:province":"Rhone-Alpes",
    "wof:name":"Cgl Thermoformage Sa",
    "wof:placetype":"venue"
},
  "geometry": {"coordinates":[6.11407,45.926991],"type":"Point"}
}