{
  "type": "Feature",
  "properties": {
    "iso:country":"FR",
    "sg:address":"B.P. 35, 71302 Montceau les Mines C\u00e9dex^^16, Rue Jean Bouverie, 71230 Saint Vallier",
    "sg:city":"Saint-Romain-sous-Gourdon",
    "sg:orig_category":"Non-Classified Establishments",
    "sg:phone":"+33 3 85 67 66 00",
    "sg:postcode":"71230",
    "sg:province":"Bourgogne",
    "wof:name":"K.c.p. Gerbe S.a.",
    "wof:placetype":"venue"
},
  "geometry": {"coordinates":[4.372046,46.640839],"type":"Point"}
}