{
  "type": "Feature",
  "properties": {
    "iso:country":"FR",
    "sg:address":"3 Rue Newton 44241 La Chapelle Sur Erdre",
    "sg:city":"La Chapelle",
    "sg:classifiers":[
        {
            "category":"Professional",
            "subcategory":"Credit Reporting & Collection",
            "type":"Services"
        }
    ],
    "sg:phone":"+33 2 40 37 14 00",
    "sg:postcode":"03300",
    "sg:province":"Auvergne",
    "sg:tags":[
        "processing",
        "data"
    ],
    "wof:name":"Sigma Informatique Sarl",
    "wof:placetype":"venue"
},
  "geometry": {"coordinates":[-1.548297,47.262165],"type":"Point"}
}