{
  "type": "Feature",
  "properties": {
    "addr:full":"20E, Rue Salomon Grumbach - Parc d'Activit\u00e9s la Mer Rouge, 68200 Mulhouse Mulhouse Alsace 68200",
    "addr:postcode":"68200;68200",
    "addr:street":"20E Rue Salomon Grumbach Parc D'Activite \u0301S La Mer Rouge",
    "iso:country":"FR",
    "sg:address":"20E, Rue Salomon Grumbach - Parc d'Activit\u00e9s la Mer Rouge, 68200 Mulhouse",
    "sg:city":"Mulhouse",
    "sg:orig_category":"Unclassifiable Establishments",
    "sg:phone":"+33 3 89 60 85 30",
    "sg:postcode":"68200",
    "sg:province":"Alsace",
    "wof:name":"Rge S.a.r.l.",
    "wof:placetype":"venue"
},
  "geometry": {"coordinates":[7.306051,47.747349],"type":"Point"}
}