{
  "type": "Feature",
  "properties": {
    "iso:country":"FR",
    "sg:address":"3 rue Flandres Dunkerque 27230 THIBERVILLE",
    "sg:classifiers":[
        {
            "category":"Manufacturing",
            "subcategory":"Textiles",
            "type":"Manufacturing & Wholesale Goods"
        }
    ],
    "sg:phone":"+33 2 32 46 80 02",
    "sg:postcode":"27230",
    "sg:province":"Haute Normandie",
    "sg:tags":[
        "natural"
    ],
    "wof:name":"Les Rubans R. Lecuyer Sarl",
    "wof:placetype":"venue"
},
  "geometry": {"coordinates":[0.460923,49.138996],"type":"Point"}
}