{
  "type": "Feature",
  "properties": {
    "addr:full":"54350 Mont Saint Martin Lorraine",
    "addr:postcode":"54350",
    "addr:street":"Mont Saint Martin",
    "iso:country":"FR",
    "sg:address":"54350 Mont Saint Martin",
    "sg:orig_category":"Unclassifiable Establishments",
    "sg:phone":"+33 3 82 25 50 50",
    "sg:province":"Lorraine",
    "wof:name":"Cerf S.a.",
    "wof:placetype":"venue"
},
  "geometry": {"coordinates":[5.784635,49.544926],"type":"Point"}
}