{
  "type": "Feature",
  "properties": {
    "iso:country":"FR",
    "sg:address":"Zi Des Tanes Basses 34800 Clermont L'H\u00e9rault",
    "sg:classifiers":[
        {
            "category":"Manufacturing",
            "subcategory":"Rubber & Plastics",
            "type":"Manufacturing & Wholesale Goods"
        }
    ],
    "sg:phone":"+33 4 67 88 48 48",
    "sg:province":"Languedoc-Roussillon",
    "wof:name":"Socah Division Pneumatiques Service Commercial Sa",
    "wof:placetype":"venue"
},
  "geometry": {"coordinates":[3.489121,43.554108],"type":"Point"}
}