{
  "type": "Feature",
  "properties": {
    "addr:full":"Rue d'Espagne - ZA de l'Europe Mions Rhone-Alpes 69780",
    "addr:postcode":"69780",
    "addr:street":"Rue D'Espagne Za De L'Europe;Rhone-Alpes",
    "iso:country":"FR",
    "sg:address":"Rue d'Espagne - ZA de l'Europe",
    "sg:city":"Mions",
    "sg:orig_category":"Unclassifiable Establishments",
    "sg:phone":"+33 4 78 20 62 55",
    "sg:postcode":"69780",
    "sg:province":"Rhone-Alpes",
    "wof:name":"Trans Viande S.a.r.l.",
    "wof:placetype":"venue"
},
  "geometry": {"coordinates":[4.935274,45.679462],"type":"Point"}
}