{
  "type": "Feature",
  "properties": {
    "iso:country":"FR",
    "sg:address":"B.P. 178, 81304 Graulhet C\u00e9dex^^88, Av. Charles de Gaulle, 81300 Graulhet",
    "sg:orig_category":"Non-Classified Establishments",
    "sg:phone":"+33 5 63 34 59 44",
    "sg:province":"Midi Pyr\u00e9n\u00e9es",
    "wof:name":"Maroquinerie Jean Mauri\u00e9s S.a.r.l.",
    "wof:placetype":"venue"
},
  "geometry": {"coordinates":[2.028947,43.697151],"type":"Point"}
}