{
  "type": "Feature",
  "properties": {
    "addr:full":"4, Rue des Rastoubles, 13127 Vitrolles Centre",
    "addr:housenumber":"4",
    "addr:postcode":"13127",
    "addr:street":"Rue Des Rastoubles",
    "iso:country":"FR",
    "sg:address":"4, Rue des Rastoubles, 13127 Vitrolles",
    "sg:orig_category":"Non-Classified Establishments",
    "sg:phone":"+33 4 42 89 83 03",
    "sg:province":"Centre",
    "wof:name":"A.i.p. S.a.r.l. - Automatisme Industriel Provence",
    "wof:placetype":"venue"
},
  "geometry": {"coordinates":[5.288325,43.423023],"type":"Point"}
}