{
  "type": "Feature",
  "properties": {
    "iso:country":"FR",
    "sg:address":"223, Av. Edmond Michelet - ZAC du Breuil, 54700 Pont \u00e0 Mousson",
    "sg:orig_category":"Unclassifiable Establishments",
    "sg:phone":"+33 3 83 84 02 03",
    "sg:province":"Lorraine",
    "wof:name":"Locapharm S.a.",
    "wof:placetype":"venue"
},
  "geometry": {"coordinates":[6.054945,48.902954],"type":"Point"}
}