{
  "type": "Feature",
  "properties": {
    "iso:country":"FR",
    "sg:address":"1, Av. de Tours, 72500 Ch\u00e2teau du Loir",
    "sg:orig_category":"Non-Classified Establishments",
    "sg:phone":"+33 2 43 44 74 00",
    "sg:postcode":"72500",
    "sg:province":"Pays de Loire",
    "wof:name":"A.r.o. Machines \u00e0 Souder S.a.",
    "wof:placetype":"venue"
},
  "geometry": {"coordinates":[0.42801,47.689548],"type":"Point"}
}