{
  "type": "Feature",
  "properties": {
    "iso:country":"FR",
    "sg:address":"22",
    "sg:city":"Galli\u00e9ni; Suresnes; 92158",
    "sg:classifiers":[
        {
            "category":"Shopping",
            "subcategory":"Computers & Home Electronics",
            "type":"Retail Goods"
        }
    ],
    "sg:phone":"+33 1 46 25 71 06",
    "sg:province":"Nord Pas-de-Calais",
    "sg:tags":[
        "chamber",
        "commerce"
    ],
    "wof:name":"Chambre De Commerce Franco-libanaise - Suresnes",
    "wof:placetype":"venue"
},
  "geometry": {"coordinates":[2.22677,48.867504],"type":"Point"}
}