{
  "type": "Feature",
  "properties": {
    "addr:full":"B.P. 314, 95190 Goussainville C\u00e9dex^^10, Rue Robert Moinon, 95190 Goussainville Ile de France",
    "addr:housenumber":"b.p. 314",
    "addr:postcode":"95190;95190",
    "addr:street":"Rue Robert Moinon",
    "iso:country":"FR",
    "sg:address":"B.P. 314, 95190 Goussainville C\u00e9dex^^10, Rue Robert Moinon, 95190 Goussainville",
    "sg:orig_category":"Non-Classified Establishments",
    "sg:phone":"+33 1 39 33 94 94",
    "sg:province":"Ile de France",
    "wof:name":"Location Industries S.a.",
    "wof:placetype":"venue"
},
  "geometry": {"coordinates":[2.47375,49.032452],"type":"Point"}
}