{
  "type": "Feature",
  "properties": {
    "addr:full":"10, Rue de Lyon, 71000 M\u00e2con Sanc\u00e9 Bourgogne 71000",
    "addr:housenumber":"10",
    "addr:postcode":"71000;71000",
    "addr:street":"Rue De Lyon",
    "iso:country":"FR",
    "sg:address":"10, Rue de Lyon, 71000 M\u00e2con",
    "sg:city":"Sanc\u00e9",
    "sg:orig_category":"Unclassifiable Establishments",
    "sg:phone":"+33 3 85 39 87 87",
    "sg:postcode":"71000",
    "sg:province":"Bourgogne",
    "wof:name":"B.p.f.c.m.a. - Banque Populaire De Franche-comt\u00e9 Du Maconnais Et De L'ain",
    "wof:placetype":"venue"
},
  "geometry": {"coordinates":[4.829699,46.30209],"type":"Point"}
}