{
  "type": "Feature",
  "properties": {
    "iso:country":"FR",
    "sg:address":"17, Av du G\u00e9n\u00e9ral de Gaulle, 58000 Nevers",
    "sg:city":"Nevers",
    "sg:orig_category":"Unclassifiable Establishments",
    "sg:phone":"+33 3 86 57 20 31",
    "sg:postcode":"58000",
    "sg:province":"Bourgogne",
    "wof:name":"Imprimerie De La Gare S.a.r.l.",
    "wof:placetype":"venue"
},
  "geometry": {"coordinates":[3.15444,46.988075],"type":"Point"}
}