{
  "type": "Feature",
  "properties": {
    "addr:full":"10, Rue Pierre Curie, 93120 La Courneuve Ile de France",
    "addr:housenumber":"10",
    "addr:postcode":"93120",
    "addr:street":"Rue Pierre Curie",
    "iso:country":"FR",
    "sg:address":"10, Rue Pierre Curie, 93120 La Courneuve",
    "sg:orig_category":"Unclassifiable Establishments",
    "sg:phone":"+33 1 53 56 15 15",
    "sg:province":"Ile de France",
    "wof:name":"Sun City S.a.",
    "wof:placetype":"venue"
},
  "geometry": {"coordinates":[2.381919,48.921173],"type":"Point"}
}