{
  "type": "Feature",
  "properties": {
    "iso:country":"FR",
    "sg:address":"R De L'Industrie Zi Des Repes 70000 Vesoul",
    "sg:classifiers":[
        {
            "category":"Wholesale",
            "subcategory":"Farm Supplies",
            "type":"Manufacturing & Wholesale Goods"
        }
    ],
    "sg:phone":"+33 3 84 96 77 00",
    "sg:postcode":"70000",
    "sg:province":"Franche Comt\u00e9",
    "sg:tags":[
        "-",
        "machine",
        "equipment",
        "engineering",
        "machinery",
        "mechanical",
        "agriculture"
    ],
    "wof:name":"Samas Evolution",
    "wof:placetype":"venue"
},
  "geometry": {"coordinates":[6.170139,47.637432],"type":"Point"}
}