{
  "type": "Feature",
  "properties": {
    "addr:full":"B.P. 2, 12550 Coupiac C\u00e9dex^^Rte de Monclar, 12550 Coupiac Midi Pyr\u00e9n\u00e9es",
    "addr:housenumber":"2",
    "addr:postcode":"12550;12550",
    "addr:street":"B.P.;Monclar",
    "iso:country":"FR",
    "sg:address":"B.P. 2, 12550 Coupiac C\u00e9dex^^Rte de Monclar, 12550 Coupiac",
    "sg:orig_category":"Non-Classified Establishments",
    "sg:phone":"+33 5 65 99 73 16",
    "sg:province":"Midi Pyr\u00e9n\u00e9es",
    "wof:name":"Stybel S.a.",
    "wof:placetype":"venue"
},
  "geometry": {"coordinates":[2.69613,43.910339],"type":"Point"}
}