{
  "type": "Feature",
  "properties": {
    "iso:country":"FR",
    "sg:address":"B.P. 511, 92005 Nanterre C\u00e9dex^^6, Rue de Watford, 92000 Nanterre",
    "sg:orig_category":"Non-Classified Establishments",
    "sg:phone":"+33 1 47 76 42 62",
    "sg:province":"Ile de France",
    "wof:name":"Sol\u00e9tanche Bachy France S.a.",
    "wof:placetype":"venue"
},
  "geometry": {"coordinates":[2.194875,48.888084],"type":"Point"}
}