{
  "type": "Feature",
  "properties": {
    "iso:country":"FR",
    "sg:address":"Place Edmont Verollot",
    "sg:city":"St Florentin",
    "sg:classifiers":[
        {
            "category":"Banks & Credit Unions",
            "subcategory":"Financial Services",
            "type":"Services"
        }
    ],
    "sg:phone":"+33 3 86 43 75 40",
    "sg:postcode":"89600",
    "sg:province":"Bourgogne",
    "sg:tags":[
        "banking",
        "finance",
        "insurance"
    ],
    "wof:name":"Caisse Regionale De Credit Agricole Mutuel De L'yonne (ca) Credit Agricole",
    "wof:placetype":"venue"
},
  "geometry": {"coordinates":[3.72972,48.002575],"type":"Point"}
}