{
  "type": "Feature",
  "properties": {
    "addr:full":"ARC ET SENANS 25610 ARC ET SENANS Franche Comt\u00e9 25610",
    "addr:postcode":"25610;25610",
    "addr:street":"Franche Comte\u0301",
    "iso:country":"FR",
    "sg:address":"ARC ET SENANS 25610 ARC ET SENANS",
    "sg:orig_category":"Joinery Supraregional",
    "sg:phone":"+33 3 81 57 41 01",
    "sg:postcode":"25610",
    "sg:province":"Franche Comt\u00e9",
    "wof:name":"Pevescal S.a.",
    "wof:placetype":"venue"
},
  "geometry": {"coordinates":[5.77834,47.03159],"type":"Point"}
}