{
  "type": "Feature",
  "properties": {
    "iso:country":"FR",
    "sg:address":"All Des Marronniers 78202 Mante La Jolie Cedex",
    "sg:classifiers":[
        {
            "category":"Home & Garden",
            "subcategory":"Furniture",
            "type":"Retail Goods"
        }
    ],
    "sg:phone":"+33 1 34 79 40 00",
    "sg:province":"Corse",
    "sg:tags":[
        "household",
        "wood"
    ],
    "wof:name":"Dunlopillo Sa",
    "wof:placetype":"venue"
},
  "geometry": {"coordinates":[-98.46299,29.42802],"type":"Point"}
}