{
  "type": "Feature",
  "properties": {
    "addr:full":"Chemin Passant Bresles Picardie 60510",
    "addr:postcode":"60510",
    "addr:street":"Chemin Passant;Picardie",
    "iso:country":"FR",
    "sg:address":"Chemin Passant",
    "sg:city":"Bresles",
    "sg:orig_category":"Unclassifiable Establishments",
    "sg:phone":"+33 3 44 76 65 39",
    "sg:postcode":"60510",
    "sg:province":"Picardie",
    "wof:name":"Rault Patrice",
    "wof:placetype":"venue"
},
  "geometry": {"coordinates":[2.246944,49.41732],"type":"Point"}
}