{
  "type": "Feature",
  "properties": {
    "addr:full":"79 Route Lyon 69320 Feyzin Rhone-Alpes",
    "addr:housenumber":"79",
    "addr:postcode":"69320",
    "addr:street":"Route Lyon",
    "iso:country":"FR",
    "sg:address":"79 Route Lyon 69320 Feyzin",
    "sg:classifiers":[
        {
            "category":"Professional",
            "type":"Services"
        }
    ],
    "sg:phone":"+33 4 78 70 39 77",
    "sg:province":"Rhone-Alpes",
    "sg:tags":[
        "transport",
        "road"
    ],
    "wof:name":"Transport Et Garage Laurent Sa",
    "wof:placetype":"venue"
},
  "geometry": {"coordinates":[4.861337,45.687698],"type":"Point"}
}