{
  "type": "Feature",
  "properties": {
    "iso:country":"FR",
    "sg:address":"4, Rue Jean Baptiste Lacroix, 13830 Ch\u00e2teaurenard",
    "sg:orig_category":"Unclassifiable Establishments",
    "sg:phone":"+33 4 90 94 12 21",
    "sg:province":"New York",
    "wof:name":"Interface S.a.r.l.",
    "wof:placetype":"venue"
},
  "geometry": {"coordinates":[-75.638588,42.44537],"type":"Point"}
}