{
  "type": "Feature",
  "properties": {
    "iso:country":"FR",
    "sg:address":"3 Av Hoche 75008 Paris",
    "sg:classifiers":[
        {
            "category":"Autos & Motor Vehicles",
            "subcategory":"Automobile Sales",
            "type":"Retail Goods"
        }
    ],
    "sg:phone":"+33 1 42 27 07 73",
    "sg:province":"Ile de France",
    "sg:tags":[
        "equipment",
        "transport"
    ],
    "wof:name":"Promorail",
    "wof:placetype":"venue"
},
  "geometry": {"coordinates":[2.305023,48.877769],"type":"Point"}
}