{
  "type": "Feature",
  "properties": {
    "iso:country":"FR",
    "sg:address":"58, Rue de l'H\u00f4pital Militaire, 59800 Lille",
    "sg:orig_category":"Unclassifiable Establishments",
    "sg:phone":"+33 3 20 57 05 07",
    "sg:province":"Nord Pas-de-Calais",
    "wof:name":"World Trade Center S.a.",
    "wof:placetype":"venue"
},
  "geometry": {"coordinates":[3.06209,50.633369],"type":"Point"}
}