{
  "type": "Feature",
  "properties": {
    "addr:full":"Parc d'Activit\u00e9s la Prade Saint M\u00e9dard d'Eyrans Aquitaine 33650",
    "addr:postcode":"33650",
    "addr:street":"La Prade Saint",
    "iso:country":"FR",
    "sg:address":"Parc d'Activit\u00e9s la Prade",
    "sg:city":"Saint M\u00e9dard d'Eyrans",
    "sg:orig_category":"Non-Classified Establishments",
    "sg:phone":"+33 5 56 78 49 49",
    "sg:postcode":"33650",
    "sg:province":"Aquitaine",
    "wof:name":"Multi Stocks Restauration S.a.r.l.",
    "wof:placetype":"venue"
},
  "geometry": {"coordinates":[-0.694469,44.739594],"type":"Point"}
}