{
  "type": "Feature",
  "properties": {
    "addr:full":"Le Grand But Ld Du Ch\u00e2teau 59160 Lomme Nord Pas-de-Calais 59160",
    "addr:postcode":"59160;59160",
    "iso:country":"FR",
    "sg:address":"Le Grand But Ld Du Ch\u00e2teau 59160 Lomme",
    "sg:classifiers":[
        {
            "category":"Travel",
            "subcategory":"Hotels & Motels",
            "type":"Entertainment"
        }
    ],
    "sg:phone":"+33 3 20 00 75 52",
    "sg:postcode":"59160",
    "sg:province":"Nord Pas-de-Calais",
    "sg:tags":[
        "hotels",
        "business",
        "restaurant"
    ],
    "wof:name":"El Rancho France",
    "wof:placetype":"venue"
},
  "geometry": {"coordinates":[2.961047,50.643799],"type":"Point"}
}