{
  "type": "Feature",
  "properties": {
    "addr:full":"11, Place de la R\u00e9publique, 56002 Vannes C\u00e9dex Pays de Loire",
    "addr:housenumber":"11",
    "addr:postcode":"56002",
    "addr:street":"Place De La Re\u0301Publique;Ce\u0301Dex",
    "iso:country":"FR",
    "sg:address":"11, Place de la R\u00e9publique, 56002 Vannes C\u00e9dex",
    "sg:orig_category":"Non-Classified Establishments",
    "sg:phone":"+33 2 97 01 58 15",
    "sg:province":"Pays de Loire",
    "wof:name":"Caisse D'epargne Et Pr\u00e9voyance De Bretagne S.a.",
    "wof:placetype":"venue"
},
  "geometry": {"coordinates":[-2.760493,47.656391],"type":"Point"}
}