{
  "type": "Feature",
  "properties": {
    "iso:country":"FR",
    "sg:address":"2 RUE DE FRIEDLAND 13006 Marseille",
    "sg:classifiers":[
        {
            "category":"Health Services",
            "subcategory":"Dentist",
            "type":"Services"
        }
    ],
    "sg:phone":"+33 4 91 78 36 06",
    "sg:province":"Poitou-Charentes",
    "sg:tags":[
        "dental",
        "material"
    ],
    "wof:name":"Sogim Ets Grimouille Sa",
    "wof:placetype":"venue"
},
  "geometry": {"coordinates":[5.386832,43.286663],"type":"Point"}
}