{
  "type": "Feature",
  "properties": {
    "addr:full":"20, Rue de Gen\u00e8ve, 01220 Divonne les Bains Rhone-Alpes 01220",
    "addr:housenumber":"20",
    "addr:postcode":"01220;01220",
    "addr:street":"Rue De Gene\u0300Ve",
    "iso:country":"FR",
    "sg:address":"20, Rue de Gen\u00e8ve, 01220 Divonne les Bains",
    "sg:orig_category":"Unclassifiable Establishments",
    "sg:phone":"+33 4 50 20 00 80",
    "sg:postcode":"01220",
    "sg:province":"Rhone-Alpes",
    "wof:name":"C.i.c. Bra Lyonnaise De Banque S.a.",
    "wof:placetype":"venue"
},
  "geometry": {"coordinates":[6.126649,46.346825],"type":"Point"}
}