{
  "type": "Feature",
  "properties": {
    "addr:full":"50 B Che Du Vallon Des Vaux 06800 Cagnes Sur Mer Languedoc-Roussillon",
    "addr:housenumber":"50 b",
    "addr:postcode":"06800",
    "addr:street":"Du Vallon Des Vaux",
    "iso:country":"FR",
    "sg:address":"50 B Che Du Vallon Des Vaux 06800 Cagnes Sur Mer",
    "sg:classifiers":[
        {
            "category":"Manufacturing",
            "subcategory":"Building Materials",
            "type":"Manufacturing & Wholesale Goods"
        }
    ],
    "sg:phone":"+33 4 93 31 79 70",
    "sg:province":"Languedoc-Roussillon",
    "sg:tags":[
        "glass",
        "ceramic"
    ],
    "wof:name":"M. Versace Pietro",
    "wof:placetype":"venue"
},
  "geometry": {"coordinates":[7.161553,43.673054],"type":"Point"}
}