{
  "type": "Feature",
  "properties": {
    "addr:full":"Zone Industrielle Mulhouse Illzach Alsace 68110",
    "addr:postcode":"68110",
    "addr:street":"Zone Industrielle",
    "iso:country":"FR",
    "sg:address":"Zone Industrielle Mulhouse",
    "sg:city":"Illzach",
    "sg:orig_category":"Unclassifiable Establishments",
    "sg:phone":"+33 3 89 31 38 38",
    "sg:postcode":"68110",
    "sg:province":"Alsace",
    "wof:name":"Tym Transports S.a.",
    "wof:placetype":"venue"
},
  "geometry": {"coordinates":[7.348394,47.782181],"type":"Point"}
}