{
  "type": "Feature",
  "properties": {
    "iso:country":"FR",
    "sg:address":"151 Avenue Gallieni 93170 Bagnolet",
    "sg:classifiers":[
        {
            "category":"Shopping",
            "subcategory":"Computers & Home Electronics",
            "type":"Retail Goods"
        }
    ],
    "sg:phone":"+33 1 48 97 32 64",
    "sg:postcode":"93170",
    "sg:province":"Ile de France",
    "sg:tags":[
        "household",
        "appliance",
        "telecommunication",
        "audio-visual"
    ],
    "wof:name":"Aston France (aston)",
    "wof:placetype":"venue"
},
  "geometry": {"coordinates":[2.415207,48.859455],"type":"Point"}
}