{
  "type": "Feature",
  "properties": {
    "addr:full":"254, Rue Francis de Pressens\u00e9, 69100 Villeurbanne Rhone-Alpes 69100",
    "addr:housenumber":"254",
    "addr:postcode":"69100;69100",
    "addr:street":"Rue Francis De Pressense\u0301",
    "iso:country":"FR",
    "sg:address":"254, Rue Francis de Pressens\u00e9, 69100 Villeurbanne",
    "sg:orig_category":"Non-Classified Establishments",
    "sg:phone":"+33 4 78 03 06 10",
    "sg:postcode":"69100",
    "sg:province":"Rhone-Alpes",
    "wof:name":"So.rh.e.a. S.a.r.l. - Soci\u00e9t\u00e9 Rhodanienne D'electronique Appliqu\u00e9e",
    "wof:placetype":"venue"
},
  "geometry": {"coordinates":[4.892495,45.76981],"type":"Point"}
}