{
  "type": "Feature",
  "properties": {
    "addr:full":"Chemin Ormissets - ZI de Oiry Oiry Champagne 51530",
    "addr:postcode":"51530",
    "addr:street":"Chemin Ormissets Zi De Oiry;Champagne",
    "iso:country":"FR",
    "sg:address":"Chemin Ormissets - ZI de Oiry",
    "sg:city":"Oiry",
    "sg:orig_category":"Unclassifiable Establishments",
    "sg:phone":"+33 3 26 57 61 67",
    "sg:postcode":"51530",
    "sg:province":"Champagne",
    "wof:name":"Sparnacienne De Constructions S.a.r.l.",
    "wof:placetype":"venue"
},
  "geometry": {"coordinates":[3.93405,49.05574],"type":"Point"}
}