{
  "type": "Feature",
  "properties": {
    "addr:full":"46 Rue Port Boyer; Nantes Bourgogne",
    "addr:housenumber":"46",
    "addr:street":"Rue Port Boyer",
    "iso:country":"FR",
    "sg:address":"46 Rue Port Boyer; Nantes",
    "sg:classifiers":[
        {
            "category":"Banks & Credit Unions",
            "subcategory":"Bank",
            "type":"Services"
        }
    ],
    "sg:phone":"+33 3340681212",
    "sg:province":"Bourgogne",
    "wof:name":"Cr\u00e9dit Mutuel",
    "wof:placetype":"venue"
},
  "geometry": {"coordinates":[-1.534688,47.241077],"type":"Point"}
}