{
  "type": "Feature",
  "properties": {
    "addr:full":"Rue Robert Schuman le Relecq Kerhuon Bretagne 29480",
    "addr:postcode":"29480",
    "addr:street":"Rue Robert Schuman;Relecq Kerhuon Bretagne",
    "iso:country":"FR",
    "sg:address":"Rue Robert Schuman",
    "sg:city":"le Relecq Kerhuon",
    "sg:orig_category":"Non-Classified Establishments",
    "sg:phone":"+33 2 98 28 03 03",
    "sg:postcode":"29480",
    "sg:province":"Bretagne",
    "wof:name":"Entreprise Court\u00e9 S.n.c.",
    "wof:placetype":"venue"
},
  "geometry": {"coordinates":[-4.407579,48.398762],"type":"Point"}
}