{
  "type": "Feature",
  "properties": {
    "iso:country":"FR",
    "sg:address":"92 Boulevard Richard Lenoir 75011 Paris",
    "sg:classifiers":[
        {
            "category":"Shopping",
            "type":"Retail Goods"
        }
    ],
    "sg:phone":"+33 1 53 82 70 10",
    "sg:postcode":"75011",
    "sg:province":"Ile de France",
    "sg:tags":[
        "metallurgy",
        "finished",
        "-",
        "metalworking",
        "metallic"
    ],
    "wof:name":"Etablissements Vachette Sa",
    "wof:placetype":"venue"
},
  "geometry": {"coordinates":[2.372554,48.86264],"type":"Point"}
}