{
  "type": "Feature",
  "properties": {
    "addr:full":"Lieu Dit Le Moulin Baudry 85590 Mallievre Pays de Loire 85590",
    "addr:postcode":"85590;85590",
    "addr:street":"Lieu Dit Le Moulin Baudry;Mallievre",
    "iso:country":"FR",
    "sg:address":"Lieu Dit Le Moulin Baudry 85590 Mallievre",
    "sg:classifiers":[
        {
            "category":"Wholesale",
            "subcategory":"Machinery & Supplies",
            "type":"Manufacturing & Wholesale Goods"
        }
    ],
    "sg:phone":"+33 2 51 65 31 91",
    "sg:postcode":"85590",
    "sg:province":"Pays de Loire",
    "sg:tags":[
        "-",
        "machine",
        "equipment",
        "engineering",
        "animal",
        "mechanical",
        "breeding",
        "agriculture"
    ],
    "wof:name":"Etablissements J Guedon",
    "wof:placetype":"venue"
},
  "geometry": {"coordinates":[-0.867757,46.912048],"type":"Point"}
}