{
  "type": "Feature",
  "properties": {
    "iso:country":"FR",
    "sg:address":"11 Rue Livio 67100 Strasbourg",
    "sg:city":"Strasbourg",
    "sg:classifiers":[
        {
            "category":"Manufacturing",
            "subcategory":"Tools & Machinery",
            "type":"Manufacturing & Wholesale Goods"
        }
    ],
    "sg:phone":"+33 3 88 40 39 39",
    "sg:postcode":"67100",
    "sg:province":"Alsace",
    "sg:tags":[
        "metallurgy",
        "metalworking"
    ],
    "wof:name":"Ferbat Sa",
    "wof:placetype":"venue"
},
  "geometry": {"coordinates":[7.739342,48.552887],"type":"Point"}
}