{
  "type": "Feature",
  "properties": {
    "iso:country":"FR",
    "sg:address":"73264 Aigueblanche C\u00e9dex",
    "sg:city":"Aigueblanche",
    "sg:orig_category":"Non-Classified Establishments",
    "sg:phone":"+33 4 79 22 32 22",
    "sg:postcode":"73260",
    "sg:province":"Rhone-Alpes",
    "wof:name":"Ucar S.n.c.",
    "wof:placetype":"venue"
},
  "geometry": {"coordinates":[6.50879,45.501801],"type":"Point"}
}