{
  "type": "Feature",
  "properties": {
    "addr:full":"B.P. 7, 38280 Villette d'Anthon^^Rue des Saphirs, 38280 Villette d'Anthon Rhone-Alpes 38280",
    "addr:housenumber":"7",
    "addr:postcode":"38280;38280;38280",
    "addr:street":"B.P.;Villette;Rhone-Alpes",
    "iso:country":"FR",
    "sg:address":"B.P. 7, 38280 Villette d'Anthon^^Rue des Saphirs, 38280 Villette d'Anthon",
    "sg:orig_category":"Non-Classified Establishments",
    "sg:phone":"+33 4 72 02 58 58",
    "sg:postcode":"38280",
    "sg:province":"Rhone-Alpes",
    "wof:name":"A.f.t. I.f.t.i.m.",
    "wof:placetype":"venue"
},
  "geometry": {"coordinates":[5.166468,45.791191],"type":"Point"}
}