{
  "type": "Feature",
  "properties": {
    "addr:full":"41, Bd de Champy - ZI les Richardets, 93166 Noisy le Grand C\u00e9dex Limousin",
    "addr:housenumber":"41",
    "addr:postcode":"93166",
    "addr:street":"Bd De Champy Zi Les Richardets",
    "iso:country":"FR",
    "sg:address":"41, Bd de Champy - ZI les Richardets, 93166 Noisy le Grand C\u00e9dex",
    "sg:orig_category":"Non-Classified Establishments",
    "sg:phone":"+33 1 48 15 05 20",
    "sg:province":"Limousin",
    "wof:name":"Seine Et Lys D\u00e9veloppement S.a.",
    "wof:placetype":"venue"
},
  "geometry": {"coordinates":[2.553644,48.848892],"type":"Point"}
}