{
  "type": "Feature",
  "properties": {
    "addr:full":"26 Rue Escouvrier 95200 Sarcelles Ile de France 95200",
    "addr:housenumber":"26",
    "addr:postcode":"95200;ile;95200",
    "addr:street":"Rue Escouvrier;France",
    "iso:country":"FR",
    "sg:address":"26 Rue Escouvrier 95200 Sarcelles",
    "sg:classifiers":[
        {
            "category":"Professional",
            "subcategory":"Engineering",
            "type":"Services"
        }
    ],
    "sg:phone":"+33 1 34 04 20 18",
    "sg:postcode":"95200",
    "sg:province":"Ile de France",
    "sg:tags":[
        "machine",
        "-",
        "mechanical"
    ],
    "wof:name":"Seguin Sa",
    "wof:placetype":"venue"
},
  "geometry": {"coordinates":[2.389812,48.99551],"type":"Point"}
}