{
  "type": "Feature",
  "properties": {
    "iso:country":"FR",
    "sg:address":"16, Rue Henri Becquerel - ZAC des Mardelles, 93600 Aulnay sous Bois",
    "sg:orig_category":"Unclassifiable Establishments",
    "sg:phone":"+33 1 58 03 04 00",
    "sg:province":"Ile de France",
    "wof:name":"Pyroban France S.a.r.l.",
    "wof:placetype":"venue"
},
  "geometry": {"coordinates":[2.480357,48.947124],"type":"Point"}
}