{
  "type": "Feature",
  "properties": {
    "addr:full":"Rue Alain Gerbault 56000 Vannes Vannes Bretagne 56000",
    "addr:postcode":"56000;56000",
    "addr:street":"Rue Alain Gerbault",
    "iso:country":"FR",
    "sg:address":"Rue Alain Gerbault 56000 Vannes",
    "sg:city":"Vannes",
    "sg:classifiers":[
        {
            "category":"Food & Beverages",
            "subcategory":"Groceries & Convenience Stores",
            "type":"Retail Goods"
        }
    ],
    "sg:phone":"+33 2 97 47 72 80",
    "sg:postcode":"56000",
    "sg:province":"Bretagne",
    "sg:tags":[
        "product",
        "related"
    ],
    "wof:name":"Ago International Sa",
    "wof:placetype":"venue"
},
  "geometry": {"coordinates":[-2.731383,47.665348],"type":"Point"}
}