{
  "type": "Feature",
  "properties": {
    "iso:country":"FR",
    "sg:address":"4, Bd Monge, 69330 Meyzieu",
    "sg:orig_category":"Non-Classified Establishments",
    "sg:phone":"+33 4 72 02 85 82",
    "sg:postcode":"69330",
    "sg:province":"Rhone-Alpes",
    "wof:name":"Arnaud Continu S.a.",
    "wof:placetype":"venue"
},
  "geometry": {"coordinates":[5.027287,45.766338],"type":"Point"}
}