{
  "type": "Feature",
  "properties": {
    "iso:country":"FR",
    "sg:address":"311 Rue Cave Des Consuls 34480 Puissalicon",
    "sg:classifiers":[
        {
            "category":"Food Court",
            "type":"Food & Drink"
        }
    ],
    "sg:phone":"+33 4 67 36 05 37",
    "sg:postcode":"34480",
    "sg:province":"Languedoc-Roussillon",
    "sg:tags":[
        "product",
        "related"
    ],
    "wof:name":"Gaec Delhon Freres",
    "wof:placetype":"venue"
},
  "geometry": {"coordinates":[3.234915,43.458614],"type":"Point"}
}