{
  "type": "Feature",
  "properties": {
    "addr:full":"7, Rue Jacques Pr\u00e9vert, 75020 Paris Ile de France",
    "addr:housenumber":"7",
    "addr:postcode":"75020",
    "addr:street":"Rue Jacques Pre\u0301Vert",
    "iso:country":"FR",
    "sg:address":"7, Rue Jacques Pr\u00e9vert, 75020 Paris",
    "sg:orig_category":"Non-Classified Establishments",
    "sg:phone":"+33 1 43 58 66 39",
    "sg:province":"Ile de France",
    "wof:name":"Fleury Catherine",
    "wof:placetype":"venue"
},
  "geometry": {"coordinates":[2.388369,48.863949],"type":"Point"}
}