{
  "type": "Feature",
  "properties": {
    "addr:full":"45770 Saran Saran Centre 45770",
    "addr:postcode":"45770;45770",
    "iso:country":"FR",
    "sg:address":"45770 Saran",
    "sg:city":"Saran",
    "sg:orig_category":"Unclassifiable Establishments",
    "sg:phone":"+33 2 38 79 09 09",
    "sg:postcode":"45770",
    "sg:province":"Centre",
    "wof:name":"H.l.f. S.a. -hays Logistique France",
    "wof:placetype":"venue"
},
  "geometry": {"coordinates":[1.88065,47.94767],"type":"Point"}
}