{
  "type": "Feature",
  "properties": {
    "addr:full":"82 Rte De Bayonne 31300 Toulouse Midi Pyr\u00e9n\u00e9es",
    "addr:housenumber":"82",
    "addr:postcode":"31300",
    "addr:street":"Rte De Bayonne",
    "iso:country":"FR",
    "sg:address":"82 Rte De Bayonne 31300 Toulouse",
    "sg:classifiers":[
        {
            "category":"Wholesale",
            "subcategory":"Machinery & Supplies",
            "type":"Manufacturing & Wholesale Goods"
        }
    ],
    "sg:phone":"+33 5 61 31 09 57",
    "sg:province":"Midi Pyr\u00e9n\u00e9es",
    "sg:tags":[
        "equipment",
        "precision"
    ],
    "wof:name":"Mb Electronique",
    "wof:placetype":"venue"
},
  "geometry": {"coordinates":[1.38924,43.608559],"type":"Point"}
}