{
  "type": "Feature",
  "properties": {
    "addr:full":"BP 3152, Immeuble PDG Part-Dieu, 141 Rue Garibaldi, 69211 Lyon, Dept 69 Rhone-Alpes",
    "addr:housenumber":"141;69",
    "addr:postcode":"3152;69211",
    "addr:street":"Rue Garibaldi;Rhone-Alpes",
    "iso:country":"FR",
    "sg:address":"BP 3152, Immeuble PDG Part-Dieu, 141 Rue Garibaldi, 69211 Lyon, Dept 69",
    "sg:classifiers":[
        {
            "category":"Banks & Credit Unions",
            "subcategory":"Bank",
            "type":"Services"
        }
    ],
    "sg:province":"Rhone-Alpes",
    "wof:name":"Banque Populaire De Lyon",
    "wof:placetype":"venue"
},
  "geometry": {"coordinates":[4.851124,45.763454],"type":"Point"}
}