{
  "type": "Feature",
  "properties": {
    "iso:country":"FR",
    "sg:address":"13, Rue de la Louvi\u00e8re, 78513 Rambouillet",
    "sg:orig_category":"Unclassifiable Establishments",
    "sg:phone":"+33 1 30 41 14 15",
    "sg:province":"\u00cele-de-France",
    "wof:name":"Qcy Frizat S.a.",
    "wof:placetype":"venue"
},
  "geometry": {"coordinates":[1.833505,48.643257],"type":"Point"}
}