{
  "type": "Feature",
  "properties": {
    "addr:full":"52 Avenue De La Gare 10130 Ervy Le Chatel Champagne 10130",
    "addr:housenumber":"52",
    "addr:postcode":"10130;10130",
    "addr:street":"Avenue De La Gare",
    "iso:country":"FR",
    "sg:address":"52 Avenue De La Gare 10130 Ervy Le Chatel",
    "sg:classifiers":[
        {
            "category":"Manufacturing",
            "subcategory":"Chemicals & Compounds",
            "type":"Manufacturing & Wholesale Goods"
        }
    ],
    "sg:phone":"+33 3 25 46 23 10",
    "sg:postcode":"10130",
    "sg:province":"Champagne",
    "sg:tags":[
        "pharmaceutical",
        "chemistry",
        "-",
        "by-product"
    ],
    "wof:name":"Ervyglass",
    "wof:placetype":"venue"
},
  "geometry": {"coordinates":[3.924123,48.048294],"type":"Point"}
}