{
  "type": "Feature",
  "properties": {
    "addr:full":"1 rue Joseph-Marie Jacquard 82000 Montauban Midi Pyr\u00e9n\u00e9es 82000",
    "addr:housenumber":"1",
    "addr:postcode":"82000;82000",
    "addr:street":"Rue Joseph-Marie Jacquard",
    "iso:country":"FR",
    "sg:address":"1 rue Joseph-Marie Jacquard 82000 Montauban",
    "sg:classifiers":[
        {
            "category":"Professional",
            "subcategory":"Testing Lab",
            "type":"Services"
        }
    ],
    "sg:phone":"+33 5 63 66 52 80",
    "sg:postcode":"82000",
    "sg:province":"Midi Pyr\u00e9n\u00e9es",
    "sg:tags":[
        "press",
        "laboratory"
    ],
    "wof:name":"3 R S.a.",
    "wof:placetype":"venue"
},
  "geometry": {"coordinates":[1.362537,44.037884],"type":"Point"}
}