{
  "type": "Feature",
  "properties": {
    "addr:full":"Rue Albert Santos Dumont Reims Champagne 51100",
    "addr:postcode":"51100",
    "addr:street":"Rue Albert Santos Dumont;Champagne",
    "iso:country":"FR",
    "sg:address":"Rue Albert Santos Dumont",
    "sg:city":"Reims",
    "sg:orig_category":"Unclassifiable Establishments",
    "sg:phone":"+33 3 26 40 05 90",
    "sg:postcode":"51100",
    "sg:province":"Champagne",
    "wof:name":"Mobuchon S.a.",
    "wof:placetype":"venue"
},
  "geometry": {"coordinates":[4.072822,49.238567],"type":"Point"}
}