{
  "type": "Feature",
  "properties": {
    "addr:full":"ZAC Rosarge Les Echets 01700 Miribel Rhone-Alpes 01700",
    "addr:postcode":"01700;01700",
    "addr:street":"Zac Rosarge Les Echets",
    "iso:country":"FR",
    "sg:address":"ZAC Rosarge Les Echets 01700 Miribel",
    "sg:classifiers":[
        {
            "category":"Building & Trades",
            "subcategory":"Plumbing",
            "type":"Services"
        }
    ],
    "sg:phone":"+33 4 72 26 29 00",
    "sg:postcode":"01700",
    "sg:province":"Rhone-Alpes",
    "sg:tags":[
        "piping"
    ],
    "wof:name":"Cmn Sa",
    "wof:placetype":"venue"
},
  "geometry": {"coordinates":[4.953455,45.824306],"type":"Point"}
}