{
  "type": "Feature",
  "properties": {
    "addr:full":"8, Rue Helder, 75009 Paris Ile de France 75009",
    "addr:housenumber":"8",
    "addr:postcode":"75009;75009",
    "addr:street":"Rue Helder",
    "iso:country":"FR",
    "sg:address":"8, Rue Helder, 75009 Paris",
    "sg:orig_category":"Non-Classified Establishments",
    "sg:phone":"+33 1 53 24 66 66",
    "sg:postcode":"75009",
    "sg:province":"Ile de France",
    "wof:name":"Auditec S.a.",
    "wof:placetype":"venue"
},
  "geometry": {"coordinates":[2.335103,48.871719],"type":"Point"}
}