{
  "type": "Feature",
  "properties": {
    "addr:full":"27, Rue Claude Decaen, 75012 Paris Ile de France",
    "addr:housenumber":"27",
    "addr:postcode":"75012",
    "addr:street":"Rue Claude Decaen",
    "iso:country":"FR",
    "sg:address":"27, Rue Claude Decaen, 75012 Paris",
    "sg:orig_category":"Unclassifiable Establishments",
    "sg:phone":"+33 1 40 04 99 00",
    "sg:province":"Ile de France",
    "wof:name":"I.b.e. S.a. - Informatique Bureautique Electronique",
    "wof:placetype":"venue"
},
  "geometry": {"coordinates":[2.400006,48.835155],"type":"Point"}
}