{
  "type": "Feature",
  "properties": {
    "iso:country":"FR",
    "sg:address":"Rte de Brive",
    "sg:city":"Tulle",
    "sg:orig_category":"Unclassifiable Establishments",
    "sg:phone":"+33 5 55 20 09 84",
    "sg:postcode":"19000",
    "sg:province":"Limousin",
    "wof:name":"Pouquet S.a.r.l.",
    "wof:placetype":"venue"
},
  "geometry": {"coordinates":[1.758091,45.252396],"type":"Point"}
}