{
  "type": "Feature",
  "properties": {
    "addr:full":"Zac St Roman 30470 Aimargues Languedoc-Roussillon",
    "addr:postcode":"30470",
    "addr:street":"Zac St Roman",
    "iso:country":"FR",
    "sg:address":"Zac St Roman 30470 Aimargues",
    "sg:classifiers":[
        {
            "category":"Professional",
            "type":"Services"
        }
    ],
    "sg:phone":"+33 4 66 88 63 48",
    "sg:province":"Languedoc-Roussillon",
    "sg:tags":[
        "transport",
        "road"
    ],
    "wof:name":"Doumen Sa",
    "wof:placetype":"venue"
},
  "geometry": {"coordinates":[4.208545,43.686466],"type":"Point"}
}