{
  "type": "Feature",
  "properties": {
    "addr:full":"Z I De Chazeau Impasse Du Malval 42700 Firminy Rhone-Alpes 42700",
    "addr:postcode":"42700;42700",
    "addr:street":"Z I De Chazeau Impasse Du Malval",
    "iso:country":"FR",
    "sg:address":"Z I De Chazeau Impasse Du Malval 42700 Firminy",
    "sg:classifiers":[
        {
            "category":"Shopping",
            "subcategory":"Crafts & Fabrics",
            "type":"Retail Goods"
        }
    ],
    "sg:phone":"+33 4 77 56 10 30",
    "sg:postcode":"42700",
    "sg:province":"Rhone-Alpes",
    "sg:tags":[
        "coated",
        "tapes"
    ],
    "wof:name":"Ste D'expl Des Etabl Perrier Sarl",
    "wof:placetype":"venue"
},
  "geometry": {"coordinates":[4.28652,45.388603],"type":"Point"}
}