{
  "type": "Feature",
  "properties": {
    "iso:country":"FR",
    "sg:address":"79 avenue Cl\u00e9menceau 57100 Thionville",
    "sg:classifiers":[
        {
            "category":"Professional",
            "subcategory":"Business Services",
            "type":"Services"
        }
    ],
    "sg:phone":"+33 3 82 53 26 47",
    "sg:postcode":"57100",
    "sg:province":"Lorraine",
    "sg:tags":[
        "high-precision",
        "mechanic"
    ],
    "wof:name":"Coutier Charles Sarl",
    "wof:placetype":"venue"
},
  "geometry": {"coordinates":[6.161968,49.363422],"type":"Point"}
}