{
  "type": "Feature",
  "properties": {
    "addr:full":"2 Pl G\u00e9n\u00e9ral De Gaulle 93340 Le Raincy Ile de France 93340",
    "addr:housenumber":"2",
    "addr:postcode":"93340;93340",
    "addr:street":"Pl Ge\u0301Ne\u0301Ral De Gaulle",
    "iso:country":"FR",
    "sg:address":"2 Pl G\u00e9n\u00e9ral De Gaulle 93340 Le Raincy",
    "sg:classifiers":[
        {
            "category":"Banks & Credit Unions",
            "subcategory":"Financial Services",
            "type":"Services"
        }
    ],
    "sg:phone":"+33 1 41 53 00 21",
    "sg:postcode":"93340",
    "sg:province":"Ile de France",
    "sg:tags":[
        "banking",
        "insurance",
        "institution",
        "finance"
    ],
    "wof:name":"Credit Lyonnais",
    "wof:placetype":"venue"
},
  "geometry": {"coordinates":[2.511558,48.890163],"type":"Point"}
}