{
  "type": "Feature",
  "properties": {
    "iso:country":"FR",
    "sg:address":"Lavalduc 13270 Fos Sur Mer",
    "sg:classifiers":[
        {
            "category":"Autos & Motor Vehicles",
            "subcategory":"Automobile Sales",
            "type":"Retail Goods"
        }
    ],
    "sg:phone":"+33 4 42 05 35 50",
    "sg:province":"Midi Pyr\u00e9n\u00e9es",
    "sg:tags":[
        "equipment",
        "motor-cars",
        "transport"
    ],
    "wof:name":"Carrosserie De Provence Sarl",
    "wof:placetype":"venue"
},
  "geometry": {"coordinates":[4.942712,43.468861],"type":"Point"}
}