{
  "type": "Feature",
  "properties": {
    "iso:country":"FR",
    "sg:address":"B.P. 277, 08103 Charleville M\u00e9zi\u00e8res C\u00e9dex^^5, Rue Duvivier, 08100 Charleville M\u00e9zi\u00e8res",
    "sg:city":"Vill\u00e9",
    "sg:orig_category":"Non-Classified Establishments",
    "sg:phone":"+33 3 24 33 20 30",
    "sg:postcode":"67220",
    "sg:province":"Alsace",
    "wof:name":"Arden S.a.r.l.",
    "wof:placetype":"venue"
},
  "geometry": {"coordinates":[3.911801,48.001587],"type":"Point"}
}