{
  "type": "Feature",
  "properties": {
    "iso:country":"FR",
    "sg:address":"Zi Les Jalassieres Lotissement 21 Cd 10 13510 Eguilles",
    "sg:classifiers":[
        {
            "category":"Shopping",
            "subcategory":"Bicycles & Sporting Goods",
            "type":"Retail Goods"
        }
    ],
    "sg:phone":"+33 4 42 59 21 64",
    "sg:province":"Midi Pyr\u00e9n\u00e9es",
    "sg:tags":[
        "product",
        "sport",
        "miscellaneous"
    ],
    "wof:name":"Loisirs Distribution",
    "wof:placetype":"venue"
},
  "geometry": {"coordinates":[5.35468,43.568626],"type":"Point"}
}