{
  "type": "Feature",
  "properties": {
    "addr:full":"246 Rue D'Irlande Zi 84100 Orange Haute Normandie",
    "addr:housenumber":"246",
    "addr:postcode":"84100",
    "addr:street":"Rue D'Irlande Zi;Haute Normandie",
    "iso:country":"FR",
    "sg:address":"246 Rue D'Irlande Zi 84100 Orange",
    "sg:classifiers":[
        {
            "category":"Manufacturing",
            "subcategory":"Metals",
            "type":"Manufacturing & Wholesale Goods"
        }
    ],
    "sg:phone":"+33 4 90 11 01 01",
    "sg:province":"Haute Normandie",
    "sg:tags":[
        "metallurgy",
        "-",
        "metalworking",
        "metallic",
        "machine",
        "engineering",
        "finished",
        "mechanical"
    ],
    "wof:name":"Brossette Bti",
    "wof:placetype":"venue"
},
  "geometry": {"coordinates":[4.838299,44.129311],"type":"Point"}
}