{
  "type": "Feature",
  "properties": {
    "iso:country":"FR",
    "sg:address":"5 rue des Malines 91090 Lisses",
    "sg:classifiers":[
        {
            "category":"Manufacturing",
            "subcategory":"Electronics",
            "type":"Manufacturing & Wholesale Goods"
        }
    ],
    "sg:phone":"+33 1 69 11 49 00",
    "sg:province":"Ile de France",
    "sg:tags":[
        "pcb",
        "printed",
        "circuit",
        "board"
    ],
    "wof:name":"R.c.i. Sa",
    "wof:placetype":"venue"
},
  "geometry": {"coordinates":[2.419993,48.604767],"type":"Point"}
}