{
  "type": "Feature",
  "properties": {
    "addr:full":"B.P. 3 Meursault Bourgogne 21190",
    "addr:postcode":"21190",
    "addr:street":"B.P. 3;Bourgogne",
    "iso:country":"FR",
    "sg:address":"B.P. 3",
    "sg:city":"Meursault",
    "sg:orig_category":"Non-Classified Establishments",
    "sg:phone":"+33 3 80 21 22 45",
    "sg:postcode":"21190",
    "sg:province":"Bourgogne",
    "wof:name":"Maison Jean Baptiste Bejot S.a.",
    "wof:placetype":"venue"
},
  "geometry": {"coordinates":[4.775,46.976566],"type":"Point"}
}