{
  "type": "Feature",
  "properties": {
    "iso:country":"FR",
    "sg:address":"343, Rue du 8 Mai 1945, 74460 Marnaz",
    "sg:orig_category":"Non-Classified Establishments",
    "sg:phone":"+33 4 50 98 11 35",
    "sg:postcode":"74460",
    "sg:province":"Rhone-Alpes",
    "wof:name":"K.m.l. S.a.r.l. - Kiefer Moenne Loccoz",
    "wof:placetype":"venue"
},
  "geometry": {"coordinates":[6.530946,46.063339],"type":"Point"}
}