{
  "type": "Feature",
  "properties": {
    "addr:full":"41, Rue M\u00e9gisserie, 81300 Graulhet Midi Pyr\u00e9n\u00e9es",
    "addr:housenumber":"41",
    "addr:postcode":"81300",
    "addr:street":"Rue Me\u0301Gisserie",
    "iso:country":"FR",
    "sg:address":"41, Rue M\u00e9gisserie, 81300 Graulhet",
    "sg:orig_category":"Unclassifiable Establishments",
    "sg:phone":"+33 5 63 34 30 00",
    "sg:province":"Midi Pyr\u00e9n\u00e9es",
    "wof:name":"Cuir Et Guttage Graulhetois S.a.r.l.",
    "wof:placetype":"venue"
},
  "geometry": {"coordinates":[2.001871,43.761074],"type":"Point"}
}