{
  "type": "Feature",
  "properties": {
    "addr:full":"36, Rue d'Helsinky - ZI les Estroublancs, 13127 Vitrolles Provence-Alpes-C\u00f4te d'Azur",
    "addr:housenumber":"36",
    "addr:postcode":"13127",
    "addr:street":"Rue D'Helsinky Zi Les Estroublancs",
    "iso:country":"FR",
    "sg:address":"36, Rue d'Helsinky - ZI les Estroublancs, 13127 Vitrolles",
    "sg:orig_category":"Non-Classified Establishments",
    "sg:phone":"+33 4 42 77 40 30",
    "sg:province":"Provence-Alpes-C\u00f4te d'Azur",
    "wof:name":"Sern Ball Valves S.a.",
    "wof:placetype":"venue"
},
  "geometry": {"coordinates":[5.26554,43.450859],"type":"Point"}
}