{
  "type": "Feature",
  "properties": {
    "iso:country":"FR",
    "sg:address":"10, Av. de l'Entreprise - Parc Saint Christophe, 95862 Cergy C\u00e9dex",
    "sg:orig_category":"Non-Classified Establishments",
    "sg:phone":"+33 1 34 24 35 00",
    "sg:province":"Ile de France",
    "wof:name":"Spie Citra S.a.",
    "wof:placetype":"venue"
},
  "geometry": {"coordinates":[2.09101,49.035709],"type":"Point"}
}