{
  "type": "Feature",
  "properties": {
    "addr:full":"Hameau Le Cornet Rue De La For\u00eat 76340 Rieux Haute Normandie 76340",
    "addr:postcode":"76340;76340",
    "addr:street":"Hameau;Rue De La Fore\u0302T",
    "iso:country":"FR",
    "sg:address":"Hameau Le Cornet",
    "sg:city":"Rue De La For\u00eat 76340 Rieux",
    "sg:classifiers":[
        {
            "category":"Manufacturing",
            "subcategory":"Rubber & Plastics",
            "type":"Manufacturing & Wholesale Goods"
        }
    ],
    "sg:phone":"+33 2 32 97 01 30",
    "sg:postcode":"76340",
    "sg:province":"Haute Normandie",
    "sg:tags":[
        "metallurgy",
        "finished",
        "-",
        "metalworking",
        "metallic"
    ],
    "wof:name":"Euro Moules Sa",
    "wof:placetype":"venue"
},
  "geometry": {"coordinates":[1.577023,49.925938],"type":"Point"}
}