{
  "type": "Feature",
  "properties": {
    "addr:full":"Za La Levraudi\u00e8re 85120 Antigny Pays de Loire 85120",
    "addr:postcode":"85120;85120",
    "addr:street":"Za La Levraudie\u0300Re",
    "iso:country":"FR",
    "sg:address":"Za La Levraudi\u00e8re 85120 Antigny",
    "sg:classifiers":[
        {
            "category":"Shopping",
            "subcategory":"Computers & Home Electronics",
            "type":"Retail Goods"
        }
    ],
    "sg:phone":"+33 2 51 69 64 25",
    "sg:postcode":"85120",
    "sg:province":"Pays de Loire",
    "sg:tags":[
        "equipment",
        "electrical",
        "component",
        "electric",
        "electronic"
    ],
    "wof:name":"N'ergy Sa",
    "wof:placetype":"venue"
},
  "geometry": {"coordinates":[-0.770111,46.620495],"type":"Point"}
}