{
  "type": "Feature",
  "properties": {
    "addr:full":"9, L\u00f4tissement Chenerai Saint Philippe, 84210 Pernes les Fontaines Provence-Alpes-C\u00f4te d'Azur",
    "addr:housenumber":"9",
    "addr:postcode":"84210",
    "addr:street":"Lo\u0302Tissement Chenerai Saint Philippe;Les Fontaines",
    "iso:country":"FR",
    "sg:address":"9, L\u00f4tissement Chenerai Saint Philippe, 84210 Pernes les Fontaines",
    "sg:orig_category":"Non-Classified Establishments",
    "sg:phone":"+33 4 90 66 06 00",
    "sg:province":"Provence-Alpes-C\u00f4te d'Azur",
    "wof:name":"Sermat S.a.r.l.",
    "wof:placetype":"venue"
},
  "geometry": {"coordinates":[5.05512,43.99826],"type":"Point"}
}