{
  "type": "Feature",
  "properties": {
    "iso:country":"FR",
    "sg:address":"8 rue Pierre Timbaud 69637 VENISSIEUX CEDEX",
    "sg:classifiers":[
        {
            "category":"Utilities",
            "subcategory":"Natural Gas",
            "type":"Services"
        }
    ],
    "sg:phone":"+33 4 72 90 01 20",
    "sg:province":"Bretagne",
    "sg:tags":[
        "plant"
    ],
    "wof:name":"Four\u00e9-lagadec Rh\u00f4ne-alpes Sarl",
    "wof:placetype":"venue"
},
  "geometry": {"coordinates":[4.903021,45.692162],"type":"Point"}
}