{
  "type": "Feature",
  "properties": {
    "addr:full":"Rue Simone Michel-L\u00e9vy - ZA Saint Lazare Ecuelles Ile de France 77250",
    "addr:postcode":"77250",
    "addr:street":"Rue Simone Michel-Le\u0301Vy Za Saint Lazare Ecuelles Ile De France",
    "iso:country":"FR",
    "sg:address":"Rue Simone Michel-L\u00e9vy - ZA Saint Lazare",
    "sg:city":"Ecuelles",
    "sg:orig_category":"Non-Classified Establishments",
    "sg:phone":"+33 1 60 70 52 35",
    "sg:postcode":"77250",
    "sg:province":"Ile de France",
    "wof:name":"Oppenot S.a.r.l.",
    "wof:placetype":"venue"
},
  "geometry": {"coordinates":[2.814518,48.372993],"type":"Point"}
}