{
  "type": "Feature",
  "properties": {
    "iso:country":"FR",
    "sg:address":"B.P. 5",
    "sg:city":"G\u00e9nelard",
    "sg:orig_category":"Non-Classified Establishments",
    "sg:phone":"+33 3 85 79 20 90",
    "sg:postcode":"71420",
    "sg:province":"Bourgogne",
    "wof:name":"Bourgogne Service Fonderie S.a.r.l.",
    "wof:placetype":"venue"
},
  "geometry": {"coordinates":[4.156883,46.575153],"type":"Point"}
}