{
  "type": "Feature",
  "properties": {
    "addr:full":"Rue Du Moulin Des Graviers 28000 Chartres Chartres Centre 28000",
    "addr:postcode":"28000;28000",
    "addr:street":"Rue Du Moulin Des Graviers",
    "iso:country":"FR",
    "sg:address":"Rue Du Moulin Des Graviers 28000 Chartres",
    "sg:city":"Chartres",
    "sg:classifiers":[
        {
            "category":"Food & Beverages",
            "subcategory":"Groceries & Convenience Stores",
            "type":"Retail Goods"
        }
    ],
    "sg:phone":"+33 2 37 88 78 87",
    "sg:postcode":"28000",
    "sg:province":"Centre",
    "sg:tags":[
        "product",
        "grain",
        "cereal",
        "related"
    ],
    "wof:name":"Etablissements A Hebert",
    "wof:placetype":"venue"
},
  "geometry": {"coordinates":[1.489615,48.454102],"type":"Point"}
}