{
  "type": "Feature",
  "properties": {
    "iso:country":"FR",
    "sg:address":"9 place de l'Europe 78140 VELIZY VILLACOUBLAY",
    "sg:classifiers":[
        {
            "category":"Home & Garden",
            "subcategory":"Garden Supply",
            "type":"Retail Goods"
        }
    ],
    "sg:phone":"+33 1 30 67 12 31",
    "sg:postcode":"78140",
    "sg:province":"Ile de France",
    "sg:tags":[
        "decoration",
        "japanese"
    ],
    "wof:name":"Nortene Jardin S.a.",
    "wof:placetype":"venue"
},
  "geometry": {"coordinates":[2.217197,48.779724],"type":"Point"}
}