{
  "type": "Feature",
  "properties": {
    "iso:country":"FR",
    "sg:address":"3 rue des Br\u00e8ches 44400 Reze",
    "sg:classifiers":[
        {
            "category":"Health Services",
            "subcategory":"Hospital",
            "type":"Services"
        }
    ],
    "sg:phone":"+33 2 40 75 98 20",
    "sg:postcode":"44400",
    "sg:province":"Pays de Loire",
    "sg:tags":[
        "hygiene"
    ],
    "wof:name":"Jvd Sa",
    "wof:placetype":"venue"
},
  "geometry": {"coordinates":[-1.533429,47.170952],"type":"Point"}
}