{
  "type": "Feature",
  "properties": {
    "addr:full":"ZI - Le Moulin Nantais Leuvrigny Champagne 51700",
    "addr:postcode":"51700",
    "addr:street":"Zi Le;Champagne",
    "iso:country":"FR",
    "sg:address":"ZI - Le Moulin Nantais",
    "sg:city":"Leuvrigny",
    "sg:orig_category":"Non-Classified Establishments",
    "sg:phone":"+33 3 26 58 18 18",
    "sg:postcode":"51700",
    "sg:province":"Champagne",
    "wof:name":"M\u00e9camarc Malbate S.a.",
    "wof:placetype":"venue"
},
  "geometry": {"coordinates":[3.75823,49.069035],"type":"Point"}
}