{
  "type": "Feature",
  "properties": {
    "addr:full":"34, Rue Casimir P\u00e9rier - B\u00e2t. R1 - Cases 8/9 March\u00e9 Gros, 69297 Lyon C\u00e9dex 02 Rhone-Alpes",
    "addr:housenumber":"34;ba\u0302t r1;8 / 9;02",
    "addr:postcode":"69297",
    "addr:street":"Rue Casimir Pe\u0301Rier;Cases;Marche\u0301 Gros;Ce\u0301Dex",
    "iso:country":"FR",
    "sg:address":"34, Rue Casimir P\u00e9rier - B\u00e2t. R1 - Cases 8/9 March\u00e9 Gros, 69297 Lyon C\u00e9dex 02",
    "sg:orig_category":"Non-Classified Establishments",
    "sg:phone":"+33 4 78 42 21 96",
    "sg:province":"Rhone-Alpes",
    "wof:name":"Providis S.a.",
    "wof:placetype":"venue"
},
  "geometry": {"coordinates":[4.82645,45.74638],"type":"Point"}
}