{
  "type": "Feature",
  "properties": {
    "addr:full":"13, Av des Roses, 57530 Courcelles Chaussy Lorraine",
    "addr:postcode":"57530",
    "addr:street":"13 Av Des Roses",
    "iso:country":"FR",
    "sg:address":"13, Av des Roses, 57530 Courcelles Chaussy",
    "sg:orig_category":"Non-Classified Establishments",
    "sg:phone":"+33 3 87 64 04 02",
    "sg:province":"Lorraine",
    "wof:name":"Frovia S.a.",
    "wof:placetype":"venue"
},
  "geometry": {"coordinates":[6.397924,49.105339],"type":"Point"}
}