{
  "type": "Feature",
  "properties": {
    "addr:full":"Chemin de Ronde Miribel Rhone-Alpes 01700",
    "addr:postcode":"01700",
    "addr:street":"Chemin De Ronde;Rhone-Alpes",
    "iso:country":"FR",
    "sg:address":"Chemin de Ronde",
    "sg:city":"Miribel",
    "sg:orig_category":"Unclassifiable Establishments",
    "sg:phone":"+33 4 72 88 08 88",
    "sg:postcode":"01700",
    "sg:province":"Rhone-Alpes",
    "wof:name":"A.t.i.r. S.a. - Atelier T\u00f4lerie Industrielle Rh\u00f4ne Alpes",
    "wof:placetype":"venue"
},
  "geometry": {"coordinates":[4.968265,45.825577],"type":"Point"}
}