{
  "type": "Feature",
  "properties": {
    "addr:full":"3, Rue d'Helsinky - ZI les Estroublancs, 13127 Vitrolles Provence-Alpes-C\u00f4te d'Azur",
    "addr:housenumber":"3",
    "addr:postcode":"13127",
    "addr:street":"Rue D'Helsinky Zi Les Estroublancs",
    "iso:country":"FR",
    "sg:address":"3, Rue d'Helsinky - ZI les Estroublancs, 13127 Vitrolles",
    "sg:orig_category":"Unclassifiable Establishments",
    "sg:phone":"+33 4 42 75 20 63",
    "sg:province":"Provence-Alpes-C\u00f4te d'Azur",
    "wof:name":"K.s.r. S.a.r.l.",
    "wof:placetype":"venue"
},
  "geometry": {"coordinates":[5.26554,43.450859],"type":"Point"}
}