{
  "type": "Feature",
  "properties": {
    "iso:country":"FR",
    "sg:address":"2, Rue Charles Lucot, 52100 Saint Dizier",
    "sg:orig_category":"Chaudronnerie en acier inoxydable Chaudronnerie, T\u00f4lerie M\u00e9cano-soudure S\u00e9parateurs S\u00e9parateurs d'hu",
    "sg:phone":"+33 3 25 06 69 77",
    "sg:postcode":"52100",
    "sg:province":"Champagne",
    "wof:name":"Chaudronnerie De Saint Dizier S.a.r.l.",
    "wof:placetype":"venue"
},
  "geometry": {"coordinates":[4.937293,48.634964],"type":"Point"}
}