{
  "type": "Feature",
  "properties": {
    "iso:country":"FR",
    "sg:address":"15 All\u00e9e Mathieu Murgue 42100 St \u00c9tienne",
    "sg:classifiers":[
        {
            "category":"Manufacturing",
            "subcategory":"Metals",
            "type":"Manufacturing & Wholesale Goods"
        }
    ],
    "sg:phone":"+33 4 77 95 53 79",
    "sg:postcode":"42100",
    "sg:province":"Rhone-Alpes",
    "sg:tags":[
        "-",
        "machine",
        "equipment",
        "engineering",
        "machinery",
        "mechanical"
    ],
    "wof:name":"Modertech Industries Sa",
    "wof:placetype":"venue"
},
  "geometry": {"coordinates":[4.43458,45.433163],"type":"Point"}
}