{
  "type": "Feature",
  "properties": {
    "addr:full":"53200 Az\u00e9 Pays de Loire",
    "addr:postcode":"53200",
    "addr:street":"Aze\u0301",
    "iso:country":"FR",
    "sg:address":"53200 Az\u00e9",
    "sg:orig_category":"Unclassifiable Establishments",
    "sg:phone":"+33 2 43 07 13 98",
    "sg:province":"Pays de Loire",
    "wof:name":"Clavreul Andr\u00e9",
    "wof:placetype":"venue"
},
  "geometry": {"coordinates":[-0.687942,47.822563],"type":"Point"}
}