{
  "type": "Feature",
  "properties": {
    "addr:full":"9 Rue Moncey 75009 Paris Ile de France",
    "addr:housenumber":"9",
    "addr:postcode":"75009",
    "addr:street":"Rue Moncey",
    "iso:country":"FR",
    "sg:address":"9 Rue Moncey 75009 Paris",
    "sg:classifiers":[
        {
            "category":"Professional",
            "subcategory":"Printing & Photocopies",
            "type":"Services"
        }
    ],
    "sg:phone":"+33 1 40 16 17 82",
    "sg:province":"Ile de France",
    "sg:tags":[
        "publishing"
    ],
    "wof:name":"Faire Savoir Plus Sa",
    "wof:placetype":"venue"
},
  "geometry": {"coordinates":[2.330264,48.879894],"type":"Point"}
}