{
  "type": "Feature",
  "properties": {
    "iso:country":"FR",
    "sg:address":"1, Rue Maurice Hollande - ZI la Pompelle, 51100 Reims",
    "sg:orig_category":"Unclassifiable Establishments",
    "sg:phone":"+33 3 26 09 19 20",
    "sg:province":"Champagne",
    "wof:name":"Wayne Dalton Europe S.a.s.",
    "wof:placetype":"venue"
},
  "geometry": {"coordinates":[4.028445,49.26284],"type":"Point"}
}