{
  "type": "Feature",
  "properties": {
    "addr:full":"Zi Jean Mal\u00e8ze 47240 Bon Encontre Bon-Encontre Aquitaine 47240",
    "addr:postcode":"47240;47240",
    "addr:street":"Zi Jean Male\u0300Ze",
    "iso:country":"FR",
    "sg:address":"Zi Jean Mal\u00e8ze 47240 Bon Encontre",
    "sg:city":"Bon-Encontre",
    "sg:classifiers":[
        {
            "category":"Professional",
            "subcategory":"Engineering",
            "type":"Services"
        }
    ],
    "sg:phone":"+33 5 53 96 72 74",
    "sg:postcode":"47240",
    "sg:province":"Aquitaine",
    "sg:tags":[
        "machine",
        "-",
        "mechanical"
    ],
    "wof:name":"De Nadai Sa",
    "wof:placetype":"venue"
},
  "geometry": {"coordinates":[0.668345,44.186184],"type":"Point"}
}