{
  "type": "Feature",
  "properties": {
    "addr:full":"1, Place du 18 Juin 1940, 74940 Annecy le Vieux C\u00e9dex Rhone-Alpes 74940",
    "addr:housenumber":"1",
    "addr:postcode":"74940;74940",
    "addr:street":"Place Du 18 Juin 1940",
    "iso:country":"FR",
    "sg:address":"1, Place du 18 Juin 1940, 74940 Annecy le Vieux C\u00e9dex",
    "sg:orig_category":"Non-Classified Establishments",
    "sg:phone":"+33 4 50 66 40 30",
    "sg:postcode":"74940",
    "sg:province":"Rhone-Alpes",
    "wof:name":"Per'inter S.a.",
    "wof:placetype":"venue"
},
  "geometry": {"coordinates":[-94.70062299999999,34.927929],"type":"Point"}
}