{
  "type": "Feature",
  "properties": {
    "addr:full":"16, Rue Lavoisier - ZI, 52800 Nogent Champagne",
    "addr:housenumber":"16",
    "addr:postcode":"52800",
    "addr:street":"Rue Lavoisier Zi",
    "iso:country":"FR",
    "sg:address":"16, Rue Lavoisier - ZI, 52800 Nogent",
    "sg:orig_category":"Unclassifiable Establishments",
    "sg:phone":"+33 3 25 02 28 28",
    "sg:province":"Champagne",
    "wof:name":"Appa S.a.",
    "wof:placetype":"venue"
},
  "geometry": {"coordinates":[5.335895,48.024647],"type":"Point"}
}