{
  "type": "Feature",
  "properties": {
    "addr:full":"6, Rue des Ecoles, 27320 La Madeleine de Nonancourt Haute Normandie",
    "addr:housenumber":"6",
    "addr:postcode":"27320",
    "addr:street":"Rue Des Ecoles;Haute Normandie",
    "iso:country":"FR",
    "sg:address":"6, Rue des Ecoles, 27320 La Madeleine de Nonancourt",
    "sg:orig_category":"Unclassifiable Establishments",
    "sg:phone":"+33 2 32 58 15 18",
    "sg:province":"Haute Normandie",
    "wof:name":"Atelier De M\u00e9canique Roussel S.a.r.l.",
    "wof:placetype":"venue"
},
  "geometry": {"coordinates":[1.204506,48.775005],"type":"Point"}
}