{
  "type": "Feature",
  "properties": {
    "addr:full":"12, Rue Cardinal Gerlier, 69005 Lyon Rhone-Alpes",
    "addr:housenumber":"12",
    "addr:postcode":"69005",
    "addr:street":"Rue Cardinal Gerlier",
    "iso:country":"FR",
    "sg:address":"12, Rue Cardinal Gerlier, 69005 Lyon",
    "sg:orig_category":"Non-Classified Establishments",
    "sg:phone":"+33 4 78 25 10 80",
    "sg:province":"Rhone-Alpes",
    "wof:name":"Soci\u00e9t\u00e9 Vienney Louis Genevois Et Fils S.a.r.l.",
    "wof:placetype":"venue"
},
  "geometry": {"coordinates":[4.81381,45.75972],"type":"Point"}
}