{
  "type": "Feature",
  "properties": {
    "iso:country":"FR",
    "sg:address":"ZI",
    "sg:city":"Lormont",
    "sg:classifiers":[
        {
            "category":"Professional",
            "type":"Services"
        }
    ],
    "sg:phone":"+33 5 57 77 78 88",
    "sg:postcode":"33310",
    "sg:province":"Aquitaine",
    "sg:tags":[
        "transport",
        "road"
    ],
    "wof:name":"Sotril",
    "wof:placetype":"venue"
},
  "geometry": {"coordinates":[-0.522408,44.879742],"type":"Point"}
}