{
  "type": "Feature",
  "properties": {
    "iso:country":"FR",
    "sg:address":"2, Chemin de la Fonderie, 69530 Brignais",
    "sg:orig_category":"Non-Classified Establishments",
    "sg:phone":"+33 4 78 05 41 74",
    "sg:province":"Rhone-Alpes",
    "wof:name":"Drovot S.a.",
    "wof:placetype":"venue"
},
  "geometry": {"coordinates":[4.765248,45.674099],"type":"Point"}
}