{
  "type": "Feature",
  "properties": {
    "addr:full":"14 Av Fr\u00e8res Montgolfier 69680 Chassieu Rhone-Alpes",
    "addr:postcode":"69680",
    "addr:street":"14 Av Fre\u0300Res Montgolfier",
    "iso:country":"FR",
    "sg:address":"14 Av Fr\u00e8res Montgolfier 69680 Chassieu",
    "sg:classifiers":[
        {
            "category":"Professional",
            "type":"Services"
        }
    ],
    "sg:phone":"+33 4 78 90 44 88",
    "sg:province":"Rhone-Alpes",
    "sg:tags":[
        "transport",
        "road"
    ],
    "wof:name":"Transports Sauron Sa",
    "wof:placetype":"venue"
},
  "geometry": {"coordinates":[4.966861,45.726498],"type":"Point"}
}