{
  "type": "Feature",
  "properties": {
    "iso:country":"FR",
    "sg:address":"117, Rue de Noisy le Sec, 93260 Les Lilas",
    "sg:orig_category":"Unclassifiable Establishments",
    "sg:phone":"+33 1 43 60 91 66",
    "sg:province":"Ile de France",
    "wof:name":"A.t.t.r. S.a.r.l.",
    "wof:placetype":"venue"
},
  "geometry": {"coordinates":[2.417001,48.875912],"type":"Point"}
}