{
  "type": "Feature",
  "properties": {
    "addr:full":"438, Av. Paul Vaillant Couturier, 93000 Bobigny Ile de France",
    "addr:housenumber":"438",
    "addr:postcode":"93000;ile",
    "addr:street":"Av. Paul Vaillant Couturier",
    "iso:country":"FR",
    "sg:address":"438, Av. Paul Vaillant Couturier, 93000 Bobigny",
    "sg:orig_category":"Unclassifiable Establishments",
    "sg:phone":"+33 1 48 50 48 70",
    "sg:province":"Ile de France",
    "wof:name":"Les Tubes De Bobigny",
    "wof:placetype":"venue"
},
  "geometry": {"coordinates":[2.466171,48.905506],"type":"Point"}
}