{
  "type": "Feature",
  "properties": {
    "addr:full":"18, Rue des Fr\u00e8res Montgolfier, 21300 Chen\u00f4ve Chen\u00f4ve Bourgogne 21300",
    "addr:housenumber":"18",
    "addr:postcode":"21300;21300",
    "addr:street":"Rue Des Fre\u0300Res Montgolfier",
    "iso:country":"FR",
    "sg:address":"18, Rue des Fr\u00e8res Montgolfier, 21300 Chen\u00f4ve",
    "sg:city":"Chen\u00f4ve",
    "sg:orig_category":"Unclassifiable Establishments",
    "sg:phone":"+33 3 80 52 05 25",
    "sg:postcode":"21300",
    "sg:province":"Bourgogne",
    "wof:name":"Sobomat Manudir S.a.r.l.",
    "wof:placetype":"venue"
},
  "geometry": {"coordinates":[5.021723,47.296234],"type":"Point"}
}