{
  "type": "Feature",
  "properties": {
    "iso:country":"FR",
    "sg:address":"1315, Rue de la For\u00eat, 41100 Vend\u00f4me",
    "sg:city":"Vend\u00f4me",
    "sg:orig_category":"Non-Classified Establishments",
    "sg:phone":"+33 2 54 77 69 68",
    "sg:postcode":"41100",
    "sg:province":"Centre",
    "wof:name":"Les Afficheurs Du Loir S.a.r.l.",
    "wof:placetype":"venue"
},
  "geometry": {"coordinates":[1.05642,47.820431],"type":"Point"}
}