{
  "type": "Feature",
  "properties": {
    "addr:full":"210 Rue Garibaldi 69003 Lyon Rhone-Alpes",
    "addr:housenumber":"210",
    "addr:postcode":"69003",
    "addr:street":"Rue Garibaldi",
    "iso:country":"FR",
    "sg:address":"210 Rue Garibaldi 69003 Lyon",
    "sg:classifiers":[
        {
            "category":"Manufacturing",
            "subcategory":"Rubber & Plastics",
            "type":"Manufacturing & Wholesale Goods"
        }
    ],
    "sg:phone":"+33 4 72 84 60 70",
    "sg:province":"Rhone-Alpes",
    "wof:name":"Metifiot Sa Metifiot",
    "wof:placetype":"venue"
},
  "geometry": {"coordinates":[4.85241,45.75811],"type":"Point"}
}