{
  "type": "Feature",
  "properties": {
    "iso:country":"FR",
    "sg:address":"Le Vincin 56610 Arradon",
    "sg:city":"Arradon",
    "sg:classifiers":[
        {
            "category":"Professional",
            "subcategory":"Business Services",
            "type":"Services"
        }
    ],
    "sg:phone":"+33 2 97 46 33 60",
    "sg:postcode":"56610",
    "sg:province":"Bretagne",
    "sg:tags":[
        "training",
        "advice"
    ],
    "wof:name":"Universite Catholique De L'ouest Bretagne Sud",
    "wof:placetype":"venue"
},
  "geometry": {"coordinates":[-2.80415,47.649643],"type":"Point"}
}