{
  "type": "Feature",
  "properties": {
    "addr:full":"6 avenue Charles de Gaulle 78150 Le Chesnay Ile de France",
    "addr:housenumber":"6",
    "addr:postcode":"78150",
    "addr:street":"Avenue Charles De Gaulle",
    "iso:country":"FR",
    "sg:address":"6 avenue Charles de Gaulle 78150 Le Chesnay",
    "sg:orig_category":"Oils, Vegetable",
    "sg:phone":"+33 1 39 54 61 00",
    "sg:province":"Ile de France",
    "wof:name":"Sercom Sa",
    "wof:placetype":"venue"
},
  "geometry": {"coordinates":[2.115254,48.829239],"type":"Point"}
}