{
  "type": "Feature",
  "properties": {
    "addr:full":"39, Av. l'Entre Deux Mers, 33370 Fargues Saint Hilaire Artigues-pr\u00e8s-Bordeaux Aquitaine 33370",
    "addr:postcode":"33370;33370",
    "addr:street":"39 Av.;Mers",
    "iso:country":"FR",
    "sg:address":"39, Av. l'Entre Deux Mers, 33370 Fargues Saint Hilaire",
    "sg:city":"Artigues-pr\u00e8s-Bordeaux",
    "sg:orig_category":"Unclassifiable Establishments",
    "sg:phone":"+33 5 56 21 25 67",
    "sg:postcode":"33370",
    "sg:province":"Aquitaine",
    "wof:name":"Soci\u00e9t\u00e9 Nouvelle Gonzalez S.a.r.l.",
    "wof:placetype":"venue"
},
  "geometry": {"coordinates":[-0.447603,44.824455],"type":"Point"}
}