{
  "type": "Feature",
  "properties": {
    "addr:full":"3 Rue Du Parc 29520 Chateauneuf Du Faou Ch\u00e2teauneuf-du-Faou Bretagne 29520",
    "addr:housenumber":"3",
    "addr:postcode":"29520;29520",
    "addr:street":"Rue Du Parc;Faou Cha\u0302Teauneuf-Du-Faou Bretagne",
    "iso:country":"FR",
    "sg:address":"3 Rue Du Parc 29520 Chateauneuf Du Faou",
    "sg:city":"Ch\u00e2teauneuf-du-Faou",
    "sg:classifiers":[
        {
            "category":"Farming",
            "subcategory":"Livestock Farm",
            "type":"Manufacturing & Wholesale Goods"
        }
    ],
    "sg:phone":"+33 2 98 81 81 75",
    "sg:postcode":"29520",
    "sg:province":"Bretagne",
    "sg:tags":[
        "breeding",
        "agriculture",
        "animal"
    ],
    "wof:name":"Sarl Dymatel",
    "wof:placetype":"venue"
},
  "geometry": {"coordinates":[-3.816904,48.18642],"type":"Point"}
}