{
  "type": "Feature",
  "properties": {
    "addr:full":"3, Rue des Pr\u00eatres, 59660 Merville Nord Pas-de-Calais 59660",
    "addr:housenumber":"3",
    "addr:postcode":"59660;59660",
    "addr:street":"Rue Des Pre\u0302Tres",
    "iso:country":"FR",
    "sg:address":"3, Rue des Pr\u00eatres, 59660 Merville",
    "sg:orig_category":"Non-Classified Establishments",
    "sg:phone":"+33 3 28 42 00 71",
    "sg:postcode":"59660",
    "sg:province":"Nord Pas-de-Calais",
    "wof:name":"Association Id\u00e9es-tout-compo",
    "wof:placetype":"venue"
},
  "geometry": {"coordinates":[2.637439,50.642715],"type":"Point"}
}