{
  "type": "Feature",
  "properties": {
    "addr:full":"40 Av Ancien Village 59760 Grande Synthe Nord Pas-de-Calais 59760",
    "addr:postcode":"59760;59760",
    "addr:street":"40 Av Ancien Village;Pas-De-Calais",
    "iso:country":"FR",
    "sg:address":"40 Av Ancien Village 59760 Grande Synthe",
    "sg:classifiers":[
        {
            "category":"Manufacturing",
            "subcategory":"Glass & Minerals",
            "type":"Manufacturing & Wholesale Goods"
        }
    ],
    "sg:phone":"+33 3 28 21 61 45",
    "sg:postcode":"59760",
    "sg:province":"Nord Pas-de-Calais",
    "sg:tags":[
        "building",
        "material"
    ],
    "wof:name":"Vanbaelinghem Daniel",
    "wof:placetype":"venue"
},
  "geometry": {"coordinates":[2.291737,51.010685],"type":"Point"}
}