{
  "type": "Feature",
  "properties": {
    "iso:country":"FR",
    "sg:address":"Rte Ste Anne 61190 Randonnai",
    "sg:city":"Randonnai",
    "sg:classifiers":[
        {
            "category":"Home & Garden",
            "subcategory":"Furniture",
            "type":"Retail Goods"
        }
    ],
    "sg:phone":"+33 2 33 34 24 14",
    "sg:postcode":"61190",
    "sg:province":"Basse Normandie",
    "sg:tags":[
        "wood"
    ],
    "wof:name":"Combustibles Greco Sarl",
    "wof:placetype":"venue"
},
  "geometry": {"coordinates":[0.673508,48.649845],"type":"Point"}
}