{
  "type": "Feature",
  "properties": {
    "iso:country":"FR",
    "sg:address":"23, Rue Charles de Gaulle, 42000 Saint Etienne",
    "sg:orig_category":"Unclassifiable Establishments",
    "sg:phone":"+33 4 77 37 07 36",
    "sg:postcode":"42000",
    "sg:province":"Rhone-Alpes",
    "wof:name":"S.m.b. S.a.r.l. - Soci\u00e9t\u00e9 Martin-binachon",
    "wof:placetype":"venue"
},
  "geometry": {"coordinates":[4.385673,45.443909],"type":"Point"}
}