{
  "type": "Feature",
  "properties": {
    "addr:full":"13, Rue Allwies, 57200 Sarreguemines Lorraine",
    "addr:housenumber":"13",
    "addr:postcode":"57200",
    "addr:street":"Rue Allwies",
    "iso:country":"FR",
    "sg:address":"13, Rue Allwies, 57200 Sarreguemines",
    "sg:orig_category":"Unclassifiable Establishments",
    "sg:phone":"+33 3 87 95 35 14",
    "sg:province":"Lorraine",
    "wof:name":"Zollern S.a.r.l.",
    "wof:placetype":"venue"
},
  "geometry": {"coordinates":[7.08869,49.118671],"type":"Point"}
}