{
  "type": "Feature",
  "properties": {
    "addr:full":"Route De Tours Les Varennes 37400 Amboise Amboise Centre 37400",
    "addr:postcode":"37400;37400",
    "addr:street":"Route De Tours Les Varennes",
    "iso:country":"FR",
    "sg:address":"Route De Tours Les Varennes 37400 Amboise",
    "sg:city":"Amboise",
    "sg:classifiers":[
        {
            "category":"Building & Trades",
            "subcategory":"Construction",
            "type":"Services"
        }
    ],
    "sg:phone":"+33 2 47 57 02 68",
    "sg:postcode":"37400",
    "sg:province":"Centre",
    "sg:tags":[
        "work",
        "public"
    ],
    "wof:name":"Lechipre Yves",
    "wof:placetype":"venue"
},
  "geometry": {"coordinates":[0.98255,47.412853],"type":"Point"}
}