{
  "type": "Feature",
  "properties": {
    "addr:full":"Rue Rapines Le Creusot Bourgogne 71200",
    "addr:postcode":"71200",
    "addr:street":"Rue Rapines",
    "iso:country":"FR",
    "sg:address":"Rue Rapines",
    "sg:city":"Le Creusot",
    "sg:orig_category":"Unclassifiable Establishments",
    "sg:phone":"+33 3 85 77 46 46",
    "sg:postcode":"71200",
    "sg:province":"Bourgogne",
    "wof:name":"Tarlet S.a.",
    "wof:placetype":"venue"
},
  "geometry": {"coordinates":[4.44083,46.78746],"type":"Point"}
}