{
  "type": "Feature",
  "properties": {
    "addr:full":"Rue Des Canuts 42810 Rozier En Donzy Rhone-Alpes 42810",
    "addr:postcode":"42810;42810",
    "addr:street":"Rue Des Canuts;Rhone-Alpes",
    "iso:country":"FR",
    "sg:address":"Rue Des Canuts 42810 Rozier En Donzy",
    "sg:classifiers":[
        {
            "category":"Shopping",
            "subcategory":"Crafts & Fabrics",
            "type":"Retail Goods"
        }
    ],
    "sg:phone":"+33 4 77 28 04 87",
    "sg:postcode":"42810",
    "sg:province":"Rhone-Alpes",
    "sg:tags":[
        "textile",
        "clothing"
    ],
    "wof:name":"Tissages Des Roziers",
    "wof:placetype":"venue"
},
  "geometry": {"coordinates":[4.272284,45.795811],"type":"Point"}
}