{
  "type": "Feature",
  "properties": {
    "iso:country":"FR",
    "sg:address":"11 Toctoucau Zi De Toctoucau 33610 Cestas",
    "sg:city":"Cestas",
    "sg:classifiers":[
        {
            "category":"Manufacturing",
            "subcategory":"Chemicals & Compounds",
            "type":"Manufacturing & Wholesale Goods"
        }
    ],
    "sg:phone":"+33 5 56 68 05 06",
    "sg:postcode":"33610",
    "sg:province":"Aquitaine",
    "sg:tags":[
        "pharmaceutical",
        "chemistry",
        "-",
        "by-product"
    ],
    "wof:name":"Sarl Rima Persyn",
    "wof:placetype":"venue"
},
  "geometry": {"coordinates":[-0.685714,44.741707],"type":"Point"}
}