{
  "type": "Feature",
  "properties": {
    "iso:country":"FR",
    "sg:address":"Rue du Ch\u00e2teau",
    "sg:city":"Houtkerque",
    "sg:orig_category":"Non-Classified Establishments",
    "sg:phone":"+33 3 28 40 92 18",
    "sg:postcode":"59470",
    "sg:province":"Nord Pas-de-Calais",
    "wof:name":"Arcos S.a.r.l.",
    "wof:placetype":"venue"
},
  "geometry": {"coordinates":[2.592538,50.876019],"type":"Point"}
}