{
  "type": "Feature",
  "properties": {
    "addr:full":"All St Etienne De Cavall 34330 La Salvetat Sur Agout Languedoc-Roussillon",
    "addr:housenumber":"34330",
    "addr:street":"St Etienne De Cavall;Salvetat;Agout",
    "iso:country":"FR",
    "sg:address":"All St Etienne De Cavall 34330 La Salvetat Sur Agout",
    "sg:classifiers":[
        {
            "category":"Professional",
            "type":"Services"
        }
    ],
    "sg:phone":"+33 4 67 97 58 20",
    "sg:province":"Languedoc-Roussillon",
    "sg:tags":[
        "transport",
        "road"
    ],
    "wof:name":"Guibbert Andre Sarl",
    "wof:placetype":"venue"
},
  "geometry": {"coordinates":[2.702342,43.610981],"type":"Point"}
}