{
  "type": "Feature",
  "properties": {
    "iso:country":"FR",
    "sg:address":"B.P. 145, 29171 Douarnenez C\u00e9dex^^ZA de Br\u00e9huel, 29100 Douarnenez",
    "sg:city":"Douarnenez",
    "sg:orig_category":"Non-Classified Establishments",
    "sg:phone":"+33 2 98 11 02 70",
    "sg:postcode":"29100",
    "sg:province":"Bretagne",
    "wof:name":"S.e.e.e.",
    "wof:placetype":"venue"
},
  "geometry": {"coordinates":[-4.327149,48.043324],"type":"Point"}
}