{
  "type": "Feature",
  "properties": {
    "addr:full":"2 avenue Elie Baylac 95660 Champagne sur Oise Ile de France 95660",
    "addr:housenumber":"2",
    "addr:postcode":"95660;95660",
    "addr:street":"Avenue Elie Baylac",
    "iso:country":"FR",
    "sg:address":"2 avenue Elie Baylac 95660 Champagne sur Oise",
    "sg:classifiers":[
        {
            "category":"Bus Stop",
            "subcategory":"None",
            "type":"Transportation"
        }
    ],
    "sg:phone":"+33 1 34 70 03 97",
    "sg:postcode":"95660",
    "sg:province":"Ile de France",
    "sg:tags":[
        "autoclave"
    ],
    "wof:name":"T.b.m. Sarl",
    "wof:placetype":"venue"
},
  "geometry": {"coordinates":[2.253433,49.142277],"type":"Point"}
}