{
  "type": "Feature",
  "properties": {
    "iso:country":"FR",
    "sg:address":"RD 518 - Parc d'Activit\u00e9s le Regain - B\u00e2t. D",
    "sg:city":"Toussieu",
    "sg:orig_category":"Non-Classified Establishments",
    "sg:phone":"+33 4 72 48 14 50",
    "sg:postcode":"69780",
    "sg:province":"Rhone-Alpes",
    "wof:name":"Ateq S.a.r.l.",
    "wof:placetype":"venue"
},
  "geometry": {"coordinates":[4.99177,45.65134],"type":"Point"}
}