{
  "type": "Feature",
  "properties": {
    "addr:full":"7 Rue Des Fr\u00e8res Montgolfier 95500 Gonesse Ile de France 95500",
    "addr:housenumber":"7",
    "addr:postcode":"95500;ile;95500",
    "addr:street":"Rue Des Fre\u0300Res Montgolfier;France",
    "iso:country":"FR",
    "sg:address":"7 Rue Des Fr\u00e8res Montgolfier 95500 Gonesse",
    "sg:classifiers":[
        {
            "category":"Wholesale",
            "subcategory":"Machinery & Supplies",
            "type":"Manufacturing & Wholesale Goods"
        }
    ],
    "sg:phone":"+33 1 34 53 47 00",
    "sg:postcode":"95500",
    "sg:province":"Ile de France",
    "sg:tags":[
        "handling",
        "material",
        "-",
        "machine",
        "equipment",
        "engineering",
        "mechanical"
    ],
    "wof:name":"Still Sarl",
    "wof:placetype":"venue"
},
  "geometry": {"coordinates":[2.456305,48.98938],"type":"Point"}
}