{
  "type": "Feature",
  "properties": {
    "iso:country":"FR",
    "sg:address":"7, Rue Narcisse Diaz, 75016 Paris",
    "sg:orig_category":"Unclassifiable Establishments",
    "sg:phone":"+33 1 45 20 70 70",
    "sg:province":"Ile de France",
    "wof:name":"Emarketclub S.a.",
    "wof:placetype":"venue"
},
  "geometry": {"coordinates":[2.27149,48.846245],"type":"Point"}
}