{
  "type": "Feature",
  "properties": {
    "addr:full":"R De La Boucle BP 33 69720 St Laurent De Mure Rhone-Alpes 69720",
    "addr:housenumber":"bp 33",
    "addr:postcode":"69720;69720",
    "addr:street":"Rhone-Alpes",
    "iso:country":"FR",
    "sg:address":"R De La Boucle BP 33 69720 St Laurent De Mure",
    "sg:classifiers":[
        {
            "category":"Utilities",
            "subcategory":"Electric",
            "type":"Services"
        }
    ],
    "sg:phone":"+33 4 72 48 33 00",
    "sg:postcode":"69720",
    "sg:province":"Rhone-Alpes",
    "sg:tags":[
        "electricity",
        "electronic",
        "electrical",
        "equipment"
    ],
    "wof:name":"2 H Energy",
    "wof:placetype":"venue"
},
  "geometry": {"coordinates":[5.063241,45.686844],"type":"Point"}
}