{
  "type": "Feature",
  "properties": {
    "addr:full":"873 Chem Camparade 40350 Pouillon Pouillon Aquitaine 40350",
    "addr:housenumber":"873",
    "addr:postcode":"40350;40350",
    "addr:street":"Chem Camparade",
    "iso:country":"FR",
    "sg:address":"873 Chem Camparade 40350 Pouillon",
    "sg:city":"Pouillon",
    "sg:classifiers":[
        {
            "category":"Wholesale",
            "subcategory":"Meat",
            "type":"Manufacturing & Wholesale Goods"
        }
    ],
    "sg:phone":"+33 5 58 98 28 52",
    "sg:postcode":"40350",
    "sg:province":"Aquitaine",
    "sg:tags":[
        "food",
        "cooked",
        "product",
        "related"
    ],
    "wof:name":"Delices Des Landes Sa",
    "wof:placetype":"venue"
},
  "geometry": {"coordinates":[-0.986422,43.594917],"type":"Point"}
}