{
  "type": "Feature",
  "properties": {
    "iso:country":"FR",
    "sg:address":"Route Nationale 08140 DOUZY",
    "sg:classifiers":[
        {
            "category":"Manufacturing",
            "subcategory":"Metals",
            "type":"Manufacturing & Wholesale Goods"
        }
    ],
    "sg:phone":"+33 3 24 26 42 80",
    "sg:postcode":"08140",
    "sg:province":"Champagne",
    "sg:tags":[
        "alloy",
        "construction",
        "lightweight"
    ],
    "wof:name":"C.m.d. Sa",
    "wof:placetype":"venue"
},
  "geometry": {"coordinates":[5.02497,49.68927],"type":"Point"}
}