{
  "type": "Feature",
  "properties": {
    "addr:full":"ZAC La Noyeraie Sarcey Rhone-Alpes 69490",
    "addr:postcode":"69490",
    "addr:street":"Zac La Noyeraie Sarcey Rhone-Alpes",
    "iso:country":"FR",
    "sg:address":"ZAC La Noyeraie",
    "sg:city":"Sarcey",
    "sg:orig_category":"Non-Classified Establishments",
    "sg:phone":"+33 4 74 26 87 69",
    "sg:postcode":"69490",
    "sg:province":"Rhone-Alpes",
    "wof:name":"Home Style France S.a.",
    "wof:placetype":"venue"
},
  "geometry": {"coordinates":[4.559615,45.879475],"type":"Point"}
}