{
  "type": "Feature",
  "properties": {
    "addr:full":"Rue Auguste Et Louise Lumi\u00e8re 53230 Coss\u00e9 Le Vivien Pays de Loire 53230",
    "addr:postcode":"53230;53230",
    "addr:street":"Rue Auguste Et Louise Lumie\u0300Re;Vivien",
    "iso:country":"FR",
    "sg:address":"Rue Auguste Et Louise Lumi\u00e8re 53230 Coss\u00e9 Le Vivien",
    "sg:classifiers":[
        {
            "category":"Professional",
            "subcategory":"Engineering",
            "type":"Services"
        }
    ],
    "sg:phone":"+33 2 43 98 80 26",
    "sg:postcode":"53230",
    "sg:province":"Pays de Loire",
    "sg:tags":[
        "machine",
        "-",
        "mechanical"
    ],
    "wof:name":"Maurice Chevalier Sa",
    "wof:placetype":"venue"
},
  "geometry": {"coordinates":[-0.915394,47.934212],"type":"Point"}
}