{
  "type": "Feature",
  "properties": {
    "addr:full":"3, Rue du Puits Loset, 54280 Seichamps Lorraine",
    "addr:housenumber":"3",
    "addr:postcode":"54280",
    "addr:street":"Rue Du Puits Loset",
    "iso:country":"FR",
    "sg:address":"3, Rue du Puits Loset, 54280 Seichamps",
    "sg:orig_category":"Unclassifiable Establishments",
    "sg:phone":"+33 3 83 29 05 83",
    "sg:province":"Lorraine",
    "wof:name":"Schillot S.a.",
    "wof:placetype":"venue"
},
  "geometry": {"coordinates":[6.266895,48.715626],"type":"Point"}
}