{
  "type": "Feature",
  "properties": {
    "addr:full":"15 rue de Palestro 75002 Paris Ile de France 75002",
    "addr:housenumber":"15",
    "addr:postcode":"75002;75002",
    "addr:street":"Rue De Palestro",
    "iso:country":"FR",
    "sg:address":"15 rue de Palestro 75002 Paris",
    "sg:orig_category":"Ladies' Handbags",
    "sg:phone":"+33 1 45 08 11 25",
    "sg:postcode":"75002",
    "sg:province":"Ile de France",
    "wof:name":"Petite Maroquinerie Universelle Sa",
    "wof:placetype":"venue"
},
  "geometry": {"coordinates":[2.351337,48.86541],"type":"Point"}
}