{
  "type": "Feature",
  "properties": {
    "addr:full":"75 Rue Richelieu 85170 LES LUCS SUR BOULOGNE Pays de Loire 85170",
    "addr:housenumber":"75",
    "addr:postcode":"85170;85170",
    "addr:street":"Rue Richelieu;Lucs",
    "iso:country":"FR",
    "sg:address":"75 Rue Richelieu 85170 LES LUCS SUR BOULOGNE",
    "sg:classifiers":[
        {
            "category":"Wholesale",
            "subcategory":"Electrical",
            "type":"Manufacturing & Wholesale Goods"
        }
    ],
    "sg:phone":"+33 2 51 31 38 38",
    "sg:postcode":"85170",
    "sg:province":"Pays de Loire",
    "sg:tags":[
        "component",
        "data",
        "network"
    ],
    "wof:name":"Decision Europe Sa",
    "wof:placetype":"venue"
},
  "geometry": {"coordinates":[-1.494036,46.84296],"type":"Point"}
}