{
  "type": "Feature",
  "properties": {
    "addr:full":"Rte de Ravel - ZI Saint Laurent d'Agny Rhone-Alpes 69440",
    "addr:postcode":"69440",
    "addr:street":"Rte De Ravel Zi Saint Laurent D'Agny Rhone-Alpes",
    "iso:country":"FR",
    "sg:address":"Rte de Ravel - ZI",
    "sg:city":"Saint Laurent d'Agny",
    "sg:orig_category":"Unclassifiable Establishments",
    "sg:phone":"+33 4 78 48 74 72",
    "sg:postcode":"69440",
    "sg:province":"Rhone-Alpes",
    "wof:name":"C.q.f.d. S.a.s. - Comptoir Quincaillerie Fer Et D\u00e9riv\u00e9s",
    "wof:placetype":"venue"
},
  "geometry": {"coordinates":[4.70959,45.618881],"type":"Point"}
}