{
  "type": "Feature",
  "properties": {
    "iso:country":"FR",
    "sg:address":"5, Bd du Mar\u00e9chal Foch, 49000 Angers",
    "sg:orig_category":"Unclassifiable Establishments",
    "sg:phone":"+33 2 41 81 71 61",
    "sg:province":"Pays de Loire",
    "wof:name":"Caisse D'epargne Pr\u00e9voyance Pays De La Loire",
    "wof:placetype":"venue"
},
  "geometry": {"coordinates":[-0.54869,47.469463],"type":"Point"}
}