{
  "type": "Feature",
  "properties": {
    "addr:full":"Lieu Dit La Batonne Carriere Monin 69390 Millery Rhone-Alpes 69390",
    "addr:postcode":"69390;69390",
    "addr:street":"Lieu Dit La Batonne;Monin;Rhone-Alpes",
    "iso:country":"FR",
    "sg:address":"Lieu Dit La Batonne Carriere Monin 69390 Millery",
    "sg:classifiers":[
        {
            "category":"Manufacturing",
            "subcategory":"Glass & Minerals",
            "type":"Manufacturing & Wholesale Goods"
        }
    ],
    "sg:phone":"+33 4 78 73 01 27",
    "sg:postcode":"69390",
    "sg:province":"Rhone-Alpes",
    "sg:tags":[
        "building",
        "material"
    ],
    "wof:name":"Beton Chantier Rhone Auvergne",
    "wof:placetype":"venue"
},
  "geometry": {"coordinates":[4.792787,45.650181],"type":"Point"}
}