{
  "type": "Feature",
  "properties": {
    "addr:full":"167 CHEMIN DU TILLEUL 74800 Amancy Rhone-Alpes 74800",
    "addr:housenumber":"167",
    "addr:postcode":"74800;74800",
    "addr:street":"Chemin Du Tilleul",
    "iso:country":"FR",
    "sg:address":"167 CHEMIN DU TILLEUL 74800 Amancy",
    "sg:classifiers":[
        {
            "category":"Food & Beverages",
            "subcategory":"Meat & Fish",
            "type":"Retail Goods"
        }
    ],
    "sg:phone":"+33 4 50 03 03 21",
    "sg:postcode":"74800",
    "sg:province":"Rhone-Alpes",
    "sg:tags":[
        "sausage",
        "cured",
        "product",
        "dried"
    ],
    "wof:name":"Amdis Sarl",
    "wof:placetype":"venue"
},
  "geometry": {"coordinates":[6.337032,46.068188],"type":"Point"}
}