{
  "type": "Feature",
  "properties": {
    "iso:country":"FR",
    "sg:address":"Za Du Chapotin 69970 Chaponnay",
    "sg:classifiers":[
        {
            "category":"Wholesale",
            "subcategory":"Meat",
            "type":"Manufacturing & Wholesale Goods"
        }
    ],
    "sg:phone":"+33 4 72 70 06 00",
    "sg:province":"Rhone-Alpes",
    "sg:tags":[
        "food",
        "cooked",
        "product",
        "related"
    ],
    "wof:name":"Sn Roger De Lyon",
    "wof:placetype":"venue"
},
  "geometry": {"coordinates":[4.93575,45.627144],"type":"Point"}
}