{
  "type": "Feature",
  "properties": {
    "addr:full":"Rte de Tours la Giraudi\u00e8re Vierzon Centre 18100",
    "addr:postcode":"18100",
    "addr:street":"Rte De Tours La",
    "iso:country":"FR",
    "sg:address":"Rte de Tours la Giraudi\u00e8re",
    "sg:city":"Vierzon",
    "sg:orig_category":"Unclassifiable Establishments",
    "sg:phone":"+33 2 48 75 28 29",
    "sg:postcode":"18100",
    "sg:province":"Centre",
    "wof:name":"Millet Et Fils S.a.",
    "wof:placetype":"venue"
},
  "geometry": {"coordinates":[2.020555,47.206581],"type":"Point"}
}