{
  "type": "Feature",
  "properties": {
    "iso:country":"FR",
    "sg:address":"Zi Les Bombes 43700 St Germain Laprade",
    "sg:city":"Blavozy",
    "sg:classifiers":[
        {
            "category":"Professional",
            "subcategory":"Engineering",
            "type":"Services"
        }
    ],
    "sg:phone":"+33 4 71 03 00 59",
    "sg:postcode":"43700",
    "sg:province":"Auvergne",
    "sg:tags":[
        "machine",
        "-",
        "mechanical"
    ],
    "wof:name":"Fci Gourgouillat Sa",
    "wof:placetype":"venue"
},
  "geometry": {"coordinates":[3.969325,45.03875],"type":"Point"}
}