{
  "type": "Feature",
  "properties": {
    "addr:full":"18, Av. des Marronniers, 93400 Saint Ouen Ile de France",
    "addr:postcode":"93400;ile",
    "addr:street":"18 Av. Des Marronniers",
    "iso:country":"FR",
    "sg:address":"18, Av. des Marronniers, 93400 Saint Ouen",
    "sg:orig_category":"Unclassifiable Establishments",
    "sg:phone":"+33 1 40 12 94 93",
    "sg:province":"Ile de France",
    "wof:name":"Bouillot Et Fils S.a.r.l.",
    "wof:placetype":"venue"
},
  "geometry": {"coordinates":[2.33915,48.910751],"type":"Point"}
}