{
  "type": "Feature",
  "properties": {
    "iso:country":"FR",
    "sg:address":"2, Rue du Centre - Immeuble Horizon II, 93885 Noisy le Grand",
    "sg:orig_category":"Unclassifiable Establishments",
    "sg:phone":"+33 1 49 32 05 44",
    "sg:province":"Haute Normandie",
    "wof:name":"Ats Conseil S.a.r.l.",
    "wof:placetype":"venue"
},
  "geometry": {"coordinates":[2.546395,48.838226],"type":"Point"}
}