{
  "type": "Feature",
  "properties": {
    "addr:full":"60200 Compi\u00e8gne Picardie",
    "addr:postcode":"60200",
    "iso:country":"FR",
    "sg:address":"60200 Compi\u00e8gne",
    "sg:orig_category":"Unclassifiable Establishments",
    "sg:phone":"+33 3 44 90 30 91",
    "sg:province":"Picardie",
    "wof:name":"Akcros Chemicals France S.a.",
    "wof:placetype":"venue"
},
  "geometry": {"coordinates":[2.85486,49.401451],"type":"Point"}
}