{
  "type": "Feature",
  "properties": {
    "addr:full":"Rue de la Breuchilli\u00e8re - Z.A.E. Cap Nord Dijon Bourgogne 21000",
    "addr:postcode":"21000",
    "addr:street":"Rue De La Breuchillie\u0300Re Z.A.E. Cap Nord;Bourgogne",
    "iso:country":"FR",
    "sg:address":"Rue de la Breuchilli\u00e8re - Z.A.E. Cap Nord",
    "sg:city":"Dijon",
    "sg:orig_category":"Unclassifiable Establishments",
    "sg:phone":"+33 3 80 28 03 10",
    "sg:postcode":"21000",
    "sg:province":"Bourgogne",
    "wof:name":"Dijon Soudure S.a.",
    "wof:placetype":"venue"
},
  "geometry": {"coordinates":[5.075628,47.345726],"type":"Point"}
}