{
  "type": "Feature",
  "properties": {
    "iso:country":"FR",
    "sg:address":"7 Rue Commerce Fresneau 17160 Haimps",
    "sg:classifiers":[
        {
            "category":"Farming",
            "subcategory":"Livestock Farm",
            "type":"Manufacturing & Wholesale Goods"
        }
    ],
    "sg:phone":"+33 5 46 58 51 94",
    "sg:postcode":"17160",
    "sg:province":"Poitou-Charentes",
    "sg:tags":[
        "breeding",
        "agriculture",
        "animal"
    ],
    "wof:name":"Bellivier-freres Sarl",
    "wof:placetype":"venue"
},
  "geometry": {"coordinates":[-0.326821,45.802044],"type":"Point"}
}