{
  "type": "Feature",
  "properties": {
    "iso:country":"FR",
    "sg:address":"4, Rue Eug\u00e8ne Sue, 42300 Roanne",
    "sg:orig_category":"Non-Classified Establishments",
    "sg:phone":"+33 4 77 23 61 70",
    "sg:province":"Rhone-Alpes",
    "wof:name":"T.d.f. S.a. - Tricotage Durand Fouillard",
    "wof:placetype":"venue"
},
  "geometry": {"coordinates":[4.070722,46.043571],"type":"Point"}
}