{
  "type": "Feature",
  "properties": {
    "addr:full":"4 Rue Bayard Paris Ile de France 75008",
    "addr:housenumber":"4",
    "addr:postcode":"75008",
    "addr:street":"Rue Bayard",
    "iso:country":"FR",
    "sg:address":"4 Rue Bayard",
    "sg:city":"Paris",
    "sg:classifiers":[
        {
            "category":"Banks & Credit Unions",
            "subcategory":"Financial Services",
            "type":"Services"
        }
    ],
    "sg:phone":"+33 1 56 88 29 29",
    "sg:postcode":"75008",
    "sg:province":"Ile de France",
    "sg:tags":[
        "banking",
        "finance",
        "insurance"
    ],
    "wof:name":"Lebray Gie",
    "wof:placetype":"venue"
},
  "geometry": {"coordinates":[2.30802,48.865143],"type":"Point"}
}