{
  "type": "Feature",
  "properties": {
    "iso:country":"FR",
    "sg:address":"Rue Fourrier Jaquard Zi N\u00b02 La Madeleine 27000 Evreux",
    "sg:classifiers":[
        {
            "category":"Shopping",
            "subcategory":"Computers & Home Electronics",
            "type":"Retail Goods"
        }
    ],
    "sg:phone":"+33 2 32 28 32 27",
    "sg:postcode":"27000",
    "sg:province":"Haute Normandie",
    "sg:tags":[
        "electric",
        "electricity",
        "component",
        "equipment",
        "electrical",
        "electronic"
    ],
    "wof:name":"Comptoir Electro-industriel Du Maine (ceim)",
    "wof:placetype":"venue"
},
  "geometry": {"coordinates":[1.150283,49.027546],"type":"Point"}
}