{
  "type": "Feature",
  "properties": {
    "iso:country":"FR",
    "sg:address":"53 Av Franche Comte 94589 Rungis",
    "sg:city":"Anch\u00e9",
    "sg:classifiers":[
        {
            "category":"Food & Beverages",
            "subcategory":"Groceries & Convenience Stores",
            "type":"Retail Goods"
        }
    ],
    "sg:phone":"+33 1 46 86 39 01",
    "sg:postcode":"37500",
    "sg:province":"Centre",
    "sg:tags":[
        "product",
        "related"
    ],
    "wof:name":"Paris Parme Sarl",
    "wof:placetype":"venue"
},
  "geometry": {"coordinates":[2.35628,48.758823],"type":"Point"}
}