{
  "type": "Feature",
  "properties": {
    "addr:full":"B.P. 49 Courchevel Cedex^^La Croisette 73120 Courchevel Rhone-Alpes 73120",
    "addr:postcode":"73120;73120",
    "addr:street":"B.P. 49 Courchevel Cedex^^La Croisette",
    "iso:country":"FR",
    "sg:address":"B.P. 49",
    "sg:city":"Courchevel Cedex^^La Croisette 73120 Courchevel",
    "sg:orig_category":"Non-Classified Establishments",
    "sg:phone":"+33 4 79 08 10 64",
    "sg:postcode":"73120",
    "sg:province":"Rhone-Alpes",
    "wof:name":"Banque De Savoie",
    "wof:placetype":"venue"
},
  "geometry": {"coordinates":[6.637385,45.434277],"type":"Point"}
}