{
  "type": "Feature",
  "properties": {
    "addr:full":"344, Rue du Jardin Colar, 34130 Lansargues Languedoc-Roussillon 34130",
    "addr:housenumber":"344",
    "addr:postcode":"34130;34130",
    "addr:street":"Rue Du Jardin Colar",
    "iso:country":"FR",
    "sg:address":"344, Rue du Jardin Colar, 34130 Lansargues",
    "sg:orig_category":"Non-Classified Establishments",
    "sg:phone":"+33 4 66 80 03 17",
    "sg:postcode":"34130",
    "sg:province":"Languedoc-Roussillon",
    "wof:name":"Duo Industrie S.a.s.",
    "wof:placetype":"venue"
},
  "geometry": {"coordinates":[4.078588,43.64489],"type":"Point"}
}