{
  "type": "Feature",
  "properties": {
    "iso:country":"FR",
    "sg:address":"460, Av. du Prado, 13008 Marseille",
    "sg:orig_category":"Unclassifiable Establishments",
    "sg:phone":"+33 4 96 20 36 36",
    "sg:province":"Provence-Alpes-C\u00f4te d'Azur",
    "wof:name":"Franchini S.a.",
    "wof:placetype":"venue"
},
  "geometry": {"coordinates":[5.382433,43.2672],"type":"Point"}
}