{
  "type": "Feature",
  "properties": {
    "iso:country":"FR",
    "sg:address":"6, Rue Carr\u00e9, 10000 Troyes",
    "sg:orig_category":"Unclassifiable Establishments",
    "sg:phone":"+33 3 25 78 05 10",
    "sg:province":"Champagne",
    "wof:name":"Pingat Weber S.a.",
    "wof:placetype":"venue"
},
  "geometry": {"coordinates":[4.070001,48.30452],"type":"Point"}
}