{
  "type": "Feature",
  "properties": {
    "addr:full":"23 avenue des Morillons 95140 Garges les Gonesse Ile de France 95140",
    "addr:housenumber":"23",
    "addr:postcode":"95140;95140",
    "addr:street":"Avenue Des Morillons",
    "iso:country":"FR",
    "sg:address":"23 avenue des Morillons 95140 Garges les Gonesse",
    "sg:orig_category":"DRIVES TECH",
    "sg:phone":"+33 1 34 45 06 00",
    "sg:postcode":"95140",
    "sg:province":"Ile de France",
    "wof:name":"Brosses Osborn S.a.",
    "wof:placetype":"venue"
},
  "geometry": {"coordinates":[2.40153,48.96413],"type":"Point"}
}