{
  "type": "Feature",
  "properties": {
    "addr:full":"60 Rue Du Lieutenant Thomas 93170 Bagnolet Ile de France 93170",
    "addr:housenumber":"60",
    "addr:postcode":"93170;ile;93170",
    "addr:street":"Rue Du Lieutenant Thomas;France",
    "iso:country":"FR",
    "sg:address":"60 Rue Du Lieutenant Thomas 93170 Bagnolet",
    "sg:classifiers":[
        {
            "category":"Home & Garden",
            "subcategory":"Furniture",
            "type":"Retail Goods"
        }
    ],
    "sg:phone":"+33 1 42 87 35 37",
    "sg:postcode":"93170",
    "sg:province":"Ile de France",
    "sg:tags":[
        "household",
        "wood"
    ],
    "wof:name":"Manassero Sa",
    "wof:placetype":"venue"
},
  "geometry": {"coordinates":[2.416029,48.858521],"type":"Point"}
}