{
  "type": "Feature",
  "properties": {
    "addr:full":"B.P. 12 Saint Maurice de Lignon C\u00e9dex^^Chazelet 43200 Saint Maurice de Lignon Auvergne 43200",
    "addr:housenumber":"12",
    "addr:postcode":"43200;43200",
    "addr:street":"B.P.;Saint Maurice De Lignon Ce\u0301Dex^^Chazelet;Lignon",
    "iso:country":"FR",
    "sg:address":"B.P. 12",
    "sg:city":"Saint Maurice de Lignon C\u00e9dex^^Chazelet 43200 Saint Maurice de Lignon",
    "sg:orig_category":"Non-Classified Establishments",
    "sg:phone":"+33 4 71 65 71 50",
    "sg:postcode":"43200",
    "sg:province":"Auvergne",
    "wof:name":"Salaisons Du Lignon S.a.",
    "wof:placetype":"venue"
},
  "geometry": {"coordinates":[4.139093,45.22718],"type":"Point"}
}