{
  "type": "Feature",
  "properties": {
    "addr:full":"59, Rue Duquesne, 69006 Lyon Rhone-Alpes 69006",
    "addr:housenumber":"59",
    "addr:postcode":"69006;69006",
    "addr:street":"Rue Duquesne",
    "iso:country":"FR",
    "sg:address":"59, Rue Duquesne, 69006 Lyon",
    "sg:orig_category":"Unclassifiable Establishments",
    "sg:phone":"+33 4 78 93 21 75",
    "sg:postcode":"69006",
    "sg:province":"Rhone-Alpes",
    "wof:name":"Amplus S.a.r.l.",
    "wof:placetype":"venue"
},
  "geometry": {"coordinates":[4.847602,45.773033],"type":"Point"}
}