{
  "type": "Feature",
  "properties": {
    "addr:full":"175 ave Jean Jaur\u00e8s; Paris; 75019 Ile de France 75019",
    "addr:housenumber":"175",
    "addr:postcode":"75019 ile;france 75019",
    "addr:street":"Ave Jean Jaure\u0300S",
    "iso:country":"FR",
    "sg:address":"175 ave Jean Jaur\u00e8s; Paris; 75019",
    "sg:classifiers":[
        {
            "category":"Banks & Credit Unions",
            "subcategory":"Bank",
            "type":"Services"
        }
    ],
    "sg:phone":"+33 1 42 02 65 90",
    "sg:postcode":"75019",
    "sg:province":"Ile de France",
    "wof:name":"Soci\u00e9t\u00e9 G\u00e9n\u00e9rale",
    "wof:placetype":"venue"
},
  "geometry": {"coordinates":[2.388446,48.887672],"type":"Point"}
}