{
  "type": "Feature",
  "properties": {
    "addr:full":"Le Bois Pontois 41130 Meusnes Meusnes Centre 41130",
    "addr:postcode":"41130;41130",
    "addr:street":"Meusnes",
    "iso:country":"FR",
    "sg:address":"Le Bois Pontois 41130 Meusnes",
    "sg:city":"Meusnes",
    "sg:orig_category":"Unclassifiable Establishments",
    "sg:phone":"+33 2 54 71 00 34",
    "sg:postcode":"41130",
    "sg:province":"Centre",
    "wof:name":"Domaines Jacky Preys G.a.e.c.",
    "wof:placetype":"venue"
},
  "geometry": {"coordinates":[1.4975,47.241322],"type":"Point"}
}