{
  "type": "Feature",
  "properties": {
    "addr:full":"2, Rue de l'Industrie, 25410 Saint Vit Franche Comt\u00e9",
    "addr:housenumber":"2",
    "addr:postcode":"25410",
    "addr:street":"Rue De L'Industrie;Franche Comte\u0301",
    "iso:country":"FR",
    "sg:address":"2, Rue de l'Industrie, 25410 Saint Vit",
    "sg:orig_category":"Unclassifiable Establishments",
    "sg:phone":"+33 3 81 87 58 87",
    "sg:province":"Franche Comt\u00e9",
    "wof:name":"Malfroy Etuis Et P.l.v. S.a.r.l.",
    "wof:placetype":"venue"
},
  "geometry": {"coordinates":[5.809787,47.184196],"type":"Point"}
}