{
  "type": "Feature",
  "properties": {
    "addr:full":"34-6, Rue de Luyot - Z.I. B, 59113 Seclin Nord Pas-de-Calais",
    "addr:housenumber":"34-6;b",
    "addr:postcode":"59113",
    "addr:street":"Rue De Luyot Z.I.",
    "iso:country":"FR",
    "sg:address":"34-6, Rue de Luyot - Z.I. B, 59113 Seclin",
    "sg:orig_category":"Non-Classified Establishments",
    "sg:phone":"+33 3 20 32 70 45",
    "sg:province":"Nord Pas-de-Calais",
    "wof:name":"Somatec E.u.r.l.",
    "wof:placetype":"venue"
},
  "geometry": {"coordinates":[3.026865,50.54681],"type":"Point"}
}