{
  "type": "Feature",
  "properties": {
    "addr:full":"Av. Guillaume Arnaud de Tontoulon - Z.I. Bazas Aquitaine 33430",
    "addr:postcode":"33430",
    "addr:street":"Av. Guillaume Arnaud De Tontoulon Z.I.",
    "iso:country":"FR",
    "sg:address":"Av. Guillaume Arnaud de Tontoulon - Z.I.",
    "sg:city":"Bazas",
    "sg:orig_category":"Non-Classified Establishments",
    "sg:phone":"+33 5 56 25 13 86",
    "sg:postcode":"33430",
    "sg:province":"Aquitaine",
    "wof:name":"Testoutil S.a.",
    "wof:placetype":"venue"
},
  "geometry": {"coordinates":[-0.230217,44.438423],"type":"Point"}
}