{
  "type": "Feature",
  "properties": {
    "addr:full":"27 Bd St Michel 75005 Paris Ile de France 75005",
    "addr:housenumber":"27",
    "addr:postcode":"75005;75005",
    "addr:street":"Bd St Michel",
    "iso:country":"FR",
    "sg:address":"27 Bd St Michel 75005 Paris",
    "sg:classifiers":[
        {
            "category":"Banks & Credit Unions",
            "subcategory":"Financial Services",
            "type":"Services"
        }
    ],
    "sg:phone":"+33 1 40 51 96 50",
    "sg:postcode":"75005",
    "sg:province":"Ile de France",
    "sg:tags":[
        "banking",
        "insurance",
        "institution",
        "finance"
    ],
    "wof:name":"Societe Generale",
    "wof:placetype":"venue"
},
  "geometry": {"coordinates":[2.342751,48.850159],"type":"Point"}
}