{
  "type": "Feature",
  "properties": {
    "iso:country":"FR",
    "sg:address":"5, Av. de la Gare, 11300 Limoux",
    "sg:orig_category":"Non-Classified Establishments",
    "sg:phone":"+33 4 68 31 83 72",
    "sg:province":"Languedoc-Roussillon",
    "wof:name":"Gaea Environnement",
    "wof:placetype":"venue"
},
  "geometry": {"coordinates":[2.22034,43.054501],"type":"Point"}
}