{
  "type": "Feature",
  "properties": {
    "addr:full":"22, Rue du Banquier, 75013 Paris Ile de France",
    "addr:housenumber":"22",
    "addr:postcode":"75013",
    "addr:street":"Rue Du Banquier",
    "iso:country":"FR",
    "sg:address":"22, Rue du Banquier, 75013 Paris",
    "sg:orig_category":"Unclassifiable Establishments",
    "sg:phone":"+33 1 55 43 18 18",
    "sg:province":"Ile de France",
    "wof:name":"Carco S.a.",
    "wof:placetype":"venue"
},
  "geometry": {"coordinates":[2.355614,48.835453],"type":"Point"}
}