{
  "type": "Feature",
  "properties": {
    "iso:country":"FR",
    "sg:address":"Les Vignes De Douces 37370 Villebourg",
    "sg:city":"Villebourg",
    "sg:classifiers":[
        {
            "category":"Farming",
            "subcategory":"Crops",
            "type":"Manufacturing & Wholesale Goods"
        }
    ],
    "sg:phone":"+33 2 47 24 82 11",
    "sg:postcode":"37370",
    "sg:province":"Centre",
    "sg:tags":[
        "vegetable",
        "fruit",
        "agriculture",
        "livestock"
    ],
    "wof:name":"Plaine Des Coeurs",
    "wof:placetype":"venue"
},
  "geometry": {"coordinates":[0.529345,47.649727],"type":"Point"}
}