{
  "type": "Feature",
  "properties": {
    "iso:country":"FR",
    "sg:address":"100 Avenue Nationale La Neuvillette BP 456 La Neuvillette 51066 Reims Cedex",
    "sg:classifiers":[
        {
            "category":"Utilities",
            "subcategory":"Telephone",
            "type":"Services"
        }
    ],
    "sg:phone":"+33 3 26 47 28 53",
    "sg:province":"Champagne-Ardenne",
    "sg:tags":[
        "telecommunication"
    ],
    "wof:name":"Ste Remoise De Luminescence Sarl",
    "wof:placetype":"venue"
},
  "geometry": {"coordinates":[4.03384,49.25415],"type":"Point"}
}