{
  "type": "Feature",
  "properties": {
    "addr:full":"213, Rue de Gerland, 69367 Lyon C\u00e9dex 07 Basse Normandie",
    "addr:housenumber":"213;07",
    "addr:postcode":"69367",
    "addr:street":"Rue De Gerland;Ce\u0301Dex",
    "iso:country":"FR",
    "sg:address":"213, Rue de Gerland, 69367 Lyon C\u00e9dex 07",
    "sg:orig_category":"Non-Classified Establishments",
    "sg:phone":"+33 4 72 72 37 60",
    "sg:province":"Basse Normandie",
    "wof:name":"Elyo Centre Est S.a.",
    "wof:placetype":"venue"
},
  "geometry": {"coordinates":[4.838019,45.72702],"type":"Point"}
}