{
  "type": "Feature",
  "properties": {
    "addr:full":"10 Rue Bayon 94100 St Maur Des Foss\u00e9s Ile de France 94100",
    "addr:housenumber":"10",
    "addr:postcode":"94100;94100",
    "addr:street":"Rue Bayon;Des Fosse\u0301S Ile De France",
    "iso:country":"FR",
    "sg:address":"10 Rue Bayon 94100 St Maur Des Foss\u00e9s",
    "sg:classifiers":[
        {
            "category":"Professional",
            "subcategory":"Engineering",
            "type":"Services"
        }
    ],
    "sg:phone":"+33 1 48 85 12 43",
    "sg:postcode":"94100",
    "sg:province":"Ile de France",
    "sg:tags":[
        "machine",
        "-",
        "mechanical"
    ],
    "wof:name":"Ratti (ets Patrice) Sarl",
    "wof:placetype":"venue"
},
  "geometry": {"coordinates":[2.489099,48.785095],"type":"Point"}
}