{
  "type": "Feature",
  "properties": {
    "addr:full":"34 Bd Louis Dupuy 01100 Oyonnax Rhone-Alpes 01100",
    "addr:housenumber":"34",
    "addr:postcode":"01100;01100",
    "addr:street":"Bd Louis Dupuy",
    "iso:country":"FR",
    "sg:address":"34 Bd Louis Dupuy 01100 Oyonnax",
    "sg:classifiers":[
        {
            "category":"Wholesale",
            "subcategory":"Medical Equipment & Supplies",
            "type":"Manufacturing & Wholesale Goods"
        }
    ],
    "sg:phone":"+33 4 74 77 17 56",
    "sg:postcode":"01100",
    "sg:province":"Rhone-Alpes",
    "sg:tags":[
        "instrument",
        "health",
        "-",
        "precision"
    ],
    "wof:name":"M. Martinez Christian",
    "wof:placetype":"venue"
},
  "geometry": {"coordinates":[5.649462,46.256905],"type":"Point"}
}