{
  "type": "Feature",
  "properties": {
    "addr:full":"9, Rue du Chemin de Fer, 68510 Sierentz Sierentz Alsace 68510",
    "addr:housenumber":"9",
    "addr:postcode":"68510;68510",
    "addr:street":"Rue Du Chemin De Fer",
    "iso:country":"FR",
    "sg:address":"9, Rue du Chemin de Fer, 68510 Sierentz",
    "sg:city":"Sierentz",
    "sg:orig_category":"Unclassifiable Establishments",
    "sg:phone":"+33 3 89 81 51 52",
    "sg:postcode":"68510",
    "sg:province":"Alsace",
    "wof:name":"Ad\u00e9co E.r.i. S.a. - Etudes Et R\u00e9alisations Industrielles",
    "wof:placetype":"venue"
},
  "geometry": {"coordinates":[7.457485,47.657108],"type":"Point"}
}