{
  "type": "Feature",
  "properties": {
    "iso:country":"FR",
    "sg:address":"17 Parc d'Arboras 69510 Soucieu en Jarret",
    "sg:classifiers":[
        {
            "category":"Health Services",
            "subcategory":"Medical Lab",
            "type":"Services"
        }
    ],
    "sg:phone":"+33 4 78 05 69 69",
    "sg:province":"Rhone-Alpes",
    "sg:tags":[
        "upholstery"
    ],
    "wof:name":"Atys Medical S.a.r.l.",
    "wof:placetype":"venue"
},
  "geometry": {"coordinates":[-83.238533,34.603992],"type":"Point"}
}