{
  "type": "Feature",
  "properties": {
    "iso:country":"FR",
    "sg:address":"R\u00e9sidence les Pins",
    "sg:city":"Tollevast",
    "sg:orig_category":"Unclassifiable Establishments",
    "sg:phone":"+33 2 33 44 46 70",
    "sg:postcode":"50470",
    "sg:province":"Basse Normandie",
    "wof:name":"Image Diffusion S.a.r.l.",
    "wof:placetype":"venue"
},
  "geometry": {"coordinates":[-1.603544,49.614346],"type":"Point"}
}