{
  "type": "Feature",
  "properties": {
    "addr:full":"52ter, Rue Jacob, 02140 Vervins Picardie",
    "addr:housenumber":"52ter",
    "addr:postcode":"02140",
    "addr:street":"Rue Jacob",
    "iso:country":"FR",
    "sg:address":"52ter, Rue Jacob, 02140 Vervins",
    "sg:orig_category":"Unclassifiable Establishments",
    "sg:phone":"+33 3 23 98 12 25",
    "sg:province":"Picardie",
    "wof:name":"Franco Argentine S.a.",
    "wof:placetype":"venue"
},
  "geometry": {"coordinates":[3.90564,49.832401],"type":"Point"}
}