{
  "type": "Feature",
  "properties": {
    "addr:full":"6 Rte Puy De Dome Font Arbre 63870 Orcines Orcines Auvergne 63870",
    "addr:housenumber":"6",
    "addr:postcode":"63870;63870",
    "addr:street":"Rte Puy De Dome Font Arbre",
    "iso:country":"FR",
    "sg:address":"6 Rte Puy De Dome Font Arbre 63870 Orcines",
    "sg:city":"Orcines",
    "sg:classifiers":[
        {
            "category":"Home & Garden",
            "subcategory":"Furniture",
            "type":"Retail Goods"
        }
    ],
    "sg:phone":"+33 4 73 62 14 50",
    "sg:postcode":"63870",
    "sg:province":"Auvergne",
    "sg:tags":[
        "wood"
    ],
    "wof:name":"Ets Esbelin Raymond Et Fils",
    "wof:placetype":"venue"
},
  "geometry": {"coordinates":[3.016467,45.786083],"type":"Point"}
}