{
  "type": "Feature",
  "properties": {
    "iso:country":"FR",
    "sg:address":"25 rue Casimir P\u00e9rier 95870 Bezons",
    "sg:classifiers":[
        {
            "category":"Structure",
            "subcategory":"Office Building",
            "type":"Public Place"
        }
    ],
    "sg:phone":"+33 1 39 61 52 62",
    "sg:province":"Ile de France",
    "sg:tags":[
        "plug",
        "power"
    ],
    "wof:name":"Ascome S.a.r.l.",
    "wof:placetype":"venue"
},
  "geometry": {"coordinates":[2.212239,48.9217],"type":"Point"}
}