{
  "type": "Feature",
  "properties": {
    "iso:country":"FR",
    "sg:address":"Ch\u00e2teau Baragne",
    "sg:city":"Cambes",
    "sg:orig_category":"Non-Classified Establishments",
    "sg:phone":"+33 5 56 21 34 16",
    "sg:postcode":"33880",
    "sg:province":"Aquitaine",
    "wof:name":"Rullaud Philippe",
    "wof:placetype":"venue"
},
  "geometry": {"coordinates":[-0.440229,44.725407],"type":"Point"}
}