{
  "type": "Feature",
  "properties": {
    "iso:country":"FR",
    "sg:address":"5 Faubourg De Montbeliard",
    "sg:city":"Belfort",
    "sg:classifiers":[
        {
            "category":"Banks & Credit Unions",
            "subcategory":"Financial Services",
            "type":"Services"
        }
    ],
    "sg:phone":"+33 3 84 21 98 20",
    "sg:postcode":"90000",
    "sg:province":"Franche Comt\u00e9",
    "sg:tags":[
        "banking",
        "finance",
        "insurance"
    ],
    "wof:name":"Credit Agricole Mutuel De France Comte",
    "wof:placetype":"venue"
},
  "geometry": {"coordinates":[6.857726,47.63702],"type":"Point"}
}