{
  "type": "Feature",
  "properties": {
    "iso:country":"FR",
    "sg:address":"21 Rue Du Parc 68700 Cernay",
    "sg:city":"Cernay",
    "sg:classifiers":[
        {
            "category":"Shopping",
            "type":"Retail Goods"
        }
    ],
    "sg:phone":"+33 3 89 75 77 83",
    "sg:postcode":"68700",
    "sg:province":"Alsace",
    "sg:tags":[
        "metallurgy",
        "finished",
        "-",
        "metalworking",
        "metallic"
    ],
    "wof:name":"Sas Fernand Schlienger Et Fils",
    "wof:placetype":"venue"
},
  "geometry": {"coordinates":[7.175107,47.802814],"type":"Point"}
}