{
  "type": "Feature",
  "properties": {
    "iso:country":"FR",
    "sg:address":"17, Rue Champs Martin, 35770 Vern sur Seiche",
    "sg:city":"Vern-sur-Seiche",
    "sg:orig_category":"Unclassifiable Establishments",
    "sg:phone":"+33 2 99 28 02 70",
    "sg:postcode":"35770",
    "sg:province":"Bretagne",
    "wof:name":"Groupe Bretagne Atelier",
    "wof:placetype":"venue"
},
  "geometry": {"coordinates":[-1.610462,48.055382],"type":"Point"}
}