{
  "type": "Feature",
  "properties": {
    "iso:country":"FR",
    "sg:address":"64, Av. Pierre Grenier, 92100 Boulogne Billancourt",
    "sg:orig_category":"Unclassifiable Establishments",
    "sg:phone":"+33 1 46 10 44 55",
    "sg:province":"Ile de France",
    "wof:name":"A.e.e.s. S.a. - Automatisme Energie Electronique Syst\u00e8mes",
    "wof:placetype":"venue"
},
  "geometry": {"coordinates":[2.254348,48.833569],"type":"Point"}
}