{
  "type": "Feature",
  "properties": {
    "addr:full":"ROUTE DE Pau 64260 SEVIGNACQ MEYRACQ Arudy Aquitaine 64260",
    "addr:postcode":"64260;64260",
    "addr:street":"Route De Pau",
    "iso:country":"FR",
    "sg:address":"ROUTE DE Pau 64260 SEVIGNACQ MEYRACQ",
    "sg:city":"Arudy",
    "sg:classifiers":[
        {
            "category":"Utilities",
            "subcategory":"Natural Gas",
            "type":"Services"
        }
    ],
    "sg:phone":"+33 5 59 05 60 61",
    "sg:postcode":"64260",
    "sg:province":"Aquitaine",
    "sg:tags":[
        "cast",
        "stone",
        "working"
    ],
    "wof:name":"Lardit Sa",
    "wof:placetype":"venue"
},
  "geometry": {"coordinates":[-0.412953,43.024239],"type":"Point"}
}