{
  "type": "Feature",
  "properties": {
    "iso:country":"FR",
    "sg:address":"2 Rue Alphonse Daudet 59240 Dunkerque",
    "sg:classifiers":[
        {
            "category":"Home & Garden",
            "subcategory":"Furniture",
            "type":"Retail Goods"
        }
    ],
    "sg:phone":"+33 3 28 63 48 20",
    "sg:province":"Midi Pyr\u00e9n\u00e9es",
    "sg:tags":[
        "household",
        "wood"
    ],
    "wof:name":"Societe Amenagement Cuisines Et Bains (saceb)",
    "wof:placetype":"venue"
},
  "geometry": {"coordinates":[2.38758,51.033802],"type":"Point"}
}