{
  "type": "Feature",
  "properties": {
    "iso:country":"FR",
    "sg:address":"22 Boulevard Voltaire",
    "sg:city":"Decize",
    "sg:classifiers":[
        {
            "category":"Banks & Credit Unions",
            "subcategory":"Financial Services",
            "type":"Services"
        }
    ],
    "sg:phone":"+33 3 86 25 24 77",
    "sg:postcode":"58300",
    "sg:province":"Bourgogne",
    "sg:tags":[
        "banking",
        "finance",
        "insurance"
    ],
    "wof:name":"Societe Fiduciaire Nationale D'expertise Comptable Fidexpert (fid)",
    "wof:placetype":"venue"
},
  "geometry": {"coordinates":[3.461023,46.830215],"type":"Point"}
}