{
  "type": "Feature",
  "properties": {
    "addr:full":"47 Rue Clisson 75013 Paris Ile de France 75013",
    "addr:housenumber":"47",
    "addr:postcode":"75013;75013",
    "addr:street":"Rue Clisson",
    "iso:country":"FR",
    "sg:address":"47 Rue Clisson 75013 Paris",
    "sg:classifiers":[
        {
            "category":"Shopping",
            "subcategory":"Computers & Home Electronics",
            "type":"Retail Goods"
        }
    ],
    "sg:phone":"+33 1 45 82 46 09",
    "sg:postcode":"75013",
    "sg:province":"Ile de France",
    "sg:tags":[
        "equipment",
        "electrical",
        "component",
        "electric",
        "electronic"
    ],
    "wof:name":"Service Et Developpement Scientifique Sarl",
    "wof:placetype":"venue"
},
  "geometry": {"coordinates":[2.366767,48.831413],"type":"Point"}
}