{
  "type": "Feature",
  "properties": {
    "iso:country":"FR",
    "sg:address":"Rue Fran\u00e7ois Jacob - Zone Industrielle de l'Alouette",
    "sg:city":"Li\u00e9vin",
    "sg:orig_category":"Non-Classified Establishments",
    "sg:phone":"+33 3 21 45 41 41",
    "sg:postcode":"62800",
    "sg:province":"Nord Pas-de-Calais",
    "wof:name":"Verbeke S.a.r.l.",
    "wof:placetype":"venue"
},
  "geometry": {"coordinates":[2.758609,50.429382],"type":"Point"}
}