{
  "type": "Feature",
  "properties": {
    "addr:full":"Rue Fran\u00e7ois Jacob - Zone Industrielle de l'Alouette Li\u00e9vin Nord Pas-de-Calais 62800",
    "addr:postcode":"62800",
    "addr:street":"Rue Franc\u0327Ois Jacob Zone Industrielle De L'Alouette Lie\u0301Vin Nord",
    "iso:country":"FR",
    "sg:address":"Rue Fran\u00e7ois Jacob - Zone Industrielle de l'Alouette",
    "sg:city":"Li\u00e9vin",
    "sg:orig_category":"Non-Classified Establishments",
    "sg:phone":"+33 3 21 45 41 41",
    "sg:postcode":"62800",
    "sg:province":"Nord Pas-de-Calais",
    "wof:name":"Verbeke S.a.r.l.",
    "wof:placetype":"venue"
},
  "geometry": {"coordinates":[2.758609,50.429382],"type":"Point"}
}