{
  "type": "Feature",
  "properties": {
    "addr:full":"B.P. 311, 37303 Jou\u00e9 l\u00e8s Tours C\u00e9dex^^Rue de Prony - ZI n\u00b0 2, 37300 Jou\u00e9 l\u00e8s Tours Jou\u00e9-l\u00e8s-Tours Centre 37300",
    "addr:housenumber":"b.p. 311",
    "addr:postcode":"37303;37300;37300",
    "addr:street":"Prony",
    "iso:country":"FR",
    "sg:address":"B.P. 311, 37303 Jou\u00e9 l\u00e8s Tours C\u00e9dex^^Rue de Prony - ZI n\u00b0 2, 37300 Jou\u00e9 l\u00e8s Tours",
    "sg:city":"Jou\u00e9-l\u00e8s-Tours",
    "sg:orig_category":"Non-Classified Establishments",
    "sg:phone":"+33 2 47 73 63 60",
    "sg:postcode":"37300",
    "sg:province":"Centre",
    "wof:name":"Sanitra Fourrier",
    "wof:placetype":"venue"
},
  "geometry": {"coordinates":[0.65424,47.337601],"type":"Point"}
}