{
  "type": "Feature",
  "properties": {
    "iso:country":"FR",
    "sg:address":"La For\u00eat 71110 Ligny en Brionnais",
    "sg:city":"Anzy-le-Duc",
    "sg:orig_category":"Non-Classified Establishments",
    "sg:phone":"+33 3 85 25 85 66",
    "sg:postcode":"71110",
    "sg:province":"Bourgogne",
    "wof:name":"Duvernay E.u.r.l.",
    "wof:placetype":"venue"
},
  "geometry": {"coordinates":[4.200394,46.230972],"type":"Point"}
}