{
  "type": "Feature",
  "properties": {
    "addr:full":"12 bis, Rue Rey Loras, 69250 Neuville sur Sa\u00f4ne Rhone-Alpes 69250",
    "addr:housenumber":"12 bis",
    "addr:postcode":"69250;69250",
    "addr:street":"Rue Rey Loras",
    "iso:country":"FR",
    "sg:address":"12 bis, Rue Rey Loras, 69250 Neuville sur Sa\u00f4ne",
    "sg:orig_category":"Non-Classified Establishments",
    "sg:phone":"+33 4 78 98 13 00",
    "sg:postcode":"69250",
    "sg:province":"Rhone-Alpes",
    "wof:name":"Technidis S.a.",
    "wof:placetype":"venue"
},
  "geometry": {"coordinates":[4.837745,45.880733],"type":"Point"}
}