{
  "type": "Feature",
  "properties": {
    "addr:full":"67 R Alexandre Luigini 69530 Orlienas Rhone-Alpes",
    "addr:housenumber":"67",
    "addr:postcode":"69530",
    "addr:street":"R Alexandre Luigini",
    "iso:country":"FR",
    "sg:address":"67 R Alexandre Luigini 69530 Orlienas",
    "sg:classifiers":[
        {
            "category":"Home & Garden",
            "subcategory":"Furniture",
            "type":"Retail Goods"
        }
    ],
    "sg:phone":"+33 4 72 31 13 39",
    "sg:province":"Rhone-Alpes",
    "sg:tags":[
        "household",
        "wood"
    ],
    "wof:name":"M. Raymond Pierre",
    "wof:placetype":"venue"
},
  "geometry": {"coordinates":[4.718448,45.657417],"type":"Point"}
}