{
  "type": "Feature",
  "properties": {
    "addr:full":"4-8 rue Sainte Anne; Paris; 75001 Ile de France 75001",
    "addr:housenumber":"4-8",
    "addr:postcode":"75001 ile;france 75001",
    "addr:street":"Rue Sainte Anne",
    "iso:country":"FR",
    "sg:address":"4-8 rue Sainte Anne; Paris; 75001",
    "sg:classifiers":[
        {
            "category":"Banks & Credit Unions",
            "subcategory":"Bank",
            "type":"Services"
        }
    ],
    "sg:phone":"+33 1 40 20 02 41",
    "sg:postcode":"75001",
    "sg:province":"Ile de France",
    "wof:name":"Bank Of Tokyo, Mitsubishi (france) Sa",
    "wof:placetype":"venue"
},
  "geometry": {"coordinates":[2.335166,48.865078],"type":"Point"}
}