{
  "type": "Feature",
  "properties": {
    "iso:country":"FR",
    "sg:address":"25, Rue Scandicci, 93698 Pantin C\u00e9dex",
    "sg:orig_category":"Non-Classified Establishments",
    "sg:phone":"+33 1 49 42 85 85",
    "sg:province":"\u00cele-de-France",
    "wof:name":"Mercure Paris Porte De Pantin",
    "wof:placetype":"venue"
},
  "geometry": {"coordinates":[2.398331,48.893234],"type":"Point"}
}