{
  "type": "Feature",
  "properties": {
    "addr:full":"73, Av. Georges Politzer - ZI de Tappes-Elancourt, 78190 Trappes Ile de France",
    "addr:postcode":"78190;ile",
    "addr:street":"73 Av. Georges Politzer Zi De Tappes-Elancourt",
    "iso:country":"FR",
    "sg:address":"73, Av. Georges Politzer - ZI de Tappes-Elancourt, 78190 Trappes",
    "sg:orig_category":"Unclassifiable Establishments",
    "sg:phone":"+33 1 30 50 76 02",
    "sg:province":"Ile de France",
    "wof:name":"Frigoscandia Distribution S.a.s.",
    "wof:placetype":"venue"
},
  "geometry": {"coordinates":[1.999285,48.774651],"type":"Point"}
}