{
  "type": "Feature",
  "properties": {
    "addr:full":"23 Rue F\u00e9lix Faure Romilly Sur Seine Champagne 10100",
    "addr:housenumber":"23",
    "addr:postcode":"10100",
    "addr:street":"Rue Fe\u0301Lix Faure Romilly Sur Seine",
    "iso:country":"FR",
    "sg:address":"23 Rue F\u00e9lix Faure",
    "sg:city":"Romilly Sur Seine",
    "sg:classifiers":[
        {
            "category":"Banks & Credit Unions",
            "subcategory":"Financial Services",
            "type":"Services"
        }
    ],
    "sg:phone":"+33 3 25 39 56 56",
    "sg:postcode":"10100",
    "sg:province":"Champagne",
    "sg:tags":[
        "banking",
        "finance",
        "insurance"
    ],
    "wof:name":"Prieur Fouquier Girot Sarl",
    "wof:placetype":"venue"
},
  "geometry": {"coordinates":[3.722512,48.512459],"type":"Point"}
}