{
  "type": "Feature",
  "properties": {
    "addr:full":"8 Route Du Mans 72270 Malicorne Sur Sarthe Pays de Loire 72270",
    "addr:housenumber":"8",
    "addr:postcode":"72270;72270",
    "addr:street":"Route Du Mans;Loire",
    "iso:country":"FR",
    "sg:address":"8 Route Du Mans 72270 Malicorne Sur Sarthe",
    "sg:classifiers":[
        {
            "category":"Utilities",
            "subcategory":"Electric",
            "type":"Services"
        }
    ],
    "sg:phone":"+33 2 43 94 55 00",
    "sg:postcode":"72270",
    "sg:province":"Pays de Loire",
    "sg:tags":[
        "electricity",
        "electronic",
        "electrical",
        "equipment"
    ],
    "wof:name":"Application Electrique Industrielle (aei)",
    "wof:placetype":"venue"
},
  "geometry": {"coordinates":[-0.078656,47.821259],"type":"Point"}
}