{
  "type": "Feature",
  "properties": {
    "addr:full":"139, Rte Nationale, 78970 M\u00e9zi\u00e8res sur Seine Ile de France",
    "addr:housenumber":"139",
    "addr:postcode":"78970",
    "addr:street":"Rte Nationale",
    "iso:country":"FR",
    "sg:address":"139, Rte Nationale, 78970 M\u00e9zi\u00e8res sur Seine",
    "sg:orig_category":"Non-Classified Establishments",
    "sg:phone":"+33 1 30 95 61 04",
    "sg:province":"Ile de France",
    "wof:name":"T.d.f. - Terre De Fruits S.a.s.",
    "wof:placetype":"venue"
},
  "geometry": {"coordinates":[1.801611,48.958885],"type":"Point"}
}