{
  "type": "Feature",
  "properties": {
    "addr:full":"2 rue Henri Breuil 60600 Clermont Picardie 60600",
    "addr:housenumber":"2",
    "addr:postcode":"60600;60600",
    "addr:street":"Rue Henri Breuil",
    "iso:country":"FR",
    "sg:address":"2 rue Henri Breuil 60600 Clermont",
    "sg:classifiers":[
        {
            "category":"Food & Beverages",
            "subcategory":"Dairy",
            "type":"Retail Goods"
        }
    ],
    "sg:phone":"+33 3 44 50 81 20",
    "sg:postcode":"60600",
    "sg:province":"Picardie",
    "sg:tags":[
        "product",
        "milk"
    ],
    "wof:name":"Soci\u00e9t\u00e9 Laiti\u00e8re De Clermont Sarl",
    "wof:placetype":"venue"
},
  "geometry": {"coordinates":[2.412126,49.385529],"type":"Point"}
}