{
  "type": "Feature",
  "properties": {
    "addr:full":"32 rue du Parc 94140 Alfortville Ile de France",
    "addr:housenumber":"32",
    "addr:postcode":"94140;ile",
    "addr:street":"Rue Du Parc",
    "iso:country":"FR",
    "sg:address":"32 rue du Parc 94140 Alfortville",
    "sg:classifiers":[
        {
            "category":"Manufacturing",
            "subcategory":"Wood Products",
            "type":"Manufacturing & Wholesale Goods"
        }
    ],
    "sg:phone":"+33 1 43 75 18 87",
    "sg:province":"Ile de France",
    "sg:tags":[
        "recycling"
    ],
    "wof:name":"Ste Sicsa S.a.",
    "wof:placetype":"venue"
},
  "geometry": {"coordinates":[2.415651,48.815311],"type":"Point"}
}