{
  "type": "Feature",
  "properties": {
    "addr:full":"1, Impasse Nicolas Fran\u00e7ois Blaux - ZI du Neuwald, 57200 Sarreguemines Lorraine 57200",
    "addr:housenumber":"1",
    "addr:postcode":"57200;57200",
    "addr:street":"Impasse Nicolas Franc\u0327Ois Blaux Zi Du Neuwald",
    "iso:country":"FR",
    "sg:address":"1, Impasse Nicolas Fran\u00e7ois Blaux - ZI du Neuwald, 57200 Sarreguemines",
    "sg:orig_category":"Fen\u00eatres PVC Menuiserie PVC Menuiserie ext\u00e9rieure Moustiquaires Portes sectionnelles Volets roulants",
    "sg:phone":"+33 3 87 27 23 40",
    "sg:postcode":"57200",
    "sg:province":"Lorraine",
    "wof:name":"Marquardt France S.a.r.l.",
    "wof:placetype":"venue"
},
  "geometry": {"coordinates":[7.070569,49.108246],"type":"Point"}
}