{
  "type": "Feature",
  "properties": {
    "addr:full":"3 Rue De Groussay 78120 Rambouillet Ile de France",
    "addr:housenumber":"3",
    "addr:postcode":"78120;ile",
    "addr:street":"Rue De Groussay",
    "iso:country":"FR",
    "sg:address":"3 Rue De Groussay 78120 Rambouillet",
    "sg:classifiers":[
        {
            "category":"Home & Garden",
            "subcategory":"Furniture",
            "type":"Retail Goods"
        }
    ],
    "sg:phone":"+33 1 34 83 01 63",
    "sg:province":"Ile de France",
    "sg:tags":[
        "wood"
    ],
    "wof:name":"Office National Des For\u00cats",
    "wof:placetype":"venue"
},
  "geometry": {"coordinates":[1.818252,48.652206],"type":"Point"}
}