{
  "type": "Feature",
  "properties": {
    "iso:country":"FR",
    "sg:address":"2 Rue D'Yvours 69540 Irigny",
    "sg:classifiers":[
        {
            "category":"Professional",
            "subcategory":"Printing & Photocopies",
            "type":"Services"
        }
    ],
    "sg:phone":"+33 4 72 66 32 66",
    "sg:province":"Rhone-Alpes",
    "sg:tags":[
        "publishing"
    ],
    "wof:name":"Livre Diffusion",
    "wof:placetype":"venue"
},
  "geometry": {"coordinates":[4.826474,45.688812],"type":"Point"}
}