{
  "type": "Feature",
  "properties": {
    "addr:full":"4, Av. de Kergroise, 56100 Lorient Lorient Bretagne 56100",
    "addr:postcode":"56100;56100",
    "addr:street":"Av. De Kergroise",
    "iso:country":"FR",
    "sg:address":"4, Av. de Kergroise, 56100 Lorient",
    "sg:city":"Lorient",
    "sg:orig_category":"Unclassifiable Establishments",
    "sg:phone":"+33 2 97 37 35 67",
    "sg:postcode":"56100",
    "sg:province":"Bretagne",
    "wof:name":"Vulcalor S.a.",
    "wof:placetype":"venue"
},
  "geometry": {"coordinates":[-3.363833,47.735924],"type":"Point"}
}