{
  "type": "Feature",
  "properties": {
    "addr:full":"22 Bis R Louis Bl\u00e9riot 63050 Clermont Ferrand Cedex 02 Clermont Rhone-Alpes 74270",
    "addr:housenumber":"22 bis",
    "addr:postcode":"63050;74270",
    "addr:street":"R Louis Ble\u0301Riot",
    "iso:country":"FR",
    "sg:address":"22 Bis R Louis Bl\u00e9riot 63050 Clermont Ferrand Cedex 02",
    "sg:city":"Clermont",
    "sg:classifiers":[
        {
            "category":"Autos & Motor Vehicles",
            "subcategory":"Automobile Sales",
            "type":"Retail Goods"
        }
    ],
    "sg:phone":"+33 4 73 92 18 72",
    "sg:postcode":"74270",
    "sg:province":"Rhone-Alpes",
    "sg:tags":[
        "equipment",
        "transport"
    ],
    "wof:name":"Ets Doupeux Gaubert Sa",
    "wof:placetype":"venue"
},
  "geometry": {"coordinates":[3.149455,45.805447],"type":"Point"}
}