{
  "type": "Feature",
  "properties": {
    "iso:country":"FR",
    "sg:address":"9, Rue Louis Armand - ZAE le Montmartre, 95600 Eaubonne",
    "sg:orig_category":"Non-Classified Establishments",
    "sg:phone":"+33 1 30 10 64 44",
    "sg:province":"Ile de France",
    "wof:name":"Mirabelle P\u00e9riph\u00e9riques Essentiels De La Communication Informatique Bureautique S.a.r.l.",
    "wof:placetype":"venue"
},
  "geometry": {"coordinates":[2.277595,48.990578],"type":"Point"}
}