{
  "type": "Feature",
  "properties": {
    "iso:country":"FR",
    "sg:address":"Traverse Gaston De Flotte Parc Des Faienciers 13012 Marseille",
    "sg:classifiers":[
        {
            "category":"Shopping",
            "subcategory":"Clothing, Apparel, & Fashions",
            "type":"Retail Goods"
        }
    ],
    "sg:phone":"+33 4 91 87 51 40",
    "sg:province":"Poitou-Charentes",
    "sg:tags":[
        "textile",
        "clothing",
        "clothes"
    ],
    "wof:name":"Sport Equipment",
    "wof:placetype":"venue"
},
  "geometry": {"coordinates":[5.427532,43.296833],"type":"Point"}
}