{
  "type": "Feature",
  "properties": {
    "iso:country":"FR",
    "sg:address":"08300 Neuflize",
    "sg:city":"Bergnicourt",
    "sg:orig_category":"Unclassifiable Establishments",
    "sg:phone":"+33 3 24 38 91 75",
    "sg:postcode":"08300",
    "sg:province":"Champagne",
    "wof:name":"Arden Oeufs S.a.r.l.",
    "wof:placetype":"venue"
},
  "geometry": {"coordinates":[4.303787,49.410927],"type":"Point"}
}