{
  "type": "Feature",
  "properties": {
    "addr:full":"9, Av. Carrassiers, 11250 Rouffiac d'Aude Languedoc-Roussillon 11250",
    "addr:postcode":"11250;d'aude;11250",
    "addr:street":"Av. Carrassiers",
    "iso:country":"FR",
    "sg:address":"9, Av. Carrassiers, 11250 Rouffiac d'Aude",
    "sg:orig_category":"Non-Classified Establishments",
    "sg:phone":"+33 4 68 25 14 25",
    "sg:postcode":"11250",
    "sg:province":"Languedoc-Roussillon",
    "wof:name":"Albert Ourtal",
    "wof:placetype":"venue"
},
  "geometry": {"coordinates":[2.299206,43.129639],"type":"Point"}
}