{
  "type": "Feature",
  "properties": {
    "addr:full":"Z.A.C. la Croisette Saint Nicolas de Port Lorraine 54210",
    "addr:postcode":"54210",
    "addr:street":"Z.A.C. La Croisette Saint Nicolas De Port Lorraine",
    "iso:country":"FR",
    "sg:address":"Z.A.C. la Croisette",
    "sg:city":"Saint Nicolas de Port",
    "sg:orig_category":"Non-Classified Establishments",
    "sg:phone":"+33 3 83 57 16 17",
    "sg:postcode":"54210",
    "sg:province":"Lorraine",
    "wof:name":"Technisol S.a.r.l.",
    "wof:placetype":"venue"
},
  "geometry": {"coordinates":[6.30159,48.631104],"type":"Point"}
}