{
  "type": "Feature",
  "properties": {
    "addr:full":"1, Rue Jeanne d'Arc, 41000 Blois Blois Centre 41000",
    "addr:housenumber":"1",
    "addr:postcode":"41000;41000",
    "addr:street":"Rue Jeanne D'Arc",
    "iso:country":"FR",
    "sg:address":"1, Rue Jeanne d'Arc, 41000 Blois",
    "sg:city":"Blois",
    "sg:orig_category":"Unclassifiable Establishments",
    "sg:phone":"+33 2 54 78 31 17",
    "sg:postcode":"41000",
    "sg:province":"Centre",
    "wof:name":"Adecco Travail Temporaire S.a.",
    "wof:placetype":"venue"
},
  "geometry": {"coordinates":[1.335811,47.587185],"type":"Point"}
}