{
  "type": "Feature",
  "properties": {
    "addr:full":"19, Rue Emile Zola, 37000 Tours Tours Centre 37000",
    "addr:housenumber":"19",
    "addr:postcode":"37000;37000",
    "addr:street":"Rue Emile Zola",
    "iso:country":"FR",
    "sg:address":"19, Rue Emile Zola, 37000 Tours",
    "sg:city":"Tours",
    "sg:orig_category":"Non-Classified Establishments",
    "sg:phone":"+33 2 47 61 94 14",
    "sg:postcode":"37000",
    "sg:province":"Centre",
    "wof:name":"Cerus Informatique S.a.s.",
    "wof:placetype":"venue"
},
  "geometry": {"coordinates":[0.689714,47.39341],"type":"Point"}
}