{
  "type": "Feature",
  "properties": {
    "addr:full":"1, Chemin du Lavoir, 61200 Urou et Crennes Argentan Basse Normandie 61200",
    "addr:housenumber":"1",
    "addr:postcode":"61200;61200",
    "addr:street":"Chemin Du Lavoir;Basse",
    "iso:country":"FR",
    "sg:address":"1, Chemin du Lavoir, 61200 Urou et Crennes",
    "sg:city":"Argentan",
    "sg:orig_category":"Unclassifiable Establishments",
    "sg:phone":"+33 2 33 36 25 20",
    "sg:postcode":"61200",
    "sg:province":"Basse Normandie",
    "wof:name":"G. Druschke S.a.",
    "wof:placetype":"venue"
},
  "geometry": {"coordinates":[0.012146,48.747181],"type":"Point"}
}