{
  "type": "Feature",
  "properties": {
    "addr:full":"B.P. 38, 47240 Bon Encontre C\u00e9dex^^ZI Jean Mal\u00e8ze, 47240 Bon Encontre Bon-Encontre Aquitaine 47240",
    "addr:postcode":"47240;47240;47240",
    "addr:street":"B.P. 38;Bon Encontre",
    "iso:country":"FR",
    "sg:address":"B.P. 38, 47240 Bon Encontre C\u00e9dex^^ZI Jean Mal\u00e8ze, 47240 Bon Encontre",
    "sg:city":"Bon-Encontre",
    "sg:orig_category":"Non-Classified Establishments",
    "sg:phone":"+33 5 53 68 49 49",
    "sg:postcode":"47240",
    "sg:province":"Aquitaine",
    "wof:name":"Soverso S.n.c.",
    "wof:placetype":"venue"
},
  "geometry": {"coordinates":[0.698695,44.16959],"type":"Point"}
}