{
  "type": "Feature",
  "properties": {
    "addr:full":"Rte de Nantes Pontch\u00e2teau Pays de Loire 44160",
    "addr:postcode":"44160",
    "addr:street":"Rte De Nantes",
    "iso:country":"FR",
    "sg:address":"Rte de Nantes",
    "sg:city":"Pontch\u00e2teau",
    "sg:orig_category":"Unclassifiable Establishments",
    "sg:phone":"+33 2 40 00 73 50",
    "sg:postcode":"44160",
    "sg:province":"Pays de Loire",
    "wof:name":"Sambron S.a.",
    "wof:placetype":"venue"
},
  "geometry": {"coordinates":[-2.088629,47.436981],"type":"Point"}
}