{
  "type": "Feature",
  "properties": {
    "iso:country":"FR",
    "sg:address":"Le Chanasson 42110 Epercieux St Paul",
    "sg:classifiers":[
        {
            "category":"Wholesale",
            "subcategory":"Farm Supplies",
            "type":"Manufacturing & Wholesale Goods"
        }
    ],
    "sg:phone":"+33 4 77 27 47 47",
    "sg:postcode":"42110",
    "sg:province":"Rhone-Alpes",
    "sg:tags":[
        "-",
        "machine",
        "equipment",
        "engineering",
        "machinery",
        "mechanical",
        "agriculture"
    ],
    "wof:name":"Mef Sarl",
    "wof:placetype":"venue"
},
  "geometry": {"coordinates":[4.216249,45.782063],"type":"Point"}
}