{
  "type": "Feature",
  "properties": {
    "iso:country":"FR",
    "sg:address":"103 boulevard de Metz 59100 Roubaix",
    "sg:classifiers":[
        {
            "category":"Shopping",
            "subcategory":"Crafts & Fabrics",
            "type":"Retail Goods"
        }
    ],
    "sg:phone":"+33 3 20 76 95 10",
    "sg:province":"Nord Pas-de-Calais",
    "sg:tags":[
        "woven",
        "cotton"
    ],
    "wof:name":"Cotrem Sas",
    "wof:placetype":"venue"
},
  "geometry": {"coordinates":[3.180271,50.704502],"type":"Point"}
}