{
  "type": "Feature",
  "properties": {
    "addr:full":"5, Av. de la Dranse, 74200 Thonon les Bains Rhone-Alpes 74200",
    "addr:postcode":"74200;74200",
    "addr:street":"Av. De La Dranse",
    "iso:country":"FR",
    "sg:address":"5, Av. de la Dranse, 74200 Thonon les Bains",
    "sg:orig_category":"Non-Classified Establishments",
    "sg:phone":"+33 4 50 71 01 88",
    "sg:postcode":"74200",
    "sg:province":"Rhone-Alpes",
    "wof:name":"Etablissement Buttay Fr\u00e8res S.a.",
    "wof:placetype":"venue"
},
  "geometry": {"coordinates":[6.492541,46.370266],"type":"Point"}
}