{
  "type": "Feature",
  "properties": {
    "addr:full":"107 Av De La Mar\u00e9chale 94420 Le Plessis Tr\u00e9vise Ile de France",
    "addr:postcode":"94420",
    "addr:street":"107 Av De La Mare\u0301Chale",
    "iso:country":"FR",
    "sg:address":"107 Av De La Mar\u00e9chale 94420 Le Plessis Tr\u00e9vise",
    "sg:classifiers":[
        {
            "category":"Manufacturing",
            "subcategory":"Paper Products",
            "type":"Manufacturing & Wholesale Goods"
        }
    ],
    "sg:phone":"+33 1 45 94 88 88",
    "sg:province":"Ile de France",
    "sg:tags":[
        "packaging",
        "material",
        "-",
        "cardboard"
    ],
    "wof:name":"Chabanne Et Compagnie (cartonnages) Sa",
    "wof:placetype":"venue"
},
  "geometry": {"coordinates":[2.572678,48.813305],"type":"Point"}
}