{
  "type": "Feature",
  "properties": {
    "addr:full":"Le Tholonet BP 100 13603 Aix En Provence Cedex 1 Nord Pas-de-Calais",
    "addr:housenumber":"100;1",
    "addr:postcode":"13603",
    "iso:country":"FR",
    "sg:address":"Le Tholonet BP 100 13603 Aix En Provence Cedex 1",
    "sg:classifiers":[
        {
            "category":"Utilities",
            "type":"Services"
        }
    ],
    "sg:phone":"+33 4 42 66 70 00",
    "sg:province":"Nord Pas-de-Calais",
    "sg:tags":[
        "raw",
        "energy",
        "material"
    ],
    "wof:name":"Ste Canal Provence Amenagement Region Proven\u00c7al",
    "wof:placetype":"venue"
},
  "geometry": {"coordinates":[5.471045,43.520016],"type":"Point"}
}