{
  "type": "Feature",
  "properties": {
    "addr:full":"7, Av de la Lib\u00e9ration, 71210 Montchanin Montchanin Bourgogne 71210",
    "addr:postcode":"71210;71210",
    "addr:street":"Av De La Libe\u0301Ration",
    "iso:country":"FR",
    "sg:address":"7, Av de la Lib\u00e9ration, 71210 Montchanin",
    "sg:city":"Montchanin",
    "sg:orig_category":"Unclassifiable Establishments",
    "sg:phone":"+33 3 85 78 13 61",
    "sg:postcode":"71210",
    "sg:province":"Bourgogne",
    "wof:name":"Genevois P\u00e8re Et Fils S.a.r.l.",
    "wof:placetype":"venue"
},
  "geometry": {"coordinates":[4.474538,46.754059],"type":"Point"}
}