{
  "type": "Feature",
  "properties": {
    "iso:country":"FR",
    "sg:address":"109 Rue D'Entraigues",
    "sg:city":"Tours",
    "sg:classifiers":[
        {
            "category":"Banks & Credit Unions",
            "subcategory":"Financial Services",
            "type":"Services"
        }
    ],
    "sg:phone":"+33 2 47 61 06 69",
    "sg:postcode":"37000",
    "sg:province":"Centre",
    "sg:tags":[
        "banking",
        "finance",
        "insurance"
    ],
    "wof:name":"Fortis Assurances",
    "wof:placetype":"venue"
},
  "geometry": {"coordinates":[0.686888,47.387947],"type":"Point"}
}