{
  "type": "Feature",
  "properties": {
    "iso:country":"FR",
    "sg:address":"Rue de Meaux",
    "sg:city":"Paris",
    "sg:orig_category":"Non-Classified Establishments",
    "sg:phone":"+33 1 43 55 21 77",
    "sg:postcode":"75019",
    "sg:province":"Ile de France",
    "wof:name":"Compagnie Lef\u00e8bvre S.a.",
    "wof:placetype":"venue"
},
  "geometry": {"coordinates":[2.38135,48.885529],"type":"Point"}
}