{
  "type": "Feature",
  "properties": {
    "addr:full":"Rue des Alisiers Arpaillargues et Aureillac Languedoc-Roussillon 30700",
    "addr:postcode":"30700",
    "addr:street":"Rue Des Alisiers Arpaillargues Et Aureillac",
    "iso:country":"FR",
    "sg:address":"Rue des Alisiers",
    "sg:city":"Arpaillargues et Aureillac",
    "sg:orig_category":"Non-Classified Establishments",
    "sg:phone":"+33 4 66 03 21 00",
    "sg:postcode":"30700",
    "sg:province":"Languedoc-Roussillon",
    "wof:name":"Magnus France",
    "wof:placetype":"venue"
},
  "geometry": {"coordinates":[4.373366,44.000397],"type":"Point"}
}