{
  "type": "Feature",
  "properties": {
    "iso:country":"FR",
    "sg:address":"Rue des Alisiers",
    "sg:city":"Arpaillargues et Aureillac",
    "sg:orig_category":"Non-Classified Establishments",
    "sg:phone":"+33 4 66 03 21 00",
    "sg:postcode":"30700",
    "sg:province":"Languedoc-Roussillon",
    "wof:name":"Magnus France",
    "wof:placetype":"venue"
},
  "geometry": {"coordinates":[4.373366,44.000397],"type":"Point"}
}