{
  "type": "Feature",
  "properties": {
    "addr:full":"9 Et 11 3 E Rue 13127 Vitrolles Centre",
    "addr:housenumber":"9 et 11 3 e",
    "addr:postcode":"13127",
    "addr:street":"Rue",
    "iso:country":"FR",
    "sg:address":"9 Et 11 3 E Rue 13127 Vitrolles",
    "sg:orig_category":"Fittings, Valves",
    "sg:phone":"+33 4 42 79 16 14",
    "sg:province":"Centre",
    "wof:name":"Europe Valves Sarl",
    "wof:placetype":"venue"
},
  "geometry": {"coordinates":[5.253005,43.449944],"type":"Point"}
}