{
  "type": "Feature",
  "properties": {
    "addr:full":"15 Rue Du General De Gaulle 29750 Loctudy Loctudy Bretagne 29750",
    "addr:housenumber":"15",
    "addr:postcode":"29750;29750",
    "addr:street":"Rue Du General De Gaulle",
    "iso:country":"FR",
    "sg:address":"15 Rue Du General De Gaulle 29750 Loctudy",
    "sg:city":"Loctudy",
    "sg:classifiers":[
        {
            "category":"Manufacturing",
            "subcategory":"Wood Products",
            "type":"Manufacturing & Wholesale Goods"
        }
    ],
    "sg:phone":"+33 2 98 87 45 96",
    "sg:postcode":"29750",
    "sg:province":"Bretagne",
    "sg:tags":[
        "professional",
        "furniture"
    ],
    "wof:name":"Entreprise Unipersonnelle A Responsabilite Limitee Bilien",
    "wof:placetype":"venue"
},
  "geometry": {"coordinates":[-4.184945,47.833534],"type":"Point"}
}