{
  "type": "Feature",
  "properties": {
    "iso:country":"FR",
    "sg:address":"Portes Du Vaudreuil Voie Du Testelet 27100 Val De Reuil",
    "sg:classifiers":[
        {
            "category":"Professional",
            "type":"Services"
        }
    ],
    "sg:phone":"+33 2 32 25 66 66",
    "sg:province":"Haute Normandie",
    "sg:tags":[
        "transport",
        "road"
    ],
    "wof:name":"Logistrans",
    "wof:placetype":"venue"
},
  "geometry": {"coordinates":[1.21452,49.271011],"type":"Point"}
}