{
  "type": "Feature",
  "properties": {
    "addr:full":"7, Rue Baumgardh, 78120 Rambouillet Ile de France",
    "addr:housenumber":"7",
    "addr:postcode":"78120;ile",
    "addr:street":"Rue Baumgardh",
    "iso:country":"FR",
    "sg:address":"7, Rue Baumgardh, 78120 Rambouillet",
    "sg:orig_category":"Unclassifiable Establishments",
    "sg:phone":"+33 1 34 94 98 18",
    "sg:province":"Ile de France",
    "wof:name":"Offset Eclair S.a.r.l.",
    "wof:placetype":"venue"
},
  "geometry": {"coordinates":[1.837,48.642704],"type":"Point"}
}