{
  "type": "Feature",
  "properties": {
    "addr:full":"171 ave Charles de Gaulle; Paris; 92200 Ile de France 92200",
    "addr:housenumber":"171",
    "addr:postcode":"92200 ile;france 92200",
    "addr:street":"Ave Charles De Gaulle",
    "iso:country":"FR",
    "sg:address":"171 ave Charles de Gaulle; Paris; 92200",
    "sg:classifiers":[
        {
            "category":"Banks & Credit Unions",
            "subcategory":"Bank",
            "type":"Services"
        }
    ],
    "sg:phone":"+33 1 88 40 10 22",
    "sg:postcode":"92200",
    "sg:province":"Ile de France",
    "wof:name":"Banque Europeenne, De Cr\u00e9dit",
    "wof:placetype":"venue"
},
  "geometry": {"coordinates":[2.262802,48.883598],"type":"Point"}
}