{
  "type": "Feature",
  "properties": {
    "addr:full":"Av. d'Iffendic Saint P\u00e9ran Bretagne 35380",
    "addr:postcode":"35380",
    "addr:street":"Av. D'Iffendic Saint Pe\u0301Ran Bretagne",
    "iso:country":"FR",
    "sg:address":"Av. d'Iffendic",
    "sg:city":"Saint P\u00e9ran",
    "sg:orig_category":"Unclassifiable Establishments",
    "sg:phone":"+33 2 99 06 81 00",
    "sg:postcode":"35380",
    "sg:province":"Bretagne",
    "wof:name":"Info Express S.a.",
    "wof:placetype":"venue"
},
  "geometry": {"coordinates":[-2.05644,48.055168],"type":"Point"}
}