{
  "type": "Feature",
  "properties": {
    "iso:country":"FR",
    "sg:address":"11, Rue Atome, 67802 Bischheim",
    "sg:city":"Bischheim",
    "sg:orig_category":"Unclassifiable Establishments",
    "sg:phone":"+33 3 88 19 72 30",
    "sg:postcode":"67800",
    "sg:province":"Alsace",
    "wof:name":"Gazomat S.a.r.l.",
    "wof:placetype":"venue"
},
  "geometry": {"coordinates":[7.771518,48.629883],"type":"Point"}
}