{
  "type": "Feature",
  "properties": {
    "iso:country":"FR",
    "sg:address":"8-10 ave Emile Zola; Boulogne Billancourt; 92109",
    "sg:city":"Ancourt",
    "sg:classifiers":[
        {
            "category":"Banks & Credit Unions",
            "subcategory":"Bank",
            "type":"Services"
        }
    ],
    "sg:phone":"+33 3346204444",
    "sg:postcode":"76370",
    "sg:province":"Haute Normandie",
    "wof:name":"Soci\u00e9t\u00e9 Financiere Et Fonciere",
    "wof:placetype":"venue"
},
  "geometry": {"coordinates":[2.239072,48.828835],"type":"Point"}
}