{
  "type": "Feature",
  "properties": {
    "iso:country":"FR",
    "sg:address":"20, Rue de la Gare, 36130 Montierchaume",
    "sg:city":"Montierchaume",
    "sg:orig_category":"Unclassifiable Establishments",
    "sg:phone":"+33 2 54 26 03 30",
    "sg:postcode":"36130",
    "sg:province":"Centre",
    "wof:name":"Erac Automation S.a.r.l.",
    "wof:placetype":"venue"
},
  "geometry": {"coordinates":[1.778,46.862259],"type":"Point"}
}