{
  "type": "Feature",
  "properties": {
    "addr:full":"59, Av. de la R\u00e9publique, 95400 Arnouville l\u00e8s Gonesse Ile de France",
    "addr:postcode":"95400",
    "addr:street":"59 Av. De La Re\u0301Publique",
    "iso:country":"FR",
    "sg:address":"59, Av. de la R\u00e9publique, 95400 Arnouville l\u00e8s Gonesse",
    "sg:orig_category":"Non-Classified Establishments",
    "sg:phone":"+33 1 39 86 32 68",
    "sg:province":"Ile de France",
    "wof:name":"L'isolaphone S.a.",
    "wof:placetype":"venue"
},
  "geometry": {"coordinates":[2.42587,48.981003],"type":"Point"}
}