{
  "type": "Feature",
  "properties": {
    "iso:country":"FR",
    "sg:address":"1 Rue De La Levee De La Loire 37520 La Riche",
    "sg:city":"La Riche",
    "sg:classifiers":[
        {
            "category":"Professional",
            "subcategory":"Printing & Photocopies",
            "type":"Services"
        }
    ],
    "sg:phone":"+33 2 47 38 74 22",
    "sg:postcode":"37520",
    "sg:province":"Centre",
    "sg:tags":[
        "publishing"
    ],
    "wof:name":"Presence Graphique",
    "wof:placetype":"venue"
},
  "geometry": {"coordinates":[0.66471,47.390419],"type":"Point"}
}