{
  "type": "Feature",
  "properties": {
    "iso:country":"FR",
    "sg:address":"Lieu Dit Le Chinaillon La Place 74450 Le Grand Bornand",
    "sg:classifiers":[
        {
            "category":"Home & Garden",
            "subcategory":"Furniture",
            "type":"Retail Goods"
        }
    ],
    "sg:phone":"+33 4 50 27 01 50",
    "sg:postcode":"74450",
    "sg:province":"Rhone-Alpes",
    "sg:tags":[
        "household",
        "wood"
    ],
    "wof:name":"Sarl Meubles Vulliet",
    "wof:placetype":"venue"
},
  "geometry": {"coordinates":[6.409583,45.92234],"type":"Point"}
}