{
  "type": "Feature",
  "properties": {
    "addr:full":"41, Bd Louis XI, 37000 Tours Tours Centre 37000",
    "addr:housenumber":"41",
    "addr:postcode":"37000;37000",
    "addr:street":"Bd Louis Xi",
    "iso:country":"FR",
    "sg:address":"41, Bd Louis XI, 37000 Tours",
    "sg:city":"Tours",
    "sg:orig_category":"Unclassifiable Establishments",
    "sg:phone":"+33 2 47 37 53 54",
    "sg:postcode":"37000",
    "sg:province":"Centre",
    "wof:name":"Num\u00e9ri Scann 37 S.a.",
    "wof:placetype":"venue"
},
  "geometry": {"coordinates":[0.66542,47.375549],"type":"Point"}
}