{
  "type": "Feature",
  "properties": {
    "iso:country":"FR",
    "sg:address":"4, Rte de Viry, 39360 Rogna",
    "sg:orig_category":"Non-Classified Establishments",
    "sg:phone":"+33 3 84 41 11 02",
    "sg:province":"Franche Comt\u00e9",
    "wof:name":"Ulys Production S.a.r.l.",
    "wof:placetype":"venue"
},
  "geometry": {"coordinates":[5.747115,46.325134],"type":"Point"}
}