{
  "type": "Feature",
  "properties": {
    "addr:full":"4 Rue Bourseul Parc D Activites Pegase 22300 Lannion Lannion Bretagne 22300",
    "addr:housenumber":"4",
    "addr:postcode":"22300;22300",
    "addr:street":"Rue Bourseul Parc D Activites Pegase",
    "iso:country":"FR",
    "sg:address":"4 Rue Bourseul Parc D Activites Pegase 22300 Lannion",
    "sg:city":"Lannion",
    "sg:classifiers":[
        {
            "category":"Utilities",
            "subcategory":"Electric",
            "type":"Services"
        }
    ],
    "sg:phone":"+33 2 96 48 44 00",
    "sg:postcode":"22300",
    "sg:province":"Bretagne",
    "sg:tags":[
        "electricity",
        "electronic",
        "electrical",
        "equipment"
    ],
    "wof:name":"Armoritel",
    "wof:placetype":"venue"
},
  "geometry": {"coordinates":[-3.463184,48.756035],"type":"Point"}
}