{
  "type": "Feature",
  "properties": {
    "addr:full":"Rue J B Colbert Zac Des Courtilleraies 77350 Le M\u00e9e Sur Seine Ile de France",
    "addr:postcode":"77350",
    "addr:street":"Rue J B Colbert Zac Des Courtilleraies",
    "iso:country":"FR",
    "sg:address":"Rue J B Colbert Zac Des Courtilleraies 77350 Le M\u00e9e Sur Seine",
    "sg:classifiers":[
        {
            "category":"Manufacturing",
            "subcategory":"Printing",
            "type":"Manufacturing & Wholesale Goods"
        }
    ],
    "sg:phone":"+33 1 60 56 55 00",
    "sg:province":"Ile de France",
    "sg:tags":[
        "publishing"
    ],
    "wof:name":"Melun Impression",
    "wof:placetype":"venue"
},
  "geometry": {"coordinates":[2.63157,48.542267],"type":"Point"}
}