{
  "type": "Feature",
  "properties": {
    "addr:full":"51, Rue Albert Camus, 47000 Agen Agen Aquitaine 47000",
    "addr:housenumber":"51",
    "addr:postcode":"47000;47000",
    "addr:street":"Rue Albert Camus",
    "iso:country":"FR",
    "sg:address":"51, Rue Albert Camus, 47000 Agen",
    "sg:city":"Agen",
    "sg:orig_category":"Non-Classified Establishments",
    "sg:phone":"+33 5 53 77 83 60",
    "sg:postcode":"47000",
    "sg:province":"Aquitaine",
    "wof:name":"Quatr'e S.a.r.l.",
    "wof:placetype":"venue"
},
  "geometry": {"coordinates":[0.639422,44.192177],"type":"Point"}
}