{
  "type": "Feature",
  "properties": {
    "iso:country":"FR",
    "sg:address":"Les Hauts Noirs Parc Activites De Sologne 41600 Lamotte Beuvron",
    "sg:city":"Chaon",
    "sg:classifiers":[
        {
            "category":"Manufacturing",
            "subcategory":"Metals",
            "type":"Manufacturing & Wholesale Goods"
        }
    ],
    "sg:phone":"+33 2 54 88 46 71",
    "sg:postcode":"41600",
    "sg:province":"Centre",
    "sg:tags":[
        "metallurgy",
        "metalworking",
        "processing"
    ],
    "wof:name":"Montech Albert Decoupe Emboutissage (made)",
    "wof:placetype":"venue"
},
  "geometry": {"coordinates":[2.035673,47.536289],"type":"Point"}
}