{
  "type": "Feature",
  "properties": {
    "iso:country":"FR",
    "sg:address":"B.P. 43, 95612 Cergy Pontoise C\u00e9dex^^Av. du Gros Ch\u00eane - ZI de Bellevue, 95610 Eragny",
    "sg:orig_category":"Non-Classified Establishments",
    "sg:phone":"+33 1 34 40 18 18",
    "sg:postcode":"95610",
    "sg:province":"Ile de France",
    "wof:name":"E.t.e.m. S.a.",
    "wof:placetype":"venue"
},
  "geometry": {"coordinates":[2.091,49.019009],"type":"Point"}
}