{
  "type": "Feature",
  "properties": {
    "iso:country":"FR",
    "sg:address":"ZI rue Raymond No\u00eal 01140 ST DIDIER SUR CHALARONNE",
    "sg:classifiers":[
        {
            "category":"Mining & Drilling",
            "type":"Manufacturing & Wholesale Goods"
        }
    ],
    "sg:phone":"+33 4 74 69 71 13",
    "sg:province":"Rhone-Alpes",
    "sg:tags":[
        "quarry"
    ],
    "wof:name":"Chaudronnerie Goyon Sa",
    "wof:placetype":"venue"
},
  "geometry": {"coordinates":[4.818525,46.178207],"type":"Point"}
}