{
  "type": "Feature",
  "properties": {
    "iso:country":"FR",
    "sg:address":"23, Rue du plessis Bouchard, 95130 Franconville",
    "sg:orig_category":"Unclassifiable Establishments",
    "sg:phone":"+33 1 34 13 79 96",
    "sg:province":"Ile de France",
    "wof:name":"Carret Munos S.a.",
    "wof:placetype":"venue"
},
  "geometry": {"coordinates":[2.225315,48.987049],"type":"Point"}
}