{
  "type": "Feature",
  "properties": {
    "addr:full":"Av Michel Baroin 58230 Ouroux En Morvan Lavault-de-Fr\u00e9toy Bourgogne 58230",
    "addr:postcode":"58230;58230",
    "addr:street":"Av Michel Baroin;Bourgogne",
    "iso:country":"FR",
    "sg:address":"Av Michel Baroin 58230 Ouroux En Morvan",
    "sg:city":"Lavault-de-Fr\u00e9toy",
    "sg:classifiers":[
        {
            "category":"Shopping",
            "subcategory":"Gifts & Souvenirs",
            "type":"Retail Goods"
        }
    ],
    "sg:phone":"+33 3 86 78 22 28",
    "sg:postcode":"58230",
    "sg:province":"Bourgogne",
    "sg:tags":[
        "product",
        "miscellaneous"
    ],
    "wof:name":"Gauthard Maurice",
    "wof:placetype":"venue"
},
  "geometry": {"coordinates":[3.94813,47.185635],"type":"Point"}
}