{
  "type": "Feature",
  "properties": {
    "addr:full":"9 Pl Brel BP 139 91132 Ris Orangis Cedex Franche Comt\u00e9",
    "addr:housenumber":"9;139",
    "addr:postcode":"91132;orangis cedex franche comte\u0301",
    "addr:street":"Pl Brel Bp",
    "iso:country":"FR",
    "sg:address":"9 Pl Brel BP 139 91132 Ris Orangis Cedex",
    "sg:classifiers":[
        {
            "category":"Shopping",
            "type":"Retail Goods"
        }
    ],
    "sg:phone":"+33 1 69 25 87 87",
    "sg:province":"Franche Comt\u00e9",
    "sg:tags":[
        "metallurgy",
        "finished",
        "-",
        "metalworking",
        "metallic"
    ],
    "wof:name":"Steelplast Sa",
    "wof:placetype":"venue"
},
  "geometry": {"coordinates":[2.409515,48.64957],"type":"Point"}
}