{
  "type": "Feature",
  "properties": {
    "addr:full":"4 Place Emile Mauguet 52100 St Dizier Champagne 52100",
    "addr:housenumber":"4",
    "addr:postcode":"52100;52100",
    "addr:street":"Place Emile Mauguet;Champagne",
    "iso:country":"FR",
    "sg:address":"4 Place Emile Mauguet 52100 St Dizier",
    "sg:classifiers":[
        {
            "category":"Wholesale",
            "subcategory":"Medical Equipment & Supplies",
            "type":"Manufacturing & Wholesale Goods"
        }
    ],
    "sg:phone":"+33 3 25 05 80 50",
    "sg:postcode":"52100",
    "sg:province":"Champagne",
    "sg:tags":[
        "instrument",
        "health",
        "-",
        "precision"
    ],
    "wof:name":"Claudin Coiffure",
    "wof:placetype":"venue"
},
  "geometry": {"coordinates":[4.950109,48.637741],"type":"Point"}
}