{
  "type": "Feature",
  "properties": {
    "iso:country":"FR",
    "sg:address":"2, Rue Jean Lebas, 59172 Roeulx",
    "sg:orig_category":"Unclassifiable Establishments",
    "sg:phone":"+33 3 27 44 06 57",
    "sg:province":"Nord Pas-de-Calais",
    "wof:name":"Warin Et Compagnie S.a.",
    "wof:placetype":"venue"
},
  "geometry": {"coordinates":[3.342445,50.317375],"type":"Point"}
}