{
  "type": "Feature",
  "properties": {
    "addr:full":"3, Rue Dieudonn\u00e9 Costes - Immeuble le Ch\u00e2teau, 31700 Blagnac Midi Pyr\u00e9n\u00e9es",
    "addr:housenumber":"3;immeuble",
    "addr:postcode":"31700",
    "addr:street":"Rue Dieudonne\u0301 Costes",
    "iso:country":"FR",
    "sg:address":"3, Rue Dieudonn\u00e9 Costes - Immeuble le Ch\u00e2teau, 31700 Blagnac",
    "sg:orig_category":"Unclassifiable Establishments",
    "sg:phone":"+33 5 61 71 02 65",
    "sg:province":"Midi Pyr\u00e9n\u00e9es",
    "wof:name":"Groupe A\u00e9roconseil S.a.",
    "wof:placetype":"venue"
},
  "geometry": {"coordinates":[1.379557,43.631187],"type":"Point"}
}