{
  "type": "Feature",
  "properties": {
    "iso:country":"FR",
    "sg:address":"90, Av. Lannesan, 69140 Champagne au Mont d'Or",
    "sg:orig_category":"Non-Classified Establishments",
    "sg:phone":"+33 4 78 66 59 59",
    "sg:postcode":"69140",
    "sg:province":"Rhone-Alpes",
    "wof:name":"Francexport S.a.",
    "wof:placetype":"venue"
},
  "geometry": {"coordinates":[-0.100754,47.869232],"type":"Point"}
}