{
  "type": "Feature",
  "properties": {
    "addr:full":"2 bis, Rue Serge Noyer - ZAC Henri IV, 78200 Mantes la Jolie Ile de France",
    "addr:housenumber":"2 bis",
    "addr:postcode":"78200",
    "addr:street":"Rue Serge Noyer Zac Henri Iv",
    "iso:country":"FR",
    "sg:address":"2 bis, Rue Serge Noyer - ZAC Henri IV, 78200 Mantes la Jolie",
    "sg:orig_category":"Non-Classified Establishments",
    "sg:phone":"+33 1 30 63 05 05",
    "sg:province":"Ile de France",
    "wof:name":"Flash Transports O + S.a.r.l.",
    "wof:placetype":"venue"
},
  "geometry": {"coordinates":[1.714715,48.989491],"type":"Point"}
}