{
  "type": "Feature",
  "properties": {
    "addr:full":"B.P. 37 Saint Malo C\u00e9dex Brittany 35404",
    "addr:housenumber":"37",
    "addr:postcode":"35404",
    "addr:street":"B.P.;Malo Ce\u0301Dex",
    "iso:country":"FR",
    "sg:address":"B.P. 37",
    "sg:city":"Saint Malo C\u00e9dex",
    "sg:orig_category":"Non-Classified Establishments",
    "sg:phone":"+33 2 99 21 12 70",
    "sg:postcode":"35404",
    "sg:province":"Brittany",
    "wof:name":"Sinto Auto S.a.",
    "wof:placetype":"venue"
},
  "geometry": {"coordinates":[-2.023279,48.650494],"type":"Point"}
}