{
  "type": "Feature",
  "properties": {
    "iso:country":"FR",
    "sg:address":"36, Rue de Chateaudun, 75009 Paris",
    "sg:orig_category":"Unclassifiable Establishments",
    "sg:phone":"+33 1 55 07 59 00",
    "sg:province":"Ile de France",
    "wof:name":"Icon M\u00e9dialab S.a.",
    "wof:placetype":"venue"
},
  "geometry": {"coordinates":[2.335978,48.876278],"type":"Point"}
}