{
  "type": "Feature",
  "properties": {
    "iso:country":"FR",
    "sg:address":"1 R De Lancry 75010 Paris",
    "sg:classifiers":[
        {
            "category":"Real Estate",
            "subcategory":"Architect",
            "type":"Services"
        }
    ],
    "sg:phone":"+33 1 42 00 53 01",
    "sg:province":"Ile de France",
    "sg:tags":[
        "textile",
        "clothing"
    ],
    "wof:name":"Rita York Sarl",
    "wof:placetype":"venue"
},
  "geometry": {"coordinates":[2.359727,48.86879],"type":"Point"}
}