{
  "type": "Feature",
  "properties": {
    "iso:country":"FR",
    "sg:address":"B.P. 46",
    "sg:city":"Villefontaine C\u00e9dex^^Le Grand Chemin 38090 Bonnefamille",
    "sg:orig_category":"Non-Classified Establishments",
    "sg:phone":"+33 4 74 96 40 34",
    "sg:postcode":"38090",
    "sg:province":"Rhone-Alpes",
    "wof:name":"R.i.p.s. S.a. - R\u00e9cup\u00e9ration Industrielle De Produits Sid\u00e9rurgiqu",
    "wof:placetype":"venue"
},
  "geometry": {"coordinates":[5.159934,45.588219],"type":"Point"}
}