{
  "type": "Feature",
  "properties": {
    "iso:country":"FR",
    "sg:address":"La Fontaine Saint Martin 03510 Molinet",
    "sg:city":"Molinet",
    "sg:orig_category":"Non-Classified Establishments",
    "sg:phone":"+33 3 85 53 08 26",
    "sg:postcode":"03510",
    "sg:province":"Auvergne",
    "wof:name":"Bonnin",
    "wof:placetype":"venue"
},
  "geometry": {"coordinates":[3.9422,46.47002],"type":"Point"}
}