{
  "type": "Feature",
  "properties": {
    "addr:full":"14 Rue De L'Abb\u00e9 Grandjean 92260 Fontenay Aux Rose Ile de France 92260",
    "addr:housenumber":"14",
    "addr:postcode":"92260;92260",
    "addr:street":"Rue De L'Abbe \u0301",
    "iso:country":"FR",
    "sg:address":"14 Rue De L'Abb\u00e9 Grandjean 92260 Fontenay Aux Rose",
    "sg:classifiers":[
        {
            "category":"Health Services",
            "subcategory":"Medical Lab",
            "type":"Services"
        }
    ],
    "sg:phone":"+33 1 43 50 30 22",
    "sg:postcode":"92260",
    "sg:province":"Ile de France",
    "sg:tags":[
        "chemical",
        "pharmaceutical",
        "pharmacy"
    ],
    "wof:name":"Laboratoire De Techniques Europeennes",
    "wof:placetype":"venue"
},
  "geometry": {"coordinates":[-76.87818900000001,43.152843],"type":"Point"}
}