{
  "type": "Feature",
  "properties": {
    "iso:country":"FR",
    "sg:address":"35 r Charles de Gaulle; L'Arbresle",
    "sg:classifiers":[
        {
            "category":"Banks & Credit Unions",
            "subcategory":"Bank",
            "type":"Services"
        }
    ],
    "sg:phone":"+33 3374011149",
    "sg:province":"Picardie",
    "wof:name":"Cr\u00e9dit Mutuel Du Canton De, L'arbresle",
    "wof:placetype":"venue"
},
  "geometry": {"coordinates":[4.615963,45.83572],"type":"Point"}
}