{
  "type": "Feature",
  "properties": {
    "addr:full":"Route De Gorron 53500 St Denis De Gastines Pays de Loire 53500",
    "addr:postcode":"53500;53500",
    "addr:street":"Route De Gorron;Gastines",
    "iso:country":"FR",
    "sg:address":"Route De Gorron 53500 St Denis De Gastines",
    "sg:classifiers":[
        {
            "category":"Shopping",
            "type":"Retail Goods"
        }
    ],
    "sg:phone":"+33 2 43 00 53 08",
    "sg:postcode":"53500",
    "sg:province":"Pays de Loire",
    "sg:tags":[
        "metallurgy",
        "finished",
        "-",
        "metalworking",
        "metallic"
    ],
    "wof:name":"Structures Boismetal",
    "wof:placetype":"venue"
},
  "geometry": {"coordinates":[-0.864707,48.342705],"type":"Point"}
}