{
  "type": "Feature",
  "properties": {
    "addr:full":"17, Av du 18\u00e8me BCP, 55700 Stenay Lorraine",
    "addr:postcode":"55700",
    "addr:street":"17 Av Du 18E\u0300Me Bcp",
    "iso:country":"FR",
    "sg:address":"17, Av du 18\u00e8me BCP, 55700 Stenay",
    "sg:orig_category":"Unclassifiable Establishments",
    "sg:phone":"+33 3 29 80 29 29",
    "sg:province":"Lorraine",
    "wof:name":"Solotra Transalliance S.a.",
    "wof:placetype":"venue"
},
  "geometry": {"coordinates":[5.178843,49.489513],"type":"Point"}
}