{
  "type": "Feature",
  "properties": {
    "iso:country":"FR",
    "sg:address":"30 R St Augustin 75002 Paris",
    "sg:classifiers":[
        {
            "category":"Professional",
            "subcategory":"Advertising",
            "type":"Services"
        }
    ],
    "sg:phone":"+33 1 42 68 82 82",
    "sg:postcode":"75002",
    "sg:province":"Ile de France",
    "sg:tags":[
        "communication",
        "medium"
    ],
    "wof:name":"Flexocolor",
    "wof:placetype":"venue"
},
  "geometry": {"coordinates":[2.33384,48.868988],"type":"Point"}
}