{
  "type": "Feature",
  "properties": {
    "iso:country":"FR",
    "sg:address":"71260 Cless\u00e9",
    "sg:city":"Cless\u00e9",
    "sg:orig_category":"Unclassifiable Establishments",
    "sg:phone":"+33 3 85 36 93 88",
    "sg:postcode":"71260",
    "sg:province":"Bourgogne",
    "wof:name":"Cave La Vigne Blanche",
    "wof:placetype":"venue"
},
  "geometry": {"coordinates":[4.81665,46.413845],"type":"Point"}
}