{
  "type": "Feature",
  "properties": {
    "addr:full":"5 rue du Chapeau 33000 Bordeaux Bordeaux Aquitaine 33000",
    "addr:housenumber":"5",
    "addr:postcode":"33000;33000",
    "addr:street":"Rue Du Chapeau",
    "iso:country":"FR",
    "sg:address":"5 rue du Chapeau 33000 Bordeaux",
    "sg:city":"Bordeaux",
    "sg:classifiers":[
        {
            "category":"Communications",
            "subcategory":"Film & Video Production",
            "type":"Services"
        }
    ],
    "sg:phone":"+33 5 56 48 47 50",
    "sg:postcode":"33000",
    "sg:province":"Aquitaine",
    "sg:tags":[
        "consulting",
        "evaluation"
    ],
    "wof:name":"Vertumne International & Associ\u00e9s Sa",
    "wof:placetype":"venue"
},
  "geometry": {"coordinates":[-0.57156,44.842426],"type":"Point"}
}