{
  "type": "Feature",
  "properties": {
    "iso:country":"FR",
    "sg:address":"B.P. 119, 45409 Saran C\u00e9dex^^1771, Rue de Montoran, 45770 Saran",
    "sg:city":"Saran",
    "sg:orig_category":"Non-Classified Establishments",
    "sg:phone":"+33 2 38 86 21 84",
    "sg:postcode":"45770",
    "sg:province":"Centre",
    "wof:name":"Transports Ronceray S.a.",
    "wof:placetype":"venue"
},
  "geometry": {"coordinates":[1.874622,47.950245],"type":"Point"}
}