{
  "type": "Feature",
  "properties": {
    "addr:full":"91 Rue Des Martyrs De La R\u00e9sistance 60110 Meru Picardie 60110",
    "addr:housenumber":"91",
    "addr:postcode":"60110;60110",
    "addr:street":"Rue Des Martyrs De La Re\u0301Sistance",
    "iso:country":"FR",
    "sg:address":"91 Rue Des Martyrs De La R\u00e9sistance 60110 Meru",
    "sg:classifiers":[
        {
            "category":"Banks & Credit Unions",
            "subcategory":"Financial Services",
            "type":"Services"
        }
    ],
    "sg:phone":"+33 3 44 52 66 60",
    "sg:postcode":"60110",
    "sg:province":"Picardie",
    "sg:tags":[
        "banking",
        "insurance",
        "institution",
        "finance"
    ],
    "wof:name":"Societe Generale",
    "wof:placetype":"venue"
},
  "geometry": {"coordinates":[2.134114,49.235455],"type":"Point"}
}