{
  "type": "Feature",
  "properties": {
    "iso:country":"FR",
    "sg:address":"B.P. 304, 84706 Sorgues C\u00e9dex^^Impasse Gutenberg - ZI, 84700 Sorgues",
    "sg:city":"Berg",
    "sg:orig_category":"Non-Classified Establishments",
    "sg:phone":"+33 4 90 83 32 11",
    "sg:postcode":"67320",
    "sg:province":"Alsace",
    "wof:name":"Seyfert Provence S.a.s.",
    "wof:placetype":"venue"
},
  "geometry": {"coordinates":[4.873481,44.00827],"type":"Point"}
}