{
  "type": "Feature",
  "properties": {
    "addr:full":"12, Quai du Rh\u00f4ne - ZI de la Tuill\u00e8re, 01700 Miribel Rhone-Alpes 01700",
    "addr:housenumber":"12",
    "addr:postcode":"01700;01700",
    "addr:street":"Quai Du Rho\u0302Ne Zi De La Tuille\u0300Re",
    "iso:country":"FR",
    "sg:address":"12, Quai du Rh\u00f4ne - ZI de la Tuill\u00e8re, 01700 Miribel",
    "sg:orig_category":"Non-Classified Establishments",
    "sg:phone":"+33 4 78 55 09 93",
    "sg:postcode":"01700",
    "sg:province":"Rhone-Alpes",
    "wof:name":"C.m.p. S.a.r.l. - Construction M\u00e9canique De Pr\u00e9cision",
    "wof:placetype":"venue"
},
  "geometry": {"coordinates":[4.96153,45.828629],"type":"Point"}
}