{
  "type": "Feature",
  "properties": {
    "iso:country":"FR",
    "sg:address":"5, Av. des Bosquets - Les Ponts de Baillet, 95560 Baillet en France",
    "sg:orig_category":"Unclassifiable Establishments",
    "sg:phone":"+33 1 34 08 39 39",
    "sg:province":"Ile de France",
    "wof:name":"N.m.b. Minebea S.a.r.l.",
    "wof:placetype":"venue"
},
  "geometry": {"coordinates":[2.309886,49.070625],"type":"Point"}
}