{
  "type": "Feature",
  "properties": {
    "iso:country":"FR",
    "sg:address":"Rue Gauds 07290 Satillieu",
    "sg:classifiers":[
        {
            "category":"Utilities",
            "subcategory":"Electric",
            "type":"Services"
        }
    ],
    "sg:phone":"+33 4 75 34 94 88",
    "sg:postcode":"07290",
    "sg:province":"Rhone-Alpes",
    "sg:tags":[
        "electricity",
        "electronic",
        "electrical",
        "equipment"
    ],
    "wof:name":"Nca Sarl",
    "wof:placetype":"venue"
},
  "geometry": {"coordinates":[4.612221,45.149124],"type":"Point"}
}