{
  "type": "Feature",
  "properties": {
    "addr:full":"19, Av du Mal Foch, 59700 Marcq en Baroeul Nord Pas-de-Calais",
    "addr:postcode":"59700",
    "addr:street":"19 Av Du Mal Foch;En Baroeul Nord",
    "iso:country":"FR",
    "sg:address":"19, Av du Mal Foch, 59700 Marcq en Baroeul",
    "sg:orig_category":"Unclassifiable Establishments",
    "sg:phone":"+33 3 20 72 00 72",
    "sg:province":"Nord Pas-de-Calais",
    "wof:name":"Sopanord S.a.",
    "wof:placetype":"venue"
},
  "geometry": {"coordinates":[3.101395,50.66769],"type":"Point"}
}