{
  "type": "Feature",
  "properties": {
    "addr:full":"164, Route de Valmant, 76400 F\u00e9camp Haute Normandie",
    "addr:housenumber":"164",
    "addr:postcode":"76400",
    "addr:street":"Route De Valmant;Haute Normandie",
    "iso:country":"FR",
    "sg:address":"164, Route de Valmant, 76400 F\u00e9camp",
    "sg:orig_category":"Unclassifiable Establishments",
    "sg:phone":"+33 2 35 29 08 86",
    "sg:province":"Haute Normandie",
    "wof:name":"Normandie Filtre S.a.r.l.",
    "wof:placetype":"venue"
},
  "geometry": {"coordinates":[0.401843,49.755409],"type":"Point"}
}