{
  "type": "Feature",
  "properties": {
    "addr:full":"B.P. 6 Landemont C\u00e9dex^^La Ferdini\u00e8re 49270 Landemont Pays de Loire 49270",
    "addr:postcode":"49270;49270",
    "addr:street":"B.P. 6 Landemont Ce\u0301Dex^^La Ferdinie\u0300Re",
    "iso:country":"FR",
    "sg:address":"B.P. 6",
    "sg:city":"Landemont C\u00e9dex^^La Ferdini\u00e8re 49270 Landemont",
    "sg:orig_category":"Non-Classified Establishments",
    "sg:phone":"+33 2 40 98 79 18",
    "sg:postcode":"49270",
    "sg:province":"Pays de Loire",
    "wof:name":"Bomex",
    "wof:placetype":"venue"
},
  "geometry": {"coordinates":[-1.184474,47.253479],"type":"Point"}
}