{
  "type": "Feature",
  "properties": {
    "addr:full":"B.P. 410, 56010 Vannes C\u00e9dex^^28, Rue Edgar Touffreau, 56880 Plo\u00ebren Ploeren Bretagne 56880",
    "addr:housenumber":"b.p. 410",
    "addr:postcode":"56010;56880;56880",
    "addr:street":"Rue Edgar Touffreau",
    "iso:country":"FR",
    "sg:address":"B.P. 410, 56010 Vannes C\u00e9dex^^28, Rue Edgar Touffreau, 56880 Plo\u00ebren",
    "sg:city":"Ploeren",
    "sg:orig_category":"Non-Classified Establishments",
    "sg:phone":"+33 2 97 63 13 52",
    "sg:postcode":"56880",
    "sg:province":"Bretagne",
    "wof:name":"Carri\u00e8res Lotod\u00e9 S.a.s.",
    "wof:placetype":"venue"
},
  "geometry": {"coordinates":[-2.857454,47.6586],"type":"Point"}
}