{
  "type": "Feature",
  "properties": {
    "iso:country":"FR",
    "sg:address":"B.P. 707, 29397 Quimperl\u00e9 C\u00e9dex^^ZI de Kervidanou 1, 29300 Quimperl\u00e9",
    "sg:city":"Quimperl\u00e9",
    "sg:orig_category":"Non-Classified Establishments",
    "sg:phone":"+33 2 98 96 35 00",
    "sg:postcode":"29300",
    "sg:province":"Bretagne",
    "wof:name":"Etablissements Liorzou S.a.",
    "wof:placetype":"venue"
},
  "geometry": {"coordinates":[-3.461656,47.859921],"type":"Point"}
}