{
  "type": "Feature",
  "properties": {
    "iso:country":"FR",
    "sg:address":"ZA du Barderff",
    "sg:city":"Mor\u00e9ac",
    "sg:orig_category":"Unclassifiable Establishments",
    "sg:phone":"+33 2 97 60 52 55",
    "sg:postcode":"56500",
    "sg:province":"Bretagne",
    "wof:name":"Mat Elevage S.a.r.l.",
    "wof:placetype":"venue"
},
  "geometry": {"coordinates":[-2.821514,47.919552],"type":"Point"}
}