{
  "type": "Feature",
  "properties": {
    "iso:country":"FR",
    "sg:address":"28, Bd Roger Salengro, 78200 Mantes la Jolie",
    "sg:orig_category":"Unclassifiable Establishments",
    "sg:phone":"+33 1 34 78 88 00",
    "sg:province":"Ile de France",
    "wof:name":"Wa~rtsila N.s.d. France S.a.",
    "wof:placetype":"venue"
},
  "geometry": {"coordinates":[1.707515,48.987717],"type":"Point"}
}