{
  "type": "Feature",
  "properties": {
    "addr:full":"B.P. 14, 45740 Lailly en Val^^ZAC des Gardoirs, 45740 Lailly en Val Lailly-en-Val Centre 45740",
    "addr:postcode":"45740;45740;45740",
    "addr:street":"B.P. 14;Val Lailly-En-Val",
    "iso:country":"FR",
    "sg:address":"B.P. 14, 45740 Lailly en Val^^ZAC des Gardoirs, 45740 Lailly en Val",
    "sg:city":"Lailly-en-Val",
    "sg:orig_category":"Non-Classified Establishments",
    "sg:phone":"+33 2 38 44 74 43",
    "sg:postcode":"45740",
    "sg:province":"Centre",
    "wof:name":"Etablissements Griveau S.a.r.l.",
    "wof:placetype":"venue"
},
  "geometry": {"coordinates":[1.686203,47.770439],"type":"Point"}
}