{
  "type": "Feature",
  "properties": {
    "addr:full":"B.P. 35, 49340 Tr\u00e9mentines C\u00e9dex^^54, Rue de Normandie, 49340 Tr\u00e9mentines Pays de Loire 49340",
    "addr:postcode":"49340;49340;49340",
    "addr:street":"B.P. 35;Rue De Normandie",
    "iso:country":"FR",
    "sg:address":"B.P. 35, 49340 Tr\u00e9mentines C\u00e9dex^^54, Rue de Normandie, 49340 Tr\u00e9mentines",
    "sg:orig_category":"Non-Classified Establishments",
    "sg:phone":"+33 2 41 56 78 21",
    "sg:postcode":"49340",
    "sg:province":"Pays de Loire",
    "wof:name":"Adstore S.a.",
    "wof:placetype":"venue"
},
  "geometry": {"coordinates":[-0.685015,47.095284],"type":"Point"}
}