{
  "type": "Feature",
  "properties": {
    "addr:full":"Quartier Rivales 26160 LE POET LAVAL Rhone-Alpes 26160",
    "addr:postcode":"26160;26160",
    "addr:street":"Poet;Rhone-Alpes",
    "iso:country":"FR",
    "sg:address":"Quartier Rivales 26160 LE POET LAVAL",
    "sg:classifiers":[
        {
            "category":"Farming",
            "subcategory":"Fish & Marine Products",
            "type":"Manufacturing & Wholesale Goods"
        }
    ],
    "sg:phone":"+33 4 75 46 41 03",
    "sg:postcode":"26160",
    "sg:province":"Rhone-Alpes",
    "sg:tags":[
        "ceramic"
    ],
    "wof:name":"Fa\u00efencerie Du Po\u00ebt Laval S.a.",
    "wof:placetype":"venue"
},
  "geometry": {"coordinates":[5.02845,44.526775],"type":"Point"}
}