{
  "type": "Feature",
  "properties": {
    "addr:full":"14, Rue Joseph-Marie Jacquard, 67400 Illkirch Graffenstaden Geispolsheim Alsace 67400",
    "addr:housenumber":"14",
    "addr:postcode":"67400;67400",
    "addr:street":"Rue Joseph-Marie Jacquard",
    "iso:country":"FR",
    "sg:address":"14, Rue Joseph-Marie Jacquard, 67400 Illkirch Graffenstaden",
    "sg:city":"Geispolsheim",
    "sg:orig_category":"Non-Classified Establishments",
    "sg:phone":"+33 3 88 66 09 97",
    "sg:postcode":"67400",
    "sg:province":"Alsace",
    "wof:name":"S.k. Route S.a.r.l.",
    "wof:placetype":"venue"
},
  "geometry": {"coordinates":[7.713558,48.507149],"type":"Point"}
}