{
  "type": "Feature",
  "properties": {
    "iso:country":"FR",
    "sg:address":"Badie 40170 Lit Et Mixe",
    "sg:city":"L\u00e9vignacq",
    "sg:classifiers":[
        {
            "category":"Home & Garden",
            "subcategory":"Furniture",
            "type":"Retail Goods"
        }
    ],
    "sg:phone":"+33 5 58 09 03 74",
    "sg:postcode":"40170",
    "sg:province":"Aquitaine",
    "sg:tags":[
        "wood"
    ],
    "wof:name":"Castets Sa",
    "wof:placetype":"venue"
},
  "geometry": {"coordinates":[-1.241009,44.039539],"type":"Point"}
}