{
  "type": "Feature",
  "properties": {
    "iso:country":"FR",
    "sg:address":"8, Rue Ratisbonne, 59000 Lille",
    "sg:orig_category":"Non-Classified Establishments",
    "sg:phone":"+33 3 20 30 61 04",
    "sg:postcode":"59000",
    "sg:province":"Nord Pas-de-Calais",
    "wof:name":"Carrefour Europ\u00e9en Des Voyages S.a.r.l.",
    "wof:placetype":"venue"
},
  "geometry": {"coordinates":[3.055995,50.630344],"type":"Point"}
}