{
  "type": "Feature",
  "properties": {
    "iso:country":"FR",
    "sg:address":"17, Rue de la Gravelle - Sorendal, 08800 Les Hautes Rivi\u00e8res",
    "sg:city":"Deville",
    "sg:orig_category":"GROSSISTE: PI\u00c8CES FORG\u00c9ES, BOULONNERIE, TIGES FILET\u00c9ES",
    "sg:phone":"+33 3 24 53 42 08",
    "sg:postcode":"08800",
    "sg:province":"Champagne",
    "wof:name":"Wiart Autier S.a.",
    "wof:placetype":"venue"
},
  "geometry": {"coordinates":[4.767382,49.882172],"type":"Point"}
}