{
  "type": "Feature",
  "properties": {
    "iso:country":"FR",
    "sg:address":"290, Rue Louis Neel - ZI du Levatel, 38140 Rives",
    "sg:orig_category":"Non-Classified Establishments",
    "sg:phone":"+33 4 76 91 14 15",
    "sg:province":"Rhone-Alpes",
    "wof:name":"G.r.i. S.a.s. - Grenoble Rodage Industrie",
    "wof:placetype":"venue"
},
  "geometry": {"coordinates":[5.428625,45.316471],"type":"Point"}
}