{
  "type": "Feature",
  "properties": {
    "addr:full":"23 rue Aimeric de Peguilhan 31300 Toulouse Midi Pyr\u00e9n\u00e9es",
    "addr:housenumber":"23",
    "addr:postcode":"31300",
    "addr:street":"Rue Aimeric De Peguilhan",
    "iso:country":"FR",
    "sg:address":"23 rue Aimeric de Peguilhan 31300 Toulouse",
    "sg:classifiers":[
        {
            "category":"Communications",
            "type":"Services"
        }
    ],
    "sg:phone":"+33 5 61 15 03 77",
    "sg:province":"Midi Pyr\u00e9n\u00e9es",
    "sg:tags":[
        "translation"
    ],
    "wof:name":"Tierce S.a.r.l.",
    "wof:placetype":"venue"
},
  "geometry": {"coordinates":[1.391839,43.598473],"type":"Point"}
}