{
  "type": "Feature",
  "properties": {
    "addr:full":"5, All\u00e9e des Gen\u00eats - Parc d'Activit\u00e9, 04200 Sisteron Pays de Loire",
    "addr:housenumber":"5",
    "addr:postcode":"04200",
    "addr:street":"Alle\u0301E Des Gene\u0302Ts Parc D'Activite \u0301",
    "iso:country":"FR",
    "sg:address":"5, All\u00e9e des Gen\u00eats - Parc d'Activit\u00e9, 04200 Sisteron",
    "sg:orig_category":"Non-Classified Establishments",
    "sg:phone":"+33 4 92 61 09 05",
    "sg:province":"Pays de Loire",
    "wof:name":"Dufour S.a.",
    "wof:placetype":"venue"
},
  "geometry": {"coordinates":[5.93131,44.211571],"type":"Point"}
}