{
  "type": "Feature",
  "properties": {
    "addr:full":"B.P. 262000, 13797 Aix en Provence C\u00e9dex^^L'Europarc de Pichaury - B\u00e2t. B8, 13100 Aix en Provence Nord Pas-de-Calais",
    "addr:housenumber":"262000;ba\u0302t b8",
    "addr:postcode":"13797;13100",
    "addr:street":"En Provence Nord",
    "iso:country":"FR",
    "sg:address":"B.P. 262000, 13797 Aix en Provence C\u00e9dex^^L'Europarc de Pichaury - B\u00e2t. B8, 13100 Aix en Provence",
    "sg:orig_category":"Non-Classified Establishments",
    "sg:phone":"+33 4 42 39 45 33",
    "sg:province":"Nord Pas-de-Calais",
    "wof:name":"Octopus S.a.",
    "wof:placetype":"venue"
},
  "geometry": {"coordinates":[5.471563,43.513065],"type":"Point"}
}