{
  "type": "Feature",
  "properties": {
    "iso:country":"FR",
    "sg:address":"1 route de Roquigny 62124 BUS",
    "sg:classifiers":[
        {
            "category":"Wholesale",
            "subcategory":"Machinery & Supplies",
            "type":"Manufacturing & Wholesale Goods"
        }
    ],
    "sg:phone":"+33 3 21 73 32 99",
    "sg:postcode":"62124",
    "sg:province":"Nord Pas-de-Calais",
    "sg:tags":[
        "agricultural",
        "equipment"
    ],
    "wof:name":"Dugave Sa",
    "wof:placetype":"venue"
},
  "geometry": {"coordinates":[2.95979,50.064705],"type":"Point"}
}