{
  "type": "Feature",
  "properties": {
    "addr:full":"B.P. 21536, 45005 Orl\u00e9ans C\u00e9dex 1^^7, Rue de la Vieille Lev\u00e9e, 45000 Orl\u00e9ans Orl\u00e9ans Centre 45000",
    "addr:housenumber":"^ 7",
    "addr:postcode":"45005;45000;45000",
    "addr:street":"Rue De La Vieille Leve\u0301E",
    "iso:country":"FR",
    "sg:address":"B.P. 21536, 45005 Orl\u00e9ans C\u00e9dex 1^^7, Rue de la Vieille Lev\u00e9e, 45000 Orl\u00e9ans",
    "sg:city":"Orl\u00e9ans",
    "sg:orig_category":"Non-Classified Establishments",
    "sg:phone":"+33 2 38 56 98 68",
    "sg:postcode":"45000",
    "sg:province":"Centre",
    "wof:name":"Armony S.a.",
    "wof:placetype":"venue"
},
  "geometry": {"coordinates":[1.904965,47.901428],"type":"Point"}
}