{
  "type": "Feature",
  "properties": {
    "addr:full":"1450, Rte Saint Anne du Portzic, 29200 Brest Brest Bretagne 29200",
    "addr:housenumber":"1450",
    "addr:postcode":"29200;29200",
    "addr:street":"Rte Saint Anne Du Portzic",
    "iso:country":"FR",
    "sg:address":"1450, Rte Saint Anne du Portzic, 29200 Brest",
    "sg:city":"Brest",
    "sg:orig_category":"Unclassifiable Establishments",
    "sg:phone":"+33 2 98 45 80 30",
    "sg:postcode":"29200",
    "sg:province":"Bretagne",
    "wof:name":"Constructions M\u00e9talliques Lelarge S.a.r.l.",
    "wof:placetype":"venue"
},
  "geometry": {"coordinates":[-4.546539,48.366436],"type":"Point"}
}