{
  "type": "Feature",
  "properties": {
    "iso:country":"FR",
    "sg:address":"B.P. 24, 69144 Rillieux la Pape C\u00e9dex^^23, Mont\u00e9e Castellane, 69140 Rillieux la Pape",
    "sg:orig_category":"Non-Classified Establishments",
    "sg:phone":"+33 4 72 01 51 01",
    "sg:postcode":"69140",
    "sg:province":"Rhone-Alpes",
    "wof:name":"St\u00e8pe S.a.",
    "wof:placetype":"venue"
},
  "geometry": {"coordinates":[4.897105,45.820801],"type":"Point"}
}