{
  "type": "Feature",
  "properties": {
    "addr:full":"ZI Route de la Fert\u00e9 Mac\u00e9 61450 LA FERRIERE AUX ETANGS Banvou Basse Normandie 61450",
    "addr:postcode":"61450;61450",
    "addr:street":"Route De La Ferte\u0301 Mace\u0301;Ferriere Aux Etangs",
    "iso:country":"FR",
    "sg:address":"ZI Route de la Fert\u00e9 Mac\u00e9 61450 LA FERRIERE AUX ETANGS",
    "sg:city":"Banvou",
    "sg:classifiers":[
        {
            "category":"Manufacturing",
            "subcategory":"Metals",
            "type":"Manufacturing & Wholesale Goods"
        }
    ],
    "sg:phone":"+33 2 33 66 91 48",
    "sg:postcode":"61450",
    "sg:province":"Basse Normandie",
    "sg:tags":[
        "ironmongery"
    ],
    "wof:name":"Styl'fer Sa",
    "wof:placetype":"venue"
},
  "geometry": {"coordinates":[-0.519624,48.662193],"type":"Point"}
}