{
  "type": "Feature",
  "properties": {
    "addr:full":"761, Rte des Vernes - ZI, 74370 Pringy Rhone-Alpes",
    "addr:housenumber":"761",
    "addr:postcode":"74370",
    "addr:street":"Rte Des Vernes Zi",
    "iso:country":"FR",
    "sg:address":"761, Rte des Vernes - ZI, 74370 Pringy",
    "sg:orig_category":"Non-Classified Establishments",
    "sg:phone":"+33 4 50 27 25 76",
    "sg:province":"Rhone-Alpes",
    "wof:name":"Transports Portier S.a.r.l.",
    "wof:placetype":"venue"
},
  "geometry": {"coordinates":[6.109395,45.934166],"type":"Point"}
}