{
  "type": "Feature",
  "properties": {
    "iso:country":"FR",
    "sg:address":"1, All\u00e9e de Londres, 91140 Villejust",
    "sg:orig_category":"Unclassifiable Establishments",
    "sg:phone":"+33 1 64 86 29 50",
    "sg:province":"Ile de France",
    "wof:name":"Soci\u00e9t\u00e9 Paridu Letourneur S.a.",
    "wof:placetype":"venue"
},
  "geometry": {"coordinates":[2.203325,48.684765],"type":"Point"}
}