{
  "type": "Feature",
  "properties": {
    "addr:full":"A\u00e9roport 78117 Toussus Le Noble Ile de France 78117",
    "addr:postcode":"78117;78117",
    "addr:street":"Ae\u0301Roport",
    "iso:country":"FR",
    "sg:address":"A\u00e9roport 78117 Toussus Le Noble",
    "sg:classifiers":[
        {
            "category":"Professional",
            "subcategory":"Business Services",
            "type":"Services"
        }
    ],
    "sg:phone":"+33 1 39 56 80 50",
    "sg:postcode":"78117",
    "sg:province":"Ile de France",
    "sg:tags":[
        "equipment",
        "advice",
        "aeronautic",
        "transport",
        "vehicle"
    ],
    "wof:name":"France Aviation Sa",
    "wof:placetype":"venue"
},
  "geometry": {"coordinates":[2.092255,48.736919],"type":"Point"}
}