{
  "type": "Feature",
  "properties": {
    "addr:full":"5, Rue de Mai, 80000 Amiens Picardie 80000",
    "addr:housenumber":"5",
    "addr:postcode":"80000;80000",
    "addr:street":"Rue De Mai",
    "iso:country":"FR",
    "sg:address":"5, Rue de Mai, 80000 Amiens",
    "sg:orig_category":"Non-Classified Establishments",
    "sg:phone":"+33 3 22 91 66 97",
    "sg:postcode":"80000",
    "sg:province":"Picardie",
    "wof:name":"Beno\u00eet Et Compagnie",
    "wof:placetype":"venue"
},
  "geometry": {"coordinates":[2.300787,49.9002],"type":"Point"}
}