{
  "type": "Feature",
  "properties": {
    "iso:country":"FR",
    "sg:address":"3, Rue de l'Industrie, 68260 Kingersheim",
    "sg:city":"Kingersheim",
    "sg:orig_category":"Non-Classified Establishments",
    "sg:phone":"+33 3 89 52 61 52",
    "sg:postcode":"68260",
    "sg:province":"Alsace",
    "wof:name":"Chocolaterie Bruntz S.a.r.l.",
    "wof:placetype":"venue"
},
  "geometry": {"coordinates":[7.312964,47.786972],"type":"Point"}
}