{
  "type": "Feature",
  "properties": {
    "iso:country":"FR",
    "sg:address":"6, Av. de l'Ard\u00e9che, 27200 Vernon",
    "sg:orig_category":"Non-Classified Establishments",
    "sg:phone":"+33 2 32 51 44 53",
    "sg:postcode":"27200",
    "sg:province":"Haute Normandie",
    "wof:name":"Construction Contemporaine S.a.",
    "wof:placetype":"venue"
},
  "geometry": {"coordinates":[1.480392,49.086922],"type":"Point"}
}