{
  "type": "Feature",
  "properties": {
    "addr:full":"4 av Maximin Isnard; Grasse Rhone-Alpes",
    "addr:street":"Av Maximin Isnard",
    "iso:country":"FR",
    "sg:address":"4 av Maximin Isnard; Grasse",
    "sg:classifiers":[
        {
            "category":"Banks & Credit Unions",
            "subcategory":"Bank",
            "type":"Services"
        }
    ],
    "sg:phone":"+33 3393403700",
    "sg:province":"Rhone-Alpes",
    "wof:name":"Soci\u00e9t\u00e9 G\u00e9n\u00e9rale",
    "wof:placetype":"venue"
},
  "geometry": {"coordinates":[6.922892,43.660332],"type":"Point"}
}