{
  "type": "Feature",
  "properties": {
    "addr:full":"3, Rue Rualm\u00e9nil, 88000 Epinal Lorraine",
    "addr:housenumber":"3",
    "addr:postcode":"88000",
    "addr:street":"Rue Rualme\u0301Nil",
    "iso:country":"FR",
    "sg:address":"3, Rue Rualm\u00e9nil, 88000 Epinal",
    "sg:orig_category":"Non-Classified Establishments",
    "sg:phone":"+33 3 29 82 39 43",
    "sg:province":"Lorraine",
    "wof:name":"Papkoff J.c. S.a.r.l.",
    "wof:placetype":"venue"
},
  "geometry": {"coordinates":[6.447328,48.174431],"type":"Point"}
}