{
  "type": "Feature",
  "properties": {
    "iso:country":"FR",
    "sg:address":"B.P. 16, 24340 Mareuil C\u00e9dex^^Rte de Saint Priest, 24340 Mareuil",
    "sg:city":"Mareuil",
    "sg:orig_category":"Non-Classified Establishments",
    "sg:phone":"+33 5 53 60 94 17",
    "sg:postcode":"24340",
    "sg:province":"Aquitaine",
    "wof:name":"Manufacture De Saint Priest Articles Chaussants S.a.r.l.",
    "wof:placetype":"venue"
},
  "geometry": {"coordinates":[0.513595,45.392006],"type":"Point"}
}