{
  "type": "Feature",
  "properties": {
    "iso:country":"FR",
    "sg:address":"47",
    "sg:city":"Louis Blanc 92984 Paris La D\u00e9fense Cedex",
    "sg:classifiers":[
        {
            "category":"Manufacturing",
            "subcategory":"Rubber & Plastics",
            "type":"Manufacturing & Wholesale Goods"
        }
    ],
    "sg:phone":"+33 1 41 16 49 45",
    "sg:province":"\u00cele-de-France",
    "wof:name":"Raimure Sa",
    "wof:placetype":"venue"
},
  "geometry": {"coordinates":[2.24119,48.888939],"type":"Point"}
}