{
  "type": "Feature",
  "properties": {
    "addr:full":"5, Rue de Verdun, 93120 La Courneuve Ile de France",
    "addr:housenumber":"5",
    "addr:postcode":"93120",
    "addr:street":"Rue De Verdun",
    "iso:country":"FR",
    "sg:address":"5, Rue de Verdun, 93120 La Courneuve",
    "sg:orig_category":"Non-Classified Establishments",
    "sg:phone":"+33 1 43 11 34 24",
    "sg:province":"Ile de France",
    "wof:name":"Soci\u00e9t\u00e9 Parisienne Conditionnement Et Distribution S.a.r.l.",
    "wof:placetype":"venue"
},
  "geometry": {"coordinates":[2.418049,48.929859],"type":"Point"}
}