{
  "type": "Feature",
  "properties": {
    "iso:country":"FR",
    "sg:address":"B.P. 5, 59392 Wattrelos C\u00e9dex^^184, Rue Jean Baptiste Lebas, 59392 Wattrelos C\u00e9dex",
    "sg:orig_category":"Non-Classified Establishments",
    "sg:phone":"+33 3 20 89 38 88",
    "sg:province":"Picardie",
    "wof:name":"C.s. Informatique S.a.r.l.",
    "wof:placetype":"venue"
},
  "geometry": {"coordinates":[3.21509,50.701679],"type":"Point"}
}