{
  "type": "Feature",
  "properties": {
    "addr:full":"2bis, Rue du G\u00e9n\u00e9ral Leclercq, 59320 Haubourdin Nord Pas-de-Calais 59320",
    "addr:housenumber":"2bis",
    "addr:postcode":"59320;59320",
    "addr:street":"Rue Du Ge\u0301Ne\u0301Ral Leclercq",
    "iso:country":"FR",
    "sg:address":"2bis, Rue du G\u00e9n\u00e9ral Leclercq, 59320 Haubourdin",
    "sg:orig_category":"Non-Classified Establishments",
    "sg:phone":"+33 3 20 07 24 60",
    "sg:postcode":"59320",
    "sg:province":"Nord Pas-de-Calais",
    "wof:name":"Etablissements Lesaffre S.a.r.l.",
    "wof:placetype":"venue"
},
  "geometry": {"coordinates":[2.987078,50.61137],"type":"Point"}
}