{
  "type": "Feature",
  "properties": {
    "iso:country":"FR",
    "sg:address":"460, Rue du Pommarin - ZI Centralp, 38430 Moirans",
    "sg:orig_category":"Unclassifiable Establishments",
    "sg:phone":"+33 4 76 57 40 00",
    "sg:province":"Rhone-Alpes",
    "wof:name":"Thal\u00e8s Electron Devices S.a.",
    "wof:placetype":"venue"
},
  "geometry": {"coordinates":[5.554805,45.327175],"type":"Point"}
}