{
  "type": "Feature",
  "properties": {
    "iso:country":"FR",
    "sg:address":"103 Chemin Ronde 78290 Croissy Sur Seine",
    "sg:classifiers":[
        {
            "category":"Utilities",
            "subcategory":"Electric",
            "type":"Services"
        }
    ],
    "sg:phone":"+33 1 30 15 07 07",
    "sg:postcode":"78290",
    "sg:province":"Ile de France",
    "sg:tags":[
        "electricity",
        "electronic",
        "electrical",
        "equipment"
    ],
    "wof:name":"Wieland Electric Sarl",
    "wof:placetype":"venue"
},
  "geometry": {"coordinates":[2.118449,48.889339],"type":"Point"}
}