{
  "type": "Feature",
  "properties": {
    "addr:full":"Avenue Churchill 24660 Coulounieix Chamiers Coulounieix-Chamiers Aquitaine 24660",
    "addr:postcode":"24660;24660",
    "addr:street":"Avenue Churchill",
    "iso:country":"FR",
    "sg:address":"Avenue Churchill 24660 Coulounieix Chamiers",
    "sg:city":"Coulounieix-Chamiers",
    "sg:classifiers":[
        {
            "category":"Manufacturing",
            "subcategory":"Printing",
            "type":"Manufacturing & Wholesale Goods"
        }
    ],
    "sg:phone":"+33 5 53 06 82 82",
    "sg:postcode":"24660",
    "sg:province":"Aquitaine",
    "sg:tags":[
        "publishing"
    ],
    "wof:name":"Imprimerie Bordas Sarl",
    "wof:placetype":"venue"
},
  "geometry": {"coordinates":[0.698661,45.184689],"type":"Point"}
}