{
  "type": "Feature",
  "properties": {
    "iso:country":"FR",
    "sg:address":"5 rue du Bailliage 78000 Versailles",
    "sg:orig_category":"Absorption Installations And Towers",
    "sg:phone":"+33 1 39 50 03 57",
    "sg:postcode":"78000",
    "sg:province":"Ile de France",
    "wof:name":"Techim S.a.r.l.",
    "wof:placetype":"venue"
},
  "geometry": {"coordinates":[2.13112,48.807541],"type":"Point"}
}