{
  "type": "Feature",
  "properties": {
    "iso:country":"FR",
    "sg:address":"5 Avenue Des Pres 94269 Fresnes Cedex",
    "sg:classifiers":[
        {
            "category":"Health Services",
            "subcategory":"Medical Lab",
            "type":"Services"
        }
    ],
    "sg:phone":"+33 1 49 84 78 00",
    "sg:province":"Nord Pas-de-Calais",
    "sg:tags":[
        "chemical",
        "pharmaceutical",
        "pharmacy"
    ],
    "wof:name":"Fresenius Medical Care France",
    "wof:placetype":"venue"
},
  "geometry": {"coordinates":[2.317931,48.764565],"type":"Point"}
}