{
  "type": "Feature",
  "properties": {
    "iso:country":"FR",
    "sg:address":"7ter, Rte de Compi\u00e8gne, 60410 Verberie",
    "sg:orig_category":"Unclassifiable Establishments",
    "sg:phone":"+33 3 44 40 67 95",
    "sg:province":"Picardie",
    "wof:name":"Cailliot Fetilleux Claudine",
    "wof:placetype":"venue"
},
  "geometry": {"coordinates":[2.740405,49.317345],"type":"Point"}
}