{
  "type": "Feature",
  "properties": {
    "addr:full":"87/89, Rue des Rosiers, 92500 Rueil Malmaison Ile de France",
    "addr:housenumber":"87 / 89",
    "addr:postcode":"92500",
    "addr:street":"Rue Des Rosiers",
    "iso:country":"FR",
    "sg:address":"87/89, Rue des Rosiers, 92500 Rueil Malmaison",
    "sg:orig_category":"Unclassifiable Establishments",
    "sg:phone":"+33 1 47 08 12 12",
    "sg:province":"Ile de France",
    "wof:name":"Formavision S.a.r.l.",
    "wof:placetype":"venue"
},
  "geometry": {"coordinates":[2.207918,48.870243],"type":"Point"}
}