{
  "type": "Feature",
  "properties": {
    "addr:full":"B.P. 201, 94203 Ivry sur Seine C\u00e9dex^^22, Rue Robert Witchitz, 94200 Ivry sur Seine Ile de France",
    "addr:housenumber":"b.p. 201",
    "addr:postcode":"94203;94200",
    "addr:street":"Rue Robert Witchitz",
    "iso:country":"FR",
    "sg:address":"B.P. 201, 94203 Ivry sur Seine C\u00e9dex^^22, Rue Robert Witchitz, 94200 Ivry sur Seine",
    "sg:orig_category":"Non-Classified Establishments",
    "sg:phone":"+33 1 49 87 06 60",
    "sg:province":"Ile de France",
    "wof:name":"Marmont S.a.",
    "wof:placetype":"venue"
},
  "geometry": {"coordinates":[2.384885,48.811668],"type":"Point"}
}