{
  "type": "Feature",
  "properties": {
    "addr:full":"B.P. 70220, 60744 Saint Maximin C\u00e9dex^^Rue Albert Einstein - ZAET des Haies, 60740 Saint Maximin Picardie",
    "addr:housenumber":"60744",
    "addr:postcode":"60740",
    "addr:street":"Saint Maximin Ce\u0301Dex^^Rue Albert",
    "iso:country":"FR",
    "sg:address":"B.P. 70220, 60744 Saint Maximin C\u00e9dex^^Rue Albert Einstein - ZAET des Haies, 60740 Saint Maximin",
    "sg:orig_category":"Non-Classified Establishments",
    "sg:phone":"+33 3 44 61 18 70",
    "sg:province":"Picardie",
    "wof:name":"James Walker France S.a.s.",
    "wof:placetype":"venue"
},
  "geometry": {"coordinates":[2.461512,49.238308],"type":"Point"}
}