{
  "type": "Feature",
  "properties": {
    "iso:country":"FR",
    "sg:address":"24, Rue Neuve, 62100 Calais",
    "sg:orig_category":"Unclassifiable Establishments",
    "sg:phone":"+33 3 21 34 61 06",
    "sg:province":"Nord Pas-de-Calais",
    "wof:name":"Codentex Calais S.a.",
    "wof:placetype":"venue"
},
  "geometry": {"coordinates":[1.855047,50.947758],"type":"Point"}
}