{
  "type": "Feature",
  "properties": {
    "addr:full":"282, Av du Pigeonnier - Br\u00e9goux , 46000 Cahors Midi Pyr\u00e9n\u00e9es",
    "addr:postcode":"46000",
    "addr:street":"282 Av Du Pigeonnier Bre\u0301Goux",
    "iso:country":"FR",
    "sg:address":"282, Av du Pigeonnier - Br\u00e9goux , 46000 Cahors",
    "sg:orig_category":"Non-Classified Establishments",
    "sg:phone":"+33 5 65 35 78 26",
    "sg:province":"Midi Pyr\u00e9n\u00e9es",
    "wof:name":"S.o.d. E.u.r.l.",
    "wof:placetype":"venue"
},
  "geometry": {"coordinates":[1.440775,44.44659],"type":"Point"}
}