{
  "type": "Feature",
  "properties": {
    "addr:full":"Cours de L'Esplanade; Privas Midi Pyr\u00e9n\u00e9es",
    "addr:street":"Cours De L'Esplanade",
    "iso:country":"FR",
    "sg:address":"Cours de L'Esplanade; Privas",
    "sg:classifiers":[
        {
            "category":"Banks & Credit Unions",
            "subcategory":"Bank",
            "type":"Services"
        }
    ],
    "sg:phone":"+33 3375641109",
    "sg:province":"Midi Pyr\u00e9n\u00e9es",
    "wof:name":"Banque Nationale De Paris",
    "wof:placetype":"venue"
},
  "geometry": {"coordinates":[4.597828,44.734711],"type":"Point"}
}