{
  "type": "Feature",
  "properties": {
    "iso:country":"FR",
    "sg:address":"avenue de Jalday 64500 ST JEAN DE LUZ",
    "sg:city":"Ciboure",
    "sg:classifiers":[
        {
            "category":"Food & Beverages",
            "subcategory":"Dairy",
            "type":"Retail Goods"
        }
    ],
    "sg:phone":"+33 5 59 51 33 45",
    "sg:postcode":"64500",
    "sg:province":"Aquitaine",
    "sg:tags":[
        "product",
        "milk"
    ],
    "wof:name":"A.d.f. Diffusion Sarl",
    "wof:placetype":"venue"
},
  "geometry": {"coordinates":[-1.624067,43.406597],"type":"Point"}
}