{
  "type": "Feature",
  "properties": {
    "addr:full":"10 All Laiton 77542 Savigny Le Temple Rhone-Alpes",
    "addr:housenumber":"10",
    "addr:postcode":"77542",
    "addr:street":"All Laiton;Rhone-Alpes",
    "iso:country":"FR",
    "sg:address":"10 All Laiton 77542 Savigny Le Temple",
    "sg:classifiers":[
        {
            "category":"Transit Center",
            "subcategory":"Freight",
            "type":"Transportation"
        }
    ],
    "sg:phone":"+33 1 64 41 75 04",
    "sg:province":"Rhone-Alpes",
    "sg:tags":[
        "metallurgy",
        "pipe",
        "metalworking",
        "sheet"
    ],
    "wof:name":"Essinox Industrie",
    "wof:placetype":"venue"
},
  "geometry": {"coordinates":[2.590772,48.590527],"type":"Point"}
}