{
  "type": "Feature",
  "properties": {
    "addr:full":"2, Rue Louis Armand, 74100 Annemasse Rhone-Alpes 74100",
    "addr:housenumber":"2",
    "addr:postcode":"74100;74100",
    "addr:street":"Rue Louis Armand",
    "iso:country":"FR",
    "sg:address":"2, Rue Louis Armand, 74100 Annemasse",
    "sg:orig_category":"Non-Classified Establishments",
    "sg:phone":"+33 4 50 37 43 08",
    "sg:postcode":"74100",
    "sg:province":"Rhone-Alpes",
    "wof:name":"A'stral S.a.",
    "wof:placetype":"venue"
},
  "geometry": {"coordinates":[6.237532,46.199265],"type":"Point"}
}