{
  "type": "Feature",
  "properties": {
    "addr:full":"3bis, Rue du Petit Robinson, 78350 Jouy en Josas Ile de France",
    "addr:housenumber":"3bis",
    "addr:postcode":"78350",
    "addr:street":"Rue Du Petit",
    "iso:country":"FR",
    "sg:address":"3bis, Rue du Petit Robinson, 78350 Jouy en Josas",
    "sg:orig_category":"Unclassifiable Establishments",
    "sg:phone":"+33 1 30 70 62 00",
    "sg:province":"Ile de France",
    "wof:name":"Omnimark Technologies Europe S.a.r.l.",
    "wof:placetype":"venue"
},
  "geometry": {"coordinates":[2.169291,48.779884],"type":"Point"}
}