{
  "type": "Feature",
  "properties": {
    "addr:full":"Pa De La Reine Blanche 60110 Lormaison Picardie 60110",
    "addr:postcode":"60110;60110",
    "addr:street":"De La Reine Blanche",
    "iso:country":"FR",
    "sg:address":"Pa De La Reine Blanche 60110 Lormaison",
    "sg:classifiers":[
        {
            "category":"Manufacturing",
            "subcategory":"Metals",
            "type":"Manufacturing & Wholesale Goods"
        }
    ],
    "sg:phone":"+33 3 44 52 42 90",
    "sg:postcode":"60110",
    "sg:province":"Picardie",
    "sg:tags":[
        "metallurgy",
        "steel",
        "metalworking"
    ],
    "wof:name":"Comptoir Des Produits Inoxydables (cpi)",
    "wof:placetype":"venue"
},
  "geometry": {"coordinates":[2.135155,49.235676],"type":"Point"}
}