{
  "type": "Feature",
  "properties": {
    "iso:country":"FR",
    "sg:address":"155, Rue Anatole France, 92300 Levallois Perret",
    "sg:orig_category":"Non-Classified Establishments",
    "sg:phone":"+33 1 41 05 80 00",
    "sg:province":"Ile de France",
    "wof:name":"Thompson Connect S.a.",
    "wof:placetype":"venue"
},
  "geometry": {"coordinates":[2.279174,48.898239],"type":"Point"}
}