{
  "type": "Feature",
  "properties": {
    "addr:full":"77, Av. du Vieux Chemin de Saint Denis, 92230 Gennevilliers Ile de France",
    "addr:postcode":"92230;ile",
    "addr:street":"77 Av. Du Vieux Chemin De Saint Denis",
    "iso:country":"FR",
    "sg:address":"77, Av. du Vieux Chemin de Saint Denis, 92230 Gennevilliers",
    "sg:orig_category":"Non-Classified Establishments",
    "sg:phone":"+33 1 47 98 41 52",
    "sg:province":"Ile de France",
    "wof:name":"T.t.a. Maritime S.a.",
    "wof:placetype":"venue"
},
  "geometry": {"coordinates":[2.317006,48.932159],"type":"Point"}
}