{
  "type": "Feature",
  "properties": {
    "addr:full":"1, Rue des Ch\u00e2taigniers, 29400 Landivisiau Landivisiau Bretagne 29400",
    "addr:housenumber":"1",
    "addr:postcode":"29400;29400",
    "addr:street":"Rue Des Cha\u0302Taigniers",
    "iso:country":"FR",
    "sg:address":"1, Rue des Ch\u00e2taigniers, 29400 Landivisiau",
    "sg:city":"Landivisiau",
    "sg:orig_category":"Unclassifiable Establishments",
    "sg:phone":"+33 2 98 68 00 20",
    "sg:postcode":"29400",
    "sg:province":"Bretagne",
    "wof:name":"Aldouest S.a.",
    "wof:placetype":"venue"
},
  "geometry": {"coordinates":[-4.068199,48.501656],"type":"Point"}
}