{
  "type": "Feature",
  "properties": {
    "addr:full":"21 bis, Rue des Peupliers, 92752 Nanterre C\u00e9dex \u00cele-de-France",
    "addr:housenumber":"21 bis",
    "addr:postcode":"92752",
    "addr:street":"Rue Des Peupliers",
    "iso:country":"FR",
    "sg:address":"21 bis, Rue des Peupliers, 92752 Nanterre C\u00e9dex",
    "sg:orig_category":"Non-Classified Establishments",
    "sg:phone":"+33 1 41 19 28 38",
    "sg:province":"\u00cele-de-France",
    "wof:name":"Tulip Computers France S.a.",
    "wof:placetype":"venue"
},
  "geometry": {"coordinates":[2.214287,48.912762],"type":"Point"}
}