{
  "type": "Feature",
  "properties": {
    "iso:country":"FR",
    "sg:address":"B.P. 171",
    "sg:city":"L'Aigle C\u00e9dex^^61300 L'Aigle",
    "sg:orig_category":"Non-Classified Establishments",
    "sg:phone":"+33 2 33 84 21 21",
    "sg:postcode":"61305",
    "sg:province":"Basse Normandie",
    "wof:name":"Fr\u00e9n\u00e9hard Et Michaux S.a.",
    "wof:placetype":"venue"
},
  "geometry": {"coordinates":[0.634017,48.760406],"type":"Point"}
}