{
  "type": "Feature",
  "properties": {
    "iso:country":"FR",
    "sg:address":"6, Rue Gustave Eiffel - ZI du Bas Pontet, 69360 Saint Symphorien d'Ozon",
    "sg:orig_category":"Non-Classified Establishments",
    "sg:phone":"+33 4 78 02 00 43",
    "sg:postcode":"69360",
    "sg:province":"Rhone-Alpes",
    "wof:name":"Gazechim Composites S.a.",
    "wof:placetype":"venue"
},
  "geometry": {"coordinates":[4.85609,45.634979],"type":"Point"}
}