{
  "type": "Feature",
  "properties": {
    "addr:full":"Usine Invensil 73870 Saint-Julien Mondenis Rhone-Alpes 73870",
    "addr:postcode":"73870;73870",
    "addr:street":"Rhone-Alpes",
    "iso:country":"FR",
    "sg:address":"Usine Invensil 73870 Saint-Julien Mondenis",
    "sg:classifiers":[
        {
            "category":"Manufacturing",
            "subcategory":"Metals",
            "type":"Manufacturing & Wholesale Goods"
        }
    ],
    "sg:phone":"+33 4 79 59 68 96",
    "sg:postcode":"73870",
    "sg:province":"Rhone-Alpes",
    "sg:tags":[
        "metallurgy",
        "steel",
        "metalworking"
    ],
    "wof:name":"Invensil Groupe Pechiney Scs",
    "wof:placetype":"venue"
},
  "geometry": {"coordinates":[6.408205,45.255169],"type":"Point"}
}