{
  "type": "Feature",
  "properties": {
    "addr:full":"317 Rue Garibaldi 69007 Lyon Rhone-Alpes",
    "addr:housenumber":"317",
    "addr:postcode":"69007",
    "addr:street":"Rue Garibaldi",
    "iso:country":"FR",
    "sg:address":"317 Rue Garibaldi 69007 Lyon",
    "sg:classifiers":[
        {
            "category":"Professional",
            "subcategory":"Business Services",
            "type":"Services"
        }
    ],
    "sg:phone":"+33 4 72 76 08 88",
    "sg:province":"Rhone-Alpes",
    "sg:tags":[
        "body",
        "advice"
    ],
    "wof:name":"Adapei Du Rhone Ass",
    "wof:placetype":"venue"
},
  "geometry": {"coordinates":[4.852849,45.748337],"type":"Point"}
}