{
  "type": "Feature",
  "properties": {
    "addr:full":"B.P. 7, 34980 Saint G\u00e9ly du Fesc^^158, All\u00e9e des Ecureuils, 34980 Saint G\u00e9ly du Fesc Languedoc-Roussillon 34980",
    "addr:housenumber":"7",
    "addr:postcode":"34980;34980;34980",
    "addr:street":"B.P.;Ge\u0301Ly;Alle\u0301E Des Ecureuils;Ge\u0301Ly",
    "iso:country":"FR",
    "sg:address":"B.P. 7, 34980 Saint G\u00e9ly du Fesc^^158, All\u00e9e des Ecureuils, 34980 Saint G\u00e9ly du Fesc",
    "sg:orig_category":"Non-Classified Establishments",
    "sg:phone":"+33 4 67 66 67 66",
    "sg:postcode":"34980",
    "sg:province":"Languedoc-Roussillon",
    "wof:name":"Cesml",
    "wof:placetype":"venue"
},
  "geometry": {"coordinates":[3.814063,43.679523],"type":"Point"}
}