{
  "type": "Feature",
  "properties": {
    "addr:full":"Rue du Th\u00e9\u00e2tre Mandeure Franche Comt\u00e9 25350",
    "addr:postcode":"25350",
    "addr:street":"Rue Du The\u0301A\u0302Tre;Franche Comte\u0301",
    "iso:country":"FR",
    "sg:address":"Rue du Th\u00e9\u00e2tre",
    "sg:city":"Mandeure",
    "sg:orig_category":"Unclassifiable Establishments",
    "sg:phone":"+33 3 81 35 21 22",
    "sg:postcode":"25350",
    "sg:province":"Franche Comt\u00e9",
    "wof:name":"Bordy S.a.",
    "wof:placetype":"venue"
},
  "geometry": {"coordinates":[6.796399,47.450577],"type":"Point"}
}