{
  "type": "Feature",
  "properties": {
    "addr:full":"3 rue Maurice Bouchor 75014 Paris Ile de France 75014",
    "addr:housenumber":"3",
    "addr:postcode":"75014;75014",
    "addr:street":"Rue Maurice Bouchor",
    "iso:country":"FR",
    "sg:address":"3 rue Maurice Bouchor 75014 Paris",
    "sg:classifiers":[
        {
            "category":"Home & Garden",
            "subcategory":"Hardware",
            "type":"Retail Goods"
        }
    ],
    "sg:phone":"+33 1 45 40 81 82",
    "sg:postcode":"75014",
    "sg:province":"Ile de France",
    "sg:tags":[
        "component",
        "electronic"
    ],
    "wof:name":"Telecom Parts Sarl",
    "wof:placetype":"venue"
},
  "geometry": {"coordinates":[2.308946,48.826385],"type":"Point"}
}