{
  "type": "Feature",
  "properties": {
    "iso:country":"FR",
    "sg:address":"716 Rue Nationale 69400 Villefranche Sur Sa\u00f4ne",
    "sg:classifiers":[
        {
            "category":"Shopping",
            "subcategory":"Clothing, Apparel, & Fashions",
            "type":"Retail Goods"
        }
    ],
    "sg:phone":"+33 4 74 68 03 07",
    "sg:postcode":"69400",
    "sg:province":"Rhone-Alpes",
    "sg:tags":[
        "textile",
        "clothing",
        "clothes"
    ],
    "wof:name":"Ets Dagnaud Sa",
    "wof:placetype":"venue"
},
  "geometry": {"coordinates":[4.718591,45.989025],"type":"Point"}
}