{
  "type": "Feature",
  "properties": {
    "addr:full":"14, Rue de la Com\u00e9die, 82000 Montauban Midi Pyr\u00e9n\u00e9es",
    "addr:housenumber":"14",
    "addr:postcode":"82000",
    "addr:street":"Rue De La Come\u0301Die",
    "iso:country":"FR",
    "sg:address":"14, Rue de la Com\u00e9die, 82000 Montauban",
    "sg:orig_category":"Unclassifiable Establishments",
    "sg:phone":"+33 5 63 03 69 43",
    "sg:province":"Midi Pyr\u00e9n\u00e9es",
    "wof:name":"Minolta S.a.",
    "wof:placetype":"venue"
},
  "geometry": {"coordinates":[1.354641,44.018932],"type":"Point"}
}