{
  "type": "Feature",
  "properties": {
    "iso:country":"FR",
    "sg:address":"52, Rue du 27 Ao\u00fbt 1944, 10270 Montreuil sur Barse",
    "sg:orig_category":"Unclassifiable Establishments",
    "sg:phone":"+33 3 25 41 29 77",
    "sg:province":"Champagne",
    "wof:name":"Melen Richard Andr\u00e9",
    "wof:placetype":"venue"
},
  "geometry": {"coordinates":[4.29743,48.222744],"type":"Point"}
}