{
  "type": "Feature",
  "properties": {
    "iso:country":"FR",
    "sg:address":"1, Rue Angiboust - ZAC de la Fontaine de Jouvence, 91460 Marcoussis",
    "sg:orig_category":"Unclassifiable Establishments",
    "sg:phone":"+33 1 69 80 63 05",
    "sg:province":"Ile de France",
    "wof:name":"Etablissement Mauran S.a.",
    "wof:placetype":"venue"
},
  "geometry": {"coordinates":[2.232715,48.642365],"type":"Point"}
}