{
  "type": "Feature",
  "properties": {
    "addr:full":"28, Rue Saint Denis, 93300 Aubervilliers Ile de France 93300",
    "addr:housenumber":"28",
    "addr:postcode":"93300;93300",
    "addr:street":"Rue Saint Denis",
    "iso:country":"FR",
    "sg:address":"28, Rue Saint Denis, 93300 Aubervilliers",
    "sg:orig_category":"Non-Classified Establishments",
    "sg:phone":"+33 1 43 52 10 44",
    "sg:postcode":"93300",
    "sg:province":"Ile de France",
    "wof:name":"Coffin Modinox S.a.",
    "wof:placetype":"venue"
},
  "geometry": {"coordinates":[2.368211,48.922749],"type":"Point"}
}