{
  "type": "Feature",
  "properties": {
    "iso:country":"FR",
    "sg:address":"16, Rue des Anciens Combattants, 02300 Chauny",
    "sg:orig_category":"Unclassifiable Establishments",
    "sg:phone":"+33 3 23 52 13 26",
    "sg:province":"Picardie",
    "wof:name":"Tayon S.a.",
    "wof:placetype":"venue"
},
  "geometry": {"coordinates":[3.230809,49.623562],"type":"Point"}
}