{
  "type": "Feature",
  "properties": {
    "iso:country":"FR",
    "sg:address":"ZAE du Bord d'Arve",
    "sg:city":"Scionzier",
    "sg:orig_category":"Unclassifiable Establishments",
    "sg:phone":"+33 4 50 96 14 19",
    "sg:postcode":"74950",
    "sg:province":"Rhone-Alpes",
    "wof:name":"D.m.s. S.a.s. - D\u00e9coupage Moulage De Savoie",
    "wof:placetype":"venue"
},
  "geometry": {"coordinates":[6.545821,46.071068],"type":"Point"}
}