{
  "type": "Feature",
  "properties": {
    "addr:full":"Rue de la Bret\u00e8che - ZI Saint Pierre des Corps Centre 37700",
    "addr:postcode":"37700",
    "addr:street":"Rue De La Brete\u0300Che Zi Saint Pierre Des Corps",
    "iso:country":"FR",
    "sg:address":"Rue de la Bret\u00e8che - ZI",
    "sg:city":"Saint Pierre des Corps",
    "sg:orig_category":"Non-Classified Establishments",
    "sg:phone":"+33 2 47 32 70 00",
    "sg:postcode":"37700",
    "sg:province":"Centre",
    "wof:name":"Albinet Allusson S.a.",
    "wof:placetype":"venue"
},
  "geometry": {"coordinates":[0.718755,47.389648],"type":"Point"}
}