{
  "type": "Feature",
  "properties": {
    "addr:full":"38 Rue De L'Orangerie Versailles Ile de France 78000",
    "addr:housenumber":"38",
    "addr:postcode":"78000",
    "addr:street":"Rue De L'Orangerie",
    "iso:country":"FR",
    "sg:address":"38 Rue De L'Orangerie",
    "sg:city":"Versailles",
    "sg:classifiers":[
        {
            "category":"Banks & Credit Unions",
            "subcategory":"Financial Services",
            "type":"Services"
        }
    ],
    "sg:phone":"+33 1 39 24 82 82",
    "sg:postcode":"78000",
    "sg:province":"Ile de France",
    "sg:tags":[
        "banking",
        "finance",
        "insurance"
    ],
    "wof:name":"Macron Bernard",
    "wof:placetype":"venue"
},
  "geometry": {"coordinates":[2.124138,48.799683],"type":"Point"}
}