{
  "type": "Feature",
  "properties": {
    "iso:country":"FR",
    "sg:address":"15 avenue Augustine 92250 La Garenne Colombes",
    "sg:classifiers":[
        {
            "category":"Military Area",
            "subcategory":"Air Force Base",
            "type":"Public Place"
        }
    ],
    "sg:phone":"+33 1 47 60 22 20",
    "sg:province":"Ile de France",
    "sg:tags":[
        "equipment",
        "safety",
        "system"
    ],
    "wof:name":"Groupe Ankri Sa",
    "wof:placetype":"venue"
},
  "geometry": {"coordinates":[2.23709,48.90686],"type":"Point"}
}