{
  "type": "Feature",
  "properties": {
    "addr:full":"6 B Rue De L Abbe Friclot 54400 Longwy Lorraine 54400",
    "addr:housenumber":"6 b",
    "addr:postcode":"54400;54400",
    "addr:street":"Rue De L;Friclot",
    "iso:country":"FR",
    "sg:address":"6 B Rue De L Abbe Friclot 54400 Longwy",
    "sg:classifiers":[
        {
            "category":"Wholesale",
            "subcategory":"Medical Equipment & Supplies",
            "type":"Manufacturing & Wholesale Goods"
        }
    ],
    "sg:phone":"+33 3 82 25 48 14",
    "sg:postcode":"54400",
    "sg:province":"Lorraine",
    "sg:tags":[
        "instrument",
        "health",
        "-",
        "precision"
    ],
    "wof:name":"Laboratoire De Protheses Dentaires Hoefler",
    "wof:placetype":"venue"
},
  "geometry": {"coordinates":[5.761896,49.522892],"type":"Point"}
}