{
  "type": "Feature",
  "properties": {
    "addr:full":"ZI Bavilliers Franche Comt\u00e9 90800",
    "addr:postcode":"90800",
    "addr:street":"Franche Comte\u0301",
    "iso:country":"FR",
    "sg:address":"ZI",
    "sg:city":"Bavilliers",
    "sg:orig_category":"Unclassifiable Establishments",
    "sg:phone":"+33 3 84 21 31 68",
    "sg:postcode":"90800",
    "sg:province":"Franche Comt\u00e9",
    "wof:name":"F.c.i.e. S.a. - Franc-comtoise D'installations Electriques",
    "wof:placetype":"venue"
},
  "geometry": {"coordinates":[6.833895,47.620541],"type":"Point"}
}