{
  "type": "Feature",
  "properties": {
    "iso:country":"FR",
    "sg:address":"ZI de Furst",
    "sg:city":"Folschviller",
    "sg:orig_category":"Unclassifiable Establishments",
    "sg:phone":"+33 3 87 92 91 52",
    "sg:postcode":"57730",
    "sg:province":"Lorraine",
    "wof:name":"T.i.m.e. S.a.r.l. - Travaux Industriels De Montage Et Entretien",
    "wof:placetype":"venue"
},
  "geometry": {"coordinates":[6.686695,49.07106],"type":"Point"}
}