{
  "type": "Feature",
  "properties": {
    "addr:full":"Zi Les Forges 57280 Maizi\u00e8res Les Metz Aizier Haute Normandie 27500",
    "addr:postcode":"57280;27500",
    "addr:street":"Zi Les Forges;Haute Normandie",
    "iso:country":"FR",
    "sg:address":"Zi Les Forges 57280 Maizi\u00e8res Les Metz",
    "sg:city":"Aizier",
    "sg:classifiers":[
        {
            "category":"Manufacturing",
            "subcategory":"Building Materials",
            "type":"Manufacturing & Wholesale Goods"
        }
    ],
    "sg:phone":"+33 3 87 80 69 69",
    "sg:postcode":"27500",
    "sg:province":"Haute Normandie",
    "sg:tags":[
        "glass",
        "ceramic"
    ],
    "wof:name":"Compagnie Europeenne De Ceramiques (cedec) Cedec",
    "wof:placetype":"venue"
},
  "geometry": {"coordinates":[6.160855,49.209999],"type":"Point"}
}