{
  "type": "Feature",
  "properties": {
    "addr:full":"133, Rte d'Avesnes, 59600 Maubeuge Nord Pas-de-Calais",
    "addr:housenumber":"133",
    "addr:postcode":"59600",
    "addr:street":"Rte D'Avesnes",
    "iso:country":"FR",
    "sg:address":"133, Rte d'Avesnes, 59600 Maubeuge",
    "sg:orig_category":"Non-Classified Establishments",
    "sg:phone":"+33 3 27 65 08 10",
    "sg:province":"Nord Pas-de-Calais",
    "wof:name":"S.t.n.i. S.a.r.l. - Soci\u00e9t\u00e9 De Travaux Et De Nettoyage Industriel",
    "wof:placetype":"venue"
},
  "geometry": {"coordinates":[3.967648,50.270241],"type":"Point"}
}