{
  "type": "Feature",
  "properties": {
    "iso:country":"FR",
    "sg:address":"Za Chabanne 03100 Lavault Ste Anne",
    "sg:city":"Montlu\u00e7on",
    "sg:classifiers":[
        {
            "category":"Shopping",
            "subcategory":"Computers & Home Electronics",
            "type":"Retail Goods"
        }
    ],
    "sg:phone":"+33 4 70 05 00 80",
    "sg:postcode":"03100",
    "sg:province":"Auvergne",
    "sg:tags":[
        "equipment",
        "electrical",
        "component",
        "electric",
        "electronic"
    ],
    "wof:name":"Transfo Centre S A",
    "wof:placetype":"venue"
},
  "geometry": {"coordinates":[2.597484,46.34124],"type":"Point"}
}