{
  "type": "Feature",
  "properties": {
    "addr:full":"Cd 15 N\u00b0 852 La Roseyre 06390 Contes Franche Comt\u00e9",
    "addr:postcode":"06390",
    "addr:street":"Cd 15 N\u00b0 852 La Roseyre;Franche Comte\u0301",
    "iso:country":"FR",
    "sg:address":"Cd 15 N\u00b0 852 La Roseyre 06390 Contes",
    "sg:classifiers":[
        {
            "category":"Building & Trades",
            "subcategory":"Electrical",
            "type":"Services"
        }
    ],
    "sg:phone":"+33 4 93 91 60 10",
    "sg:province":"Franche Comt\u00e9",
    "sg:tags":[
        "electronic",
        "lighting",
        "equipment"
    ],
    "wof:name":"Aluminor Sa",
    "wof:placetype":"venue"
},
  "geometry": {"coordinates":[7.31372,43.817459],"type":"Point"}
}