{
  "type": "Feature",
  "properties": {
    "addr:full":"Rue Pont de La\u00ebr Mo\u00eblan sur Mer Bretagne 29350",
    "addr:postcode":"29350",
    "addr:street":"Rue Pont De Lae\u0308R Moe\u0308Lan Sur Mer",
    "iso:country":"FR",
    "sg:address":"Rue Pont de La\u00ebr",
    "sg:city":"Mo\u00eblan sur Mer",
    "sg:orig_category":"Unclassifiable Establishments",
    "sg:phone":"+33 2 98 96 51 51",
    "sg:postcode":"29350",
    "sg:province":"Bretagne",
    "wof:name":"Ferembal Ouest S.a.",
    "wof:placetype":"venue"
},
  "geometry": {"coordinates":[-3.629243,47.813122],"type":"Point"}
}