{
  "type": "Feature",
  "properties": {
    "addr:full":"32 Rue Mounie 92160 Antony Ile de France",
    "addr:housenumber":"32",
    "addr:postcode":"92160",
    "addr:street":"Rue Mounie",
    "iso:country":"FR",
    "sg:address":"32 Rue Mounie 92160 Antony",
    "sg:classifiers":[
        {
            "category":"Banks & Credit Unions",
            "subcategory":"Investment Brokerage",
            "type":"Services"
        }
    ],
    "sg:phone":"+33 1 46 74 11 30",
    "sg:province":"Ile de France",
    "sg:tags":[
        "-",
        "transport",
        "related"
    ],
    "wof:name":"La Poste",
    "wof:placetype":"venue"
},
  "geometry": {"coordinates":[2.302611,48.754047],"type":"Point"}
}