{
  "type": "Feature",
  "properties": {
    "addr:full":"20 rue Louis Fr\u00e9bault 94110 Arcueil Ile de France 94110",
    "addr:housenumber":"20",
    "addr:postcode":"94110;ile;94110",
    "addr:street":"Rue Louis Fre\u0301Bault;France",
    "iso:country":"FR",
    "sg:address":"20 rue Louis Fr\u00e9bault 94110 Arcueil",
    "sg:classifiers":[
        {
            "category":"Manufacturing",
            "subcategory":"Metals",
            "type":"Manufacturing & Wholesale Goods"
        }
    ],
    "sg:phone":"+33 1 45 47 03 84",
    "sg:postcode":"94110",
    "sg:province":"Ile de France",
    "sg:tags":[
        "blanking",
        "dy"
    ],
    "wof:name":"L.c.m.",
    "wof:placetype":"venue"
},
  "geometry": {"coordinates":[2.335845,48.80479],"type":"Point"}
}