{
  "type": "Feature",
  "properties": {
    "addr:full":"Le Belvaux 56500 Locmin\u00e9 Locmin\u00e9 Bretagne 56500",
    "addr:postcode":"56500;56500",
    "iso:country":"FR",
    "sg:address":"Le Belvaux 56500 Locmin\u00e9",
    "sg:city":"Locmin\u00e9",
    "sg:orig_category":"Unclassifiable Establishments",
    "sg:phone":"+33 2 97 44 27 27",
    "sg:postcode":"56500",
    "sg:province":"Bretagne",
    "wof:name":"U.f.m. - Union Fermi\u00e8re Morbihannaise",
    "wof:placetype":"venue"
},
  "geometry": {"coordinates":[-2.870512,47.839455],"type":"Point"}
}