{
  "type": "Feature",
  "properties": {
    "addr:full":"3, Rue de la Filature, 49310 Cholet Pays de Loire",
    "addr:housenumber":"3",
    "addr:postcode":"49310",
    "addr:street":"Rue De La Filature",
    "iso:country":"FR",
    "sg:address":"3, Rue de la Filature, 49310 Cholet",
    "sg:orig_category":"Unclassifiable Establishments",
    "sg:phone":"+33 2 41 65 58 42",
    "sg:province":"Pays de Loire",
    "wof:name":"M.c.m. S.a.r.l.",
    "wof:placetype":"venue"
},
  "geometry": {"coordinates":[-0.878799,47.062576],"type":"Point"}
}