{
  "type": "Feature",
  "properties": {
    "addr:full":"B.P. 11 Les Mages C\u00e9dex^^Le Coussac 30960 Les Mages Languedoc-Roussillon 30960",
    "addr:postcode":"30960;30960",
    "addr:street":"B.P. 11 Les;Ce\u0301Dex^^Le Coussac",
    "iso:country":"FR",
    "sg:address":"B.P. 11",
    "sg:city":"Les Mages C\u00e9dex^^Le Coussac 30960 Les Mages",
    "sg:orig_category":"Non-Classified Establishments",
    "sg:phone":"+33 4 66 25 83 94",
    "sg:postcode":"30960",
    "sg:province":"Languedoc-Roussillon",
    "wof:name":"Manufacture De Stores Du Languedoc S.a.",
    "wof:placetype":"venue"
},
  "geometry": {"coordinates":[4.165712,44.228905],"type":"Point"}
}