{
  "type": "Feature",
  "properties": {
    "addr:full":"B.P. 42, 76520 Boos^^36, Rue de la Forge F\u00e9ret, 76520 Boos Haute Normandie",
    "addr:postcode":"76520;76520",
    "addr:street":"B.P. 42;Rue De La Forge Fe\u0301Ret",
    "iso:country":"FR",
    "sg:address":"B.P. 42, 76520 Boos^^36, Rue de la Forge F\u00e9ret, 76520 Boos",
    "sg:orig_category":"Non-Classified Establishments",
    "sg:phone":"+33 2 32 86 51 21",
    "sg:province":"Haute Normandie",
    "wof:name":"Sericad S.a.r.l.",
    "wof:placetype":"venue"
},
  "geometry": {"coordinates":[1.17631,49.401428],"type":"Point"}
}