{
  "type": "Feature",
  "properties": {
    "addr:full":"325 route de Toulon 83400 HYERES Bourgogne",
    "addr:housenumber":"325",
    "addr:postcode":"83400",
    "addr:street":"Route De Toulon",
    "iso:country":"FR",
    "sg:address":"325 route de Toulon 83400 HYERES",
    "sg:classifiers":[
        {
            "category":"Utilities",
            "subcategory":"Natural Gas",
            "type":"Services"
        }
    ],
    "sg:phone":"+33 4 94 01 44 10",
    "sg:province":"Bourgogne",
    "sg:tags":[
        "flower",
        "dried"
    ],
    "wof:name":"Virgie Flor Sarl",
    "wof:placetype":"venue"
},
  "geometry": {"coordinates":[6.102955,43.12606],"type":"Point"}
}