{
  "type": "Feature",
  "properties": {
    "addr:full":"307, Square des Champs Elys\u00e9es, 91000 Evry Ile de France",
    "addr:housenumber":"307",
    "addr:postcode":"91000",
    "addr:street":"Square Des Champs Elyse\u0301Es",
    "iso:country":"FR",
    "sg:address":"307, Square des Champs Elys\u00e9es, 91000 Evry",
    "sg:orig_category":"Unclassifiable Establishments",
    "sg:phone":"+33 1 60 78 01 11",
    "sg:province":"Ile de France",
    "wof:name":"Ecsat S.a.",
    "wof:placetype":"venue"
},
  "geometry": {"coordinates":[2.433357,48.641582],"type":"Point"}
}