{
  "type": "Feature",
  "properties": {
    "iso:country":"FR",
    "sg:address":"9 Rue De Nantes",
    "sg:city":"Pontchateau",
    "sg:classifiers":[
        {
            "category":"Banks & Credit Unions",
            "subcategory":"Financial Services",
            "type":"Services"
        }
    ],
    "sg:phone":"+33 2 40 01 61 51",
    "sg:postcode":"44160",
    "sg:province":"Pays de Loire",
    "sg:tags":[
        "banking",
        "finance",
        "insurance"
    ],
    "wof:name":"Caisse Regionale De Credit Agricole Mutuel De Loire Atlanti (crcam Loire Atlantique)",
    "wof:placetype":"venue"
},
  "geometry": {"coordinates":[-2.089011,47.437111],"type":"Point"}
}