{
  "type": "Feature",
  "properties": {
    "iso:country":"FR",
    "sg:address":"240, Av de Maurettes, 06270 Villeneuve Loubet",
    "sg:city":"Vill\u00e9",
    "sg:orig_category":"Unclassifiable Establishments",
    "sg:phone":"+33 4 93 20 72 92",
    "sg:postcode":"67220",
    "sg:province":"Alsace",
    "wof:name":"Genofer S.a.r.l.",
    "wof:placetype":"venue"
},
  "geometry": {"coordinates":[7.130233,43.630848],"type":"Point"}
}