{
  "type": "Feature",
  "properties": {
    "iso:country":"FR",
    "sg:address":"B.P. 561, 31674 Lab\u00e8ge^^Voie 5 - Technoparc - B\u00e2t. 1, 82000 Montauban",
    "sg:orig_category":"Non-Classified Establishments",
    "sg:phone":"+33 5 61 00 92 00",
    "sg:province":"Midi Pyr\u00e9n\u00e9es",
    "wof:name":"Val Informatique S.a.",
    "wof:placetype":"venue"
},
  "geometry": {"coordinates":[1.352205,44.016762],"type":"Point"}
}