{
  "type": "Feature",
  "properties": {
    "addr:full":"Pl March\u00e9 64350 Lembeye Lembeye Aquitaine 64350",
    "addr:postcode":"64350;64350",
    "addr:street":"Pl Marche\u0301",
    "iso:country":"FR",
    "sg:address":"Pl March\u00e9 64350 Lembeye",
    "sg:city":"Lembeye",
    "sg:classifiers":[
        {
            "category":"Farming",
            "subcategory":"Livestock Farm",
            "type":"Manufacturing & Wholesale Goods"
        }
    ],
    "sg:phone":"+33 5 59 68 10 24",
    "sg:postcode":"64350",
    "sg:province":"Aquitaine",
    "sg:tags":[
        "grain",
        "agriculture",
        "cereal"
    ],
    "wof:name":"Lacoustille Sa",
    "wof:placetype":"venue"
},
  "geometry": {"coordinates":[-0.138224,43.394199],"type":"Point"}
}