{
  "type": "Feature",
  "properties": {
    "addr:full":"21ter, Rue des Compagnons, 51350 Cormontreuil Champagne",
    "addr:housenumber":"21ter",
    "addr:postcode":"51350",
    "addr:street":"Rue Des Compagnons",
    "iso:country":"FR",
    "sg:address":"21ter, Rue des Compagnons, 51350 Cormontreuil",
    "sg:orig_category":"Unclassifiable Establishments",
    "sg:phone":"+33 3 26 82 82 14",
    "sg:province":"Champagne",
    "wof:name":"Air L'express S.a.r.l.",
    "wof:placetype":"venue"
},
  "geometry": {"coordinates":[4.063694,49.217243],"type":"Point"}
}