{
  "type": "Feature",
  "properties": {
    "addr:full":"43 Boulevard Du Mar\u00e9chal Joffre Bourg La Reine Ile de France 92340",
    "addr:housenumber":"43",
    "addr:postcode":"92340",
    "addr:street":"Boulevard Du Mare\u0301Chal Joffre",
    "iso:country":"FR",
    "sg:address":"43 Boulevard Du Mar\u00e9chal Joffre",
    "sg:city":"Bourg La Reine",
    "sg:classifiers":[
        {
            "category":"Banks & Credit Unions",
            "subcategory":"Financial Services",
            "type":"Services"
        }
    ],
    "sg:phone":"+33 1 40 91 30 30",
    "sg:postcode":"92340",
    "sg:province":"Ile de France",
    "sg:tags":[
        "banking",
        "finance",
        "insurance"
    ],
    "wof:name":"Cemka",
    "wof:placetype":"venue"
},
  "geometry": {"coordinates":[2.315182,48.78273],"type":"Point"}
}