{
  "type": "Feature",
  "properties": {
    "iso:country":"FR",
    "sg:address":"17, Place de la R\u00e9publique, 59280 Armenti\u00e8res",
    "sg:orig_category":"Unclassifiable Establishments",
    "sg:phone":"+33 3 20 44 12 79",
    "sg:province":"Nord Pas-de-Calais",
    "wof:name":"Aries S.a.r.l.",
    "wof:placetype":"venue"
},
  "geometry": {"coordinates":[2.875274,50.68383],"type":"Point"}
}