{
  "type": "Feature",
  "properties": {
    "addr:full":"77, Av. de Jasseron, 01000 Bourg en Bresse Rhone-Alpes 01000",
    "addr:postcode":"01000;01000",
    "addr:street":"77 Av. De Jasseron;Rhone-Alpes",
    "iso:country":"FR",
    "sg:address":"77, Av. de Jasseron, 01000 Bourg en Bresse",
    "sg:orig_category":"Non-Classified Establishments",
    "sg:phone":"+33 4 74 22 60 95",
    "sg:postcode":"01000",
    "sg:province":"Rhone-Alpes",
    "wof:name":"Charnaux Michel",
    "wof:placetype":"venue"
},
  "geometry": {"coordinates":[5.25643,46.21159],"type":"Point"}
}