{
  "type": "Feature",
  "properties": {
    "addr:full":"Rue de l'Europe - Zone Industrielle Caudry Nord Pas-de-Calais 59540",
    "addr:postcode":"59540",
    "addr:street":"Rue De L'Europe Zone Industrielle Caudry Nord",
    "iso:country":"FR",
    "sg:address":"Rue de l'Europe - Zone Industrielle",
    "sg:city":"Caudry",
    "sg:orig_category":"Unclassifiable Establishments",
    "sg:phone":"+33 3 27 85 51 51",
    "sg:postcode":"59540",
    "sg:province":"Nord Pas-de-Calais",
    "wof:name":"Texidel Lnt S.a.",
    "wof:placetype":"venue"
},
  "geometry": {"coordinates":[3.43628,50.12624],"type":"Point"}
}