{
  "type": "Feature",
  "properties": {
    "addr:full":"74 Rue R\u00e9n\u00e9 Binet 89100 Sens Sens Bourgogne 89100",
    "addr:housenumber":"74",
    "addr:postcode":"89100;89100",
    "addr:street":"Rue Re\u0301Ne\u0301 Binet",
    "iso:country":"FR",
    "sg:address":"74 Rue R\u00e9n\u00e9 Binet 89100 Sens",
    "sg:city":"Sens",
    "sg:classifiers":[
        {
            "category":"Home & Garden",
            "subcategory":"Building Materials",
            "type":"Retail Goods"
        }
    ],
    "sg:phone":"+33 3 86 64 72 80",
    "sg:postcode":"89100",
    "sg:province":"Bourgogne",
    "sg:tags":[
        "equipment",
        "energy",
        "-",
        "environment",
        "raw",
        "machinery"
    ],
    "wof:name":"Societe D'amenagement Urbain Et Rural De La Saur",
    "wof:placetype":"venue"
},
  "geometry": {"coordinates":[3.296385,48.191956],"type":"Point"}
}