{
  "type": "Feature",
  "properties": {
    "iso:country":"FR",
    "sg:address":"49 bis, Av. M\u00e9d\u00e9ric, 93160 Noisy le Grand",
    "sg:orig_category":"Non-Classified Establishments",
    "sg:phone":"+33 1 49 31 05 42",
    "sg:postcode":"93160",
    "sg:province":"Ile de France",
    "wof:name":"Ast New Alarme S.a.r.l.",
    "wof:placetype":"venue"
},
  "geometry": {"coordinates":[2.564021,48.829742],"type":"Point"}
}