{
  "type": "Feature",
  "properties": {
    "addr:full":"Route De Sort Zone Artisanale 40180 Narrosse Narrosse Aquitaine 40180",
    "addr:postcode":"40180;40180",
    "addr:street":"Route De Sort Zone Artisanale",
    "iso:country":"FR",
    "sg:address":"Route De Sort Zone Artisanale 40180 Narrosse",
    "sg:city":"Narrosse",
    "sg:classifiers":[
        {
            "category":"Food & Beverages",
            "subcategory":"Meat & Fish",
            "type":"Retail Goods"
        }
    ],
    "sg:phone":"+33 5 58 58 04 30",
    "sg:postcode":"40180",
    "sg:province":"Aquitaine",
    "sg:tags":[
        "preserve",
        "cooked",
        "product",
        "related"
    ],
    "wof:name":"Marthe",
    "wof:placetype":"venue"
},
  "geometry": {"coordinates":[-1.036179,43.643139],"type":"Point"}
}