{
  "type": "Feature",
  "properties": {
    "addr:full":"Les Ormes Rn 6 71680 Creches Sur Saone Cr\u00eaches-sur-Sa\u00f4ne Bourgogne 71680",
    "addr:housenumber":"ormes",
    "addr:postcode":"71680;71680",
    "addr:street":"Rn 6;Bourgogne",
    "iso:country":"FR",
    "sg:address":"Les Ormes Rn 6 71680 Creches Sur Saone",
    "sg:city":"Cr\u00eaches-sur-Sa\u00f4ne",
    "sg:classifiers":[
        {
            "category":"Manufacturing",
            "subcategory":"Metals",
            "type":"Manufacturing & Wholesale Goods"
        }
    ],
    "sg:phone":"+33 3 85 36 51 52",
    "sg:postcode":"71680",
    "sg:province":"Bourgogne",
    "sg:tags":[
        "-",
        "machine",
        "equipment",
        "engineering",
        "machinery",
        "mechanical"
    ],
    "wof:name":"Flasch Bat",
    "wof:placetype":"venue"
},
  "geometry": {"coordinates":[4.787081,46.246044],"type":"Point"}
}