{
  "type": "Feature",
  "properties": {
    "addr:full":"10 Rue Etienne Marey 75020 Paris Ile de France",
    "addr:housenumber":"10",
    "addr:postcode":"75020",
    "addr:street":"Rue Etienne Marey",
    "iso:country":"FR",
    "sg:address":"10 Rue Etienne Marey 75020 Paris",
    "sg:classifiers":[
        {
            "category":"Manufacturing",
            "subcategory":"Printing",
            "type":"Manufacturing & Wholesale Goods"
        }
    ],
    "sg:phone":"+33 1 40 32 40 60",
    "sg:province":"Ile de France",
    "sg:tags":[
        "publishing"
    ],
    "wof:name":"Panchro Grenelle",
    "wof:placetype":"venue"
},
  "geometry": {"coordinates":[2.406104,48.867161],"type":"Point"}
}