{
  "type": "Feature",
  "properties": {
    "addr:full":"1 Rue Des Chataigniers BP 11 Za Des Bauches 44460 St Nicolas De Redon Pays de Loire 44460",
    "addr:housenumber":"1;11",
    "addr:postcode":"44460 st;44460",
    "addr:street":"Rue Des Chataigniers Bp;Za Des Bauches;Redon",
    "iso:country":"FR",
    "sg:address":"1 Rue Des Chataigniers BP 11 Za Des Bauches 44460 St Nicolas De Redon",
    "sg:classifiers":[
        {
            "category":"Utilities",
            "subcategory":"Electric",
            "type":"Services"
        }
    ],
    "sg:phone":"+33 2 99 71 44 66",
    "sg:postcode":"44460",
    "sg:province":"Pays de Loire",
    "sg:tags":[
        "electricity",
        "raw",
        "energy",
        "material"
    ],
    "wof:name":"Ei Reseaux Ouest",
    "wof:placetype":"venue"
},
  "geometry": {"coordinates":[-2.044664,47.584846],"type":"Point"}
}