{
  "type": "Feature",
  "properties": {
    "iso:country":"FR",
    "sg:address":"ZI le Royeux",
    "sg:city":"Gauchy",
    "sg:orig_category":"Unclassifiable Establishments",
    "sg:phone":"+33 3 23 62 48 72",
    "sg:postcode":"02430",
    "sg:province":"Picardie",
    "wof:name":"Missenard Quint Industries S.a.",
    "wof:placetype":"venue"
},
  "geometry": {"coordinates":[3.278895,49.826702],"type":"Point"}
}