{
  "type": "Feature",
  "properties": {
    "addr:full":"Avenue Ambroise Croizat 59125 Trith St Leger Nord Pas-de-Calais 59125",
    "addr:postcode":"59125;59125",
    "addr:street":"Avenue Ambroise Croizat;Trith St Leger Nord",
    "iso:country":"FR",
    "sg:address":"Avenue Ambroise Croizat 59125 Trith St Leger",
    "sg:classifiers":[
        {
            "category":"Professional",
            "subcategory":"Engineering",
            "type":"Services"
        }
    ],
    "sg:phone":"+33 3 27 21 00 70",
    "sg:postcode":"59125",
    "sg:province":"Nord Pas-de-Calais",
    "sg:tags":[
        "machine",
        "-",
        "mechanical"
    ],
    "wof:name":"Fabrications Mecaniques",
    "wof:placetype":"venue"
},
  "geometry": {"coordinates":[3.488853,50.331028],"type":"Point"}
}