{
  "type": "Feature",
  "properties": {
    "iso:country":"FR",
    "sg:address":"B.P. 36, 88250 La Bresse^^11, Rte de Cornimont, 88250 La Bresse",
    "sg:orig_category":"Non-Classified Establishments",
    "sg:phone":"+33 3 29 25 53 80",
    "sg:province":"Lorraine",
    "wof:name":"Grandemange Agencement S.a.",
    "wof:placetype":"venue"
},
  "geometry": {"coordinates":[6.87512,48.003704],"type":"Point"}
}