{
  "type": "Feature",
  "properties": {
    "addr:full":"3, Place Saint Nabor, 57500 Saint Avold Lorraine",
    "addr:housenumber":"3",
    "addr:postcode":"57500",
    "addr:street":"Place Saint Nabor;Avold",
    "iso:country":"FR",
    "sg:address":"3, Place Saint Nabor, 57500 Saint Avold",
    "sg:orig_category":"Non-Classified Establishments",
    "sg:phone":"+33 3 87 91 21 00",
    "sg:province":"Lorraine",
    "wof:name":"Starcolor S.a.r.l.",
    "wof:placetype":"venue"
},
  "geometry": {"coordinates":[6.708876,49.105103],"type":"Point"}
}