{
  "type": "Feature",
  "properties": {
    "iso:country":"FR",
    "sg:address":"46, Av de Belgique, 68110 Illzach",
    "sg:city":"Illzach",
    "sg:orig_category":"Unclassifiable Establishments",
    "sg:phone":"+33 3 89 61 70 66",
    "sg:postcode":"68110",
    "sg:province":"Alsace",
    "wof:name":"Weber Et Hecky S.a.",
    "wof:placetype":"venue"
},
  "geometry": {"coordinates":[7.369546,47.767513],"type":"Point"}
}