{
  "type": "Feature",
  "properties": {
    "iso:country":"FR",
    "sg:address":"36, Av. Jos\u00e9 Nobre - ZI Ecopolis Sud, 13500 Martigues",
    "sg:city":"Artigue",
    "sg:orig_category":"Non-Classified Establishments",
    "sg:phone":"+33 4 42 81 63 01",
    "sg:postcode":"31110",
    "sg:province":"Midi Pyr\u00e9n\u00e9es",
    "wof:name":"Auxitec Industrie S.a.",
    "wof:placetype":"venue"
},
  "geometry": {"coordinates":[5.055235,43.406536],"type":"Point"}
}