{
  "type": "Feature",
  "properties": {
    "addr:full":"126, Av. Vend\u00f4me, 41000 Blois Blois Centre 41000",
    "addr:postcode":"41000;41000",
    "addr:street":"126 Av. Vendo\u0302Me",
    "iso:country":"FR",
    "sg:address":"126, Av. Vend\u00f4me, 41000 Blois",
    "sg:city":"Blois",
    "sg:orig_category":"Non-Classified Establishments",
    "sg:phone":"+33 2 54 52 22 00",
    "sg:postcode":"41000",
    "sg:province":"Centre",
    "wof:name":"Laboratoire Lachartre S.n.c.",
    "wof:placetype":"venue"
},
  "geometry": {"coordinates":[1.31154,47.606964],"type":"Point"}
}