{
  "type": "Feature",
  "properties": {
    "iso:country":"FR",
    "sg:address":"B.P. 37, 38530 Pontcharra C\u00e9dex^^540, Rue du Stade, 38530 Pontcharra",
    "sg:orig_category":"Non-Classified Establishments",
    "sg:phone":"+33 4 76 97 60 50",
    "sg:postcode":"38530",
    "sg:province":"Rhone-Alpes",
    "wof:name":"C.m.b. S.a. - Constructions M\u00e9caniques Bernard",
    "wof:placetype":"venue"
},
  "geometry": {"coordinates":[6.024777,45.431976],"type":"Point"}
}