{
  "type": "Feature",
  "properties": {
    "iso:country":"FR",
    "sg:address":"Zi Du Vieux Domaine 18100 Vierzon",
    "sg:city":"Vierzon",
    "sg:classifiers":[
        {
            "category":"Professional",
            "type":"Services"
        }
    ],
    "sg:phone":"+33 2 48 75 57 54",
    "sg:postcode":"18100",
    "sg:province":"Centre",
    "sg:tags":[
        "transport",
        "road"
    ],
    "wof:name":"Transports Leveque Sarl",
    "wof:placetype":"venue"
},
  "geometry": {"coordinates":[2.066647,47.222672],"type":"Point"}
}