{
  "type": "Feature",
  "properties": {
    "iso:country":"FR",
    "sg:address":"Le Bois Joly 44330 Le Pallet",
    "sg:orig_category":"Unclassifiable Establishments",
    "sg:phone":"+33 2 40 80 40 83",
    "sg:province":"Pays de Loire",
    "wof:name":"Domaine Du Bois Joly G.a.e.c.",
    "wof:placetype":"venue"
},
  "geometry": {"coordinates":[-1.344869,47.145786],"type":"Point"}
}