{
  "type": "Feature",
  "properties": {
    "addr:full":"27, Rue du Faubourg Saint Andr\u00e9, 60000 Beauvais Picardie 60000",
    "addr:housenumber":"27",
    "addr:postcode":"60000;60000",
    "addr:street":"Rue Du Faubourg Saint Andre\u0301",
    "iso:country":"FR",
    "sg:address":"27, Rue du Faubourg Saint Andr\u00e9, 60000 Beauvais",
    "sg:orig_category":"Non-Classified Establishments",
    "sg:phone":"+33 3 44 45 71 41",
    "sg:postcode":"60000",
    "sg:province":"Picardie",
    "wof:name":"Danjou S.a.",
    "wof:placetype":"venue"
},
  "geometry": {"coordinates":[2.092121,49.432133],"type":"Point"}
}