{
  "type": "Feature",
  "properties": {
    "addr:full":"7, rue Kant, 67000 Strasbourg Strasbourg Alsace 67000",
    "addr:housenumber":"7",
    "addr:postcode":"67000;67000",
    "addr:street":"Rue Kant",
    "iso:country":"FR",
    "sg:address":"7, rue Kant, 67000 Strasbourg",
    "sg:city":"Strasbourg",
    "sg:orig_category":"Non-Classified Establishments",
    "sg:phone":"+33 3 88 45 33 10",
    "sg:postcode":"67000",
    "sg:province":"Alsace",
    "wof:name":"Klocke France S.a.r.l.",
    "wof:placetype":"venue"
},
  "geometry": {"coordinates":[7.784415,48.587109],"type":"Point"}
}