{
  "type": "Feature",
  "properties": {
    "addr:full":"Rue La Fontaine 62119 Dourges Nord Pas-de-Calais 62119",
    "addr:postcode":"62119;62119",
    "addr:street":"Rue La Fontaine",
    "iso:country":"FR",
    "sg:address":"Rue La Fontaine 62119 Dourges",
    "sg:classifiers":[
        {
            "category":"Wholesale",
            "subcategory":"Metals & Minerals",
            "type":"Manufacturing & Wholesale Goods"
        }
    ],
    "sg:phone":"+33 3 21 20 06 17",
    "sg:postcode":"62119",
    "sg:province":"Nord Pas-de-Calais",
    "sg:tags":[
        "steel",
        "-",
        "metalworking",
        "metallic",
        "metallurgy",
        "finished"
    ],
    "wof:name":"Flinois Sa",
    "wof:placetype":"venue"
},
  "geometry": {"coordinates":[2.985448,50.430389],"type":"Point"}
}