{
  "type": "Feature",
  "properties": {
    "addr:full":"Zi Des Noes 44550 Montoir De Bretagne Pays de Loire 44550",
    "addr:postcode":"44550;44550",
    "addr:street":"Des Noes",
    "iso:country":"FR",
    "sg:address":"Zi Des Noes 44550 Montoir De Bretagne",
    "sg:orig_category":"Miscellaneous Products",
    "sg:phone":"+33 2 40 19 59 25",
    "sg:postcode":"44550",
    "sg:province":"Pays de Loire",
    "wof:name":"Fabrication Gaines Aerauliques",
    "wof:placetype":"venue"
},
  "geometry": {"coordinates":[-2.153179,47.327759],"type":"Point"}
}