{
  "type": "Feature",
  "properties": {
    "addr:full":"19 Rue Tronchet 75008 Paris Ile de France 75008",
    "addr:housenumber":"19",
    "addr:postcode":"75008;75008",
    "addr:street":"Rue Tronchet",
    "iso:country":"FR",
    "sg:address":"19 Rue Tronchet 75008 Paris",
    "sg:classifiers":[
        {
            "category":"Travel",
            "subcategory":"Hotels & Motels",
            "type":"Entertainment"
        }
    ],
    "sg:phone":"+33 1 42 65 77 97",
    "sg:postcode":"75008",
    "sg:province":"Ile de France",
    "sg:tags":[
        "hotels",
        "business",
        "restaurant"
    ],
    "wof:name":"Hotel Opal *** Nn",
    "wof:placetype":"venue"
},
  "geometry": {"coordinates":[2.325866,48.872253],"type":"Point"}
}