{
  "type": "Feature",
  "properties": {
    "iso:country":"FR",
    "sg:address":"36, Rue de la Briche, 93200 Saint Denis",
    "sg:orig_category":"Non-Classified Establishments",
    "sg:phone":"+33 1 49 17 01 73",
    "sg:province":"Ile de France",
    "wof:name":"Kiloutou S.a.",
    "wof:placetype":"venue"
},
  "geometry": {"coordinates":[2.340184,48.942959],"type":"Point"}
}