{
  "type": "Feature",
  "properties": {
    "iso:country":"FR",
    "sg:address":"5 rue Paul Sabatier 71100 Chalon Sur Saone",
    "sg:city":"Chalon-sur-Sa\u00f4ne",
    "sg:classifiers":[
        {
            "category":"Banks & Credit Unions",
            "subcategory":"Bureau De Change",
            "type":"Services"
        }
    ],
    "sg:phone":"+33 3 85 47 88 00",
    "sg:postcode":"71100",
    "sg:province":"Bourgogne",
    "sg:tags":[
        "press",
        "hydraulic"
    ],
    "wof:name":"Pinette Emidecau Industrie S.a.",
    "wof:placetype":"venue"
},
  "geometry": {"coordinates":[4.85457,46.81184],"type":"Point"}
}