{
  "type": "Feature",
  "properties": {
    "iso:country":"FR",
    "sg:address":"9, Rue du Moulin, 02110 Montigny en Arrouaise",
    "sg:orig_category":"Non-Classified Establishments",
    "sg:phone":"+33 3 23 07 93 83",
    "sg:province":"Picardie",
    "wof:name":"Favereaux S.a.",
    "wof:placetype":"venue"
},
  "geometry": {"coordinates":[3.472175,49.904137],"type":"Point"}
}