{
  "type": "Feature",
  "properties": {
    "iso:country":"FR",
    "sg:address":"Rte de Saint Sauveur",
    "sg:city":"Bricquebec",
    "sg:orig_category":"Non-Classified Establishments",
    "sg:phone":"+33 2 33 52 24 77",
    "sg:postcode":"50260",
    "sg:province":"Basse Normandie",
    "wof:name":"Etablissement Requier S.a.s.",
    "wof:placetype":"venue"
},
  "geometry": {"coordinates":[-1.634204,49.467323],"type":"Point"}
}