{
  "type": "Feature",
  "properties": {
    "addr:full":"19, Av. Jules Ferry, 74200 Thonon les Bains Rhone-Alpes 74200",
    "addr:postcode":"74200;74200",
    "addr:street":"19 Av. Jules Ferry",
    "iso:country":"FR",
    "sg:address":"19, Av. Jules Ferry, 74200 Thonon les Bains",
    "sg:orig_category":"Unclassifiable Establishments",
    "sg:phone":"+33 4 50 71 36 92",
    "sg:postcode":"74200",
    "sg:province":"Rhone-Alpes",
    "wof:name":"G. Dubouloz S.a.",
    "wof:placetype":"venue"
},
  "geometry": {"coordinates":[6.484333,46.372898],"type":"Point"}
}