{
  "type": "Feature",
  "properties": {
    "addr:full":"B.P. 123, 59330 Hautmont^^158, Rue de Louvroil, 59330 Hautmont Nord Pas-de-Calais",
    "addr:housenumber":"b.p. 123",
    "addr:postcode":"59330;59330",
    "addr:street":"Rue De Louvroil",
    "iso:country":"FR",
    "sg:address":"B.P. 123, 59330 Hautmont^^158, Rue de Louvroil, 59330 Hautmont",
    "sg:orig_category":"Non-Classified Establishments",
    "sg:phone":"+33 3 27 68 68 68",
    "sg:province":"Nord Pas-de-Calais",
    "wof:name":"Jouannot Et Compagnie S.a.",
    "wof:placetype":"venue"
},
  "geometry": {"coordinates":[3.921155,50.250759],"type":"Point"}
}