{
  "type": "Feature",
  "properties": {
    "addr:full":"13, Rue Michel le Comte, 75003 Paris Ile de France",
    "addr:housenumber":"13",
    "addr:postcode":"75003",
    "addr:street":"Rue Michel Le Comte",
    "iso:country":"FR",
    "sg:address":"13, Rue Michel le Comte, 75003 Paris",
    "sg:orig_category":"Unclassifiable Establishments",
    "sg:phone":"+33 1 49 72 89 89",
    "sg:province":"Ile de France",
    "wof:name":"Com\u00e9xo S.a.",
    "wof:placetype":"venue"
},
  "geometry": {"coordinates":[2.355816,48.862156],"type":"Point"}
}