{
  "type": "Feature",
  "properties": {
    "addr:full":"Cote Du Baron Z I Le Lac 07000 Privas Rhone-Alpes 07000",
    "addr:postcode":"07000;07000",
    "addr:street":"Cote Du Baron Z I Le Lac",
    "iso:country":"FR",
    "sg:address":"Cote Du Baron Z I Le Lac 07000 Privas",
    "sg:classifiers":[
        {
            "category":"Shopping",
            "subcategory":"Stationery & Office Supplies",
            "type":"Retail Goods"
        }
    ],
    "sg:phone":"+33 4 75 64 60 63",
    "sg:postcode":"07000",
    "sg:province":"Rhone-Alpes",
    "sg:tags":[
        "information",
        "technology",
        "telecommunication",
        "equipment"
    ],
    "wof:name":"Technopli",
    "wof:placetype":"venue"
},
  "geometry": {"coordinates":[4.59695,44.738419],"type":"Point"}
}