{
  "type": "Feature",
  "properties": {
    "iso:country":"FR",
    "sg:address":"27 Rue Pierre S\u00e9mard 69800 St Priest",
    "sg:classifiers":[
        {
            "category":"Professional",
            "type":"Services"
        }
    ],
    "sg:phone":"+33 4 72 23 40 50",
    "sg:province":"Rhone-Alpes",
    "sg:tags":[
        "transport",
        "road"
    ],
    "wof:name":"Transports Huppener Lambert Et Valette (sa)",
    "wof:placetype":"venue"
},
  "geometry": {"coordinates":[4.927587,45.687618],"type":"Point"}
}