{
  "type": "Feature",
  "properties": {
    "addr:full":"16, Rue Allard Dugauquier, 59040 Lille C\u00e9dex^^16, Rue Allard Dugauquier, 59800 Lille Nord Pas-de-Calais 59800",
    "addr:housenumber":"16",
    "addr:postcode":"59040;59800;59800",
    "addr:street":"Rue Allard Dugauquier;Rue Allard Dugauquier",
    "iso:country":"FR",
    "sg:address":"16, Rue Allard Dugauquier, 59040 Lille C\u00e9dex^^16, Rue Allard Dugauquier, 59800 Lille",
    "sg:orig_category":"Non-Classified Establishments",
    "sg:phone":"+33 3 20 15 55 55",
    "sg:postcode":"59800",
    "sg:province":"Nord Pas-de-Calais",
    "wof:name":"Choky S.a.",
    "wof:placetype":"venue"
},
  "geometry": {"coordinates":[3.08024,50.636189],"type":"Point"}
}