{
  "type": "Feature",
  "properties": {
    "addr:full":"46, Rue de Dijon, 21121 Daix Daix Bourgogne 21121",
    "addr:housenumber":"46",
    "addr:postcode":"21121;21121",
    "addr:street":"Rue De Dijon",
    "iso:country":"FR",
    "sg:address":"46, Rue de Dijon, 21121 Daix",
    "sg:city":"Daix",
    "sg:orig_category":"Unclassifiable Establishments",
    "sg:phone":"+33 3 80 56 37 31",
    "sg:postcode":"21121",
    "sg:province":"Bourgogne",
    "wof:name":"Bidault S.a.r.l.",
    "wof:placetype":"venue"
},
  "geometry": {"coordinates":[5.00097,47.347675],"type":"Point"}
}