{
  "type": "Feature",
  "properties": {
    "addr:full":"Rue Lech Walesa Lognes Ile de France 77185",
    "addr:postcode":"77185",
    "addr:street":"Rue Lech Walesa;Ile De France",
    "iso:country":"FR",
    "sg:address":"Rue Lech Walesa",
    "sg:city":"Lognes",
    "sg:orig_category":"Unclassifiable Establishments",
    "sg:phone":"+33 1 60 06 38 38",
    "sg:postcode":"77185",
    "sg:province":"Ile de France",
    "wof:name":"Pap Star France S.a.r.l.",
    "wof:placetype":"venue"
},
  "geometry": {"coordinates":[2.625685,48.826942],"type":"Point"}
}