{
  "type": "Feature",
  "properties": {
    "addr:full":"Rte de Reims Montcornet Picardie 02340",
    "addr:postcode":"02340",
    "addr:street":"Rte De Reims;Picardie",
    "iso:country":"FR",
    "sg:address":"Rte de Reims",
    "sg:city":"Montcornet",
    "sg:orig_category":"Unclassifiable Establishments",
    "sg:phone":"+33 3 23 21 88 88",
    "sg:postcode":"02340",
    "sg:province":"Picardie",
    "wof:name":"Aromont S.a.",
    "wof:placetype":"venue"
},
  "geometry": {"coordinates":[4.01136,49.687805],"type":"Point"}
}