{
  "type": "Feature",
  "properties": {
    "addr:full":"B.P. 28, 67127 Molsheim C\u00e9dex^^Rue Claude Chapp\u00e9 - ZI, 67120 Duppigheim Molsheim Alsace 67120",
    "addr:postcode":"67127;67120;67120",
    "addr:street":"B.P. 28;Zi",
    "iso:country":"FR",
    "sg:address":"B.P. 28, 67127 Molsheim C\u00e9dex^^Rue Claude Chapp\u00e9 - ZI, 67120 Duppigheim",
    "sg:city":"Molsheim",
    "sg:orig_category":"Non-Classified Establishments",
    "sg:phone":"+33 3 88 48 20 00",
    "sg:postcode":"67120",
    "sg:province":"Alsace",
    "wof:name":"Metaltex France S.a.",
    "wof:placetype":"venue"
},
  "geometry": {"coordinates":[7.490672,48.540382],"type":"Point"}
}