{
  "type": "Feature",
  "properties": {
    "addr:full":"42, Rue Edmond Besse, 33000 Bordeaux Bordeaux Aquitaine 33000",
    "addr:housenumber":"42",
    "addr:postcode":"33000;33000",
    "addr:street":"Rue Edmond Besse",
    "iso:country":"FR",
    "sg:address":"42, Rue Edmond Besse, 33000 Bordeaux",
    "sg:city":"Bordeaux",
    "sg:orig_category":"Unclassifiable Establishments",
    "sg:phone":"+33 5 56 69 35 00",
    "sg:postcode":"33000",
    "sg:province":"Aquitaine",
    "wof:name":"Sud-ouest Caoutchouc S.a.",
    "wof:placetype":"venue"
},
  "geometry": {"coordinates":[-0.581039,44.836636],"type":"Point"}
}