{
  "type": "Feature",
  "properties": {
    "iso:country":"FR",
    "sg:address":"Av 18\u00e8me Bcp 55700 Stenay",
    "sg:classifiers":[
        {
            "category":"Manufacturing",
            "subcategory":"Paper Products",
            "type":"Manufacturing & Wholesale Goods"
        }
    ],
    "sg:phone":"+33 3 29 80 30 10",
    "sg:province":"Lorraine",
    "sg:tags":[
        "raw",
        "material",
        "-",
        "cardboard"
    ],
    "wof:name":"Ahltrom Labelpack",
    "wof:placetype":"venue"
},
  "geometry": {"coordinates":[5.178843,49.489513],"type":"Point"}
}