{
  "type": "Feature",
  "properties": {
    "addr:full":"231 Rue St Honor\u00e9 75001 Paris Ile de France 75001",
    "addr:housenumber":"231",
    "addr:postcode":"75001;75001",
    "addr:street":"Rue St Honore\u0301",
    "iso:country":"FR",
    "sg:address":"231 Rue St Honor\u00e9 75001 Paris",
    "sg:classifiers":[
        {
            "category":"Communications",
            "type":"Services"
        }
    ],
    "sg:phone":"+33 1 49 26 08 91",
    "sg:postcode":"75001",
    "sg:province":"Ile de France",
    "sg:tags":[
        "advice",
        "interpretation",
        "translation",
        "business"
    ],
    "wof:name":"Sogedicom Sarl",
    "wof:placetype":"venue"
},
  "geometry": {"coordinates":[2.329003,48.866241],"type":"Point"}
}