{
  "type": "Feature",
  "properties": {
    "addr:full":"2 Avenue Lionel Terray 69330 Meyzieu Rhone-Alpes",
    "addr:housenumber":"2",
    "addr:postcode":"69330",
    "addr:street":"Avenue Lionel Terray",
    "iso:country":"FR",
    "sg:address":"2 Avenue Lionel Terray 69330 Meyzieu",
    "sg:classifiers":[
        {
            "category":"Manufacturing",
            "subcategory":"Rubber & Plastics",
            "type":"Manufacturing & Wholesale Goods"
        }
    ],
    "sg:phone":"+33 4 78 04 70 70",
    "sg:province":"Rhone-Alpes",
    "wof:name":"Plastiques Et Isolants Techniques Sa",
    "wof:placetype":"venue"
},
  "geometry": {"coordinates":[5.017525,45.771618],"type":"Point"}
}