{
  "type": "Feature",
  "properties": {
    "addr:full":"122, Bd Th\u00e9ophile Sueur, 93100 Montreuil Ile de France",
    "addr:housenumber":"122",
    "addr:postcode":"93100",
    "addr:street":"Bd The\u0301Ophile Sueur",
    "iso:country":"FR",
    "sg:address":"122, Bd Th\u00e9ophile Sueur, 93100 Montreuil",
    "sg:orig_category":"Unclassifiable Establishments",
    "sg:phone":"+33 1 48 54 52 30",
    "sg:province":"Ile de France",
    "wof:name":"S.e.p.t. S.a.r.l. - Soci\u00e9t\u00e9 Europ\u00e9enne De Produits Techniques",
    "wof:placetype":"venue"
},
  "geometry": {"coordinates":[2.468761,48.865753],"type":"Point"}
}