{
  "type": "Feature",
  "properties": {
    "addr:full":"11, Rue de Versailles, 49600 Beaupr\u00e9au Pays de Loire",
    "addr:housenumber":"11",
    "addr:postcode":"49600",
    "addr:street":"Rue De Versailles",
    "iso:country":"FR",
    "sg:address":"11, Rue de Versailles, 49600 Beaupr\u00e9au",
    "sg:orig_category":"Unclassifiable Establishments",
    "sg:phone":"+33 2 41 63 01 46",
    "sg:province":"Pays de Loire",
    "wof:name":"Etablissements Peau P\u00e8re Et Fils S.a.",
    "wof:placetype":"venue"
},
  "geometry": {"coordinates":[-0.9809,47.205242],"type":"Point"}
}