{
  "type": "Feature",
  "properties": {
    "iso:country":"FR",
    "sg:address":"2 Rue Joseph Monier, Rueil-Malmaison, Dept 92",
    "sg:classifiers":[
        {
            "category":"Banks & Credit Unions",
            "subcategory":"Bank",
            "type":"Services"
        }
    ],
    "sg:province":"Picardie",
    "wof:name":"Sfcv (societe Francaise Du Cheque De Voyage)",
    "wof:placetype":"venue"
},
  "geometry": {"coordinates":[2.172343,48.890797],"type":"Point"}
}