{
  "type": "Feature",
  "properties": {
    "addr:full":"ZA Le Valmer Cherr\u00e9 Pays de Loire 72400",
    "addr:postcode":"72400",
    "addr:street":"Za Le",
    "iso:country":"FR",
    "sg:address":"ZA Le Valmer",
    "sg:city":"Cherr\u00e9",
    "sg:orig_category":"Unclassifiable Establishments",
    "sg:phone":"+33 2 43 60 19 00",
    "sg:postcode":"72400",
    "sg:province":"Pays de Loire",
    "wof:name":"Rillettes Sarthoises Du Val D'huisne S.a.s.",
    "wof:placetype":"venue"
},
  "geometry": {"coordinates":[0.65629,48.173904],"type":"Point"}
}