{
  "type": "Feature",
  "properties": {
    "iso:country":"FR",
    "sg:address":"B.P. 9, 74311 Cluses C\u00e9dex^^94, Av. des Iles - ZI des Iles d'Arve Thyez, 74300 Cluses",
    "sg:orig_category":"Non-Classified Establishments",
    "sg:phone":"+33 4 50 34 57 77",
    "sg:postcode":"74300",
    "sg:province":"Rhone-Alpes",
    "wof:name":"F.p. Hydraulique S.a.",
    "wof:placetype":"venue"
},
  "geometry": {"coordinates":[6.540297,46.074963],"type":"Point"}
}