{
  "type": "Feature",
  "properties": {
    "addr:full":"B.P. 317, 59056 Roubaix C\u00e9dex 1^^85, Rue Monge, 59100 Roubaix Nord Pas-de-Calais 59100",
    "addr:housenumber":"b.p. 317;1;^ 85",
    "addr:postcode":"59056;59100;59100",
    "addr:street":"^;Rue Monge",
    "iso:country":"FR",
    "sg:address":"B.P. 317, 59056 Roubaix C\u00e9dex 1^^85, Rue Monge, 59100 Roubaix",
    "sg:orig_category":"Non-Classified Establishments",
    "sg:phone":"+33 3 20 65 96 96",
    "sg:postcode":"59100",
    "sg:province":"Nord Pas-de-Calais",
    "wof:name":"Bayart Achille Et Compagnie S.a.",
    "wof:placetype":"venue"
},
  "geometry": {"coordinates":[3.1752,50.691704],"type":"Point"}
}