{
  "type": "Feature",
  "properties": {
    "addr:full":"79 Chem De L'Etang Long 66380 Pia Languedoc-Roussillon",
    "addr:housenumber":"79",
    "addr:postcode":"66380",
    "addr:street":"Chem De L'Etang Long",
    "iso:country":"FR",
    "sg:address":"79 Chem De L'Etang Long 66380 Pia",
    "sg:classifiers":[
        {
            "category":"Manufacturing",
            "subcategory":"Rubber & Plastics",
            "type":"Manufacturing & Wholesale Goods"
        }
    ],
    "sg:phone":"+33 4 68 63 41 22",
    "sg:province":"Languedoc-Roussillon",
    "wof:name":"Citec Environnement",
    "wof:placetype":"venue"
},
  "geometry": {"coordinates":[2.9041,42.742199],"type":"Point"}
}