{
  "type": "Feature",
  "properties": {
    "addr:full":"29403 Landivisiau Landivisiau Bretagne 29400",
    "addr:postcode":"29403;29400",
    "iso:country":"FR",
    "sg:address":"29403 Landivisiau",
    "sg:city":"Landivisiau",
    "sg:classifiers":[
        {
            "category":"Wholesale",
            "subcategory":"Meat",
            "type":"Manufacturing & Wholesale Goods"
        }
    ],
    "sg:phone":"+33 2 98 68 68 68",
    "sg:postcode":"29400",
    "sg:province":"Bretagne",
    "sg:tags":[
        "food",
        "cooked",
        "product",
        "related"
    ],
    "wof:name":"Bretonne De Salaisons",
    "wof:placetype":"venue"
},
  "geometry": {"coordinates":[-4.07161,48.51049],"type":"Point"}
}