{
  "type": "Feature",
  "properties": {
    "iso:country":"FR",
    "sg:address":"6 Rue Fran\u00e7ois Elleviou 35000 Rennes",
    "sg:city":"Rennes",
    "sg:classifiers":[
        {
            "category":"Utilities",
            "subcategory":"Electric",
            "type":"Services"
        }
    ],
    "sg:phone":"+33 2 99 65 51 66",
    "sg:postcode":"35000",
    "sg:province":"Bretagne",
    "sg:tags":[
        "electricity",
        "electronic",
        "electrical",
        "equipment"
    ],
    "wof:name":"Aidelec Reseaux",
    "wof:placetype":"venue"
},
  "geometry": {"coordinates":[-1.688351,48.099648],"type":"Point"}
}