{
  "type": "Feature",
  "properties": {
    "iso:country":"FR",
    "sg:address":"route des Gorges du Sierroz 73100 Gresy sur Aix",
    "sg:classifiers":[
        {
            "category":"Manufacturing",
            "subcategory":"Metals",
            "type":"Manufacturing & Wholesale Goods"
        }
    ],
    "sg:phone":"+33 4 79 88 50 00",
    "sg:postcode":"73100",
    "sg:province":"Rhone-Alpes",
    "sg:tags":[
        "chromium-metal"
    ],
    "wof:name":"Cellinox Sa",
    "wof:placetype":"venue"
},
  "geometry": {"coordinates":[5.921839,45.723614],"type":"Point"}
}