{
  "type": "Feature",
  "properties": {
    "iso:country":"FR",
    "sg:address":"3 Rue Des Malines Zi Des Maline 91090 Lisses",
    "sg:classifiers":[
        {
            "category":"Manufacturing",
            "subcategory":"Rubber & Plastics",
            "type":"Manufacturing & Wholesale Goods"
        }
    ],
    "sg:phone":"+33 1 64 97 56 00",
    "sg:province":"Ile de France",
    "wof:name":"Fluortec",
    "wof:placetype":"venue"
},
  "geometry": {"coordinates":[2.423843,48.597694],"type":"Point"}
}