{
  "type": "Feature",
  "properties": {
    "iso:country":"FR",
    "sg:address":"Rue Industrie",
    "sg:city":"Montbrison",
    "sg:orig_category":"Unclassifiable Establishments",
    "sg:phone":"+33 4 77 58 31 77",
    "sg:postcode":"42600",
    "sg:province":"Rhone-Alpes",
    "wof:name":"Soci\u00e9t\u00e9 Montbri Remorques L\u00e9v\u00eaques S.a.",
    "wof:placetype":"venue"
},
  "geometry": {"coordinates":[3.996271,45.571075],"type":"Point"}
}