{
  "type": "Feature",
  "properties": {
    "addr:full":"Chemin de L\u00e8ze Morte Saint Sulpice sur L\u00e8ze Midi Pyr\u00e9n\u00e9es 31410",
    "addr:postcode":"31410",
    "addr:street":"Chemin De Le\u0300Ze Morte Saint Sulpice Sur Le\u0300Ze Midi Pyre\u0301Ne\u0301Es",
    "iso:country":"FR",
    "sg:address":"Chemin de L\u00e8ze Morte",
    "sg:city":"Saint Sulpice sur L\u00e8ze",
    "sg:orig_category":"Non-Classified Establishments",
    "sg:phone":"+33 5 61 97 38 45",
    "sg:postcode":"31410",
    "sg:province":"Midi Pyr\u00e9n\u00e9es",
    "wof:name":"D\u00e9colletage De La Vall\u00e9e De La L\u00e8ze S.a.r.l.",
    "wof:placetype":"venue"
},
  "geometry": {"coordinates":[1.330745,43.327606],"type":"Point"}
}