{
  "type": "Feature",
  "properties": {
    "addr:full":"20, Rue du Fort, 67118 Geispolsheim Geispolsheim Alsace 67400",
    "addr:housenumber":"20",
    "addr:postcode":"67118;67400",
    "addr:street":"Rue Du Fort",
    "iso:country":"FR",
    "sg:address":"20, Rue du Fort, 67118 Geispolsheim",
    "sg:city":"Geispolsheim",
    "sg:orig_category":"Unclassifiable Establishments",
    "sg:phone":"+33 3 88 66 08 45",
    "sg:postcode":"67400",
    "sg:province":"Alsace",
    "wof:name":"Alsace Electro Di\u00e9sel S.a.",
    "wof:placetype":"venue"
},
  "geometry": {"coordinates":[7.696912,48.518806],"type":"Point"}
}