{
  "type": "Feature",
  "properties": {
    "addr:full":"B.P. 12, 41400 Bourr\u00e9^^Rte des Roches, 41400 Bourr\u00e9 Bourr\u00e9 Centre 41400",
    "addr:postcode":"41400;41400;41400",
    "addr:street":"B.P. 12;Des Roches;Bourre\u0301",
    "iso:country":"FR",
    "sg:address":"B.P. 12, 41400 Bourr\u00e9^^Rte des Roches, 41400 Bourr\u00e9",
    "sg:city":"Bourr\u00e9",
    "sg:orig_category":"Non-Classified Establishments",
    "sg:phone":"+33 2 54 32 08 62",
    "sg:postcode":"41400",
    "sg:province":"Centre",
    "wof:name":"Rolez S.a.",
    "wof:placetype":"venue"
},
  "geometry": {"coordinates":[1.113451,47.301311],"type":"Point"}
}