{
  "type": "Feature",
  "properties": {
    "iso:country":"FR",
    "sg:address":"10, Av. du Docteur Schweitzer, 69330 Meyzieu",
    "sg:orig_category":"Non-Classified Establishments",
    "sg:phone":"+33 4 78 31 95 95",
    "sg:postcode":"69330",
    "sg:province":"Rhone-Alpes",
    "wof:name":"M.i.l. S.a.r.l. - Maintenance Industrielle Lyonnaise",
    "wof:placetype":"venue"
},
  "geometry": {"coordinates":[5.02861,45.765289],"type":"Point"}
}