{
  "type": "Feature",
  "properties": {
    "addr:full":"B.P. 16, 06370 Mouans Sartoux^^252, Av. de la Quiera, 06370 Mouans Sartoux Midi Pyr\u00e9n\u00e9es",
    "addr:postcode":"06370;06370",
    "addr:street":"B.P. 16;Av. De La Quiera",
    "iso:country":"FR",
    "sg:address":"B.P. 16, 06370 Mouans Sartoux^^252, Av. de la Quiera, 06370 Mouans Sartoux",
    "sg:orig_category":"Non-Classified Establishments",
    "sg:phone":"+33 4 92 92 58 00",
    "sg:province":"Midi Pyr\u00e9n\u00e9es",
    "wof:name":"Construction Sigma S.a.",
    "wof:placetype":"venue"
},
  "geometry": {"coordinates":[6.96621,43.618511],"type":"Point"}
}