{
  "type": "Feature",
  "properties": {
    "iso:country":"FR",
    "sg:address":"13 rue Honville 88520 Ban De Laveline",
    "sg:classifiers":[
        {
            "category":"Health Services",
            "subcategory":"Hospital",
            "type":"Services"
        }
    ],
    "sg:phone":"+33 3 29 51 77 48",
    "sg:postcode":"88520",
    "sg:province":"Lorraine",
    "sg:tags":[
        "furniture"
    ],
    "wof:name":"Daillot Sa",
    "wof:placetype":"venue"
},
  "geometry": {"coordinates":[7.077339,48.241039],"type":"Point"}
}