{
  "type": "Feature",
  "properties": {
    "iso:country":"FR",
    "sg:address":"10 Rue Pierre G\u00e9min 53800 Renaz\u00e9",
    "sg:classifiers":[
        {
            "category":"Professional",
            "subcategory":"Computer Services",
            "type":"Services"
        }
    ],
    "sg:phone":"+33 2 43 09 63 63",
    "sg:postcode":"53800",
    "sg:province":"Pays de Loire",
    "sg:tags":[
        "information",
        "technology"
    ],
    "wof:name":"Rover Sa",
    "wof:placetype":"venue"
},
  "geometry": {"coordinates":[-1.040699,47.790184],"type":"Point"}
}