{
  "type": "Feature",
  "properties": {
    "iso:country":"FR",
    "sg:address":"Zi Le Gua Zi Sud 34880 Laverune",
    "sg:classifiers":[
        {
            "category":"Farming",
            "subcategory":"Fish & Marine Products",
            "type":"Manufacturing & Wholesale Goods"
        }
    ],
    "sg:phone":"+33 4 67 07 05 20",
    "sg:postcode":"34880",
    "sg:province":"Languedoc-Roussillon",
    "sg:tags":[
        "pharmaceutical",
        "entertainment",
        "-",
        "miscellaneous",
        "chemical",
        "game",
        "chemistry",
        "by-product"
    ],
    "wof:name":"Esteban Sa",
    "wof:placetype":"venue"
},
  "geometry": {"coordinates":[3.80383,43.584637],"type":"Point"}
}