{
  "type": "Feature",
  "properties": {
    "iso:country":"FR",
    "sg:address":"1202 Vieux Chem De Toulon 83300 Hy\u00e8res",
    "sg:classifiers":[
        {
            "category":"Farming",
            "subcategory":"Farm",
            "type":"Manufacturing & Wholesale Goods"
        }
    ],
    "sg:phone":"+33 4 94 12 31 00",
    "sg:province":"Haute Normandie",
    "sg:tags":[
        "horticulture",
        "agriculture",
        "livestock"
    ],
    "wof:name":"Snc Daziano",
    "wof:placetype":"venue"
},
  "geometry": {"coordinates":[6.463645,43.539795],"type":"Point"}
}