{
  "type": "Feature",
  "properties": {
    "addr:full":"16 Av De Chavailles Bureaux Du Lac Imm 1 33525 Bruges Cedex Lorraine",
    "addr:housenumber":"1",
    "addr:postcode":"33525",
    "addr:street":"16 Av De Chavailles;Imm",
    "iso:country":"FR",
    "sg:address":"16 Av De Chavailles Bureaux Du Lac Imm 1 33525 Bruges Cedex",
    "sg:classifiers":[
        {
            "category":"Manufacturing",
            "subcategory":"Paper Products",
            "type":"Manufacturing & Wholesale Goods"
        }
    ],
    "sg:phone":"+33 5 57 19 39 50",
    "sg:province":"Lorraine",
    "sg:tags":[
        "raw",
        "material",
        "-",
        "cardboard"
    ],
    "wof:name":"Papeteries De France",
    "wof:placetype":"venue"
},
  "geometry": {"coordinates":[-0.610265,44.887768],"type":"Point"}
}