{
  "type": "Feature",
  "properties": {
    "addr:full":"Domaine Dozon le Rouilly 37500 Ligr\u00e9 Ligr\u00e9 Centre 37500",
    "addr:housenumber":"ligre\u0301",
    "addr:postcode":"37500;37500",
    "iso:country":"FR",
    "sg:address":"Domaine Dozon le Rouilly 37500 Ligr\u00e9",
    "sg:city":"Ligr\u00e9",
    "sg:orig_category":"Non-Classified Establishments",
    "sg:phone":"+33 2 47 93 17 67",
    "sg:postcode":"37500",
    "sg:province":"Centre",
    "wof:name":"Dozon E.a.r.l.",
    "wof:placetype":"venue"
},
  "geometry": {"coordinates":[0.19145,47.077888],"type":"Point"}
}