{
  "type": "Feature",
  "properties": {
    "addr:full":"15, Les Plaines, 09390 L'Hospitalet pr\u00e8s l'Andorre Midi Pyr\u00e9n\u00e9es",
    "addr:housenumber":"15",
    "addr:postcode":"09390",
    "addr:street":"Les Plaines",
    "iso:country":"FR",
    "sg:address":"15, Les Plaines, 09390 L'Hospitalet pr\u00e8s l'Andorre",
    "sg:orig_category":"Non-Classified Establishments",
    "sg:phone":"+33 5 61 05 20 25",
    "sg:province":"Midi Pyr\u00e9n\u00e9es",
    "wof:name":"Pyr\u00e9transit",
    "wof:placetype":"venue"
},
  "geometry": {"coordinates":[1.59837,42.541821],"type":"Point"}
}