{
  "type": "Feature",
  "properties": {
    "addr:full":"129, Rue Servient, 69003 Lyon Rhone-Alpes 69003",
    "addr:housenumber":"129",
    "addr:postcode":"69003;69003",
    "addr:street":"Rue Servient",
    "iso:country":"FR",
    "sg:address":"129, Rue Servient, 69003 Lyon",
    "sg:orig_category":"Unclassifiable Establishments",
    "sg:phone":"+33 4 78 63 61 50",
    "sg:postcode":"69003",
    "sg:province":"Rhone-Alpes",
    "wof:name":"Biscuiterie Bn S.a.",
    "wof:placetype":"venue"
},
  "geometry": {"coordinates":[4.854983,45.760986],"type":"Point"}
}