{
  "type": "Feature",
  "properties": {
    "addr:full":"155 Av D'Italie 74300 Cluses Rhone-Alpes 74300",
    "addr:postcode":"74300;74300",
    "addr:street":"155 Av D'Italie",
    "iso:country":"FR",
    "sg:address":"155 Av D'Italie 74300 Cluses",
    "sg:classifiers":[
        {
            "category":"Shopping",
            "subcategory":"Computers & Home Electronics",
            "type":"Retail Goods"
        }
    ],
    "sg:phone":"+33 4 50 96 06 99",
    "sg:postcode":"74300",
    "sg:province":"Rhone-Alpes",
    "sg:tags":[
        "electronic",
        "electrical",
        "equipment"
    ],
    "wof:name":"Distribution Automatique Service Sa",
    "wof:placetype":"venue"
},
  "geometry": {"coordinates":[6.595942,46.048561],"type":"Point"}
}