{
  "type": "Feature",
  "properties": {
    "iso:country":"FR",
    "sg:address":"5, Rue des Rubis - ZI, 38280 Villette d'Anthon",
    "sg:orig_category":"Unclassifiable Establishments",
    "sg:phone":"+33 4 72 02 43 73",
    "sg:province":"Rhone-Alpes",
    "wof:name":"M.i.p. Or\u00e8nes",
    "wof:placetype":"venue"
},
  "geometry": {"coordinates":[5.129836,45.793613],"type":"Point"}
}