{
  "type": "Feature",
  "properties": {
    "iso:country":"FR",
    "sg:address":"2-4 rue Saint Thomas; S. L\u00f4",
    "sg:classifiers":[
        {
            "category":"Banks & Credit Unions",
            "subcategory":"Bank",
            "type":"Services"
        }
    ],
    "sg:phone":"+33 2 33 77 34 10",
    "sg:province":"Picardie",
    "wof:name":"Cr\u00e9dit Industriel, De Normandie Sa",
    "wof:placetype":"venue"
},
  "geometry": {"coordinates":[-73.28117399999999,42.277397],"type":"Point"}
}