{
  "type": "Feature",
  "properties": {
    "addr:full":"B.P. 8, 54250 Champigneulles^^ZI du Canal, 54250 Champigneulles Lorraine 54250",
    "addr:housenumber":"8",
    "addr:postcode":"54250;54250;54250",
    "addr:street":"B.P.;Du Canal",
    "iso:country":"FR",
    "sg:address":"B.P. 8, 54250 Champigneulles^^ZI du Canal, 54250 Champigneulles",
    "sg:orig_category":"Etanch\u00e9it\u00e9 pour la construction, Mat\u00e9riaux d' Etanch\u00e9it\u00e9, Produits d' Gaines isolantes Isolants pour",
    "sg:phone":"+33 3 83 38 80 80",
    "sg:postcode":"54250",
    "sg:province":"Lorraine",
    "wof:name":"Ouest Isol S.a.",
    "wof:placetype":"venue"
},
  "geometry": {"coordinates":[6.16533,48.73391],"type":"Point"}
}