{
  "type": "Feature",
  "properties": {
    "iso:country":"FR",
    "sg:address":"6, Impasse Denise Nogent l'Artaud, 02310 Charly",
    "sg:orig_category":"Non-Classified Establishments",
    "sg:phone":"+33 3 23 70 00 31",
    "sg:province":"Picardie",
    "wof:name":"Gr\u00e9goire Richard S.a.r.l.",
    "wof:placetype":"venue"
},
  "geometry": {"coordinates":[3.321343,48.965584],"type":"Point"}
}