{
  "type": "Feature",
  "properties": {
    "addr:full":"B.P. 204, 95106 Argenteuil C\u00e9dex^^12/14, Rue Jean Poulmarek, 95100 Argenteuil Ile de France",
    "addr:housenumber":"b.p. 204;14",
    "addr:postcode":"95106;95100;ile",
    "addr:street":"Rue Jean Poulmarek;De France",
    "iso:country":"FR",
    "sg:address":"B.P. 204, 95106 Argenteuil C\u00e9dex^^12/14, Rue Jean Poulmarek, 95100 Argenteuil",
    "sg:orig_category":"Non-Classified Establishments",
    "sg:phone":"+33 1 30 25 75 75",
    "sg:province":"Ile de France",
    "wof:name":"Pentax France S.a.",
    "wof:placetype":"venue"
},
  "geometry": {"coordinates":[2.245075,48.942097],"type":"Point"}
}