{
  "type": "Feature",
  "properties": {
    "iso:country":"FR",
    "sg:address":"B.P. 412",
    "sg:city":"Lab\u00e8ge C\u00e9dex",
    "sg:orig_category":"Non-Classified Establishments",
    "sg:phone":"+33 5 62 24 20 20",
    "sg:postcode":"31314",
    "sg:province":"Midi Pyr\u00e9n\u00e9es",
    "wof:name":"T.d.i.e. S.a. - Technique Et D\u00e9veloppement Informatique Et Edition",
    "wof:placetype":"venue"
},
  "geometry": {"coordinates":[1.52968,43.528912],"type":"Point"}
}