{
  "type": "Feature",
  "properties": {
    "addr:full":"7, Rue du 19 mars 1962, 87350 Panazol Limousin",
    "addr:housenumber":"7",
    "addr:postcode":"87350",
    "addr:street":"Rue Du 19 Mars 1962",
    "iso:country":"FR",
    "sg:address":"7, Rue du 19 mars 1962, 87350 Panazol",
    "sg:orig_category":"Non-Classified Establishments",
    "sg:phone":"+33 5 55 30 48 90",
    "sg:province":"Limousin",
    "wof:name":"Panazol Nettoyage S.a.s.",
    "wof:placetype":"venue"
},
  "geometry": {"coordinates":[1.299613,45.828655],"type":"Point"}
}