{
  "type": "Feature",
  "properties": {
    "addr:full":"2, Rue du Pont Colbert, 78000 Versailles Ile de France",
    "addr:housenumber":"2",
    "addr:postcode":"78000",
    "addr:street":"Rue Du Pont Colbert",
    "iso:country":"FR",
    "sg:address":"2, Rue du Pont Colbert, 78000 Versailles",
    "sg:orig_category":"Non-Classified Establishments",
    "sg:phone":"+33 1 39 50 97 79",
    "sg:province":"Ile de France",
    "wof:name":"Mill\u00e9nnium S.a.",
    "wof:placetype":"venue"
},
  "geometry": {"coordinates":[2.146112,48.791454],"type":"Point"}
}