{
  "type": "Feature",
  "properties": {
    "iso:country":"FR",
    "sg:address":"9 Chemin Du Vieux Chene Zirst 38240 Meylan",
    "sg:classifiers":[
        {
            "category":"Professional",
            "subcategory":"Printing & Photocopies",
            "type":"Services"
        }
    ],
    "sg:phone":"+33 4 76 90 93 94",
    "sg:postcode":"38240",
    "sg:province":"Rhone-Alpes",
    "sg:tags":[
        "publishing"
    ],
    "wof:name":"Imatec Diffusion",
    "wof:placetype":"venue"
},
  "geometry": {"coordinates":[5.784548,45.207184],"type":"Point"}
}