{
  "type": "Feature",
  "properties": {
    "iso:country":"FR",
    "sg:address":"92/96, Rue Paul Lescop, 92000 Nanterre",
    "sg:orig_category":"Non-Classified Establishments",
    "sg:phone":"+33 1 47 21 13 17",
    "sg:province":"Ile de France",
    "wof:name":"Fours Et R\u00e9fractaires S.a.",
    "wof:placetype":"venue"
},
  "geometry": {"coordinates":[2.185186,48.896206],"type":"Point"}
}