{
  "type": "Feature",
  "properties": {
    "iso:country":"FR",
    "sg:address":"38, Rue Paul Lambard, 76120 Le Grand Quevilly",
    "sg:orig_category":"Unclassifiable Establishments",
    "sg:phone":"+33 2 35 69 65 56",
    "sg:province":"Haute Normandie",
    "wof:name":"Desormeaux S.a.",
    "wof:placetype":"venue"
},
  "geometry": {"coordinates":[1.053784,49.416759],"type":"Point"}
}