{
  "type": "Feature",
  "properties": {
    "addr:full":"Le Four \u00e0 Chaux 01640 Saint Jean le Vieux Rhone-Alpes 01640",
    "addr:postcode":"01640;01640",
    "addr:street":"Saint Jean Le",
    "iso:country":"FR",
    "sg:address":"Le Four \u00e0 Chaux 01640 Saint Jean le Vieux",
    "sg:orig_category":"Non-Classified Establishments",
    "sg:phone":"+33 4 74 36 95 83",
    "sg:postcode":"01640",
    "sg:province":"Rhone-Alpes",
    "wof:name":"Entreprise Dubois Christian",
    "wof:placetype":"venue"
},
  "geometry": {"coordinates":[5.39972,46.033405],"type":"Point"}
}