{
  "type": "Feature",
  "properties": {
    "addr:full":"B.P. 18, 59370 Mons en Baroeul^^23, Av L\u00e9on Blum, 59370 Mons en Baroeul Nord Pas-de-Calais",
    "addr:postcode":"59370;59370",
    "addr:street":"B.P. 18;Av Le\u0301On Blum",
    "iso:country":"FR",
    "sg:address":"B.P. 18, 59370 Mons en Baroeul^^23, Av L\u00e9on Blum, 59370 Mons en Baroeul",
    "sg:orig_category":"Non-Classified Establishments",
    "sg:phone":"+33 3 20 04 22 56",
    "sg:province":"Nord Pas-de-Calais",
    "wof:name":"Vidailhet S.a.",
    "wof:placetype":"venue"
},
  "geometry": {"coordinates":[3.11015,50.643887],"type":"Point"}
}