{
  "type": "Feature",
  "properties": {
    "addr:full":"69, Rue Charlet, 18000 Bourges Bourges Centre 18000",
    "addr:housenumber":"69",
    "addr:postcode":"18000;18000",
    "addr:street":"Rue Charlet",
    "iso:country":"FR",
    "sg:address":"69, Rue Charlet, 18000 Bourges",
    "sg:city":"Bourges",
    "sg:orig_category":"Non-Classified Establishments",
    "sg:phone":"+33 2 51 80 51 45",
    "sg:postcode":"18000",
    "sg:province":"Centre",
    "wof:name":"Ugine France Service S.a.",
    "wof:placetype":"venue"
},
  "geometry": {"coordinates":[2.413746,47.084618],"type":"Point"}
}