{
  "type": "Feature",
  "properties": {
    "iso:country":"FR",
    "sg:address":"74A, Rue de la R\u00e9publique, 68120 Pfastatt",
    "sg:city":"Pfastatt",
    "sg:orig_category":"Non-Classified Establishments",
    "sg:phone":"+33 3 89 52 87 87",
    "sg:postcode":"68120",
    "sg:province":"Alsace",
    "wof:name":"M.i.e. 2 S.a. - Maintenance Industrielle Europ\u00e9enne",
    "wof:placetype":"venue"
},
  "geometry": {"coordinates":[7.310723,47.767601],"type":"Point"}
}