{
  "type": "Feature",
  "properties": {
    "addr:full":"149, Anniche, 33550 Haux Haux Aquitaine 33550",
    "addr:housenumber":"149",
    "addr:postcode":"33550;33550",
    "addr:street":"Anniche",
    "iso:country":"FR",
    "sg:address":"149, Anniche, 33550 Haux",
    "sg:city":"Haux",
    "sg:orig_category":"Non-Classified Establishments",
    "sg:phone":"+33 5 56 23 05 15",
    "sg:postcode":"33550",
    "sg:province":"Aquitaine",
    "wof:name":"Vignobles Michel Pion S.c.e.a.",
    "wof:placetype":"venue"
},
  "geometry": {"coordinates":[-0.353513,44.742374],"type":"Point"}
}