{
  "type": "Feature",
  "properties": {
    "addr:full":"1 rue Hauteville; Paris; 75010 Ile de France 75010",
    "addr:housenumber":"1",
    "addr:postcode":"75010 ile;france 75010",
    "addr:street":"Rue Hauteville",
    "iso:country":"FR",
    "sg:address":"1 rue Hauteville; Paris; 75010",
    "sg:classifiers":[
        {
            "category":"Banks & Credit Unions",
            "subcategory":"Bank",
            "type":"Services"
        }
    ],
    "sg:phone":"+33 1 47 70 38 95",
    "sg:postcode":"75010",
    "sg:province":"Ile de France",
    "wof:name":"Banque Populaire, De La R\u00e9gion Nord",
    "wof:placetype":"venue"
},
  "geometry": {"coordinates":[2.349407,48.870632],"type":"Point"}
}