{
  "type": "Feature",
  "properties": {
    "iso:country":"FR",
    "sg:address":"Av. Villas",
    "sg:city":"Marmande",
    "sg:orig_category":"Non-Classified Establishments",
    "sg:phone":"+33 5 53 20 45 00",
    "sg:postcode":"47200",
    "sg:province":"Aquitaine",
    "wof:name":"Creuzet A\u00e9ronautique S.a.",
    "wof:placetype":"venue"
},
  "geometry": {"coordinates":[0.168593,44.51466],"type":"Point"}
}