{
  "type": "Feature",
  "properties": {
    "iso:country":"FR",
    "sg:address":"14, Av. Arago, 91420 Morangis",
    "sg:orig_category":"Unclassifiable Establishments",
    "sg:phone":"+33 1 69 79 36 50",
    "sg:province":"Ile de France",
    "wof:name":"Jep S.a.",
    "wof:placetype":"venue"
},
  "geometry": {"coordinates":[2.338153,48.703144],"type":"Point"}
}