{
  "type": "Feature",
  "properties": {
    "addr:full":"38, Rue du 11 Novembre, 42500 Le Chambon Feugerolles Rhone-Alpes 42500",
    "addr:housenumber":"38",
    "addr:postcode":"42500;42500",
    "addr:street":"Rue Du 11 Novembre;Chambon Feugerolles Rhone-Alpes",
    "iso:country":"FR",
    "sg:address":"38, Rue du 11 Novembre, 42500 Le Chambon Feugerolles",
    "sg:orig_category":"Unclassifiable Establishments",
    "sg:phone":"+33 4 77 61 41 86",
    "sg:postcode":"42500",
    "sg:province":"Rhone-Alpes",
    "wof:name":"Sn Loire Oxycoupage S.a.r.l. - Soci\u00e9t\u00e9 Nouvelle Loire Oxycoupage",
    "wof:placetype":"venue"
},
  "geometry": {"coordinates":[4.333797,45.397919],"type":"Point"}
}