{
  "type": "Feature",
  "properties": {
    "iso:country":"FR",
    "sg:address":"Rue du Petit Pont",
    "sg:city":"Couilly Pont aux Dames",
    "sg:orig_category":"Unclassifiable Establishments",
    "sg:phone":"+33 1 60 04 02 96",
    "sg:postcode":"77860",
    "sg:province":"Ile de France",
    "wof:name":"S.f.c.p. S.a.r.l. - Soci\u00e9t\u00e9 Fran\u00e7aise De Conditionnement Publicitaire",
    "wof:placetype":"venue"
},
  "geometry": {"coordinates":[2.865693,48.876022],"type":"Point"}
}