{
  "type": "Feature",
  "properties": {
    "iso:country":"FR",
    "sg:address":"Technopole 58470 Magny Cours",
    "sg:city":"Gimouille",
    "sg:orig_category":"Motor Cleaning And Washing Services",
    "sg:phone":"+33 3 86 21 29 20",
    "sg:postcode":"58470",
    "sg:province":"Bourgogne",
    "wof:name":"Sodemo S.a.",
    "wof:placetype":"venue"
},
  "geometry": {"coordinates":[3.151245,46.883995],"type":"Point"}
}