{
  "type": "Feature",
  "properties": {
    "iso:country":"FR",
    "sg:address":"Lieu dit Planchemouton 87120 Eymoutiers",
    "sg:orig_category":"Unclassifiable Establishments",
    "sg:phone":"+33 5 55 69 82 00",
    "sg:province":"Limousin",
    "wof:name":"Soci\u00e9t\u00e9 Jean Champeau Et Compagnie S.a.",
    "wof:placetype":"venue"
},
  "geometry": {"coordinates":[1.762875,45.73716],"type":"Point"}
}