{
  "type": "Feature",
  "properties": {
    "addr:full":"4 Rue Gustave Cuvelier 62100 Calais Nord Pas-de-Calais 62100",
    "addr:housenumber":"4",
    "addr:postcode":"62100;62100",
    "addr:street":"Rue Gustave Cuvelier;Calais;Pas-De-Calais",
    "iso:country":"FR",
    "sg:address":"4 Rue Gustave Cuvelier 62100 Calais",
    "sg:classifiers":[
        {
            "category":"Home & Garden",
            "subcategory":"Furniture",
            "type":"Retail Goods"
        }
    ],
    "sg:phone":"+33 3 21 35 50 98",
    "sg:postcode":"62100",
    "sg:province":"Nord Pas-de-Calais",
    "sg:tags":[
        "household",
        "wood"
    ],
    "wof:name":"Meubles Barbier",
    "wof:placetype":"venue"
},
  "geometry": {"coordinates":[1.85325,50.946194],"type":"Point"}
}