{
  "type": "Feature",
  "properties": {
    "iso:country":"FR",
    "sg:address":"16BIS rue Michel Colle 54120 Baccarat",
    "sg:classifiers":[
        {
            "category":"Education",
            "subcategory":"Special Training",
            "type":"Public Place"
        }
    ],
    "sg:phone":"+33 3 83 75 14 94",
    "sg:province":"Lorraine",
    "sg:tags":[
        "machines",
        "heated"
    ],
    "wof:name":"M.g.b. Sa",
    "wof:placetype":"venue"
},
  "geometry": {"coordinates":[6.724215,48.447227],"type":"Point"}
}