{
  "type": "Feature",
  "properties": {
    "addr:full":"45, Rue de Montpatour, 45140 Ingr\u00e9 Ingr\u00e9 Centre 45140",
    "addr:housenumber":"45",
    "addr:postcode":"45140;45140",
    "addr:street":"Rue De Montpatour",
    "iso:country":"FR",
    "sg:address":"45, Rue de Montpatour, 45140 Ingr\u00e9",
    "sg:city":"Ingr\u00e9",
    "sg:orig_category":"Unclassifiable Establishments",
    "sg:phone":"+33 2 38 88 32 82",
    "sg:postcode":"45140",
    "sg:province":"Centre",
    "wof:name":"Affutor S.a.r.l.",
    "wof:placetype":"venue"
},
  "geometry": {"coordinates":[1.840008,47.908028],"type":"Point"}
}