{
  "type": "Feature",
  "properties": {
    "addr:full":"B.P. 1521, 87020 Limoges C\u00e9dex^^Rue Barth\u00e9l\u00e9my Thimonier - ZI Nord, 87280 Limoges Limousin",
    "addr:housenumber":"1521",
    "addr:postcode":"87020;87280",
    "addr:street":"B.P.;Barthe\u0301Le\u0301My Thimonier Zi Nord",
    "iso:country":"FR",
    "sg:address":"B.P. 1521, 87020 Limoges C\u00e9dex^^Rue Barth\u00e9l\u00e9my Thimonier - ZI Nord, 87280 Limoges",
    "sg:orig_category":"Non-Classified Establishments",
    "sg:phone":"+33 5 55 37 43 52",
    "sg:province":"Limousin",
    "wof:name":"Mory-team S.a.",
    "wof:placetype":"venue"
},
  "geometry": {"coordinates":[1.299435,45.914837],"type":"Point"}
}