{
  "type": "Feature",
  "properties": {
    "addr:full":"17, Rue Georges Bizet, 75016 Paris Ile de France",
    "addr:housenumber":"17",
    "addr:postcode":"75016",
    "addr:street":"Rue Georges Bizet",
    "iso:country":"FR",
    "sg:address":"17, Rue Georges Bizet, 75016 Paris",
    "sg:orig_category":"Unclassifiable Establishments",
    "sg:phone":"+33 1 56 62 27 00",
    "sg:province":"Ile de France",
    "wof:name":"Agrifigest S.a. - Alma Soci\u00e9t\u00e9 Financi\u00e8re Agricole De Gestin",
    "wof:placetype":"venue"
},
  "geometry": {"coordinates":[2.297593,48.867252],"type":"Point"}
}