{
  "type": "Feature",
  "properties": {
    "addr:full":"B.P. 1, 80210 Tours en Vimeu^^Rue Centrale, 80210 Tours en Vimeu Picardie 80210",
    "addr:housenumber":"1",
    "addr:postcode":"80210;80210;80210",
    "addr:street":"B.P.",
    "iso:country":"FR",
    "sg:address":"B.P. 1, 80210 Tours en Vimeu^^Rue Centrale, 80210 Tours en Vimeu",
    "sg:orig_category":"Non-Classified Establishments",
    "sg:phone":"+33 3 22 26 20 31",
    "sg:postcode":"80210",
    "sg:province":"Picardie",
    "wof:name":"Coop\u00e9rative Agricole Avenir Du Vimeu",
    "wof:placetype":"venue"
},
  "geometry": {"coordinates":[1.646165,50.062897],"type":"Point"}
}