{
  "type": "Feature",
  "properties": {
    "addr:full":"24, Quai Carnot, 92210 Saint Cloud Ile de France 92210",
    "addr:housenumber":"24",
    "addr:postcode":"92210;92210",
    "addr:street":"Quai Carnot",
    "iso:country":"FR",
    "sg:address":"24, Quai Carnot, 92210 Saint Cloud",
    "sg:orig_category":"Non-Classified Establishments",
    "sg:phone":"+33 1 47 71 21 46",
    "sg:postcode":"92210",
    "sg:province":"Ile de France",
    "wof:name":"Demolin Reims S.a.",
    "wof:placetype":"venue"
},
  "geometry": {"coordinates":[2.223459,48.846272],"type":"Point"}
}