{
  "type": "Feature",
  "properties": {
    "addr:full":"1 Rue Des Recollets BP 89 29260 Lesneven Lesneven Bretagne 29260",
    "addr:housenumber":"1;89",
    "addr:postcode":"29260;lesneven;29260",
    "addr:street":"Rue Des Recollets Bp",
    "iso:country":"FR",
    "sg:address":"1 Rue Des Recollets BP 89 29260 Lesneven",
    "sg:city":"Lesneven",
    "sg:classifiers":[
        {
            "category":"Professional",
            "subcategory":"Business Services",
            "type":"Services"
        }
    ],
    "sg:phone":"+33 2 98 83 09 22",
    "sg:postcode":"29260",
    "sg:province":"Bretagne",
    "sg:tags":[
        "training",
        "advice"
    ],
    "wof:name":"Groupe Scolaire St Francoise Notre Dame",
    "wof:placetype":"venue"
},
  "geometry": {"coordinates":[-4.324765,48.570831],"type":"Point"}
}