{
  "type": "Feature",
  "properties": {
    "iso:country":"FR",
    "sg:address":"4, Rue de la Libert\u00e9, 62121 Hamelincourt",
    "sg:orig_category":"Non-Classified Establishments",
    "sg:phone":"+33 3 21 59 71 71",
    "sg:province":"Nord Pas-de-Calais",
    "wof:name":"Shirt Label Act E.u.r.l.",
    "wof:placetype":"venue"
},
  "geometry": {"coordinates":[2.800943,50.186031],"type":"Point"}
}