{
  "type": "Feature",
  "properties": {
    "addr:full":"4, Rue de la Libert\u00e9, 62121 Hamelincourt Nord Pas-de-Calais",
    "addr:housenumber":"4",
    "addr:postcode":"62121",
    "addr:street":"Rue De La Liberte\u0301",
    "iso:country":"FR",
    "sg:address":"4, Rue de la Libert\u00e9, 62121 Hamelincourt",
    "sg:orig_category":"Non-Classified Establishments",
    "sg:phone":"+33 3 21 59 71 71",
    "sg:province":"Nord Pas-de-Calais",
    "wof:name":"Shirt Label Act E.u.r.l.",
    "wof:placetype":"venue"
},
  "geometry": {"coordinates":[2.800943,50.186031],"type":"Point"}
}