{
  "type": "Feature",
  "properties": {
    "addr:full":"B.P. 2 Corbenay^^70320 Corbenay Franche Comt\u00e9 70320",
    "addr:postcode":"70320",
    "addr:street":"B.P. 2 Corbenay^^70320;Franche Comte\u0301",
    "iso:country":"FR",
    "sg:address":"B.P. 2",
    "sg:city":"Corbenay^^70320 Corbenay",
    "sg:orig_category":"Non-Classified Establishments",
    "sg:phone":"+33 3 84 49 01 69",
    "sg:postcode":"70320",
    "sg:province":"Franche Comt\u00e9",
    "wof:name":"Gircourt S.a.r.l.",
    "wof:placetype":"venue"
},
  "geometry": {"coordinates":[6.336723,47.919704],"type":"Point"}
}