{
  "type": "Feature",
  "properties": {
    "addr:full":"La Croix Gillet 77122 Monthyon Ile de France",
    "addr:postcode":"77122;ile",
    "addr:street":"La Croix Gillet",
    "iso:country":"FR",
    "sg:address":"La Croix Gillet 77122 Monthyon",
    "sg:orig_category":"Non-Classified Establishments",
    "sg:phone":"+33 1 64 36 54 60",
    "sg:province":"Ile de France",
    "wof:name":"Somoval S.a.",
    "wof:placetype":"venue"
},
  "geometry": {"coordinates":[2.833215,49.006104],"type":"Point"}
}