{
  "type": "Feature",
  "properties": {
    "iso:country":"FR",
    "sg:address":"Rte De Gesten 56530 Qu\u00e9ven",
    "sg:city":"Qu\u00e9ven",
    "sg:classifiers":[
        {
            "category":"Professional",
            "subcategory":"Business Services",
            "type":"Services"
        }
    ],
    "sg:phone":"+33 2 97 05 08 58",
    "sg:postcode":"56530",
    "sg:province":"Bretagne",
    "sg:tags":[
        "training",
        "advice"
    ],
    "wof:name":"College Le Ronquedo",
    "wof:placetype":"venue"
},
  "geometry": {"coordinates":[-3.416069,47.788921],"type":"Point"}
}