{
  "type": "Feature",
  "properties": {
    "iso:country":"FR",
    "sg:address":"ZA Le grand Chemin 24570 LE LARDIN ST LAZARE",
    "sg:city":"Condat-sur-V\u00e9z\u00e8re",
    "sg:classifiers":[
        {
            "category":"Professional",
            "type":"Services"
        }
    ],
    "sg:phone":"+33 5 53 51 45 45",
    "sg:postcode":"24570",
    "sg:province":"Aquitaine",
    "sg:tags":[
        "transport"
    ],
    "wof:name":"V\u00e8z\u00e8re Transport S.a.",
    "wof:placetype":"venue"
},
  "geometry": {"coordinates":[1.22628,45.129089],"type":"Point"}
}