{
  "type": "Feature",
  "properties": {
    "iso:country":"FR",
    "sg:address":"Rte Du Nord BP 8 44590 Derval",
    "sg:classifiers":[
        {
            "category":"Food & Beverages",
            "subcategory":"Dairy",
            "type":"Retail Goods"
        }
    ],
    "sg:phone":"+33 2 40 07 78 21",
    "sg:postcode":"44590",
    "sg:province":"Pays de Loire",
    "sg:tags":[
        "product",
        "related"
    ],
    "wof:name":"Cie Laiti\u00c8re De Derval",
    "wof:placetype":"venue"
},
  "geometry": {"coordinates":[-1.660924,47.668575],"type":"Point"}
}