{
  "type": "Feature",
  "properties": {
    "addr:full":"BAMI - Foreign Department & Correspondent Banking BSE, 88 rue de Bahinos, F-64600 Anglet, Dept 64, F Anglet Aquitaine 64600",
    "addr:housenumber":"88;64 f",
    "addr:postcode":"f-64600;64600",
    "addr:street":"Rue De Bahinos",
    "iso:country":"FR",
    "sg:address":"BAMI - Foreign Department & Correspondent Banking BSE, 88 rue de Bahinos, F-64600 Anglet, Dept 64, F",
    "sg:city":"Anglet",
    "sg:classifiers":[
        {
            "category":"Banks & Credit Unions",
            "subcategory":"Bank",
            "type":"Services"
        }
    ],
    "sg:phone":"+33 5 59 22 40 42",
    "sg:postcode":"64600",
    "sg:province":"Aquitaine",
    "wof:name":"Banque Michel Inchausp\u00e9 - Bami;banque Michel Inchausp\u00e9 - Bami;banque Michel Inchausp\u00e9 - Bami;banque ",
    "wof:placetype":"venue"
},
  "geometry": {"coordinates":[-1.518794,43.494717],"type":"Point"}
}