{
  "type": "Feature",
  "properties": {
    "iso:country":"FR",
    "sg:address":"316, Av. des Escures, 19600 Saint Pantal\u00e9on de Larche",
    "sg:orig_category":"Unclassifiable Establishments",
    "sg:phone":"+33 5 55 88 00 48",
    "sg:province":"Limousin",
    "wof:name":"Co.ce.co. S.a.r.l. - Comptoir Central De Confection",
    "wof:placetype":"venue"
},
  "geometry": {"coordinates":[1.443713,45.143929],"type":"Point"}
}