{
  "type": "Feature",
  "properties": {
    "iso:country":"FR",
    "sg:address":"26, Rue Ren\u00e9 Nicod, 01100 Oyonnax",
    "sg:orig_category":"Unclassifiable Establishments",
    "sg:phone":"+33 4 74 81 99 00",
    "sg:postcode":"01100",
    "sg:province":"Rhone-Alpes",
    "wof:name":"F.i.m. Or\u00e9fi S.a. - Fournitures Industrielles Pour Moules",
    "wof:placetype":"venue"
},
  "geometry": {"coordinates":[5.654198,46.262375],"type":"Point"}
}