{
  "type": "Feature",
  "properties": {
    "addr:full":"Rue des Marchandises Nantes Pays de Loire 44200",
    "addr:postcode":"44200",
    "addr:street":"Rue Des Marchandises",
    "iso:country":"FR",
    "sg:address":"Rue des Marchandises",
    "sg:city":"Nantes",
    "sg:orig_category":"Non-Classified Establishments",
    "sg:phone":"+33 2 40 35 46 47",
    "sg:postcode":"44200",
    "sg:province":"Pays de Loire",
    "wof:name":"Les Ateliers De Saint Valentin S.n.c.",
    "wof:placetype":"venue"
},
  "geometry": {"coordinates":[-1.554109,47.203232],"type":"Point"}
}