{
  "type": "Feature",
  "properties": {
    "iso:country":"FR",
    "sg:address":"23, Rte de Lyon, 67400 Illkirch Graffenstaden",
    "sg:city":"Geispolsheim",
    "sg:orig_category":"Non-Classified Establishments",
    "sg:phone":"+33 3 88 66 10 67",
    "sg:postcode":"67400",
    "sg:province":"Alsace",
    "wof:name":"La Techni-soudure S.a.",
    "wof:placetype":"venue"
},
  "geometry": {"coordinates":[7.727278,48.536797],"type":"Point"}
}