{
  "type": "Feature",
  "properties": {
    "iso:country":"FR",
    "sg:address":"B.P. 33, 39130 Clairvaux les Lacs^^ZI en B\u00e9riat, 39130 Clairvaux les Lacs",
    "sg:orig_category":"Non-Classified Establishments",
    "sg:phone":"+33 3 84 25 25 25",
    "sg:province":"Franche Comt\u00e9",
    "wof:name":"Gaillard Automatismes S.a.r.l.",
    "wof:placetype":"venue"
},
  "geometry": {"coordinates":[5.748384,46.57431],"type":"Point"}
}