{
  "type": "Feature",
  "properties": {
    "addr:full":"30 bis, Rue de Paradis, 75010 Paris Ile de France",
    "addr:housenumber":"30 bis",
    "addr:postcode":"75010",
    "addr:street":"Rue De Paradis",
    "iso:country":"FR",
    "sg:address":"30 bis, Rue de Paradis, 75010 Paris",
    "sg:orig_category":"Unclassifiable Establishments",
    "sg:phone":"+33 1 47 70 64 30",
    "sg:province":"Ile de France",
    "wof:name":"Baccarat S.a.",
    "wof:placetype":"venue"
},
  "geometry": {"coordinates":[2.352025,48.875263],"type":"Point"}
}