{
  "type": "Feature",
  "properties": {
    "addr:full":"5, Rue Yvon Villarceau, 75016 Paris Ile de France",
    "addr:housenumber":"5",
    "addr:postcode":"75016",
    "addr:street":"Rue Yvon Villarceau",
    "iso:country":"FR",
    "sg:address":"5, Rue Yvon Villarceau, 75016 Paris",
    "sg:orig_category":"Unclassifiable Establishments",
    "sg:phone":"+33 1 45 01 75 28",
    "sg:province":"Ile de France",
    "wof:name":"Cabinet D'ormane S.a.",
    "wof:placetype":"venue"
},
  "geometry": {"coordinates":[2.287646,48.868984],"type":"Point"}
}