{
  "type": "Feature",
  "properties": {
    "addr:full":"30, Rue du Fort, 92500 Rueil Malmaison Ile de France",
    "addr:housenumber":"30",
    "addr:postcode":"92500",
    "addr:street":"Rue Du Fort",
    "iso:country":"FR",
    "sg:address":"30, Rue du Fort, 92500 Rueil Malmaison",
    "sg:orig_category":"Unclassifiable Establishments",
    "sg:phone":"+33 1 47 32 81 30",
    "sg:province":"Ile de France",
    "wof:name":"Unipex S.a.",
    "wof:placetype":"venue"
},
  "geometry": {"coordinates":[2.188298,48.87838],"type":"Point"}
}