{
  "type": "Feature",
  "properties": {
    "addr:full":"60 rue du Guesclin 69006 Lyon Rhone-Alpes",
    "addr:housenumber":"60",
    "addr:postcode":"69006",
    "addr:street":"Rue Du Guesclin",
    "iso:country":"FR",
    "sg:address":"60 rue du Guesclin 69006 Lyon",
    "sg:classifiers":[
        {
            "category":"Banks & Credit Unions",
            "subcategory":"Investment Brokerage",
            "type":"Services"
        }
    ],
    "sg:phone":"+33 4 78 89 28 00",
    "sg:province":"Rhone-Alpes",
    "sg:tags":[
        "new",
        "consulting",
        "management",
        "starting",
        "business"
    ],
    "wof:name":"Hako France Sarl",
    "wof:placetype":"venue"
},
  "geometry": {"coordinates":[4.849785,45.769245],"type":"Point"}
}