{
  "type": "Feature",
  "properties": {
    "addr:full":"Zi 67120 Duppigheim Duppigheim Alsace 67120",
    "addr:postcode":"67120;67120",
    "addr:street":"Zi;Duppigheim",
    "iso:country":"FR",
    "sg:address":"Zi 67120 Duppigheim",
    "sg:city":"Duppigheim",
    "sg:classifiers":[
        {
            "category":"Building & Trades",
            "subcategory":"Construction",
            "type":"Services"
        }
    ],
    "sg:phone":"+33 3 88 38 69 23",
    "sg:postcode":"67120",
    "sg:province":"Alsace",
    "sg:tags":[
        "work",
        "public"
    ],
    "wof:name":"Demathieu Et Bard",
    "wof:placetype":"venue"
},
  "geometry": {"coordinates":[7.57952,48.543633],"type":"Point"}
}