{
  "type": "Feature",
  "properties": {
    "addr:full":"Za Les Sablons 27460 Alizay Haute Normandie 27460",
    "addr:postcode":"27460;27460",
    "addr:street":"Za Les Sablons;Haute Normandie",
    "iso:country":"FR",
    "sg:address":"Za Les Sablons 27460 Alizay",
    "sg:classifiers":[
        {
            "category":"Manufacturing",
            "subcategory":"Tools & Machinery",
            "type":"Manufacturing & Wholesale Goods"
        }
    ],
    "sg:phone":"+33 2 35 02 04 04",
    "sg:postcode":"27460",
    "sg:province":"Haute Normandie",
    "sg:tags":[
        "metallurgy",
        "metalworking"
    ],
    "wof:name":"Sotrafer Sa",
    "wof:placetype":"venue"
},
  "geometry": {"coordinates":[1.183945,49.32132],"type":"Point"}
}