{
  "type": "Feature",
  "properties": {
    "addr:full":"B.P. 40, 67305 Schiltigheim C\u00e9dex^^Rue Alfred Kastler, 67300 Schiltigheim Schiltigheim Alsace 67300",
    "addr:postcode":"67305;67300;67300",
    "addr:street":"B.P. 40;Alfred Kastler",
    "iso:country":"FR",
    "sg:address":"B.P. 40, 67305 Schiltigheim C\u00e9dex^^Rue Alfred Kastler, 67300 Schiltigheim",
    "sg:city":"Schiltigheim",
    "sg:orig_category":"Non-Classified Establishments",
    "sg:phone":"+33 3 88 19 12 12",
    "sg:postcode":"67300",
    "sg:province":"Alsace",
    "wof:name":"Devel S.a.",
    "wof:placetype":"venue"
},
  "geometry": {"coordinates":[7.748565,48.605949],"type":"Point"}
}