{
  "type": "Feature",
  "properties": {
    "addr:full":"46090 Lamagdelaine Midi Pyr\u00e9n\u00e9es 46090",
    "addr:housenumber":"46090",
    "addr:postcode":"46090",
    "addr:street":"Lamagdelaine Midi Pyre\u0301Ne\u0301Es",
    "iso:country":"FR",
    "sg:address":"46090 Lamagdelaine",
    "sg:orig_category":"Non-Classified Establishments",
    "sg:phone":"+33 5 65 35 64 35",
    "sg:postcode":"46090",
    "sg:province":"Midi Pyr\u00e9n\u00e9es",
    "wof:name":"Entreprise Marty S.a.r.l.",
    "wof:placetype":"venue"
},
  "geometry": {"coordinates":[1.48625,44.466434],"type":"Point"}
}