{
  "type": "Feature",
  "properties": {
    "iso:country":"FR",
    "sg:address":"Le Jard 24610 Saint M\u00e9ard de Gur\u00e7on",
    "sg:city":"Carsac-de-Gurson",
    "sg:orig_category":"Unclassifiable Establishments",
    "sg:phone":"+33 5 53 82 48 36",
    "sg:postcode":"24610",
    "sg:province":"Aquitaine",
    "wof:name":"G.a.e.c. Du Maine",
    "wof:placetype":"venue"
},
  "geometry": {"coordinates":[0.183472,44.908039],"type":"Point"}
}