{
  "type": "Feature",
  "properties": {
    "iso:country":"FR",
    "sg:address":"B.P. 81041, 30134 Pont Saint Esprit C\u00e9dex^^Rue des Amandiers, 30130 Pont Saint Esprit",
    "sg:orig_category":"Non-Classified Establishments",
    "sg:phone":"+33 4 66 39 11 86",
    "sg:province":"Languedoc-Roussillon",
    "wof:name":"S.e.c. Dondey Et Compagnie S.a.r.l.",
    "wof:placetype":"venue"
},
  "geometry": {"coordinates":[4.65332,44.20892],"type":"Point"}
}