{
  "type": "Feature",
  "properties": {
    "addr:full":"12 Bd De La Libert\u00e9 49000 Angers Pays de Loire 49000",
    "addr:housenumber":"12",
    "addr:postcode":"49000;49000",
    "addr:street":"Bd De La Liberte\u0301",
    "iso:country":"FR",
    "sg:address":"12 Bd De La Libert\u00e9 49000 Angers",
    "sg:classifiers":[
        {
            "category":"Autos & Motor Vehicles",
            "subcategory":"Automobile Sales",
            "type":"Retail Goods"
        }
    ],
    "sg:phone":"+33 2 41 44 55 66",
    "sg:postcode":"49000",
    "sg:province":"Pays de Loire",
    "sg:tags":[
        "equipment",
        "motor-cars",
        "transport"
    ],
    "wof:name":"Sada Distribution Sa",
    "wof:placetype":"venue"
},
  "geometry": {"coordinates":[-0.533514,47.448711],"type":"Point"}
}