{
  "type": "Feature",
  "properties": {
    "addr:full":"ZA Carreau de la Mine Crehange Lorraine 57690",
    "addr:postcode":"57690",
    "addr:street":"Za Carreau De La;Crehange Lorraine",
    "iso:country":"FR",
    "sg:address":"ZA Carreau de la Mine",
    "sg:city":"Crehange",
    "sg:orig_category":"Unclassifiable Establishments",
    "sg:phone":"+33 3 87 90 70 04",
    "sg:postcode":"57690",
    "sg:province":"Lorraine",
    "wof:name":"Vani S.a.r.l.",
    "wof:placetype":"venue"
},
  "geometry": {"coordinates":[6.58013,49.062054],"type":"Point"}
}