{
  "type": "Feature",
  "properties": {
    "iso:country":"FR",
    "sg:address":"B.P. 648, 57146 Woippy C\u00e9dex^^116, Rte de Thionville, 57140 Woippy",
    "sg:orig_category":"Non-Classified Establishments",
    "sg:phone":"+33 3 87 34 29 44",
    "sg:province":"Lorraine",
    "wof:name":"Tilly Holding S.a.",
    "wof:placetype":"venue"
},
  "geometry": {"coordinates":[6.150305,49.15131],"type":"Point"}
}