{
  "type": "Feature",
  "properties": {
    "iso:country":"FR",
    "sg:address":"25, Av de Coulin - Parc d'Activit\u00e9s de G\u00e9menos, 13420 G\u00e9menos",
    "sg:orig_category":"Unclassifiable Establishments",
    "sg:phone":"+33 4 42 32 23 23",
    "sg:province":"Provence-Alpes-C\u00f4te d'Azur",
    "wof:name":"Cepasco S.a.r.l.",
    "wof:placetype":"venue"
},
  "geometry": {"coordinates":[5.638721,43.274773],"type":"Point"}
}