{
  "type": "Feature",
  "properties": {
    "addr:full":"22, Rue Kerhoas - Parc d'Activit\u00e9s Armor Oc\u00e9an, 56260 Larmor Plage Larmor-Plage Bretagne 56260",
    "addr:housenumber":"22",
    "addr:postcode":"56260;56260",
    "addr:street":"Rue Kerhoas Parc D'Activite \u0301S;Larmor-Plage Bretagne",
    "iso:country":"FR",
    "sg:address":"22, Rue Kerhoas - Parc d'Activit\u00e9s Armor Oc\u00e9an, 56260 Larmor Plage",
    "sg:city":"Larmor-Plage",
    "sg:orig_category":"Unclassifiable Establishments",
    "sg:phone":"+33 2 97 37 47 31",
    "sg:postcode":"56260",
    "sg:province":"Bretagne",
    "wof:name":"Infosup S.a.s.",
    "wof:placetype":"venue"
},
  "geometry": {"coordinates":[-3.390632,47.72364],"type":"Point"}
}