{
  "type": "Feature",
  "properties": {
    "iso:country":"FR",
    "sg:address":"15 Bd Bigo Danel 59000 Lille",
    "sg:classifiers":[
        {
            "category":"Autos & Motor Vehicles",
            "subcategory":"Automobile Sales",
            "type":"Retail Goods"
        }
    ],
    "sg:phone":"+33 3 20 00 91 91",
    "sg:postcode":"59000",
    "sg:province":"Nord Pas-de-Calais",
    "sg:tags":[
        "equipment",
        "motor-cars",
        "transport"
    ],
    "wof:name":"Eurial Sa",
    "wof:placetype":"venue"
},
  "geometry": {"coordinates":[3.0416,50.627228],"type":"Point"}
}