{
  "type": "Feature",
  "properties": {
    "iso:country":"FR",
    "sg:address":"4, Rue Saint Nicolas - ZAC des Ormeaux, 71150 Fontaines",
    "sg:city":"Fontaines",
    "sg:orig_category":"Unclassifiable Establishments",
    "sg:phone":"+33 3 85 91 43 12",
    "sg:postcode":"71150",
    "sg:province":"Bourgogne",
    "wof:name":"Hunault Production S.a.r.l.",
    "wof:placetype":"venue"
},
  "geometry": {"coordinates":[4.75459,46.910526],"type":"Point"}
}