{
  "type": "Feature",
  "properties": {
    "addr:full":"Les Grandes Vignes 24120 Coly Coly Aquitaine 24120",
    "addr:postcode":"24120;24120",
    "addr:street":"Les Grandes Vignes",
    "iso:country":"FR",
    "sg:address":"Les Grandes Vignes 24120 Coly",
    "sg:city":"Coly",
    "sg:orig_category":"Non-Classified Establishments",
    "sg:phone":"+33 5 53 51 40 40",
    "sg:postcode":"24120",
    "sg:province":"Aquitaine",
    "wof:name":"P\u00e9rigord-palettes S.a.",
    "wof:placetype":"venue"
},
  "geometry": {"coordinates":[1.31693,45.046028],"type":"Point"}
}