{
  "type": "Feature",
  "properties": {
    "addr:full":"37 Chemin De Chiradie Zi Nord 69530 Brignais Rhone-Alpes",
    "addr:housenumber":"37",
    "addr:postcode":"69530",
    "addr:street":"Chemin De Chiradie Zi Nord",
    "iso:country":"FR",
    "sg:address":"37 Chemin De Chiradie Zi Nord 69530 Brignais",
    "sg:classifiers":[
        {
            "category":"Professional",
            "subcategory":"Engineering",
            "type":"Services"
        }
    ],
    "sg:phone":"+33 4 72 31 55 55",
    "sg:province":"Rhone-Alpes",
    "sg:tags":[
        "machine",
        "-",
        "mechanical"
    ],
    "wof:name":"Resurgence",
    "wof:placetype":"venue"
},
  "geometry": {"coordinates":[4.753949,45.674034],"type":"Point"}
}