{
  "type": "Feature",
  "properties": {
    "addr:full":"B.P. 1, 53420 Chailland^^ZAC le Tertre, 53420 Chailland Pays de Loire",
    "addr:housenumber":"1",
    "addr:postcode":"53420;53420",
    "addr:street":"B.P.;Le Tertre",
    "iso:country":"FR",
    "sg:address":"B.P. 1, 53420 Chailland^^ZAC le Tertre, 53420 Chailland",
    "sg:orig_category":"Non-Classified Establishments",
    "sg:phone":"+33 2 43 01 24 60",
    "sg:province":"Pays de Loire",
    "wof:name":"Secou\u00e9 S.a.",
    "wof:placetype":"venue"
},
  "geometry": {"coordinates":[-0.874489,48.225796],"type":"Point"}
}