{
  "type": "Feature",
  "properties": {
    "addr:full":"Zi Attichy 60350 Attichy Picardie 60350",
    "addr:postcode":"60350;60350",
    "addr:street":"Picardie",
    "iso:country":"FR",
    "sg:address":"Zi Attichy 60350 Attichy",
    "sg:classifiers":[
        {
            "category":"Manufacturing",
            "subcategory":"Metals",
            "type":"Manufacturing & Wholesale Goods"
        }
    ],
    "sg:phone":"+33 3 44 95 39 00",
    "sg:postcode":"60350",
    "sg:province":"Picardie",
    "sg:tags":[
        "metallurgy",
        "metalworking"
    ],
    "wof:name":"Usiprofil Sa",
    "wof:placetype":"venue"
},
  "geometry": {"coordinates":[3.04568,49.413269],"type":"Point"}
}