{
  "type": "Feature",
  "properties": {
    "addr:full":"9 rue biscornet Paris 75012",
    "addr:housenumber":"9",
    "addr:postcode":"75012",
    "addr:street":"Rue Biscornet",
    "iso:country":"FR",
    "sg:address":"9 rue biscornet",
    "sg:city":"Paris",
    "sg:classifiers":[
        {
            "category":"Professional",
            "subcategory":"Computer Services",
            "type":"Services"
        }
    ],
    "sg:postcode":"75012",
    "sg:website":"http://www.2minutes.fr",
    "wof:name":"2 Minutes",
    "wof:placetype":"venue"
},
  "geometry": {"coordinates":[2.369803,48.850206],"type":"Point"}
}