{
  "type": "Feature",
  "properties": {
    "addr:full":"2 Rue Robert Keller 10150 Pont Ste Marie Champagne 10150",
    "addr:housenumber":"2",
    "addr:postcode":"10150;10150",
    "addr:street":"Rue Robert Keller;Ste Marie Champagne",
    "iso:country":"FR",
    "sg:address":"2 Rue Robert Keller 10150 Pont Ste Marie",
    "sg:classifiers":[
        {
            "category":"Shopping",
            "subcategory":"Computers & Home Electronics",
            "type":"Retail Goods"
        }
    ],
    "sg:phone":"+33 3 25 76 23 40",
    "sg:postcode":"10150",
    "sg:province":"Champagne",
    "sg:tags":[
        "household",
        "appliance",
        "telecommunication",
        "audio-visual"
    ],
    "wof:name":"Temex Sa",
    "wof:placetype":"venue"
},
  "geometry": {"coordinates":[4.108229,48.322769],"type":"Point"}
}