{
  "type": "Feature",
  "properties": {
    "addr:full":"RN 10 - La Croix Blanche Champniers Poitou-Charentes 16430",
    "addr:postcode":"16430",
    "addr:street":"Rn 10 La",
    "iso:country":"FR",
    "sg:address":"RN 10 - La Croix Blanche",
    "sg:city":"Champniers",
    "sg:orig_category":"Unclassifiable Establishments",
    "sg:phone":"+33 5 45 68 12 11",
    "sg:postcode":"16430",
    "sg:province":"Poitou-Charentes",
    "wof:name":"Guillot",
    "wof:placetype":"venue"
},
  "geometry": {"coordinates":[0.211168,45.691833],"type":"Point"}
}