{
  "type": "Feature",
  "properties": {
    "addr:full":"B.P. 3005, 30002 N\u00eemes C\u00e9dex^^Rte de Beaucaire - ZI de Gr\u00e9zan, 30000 N\u00eemes Languedoc-Roussillon",
    "addr:postcode":"30002;30000",
    "addr:street":"B.P. 3005",
    "iso:country":"FR",
    "sg:address":"B.P. 3005, 30002 N\u00eemes C\u00e9dex^^Rte de Beaucaire - ZI de Gr\u00e9zan, 30000 N\u00eemes",
    "sg:orig_category":"Non-Classified Establishments",
    "sg:phone":"+33 4 66 27 11 23",
    "sg:province":"Languedoc-Roussillon",
    "wof:name":"Transports Graveleau S.a.",
    "wof:placetype":"venue"
},
  "geometry": {"coordinates":[4.36035,43.86256],"type":"Point"}
}