{
  "type": "Feature",
  "properties": {
    "addr:full":"Rue Aristide Berges Zi De Perigny 17180 Perigny Poitou-Charentes 17180",
    "addr:postcode":"17180;17180",
    "addr:street":"Rue Aristide Berges Zi De Perigny;Perigny",
    "iso:country":"FR",
    "sg:address":"Rue Aristide Berges Zi De Perigny 17180 Perigny",
    "sg:classifiers":[
        {
            "category":"Professional",
            "subcategory":"Engineering",
            "type":"Services"
        }
    ],
    "sg:phone":"+33 5 46 34 67 45",
    "sg:postcode":"17180",
    "sg:province":"Poitou-Charentes",
    "sg:tags":[
        "machine",
        "-",
        "mechanical"
    ],
    "wof:name":"Des Choses Et D'autres",
    "wof:placetype":"venue"
},
  "geometry": {"coordinates":[-1.096665,46.15501],"type":"Point"}
}