{
  "type": "Feature",
  "properties": {
    "addr:full":"8, Rue Joseph Cugnot, 38300 Bourgoin Jallieu Rhone-Alpes",
    "addr:housenumber":"8",
    "addr:postcode":"38300",
    "addr:street":"Rue Joseph Cugnot",
    "iso:country":"FR",
    "sg:address":"8, Rue Joseph Cugnot, 38300 Bourgoin Jallieu",
    "sg:orig_category":"Unclassifiable Establishments",
    "sg:phone":"+33 4 74 28 02 69",
    "sg:province":"Rhone-Alpes",
    "wof:name":"Logapro S.a.r.l. - Logiciels Appliqu\u00e9s \u00e0 La Productique",
    "wof:placetype":"venue"
},
  "geometry": {"coordinates":[5.277072,45.587364],"type":"Point"}
}