{
  "type": "Feature",
  "properties": {
    "addr:full":"Quai Des Nerviens BP 127 59602 Maubeuge Basse Normandie",
    "addr:housenumber":"127",
    "addr:postcode":"59602",
    "addr:street":"Quai Des Nerviens Bp",
    "iso:country":"FR",
    "sg:address":"Quai Des Nerviens BP 127 59602 Maubeuge",
    "sg:classifiers":[
        {
            "category":"Professional",
            "subcategory":"Business Services",
            "type":"Services"
        }
    ],
    "sg:phone":"+33 3 27 65 84 13",
    "sg:province":"Basse Normandie",
    "sg:tags":[
        "training",
        "advice"
    ],
    "wof:name":"Groupe Scolaire Notre Dame De Gr\u00c2ce",
    "wof:placetype":"venue"
},
  "geometry": {"coordinates":[3.96905,50.276485],"type":"Point"}
}