{
  "type": "Feature",
  "properties": {
    "addr:full":"avenue Pierre S\u00e9mard 84000 Avignon Languedoc-Roussillon",
    "addr:postcode":"84000",
    "addr:street":"Avenue Pierre Se\u0301Mard",
    "iso:country":"FR",
    "sg:address":"avenue Pierre S\u00e9mard 84000 Avignon",
    "sg:classifiers":[
        {
            "category":"Banks & Credit Unions",
            "subcategory":"Investment Brokerage",
            "type":"Services"
        }
    ],
    "sg:phone":"+33 4 90 87 78 33",
    "sg:province":"Languedoc-Roussillon",
    "sg:tags":[
        "casting",
        "lost",
        "wax"
    ],
    "wof:name":"Etablissements Jacques Vernet S.a.",
    "wof:placetype":"venue"
},
  "geometry": {"coordinates":[4.815334,43.943516],"type":"Point"}
}