{
  "type": "Feature",
  "properties": {
    "iso:country":"FR",
    "sg:address":"57/59, Rue Alphonse Pluchet, 92223 Bagneux C\u00e9dex",
    "sg:city":"Bagneux",
    "sg:orig_category":"Non-Classified Establishments",
    "sg:phone":"+33 1 40 92 74 44",
    "sg:postcode":"92220",
    "sg:province":"Ile de France",
    "wof:name":"Automatic Systems S.a.",
    "wof:placetype":"venue"
},
  "geometry": {"coordinates":[2.30019,48.799259],"type":"Point"}
}