{
  "type": "Feature",
  "properties": {
    "addr:full":"Le Mas 43200 Grazac Grazac Auvergne 43200",
    "addr:postcode":"43200;grazac;43200",
    "iso:country":"FR",
    "sg:address":"Le Mas 43200 Grazac",
    "sg:city":"Grazac",
    "sg:classifiers":[
        {
            "category":"Manufacturing",
            "subcategory":"Rubber & Plastics",
            "type":"Manufacturing & Wholesale Goods"
        }
    ],
    "sg:phone":"+33 4 71 59 32 41",
    "sg:postcode":"43200",
    "sg:province":"Auvergne",
    "sg:tags":[
        "packaging",
        "material",
        "-"
    ],
    "wof:name":"Sopil",
    "wof:placetype":"venue"
},
  "geometry": {"coordinates":[4.19534,45.196297],"type":"Point"}
}