{
  "type": "Feature",
  "properties": {
    "addr:full":"10 rue de Chevreul 92150 Suresnes Ile de France 92150",
    "addr:housenumber":"10",
    "addr:postcode":"92150;ile;92150",
    "addr:street":"Rue De Chevreul;France",
    "iso:country":"FR",
    "sg:address":"10 rue de Chevreul 92150 Suresnes",
    "sg:classifiers":[
        {
            "category":"Wholesale",
            "subcategory":"Books, Periodicals, & Newspapers",
            "type":"Manufacturing & Wholesale Goods"
        }
    ],
    "sg:phone":"+33 1 41 44 79 99",
    "sg:postcode":"92150",
    "sg:province":"Ile de France",
    "sg:tags":[
        "directory",
        "publisher"
    ],
    "wof:name":"Taylor & Partners Sa",
    "wof:placetype":"venue"
},
  "geometry": {"coordinates":[2.223041,48.86702],"type":"Point"}
}