{
  "type": "Feature",
  "properties": {
    "addr:full":"7-9 rue du Parc 93150 Le Blanc Mesnil Ile de France",
    "addr:housenumber":"7-9",
    "addr:postcode":"93150",
    "addr:street":"Rue Du Parc",
    "iso:country":"FR",
    "sg:address":"7-9 rue du Parc 93150 Le Blanc Mesnil",
    "sg:classifiers":[
        {
            "category":"Wholesale",
            "subcategory":"Plants",
            "type":"Manufacturing & Wholesale Goods"
        }
    ],
    "sg:phone":"+33 1 45 91 93 93",
    "sg:province":"Ile de France",
    "sg:tags":[
        "part",
        "spare",
        "smelting"
    ],
    "wof:name":"Jefer Sa",
    "wof:placetype":"venue"
},
  "geometry": {"coordinates":[2.440202,48.938541],"type":"Point"}
}