{
  "type": "Feature",
  "properties": {
    "iso:country":"FR",
    "sg:address":"23, Rue L\u00e9on Maurice Nordmann, 92250 La Garenne Colombes",
    "sg:orig_category":"Non-Classified Establishments",
    "sg:phone":"+33 1 42 42 67 86",
    "sg:province":"Ile de France",
    "wof:name":"Hausser Et Compagnie S.a.r.l.",
    "wof:placetype":"venue"
},
  "geometry": {"coordinates":[2.241982,48.90358],"type":"Point"}
}