{
  "type": "Feature",
  "properties": {
    "addr:full":"52, Rue des Costelles, 88460 Docelles Lorraine",
    "addr:housenumber":"52",
    "addr:postcode":"88460",
    "addr:street":"Rue Des Costelles",
    "iso:country":"FR",
    "sg:address":"52, Rue des Costelles, 88460 Docelles",
    "sg:orig_category":"Unclassifiable Establishments",
    "sg:phone":"+33 3 29 33 20 11",
    "sg:province":"Lorraine",
    "wof:name":"Halbout S.a.",
    "wof:placetype":"venue"
},
  "geometry": {"coordinates":[6.62182,48.146591],"type":"Point"}
}