{
  "type": "Feature",
  "properties": {
    "addr:full":"15 Rue Des Belges 87100 Limoges Limousin 87100",
    "addr:housenumber":"15",
    "addr:postcode":"87100;87100",
    "addr:street":"Rue Des Belges",
    "iso:country":"FR",
    "sg:address":"15 Rue Des Belges 87100 Limoges",
    "sg:classifiers":[
        {
            "category":"Home & Garden",
            "subcategory":"Furniture",
            "type":"Retail Goods"
        }
    ],
    "sg:phone":"+33 5 55 79 84 94",
    "sg:postcode":"87100",
    "sg:province":"Limousin",
    "sg:tags":[
        "household",
        "wood"
    ],
    "wof:name":"Sarl Porcelaines Imperialimoges (imperialimoges)",
    "wof:placetype":"venue"
},
  "geometry": {"coordinates":[1.245893,45.838997],"type":"Point"}
}