{
  "type": "Feature",
  "properties": {
    "addr:full":"10, Rte de Verri\u00e8res, 10450 Br\u00e9viandes Champagne-Ardenne",
    "addr:housenumber":"10",
    "addr:postcode":"10450",
    "addr:street":"Rte De Verrie\u0300Res",
    "iso:country":"FR",
    "sg:address":"10, Rte de Verri\u00e8res, 10450 Br\u00e9viandes",
    "sg:orig_category":"Unclassifiable Establishments",
    "sg:phone":"+33 3 25 82 22 70",
    "sg:province":"Champagne-Ardenne",
    "wof:name":"T.m.m. S.a.r.l. - Trans Manu Machines",
    "wof:placetype":"venue"
},
  "geometry": {"coordinates":[4.110329,48.264378],"type":"Point"}
}