{
  "type": "Feature",
  "properties": {
    "addr:full":"7 Pl Du Gal Leclerc 93600 Aulnay Sous Bois Ile de France 93600",
    "addr:housenumber":"7",
    "addr:postcode":"93600;93600",
    "addr:street":"Pl Du Gal Leclerc",
    "iso:country":"FR",
    "sg:address":"7 Pl Du Gal Leclerc 93600 Aulnay Sous Bois",
    "sg:classifiers":[
        {
            "category":"Banks & Credit Unions",
            "subcategory":"Financial Services",
            "type":"Services"
        }
    ],
    "sg:phone":"+33 1 48 79 56 80",
    "sg:postcode":"93600",
    "sg:province":"Ile de France",
    "sg:tags":[
        "banking",
        "insurance",
        "institution",
        "finance"
    ],
    "wof:name":"Credit Lyonnais",
    "wof:placetype":"venue"
},
  "geometry": {"coordinates":[2.490561,48.92746],"type":"Point"}
}