{
  "type": "Feature",
  "properties": {
    "iso:country":"FR",
    "sg:address":"12-14 Rd Pt des Champs-Elys\u00e9es; Paris; 75008",
    "sg:classifiers":[
        {
            "category":"Banks & Credit Unions",
            "subcategory":"Bank",
            "type":"Services"
        }
    ],
    "sg:phone":"+33 1 45 62 15 32",
    "sg:postcode":"75008",
    "sg:province":"Ile de France",
    "wof:name":"State Bank Of India",
    "wof:placetype":"venue"
},
  "geometry": {"coordinates":[2.3111,48.873241],"type":"Point"}
}