{
  "type": "Feature",
  "properties": {
    "addr:full":"6 Rue Des Pr\u00e9s Riants Aix Les Bains Rhone-Alpes 73100",
    "addr:housenumber":"6",
    "addr:postcode":"73100",
    "addr:street":"Rue Des Pre\u0301S Riants Aix",
    "iso:country":"FR",
    "sg:address":"6 Rue Des Pr\u00e9s Riants",
    "sg:city":"Aix Les Bains",
    "sg:classifiers":[
        {
            "category":"Banks & Credit Unions",
            "subcategory":"Financial Services",
            "type":"Services"
        }
    ],
    "sg:phone":"+33 4 79 35 07 99",
    "sg:postcode":"73100",
    "sg:province":"Rhone-Alpes",
    "sg:tags":[
        "banking",
        "finance",
        "insurance"
    ],
    "wof:name":"Ladouce Daniel Et Perrier Gustin Jacques",
    "wof:placetype":"venue"
},
  "geometry": {"coordinates":[5.909481,45.694588],"type":"Point"}
}