{
  "type": "Feature",
  "properties": {
    "iso:country":"FR",
    "sg:address":"ZI de Lannugat",
    "sg:city":"Douarnenez C\u00e9dex",
    "sg:orig_category":"Non-Classified Establishments",
    "sg:phone":"+33 2 98 75 42 00",
    "sg:postcode":"29177",
    "sg:province":"Midi Pyr\u00e9n\u00e9es",
    "wof:name":"E.a.d.s. -dsn S.a.",
    "wof:placetype":"venue"
},
  "geometry": {"coordinates":[-4.298839,48.079185],"type":"Point"}
}