{
  "type": "Feature",
  "properties": {
    "iso:country":"FR",
    "sg:address":"14, Rue du Docteur Charcot, 91420 Morangis",
    "sg:orig_category":"Unclassifiable Establishments",
    "sg:phone":"+33 1 69 10 26 80",
    "sg:province":"Ile de France",
    "wof:name":"Soci\u00e9t\u00e9 Nouvelle Des Entreprises Semprez S.a.",
    "wof:placetype":"venue"
},
  "geometry": {"coordinates":[2.338666,48.694832],"type":"Point"}
}