{
  "type": "Feature",
  "properties": {
    "iso:country":"FR",
    "sg:address":"46, Rte d'Agde, 31500 Toulouse",
    "sg:orig_category":"Non-Classified Establishments",
    "sg:phone":"+33 5 61 48 72 97",
    "sg:postcode":"31500",
    "sg:province":"Midi Pyr\u00e9n\u00e9es",
    "wof:name":"Composition Legrand S.a.r.l.",
    "wof:placetype":"venue"
},
  "geometry": {"coordinates":[1.473593,43.623611],"type":"Point"}
}