{
  "type": "Feature",
  "properties": {
    "addr:full":"B.P. 14, 95250 Beauchamp C\u00e9dex^^21, Rue Denis Papin, 95250 Beauchamp Ile de France 95250",
    "addr:postcode":"95250;95250;ile;95250",
    "addr:street":"B.P. 14;Rue Denis Papin;France",
    "iso:country":"FR",
    "sg:address":"B.P. 14, 95250 Beauchamp C\u00e9dex^^21, Rue Denis Papin, 95250 Beauchamp",
    "sg:orig_category":"Non-Classified Establishments",
    "sg:phone":"+33 1 34 13 18 47",
    "sg:postcode":"95250",
    "sg:province":"Ile de France",
    "wof:name":"Etablissements Gaston Carbonne S.a.",
    "wof:placetype":"venue"
},
  "geometry": {"coordinates":[2.198048,49.009228],"type":"Point"}
}