{
  "type": "Feature",
  "properties": {
    "iso:country":"FR",
    "sg:address":"13 Rue Aristide Briand 69800 St Priest",
    "sg:classifiers":[
        {
            "category":"Bakery",
            "type":"Food & Drink"
        }
    ],
    "sg:phone":"+33 4 78 21 19 60",
    "sg:postcode":"69800",
    "sg:province":"Rhone-Alpes",
    "sg:tags":[
        "cake",
        "product",
        "related",
        "bread"
    ],
    "wof:name":"Sofrespi",
    "wof:placetype":"venue"
},
  "geometry": {"coordinates":[4.934966,45.691093],"type":"Point"}
}