{
  "type": "Feature",
  "properties": {
    "addr:full":"B.P. 235, 91007 Evry C\u00e9dex^^9/13, Av. du Lac - Parc du Bois Briard, 91080 Courcouronnes Ile de France 91080",
    "addr:housenumber":"b.p. 235",
    "addr:postcode":"91007;91080;91080",
    "addr:street":"13 Av. Du Lac Parc",
    "iso:country":"FR",
    "sg:address":"B.P. 235, 91007 Evry C\u00e9dex^^9/13, Av. du Lac - Parc du Bois Briard, 91080 Courcouronnes",
    "sg:orig_category":"Non-Classified Establishments",
    "sg:phone":"+33 1 69 87 51 11",
    "sg:postcode":"91080",
    "sg:province":"Ile de France",
    "wof:name":"Compaq S.a.r.l.",
    "wof:placetype":"venue"
},
  "geometry": {"coordinates":[2.410883,48.618111],"type":"Point"}
}