{
  "type": "Feature",
  "properties": {
    "addr:full":"58, Rue Pr\u00e9 Magne, 69126 Brindas Rhone-Alpes 69126",
    "addr:housenumber":"58",
    "addr:postcode":"69126;69126",
    "addr:street":"Rue Pre\u0301 Magne",
    "iso:country":"FR",
    "sg:address":"58, Rue Pr\u00e9 Magne, 69126 Brindas",
    "sg:orig_category":"Non-Classified Establishments",
    "sg:phone":"+33 4 78 45 09 42",
    "sg:postcode":"69126",
    "sg:province":"Rhone-Alpes",
    "wof:name":"D.p.i.b. S.a.r.l. - Distribution Peintures Industrielles Et B\u00e2timent",
    "wof:placetype":"venue"
},
  "geometry": {"coordinates":[4.697782,45.718861],"type":"Point"}
}