{
  "type": "Feature",
  "properties": {
    "addr:full":"B.P. 87, 69573 Dardilly C\u00e9dex^^11, Chemin des Hirondelles, 69570 Dardilly Rhone-Alpes",
    "addr:postcode":"69573;69570",
    "addr:street":"B.P. 87;Chemin Des Hirondelles",
    "iso:country":"FR",
    "sg:address":"B.P. 87, 69573 Dardilly C\u00e9dex^^11, Chemin des Hirondelles, 69570 Dardilly",
    "sg:orig_category":"Non-Classified Establishments",
    "sg:phone":"+33 4 78 43 27 25",
    "sg:province":"Rhone-Alpes",
    "wof:name":"Tc S.a.",
    "wof:placetype":"venue"
},
  "geometry": {"coordinates":[4.753535,45.805908],"type":"Point"}
}