{
  "type": "Feature",
  "properties": {
    "iso:country":"FR",
    "sg:address":"81630 Salvagnac",
    "sg:orig_category":"Unclassifiable Establishments",
    "sg:phone":"+33 5 63 40 46 71",
    "sg:province":"Midi Pyr\u00e9n\u00e9es",
    "wof:name":"Micro Pointe S.a.r.l.",
    "wof:placetype":"venue"
},
  "geometry": {"coordinates":[1.685331,43.906593],"type":"Point"}
}