{
  "type": "Feature",
  "properties": {
    "addr:full":"15 Boulevard Poissonniere Paris Ile de France 75002",
    "addr:housenumber":"15",
    "addr:postcode":"75002",
    "addr:street":"Boulevard Poissonniere",
    "iso:country":"FR",
    "sg:address":"15 Boulevard Poissonniere",
    "sg:city":"Paris",
    "sg:classifiers":[
        {
            "category":"Banks & Credit Unions",
            "subcategory":"Financial Services",
            "type":"Services"
        }
    ],
    "sg:phone":"+33 1 55 34 19 92",
    "sg:postcode":"75002",
    "sg:province":"Ile de France",
    "sg:tags":[
        "banking",
        "finance",
        "insurance"
    ],
    "wof:name":"Bnp Equitis",
    "wof:placetype":"venue"
},
  "geometry": {"coordinates":[2.345016,48.871006],"type":"Point"}
}