{
  "type": "Feature",
  "properties": {
    "addr:full":"78 R Des Solets 94533 Rungis Ile de France",
    "addr:housenumber":"78",
    "addr:postcode":"94533",
    "addr:street":"R Des Solets",
    "iso:country":"FR",
    "sg:address":"78 R Des Solets 94533 Rungis",
    "sg:classifiers":[
        {
            "category":"Shopping",
            "subcategory":"Computers & Home Electronics",
            "type":"Retail Goods"
        }
    ],
    "sg:phone":"+33 1 45 12 99 00",
    "sg:province":"Ile de France",
    "sg:tags":[
        "equipment",
        "electrical",
        "component",
        "electric",
        "electronic"
    ],
    "wof:name":"Elmitech Sa",
    "wof:placetype":"venue"
},
  "geometry": {"coordinates":[2.358515,48.744316],"type":"Point"}
}