{
  "type": "Feature",
  "properties": {
    "iso:country":"FR",
    "sg:address":"352 Rue Lecourbe 75015 Paris",
    "sg:classifiers":[
        {
            "category":"Food & Beverages",
            "subcategory":"Groceries & Convenience Stores",
            "type":"Retail Goods"
        }
    ],
    "sg:phone":"+33 1 45 54 76 94",
    "sg:postcode":"75015",
    "sg:province":"Ile de France",
    "sg:tags":[
        "product",
        "related"
    ],
    "wof:name":"Flo Boutique Sa",
    "wof:placetype":"venue"
},
  "geometry": {"coordinates":[2.282757,48.836678],"type":"Point"}
}