{
  "type": "Feature",
  "properties": {
    "iso:country":"FR",
    "sg:address":"38 Rue Du Gal Leclerc 94000 Cr\u00e9teil",
    "sg:classifiers":[
        {
            "category":"Bakery",
            "type":"Food & Drink"
        }
    ],
    "sg:phone":"+33 1 42 07 19 92",
    "sg:postcode":"94000",
    "sg:province":"Ile de France",
    "sg:tags":[
        "cake",
        "product",
        "related",
        "bread"
    ],
    "wof:name":"Patisserie Douceur D'ange",
    "wof:placetype":"venue"
},
  "geometry": {"coordinates":[2.463044,48.792435],"type":"Point"}
}