{
  "type": "Feature",
  "properties": {
    "addr:full":"8, Rue Eug\u00e8ne Varlin, 75010 Paris Ile de France 75010",
    "addr:housenumber":"8",
    "addr:postcode":"75010;75010",
    "addr:street":"Rue Euge\u0300Ne Varlin",
    "iso:country":"FR",
    "sg:address":"8, Rue Eug\u00e8ne Varlin, 75010 Paris",
    "sg:orig_category":"Non-Classified Establishments",
    "sg:phone":"+33 1 44 89 65 87",
    "sg:postcode":"75010",
    "sg:province":"Ile de France",
    "wof:name":"A.e.b.k. S.a.r.l.",
    "wof:placetype":"venue"
},
  "geometry": {"coordinates":[2.3649,48.8783],"type":"Point"}
}