{
  "type": "Feature",
  "properties": {
    "addr:full":"Rue Paul Bovier Lapierre Brignais Rhone-Alpes 69530",
    "addr:postcode":"69530",
    "addr:street":"Rue Paul Bovier Lapierre;Rhone-Alpes",
    "iso:country":"FR",
    "sg:address":"Rue Paul Bovier Lapierre",
    "sg:city":"Brignais",
    "sg:orig_category":"Non-Classified Establishments",
    "sg:phone":"+33 4 72 31 00 06",
    "sg:postcode":"69530",
    "sg:province":"Rhone-Alpes",
    "wof:name":"A.b.s. S.a.",
    "wof:placetype":"venue"
},
  "geometry": {"coordinates":[4.760495,45.673565],"type":"Point"}
}