{
  "type": "Feature",
  "properties": {
    "iso:country":"FR",
    "sg:address":"rue de la Vigne Adam 02210 GRISOLLES",
    "sg:classifiers":[
        {
            "category":"Manufacturing",
            "subcategory":"Motor Vehicles & Parts",
            "type":"Manufacturing & Wholesale Goods"
        }
    ],
    "sg:phone":"+33 3 23 71 27 40",
    "sg:province":"Picardie",
    "sg:tags":[
        "precision",
        "mechanic"
    ],
    "wof:name":"D-m France S.a.r.l",
    "wof:placetype":"venue"
},
  "geometry": {"coordinates":[3.35933,49.141529],"type":"Point"}
}