{
  "type": "Feature",
  "properties": {
    "iso:country":"FR",
    "sg:address":"10 All Des Grands Paquis 54180 Heillecourt",
    "sg:classifiers":[
        {
            "category":"Manufacturing",
            "subcategory":"Tools & Machinery",
            "type":"Manufacturing & Wholesale Goods"
        }
    ],
    "sg:phone":"+33 3 83 57 93 93",
    "sg:postcode":"54180",
    "sg:province":"Lorraine",
    "sg:tags":[
        "equipment",
        "measurement",
        "-",
        "precision",
        "instrument"
    ],
    "wof:name":"Babcock Wanson",
    "wof:placetype":"venue"
},
  "geometry": {"coordinates":[6.209676,48.649765],"type":"Point"}
}