{
  "type": "Feature",
  "properties": {
    "addr:full":"Departementale 8 Puits Gerard 13105 Mimet Basse Normandie",
    "addr:housenumber":"8",
    "addr:postcode":"13105",
    "addr:street":"Departementale;Gerard",
    "iso:country":"FR",
    "sg:address":"Departementale 8 Puits Gerard 13105 Mimet",
    "sg:classifiers":[
        {
            "category":"Manufacturing",
            "subcategory":"Metals",
            "type":"Manufacturing & Wholesale Goods"
        }
    ],
    "sg:phone":"+33 4 42 51 22 32",
    "sg:province":"Basse Normandie",
    "sg:tags":[
        "metallurgy",
        "steel",
        "metalworking"
    ],
    "wof:name":"Structures Espace Lumiere",
    "wof:placetype":"venue"
},
  "geometry": {"coordinates":[5.504875,43.414104],"type":"Point"}
}