{
  "type": "Feature",
  "properties": {
    "addr:full":"B.P. 66, 79260 La Cr\u00e8che C\u00e9dex^^ZI des Grands Champs, 79260 La Cr\u00e8che Poitou-Charentes",
    "addr:postcode":"79260;79260",
    "addr:street":"B.P. 66;Des Grands Champs;Cre\u0300Che",
    "iso:country":"FR",
    "sg:address":"B.P. 66, 79260 La Cr\u00e8che C\u00e9dex^^ZI des Grands Champs, 79260 La Cr\u00e8che",
    "sg:orig_category":"Non-Classified Establishments",
    "sg:phone":"+33 5 49 25 11 86",
    "sg:province":"Poitou-Charentes",
    "wof:name":"S.p.p. S.a. - Soci\u00e9t\u00e9 De Profilage Du Poitou",
    "wof:placetype":"venue"
},
  "geometry": {"coordinates":[-0.299454,46.36187],"type":"Point"}
}