{
  "type": "Feature",
  "properties": {
    "addr:full":"Zi Rte Des Aliz\u00e9s 76430 Sandouville Haute Normandie",
    "addr:postcode":"76430",
    "addr:street":"Rte Des Alize\u0301S;Haute Normandie",
    "iso:country":"FR",
    "sg:address":"Zi Rte Des Aliz\u00e9s 76430 Sandouville",
    "sg:classifiers":[
        {
            "category":"Professional",
            "type":"Services"
        }
    ],
    "sg:phone":"+33 2 35 55 46 46",
    "sg:province":"Haute Normandie",
    "sg:tags":[
        "transport"
    ],
    "wof:name":"Hesnault Sa",
    "wof:placetype":"venue"
},
  "geometry": {"coordinates":[0.321059,49.499043],"type":"Point"}
}