{
  "type": "Feature",
  "properties": {
    "addr:full":"Z.I. Du Roitelet 54730 GORCY Lorraine 54730",
    "addr:postcode":"54730;54730",
    "addr:street":"Z.I. Du Roitelet",
    "iso:country":"FR",
    "sg:address":"Z.I. Du Roitelet 54730 GORCY",
    "sg:classifiers":[
        {
            "category":"Professional",
            "subcategory":"Business Services",
            "type":"Services"
        }
    ],
    "sg:phone":"+33 3 82 26 84 87",
    "sg:postcode":"54730",
    "sg:province":"Lorraine",
    "sg:tags":[
        "high-precision",
        "mechanic"
    ],
    "wof:name":"Outipress Sa",
    "wof:placetype":"venue"
},
  "geometry": {"coordinates":[5.67516,49.542789],"type":"Point"}
}