{
  "type": "Feature",
  "properties": {
    "addr:full":"avenue Paul-Louis Merlin 73800 Montmelian Rhone-Alpes",
    "addr:postcode":"73800",
    "addr:street":"Avenue Paul-Louis Merlin",
    "iso:country":"FR",
    "sg:address":"avenue Paul-Louis Merlin 73800 Montmelian",
    "sg:classifiers":[
        {
            "category":"Farming",
            "subcategory":"Orchard",
            "type":"Manufacturing & Wholesale Goods"
        }
    ],
    "sg:phone":"+33 4 79 75 48 00",
    "sg:province":"Rhone-Alpes",
    "sg:tags":[
        "switchgear"
    ],
    "wof:name":"M.g.a. Sa",
    "wof:placetype":"venue"
},
  "geometry": {"coordinates":[6.058194,45.503727],"type":"Point"}
}