{
  "type": "Feature",
  "properties": {
    "iso:country":"FR",
    "sg:address":"31 rue de la Convention 38200 Vienne",
    "sg:classifiers":[
        {
            "category":"Animal Shelter",
            "type":"Public Place"
        }
    ],
    "sg:phone":"+33 4 74 78 03 87",
    "sg:postcode":"38200",
    "sg:province":"Rhone-Alpes",
    "sg:tags":[
        "civil",
        "defence"
    ],
    "wof:name":"Texabri Sa",
    "wof:placetype":"venue"
},
  "geometry": {"coordinates":[4.864699,45.540928],"type":"Point"}
}