{
  "type": "Feature",
  "properties": {
    "iso:country":"FR",
    "sg:address":"Z.I.",
    "sg:city":"Saint James",
    "sg:orig_category":"Unclassifiable Establishments",
    "sg:phone":"+33 2 33 89 15 60",
    "sg:postcode":"50240",
    "sg:province":"Basse Normandie",
    "wof:name":"Financi\u00e8re Tricots Saint James S.a.",
    "wof:placetype":"venue"
},
  "geometry": {"coordinates":[-1.420162,48.496712],"type":"Point"}
}