{
  "type": "Feature",
  "properties": {
    "addr:full":"11 Rue Des Jardiniers Za Deux Rivi\u00e8res 76000 Rouen Haute Normandie 76000",
    "addr:housenumber":"11;deux",
    "addr:postcode":"76000;76000",
    "addr:street":"Rue Des Jardiniers Za;Rivie\u0300Res;Haute Normandie",
    "iso:country":"FR",
    "sg:address":"11 Rue Des Jardiniers Za Deux Rivi\u00e8res 76000 Rouen",
    "sg:classifiers":[
        {
            "category":"Manufacturing",
            "subcategory":"Glass & Minerals",
            "type":"Manufacturing & Wholesale Goods"
        }
    ],
    "sg:phone":"+33 2 35 08 02 02",
    "sg:postcode":"76000",
    "sg:province":"Haute Normandie",
    "sg:tags":[
        "building",
        "material"
    ],
    "wof:name":"Miroiterie Dutheil Sa",
    "wof:placetype":"venue"
},
  "geometry": {"coordinates":[1.08933,49.44038],"type":"Point"}
}