{
  "type": "Feature",
  "properties": {
    "addr:full":"508, Rue Guynemer, 59500 Douai Nord Pas-de-Calais",
    "addr:housenumber":"508",
    "addr:postcode":"59500",
    "addr:street":"Rue Guynemer",
    "iso:country":"FR",
    "sg:address":"508, Rue Guynemer, 59500 Douai",
    "sg:orig_category":"Unclassifiable Establishments",
    "sg:phone":"+33 3 27 95 89 58",
    "sg:province":"Nord Pas-de-Calais",
    "wof:name":"N.e.t.r.e.l., S.a.",
    "wof:placetype":"venue"
},
  "geometry": {"coordinates":[3.059645,50.372169],"type":"Point"}
}