{
  "type": "Feature",
  "properties": {
    "addr:full":"B.P. 2038, 71020 Macon C\u00e9dex 9^^22, Rue du 134\u00e8me RI, 71000 M\u00e2con Sanc\u00e9 Bourgogne 71000",
    "addr:housenumber":"2038;9 ^ ^ 22",
    "addr:postcode":"71020;71000;71000",
    "addr:street":"B.P.;Ce\u0301Dex;Rue Du 134E\u0300Me",
    "iso:country":"FR",
    "sg:address":"B.P. 2038, 71020 Macon C\u00e9dex 9^^22, Rue du 134\u00e8me RI, 71000 M\u00e2con",
    "sg:city":"Sanc\u00e9",
    "sg:orig_category":"Non-Classified Establishments",
    "sg:phone":"+33 3 85 32 82 32",
    "sg:postcode":"71000",
    "sg:province":"Bourgogne",
    "wof:name":"Macon Imprimerie S.a.s.",
    "wof:placetype":"venue"
},
  "geometry": {"coordinates":[4.833055,46.303043],"type":"Point"}
}