{
  "type": "Feature",
  "properties": {
    "iso:country":"FR",
    "sg:address":"Chezeau BP 08 Ciel 71350 Verdun Sur Le Doubs",
    "sg:city":"Ciel",
    "sg:classifiers":[
        {
            "category":"Food & Beverages",
            "subcategory":"Fruits & Vegetables",
            "type":"Retail Goods"
        }
    ],
    "sg:phone":"+33 3 85 91 79 00",
    "sg:postcode":"71350",
    "sg:province":"Bourgogne",
    "sg:tags":[
        "preserve",
        "product",
        "related"
    ],
    "wof:name":"Val Daucy Sa",
    "wof:placetype":"venue"
},
  "geometry": {"coordinates":[4.909348,46.946522],"type":"Point"}
}