{
  "type": "Feature",
  "properties": {
    "addr:full":"195 Rue Marcel M\u00e9rieux 69007 Lyon Rhone-Alpes",
    "addr:housenumber":"195",
    "addr:postcode":"69007",
    "addr:street":"Rue Marcel Me\u0301Rieux",
    "iso:country":"FR",
    "sg:address":"195 Rue Marcel M\u00e9rieux 69007 Lyon",
    "sg:classifiers":[
        {
            "category":"Manufacturing",
            "subcategory":"Metals",
            "type":"Manufacturing & Wholesale Goods"
        }
    ],
    "sg:phone":"+33 4 78 58 01 22",
    "sg:province":"Rhone-Alpes",
    "sg:tags":[
        "metallurgy",
        "-",
        "metalworking",
        "metallic",
        "machine",
        "engineering",
        "finished",
        "mechanical"
    ],
    "wof:name":"Porcher Distribution Roussin",
    "wof:placetype":"venue"
},
  "geometry": {"coordinates":[4.829806,45.733608],"type":"Point"}
}