{
  "type": "Feature",
  "properties": {
    "addr:full":"ZI Thuisseau 37270 Montlouis sur Loire Ath\u00e9e-sur-Cher Centre 37270",
    "addr:housenumber":"athe\u0301e-sur-cher",
    "addr:postcode":"37270;37270",
    "iso:country":"FR",
    "sg:address":"ZI Thuisseau 37270 Montlouis sur Loire",
    "sg:city":"Ath\u00e9e-sur-Cher",
    "sg:classifiers":[
        {
            "category":"Autos & Motor Vehicles",
            "subcategory":"Automobile Sales",
            "type":"Retail Goods"
        }
    ],
    "sg:phone":"+33 2 47 45 03 25",
    "sg:postcode":"37270",
    "sg:province":"Centre",
    "sg:tags":[
        "equipment",
        "transport"
    ],
    "wof:name":"Occas'mat",
    "wof:placetype":"venue"
},
  "geometry": {"coordinates":[0.827175,47.388725],"type":"Point"}
}