{
  "type": "Feature",
  "properties": {
    "addr:full":"30 Rue Yves Lacelle 18400 Lunery Lunery Centre 18400",
    "addr:housenumber":"30;lunery",
    "addr:postcode":"18400;18400",
    "addr:street":"Rue Yves Lacelle",
    "iso:country":"FR",
    "sg:address":"30 Rue Yves Lacelle 18400 Lunery",
    "sg:city":"Lunery",
    "sg:classifiers":[
        {
            "category":"Shopping",
            "subcategory":"Computers & Home Electronics",
            "type":"Retail Goods"
        }
    ],
    "sg:phone":"+33 2 48 55 78 00",
    "sg:postcode":"18400",
    "sg:province":"Centre",
    "sg:tags":[
        "equipment",
        "household",
        "electrical",
        "appliance",
        "electronic"
    ],
    "wof:name":"Usines Rosieres",
    "wof:placetype":"venue"
},
  "geometry": {"coordinates":[2.25251,46.95726],"type":"Point"}
}