{
  "type": "Feature",
  "properties": {
    "addr:full":"R Des Bouvi\u00e8res 74940 Annecy Le Vieux Rhone-Alpes 74940",
    "addr:postcode":"74940;74940",
    "iso:country":"FR",
    "sg:address":"R Des Bouvi\u00e8res 74940 Annecy Le Vieux",
    "sg:orig_category":"Miscellaneous Products",
    "sg:phone":"+33 4 50 64 03 21",
    "sg:postcode":"74940",
    "sg:province":"Rhone-Alpes",
    "wof:name":"Bmf Bureau Moderne France Sa",
    "wof:placetype":"venue"
},
  "geometry": {"coordinates":[6.168633,45.927624],"type":"Point"}
}