{
  "type": "Feature",
  "properties": {
    "addr:full":"Rue de la Fr\u00e9gi\u00e8re 46200 SOUILLAC Midi Pyr\u00e9n\u00e9es 46200",
    "addr:postcode":"46200;46200",
    "addr:street":"Rue De La Fre\u0301Gie\u0300Re",
    "iso:country":"FR",
    "sg:address":"Rue de la Fr\u00e9gi\u00e8re 46200 SOUILLAC",
    "sg:classifiers":[
        {
            "category":"Farming",
            "subcategory":"Fish & Marine Products",
            "type":"Manufacturing & Wholesale Goods"
        }
    ],
    "sg:phone":"+33 5 65 27 07 07",
    "sg:postcode":"46200",
    "sg:province":"Midi Pyr\u00e9n\u00e9es",
    "sg:tags":[
        "closure",
        "pharmaceutical",
        "aluminium",
        "chemical-technical",
        "cosmetic"
    ],
    "wof:name":"Pivaudran Sa",
    "wof:placetype":"venue"
},
  "geometry": {"coordinates":[1.47424,44.893276],"type":"Point"}
}