{
  "type": "Feature",
  "properties": {
    "iso:country":"FR",
    "sg:address":"5 rue Cl\u00e9ment Ader 85340 Olonne sur Mer",
    "sg:classifiers":[
        {
            "category":"Home & Garden",
            "subcategory":"Household Appliances",
            "type":"Retail Goods"
        }
    ],
    "sg:phone":"+33 2 51 21 13 09",
    "sg:postcode":"85340",
    "sg:province":"Pays de Loire",
    "sg:tags":[
        "electric"
    ],
    "wof:name":"Saprofil Sa",
    "wof:placetype":"venue"
},
  "geometry": {"coordinates":[-1.781559,46.515766],"type":"Point"}
}