{
  "type": "Feature",
  "properties": {
    "addr:full":"31 Route De La Wantzenau 67800 Hoenheim Hoenheim Alsace 67800",
    "addr:housenumber":"31",
    "addr:postcode":"67800;67800",
    "addr:street":"Route De La Wantzenau",
    "iso:country":"FR",
    "sg:address":"31 Route De La Wantzenau 67800 Hoenheim",
    "sg:city":"Hoenheim",
    "sg:classifiers":[
        {
            "category":"Utilities",
            "subcategory":"Telephone",
            "type":"Services"
        }
    ],
    "sg:phone":"+33 3 88 62 51 00",
    "sg:postcode":"67800",
    "sg:province":"Alsace",
    "sg:tags":[
        "telecommunication"
    ],
    "wof:name":"Alsace Fabrication Publicite",
    "wof:placetype":"venue"
},
  "geometry": {"coordinates":[7.766943,48.632679],"type":"Point"}
}