{
  "type": "Feature",
  "properties": {
    "addr:full":"17 Rue Du Kefir Senia Sud 94310 Orly Ile de France 94310",
    "addr:housenumber":"17",
    "addr:postcode":"94310;94310",
    "addr:street":"Rue Du Kefir Senia Sud;Ile De France",
    "iso:country":"FR",
    "sg:address":"17 Rue Du Kefir Senia Sud 94310 Orly",
    "sg:classifiers":[
        {
            "category":"Food & Beverages",
            "subcategory":"Meat & Fish",
            "type":"Retail Goods"
        }
    ],
    "sg:phone":"+33 1 46 87 07 21",
    "sg:postcode":"94310",
    "sg:province":"Ile de France",
    "sg:tags":[
        "preserve",
        "cooked",
        "product",
        "related"
    ],
    "wof:name":"Sa Rougie Bizac International",
    "wof:placetype":"venue"
},
  "geometry": {"coordinates":[2.40138,48.743031],"type":"Point"}
}