{
  "type": "Feature",
  "properties": {
    "addr:full":"9 Rue Des Hallebardes 67000 Strasbourg Strasbourg Alsace 67000",
    "addr:housenumber":"9",
    "addr:postcode":"67000;67000",
    "addr:street":"Rue Des Hallebardes",
    "iso:country":"FR",
    "sg:address":"9 Rue Des Hallebardes 67000 Strasbourg",
    "sg:city":"Strasbourg",
    "sg:classifiers":[
        {
            "category":"Wholesale",
            "subcategory":"Machinery & Supplies",
            "type":"Manufacturing & Wholesale Goods"
        }
    ],
    "sg:phone":"+33 3 88 32 17 06",
    "sg:postcode":"67000",
    "sg:province":"Alsace",
    "sg:tags":[
        "equipment",
        "optical",
        "precision",
        "instrument"
    ],
    "wof:name":"Meyer Et Wanner",
    "wof:placetype":"venue"
},
  "geometry": {"coordinates":[7.749025,48.58202],"type":"Point"}
}