{
  "type": "Feature",
  "properties": {
    "iso:country":"FR",
    "sg:address":"ZA de la Foss\u00e9 Yvon",
    "sg:city":"Beaumont Hague",
    "sg:orig_category":"Non-Classified Establishments",
    "sg:phone":"+33 2 33 52 27 90",
    "sg:postcode":"50440",
    "sg:province":"Basse Normandie",
    "wof:name":"S\u00e9ma Group",
    "wof:placetype":"venue"
},
  "geometry": {"coordinates":[-1.836334,49.663555],"type":"Point"}
}