{
  "type": "Feature",
  "properties": {
    "addr:full":"Rue de Manbary - ZAC des Chataigniers Ormes Centre 45140",
    "addr:postcode":"45140",
    "addr:street":"Rue De Manbary Zac Des Chataigniers Ormes",
    "iso:country":"FR",
    "sg:address":"Rue de Manbary - ZAC des Chataigniers",
    "sg:city":"Ormes",
    "sg:orig_category":"Unclassifiable Establishments",
    "sg:phone":"+33 2 38 74 77 77",
    "sg:postcode":"45140",
    "sg:province":"Centre",
    "wof:name":"Burban Palettes Recyclage S.a.",
    "wof:placetype":"venue"
},
  "geometry": {"coordinates":[1.8745,47.912949],"type":"Point"}
}