{
  "type": "Feature",
  "properties": {
    "addr:full":"Rn7 Zone Industrielle Les Ortis 26240 Laveyron Rhone-Alpes",
    "addr:housenumber":"rn7",
    "addr:postcode":"26240",
    "addr:street":"Zone Industrielle Les Ortis",
    "iso:country":"FR",
    "sg:address":"Rn7 Zone Industrielle Les Ortis 26240 Laveyron",
    "sg:classifiers":[
        {
            "category":"Manufacturing",
            "subcategory":"Wood Products",
            "type":"Manufacturing & Wholesale Goods"
        }
    ],
    "sg:phone":"+33 4 75 23 22 03",
    "sg:province":"Rhone-Alpes",
    "sg:tags":[
        "furniture"
    ],
    "wof:name":"Sce De Protection De L Habitat Francais Sarl",
    "wof:placetype":"venue"
},
  "geometry": {"coordinates":[4.836268,45.159122],"type":"Point"}
}