{
  "type": "Feature",
  "properties": {
    "iso:country":"FR",
    "sg:address":"1 Av Eug\u00e8ne Freyssinet Challenger 78064 St Quentin En Yvelines",
    "sg:classifiers":[
        {
            "category":"Manufacturing",
            "subcategory":"Tools & Machinery",
            "type":"Manufacturing & Wholesale Goods"
        }
    ],
    "sg:phone":"+33 1 30 60 22 60",
    "sg:province":"Haute Normandie",
    "sg:tags":[
        "environment",
        "equipment",
        "-"
    ],
    "wof:name":"Saur",
    "wof:placetype":"venue"
},
  "geometry": {"coordinates":[2.04549,48.785019],"type":"Point"}
}