{
  "type": "Feature",
  "properties": {
    "addr:full":"54603 Villers l\u00e8s Nancy C\u00e9dex^^8, All\u00e9e Pelletier Doisy, 54600 Villers l\u00e8s Nancy Lorraine",
    "addr:postcode":"54603;54600",
    "addr:street":"Alle\u0301E Pelletier Doisy",
    "iso:country":"FR",
    "sg:address":"54603 Villers l\u00e8s Nancy C\u00e9dex^^8, All\u00e9e Pelletier Doisy, 54600 Villers l\u00e8s Nancy",
    "sg:orig_category":"Non-Classified Establishments",
    "sg:phone":"+33 3 83 50 44 45",
    "sg:province":"Lorraine",
    "wof:name":"Synt\u00e9gra S.a.",
    "wof:placetype":"venue"
},
  "geometry": {"coordinates":[6.153395,48.673084],"type":"Point"}
}