{
  "type": "Feature",
  "properties": {
    "iso:country":"FR",
    "sg:address":"ZI Saveyrolles",
    "sg:city":"Pierrelatte",
    "sg:orig_category":"Non-Classified Establishments",
    "sg:phone":"+33 4 75 96 88 30",
    "sg:postcode":"26700",
    "sg:province":"Rhone-Alpes",
    "wof:name":"Gyma Surgel\u00e9s S.a.",
    "wof:placetype":"venue"
},
  "geometry": {"coordinates":[4.69703,44.375584],"type":"Point"}
}