{
  "type": "Feature",
  "properties": {
    "addr:full":"B.P. 321, 69125 Lyon C\u00e9dex^^Zone de Fr\u00eat, 69120 Lyon Rhone-Alpes 69120",
    "addr:housenumber":"b.p. 321",
    "addr:postcode":"69125;69120;69120",
    "iso:country":"FR",
    "sg:address":"B.P. 321, 69125 Lyon C\u00e9dex^^Zone de Fr\u00eat, 69120 Lyon",
    "sg:orig_category":"Non-Classified Establishments",
    "sg:phone":"+33 4 72 22 71 51",
    "sg:postcode":"69120",
    "sg:province":"Rhone-Alpes",
    "wof:name":"Alloin Exmare S.a.",
    "wof:placetype":"venue"
},
  "geometry": {"coordinates":[4.916895,45.779022],"type":"Point"}
}