{
  "type": "Feature",
  "properties": {
    "iso:country":"FR",
    "sg:address":"33 Rte De Pau 65420 Ibos",
    "sg:classifiers":[
        {
            "category":"Manufacturing",
            "subcategory":"Chemicals & Compounds",
            "type":"Manufacturing & Wholesale Goods"
        }
    ],
    "sg:phone":"+33 5 62 90 61 75",
    "sg:postcode":"65420",
    "sg:province":"Midi Pyr\u00e9n\u00e9es",
    "sg:tags":[
        "pharmaceutical",
        "chemistry",
        "-",
        "by-product"
    ],
    "wof:name":"Bastiq Findley Sa",
    "wof:placetype":"venue"
},
  "geometry": {"coordinates":[-0.030319,43.24522],"type":"Point"}
}