{
  "type": "Feature",
  "properties": {
    "addr:full":"23, Rue des Carmes, 44000 Nantes Pays de Loire 44000",
    "addr:housenumber":"23",
    "addr:postcode":"44000;44000",
    "addr:street":"Rue Des Carmes",
    "iso:country":"FR",
    "sg:address":"23, Rue des Carmes, 44000 Nantes",
    "sg:orig_category":"Non-Classified Establishments",
    "sg:phone":"+33 2 40 47 68 32",
    "sg:postcode":"44000",
    "sg:province":"Pays de Loire",
    "wof:name":"Boulangerie Gabillet",
    "wof:placetype":"venue"
},
  "geometry": {"coordinates":[-1.555447,47.216377],"type":"Point"}
}