{
  "type": "Feature",
  "properties": {
    "addr:full":"Rte B\u00e9gude 26160 St Gervais Sur Roubion Rhone-Alpes",
    "addr:postcode":"26160",
    "addr:street":"Rte Be\u0301Gude",
    "iso:country":"FR",
    "sg:address":"Rte B\u00e9gude 26160 St Gervais Sur Roubion",
    "sg:classifiers":[
        {
            "category":"Professional",
            "type":"Services"
        }
    ],
    "sg:phone":"+33 4 75 53 90 08",
    "sg:province":"Rhone-Alpes",
    "sg:tags":[
        "transport",
        "road"
    ],
    "wof:name":"Transports Noyer Fils Sarl",
    "wof:placetype":"venue"
},
  "geometry": {"coordinates":[4.858505,44.503109],"type":"Point"}
}