{
  "type": "Feature",
  "properties": {
    "addr:full":"Lesgall 29260 PLOUDANIEL Ploudaniel Bretagne 29260",
    "addr:postcode":"29260;29260",
    "addr:street":"Lesgall",
    "iso:country":"FR",
    "sg:address":"Lesgall 29260 PLOUDANIEL",
    "sg:city":"Ploudaniel",
    "sg:classifiers":[
        {
            "category":"Food & Beverages",
            "subcategory":"Meat & Fish",
            "type":"Retail Goods"
        }
    ],
    "sg:phone":"+33 2 98 85 52 06",
    "sg:postcode":"29260",
    "sg:province":"Bretagne",
    "sg:tags":[
        "product"
    ],
    "wof:name":"Ouest Elevage Coop\u00e9rative",
    "wof:placetype":"venue"
},
  "geometry": {"coordinates":[-4.366049,48.539703],"type":"Point"}
}