{
  "type": "Feature",
  "properties": {
    "addr:full":"2 rue du G\u00e9n\u00e9ral de Gaulle; Schirmeck; 67130 Schirmeck Alsace 67130",
    "addr:housenumber":"2",
    "addr:postcode":"67130;67130",
    "addr:street":"Rue Du Ge\u0301Ne\u0301Ral De Gaulle",
    "iso:country":"FR",
    "sg:address":"2 rue du G\u00e9n\u00e9ral de Gaulle; Schirmeck; 67130",
    "sg:city":"Schirmeck",
    "sg:classifiers":[
        {
            "category":"Banks & Credit Unions",
            "subcategory":"Bank",
            "type":"Services"
        }
    ],
    "sg:phone":"+33 3 88 97 90 93",
    "sg:postcode":"67130",
    "sg:province":"Alsace",
    "wof:name":"Cr\u00e9dit Industriel D'alsace, Et De Lorraine Sa",
    "wof:placetype":"venue"
},
  "geometry": {"coordinates":[7.207988,48.481342],"type":"Point"}
}