{
  "type": "Feature",
  "properties": {
    "addr:full":"Foun De Boou 66210 Les Angles Languedoc-Roussillon 66210",
    "addr:postcode":"66210 les angles;66210",
    "addr:street":"Foun",
    "iso:country":"FR",
    "sg:address":"Foun De Boou 66210 Les Angles",
    "sg:classifiers":[
        {
            "category":"Farming",
            "subcategory":"Farm & Veterinary Services",
            "type":"Manufacturing & Wholesale Goods"
        }
    ],
    "sg:phone":"+33 4 68 30 99 09",
    "sg:postcode":"66210",
    "sg:province":"Languedoc-Roussillon",
    "sg:tags":[
        "advice",
        "agriculture",
        "livestock",
        "business"
    ],
    "wof:name":"Capcir Bois",
    "wof:placetype":"venue"
},
  "geometry": {"coordinates":[2.077859,42.50407],"type":"Point"}
}