{
  "type": "Feature",
  "properties": {
    "iso:country":"FR",
    "sg:address":"16 Avenue Pablo Picasso 01000 Bourg En Bresse",
    "sg:classifiers":[
        {
            "category":"Manufacturing",
            "subcategory":"Metals",
            "type":"Manufacturing & Wholesale Goods"
        }
    ],
    "sg:phone":"+33 4 74 22 26 81",
    "sg:postcode":"01000",
    "sg:province":"Rhone-Alpes",
    "sg:tags":[
        "metallurgy",
        "steel",
        "metalworking"
    ],
    "wof:name":"Mecano Soudure De Lain Sas",
    "wof:placetype":"venue"
},
  "geometry": {"coordinates":[5.247123,46.199921],"type":"Point"}
}