{
  "type": "Feature",
  "properties": {
    "addr:full":"B.P. 34, 59640 Dunkerque^^Rue Armand Carrel, 59640 Dunkerque Languedoc-Roussillon",
    "addr:postcode":"59640;59640",
    "addr:street":"B.P. 34;Armand Carrel",
    "iso:country":"FR",
    "sg:address":"B.P. 34, 59640 Dunkerque^^Rue Armand Carrel, 59640 Dunkerque",
    "sg:orig_category":"Non-Classified Establishments",
    "sg:phone":"+33 3 28 61 99 40",
    "sg:province":"Languedoc-Roussillon",
    "wof:name":"Boccard S.a.",
    "wof:placetype":"venue"
},
  "geometry": {"coordinates":[2.33656,51.01675],"type":"Point"}
}