{
  "type": "Feature",
  "properties": {
    "iso:country":"FR",
    "sg:address":"2 rue Georges Cl\u00e9menceau 57200 Sarreguemines",
    "sg:classifiers":[
        {
            "category":"Professional",
            "subcategory":"Employment Agencies",
            "type":"Services"
        }
    ],
    "sg:phone":"+33 3 87 28 15 57",
    "sg:province":"Lorraine",
    "sg:tags":[
        "personnel",
        "temporary"
    ],
    "wof:name":"Indumat Service S.a.r.l.",
    "wof:placetype":"venue"
},
  "geometry": {"coordinates":[7.0711,49.11475],"type":"Point"}
}