{
  "type": "Feature",
  "properties": {
    "addr:full":"29650 Guerlesquin Guerlesquin Bretagne 29650",
    "addr:postcode":"29650;29650",
    "addr:street":"Guerlesquin",
    "iso:country":"FR",
    "sg:address":"29650 Guerlesquin",
    "sg:city":"Guerlesquin",
    "sg:orig_category":"Non-Classified Establishments",
    "sg:phone":"+33 2 98 72 84 11",
    "sg:postcode":"29650",
    "sg:province":"Bretagne",
    "wof:name":"Tilly-sabco S.a.",
    "wof:placetype":"venue"
},
  "geometry": {"coordinates":[-3.587335,48.517735],"type":"Point"}
}