{
  "type": "Feature",
  "properties": {
    "addr:full":"104 bis, Rue Commandant Charcot, 69005 Lyon Rhone-Alpes",
    "addr:housenumber":"104 bis",
    "addr:postcode":"69005",
    "addr:street":"Rue Commandant Charcot",
    "iso:country":"FR",
    "sg:address":"104 bis, Rue Commandant Charcot, 69005 Lyon",
    "sg:orig_category":"Unclassifiable Establishments",
    "sg:phone":"+33 4 78 15 08 08",
    "sg:province":"Rhone-Alpes",
    "wof:name":"Aldec S.a.",
    "wof:placetype":"venue"
},
  "geometry": {"coordinates":[4.795322,45.749653],"type":"Point"}
}