{
  "type": "Feature",
  "properties": {
    "iso:country":"FR",
    "sg:address":"Rue Pierre et Marie Curie - ZAL du 14 Juillet",
    "sg:city":"Saint Laurent Blangy",
    "sg:orig_category":"Non-Classified Establishments",
    "sg:phone":"+33 3 21 73 48 10",
    "sg:postcode":"62223",
    "sg:province":"Nord Pas-de-Calais",
    "wof:name":"Klinos S.a.",
    "wof:placetype":"venue"
},
  "geometry": {"coordinates":[2.80747,50.30629],"type":"Point"}
}