{
  "type": "Feature",
  "properties": {
    "addr:full":"1, Rue des Nuattes - ZA, 10220 Piney Champagne",
    "addr:housenumber":"1;10220",
    "addr:street":"Rue Des Nuattes Za",
    "iso:country":"FR",
    "sg:address":"1, Rue des Nuattes - ZA, 10220 Piney",
    "sg:orig_category":"Unclassifiable Establishments",
    "sg:phone":"+33 3 25 46 40 34",
    "sg:province":"Champagne",
    "wof:name":"Rapinat S.a.r.l.",
    "wof:placetype":"venue"
},
  "geometry": {"coordinates":[4.32583,48.363701],"type":"Point"}
}