{
  "type": "Feature",
  "properties": {
    "addr:full":"Chemin des H\u00e9rissons - ZA le Gorget Saint Prest Centre 28300",
    "addr:postcode":"28300",
    "addr:street":"Chemin Des He\u0301Rissons Za Le Gorget Saint Prest",
    "iso:country":"FR",
    "sg:address":"Chemin des H\u00e9rissons - ZA le Gorget",
    "sg:city":"Saint Prest",
    "sg:orig_category":"Non-Classified Establishments",
    "sg:phone":"+33 2 37 21 33 66",
    "sg:postcode":"28300",
    "sg:province":"Centre",
    "wof:name":"S\u00e9rigraphie Daniel S.a.r.l.",
    "wof:placetype":"venue"
},
  "geometry": {"coordinates":[1.464137,48.448517],"type":"Point"}
}