{
  "type": "Feature",
  "properties": {
    "addr:full":"12 Rue Pierre De Blois Blois Centre 41000",
    "addr:housenumber":"12",
    "addr:postcode":"41000",
    "addr:street":"Rue Pierre De Blois Blois",
    "iso:country":"FR",
    "sg:address":"12 Rue Pierre De Blois",
    "sg:city":"Blois",
    "sg:classifiers":[
        {
            "category":"Banks & Credit Unions",
            "subcategory":"Financial Services",
            "type":"Services"
        }
    ],
    "sg:phone":"+33 2 54 78 10 52",
    "sg:postcode":"41000",
    "sg:province":"Centre",
    "sg:tags":[
        "banking",
        "finance",
        "insurance"
    ],
    "wof:name":"Societe Fiduciaire Nationale D'expertise Comptable Fidexpert (fid)",
    "wof:placetype":"venue"
},
  "geometry": {"coordinates":[1.334617,47.588085],"type":"Point"}
}