{
  "type": "Feature",
  "properties": {
    "addr:full":"14, Rue Dorian, 42190 Charlieu Rhone-Alpes",
    "addr:housenumber":"14",
    "addr:postcode":"42190",
    "addr:street":"Rue Dorian",
    "iso:country":"FR",
    "sg:address":"14, Rue Dorian, 42190 Charlieu",
    "sg:orig_category":"Unclassifiable Establishments",
    "sg:phone":"+33 4 77 69 33 69",
    "sg:province":"Rhone-Alpes",
    "wof:name":"A.d.a.p.e.i. - C.a.t. De Charlieu",
    "wof:placetype":"venue"
},
  "geometry": {"coordinates":[4.166522,46.155891],"type":"Point"}
}