{
  "type": "Feature",
  "properties": {
    "addr:full":"B.P. 3, 09700 Saverdun C\u00e9dex^^7, Rue du Moulin, 09700 Saverdun Midi Pyr\u00e9n\u00e9es",
    "addr:housenumber":"3",
    "addr:postcode":"09700;09700",
    "addr:street":"B.P.;Rue Du Moulin",
    "iso:country":"FR",
    "sg:address":"B.P. 3, 09700 Saverdun C\u00e9dex^^7, Rue du Moulin, 09700 Saverdun",
    "sg:orig_category":"Non-Classified Establishments",
    "sg:phone":"+33 5 61 60 30 09",
    "sg:province":"Midi Pyr\u00e9n\u00e9es",
    "wof:name":"Minoterie Mercier Capla S.a.",
    "wof:placetype":"venue"
},
  "geometry": {"coordinates":[1.5882,43.211658],"type":"Point"}
}