{
  "type": "Feature",
  "properties": {
    "addr:full":"38, Av. du G\u00e9n\u00e9ral de Gaulle, 33720 Barsac Barsac Aquitaine 33720",
    "addr:postcode":"33720;33720",
    "addr:street":"38 Av. Du Ge\u0301Ne\u0301Ral De Gaulle",
    "iso:country":"FR",
    "sg:address":"38, Av. du G\u00e9n\u00e9ral de Gaulle, 33720 Barsac",
    "sg:city":"Barsac",
    "sg:orig_category":"Unclassifiable Establishments",
    "sg:phone":"+33 5 56 27 15 26",
    "sg:postcode":"33720",
    "sg:province":"Aquitaine",
    "wof:name":"Michel Roumazeille Et Fils S.a.",
    "wof:placetype":"venue"
},
  "geometry": {"coordinates":[-0.321983,44.605534],"type":"Point"}
}