{
  "type": "Feature",
  "properties": {
    "iso:country":"FR",
    "sg:address":"La Rivi\u00e8re de Palisse 19360 Malemort sur Corr\u00e8ze",
    "sg:orig_category":"Non-Classified Establishments",
    "sg:phone":"+33 5 55 92 12 29",
    "sg:province":"Limousin",
    "wof:name":"Plasticor S.a.",
    "wof:placetype":"venue"
},
  "geometry": {"coordinates":[1.585306,45.135616],"type":"Point"}
}