{
  "type": "Feature",
  "properties": {
    "addr:full":"B.P. 79, 84302 Cavaillon C\u00e9dex^^Av. du G\u00e9n\u00e9ral de Gaulle, 84300 Cavaillon Pays de Loire",
    "addr:postcode":"84302;84300",
    "addr:street":"B.P. 79;Ge\u0301Ne\u0301Ral De Gaulle",
    "iso:country":"FR",
    "sg:address":"B.P. 79, 84302 Cavaillon C\u00e9dex^^Av. du G\u00e9n\u00e9ral de Gaulle, 84300 Cavaillon",
    "sg:orig_category":"Non-Classified Establishments",
    "sg:phone":"+33 4 90 71 55 74",
    "sg:province":"Pays de Loire",
    "wof:name":"Etablissements B\u00e9rard S.a.",
    "wof:placetype":"venue"
},
  "geometry": {"coordinates":[5.039415,43.837685],"type":"Point"}
}