{
  "type": "Feature",
  "properties": {
    "addr:full":"B.P. 307, 16008 Angoul\u00eame C\u00e9dex^^58, Rue Leclerc Chauvin, 16000 Angoul\u00eame Poitou-Charentes 16000",
    "addr:housenumber":"b.p. 307",
    "addr:postcode":"16008;16000;16000",
    "addr:street":"Rue Leclerc Chauvin",
    "iso:country":"FR",
    "sg:address":"B.P. 307, 16008 Angoul\u00eame C\u00e9dex^^58, Rue Leclerc Chauvin, 16000 Angoul\u00eame",
    "sg:orig_category":"Non-Classified Establishments",
    "sg:phone":"+33 5 45 95 87 62",
    "sg:postcode":"16000",
    "sg:province":"Poitou-Charentes",
    "wof:name":"Agence C.n.c. - Compagnie Nouvelle De Containers",
    "wof:placetype":"venue"
},
  "geometry": {"coordinates":[0.156985,45.649239],"type":"Point"}
}