{
  "type": "Feature",
  "properties": {
    "iso:country":"FR",
    "sg:address":"Route Duvigneau",
    "sg:city":"Industrielle Des Huttes 59820 Gravelines",
    "sg:classifiers":[
        {
            "category":"Manufacturing",
            "subcategory":"Metals",
            "type":"Manufacturing & Wholesale Goods"
        }
    ],
    "sg:phone":"+33 3 28 51 91 91",
    "sg:postcode":"59820",
    "sg:province":"Nord Pas-de-Calais",
    "sg:tags":[
        "metallurgy",
        "steel",
        "metalworking"
    ],
    "wof:name":"Bus Valera",
    "wof:placetype":"venue"
},
  "geometry": {"coordinates":[2.13518,50.990211],"type":"Point"}
}