{
  "type": "Feature",
  "properties": {
    "addr:full":"48, Av. des Templiers - ZA Napollon, 13676 Aubagne C\u00e9dex Languedoc-Roussillon",
    "addr:postcode":"13676;ce\u0301dex",
    "addr:street":"48 Av. Des Templiers Za Napollon",
    "iso:country":"FR",
    "sg:address":"48, Av. des Templiers - ZA Napollon, 13676 Aubagne C\u00e9dex",
    "sg:orig_category":"Non-Classified Establishments",
    "sg:phone":"+33 4 42 18 71 87",
    "sg:province":"Languedoc-Roussillon",
    "wof:name":"Technofirst S.a.",
    "wof:placetype":"venue"
},
  "geometry": {"coordinates":[5.57028,43.293251],"type":"Point"}
}