{
  "type": "Feature",
  "properties": {
    "addr:full":"Rte De Laghet 06340 La Trinit\u00e9 La Trinit\u00e9 Basse Normandie 50800",
    "addr:postcode":"06340;50800",
    "addr:street":"Rte De Laghet",
    "iso:country":"FR",
    "sg:address":"Rte De Laghet 06340 La Trinit\u00e9",
    "sg:city":"La Trinit\u00e9",
    "sg:classifiers":[
        {
            "category":"Shopping",
            "type":"Retail Goods"
        }
    ],
    "sg:phone":"+33 4 97 00 03 51",
    "sg:postcode":"50800",
    "sg:province":"Basse Normandie",
    "sg:tags":[
        "metallurgy",
        "finished",
        "-",
        "metalworking",
        "metallic"
    ],
    "wof:name":"Ste Mediterraneenne De Batiment Et De Renovation",
    "wof:placetype":"venue"
},
  "geometry": {"coordinates":[7.384415,43.750359],"type":"Point"}
}