{
  "type": "Feature",
  "properties": {
    "iso:country":"FR",
    "sg:address":"ZI de Pouillot",
    "sg:city":"Ch\u00e2teaulin",
    "sg:orig_category":"Unclassifiable Establishments",
    "sg:phone":"+33 2 98 86 37 37",
    "sg:postcode":"29150",
    "sg:province":"Bretagne",
    "wof:name":"Etablissements Cras S.a.r.l.",
    "wof:placetype":"venue"
},
  "geometry": {"coordinates":[-4.091959,48.196465],"type":"Point"}
}