{
  "type": "Feature",
  "properties": {
    "addr:full":"Avenue De La Gare 34360 St Chinian Languedoc-Roussillon 34360",
    "addr:postcode":"34360;34360",
    "addr:street":"Avenue De La Gare",
    "iso:country":"FR",
    "sg:address":"Avenue De La Gare 34360 St Chinian",
    "sg:classifiers":[
        {
            "category":"Building & Trades",
            "subcategory":"Construction",
            "type":"Services"
        }
    ],
    "sg:phone":"+33 4 67 38 00 07",
    "sg:postcode":"34360",
    "sg:province":"Languedoc-Roussillon",
    "sg:tags":[
        "advice",
        "work",
        "public",
        "business"
    ],
    "wof:name":"Societe D'amenagement Urbain Et Rural",
    "wof:placetype":"venue"
},
  "geometry": {"coordinates":[2.949045,43.421013],"type":"Point"}
}