{
  "type": "Feature",
  "properties": {
    "addr:full":"Parc d'Activit\u00e9s Festre sud BP 11 06530 Saint C\u00e9zaire sur Siagne Champagne",
    "addr:postcode":"06530",
    "addr:street":"Bp 11",
    "iso:country":"FR",
    "sg:address":"Parc d'Activit\u00e9s Festre sud BP 11 06530 Saint C\u00e9zaire sur Siagne",
    "sg:classifiers":[
        {
            "category":"Manufacturing",
            "subcategory":"Chemicals & Compounds",
            "type":"Manufacturing & Wholesale Goods"
        }
    ],
    "sg:phone":"+33 4 93 60 23 55",
    "sg:province":"Champagne",
    "sg:tags":[
        "pharmaceutical",
        "cosmetic"
    ],
    "wof:name":"Societe Francaise Aromatique R. Romani",
    "wof:placetype":"venue"
},
  "geometry": {"coordinates":[6.79297,43.650108],"type":"Point"}
}