{
  "type": "Feature",
  "properties": {
    "iso:country":"FR",
    "sg:address":"140 Av Jean Lolive Bat C1 93500 Pantin Cedex",
    "sg:classifiers":[
        {
            "category":"Shopping",
            "subcategory":"Computers & Home Electronics",
            "type":"Retail Goods"
        }
    ],
    "sg:phone":"+33 1 48 10 60 00",
    "sg:postcode":"93500",
    "sg:province":"Ile de France",
    "sg:tags":[
        "equipment",
        "electrical",
        "component",
        "electric",
        "electronic"
    ],
    "wof:name":"Ifm Electronic",
    "wof:placetype":"venue"
},
  "geometry": {"coordinates":[2.414667,48.893345],"type":"Point"}
}