{
  "type": "Feature",
  "properties": {
    "addr:full":"RUE DES EAUX 35500 VITRE Vitr\u00e9 Bretagne 35500",
    "addr:postcode":"35500 vitre vitre\u0301;35500",
    "addr:street":"Rue Des Eaux",
    "iso:country":"FR",
    "sg:address":"RUE DES EAUX 35500 VITRE",
    "sg:city":"Vitr\u00e9",
    "sg:classifiers":[
        {
            "category":"Personal",
            "subcategory":"Skin Care",
            "type":"Services"
        }
    ],
    "sg:phone":"+33 2 99 75 77 00",
    "sg:postcode":"35500",
    "sg:province":"Bretagne",
    "sg:tags":[
        "clips",
        "earrings",
        "ear",
        "stud"
    ],
    "wof:name":"Allflex Europe Sa",
    "wof:placetype":"venue"
},
  "geometry": {"coordinates":[-1.187796,48.114586],"type":"Point"}
}