{
  "type": "Feature",
  "properties": {
    "addr:full":"Chemin Port Bernalin Parcieux Rhone-Alpes 01600",
    "addr:postcode":"01600",
    "addr:street":"Chemin Port Bernalin;Rhone-Alpes",
    "iso:country":"FR",
    "sg:address":"Chemin Port Bernalin",
    "sg:city":"Parcieux",
    "sg:orig_category":"Non-Classified Establishments",
    "sg:phone":"+33 4 72 08 68 63",
    "sg:postcode":"01600",
    "sg:province":"Rhone-Alpes",
    "wof:name":"G.e.i. S.a. - G\u00e9n\u00e9rale D'entreprise Industrielle",
    "wof:placetype":"venue"
},
  "geometry": {"coordinates":[4.81088,45.920204],"type":"Point"}
}