{
  "type": "Feature",
  "properties": {
    "addr:full":"8, Rue Paul Doumer, 34140 M\u00e8ze Languedoc-Roussillon",
    "addr:housenumber":"8",
    "addr:postcode":"34140",
    "addr:street":"Rue Paul Doumer",
    "iso:country":"FR",
    "sg:address":"8, Rue Paul Doumer, 34140 M\u00e8ze",
    "sg:orig_category":"Unclassifiable Establishments",
    "sg:phone":"+33 4 67 43 80 68",
    "sg:province":"Languedoc-Roussillon",
    "wof:name":"Etablissements Bessier S.a.r.l.",
    "wof:placetype":"venue"
},
  "geometry": {"coordinates":[3.60527,43.425346],"type":"Point"}
}