{
  "type": "Feature",
  "properties": {
    "iso:country":"FR",
    "sg:address":"22, Rue Jacques Terrible, 33190 La R\u00e9ole",
    "sg:city":"La R\u00e9ole",
    "sg:orig_category":"Unclassifiable Establishments",
    "sg:phone":"+33 5 56 61 01 32",
    "sg:postcode":"33190",
    "sg:province":"Aquitaine",
    "wof:name":"C.r.b. S.a.s. - Centrale R\u00e9olaise Des Bois",
    "wof:placetype":"venue"
},
  "geometry": {"coordinates":[-0.044073,44.581535],"type":"Point"}
}