{
  "type": "Feature",
  "properties": {
    "iso:country":"FR",
    "sg:address":"28, Rue de Terre Rouge, 25000 Besan\u00e7on",
    "sg:orig_category":"Non-Classified Establishments",
    "sg:phone":"+33 3 81 52 79 32",
    "sg:postcode":"25000",
    "sg:province":"Franche Comt\u00e9",
    "wof:name":"Baronchelli P\u00e8re Et Fils S.a.r.l.",
    "wof:placetype":"venue"
},
  "geometry": {"coordinates":[5.982289,47.228996],"type":"Point"}
}