{
  "type": "Feature",
  "properties": {
    "addr:full":"11, Rue Andr\u00e9 Amp\u00e8re - ZI de la Chartreuse, 81100 Castres Midi Pyr\u00e9n\u00e9es",
    "addr:housenumber":"11",
    "addr:postcode":"81100",
    "addr:street":"Rue Andre\u0301 Ampe\u0300Re Zi De La Chartreuse",
    "iso:country":"FR",
    "sg:address":"11, Rue Andr\u00e9 Amp\u00e8re - ZI de la Chartreuse, 81100 Castres",
    "sg:orig_category":"Unclassifiable Establishments",
    "sg:phone":"+33 5 63 59 29 31",
    "sg:province":"Midi Pyr\u00e9n\u00e9es",
    "wof:name":"Radua S.a.r.l.",
    "wof:placetype":"venue"
},
  "geometry": {"coordinates":[2.257356,43.56094],"type":"Point"}
}