{
  "type": "Feature",
  "properties": {
    "addr:full":"31 Bd D'Artagnan Eauze Midi Pyr\u00e9n\u00e9es 32800",
    "addr:housenumber":"31",
    "addr:postcode":"32800",
    "addr:street":"Bd D'Artagnan",
    "iso:country":"FR",
    "sg:address":"31 Bd D'Artagnan",
    "sg:city":"Eauze",
    "sg:classifiers":[
        {
            "category":"Banks & Credit Unions",
            "subcategory":"Financial Services",
            "type":"Services"
        }
    ],
    "sg:phone":"+33 5 62 09 88 67",
    "sg:postcode":"32800",
    "sg:province":"Midi Pyr\u00e9n\u00e9es",
    "sg:tags":[
        "banking",
        "finance",
        "insurance"
    ],
    "wof:name":"Ctre Comptabilite Gestion Agriculteurs Ass",
    "wof:placetype":"venue"
},
  "geometry": {"coordinates":[0.100024,43.862263],"type":"Point"}
}