{
  "type": "Feature",
  "properties": {
    "iso:country":"FR",
    "sg:address":"35 rue des Messiers 93100 Montreuil",
    "sg:classifiers":[
        {
            "category":"Communications",
            "subcategory":"Newspaper",
            "type":"Services"
        }
    ],
    "sg:phone":"+33 1 55 86 18 00",
    "sg:province":"Ile de France",
    "sg:tags":[
        "specialist"
    ],
    "wof:name":"Les Editions De La Ffmc S.a.r.l.",
    "wof:placetype":"venue"
},
  "geometry": {"coordinates":[2.429309,48.859955],"type":"Point"}
}