{
  "type": "Feature",
  "properties": {
    "addr:full":"30BIS rue Paul Sabatier 71530 Crissey Crissey Bourgogne 71530",
    "addr:housenumber":"30bis",
    "addr:postcode":"71530;71530",
    "addr:street":"Rue Paul Sabatier",
    "iso:country":"FR",
    "sg:address":"30BIS rue Paul Sabatier 71530 Crissey",
    "sg:city":"Crissey",
    "sg:classifiers":[
        {
            "category":"Professional",
            "type":"Services"
        }
    ],
    "sg:phone":"+33 3 85 97 40 00",
    "sg:postcode":"71530",
    "sg:province":"Bourgogne",
    "sg:tags":[
        "transport"
    ],
    "wof:name":"Sobotran Sa",
    "wof:placetype":"venue"
},
  "geometry": {"coordinates":[4.862958,46.820801],"type":"Point"}
}