{
  "type": "Feature",
  "properties": {
    "iso:country":"FR",
    "sg:address":"147 La Forge Feret 76520 Boos",
    "sg:classifiers":[
        {
            "category":"Professional",
            "subcategory":"Engineering",
            "type":"Services"
        }
    ],
    "sg:phone":"+33 2 35 79 01 02",
    "sg:postcode":"76520",
    "sg:province":"Haute Normandie",
    "sg:tags":[
        "machine",
        "-",
        "mechanical"
    ],
    "wof:name":"Ida (innovation Developpement Application)",
    "wof:placetype":"venue"
},
  "geometry": {"coordinates":[1.208435,49.388969],"type":"Point"}
}