{
  "type": "Feature",
  "properties": {
    "iso:country":"FR",
    "sg:address":"11 Rue Amp\u00e8re 85270 St Hilaire De Riez",
    "sg:classifiers":[
        {
            "category":"Manufacturing",
            "subcategory":"Metals",
            "type":"Manufacturing & Wholesale Goods"
        }
    ],
    "sg:phone":"+33 2 51 54 31 03",
    "sg:postcode":"85270",
    "sg:province":"Pays de Loire",
    "sg:tags":[
        "metallurgy",
        "metalworking",
        "processing"
    ],
    "wof:name":"Ets Farges Sarl",
    "wof:placetype":"venue"
},
  "geometry": {"coordinates":[-1.938697,46.729198],"type":"Point"}
}