{
  "type": "Feature",
  "properties": {
    "addr:full":"79 Av Alfred Anatole Th\u00e9venet 51319 Magenta Aquitaine",
    "addr:postcode":"51319",
    "addr:street":"79 Av Alfred Anatole The\u0301Venet",
    "iso:country":"FR",
    "sg:address":"79 Av Alfred Anatole Th\u00e9venet 51319 Magenta",
    "sg:classifiers":[
        {
            "category":"Professional",
            "subcategory":"Engineering",
            "type":"Services"
        }
    ],
    "sg:phone":"+33 3 26 51 56 45",
    "sg:province":"Aquitaine",
    "sg:tags":[
        "machine",
        "-",
        "mechanical"
    ],
    "wof:name":"Station Oenotechnique De Champagne Martin Vialatte",
    "wof:placetype":"venue"
},
  "geometry": {"coordinates":[-93.579498,32.373512],"type":"Point"}
}