{
  "type": "Feature",
  "properties": {
    "iso:country":"FR",
    "sg:address":"1, Chemin de la Fosse Boulard, 78125 Emanc\u00e9",
    "sg:orig_category":"Unclassifiable Establishments",
    "sg:phone":"+33 1 34 94 07 07",
    "sg:province":"Ile de France",
    "wof:name":"Solution S.a.",
    "wof:placetype":"venue"
},
  "geometry": {"coordinates":[1.74325,48.588886],"type":"Point"}
}