{
  "type": "Feature",
  "properties": {
    "addr:full":"2 rue des Terres Fortes 77600 Chanteloup en Brie Ile de France",
    "addr:housenumber":"2",
    "addr:postcode":"77600",
    "addr:street":"Rue Des Terres Fortes",
    "iso:country":"FR",
    "sg:address":"2 rue des Terres Fortes 77600 Chanteloup en Brie",
    "sg:classifiers":[
        {
            "category":"Wholesale",
            "subcategory":"Vending Machines",
            "type":"Manufacturing & Wholesale Goods"
        }
    ],
    "sg:phone":"+33 1 60 31 55 55",
    "sg:province":"Ile de France",
    "sg:tags":[
        "packaging",
        "machines",
        "robotic"
    ],
    "wof:name":"Stoppil Sa",
    "wof:placetype":"venue"
},
  "geometry": {"coordinates":[2.740507,48.853081],"type":"Point"}
}