{
  "type": "Feature",
  "properties": {
    "addr:full":"151, Av. du Maine, 75014 Paris Ile de France",
    "addr:postcode":"75014",
    "addr:street":"151 Av. Du Maine",
    "iso:country":"FR",
    "sg:address":"151, Av. du Maine, 75014 Paris",
    "sg:orig_category":"Unclassifiable Establishments",
    "sg:phone":"+33 1 40 52 81 81",
    "sg:province":"Ile de France",
    "wof:name":"I. Guzzini Illuminazione France S.a.",
    "wof:placetype":"venue"
},
  "geometry": {"coordinates":[2.324649,48.833839],"type":"Point"}
}