{
  "type": "Feature",
  "properties": {
    "iso:country":"FR",
    "sg:address":"30 Route De Montlhery 91400 Orsay",
    "sg:classifiers":[
        {
            "category":"Shopping",
            "subcategory":"Computers & Home Electronics",
            "type":"Retail Goods"
        }
    ],
    "sg:phone":"+33 1 69 07 84 18",
    "sg:postcode":"91400",
    "sg:province":"Ile de France",
    "sg:tags":[
        "electronic",
        "electrical",
        "equipment"
    ],
    "wof:name":"Sca Habitat",
    "wof:placetype":"venue"
},
  "geometry": {"coordinates":[2.181339,48.689156],"type":"Point"}
}