{
  "type": "Feature",
  "properties": {
    "addr:full":"116, Rue du Faubourg Saint Honor\u00e9, 75008 Paris Ile de France 75008",
    "addr:housenumber":"116",
    "addr:postcode":"75008;75008",
    "addr:street":"Rue Du Faubourg Saint Honore\u0301",
    "iso:country":"FR",
    "sg:address":"116, Rue du Faubourg Saint Honor\u00e9, 75008 Paris",
    "sg:orig_category":"Non-Classified Establishments",
    "sg:phone":"+33 1 42 66 65 27",
    "sg:postcode":"75008",
    "sg:province":"Ile de France",
    "wof:name":"Banco Popular Comercial S.a.",
    "wof:placetype":"venue"
},
  "geometry": {"coordinates":[2.314436,48.871807],"type":"Point"}
}