{
  "type": "Feature",
  "properties": {
    "addr:full":"3, Av. de la Concorde, 78500 Sartrouville Ile de France",
    "addr:postcode":"78500;ile",
    "addr:street":"Av. De La Concorde",
    "iso:country":"FR",
    "sg:address":"3, Av. de la Concorde, 78500 Sartrouville",
    "sg:orig_category":"Non-Classified Establishments",
    "sg:phone":"+33 1 39 57 98 94",
    "sg:province":"Ile de France",
    "wof:name":"Technofluor S.a.r.l.",
    "wof:placetype":"venue"
},
  "geometry": {"coordinates":[2.155351,48.937969],"type":"Point"}
}