{
  "type": "Feature",
  "properties": {
    "iso:country":"FR",
    "sg:address":"59, Av. de Laon, 51100 Reims",
    "sg:orig_category":"Unclassifiable Establishments",
    "sg:phone":"+33 3 26 47 41 11",
    "sg:province":"Champagne",
    "wof:name":"Le Cheval Blanc",
    "wof:placetype":"venue"
},
  "geometry": {"coordinates":[4.026738,49.264561],"type":"Point"}
}