{
  "type": "Feature",
  "properties": {
    "addr:full":"6 Avenue Edouard Millaud 69290 Craponne Rhone-Alpes 69290",
    "addr:housenumber":"6",
    "addr:postcode":"69290;69290",
    "addr:street":"Avenue Edouard Millaud",
    "iso:country":"FR",
    "sg:address":"6 Avenue Edouard Millaud 69290 Craponne",
    "sg:classifiers":[
        {
            "category":"Home & Garden",
            "subcategory":"Furniture",
            "type":"Retail Goods"
        }
    ],
    "sg:phone":"+33 4 78 57 04 02",
    "sg:postcode":"69290",
    "sg:province":"Rhone-Alpes",
    "sg:tags":[
        "household",
        "wood"
    ],
    "wof:name":"Etablissements Reymondon",
    "wof:placetype":"venue"
},
  "geometry": {"coordinates":[4.745428,45.747543],"type":"Point"}
}