{
  "type": "Feature",
  "properties": {
    "addr:full":"B.P. 102, 76210 Bolbec^^50, Rue Georges Lema\u00eetre, 76210 Bolbec Haute Normandie 76210",
    "addr:housenumber":"b.p. 102",
    "addr:postcode":"76210;76210;76210",
    "addr:street":"Rue Georges Lemai\u0302Tre;Haute Normandie",
    "iso:country":"FR",
    "sg:address":"B.P. 102, 76210 Bolbec^^50, Rue Georges Lema\u00eetre, 76210 Bolbec",
    "sg:orig_category":"Non-Classified Establishments",
    "sg:phone":"+33 2 35 31 00 03",
    "sg:postcode":"76210",
    "sg:province":"Haute Normandie",
    "wof:name":"Aci\u00e9ries Et Fonderies Du Val Ricard S.a.",
    "wof:placetype":"venue"
},
  "geometry": {"coordinates":[0.451852,49.553249],"type":"Point"}
}