{
  "type": "Feature",
  "properties": {
    "addr:full":"Zi Du Cerisier Noir 86530 Naintr\u00e9 Poitou-Charentes",
    "addr:postcode":"86530",
    "addr:street":"Zi Du Cerisier Noir",
    "iso:country":"FR",
    "sg:address":"Zi Du Cerisier Noir 86530 Naintr\u00e9",
    "sg:classifiers":[
        {
            "category":"Home & Garden",
            "subcategory":"Furniture",
            "type":"Retail Goods"
        }
    ],
    "sg:phone":"+33 5 49 19 11 29",
    "sg:province":"Poitou-Charentes",
    "sg:tags":[
        "wood"
    ],
    "wof:name":"Bureau Central De Securite Ouest (bcso)",
    "wof:placetype":"venue"
},
  "geometry": {"coordinates":[0.48177,46.758995],"type":"Point"}
}