{
  "type": "Feature",
  "properties": {
    "addr:full":"28, Av. de Broglie - ZA Valnor, 95500 Le Thillay Ile de France",
    "addr:postcode":"95500",
    "addr:street":"28 Av. De Broglie Za Valnor",
    "iso:country":"FR",
    "sg:address":"28, Av. de Broglie - ZA Valnor, 95500 Le Thillay",
    "sg:orig_category":"Unclassifiable Establishments",
    "sg:phone":"+33 1 30 18 15 15",
    "sg:province":"Ile de France",
    "wof:name":"Soci\u00e9t\u00e9 Fran\u00e7aise De Fixation S.a.",
    "wof:placetype":"venue"
},
  "geometry": {"coordinates":[2.449633,48.986462],"type":"Point"}
}