{
  "type": "Feature",
  "properties": {
    "iso:country":"FR",
    "sg:address":"140, Rue du 8 Mai 1945, 80270 Allery",
    "sg:orig_category":"Non-Classified Establishments",
    "sg:phone":"+33 3 22 29 38 22",
    "sg:province":"Picardie",
    "wof:name":"M.p.n. S.a. - Moulages Plastiques Du Nord",
    "wof:placetype":"venue"
},
  "geometry": {"coordinates":[1.942868,49.965263],"type":"Point"}
}