{
  "type": "Feature",
  "properties": {
    "iso:country":"FR",
    "sg:address":"5, Rue de la Mairie - La Poitevini\u00e8re , 85150 Sainte Flaive des Loups",
    "sg:orig_category":"Non-Classified Establishments",
    "sg:phone":"+33 2 51 46 67 67",
    "sg:province":"Pays de Loire",
    "wof:name":"Pajot Espaces Verts S.a.r.l.",
    "wof:placetype":"venue"
},
  "geometry": {"coordinates":[-1.691519,46.513008],"type":"Point"}
}