{
  "type": "Feature",
  "properties": {
    "iso:country":"FR",
    "sg:address":"16, Rue du Tour de l'Eau - ZI Champ Roman, 38400 Saint Martin d'H\u00e8res",
    "sg:orig_category":"Unclassifiable Establishments",
    "sg:phone":"+33 4 76 51 72 02",
    "sg:postcode":"38400",
    "sg:province":"Rhone-Alpes",
    "wof:name":"C.e.t.i.m. - Centre Technique Des Industries M\u00e9caniques",
    "wof:placetype":"venue"
},
  "geometry": {"coordinates":[5.775027,45.184116],"type":"Point"}
}