{
  "type": "Feature",
  "properties": {
    "iso:country":"FR",
    "sg:address":"188 Avenue Ferdinand Janvier Pepiniere Grosberty 07100 Annonay",
    "sg:classifiers":[
        {
            "category":"Wholesale",
            "subcategory":"Medical Equipment & Supplies",
            "type":"Manufacturing & Wholesale Goods"
        }
    ],
    "sg:phone":"+33 4 75 67 66 89",
    "sg:postcode":"07100",
    "sg:province":"Rhone-Alpes",
    "sg:tags":[
        "instrument",
        "health",
        "-",
        "precision"
    ],
    "wof:name":"Alaboratoire De Prothese Dentaire Martinez Carpentier",
    "wof:placetype":"venue"
},
  "geometry": {"coordinates":[4.661749,45.265881],"type":"Point"}
}