{
  "type": "Feature",
  "properties": {
    "addr:full":"280, Rue Henry Bessemer, 60100 Creil Picardie",
    "addr:housenumber":"280",
    "addr:postcode":"60100",
    "addr:street":"Rue Henry Bessemer",
    "iso:country":"FR",
    "sg:address":"280, Rue Henry Bessemer, 60100 Creil",
    "sg:orig_category":"Unclassifiable Establishments",
    "sg:phone":"+33 3 44 64 13 95",
    "sg:province":"Picardie",
    "wof:name":"I.s.l. S.a.r.l. - Imprimerie De Saint Leu",
    "wof:placetype":"venue"
},
  "geometry": {"coordinates":[2.46368,49.240849],"type":"Point"}
}