{
  "type": "Feature",
  "properties": {
    "addr:full":"Rue Artisanat - ZI Plaisance Narbonne Languedoc-Roussillon 11000",
    "addr:postcode":"11000",
    "addr:street":"Rue Artisanat Zi",
    "iso:country":"FR",
    "sg:address":"Rue Artisanat - ZI Plaisance",
    "sg:city":"Narbonne",
    "sg:orig_category":"Non-Classified Establishments",
    "sg:phone":"+33 4 68 41 59 30",
    "sg:postcode":"11000",
    "sg:province":"Languedoc-Roussillon",
    "wof:name":"J.p. Aiguille S.a.",
    "wof:placetype":"venue"
},
  "geometry": {"coordinates":[3.00432,43.188351],"type":"Point"}
}