{
  "type": "Feature",
  "properties": {
    "addr:full":"8, Rue Louis David, 93170 Bagnolet Ile de France",
    "addr:housenumber":"8",
    "addr:postcode":"93170;ile",
    "addr:street":"Rue Louis David",
    "iso:country":"FR",
    "sg:address":"8, Rue Louis David, 93170 Bagnolet",
    "sg:orig_category":"Non-Classified Establishments",
    "sg:phone":"+33 1 48 97 43 90",
    "sg:province":"Ile de France",
    "wof:name":"Sieva S.a.",
    "wof:placetype":"venue"
},
  "geometry": {"coordinates":[2.414307,48.872581],"type":"Point"}
}