{
  "type": "Feature",
  "properties": {
    "iso:country":"FR",
    "sg:address":"19-21 rue de Bretagne 95310 St Ouen L'Aumone",
    "sg:classifiers":[
        {
            "category":"Building & Trades",
            "subcategory":"Construction",
            "type":"Services"
        }
    ],
    "sg:phone":"+33 1 34 40 39 00",
    "sg:postcode":"95310",
    "sg:province":"Ile de France",
    "sg:tags":[
        "central",
        "heating",
        "system"
    ],
    "wof:name":"Roca Sarl",
    "wof:placetype":"venue"
},
  "geometry": {"coordinates":[2.143651,49.044979],"type":"Point"}
}