{
  "type": "Feature",
  "properties": {
    "iso:country":"FR",
    "sg:address":"7, Rue du Tertre de la Motte, 41100 Vend\u00f4me",
    "sg:city":"Vend\u00f4me",
    "sg:orig_category":"Non-Classified Establishments",
    "sg:phone":"+33 2 54 77 04 01",
    "sg:postcode":"41100",
    "sg:province":"Centre",
    "wof:name":"Gilles Mercey Ing\u00e9nierie S.a.r.l.",
    "wof:placetype":"venue"
},
  "geometry": {"coordinates":[1.061531,47.789692],"type":"Point"}
}