{
  "type": "Feature",
  "properties": {
    "addr:full":"ZI Ath\u00e9lia III La Ciotat C\u00e9dex Corse 13705",
    "addr:postcode":"13705",
    "iso:country":"FR",
    "sg:address":"ZI Ath\u00e9lia III",
    "sg:city":"La Ciotat C\u00e9dex",
    "sg:orig_category":"Non-Classified Establishments",
    "sg:phone":"+33 4 42 71 64 67",
    "sg:postcode":"13705",
    "sg:province":"Corse",
    "wof:name":"Formaglass S.a.r.l.",
    "wof:placetype":"venue"
},
  "geometry": {"coordinates":[5.596601,43.17804],"type":"Point"}
}