{
  "type": "Feature",
  "properties": {
    "iso:country":"FR",
    "sg:address":"320, Rue du Mont des Cats, 59270 Godewaersvelde",
    "sg:orig_category":"Unclassifiable Establishments",
    "sg:phone":"+33 3 28 42 59 98",
    "sg:province":"Nord Pas-de-Calais",
    "wof:name":"Markus Technology S.a.r.l.",
    "wof:placetype":"venue"
},
  "geometry": {"coordinates":[2.645413,50.790592],"type":"Point"}
}