{
  "type": "Feature",
  "properties": {
    "addr:full":"11, Rue Sidonie Appolinaire, 69009 Lyon Rhone-Alpes 69009",
    "addr:housenumber":"11",
    "addr:postcode":"69009;69009",
    "addr:street":"Rue Sidonie Appolinaire",
    "iso:country":"FR",
    "sg:address":"11, Rue Sidonie Appolinaire, 69009 Lyon",
    "sg:orig_category":"Unclassifiable Establishments",
    "sg:phone":"+33 4 78 47 11 11",
    "sg:postcode":"69009",
    "sg:province":"Rhone-Alpes",
    "wof:name":"Sovelor S.a.r.l.",
    "wof:placetype":"venue"
},
  "geometry": {"coordinates":[4.805335,45.774105],"type":"Point"}
}