{
  "type": "Feature",
  "properties": {
    "iso:country":"FR",
    "sg:address":"2 RUE DE LA BOISSIERE 78310 COIGNIERES",
    "sg:orig_category":"Polyurethane Sealing Compounds For Aircraft Construction",
    "sg:phone":"+33 1 30 69 30 00",
    "sg:province":"Ile de France",
    "wof:name":"Perkinelmer Sas",
    "wof:placetype":"venue"
},
  "geometry": {"coordinates":[1.916526,48.748924],"type":"Point"}
}