{
  "type": "Feature",
  "properties": {
    "addr:full":"85 Avenue De Neuilly 94120 Fontenay Sous Bois Ile de France 94120",
    "addr:housenumber":"85",
    "addr:postcode":"94120;94120",
    "addr:street":"Avenue De Neuilly;Bois Ile De France",
    "iso:country":"FR",
    "sg:address":"85 Avenue De Neuilly 94120 Fontenay Sous Bois",
    "sg:classifiers":[
        {
            "category":"Shopping",
            "type":"Retail Goods"
        }
    ],
    "sg:phone":"+33 1 45 14 01 10",
    "sg:postcode":"94120",
    "sg:province":"Ile de France",
    "sg:tags":[
        "metallurgy",
        "finished",
        "-",
        "metalworking",
        "metallic"
    ],
    "wof:name":"Societe Eliot Et Compagnie",
    "wof:placetype":"venue"
},
  "geometry": {"coordinates":[2.489953,48.848133],"type":"Point"}
}