{
  "type": "Feature",
  "properties": {
    "iso:country":"FR",
    "sg:address":"6 Rue La Verrerie 49123 Ingrandes Sur Loire",
    "sg:classifiers":[
        {
            "category":"Food Court",
            "type":"Food & Drink"
        }
    ],
    "sg:phone":"+33 2 41 39 40 44",
    "sg:postcode":"49123",
    "sg:province":"Pays de Loire",
    "sg:tags":[
        "product",
        "related"
    ],
    "wof:name":"Caves De La Bouvraie",
    "wof:placetype":"venue"
},
  "geometry": {"coordinates":[-0.92247,47.404781],"type":"Point"}
}