{
  "type": "Feature",
  "properties": {
    "iso:country":"FR",
    "sg:address":"Le Double Six 72370 Soulitre",
    "sg:classifiers":[
        {
            "category":"Farming",
            "subcategory":"Livestock Farm",
            "type":"Manufacturing & Wholesale Goods"
        }
    ],
    "sg:phone":"+33 2 43 54 17 17",
    "sg:postcode":"72370",
    "sg:province":"Pays de Loire",
    "sg:tags":[
        "breeding",
        "agriculture",
        "animal"
    ],
    "wof:name":"Selection Avicole Du Sud Ouest (saso)",
    "wof:placetype":"venue"
},
  "geometry": {"coordinates":[0.414445,48.035091],"type":"Point"}
}