{
  "type": "Feature",
  "properties": {
    "iso:country":"FR",
    "sg:address":"29, Rue des Echarmeaux, 69430 Beaujeu",
    "sg:orig_category":"Non-Classified Establishments",
    "sg:phone":"+33 4 74 69 28 06",
    "sg:province":"Rhone-Alpes",
    "wof:name":"Huilerie Beaujolaise S.a.r.l.",
    "wof:placetype":"venue"
},
  "geometry": {"coordinates":[4.583447,46.157345],"type":"Point"}
}