{
  "type": "Feature",
  "properties": {
    "iso:country":"FR",
    "sg:address":"Rte De Turckheim 68040 Ingersheim",
    "sg:city":"Ingersheim",
    "sg:classifiers":[
        {
            "category":"Professional",
            "subcategory":"Business Services",
            "type":"Services"
        }
    ],
    "sg:phone":"+33 3 89 27 92 40",
    "sg:postcode":"68040",
    "sg:province":"Alsace",
    "sg:tags":[
        "training",
        "advice"
    ],
    "wof:name":"Lycee Polyvalent Lazare De Schwendi",
    "wof:placetype":"venue"
},
  "geometry": {"coordinates":[7.299877,48.092594],"type":"Point"}
}