{
  "type": "Feature",
  "properties": {
    "addr:full":"9 Rue Lepine Zone Activites Parc Lann 56000 Vannes Vannes Bretagne 56000",
    "addr:housenumber":"9",
    "addr:postcode":"56000;56000",
    "addr:street":"Rue Lepine;Activites Parc Lann",
    "iso:country":"FR",
    "sg:address":"9 Rue Lepine Zone Activites Parc Lann 56000 Vannes",
    "sg:city":"Vannes",
    "sg:classifiers":[
        {
            "category":"Utilities",
            "subcategory":"Telephone",
            "type":"Services"
        }
    ],
    "sg:phone":"+33 2 97 40 38 35",
    "sg:postcode":"56000",
    "sg:province":"Bretagne",
    "sg:tags":[
        "telecommunication"
    ],
    "wof:name":"Espace Entreprise",
    "wof:placetype":"venue"
},
  "geometry": {"coordinates":[-2.759959,47.658169],"type":"Point"}
}