{
  "type": "Feature",
  "properties": {
    "iso:country":"FR",
    "sg:address":"7, Rue de la M\u00e9tallurgie - ZI, 44477 Carquefou C\u00e9dex",
    "sg:city":"Carquefou",
    "sg:orig_category":"Non-Classified Establishments",
    "sg:phone":"+33 2 51 85 27 00",
    "sg:postcode":"44470",
    "sg:province":"Pays de Loire",
    "wof:name":"Dubois International",
    "wof:placetype":"venue"
},
  "geometry": {"coordinates":[-1.492114,47.297066],"type":"Point"}
}