{
  "type": "Feature",
  "properties": {
    "addr:full":"B.P. 1103, 64011 Pau C\u00e9dex^^84, Av. des Lilas, 64000 Pau Pau Aquitaine 64000",
    "addr:postcode":"64011;64000;64000",
    "addr:street":"B.P. 1103;Av. Des Lilas",
    "iso:country":"FR",
    "sg:address":"B.P. 1103, 64011 Pau C\u00e9dex^^84, Av. des Lilas, 64000 Pau",
    "sg:city":"Pau",
    "sg:orig_category":"Non-Classified Establishments",
    "sg:phone":"+33 5 59 02 66 37",
    "sg:postcode":"64000",
    "sg:province":"Aquitaine",
    "wof:name":"Com\u00e9to S.a.r.l.",
    "wof:placetype":"venue"
},
  "geometry": {"coordinates":[-0.374294,43.296558],"type":"Point"}
}