{
  "type": "Feature",
  "properties": {
    "addr:full":"Chemin des Sondes Montmorot Franche Comt\u00e9 39570",
    "addr:postcode":"39570",
    "addr:street":"Chemin Des Sondes;Franche Comte\u0301",
    "iso:country":"FR",
    "sg:address":"Chemin des Sondes",
    "sg:city":"Montmorot",
    "sg:orig_category":"Non-Classified Establishments",
    "sg:phone":"+33 3 84 87 15 15",
    "sg:postcode":"39570",
    "sg:province":"Franche Comt\u00e9",
    "wof:name":"C.c.e. -comptoir Commercial Electricit\u00e9 S.a.",
    "wof:placetype":"venue"
},
  "geometry": {"coordinates":[5.533812,46.674938],"type":"Point"}
}