{
  "type": "Feature",
  "properties": {
    "iso:country":"FR",
    "sg:address":"18 rue Galibert Pons 81201 MAZAMET CEDEX",
    "sg:classifiers":[
        {
            "category":"Transit Center",
            "subcategory":"Freight",
            "type":"Transportation"
        }
    ],
    "sg:phone":"+33 5 63 61 01 07",
    "sg:province":"Auvergne",
    "sg:tags":[
        "leather",
        "sole",
        "bottom"
    ],
    "wof:name":"Hirimex Sarl",
    "wof:placetype":"venue"
},
  "geometry": {"coordinates":[2.379232,43.498081],"type":"Point"}
}