{
  "type": "Feature",
  "properties": {
    "addr:full":"270 rue des Pommiers 50110 Tourlaville Tourlaville Basse Normandie 50110",
    "addr:housenumber":"270",
    "addr:postcode":"50110;50110",
    "addr:street":"Rue Des Pommiers",
    "iso:country":"FR",
    "sg:address":"270 rue des Pommiers 50110 Tourlaville",
    "sg:city":"Tourlaville",
    "sg:classifiers":[
        {
            "category":"Wholesale",
            "subcategory":"Machinery & Supplies",
            "type":"Manufacturing & Wholesale Goods"
        }
    ],
    "sg:phone":"+33 2 33 44 17 80",
    "sg:postcode":"50110",
    "sg:province":"Basse Normandie",
    "sg:tags":[
        "industry",
        "workshop"
    ],
    "wof:name":"Porquet S.a.",
    "wof:placetype":"venue"
},
  "geometry": {"coordinates":[-1.582855,49.633614],"type":"Point"}
}