{
  "type": "Feature",
  "properties": {
    "iso:country":"FR",
    "sg:address":"14 All Mouesca 64600 Anglet",
    "sg:city":"Anglet",
    "sg:classifiers":[
        {
            "category":"Utilities",
            "subcategory":"Electric",
            "type":"Services"
        }
    ],
    "sg:phone":"+33 5 59 63 96 95",
    "sg:postcode":"64600",
    "sg:province":"Aquitaine",
    "sg:tags":[
        "electricity",
        "electronic",
        "electrical",
        "equipment"
    ],
    "wof:name":"Societe D'applications Et D'utilisations Generales",
    "wof:placetype":"venue"
},
  "geometry": {"coordinates":[-1.499433,43.519539],"type":"Point"}
}