{
  "type": "Feature",
  "properties": {
    "addr:full":"20bis, Rue du G\u00e9n\u00e9ral Pershing, 54400 Longwy Lorraine",
    "addr:housenumber":"20bis",
    "addr:postcode":"54400",
    "addr:street":"Rue Du Ge\u0301Ne\u0301Ral Pershing",
    "iso:country":"FR",
    "sg:address":"20bis, Rue du G\u00e9n\u00e9ral Pershing, 54400 Longwy",
    "sg:orig_category":"Unclassifiable Establishments",
    "sg:phone":"+33 3 82 24 30 02",
    "sg:province":"Lorraine",
    "wof:name":"K - Info S.a.r.l.",
    "wof:placetype":"venue"
},
  "geometry": {"coordinates":[5.766416,49.514805],"type":"Point"}
}