{
  "type": "Feature",
  "properties": {
    "addr:full":"16, Rue Saint Denis, 92513 Boulogne Billancourt C\u00e9dex Ancourt Haute Normandie 76370",
    "addr:housenumber":"16",
    "addr:postcode":"92513;76370",
    "addr:street":"Rue Saint Denis;Haute Normandie",
    "iso:country":"FR",
    "sg:address":"16, Rue Saint Denis, 92513 Boulogne Billancourt C\u00e9dex",
    "sg:city":"Ancourt",
    "sg:orig_category":"Non-Classified Establishments",
    "sg:phone":"+33 1 41 86 20 00",
    "sg:postcode":"76370",
    "sg:province":"Haute Normandie",
    "wof:name":"Groupe Promodip S.a.",
    "wof:placetype":"venue"
},
  "geometry": {"coordinates":[2.231619,48.843975],"type":"Point"}
}