{
  "type": "Feature",
  "properties": {
    "addr:full":"1 Rue Du Rhone 26140 ST RAMBERT D ALBON Rhone-Alpes",
    "addr:housenumber":"1",
    "addr:postcode":"26140",
    "addr:street":"Rue Du Rhone",
    "iso:country":"FR",
    "sg:address":"1 Rue Du Rhone 26140 ST RAMBERT D ALBON",
    "sg:classifiers":[
        {
            "category":"Bars & Pubs",
            "subcategory":"Biergarten",
            "type":"Food & Drink"
        }
    ],
    "sg:phone":"+33 4 75 31 07 07",
    "sg:province":"Rhone-Alpes",
    "sg:tags":[
        "cover",
        "swimming-pool"
    ],
    "wof:name":"Albon Plastiques Sa",
    "wof:placetype":"venue"
},
  "geometry": {"coordinates":[4.812505,45.293709],"type":"Point"}
}