{
  "type": "Feature",
  "properties": {
    "iso:country":"FR",
    "sg:address":"24, All\u00e9e des Grands Paquis - ZI Heillecourt Est, 54180 Heillecourt",
    "sg:orig_category":"Non-Classified Establishments",
    "sg:phone":"+33 3 83 53 32 33",
    "sg:postcode":"54180",
    "sg:province":"Lorraine",
    "wof:name":"Etablissements M\u00e9on Charles S.a.",
    "wof:placetype":"venue"
},
  "geometry": {"coordinates":[6.194192,48.653137],"type":"Point"}
}