{
  "type": "Feature",
  "properties": {
    "addr:full":"1 Boulevard Charles De Gaulle Residence La Pepiniere 15200 Mauriac Mauriac Auvergne 15200",
    "addr:housenumber":"1",
    "addr:postcode":"15200;15200",
    "addr:street":"Boulevard Charles De Gaulle;La Pepiniere",
    "iso:country":"FR",
    "sg:address":"1 Boulevard Charles De Gaulle Residence La Pepiniere 15200 Mauriac",
    "sg:city":"Mauriac",
    "sg:classifiers":[
        {
            "category":"Professional",
            "subcategory":"Printing & Photocopies",
            "type":"Services"
        }
    ],
    "sg:phone":"+33 4 71 68 00 33",
    "sg:postcode":"15200",
    "sg:province":"Auvergne",
    "sg:tags":[
        "publishing"
    ],
    "wof:name":"Le Reveil De Mauriac",
    "wof:placetype":"venue"
},
  "geometry": {"coordinates":[2.326109,45.222088],"type":"Point"}
}