{
  "type": "Feature",
  "properties": {
    "addr:full":"57, Rue des Ayres, 33000 Bordeaux Bordeaux Aquitaine 33000",
    "addr:housenumber":"57",
    "addr:postcode":"33000;33000",
    "addr:street":"Rue Des Ayres",
    "iso:country":"FR",
    "sg:address":"57, Rue des Ayres, 33000 Bordeaux",
    "sg:city":"Bordeaux",
    "sg:orig_category":"Non-Classified Establishments",
    "sg:phone":"+33 5 56 52 11 09",
    "sg:postcode":"33000",
    "sg:province":"Aquitaine",
    "wof:name":"Alter Eco S.a.r.l.",
    "wof:placetype":"venue"
},
  "geometry": {"coordinates":[-0.57433,44.836967],"type":"Point"}
}