{
  "type": "Feature",
  "properties": {
    "iso:country":"FR",
    "sg:address":"16 Av Paul Santy BP 8211 69008 Lyon",
    "sg:classifiers":[
        {
            "category":"Manufacturing",
            "subcategory":"Metals",
            "type":"Manufacturing & Wholesale Goods"
        }
    ],
    "sg:phone":"+33 4 78 78 16 00",
    "sg:postcode":"69008",
    "sg:province":"Rhone-Alpes",
    "sg:tags":[
        "metallurgy",
        "steel",
        "metalworking"
    ],
    "wof:name":"Comap Sa",
    "wof:placetype":"venue"
},
  "geometry": {"coordinates":[4.875354,45.729404],"type":"Point"}
}