{
  "type": "Feature",
  "properties": {
    "iso:country":"FR",
    "sg:address":"49, Rue des Fr\u00e8res Lumi\u00e8re - ZI des Chanoux, 93330 Neuilly sur Marne",
    "sg:orig_category":"Unclassifiable Establishments",
    "sg:phone":"+33 1 43 09 88 88",
    "sg:province":"Ile de France",
    "wof:name":"Imprimerie Dride S.a.",
    "wof:placetype":"venue"
},
  "geometry": {"coordinates":[2.52871,48.857376],"type":"Point"}
}