{
  "type": "Feature",
  "properties": {
    "iso:country":"FR",
    "sg:address":"13, Av. Paul H\u00e9roult - ZI de la Delorme, 13015 Marseille",
    "sg:orig_category":"Unclassifiable Establishments",
    "sg:phone":"+33 4 91 03 21 50",
    "sg:province":"Provence-Alpes-C\u00f4te d'Azur",
    "wof:name":"R.j. International S.a.",
    "wof:placetype":"venue"
},
  "geometry": {"coordinates":[5.37278,43.344948],"type":"Point"}
}