{
  "type": "Feature",
  "properties": {
    "iso:country":"FR",
    "sg:address":"8 Rue Du Gresmont 60590 FLAVACOURT",
    "sg:classifiers":[
        {
            "category":"Professional",
            "subcategory":"Business Services",
            "type":"Services"
        }
    ],
    "sg:phone":"+33 3 44 84 83 56",
    "sg:postcode":"60590",
    "sg:province":"Picardie",
    "sg:tags":[
        "data"
    ],
    "wof:name":"Realisations Francaises En Imagerie Sa",
    "wof:placetype":"venue"
},
  "geometry": {"coordinates":[1.821179,49.33453],"type":"Point"}
}