{
  "type": "Feature",
  "properties": {
    "iso:country":"FR",
    "sg:address":"Chemin De Baconnes 51400 Mourmelon Le Petit",
    "sg:classifiers":[
        {
            "category":"Manufacturing",
            "subcategory":"Rubber & Plastics",
            "type":"Manufacturing & Wholesale Goods"
        }
    ],
    "sg:phone":"+33 3 26 66 15 79",
    "sg:province":"Champagne",
    "wof:name":"Dub Plastiques Sa",
    "wof:placetype":"venue"
},
  "geometry": {"coordinates":[4.32003,49.142021],"type":"Point"}
}