{
  "type": "Feature",
  "properties": {
    "addr:full":"Rue Du Nouveau Monde Zone Industrielle 80240 Roisel Picardie 80240",
    "addr:postcode":"80240;80240",
    "addr:street":"Rue Du Nouveau Monde Zone Industrielle;Picardie",
    "iso:country":"FR",
    "sg:address":"Rue Du Nouveau Monde Zone Industrielle 80240 Roisel",
    "sg:classifiers":[
        {
            "category":"Food & Beverages",
            "subcategory":"Groceries & Convenience Stores",
            "type":"Retail Goods"
        }
    ],
    "sg:phone":"+33 3 22 86 42 00",
    "sg:postcode":"80240",
    "sg:province":"Picardie",
    "sg:tags":[
        "product",
        "related"
    ],
    "wof:name":"Conseil Realisation Etude En Agro Alimentaire",
    "wof:placetype":"venue"
},
  "geometry": {"coordinates":[3.1012,49.946064],"type":"Point"}
}