{
  "type": "Feature",
  "properties": {
    "addr:full":"B.P. 19, 69655 Villefranche sur Sa\u00f4ne C\u00e9dex^^411, Rue Camille Desmoulins, 69400 Villefranche sur Sa\u00f4 Rhone-Alpes 69400",
    "addr:postcode":"69655;69400;69400",
    "addr:street":"B.P. 19;Rue Camille Desmoulins;Rhone-Alpes",
    "iso:country":"FR",
    "sg:address":"B.P. 19, 69655 Villefranche sur Sa\u00f4ne C\u00e9dex^^411, Rue Camille Desmoulins, 69400 Villefranche sur Sa\u00f4",
    "sg:orig_category":"Non-Classified Establishments",
    "sg:phone":"+33 4 74 68 21 68",
    "sg:postcode":"69400",
    "sg:province":"Rhone-Alpes",
    "wof:name":"Imprimerie Caladoise S.a.r.l.",
    "wof:placetype":"venue"
},
  "geometry": {"coordinates":[4.64756,45.957378],"type":"Point"}
}