{
  "type": "Feature",
  "properties": {
    "iso:country":"FR",
    "sg:address":"Zi De Grangeneuve 26800 Portes Les Valence",
    "sg:classifiers":[
        {
            "category":"Autos & Motor Vehicles",
            "subcategory":"Automobile Sales",
            "type":"Retail Goods"
        }
    ],
    "sg:phone":"+33 4 75 57 87 40",
    "sg:postcode":"26800",
    "sg:province":"Rhone-Alpes",
    "sg:tags":[
        "equipment",
        "motor-cars",
        "transport"
    ],
    "wof:name":"Residences Trigano",
    "wof:placetype":"venue"
},
  "geometry": {"coordinates":[4.87721,44.876316],"type":"Point"}
}