{
  "type": "Feature",
  "properties": {
    "addr:full":"Rue Marcelin Berthelot - Parc d'Activit\u00e9s du Moulin Neuf - Immeuble Atlantique Saint Herblain Pays de Loire 44800",
    "addr:postcode":"44800",
    "addr:street":"Rue Marcelin Berthelot;Moulin Neuf;Herblain",
    "iso:country":"FR",
    "sg:address":"Rue Marcelin Berthelot - Parc d'Activit\u00e9s du Moulin Neuf - Immeuble Atlantique",
    "sg:city":"Saint Herblain",
    "sg:orig_category":"Non-Classified Establishments",
    "sg:phone":"+33 2 40 95 75 75",
    "sg:postcode":"44800",
    "sg:province":"Pays de Loire",
    "wof:name":"Cegid S.a.",
    "wof:placetype":"venue"
},
  "geometry": {"coordinates":[-1.606719,47.223927],"type":"Point"}
}