{
  "type": "Feature",
  "properties": {
    "addr:full":"27, Rue du Hameau, 25660 Sa\u00f4ne Franche Comt\u00e9",
    "addr:housenumber":"27",
    "addr:postcode":"25660",
    "addr:street":"Rue Du Hameau;Franche Comte\u0301",
    "iso:country":"FR",
    "sg:address":"27, Rue du Hameau, 25660 Sa\u00f4ne",
    "sg:orig_category":"Unclassifiable Establishments",
    "sg:phone":"+33 3 81 55 79 51",
    "sg:province":"Franche Comt\u00e9",
    "wof:name":"I.g.m. S.a.r.l. - Informatique De Gestion Multipostes",
    "wof:placetype":"venue"
},
  "geometry": {"coordinates":[6.122391,47.227245],"type":"Point"}
}