{
  "type": "Feature",
  "properties": {
    "addr:full":"Route De Saint Girons 09160 PRAT BONREPAUX Midi Pyr\u00e9n\u00e9es 09160",
    "addr:postcode":"09160;09160",
    "addr:street":"Route De Saint Girons",
    "iso:country":"FR",
    "sg:address":"Route De Saint Girons 09160 PRAT BONREPAUX",
    "sg:classifiers":[
        {
            "category":"Manufacturing",
            "subcategory":"Wood Products",
            "type":"Manufacturing & Wholesale Goods"
        }
    ],
    "sg:phone":"+33 5 61 04 00 50",
    "sg:postcode":"09160",
    "sg:province":"Midi Pyr\u00e9n\u00e9es",
    "sg:tags":[
        "lumber"
    ],
    "wof:name":"Sarl Ortet Et Fils",
    "wof:placetype":"venue"
},
  "geometry": {"coordinates":[1.046034,43.034393],"type":"Point"}
}