{
  "type": "Feature",
  "properties": {
    "addr:full":"64, Rue Gohier, 88300 Neufch\u00e2teau Lorraine",
    "addr:housenumber":"64",
    "addr:postcode":"88300",
    "addr:street":"Rue Gohier",
    "iso:country":"FR",
    "sg:address":"64, Rue Gohier, 88300 Neufch\u00e2teau",
    "sg:orig_category":"Unclassifiable Establishments",
    "sg:phone":"+33 3 29 06 12 38",
    "sg:province":"Lorraine",
    "wof:name":"Cr\u00e9ation Styles Contemporain E.u.r.l.",
    "wof:placetype":"venue"
},
  "geometry": {"coordinates":[5.69689,48.35199],"type":"Point"}
}