{
  "type": "Feature",
  "properties": {
    "addr:full":"ZI les Troques 69630 CHAPONOST Rhone-Alpes",
    "addr:postcode":"69630",
    "addr:street":"Zi Les Troques",
    "iso:country":"FR",
    "sg:address":"ZI les Troques 69630 CHAPONOST",
    "sg:orig_category":"Swaged Fittings For Industrial Uses",
    "sg:phone":"+33 4 78 56 22 88",
    "sg:province":"Rhone-Alpes",
    "wof:name":"Eurobinox Sa",
    "wof:placetype":"venue"
},
  "geometry": {"coordinates":[4.74319,45.710232],"type":"Point"}
}