{
  "type": "Feature",
  "properties": {
    "addr:full":"BP 118 43100 Brioude Brioude Auvergne 43100",
    "addr:housenumber":"118",
    "addr:postcode":"43100;brioude;43100",
    "iso:country":"FR",
    "sg:address":"BP 118 43100 Brioude",
    "sg:city":"Brioude",
    "sg:classifiers":[
        {
            "category":"Professional",
            "subcategory":"Business Services",
            "type":"Services"
        }
    ],
    "sg:phone":"+33 4 71 74 53 50",
    "sg:postcode":"43100",
    "sg:province":"Auvergne",
    "sg:tags":[
        "training",
        "advice"
    ],
    "wof:name":"Etablissement Regional Enseignement Adapte",
    "wof:placetype":"venue"
},
  "geometry": {"coordinates":[3.383711,45.29179],"type":"Point"}
}