{
  "type": "Feature",
  "properties": {
    "addr:full":"Zone de l'Ardoise Laudun Languedoc-Roussillon 30290",
    "addr:postcode":"30290",
    "addr:street":"De;Laudun",
    "iso:country":"FR",
    "sg:address":"Zone de l'Ardoise",
    "sg:city":"Laudun",
    "sg:orig_category":"Unclassifiable Establishments",
    "sg:phone":"+33 4 66 90 48 00",
    "sg:postcode":"30290",
    "sg:province":"Languedoc-Roussillon",
    "wof:name":"Ugine S.a.",
    "wof:placetype":"venue"
},
  "geometry": {"coordinates":[4.70088,44.097919],"type":"Point"}
}