{
  "type": "Feature",
  "properties": {
    "addr:full":"B.P. 53, 90101 Delle C\u00e9dex^^50bis, Rue du G\u00e9n\u00e9ral de Gaulle, 90100 Delle Franche Comt\u00e9",
    "addr:postcode":"90101;90100",
    "addr:street":"B.P. 53;Delle;Rue Du Ge\u0301Ne\u0301Ral De Gaulle;Franche Comte\u0301",
    "iso:country":"FR",
    "sg:address":"B.P. 53, 90101 Delle C\u00e9dex^^50bis, Rue du G\u00e9n\u00e9ral de Gaulle, 90100 Delle",
    "sg:orig_category":"Non-Classified Establishments",
    "sg:phone":"+33 3 84 36 21 55",
    "sg:province":"Franche Comt\u00e9",
    "wof:name":"Sofex S.a.",
    "wof:placetype":"venue"
},
  "geometry": {"coordinates":[7.00309,47.508034],"type":"Point"}
}