{
  "type": "Feature",
  "properties": {
    "iso:country":"FR",
    "sg:address":"10, Rue Lat\u00e9rale, 92051 Courbevoie C\u00e9dex",
    "sg:orig_category":"Unclassifiable Establishments",
    "sg:phone":"+33 1 41 16 31 58",
    "sg:province":"California",
    "wof:name":"S\u00e9curicor Valeurs S.a.",
    "wof:placetype":"venue"
},
  "geometry": {"coordinates":[-117.380547,33.19717],"type":"Point"}
}