{
  "type": "Feature",
  "properties": {
    "addr:full":"11, Bd du Fr\u00eane, 79200 Ch\u00e2tillon sur Thouet Poitou-Charentes",
    "addr:housenumber":"11",
    "addr:postcode":"79200;thouet",
    "addr:street":"Bd Du Fre\u0302Ne",
    "iso:country":"FR",
    "sg:address":"11, Bd du Fr\u00eane, 79200 Ch\u00e2tillon sur Thouet",
    "sg:orig_category":"Unclassifiable Establishments",
    "sg:phone":"+33 5 49 95 09 21",
    "sg:province":"Poitou-Charentes",
    "wof:name":"Morin",
    "wof:placetype":"venue"
},
  "geometry": {"coordinates":[-0.228731,46.668449],"type":"Point"}
}