{
  "type": "Feature",
  "properties": {
    "addr:full":"B.P. 69, 59820 Gravelines^^Rue des Dunes, 59820 Gravelines Nord Pas-de-Calais",
    "addr:postcode":"59820;59820",
    "addr:street":"B.P. 69;Des Dunes",
    "iso:country":"FR",
    "sg:address":"B.P. 69, 59820 Gravelines^^Rue des Dunes, 59820 Gravelines",
    "sg:orig_category":"Non-Classified Establishments",
    "sg:phone":"+33 3 28 51 82 00",
    "sg:province":"Nord Pas-de-Calais",
    "wof:name":"Tarlin Et Fils S.a.",
    "wof:placetype":"venue"
},
  "geometry": {"coordinates":[2.13518,50.990211],"type":"Point"}
}