{
  "type": "Feature",
  "properties": {
    "addr:full":"Rn 572 D'Arles 30800 Saint Gilles Languedoc-Roussillon",
    "addr:postcode":"30800",
    "addr:street":"Rn 572 D'Arles;Gilles",
    "iso:country":"FR",
    "sg:address":"Rn 572 D'Arles 30800 Saint Gilles",
    "sg:classifiers":[
        {
            "category":"Manufacturing",
            "subcategory":"Rubber & Plastics",
            "type":"Manufacturing & Wholesale Goods"
        }
    ],
    "sg:phone":"+33 4 66 58 34 00",
    "sg:province":"Languedoc-Roussillon",
    "wof:name":"Pipelife France",
    "wof:placetype":"venue"
},
  "geometry": {"coordinates":[4.438962,43.672005],"type":"Point"}
}