{
  "type": "Feature",
  "properties": {
    "addr:full":"9, Rue des R\u00e9servoirs, 68480 Oltingue Oltingue Alsace 68480",
    "addr:housenumber":"9",
    "addr:postcode":"68480;68480",
    "addr:street":"Rue Des Re\u0301Servoirs",
    "iso:country":"FR",
    "sg:address":"9, Rue des R\u00e9servoirs, 68480 Oltingue",
    "sg:city":"Oltingue",
    "sg:orig_category":"Non-Classified Establishments",
    "sg:phone":"+33 3 89 40 71 85",
    "sg:postcode":"68480",
    "sg:province":"Alsace",
    "wof:name":"Walbott Louis Mat\u00e9riaux De Construction S.a.r.l.",
    "wof:placetype":"venue"
},
  "geometry": {"coordinates":[7.397087,47.488594],"type":"Point"}
}