{
  "type": "Feature",
  "properties": {
    "iso:country":"FR",
    "sg:address":"248 Rue De Lyon 42540 ST JUST LA PENDUE",
    "sg:classifiers":[
        {
            "category":"Banks & Credit Unions",
            "subcategory":"Investment Brokerage",
            "type":"Services"
        }
    ],
    "sg:phone":"+33 4 77 63 21 14",
    "sg:postcode":"42540",
    "sg:province":"Rhone-Alpes",
    "sg:tags":[
        "curtain",
        "accessory"
    ],
    "wof:name":"Tissages Mondiere Sa",
    "wof:placetype":"venue"
},
  "geometry": {"coordinates":[4.243695,45.890148],"type":"Point"}
}