{
  "type": "Feature",
  "properties": {
    "iso:country":"FR",
    "sg:address":"117, Av. Maux Dormoy, 94500 Champigny sur Marne",
    "sg:orig_category":"Non-Classified Establishments",
    "sg:phone":"+33 1 45 16 99 99",
    "sg:postcode":"94500",
    "sg:province":"Ile de France",
    "wof:name":"A.o.m. S.a.r.l. - Les Applications Oleo M\u00e9caniques",
    "wof:placetype":"venue"
},
  "geometry": {"coordinates":[2.529285,48.806442],"type":"Point"}
}