{
  "type": "Feature",
  "properties": {
    "addr:full":"14 Avenue Du General Leclerc Rn 7 45120 Chalette Sur Loing Cepoy Centre 45120",
    "addr:housenumber":"14;cepoy",
    "addr:postcode":"45120;45120",
    "addr:street":"Avenue Du General Leclerc Rn 7",
    "iso:country":"FR",
    "sg:address":"14 Avenue Du General Leclerc Rn 7 45120 Chalette Sur Loing",
    "sg:city":"Cepoy",
    "sg:classifiers":[
        {
            "category":"Professional",
            "subcategory":"Engineering",
            "type":"Services"
        }
    ],
    "sg:phone":"+33 2 38 26 58 42",
    "sg:postcode":"45120",
    "sg:province":"Centre",
    "sg:tags":[
        "machine",
        "-",
        "environment",
        "equipment",
        "machinery",
        "mechanical"
    ],
    "wof:name":"Sprinkler 45",
    "wof:placetype":"venue"
},
  "geometry": {"coordinates":[2.731191,48.014793],"type":"Point"}
}