{
  "type": "Feature",
  "properties": {
    "addr:full":"23 Rue Chapelet Za La Negresse 64200 Biarritz Biarritz Aquitaine 64200",
    "addr:housenumber":"23",
    "addr:postcode":"64200;64200",
    "addr:street":"Rue Chapelet Za La Negresse",
    "iso:country":"FR",
    "sg:address":"23 Rue Chapelet Za La Negresse 64200 Biarritz",
    "sg:city":"Biarritz",
    "sg:classifiers":[
        {
            "category":"Utilities",
            "subcategory":"Mobile Phone",
            "type":"Services"
        }
    ],
    "sg:phone":"+33 5 59 41 18 18",
    "sg:postcode":"64200",
    "sg:province":"Aquitaine",
    "sg:tags":[
        "good",
        "telecommunication",
        "-",
        "metalworking",
        "metallic",
        "metallurgy",
        "finished"
    ],
    "wof:name":"Graffiti",
    "wof:placetype":"venue"
},
  "geometry": {"coordinates":[-1.558793,43.482571],"type":"Point"}
}