{
  "type": "Feature",
  "properties": {
    "addr:full":"121 Rue De Courlancy Reims Champagne 51100",
    "addr:housenumber":"121",
    "addr:postcode":"51100",
    "addr:street":"Rue De Courlancy;Champagne",
    "iso:country":"FR",
    "sg:address":"121 Rue De Courlancy",
    "sg:city":"Reims",
    "sg:classifiers":[
        {
            "category":"Banks & Credit Unions",
            "subcategory":"Financial Services",
            "type":"Services"
        }
    ],
    "sg:phone":"+33 3 26 04 27 05",
    "sg:postcode":"51100",
    "sg:province":"Champagne",
    "sg:tags":[
        "banking",
        "finance",
        "insurance"
    ],
    "wof:name":"Fifco (cabinet)",
    "wof:placetype":"venue"
},
  "geometry": {"coordinates":[4.020138,49.244137],"type":"Point"}
}