{
  "type": "Feature",
  "properties": {
    "addr:full":"B.P. 1122, 45001 Orl\u00e9ans C\u00e9dex^^226, Rue du Faubourg Saint Vincent, 45000 Orl\u00e9ans Orl\u00e9ans Centre 45000",
    "addr:housenumber":"1122",
    "addr:postcode":"45001;45000;45000",
    "addr:street":"B.P.;Rue Du Faubourg Saint Vincent",
    "iso:country":"FR",
    "sg:address":"B.P. 1122, 45001 Orl\u00e9ans C\u00e9dex^^226, Rue du Faubourg Saint Vincent, 45000 Orl\u00e9ans",
    "sg:city":"Orl\u00e9ans",
    "sg:orig_category":"Non-Classified Establishments",
    "sg:phone":"+33 2 38 86 48 60",
    "sg:postcode":"45000",
    "sg:province":"Centre",
    "wof:name":"Congex International S.a.",
    "wof:placetype":"venue"
},
  "geometry": {"coordinates":[1.904965,47.901428],"type":"Point"}
}