{
  "type": "Feature",
  "properties": {
    "addr:full":"265, Rte de Plaimpalais, 74540 Alby sur Ch\u00e9ran Rhone-Alpes",
    "addr:housenumber":"265",
    "addr:postcode":"74540",
    "addr:street":"Rte De Plaimpalais",
    "iso:country":"FR",
    "sg:address":"265, Rte de Plaimpalais, 74540 Alby sur Ch\u00e9ran",
    "sg:orig_category":"Unclassifiable Establishments",
    "sg:phone":"+33 4 50 68 10 38",
    "sg:province":"Rhone-Alpes",
    "wof:name":"Mi\u00e8vre Et Fils S.a.r.l.",
    "wof:placetype":"venue"
},
  "geometry": {"coordinates":[6.019681,45.819397],"type":"Point"}
}