{
  "type": "Feature",
  "properties": {
    "iso:country":"FR",
    "sg:address":"6, Chemin Saint Joseph - Le Plan de Grasse , 06130 Grasse",
    "sg:orig_category":"Non-Classified Establishments",
    "sg:phone":"+33 4 93 09 19 27",
    "sg:province":"Provence-Alpes-C\u00f4te d'Azur",
    "wof:name":"M.p.e. S.a. - Mati\u00e8res Premi\u00e8res Essentielles",
    "wof:placetype":"venue"
},
  "geometry": {"coordinates":[6.931648,43.649738],"type":"Point"}
}