{
  "type": "Feature",
  "properties": {
    "addr:full":"251 Boulevard Pereire Paris Ile de France 75017",
    "addr:housenumber":"251",
    "addr:postcode":"75017",
    "addr:street":"Boulevard Pereire",
    "iso:country":"FR",
    "sg:address":"251 Boulevard Pereire",
    "sg:city":"Paris",
    "sg:classifiers":[
        {
            "category":"Banks & Credit Unions",
            "subcategory":"Financial Services",
            "type":"Services"
        }
    ],
    "sg:phone":"+33 1 53 81 86 60",
    "sg:postcode":"75017",
    "sg:province":"Ile de France",
    "sg:tags":[
        "banking",
        "finance",
        "insurance"
    ],
    "wof:name":"Banque Du Batiment Et Des Travaux Publics",
    "wof:placetype":"venue"
},
  "geometry": {"coordinates":[2.286443,48.87878],"type":"Point"}
}