{
  "type": "Feature",
  "properties": {
    "addr:full":"Zi Nord Rue Du 1er Mai 01100 Arbent Rhone-Alpes 01100",
    "addr:postcode":"01100;01100",
    "addr:street":"Zi;Rue Du 1Er Mai;Rhone-Alpes",
    "iso:country":"FR",
    "sg:address":"Zi Nord",
    "sg:city":"Rue Du 1er Mai 01100 Arbent",
    "sg:classifiers":[
        {
            "category":"Health Services",
            "subcategory":"Doctor",
            "type":"Services"
        }
    ],
    "sg:phone":"+33 4 74 77 07 35",
    "sg:postcode":"01100",
    "sg:province":"Rhone-Alpes",
    "sg:tags":[
        "product",
        "equipment",
        "-",
        "miscellaneous",
        "precis",
        "instrument",
        "optical"
    ],
    "wof:name":"Morand Lucien Sarl",
    "wof:placetype":"venue"
},
  "geometry": {"coordinates":[5.65945,46.275482],"type":"Point"}
}