{
  "type": "Feature",
  "properties": {
    "iso:country":"FR",
    "sg:address":"Zone d'Activit\u00e9s",
    "sg:city":"Walheim",
    "sg:orig_category":"Non-Classified Establishments",
    "sg:phone":"+33 3 89 40 26 55",
    "sg:postcode":"68130",
    "sg:province":"Alsace",
    "wof:name":"Controls S.a.r.l.",
    "wof:placetype":"venue"
},
  "geometry": {"coordinates":[7.26432,47.639751],"type":"Point"}
}