{
  "type": "Feature",
  "properties": {
    "addr:full":"ld Coulonges BP 16 16370 Saint Sulpice de Cognac Poitou-Charentes 16370",
    "addr:postcode":"16370;de cognac;16370",
    "addr:street":"Ld;Bp 16",
    "iso:country":"FR",
    "sg:address":"ld Coulonges BP 16 16370 Saint Sulpice de Cognac",
    "sg:classifiers":[
        {
            "category":"Home & Garden",
            "subcategory":"Furniture",
            "type":"Retail Goods"
        }
    ],
    "sg:phone":"+33 5 45 83 84 36",
    "sg:postcode":"16370",
    "sg:province":"Poitou-Charentes",
    "sg:tags":[
        "household",
        "wood"
    ],
    "wof:name":"Sulpie (eurl)",
    "wof:placetype":"venue"
},
  "geometry": {"coordinates":[-0.370158,45.770893],"type":"Point"}
}