{
  "type": "Feature",
  "properties": {
    "addr:full":"Rte de Saint Germain Cailly Haute Normandie 76690",
    "addr:postcode":"76690",
    "addr:street":"Rte De Saint;Haute Normandie",
    "iso:country":"FR",
    "sg:address":"Rte de Saint Germain",
    "sg:city":"Cailly",
    "sg:orig_category":"Non-Classified Establishments",
    "sg:phone":"+33 2 32 80 01 10",
    "sg:postcode":"76690",
    "sg:province":"Haute Normandie",
    "wof:name":"Sabe S.a.r.l. - Bureau D'etudes Techniques Pierre Sassine",
    "wof:placetype":"venue"
},
  "geometry": {"coordinates":[1.228075,49.579964],"type":"Point"}
}