{
  "type": "Feature",
  "properties": {
    "addr:full":"Rue Du G\u00e9n\u00e9ral De Gaulle 57730 VALMONT Lorraine 57730",
    "addr:postcode":"57730;57730",
    "addr:street":"Rue Du Ge\u0301Ne\u0301Ral De Gaulle",
    "iso:country":"FR",
    "sg:address":"Rue Du G\u00e9n\u00e9ral De Gaulle 57730 VALMONT",
    "sg:classifiers":[
        {
            "category":"Autos & Motor Vehicles",
            "subcategory":"Recreational Vehicle Sales",
            "type":"Retail Goods"
        }
    ],
    "sg:phone":"+33 3 87 91 36 20",
    "sg:postcode":"57730",
    "sg:province":"Lorraine",
    "sg:tags":[
        "battery",
        "charger"
    ],
    "wof:name":"Absaar Sa",
    "wof:placetype":"venue"
},
  "geometry": {"coordinates":[6.717364,49.089806],"type":"Point"}
}