{
  "type": "Feature",
  "properties": {
    "addr:full":"7, Rue des Vernaies - Z.A. Ferrasses, 74230 Th\u00f4nes Rhone-Alpes",
    "addr:housenumber":"7",
    "addr:postcode":"74230",
    "addr:street":"Rue Des Vernaies Z.A. Ferrasses",
    "iso:country":"FR",
    "sg:address":"7, Rue des Vernaies - Z.A. Ferrasses, 74230 Th\u00f4nes",
    "sg:orig_category":"Non-Classified Establishments",
    "sg:phone":"+33 4 50 02 91 36",
    "sg:province":"Rhone-Alpes",
    "wof:name":"Mermillod Porret S.a.",
    "wof:placetype":"venue"
},
  "geometry": {"coordinates":[6.36344,45.79697],"type":"Point"}
}