{
  "type": "Feature",
  "properties": {
    "iso:country":"FR",
    "sg:address":"1 Rue Des Artisans 21800 Quetigny",
    "sg:city":"Quetigny",
    "sg:classifiers":[
        {
            "category":"Professional",
            "subcategory":"Printing & Photocopies",
            "type":"Services"
        }
    ],
    "sg:phone":"+33 3 80 48 98 48",
    "sg:postcode":"21800",
    "sg:province":"Bourgogne",
    "sg:tags":[
        "publishing"
    ],
    "wof:name":"Editions Faton",
    "wof:placetype":"venue"
},
  "geometry": {"coordinates":[5.104184,47.306072],"type":"Point"}
}