{
  "type": "Feature",
  "properties": {
    "addr:full":"B.P. 5 Morbier^^Les Buclets 39400 Morbier Franche Comt\u00e9 39400",
    "addr:postcode":"39400;39400",
    "addr:street":"B.P. 5 Morbier^^Les Buclets;Franche Comte\u0301",
    "iso:country":"FR",
    "sg:address":"B.P. 5",
    "sg:city":"Morbier^^Les Buclets 39400 Morbier",
    "sg:orig_category":"Non-Classified Establishments",
    "sg:phone":"+33 3 84 34 16 00",
    "sg:postcode":"39400",
    "sg:province":"Franche Comt\u00e9",
    "wof:name":"Cottet S.a.",
    "wof:placetype":"venue"
},
  "geometry": {"coordinates":[6.015896,46.535824],"type":"Point"}
}