{
  "type": "Feature",
  "properties": {
    "addr:full":"Chem De L'Albaret 81160 St. Ju\u00e9ry Midi Pyr\u00e9n\u00e9es 81160",
    "addr:postcode":"81160;81160",
    "addr:street":"Chem",
    "iso:country":"FR",
    "sg:address":"Chem De L'Albaret 81160 St. Ju\u00e9ry",
    "sg:classifiers":[
        {
            "category":"Manufacturing",
            "subcategory":"Tools & Machinery",
            "type":"Manufacturing & Wholesale Goods"
        }
    ],
    "sg:phone":"+33 5 63 78 20 40",
    "sg:postcode":"81160",
    "sg:province":"Midi Pyr\u00e9n\u00e9es",
    "sg:tags":[
        "metallurgy",
        "metalworking"
    ],
    "wof:name":"Auriou Ets Sarl",
    "wof:placetype":"venue"
},
  "geometry": {"coordinates":[2.197184,43.947655],"type":"Point"}
}