{
  "type": "Feature",
  "properties": {
    "addr:full":"46 Grand Place 62400 B\u00e9thune Nord Pas-de-Calais 62400",
    "addr:housenumber":"46",
    "addr:postcode":"62400;62400",
    "addr:street":"Grand Place",
    "iso:country":"FR",
    "sg:address":"46 Grand Place 62400 B\u00e9thune",
    "sg:classifiers":[
        {
            "category":"Banks & Credit Unions",
            "subcategory":"Financial Services",
            "type":"Services"
        }
    ],
    "sg:phone":"+33 3 21 63 76 00",
    "sg:postcode":"62400",
    "sg:province":"Nord Pas-de-Calais",
    "sg:tags":[
        "banking",
        "insurance",
        "institution",
        "finance"
    ],
    "wof:name":"Credit Lyonnais",
    "wof:placetype":"venue"
},
  "geometry": {"coordinates":[2.639927,50.531136],"type":"Point"}
}