{
  "type": "Feature",
  "properties": {
    "iso:country":"FR",
    "sg:address":"B.P. 2, 86280 Saint Beno\u00eet C\u00e9dex^^Av. des Grottes de Passe Lourdin, 86280 Saint Beno\u00eet",
    "sg:orig_category":"Non-Classified Establishments",
    "sg:phone":"+33 5 49 55 72 72",
    "sg:postcode":"86280",
    "sg:province":"Poitou-Charentes",
    "wof:name":"N Et N Europroduction S.a.",
    "wof:placetype":"venue"
},
  "geometry": {"coordinates":[0.31815,46.55444],"type":"Point"}
}