{
  "type": "Feature",
  "properties": {
    "iso:country":"FR",
    "sg:address":"Lotissement Parc Aquatechnique Lotissement 42 34200 Sete",
    "sg:classifiers":[
        {
            "category":"Autos & Motor Vehicles",
            "subcategory":"Boat Sales",
            "type":"Retail Goods"
        }
    ],
    "sg:phone":"+33 4 67 43 58 98",
    "sg:postcode":"34200",
    "sg:province":"Languedoc-Roussillon",
    "sg:tags":[
        "equipment",
        "transport"
    ],
    "wof:name":"Sterne Voiles",
    "wof:placetype":"venue"
},
  "geometry": {"coordinates":[3.69633,43.399052],"type":"Point"}
}