{
  "type": "Feature",
  "properties": {
    "iso:country":"FR",
    "sg:address":"Av. du 1er Mai - ZI",
    "sg:city":"Tarnos",
    "sg:orig_category":"Non-Classified Establishments",
    "sg:phone":"+33 5 59 64 97 98",
    "sg:postcode":"40220",
    "sg:province":"Aquitaine",
    "wof:name":"D.b.m. S.a.r.l.",
    "wof:placetype":"venue"
},
  "geometry": {"coordinates":[-1.487594,43.547791],"type":"Point"}
}