{
  "type": "Feature",
  "properties": {
    "iso:country":"FR",
    "sg:address":"28, Rue des Tuileries - Parc d'Activit\u00e9s de la Souffel, 67460 Souffelweyersheim",
    "sg:city":"Souffelweyersheim",
    "sg:orig_category":"Unclassifiable Establishments",
    "sg:phone":"+33 3 88 19 00 19",
    "sg:postcode":"67460",
    "sg:province":"Alsace",
    "wof:name":"Jcf Impressions S.a.r.l.",
    "wof:placetype":"venue"
},
  "geometry": {"coordinates":[7.727059,48.626476],"type":"Point"}
}