{
  "type": "Feature",
  "properties": {
    "iso:country":"FR",
    "sg:address":"Rte des Aliz\u00e9s - ZI Est",
    "sg:city":"Sandouville",
    "sg:orig_category":"Unclassifiable Establishments",
    "sg:phone":"+33 2 35 11 33 33",
    "sg:postcode":"76430",
    "sg:province":"Haute Normandie",
    "wof:name":"C.n.m.t. S.a. - Compagnie Nouvelle De Manutentions Et De Transports",
    "wof:placetype":"venue"
},
  "geometry": {"coordinates":[0.288194,49.494537],"type":"Point"}
}