{
  "type": "Feature",
  "properties": {
    "addr:full":"Primindus-ZI Saint Mitre II de la Vall\u00e9e 13400 Aubagne Franche Comt\u00e9",
    "addr:postcode":"13400",
    "addr:street":"Valle\u0301E;Franche Comte\u0301",
    "iso:country":"FR",
    "sg:address":"Primindus-ZI Saint Mitre II",
    "sg:city":"de la Vall\u00e9e 13400 Aubagne",
    "sg:classifiers":[
        {
            "category":"Utilities",
            "subcategory":"Electric",
            "type":"Services"
        }
    ],
    "sg:phone":"+33 4 42 36 94 94",
    "sg:province":"Franche Comt\u00e9",
    "sg:tags":[
        "electricity",
        "electronic",
        "electrical",
        "equipment"
    ],
    "wof:name":"Energelec",
    "wof:placetype":"venue"
},
  "geometry": {"coordinates":[5.51861,43.28693],"type":"Point"}
}