{
  "type": "Feature",
  "properties": {
    "iso:country":"FR",
    "sg:address":"11 Rue De Bellevue 35210 Chatillon En Vendelais",
    "sg:city":"Combourtill\u00e9",
    "sg:classifiers":[
        {
            "category":"Home & Garden",
            "subcategory":"Furniture",
            "type":"Retail Goods"
        }
    ],
    "sg:phone":"+33 2 99 76 06 30",
    "sg:postcode":"35210",
    "sg:province":"Bretagne",
    "sg:tags":[
        "household",
        "wood"
    ],
    "wof:name":"Duvel Lucette",
    "wof:placetype":"venue"
},
  "geometry": {"coordinates":[-1.175827,48.225159],"type":"Point"}
}