{
  "type": "Feature",
  "properties": {
    "iso:country":"FR",
    "sg:address":"32, All\u00e9es de la For\u00eat, 51000 Ch\u00e2lons en Champagne",
    "sg:orig_category":"Unclassifiable Establishments",
    "sg:phone":"+33 3 26 65 17 16",
    "sg:province":"Champagne",
    "wof:name":"Bon S.a.",
    "wof:placetype":"venue"
},
  "geometry": {"coordinates":[4.364644,48.947014],"type":"Point"}
}