{
  "type": "Feature",
  "properties": {
    "iso:country":"FR",
    "sg:address":"16, Bd des Alli\u00e9s, 94600 Choisy le Roi",
    "sg:orig_category":"Unclassifiable Establishments",
    "sg:phone":"+33 1 48 92 55 11",
    "sg:province":"Ile de France",
    "wof:name":"Adia France S.a.",
    "wof:placetype":"venue"
},
  "geometry": {"coordinates":[2.40587,48.76543],"type":"Point"}
}