{
  "type": "Feature",
  "properties": {
    "iso:country":"FR",
    "sg:address":"Rue Jean-Marie Perret - ZI Cert\u00e9 Oc\u00e9ane",
    "sg:city":"Trignac",
    "sg:orig_category":"Non-Classified Establishments",
    "sg:phone":"+33 2 40 45 88 66",
    "sg:postcode":"44570",
    "sg:province":"Pays de Loire",
    "wof:name":"Entrepose S.a.",
    "wof:placetype":"venue"
},
  "geometry": {"coordinates":[-2.187869,47.317436],"type":"Point"}
}