{
  "type": "Feature",
  "properties": {
    "iso:country":"FR",
    "sg:address":"ZA du Hillans",
    "sg:city":"Saint Pierre d'Irube",
    "sg:orig_category":"Unclassifiable Establishments",
    "sg:phone":"+33 5 59 44 01 20",
    "sg:postcode":"64990",
    "sg:province":"Aquitaine",
    "wof:name":"Cop\u00e9lectronic S.a.",
    "wof:placetype":"venue"
},
  "geometry": {"coordinates":[-1.4568,43.476341],"type":"Point"}
}