{
  "type": "Feature",
  "properties": {
    "iso:country":"FR",
    "sg:address":"22 Imp Du Sauze 85340 Olonne Sur Mer",
    "sg:classifiers":[
        {
            "category":"Autos & Motor Vehicles",
            "subcategory":"Automobile Sales",
            "type":"Retail Goods"
        }
    ],
    "sg:phone":"+33 2 51 21 21 21",
    "sg:postcode":"85340",
    "sg:province":"Pays de Loire",
    "sg:tags":[
        "equipment",
        "motor-cars",
        "transport"
    ],
    "wof:name":"Fwi-sotrami",
    "wof:placetype":"venue"
},
  "geometry": {"coordinates":[-1.784139,46.507919],"type":"Point"}
}