{
  "type": "Feature",
  "properties": {
    "addr:full":"18, Rue des Caillottes - ZI Plaine des Isles, 89015 Auxerre C\u00e9dex Plaine Alsace 67420",
    "addr:housenumber":"18",
    "addr:postcode":"89015;67420",
    "addr:street":"Rue Des Caillottes Zi Plaine Des",
    "iso:country":"FR",
    "sg:address":"18, Rue des Caillottes - ZI Plaine des Isles, 89015 Auxerre C\u00e9dex",
    "sg:city":"Plaine",
    "sg:orig_category":"Non-Classified Establishments",
    "sg:phone":"+33 3 86 48 24 10",
    "sg:postcode":"67420",
    "sg:province":"Alsace",
    "wof:name":"Fluides Service B S.a.",
    "wof:placetype":"venue"
},
  "geometry": {"coordinates":[3.5744,47.79829],"type":"Point"}
}