{
  "type": "Feature",
  "properties": {
    "addr:full":"B.P. 47, 16200 Jarnac C\u00e9dex^^31, Place Charles de Gaulle, 16200 Jarnac Poitou-Charentes",
    "addr:postcode":"16200;16200",
    "addr:street":"B.P. 47;Ce\u0301Dex^^31 Place Charles De Gaulle",
    "iso:country":"FR",
    "sg:address":"B.P. 47, 16200 Jarnac C\u00e9dex^^31, Place Charles de Gaulle, 16200 Jarnac",
    "sg:orig_category":"Non-Classified Establishments",
    "sg:phone":"+33 5 45 81 01 16",
    "sg:province":"Poitou-Charentes",
    "wof:name":"Imprimerie Bru S.a.",
    "wof:placetype":"venue"
},
  "geometry": {"coordinates":[-0.189326,45.64222],"type":"Point"}
}