{
  "type": "Feature",
  "properties": {
    "addr:full":"230 Rue Jean Mermoz 33320 Eysines Eysines Aquitaine 33320",
    "addr:housenumber":"230",
    "addr:postcode":"33320;33320",
    "addr:street":"Rue Jean Mermoz",
    "iso:country":"FR",
    "sg:address":"230 Rue Jean Mermoz 33320 Eysines",
    "sg:city":"Eysines",
    "sg:classifiers":[
        {
            "category":"Manufacturing",
            "subcategory":"Wood Products",
            "type":"Manufacturing & Wholesale Goods"
        }
    ],
    "sg:phone":"+33 5 56 34 17 45",
    "sg:postcode":"33320",
    "sg:province":"Aquitaine",
    "sg:tags":[
        "furniture"
    ],
    "wof:name":"Amorim France Sa",
    "wof:placetype":"venue"
},
  "geometry": {"coordinates":[-0.664619,44.864868],"type":"Point"}
}