{
  "type": "Feature",
  "properties": {
    "addr:full":"24, Bd des Iles, 92130 Issy les Moulineaux Ile de France",
    "addr:housenumber":"24",
    "addr:postcode":"92130",
    "addr:street":"Bd Des Iles",
    "iso:country":"FR",
    "sg:address":"24, Bd des Iles, 92130 Issy les Moulineaux",
    "sg:orig_category":"Non-Classified Establishments",
    "sg:phone":"+33 1 41 09 19 99",
    "sg:province":"Ile de France",
    "wof:name":"Filemaker France S.a.s.",
    "wof:placetype":"venue"
},
  "geometry": {"coordinates":[2.24969,48.822529],"type":"Point"}
}