{
  "type": "Feature",
  "properties": {
    "addr:full":"129, Rue du Faubourg Poissonni\u00e8re, 75008 Paris Ile de France",
    "addr:housenumber":"129",
    "addr:postcode":"75008",
    "addr:street":"Rue Du Faubourg Poissonnie\u0300Re",
    "iso:country":"FR",
    "sg:address":"129, Rue du Faubourg Poissonni\u00e8re, 75008 Paris",
    "sg:orig_category":"Non-Classified Establishments",
    "sg:phone":"+33 1 49 70 86 86",
    "sg:province":"Ile de France",
    "wof:name":"Prodintour S.a.",
    "wof:placetype":"venue"
},
  "geometry": {"coordinates":[2.348997,48.878658],"type":"Point"}
}