{
  "type": "Feature",
  "properties": {
    "addr:full":"55, Bd du Parc des Expositions, 33525 Bruges C\u00e9dex Lorraine",
    "addr:housenumber":"55",
    "addr:postcode":"33525",
    "addr:street":"Bd Du Parc Des Expositions",
    "iso:country":"FR",
    "sg:address":"55, Bd du Parc des Expositions, 33525 Bruges C\u00e9dex",
    "sg:orig_category":"Non-Classified Establishments",
    "sg:phone":"+33 5 56 11 71 71",
    "sg:province":"Lorraine",
    "wof:name":"Dalkia S.a.",
    "wof:placetype":"venue"
},
  "geometry": {"coordinates":[-0.577286,44.877178],"type":"Point"}
}