{
  "type": "Feature",
  "properties": {
    "iso:country":"FR",
    "sg:address":"352, Chemin des Mauruches Sup\u00e9rieures, 06220 Vallauris",
    "sg:orig_category":"Non-Classified Establishments",
    "sg:phone":"+33 4 93 64 27 07",
    "sg:province":"Rhone-Alpes",
    "wof:name":"J.p.b. S.a.r.l.",
    "wof:placetype":"venue"
},
  "geometry": {"coordinates":[7.062188,43.57626],"type":"Point"}
}