{
  "type": "Feature",
  "properties": {
    "iso:country":"FR",
    "sg:address":"ZI de la Grange Blanche 84350 Courthezon",
    "sg:city":"Anch\u00e9",
    "sg:classifiers":[
        {
            "category":"Building & Trades",
            "subcategory":"Cleaning & Sanitation",
            "type":"Services"
        }
    ],
    "sg:phone":"+33 4 90 70 31 00",
    "sg:postcode":"37500",
    "sg:province":"Centre",
    "sg:tags":[
        "sanitary",
        "supply"
    ],
    "wof:name":"Paul Masquin Sa",
    "wof:placetype":"venue"
},
  "geometry": {"coordinates":[4.882788,44.085251],"type":"Point"}
}