{
  "type": "Feature",
  "properties": {
    "addr:full":"2, Place Paisy, 69574 Dardilly C\u00e9dex Rhone-Alpes",
    "addr:housenumber":"2",
    "addr:postcode":"69574",
    "addr:street":"Place Paisy",
    "iso:country":"FR",
    "sg:address":"2, Place Paisy, 69574 Dardilly C\u00e9dex",
    "sg:orig_category":"Non-Classified Establishments",
    "sg:phone":"+33 4 37 49 99 99",
    "sg:province":"Rhone-Alpes",
    "wof:name":"Firex Cabinet Burnichon Fournier & Assoc S.a.",
    "wof:placetype":"venue"
},
  "geometry": {"coordinates":[4.764042,45.804581],"type":"Point"}
}