{
  "type": "Feature",
  "properties": {
    "addr:full":"B.P. 654, 31319 Lab\u00e8ge C\u00e9dex^^Immeuble California - B\u00e2t. A1, 31670 Lab\u00e8ge Midi Pyr\u00e9n\u00e9es",
    "addr:housenumber":"b.p. 654;ba\u0302t a1",
    "addr:postcode":"31319;31670",
    "iso:country":"FR",
    "sg:address":"B.P. 654, 31319 Lab\u00e8ge C\u00e9dex^^Immeuble California - B\u00e2t. A1, 31670 Lab\u00e8ge",
    "sg:orig_category":"Non-Classified Establishments",
    "sg:phone":"+33 5 61 39 16 87",
    "sg:province":"Midi Pyr\u00e9n\u00e9es",
    "wof:name":"Exp\u00e9rian S.a.",
    "wof:placetype":"venue"
},
  "geometry": {"coordinates":[1.527111,43.529713],"type":"Point"}
}