{
  "type": "Feature",
  "properties": {
    "addr:full":"Rte de Narbonne - RN 113 L\u00e9zignan Corbi\u00e8res Languedoc-Roussillon 11200",
    "addr:housenumber":"113",
    "addr:postcode":"11200",
    "addr:street":"Rte De Narbonne Rn;Corbie\u0300Res",
    "iso:country":"FR",
    "sg:address":"Rte de Narbonne - RN 113",
    "sg:city":"L\u00e9zignan Corbi\u00e8res",
    "sg:orig_category":"Unclassifiable Establishments",
    "sg:phone":"+33 4 68 27 85 15",
    "sg:postcode":"11200",
    "sg:province":"Languedoc-Roussillon",
    "wof:name":"So.fra.lab S.a.s. - Soci\u00e9t\u00e9 Fran\u00e7aise De Laboratoires D'oenologie",
    "wof:placetype":"venue"
},
  "geometry": {"coordinates":[2.808569,43.103775],"type":"Point"}
}