{
  "type": "Feature",
  "properties": {
    "iso:country":"FR",
    "sg:address":"B.P. 24, 67038 Strasbourg C\u00e9dex^^15, Rue des Fr\u00e8res Lumi\u00e8re, 67201 Eckbolsheim",
    "sg:city":"Eckbolsheim",
    "sg:orig_category":"Non-Classified Establishments",
    "sg:phone":"+33 3 88 10 26 66",
    "sg:postcode":"67201",
    "sg:province":"Alsace",
    "wof:name":"C.m.r. - S.m.r. S.a.",
    "wof:placetype":"venue"
},
  "geometry": {"coordinates":[7.687253,48.579323],"type":"Point"}
}