{
  "type": "Feature",
  "properties": {
    "addr:full":"86, Rue de la Libert\u00e9, 38180 Seyssins Rhone-Alpes 38180",
    "addr:housenumber":"86",
    "addr:postcode":"38180;38180",
    "addr:street":"Rue De La Liberte\u0301",
    "iso:country":"FR",
    "sg:address":"86, Rue de la Libert\u00e9, 38180 Seyssins",
    "sg:orig_category":"Non-Classified Establishments",
    "sg:phone":"+33 4 76 21 80 48",
    "sg:postcode":"38180",
    "sg:province":"Rhone-Alpes",
    "wof:name":"B.g.e. S.a.r.l.",
    "wof:placetype":"venue"
},
  "geometry": {"coordinates":[5.696423,45.163475],"type":"Point"}
}