{
  "type": "Feature",
  "properties": {
    "iso:country":"FR",
    "sg:address":"17, Rue Despax - Cauderan , 33200 Bordeaux",
    "sg:city":"Bordeaux",
    "sg:orig_category":"Unclassifiable Establishments",
    "sg:phone":"+33 5 56 08 53 45",
    "sg:postcode":"33200",
    "sg:province":"Aquitaine",
    "wof:name":"Baco Agence R\u00e9gional",
    "wof:placetype":"venue"
},
  "geometry": {"coordinates":[-0.599039,44.848839],"type":"Point"}
}