{
  "type": "Feature",
  "properties": {
    "iso:country":"FR",
    "sg:address":"16 rue Jean Bouveri 71230 St Valliers",
    "sg:city":"Saint-Romain-sous-Gourdon",
    "sg:orig_category":"Ladies' Stockings",
    "sg:phone":"+33 3 85 67 66 00",
    "sg:postcode":"71230",
    "sg:province":"Bourgogne",
    "wof:name":"Gerbe Sa",
    "wof:placetype":"venue"
},
  "geometry": {"coordinates":[-91.627937,34.319626],"type":"Point"}
}