{
  "type": "Feature",
  "properties": {
    "iso:country":"FR",
    "sg:address":"Z I 4 88700 Rambervillers",
    "sg:classifiers":[
        {
            "category":"Autos & Motor Vehicles",
            "subcategory":"Automobile Sales",
            "type":"Retail Goods"
        }
    ],
    "sg:phone":"+33 3 29 43 10 40",
    "sg:postcode":"88700",
    "sg:province":"Lorraine",
    "sg:tags":[
        "used",
        "vehicles"
    ],
    "wof:name":"Egger Rambervillers S.a.r.l.",
    "wof:placetype":"venue"
},
  "geometry": {"coordinates":[6.63509,48.345825],"type":"Point"}
}