{
  "type": "Feature",
  "properties": {
    "iso:country":"FR",
    "sg:address":"Av. Gaston Foebus",
    "sg:city":"Lescar",
    "sg:orig_category":"Unclassifiable Establishments",
    "sg:phone":"+33 5 59 92 38 38",
    "sg:postcode":"64230",
    "sg:province":"Aquitaine",
    "wof:name":"Pau Euralis Union",
    "wof:placetype":"venue"
},
  "geometry": {"coordinates":[-0.447339,43.333431],"type":"Point"}
}