{
  "type": "Feature",
  "properties": {
    "addr:full":"26, Rue des Usines, 44300 Nantes Pays de Loire 44300",
    "addr:housenumber":"26",
    "addr:postcode":"44300;44300",
    "addr:street":"Rue Des Usines",
    "iso:country":"FR",
    "sg:address":"26, Rue des Usines, 44300 Nantes",
    "sg:orig_category":"Non-Classified Establishments",
    "sg:phone":"+33 2 40 43 50 66",
    "sg:postcode":"44300",
    "sg:province":"Pays de Loire",
    "wof:name":"Atlantic Industrie S.a.",
    "wof:placetype":"venue"
},
  "geometry": {"coordinates":[-1.542019,47.252708],"type":"Point"}
}