{
  "type": "Feature",
  "properties": {
    "iso:country":"FR",
    "sg:address":"B.P. 40, 39202 Saint Claude C\u00e9dex^^12, Rue Carnot, 39200 Saint Claude",
    "sg:orig_category":"Non-Classified Establishments",
    "sg:phone":"+33 3 84 45 19 54",
    "sg:province":"Franche Comt\u00e9",
    "wof:name":"Taillerie De France S.a.r.l.",
    "wof:placetype":"venue"
},
  "geometry": {"coordinates":[5.84194,46.34193],"type":"Point"}
}