{
  "type": "Feature",
  "properties": {
    "addr:full":"Place de la Commune de Paris - La Closeraie Mont d'Est Noisy le Grand Ile de France 93160",
    "addr:postcode":"93160",
    "addr:street":"Place De La Commune De Paris La Closeraie Mont D'Est Noisy",
    "iso:country":"FR",
    "sg:address":"Place de la Commune de Paris - La Closeraie Mont d'Est",
    "sg:city":"Noisy le Grand",
    "sg:orig_category":"Non-Classified Establishments",
    "sg:phone":"+33 1 41 67 41 41",
    "sg:postcode":"93160",
    "sg:province":"Ile de France",
    "wof:name":"Plantronics S.a.r.l.",
    "wof:placetype":"venue"
},
  "geometry": {"coordinates":[2.348794,48.827415],"type":"Point"}
}