{
  "type": "Feature",
  "properties": {
    "iso:country":"FR",
    "sg:address":"B.P. 636, 73006 Chamb\u00e9ry C\u00e9dex^^6, Rue Saint Antoine, 73000 Chamb\u00e9ry",
    "sg:orig_category":"Non-Classified Establishments",
    "sg:phone":"+33 4 79 33 60 52",
    "sg:province":"Rhone-Alpes",
    "wof:name":"Madelon S.a.",
    "wof:placetype":"venue"
},
  "geometry": {"coordinates":[5.90839,45.538151],"type":"Point"}
}