{
  "type": "Feature",
  "properties": {
    "addr:full":"7 Rue Seigneurs 68740 Balgau Balgau Alsace 68740",
    "addr:housenumber":"7",
    "addr:postcode":"68740;68740",
    "addr:street":"Rue Seigneurs",
    "iso:country":"FR",
    "sg:address":"7 Rue Seigneurs 68740 Balgau",
    "sg:city":"Balgau",
    "sg:classifiers":[
        {
            "category":"Farming",
            "subcategory":"Livestock Farm",
            "type":"Manufacturing & Wholesale Goods"
        }
    ],
    "sg:phone":"+33 3 89 48 60 32",
    "sg:postcode":"68740",
    "sg:province":"Alsace",
    "sg:tags":[
        "breeding",
        "agriculture",
        "animal"
    ],
    "wof:name":"Fessler Thierry",
    "wof:placetype":"venue"
},
  "geometry": {"coordinates":[7.543165,47.926655],"type":"Point"}
}