{
  "type": "Feature",
  "properties": {
    "iso:country":"FR",
    "sg:address":"B.P. 34, 31701 Blagnac C\u00e9dex^^5, Av. Escadrille Normandie Niemen, 31700 Blagnac",
    "sg:orig_category":"Non-Classified Establishments",
    "sg:phone":"+33 5 61 30 51 00",
    "sg:postcode":"31700",
    "sg:province":"Midi Pyr\u00e9n\u00e9es",
    "wof:name":"Assystem Services S.a.s.",
    "wof:placetype":"venue"
},
  "geometry": {"coordinates":[1.39684,43.634586],"type":"Point"}
}