{
  "type": "Feature",
  "properties": {
    "iso:country":"FR",
    "sg:address":"ZI de Felet 63309 THIERS CEDEX",
    "sg:classifiers":[
        {
            "category":"Bars & Pubs",
            "subcategory":"Oxygen Bar",
            "type":"Food & Drink"
        }
    ],
    "sg:phone":"+33 4 73 80 04 81",
    "sg:province":"Auvergne",
    "sg:tags":[
        "scissors"
    ],
    "wof:name":"Felet-estampage Ets Ren\u00e9 Beaujeu Sa",
    "wof:placetype":"venue"
},
  "geometry": {"coordinates":[3.548272,45.855244],"type":"Point"}
}