{
  "type": "Feature",
  "properties": {
    "iso:country":"FR",
    "sg:address":"6, Sentier du Sac \u00e0 Vin, 78640 Villiers Saint Fr\u00e9d\u00e9ric",
    "sg:orig_category":"Non-Classified Establishments",
    "sg:phone":"+33 1 34 89 75 75",
    "sg:province":"Ile de France",
    "wof:name":"V.s.f. Parcs Et Jardins S.a.r.l.",
    "wof:placetype":"venue"
},
  "geometry": {"coordinates":[1.88767,48.81879],"type":"Point"}
}