{
  "type": "Feature",
  "properties": {
    "iso:country":"FR",
    "sg:address":"Rue De Blochmont 68330 Huningue",
    "sg:city":"Huningue",
    "sg:classifiers":[
        {
            "category":"Government",
            "subcategory":"Department Of Motor Vehicles",
            "type":"Public Place"
        }
    ],
    "sg:phone":"+33 3 89 69 11 11",
    "sg:postcode":"68330",
    "sg:province":"Alsace",
    "sg:tags":[
        "equipment",
        "industrial",
        "transport",
        "motor-cars"
    ],
    "wof:name":"Socar Schelcher Sa",
    "wof:placetype":"venue"
},
  "geometry": {"coordinates":[7.579226,47.587387],"type":"Point"}
}