{
  "type": "Feature",
  "properties": {
    "iso:country":"FR",
    "sg:address":"B.P. 31, 71210 Montchanin^^113, Av de la Lib\u00e9ration, 71210 Montchanin",
    "sg:city":"Montchanin",
    "sg:orig_category":"Fa\u00e7on, Pi\u00e8ces unitaires \u00e0 M\u00e9canique de pr\u00e9cision Prototypes",
    "sg:phone":"+33 3 85 78 11 84",
    "sg:postcode":"71210",
    "sg:province":"Bourgogne",
    "wof:name":"Sicovi S.a.r.l.",
    "wof:placetype":"venue"
},
  "geometry": {"coordinates":[4.463261,46.713284],"type":"Point"}
}