{
  "type": "Feature",
  "properties": {
    "addr:full":"Rue Dampierre 28350 St Lubin Des Joncherets Dampierre-sur-Avre Centre 28350",
    "addr:housenumber":"dampierre-sur-avre",
    "addr:postcode":"28350;28350",
    "addr:street":"Rue Dampierre;Des Joncherets",
    "iso:country":"FR",
    "sg:address":"Rue Dampierre 28350 St Lubin Des Joncherets",
    "sg:city":"Dampierre-sur-Avre",
    "sg:classifiers":[
        {
            "category":"Manufacturing",
            "subcategory":"Rubber & Plastics",
            "type":"Manufacturing & Wholesale Goods"
        }
    ],
    "sg:phone":"+33 2 32 60 62 50",
    "sg:postcode":"28350",
    "sg:province":"Centre",
    "wof:name":"Sacred Sa",
    "wof:placetype":"venue"
},
  "geometry": {"coordinates":[1.192761,48.768749],"type":"Point"}
}