{
  "type": "Feature",
  "properties": {
    "addr:full":"48 Fbg De Belfort 90100 Delle Franche Comt\u00e9 90100",
    "addr:housenumber":"48",
    "addr:postcode":"90100;90100",
    "addr:street":"Fbg De Belfort;Franche Comte\u0301",
    "iso:country":"FR",
    "sg:address":"48 Fbg De Belfort 90100 Delle",
    "sg:orig_category":"Chemicals and Pharmaceuticals Chemistry - by-products Electric and electronic components Electrical ",
    "sg:phone":"+33 3 84 36 84 36",
    "sg:postcode":"90100",
    "sg:province":"Franche Comt\u00e9",
    "wof:name":"Usine Dielectriques De Delle Et Du Fil Isole Moderne (udd-fim)",
    "wof:placetype":"venue"
},
  "geometry": {"coordinates":[7.000732,47.513607],"type":"Point"}
}