{
  "type": "Feature",
  "properties": {
    "addr:full":"2, Rue Jean Mac\u00e9, 05000 Gap Basse Normandie",
    "addr:housenumber":"2",
    "addr:postcode":"05000",
    "addr:street":"Rue Jean Mace\u0301",
    "iso:country":"FR",
    "sg:address":"2, Rue Jean Mac\u00e9, 05000 Gap",
    "sg:orig_category":"Non-Classified Establishments",
    "sg:phone":"+33 4 76 59 16 80",
    "sg:province":"Basse Normandie",
    "wof:name":"Soci\u00e9t\u00e9 Fran\u00e7aise Des Ascenseurs Kon\u00e9",
    "wof:placetype":"venue"
},
  "geometry": {"coordinates":[6.075891,44.562778],"type":"Point"}
}