{
  "type": "Feature",
  "properties": {
    "addr:full":"75 Rue Compans 75019 Paris Ile de France",
    "addr:housenumber":"75",
    "addr:postcode":"75019",
    "addr:street":"Rue Compans",
    "iso:country":"FR",
    "sg:address":"75 Rue Compans 75019 Paris",
    "sg:classifiers":[
        {
            "category":"Professional",
            "subcategory":"Printing & Photocopies",
            "type":"Services"
        }
    ],
    "sg:phone":"+33 1 55 56 41 41",
    "sg:province":"Ile de France",
    "sg:tags":[
        "publishing"
    ],
    "wof:name":"Forum",
    "wof:placetype":"venue"
},
  "geometry": {"coordinates":[2.390499,48.879642],"type":"Point"}
}