{
  "type": "Feature",
  "properties": {
    "addr:full":"11, Rue Pasteur, 02390 Origny Sainte Beno\u00eete Picardie",
    "addr:housenumber":"11",
    "addr:postcode":"02390",
    "addr:street":"Rue Pasteur",
    "iso:country":"FR",
    "sg:address":"11, Rue Pasteur, 02390 Origny Sainte Beno\u00eete",
    "sg:orig_category":"Unclassifiable Establishments",
    "sg:phone":"+33 3 23 09 32 32",
    "sg:province":"Picardie",
    "wof:name":"Union Sda - Union Et Distileries Agricoles",
    "wof:placetype":"venue"
},
  "geometry": {"coordinates":[3.481716,49.839836],"type":"Point"}
}