{
  "type": "Feature",
  "properties": {
    "addr:full":"1, Chemin du Moulin de la ville, 71150 Chagny Chagny Bourgogne 71150",
    "addr:housenumber":"1",
    "addr:postcode":"71150;71150",
    "addr:street":"Chemin Du Moulin De La Ville",
    "iso:country":"FR",
    "sg:address":"1, Chemin du Moulin de la ville, 71150 Chagny",
    "sg:city":"Chagny",
    "sg:orig_category":"Unclassifiable Establishments",
    "sg:phone":"+33 3 85 87 50 50",
    "sg:postcode":"71150",
    "sg:province":"Bourgogne",
    "wof:name":"Pelizzari Serge S.a.",
    "wof:placetype":"venue"
},
  "geometry": {"coordinates":[4.757582,46.915482],"type":"Point"}
}