{
  "type": "Feature",
  "properties": {
    "addr:full":"All De Becquerel 35708 Reims Cedex 07 Champagne",
    "addr:postcode":"35708;cedex 07",
    "iso:country":"FR",
    "sg:address":"All De Becquerel 35708 Reims Cedex 07",
    "sg:classifiers":[
        {
            "category":"Shopping",
            "subcategory":"Computers & Home Electronics",
            "type":"Retail Goods"
        }
    ],
    "sg:phone":"+33 2 99 27 55 55",
    "sg:province":"Champagne",
    "sg:tags":[
        "equipment",
        "electrical",
        "component",
        "electric",
        "electronic"
    ],
    "wof:name":"Philips Semi Conductors",
    "wof:placetype":"venue"
},
  "geometry": {"coordinates":[4.02844,49.26284],"type":"Point"}
}