{
  "type": "Feature",
  "properties": {
    "iso:country":"FR",
    "sg:address":"6, Rue Joseph Jacquard, 21300 Chen\u00f4ve",
    "sg:city":"Chen\u00f4ve",
    "sg:orig_category":"Unclassifiable Establishments",
    "sg:phone":"+33 3 80 51 71 72",
    "sg:postcode":"21300",
    "sg:province":"Bourgogne",
    "wof:name":"Grand Format S.a.r.l.",
    "wof:placetype":"venue"
},
  "geometry": {"coordinates":[5.01612,47.291161],"type":"Point"}
}