{
  "type": "Feature",
  "properties": {
    "addr:full":"Chemin de la Maladrie Saint Jean de Lini\u00e8res Pays de Loire 49070",
    "addr:postcode":"49070",
    "addr:street":"Chemin De La Maladrie Saint Jean De Linie\u0300Res Pays",
    "iso:country":"FR",
    "sg:address":"Chemin de la Maladrie",
    "sg:city":"Saint Jean de Lini\u00e8res",
    "sg:orig_category":"Non-Classified Establishments",
    "sg:phone":"+33 2 41 39 73 12",
    "sg:postcode":"49070",
    "sg:province":"Pays de Loire",
    "wof:name":"Les Greniers Du Poitou S.a.r.l.",
    "wof:placetype":"venue"
},
  "geometry": {"coordinates":[-0.655794,47.461025],"type":"Point"}
}