{
  "type": "Feature",
  "properties": {
    "addr:full":"24 rue Paul Eluard 59750 Feignies Nord Pas-de-Calais",
    "addr:housenumber":"24",
    "addr:postcode":"59750",
    "addr:street":"Rue Paul Eluard",
    "iso:country":"FR",
    "sg:address":"24 rue Paul Eluard 59750 Feignies",
    "sg:classifiers":[
        {
            "category":"Structure",
            "subcategory":"Office Building",
            "type":"Public Place"
        }
    ],
    "sg:phone":"+33 3 27 65 28 28",
    "sg:province":"Nord Pas-de-Calais",
    "sg:tags":[
        "steel",
        "nipple",
        "taper"
    ],
    "wof:name":"Deltinox Sa",
    "wof:placetype":"venue"
},
  "geometry": {"coordinates":[3.930015,50.275513],"type":"Point"}
}