{
  "type": "Feature",
  "properties": {
    "addr:full":"B.P. 69 Saint Marcellin C\u00e9dex^^Les Echavagnes 38160 Saint Marcellin Rhone-Alpes 38160",
    "addr:housenumber":"69",
    "addr:postcode":"38160;38160",
    "addr:street":"B.P.;Marcellin Ce\u0301Dex^^Les Echavagnes;Marcellin Rhone-Alpes",
    "iso:country":"FR",
    "sg:address":"B.P. 69",
    "sg:city":"Saint Marcellin C\u00e9dex^^Les Echavagnes 38160 Saint Marcellin",
    "sg:orig_category":"Non-Classified Establishments",
    "sg:phone":"+33 4 76 64 93 40",
    "sg:postcode":"38160",
    "sg:province":"Rhone-Alpes",
    "wof:name":"Cotte Industrie S.a.",
    "wof:placetype":"venue"
},
  "geometry": {"coordinates":[5.337755,45.121132],"type":"Point"}
}