{
  "type": "Feature",
  "properties": {
    "addr:full":"32, Bd Poissonni\u00e8re, 75009 Paris Ile de France",
    "addr:housenumber":"32",
    "addr:postcode":"75009",
    "addr:street":"Bd Poissonnie\u0300Re",
    "iso:country":"FR",
    "sg:address":"32, Bd Poissonni\u00e8re, 75009 Paris",
    "sg:orig_category":"Unclassifiable Establishments",
    "sg:phone":"+33 1 47 70 25 55",
    "sg:province":"Ile de France",
    "wof:name":"H\u00f4tel Br\u00e9bant S.a.",
    "wof:placetype":"venue"
},
  "geometry": {"coordinates":[2.343529,48.871544],"type":"Point"}
}