{
  "type": "Feature",
  "properties": {
    "addr:full":"ZI Ambert Auvergne 63600",
    "addr:postcode":"63600",
    "addr:street":"Ambert",
    "iso:country":"FR",
    "sg:address":"ZI",
    "sg:city":"Ambert",
    "sg:orig_category":"Unclassifiable Establishments",
    "sg:phone":"+33 4 73 82 41 41",
    "sg:postcode":"63600",
    "sg:province":"Auvergne",
    "wof:name":"Sautra S.a. - Soci\u00e9t\u00e9 Auvergnate Transport Rh\u00f4ne-alpes",
    "wof:placetype":"venue"
},
  "geometry": {"coordinates":[3.72926,45.543671],"type":"Point"}
}