{
  "type": "Feature",
  "properties": {
    "addr:full":"25, Av. des Guilleraies, 92000 Nanterre Ile de France",
    "addr:postcode":"92000",
    "addr:street":"25 Av. Des Guilleraies",
    "iso:country":"FR",
    "sg:address":"25, Av. des Guilleraies, 92000 Nanterre",
    "sg:orig_category":"Non-Classified Establishments",
    "sg:phone":"+33 1 41 20 22 32",
    "sg:province":"Ile de France",
    "wof:name":"Point P Cdo S.a.",
    "wof:placetype":"venue"
},
  "geometry": {"coordinates":[2.184357,48.894363],"type":"Point"}
}