{
  "type": "Feature",
  "properties": {
    "addr:full":"11, Av. Jean M\u00e9decin, 06000 Nice Provence-Alpes-C\u00f4te d'Azur",
    "addr:postcode":"06000",
    "addr:street":"11 Av. Jean Me\u0301Decin",
    "iso:country":"FR",
    "sg:address":"11, Av. Jean M\u00e9decin, 06000 Nice",
    "sg:orig_category":"Non-Classified Establishments",
    "sg:phone":"+33 4 93 87 68 15",
    "sg:province":"Provence-Alpes-C\u00f4te d'Azur",
    "wof:name":"Xc Cosm\u00e9tics S.a.r.l.",
    "wof:placetype":"venue"
},
  "geometry": {"coordinates":[7.268731,43.699036],"type":"Point"}
}