{
  "type": "Feature",
  "properties": {
    "iso:country":"FR",
    "sg:address":"Zone Industrielle de l'Avelon",
    "sg:city":"Beauvais",
    "sg:orig_category":"Non-Classified Establishments",
    "sg:phone":"+33 3 44 45 76 77",
    "sg:postcode":"60000",
    "sg:province":"Picardie",
    "wof:name":"Lenormant Manutention S.a.",
    "wof:placetype":"venue"
},
  "geometry": {"coordinates":[2.042399,49.416889],"type":"Point"}
}