{
  "type": "Feature",
  "properties": {
    "addr:full":"34, Rue de Saint Am\u00e9, 88120 Cleurie Lorraine",
    "addr:housenumber":"34",
    "addr:postcode":"88120",
    "addr:street":"Rue De Saint Ame\u0301",
    "iso:country":"FR",
    "sg:address":"34, Rue de Saint Am\u00e9, 88120 Cleurie",
    "sg:orig_category":"Unclassifiable Establishments",
    "sg:phone":"+33 3 29 61 11 02",
    "sg:province":"Lorraine",
    "wof:name":"Blaison Fils S.a.r.l.",
    "wof:placetype":"venue"
},
  "geometry": {"coordinates":[6.764836,47.98867],"type":"Point"}
}