{
  "type": "Feature",
  "properties": {
    "addr:full":"Rue de Gleizes Bayonne Aquitaine 64100",
    "addr:postcode":"64100",
    "addr:street":"Rue De Gleizes",
    "iso:country":"FR",
    "sg:address":"Rue de Gleizes",
    "sg:city":"Bayonne",
    "sg:orig_category":"Unclassifiable Establishments",
    "sg:phone":"+33 5 59 50 65 65",
    "sg:postcode":"64100",
    "sg:province":"Aquitaine",
    "wof:name":"Plastitube S.a.",
    "wof:placetype":"venue"
},
  "geometry": {"coordinates":[-1.456719,43.492744],"type":"Point"}
}