{
  "type": "Feature",
  "properties": {
    "iso:country":"FR",
    "sg:address":"70 Rue De La Restanque Zi 34000 Montpellier",
    "sg:classifiers":[
        {
            "category":"Banks & Credit Unions",
            "subcategory":"Investment Brokerage",
            "type":"Services"
        }
    ],
    "sg:phone":"+33 4 67 12 80 40",
    "sg:province":"Languedoc-Roussillon",
    "sg:tags":[
        "-",
        "transport",
        "related"
    ],
    "wof:name":"Danzas Sa",
    "wof:placetype":"venue"
},
  "geometry": {"coordinates":[3.87609,43.610855],"type":"Point"}
}