{
  "type": "Feature",
  "properties": {
    "addr:full":"B.P. 40, 56240 Plouay C\u00e9dex^^ZI de Rosterwel, 56240 Plouay Plouay Bretagne 56240",
    "addr:postcode":"56240;56240;56240",
    "addr:street":"B.P. 40",
    "iso:country":"FR",
    "sg:address":"B.P. 40, 56240 Plouay C\u00e9dex^^ZI de Rosterwel, 56240 Plouay",
    "sg:city":"Plouay",
    "sg:orig_category":"Non-Classified Establishments",
    "sg:phone":"+33 2 97 33 32 85",
    "sg:postcode":"56240",
    "sg:province":"Bretagne",
    "wof:name":"Loy & Compagnie S.a.",
    "wof:placetype":"venue"
},
  "geometry": {"coordinates":[-3.322345,47.87484],"type":"Point"}
}