{
  "type": "Feature",
  "properties": {
    "addr:full":"B.P. 47, 59009 Lille C\u00e9dex^^16, Fa\u00e7ade de l'Esplanade, 59000 Lille Nord Pas-de-Calais 59000",
    "addr:postcode":"59009;59000;59000",
    "addr:street":"B.P. 47;L'Esplanade",
    "iso:country":"FR",
    "sg:address":"B.P. 47, 59009 Lille C\u00e9dex^^16, Fa\u00e7ade de l'Esplanade, 59000 Lille",
    "sg:orig_category":"Non-Classified Establishments",
    "sg:phone":"+33 3 20 06 46 40",
    "sg:postcode":"59000",
    "sg:province":"Nord Pas-de-Calais",
    "wof:name":"Danjou S.a.",
    "wof:placetype":"venue"
},
  "geometry": {"coordinates":[3.054026,50.64064],"type":"Point"}
}