{
  "type": "Feature",
  "properties": {
    "addr:full":"Rte du Pont Noir Dunkerque Nord Pas-de-Calais 59140",
    "addr:postcode":"59140",
    "addr:street":"Rte Du Pont Noir",
    "iso:country":"FR",
    "sg:address":"Rte du Pont Noir",
    "sg:city":"Dunkerque",
    "sg:orig_category":"Non-Classified Establishments",
    "sg:phone":"+33 3 28 60 33 00",
    "sg:postcode":"59140",
    "sg:province":"Nord Pas-de-Calais",
    "wof:name":"Semur S.a.r.l.",
    "wof:placetype":"venue"
},
  "geometry": {"coordinates":[2.345095,51.041218],"type":"Point"}
}