{
  "type": "Feature",
  "properties": {
    "addr:full":"4 Rue Alfred Kastler 44307 Nantes Cedex 03 Midi Pyr\u00e9n\u00e9es",
    "addr:housenumber":"4",
    "addr:postcode":"44307",
    "addr:street":"Rue Alfred Kastler",
    "iso:country":"FR",
    "sg:address":"4 Rue Alfred Kastler 44307 Nantes Cedex 03",
    "sg:classifiers":[
        {
            "category":"Professional",
            "subcategory":"Business Services",
            "type":"Services"
        }
    ],
    "sg:phone":"+33 2 51 85 81 00",
    "sg:province":"Midi Pyr\u00e9n\u00e9es",
    "sg:tags":[
        "training",
        "advice"
    ],
    "wof:name":"Ecole Nat Super Techn Indus Et Des Mines La Chantrerie",
    "wof:placetype":"venue"
},
  "geometry": {"coordinates":[-1.520547,47.281116],"type":"Point"}
}