{
  "type": "Feature",
  "properties": {
    "addr:full":"43, Av Blanqui, 08120 Bogny sur Meuse Bogny-sur-Meuse Champagne 08120",
    "addr:postcode":"08120;08120",
    "addr:street":"43 Av Blanqui;Bogny;Meuse;Champagne",
    "iso:country":"FR",
    "sg:address":"43, Av Blanqui, 08120 Bogny sur Meuse",
    "sg:city":"Bogny-sur-Meuse",
    "sg:orig_category":"Non-Classified Establishments",
    "sg:phone":"+33 3 24 32 07 07",
    "sg:postcode":"08120",
    "sg:province":"Champagne",
    "wof:name":"C.e.m.m. Thom\u00e9 S.a.",
    "wof:placetype":"venue"
},
  "geometry": {"coordinates":[4.76688,49.855499],"type":"Point"}
}