{
  "type": "Feature",
  "properties": {
    "iso:country":"FR",
    "sg:address":"20, Rue Jean Hausseguy, 64600 Anglet",
    "sg:city":"Anglet",
    "sg:orig_category":"Non-Classified Establishments",
    "sg:phone":"+33 5 59 03 56 52",
    "sg:postcode":"64600",
    "sg:province":"Aquitaine",
    "wof:name":"Mensys International S.a.r.l.",
    "wof:placetype":"venue"
},
  "geometry": {"coordinates":[-1.521409,43.493275],"type":"Point"}
}