{
  "type": "Feature",
  "properties": {
    "addr:full":"5, Bd du Havre, 95220 Herblay Ile de France 95220",
    "addr:housenumber":"5",
    "addr:postcode":"95220;ile;95220",
    "addr:street":"Bd Du Havre;France",
    "iso:country":"FR",
    "sg:address":"5, Bd du Havre, 95220 Herblay",
    "sg:orig_category":"Non-Classified Establishments",
    "sg:phone":"+33 1 39 31 63 40",
    "sg:postcode":"95220",
    "sg:province":"Ile de France",
    "wof:name":"D.p.l.g. S.a.",
    "wof:placetype":"venue"
},
  "geometry": {"coordinates":[2.183626,48.999779],"type":"Point"}
}