{
  "type": "Feature",
  "properties": {
    "iso:country":"FR",
    "sg:address":"B.P. 8",
    "sg:city":"Tarascon^^les Radoubs 13150 Tarascon",
    "sg:orig_category":"Non-Classified Establishments",
    "sg:phone":"+33 4 90 91 03 00",
    "sg:postcode":"13156",
    "sg:province":"Corse",
    "wof:name":"Tembec S.a.",
    "wof:placetype":"venue"
},
  "geometry": {"coordinates":[4.658177,43.802715],"type":"Point"}
}