{
  "type": "Feature",
  "properties": {
    "addr:full":"L'Orcerie 44840 Les Sorini\u00e8res Pays de Loire",
    "addr:postcode":"44840",
    "addr:street":"L'Orcerie;Sorinie\u0300Res",
    "iso:country":"FR",
    "sg:address":"L'Orcerie 44840 Les Sorini\u00e8res",
    "sg:orig_category":"Non-Classified Establishments",
    "sg:phone":"+33 2 40 80 32 00",
    "sg:province":"Pays de Loire",
    "wof:name":"Staub France S.a.",
    "wof:placetype":"venue"
},
  "geometry": {"coordinates":[-1.5315,47.148571],"type":"Point"}
}