{
  "type": "Feature",
  "properties": {
    "addr:full":"142 Rue De Bayeux 14063 Caen Champagne",
    "addr:housenumber":"142",
    "addr:postcode":"14063",
    "addr:street":"Rue De Bayeux",
    "iso:country":"FR",
    "sg:address":"142 Rue De Bayeux 14063 Caen",
    "sg:classifiers":[
        {
            "category":"Professional",
            "subcategory":"Business Services",
            "type":"Services"
        }
    ],
    "sg:phone":"+33 2 31 38 71 00",
    "sg:province":"Champagne",
    "sg:tags":[
        "training",
        "advice"
    ],
    "wof:name":"Association Sainte Angele",
    "wof:placetype":"venue"
},
  "geometry": {"coordinates":[-0.383999,49.183186],"type":"Point"}
}