{
  "type": "Feature",
  "properties": {
    "iso:country":"FR",
    "sg:address":"310 Rue Jules Valles Parc Eurasante 59120 Loos",
    "sg:classifiers":[
        {
            "category":"Wholesale",
            "subcategory":"Medical Equipment & Supplies",
            "type":"Manufacturing & Wholesale Goods"
        }
    ],
    "sg:phone":"+33 3 28 16 04 80",
    "sg:postcode":"59120",
    "sg:province":"Nord Pas-de-Calais",
    "sg:tags":[
        "instrument",
        "health",
        "-",
        "precision"
    ],
    "wof:name":"Biolume",
    "wof:placetype":"venue"
},
  "geometry": {"coordinates":[3.046229,50.603497],"type":"Point"}
}