{
  "type": "Feature",
  "properties": {
    "addr:full":"24 Rue F\u00e9lix Eboue 44400 Reze Pays de Loire 44400",
    "addr:housenumber":"24",
    "addr:postcode":"44400;44400",
    "addr:street":"Rue Fe\u0301Lix Eboue",
    "iso:country":"FR",
    "sg:address":"24 Rue F\u00e9lix Eboue 44400 Reze",
    "sg:classifiers":[
        {
            "category":"Wholesale",
            "subcategory":"Machinery & Supplies",
            "type":"Manufacturing & Wholesale Goods"
        }
    ],
    "sg:phone":"+33 2 28 00 02 60",
    "sg:postcode":"44400",
    "sg:province":"Pays de Loire",
    "sg:tags":[
        "handling",
        "material",
        "-",
        "machine",
        "equipment",
        "engineering",
        "mechanical"
    ],
    "wof:name":"Otis",
    "wof:placetype":"venue"
},
  "geometry": {"coordinates":[-1.561233,47.196529],"type":"Point"}
}