{
  "type": "Feature",
  "properties": {
    "iso:country":"FR",
    "sg:address":"178 Av Charles De Gaulle 92200 Neuilly Sur Seine",
    "sg:classifiers":[
        {
            "category":"Travel",
            "subcategory":"Hotels & Motels",
            "type":"Entertainment"
        }
    ],
    "sg:phone":"+33 1 47 38 22 10",
    "sg:postcode":"92200",
    "sg:province":"Ile de France",
    "sg:tags":[
        "hotels",
        "business",
        "restaurant"
    ],
    "wof:name":"Pizza Hut",
    "wof:placetype":"venue"
},
  "geometry": {"coordinates":[2.259001,48.885624],"type":"Point"}
}