{
  "type": "Feature",
  "properties": {
    "iso:country":"FR",
    "sg:address":"4 avenue Louis Delage 91310 Linas",
    "sg:classifiers":[
        {
            "category":"Manufacturing",
            "subcategory":"Rubber & Plastics",
            "type":"Manufacturing & Wholesale Goods"
        }
    ],
    "sg:phone":"+33 1 64 49 38 38",
    "sg:province":"Ile de France",
    "sg:tags":[
        "glass"
    ],
    "wof:name":"Plasteca Sarl",
    "wof:placetype":"venue"
},
  "geometry": {"coordinates":[2.26081,48.629841],"type":"Point"}
}