{
  "type": "Feature",
  "properties": {
    "addr:full":"ZAC de Nombel 47110 Ste Livrade Sur Lot Allez-et-Cazeneuve Aquitaine 47110",
    "addr:postcode":"47110;47110",
    "addr:street":"Zac De Nombel;Livrade",
    "iso:country":"FR",
    "sg:address":"ZAC de Nombel 47110 Ste Livrade Sur Lot",
    "sg:city":"Allez-et-Cazeneuve",
    "sg:classifiers":[
        {
            "category":"Manufacturing",
            "subcategory":"Food",
            "type":"Manufacturing & Wholesale Goods"
        }
    ],
    "sg:phone":"+33 5 53 01 02 64",
    "sg:postcode":"47110",
    "sg:province":"Aquitaine",
    "sg:tags":[
        "packaging",
        "industry"
    ],
    "wof:name":"Horti Service Sarl",
    "wof:placetype":"venue"
},
  "geometry": {"coordinates":[0.587745,44.40007],"type":"Point"}
}