{
  "type": "Feature",
  "properties": {
    "addr:full":"47, Rue Henri Moissan, 81000 Albi Midi Pyr\u00e9n\u00e9es",
    "addr:housenumber":"47",
    "addr:postcode":"81000",
    "addr:street":"Rue Henri Moissan",
    "iso:country":"FR",
    "sg:address":"47, Rue Henri Moissan, 81000 Albi",
    "sg:orig_category":"Unclassifiable Establishments",
    "sg:phone":"+33 5 63 60 22 10",
    "sg:province":"Midi Pyr\u00e9n\u00e9es",
    "wof:name":"Soci\u00e9t\u00e9 Cailhol S.a.",
    "wof:placetype":"venue"
},
  "geometry": {"coordinates":[2.186089,43.923809],"type":"Point"}
}