{
  "type": "Feature",
  "properties": {
    "iso:country":"FR",
    "sg:address":"rue Monge 85000 La Roche sur Yon",
    "sg:classifiers":[
        {
            "category":"Professional",
            "type":"Services"
        }
    ],
    "sg:phone":"+33 2 51 37 14 46",
    "sg:province":"Pays de Loire",
    "sg:tags":[
        "transport"
    ],
    "wof:name":"Tnt Chrono Service France Sa",
    "wof:placetype":"venue"
},
  "geometry": {"coordinates":[-1.433754,46.68478],"type":"Point"}
}