{
  "type": "Feature",
  "properties": {
    "iso:country":"FR",
    "sg:address":"Pl Malherbe 83470 St Maximin La Ste Baume",
    "sg:classifiers":[
        {
            "category":"Education",
            "subcategory":"Special Training",
            "type":"Public Place"
        }
    ],
    "sg:phone":"+33 4 98 05 90 10",
    "sg:tags":[
        "pharmaceutical",
        "livestock",
        "animal",
        "chemical",
        "grain",
        "cereal",
        "breeding",
        "chem",
        "agriculture"
    ],
    "wof:name":"Gamme Vert",
    "wof:placetype":"venue"
},
  "geometry": {"coordinates":[5.860262,43.453674],"type":"Point"}
}