{
  "type": "Feature",
  "properties": {
    "addr:full":"Rue Ren\u00e9 Fonck 44860 Pont St Martin Pays de Loire 44860",
    "addr:postcode":"44860;44860",
    "addr:street":"Rue Rene\u0301 Fonck;Pont St",
    "iso:country":"FR",
    "sg:address":"Rue Ren\u00e9 Fonck 44860 Pont St Martin",
    "sg:classifiers":[
        {
            "category":"Banks & Credit Unions",
            "subcategory":"Investment Brokerage",
            "type":"Services"
        }
    ],
    "sg:phone":"+33 2 40 32 12 50",
    "sg:postcode":"44860",
    "sg:province":"Pays de Loire",
    "sg:tags":[
        "business",
        "electricity",
        "advice",
        "equipment",
        "electrical",
        "electronic"
    ],
    "wof:name":"Alstom Sa",
    "wof:placetype":"venue"
},
  "geometry": {"coordinates":[-1.591605,47.152943],"type":"Point"}
}