{
  "type": "Feature",
  "properties": {
    "addr:full":"486, Rue Sadi Carnot, 59184 Sainghin en Weppes Nord Pas-de-Calais",
    "addr:housenumber":"486",
    "addr:postcode":"59184",
    "addr:street":"Rue Sadi Carnot",
    "iso:country":"FR",
    "sg:address":"486, Rue Sadi Carnot, 59184 Sainghin en Weppes",
    "sg:orig_category":"Unclassifiable Establishments",
    "sg:phone":"+33 3 20 58 18 88",
    "sg:province":"Nord Pas-de-Calais",
    "wof:name":"Equipements T\u00e9l\u00e9phoniques Du Nord S.a.",
    "wof:placetype":"venue"
},
  "geometry": {"coordinates":[2.894722,50.554939],"type":"Point"}
}