{
  "type": "Feature",
  "properties": {
    "addr:full":"2, Rue de l'Amiral Nielly, 29200 Brest Brest Bretagne 29200",
    "addr:housenumber":"2",
    "addr:postcode":"29200;29200",
    "addr:street":"Rue De L'Amiral Nielly",
    "iso:country":"FR",
    "sg:address":"2, Rue de l'Amiral Nielly, 29200 Brest",
    "sg:city":"Brest",
    "sg:orig_category":"Unclassifiable Establishments",
    "sg:phone":"+33 2 98 43 29 30",
    "sg:postcode":"29200",
    "sg:province":"Bretagne",
    "wof:name":"Contraste S.a.r.l.",
    "wof:placetype":"venue"
},
  "geometry": {"coordinates":[-4.484762,48.383289],"type":"Point"}
}