{
  "type": "Feature",
  "properties": {
    "addr:full":"Rte De La Vall\u00e9e BP 46 14510 Houlgate Cedex 00 Houlgate Basse Normandie 14510",
    "addr:housenumber":"46",
    "addr:postcode":"14510;cedex 00;14510",
    "addr:street":"Rte De La Valle\u0301E Bp;Houlgate Basse",
    "iso:country":"FR",
    "sg:address":"Rte De La Vall\u00e9e BP 46 14510 Houlgate Cedex 00",
    "sg:city":"Houlgate",
    "sg:classifiers":[
        {
            "category":"Professional",
            "subcategory":"Business Services",
            "type":"Services"
        }
    ],
    "sg:phone":"+33 2 31 28 80 00",
    "sg:postcode":"14510",
    "sg:province":"Basse Normandie",
    "sg:tags":[
        "training",
        "advice"
    ],
    "wof:name":"Ctre D Education Populaire Et De Sport",
    "wof:placetype":"venue"
},
  "geometry": {"coordinates":[-0.061427,49.295109],"type":"Point"}
}