{
  "type": "Feature",
  "properties": {
    "addr:full":"Immeuble Le Val d'Or; La Valette du Var; 83160 Alette Nord Pas-de-Calais 62650",
    "addr:postcode":"83160;62650",
    "addr:street":"Var;Alette Nord",
    "iso:country":"FR",
    "sg:address":"Immeuble Le Val d'Or; La Valette du Var; 83160",
    "sg:city":"Alette",
    "sg:classifiers":[
        {
            "category":"Banks & Credit Unions",
            "subcategory":"Bank",
            "type":"Services"
        }
    ],
    "sg:phone":"+33 4 94 20 66 86",
    "sg:postcode":"62650",
    "sg:province":"Nord Pas-de-Calais",
    "wof:name":"Soci\u00e9t\u00e9 G\u00e9n\u00e9rale",
    "wof:placetype":"venue"
},
  "geometry": {"coordinates":[5.98935,43.148201],"type":"Point"}
}