{
  "type": "Feature",
  "properties": {
    "addr:full":"B.P. 72, 34800 Clermont l'H\u00e9rault C\u00e9dex^^Rte de S\u00e8te - ZAE les Tanes Basses, 34800 Clermont l'H\u00e9raul Languedoc-Roussillon 34800",
    "addr:postcode":"34800;34800;34800",
    "addr:street":"B.P. 72;Zae;\u0301Raul",
    "iso:country":"FR",
    "sg:address":"B.P. 72, 34800 Clermont l'H\u00e9rault C\u00e9dex^^Rte de S\u00e8te - ZAE les Tanes Basses, 34800 Clermont l'H\u00e9raul",
    "sg:orig_category":"Non-Classified Establishments",
    "sg:phone":"+33 4 67 88 47 00",
    "sg:postcode":"34800",
    "sg:province":"Languedoc-Roussillon",
    "wof:name":"Bigmat S.a.",
    "wof:placetype":"venue"
},
  "geometry": {"coordinates":[3.698464,43.409725],"type":"Point"}
}