{
  "type": "Feature",
  "properties": {
    "addr:full":"135 Avenue 69 Regiment D Infant 54270 Essey Les Nancy Lorraine 54270",
    "addr:housenumber":"135",
    "addr:postcode":"54270;54270",
    "addr:street":"Avenue 69 Regiment D Infant",
    "iso:country":"FR",
    "sg:address":"135 Avenue 69 Regiment D Infant 54270 Essey Les Nancy",
    "sg:classifiers":[
        {
            "category":"Home & Garden",
            "subcategory":"Furniture",
            "type":"Retail Goods"
        }
    ],
    "sg:phone":"+33 3 83 21 27 91",
    "sg:postcode":"54270",
    "sg:province":"Lorraine",
    "sg:tags":[
        "household",
        "wood"
    ],
    "wof:name":"Societe Anonyme Sacel",
    "wof:placetype":"venue"
},
  "geometry": {"coordinates":[6.22215,48.70565],"type":"Point"}
}