{
  "type": "Feature",
  "properties": {
    "addr:full":"B.P. 87, 49700 Dou\u00e9 la Fontaine^^ZI des Douces, 49700 Pays de Loire",
    "addr:postcode":"49700;49700;de",
    "addr:street":"B.P. 87",
    "iso:country":"FR",
    "sg:address":"B.P. 87, 49700 Dou\u00e9 la Fontaine^^ZI des Douces, 49700",
    "sg:orig_category":"Non-Classified Establishments",
    "sg:phone":"+33 2 41 59 09 45",
    "sg:province":"Pays de Loire",
    "wof:name":"T.c.t. S.a.s. - Thermoplastiques Cousin Tessier",
    "wof:placetype":"venue"
},
  "geometry": {"coordinates":[-0.266389,47.140175],"type":"Point"}
}