{
  "type": "Feature",
  "properties": {
    "iso:country":"FR",
    "sg:address":"9/11, Rue Benoit Malon, 92156 Suresnes C\u00e9dex",
    "sg:orig_category":"Non-Classified Establishments",
    "sg:phone":"+33 1 46 14 82 00",
    "sg:province":"\u00cele-de-France",
    "wof:name":"Rexam M\u00e9dical Packaging S.a.r.l.",
    "wof:placetype":"venue"
},
  "geometry": {"coordinates":[2.232669,48.872433],"type":"Point"}
}