{
  "type": "Feature",
  "properties": {
    "addr:full":"12, Rue du Perthois, 51300 Norrois Champagne",
    "addr:housenumber":"12",
    "addr:postcode":"51300",
    "addr:street":"Rue Du Perthois",
    "iso:country":"FR",
    "sg:address":"12, Rue du Perthois, 51300 Norrois",
    "sg:orig_category":"Unclassifiable Establishments",
    "sg:phone":"+33 3 26 74 44 99",
    "sg:province":"Champagne",
    "wof:name":"Tidest S.a.r.l.",
    "wof:placetype":"venue"
},
  "geometry": {"coordinates":[4.627618,48.670242],"type":"Point"}
}