{
  "type": "Feature",
  "properties": {
    "iso:country":"FR",
    "sg:address":"4, Rue Louis Bl\u00e9riot, 92561 Rueil Malmaison C\u00e9dex",
    "sg:orig_category":"Non-Classified Establishments",
    "sg:phone":"+33 1 47 77 74 09",
    "sg:province":"Basse Normandie",
    "wof:name":"American Express Carte France S.a.",
    "wof:placetype":"venue"
},
  "geometry": {"coordinates":[2.17913,48.877399],"type":"Point"}
}