{
  "type": "Feature",
  "properties": {
    "addr:full":"15 Bourg Neuve 42308 Roanne Cedex Centre",
    "addr:housenumber":"15",
    "addr:postcode":"42308;cedex",
    "addr:street":"Bourg Neuve",
    "iso:country":"FR",
    "sg:address":"15 Bourg Neuve 42308 Roanne Cedex",
    "sg:classifiers":[
        {
            "category":"Professional",
            "subcategory":"Business Services",
            "type":"Services"
        }
    ],
    "sg:phone":"+33 4 77 71 22 87",
    "sg:province":"Centre",
    "sg:tags":[
        "training",
        "advice"
    ],
    "wof:name":"Ogec Centre Scolaire Charite St Paul",
    "wof:placetype":"venue"
},
  "geometry": {"coordinates":[4.07255,46.035316],"type":"Point"}
}