{
  "type": "Feature",
  "properties": {
    "addr:full":"3, Impasse Croix de Clary, 81000 Albi Midi Pyr\u00e9n\u00e9es",
    "addr:housenumber":"3",
    "addr:postcode":"81000",
    "addr:street":"Impasse Croix De Clary",
    "iso:country":"FR",
    "sg:address":"3, Impasse Croix de Clary, 81000 Albi",
    "sg:orig_category":"Non-Classified Establishments",
    "sg:phone":"+33 5 63 43 68 91",
    "sg:province":"Midi Pyr\u00e9n\u00e9es",
    "wof:name":"Weezz S.a.r.l.",
    "wof:placetype":"venue"
},
  "geometry": {"coordinates":[2.136878,43.940098],"type":"Point"}
}