{
  "type": "Feature",
  "properties": {
    "addr:full":"1 r H\u00f4tel de Ville; Le Puy en Velay Vill\u00e9 Alsace 67220",
    "addr:housenumber":"1",
    "addr:postcode":"67220",
    "addr:street":"R Ho\u0302Tel;Ville\u0301",
    "iso:country":"FR",
    "sg:address":"1 r H\u00f4tel de Ville; Le Puy en Velay",
    "sg:city":"Vill\u00e9",
    "sg:classifiers":[
        {
            "category":"Banks & Credit Unions",
            "subcategory":"Bank",
            "type":"Services"
        }
    ],
    "sg:phone":"+33 3342618954",
    "sg:postcode":"67220",
    "sg:province":"Alsace",
    "wof:name":"Cr\u00e9dit Agricole",
    "wof:placetype":"venue"
},
  "geometry": {"coordinates":[3.883285,45.042027],"type":"Point"}
}