{
  "type": "Feature",
  "properties": {
    "addr:full":"9, Rue Portefoin, 75003 Paris Ile de France",
    "addr:housenumber":"9",
    "addr:postcode":"75003",
    "addr:street":"Rue Portefoin",
    "iso:country":"FR",
    "sg:address":"9, Rue Portefoin, 75003 Paris",
    "sg:orig_category":"Non-Classified Establishments",
    "sg:phone":"+33 1 42 77 72 23",
    "sg:province":"Ile de France",
    "wof:name":"Morisot G\u00e9rard",
    "wof:placetype":"venue"
},
  "geometry": {"coordinates":[2.359845,48.863525],"type":"Point"}
}