{
  "type": "Feature",
  "properties": {
    "iso:country":"FR",
    "sg:address":"1325, Rue de Gautray, 45075 Orl\u00e9ans C\u00e9dex 2",
    "sg:orig_category":"Non-Classified Establishments",
    "sg:phone":"+33 2 38 69 66 00",
    "sg:province":"Centre",
    "wof:name":"Sol'agri S.a.r.l.",
    "wof:placetype":"venue"
},
  "geometry": {"coordinates":[1.90398,47.90139],"type":"Point"}
}