{
  "type": "Feature",
  "properties": {
    "addr:full":"ZAC Le Grand Pasquier Brazey en Plaine Bourgogne 21470",
    "addr:postcode":"21470",
    "addr:street":"Zac Le Grand Pasquier Brazey En Plaine Bourgogne",
    "iso:country":"FR",
    "sg:address":"ZAC Le Grand Pasquier",
    "sg:city":"Brazey en Plaine",
    "sg:orig_category":"Unclassifiable Establishments",
    "sg:phone":"+33 3 80 29 90 63",
    "sg:postcode":"21470",
    "sg:province":"Bourgogne",
    "wof:name":"Cbi S.a.",
    "wof:placetype":"venue"
},
  "geometry": {"coordinates":[5.21622,47.132481],"type":"Point"}
}