{
  "type": "Feature",
  "properties": {
    "iso:country":"FR",
    "sg:address":"LD BEL AIR 69220 Saint Jean d'Ardi\u00e8res",
    "sg:classifiers":[
        {
            "category":"Food Court",
            "type":"Food & Drink"
        }
    ],
    "sg:phone":"+33 4 74 06 16 05",
    "sg:postcode":"69220",
    "sg:province":"Rhone-Alpes",
    "sg:tags":[
        "product",
        "related"
    ],
    "wof:name":"Cave Des Vignerons De Bel Air",
    "wof:placetype":"venue"
},
  "geometry": {"coordinates":[4.800977,46.174179],"type":"Point"}
}