{
  "type": "Feature",
  "properties": {
    "addr:full":"B.P. 193, 62404 B\u00e9thune C\u00e9dex^^123, Rue du Silo, 62400 B\u00e9thune Nord Pas-de-Calais",
    "addr:housenumber":"b.p. 193",
    "addr:postcode":"62404;62400",
    "addr:street":"Rue Du Silo",
    "iso:country":"FR",
    "sg:address":"B.P. 193, 62404 B\u00e9thune C\u00e9dex^^123, Rue du Silo, 62400 B\u00e9thune",
    "sg:orig_category":"Non-Classified Establishments",
    "sg:phone":"+33 3 21 56 32 21",
    "sg:province":"Nord Pas-de-Calais",
    "wof:name":"S.n.b. S.a.r.l. - Soci\u00e9t\u00e9 Nouvelle Brosset",
    "wof:placetype":"venue"
},
  "geometry": {"coordinates":[2.63787,50.530472],"type":"Point"}
}