{
  "type": "Feature",
  "properties": {
    "addr:full":"3 Rue Andr\u00e9 Rousselot 90300 Valdoie Franche Comt\u00e9 90300",
    "addr:housenumber":"3",
    "addr:postcode":"90300;90300",
    "addr:street":"Rue Andre\u0301 Rousselot;Franche Comte\u0301",
    "iso:country":"FR",
    "sg:address":"3 Rue Andr\u00e9 Rousselot 90300 Valdoie",
    "sg:classifiers":[
        {
            "category":"Professional",
            "subcategory":"Advertising",
            "type":"Services"
        }
    ],
    "sg:phone":"+33 3 84 26 26 16",
    "sg:postcode":"90300",
    "sg:province":"Franche Comt\u00e9",
    "sg:tags":[
        "communication",
        "medium"
    ],
    "wof:name":"Az Publicit\u00c9",
    "wof:placetype":"venue"
},
  "geometry": {"coordinates":[6.85156,47.679489],"type":"Point"}
}