{
  "type": "Feature",
  "properties": {
    "addr:full":"Z.I. de Montifaut 85700 Pouzauges Pays de Loire 85700",
    "addr:postcode":"85700;85700",
    "addr:street":"Z.I.;Montifaut",
    "iso:country":"FR",
    "sg:address":"Z.I. de Montifaut 85700 Pouzauges",
    "sg:classifiers":[
        {
            "category":"Bus Stop",
            "subcategory":"None",
            "type":"Transportation"
        }
    ],
    "sg:phone":"+33 2 51 57 58 59",
    "sg:postcode":"85700",
    "sg:province":"Pays de Loire",
    "sg:tags":[
        "block",
        "hydraulic"
    ],
    "wof:name":"Mecabor Sa",
    "wof:placetype":"venue"
},
  "geometry": {"coordinates":[-0.80288,46.721252],"type":"Point"}
}