{
  "type": "Feature",
  "properties": {
    "addr:full":"Avenue Jean Moulin 65100 Lourdes Midi Pyr\u00e9n\u00e9es 65100",
    "addr:postcode":"65100;65100",
    "addr:street":"Avenue Jean Moulin",
    "iso:country":"FR",
    "sg:address":"Avenue Jean Moulin 65100 Lourdes",
    "sg:classifiers":[
        {
            "category":"Shopping",
            "subcategory":"Computers & Home Electronics",
            "type":"Retail Goods"
        }
    ],
    "sg:phone":"+33 5 62 42 75 00",
    "sg:postcode":"65100",
    "sg:province":"Midi Pyr\u00e9n\u00e9es",
    "sg:tags":[
        "equipment",
        "household",
        "electrical",
        "appliance",
        "electronic"
    ],
    "wof:name":"Sa Seb",
    "wof:placetype":"venue"
},
  "geometry": {"coordinates":[-0.027415,43.102936],"type":"Point"}
}