{
  "type": "Feature",
  "properties": {
    "iso:country":"FR",
    "sg:address":"9, Place des Etudiants, 67000 Strasbourg",
    "sg:city":"Strasbourg",
    "sg:orig_category":"Unclassifiable Establishments",
    "sg:phone":"+33 3 88 32 01 57",
    "sg:postcode":"67000",
    "sg:province":"Alsace",
    "wof:name":"Justin Guttmann",
    "wof:placetype":"venue"
},
  "geometry": {"coordinates":[7.747612,48.583942],"type":"Point"}
}