{
  "type": "Feature",
  "properties": {
    "addr:full":"01130 Lalleyriat Rhone-Alpes",
    "addr:postcode":"01130",
    "iso:country":"FR",
    "sg:address":"01130 Lalleyriat",
    "sg:orig_category":"Non-Classified Establishments",
    "sg:phone":"+33 4 74 75 30 96",
    "sg:province":"Rhone-Alpes",
    "wof:name":"L.m.o. S.a.r.l. - Lalleyriat Moules Outils",
    "wof:placetype":"venue"
},
  "geometry": {"coordinates":[5.713611,46.154259],"type":"Point"}
}