{
  "type": "Feature",
  "properties": {
    "addr:full":"13, Rue des Fr\u00e8res Lumi\u00e8re, 78370 Plaisir Ile de France 78370",
    "addr:housenumber":"13",
    "addr:postcode":"78370;78370",
    "addr:street":"Rue Des Fre\u0300Res Lumie\u0300Re",
    "iso:country":"FR",
    "sg:address":"13, Rue des Fr\u00e8res Lumi\u00e8re, 78370 Plaisir",
    "sg:orig_category":"Non-Classified Establishments",
    "sg:phone":"+33 1 30 81 70 47",
    "sg:postcode":"78370",
    "sg:province":"Ile de France",
    "wof:name":"E.t.d.e. Ile De France Normandie S.a.",
    "wof:placetype":"venue"
},
  "geometry": {"coordinates":[1.954093,48.828899],"type":"Point"}
}