{
  "type": "Feature",
  "properties": {
    "addr:full":"58, Rue du G\u00e9n\u00e9ral de Gaulle, 10000 Troyes Champagne",
    "addr:housenumber":"58",
    "addr:postcode":"10000",
    "addr:street":"Rue Du Ge\u0301Ne\u0301Ral De Gaulle",
    "iso:country":"FR",
    "sg:address":"58, Rue du G\u00e9n\u00e9ral de Gaulle, 10000 Troyes",
    "sg:orig_category":"Unclassifiable Establishments",
    "sg:phone":"+33 3 25 73 45 92",
    "sg:province":"Champagne",
    "wof:name":"C.r.2.i. S.a. - Conception R\u00e9alisation Industrielle Et Immobili\u00e8re",
    "wof:placetype":"venue"
},
  "geometry": {"coordinates":[4.073475,48.298965],"type":"Point"}
}