{
  "type": "Feature",
  "properties": {
    "addr:full":"56 Rue De La Belle Croix 62240 Desvres Nord Pas-de-Calais 62240",
    "addr:housenumber":"56",
    "addr:postcode":"62240;62240",
    "addr:street":"Rue De La Belle Croix",
    "iso:country":"FR",
    "sg:address":"56 Rue De La Belle Croix 62240 Desvres",
    "sg:classifiers":[
        {
            "category":"Manufacturing",
            "subcategory":"Building Materials",
            "type":"Manufacturing & Wholesale Goods"
        }
    ],
    "sg:phone":"+33 3 21 10 10 40",
    "sg:postcode":"62240",
    "sg:province":"Nord Pas-de-Calais",
    "sg:tags":[
        "glass",
        "ceramic"
    ],
    "wof:name":"Cofrac Cermix Desvres",
    "wof:placetype":"venue"
},
  "geometry": {"coordinates":[1.834872,50.664223],"type":"Point"}
}