{
  "type": "Feature",
  "properties": {
    "iso:country":"FR",
    "sg:address":"27 Bd Pasteur 63500 Issoire",
    "sg:city":"Issoire",
    "sg:classifiers":[
        {
            "category":"Professional",
            "subcategory":"Business Services",
            "type":"Services"
        }
    ],
    "sg:phone":"+33 4 73 89 42 47",
    "sg:postcode":"63500",
    "sg:province":"Auvergne",
    "sg:tags":[
        "training",
        "advice"
    ],
    "wof:name":"Lycee Polyvalent Regional",
    "wof:placetype":"venue"
},
  "geometry": {"coordinates":[3.248179,45.550358],"type":"Point"}
}