{
  "type": "Feature",
  "properties": {
    "addr:full":"Croix Blanche 56120 Gu\u00e9gon Gu\u00e9gon Bretagne 56120",
    "addr:postcode":"56120;56120",
    "addr:street":"Gue\u0301Gon",
    "iso:country":"FR",
    "sg:address":"Croix Blanche 56120 Gu\u00e9gon",
    "sg:city":"Gu\u00e9gon",
    "sg:classifiers":[
        {
            "category":"Home & Garden",
            "subcategory":"Furniture",
            "type":"Retail Goods"
        }
    ],
    "sg:phone":"+33 2 97 22 20 75",
    "sg:postcode":"56120",
    "sg:province":"Bretagne",
    "sg:tags":[
        "household",
        "wood"
    ],
    "wof:name":"Guillot Encadrements Sa",
    "wof:placetype":"venue"
},
  "geometry": {"coordinates":[-2.585969,47.944897],"type":"Point"}
}