{
  "type": "Feature",
  "properties": {
    "iso:country":"FR",
    "sg:address":"B.P. 273, 44818 Saint Herblain C\u00e9dex^^9, Rue du Ch\u00eane Lass\u00e9, 44810 Saint Herblain",
    "sg:orig_category":"Non-Classified Establishments",
    "sg:phone":"+33 2 40 92 14 14",
    "sg:postcode":"44810",
    "sg:province":"Pays de Loire",
    "wof:name":"Atlang\u00e8ne Applications S.a.r.l.",
    "wof:placetype":"venue"
},
  "geometry": {"coordinates":[-1.652276,47.414013],"type":"Point"}
}