{
  "type": "Feature",
  "properties": {
    "addr:full":"56, Rue Fabvier, 54700 Pont \u00e0 Mousson Lorraine 54700",
    "addr:housenumber":"56",
    "addr:postcode":"54700;54700",
    "addr:street":"Rue Fabvier",
    "iso:country":"FR",
    "sg:address":"56, Rue Fabvier, 54700 Pont \u00e0 Mousson",
    "sg:orig_category":"Non-Classified Establishments",
    "sg:phone":"+33 3 83 82 28 40",
    "sg:postcode":"54700",
    "sg:province":"Lorraine",
    "wof:name":"Colors S.a.r.l.",
    "wof:placetype":"venue"
},
  "geometry": {"coordinates":[6.051655,48.905174],"type":"Point"}
}