{
  "type": "Feature",
  "properties": {
    "iso:country":"FR",
    "sg:address":"8 rue des Deux Cedres 93290 Tremblay en France",
    "sg:classifiers":[
        {
            "category":"Professional",
            "type":"Services"
        }
    ],
    "sg:phone":"+33 1 48 16 76 76",
    "sg:province":"Ile de France",
    "sg:tags":[
        "transport"
    ],
    "wof:name":"International Container Et Transport S.a.",
    "wof:placetype":"venue"
},
  "geometry": {"coordinates":[2.56727,48.951214],"type":"Point"}
}