{
  "type": "Feature",
  "properties": {
    "addr:full":"B.P. 5, 62138 Haisnes^^207bis, Rte de Lens, 62138 Haisnes Nord Pas-de-Calais",
    "addr:housenumber":"5",
    "addr:postcode":"62138;62138",
    "addr:street":"B.P.;Rte De Lens",
    "iso:country":"FR",
    "sg:address":"B.P. 5, 62138 Haisnes^^207bis, Rte de Lens, 62138 Haisnes",
    "sg:orig_category":"Non-Classified Establishments",
    "sg:phone":"+33 3 21 63 41 21",
    "sg:province":"Nord Pas-de-Calais",
    "wof:name":"Stylvet S.a.r.l.",
    "wof:placetype":"venue"
},
  "geometry": {"coordinates":[2.831475,50.508141],"type":"Point"}
}