{
  "type": "Feature",
  "properties": {
    "addr:full":"201 Av Pierre Brossolette 92120 Montrouge Ile de France 92120",
    "addr:housenumber":"201",
    "addr:postcode":"92120;92120",
    "addr:street":"Av Pierre Brossolette",
    "iso:country":"FR",
    "sg:address":"201 Av Pierre Brossolette 92120 Montrouge",
    "sg:classifiers":[
        {
            "category":"Professional",
            "subcategory":"Advertising",
            "type":"Services"
        }
    ],
    "sg:phone":"+33 1 55 58 07 60",
    "sg:postcode":"92120",
    "sg:province":"Ile de France",
    "sg:tags":[
        "communication",
        "medium"
    ],
    "wof:name":"M. Duris Michel",
    "wof:placetype":"venue"
},
  "geometry": {"coordinates":[2.302429,48.813427],"type":"Point"}
}