{
  "type": "Feature",
  "properties": {
    "addr:full":"Z.A. La Croix Saint Mathieu Gallardon Centre 28320",
    "addr:postcode":"28320",
    "addr:street":"Z.A. La Croix Saint Mathieu Gallardon",
    "iso:country":"FR",
    "sg:address":"Z.A. La Croix Saint Mathieu",
    "sg:city":"Gallardon",
    "sg:orig_category":"Non-Classified Establishments",
    "sg:phone":"+33 2 37 33 47 00",
    "sg:postcode":"28320",
    "sg:province":"Centre",
    "wof:name":"Francel S.a.",
    "wof:placetype":"venue"
},
  "geometry": {"coordinates":[1.683245,48.530106],"type":"Point"}
}