{
  "type": "Feature",
  "properties": {
    "iso:country":"FR",
    "sg:address":"11/13, Bd Fernand Point, 38200 Vienne",
    "sg:orig_category":"Unclassifiable Establishments",
    "sg:phone":"+33 4 74 53 18 17",
    "sg:postcode":"38200",
    "sg:province":"Rhone-Alpes",
    "wof:name":"I.d. - Imprimerie Dauphinoise",
    "wof:placetype":"venue"
},
  "geometry": {"coordinates":[4.866286,45.517223],"type":"Point"}
}