{
  "type": "Feature",
  "properties": {
    "addr:full":"28 Rue Eug\u00e8ne Beaune 42000 St Etienne Rhone-Alpes 42000",
    "addr:housenumber":"28",
    "addr:postcode":"42000;42000",
    "addr:street":"Rue Euge\u0300Ne Beaune",
    "iso:country":"FR",
    "sg:address":"28 Rue Eug\u00e8ne Beaune 42000 St Etienne",
    "sg:classifiers":[
        {
            "category":"Utilities",
            "type":"Services"
        }
    ],
    "sg:phone":"+33 810 36 83 68",
    "sg:postcode":"42000",
    "sg:province":"Rhone-Alpes",
    "sg:tags":[
        "raw",
        "energy",
        "material"
    ],
    "wof:name":"La Societe Stephanoise Des Eaux",
    "wof:placetype":"venue"
},
  "geometry": {"coordinates":[4.405183,45.455383],"type":"Point"}
}