{
  "type": "Feature",
  "properties": {
    "addr:full":"5, Av. Franklin Roosevelt, 69150 D\u00e9cines Charpieu Rhone-Alpes 69150",
    "addr:postcode":"69150;69150",
    "addr:street":"Av. Franklin Roosevelt;Rhone-Alpes",
    "iso:country":"FR",
    "sg:address":"5, Av. Franklin Roosevelt, 69150 D\u00e9cines Charpieu",
    "sg:orig_category":"Unclassifiable Establishments",
    "sg:phone":"+33 4 78 49 07 90",
    "sg:postcode":"69150",
    "sg:province":"Rhone-Alpes",
    "wof:name":"Soci\u00e9t\u00e9 Des Etablissements Madoyan S.a.r.l.",
    "wof:placetype":"venue"
},
  "geometry": {"coordinates":[4.937118,45.765057],"type":"Point"}
}