{
  "type": "Feature",
  "properties": {
    "addr:full":"Chemin De Morgiou 17 Beauvallon Centre 13009 Marseille Poitou-Charentes",
    "addr:housenumber":"17",
    "addr:postcode":"13009",
    "addr:street":"Chemin De Morgiou",
    "iso:country":"FR",
    "sg:address":"Chemin De Morgiou 17 Beauvallon Centre 13009 Marseille",
    "sg:classifiers":[
        {
            "category":"Professional",
            "subcategory":"Business Services",
            "type":"Services"
        }
    ],
    "sg:phone":"+33 4 91 40 37 40",
    "sg:province":"Poitou-Charentes",
    "sg:tags":[
        "body",
        "advice"
    ],
    "wof:name":"Service Europeen De Diffusion Des Inventions",
    "wof:placetype":"venue"
},
  "geometry": {"coordinates":[5.401315,43.248466],"type":"Point"}
}