{
  "type": "Feature",
  "properties": {
    "addr:full":"14 Avenue De La R\u00e9publique Nanterre Ile de France 92000",
    "addr:housenumber":"14",
    "addr:postcode":"92000",
    "addr:street":"Avenue De La Re\u0301Publique",
    "iso:country":"FR",
    "sg:address":"14 Avenue De La R\u00e9publique",
    "sg:city":"Nanterre",
    "sg:classifiers":[
        {
            "category":"Banks & Credit Unions",
            "subcategory":"Financial Services",
            "type":"Services"
        }
    ],
    "sg:phone":"+33 1 47 29 00 11",
    "sg:postcode":"92000",
    "sg:province":"Ile de France",
    "sg:tags":[
        "banking",
        "finance",
        "insurance"
    ],
    "wof:name":"Societe Bariteg Sarl",
    "wof:placetype":"venue"
},
  "geometry": {"coordinates":[2.197915,48.897369],"type":"Point"}
}