{
  "type": "Feature",
  "properties": {
    "iso:country":"FR",
    "sg:address":"ZA du Moulin de Bourdini\u00e8re",
    "sg:city":"Coudray au Perche",
    "sg:orig_category":"Unclassifiable Establishments",
    "sg:phone":"+33 2 37 29 15 87",
    "sg:postcode":"28330",
    "sg:province":"Centre",
    "wof:name":"Ferme De Vallegrain S.a.r.l.",
    "wof:placetype":"venue"
},
  "geometry": {"coordinates":[0.85614,48.231976],"type":"Point"}
}