{
  "type": "Feature",
  "properties": {
    "addr:full":"2, Rue du Canal - ZA, 67490 Dettwiller Dettwiller Alsace 67490",
    "addr:housenumber":"2",
    "addr:postcode":"67490;67490",
    "addr:street":"Rue Du Canal Za",
    "iso:country":"FR",
    "sg:address":"2, Rue du Canal - ZA, 67490 Dettwiller",
    "sg:city":"Dettwiller",
    "sg:orig_category":"Unclassifiable Establishments",
    "sg:phone":"+33 3 88 91 40 30",
    "sg:postcode":"67490",
    "sg:province":"Alsace",
    "wof:name":"Trumpf Et Fils S.a.r.l.",
    "wof:placetype":"venue"
},
  "geometry": {"coordinates":[7.46685,48.754059],"type":"Point"}
}