{
  "type": "Feature",
  "properties": {
    "addr:full":"Rue du 11 Novembre 1918 - Ferme Saint Eloi Pithiviers Centre 45300",
    "addr:postcode":"45300",
    "addr:street":"Rue Du 11 Novembre 1918 Ferme Saint Eloi Pithiviers",
    "iso:country":"FR",
    "sg:address":"Rue du 11 Novembre 1918 - Ferme Saint Eloi",
    "sg:city":"Pithiviers",
    "sg:orig_category":"Unclassifiable Establishments",
    "sg:phone":"+33 2 38 30 00 57",
    "sg:postcode":"45300",
    "sg:province":"Centre",
    "wof:name":"Dal Industries S.a.",
    "wof:placetype":"venue"
},
  "geometry": {"coordinates":[2.25153,48.179707],"type":"Point"}
}