{
  "type": "Feature",
  "properties": {
    "addr:full":"21 Rue Vavin 75006 Paris Ile de France 75006",
    "addr:housenumber":"21",
    "addr:postcode":"75006;75006",
    "addr:street":"Rue Vavin",
    "iso:country":"FR",
    "sg:address":"21 Rue Vavin 75006 Paris",
    "sg:classifiers":[
        {
            "category":"Travel",
            "subcategory":"Hotels & Motels",
            "type":"Entertainment"
        }
    ],
    "sg:phone":"+33 1 43 26 93 78",
    "sg:postcode":"75006",
    "sg:province":"Ile de France",
    "sg:tags":[
        "hotels",
        "business",
        "restaurant"
    ],
    "wof:name":"Hotel Danemark",
    "wof:placetype":"venue"
},
  "geometry": {"coordinates":[2.330129,48.843529],"type":"Point"}
}