{
  "type": "Feature",
  "properties": {
    "addr:full":"Zone d'Emploi : Ma Campagne Angoul\u00eame Poitou-Charentes 16000",
    "addr:postcode":"16000",
    "addr:street":"Angoule\u0302Me",
    "iso:country":"FR",
    "sg:address":"Zone d'Emploi : Ma Campagne",
    "sg:city":"Angoul\u00eame",
    "sg:orig_category":"Unclassifiable Establishments",
    "sg:phone":"+33 5 45 65 27 27",
    "sg:postcode":"16000",
    "sg:province":"Poitou-Charentes",
    "wof:name":"Composervices S.a.r.l.",
    "wof:placetype":"venue"
},
  "geometry": {"coordinates":[0.14514,45.645672],"type":"Point"}
}