{
  "type": "Feature",
  "properties": {
    "addr:full":"40 Avenue Des Benedictins 87031 Limoges Cedex 1 Limoges Limousin 87280",
    "addr:housenumber":"40",
    "addr:postcode":"87031;87280",
    "addr:street":"Avenue Des Benedictins",
    "iso:country":"FR",
    "sg:address":"40 Avenue Des Benedictins 87031 Limoges Cedex 1",
    "sg:city":"Limoges",
    "sg:classifiers":[
        {
            "category":"Farming",
            "subcategory":"Farm & Veterinary Services",
            "type":"Manufacturing & Wholesale Goods"
        }
    ],
    "sg:phone":"+33 5 55 34 53 13",
    "sg:postcode":"87280",
    "sg:province":"Limousin",
    "sg:tags":[
        "advice",
        "agriculture",
        "livestock",
        "business"
    ],
    "wof:name":"Office National Des Forets (onf)",
    "wof:placetype":"venue"
},
  "geometry": {"coordinates":[1.265789,45.832653],"type":"Point"}
}