{
  "type": "Feature",
  "properties": {
    "addr:full":"53 rue de Grenelle 75007 Paris Ile de France 75007",
    "addr:housenumber":"53",
    "addr:postcode":"75007;75007",
    "addr:street":"Rue De Grenelle",
    "iso:country":"FR",
    "sg:address":"53 rue de Grenelle 75007 Paris",
    "sg:classifiers":[
        {
            "category":"Professional",
            "subcategory":"Engineering",
            "type":"Services"
        }
    ],
    "sg:phone":"+33 1 44 39 06 00",
    "sg:postcode":"75007",
    "sg:province":"Ile de France",
    "sg:tags":[
        "logistics"
    ],
    "wof:name":"Ectei - Groupe Ece Sa",
    "wof:placetype":"venue"
},
  "geometry": {"coordinates":[2.325201,48.854561],"type":"Point"}
}