{
  "type": "Feature",
  "properties": {
    "addr:full":"39 Rue Valmy 60740 St Maximin Picardie 60740",
    "addr:housenumber":"39",
    "addr:postcode":"60740;60740",
    "addr:street":"Rue Valmy",
    "iso:country":"FR",
    "sg:address":"39 Rue Valmy 60740 St Maximin",
    "sg:classifiers":[
        {
            "category":"Manufacturing",
            "subcategory":"Textiles",
            "type":"Manufacturing & Wholesale Goods"
        }
    ],
    "sg:phone":"+33 3 44 25 90 40",
    "sg:postcode":"60740",
    "sg:province":"Picardie",
    "sg:tags":[
        "clothing",
        "accessory"
    ],
    "wof:name":"Gemo",
    "wof:placetype":"venue"
},
  "geometry": {"coordinates":[2.467142,49.234055],"type":"Point"}
}