{
  "type": "Feature",
  "properties": {
    "iso:country":"FR",
    "sg:address":"55 Avenue De Bruxelles 83500 La Seyne Sur Mer",
    "sg:classifiers":[
        {
            "category":"Manufacturing",
            "subcategory":"Metals",
            "type":"Manufacturing & Wholesale Goods"
        }
    ],
    "sg:phone":"+33 4 94 10 97 10",
    "sg:province":"Lorraine",
    "sg:tags":[
        "metallurgy",
        "steel",
        "metalworking"
    ],
    "wof:name":"Nocella Freres Systeme Aluminium Pour Le Batiment Et L'industrie (sabi)",
    "wof:placetype":"venue"
},
  "geometry": {"coordinates":[5.850535,43.113045],"type":"Point"}
}