{
  "type": "Feature",
  "properties": {
    "iso:country":"FR",
    "sg:address":"29 rue des Aviateurs 67500 Haguenau",
    "sg:city":"Haguenau",
    "sg:classifiers":[
        {
            "category":"Manufacturing",
            "subcategory":"Motor Vehicles & Parts",
            "type":"Manufacturing & Wholesale Goods"
        }
    ],
    "sg:phone":"+33 3 88 93 05 47",
    "sg:postcode":"67500",
    "sg:province":"Alsace",
    "sg:tags":[
        "spindle",
        "unit"
    ],
    "wof:name":"S.o.b. - Klink France",
    "wof:placetype":"venue"
},
  "geometry": {"coordinates":[7.805415,48.801926],"type":"Point"}
}