{
  "type": "Feature",
  "properties": {
    "addr:full":"La Charbonniere Zac 77144 Montevrain Ile de France 77144",
    "addr:postcode":"77144;77144",
    "addr:street":"Zac;Ile De France",
    "iso:country":"FR",
    "sg:address":"La Charbonniere Zac 77144 Montevrain",
    "sg:orig_category":"Miscellaneous Products",
    "sg:phone":"+33 1 64 77 00 30",
    "sg:postcode":"77144",
    "sg:province":"Ile de France",
    "wof:name":"Bic Ecriture 2000",
    "wof:placetype":"venue"
},
  "geometry": {"coordinates":[2.768885,48.853802],"type":"Point"}
}