{
  "type": "Feature",
  "properties": {
    "addr:full":"38, Av. de la Grande-Bretagne, 66000 Perpignan Languedoc-Roussillon",
    "addr:postcode":"66000",
    "addr:street":"38 Av. De La Grande-Bretagne",
    "iso:country":"FR",
    "sg:address":"38, Av. de la Grande-Bretagne, 66000 Perpignan",
    "sg:orig_category":"Unclassifiable Establishments",
    "sg:phone":"+33 4 68 34 63 83",
    "sg:province":"Languedoc-Roussillon",
    "wof:name":"S.i.c.o.e. - Soci\u00e9t\u00e9 D'ing\u00e9nierie Et Conseil Oenotechnique",
    "wof:placetype":"venue"
},
  "geometry": {"coordinates":[2.883761,42.699486],"type":"Point"}
}