{
  "type": "Feature",
  "properties": {
    "iso:country":"FR",
    "sg:address":"Rue du Clos Renard",
    "sg:city":"Ch\u00e2teauneuf sur Loire",
    "sg:orig_category":"Unclassifiable Establishments",
    "sg:phone":"+33 2 38 46 83 80",
    "sg:postcode":"45110",
    "sg:province":"Centre",
    "wof:name":"Soci\u00e9t\u00e9 D'exploitation Des Surgel\u00e9s Disval S.a.s.",
    "wof:placetype":"venue"
},
  "geometry": {"coordinates":[2.209845,47.866165],"type":"Point"}
}