{
  "type": "Feature",
  "properties": {
    "addr:full":"B.P. 163, 52202 Langres C\u00e9dex^^ZI les Franchises, 52200 Langres Champagne 52200",
    "addr:housenumber":"b.p. 163",
    "addr:postcode":"52202;52200;52200",
    "addr:street":"Les Franchises;Champagne",
    "iso:country":"FR",
    "sg:address":"B.P. 163, 52202 Langres C\u00e9dex^^ZI les Franchises, 52200 Langres",
    "sg:orig_category":"Non-Classified Establishments",
    "sg:phone":"+33 3 25 84 32 32",
    "sg:postcode":"52200",
    "sg:province":"Champagne",
    "wof:name":"Docdata France S.a.",
    "wof:placetype":"venue"
},
  "geometry": {"coordinates":[5.33113,47.858158],"type":"Point"}
}