{
  "type": "Feature",
  "properties": {
    "iso:country":"FR",
    "sg:address":"Rue Philippe Lebon Zone Industrielle Nord 85000 La Roche Sur Yon",
    "sg:classifiers":[
        {
            "category":"Manufacturing",
            "subcategory":"Printing",
            "type":"Manufacturing & Wholesale Goods"
        }
    ],
    "sg:phone":"+33 2 51 36 26 48",
    "sg:province":"Pays de Loire",
    "sg:tags":[
        "publishing"
    ],
    "wof:name":"Seritip",
    "wof:placetype":"venue"
},
  "geometry": {"coordinates":[-1.427199,46.67157],"type":"Point"}
}