{
  "type": "Feature",
  "properties": {
    "addr:full":"11 R Raymond Poincar\u00e9 54000 Nancy Lorraine 54000",
    "addr:housenumber":"11",
    "addr:postcode":"54000;54000",
    "addr:street":"R Raymond Poincare\u0301",
    "iso:country":"FR",
    "sg:address":"11 R Raymond Poincar\u00e9 54000 Nancy",
    "sg:classifiers":[
        {
            "category":"Travel",
            "subcategory":"Hotels & Motels",
            "type":"Entertainment"
        }
    ],
    "sg:phone":"+33 3 83 39 75 75",
    "sg:postcode":"54000",
    "sg:province":"Lorraine",
    "sg:tags":[
        "hotels",
        "business",
        "restaurant"
    ],
    "wof:name":"Hotel Mercure",
    "wof:placetype":"venue"
},
  "geometry": {"coordinates":[6.174595,48.690681],"type":"Point"}
}