{
  "type": "Feature",
  "properties": {
    "iso:country":"FR",
    "sg:address":"B.P. 30, 63650 La Monnerie le Montel^^ZI Racine Palladuc, 63650 La Monnerie le Montel",
    "sg:city":"Monnerie-le-Montel",
    "sg:orig_category":"Non-Classified Establishments",
    "sg:phone":"+33 4 73 51 81 01",
    "sg:postcode":"63650",
    "sg:province":"Auvergne",
    "wof:name":"G.c.p. S.a. - Gouttebarge Coupe Pr\u00e9cision",
    "wof:placetype":"venue"
},
  "geometry": {"coordinates":[3.604876,45.869713],"type":"Point"}
}