{
  "type": "Feature",
  "properties": {
    "iso:country":"FR",
    "sg:address":"101, Av. de la D\u00e9fense Passive, 80000 Amiens",
    "sg:orig_category":"Unclassifiable Establishments",
    "sg:phone":"+33 3 22 44 24 26",
    "sg:province":"Picardie",
    "wof:name":"Denis Catherine S.a.r.l.",
    "wof:placetype":"venue"
},
  "geometry": {"coordinates":[2.327372,49.909428],"type":"Point"}
}