{
  "type": "Feature",
  "properties": {
    "iso:country":"FR",
    "sg:address":"87C, Rte de Ch\u00e2teau Renault - Village l'Arroue, 41000 Blois",
    "sg:city":"Blois",
    "sg:orig_category":"Non-Classified Establishments",
    "sg:phone":"+33 2 54 43 62 12",
    "sg:postcode":"41000",
    "sg:province":"Centre",
    "wof:name":"Blois Proth\u00e8se S.a.r.l.",
    "wof:placetype":"venue"
},
  "geometry": {"coordinates":[1.316815,47.587532],"type":"Point"}
}