{
  "type": "Feature",
  "properties": {
    "addr:full":"103 boulevard Saint-Denis 92400 Courbevoie Ile de France",
    "addr:housenumber":"103",
    "addr:postcode":"92400",
    "addr:street":"Boulevard Saint-Denis",
    "iso:country":"FR",
    "sg:address":"103 boulevard Saint-Denis 92400 Courbevoie",
    "sg:classifiers":[
        {
            "category":"Professional",
            "subcategory":"Accounting & Tax Preparation",
            "type":"Services"
        }
    ],
    "sg:phone":"+33 1 43 34 30 60",
    "sg:province":"Ile de France",
    "sg:tags":[
        "scanning",
        "electron",
        "microscope"
    ],
    "wof:name":"Cameca S.a.",
    "wof:placetype":"venue"
},
  "geometry": {"coordinates":[2.263388,48.898071],"type":"Point"}
}