{
  "type": "Feature",
  "properties": {
    "iso:country":"FR",
    "sg:address":"Rte de Vitry en Perthois",
    "sg:city":"Vitry le Fran\u00e7ois",
    "sg:orig_category":"Unclassifiable Establishments",
    "sg:phone":"+33 3 26 74 62 51",
    "sg:postcode":"51300",
    "sg:province":"Champagne",
    "wof:name":"S.i.b.e.m. S.a.r.l. - Soci\u00e9t\u00e9 Industrielle Des Bois Assembl\u00e9s Et Menuiserie",
    "wof:placetype":"venue"
},
  "geometry": {"coordinates":[4.598585,48.730373],"type":"Point"}
}