{
  "type": "Feature",
  "properties": {
    "iso:country":"FR",
    "sg:address":"Route du Demi Boeuf 44310 LA LIMOUZINIERE",
    "sg:classifiers":[
        {
            "category":"Shopping",
            "subcategory":"Computers & Home Electronics",
            "type":"Retail Goods"
        }
    ],
    "sg:phone":"+33 2 40 32 16 00",
    "sg:postcode":"44310",
    "sg:province":"Pays de Loire",
    "sg:tags":[
        "caravan",
        "vehicles",
        "motor",
        "camping",
        "homes"
    ],
    "wof:name":"Pilote Sa",
    "wof:placetype":"venue"
},
  "geometry": {"coordinates":[-1.596309,47.002151],"type":"Point"}
}