{
  "type": "Feature",
  "properties": {
    "addr:full":"Av. Beno\u00eet Frachon - ZA de la Cruizille Villefontaine Rhone-Alpes 38090",
    "addr:postcode":"38090",
    "addr:street":"Av. Benoi\u0302T Frachon Za De La Cruizille;Rhone-Alpes",
    "iso:country":"FR",
    "sg:address":"Av. Beno\u00eet Frachon - ZA de la Cruizille",
    "sg:city":"Villefontaine",
    "sg:orig_category":"Non-Classified Establishments",
    "sg:phone":"+33 4 74 96 23 86",
    "sg:postcode":"38090",
    "sg:province":"Rhone-Alpes",
    "wof:name":"Jeanjean S.a.r.l.",
    "wof:placetype":"venue"
},
  "geometry": {"coordinates":[5.14945,45.615166],"type":"Point"}
}