{
  "type": "Feature",
  "properties": {
    "addr:full":"B.P. 10, 61270 Rai C\u00e9dex^^Rue Jean Racine, 61270 Rai Rai Basse Normandie 61270",
    "addr:postcode":"61270;61270;61270",
    "addr:street":"B.P. 10",
    "iso:country":"FR",
    "sg:address":"B.P. 10, 61270 Rai C\u00e9dex^^Rue Jean Racine, 61270 Rai",
    "sg:city":"Rai",
    "sg:orig_category":"Non-Classified Establishments",
    "sg:phone":"+33 2 33 84 25 55",
    "sg:postcode":"61270",
    "sg:province":"Basse Normandie",
    "wof:name":"Euro Fac M\u00e9tal S.a.r.l.",
    "wof:placetype":"venue"
},
  "geometry": {"coordinates":[0.568433,48.664421],"type":"Point"}
}