{
  "type": "Feature",
  "properties": {
    "addr:full":"Rue Curie; Miramas; 13142 Basse Normandie",
    "addr:postcode":"13142",
    "addr:street":"Rue Curie",
    "iso:country":"FR",
    "sg:address":"Rue Curie; Miramas; 13142",
    "sg:classifiers":[
        {
            "category":"Banks & Credit Unions",
            "subcategory":"Bank",
            "type":"Services"
        }
    ],
    "sg:phone":"+33 3390580893",
    "sg:province":"Basse Normandie",
    "wof:name":"Credit Agricole, Alpes Provence Agence Miramas",
    "wof:placetype":"venue"
},
  "geometry": {"coordinates":[4.999775,43.58358],"type":"Point"}
}