{
  "type": "Feature",
  "properties": {
    "addr:full":"2, Bd Guey, 13012 Marseille Provence-Alpes-C\u00f4te d'Azur",
    "addr:housenumber":"2",
    "addr:postcode":"13012",
    "addr:street":"Bd Guey",
    "iso:country":"FR",
    "sg:address":"2, Bd Guey, 13012 Marseille",
    "sg:orig_category":"Non-Classified Establishments",
    "sg:phone":"+33 4 91 34 41 34",
    "sg:province":"Provence-Alpes-C\u00f4te d'Azur",
    "wof:name":"Euroco S.a.s.",
    "wof:placetype":"venue"
},
  "geometry": {"coordinates":[5.422151,43.30653],"type":"Point"}
}