{
  "type": "Feature",
  "properties": {
    "iso:country":"FR",
    "sg:address":"Chemin De Noyelles Za Du Pommier 62110 Henin Beaumont",
    "sg:classifiers":[
        {
            "category":"Manufacturing",
            "subcategory":"Metals",
            "type":"Manufacturing & Wholesale Goods"
        }
    ],
    "sg:phone":"+33 3 21 13 84 00",
    "sg:postcode":"62110",
    "sg:province":"Nord Pas-de-Calais",
    "sg:tags":[
        "metallurgy",
        "steel",
        "metalworking"
    ],
    "wof:name":"Thyssen France",
    "wof:placetype":"venue"
},
  "geometry": {"coordinates":[2.947094,50.41885],"type":"Point"}
}