{
  "type": "Feature",
  "properties": {
    "addr:full":"24, Rue du Caire, 75002 Paris Ile de France",
    "addr:housenumber":"24",
    "addr:postcode":"75002",
    "addr:street":"Rue Du Caire",
    "iso:country":"FR",
    "sg:address":"24, Rue du Caire, 75002 Paris",
    "sg:orig_category":"Unclassifiable Establishments",
    "sg:phone":"+33 1 42 36 81 92",
    "sg:province":"Ile de France",
    "wof:name":"Vango S.a.",
    "wof:placetype":"venue"
},
  "geometry": {"coordinates":[2.350773,48.86768],"type":"Point"}
}