{
  "type": "Feature",
  "properties": {
    "addr:full":"88 route de la Fin 39400 La Mouille Franche Comt\u00e9",
    "addr:housenumber":"88",
    "addr:postcode":"39400",
    "addr:street":"Route De La Fin;Franche Comte\u0301",
    "iso:country":"FR",
    "sg:address":"88 route de la Fin 39400 La Mouille",
    "sg:classifiers":[
        {
            "category":"Health Services",
            "subcategory":"Optometrist",
            "type":"Services"
        }
    ],
    "sg:phone":"+33 3 84 60 62 09",
    "sg:province":"Franche Comt\u00e9",
    "sg:tags":[
        "glass",
        "ready-made"
    ],
    "wof:name":"Applications Luneti\u00e8res Sa",
    "wof:placetype":"venue"
},
  "geometry": {"coordinates":[5.980776,46.506668],"type":"Point"}
}