{
  "type": "Feature",
  "properties": {
    "iso:country":"FR",
    "sg:address":"19, Rue Bleue, 75009 Paris",
    "sg:orig_category":"Non-Classified Establishments",
    "sg:phone":"+33 1 56 03 03 03",
    "sg:province":"Ile de France",
    "wof:name":"S.c.j.m.p. S.a.r.l.",
    "wof:placetype":"venue"
},
  "geometry": {"coordinates":[2.345849,48.875816],"type":"Point"}
}