{
  "type": "Feature",
  "properties": {
    "addr:full":"6, Av. Charles de Gaulle, 78150 Le Chesnay Ile de France",
    "addr:postcode":"78150",
    "addr:street":"Av. Charles De Gaulle",
    "iso:country":"FR",
    "sg:address":"6, Av. Charles de Gaulle, 78150 Le Chesnay",
    "sg:orig_category":"Unclassifiable Establishments",
    "sg:phone":"+33 1 39 55 52 60",
    "sg:province":"Ile de France",
    "wof:name":"Amcan Ingr\u00e9dients Int'l S.a.r.l.",
    "wof:placetype":"venue"
},
  "geometry": {"coordinates":[2.115254,48.829239],"type":"Point"}
}