{
  "type": "Feature",
  "properties": {
    "addr:full":"8, Rue Claude Chappe - ZI, 10152 Pont Sainte Marie Bourgogne",
    "addr:housenumber":"8",
    "addr:postcode":"10152",
    "addr:street":"Rue Claude Chappe Zi",
    "iso:country":"FR",
    "sg:address":"8, Rue Claude Chappe - ZI, 10152 Pont Sainte Marie",
    "sg:orig_category":"CHAUDRONNERIE INDUSTRIELLE ALUMINIUM ET INOX SOUDAGE PAR POINTS, SOUDAGE ALUMINIUM maintenance indus",
    "sg:phone":"+33 3 25 81 19 21",
    "sg:province":"Bourgogne",
    "wof:name":"S.i.c. S.a.r.l. - Soci\u00e9t\u00e9 Industrielle De Chaudronnerie",
    "wof:placetype":"venue"
},
  "geometry": {"coordinates":[2.886713,44.877476],"type":"Point"}
}