{
  "type": "Feature",
  "properties": {
    "addr:full":"6, Place de l' Eglise, 85110 Sainte C\u00e9cile Pays de Loire",
    "addr:housenumber":"6",
    "addr:postcode":"85110",
    "addr:street":"Place De L ' Eglise;Ce\u0301Cile",
    "iso:country":"FR",
    "sg:address":"6, Place de l' Eglise, 85110 Sainte C\u00e9cile",
    "sg:orig_category":"Unclassifiable Establishments",
    "sg:phone":"+33 2 51 40 24 01",
    "sg:province":"Pays de Loire",
    "wof:name":"Raymond Rochereau Et Compagnie S.a.r.l.",
    "wof:placetype":"venue"
},
  "geometry": {"coordinates":[-1.114073,46.743942],"type":"Point"}
}