{
  "type": "Feature",
  "properties": {
    "iso:country":"FR",
    "sg:address":"2/4, Av. Antoine V\u00e9ran, 06100 Nice",
    "sg:orig_category":"Non-Classified Establishments",
    "sg:phone":"+33 4 92 07 55 50",
    "sg:province":"Basse Normandie",
    "wof:name":"Cofratel Rh\u00f4ne Alpes S.a.",
    "wof:placetype":"venue"
},
  "geometry": {"coordinates":[7.249412,43.724342],"type":"Point"}
}