{
  "type": "Feature",
  "properties": {
    "addr:full":"B.P. 109, 13153 Tarascon C\u00e9dex^^ZAC du Roubian, 13150 Tarascon Corse",
    "addr:housenumber":"b.p. 109",
    "addr:postcode":"13153;13150",
    "iso:country":"FR",
    "sg:address":"B.P. 109, 13153 Tarascon C\u00e9dex^^ZAC du Roubian, 13150 Tarascon",
    "sg:orig_category":"Non-Classified Establishments",
    "sg:phone":"+33 4 90 91 51 70",
    "sg:province":"Corse",
    "wof:name":"B.c.s. Panita S.a. - Boulangerie Coagul\u00e9e Surgel\u00e9e",
    "wof:placetype":"venue"
},
  "geometry": {"coordinates":[4.658177,43.802715],"type":"Point"}
}