{
  "type": "Feature",
  "properties": {
    "addr:full":"5 rue Thiers; La Roche sur Yon; 85000 Pays de Loire 85000",
    "addr:housenumber":"5",
    "addr:postcode":"85000;85000",
    "addr:street":"Rue Thiers La;Yon",
    "iso:country":"FR",
    "sg:address":"5 rue Thiers; La Roche sur Yon; 85000",
    "sg:classifiers":[
        {
            "category":"Banks & Credit Unions",
            "subcategory":"Bank",
            "type":"Services"
        }
    ],
    "sg:phone":"+33 2 51 07 09 79",
    "sg:postcode":"85000",
    "sg:province":"Pays de Loire",
    "wof:name":"Banque G\u00e9n\u00e9rale, Du Commerce",
    "wof:placetype":"venue"
},
  "geometry": {"coordinates":[-1.430076,46.669514],"type":"Point"}
}