{
  "type": "Feature",
  "properties": {
    "iso:country":"FR",
    "sg:address":"Zi De Velesmes Essarts Rn 73 25410 St Vit",
    "sg:classifiers":[
        {
            "category":"Manufacturing",
            "subcategory":"Tools & Machinery",
            "type":"Manufacturing & Wholesale Goods"
        }
    ],
    "sg:phone":"+33 3 81 58 46 00",
    "sg:postcode":"25410",
    "sg:province":"Franche Comt\u00e9",
    "sg:tags":[
        "metallurgy",
        "metalworking"
    ],
    "wof:name":"Cablac",
    "wof:placetype":"venue"
},
  "geometry": {"coordinates":[5.81099,47.181793],"type":"Point"}
}