{
  "type": "Feature",
  "properties": {
    "addr:full":"20 Rue Thimonnier 63100 Clermont Ferrand Clermont-Ferrand Auvergne 63100",
    "addr:housenumber":"20",
    "addr:postcode":"63100;63100",
    "addr:street":"Rue Thimonnier",
    "iso:country":"FR",
    "sg:address":"20 Rue Thimonnier 63100 Clermont Ferrand",
    "sg:city":"Clermont-Ferrand",
    "sg:classifiers":[
        {
            "category":"Professional",
            "subcategory":"Engineering",
            "type":"Services"
        }
    ],
    "sg:phone":"+33 4 73 92 19 92",
    "sg:postcode":"63100",
    "sg:province":"Auvergne",
    "sg:tags":[
        "machine",
        "-",
        "mechanical"
    ],
    "wof:name":"Le Froid Electronique",
    "wof:placetype":"venue"
},
  "geometry": {"coordinates":[3.129362,45.788277],"type":"Point"}
}