{
  "type": "Feature",
  "properties": {
    "iso:country":"FR",
    "sg:address":"4, Rue du Mans, 49300 Cholet",
    "sg:orig_category":"Unclassifiable Establishments",
    "sg:phone":"+33 2 41 75 20 10",
    "sg:province":"Pays de Loire",
    "wof:name":"S\u00e9rac S.a.",
    "wof:placetype":"venue"
},
  "geometry": {"coordinates":[-0.863361,47.075111],"type":"Point"}
}