{
  "type": "Feature",
  "properties": {
    "iso:country":"FR",
    "sg:address":"24",
    "sg:city":"Champforgeuil",
    "sg:classifiers":[
        {
            "category":"Wholesale",
            "subcategory":"Metals & Minerals",
            "type":"Manufacturing & Wholesale Goods"
        }
    ],
    "sg:phone":"+33 3 85 43 43 78",
    "sg:postcode":"71530",
    "sg:province":"Bourgogne",
    "sg:tags":[
        "steel",
        "-",
        "metalworking",
        "metallic",
        "metallurgy",
        "finished"
    ],
    "wof:name":"Fonderie Mathieu",
    "wof:placetype":"venue"
},
  "geometry": {"coordinates":[4.847232,46.814735],"type":"Point"}
}