{
  "type": "Feature",
  "properties": {
    "addr:full":"341, Rte de Clisson, 44230 Saint S\u00e9bastien sur Loire Pays de Loire",
    "addr:housenumber":"341",
    "addr:postcode":"44230",
    "addr:street":"Rte De Clisson;Se\u0301Bastien;Loire",
    "iso:country":"FR",
    "sg:address":"341, Rte de Clisson, 44230 Saint S\u00e9bastien sur Loire",
    "sg:orig_category":"Unclassifiable Establishments",
    "sg:phone":"+33 2 51 79 10 00",
    "sg:province":"Pays de Loire",
    "wof:name":"Covi Pca S.a.",
    "wof:placetype":"venue"
},
  "geometry": {"coordinates":[-1.488709,47.187901],"type":"Point"}
}