{
  "type": "Feature",
  "properties": {
    "addr:full":"5/7, Rue Marpignies, 75020 Paris Ile de France",
    "addr:housenumber":"5 / 7",
    "addr:postcode":"75020",
    "addr:street":"Rue Marpignies",
    "iso:country":"FR",
    "sg:address":"5/7, Rue Marpignies, 75020 Paris",
    "sg:orig_category":"Unclassifiable Establishments",
    "sg:phone":"+33 1 40 31 83 98",
    "sg:province":"Ile de France",
    "wof:name":"Stokmeul Etablissements Bontemps S.a.r.l.",
    "wof:placetype":"venue"
},
  "geometry": {"coordinates":[2.399365,48.864849],"type":"Point"}
}