{
  "type": "Feature",
  "properties": {
    "addr:full":"61 rue Amp\u00e8re 68000 Colmar Colmar Alsace 68000",
    "addr:housenumber":"61",
    "addr:postcode":"68000;68000",
    "addr:street":"Rue Ampe\u0300Re",
    "iso:country":"FR",
    "sg:address":"61 rue Amp\u00e8re 68000 Colmar",
    "sg:city":"Colmar",
    "sg:classifiers":[
        {
            "category":"Professional",
            "subcategory":"Computer Services",
            "type":"Services"
        }
    ],
    "sg:phone":"+33 3 89 20 74 74",
    "sg:postcode":"68000",
    "sg:province":"Alsace",
    "sg:tags":[
        "administration",
        "software"
    ],
    "wof:name":"Ste Alsac Logiciels Informat Communaux S.a.r.l.",
    "wof:placetype":"venue"
},
  "geometry": {"coordinates":[7.37422,48.085499],"type":"Point"}
}