{
  "type": "Feature",
  "properties": {
    "addr:full":"7, Rue Amp\u00e8re, 76150 Maromme Haute Normandie",
    "addr:housenumber":"7",
    "addr:postcode":"76150",
    "addr:street":"Rue Ampe\u0300Re;Haute Normandie",
    "iso:country":"FR",
    "sg:address":"7, Rue Amp\u00e8re, 76150 Maromme",
    "sg:orig_category":"Unclassifiable Establishments",
    "sg:phone":"+33 2 32 82 38 38",
    "sg:province":"Haute Normandie",
    "wof:name":"Nadella S.a.",
    "wof:placetype":"venue"
},
  "geometry": {"coordinates":[-97.32923099999999,32.748508],"type":"Point"}
}