{
  "type": "Feature",
  "properties": {
    "addr:full":"Rue du Ch\u00e2teau Sailly Saillisel Picardie 80360",
    "addr:postcode":"80360",
    "addr:street":"Rue Du Cha\u0302Teau Sailly Saillisel Picardie",
    "iso:country":"FR",
    "sg:address":"Rue du Ch\u00e2teau",
    "sg:city":"Sailly Saillisel",
    "sg:orig_category":"Unclassifiable Establishments",
    "sg:phone":"+33 3 22 85 04 22",
    "sg:postcode":"80360",
    "sg:province":"Picardie",
    "wof:name":"Tripette Et Renaud S.a.",
    "wof:placetype":"venue"
},
  "geometry": {"coordinates":[2.910705,50.029018],"type":"Point"}
}