{
  "type": "Feature",
  "properties": {
    "addr:full":"27, Cours Evrard de Fayolle, 33000 Bordeaux Bordeaux Aquitaine 33000",
    "addr:housenumber":"27",
    "addr:postcode":"33000;33000",
    "addr:street":"Cours Evrard De Fayolle",
    "iso:country":"FR",
    "sg:address":"27, Cours Evrard de Fayolle, 33000 Bordeaux",
    "sg:city":"Bordeaux",
    "sg:orig_category":"Non-Classified Establishments",
    "sg:phone":"+33 5 56 01 99 99",
    "sg:postcode":"33000",
    "sg:province":"Aquitaine",
    "wof:name":"Fiduciaire D'aquitaine S.a.r.l.",
    "wof:placetype":"venue"
},
  "geometry": {"coordinates":[-0.574506,44.854263],"type":"Point"}
}