{
  "type": "Feature",
  "properties": {
    "addr:full":"impasse Saint-Eloi 77220 Gretz Armainvilliers Ile de France 77220",
    "addr:postcode":"77220;77220",
    "addr:street":"Impasse Saint-Eloi",
    "iso:country":"FR",
    "sg:address":"impasse Saint-Eloi 77220 Gretz Armainvilliers",
    "sg:orig_category":"Adhesives, Non-Combustible",
    "sg:phone":"+33 1 64 07 29 00",
    "sg:postcode":"77220",
    "sg:province":"Ile de France",
    "wof:name":"Cellochrome Sarl",
    "wof:placetype":"venue"
},
  "geometry": {"coordinates":[2.72897,48.730026],"type":"Point"}
}