{
  "type": "Feature",
  "properties": {
    "addr:full":"21 pl de l'\u00c9glise; Mo\u00eblan sur Mer; 29350 Mo\u00eblan-sur-Mer Bretagne 29350",
    "addr:housenumber":"21",
    "addr:postcode":"29350;29350",
    "addr:street":"Pl De L'E \u0301Glise Moe\u0308Lan Sur Mer;Moe\u0308Lan-Sur-Mer Bretagne",
    "iso:country":"FR",
    "sg:address":"21 pl de l'\u00c9glise; Mo\u00eblan sur Mer; 29350",
    "sg:city":"Mo\u00eblan-sur-Mer",
    "sg:classifiers":[
        {
            "category":"Banks & Credit Unions",
            "subcategory":"Bank",
            "type":"Services"
        }
    ],
    "sg:phone":"+33 2 98 39 66 63",
    "sg:postcode":"29350",
    "sg:province":"Bretagne",
    "wof:name":"Caisse Regionale De Cr\u00e9dit, Maritime Mutuel Du Finist\u00e8re",
    "wof:placetype":"venue"
},
  "geometry": {"coordinates":[-3.629334,47.81406],"type":"Point"}
}