{
  "type": "Feature",
  "properties": {
    "iso:country":"FR",
    "sg:address":"18, Rue de la Marchanderie - La Bouilloni\u00e8re , 50660 Quettreville sur Sienne",
    "sg:city":"Annoville",
    "sg:orig_category":"Unclassifiable Establishments",
    "sg:phone":"+33 2 33 07 41 07",
    "sg:postcode":"50660",
    "sg:province":"Basse Normandie",
    "wof:name":"P\u00e9pini\u00e8re Lebas G.a.e.c.",
    "wof:placetype":"venue"
},
  "geometry": {"coordinates":[-1.558889,48.949661],"type":"Point"}
}