{
  "type": "Feature",
  "properties": {
    "addr:full":"4, Rue Ren\u00e9 Razel - Domaine Technologique , 91400 Saclay Ile de France",
    "addr:housenumber":"4",
    "addr:postcode":"91400;ile",
    "addr:street":"Rue Rene\u0301 Razel;Technologique",
    "iso:country":"FR",
    "sg:address":"4, Rue Ren\u00e9 Razel - Domaine Technologique , 91400 Saclay",
    "sg:orig_category":"Unclassifiable Establishments",
    "sg:phone":"+33 1 69 33 23 23",
    "sg:province":"Ile de France",
    "wof:name":"Ultimate Renaissance S.a.r.l.",
    "wof:placetype":"venue"
},
  "geometry": {"coordinates":[2.187755,48.698891],"type":"Point"}
}