{
  "type": "Feature",
  "properties": {
    "addr:full":"B.P. 80, 60304 Senlis C\u00e9dex^^23, Av. F\u00e9lix Louat, 60300 Senlis Picardie 60300",
    "addr:postcode":"60304;60300;60300",
    "addr:street":"B.P. 80;Av. Fe\u0301Lix Louat",
    "iso:country":"FR",
    "sg:address":"B.P. 80, 60304 Senlis C\u00e9dex^^23, Av. F\u00e9lix Louat, 60300 Senlis",
    "sg:orig_category":"Non-Classified Establishments",
    "sg:phone":"+33 3 44 53 92 92",
    "sg:postcode":"60300",
    "sg:province":"Picardie",
    "wof:name":"Asgrow France S.a.",
    "wof:placetype":"venue"
},
  "geometry": {"coordinates":[2.5857,49.206364],"type":"Point"}
}