{
  "type": "Feature",
  "properties": {
    "addr:full":"Rte De Lugos 33770 Salles Salles Aquitaine 33770",
    "addr:postcode":"33770;33770",
    "addr:street":"Rte De Lugos",
    "iso:country":"FR",
    "sg:address":"Rte De Lugos 33770 Salles",
    "sg:city":"Salles",
    "sg:classifiers":[
        {
            "category":"Professional",
            "subcategory":"Engineering",
            "type":"Services"
        }
    ],
    "sg:phone":"+33 5 56 88 41 69",
    "sg:postcode":"33770",
    "sg:province":"Aquitaine",
    "sg:tags":[
        "machine",
        "-",
        "mechanical"
    ],
    "wof:name":"Gaudilliere Sarl",
    "wof:placetype":"venue"
},
  "geometry": {"coordinates":[-0.869998,44.552193],"type":"Point"}
}