{
  "type": "Feature",
  "properties": {
    "iso:country":"FR",
    "sg:address":"ZAC du Pont Loby",
    "sg:city":"Dunkerque",
    "sg:orig_category":"Non-Classified Establishments",
    "sg:phone":"+33 3 28 29 26 26",
    "sg:postcode":"59640",
    "sg:province":"Nord-Pas-de-Calais",
    "wof:name":"Facen S.a.",
    "wof:placetype":"venue"
},
  "geometry": {"coordinates":[2.34095,51.015747],"type":"Point"}
}