{
  "type": "Feature",
  "properties": {
    "addr:full":"Rue Henri Moissan 69491 Pierre Benite Languedoc-Roussillon",
    "addr:postcode":"69491",
    "addr:street":"Rue Henri Moissan;Pierre Benite",
    "iso:country":"FR",
    "sg:address":"Rue Henri Moissan 69491 Pierre Benite",
    "sg:classifiers":[
        {
            "category":"Manufacturing",
            "subcategory":"Chemicals & Compounds",
            "type":"Manufacturing & Wholesale Goods"
        }
    ],
    "sg:phone":"+33 4 72 39 80 00",
    "sg:province":"Languedoc-Roussillon",
    "sg:tags":[
        "pharmaceutical",
        "chemistry"
    ],
    "wof:name":"Atofina",
    "wof:placetype":"venue"
},
  "geometry": {"coordinates":[4.821248,45.709507],"type":"Point"}
}