{
  "type": "Feature",
  "properties": {
    "iso:country":"FR",
    "sg:address":"14, Rue Cruzin, 69120 Vaulx en Velin",
    "sg:orig_category":"Non-Classified Establishments",
    "sg:phone":"+33 4 78 79 29 79",
    "sg:postcode":"69120",
    "sg:province":"Rhone-Alpes",
    "wof:name":"E.t.p. S.a.r.l. - Etude En Tuyauterie Et Process",
    "wof:placetype":"venue"
},
  "geometry": {"coordinates":[4.916895,45.779022],"type":"Point"}
}