{
  "type": "Feature",
  "properties": {
    "addr:full":"all\u00e9e Gibel\u00e9ou 64100 Bayonne Bayonne Aquitaine 64100",
    "addr:postcode":"64100 bayonne;64100",
    "addr:street":"Alle\u0301E Gibele\u0301Ou",
    "iso:country":"FR",
    "sg:address":"all\u00e9e Gibel\u00e9ou 64100 Bayonne",
    "sg:city":"Bayonne",
    "sg:classifiers":[
        {
            "category":"Shopping",
            "subcategory":"Clothing, Apparel, & Fashions",
            "type":"Retail Goods"
        }
    ],
    "sg:phone":"+33 5 59 50 20 00",
    "sg:postcode":"64100",
    "sg:province":"Aquitaine",
    "sg:tags":[
        "sportswear"
    ],
    "wof:name":"Troiscentsoixante Sa",
    "wof:placetype":"venue"
},
  "geometry": {"coordinates":[-1.457024,43.491268],"type":"Point"}
}