{
  "type": "Feature",
  "properties": {
    "addr:full":"2 rue de Solf\u00e9rino 75007 Paris Ile de France 75007",
    "addr:housenumber":"2",
    "addr:postcode":"75007;75007",
    "addr:street":"Rue De Solfe\u0301Rino",
    "iso:country":"FR",
    "sg:address":"2 rue de Solf\u00e9rino 75007 Paris",
    "sg:classifiers":[
        {
            "category":"Insurance",
            "subcategory":"Insurance Agent",
            "type":"Services"
        }
    ],
    "sg:phone":"+33 1 44 11 77 00",
    "sg:postcode":"75007",
    "sg:province":"Ile de France",
    "sg:tags":[
        "alcohol"
    ],
    "wof:name":"Pr Europe-spirits & Wines Sa",
    "wof:placetype":"venue"
},
  "geometry": {"coordinates":[2.323835,48.860989],"type":"Point"}
}