{
  "type": "Feature",
  "properties": {
    "addr:full":"Rue De Marquillies 59480 La Bass\u00e9e Nord Pas-de-Calais 59480",
    "addr:postcode":"59480;59480",
    "addr:street":"Rue De Marquillies;Pas-De-Calais",
    "iso:country":"FR",
    "sg:address":"Rue De Marquillies 59480 La Bass\u00e9e",
    "sg:classifiers":[
        {
            "category":"Shopping",
            "type":"Retail Goods"
        }
    ],
    "sg:phone":"+33 3 20 29 98 50",
    "sg:postcode":"59480",
    "sg:province":"Nord Pas-de-Calais",
    "sg:tags":[
        "metallurgy",
        "finished",
        "-",
        "metalworking",
        "metallic"
    ],
    "wof:name":"Chaudronnerie Industrielle De La Bassee Sa",
    "wof:placetype":"venue"
},
  "geometry": {"coordinates":[2.81509,50.532192],"type":"Point"}
}