{
  "type": "Feature",
  "properties": {
    "addr:full":"Technoparc B\u00e2t. 3 Voie 5 31674 Lab\u00e8ge Cedex Lab\u00e8ge Midi Pyr\u00e9n\u00e9es 31670",
    "addr:housenumber":"3;5",
    "addr:postcode":"31674;31670",
    "addr:street":"Voie",
    "iso:country":"FR",
    "sg:address":"Technoparc B\u00e2t. 3 Voie 5 31674 Lab\u00e8ge Cedex",
    "sg:city":"Lab\u00e8ge",
    "sg:classifiers":[
        {
            "category":"Professional",
            "subcategory":"Business Services",
            "type":"Services"
        }
    ],
    "sg:phone":"+33 5 61 39 88 81",
    "sg:postcode":"31670",
    "sg:province":"Midi Pyr\u00e9n\u00e9es",
    "sg:tags":[
        "information",
        "advice",
        "technology",
        "software"
    ],
    "wof:name":"Labeo Sa",
    "wof:placetype":"venue"
},
  "geometry": {"coordinates":[1.527111,43.529713],"type":"Point"}
}