{
  "type": "Feature",
  "properties": {
    "addr:full":"Rte de Varennes Aubign\u00e9 Racan Pays de Loire 72800",
    "addr:postcode":"72800",
    "addr:street":"Rte De Varennes;Racan",
    "iso:country":"FR",
    "sg:address":"Rte de Varennes",
    "sg:city":"Aubign\u00e9 Racan",
    "sg:orig_category":"Non-Classified Establishments",
    "sg:phone":"+33 2 43 46 21 88",
    "sg:postcode":"72800",
    "sg:province":"Pays de Loire",
    "wof:name":"Arm\u00e9tal S.a.",
    "wof:placetype":"venue"
},
  "geometry": {"coordinates":[0.155365,47.608517],"type":"Point"}
}