{
  "type": "Feature",
  "properties": {
    "addr:full":"Les Hauts Rochers 35133 Saint Germain en Cogl\u00e8s Beauc\u00e9 Bretagne 35133",
    "addr:postcode":"35133;35133",
    "addr:street":"Les Hauts Rochers;Beauce\u0301 Bretagne",
    "iso:country":"FR",
    "sg:address":"Les Hauts Rochers 35133 Saint Germain en Cogl\u00e8s",
    "sg:city":"Beauc\u00e9",
    "sg:orig_category":"Non-Classified Establishments",
    "sg:phone":"+33 2 99 95 42 84",
    "sg:postcode":"35133",
    "sg:province":"Bretagne",
    "wof:name":"Etablissements Michel S.a.",
    "wof:placetype":"venue"
},
  "geometry": {"coordinates":[-1.25145,48.404819],"type":"Point"}
}