{
  "type": "Feature",
  "properties": {
    "addr:full":"3 pl de la R\u00e9publique; Eysines; 33320 Eysines Aquitaine 33320",
    "addr:housenumber":"3",
    "addr:postcode":"33320;33320",
    "addr:street":"Pl De La Re\u0301Publique",
    "iso:country":"FR",
    "sg:address":"3 pl de la R\u00e9publique; Eysines; 33320",
    "sg:city":"Eysines",
    "sg:classifiers":[
        {
            "category":"Banks & Credit Unions",
            "subcategory":"Bank",
            "type":"Services"
        }
    ],
    "sg:phone":"+33 3356282030",
    "sg:postcode":"33320",
    "sg:province":"Aquitaine",
    "wof:name":"Banque Nationale De Paris",
    "wof:placetype":"venue"
},
  "geometry": {"coordinates":[-0.651285,44.884655],"type":"Point"}
}