{
  "type": "Feature",
  "properties": {
    "iso:country":"FR",
    "sg:address":"3 pl de la R\u00e9publique; Eysines; 33320",
    "sg:city":"Eysines",
    "sg:classifiers":[
        {
            "category":"Banks & Credit Unions",
            "subcategory":"Bank",
            "type":"Services"
        }
    ],
    "sg:phone":"+33 3356282030",
    "sg:postcode":"33320",
    "sg:province":"Aquitaine",
    "wof:name":"Banque Nationale De Paris",
    "wof:placetype":"venue"
},
  "geometry": {"coordinates":[-0.651285,44.884655],"type":"Point"}
}