{
  "type": "Feature",
  "properties": {
    "iso:country":"FR",
    "sg:address":"B.P. 55, 01440 Viriat C\u00e9dex^^ZA les Baisses, 01440 Viriat",
    "sg:orig_category":"Non-Classified Establishments",
    "sg:phone":"+33 4 74 25 39 91",
    "sg:province":"Rhone-Alpes",
    "wof:name":"S.e.e.c. S.a. - Soci\u00e9t\u00e9 Europ\u00e9enne D'etiquetage Et De Conditionn",
    "wof:placetype":"venue"
},
  "geometry": {"coordinates":[5.216965,46.252529],"type":"Point"}
}