{
  "type": "Feature",
  "properties": {
    "addr:full":"route du Viala 34700 St Jean De La Blaquiere Languedoc-Roussillon",
    "addr:postcode":"34700",
    "addr:street":"Route Du Viala;Blaquiere",
    "iso:country":"FR",
    "sg:address":"route du Viala 34700 St Jean De La Blaquiere",
    "sg:classifiers":[
        {
            "category":"Wholesale",
            "subcategory":"Wine & Distilled Alcoholic Beverages",
            "type":"Manufacturing & Wholesale Goods"
        }
    ],
    "sg:phone":"+33 4 67 44 70 53",
    "sg:province":"Languedoc-Roussillon",
    "sg:tags":[
        "packaging"
    ],
    "wof:name":"Vinobag Sa",
    "wof:placetype":"venue"
},
  "geometry": {"coordinates":[3.421725,43.71413],"type":"Point"}
}