{
  "type": "Feature",
  "properties": {
    "addr:full":"16, All\u00e9e des Guionnes, 93240 Stains Ile de France",
    "addr:housenumber":"16",
    "addr:postcode":"93240;ile",
    "addr:street":"Alle\u0301E Des Guionnes",
    "iso:country":"FR",
    "sg:address":"16, All\u00e9e des Guionnes, 93240 Stains",
    "sg:orig_category":"Non-Classified Establishments",
    "sg:phone":"+33 1 48 26 62 68",
    "sg:province":"Ile de France",
    "wof:name":"Transports Yves Journaux S.a.",
    "wof:placetype":"venue"
},
  "geometry": {"coordinates":[2.39478,48.956223],"type":"Point"}
}