{
  "type": "Feature",
  "properties": {
    "addr:full":"36 Rue Des Grands Pr\u00e9s Montlu\u00e7on Auvergne 03100",
    "addr:housenumber":"36",
    "addr:postcode":"03100",
    "addr:street":"Rue Des Grands Pre\u0301S",
    "iso:country":"FR",
    "sg:address":"36 Rue Des Grands Pr\u00e9s",
    "sg:city":"Montlu\u00e7on",
    "sg:classifiers":[
        {
            "category":"Banks & Credit Unions",
            "subcategory":"Financial Services",
            "type":"Services"
        }
    ],
    "sg:phone":"+33 4 70 28 10 57",
    "sg:postcode":"03100",
    "sg:province":"Auvergne",
    "sg:tags":[
        "banking",
        "finance",
        "insurance"
    ],
    "wof:name":"S E C A C Societe D Expertise Comptable Et D Audit Du Centre Sa",
    "wof:placetype":"venue"
},
  "geometry": {"coordinates":[2.604712,46.335548],"type":"Point"}
}