{
  "type": "Feature",
  "properties": {
    "iso:country":"FR",
    "sg:address":"8, Rue Sylvestre, 69100 Villeurbanne",
    "sg:orig_category":"Unclassifiable Establishments",
    "sg:phone":"+33 4 72 74 44 63",
    "sg:province":"Rhone-Alpes",
    "wof:name":"Techni Lift S.a.",
    "wof:placetype":"venue"
},
  "geometry": {"coordinates":[4.865959,45.769043],"type":"Point"}
}