{
  "type": "Feature",
  "properties": {
    "addr:full":"22 Avenue Paul Langevin Ensemble Industriel N 1 95220 Herblay Ile de France 95220",
    "addr:housenumber":"22;1",
    "addr:postcode":"95220;ile;95220",
    "addr:street":"Avenue Paul Langevin;Industriel N;France",
    "iso:country":"FR",
    "sg:address":"22 Avenue Paul Langevin Ensemble Industriel N 1 95220 Herblay",
    "sg:classifiers":[
        {
            "category":"Professional",
            "subcategory":"Engineering",
            "type":"Services"
        }
    ],
    "sg:phone":"+33 1 34 50 09 09",
    "sg:postcode":"95220",
    "sg:province":"Ile de France",
    "sg:tags":[
        "machine",
        "-",
        "mechanical"
    ],
    "wof:name":"Distribution Sanitaire Chauffage (dsc)",
    "wof:placetype":"venue"
},
  "geometry": {"coordinates":[2.163532,48.989609],"type":"Point"}
}