{
  "type": "Feature",
  "properties": {
    "iso:country":"FR",
    "sg:address":"Centre Routier d'Agen",
    "sg:city":"Le Passage",
    "sg:orig_category":"Unclassifiable Establishments",
    "sg:phone":"+33 5 53 47 12 34",
    "sg:postcode":"47520",
    "sg:province":"Aquitaine",
    "wof:name":"Tucom S.a.",
    "wof:placetype":"venue"
},
  "geometry": {"coordinates":[0.60591,44.20142],"type":"Point"}
}