{
  "type": "Feature",
  "properties": {
    "addr:full":"30, Av. Gustave Eiffel, 33600 Pessac Pessac Aquitaine 33600",
    "addr:postcode":"33600;33600",
    "addr:street":"30 Av. Gustave Eiffel",
    "iso:country":"FR",
    "sg:address":"30, Av. Gustave Eiffel, 33600 Pessac",
    "sg:city":"Pessac",
    "sg:orig_category":"Unclassifiable Establishments",
    "sg:phone":"+33 5 57 26 38 90",
    "sg:postcode":"33600",
    "sg:province":"Aquitaine",
    "wof:name":"Eltek Technologie Semiconducteurs S.a.",
    "wof:placetype":"venue"
},
  "geometry": {"coordinates":[-0.651143,44.780758],"type":"Point"}
}