{
  "type": "Feature",
  "properties": {
    "addr:full":"Rte d'Auch - ZI Seissan Midi Pyr\u00e9n\u00e9es 32260",
    "addr:postcode":"32260",
    "addr:street":"Rte D'Auch Zi",
    "iso:country":"FR",
    "sg:address":"Rte d'Auch - ZI",
    "sg:city":"Seissan",
    "sg:orig_category":"Non-Classified Establishments",
    "sg:phone":"+33 5 62 66 28 62",
    "sg:postcode":"32260",
    "sg:province":"Midi Pyr\u00e9n\u00e9es",
    "wof:name":"So-di-gaz S.a.",
    "wof:placetype":"venue"
},
  "geometry": {"coordinates":[0.594375,43.496983],"type":"Point"}
}