{
  "type": "Feature",
  "properties": {
    "addr:full":"417, Rue L\u00e9on Blum, 34000 Montpellier Languedoc-Roussillon",
    "addr:housenumber":"417",
    "addr:postcode":"34000",
    "addr:street":"Rue Le\u0301On Blum",
    "iso:country":"FR",
    "sg:address":"417, Rue L\u00e9on Blum, 34000 Montpellier",
    "sg:orig_category":"Non-Classified Establishments",
    "sg:phone":"+33 4 67 99 35 39",
    "sg:province":"Languedoc-Roussillon",
    "wof:name":"First Copy",
    "wof:placetype":"venue"
},
  "geometry": {"coordinates":[3.890266,43.606602],"type":"Point"}
}