{
  "type": "Feature",
  "properties": {
    "iso:country":"FR",
    "sg:address":"9 Rue Jean Jaures 29000 Quimper",
    "sg:city":"Quimper",
    "sg:classifiers":[
        {
            "category":"Wholesale",
            "subcategory":"Medical Equipment & Supplies",
            "type":"Manufacturing & Wholesale Goods"
        }
    ],
    "sg:phone":"+33 2 98 90 19 67",
    "sg:postcode":"29000",
    "sg:province":"Bretagne",
    "sg:tags":[
        "instrument",
        "health",
        "-",
        "precision"
    ],
    "wof:name":"Martin",
    "wof:placetype":"venue"
},
  "geometry": {"coordinates":[-4.097098,47.993496],"type":"Point"}
}