{
  "type": "Feature",
  "properties": {
    "iso:country":"FR",
    "sg:address":"B.P. 25, 06511 Carros C\u00e9dex^^1\u00e8re Avenue 14\u00e9me Rue, 06510 Carros",
    "sg:orig_category":"Non-Classified Establishments",
    "sg:phone":"+33 4 93 29 11 29",
    "sg:province":"Corse",
    "wof:name":"Audemard S.a.",
    "wof:placetype":"venue"
},
  "geometry": {"coordinates":[7.17573,43.785782],"type":"Point"}
}