{
  "type": "Feature",
  "properties": {
    "iso:country":"FR",
    "sg:address":"BP 67 14000 Caen",
    "sg:city":"Caen",
    "sg:classifiers":[
        {
            "category":"Manufacturing",
            "subcategory":"Printing",
            "type":"Manufacturing & Wholesale Goods"
        }
    ],
    "sg:phone":"+33 2 31 70 88 10",
    "sg:postcode":"14000",
    "sg:province":"Basse Normandie",
    "sg:tags":[
        "publishing"
    ],
    "wof:name":"Normandie Information Impression",
    "wof:placetype":"venue"
},
  "geometry": {"coordinates":[-0.36111,49.184361],"type":"Point"}
}