{
  "type": "Feature",
  "properties": {
    "addr:full":"Bourdevaire 85110 Ste C\u00e9cile Pays de Loire 85110",
    "addr:postcode":"85110;85110",
    "addr:street":"Bourdevaire;Ce\u0301Cile",
    "iso:country":"FR",
    "sg:address":"Bourdevaire 85110 Ste C\u00e9cile",
    "sg:classifiers":[
        {
            "category":"Professional",
            "subcategory":"Business Services",
            "type":"Services"
        }
    ],
    "sg:phone":"+33 2 51 40 24 86",
    "sg:postcode":"85110",
    "sg:province":"Pays de Loire",
    "sg:tags":[
        "training",
        "advice"
    ],
    "wof:name":"Ecole College Et Lycee Prive L'esperance Bourdevaire",
    "wof:placetype":"venue"
},
  "geometry": {"coordinates":[-1.114309,46.712364],"type":"Point"}
}