{
  "type": "Feature",
  "properties": {
    "addr:full":"Les Moquets 71800 La Chapelle sous Dun Baudemont Bourgogne 71800",
    "addr:postcode":"71800;71800",
    "addr:street":"Dun",
    "iso:country":"FR",
    "sg:address":"Les Moquets 71800 La Chapelle sous Dun",
    "sg:city":"Baudemont",
    "sg:orig_category":"Unclassifiable Establishments",
    "sg:phone":"+33 3 85 28 03 32",
    "sg:postcode":"71800",
    "sg:province":"Bourgogne",
    "wof:name":"Thivent S.a.",
    "wof:placetype":"venue"
},
  "geometry": {"coordinates":[4.287948,46.26664],"type":"Point"}
}