{
  "type": "Feature",
  "properties": {
    "addr:full":"1, Bd de l'Oise - Immeuble Maradas, 95030 Cergy Pontoise C\u00e9dex Ile de France",
    "addr:housenumber":"1",
    "addr:postcode":"95030",
    "addr:street":"Bd De L'Oise",
    "iso:country":"FR",
    "sg:address":"1, Bd de l'Oise - Immeuble Maradas, 95030 Cergy Pontoise C\u00e9dex",
    "sg:orig_category":"Non-Classified Establishments",
    "sg:phone":"+33 1 30 73 45 65",
    "sg:province":"Ile de France",
    "wof:name":"M.s. Ambrogio France S.a.r.l.",
    "wof:placetype":"venue"
},
  "geometry": {"coordinates":[-121.988663,37.22607],"type":"Point"}
}