{
  "type": "Feature",
  "properties": {
    "iso:country":"FR",
    "sg:address":"Rue Claude Bernard",
    "sg:city":"Lavaur",
    "sg:orig_category":"Non-Classified Establishments",
    "sg:phone":"+33 5 63 83 10 09",
    "sg:postcode":"81500",
    "sg:province":"Midi Pyr\u00e9n\u00e9es",
    "wof:name":"S.i.a. S.a. - Soci\u00e9t\u00e9 D'imprimerie Artistique",
    "wof:placetype":"venue"
},
  "geometry": {"coordinates":[1.818965,43.70676],"type":"Point"}
}