{
  "type": "Feature",
  "properties": {
    "addr:full":"29 Boulevard Des Alpes Ctre Buro Club 38240 Meylan Rhone-Alpes 38240",
    "addr:housenumber":"29",
    "addr:postcode":"38240;38240",
    "addr:street":"Boulevard Des Alpes Ctre",
    "iso:country":"FR",
    "sg:address":"29 Boulevard Des Alpes Ctre Buro Club 38240 Meylan",
    "sg:classifiers":[
        {
            "category":"Manufacturing",
            "subcategory":"Wood Products",
            "type":"Manufacturing & Wholesale Goods"
        }
    ],
    "sg:phone":"+33 4 76 61 44 74",
    "sg:postcode":"38240",
    "sg:province":"Rhone-Alpes",
    "sg:tags":[
        "furniture"
    ],
    "wof:name":"Roneo",
    "wof:placetype":"venue"
},
  "geometry": {"coordinates":[5.77846,45.209316],"type":"Point"}
}