{
  "type": "Feature",
  "properties": {
    "addr:full":"Chemin Du Polygone Quai Castellamre 13250 St Chamas Midi Pyr\u00e9n\u00e9es",
    "addr:postcode":"13250",
    "addr:street":"Chemin Du Polygone Quai Castellamre",
    "iso:country":"FR",
    "sg:address":"Chemin Du Polygone Quai Castellamre 13250 St Chamas",
    "sg:classifiers":[
        {
            "category":"Utilities",
            "subcategory":"Electric",
            "type":"Services"
        }
    ],
    "sg:phone":"+33 4 90 50 99 00",
    "sg:province":"Midi Pyr\u00e9n\u00e9es",
    "sg:tags":[
        "electricity",
        "electronic",
        "electrical",
        "equipment"
    ],
    "wof:name":"Controle Electricite Etudes Et Maintenances Industrielles (ceemi)",
    "wof:placetype":"venue"
},
  "geometry": {"coordinates":[5.032915,43.550137],"type":"Point"}
}