{
  "type": "Feature",
  "properties": {
    "addr:full":"Le Bois De Chize 71500 Branges Branges Bourgogne 71500",
    "addr:postcode":"71500;71500",
    "addr:street":"Le Bois De Chize",
    "iso:country":"FR",
    "sg:address":"Le Bois De Chize 71500 Branges",
    "sg:city":"Branges",
    "sg:classifiers":[
        {
            "category":"Professional",
            "type":"Services"
        }
    ],
    "sg:phone":"+33 3 85 76 44 11",
    "sg:postcode":"71500",
    "sg:province":"Bourgogne",
    "sg:tags":[
        "transport",
        "road"
    ],
    "wof:name":"Dpsa Transports Prudent",
    "wof:placetype":"venue"
},
  "geometry": {"coordinates":[5.20029,46.663715],"type":"Point"}
}