{
  "type": "Feature",
  "properties": {
    "iso:country":"FR",
    "sg:address":"B.P. 48, 68220 H\u00e9singue^^Zone Industrielle, 68220 H\u00e9singue",
    "sg:city":"H\u00e9singue",
    "sg:orig_category":"Non-Classified Establishments",
    "sg:phone":"+33 3 89 70 27 27",
    "sg:postcode":"68220",
    "sg:province":"Alsace",
    "wof:name":"Cryostar France S.a.",
    "wof:placetype":"venue"
},
  "geometry": {"coordinates":[7.52344,47.561153],"type":"Point"}
}