{
  "type": "Feature",
  "properties": {
    "iso:country":"FR",
    "sg:address":"194, Av. du G\u00e9n\u00e9ral Leclerc, 78220 Viroflay",
    "sg:orig_category":"Unclassifiable Establishments",
    "sg:phone":"+33 1 30 24 10 33",
    "sg:province":"Ile de France",
    "wof:name":"Spot Hitec S.a.r.l.",
    "wof:placetype":"venue"
},
  "geometry": {"coordinates":[2.163388,48.801746],"type":"Point"}
}