{
  "type": "Feature",
  "properties": {
    "iso:country":"FR",
    "sg:address":"ZI Saint Joseph",
    "sg:city":"Manosque",
    "sg:orig_category":"Unclassifiable Establishments",
    "sg:phone":"+33 4 92 87 57 76",
    "sg:postcode":"04100",
    "sg:province":"Provence-Alpes-C\u00f4te d'Azur",
    "wof:name":"Jardiver Technic E.u.r.l.",
    "wof:placetype":"venue"
},
  "geometry": {"coordinates":[5.784205,43.831474],"type":"Point"}
}