{
  "type": "Feature",
  "properties": {
    "iso:country":"FR",
    "sg:address":"3, Av. de la Vieille France, 95380 Louvres",
    "sg:orig_category":"Unclassifiable Establishments",
    "sg:phone":"+33 1 30 29 10 07",
    "sg:province":"Ile de France",
    "wof:name":"Algety S.a.",
    "wof:placetype":"venue"
},
  "geometry": {"coordinates":[2.504108,49.043316],"type":"Point"}
}