{
  "type": "Feature",
  "properties": {
    "addr:full":"B.P. 13, 33870 Vayres^^Rte d'Izon, 33870 Vayres Vayres Aquitaine 33870",
    "addr:postcode":"33870;33870;33870",
    "addr:street":"B.P. 13;D'Izon",
    "iso:country":"FR",
    "sg:address":"B.P. 13, 33870 Vayres^^Rte d'Izon, 33870 Vayres",
    "sg:city":"Vayres",
    "sg:orig_category":"Non-Classified Establishments",
    "sg:phone":"+33 5 57 55 39 00",
    "sg:postcode":"33870",
    "sg:province":"Aquitaine",
    "wof:name":"Roncadin S.a.",
    "wof:placetype":"venue"
},
  "geometry": {"coordinates":[-0.31648,44.897469],"type":"Point"}
}