{
  "type": "Feature",
  "properties": {
    "iso:country":"FR",
    "sg:address":"Rue de la Plaine",
    "sg:city":"Leers",
    "sg:orig_category":"Unclassifiable Establishments",
    "sg:phone":"+33 3 20 80 72 00",
    "sg:postcode":"59115",
    "sg:province":"Nord Pas-de-Calais",
    "wof:name":"Luxor S.a.",
    "wof:placetype":"venue"
},
  "geometry": {"coordinates":[3.233725,50.67466],"type":"Point"}
}