{
  "type": "Feature",
  "properties": {
    "addr:full":"Rue James Watt - ZAC de Chanteloup Aulnay sous Bois Ile de France 93600",
    "addr:housenumber":"zac",
    "addr:postcode":"93600",
    "addr:street":"Rue James Watt;De Chanteloup",
    "iso:country":"FR",
    "sg:address":"Rue James Watt - ZAC de Chanteloup",
    "sg:city":"Aulnay sous Bois",
    "sg:orig_category":"Unclassifiable Establishments",
    "sg:phone":"+33 1 48 66 46 46",
    "sg:postcode":"93600",
    "sg:province":"Ile de France",
    "wof:name":"Planet Impression S.a.r.l.",
    "wof:placetype":"venue"
},
  "geometry": {"coordinates":[2.49124,48.927509],"type":"Point"}
}