{
  "type": "Feature",
  "properties": {
    "iso:country":"FR",
    "sg:address":"92707 Colombes C\u00e9dex^^18, Bd Louis Seguin, 92700 Colombes",
    "sg:orig_category":"Non-Classified Establishments",
    "sg:phone":"+33 1 41 30 50 10",
    "sg:province":"Ile de France",
    "wof:name":"Hispano Suiza S.a.",
    "wof:placetype":"venue"
},
  "geometry": {"coordinates":[2.252625,48.922081],"type":"Point"}
}