{
  "type": "Feature",
  "properties": {
    "addr:full":"6 Rue Viaduc 52140 Val De Meuse Champagne",
    "addr:housenumber":"6",
    "addr:postcode":"52140",
    "addr:street":"Rue Viaduc;Meuse",
    "iso:country":"FR",
    "sg:address":"6 Rue Viaduc 52140 Val De Meuse",
    "sg:classifiers":[
        {
            "category":"Home & Garden",
            "subcategory":"Furniture",
            "type":"Retail Goods"
        }
    ],
    "sg:phone":"+33 3 25 90 38 22",
    "sg:province":"Champagne",
    "sg:tags":[
        "wood"
    ],
    "wof:name":"Scierie Richardot Sarl",
    "wof:placetype":"venue"
},
  "geometry": {"coordinates":[5.551008,47.992123],"type":"Point"}
}