{
  "type": "Feature",
  "properties": {
    "addr:full":"Washington Plaza; Paris; 75408 Bretagne",
    "addr:postcode":"75408",
    "addr:street":"Paris",
    "iso:country":"FR",
    "sg:address":"Washington Plaza; Paris; 75408",
    "sg:classifiers":[
        {
            "category":"Banks & Credit Unions",
            "subcategory":"Bank",
            "type":"Services"
        }
    ],
    "sg:phone":"+33 14253834100",
    "sg:province":"Bretagne",
    "wof:name":"Banque Ibj (france) Sa",
    "wof:placetype":"venue"
},
  "geometry": {"coordinates":[2.3111,48.873241],"type":"Point"}
}