{
  "type": "Feature",
  "properties": {
    "addr:full":"Promenade Robert Schumann 06190 Roquebrune Cap Martin Midi Pyr\u00e9n\u00e9es",
    "addr:postcode":"06190",
    "addr:street":"Promenade;Schumann;Cap",
    "iso:country":"FR",
    "sg:address":"Promenade Robert Schumann 06190 Roquebrune Cap Martin",
    "sg:classifiers":[
        {
            "category":"Travel",
            "subcategory":"Hotels & Motels",
            "type":"Entertainment"
        }
    ],
    "sg:phone":"+33 4 93 35 91 43",
    "sg:province":"Midi Pyr\u00e9n\u00e9es",
    "sg:tags":[
        "hotels",
        "business",
        "restaurant"
    ],
    "wof:name":"Solenzara Bar Restaurant Sarl",
    "wof:placetype":"venue"
},
  "geometry": {"coordinates":[7.48445,43.761848],"type":"Point"}
}