{
  "type": "Feature",
  "properties": {
    "iso:country":"FR",
    "sg:address":"Zi Montredon Plaine Rn 11100 Montredon Des Corbi\u00e8res",
    "sg:classifiers":[
        {
            "category":"Professional",
            "type":"Services"
        }
    ],
    "sg:phone":"+33 4 68 41 79 50",
    "sg:province":"Languedoc-Roussillon",
    "sg:tags":[
        "transport",
        "road"
    ],
    "wof:name":"Nexia Sa",
    "wof:placetype":"venue"
},
  "geometry": {"coordinates":[2.927483,43.190941],"type":"Point"}
}