{
  "type": "Feature",
  "properties": {
    "addr:full":"5 Rue De Satao 64232 Lescar Aquitaine",
    "addr:housenumber":"5",
    "addr:postcode":"64232",
    "addr:street":"Rue De Satao",
    "iso:country":"FR",
    "sg:address":"5 Rue De Satao 64232 Lescar",
    "sg:classifiers":[
        {
            "category":"Utilities",
            "subcategory":"Electric",
            "type":"Services"
        }
    ],
    "sg:phone":"+33 5 59 81 32 00",
    "sg:province":"Aquitaine",
    "sg:tags":[
        "electricity",
        "electronic",
        "electrical",
        "equipment"
    ],
    "wof:name":"Schneider Electric Industrie Sa",
    "wof:placetype":"venue"
},
  "geometry": {"coordinates":[-0.43885,43.327915],"type":"Point"}
}