{
  "type": "Feature",
  "properties": {
    "addr:full":"1, Rue Val-Eglantier, 76170 Saint Nicolas de la Taille Haute Normandie",
    "addr:housenumber":"1",
    "addr:postcode":"76170",
    "addr:street":"Rue Val-Eglantier;Nicolas De La Taille Haute Normandie",
    "iso:country":"FR",
    "sg:address":"1, Rue Val-Eglantier, 76170 Saint Nicolas de la Taille",
    "sg:orig_category":"Non-Classified Establishments",
    "sg:phone":"+33 2 35 39 80 37",
    "sg:province":"Haute Normandie",
    "wof:name":"Hauchard Pierre S.a.",
    "wof:placetype":"venue"
},
  "geometry": {"coordinates":[0.470921,49.507622],"type":"Point"}
}