{
  "type": "Feature",
  "properties": {
    "addr:full":"Zi D'Occitanie 11300 Limoux Languedoc-Roussillon",
    "addr:postcode":"11300",
    "iso:country":"FR",
    "sg:address":"Zi D'Occitanie 11300 Limoux",
    "sg:classifiers":[
        {
            "category":"Manufacturing",
            "subcategory":"Paper Products",
            "type":"Manufacturing & Wholesale Goods"
        }
    ],
    "sg:phone":"+33 4 68 31 96 10",
    "sg:province":"Languedoc-Roussillon",
    "sg:tags":[
        "packaging",
        "material",
        "-",
        "cardboard"
    ],
    "wof:name":"Compagnie G\u00c9n\u00c9rale Francaise Cartonnage Imprimerie Cgfci",
    "wof:placetype":"venue"
},
  "geometry": {"coordinates":[2.199721,43.0574],"type":"Point"}
}