{
  "type": "Feature",
  "properties": {
    "iso:country":"FR",
    "sg:address":"B.P. 1",
    "sg:city":"Tressange C\u00e9dex^^Carreau de la Mine de Bure 57710 Tressange",
    "sg:orig_category":"Non-Classified Establishments",
    "sg:phone":"+33 3 82 91 85 55",
    "sg:postcode":"57710",
    "sg:province":"Lorraine",
    "wof:name":"Euro Industrie S.a.",
    "wof:placetype":"venue"
},
  "geometry": {"coordinates":[5.940475,49.416756],"type":"Point"}
}