{
  "type": "Feature",
  "properties": {
    "iso:country":"FR",
    "sg:address":"77, Bd Henri Becquerel - ZI des Touches, 53000 Laval",
    "sg:orig_category":"Unclassifiable Establishments",
    "sg:phone":"+33 2 43 53 63 71",
    "sg:province":"Pays de Loire",
    "wof:name":"C.g.e. Distribution",
    "wof:placetype":"venue"
},
  "geometry": {"coordinates":[-0.756451,48.036293],"type":"Point"}
}