{
  "type": "Feature",
  "properties": {
    "addr:full":"160 Route Des Pres Rollier Zac Des Bromines 74330 Sillingy Rhone-Alpes",
    "addr:housenumber":"160",
    "addr:postcode":"74330",
    "addr:street":"Route Des Pres Rollier Zac Des Bromines",
    "iso:country":"FR",
    "sg:address":"160 Route Des Pres Rollier Zac Des Bromines 74330 Sillingy",
    "sg:classifiers":[
        {
            "category":"Manufacturing",
            "subcategory":"Wood Products",
            "type":"Manufacturing & Wholesale Goods"
        }
    ],
    "sg:phone":"+33 4 50 22 68 75",
    "sg:province":"Rhone-Alpes",
    "sg:tags":[
        "professional",
        "furniture"
    ],
    "wof:name":"Sarl Avrillon Ebenisterie Agencement",
    "wof:placetype":"venue"
},
  "geometry": {"coordinates":[6.041031,45.898506],"type":"Point"}
}