{
  "type": "Feature",
  "properties": {
    "addr:full":"11 Avenue Des Alpes 06800 Cagnes Sur Mer Centre",
    "addr:housenumber":"11",
    "addr:postcode":"06800",
    "addr:street":"Avenue Des Alpes;Mer",
    "iso:country":"FR",
    "sg:address":"11 Avenue Des Alpes 06800 Cagnes Sur Mer",
    "sg:classifiers":[
        {
            "category":"Professional",
            "subcategory":"Business Services",
            "type":"Services"
        }
    ],
    "sg:phone":"+33 4 93 20 69 76",
    "sg:province":"Centre",
    "sg:tags":[
        "training",
        "advice"
    ],
    "wof:name":"Cours La Fontaine",
    "wof:placetype":"venue"
},
  "geometry": {"coordinates":[7.137415,43.659946],"type":"Point"}
}