{
  "type": "Feature",
  "properties": {
    "iso:country":"FR",
    "sg:address":"rue de Chorey 21200 Beaune",
    "sg:city":"Beaune",
    "sg:classifiers":[
        {
            "category":"Autos & Motor Vehicles",
            "subcategory":"Auto Supplies",
            "type":"Retail Goods"
        }
    ],
    "sg:phone":"+33 3 80 22 34 95",
    "sg:postcode":"21200",
    "sg:province":"Bourgogne",
    "sg:tags":[
        "machine",
        "filling",
        "sealing",
        "bottle"
    ],
    "wof:name":"Ste Bourguignonne D Embouteillage Sarl",
    "wof:placetype":"venue"
},
  "geometry": {"coordinates":[4.841229,47.027695],"type":"Point"}
}