{
  "type": "Feature",
  "properties": {
    "iso:country":"FR",
    "sg:address":"3, Rue Eug\u00e8ne et Armand Peugeot - Tour Corosa, 92500 Rueil Malmaison",
    "sg:orig_category":"Unclassifiable Establishments",
    "sg:phone":"+33 1 47 52 80 00",
    "sg:province":"Ile de France",
    "wof:name":"C\u00e9gelec S.a.",
    "wof:placetype":"venue"
},
  "geometry": {"coordinates":[2.172779,48.889957],"type":"Point"}
}