{
  "type": "Feature",
  "properties": {
    "addr:full":"16 Rue Bretueil 13001 Marseille Poitou-Charentes",
    "addr:housenumber":"16",
    "addr:postcode":"13001",
    "addr:street":"Rue Bretueil",
    "iso:country":"FR",
    "sg:address":"16 Rue Bretueil 13001 Marseille",
    "sg:classifiers":[
        {
            "category":"Banks & Credit Unions",
            "subcategory":"Financial Services",
            "type":"Services"
        }
    ],
    "sg:phone":"+33 4 91 33 80 90",
    "sg:province":"Poitou-Charentes",
    "sg:tags":[
        "banking",
        "finance",
        "insurance"
    ],
    "wof:name":"Navyclaim Sarl",
    "wof:placetype":"venue"
},
  "geometry": {"coordinates":[5.37496,43.291927],"type":"Point"}
}