{
  "type": "Feature",
  "properties": {
    "iso:country":"FR",
    "sg:address":"37150 Civray de Touraine",
    "sg:city":"Bl\u00e9r\u00e9",
    "sg:orig_category":"Unclassifiable Establishments",
    "sg:phone":"+33 2 47 23 82 82",
    "sg:postcode":"37150",
    "sg:province":"Centre",
    "wof:name":"Petitbon Et Fils S.a.r.l.",
    "wof:placetype":"venue"
},
  "geometry": {"coordinates":[1.03177,47.332954],"type":"Point"}
}