{
  "type": "Feature",
  "properties": {
    "iso:country":"FR",
    "sg:address":"B.P. 1204, 49312 Cholet C\u00e9dex^^31, Av. Tessoualle, 49300 Cholet",
    "sg:orig_category":"Non-Classified Establishments",
    "sg:phone":"+33 2 41 62 60 75",
    "sg:postcode":"49300",
    "sg:province":"Pays de Loire",
    "wof:name":"Algimouss S.a.",
    "wof:placetype":"venue"
},
  "geometry": {"coordinates":[-0.892689,46.99659],"type":"Point"}
}