{
  "type": "Feature",
  "properties": {
    "addr:full":"B.P. 65, 75050 Paris C\u00e9dex 01^^19, Rue des Capucines, 75001 Paris Ile de France 75001",
    "addr:housenumber":"01;^ 19",
    "addr:postcode":"75050;75001;75001",
    "addr:street":"B.P. 65;^;Rue Des Capucines",
    "iso:country":"FR",
    "sg:address":"B.P. 65, 75050 Paris C\u00e9dex 01^^19, Rue des Capucines, 75001 Paris",
    "sg:orig_category":"Non-Classified Establishments",
    "sg:phone":"+33 1 42 44 80 00",
    "sg:postcode":"75001",
    "sg:province":"Ile de France",
    "wof:name":"Ccf S.a. - Cr\u00e9dit Foncier De France",
    "wof:placetype":"venue"
},
  "geometry": {"coordinates":[2.34121,48.856926],"type":"Point"}
}