{
  "type": "Feature",
  "properties": {
    "addr:full":"Rue Jacques Brel - ZI 2 Prouvy Valenciennes Nord Pas-de-Calais 59309",
    "addr:housenumber":"2",
    "addr:postcode":"59309",
    "addr:street":"Rue Jacques Brel Zi",
    "iso:country":"FR",
    "sg:address":"Rue Jacques Brel - ZI 2 Prouvy",
    "sg:city":"Valenciennes",
    "sg:orig_category":"Unclassifiable Establishments",
    "sg:phone":"+33 3 27 21 06 00",
    "sg:postcode":"59309",
    "sg:province":"Nord Pas-de-Calais",
    "wof:name":"A.f.m. S.a.r.l. - Accessoires Fixation Mat\u00e9riel",
    "wof:placetype":"venue"
},
  "geometry": {"coordinates":[3.524105,50.358494],"type":"Point"}
}