{
  "type": "Feature",
  "properties": {
    "iso:country":"FR",
    "sg:address":"ZI des Serpoli\u00e8res",
    "sg:city":"Saint Romain de Jalionas",
    "sg:orig_category":"Non-Classified Establishments",
    "sg:phone":"+33 4 74 90 46 17",
    "sg:postcode":"38460",
    "sg:province":"Rhone-Alpes",
    "wof:name":"C.c.t.v. S.a.r.l. - Climatisation Chaudronnerie Tuyauterie Ventilatio",
    "wof:placetype":"venue"
},
  "geometry": {"coordinates":[5.218995,45.757172],"type":"Point"}
}