{
  "type": "Feature",
  "properties": {
    "iso:country":"FR",
    "sg:address":"34, All\u00e9e du Closeau - ZI des Richardets, 93160 Noisy le Grand",
    "sg:orig_category":"Unclassifiable Establishments",
    "sg:phone":"+33 1 43 03 03 03",
    "sg:province":"Ile de France",
    "wof:name":"Comitronic S.a.",
    "wof:placetype":"venue"
},
  "geometry": {"coordinates":[2.553644,48.848892],"type":"Point"}
}