{
  "type": "Feature",
  "properties": {
    "iso:country":"FR",
    "sg:address":"7 rue Jean Calvin; Amiens; 80000",
    "sg:classifiers":[
        {
            "category":"Banks & Credit Unions",
            "subcategory":"Bank",
            "type":"Services"
        }
    ],
    "sg:phone":"+33 22923219",
    "sg:postcode":"80000",
    "sg:province":"Picardie",
    "wof:name":"Sovac",
    "wof:placetype":"venue"
},
  "geometry": {"coordinates":[2.29265,49.895184],"type":"Point"}
}