{
  "type": "Feature",
  "properties": {
    "addr:full":"B\u00e2t. Ela Taill\u00e9e - Le Granier Villars Rhone-Alpes 42390",
    "addr:housenumber":"ba\u0302t",
    "addr:postcode":"42390",
    "iso:country":"FR",
    "sg:address":"B\u00e2t. Ela Taill\u00e9e - Le Granier",
    "sg:city":"Villars",
    "sg:orig_category":"Non-Classified Establishments",
    "sg:phone":"+33 4 77 79 91 86",
    "sg:postcode":"42390",
    "sg:province":"Rhone-Alpes",
    "wof:name":"Composit S.a.",
    "wof:placetype":"venue"
},
  "geometry": {"coordinates":[4.36256,45.465858],"type":"Point"}
}