{
  "type": "Feature",
  "properties": {
    "addr:full":"2, Rue du Bois Chaland, 91090 Lisses Ile de France",
    "addr:housenumber":"2",
    "addr:postcode":"91090;ile",
    "addr:street":"Rue Du Bois Chaland",
    "iso:country":"FR",
    "sg:address":"2, Rue du Bois Chaland, 91090 Lisses",
    "sg:orig_category":"Unclassifiable Establishments",
    "sg:phone":"+33 1 69 11 21 24",
    "sg:province":"Ile de France",
    "wof:name":"Brita France S.a.r.l.",
    "wof:placetype":"venue"
},
  "geometry": {"coordinates":[2.428643,48.606888],"type":"Point"}
}