{
  "type": "Feature",
  "properties": {
    "iso:country":"FR",
    "sg:address":"Rte D'Arthez 64170 Lacq",
    "sg:city":"Lacq",
    "sg:orig_category":"Mechanical Engineering - machines Metallurgy and Metalworking Plastics Rubber Rubber and Plastics Sh",
    "sg:phone":"+33 5 59 60 03 32",
    "sg:postcode":"64170",
    "sg:province":"Aquitaine",
    "wof:name":"Endel",
    "wof:placetype":"venue"
},
  "geometry": {"coordinates":[-0.638325,43.423576],"type":"Point"}
}