{
  "type": "Feature",
  "properties": {
    "iso:country":"FR",
    "sg:address":"Rue du Kemmel - ZI 3",
    "sg:city":"Armenti\u00e8res",
    "sg:orig_category":"Unclassifiable Establishments",
    "sg:phone":"+33 3 20 10 59 00",
    "sg:postcode":"59280",
    "sg:province":"Nord Pas-de-Calais",
    "wof:name":"Solaronics S.a.",
    "wof:placetype":"venue"
},
  "geometry": {"coordinates":[2.881701,50.686623],"type":"Point"}
}