{
  "type": "Feature",
  "properties": {
    "addr:full":"15 ave du Consul G\u00e9n\u00e9ral; Livry Gargan; 93190 Ile de France 93190",
    "addr:postcode":"93190 ile;france 93190",
    "addr:street":"15 Ave Du Consul Ge\u0301Ne\u0301Ral Livry",
    "iso:country":"FR",
    "sg:address":"15 ave du Consul G\u00e9n\u00e9ral; Livry Gargan; 93190",
    "sg:classifiers":[
        {
            "category":"Banks & Credit Unions",
            "subcategory":"Bank",
            "type":"Services"
        }
    ],
    "sg:phone":"+33 13306233",
    "sg:postcode":"93190",
    "sg:province":"Ile de France",
    "wof:name":"Soci\u00e9t\u00e9 G\u00e9n\u00e9rale",
    "wof:placetype":"venue"
},
  "geometry": {"coordinates":[2.536121,48.918381],"type":"Point"}
}