{
  "type": "Feature",
  "properties": {
    "addr:full":"Rue Jean-Baptiste Lebas - ZI du Ch\u00e2teau d'eau Auby Nord Pas-de-Calais 59950",
    "addr:postcode":"59950",
    "addr:street":"Rue Jean-Baptiste Lebas Zi Du Cha\u0302Teau D'Eau Auby Nord",
    "iso:country":"FR",
    "sg:address":"Rue Jean-Baptiste Lebas - ZI du Ch\u00e2teau d'eau",
    "sg:city":"Auby",
    "sg:orig_category":"Unclassifiable Establishments",
    "sg:phone":"+33 3 27 92 18 33",
    "sg:postcode":"59950",
    "sg:province":"Nord Pas-de-Calais",
    "wof:name":"Segula Industries S.a.",
    "wof:placetype":"venue"
},
  "geometry": {"coordinates":[3.066093,50.416393],"type":"Point"}
}