{
  "type": "Feature",
  "properties": {
    "addr:full":"15 Rue Esp\u00e9rance 08800 Les Hautes Rivi\u00e8res Deville Champagne 08800",
    "addr:housenumber":"15",
    "addr:postcode":"08800;08800",
    "addr:street":"Rue Espe\u0301Rance",
    "iso:country":"FR",
    "sg:address":"15 Rue Esp\u00e9rance 08800 Les Hautes Rivi\u00e8res",
    "sg:city":"Deville",
    "sg:classifiers":[
        {
            "category":"Manufacturing",
            "subcategory":"Tools & Machinery",
            "type":"Manufacturing & Wholesale Goods"
        }
    ],
    "sg:phone":"+33 3 24 53 42 40",
    "sg:postcode":"08800",
    "sg:province":"Champagne",
    "sg:tags":[
        "metallurgy",
        "metalworking"
    ],
    "wof:name":"Marcel Barteaux Sarl",
    "wof:placetype":"venue"
},
  "geometry": {"coordinates":[4.841681,49.879978],"type":"Point"}
}