{
  "type": "Feature",
  "properties": {
    "addr:full":"Av Santos Dumont 44860 St Aignan Pays de Loire",
    "addr:postcode":"44860",
    "addr:street":"Av Santos Dumont",
    "iso:country":"FR",
    "sg:address":"Av Santos Dumont 44860 St Aignan",
    "sg:classifiers":[
        {
            "category":"Banks & Credit Unions",
            "subcategory":"Investment Brokerage",
            "type":"Services"
        }
    ],
    "sg:phone":"+33 2 40 13 56 00",
    "sg:province":"Pays de Loire",
    "sg:tags":[
        "-",
        "transport",
        "related"
    ],
    "wof:name":"Ste Des Transports Graveleau Sa",
    "wof:placetype":"venue"
},
  "geometry": {"coordinates":[-1.537854,47.118416],"type":"Point"}
}