{
  "type": "Feature",
  "properties": {
    "addr:full":"102, Rue de l'Hommelet, 59100 Roubaix Nord Pas-de-Calais",
    "addr:housenumber":"102",
    "addr:postcode":"59100",
    "addr:street":"Rue De L'Hommelet",
    "iso:country":"FR",
    "sg:address":"102, Rue de l'Hommelet, 59100 Roubaix",
    "sg:orig_category":"Unclassifiable Establishments",
    "sg:phone":"+33 3 20 73 72 64",
    "sg:province":"Nord Pas-de-Calais",
    "wof:name":"Beuque Et Compagnie S.c.s. - Soci\u00e9t\u00e9 Commandite Simple",
    "wof:placetype":"venue"
},
  "geometry": {"coordinates":[3.160883,50.695164],"type":"Point"}
}