{
  "type": "Feature",
  "properties": {
    "iso:country":"FR",
    "sg:address":"2 Bd De La Lib\u00e9ration 93284 Saint-Denis",
    "sg:classifiers":[
        {
            "category":"Manufacturing",
            "subcategory":"Chemicals & Compounds",
            "type":"Manufacturing & Wholesale Goods"
        }
    ],
    "sg:phone":"+33 1 48 13 38 38",
    "sg:province":"Midi Pyr\u00e9n\u00e9es",
    "sg:tags":[
        "pharmaceutical",
        "chemistry",
        "-",
        "by-product"
    ],
    "wof:name":"Socomari (ste Commerciale Maritime)",
    "wof:placetype":"venue"
},
  "geometry": {"coordinates":[2.340813,48.928818],"type":"Point"}
}