{
  "type": "Feature",
  "properties": {
    "addr:full":"50 Rue De La Victoire 59137 Busigny Nord Pas-de-Calais",
    "addr:housenumber":"50",
    "addr:postcode":"59137",
    "addr:street":"Rue De La Victoire",
    "iso:country":"FR",
    "sg:address":"50 Rue De La Victoire 59137 Busigny",
    "sg:classifiers":[
        {
            "category":"Home & Garden",
            "subcategory":"Furniture",
            "type":"Retail Goods"
        }
    ],
    "sg:phone":"+33 3 27 85 71 39",
    "sg:province":"Nord Pas-de-Calais",
    "sg:tags":[
        "wood"
    ],
    "wof:name":"Sarl Messin Pruvot",
    "wof:placetype":"venue"
},
  "geometry": {"coordinates":[3.478217,50.037712],"type":"Point"}
}