{
  "type": "Feature",
  "properties": {
    "addr:full":"B.P. 20414, 57018 Metz C\u00e9dex 1^^47, Rue Haute Seille, 57070 Metz Lorraine",
    "addr:housenumber":"1 ^ ^ 47",
    "addr:postcode":"57018;57070",
    "addr:street":"Ce\u0301Dex;Rue Haute Seille",
    "iso:country":"FR",
    "sg:address":"B.P. 20414, 57018 Metz C\u00e9dex 1^^47, Rue Haute Seille, 57070 Metz",
    "sg:orig_category":"Non-Classified Establishments",
    "sg:phone":"+33 3 87 39 55 55",
    "sg:province":"Lorraine",
    "wof:name":"G.i.e. Batig\u00e8re",
    "wof:placetype":"venue"
},
  "geometry": {"coordinates":[6.202294,49.133659],"type":"Point"}
}