{
  "type": "Feature",
  "properties": {
    "iso:country":"FR",
    "sg:address":"108, Rue de la Lib\u00e9ration, 73300 Saint Jean de Maurienne",
    "sg:orig_category":"Unclassifiable Establishments",
    "sg:phone":"+33 820 33 79 61",
    "sg:postcode":"73300",
    "sg:province":"Rhone-Alpes",
    "wof:name":"B.p.s.",
    "wof:placetype":"venue"
},
  "geometry": {"coordinates":[6.344526,45.27829],"type":"Point"}
}