{
  "type": "Feature",
  "properties": {
    "addr:full":"ZA l'Aulnay Le Pin en Mauges Pays de Loire 49110",
    "addr:postcode":"49110",
    "addr:street":"Za L'Aulnay",
    "iso:country":"FR",
    "sg:address":"ZA l'Aulnay",
    "sg:city":"Le Pin en Mauges",
    "sg:orig_category":"Unclassifiable Establishments",
    "sg:phone":"+33 2 41 70 00 23",
    "sg:postcode":"49110",
    "sg:province":"Pays de Loire",
    "wof:name":"Veron - Diet Et Compagnie S.a.r.l.",
    "wof:placetype":"venue"
},
  "geometry": {"coordinates":[-1.083335,47.254768],"type":"Point"}
}