{
  "type": "Feature",
  "properties": {
    "addr:full":"167 avenue du G\u00e9n\u00e9ral Leclerc 33600 Pessac Pessac Aquitaine 33600",
    "addr:housenumber":"167",
    "addr:postcode":"33600;33600",
    "addr:street":"Avenue Du Ge\u0301Ne\u0301Ral Leclerc",
    "iso:country":"FR",
    "sg:address":"167 avenue du G\u00e9n\u00e9ral Leclerc 33600 Pessac",
    "sg:city":"Pessac",
    "sg:classifiers":[
        {
            "category":"Transit Center",
            "subcategory":"Freight",
            "type":"Transportation"
        }
    ],
    "sg:phone":"+33 5 56 07 67 08",
    "sg:postcode":"33600",
    "sg:province":"Aquitaine",
    "sg:tags":[
        "towing",
        "trailer"
    ],
    "wof:name":"Sud Ouest Remorques Sa",
    "wof:placetype":"venue"
},
  "geometry": {"coordinates":[-0.683372,44.78479],"type":"Point"}
}