{
  "type": "Feature",
  "properties": {
    "addr:full":"48 Av Leon Crete 78490 Mere Ile de France 78490",
    "addr:postcode":"78490;france 78490",
    "addr:street":"48 Av Leon Crete",
    "iso:country":"FR",
    "sg:address":"48 Av Leon Crete 78490 Mere",
    "sg:classifiers":[
        {
            "category":"Manufacturing",
            "subcategory":"Tools & Machinery",
            "type":"Manufacturing & Wholesale Goods"
        }
    ],
    "sg:phone":"+33 1 34 86 22 22",
    "sg:postcode":"78490",
    "sg:province":"Ile de France",
    "sg:tags":[
        "metallurgy",
        "metalworking"
    ],
    "wof:name":"Mecanindus",
    "wof:placetype":"venue"
},
  "geometry": {"coordinates":[1.813523,48.791679],"type":"Point"}
}