{
  "type": "Feature",
  "properties": {
    "addr:full":"B.P. 5, 01350 Culoz^^Parc d'Activit\u00e9s Economique des Fours, 01350 Culoz Rhone-Alpes 01350",
    "addr:housenumber":"5",
    "addr:postcode":"01350;01350;01350",
    "addr:street":"B.P.;Rhone-Alpes",
    "iso:country":"FR",
    "sg:address":"B.P. 5, 01350 Culoz^^Parc d'Activit\u00e9s Economique des Fours, 01350 Culoz",
    "sg:orig_category":"Non-Classified Establishments",
    "sg:phone":"+33 4 79 87 02 75",
    "sg:postcode":"01350",
    "sg:province":"Rhone-Alpes",
    "wof:name":"Beguet C.m.t.c. S.a.",
    "wof:placetype":"venue"
},
  "geometry": {"coordinates":[5.772151,45.844227],"type":"Point"}
}