{
  "type": "Feature",
  "properties": {
    "addr:full":"43, Bd Winston Churchill, 72000 Le Mans Pays de Loire 72000",
    "addr:housenumber":"43",
    "addr:postcode":"72000;72000",
    "addr:street":"Bd Winston Churchill",
    "iso:country":"FR",
    "sg:address":"43, Bd Winston Churchill, 72000 Le Mans",
    "sg:orig_category":"Non-Classified Establishments",
    "sg:phone":"+33 2 43 50 22 30",
    "sg:postcode":"72000",
    "sg:province":"Pays de Loire",
    "wof:name":"Centre Technique De L'apave Nord-ouest S.a.",
    "wof:placetype":"venue"
},
  "geometry": {"coordinates":[0.218782,47.99041],"type":"Point"}
}