{
  "type": "Feature",
  "properties": {
    "iso:country":"FR",
    "sg:address":"18 rue du Docteur Gerard; Beauvais; 60000",
    "sg:classifiers":[
        {
            "category":"Banks & Credit Unions",
            "subcategory":"Bank",
            "type":"Services"
        }
    ],
    "sg:phone":"+33 3344485217",
    "sg:postcode":"60000",
    "sg:province":"Picardie",
    "wof:name":"Banque Nationale De Paris",
    "wof:placetype":"venue"
},
  "geometry": {"coordinates":[2.07999,49.430008],"type":"Point"}
}