{
  "type": "Feature",
  "properties": {
    "iso:country":"FR",
    "sg:address":"5, Rue des Grouaches - ZI, 28630 Sours",
    "sg:city":"Sours",
    "sg:orig_category":"Non-Classified Establishments",
    "sg:phone":"+33 2 37 25 77 83",
    "sg:postcode":"28630",
    "sg:province":"Centre",
    "wof:name":"Prodex S.a.r.l.",
    "wof:placetype":"venue"
},
  "geometry": {"coordinates":[1.49045,48.429531],"type":"Point"}
}