{
  "type": "Feature",
  "properties": {
    "iso:country":"FR",
    "sg:address":"11, Av. du G\u00e9n\u00e9ral Leclerc, 65112 Cauterets C\u00e9dex",
    "sg:city":"Cauterets",
    "sg:orig_category":"Non-Classified Establishments",
    "sg:phone":"+33 5 62 92 60 00",
    "sg:postcode":"65110",
    "sg:province":"Midi Pyr\u00e9n\u00e9es",
    "wof:name":"Sopytel",
    "wof:placetype":"venue"
},
  "geometry": {"coordinates":[-0.114187,42.889942],"type":"Point"}
}