{
  "type": "Feature",
  "properties": {
    "iso:country":"FR",
    "sg:address":"39ter, Rue Voltaire, 59116 Houplines",
    "sg:orig_category":"Unclassifiable Establishments",
    "sg:phone":"+33 3 20 77 29 21",
    "sg:province":"Nord Pas-de-Calais",
    "wof:name":"Carpentier Haviez S.a.r.l.",
    "wof:placetype":"venue"
},
  "geometry": {"coordinates":[2.899768,50.690647],"type":"Point"}
}