{
  "type": "Feature",
  "properties": {
    "addr:full":"2 Rue Du Repos 75020 Paris Ile de France 75020",
    "addr:housenumber":"2",
    "addr:postcode":"75020;75020",
    "addr:street":"Rue Du Repos",
    "iso:country":"FR",
    "sg:address":"2 Rue Du Repos 75020 Paris",
    "sg:classifiers":[
        {
            "category":"Professional",
            "subcategory":"Advertising",
            "type":"Services"
        }
    ],
    "sg:phone":"+33 1 40 09 77 12",
    "sg:postcode":"75020",
    "sg:province":"Ile de France",
    "sg:tags":[
        "communication",
        "medium"
    ],
    "wof:name":"Artifica Multimedia",
    "wof:placetype":"venue"
},
  "geometry": {"coordinates":[2.392177,48.858025],"type":"Point"}
}