{
  "type": "Feature",
  "properties": {
    "iso:country":"FR",
    "sg:address":"Rue Du Docteur Robin Centre Commercial Du Nautisme 83400 Hyeres",
    "sg:classifiers":[
        {
            "category":"Professional",
            "type":"Services"
        }
    ],
    "sg:phone":"+33 4 94 01 47 30",
    "sg:province":"Pays de Loire",
    "sg:tags":[
        "transport"
    ],
    "wof:name":"Hexavoile",
    "wof:placetype":"venue"
},
  "geometry": {"coordinates":[6.155135,43.029346],"type":"Point"}
}