{
  "type": "Feature",
  "properties": {
    "iso:country":"FR",
    "sg:address":"27 Avenue Felix Louat 60300 Senlis",
    "sg:classifiers":[
        {
            "category":"Park",
            "type":"Public Place"
        }
    ],
    "sg:phone":"+33 3 44 53 83 88",
    "sg:postcode":"60300",
    "sg:province":"Picardie",
    "sg:tags":[
        "work",
        "construction",
        "sport"
    ],
    "wof:name":"Aquavite",
    "wof:placetype":"venue"
},
  "geometry": {"coordinates":[2.602699,49.203327],"type":"Point"}
}