{
  "type": "Feature",
  "properties": {
    "addr:full":"27 Avenue Felix Louat 60300 Senlis Picardie 60300",
    "addr:housenumber":"27",
    "addr:postcode":"60300;60300",
    "addr:street":"Avenue Felix Louat",
    "iso:country":"FR",
    "sg:address":"27 Avenue Felix Louat 60300 Senlis",
    "sg:classifiers":[
        {
            "category":"Park",
            "type":"Public Place"
        }
    ],
    "sg:phone":"+33 3 44 53 83 88",
    "sg:postcode":"60300",
    "sg:province":"Picardie",
    "sg:tags":[
        "work",
        "construction",
        "sport"
    ],
    "wof:name":"Aquavite",
    "wof:placetype":"venue"
},
  "geometry": {"coordinates":[2.602699,49.203327],"type":"Point"}
}