{
  "type": "Feature",
  "properties": {
    "addr:full":"ZA K\u00e9rabraham Questembert Bretagne 56230",
    "addr:postcode":"56230",
    "addr:street":"Za Ke\u0301Rabraham Questembert Bretagne",
    "iso:country":"FR",
    "sg:address":"ZA K\u00e9rabraham",
    "sg:city":"Questembert",
    "sg:orig_category":"Unclassifiable Establishments",
    "sg:phone":"+33 2 97 26 56 56",
    "sg:postcode":"56230",
    "sg:province":"Bretagne",
    "wof:name":"Plastigraf S.a.r.l.",
    "wof:placetype":"venue"
},
  "geometry": {"coordinates":[-2.452149,47.660885],"type":"Point"}
}