{
  "type": "Feature",
  "properties": {
    "iso:country":"FR",
    "sg:address":"19, Rue Gay Lussac, 94438 Chennevi\u00e8res sur Marne C\u00e9dex",
    "sg:orig_category":"Non-Classified Establishments",
    "sg:phone":"+33 1 45 76 69 92",
    "sg:province":"Midi Pyr\u00e9n\u00e9es",
    "wof:name":"Dialog S.a.",
    "wof:placetype":"venue"
},
  "geometry": {"coordinates":[2.542441,48.795429],"type":"Point"}
}