{
  "type": "Feature",
  "properties": {
    "addr:full":"10, Chemin de l'Isle Vert - La Gaillardi\u00e8re , 41150 Chouzy sur Cisse Chouzy-sur-Cisse Centre 41150",
    "addr:housenumber":"10;chouzy-sur-cisse",
    "addr:postcode":"41150;41150",
    "addr:street":"Chemin De L'Isle Vert La Gaillardie\u0300Re",
    "iso:country":"FR",
    "sg:address":"10, Chemin de l'Isle Vert - La Gaillardi\u00e8re , 41150 Chouzy sur Cisse",
    "sg:city":"Chouzy-sur-Cisse",
    "sg:orig_category":"Unclassifiable Establishments",
    "sg:phone":"+33 2 54 20 48 33",
    "sg:postcode":"41150",
    "sg:province":"Centre",
    "wof:name":"Soci\u00e9t\u00e9 Delanoue S.a.r.l.",
    "wof:placetype":"venue"
},
  "geometry": {"coordinates":[1.262093,47.533382],"type":"Point"}
}