{
  "type": "Feature",
  "properties": {
    "addr:full":"43150 Freycenet La Tour Les Estables Auvergne 43150",
    "addr:housenumber":"43150",
    "addr:postcode":"43150",
    "addr:street":"Freycenet La Tour Les Estables",
    "iso:country":"FR",
    "sg:address":"43150 Freycenet La Tour",
    "sg:city":"Les Estables",
    "sg:classifiers":[
        {
            "category":"Professional",
            "subcategory":"Engineering",
            "type":"Services"
        }
    ],
    "sg:phone":"+33 4 71 03 80 82",
    "sg:postcode":"43150",
    "sg:province":"Auvergne",
    "sg:tags":[
        "machine",
        "-",
        "mechanical"
    ],
    "wof:name":"Salaisons Nicolas Freres",
    "wof:placetype":"venue"
},
  "geometry": {"coordinates":[4.059525,44.938171],"type":"Point"}
}