{
  "type": "Feature",
  "properties": {
    "addr:full":"Le Costet 88400 Gerardmer Lorraine",
    "addr:postcode":"88400",
    "iso:country":"FR",
    "sg:address":"Le Costet 88400 Gerardmer",
    "sg:classifiers":[
        {
            "category":"Shopping",
            "subcategory":"Crafts & Fabrics",
            "type":"Retail Goods"
        }
    ],
    "sg:phone":"+33 3 29 63 04 42",
    "sg:province":"Lorraine",
    "sg:tags":[
        "textile",
        "bleaching"
    ],
    "wof:name":"Paul Doridant Et Compagnie S.a.",
    "wof:placetype":"venue"
},
  "geometry": {"coordinates":[6.886855,48.061665],"type":"Point"}
}