{
  "type": "Feature",
  "properties": {
    "addr:full":"9, Rue de Fos sur Mer, 69007 Lyon Rhone-Alpes 69007",
    "addr:housenumber":"9",
    "addr:postcode":"69007;69007",
    "addr:street":"Rue De Fos;Mer",
    "iso:country":"FR",
    "sg:address":"9, Rue de Fos sur Mer, 69007 Lyon",
    "sg:orig_category":"Unclassifiable Establishments",
    "sg:phone":"+33 4 72 73 00 54",
    "sg:postcode":"69007",
    "sg:province":"Rhone-Alpes",
    "wof:name":"Santelli S.a.",
    "wof:placetype":"venue"
},
  "geometry": {"coordinates":[4.840445,45.722317],"type":"Point"}
}