{
  "type": "Feature",
  "properties": {
    "addr:full":"Beausoleil 14290 La Vespi\u00e8re La Vespi\u00e8re Basse Normandie 14290",
    "addr:postcode":"14290;14290",
    "addr:street":"Beausoleil",
    "iso:country":"FR",
    "sg:address":"Beausoleil 14290 La Vespi\u00e8re",
    "sg:city":"La Vespi\u00e8re",
    "sg:classifiers":[
        {
            "category":"Professional",
            "subcategory":"Engineering",
            "type":"Services"
        }
    ],
    "sg:phone":"+33 2 31 48 54 80",
    "sg:postcode":"14290",
    "sg:province":"Basse Normandie",
    "sg:tags":[
        "machine",
        "-",
        "mechanical"
    ],
    "wof:name":"Fevi International",
    "wof:placetype":"venue"
},
  "geometry": {"coordinates":[0.419651,49.024784],"type":"Point"}
}