{
  "type": "Feature",
  "properties": {
    "addr:full":"37, Rte de Lyon, 69530 Orli\u00e9nas Rhone-Alpes",
    "addr:housenumber":"37",
    "addr:postcode":"69530",
    "addr:street":"Rte De Lyon",
    "iso:country":"FR",
    "sg:address":"37, Rte de Lyon, 69530 Orli\u00e9nas",
    "sg:orig_category":"Non-Classified Establishments",
    "sg:phone":"+33 4 78 05 08 08",
    "sg:province":"Rhone-Alpes",
    "wof:name":"Antartic S.a.r.l.",
    "wof:placetype":"venue"
},
  "geometry": {"coordinates":[4.749285,45.652809],"type":"Point"}
}