{
  "type": "Feature",
  "properties": {
    "iso:country":"FR",
    "sg:address":"37, Rte de Lyon, 69530 Orli\u00e9nas",
    "sg:orig_category":"Non-Classified Establishments",
    "sg:phone":"+33 4 78 05 08 08",
    "sg:province":"Rhone-Alpes",
    "wof:name":"Antartic S.a.r.l.",
    "wof:placetype":"venue"
},
  "geometry": {"coordinates":[4.749285,45.652809],"type":"Point"}
}