{
  "type": "Feature",
  "properties": {
    "iso:country":"FR",
    "sg:address":"4, Impasse Denis Papin, 69740 Genas",
    "sg:orig_category":"Unclassifiable Establishments",
    "sg:phone":"+33 4 72 79 02 50",
    "sg:postcode":"69740",
    "sg:province":"Rhone-Alpes",
    "wof:name":"Motovario S.a.",
    "wof:placetype":"venue"
},
  "geometry": {"coordinates":[4.97912,45.723656],"type":"Point"}
}