{
  "type": "Feature",
  "properties": {
    "addr:full":"Rue Jean Charles Chevillotte Brest Bretagne 29200",
    "addr:postcode":"29200",
    "addr:street":"Rue Jean Charles Chevillotte;Bretagne",
    "iso:country":"FR",
    "sg:address":"Rue Jean Charles Chevillotte",
    "sg:city":"Brest",
    "sg:orig_category":"Non-Classified Establishments",
    "sg:phone":"+33 2 98 80 03 30",
    "sg:postcode":"29200",
    "sg:province":"Bretagne",
    "wof:name":"Brest R\u00e9cup\u00e9ration S.a.",
    "wof:placetype":"venue"
},
  "geometry": {"coordinates":[-4.45517,48.388462],"type":"Point"}
}