{
  "type": "Feature",
  "properties": {
    "iso:country":"FR",
    "sg:address":"B.P. 109, 27110 Le Neubourg^^56, Rue de la R\u00e9publique, 27110 Le Neubourg",
    "sg:orig_category":"Non-Classified Establishments",
    "sg:phone":"+33 2 32 35 03 32",
    "sg:postcode":"27110",
    "sg:province":"Haute Normandie",
    "wof:name":"Andr\u00e9 Service Imprimerie S.a.r.l.",
    "wof:placetype":"venue"
},
  "geometry": {"coordinates":[0.940293,49.089191],"type":"Point"}
}