{
  "type": "Feature",
  "properties": {
    "addr:full":"21, Rue Amp\u00e8re, 69680 Chassieu Rhone-Alpes",
    "addr:housenumber":"21",
    "addr:postcode":"69680",
    "addr:street":"Rue Ampe\u0300Re",
    "iso:country":"FR",
    "sg:address":"21, Rue Amp\u00e8re, 69680 Chassieu",
    "sg:orig_category":"Unclassifiable Establishments",
    "sg:phone":"+33 4 72 22 96 03",
    "sg:province":"Rhone-Alpes",
    "wof:name":"Hyster Centre Sud Est S.a.",
    "wof:placetype":"venue"
},
  "geometry": {"coordinates":[4.975639,45.730896],"type":"Point"}
}