{
  "type": "Feature",
  "properties": {
    "iso:country":"FR",
    "sg:address":"21, Rue Amp\u00e8re, 69680 Chassieu",
    "sg:orig_category":"Unclassifiable Establishments",
    "sg:phone":"+33 4 72 22 96 03",
    "sg:province":"Rhone-Alpes",
    "wof:name":"Hyster Centre Sud Est S.a.",
    "wof:placetype":"venue"
},
  "geometry": {"coordinates":[4.975639,45.730896],"type":"Point"}
}