{
  "type": "Feature",
  "properties": {
    "addr:full":"16, Rue de la Grenouill\u00e8re, 01000 Bourg en Bresse Rhone-Alpes",
    "addr:housenumber":"16",
    "addr:postcode":"01000",
    "addr:street":"Rue De La Grenouille\u0300Re",
    "iso:country":"FR",
    "sg:address":"16, Rue de la Grenouill\u00e8re, 01000 Bourg en Bresse",
    "sg:orig_category":"Unclassifiable Establishments",
    "sg:phone":"+33 4 74 23 10 77",
    "sg:province":"Rhone-Alpes",
    "wof:name":"Seda S.a.",
    "wof:placetype":"venue"
},
  "geometry": {"coordinates":[5.226269,46.208324],"type":"Point"}
}