{
  "type": "Feature",
  "properties": {
    "addr:full":"B.P. 303, 59813 Lesquin C\u00e9dex^^Rue des Farnards - Acticentre, 59813 Lesquin Languedoc-Roussillon",
    "addr:housenumber":"b.p. 303",
    "addr:postcode":"59813;59813",
    "addr:street":"Acticentre",
    "iso:country":"FR",
    "sg:address":"B.P. 303, 59813 Lesquin C\u00e9dex^^Rue des Farnards - Acticentre, 59813 Lesquin",
    "sg:orig_category":"Non-Classified Establishments",
    "sg:phone":"+33 3 20 87 00 40",
    "sg:province":"Languedoc-Roussillon",
    "wof:name":"S.a.f. S.a. - La Soudure Autog\u00e8ne Fran\u00e7aise",
    "wof:placetype":"venue"
},
  "geometry": {"coordinates":[3.11003,50.588009],"type":"Point"}
}