{
  "type": "Feature",
  "properties": {
    "addr:full":"93 Av Progr\u00e8s 69680 Chassieu Rhone-Alpes 69680",
    "addr:postcode":"69680;69680",
    "addr:street":"93 Av Progre\u0300S",
    "iso:country":"FR",
    "sg:address":"93 Av Progr\u00e8s 69680 Chassieu",
    "sg:classifiers":[
        {
            "category":"Professional",
            "subcategory":"Advertising",
            "type":"Services"
        }
    ],
    "sg:phone":"+33 4 72 22 23 23",
    "sg:postcode":"69680",
    "sg:province":"Rhone-Alpes",
    "sg:tags":[
        "information",
        "medium",
        "communication"
    ],
    "wof:name":"Progres",
    "wof:placetype":"venue"
},
  "geometry": {"coordinates":[4.96213,45.723907],"type":"Point"}
}