{
  "type": "Feature",
  "properties": {
    "addr:full":"39, Quai des Canotiers, 59200 Tourcoing Nord Pas-de-Calais",
    "addr:housenumber":"39",
    "addr:postcode":"59200",
    "addr:street":"Quai Des Canotiers",
    "iso:country":"FR",
    "sg:address":"39, Quai des Canotiers, 59200 Tourcoing",
    "sg:orig_category":"Unclassifiable Establishments",
    "sg:phone":"+33 3 20 76 93 00",
    "sg:province":"Nord Pas-de-Calais",
    "wof:name":"Vermeulen Mat\u00e9riaux S.a.",
    "wof:placetype":"venue"
},
  "geometry": {"coordinates":[3.146718,50.693878],"type":"Point"}
}