{
  "type": "Feature",
  "properties": {
    "addr:full":"ZA Champs de Letraye Cleurie Lorraine 88120",
    "addr:postcode":"88120",
    "addr:street":"Za Champs De Letraye Cleurie Lorraine",
    "iso:country":"FR",
    "sg:address":"ZA Champs de Letraye",
    "sg:city":"Cleurie",
    "sg:orig_category":"Non-Classified Establishments",
    "sg:phone":"+33 3 29 28 88 88",
    "sg:postcode":"88120",
    "sg:province":"Lorraine",
    "wof:name":"Enrulec S.a.",
    "wof:placetype":"venue"
},
  "geometry": {"coordinates":[6.693268,48.058903],"type":"Point"}
}