{
  "type": "Feature",
  "properties": {
    "addr:full":"35, Bd de la Barrasse, 13011 Marseille Provence-Alpes-C\u00f4te d'Azur",
    "addr:housenumber":"35",
    "addr:postcode":"13011",
    "addr:street":"Bd De La Barrasse",
    "iso:country":"FR",
    "sg:address":"35, Bd de la Barrasse, 13011 Marseille",
    "sg:orig_category":"Unclassifiable Establishments",
    "sg:phone":"+33 4 91 18 24 45",
    "sg:province":"Provence-Alpes-C\u00f4te d'Azur",
    "wof:name":"Cisametal S.a.",
    "wof:placetype":"venue"
},
  "geometry": {"coordinates":[5.476692,43.286366],"type":"Point"}
}