{
  "type": "Feature",
  "properties": {
    "iso:country":"FR",
    "sg:address":"Rue Fran\u00e7ois Arago - ZI",
    "sg:city":"Royan",
    "sg:orig_category":"Unclassifiable Establishments",
    "sg:phone":"+33 5 46 05 82 64",
    "sg:postcode":"17200",
    "sg:province":"Poitou-Charentes",
    "wof:name":"B\u00e9tons Libaud S.a.",
    "wof:placetype":"venue"
},
  "geometry": {"coordinates":[-1.030124,45.626137],"type":"Point"}
}