{
  "type": "Feature",
  "properties": {
    "iso:country":"FR",
    "sg:address":"Ld Zone Industrielle 90800 Argi\u00e9sans",
    "sg:classifiers":[
        {
            "category":"Professional",
            "type":"Services"
        }
    ],
    "sg:phone":"+33 3 84 28 59 89",
    "sg:province":"Franche Comt\u00e9",
    "sg:tags":[
        "transport",
        "road"
    ],
    "wof:name":"Transports Jordan",
    "wof:placetype":"venue"
},
  "geometry": {"coordinates":[6.833895,47.620541],"type":"Point"}
}