{
  "type": "Feature",
  "properties": {
    "addr:full":"5 R De La Source 57470 Hombourg Haut Lorraine 57470",
    "addr:housenumber":"5",
    "addr:postcode":"57470;57470",
    "addr:street":"R De La Source;Haut Lorraine",
    "iso:country":"FR",
    "sg:address":"5 R De La Source 57470 Hombourg Haut",
    "sg:classifiers":[
        {
            "category":"Wholesale",
            "subcategory":"Medical Equipment & Supplies",
            "type":"Manufacturing & Wholesale Goods"
        }
    ],
    "sg:phone":"+33 3 87 04 51 57",
    "sg:postcode":"57470",
    "sg:province":"Lorraine",
    "sg:tags":[
        "instrument",
        "health",
        "-",
        "precision"
    ],
    "wof:name":"M. Felix Marcel",
    "wof:placetype":"venue"
},
  "geometry": {"coordinates":[6.79388,49.140369],"type":"Point"}
}