{
  "type": "Feature",
  "properties": {
    "addr:full":"Rd 42 69230 St G\u00e9nis Laval Rhone-Alpes 69230",
    "addr:postcode":"69230;69230",
    "addr:street":"Rd 42;Rhone-Alpes",
    "iso:country":"FR",
    "sg:address":"Rd 42 69230 St G\u00e9nis Laval",
    "sg:classifiers":[
        {
            "category":"Professional",
            "type":"Services"
        }
    ],
    "sg:phone":"+33 4 78 56 04 00",
    "sg:postcode":"69230",
    "sg:province":"Rhone-Alpes",
    "sg:tags":[
        "transport",
        "road"
    ],
    "wof:name":"Servanin Sa",
    "wof:placetype":"venue"
},
  "geometry": {"coordinates":[-73.744637,45.551567],"type":"Point"}
}