{
  "type": "Feature",
  "properties": {
    "addr:full":"10 Rue Expansion 73460 Frontenex Rhone-Alpes 73460",
    "addr:housenumber":"10",
    "addr:postcode":"73460;73460",
    "addr:street":"Rue Expansion",
    "iso:country":"FR",
    "sg:address":"10 Rue Expansion 73460 Frontenex",
    "sg:classifiers":[
        {
            "category":"Professional",
            "subcategory":"Engineering",
            "type":"Services"
        }
    ],
    "sg:phone":"+33 4 79 38 58 88",
    "sg:postcode":"73460",
    "sg:province":"Rhone-Alpes",
    "sg:tags":[
        "machine",
        "-",
        "mechanical"
    ],
    "wof:name":"Bucari Et Fils Sa",
    "wof:placetype":"venue"
},
  "geometry": {"coordinates":[6.306249,45.587067],"type":"Point"}
}