{
  "type": "Feature",
  "properties": {
    "addr:full":"74, Rue des Alli\u00e9s, 57410 Rohrbach l\u00e8s Bitche Lorraine",
    "addr:housenumber":"74",
    "addr:postcode":"57410",
    "addr:street":"Rue Des Allie\u0301S",
    "iso:country":"FR",
    "sg:address":"74, Rue des Alli\u00e9s, 57410 Rohrbach l\u00e8s Bitche",
    "sg:orig_category":"Unclassifiable Establishments",
    "sg:phone":"+33 3 87 09 71 54",
    "sg:province":"Lorraine",
    "wof:name":"Solorim Publicit\u00e9 S.a.r.l.",
    "wof:placetype":"venue"
},
  "geometry": {"coordinates":[7.26454,49.046734],"type":"Point"}
}