{
  "type": "Feature",
  "properties": {
    "iso:country":"FR",
    "sg:address":"Bd Michel Chevalier - ZI du Bois de Grasse",
    "sg:city":"Grasse",
    "sg:orig_category":"Unclassifiable Establishments",
    "sg:phone":"+33 4 93 70 18 22",
    "sg:postcode":"06130",
    "sg:province":"Provence-Alpes-C\u00f4te d'Azur",
    "wof:name":"Kato International S.a.",
    "wof:placetype":"venue"
},
  "geometry": {"coordinates":[6.931647,43.649738],"type":"Point"}
}