{
  "type": "Feature",
  "properties": {
    "iso:country":"FR",
    "sg:address":"Le Val Bodron 56490 Meneac",
    "sg:city":"M\u00e9n\u00e9ac",
    "sg:classifiers":[
        {
            "category":"Home & Garden",
            "subcategory":"Furniture",
            "type":"Retail Goods"
        }
    ],
    "sg:phone":"+33 2 97 93 37 38",
    "sg:postcode":"56490",
    "sg:province":"Bretagne",
    "sg:tags":[
        "household",
        "wood"
    ],
    "wof:name":"Cadrim",
    "wof:placetype":"venue"
},
  "geometry": {"coordinates":[-2.446199,48.149776],"type":"Point"}
}