{
  "type": "Feature",
  "properties": {
    "iso:country":"FR",
    "sg:address":"Mont\u00e9e du Long 26500 Bourg l\u00e8s Valence",
    "sg:orig_category":"Unclassifiable Establishments",
    "sg:phone":"+33 4 75 83 09 81",
    "sg:province":"Rhone-Alpes",
    "wof:name":"Drome Mat\u00e9riel S.a.r.l.",
    "wof:placetype":"venue"
},
  "geometry": {"coordinates":[4.886222,44.9673],"type":"Point"}
}