{
  "type": "Feature",
  "properties": {
    "iso:country":"FR",
    "sg:address":"Rue Principale 08310 Cauroy",
    "sg:classifiers":[
        {
            "category":"Professional",
            "type":"Services"
        }
    ],
    "sg:phone":"+33 3 24 30 37 30",
    "sg:province":"Champagne",
    "sg:tags":[
        "transport",
        "road"
    ],
    "wof:name":"Transports Michel Leblanc Sarl",
    "wof:placetype":"venue"
},
  "geometry": {"coordinates":[4.455163,49.354828],"type":"Point"}
}