{
  "type": "Feature",
  "properties": {
    "iso:country":"FR",
    "sg:address":"B.P. 45, 31140 Saint Alban C\u00e9dex^^Av. L\u00e9on Jouhaux - ZI du Terroir, 31140 Saint Alban",
    "sg:orig_category":"Non-Classified Establishments",
    "sg:phone":"+33 5 61 35 43 72",
    "sg:province":"Midi Pyr\u00e9n\u00e9es",
    "wof:name":"G\u00e9n\u00e9ral Traiters Industrie",
    "wof:placetype":"venue"
},
  "geometry": {"coordinates":[1.400911,43.700218],"type":"Point"}
}