{
  "type": "Feature",
  "properties": {
    "addr:full":"116, Rue Jules Ferry, 76250 Deville les Rouen Haute Normandie",
    "addr:housenumber":"116",
    "addr:postcode":"76250",
    "addr:street":"Rue Jules Ferry;Deville;Haute Normandie",
    "iso:country":"FR",
    "sg:address":"116, Rue Jules Ferry, 76250 Deville les Rouen",
    "sg:orig_category":"Non-Classified Establishments",
    "sg:phone":"+33 2 35 76 61 97",
    "sg:province":"Haute Normandie",
    "wof:name":"Im.r.e.p. S.a.r.l. - Imprimerie Rouannaise D'edition Et De Publicit\u00e9",
    "wof:placetype":"venue"
},
  "geometry": {"coordinates":[1.04189,49.468109],"type":"Point"}
}