{
  "type": "Feature",
  "properties": {
    "addr:full":"28700 Garanci\u00e8res en Beauce Ardelu Centre 28700",
    "addr:postcode":"28700;28700",
    "iso:country":"FR",
    "sg:address":"28700 Garanci\u00e8res en Beauce",
    "sg:city":"Ardelu",
    "sg:orig_category":"Unclassifiable Establishments",
    "sg:phone":"+33 2 37 24 69 50",
    "sg:postcode":"28700",
    "sg:province":"Centre",
    "wof:name":"App\u00e9tit De France S.a.",
    "wof:placetype":"venue"
},
  "geometry": {"coordinates":[1.920575,48.437595],"type":"Point"}
}