{
  "type": "Feature",
  "properties": {
    "addr:full":"68 Avenue Des Gardes Messiers 91360 Villemoisson Sur Orge Ile de France 91360",
    "addr:housenumber":"68",
    "addr:postcode":"91360;91360",
    "addr:street":"Avenue Des Gardes Messiers",
    "iso:country":"FR",
    "sg:address":"68 Avenue Des Gardes Messiers 91360 Villemoisson Sur Orge",
    "sg:classifiers":[
        {
            "category":"Bakery",
            "type":"Food & Drink"
        }
    ],
    "sg:phone":"+33 1 69 04 26 47",
    "sg:postcode":"91360",
    "sg:province":"Ile de France",
    "sg:tags":[
        "cake",
        "product",
        "related",
        "bread"
    ],
    "wof:name":"William Pelloille Et Compagnie",
    "wof:placetype":"venue"
},
  "geometry": {"coordinates":[2.340304,48.661915],"type":"Point"}
}