{
  "type": "Feature",
  "properties": {
    "addr:full":"Chemin de la Monge Saint Sulpice Midi Pyr\u00e9n\u00e9es 81370",
    "addr:postcode":"81370",
    "addr:street":"Chemin De La Monge Saint;Midi",
    "iso:country":"FR",
    "sg:address":"Chemin de la Monge",
    "sg:city":"Saint Sulpice",
    "sg:orig_category":"Unclassifiable Establishments",
    "sg:phone":"+33 5 63 41 83 01",
    "sg:postcode":"81370",
    "sg:province":"Midi Pyr\u00e9n\u00e9es",
    "wof:name":"Roques S.a.r.l.",
    "wof:placetype":"venue"
},
  "geometry": {"coordinates":[1.688669,43.759274],"type":"Point"}
}