{
  "type": "Feature",
  "properties": {
    "iso:country":"FR",
    "sg:address":"44 Grande Rue 25310 Mesli\u00e8res",
    "sg:classifiers":[
        {
            "category":"Manufacturing",
            "subcategory":"Metals",
            "type":"Manufacturing & Wholesale Goods"
        }
    ],
    "sg:phone":"+33 3 81 36 39 30",
    "sg:postcode":"25310",
    "sg:province":"Franche Comt\u00e9",
    "sg:tags":[
        "metallurgy",
        "metalworking",
        "processing"
    ],
    "wof:name":"Societe Fmx",
    "wof:placetype":"venue"
},
  "geometry": {"coordinates":[6.887191,47.417187],"type":"Point"}
}