{
  "type": "Feature",
  "properties": {
    "iso:country":"FR",
    "sg:address":"26, Rue de la Godde, 45800 Saint Jean de Braye",
    "sg:city":"Combleux",
    "sg:orig_category":"Unclassifiable Establishments",
    "sg:phone":"+33 2 38 60 24 00",
    "sg:postcode":"45800",
    "sg:province":"Centre",
    "wof:name":"Celica S.a.",
    "wof:placetype":"venue"
},
  "geometry": {"coordinates":[1.978739,47.919048],"type":"Point"}
}