{
  "type": "Feature",
  "properties": {
    "addr:full":"152, Grande Rue Saint Clair, 69300 Caluire et Cuire Rhone-Alpes",
    "addr:housenumber":"152",
    "addr:postcode":"69300",
    "addr:street":"Grande Rue Saint Clair",
    "iso:country":"FR",
    "sg:address":"152, Grande Rue Saint Clair, 69300 Caluire et Cuire",
    "sg:orig_category":"Non-Classified Establishments",
    "sg:phone":"+33 4 72 27 45 67",
    "sg:province":"Rhone-Alpes",
    "wof:name":"Pitney Bowes S.a.",
    "wof:placetype":"venue"
},
  "geometry": {"coordinates":[4.86225,45.789089],"type":"Point"}
}