{
  "type": "Feature",
  "properties": {
    "addr:full":"17, Rue de Constantinople, 75008 Paris Ile de France 75008",
    "addr:housenumber":"17",
    "addr:postcode":"75008;75008",
    "addr:street":"Rue De Constantinople",
    "iso:country":"FR",
    "sg:address":"17, Rue de Constantinople, 75008 Paris",
    "sg:orig_category":"Non-Classified Establishments",
    "sg:phone":"+33 1 53 42 19 19",
    "sg:postcode":"75008",
    "sg:province":"Ile de France",
    "wof:name":"Energy Supply S.a.",
    "wof:placetype":"venue"
},
  "geometry": {"coordinates":[2.320468,48.879864],"type":"Point"}
}