{
  "type": "Feature",
  "properties": {
    "iso:country":"FR",
    "sg:address":"6, Rue des Je\u00fbneurs, 75002 Paris",
    "sg:orig_category":"Non-Classified Establishments",
    "sg:phone":"+33 1 45 08 87 77",
    "sg:postcode":"75002",
    "sg:province":"Ile de France",
    "wof:name":"Cr\u00e9lec Electronique",
    "wof:placetype":"venue"
},
  "geometry": {"coordinates":[2.347302,48.86903],"type":"Point"}
}