{
  "type": "Feature",
  "properties": {
    "iso:country":"FR",
    "sg:address":"43230 Couteuges",
    "sg:city":"Couteuges",
    "sg:orig_category":"Non-Classified Establishments",
    "sg:phone":"+33 4 71 76 85 55",
    "sg:postcode":"43230",
    "sg:province":"Auvergne",
    "wof:name":"Carofrance C\u00e9ramique S.a.",
    "wof:placetype":"venue"
},
  "geometry": {"coordinates":[3.498395,45.187145],"type":"Point"}
}