{
  "type": "Feature",
  "properties": {
    "addr:full":"12 Rue Sadi Carnot 94880 Noiseau Ile de France",
    "addr:housenumber":"12",
    "addr:postcode":"94880;ile",
    "addr:street":"Rue Sadi Carnot",
    "iso:country":"FR",
    "sg:address":"12 Rue Sadi Carnot 94880 Noiseau",
    "sg:classifiers":[
        {
            "category":"Utilities",
            "subcategory":"Telephone",
            "type":"Services"
        }
    ],
    "sg:phone":"+33 1 45 90 62 70",
    "sg:province":"Ile de France",
    "sg:tags":[
        "telecommunication"
    ],
    "wof:name":"Prosum Sarl",
    "wof:placetype":"venue"
},
  "geometry": {"coordinates":[2.551241,48.775276],"type":"Point"}
}