{
  "type": "Feature",
  "properties": {
    "addr:full":"8, Av. de Buffon - ZI la Source, 45100 Orl\u00e9ans Orl\u00e9ans Centre 45100",
    "addr:postcode":"45100;45100",
    "addr:street":"Av. De Buffon Zi La Source",
    "iso:country":"FR",
    "sg:address":"8, Av. de Buffon - ZI la Source, 45100 Orl\u00e9ans",
    "sg:city":"Orl\u00e9ans",
    "sg:orig_category":"Unclassifiable Establishments",
    "sg:phone":"+33 2 38 64 15 55",
    "sg:postcode":"45100",
    "sg:province":"Centre",
    "wof:name":"G.m.i. S.a.r.l. - Grenoble Modular Instruments",
    "wof:placetype":"venue"
},
  "geometry": {"coordinates":[1.927919,47.829445],"type":"Point"}
}