{
  "type": "Feature",
  "properties": {
    "addr:full":"4, Impasse Tuffi\u00e8res, 80820 Arrest Picardie 80820",
    "addr:housenumber":"4",
    "addr:postcode":"80820;80820",
    "addr:street":"Impasse Tuffie\u0300Res",
    "iso:country":"FR",
    "sg:address":"4, Impasse Tuffi\u00e8res, 80820 Arrest",
    "sg:orig_category":"Non-Classified Establishments",
    "sg:phone":"+33 3 22 60 84 89",
    "sg:postcode":"80820",
    "sg:province":"Picardie",
    "wof:name":"Deligni\u00e8res Et Fils",
    "wof:placetype":"venue"
},
  "geometry": {"coordinates":[1.613895,50.12299],"type":"Point"}
}