{
  "type": "Feature",
  "properties": {
    "iso:country":"FR",
    "sg:address":"Route De Chantemerle 51260 BETHON",
    "sg:classifiers":[
        {
            "category":"Food & Beverages",
            "subcategory":"Liquor & Beverages",
            "type":"Retail Goods"
        }
    ],
    "sg:phone":"+33 3 26 80 48 43",
    "sg:postcode":"51260",
    "sg:province":"Champagne",
    "sg:tags":[
        "champagne"
    ],
    "wof:name":"Ste Coop Vinicole Le Brun De Neuville",
    "wof:placetype":"venue"
},
  "geometry": {"coordinates":[3.78155,48.554821],"type":"Point"}
}