{
  "type": "Feature",
  "properties": {
    "iso:country":"FR",
    "sg:address":"5 Rue De Charonne 75011 Paris",
    "sg:classifiers":[
        {
            "category":"Shopping",
            "subcategory":"Hobbies, Toys, & Games",
            "type":"Retail Goods"
        }
    ],
    "sg:phone":"+33 1 43 55 99 04",
    "sg:postcode":"75011",
    "sg:province":"Ile de France",
    "sg:tags":[
        "product",
        "miscellaneous",
        "entertainment"
    ],
    "wof:name":"Jacpierre",
    "wof:placetype":"venue"
},
  "geometry": {"coordinates":[2.373868,48.852211],"type":"Point"}
}