{
  "type": "Feature",
  "properties": {
    "addr:full":"1, Av. Thermale, 03200 Vichy Vichy Auvergne 03200",
    "addr:postcode":"03200;03200",
    "addr:street":"Av. Thermale",
    "iso:country":"FR",
    "sg:address":"1, Av. Thermale, 03200 Vichy",
    "sg:city":"Vichy",
    "sg:orig_category":"Non-Classified Establishments",
    "sg:phone":"+33 4 70 31 04 39",
    "sg:postcode":"03200",
    "sg:province":"Auvergne",
    "wof:name":"Novotel Thermalia",
    "wof:placetype":"venue"
},
  "geometry": {"coordinates":[3.419705,46.126614],"type":"Point"}
}