{
  "type": "Feature",
  "properties": {
    "iso:country":"FR",
    "sg:address":"76, Quai des Carri\u00e8res, 94220 Charenton le Pont",
    "sg:orig_category":"Unclassifiable Establishments",
    "sg:phone":"+33 1 43 96 38 38",
    "sg:province":"Ile de France",
    "wof:name":"M.b. Communications Associ\u00e9s S.a.r.l.",
    "wof:placetype":"venue"
},
  "geometry": {"coordinates":[2.404454,48.820114],"type":"Point"}
}