{
  "type": "Feature",
  "properties": {
    "iso:country":"FR",
    "sg:address":"1 rue de la Plage 67540 Ostwald",
    "sg:city":"Ostwald",
    "sg:classifiers":[
        {
            "category":"Recreation",
            "subcategory":"Boat Charter",
            "type":"Entertainment"
        }
    ],
    "sg:phone":"+33 3 88 55 90 02",
    "sg:postcode":"67540",
    "sg:province":"Alsace",
    "sg:tags":[
        "electrotechnical",
        "trailer",
        "accessory"
    ],
    "wof:name":"Esi S.a.r.l.",
    "wof:placetype":"venue"
},
  "geometry": {"coordinates":[7.715981,48.555775],"type":"Point"}
}