{
  "type": "Feature",
  "properties": {
    "iso:country":"FR",
    "sg:address":"14, Rue Franklin, 68200 Mulhouse",
    "sg:city":"Mulhouse",
    "sg:orig_category":"Unclassifiable Establishments",
    "sg:phone":"+33 3 89 59 51 11",
    "sg:postcode":"68200",
    "sg:province":"Alsace",
    "wof:name":"Burocom 68 S.a.",
    "wof:placetype":"venue"
},
  "geometry": {"coordinates":[7.3353,47.752319],"type":"Point"}
}