{
  "type": "Feature",
  "properties": {
    "addr:full":"Rte de Paris Franqueville Saint Pierre Haute Normandie 76520",
    "addr:postcode":"76520",
    "addr:street":"Rte De Paris",
    "iso:country":"FR",
    "sg:address":"Rte de Paris",
    "sg:city":"Franqueville Saint Pierre",
    "sg:orig_category":"Unclassifiable Establishments",
    "sg:phone":"+33 2 35 79 46 46",
    "sg:postcode":"76520",
    "sg:province":"Haute Normandie",
    "wof:name":"Carrier Transicold Europe S.a.",
    "wof:placetype":"venue"
},
  "geometry": {"coordinates":[1.15389,49.404495],"type":"Point"}
}