{
  "type": "Feature",
  "properties": {
    "iso:country":"FR",
    "sg:address":"B.P. 25, 52101 Saint Dizier C\u00e9dex^^ZI de la Tambourine, 52100 Saint Dizier",
    "sg:orig_category":"Non-Classified Establishments",
    "sg:phone":"+33 3 25 05 61 77",
    "sg:province":"Champagne",
    "wof:name":"Garnier Pro S.a.",
    "wof:placetype":"venue"
},
  "geometry": {"coordinates":[4.946965,48.636589],"type":"Point"}
}