{
  "type": "Feature",
  "properties": {
    "addr:full":"9 Rue Augustin Thierry 42000 St Etienne Rhone-Alpes 42000",
    "addr:housenumber":"9",
    "addr:postcode":"42000;42000",
    "addr:street":"Rue Augustin Thierry",
    "iso:country":"FR",
    "sg:address":"9 Rue Augustin Thierry 42000 St Etienne",
    "sg:classifiers":[
        {
            "category":"Professional",
            "subcategory":"Engineering",
            "type":"Services"
        }
    ],
    "sg:phone":"+33 4 77 79 33 18",
    "sg:postcode":"42000",
    "sg:province":"Rhone-Alpes",
    "sg:tags":[
        "machine",
        "-",
        "mechanical"
    ],
    "wof:name":"Ksi",
    "wof:placetype":"venue"
},
  "geometry": {"coordinates":[4.387921,45.439053],"type":"Point"}
}