{
  "type": "Feature",
  "properties": {
    "addr:full":"Le Fougeray 50530 Bacilly Bacilly Basse Normandie 50530",
    "addr:postcode":"50530;50530",
    "iso:country":"FR",
    "sg:address":"Le Fougeray 50530 Bacilly",
    "sg:city":"Bacilly",
    "sg:classifiers":[
        {
            "category":"Building & Trades",
            "subcategory":"Construction",
            "type":"Services"
        }
    ],
    "sg:phone":"+33 2 33 79 06 79",
    "sg:postcode":"50530",
    "sg:province":"Basse Normandie",
    "sg:tags":[
        "work",
        "public"
    ],
    "wof:name":"Barenton Sa",
    "wof:placetype":"venue"
},
  "geometry": {"coordinates":[-1.441009,48.68829],"type":"Point"}
}