{
  "type": "Feature",
  "properties": {
    "iso:country":"FR",
    "sg:address":"Cleherlan 56230 Questembert",
    "sg:city":"Questembert",
    "sg:classifiers":[
        {
            "category":"Farming",
            "subcategory":"Livestock Farm",
            "type":"Manufacturing & Wholesale Goods"
        }
    ],
    "sg:phone":"+33 2 97 26 18 14",
    "sg:postcode":"56230",
    "sg:province":"Bretagne",
    "sg:tags":[
        "breeding",
        "agriculture",
        "animal"
    ],
    "wof:name":"Evialis Sa",
    "wof:placetype":"venue"
},
  "geometry": {"coordinates":[-2.461974,47.680656],"type":"Point"}
}