{
  "type": "Feature",
  "properties": {
    "addr:full":"5, Rue des Gen\u00eats, 67110 Gundershoffen Gundershoffen Alsace 67110",
    "addr:housenumber":"5",
    "addr:postcode":"67110;67110",
    "addr:street":"Rue Des Gene\u0302Ts;Gundershoffen",
    "iso:country":"FR",
    "sg:address":"5, Rue des Gen\u00eats, 67110 Gundershoffen",
    "sg:city":"Gundershoffen",
    "sg:orig_category":"Non-Classified Establishments",
    "sg:phone":"+33 3 88 72 99 70",
    "sg:postcode":"67110",
    "sg:province":"Alsace",
    "wof:name":"Info Industrie S.a.",
    "wof:placetype":"venue"
},
  "geometry": {"coordinates":[7.6532,48.903351],"type":"Point"}
}