{
  "type": "Feature",
  "properties": {
    "addr:full":"Chem Pr\u00e9 Hardy 27300 Menneval Haute Normandie 27300",
    "addr:postcode":"27300;27300",
    "addr:street":"Chem Pre\u0301 Hardy;Haute Normandie",
    "iso:country":"FR",
    "sg:address":"Chem Pr\u00e9 Hardy 27300 Menneval",
    "sg:classifiers":[
        {
            "category":"Farming",
            "subcategory":"Farm",
            "type":"Manufacturing & Wholesale Goods"
        }
    ],
    "sg:phone":"+33 2 32 43 07 78",
    "sg:postcode":"27300",
    "sg:province":"Haute Normandie",
    "sg:tags":[
        "horticulture",
        "agriculture",
        "livestock"
    ],
    "wof:name":"Ste Nouvelle Pepinieres De Bernay",
    "wof:placetype":"venue"
},
  "geometry": {"coordinates":[0.614025,49.105831],"type":"Point"}
}