{
  "type": "Feature",
  "properties": {
    "addr:full":"Rte de Bussi\u00e8re - ZI Nord Dange Saint Romain Poitou-Charentes 86220",
    "addr:postcode":"86220",
    "addr:street":"Rte De Bussie\u0300Re Zi Nord;Romain",
    "iso:country":"FR",
    "sg:address":"Rte de Bussi\u00e8re - ZI Nord",
    "sg:city":"Dange Saint Romain",
    "sg:orig_category":"Unclassifiable Establishments",
    "sg:phone":"+33 5 49 86 41 48",
    "sg:postcode":"86220",
    "sg:province":"Poitou-Charentes",
    "wof:name":"M.m.m. Sa - Maintenance, M\u00e9canique, Menuiserie",
    "wof:placetype":"venue"
},
  "geometry": {"coordinates":[0.628151,46.872829],"type":"Point"}
}