{
  "type": "Feature",
  "properties": {
    "addr:full":"B.P. 50271, 87007 Limoges C\u00e9dex^^2, Av. Locarno, 87000 Limoges Limousin",
    "addr:postcode":"87007;87000",
    "addr:street":"Av. Locarno",
    "iso:country":"FR",
    "sg:address":"B.P. 50271, 87007 Limoges C\u00e9dex^^2, Av. Locarno, 87000 Limoges",
    "sg:orig_category":"Non-Classified Establishments",
    "sg:phone":"+33 5 55 11 34 00",
    "sg:province":"Limousin",
    "wof:name":"Serdie S.a. - Services Et D\u00e9veloppements Informatiques",
    "wof:placetype":"venue"
},
  "geometry": {"coordinates":[1.26201,45.828785],"type":"Point"}
}