{
  "type": "Feature",
  "properties": {
    "iso:country":"FR",
    "sg:address":"rue du Vide Arpents 77100 Meaux",
    "sg:classifiers":[
        {
            "category":"Food & Beverages",
            "subcategory":"Meat & Fish",
            "type":"Retail Goods"
        }
    ],
    "sg:phone":"+33 1 64 36 55 30",
    "sg:postcode":"77100",
    "sg:province":"Ile de France",
    "sg:tags":[
        "sausage"
    ],
    "wof:name":"Produits Auge Roger S.a.",
    "wof:placetype":"venue"
},
  "geometry": {"coordinates":[2.904648,48.965446],"type":"Point"}
}