{
  "type": "Feature",
  "properties": {
    "iso:country":"FR",
    "sg:address":"27, Rue de la Burelle, 45800 Saint Jean de Braye",
    "sg:city":"Combleux",
    "sg:orig_category":"Unclassifiable Establishments",
    "sg:phone":"+33 2 38 71 94 00",
    "sg:postcode":"45800",
    "sg:province":"Centre",
    "wof:name":"C.g.p.-kon\u00e9crames S.a.",
    "wof:placetype":"venue"
},
  "geometry": {"coordinates":[1.943596,47.911694],"type":"Point"}
}