{
  "type": "Feature",
  "properties": {
    "addr:full":"262 Avenue Maurice Planes 34070 Montpellier Languedoc-Roussillon",
    "addr:housenumber":"262",
    "addr:postcode":"34070",
    "addr:street":"Avenue Maurice Planes",
    "iso:country":"FR",
    "sg:address":"262 Avenue Maurice Planes 34070 Montpellier",
    "sg:classifiers":[
        {
            "category":"Manufacturing",
            "subcategory":"Printing",
            "type":"Manufacturing & Wholesale Goods"
        }
    ],
    "sg:phone":"+33 4 67 99 49 49",
    "sg:province":"Languedoc-Roussillon",
    "sg:tags":[
        "publishing"
    ],
    "wof:name":"Editions Mimosa",
    "wof:placetype":"venue"
},
  "geometry": {"coordinates":[3.845151,43.596272],"type":"Point"}
}