{
  "type": "Feature",
  "properties": {
    "iso:country":"FR",
    "sg:address":"29 R De Valenton 94470 Boissy St L\u00e9ger",
    "sg:classifiers":[
        {
            "category":"Farming",
            "subcategory":"Farm",
            "type":"Manufacturing & Wholesale Goods"
        }
    ],
    "sg:phone":"+33 1 45 69 10 42",
    "sg:postcode":"94470",
    "sg:province":"Ile de France",
    "sg:tags":[
        "horticulture",
        "agriculture",
        "livestock"
    ],
    "wof:name":"Vacherot Et Lecoufle",
    "wof:placetype":"venue"
},
  "geometry": {"coordinates":[2.504501,48.744022],"type":"Point"}
}