{
  "type": "Feature",
  "properties": {
    "addr:full":"11 Rue De La Sourdiere 75001 Paris Ile de France",
    "addr:housenumber":"11",
    "addr:postcode":"75001",
    "addr:street":"Rue De La Sourdiere",
    "iso:country":"FR",
    "sg:address":"11 Rue De La Sourdiere 75001 Paris",
    "sg:classifiers":[
        {
            "category":"Professional",
            "subcategory":"Printing & Photocopies",
            "type":"Services"
        }
    ],
    "sg:phone":"+33 1 40 20 02 50",
    "sg:province":"Ile de France",
    "sg:tags":[
        "publishing"
    ],
    "wof:name":"Agendas Kronos",
    "wof:placetype":"venue"
},
  "geometry": {"coordinates":[2.33182,48.865726],"type":"Point"}
}