{
  "type": "Feature",
  "properties": {
    "iso:country":"FR",
    "sg:address":"232, Av Becquart, 59130 Lambersart",
    "sg:orig_category":"Unclassifiable Establishments",
    "sg:phone":"+33 3 20 09 35 16",
    "sg:province":"Nord Pas-de-Calais",
    "wof:name":"Safi S.a.",
    "wof:placetype":"venue"
},
  "geometry": {"coordinates":[3.03073,50.651913],"type":"Point"}
}