{
  "type": "Feature",
  "properties": {
    "addr:full":"3, Rue de l'H\u00f4tel de Ville, 44000 Nantes Pays de Loire",
    "addr:housenumber":"3",
    "addr:postcode":"44000",
    "addr:street":"Rue De L'Ho \u0302Tel De Ville",
    "iso:country":"FR",
    "sg:address":"3, Rue de l'H\u00f4tel de Ville, 44000 Nantes",
    "sg:orig_category":"Unclassifiable Establishments",
    "sg:phone":"+33 2 40 89 55 17",
    "sg:province":"Pays de Loire",
    "wof:name":"S\u00e9curifrance S.a.",
    "wof:placetype":"venue"
},
  "geometry": {"coordinates":[-1.554471,47.21777],"type":"Point"}
}