{
  "type": "Feature",
  "properties": {
    "addr:full":"chemin de la Rivi\u00e8re 69290 Grezieu la Varenne Rhone-Alpes 69290",
    "addr:postcode":"69290;69290",
    "addr:street":"Chemin De La Rivie\u0300Re",
    "iso:country":"FR",
    "sg:address":"chemin de la Rivi\u00e8re 69290 Grezieu la Varenne",
    "sg:classifiers":[
        {
            "category":"Wholesale",
            "subcategory":"Chemicals & Plastics",
            "type":"Manufacturing & Wholesale Goods"
        }
    ],
    "sg:phone":"+33 4 78 57 88 89",
    "sg:postcode":"69290",
    "sg:province":"Rhone-Alpes",
    "sg:tags":[
        "dyestuff"
    ],
    "wof:name":"Colorey Sa",
    "wof:placetype":"venue"
},
  "geometry": {"coordinates":[4.705934,45.756359],"type":"Point"}
}