{
  "type": "Feature",
  "properties": {
    "iso:country":"FR",
    "sg:address":"Place Centrale",
    "sg:city":"Le Pont de Beauvoisin",
    "sg:orig_category":"Unclassifiable Establishments",
    "sg:phone":"+33 4 76 37 03 33",
    "sg:postcode":"73330",
    "sg:province":"Rhone-Alpes",
    "wof:name":"Faure Tourisme S.a.",
    "wof:placetype":"venue"
},
  "geometry": {"coordinates":[5.673195,45.536446],"type":"Point"}
}