{
  "type": "Feature",
  "properties": {
    "addr:full":"B.P. 300, 13667 Salon de Provence C\u00e9dex^^Av. Gabriel Voisin - ZI de la Crau Oues, 13300 Salon de Pro Outre-Mer",
    "addr:housenumber":"b.p. 300",
    "addr:postcode":"13667;13300",
    "addr:street":"Zi De La;Oues",
    "iso:country":"FR",
    "sg:address":"B.P. 300, 13667 Salon de Provence C\u00e9dex^^Av. Gabriel Voisin - ZI de la Crau Oues, 13300 Salon de Pro",
    "sg:orig_category":"Non-Classified Establishments",
    "sg:phone":"+33 4 90 17 22 00",
    "sg:province":"Outre-Mer",
    "wof:name":"Logidis S.a.",
    "wof:placetype":"venue"
},
  "geometry": {"coordinates":[5.098957,43.638432],"type":"Point"}
}