{
  "type": "Feature",
  "properties": {
    "addr:full":"St Andr\u00e9 47270 St Caprais De Lerm Saint-Martin-de-Beauville Aquitaine 47270",
    "addr:postcode":"47270;47270",
    "iso:country":"FR",
    "sg:address":"St Andr\u00e9 47270 St Caprais De Lerm",
    "sg:city":"Saint-Martin-de-Beauville",
    "sg:classifiers":[
        {
            "category":"Professional",
            "type":"Services"
        }
    ],
    "sg:phone":"+33 5 53 87 77 77",
    "sg:postcode":"47270",
    "sg:province":"Aquitaine",
    "sg:tags":[
        "transport",
        "road"
    ],
    "wof:name":"T R A P Sarl",
    "wof:placetype":"venue"
},
  "geometry": {"coordinates":[0.730955,44.203014],"type":"Point"}
}