{
  "type": "Feature",
  "properties": {
    "iso:country":"FR",
    "sg:address":"238 Rue D Esquerchin 59500 Douai",
    "sg:classifiers":[
        {
            "category":"Wholesale",
            "subcategory":"Medical Equipment & Supplies",
            "type":"Manufacturing & Wholesale Goods"
        }
    ],
    "sg:phone":"+33 3 27 98 19 09",
    "sg:postcode":"59500",
    "sg:province":"Nord Pas-de-Calais",
    "sg:tags":[
        "instrument",
        "health",
        "-",
        "precision"
    ],
    "wof:name":"Laboratoire Jlb",
    "wof:placetype":"venue"
},
  "geometry": {"coordinates":[3.072,50.370937],"type":"Point"}
}