{
  "type": "Feature",
  "properties": {
    "iso:country":"FR",
    "sg:address":"51, Bd Carnot, 78110 Le V\u00e9sinet",
    "sg:orig_category":"Unclassifiable Establishments",
    "sg:phone":"+33 1 39 76 74 54",
    "sg:province":"Ile de France",
    "wof:name":"Dix S.a.r.l.",
    "wof:placetype":"venue"
},
  "geometry": {"coordinates":[2.136074,48.89365],"type":"Point"}
}