{
  "type": "Feature",
  "properties": {
    "addr:full":"201, Rue Jean Jaur\u00e8s, 56600 Lanester Lanester Bretagne 56600",
    "addr:housenumber":"201",
    "addr:postcode":"56600;56600",
    "addr:street":"Rue Jean Jaure\u0300S",
    "iso:country":"FR",
    "sg:address":"201, Rue Jean Jaur\u00e8s, 56600 Lanester",
    "sg:city":"Lanester",
    "sg:orig_category":"Non-Classified Establishments",
    "sg:phone":"+33 2 57 76 14 81",
    "sg:postcode":"56600",
    "sg:province":"Bretagne",
    "wof:name":"Hellin S.a.",
    "wof:placetype":"venue"
},
  "geometry": {"coordinates":[-3.351751,47.769413],"type":"Point"}
}