{
  "type": "Feature",
  "properties": {
    "addr:full":"Ccal De La Sapini\u00e8re 54520 Laxou Lorraine 54520",
    "addr:postcode":"54520;54520",
    "iso:country":"FR",
    "sg:address":"Ccal De La Sapini\u00e8re 54520 Laxou",
    "sg:classifiers":[
        {
            "category":"Shopping",
            "subcategory":"Luggage & Leather Goods",
            "type":"Retail Goods"
        }
    ],
    "sg:phone":"+33 3 83 98 71 56",
    "sg:postcode":"54520",
    "sg:province":"Lorraine",
    "sg:tags":[
        "shoe"
    ],
    "wof:name":"Eram Shop",
    "wof:placetype":"venue"
},
  "geometry": {"coordinates":[6.15226,48.68528],"type":"Point"}
}