{
  "type": "Feature",
  "properties": {
    "iso:country":"FR",
    "sg:address":"B.P. 39, 78440 Gargenville^^25, Av. du Val - ZI Limay Porcheville, 78440 Gargenville",
    "sg:orig_category":"Non-Classified Establishments",
    "sg:phone":"+33 1 30 98 20 00",
    "sg:province":"Ile de France",
    "wof:name":"Ilva France S.a.",
    "wof:placetype":"venue"
},
  "geometry": {"coordinates":[1.81015,48.989475],"type":"Point"}
}