{
  "type": "Feature",
  "properties": {
    "addr:full":"1, Bd de la Raffinerie, 13014 Marseille Poitou-Charentes",
    "addr:housenumber":"1",
    "addr:postcode":"13014",
    "addr:street":"Bd De La Raffinerie",
    "iso:country":"FR",
    "sg:address":"1, Bd de la Raffinerie, 13014 Marseille",
    "sg:orig_category":"Unclassifiable Establishments",
    "sg:phone":"+33 4 91 98 90 24",
    "sg:province":"Poitou-Charentes",
    "wof:name":"C.i.m.a.t. Sartec S.a. - Compagnie Internationale De Maintenance Et D'assi",
    "wof:placetype":"venue"
},
  "geometry": {"coordinates":[5.37997,43.33371],"type":"Point"}
}