{
  "type": "Feature",
  "properties": {
    "addr:full":"Rte du Mont Beuvray - Les Gargotti\u00e8res Onlay Bourgogne 58370",
    "addr:postcode":"58370",
    "addr:street":"Rte Du Mont Beuvray Les;Bourgogne",
    "iso:country":"FR",
    "sg:address":"Rte du Mont Beuvray - Les Gargotti\u00e8res",
    "sg:city":"Onlay",
    "sg:orig_category":"Non-Classified Establishments",
    "sg:phone":"+33 3 86 84 33 66",
    "sg:postcode":"58370",
    "sg:province":"Bourgogne",
    "wof:name":"Les Terrines Du Morvan S.a.",
    "wof:placetype":"venue"
},
  "geometry": {"coordinates":[4.003023,46.87738],"type":"Point"}
}