{
  "type": "Feature",
  "properties": {
    "addr:full":"B.P. 1 Al\u00e9ria^^Etang de Diane 20270 Al\u00e9ria Corse 20270",
    "addr:postcode":"20270;20270",
    "addr:street":"B.P. 1;De Diane",
    "iso:country":"FR",
    "sg:address":"B.P. 1",
    "sg:city":"Al\u00e9ria^^Etang de Diane 20270 Al\u00e9ria",
    "sg:orig_category":"Non-Classified Establishments",
    "sg:phone":"+33 4 95 57 02 53",
    "sg:postcode":"20270",
    "sg:province":"Corse",
    "wof:name":"L'etang De Diane S.a.r.l.",
    "wof:placetype":"venue"
},
  "geometry": {"coordinates":[9.513284,42.11599],"type":"Point"}
}