{
  "type": "Feature",
  "properties": {
    "addr:full":"r Pierre Charignon 26750 G\u00e9nissieux Rhone-Alpes 26750",
    "addr:postcode":"26750;26750",
    "addr:street":"R;Rhone-Alpes",
    "iso:country":"FR",
    "sg:address":"r Pierre Charignon 26750 G\u00e9nissieux",
    "sg:classifiers":[
        {
            "category":"Shopping",
            "subcategory":"Hobbies, Toys, & Games",
            "type":"Retail Goods"
        }
    ],
    "sg:phone":"+33 4 75 72 55 22",
    "sg:postcode":"26750",
    "sg:province":"Rhone-Alpes",
    "sg:tags":[
        "product",
        "miscellaneous",
        "entertainment"
    ],
    "wof:name":"Christian Fabrications (sarl)",
    "wof:placetype":"venue"
},
  "geometry": {"coordinates":[5.083657,45.080036],"type":"Point"}
}