{
  "type": "Feature",
  "properties": {
    "addr:full":"3 R Auguste Nayel 56100 Lorient Lorient Bretagne 56100",
    "addr:housenumber":"3",
    "addr:postcode":"56100;56100",
    "addr:street":"R Auguste Nayel",
    "iso:country":"FR",
    "sg:address":"3 R Auguste Nayel 56100 Lorient",
    "sg:city":"Lorient",
    "sg:classifiers":[
        {
            "category":"Wholesale",
            "subcategory":"Medical Equipment & Supplies",
            "type":"Manufacturing & Wholesale Goods"
        }
    ],
    "sg:phone":"+33 2 97 21 50 61",
    "sg:postcode":"56100",
    "sg:province":"Bretagne",
    "sg:tags":[
        "instrument",
        "health",
        "-",
        "precision"
    ],
    "wof:name":"M. Souchet Jean-michel",
    "wof:placetype":"venue"
},
  "geometry": {"coordinates":[-3.359985,47.746586],"type":"Point"}
}