{
  "type": "Feature",
  "properties": {
    "addr:full":"4, Rte de Villeneuve, 95510 Vienne en Arthies Ile de France 95510",
    "addr:housenumber":"4",
    "addr:postcode":"95510;95510",
    "addr:street":"Rte De Villeneuve",
    "iso:country":"FR",
    "sg:address":"4, Rte de Villeneuve, 95510 Vienne en Arthies",
    "sg:orig_category":"Non-Classified Establishments",
    "sg:phone":"+33 1 34 78 15 59",
    "sg:postcode":"95510",
    "sg:province":"Ile de France",
    "wof:name":"C.c.p.a. - Centrale Coop\u00e9rative Productions Animales",
    "wof:placetype":"venue"
},
  "geometry": {"coordinates":[1.732634,49.0695],"type":"Point"}
}