{
  "type": "Feature",
  "properties": {
    "addr:full":"ROUTE DE SAINT REMY 13150 Tarascon Corse",
    "addr:postcode":"13150",
    "addr:street":"Route De Saint Remy",
    "iso:country":"FR",
    "sg:address":"ROUTE DE SAINT REMY 13150 Tarascon",
    "sg:classifiers":[
        {
            "category":"Education",
            "subcategory":"Special Training",
            "type":"Public Place"
        }
    ],
    "sg:phone":"+33 4 90 91 51 70",
    "sg:province":"Corse",
    "sg:tags":[
        "bread"
    ],
    "wof:name":"Bcs Panita S.a.r.l.",
    "wof:placetype":"venue"
},
  "geometry": {"coordinates":[4.678039,43.799809],"type":"Point"}
}