{
  "type": "Feature",
  "properties": {
    "iso:country":"FR",
    "sg:address":"965, Rte de Granges, 88220 Xertigny",
    "sg:orig_category":"Unclassifiable Establishments",
    "sg:phone":"+33 3 29 30 10 11",
    "sg:province":"Lorraine",
    "wof:name":"Tr\u00e9fileries De Conflandey S.a.",
    "wof:placetype":"venue"
},
  "geometry": {"coordinates":[6.403905,48.044949],"type":"Point"}
}