{
  "type": "Feature",
  "properties": {
    "addr:full":"8 Paul de la Monneraye; Herbignac; 44410 Pays de Loire 44410",
    "addr:housenumber":"8",
    "addr:postcode":"44410;44410",
    "addr:street":"Paul De La Monneraye",
    "iso:country":"FR",
    "sg:address":"8",
    "sg:city":"Paul de la Monneraye; Herbignac; 44410",
    "sg:classifiers":[
        {
            "category":"Banks & Credit Unions",
            "subcategory":"Bank",
            "type":"Services"
        }
    ],
    "sg:phone":"+33 3340889037",
    "sg:postcode":"44410",
    "sg:province":"Pays de Loire",
    "wof:name":"Caisse R\u00e9gionale, De Cr\u00e9dit Agricole",
    "wof:placetype":"venue"
},
  "geometry": {"coordinates":[-2.374192,47.357456],"type":"Point"}
}