{
  "type": "Feature",
  "properties": {
    "addr:full":"52, Rue Paul Lafargue, 69100 Villeurbanne Rhone-Alpes",
    "addr:housenumber":"52",
    "addr:postcode":"69100",
    "addr:street":"Rue Paul Lafargue",
    "iso:country":"FR",
    "sg:address":"52, Rue Paul Lafargue, 69100 Villeurbanne",
    "sg:orig_category":"Unclassifiable Establishments",
    "sg:phone":"+33 4 78 68 26 09",
    "sg:province":"Rhone-Alpes",
    "wof:name":"S.m.i.n. S.a.r.l. - Soci\u00e9t\u00e9 De Moules Industriels Nury",
    "wof:placetype":"venue"
},
  "geometry": {"coordinates":[4.88342,45.765934],"type":"Point"}
}