{
  "type": "Feature",
  "properties": {
    "iso:country":"FR",
    "sg:address":"69, Rue Edouard Plachez, 62220 Carvin",
    "sg:orig_category":"Unclassifiable Establishments",
    "sg:phone":"+33 3 21 08 93 00",
    "sg:province":"Nord Pas-de-Calais",
    "wof:name":"A.n.p.e.",
    "wof:placetype":"venue"
},
  "geometry": {"coordinates":[2.955486,50.490292],"type":"Point"}
}