{
  "type": "Feature",
  "properties": {
    "iso:country":"FR",
    "sg:address":"131 place Aristide Berges 74190 PASSY",
    "sg:classifiers":[
        {
            "category":"Arena",
            "subcategory":"Sports Club",
            "type":"Entertainment"
        }
    ],
    "sg:phone":"+33 4 50 47 47 00",
    "sg:postcode":"74190",
    "sg:province":"Rhone-Alpes",
    "sg:tags":[
        "graphite"
    ],
    "wof:name":"S.g.l. Carbon Sa",
    "wof:placetype":"venue"
},
  "geometry": {"coordinates":[6.727105,45.926815],"type":"Point"}
}