{
  "type": "Feature",
  "properties": {
    "addr:full":"ZA 74700 Sallanches Rhone-Alpes 74700",
    "addr:postcode":"74700;74700",
    "addr:street":"Za",
    "iso:country":"FR",
    "sg:address":"ZA 74700 Sallanches",
    "sg:classifiers":[
        {
            "category":"Building & Trades",
            "subcategory":"Plumbing",
            "type":"Services"
        }
    ],
    "sg:phone":"+33 4 50 58 05 21",
    "sg:postcode":"74700",
    "sg:province":"Rhone-Alpes",
    "sg:tags":[
        "cropping",
        "tool"
    ],
    "wof:name":"Ravinet Gaston Sarl",
    "wof:placetype":"venue"
},
  "geometry": {"coordinates":[6.648797,45.913139],"type":"Point"}
}