{
  "type": "Feature",
  "properties": {
    "iso:country":"FR",
    "sg:address":"47 avenue Fr\u00e9d\u00e9ric Mistral 13013 Marseille",
    "sg:classifiers":[
        {
            "category":"Manufacturing",
            "subcategory":"Textiles",
            "type":"Manufacturing & Wholesale Goods"
        }
    ],
    "sg:phone":"+33 4 91 66 96 66",
    "sg:province":"Poitou-Charentes",
    "sg:tags":[
        "natural"
    ],
    "wof:name":"Coastland Sarl",
    "wof:placetype":"venue"
},
  "geometry": {"coordinates":[5.417715,43.322464],"type":"Point"}
}