{
  "type": "Feature",
  "properties": {
    "addr:full":"75 Avenue Borriglione 06000 Nice Basse Normandie",
    "addr:housenumber":"75",
    "addr:postcode":"06000",
    "addr:street":"Avenue Borriglione",
    "iso:country":"FR",
    "sg:address":"75 Avenue Borriglione 06000 Nice",
    "sg:classifiers":[
        {
            "category":"Professional",
            "subcategory":"Advertising",
            "type":"Services"
        }
    ],
    "sg:phone":"+33 4 93 51 18 18",
    "sg:province":"Basse Normandie",
    "sg:tags":[
        "communication",
        "medium"
    ],
    "wof:name":"Bureau D'edition Publicitaire (bep)",
    "wof:placetype":"venue"
},
  "geometry": {"coordinates":[7.26146,43.717064],"type":"Point"}
}