{
  "type": "Feature",
  "properties": {
    "addr:full":"103, Rte du Plan de la Tour, 83120 Sainte Maxime Provence-Alpes-C\u00f4te d'Azur",
    "addr:housenumber":"103",
    "addr:postcode":"83120",
    "addr:street":"Rte Du Plan De La Tour;Maxime",
    "iso:country":"FR",
    "sg:address":"103, Rte du Plan de la Tour, 83120 Sainte Maxime",
    "sg:orig_category":"Unclassifiable Establishments",
    "sg:phone":"+33 4 94 49 70 00",
    "sg:province":"Provence-Alpes-C\u00f4te d'Azur",
    "wof:name":"H\u00f4tel Coralia Sainte Maxime",
    "wof:placetype":"venue"
},
  "geometry": {"coordinates":[6.629118,43.322708],"type":"Point"}
}