{
  "type": "Feature",
  "properties": {
    "addr:full":"Zi Secteur A All\u00e9e Paul Sabatier 27940 Aubevoye Haute Normandie 27940",
    "addr:housenumber":"a",
    "addr:postcode":"27940;27940",
    "addr:street":"Zi;Alle\u0301E Paul Sabatier;Haute Normandie",
    "iso:country":"FR",
    "sg:address":"Zi Secteur A All\u00e9e Paul Sabatier 27940 Aubevoye",
    "sg:classifiers":[
        {
            "category":"Manufacturing",
            "subcategory":"Chemicals & Compounds",
            "type":"Manufacturing & Wholesale Goods"
        }
    ],
    "sg:phone":"+33 2 32 77 30 77",
    "sg:postcode":"27940",
    "sg:province":"Haute Normandie",
    "sg:tags":[
        "pharmaceutical",
        "chemistry",
        "-",
        "by-product"
    ],
    "wof:name":"Bs Coating Sa",
    "wof:placetype":"venue"
},
  "geometry": {"coordinates":[1.33632,49.167137],"type":"Point"}
}