{
  "type": "Feature",
  "properties": {
    "addr:full":"Moulin Garnier La Roche Vineuse Bourgogne 71960",
    "addr:postcode":"71960",
    "iso:country":"FR",
    "sg:address":"Moulin Garnier",
    "sg:city":"La Roche Vineuse",
    "sg:orig_category":"Non-Classified Establishments",
    "sg:phone":"+33 3 85 51 61 48",
    "sg:postcode":"71960",
    "sg:province":"Bourgogne",
    "wof:name":"C.v.s. S.a.r.l. - Composite Du Val De Sa\u00f4ne",
    "wof:placetype":"venue"
},
  "geometry": {"coordinates":[4.72859,46.33667],"type":"Point"}
}