{
  "type": "Feature",
  "properties": {
    "iso:country":"FR",
    "sg:address":"50 Rue Des Martyrs",
    "sg:city":"Elbeuf",
    "sg:classifiers":[
        {
            "category":"Banks & Credit Unions",
            "subcategory":"Financial Services",
            "type":"Services"
        }
    ],
    "sg:phone":"+33 2 32 96 99 30",
    "sg:postcode":"76500",
    "sg:province":"Haute Normandie",
    "sg:tags":[
        "banking",
        "finance",
        "insurance"
    ],
    "wof:name":"Caisse Regionale De Credit Agricole Mutuel De La Haute Norm (crcamh N)",
    "wof:placetype":"venue"
},
  "geometry": {"coordinates":[1.005766,49.289207],"type":"Point"}
}