{
  "type": "Feature",
  "properties": {
    "addr:full":"128, Rue de Thiers, 92100 Boulogne Billancourt Ile de France",
    "addr:housenumber":"128",
    "addr:postcode":"92100",
    "addr:street":"Rue De Thiers",
    "iso:country":"FR",
    "sg:address":"128, Rue de Thiers, 92100 Boulogne Billancourt",
    "sg:orig_category":"Non-Classified Establishments",
    "sg:phone":"+33 1 47 61 17 82",
    "sg:province":"Ile de France",
    "wof:name":"Locasoft S.a.",
    "wof:placetype":"venue"
},
  "geometry": {"coordinates":[2.252078,48.831631],"type":"Point"}
}