{
  "type": "Feature",
  "properties": {
    "addr:full":"88, Rue Principale, 57510 R\u00e9mering l\u00e8s Puttelange Lorraine",
    "addr:housenumber":"88",
    "addr:postcode":"57510",
    "addr:street":"Rue Principale;Puttelange",
    "iso:country":"FR",
    "sg:address":"88, Rue Principale, 57510 R\u00e9mering l\u00e8s Puttelange",
    "sg:orig_category":"Unclassifiable Establishments",
    "sg:phone":"+33 3 87 09 40 78",
    "sg:province":"Lorraine",
    "wof:name":"Schorung S.a.r.l.",
    "wof:placetype":"venue"
},
  "geometry": {"coordinates":[6.940215,49.03553],"type":"Point"}
}