{
  "type": "Feature",
  "properties": {
    "addr:full":"118 rue Saint Jacques; Douai; 59500 Nord Pas-de-Calais 59500",
    "addr:housenumber":"118",
    "addr:postcode":"59500;59500",
    "addr:street":"Rue Saint Jacques Douai",
    "iso:country":"FR",
    "sg:address":"118 rue Saint Jacques; Douai; 59500",
    "sg:classifiers":[
        {
            "category":"Banks & Credit Unions",
            "subcategory":"Bank",
            "type":"Services"
        }
    ],
    "sg:phone":"+33 27872365",
    "sg:postcode":"59500",
    "sg:province":"Nord Pas-de-Calais",
    "wof:name":"Soci\u00e9t\u00e9 G\u00e9n\u00e9rale",
    "wof:placetype":"venue"
},
  "geometry": {"coordinates":[3.084333,50.371033],"type":"Point"}
}