{
  "type": "Feature",
  "properties": {
    "addr:full":"24, Rue du Faubourg de l'Aumonerie, 86300 Chauvigny Poitou-Charentes",
    "addr:housenumber":"24",
    "addr:postcode":"86300",
    "addr:street":"Rue Du Faubourg De L'Aumonerie",
    "iso:country":"FR",
    "sg:address":"24, Rue du Faubourg de l'Aumonerie, 86300 Chauvigny",
    "sg:orig_category":"Non-Classified Establishments",
    "sg:phone":"+33 5 49 46 36 44",
    "sg:province":"Poitou-Charentes",
    "wof:name":"L.t.p.g. Transports Rideau S.a.r.l. - Les Transports Poitevins Et G\u00e9n\u00e9raux Transports R",
    "wof:placetype":"venue"
},
  "geometry": {"coordinates":[0.646514,46.566139],"type":"Point"}
}