{
  "type": "Feature",
  "properties": {
    "addr:full":"42 Pl Du Gal De Gaulle 50250 La Haye Du Puits Neuville-en-Beaumont Basse Normandie 50250",
    "addr:housenumber":"42",
    "addr:postcode":"50250;50250",
    "addr:street":"Pl Du Gal De Gaulle;Basse",
    "iso:country":"FR",
    "sg:address":"42 Pl Du Gal De Gaulle 50250 La Haye Du Puits",
    "sg:city":"Neuville-en-Beaumont",
    "sg:classifiers":[
        {
            "category":"Shopping",
            "subcategory":"Clothing, Apparel, & Fashions",
            "type":"Retail Goods"
        }
    ],
    "sg:phone":"+33 2 33 46 01 44",
    "sg:postcode":"50250",
    "sg:province":"Basse Normandie",
    "sg:tags":[
        "textile",
        "clothing",
        "clothes"
    ],
    "wof:name":"Lecaplain Nouveautes Sa",
    "wof:placetype":"venue"
},
  "geometry": {"coordinates":[-1.542971,49.289459],"type":"Point"}
}