{
  "type": "Feature",
  "properties": {
    "iso:country":"FR",
    "sg:address":"5 cours de Verdun 01100 Oyonnax",
    "sg:classifiers":[
        {
            "category":"Manufacturing",
            "subcategory":"Metals",
            "type":"Manufacturing & Wholesale Goods"
        }
    ],
    "sg:phone":"+33 4 74 77 02 39",
    "sg:postcode":"01100",
    "sg:province":"Rhone-Alpes",
    "sg:tags":[
        "mould",
        "aluminium",
        "industry",
        "plastic"
    ],
    "wof:name":"Curvat Lacroix Mecanique Sas",
    "wof:placetype":"venue"
},
  "geometry": {"coordinates":[5.658633,46.26984],"type":"Point"}
}