{
  "type": "Feature",
  "properties": {
    "addr:full":"14, Rue du Moulin, 60210 Thieuloy Saint Antoine Picardie",
    "addr:housenumber":"14",
    "addr:postcode":"60210",
    "addr:street":"Rue Du Moulin",
    "iso:country":"FR",
    "sg:address":"14, Rue du Moulin, 60210 Thieuloy Saint Antoine",
    "sg:orig_category":"Non-Classified Establishments",
    "sg:phone":"+33 3 44 46 69 96",
    "sg:province":"Picardie",
    "wof:name":"M.a.p. S.a.r.l. - La Menuiserie Aluminium Et Plastique",
    "wof:placetype":"venue"
},
  "geometry": {"coordinates":[1.947171,49.633823],"type":"Point"}
}