{
  "type": "Feature",
  "properties": {
    "addr:full":"173 Bd De St-Loup 13011 Marseille Poitou-Charentes",
    "addr:housenumber":"173",
    "addr:postcode":"13011",
    "addr:street":"Bd De St-Loup",
    "iso:country":"FR",
    "sg:address":"173 Bd De St-Loup 13011 Marseille",
    "sg:classifiers":[
        {
            "category":"Food & Beverages",
            "subcategory":"Groceries & Convenience Stores",
            "type":"Retail Goods"
        }
    ],
    "sg:phone":"+33 4 91 44 89 87",
    "sg:province":"Poitou-Charentes",
    "sg:tags":[
        "product",
        "grain",
        "cereal",
        "related"
    ],
    "wof:name":"Anepia Sa",
    "wof:placetype":"venue"
},
  "geometry": {"coordinates":[5.438063,43.284889],"type":"Point"}
}