{
  "type": "Feature",
  "properties": {
    "addr:full":"11, Rue Fran\u00e7ois Verdier - ZA, 31830 Plaisance du Touch Midi Pyr\u00e9n\u00e9es",
    "addr:housenumber":"11",
    "addr:postcode":"31830",
    "addr:street":"Rue Franc\u0327Ois Verdier Za",
    "iso:country":"FR",
    "sg:address":"11, Rue Fran\u00e7ois Verdier - ZA, 31830 Plaisance du Touch",
    "sg:orig_category":"Non-Classified Establishments",
    "sg:phone":"+33 5 61 86 21 60",
    "sg:province":"Midi Pyr\u00e9n\u00e9es",
    "wof:name":"G.e.a. Matal S.a.",
    "wof:placetype":"venue"
},
  "geometry": {"coordinates":[1.287604,43.562386],"type":"Point"}
}