{
  "type": "Feature",
  "properties": {
    "iso:country":"FR",
    "sg:address":"2 Place George Sand",
    "sg:city":"Bourges",
    "sg:classifiers":[
        {
            "category":"Banks & Credit Unions",
            "subcategory":"Financial Services",
            "type":"Services"
        }
    ],
    "sg:phone":"+33 2 48 69 78 30",
    "sg:postcode":"18000",
    "sg:province":"Centre",
    "sg:tags":[
        "banking",
        "finance",
        "insurance"
    ],
    "wof:name":"Azur Assurances Iard",
    "wof:placetype":"venue"
},
  "geometry": {"coordinates":[2.39812,47.08374],"type":"Point"}
}