{
  "type": "Feature",
  "properties": {
    "iso:country":"FR",
    "sg:address":"74, Bd de l'Industrie, 53940 Saint Berthevin",
    "sg:orig_category":"Non-Classified Establishments",
    "sg:phone":"+33 2 43 69 22 12",
    "sg:province":"Pays de Loire",
    "wof:name":"Modelage R\u00e9gent S.a.r.l.",
    "wof:placetype":"venue"
},
  "geometry": {"coordinates":[-0.81588,48.06382],"type":"Point"}
}