{
  "type": "Feature",
  "properties": {
    "iso:country":"FR",
    "sg:address":"Za Grand Banc 08000 La Francheville",
    "sg:city":"Charleville-M\u00e9zi\u00e8res",
    "sg:classifiers":[
        {
            "category":"Professional",
            "subcategory":"Engineering",
            "type":"Services"
        }
    ],
    "sg:phone":"+33 3 24 37 44 44",
    "sg:postcode":"08000",
    "sg:province":"Champagne",
    "sg:tags":[
        "machine",
        "-",
        "mechanical"
    ],
    "wof:name":"Frigeclim Sa",
    "wof:placetype":"venue"
},
  "geometry": {"coordinates":[4.713027,49.72868],"type":"Point"}
}