{
  "type": "Feature",
  "properties": {
    "iso:country":"FR",
    "sg:address":"13, Rue de la R\u00e9publique, 57380 Faulquemont",
    "sg:orig_category":"Non-Classified Establishments",
    "sg:phone":"+33 3 87 90 71 15",
    "sg:postcode":"57380",
    "sg:province":"Lorraine",
    "wof:name":"Docu-vit S.a.r.l.",
    "wof:placetype":"venue"
},
  "geometry": {"coordinates":[6.598612,49.041309],"type":"Point"}
}