{
  "type": "Feature",
  "properties": {
    "iso:country":"FR",
    "sg:address":"B.P. 38, 13367 Marseille C\u00e9dex 11^^61, Bd de la Cartonnerie, 13000 Marseille",
    "sg:orig_category":"Non-Classified Establishments",
    "sg:phone":"+33 4 91 87 61 20",
    "sg:province":"Poitou-Charentes",
    "wof:name":"Socarei Enco S.a.r.l.",
    "wof:placetype":"venue"
},
  "geometry": {"coordinates":[5.37249,43.293686],"type":"Point"}
}