{
  "type": "Feature",
  "properties": {
    "iso:country":"FR",
    "sg:address":"Le Graveray 61300 ST SULPICE SUR RISLE",
    "sg:city":"Chandai",
    "sg:classifiers":[
        {
            "category":"Manufacturing",
            "subcategory":"Lumber",
            "type":"Manufacturing & Wholesale Goods"
        }
    ],
    "sg:phone":"+33 2 33 24 24 77",
    "sg:postcode":"61300",
    "sg:province":"Basse Normandie",
    "sg:tags":[
        "hardwood",
        "sawmill"
    ],
    "wof:name":"Ste Expl Des Scieries Leloup Sarl",
    "wof:placetype":"venue"
},
  "geometry": {"coordinates":[0.66727,48.70697],"type":"Point"}
}