{
  "type": "Feature",
  "properties": {
    "addr:full":"B.P. 102, 89400 Migennes^^Rue Poincar\u00e9 - Zone Industrielle du Moutois, 89400 Migennes Migennes Bourgogne 89400",
    "addr:housenumber":"b.p. 102",
    "addr:postcode":"89400;89400;89400",
    "addr:street":"Poincare\u0301 Zone Industrielle Du Moutois",
    "iso:country":"FR",
    "sg:address":"B.P. 102, 89400 Migennes^^Rue Poincar\u00e9 - Zone Industrielle du Moutois, 89400 Migennes",
    "sg:city":"Migennes",
    "sg:orig_category":"Non-Classified Establishments",
    "sg:phone":"+33 3 86 92 62 50",
    "sg:postcode":"89400",
    "sg:province":"Bourgogne",
    "wof:name":"F.f.f. S.a. - Fabrication Et Formage De Fonds",
    "wof:placetype":"venue"
},
  "geometry": {"coordinates":[3.51162,47.963699],"type":"Point"}
}