{
  "type": "Feature",
  "properties": {
    "iso:country":"FR",
    "sg:address":"14 Rue Joseph Cugnot 57070 Metz",
    "sg:classifiers":[
        {
            "category":"Food & Beverages",
            "subcategory":"Dairy",
            "type":"Retail Goods"
        }
    ],
    "sg:phone":"+33 3 87 75 38 15",
    "sg:postcode":"57070",
    "sg:province":"Lorraine",
    "sg:tags":[
        "product",
        "related"
    ],
    "wof:name":"Relais D'or - Miko",
    "wof:placetype":"venue"
},
  "geometry": {"coordinates":[6.243304,49.11797],"type":"Point"}
}