{
  "type": "Feature",
  "properties": {
    "addr:full":"11 Rue Georges Honor\u00e9 BP 447 62206 Boulogne Sur Mer Centre",
    "addr:housenumber":"11;447",
    "addr:postcode":"62206",
    "addr:street":"Rue Georges Honore\u0301 Bp;Mer",
    "iso:country":"FR",
    "sg:address":"11 Rue Georges Honor\u00e9 BP 447 62206 Boulogne Sur Mer",
    "sg:classifiers":[
        {
            "category":"Farming",
            "subcategory":"Livestock Farm",
            "type":"Manufacturing & Wholesale Goods"
        }
    ],
    "sg:phone":"+33 3 21 33 82 33",
    "sg:province":"Centre",
    "sg:tags":[
        "breeding",
        "agriculture",
        "animal"
    ],
    "wof:name":"Nord Pecheries (sa)",
    "wof:placetype":"venue"
},
  "geometry": {"coordinates":[1.594247,50.72192],"type":"Point"}
}