{
  "type": "Feature",
  "properties": {
    "addr:full":"av du Pdt John Kennedy 87000 Limoges Limousin 87000",
    "addr:postcode":"87000;87000",
    "addr:street":"Av Du Pdt John Kennedy",
    "iso:country":"FR",
    "sg:address":"av du Pdt John Kennedy 87000 Limoges",
    "sg:classifiers":[
        {
            "category":"Manufacturing",
            "subcategory":"Pottery",
            "type":"Manufacturing & Wholesale Goods"
        }
    ],
    "sg:phone":"+33 5 55 30 26 23",
    "sg:postcode":"87000",
    "sg:province":"Limousin",
    "sg:tags":[
        "decorative",
        "porcelain"
    ],
    "wof:name":"Porcelaines Limoges Castel S.a.r.l.",
    "wof:placetype":"venue"
},
  "geometry": {"coordinates":[1.286561,45.804707],"type":"Point"}
}