{
  "type": "Feature",
  "properties": {
    "iso:country":"FR",
    "sg:address":"7 Rue De Thues 66000 Perpignan",
    "sg:classifiers":[
        {
            "category":"Shopping",
            "subcategory":"Clothing, Apparel, & Fashions",
            "type":"Retail Goods"
        }
    ],
    "sg:phone":"+33 4 68 51 31 38",
    "sg:postcode":"66000",
    "sg:province":"Languedoc-Roussillon",
    "sg:tags":[
        "textile",
        "clothing",
        "clothes"
    ],
    "wof:name":"Sarl Tricot Dio",
    "wof:placetype":"venue"
},
  "geometry": {"coordinates":[2.88154,42.699799],"type":"Point"}
}