{
  "type": "Feature",
  "properties": {
    "iso:country":"FR",
    "sg:address":"49/51, Av. Marceau, 92400 Courbevoie",
    "sg:orig_category":"Unclassifiable Establishments",
    "sg:phone":"+33 1 46 67 33 55",
    "sg:province":"Ile de France",
    "wof:name":"Com\u00e9tam S.a.",
    "wof:placetype":"venue"
},
  "geometry": {"coordinates":[2.244801,48.900291],"type":"Point"}
}