{
  "type": "Feature",
  "properties": {
    "addr:full":"9 Soustons Aquitaine 40140",
    "addr:housenumber":"9",
    "addr:postcode":"40140",
    "iso:country":"FR",
    "sg:address":"9",
    "sg:city":"Soustons",
    "sg:classifiers":[
        {
            "category":"Home & Garden",
            "subcategory":"Furniture",
            "type":"Retail Goods"
        }
    ],
    "sg:phone":"+33 5 58 41 18 65",
    "sg:postcode":"40140",
    "sg:province":"Aquitaine",
    "sg:tags":[
        "wood"
    ],
    "wof:name":"Au Liegeur",
    "wof:placetype":"venue"
},
  "geometry": {"coordinates":[-1.331412,43.750694],"type":"Point"}
}