{
  "type": "Feature",
  "properties": {
    "addr:full":"B.P. 35, 69632 V\u00e9nissieux C\u00e9dex^^9, Rue Marx Dormoy, 69200 V\u00e9nissieux Rhone-Alpes",
    "addr:postcode":"69632;69200",
    "addr:street":"B.P. 35;Rue Marx Dormoy",
    "iso:country":"FR",
    "sg:address":"B.P. 35, 69632 V\u00e9nissieux C\u00e9dex^^9, Rue Marx Dormoy, 69200 V\u00e9nissieux",
    "sg:orig_category":"Non-Classified Establishments",
    "sg:phone":"+33 4 78 78 48 78",
    "sg:province":"Rhone-Alpes",
    "wof:name":"Eurodec S.a.",
    "wof:placetype":"venue"
},
  "geometry": {"coordinates":[4.885109,45.696575],"type":"Point"}
}