{
  "type": "Feature",
  "properties": {
    "addr:full":"2 du Mar\u00e9chal Foch; Sarrebourg; 57403 Languedoc-Roussillon",
    "addr:housenumber":"2",
    "addr:postcode":"57403",
    "addr:street":"Du Mare\u0301Chal Foch",
    "iso:country":"FR",
    "sg:address":"2",
    "sg:city":"du Mar\u00e9chal Foch; Sarrebourg; 57403",
    "sg:classifiers":[
        {
            "category":"Banks & Credit Unions",
            "subcategory":"Bank",
            "type":"Services"
        }
    ],
    "sg:phone":"+33 3387031021",
    "sg:province":"Languedoc-Roussillon",
    "wof:name":"Soci\u00e9t\u00e9 G\u00e9n\u00e9rale",
    "wof:placetype":"venue"
},
  "geometry": {"coordinates":[7.056513,48.734604],"type":"Point"}
}