{
  "type": "Feature",
  "properties": {
    "addr:full":"167, Rue Nationale, 57600 Forbach Lorraine",
    "addr:housenumber":"167",
    "addr:postcode":"57600",
    "addr:street":"Rue Nationale",
    "iso:country":"FR",
    "sg:address":"167, Rue Nationale, 57600 Forbach",
    "sg:orig_category":"Unclassifiable Establishments",
    "sg:phone":"+33 3 87 85 25 51",
    "sg:province":"Lorraine",
    "wof:name":"S.i.a.l. S.a.r.l. - Soci\u00e9t\u00e9 Int\u00e9rimaire D'alsace Et De Lorraine",
    "wof:placetype":"venue"
},
  "geometry": {"coordinates":[6.895146,49.184753],"type":"Point"}
}