{
  "type": "Feature",
  "properties": {
    "addr:full":"Rte des Groises - ZA Sancergues Centre 18140",
    "addr:postcode":"18140",
    "addr:street":"Rte Des Groises Za Sancergues",
    "iso:country":"FR",
    "sg:address":"Rte des Groises - ZA",
    "sg:city":"Sancergues",
    "sg:orig_category":"Non-Classified Establishments",
    "sg:phone":"+33 2 48 69 78 00",
    "sg:postcode":"18140",
    "sg:province":"Centre",
    "wof:name":"Valoiris S.a.r.l.",
    "wof:placetype":"venue"
},
  "geometry": {"coordinates":[2.88763,47.086769],"type":"Point"}
}