{
  "type": "Feature",
  "properties": {
    "iso:country":"FR",
    "sg:address":"265 Route De La Baronne Zi Le Fongeri 06640 St Jeannet",
    "sg:classifiers":[
        {
            "category":"Shopping",
            "subcategory":"Crafts & Fabrics",
            "type":"Retail Goods"
        }
    ],
    "sg:phone":"+33 4 92 12 04 00",
    "sg:province":"Pays de Loire",
    "sg:tags":[
        "textile",
        "linen",
        "clothing"
    ],
    "wof:name":"Azur Scenic",
    "wof:placetype":"venue"
},
  "geometry": {"coordinates":[7.14787,43.746399],"type":"Point"}
}