{
  "type": "Feature",
  "properties": {
    "addr:full":"146, Rue de Stasbourg, 49300 Cholet Pays de Loire",
    "addr:housenumber":"146",
    "addr:postcode":"49300",
    "addr:street":"Rue De Stasbourg",
    "iso:country":"FR",
    "sg:address":"146, Rue de Stasbourg, 49300 Cholet",
    "sg:orig_category":"Unclassifiable Establishments",
    "sg:phone":"+33 2 41 58 36 05",
    "sg:province":"Pays de Loire",
    "wof:name":"Transmission Plus E.u.r.l.",
    "wof:placetype":"venue"
},
  "geometry": {"coordinates":[-0.875431,47.070396],"type":"Point"}
}