{
  "type": "Feature",
  "properties": {
    "addr:full":"21 Rue Benjamin Constant 31400 Toulouse Midi Pyr\u00e9n\u00e9es 31400",
    "addr:housenumber":"21",
    "addr:postcode":"31400;31400",
    "addr:street":"Rue Benjamin Constant",
    "iso:country":"FR",
    "sg:address":"21 Rue Benjamin Constant 31400 Toulouse",
    "sg:classifiers":[
        {
            "category":"Wholesale",
            "subcategory":"Machinery & Supplies",
            "type":"Manufacturing & Wholesale Goods"
        }
    ],
    "sg:phone":"+33 5 61 52 92 19",
    "sg:postcode":"31400",
    "sg:province":"Midi Pyr\u00e9n\u00e9es",
    "sg:tags":[
        "food",
        "processing",
        "-",
        "machine",
        "equipment",
        "engineering",
        "mechanical"
    ],
    "wof:name":"Glaces Polaire",
    "wof:placetype":"venue"
},
  "geometry": {"coordinates":[1.455379,43.593876],"type":"Point"}
}