{
  "type": "Feature",
  "properties": {
    "addr:full":"88 B Av Colbert 58000 Nevers Nevers Bourgogne 58000",
    "addr:housenumber":"88",
    "addr:postcode":"58000;58000",
    "addr:street":"B Av Colbert",
    "iso:country":"FR",
    "sg:address":"88 B Av Colbert 58000 Nevers",
    "sg:city":"Nevers",
    "sg:classifiers":[
        {
            "category":"Social Services",
            "subcategory":"Retirement Home",
            "type":"Services"
        }
    ],
    "sg:phone":"+33 3 86 61 19 25",
    "sg:postcode":"58000",
    "sg:province":"Bourgogne",
    "sg:tags":[
        "ceramic",
        "wood",
        "household",
        "good",
        "furniture"
    ],
    "wof:name":"Faiencerie D'art De Nevers",
    "wof:placetype":"venue"
},
  "geometry": {"coordinates":[3.156223,46.998356],"type":"Point"}
}