{
  "type": "Feature",
  "properties": {
    "addr:full":"Rte de Vigan Gourdon Midi Pyr\u00e9n\u00e9es 46300",
    "addr:postcode":"46300",
    "addr:street":"Rte De Vigan Gourdon",
    "iso:country":"FR",
    "sg:address":"Rte de Vigan",
    "sg:city":"Gourdon",
    "sg:orig_category":"Unclassifiable Establishments",
    "sg:phone":"+33 5 65 41 47 01",
    "sg:postcode":"46300",
    "sg:province":"Midi Pyr\u00e9n\u00e9es",
    "wof:name":"Loubi\u00e8res Et Compagnie S.a.r.l.",
    "wof:placetype":"venue"
},
  "geometry": {"coordinates":[1.401795,44.74099],"type":"Point"}
}