{
  "type": "Feature",
  "properties": {
    "addr:full":"20, Rue de la Commanderie, 67120 Molsheim Molsheim Alsace 67120",
    "addr:housenumber":"20",
    "addr:postcode":"67120;67120",
    "addr:street":"Rue De La Commanderie",
    "iso:country":"FR",
    "sg:address":"20, Rue de la Commanderie, 67120 Molsheim",
    "sg:city":"Molsheim",
    "sg:orig_category":"Non-Classified Establishments",
    "sg:phone":"+33 3 88 38 11 07",
    "sg:postcode":"67120",
    "sg:province":"Alsace",
    "wof:name":"Feidt Scierie S.a.",
    "wof:placetype":"venue"
},
  "geometry": {"coordinates":[7.497291,48.531345],"type":"Point"}
}