{
  "type": "Feature",
  "properties": {
    "iso:country":"FR",
    "sg:address":"ZAC DE LA GOULGATIERE 35220 CHATEAUBOURG",
    "sg:city":"Ch\u00e2teaubourg",
    "sg:classifiers":[
        {
            "category":"Manufacturing",
            "subcategory":"Electronics",
            "type":"Manufacturing & Wholesale Goods"
        }
    ],
    "sg:phone":"+33 2 99 00 37 03",
    "sg:postcode":"35220",
    "sg:province":"Bretagne",
    "sg:tags":[
        "pcb",
        "printed",
        "circuit",
        "board"
    ],
    "wof:name":"Avi Et Peschard S.a.",
    "wof:placetype":"venue"
},
  "geometry": {"coordinates":[-1.392459,48.111],"type":"Point"}
}