{
  "type": "Feature",
  "properties": {
    "addr:full":"5, Rue d'Ecosse, 35000 Rennes Rennes Bretagne 35000",
    "addr:housenumber":"5",
    "addr:postcode":"35000;35000",
    "addr:street":"Rue D'Ecosse",
    "iso:country":"FR",
    "sg:address":"5, Rue d'Ecosse, 35000 Rennes",
    "sg:city":"Rennes",
    "sg:orig_category":"Unclassifiable Establishments",
    "sg:phone":"+33 2 99 50 10 38",
    "sg:postcode":"35000",
    "sg:province":"Bretagne",
    "wof:name":"Cabinet Eveno Expertise Comptable S.a.",
    "wof:placetype":"venue"
},
  "geometry": {"coordinates":[-1.68848,48.11203],"type":"Point"}
}