{
  "type": "Feature",
  "properties": {
    "iso:country":"FR",
    "sg:address":"248, Rue Alphonse Daudet - Centre Commercial les Pugets, 06700 Saint Laurent du Var",
    "sg:orig_category":"Unclassifiable Establishments",
    "sg:phone":"+33 4 93 14 02 42",
    "sg:province":"Provence-Alpes-C\u00f4te d'Azur",
    "wof:name":"Astic Services S.a.r.l.",
    "wof:placetype":"venue"
},
  "geometry": {"coordinates":[7.183002,43.685127],"type":"Point"}
}