{
  "type": "Feature",
  "properties": {
    "addr:full":"42 Rte De Saverne 67700 Maennolsheim Saverne Alsace 67700",
    "addr:housenumber":"42",
    "addr:postcode":"67700;67700",
    "addr:street":"Rte De Saverne",
    "iso:country":"FR",
    "sg:address":"42 Rte De Saverne 67700 Maennolsheim",
    "sg:city":"Saverne",
    "sg:classifiers":[
        {
            "category":"Professional",
            "type":"Services"
        }
    ],
    "sg:phone":"+33 3 88 70 27 09",
    "sg:postcode":"67700",
    "sg:province":"Alsace",
    "sg:tags":[
        "transport",
        "road"
    ],
    "wof:name":"Transport Patrick Metz Eurl",
    "wof:placetype":"venue"
},
  "geometry": {"coordinates":[7.450934,48.698345],"type":"Point"}
}