{
  "type": "Feature",
  "properties": {
    "iso:country":"FR",
    "sg:address":"59, Rte des Roches, 38110 Cessieu",
    "sg:orig_category":"Unclassifiable Establishments",
    "sg:phone":"+33 4 74 33 47 57",
    "sg:postcode":"38110",
    "sg:province":"Rhone-Alpes",
    "wof:name":"S.2.s. S.a.",
    "wof:placetype":"venue"
},
  "geometry": {"coordinates":[5.368005,45.572723],"type":"Point"}
}