{
  "type": "Feature",
  "properties": {
    "iso:country":"FR",
    "sg:address":"148, Rte des Trois Lucs \u00e0 la Valentine, 13012 Marseille",
    "sg:orig_category":"Unclassifiable Establishments",
    "sg:phone":"+33 4 91 87 51 30",
    "sg:province":"Poitou-Charentes",
    "wof:name":"Si\u00e9pa S.a.",
    "wof:placetype":"venue"
},
  "geometry": {"coordinates":[5.470102,43.307194],"type":"Point"}
}