{
  "type": "Feature",
  "properties": {
    "addr:full":"Bd Saragat Saint Gaudens C\u00e9dex Midi Pyr\u00e9n\u00e9es 31803",
    "addr:postcode":"31803",
    "addr:street":"Bd Saragat Saint Gaudens Ce\u0301Dex",
    "iso:country":"FR",
    "sg:address":"Bd Saragat",
    "sg:city":"Saint Gaudens C\u00e9dex",
    "sg:orig_category":"Non-Classified Establishments",
    "sg:phone":"+33 5 61 94 75 75",
    "sg:postcode":"31803",
    "sg:province":"Midi Pyr\u00e9n\u00e9es",
    "wof:name":"Tembec Saint Gaudens S.a.",
    "wof:placetype":"venue"
},
  "geometry": {"coordinates":[0.727739,43.108955],"type":"Point"}
}