{
  "type": "Feature",
  "properties": {
    "addr:full":"Gare Sncs 60100 Creil Picardie",
    "addr:postcode":"60100",
    "iso:country":"FR",
    "sg:address":"Gare Sncs 60100 Creil",
    "sg:classifiers":[
        {
            "category":"Banks & Credit Unions",
            "subcategory":"Investment Brokerage",
            "type":"Services"
        }
    ],
    "sg:phone":"+33 3 44 55 20 91",
    "sg:province":"Picardie",
    "sg:tags":[
        "-",
        "transport",
        "related"
    ],
    "wof:name":"Geodis Bm",
    "wof:placetype":"venue"
},
  "geometry": {"coordinates":[2.47547,49.259537],"type":"Point"}
}