{
  "type": "Feature",
  "properties": {
    "addr:full":"19/21, Av. Georges V, 75008 Paris Ile de France",
    "addr:housenumber":"19 / 21",
    "addr:postcode":"75008",
    "addr:street":"Av. Georges V",
    "iso:country":"FR",
    "sg:address":"19/21, Av. Georges V, 75008 Paris",
    "sg:orig_category":"Unclassifiable Establishments",
    "sg:phone":"+33 1 40 69 66 40",
    "sg:province":"Ile de France",
    "wof:name":"Etablissement Dor\u00e9-dor\u00e9 S.a.",
    "wof:placetype":"venue"
},
  "geometry": {"coordinates":[2.30088,48.866951],"type":"Point"}
}