{
  "type": "Feature",
  "properties": {
    "iso:country":"FR",
    "sg:address":"Rte de Grignols",
    "sg:city":"Bazas",
    "sg:orig_category":"Unclassifiable Establishments",
    "sg:phone":"+33 5 56 25 01 76",
    "sg:postcode":"33430",
    "sg:province":"Aquitaine",
    "wof:name":"C\u00e9ramique De La Gironde S.a.",
    "wof:placetype":"venue"
},
  "geometry": {"coordinates":[-0.197015,44.430569],"type":"Point"}
}