{
  "type": "Feature",
  "properties": {
    "iso:country":"FR",
    "sg:address":"41 Boulevard Montfleury 06400 Cannes",
    "sg:classifiers":[
        {
            "category":"Wholesale",
            "subcategory":"Medical Equipment & Supplies",
            "type":"Manufacturing & Wholesale Goods"
        }
    ],
    "sg:phone":"+33 4 93 99 03 53",
    "sg:province":"Centre",
    "sg:tags":[
        "instrument",
        "health",
        "-",
        "precision"
    ],
    "wof:name":"Azur Dental",
    "wof:placetype":"venue"
},
  "geometry": {"coordinates":[7.031668,43.555965],"type":"Point"}
}