{
  "type": "Feature",
  "properties": {
    "addr:full":"Rue Oradour Sur Glane 95270 Chaumontel Ile de France 95270",
    "addr:postcode":"95270;ile;95270",
    "addr:street":"Rue Oradour Sur Glane;France",
    "iso:country":"FR",
    "sg:address":"Rue Oradour Sur Glane 95270 Chaumontel",
    "sg:classifiers":[
        {
            "category":"Manufacturing",
            "subcategory":"Motor Vehicles & Parts",
            "type":"Manufacturing & Wholesale Goods"
        }
    ],
    "sg:phone":"+33 1 30 29 58 88",
    "sg:postcode":"95270",
    "sg:province":"Ile de France",
    "sg:tags":[
        "engine",
        "machine",
        "engineering",
        "-",
        "mechanical"
    ],
    "wof:name":"Engrenages Ribaut",
    "wof:placetype":"venue"
},
  "geometry": {"coordinates":[2.426366,49.11882],"type":"Point"}
}