{
  "type": "Feature",
  "properties": {
    "addr:full":"B.P. 92, 42402 Saint Chamond C\u00e9dex^^ZI de Fonsala, 42400 Saint Chamond Rhone-Alpes 42400",
    "addr:postcode":"42402;42400 saint;42400",
    "addr:street":"B.P. 92;Chamond;Chamond Rhone-Alpes",
    "iso:country":"FR",
    "sg:address":"B.P. 92, 42402 Saint Chamond C\u00e9dex^^ZI de Fonsala, 42400 Saint Chamond",
    "sg:orig_category":"Non-Classified Establishments",
    "sg:phone":"+33 4 77 31 73 73",
    "sg:postcode":"42400",
    "sg:province":"Rhone-Alpes",
    "wof:name":"Rafer S.a.",
    "wof:placetype":"venue"
},
  "geometry": {"coordinates":[4.529112,45.471375],"type":"Point"}
}