{
  "type": "Feature",
  "properties": {
    "addr:full":"333 Avenue De Verdun 33700 M\u00e9rignac M\u00e9rignac Aquitaine 33700",
    "addr:housenumber":"333",
    "addr:postcode":"33700;33700",
    "addr:street":"Avenue De Verdun",
    "iso:country":"FR",
    "sg:address":"333 Avenue De Verdun 33700 M\u00e9rignac",
    "sg:city":"M\u00e9rignac",
    "sg:classifiers":[
        {
            "category":"Bakery",
            "type":"Food & Drink"
        }
    ],
    "sg:phone":"+33 5 56 97 94 21",
    "sg:postcode":"33700",
    "sg:province":"Aquitaine",
    "sg:tags":[
        "cake",
        "product",
        "related",
        "bread"
    ],
    "wof:name":"Le Fournil 85",
    "wof:placetype":"venue"
},
  "geometry": {"coordinates":[-0.631829,44.83934],"type":"Point"}
}