{
  "type": "Feature",
  "properties": {
    "addr:full":"1 Rue De Bourgogne 89000 Auxerre Auxerre Bourgogne 89000",
    "addr:housenumber":"1",
    "addr:postcode":"89000;89000",
    "addr:street":"Rue De Bourgogne",
    "iso:country":"FR",
    "sg:address":"1 Rue De Bourgogne 89000 Auxerre",
    "sg:city":"Auxerre",
    "sg:classifiers":[
        {
            "category":"Manufacturing",
            "subcategory":"Textiles",
            "type":"Manufacturing & Wholesale Goods"
        }
    ],
    "sg:phone":"+33 3 86 52 53 48",
    "sg:postcode":"89000",
    "sg:province":"Bourgogne",
    "sg:tags":[
        "clothing",
        "accessory"
    ],
    "wof:name":"Ets Genete Sa",
    "wof:placetype":"venue"
},
  "geometry": {"coordinates":[3.580896,47.786774],"type":"Point"}
}