{
  "type": "Feature",
  "properties": {
    "addr:full":"13 Rue De Deux Tons 18230 St Doulchard Saint-Doulchard Centre 18230",
    "addr:housenumber":"13",
    "addr:postcode":"18230;18230",
    "addr:street":"Rue De Deux Tons",
    "iso:country":"FR",
    "sg:address":"13 Rue De Deux Tons 18230 St Doulchard",
    "sg:city":"Saint-Doulchard",
    "sg:classifiers":[
        {
            "category":"Manufacturing",
            "subcategory":"Rubber & Plastics",
            "type":"Manufacturing & Wholesale Goods"
        }
    ],
    "sg:phone":"+33 2 48 68 88 23",
    "sg:postcode":"18230",
    "sg:province":"Centre",
    "wof:name":"Michelin",
    "wof:placetype":"venue"
},
  "geometry": {"coordinates":[2.35792,47.104084],"type":"Point"}
}