{
  "type": "Feature",
  "properties": {
    "addr:full":"Rte Palmas 12310 Laissac Midi Pyr\u00e9n\u00e9es 12310",
    "addr:postcode":"12310;12310",
    "addr:street":"Rte Palmas",
    "iso:country":"FR",
    "sg:address":"Rte Palmas 12310 Laissac",
    "sg:classifiers":[
        {
            "category":"Farming",
            "subcategory":"Farm & Veterinary Services",
            "type":"Manufacturing & Wholesale Goods"
        }
    ],
    "sg:phone":"+33 5 65 69 61 45",
    "sg:postcode":"12310",
    "sg:province":"Midi Pyr\u00e9n\u00e9es",
    "sg:tags":[
        "food",
        "product",
        "breeding",
        "animal",
        "related"
    ],
    "wof:name":"Sca Unicorpoint Vert",
    "wof:placetype":"venue"
},
  "geometry": {"coordinates":[2.929336,44.354931],"type":"Point"}
}