{
  "type": "Feature",
  "properties": {
    "addr:full":"23, Rue d'Aiguillon, 35200 Rennes Rennes Bretagne 35200",
    "addr:housenumber":"23",
    "addr:postcode":"35200;35200",
    "addr:street":"Rue D'Aiguillon",
    "iso:country":"FR",
    "sg:address":"23, Rue d'Aiguillon, 35200 Rennes",
    "sg:city":"Rennes",
    "sg:orig_category":"Non-Classified Establishments",
    "sg:phone":"+33 2 99 53 54 00",
    "sg:postcode":"35200",
    "sg:province":"Bretagne",
    "wof:name":"A.t.c.s.",
    "wof:placetype":"venue"
},
  "geometry": {"coordinates":[-1.684577,48.092613],"type":"Point"}
}