{
  "type": "Feature",
  "properties": {
    "addr:full":"Rue Des Barronnieres 01700 Beynost Rhone-Alpes 01700",
    "addr:postcode":"01700;01700",
    "addr:street":"Rue Des Barronnieres",
    "iso:country":"FR",
    "sg:address":"Rue Des Barronnieres 01700 Beynost",
    "sg:classifiers":[
        {
            "category":"Professional",
            "subcategory":"Engineering",
            "type":"Services"
        }
    ],
    "sg:phone":"+33 4 72 88 11 11",
    "sg:postcode":"01700",
    "sg:province":"Rhone-Alpes",
    "sg:tags":[
        "machine",
        "-",
        "mechanical"
    ],
    "wof:name":"France Air",
    "wof:placetype":"venue"
},
  "geometry": {"coordinates":[5.006791,45.833256],"type":"Point"}
}