{
  "type": "Feature",
  "properties": {
    "addr:full":"Usine Tannebrune Charleval Haute Normandie 27380",
    "addr:postcode":"27380",
    "iso:country":"FR",
    "sg:address":"Usine Tannebrune",
    "sg:city":"Charleval",
    "sg:orig_category":"Unclassifiable Establishments",
    "sg:phone":"+33 2 32 68 33 44",
    "sg:postcode":"27380",
    "sg:province":"Haute Normandie",
    "wof:name":"Caudrillier S.a.",
    "wof:placetype":"venue"
},
  "geometry": {"coordinates":[1.340605,49.378746],"type":"Point"}
}