{
  "type": "Feature",
  "properties": {
    "iso:country":"FR",
    "sg:address":"Parc d'Activit\u00e9 de Berlange",
    "sg:city":"Woippy",
    "sg:orig_category":"Unclassifiable Establishments",
    "sg:phone":"+33 3 87 30 64 60",
    "sg:postcode":"57140",
    "sg:province":"Lorraine",
    "wof:name":"Adislor S.a.",
    "wof:placetype":"venue"
},
  "geometry": {"coordinates":[6.157838,49.152752],"type":"Point"}
}