{
  "type": "Feature",
  "properties": {
    "addr:full":"59 Route Du Village D En Haut 18230 St Doulchard Saint-Doulchard Centre 18230",
    "addr:housenumber":"59",
    "addr:postcode":"18230;18230",
    "addr:street":"Route Du Village D En Haut",
    "iso:country":"FR",
    "sg:address":"59 Route Du Village D En Haut 18230 St Doulchard",
    "sg:city":"Saint-Doulchard",
    "sg:classifiers":[
        {
            "category":"Shopping",
            "subcategory":"Clothing, Apparel, & Fashions",
            "type":"Retail Goods"
        }
    ],
    "sg:phone":"+33 2 48 24 61 81",
    "sg:postcode":"18230",
    "sg:province":"Centre",
    "sg:tags":[
        "textile",
        "clothing",
        "clothes"
    ],
    "wof:name":"P Tit Bout Family",
    "wof:placetype":"venue"
},
  "geometry": {"coordinates":[2.345233,47.107243],"type":"Point"}
}