{
  "type": "Feature",
  "properties": {
    "iso:country":"FR",
    "sg:address":"19, Bd des Nations Unies, 92190 Meudon",
    "sg:orig_category":"Unclassifiable Establishments",
    "sg:phone":"+33 1 46 23 11 11",
    "sg:province":"Ile de France",
    "wof:name":"Scarlett S.a.",
    "wof:placetype":"venue"
},
  "geometry": {"coordinates":[2.23594,48.813347],"type":"Point"}
}