{
  "type": "Feature",
  "properties": {
    "addr:full":"Rue des M\u00e9tiers - Zone Activit\u00e9 de la Parfonterie Granville Basse Normandie 50400",
    "addr:postcode":"50400",
    "addr:street":"Rue Des Me\u0301Tiers Zone Activite\u0301 De La Parfonterie;Basse",
    "iso:country":"FR",
    "sg:address":"Rue des M\u00e9tiers - Zone Activit\u00e9 de la Parfonterie",
    "sg:city":"Granville",
    "sg:orig_category":"Unclassifiable Establishments",
    "sg:phone":"+33 2 33 90 66 24",
    "sg:postcode":"50400",
    "sg:province":"Basse Normandie",
    "wof:name":"Entreprise Fouchard S.a.",
    "wof:placetype":"venue"
},
  "geometry": {"coordinates":[-1.598484,48.838661],"type":"Point"}
}