{
  "type": "Feature",
  "properties": {
    "addr:full":"383 route d'Entraigues 84700 Sorgues Entraigues Auvergne 63720",
    "addr:housenumber":"383",
    "addr:postcode":"84700;63720",
    "addr:street":"Route D'Entraigues",
    "iso:country":"FR",
    "sg:address":"383 route d'Entraigues 84700 Sorgues",
    "sg:city":"Entraigues",
    "sg:classifiers":[
        {
            "category":"Home & Garden",
            "subcategory":"Furniture",
            "type":"Retail Goods"
        }
    ],
    "sg:phone":"+33 4 90 39 21 56",
    "sg:postcode":"63720",
    "sg:province":"Auvergne",
    "wof:name":"Au Venaissin Sa",
    "wof:placetype":"venue"
},
  "geometry": {"coordinates":[4.876366,44.00819],"type":"Point"}
}