{
  "type": "Feature",
  "properties": {
    "addr:full":"Zi Dioulan 29140 Rosporden Rosporden Bretagne 29140",
    "addr:postcode":"29140;29140",
    "addr:street":"Rosporden",
    "iso:country":"FR",
    "sg:address":"Zi Dioulan 29140 Rosporden",
    "sg:city":"Rosporden",
    "sg:classifiers":[
        {
            "category":"Banks & Credit Unions",
            "subcategory":"Investment Brokerage",
            "type":"Services"
        }
    ],
    "sg:phone":"+33 2 98 59 88 95",
    "sg:postcode":"29140",
    "sg:province":"Bretagne",
    "sg:tags":[
        "-",
        "transport",
        "related"
    ],
    "wof:name":"Bretagne Frigo",
    "wof:placetype":"venue"
},
  "geometry": {"coordinates":[-3.829804,47.95916],"type":"Point"}
}