{
  "type": "Feature",
  "properties": {
    "addr:full":"146 avenue des Etats-Unis 31200 Toulouse Midi Pyr\u00e9n\u00e9es 31200",
    "addr:housenumber":"146",
    "addr:postcode":"31200;31200",
    "addr:street":"Avenue Des Etats-Unis",
    "iso:country":"FR",
    "sg:address":"146 avenue des Etats-Unis 31200 Toulouse",
    "sg:classifiers":[
        {
            "category":"Banks & Credit Unions",
            "subcategory":"Financial Services",
            "type":"Services"
        }
    ],
    "sg:phone":"+33 5 61 47 60 61",
    "sg:postcode":"31200",
    "sg:province":"Midi Pyr\u00e9n\u00e9es",
    "sg:tags":[
        "wreath",
        "spray",
        "flower"
    ],
    "wof:name":"La Riviere Sa",
    "wof:placetype":"venue"
},
  "geometry": {"coordinates":[1.430138,43.637642],"type":"Point"}
}