{
  "type": "Feature",
  "properties": {
    "iso:country":"FR",
    "sg:address":"Zi De Kersal\u00e9 29900 Concarneau",
    "sg:city":"Concarneau",
    "sg:classifiers":[
        {
            "category":"Shopping",
            "type":"Retail Goods"
        }
    ],
    "sg:phone":"+33 2 98 97 26 08",
    "sg:postcode":"29900",
    "sg:province":"Bretagne",
    "sg:tags":[
        "metallurgy",
        "finished",
        "-",
        "metalworking",
        "metallic"
    ],
    "wof:name":"Metal Db Sa",
    "wof:placetype":"venue"
},
  "geometry": {"coordinates":[-3.917344,47.871864],"type":"Point"}
}