{
  "type": "Feature",
  "properties": {
    "addr:full":"21, Rue du Moulin au Roy, 14000 Caen Caen Basse Normandie 14000",
    "addr:housenumber":"21",
    "addr:postcode":"14000;14000",
    "addr:street":"Rue Du Moulin Au Roy",
    "iso:country":"FR",
    "sg:address":"21, Rue du Moulin au Roy, 14000 Caen",
    "sg:city":"Caen",
    "sg:orig_category":"Unclassifiable Establishments",
    "sg:phone":"+33 2 31 56 64 64",
    "sg:postcode":"14000",
    "sg:province":"Basse Normandie",
    "wof:name":"D\u00e9l\u00e9guation R\u00e9gionale De L'o.n.i.s.e.p.",
    "wof:placetype":"venue"
},
  "geometry": {"coordinates":[-0.361249,49.194611],"type":"Point"}
}