{
  "type": "Feature",
  "properties": {
    "addr:full":"ZA les Marli\u00e8res Avelin Nord Pas-de-Calais 59710",
    "addr:postcode":"59710",
    "addr:street":"Za Les;Avelin;Pas-De-Calais",
    "iso:country":"FR",
    "sg:address":"ZA les Marli\u00e8res",
    "sg:city":"Avelin",
    "sg:orig_category":"Non-Classified Establishments",
    "sg:phone":"+33 3 20 62 56 80",
    "sg:postcode":"59710",
    "sg:province":"Nord Pas-de-Calais",
    "wof:name":"Autinor S.a.",
    "wof:placetype":"venue"
},
  "geometry": {"coordinates":[3.080295,50.53793],"type":"Point"}
}