{
  "type": "Feature",
  "properties": {
    "iso:country":"FR",
    "sg:address":"2, Av Andr\u00e9 Amp\u00e8re - ZA la Garrigue II, 34170 Castelnau le Lez",
    "sg:orig_category":"Non-Classified Establishments",
    "sg:phone":"+33 4 67 72 26 52",
    "sg:postcode":"34170",
    "sg:province":"Languedoc-Roussillon",
    "wof:name":"Etablissements Chausson Service S.a.r.l.",
    "wof:placetype":"venue"
},
  "geometry": {"coordinates":[3.89542,43.633732],"type":"Point"}
}