{
  "type": "Feature",
  "properties": {
    "addr:full":"170, Bd Stalingrad, 69006 Lyon Rhone-Alpes",
    "addr:housenumber":"170",
    "addr:postcode":"69006",
    "addr:street":"Bd Stalingrad",
    "iso:country":"FR",
    "sg:address":"170, Bd Stalingrad, 69006 Lyon",
    "sg:orig_category":"Unclassifiable Establishments",
    "sg:phone":"+33 4 72 69 90 90",
    "sg:province":"Rhone-Alpes",
    "wof:name":"Ever S.a.",
    "wof:placetype":"venue"
},
  "geometry": {"coordinates":[4.858268,45.770477],"type":"Point"}
}