{
  "type": "Feature",
  "properties": {
    "addr:full":"All\u00e9e des Cormorans - ZI la Fray\u00e8re Cannes Provence-Alpes-C\u00f4te d'Azur 06150",
    "addr:postcode":"06150",
    "addr:street":"Alle\u0301E Des Cormorans Zi La Fraye\u0300Re Cannes",
    "iso:country":"FR",
    "sg:address":"All\u00e9e des Cormorans - ZI la Fray\u00e8re",
    "sg:city":"Cannes",
    "sg:orig_category":"Non-Classified Establishments",
    "sg:phone":"+33 4 93 90 52 00",
    "sg:postcode":"06150",
    "sg:province":"Provence-Alpes-C\u00f4te d'Azur",
    "wof:name":"Teuchos Paca S.a.r.l.",
    "wof:placetype":"venue"
},
  "geometry": {"coordinates":[6.96872,43.55698],"type":"Point"}
}