{
  "type": "Feature",
  "properties": {
    "addr:full":"22, Rue Gutemberg - ZI de l'Escudilliers, 15000 Aurillac Aurillac Auvergne 15000",
    "addr:housenumber":"22",
    "addr:postcode":"15000;15000",
    "addr:street":"Rue Gutemberg Zi De L'Escudilliers",
    "iso:country":"FR",
    "sg:address":"22, Rue Gutemberg - ZI de l'Escudilliers, 15000 Aurillac",
    "sg:city":"Aurillac",
    "sg:orig_category":"Unclassifiable Establishments",
    "sg:phone":"+33 4 71 46 26 50",
    "sg:postcode":"15000",
    "sg:province":"Auvergne",
    "wof:name":"S.c. Tout\u00e9lectric S.a.",
    "wof:placetype":"venue"
},
  "geometry": {"coordinates":[2.429809,44.915771],"type":"Point"}
}