{
  "type": "Feature",
  "properties": {
    "addr:full":"Rue Pelouze Lomme Nord Pas-de-Calais 59160",
    "addr:postcode":"59160",
    "addr:street":"Rue Pelouze Lomme Nord",
    "iso:country":"FR",
    "sg:address":"Rue Pelouze",
    "sg:city":"Lomme",
    "sg:orig_category":"Unclassifiable Establishments",
    "sg:phone":"+33 3 20 17 03 48",
    "sg:postcode":"59160",
    "sg:province":"Nord Pas-de-Calais",
    "wof:name":"Cl\u00e9ment R.p.c. S.a.",
    "wof:placetype":"venue"
},
  "geometry": {"coordinates":[3.009418,50.627323],"type":"Point"}
}