{
  "type": "Feature",
  "properties": {
    "addr:full":"6, Rue Saint Sauveur, 27170 Beaumont le Roger Haute Normandie",
    "addr:housenumber":"6",
    "addr:postcode":"27170",
    "addr:street":"Rue Saint Sauveur;Roger Haute Normandie",
    "iso:country":"FR",
    "sg:address":"6, Rue Saint Sauveur, 27170 Beaumont le Roger",
    "sg:orig_category":"Unclassifiable Establishments",
    "sg:phone":"+33 2 32 45 27 81",
    "sg:province":"Haute Normandie",
    "wof:name":"I.c.v. S.a. - Imprimerie Des Ch\u00e8ques Et Valeurs",
    "wof:placetype":"venue"
},
  "geometry": {"coordinates":[0.784047,49.072372],"type":"Point"}
}