{
  "type": "Feature",
  "properties": {
    "iso:country":"FR",
    "sg:address":"6, Rue Saint Sauveur, 27170 Beaumont le Roger",
    "sg:orig_category":"Unclassifiable Establishments",
    "sg:phone":"+33 2 32 45 27 81",
    "sg:province":"Haute Normandie",
    "wof:name":"I.c.v. S.a. - Imprimerie Des Ch\u00e8ques Et Valeurs",
    "wof:placetype":"venue"
},
  "geometry": {"coordinates":[0.784047,49.072372],"type":"Point"}
}