{
  "type": "Feature",
  "properties": {
    "addr:full":"19 Avenue Jean Barraud 71170 Chauffailles Chauffailles Bourgogne 71170",
    "addr:housenumber":"19",
    "addr:postcode":"71170;71170",
    "addr:street":"Avenue Jean Barraud",
    "iso:country":"FR",
    "sg:address":"19 Avenue Jean Barraud 71170 Chauffailles",
    "sg:city":"Chauffailles",
    "sg:classifiers":[
        {
            "category":"Professional",
            "subcategory":"Engineering",
            "type":"Services"
        }
    ],
    "sg:phone":"+33 3 85 26 00 26",
    "sg:postcode":"71170",
    "sg:province":"Bourgogne",
    "sg:tags":[
        "machine",
        "-",
        "mechanical"
    ],
    "wof:name":"Lbl Brenta Cd Sarl",
    "wof:placetype":"venue"
},
  "geometry": {"coordinates":[4.34361,46.207451],"type":"Point"}
}