{
  "type": "Feature",
  "properties": {
    "iso:country":"FR",
    "sg:address":"13, Place Littr\u00e9, 50300 Avranches",
    "sg:city":"Avranches",
    "sg:orig_category":"Non-Classified Establishments",
    "sg:phone":"+33 2 33 89 15 00",
    "sg:postcode":"50300",
    "sg:province":"Basse Normandie",
    "wof:name":"Tesson Informatique S.a.",
    "wof:placetype":"venue"
},
  "geometry": {"coordinates":[-1.361815,48.686291],"type":"Point"}
}