{
  "type": "Feature",
  "properties": {
    "addr:full":"Rte de Cala Rossa - Presqu'ile du Benedettu Lecci Corse 20137",
    "addr:postcode":"20137",
    "addr:street":"Rte De Cala Rossa Presqu'Ile Du Benedettu",
    "iso:country":"FR",
    "sg:address":"Rte de Cala Rossa - Presqu'ile du Benedettu",
    "sg:city":"Lecci",
    "sg:orig_category":"Non-Classified Establishments",
    "sg:phone":"+33 4 95 71 62 81",
    "sg:postcode":"20137",
    "sg:province":"Corse",
    "wof:name":"H\u00f4tel U Benedettu",
    "wof:placetype":"venue"
},
  "geometry": {"coordinates":[9.31629,41.677631],"type":"Point"}
}