{
  "type": "Feature",
  "properties": {
    "addr:full":"Traverse Fran\u00e7ois Blanc Vallauris Provence-Alpes-C\u00f4te d'Azur 06220",
    "addr:postcode":"06220",
    "addr:street":"Traverse Franc\u0327Ois Blanc Vallauris",
    "iso:country":"FR",
    "sg:address":"Traverse Fran\u00e7ois Blanc",
    "sg:city":"Vallauris",
    "sg:orig_category":"Non-Classified Establishments",
    "sg:phone":"+33 4 93 64 05 93",
    "sg:postcode":"06220",
    "sg:province":"Provence-Alpes-C\u00f4te d'Azur",
    "wof:name":"E.c. Diffusion S.a.r.l.",
    "wof:placetype":"venue"
},
  "geometry": {"coordinates":[7.055925,43.578835],"type":"Point"}
}