{
  "type": "Feature",
  "properties": {
    "addr:full":"Clos de Jourdan Gimeaux 13200 Arles Provence-Alpes-C\u00f4te d'Azur",
    "addr:postcode":"13200",
    "addr:street":"Clos De Jourdan",
    "iso:country":"FR",
    "sg:address":"Clos de Jourdan Gimeaux 13200 Arles",
    "sg:orig_category":"Non-Classified Establishments",
    "sg:phone":"+33 4 90 93 60 51",
    "sg:province":"Provence-Alpes-C\u00f4te d'Azur",
    "wof:name":"France Riz",
    "wof:placetype":"venue"
},
  "geometry": {"coordinates":[4.589861,43.668671],"type":"Point"}
}