{
  "type": "Feature",
  "properties": {
    "iso:country":"FR",
    "sg:address":"55 Boulevard Richard Lenoir 75011 Paris",
    "sg:classifiers":[
        {
            "category":"Shopping",
            "type":"Retail Goods"
        }
    ],
    "sg:phone":"+33 1 49 29 75 00",
    "sg:postcode":"75011",
    "sg:province":"Ile de France",
    "sg:tags":[
        "metallurgy",
        "finished",
        "-",
        "metalworking",
        "metallic"
    ],
    "wof:name":"Serdaneli",
    "wof:placetype":"venue"
},
  "geometry": {"coordinates":[2.371765,48.859879],"type":"Point"}
}