{
  "type": "Feature",
  "properties": {
    "iso:country":"FR",
    "sg:address":"B.P. 23125, 25047 Besan\u00e7on C\u00e9dex^^ZI - Les Planches du Mont , 25480 Miserey Salines",
    "sg:orig_category":"Non-Classified Establishments",
    "sg:phone":"+33 3 81 50 30 30",
    "sg:province":"Franche Comt\u00e9",
    "wof:name":"F.g. Manutention S.a.r.l. - Fran\u00e7ois Greset Manutention",
    "wof:placetype":"venue"
},
  "geometry": {"coordinates":[5.982078,47.27187],"type":"Point"}
}