{
  "type": "Feature",
  "properties": {
    "addr:full":"1, Grande Rue, 01460 Nurieux Volognat Rhone-Alpes 01460",
    "addr:housenumber":"1",
    "addr:postcode":"01460;01460",
    "addr:street":"Grande Rue;Rhone-Alpes",
    "iso:country":"FR",
    "sg:address":"1, Grande Rue, 01460 Nurieux Volognat",
    "sg:orig_category":"Unclassifiable Establishments",
    "sg:phone":"+33 4 74 76 25 21",
    "sg:postcode":"01460",
    "sg:province":"Rhone-Alpes",
    "wof:name":"Entreprise Debourg Michel",
    "wof:placetype":"venue"
},
  "geometry": {"coordinates":[5.514189,46.172836],"type":"Point"}
}