{
  "type": "Feature",
  "properties": {
    "addr:full":"all\u00e9e de la Grindolli\u00e8re 49500 SEGRE Pays de Loire",
    "addr:postcode":"49500",
    "addr:street":"Alle\u0301E De La Grindollie\u0300Re;Segre",
    "iso:country":"FR",
    "sg:address":"all\u00e9e de la Grindolli\u00e8re 49500 SEGRE",
    "sg:classifiers":[
        {
            "category":"Retail",
            "subcategory":"Animal Services",
            "type":"Services"
        }
    ],
    "sg:phone":"+33 2 41 94 72 30",
    "sg:province":"Pays de Loire",
    "sg:tags":[
        "article",
        "veterinary",
        "drug",
        "care"
    ],
    "wof:name":"Schering-plough Sant\u00e9 Animale Sas",
    "wof:placetype":"venue"
},
  "geometry": {"coordinates":[-0.87246,47.692238],"type":"Point"}
}