{
  "type": "Feature",
  "properties": {
    "iso:country":"FR",
    "sg:address":"14, Rue de Tolbiac, 75013 Paris",
    "sg:orig_category":"Unclassifiable Establishments",
    "sg:phone":"+33 1 45 84 27 54",
    "sg:province":"Ile de France",
    "wof:name":"Hard Informatique S.a.",
    "wof:placetype":"venue"
},
  "geometry": {"coordinates":[2.374867,48.829735],"type":"Point"}
}