{
  "type": "Feature",
  "properties": {
    "addr:full":"6, Rue du Colonel R\u00e9my, 14000 Caen Caen Basse Normandie 14000",
    "addr:housenumber":"6",
    "addr:postcode":"14000;14000",
    "addr:street":"Rue Du Colonel Re\u0301My",
    "iso:country":"FR",
    "sg:address":"6, Rue du Colonel R\u00e9my, 14000 Caen",
    "sg:city":"Caen",
    "sg:orig_category":"Non-Classified Establishments",
    "sg:phone":"+33 2 31 46 52 00",
    "sg:postcode":"14000",
    "sg:province":"Basse Normandie",
    "wof:name":"Robinson S.a.r.l.",
    "wof:placetype":"venue"
},
  "geometry": {"coordinates":[-0.387896,49.202145],"type":"Point"}
}