{
  "type": "Feature",
  "properties": {
    "iso:country":"FR",
    "sg:address":"202, Chemin de l'Arm\u00e9e d'Afrique, 13010 Marseille",
    "sg:orig_category":"Unclassifiable Establishments",
    "sg:phone":"+33 4 91 47 18 47",
    "sg:province":"Provence-Alpes-C\u00f4te d'Azur",
    "wof:name":"Gu\u00e9rin S.a.",
    "wof:placetype":"venue"
},
  "geometry": {"coordinates":[5.441036,43.280792],"type":"Point"}
}