{
  "type": "Feature",
  "properties": {
    "addr:full":"B.P. 5, 41240 Ouzouer le March\u00e9^^34, Rue Louis Chevais, 41240 Ouzouer le March\u00e9 Autainville Centre 41240",
    "addr:housenumber":"5",
    "addr:postcode":"41240;41240;41240",
    "addr:street":"B.P.;Rue Louis Chevais",
    "iso:country":"FR",
    "sg:address":"B.P. 5, 41240 Ouzouer le March\u00e9^^34, Rue Louis Chevais, 41240 Ouzouer le March\u00e9",
    "sg:city":"Autainville",
    "sg:orig_category":"Non-Classified Establishments",
    "sg:phone":"+33 2 54 82 42 10",
    "sg:postcode":"41240",
    "sg:province":"Centre",
    "wof:name":"Christian Boulet Et Compagnie S.a.",
    "wof:placetype":"venue"
},
  "geometry": {"coordinates":[1.508777,47.845856],"type":"Point"}
}