{
  "type": "Feature",
  "properties": {
    "iso:country":"FR",
    "sg:address":"B.P. 28, 35420 Louvign\u00e9 du D\u00e9sert^^ZI de la Gare, 35420 Louvign\u00e9 du D\u00e9sert",
    "sg:city":"La Bazouge-du-D\u00e9sert",
    "sg:orig_category":"Non-Classified Establishments",
    "sg:phone":"+33 2 99 98 54 97",
    "sg:postcode":"35420",
    "sg:province":"Bretagne",
    "wof:name":"Centrale De Voirie E.u.r.l.",
    "wof:placetype":"venue"
},
  "geometry": {"coordinates":[-1.123834,48.48151],"type":"Point"}
}