{
  "type": "Feature",
  "properties": {
    "addr:full":"76570 Sainte Austreberthe Haute Normandie",
    "addr:postcode":"76570",
    "iso:country":"FR",
    "sg:address":"76570 Sainte Austreberthe",
    "sg:orig_category":"Unclassifiable Establishments",
    "sg:phone":"+33 2 32 94 94 94",
    "sg:province":"Haute Normandie",
    "wof:name":"Biard Et Noblesse S.a.",
    "wof:placetype":"venue"
},
  "geometry": {"coordinates":[0.9746,49.598045],"type":"Point"}
}