{
  "type": "Feature",
  "properties": {
    "iso:country":"FR",
    "sg:address":"B.P. 13, 31270 Cugnaux^^102, Rte de Toulouse, 31270 Cugnaux",
    "sg:orig_category":"Non-Classified Establishments",
    "sg:phone":"+33 5 62 13 57 57",
    "sg:province":"Midi Pyr\u00e9n\u00e9es",
    "wof:name":"Ransomes S.a.",
    "wof:placetype":"venue"
},
  "geometry": {"coordinates":[1.34424,43.536976],"type":"Point"}
}