{
  "type": "Feature",
  "properties": {
    "addr:full":"Zi De St M\u00e9dard Des Pr\u00e9s 85201 Fontenay Le Comte Cedex Champagne",
    "addr:postcode":"85201;le;cedex",
    "addr:street":"Zi De St Me\u0301Dard Des Pre\u0301S",
    "iso:country":"FR",
    "sg:address":"Zi De St M\u00e9dard Des Pr\u00e9s 85201 Fontenay Le Comte Cedex",
    "sg:classifiers":[
        {
            "category":"Bakery",
            "type":"Food & Drink"
        }
    ],
    "sg:phone":"+33 2 51 69 27 31",
    "sg:province":"Champagne",
    "sg:tags":[
        "cake",
        "product",
        "related",
        "bread"
    ],
    "wof:name":"Albatros Sa",
    "wof:placetype":"venue"
},
  "geometry": {"coordinates":[-0.802274,46.464867],"type":"Point"}
}