{
  "type": "Feature",
  "properties": {
    "addr:full":"Lieu Dit La Quintane 66440 Torreilles Languedoc-Roussillon 66440",
    "addr:postcode":"66440;66440",
    "addr:street":"Lieu Dit La Quintane",
    "iso:country":"FR",
    "sg:address":"Lieu Dit La Quintane 66440 Torreilles",
    "sg:classifiers":[
        {
            "category":"Farming",
            "subcategory":"Farm",
            "type":"Manufacturing & Wholesale Goods"
        }
    ],
    "sg:phone":"+33 4 68 59 65 88",
    "sg:postcode":"66440",
    "sg:province":"Languedoc-Roussillon",
    "sg:tags":[
        "horticulture",
        "agriculture",
        "livestock"
    ],
    "wof:name":"Floranil",
    "wof:placetype":"venue"
},
  "geometry": {"coordinates":[2.998835,42.759254],"type":"Point"}
}