{
  "type": "Feature",
  "properties": {
    "iso:country":"FR",
    "sg:address":"B.P. 09, 45141 Ingr\u00e9 C\u00e9dex^^5, Rue Henri Dunant - ZI de Ingr\u00e9, 45140 Ingr\u00e9",
    "sg:city":"Ingr\u00e9",
    "sg:orig_category":"Non-Classified Establishments",
    "sg:phone":"+33 2 38 72 90 00",
    "sg:postcode":"45140",
    "sg:province":"Centre",
    "wof:name":"Informatique 45 S.a.r.l.",
    "wof:placetype":"venue"
},
  "geometry": {"coordinates":[1.8745,47.912949],"type":"Point"}
}