{
  "type": "Feature",
  "properties": {
    "addr:full":"rue Pr\u00e9verie; Fegreac Picardie",
    "addr:street":"Rue Pre\u0301Verie Fegreac",
    "iso:country":"FR",
    "sg:address":"rue Pr\u00e9verie; Fegreac",
    "sg:classifiers":[
        {
            "category":"Banks & Credit Unions",
            "subcategory":"Bank",
            "type":"Services"
        }
    ],
    "sg:phone":"+33 3340912037",
    "sg:province":"Picardie",
    "wof:name":"Cr\u00e9dit Mutuel De Fegreac",
    "wof:placetype":"venue"
},
  "geometry": {"coordinates":[-2.044273,47.584988],"type":"Point"}
}