{
  "type": "Feature",
  "properties": {
    "addr:full":"70, Rue du Verbois, 75003 Paris Ile de France",
    "addr:housenumber":"70",
    "addr:postcode":"75003",
    "addr:street":"Rue Du Verbois",
    "iso:country":"FR",
    "sg:address":"70, Rue du Verbois, 75003 Paris",
    "sg:orig_category":"Non-Classified Establishments",
    "sg:phone":"+33 1 42 78 58 51",
    "sg:province":"Ile de France",
    "wof:name":"N\u00e9go Fil E.u.r.l.",
    "wof:placetype":"venue"
},
  "geometry": {"coordinates":[2.355592,48.867687],"type":"Point"}
}