{
  "type": "Feature",
  "properties": {
    "iso:country":"FR",
    "sg:address":"Av De La M\u00e9rindole Zi La Grande Colle",
    "sg:city":"18 13110 Port De Bouc",
    "sg:classifiers":[
        {
            "category":"Shopping",
            "type":"Retail Goods"
        }
    ],
    "sg:phone":"+33 4 42 40 17 65",
    "sg:province":"Haute Normandie",
    "sg:tags":[
        "metallurgy",
        "finished",
        "-",
        "metalworking",
        "metallic"
    ],
    "wof:name":"Les Portails Du Midi Sa",
    "wof:placetype":"venue"
},
  "geometry": {"coordinates":[4.984465,43.405624],"type":"Point"}
}