{
  "type": "Feature",
  "properties": {
    "iso:country":"FR",
    "sg:address":"B.P. 23, 01151 Lagnieu C\u00e9dex^^Rte de Gervais, 01150 Lagnieu",
    "sg:orig_category":"Non-Classified Establishments",
    "sg:phone":"+33 4 74 34 15 49",
    "sg:province":"Rhone-Alpes",
    "wof:name":"Usine Saint Gobain Emballage",
    "wof:placetype":"venue"
},
  "geometry": {"coordinates":[5.3382,45.88237],"type":"Point"}
}