{
  "type": "Feature",
  "properties": {
    "iso:country":"FR",
    "sg:address":"25, Rue Marc Verdier - ZI, 10150 Pont Sainte Marie",
    "sg:orig_category":"Unclassifiable Establishments",
    "sg:phone":"+33 3 25 81 20 88",
    "sg:province":"Champagne",
    "wof:name":"Fidia S.a.",
    "wof:placetype":"venue"
},
  "geometry": {"coordinates":[4.09298,48.317806],"type":"Point"}
}