{
  "type": "Feature",
  "properties": {
    "iso:country":"FR",
    "sg:address":"Rue Henry de Crousaz - Ile Napol\u00e9on",
    "sg:city":"Illzach",
    "sg:orig_category":"Unclassifiable Establishments",
    "sg:phone":"+33 3 89 61 74 47",
    "sg:postcode":"68110",
    "sg:province":"Alsace",
    "wof:name":"Papeteries Du Rhin S.a.",
    "wof:placetype":"venue"
},
  "geometry": {"coordinates":[7.348394,47.782181],"type":"Point"}
}