{
  "type": "Feature",
  "properties": {
    "addr:full":"B.P. 10109, 60201 Compi\u00e8gne C\u00e9dex^^Rue du Fonds Pernant - ZAC de Merci\u00e8res Zone 3, 60200 Compi\u00e8gne Picardie 60200",
    "addr:housenumber":"10109",
    "addr:postcode":"60201;60200;60200",
    "addr:street":"Pernant Zac De Mercie\u0300Res",
    "iso:country":"FR",
    "sg:address":"B.P. 10109, 60201 Compi\u00e8gne C\u00e9dex^^Rue du Fonds Pernant - ZAC de Merci\u00e8res Zone 3, 60200 Compi\u00e8gne",
    "sg:orig_category":"Non-Classified Establishments",
    "sg:phone":"+33 3 44 30 58 00",
    "sg:postcode":"60200",
    "sg:province":"Picardie",
    "wof:name":"A.r.c. S.a.",
    "wof:placetype":"venue"
},
  "geometry": {"coordinates":[2.825,49.417671],"type":"Point"}
}