{
  "type": "Feature",
  "properties": {
    "iso:country":"FR",
    "sg:address":"51 Rue Des 3 Fontanot 92000 Nanterre",
    "sg:classifiers":[
        {
            "category":"Building & Trades",
            "subcategory":"Construction",
            "type":"Services"
        }
    ],
    "sg:phone":"+33 1 46 95 20 00",
    "sg:postcode":"92000",
    "sg:province":"Ile de France",
    "sg:tags":[
        "work",
        "public"
    ],
    "wof:name":"Cegelec",
    "wof:placetype":"venue"
},
  "geometry": {"coordinates":[2.221757,48.895855],"type":"Point"}
}