{
  "type": "Feature",
  "properties": {
    "addr:full":"chem Muriers 69540 Irigny Rhone-Alpes 69540",
    "addr:postcode":"69540;69540",
    "addr:street":"Muriers",
    "iso:country":"FR",
    "sg:address":"chem Muriers 69540 Irigny",
    "sg:classifiers":[
        {
            "category":"Wholesale",
            "subcategory":"Machinery & Supplies",
            "type":"Manufacturing & Wholesale Goods"
        }
    ],
    "sg:phone":"+33 4 72 66 33 22",
    "sg:postcode":"69540",
    "sg:province":"Rhone-Alpes",
    "sg:tags":[
        "equipment",
        "precision"
    ],
    "wof:name":"Sedatelec Acupuncture",
    "wof:placetype":"venue"
},
  "geometry": {"coordinates":[4.821341,45.694866],"type":"Point"}
}