{
  "type": "Feature",
  "properties": {
    "addr:full":"13 Rue Auguste Desgen\u00e9tais 76210 Bolbec Haute Normandie 76210",
    "addr:housenumber":"13",
    "addr:postcode":"76210;76210",
    "addr:street":"Rue Auguste Desgene\u0301Tais;Haute Normandie",
    "iso:country":"FR",
    "sg:address":"13 Rue Auguste Desgen\u00e9tais 76210 Bolbec",
    "sg:classifiers":[
        {
            "category":"Manufacturing",
            "subcategory":"Chemicals & Compounds",
            "type":"Manufacturing & Wholesale Goods"
        }
    ],
    "sg:phone":"+33 2 35 39 33 00",
    "sg:postcode":"76210",
    "sg:province":"Haute Normandie",
    "sg:tags":[
        "pharmaceutical",
        "chemistry",
        "-",
        "by-product",
        "pharmacy"
    ],
    "wof:name":"Oril Industrie",
    "wof:placetype":"venue"
},
  "geometry": {"coordinates":[0.495619,49.577034],"type":"Point"}
}