{
  "type": "Feature",
  "properties": {
    "addr:full":"Za Les Fougerousses 16430 Balzac Poitou-Charentes",
    "addr:postcode":"16430",
    "addr:street":"Za Les Fougerousses",
    "iso:country":"FR",
    "sg:address":"Za Les Fougerousses 16430 Balzac",
    "sg:classifiers":[
        {
            "category":"Utilities",
            "subcategory":"Natural Gas",
            "type":"Services"
        }
    ],
    "sg:phone":"+33 5 45 39 28 00",
    "sg:province":"Poitou-Charentes",
    "sg:tags":[
        "plant"
    ],
    "wof:name":"Defi-meca Sarl",
    "wof:placetype":"venue"
},
  "geometry": {"coordinates":[0.14475,45.714546],"type":"Point"}
}