{
  "type": "Feature",
  "properties": {
    "addr:full":"Ch De Valenciennes Terril De Cuvinot 59264 Onnaing Nord Pas-de-Calais 59264",
    "addr:postcode":"59264;59264",
    "addr:street":"Ch De Valenciennes",
    "iso:country":"FR",
    "sg:address":"Ch De Valenciennes Terril De Cuvinot 59264 Onnaing",
    "sg:classifiers":[
        {
            "category":"Manufacturing",
            "subcategory":"Tools & Machinery",
            "type":"Manufacturing & Wholesale Goods"
        }
    ],
    "sg:phone":"+33 3 27 35 38 78",
    "sg:postcode":"59264",
    "sg:province":"Nord Pas-de-Calais",
    "sg:tags":[
        "equipment",
        "measurement",
        "-",
        "precision",
        "instrument"
    ],
    "wof:name":"Tercharnor",
    "wof:placetype":"venue"
},
  "geometry": {"coordinates":[3.59677,50.38562],"type":"Point"}
}