{
  "type": "Feature",
  "properties": {
    "iso:country":"FR",
    "sg:address":"16 Quai De L Orangerie 16200 JARNAC",
    "sg:classifiers":[
        {
            "category":"Wholesale",
            "subcategory":"Wine & Distilled Alcoholic Beverages",
            "type":"Manufacturing & Wholesale Goods"
        }
    ],
    "sg:phone":"+33 5 45 35 59 59",
    "sg:postcode":"16200",
    "sg:province":"Poitou-Charentes",
    "sg:tags":[
        "french"
    ],
    "wof:name":"Thomas Hine And Co Sa",
    "wof:placetype":"venue"
},
  "geometry": {"coordinates":[-0.175404,45.67865],"type":"Point"}
}