{
  "type": "Feature",
  "properties": {
    "addr:full":"Chasse Alouette 42123 St Cyr De Favieres Rhone-Alpes 42123",
    "addr:postcode":"42123;42123",
    "addr:street":"Rhone-Alpes",
    "iso:country":"FR",
    "sg:address":"Chasse Alouette 42123 St Cyr De Favieres",
    "sg:classifiers":[
        {
            "category":"Professional",
            "subcategory":"Engineering",
            "type":"Services"
        }
    ],
    "sg:phone":"+33 4 77 72 09 13",
    "sg:postcode":"42123",
    "sg:province":"Rhone-Alpes",
    "sg:tags":[
        "machine",
        "-",
        "mechanical"
    ],
    "wof:name":"L'orangerie",
    "wof:placetype":"venue"
},
  "geometry": {"coordinates":[4.072973,45.973549],"type":"Point"}
}