{
  "type": "Feature",
  "properties": {
    "addr:full":"B.P. 14 Cherves Richemont C\u00e9dex^^les Vignolles 16370 Mesnac Poitou-Charentes 16370",
    "addr:postcode":"16370;16370",
    "addr:street":"B.P. 14 Cherves Richemont Ce\u0301Dex^^Les",
    "iso:country":"FR",
    "sg:address":"B.P. 14",
    "sg:city":"Cherves Richemont C\u00e9dex^^les Vignolles 16370 Mesnac",
    "sg:orig_category":"Non-Classified Establishments",
    "sg:phone":"+33 5 45 83 25 25",
    "sg:postcode":"16370",
    "sg:province":"Poitou-Charentes",
    "wof:name":"Sern S.a.r.l.",
    "wof:placetype":"venue"
},
  "geometry": {"coordinates":[-0.364414,45.72197],"type":"Point"}
}