{
  "type": "Feature",
  "properties": {
    "addr:full":"11 rue de Lorraine 88360 RUPT SUR MOSELLE Lorraine 88360",
    "addr:housenumber":"11",
    "addr:postcode":"88360;88360",
    "addr:street":"Rue De Lorraine",
    "iso:country":"FR",
    "sg:address":"11 rue de Lorraine 88360 RUPT SUR MOSELLE",
    "sg:classifiers":[
        {
            "category":"Manufacturing",
            "subcategory":"Tools & Machinery",
            "type":"Manufacturing & Wholesale Goods"
        }
    ],
    "sg:phone":"+33 3 29 26 70 20",
    "sg:postcode":"88360",
    "sg:province":"Lorraine",
    "sg:tags":[
        "industrial",
        "handheld"
    ],
    "wof:name":"Ste De Fabrication Bostitch - Simax S.a.",
    "wof:placetype":"venue"
},
  "geometry": {"coordinates":[6.65603,47.929379],"type":"Point"}
}