{
  "type": "Feature",
  "properties": {
    "addr:full":"23 Route Nationale 72330 Cerans Foulletourte Pays de Loire 72330",
    "addr:housenumber":"23",
    "addr:postcode":"72330;72330",
    "addr:street":"Route Nationale;Foulletourte",
    "iso:country":"FR",
    "sg:address":"23 Route Nationale 72330 Cerans Foulletourte",
    "sg:classifiers":[
        {
            "category":"Farming",
            "subcategory":"Livestock Farm",
            "type":"Manufacturing & Wholesale Goods"
        }
    ],
    "sg:phone":"+33 2 43 87 80 19",
    "sg:postcode":"72330",
    "sg:province":"Pays de Loire",
    "sg:tags":[
        "agriculture"
    ],
    "wof:name":"Sapiniere Sa",
    "wof:placetype":"venue"
},
  "geometry": {"coordinates":[0.073415,47.824665],"type":"Point"}
}