{
  "type": "Feature",
  "properties": {
    "addr:full":"B.P. 7091, 69348 Lyon C\u00e9dex 7^^76, Av. Tony Garnier, 69007 Lyon Rhone-Alpes 69007",
    "addr:housenumber":"7 ^ ^ 76",
    "addr:postcode":"69348;69007;69007",
    "addr:street":"B.P. 7091;Ce\u0301Dex;Av. Tony Garnier",
    "iso:country":"FR",
    "sg:address":"B.P. 7091, 69348 Lyon C\u00e9dex 7^^76, Av. Tony Garnier, 69007 Lyon",
    "sg:orig_category":"Non-Classified Establishments",
    "sg:phone":"+33 4 78 72 62 62",
    "sg:postcode":"69007",
    "sg:province":"Rhone-Alpes",
    "wof:name":"France Boissons Solybo S.n.c.",
    "wof:placetype":"venue"
},
  "geometry": {"coordinates":[4.842415,45.746235],"type":"Point"}
}