{
  "type": "Feature",
  "properties": {
    "addr:full":"Quai Georges Raverat Le Havre Haute Normandie 76600",
    "addr:postcode":"76600",
    "addr:street":"Quai Georges Raverat",
    "iso:country":"FR",
    "sg:address":"Quai Georges Raverat",
    "sg:city":"Le Havre",
    "sg:orig_category":"Unclassifiable Establishments",
    "sg:phone":"+33 2 35 25 50 00",
    "sg:postcode":"76600",
    "sg:province":"Haute Normandie",
    "wof:name":"C.m.s. S.a. - Chaudronnerie Et M\u00e9cano-soudure",
    "wof:placetype":"venue"
},
  "geometry": {"coordinates":[0.15433,49.486431],"type":"Point"}
}