{
  "type": "Feature",
  "properties": {
    "iso:country":"FR",
    "sg:address":"12, Quai Jobez - Immeuble Rive Gauche, 39400 Morez",
    "sg:orig_category":"Non-Classified Establishments",
    "sg:phone":"+33 3 84 33 29 46",
    "sg:postcode":"39400",
    "sg:province":"Franche Comt\u00e9",
    "wof:name":"C.c.i. Du Jura",
    "wof:placetype":"venue"
},
  "geometry": {"coordinates":[6.021419,46.52142],"type":"Point"}
}