{
  "type": "Feature",
  "properties": {
    "addr:full":"43 Rte De Mantes 78240 Chambourcy Ile de France 78240",
    "addr:housenumber":"43",
    "addr:postcode":"78240;ile;78240",
    "addr:street":"Rte De Mantes;France",
    "iso:country":"FR",
    "sg:address":"43 Rte De Mantes 78240 Chambourcy",
    "sg:classifiers":[
        {
            "category":"Manufacturing",
            "subcategory":"Glass & Minerals",
            "type":"Manufacturing & Wholesale Goods"
        }
    ],
    "sg:phone":"+33 1 39 22 58 58",
    "sg:postcode":"78240",
    "sg:province":"Ile de France",
    "sg:tags":[
        "building",
        "material"
    ],
    "wof:name":"Demazel Sa",
    "wof:placetype":"venue"
},
  "geometry": {"coordinates":[2.04602,48.907063],"type":"Point"}
}