{
  "type": "Feature",
  "properties": {
    "iso:country":"FR",
    "sg:address":"13, Rue Lazare Carnot, 61000 Alen\u00e7on",
    "sg:city":"Alen\u00e7on",
    "sg:orig_category":"Unclassifiable Establishments",
    "sg:phone":"+33 2 33 29 46 74",
    "sg:postcode":"61000",
    "sg:province":"Basse Normandie",
    "wof:name":"Agence S.t.a.o. - Soci\u00e9t\u00e9 De Transports Automobiles De L'ouest",
    "wof:placetype":"venue"
},
  "geometry": {"coordinates":[0.095189,48.445633],"type":"Point"}
}