{
  "type": "Feature",
  "properties": {
    "iso:country":"FR",
    "sg:address":"ZI du Pr\u00e9 \u00e0 Varois",
    "sg:city":"Custines",
    "sg:orig_category":"Unclassifiable Establishments",
    "sg:phone":"+33 3 83 49 49 00",
    "sg:postcode":"54670",
    "sg:province":"Lorraine",
    "wof:name":"Allevard Autosuspensions S.a.",
    "wof:placetype":"venue"
},
  "geometry": {"coordinates":[6.142335,48.791302],"type":"Point"}
}