{
  "type": "Feature",
  "properties": {
    "iso:country":"FR",
    "sg:address":"B.P. 51, 08502 Revin C\u00e9dex^^5, Rue Jean Jacques Rousseau, 08500 Revin",
    "sg:city":"Les Mazures",
    "sg:orig_category":"Non-Classified Establishments",
    "sg:phone":"+33 3 24 42 80 00",
    "sg:postcode":"08500",
    "sg:province":"Champagne",
    "wof:name":"Electrolux Home Products France S.a.s.",
    "wof:placetype":"venue"
},
  "geometry": {"coordinates":[4.64354,49.926094],"type":"Point"}
}