{
  "type": "Feature",
  "properties": {
    "addr:full":"Bertheuil 40090 Saint Perdon Artassenx Aquitaine 40090",
    "addr:postcode":"40090;perdon;40090",
    "addr:street":"Bertheuil",
    "iso:country":"FR",
    "sg:address":"Bertheuil 40090 Saint Perdon",
    "sg:city":"Artassenx",
    "sg:orig_category":"Unclassifiable Establishments",
    "sg:phone":"+33 5 58 06 36 36",
    "sg:postcode":"40090",
    "sg:province":"Aquitaine",
    "wof:name":"L.s.a. S.a. - Les Scieries D' Aquitaine",
    "wof:placetype":"venue"
},
  "geometry": {"coordinates":[-0.604879,43.872478],"type":"Point"}
}