{
  "type": "Feature",
  "properties": {
    "addr:full":"Pointe De Toulvern 56870 Baden Baden Bretagne 56870",
    "addr:postcode":"56870;56870",
    "addr:street":"Baden Bretagne",
    "iso:country":"FR",
    "sg:address":"Pointe De Toulvern 56870 Baden",
    "sg:city":"Baden",
    "sg:classifiers":[
        {
            "category":"Farming",
            "subcategory":"Livestock Farm",
            "type":"Manufacturing & Wholesale Goods"
        }
    ],
    "sg:phone":"+33 2 97 57 00 19",
    "sg:postcode":"56870",
    "sg:province":"Bretagne",
    "sg:tags":[
        "breeding",
        "agriculture",
        "animal"
    ],
    "wof:name":"Anse De Toulvern Snc",
    "wof:placetype":"venue"
},
  "geometry": {"coordinates":[-2.945114,47.603947],"type":"Point"}
}