{
  "type": "Feature",
  "properties": {
    "addr:full":"B.P. 139, 13267 Marseille C\u00e9dex 08^^78, Av. de Hambourg, 13000 Marseille Poitou-Charentes",
    "addr:housenumber":"b.p. 139;08 ^ ^ 78",
    "addr:postcode":"13267;13000",
    "addr:street":"Ce\u0301Dex;Av. De Hambourg",
    "iso:country":"FR",
    "sg:address":"B.P. 139, 13267 Marseille C\u00e9dex 08^^78, Av. de Hambourg, 13000 Marseille",
    "sg:orig_category":"Non-Classified Establishments",
    "sg:phone":"+33 4 91 16 51 91",
    "sg:province":"Poitou-Charentes",
    "wof:name":"Cesia S.a. - Conseil En Organisation Et Syst\u00e8mes D'information",
    "wof:placetype":"venue"
},
  "geometry": {"coordinates":[5.37249,43.293686],"type":"Point"}
}