{
  "type": "Feature",
  "properties": {
    "iso:country":"FR",
    "sg:address":"176, Av. Gambetta, 19110 Bort les Orgues",
    "sg:orig_category":"Non-Classified Establishments",
    "sg:phone":"+33 5 55 96 00 21",
    "sg:province":"Limousin",
    "wof:name":"Etablissements Vialleix S.a.",
    "wof:placetype":"venue"
},
  "geometry": {"coordinates":[2.493884,45.389553],"type":"Point"}
}