{
  "type": "Feature",
  "properties": {
    "addr:full":"Zac De Castelculier 47240 CASTELCULIER Castelculier Aquitaine 47240",
    "addr:postcode":"47240;47240",
    "addr:street":"Zac De Castelculier",
    "iso:country":"FR",
    "sg:address":"Zac De Castelculier 47240 CASTELCULIER",
    "sg:city":"Castelculier",
    "sg:orig_category":"Additives For Plant Protection Products",
    "sg:phone":"+33 5 53 68 57 00",
    "sg:postcode":"47240",
    "sg:province":"Aquitaine",
    "wof:name":"Etablissements Prely Sa",
    "wof:placetype":"venue"
},
  "geometry": {"coordinates":[0.69087,44.17498],"type":"Point"}
}