{
  "type": "Feature",
  "properties": {
    "addr:full":"Rte de Romilly - ZI Saint S\u00e9verin Cloyes sur le Loir Centre 28220",
    "addr:postcode":"28220",
    "addr:street":"Rte De Romilly Zi Saint Se\u0301Verin Cloyes Sur Le Loir",
    "iso:country":"FR",
    "sg:address":"Rte de Romilly - ZI Saint S\u00e9verin",
    "sg:city":"Cloyes sur le Loir",
    "sg:orig_category":"Unclassifiable Establishments",
    "sg:phone":"+33 2 37 98 61 50",
    "sg:postcode":"28220",
    "sg:province":"Centre",
    "wof:name":"Nitram S.a.",
    "wof:placetype":"venue"
},
  "geometry": {"coordinates":[1.32596,47.972462],"type":"Point"}
}