{
  "type": "Feature",
  "properties": {
    "addr:full":"Tournel 42600 Champdieu Rhone-Alpes 42600",
    "addr:postcode":"42600;42600",
    "addr:street":"Tournel;Rhone-Alpes",
    "iso:country":"FR",
    "sg:address":"Tournel 42600 Champdieu",
    "sg:classifiers":[
        {
            "category":"Professional",
            "subcategory":"Engineering",
            "type":"Services"
        }
    ],
    "sg:phone":"+33 4 77 58 42 11",
    "sg:postcode":"42600",
    "sg:province":"Rhone-Alpes",
    "sg:tags":[
        "machine",
        "-",
        "mechanical"
    ],
    "wof:name":"Ateliers Mecanique De La Madeleine Sa",
    "wof:placetype":"venue"
},
  "geometry": {"coordinates":[4.056175,45.633751],"type":"Point"}
}