{
  "type": "Feature",
  "properties": {
    "addr:full":"21, Rue de la Pourvoierie, 78000 Versailles Ile de France",
    "addr:housenumber":"21",
    "addr:postcode":"78000",
    "addr:street":"Rue De La Pourvoierie",
    "iso:country":"FR",
    "sg:address":"21, Rue de la Pourvoierie, 78000 Versailles",
    "sg:orig_category":"Unclassifiable Establishments",
    "sg:phone":"+33 1 39 50 29 00",
    "sg:province":"Ile de France",
    "wof:name":"G.i.c. S.a.r.l. - Guibert International Consultants",
    "wof:placetype":"venue"
},
  "geometry": {"coordinates":[2.132989,48.807041],"type":"Point"}
}