{
  "type": "Feature",
  "properties": {
    "iso:country":"FR",
    "sg:address":"B.P. 12, 08320 Vireux Molhain^^ZI les Forges, 08320 Vireux Molhain",
    "sg:city":"Aubrives",
    "sg:orig_category":"Non-Classified Establishments",
    "sg:phone":"+33 3 24 41 80 00",
    "sg:postcode":"08320",
    "sg:province":"Champagne",
    "wof:name":"F.t.v. S.a. - Forges Et Tr\u00e9filerie De Vireux",
    "wof:placetype":"venue"
},
  "geometry": {"coordinates":[4.73821,50.105011],"type":"Point"}
}