{
  "type": "Feature",
  "properties": {
    "iso:country":"FR",
    "sg:address":"Le Bierson 86370 Mar\u00e7ay",
    "sg:orig_category":"Non-Classified Establishments",
    "sg:phone":"+33 5 49 60 82 00",
    "sg:postcode":"86370",
    "sg:province":"Poitou-Charentes",
    "wof:name":"A.d.f. Chimie S.a.",
    "wof:placetype":"venue"
},
  "geometry": {"coordinates":[0.314755,46.41745],"type":"Point"}
}