{
  "type": "Feature",
  "properties": {
    "addr:full":"602, rue de Chauny, 60400 Noyon Picardie",
    "addr:housenumber":"602",
    "addr:postcode":"60400",
    "addr:street":"Rue De Chauny",
    "iso:country":"FR",
    "sg:address":"602, rue de Chauny, 60400 Noyon",
    "sg:orig_category":"Non-Classified Establishments",
    "sg:phone":"+33 3 44 09 07 70",
    "sg:province":"Picardie",
    "wof:name":"S.n.a.a.m. S.a. - Soci\u00e9t\u00e9 Nouvelle Des Armatures Assembl\u00e9es Mure",
    "wof:placetype":"venue"
},
  "geometry": {"coordinates":[3.018545,49.578739],"type":"Point"}
}