{
  "type": "Feature",
  "properties": {
    "iso:country":"FR",
    "sg:address":"Zi La Borie 24110 St Astier",
    "sg:city":"Saint-Aquilin",
    "sg:classifiers":[
        {
            "category":"Shopping",
            "subcategory":"Luggage & Leather Goods",
            "type":"Retail Goods"
        }
    ],
    "sg:phone":"+33 5 53 07 06 91",
    "sg:postcode":"24110",
    "sg:province":"Aquitaine",
    "sg:tags":[
        "shoe"
    ],
    "wof:name":"Aster Chaussures Sas",
    "wof:placetype":"venue"
},
  "geometry": {"coordinates":[0.53028,45.146221],"type":"Point"}
}