{
  "type": "Feature",
  "properties": {
    "iso:country":"FR",
    "sg:address":"224, Chemin de la Plaine, 06250 Mougins",
    "sg:city":"Plaine",
    "sg:orig_category":"Unclassifiable Establishments",
    "sg:phone":"+33 4 93 75 56 33",
    "sg:postcode":"67420",
    "sg:province":"Alsace",
    "wof:name":"Delta Industries S.a.r.l.",
    "wof:placetype":"venue"
},
  "geometry": {"coordinates":[6.975683,43.610378],"type":"Point"}
}