{
  "type": "Feature",
  "properties": {
    "addr:full":"ZI du Cheix La Souterraine Limousin 23300",
    "addr:postcode":"23300",
    "addr:street":"Zi Du Cheix",
    "iso:country":"FR",
    "sg:address":"ZI du Cheix",
    "sg:city":"La Souterraine",
    "sg:orig_category":"Non-Classified Establishments",
    "sg:phone":"+33 5 55 63 07 17",
    "sg:postcode":"23300",
    "sg:province":"Limousin",
    "wof:name":"S.o.m.a.c. S.a. - Soci\u00e9t\u00e9 M\u00e9canique Et D' Assemblage Du Cheix",
    "wof:placetype":"venue"
},
  "geometry": {"coordinates":[1.486875,46.236874],"type":"Point"}
}