{
  "type": "Feature",
  "properties": {
    "iso:country":"FR",
    "sg:address":"B.P. 57, 38352 La Tour du Pin C\u00e9dex^^Rte d'Italie, 38110 La Tour du Pin",
    "sg:orig_category":"Non-Classified Establishments",
    "sg:phone":"+33 4 74 97 24 88",
    "sg:province":"Rhone-Alpes",
    "wof:name":"S.t.u.m.e.c. S.a. - Soci\u00e9t\u00e9 Turpinoise De M\u00e9canique",
    "wof:placetype":"venue"
},
  "geometry": {"coordinates":[5.465375,45.5509],"type":"Point"}
}