{
  "type": "Feature",
  "properties": {
    "iso:country":"FR",
    "sg:address":"Rue De Lansade 33420 Rauzan",
    "sg:city":"Rauzan",
    "sg:classifiers":[
        {
            "category":"Utilities",
            "type":"Services"
        }
    ],
    "sg:phone":"+33 5 57 84 14 43",
    "sg:postcode":"33420",
    "sg:province":"Aquitaine",
    "sg:tags":[
        "raw",
        "energy",
        "material"
    ],
    "wof:name":"Societe De Gerance De Distribution D'eau Sogedo (sogedo)",
    "wof:placetype":"venue"
},
  "geometry": {"coordinates":[-0.127312,44.774952],"type":"Point"}
}