{
  "type": "Feature",
  "properties": {
    "addr:full":"27, Rue Boucher de Perthes, 62200 Boulogne sur Mer Nord Pas-de-Calais",
    "addr:housenumber":"27",
    "addr:postcode":"62200",
    "addr:street":"Rue Boucher De Perthes;Sur Mer Nord",
    "iso:country":"FR",
    "sg:address":"27, Rue Boucher de Perthes, 62200 Boulogne sur Mer",
    "sg:orig_category":"Unclassifiable Establishments",
    "sg:phone":"+33 6 07 49 84 13",
    "sg:province":"Nord Pas-de-Calais",
    "wof:name":"A.p.r.i.l. - Agence Priv\u00e9e De Recherches Et D'investigations Du Littoral",
    "wof:placetype":"venue"
},
  "geometry": {"coordinates":[1.61753,50.722092],"type":"Point"}
}