{
  "type": "Feature",
  "properties": {
    "addr:full":"87 Rue Des Fr\u00e8res Amieux 44100 Nantes Pays de Loire 44100",
    "addr:housenumber":"87",
    "addr:postcode":"44100;44100",
    "addr:street":"Rue Des Fre\u0300Res Amieux",
    "iso:country":"FR",
    "sg:address":"87 Rue Des Fr\u00e8res Amieux 44100 Nantes",
    "sg:classifiers":[
        {
            "category":"Manufacturing",
            "subcategory":"Chemicals & Compounds",
            "type":"Manufacturing & Wholesale Goods"
        }
    ],
    "sg:phone":"+33 2 51 80 12 00",
    "sg:postcode":"44100",
    "sg:province":"Pays de Loire",
    "sg:tags":[
        "pharmaceutical",
        "chemistry",
        "-",
        "by-product"
    ],
    "wof:name":"Societe Des Etablissements Broyages Et Enduits Modernes Reunies Sa",
    "wof:placetype":"venue"
},
  "geometry": {"coordinates":[-1.612499,47.198769],"type":"Point"}
}