{
  "type": "Feature",
  "properties": {
    "addr:full":"Centre Euronat; Grayan et l'H\u00f4pital Champagne",
    "iso:country":"FR",
    "sg:address":"Centre Euronat; Grayan et l'H\u00f4pital",
    "sg:classifiers":[
        {
            "category":"Banks & Credit Unions",
            "subcategory":"Bank",
            "type":"Services"
        }
    ],
    "sg:phone":"+33 3356093995",
    "sg:province":"Champagne",
    "wof:name":"Cr\u00e9dit Agricole",
    "wof:placetype":"venue"
},
  "geometry": {"coordinates":[-1.066956,45.411655],"type":"Point"}
}