{
  "type": "Feature",
  "properties": {
    "iso:country":"FR",
    "sg:address":"1 Square De La Rochette 42700 Firminy",
    "sg:classifiers":[
        {
            "category":"Personal",
            "subcategory":"Shoe Repair & Shine",
            "type":"Services"
        }
    ],
    "sg:phone":"+33 4 77 89 17 78",
    "sg:postcode":"42700",
    "sg:province":"Rhone-Alpes",
    "sg:tags":[
        "leather",
        "raw",
        "material",
        "good",
        "-"
    ],
    "wof:name":"Ad Maroquiniers",
    "wof:placetype":"venue"
},
  "geometry": {"coordinates":[4.29454,45.389503],"type":"Point"}
}