{
  "type": "Feature",
  "properties": {
    "iso:country":"FR",
    "sg:address":"5, Rue Henri Jadart, 51100 Reims",
    "sg:orig_category":"Unclassifiable Establishments",
    "sg:phone":"+33 3 26 86 76 10",
    "sg:province":"Champagne",
    "wof:name":"Cr\u00e9dit Municipal De Reims S.a.",
    "wof:placetype":"venue"
},
  "geometry": {"coordinates":[4.030297,49.253189],"type":"Point"}
}