{
  "type": "Feature",
  "properties": {
    "iso:country":"FR",
    "sg:address":"2 Rue Ettore Bugatti 67200 Eckbolsheim",
    "sg:city":"Strasbourg",
    "sg:classifiers":[
        {
            "category":"Banks & Credit Unions",
            "subcategory":"Investment Brokerage",
            "type":"Services"
        }
    ],
    "sg:phone":"+33 3 88 76 52 19",
    "sg:postcode":"67200",
    "sg:province":"Alsace",
    "sg:tags":[
        "finance",
        "institution",
        "banking",
        "road",
        "insurance",
        "transport"
    ],
    "wof:name":"Fiduciaire Sa",
    "wof:placetype":"venue"
},
  "geometry": {"coordinates":[7.685993,48.589901],"type":"Point"}
}