{
  "type": "Feature",
  "properties": {
    "iso:country":"FR",
    "sg:address":"Rue Lavoisier",
    "sg:city":"Le Pont de Claix",
    "sg:orig_category":"Unclassifiable Establishments",
    "sg:phone":"+33 4 76 40 90 40",
    "sg:postcode":"38800",
    "sg:province":"Rhone-Alpes",
    "wof:name":"C.e.r.g. S.a. - Centre D'etudes Et De Recherches De Grenoble",
    "wof:placetype":"venue"
},
  "geometry": {"coordinates":[5.70272,45.133533],"type":"Point"}
}