{
  "type": "Feature",
  "properties": {
    "iso:country":"FR",
    "sg:address":"117, Traverse Bovis, 13016 Marseille",
    "sg:orig_category":"Unclassifiable Establishments",
    "sg:phone":"+33 4 91 46 18 19",
    "sg:province":"Poitou-Charentes",
    "wof:name":"Formex Pro S.a.r.l.",
    "wof:placetype":"venue"
},
  "geometry": {"coordinates":[5.3217,43.364235],"type":"Point"}
}