{
  "type": "Feature",
  "properties": {
    "addr:full":"166 quai du Port; Marseille; 13002 Poitou-Charentes",
    "addr:housenumber":"166",
    "addr:postcode":"13002",
    "addr:street":"Quai Du Port",
    "iso:country":"FR",
    "sg:address":"166 quai du Port; Marseille; 13002",
    "sg:classifiers":[
        {
            "category":"Banks & Credit Unions",
            "subcategory":"Bank",
            "type":"Services"
        }
    ],
    "sg:phone":"+33 4 91 90 13 72",
    "sg:province":"Poitou-Charentes",
    "wof:name":"Caisse Regionale De Cr\u00e9dit, Maritime Mutuel Du Finist\u00e8re",
    "wof:placetype":"venue"
},
  "geometry": {"coordinates":[5.364691,43.295475],"type":"Point"}
}