{
  "type": "Feature",
  "properties": {
    "addr:full":"52/58, Rue Perroncel, 69100 Villeurbanne Rhone-Alpes",
    "addr:housenumber":"52 / 58",
    "addr:postcode":"69100",
    "addr:street":"Rue Perroncel",
    "iso:country":"FR",
    "sg:address":"52/58, Rue Perroncel, 69100 Villeurbanne",
    "sg:orig_category":"Non-Classified Establishments",
    "sg:phone":"+33 4 78 93 93 24",
    "sg:province":"Rhone-Alpes",
    "wof:name":"G. Coutier S.a.",
    "wof:placetype":"venue"
},
  "geometry": {"coordinates":[4.875854,45.77496],"type":"Point"}
}