{
  "type": "Feature",
  "properties": {
    "addr:full":"La Grivol\u00e9e 38410 Saint Martin d'Uriage Rhone-Alpes 38410",
    "addr:postcode":"38410;38410",
    "iso:country":"FR",
    "sg:address":"La Grivol\u00e9e 38410 Saint Martin d'Uriage",
    "sg:orig_category":"Non-Classified Establishments",
    "sg:phone":"+33 4 76 89 73 09",
    "sg:postcode":"38410",
    "sg:province":"Rhone-Alpes",
    "wof:name":"Roche Clovis & Fils S.a.r.l.",
    "wof:placetype":"venue"
},
  "geometry": {"coordinates":[5.857688,45.147141],"type":"Point"}
}