{
  "type": "Feature",
  "properties": {
    "addr:full":"25 Rue Porte D'Autun 71400 St Forgeot Autun Bourgogne 71400",
    "addr:housenumber":"25",
    "addr:postcode":"71400;71400",
    "addr:street":"Rue Porte D'Autun",
    "iso:country":"FR",
    "sg:address":"25 Rue Porte D'Autun 71400 St Forgeot",
    "sg:city":"Autun",
    "sg:classifiers":[
        {
            "category":"Shopping",
            "subcategory":"Clothing, Apparel, & Fashions",
            "type":"Retail Goods"
        }
    ],
    "sg:phone":"+33 3 85 86 57 31",
    "sg:postcode":"71400",
    "sg:province":"Bourgogne",
    "sg:tags":[
        "textile",
        "clothing",
        "clothes"
    ],
    "wof:name":"Bacou Sa",
    "wof:placetype":"venue"
},
  "geometry": {"coordinates":[4.30019,47.00367],"type":"Point"}
}