{
  "type": "Feature",
  "properties": {
    "iso:country":"FR",
    "sg:address":"13, Rue Gabriel P\u00e9ri, 93200 Saint Denis",
    "sg:orig_category":"Unclassifiable Establishments",
    "sg:phone":"+33 1 48 09 45 92",
    "sg:province":"Ile de France",
    "wof:name":"Adia S.a.",
    "wof:placetype":"venue"
},
  "geometry": {"coordinates":[2.355845,48.931679],"type":"Point"}
}