{
  "type": "Feature",
  "properties": {
    "iso:country":"FR",
    "sg:address":"Les Montiers 61800 Tinchebray",
    "sg:city":"Tinchebray",
    "sg:orig_category":"Unclassifiable Establishments",
    "sg:phone":"+33 2 33 66 64 82",
    "sg:postcode":"61800",
    "sg:province":"Basse Normandie",
    "wof:name":"Feillet Jean Jacques",
    "wof:placetype":"venue"
},
  "geometry": {"coordinates":[-0.734217,48.758949],"type":"Point"}
}