{
  "type": "Feature",
  "properties": {
    "addr:full":"35200 Rennes Rennes Bretagne 35200",
    "addr:postcode":"35200;35200",
    "iso:country":"FR",
    "sg:address":"35200 Rennes",
    "sg:city":"Rennes",
    "sg:orig_category":"Unclassifiable Establishments",
    "sg:phone":"+33 2 99 53 88 88",
    "sg:postcode":"35200",
    "sg:province":"Bretagne",
    "wof:name":"F.i.t. S.a. - France International Trade",
    "wof:placetype":"venue"
},
  "geometry": {"coordinates":[-1.66606,48.089329],"type":"Point"}
}