{
  "type": "Feature",
  "properties": {
    "iso:country":"FR",
    "sg:address":"10, Rue des Horts, 85200 Fontenay le Comte",
    "sg:orig_category":"Unclassifiable Establishments",
    "sg:phone":"+33 2 51 69 16 71",
    "sg:province":"Pays de Loire",
    "wof:name":"Imprimerie B. Giraudeau S.a.",
    "wof:placetype":"venue"
},
  "geometry": {"coordinates":[-0.801231,46.467125],"type":"Point"}
}