{
  "type": "Feature",
  "properties": {
    "addr:full":"10, Rue des Horts, 85200 Fontenay le Comte Pays de Loire",
    "addr:housenumber":"10",
    "addr:postcode":"85200",
    "addr:street":"Rue Des Horts;Le Comte Pays",
    "iso:country":"FR",
    "sg:address":"10, Rue des Horts, 85200 Fontenay le Comte",
    "sg:orig_category":"Unclassifiable Establishments",
    "sg:phone":"+33 2 51 69 16 71",
    "sg:province":"Pays de Loire",
    "wof:name":"Imprimerie B. Giraudeau S.a.",
    "wof:placetype":"venue"
},
  "geometry": {"coordinates":[-0.801231,46.467125],"type":"Point"}
}