{
  "type": "Feature",
  "properties": {
    "iso:country":"FR",
    "sg:address":"64 rue de l'Industrie 45550 St Denis de l'Hotel",
    "sg:classifiers":[
        {
            "category":"Retail",
            "subcategory":"Auto Repair",
            "type":"Services"
        }
    ],
    "sg:phone":"+33 2 38 46 83 10",
    "sg:province":"Centre",
    "sg:tags":[
        "railway",
        "carriage"
    ],
    "wof:name":"Sdh Ferroviaire S.a.",
    "wof:placetype":"venue"
},
  "geometry": {"coordinates":[2.12803,47.874748],"type":"Point"}
}