{
  "type": "Feature",
  "properties": {
    "addr:full":"6, Av. de la Lib\u00e9ration, 33127 Martignas sur Jalle Martignas-sur-Jalle Aquitaine 33127",
    "addr:postcode":"33127;33127",
    "addr:street":"Av. De La Libe\u0301Ration",
    "iso:country":"FR",
    "sg:address":"6, Av. de la Lib\u00e9ration, 33127 Martignas sur Jalle",
    "sg:city":"Martignas-sur-Jalle",
    "sg:orig_category":"Unclassifiable Establishments",
    "sg:phone":"+33 5 56 78 67 47",
    "sg:postcode":"33127",
    "sg:province":"Aquitaine",
    "wof:name":"M\u00e9dical Thiry",
    "wof:placetype":"venue"
},
  "geometry": {"coordinates":[-0.775967,44.840233],"type":"Point"}
}