{
  "type": "Feature",
  "properties": {
    "iso:country":"FR",
    "sg:address":"10 bis, Av. Percier, 75008 Paris",
    "sg:orig_category":"Unclassifiable Establishments",
    "sg:phone":"+33 1 44 95 80 80",
    "sg:province":"Ile de France",
    "wof:name":"E.i.m.c.o. S.a.",
    "wof:placetype":"venue"
},
  "geometry": {"coordinates":[2.314573,48.874676],"type":"Point"}
}