{
  "type": "Feature",
  "properties": {
    "iso:country":"FR",
    "sg:address":"104, Av. des Champs Elys\u00e9es, 75379 Paris C\u00e9dex 8",
    "sg:orig_category":"Non-Classified Establishments",
    "sg:phone":"+33 1 45 61 69 69",
    "sg:province":"Auvergne",
    "wof:name":"Alain Afflelou S.a.",
    "wof:placetype":"venue"
},
  "geometry": {"coordinates":[2.301455,48.871864],"type":"Point"}
}