{
  "type": "Feature",
  "properties": {
    "addr:full":"181, Rue de Cocq, 45160 Olivet Ardon Centre 45160",
    "addr:housenumber":"181",
    "addr:postcode":"45160;45160",
    "addr:street":"Rue De Cocq",
    "iso:country":"FR",
    "sg:address":"181, Rue de Cocq, 45160 Olivet",
    "sg:city":"Ardon",
    "sg:orig_category":"Non-Classified Establishments",
    "sg:phone":"+33 2 38 76 07 34",
    "sg:postcode":"45160",
    "sg:province":"Centre",
    "wof:name":"Mdic S.a.r.l. - Maintenance D\u00e9pannage Industrielle Du Centre",
    "wof:placetype":"venue"
},
  "geometry": {"coordinates":[1.876528,47.865971],"type":"Point"}
}