{
  "type": "Feature",
  "properties": {
    "iso:country":"FR",
    "sg:address":"89 Avenue De Colmar 67100 Strasbourg",
    "sg:city":"Strasbourg",
    "sg:classifiers":[
        {
            "category":"Travel",
            "subcategory":"Hotels & Motels",
            "type":"Entertainment"
        }
    ],
    "sg:phone":"+33 3 88 84 02 03",
    "sg:postcode":"67100",
    "sg:province":"Alsace",
    "sg:tags":[
        "hotels",
        "business",
        "restaurant"
    ],
    "wof:name":"Dominos Pizza",
    "wof:placetype":"venue"
},
  "geometry": {"coordinates":[7.752166,48.568356],"type":"Point"}
}