{
  "type": "Feature",
  "properties": {
    "addr:full":"2, 3\u00e8me Rue - ZI des Estroublans, 13127 Vitrolles Midi Pyr\u00e9n\u00e9es",
    "addr:housenumber":"2",
    "addr:postcode":"13127",
    "addr:street":"Rue Zi Des Estroublans",
    "iso:country":"FR",
    "sg:address":"2, 3\u00e8me Rue - ZI des Estroublans, 13127 Vitrolles",
    "sg:orig_category":"Unclassifiable Establishments",
    "sg:phone":"+33 4 42 46 18 46",
    "sg:province":"Midi Pyr\u00e9n\u00e9es",
    "wof:name":"Adres Routage S.a.",
    "wof:placetype":"venue"
},
  "geometry": {"coordinates":[5.24562,43.428753],"type":"Point"}
}