{
  "type": "Feature",
  "properties": {
    "iso:country":"FR",
    "sg:address":"Les D\u00e9pots 69430 St Didier Sur Beaujeu",
    "sg:classifiers":[
        {
            "category":"Wholesale",
            "subcategory":"Farm Supplies",
            "type":"Manufacturing & Wholesale Goods"
        }
    ],
    "sg:phone":"+33 4 74 04 85 26",
    "sg:postcode":"69430",
    "sg:province":"Rhone-Alpes",
    "sg:tags":[
        "-",
        "machine",
        "equipment",
        "engineering",
        "machinery",
        "mechanical",
        "agriculture"
    ],
    "wof:name":"Ets Paul Butty Sarl",
    "wof:placetype":"venue"
},
  "geometry": {"coordinates":[4.571452,46.113628],"type":"Point"}
}