{
  "type": "Feature",
  "properties": {
    "addr:full":"11, Rue Alfred Kastler - ZA du Mittelfeld, 67300 Schiltigheim Schiltigheim Alsace 67300",
    "addr:housenumber":"11",
    "addr:postcode":"67300;67300",
    "addr:street":"Rue Alfred Kastler Za Du Mittelfeld",
    "iso:country":"FR",
    "sg:address":"11, Rue Alfred Kastler - ZA du Mittelfeld, 67300 Schiltigheim",
    "sg:city":"Schiltigheim",
    "sg:orig_category":"Unclassifiable Establishments",
    "sg:phone":"+33 3 88 83 11 89",
    "sg:postcode":"67300",
    "sg:province":"Alsace",
    "wof:name":"Tr\u00e9ma S.a.",
    "wof:placetype":"venue"
},
  "geometry": {"coordinates":[7.748565,48.605949],"type":"Point"}
}