{
  "type": "Feature",
  "properties": {
    "addr:full":"41, Rte de Poitiers, 86340 Nouaille Maupertuis Poitou-Charentes",
    "addr:housenumber":"41",
    "addr:postcode":"86340",
    "addr:street":"Rte De Poitiers",
    "iso:country":"FR",
    "sg:address":"41, Rte de Poitiers, 86340 Nouaille Maupertuis",
    "sg:orig_category":"Non-Classified Establishments",
    "sg:phone":"+33 5 49 46 54 63",
    "sg:province":"Poitou-Charentes",
    "wof:name":"T.m.o. Sarl - Taillage Mortissage De L'ouest",
    "wof:placetype":"venue"
},
  "geometry": {"coordinates":[0.486596,46.425323],"type":"Point"}
}