{
  "type": "Feature",
  "properties": {
    "iso:country":"FR",
    "sg:address":"144, Rue de la Lib\u00e9ration, 60530 Le Mesnil en Thelle",
    "sg:orig_category":"Unclassifiable Establishments",
    "sg:phone":"+33 3 44 26 77 05",
    "sg:province":"Picardie",
    "wof:name":"Dobigny S.a.r.l.",
    "wof:placetype":"venue"
},
  "geometry": {"coordinates":[2.285613,49.185246],"type":"Point"}
}