{
  "type": "Feature",
  "properties": {
    "iso:country":"FR",
    "sg:address":"ZI de la Gare",
    "sg:city":"Sore",
    "sg:orig_category":"Non-Classified Establishments",
    "sg:phone":"+33 5 58 07 61 79",
    "sg:postcode":"40430",
    "sg:province":"Aquitaine",
    "wof:name":"Lecopin S.a.",
    "wof:placetype":"venue"
},
  "geometry": {"coordinates":[-0.583024,44.323235],"type":"Point"}
}