{
  "type": "Feature",
  "properties": {
    "addr:full":"28, Av. du G\u00e9n\u00e9ral Guillaut, 66000 Perpignan Languedoc-Roussillon",
    "addr:postcode":"66000",
    "addr:street":"28 Av. Du Ge\u0301Ne\u0301Ral Guillaut",
    "iso:country":"FR",
    "sg:address":"28, Av. du G\u00e9n\u00e9ral Guillaut, 66000 Perpignan",
    "sg:orig_category":"Unclassifiable Establishments",
    "sg:phone":"+33 4 68 56 99 19",
    "sg:province":"Languedoc-Roussillon",
    "wof:name":"A.d.g. M\u00e9dit\u00e9rann\u00e9e S.a.",
    "wof:placetype":"venue"
},
  "geometry": {"coordinates":[2.894346,42.689198],"type":"Point"}
}