{
  "type": "Feature",
  "properties": {
    "addr:full":"route d'Aunay 14500 ST GERMAIN DE TALLEVENDE Campagnolles Basse Normandie 14500",
    "addr:postcode":"14500;14500",
    "addr:street":"Route D'Aunay",
    "iso:country":"FR",
    "sg:address":"route d'Aunay 14500 ST GERMAIN DE TALLEVENDE",
    "sg:city":"Campagnolles",
    "sg:classifiers":[
        {
            "category":"Shopping",
            "subcategory":"Jewelry",
            "type":"Retail Goods"
        }
    ],
    "sg:phone":"+33 2 31 66 44 00",
    "sg:postcode":"14500",
    "sg:province":"Basse Normandie",
    "sg:tags":[
        "jewellery",
        "gold"
    ],
    "wof:name":"Guy Degrenne S.a.",
    "wof:placetype":"venue"
},
  "geometry": {"coordinates":[-0.90003,48.800549],"type":"Point"}
}