{
  "type": "Feature",
  "properties": {
    "iso:country":"FR",
    "sg:address":"7 av Jean Moulin; Vitrolles",
    "sg:classifiers":[
        {
            "category":"Banks & Credit Unions",
            "subcategory":"Bank",
            "type":"Services"
        }
    ],
    "sg:phone":"+33 3342894717",
    "sg:province":"Centre",
    "wof:name":"Lyonnaise De Banque",
    "wof:placetype":"venue"
},
  "geometry": {"coordinates":[5.248614,43.457245],"type":"Point"}
}