{
  "type": "Feature",
  "properties": {
    "iso:country":"FR",
    "sg:address":"rue des P\u00e2tis 76140 Le Petit Quevilly",
    "sg:orig_category":"Telecommunication Equipment",
    "sg:phone":"+33 2 32 81 64 81",
    "sg:province":"Haute Normandie",
    "wof:name":"Trans Service Sa",
    "wof:placetype":"venue"
},
  "geometry": {"coordinates":[1.041358,49.431187],"type":"Point"}
}