{
  "type": "Feature",
  "properties": {
    "addr:full":"19 rue de la Pr\u00e9fecture; Besan\u00e7on; 25044 Besan\u00e7on Franche Comt\u00e9 25000",
    "addr:housenumber":"19",
    "addr:postcode":"25044;25000",
    "addr:street":"Rue De La Pre\u0301Fecture;Franche Comte\u0301",
    "iso:country":"FR",
    "sg:address":"19 rue de la Pr\u00e9fecture; Besan\u00e7on; 25044",
    "sg:city":"Besan\u00e7on",
    "sg:classifiers":[
        {
            "category":"Banks & Credit Unions",
            "subcategory":"Bank",
            "type":"Services"
        }
    ],
    "sg:phone":"+33 3 81 65 21 21",
    "sg:postcode":"25000",
    "sg:province":"Franche Comt\u00e9",
    "wof:name":"Banque De France",
    "wof:placetype":"venue"
},
  "geometry": {"coordinates":[6.024029,47.234234],"type":"Point"}
}