{
  "type": "Feature",
  "properties": {
    "iso:country":"FR",
    "sg:address":"B.P. 27, 27160 Breteuil^^262, Rue Modeste Leroy, 27160 Breteuil",
    "sg:orig_category":"Non-Classified Establishments",
    "sg:phone":"+33 2 32 29 74 90",
    "sg:province":"Haute Normandie",
    "wof:name":"S.e.w.f. S.a.r.l. S.a.r.l. - Soci\u00e9t\u00e9 D'exploitation Wohlschlegel & Fils",
    "wof:placetype":"venue"
},
  "geometry": {"coordinates":[0.85262,48.788513],"type":"Point"}
}