{
  "type": "Feature",
  "properties": {
    "iso:country":"FR",
    "sg:address":"54, Quai Michelet, 92681 Levallois Perret C\u00e9dex",
    "sg:orig_category":"Unclassifiable Establishments",
    "sg:phone":"+33 1 41 34 50 00",
    "sg:province":"\u00cele-de-France",
    "wof:name":"Marsh S.a.",
    "wof:placetype":"venue"
},
  "geometry": {"coordinates":[2.284577,48.900864],"type":"Point"}
}