{
  "type": "Feature",
  "properties": {
    "iso:country":"FR",
    "sg:address":"9 rue Franklin 78180 Montigny le Bretonneux",
    "sg:classifiers":[
        {
            "category":"Airport",
            "subcategory":"General Aviation",
            "type":"Transportation"
        }
    ],
    "sg:phone":"+33 1 30 85 43 00",
    "sg:postcode":"78180",
    "sg:province":"Ile de France",
    "sg:tags":[
        "engine"
    ],
    "wof:name":"Groupe Labinal S.a.r.l.",
    "wof:placetype":"venue"
},
  "geometry": {"coordinates":[2.039345,48.770237],"type":"Point"}
}