{
  "type": "Feature",
  "properties": {
    "addr:full":"21 rue Westrich 67600 Selestat S\u00e9lestat Alsace 67600",
    "addr:housenumber":"21",
    "addr:postcode":"67600;67600",
    "addr:street":"Rue Westrich",
    "iso:country":"FR",
    "sg:address":"21 rue Westrich 67600 Selestat",
    "sg:city":"S\u00e9lestat",
    "sg:classifiers":[
        {
            "category":"Banks & Credit Unions",
            "subcategory":"Investment Brokerage",
            "type":"Services"
        }
    ],
    "sg:phone":"+33 3 88 57 48 50",
    "sg:postcode":"67600",
    "sg:province":"Alsace",
    "sg:tags":[
        "table",
        "all-purpose",
        "roller"
    ],
    "wof:name":"St\u00e9 Wanzl Sa",
    "wof:placetype":"venue"
},
  "geometry": {"coordinates":[7.46336,48.283817],"type":"Point"}
}