{
  "type": "Feature",
  "properties": {
    "addr:full":"2, Bd du Petit Quinquin - Z.I. du CRT de Lesquin, 59273 Fretin Nord Pas-de-Calais 59273",
    "addr:housenumber":"2",
    "addr:postcode":"59273;59273",
    "addr:street":"Bd Du Petit Quinquin Z.I. Du Crt De Lesquin",
    "iso:country":"FR",
    "sg:address":"2, Bd du Petit Quinquin - Z.I. du CRT de Lesquin, 59273 Fretin",
    "sg:orig_category":"Non-Classified Establishments",
    "sg:phone":"+33 3 20 16 17 18",
    "sg:postcode":"59273",
    "sg:province":"Nord Pas-de-Calais",
    "wof:name":"59 Express - Flandre Express S.a.",
    "wof:placetype":"venue"
},
  "geometry": {"coordinates":[3.133035,50.557724],"type":"Point"}
}