{
  "type": "Feature",
  "properties": {
    "iso:country":"FR",
    "sg:address":"Rue Poil Girard 45310 Patay",
    "sg:city":"Patay",
    "sg:classifiers":[
        {
            "category":"Home & Garden",
            "subcategory":"Furniture",
            "type":"Retail Goods"
        }
    ],
    "sg:phone":"+33 2 38 80 07 53",
    "sg:postcode":"45310",
    "sg:province":"Centre",
    "sg:tags":[
        "wood"
    ],
    "wof:name":"France Palettes Services Sarl",
    "wof:placetype":"venue"
},
  "geometry": {"coordinates":[1.69743,48.05117],"type":"Point"}
}