{
  "type": "Feature",
  "properties": {
    "iso:country":"FR",
    "sg:address":"B.P. 160, 71204 Le Creusot C\u00e9dex^^27/29, Rue de Serbie, 71200 Le Creusot",
    "sg:city":"Le Creusot",
    "sg:orig_category":"Non-Classified Establishments",
    "sg:phone":"+33 3 85 77 90 30",
    "sg:postcode":"71200",
    "sg:province":"Bourgogne",
    "wof:name":"A.c.i.m. S.a. - Atelier De Chaudronnerie Industrielle Et M\u00e9canique",
    "wof:placetype":"venue"
},
  "geometry": {"coordinates":[4.421295,46.806164],"type":"Point"}
}