{
  "type": "Feature",
  "properties": {
    "iso:country":"FR",
    "sg:address":"ZA de Domagne 01250 Ceyzeriat",
    "sg:classifiers":[
        {
            "category":"Manufacturing",
            "subcategory":"Printing",
            "type":"Manufacturing & Wholesale Goods"
        }
    ],
    "sg:phone":"+33 4 74 30 06 44",
    "sg:province":"Rhone-Alpes",
    "sg:tags":[
        "screen",
        "foil"
    ],
    "wof:name":"Euroseri Sa",
    "wof:placetype":"venue"
},
  "geometry": {"coordinates":[5.324115,46.178776],"type":"Point"}
}