{
  "type": "Feature",
  "properties": {
    "addr:full":"Min Saint Augustin 06200 Nice Basse Normandie",
    "addr:postcode":"06200",
    "iso:country":"FR",
    "sg:address":"Min Saint Augustin 06200 Nice",
    "sg:classifiers":[
        {
            "category":"Home & Garden",
            "subcategory":"Garden Supply",
            "type":"Retail Goods"
        }
    ],
    "sg:phone":"+33 4 93 83 23 80",
    "sg:province":"Basse Normandie",
    "sg:tags":[
        "supplies",
        "florist's",
        "miscellaneous"
    ],
    "wof:name":"F.j.c Mediterran\u00e9e S.a.r.l.",
    "wof:placetype":"venue"
},
  "geometry": {"coordinates":[7.205069,43.674545],"type":"Point"}
}