{
  "type": "Feature",
  "properties": {
    "iso:country":"FR",
    "sg:address":"862, Rue de Crais, 71000 M\u00e2con",
    "sg:city":"Sanc\u00e9",
    "sg:orig_category":"Unclassifiable Establishments",
    "sg:phone":"+33 3 85 20 44 00",
    "sg:postcode":"71000",
    "sg:province":"Bourgogne",
    "wof:name":"Simire S.a.",
    "wof:placetype":"venue"
},
  "geometry": {"coordinates":[4.792668,46.286102],"type":"Point"}
}