{
  "type": "Feature",
  "properties": {
    "iso:country":"FR",
    "sg:address":"Av Andr\u00e9 Chausson Zi De Gr\u00e9vaux Les Guides 59600 Maubeuge",
    "sg:classifiers":[
        {
            "category":"Autos & Motor Vehicles",
            "subcategory":"Automobile Sales",
            "type":"Retail Goods"
        }
    ],
    "sg:phone":"+33 3 27 53 54 55",
    "sg:postcode":"59600",
    "sg:province":"Nord Pas-de-Calais",
    "sg:tags":[
        "equipment",
        "motor-cars",
        "transport"
    ],
    "wof:name":"Mca",
    "wof:placetype":"venue"
},
  "geometry": {"coordinates":[3.973845,50.278664],"type":"Point"}
}