{
  "type": "Feature",
  "properties": {
    "iso:country":"FR",
    "sg:address":"Le Bourg 71370 Baudri\u00e8res",
    "sg:city":"Baudri\u00e8res",
    "sg:classifiers":[
        {
            "category":"Farming",
            "subcategory":"Farm & Veterinary Services",
            "type":"Manufacturing & Wholesale Goods"
        }
    ],
    "sg:phone":"+33 3 85 42 04 04",
    "sg:postcode":"71370",
    "sg:province":"Bourgogne",
    "sg:tags":[
        "food",
        "product",
        "breeding",
        "animal",
        "related"
    ],
    "wof:name":"Compagnie De Distribution Des Prodiuts Neolait (codislait) Codislait",
    "wof:placetype":"venue"
},
  "geometry": {"coordinates":[4.9812,46.652473],"type":"Point"}
}