{
  "type": "Feature",
  "properties": {
    "iso:country":"FR",
    "sg:address":"B.P. 271, 73375 Le Bourget du Lac C\u00e9dex^^Technolac B\u00e2t. Suro\u00eet, 73370 Le Bourget du Lac",
    "sg:orig_category":"Non-Classified Establishments",
    "sg:phone":"+33 4 79 25 07 83",
    "sg:province":"Rhone-Alpes",
    "wof:name":"M.b.e. S.a.r.l. - Maquettes Et Bureau D'etudes",
    "wof:placetype":"venue"
},
  "geometry": {"coordinates":[5.86225,45.643875],"type":"Point"}
}