{
  "type": "Feature",
  "properties": {
    "addr:full":"40 rue du Tribunal; Foug\u00e8res Centre",
    "addr:housenumber":"40",
    "addr:street":"Rue Du Tribunal",
    "iso:country":"FR",
    "sg:address":"40 rue du Tribunal; Foug\u00e8res",
    "sg:classifiers":[
        {
            "category":"Banks & Credit Unions",
            "subcategory":"Bank",
            "type":"Services"
        }
    ],
    "sg:phone":"+33 2 99 94 49 00",
    "sg:province":"Centre",
    "wof:name":"Banque De Bretagne Sa",
    "wof:placetype":"venue"
},
  "geometry": {"coordinates":[-1.200714,48.351982],"type":"Point"}
}