{
  "type": "Feature",
  "properties": {
    "iso:country":"FR",
    "sg:address":"62, Rue Denfert Rochereau, 84800 L'Isle sur la Sorgue",
    "sg:orig_category":"Unclassifiable Establishments",
    "sg:phone":"+33 4 90 38 45 45",
    "sg:province":"Limousin",
    "wof:name":"Le Mellec Conseil",
    "wof:placetype":"venue"
},
  "geometry": {"coordinates":[5.049306,43.921345],"type":"Point"}
}