{
  "type": "Feature",
  "properties": {
    "iso:country":"FR",
    "sg:address":"47, Rue Ayguelongue - Z.I. de Benlanne, 64160 Morla\u00e0s",
    "sg:city":"Morla\u00e0s",
    "sg:orig_category":"Non-Classified Establishments",
    "sg:phone":"+33 5 59 14 12 15",
    "sg:postcode":"64160",
    "sg:province":"Aquitaine",
    "wof:name":"Triangle Service S.a.r.l.",
    "wof:placetype":"venue"
},
  "geometry": {"coordinates":[-0.187904,43.318733],"type":"Point"}
}