{
  "type": "Feature",
  "properties": {
    "addr:full":"Rouvier Plane Domaine De Rouviere Plane 83670 Chateauvert Champagne",
    "addr:postcode":"83670",
    "addr:street":"Rouvier Plane Domaine;Plane",
    "iso:country":"FR",
    "sg:address":"Rouvier Plane Domaine De Rouviere Plane 83670 Chateauvert",
    "sg:classifiers":[
        {
            "category":"Food Court",
            "type":"Food & Drink"
        }
    ],
    "sg:phone":"+33 4 98 05 25 80",
    "sg:province":"Champagne",
    "sg:tags":[
        "product",
        "related"
    ],
    "wof:name":"Rouviere Plane",
    "wof:placetype":"venue"
},
  "geometry": {"coordinates":[6.021936,43.49667],"type":"Point"}
}