{
  "type": "Feature",
  "properties": {
    "iso:country":"FR",
    "sg:address":"Av de Vabre",
    "sg:city":"Rodez",
    "sg:orig_category":"Unclassifiable Establishments",
    "sg:phone":"+33 5 65 78 12 12",
    "sg:postcode":"12000",
    "sg:province":"Midi Pyr\u00e9n\u00e9es",
    "wof:name":"12 Express S.a.r.l.",
    "wof:placetype":"venue"
},
  "geometry": {"coordinates":[2.570845,44.368382],"type":"Point"}
}