{
  "type": "Feature",
  "properties": {
    "addr:full":"79, Bd de la R\u00e9publique, 92430 Marnes la Coquette Ile de France",
    "addr:housenumber":"79",
    "addr:postcode":"92430",
    "addr:street":"Bd De La Re\u0301Publique",
    "iso:country":"FR",
    "sg:address":"79, Bd de la R\u00e9publique, 92430 Marnes la Coquette",
    "sg:orig_category":"Unclassifiable Establishments",
    "sg:phone":"+33 1 47 10 91 00",
    "sg:province":"Ile de France",
    "wof:name":"Satti Informatique S.a.r.l.",
    "wof:placetype":"venue"
},
  "geometry": {"coordinates":[2.156325,48.837528],"type":"Point"}
}