{
  "type": "Feature",
  "properties": {
    "addr:full":"19 Rue Du Bas Village Zi Sud-Est 35510 Cesson S\u00e9vign\u00e9 Cesson-S\u00e9vign\u00e9 Bretagne 35510",
    "addr:housenumber":"19",
    "addr:postcode":"35510;se\u0301vigne\u0301 cesson-se\u0301vigne\u0301;35510",
    "addr:street":"Rue Du Bas Village",
    "iso:country":"FR",
    "sg:address":"19 Rue Du Bas Village Zi Sud-Est 35510 Cesson S\u00e9vign\u00e9",
    "sg:city":"Cesson-S\u00e9vign\u00e9",
    "sg:classifiers":[
        {
            "category":"Wholesale",
            "subcategory":"Meat",
            "type":"Manufacturing & Wholesale Goods"
        }
    ],
    "sg:phone":"+33 2 99 50 91 94",
    "sg:postcode":"35510",
    "sg:province":"Bretagne",
    "sg:tags":[
        "food",
        "cooked",
        "product",
        "related"
    ],
    "wof:name":"Charcuterie Delaunay Sa",
    "wof:placetype":"venue"
},
  "geometry": {"coordinates":[-1.604404,48.117016],"type":"Point"}
}