{
  "type": "Feature",
  "properties": {
    "addr:full":"Za Lini\u00e8re 37600 Beaulieu Les Loches Loches Centre 37600",
    "addr:postcode":"37600;37600",
    "addr:street":"Za Linie\u0300Re",
    "iso:country":"FR",
    "sg:address":"Za Lini\u00e8re 37600 Beaulieu Les Loches",
    "sg:city":"Loches",
    "sg:classifiers":[
        {
            "category":"Government",
            "subcategory":"Department Of Motor Vehicles",
            "type":"Public Place"
        }
    ],
    "sg:phone":"+33 2 47 91 28 20",
    "sg:postcode":"37600",
    "sg:province":"Centre",
    "sg:tags":[
        "equipment",
        "industrial",
        "transport",
        "motor-cars"
    ],
    "wof:name":"Avon Polymeres France Sa",
    "wof:placetype":"venue"
},
  "geometry": {"coordinates":[1.01256,47.129227],"type":"Point"}
}