{
  "type": "Feature",
  "properties": {
    "iso:country":"FR",
    "sg:address":"69, Rue de Paris, 91400 Orsay",
    "sg:orig_category":"Unclassifiable Establishments",
    "sg:phone":"+33 1 64 46 25 27",
    "sg:province":"Ile de France",
    "wof:name":"Lexibook S.a.",
    "wof:placetype":"venue"
},
  "geometry": {"coordinates":[2.18861,48.697792],"type":"Point"}
}