{
  "type": "Feature",
  "properties": {
    "addr:full":"60 bis, Rue de l'Est, 92100 Boulogne Billancourt Ile de France",
    "addr:housenumber":"60 bis",
    "addr:postcode":"92100",
    "addr:street":"Rue De L'Est",
    "iso:country":"FR",
    "sg:address":"60 bis, Rue de l'Est, 92100 Boulogne Billancourt",
    "sg:orig_category":"Non-Classified Establishments",
    "sg:phone":"+33 1 41 22 02 90",
    "sg:province":"Ile de France",
    "wof:name":"Sarbacane S.a.r.l.",
    "wof:placetype":"venue"
},
  "geometry": {"coordinates":[2.244107,48.841747],"type":"Point"}
}