{
  "type": "Feature",
  "properties": {
    "addr:full":"1 Promenade De La Bonnette Gennevilliers Ile de France 92230",
    "addr:housenumber":"1",
    "addr:postcode":"92230",
    "addr:street":"Promenade De La Bonnette;Ile De France",
    "iso:country":"FR",
    "sg:address":"1 Promenade De La Bonnette",
    "sg:city":"Gennevilliers",
    "sg:classifiers":[
        {
            "category":"Banks & Credit Unions",
            "subcategory":"Financial Services",
            "type":"Services"
        }
    ],
    "sg:phone":"+33 1 41 85 85 85",
    "sg:postcode":"92230",
    "sg:province":"Ile de France",
    "sg:tags":[
        "banking",
        "finance",
        "insurance"
    ],
    "wof:name":"Europ Assistance",
    "wof:placetype":"venue"
},
  "geometry": {"coordinates":[2.304862,48.934113],"type":"Point"}
}