{
  "type": "Feature",
  "properties": {
    "addr:full":"137 avenue de Toulouse 65601 SEMEAC CEDEX Midi-Pyr\u00e9n\u00e9es",
    "addr:housenumber":"137",
    "addr:postcode":"65601;cedex",
    "addr:street":"Avenue De Toulouse",
    "iso:country":"FR",
    "sg:address":"137 avenue de Toulouse 65601 SEMEAC CEDEX",
    "sg:orig_category":"Trailers, Semi-Trailers For Transporting Agricultural Machinery And Trucks",
    "sg:phone":"+33 5 62 33 96 76",
    "sg:province":"Midi-Pyr\u00e9n\u00e9es",
    "wof:name":"Pomiers Sa",
    "wof:placetype":"venue"
},
  "geometry": {"coordinates":[0.11471,43.212048],"type":"Point"}
}