{
  "type": "Feature",
  "properties": {
    "iso:country":"FR",
    "sg:address":"3, Rue Pasteur, 17340 Ch\u00e2telaillon Plage",
    "sg:orig_category":"Non-Classified Establishments",
    "sg:phone":"+33 5 46 56 33 46",
    "sg:postcode":"17340",
    "sg:province":"Poitou-Charentes",
    "wof:name":"Atout Pique S.a.",
    "wof:placetype":"venue"
},
  "geometry": {"coordinates":[-1.088491,46.076443],"type":"Point"}
}