{
  "type": "Feature",
  "properties": {
    "addr:full":"44 Rue De Ch\u00e2teaudun 75009 Paris Ile de France 75009",
    "addr:housenumber":"44",
    "addr:postcode":"75009;75009",
    "addr:street":"Rue De Cha\u0302Teaudun",
    "iso:country":"FR",
    "sg:address":"44 Rue De Ch\u00e2teaudun 75009 Paris",
    "sg:classifiers":[
        {
            "category":"Banks & Credit Unions",
            "subcategory":"Financial Services",
            "type":"Services"
        }
    ],
    "sg:phone":"+33 1 70 96 60 00",
    "sg:postcode":"75009",
    "sg:province":"Ile de France",
    "sg:tags":[
        "banking",
        "finance",
        "insurance"
    ],
    "wof:name":"Contingency Insurance",
    "wof:placetype":"venue"
},
  "geometry": {"coordinates":[2.334572,48.876366],"type":"Point"}
}