{
  "type": "Feature",
  "properties": {
    "addr:full":"33 Route De La Federation 67100 Strasbourg Strasbourg Alsace 67100",
    "addr:housenumber":"33",
    "addr:postcode":"67100;67100",
    "addr:street":"Route De La Federation",
    "iso:country":"FR",
    "sg:address":"33 Route De La Federation 67100 Strasbourg",
    "sg:city":"Strasbourg",
    "sg:classifiers":[
        {
            "category":"Professional",
            "subcategory":"Printing & Photocopies",
            "type":"Services"
        }
    ],
    "sg:phone":"+33 3 88 79 40 10",
    "sg:postcode":"67100",
    "sg:province":"Alsace",
    "sg:tags":[
        "publishing"
    ],
    "wof:name":"Sarl Europub",
    "wof:placetype":"venue"
},
  "geometry": {"coordinates":[7.740646,48.56432],"type":"Point"}
}