{
  "type": "Feature",
  "properties": {
    "iso:country":"FR",
    "sg:address":"124 rue du G\u00e9n\u00e9ral; La Madeleine; 59110",
    "sg:classifiers":[
        {
            "category":"Banks & Credit Unions",
            "subcategory":"Bank",
            "type":"Services"
        }
    ],
    "sg:phone":"+33 20511740",
    "sg:postcode":"59110",
    "sg:province":"Nord Pas-de-Calais",
    "wof:name":"Banque Nationale De Paris",
    "wof:placetype":"venue"
},
  "geometry": {"coordinates":[3.073131,50.652668],"type":"Point"}
}