{
  "type": "Feature",
  "properties": {
    "iso:country":"FR",
    "sg:address":"163, Bd Davout, 75020 Paris",
    "sg:orig_category":"Unclassifiable Establishments",
    "sg:phone":"+33 1 40 30 28 63",
    "sg:province":"Ile de France",
    "wof:name":"Bona S.a.r.l.",
    "wof:placetype":"venue"
},
  "geometry": {"coordinates":[2.40937,48.859192],"type":"Point"}
}