{
  "type": "Feature",
  "properties": {
    "iso:country":"FR",
    "sg:address":"94/96, Rue de la Haye, 78130 Les Mureaux",
    "sg:orig_category":"Non-Classified Establishments",
    "sg:phone":"+33 1 34 92 50 00",
    "sg:province":"Ile de France",
    "wof:name":"Mgi Coutier S.a.",
    "wof:placetype":"venue"
},
  "geometry": {"coordinates":[1.900157,48.995056],"type":"Point"}
}