{
  "type": "Feature",
  "properties": {
    "iso:country":"FR",
    "sg:address":"La Grange des Meuniers 26170 MONTGUERS",
    "sg:classifiers":[
        {
            "category":"Retail",
            "subcategory":"Car Wash",
            "type":"Services"
        }
    ],
    "sg:phone":"+33 4 75 28 01 22",
    "sg:postcode":"26170",
    "sg:province":"Rhone-Alpes",
    "sg:tags":[
        "oil",
        "essential"
    ],
    "wof:name":"France Lavande Coop",
    "wof:placetype":"venue"
},
  "geometry": {"coordinates":[5.189085,44.235435],"type":"Point"}
}