{
  "type": "Feature",
  "properties": {
    "addr:full":"8 rue Biscarbidea 64500 ST JEAN DE LUZ Ciboure Aquitaine 64500",
    "addr:housenumber":"8",
    "addr:postcode":"64500;64500",
    "addr:street":"Rue Biscarbidea",
    "iso:country":"FR",
    "sg:address":"8 rue Biscarbidea 64500 ST JEAN DE LUZ",
    "sg:city":"Ciboure",
    "sg:classifiers":[
        {
            "category":"Building & Trades",
            "subcategory":"Construction",
            "type":"Services"
        }
    ],
    "sg:phone":"+33 5 59 51 20 20",
    "sg:postcode":"64500",
    "sg:province":"Aquitaine",
    "sg:tags":[
        "front",
        "door"
    ],
    "wof:name":"France Portes S.a.",
    "wof:placetype":"venue"
},
  "geometry": {"coordinates":[-1.656215,43.388443],"type":"Point"}
}