{
  "type": "Feature",
  "properties": {
    "addr:full":"Rue Berfnard Thimonnier Saint Just Saint Rambert C\u00e9dex Rhone-Alpes 42176",
    "addr:postcode":"42176",
    "addr:street":"Rue Berfnard Thimonnier;Rhone-Alpes",
    "iso:country":"FR",
    "sg:address":"Rue Berfnard Thimonnier",
    "sg:city":"Saint Just Saint Rambert C\u00e9dex",
    "sg:orig_category":"Non-Classified Establishments",
    "sg:phone":"+33 4 77 36 08 90",
    "sg:postcode":"42176",
    "sg:province":"Rhone-Alpes",
    "wof:name":"Ganzoni France S.a.",
    "wof:placetype":"venue"
},
  "geometry": {"coordinates":[4.273432,45.521198],"type":"Point"}
}