{
  "type": "Feature",
  "properties": {
    "addr:full":"240 Rue Jean Jaur\u00e8s 29287 Brest Cedex Champagne",
    "addr:housenumber":"240",
    "addr:postcode":"29287",
    "addr:street":"Rue Jean Jaure\u0300S",
    "iso:country":"FR",
    "sg:address":"240 Rue Jean Jaur\u00e8s 29287 Brest Cedex",
    "sg:classifiers":[
        {
            "category":"Professional",
            "subcategory":"Business Services",
            "type":"Services"
        }
    ],
    "sg:phone":"+33 2 98 02 20 52",
    "sg:province":"Champagne",
    "sg:tags":[
        "training",
        "advice"
    ],
    "wof:name":"Groupe Scolaire De L'estran St. Joseph",
    "wof:placetype":"venue"
},
  "geometry": {"coordinates":[-4.4869,48.390598],"type":"Point"}
}