{
  "type": "Feature",
  "properties": {
    "addr:full":"62930 Wimereux Nord Pas-de-Calais",
    "addr:postcode":"62930",
    "iso:country":"FR",
    "sg:address":"62930 Wimereux",
    "sg:orig_category":"Unclassifiable Establishments",
    "sg:phone":"+33 3 21 80 44 10",
    "sg:province":"Nord Pas-de-Calais",
    "wof:name":"P.i.d.m. S.a.r.l. - Peinture, Industrie, D\u00e9capage, Marine",
    "wof:placetype":"venue"
},
  "geometry": {"coordinates":[1.61484,50.772881],"type":"Point"}
}