{
  "type": "Feature",
  "properties": {
    "addr:full":"6, Place Saint Martin, 57000 Metz Lorraine",
    "addr:housenumber":"6",
    "addr:postcode":"57000",
    "addr:street":"Place Saint Martin",
    "iso:country":"FR",
    "sg:address":"6, Place Saint Martin, 57000 Metz",
    "sg:orig_category":"Unclassifiable Establishments",
    "sg:phone":"+33 3 87 76 42 80",
    "sg:province":"Lorraine",
    "wof:name":"Euro Cap Est S.a.",
    "wof:placetype":"venue"
},
  "geometry": {"coordinates":[6.176659,49.114719],"type":"Point"}
}