{
  "type": "Feature",
  "properties": {
    "iso:country":"FR",
    "sg:address":"5 rue Jean Mac\u00e9 92150 Suresnes",
    "sg:classifiers":[
        {
            "category":"Professional",
            "subcategory":"Testing Lab",
            "type":"Services"
        }
    ],
    "sg:phone":"+33 1 46 97 26 00",
    "sg:province":"Ile de France",
    "sg:tags":[
        "simulator"
    ],
    "wof:name":"G.d.i. Simulation Sa",
    "wof:placetype":"venue"
},
  "geometry": {"coordinates":[2.229118,48.87413],"type":"Point"}
}