{
  "type": "Feature",
  "properties": {
    "addr:full":"30, Av Faidherbe, 59240 Dunkerque Midi Pyr\u00e9n\u00e9es",
    "addr:postcode":"59240",
    "addr:street":"30 Av Faidherbe",
    "iso:country":"FR",
    "sg:address":"30, Av Faidherbe, 59240 Dunkerque",
    "sg:orig_category":"Non-Classified Establishments",
    "sg:phone":"+33 3 28 63 20 62",
    "sg:province":"Midi Pyr\u00e9n\u00e9es",
    "wof:name":"Ave S.a.r.l.",
    "wof:placetype":"venue"
},
  "geometry": {"coordinates":[2.394218,51.047249],"type":"Point"}
}