{
  "type": "Feature",
  "properties": {
    "addr:full":"14, Cours D'Herbouville, 69004 Lyon Rhone-Alpes 69004",
    "addr:housenumber":"14",
    "addr:postcode":"69004;69004",
    "addr:street":"Cours D'Herbouville",
    "iso:country":"FR",
    "sg:address":"14, Cours D'Herbouville, 69004 Lyon",
    "sg:orig_category":"Non-Classified Establishments",
    "sg:phone":"+33 4 78 30 83 64",
    "sg:postcode":"69004",
    "sg:province":"Rhone-Alpes",
    "wof:name":"Sc\u00e9ram S.a.",
    "wof:placetype":"venue"
},
  "geometry": {"coordinates":[4.840374,45.778259],"type":"Point"}
}