{
  "type": "Feature",
  "properties": {
    "iso:country":"FR",
    "sg:address":"13, Rue T\u00e9mara, 78100 Saint Germain en Laye",
    "sg:orig_category":"Non-Classified Establishments",
    "sg:phone":"+33 1 30 61 41 10",
    "sg:province":"Ile de France",
    "wof:name":"Rafal Repro S.a.r.l.",
    "wof:placetype":"venue"
},
  "geometry": {"coordinates":[2.074834,48.893097],"type":"Point"}
}