{
  "type": "Feature",
  "properties": {
    "iso:country":"FR",
    "sg:address":"Av Gontran Bienvenu Zi Le Prat 56000 Vannes",
    "sg:city":"Vannes",
    "sg:classifiers":[
        {
            "category":"Building & Trades",
            "subcategory":"Construction",
            "type":"Services"
        }
    ],
    "sg:phone":"+33 2 97 54 91 65",
    "sg:postcode":"56000",
    "sg:province":"Bretagne",
    "sg:tags":[
        "work",
        "public"
    ],
    "wof:name":"Coca Atlantique",
    "wof:placetype":"venue"
},
  "geometry": {"coordinates":[-2.759959,47.658169],"type":"Point"}
}