{
  "type": "Feature",
  "properties": {
    "iso:country":"FR",
    "sg:address":"30",
    "sg:city":"Obernai",
    "sg:classifiers":[
        {
            "category":"Food Court",
            "type":"Food & Drink"
        }
    ],
    "sg:phone":"+33 3 88 47 60 20",
    "sg:postcode":"67210",
    "sg:province":"Alsace",
    "sg:tags":[
        "product",
        "related"
    ],
    "wof:name":"Cave Vinicole D'obernai Divinal",
    "wof:placetype":"venue"
},
  "geometry": {"coordinates":[7.49561,48.472008],"type":"Point"}
}