{
  "type": "Feature",
  "properties": {
    "iso:country":"FR",
    "sg:address":"68 B Boulevard De Poitiers",
    "sg:city":"Bressuire",
    "sg:classifiers":[
        {
            "category":"Banks & Credit Unions",
            "subcategory":"Financial Services",
            "type":"Services"
        }
    ],
    "sg:phone":"+33 5 49 74 24 02",
    "sg:postcode":"79300",
    "sg:province":"Poitou-Charentes",
    "sg:tags":[
        "banking",
        "finance",
        "insurance"
    ],
    "wof:name":"Societe D'expertise Comptabilite Controle Conseil (e 3 C)",
    "wof:placetype":"venue"
},
  "geometry": {"coordinates":[-0.483516,46.838608],"type":"Point"}
}