{
  "type": "Feature",
  "properties": {
    "addr:full":"8, Place des Ursulines, 51000 Ch\u00e2lons en Champagne Champagne",
    "addr:housenumber":"8",
    "addr:postcode":"51000",
    "addr:street":"Place Des Ursulines",
    "iso:country":"FR",
    "sg:address":"8, Place des Ursulines, 51000 Ch\u00e2lons en Champagne",
    "sg:orig_category":"Unclassifiable Establishments",
    "sg:phone":"+33 3 26 68 02 65",
    "sg:province":"Champagne",
    "wof:name":"Salaisons Champenoises S.a.",
    "wof:placetype":"venue"
},
  "geometry": {"coordinates":[4.37067,48.956932],"type":"Point"}
}