{
  "type": "Feature",
  "properties": {
    "iso:country":"FR",
    "sg:address":"Rue Louis Jacques Th\u00e9nard - Zone Industrielle",
    "sg:city":"Ch\u00e2lon sur Sa\u00f4ne",
    "sg:orig_category":"Unclassifiable Establishments",
    "sg:phone":"+33 3 85 97 21 40",
    "sg:postcode":"71100",
    "sg:province":"Bourgogne",
    "wof:name":"Sateba S.a.",
    "wof:placetype":"venue"
},
  "geometry": {"coordinates":[4.854945,46.808941],"type":"Point"}
}