{
  "type": "Feature",
  "properties": {
    "addr:full":"B.P. 1228, 69611 Villeurbanne C\u00e9dex^^64, Bd du 11 Novembre 1918, 69100 Villeurbanne Rhone-Alpes 69100",
    "addr:postcode":"69611;ce\u0301dex^^64;69100;69100",
    "addr:street":"B.P. 1228;Bd Du 11 Novembre 1918",
    "iso:country":"FR",
    "sg:address":"B.P. 1228, 69611 Villeurbanne C\u00e9dex^^64, Bd du 11 Novembre 1918, 69100 Villeurbanne",
    "sg:orig_category":"Non-Classified Establishments",
    "sg:phone":"+33 4 26 68 65 00",
    "sg:postcode":"69100",
    "sg:province":"Rhone-Alpes",
    "wof:name":"B.s.n. Glasspack S.a.s.",
    "wof:placetype":"venue"
},
  "geometry": {"coordinates":[4.87905,45.769596],"type":"Point"}
}