{
  "type": "Feature",
  "properties": {
    "addr:full":"30 Rue Du Dr. Finlay 75015 Paris Ile de France 75015",
    "addr:housenumber":"30",
    "addr:postcode":"75015;75015",
    "addr:street":"Rue Du Dr. Finlay",
    "iso:country":"FR",
    "sg:address":"30 Rue Du Dr. Finlay 75015 Paris",
    "sg:classifiers":[
        {
            "category":"Professional",
            "subcategory":"Advertising",
            "type":"Services"
        }
    ],
    "sg:phone":"+33 1 44 37 56 56",
    "sg:postcode":"75015",
    "sg:province":"Ile de France",
    "sg:tags":[
        "information",
        "medium",
        "communication"
    ],
    "wof:name":"Highway Tv Sa",
    "wof:placetype":"venue"
},
  "geometry": {"coordinates":[2.289446,48.851673],"type":"Point"}
}