{
  "type": "Feature",
  "properties": {
    "addr:full":"8 Rue Leh 67720 Hoerdt Hoerdt Alsace 67720",
    "addr:housenumber":"8",
    "addr:postcode":"67720;67720",
    "addr:street":"Rue Leh",
    "iso:country":"FR",
    "sg:address":"8 Rue Leh 67720 Hoerdt",
    "sg:city":"Hoerdt",
    "sg:classifiers":[
        {
            "category":"Professional",
            "type":"Services"
        }
    ],
    "sg:phone":"+33 3 88 51 74 88",
    "sg:postcode":"67720",
    "sg:province":"Alsace",
    "sg:tags":[
        "transport",
        "road"
    ],
    "wof:name":"Transports Duchmann Et Fils Sarl",
    "wof:placetype":"venue"
},
  "geometry": {"coordinates":[7.7804,48.695717],"type":"Point"}
}