{
  "type": "Feature",
  "properties": {
    "iso:country":"FR",
    "sg:address":"6, Rte du Breuil, 78550 Bazainville",
    "sg:orig_category":"Non-Classified Establishments",
    "sg:phone":"+33 1 34 87 75 89",
    "sg:province":"Ile de France",
    "wof:name":"Tilt Import S.a.r.l.",
    "wof:placetype":"venue"
},
  "geometry": {"coordinates":[1.664773,48.803219],"type":"Point"}
}