{
  "type": "Feature",
  "properties": {
    "addr:full":"3, Rue de la Station, 95550 Bessancourt Ile de France 95550",
    "addr:housenumber":"3",
    "addr:postcode":"95550;95550",
    "addr:street":"Rue De La Station;Ile De France",
    "iso:country":"FR",
    "sg:address":"3, Rue de la Station, 95550 Bessancourt",
    "sg:orig_category":"Non-Classified Establishments",
    "sg:phone":"+33 1 34 18 03 10",
    "sg:postcode":"95550",
    "sg:province":"Ile de France",
    "wof:name":"A2l Multim\u00e9dia S.a.r.l.",
    "wof:placetype":"venue"
},
  "geometry": {"coordinates":[2.21087,49.035519],"type":"Point"}
}