{
  "type": "Feature",
  "properties": {
    "iso:country":"FR",
    "sg:address":"8 Rue De La Croix Martre 91120 Palaiseau",
    "sg:classifiers":[
        {
            "category":"Manufacturing",
            "subcategory":"Printing",
            "type":"Manufacturing & Wholesale Goods"
        }
    ],
    "sg:phone":"+33 1 69 30 11 75",
    "sg:province":"Ile de France",
    "sg:tags":[
        "publishing"
    ],
    "wof:name":"Sndf",
    "wof:placetype":"venue"
},
  "geometry": {"coordinates":[2.260229,48.719883],"type":"Point"}
}