{
  "type": "Feature",
  "properties": {
    "iso:country":"FR",
    "sg:address":"23, Rue Sergent Buttin, 69500 Bron",
    "sg:orig_category":"Non-Classified Establishments",
    "sg:phone":"+33 4 78 74 02 92",
    "sg:postcode":"69500",
    "sg:province":"Rhone-Alpes",
    "wof:name":"B\u00e9tonpierre S.a.",
    "wof:placetype":"venue"
},
  "geometry": {"coordinates":[4.89158,45.733734],"type":"Point"}
}