{
  "type": "Feature",
  "properties": {
    "iso:country":"FR",
    "sg:address":"143, Rue Louis Becker, 69100 Villeurbanne",
    "sg:orig_category":"Non-Classified Establishments",
    "sg:phone":"+33 4 78 84 53 10",
    "sg:province":"Rhone-Alpes",
    "wof:name":"Guignard S.a.r.l.",
    "wof:placetype":"venue"
},
  "geometry": {"coordinates":[4.878454,45.765446],"type":"Point"}
}