{
  "type": "Feature",
  "properties": {
    "addr:full":"B.P. 73, 31772 Colomiers C\u00e9dex^^31, Rue de Salvetat, 31770 Colomiers Midi Pyr\u00e9n\u00e9es",
    "addr:postcode":"31772;31770",
    "addr:street":"B.P. 73;Rue De Salvetat",
    "iso:country":"FR",
    "sg:address":"B.P. 73, 31772 Colomiers C\u00e9dex^^31, Rue de Salvetat, 31770 Colomiers",
    "sg:orig_category":"Non-Classified Establishments",
    "sg:phone":"+33 5 61 15 94 60",
    "sg:province":"Midi Pyr\u00e9n\u00e9es",
    "wof:name":"Lafarge Couverture S.a.s.",
    "wof:placetype":"venue"
},
  "geometry": {"coordinates":[1.33337,43.612431],"type":"Point"}
}