{
  "type": "Feature",
  "properties": {
    "iso:country":"FR",
    "sg:address":"R Maurice P\u00e9rin 08090 Tournes",
    "sg:city":"Aiglemont",
    "sg:orig_category":"Mechanical Engineering - machines Paper and Cardboard Paper and cardboard - Packaging materials",
    "sg:phone":"+33 3 24 52 90 46",
    "sg:postcode":"08090",
    "sg:province":"Champagne",
    "wof:name":"Ardenn'pac Sa",
    "wof:placetype":"venue"
},
  "geometry": {"coordinates":[4.632387,49.793259],"type":"Point"}
}