{
  "type": "Feature",
  "properties": {
    "addr:full":"3 Rn 83 67640 Fegersheim Fegersheim Alsace 67640",
    "addr:housenumber":"3",
    "addr:postcode":"67640;67640",
    "addr:street":"Rn 83",
    "iso:country":"FR",
    "sg:address":"3 Rn 83 67640 Fegersheim",
    "sg:city":"Fegersheim",
    "sg:classifiers":[
        {
            "category":"Food Court",
            "type":"Food & Drink"
        }
    ],
    "sg:phone":"+33 3 89 96 10 10",
    "sg:postcode":"67640",
    "sg:province":"Alsace",
    "sg:tags":[
        "product",
        "related"
    ],
    "wof:name":"Orangina France Sa",
    "wof:placetype":"venue"
},
  "geometry": {"coordinates":[7.679595,48.489704],"type":"Point"}
}