{
  "type": "Feature",
  "properties": {
    "iso:country":"FR",
    "sg:address":"B.P. 175, 81304 Graulhet C\u00e9dex^^14/16, Bd du Docteur Pontier, 81300 Graulhet",
    "sg:orig_category":"Non-Classified Establishments",
    "sg:phone":"+33 5 63 42 83 83",
    "sg:province":"Midi Pyr\u00e9n\u00e9es",
    "wof:name":"K.j. Quinn S.a.s.",
    "wof:placetype":"venue"
},
  "geometry": {"coordinates":[2.028947,43.697151],"type":"Point"}
}