{
  "type": "Feature",
  "properties": {
    "addr:full":"176 Avenue De Strasbourg 67170 Brumath Brumath Alsace 67170",
    "addr:housenumber":"176",
    "addr:postcode":"67170;67170",
    "addr:street":"Avenue De Strasbourg",
    "iso:country":"FR",
    "sg:address":"176 Avenue De Strasbourg 67170 Brumath",
    "sg:city":"Brumath",
    "sg:classifiers":[
        {
            "category":"Wholesale",
            "subcategory":"Medical Equipment & Supplies",
            "type":"Manufacturing & Wholesale Goods"
        }
    ],
    "sg:phone":"+33 3 88 68 37 73",
    "sg:postcode":"67170",
    "sg:province":"Alsace",
    "sg:tags":[
        "instrument",
        "health",
        "-",
        "precision"
    ],
    "wof:name":"Euro Proth",
    "wof:placetype":"venue"
},
  "geometry": {"coordinates":[7.707455,48.712646],"type":"Point"}
}