{
  "type": "Feature",
  "properties": {
    "iso:country":"FR",
    "sg:address":"12, Rue du Professeur Deperet, 69160 Tassin la Demi Lune",
    "sg:orig_category":"Non-Classified Establishments",
    "sg:phone":"+33 4 78 34 47 47",
    "sg:postcode":"69160",
    "sg:province":"Rhone-Alpes",
    "wof:name":"Flowserve International S.a.s",
    "wof:placetype":"venue"
},
  "geometry": {"coordinates":[4.76138,45.758121],"type":"Point"}
}