{
  "type": "Feature",
  "properties": {
    "iso:country":"FR",
    "sg:address":"532, Rue Foch - ZI de Vaux le P\u00e9nil, 77000 Melun",
    "sg:orig_category":"Unclassifiable Establishments",
    "sg:phone":"+33 1 64 83 57 00",
    "sg:province":"Ile de France",
    "wof:name":"Concept Bureau S.a.",
    "wof:placetype":"venue"
},
  "geometry": {"coordinates":[2.664085,48.539577],"type":"Point"}
}