{
  "type": "Feature",
  "properties": {
    "addr:full":"30 rue Fremicourt 75015 Paris Ile de France 75015",
    "addr:housenumber":"30",
    "addr:postcode":"75015;75015",
    "addr:street":"Rue Fremicourt",
    "iso:country":"FR",
    "sg:address":"30 rue Fremicourt 75015 Paris",
    "sg:classifiers":[
        {
            "category":"Shopping",
            "subcategory":"Computers & Home Electronics",
            "type":"Retail Goods"
        }
    ],
    "sg:phone":"+33 1 45 66 72 72",
    "sg:postcode":"75015",
    "sg:province":"Ile de France",
    "sg:tags":[
        "client-server",
        "software"
    ],
    "wof:name":"Axe Bureautique Informatique Sa",
    "wof:placetype":"venue"
},
  "geometry": {"coordinates":[2.299292,48.847412],"type":"Point"}
}