{
  "type": "Feature",
  "properties": {
    "iso:country":"FR",
    "sg:address":"18 quai Rouget de I'Isle; L'Isle sur la Sorgue",
    "sg:classifiers":[
        {
            "category":"Banks & Credit Unions",
            "subcategory":"Bank",
            "type":"Services"
        }
    ],
    "sg:phone":"+33 3390206360",
    "sg:province":"Limousin",
    "wof:name":"Soci\u00e9t\u00e9 Marseillaise De Cr\u00e9dit",
    "wof:placetype":"venue"
},
  "geometry": {"coordinates":[5.0533,43.91814],"type":"Point"}
}