{
  "type": "Feature",
  "properties": {
    "addr:full":"154, Rue Saint Acheul, 80090 Amiens Amiens Picardie 80000",
    "addr:housenumber":"154",
    "addr:postcode":"80090 amiens;80000",
    "addr:street":"Rue Saint Acheul",
    "iso:country":"FR",
    "sg:address":"154, Rue Saint Acheul, 80090 Amiens",
    "sg:city":"Amiens",
    "sg:orig_category":"Non-Classified Establishments",
    "sg:phone":"+33 3 22 46 23 09",
    "sg:postcode":"80000",
    "sg:province":"Picardie",
    "wof:name":"Couty Cl\u00e9ment S.a.",
    "wof:placetype":"venue"
},
  "geometry": {"coordinates":[2.32997,49.885151],"type":"Point"}
}