{
  "type": "Feature",
  "properties": {
    "addr:full":"Eyzat 19200 Saint Bonnet Pr\u00e8s Bort Limousin",
    "addr:postcode":"19200",
    "addr:street":"Eyzat",
    "iso:country":"FR",
    "sg:address":"Eyzat 19200 Saint Bonnet Pr\u00e8s Bort",
    "sg:orig_category":"Unclassifiable Establishments",
    "sg:phone":"+33 5 55 94 83 32",
    "sg:province":"Limousin",
    "wof:name":"Seve S.a.r.l.",
    "wof:placetype":"venue"
},
  "geometry": {"coordinates":[2.429582,45.483063],"type":"Point"}
}