{
  "type": "Feature",
  "properties": {
    "iso:country":"FR",
    "sg:address":"Parc d'Activit\u00e9 la Grange Blanche",
    "sg:city":"Courth\u00e9zon",
    "sg:orig_category":"Unclassifiable Establishments",
    "sg:phone":"+33 4 90 70 40 00",
    "sg:postcode":"84350",
    "sg:province":"Centre",
    "wof:name":"5/7 Etiquette S.a.",
    "wof:placetype":"venue"
},
  "geometry": {"coordinates":[4.88278,44.085239],"type":"Point"}
}