{
  "type": "Feature",
  "properties": {
    "iso:country":"FR",
    "sg:address":"Rue Nouvelle - Z.I. le Poirier",
    "sg:city":"Nogent le Roi",
    "sg:orig_category":"Unclassifiable Establishments",
    "sg:phone":"+33 2 37 65 50 00",
    "sg:postcode":"28210",
    "sg:province":"Centre",
    "wof:name":"Z.e.p. Industrie S.a.",
    "wof:placetype":"venue"
},
  "geometry": {"coordinates":[1.51454,48.635647],"type":"Point"}
}