{
  "type": "Feature",
  "properties": {
    "addr:full":"Rue Andr\u00e9 Sentuc Zac De L'Arsenal 69200 V\u00e9nissieux Rhone-Alpes",
    "addr:postcode":"69200",
    "addr:street":"Rue Andre\u0301 Sentuc Zac De L'Arsenal",
    "iso:country":"FR",
    "sg:address":"Rue Andr\u00e9 Sentuc Zac De L'Arsenal 69200 V\u00e9nissieux",
    "sg:classifiers":[
        {
            "category":"Shopping",
            "subcategory":"Computers & Home Electronics",
            "type":"Retail Goods"
        }
    ],
    "sg:phone":"+33 4 72 51 34 86",
    "sg:province":"Rhone-Alpes",
    "sg:tags":[
        "household",
        "appliance",
        "telecommunication",
        "audio-visual"
    ],
    "wof:name":"Cde",
    "wof:placetype":"venue"
},
  "geometry": {"coordinates":[4.874812,45.707661],"type":"Point"}
}