{
  "type": "Feature",
  "properties": {
    "addr:full":"4 Route De Blendecques 62219 Longuenesse Nord Pas-de-Calais 62219",
    "addr:housenumber":"4",
    "addr:postcode":"62219;62219",
    "addr:street":"Route De Blendecques",
    "iso:country":"FR",
    "sg:address":"4 Route De Blendecques 62219 Longuenesse",
    "sg:classifiers":[
        {
            "category":"Professional",
            "subcategory":"Engineering",
            "type":"Services"
        }
    ],
    "sg:phone":"+33 3 21 98 80 70",
    "sg:postcode":"62219",
    "sg:province":"Nord Pas-de-Calais",
    "sg:tags":[
        "machine",
        "-",
        "mechanical"
    ],
    "wof:name":"Sa Celsius",
    "wof:placetype":"venue"
},
  "geometry": {"coordinates":[2.26427,50.73769],"type":"Point"}
}