{
  "type": "Feature",
  "properties": {
    "iso:country":"FR",
    "sg:address":"5 boulevard de la Pin\u00e8de 06160 Juan les Pins",
    "sg:classifiers":[
        {
            "category":"Government",
            "subcategory":"Post Office",
            "type":"Public Place"
        }
    ],
    "sg:phone":"+33 4 93 67 55 84",
    "sg:province":"Centre",
    "sg:tags":[
        "mail",
        "order",
        "business"
    ],
    "wof:name":"Smart City Sarl",
    "wof:placetype":"venue"
},
  "geometry": {"coordinates":[7.1141,43.568306],"type":"Point"}
}