{
  "type": "Feature",
  "properties": {
    "addr:full":"172 Rue De Savoie 93410 Vaujours Ile de France 93410",
    "addr:housenumber":"172",
    "addr:postcode":"93410;ile;93410",
    "addr:street":"Rue De Savoie;France",
    "iso:country":"FR",
    "sg:address":"172 Rue De Savoie 93410 Vaujours",
    "sg:classifiers":[
        {
            "category":"Government",
            "subcategory":"Department Of Motor Vehicles",
            "type":"Public Place"
        }
    ],
    "sg:phone":"+33 1 49 63 10 50",
    "sg:postcode":"93410",
    "sg:province":"Ile de France",
    "sg:tags":[
        "equipment",
        "industrial",
        "transport",
        "motor-cars"
    ],
    "wof:name":"Safir Distribution",
    "wof:placetype":"venue"
},
  "geometry": {"coordinates":[2.592153,48.937824],"type":"Point"}
}