{
  "type": "Feature",
  "properties": {
    "iso:country":"FR",
    "sg:address":"Base A\u00e9rienne 125 13800 Istres",
    "sg:orig_category":"Unclassifiable Establishments",
    "sg:phone":"+33 4 42 56 77 77",
    "sg:province":"Provence-Alpes-C\u00f4te d'Azur",
    "wof:name":"Dassault Aviation S.a.",
    "wof:placetype":"venue"
},
  "geometry": {"coordinates":[4.986208,43.515144],"type":"Point"}
}