{
  "type": "Feature",
  "properties": {
    "iso:country":"FR",
    "sg:address":"Rue Gutenberg 89500 Villeneuve Sur Yonne",
    "sg:city":"Cornant",
    "sg:classifiers":[
        {
            "category":"Manufacturing",
            "subcategory":"Metals",
            "type":"Manufacturing & Wholesale Goods"
        }
    ],
    "sg:phone":"+33 3 86 87 22 29",
    "sg:postcode":"89500",
    "sg:province":"Bourgogne",
    "sg:tags":[
        "-",
        "machine",
        "equipment",
        "engineering",
        "machinery",
        "mechanical"
    ],
    "wof:name":"Famey",
    "wof:placetype":"venue"
},
  "geometry": {"coordinates":[3.280524,48.088497],"type":"Point"}
}