{
  "type": "Feature",
  "properties": {
    "addr:full":"113 Rue Charles Van Wyngene 77181 Courtry Ile de France",
    "addr:housenumber":"113",
    "addr:postcode":"77181;ile",
    "addr:street":"Rue Charles Van Wyngene",
    "iso:country":"FR",
    "sg:address":"113 Rue Charles Van Wyngene 77181 Courtry",
    "sg:classifiers":[
        {
            "category":"Manufacturing",
            "subcategory":"Paper Products",
            "type":"Manufacturing & Wholesale Goods"
        }
    ],
    "sg:phone":"+33 1 60 20 21 88",
    "sg:province":"Ile de France",
    "sg:tags":[
        "raw",
        "material",
        "-",
        "cardboard"
    ],
    "wof:name":"Robert Renault Et Compagnie Sa",
    "wof:placetype":"venue"
},
  "geometry": {"coordinates":[2.603316,48.908489],"type":"Point"}
}