{
  "type": "Feature",
  "properties": {
    "addr:full":"Rue de Daubensand Obenheim Alsace 67230",
    "addr:postcode":"67230",
    "addr:street":"Rue De Daubensand",
    "iso:country":"FR",
    "sg:address":"Rue de Daubensand",
    "sg:city":"Obenheim",
    "sg:orig_category":"Unclassifiable Establishments",
    "sg:phone":"+33 3 88 98 31 05",
    "sg:postcode":"67230",
    "sg:province":"Alsace",
    "wof:name":"Choucroute Du Rhin S.a.",
    "wof:placetype":"venue"
},
  "geometry": {"coordinates":[7.697965,48.359444],"type":"Point"}
}