{
  "type": "Feature",
  "properties": {
    "addr:full":"B.P. 49, 67140 Gertwiller^^Chemin Bruchelmatt, 67140 Gertwiller Gertwiller Alsace 67140",
    "addr:postcode":"67140;67140;67140",
    "addr:street":"B.P. 49;Bruchelmatt;Gertwiller",
    "iso:country":"FR",
    "sg:address":"B.P. 49, 67140 Gertwiller^^Chemin Bruchelmatt, 67140 Gertwiller",
    "sg:city":"Gertwiller",
    "sg:orig_category":"Non-Classified Establishments",
    "sg:phone":"+33 3 88 58 54 60",
    "sg:postcode":"67140",
    "sg:province":"Alsace",
    "wof:name":"N\u00e9o Color S.a.r.l.",
    "wof:placetype":"venue"
},
  "geometry": {"coordinates":[7.452449,48.406513],"type":"Point"}
}