{
  "type": "Feature",
  "properties": {
    "addr:full":"B.P. 513, 13127 Vitrolles^^Voie d'Autriche, 13127 Vitrolles Provence-Alpes-C\u00f4te d'Azur",
    "addr:housenumber":"b.p. 513",
    "addr:postcode":"13127;13127",
    "addr:street":"D'Autriche",
    "iso:country":"FR",
    "sg:address":"B.P. 513, 13127 Vitrolles^^Voie d'Autriche, 13127 Vitrolles",
    "sg:orig_category":"Non-Classified Establishments",
    "sg:phone":"+33 4 42 46 89 50",
    "sg:province":"Provence-Alpes-C\u00f4te d'Azur",
    "wof:name":"Gama International S.a.",
    "wof:placetype":"venue"
},
  "geometry": {"coordinates":[5.265164,43.419769],"type":"Point"}
}