{
  "type": "Feature",
  "properties": {
    "iso:country":"FR",
    "sg:address":"6 Rue General Mocquery 37550 St Avertin",
    "sg:city":"Saint-Avertin",
    "sg:classifiers":[
        {
            "category":"Health Services",
            "subcategory":"Medical Lab",
            "type":"Services"
        }
    ],
    "sg:phone":"+33 2 47 27 75 42",
    "sg:postcode":"37550",
    "sg:province":"Centre",
    "sg:tags":[
        "instrument",
        "-",
        "precision",
        "equipment",
        "electrical",
        "electronic"
    ],
    "wof:name":"Meditech",
    "wof:placetype":"venue"
},
  "geometry": {"coordinates":[0.736225,47.34243],"type":"Point"}
}