{
  "type": "Feature",
  "properties": {
    "iso:country":"FR",
    "sg:address":"1 rue de La Petite Buissi\u00e8re 25410 ST VIT",
    "sg:classifiers":[
        {
            "category":"Manufacturing",
            "subcategory":"Motor Vehicles & Parts",
            "type":"Manufacturing & Wholesale Goods"
        }
    ],
    "sg:phone":"+33 3 81 55 11 12",
    "sg:province":"Franche Comt\u00e9",
    "sg:tags":[
        "precision",
        "mechanic"
    ],
    "wof:name":"Jone Orti Sa",
    "wof:placetype":"venue"
},
  "geometry": {"coordinates":[5.825425,47.182213],"type":"Point"}
}