{
  "type": "Feature",
  "properties": {
    "addr:full":"Rue de la Semoy 08800 LES HAUTES RIVIERES Deville Champagne 08800",
    "addr:postcode":"08800;08800",
    "addr:street":"Rue De La Semoy;Champagne",
    "iso:country":"FR",
    "sg:address":"Rue de la Semoy 08800 LES HAUTES RIVIERES",
    "sg:city":"Deville",
    "sg:classifiers":[
        {
            "category":"Government",
            "subcategory":"Fire Station",
            "type":"Public Place"
        }
    ],
    "sg:phone":"+33 3 24 53 40 45",
    "sg:postcode":"08800",
    "sg:province":"Champagne",
    "sg:tags":[
        "steel",
        "made",
        "component",
        "forged"
    ],
    "wof:name":"St\u00e9venin Nollevaux Sa",
    "wof:placetype":"venue"
},
  "geometry": {"coordinates":[4.845785,49.87492],"type":"Point"}
}