{
  "type": "Feature",
  "properties": {
    "iso:country":"FR",
    "sg:address":"Rue des Prairies - ZAC du Sablar",
    "sg:city":"Dax",
    "sg:orig_category":"Unclassifiable Establishments",
    "sg:phone":"+33 5 58 74 03 39",
    "sg:postcode":"40100",
    "sg:province":"Aquitaine",
    "wof:name":"Soci\u00e9t\u00e9 Agro Alimentaire Du Sablar S.a.",
    "wof:placetype":"venue"
},
  "geometry": {"coordinates":[-1.050939,43.707466],"type":"Point"}
}