{
  "type": "Feature",
  "properties": {
    "iso:country":"FR",
    "sg:address":"Rue du B\u00e9n\u00e9lux - ZI Euronord",
    "sg:city":"Lespinasse",
    "sg:orig_category":"Non-Classified Establishments",
    "sg:phone":"+33 5 62 79 87 98",
    "sg:postcode":"31150",
    "sg:province":"Midi Pyr\u00e9n\u00e9es",
    "wof:name":"Sodicob S.a.r.l.",
    "wof:placetype":"venue"
},
  "geometry": {"coordinates":[1.411975,43.726673],"type":"Point"}
}