{
  "type": "Feature",
  "properties": {
    "iso:country":"FR",
    "sg:address":"22 rue Georges Clemenceau; Champagne; 77430",
    "sg:classifiers":[
        {
            "category":"Banks & Credit Unions",
            "subcategory":"Bank",
            "type":"Services"
        }
    ],
    "sg:phone":"+33 3364230285",
    "sg:postcode":"77430",
    "sg:province":"Ile de France",
    "wof:name":"Soci\u00e9t\u00e9 G\u00e9n\u00e9rale",
    "wof:placetype":"venue"
},
  "geometry": {"coordinates":[2.797208,48.399689],"type":"Point"}
}