{
  "type": "Feature",
  "properties": {
    "addr:full":"B.P. 125, 70003 Vesoul C\u00e9dex^^Rue Saint Martin Prolong\u00e9e - Les Haberges , 70000 Vesoul Franche Comt\u00e9",
    "addr:housenumber":"b.p. 125",
    "addr:postcode":"70003;70000",
    "addr:street":"Prolonge\u0301E Les Haberges;Franche Comte\u0301",
    "iso:country":"FR",
    "sg:address":"B.P. 125, 70003 Vesoul C\u00e9dex^^Rue Saint Martin Prolong\u00e9e - Les Haberges , 70000 Vesoul",
    "sg:orig_category":"Non-Classified Establishments",
    "sg:phone":"+33 3 84 68 26 26",
    "sg:province":"Franche Comt\u00e9",
    "wof:name":"Techni Compta S.a.",
    "wof:placetype":"venue"
},
  "geometry": {"coordinates":[6.034054,47.524078],"type":"Point"}
}