{
  "type": "Feature",
  "properties": {
    "addr:full":"6 R Amp\u00e8re 65100 Lourdes Midi Pyr\u00e9n\u00e9es",
    "addr:housenumber":"6",
    "addr:postcode":"65100",
    "addr:street":"R Ampe\u0300Re",
    "iso:country":"FR",
    "sg:address":"6 R Amp\u00e8re 65100 Lourdes",
    "sg:classifiers":[
        {
            "category":"Manufacturing",
            "subcategory":"Printing",
            "type":"Manufacturing & Wholesale Goods"
        }
    ],
    "sg:phone":"+33 5 62 42 28 28",
    "sg:province":"Midi Pyr\u00e9n\u00e9es",
    "sg:tags":[
        "publishing"
    ],
    "wof:name":"Trans-log S.a.",
    "wof:placetype":"venue"
},
  "geometry": {"coordinates":[-0.028357,43.126717],"type":"Point"}
}