{
  "type": "Feature",
  "properties": {
    "addr:full":"3, Rue Gustave Eiffel - Le Technoparc - Espace M\u00e9dia, 78306 Poissy C\u00e9dex Basse Normandie",
    "addr:housenumber":"3",
    "addr:postcode":"78306",
    "addr:street":"Rue Gustave Eiffel Le",
    "iso:country":"FR",
    "sg:address":"3, Rue Gustave Eiffel - Le Technoparc - Espace M\u00e9dia, 78306 Poissy C\u00e9dex",
    "sg:orig_category":"Non-Classified Establishments",
    "sg:phone":"+33 1 39 22 63 45",
    "sg:province":"Basse Normandie",
    "wof:name":"Assist Tec S.a.r.l.",
    "wof:placetype":"venue"
},
  "geometry": {"coordinates":[2.04256,48.927971],"type":"Point"}
}