{
  "type": "Feature",
  "properties": {
    "addr:full":"6, Rue de Rouen, 67000 Strasbourg Strasbourg Alsace 67000",
    "addr:housenumber":"6",
    "addr:postcode":"67000;67000",
    "addr:street":"Rue De Rouen",
    "iso:country":"FR",
    "sg:address":"6, Rue de Rouen, 67000 Strasbourg",
    "sg:city":"Strasbourg",
    "sg:orig_category":"Non-Classified Establishments",
    "sg:phone":"+33 3 88 61 91 21",
    "sg:postcode":"67000",
    "sg:province":"Alsace",
    "wof:name":"Kapp Fran\u00e7is S.a.r.l.",
    "wof:placetype":"venue"
},
  "geometry": {"coordinates":[7.791294,48.591553],"type":"Point"}
}