{
  "type": "Feature",
  "properties": {
    "addr:full":"5, Rue de Bordeu, 64000 Pau Pau Aquitaine 64000",
    "addr:housenumber":"5",
    "addr:postcode":"64000;64000",
    "addr:street":"Rue De Bordeu",
    "iso:country":"FR",
    "sg:address":"5, Rue de Bordeu, 64000 Pau",
    "sg:city":"Pau",
    "sg:orig_category":"Unclassifiable Establishments",
    "sg:phone":"+33 5 59 80 28 18",
    "sg:postcode":"64000",
    "sg:province":"Aquitaine",
    "wof:name":"G.s.f. Atlantis S.a.",
    "wof:placetype":"venue"
},
  "geometry": {"coordinates":[-0.370974,43.303448],"type":"Point"}
}