{
  "type": "Feature",
  "properties": {
    "iso:country":"FR",
    "sg:address":"24 avenue du G\u00e9n\u00e9ral de Gaulle 92150 Suresnes",
    "sg:classifiers":[
        {
            "category":"Banks & Credit Unions",
            "subcategory":"Financial Services",
            "type":"Services"
        }
    ],
    "sg:phone":"+33 1 42 04 84 00",
    "sg:province":"Ile de France",
    "sg:tags":[
        "card",
        "smart"
    ],
    "wof:name":"Activcard Europe Sarl",
    "wof:placetype":"venue"
},
  "geometry": {"coordinates":[2.224408,48.870373],"type":"Point"}
}