{
  "type": "Feature",
  "properties": {
    "iso:country":"FR",
    "sg:address":"57 Rue De La Roquette 75011 Paris",
    "sg:classifiers":[
        {
            "category":"Professional",
            "subcategory":"Printing & Photocopies",
            "type":"Services"
        }
    ],
    "sg:phone":"+33 1 48 05 70 10",
    "sg:province":"Ile de France",
    "sg:tags":[
        "publishing"
    ],
    "wof:name":"Somogy Editions D'art",
    "wof:placetype":"venue"
},
  "geometry": {"coordinates":[2.375563,48.856102],"type":"Point"}
}