{
  "type": "Feature",
  "properties": {
    "addr:full":"ZI les Bracots Bons en Chablais Rhone-Alpes 74890",
    "addr:postcode":"74890",
    "addr:street":"Zi Les",
    "iso:country":"FR",
    "sg:address":"ZI les Bracots",
    "sg:city":"Bons en Chablais",
    "sg:orig_category":"Unclassifiable Establishments",
    "sg:phone":"+33 4 50 36 12 24",
    "sg:postcode":"74890",
    "sg:province":"Rhone-Alpes",
    "wof:name":"M.b.t.p. S.a.s. - Mat\u00e9riel Bonsois Travaux Publics",
    "wof:placetype":"venue"
},
  "geometry": {"coordinates":[6.37106,46.264935],"type":"Point"}
}