{
  "type": "Feature",
  "properties": {
    "iso:country":"FR",
    "sg:address":"31, Rue Amp\u00e8re, 69680 Chassieu",
    "sg:orig_category":"Non-Classified Establishments",
    "sg:phone":"+33 4 78 90 93 93",
    "sg:province":"Rhone-Alpes",
    "wof:name":"Ing\u00e9nierie Technique S.a.r.l.",
    "wof:placetype":"venue"
},
  "geometry": {"coordinates":[4.975787,45.729679],"type":"Point"}
}