{
  "type": "Feature",
  "properties": {
    "addr:full":"31, Rue Amp\u00e8re, 69680 Chassieu Rhone-Alpes",
    "addr:housenumber":"31",
    "addr:postcode":"69680",
    "addr:street":"Rue Ampe\u0300Re",
    "iso:country":"FR",
    "sg:address":"31, Rue Amp\u00e8re, 69680 Chassieu",
    "sg:orig_category":"Non-Classified Establishments",
    "sg:phone":"+33 4 78 90 93 93",
    "sg:province":"Rhone-Alpes",
    "wof:name":"Ing\u00e9nierie Technique S.a.r.l.",
    "wof:placetype":"venue"
},
  "geometry": {"coordinates":[4.975787,45.729679],"type":"Point"}
}