{
  "type": "Feature",
  "properties": {
    "addr:full":"Rue Jean Fran\u00e7ois Cail - ZI Nord Lucon Pays de Loire 85400",
    "addr:postcode":"85400",
    "addr:street":"Rue Jean Franc\u0327Ois Cail Zi Nord",
    "iso:country":"FR",
    "sg:address":"Rue Jean Fran\u00e7ois Cail - ZI Nord",
    "sg:city":"Lucon",
    "sg:orig_category":"Unclassifiable Establishments",
    "sg:phone":"+33 2 51 56 08 50",
    "sg:postcode":"85400",
    "sg:province":"Pays de Loire",
    "wof:name":"Soci\u00e9t\u00e9 M\u00e9canique De Pr\u00e9cision Baudry S.a.s.",
    "wof:placetype":"venue"
},
  "geometry": {"coordinates":[-1.169782,46.468372],"type":"Point"}
}