{
  "type": "Feature",
  "properties": {
    "iso:country":"FR",
    "sg:address":"B.P. 57, 59510 Hem^^7, All\u00e9e Gabert - ZA le Rivage, 59510 Hem",
    "sg:orig_category":"Non-Classified Establishments",
    "sg:phone":"+33 3 20 81 96 96",
    "sg:province":"Nord Pas-de-Calais",
    "wof:name":"Nord-climindustrie S.a.",
    "wof:placetype":"venue"
},
  "geometry": {"coordinates":[3.184105,50.653839],"type":"Point"}
}