{
  "type": "Feature",
  "properties": {
    "addr:full":"2 Av De L'Industrie 32730 Villecomtal Sur Arros Midi Pyr\u00e9n\u00e9es 32730",
    "addr:postcode":"32730;32730",
    "addr:street":"Av De L'Industrie",
    "iso:country":"FR",
    "sg:address":"2 Av De L'Industrie 32730 Villecomtal Sur Arros",
    "sg:classifiers":[
        {
            "category":"Food & Beverages",
            "subcategory":"Dairy",
            "type":"Retail Goods"
        }
    ],
    "sg:phone":"+33 5 62 64 78 05",
    "sg:postcode":"32730",
    "sg:province":"Midi Pyr\u00e9n\u00e9es",
    "sg:tags":[
        "product",
        "related"
    ],
    "wof:name":"Danone Villecomtal",
    "wof:placetype":"venue"
},
  "geometry": {"coordinates":[0.194182,43.401218],"type":"Point"}
}