{
  "type": "Feature",
  "properties": {
    "addr:full":"Chem Des Acacias Zi Les Ateliers Centraux 81400 Carmaux Midi Pyr\u00e9n\u00e9es 81400",
    "addr:postcode":"81400;81400",
    "addr:street":"Des Acacias Zi",
    "iso:country":"FR",
    "sg:address":"Chem Des Acacias Zi Les Ateliers Centraux 81400 Carmaux",
    "sg:classifiers":[
        {
            "category":"Manufacturing",
            "subcategory":"Metals",
            "type":"Manufacturing & Wholesale Goods"
        }
    ],
    "sg:phone":"+33 5 63 36 51 51",
    "sg:postcode":"81400",
    "sg:province":"Midi Pyr\u00e9n\u00e9es",
    "sg:tags":[
        "metallurgy",
        "-",
        "metalworking",
        "metallic",
        "machine",
        "engineering",
        "finished",
        "mechanical"
    ],
    "wof:name":"Etudes Realisations Industrielles Carmaux",
    "wof:placetype":"venue"
},
  "geometry": {"coordinates":[2.132425,44.032146],"type":"Point"}
}