{
  "type": "Feature",
  "properties": {
    "iso:country":"FR",
    "sg:address":"rue des Gatons 13008 Marseille",
    "sg:classifiers":[
        {
            "category":"Shopping",
            "subcategory":"Clothing, Apparel, & Fashions",
            "type":"Retail Goods"
        }
    ],
    "sg:phone":"+33 4 91 93 02 33",
    "sg:province":"Poitou-Charentes",
    "sg:tags":[
        "blouse",
        "ladies'",
        "dress"
    ],
    "wof:name":"Johnny Mailles Et Confection Sa",
    "wof:placetype":"venue"
},
  "geometry": {"coordinates":[5.376273,43.25238],"type":"Point"}
}