{
  "type": "Feature",
  "properties": {
    "addr:full":"Pa De Ragon Av Descartes 44119 Treilli\u00e8res Pays de Loire 44119",
    "addr:postcode":"44119;44119",
    "addr:street":"Av Descartes",
    "iso:country":"FR",
    "sg:address":"Pa De Ragon",
    "sg:city":"Av Descartes 44119 Treilli\u00e8res",
    "sg:classifiers":[
        {
            "category":"Professional",
            "subcategory":"Advertising",
            "type":"Services"
        }
    ],
    "sg:phone":"+33 2 51 12 34 00",
    "sg:postcode":"44119",
    "sg:province":"Pays de Loire",
    "sg:tags":[
        "information",
        "medium",
        "communication"
    ],
    "wof:name":"Greleg Publicite Peinte Ateliers Greleg",
    "wof:placetype":"venue"
},
  "geometry": {"coordinates":[-1.622475,47.330029],"type":"Point"}
}