{
  "type": "Feature",
  "properties": {
    "addr:full":"12 Rue De Palestine 75019 Paris Ile de France",
    "addr:housenumber":"12",
    "addr:postcode":"75019",
    "addr:street":"Rue De Palestine",
    "iso:country":"FR",
    "sg:address":"12 Rue De Palestine 75019 Paris",
    "sg:classifiers":[
        {
            "category":"Manufacturing",
            "subcategory":"Printing",
            "type":"Manufacturing & Wholesale Goods"
        }
    ],
    "sg:phone":"+33 1 42 02 13 38",
    "sg:province":"Ile de France",
    "sg:tags":[
        "publishing"
    ],
    "wof:name":"Huerma Ste Les Ateliers Sa",
    "wof:placetype":"venue"
},
  "geometry": {"coordinates":[2.389731,48.876343],"type":"Point"}
}