{
  "type": "Feature",
  "properties": {
    "iso:country":"FR",
    "sg:address":"20, Rue Roger Salengro, 77270 Villeparisis",
    "sg:orig_category":"Unclassifiable Establishments",
    "sg:phone":"+33 1 64 27 06 21",
    "sg:province":"Ile de France",
    "wof:name":"Cano S.a.",
    "wof:placetype":"venue"
},
  "geometry": {"coordinates":[2.605964,48.951828],"type":"Point"}
}