{
  "type": "Feature",
  "properties": {
    "iso:country":"FR",
    "sg:address":"B.P. 25, 85490 Benet Cedex^^Rte de Niort, 85490 Benet",
    "sg:orig_category":"Non-Classified Establishments",
    "sg:phone":"+33 2 51 00 90 86",
    "sg:postcode":"85490",
    "sg:province":"Pays de Loire",
    "wof:name":"Etablissement Lucas S.a.",
    "wof:placetype":"venue"
},
  "geometry": {"coordinates":[-0.595849,46.369236],"type":"Point"}
}