{
  "type": "Feature",
  "properties": {
    "iso:country":"FR",
    "sg:address":"Rue Laennec - Zone Forum",
    "sg:city":"Coigni\u00e8res",
    "sg:orig_category":"Unclassifiable Establishments",
    "sg:phone":"+33 1 30 05 00 50",
    "sg:postcode":"78310",
    "sg:province":"Ile de France",
    "wof:name":"Cardy Blue Station S.a.r.l.",
    "wof:placetype":"venue"
},
  "geometry": {"coordinates":[1.944855,48.761749],"type":"Point"}
}