{
  "type": "Feature",
  "properties": {
    "iso:country":"FR",
    "sg:address":"3, Rue Nationale, 35000 Rennes",
    "sg:city":"Rennes",
    "sg:orig_category":"Non-Classified Establishments",
    "sg:phone":"+33 2 99 79 12 12",
    "sg:postcode":"35000",
    "sg:province":"Bretagne",
    "wof:name":"Club Med Voyages",
    "wof:placetype":"venue"
},
  "geometry": {"coordinates":[-1.678984,48.11253],"type":"Point"}
}