{
  "type": "Feature",
  "properties": {
    "addr:full":"49, Rte d'Auxerre, 89470 Mon\u00e9teau Mon\u00e9teau Bourgogne 89470",
    "addr:housenumber":"49",
    "addr:postcode":"89470;89470",
    "addr:street":"Rte D'Auxerre",
    "iso:country":"FR",
    "sg:address":"49, Rte d'Auxerre, 89470 Mon\u00e9teau",
    "sg:city":"Mon\u00e9teau",
    "sg:orig_category":"Unclassifiable Establishments",
    "sg:phone":"+33 3 86 53 44 00",
    "sg:postcode":"89470",
    "sg:province":"Bourgogne",
    "wof:name":"S.n.a.b. Jacques Coeur S.a. - Soci\u00e9t\u00e9 Nutrition Animale De Bourgogne",
    "wof:placetype":"venue"
},
  "geometry": {"coordinates":[3.580072,47.844311],"type":"Point"}
}