{
  "type": "Feature",
  "properties": {
    "iso:country":"FR",
    "sg:address":"14 Avenue D Helvetie 25200 Montbeliard",
    "sg:classifiers":[
        {
            "category":"Autos & Motor Vehicles",
            "subcategory":"Automobile Sales",
            "type":"Retail Goods"
        }
    ],
    "sg:phone":"+33 3 81 99 44 27",
    "sg:postcode":"25200",
    "sg:province":"Franche Comt\u00e9",
    "sg:tags":[
        "equipment",
        "motor-cars",
        "transport"
    ],
    "wof:name":"Siedoubs",
    "wof:placetype":"venue"
},
  "geometry": {"coordinates":[6.806542,47.508389],"type":"Point"}
}