{
  "type": "Feature",
  "properties": {
    "iso:country":"FR",
    "sg:address":"Av. Lateco\u00e8re",
    "sg:city":"Cornebarrieu",
    "sg:orig_category":"Unclassifiable Establishments",
    "sg:phone":"+33 5 62 13 73 73",
    "sg:postcode":"31700",
    "sg:province":"Midi Pyr\u00e9n\u00e9es",
    "wof:name":"A.t.e. S.a. - A\u00e9ro Technique Espace",
    "wof:placetype":"venue"
},
  "geometry": {"coordinates":[1.3365,43.646358],"type":"Point"}
}