{
  "type": "Feature",
  "properties": {
    "addr:full":"Les Billets 74340 Samoens Rhone-Alpes 74340",
    "addr:postcode":"74340;74340",
    "addr:street":"Rhone-Alpes",
    "iso:country":"FR",
    "sg:address":"Les Billets 74340 Samoens",
    "sg:classifiers":[
        {
            "category":"Food & Beverages",
            "subcategory":"Dairy",
            "type":"Retail Goods"
        }
    ],
    "sg:phone":"+33 4 50 34 44 01",
    "sg:postcode":"74340",
    "sg:province":"Rhone-Alpes",
    "sg:tags":[
        "product",
        "related"
    ],
    "wof:name":"Slhs",
    "wof:placetype":"venue"
},
  "geometry": {"coordinates":[6.724346,46.082073],"type":"Point"}
}