{
  "type": "Feature",
  "properties": {
    "addr:full":"38, Rue de Bignon - Forum de la Rocade, 35510 Cesson S\u00e9vign\u00e9 Cesson-S\u00e9vign\u00e9 Bretagne 35510",
    "addr:housenumber":"38",
    "addr:postcode":"35510;se\u0301vigne\u0301 cesson-se\u0301vigne\u0301;35510",
    "addr:street":"Rue De Bignon Forum De La Rocade",
    "iso:country":"FR",
    "sg:address":"38, Rue de Bignon - Forum de la Rocade, 35510 Cesson S\u00e9vign\u00e9",
    "sg:city":"Cesson-S\u00e9vign\u00e9",
    "sg:orig_category":"Unclassifiable Establishments",
    "sg:phone":"+33 2 23 30 09 30",
    "sg:postcode":"35510",
    "sg:province":"Bretagne",
    "wof:name":"Cl\u00e9messy S.a.",
    "wof:placetype":"venue"
},
  "geometry": {"coordinates":[-1.604404,48.117016],"type":"Point"}
}