{
  "type": "Feature",
  "properties": {
    "iso:country":"FR",
    "sg:address":"Parc D'Activite 01360 BELIGNEUX",
    "sg:classifiers":[
        {
            "category":"Shopping",
            "subcategory":"Beauty & Cosmetics",
            "type":"Retail Goods"
        }
    ],
    "sg:phone":"+33 4 78 06 59 01",
    "sg:province":"Rhone-Alpes",
    "sg:tags":[
        "permanent"
    ],
    "wof:name":"Sobrecos S.a.",
    "wof:placetype":"venue"
},
  "geometry": {"coordinates":[5.12833,45.867249],"type":"Point"}
}