{
  "type": "Feature",
  "properties": {
    "iso:country":"FR",
    "sg:address":"rue Sigmund Freud 69120 Vaulx en Velin",
    "sg:orig_category":"Gaskets, Washers, Seals",
    "sg:phone":"+33 4 78 80 64 29",
    "sg:postcode":"69120",
    "sg:province":"Rhone-Alpes",
    "wof:name":"Delta Joint Sa",
    "wof:placetype":"venue"
},
  "geometry": {"coordinates":[4.926988,45.773235],"type":"Point"}
}