{
  "type": "Feature",
  "properties": {
    "iso:country":"FR",
    "sg:address":"B.P. 5081, 34033 Montpellier C\u00e9dex 1^^1, Av. Emile Bertin-Sans, 34000 Montpellier",
    "sg:orig_category":"Non-Classified Establishments",
    "sg:phone":"+33 4 67 41 68 68",
    "sg:province":"Languedoc-Roussillon",
    "wof:name":"Neoptec S.a.r.l.",
    "wof:placetype":"venue"
},
  "geometry": {"coordinates":[3.87609,43.610855],"type":"Point"}
}