{
  "type": "Feature",
  "properties": {
    "iso:country":"FR",
    "sg:address":"23, Rue Raspail, 94858 Ivry sur Seine C\u00e9dex",
    "sg:orig_category":"Non-Classified Establishments",
    "sg:phone":"+33 1 45 15 70 00",
    "sg:province":"\u00cele-de-France",
    "wof:name":"Jet Tours S.a.",
    "wof:placetype":"venue"
},
  "geometry": {"coordinates":[2.389991,48.809814],"type":"Point"}
}