{
  "type": "Feature",
  "properties": {
    "addr:full":"9 Chem St-Geni\u00e8s 30700 Uz\u00e8s Languedoc-Roussillon",
    "addr:housenumber":"9",
    "addr:postcode":"30700",
    "addr:street":"Chem St-Genie\u0300S",
    "iso:country":"FR",
    "sg:address":"9 Chem St-Geni\u00e8s 30700 Uz\u00e8s",
    "sg:classifiers":[
        {
            "category":"Professional",
            "subcategory":"Credit Reporting & Collection",
            "type":"Services"
        }
    ],
    "sg:phone":"+33 4 66 22 60 77",
    "sg:province":"Languedoc-Roussillon",
    "sg:tags":[
        "good",
        "publishing",
        "printing",
        "-",
        "finished",
        "paper",
        "cardboard"
    ],
    "wof:name":"Papetterie Du Val D'eure",
    "wof:placetype":"venue"
},
  "geometry": {"coordinates":[4.416311,44.023045],"type":"Point"}
}