{
  "type": "Feature",
  "properties": {
    "iso:country":"FR",
    "sg:address":"1 Voie D'Angleterre 13127 Vitrolles",
    "sg:city":"Anglet",
    "sg:classifiers":[
        {
            "category":"Shopping",
            "subcategory":"Computers & Home Electronics",
            "type":"Retail Goods"
        }
    ],
    "sg:phone":"+33 4 32 41 54 00",
    "sg:postcode":"64600",
    "sg:province":"Aquitaine",
    "sg:tags":[
        "electronic",
        "electrical",
        "equipment"
    ],
    "wof:name":"Siren Distribution Sa",
    "wof:placetype":"venue"
},
  "geometry": {"coordinates":[5.260901,43.426197],"type":"Point"}
}