{
  "type": "Feature",
  "properties": {
    "iso:country":"FR",
    "sg:address":"Za Des Vall\u00e9es 22640 Plen\u00e9e Jugon",
    "sg:city":"Pl\u00e9n\u00e9e-Jugon",
    "sg:classifiers":[
        {
            "category":"Manufacturing",
            "subcategory":"Leather Goods",
            "type":"Manufacturing & Wholesale Goods"
        }
    ],
    "sg:phone":"+33 2 96 51 72 00",
    "sg:postcode":"22640",
    "sg:province":"Bretagne",
    "sg:tags":[
        "shoe"
    ],
    "wof:name":"Top Bagage International",
    "wof:placetype":"venue"
},
  "geometry": {"coordinates":[-78.125183,38.811451],"type":"Point"}
}