{
  "type": "Feature",
  "properties": {
    "addr:full":"11 Rue Poncelet 75017 Paris Ile de France 75017",
    "addr:housenumber":"11",
    "addr:postcode":"75017;75017",
    "addr:street":"Rue Poncelet",
    "iso:country":"FR",
    "sg:address":"11 Rue Poncelet 75017 Paris",
    "sg:classifiers":[
        {
            "category":"Bakery",
            "type":"Food & Drink"
        }
    ],
    "sg:phone":"+33 1 42 27 86 28",
    "sg:postcode":"75017",
    "sg:province":"Ile de France",
    "sg:tags":[
        "cake",
        "product",
        "related",
        "bread"
    ],
    "wof:name":"Le Stubli",
    "wof:placetype":"venue"
},
  "geometry": {"coordinates":[2.296348,48.878975],"type":"Point"}
}