{
  "type": "Feature",
  "properties": {
    "addr:full":"Za Du Pont 81500 Ambres Midi Pyr\u00e9n\u00e9es 81500",
    "addr:postcode":"81500;81500",
    "addr:street":"Za Du Pont",
    "iso:country":"FR",
    "sg:address":"Za Du Pont 81500 Ambres",
    "sg:classifiers":[
        {
            "category":"Manufacturing",
            "subcategory":"Metals",
            "type":"Manufacturing & Wholesale Goods"
        }
    ],
    "sg:phone":"+33 5 63 58 71 12",
    "sg:postcode":"81500",
    "sg:province":"Midi Pyr\u00e9n\u00e9es",
    "sg:tags":[
        "metallurgy",
        "metalworking",
        "processing"
    ],
    "wof:name":"Societe Audoise De Precision (sap)",
    "wof:placetype":"venue"
},
  "geometry": {"coordinates":[1.81358,43.732384],"type":"Point"}
}