{
  "type": "Feature",
  "properties": {
    "addr:full":"Z.A. de la Croix Rouge La Ferri\u00e8re Pays de Loire 85280",
    "addr:postcode":"85280",
    "addr:street":"Z.A. De La Croix Rouge La Ferrie\u0300Re Pays",
    "iso:country":"FR",
    "sg:address":"Z.A. de la Croix Rouge",
    "sg:city":"La Ferri\u00e8re",
    "sg:orig_category":"Unclassifiable Establishments",
    "sg:phone":"+33 2 51 40 61 80",
    "sg:postcode":"85280",
    "sg:province":"Pays de Loire",
    "wof:name":"Vend\u00e9e Sani Therm S.a.",
    "wof:placetype":"venue"
},
  "geometry": {"coordinates":[-1.308186,46.711346],"type":"Point"}
}