{
  "type": "Feature",
  "properties": {
    "addr:full":"6bis, Av Gambetta, 76372 Dieppe C\u00e9dex Rhone-Alpes",
    "addr:postcode":"76372",
    "addr:street":"Av Gambetta",
    "iso:country":"FR",
    "sg:address":"6bis, Av Gambetta, 76372 Dieppe C\u00e9dex",
    "sg:orig_category":"Unclassifiable Establishments",
    "sg:phone":"+33 2 35 84 38 21",
    "sg:province":"Rhone-Alpes",
    "wof:name":"S.e.c.h.n. - Soci\u00e9t\u00e9 D'expertises Comptables De Haute Normandie S.a.",
    "wof:placetype":"venue"
},
  "geometry": {"coordinates":[1.072994,49.922543],"type":"Point"}
}