{
  "type": "Feature",
  "properties": {
    "addr:full":"10, Chemin de Saint Joseph, 06130 Le Plan de Grasse Provence-Alpes-C\u00f4te d'Azur",
    "addr:housenumber":"10",
    "addr:postcode":"06130",
    "addr:street":"Chemin De Saint Joseph;Plan De Grasse",
    "iso:country":"FR",
    "sg:address":"10, Chemin de Saint Joseph, 06130 Le Plan de Grasse",
    "sg:orig_category":"Non-Classified Establishments",
    "sg:phone":"+33 4 93 70 13 02",
    "sg:province":"Provence-Alpes-C\u00f4te d'Azur",
    "wof:name":"La Diffusion Electrique S.a.r.l.",
    "wof:placetype":"venue"
},
  "geometry": {"coordinates":[6.953267,43.651054],"type":"Point"}
}