{
  "type": "Feature",
  "properties": {
    "addr:full":"3 Rue Corneille 75006 Paris Ile de France",
    "addr:housenumber":"3",
    "addr:postcode":"75006",
    "addr:street":"Rue Corneille",
    "iso:country":"FR",
    "sg:address":"3 Rue Corneille 75006 Paris",
    "sg:classifiers":[
        {
            "category":"Professional",
            "subcategory":"Printing & Photocopies",
            "type":"Services"
        }
    ],
    "sg:phone":"+33 1 40 46 70 70",
    "sg:province":"Ile de France",
    "sg:tags":[
        "publishing"
    ],
    "wof:name":"Les Editions De La Table Ronde Sa",
    "wof:placetype":"venue"
},
  "geometry": {"coordinates":[2.33916,48.849541],"type":"Point"}
}