{
  "type": "Feature",
  "properties": {
    "iso:country":"FR",
    "sg:address":"17, Rue Emile Milocheau, 28700 B\u00e9ville le Comte",
    "sg:city":"Ardelu",
    "sg:orig_category":"Unclassifiable Establishments",
    "sg:phone":"+33 2 37 31 73 10",
    "sg:postcode":"28700",
    "sg:province":"Centre",
    "wof:name":"Alimel S.a.",
    "wof:placetype":"venue"
},
  "geometry": {"coordinates":[1.910886,48.354084],"type":"Point"}
}