{
  "type": "Feature",
  "properties": {
    "iso:country":"FR",
    "sg:address":"Zone Industrielle 89110 Aillant sur Tholon",
    "sg:city":"Aillant-sur-Tholon",
    "sg:classifiers":[
        {
            "category":"Wholesale",
            "subcategory":"Medical Equipment & Supplies",
            "type":"Manufacturing & Wholesale Goods"
        }
    ],
    "sg:phone":"+33 3 86 92 39 05",
    "sg:postcode":"89110",
    "sg:province":"Bourgogne",
    "sg:tags":[
        "machine",
        "technology",
        "special"
    ],
    "wof:name":"Agencinox Sa",
    "wof:placetype":"venue"
},
  "geometry": {"coordinates":[3.35024,47.874481],"type":"Point"}
}