{
  "type": "Feature",
  "properties": {
    "iso:country":"FR",
    "sg:address":"Z.I. la Martinerie",
    "sg:city":"Diors",
    "sg:orig_category":"Unclassifiable Establishments",
    "sg:phone":"+33 2 54 22 13 77",
    "sg:postcode":"36130",
    "sg:province":"Centre",
    "wof:name":"O & K Escalators S.a.",
    "wof:placetype":"venue"
},
  "geometry": {"coordinates":[1.70056,46.82576],"type":"Point"}
}