{
  "type": "Feature",
  "properties": {
    "iso:country":"FR",
    "sg:address":"1, Chemin du Gu\u00e9, 41220 Crouy sur Cosson",
    "sg:city":"Crouy-sur-Cosson",
    "sg:orig_category":"Non-Classified Establishments",
    "sg:phone":"+33 2 54 87 51 36",
    "sg:postcode":"41220",
    "sg:province":"Centre",
    "wof:name":"Constructions De Sologne S.a.r.l.",
    "wof:placetype":"venue"
},
  "geometry": {"coordinates":[1.607448,47.649616],"type":"Point"}
}