{
  "type": "Feature",
  "properties": {
    "addr:full":"530, Rte de Flaine, 74300 Araches Rhone-Alpes 74300",
    "addr:housenumber":"530",
    "addr:postcode":"74300;74300",
    "addr:street":"Rte De Flaine;Rhone-Alpes",
    "iso:country":"FR",
    "sg:address":"530, Rte de Flaine, 74300 Araches",
    "sg:orig_category":"Non-Classified Establishments",
    "sg:phone":"+33 4 50 90 02 34",
    "sg:postcode":"74300",
    "sg:province":"Rhone-Alpes",
    "wof:name":"Effrancey S.a.",
    "wof:placetype":"venue"
},
  "geometry": {"coordinates":[6.633185,45.987919],"type":"Point"}
}