{
  "type": "Feature",
  "properties": {
    "iso:country":"FR",
    "sg:address":"Technolac",
    "sg:city":"Le Bourget du Lac",
    "sg:orig_category":"Unclassifiable Establishments",
    "sg:phone":"+33 4 79 25 23 90",
    "sg:postcode":"73370",
    "sg:province":"Rhone-Alpes",
    "wof:name":"Aixia S.a.",
    "wof:placetype":"venue"
},
  "geometry": {"coordinates":[5.866365,45.643967],"type":"Point"}
}