{
  "type": "Feature",
  "properties": {
    "addr:full":"36 Avenue Des Oliviers 83310 GRIMAUD Picardie",
    "addr:housenumber":"36",
    "addr:postcode":"83310",
    "addr:street":"Avenue Des Oliviers",
    "iso:country":"FR",
    "sg:address":"36 Avenue Des Oliviers 83310 GRIMAUD",
    "sg:classifiers":[
        {
            "category":"Wholesale",
            "subcategory":"Wine & Distilled Alcoholic Beverages",
            "type":"Manufacturing & Wholesale Goods"
        }
    ],
    "sg:phone":"+33 4 94 43 20 14",
    "sg:province":"Picardie",
    "sg:tags":[
        "french"
    ],
    "wof:name":"Coop Vinicole",
    "wof:placetype":"venue"
},
  "geometry": {"coordinates":[6.465188,43.207832],"type":"Point"}
}