{
  "type": "Feature",
  "properties": {
    "iso:country":"FR",
    "sg:address":"10, Rue de Cond\u00e9, 69002 Lyon",
    "sg:orig_category":"Unclassifiable Establishments",
    "sg:phone":"+33 4 78 37 84 84",
    "sg:postcode":"69002",
    "sg:province":"Rhone-Alpes",
    "wof:name":"Interface Conseil S.a.r.l.",
    "wof:placetype":"venue"
},
  "geometry": {"coordinates":[4.825839,45.752159],"type":"Point"}
}