{
  "type": "Feature",
  "properties": {
    "addr:full":"1, Rue de l'Atlantique - ZI P\u00f4le Sud, 44115 Basse Goulaine Pays de Loire",
    "addr:housenumber":"1",
    "addr:postcode":"44115;goulaine",
    "addr:street":"Rue De L'Atlantique Zi Po\u0302Le Sud",
    "iso:country":"FR",
    "sg:address":"1, Rue de l'Atlantique - ZI P\u00f4le Sud, 44115 Basse Goulaine",
    "sg:orig_category":"Unclassifiable Establishments",
    "sg:phone":"+33 2 51 71 28 88",
    "sg:province":"Pays de Loire",
    "wof:name":"Gasnier Maroquinerie S.a.",
    "wof:placetype":"venue"
},
  "geometry": {"coordinates":[-1.463597,47.187096],"type":"Point"}
}