{
  "type": "Feature",
  "properties": {
    "addr:full":"B.P. 89, 44708 Orvault C\u00e9dex^^300, Rte de Vannes, 44700 Orvault Pays de Loire",
    "addr:postcode":"44708;44700",
    "addr:street":"B.P. 89;Rte De Vannes",
    "iso:country":"FR",
    "sg:address":"B.P. 89, 44708 Orvault C\u00e9dex^^300, Rte de Vannes, 44700 Orvault",
    "sg:orig_category":"Non-Classified Establishments",
    "sg:phone":"+33 2 40 67 46 00",
    "sg:province":"Pays de Loire",
    "wof:name":"Total Raffinage Distribution S.a.",
    "wof:placetype":"venue"
},
  "geometry": {"coordinates":[-1.623129,47.270981],"type":"Point"}
}