{
  "type": "Feature",
  "properties": {
    "addr:full":"10 Place De L'H\u00f4tel De Ville Annemasse Rhone-Alpes 74100",
    "addr:housenumber":"10",
    "addr:postcode":"74100",
    "addr:street":"Place De L'Ho \u0302Tel De Ville;Rhone-Alpes",
    "iso:country":"FR",
    "sg:address":"10 Place De L'H\u00f4tel De Ville",
    "sg:city":"Annemasse",
    "sg:classifiers":[
        {
            "category":"Banks & Credit Unions",
            "subcategory":"Financial Services",
            "type":"Services"
        }
    ],
    "sg:phone":"+33 4 50 35 57 00",
    "sg:postcode":"74100",
    "sg:province":"Rhone-Alpes",
    "sg:tags":[
        "banking",
        "finance",
        "insurance"
    ],
    "wof:name":"Societe Generale Sa",
    "wof:placetype":"venue"
},
  "geometry": {"coordinates":[6.249175,46.200745],"type":"Point"}
}