{
  "type": "Feature",
  "properties": {
    "iso:country":"FR",
    "sg:address":"B.P. 3",
    "sg:city":"Creysse",
    "sg:orig_category":"Non-Classified Establishments",
    "sg:phone":"+33 5 53 23 21 05",
    "sg:postcode":"24100",
    "sg:province":"Aquitaine",
    "wof:name":"Dumas Bernard S.a.",
    "wof:placetype":"venue"
},
  "geometry": {"coordinates":[0.45362,44.815235],"type":"Point"}
}