{
  "type": "Feature",
  "properties": {
    "addr:full":"B.P. 34, 68170 Rixheim^^18, Rue de Habsheim, 68170 Rixheim Rixheim Alsace 68170",
    "addr:postcode":"68170;68170;68170",
    "addr:street":"B.P. 34;Rue De Habsheim;Rixheim",
    "iso:country":"FR",
    "sg:address":"B.P. 34, 68170 Rixheim^^18, Rue de Habsheim, 68170 Rixheim",
    "sg:city":"Rixheim",
    "sg:orig_category":"Non-Classified Establishments",
    "sg:phone":"+33 3 89 44 76 90",
    "sg:postcode":"68170",
    "sg:province":"Alsace",
    "wof:name":"Etablissements Wybrecht Pierre S.a.r.l.",
    "wof:placetype":"venue"
},
  "geometry": {"coordinates":[7.397395,47.744122],"type":"Point"}
}