{
  "type": "Feature",
  "properties": {
    "iso:country":"FR",
    "sg:address":"12, Rue Pasteur, 92000 Nanterre",
    "sg:orig_category":"Unclassifiable Establishments",
    "sg:phone":"+33 1 47 28 93 52",
    "sg:province":"Ile de France",
    "wof:name":"E.i.m.i. S.a.",
    "wof:placetype":"venue"
},
  "geometry": {"coordinates":[2.219283,48.885204],"type":"Point"}
}