{
  "type": "Feature",
  "properties": {
    "addr:full":"Grande Voie De Vignes 92295 Chatenay Malabry \u00cele-de-France",
    "addr:postcode":"92295",
    "addr:street":"Grande Voie De Vignes;Malabry",
    "iso:country":"FR",
    "sg:address":"Grande Voie De Vignes 92295 Chatenay Malabry",
    "sg:classifiers":[
        {
            "category":"Wholesale",
            "subcategory":"Machinery & Supplies",
            "type":"Manufacturing & Wholesale Goods"
        }
    ],
    "sg:phone":"+33 1 41 13 11 73",
    "sg:province":"\u00cele-de-France",
    "sg:tags":[
        "equipment",
        "optical",
        "precision",
        "instrument"
    ],
    "wof:name":"Centrale Recherche Sa",
    "wof:placetype":"venue"
},
  "geometry": {"coordinates":[2.28914,48.766445],"type":"Point"}
}