{
  "type": "Feature",
  "properties": {
    "addr:full":"61bis ave de la R\u00e9publique; Aurillac; 15001 Aurillac Auvergne 15000",
    "addr:housenumber":"61bis",
    "addr:postcode":"15001;15000",
    "addr:street":"Ave De La Re\u0301Publique",
    "iso:country":"FR",
    "sg:address":"61bis ave de la R\u00e9publique; Aurillac; 15001",
    "sg:city":"Aurillac",
    "sg:classifiers":[
        {
            "category":"Banks & Credit Unions",
            "subcategory":"Bank",
            "type":"Services"
        }
    ],
    "sg:phone":"+33 3371480002",
    "sg:postcode":"15000",
    "sg:province":"Auvergne",
    "wof:name":"Banque De France",
    "wof:placetype":"venue"
},
  "geometry": {"coordinates":[2.438987,44.925209],"type":"Point"}
}