{
  "type": "Feature",
  "properties": {
    "addr:full":"10 Rue Du Pont Rouge 85150 La Mothe Achard Pays de Loire 85150",
    "addr:housenumber":"10",
    "addr:postcode":"85150;achard;85150",
    "addr:street":"Rue Du Pont Rouge",
    "iso:country":"FR",
    "sg:address":"10 Rue Du Pont Rouge 85150 La Mothe Achard",
    "sg:classifiers":[
        {
            "category":"Autos & Motor Vehicles",
            "subcategory":"Boat Sales",
            "type":"Retail Goods"
        }
    ],
    "sg:phone":"+33 2 51 38 61 79",
    "sg:postcode":"85150",
    "sg:province":"Pays de Loire",
    "sg:tags":[
        "equipment",
        "transport"
    ],
    "wof:name":"Svtm Accastillage Violleau Sarl",
    "wof:placetype":"venue"
},
  "geometry": {"coordinates":[-1.657253,46.604542],"type":"Point"}
}