{
  "type": "Feature",
  "properties": {
    "addr:full":"160 bis, Rue de Paris, 92100 Boulogne Billancourt Ile de France",
    "addr:housenumber":"160 bis",
    "addr:postcode":"92100",
    "addr:street":"Rue De Paris",
    "iso:country":"FR",
    "sg:address":"160 bis, Rue de Paris, 92100 Boulogne Billancourt",
    "sg:orig_category":"Unclassifiable Establishments",
    "sg:phone":"+33 1 47 12 90 05",
    "sg:province":"Ile de France",
    "wof:name":"Raps Epices S.a.r.l.",
    "wof:placetype":"venue"
},
  "geometry": {"coordinates":[2.234079,48.841721],"type":"Point"}
}