{
  "type": "Feature",
  "properties": {
    "addr:full":"La Camelle 31350 P\u00e9guilhan Midi Pyr\u00e9n\u00e9es",
    "addr:postcode":"31350",
    "iso:country":"FR",
    "sg:address":"La Camelle 31350 P\u00e9guilhan",
    "sg:classifiers":[
        {
            "category":"Manufacturing",
            "subcategory":"Wood Products",
            "type":"Manufacturing & Wholesale Goods"
        }
    ],
    "sg:phone":"+33 5 61 88 78 51",
    "sg:province":"Midi Pyr\u00e9n\u00e9es",
    "sg:tags":[
        "furniture"
    ],
    "wof:name":"Satob Sa",
    "wof:placetype":"venue"
},
  "geometry": {"coordinates":[0.670775,43.321754],"type":"Point"}
}