{
  "type": "Feature",
  "properties": {
    "addr:full":"11 chemin de Marticot 33610 Cestas Cestas Aquitaine 33610",
    "addr:housenumber":"11",
    "addr:postcode":"33610;33610",
    "addr:street":"Chemin De Marticot",
    "iso:country":"FR",
    "sg:address":"11 chemin de Marticot 33610 Cestas",
    "sg:city":"Cestas",
    "sg:classifiers":[
        {
            "category":"Professional",
            "subcategory":"Business Services",
            "type":"Services"
        }
    ],
    "sg:phone":"+33 5 57 97 72 72",
    "sg:postcode":"33610",
    "sg:province":"Aquitaine",
    "sg:tags":[
        "data"
    ],
    "wof:name":"Com 1 Sa",
    "wof:placetype":"venue"
},
  "geometry": {"coordinates":[-0.685784,44.752537],"type":"Point"}
}