{
  "type": "Feature",
  "properties": {
    "addr:full":"20, Rue Jules Vall\u00e8s - Immeuble le Moulin du Comte, 35000 Rennes Rennes Bretagne 35000",
    "addr:housenumber":"20;immeuble",
    "addr:postcode":"35000;35000",
    "addr:street":"Rue Jules Valle\u0300S",
    "iso:country":"FR",
    "sg:address":"20, Rue Jules Vall\u00e8s - Immeuble le Moulin du Comte, 35000 Rennes",
    "sg:city":"Rennes",
    "sg:orig_category":"Non-Classified Establishments",
    "sg:phone":"+33 2 99 35 08 05",
    "sg:postcode":"35000",
    "sg:province":"Bretagne",
    "wof:name":"Staim Bretagne S.a.",
    "wof:placetype":"venue"
},
  "geometry": {"coordinates":[-1.70616,48.105473],"type":"Point"}
}