{
  "type": "Feature",
  "properties": {
    "addr:full":"Lieu Dit Chardillonnay Za De Maubec 38300 Maubec Rhone-Alpes",
    "addr:postcode":"38300",
    "addr:street":"Lieu Dit Chardillonnay Za De Maubec",
    "iso:country":"FR",
    "sg:address":"Lieu Dit Chardillonnay Za De Maubec 38300 Maubec",
    "sg:classifiers":[
        {
            "category":"Manufacturing",
            "subcategory":"Paper Products",
            "type":"Manufacturing & Wholesale Goods"
        }
    ],
    "sg:phone":"+33 4 74 93 71 55",
    "sg:province":"Rhone-Alpes",
    "sg:tags":[
        "packaging",
        "material",
        "-",
        "cardboard"
    ],
    "wof:name":"Multipapiers Sarl",
    "wof:placetype":"venue"
},
  "geometry": {"coordinates":[5.30075,45.4981],"type":"Point"}
}