{
  "type": "Feature",
  "properties": {
    "addr:full":"54603 Villers l\u00e8s Nancy C\u00e9dex^^6, All\u00e9e Pelletier Doisy - P\u00f4le Techno de Nancy Bradois, 54600 Viller Lorraine",
    "addr:postcode":"54603;54600",
    "addr:street":"Alle\u0301E Pelletier Doisy Po\u0302Le;Bradois",
    "iso:country":"FR",
    "sg:address":"54603 Villers l\u00e8s Nancy C\u00e9dex^^6, All\u00e9e Pelletier Doisy - P\u00f4le Techno de Nancy Bradois, 54600 Viller",
    "sg:orig_category":"Non-Classified Establishments",
    "sg:phone":"+33 3 83 44 81 81",
    "sg:province":"Lorraine",
    "wof:name":"Micro 6 S.a.r.l.",
    "wof:placetype":"venue"
},
  "geometry": {"coordinates":[6.1834,48.689548],"type":"Point"}
}