{
  "type": "Feature",
  "properties": {
    "addr:full":"2 rue des Bordes 91070 Bondoufle Ile de France 91070",
    "addr:housenumber":"2",
    "addr:postcode":"91070;ile;91070",
    "addr:street":"Rue Des Bordes;France",
    "iso:country":"FR",
    "sg:address":"2 rue des Bordes 91070 Bondoufle",
    "sg:classifiers":[
        {
            "category":"Manufacturing",
            "subcategory":"Printing",
            "type":"Manufacturing & Wholesale Goods"
        }
    ],
    "sg:phone":"+33 1 60 86 40 75",
    "sg:postcode":"91070",
    "sg:province":"Ile de France",
    "sg:tags":[
        "house",
        "book"
    ],
    "wof:name":"Codimag Sarl",
    "wof:placetype":"venue"
},
  "geometry": {"coordinates":[2.370441,48.607811],"type":"Point"}
}