{
  "type": "Feature",
  "properties": {
    "iso:country":"FR",
    "sg:address":"B.P. 9, 54650 Saulnes^^Zone Industrielle, 54650 Saulnes",
    "sg:orig_category":"Non-Classified Establishments",
    "sg:phone":"+33 3 82 24 56 46",
    "sg:province":"Lorraine",
    "wof:name":"Socom\u00e9sa S.a.r.l. - Soci\u00e9t\u00e9 De Construction M\u00e9canique Saulnoise",
    "wof:placetype":"venue"
},
  "geometry": {"coordinates":[5.823113,49.531475],"type":"Point"}
}