{
  "type": "Feature",
  "properties": {
    "iso:country":"FR",
    "sg:address":"7, Av. Harrokan, 64990 Saint Pierre d'Irube",
    "sg:city":"Lahonce",
    "sg:orig_category":"Unclassifiable Establishments",
    "sg:phone":"+33 5 59 44 04 34",
    "sg:postcode":"64990",
    "sg:province":"Aquitaine",
    "wof:name":"Alliages Industrie S.a.r.l.",
    "wof:placetype":"venue"
},
  "geometry": {"coordinates":[-1.43804,43.462585],"type":"Point"}
}