{
  "type": "Feature",
  "properties": {
    "addr:full":"ZAC des Baterses - Beynost Miribel Rhone-Alpes 01700",
    "addr:housenumber":"zac",
    "addr:postcode":"01700",
    "addr:street":"Des Baterses",
    "iso:country":"FR",
    "sg:address":"ZAC des Baterses - Beynost",
    "sg:city":"Miribel",
    "sg:orig_category":"Unclassifiable Establishments",
    "sg:phone":"+33 4 78 55 41 25",
    "sg:postcode":"01700",
    "sg:province":"Rhone-Alpes",
    "wof:name":"A.b.m. Industrie S.a. - Acc\u00e8s B\u00e2timents Manutention",
    "wof:placetype":"venue"
},
  "geometry": {"coordinates":[4.953455,45.824306],"type":"Point"}
}