{
  "type": "Feature",
  "properties": {
    "iso:country":"FR",
    "sg:address":"11, Rue du Canougue, 59600 Mairieux",
    "sg:orig_category":"Non-Classified Establishments",
    "sg:phone":"+33 3 27 67 98 20",
    "sg:province":"Nord Pas-de-Calais",
    "wof:name":"Transmatic S.a.r.l.",
    "wof:placetype":"venue"
},
  "geometry": {"coordinates":[3.986997,50.307446],"type":"Point"}
}