{
  "type": "Feature",
  "properties": {
    "addr:full":"Zone de l'Etoile Rethel Champagne 08300",
    "addr:postcode":"08300",
    "addr:street":"De;Champagne",
    "iso:country":"FR",
    "sg:address":"Zone de l'Etoile",
    "sg:city":"Rethel",
    "sg:orig_category":"Unclassifiable Establishments",
    "sg:phone":"+33 3 24 39 53 53",
    "sg:postcode":"08300",
    "sg:province":"Champagne",
    "wof:name":"Simon Transports S.a.",
    "wof:placetype":"venue"
},
  "geometry": {"coordinates":[4.35429,49.490059],"type":"Point"}
}