{
  "type": "Feature",
  "properties": {
    "addr:full":"Chesne Du Vexin BP 616 Pa Des Portes 27106 Val De Reuil Cedex Haute Normandie",
    "addr:housenumber":"616",
    "addr:postcode":"27106;reuil cedex",
    "addr:street":"Pa Des Portes",
    "iso:country":"FR",
    "sg:address":"Chesne Du Vexin BP 616 Pa Des Portes 27106 Val De Reuil Cedex",
    "sg:classifiers":[
        {
            "category":"Shopping",
            "subcategory":"Pharmacy",
            "type":"Retail Goods"
        }
    ],
    "sg:phone":"+33 2 32 09 20 00",
    "sg:province":"Haute Normandie",
    "sg:tags":[
        "chemical",
        "pharmaceutical",
        "chemistry"
    ],
    "wof:name":"Carlo Erba Reactifs",
    "wof:placetype":"venue"
},
  "geometry": {"coordinates":[1.21452,49.271011],"type":"Point"}
}