{
  "type": "Feature",
  "properties": {
    "addr:full":"104 Rue De Miromesnil 75008 Paris Ile de France 75008",
    "addr:housenumber":"104",
    "addr:postcode":"75008;75008",
    "addr:street":"Rue De Miromesnil",
    "iso:country":"FR",
    "sg:address":"104 Rue De Miromesnil 75008 Paris",
    "sg:classifiers":[
        {
            "category":"Professional",
            "subcategory":"Business Services",
            "type":"Services"
        }
    ],
    "sg:phone":"+33 1 53 89 11 00",
    "sg:postcode":"75008",
    "sg:province":"Ile de France",
    "sg:tags":[
        "body",
        "advice"
    ],
    "wof:name":"Chambre De Commerce Franco-americaine",
    "wof:placetype":"venue"
},
  "geometry": {"coordinates":[2.315593,48.880386],"type":"Point"}
}