{
  "type": "Feature",
  "properties": {
    "iso:country":"FR",
    "sg:address":"56, Rue de Billancourt, 92100 Boulogne Billancourt",
    "sg:orig_category":"Non-Classified Establishments",
    "sg:phone":"+33 1 46 04 61 14",
    "sg:province":"Ile de France",
    "wof:name":"Hexalog S.a.",
    "wof:placetype":"venue"
},
  "geometry": {"coordinates":[2.235911,48.838779],"type":"Point"}
}