{
  "type": "Feature",
  "properties": {
    "iso:country":"FR",
    "sg:address":"Lande du Bignon",
    "sg:city":"Erbray",
    "sg:orig_category":"Non-Classified Establishments",
    "sg:phone":"+33 2 40 81 29 36",
    "sg:postcode":"44110",
    "sg:province":"Pays de Loire",
    "wof:name":"Edwimode S.a.",
    "wof:placetype":"venue"
},
  "geometry": {"coordinates":[-1.317649,47.655094],"type":"Point"}
}