{
  "type": "Feature",
  "properties": {
    "addr:full":"Rue L\u00e9on Foucault - ZI Mitry Compans Mitry Mory Ile de France 77290",
    "addr:postcode":"77290",
    "addr:street":"Rue Le\u0301On Foucault Zi Mitry Compans",
    "iso:country":"FR",
    "sg:address":"Rue L\u00e9on Foucault - ZI Mitry Compans",
    "sg:city":"Mitry Mory",
    "sg:orig_category":"Unclassifiable Establishments",
    "sg:phone":"+33 1 64 67 97 78",
    "sg:postcode":"77290",
    "sg:province":"Ile de France",
    "wof:name":"Forveil Transports",
    "wof:placetype":"venue"
},
  "geometry": {"coordinates":[2.619585,48.984165],"type":"Point"}
}