{
  "type": "Feature",
  "properties": {
    "addr:full":"23, Grande Rue, 25420 Voujeaucourt Franche Comt\u00e9",
    "addr:housenumber":"23",
    "addr:postcode":"25420",
    "addr:street":"Grande Rue;Franche Comte\u0301",
    "iso:country":"FR",
    "sg:address":"23, Grande Rue, 25420 Voujeaucourt",
    "sg:orig_category":"Non-Classified Establishments",
    "sg:phone":"+33 3 81 90 29 02",
    "sg:province":"Franche Comt\u00e9",
    "wof:name":"H.p.e. S.a.r.l. - Hydraulique Pneumatique Equipement",
    "wof:placetype":"venue"
},
  "geometry": {"coordinates":[6.767626,47.473343],"type":"Point"}
}