{
  "type": "Feature",
  "properties": {
    "addr:full":"B.P. 109, 59427 Armenti\u00e8res C\u00e9dex^^27, Rue de la Paix, 59280 Armenti\u00e8res Nord Pas-de-Calais",
    "addr:housenumber":"b.p. 109",
    "addr:postcode":"59427;59280",
    "addr:street":"Rue De La Paix",
    "iso:country":"FR",
    "sg:address":"B.P. 109, 59427 Armenti\u00e8res C\u00e9dex^^27, Rue de la Paix, 59280 Armenti\u00e8res",
    "sg:orig_category":"Non-Classified Establishments",
    "sg:phone":"+33 3 20 10 34 53",
    "sg:province":"Nord Pas-de-Calais",
    "wof:name":"T.r.p. Charvet S.a.r.l.",
    "wof:placetype":"venue"
},
  "geometry": {"coordinates":[2.881701,50.686623],"type":"Point"}
}