{
  "type": "Feature",
  "properties": {
    "iso:country":"FR",
    "sg:address":"4, Place Sathonay, 69001 Lyon",
    "sg:orig_category":"Non-Classified Establishments",
    "sg:phone":"+33 4 78 28 24 27",
    "sg:province":"Rhone-Alpes",
    "wof:name":"Iconos S.a.r.l.",
    "wof:placetype":"venue"
},
  "geometry": {"coordinates":[4.829952,45.769257],"type":"Point"}
}