{
  "type": "Feature",
  "properties": {
    "addr:full":"16, Rue Charlemagne, 75004 Paris Ile de France",
    "addr:housenumber":"16",
    "addr:postcode":"75004",
    "addr:street":"Rue Charlemagne",
    "iso:country":"FR",
    "sg:address":"16, Rue Charlemagne, 75004 Paris",
    "sg:orig_category":"Unclassifiable Establishments",
    "sg:phone":"+33 1 42 72 85 96",
    "sg:province":"Ile de France",
    "wof:name":"New York S. A. R. L.",
    "wof:placetype":"venue"
},
  "geometry": {"coordinates":[2.359645,48.854416],"type":"Point"}
}