{
  "type": "Feature",
  "properties": {
    "addr:full":"62/63, Rue Dani\u00e8le Casanova, 93200 Saint Denis Ile de France 93200",
    "addr:housenumber":"62 / 63",
    "addr:postcode":"93200;93200",
    "addr:street":"Rue Danie\u0300Le Casanova",
    "iso:country":"FR",
    "sg:address":"62/63, Rue Dani\u00e8le Casanova, 93200 Saint Denis",
    "sg:orig_category":"Non-Classified Establishments",
    "sg:phone":"+33 1 42 43 35 35",
    "sg:postcode":"93200",
    "sg:province":"Ile de France",
    "wof:name":"Avab Transtehnik France S.a.r.l.",
    "wof:placetype":"venue"
},
  "geometry": {"coordinates":[2.362465,48.928577],"type":"Point"}
}