{
  "type": "Feature",
  "properties": {
    "iso:country":"FR",
    "sg:address":"1 Tuilerie Nord 33210 Maz\u00e8res",
    "sg:city":"Maz\u00e8res",
    "sg:classifiers":[
        {
            "category":"Home & Garden",
            "subcategory":"Furniture",
            "type":"Retail Goods"
        }
    ],
    "sg:phone":"+33 5 56 63 24 38",
    "sg:postcode":"33210",
    "sg:province":"Aquitaine",
    "sg:tags":[
        "wood"
    ],
    "wof:name":"Ferbos",
    "wof:placetype":"venue"
},
  "geometry": {"coordinates":[-0.260022,44.494415],"type":"Point"}
}