{
  "type": "Feature",
  "properties": {
    "addr:full":"61, Rte Jean Briaud - B\u00e2t. A 1, 33700 M\u00e9rignac M\u00e9rignac Aquitaine 33700",
    "addr:housenumber":"61;ba\u0302t a 1",
    "addr:postcode":"33700;33700",
    "addr:street":"Rte Jean Briaud",
    "iso:country":"FR",
    "sg:address":"61, Rte Jean Briaud - B\u00e2t. A 1, 33700 M\u00e9rignac",
    "sg:city":"M\u00e9rignac",
    "sg:orig_category":"Unclassifiable Establishments",
    "sg:phone":"+33 5 57 92 43 00",
    "sg:postcode":"33700",
    "sg:province":"Aquitaine",
    "wof:name":"2 S.i.s. S.a.",
    "wof:placetype":"venue"
},
  "geometry": {"coordinates":[-0.671103,44.825298],"type":"Point"}
}