{
  "type": "Feature",
  "properties": {
    "addr:full":"Pa Fontvieille Lot B3 13190 Allauch Midi Pyr\u00e9n\u00e9es",
    "addr:housenumber":"b3",
    "addr:postcode":"13190",
    "iso:country":"FR",
    "sg:address":"Pa Fontvieille Lot B3 13190 Allauch",
    "sg:classifiers":[
        {
            "category":"Professional",
            "subcategory":"Engineering",
            "type":"Services"
        }
    ],
    "sg:phone":"+33 4 91 68 90 50",
    "sg:province":"Midi Pyr\u00e9n\u00e9es",
    "sg:tags":[
        "machine",
        "-",
        "mechanical"
    ],
    "wof:name":"Gaines Plafond Isolation (gpi)",
    "wof:placetype":"venue"
},
  "geometry": {"coordinates":[5.482075,43.336685],"type":"Point"}
}