{
  "type": "Feature",
  "properties": {
    "iso:country":"FR",
    "sg:address":"9, Rue du Faubourg Poissonni\u00e8re, 75009 Paris",
    "sg:orig_category":"Non-Classified Establishments",
    "sg:phone":"+33 1 48 24 12 12",
    "sg:province":"Ile de France",
    "wof:name":"I.t.g. S.a.r.l. - Innovations Et Techniques Graphiques",
    "wof:placetype":"venue"
},
  "geometry": {"coordinates":[2.347712,48.871498],"type":"Point"}
}