{
  "type": "Feature",
  "properties": {
    "iso:country":"FR",
    "sg:address":"Zi Des Barillettes 73230 St Alban Leysse",
    "sg:classifiers":[
        {
            "category":"Manufacturing",
            "subcategory":"Printing",
            "type":"Manufacturing & Wholesale Goods"
        }
    ],
    "sg:phone":"+33 4 79 85 05 97",
    "sg:province":"Rhone-Alpes",
    "sg:tags":[
        "publishing"
    ],
    "wof:name":"Imprimerie Poncet Sa",
    "wof:placetype":"venue"
},
  "geometry": {"coordinates":[5.958034,45.580639],"type":"Point"}
}