{
  "type": "Feature",
  "properties": {
    "addr:full":"Chemin D\u00e9partemental 6 Cabries Provence-Alpes-C\u00f4te d'Azur 13480",
    "addr:housenumber":"6",
    "addr:postcode":"13480",
    "addr:street":"Chemin De\u0301Partemental",
    "iso:country":"FR",
    "sg:address":"Chemin D\u00e9partemental 6",
    "sg:city":"Cabries",
    "sg:orig_category":"Non-Classified Establishments",
    "sg:phone":"+33 4 42 94 29 19",
    "sg:postcode":"13480",
    "sg:province":"Provence-Alpes-C\u00f4te d'Azur",
    "wof:name":"B.a.r.c.o. S.a.r.l. - Barlatier Camionnage Organisation",
    "wof:placetype":"venue"
},
  "geometry": {"coordinates":[5.379897,43.441792],"type":"Point"}
}