{
  "type": "Feature",
  "properties": {
    "iso:country":"FR",
    "sg:address":"B.P. 75",
    "sg:city":"Saint Malo C\u00e9dex^^La Varde 35400 Saint Malo",
    "sg:orig_category":"Non-Classified Establishments",
    "sg:phone":"+33 2 99 40 23 41",
    "sg:postcode":"35406",
    "sg:province":"Bretagne",
    "wof:name":"Shell Fish Viviers De Saint Malo S.a.",
    "wof:placetype":"venue"
},
  "geometry": {"coordinates":[-2.003669,48.604897],"type":"Point"}
}