{
  "type": "Feature",
  "properties": {
    "iso:country":"FR",
    "sg:address":"route du Marais 74800 Cornier",
    "sg:classifiers":[
        {
            "category":"Manufacturing",
            "subcategory":"Motor Vehicles & Parts",
            "type":"Manufacturing & Wholesale Goods"
        }
    ],
    "sg:phone":"+33 4 50 03 22 15",
    "sg:province":"Rhone-Alpes",
    "sg:tags":[
        "precision",
        "mechanic"
    ],
    "wof:name":"Lejeune S.a.",
    "wof:placetype":"venue"
},
  "geometry": {"coordinates":[6.30743,46.085297],"type":"Point"}
}