{
  "type": "Feature",
  "properties": {
    "addr:full":"51/59, Rue Ledru Rollin, 94200 Ivry sur Seine Ile de France",
    "addr:housenumber":"51 / 59",
    "addr:postcode":"94200",
    "addr:street":"Rue Ledru Rollin",
    "iso:country":"FR",
    "sg:address":"51/59, Rue Ledru Rollin, 94200 Ivry sur Seine",
    "sg:orig_category":"Non-Classified Establishments",
    "sg:phone":"+33 1 49 87 06 00",
    "sg:province":"Ile de France",
    "wof:name":"Sin\u00e9qua S.a.",
    "wof:placetype":"venue"
},
  "geometry": {"coordinates":[2.386509,48.817204],"type":"Point"}
}