{
  "type": "Feature",
  "properties": {
    "iso:country":"FR",
    "sg:address":"7, Rue du Colonel Pierre Avia, 75015 Paris",
    "sg:orig_category":"Unclassifiable Establishments",
    "sg:phone":"+33 1 41 33 96 00",
    "sg:province":"Ile de France",
    "wof:name":"S.a.m.p. S.a.r.l. - Soci\u00e9t\u00e9 Des Ateliers M\u00e9caniques Du Pont Sur Sambre",
    "wof:placetype":"venue"
},
  "geometry": {"coordinates":[2.299265,48.841057],"type":"Point"}
}