{
  "type": "Feature",
  "properties": {
    "iso:country":"FR",
    "sg:address":"2 Rue Virginie Mauvais BP 3388 54015 Nancy Cedex",
    "sg:classifiers":[
        {
            "category":"Professional",
            "type":"Services"
        }
    ],
    "sg:phone":"+33 3 83 39 89 89",
    "sg:province":"Lorraine",
    "sg:tags":[
        "transport",
        "road"
    ],
    "wof:name":"Screg Est",
    "wof:placetype":"venue"
},
  "geometry": {"coordinates":[6.18163,48.703632],"type":"Point"}
}