{
  "type": "Feature",
  "properties": {
    "addr:full":"12, Bd Antoine Gautier, 33000 Bordeaux Bordeaux Aquitaine 33000",
    "addr:housenumber":"12",
    "addr:postcode":"33000;33000",
    "addr:street":"Bd Antoine Gautier",
    "iso:country":"FR",
    "sg:address":"12, Bd Antoine Gautier, 33000 Bordeaux",
    "sg:city":"Bordeaux",
    "sg:orig_category":"Unclassifiable Establishments",
    "sg:phone":"+33 5 57 01 57 01",
    "sg:postcode":"33000",
    "sg:province":"Aquitaine",
    "wof:name":"Cagir",
    "wof:placetype":"venue"
},
  "geometry": {"coordinates":[-0.599001,44.83593],"type":"Point"}
}