{
  "type": "Feature",
  "properties": {
    "addr:full":"1 Rue Des Moines Z I 77140 Nemours Ile de France 77140",
    "addr:housenumber":"1",
    "addr:postcode":"77140;77140",
    "addr:street":"Rue Des Moines Z;Ile De France",
    "iso:country":"FR",
    "sg:address":"1 Rue Des Moines Z I 77140 Nemours",
    "sg:classifiers":[
        {
            "category":"Wholesale",
            "subcategory":"Medical Equipment & Supplies",
            "type":"Manufacturing & Wholesale Goods"
        }
    ],
    "sg:phone":"+33 1 64 29 28 29",
    "sg:postcode":"77140",
    "sg:province":"Ile de France",
    "sg:tags":[
        "instrument",
        "health",
        "-",
        "precision"
    ],
    "wof:name":"Societe D'exploitation Des Etablissements Raymond Ferlain",
    "wof:placetype":"venue"
},
  "geometry": {"coordinates":[2.69474,48.2672],"type":"Point"}
}