{
  "type": "Feature",
  "properties": {
    "iso:country":"FR",
    "sg:address":"1, Rue Colombia - Parc d'Esther, 87000 Limoges",
    "sg:orig_category":"Unclassifiable Establishments",
    "sg:phone":"+33 5 55 35 06 40",
    "sg:province":"Limousin",
    "wof:name":"M.i.l. S.a. - Mat\u00e9riel Et Implants Du Limousin",
    "wof:placetype":"venue"
},
  "geometry": {"coordinates":[1.273448,45.820042],"type":"Point"}
}