{
  "type": "Feature",
  "properties": {
    "iso:country":"FR",
    "sg:address":"35, Av. Delattre de Tassigny, 93806 Epinay sur Seine C\u00e9dex",
    "sg:orig_category":"Non-Classified Establishments",
    "sg:phone":"+33 1 49 71 54 11",
    "sg:province":"\u00cele-de-France",
    "wof:name":"Interm\u00e9taux S.a.",
    "wof:placetype":"venue"
},
  "geometry": {"coordinates":[2.310093,48.956867],"type":"Point"}
}