{
  "type": "Feature",
  "properties": {
    "iso:country":"FR",
    "sg:address":"6 Rue Freyssinet 22360 Langueux",
    "sg:city":"Langueux",
    "sg:classifiers":[
        {
            "category":"Shopping",
            "subcategory":"Bicycles & Sporting Goods",
            "type":"Retail Goods"
        }
    ],
    "sg:phone":"+33 2 96 61 98 62",
    "sg:postcode":"22360",
    "sg:province":"Bretagne",
    "sg:tags":[
        "product",
        "sport",
        "miscellaneous"
    ],
    "wof:name":"Elies Sport",
    "wof:placetype":"venue"
},
  "geometry": {"coordinates":[-2.72765,48.497711],"type":"Point"}
}