{
  "type": "Feature",
  "properties": {
    "addr:full":"10, Av. du Preconil - Immeuble Saint Christophe, 83120 Sainte Maxime Haute Normandie",
    "addr:postcode":"83120",
    "addr:street":"10 Av. Du Preconil;Haute Normandie",
    "iso:country":"FR",
    "sg:address":"10, Av. du Preconil - Immeuble Saint Christophe, 83120 Sainte Maxime",
    "sg:orig_category":"Unclassifiable Establishments",
    "sg:phone":"+33 4 94 56 61 61",
    "sg:province":"Haute Normandie",
    "wof:name":"Sogex Dayan S.a.",
    "wof:placetype":"venue"
},
  "geometry": {"coordinates":[6.635615,43.309326],"type":"Point"}
}