{
  "type": "Feature",
  "properties": {
    "addr:full":"32, Rue du Bois Chaland, 91090 Lisses Ile de France",
    "addr:housenumber":"32",
    "addr:postcode":"91090;ile",
    "addr:street":"Rue Du Bois Chaland",
    "iso:country":"FR",
    "sg:address":"32, Rue du Bois Chaland, 91090 Lisses",
    "sg:orig_category":"Unclassifiable Establishments",
    "sg:phone":"+33 1 69 11 16 60",
    "sg:province":"Ile de France",
    "wof:name":"Aures Technologie S.a.",
    "wof:placetype":"venue"
},
  "geometry": {"coordinates":[2.436438,48.600742],"type":"Point"}
}