{
  "type": "Feature",
  "properties": {
    "iso:country":"FR",
    "sg:address":"2 rue de l'Industrie 80300 Albert",
    "sg:classifiers":[
        {
            "category":"Utilities",
            "subcategory":"Natural Gas",
            "type":"Services"
        }
    ],
    "sg:phone":"+33 3 22 74 31 00",
    "sg:postcode":"80300",
    "sg:province":"Picardie",
    "sg:tags":[
        "cylinder",
        "hydraulic"
    ],
    "wof:name":"Douce Hydro Sa",
    "wof:placetype":"venue"
},
  "geometry": {"coordinates":[2.636388,50.001858],"type":"Point"}
}