{
  "type": "Feature",
  "properties": {
    "iso:country":"FR",
    "sg:address":"2 Chemin Des Vignes Zi Des Grandes Vignes 74330 La Balme De Sillingy",
    "sg:classifiers":[
        {
            "category":"Professional",
            "subcategory":"Engineering",
            "type":"Services"
        }
    ],
    "sg:phone":"+33 4 50 68 70 06",
    "sg:postcode":"74330",
    "sg:province":"Rhone-Alpes",
    "sg:tags":[
        "machine",
        "-",
        "mechanical"
    ],
    "wof:name":"Lamberet Rene Curioz",
    "wof:placetype":"venue"
},
  "geometry": {"coordinates":[6.041031,45.898506],"type":"Point"}
}