{
  "type": "Feature",
  "properties": {
    "addr:full":"13 Rue Ormeaux 85500 Les Herbiers Pays de Loire 85500",
    "addr:housenumber":"13",
    "addr:postcode":"85500;85500",
    "addr:street":"Rue Ormeaux;Herbiers",
    "iso:country":"FR",
    "sg:address":"13 Rue Ormeaux 85500 Les Herbiers",
    "sg:classifiers":[
        {
            "category":"Professional",
            "subcategory":"Engineering",
            "type":"Services"
        }
    ],
    "sg:phone":"+33 2 51 64 85 91",
    "sg:postcode":"85500",
    "sg:province":"Pays de Loire",
    "sg:tags":[
        "leather",
        "material",
        "-",
        "machine",
        "raw",
        "mechanical"
    ],
    "wof:name":"Daviaud Jean Pierre",
    "wof:placetype":"venue"
},
  "geometry": {"coordinates":[-1.011275,46.886101],"type":"Point"}
}