{
  "type": "Feature",
  "properties": {
    "addr:full":"14 Rue Louis Bl\u00e9riot 86100 Ch\u00e2tellerault Poitou-Charentes 86100",
    "addr:housenumber":"14",
    "addr:postcode":"86100;86100",
    "addr:street":"Rue Louis Ble\u0301Riot",
    "iso:country":"FR",
    "sg:address":"14 Rue Louis Bl\u00e9riot 86100 Ch\u00e2tellerault",
    "sg:classifiers":[
        {
            "category":"Manufacturing",
            "subcategory":"Chemicals & Compounds",
            "type":"Manufacturing & Wholesale Goods"
        }
    ],
    "sg:phone":"+33 5 49 21 21 54",
    "sg:postcode":"86100",
    "sg:province":"Poitou-Charentes",
    "sg:tags":[
        "pharmaceutical",
        "chemistry"
    ],
    "wof:name":"Alu Durmax",
    "wof:placetype":"venue"
},
  "geometry": {"coordinates":[0.544481,46.84549],"type":"Point"}
}