{
  "type": "Feature",
  "properties": {
    "iso:country":"FR",
    "sg:address":"Chem Des Meuniers 91320 Wissous",
    "sg:classifiers":[
        {
            "category":"Professional",
            "subcategory":"Printing & Photocopies",
            "type":"Services"
        }
    ],
    "sg:phone":"+33 1 69 81 28 00",
    "sg:province":"Ile de France",
    "sg:tags":[
        "paper",
        "raw",
        "material",
        "-",
        "cardboard"
    ],
    "wof:name":"De Ruysscher Papyrus Sa",
    "wof:placetype":"venue"
},
  "geometry": {"coordinates":[2.32856,48.737095],"type":"Point"}
}