{
  "type": "Feature",
  "properties": {
    "addr:full":"Jouvernex 74200 Margencel Rhone-Alpes 74200",
    "addr:postcode":"74200;74200",
    "addr:street":"Jouvernex;Rhone-Alpes",
    "iso:country":"FR",
    "sg:address":"Jouvernex 74200 Margencel",
    "sg:classifiers":[
        {
            "category":"Wholesale",
            "subcategory":"Medical Equipment & Supplies",
            "type":"Manufacturing & Wholesale Goods"
        }
    ],
    "sg:phone":"+33 4 50 72 70 80",
    "sg:postcode":"74200",
    "sg:province":"Rhone-Alpes",
    "sg:tags":[
        "-",
        "health",
        "instrument"
    ],
    "wof:name":"Thiebaud Freres Sa",
    "wof:placetype":"venue"
},
  "geometry": {"coordinates":[6.43229,46.334965],"type":"Point"}
}