{
  "type": "Feature",
  "properties": {
    "addr:full":"Rue de la Prairie - Villebon sur Yvette Palaiseau C\u00e9dex Alsace 91163",
    "addr:postcode":"91163",
    "addr:street":"Rue De La Prairie;Ce\u0301Dex",
    "iso:country":"FR",
    "sg:address":"Rue de la Prairie - Villebon sur Yvette",
    "sg:city":"Palaiseau C\u00e9dex",
    "sg:orig_category":"Non-Classified Establishments",
    "sg:phone":"+33 1 69 10 47 00",
    "sg:postcode":"91163",
    "sg:province":"Alsace",
    "wof:name":"Rowecom France S.a.",
    "wof:placetype":"venue"
},
  "geometry": {"coordinates":[2.24629,48.713032],"type":"Point"}
}