{
  "type": "Feature",
  "properties": {
    "addr:full":"2, Rue Jean Baptiste Say, 87000 Limoges Limousin",
    "addr:housenumber":"2",
    "addr:postcode":"87000",
    "addr:street":"Rue Jean Baptiste Say",
    "iso:country":"FR",
    "sg:address":"2, Rue Jean Baptiste Say, 87000 Limoges",
    "sg:orig_category":"Non-Classified Establishments",
    "sg:phone":"+33 5 55 30 34 98",
    "sg:province":"Limousin",
    "wof:name":"Soci\u00e9t\u00e9 Nouvelle Tout Pour Le Froid S.a.",
    "wof:placetype":"venue"
},
  "geometry": {"coordinates":[1.267239,45.810276],"type":"Point"}
}