{
  "type": "Feature",
  "properties": {
    "addr:full":"69220 Charentay Rhone-Alpes 69220",
    "addr:postcode":"69220;69220",
    "addr:street":"Rhone-Alpes",
    "iso:country":"FR",
    "sg:address":"69220 Charentay",
    "sg:classifiers":[
        {
            "category":"Professional",
            "subcategory":"Engineering",
            "type":"Services"
        }
    ],
    "sg:phone":"+33 4 74 66 81 64",
    "sg:postcode":"69220",
    "sg:province":"Rhone-Alpes",
    "sg:tags":[
        "machine",
        "-",
        "mechanical"
    ],
    "wof:name":"Societe Nouvelle D'embouteillage Et De Filtration (sonef)",
    "wof:placetype":"venue"
},
  "geometry": {"coordinates":[4.678782,46.0886],"type":"Point"}
}