{
  "type": "Feature",
  "properties": {
    "addr:full":"Rue Pierre Et Marie Curie 28310 JANVILLE Janville Centre 28310",
    "addr:postcode":"28310;28310",
    "addr:street":"Rue Pierre Et Marie Curie",
    "iso:country":"FR",
    "sg:address":"Rue Pierre Et Marie Curie 28310 JANVILLE",
    "sg:city":"Janville",
    "sg:classifiers":[
        {
            "category":"Military Area",
            "subcategory":"Air Force Base",
            "type":"Public Place"
        }
    ],
    "sg:phone":"+33 2 37 90 23 00",
    "sg:postcode":"28310",
    "sg:province":"Centre",
    "sg:tags":[
        "masonry",
        "reinforcement"
    ],
    "wof:name":"Asc Sas",
    "wof:placetype":"venue"
},
  "geometry": {"coordinates":[1.875264,48.204662],"type":"Point"}
}