{
  "type": "Feature",
  "properties": {
    "addr:full":"1, All\u00e9e du Midi, 54270 Essey l\u00e8s Nancy Lorraine",
    "addr:housenumber":"1",
    "addr:postcode":"54270",
    "addr:street":"Alle\u0301E Du Midi",
    "iso:country":"FR",
    "sg:address":"1, All\u00e9e du Midi, 54270 Essey l\u00e8s Nancy",
    "sg:orig_category":"Unclassifiable Establishments",
    "sg:phone":"+33 3 83 21 42 42",
    "sg:province":"Lorraine",
    "wof:name":"Krier S.a.",
    "wof:placetype":"venue"
},
  "geometry": {"coordinates":[6.248097,48.706329],"type":"Point"}
}