{
  "type": "Feature",
  "properties": {
    "addr:full":"19, Rue Charles Tellier, 13014 Marseille Poitou-Charentes",
    "addr:housenumber":"19",
    "addr:postcode":"13014",
    "addr:street":"Rue Charles Tellier",
    "iso:country":"FR",
    "sg:address":"19, Rue Charles Tellier, 13014 Marseille",
    "sg:orig_category":"Non-Classified Establishments",
    "sg:phone":"+33 4 91 02 16 72",
    "sg:province":"Poitou-Charentes",
    "wof:name":"Onyx M\u00e9diterran\u00e9e S.a.",
    "wof:placetype":"venue"
},
  "geometry": {"coordinates":[5.370781,43.336563],"type":"Point"}
}