{
  "type": "Feature",
  "properties": {
    "iso:country":"FR",
    "sg:address":"Rue au Ch\u00eane - Z.I. au Bois",
    "sg:city":"Franois",
    "sg:orig_category":"Unclassifiable Establishments",
    "sg:phone":"+33 3 81 59 92 90",
    "sg:postcode":"25770",
    "sg:province":"Franche Comt\u00e9",
    "wof:name":"Ermap Vibrations S.a.",
    "wof:placetype":"venue"
},
  "geometry": {"coordinates":[5.93433,47.228195],"type":"Point"}
}