{
  "type": "Feature",
  "properties": {
    "addr:full":"Rue De Pr\u00e9 Comtal 63100 Clermont Ferrand Clermont-Ferrand Auvergne 63100",
    "addr:postcode":"63100;63100",
    "addr:street":"Rue De Pre\u0301 Comtal",
    "iso:country":"FR",
    "sg:address":"Rue De Pr\u00e9 Comtal 63100 Clermont Ferrand",
    "sg:city":"Clermont-Ferrand",
    "sg:classifiers":[
        {
            "category":"Food & Beverages",
            "subcategory":"Groceries & Convenience Stores",
            "type":"Retail Goods"
        }
    ],
    "sg:phone":"+33 4 73 23 49 79",
    "sg:postcode":"63100",
    "sg:province":"Auvergne",
    "sg:tags":[
        "product",
        "related"
    ],
    "wof:name":"Promocash",
    "wof:placetype":"venue"
},
  "geometry": {"coordinates":[3.131298,45.802559],"type":"Point"}
}