{
  "type": "Feature",
  "properties": {
    "iso:country":"FR",
    "sg:address":"Route Tilloy",
    "sg:city":"Beaurains",
    "sg:orig_category":"Non-Classified Establishments",
    "sg:phone":"+33 3 21 60 41 60",
    "sg:postcode":"62217",
    "sg:province":"Nord Pas-de-Calais",
    "wof:name":"Sigmatec, S.a.r.l.",
    "wof:placetype":"venue"
},
  "geometry": {"coordinates":[2.792657,50.265518],"type":"Point"}
}