{
  "type": "Feature",
  "properties": {
    "iso:country":"FR",
    "sg:address":"65 Rue Gambetta 64500 St Jean De Luz",
    "sg:city":"Ciboure",
    "sg:classifiers":[
        {
            "category":"Shopping",
            "subcategory":"Clothing, Apparel, & Fashions",
            "type":"Retail Goods"
        }
    ],
    "sg:phone":"+33 5 59 26 86 70",
    "sg:postcode":"64500",
    "sg:province":"Aquitaine",
    "sg:tags":[
        "textile",
        "clothing",
        "clothes"
    ],
    "wof:name":"Pp And Mick Sarl",
    "wof:placetype":"venue"
},
  "geometry": {"coordinates":[-1.659708,43.389572],"type":"Point"}
}