{
  "type": "Feature",
  "properties": {
    "addr:full":"Le Peyron quart Pr\u00e9s; S. Jeannet Aquitaine",
    "addr:street":"Quart Pre\u0301S S. Jeannet",
    "iso:country":"FR",
    "sg:address":"Le Peyron quart Pr\u00e9s; S. Jeannet",
    "sg:classifiers":[
        {
            "category":"Banks & Credit Unions",
            "subcategory":"Bank",
            "type":"Services"
        }
    ],
    "sg:phone":"+33 3393248855",
    "sg:province":"Aquitaine",
    "wof:name":"Cr\u00e9dit Agricole Des Alpes Maritimes",
    "wof:placetype":"venue"
},
  "geometry": {"coordinates":[4.49661,44.97517],"type":"Point"}
}