{
  "type": "Feature",
  "properties": {
    "addr:full":"137, Av. de Jalday - ZI de Jalday, 64500 Saint Jean de Luz Ciboure Aquitaine 64500",
    "addr:postcode":"64500;64500",
    "addr:street":"137 Av. De Jalday Zi De Jalday",
    "iso:country":"FR",
    "sg:address":"137, Av. de Jalday - ZI de Jalday, 64500 Saint Jean de Luz",
    "sg:city":"Ciboure",
    "sg:orig_category":"Unclassifiable Establishments",
    "sg:phone":"+33 5 59 08 00 10",
    "sg:postcode":"64500",
    "sg:province":"Aquitaine",
    "wof:name":"Cervac Midi Atlantique S.a.r.l.",
    "wof:placetype":"venue"
},
  "geometry": {"coordinates":[-1.660884,43.38773],"type":"Point"}
}