{
  "type": "Feature",
  "properties": {
    "iso:country":"FR",
    "sg:address":"40 rue Boucher de Perthes 59100 Roubaix",
    "sg:classifiers":[
        {
            "category":"Retail",
            "subcategory":"Repair Shop",
            "type":"Services"
        }
    ],
    "sg:phone":"+33 3 20 25 71 00",
    "sg:province":"Nord Pas-de-Calais",
    "sg:tags":[
        "press",
        "ironing",
        "workshop",
        "laundry"
    ],
    "wof:name":"Lemaire Et Cie Sa",
    "wof:placetype":"venue"
},
  "geometry": {"coordinates":[3.155043,50.693157],"type":"Point"}
}