{
  "type": "Feature",
  "properties": {
    "iso:country":"FR",
    "sg:address":"6, Cit\u00e9 Paradis, 75010 Paris",
    "sg:orig_category":"Non-Classified Establishments",
    "sg:phone":"+33 1 53 24 24 00",
    "sg:province":"Ile de France",
    "wof:name":"Varenne Entreprises S.a.r.l.",
    "wof:placetype":"venue"
},
  "geometry": {"coordinates":[2.350062,48.875057],"type":"Point"}
}