{
  "type": "Feature",
  "properties": {
    "addr:full":"48/50, Av. Georges Cl\u00e9menceau, 77400 Lagny sur Marne Ile de France",
    "addr:housenumber":"48 / 50",
    "addr:postcode":"77400",
    "addr:street":"Av. Georges Cle\u0301Menceau",
    "iso:country":"FR",
    "sg:address":"48/50, Av. Georges Cl\u00e9menceau, 77400 Lagny sur Marne",
    "sg:orig_category":"Unclassifiable Establishments",
    "sg:phone":"+33 1 60 07 28 23",
    "sg:province":"Ile de France",
    "wof:name":"T.l.m. Services Bobcat S.a.",
    "wof:placetype":"venue"
},
  "geometry": {"coordinates":[2.725013,48.877403],"type":"Point"}
}