{
  "type": "Feature",
  "properties": {
    "iso:country":"FR",
    "sg:address":"27 R Maurice Gunsbourg 94200 Ivry Sur Seine",
    "sg:classifiers":[
        {
            "category":"Home & Garden",
            "subcategory":"Furniture",
            "type":"Retail Goods"
        }
    ],
    "sg:phone":"+33 1 49 59 02 90",
    "sg:postcode":"94200",
    "sg:province":"Ile de France",
    "sg:tags":[
        "household",
        "wood"
    ],
    "wof:name":"Etablissements Sayag",
    "wof:placetype":"venue"
},
  "geometry": {"coordinates":[2.405927,48.812763],"type":"Point"}
}