{
  "type": "Feature",
  "properties": {
    "addr:full":"85 Cours De Verdun Le Moliere 01100 Oyonnax Rhone-Alpes 01100",
    "addr:housenumber":"85",
    "addr:postcode":"01100;01100",
    "addr:street":"Cours De Verdun Le Moliere",
    "iso:country":"FR",
    "sg:address":"85 Cours De Verdun Le Moliere 01100 Oyonnax",
    "sg:classifiers":[
        {
            "category":"Manufacturing",
            "subcategory":"Rubber & Plastics",
            "type":"Manufacturing & Wholesale Goods"
        }
    ],
    "sg:phone":"+33 4 74 81 28 60",
    "sg:postcode":"01100",
    "sg:province":"Rhone-Alpes",
    "sg:tags":[
        "metallurgy",
        "finished",
        "-",
        "metalworking",
        "metallic"
    ],
    "wof:name":"Constructeurs Moulistes Oyonnaxiens (cmo)",
    "wof:placetype":"venue"
},
  "geometry": {"coordinates":[5.64399,46.24971],"type":"Point"}
}