{
  "type": "Feature",
  "properties": {
    "addr:full":"4, Rue de Lombardie - ZI les Pivolles, 69150 D\u00e9cines Charpieu Rhone-Alpes",
    "addr:housenumber":"4",
    "addr:postcode":"69150",
    "addr:street":"Rue De Lombardie Zi Les Pivolles",
    "iso:country":"FR",
    "sg:address":"4, Rue de Lombardie - ZI les Pivolles, 69150 D\u00e9cines Charpieu",
    "sg:orig_category":"Non-Classified Establishments",
    "sg:phone":"+33 4 72 14 51 51",
    "sg:province":"Rhone-Alpes",
    "wof:name":"I.t.e.c. S.a. - Installations Thermiques Et Canalisations",
    "wof:placetype":"venue"
},
  "geometry": {"coordinates":[4.95911,45.770794],"type":"Point"}
}