{
  "type": "Feature",
  "properties": {
    "addr:full":"B.P. 10 Maillezais^^La Garenne 85420 Maillezais Pays de Loire 85240",
    "addr:postcode":"85420;85240",
    "addr:street":"B.P. 10 Maillezais^^La Garenne",
    "iso:country":"FR",
    "sg:address":"B.P. 10",
    "sg:city":"Maillezais^^La Garenne 85420 Maillezais",
    "sg:orig_category":"Non-Classified Establishments",
    "sg:phone":"+33 2 51 00 79 10",
    "sg:postcode":"85240",
    "sg:province":"Pays de Loire",
    "wof:name":"Bobelec S.a.r.l.",
    "wof:placetype":"venue"
},
  "geometry": {"coordinates":[-0.719817,46.307911],"type":"Point"}
}