{
  "type": "Feature",
  "properties": {
    "iso:country":"FR",
    "sg:address":"Av. Lascos - ZI Martigues Sud",
    "sg:city":"Martigues",
    "sg:orig_category":"Unclassifiable Establishments",
    "sg:phone":"+33 4 42 81 81 13",
    "sg:postcode":"13500",
    "sg:province":"Midi Pyr\u00e9n\u00e9es",
    "wof:name":"Etablissements Caprioni Et Brachet S.a.r.l.",
    "wof:placetype":"venue"
},
  "geometry": {"coordinates":[5.055235,43.406536],"type":"Point"}
}