{
  "type": "Feature",
  "properties": {
    "addr:full":"B.P. 464, 59338 Tourcoing C\u00e9dex^^200, Chauss\u00e9e Fernand Forest, 59200 Tourcoing Nord Pas-de-Calais",
    "addr:housenumber":"b.p. 464",
    "addr:postcode":"59338;59200",
    "addr:street":"Chausse\u0301E Fernand Forest",
    "iso:country":"FR",
    "sg:address":"B.P. 464, 59338 Tourcoing C\u00e9dex^^200, Chauss\u00e9e Fernand Forest, 59200 Tourcoing",
    "sg:orig_category":"Non-Classified Establishments",
    "sg:phone":"+33 3 20 11 84 00",
    "sg:province":"Nord Pas-de-Calais",
    "wof:name":"Maco Pharma S.a.",
    "wof:placetype":"venue"
},
  "geometry": {"coordinates":[3.159375,50.722389],"type":"Point"}
}