{
  "type": "Feature",
  "properties": {
    "iso:country":"FR",
    "sg:address":"15 rue du Mar\u00e9chal Juin; Lannemezan",
    "sg:classifiers":[
        {
            "category":"Banks & Credit Unions",
            "subcategory":"Bank",
            "type":"Services"
        }
    ],
    "sg:phone":"+33 5 62 98 03 81",
    "sg:province":"Midi Pyr\u00e9n\u00e9es",
    "wof:name":"Soci\u00e9t\u00e9 Bordelaise, De Cic Sa",
    "wof:placetype":"venue"
},
  "geometry": {"coordinates":[0.384849,43.123127],"type":"Point"}
}