{
  "type": "Feature",
  "properties": {
    "addr:full":"4, Rue des Ferblantiers - Metz Actipole, 57070 Metz Lorraine",
    "addr:housenumber":"4",
    "addr:postcode":"57070",
    "addr:street":"Rue Des Ferblantiers;Actipole",
    "iso:country":"FR",
    "sg:address":"4, Rue des Ferblantiers - Metz Actipole, 57070 Metz",
    "sg:orig_category":"Unclassifiable Establishments",
    "sg:phone":"+33 3 87 75 02 20",
    "sg:province":"Lorraine",
    "wof:name":"Ns 2 S.a. - Nord S\u00e9curit\u00e9 Services",
    "wof:placetype":"venue"
},
  "geometry": {"coordinates":[6.251153,49.114746],"type":"Point"}
}