{
  "type": "Feature",
  "properties": {
    "addr:full":"Av De La Lib\u00e9ration BP 80 62702 Bruay La Buissi\u00e8re Cedex Nord-Pas-de-Calais",
    "addr:housenumber":"80",
    "addr:postcode":"62702;buissie\u0300re cedex",
    "addr:street":"Av De La Libe\u0301Ration Bp",
    "iso:country":"FR",
    "sg:address":"Av De La Lib\u00e9ration BP 80 62702 Bruay La Buissi\u00e8re Cedex",
    "sg:classifiers":[
        {
            "category":"Banks & Credit Unions",
            "subcategory":"Investment Brokerage",
            "type":"Services"
        }
    ],
    "sg:phone":"+33 3 21 61 65 00",
    "sg:province":"Nord-Pas-de-Calais",
    "sg:tags":[
        "-",
        "transport",
        "related"
    ],
    "wof:name":"Base De Labuissere Sa",
    "wof:placetype":"venue"
},
  "geometry": {"coordinates":[2.567905,50.492165],"type":"Point"}
}