{
  "type": "Feature",
  "properties": {
    "iso:country":"FR",
    "sg:address":"5 Rue James Watt 93600 Aulnay Sous Bois",
    "sg:classifiers":[
        {
            "category":"Manufacturing",
            "subcategory":"Printing",
            "type":"Manufacturing & Wholesale Goods"
        }
    ],
    "sg:phone":"+33 1 48 66 46 46",
    "sg:province":"Ile de France",
    "sg:tags":[
        "publishing"
    ],
    "wof:name":"Irba Imprimerie Sa",
    "wof:placetype":"venue"
},
  "geometry": {"coordinates":[2.510785,48.930344],"type":"Point"}
}