{
  "type": "Feature",
  "properties": {
    "addr:full":"4, Rue du Cercle - B\u00e2t. 3310, 95700 Roissy en France Ile de France",
    "addr:housenumber":"4;ba\u0302t",
    "addr:postcode":"95700",
    "addr:street":"Rue Du Cercle",
    "iso:country":"FR",
    "sg:address":"4, Rue du Cercle - B\u00e2t. 3310, 95700 Roissy en France",
    "sg:orig_category":"Unclassifiable Establishments",
    "sg:phone":"+33 1 49 19 52 00",
    "sg:province":"Ile de France",
    "wof:name":"B.b.a. S.a. - Business By Air",
    "wof:placetype":"venue"
},
  "geometry": {"coordinates":[2.522079,48.994728],"type":"Point"}
}