{
  "type": "Feature",
  "properties": {
    "iso:country":"FR",
    "sg:address":"1, Bd Ney, 75018 Paris",
    "sg:orig_category":"Non-Classified Establishments",
    "sg:phone":"+33 1 40 38 65 40",
    "sg:province":"Ile de France",
    "wof:name":"Stedi S.a.",
    "wof:placetype":"venue"
},
  "geometry": {"coordinates":[2.369058,48.898365],"type":"Point"}
}