{
  "type": "Feature",
  "properties": {
    "addr:full":"230 R De L' Aven Zae Des Verriettes 34980 St G\u00e9ly Du Fesc Languedoc-Roussillon",
    "addr:housenumber":"230",
    "addr:postcode":"34980",
    "addr:street":"R De L ' Aven Zae Des Verriettes",
    "iso:country":"FR",
    "sg:address":"230 R De L' Aven Zae Des Verriettes 34980 St G\u00e9ly Du Fesc",
    "sg:classifiers":[
        {
            "category":"Wholesale",
            "subcategory":"Machinery & Supplies",
            "type":"Manufacturing & Wholesale Goods"
        }
    ],
    "sg:phone":"+33 4 67 84 81 10",
    "sg:province":"Languedoc-Roussillon",
    "sg:tags":[
        "equipment",
        "precision"
    ],
    "wof:name":"Save Sa",
    "wof:placetype":"venue"
},
  "geometry": {"coordinates":[3.813625,43.678165],"type":"Point"}
}