{
  "type": "Feature",
  "properties": {
    "iso:country":"FR",
    "sg:address":"17 rue des Neaux 95320 St Leu La Foret",
    "sg:classifiers":[
        {
            "category":"Wholesale",
            "subcategory":"Machinery & Supplies",
            "type":"Manufacturing & Wholesale Goods"
        }
    ],
    "sg:phone":"+33 1 39 95 56 76",
    "sg:postcode":"95320",
    "sg:province":"Ile de France",
    "sg:tags":[
        "pin",
        "clevis"
    ],
    "wof:name":"Vis Plus Sarl",
    "wof:placetype":"venue"
},
  "geometry": {"coordinates":[2.246154,49.013702],"type":"Point"}
}