{
  "type": "Feature",
  "properties": {
    "addr:full":"16 Rue De L Abbaye 75006 Paris Ile de France 75006",
    "addr:housenumber":"16",
    "addr:postcode":"75006;75006",
    "addr:street":"Rue De L",
    "iso:country":"FR",
    "sg:address":"16 Rue De L Abbaye 75006 Paris",
    "sg:classifiers":[
        {
            "category":"Shopping",
            "subcategory":"Clothing, Apparel, & Fashions",
            "type":"Retail Goods"
        }
    ],
    "sg:phone":"+33 1 56 24 90 53",
    "sg:postcode":"75006",
    "sg:province":"Ile de France",
    "sg:tags":[
        "textile",
        "clothing",
        "clothes"
    ],
    "wof:name":"Christian Dior Couture",
    "wof:placetype":"venue"
},
  "geometry": {"coordinates":[2.334173,48.854496],"type":"Point"}
}