{
  "type": "Feature",
  "properties": {
    "addr:full":"10 Rue Martin 71710 Montcenis Montcenis Bourgogne 71710",
    "addr:housenumber":"10",
    "addr:postcode":"71710;71710",
    "addr:street":"Rue Martin",
    "iso:country":"FR",
    "sg:address":"10 Rue Martin 71710 Montcenis",
    "sg:city":"Montcenis",
    "sg:classifiers":[
        {
            "category":"Manufacturing",
            "subcategory":"Wood Products",
            "type":"Manufacturing & Wholesale Goods"
        }
    ],
    "sg:phone":"+33 3 85 55 12 09",
    "sg:postcode":"71710",
    "sg:province":"Bourgogne",
    "sg:tags":[
        "professional",
        "furniture"
    ],
    "wof:name":"Gambut Andre",
    "wof:placetype":"venue"
},
  "geometry": {"coordinates":[4.410285,46.789158],"type":"Point"}
}