{
  "type": "Feature",
  "properties": {
    "addr:full":"2 Rue De Gen\u00e8ve 74100 Annemasse Rhone-Alpes 74100",
    "addr:housenumber":"2",
    "addr:postcode":"74100;74100",
    "addr:street":"Rue De Gene\u0300Ve",
    "iso:country":"FR",
    "sg:address":"2 Rue De Gen\u00e8ve 74100 Annemasse",
    "sg:orig_category":"Miscellaneous Products",
    "sg:phone":"+33 4 50 38 13 89",
    "sg:postcode":"74100",
    "sg:province":"Rhone-Alpes",
    "wof:name":"Touzeau Sa",
    "wof:placetype":"venue"
},
  "geometry": {"coordinates":[6.233171,46.193111],"type":"Point"}
}