{
  "type": "Feature",
  "properties": {
    "addr:full":"14, Rue Colbert, 21600 Longvic Longvic Bourgogne 21600",
    "addr:housenumber":"14",
    "addr:postcode":"21600;21600",
    "addr:street":"Rue Colbert",
    "iso:country":"FR",
    "sg:address":"14, Rue Colbert, 21600 Longvic",
    "sg:city":"Longvic",
    "sg:orig_category":"Non-Classified Establishments",
    "sg:phone":"+33 3 80 66 21 96",
    "sg:postcode":"21600",
    "sg:province":"Bourgogne",
    "wof:name":"T.m.a. S.a.",
    "wof:placetype":"venue"
},
  "geometry": {"coordinates":[5.042291,47.279831],"type":"Point"}
}