{
  "type": "Feature",
  "properties": {
    "iso:country":"FR",
    "sg:address":"B.P. 45, 59279 Loon Plage^^Rue Georges Pompidou, 59279 Loon Plage",
    "sg:orig_category":"Non-Classified Establishments",
    "sg:phone":"+33 3 28 58 76 66",
    "sg:province":"Nord Pas-de-Calais",
    "wof:name":"T.d.b. S.a. - Thulliez Dunkerque Bardage",
    "wof:placetype":"venue"
},
  "geometry": {"coordinates":[2.21998,50.994347],"type":"Point"}
}