{
  "type": "Feature",
  "properties": {
    "iso:country":"FR",
    "sg:address":"50, Rue du Pont Colbert, 78000 Versailles",
    "sg:orig_category":"Unclassifiable Establishments",
    "sg:phone":"+33 1 39 49 49 96",
    "sg:province":"Ile de France",
    "wof:name":"Qualiconsult S\u00e9curit\u00e9 S.a.",
    "wof:placetype":"venue"
},
  "geometry": {"coordinates":[2.14954,48.788471],"type":"Point"}
}