{
  "type": "Feature",
  "properties": {
    "iso:country":"FR",
    "sg:address":"1 Rte De L'Ecole 39150 La Chaumusse",
    "sg:classifiers":[
        {
            "category":"Health Services",
            "subcategory":"Optometrist",
            "type":"Services"
        }
    ],
    "sg:phone":"+33 3 84 60 84 99",
    "sg:postcode":"39150",
    "sg:province":"Franche Comt\u00e9",
    "sg:tags":[
        "instrument",
        "optical",
        "-",
        "precision",
        "equipment"
    ],
    "wof:name":"Cemo Sa",
    "wof:placetype":"venue"
},
  "geometry": {"coordinates":[5.956004,46.593678],"type":"Point"}
}