{
  "type": "Feature",
  "properties": {
    "iso:country":"FR",
    "sg:address":"10",
    "sg:city":"Libourne",
    "sg:classifiers":[
        {
            "category":"Food Court",
            "type":"Food & Drink"
        }
    ],
    "sg:phone":"+33 5 57 55 00 53",
    "sg:postcode":"33500",
    "sg:province":"Aquitaine",
    "sg:tags":[
        "product",
        "related"
    ],
    "wof:name":"Bordeaux Rive Droite",
    "wof:placetype":"venue"
},
  "geometry": {"coordinates":[-0.286437,44.884071],"type":"Point"}
}