{
  "type": "Feature",
  "properties": {
    "addr:full":"290, Av de Colmar, 67100 Strasbourg Strasbourg Alsace 67100",
    "addr:postcode":"67100;67100",
    "addr:street":"290 Av De Colmar",
    "iso:country":"FR",
    "sg:address":"290, Av de Colmar, 67100 Strasbourg",
    "sg:city":"Strasbourg",
    "sg:orig_category":"DISJONCTEURS ET INTERRUPTEURS DIFF\u00c9RENTIELS, COMMUTATEURS \u00c0 CAMES, AUXILIAIRES DE COMMANDE ET DE SIG",
    "sg:phone":"+33 3 88 79 33 33",
    "sg:postcode":"67100",
    "sg:province":"Alsace",
    "wof:name":"Baco Constructions Electriques S.a.",
    "wof:placetype":"venue"
},
  "geometry": {"coordinates":[7.742495,48.551102],"type":"Point"}
}