{
  "type": "Feature",
  "properties": {
    "addr:full":"Hameau De Beauvert Cd 3 91460 Marcoussis Ile de France 91460",
    "addr:housenumber":"3",
    "addr:postcode":"91460;ile;91460",
    "addr:street":"Hameau De Beauvert Cd;France",
    "iso:country":"FR",
    "sg:address":"Hameau De Beauvert Cd 3 91460 Marcoussis",
    "sg:classifiers":[
        {
            "category":"Professional",
            "subcategory":"Engineering",
            "type":"Services"
        }
    ],
    "sg:phone":"+33 1 69 80 18 03",
    "sg:postcode":"91460",
    "sg:province":"Ile de France",
    "sg:tags":[
        "machine",
        "-",
        "mechanical"
    ],
    "wof:name":"Matrasur Composites",
    "wof:placetype":"venue"
},
  "geometry": {"coordinates":[2.19525,48.646297],"type":"Point"}
}