{
  "type": "Feature",
  "properties": {
    "addr:full":"Impasse des Fr\u00e8res Lumi\u00e8re - ZAC de Villemandeur Villemandeur Centre 45700",
    "addr:housenumber":"villemandeur",
    "addr:postcode":"45700",
    "addr:street":"Impasse Des Fre\u0300Res Lumie\u0300Re Zac De Villemandeur",
    "iso:country":"FR",
    "sg:address":"Impasse des Fr\u00e8res Lumi\u00e8re - ZAC de Villemandeur",
    "sg:city":"Villemandeur",
    "sg:orig_category":"Non-Classified Establishments",
    "sg:phone":"+33 2 38 98 02 35",
    "sg:postcode":"45700",
    "sg:province":"Centre",
    "wof:name":"Nci",
    "wof:placetype":"venue"
},
  "geometry": {"coordinates":[2.765315,47.896927],"type":"Point"}
}