{
  "type": "Feature",
  "properties": {
    "addr:full":"Le Bourg 01290 Biziat Rhone-Alpes 01290",
    "addr:postcode":"01290;01290",
    "addr:street":"Le Bourg;Rhone-Alpes",
    "iso:country":"FR",
    "sg:address":"Le Bourg 01290 Biziat",
    "sg:orig_category":"Non-Classified Establishments",
    "sg:phone":"+33 4 74 50 03 15",
    "sg:postcode":"01290",
    "sg:province":"Rhone-Alpes",
    "wof:name":"Villier Bernard S.a.r.l.",
    "wof:placetype":"venue"
},
  "geometry": {"coordinates":[4.88765,46.247299],"type":"Point"}
}