{
  "type": "Feature",
  "properties": {
    "iso:country":"FR",
    "sg:address":"7 Avenue Gabriel Peri 93150 Le Blanc Mesnil",
    "sg:classifiers":[
        {
            "category":"Utilities",
            "type":"Services"
        }
    ],
    "sg:phone":"+33 1 48 67 42 95",
    "sg:postcode":"93150",
    "sg:province":"Ile de France",
    "sg:tags":[
        "raw",
        "energy",
        "material"
    ],
    "wof:name":"Saur France",
    "wof:placetype":"venue"
},
  "geometry": {"coordinates":[2.461174,48.93856],"type":"Point"}
}