{
  "type": "Feature",
  "properties": {
    "iso:country":"FR",
    "sg:address":"Rue Jean Moulin - ZI du Bayon",
    "sg:city":"La Ricamarie",
    "sg:orig_category":"Non-Classified Establishments",
    "sg:phone":"+33 4 77 81 30 17",
    "sg:postcode":"42150",
    "sg:province":"Rhone-Alpes",
    "wof:name":"Imprimerie Touron S.a.",
    "wof:placetype":"venue"
},
  "geometry": {"coordinates":[4.36615,45.40406],"type":"Point"}
}