{
  "type": "Feature",
  "properties": {
    "iso:country":"FR",
    "sg:address":"40 Rue Louis Blanc 75010 Paris",
    "sg:classifiers":[
        {
            "category":"Shopping",
            "subcategory":"Clothing, Apparel, & Fashions",
            "type":"Retail Goods"
        }
    ],
    "sg:phone":"+33 1 40 37 11 61",
    "sg:postcode":"75010",
    "sg:province":"Ile de France",
    "sg:tags":[
        "textile",
        "clothing",
        "clothes"
    ],
    "wof:name":"D Baran",
    "wof:placetype":"venue"
},
  "geometry": {"coordinates":[2.36431,48.881737],"type":"Point"}
}