{
  "type": "Feature",
  "properties": {
    "addr:full":"Av Du Gros Ch\u00eane 95610 Eragny Sur Oise Ile de France 95610",
    "addr:postcode":"95610;95610",
    "addr:street":"Av Du Gros Che\u0302Ne",
    "iso:country":"FR",
    "sg:address":"Av Du Gros Ch\u00eane 95610 Eragny Sur Oise",
    "sg:classifiers":[
        {
            "category":"Shopping",
            "subcategory":"Stationery & Office Supplies",
            "type":"Retail Goods"
        }
    ],
    "sg:phone":"+33 1 34 30 24 90",
    "sg:postcode":"95610",
    "sg:province":"Ile de France",
    "sg:tags":[
        "information",
        "technology",
        "telecommunication",
        "equipment"
    ],
    "wof:name":"Office Depot Eragny",
    "wof:placetype":"venue"
},
  "geometry": {"coordinates":[2.107264,49.027889],"type":"Point"}
}