{
  "type": "Feature",
  "properties": {
    "addr:full":"Route De P\u00e9zenas 34500 B\u00e9ziers Languedoc-Roussillon 34500",
    "addr:postcode":"34500;34500",
    "addr:street":"Route De Pe\u0301Zenas",
    "iso:country":"FR",
    "sg:address":"Route De P\u00e9zenas 34500 B\u00e9ziers",
    "sg:classifiers":[
        {
            "category":"Food Court",
            "type":"Food & Drink"
        }
    ],
    "sg:phone":"+33 4 67 09 22 44",
    "sg:postcode":"34500",
    "sg:province":"Languedoc-Roussillon",
    "sg:tags":[
        "product",
        "related"
    ],
    "wof:name":"Bieres Boissons Beziers Snc",
    "wof:placetype":"venue"
},
  "geometry": {"coordinates":[3.216105,43.344234],"type":"Point"}
}