{
  "type": "Feature",
  "properties": {
    "addr:full":"22, Rue Merim\u00e9e, 06110 Le Cannet Provence-Alpes-C\u00f4te d'Azur",
    "addr:housenumber":"22",
    "addr:postcode":"06110",
    "addr:street":"Rue Merime\u0301E;Cannet",
    "iso:country":"FR",
    "sg:address":"22, Rue Merim\u00e9e, 06110 Le Cannet",
    "sg:orig_category":"Non-Classified Establishments",
    "sg:phone":"+33 4 93 38 83 77",
    "sg:province":"Provence-Alpes-C\u00f4te d'Azur",
    "wof:name":"Laboratoires Gramon S.a.r.l.",
    "wof:placetype":"venue"
},
  "geometry": {"coordinates":[7.017305,43.569218],"type":"Point"}
}