{
  "type": "Feature",
  "properties": {
    "addr:full":"290 Rue Faventines Valence Rhone-Alpes 26000",
    "addr:housenumber":"290",
    "addr:postcode":"26000",
    "addr:street":"Rue Faventines;Rhone-Alpes",
    "iso:country":"FR",
    "sg:address":"290 Rue Faventines",
    "sg:city":"Valence",
    "sg:classifiers":[
        {
            "category":"Banks & Credit Unions",
            "subcategory":"Financial Services",
            "type":"Services"
        }
    ],
    "sg:phone":"+33 4 75 78 86 00",
    "sg:postcode":"26000",
    "sg:province":"Rhone-Alpes",
    "sg:tags":[
        "banking",
        "finance",
        "insurance"
    ],
    "wof:name":"Caisse Regionale Credit Agricole Mutuel De La Drome",
    "wof:placetype":"venue"
},
  "geometry": {"coordinates":[4.908947,44.917664],"type":"Point"}
}