{
  "type": "Feature",
  "properties": {
    "addr:full":"Rue Du Gros Chene Za De La Corderie 35750 Iffendic Iffendic Bretagne 35750",
    "addr:postcode":"35750;35750",
    "addr:street":"Rue Du Gros Chene Za De La Corderie;Iffendic",
    "iso:country":"FR",
    "sg:address":"Rue Du Gros Chene Za De La Corderie 35750 Iffendic",
    "sg:city":"Iffendic",
    "sg:classifiers":[
        {
            "category":"Professional",
            "subcategory":"Printing & Photocopies",
            "type":"Services"
        }
    ],
    "sg:phone":"+33 2 99 09 95 10",
    "sg:postcode":"35750",
    "sg:province":"Bretagne",
    "sg:tags":[
        "publishing"
    ],
    "wof:name":"Hebdoprint (psp)",
    "wof:placetype":"venue"
},
  "geometry": {"coordinates":[-2.099445,48.092762],"type":"Point"}
}