{
  "type": "Feature",
  "properties": {
    "addr:full":"47, Rte de Ch\u00e2tillon, 36290 M\u00e9zi\u00e8res en Brenne Azay-le-Ferron Centre 36290",
    "addr:housenumber":"47;azay-le-ferron",
    "addr:postcode":"36290;36290",
    "addr:street":"Rte De Cha\u0302Tillon",
    "iso:country":"FR",
    "sg:address":"47, Rte de Ch\u00e2tillon, 36290 M\u00e9zi\u00e8res en Brenne",
    "sg:city":"Azay-le-Ferron",
    "sg:orig_category":"Non-Classified Establishments",
    "sg:phone":"+33 2 54 28 67 67",
    "sg:postcode":"36290",
    "sg:province":"Centre",
    "wof:name":"Noiseraie Productions S.a.r.l.",
    "wof:placetype":"venue"
},
  "geometry": {"coordinates":[1.20918,46.821484],"type":"Point"}
}