{
  "type": "Feature",
  "properties": {
    "iso:country":"FR",
    "sg:address":"B.P. 95, 80500 Montdidier^^Zone Industrielle de la Roseraie, 80500 Montdidier",
    "sg:orig_category":"Non-Classified Establishments",
    "sg:phone":"+33 3 22 78 06 46",
    "sg:province":"Picardie",
    "wof:name":"Lema\u00eetre Bruno S.a.r.l.",
    "wof:placetype":"venue"
},
  "geometry": {"coordinates":[2.571364,49.647224],"type":"Point"}
}