{
  "type": "Feature",
  "properties": {
    "addr:full":"Avenue Andre Reinson Centre Commercial Auchan Lac 33300 Bordeaux Bordeaux Aquitaine 33300",
    "addr:postcode":"33300;33300",
    "addr:street":"Avenue Andre Reinson Centre;Lac",
    "iso:country":"FR",
    "sg:address":"Avenue Andre Reinson Centre Commercial Auchan Lac 33300 Bordeaux",
    "sg:city":"Bordeaux",
    "sg:classifiers":[
        {
            "category":"Shopping",
            "subcategory":"Clothing, Apparel, & Fashions",
            "type":"Retail Goods"
        }
    ],
    "sg:phone":"+33 5 56 50 01 66",
    "sg:postcode":"33300",
    "sg:province":"Aquitaine",
    "sg:tags":[
        "textile",
        "clothing",
        "clothes"
    ],
    "wof:name":"Promod",
    "wof:placetype":"venue"
},
  "geometry": {"coordinates":[-0.56244,44.87672],"type":"Point"}
}