{
  "type": "Feature",
  "properties": {
    "addr:full":"Za Le Bourgneuf 72230 Mulsanne Pays de Loire 72230",
    "addr:postcode":"72230;72230",
    "addr:street":"Za Le Bourgneuf",
    "iso:country":"FR",
    "sg:address":"Za Le Bourgneuf 72230 Mulsanne",
    "sg:classifiers":[
        {
            "category":"Retail",
            "subcategory":"Laundry & Dry Cleaning",
            "type":"Services"
        }
    ],
    "sg:phone":"+33 2 43 42 82 00",
    "sg:postcode":"72230",
    "sg:province":"Pays de Loire",
    "sg:tags":[
        "equipment"
    ],
    "wof:name":"N A S A T Sarl",
    "wof:placetype":"venue"
},
  "geometry": {"coordinates":[0.244285,47.909885],"type":"Point"}
}