{
  "type": "Feature",
  "properties": {
    "iso:country":"FR",
    "sg:address":"B.P. 24, 88001 Epinal C\u00e9dex^^Cour de la Gare, 88000 Epinal",
    "sg:orig_category":"Non-Classified Establishments",
    "sg:phone":"+33 3 29 69 31 12",
    "sg:province":"Lorraine",
    "wof:name":"Sernam",
    "wof:placetype":"venue"
},
  "geometry": {"coordinates":[6.4497,48.175686],"type":"Point"}
}