{
  "type": "Feature",
  "properties": {
    "iso:country":"FR",
    "sg:address":"B.P. 511, 89105 Sens C\u00e9dex^^5, Rue Longues Raies, 89100 Sens",
    "sg:city":"Sens",
    "sg:orig_category":"Non-Classified Establishments",
    "sg:phone":"+33 3 86 95 09 00",
    "sg:postcode":"89100",
    "sg:province":"Bourgogne",
    "wof:name":"Socap S.a. - Service Outils Coupants Aff\u00fbtage Pr\u00e9au",
    "wof:placetype":"venue"
},
  "geometry": {"coordinates":[3.3115,48.150352],"type":"Point"}
}