{
  "type": "Feature",
  "properties": {
    "addr:full":"Rue De L'Ing\u00e9nieur Moriandi\u00e8re Monts Centre 37260",
    "addr:postcode":"37260",
    "addr:street":"Rue De L'Inge \u0301Nieur Moriandie\u0300Re Monts",
    "iso:country":"FR",
    "sg:address":"Rue De L'Ing\u00e9nieur Moriandi\u00e8re",
    "sg:city":"Monts",
    "sg:classifiers":[
        {
            "category":"Utilities",
            "subcategory":"Telephone",
            "type":"Services"
        }
    ],
    "sg:phone":"+33 2 47 26 66 66",
    "sg:postcode":"37260",
    "sg:province":"Centre",
    "sg:tags":[
        "telecommunication"
    ],
    "wof:name":"Optifib",
    "wof:placetype":"venue"
},
  "geometry": {"coordinates":[0.658664,47.283562],"type":"Point"}
}