{
  "type": "Feature",
  "properties": {
    "iso:country":"FR",
    "sg:address":"Zi Blactot 50500 Carentan",
    "sg:city":"Carentan",
    "sg:classifiers":[
        {
            "category":"Shopping",
            "type":"Retail Goods"
        }
    ],
    "sg:phone":"+33 2 33 42 41 48",
    "sg:postcode":"50500",
    "sg:province":"Basse Normandie",
    "sg:tags":[
        "metallurgy",
        "finished",
        "-",
        "metalworking",
        "metallic"
    ],
    "wof:name":"Ctra",
    "wof:placetype":"venue"
},
  "geometry": {"coordinates":[-1.247078,49.30291],"type":"Point"}
}