{
  "type": "Feature",
  "properties": {
    "iso:country":"FR",
    "sg:address":"B.P. 5037, 49180 Saint Barth\u00e9l\u00e9my d'Anjou C\u00e9dex^^Rue de Champfleur - ZI, 49124 Saint Barth\u00e9l\u00e9my d'An",
    "sg:orig_category":"Non-Classified Establishments",
    "sg:phone":"+33 2 41 18 82 84",
    "sg:province":"Pays de Loire",
    "wof:name":"M.r.s. S.a.",
    "wof:placetype":"venue"
},
  "geometry": {"coordinates":[-1.334822,47.273693],"type":"Point"}
}