{
  "type": "Feature",
  "properties": {
    "addr:full":"32 Rue Fenouillet 31140 St Alban Midi Pyr\u00e9n\u00e9es",
    "addr:housenumber":"32",
    "addr:postcode":"31140",
    "addr:street":"Rue Fenouillet",
    "iso:country":"FR",
    "sg:address":"32 Rue Fenouillet 31140 St Alban",
    "sg:classifiers":[
        {
            "category":"Professional",
            "type":"Services"
        }
    ],
    "sg:phone":"+33 5 61 70 70 28",
    "sg:province":"Midi Pyr\u00e9n\u00e9es",
    "sg:tags":[
        "transport",
        "road"
    ],
    "wof:name":"Trans-occitan Sarl",
    "wof:placetype":"venue"
},
  "geometry": {"coordinates":[1.407884,43.688473],"type":"Point"}
}