{
  "type": "Feature",
  "properties": {
    "addr:full":"21 rue du Prieure; Aubigny; 18700 Aubigny-sur-N\u00e8re Centre 18700",
    "addr:housenumber":"21;aubigny-sur-ne\u0300re",
    "addr:postcode":"18700;18700",
    "addr:street":"Rue Du Prieure",
    "iso:country":"FR",
    "sg:address":"21 rue du Prieure; Aubigny; 18700",
    "sg:city":"Aubigny-sur-N\u00e8re",
    "sg:classifiers":[
        {
            "category":"Banks & Credit Unions",
            "subcategory":"Bank",
            "type":"Services"
        }
    ],
    "sg:phone":"+33 3348580036",
    "sg:postcode":"18700",
    "sg:province":"Centre",
    "wof:name":"Banque Nationale De Paris",
    "wof:placetype":"venue"
},
  "geometry": {"coordinates":[2.50778,47.421684],"type":"Point"}
}