{
  "type": "Feature",
  "properties": {
    "iso:country":"FR",
    "sg:address":"B.P. 10, 08800 Thilay^^3, Rue du Baquet, 08800 Thilay",
    "sg:city":"Deville",
    "sg:orig_category":"Ancrages Boulonnerie Boulonnerie d'ancrage Boulonnerie en acier inoxydable Boulonnerie galvanis\u00e9e Bo",
    "sg:phone":"+33 3 24 32 80 90",
    "sg:postcode":"08800",
    "sg:province":"Champagne",
    "wof:name":"Bayonet S.a.",
    "wof:placetype":"venue"
},
  "geometry": {"coordinates":[4.76741,49.882038],"type":"Point"}
}