{
  "type": "Feature",
  "properties": {
    "addr:full":"25 rue Bossuet 91160 Longjumeau Ile de France",
    "addr:housenumber":"25",
    "addr:postcode":"91160;ile",
    "addr:street":"Rue Bossuet",
    "iso:country":"FR",
    "sg:address":"25 rue Bossuet 91160 Longjumeau",
    "sg:classifiers":[
        {
            "category":"Utilities",
            "subcategory":"Water",
            "type":"Services"
        }
    ],
    "sg:phone":"+33 1 69 09 72 82",
    "sg:province":"Ile de France",
    "sg:tags":[
        "steam",
        "boiler"
    ],
    "wof:name":"Barata Sa",
    "wof:placetype":"venue"
},
  "geometry": {"coordinates":[2.301612,48.704369],"type":"Point"}
}