{
  "type": "Feature",
  "properties": {
    "addr:full":"Rte de Toulouse Mas Saintes Ruelles - Les Carmes Castelnaudary C\u00e9dex Midi-Pyr\u00e9n\u00e9es 11492",
    "addr:postcode":"11492",
    "addr:street":"Rte De Toulouse Mas Saintes Ruelles Les",
    "iso:country":"FR",
    "sg:address":"Rte de Toulouse Mas Saintes Ruelles - Les Carmes",
    "sg:city":"Castelnaudary C\u00e9dex",
    "sg:orig_category":"Non-Classified Establishments",
    "sg:phone":"+33 4 68 60 04 07",
    "sg:postcode":"11492",
    "sg:province":"Midi-Pyr\u00e9n\u00e9es",
    "wof:name":"Poterie De Castel S.a.",
    "wof:placetype":"venue"
},
  "geometry": {"coordinates":[1.44868,43.605751],"type":"Point"}
}