{
  "type": "Feature",
  "properties": {
    "addr:full":"B.P. 33 Saint Laurent sur S\u00e8vre Pays de Loire 85290",
    "addr:housenumber":"33",
    "addr:postcode":"85290",
    "addr:street":"B.P.;Se\u0300Vre",
    "iso:country":"FR",
    "sg:address":"B.P. 33",
    "sg:city":"Saint Laurent sur S\u00e8vre",
    "sg:orig_category":"Non-Classified Establishments",
    "sg:phone":"+33 2 51 64 64 64",
    "sg:postcode":"85290",
    "sg:province":"Pays de Loire",
    "wof:name":"G.i.f.a. S.a. - Groupement Industriel De Fabrication Ambulances",
    "wof:placetype":"venue"
},
  "geometry": {"coordinates":[-0.891658,46.959106],"type":"Point"}
}