{
  "type": "Feature",
  "properties": {
    "iso:country":"FR",
    "sg:address":"11, Rue de Maurice Genevoix, 75018 Paris",
    "sg:orig_category":"Unclassifiable Establishments",
    "sg:phone":"+33 1 40 35 99 77",
    "sg:province":"Ile de France",
    "wof:name":"N.s.g. S.a. - Novatec S\u00e9curit\u00e9 Gardiennage",
    "wof:placetype":"venue"
},
  "geometry": {"coordinates":[2.34463,48.892471],"type":"Point"}
}