{
  "type": "Feature",
  "properties": {
    "iso:country":"FR",
    "sg:address":"Enceinte Portuaire Porte 4 13015 Marseille",
    "sg:classifiers":[
        {
            "category":"Manufacturing",
            "subcategory":"Motor Vehicles & Parts",
            "type":"Manufacturing & Wholesale Goods"
        }
    ],
    "sg:phone":"+33 4 91 03 99 20",
    "sg:province":"Champagne",
    "sg:tags":[
        "engine",
        "machine",
        "engineering",
        "-",
        "mechanical"
    ],
    "wof:name":"Wartsila Nsd France Sa",
    "wof:placetype":"venue"
},
  "geometry": {"coordinates":[5.37278,43.344948],"type":"Point"}
}