{
  "type": "Feature",
  "properties": {
    "iso:country":"FR",
    "sg:address":"17, Av. de Roquefavour - Local 5, 13015 Marseille",
    "sg:orig_category":"Non-Classified Establishments",
    "sg:phone":"+33 4 95 06 42 80",
    "sg:province":"Poitou-Charentes",
    "wof:name":"Mapac S.a.r.l.",
    "wof:placetype":"venue"
},
  "geometry": {"coordinates":[5.37278,43.344948],"type":"Point"}
}