{
  "type": "Feature",
  "properties": {
    "addr:full":"2 Rue Danel, Lille, Dept 59 Nord Pas-de-Calais",
    "addr:housenumber":"2;59",
    "addr:street":"Rue Danel",
    "iso:country":"FR",
    "sg:address":"2 Rue Danel, Lille, Dept 59",
    "sg:classifiers":[
        {
            "category":"Banks & Credit Unions",
            "subcategory":"Bank",
            "type":"Services"
        }
    ],
    "sg:province":"Nord Pas-de-Calais",
    "wof:name":"Artesia Bail",
    "wof:placetype":"venue"
},
  "geometry": {"coordinates":[3.057553,50.640186],"type":"Point"}
}