{
  "type": "Feature",
  "properties": {
    "addr:full":"Gare 71570 Roman\u00e8che Thorins Chaintr\u00e9 Bourgogne 71570",
    "addr:postcode":"71570;71570",
    "addr:street":"Gare",
    "iso:country":"FR",
    "sg:address":"Gare 71570 Roman\u00e8che Thorins",
    "sg:city":"Chaintr\u00e9",
    "sg:classifiers":[
        {
            "category":"Food Court",
            "type":"Food & Drink"
        }
    ],
    "sg:phone":"+33 3 85 35 51 85",
    "sg:postcode":"71570",
    "sg:province":"Bourgogne",
    "sg:tags":[
        "product",
        "related"
    ],
    "wof:name":"Jacoulot Sas",
    "wof:placetype":"venue"
},
  "geometry": {"coordinates":[4.740734,46.176765],"type":"Point"}
}