{
  "type": "Feature",
  "properties": {
    "addr:full":"Bel Air Bel Air 12000 Rodez Midi Pyr\u00e9n\u00e9es",
    "addr:postcode":"12000",
    "addr:street":"Bel Air",
    "iso:country":"FR",
    "sg:address":"Bel Air Bel Air 12000 Rodez",
    "sg:classifiers":[
        {
            "category":"Home & Garden",
            "subcategory":"Furniture",
            "type":"Retail Goods"
        }
    ],
    "sg:phone":"+33 5 65 42 22 36",
    "sg:province":"Midi Pyr\u00e9n\u00e9es",
    "sg:tags":[
        "wood"
    ],
    "wof:name":"Etablissements Alram",
    "wof:placetype":"venue"
},
  "geometry": {"coordinates":[2.57289,44.349735],"type":"Point"}
}