{
  "type": "Feature",
  "properties": {
    "iso:country":"FR",
    "sg:address":"Rue Alain Colas - ZI Tyar M\u00e9nez",
    "sg:city":"Plougastel Daoulas",
    "sg:orig_category":"Unclassifiable Establishments",
    "sg:phone":"+33 2 98 40 20 20",
    "sg:postcode":"29470",
    "sg:province":"Bretagne",
    "wof:name":"Enseignes Techni D\u00e9cors S.a.r.l.",
    "wof:placetype":"venue"
},
  "geometry": {"coordinates":[-4.260644,48.359119],"type":"Point"}
}