{
  "type": "Feature",
  "properties": {
    "addr:full":"9 Rue Bleue 75009 Paris Ile de France 75009",
    "addr:housenumber":"9",
    "addr:postcode":"75009;75009",
    "addr:street":"Rue Bleue",
    "iso:country":"FR",
    "sg:address":"9 Rue Bleue 75009 Paris",
    "sg:classifiers":[
        {
            "category":"Professional",
            "subcategory":"Business Services",
            "type":"Services"
        }
    ],
    "sg:phone":"+33 1 45 23 20 56",
    "sg:postcode":"75009",
    "sg:province":"Ile de France",
    "sg:tags":[
        "training",
        "advice"
    ],
    "wof:name":"Cours Prive Le Maitre",
    "wof:placetype":"venue"
},
  "geometry": {"coordinates":[2.346811,48.875751],"type":"Point"}
}