{
  "type": "Feature",
  "properties": {
    "addr:full":"31, Rue Henri Sellier, 79000 Niort Poitou-Charentes",
    "addr:housenumber":"31",
    "addr:postcode":"79000",
    "addr:street":"Rue Henri Sellier",
    "iso:country":"FR",
    "sg:address":"31, Rue Henri Sellier, 79000 Niort",
    "sg:orig_category":"Unclassifiable Establishments",
    "sg:phone":"+33 5 49 79 92 92",
    "sg:province":"Poitou-Charentes",
    "wof:name":"Menneguerre Photogravure S.a.r.l.",
    "wof:placetype":"venue"
},
  "geometry": {"coordinates":[-0.458533,46.312016],"type":"Point"}
}