{
  "type": "Feature",
  "properties": {
    "addr:full":"Impasse Sabli\u00e8re Saint Eloi Bourgogne 58000",
    "addr:postcode":"58000",
    "addr:street":"Impasse Sablie\u0300Re Saint Eloi Bourgogne",
    "iso:country":"FR",
    "sg:address":"Impasse Sabli\u00e8re",
    "sg:city":"Saint Eloi",
    "sg:orig_category":"Unclassifiable Establishments",
    "sg:phone":"+33 3 86 37 77 87",
    "sg:postcode":"58000",
    "sg:province":"Bourgogne",
    "wof:name":"S.e.m.m. S.a. - Schneider Electricit\u00e9 M\u00e9canique Maintenance",
    "wof:placetype":"venue"
},
  "geometry": {"coordinates":[3.21222,46.983753],"type":"Point"}
}