{
  "type": "Feature",
  "properties": {
    "addr:full":"Sph\u00e8re r L\u00e9on Foucault H\u00e9rouville Saint Clair Basse Normandie 14200",
    "addr:postcode":"14200",
    "addr:street":"R;Saint Clair Basse",
    "iso:country":"FR",
    "sg:address":"Sph\u00e8re r L\u00e9on Foucault",
    "sg:city":"H\u00e9rouville Saint Clair",
    "sg:classifiers":[
        {
            "category":"Banks & Credit Unions",
            "subcategory":"Financial Services",
            "type":"Services"
        }
    ],
    "sg:phone":"+33 2 31 44 39 39",
    "sg:postcode":"14200",
    "sg:province":"Basse Normandie",
    "sg:tags":[
        "banking",
        "finance",
        "insurance"
    ],
    "wof:name":"Cabinet D'expertise Mouret",
    "wof:placetype":"venue"
},
  "geometry": {"coordinates":[-0.348682,49.213131],"type":"Point"}
}