{
  "type": "Feature",
  "properties": {
    "iso:country":"FR",
    "sg:address":"Zi Nord 85607 Montaigu Cedex",
    "sg:classifiers":[
        {
            "category":"Airport",
            "type":"Transportation"
        }
    ],
    "sg:phone":"+33 2 51 45 20 00",
    "sg:province":"Aquitaine",
    "sg:tags":[
        "transport",
        "air"
    ],
    "wof:name":"Transports Rapides Joyau",
    "wof:placetype":"venue"
},
  "geometry": {"coordinates":[-1.312719,46.975365],"type":"Point"}
}