{
  "type": "Feature",
  "properties": {
    "iso:country":"FR",
    "sg:address":"B.P. CF 30911, 08209 Sedan C\u00e9dex^^Bd de l'Europe, 08200 Sedan",
    "sg:orig_category":"Non-Classified Establishments",
    "sg:phone":"+33 3 24 27 88 88",
    "sg:province":"Champagne",
    "wof:name":"Michaux S.a.",
    "wof:placetype":"venue"
},
  "geometry": {"coordinates":[4.923699,49.692963],"type":"Point"}
}