{
  "type": "Feature",
  "properties": {
    "addr:full":"6 Rue Paul Bert 92240 Malakoff Ile de France 92240",
    "addr:housenumber":"6",
    "addr:postcode":"92240;ile;92240",
    "addr:street":"Rue Paul Bert;France",
    "iso:country":"FR",
    "sg:address":"6 Rue Paul Bert 92240 Malakoff",
    "sg:classifiers":[
        {
            "category":"Shopping",
            "type":"Retail Goods"
        }
    ],
    "sg:phone":"+33 1 46 73 92 92",
    "sg:postcode":"92240",
    "sg:province":"Ile de France",
    "sg:tags":[
        "metallurgy",
        "finished",
        "-",
        "metalworking",
        "metallic"
    ],
    "wof:name":"Ds Dynatec",
    "wof:placetype":"venue"
},
  "geometry": {"coordinates":[2.297091,48.818829],"type":"Point"}
}