{
  "type": "Feature",
  "properties": {
    "addr:full":"451, Rue Oehmichen, 25460 Etupes Franche Comt\u00e9",
    "addr:housenumber":"451",
    "addr:postcode":"25460",
    "addr:street":"Rue Oehmichen;Franche Comte\u0301",
    "iso:country":"FR",
    "sg:address":"451, Rue Oehmichen, 25460 Etupes",
    "sg:orig_category":"Unclassifiable Establishments",
    "sg:phone":"+33 3 81 32 24 30",
    "sg:province":"Franche Comt\u00e9",
    "wof:name":"M.p.m.e. Groupe Servocam - Mat\u00e9riaux Plasturgie M\u00e9trologie Essais",
    "wof:placetype":"venue"
},
  "geometry": {"coordinates":[6.872015,47.516636],"type":"Point"}
}