{
  "type": "Feature",
  "properties": {
    "addr:full":"Mollian 42130 Ste Agathe La Bouter\u00e8sse Rhone-Alpes 42130",
    "addr:postcode":"42130;42130",
    "addr:street":"Mollian;Agathe;Rhone-Alpes",
    "iso:country":"FR",
    "sg:address":"Mollian 42130 Ste Agathe La Bouter\u00e8sse",
    "sg:classifiers":[
        {
            "category":"Manufacturing",
            "subcategory":"Textiles",
            "type":"Manufacturing & Wholesale Goods"
        }
    ],
    "sg:phone":"+33 4 77 97 74 00",
    "sg:postcode":"42130",
    "sg:province":"Rhone-Alpes",
    "sg:tags":[
        "clothing",
        "accessory"
    ],
    "wof:name":"Ets Thevenon Sa",
    "wof:placetype":"venue"
},
  "geometry": {"coordinates":[4.020175,45.740231],"type":"Point"}
}