{
  "type": "Feature",
  "properties": {
    "addr:full":"5-9 rue des Cascades 75020 Paris Ile de France 75020",
    "addr:housenumber":"5-9",
    "addr:postcode":"75020;75020",
    "addr:street":"Rue Des Cascades",
    "iso:country":"FR",
    "sg:address":"5-9 rue des Cascades 75020 Paris",
    "sg:classifiers":[
        {
            "category":"Health Services",
            "subcategory":"Nursing And Care Facility",
            "type":"Services"
        }
    ],
    "sg:phone":"+33 1 43 66 53 05",
    "sg:postcode":"75020",
    "sg:province":"Ile de France",
    "sg:tags":[
        "balneology",
        "electrotherapy",
        "fitting",
        "physiotherapy"
    ],
    "wof:name":"D.o.r.v.i.t. Sa",
    "wof:placetype":"venue"
},
  "geometry": {"coordinates":[2.390923,48.869411],"type":"Point"}
}