{
  "type": "Feature",
  "properties": {
    "addr:full":"9, Rue de l'Ouvrage \u00e0 Cornes, 17000 La Rochelle Poitou-Charentes",
    "addr:housenumber":"9",
    "addr:postcode":"17000",
    "addr:street":"Rue De L'Ouvrage A\u0300 Cornes",
    "iso:country":"FR",
    "sg:address":"9, Rue de l'Ouvrage \u00e0 Cornes, 17000 La Rochelle",
    "sg:orig_category":"Unclassifiable Establishments",
    "sg:phone":"+33 5 46 50 57 67",
    "sg:province":"Poitou-Charentes",
    "wof:name":"K.p.m.g. S.a.",
    "wof:placetype":"venue"
},
  "geometry": {"coordinates":[-1.17657,46.16206],"type":"Point"}
}