{
  "type": "Feature",
  "properties": {
    "iso:country":"FR",
    "sg:address":"B.P. 3847, 53032 Laval C\u00e9dex 9^^Av. d'Angers, 53000 Laval",
    "sg:orig_category":"Non-Classified Establishments",
    "sg:phone":"+33 2 43 49 66 00",
    "sg:province":"Pays de Loire",
    "wof:name":"Solvay Automotive France S.a.",
    "wof:placetype":"venue"
},
  "geometry": {"coordinates":[-0.752772,48.058357],"type":"Point"}
}