{
  "type": "Feature",
  "properties": {
    "iso:country":"FR",
    "sg:address":"38 Rue De Paris 59200 Tourcoing",
    "sg:classifiers":[
        {
            "category":"Shopping",
            "subcategory":"Gifts & Souvenirs",
            "type":"Retail Goods"
        }
    ],
    "sg:phone":"+33 3 20 36 20 20",
    "sg:postcode":"59200",
    "sg:province":"Nord Pas-de-Calais",
    "sg:tags":[
        "product",
        "miscellaneous"
    ],
    "wof:name":"Compagnie Internationale Achats Et Distrubition",
    "wof:placetype":"venue"
},
  "geometry": {"coordinates":[3.144678,50.7234],"type":"Point"}
}