{
  "type": "Feature",
  "properties": {
    "iso:country":"FR",
    "sg:address":"3 bis, Rue Thimonnier, 78120 Rambouillet",
    "sg:orig_category":"Non-Classified Establishments",
    "sg:phone":"+33 1 30 41 14 74",
    "sg:province":"Ile de France",
    "wof:name":"Eurogerm Ingr\u00e9dients S.a.r.l.",
    "wof:placetype":"venue"
},
  "geometry": {"coordinates":[1.829425,48.622337],"type":"Point"}
}