{
  "type": "Feature",
  "properties": {
    "iso:country":"FR",
    "sg:address":"10, Rue Lassaigne, 42000 Saint Etienne",
    "sg:orig_category":"Unclassifiable Establishments",
    "sg:phone":"+33 4 77 49 40 00",
    "sg:postcode":"42000",
    "sg:province":"Rhone-Alpes",
    "wof:name":"In Extenso Rh\u00f4nes-alpes S.a.",
    "wof:placetype":"venue"
},
  "geometry": {"coordinates":[4.397537,45.430302],"type":"Point"}
}