{
  "type": "Feature",
  "properties": {
    "addr:full":"B.P. 272, 44158 Ancenis C\u00e9dex^^Rue de Versailles, 44150 Saint Herblon Pays de Loire 44150",
    "addr:housenumber":"b.p. 272",
    "addr:postcode":"44158;44150 saint herblon;44150",
    "iso:country":"FR",
    "sg:address":"B.P. 272, 44158 Ancenis C\u00e9dex^^Rue de Versailles, 44150 Saint Herblon",
    "sg:orig_category":"Non-Classified Establishments",
    "sg:phone":"+33 2 40 98 02 28",
    "sg:postcode":"44150",
    "sg:province":"Pays de Loire",
    "wof:name":"Courant S.a.",
    "wof:placetype":"venue"
},
  "geometry": {"coordinates":[-1.178869,47.371174],"type":"Point"}
}