{
  "type": "Feature",
  "properties": {
    "addr:full":"B.P. 30, 67038 Strasbourg C\u00e9dex 2^^Rue Ettore Bugatti - Quartier d'Entreprises, 67200 Eckbolsheim Strasbourg Alsace 67200",
    "addr:postcode":"67038;67200;67200",
    "addr:street":"B.P. 30;Bugatti",
    "iso:country":"FR",
    "sg:address":"B.P. 30, 67038 Strasbourg C\u00e9dex 2^^Rue Ettore Bugatti - Quartier d'Entreprises, 67200 Eckbolsheim",
    "sg:city":"Strasbourg",
    "sg:orig_category":"Non-Classified Establishments",
    "sg:phone":"+33 3 88 78 88 08",
    "sg:postcode":"67200",
    "sg:province":"Alsace",
    "wof:name":"Kwc Robinetterie",
    "wof:placetype":"venue"
},
  "geometry": {"coordinates":[7.685986,48.589954],"type":"Point"}
}