{
  "type": "Feature",
  "properties": {
    "iso:country":"FR",
    "sg:address":"24 r 9 Ao\u00fbt; Plouigneau",
    "sg:classifiers":[
        {
            "category":"Banks & Credit Unions",
            "subcategory":"Bank",
            "type":"Services"
        }
    ],
    "sg:phone":"+33 3398798438",
    "sg:province":"Pays de Loire",
    "wof:name":"Cr\u00e9dit Mutuel De Bretagne",
    "wof:placetype":"venue"
},
  "geometry": {"coordinates":[-3.702236,48.568428],"type":"Point"}
}