{
  "type": "Feature",
  "properties": {
    "addr:full":"Z.A. la Troul\u00e8re Saint Pierre du Mont Aquitaine 40280",
    "addr:postcode":"40280",
    "addr:street":"Z.A. La Troule\u0300Re",
    "iso:country":"FR",
    "sg:address":"Z.A. la Troul\u00e8re",
    "sg:city":"Saint Pierre du Mont",
    "sg:orig_category":"Unclassifiable Establishments",
    "sg:phone":"+33 5 58 05 45 00",
    "sg:postcode":"40280",
    "sg:province":"Aquitaine",
    "wof:name":"Delpeyrat S.a.",
    "wof:placetype":"venue"
},
  "geometry": {"coordinates":[-0.558115,43.826271],"type":"Point"}
}