{
  "type": "Feature",
  "properties": {
    "iso:country":"FR",
    "sg:address":"79 Rue Du Petit Pont 45000 Orl\u00e9ans",
    "sg:city":"Orl\u00e9ans",
    "sg:classifiers":[
        {
            "category":"Professional",
            "subcategory":"Business Services",
            "type":"Services"
        }
    ],
    "sg:phone":"+33 2 38 86 02 51",
    "sg:postcode":"45000",
    "sg:province":"Centre",
    "sg:tags":[
        "training",
        "advice"
    ],
    "wof:name":"A.for.pro.ba Cfa Du Batiment",
    "wof:placetype":"venue"
},
  "geometry": {"coordinates":[1.928643,47.917603],"type":"Point"}
}