{
  "type": "Feature",
  "properties": {
    "addr:full":"B.P. 1281, 25005 Besan\u00e7on C\u00e9dex^^6, Bd Diderot, 25000 Besan\u00e7on Franche Comt\u00e9",
    "addr:housenumber":"1281",
    "addr:postcode":"25005;25000",
    "addr:street":"B.P.;Bd Diderot;Franche Comte\u0301",
    "iso:country":"FR",
    "sg:address":"B.P. 1281, 25005 Besan\u00e7on C\u00e9dex^^6, Bd Diderot, 25000 Besan\u00e7on",
    "sg:orig_category":"Non-Classified Establishments",
    "sg:phone":"+33 3 81 47 92 00",
    "sg:province":"Franche Comt\u00e9",
    "wof:name":"S.n.o. S.a. - Soci\u00e9t\u00e9 Nouvelle Ordicars",
    "wof:placetype":"venue"
},
  "geometry": {"coordinates":[6.025686,47.242317],"type":"Point"}
}