{
  "type": "Feature",
  "properties": {
    "iso:country":"FR",
    "sg:address":"23, Rue du Mouline Bateau, 94387 Bonneuil sur Marne C\u00e9dex",
    "sg:orig_category":"Non-Classified Establishments",
    "sg:phone":"+33 1 43 39 06 33",
    "sg:province":"\u00cele-de-France",
    "wof:name":"Mat\u00e9riel Graphique Moderne S.a.",
    "wof:placetype":"venue"
},
  "geometry": {"coordinates":[2.497618,48.782665],"type":"Point"}
}