{
  "type": "Feature",
  "properties": {
    "iso:country":"FR",
    "sg:address":"B.P. 8, 59190 Ca\u00ebstre^^767, Route de Strazeele, 59190 Ca\u00ebstre",
    "sg:orig_category":"Non-Classified Establishments",
    "sg:phone":"+33 3 28 40 21 56",
    "sg:province":"Nord Pas-de-Calais",
    "wof:name":"Jarbeau S.a.",
    "wof:placetype":"venue"
},
  "geometry": {"coordinates":[2.53621,50.722012],"type":"Point"}
}