{
  "type": "Feature",
  "properties": {
    "iso:country":"FR",
    "sg:address":"33 Rue Assalit 31500 Toulouse",
    "sg:classifiers":[
        {
            "category":"Wholesale",
            "subcategory":"Machinery & Supplies",
            "type":"Manufacturing & Wholesale Goods"
        }
    ],
    "sg:phone":"+33 5 62 16 35 07",
    "sg:postcode":"31500",
    "sg:province":"Midi Pyr\u00e9n\u00e9es",
    "sg:tags":[
        "handling",
        "material",
        "-",
        "machine",
        "equipment",
        "engineering",
        "mechanical"
    ],
    "wof:name":"Ascmer",
    "wof:placetype":"venue"
},
  "geometry": {"coordinates":[1.468291,43.6045],"type":"Point"}
}