{
  "type": "Feature",
  "properties": {
    "iso:country":"FR",
    "sg:address":"114, Av. du Merlan, 13014 Marseille",
    "sg:orig_category":"Unclassifiable Establishments",
    "sg:phone":"+33 4 91 21 66 88",
    "sg:province":"Provence-Alpes-C\u00f4te d'Azur",
    "wof:name":"Le Froid S.a.r.l.",
    "wof:placetype":"venue"
},
  "geometry": {"coordinates":[5.40848,43.343323],"type":"Point"}
}