{
  "type": "Feature",
  "properties": {
    "addr:full":"B.P. 62, 92233 Genevilliers^^97, Rue du Moulin de Cage, 92230 Gennevilliers Ile de France 92230",
    "addr:postcode":"92233;92230;ile;92230",
    "addr:street":"B.P. 62;Rue Du Moulin De Cage;France",
    "iso:country":"FR",
    "sg:address":"B.P. 62, 92233 Genevilliers^^97, Rue du Moulin de Cage, 92230 Gennevilliers",
    "sg:orig_category":"Non-Classified Establishments",
    "sg:phone":"+33 1 40 85 25 25",
    "sg:postcode":"92230",
    "sg:province":"Ile de France",
    "wof:name":"C.a.t. S.a. - Compagnie D'affr\u00eatement Et De Transport",
    "wof:placetype":"venue"
},
  "geometry": {"coordinates":[2.29447,48.925026],"type":"Point"}
}