{
  "type": "Feature",
  "properties": {
    "addr:full":"Rue Jean Loup Chr\u00e9tien - Zone d'Affaires Kennedy Tarbes Midi Pyr\u00e9n\u00e9es 65000",
    "addr:postcode":"65000",
    "addr:street":"Rue Jean Loup Chre\u0301Tien Zone D'Affaires Kennedy",
    "iso:country":"FR",
    "sg:address":"Rue Jean Loup Chr\u00e9tien - Zone d'Affaires Kennedy",
    "sg:city":"Tarbes",
    "sg:orig_category":"Non-Classified Establishments",
    "sg:phone":"+33 5 62 93 07 33",
    "sg:postcode":"65000",
    "sg:province":"Midi Pyr\u00e9n\u00e9es",
    "wof:name":"Cabinet Depond S.a.r.l.",
    "wof:placetype":"venue"
},
  "geometry": {"coordinates":[0.086219,43.216999],"type":"Point"}
}