{
  "type": "Feature",
  "properties": {
    "iso:country":"FR",
    "sg:address":"55, Rue de l'Yser, 59200 Tourcoing",
    "sg:orig_category":"Unclassifiable Establishments",
    "sg:phone":"+33 3 20 46 65 55",
    "sg:province":"Nord Pas-de-Calais",
    "wof:name":"Benasich, S.a.r.l.",
    "wof:placetype":"venue"
},
  "geometry": {"coordinates":[3.167858,50.741756],"type":"Point"}
}