{
  "type": "Feature",
  "properties": {
    "iso:country":"FR",
    "sg:address":"52 Av Des Aur\u00e9ats 26000 Valence",
    "sg:classifiers":[
        {
            "category":"Shopping",
            "type":"Retail Goods"
        }
    ],
    "sg:phone":"+33 4 75 40 12 58",
    "sg:postcode":"26000",
    "sg:province":"Rhone-Alpes",
    "sg:tags":[
        "metallurgy",
        "finished",
        "-",
        "metalworking",
        "metallic"
    ],
    "wof:name":"Froid Et Amenagement Sarl",
    "wof:placetype":"venue"
},
  "geometry": {"coordinates":[4.88438,44.901318],"type":"Point"}
}