{
  "type": "Feature",
  "properties": {
    "iso:country":"FR",
    "sg:address":"b\u00e2t",
    "sg:city":"Danemark Actipole BP 602 13127 Vitrolles",
    "sg:classifiers":[
        {
            "category":"Manufacturing",
            "subcategory":"Tools & Machinery",
            "type":"Manufacturing & Wholesale Goods"
        }
    ],
    "sg:phone":"+33 4 42 89 36 88",
    "sg:province":"Centre",
    "sg:tags":[
        "equipment",
        "measurement",
        "-",
        "precision",
        "instrument"
    ],
    "wof:name":"Laboratoires Services Diagnostics",
    "wof:placetype":"venue"
},
  "geometry": {"coordinates":[5.25892,43.424545],"type":"Point"}
}