{
  "type": "Feature",
  "properties": {
    "addr:full":"Les Quatre Nations 44360 Vigneux De Bretagne Pays de Loire 44360",
    "addr:postcode":"44360;44360",
    "iso:country":"FR",
    "sg:address":"Les Quatre Nations 44360 Vigneux De Bretagne",
    "sg:classifiers":[
        {
            "category":"Manufacturing",
            "subcategory":"Metals",
            "type":"Manufacturing & Wholesale Goods"
        }
    ],
    "sg:phone":"+33 2 40 57 34 10",
    "sg:postcode":"44360",
    "sg:province":"Pays de Loire",
    "sg:tags":[
        "-",
        "machine",
        "equipment",
        "engineering",
        "machinery",
        "mechanical"
    ],
    "wof:name":"Astec Sa",
    "wof:placetype":"venue"
},
  "geometry": {"coordinates":[-1.75054,47.300831],"type":"Point"}
}