{
  "type": "Feature",
  "properties": {
    "addr:full":"B.P. 715, 15007 Aurillac C\u00e9dex^^19, Rue Gutemberg, 15000 Aurillac Aurillac Auvergne 15000",
    "addr:housenumber":"b.p. 715",
    "addr:postcode":"15007;15000;15000",
    "addr:street":"Rue Gutemberg",
    "iso:country":"FR",
    "sg:address":"B.P. 715, 15007 Aurillac C\u00e9dex^^19, Rue Gutemberg, 15000 Aurillac",
    "sg:city":"Aurillac",
    "sg:orig_category":"Non-Classified Establishments",
    "sg:phone":"+33 4 71 63 46 90",
    "sg:postcode":"15000",
    "sg:province":"Auvergne",
    "wof:name":"Entreprise Demaison S.a.",
    "wof:placetype":"venue"
},
  "geometry": {"coordinates":[2.445125,44.927765],"type":"Point"}
}