{
  "type": "Feature",
  "properties": {
    "addr:full":"All De Coat A Noz 35135 Chantepie Chantepie Bretagne 35135",
    "addr:postcode":"35135;35135",
    "iso:country":"FR",
    "sg:address":"All De Coat A Noz 35135 Chantepie",
    "sg:city":"Chantepie",
    "sg:classifiers":[
        {
            "category":"Shopping",
            "subcategory":"Bicycles & Sporting Goods",
            "type":"Retail Goods"
        }
    ],
    "sg:phone":"+33 2 99 26 04 26",
    "sg:postcode":"35135",
    "sg:province":"Bretagne",
    "sg:tags":[
        "product",
        "sport",
        "miscellaneous"
    ],
    "wof:name":"Super Sport Sa",
    "wof:placetype":"venue"
},
  "geometry": {"coordinates":[-1.628344,48.085186],"type":"Point"}
}