{
  "type": "Feature",
  "properties": {
    "addr:full":"23 rue Louis le Grand; Paris; 75002 Ile de France 75002",
    "addr:housenumber":"23",
    "addr:postcode":"75002;75002",
    "addr:street":"Rue Louis Le Grand Paris;France",
    "iso:country":"FR",
    "sg:address":"23 rue Louis le Grand; Paris; 75002",
    "sg:classifiers":[
        {
            "category":"Banks & Credit Unions",
            "subcategory":"Bank",
            "type":"Services"
        }
    ],
    "sg:phone":"+33 1 47 42 06 30",
    "sg:postcode":"75002",
    "sg:province":"Ile de France",
    "wof:name":"Uniao De Bancos Portugueses",
    "wof:placetype":"venue"
},
  "geometry": {"coordinates":[2.333734,48.870373],"type":"Point"}
}