{
  "type": "Feature",
  "properties": {
    "addr:full":"Chemin D\u00e9partementale 80 Lachelle Picardie 60190",
    "addr:postcode":"60190",
    "addr:street":"Chemin De\u0301Partementale 80;Picardie",
    "iso:country":"FR",
    "sg:address":"Chemin D\u00e9partementale 80",
    "sg:city":"Lachelle",
    "sg:orig_category":"Unclassifiable Establishments",
    "sg:phone":"+33 3 44 42 04 88",
    "sg:postcode":"60190",
    "sg:province":"Picardie",
    "wof:name":"Crefaco S.a.r.l.",
    "wof:placetype":"venue"
},
  "geometry": {"coordinates":[2.6372,49.425014],"type":"Point"}
}