{
  "type": "Feature",
  "properties": {
    "addr:full":"67, Rue des Vignes - ZA de Marcilly en Villette, 45240 Marcilly en Villette La Fert\u00e9-Saint-Aubin Centre 45240",
    "addr:housenumber":"67",
    "addr:postcode":"45240;45240",
    "addr:street":"Rue Des Vignes Za De Marcilly En Villette",
    "iso:country":"FR",
    "sg:address":"67, Rue des Vignes - ZA de Marcilly en Villette, 45240 Marcilly en Villette",
    "sg:city":"La Fert\u00e9-Saint-Aubin",
    "sg:orig_category":"Non-Classified Establishments",
    "sg:phone":"+33 2 38 76 12 00",
    "sg:postcode":"45240",
    "sg:province":"Centre",
    "wof:name":"Triax S.a.r.l.",
    "wof:placetype":"venue"
},
  "geometry": {"coordinates":[1.78052,47.683125],"type":"Point"}
}