{
  "type": "Feature",
  "properties": {
    "addr:full":"43300 Siaugues Sainte Marie Chanteuges Auvergne 43300",
    "addr:postcode":"43300;43300",
    "addr:street":"Chanteuges",
    "iso:country":"FR",
    "sg:address":"43300 Siaugues Sainte Marie",
    "sg:city":"Chanteuges",
    "sg:orig_category":"Unclassifiable Establishments",
    "sg:phone":"+33 4 71 74 29 27",
    "sg:postcode":"43300",
    "sg:province":"Auvergne",
    "wof:name":"P.e.m. S.a.s.",
    "wof:placetype":"venue"
},
  "geometry": {"coordinates":[3.632503,45.0937],"type":"Point"}
}