{
  "type": "Feature",
  "properties": {
    "iso:country":"FR",
    "sg:address":"B.P. 395, 60312 Creil C\u00e9dex^^175, Rue Jean Jaur\u00e8s, 60100 Creil",
    "sg:orig_category":"Non-Classified Establishments",
    "sg:phone":"+33 3 44 28 06 07",
    "sg:province":"Picardie",
    "wof:name":"Magasins G\u00e9n\u00e9raux De France",
    "wof:placetype":"venue"
},
  "geometry": {"coordinates":[2.47547,49.259537],"type":"Point"}
}