{
  "type": "Feature",
  "properties": {
    "addr:full":"9, Bd de l'Oc\u00e9an, 33120 Arcachon Arcachon Aquitaine 33120",
    "addr:housenumber":"9",
    "addr:postcode":"33120;33120",
    "addr:street":"Bd De L'Oce \u0301An",
    "iso:country":"FR",
    "sg:address":"9, Bd de l'Oc\u00e9an, 33120 Arcachon",
    "sg:city":"Arcachon",
    "sg:orig_category":"Non-Classified Establishments",
    "sg:phone":"+33 5 56 83 03 75",
    "sg:postcode":"33120",
    "sg:province":"Aquitaine",
    "wof:name":"Les Vagues Et Aquamarina",
    "wof:placetype":"venue"
},
  "geometry": {"coordinates":[-1.185094,44.662041],"type":"Point"}
}