{
  "type": "Feature",
  "properties": {
    "addr:full":"B.P. 52, 92105 Boulogne Billancourt C\u00e9dex^^73/77, Rue de S\u00e8vres, 92100 Boulogne Billancourt Ile de France 92100",
    "addr:housenumber":"77",
    "addr:postcode":"92105;92100;92100",
    "addr:street":"B.P. 52;Rue De Se\u0300Vres",
    "iso:country":"FR",
    "sg:address":"B.P. 52, 92105 Boulogne Billancourt C\u00e9dex^^73/77, Rue de S\u00e8vres, 92100 Boulogne Billancourt",
    "sg:orig_category":"Non-Classified Establishments",
    "sg:phone":"+33 1 41 10 06 10",
    "sg:postcode":"92100",
    "sg:province":"Ile de France",
    "wof:name":"E.m.s. - Chemie France S.a.",
    "wof:placetype":"venue"
},
  "geometry": {"coordinates":[2.24102,48.835155],"type":"Point"}
}