{
  "type": "Feature",
  "properties": {
    "addr:full":"56, Chemin des Meuniers, 78200 Buchelay Ile de France",
    "addr:housenumber":"56",
    "addr:postcode":"78200",
    "addr:street":"Chemin Des Meuniers;Ile De France",
    "iso:country":"FR",
    "sg:address":"56, Chemin des Meuniers, 78200 Buchelay",
    "sg:orig_category":"Non-Classified Establishments",
    "sg:phone":"+33 1 30 92 22 90",
    "sg:province":"Ile de France",
    "wof:name":"M.p.i. S.a. - Mantes Poudrage Industries",
    "wof:placetype":"venue"
},
  "geometry": {"coordinates":[1.692406,48.987797],"type":"Point"}
}