{
  "type": "Feature",
  "properties": {
    "addr:full":"11, Rue de la Roche, 29870 Lannilis Lannilis Bretagne 29870",
    "addr:housenumber":"11",
    "addr:postcode":"29870;29870",
    "addr:street":"Rue De La Roche;Lannilis",
    "iso:country":"FR",
    "sg:address":"11, Rue de la Roche, 29870 Lannilis",
    "sg:city":"Lannilis",
    "sg:orig_category":"Unclassifiable Establishments",
    "sg:phone":"+33 2 98 04 02 39",
    "sg:postcode":"29870",
    "sg:province":"Bretagne",
    "wof:name":"Tanguy Bois Mat\u00e9riaux S.a.",
    "wof:placetype":"venue"
},
  "geometry": {"coordinates":[-4.52568,48.572346],"type":"Point"}
}