{
  "type": "Feature",
  "properties": {
    "iso:country":"FR",
    "sg:address":"17, Rue Eug\u00e8ne Delacroix, 75016 Paris",
    "sg:orig_category":"Non-Classified Establishments",
    "sg:phone":"+33 1 45 04 84 13",
    "sg:province":"Ile de France",
    "wof:name":"M\u00e9tabap S.a.",
    "wof:placetype":"venue"
},
  "geometry": {"coordinates":[2.277881,48.862514],"type":"Point"}
}