{
  "type": "Feature",
  "properties": {
    "addr:full":"3 rue Pierre Curie 91230 Montgeron Ile de France 91230",
    "addr:housenumber":"3",
    "addr:postcode":"91230;ile;91230",
    "addr:street":"Rue Pierre Curie;France",
    "iso:country":"FR",
    "sg:address":"3 rue Pierre Curie 91230 Montgeron",
    "sg:classifiers":[
        {
            "category":"Building & Trades",
            "subcategory":"Electrical",
            "type":"Services"
        }
    ],
    "sg:phone":"+33 1 69 52 47 00",
    "sg:postcode":"91230",
    "sg:province":"Ile de France",
    "sg:tags":[
        "drying",
        "cabinets",
        "electric"
    ],
    "wof:name":"Ste Automatismes Seguin S.a.",
    "wof:placetype":"venue"
},
  "geometry": {"coordinates":[2.439013,48.707344],"type":"Point"}
}