{
  "type": "Feature",
  "properties": {
    "addr:full":"3, Rue Emile Zola, 60110 M\u00e9ru Picardie 60110",
    "addr:housenumber":"3",
    "addr:postcode":"60110;60110",
    "addr:street":"Rue Emile Zola",
    "iso:country":"FR",
    "sg:address":"3, Rue Emile Zola, 60110 M\u00e9ru",
    "sg:orig_category":"Non-Classified Establishments",
    "sg:phone":"+33 3 44 52 66 00",
    "sg:postcode":"60110",
    "sg:province":"Picardie",
    "wof:name":"Auxilec S.a.",
    "wof:placetype":"venue"
},
  "geometry": {"coordinates":[2.13602,49.221191],"type":"Point"}
}