{
  "type": "Feature",
  "properties": {
    "addr:full":"Zi Richard Bloch 69700 Chassagny Rhone-Alpes 69700",
    "addr:postcode":"69700;69700",
    "addr:street":"Rhone-Alpes",
    "iso:country":"FR",
    "sg:address":"Zi Richard Bloch 69700 Chassagny",
    "sg:classifiers":[
        {
            "category":"Professional",
            "subcategory":"Engineering",
            "type":"Services"
        }
    ],
    "sg:phone":"+33 4 78 48 75 33",
    "sg:postcode":"69700",
    "sg:province":"Rhone-Alpes",
    "sg:tags":[
        "machine",
        "-",
        "mechanical"
    ],
    "wof:name":"Neofeu Sa",
    "wof:placetype":"venue"
},
  "geometry": {"coordinates":[4.73243,45.60619],"type":"Point"}
}