{
  "type": "Feature",
  "properties": {
    "addr:full":"Zi Des Erables 61130 Bell\u00eame Bell\u00eame Basse Normandie 61130",
    "addr:postcode":"61130;61130",
    "addr:street":"Des Erables",
    "iso:country":"FR",
    "sg:address":"Zi Des Erables 61130 Bell\u00eame",
    "sg:city":"Bell\u00eame",
    "sg:classifiers":[
        {
            "category":"Shopping",
            "subcategory":"Computers & Home Electronics",
            "type":"Retail Goods"
        }
    ],
    "sg:phone":"+33 2 33 83 25 53",
    "sg:postcode":"61130",
    "sg:province":"Basse Normandie",
    "sg:tags":[
        "equipment",
        "electrical",
        "component",
        "electric",
        "electronic"
    ],
    "wof:name":"Cig (circuits Imprimes) Sa",
    "wof:placetype":"venue"
},
  "geometry": {"coordinates":[0.564318,48.375156],"type":"Point"}
}