{
  "type": "Feature",
  "properties": {
    "addr:full":"6 Cs De Verdun BP 201 Zi Nord Sous Tamas 01106 Oyonnax Midi Pyr\u00e9n\u00e9es",
    "addr:housenumber":"bp 201",
    "addr:postcode":"01106",
    "addr:street":"Cs De Verdun;Zi Nord Sous Tamas",
    "iso:country":"FR",
    "sg:address":"6 Cs De Verdun BP 201 Zi Nord Sous Tamas 01106 Oyonnax",
    "sg:classifiers":[
        {
            "category":"Manufacturing",
            "subcategory":"Rubber & Plastics",
            "type":"Manufacturing & Wholesale Goods"
        }
    ],
    "sg:phone":"+33 4 74 77 90 57",
    "sg:province":"Midi Pyr\u00e9n\u00e9es",
    "wof:name":"Vernicolor",
    "wof:placetype":"venue"
},
  "geometry": {"coordinates":[5.658239,46.259094],"type":"Point"}
}