{
  "type": "Feature",
  "properties": {
    "addr:full":"15, Rue Jacques Cartier, 41100 Saint Ouen Lisle Centre 41100",
    "addr:housenumber":"15",
    "addr:postcode":"41100;41100",
    "addr:street":"Rue Jacques Cartier",
    "iso:country":"FR",
    "sg:address":"15, Rue Jacques Cartier, 41100 Saint Ouen",
    "sg:city":"Lisle",
    "sg:orig_category":"Non-Classified Establishments",
    "sg:phone":"+33 2 54 77 34 33",
    "sg:postcode":"41100",
    "sg:province":"Centre",
    "wof:name":"C.m.a. Bigmat S.a. - Soci\u00e9te Des Chaux Et Mat\u00e9riaux D'amboise",
    "wof:placetype":"venue"
},
  "geometry": {"coordinates":[1.068651,47.81031],"type":"Point"}
}