{
  "type": "Feature",
  "properties": {
    "addr:full":"5 Rue Des Papetiers 27500 Pont Audemer Haute Normandie",
    "addr:housenumber":"5",
    "addr:postcode":"27500",
    "addr:street":"Rue Des Papetiers;Audemer Haute Normandie",
    "iso:country":"FR",
    "sg:address":"5 Rue Des Papetiers 27500 Pont Audemer",
    "sg:classifiers":[
        {
            "category":"Communications",
            "subcategory":"Newspaper",
            "type":"Services"
        }
    ],
    "sg:phone":"+33 2 32 41 69 70",
    "sg:province":"Haute Normandie",
    "sg:tags":[
        "material",
        "-",
        "packaging",
        "raw",
        "paper",
        "cardboard"
    ],
    "wof:name":"Communaute De Communes De Pont Audemer",
    "wof:placetype":"venue"
},
  "geometry": {"coordinates":[0.509027,49.356693],"type":"Point"}
}