{
  "type": "Feature",
  "properties": {
    "addr:full":"11, Rue Degas, 75016 Paris Ile de France",
    "addr:housenumber":"11",
    "addr:postcode":"75016",
    "addr:street":"Rue Degas",
    "iso:country":"FR",
    "sg:address":"11, Rue Degas, 75016 Paris",
    "sg:orig_category":"Unclassifiable Establishments",
    "sg:phone":"+33 1 40 50 07 22",
    "sg:province":"Ile de France",
    "wof:name":"G.b.c. S.a.",
    "wof:placetype":"venue"
},
  "geometry": {"coordinates":[2.274024,48.848892],"type":"Point"}
}