{
  "type": "Feature",
  "properties": {
    "iso:country":"FR",
    "sg:address":"B.P. 32, 63306 Thiers C\u00e9dex^^110, Av. L\u00e9o Lagrange, 63300 Thiers",
    "sg:city":"Thiers",
    "sg:orig_category":"Non-Classified Establishments",
    "sg:phone":"+33 4 73 80 20 69",
    "sg:postcode":"63300",
    "sg:province":"Auvergne",
    "wof:name":"Arno Industrie S.a.r.l.",
    "wof:placetype":"venue"
},
  "geometry": {"coordinates":[3.563396,45.82058],"type":"Point"}
}