{
  "type": "Feature",
  "properties": {
    "addr:full":"Rte de Commelinges Allinges Rhone-Alpes 74200",
    "addr:postcode":"74200",
    "addr:street":"Rte De Commelinges;Rhone-Alpes",
    "iso:country":"FR",
    "sg:address":"Rte de Commelinges",
    "sg:city":"Allinges",
    "sg:orig_category":"Unclassifiable Establishments",
    "sg:phone":"+33 4 50 71 21 45",
    "sg:postcode":"74200",
    "sg:province":"Rhone-Alpes",
    "wof:name":"E.i.b. S.a.r.l. - Electricit\u00e9 Industrielle Du B\u00e2timent",
    "wof:placetype":"venue"
},
  "geometry": {"coordinates":[6.462285,46.334644],"type":"Point"}
}