{
  "type": "Feature",
  "properties": {
    "iso:country":"FR",
    "sg:address":"1, Rte de Mardyck - P.A.E. du Pont de Spycker, 59380 Spycker",
    "sg:orig_category":"Unclassifiable Establishments",
    "sg:phone":"+33 3 28 28 90 09",
    "sg:province":"Nord Pas-de-Calais",
    "wof:name":"Littoral Service S.a.",
    "wof:placetype":"venue"
},
  "geometry": {"coordinates":[2.493145,50.976814],"type":"Point"}
}