{
  "type": "Feature",
  "properties": {
    "addr:full":"413 avenue Robert Brun 83500 La Seyne sur Mer Provence-Alpes-C\u00f4te d'Azur",
    "addr:housenumber":"413",
    "addr:postcode":"83500",
    "addr:street":"Avenue Robert Brun;Seyne;Mer",
    "iso:country":"FR",
    "sg:address":"413 avenue Robert Brun 83500 La Seyne sur Mer",
    "sg:classifiers":[
        {
            "category":"Utilities",
            "subcategory":"Electric",
            "type":"Services"
        }
    ],
    "sg:phone":"+33 4 94 87 07 77",
    "sg:province":"Provence-Alpes-C\u00f4te d'Azur",
    "sg:tags":[
        "switching",
        "system"
    ],
    "wof:name":"Bilbo Marine Technique Industrie Sa",
    "wof:placetype":"venue"
},
  "geometry": {"coordinates":[5.87283,43.116302],"type":"Point"}
}