{
  "type": "Feature",
  "properties": {
    "iso:country":"FR",
    "sg:address":"339 Rue Andr\u00e9 Amp\u00e8re 77190 Dammarie Les Lys",
    "sg:classifiers":[
        {
            "category":"Building & Trades",
            "subcategory":"Construction",
            "type":"Services"
        }
    ],
    "sg:phone":"+33 1 64 10 40 80",
    "sg:postcode":"77190",
    "sg:province":"Ile de France",
    "sg:tags":[
        "work",
        "public"
    ],
    "wof:name":"Roland",
    "wof:placetype":"venue"
},
  "geometry": {"coordinates":[2.609499,48.511951],"type":"Point"}
}