{
  "type": "Feature",
  "properties": {
    "addr:full":"339 Rue Andr\u00e9 Amp\u00e8re 77190 Dammarie Les Lys Ile de France 77190",
    "addr:housenumber":"339",
    "addr:postcode":"77190;77190",
    "addr:street":"Rue Andre\u0301 Ampe\u0300Re",
    "iso:country":"FR",
    "sg:address":"339 Rue Andr\u00e9 Amp\u00e8re 77190 Dammarie Les Lys",
    "sg:classifiers":[
        {
            "category":"Building & Trades",
            "subcategory":"Construction",
            "type":"Services"
        }
    ],
    "sg:phone":"+33 1 64 10 40 80",
    "sg:postcode":"77190",
    "sg:province":"Ile de France",
    "sg:tags":[
        "work",
        "public"
    ],
    "wof:name":"Roland",
    "wof:placetype":"venue"
},
  "geometry": {"coordinates":[2.609499,48.511951],"type":"Point"}
}