{
  "type": "Feature",
  "properties": {
    "addr:full":"Le Bourg 69220 Lancie Rhone-Alpes 69220",
    "addr:postcode":"69220;69220",
    "addr:street":"Le Bourg;Rhone-Alpes",
    "iso:country":"FR",
    "sg:address":"Le Bourg 69220 Lancie",
    "sg:classifiers":[
        {
            "category":"Wholesale",
            "subcategory":"Wine & Distilled Alcoholic Beverages",
            "type":"Manufacturing & Wholesale Goods"
        }
    ],
    "sg:phone":"+33 4 74 04 17 00",
    "sg:postcode":"69220",
    "sg:province":"Rhone-Alpes",
    "sg:tags":[
        "french"
    ],
    "wof:name":"Savour Club Selection Sa",
    "wof:placetype":"venue"
},
  "geometry": {"coordinates":[4.678782,46.0886],"type":"Point"}
}