{
  "type": "Feature",
  "properties": {
    "iso:country":"FR",
    "sg:address":"Lot. de la Clause n\u00b015",
    "sg:city":"Trausse",
    "sg:orig_category":"Non-Classified Establishments",
    "sg:phone":"+33 4 68 78 34 10",
    "sg:postcode":"11160",
    "sg:province":"Languedoc-Roussillon",
    "wof:name":"Fabrie Champignons S.a.r.l.",
    "wof:placetype":"venue"
},
  "geometry": {"coordinates":[2.586085,43.282204],"type":"Point"}
}