{
  "type": "Feature",
  "properties": {
    "iso:country":"FR",
    "sg:address":"B.P. 187, 62004 Arras C\u00e9dex^^30, Rue No\u00ebl Trannin, 62000 Arras",
    "sg:orig_category":"Non-Classified Establishments",
    "sg:phone":"+33 3 21 55 43 58",
    "sg:province":"Nord Pas-de-Calais",
    "wof:name":"Triboulet Jacques",
    "wof:placetype":"venue"
},
  "geometry": {"coordinates":[2.77891,50.290989],"type":"Point"}
}