{
  "type": "Feature",
  "properties": {
    "addr:full":"B.P. 312, 29413 Landerneau C\u00e9dex^^ZI de Lannuzel, 29460 Dirinon Dirinon Bretagne 29460",
    "addr:housenumber":"b.p. 312",
    "addr:postcode":"29413;29460;29460",
    "addr:street":"Lannuzel;Dirinon",
    "iso:country":"FR",
    "sg:address":"B.P. 312, 29413 Landerneau C\u00e9dex^^ZI de Lannuzel, 29460 Dirinon",
    "sg:city":"Dirinon",
    "sg:orig_category":"Non-Classified Establishments",
    "sg:phone":"+33 2 98 07 31 50",
    "sg:postcode":"29460",
    "sg:province":"Bretagne",
    "wof:name":"S.r.3.m. S.a.r.l.",
    "wof:placetype":"venue"
},
  "geometry": {"coordinates":[-4.160824,48.327675],"type":"Point"}
}