{
  "type": "Feature",
  "properties": {
    "addr:full":"Rue Du Flottage 60350 Trosly Breuil Picardie 60350",
    "addr:postcode":"60350;60350",
    "addr:street":"Rue Du Flottage",
    "iso:country":"FR",
    "sg:address":"Rue Du Flottage 60350 Trosly Breuil",
    "sg:classifiers":[
        {
            "category":"Manufacturing",
            "subcategory":"Chemicals & Compounds",
            "type":"Manufacturing & Wholesale Goods"
        }
    ],
    "sg:phone":"+33 3 44 85 40 00",
    "sg:postcode":"60350",
    "sg:province":"Picardie",
    "sg:tags":[
        "pharmaceutical",
        "chemistry",
        "-",
        "by-product"
    ],
    "wof:name":"Clariant France",
    "wof:placetype":"venue"
},
  "geometry": {"coordinates":[3.000505,49.40406],"type":"Point"}
}