{
  "type": "Feature",
  "properties": {
    "addr:full":"12 Route De Montargis 89309 JOIGNY CEDEX Rhone-Alpes",
    "addr:housenumber":"12",
    "addr:postcode":"89309 joigny cedex rhone-alpes",
    "addr:street":"Route De Montargis",
    "iso:country":"FR",
    "sg:address":"12 Route De Montargis 89309 JOIGNY CEDEX",
    "sg:classifiers":[
        {
            "category":"Farming",
            "subcategory":"Berry Farm",
            "type":"Manufacturing & Wholesale Goods"
        }
    ],
    "sg:phone":"+33 3 86 19 31 31",
    "sg:province":"Rhone-Alpes",
    "sg:tags":[
        "preserve"
    ],
    "wof:name":"Efirack Sa",
    "wof:placetype":"venue"
},
  "geometry": {"coordinates":[3.38588,47.97765],"type":"Point"}
}