{
  "type": "Feature",
  "properties": {
    "addr:full":"A\u00e9roport De M\u00e9rignac 33700 M\u00e9rignac M\u00e9rignac Aquitaine 33700",
    "addr:postcode":"33700;33700",
    "iso:country":"FR",
    "sg:address":"A\u00e9roport De M\u00e9rignac 33700 M\u00e9rignac",
    "sg:city":"M\u00e9rignac",
    "sg:classifiers":[
        {
            "category":"Airport",
            "type":"Transportation"
        }
    ],
    "sg:phone":"+33 5 57 92 50 70",
    "sg:postcode":"33700",
    "sg:province":"Aquitaine",
    "sg:tags":[
        "transport",
        "air"
    ],
    "wof:name":"Geodis Overseas France",
    "wof:placetype":"venue"
},
  "geometry": {"coordinates":[-0.70278,44.82909],"type":"Point"}
}