{
  "type": "Feature",
  "properties": {
    "addr:full":"79 Av De La R\u00e9publique 46130 Biars Sur C\u00e8re Midi Pyr\u00e9n\u00e9es 46130",
    "addr:postcode":"46130;46130",
    "addr:street":"79 Av De La Re\u0301Publique",
    "iso:country":"FR",
    "sg:address":"79 Av De La R\u00e9publique 46130 Biars Sur C\u00e8re",
    "sg:classifiers":[
        {
            "category":"Food & Beverages",
            "subcategory":"Fruits & Vegetables",
            "type":"Retail Goods"
        }
    ],
    "sg:phone":"+33 5 65 38 43 88",
    "sg:postcode":"46130",
    "sg:province":"Midi Pyr\u00e9n\u00e9es",
    "sg:tags":[
        "preserve",
        "product",
        "related"
    ],
    "wof:name":"Ets Boy Sarl",
    "wof:placetype":"venue"
},
  "geometry": {"coordinates":[1.839116,44.917339],"type":"Point"}
}