{
  "type": "Feature",
  "properties": {
    "iso:country":"FR",
    "sg:address":"65 Rue Du Petit Gigognan Zi De Courtine 84000 Avignon",
    "sg:classifiers":[
        {
            "category":"Professional",
            "subcategory":"Advertising",
            "type":"Services"
        }
    ],
    "sg:phone":"+33 4 90 80 73 73",
    "sg:province":"Franche Comt\u00e9",
    "sg:tags":[
        "information",
        "medium",
        "communication"
    ],
    "wof:name":"Dauphin Affichage",
    "wof:placetype":"venue"
},
  "geometry": {"coordinates":[4.806015,43.948753],"type":"Point"}
}