{
  "type": "Feature",
  "properties": {
    "addr:full":"166 Rue De Paris 59800 Lille Nord Pas-de-Calais 59800",
    "addr:housenumber":"166",
    "addr:postcode":"59800;59800",
    "addr:street":"Rue De Paris",
    "iso:country":"FR",
    "sg:address":"166 Rue De Paris 59800 Lille",
    "sg:classifiers":[
        {
            "category":"Banks & Credit Unions",
            "subcategory":"Financial Services",
            "type":"Services"
        }
    ],
    "sg:phone":"+33 3 20 14 54 20",
    "sg:postcode":"59800",
    "sg:province":"Nord Pas-de-Calais",
    "sg:tags":[
        "banking",
        "insurance",
        "institution",
        "finance"
    ],
    "wof:name":"Aref Btp",
    "wof:placetype":"venue"
},
  "geometry": {"coordinates":[3.067944,50.632202],"type":"Point"}
}