{
  "type": "Feature",
  "properties": {
    "iso:country":"FR",
    "sg:address":"7, Av. Georges V, 75008 Paris",
    "sg:orig_category":"Non-Classified Establishments",
    "sg:phone":"+33 1 56 62 64 00",
    "sg:province":"Ile de France",
    "wof:name":"Yves Saint Laurent S.a.s.",
    "wof:placetype":"venue"
},
  "geometry": {"coordinates":[2.301032,48.86554],"type":"Point"}
}