{
  "type": "Feature",
  "properties": {
    "addr:full":"25 Rue Du Moulin De La Cane 45300 Pithiviers Courcelles Centre 45300",
    "addr:housenumber":"25",
    "addr:postcode":"45300;45300",
    "addr:street":"Rue Du Moulin De La Cane;Courcelles",
    "iso:country":"FR",
    "sg:address":"25 Rue Du Moulin De La Cane 45300 Pithiviers",
    "sg:city":"Courcelles",
    "sg:classifiers":[
        {
            "category":"Wholesale",
            "subcategory":"Drugs",
            "type":"Manufacturing & Wholesale Goods"
        }
    ],
    "sg:phone":"+33 2 38 06 20 00",
    "sg:postcode":"45300",
    "sg:province":"Centre",
    "sg:tags":[
        "chemical",
        "pharmaceutical"
    ],
    "wof:name":"Merck Sante",
    "wof:placetype":"venue"
},
  "geometry": {"coordinates":[2.24573,48.181011],"type":"Point"}
}