{
  "type": "Feature",
  "properties": {
    "addr:full":"Ch\u00e2teau Talbot 33250 Saint Julien Beychevelle Cissac-M\u00e9doc Aquitaine 33250",
    "addr:housenumber":"cissac-me\u0301doc",
    "addr:postcode":"33250;33250",
    "addr:street":"Saint",
    "iso:country":"FR",
    "sg:address":"Ch\u00e2teau Talbot 33250 Saint Julien Beychevelle",
    "sg:city":"Cissac-M\u00e9doc",
    "sg:orig_category":"Non-Classified Establishments",
    "sg:phone":"+33 5 56 73 21 50",
    "sg:postcode":"33250",
    "sg:province":"Aquitaine",
    "wof:name":"C.g.w. S.a.",
    "wof:placetype":"venue"
},
  "geometry": {"coordinates":[-0.74175,45.165821],"type":"Point"}
}