{
  "type": "Feature",
  "properties": {
    "iso:country":"FR",
    "sg:address":"50, Rue du G\u00e9n\u00e9ral Delestraint - ZI, 77000 Vaux le P\u00e9nil",
    "sg:orig_category":"Unclassifiable Establishments",
    "sg:phone":"+33 1 64 39 59 39",
    "sg:province":"Ile de France",
    "wof:name":"Pr\u00e9cia Molen Services S.a.",
    "wof:placetype":"venue"
},
  "geometry": {"coordinates":[2.664085,48.539577],"type":"Point"}
}