{
  "type": "Feature",
  "properties": {
    "addr:full":"ZI - Centre de Fr\u00eat Mouguerre Aquitaine 64990",
    "addr:postcode":"64990",
    "iso:country":"FR",
    "sg:address":"ZI - Centre de Fr\u00eat",
    "sg:city":"Mouguerre",
    "sg:orig_category":"Unclassifiable Establishments",
    "sg:phone":"+33 5 59 31 69 00",
    "sg:postcode":"64990",
    "sg:province":"Aquitaine",
    "wof:name":"Laussuy Messagerie S.a.",
    "wof:placetype":"venue"
},
  "geometry": {"coordinates":[-1.417994,43.467365],"type":"Point"}
}