{
  "type": "Feature",
  "properties": {
    "addr:full":"Les Echavagnes 38160 St Marcellin Rhone-Alpes",
    "addr:housenumber":"38160",
    "addr:street":"St Marcellin Rhone-Alpes",
    "iso:country":"FR",
    "sg:address":"Les Echavagnes 38160 St Marcellin",
    "sg:classifiers":[
        {
            "category":"Manufacturing",
            "subcategory":"Rubber & Plastics",
            "type":"Manufacturing & Wholesale Goods"
        }
    ],
    "sg:phone":"+33 4 76 64 92 98",
    "sg:province":"Rhone-Alpes",
    "wof:name":"Itw Fastex France",
    "wof:placetype":"venue"
},
  "geometry": {"coordinates":[5.327735,45.141499],"type":"Point"}
}