{
  "type": "Feature",
  "properties": {
    "addr:full":"1, rue de l'Industrie, 78210 Saint Cyr l'Ecole Ile de France",
    "addr:housenumber":"1",
    "addr:postcode":"78210;ile",
    "addr:street":"Rue De L'Industrie",
    "iso:country":"FR",
    "sg:address":"1, rue de l'Industrie, 78210 Saint Cyr l'Ecole",
    "sg:orig_category":"Non-Classified Establishments",
    "sg:phone":"+33 1 30 58 47 34",
    "sg:province":"Ile de France",
    "wof:name":"Proengin S.a.",
    "wof:placetype":"venue"
},
  "geometry": {"coordinates":[-98.461052,29.39657],"type":"Point"}
}