{
  "type": "Feature",
  "properties": {
    "addr:full":"rue I et F Joliot Curie 34420 Villeneuve Les Beziers Languedoc-Roussillon 34420",
    "addr:postcode":"34420;34420",
    "addr:street":"Rue I Et F Joliot Curie;Beziers",
    "iso:country":"FR",
    "sg:address":"rue I et F Joliot Curie 34420 Villeneuve Les Beziers",
    "sg:classifiers":[
        {
            "category":"Train Station",
            "subcategory":"Light Rail",
            "type":"Transportation"
        }
    ],
    "sg:phone":"+33 4 67 35 20 02",
    "sg:postcode":"34420",
    "sg:province":"Languedoc-Roussillon",
    "sg:tags":[
        "luminous",
        "sign"
    ],
    "wof:name":"Syst\u00e8mes Information Communication Sa",
    "wof:placetype":"venue"
},
  "geometry": {"coordinates":[3.334264,43.303394],"type":"Point"}
}