{
  "type": "Feature",
  "properties": {
    "iso:country":"FR",
    "sg:address":"B.P. 14, 38470 Vinay^^6, Rue du Moulin, 38470 Vinay",
    "sg:orig_category":"Non-Classified Establishments",
    "sg:phone":"+33 4 76 36 70 86",
    "sg:postcode":"38470",
    "sg:province":"Rhone-Alpes",
    "wof:name":"Gu\u00e9ripel S.a.",
    "wof:placetype":"venue"
},
  "geometry": {"coordinates":[5.438091,45.147182],"type":"Point"}
}