{
  "type": "Feature",
  "properties": {
    "addr:full":"Chem De L'Aumone Vieille Parc De L'Angevini\u00e8re 13400 Aubagne Centre",
    "addr:postcode":"13400",
    "addr:street":"Chem De L'Aumone Vieille Parc De L'Angevinie \u0300Re",
    "iso:country":"FR",
    "sg:address":"Chem De L'Aumone Vieille Parc De L'Angevini\u00e8re 13400 Aubagne",
    "sg:classifiers":[
        {
            "category":"Shopping",
            "subcategory":"Stationery & Office Supplies",
            "type":"Retail Goods"
        }
    ],
    "sg:phone":"+33 4 91 27 04 70",
    "sg:province":"Centre",
    "sg:tags":[
        "information",
        "technology",
        "telecommunication",
        "equipment"
    ],
    "wof:name":"Riso France Sa",
    "wof:placetype":"venue"
},
  "geometry": {"coordinates":[5.521601,43.285622],"type":"Point"}
}