{
  "type": "Feature",
  "properties": {
    "addr:full":"44-46 All L\u00e9on Gambetta 92110 Clichy Ile de France 92110",
    "addr:housenumber":"44-46",
    "addr:postcode":"92110;92110",
    "addr:street":"All Le\u0301On Gambetta;Ile De France",
    "iso:country":"FR",
    "sg:address":"44-46 All L\u00e9on Gambetta 92110 Clichy",
    "sg:classifiers":[
        {
            "category":"Professional",
            "subcategory":"Business Services",
            "type":"Services"
        }
    ],
    "sg:phone":"+33 1 47 56 22 15",
    "sg:postcode":"92110",
    "sg:province":"Ile de France",
    "sg:tags":[
        "pharmaceutical",
        "advice",
        "-",
        "chemical",
        "chemistry",
        "energy",
        "by-product"
    ],
    "wof:name":"Jesel Et Widemann",
    "wof:placetype":"venue"
},
  "geometry": {"coordinates":[2.311909,48.903175],"type":"Point"}
}