{
  "type": "Feature",
  "properties": {
    "addr:full":"Plaine Du Gier 69700 Givors Rhone-Alpes 69700",
    "addr:postcode":"69700;69700",
    "addr:street":"Plaine;Gier",
    "iso:country":"FR",
    "sg:address":"Plaine Du Gier 69700 Givors",
    "sg:classifiers":[
        {
            "category":"Travel",
            "subcategory":"Hotels & Motels",
            "type":"Entertainment"
        }
    ],
    "sg:phone":"+33 4 72 24 00 28",
    "sg:postcode":"69700",
    "sg:province":"Rhone-Alpes",
    "sg:tags":[
        "hotels",
        "business",
        "restaurant"
    ],
    "wof:name":"Flunch",
    "wof:placetype":"venue"
},
  "geometry": {"coordinates":[4.742869,45.583141],"type":"Point"}
}