{
  "type": "Feature",
  "properties": {
    "iso:country":"FR",
    "sg:address":"1 R De Dourdaigne 45130 Huisseau Sur Mauves",
    "sg:city":"Baule",
    "sg:classifiers":[
        {
            "category":"Farming",
            "subcategory":"Farm",
            "type":"Manufacturing & Wholesale Goods"
        }
    ],
    "sg:phone":"+33 2 38 80 76 58",
    "sg:postcode":"45130",
    "sg:province":"Centre",
    "sg:tags":[
        "horticulture",
        "agriculture",
        "livestock"
    ],
    "wof:name":"Produits Chimiques Engrais Hurel Arc",
    "wof:placetype":"venue"
},
  "geometry": {"coordinates":[1.715369,47.887997],"type":"Point"}
}