{
  "type": "Feature",
  "properties": {
    "addr:full":"Rte Ancenis 44330 Vallet Pays de Loire",
    "addr:postcode":"44330",
    "addr:street":"Rte Ancenis",
    "iso:country":"FR",
    "sg:address":"Rte Ancenis 44330 Vallet",
    "sg:classifiers":[
        {
            "category":"Banks & Credit Unions",
            "subcategory":"Investment Brokerage",
            "type":"Services"
        }
    ],
    "sg:phone":"+33 2 40 36 46 19",
    "sg:province":"Pays de Loire",
    "sg:tags":[
        "-",
        "transport",
        "related"
    ],
    "wof:name":"Jardinerie Bricomarche",
    "wof:placetype":"venue"
},
  "geometry": {"coordinates":[-1.280539,47.147301],"type":"Point"}
}