{
  "type": "Feature",
  "properties": {
    "iso:country":"FR",
    "sg:address":"3, Rue Gilbert Romme, 72200 La Fl\u00e8che",
    "sg:orig_category":"Unclassifiable Establishments",
    "sg:phone":"+33 2 43 45 90 83",
    "sg:province":"Pays de Loire",
    "wof:name":"Xeilom Sa",
    "wof:placetype":"venue"
},
  "geometry": {"coordinates":[-0.107219,47.713024],"type":"Point"}
}