{
  "type": "Feature",
  "properties": {
    "addr:full":"21, Rue John Fitzgerald Kennedy, 77140 Nemours Ile de France",
    "addr:housenumber":"21",
    "addr:postcode":"77140",
    "addr:street":"Rue John Fitzgerald Kennedy;Ile De France",
    "iso:country":"FR",
    "sg:address":"21, Rue John Fitzgerald Kennedy, 77140 Nemours",
    "sg:orig_category":"Unclassifiable Establishments",
    "sg:phone":"+33 1 64 28 04 66",
    "sg:province":"Ile de France",
    "wof:name":"Renaud Transports S.a.",
    "wof:placetype":"venue"
},
  "geometry": {"coordinates":[2.710204,48.264908],"type":"Point"}
}