{
  "type": "Feature",
  "properties": {
    "addr:full":"49 Route Aigre 16700 Ruffec Poitou-Charentes",
    "addr:housenumber":"49",
    "addr:postcode":"16700",
    "addr:street":"Route Aigre",
    "iso:country":"FR",
    "sg:address":"49 Route Aigre 16700 Ruffec",
    "sg:classifiers":[
        {
            "category":"Home & Garden",
            "subcategory":"Furniture",
            "type":"Retail Goods"
        }
    ],
    "sg:phone":"+33 5 45 31 09 32",
    "sg:province":"Poitou-Charentes",
    "sg:tags":[
        "household",
        "wood"
    ],
    "wof:name":"Meubles Moulignier Sarl",
    "wof:placetype":"venue"
},
  "geometry": {"coordinates":[0.191186,46.021835],"type":"Point"}
}