{
  "type": "Feature",
  "properties": {
    "iso:country":"FR",
    "sg:address":"11, Rue Jean Claret, 63000 Clermont Ferrand",
    "sg:city":"Clermont-Ferrand",
    "sg:orig_category":"Unclassifiable Establishments",
    "sg:phone":"+33 4 73 28 13 13",
    "sg:postcode":"63000",
    "sg:province":"Auvergne",
    "wof:name":"Ma.com S.a.",
    "wof:placetype":"venue"
},
  "geometry": {"coordinates":[3.135953,45.765022],"type":"Point"}
}