{
  "type": "Feature",
  "properties": {
    "addr:full":"91 Bis R Du Cherche Midi 75006 Paris Ile de France 75006",
    "addr:housenumber":"91 bis",
    "addr:postcode":"75006;75006",
    "addr:street":"R Du Cherche Midi",
    "iso:country":"FR",
    "sg:address":"91 Bis R Du Cherche Midi 75006 Paris",
    "sg:classifiers":[
        {
            "category":"Professional",
            "subcategory":"Advertising",
            "type":"Services"
        }
    ],
    "sg:phone":"+33 1 49 54 53 53",
    "sg:postcode":"75006",
    "sg:province":"Ile de France",
    "sg:tags":[
        "information",
        "medium",
        "communication"
    ],
    "wof:name":"Prestige Television",
    "wof:placetype":"venue"
},
  "geometry": {"coordinates":[2.322034,48.847012],"type":"Point"}
}