{
  "type": "Feature",
  "properties": {
    "iso:country":"FR",
    "sg:address":"Chemin de la Peyrade",
    "sg:city":"Sorgues",
    "sg:orig_category":"Unclassifiable Establishments",
    "sg:phone":"+33 4 90 83 42 17",
    "sg:postcode":"84700",
    "sg:province":"Provence-Alpes-C\u00f4te d'Azur",
    "wof:name":"C.m.p.r. S.a.r.l. - Constructions M\u00e9caniques De Pr\u00e9cision R\u00e9paration",
    "wof:placetype":"venue"
},
  "geometry": {"coordinates":[4.868923,43.998512],"type":"Point"}
}