{
  "type": "Feature",
  "properties": {
    "addr:full":"9 Rue L\u00e9on Cogniet 75017 Paris Ile de France 75017",
    "addr:housenumber":"9",
    "addr:postcode":"75017;75017",
    "addr:street":"Rue Le\u0301On Cogniet",
    "iso:country":"FR",
    "sg:address":"9 Rue L\u00e9on Cogniet 75017 Paris",
    "sg:classifiers":[
        {
            "category":"Communications",
            "type":"Services"
        }
    ],
    "sg:phone":"+33 1 47 64 10 00",
    "sg:postcode":"75017",
    "sg:province":"Ile de France",
    "sg:tags":[
        "advice",
        "interpretation",
        "translation",
        "business"
    ],
    "wof:name":"Cir",
    "wof:placetype":"venue"
},
  "geometry": {"coordinates":[2.302594,48.881126],"type":"Point"}
}