{
  "type": "Feature",
  "properties": {
    "iso:country":"FR",
    "sg:address":"B.P. 69, 59560 Warneton^^44, Rte de Delemont, 59560 Warneton",
    "sg:orig_category":"Non-Classified Establishments",
    "sg:phone":"+33 3 20 14 59 30",
    "sg:province":"Nord Pas-de-Calais",
    "wof:name":"V.s. 59 Verandalys S.a.r.l.",
    "wof:placetype":"venue"
},
  "geometry": {"coordinates":[3.006479,50.764984],"type":"Point"}
}