{
  "type": "Feature",
  "properties": {
    "addr:full":"28 rue Joseph Pinvidic; Landivisiau; 29400 Landivisiau Bretagne 29400",
    "addr:housenumber":"28",
    "addr:postcode":"29400;29400",
    "addr:street":"Rue Joseph Pinvidic;Bretagne",
    "iso:country":"FR",
    "sg:address":"28 rue Joseph Pinvidic; Landivisiau; 29400",
    "sg:city":"Landivisiau",
    "sg:classifiers":[
        {
            "category":"Banks & Credit Unions",
            "subcategory":"Bank",
            "type":"Services"
        }
    ],
    "sg:phone":"+33 2 98 68 10 89",
    "sg:postcode":"29400",
    "sg:province":"Bretagne",
    "wof:name":"Banque C.i.o.",
    "wof:placetype":"venue"
},
  "geometry": {"coordinates":[-4.070302,48.508648],"type":"Point"}
}