{
  "type": "Feature",
  "properties": {
    "iso:country":"FR",
    "sg:address":"35 Av Montaigne 75008 Paris",
    "sg:classifiers":[
        {
            "category":"Professional",
            "subcategory":"Business Services",
            "type":"Services"
        }
    ],
    "sg:phone":"+33 1 44 43 29 00",
    "sg:postcode":"75008",
    "sg:province":"Ile de France",
    "sg:tags":[
        "body",
        "advice"
    ],
    "wof:name":"Canada - Ambassade",
    "wof:placetype":"venue"
},
  "geometry": {"coordinates":[2.305416,48.866859],"type":"Point"}
}