{
  "type": "Feature",
  "properties": {
    "iso:country":"FR",
    "sg:address":"24, Rue Ronsard, 64000 Pau",
    "sg:city":"Pau",
    "sg:orig_category":"Unclassifiable Establishments",
    "sg:phone":"+33 5 59 83 96 00",
    "sg:postcode":"64000",
    "sg:province":"Aquitaine",
    "wof:name":"B.f.c.c. S.a. - Banque Fran\u00e7aise De Cr\u00e9dit Coop\u00e9ratif",
    "wof:placetype":"venue"
},
  "geometry": {"coordinates":[-0.356399,43.318081],"type":"Point"}
}