{
  "type": "Feature",
  "properties": {
    "addr:full":"921 Rue Des Montaudins 45560 St Denis En Val Saint-Denis-en-Val Centre 45560",
    "addr:housenumber":"921",
    "addr:postcode":"45560;45560",
    "addr:street":"Rue Des Montaudins;Val Saint-Denis-En-Val",
    "iso:country":"FR",
    "sg:address":"921 Rue Des Montaudins 45560 St Denis En Val",
    "sg:city":"Saint-Denis-en-Val",
    "sg:classifiers":[
        {
            "category":"Farming",
            "subcategory":"Livestock Farm",
            "type":"Manufacturing & Wholesale Goods"
        }
    ],
    "sg:phone":"+33 2 38 76 81 81",
    "sg:postcode":"45560",
    "sg:province":"Centre",
    "sg:tags":[
        "agriculture"
    ],
    "wof:name":"Pepinieres Dupont Et Fils Sarl",
    "wof:placetype":"venue"
},
  "geometry": {"coordinates":[1.989227,47.887455],"type":"Point"}
}