{
  "type": "Feature",
  "properties": {
    "addr:full":"40 Rue Aristide Berg\u00e8s Zi Du Casque 31270 Cugnaux Midi Pyr\u00e9n\u00e9es 31270",
    "addr:housenumber":"40",
    "addr:postcode":"31270;31270",
    "addr:street":"Rue Aristide Berge\u0300S Zi Du Casque",
    "iso:country":"FR",
    "sg:address":"40 Rue Aristide Berg\u00e8s Zi Du Casque 31270 Cugnaux",
    "sg:classifiers":[
        {
            "category":"Transit Center",
            "subcategory":"Freight",
            "type":"Transportation"
        }
    ],
    "sg:phone":"+33 5 62 13 57 40",
    "sg:postcode":"31270",
    "sg:province":"Midi Pyr\u00e9n\u00e9es",
    "sg:tags":[
        "metallurgy",
        "pipe",
        "metalworking",
        "sheet"
    ],
    "wof:name":"Peintures Et Techniques Appliquees (pta)",
    "wof:placetype":"venue"
},
  "geometry": {"coordinates":[1.34424,43.536976],"type":"Point"}
}