{
  "type": "Feature",
  "properties": {
    "addr:full":"Grand Champs de Baumac Tocane Saint Apre Aquitaine 24350",
    "addr:postcode":"24350",
    "addr:street":"Grand Champs De Baumac Tocane Saint Apre",
    "iso:country":"FR",
    "sg:address":"Grand Champs de Baumac",
    "sg:city":"Tocane Saint Apre",
    "sg:orig_category":"Non-Classified Establishments",
    "sg:phone":"+33 5 53 90 70 36",
    "sg:postcode":"24350",
    "sg:province":"Aquitaine",
    "wof:name":"A. Delage S.a.",
    "wof:placetype":"venue"
},
  "geometry": {"coordinates":[0.49544,45.25404],"type":"Point"}
}