{
  "type": "Feature",
  "properties": {
    "addr:full":"Zi De La Fiolle 71450 Blanzy Blanzy Bourgogne 71450",
    "addr:postcode":"71450;71450",
    "addr:street":"Zi De La Fiolle",
    "iso:country":"FR",
    "sg:address":"Zi De La Fiolle 71450 Blanzy",
    "sg:city":"Blanzy",
    "sg:classifiers":[
        {
            "category":"Manufacturing",
            "subcategory":"Rubber & Plastics",
            "type":"Manufacturing & Wholesale Goods"
        }
    ],
    "sg:phone":"+33 3 85 67 32 00",
    "sg:postcode":"71450",
    "sg:province":"Bourgogne",
    "wof:name":"Michelin (manufacture Francaise Des Pneumatiques)",
    "wof:placetype":"venue"
},
  "geometry": {"coordinates":[4.390975,46.696674],"type":"Point"}
}