{
  "type": "Feature",
  "properties": {
    "iso:country":"FR",
    "sg:address":"33 Boulevard Domenget Imm Le Rond Point 73100 Aix Les Bains",
    "sg:classifiers":[
        {
            "category":"Professional",
            "subcategory":"Printing & Photocopies",
            "type":"Services"
        }
    ],
    "sg:phone":"+33 4 79 61 16 38",
    "sg:postcode":"73100",
    "sg:province":"Rhone-Alpes",
    "sg:tags":[
        "publishing"
    ],
    "wof:name":"Impact Conseil",
    "wof:placetype":"venue"
},
  "geometry": {"coordinates":[5.90804,45.696751],"type":"Point"}
}