{
  "type": "Feature",
  "properties": {
    "iso:country":"FR",
    "sg:address":"13, Rue du 8 mai 1945, 37460 Orbigny",
    "sg:city":"Orbigny",
    "sg:orig_category":"Unclassifiable Establishments",
    "sg:phone":"+33 2 47 94 21 37",
    "sg:postcode":"37460",
    "sg:province":"Centre",
    "wof:name":"New Fashion Economiste Limited",
    "wof:placetype":"venue"
},
  "geometry": {"coordinates":[1.257498,47.05426],"type":"Point"}
}