{
  "type": "Feature",
  "properties": {
    "addr:full":"13, Rue du 8 mai 1945, 37460 Orbigny Orbigny Centre 37460",
    "addr:housenumber":"13;orbigny",
    "addr:postcode":"37460;37460",
    "addr:street":"Rue Du 8 Mai 1945",
    "iso:country":"FR",
    "sg:address":"13, Rue du 8 mai 1945, 37460 Orbigny",
    "sg:city":"Orbigny",
    "sg:orig_category":"Unclassifiable Establishments",
    "sg:phone":"+33 2 47 94 21 37",
    "sg:postcode":"37460",
    "sg:province":"Centre",
    "wof:name":"New Fashion Economiste Limited",
    "wof:placetype":"venue"
},
  "geometry": {"coordinates":[1.257498,47.05426],"type":"Point"}
}