{
  "type": "Feature",
  "properties": {
    "addr:full":"B.P. 7068, 95052 Cergy Pontoise C\u00e9dex^^6, Rue Paul Appel - ZI du Vert Galant, 95310 Saint Ouen l'Aum Ile de France 95310",
    "addr:postcode":"95052;95310;95310",
    "addr:street":"B.P. 7068;Rue Paul Appel Zi Du Vert Galant",
    "iso:country":"FR",
    "sg:address":"B.P. 7068, 95052 Cergy Pontoise C\u00e9dex^^6, Rue Paul Appel - ZI du Vert Galant, 95310 Saint Ouen l'Aum",
    "sg:orig_category":"Non-Classified Establishments",
    "sg:phone":"+33 1 34 48 92 82",
    "sg:postcode":"95310",
    "sg:province":"Ile de France",
    "wof:name":"A.f.e.r. S.a.r.l.",
    "wof:placetype":"venue"
},
  "geometry": {"coordinates":[2.933116,48.55759],"type":"Point"}
}