{
  "type": "Feature",
  "properties": {
    "addr:full":"262 Rue Fontchaudi\u00e8re Angoul\u00eame Poitou-Charentes 16000",
    "addr:housenumber":"262",
    "addr:postcode":"16000",
    "addr:street":"Rue Fontchaudie\u0300Re Angoule\u0302Me",
    "iso:country":"FR",
    "sg:address":"262 Rue Fontchaudi\u00e8re",
    "sg:city":"Angoul\u00eame",
    "sg:classifiers":[
        {
            "category":"Banks & Credit Unions",
            "subcategory":"Financial Services",
            "type":"Services"
        }
    ],
    "sg:phone":"+33 5 45 38 20 73",
    "sg:postcode":"16000",
    "sg:province":"Poitou-Charentes",
    "sg:tags":[
        "banking",
        "finance",
        "insurance"
    ],
    "wof:name":"Faux Georges Chobelet Guy Scm Expert Comptab",
    "wof:placetype":"venue"
},
  "geometry": {"coordinates":[0.15591,45.661678],"type":"Point"}
}