{
  "type": "Feature",
  "properties": {
    "addr:full":"25, Rte Nationale, 54135 Mexy Lorraine",
    "addr:housenumber":"25",
    "addr:postcode":"54135",
    "addr:street":"Rte Nationale",
    "iso:country":"FR",
    "sg:address":"25, Rte Nationale, 54135 Mexy",
    "sg:orig_category":"Non-Classified Establishments",
    "sg:phone":"+33 3 82 24 28 95",
    "sg:province":"Lorraine",
    "wof:name":"Longwy Mat\u00e9riaux S.a.",
    "wof:placetype":"venue"
},
  "geometry": {"coordinates":[5.793831,49.496506],"type":"Point"}
}