{
  "type": "Feature",
  "properties": {
    "addr:full":"B.P. 113, 37401 Amboise C\u00e9dex^^10, Bd de l'Avenir - ZI Nazelles Negron, 37400 Amboise Amboise Centre 37400",
    "addr:housenumber":"b.p. 113",
    "addr:postcode":"37401;ce\u0301dex^^10;37400;37400",
    "addr:street":"Bd De L'Avenir Zi Nazelles Negron",
    "iso:country":"FR",
    "sg:address":"B.P. 113, 37401 Amboise C\u00e9dex^^10, Bd de l'Avenir - ZI Nazelles Negron, 37400 Amboise",
    "sg:city":"Amboise",
    "sg:orig_category":"Non-Classified Establishments",
    "sg:phone":"+33 2 47 23 72 23",
    "sg:postcode":"37400",
    "sg:province":"Centre",
    "wof:name":"Reorev Technologie S.a.r.l.",
    "wof:placetype":"venue"
},
  "geometry": {"coordinates":[0.980454,47.418278],"type":"Point"}
}