{
  "type": "Feature",
  "properties": {
    "addr:full":"35 Faubourgs Des Vosges 67120 Dorlisheim Dorlisheim Alsace 67120",
    "addr:housenumber":"35",
    "addr:postcode":"67120;67120",
    "addr:street":"Faubourgs Des Vosges;Dorlisheim",
    "iso:country":"FR",
    "sg:address":"35 Faubourgs Des Vosges 67120 Dorlisheim",
    "sg:city":"Dorlisheim",
    "sg:orig_category":"Chemicals and Pharmaceuticals Games and entertainment Household goods Metallurgy and Metalworking Mi",
    "sg:phone":"+33 3 88 38 52 50",
    "sg:postcode":"67120",
    "sg:province":"Alsace",
    "wof:name":"Armena Sa",
    "wof:placetype":"venue"
},
  "geometry": {"coordinates":[7.565965,48.52454],"type":"Point"}
}