{
  "type": "Feature",
  "properties": {
    "addr:full":"25, Rue Louis Chatin, 42400 Saint Chamond Rhone-Alpes",
    "addr:housenumber":"25",
    "addr:postcode":"42400",
    "addr:street":"Rue Louis Chatin;Chamond Rhone-Alpes",
    "iso:country":"FR",
    "sg:address":"25, Rue Louis Chatin, 42400 Saint Chamond",
    "sg:orig_category":"Unclassifiable Establishments",
    "sg:phone":"+33 4 77 31 86 43",
    "sg:province":"Rhone-Alpes",
    "wof:name":"Maille Diffusion S.a.r.l.",
    "wof:placetype":"venue"
},
  "geometry": {"coordinates":[4.504635,45.450874],"type":"Point"}
}