{
  "type": "Feature",
  "properties": {
    "addr:full":"6 Rue Du Pin 44300 Nantes Pays de Loire 44300",
    "addr:housenumber":"6",
    "addr:postcode":"44300;44300",
    "addr:street":"Rue Du Pin",
    "iso:country":"FR",
    "sg:address":"6 Rue Du Pin 44300 Nantes",
    "sg:classifiers":[
        {
            "category":"Autos & Motor Vehicles",
            "subcategory":"Automobile Sales",
            "type":"Retail Goods"
        }
    ],
    "sg:phone":"+33 2 40 14 53 20",
    "sg:postcode":"44300",
    "sg:province":"Pays de Loire",
    "sg:tags":[
        "equipment",
        "motor-cars",
        "transport"
    ],
    "wof:name":"Inter Actions Sa",
    "wof:placetype":"venue"
},
  "geometry": {"coordinates":[-1.562397,47.234367],"type":"Point"}
}