{
  "type": "Feature",
  "properties": {
    "iso:country":"FR",
    "sg:address":"27, Rue Juliette Dodu, 75010 Paris",
    "sg:orig_category":"Unclassifiable Establishments",
    "sg:phone":"+33 1 53 72 50 00",
    "sg:province":"Ile de France",
    "wof:name":"Fondation Jean Dausset Ceph - Centre D'etudes Du Polymorphisme Humain",
    "wof:placetype":"venue"
},
  "geometry": {"coordinates":[2.368916,48.875492],"type":"Point"}
}