{
  "type": "Feature",
  "properties": {
    "addr:full":"48 r Charles de Gaulle; L'Arbresle Picardie",
    "addr:housenumber":"48",
    "addr:street":"R Charles De Gaulle",
    "iso:country":"FR",
    "sg:address":"48 r Charles de Gaulle; L'Arbresle",
    "sg:classifiers":[
        {
            "category":"Banks & Credit Unions",
            "subcategory":"Bank",
            "type":"Services"
        }
    ],
    "sg:phone":"+33 3374013066",
    "sg:province":"Picardie",
    "wof:name":"Lyonnaise De Banque",
    "wof:placetype":"venue"
},
  "geometry": {"coordinates":[4.616758,45.83662],"type":"Point"}
}