{
  "type": "Feature",
  "properties": {
    "iso:country":"FR",
    "sg:address":"Rue Pierre Mend\u00e8s France - ZA le Sablon",
    "sg:city":"Mulsanne",
    "sg:orig_category":"Unclassifiable Establishments",
    "sg:phone":"+33 2 43 77 10 11",
    "sg:postcode":"72230",
    "sg:province":"Pays de Loire",
    "wof:name":"G.p. Automation S.a.r.l.",
    "wof:placetype":"venue"
},
  "geometry": {"coordinates":[0.12903,47.877361],"type":"Point"}
}