{
  "type": "Feature",
  "properties": {
    "addr:full":"Le Bourg; Julli\u00e9 Centre",
    "addr:street":"Le Bourg Jullie\u0301",
    "iso:country":"FR",
    "sg:address":"Le Bourg; Julli\u00e9",
    "sg:classifiers":[
        {
            "category":"Banks & Credit Unions",
            "subcategory":"Bank",
            "type":"Services"
        }
    ],
    "sg:phone":"+33 3374044279",
    "sg:province":"Centre",
    "wof:name":"Cr\u00e9dit Agricole Du Sud Est",
    "wof:placetype":"venue"
},
  "geometry": {"coordinates":[4.677569,46.24202],"type":"Point"}
}