{
  "type": "Feature",
  "properties": {
    "iso:country":"FR",
    "sg:address":"285, Rue du Vern - ZI du Vern, 29200 Brest",
    "sg:city":"Brest",
    "sg:orig_category":"Unclassifiable Establishments",
    "sg:phone":"+33 2 98 05 56 57",
    "sg:postcode":"29200",
    "sg:province":"Bretagne",
    "wof:name":"Fily",
    "wof:placetype":"venue"
},
  "geometry": {"coordinates":[-4.486228,48.39024],"type":"Point"}
}