{
  "type": "Feature",
  "properties": {
    "iso:country":"FR",
    "sg:address":"B.P. 108, 10202 Bar sur Aube C\u00e9dex^^28, Av. du G\u00e9n\u00e9ral Leclerc, 10200 Bar sur Aube",
    "sg:orig_category":"Non-Classified Establishments",
    "sg:phone":"+33 3 25 92 50 40",
    "sg:province":"Champagne",
    "wof:name":"Groupe J. Michel Tivoly S.a.",
    "wof:placetype":"venue"
},
  "geometry": {"coordinates":[4.705215,48.234325],"type":"Point"}
}