{
  "type": "Feature",
  "properties": {
    "addr:full":"8, Av. Philippe Auguste, 75011 Paris Ile de France",
    "addr:postcode":"75011",
    "addr:street":"Av. Philippe Auguste",
    "iso:country":"FR",
    "sg:address":"8, Av. Philippe Auguste, 75011 Paris",
    "sg:orig_category":"Non-Classified Establishments",
    "sg:phone":"+33 1 43 48 91 55",
    "sg:province":"Ile de France",
    "wof:name":"Ordinter",
    "wof:placetype":"venue"
},
  "geometry": {"coordinates":[2.395165,48.849911],"type":"Point"}
}