{
  "type": "Feature",
  "properties": {
    "addr:full":"B.P. 45, 84232 Ch\u00e2teauneuf du Pape C\u00e9dex^^7, Av. des Bosquets, 84230 Ch\u00e2teauneuf du Pape Provence-Alpes-C\u00f4te d'Azur",
    "addr:postcode":"84232;84230",
    "addr:street":"B.P. 45;Av. Des Bosquets;Pape",
    "iso:country":"FR",
    "sg:address":"B.P. 45, 84232 Ch\u00e2teauneuf du Pape C\u00e9dex^^7, Av. des Bosquets, 84230 Ch\u00e2teauneuf du Pape",
    "sg:orig_category":"Non-Classified Establishments",
    "sg:phone":"+33 4 90 83 72 87",
    "sg:province":"Provence-Alpes-C\u00f4te d'Azur",
    "wof:name":"Jean Comte De Lauze S.c.e.a.",
    "wof:placetype":"venue"
},
  "geometry": {"coordinates":[4.835999,44.049744],"type":"Point"}
}