{
  "type": "Feature",
  "properties": {
    "addr:full":"04230 St Etienne Les Orgues Provence-Alpes-C\u00f4te d'Azur",
    "addr:housenumber":"04230",
    "addr:street":"St Etienne Les Orgues",
    "iso:country":"FR",
    "sg:address":"04230 St Etienne Les Orgues",
    "sg:classifiers":[
        {
            "category":"Manufacturing",
            "subcategory":"Paper Products",
            "type":"Manufacturing & Wholesale Goods"
        }
    ],
    "sg:phone":"+33 4 92 73 03 08",
    "sg:province":"Provence-Alpes-C\u00f4te d'Azur",
    "sg:tags":[
        "packaging",
        "material",
        "-",
        "cardboard"
    ],
    "wof:name":"Papeterie Mosca Et Belmonte Societe D'exploitation",
    "wof:placetype":"venue"
},
  "geometry": {"coordinates":[5.781085,44.045422],"type":"Point"}
}