{
  "type": "Feature",
  "properties": {
    "iso:country":"FR",
    "sg:address":"4 Av Du Midi 30111 Cong\u00e9nies",
    "sg:classifiers":[
        {
            "category":"Wholesale",
            "subcategory":"Medical Equipment & Supplies",
            "type":"Manufacturing & Wholesale Goods"
        }
    ],
    "sg:phone":"+33 4 66 80 22 89",
    "sg:postcode":"30111",
    "sg:province":"Languedoc-Roussillon",
    "sg:tags":[
        "instrument",
        "health",
        "-",
        "precision"
    ],
    "wof:name":"Interson Les Embouts Monier Sarl",
    "wof:placetype":"venue"
},
  "geometry": {"coordinates":[4.163047,43.774998],"type":"Point"}
}