{
  "type": "Feature",
  "properties": {
    "addr:full":"route de Balagny 60250 Mouy Picardie 60250",
    "addr:postcode":"60250;60250",
    "addr:street":"Route De Balagny",
    "iso:country":"FR",
    "sg:address":"route de Balagny 60250 Mouy",
    "sg:classifiers":[
        {
            "category":"Shopping",
            "subcategory":"Computers & Home Electronics",
            "type":"Retail Goods"
        }
    ],
    "sg:phone":"+33 3 44 26 43 73",
    "sg:postcode":"60250",
    "sg:province":"Picardie",
    "sg:tags":[
        "electronic",
        "module"
    ],
    "wof:name":"Bristol Babcock S.a.",
    "wof:placetype":"venue"
},
  "geometry": {"coordinates":[2.326845,49.309956],"type":"Point"}
}