{
  "type": "Feature",
  "properties": {
    "addr:full":"83, Av. Charles de Gaulle, 92200 Neuilly sur Seine Ile de France",
    "addr:postcode":"92200",
    "addr:street":"83 Av. Charles De Gaulle",
    "iso:country":"FR",
    "sg:address":"83, Av. Charles de Gaulle, 92200 Neuilly sur Seine",
    "sg:orig_category":"Unclassifiable Establishments",
    "sg:phone":"+33 1 55 62 09 90",
    "sg:province":"Ile de France",
    "wof:name":"Editions Axel Springer S.a.r.l.",
    "wof:placetype":"venue"
},
  "geometry": {"coordinates":[2.273864,48.88007],"type":"Point"}
}