{
  "type": "Feature",
  "properties": {
    "addr:full":"rue du Planty 86300 Chauvigny Poitou-Charentes 86300",
    "addr:postcode":"86300;86300",
    "addr:street":"Rue Du Planty",
    "iso:country":"FR",
    "sg:address":"rue du Planty 86300 Chauvigny",
    "sg:orig_category":"HOTELS: CHINA",
    "sg:phone":"+33 5 49 61 50 00",
    "sg:postcode":"86300",
    "sg:province":"Poitou-Charentes",
    "wof:name":"Deshoulieres Sa",
    "wof:placetype":"venue"
},
  "geometry": {"coordinates":[0.651772,46.560455],"type":"Point"}
}