{
  "type": "Feature",
  "properties": {
    "iso:country":"FR",
    "sg:address":"Rue Paul Painlev\u00e9 - ZI le Vert Galant",
    "sg:city":"Saint Ouen l'Aum\u00f4ne",
    "sg:orig_category":"Unclassifiable Establishments",
    "sg:phone":"+33 1 34 30 28 30",
    "sg:postcode":"95310",
    "sg:province":"Ile de France",
    "wof:name":"Mobrey S.a.",
    "wof:placetype":"venue"
},
  "geometry": {"coordinates":[0.207837,47.831627],"type":"Point"}
}