{
  "type": "Feature",
  "properties": {
    "addr:full":"39, Rte du Bassin N\u00b06, 92230 Gennevilliers Ile de France",
    "addr:housenumber":"39",
    "addr:postcode":"92230;ile",
    "addr:street":"Rte Du Bassin N\u00b06",
    "iso:country":"FR",
    "sg:address":"39, Rte du Bassin N\u00b06, 92230 Gennevilliers",
    "sg:orig_category":"Unclassifiable Establishments",
    "sg:phone":"+33 1 41 47 46 00",
    "sg:province":"Ile de France",
    "wof:name":"Savos S.a.r.l.",
    "wof:placetype":"venue"
},
  "geometry": {"coordinates":[2.29546,48.94725],"type":"Point"}
}