{
  "type": "Feature",
  "properties": {
    "iso:country":"FR",
    "sg:address":"2, Av. du Pr\u00e9sident Salvadore Allend\u00e9, 93100 Montreuil",
    "sg:orig_category":"Non-Classified Establishments",
    "sg:phone":"+33 1 48 51 98 92",
    "sg:postcode":"93100",
    "sg:province":"Ile de France",
    "wof:name":"B.r. 93 S.a.r.l. - Les Brocheurs R\u00e9unis",
    "wof:placetype":"venue"
},
  "geometry": {"coordinates":[2.456176,48.868721],"type":"Point"}
}