{
  "type": "Feature",
  "properties": {
    "iso:country":"FR",
    "sg:address":"Rte de Balizac",
    "sg:city":"Landiras",
    "sg:orig_category":"Unclassifiable Establishments",
    "sg:phone":"+33 5 57 98 07 20",
    "sg:postcode":"33720",
    "sg:province":"Aquitaine",
    "wof:name":"Les Caves De Landiras S.a.",
    "wof:placetype":"venue"
},
  "geometry": {"coordinates":[-0.418334,44.562531],"type":"Point"}
}