{
  "type": "Feature",
  "properties": {
    "iso:country":"FR",
    "sg:address":"ZI",
    "sg:city":"Luceau",
    "sg:orig_category":"Non-Classified Establishments",
    "sg:phone":"+33 2 43 44 31 02",
    "sg:postcode":"72500",
    "sg:province":"Pays de Loire",
    "wof:name":"Tertrain Raymond",
    "wof:placetype":"venue"
},
  "geometry": {"coordinates":[0.33858,47.612446],"type":"Point"}
}