{
  "type": "Feature",
  "properties": {
    "addr:full":"8 Allee Thomas Edison Zi Ecopolis Martiques Sud 13500 Martigues Artigue Midi Pyr\u00e9n\u00e9es 31110",
    "addr:housenumber":"8",
    "addr:postcode":"13500;31110",
    "addr:street":"Allee Thomas Edison Zi Ecopolis Martiques Sud",
    "iso:country":"FR",
    "sg:address":"8 Allee Thomas Edison Zi Ecopolis Martiques Sud 13500 Martigues",
    "sg:city":"Artigue",
    "sg:classifiers":[
        {
            "category":"Building & Trades",
            "subcategory":"Construction",
            "type":"Services"
        }
    ],
    "sg:phone":"+33 4 42 81 82 82",
    "sg:postcode":"31110",
    "sg:province":"Midi Pyr\u00e9n\u00e9es",
    "sg:tags":[
        "work",
        "public"
    ],
    "wof:name":"Provence Tp",
    "wof:placetype":"venue"
},
  "geometry": {"coordinates":[5.055235,43.406536],"type":"Point"}
}