{
  "type": "Feature",
  "properties": {
    "iso:country":"FR",
    "sg:address":"Zone Industrielle 38660 ST VINCENT DE MERCUZE",
    "sg:orig_category":"Swimming Equipment And Swimming Costumes",
    "sg:phone":"+33 4 76 08 45 11",
    "sg:province":"Rhone-Alpes",
    "wof:name":"Sofaditex S.a.",
    "wof:placetype":"venue"
},
  "geometry": {"coordinates":[5.95282,45.37141],"type":"Point"}
}