{
  "type": "Feature",
  "properties": {
    "iso:country":"FR",
    "sg:address":"6 rue de Bretagne 68390 Sausheim",
    "sg:city":"Sausheim",
    "sg:classifiers":[
        {
            "category":"Professional",
            "type":"Services"
        }
    ],
    "sg:phone":"+33 3 89 31 21 21",
    "sg:postcode":"68390",
    "sg:province":"Alsace",
    "sg:tags":[
        "transport"
    ],
    "wof:name":"Trans Hit International S.a.",
    "wof:placetype":"venue"
},
  "geometry": {"coordinates":[7.391577,47.779716],"type":"Point"}
}