{
  "type": "Feature",
  "properties": {
    "addr:full":"4, Rue de Ch\u00e8vreloup, 78150 Rocquencourt Ile de France",
    "addr:housenumber":"4",
    "addr:postcode":"78150;ile",
    "addr:street":"Rue De Che\u0300Vreloup",
    "iso:country":"FR",
    "sg:address":"4, Rue de Ch\u00e8vreloup, 78150 Rocquencourt",
    "sg:orig_category":"Unclassifiable Establishments",
    "sg:phone":"+33 1 39 23 19 41",
    "sg:province":"Ile de France",
    "wof:name":"Scanroc S.a.r.l.",
    "wof:placetype":"venue"
},
  "geometry": {"coordinates":[2.097819,48.835995],"type":"Point"}
}