{
  "type": "Feature",
  "properties": {
    "addr:full":"32 Avenue Des Champs Elysees 75008 Paris Ile de France 75008",
    "addr:housenumber":"32",
    "addr:postcode":"75008;75008",
    "addr:street":"Avenue Des Champs Elysees",
    "iso:country":"FR",
    "sg:address":"32 Avenue Des Champs Elysees 75008 Paris",
    "sg:classifiers":[
        {
            "category":"Wholesale",
            "subcategory":"Drugs",
            "type":"Manufacturing & Wholesale Goods"
        }
    ],
    "sg:phone":"+33 1 42 25 02 79",
    "sg:postcode":"75008",
    "sg:province":"Ile de France",
    "sg:tags":[
        "chemical",
        "pharmaceutical"
    ],
    "wof:name":"Sarl Josyval",
    "wof:placetype":"venue"
},
  "geometry": {"coordinates":[2.308114,48.869774],"type":"Point"}
}