{
  "type": "Feature",
  "properties": {
    "addr:full":"Sous l'Eglise - Office du Tourisme Lanslevillard Rhone-Alpes 73480",
    "addr:postcode":"73480",
    "addr:street":"Sous;Rhone-Alpes",
    "iso:country":"FR",
    "sg:address":"Sous l'Eglise - Office du Tourisme",
    "sg:city":"Lanslevillard",
    "sg:orig_category":"Unclassifiable Establishments",
    "sg:phone":"+33 4 79 05 87 77",
    "sg:postcode":"73480",
    "sg:province":"Rhone-Alpes",
    "wof:name":"Banque De Savoie",
    "wof:placetype":"venue"
},
  "geometry": {"coordinates":[6.91357,45.29039],"type":"Point"}
}