{
  "type": "Feature",
  "properties": {
    "iso:country":"FR",
    "sg:address":"166 Rue La Fosse Aux Anglais 77190 Dammarie Les Lys",
    "sg:classifiers":[
        {
            "category":"Shopping",
            "subcategory":"Crafts & Fabrics",
            "type":"Retail Goods"
        }
    ],
    "sg:phone":"+33 1 64 39 37 96",
    "sg:postcode":"77190",
    "sg:province":"Ile de France",
    "sg:tags":[
        "textile",
        "clothing"
    ],
    "wof:name":"Sellerie Dulys",
    "wof:placetype":"venue"
},
  "geometry": {"coordinates":[2.64314,48.531136],"type":"Point"}
}