{
  "type": "Feature",
  "properties": {
    "addr:full":"ZI Laiz Rhone-Alpes 01290",
    "addr:postcode":"01290",
    "iso:country":"FR",
    "sg:address":"ZI",
    "sg:city":"Laiz",
    "sg:orig_category":"Unclassifiable Establishments",
    "sg:phone":"+33 3 85 23 98 98",
    "sg:postcode":"01290",
    "sg:province":"Rhone-Alpes",
    "wof:name":"M\u00e9canique G\u00e9n\u00e9rale Victor Diez S.a.",
    "wof:placetype":"venue"
},
  "geometry": {"coordinates":[4.88765,46.247299],"type":"Point"}
}