{
  "type": "Feature",
  "properties": {
    "addr:full":"15 Rue Cardinal G D'Amboise Amboise Centre 37400",
    "addr:housenumber":"15",
    "addr:postcode":"37400",
    "addr:street":"Rue Cardinal G D'Amboise Amboise",
    "iso:country":"FR",
    "sg:address":"15 Rue Cardinal G D'Amboise",
    "sg:city":"Amboise",
    "sg:classifiers":[
        {
            "category":"Banks & Credit Unions",
            "subcategory":"Financial Services",
            "type":"Services"
        }
    ],
    "sg:phone":"+33 2 47 57 57 06",
    "sg:postcode":"37400",
    "sg:province":"Centre",
    "sg:tags":[
        "banking",
        "finance",
        "insurance"
    ],
    "wof:name":"Societe D'expertise Comptabilite Controle Conseil (e 3 C)",
    "wof:placetype":"venue"
},
  "geometry": {"coordinates":[0.984919,47.40691],"type":"Point"}
}