{
  "type": "Feature",
  "properties": {
    "addr:full":"7, Chemin des Pr\u00e9s, 38240 Meylan Rhone-Alpes 38240",
    "addr:housenumber":"7",
    "addr:postcode":"38240;38240",
    "addr:street":"Chemin Des Pre\u0301S",
    "iso:country":"FR",
    "sg:address":"7, Chemin des Pr\u00e9s, 38240 Meylan",
    "sg:orig_category":"Non-Classified Establishments",
    "sg:phone":"+33 4 76 90 52 27",
    "sg:postcode":"38240",
    "sg:province":"Rhone-Alpes",
    "wof:name":"C.e.b.t.p. S.a. - Centre D'expertise Du B\u00e2timent Et Des Travaux Publics",
    "wof:placetype":"venue"
},
  "geometry": {"coordinates":[5.789758,45.210754],"type":"Point"}
}