{
  "type": "Feature",
  "properties": {
    "iso:country":"FR",
    "sg:address":"25, Av. des 3 Fontaines - ZI Vouvray, 74600 Seynod",
    "sg:orig_category":"Non-Classified Establishments",
    "sg:phone":"+33 4 50 51 18 94",
    "sg:postcode":"74600",
    "sg:province":"Rhone-Alpes",
    "wof:name":"Brossette B.t.i. S.a.",
    "wof:placetype":"venue"
},
  "geometry": {"coordinates":[6.112832,45.887939],"type":"Point"}
}