{
  "type": "Feature",
  "properties": {
    "addr:full":"La Gu\u00e9roulde 27160 Breteuil Haute Normandie",
    "addr:postcode":"27160",
    "addr:street":"La;Haute Normandie",
    "iso:country":"FR",
    "sg:address":"La Gu\u00e9roulde 27160 Breteuil",
    "sg:orig_category":"Unclassifiable Establishments",
    "sg:phone":"+33 2 32 29 81 90",
    "sg:province":"Haute Normandie",
    "wof:name":"Chaubeyre S.a.",
    "wof:placetype":"venue"
},
  "geometry": {"coordinates":[0.909438,48.830772],"type":"Point"}
}