{
  "type": "Feature",
  "properties": {
    "iso:country":"FR",
    "sg:address":"Zi 14600 Honfleur",
    "sg:city":"Honfleur",
    "sg:classifiers":[
        {
            "category":"Manufacturing",
            "subcategory":"Metals",
            "type":"Manufacturing & Wholesale Goods"
        }
    ],
    "sg:phone":"+33 2 31 89 03 14",
    "sg:postcode":"14600",
    "sg:province":"Basse Normandie",
    "sg:tags":[
        "metallurgy",
        "steel",
        "metalworking"
    ],
    "wof:name":"Liametho Sa",
    "wof:placetype":"venue"
},
  "geometry": {"coordinates":[0.234295,49.356091],"type":"Point"}
}