{
  "type": "Feature",
  "properties": {
    "addr:full":"13, Rue Crucy, 44000 Nantes Pays de Loire",
    "addr:housenumber":"13",
    "addr:postcode":"44000",
    "addr:street":"Rue Crucy",
    "iso:country":"FR",
    "sg:address":"13, Rue Crucy, 44000 Nantes",
    "sg:orig_category":"Unclassifiable Establishments",
    "sg:phone":"+33 2 51 88 78 00",
    "sg:province":"Pays de Loire",
    "wof:name":"Guillois Et Associ\u00e9s S.a.",
    "wof:placetype":"venue"
},
  "geometry": {"coordinates":[-1.547956,47.213982],"type":"Point"}
}