{
  "type": "Feature",
  "properties": {
    "addr:full":"B.P. 168, 67503 Haguenau C\u00e9dex^^23, Rte de Bischwiller, 67500 Haguenau Haguenau Alsace 67500",
    "addr:housenumber":"b.p. 168",
    "addr:postcode":"67503;67500;67500",
    "addr:street":"Rte De Bischwiller",
    "iso:country":"FR",
    "sg:address":"B.P. 168, 67503 Haguenau C\u00e9dex^^23, Rte de Bischwiller, 67500 Haguenau",
    "sg:city":"Haguenau",
    "sg:orig_category":"Non-Classified Establishments",
    "sg:phone":"+33 3 88 93 09 65",
    "sg:postcode":"67500",
    "sg:province":"Alsace",
    "wof:name":"Mondia Division - Sanara Est S.a.",
    "wof:placetype":"venue"
},
  "geometry": {"coordinates":[7.788681,48.814358],"type":"Point"}
}