{
  "type": "Feature",
  "properties": {
    "iso:country":"FR",
    "sg:address":"46, Rue de la Tour, 75016 Paris",
    "sg:orig_category":"Unclassifiable Establishments",
    "sg:phone":"+33 1 73 00 55 00",
    "sg:province":"Ile de France",
    "wof:name":"Soft Computing S.a.",
    "wof:placetype":"venue"
},
  "geometry": {"coordinates":[2.281931,48.859932],"type":"Point"}
}