{
  "type": "Feature",
  "properties": {
    "addr:full":"105, Cours du G\u00e9n\u00e9ral de Gaulle, 33170 Gradignan Gradignan Aquitaine 33170",
    "addr:housenumber":"105",
    "addr:postcode":"33170;33170",
    "addr:street":"Cours Du Ge\u0301Ne\u0301Ral De Gaulle",
    "iso:country":"FR",
    "sg:address":"105, Cours du G\u00e9n\u00e9ral de Gaulle, 33170 Gradignan",
    "sg:city":"Gradignan",
    "sg:orig_category":"Unclassifiable Establishments",
    "sg:phone":"+33 5 56 89 06 09",
    "sg:postcode":"33170",
    "sg:province":"Aquitaine",
    "wof:name":"Soci\u00e9t\u00e9 Bouniord Et Fils S.a.r.l.",
    "wof:placetype":"venue"
},
  "geometry": {"coordinates":[-0.611429,44.776169],"type":"Point"}
}