{
  "type": "Feature",
  "properties": {
    "addr:full":"181 ave de Clichy; Paris; 75017 Ile de France 75017",
    "addr:housenumber":"181",
    "addr:postcode":"75017 ile;france 75017",
    "addr:street":"Ave De Clichy",
    "iso:country":"FR",
    "sg:address":"181 ave de Clichy; Paris; 75017",
    "sg:classifiers":[
        {
            "category":"Banks & Credit Unions",
            "subcategory":"Bank",
            "type":"Services"
        }
    ],
    "sg:phone":"+33 1 42 29 30 60",
    "sg:postcode":"75017",
    "sg:province":"Ile de France",
    "wof:name":"Banque Commerciale, Du Maroc Sa",
    "wof:placetype":"venue"
},
  "geometry": {"coordinates":[2.315619,48.893005],"type":"Point"}
}