{
  "type": "Feature",
  "properties": {
    "addr:full":"73 Rue Jules C\u00e9sar 02100 St Quentin Picardie 02100",
    "addr:housenumber":"73",
    "addr:postcode":"02100;02100",
    "addr:street":"Rue Jules Ce\u0301Sar",
    "iso:country":"FR",
    "sg:address":"73 Rue Jules C\u00e9sar 02100 St Quentin",
    "sg:classifiers":[
        {
            "category":"Manufacturing",
            "subcategory":"Metals",
            "type":"Manufacturing & Wholesale Goods"
        }
    ],
    "sg:phone":"+33 3 23 68 12 96",
    "sg:postcode":"02100",
    "sg:province":"Picardie",
    "sg:tags":[
        "metallurgy",
        "steel",
        "metalworking"
    ],
    "wof:name":"Ets Michel Sauvage Sarl",
    "wof:placetype":"venue"
},
  "geometry": {"coordinates":[3.297645,49.837025],"type":"Point"}
}