{
  "type": "Feature",
  "properties": {
    "addr:full":"76, Rue du G\u00e9n\u00e9ral de Gaulle, 67310 Wasselonne Wasselonne Alsace 67310",
    "addr:housenumber":"76",
    "addr:postcode":"67310;67310",
    "addr:street":"Rue Du Ge\u0301Ne\u0301Ral De Gaulle",
    "iso:country":"FR",
    "sg:address":"76, Rue du G\u00e9n\u00e9ral de Gaulle, 67310 Wasselonne",
    "sg:city":"Wasselonne",
    "sg:orig_category":"Unclassifiable Establishments",
    "sg:phone":"+33 3 88 87 04 50",
    "sg:postcode":"67310",
    "sg:province":"Alsace",
    "wof:name":"Loroch Et Compagnie S.a.r.l.",
    "wof:placetype":"venue"
},
  "geometry": {"coordinates":[7.444943,48.637856],"type":"Point"}
}