{
  "type": "Feature",
  "properties": {
    "addr:full":"1091 Av De La Boisse 73000 Chamb\u00e9ry Rhone-Alpes 73000",
    "addr:housenumber":"1091",
    "addr:postcode":"73000;73000",
    "addr:street":"Av De La Boisse",
    "iso:country":"FR",
    "sg:address":"1091 Av De La Boisse 73000 Chamb\u00e9ry",
    "sg:classifiers":[
        {
            "category":"Building & Trades",
            "subcategory":"Construction",
            "type":"Services"
        }
    ],
    "sg:phone":"+33 4 79 68 27 27",
    "sg:postcode":"73000",
    "sg:province":"Rhone-Alpes",
    "sg:tags":[
        "work",
        "public"
    ],
    "wof:name":"Spie Tondella Sa",
    "wof:placetype":"venue"
},
  "geometry": {"coordinates":[5.912948,45.579247],"type":"Point"}
}