{
  "type": "Feature",
  "properties": {
    "addr:full":"56 boulevard du Courcerin 77183 Croissy Beaubourg Ile de France",
    "addr:housenumber":"56",
    "addr:postcode":"77183",
    "addr:street":"Boulevard Du Courcerin",
    "iso:country":"FR",
    "sg:address":"56 boulevard du Courcerin 77183 Croissy Beaubourg",
    "sg:classifiers":[
        {
            "category":"Wholesale",
            "subcategory":"Plants",
            "type":"Manufacturing & Wholesale Goods"
        }
    ],
    "sg:phone":"+33 1 60 05 02 22",
    "sg:province":"Ile de France",
    "sg:tags":[
        "pressure",
        "drainage"
    ],
    "wof:name":"Zedrys-zeolite Drying System S.a.",
    "wof:placetype":"venue"
},
  "geometry": {"coordinates":[2.630618,48.82476],"type":"Point"}
}