{
  "type": "Feature",
  "properties": {
    "addr:full":"14, Rue Cl\u00e9ment Bayard, 92300 Levallois Perret Ile de France",
    "addr:housenumber":"14",
    "addr:postcode":"92300;ile",
    "addr:street":"Rue Cle\u0301Ment Bayard",
    "iso:country":"FR",
    "sg:address":"14, Rue Cl\u00e9ment Bayard, 92300 Levallois Perret",
    "sg:orig_category":"Non-Classified Establishments",
    "sg:phone":"+33 1 42 70 19 80",
    "sg:province":"Ile de France",
    "wof:name":"Kick Off S.a.r.l.",
    "wof:placetype":"venue"
},
  "geometry": {"coordinates":[2.283668,48.898438],"type":"Point"}
}