{
  "type": "Feature",
  "properties": {
    "addr:full":"2 Rue Des Vignes 17260 Montpellier De Medillan Poitou-Charentes 17260",
    "addr:housenumber":"2",
    "addr:postcode":"17260;17260",
    "addr:street":"Rue Des Vignes;Medillan",
    "iso:country":"FR",
    "sg:address":"2 Rue Des Vignes 17260 Montpellier De Medillan",
    "sg:classifiers":[
        {
            "category":"Farming",
            "subcategory":"Crops",
            "type":"Manufacturing & Wholesale Goods"
        }
    ],
    "sg:phone":"+33 5 46 90 07 61",
    "sg:postcode":"17260",
    "sg:province":"Poitou-Charentes",
    "sg:tags":[
        "vegetable",
        "fruit",
        "agriculture",
        "livestock"
    ],
    "wof:name":"Picoulet Jean Claude",
    "wof:placetype":"venue"
},
  "geometry": {"coordinates":[-0.62872,45.543926],"type":"Point"}
}