{
  "type": "Feature",
  "properties": {
    "iso:country":"FR",
    "sg:address":"12, Rue du Clos Fleury, 74100 Annemasse",
    "sg:orig_category":"Unclassifiable Establishments",
    "sg:phone":"+33 4 50 95 05 80",
    "sg:postcode":"74100",
    "sg:province":"Rhone-Alpes",
    "wof:name":"Cabinet Expert Comptable J.p. Blanc S.a.",
    "wof:placetype":"venue"
},
  "geometry": {"coordinates":[6.232476,46.192436],"type":"Point"}
}