{
  "type": "Feature",
  "properties": {
    "addr:full":"611, Av. Daniel Dreyfous Ducas, 78520 Limay Ile de France",
    "addr:housenumber":"611",
    "addr:postcode":"78520",
    "addr:street":"Av. Daniel Dreyfous Ducas;Ile De France",
    "iso:country":"FR",
    "sg:address":"611, Av. Daniel Dreyfous Ducas, 78520 Limay",
    "sg:orig_category":"Non-Classified Establishments",
    "sg:phone":"+33 1 30 98 02 98",
    "sg:province":"Ile de France",
    "wof:name":"Jean D'huart Et Compagnie S.a.",
    "wof:placetype":"venue"
},
  "geometry": {"coordinates":[1.73261,48.994545],"type":"Point"}
}