{
  "type": "Feature",
  "properties": {
    "addr:full":"2 avenue Foch 76600 Le Havre Haute Normandie 76600",
    "addr:housenumber":"2",
    "addr:postcode":"76600;76600",
    "addr:street":"Avenue Foch",
    "iso:country":"FR",
    "sg:address":"2 avenue Foch 76600 Le Havre",
    "sg:classifiers":[
        {
            "category":"Shopping",
            "subcategory":"Computers & Home Electronics",
            "type":"Retail Goods"
        }
    ],
    "sg:phone":"+33 2 35 19 66 66",
    "sg:postcode":"76600",
    "sg:province":"Haute Normandie",
    "sg:tags":[
        "import",
        "african"
    ],
    "wof:name":"Scamar Sa",
    "wof:placetype":"venue"
},
  "geometry": {"coordinates":[0.096679,49.493519],"type":"Point"}
}