{
  "type": "Feature",
  "properties": {
    "addr:full":"ZI Ravennes les Francs Bondues Nord Pas-de-Calais 59910",
    "addr:postcode":"59910",
    "addr:street":"Pas-De-Calais",
    "iso:country":"FR",
    "sg:address":"ZI Ravennes les Francs",
    "sg:city":"Bondues",
    "sg:orig_category":"Non-Classified Establishments",
    "sg:phone":"+33 3 20 26 86 55",
    "sg:postcode":"59910",
    "sg:province":"Nord Pas-de-Calais",
    "wof:name":"Publi-screen S.a.",
    "wof:placetype":"venue"
},
  "geometry": {"coordinates":[3.092863,50.703629],"type":"Point"}
}