{
  "type": "Feature",
  "properties": {
    "iso:country":"FR",
    "sg:address":"453, Av du Breuil, 25461 Etupes",
    "sg:orig_category":"Unclassifiable Establishments",
    "sg:phone":"+33 3 81 99 35 00",
    "sg:province":"Franche-Comt\u00e9",
    "wof:name":"Edefi Cao S.a.",
    "wof:placetype":"venue"
},
  "geometry": {"coordinates":[6.862814,47.506931],"type":"Point"}
}