{
  "type": "Feature",
  "properties": {
    "iso:country":"FR",
    "sg:address":"Zi St Ulfrand Ouest 27500 Pont Audemer",
    "sg:classifiers":[
        {
            "category":"Manufacturing",
            "subcategory":"Tools & Machinery",
            "type":"Manufacturing & Wholesale Goods"
        }
    ],
    "sg:phone":"+33 2 32 56 77 00",
    "sg:postcode":"27500",
    "sg:province":"Haute Normandie",
    "sg:tags":[
        "equipment",
        "measurement",
        "-",
        "precision",
        "instrument"
    ],
    "wof:name":"Schlumberger Industries Sa",
    "wof:placetype":"venue"
},
  "geometry": {"coordinates":[0.514265,49.354889],"type":"Point"}
}