{
  "type": "Feature",
  "properties": {
    "iso:country":"FR",
    "sg:address":"19 Avenue Saint-Vincent De Paul 40100 Dax",
    "sg:city":"Dax",
    "sg:classifiers":[
        {
            "category":"Professional",
            "subcategory":"Advertising",
            "type":"Services"
        }
    ],
    "sg:phone":"+33 5 58 56 11 63",
    "sg:postcode":"40100",
    "sg:province":"Aquitaine",
    "sg:tags":[
        "information",
        "medium",
        "communication"
    ],
    "wof:name":"Photo Vit Sarl",
    "wof:placetype":"venue"
},
  "geometry": {"coordinates":[-1.054468,43.714325],"type":"Point"}
}