{
  "type": "Feature",
  "properties": {
    "iso:country":"FR",
    "sg:address":"40 Rue De Rochechouart 75009 Paris",
    "sg:classifiers":[
        {
            "category":"Shopping",
            "subcategory":"Clothing, Apparel, & Fashions",
            "type":"Retail Goods"
        }
    ],
    "sg:phone":"+33 1 48 78 67 94",
    "sg:postcode":"75009",
    "sg:province":"Ile de France",
    "sg:tags":[
        "textile",
        "clothing",
        "clothes"
    ],
    "wof:name":"Sarah Lazure",
    "wof:placetype":"venue"
},
  "geometry": {"coordinates":[2.345788,48.879196],"type":"Point"}
}