{
  "type": "Feature",
  "properties": {
    "iso:country":"FR",
    "sg:address":"Rte Bacqueville",
    "sg:city":"Val de Sa\u00e2ne",
    "sg:orig_category":"Non-Classified Establishments",
    "sg:phone":"+33 2 35 32 30 43",
    "sg:postcode":"76890",
    "sg:province":"Haute Normandie",
    "wof:name":"Heurtevent Industrie S.a.r.l.",
    "wof:placetype":"venue"
},
  "geometry": {"coordinates":[1.02931,49.615215],"type":"Point"}
}