{
  "type": "Feature",
  "properties": {
    "iso:country":"FR",
    "sg:address":"41 R De La R\u00e9galle 77181 Courtry",
    "sg:classifiers":[
        {
            "category":"Manufacturing",
            "subcategory":"Metals",
            "type":"Manufacturing & Wholesale Goods"
        }
    ],
    "sg:phone":"+33 1 60 08 92 33",
    "sg:postcode":"77181",
    "sg:province":"Ile de France",
    "sg:tags":[
        "metallurgy",
        "metalworking",
        "processing"
    ],
    "wof:name":"Cmec",
    "wof:placetype":"venue"
},
  "geometry": {"coordinates":[2.605366,48.90715],"type":"Point"}
}