{
  "type": "Feature",
  "properties": {
    "addr:full":"22, Av. Gaston Doumergue, 31130 Balma Midi Pyr\u00e9n\u00e9es",
    "addr:postcode":"31130",
    "addr:street":"22 Av. Gaston Doumergue",
    "iso:country":"FR",
    "sg:address":"22, Av. Gaston Doumergue, 31130 Balma",
    "sg:orig_category":"Non-Classified Establishments",
    "sg:phone":"+33 5 61 24 30 87",
    "sg:province":"Midi Pyr\u00e9n\u00e9es",
    "wof:name":"Rival Production S.a.r.l.",
    "wof:placetype":"venue"
},
  "geometry": {"coordinates":[1.501917,43.62104],"type":"Point"}
}