{
  "type": "Feature",
  "properties": {
    "iso:country":"FR",
    "sg:address":"1 Rue Marcel Gauthier 63610 Besse Et St Anastaise",
    "sg:city":"Besse-et-Saint-Anastaise",
    "sg:classifiers":[
        {
            "category":"Travel",
            "subcategory":"Hotels & Motels",
            "type":"Entertainment"
        }
    ],
    "sg:phone":"+33 4 73 79 60 15",
    "sg:postcode":"63610",
    "sg:province":"Auvergne",
    "sg:tags":[
        "hotels",
        "business",
        "restaurant"
    ],
    "wof:name":"Hotel Gergovia",
    "wof:placetype":"venue"
},
  "geometry": {"coordinates":[2.93213,45.510139],"type":"Point"}
}