{
  "type": "Feature",
  "properties": {
    "addr:full":"Zac De Mestre Marty 47310 Estillac Estillac Aquitaine 47310",
    "addr:postcode":"47310;47310",
    "addr:street":"Zac De Mestre Marty",
    "iso:country":"FR",
    "sg:address":"Zac De Mestre Marty 47310 Estillac",
    "sg:city":"Estillac",
    "sg:classifiers":[
        {
            "category":"Autos & Motor Vehicles",
            "subcategory":"Automobile Sales",
            "type":"Retail Goods"
        }
    ],
    "sg:phone":"+33 5 53 68 38 63",
    "sg:postcode":"47310",
    "sg:province":"Aquitaine",
    "sg:tags":[
        "equipment",
        "industrial",
        "transport"
    ],
    "wof:name":"Equipements Frigorifiques Routiers (efr)",
    "wof:placetype":"venue"
},
  "geometry": {"coordinates":[0.563847,44.157024],"type":"Point"}
}