{
  "type": "Feature",
  "properties": {
    "iso:country":"FR",
    "sg:address":"Rte de la Pellerine - ZA",
    "sg:city":"Saint Pierre des Landes",
    "sg:orig_category":"Non-Classified Establishments",
    "sg:phone":"+33 2 43 05 90 36",
    "sg:postcode":"53500",
    "sg:province":"Pays de Loire",
    "wof:name":"Transports Bouhallier S.a.",
    "wof:placetype":"venue"
},
  "geometry": {"coordinates":[-1.027721,48.273811],"type":"Point"}
}