{
  "type": "Feature",
  "properties": {
    "addr:full":"21, Av. Georges Pompidou - Immeuble Danica B, 69486 Lyon C\u00e9dex 3 Haute Normandie",
    "addr:housenumber":"69486;3",
    "addr:street":"21 Av. Georges Pompidou;Ce\u0301Dex;Haute Normandie",
    "iso:country":"FR",
    "sg:address":"21, Av. Georges Pompidou - Immeuble Danica B, 69486 Lyon C\u00e9dex 3",
    "sg:orig_category":"Non-Classified Establishments",
    "sg:phone":"+33 4 72 91 30 08",
    "sg:province":"Haute Normandie",
    "wof:name":"B.m.c. Software",
    "wof:placetype":"venue"
},
  "geometry": {"coordinates":[4.86843,45.751369],"type":"Point"}
}