{
  "type": "Feature",
  "properties": {
    "iso:country":"FR",
    "sg:address":"107 Rue De Guebwiller 68260 Kingersheim",
    "sg:city":"Kingersheim",
    "sg:classifiers":[
        {
            "category":"Home & Garden",
            "subcategory":"Furniture",
            "type":"Retail Goods"
        }
    ],
    "sg:phone":"+33 3 89 50 03 39",
    "sg:postcode":"68260",
    "sg:province":"Alsace",
    "sg:tags":[
        "household",
        "wood"
    ],
    "wof:name":"Societe D'exploitation Des Cuisines De Mulhouse (secm)",
    "wof:placetype":"venue"
},
  "geometry": {"coordinates":[7.315044,47.794636],"type":"Point"}
}