{
  "type": "Feature",
  "properties": {
    "addr:full":"12 Rue Du 8 Mai 1945 78300 Poissy Ile de France",
    "addr:housenumber":"12",
    "addr:postcode":"78300;ile",
    "addr:street":"Rue Du 8 Mai 1945",
    "iso:country":"FR",
    "sg:address":"12 Rue Du 8 Mai 1945 78300 Poissy",
    "sg:classifiers":[
        {
            "category":"Professional",
            "subcategory":"Printing & Photocopies",
            "type":"Services"
        }
    ],
    "sg:phone":"+33 1 39 79 63 20",
    "sg:province":"Ile de France",
    "sg:tags":[
        "publishing"
    ],
    "wof:name":"Le Parisien Snc",
    "wof:placetype":"venue"
},
  "geometry": {"coordinates":[2.043607,48.927704],"type":"Point"}
}