{
  "type": "Feature",
  "properties": {
    "iso:country":"FR",
    "sg:address":"44 Av Cyrille Besset 06184 Nice Cedex 2",
    "sg:classifiers":[
        {
            "category":"Utilities",
            "subcategory":"Telephone",
            "type":"Services"
        }
    ],
    "sg:phone":"+33 4 92 09 30 30",
    "sg:province":"Provence-Alpes-C\u00f4te d'Azur",
    "sg:tags":[
        "telecommunication"
    ],
    "wof:name":"France Telecom",
    "wof:placetype":"venue"
},
  "geometry": {"coordinates":[7.256746,43.716648],"type":"Point"}
}