{
  "type": "Feature",
  "properties": {
    "addr:full":"21 R De Clichy 93584 Saint-Ouen Ile de France",
    "addr:housenumber":"21",
    "addr:postcode":"93584",
    "addr:street":"R De Clichy",
    "iso:country":"FR",
    "sg:address":"21 R De Clichy 93584 Saint-Ouen",
    "sg:classifiers":[
        {
            "category":"Health Services",
            "subcategory":"Podiatrist",
            "type":"Services"
        }
    ],
    "sg:phone":"+33 1 49 48 94 50",
    "sg:province":"Ile de France",
    "sg:tags":[
        "instrument",
        "measurement",
        "-",
        "precision",
        "equipment"
    ],
    "wof:name":"Controlab Sa",
    "wof:placetype":"venue"
},
  "geometry": {"coordinates":[1.63802,48.607769],"type":"Point"}
}