{
  "type": "Feature",
  "properties": {
    "addr:full":"24 R La Pierre Qui Tourne 37400 Amboise Amboise Centre 37400",
    "addr:housenumber":"24",
    "addr:postcode":"37400;37400",
    "addr:street":"R La Pierre Qui Tourne",
    "iso:country":"FR",
    "sg:address":"24 R La Pierre Qui Tourne 37400 Amboise",
    "sg:city":"Amboise",
    "sg:classifiers":[
        {
            "category":"Manufacturing",
            "subcategory":"Wood Products",
            "type":"Manufacturing & Wholesale Goods"
        }
    ],
    "sg:phone":"+33 2 47 57 40 50",
    "sg:postcode":"37400",
    "sg:province":"Centre",
    "sg:tags":[
        "professional",
        "furniture"
    ],
    "wof:name":"M. Puyjalon Patrice P A M.",
    "wof:placetype":"venue"
},
  "geometry": {"coordinates":[0.973771,47.405952],"type":"Point"}
}