{
  "type": "Feature",
  "properties": {
    "iso:country":"FR",
    "sg:address":"A\u00e9rogare 2 - Hall F",
    "sg:city":"Le Mesnil Amelot",
    "sg:orig_category":"Non-Classified Establishments",
    "sg:phone":"+33 1 48 16 29 69",
    "sg:postcode":"77990",
    "sg:province":"Ile de France",
    "wof:name":"Abilis S.a.",
    "wof:placetype":"venue"
},
  "geometry": {"coordinates":[2.590909,49.017994],"type":"Point"}
}