{
  "type": "Feature",
  "properties": {
    "addr:full":"3 Rue De L'Industrie 39400 Morez Franche Comt\u00e9 39400",
    "addr:housenumber":"3",
    "addr:postcode":"39400;39400",
    "addr:street":"Rue De L'Industrie;Franche Comte\u0301",
    "iso:country":"FR",
    "sg:address":"3 Rue De L'Industrie 39400 Morez",
    "sg:classifiers":[
        {
            "category":"Health Services",
            "subcategory":"Optometrist",
            "type":"Services"
        }
    ],
    "sg:phone":"+33 3 84 33 30 21",
    "sg:postcode":"39400",
    "sg:province":"Franche Comt\u00e9",
    "sg:tags":[
        "instrument",
        "optical",
        "-",
        "precision",
        "equipment"
    ],
    "wof:name":"P M V Sarl",
    "wof:placetype":"venue"
},
  "geometry": {"coordinates":[6.021021,46.522213],"type":"Point"}
}