{
  "type": "Feature",
  "properties": {
    "iso:country":"FR",
    "sg:address":"55, Av. Paul Vaillant Couturier, 93220 Gagny",
    "sg:orig_category":"Unclassifiable Establishments",
    "sg:phone":"+33 1 43 09 25 65",
    "sg:province":"Ile de France",
    "wof:name":"Sovipro S.a.r.l.",
    "wof:placetype":"venue"
},
  "geometry": {"coordinates":[2.552866,48.873989],"type":"Point"}
}