{
  "type": "Feature",
  "properties": {
    "iso:country":"FR",
    "sg:address":"R Des Martyrs De La Lib\u00e9ration 69310 Pierre Benite",
    "sg:classifiers":[
        {
            "category":"Government",
            "subcategory":"Department Of Motor Vehicles",
            "type":"Public Place"
        }
    ],
    "sg:phone":"+33 4 72 66 31 20",
    "sg:postcode":"69310",
    "sg:province":"Rhone-Alpes",
    "sg:tags":[
        "equipment",
        "industrial",
        "transport",
        "motor-cars"
    ],
    "wof:name":"General Trailers France Sa",
    "wof:placetype":"venue"
},
  "geometry": {"coordinates":[4.824495,45.700436],"type":"Point"}
}