{
  "type": "Feature",
  "properties": {
    "addr:full":"12 Bd Gabriel Lippman 29850 Gouesnou Gouesnou Bretagne 29850",
    "addr:housenumber":"12",
    "addr:postcode":"29850;29850",
    "addr:street":"Bd Gabriel Lippman",
    "iso:country":"FR",
    "sg:address":"12 Bd Gabriel Lippman 29850 Gouesnou",
    "sg:city":"Gouesnou",
    "sg:classifiers":[
        {
            "category":"Wholesale",
            "subcategory":"Machinery & Supplies",
            "type":"Manufacturing & Wholesale Goods"
        }
    ],
    "sg:phone":"+33 2 98 02 03 26",
    "sg:postcode":"29850",
    "sg:province":"Bretagne",
    "sg:tags":[
        "handling",
        "material",
        "-",
        "machine",
        "equipment",
        "engineering",
        "mechanical"
    ],
    "wof:name":"Bretagne Manutention",
    "wof:placetype":"venue"
},
  "geometry": {"coordinates":[-4.453709,48.428452],"type":"Point"}
}