{
  "type": "Feature",
  "properties": {
    "addr:full":"37, Rte Nationale, 59219 Larouillies Nord Pas-de-Calais",
    "addr:housenumber":"37",
    "addr:postcode":"59219",
    "addr:street":"Rte Nationale",
    "iso:country":"FR",
    "sg:address":"37, Rte Nationale, 59219 Larouillies",
    "sg:orig_category":"Unclassifiable Establishments",
    "sg:phone":"+33 3 27 59 22 63",
    "sg:province":"Nord Pas-de-Calais",
    "wof:name":"Delva Frans S.a.",
    "wof:placetype":"venue"
},
  "geometry": {"coordinates":[3.924563,50.033768],"type":"Point"}
}