{
  "type": "Feature",
  "properties": {
    "iso:country":"FR",
    "sg:address":"Dinard 35800 Dinard",
    "sg:city":"Dinard",
    "sg:classifiers":[
        {
            "category":"Professional",
            "subcategory":"Accounting & Tax Preparation",
            "type":"Services"
        }
    ],
    "sg:phone":"+33 2 99 82 72 00",
    "sg:postcode":"35800",
    "sg:province":"Bretagne",
    "sg:tags":[
        "repair",
        "aircraft",
        "overhaul",
        "maintenance"
    ],
    "wof:name":"Tat Industrie S.a.",
    "wof:placetype":"venue"
},
  "geometry": {"coordinates":[-2.09071,48.617828],"type":"Point"}
}