{
  "type": "Feature",
  "properties": {
    "iso:country":"FR",
    "sg:address":"52",
    "sg:city":"d'Enghien 93800 Epinay sur Seine",
    "sg:classifiers":[
        {
            "category":"Manufacturing",
            "subcategory":"Tools & Machinery",
            "type":"Manufacturing & Wholesale Goods"
        }
    ],
    "sg:phone":"+33 1 49 33 89 33",
    "sg:postcode":"93800",
    "sg:province":"Ile de France",
    "sg:tags":[
        "equipment",
        "measurement",
        "-",
        "precision",
        "instrument"
    ],
    "wof:name":"Le Calibre",
    "wof:placetype":"venue"
},
  "geometry": {"coordinates":[2.307356,48.959862],"type":"Point"}
}