{
  "type": "Feature",
  "properties": {
    "iso:country":"FR",
    "sg:address":"17, Av Jean Foucault, 34500 B\u00e9ziers",
    "sg:orig_category":"Unclassifiable Establishments",
    "sg:phone":"+33 4 67 35 10 84",
    "sg:province":"Languedoc-Roussillon",
    "wof:name":"Soci\u00e9t\u00e9 Nouvelle Silvain S.a.r.l.",
    "wof:placetype":"venue"
},
  "geometry": {"coordinates":[3.263491,43.328281],"type":"Point"}
}