{
  "type": "Feature",
  "properties": {
    "iso:country":"FR",
    "sg:address":"ZAC du Bois de l'Arsot",
    "sg:city":"Valdoie",
    "sg:orig_category":"Non-Classified Establishments",
    "sg:phone":"+33 3 84 26 98 79",
    "sg:postcode":"90300",
    "sg:province":"Franche Comt\u00e9",
    "wof:name":"Objectif Bois S.a.",
    "wof:placetype":"venue"
},
  "geometry": {"coordinates":[6.845019,47.666039],"type":"Point"}
}