{
  "type": "Feature",
  "properties": {
    "addr:full":"17 Bd Des Capucines 75002 Paris Ile de France 75002",
    "addr:housenumber":"17",
    "addr:postcode":"75002;75002",
    "addr:street":"Bd Des Capucines",
    "iso:country":"FR",
    "sg:address":"17 Bd Des Capucines 75002 Paris",
    "sg:classifiers":[
        {
            "category":"Travel",
            "subcategory":"Hotels & Motels",
            "type":"Entertainment"
        }
    ],
    "sg:phone":"+33 1 53 43 82 00",
    "sg:postcode":"75002",
    "sg:province":"Ile de France",
    "sg:tags":[
        "hotels",
        "business",
        "restaurant"
    ],
    "wof:name":"Chez Clement",
    "wof:placetype":"venue"
},
  "geometry": {"coordinates":[2.331974,48.870541],"type":"Point"}
}