{
  "type": "Feature",
  "properties": {
    "iso:country":"FR",
    "sg:address":"Zi Les Taillas 43600 Ste Sigolene",
    "sg:city":"Les Villettes",
    "sg:classifiers":[
        {
            "category":"Manufacturing",
            "subcategory":"Rubber & Plastics",
            "type":"Manufacturing & Wholesale Goods"
        }
    ],
    "sg:phone":"+33 4 71 75 69 70",
    "sg:postcode":"43600",
    "sg:province":"Auvergne",
    "wof:name":"Bancet Sa",
    "wof:placetype":"venue"
},
  "geometry": {"coordinates":[4.23542,45.243401],"type":"Point"}
}