{
  "type": "Feature",
  "properties": {
    "addr:full":"22, Rue Saint Jacques, 72500 Ch\u00e2teau du Loir Pays de Loire",
    "addr:housenumber":"22",
    "addr:postcode":"72500",
    "addr:street":"Rue Saint Jacques;Loir",
    "iso:country":"FR",
    "sg:address":"22, Rue Saint Jacques, 72500 Ch\u00e2teau du Loir",
    "sg:orig_category":"Unclassifiable Establishments",
    "sg:phone":"+33 2 43 79 51 57",
    "sg:province":"Pays de Loire",
    "wof:name":"Zeppelin S.a.r.l.",
    "wof:placetype":"venue"
},
  "geometry": {"coordinates":[0.421428,47.690613],"type":"Point"}
}