{
  "type": "Feature",
  "properties": {
    "addr:full":"2 Rue Ren\u00e9 Cassin Zi Rte De Paris 45300 Pithiviers Courcelles Centre 45300",
    "addr:housenumber":"2",
    "addr:postcode":"45300;45300",
    "addr:street":"Rue Rene\u0301 Cassin Zi Rte De Paris;Courcelles",
    "iso:country":"FR",
    "sg:address":"2 Rue Ren\u00e9 Cassin Zi Rte De Paris 45300 Pithiviers",
    "sg:city":"Courcelles",
    "sg:classifiers":[
        {
            "category":"Banks & Credit Unions",
            "subcategory":"Investment Brokerage",
            "type":"Services"
        }
    ],
    "sg:phone":"+33 2 38 32 36 66",
    "sg:postcode":"45300",
    "sg:province":"Centre",
    "sg:tags":[
        "-",
        "transport",
        "related"
    ],
    "wof:name":"Caroll International",
    "wof:placetype":"venue"
},
  "geometry": {"coordinates":[2.21384,48.064007],"type":"Point"}
}