{
  "type": "Feature",
  "properties": {
    "addr:full":"106BIS rue de Rennes 75006 Paris Ile de France",
    "addr:housenumber":"106bis",
    "addr:postcode":"75006",
    "addr:street":"Rue De Rennes",
    "iso:country":"FR",
    "sg:address":"106BIS rue de Rennes 75006 Paris",
    "sg:orig_category":"Non-Classified Establishments",
    "sg:phone":"+33 1 42 22 62 80",
    "sg:province":"Ile de France",
    "wof:name":"Sciama Sa",
    "wof:placetype":"venue"
},
  "geometry": {"coordinates":[2.328354,48.848839],"type":"Point"}
}