{
  "type": "Feature",
  "properties": {
    "iso:country":"FR",
    "sg:address":"B.P. 85, 63307 Thiers C\u00e9dex^^ZI Felet, 63300 Thiers",
    "sg:city":"Thiers",
    "sg:orig_category":"Non-Classified Establishments",
    "sg:phone":"+33 4 73 51 65 00",
    "sg:postcode":"63300",
    "sg:province":"Auvergne",
    "wof:name":"Wichard S.a.",
    "wof:placetype":"venue"
},
  "geometry": {"coordinates":[3.563396,45.82058],"type":"Point"}
}