{
  "type": "Feature",
  "properties": {
    "addr:full":"9 Rue Eug\u00e8ne Varlin 76120 Le Grand Quevilly Haute Normandie 76120",
    "addr:housenumber":"9",
    "addr:postcode":"76120;76120",
    "addr:street":"Rue Euge\u0300Ne Varlin;Haute Normandie",
    "iso:country":"FR",
    "sg:address":"9 Rue Eug\u00e8ne Varlin 76120 Le Grand Quevilly",
    "sg:orig_category":"Business advice and other services Finished goods - metallic Metallurgy and Metalworking Sheets and ",
    "sg:phone":"+33 2 32 11 50 80",
    "sg:postcode":"76120",
    "sg:province":"Haute Normandie",
    "wof:name":"Ets Ponticelli Freres Sa",
    "wof:placetype":"venue"
},
  "geometry": {"coordinates":[1.029066,49.407578],"type":"Point"}
}