{
  "type": "Feature",
  "properties": {
    "iso:country":"FR",
    "sg:address":"B.P. 323, 59336 Tourcoing C\u00e9dex^^12, Rue Duguay Trouin, 59200 Tourcoing",
    "sg:orig_category":"Non-Classified Establishments",
    "sg:phone":"+33 3 20 76 42 31",
    "sg:province":"Nord Pas-de-Calais",
    "wof:name":"M.a.l.i.p. S.a. - Manufacture Linselloise De Plastiques",
    "wof:placetype":"venue"
},
  "geometry": {"coordinates":[3.159375,50.722389],"type":"Point"}
}