{
  "type": "Feature",
  "properties": {
    "iso:country":"FR",
    "sg:address":"Chem De Halage BP 25 45120 Ch\u00e2lette Sur Loing",
    "sg:city":"Cepoy",
    "sg:classifiers":[
        {
            "category":"Professional",
            "type":"Services"
        }
    ],
    "sg:phone":"+33 2 38 89 70 00",
    "sg:postcode":"45120",
    "sg:province":"Centre",
    "sg:tags":[
        "transport",
        "road"
    ],
    "wof:name":"Transports Pierre Janssens",
    "wof:placetype":"venue"
},
  "geometry": {"coordinates":[2.731191,48.014793],"type":"Point"}
}