{
  "type": "Feature",
  "properties": {
    "iso:country":"FR",
    "sg:address":"142 Av G\u00e9n\u00e9ral de Gaulle; Pornichet",
    "sg:classifiers":[
        {
            "category":"Banks & Credit Unions",
            "subcategory":"Bank",
            "type":"Services"
        }
    ],
    "sg:phone":"+33 3340610412",
    "sg:province":"Pays de Loire",
    "wof:name":"Banque Cio",
    "wof:placetype":"venue"
},
  "geometry": {"coordinates":[-2.339569,47.261452],"type":"Point"}
}