{
  "type": "Feature",
  "properties": {
    "addr:full":"ZI de l'Albanne La Ravoire Rhone-Alpes 73490",
    "addr:postcode":"73490",
    "addr:street":"Zi De L'Albanne La;Rhone-Alpes",
    "iso:country":"FR",
    "sg:address":"ZI de l'Albanne",
    "sg:city":"La Ravoire",
    "sg:orig_category":"Non-Classified Establishments",
    "sg:phone":"+33 4 79 28 28 22",
    "sg:postcode":"73490",
    "sg:province":"Rhone-Alpes",
    "wof:name":"Entrepose S.a.",
    "wof:placetype":"venue"
},
  "geometry": {"coordinates":[5.958541,45.546753],"type":"Point"}
}