{
  "type": "Feature",
  "properties": {
    "addr:full":"Fbg Collini\u00e8re 52200 Langres Champagne",
    "addr:postcode":"52200",
    "iso:country":"FR",
    "sg:address":"Fbg Collini\u00e8re 52200 Langres",
    "sg:classifiers":[
        {
            "category":"Professional",
            "type":"Services"
        }
    ],
    "sg:phone":"+33 3 25 87 47 12",
    "sg:province":"Champagne",
    "sg:tags":[
        "transport",
        "road"
    ],
    "wof:name":"Oertli Sa",
    "wof:placetype":"venue"
},
  "geometry": {"coordinates":[5.329666,47.86681],"type":"Point"}
}