{
  "type": "Feature",
  "properties": {
    "iso:country":"FR",
    "sg:address":"Rue du Lavoir",
    "sg:city":"Roy\u00e8re de Vassivi\u00e8re",
    "sg:orig_category":"Non-Classified Establishments",
    "sg:phone":"+33 5 55 64 71 20",
    "sg:postcode":"23460",
    "sg:province":"Limousin",
    "wof:name":"Pateyron Georgette",
    "wof:placetype":"venue"
},
  "geometry": {"coordinates":[1.9094,45.840664],"type":"Point"}
}