{
  "type": "Feature",
  "properties": {
    "addr:full":"route de Blanzac 16120 CHATEAUNEUF SUR CHARENTE Poitou-Charentes 16120",
    "addr:postcode":"16120;16120",
    "addr:street":"Route De Blanzac",
    "iso:country":"FR",
    "sg:address":"route de Blanzac 16120 CHATEAUNEUF SUR CHARENTE",
    "sg:classifiers":[
        {
            "category":"Autos & Motor Vehicles",
            "subcategory":"Auto Supplies",
            "type":"Retail Goods"
        }
    ],
    "sg:phone":"+33 5 45 66 61 61",
    "sg:postcode":"16120",
    "sg:province":"Poitou-Charentes",
    "sg:tags":[
        "electric"
    ],
    "wof:name":"Bertrand Polico S.a.",
    "wof:placetype":"venue"
},
  "geometry": {"coordinates":[-0.065611,45.515121],"type":"Point"}
}