{
  "type": "Feature",
  "properties": {
    "iso:country":"FR",
    "sg:address":"Chemin Catupolan",
    "sg:city":"Vaulx en Velin",
    "sg:orig_category":"Unclassifiable Establishments",
    "sg:phone":"+33 4 72 15 08 08",
    "sg:postcode":"69120",
    "sg:province":"Rhone-Alpes",
    "wof:name":"A.p.m.g. S.a. - Atelier De Pr\u00e9cision Et De M\u00e9canique G\u00e9n\u00e9rale",
    "wof:placetype":"venue"
},
  "geometry": {"coordinates":[4.932021,45.762516],"type":"Point"}
}