{
  "type": "Feature",
  "properties": {
    "addr:full":"25, Rue Emile Zola, 59239 Thumeries Nord Pas-de-Calais",
    "addr:housenumber":"25",
    "addr:postcode":"59239",
    "addr:street":"Rue Emile Zola",
    "iso:country":"FR",
    "sg:address":"25, Rue Emile Zola, 59239 Thumeries",
    "sg:orig_category":"Unclassifiable Establishments",
    "sg:phone":"+33 3 20 86 99 52",
    "sg:province":"Nord Pas-de-Calais",
    "wof:name":"Milleville Anciens Etablissements S.a.r.l.",
    "wof:placetype":"venue"
},
  "geometry": {"coordinates":[3.059163,50.478024],"type":"Point"}
}