{
  "type": "Feature",
  "properties": {
    "iso:country":"FR",
    "sg:address":"111 Route d'Ingwiller 57620 GOETZENBRUCK",
    "sg:classifiers":[
        {
            "category":"Real Estate",
            "subcategory":"Real Estate Operator",
            "type":"Services"
        }
    ],
    "sg:phone":"+33 3 87 96 80 55",
    "sg:postcode":"57620",
    "sg:province":"Lorraine",
    "sg:tags":[
        "flat",
        "working",
        "glass"
    ],
    "wof:name":"M.m.g. Sarl",
    "wof:placetype":"venue"
},
  "geometry": {"coordinates":[7.379759,48.976906],"type":"Point"}
}