{
  "type": "Feature",
  "properties": {
    "iso:country":"FR",
    "sg:address":"B.P. 39, 49241 Avrill\u00e9 C\u00e9dex^^ZI la Beurri\u00e8re, 49240 Avrill\u00e9",
    "sg:orig_category":"Non-Classified Establishments",
    "sg:phone":"+33 2 41 21 25 00",
    "sg:province":"Pays de Loire",
    "wof:name":"Psm Fixation S.a.",
    "wof:placetype":"venue"
},
  "geometry": {"coordinates":[-0.587263,47.504822],"type":"Point"}
}