{
  "type": "Feature",
  "properties": {
    "iso:country":"FR",
    "sg:address":"33 rue Paul Langevin 49240 Avrille",
    "sg:orig_category":"Exterior Vibrators",
    "sg:phone":"+33 2 41 42 39 76",
    "sg:postcode":"49240",
    "sg:province":"Pays de Loire",
    "wof:name":"Pajot Sa",
    "wof:placetype":"venue"
},
  "geometry": {"coordinates":[-0.612301,47.517056],"type":"Point"}
}