{
  "type": "Feature",
  "properties": {
    "iso:country":"FR",
    "sg:address":"867 Avenue De La Republique 59700 Marcq En Baroeul",
    "sg:classifiers":[
        {
            "category":"Professional",
            "subcategory":"Business Services",
            "type":"Services"
        }
    ],
    "sg:phone":"+33 3 28 33 77 00",
    "sg:postcode":"59700",
    "sg:province":"Nord Pas-de-Calais",
    "sg:tags":[
        "advice",
        "telecommunication"
    ],
    "wof:name":"Danka France",
    "wof:placetype":"venue"
},
  "geometry": {"coordinates":[3.092353,50.659615],"type":"Point"}
}