{
  "type": "Feature",
  "properties": {
    "addr:full":"28, Av Champlain, 76100 Rouen Haute Normandie 76100",
    "addr:postcode":"76100;76100",
    "addr:street":"28 Av Champlain;Haute Normandie",
    "iso:country":"FR",
    "sg:address":"28, Av Champlain, 76100 Rouen",
    "sg:orig_category":"Non-Classified Establishments",
    "sg:phone":"+33 2 35 63 07 87",
    "sg:postcode":"76100",
    "sg:province":"Haute Normandie",
    "wof:name":"C.r.i.t. Int\u00e9rim S.a.",
    "wof:placetype":"venue"
},
  "geometry": {"coordinates":[1.092892,49.434235],"type":"Point"}
}