{
  "type": "Feature",
  "properties": {
    "addr:full":"La Prade Zi 12850 Onet Le Chateau Midi Pyr\u00e9n\u00e9es",
    "addr:postcode":"12850",
    "addr:street":"La Prade Zi",
    "iso:country":"FR",
    "sg:address":"La Prade Zi 12850 Onet Le Chateau",
    "sg:classifiers":[
        {
            "category":"Home & Garden",
            "subcategory":"Furniture",
            "type":"Retail Goods"
        }
    ],
    "sg:phone":"+33 5 65 67 21 11",
    "sg:province":"Midi Pyr\u00e9n\u00e9es",
    "sg:tags":[
        "wood"
    ],
    "wof:name":"Ets Pierre Catusse Filature Des Landes",
    "wof:placetype":"venue"
},
  "geometry": {"coordinates":[2.655292,44.306908],"type":"Point"}
}