{
  "type": "Feature",
  "properties": {
    "iso:country":"FR",
    "sg:address":"ZA Belchamp",
    "sg:city":"Valentigney",
    "sg:orig_category":"Unclassifiable Establishments",
    "sg:phone":"+33 3 81 30 68 43",
    "sg:postcode":"25700",
    "sg:province":"Franche Comt\u00e9",
    "wof:name":"Rota S.a.",
    "wof:placetype":"venue"
},
  "geometry": {"coordinates":[6.837825,47.464218],"type":"Point"}
}