{
  "type": "Feature",
  "properties": {
    "addr:full":"41, Rue Saint S\u00e9bastien, 75011 Paris Ile de France",
    "addr:housenumber":"41",
    "addr:postcode":"75011",
    "addr:street":"Rue Saint Se\u0301Bastien",
    "iso:country":"FR",
    "sg:address":"41, Rue Saint S\u00e9bastien, 75011 Paris",
    "sg:orig_category":"Unclassifiable Establishments",
    "sg:phone":"+33 1 49 29 11 00",
    "sg:province":"Ile de France",
    "wof:name":"Comptoir Saint S\u00e9bastien S.a.r.l.",
    "wof:placetype":"venue"
},
  "geometry": {"coordinates":[2.37124,48.861797],"type":"Point"}
}