{
  "type": "Feature",
  "properties": {
    "iso:country":"FR",
    "sg:address":"ZA",
    "sg:city":"Saint Denis d'Orques",
    "sg:orig_category":"Unclassifiable Establishments",
    "sg:phone":"+33 2 43 88 23 80",
    "sg:postcode":"72350",
    "sg:province":"Pays de Loire",
    "wof:name":"D.m.p. S.a. - D\u00e9veloppement Et Moulage En Plastiques",
    "wof:placetype":"venue"
},
  "geometry": {"coordinates":[-0.272504,48.029125],"type":"Point"}
}