{
  "type": "Feature",
  "properties": {
    "addr:full":"10 Rue Lambert 59191 Ligny En Cambr\u00e9sis Nord Pas-de-Calais 59191",
    "addr:housenumber":"10",
    "addr:postcode":"59191;59191",
    "addr:street":"Rue Lambert;Pas-De-Calais",
    "iso:country":"FR",
    "sg:address":"10 Rue Lambert 59191 Ligny En Cambr\u00e9sis",
    "sg:classifiers":[
        {
            "category":"Professional",
            "subcategory":"Engineering",
            "type":"Services"
        }
    ],
    "sg:phone":"+33 3 27 76 55 00",
    "sg:postcode":"59191",
    "sg:province":"Nord Pas-de-Calais",
    "sg:tags":[
        "machine",
        "-",
        "mechanical"
    ],
    "wof:name":"Mecajet Sa",
    "wof:placetype":"venue"
},
  "geometry": {"coordinates":[3.383653,50.099113],"type":"Point"}
}