{
  "type": "Feature",
  "properties": {
    "addr:full":"31 Rue Colbert 35300 Foug\u00e8res Foug\u00e8res Bretagne 35300",
    "addr:housenumber":"31",
    "addr:postcode":"35300;35300",
    "addr:street":"Rue Colbert",
    "iso:country":"FR",
    "sg:address":"31 Rue Colbert 35300 Foug\u00e8res",
    "sg:city":"Foug\u00e8res",
    "sg:classifiers":[
        {
            "category":"Home & Garden",
            "subcategory":"Furniture",
            "type":"Retail Goods"
        }
    ],
    "sg:phone":"+33 2 99 99 03 89",
    "sg:postcode":"35300",
    "sg:province":"Bretagne",
    "sg:tags":[
        "wood"
    ],
    "wof:name":"Menuiserie Helleux Sarl",
    "wof:placetype":"venue"
},
  "geometry": {"coordinates":[-1.174333,48.340511],"type":"Point"}
}