{
  "type": "Feature",
  "properties": {
    "addr:full":"rue Aranoa 64200 Biarritz Biarritz Aquitaine 64200",
    "addr:postcode":"64200;64200",
    "addr:street":"Rue Aranoa",
    "iso:country":"FR",
    "sg:address":"rue Aranoa 64200 Biarritz",
    "sg:city":"Biarritz",
    "sg:classifiers":[
        {
            "category":"Food & Beverages",
            "subcategory":"Fruits & Vegetables",
            "type":"Retail Goods"
        }
    ],
    "sg:phone":"+33 5 59 43 80 00",
    "sg:postcode":"64200",
    "sg:province":"Aquitaine",
    "sg:tags":[
        "juice",
        "nectar"
    ],
    "wof:name":"Cooperative Bureau Couecou",
    "wof:placetype":"venue"
},
  "geometry": {"coordinates":[-1.553884,43.451778],"type":"Point"}
}