{
  "type": "Feature",
  "properties": {
    "iso:country":"FR",
    "sg:address":"ZI La Martinerie - B\u00e2t 13",
    "sg:city":"Diors",
    "sg:orig_category":"Non-Classified Establishments",
    "sg:phone":"+33 2 54 22 01 31",
    "sg:postcode":"36130",
    "sg:province":"Centre",
    "wof:name":"A.t.a.c. Industrie S.a.r.l. - Atelier T\u00f4lerie Assemblage Du Centre",
    "wof:placetype":"venue"
},
  "geometry": {"coordinates":[1.70056,46.82576],"type":"Point"}
}