{
  "type": "Feature",
  "properties": {
    "iso:country":"FR",
    "sg:address":"175, Rue de Silly, 92100 Boulogne Billancourt",
    "sg:orig_category":"Non-Classified Establishments",
    "sg:phone":"+33 1 46 99 97 17",
    "sg:postcode":"92100",
    "sg:province":"Ile de France",
    "wof:name":"Bruas Philippe",
    "wof:placetype":"venue"
},
  "geometry": {"coordinates":[2.2347,48.831284],"type":"Point"}
}