{
  "type": "Feature",
  "properties": {
    "iso:country":"FR",
    "sg:address":"Rue du Mar\u00e9chal Foch",
    "sg:city":"Phalempin",
    "sg:orig_category":"Unclassifiable Establishments",
    "sg:phone":"+33 3 20 90 28 33",
    "sg:postcode":"59133",
    "sg:province":"Nord Pas-de-Calais",
    "wof:name":"M.g.p. S.a.r.l. - M\u00e9canique G\u00e9n\u00e9rale Phalempinoise",
    "wof:placetype":"venue"
},
  "geometry": {"coordinates":[3.006164,50.519081],"type":"Point"}
}