{
  "type": "Feature",
  "properties": {
    "addr:full":"67 Rte De Nantes 56860 S\u00e9n\u00e9 S\u00e9n\u00e9 Bretagne 56860",
    "addr:housenumber":"67",
    "addr:postcode":"56860;56860",
    "addr:street":"Rte De Nantes",
    "iso:country":"FR",
    "sg:address":"67 Rte De Nantes 56860 S\u00e9n\u00e9",
    "sg:city":"S\u00e9n\u00e9",
    "sg:classifiers":[
        {
            "category":"Wholesale",
            "subcategory":"Machinery & Supplies",
            "type":"Manufacturing & Wholesale Goods"
        }
    ],
    "sg:phone":"+33 2 97 54 34 16",
    "sg:postcode":"56860",
    "sg:province":"Bretagne",
    "sg:tags":[
        "handling",
        "material",
        "-",
        "machine",
        "equipment",
        "engineering",
        "mechanical"
    ],
    "wof:name":"Le Gal (ets) Sa",
    "wof:placetype":"venue"
},
  "geometry": {"coordinates":[-2.711294,47.6492],"type":"Point"}
}