{
  "type": "Feature",
  "properties": {
    "addr:full":"B.P. CE 1410, 91019 Evry C\u00e9dex^^ZI de la Petite Montagne Nord, 91000 Evry Ile de France 91000",
    "addr:postcode":"91019;91000;91000",
    "addr:street":"Petite",
    "iso:country":"FR",
    "sg:address":"B.P. CE 1410, 91019 Evry C\u00e9dex^^ZI de la Petite Montagne Nord, 91000 Evry",
    "sg:orig_category":"Non-Classified Establishments",
    "sg:phone":"+33 1 69 36 68 50",
    "sg:postcode":"91000",
    "sg:province":"Ile de France",
    "wof:name":"Algaflex S.a.s.",
    "wof:placetype":"venue"
},
  "geometry": {"coordinates":[2.4293,48.624664],"type":"Point"}
}