{
  "type": "Feature",
  "properties": {
    "iso:country":"FR",
    "sg:address":"9 Av De La Marne 45000 Orl\u00e9ans",
    "sg:city":"Orl\u00e9ans",
    "sg:classifiers":[
        {
            "category":"Professional",
            "subcategory":"Engineering",
            "type":"Services"
        }
    ],
    "sg:phone":"+33 2 38 86 43 24",
    "sg:postcode":"45000",
    "sg:province":"Centre",
    "sg:tags":[
        "machine",
        "-",
        "mechanical"
    ],
    "wof:name":"Fricom Sa",
    "wof:placetype":"venue"
},
  "geometry": {"coordinates":[1.929434,47.915329],"type":"Point"}
}