{
  "type": "Feature",
  "properties": {
    "addr:full":"Les Blaches Alissas Rhone-Alpes 07210",
    "addr:postcode":"07210",
    "addr:street":"Rhone-Alpes",
    "iso:country":"FR",
    "sg:address":"Les Blaches",
    "sg:city":"Alissas",
    "sg:orig_category":"Non-Classified Establishments",
    "sg:phone":"+33 4 75 64 10 44",
    "sg:postcode":"07210",
    "sg:province":"Rhone-Alpes",
    "wof:name":"Sardem S.a.",
    "wof:placetype":"venue"
},
  "geometry": {"coordinates":[4.624416,44.711838],"type":"Point"}
}