{
  "type": "Feature",
  "properties": {
    "addr:full":"12 Rue Du 4 Septembre 75002 Paris Ile de France",
    "addr:housenumber":"12",
    "addr:postcode":"75002",
    "addr:street":"Rue Du 4 Septembre",
    "iso:country":"FR",
    "sg:address":"12 Rue Du 4 Septembre 75002 Paris",
    "sg:classifiers":[
        {
            "category":"Professional",
            "subcategory":"Printing & Photocopies",
            "type":"Services"
        }
    ],
    "sg:phone":"+33 4 77 43 26 74",
    "sg:province":"Ile de France",
    "sg:tags":[
        "publishing"
    ],
    "wof:name":"Agpa Editions",
    "wof:placetype":"venue"
},
  "geometry": {"coordinates":[2.337097,48.869511],"type":"Point"}
}