{
  "type": "Feature",
  "properties": {
    "addr:full":"Route De Domfront 61100 Flers Flers Basse Normandie 61100",
    "addr:postcode":"61100;61100",
    "addr:street":"Route De Domfront",
    "iso:country":"FR",
    "sg:address":"Route De Domfront 61100 Flers",
    "sg:city":"Flers",
    "sg:classifiers":[
        {
            "category":"Autos & Motor Vehicles",
            "subcategory":"Automobile Sales",
            "type":"Retail Goods"
        }
    ],
    "sg:phone":"+33 2 33 65 77 55",
    "sg:postcode":"61100",
    "sg:province":"Basse Normandie",
    "sg:tags":[
        "equipment",
        "motor-cars",
        "transport"
    ],
    "wof:name":"Manson S A",
    "wof:placetype":"venue"
},
  "geometry": {"coordinates":[-0.583099,48.710281],"type":"Point"}
}