{
  "type": "Feature",
  "properties": {
    "addr:full":"22, Fbg de la S\u00e9auve, 43140 Saint Didier en Velay Saint-Didier-en-Velay Auvergne 43140",
    "addr:housenumber":"22",
    "addr:postcode":"43140;43140",
    "addr:street":"Fbg De La Se\u0301Auve;Didier En Velay",
    "iso:country":"FR",
    "sg:address":"22, Fbg de la S\u00e9auve, 43140 Saint Didier en Velay",
    "sg:city":"Saint-Didier-en-Velay",
    "sg:orig_category":"Unclassifiable Establishments",
    "sg:phone":"+33 4 71 66 22 00",
    "sg:postcode":"43140",
    "sg:province":"Auvergne",
    "wof:name":"E.r.c.e.i. S.a.r.l. - Etudes R\u00e9alisation Commercialisation Exploitation",
    "wof:placetype":"venue"
},
  "geometry": {"coordinates":[4.274041,45.302921],"type":"Point"}
}