{
  "type": "Feature",
  "properties": {
    "addr:full":"B.P. 488, 38312 Bourgoin Jallieu C\u00e9dex^^94, Av. des Cantini\u00e8res, 38300 Ruy Rhone-Alpes 38300",
    "addr:housenumber":"b.p. 488",
    "addr:postcode":"38312;38300;38300",
    "addr:street":"Av. Des Cantinie\u0300Res;Ruy Rhone-Alpes",
    "iso:country":"FR",
    "sg:address":"B.P. 488, 38312 Bourgoin Jallieu C\u00e9dex^^94, Av. des Cantini\u00e8res, 38300 Ruy",
    "sg:orig_category":"Non-Classified Establishments",
    "sg:phone":"+33 4 74 93 38 10",
    "sg:postcode":"38300",
    "sg:province":"Rhone-Alpes",
    "wof:name":"C.r.n.c. S.a. - Cherry Rocher Neyret Chavin",
    "wof:placetype":"venue"
},
  "geometry": {"coordinates":[5.30075,45.4981],"type":"Point"}
}