{
  "type": "Feature",
  "properties": {
    "addr:full":"27, Rue du Docteur Schweitzer, 57130 Ars sur Moselle Lorraine 57130",
    "addr:housenumber":"27",
    "addr:postcode":"57130;57130",
    "addr:street":"Rue Du Docteur Schweitzer",
    "iso:country":"FR",
    "sg:address":"27, Rue du Docteur Schweitzer, 57130 Ars sur Moselle",
    "sg:orig_category":"Non-Classified Establishments",
    "sg:phone":"+33 3 87 60 66 04",
    "sg:postcode":"57130",
    "sg:province":"Lorraine",
    "wof:name":"Escapade S.a.r.l.",
    "wof:placetype":"venue"
},
  "geometry": {"coordinates":[6.082644,49.076519],"type":"Point"}
}