{
  "type": "Feature",
  "properties": {
    "addr:full":"11 Bd Monge 69330 Meyzieu Rhone-Alpes",
    "addr:housenumber":"11",
    "addr:postcode":"69330",
    "addr:street":"Bd Monge",
    "iso:country":"FR",
    "sg:address":"11 Bd Monge 69330 Meyzieu",
    "sg:classifiers":[
        {
            "category":"Manufacturing",
            "subcategory":"Metals",
            "type":"Manufacturing & Wholesale Goods"
        }
    ],
    "sg:phone":"+33 4 72 45 17 90",
    "sg:province":"Rhone-Alpes",
    "sg:tags":[
        "metallurgy",
        "metalworking",
        "processing"
    ],
    "wof:name":"Galvalion Service",
    "wof:placetype":"venue"
},
  "geometry": {"coordinates":[5.021758,45.767307],"type":"Point"}
}