{
  "type": "Feature",
  "properties": {
    "addr:full":"29, Rue Raymond Brosse, 93430 Villetaneuse Ile de France",
    "addr:housenumber":"29",
    "addr:postcode":"93430;ile",
    "addr:street":"Rue Raymond Brosse",
    "iso:country":"FR",
    "sg:address":"29, Rue Raymond Brosse, 93430 Villetaneuse",
    "sg:orig_category":"Unclassifiable Establishments",
    "sg:phone":"+33 1 48 27 00 39",
    "sg:province":"Ile de France",
    "wof:name":"S.m.i. S.a.r.l. - Soci\u00e9t\u00e9 Mat\u00e9riel Imprimerie",
    "wof:placetype":"venue"
},
  "geometry": {"coordinates":[2.346325,48.956123],"type":"Point"}
}