{
  "type": "Feature",
  "properties": {
    "addr:full":"Rue de l'Industrie Briare Centre 45250",
    "addr:postcode":"45250",
    "addr:street":"Rue De L'Industrie Briare",
    "iso:country":"FR",
    "sg:address":"Rue de l'Industrie",
    "sg:city":"Briare",
    "sg:orig_category":"Unclassifiable Establishments",
    "sg:phone":"+33 2 38 29 55 55",
    "sg:postcode":"45250",
    "sg:province":"Centre",
    "wof:name":"Stock Express Briare S.a.",
    "wof:placetype":"venue"
},
  "geometry": {"coordinates":[2.746006,47.627872],"type":"Point"}
}