{
  "type": "Feature",
  "properties": {
    "iso:country":"FR",
    "sg:address":"2, Rue des Cheminots, 43110 Aurec sur Loire",
    "sg:city":"Aurec-sur-Loire",
    "sg:orig_category":"Unclassifiable Establishments",
    "sg:phone":"+33 4 77 35 41 13",
    "sg:postcode":"43110",
    "sg:province":"Auvergne",
    "wof:name":"Gremy S.a.r.l.",
    "wof:placetype":"venue"
},
  "geometry": {"coordinates":[4.199165,45.371586],"type":"Point"}
}