{
  "type": "Feature",
  "properties": {
    "addr:full":"B.P. 429, 18104 Vierzon C\u00e9dex^^16, Rue Albert et Paul Thouvenin, 18100 Vierzon Vierzon Centre 18100",
    "addr:housenumber":"b.p. 429;vierzon",
    "addr:postcode":"18104;18100;centre 18100",
    "addr:street":"Rue Albert Et Paul Thouvenin",
    "iso:country":"FR",
    "sg:address":"B.P. 429, 18104 Vierzon C\u00e9dex^^16, Rue Albert et Paul Thouvenin, 18100 Vierzon",
    "sg:city":"Vierzon",
    "sg:orig_category":"Non-Classified Establishments",
    "sg:phone":"+33 2 48 52 72 00",
    "sg:postcode":"18100",
    "sg:province":"Centre",
    "wof:name":"Distri Centre Logistique S.a.r.l.",
    "wof:placetype":"venue"
},
  "geometry": {"coordinates":[2.020555,47.206581],"type":"Point"}
}