{
  "type": "Feature",
  "properties": {
    "addr:full":"70, Rue Pierre Marty, 25460 Etupes Franche Comt\u00e9",
    "addr:housenumber":"70",
    "addr:postcode":"25460",
    "addr:street":"Rue Pierre Marty;Franche Comte\u0301",
    "iso:country":"FR",
    "sg:address":"70, Rue Pierre Marty, 25460 Etupes",
    "sg:orig_category":"Unclassifiable Establishments",
    "sg:phone":"+33 3 81 31 17 77",
    "sg:province":"Franche Comt\u00e9",
    "wof:name":"Soci\u00e9t\u00e9 Nouvelle Begey S.a.",
    "wof:placetype":"venue"
},
  "geometry": {"coordinates":[6.857835,47.517941],"type":"Point"}
}