{
  "type": "Feature",
  "properties": {
    "addr:full":"12 Rue Du Ladhof 68000 Colmar Colmar Alsace 68000",
    "addr:housenumber":"12",
    "addr:postcode":"68000;68000",
    "addr:street":"Rue Du Ladhof",
    "iso:country":"FR",
    "sg:address":"12 Rue Du Ladhof 68000 Colmar",
    "sg:city":"Colmar",
    "sg:classifiers":[
        {
            "category":"Shopping",
            "subcategory":"Hobbies, Toys, & Games",
            "type":"Retail Goods"
        }
    ],
    "sg:phone":"+33 3 89 41 35 52",
    "sg:postcode":"68000",
    "sg:province":"Alsace",
    "sg:tags":[
        "product",
        "miscellaneous",
        "entertainment"
    ],
    "wof:name":"Atelier De Sculpture Schicke",
    "wof:placetype":"venue"
},
  "geometry": {"coordinates":[7.366421,48.084038],"type":"Point"}
}