{
  "type": "Feature",
  "properties": {
    "iso:country":"FR",
    "sg:address":"Rue d'Aste B\u00e9on - ZI du Haut d'Ossau",
    "sg:city":"Serres Castet",
    "sg:orig_category":"Unclassifiable Establishments",
    "sg:phone":"+33 5 59 33 77 70",
    "sg:postcode":"64121",
    "sg:province":"Aquitaine",
    "wof:name":"Promo Vert S.a.",
    "wof:placetype":"venue"
},
  "geometry": {"coordinates":[-0.3603,43.37347],"type":"Point"}
}