{
  "type": "Feature",
  "properties": {
    "iso:country":"FR",
    "sg:address":"ZA la Bussie",
    "sg:city":"Vaur\u00e9al",
    "sg:orig_category":"Unclassifiable Establishments",
    "sg:phone":"+33 1 34 32 79 00",
    "sg:postcode":"95490",
    "sg:province":"Ile de France",
    "wof:name":"Infovive S.a.r.l.",
    "wof:placetype":"venue"
},
  "geometry": {"coordinates":[2.030312,49.023499],"type":"Point"}
}