{
  "type": "Feature",
  "properties": {
    "addr:full":"7 Rue De Morsan 27300 Bernay Haute Normandie",
    "addr:housenumber":"7",
    "addr:postcode":"27300",
    "addr:street":"Rue De Morsan;Haute Normandie",
    "iso:country":"FR",
    "sg:address":"7 Rue De Morsan 27300 Bernay",
    "sg:classifiers":[
        {
            "category":"Professional",
            "subcategory":"Printing & Photocopies",
            "type":"Services"
        }
    ],
    "sg:phone":"+33 2 32 44 60 60",
    "sg:province":"Haute Normandie",
    "sg:tags":[
        "publishing"
    ],
    "wof:name":"Id Editions",
    "wof:placetype":"venue"
},
  "geometry": {"coordinates":[0.594772,49.088417],"type":"Point"}
}