{
  "type": "Feature",
  "properties": {
    "iso:country":"FR",
    "sg:address":"5 rue de la Gare 35560 Antrain",
    "sg:city":"Antrain",
    "sg:classifiers":[
        {
            "category":"Food & Beverages",
            "subcategory":"Fruits & Vegetables",
            "type":"Retail Goods"
        }
    ],
    "sg:phone":"+33 2 99 98 43 40",
    "sg:postcode":"35560",
    "sg:province":"Bretagne",
    "sg:tags":[
        "juice",
        "nectar"
    ],
    "wof:name":"Diana Vegetal S.a.",
    "wof:placetype":"venue"
},
  "geometry": {"coordinates":[-1.570554,48.368214],"type":"Point"}
}