{
  "type": "Feature",
  "properties": {
    "iso:country":"FR",
    "sg:address":"B.P. 101, 95505 Gonesse C\u00e9dex^^3, Rue d'Arsonval - ZI Nord, 95500 Gonesse",
    "sg:orig_category":"Non-Classified Establishments",
    "sg:phone":"+33 1 30 11 66 66",
    "sg:province":"Ile de France",
    "wof:name":"Groupe Heppner S.a.",
    "wof:placetype":"venue"
},
  "geometry": {"coordinates":[2.459794,48.985466],"type":"Point"}
}