{
  "type": "Feature",
  "properties": {
    "addr:full":"20, Rue Henri R\u00e9gnault - Parc d'Activit\u00e9 Chartreuse, 81100 Castres Midi Pyr\u00e9n\u00e9es",
    "addr:housenumber":"20",
    "addr:postcode":"81100",
    "addr:street":"Rue Henri Re\u0301Gnault Parc D'Activite \u0301 Chartreuse",
    "iso:country":"FR",
    "sg:address":"20, Rue Henri R\u00e9gnault - Parc d'Activit\u00e9 Chartreuse, 81100 Castres",
    "sg:orig_category":"Unclassifiable Establishments",
    "sg:phone":"+33 5 63 71 65 55",
    "sg:province":"Midi Pyr\u00e9n\u00e9es",
    "wof:name":"Coprover S.a.",
    "wof:placetype":"venue"
},
  "geometry": {"coordinates":[2.27929,43.61729],"type":"Point"}
}