{
  "type": "Feature",
  "properties": {
    "iso:country":"FR",
    "sg:address":"29490 Gu\u00efpavas",
    "sg:city":"Guipavas",
    "sg:orig_category":"Unclassifiable Establishments",
    "sg:phone":"+33 2 98 32 01 00",
    "sg:postcode":"29490",
    "sg:province":"Bretagne",
    "wof:name":"A\u00e9roport De Brest Bretagne",
    "wof:placetype":"venue"
},
  "geometry": {"coordinates":[-4.400551,48.435982],"type":"Point"}
}