{
  "type": "Feature",
  "properties": {
    "iso:country":"FR",
    "sg:address":"All\u00e9e Des Combes 01150 Blyes",
    "sg:classifiers":[
        {
            "category":"Manufacturing",
            "subcategory":"Chemicals & Compounds",
            "type":"Manufacturing & Wholesale Goods"
        }
    ],
    "sg:phone":"+33 4 74 46 23 60",
    "sg:postcode":"01150",
    "sg:province":"Rhone-Alpes",
    "sg:tags":[
        "pharmaceutical",
        "chemistry",
        "-",
        "by-product"
    ],
    "wof:name":"Maire Et Compagnie Sa",
    "wof:placetype":"venue"
},
  "geometry": {"coordinates":[5.259433,45.842175],"type":"Point"}
}