{
  "type": "Feature",
  "properties": {
    "addr:full":"8 Rue De Kerv\u00e9zennec 29601 Brest Cedex Bretagne",
    "addr:housenumber":"8",
    "addr:postcode":"29601;cedex",
    "addr:street":"Rue De Kerve\u0301Zennec",
    "iso:country":"FR",
    "sg:address":"8 Rue De Kerv\u00e9zennec 29601 Brest Cedex",
    "sg:classifiers":[
        {
            "category":"Utilities",
            "subcategory":"Telephone",
            "type":"Services"
        }
    ],
    "sg:phone":"+33 2 98 14 33 22",
    "sg:province":"Bretagne",
    "sg:tags":[
        "telecommunication"
    ],
    "wof:name":"Alcatel Business Systems",
    "wof:placetype":"venue"
},
  "geometry": {"coordinates":[-4.461381,48.41861],"type":"Point"}
}