{
  "type": "Feature",
  "properties": {
    "addr:full":"4, Rue des Armoiries, 94500 Champigny sur Marne Ile de France",
    "addr:housenumber":"4",
    "addr:postcode":"94500",
    "addr:street":"Rue Des Armoiries",
    "iso:country":"FR",
    "sg:address":"4, Rue des Armoiries, 94500 Champigny sur Marne",
    "sg:orig_category":"Unclassifiable Establishments",
    "sg:phone":"+33 1 48 82 13 00",
    "sg:province":"Ile de France",
    "wof:name":"S.2.e.i. S.a.r.l. - Soci\u00e9t\u00e9 Europ\u00e9enne D'equipements Industriels",
    "wof:placetype":"venue"
},
  "geometry": {"coordinates":[2.524333,48.821682],"type":"Point"}
}