{
  "type": "Feature",
  "properties": {
    "iso:country":"FR",
    "sg:address":"9, Rue Westrich, 67600 S\u00e9lestat",
    "sg:city":"S\u00e9lestat",
    "sg:orig_category":"Unclassifiable Establishments",
    "sg:phone":"+33 3 88 82 12 09",
    "sg:postcode":"67600",
    "sg:province":"Alsace",
    "wof:name":"Bermo Bijoux S.a.",
    "wof:placetype":"venue"
},
  "geometry": {"coordinates":[7.463701,48.280228],"type":"Point"}
}