{
  "type": "Feature",
  "properties": {
    "iso:country":"FR",
    "sg:address":"5 Rue Dominique D'Hausen P.I. Sud 57200 Sarreguemines",
    "sg:classifiers":[
        {
            "category":"Manufacturing",
            "subcategory":"Tools & Machinery",
            "type":"Manufacturing & Wholesale Goods"
        }
    ],
    "sg:phone":"+33 3 87 27 67 67",
    "sg:postcode":"57200",
    "sg:province":"Lorraine",
    "sg:tags":[
        "metallurgy",
        "metalworking"
    ],
    "wof:name":"Etablissements Guermont Weber",
    "wof:placetype":"venue"
},
  "geometry": {"coordinates":[7.105528,49.105751],"type":"Point"}
}