{
  "type": "Feature",
  "properties": {
    "addr:full":"11 Rue Forge 68160 Ste Marie Aux Mines Sainte-Croix-aux-Mines Alsace 68160",
    "addr:housenumber":"11",
    "addr:postcode":"68160;68160",
    "addr:street":"Rue Forge;Aux Mines",
    "iso:country":"FR",
    "sg:address":"11 Rue Forge 68160 Ste Marie Aux Mines",
    "sg:city":"Sainte-Croix-aux-Mines",
    "sg:classifiers":[
        {
            "category":"Manufacturing",
            "subcategory":"Metals",
            "type":"Manufacturing & Wholesale Goods"
        }
    ],
    "sg:phone":"+33 3 89 58 65 81",
    "sg:postcode":"68160",
    "sg:province":"Alsace",
    "sg:tags":[
        "metallurgy",
        "equipment",
        "metalworking",
        "processing",
        "precision"
    ],
    "wof:name":"Laserjet Sa",
    "wof:placetype":"venue"
},
  "geometry": {"coordinates":[7.202041,48.254662],"type":"Point"}
}