{
  "type": "Feature",
  "properties": {
    "iso:country":"FR",
    "sg:address":"6, Rte de la Forme, 59140 Dunkerque",
    "sg:orig_category":"Non-Classified Establishments",
    "sg:phone":"+33 3 28 59 34 56",
    "sg:postcode":"59140",
    "sg:province":"Nord Pas-de-Calais",
    "wof:name":"E.g.e.f. S.a. - Entreprise G\u00e9n\u00e9rale D'electricit\u00e9 Des Flandres",
    "wof:placetype":"venue"
},
  "geometry": {"coordinates":[2.37693,51.036995],"type":"Point"}
}