{
  "type": "Feature",
  "properties": {
    "addr:full":"Za Les Vignettes 63400 Chamali\u00e8res Chamali\u00e8res Auvergne 63400",
    "addr:postcode":"63400;63400",
    "addr:street":"Za Les Vignettes",
    "iso:country":"FR",
    "sg:address":"Za Les Vignettes 63400 Chamali\u00e8res",
    "sg:city":"Chamali\u00e8res",
    "sg:classifiers":[
        {
            "category":"Professional",
            "subcategory":"Engineering",
            "type":"Services"
        }
    ],
    "sg:phone":"+33 4 73 19 68 00",
    "sg:postcode":"63400",
    "sg:province":"Auvergne",
    "sg:tags":[
        "machine",
        "-",
        "mechanical"
    ],
    "wof:name":"Api",
    "wof:placetype":"venue"
},
  "geometry": {"coordinates":[3.06912,45.77533],"type":"Point"}
}