{
  "type": "Feature",
  "properties": {
    "addr:full":"B.P. 439, 74108 Ville la Grand^^18, All\u00e9e de Montr\u00e9al - ZI, 74100 Ville la Grand Rhone-Alpes 74100",
    "addr:housenumber":"b.p. 439",
    "addr:postcode":"74108;74100;74100",
    "addr:street":"Alle\u0301E De Montre\u0301Al Zi;La Grand Rhone-Alpes",
    "iso:country":"FR",
    "sg:address":"B.P. 439, 74108 Ville la Grand^^18, All\u00e9e de Montr\u00e9al - ZI, 74100 Ville la Grand",
    "sg:orig_category":"Non-Classified Establishments",
    "sg:phone":"+33 4 50 87 72 50",
    "sg:postcode":"74100",
    "sg:province":"Rhone-Alpes",
    "wof:name":"Label S.a.",
    "wof:placetype":"venue"
},
  "geometry": {"coordinates":[6.23712,46.192455],"type":"Point"}
}