{
  "type": "Feature",
  "properties": {
    "addr:full":"79 bourg Nord 01440 Viriat Rhone-Alpes 01440",
    "addr:housenumber":"79",
    "addr:postcode":"01440;01440",
    "addr:street":"Bourg Nord",
    "iso:country":"FR",
    "sg:address":"79 bourg Nord 01440 Viriat",
    "sg:classifiers":[
        {
            "category":"Retail",
            "subcategory":"Auto Repair",
            "type":"Services"
        }
    ],
    "sg:phone":"+33 4 74 23 19 55",
    "sg:postcode":"01440",
    "sg:province":"Rhone-Alpes",
    "sg:tags":[
        "machine",
        "equipment",
        "construction"
    ],
    "wof:name":"Serma Industrie Sa",
    "wof:placetype":"venue"
},
  "geometry": {"coordinates":[5.219012,46.251541],"type":"Point"}
}