{
  "type": "Feature",
  "properties": {
    "addr:full":"29, Rue Lamartine, 69800 Saint Priest Rhone-Alpes 69800",
    "addr:housenumber":"29",
    "addr:postcode":"69800;69800",
    "addr:street":"Rue Lamartine;Priest Rhone-Alpes",
    "iso:country":"FR",
    "sg:address":"29, Rue Lamartine, 69800 Saint Priest",
    "sg:orig_category":"Unclassifiable Establishments",
    "sg:phone":"+33 4 72 47 33 00",
    "sg:postcode":"69800",
    "sg:province":"Rhone-Alpes",
    "wof:name":"Debeaux",
    "wof:placetype":"venue"
},
  "geometry": {"coordinates":[4.968734,45.711483],"type":"Point"}
}