{
  "type": "Feature",
  "properties": {
    "addr:full":"118, Rue de Turenne, 75003 Paris Ile de France",
    "addr:housenumber":"118",
    "addr:postcode":"75003",
    "addr:street":"Rue De Turenne",
    "iso:country":"FR",
    "sg:address":"118, Rue de Turenne, 75003 Paris",
    "sg:orig_category":"Non-Classified Establishments",
    "sg:phone":"+33 1 48 87 47 67",
    "sg:province":"Ile de France",
    "wof:name":"F.d.n. Andr\u00e9 S.a.",
    "wof:placetype":"venue"
},
  "geometry": {"coordinates":[2.364785,48.863304],"type":"Point"}
}