{
  "type": "Feature",
  "properties": {
    "addr:full":"B.P. 43, 59750 Feignies^^9, Rte de Valenciennes, 59750 Feignies Nord Pas-de-Calais",
    "addr:postcode":"59750;59750",
    "addr:street":"B.P. 43;Rte De Valenciennes",
    "iso:country":"FR",
    "sg:address":"B.P. 43, 59750 Feignies^^9, Rte de Valenciennes, 59750 Feignies",
    "sg:orig_category":"Non-Classified Establishments",
    "sg:phone":"+33 3 27 53 25 33",
    "sg:province":"Nord Pas-de-Calais",
    "wof:name":"Soci\u00e9t\u00e9 D'assistance Commerciale Et Technique S.a.",
    "wof:placetype":"venue"
},
  "geometry": {"coordinates":[3.915413,50.29781],"type":"Point"}
}