{
  "type": "Feature",
  "properties": {
    "iso:country":"FR",
    "sg:address":"lieu dit le Sauvage 01960 Servas",
    "sg:classifiers":[
        {
            "category":"Food & Beverages",
            "subcategory":"Cheese",
            "type":"Retail Goods"
        }
    ],
    "sg:phone":"+33 4 74 52 77 22",
    "sg:postcode":"01960",
    "sg:province":"Rhone-Alpes",
    "wof:name":"Fromageries Bresse Bleu Sa",
    "wof:placetype":"venue"
},
  "geometry": {"coordinates":[5.196865,46.156715],"type":"Point"}
}