{
  "type": "Feature",
  "properties": {
    "addr:full":"6, Rue du Charon, 67370 Dingsheim Dingsheim Alsace 67370",
    "addr:housenumber":"6",
    "addr:postcode":"67370;67370",
    "addr:street":"Rue Du Charon",
    "iso:country":"FR",
    "sg:address":"6, Rue du Charon, 67370 Dingsheim",
    "sg:city":"Dingsheim",
    "sg:orig_category":"Unclassifiable Establishments",
    "sg:phone":"+33 3 88 83 90 10",
    "sg:postcode":"67370",
    "sg:province":"Alsace",
    "wof:name":"Hanssen Et Compagnie S.a.",
    "wof:placetype":"venue"
},
  "geometry": {"coordinates":[7.670764,48.63089],"type":"Point"}
}