{
  "type": "Feature",
  "properties": {
    "iso:country":"FR",
    "sg:address":"B.P. 1206, 68054 Mulhouse C\u00e9dex^^9, Rue de Bantzenheim, 68100 Mulhouse",
    "sg:city":"Mulhouse",
    "sg:orig_category":"Non-Classified Establishments",
    "sg:phone":"+33 3 89 44 45 80",
    "sg:postcode":"68100",
    "sg:province":"Alsace",
    "wof:name":"Mund E. S.a.r.l.",
    "wof:placetype":"venue"
},
  "geometry": {"coordinates":[7.34365,47.751709],"type":"Point"}
}