{
  "type": "Feature",
  "properties": {
    "addr:full":"Rue Aristide Briand Pithiviers Centre 45300",
    "addr:postcode":"45300",
    "addr:street":"Rue Aristide Briand",
    "iso:country":"FR",
    "sg:address":"Rue Aristide Briand",
    "sg:city":"Pithiviers",
    "sg:orig_category":"Unclassifiable Establishments",
    "sg:phone":"+33 2 38 30 87 84",
    "sg:postcode":"45300",
    "sg:province":"Centre",
    "wof:name":"H20 Production S.a.",
    "wof:placetype":"venue"
},
  "geometry": {"coordinates":[2.251816,48.184475],"type":"Point"}
}