{
  "type": "Feature",
  "properties": {
    "iso:country":"FR",
    "sg:address":"Rue du Progr\u00e8s 44140 GENESTON",
    "sg:orig_category":"Waste Paper Presses",
    "sg:phone":"+33 2 40 26 13 16",
    "sg:province":"Pays de Loire",
    "wof:name":"Ecp Group Sa",
    "wof:placetype":"venue"
},
  "geometry": {"coordinates":[-1.516594,47.068939],"type":"Point"}
}