{
  "type": "Feature",
  "properties": {
    "addr:full":"B.P. 86, 39200 Saint Claude^^10, Rue Edouard Branly, 39200 Saint Claude Franche Comt\u00e9 39200",
    "addr:postcode":"39200;39200;39200",
    "addr:street":"B.P. 86;Rue Edouard Branly;Franche Comte\u0301",
    "iso:country":"FR",
    "sg:address":"B.P. 86, 39200 Saint Claude^^10, Rue Edouard Branly, 39200 Saint Claude",
    "sg:orig_category":"Engineering plasturgie Etampes et matrices Moules Moules d'injection Moules d'injection d'aluminium ",
    "sg:phone":"+33 3 84 45 13 04",
    "sg:postcode":"39200",
    "sg:province":"Franche Comt\u00e9",
    "wof:name":"Regad Paul S.a.",
    "wof:placetype":"venue"
},
  "geometry": {"coordinates":[5.84194,46.34193],"type":"Point"}
}