{
  "type": "Feature",
  "properties": {
    "iso:country":"FR",
    "sg:address":"Dabisse",
    "sg:city":"Les M\u00e9es",
    "sg:orig_category":"Unclassifiable Establishments",
    "sg:phone":"+33 4 92 34 00 10",
    "sg:postcode":"04190",
    "sg:province":"Pays de Loire",
    "wof:name":"La Bastide Blanche G.a.e.c.",
    "wof:placetype":"venue"
},
  "geometry": {"coordinates":[5.92825,43.984001],"type":"Point"}
}