{
  "type": "Feature",
  "properties": {
    "addr:full":"55 R Du G\u00e9n\u00e9ral De Gaulle 76770 Le Houlme Haute Normandie 76770",
    "addr:housenumber":"55",
    "addr:postcode":"76770;76770",
    "addr:street":"R Du Ge\u0301Ne\u0301Ral De Gaulle;Haute Normandie",
    "iso:country":"FR",
    "sg:address":"55 R Du G\u00e9n\u00e9ral De Gaulle 76770 Le Houlme",
    "sg:classifiers":[
        {
            "category":"Manufacturing",
            "subcategory":"Glass & Minerals",
            "type":"Manufacturing & Wholesale Goods"
        }
    ],
    "sg:phone":"+33 2 32 82 80 40",
    "sg:postcode":"76770",
    "sg:province":"Haute Normandie",
    "sg:tags":[
        "building",
        "material"
    ],
    "wof:name":"Normanver Sa",
    "wof:placetype":"venue"
},
  "geometry": {"coordinates":[1.040011,49.505997],"type":"Point"}
}