{
  "type": "Feature",
  "properties": {
    "addr:full":"Kerlevinez 56500 Locmine Locmin\u00e9 Bretagne 56500",
    "addr:postcode":"56500;56500",
    "addr:street":"Kerlevinez;Locmine\u0301",
    "iso:country":"FR",
    "sg:address":"Kerlevinez 56500 Locmine",
    "sg:city":"Locmin\u00e9",
    "sg:classifiers":[
        {
            "category":"Farming",
            "subcategory":"Farm & Veterinary Services",
            "type":"Manufacturing & Wholesale Goods"
        }
    ],
    "sg:phone":"+33 2 97 60 02 45",
    "sg:postcode":"56500",
    "sg:province":"Bretagne",
    "sg:tags":[
        "food",
        "product",
        "breeding",
        "animal",
        "related"
    ],
    "wof:name":"Kervalis",
    "wof:placetype":"venue"
},
  "geometry": {"coordinates":[-2.847489,47.87101],"type":"Point"}
}