{
  "type": "Feature",
  "properties": {
    "addr:full":"13 avenue Charles de Gaulle 94470 Boissy St Leger Ile de France",
    "addr:housenumber":"13",
    "addr:postcode":"94470",
    "addr:street":"Avenue Charles De Gaulle;Boissy St",
    "iso:country":"FR",
    "sg:address":"13 avenue Charles de Gaulle 94470 Boissy St Leger",
    "sg:orig_category":"Recording Systems For Telephone Charges",
    "sg:phone":"+33 1 45 10 31 00",
    "sg:province":"Ile de France",
    "wof:name":"Cogis Industries Sa",
    "wof:placetype":"venue"
},
  "geometry": {"coordinates":[2.500694,48.751579],"type":"Point"}
}