{
  "type": "Feature",
  "properties": {
    "addr:full":"Zone Industrielle 01140 St Didier Sur Chalaronne Rhone-Alpes 01140",
    "addr:postcode":"01140;01140",
    "addr:street":"Zone Industrielle;Chalaronne Rhone-Alpes",
    "iso:country":"FR",
    "sg:address":"Zone Industrielle 01140 St Didier Sur Chalaronne",
    "sg:classifiers":[
        {
            "category":"Manufacturing",
            "subcategory":"Metals",
            "type":"Manufacturing & Wholesale Goods"
        }
    ],
    "sg:phone":"+33 4 74 06 67 20",
    "sg:postcode":"01140",
    "sg:province":"Rhone-Alpes",
    "sg:tags":[
        "metallurgy",
        "steel",
        "metalworking"
    ],
    "wof:name":"Architecture Metal Sa",
    "wof:placetype":"venue"
},
  "geometry": {"coordinates":[4.818525,46.178207],"type":"Point"}
}