{
  "type": "Feature",
  "properties": {
    "addr:full":"1 rue d'Alsace 68210 CHAVANNES SUR L ETANG Ballersdorf Alsace 68210",
    "addr:housenumber":"1",
    "addr:postcode":"68210;68210",
    "addr:street":"Rue D'Alsace",
    "iso:country":"FR",
    "sg:address":"1 rue d'Alsace 68210 CHAVANNES SUR L ETANG",
    "sg:city":"Ballersdorf",
    "sg:classifiers":[
        {
            "category":"Food & Beverages",
            "subcategory":"Ethnic Foods",
            "type":"Retail Goods"
        }
    ],
    "sg:phone":"+33 3 89 25 21 96",
    "sg:postcode":"68210",
    "sg:province":"Alsace",
    "sg:tags":[
        "sauerkraut"
    ],
    "wof:name":"Choucrouterie Claude Sarl",
    "wof:placetype":"venue"
},
  "geometry": {"coordinates":[7.10888,47.648411],"type":"Point"}
}