{
  "type": "Feature",
  "properties": {
    "addr:full":"2 Rue Andr\u00e9 Citro\u00ebn 95130 Franconville Ile de France 95130",
    "addr:housenumber":"2",
    "addr:postcode":"95130;ile;95130",
    "addr:street":"Rue Andre\u0301 Citroe\u0308N;France",
    "iso:country":"FR",
    "sg:address":"2 Rue Andr\u00e9 Citro\u00ebn 95130 Franconville",
    "sg:classifiers":[
        {
            "category":"Manufacturing",
            "subcategory":"Metals",
            "type":"Manufacturing & Wholesale Goods"
        }
    ],
    "sg:phone":"+33 1 30 72 84 30",
    "sg:postcode":"95130",
    "sg:province":"Ile de France",
    "sg:tags":[
        "metallurgy",
        "metalworking",
        "processing"
    ],
    "wof:name":"Compagnie Des Technologies De Luxe France",
    "wof:placetype":"venue"
},
  "geometry": {"coordinates":[2.209903,48.990181],"type":"Point"}
}