{
  "type": "Feature",
  "properties": {
    "iso:country":"FR",
    "sg:address":"B.P. 365, 70014 Vesoul C\u00e9dex^^Place du 11e Chasseur, 70000 Vesoul",
    "sg:orig_category":"Non-Classified Establishments",
    "sg:phone":"+33 3 84 76 07 46",
    "sg:province":"Franche Comt\u00e9",
    "wof:name":"Greta De Vesoul/gray",
    "wof:placetype":"venue"
},
  "geometry": {"coordinates":[6.034054,47.524078],"type":"Point"}
}