{
  "type": "Feature",
  "properties": {
    "addr:full":"B.P. 345, 38204 Vienne C\u00e9dex^^47, Av. du G\u00e9n\u00e9ral Leclerc, 38200 Vienne Rhone-Alpes 38200",
    "addr:housenumber":"b.p. 345",
    "addr:postcode":"38204;38200;38200",
    "addr:street":"Av. Du Ge\u0301Ne\u0301Ral Leclerc",
    "iso:country":"FR",
    "sg:address":"B.P. 345, 38204 Vienne C\u00e9dex^^47, Av. du G\u00e9n\u00e9ral Leclerc, 38200 Vienne",
    "sg:orig_category":"Non-Classified Establishments",
    "sg:phone":"+33 4 74 78 32 32",
    "sg:postcode":"38200",
    "sg:province":"Rhone-Alpes",
    "wof:name":"Cabinet Bonnet S.a.",
    "wof:placetype":"venue"
},
  "geometry": {"coordinates":[4.942395,45.467644],"type":"Point"}
}