{
  "type": "Feature",
  "properties": {
    "addr:full":"9 Rue Chaponval Zac Du Cornouiller 78870 Bailly Ile de France 78870",
    "addr:housenumber":"9",
    "addr:postcode":"78870;ile;78870",
    "addr:street":"Rue Chaponval Zac Du Cornouiller;France",
    "iso:country":"FR",
    "sg:address":"9 Rue Chaponval Zac Du Cornouiller 78870 Bailly",
    "sg:classifiers":[
        {
            "category":"Banks & Credit Unions",
            "subcategory":"Financial Services",
            "type":"Services"
        }
    ],
    "sg:phone":"+33 1 30 80 84 00",
    "sg:postcode":"78870",
    "sg:province":"Ile de France",
    "sg:tags":[
        "banking",
        "insurance",
        "institution",
        "finance"
    ],
    "wof:name":"Daimler Chrysler Financial",
    "wof:placetype":"venue"
},
  "geometry": {"coordinates":[2.079645,48.839886],"type":"Point"}
}