{
  "type": "Feature",
  "properties": {
    "iso:country":"FR",
    "sg:address":"Chatel G\u00e9rard 89310 Noyers",
    "sg:city":"Noyers",
    "sg:orig_category":"Unclassifiable Establishments",
    "sg:phone":"+33 3 86 55 38 55",
    "sg:postcode":"89310",
    "sg:province":"Bourgogne",
    "wof:name":"S.a.c.g. S.a.",
    "wof:placetype":"venue"
},
  "geometry": {"coordinates":[3.996665,47.692291],"type":"Point"}
}