{
  "type": "Feature",
  "properties": {
    "addr:full":"45 Rue Antilles 94150 Rungis Ile de France 94150",
    "addr:housenumber":"45",
    "addr:postcode":"94150;94150",
    "addr:street":"Rue Antilles",
    "iso:country":"FR",
    "sg:address":"45 Rue Antilles 94150 Rungis",
    "sg:classifiers":[
        {
            "category":"Food & Beverages",
            "subcategory":"Fruits & Vegetables",
            "type":"Retail Goods"
        }
    ],
    "sg:phone":"+33 1 46 86 45 08",
    "sg:postcode":"94150",
    "sg:province":"Ile de France",
    "sg:tags":[
        "frozen",
        "product",
        "related"
    ],
    "wof:name":"Canovas Et Compagnie Sarl",
    "wof:placetype":"venue"
},
  "geometry": {"coordinates":[2.355623,48.752335],"type":"Point"}
}