{
  "type": "Feature",
  "properties": {
    "iso:country":"FR",
    "sg:address":"73250 St Pierre D Albigny",
    "sg:classifiers":[
        {
            "category":"Shopping",
            "subcategory":"Clothing, Apparel, & Fashions",
            "type":"Retail Goods"
        }
    ],
    "sg:phone":"+33 4 79 28 51 96",
    "sg:postcode":"73250",
    "sg:province":"Rhone-Alpes",
    "sg:tags":[
        "textile",
        "clothing",
        "clothes"
    ],
    "wof:name":"Saint Pierre Confection",
    "wof:placetype":"venue"
},
  "geometry": {"coordinates":[6.15751,45.569004],"type":"Point"}
}