{
  "type": "Feature",
  "properties": {
    "addr:full":"113, Rue des Deux Ruisseaux, 69400 Gleiz\u00e9 Rhone-Alpes 69400",
    "addr:housenumber":"113",
    "addr:postcode":"69400;69400",
    "addr:street":"Rue Des Deux Ruisseaux",
    "iso:country":"FR",
    "sg:address":"113, Rue des Deux Ruisseaux, 69400 Gleiz\u00e9",
    "sg:orig_category":"Unclassifiable Establishments",
    "sg:phone":"+33 4 74 68 75 69",
    "sg:postcode":"69400",
    "sg:province":"Rhone-Alpes",
    "wof:name":"S.d.p. S.a.r.l. - Soci\u00e9t\u00e9 De Distribution Et De Promotion",
    "wof:placetype":"venue"
},
  "geometry": {"coordinates":[4.693132,45.983452],"type":"Point"}
}