{
  "type": "Feature",
  "properties": {
    "iso:country":"FR",
    "sg:address":"Rue de Tritteling - Case de Faulquemont",
    "sg:city":"Faulquemont",
    "sg:orig_category":"Unclassifiable Establishments",
    "sg:phone":"+33 3 87 90 71 17",
    "sg:postcode":"57380",
    "sg:province":"Lorraine",
    "wof:name":"Conseil Et Assistance En Environnement E.u.r.l.",
    "wof:placetype":"venue"
},
  "geometry": {"coordinates":[6.5989,49.045826],"type":"Point"}
}