{
  "type": "Feature",
  "properties": {
    "addr:full":"Av Des Vignerons 31620 Fronton Midi Pyr\u00e9n\u00e9es 31620",
    "addr:postcode":"31620;31620",
    "addr:street":"Av Des Vignerons",
    "iso:country":"FR",
    "sg:address":"Av Des Vignerons 31620 Fronton",
    "sg:classifiers":[
        {
            "category":"Food Court",
            "type":"Food & Drink"
        }
    ],
    "sg:phone":"+33 5 62 79 97 79",
    "sg:postcode":"31620",
    "sg:province":"Midi Pyr\u00e9n\u00e9es",
    "sg:tags":[
        "product",
        "related"
    ],
    "wof:name":"Caves De Frontons Comte De Negret Coop",
    "wof:placetype":"venue"
},
  "geometry": {"coordinates":[1.38855,43.844765],"type":"Point"}
}