{
  "type": "Feature",
  "properties": {
    "addr:full":"3, Rue Carl Linn\u00e9, 49000 Angers Pays de Loire",
    "addr:housenumber":"3",
    "addr:postcode":"49000",
    "addr:street":"Rue Carl Linne\u0301",
    "iso:country":"FR",
    "sg:address":"3, Rue Carl Linn\u00e9, 49000 Angers",
    "sg:orig_category":"Non-Classified Establishments",
    "sg:phone":"+33 2 41 45 73 19",
    "sg:province":"Pays de Loire",
    "wof:name":"Legendre S.a.",
    "wof:placetype":"venue"
},
  "geometry": {"coordinates":[-0.54548,47.446198],"type":"Point"}
}