{
  "type": "Feature",
  "properties": {
    "addr:full":"rue Marthe Duteil 87220 Feytiat Limousin",
    "addr:postcode":"87220",
    "addr:street":"Rue Marthe Duteil",
    "iso:country":"FR",
    "sg:address":"rue Marthe Duteil 87220 Feytiat",
    "sg:classifiers":[
        {
            "category":"Wholesale",
            "subcategory":"Vending Machines",
            "type":"Manufacturing & Wholesale Goods"
        }
    ],
    "sg:phone":"+33 5 55 30 41 26",
    "sg:province":"Limousin",
    "sg:tags":[
        "thermoforming"
    ],
    "wof:name":"Fininplast S.a.",
    "wof:placetype":"venue"
},
  "geometry": {"coordinates":[1.302381,45.815933],"type":"Point"}
}