{
  "type": "Feature",
  "properties": {
    "iso:country":"FR",
    "sg:address":"Rte De Limoges 87400 St L\u00e9onard De Noblat",
    "sg:classifiers":[
        {
            "category":"Manufacturing",
            "subcategory":"Printing",
            "type":"Manufacturing & Wholesale Goods"
        }
    ],
    "sg:phone":"+33 5 55 56 04 90",
    "sg:province":"Limousin",
    "sg:tags":[
        "publishing"
    ],
    "wof:name":"Imprimerie Montibus Et Fils",
    "wof:placetype":"venue"
},
  "geometry": {"coordinates":[1.477735,45.834045],"type":"Point"}
}