{
  "type": "Feature",
  "properties": {
    "addr:full":"La Gravi\u00e8re 01400 Neuville les Dames Rhone-Alpes 01400",
    "addr:postcode":"01400;01400",
    "addr:street":"La Gravie\u0300Re",
    "iso:country":"FR",
    "sg:address":"La Gravi\u00e8re 01400 Neuville les Dames",
    "sg:orig_category":"Unclassifiable Establishments",
    "sg:phone":"+33 4 74 55 64 90",
    "sg:postcode":"01400",
    "sg:province":"Rhone-Alpes",
    "wof:name":"Entreprise L'artisan Du Sol E.u.r.l.",
    "wof:placetype":"venue"
},
  "geometry": {"coordinates":[4.99054,46.134781],"type":"Point"}
}