{
  "type": "Feature",
  "properties": {
    "addr:full":"B.P. 2042, 31018 Toulouse C\u00e9dex 2^^3, Rue Nicolas Poussin, 31200 Toulouse Midi Pyr\u00e9n\u00e9es",
    "addr:housenumber":"2;^ 3",
    "addr:postcode":"31018;31200",
    "addr:street":"B.P. 2042;^;Rue Nicolas Poussin",
    "iso:country":"FR",
    "sg:address":"B.P. 2042, 31018 Toulouse C\u00e9dex 2^^3, Rue Nicolas Poussin, 31200 Toulouse",
    "sg:orig_category":"Non-Classified Establishments",
    "sg:phone":"+33 5 61 47 52 50",
    "sg:province":"Midi Pyr\u00e9n\u00e9es",
    "wof:name":"Tricotage Garonnais",
    "wof:placetype":"venue"
},
  "geometry": {"coordinates":[1.44954,43.639011],"type":"Point"}
}