{
  "type": "Feature",
  "properties": {
    "iso:country":"FR",
    "sg:address":"28 Bis Rue Fr\u00e9d\u00e9ric Mistral 84101 Orange",
    "sg:classifiers":[
        {
            "category":"Food Court",
            "type":"Food & Drink"
        }
    ],
    "sg:phone":"+33 4 90 34 06 07",
    "sg:province":"Centre",
    "sg:tags":[
        "product",
        "related"
    ],
    "wof:name":"Michel Raphael Sa",
    "wof:placetype":"venue"
},
  "geometry": {"coordinates":[4.813864,44.13773],"type":"Point"}
}