{
  "type": "Feature",
  "properties": {
    "addr:full":"Zi Garenne 71880 Ch\u00e2tenoy Le Royal Ch\u00e2tenoy-le-Royal Bourgogne 71880",
    "addr:postcode":"71880;71880",
    "addr:street":"Zi Garenne",
    "iso:country":"FR",
    "sg:address":"Zi Garenne 71880 Ch\u00e2tenoy Le Royal",
    "sg:city":"Ch\u00e2tenoy-le-Royal",
    "sg:classifiers":[
        {
            "category":"Utilities",
            "subcategory":"Electric",
            "type":"Services"
        }
    ],
    "sg:phone":"+33 3 85 98 22 00",
    "sg:postcode":"71880",
    "sg:province":"Bourgogne",
    "sg:tags":[
        "electricity",
        "electronic",
        "electrical",
        "equipment"
    ],
    "wof:name":"Alstom",
    "wof:placetype":"venue"
},
  "geometry": {"coordinates":[4.814135,46.795506],"type":"Point"}
}