{
  "type": "Feature",
  "properties": {
    "addr:full":"200, Rue Lecourbe, 75015 Paris Ile de France 75015",
    "addr:housenumber":"200",
    "addr:postcode":"75015;75015",
    "addr:street":"Rue Lecourbe",
    "iso:country":"FR",
    "sg:address":"200, Rue Lecourbe, 75015 Paris",
    "sg:orig_category":"Non-Classified Establishments",
    "sg:phone":"+33 1 48 28 62 43",
    "sg:postcode":"75015",
    "sg:province":"Ile de France",
    "wof:name":"B.i.c.s.",
    "wof:placetype":"venue"
},
  "geometry": {"coordinates":[2.295528,48.840488],"type":"Point"}
}