{
  "type": "Feature",
  "properties": {
    "addr:full":"B.P. 51, 60330 Le Plessis Belleville^^Rte de Mareuil, 60330 Lagny le Sec Picardie 60330",
    "addr:postcode":"60330;60330;60330",
    "addr:street":"B.P. 51;Mareuil",
    "iso:country":"FR",
    "sg:address":"B.P. 51, 60330 Le Plessis Belleville^^Rte de Mareuil, 60330 Lagny le Sec",
    "sg:orig_category":"Non-Classified Establishments",
    "sg:phone":"+33 3 44 60 89 27",
    "sg:postcode":"60330",
    "sg:province":"Picardie",
    "wof:name":"Bertin Michel S.a.",
    "wof:placetype":"venue"
},
  "geometry": {"coordinates":[2.756738,49.096386],"type":"Point"}
}