{
  "type": "Feature",
  "properties": {
    "addr:full":"15 avenue de S\u00e9gur 75007 Paris Ile de France",
    "addr:housenumber":"15",
    "addr:postcode":"75007",
    "addr:street":"Avenue De Se\u0301Gur",
    "iso:country":"FR",
    "sg:address":"15 avenue de S\u00e9gur 75007 Paris",
    "sg:orig_category":"Training In Occupational Safety",
    "sg:phone":"+33 1 45 55 89 00",
    "sg:province":"Ile de France",
    "wof:name":"Images Pour La Formation Sa",
    "wof:placetype":"venue"
},
  "geometry": {"coordinates":[2.310911,48.852177],"type":"Point"}
}