{
  "type": "Feature",
  "properties": {
    "addr:full":"3, Rue de Vienne, 75008 Paris Ile de France",
    "addr:housenumber":"3",
    "addr:postcode":"75008",
    "addr:street":"Rue De Vienne",
    "iso:country":"FR",
    "sg:address":"3, Rue de Vienne, 75008 Paris",
    "sg:orig_category":"Unclassifiable Establishments",
    "sg:phone":"+33 1 42 94 21 34",
    "sg:province":"Ile de France",
    "wof:name":"Alph\u00e9e S.a.",
    "wof:placetype":"venue"
},
  "geometry": {"coordinates":[2.32117,48.876564],"type":"Point"}
}