{
  "type": "Feature",
  "properties": {
    "addr:full":"B.P. 68 Saint Junien C\u00e9dex^^87200 Saint Junien Limousin 87203",
    "addr:housenumber":"68",
    "addr:postcode":"87203",
    "addr:street":"B.P.",
    "iso:country":"FR",
    "sg:address":"B.P. 68",
    "sg:city":"Saint Junien C\u00e9dex^^87200 Saint Junien",
    "sg:orig_category":"Non-Classified Establishments",
    "sg:phone":"+33 5 55 43 08 10",
    "sg:postcode":"87203",
    "sg:province":"Limousin",
    "wof:name":"Mingaud S.a.",
    "wof:placetype":"venue"
},
  "geometry": {"coordinates":[0.871925,45.87748],"type":"Point"}
}