{
  "type": "Feature",
  "properties": {
    "iso:country":"FR",
    "sg:address":"4, Chemin d'El Pey, 31770 Colomiers",
    "sg:orig_category":"Unclassifiable Establishments",
    "sg:phone":"+33 5 61 16 44 20",
    "sg:province":"Midi Pyr\u00e9n\u00e9es",
    "wof:name":"Saint Louis Sucre S.n.c.",
    "wof:placetype":"venue"
},
  "geometry": {"coordinates":[1.314649,43.604172],"type":"Point"}
}