{
  "type": "Feature",
  "properties": {
    "iso:country":"FR",
    "sg:address":"11, Rue Jules Verne, 95320 Saint Leu la For\u00eat",
    "sg:orig_category":"Non-Classified Establishments",
    "sg:phone":"+33 1 30 40 55 65",
    "sg:province":"Ile de France",
    "wof:name":"Rh\u00e9oval S.a.r.l.",
    "wof:placetype":"venue"
},
  "geometry": {"coordinates":[2.250951,49.006477],"type":"Point"}
}