{
  "type": "Feature",
  "properties": {
    "iso:country":"FR",
    "sg:address":"27, Fbg de Belfort, 10200 Bar sur Aube",
    "sg:orig_category":"Non-Classified Establishments",
    "sg:phone":"+33 3 25 27 04 32",
    "sg:province":"Champagne",
    "wof:name":"Mossbach Fils Et Compagnie S.a.",
    "wof:placetype":"venue"
},
  "geometry": {"coordinates":[4.72037,48.228008],"type":"Point"}
}