{
  "type": "Feature",
  "properties": {
    "addr:full":"Rte de la Chapelle Fortin La Fert\u00e9 Vidame Centre 28340",
    "addr:postcode":"28340",
    "addr:street":"Rte De La Chapelle Fortin;Vidame",
    "iso:country":"FR",
    "sg:address":"Rte de la Chapelle Fortin",
    "sg:city":"La Fert\u00e9 Vidame",
    "sg:orig_category":"Non-Classified Establishments",
    "sg:phone":"+33 2 37 38 59 00",
    "sg:postcode":"28340",
    "sg:province":"Centre",
    "wof:name":"La Boissellerie Fertoise S.a.",
    "wof:placetype":"venue"
},
  "geometry": {"coordinates":[0.93788,48.595718],"type":"Point"}
}