{
  "type": "Feature",
  "properties": {
    "addr:full":"Rue de Saint Louis Creutzwald Lorraine 57150",
    "addr:postcode":"57150",
    "addr:street":"Rue De;Lorraine",
    "iso:country":"FR",
    "sg:address":"Rue de Saint Louis",
    "sg:city":"Creutzwald",
    "sg:orig_category":"Unclassifiable Establishments",
    "sg:phone":"+33 3 87 29 88 77",
    "sg:postcode":"57150",
    "sg:province":"Lorraine",
    "wof:name":"France Illuminations S.a.r.l.",
    "wof:placetype":"venue"
},
  "geometry": {"coordinates":[6.703052,49.188515],"type":"Point"}
}