{
  "type": "Feature",
  "properties": {
    "iso:country":"FR",
    "sg:address":"Rue Pierre et Marie Curie - ZI Vaux le P\u00e9nil",
    "sg:city":"Melun",
    "sg:orig_category":"Unclassifiable Establishments",
    "sg:phone":"+33 1 64 37 37 10",
    "sg:postcode":"77000",
    "sg:province":"Ile de France",
    "wof:name":"Bois Tranches Claudet S.a.",
    "wof:placetype":"venue"
},
  "geometry": {"coordinates":[2.664085,48.539577],"type":"Point"}
}