{
  "type": "Feature",
  "properties": {
    "addr:full":"ZA Blacherande Etoile sur Rh\u00f4ne Rhone-Alpes 26800",
    "addr:postcode":"26800",
    "addr:street":"Za Blacherande Etoile",
    "iso:country":"FR",
    "sg:address":"ZA Blacherande",
    "sg:city":"Etoile sur Rh\u00f4ne",
    "sg:orig_category":"Non-Classified Establishments",
    "sg:phone":"+33 4 75 60 71 11",
    "sg:postcode":"26800",
    "sg:province":"Rhone-Alpes",
    "wof:name":"Salsis Emballage S.a.",
    "wof:placetype":"venue"
},
  "geometry": {"coordinates":[4.8962,44.83691],"type":"Point"}
}