{
  "type": "Feature",
  "properties": {
    "iso:country":"FR",
    "sg:address":"20, Quai du Commandant Malbert, 29200 Brest",
    "sg:city":"Brest",
    "sg:orig_category":"Non-Classified Establishments",
    "sg:phone":"+33 2 98 80 11 51",
    "sg:postcode":"29200",
    "sg:province":"Bretagne",
    "wof:name":"Hertz France",
    "wof:placetype":"venue"
},
  "geometry": {"coordinates":[-4.486737,48.379723],"type":"Point"}
}