{
  "type": "Feature",
  "properties": {
    "addr:full":"les Bordes 72400 Cherr\u00e9 Pays de Loire",
    "addr:postcode":"72400",
    "iso:country":"FR",
    "sg:address":"les Bordes 72400 Cherr\u00e9",
    "sg:orig_category":"Unclassifiable Establishments",
    "sg:phone":"+33 2 43 60 22 22",
    "sg:province":"Pays de Loire",
    "wof:name":"Socopa Cuirs G.i.e.",
    "wof:placetype":"venue"
},
  "geometry": {"coordinates":[0.65908,48.171379],"type":"Point"}
}