{
  "type": "Feature",
  "properties": {
    "iso:country":"FR",
    "sg:address":"B.P. 69, 67542 Ostwald^^3, Rue Albert Gerig, 67540 Ostwald",
    "sg:city":"Ostwald",
    "sg:orig_category":"Non-Classified Establishments",
    "sg:phone":"+33 3 88 10 52 42",
    "sg:postcode":"67540",
    "sg:province":"Alsace",
    "wof:name":"Sofima S.a.",
    "wof:placetype":"venue"
},
  "geometry": {"coordinates":[7.71046,48.543736],"type":"Point"}
}