{
  "type": "Feature",
  "properties": {
    "addr:full":"17 Rue De Seine 92700 Colombes Ile de France 92700",
    "addr:housenumber":"17",
    "addr:postcode":"92700;ile;92700",
    "addr:street":"Rue De Seine;France",
    "iso:country":"FR",
    "sg:address":"17 Rue De Seine 92700 Colombes",
    "sg:classifiers":[
        {
            "category":"Professional",
            "subcategory":"Engineering",
            "type":"Services"
        }
    ],
    "sg:phone":"+33 1 41 19 25 20",
    "sg:postcode":"92700",
    "sg:province":"Ile de France",
    "sg:tags":[
        "machine",
        "-",
        "mechanical"
    ],
    "wof:name":"Societe Industrielle De Brochage Sa",
    "wof:placetype":"venue"
},
  "geometry": {"coordinates":[2.228091,48.921513],"type":"Point"}
}