{
  "type": "Feature",
  "properties": {
    "addr:full":"B.P. 1 Steenwerck Nord Pas-de-Calais 59181",
    "addr:postcode":"59181",
    "addr:street":"B.P. 1 Steenwerck Nord",
    "iso:country":"FR",
    "sg:address":"B.P. 1",
    "sg:city":"Steenwerck",
    "sg:orig_category":"Non-Classified Establishments",
    "sg:phone":"+33 3 28 49 97 08",
    "sg:postcode":"59181",
    "sg:province":"Nord Pas-de-Calais",
    "wof:name":"Maison Lecouffe S.a.r.l.",
    "wof:placetype":"venue"
},
  "geometry": {"coordinates":[2.777725,50.70031],"type":"Point"}
}