{
  "type": "Feature",
  "properties": {
    "addr:full":"Rue du Docteur Calmette - ZI Toulon Est Toulon Haute Normandie 83100",
    "addr:postcode":"83100",
    "addr:street":"Rue Du Docteur Calmette Zi",
    "iso:country":"FR",
    "sg:address":"Rue du Docteur Calmette - ZI Toulon Est",
    "sg:city":"Toulon",
    "sg:orig_category":"Unclassifiable Establishments",
    "sg:phone":"+33 4 94 08 78 60",
    "sg:postcode":"83100",
    "sg:province":"Haute Normandie",
    "wof:name":"T.f.e - Transports Frigorifiques Europ\u00e9ens",
    "wof:placetype":"venue"
},
  "geometry": {"coordinates":[5.96595,43.126099],"type":"Point"}
}