{
  "type": "Feature",
  "properties": {
    "addr:full":"ZA les Surcens Attichy Picardie 60350",
    "addr:postcode":"60350",
    "addr:street":"Za Les;Attichy Picardie",
    "iso:country":"FR",
    "sg:address":"ZA les Surcens",
    "sg:city":"Attichy",
    "sg:orig_category":"Non-Classified Establishments",
    "sg:phone":"+33 3 44 42 12 66",
    "sg:postcode":"60350",
    "sg:province":"Picardie",
    "wof:name":"Meca Ei S.a.r.l.",
    "wof:placetype":"venue"
},
  "geometry": {"coordinates":[3.04568,49.413269],"type":"Point"}
}