{
  "type": "Feature",
  "properties": {
    "addr:full":"Zac Vialette 81150 Marssac Sur Tarn Midi Pyr\u00e9n\u00e9es",
    "addr:postcode":"81150",
    "addr:street":"Zac Vialette",
    "iso:country":"FR",
    "sg:address":"Zac Vialette 81150 Marssac Sur Tarn",
    "sg:classifiers":[
        {
            "category":"Manufacturing",
            "subcategory":"Rubber & Plastics",
            "type":"Manufacturing & Wholesale Goods"
        }
    ],
    "sg:phone":"+33 5 63 53 25 78",
    "sg:province":"Midi Pyr\u00e9n\u00e9es",
    "wof:name":"Treviform Sa",
    "wof:placetype":"venue"
},
  "geometry": {"coordinates":[2.02965,43.917301],"type":"Point"}
}