{
  "type": "Feature",
  "properties": {
    "addr:full":"Avenue De Bordeaux Cap De La Coste 40800 Aire Sur L Adour Duhort-Bachen Aquitaine 40800",
    "addr:postcode":"40800;40800",
    "addr:street":"Avenue De Bordeaux Cap De La Coste;Aire;L",
    "iso:country":"FR",
    "sg:address":"Avenue De Bordeaux Cap De La Coste 40800 Aire Sur L Adour",
    "sg:city":"Duhort-Bachen",
    "sg:classifiers":[
        {
            "category":"Home & Garden",
            "subcategory":"Furniture",
            "type":"Retail Goods"
        }
    ],
    "sg:phone":"+33 5 58 49 20 40",
    "sg:postcode":"40800",
    "sg:province":"Aquitaine",
    "sg:tags":[
        "wood"
    ],
    "wof:name":"Delpeyrat Sa (dsa)",
    "wof:placetype":"venue"
},
  "geometry": {"coordinates":[-0.273659,43.592381],"type":"Point"}
}