{
  "type": "Feature",
  "properties": {
    "addr:full":"5 Rue Du G\u00e9n\u00e9ral Cassagnou 68301 St Louis Pays de Loire",
    "addr:housenumber":"5",
    "addr:postcode":"68301",
    "addr:street":"Rue Du Ge\u0301Ne\u0301Ral Cassagnou;St Louis Pays",
    "iso:country":"FR",
    "sg:address":"5 Rue Du G\u00e9n\u00e9ral Cassagnou 68301 St Louis",
    "sg:classifiers":[
        {
            "category":"Professional",
            "subcategory":"Business Services",
            "type":"Services"
        }
    ],
    "sg:phone":"+33 3 89 69 50 00",
    "sg:province":"Pays de Loire",
    "sg:tags":[
        "body",
        "advice"
    ],
    "wof:name":"Institut Franco-allemand De Recherches De St Louis",
    "wof:placetype":"venue"
},
  "geometry": {"coordinates":[7.561835,47.591236],"type":"Point"}
}