{
  "type": "Feature",
  "properties": {
    "addr:full":"Rue du Lusiau - ZA les Laumes Venarey les Laumes Bourgogne 21150",
    "addr:postcode":"21150",
    "addr:street":"Rue Du Lusiau Za Les;Venarey",
    "iso:country":"FR",
    "sg:address":"Rue du Lusiau - ZA les Laumes",
    "sg:city":"Venarey les Laumes",
    "sg:orig_category":"Non-Classified Establishments",
    "sg:phone":"+33 3 80 96 85 20",
    "sg:postcode":"21150",
    "sg:province":"Bourgogne",
    "wof:name":"M.c.m. S.a.",
    "wof:placetype":"venue"
},
  "geometry": {"coordinates":[4.459186,47.542641],"type":"Point"}
}