{
  "type": "Feature",
  "properties": {
    "addr:full":"18 Rue Lafayette Paris Ile de France 75009",
    "addr:housenumber":"18",
    "addr:postcode":"75009",
    "addr:street":"Rue Lafayette",
    "iso:country":"FR",
    "sg:address":"18 Rue Lafayette",
    "sg:city":"Paris",
    "sg:classifiers":[
        {
            "category":"Banks & Credit Unions",
            "subcategory":"Financial Services",
            "type":"Services"
        }
    ],
    "sg:phone":"+33 1 48 00 52 52",
    "sg:postcode":"75009",
    "sg:province":"Ile de France",
    "sg:tags":[
        "banking",
        "finance",
        "insurance"
    ],
    "wof:name":"Association Francaise Des Banques",
    "wof:placetype":"venue"
},
  "geometry": {"coordinates":[2.340605,48.87368],"type":"Point"}
}