{
  "type": "Feature",
  "properties": {
    "iso:country":"FR",
    "sg:address":"ZA Beaux Vallons",
    "sg:city":"Saint Sauveur d'Aunis",
    "sg:orig_category":"Non-Classified Establishments",
    "sg:phone":"+33 5 46 01 90 32",
    "sg:postcode":"17540",
    "sg:province":"Poitou-Charentes",
    "wof:name":"B\u00e2teaux Boutemy S.a.r.l.",
    "wof:placetype":"venue"
},
  "geometry": {"coordinates":[-0.89154,46.216702],"type":"Point"}
}