{
  "type": "Feature",
  "properties": {
    "iso:country":"FR",
    "sg:address":"15c Rue De Lille Zi Cd 549 59113 Seclin",
    "sg:classifiers":[
        {
            "category":"Food & Beverages",
            "subcategory":"Fruits & Vegetables",
            "type":"Retail Goods"
        }
    ],
    "sg:phone":"+33 3 20 16 63 60",
    "sg:postcode":"59113",
    "sg:province":"Nord Pas-de-Calais",
    "sg:tags":[
        "frozen",
        "product",
        "related"
    ],
    "wof:name":"Relais D'or Miko Rom",
    "wof:placetype":"venue"
},
  "geometry": {"coordinates":[3.035211,50.559502],"type":"Point"}
}