{
  "type": "Feature",
  "properties": {
    "iso:country":"FR",
    "sg:address":"Ch\u00e2teau Landon",
    "sg:city":"B\u00e9gadan",
    "sg:orig_category":"Non-Classified Establishments",
    "sg:phone":"+33 5 56 41 50 42",
    "sg:postcode":"33340",
    "sg:province":"Aquitaine",
    "wof:name":"Philippe Gillet Et Fils E.a.r.l.",
    "wof:placetype":"venue"
},
  "geometry": {"coordinates":[-0.874804,45.348179],"type":"Point"}
}