{
  "type": "Feature",
  "properties": {
    "iso:country":"FR",
    "sg:address":"284",
    "sg:city":"Laquets 74800 Saint Pierre en Faucigny",
    "sg:classifiers":[
        {
            "category":"Manufacturing",
            "subcategory":"Metals",
            "type":"Manufacturing & Wholesale Goods"
        }
    ],
    "sg:phone":"+33 4 50 25 01 33",
    "sg:postcode":"74800",
    "sg:province":"Rhone-Alpes",
    "sg:tags":[
        "-",
        "machine",
        "equipment",
        "engineering",
        "machinery",
        "mechanical"
    ],
    "wof:name":"Decip (sa)",
    "wof:placetype":"venue"
},
  "geometry": {"coordinates":[6.374261,46.074505],"type":"Point"}
}