{
  "type": "Feature",
  "properties": {
    "addr:full":"1 bis, Rue des A\u00e9rostiers - ZI Les Richardets, 93165 Noisy le Grand C\u00e9dex Limousin",
    "addr:housenumber":"1 bis",
    "addr:postcode":"93165",
    "addr:street":"Rue Des Ae\u0301Rostiers Zi Les Richardets",
    "iso:country":"FR",
    "sg:address":"1 bis, Rue des A\u00e9rostiers - ZI Les Richardets, 93165 Noisy le Grand C\u00e9dex",
    "sg:orig_category":"Non-Classified Establishments",
    "sg:phone":"+33 1 41 67 30 00",
    "sg:province":"Limousin",
    "wof:name":"E.c.s. Maintenance S.a. - Europe Computer Syst\u00e8mes",
    "wof:placetype":"venue"
},
  "geometry": {"coordinates":[2.553644,48.848892],"type":"Point"}
}