{
  "type": "Feature",
  "properties": {
    "iso:country":"FR",
    "sg:address":"101 Av Du Marin Blanc BP 1322 13784 Aubagne",
    "sg:classifiers":[
        {
            "category":"Professional",
            "subcategory":"Engineering",
            "type":"Services"
        }
    ],
    "sg:phone":"+33 4 42 18 02 60",
    "sg:province":"Midi Pyr\u00e9n\u00e9es",
    "sg:tags":[
        "machine",
        "-",
        "mechanical"
    ],
    "wof:name":"Generale Frigorifique Provencale-gfp",
    "wof:placetype":"venue"
},
  "geometry": {"coordinates":[5.596233,43.284927],"type":"Point"}
}