{
  "type": "Feature",
  "properties": {
    "iso:country":"FR",
    "sg:address":"13, Rue Charles Linn\u00e9 - ZAC Lavall\u00e9e, 02100 Saint Quentin",
    "sg:orig_category":"Non-Classified Establishments",
    "sg:phone":"+33 3 23 06 23 06",
    "sg:postcode":"02100",
    "sg:province":"Picardie",
    "wof:name":"Bruhy Vacherand S.a.",
    "wof:placetype":"venue"
},
  "geometry": {"coordinates":[3.291399,49.850842],"type":"Point"}
}