{
  "type": "Feature",
  "properties": {
    "iso:country":"FR",
    "sg:address":"2 pl de la Fontaine; Mutzig; 67190",
    "sg:city":"Mutzig",
    "sg:classifiers":[
        {
            "category":"Banks & Credit Unions",
            "subcategory":"Bank",
            "type":"Services"
        }
    ],
    "sg:phone":"+33 3 88 38 13 93",
    "sg:postcode":"67190",
    "sg:province":"Alsace",
    "wof:name":"Cr\u00e9dit Indsutriel D'alsace, Et De Lorraine Sa",
    "wof:placetype":"venue"
},
  "geometry": {"coordinates":[7.45611,48.538715],"type":"Point"}
}