{
  "type": "Feature",
  "properties": {
    "addr:full":"15 Rue Louis L\u00e9pine Zone Commerciale Royan 2 17200 Royan Poitou-Charentes 17200",
    "addr:housenumber":"15;2",
    "addr:postcode":"17200;17200",
    "addr:street":"Rue Louis Le\u0301Pine Zone Commerciale",
    "iso:country":"FR",
    "sg:address":"15 Rue Louis L\u00e9pine Zone Commerciale Royan 2 17200 Royan",
    "sg:classifiers":[
        {
            "category":"Manufacturing",
            "subcategory":"Tools & Machinery",
            "type":"Manufacturing & Wholesale Goods"
        }
    ],
    "sg:phone":"+33 5 46 05 08 83",
    "sg:postcode":"17200",
    "sg:province":"Poitou-Charentes",
    "sg:tags":[
        "metallurgy",
        "metalworking"
    ],
    "wof:name":"Comptoir Agricole Et Commercial De Cognac (cacc)",
    "wof:placetype":"venue"
},
  "geometry": {"coordinates":[-1.030124,45.626137],"type":"Point"}
}