{
  "type": "Feature",
  "properties": {
    "iso:country":"FR",
    "sg:address":"17, Rue de l'Abattoir, 70800 Saint Loup sur Semouse",
    "sg:orig_category":"Non-Classified Establishments",
    "sg:phone":"+33 3 84 49 01 59",
    "sg:province":"Franche Comt\u00e9",
    "wof:name":"Soci\u00e9t\u00e9 De Menuiserie G\u00e9n\u00e9rale Hubert S.a.r.l.",
    "wof:placetype":"venue"
},
  "geometry": {"coordinates":[6.270444,47.886108],"type":"Point"}
}