{
  "type": "Feature",
  "properties": {
    "iso:country":"FR",
    "sg:address":"86 Rue Des Archives 75003 Paris",
    "sg:classifiers":[
        {
            "category":"Manufacturing",
            "subcategory":"Metals",
            "type":"Manufacturing & Wholesale Goods"
        }
    ],
    "sg:phone":"+33 1 42 78 70 10",
    "sg:postcode":"75003",
    "sg:province":"Ile de France",
    "sg:tags":[
        "-",
        "machine",
        "equipment",
        "engineering",
        "machinery",
        "mechanical"
    ],
    "wof:name":"Emporte Piece Du Marais",
    "wof:placetype":"venue"
},
  "geometry": {"coordinates":[2.360525,48.862988],"type":"Point"}
}