{
  "type": "Feature",
  "properties": {
    "addr:full":"82 Entrepreneurs 75015 Paris Ile de France 75015",
    "addr:housenumber":"82",
    "addr:postcode":"75015;75015",
    "addr:street":"Entrepreneurs",
    "iso:country":"FR",
    "sg:address":"82",
    "sg:city":"Entrepreneurs 75015 Paris",
    "sg:orig_category":"Agriculture and Livestock Ceramics Cereals and grains Glass and Building Materials Miscellaneous Pro",
    "sg:phone":"+33 1 45 77 95 95",
    "sg:postcode":"75015",
    "sg:province":"Ile de France",
    "wof:name":"Abrilplus",
    "wof:placetype":"venue"
},
  "geometry": {"coordinates":[2.291204,48.844254],"type":"Point"}
}