{
  "type": "Feature",
  "properties": {
    "addr:full":"Rue Bramafan 73230 Barby Rhone-Alpes 73230",
    "addr:postcode":"73230;73230",
    "addr:street":"Rue Bramafan",
    "iso:country":"FR",
    "sg:address":"Rue Bramafan 73230 Barby",
    "sg:classifiers":[
        {
            "category":"Building & Trades",
            "subcategory":"Construction",
            "type":"Services"
        }
    ],
    "sg:phone":"+33 4 79 71 09 09",
    "sg:postcode":"73230",
    "sg:province":"Rhone-Alpes",
    "sg:tags":[
        "work",
        "public"
    ],
    "wof:name":"Entreprise Piani",
    "wof:placetype":"venue"
},
  "geometry": {"coordinates":[5.97682,45.566013],"type":"Point"}
}