{
  "type": "Feature",
  "properties": {
    "iso:country":"FR",
    "sg:address":"25, Bd de Strasbourg, 75010 Paris",
    "sg:orig_category":"Non-Classified Establishments",
    "sg:phone":"+33 1 42 49 02 31",
    "sg:province":"Ile de France",
    "wof:name":"Glasman Et Compagnie S.a.",
    "wof:placetype":"venue"
},
  "geometry": {"coordinates":[2.354902,48.870926],"type":"Point"}
}