{
  "type": "Feature",
  "properties": {
    "addr:full":"48 R Aristide Briand 77170 Coubert Ile de France 77170",
    "addr:housenumber":"48",
    "addr:postcode":"77170;77170",
    "addr:street":"R Aristide Briand;Ile De France",
    "iso:country":"FR",
    "sg:address":"48 R Aristide Briand 77170 Coubert",
    "sg:classifiers":[
        {
            "category":"Food & Beverages",
            "subcategory":"Groceries & Convenience Stores",
            "type":"Retail Goods"
        }
    ],
    "sg:phone":"+33 1 64 06 74 89",
    "sg:postcode":"77170",
    "sg:province":"Ile de France",
    "sg:tags":[
        "product",
        "related"
    ],
    "wof:name":"M. Lemarie Marc",
    "wof:placetype":"venue"
},
  "geometry": {"coordinates":[2.698136,48.674084],"type":"Point"}
}