{
  "type": "Feature",
  "properties": {
    "iso:country":"FR",
    "sg:address":"4, Rue du Fort - Centre de Gros n\u00b02, 59818 Lesquin C\u00e9dex",
    "sg:city":"Lesquin",
    "sg:orig_category":"Non-Classified Establishments",
    "sg:phone":"+33 3 20 18 03 00",
    "sg:postcode":"59810",
    "sg:province":"Nord Pas-de-Calais",
    "wof:name":"Etandex S.a.",
    "wof:placetype":"venue"
},
  "geometry": {"coordinates":[3.11003,50.588009],"type":"Point"}
}