{
  "type": "Feature",
  "properties": {
    "iso:country":"FR",
    "sg:address":"32260 Ornezan",
    "sg:classifiers":[
        {
            "category":"Health Services",
            "subcategory":"Medical Lab",
            "type":"Services"
        }
    ],
    "sg:phone":"+33 5 62 66 22 80",
    "sg:postcode":"32260",
    "sg:province":"Midi Pyr\u00e9n\u00e9es",
    "sg:tags":[
        "chemical",
        "pharmaceutical",
        "pharmacy"
    ],
    "wof:name":"Cdp Clartex",
    "wof:placetype":"venue"
},
  "geometry": {"coordinates":[0.601615,43.510994],"type":"Point"}
}