{
  "type": "Feature",
  "properties": {
    "addr:full":"B.P. 80439, 60544 M\u00e9ru C\u00e9dex^^4, Rue du Professeur Dubos, 60119 H\u00e9nonville Picardie",
    "addr:postcode":"60544;60119",
    "addr:street":"Rue Du Professeur Dubos",
    "iso:country":"FR",
    "sg:address":"B.P. 80439, 60544 M\u00e9ru C\u00e9dex^^4, Rue du Professeur Dubos, 60119 H\u00e9nonville",
    "sg:orig_category":"Non-Classified Establishments",
    "sg:phone":"+33 3 44 49 86 22",
    "sg:province":"Picardie",
    "wof:name":"Max Perles Et Compagnie S.a.",
    "wof:placetype":"venue"
},
  "geometry": {"coordinates":[2.01141,49.200165],"type":"Point"}
}