{
  "type": "Feature",
  "properties": {
    "addr:full":"All Des Roses 30130 Pont St Esprit Languedoc-Roussillon 30130",
    "addr:postcode":"30130;30130",
    "addr:street":"Pont St Esprit",
    "iso:country":"FR",
    "sg:address":"All Des Roses 30130 Pont St Esprit",
    "sg:classifiers":[
        {
            "category":"Farming",
            "subcategory":"Livestock Farm",
            "type":"Manufacturing & Wholesale Goods"
        }
    ],
    "sg:phone":"+33 4 66 39 08 52",
    "sg:postcode":"30130",
    "sg:province":"Languedoc-Roussillon",
    "sg:tags":[
        "grain",
        "agriculture",
        "cereal"
    ],
    "wof:name":"Capl",
    "wof:placetype":"venue"
},
  "geometry": {"coordinates":[4.640658,44.243977],"type":"Point"}
}