{
  "type": "Feature",
  "properties": {
    "iso:country":"FR",
    "sg:address":"Rue Louis Armand - ZI du Chiriac",
    "sg:city":"Albertville",
    "sg:orig_category":"Non-Classified Establishments",
    "sg:phone":"+33 4 79 37 89 81",
    "sg:postcode":"73200",
    "sg:province":"Rhone-Alpes",
    "wof:name":"Etablissements Descours & Cabaud",
    "wof:placetype":"venue"
},
  "geometry": {"coordinates":[6.359874,45.63168],"type":"Point"}
}