{
  "type": "Feature",
  "properties": {
    "addr:full":"Route Nationale 4 51300 Thieblemont Faremont Champagne 51300",
    "addr:postcode":"51300;51300",
    "addr:street":"Route Nationale 4;Champagne",
    "iso:country":"FR",
    "sg:address":"Route Nationale 4 51300 Thieblemont Faremont",
    "sg:classifiers":[
        {
            "category":"Wholesale",
            "subcategory":"Machinery & Supplies",
            "type":"Manufacturing & Wholesale Goods"
        }
    ],
    "sg:phone":"+33 3 26 72 24 45",
    "sg:postcode":"51300",
    "sg:province":"Champagne",
    "sg:tags":[
        "handling",
        "material",
        "-",
        "machine",
        "equipment",
        "engineering",
        "mechanical"
    ],
    "wof:name":"Champagne Palettes",
    "wof:placetype":"venue"
},
  "geometry": {"coordinates":[4.563456,48.648991],"type":"Point"}
}