{
  "type": "Feature",
  "properties": {
    "iso:country":"FR",
    "sg:address":"1, Rue Gutemberg, 78500 Sartrouville",
    "sg:orig_category":"Non-Classified Establishments",
    "sg:phone":"+33 1 39 68 41 41",
    "sg:province":"Ile de France",
    "wof:name":"Soci\u00e9t\u00e9 Isartel S.a.r.l.",
    "wof:placetype":"venue"
},
  "geometry": {"coordinates":[2.166986,48.928471],"type":"Point"}
}