{
  "type": "Feature",
  "properties": {
    "addr:full":"38, Rue de Colli\u00e8re, 69780 Mions Rhone-Alpes 69780",
    "addr:housenumber":"38",
    "addr:postcode":"69780;69780",
    "addr:street":"Rue De Collie\u0300Re;Rhone-Alpes",
    "iso:country":"FR",
    "sg:address":"38, Rue de Colli\u00e8re, 69780 Mions",
    "sg:orig_category":"Non-Classified Establishments",
    "sg:phone":"+33 4 78 20 26 99",
    "sg:postcode":"69780",
    "sg:province":"Rhone-Alpes",
    "wof:name":"Sogec S.a.",
    "wof:placetype":"venue"
},
  "geometry": {"coordinates":[4.93919,45.683018],"type":"Point"}
}