{
  "type": "Feature",
  "properties": {
    "addr:full":"Les Maurissoux 24620 Marquay Marquay Aquitaine 24620",
    "addr:postcode":"24620;24620",
    "iso:country":"FR",
    "sg:address":"Les Maurissoux 24620 Marquay",
    "sg:city":"Marquay",
    "sg:orig_category":"Unclassifiable Establishments",
    "sg:phone":"+33 5 53 31 79 79",
    "sg:postcode":"24620",
    "sg:province":"Aquitaine",
    "wof:name":"Les Hauts De Marquay",
    "wof:placetype":"venue"
},
  "geometry": {"coordinates":[1.013269,44.935936],"type":"Point"}
}