{
  "type": "Feature",
  "properties": {
    "addr:full":"83 A, Rte de Ch\u00e2teaurenault, 41000 Blois Blois Centre 41000",
    "addr:housenumber":"83",
    "addr:postcode":"41000;41000",
    "addr:street":"A Rte De Cha\u0302Teaurenault",
    "iso:country":"FR",
    "sg:address":"83 A, Rte de Ch\u00e2teaurenault, 41000 Blois",
    "sg:city":"Blois",
    "sg:orig_category":"Unclassifiable Establishments",
    "sg:phone":"+33 2 54 78 40 91",
    "sg:postcode":"41000",
    "sg:province":"Centre",
    "wof:name":"J.c.g. Entreprises S.a.",
    "wof:placetype":"venue"
},
  "geometry": {"coordinates":[1.30574,47.583199],"type":"Point"}
}