{
  "type": "Feature",
  "properties": {
    "iso:country":"FR",
    "sg:address":"282, Rue Cr\u00e9qui, 69007 Lyon",
    "sg:orig_category":"Unclassifiable Establishments",
    "sg:phone":"+33 4 72 71 69 45",
    "sg:province":"Rhone-Alpes",
    "wof:name":"Axis S.a.",
    "wof:placetype":"venue"
},
  "geometry": {"coordinates":[4.848304,45.751331],"type":"Point"}
}