{
  "type": "Feature",
  "properties": {
    "iso:country":"FR",
    "sg:address":"B.P. 242, 71309 Montceau les Mines C\u00e9dex^^6, Rue de Gueugnon, 71300 Montceau les Mines",
    "sg:city":"Saint-Berain-sous-Sanvignes",
    "sg:orig_category":"Non-Classified Establishments",
    "sg:phone":"+33 3 85 69 07 00",
    "sg:postcode":"71300",
    "sg:province":"Bourgogne",
    "wof:name":"Serib T\u00f4lerie S.a.r.l.",
    "wof:placetype":"venue"
},
  "geometry": {"coordinates":[4.498485,46.618446],"type":"Point"}
}