{
  "type": "Feature",
  "properties": {
    "addr:full":"7 pl R\u00e9publique; Mions Rhone-Alpes",
    "addr:housenumber":"7;re\u0301publique",
    "addr:street":"Pl",
    "iso:country":"FR",
    "sg:address":"7 pl R\u00e9publique; Mions",
    "sg:classifiers":[
        {
            "category":"Banks & Credit Unions",
            "subcategory":"Bank",
            "type":"Services"
        }
    ],
    "sg:phone":"+33 3378203423",
    "sg:province":"Rhone-Alpes",
    "wof:name":"Cr\u00e9dit Agricole Du Sud Est",
    "wof:placetype":"venue"
},
  "geometry": {"coordinates":[4.95673,45.664009],"type":"Point"}
}