{
  "type": "Feature",
  "properties": {
    "iso:country":"FR",
    "sg:address":"265, Bd de la Madeleine, 06000 Nice",
    "sg:orig_category":"Non-Classified Establishments",
    "sg:phone":"+33 4 93 44 85 83",
    "sg:province":"Midi Pyr\u00e9n\u00e9es",
    "wof:name":"Contact Azur S.a.r.l.",
    "wof:placetype":"venue"
},
  "geometry": {"coordinates":[7.227191,43.710781],"type":"Point"}
}