{
  "type": "Feature",
  "properties": {
    "addr:full":"Chem Usine 21250 Pouilly Sur Sa\u00f4ne Villy-le-Moutier Bourgogne 21250",
    "addr:postcode":"21250;21250",
    "addr:street":"Chem Usine",
    "iso:country":"FR",
    "sg:address":"Chem Usine 21250 Pouilly Sur Sa\u00f4ne",
    "sg:city":"Villy-le-Moutier",
    "sg:classifiers":[
        {
            "category":"Home & Garden",
            "subcategory":"Furniture",
            "type":"Retail Goods"
        }
    ],
    "sg:phone":"+33 3 80 20 38 40",
    "sg:postcode":"21250",
    "sg:province":"Bourgogne",
    "sg:tags":[
        "household",
        "wood"
    ],
    "wof:name":"Bois Secs De Bourgogne Sa",
    "wof:placetype":"venue"
},
  "geometry": {"coordinates":[5.117415,47.018879],"type":"Point"}
}