{
  "type": "Feature",
  "properties": {
    "addr:full":"Rue Denis Papin 10371 VILLENAUXE LA GRANDE Vill\u00e9 Alsace 67220",
    "addr:postcode":"10371;67220",
    "addr:street":"Rue Denis Papin",
    "iso:country":"FR",
    "sg:address":"Rue Denis Papin 10371 VILLENAUXE LA GRANDE",
    "sg:city":"Vill\u00e9",
    "sg:orig_category":"Polishing Wheels",
    "sg:phone":"+33 3 25 39 54 70",
    "sg:postcode":"67220",
    "sg:province":"Alsace",
    "wof:name":"Hilzinger France Sarl",
    "wof:placetype":"venue"
},
  "geometry": {"coordinates":[4.081093,43.561741],"type":"Point"}
}