{
  "type": "Feature",
  "properties": {
    "iso:country":"FR",
    "sg:address":"1 bis rue de l'\u00c9glise; Limay; 78520",
    "sg:classifiers":[
        {
            "category":"Banks & Credit Unions",
            "subcategory":"Bank",
            "type":"Services"
        }
    ],
    "sg:phone":"+33 3334775458",
    "sg:postcode":"78520",
    "sg:province":"Ile de France",
    "wof:name":"Soci\u00e9t\u00e9 G\u00e9n\u00e9rale",
    "wof:placetype":"venue"
},
  "geometry": {"coordinates":[1.731321,48.994373],"type":"Point"}
}