{
  "type": "Feature",
  "properties": {
    "addr:full":"6/10, Rue de la Poti\u00e8re, 51450 B\u00e9theny Champagne",
    "addr:housenumber":"6 / 10",
    "addr:postcode":"51450",
    "addr:street":"Rue De La Potie\u0300Re",
    "iso:country":"FR",
    "sg:address":"6/10, Rue de la Poti\u00e8re, 51450 B\u00e9theny",
    "sg:orig_category":"Non-Classified Establishments",
    "sg:phone":"+33 3 26 07 89 30",
    "sg:province":"Champagne",
    "wof:name":"S.f.e.a. Attelage Brink Et Atlux S.a. - Soci\u00e9t\u00e9 De Fabrication D'equipements D'accessoires",
    "wof:placetype":"venue"
},
  "geometry": {"coordinates":[4.054099,49.277527],"type":"Point"}
}