{
  "type": "Feature",
  "properties": {
    "addr:full":"Rue Lieron 91160 Longjumeau Ile de France",
    "addr:postcode":"91160;ile",
    "addr:street":"Rue Lieron",
    "iso:country":"FR",
    "sg:address":"Rue Lieron 91160 Longjumeau",
    "sg:classifiers":[
        {
            "category":"Manufacturing",
            "subcategory":"Printing",
            "type":"Manufacturing & Wholesale Goods"
        }
    ],
    "sg:phone":"+33 1 69 10 17 80",
    "sg:province":"Ile de France",
    "sg:tags":[
        "publishing"
    ],
    "wof:name":"J M D Etiquettes Sa",
    "wof:placetype":"venue"
},
  "geometry": {"coordinates":[2.29093,48.692616],"type":"Point"}
}