{
  "type": "Feature",
  "properties": {
    "addr:full":"7 Quai Alsace Lorraine 77000 Melun Ile de France 77000",
    "addr:housenumber":"7",
    "addr:postcode":"77000;ile;77000",
    "addr:street":"Quai Alsace Lorraine;France",
    "iso:country":"FR",
    "sg:address":"7 Quai Alsace Lorraine 77000 Melun",
    "sg:classifiers":[
        {
            "category":"Wholesale",
            "subcategory":"Machinery & Supplies",
            "type":"Manufacturing & Wholesale Goods"
        }
    ],
    "sg:phone":"+33 1 64 52 07 69",
    "sg:postcode":"77000",
    "sg:province":"Ile de France",
    "sg:tags":[
        "equipment",
        "-",
        "precision",
        "glass",
        "optical",
        "health",
        "instrument"
    ],
    "wof:name":"Les Opticiens Balouzat 77",
    "wof:placetype":"venue"
},
  "geometry": {"coordinates":[2.659974,48.537449],"type":"Point"}
}