{
  "type": "Feature",
  "properties": {
    "iso:country":"FR",
    "sg:address":"La Chanal 69640 Jarnioux",
    "sg:orig_category":"Non-Classified Establishments",
    "sg:phone":"+33 4 74 03 89 17",
    "sg:postcode":"69640",
    "sg:province":"Rhone-Alpes",
    "wof:name":"Etablissements D. Le Goff",
    "wof:placetype":"venue"
},
  "geometry": {"coordinates":[4.621863,45.966698],"type":"Point"}
}