{
  "type": "Feature",
  "properties": {
    "iso:country":"FR",
    "sg:address":"30, Rue Denis Papin - La Duri\u00e8re , 42170 Saint Just Saint Rambert",
    "sg:orig_category":"Non-Classified Establishments",
    "sg:phone":"+33 4 77 36 17 17",
    "sg:postcode":"42170",
    "sg:province":"Rhone-Alpes",
    "wof:name":"Soci\u00e9t\u00e9 D'exploitation Vacher Marcel S.a.r.l.",
    "wof:placetype":"venue"
},
  "geometry": {"coordinates":[4.281378,45.515099],"type":"Point"}
}