{
  "type": "Feature",
  "properties": {
    "iso:country":"FR",
    "sg:address":"B.P. 813, 31080 Toulouse C\u00e9dex^^8, Esplanade Compans Caffarelli, 31000 Toulouse",
    "sg:orig_category":"Non-Classified Establishments",
    "sg:phone":"+33 5 62 30 50 03",
    "sg:province":"Midi Pyr\u00e9n\u00e9es",
    "wof:name":"Intentia Consulting",
    "wof:placetype":"venue"
},
  "geometry": {"coordinates":[1.44869,43.60574],"type":"Point"}
}