{
  "type": "Feature",
  "properties": {
    "addr:full":"2 rue Jacques Preiss 68340 Riquewihr Riquewihr Alsace 68340",
    "addr:housenumber":"2",
    "addr:postcode":"68340;68340",
    "addr:street":"Rue Jacques Preiss",
    "iso:country":"FR",
    "sg:address":"2 rue Jacques Preiss 68340 Riquewihr",
    "sg:city":"Riquewihr",
    "sg:classifiers":[
        {
            "category":"Wholesale",
            "subcategory":"Wine & Distilled Alcoholic Beverages",
            "type":"Manufacturing & Wholesale Goods"
        }
    ],
    "sg:phone":"+33 3 89 49 09 69",
    "sg:postcode":"68340",
    "sg:province":"Alsace",
    "sg:tags":[
        "french"
    ],
    "wof:name":"Alsace Burckard Sa",
    "wof:placetype":"venue"
},
  "geometry": {"coordinates":[7.303828,48.165863],"type":"Point"}
}