{
  "type": "Feature",
  "properties": {
    "addr:full":"Reinacker 67440 Reutenbourg Reutenbourg Alsace 67440",
    "addr:postcode":"67440;67440",
    "addr:street":"Reinacker",
    "iso:country":"FR",
    "sg:address":"Reinacker 67440 Reutenbourg",
    "sg:city":"Reutenbourg",
    "sg:classifiers":[
        {
            "category":"Professional",
            "subcategory":"Business Services",
            "type":"Services"
        }
    ],
    "sg:phone":"+33 3 88 70 60 50",
    "sg:postcode":"67440",
    "sg:province":"Alsace",
    "sg:tags":[
        "body",
        "advice"
    ],
    "wof:name":"Association Reinacker",
    "wof:placetype":"venue"
},
  "geometry": {"coordinates":[7.407433,48.68124],"type":"Point"}
}