{
  "type": "Feature",
  "properties": {
    "iso:country":"FR",
    "sg:address":"4 Rue De Bastogne Zae Cap Nord 21850 St Apollinaire",
    "sg:city":"Saint-Apollinaire",
    "sg:classifiers":[
        {
            "category":"Professional",
            "subcategory":"Printing & Photocopies",
            "type":"Services"
        }
    ],
    "sg:phone":"+33 3 80 78 90 40",
    "sg:postcode":"21850",
    "sg:province":"Bourgogne",
    "sg:tags":[
        "publishing"
    ],
    "wof:name":"Ste Edition Et Publication De Bourgogne",
    "wof:placetype":"venue"
},
  "geometry": {"coordinates":[5.083654,47.333641],"type":"Point"}
}