{
  "type": "Feature",
  "properties": {
    "addr:full":"5 Chem Br\u00fbl\u00e9 62910 Houlle Nord Pas-de-Calais",
    "addr:housenumber":"5",
    "addr:postcode":"62910",
    "addr:street":"Chem Bru\u0302Le\u0301",
    "iso:country":"FR",
    "sg:address":"5 Chem Br\u00fbl\u00e9 62910 Houlle",
    "sg:classifiers":[
        {
            "category":"Professional",
            "type":"Services"
        }
    ],
    "sg:phone":"+33 3 21 93 13 59",
    "sg:province":"Nord Pas-de-Calais",
    "sg:tags":[
        "transport",
        "road"
    ],
    "wof:name":"Etablissements Wierre Sarl",
    "wof:placetype":"venue"
},
  "geometry": {"coordinates":[2.17094,50.795506],"type":"Point"}
}