{
  "type": "Feature",
  "properties": {
    "iso:country":"FR",
    "sg:address":"B.P. 2, 34630 Saint Thib\u00e9ry^^Ancien Chemin de Bessan - Zone d'Activit\u00e9 le Causse, 34630 Saint Thib\u00e9r",
    "sg:orig_category":"Non-Classified Establishments",
    "sg:phone":"+33 4 67 77 76 97",
    "sg:province":"Languedoc-Roussillon",
    "wof:name":"Routiers Languedociens S.a.r.l.",
    "wof:placetype":"venue"
},
  "geometry": {"coordinates":[3.370532,43.419968],"type":"Point"}
}