{
  "type": "Feature",
  "properties": {
    "addr:full":"Rte De Dijon 70100 Mantoche Franche Comt\u00e9",
    "addr:postcode":"70100",
    "addr:street":"Rte De Dijon;Franche Comte\u0301",
    "iso:country":"FR",
    "sg:address":"Rte De Dijon 70100 Mantoche",
    "sg:classifiers":[
        {
            "category":"Professional",
            "type":"Services"
        }
    ],
    "sg:phone":"+33 3 84 65 13 23",
    "sg:province":"Franche Comt\u00e9",
    "sg:tags":[
        "transport",
        "road"
    ],
    "wof:name":"Baulard Pere Et Fils Sa",
    "wof:placetype":"venue"
},
  "geometry": {"coordinates":[5.52492,47.41803],"type":"Point"}
}