{
  "type": "Feature",
  "properties": {
    "iso:country":"FR",
    "sg:address":"ZA le Foss\u00e9 de la Cage",
    "sg:city":"Avrainville",
    "sg:orig_category":"Unclassifiable Establishments",
    "sg:phone":"+33 1 60 82 01 10",
    "sg:postcode":"91630",
    "sg:province":"Ile de France",
    "wof:name":"Pr\u00e9cis Moule",
    "wof:placetype":"venue"
},
  "geometry": {"coordinates":[2.246009,48.561462],"type":"Point"}
}