{
  "type": "Feature",
  "properties": {
    "addr:full":"Rue Claude Bernard 76330 Notre Dame De Gravenchon Haute Normandie 76330",
    "addr:postcode":"76330;76330",
    "addr:street":"Rue Claude Bernard;Dame",
    "iso:country":"FR",
    "sg:address":"Rue Claude Bernard 76330 Notre Dame De Gravenchon",
    "sg:classifiers":[
        {
            "category":"Manufacturing",
            "subcategory":"Tools & Machinery",
            "type":"Manufacturing & Wholesale Goods"
        }
    ],
    "sg:phone":"+33 2 35 38 04 63",
    "sg:postcode":"76330",
    "sg:province":"Haute Normandie",
    "sg:tags":[
        "metallurgy",
        "metalworking"
    ],
    "wof:name":"Comptoir Industriel Estuaire De La Seine",
    "wof:placetype":"venue"
},
  "geometry": {"coordinates":[0.582365,49.480915],"type":"Point"}
}