{
  "type": "Feature",
  "properties": {
    "addr:full":"1, Rte de Pannes, 54470 Essey et Maizerais Lorraine 54470",
    "addr:housenumber":"1",
    "addr:postcode":"54470;54470",
    "addr:street":"Rte De Pannes;Lorraine",
    "iso:country":"FR",
    "sg:address":"1, Rte de Pannes, 54470 Essey et Maizerais",
    "sg:orig_category":"Non-Classified Establishments",
    "sg:phone":"+33 3 83 81 92 10",
    "sg:postcode":"54470",
    "sg:province":"Lorraine",
    "wof:name":"Didier S.a.",
    "wof:placetype":"venue"
},
  "geometry": {"coordinates":[5.862805,48.955154],"type":"Point"}
}