{
  "type": "Feature",
  "properties": {
    "addr:full":"11 R Des Marronniers Le Zac Dup Zac Du Plateau 94240 L Hay Les Roses Ile de France 94240",
    "addr:housenumber":"11",
    "addr:postcode":"94240;94240",
    "addr:street":"R Des Marronniers Le Zac Dup Zac Du Plateau;Hay",
    "iso:country":"FR",
    "sg:address":"11 R Des Marronniers Le Zac Dup Zac Du Plateau 94240 L Hay Les Roses",
    "sg:classifiers":[
        {
            "category":"Manufacturing",
            "subcategory":"Leather Goods",
            "type":"Manufacturing & Wholesale Goods"
        }
    ],
    "sg:phone":"+33 1 46 87 35 55",
    "sg:postcode":"94240",
    "sg:province":"Ile de France",
    "sg:tags":[
        "shoe"
    ],
    "wof:name":"Cofraplex",
    "wof:placetype":"venue"
},
  "geometry": {"coordinates":[2.33898,48.778679],"type":"Point"}
}