{
  "type": "Feature",
  "properties": {
    "iso:country":"FR",
    "sg:address":"1, Rue du Nouette - Z.I., 22100 Dinan",
    "sg:city":"Dinan",
    "sg:orig_category":"Unclassifiable Establishments",
    "sg:phone":"+33 2 96 39 02 80",
    "sg:postcode":"22100",
    "sg:province":"Bretagne",
    "wof:name":"Sol Vit Net S.a.",
    "wof:placetype":"venue"
},
  "geometry": {"coordinates":[-2.064859,48.390835],"type":"Point"}
}