{
  "type": "Feature",
  "properties": {
    "addr:full":"41-49, Rue Gauthier Dumont, 42100 Saint Etienne Rhone-Alpes 42100",
    "addr:housenumber":"41-49",
    "addr:postcode":"42100;42100",
    "addr:street":"Rue Gauthier Dumont",
    "iso:country":"FR",
    "sg:address":"41-49, Rue Gauthier Dumont, 42100 Saint Etienne",
    "sg:orig_category":"Unclassifiable Establishments",
    "sg:phone":"+33 4 77 38 11 54",
    "sg:postcode":"42100",
    "sg:province":"Rhone-Alpes",
    "wof:name":"Hp Production S.a.r.l.",
    "wof:placetype":"venue"
},
  "geometry": {"coordinates":[4.418804,45.435688],"type":"Point"}
}