{
  "type": "Feature",
  "properties": {
    "addr:full":"9, Bd de l'Europe - Immeuble Delta, 91000 Evry Ile de France 91000",
    "addr:housenumber":"9",
    "addr:postcode":"91000;91000",
    "addr:street":"Bd De L'Europe",
    "iso:country":"FR",
    "sg:address":"9, Bd de l'Europe - Immeuble Delta, 91000 Evry",
    "sg:orig_category":"Non-Classified Establishments",
    "sg:phone":"+33 1 60 87 01 20",
    "sg:postcode":"91000",
    "sg:province":"Ile de France",
    "wof:name":"Dynamic Spray S.a.",
    "wof:placetype":"venue"
},
  "geometry": {"coordinates":[2.110918,51.002602],"type":"Point"}
}