{
  "type": "Feature",
  "properties": {
    "iso:country":"FR",
    "sg:address":"B.P. 138, 33321 B\u00e8gles C\u00e9dex^^360, Rte de Toulouse, 33130 B\u00e8gles",
    "sg:city":"B\u00e8gles",
    "sg:orig_category":"Non-Classified Establishments",
    "sg:phone":"+33 5 56 85 77 91",
    "sg:postcode":"33130",
    "sg:province":"Aquitaine",
    "wof:name":"C.g.l. S.a. - Compagnie G\u00e9n\u00e9rale De Location",
    "wof:placetype":"venue"
},
  "geometry": {"coordinates":[-0.553904,44.808079],"type":"Point"}
}