{
  "type": "Feature",
  "properties": {
    "addr:full":"11 Avenue Normandie Sussex 76200 Dieppe Haute Normandie",
    "addr:housenumber":"11",
    "addr:postcode":"76200",
    "addr:street":"Avenue Normandie Sussex",
    "iso:country":"FR",
    "sg:address":"11 Avenue Normandie Sussex 76200 Dieppe",
    "sg:classifiers":[
        {
            "category":"Wholesale",
            "subcategory":"Machinery & Supplies",
            "type":"Manufacturing & Wholesale Goods"
        }
    ],
    "sg:phone":"+33 2 35 82 43 29",
    "sg:province":"Haute Normandie",
    "sg:tags":[
        "equipment",
        "optical",
        "precision",
        "instrument"
    ],
    "wof:name":"Bao Move",
    "wof:placetype":"venue"
},
  "geometry": {"coordinates":[1.088345,49.917698],"type":"Point"}
}