{
  "type": "Feature",
  "properties": {
    "iso:country":"FR",
    "sg:address":"6 Rue Des Ponts 10000 Troyes",
    "sg:classifiers":[
        {
            "category":"Shopping",
            "subcategory":"Crafts & Fabrics",
            "type":"Retail Goods"
        }
    ],
    "sg:phone":"+33 3 25 82 95 99",
    "sg:postcode":"10000",
    "sg:province":"Champagne",
    "sg:tags":[
        "textile",
        "clothing"
    ],
    "wof:name":"Tricotage Maille 2-3",
    "wof:placetype":"venue"
},
  "geometry": {"coordinates":[4.089113,48.290443],"type":"Point"}
}