{
  "type": "Feature",
  "properties": {
    "iso:country":"FR",
    "sg:address":"B.P. 3",
    "sg:city":"Seveux^^70130 Seveux",
    "sg:orig_category":"Non-Classified Establishments",
    "sg:phone":"+33 3 84 67 11 00",
    "sg:postcode":"70130",
    "sg:province":"Franche Comt\u00e9",
    "wof:name":"Ontani Fr\u00e8res S.a.r.l.",
    "wof:placetype":"venue"
},
  "geometry": {"coordinates":[5.876931,47.582588],"type":"Point"}
}