{
  "type": "Feature",
  "properties": {
    "iso:country":"FR",
    "sg:address":"Impasse Sainte Victoire",
    "sg:city":"Saint Mitre les Remparts",
    "sg:orig_category":"Unclassifiable Establishments",
    "sg:phone":"+33 4 42 80 98 72",
    "sg:postcode":"13920",
    "sg:province":"Provence-Alpes-C\u00f4te d'Azur",
    "wof:name":"Evulca Sud S.a.r.l.",
    "wof:placetype":"venue"
},
  "geometry": {"coordinates":[5.01964,43.454041],"type":"Point"}
}