{
  "type": "Feature",
  "properties": {
    "iso:country":"FR",
    "sg:address":"B.P. 10, 70101 Gray C\u00e9dex^^Zone Industrielle les Giranaux, 70100 Arc l\u00e8s Gray",
    "sg:orig_category":"Non-Classified Establishments",
    "sg:phone":"+33 3 84 65 11 04",
    "sg:postcode":"70100",
    "sg:province":"Franche Comt\u00e9",
    "wof:name":"Cabinet D'expertise Comptable Champel S.a.",
    "wof:placetype":"venue"
},
  "geometry": {"coordinates":[5.514565,47.369511],"type":"Point"}
}