{
  "type": "Feature",
  "properties": {
    "addr:full":"10 Chem De La Gare 30340 Mons Languedoc-Roussillon 30340",
    "addr:housenumber":"10",
    "addr:postcode":"30340;30340",
    "addr:street":"Chem De La Gare",
    "iso:country":"FR",
    "sg:address":"10 Chem De La Gare 30340 Mons",
    "sg:classifiers":[
        {
            "category":"Professional",
            "subcategory":"Engineering",
            "type":"Services"
        }
    ],
    "sg:phone":"+33 4 66 83 15 81",
    "sg:postcode":"30340",
    "sg:province":"Languedoc-Roussillon",
    "sg:tags":[
        "instrument",
        "measurement",
        "-",
        "precision",
        "machine",
        "equipment",
        "mechanical"
    ],
    "wof:name":"Automatismes Mesure Controle Regulation Amcr",
    "wof:placetype":"venue"
},
  "geometry": {"coordinates":[4.17402,44.137169],"type":"Point"}
}