{
  "type": "Feature",
  "properties": {
    "addr:full":"31 Av Louis Gros 13230 Port St Louis Du Rhone Rhone-Alpes",
    "addr:housenumber":"13230",
    "addr:street":"31 Av Louis Gros",
    "iso:country":"FR",
    "sg:address":"31 Av Louis Gros 13230 Port St Louis Du Rhone",
    "sg:classifiers":[
        {
            "category":"Building & Trades",
            "subcategory":"Construction",
            "type":"Services"
        }
    ],
    "sg:phone":"+33 4 42 86 10 41",
    "sg:province":"Rhone-Alpes",
    "sg:tags":[
        "work",
        "public"
    ],
    "wof:name":"Sltp",
    "wof:placetype":"venue"
},
  "geometry": {"coordinates":[4.802599,43.38755],"type":"Point"}
}