{
  "type": "Feature",
  "properties": {
    "addr:full":"Avenue De Cambo Quartier Sutar 64600 Anglet Anglet Aquitaine 64600",
    "addr:postcode":"64600;64600",
    "addr:street":"Avenue De Cambo",
    "iso:country":"FR",
    "sg:address":"Avenue De Cambo Quartier Sutar 64600 Anglet",
    "sg:city":"Anglet",
    "sg:classifiers":[
        {
            "category":"Government",
            "subcategory":"Department Of Motor Vehicles",
            "type":"Public Place"
        }
    ],
    "sg:phone":"+33 5 59 42 52 32",
    "sg:postcode":"64600",
    "sg:province":"Aquitaine",
    "sg:tags":[
        "equipment",
        "industrial",
        "transport",
        "motor-cars"
    ],
    "wof:name":"Prieur Sarl Etablissements",
    "wof:placetype":"venue"
},
  "geometry": {"coordinates":[-1.514707,43.481705],"type":"Point"}
}