{
  "type": "Feature",
  "properties": {
    "iso:country":"FR",
    "sg:address":"B.P. 2029, 66011 Perpignan C\u00e9dex^^85, Rue Pascal Marie Agasse, 66000 Perpignan",
    "sg:orig_category":"Non-Classified Establishments",
    "sg:phone":"+33 4 68 85 65 00",
    "sg:postcode":"66000",
    "sg:province":"Languedoc-Roussillon",
    "wof:name":"Biscuiterie Confiserie Lor S.a.",
    "wof:placetype":"venue"
},
  "geometry": {"coordinates":[2.88743,42.69812],"type":"Point"}
}