{
  "type": "Feature",
  "properties": {
    "iso:country":"FR",
    "sg:address":"Bd des Pyr\u00e9n\u00e9es",
    "sg:city":"Mirande",
    "sg:orig_category":"Unclassifiable Establishments",
    "sg:phone":"+33 5 62 66 88 80",
    "sg:postcode":"32300",
    "sg:province":"Midi Pyr\u00e9n\u00e9es",
    "wof:name":"Les Silos Mirandais",
    "wof:placetype":"venue"
},
  "geometry": {"coordinates":[0.396043,43.507755],"type":"Point"}
}