{
  "type": "Feature",
  "properties": {
    "addr:full":"RN 23 - Le Point du Jour Saint Jean de la Motte Pays de Loire 72510",
    "addr:housenumber":"23",
    "addr:postcode":"72510",
    "addr:street":"Rn;Le Point;Saint;La Motte Pays",
    "iso:country":"FR",
    "sg:address":"RN 23 - Le Point du Jour",
    "sg:city":"Saint Jean de la Motte",
    "sg:orig_category":"Non-Classified Establishments",
    "sg:phone":"+33 2 43 45 71 05",
    "sg:postcode":"72510",
    "sg:province":"Pays de Loire",
    "wof:name":"Etablissement Girard S.a.r.l.",
    "wof:placetype":"venue"
},
  "geometry": {"coordinates":[0.01717,47.763721],"type":"Point"}
}