{
  "type": "Feature",
  "properties": {
    "addr:full":"Rue des Artisans Doubs Franche Comt\u00e9 25300",
    "addr:postcode":"25300",
    "addr:street":"Rue Des Artisans;Franche Comte\u0301",
    "iso:country":"FR",
    "sg:address":"Rue des Artisans",
    "sg:city":"Doubs",
    "sg:orig_category":"Unclassifiable Establishments",
    "sg:phone":"+33 3 81 46 43 67",
    "sg:postcode":"25300",
    "sg:province":"Franche Comt\u00e9",
    "wof:name":"Enett S.a.",
    "wof:placetype":"venue"
},
  "geometry": {"coordinates":[6.349997,46.933521],"type":"Point"}
}