{
  "type": "Feature",
  "properties": {
    "addr:full":"63, Rue Principale, 67140 Saint Pierre Andlau Alsace 67140",
    "addr:housenumber":"63",
    "addr:postcode":"67140;67140",
    "addr:street":"Rue Principale",
    "iso:country":"FR",
    "sg:address":"63, Rue Principale, 67140 Saint Pierre",
    "sg:city":"Andlau",
    "sg:orig_category":"Unclassifiable Establishments",
    "sg:phone":"+33 3 88 58 58 23",
    "sg:postcode":"67140",
    "sg:province":"Alsace",
    "wof:name":"Weber Alfred S.a.",
    "wof:placetype":"venue"
},
  "geometry": {"coordinates":[7.470024,48.381737],"type":"Point"}
}