{
  "type": "Feature",
  "properties": {
    "addr:full":"33, Rue Amp\u00e8re - ZI de Villemilan, 91320 Wissous Ile de France",
    "addr:housenumber":"33",
    "addr:postcode":"91320;ile",
    "addr:street":"Rue Ampe\u0300Re Zi De Villemilan",
    "iso:country":"FR",
    "sg:address":"33, Rue Amp\u00e8re - ZI de Villemilan, 91320 Wissous",
    "sg:orig_category":"Unclassifiable Establishments",
    "sg:phone":"+33 1 60 11 03 38",
    "sg:province":"Ile de France",
    "wof:name":"A.m.v. S.a.r.l. - Ateliers M\u00e9caniques De Vitry",
    "wof:placetype":"venue"
},
  "geometry": {"coordinates":[2.32612,48.731461],"type":"Point"}
}