{
  "type": "Feature",
  "properties": {
    "iso:country":"FR",
    "sg:address":"Rue Du Riez Z I",
    "sg:city":"Templeuve",
    "sg:classifiers":[
        {
            "category":"Banks & Credit Unions",
            "subcategory":"Financial Services",
            "type":"Services"
        }
    ],
    "sg:phone":"+33 3 20 64 65 40",
    "sg:postcode":"59242",
    "sg:province":"Nord Pas-de-Calais",
    "sg:tags":[
        "banking",
        "finance",
        "insurance"
    ],
    "wof:name":"Societe D'expertise Comptabilite Controle Conseil (e 3 C) E3c Templeuve",
    "wof:placetype":"venue"
},
  "geometry": {"coordinates":[3.169425,50.52676],"type":"Point"}
}