{
  "type": "Feature",
  "properties": {
    "addr:full":"62 Rue Oberlin 54000 Nancy Lorraine",
    "addr:housenumber":"62",
    "addr:postcode":"54000",
    "addr:street":"Rue Oberlin",
    "iso:country":"FR",
    "sg:address":"62 Rue Oberlin 54000 Nancy",
    "sg:classifiers":[
        {
            "category":"Banks & Credit Unions",
            "subcategory":"Bank",
            "type":"Services"
        }
    ],
    "sg:phone":"+33 3 83 35 51 63",
    "sg:province":"Lorraine",
    "sg:tags":[
        "sea",
        "transport",
        "road"
    ],
    "wof:name":"Tmf Operating (cositraf)",
    "wof:placetype":"venue"
},
  "geometry": {"coordinates":[6.183782,48.702583],"type":"Point"}
}