{
  "type": "Feature",
  "properties": {
    "addr:full":"254 Rue Francis De Pressenc\u00e9 69100 Villeurbanne Rhone-Alpes 69100",
    "addr:housenumber":"254",
    "addr:postcode":"69100;69100",
    "addr:street":"Rue Francis De Pressence\u0301",
    "iso:country":"FR",
    "sg:address":"254 Rue Francis De Pressenc\u00e9 69100 Villeurbanne",
    "sg:classifiers":[
        {
            "category":"Professional",
            "subcategory":"Engineering",
            "type":"Services"
        }
    ],
    "sg:phone":"+33 4 78 84 06 55",
    "sg:postcode":"69100",
    "sg:province":"Rhone-Alpes",
    "sg:tags":[
        "machine",
        "-",
        "mechanical"
    ],
    "wof:name":"Froid Et Machines Lyon Sa",
    "wof:placetype":"venue"
},
  "geometry": {"coordinates":[4.87905,45.769596],"type":"Point"}
}