{
  "type": "Feature",
  "properties": {
    "iso:country":"FR",
    "sg:address":"1 Rue De La Brasserie 67340 Ingwiller",
    "sg:city":"Ingwiller",
    "sg:classifiers":[
        {
            "category":"Food & Beverages",
            "subcategory":"Groceries & Convenience Stores",
            "type":"Retail Goods"
        }
    ],
    "sg:phone":"+33 3 88 89 45 47",
    "sg:postcode":"67340",
    "sg:province":"Alsace",
    "sg:tags":[
        "product",
        "related"
    ],
    "wof:name":"Les Epices D Ingwiller Sarl",
    "wof:placetype":"venue"
},
  "geometry": {"coordinates":[7.483897,48.867302],"type":"Point"}
}