{
  "type": "Feature",
  "properties": {
    "iso:country":"FR",
    "sg:address":"95 Boulevard Du General Leclerc",
    "sg:city":"Reims",
    "sg:classifiers":[
        {
            "category":"Banks & Credit Unions",
            "subcategory":"Financial Services",
            "type":"Services"
        }
    ],
    "sg:phone":"+33 3 26 47 52 75",
    "sg:postcode":"51100",
    "sg:province":"Champagne",
    "sg:tags":[
        "banking",
        "finance",
        "insurance"
    ],
    "wof:name":"Fidulor Societe D'expertise Comptable",
    "wof:placetype":"venue"
},
  "geometry": {"coordinates":[4.021592,49.252163],"type":"Point"}
}