{
  "type": "Feature",
  "properties": {
    "addr:full":"1 Rue Nic\u00e9phore Niepce 42100 St Etienne Rhone-Alpes 42100",
    "addr:housenumber":"1",
    "addr:postcode":"42100;42100",
    "addr:street":"Rue Nice\u0301Phore Niepce",
    "iso:country":"FR",
    "sg:address":"1 Rue Nic\u00e9phore Niepce 42100 St Etienne",
    "sg:classifiers":[
        {
            "category":"Government",
            "subcategory":"Department Of Motor Vehicles",
            "type":"Public Place"
        }
    ],
    "sg:phone":"+33 4 77 57 25 13",
    "sg:postcode":"42100",
    "sg:province":"Rhone-Alpes",
    "sg:tags":[
        "equipment",
        "industrial",
        "transport",
        "motor-cars"
    ],
    "wof:name":"Fournier Autocenter Sa",
    "wof:placetype":"venue"
},
  "geometry": {"coordinates":[4.404361,45.412941],"type":"Point"}
}