{
  "type": "Feature",
  "properties": {
    "iso:country":"FR",
    "sg:address":"13, Bd Anatole France, 93200 Saint Denis",
    "sg:orig_category":"Unclassifiable Establishments",
    "sg:phone":"+33 1 48 13 54 80",
    "sg:province":"Ile de France",
    "wof:name":"Info - Salons S.a.r.l.",
    "wof:placetype":"venue"
},
  "geometry": {"coordinates":[2.339302,48.917652],"type":"Point"}
}