{
  "type": "Feature",
  "properties": {
    "addr:full":"23, Rue de D\u00e9lizy, 93500 Pantin Ile de France",
    "addr:housenumber":"23",
    "addr:postcode":"93500;ile",
    "addr:street":"Rue De De\u0301Lizy",
    "iso:country":"FR",
    "sg:address":"23, Rue de D\u00e9lizy, 93500 Pantin",
    "sg:orig_category":"Non-Classified Establishments",
    "sg:phone":"+33 1 48 44 67 66",
    "sg:province":"Ile de France",
    "wof:name":"P.o.m. S.a.r.l.",
    "wof:placetype":"venue"
},
  "geometry": {"coordinates":[2.409567,48.895622],"type":"Point"}
}