{
  "type": "Feature",
  "properties": {
    "addr:full":"B.P. 122, 22300 Lannion C\u00e9dex^^25, Rue Ernest Renan, 22300 Lannion Lannion Bretagne 22300",
    "addr:housenumber":"b.p. 122",
    "addr:postcode":"22300;22300;22300",
    "addr:street":"Rue Ernest Renan",
    "iso:country":"FR",
    "sg:address":"B.P. 122, 22300 Lannion C\u00e9dex^^25, Rue Ernest Renan, 22300 Lannion",
    "sg:city":"Lannion",
    "sg:orig_category":"Non-Classified Establishments",
    "sg:phone":"+33 2 96 37 00 44",
    "sg:postcode":"22300",
    "sg:province":"Bretagne",
    "wof:name":"O.m.b. S.a.r.l. - Organisation Moderne De Bureau",
    "wof:placetype":"venue"
},
  "geometry": {"coordinates":[-3.508297,48.647575],"type":"Point"}
}