{
  "type": "Feature",
  "properties": {
    "addr:full":"1 rue Alexander Fl\u00e9ming 93360 Neuilly Plaisance Ile de France",
    "addr:housenumber":"1",
    "addr:postcode":"93360",
    "addr:street":"Rue Alexander Fle\u0301Ming;Ile De France",
    "iso:country":"FR",
    "sg:address":"1 rue Alexander Fl\u00e9ming 93360 Neuilly Plaisance",
    "sg:classifiers":[
        {
            "category":"Banks & Credit Unions",
            "subcategory":"Investment Brokerage",
            "type":"Services"
        }
    ],
    "sg:phone":"+33 1 41 54 12 12",
    "sg:province":"Ile de France",
    "sg:tags":[
        "textile",
        "machine"
    ],
    "wof:name":"Ste Textile Industrielle Sa",
    "wof:placetype":"venue"
},
  "geometry": {"coordinates":[2.516327,48.866169],"type":"Point"}
}