{
  "type": "Feature",
  "properties": {
    "iso:country":"FR",
    "sg:address":"87 boulevard de Courcelles 75008 Paris",
    "sg:classifiers":[
        {
            "category":"Food & Beverages",
            "subcategory":"Fruits & Vegetables",
            "type":"Retail Goods"
        }
    ],
    "sg:phone":"+33 1 46 22 21 35",
    "sg:postcode":"75008",
    "sg:province":"Ile de France",
    "sg:tags":[
        "sponge",
        "foam",
        "cellulose"
    ],
    "wof:name":"Cotonella Cie Interna Commerce Du Coton S.a.r.l.",
    "wof:placetype":"venue"
},
  "geometry": {"coordinates":[2.299477,48.87825],"type":"Point"}
}