{
  "type": "Feature",
  "properties": {
    "addr:full":"24 Rue De La Paix 75002 Paris Ile de France 75002",
    "addr:housenumber":"24",
    "addr:postcode":"75002;75002",
    "addr:street":"Rue De La Paix",
    "iso:country":"FR",
    "sg:address":"24 Rue De La Paix 75002 Paris",
    "sg:classifiers":[
        {
            "category":"Manufacturing",
            "subcategory":"Jewelry",
            "type":"Manufacturing & Wholesale Goods"
        }
    ],
    "sg:phone":"+33 1 42 65 62 43",
    "sg:postcode":"75002",
    "sg:province":"Ile de France",
    "sg:tags":[
        "product",
        "miscellaneous",
        "jewellery"
    ],
    "wof:name":"Pavillon Christofle",
    "wof:placetype":"venue"
},
  "geometry": {"coordinates":[2.332216,48.870029],"type":"Point"}
}