{
  "type": "Feature",
  "properties": {
    "addr:full":"26, Rue Lamartine, 76600 Le Havre Haute Normandie",
    "addr:housenumber":"26",
    "addr:postcode":"76600",
    "addr:street":"Rue Lamartine",
    "iso:country":"FR",
    "sg:address":"26, Rue Lamartine, 76600 Le Havre",
    "sg:orig_category":"Non-Classified Establishments",
    "sg:phone":"+33 2 32 92 52 00",
    "sg:province":"Haute Normandie",
    "wof:name":"Forlumen S.a.",
    "wof:placetype":"venue"
},
  "geometry": {"coordinates":[0.142787,49.492126],"type":"Point"}
}