{
  "type": "Feature",
  "properties": {
    "addr:full":"60, Rue Gaston Landry, 93700 Drancy Ile de France 93700",
    "addr:housenumber":"60",
    "addr:postcode":"93700;ile;93700",
    "addr:street":"Rue Gaston Landry;France",
    "iso:country":"FR",
    "sg:address":"60, Rue Gaston Landry, 93700 Drancy",
    "sg:orig_category":"Non-Classified Establishments",
    "sg:phone":"+33 1 48 95 40 26",
    "sg:postcode":"93700",
    "sg:province":"Ile de France",
    "wof:name":"B.e.c. S.a. - Bastin Et Compagnie",
    "wof:placetype":"venue"
},
  "geometry": {"coordinates":[2.45442,48.921635],"type":"Point"}
}