{
  "type": "Feature",
  "properties": {
    "addr:full":"9 Rue Buzelin 75018 Paris Ile de France 75018",
    "addr:housenumber":"9",
    "addr:postcode":"75018;75018",
    "addr:street":"Rue Buzelin",
    "iso:country":"FR",
    "sg:address":"9 Rue Buzelin 75018 Paris",
    "sg:classifiers":[
        {
            "category":"Shopping",
            "subcategory":"Clothing, Apparel, & Fashions",
            "type":"Retail Goods"
        }
    ],
    "sg:phone":"+33 1 46 07 04 16",
    "sg:postcode":"75018",
    "sg:province":"Ile de France",
    "sg:tags":[
        "textile",
        "clothing",
        "clothes"
    ],
    "wof:name":"Mode Thuy",
    "wof:placetype":"venue"
},
  "geometry": {"coordinates":[2.363727,48.890472],"type":"Point"}
}