{
  "type": "Feature",
  "properties": {
    "addr:full":"B.P. 67, 67702 Saverne C\u00e9dex^^Rte de Saessolsheim, 67700 Landersheim Saverne Alsace 67700",
    "addr:postcode":"67702;67700;67700",
    "addr:street":"B.P. 67",
    "iso:country":"FR",
    "sg:address":"B.P. 67, 67702 Saverne C\u00e9dex^^Rte de Saessolsheim, 67700 Landersheim",
    "sg:city":"Saverne",
    "sg:orig_category":"Non-Classified Establishments",
    "sg:phone":"+33 3 88 87 88 00",
    "sg:postcode":"67700",
    "sg:province":"Alsace",
    "wof:name":"Adidas Sarragan France S.a.r.l.",
    "wof:placetype":"venue"
},
  "geometry": {"coordinates":[7.366026,48.739471],"type":"Point"}
}