{
  "type": "Feature",
  "properties": {
    "iso:country":"FR",
    "sg:address":"39 Avenue Georges Pompidou 56800 Ploermel",
    "sg:city":"Plo\u00ebrmel",
    "sg:classifiers":[
        {
            "category":"Utilities",
            "subcategory":"Electric",
            "type":"Services"
        }
    ],
    "sg:phone":"+33 810 51 50 57",
    "sg:postcode":"56800",
    "sg:province":"Bretagne",
    "sg:tags":[
        "electricity",
        "raw",
        "energy",
        "material"
    ],
    "wof:name":"Electricite De France (edf)",
    "wof:placetype":"venue"
},
  "geometry": {"coordinates":[-2.38447,47.932201],"type":"Point"}
}