{
  "type": "Feature",
  "properties": {
    "addr:full":"44 Rue Du Havre 14015 Caen Cedex 1 Basse Normandie",
    "addr:housenumber":"44",
    "addr:postcode":"14015",
    "addr:street":"Rue Du Havre",
    "iso:country":"FR",
    "sg:address":"44 Rue Du Havre 14015 Caen Cedex 1",
    "sg:classifiers":[
        {
            "category":"Professional",
            "subcategory":"Printing & Photocopies",
            "type":"Services"
        }
    ],
    "sg:phone":"+33 2 31 86 03 32",
    "sg:province":"Basse Normandie",
    "sg:tags":[
        "publishing"
    ],
    "wof:name":"Editions De Basse-normandie",
    "wof:placetype":"venue"
},
  "geometry": {"coordinates":[-0.355616,49.180122],"type":"Point"}
}