{
  "type": "Feature",
  "properties": {
    "addr:full":"Rte de Compi\u00e8gne Montigny Lengrain Picardie 02290",
    "addr:housenumber":"montigny",
    "addr:postcode":"02290",
    "addr:street":"Rte De Compie\u0300Gne;Picardie",
    "iso:country":"FR",
    "sg:address":"Rte de Compi\u00e8gne",
    "sg:city":"Montigny Lengrain",
    "sg:orig_category":"Non-Classified Establishments",
    "sg:phone":"+33 3 23 55 50 23",
    "sg:postcode":"02290",
    "sg:province":"Picardie",
    "wof:name":"F\u00e9culerie Coop\u00e9rative Agricole",
    "wof:placetype":"venue"
},
  "geometry": {"coordinates":[3.10933,49.39587],"type":"Point"}
}