{
  "type": "Feature",
  "properties": {
    "addr:full":"Zi Village Entreprises 78270 Bonnieres Sur Seine Ile de France 78270",
    "addr:postcode":"78270;78270",
    "addr:street":"Zi Village Entreprises;France",
    "iso:country":"FR",
    "sg:address":"Zi Village Entreprises 78270 Bonnieres Sur Seine",
    "sg:classifiers":[
        {
            "category":"Shopping",
            "subcategory":"Computers & Home Electronics",
            "type":"Retail Goods"
        }
    ],
    "sg:phone":"+33 1 30 98 98 40",
    "sg:postcode":"78270",
    "sg:province":"Ile de France",
    "sg:tags":[
        "electronic",
        "electrical",
        "equipment"
    ],
    "wof:name":"Sintech France",
    "wof:placetype":"venue"
},
  "geometry": {"coordinates":[1.579122,49.037071],"type":"Point"}
}