{
  "type": "Feature",
  "properties": {
    "iso:country":"FR",
    "sg:address":"19230 Arnac Pompadour",
    "sg:classifiers":[
        {
            "category":"Utilities",
            "subcategory":"Electric",
            "type":"Services"
        }
    ],
    "sg:phone":"+33 5 55 73 89 20",
    "sg:postcode":"19230",
    "sg:province":"Limousin",
    "sg:tags":[
        "electricity",
        "electronic",
        "electrical",
        "equipment"
    ],
    "wof:name":"Cegers Outillage",
    "wof:placetype":"venue"
},
  "geometry": {"coordinates":[1.37104,45.38995],"type":"Point"}
}