{
  "type": "Feature",
  "properties": {
    "addr:full":"Route de N\u00e9rac 47230 LAVARDAC Lavardac Aquitaine 47230",
    "addr:postcode":"47230;47230",
    "addr:street":"Route De Ne\u0301Rac",
    "iso:country":"FR",
    "sg:address":"Route de N\u00e9rac 47230 LAVARDAC",
    "sg:city":"Lavardac",
    "sg:classifiers":[
        {
            "category":"Recreation",
            "subcategory":"Fishing",
            "type":"Entertainment"
        }
    ],
    "sg:phone":"+33 5 53 65 50 12",
    "sg:postcode":"47230",
    "sg:province":"Aquitaine",
    "sg:tags":[
        "float"
    ],
    "wof:name":"Cruz Robert Sarl",
    "wof:placetype":"venue"
},
  "geometry": {"coordinates":[0.301085,44.166965],"type":"Point"}
}