{
  "type": "Feature",
  "properties": {
    "addr:full":"Technoparc Futura 62400 Bethune Nord Pas-de-Calais",
    "addr:postcode":"62400",
    "addr:street":"Bethune Nord",
    "iso:country":"FR",
    "sg:address":"Technoparc Futura 62400 Bethune",
    "sg:classifiers":[
        {
            "category":"Manufacturing",
            "subcategory":"Printing",
            "type":"Manufacturing & Wholesale Goods"
        }
    ],
    "sg:phone":"+33 3 21 01 65 65",
    "sg:province":"Nord Pas-de-Calais",
    "sg:tags":[
        "publishing"
    ],
    "wof:name":"Sigma",
    "wof:placetype":"venue"
},
  "geometry": {"coordinates":[2.63787,50.530472],"type":"Point"}
}