{
  "type": "Feature",
  "properties": {
    "addr:full":"La Lande 49170 Saint Martin du Fouilloux Pays de Loire",
    "addr:postcode":"49170",
    "addr:street":"Lande;Fouilloux",
    "iso:country":"FR",
    "sg:address":"La Lande 49170 Saint Martin du Fouilloux",
    "sg:orig_category":"Non-Classified Establishments",
    "sg:phone":"+33 2 41 39 50 82",
    "sg:province":"Pays de Loire",
    "wof:name":"Transports Cadeau Hubert S.a.",
    "wof:placetype":"venue"
},
  "geometry": {"coordinates":[-0.645864,47.405823],"type":"Point"}
}