{
  "type": "Feature",
  "properties": {
    "addr:full":"10 rue La Fayette 67100 Strasbourg Strasbourg Alsace 67100",
    "addr:housenumber":"10",
    "addr:postcode":"67100;67100",
    "addr:street":"Rue La Fayette",
    "iso:country":"FR",
    "sg:address":"10 rue La Fayette 67100 Strasbourg",
    "sg:city":"Strasbourg",
    "sg:classifiers":[
        {
            "category":"Structure",
            "subcategory":"Tower",
            "type":"Public Place"
        }
    ],
    "sg:phone":"+33 3 88 39 18 49",
    "sg:postcode":"67100",
    "sg:province":"Alsace",
    "sg:tags":[
        "steel",
        "structural"
    ],
    "wof:name":"Comptoir Des Aciers Gunther S.a.",
    "wof:placetype":"venue"
},
  "geometry": {"coordinates":[7.743856,48.561775],"type":"Point"}
}