{
  "type": "Feature",
  "properties": {
    "iso:country":"FR",
    "sg:address":"18 Rue Desseaux 76100 Rouen",
    "sg:classifiers":[
        {
            "category":"Professional",
            "subcategory":"Engineering",
            "type":"Services"
        }
    ],
    "sg:phone":"+33 2 35 72 79 98",
    "sg:postcode":"76100",
    "sg:province":"Haute Normandie",
    "sg:tags":[
        "machine",
        "-",
        "mechanical"
    ],
    "wof:name":"La Bovida",
    "wof:placetype":"venue"
},
  "geometry": {"coordinates":[1.094322,49.430218],"type":"Point"}
}