{
  "type": "Feature",
  "properties": {
    "addr:full":"11, Rue de Pavre, 25510 Pierrefontaine les Varans Franche Comt\u00e9",
    "addr:housenumber":"11",
    "addr:postcode":"25510",
    "addr:street":"Rue De Pavre;Franche Comte\u0301",
    "iso:country":"FR",
    "sg:address":"11, Rue de Pavre, 25510 Pierrefontaine les Varans",
    "sg:orig_category":"Unclassifiable Establishments",
    "sg:phone":"+33 3 81 56 05 65",
    "sg:province":"Franche Comt\u00e9",
    "wof:name":"Rota S.a.",
    "wof:placetype":"venue"
},
  "geometry": {"coordinates":[6.540655,47.220627],"type":"Point"}
}