{
  "type": "Feature",
  "properties": {
    "iso:country":"FR",
    "sg:address":"211/213, Av. Maurice Berthaud, 78500 Sartrouville",
    "sg:orig_category":"Non-Classified Establishments",
    "sg:phone":"+33 1 39 58 68 80",
    "sg:province":"Ile de France",
    "wof:name":"M.c.h. S.a.r.l. - Marbre Carrelages Pour L'habitat",
    "wof:placetype":"venue"
},
  "geometry": {"coordinates":[2.175728,48.935806],"type":"Point"}
}