{
  "type": "Feature",
  "properties": {
    "addr:full":"B.P. 2271, 27950 Saint Marcel^^6, Rue de la Garenne, 27950 Saint Marcel Haute Normandie",
    "addr:housenumber":"2271",
    "addr:postcode":"27950;27950",
    "addr:street":"B.P.;Rue De La Garenne;Marcel Haute Normandie",
    "iso:country":"FR",
    "sg:address":"B.P. 2271, 27950 Saint Marcel^^6, Rue de la Garenne, 27950 Saint Marcel",
    "sg:orig_category":"Non-Classified Establishments",
    "sg:phone":"+33 2 32 21 11 99",
    "sg:province":"Haute Normandie",
    "wof:name":"Presta M\u00e9tal S.a.r.l.",
    "wof:placetype":"venue"
},
  "geometry": {"coordinates":[1.455387,49.102932],"type":"Point"}
}