{
  "type": "Feature",
  "properties": {
    "addr:full":"Beaubutaines 58200 Cosne Cours Sur Loire Cosne-Cours-sur-Loire Bourgogne 58200",
    "addr:postcode":"58200;58200",
    "addr:street":"Beaubutaines",
    "iso:country":"FR",
    "sg:address":"Beaubutaines 58200 Cosne Cours Sur Loire",
    "sg:city":"Cosne-Cours-sur-Loire",
    "sg:classifiers":[
        {
            "category":"Banks & Credit Unions",
            "subcategory":"Investment Brokerage",
            "type":"Services"
        }
    ],
    "sg:phone":"+33 3 86 28 24 34",
    "sg:postcode":"58200",
    "sg:province":"Bourgogne",
    "sg:tags":[
        "-",
        "transport",
        "related"
    ],
    "wof:name":"Cosne Transports",
    "wof:placetype":"venue"
},
  "geometry": {"coordinates":[2.92471,47.385506],"type":"Point"}
}