{
  "type": "Feature",
  "properties": {
    "iso:country":"FR",
    "sg:address":"49-55 R Du Lieutenant Thomas 93170 Bagnolet",
    "sg:classifiers":[
        {
            "category":"Manufacturing",
            "subcategory":"Textiles",
            "type":"Manufacturing & Wholesale Goods"
        }
    ],
    "sg:phone":"+33 1 48 57 63 33",
    "sg:postcode":"93170",
    "sg:province":"Ile de France",
    "sg:tags":[
        "printing",
        "clothing",
        "fabric"
    ],
    "wof:name":"Symbole Textile Europeen",
    "wof:placetype":"venue"
},
  "geometry": {"coordinates":[2.416847,48.858681],"type":"Point"}
}