{
  "type": "Feature",
  "properties": {
    "iso:country":"FR",
    "sg:address":"ZI de la Fert\u00e9",
    "sg:city":"Varades",
    "sg:orig_category":"Unclassifiable Establishments",
    "sg:phone":"+33 2 40 09 70 09",
    "sg:postcode":"44370",
    "sg:province":"Pays de Loire",
    "wof:name":"Atlantique Industrie E.u.r.l.",
    "wof:placetype":"venue"
},
  "geometry": {"coordinates":[-1.030304,47.384911],"type":"Point"}
}