{
  "type": "Feature",
  "properties": {
    "iso:country":"FR",
    "sg:address":"Le Bois Des Roches",
    "sg:city":"D\u00e9partemental 36 78114 Magny Les Hameaux",
    "sg:classifiers":[
        {
            "category":"Government",
            "subcategory":"Department Of Motor Vehicles",
            "type":"Public Place"
        }
    ],
    "sg:phone":"+33 1 39 56 33 40",
    "sg:postcode":"78114",
    "sg:province":"Ile de France",
    "sg:tags":[
        "equipment",
        "industrial",
        "transport",
        "motor-cars"
    ],
    "wof:name":"Depann Service 78 Sarl",
    "wof:placetype":"venue"
},
  "geometry": {"coordinates":[2.103455,48.71944],"type":"Point"}
}