{
  "type": "Feature",
  "properties": {
    "iso:country":"FR",
    "sg:address":"52, Rue du Rendez-Vous, 75012 Paris",
    "sg:orig_category":"Unclassifiable Establishments",
    "sg:phone":"+33 1 43 45 47 47",
    "sg:province":"Ile de France",
    "wof:name":"Quasar S.a.r.l.",
    "wof:placetype":"venue"
},
  "geometry": {"coordinates":[2.401887,48.846416],"type":"Point"}
}