{
  "type": "Feature",
  "properties": {
    "addr:full":"Rue Du Champs De Mars 55840 Thierville Sur Meuse Lorraine",
    "addr:postcode":"55840",
    "addr:street":"Rue Du Champs De Mars;Meuse",
    "iso:country":"FR",
    "sg:address":"Rue Du Champs De Mars 55840 Thierville Sur Meuse",
    "sg:classifiers":[
        {
            "category":"Professional",
            "type":"Services"
        }
    ],
    "sg:phone":"+33 3 29 86 44 52",
    "sg:province":"Lorraine",
    "sg:tags":[
        "transport",
        "road"
    ],
    "wof:name":"Sotrago",
    "wof:placetype":"venue"
},
  "geometry": {"coordinates":[5.37426,49.167294],"type":"Point"}
}