{
  "type": "Feature",
  "properties": {
    "addr:full":"Cote de la Dr\u00e8che Lescure d'Albigeois Midi Pyr\u00e9n\u00e9es 81380",
    "addr:postcode":"81380",
    "addr:street":"Cote De La Dre\u0300Che Lescure;Midi",
    "iso:country":"FR",
    "sg:address":"Cote de la Dr\u00e8che",
    "sg:city":"Lescure d'Albigeois",
    "sg:orig_category":"Unclassifiable Establishments",
    "sg:phone":"+33 5 63 53 90 55",
    "sg:postcode":"81380",
    "sg:province":"Midi Pyr\u00e9n\u00e9es",
    "wof:name":"A.p.m.p.s. S.a.r.l. - Agence Priv\u00e9e Midi-pyr\u00e9n\u00e9es De Surveillance",
    "wof:placetype":"venue"
},
  "geometry": {"coordinates":[2.153742,43.951042],"type":"Point"}
}