{
  "type": "Feature",
  "properties": {
    "iso:country":"FR",
    "sg:address":"5 Rue Planchette 77120 Beautheil",
    "sg:classifiers":[
        {
            "category":"Manufacturing",
            "subcategory":"Metals",
            "type":"Manufacturing & Wholesale Goods"
        }
    ],
    "sg:phone":"+33 1 64 03 19 23",
    "sg:postcode":"77120",
    "sg:province":"Ile de France",
    "sg:tags":[
        "metallurgy",
        "steel",
        "metalworking"
    ],
    "wof:name":"Etablissements Brangea Sarl",
    "wof:placetype":"venue"
},
  "geometry": {"coordinates":[3.086509,48.763615],"type":"Point"}
}