{
  "type": "Feature",
  "properties": {
    "iso:country":"FR",
    "sg:address":"Villa de la Grange 63330 Pionsat",
    "sg:city":"Pionsat",
    "sg:orig_category":"Non-Classified Establishments",
    "sg:phone":"+33 4 73 85 66 95",
    "sg:postcode":"63330",
    "sg:province":"Auvergne",
    "wof:name":"Newsmith France S.a.",
    "wof:placetype":"venue"
},
  "geometry": {"coordinates":[2.687897,46.109341],"type":"Point"}
}