{
  "type": "Feature",
  "properties": {
    "addr:full":"Rte de Plascassier - Quartier Saint Joseph Grasse Provence-Alpes-C\u00f4te d'Azur 06130",
    "addr:postcode":"06130",
    "addr:street":"Rte De Plascassier",
    "iso:country":"FR",
    "sg:address":"Rte de Plascassier - Quartier Saint Joseph",
    "sg:city":"Grasse",
    "sg:orig_category":"Non-Classified Establishments",
    "sg:phone":"+33 4 93 09 16 00",
    "sg:postcode":"06130",
    "sg:province":"Provence-Alpes-C\u00f4te d'Azur",
    "wof:name":"P\u00e9raline S.a.",
    "wof:placetype":"venue"
},
  "geometry": {"coordinates":[6.931647,43.649738],"type":"Point"}
}