{
  "type": "Feature",
  "properties": {
    "iso:country":"FR",
    "sg:address":"Rte De Gargas Zi BP 16 84400 Apt",
    "sg:classifiers":[
        {
            "category":"Food & Beverages",
            "subcategory":"Fruits & Vegetables",
            "type":"Retail Goods"
        }
    ],
    "sg:phone":"+33 4 90 74 15 30",
    "sg:province":"Midi Pyr\u00e9n\u00e9es",
    "sg:tags":[
        "preserve",
        "product",
        "related"
    ],
    "wof:name":"Marliagues Leopold Sa",
    "wof:placetype":"venue"
},
  "geometry": {"coordinates":[5.403555,43.828659],"type":"Point"}
}