{
  "type": "Feature",
  "properties": {
    "addr:full":"Rue Alessandro Volta 33700 M\u00e9rignac M\u00e9rignac Aquitaine 33700",
    "addr:postcode":"33700;33700",
    "addr:street":"Rue Alessandro Volta",
    "iso:country":"FR",
    "sg:address":"Rue Alessandro Volta 33700 M\u00e9rignac",
    "sg:city":"M\u00e9rignac",
    "sg:classifiers":[
        {
            "category":"Shopping",
            "subcategory":"Computers & Home Electronics",
            "type":"Retail Goods"
        }
    ],
    "sg:phone":"+33 5 56 34 32 25",
    "sg:postcode":"33700",
    "sg:province":"Aquitaine",
    "sg:tags":[
        "electric",
        "electricity",
        "component",
        "equipment",
        "electrical",
        "electronic"
    ],
    "wof:name":"Dervaux Distribution Agmt",
    "wof:placetype":"venue"
},
  "geometry": {"coordinates":[-0.676154,44.853756],"type":"Point"}
}