{
  "type": "Feature",
  "properties": {
    "addr:full":"Rte de Ravenoville - Les Petites Pi\u00e8ces du Fresnes Ravenoville Basse Normandie 50480",
    "addr:postcode":"50480",
    "addr:street":"Rte De Ravenoville Les Petites Pie\u0300Ces Du Fresnes",
    "iso:country":"FR",
    "sg:address":"Rte de Ravenoville - Les Petites Pi\u00e8ces du Fresnes",
    "sg:city":"Ravenoville",
    "sg:orig_category":"Unclassifiable Establishments",
    "sg:phone":"+33 2 33 41 44 59",
    "sg:postcode":"50480",
    "sg:province":"Basse Normandie",
    "wof:name":"P.r.e.m.a.c.o. S.a. - Pr\u00e9fabrication De Mat\u00e9riaux Du Cotentin",
    "wof:placetype":"venue"
},
  "geometry": {"coordinates":[-1.254904,49.35006],"type":"Point"}
}