{
  "type": "Feature",
  "properties": {
    "addr:full":"Chemin De Caylus 34170 Castelnau Le Lez Languedoc-Roussillon 34170",
    "addr:postcode":"34170;34170",
    "addr:street":"Chemin De Caylus",
    "iso:country":"FR",
    "sg:address":"Chemin De Caylus 34170 Castelnau Le Lez",
    "sg:classifiers":[
        {
            "category":"Building & Trades",
            "subcategory":"Construction",
            "type":"Services"
        }
    ],
    "sg:phone":"+33 4 67 79 55 00",
    "sg:postcode":"34170",
    "sg:province":"Languedoc-Roussillon",
    "sg:tags":[
        "work",
        "public"
    ],
    "wof:name":"Tp Sud Sarl",
    "wof:placetype":"venue"
},
  "geometry": {"coordinates":[3.903842,43.647842],"type":"Point"}
}