{
  "type": "Feature",
  "properties": {
    "iso:country":"FR",
    "sg:address":"57 Av De Cond\u00e9 94100 St Maur Des Fosses",
    "sg:classifiers":[
        {
            "category":"Health Services",
            "subcategory":"Optometrist",
            "type":"Services"
        }
    ],
    "sg:phone":"+33 1 55 96 46 00",
    "sg:postcode":"94100",
    "sg:province":"Ile de France",
    "sg:tags":[
        "instrument",
        "optical",
        "-",
        "precision",
        "equipment"
    ],
    "wof:name":"Essilor International",
    "wof:placetype":"venue"
},
  "geometry": {"coordinates":[2.481787,48.810226],"type":"Point"}
}