{
  "type": "Feature",
  "properties": {
    "addr:full":"27 Rue Maurice Flandin Forum Part Dieu Lyon Cedex 03 Rhone-Alpes 69003",
    "addr:housenumber":"27",
    "addr:postcode":"03;69003",
    "addr:street":"Rue Maurice Flandin;Dieu;Rhone-Alpes",
    "iso:country":"FR",
    "sg:address":"27 Rue Maurice Flandin Forum Part Dieu",
    "sg:city":"Lyon Cedex 03",
    "sg:classifiers":[
        {
            "category":"Banks & Credit Unions",
            "subcategory":"Financial Services",
            "type":"Services"
        }
    ],
    "sg:phone":"+33 4 72 68 84 84",
    "sg:postcode":"69003",
    "sg:province":"Rhone-Alpes",
    "sg:tags":[
        "banking",
        "finance",
        "insurance"
    ],
    "wof:name":"La Mondiale",
    "wof:placetype":"venue"
},
  "geometry": {"coordinates":[4.84978,45.760479],"type":"Point"}
}