{
  "type": "Feature",
  "properties": {
    "iso:country":"FR",
    "sg:address":"16, Rue Jean Jacques Rousseau, 75001 Paris",
    "sg:orig_category":"Unclassifiable Establishments",
    "sg:phone":"+33 1 42 33 32 12",
    "sg:province":"Ile de France",
    "wof:name":"P.b.o. S.a.r.l. - Pour Bien Organiser",
    "wof:placetype":"venue"
},
  "geometry": {"coordinates":[2.340584,48.862476],"type":"Point"}
}