{
  "type": "Feature",
  "properties": {
    "addr:full":"Rue Emmanuel L\u00e9ger - ZI Patay Centre 45310",
    "addr:postcode":"45310",
    "addr:street":"Rue Emmanuel Le\u0301Ger Zi Patay",
    "iso:country":"FR",
    "sg:address":"Rue Emmanuel L\u00e9ger - ZI",
    "sg:city":"Patay",
    "sg:orig_category":"Non-Classified Establishments",
    "sg:phone":"+33 2 38 78 75 00",
    "sg:postcode":"45310",
    "sg:province":"Centre",
    "wof:name":"Elips Enseignes S.a.",
    "wof:placetype":"venue"
},
  "geometry": {"coordinates":[1.69568,48.048164],"type":"Point"}
}