{
  "type": "Feature",
  "properties": {
    "addr:full":"12, Av. Henri Barbusse, 92700 Colombes Ile de France",
    "addr:postcode":"92700;ile",
    "addr:street":"12 Av. Henri Barbusse",
    "iso:country":"FR",
    "sg:address":"12, Av. Henri Barbusse, 92700 Colombes",
    "sg:orig_category":"Unclassifiable Establishments",
    "sg:phone":"+33 1 47 80 71 05",
    "sg:province":"Ile de France",
    "wof:name":"Adia France S.a.",
    "wof:placetype":"venue"
},
  "geometry": {"coordinates":[2.252419,48.921543],"type":"Point"}
}