{
  "type": "Feature",
  "properties": {
    "addr:full":"Place Du Monument 38460 Cremieu Rhone-Alpes 38460",
    "addr:postcode":"38460;38460",
    "addr:street":"Place Du Monument;Rhone-Alpes",
    "iso:country":"FR",
    "sg:address":"Place Du Monument 38460 Cremieu",
    "sg:classifiers":[
        {
            "category":"Park",
            "type":"Public Place"
        }
    ],
    "sg:phone":"+33 4 74 90 06 54",
    "sg:postcode":"38460",
    "sg:province":"Rhone-Alpes",
    "sg:tags":[
        "work",
        "construction",
        "sport"
    ],
    "wof:name":"Isere Technic Industry It Industry",
    "wof:placetype":"venue"
},
  "geometry": {"coordinates":[5.27697,45.658482],"type":"Point"}
}