{
  "type": "Feature",
  "properties": {
    "addr:full":"22 Rue Croix St Jean 33890 Gensac Gensac Aquitaine 33890",
    "addr:housenumber":"22",
    "addr:postcode":"33890;33890",
    "addr:street":"Rue Croix St Jean",
    "iso:country":"FR",
    "sg:address":"22 Rue Croix St Jean 33890 Gensac",
    "sg:city":"Gensac",
    "sg:classifiers":[
        {
            "category":"Manufacturing",
            "subcategory":"Leather Goods",
            "type":"Manufacturing & Wholesale Goods"
        }
    ],
    "sg:phone":"+33 5 57 56 01 10",
    "sg:postcode":"33890",
    "sg:province":"Aquitaine",
    "sg:tags":[
        "shoe"
    ],
    "wof:name":"Delvaux France Sa",
    "wof:placetype":"venue"
},
  "geometry": {"coordinates":[0.073601,44.804993],"type":"Point"}
}