{
  "type": "Feature",
  "properties": {
    "iso:country":"FR",
    "sg:address":"5 Avenue Albert Durand 31700 Blagnac",
    "sg:classifiers":[
        {
            "category":"Professional",
            "subcategory":"Computer Services",
            "type":"Services"
        }
    ],
    "sg:phone":"+33 5 61 16 40 40",
    "sg:postcode":"31700",
    "sg:province":"Midi Pyr\u00e9n\u00e9es",
    "sg:tags":[
        "information",
        "technology",
        "software"
    ],
    "wof:name":"Unilog It Services",
    "wof:placetype":"venue"
},
  "geometry": {"coordinates":[1.376055,43.635399],"type":"Point"}
}