{
  "type": "Feature",
  "properties": {
    "iso:country":"FR",
    "sg:address":"6, All\u00e9e des P\u00e9ni\u00e8res, 85670 Falleron",
    "sg:orig_category":"Unclassifiable Establishments",
    "sg:phone":"+33 2 51 93 24 89",
    "sg:province":"Pays de Loire",
    "wof:name":"O.p.a. S.a.s. - Ouest Produits Alimentaires",
    "wof:placetype":"venue"
},
  "geometry": {"coordinates":[-1.6963,46.883408],"type":"Point"}
}