{
  "type": "Feature",
  "properties": {
    "addr:full":"Rue Octave Portal 12500 Espalion Midi Pyr\u00e9n\u00e9es 12500",
    "addr:postcode":"12500;12500",
    "addr:street":"Rue Octave Portal",
    "iso:country":"FR",
    "sg:address":"Rue Octave Portal 12500 Espalion",
    "sg:classifiers":[
        {
            "category":"Professional",
            "subcategory":"Business Services",
            "type":"Services"
        }
    ],
    "sg:phone":"+33 5 65 44 02 17",
    "sg:postcode":"12500",
    "sg:province":"Midi Pyr\u00e9n\u00e9es",
    "sg:tags":[
        "training",
        "advice"
    ],
    "wof:name":"College Louis Denayrouze",
    "wof:placetype":"venue"
},
  "geometry": {"coordinates":[2.759911,44.525105],"type":"Point"}
}