{
  "type": "Feature",
  "properties": {
    "addr:full":"384 rue de Vaugirard 75015 Paris Ile de France 75015",
    "addr:housenumber":"384",
    "addr:postcode":"75015;75015",
    "addr:street":"Rue De Vaugirard",
    "iso:country":"FR",
    "sg:address":"384 rue de Vaugirard 75015 Paris",
    "sg:classifiers":[
        {
            "category":"Professional",
            "subcategory":"Business Services",
            "type":"Services"
        }
    ],
    "sg:phone":"+33 1 53 68 95 95",
    "sg:postcode":"75015",
    "sg:province":"Ile de France",
    "sg:tags":[
        "industrial",
        "export"
    ],
    "wof:name":"St\u00e9 D' Exportation De Produits Agricoles Sa",
    "wof:placetype":"venue"
},
  "geometry": {"coordinates":[2.288495,48.832981],"type":"Point"}
}