{
  "type": "Feature",
  "properties": {
    "addr:full":"B.P. 199, 26702 Pierrelatte C\u00e9dex^^ZI les Malalonnes, 26700 Pierrelatte Rhone-Alpes 26700",
    "addr:housenumber":"b.p. 199",
    "addr:postcode":"26702;26700;26700",
    "iso:country":"FR",
    "sg:address":"B.P. 199, 26702 Pierrelatte C\u00e9dex^^ZI les Malalonnes, 26700 Pierrelatte",
    "sg:orig_category":"Non-Classified Establishments",
    "sg:phone":"+33 4 75 96 51 00",
    "sg:postcode":"26700",
    "sg:province":"Rhone-Alpes",
    "wof:name":"Salvarem S.a.",
    "wof:placetype":"venue"
},
  "geometry": {"coordinates":[4.69703,44.375584],"type":"Point"}
}