{
  "type": "Feature",
  "properties": {
    "addr:full":"26, Bd Gay Lussac, 13014 Marseille Poitou-Charentes",
    "addr:housenumber":"26",
    "addr:postcode":"13014",
    "addr:street":"Bd Gay Lussac",
    "iso:country":"FR",
    "sg:address":"26, Bd Gay Lussac, 13014 Marseille",
    "sg:orig_category":"Non-Classified Establishments",
    "sg:phone":"+33 4 91 98 37 82",
    "sg:province":"Poitou-Charentes",
    "wof:name":"Algro S.a.r.l.",
    "wof:placetype":"venue"
},
  "geometry": {"coordinates":[5.374778,43.334049],"type":"Point"}
}