{
  "type": "Feature",
  "properties": {
    "addr:full":"190 Rue De Rivoli 75001 Paris Ile de France 75001",
    "addr:housenumber":"190",
    "addr:postcode":"75001;75001",
    "addr:street":"Rue De Rivoli",
    "iso:country":"FR",
    "sg:address":"190 Rue De Rivoli 75001 Paris",
    "sg:classifiers":[
        {
            "category":"Manufacturing",
            "subcategory":"Tools & Machinery",
            "type":"Manufacturing & Wholesale Goods"
        }
    ],
    "sg:phone":"+33 1 42 61 51 53",
    "sg:postcode":"75001",
    "sg:province":"Ile de France",
    "sg:tags":[
        "metallurgy",
        "metalworking"
    ],
    "wof:name":"Fontaine Deny Sa",
    "wof:placetype":"venue"
},
  "geometry": {"coordinates":[2.332951,48.863613],"type":"Point"}
}