{
  "type": "Feature",
  "properties": {
    "iso:country":"FR",
    "sg:address":"22 Avenue Division Leclerc 93000 Bobigny",
    "sg:classifiers":[
        {
            "category":"Manufacturing",
            "subcategory":"Paper Products",
            "type":"Manufacturing & Wholesale Goods"
        }
    ],
    "sg:phone":"+33 1 48 95 89 19",
    "sg:province":"Ile de France",
    "sg:tags":[
        "packaging",
        "material",
        "-",
        "cardboard"
    ],
    "wof:name":"Sa Sedic Vitrafix",
    "wof:placetype":"venue"
},
  "geometry": {"coordinates":[2.423365,48.907597],"type":"Point"}
}