{
  "type": "Feature",
  "properties": {
    "addr:full":"6, Rue Ren\u00e9 Cassin, 95220 Herblay Ile de France",
    "addr:housenumber":"6",
    "addr:postcode":"95220;ile",
    "addr:street":"Rue Rene\u0301 Cassin",
    "iso:country":"FR",
    "sg:address":"6, Rue Ren\u00e9 Cassin, 95220 Herblay",
    "sg:orig_category":"Unclassifiable Establishments",
    "sg:phone":"+33 1 39 97 60 44",
    "sg:province":"Ile de France",
    "wof:name":"Caf\u00e9 Suavor",
    "wof:placetype":"venue"
},
  "geometry": {"coordinates":[2.184023,48.997936],"type":"Point"}
}