{
  "type": "Feature",
  "properties": {
    "addr:full":"385, Av. Eug\u00e8ne Milon, 45470 Loury Loury Centre 45470",
    "addr:housenumber":"385;loury",
    "addr:postcode":"45470;45470",
    "addr:street":"Av. Euge\u0300Ne Milon",
    "iso:country":"FR",
    "sg:address":"385, Av. Eug\u00e8ne Milon, 45470 Loury",
    "sg:city":"Loury",
    "sg:orig_category":"Unclassifiable Establishments",
    "sg:phone":"+33 2 38 65 60 29",
    "sg:postcode":"45470",
    "sg:province":"Centre",
    "wof:name":"Etablissements Pillette Et Fils S.a.",
    "wof:placetype":"venue"
},
  "geometry": {"coordinates":[2.090335,47.999298],"type":"Point"}
}