{
  "type": "Feature",
  "properties": {
    "iso:country":"FR",
    "sg:address":"13, Rue Lavoisier - ZI, 45140 Ingr\u00e9",
    "sg:city":"Ingr\u00e9",
    "sg:orig_category":"Unclassifiable Establishments",
    "sg:phone":"+33 2 38 22 33 77",
    "sg:postcode":"45140",
    "sg:province":"Centre",
    "wof:name":"C.o.m.e.t. S.a.s. - Compagnie Orl\u00e9anaise De Mat\u00e9riel Electrique Et Thermique",
    "wof:placetype":"venue"
},
  "geometry": {"coordinates":[1.8745,47.912949],"type":"Point"}
}