{
  "type": "Feature",
  "properties": {
    "iso:country":"FR",
    "sg:address":"46 Rue Blanche Monier",
    "sg:city":"Grenoble",
    "sg:classifiers":[
        {
            "category":"Banks & Credit Unions",
            "subcategory":"Financial Services",
            "type":"Services"
        }
    ],
    "sg:phone":"+33 4 76 60 36 36",
    "sg:postcode":"38000",
    "sg:province":"Rhone-Alpes",
    "sg:tags":[
        "banking",
        "finance",
        "insurance"
    ],
    "wof:name":"Assedic De Grenoble",
    "wof:placetype":"venue"
},
  "geometry": {"coordinates":[5.737306,45.196484],"type":"Point"}
}