{
  "type": "Feature",
  "properties": {
    "addr:full":"26, Rue Henri Poincar\u00e9, 70000 Vesoul Franche Comt\u00e9",
    "addr:housenumber":"26",
    "addr:postcode":"70000",
    "addr:street":"Rue Henri Poincare\u0301;Franche Comte\u0301",
    "iso:country":"FR",
    "sg:address":"26, Rue Henri Poincar\u00e9, 70000 Vesoul",
    "sg:orig_category":"Unclassifiable Establishments",
    "sg:phone":"+33 3 84 75 96 00",
    "sg:province":"Franche Comt\u00e9",
    "wof:name":"Pagot Caput S.a.",
    "wof:placetype":"venue"
},
  "geometry": {"coordinates":[6.167409,47.617142],"type":"Point"}
}