{
  "type": "Feature",
  "properties": {
    "iso:country":"FR",
    "sg:address":"18 rue du Roi de Sicile 75004 Paris",
    "sg:classifiers":[
        {
            "category":"Professional",
            "subcategory":"Testing Lab",
            "type":"Services"
        }
    ],
    "sg:phone":"+33 1 42 71 65 10",
    "sg:province":"Ile de France",
    "sg:tags":[
        "large",
        "laboratory",
        "laboratories",
        "photographic"
    ],
    "wof:name":"Ste Publimod Photo S.a.",
    "wof:placetype":"venue"
},
  "geometry": {"coordinates":[2.359538,48.856045],"type":"Point"}
}