{
  "type": "Feature",
  "properties": {
    "iso:country":"FR",
    "sg:address":"Rue de Br\u00e8me",
    "sg:city":"Brest",
    "sg:orig_category":"Unclassifiable Establishments",
    "sg:phone":"+33 2 48 46 18 66",
    "sg:postcode":"29200",
    "sg:province":"Bretagne",
    "wof:name":"Atlantique Transports Rousseau S.a.r.l.",
    "wof:placetype":"venue"
},
  "geometry": {"coordinates":[-4.47432,48.383446],"type":"Point"}
}