{
  "type": "Feature",
  "properties": {
    "iso:country":"FR",
    "sg:address":"Zi 4 St Porchaire 79301 Bressuire",
    "sg:classifiers":[
        {
            "category":"Professional",
            "subcategory":"Engineering",
            "type":"Services"
        }
    ],
    "sg:phone":"+33 5 49 74 12 75",
    "sg:province":"Champagne",
    "sg:tags":[
        "machine",
        "-",
        "mechanical"
    ],
    "wof:name":"Becot Climatique Sa",
    "wof:placetype":"venue"
},
  "geometry": {"coordinates":[-0.492539,46.840065],"type":"Point"}
}