{
  "type": "Feature",
  "properties": {
    "iso:country":"FR",
    "sg:address":"1, Rue de l'Industrie - ZA, 19300 Montaignac Saint Hippolyte",
    "sg:orig_category":"Unclassifiable Establishments",
    "sg:phone":"+33 5 55 27 60 44",
    "sg:province":"Limousin",
    "wof:name":"Sov\u00e9co - Plast S.a.",
    "wof:placetype":"venue"
},
  "geometry": {"coordinates":[1.983277,45.359978],"type":"Point"}
}