{
  "type": "Feature",
  "properties": {
    "iso:country":"FR",
    "sg:address":"ZA Champs Trentenier",
    "sg:city":"Charmes sur Rh\u00f4ne",
    "sg:orig_category":"Unclassifiable Establishments",
    "sg:phone":"+33 4 75 60 80 23",
    "sg:postcode":"07800",
    "sg:province":"Rhone-Alpes",
    "wof:name":"Chapus Plastiques S.a.r.l.",
    "wof:placetype":"venue"
},
  "geometry": {"coordinates":[4.83475,44.862598],"type":"Point"}
}