{
  "type": "Feature",
  "properties": {
    "iso:country":"FR",
    "sg:address":"B.P. 185, 59603 Maubeuge C\u00e9dex^^Rue du Chemin de Fer, 59600 Maubeuge",
    "sg:orig_category":"Non-Classified Establishments",
    "sg:phone":"+33 3 27 64 97 71",
    "sg:province":"Nord Pas-de-Calais",
    "wof:name":"Martin Ren\u00e9 S.a.",
    "wof:placetype":"venue"
},
  "geometry": {"coordinates":[3.973845,50.278664],"type":"Point"}
}