{
  "type": "Feature",
  "properties": {
    "iso:country":"FR",
    "sg:address":"B.P. 318, 73375 Le Bourget du Lac C\u00e9dex^^Savoie Technolac, 73370 Le Bourget du Lac",
    "sg:orig_category":"Non-Classified Establishments",
    "sg:phone":"+33 4 79 26 46 00",
    "sg:postcode":"73370",
    "sg:province":"Rhone-Alpes",
    "wof:name":"Saunier Environnement S.a.",
    "wof:placetype":"venue"
},
  "geometry": {"coordinates":[5.86225,45.643875],"type":"Point"}
}