{
  "type": "Feature",
  "properties": {
    "addr:full":"Rte de Marolles - ZA du Charbonneau Cheptainville Ile de France 91630",
    "addr:postcode":"91630",
    "addr:street":"Rte De Marolles Za Du Charbonneau",
    "iso:country":"FR",
    "sg:address":"Rte de Marolles - ZA du Charbonneau",
    "sg:city":"Cheptainville",
    "sg:orig_category":"Unclassifiable Establishments",
    "sg:phone":"+33 1 64 56 23 23",
    "sg:postcode":"91630",
    "sg:province":"Ile de France",
    "wof:name":"Seripli S.a.",
    "wof:placetype":"venue"
},
  "geometry": {"coordinates":[2.30128,48.561611],"type":"Point"}
}