{
  "type": "Feature",
  "properties": {
    "addr:full":"44, Bd de Saint Quentin, 80090 Amiens Picardie",
    "addr:housenumber":"44",
    "addr:postcode":"80090",
    "addr:street":"Bd De Saint Quentin",
    "iso:country":"FR",
    "sg:address":"44, Bd de Saint Quentin, 80090 Amiens",
    "sg:orig_category":"Unclassifiable Establishments",
    "sg:phone":"+33 3 22 89 77 97",
    "sg:province":"Picardie",
    "wof:name":"Airetec S.a.r.l.",
    "wof:placetype":"venue"
},
  "geometry": {"coordinates":[2.294872,49.879074],"type":"Point"}
}