{
  "type": "Feature",
  "properties": {
    "addr:full":"3, Rue de Verdun - Eurocampus B\u00e2t. G, 78590 Noisy le Roi Ile de France",
    "addr:housenumber":"3;ba\u0302t g",
    "addr:postcode":"78590",
    "addr:street":"Rue De Verdun",
    "iso:country":"FR",
    "sg:address":"3, Rue de Verdun - Eurocampus B\u00e2t. G, 78590 Noisy le Roi",
    "sg:orig_category":"Non-Classified Establishments",
    "sg:phone":"+33 1 30 80 42 22",
    "sg:province":"Ile de France",
    "wof:name":"Tell Concept S.a.",
    "wof:placetype":"venue"
},
  "geometry": {"coordinates":[2.065082,48.843803],"type":"Point"}
}