{
  "type": "Feature",
  "properties": {
    "addr:full":"30, Rue de l'Hermitte - Centre Tertiaire les 3 Ponts, 59140 Dunkerque Nord Pas-de-Calais",
    "addr:housenumber":"30",
    "addr:postcode":"59140",
    "addr:street":"Rue De L'Hermitte Centre Tertiaire Les;Ponts",
    "iso:country":"FR",
    "sg:address":"30, Rue de l'Hermitte - Centre Tertiaire les 3 Ponts, 59140 Dunkerque",
    "sg:orig_category":"Unclassifiable Establishments",
    "sg:phone":"+33 3 28 24 41 41",
    "sg:province":"Nord Pas-de-Calais",
    "wof:name":"United Arab Agencies France S.a.",
    "wof:placetype":"venue"
},
  "geometry": {"coordinates":[2.34684,51.041801],"type":"Point"}
}