{
  "type": "Feature",
  "properties": {
    "iso:country":"FR",
    "sg:address":"Route D Avignon 84301 CAVAILLON",
    "sg:classifiers":[
        {
            "category":"Food & Beverages",
            "subcategory":"Fruits & Vegetables",
            "type":"Retail Goods"
        }
    ],
    "sg:phone":"+33 4 90 71 36 33",
    "sg:province":"Languedoc-Roussillon",
    "sg:tags":[
        "machine",
        "processing",
        "complete",
        "systems"
    ],
    "wof:name":"Calibrex Sa",
    "wof:placetype":"venue"
},
  "geometry": {"coordinates":[5.008385,43.860233],"type":"Point"}
}