{
  "type": "Feature",
  "properties": {
    "addr:full":"Rue du Terrain de Sport Landaul Bretagne 56690",
    "addr:postcode":"56690",
    "addr:street":"Rue Du Terrain De Sport Landaul Bretagne",
    "iso:country":"FR",
    "sg:address":"Rue du Terrain de Sport",
    "sg:city":"Landaul",
    "sg:orig_category":"Non-Classified Establishments",
    "sg:phone":"+33 2 97 24 62 28",
    "sg:postcode":"56690",
    "sg:province":"Bretagne",
    "wof:name":"Le Dr\u00e9au Jean-yves",
    "wof:placetype":"venue"
},
  "geometry": {"coordinates":[-3.074979,47.748268],"type":"Point"}
}