{
  "type": "Feature",
  "properties": {
    "iso:country":"FR",
    "sg:address":"Rte D\u00e9partementale 100",
    "sg:city":"Le Plessis Belleville",
    "sg:orig_category":"Unclassifiable Establishments",
    "sg:phone":"+33 3 44 60 50 16",
    "sg:postcode":"60330",
    "sg:province":"Picardie",
    "wof:name":"Lavaux S.a.",
    "wof:placetype":"venue"
},
  "geometry": {"coordinates":[2.756738,49.096386],"type":"Point"}
}