{
  "type": "Feature",
  "properties": {
    "iso:country":"FR",
    "sg:address":"1 All Cassard 44000 Nantes",
    "sg:classifiers":[
        {
            "category":"Professional",
            "subcategory":"Computer Services",
            "type":"Services"
        }
    ],
    "sg:phone":"+33 2 40 47 38 38",
    "sg:postcode":"44000",
    "sg:province":"Pays de Loire",
    "sg:tags":[
        "information",
        "technology",
        "software"
    ],
    "wof:name":"Arobas System Sarl",
    "wof:placetype":"venue"
},
  "geometry": {"coordinates":[-1.555873,47.21405],"type":"Point"}
}