{
  "type": "Feature",
  "properties": {
    "iso:country":"FR",
    "sg:address":"8 Rue Paul Sabatier Zac De Kergaradec 29200 Brest",
    "sg:city":"Brest",
    "sg:classifiers":[
        {
            "category":"Food & Beverages",
            "subcategory":"Fruits & Vegetables",
            "type":"Retail Goods"
        }
    ],
    "sg:phone":"+33 2 98 02 15 51",
    "sg:postcode":"29200",
    "sg:province":"Bretagne",
    "sg:tags":[
        "frozen",
        "product",
        "related"
    ],
    "wof:name":"Toupargel Surgeles",
    "wof:placetype":"venue"
},
  "geometry": {"coordinates":[-4.486228,48.39024],"type":"Point"}
}