{
  "type": "Feature",
  "properties": {
    "addr:full":"77876 Montereau Fault Yonne C\u00e9dex^^36, Rue de la Grande Haie - ZI, 77130 Montereau Fault Yonne Ile de France",
    "addr:postcode":"77876;77130",
    "addr:street":"Rue De La Grande Haie Zi",
    "iso:country":"FR",
    "sg:address":"77876 Montereau Fault Yonne C\u00e9dex^^36, Rue de la Grande Haie - ZI, 77130 Montereau Fault Yonne",
    "sg:orig_category":"Non-Classified Establishments",
    "sg:phone":"+33 1 64 70 01 56",
    "sg:province":"Ile de France",
    "wof:name":"S.m.b. S.a. - Soci\u00e9t\u00e9 Monterelaise De Broyage",
    "wof:placetype":"venue"
},
  "geometry": {"coordinates":[2.891333,48.303902],"type":"Point"}
}