{
  "type": "Feature",
  "properties": {
    "addr:full":"15140 Saint Martin Valmeroux Besse Auvergne 15140",
    "addr:housenumber":"15140",
    "addr:postcode":"15140",
    "addr:street":"Saint;Valmeroux",
    "iso:country":"FR",
    "sg:address":"15140 Saint Martin Valmeroux",
    "sg:city":"Besse",
    "sg:orig_category":"Unclassifiable Establishments",
    "sg:phone":"+33 4 71 69 20 01",
    "sg:postcode":"15140",
    "sg:province":"Auvergne",
    "wof:name":"Totes Isotoner S.a.s.",
    "wof:placetype":"venue"
},
  "geometry": {"coordinates":[2.428157,45.118404],"type":"Point"}
}