{
  "type": "Feature",
  "properties": {
    "iso:country":"FR",
    "sg:address":"Quartier St Pierre 07204 Aubenas",
    "sg:classifiers":[
        {
            "category":"Shopping",
            "type":"Retail Goods"
        }
    ],
    "sg:phone":"+33 4 75 87 82 82",
    "sg:province":"Basse Normandie",
    "sg:tags":[
        "metallurgy",
        "finished",
        "-",
        "metalworking",
        "metallic"
    ],
    "wof:name":"Cma Industrie",
    "wof:placetype":"venue"
},
  "geometry": {"coordinates":[4.406191,44.592556],"type":"Point"}
}