{
  "type": "Feature",
  "properties": {
    "addr:full":"61 rue de l'Ouest 59100 Roubaix Nord Pas-de-Calais",
    "addr:housenumber":"61",
    "addr:postcode":"59100",
    "addr:street":"Rue De L'Ouest",
    "iso:country":"FR",
    "sg:address":"61 rue de l'Ouest 59100 Roubaix",
    "sg:classifiers":[
        {
            "category":"Shopping",
            "subcategory":"Stationery & Office Supplies",
            "type":"Retail Goods"
        }
    ],
    "sg:phone":"+33 3 20 26 85 85",
    "sg:province":"Nord Pas-de-Calais",
    "sg:tags":[
        "supplies",
        "ecological"
    ],
    "wof:name":"Etablissements Vial Et Fils Sa",
    "wof:placetype":"venue"
},
  "geometry": {"coordinates":[3.160883,50.695164],"type":"Point"}
}