{
  "type": "Feature",
  "properties": {
    "iso:country":"FR",
    "sg:address":"70, Rue de la R\u00e9sistance, 28700 Auneau",
    "sg:city":"Auneau",
    "sg:orig_category":"Unclassifiable Establishments",
    "sg:phone":"+33 2 37 91 35 80",
    "sg:postcode":"28700",
    "sg:province":"Centre",
    "wof:name":"V.i.p. S.a. - Vicat Produits Industriels",
    "wof:placetype":"venue"
},
  "geometry": {"coordinates":[1.7741,48.450809],"type":"Point"}
}