{
  "type": "Feature",
  "properties": {
    "addr:full":"Place Darralde Navarrenx Aquitaine 64190",
    "addr:postcode":"64190",
    "addr:street":"Place Darralde",
    "iso:country":"FR",
    "sg:address":"Place Darralde",
    "sg:city":"Navarrenx",
    "sg:orig_category":"Non-Classified Establishments",
    "sg:phone":"+33 5 59 66 01 00",
    "sg:postcode":"64190",
    "sg:province":"Aquitaine",
    "wof:name":"Banque Populaire Du Sud-ouest S.a.",
    "wof:placetype":"venue"
},
  "geometry": {"coordinates":[-0.761284,43.322014],"type":"Point"}
}