{
  "type": "Feature",
  "properties": {
    "addr:full":"5 Rue De La Breche D Oger 51190 Le Mesnil Sur Oger Champagne 51190",
    "addr:housenumber":"5",
    "addr:postcode":"51190;51190",
    "addr:street":"Rue De La Breche D Oger;Mesnil;Oger Champagne",
    "iso:country":"FR",
    "sg:address":"5 Rue De La Breche D Oger 51190 Le Mesnil Sur Oger",
    "sg:classifiers":[
        {
            "category":"Food Court",
            "type":"Food & Drink"
        }
    ],
    "sg:phone":"+33 3 26 57 51 65",
    "sg:postcode":"51190",
    "sg:province":"Champagne",
    "sg:tags":[
        "product",
        "related"
    ],
    "wof:name":"Societe As",
    "wof:placetype":"venue"
},
  "geometry": {"coordinates":[4.018288,48.946926],"type":"Point"}
}