{
  "type": "Feature",
  "properties": {
    "iso:country":"FR",
    "sg:address":"36 Quai De La Rap\u00e9e 75012 Paris",
    "sg:classifiers":[
        {
            "category":"Manufacturing",
            "subcategory":"Chemicals & Compounds",
            "type":"Manufacturing & Wholesale Goods"
        }
    ],
    "sg:phone":"+33 1 46 28 11 45",
    "sg:postcode":"75012",
    "sg:province":"Ile de France",
    "sg:tags":[
        "pharmaceutical",
        "energy",
        "chemistry",
        "-",
        "by-product"
    ],
    "wof:name":"Esso Dsm",
    "wof:placetype":"venue"
},
  "geometry": {"coordinates":[2.373175,48.841625],"type":"Point"}
}