{
  "type": "Feature",
  "properties": {
    "addr:full":"10 B R Maleville 24000 Perigueux P\u00e9rigueux Aquitaine 24000",
    "addr:housenumber":"10",
    "addr:postcode":"24000;24000",
    "addr:street":"B R Maleville",
    "iso:country":"FR",
    "sg:address":"10 B R Maleville 24000 Perigueux",
    "sg:city":"P\u00e9rigueux",
    "sg:classifiers":[
        {
            "category":"Wholesale",
            "subcategory":"Medical Equipment & Supplies",
            "type":"Manufacturing & Wholesale Goods"
        }
    ],
    "sg:phone":"+33 5 53 08 79 90",
    "sg:postcode":"24000",
    "sg:province":"Aquitaine",
    "sg:tags":[
        "instrument",
        "health",
        "-",
        "precision"
    ],
    "wof:name":"M. Duverneuil Guy",
    "wof:placetype":"venue"
},
  "geometry": {"coordinates":[0.719381,45.186108],"type":"Point"}
}