{
  "type": "Feature",
  "properties": {
    "addr:full":"15, Rue de la Gare, 69009 Lyon Rhone-Alpes",
    "addr:housenumber":"15",
    "addr:postcode":"69009",
    "addr:street":"Rue De La Gare",
    "iso:country":"FR",
    "sg:address":"15, Rue de la Gare, 69009 Lyon",
    "sg:orig_category":"Unclassifiable Establishments",
    "sg:phone":"+33 4 78 83 76 97",
    "sg:province":"Rhone-Alpes",
    "wof:name":"Perrier Constructeur S.a.",
    "wof:placetype":"venue"
},
  "geometry": {"coordinates":[4.805335,45.774105],"type":"Point"}
}