{
  "type": "Feature",
  "properties": {
    "iso:country":"FR",
    "sg:address":"Z.I. de l'Aubr\u00e9e",
    "sg:city":"Sabl\u00e9 sur Sarthe",
    "sg:orig_category":"Unclassifiable Establishments",
    "sg:phone":"+33 2 43 62 12 20",
    "sg:postcode":"72300",
    "sg:province":"Pays de Loire",
    "wof:name":"G\u00e9n\u00e9rale Traiteur S.a.",
    "wof:placetype":"venue"
},
  "geometry": {"coordinates":[-0.299539,47.82737],"type":"Point"}
}