{
  "type": "Feature",
  "properties": {
    "addr:full":"7, Rte Nationale, 59152 Tressin Nord Pas-de-Calais",
    "addr:housenumber":"7",
    "addr:postcode":"59152",
    "addr:street":"Rte Nationale",
    "iso:country":"FR",
    "sg:address":"7, Rte Nationale, 59152 Tressin",
    "sg:orig_category":"Unclassifiable Establishments",
    "sg:phone":"+33 3 20 41 29 76",
    "sg:province":"Nord Pas-de-Calais",
    "wof:name":"Clowill S.a.",
    "wof:placetype":"venue"
},
  "geometry": {"coordinates":[3.181394,50.609669],"type":"Point"}
}