{
  "type": "Feature",
  "properties": {
    "addr:full":"Bd de Fleurus Limoges Limousin 87000",
    "addr:postcode":"87000",
    "addr:street":"Bd De Fleurus",
    "iso:country":"FR",
    "sg:address":"Bd de Fleurus",
    "sg:city":"Limoges",
    "sg:orig_category":"Unclassifiable Establishments",
    "sg:phone":"+33 5 55 34 46 87",
    "sg:postcode":"87000",
    "sg:province":"Limousin",
    "wof:name":"Syndicat D'initiative De Limoges",
    "wof:placetype":"venue"
},
  "geometry": {"coordinates":[1.263514,45.830875],"type":"Point"}
}