{
  "type": "Feature",
  "properties": {
    "addr:full":"B.P. 14, 67850 Herrlisheim^^ZI le Ried, 67850 Herrlisheim Herrlisheim Alsace 67850",
    "addr:postcode":"67850;67850;67850",
    "addr:street":"B.P. 14;Ried",
    "iso:country":"FR",
    "sg:address":"B.P. 14, 67850 Herrlisheim^^ZI le Ried, 67850 Herrlisheim",
    "sg:city":"Herrlisheim",
    "sg:orig_category":"Non-Classified Establishments",
    "sg:phone":"+33 3 88 59 77 99",
    "sg:postcode":"67850",
    "sg:province":"Alsace",
    "wof:name":"A.p.m. S.a.r.l.",
    "wof:placetype":"venue"
},
  "geometry": {"coordinates":[7.90651,48.729767],"type":"Point"}
}