{
  "type": "Feature",
  "properties": {
    "iso:country":"FR",
    "sg:address":"B.P. 22, 59124 Escaudain^^Chemin de Mastaing - Les Onze Muids, 59124 Escaudain",
    "sg:orig_category":"Non-Classified Establishments",
    "sg:phone":"+33 3 27 44 27 67",
    "sg:province":"Nord Pas-de-Calais",
    "wof:name":"Renard S.a.",
    "wof:placetype":"venue"
},
  "geometry": {"coordinates":[3.3443,50.334515],"type":"Point"}
}