{
  "type": "Feature",
  "properties": {
    "iso:country":"FR",
    "sg:address":"B.P. 8318, 95803 Cergy Pontoise C\u00e9dex^^47, Av. des Genottes - B\u00e2t. B - Le C\u00e9rame , 95800 Cergy",
    "sg:orig_category":"Non-Classified Establishments",
    "sg:phone":"+33 1 34 25 55 55",
    "sg:province":"Ile de France",
    "wof:name":"Saint Gobain Stradal S.a.",
    "wof:placetype":"venue"
},
  "geometry": {"coordinates":[2.000455,49.035156],"type":"Point"}
}