{
  "type": "Feature",
  "properties": {
    "addr:full":"18, Rue de Tarayre, 12000 Rodez Midi Pyr\u00e9n\u00e9es 12000",
    "addr:housenumber":"18",
    "addr:postcode":"12000;12000",
    "addr:street":"Rue De Tarayre",
    "iso:country":"FR",
    "sg:address":"18, Rue de Tarayre, 12000 Rodez",
    "sg:orig_category":"Non-Classified Establishments",
    "sg:phone":"+33 5 65 78 34 09",
    "sg:postcode":"12000",
    "sg:province":"Midi Pyr\u00e9n\u00e9es",
    "wof:name":"E.e.g Simecsol S.a.",
    "wof:placetype":"venue"
},
  "geometry": {"coordinates":[2.577575,44.35603],"type":"Point"}
}