{
  "type": "Feature",
  "properties": {
    "addr:full":"21 Rue De La Solidarit\u00e9 94230 Cachan Ile de France 94230",
    "addr:housenumber":"21",
    "addr:postcode":"94230;ile;94230",
    "addr:street":"Rue De La Solidarite\u0301;France",
    "iso:country":"FR",
    "sg:address":"21 Rue De La Solidarit\u00e9 94230 Cachan",
    "sg:classifiers":[
        {
            "category":"Professional",
            "subcategory":"Computer Services",
            "type":"Services"
        }
    ],
    "sg:phone":"+33 1 45 46 93 21",
    "sg:postcode":"94230",
    "sg:province":"Ile de France",
    "sg:tags":[
        "information",
        "technology",
        "software"
    ],
    "wof:name":"Imtech Sa",
    "wof:placetype":"venue"
},
  "geometry": {"coordinates":[2.343204,48.792072],"type":"Point"}
}