{
  "type": "Feature",
  "properties": {
    "iso:country":"FR",
    "sg:address":"B.P. 107, 33260 La Teste de Buch^^11, Av. Mariotte - ZI, 33260 La Teste de Buch",
    "sg:city":"Teste-de-Buch",
    "sg:orig_category":"Non-Classified Establishments",
    "sg:phone":"+33 5 56 22 30 60",
    "sg:postcode":"33260",
    "sg:province":"Aquitaine",
    "wof:name":"Nanni Industries S.a.",
    "wof:placetype":"venue"
},
  "geometry": {"coordinates":[-1.145227,44.632915],"type":"Point"}
}