{
  "type": "Feature",
  "properties": {
    "iso:country":"FR",
    "sg:address":"115 av G\u00e9n\u00e9ral de Gaulle; Bruges",
    "sg:classifiers":[
        {
            "category":"Banks & Credit Unions",
            "subcategory":"Bank",
            "type":"Services"
        }
    ],
    "sg:phone":"+33 3356289500",
    "sg:province":"Lorraine",
    "wof:name":"Banque National De Paris",
    "wof:placetype":"venue"
},
  "geometry": {"coordinates":[3.224519,51.208485],"type":"Point"}
}