{
  "type": "Feature",
  "properties": {
    "iso:country":"FR",
    "sg:address":"B.P. Fru 152, 92522 Rungis C\u00e9dex^^26, Av. de Bretagne, 94550 Chevilly Larue",
    "sg:orig_category":"Non-Classified Establishments",
    "sg:phone":"+33 1 46 87 23 09",
    "sg:province":"Ile de France",
    "wof:name":"S.d.i. S.a.r.l. - Soci\u00e9t\u00e9 De Distribution Internationale",
    "wof:placetype":"venue"
},
  "geometry": {"coordinates":[2.35062,48.770672],"type":"Point"}
}