{
  "type": "Feature",
  "properties": {
    "iso:country":"FR",
    "sg:address":"36 bis, Rue Fr\u00e9d\u00e9ric Sarazin, 77550 Reau",
    "sg:orig_category":"Unclassifiable Establishments",
    "sg:phone":"+33 1 60 60 59 09",
    "sg:province":"Ile de France",
    "wof:name":"Osimec S.a.r.l.",
    "wof:placetype":"venue"
},
  "geometry": {"coordinates":[2.624266,48.607224],"type":"Point"}
}