{
  "type": "Feature",
  "properties": {
    "addr:full":"36 bis, Rue Fr\u00e9d\u00e9ric Sarazin, 77550 Reau Ile de France",
    "addr:housenumber":"36 bis",
    "addr:postcode":"77550",
    "addr:street":"Rue Fre\u0301De\u0301Ric Sarazin;Ile De France",
    "iso:country":"FR",
    "sg:address":"36 bis, Rue Fr\u00e9d\u00e9ric Sarazin, 77550 Reau",
    "sg:orig_category":"Unclassifiable Establishments",
    "sg:phone":"+33 1 60 60 59 09",
    "sg:province":"Ile de France",
    "wof:name":"Osimec S.a.r.l.",
    "wof:placetype":"venue"
},
  "geometry": {"coordinates":[2.624266,48.607224],"type":"Point"}
}