{
  "type": "Feature",
  "properties": {
    "iso:country":"FR",
    "sg:address":"Z I 07250 LE POUZIN",
    "sg:classifiers":[
        {
            "category":"Retail",
            "subcategory":"Car Wash",
            "type":"Services"
        }
    ],
    "sg:phone":"+33 4 75 63 81 20",
    "sg:postcode":"07250",
    "sg:province":"Rhone-Alpes",
    "sg:tags":[
        "elevator"
    ],
    "wof:name":"Ste De Metallerie Pour Ascenseur E.u.r.l.",
    "wof:placetype":"venue"
},
  "geometry": {"coordinates":[4.74692,44.757591],"type":"Point"}
}