{
  "type": "Feature",
  "properties": {
    "iso:country":"FR",
    "sg:address":"1642 route des Pugets 06700 ST LAURENT DU VAR",
    "sg:classifiers":[
        {
            "category":"Shopping",
            "subcategory":"Clothing, Apparel, & Fashions",
            "type":"Retail Goods"
        }
    ],
    "sg:phone":"+33 4 93 07 41 41",
    "sg:province":"Champagne",
    "sg:tags":[
        "clothing",
        "fabric"
    ],
    "wof:name":"Savit Concept Sa",
    "wof:placetype":"venue"
},
  "geometry": {"coordinates":[7.183891,43.692486],"type":"Point"}
}