{
  "type": "Feature",
  "properties": {
    "iso:country":"FR",
    "sg:address":"B.P. 261, 69515 Vaulx en Velin C\u00e9dex^^11, Av. Karl Marx - ZI Est, 69120 Vaulx en Velin",
    "sg:orig_category":"Non-Classified Establishments",
    "sg:phone":"+33 4 37 45 11 00",
    "sg:postcode":"69120",
    "sg:province":"Rhone-Alpes",
    "wof:name":"E.r.m.o. S.a. - Europe Ressources Machines Outils",
    "wof:placetype":"venue"
},
  "geometry": {"coordinates":[4.916895,45.779022],"type":"Point"}
}