{
  "type": "Feature",
  "properties": {
    "addr:full":"Usine De Tissage 42540 St Just La Pendue Rhone-Alpes 42540",
    "addr:postcode":"42540;pendue;42540",
    "addr:street":"Rhone-Alpes",
    "iso:country":"FR",
    "sg:address":"Usine De Tissage 42540 St Just La Pendue",
    "sg:classifiers":[
        {
            "category":"Shopping",
            "subcategory":"Crafts & Fabrics",
            "type":"Retail Goods"
        }
    ],
    "sg:phone":"+33 4 77 63 20 04",
    "sg:postcode":"42540",
    "sg:province":"Rhone-Alpes",
    "sg:tags":[
        "textile",
        "clothing"
    ],
    "wof:name":"Sfate Et Combier",
    "wof:placetype":"venue"
},
  "geometry": {"coordinates":[4.241717,45.892799],"type":"Point"}
}