{
  "type": "Feature",
  "properties": {
    "iso:country":"FR",
    "sg:address":"Les Serves Basses 01290 Crottet",
    "sg:orig_category":"Unclassifiable Establishments",
    "sg:phone":"+33 3 85 31 51 92",
    "sg:province":"Rhone-Alpes",
    "wof:name":"Cochet S.a.r.l.",
    "wof:placetype":"venue"
},
  "geometry": {"coordinates":[4.900125,46.276711],"type":"Point"}
}