{
  "type": "Feature",
  "properties": {
    "addr:full":"Av du Docteur Lef\u00e8bvre - Les Plans Villeneuve Loubet Provence-Alpes-C\u00f4te d'Azur 06270",
    "addr:postcode":"06270",
    "addr:street":"Av Du Docteur Lefe\u0300Bvre Les;Loubet",
    "iso:country":"FR",
    "sg:address":"Av du Docteur Lef\u00e8bvre - Les Plans",
    "sg:city":"Villeneuve Loubet",
    "sg:orig_category":"Unclassifiable Establishments",
    "sg:phone":"+33 4 93 22 58 83",
    "sg:postcode":"06270",
    "sg:province":"Provence-Alpes-C\u00f4te d'Azur",
    "wof:name":"S.t.e.m. S.a.r.l. - Services De Transports, D'entreposage Et De Magas",
    "wof:placetype":"venue"
},
  "geometry": {"coordinates":[7.132785,43.636009],"type":"Point"}
}