{
  "type": "Feature",
  "properties": {
    "addr:full":"5 rue de la Manutention 75116 Paris Ile de France",
    "addr:housenumber":"5",
    "addr:postcode":"75116",
    "addr:street":"Rue De La Manutention",
    "iso:country":"FR",
    "sg:address":"5 rue de la Manutention 75116 Paris",
    "sg:classifiers":[
        {
            "category":"Home & Garden",
            "subcategory":"Furniture",
            "type":"Retail Goods"
        }
    ],
    "sg:phone":"+33 1 47 23 95 00",
    "sg:province":"Ile de France",
    "sg:tags":[
        "designer"
    ],
    "wof:name":"G\u00e9n\u00e9ral Marine Sarl",
    "wof:placetype":"venue"
},
  "geometry": {"coordinates":[2.295865,48.863922],"type":"Point"}
}