{
  "type": "Feature",
  "properties": {
    "iso:country":"FR",
    "sg:address":"B.P. 281, 69659 Villefranche sur Sa\u00f4ne C\u00e9dex^^Rue des Fr\u00e8res Bonnet, 69400 Villefranche sur Sa\u00f4ne",
    "sg:orig_category":"Non-Classified Establishments",
    "sg:phone":"+33 4 74 68 64 72",
    "sg:province":"Rhone-Alpes",
    "wof:name":"Hydro Calade S.a.",
    "wof:placetype":"venue"
},
  "geometry": {"coordinates":[4.738465,45.988438],"type":"Point"}
}