{
  "type": "Feature",
  "properties": {
    "iso:country":"FR",
    "sg:address":"B.P. 3, 85620 Rocheservi\u00e8re C\u00e9dex^^6, Rue du Grand Moulin, 85620 Rocheservi\u00e8re",
    "sg:orig_category":"Non-Classified Establishments",
    "sg:phone":"+33 2 51 94 98 02",
    "sg:province":"Pays de Loire",
    "wof:name":"L.c.m.i. S.a. - Le Composant M\u00e9canique Industriel",
    "wof:placetype":"venue"
},
  "geometry": {"coordinates":[-1.501054,46.942135],"type":"Point"}
}