{
  "type": "Feature",
  "properties": {
    "addr:full":"17 Rue De La Doneliere Rennes Bretagne 35000",
    "addr:housenumber":"17",
    "addr:postcode":"35000",
    "addr:street":"Rue De La Doneliere Rennes",
    "iso:country":"FR",
    "sg:address":"17 Rue De La Doneliere",
    "sg:city":"Rennes",
    "sg:classifiers":[
        {
            "category":"Banks & Credit Unions",
            "subcategory":"Financial Services",
            "type":"Services"
        }
    ],
    "sg:phone":"+33 2 99 87 16 87",
    "sg:postcode":"35000",
    "sg:province":"Bretagne",
    "sg:tags":[
        "banking",
        "finance",
        "insurance"
    ],
    "wof:name":"Syndex",
    "wof:placetype":"venue"
},
  "geometry": {"coordinates":[-1.6863,48.130325],"type":"Point"}
}