{
  "type": "Feature",
  "properties": {
    "iso:country":"FR",
    "sg:address":"1 Grand Rue 68770 Ammerschwihr",
    "sg:city":"Ammerschwihr",
    "sg:classifiers":[
        {
            "category":"Travel",
            "subcategory":"Hotels & Motels",
            "type":"Entertainment"
        }
    ],
    "sg:phone":"+33 3 89 47 10 12",
    "sg:postcode":"68770",
    "sg:province":"Alsace",
    "sg:tags":[
        "hotels",
        "business",
        "restaurant"
    ],
    "wof:name":"Hotel Restaurant Aux Armes De France Sa",
    "wof:placetype":"venue"
},
  "geometry": {"coordinates":[7.284018,48.125671],"type":"Point"}
}