{
  "type": "Feature",
  "properties": {
    "addr:full":"Av De La Lib\u00e9ration 20600 Bastia Corse",
    "addr:postcode":"20600",
    "addr:street":"Av De La Libe\u0301Ration",
    "iso:country":"FR",
    "sg:address":"Av De La Lib\u00e9ration 20600 Bastia",
    "sg:classifiers":[
        {
            "category":"Professional",
            "type":"Services"
        }
    ],
    "sg:phone":"+33 4 95 30 20 20",
    "sg:province":"Corse",
    "sg:tags":[
        "transport",
        "road"
    ],
    "wof:name":"Sarl Ambulances Matelli",
    "wof:placetype":"venue"
},
  "geometry": {"coordinates":[9.44517,42.685314],"type":"Point"}
}