{
  "type": "Feature",
  "properties": {
    "iso:country":"FR",
    "sg:address":"5, Rue Lequesne, 94130 Nogent sur Marne",
    "sg:orig_category":"Unclassifiable Establishments",
    "sg:phone":"+33 1 48 73 50 32",
    "sg:province":"Ile de France",
    "wof:name":"Soci\u00e9t\u00e9 Nouvelle Mondial Electronique S.a.r.l.",
    "wof:placetype":"venue"
},
  "geometry": {"coordinates":[2.483728,48.839546],"type":"Point"}
}