{
  "type": "Feature",
  "properties": {
    "addr:full":"123 Bd De Grenelle BP 6 75725 Paris Cedex 15 Ile de France",
    "addr:housenumber":"123;6",
    "addr:postcode":"75725",
    "addr:street":"Bd De Grenelle Bp",
    "iso:country":"FR",
    "sg:address":"123 Bd De Grenelle BP 6 75725 Paris Cedex 15",
    "sg:classifiers":[
        {
            "category":"Professional",
            "subcategory":"Printing & Photocopies",
            "type":"Services"
        }
    ],
    "sg:phone":"+33 1 45 68 60 00",
    "sg:province":"Ile de France",
    "sg:tags":[
        "publishing"
    ],
    "wof:name":"France Loisirs Service",
    "wof:placetype":"venue"
},
  "geometry": {"coordinates":[2.299311,48.848904],"type":"Point"}
}