{
  "type": "Feature",
  "properties": {
    "addr:full":"La Gare 42430 St Just En Chevalet Rhone-Alpes",
    "addr:postcode":"42430",
    "iso:country":"FR",
    "sg:address":"La Gare 42430 St Just En Chevalet",
    "sg:classifiers":[
        {
            "category":"Home & Garden",
            "subcategory":"Furniture",
            "type":"Retail Goods"
        }
    ],
    "sg:phone":"+33 4 77 65 14 77",
    "sg:province":"Rhone-Alpes",
    "sg:tags":[
        "wood"
    ],
    "wof:name":"Charpentes Menuiseries Foreziennes Sa",
    "wof:placetype":"venue"
},
  "geometry": {"coordinates":[3.845475,45.908726],"type":"Point"}
}