{
  "type": "Feature",
  "properties": {
    "addr:full":"19 Rue Du Cadran St Pierre 51100 Reims Champagne 51100",
    "addr:housenumber":"19",
    "addr:postcode":"51100;51100",
    "addr:street":"Rue Du Cadran St Pierre",
    "iso:country":"FR",
    "sg:address":"19 Rue Du Cadran St Pierre 51100 Reims",
    "sg:classifiers":[
        {
            "category":"Professional",
            "subcategory":"Advertising",
            "type":"Services"
        }
    ],
    "sg:phone":"+33 3 26 50 55 50",
    "sg:postcode":"51100",
    "sg:province":"Champagne",
    "sg:tags":[
        "information",
        "medium",
        "communication"
    ],
    "wof:name":"Publi Reims",
    "wof:placetype":"venue"
},
  "geometry": {"coordinates":[4.02896,49.25568],"type":"Point"}
}