{
  "type": "Feature",
  "properties": {
    "addr:full":"68 rte Nationale; Drap",
    "addr:housenumber":"68",
    "addr:street":"Rte Nationale",
    "iso:country":"FR",
    "sg:address":"68 rte Nationale; Drap",
    "sg:classifiers":[
        {
            "category":"Banks & Credit Unions",
            "subcategory":"Bank",
            "type":"Services"
        }
    ],
    "sg:phone":"+33 3393548367",
    "wof:name":"Cr\u00e9dit Agricole Des Alpes Maritimes",
    "wof:placetype":"venue"
},
  "geometry": {"coordinates":[7.32029,43.754795],"type":"Point"}
}