{
  "type": "Feature",
  "properties": {
    "iso:country":"FR",
    "sg:address":"1 Rue Jean Carrasso 95870 Bezons",
    "sg:classifiers":[
        {
            "category":"Shopping",
            "subcategory":"Pharmacy",
            "type":"Retail Goods"
        }
    ],
    "sg:phone":"+33 1 55 69 37 80",
    "sg:postcode":"95870",
    "sg:province":"Ile de France",
    "sg:tags":[
        "chemical",
        "pharmaceutical",
        "chemistry"
    ],
    "wof:name":"Raschig France",
    "wof:placetype":"venue"
},
  "geometry": {"coordinates":[2.216344,48.920918],"type":"Point"}
}