{
  "type": "Feature",
  "properties": {
    "iso:country":"FR",
    "sg:address":"46 blvd Jean Jaur\u00e8s; Rognac; 13340",
    "sg:classifiers":[
        {
            "category":"Banks & Credit Unions",
            "subcategory":"Bank",
            "type":"Services"
        }
    ],
    "sg:phone":"+33 3342870308",
    "sg:province":"Champagne",
    "wof:name":"Banque Nationale De Paris",
    "wof:placetype":"venue"
},
  "geometry": {"coordinates":[5.226829,43.487713],"type":"Point"}
}