{
  "type": "Feature",
  "properties": {
    "iso:country":"FR",
    "sg:address":"1",
    "sg:city":"du Mar Joffre Usine de Chantereine 60150 Thourotte",
    "sg:classifiers":[
        {
            "category":"Manufacturing",
            "subcategory":"Glass & Minerals",
            "type":"Manufacturing & Wholesale Goods"
        }
    ],
    "sg:phone":"+33 3 44 92 37 00",
    "sg:postcode":"60150",
    "sg:province":"Picardie",
    "sg:tags":[
        "building",
        "material"
    ],
    "wof:name":"Saint Gobain Sekurit France",
    "wof:placetype":"venue"
},
  "geometry": {"coordinates":[2.878735,49.484856],"type":"Point"}
}