{
  "type": "Feature",
  "properties": {
    "iso:country":"FR",
    "sg:address":"23, Rue de la Maison Rouge, 77185 Lognes",
    "sg:orig_category":"Unclassifiable Establishments",
    "sg:phone":"+33 1 64 11 25 35",
    "sg:province":"Ile de France",
    "wof:name":"Sikla France S.a.r.l.",
    "wof:placetype":"venue"
},
  "geometry": {"coordinates":[2.629594,48.832588],"type":"Point"}
}