{
  "type": "Feature",
  "properties": {
    "iso:country":"FR",
    "sg:address":"Bd S\u00e9bastien Brant 67400 Illkirch Graffenstaden",
    "sg:city":"Geispolsheim",
    "sg:classifiers":[
        {
            "category":"Travel",
            "subcategory":"Hotels & Motels",
            "type":"Entertainment"
        }
    ],
    "sg:phone":"+33 3 88 40 84 84",
    "sg:postcode":"67400",
    "sg:province":"Alsace",
    "sg:tags":[
        "hotels",
        "business",
        "restaurant"
    ],
    "wof:name":"Hotel Holiday Inn Garden Court",
    "wof:placetype":"venue"
},
  "geometry": {"coordinates":[7.735609,48.526154],"type":"Point"}
}