{
  "type": "Feature",
  "properties": {
    "iso:country":"FR",
    "sg:address":"Zi De Graces 22200 Guingamp",
    "sg:city":"Guingamp",
    "sg:classifiers":[
        {
            "category":"Food & Beverages",
            "subcategory":"Groceries & Convenience Stores",
            "type":"Retail Goods"
        }
    ],
    "sg:phone":"+33 2 96 40 12 90",
    "sg:postcode":"22200",
    "sg:province":"Bretagne",
    "sg:tags":[
        "product",
        "related"
    ],
    "wof:name":"Cheritel (eurl)",
    "wof:placetype":"venue"
},
  "geometry": {"coordinates":[-3.149486,48.562763],"type":"Point"}
}