{
  "type": "Feature",
  "properties": {
    "addr:full":"48, Rue de la Fraternit\u00e9, 93170 Bagnolet Ile de France",
    "addr:housenumber":"48",
    "addr:postcode":"93170;ile",
    "addr:street":"Rue De La Fraternite\u0301",
    "iso:country":"FR",
    "sg:address":"48, Rue de la Fraternit\u00e9, 93170 Bagnolet",
    "sg:orig_category":"Unclassifiable Establishments",
    "sg:phone":"+33 1 43 60 31 11",
    "sg:province":"Ile de France",
    "wof:name":"S.e.e.c. S.a.r.l. - Soci\u00e9t\u00e9 D'exploitation Des Entreprises Casals",
    "wof:placetype":"venue"
},
  "geometry": {"coordinates":[2.423245,48.859905],"type":"Point"}
}