{
  "type": "Feature",
  "properties": {
    "iso:country":"FR",
    "sg:address":"B.P. 3023, 68061 Mulhouse C\u00e9dex^^14, Rue Franklin, 68200 Mulhouse",
    "sg:city":"Mulhouse",
    "sg:orig_category":"Non-Classified Establishments",
    "sg:phone":"+33 3 89 59 51 11",
    "sg:postcode":"68200",
    "sg:province":"Alsace",
    "wof:name":"Burocom 68 S.a.",
    "wof:placetype":"venue"
},
  "geometry": {"coordinates":[7.31201,47.75547],"type":"Point"}
}