{
  "type": "Feature",
  "properties": {
    "iso:country":"FR",
    "sg:address":"20, Rue de la R\u00e9publique, 21340 Nolay",
    "sg:city":"Nolay",
    "sg:orig_category":"Unclassifiable Establishments",
    "sg:phone":"+33 3 80 20 27 10",
    "sg:postcode":"21340",
    "sg:province":"Bourgogne",
    "wof:name":"Caisse D'\u00e9pargne De Bourgogne, Agence Nolay",
    "wof:placetype":"venue"
},
  "geometry": {"coordinates":[4.633698,46.952606],"type":"Point"}
}