{
  "type": "Feature",
  "properties": {
    "addr:full":"L.D. L'Ange Marie 72290 Messi\u00e8res Sur Ponthouin Pays de Loire",
    "addr:postcode":"72290",
    "addr:street":"Marie;Ponthouin",
    "iso:country":"FR",
    "sg:address":"L.D. L'Ange Marie 72290 Messi\u00e8res Sur Ponthouin",
    "sg:classifiers":[
        {
            "category":"Home & Garden",
            "subcategory":"Furniture",
            "type":"Retail Goods"
        }
    ],
    "sg:phone":"+33 2 43 97 45 05",
    "sg:province":"Pays de Loire",
    "sg:tags":[
        "wood"
    ],
    "wof:name":"Ets Drouin Sa",
    "wof:placetype":"venue"
},
  "geometry": {"coordinates":[0.29267,48.211411],"type":"Point"}
}