{
  "type": "Feature",
  "properties": {
    "addr:full":"160 Rue Jules Verne Za Champ Madame 63110 Beaumont Beaumont Auvergne 63110",
    "addr:housenumber":"160",
    "addr:postcode":"63110;63110",
    "addr:street":"Rue Jules Verne Za Champ Madame",
    "iso:country":"FR",
    "sg:address":"160 Rue Jules Verne Za Champ Madame 63110 Beaumont",
    "sg:city":"Beaumont",
    "sg:classifiers":[
        {
            "category":"Professional",
            "subcategory":"Engineering",
            "type":"Services"
        }
    ],
    "sg:phone":"+33 4 73 15 00 40",
    "sg:postcode":"63110",
    "sg:province":"Auvergne",
    "sg:tags":[
        "machine",
        "-",
        "mechanical"
    ],
    "wof:name":"Taillandier Jp Ingenierie",
    "wof:placetype":"venue"
},
  "geometry": {"coordinates":[3.08568,45.753647],"type":"Point"}
}