{
  "type": "Feature",
  "properties": {
    "iso:country":"FR",
    "sg:address":"Gare Maritime du Naye",
    "sg:city":"Saint Malo",
    "sg:orig_category":"Unclassifiable Establishments",
    "sg:phone":"+33 2 99 21 15 00",
    "sg:postcode":"35400",
    "sg:province":"Bretagne",
    "wof:name":"Etablissements Laurent Pelliet S.a.",
    "wof:placetype":"venue"
},
  "geometry": {"coordinates":[-2.003669,48.604897],"type":"Point"}
}