{
  "type": "Feature",
  "properties": {
    "addr:full":"1, Rue Edouard Herriot, 24120 Terrasson la Villedieu Beauregard-de-Terrasson Aquitaine 24120",
    "addr:housenumber":"1",
    "addr:postcode":"24120;24120",
    "addr:street":"Rue Edouard Herriot",
    "iso:country":"FR",
    "sg:address":"1, Rue Edouard Herriot, 24120 Terrasson la Villedieu",
    "sg:city":"Beauregard-de-Terrasson",
    "sg:orig_category":"Unclassifiable Establishments",
    "sg:phone":"+33 5 53 50 01 01",
    "sg:postcode":"24120",
    "sg:province":"Aquitaine",
    "wof:name":"Imprimerie De L'avenir S.a.r.l.",
    "wof:placetype":"venue"
},
  "geometry": {"coordinates":[1.30349,45.135864],"type":"Point"}
}