{
  "type": "Feature",
  "properties": {
    "addr:full":"B.P. 11, 59198 Haspres^^3, Rue de Villers en Cauchies, 59198 Haspres Nord Pas-de-Calais 59198",
    "addr:postcode":"59198;59198;59198",
    "addr:street":"B.P. 11;Rue De Villers En Cauchies",
    "iso:country":"FR",
    "sg:address":"B.P. 11, 59198 Haspres^^3, Rue de Villers en Cauchies, 59198 Haspres",
    "sg:orig_category":"Non-Classified Establishments",
    "sg:phone":"+33 3 27 25 79 90",
    "sg:postcode":"59198",
    "sg:province":"Nord Pas-de-Calais",
    "wof:name":"Cobelak France S.a.",
    "wof:placetype":"venue"
},
  "geometry": {"coordinates":[3.415765,50.257839],"type":"Point"}
}