{
  "type": "Feature",
  "properties": {
    "iso:country":"FR",
    "sg:address":"12 Rue Des Forges Zi Nord 86200 Loudun",
    "sg:classifiers":[
        {
            "category":"Food & Beverages",
            "subcategory":"Fruits & Vegetables",
            "type":"Retail Goods"
        }
    ],
    "sg:phone":"+33 5 49 98 65 00",
    "sg:postcode":"86200",
    "sg:province":"Poitou-Charentes",
    "sg:tags":[
        "preserve",
        "product",
        "related"
    ],
    "wof:name":"Sarl Tradition Epicerie Fine",
    "wof:placetype":"venue"
},
  "geometry": {"coordinates":[0.156242,46.958393],"type":"Point"}
}