{
  "type": "Feature",
  "properties": {
    "addr:full":"21 R Vi\u00e8te 75017 Paris Ile de France 75017",
    "addr:housenumber":"21",
    "addr:postcode":"75017;75017",
    "addr:street":"R Vie\u0300Te",
    "iso:country":"FR",
    "sg:address":"21 R Vi\u00e8te 75017 Paris",
    "sg:classifiers":[
        {
            "category":"Professional",
            "subcategory":"Advertising",
            "type":"Services"
        }
    ],
    "sg:phone":"+33 1 40 53 47 47",
    "sg:postcode":"75017",
    "sg:province":"Ile de France",
    "sg:tags":[
        "marketing",
        "medium",
        "communication"
    ],
    "wof:name":"Infraforces Sarl",
    "wof:placetype":"venue"
},
  "geometry": {"coordinates":[2.307176,48.884514],"type":"Point"}
}