{
  "type": "Feature",
  "properties": {
    "iso:country":"FR",
    "sg:address":"100, Rue des 4 Termes, 13780 Aubagne",
    "sg:orig_category":"Unclassifiable Establishments",
    "sg:phone":"+33 4 42 70 03 81",
    "sg:province":"Picardie",
    "wof:name":"Agipa",
    "wof:placetype":"venue"
},
  "geometry": {"coordinates":[5.598311,43.288445],"type":"Point"}
}