{
  "type": "Feature",
  "properties": {
    "addr:full":"Domaine De Bayanne 26300 Alixan Rhone-Alpes 26300",
    "addr:postcode":"26300;26300",
    "iso:country":"FR",
    "sg:address":"Domaine De Bayanne 26300 Alixan",
    "sg:classifiers":[
        {
            "category":"Farming",
            "subcategory":"Farm",
            "type":"Manufacturing & Wholesale Goods"
        }
    ],
    "sg:phone":"+33 4 75 47 07 00",
    "sg:postcode":"26300",
    "sg:province":"Rhone-Alpes",
    "sg:tags":[
        "horticulture",
        "agriculture",
        "livestock"
    ],
    "wof:name":"Sa Domaine De Bayanne",
    "wof:placetype":"venue"
},
  "geometry": {"coordinates":[5.005035,45.002258],"type":"Point"}
}