{
  "type": "Feature",
  "properties": {
    "iso:country":"FR",
    "sg:address":"76, Rue de la Houve, 57150 Creutzwald",
    "sg:orig_category":"Non-Classified Establishments",
    "sg:phone":"+33 3 87 93 01 21",
    "sg:province":"Lorraine",
    "wof:name":"Niesner S.a.",
    "wof:placetype":"venue"
},
  "geometry": {"coordinates":[6.696407,49.210236],"type":"Point"}
}