{
  "type": "Feature",
  "properties": {
    "addr:full":"B.P. 34, 91223 Br\u00e9tigny sur Orge C\u00e9dex^^ZA des Cochets, 91220 Br\u00e9tigny sur Orge Ile de France 91220",
    "addr:postcode":"91223;91220;91220",
    "addr:street":"B.P. 34",
    "iso:country":"FR",
    "sg:address":"B.P. 34, 91223 Br\u00e9tigny sur Orge C\u00e9dex^^ZA des Cochets, 91220 Br\u00e9tigny sur Orge",
    "sg:orig_category":"Non-Classified Establishments",
    "sg:phone":"+33 1 69 88 39 00",
    "sg:postcode":"91220",
    "sg:province":"Ile de France",
    "wof:name":"Bomag S.a.f. S.a. - Soci\u00e9t\u00e9 Anonyme Fran\u00e7aise",
    "wof:placetype":"venue"
},
  "geometry": {"coordinates":[2.30564,48.604824],"type":"Point"}
}