{
  "type": "Feature",
  "properties": {
    "addr:full":"41 Ave. Montaigne; 75008 Paris Ile de France",
    "addr:postcode":"75008",
    "addr:street":"41 Ave. Montaigne",
    "iso:country":"FR",
    "sg:address":"41 Ave. Montaigne; 75008 Paris",
    "sg:classifiers":[
        {
            "category":"Industrial Area",
            "type":"Public Place"
        }
    ],
    "sg:phone":"+33 1 44 13 22 22",
    "sg:province":"Ile de France",
    "sg:tags":[
        "large",
        "private"
    ],
    "wof:name":"Groupe Arnault Sas",
    "wof:placetype":"venue"
},
  "geometry": {"coordinates":[2.306273,48.867268],"type":"Point"}
}