{
  "type": "Feature",
  "properties": {
    "iso:country":"FR",
    "sg:address":"148 Rue Haffreingue 62360 Pont De Briques",
    "sg:classifiers":[
        {
            "category":"Manufacturing",
            "subcategory":"Paper Products",
            "type":"Manufacturing & Wholesale Goods"
        }
    ],
    "sg:phone":"+33 3 21 87 41 30",
    "sg:province":"Nord Pas-de-Calais",
    "sg:tags":[
        "packaging",
        "material",
        "-",
        "cardboard"
    ],
    "wof:name":"Cartonnages Gaultier Sas",
    "wof:placetype":"venue"
},
  "geometry": {"coordinates":[1.621017,50.684578],"type":"Point"}
}