{
  "type": "Feature",
  "properties": {
    "iso:country":"FR",
    "sg:address":"Domaine de Clastron",
    "sg:city":"La Motte",
    "sg:orig_category":"Non-Classified Establishments",
    "sg:phone":"+33 4 94 70 24 57",
    "sg:postcode":"83920",
    "sg:province":"Provence-Alpes-C\u00f4te d'Azur",
    "wof:name":"Domaine De Clastron G.f.a.",
    "wof:placetype":"venue"
},
  "geometry": {"coordinates":[6.55536,43.492901],"type":"Point"}
}