{
  "type": "Feature",
  "properties": {
    "iso:country":"FR",
    "sg:address":"Dessy 74440 Mieussy",
    "sg:orig_category":"Unclassifiable Establishments",
    "sg:phone":"+33 4 50 43 03 06",
    "sg:postcode":"74440",
    "sg:province":"Rhone-Alpes",
    "wof:name":"Gay G\u00e9rard S.a.r.l.",
    "wof:placetype":"venue"
},
  "geometry": {"coordinates":[6.51889,46.127216],"type":"Point"}
}