{
  "type": "Feature",
  "properties": {
    "iso:country":"FR",
    "sg:address":"45 Av De Marseille 26000 Valence",
    "sg:classifiers":[
        {
            "category":"Banks & Credit Unions",
            "subcategory":"Investment Brokerage",
            "type":"Services"
        }
    ],
    "sg:phone":"+33 4 75 78 60 26",
    "sg:province":"Rhone-Alpes",
    "sg:tags":[
        "-",
        "transport",
        "related"
    ],
    "wof:name":"Mory Team",
    "wof:placetype":"venue"
},
  "geometry": {"coordinates":[4.881676,44.897144],"type":"Point"}
}