{
  "type": "Feature",
  "properties": {
    "addr:full":"Z Artisanale Bassilour 64210 Bidart Bidart Aquitaine 64210",
    "addr:postcode":"64210;64210",
    "iso:country":"FR",
    "sg:address":"Z Artisanale Bassilour 64210 Bidart",
    "sg:city":"Bidart",
    "sg:classifiers":[
        {
            "category":"Banks & Credit Unions",
            "subcategory":"Investment Brokerage",
            "type":"Services"
        }
    ],
    "sg:phone":"+33 5 59 54 66 66",
    "sg:postcode":"64210",
    "sg:province":"Aquitaine",
    "sg:tags":[
        "bag",
        "blood"
    ],
    "wof:name":"Technoflex Industries S.a.",
    "wof:placetype":"venue"
},
  "geometry": {"coordinates":[-1.573789,43.430237],"type":"Point"}
}