{
  "type": "Feature",
  "properties": {
    "addr:full":"La Moutonnerie 44450 St Julien De Concelles Pays de Loire 44450",
    "addr:postcode":"44450;44450",
    "addr:street":"St Julien De Concelles Pays",
    "iso:country":"FR",
    "sg:address":"La Moutonnerie 44450 St Julien De Concelles",
    "sg:classifiers":[
        {
            "category":"Farming",
            "subcategory":"Crops",
            "type":"Manufacturing & Wholesale Goods"
        }
    ],
    "sg:phone":"+33 2 40 54 11 11",
    "sg:postcode":"44450",
    "sg:province":"Pays de Loire",
    "sg:tags":[
        "vegetable",
        "fruit",
        "agriculture",
        "livestock"
    ],
    "wof:name":"Sa Robert",
    "wof:placetype":"venue"
},
  "geometry": {"coordinates":[-1.440544,47.240059],"type":"Point"}
}