{
  "type": "Feature",
  "properties": {
    "iso:country":"FR",
    "sg:address":"Quartier les Parans",
    "sg:city":"V\u00e9n\u00e9jan",
    "sg:orig_category":"Non-Classified Establishments",
    "sg:phone":"+33 4 66 79 21 76",
    "sg:postcode":"30200",
    "sg:province":"Languedoc-Roussillon",
    "wof:name":"C.i.m.e. S.a. - Compagnie Industrielle De Montage Et Entretien",
    "wof:placetype":"venue"
},
  "geometry": {"coordinates":[4.541553,44.125595],"type":"Point"}
}