{
  "type": "Feature",
  "properties": {
    "iso:country":"FR",
    "sg:address":"196, Ancienne Rte de Beaujeu, 69400 Gleiz\u00e9",
    "sg:orig_category":"Unclassifiable Establishments",
    "sg:phone":"+33 4 74 65 34 17",
    "sg:postcode":"69400",
    "sg:province":"Rhone-Alpes",
    "wof:name":"Pratica S.a.",
    "wof:placetype":"venue"
},
  "geometry": {"coordinates":[4.715217,46.0051],"type":"Point"}
}