{
  "type": "Feature",
  "properties": {
    "iso:country":"FR",
    "sg:address":"130, Rue de la Scierie, 88800 Vittel",
    "sg:orig_category":"Unclassifiable Establishments",
    "sg:phone":"+33 3 29 08 07 45",
    "sg:province":"Lorraine",
    "wof:name":"Caremat S.a.s.",
    "wof:placetype":"venue"
},
  "geometry": {"coordinates":[5.9599,48.200096],"type":"Point"}
}