{
  "type": "Feature",
  "properties": {
    "iso:country":"FR",
    "sg:address":"Rte Nationale 3",
    "sg:city":"Blesmes",
    "sg:orig_category":"Unclassifiable Establishments",
    "sg:phone":"+33 3 23 83 21 85",
    "sg:postcode":"02400",
    "sg:province":"Picardie",
    "wof:name":"Prat Henri Et Ses Fils Parcs Et Jardins Du Val De Marne S.a.r.l.",
    "wof:placetype":"venue"
},
  "geometry": {"coordinates":[3.44202,49.039574],"type":"Point"}
}