{
  "type": "Feature",
  "properties": {
    "addr:full":"2 Fbg Agnicourt 60110 Meru Picardie",
    "addr:housenumber":"2",
    "addr:postcode":"60110",
    "addr:street":"Fbg Agnicourt",
    "iso:country":"FR",
    "sg:address":"2 Fbg Agnicourt 60110 Meru",
    "sg:classifiers":[
        {
            "category":"Professional",
            "type":"Services"
        }
    ],
    "sg:phone":"+33 3 44 52 60 00",
    "sg:province":"Picardie",
    "sg:tags":[
        "transport",
        "road"
    ],
    "wof:name":"Prevote (transports) Sa",
    "wof:placetype":"venue"
},
  "geometry": {"coordinates":[2.136731,49.223248],"type":"Point"}
}