{
  "type": "Feature",
  "properties": {
    "iso:country":"FR",
    "sg:address":"340 Rue de la Gare; 74370 Pringy",
    "sg:classifiers":[
        {
            "category":"Industrial Area",
            "type":"Public Place"
        }
    ],
    "sg:phone":"+33 4 50 66 98 61",
    "sg:postcode":"74370",
    "sg:province":"Rhone-Alpes",
    "sg:tags":[
        "large",
        "private"
    ],
    "wof:name":"Blue Industries, Inc.",
    "wof:placetype":"venue"
},
  "geometry": {"coordinates":[6.124791,45.937958],"type":"Point"}
}