{
  "type": "Feature",
  "properties": {
    "addr:full":"14, Rue Br\u00e9montier, 75017 Paris Ile de France",
    "addr:housenumber":"14",
    "addr:postcode":"75017",
    "addr:street":"Rue Bre\u0301Montier",
    "iso:country":"FR",
    "sg:address":"14, Rue Br\u00e9montier, 75017 Paris",
    "sg:orig_category":"Unclassifiable Establishments",
    "sg:phone":"+33 1 47 63 27 97",
    "sg:province":"Ile de France",
    "wof:name":"G\u00e9nie Sanitaire S.a.r.l.",
    "wof:placetype":"venue"
},
  "geometry": {"coordinates":[2.304013,48.884876],"type":"Point"}
}