{
  "type": "Feature",
  "properties": {
    "iso:country":"FR",
    "sg:address":"B.P. 102, 07430 Dav\u00e9zieux C\u00e9dex^^ZI de la Lombardi\u00e8re, 07430 Dav\u00e9zieux",
    "sg:orig_category":"Non-Classified Establishments",
    "sg:phone":"+33 4 75 69 32 32",
    "sg:postcode":"07430",
    "sg:province":"Rhone-Alpes",
    "wof:name":"Brossier S.a.s.",
    "wof:placetype":"venue"
},
  "geometry": {"coordinates":[4.7076,45.255531],"type":"Point"}
}