{
  "type": "Feature",
  "properties": {
    "addr:full":"Parc D'Activit\u00e9s Du Sandholz Rn 62 67110 Niederbronn Les Bains Dambach Alsace 67110",
    "addr:postcode":"67110;67110",
    "addr:street":"Rn 62",
    "iso:country":"FR",
    "sg:address":"Parc D'Activit\u00e9s Du Sandholz Rn 62 67110 Niederbronn Les Bains",
    "sg:city":"Dambach",
    "sg:classifiers":[
        {
            "category":"Manufacturing",
            "subcategory":"Metals",
            "type":"Manufacturing & Wholesale Goods"
        }
    ],
    "sg:phone":"+33 3 88 05 89 89",
    "sg:postcode":"67110",
    "sg:province":"Alsace",
    "sg:tags":[
        "metallurgy",
        "metalworking",
        "processing"
    ],
    "wof:name":"Ernst Decoupage Emboutissage",
    "wof:placetype":"venue"
},
  "geometry": {"coordinates":[7.644521,48.931374],"type":"Point"}
}