{
  "type": "Feature",
  "properties": {
    "addr:full":"3, Bd Georges Cl\u00e9menceau, 17340 Ch\u00e2telaillon Plage Poitou-Charentes",
    "addr:housenumber":"3",
    "addr:postcode":"17340",
    "addr:street":"Bd Georges Cle\u0301Menceau;Plage",
    "iso:country":"FR",
    "sg:address":"3, Bd Georges Cl\u00e9menceau, 17340 Ch\u00e2telaillon Plage",
    "sg:orig_category":"Unclassifiable Establishments",
    "sg:phone":"+33 5 46 56 16 44",
    "sg:province":"Poitou-Charentes",
    "wof:name":"A.d.f. S.a. - Agglom\u00e9r\u00e9 Dominique Faltot",
    "wof:placetype":"venue"
},
  "geometry": {"coordinates":[-1.081734,46.073238],"type":"Point"}
}