{
  "type": "Feature",
  "properties": {
    "iso:country":"FR",
    "sg:address":"97, Av. de T\u00e9cheney, 33370 Artigues pr\u00e8s Bordeaux",
    "sg:city":"Artigues-pr\u00e8s-Bordeaux",
    "sg:orig_category":"Unclassifiable Establishments",
    "sg:phone":"+33 5 56 31 67 28",
    "sg:postcode":"33370",
    "sg:province":"Aquitaine",
    "wof:name":"Sobeca S.a.",
    "wof:placetype":"venue"
},
  "geometry": {"coordinates":[-0.489383,44.874207],"type":"Point"}
}