{
  "type": "Feature",
  "properties": {
    "addr:full":"ZA les Planques Lamonzie Saint Martin Aquitaine 24680",
    "addr:postcode":"24680",
    "addr:street":"Za Les;Lamonzie",
    "iso:country":"FR",
    "sg:address":"ZA les Planques",
    "sg:city":"Lamonzie Saint Martin",
    "sg:orig_category":"Unclassifiable Establishments",
    "sg:phone":"+33 5 53 24 28 71",
    "sg:postcode":"24680",
    "sg:province":"Aquitaine",
    "wof:name":"Etablissement Villegente S.a.r.l.",
    "wof:placetype":"venue"
},
  "geometry": {"coordinates":[0.380631,44.842701],"type":"Point"}
}