{
  "type": "Feature",
  "properties": {
    "addr:full":"31, Rue du Lieutenant G\u00e9n\u00e9ral Eysseric, 73200 Albertville Rhone-Alpes 73200",
    "addr:housenumber":"31",
    "addr:postcode":"73200;73200",
    "addr:street":"Rue Du Lieutenant Ge\u0301Ne\u0301Ral Eysseric",
    "iso:country":"FR",
    "sg:address":"31, Rue du Lieutenant G\u00e9n\u00e9ral Eysseric, 73200 Albertville",
    "sg:orig_category":"Non-Classified Establishments",
    "sg:phone":"+33 4 79 31 16 00",
    "sg:postcode":"73200",
    "sg:province":"Rhone-Alpes",
    "wof:name":"B.m.r.a.",
    "wof:placetype":"venue"
},
  "geometry": {"coordinates":[6.398158,45.663372],"type":"Point"}
}