{
  "type": "Feature",
  "properties": {
    "addr:full":"300 Rue Roland Garros Esplanade Comm Frejorgues Ouest 34130 Mauguio Languedoc-Roussillon 34130",
    "addr:housenumber":"300",
    "addr:postcode":"34130;34130",
    "addr:street":"Rue Roland Garros Esplanade Comm Frejorgues Ouest",
    "iso:country":"FR",
    "sg:address":"300 Rue Roland Garros Esplanade Comm Frejorgues Ouest 34130 Mauguio",
    "sg:classifiers":[
        {
            "category":"Manufacturing",
            "subcategory":"Chemicals & Compounds",
            "type":"Manufacturing & Wholesale Goods"
        }
    ],
    "sg:phone":"+33 4 99 13 39 11",
    "sg:postcode":"34130",
    "sg:province":"Languedoc-Roussillon",
    "sg:tags":[
        "pharmaceutical",
        "chemistry",
        "-",
        "by-product"
    ],
    "wof:name":"Bio Uv Specialiste Du Traitement Des Eaux (bio Uv)",
    "wof:placetype":"venue"
},
  "geometry": {"coordinates":[4.0079,43.617867],"type":"Point"}
}