{
  "type": "Feature",
  "properties": {
    "addr:full":"Lieu Dit Les Mesers 74450 St Jean De Sixt Rhone-Alpes 74450",
    "addr:postcode":"74450;74450",
    "addr:street":"Lieu Dit Les Mesers;Rhone-Alpes",
    "iso:country":"FR",
    "sg:address":"Lieu Dit Les Mesers 74450 St Jean De Sixt",
    "sg:classifiers":[
        {
            "category":"Home & Garden",
            "subcategory":"Furniture",
            "type":"Retail Goods"
        }
    ],
    "sg:phone":"+33 4 50 02 23 34",
    "sg:postcode":"74450",
    "sg:province":"Rhone-Alpes",
    "sg:tags":[
        "household",
        "wood"
    ],
    "wof:name":"Meubles Montagnards",
    "wof:placetype":"venue"
},
  "geometry": {"coordinates":[6.409583,45.92234],"type":"Point"}
}