{
  "type": "Feature",
  "properties": {
    "addr:full":"38160 Chevrieres Rhone-Alpes 38160",
    "addr:housenumber":"38160",
    "addr:postcode":"38160",
    "addr:street":"Chevrieres Rhone-Alpes",
    "iso:country":"FR",
    "sg:address":"38160 Chevrieres",
    "sg:classifiers":[
        {
            "category":"Food & Beverages",
            "subcategory":"Dairy",
            "type":"Retail Goods"
        }
    ],
    "sg:phone":"+33 4 76 64 13 97",
    "sg:postcode":"38160",
    "sg:province":"Rhone-Alpes",
    "sg:tags":[
        "product",
        "related"
    ],
    "wof:name":"Ets R Cholet",
    "wof:placetype":"venue"
},
  "geometry": {"coordinates":[5.290652,45.187851],"type":"Point"}
}