{
  "type": "Feature",
  "properties": {
    "iso:country":"FR",
    "sg:address":"5/7, Rue de Bretagne - ZI des B\u00e9thunes, 95310 Saint Ouen l'Aum\u00f4ne",
    "sg:orig_category":"Unclassifiable Establishments",
    "sg:phone":"+33 1 34 32 38 00",
    "sg:province":"Ile de France",
    "wof:name":"A.m.p.e.r.e Industrie S.a.",
    "wof:placetype":"venue"
},
  "geometry": {"coordinates":[0.113387,48.415726],"type":"Point"}
}