{
  "type": "Feature",
  "properties": {
    "iso:country":"FR",
    "sg:address":"4-8 Quai De Seine 93584 St-Ouen Cedex",
    "sg:classifiers":[
        {
            "category":"Manufacturing",
            "subcategory":"Rubber & Plastics",
            "type":"Manufacturing & Wholesale Goods"
        }
    ],
    "sg:phone":"+33 1 40 12 02 34",
    "sg:province":"Ile-de-France",
    "wof:name":"Gremco Sa",
    "wof:placetype":"venue"
},
  "geometry": {"coordinates":[2.315616,48.913425],"type":"Point"}
}