{
  "type": "Feature",
  "properties": {
    "iso:country":"FR",
    "sg:address":"23, Rue Choiseul, 75002 Paris",
    "sg:orig_category":"Unclassifiable Establishments",
    "sg:phone":"+33 1 49 24 92 56",
    "sg:province":"Ile de France",
    "wof:name":"Imprimerie De L'indre S.a.",
    "wof:placetype":"venue"
},
  "geometry": {"coordinates":[2.335757,48.870678],"type":"Point"}
}