{
  "type": "Feature",
  "properties": {
    "addr:full":"Aeroport Nice 06281 Nice Rhone-Alpes",
    "addr:postcode":"06281",
    "addr:street":"Aeroport",
    "iso:country":"FR",
    "sg:address":"Aeroport Nice 06281 Nice",
    "sg:orig_category":"Customs Agencies, Declarants",
    "sg:phone":"+33 4 93 21 35 55",
    "sg:province":"Rhone-Alpes",
    "wof:name":"Ste Blue Trans Air Services Sarl",
    "wof:placetype":"venue"
},
  "geometry": {"coordinates":[7.26627,43.703388],"type":"Point"}
}