{
  "type": "Feature",
  "properties": {
    "iso:country":"FR",
    "sg:address":"129, Rue Bannier, 45057 Orl\u00e9ans C\u00e9dex 1",
    "sg:orig_category":"Non-Classified Establishments",
    "sg:phone":"+33 2 38 53 60 00",
    "sg:province":"Centre",
    "wof:name":"Sopep S.a.",
    "wof:placetype":"venue"
},
  "geometry": {"coordinates":[1.901611,47.906712],"type":"Point"}
}