{
  "type": "Feature",
  "properties": {
    "addr:full":"B.P. 30, 95250 Beauchamp C\u00e9dex^^208bis, Chauss\u00e9e Jules C\u00e9sar, 95250 Beauchamp Ile de France 95250",
    "addr:postcode":"95250 beauchamp ce\u0301dex^^208bis;95250;ile;95250",
    "addr:street":"B.P. 30;Chausse\u0301E Jules Ce\u0301Sar;France",
    "iso:country":"FR",
    "sg:address":"B.P. 30, 95250 Beauchamp C\u00e9dex^^208bis, Chauss\u00e9e Jules C\u00e9sar, 95250 Beauchamp",
    "sg:orig_category":"Non-Classified Establishments",
    "sg:phone":"+33 1 34 18 96 96",
    "sg:postcode":"95250",
    "sg:province":"Ile de France",
    "wof:name":"C.g.r. Roulements S.n.c.",
    "wof:placetype":"venue"
},
  "geometry": {"coordinates":[2.198048,49.009228],"type":"Point"}
}