{
  "type": "Feature",
  "properties": {
    "iso:country":"FR",
    "sg:address":"B.P. 30, 95250 Beauchamp C\u00e9dex^^208bis, Chauss\u00e9e Jules C\u00e9sar, 95250 Beauchamp",
    "sg:orig_category":"Non-Classified Establishments",
    "sg:phone":"+33 1 34 18 96 96",
    "sg:postcode":"95250",
    "sg:province":"Ile de France",
    "wof:name":"C.g.r. Roulements S.n.c.",
    "wof:placetype":"venue"
},
  "geometry": {"coordinates":[2.198048,49.009228],"type":"Point"}
}