{
  "type": "Feature",
  "properties": {
    "addr:full":"136 av Franklin Roosevelt; Bron Rhone-Alpes",
    "addr:street":"136 Av Franklin Roosevelt Bron Rhone-Alpes",
    "iso:country":"FR",
    "sg:address":"136 av Franklin Roosevelt; Bron",
    "sg:classifiers":[
        {
            "category":"Banks & Credit Unions",
            "subcategory":"Bank",
            "type":"Services"
        }
    ],
    "sg:phone":"+33 3378411600",
    "sg:province":"Rhone-Alpes",
    "wof:name":"Cr\u00e9dit Mutuel De Bron",
    "wof:placetype":"venue"
},
  "geometry": {"coordinates":[-73.923248,40.825745],"type":"Point"}
}