{
  "type": "Feature",
  "properties": {
    "iso:country":"FR",
    "sg:address":"Villa aux Nonains 28250 Senonches",
    "sg:city":"Senonches",
    "sg:orig_category":"Non-Classified Establishments",
    "sg:phone":"+33 2 37 53 52 98",
    "sg:postcode":"28250",
    "sg:province":"Centre",
    "wof:name":"L'esprit Et Le Vin S.a.",
    "wof:placetype":"venue"
},
  "geometry": {"coordinates":[1.08708,48.554508],"type":"Point"}
}