{
  "type": "Feature",
  "properties": {
    "addr:full":"Moye 44220 Cou\u00ebron Pays de Loire",
    "addr:postcode":"44220",
    "addr:street":"Moye",
    "iso:country":"FR",
    "sg:address":"Moye 44220 Cou\u00ebron",
    "sg:orig_category":"Unclassifiable Establishments",
    "sg:phone":"+33 2 40 38 09 00",
    "sg:province":"Pays de Loire",
    "wof:name":"Trafat S.a.r.l.",
    "wof:placetype":"venue"
},
  "geometry": {"coordinates":[-1.69959,47.23848],"type":"Point"}
}