{
  "type": "Feature",
  "properties": {
    "addr:full":"Rn 152 Les Contres Ouches 45300 Manchecourt Courcelles Centre 45300",
    "addr:postcode":"45300;45300",
    "addr:street":"Rn 152 Les;Courcelles",
    "iso:country":"FR",
    "sg:address":"Rn 152 Les Contres Ouches 45300 Manchecourt",
    "sg:city":"Courcelles",
    "sg:classifiers":[
        {
            "category":"Manufacturing",
            "subcategory":"Printing",
            "type":"Manufacturing & Wholesale Goods"
        }
    ],
    "sg:phone":"+33 2 38 34 54 54",
    "sg:postcode":"45300",
    "sg:province":"Centre",
    "sg:tags":[
        "publishing"
    ],
    "wof:name":"Maury Imprimeur",
    "wof:placetype":"venue"
},
  "geometry": {"coordinates":[2.21384,48.064007],"type":"Point"}
}