{
  "type": "Feature",
  "properties": {
    "addr:full":"B.P. 94, 38503 Voiron C\u00e9dex^^6, Av. des Fr\u00e8res Tardy, 38500 Voiron Rhone-Alpes 38500",
    "addr:postcode":"38503;38500;38500",
    "addr:street":"B.P. 94;Av. Des Fre\u0300Res Tardy",
    "iso:country":"FR",
    "sg:address":"B.P. 94, 38503 Voiron C\u00e9dex^^6, Av. des Fr\u00e8res Tardy, 38500 Voiron",
    "sg:orig_category":"Non-Classified Establishments",
    "sg:phone":"+33 4 76 67 08 00",
    "sg:postcode":"38500",
    "sg:province":"Rhone-Alpes",
    "wof:name":"Cr\u00e9dit Agricole Sud Rh\u00f4ne Alpes",
    "wof:placetype":"venue"
},
  "geometry": {"coordinates":[5.621252,45.335114],"type":"Point"}
}