{
  "type": "Feature",
  "properties": {
    "iso:country":"FR",
    "sg:address":"15 Rue Georges Cl\u00e9menceau 91405 Orsay Cedex",
    "sg:classifiers":[
        {
            "category":"Professional",
            "subcategory":"Business Services",
            "type":"Services"
        }
    ],
    "sg:phone":"+33 1 69 15 67 50",
    "sg:province":"Champagne",
    "sg:tags":[
        "training",
        "advice"
    ],
    "wof:name":"Universite De Paris Xi Paris Sud",
    "wof:placetype":"venue"
},
  "geometry": {"coordinates":[-118.444366,34.202679],"type":"Point"}
}