{
  "type": "Feature",
  "properties": {
    "iso:country":"FR",
    "sg:address":"Cd 18 83430 St Mandrier Sur Mer",
    "sg:classifiers":[
        {
            "category":"Autos & Motor Vehicles",
            "subcategory":"Boat Sales",
            "type":"Retail Goods"
        }
    ],
    "sg:phone":"+33 4 94 30 54 94",
    "sg:province":"Centre",
    "sg:tags":[
        "equipment",
        "transport"
    ],
    "wof:name":"International Marine Services Sa",
    "wof:placetype":"venue"
},
  "geometry": {"coordinates":[5.905695,43.07711],"type":"Point"}
}