{
  "type": "Feature",
  "properties": {
    "addr:full":"1 Rue Du Marechal Foch 10300 Ste Savine Champagne 10300",
    "addr:housenumber":"1",
    "addr:postcode":"10300;10300",
    "addr:street":"Rue Du Marechal Foch",
    "iso:country":"FR",
    "sg:address":"1 Rue Du Marechal Foch 10300 Ste Savine",
    "sg:classifiers":[
        {
            "category":"Shopping",
            "subcategory":"Crafts & Fabrics",
            "type":"Retail Goods"
        }
    ],
    "sg:phone":"+33 3 25 79 05 03",
    "sg:postcode":"10300",
    "sg:province":"Champagne",
    "sg:tags":[
        "textile",
        "clothing"
    ],
    "wof:name":"Atelier De Broderie Et Impression Sur Textiles (abitex)",
    "wof:placetype":"venue"
},
  "geometry": {"coordinates":[4.050356,48.293156],"type":"Point"}
}