{
  "type": "Feature",
  "properties": {
    "addr:full":"B.P. 605, 59061 Roubaix C\u00e9dex 1^^15, Av. des Paraboles, 59000 Roubaix Nord Pas-de-Calais",
    "addr:housenumber":"b.p. 605;1;^ 15",
    "addr:postcode":"59061;59000",
    "addr:street":"^;Av. Des Paraboles",
    "iso:country":"FR",
    "sg:address":"B.P. 605, 59061 Roubaix C\u00e9dex 1^^15, Av. des Paraboles, 59000 Roubaix",
    "sg:orig_category":"Non-Classified Establishments",
    "sg:phone":"+33 3 20 20 57 57",
    "sg:province":"Nord Pas-de-Calais",
    "wof:name":"S.r.t.p. S.n.c. - Soci\u00e9t\u00e9 De Routes Et De Travaux Publics",
    "wof:placetype":"venue"
},
  "geometry": {"coordinates":[3.17924,50.694778],"type":"Point"}
}