{
  "type": "Feature",
  "properties": {
    "iso:country":"FR",
    "sg:address":"Route Jargeau 45300 Ascoux",
    "sg:city":"Courcelles",
    "sg:classifiers":[
        {
            "category":"Manufacturing",
            "subcategory":"Paper Products",
            "type":"Manufacturing & Wholesale Goods"
        }
    ],
    "sg:phone":"+33 2 38 33 00 04",
    "sg:postcode":"45300",
    "sg:province":"Centre",
    "sg:tags":[
        "packaging",
        "material",
        "-",
        "cardboard"
    ],
    "wof:name":"Printor Packaging Sa",
    "wof:placetype":"venue"
},
  "geometry": {"coordinates":[2.25113,48.121426],"type":"Point"}
}