{
  "type": "Feature",
  "properties": {
    "addr:full":"20, Rue des Boeufs - ZA Les Bosquets, 95540 M\u00e9ry sur Oise Ile de France",
    "addr:housenumber":"20",
    "addr:postcode":"95540",
    "addr:street":"Rue Des Boeufs Za Les Bosquets",
    "iso:country":"FR",
    "sg:address":"20, Rue des Boeufs - ZA Les Bosquets, 95540 M\u00e9ry sur Oise",
    "sg:orig_category":"Unclassifiable Establishments",
    "sg:phone":"+33 1 34 48 17 77",
    "sg:province":"Ile de France",
    "wof:name":"A.l.m. S.a.r.l. - Accessoires Levage Manutention",
    "wof:placetype":"venue"
},
  "geometry": {"coordinates":[2.185465,49.064209],"type":"Point"}
}