{
  "type": "Feature",
  "properties": {
    "addr:full":"16/18, Rue de la Poterie, 93200 Saint Denis Ile de France",
    "addr:housenumber":"16 / 18",
    "addr:postcode":"93200",
    "addr:street":"Rue De La Poterie",
    "iso:country":"FR",
    "sg:address":"16/18, Rue de la Poterie, 93200 Saint Denis",
    "sg:orig_category":"Unclassifiable Establishments",
    "sg:phone":"+33 1 49 71 95 00",
    "sg:province":"Ile de France",
    "wof:name":"H.t.f. S.a.r.l. - High Tech Fournitures",
    "wof:placetype":"venue"
},
  "geometry": {"coordinates":[2.346922,48.944305],"type":"Point"}
}