{
  "type": "Feature",
  "properties": {
    "addr:full":"Rue Lavoisier - Z.I. Morhange Lorraine 57340",
    "addr:postcode":"57340",
    "addr:street":"Rue Lavoisier",
    "iso:country":"FR",
    "sg:address":"Rue Lavoisier - Z.I.",
    "sg:city":"Morhange",
    "sg:orig_category":"Unclassifiable Establishments",
    "sg:phone":"+33 3 87 86 16 13",
    "sg:postcode":"57340",
    "sg:province":"Lorraine",
    "wof:name":"Ackermann S.a.",
    "wof:placetype":"venue"
},
  "geometry": {"coordinates":[6.63812,48.917282],"type":"Point"}
}