{
  "type": "Feature",
  "properties": {
    "iso:country":"FR",
    "sg:address":"47 bd Georges Cl\u00e9menceau 92400 Courbevoie",
    "sg:classifiers":[
        {
            "category":"Autos & Motor Vehicles",
            "subcategory":"Motorcycle Sales",
            "type":"Retail Goods"
        }
    ],
    "sg:phone":"+33 1 46 91 66 68",
    "sg:postcode":"92400",
    "sg:province":"Ile de France",
    "sg:tags":[
        "battery",
        "car"
    ],
    "wof:name":"Vb Autobatterie S.a.",
    "wof:placetype":"venue"
},
  "geometry": {"coordinates":[2.269299,48.903046],"type":"Point"}
}