{
  "type": "Feature",
  "properties": {
    "addr:full":"Route De Chatres 10170 MESGRIGNY Champagne",
    "addr:postcode":"10170",
    "addr:street":"Route De Chatres",
    "iso:country":"FR",
    "sg:address":"Route De Chatres 10170 MESGRIGNY",
    "sg:classifiers":[
        {
            "category":"Manufacturing",
            "subcategory":"Wood Products",
            "type":"Manufacturing & Wholesale Goods"
        }
    ],
    "sg:phone":"+33 3 25 21 12 57",
    "sg:province":"Champagne",
    "sg:tags":[
        "pallet",
        "made"
    ],
    "wof:name":"Mery Palettes S.a.r.l.",
    "wof:placetype":"venue"
},
  "geometry": {"coordinates":[3.88246,48.487019],"type":"Point"}
}