{
  "type": "Feature",
  "properties": {
    "addr:full":"1 Rue Le Notre 95190 Goussainville Ile de France 95190",
    "addr:housenumber":"1",
    "addr:postcode":"95190;95190",
    "addr:street":"Rue Le Notre",
    "iso:country":"FR",
    "sg:address":"1 Rue Le Notre 95190 Goussainville",
    "sg:classifiers":[
        {
            "category":"Professional",
            "subcategory":"Engineering",
            "type":"Services"
        }
    ],
    "sg:phone":"+33 1 39 88 63 00",
    "sg:postcode":"95190",
    "sg:province":"Ile de France",
    "sg:tags":[
        "machine",
        "-",
        "mechanical"
    ],
    "wof:name":"Modulfroid Service Sarl",
    "wof:placetype":"venue"
},
  "geometry": {"coordinates":[2.459801,49.019005],"type":"Point"}
}