{
  "type": "Feature",
  "properties": {
    "addr:full":"93, Rte de Metz, 54320 Max\u00e9ville Lorraine",
    "addr:housenumber":"93",
    "addr:postcode":"54320",
    "addr:street":"Rte De Metz",
    "iso:country":"FR",
    "sg:address":"93, Rte de Metz, 54320 Max\u00e9ville",
    "sg:orig_category":"Unclassifiable Establishments",
    "sg:phone":"+33 3 83 35 62 12",
    "sg:province":"Lorraine",
    "wof:name":"Autom\u00e9lor",
    "wof:placetype":"venue"
},
  "geometry": {"coordinates":[6.167668,48.711975],"type":"Point"}
}