{
  "type": "Feature",
  "properties": {
    "addr:full":"Rn 191 Moulin Du Tan 78580 Maule Ile de France 78580",
    "addr:postcode":"78580;78580",
    "addr:street":"Rn 191;Ile De France",
    "iso:country":"FR",
    "sg:address":"Rn 191 Moulin Du Tan 78580 Maule",
    "sg:classifiers":[
        {
            "category":"Manufacturing",
            "subcategory":"Tools & Machinery",
            "type":"Manufacturing & Wholesale Goods"
        }
    ],
    "sg:phone":"+33 1 34 75 08 40",
    "sg:postcode":"78580",
    "sg:province":"Ile de France",
    "sg:tags":[
        "metallurgy",
        "household",
        "wood",
        "metalworking",
        "furniture"
    ],
    "wof:name":"Strauss Vonderweidt Et Cie",
    "wof:placetype":"venue"
},
  "geometry": {"coordinates":[1.85181,48.909134],"type":"Point"}
}