{
  "type": "Feature",
  "properties": {
    "iso:country":"FR",
    "sg:address":"Route De Cambo 64100 Bayonne",
    "sg:city":"Bayonne",
    "sg:classifiers":[
        {
            "category":"Autos & Motor Vehicles",
            "subcategory":"Automobile Sales",
            "type":"Retail Goods"
        }
    ],
    "sg:phone":"+33 5 59 42 46 46",
    "sg:postcode":"64100",
    "sg:province":"Aquitaine",
    "sg:tags":[
        "equipment",
        "motor-cars",
        "transport"
    ],
    "wof:name":"Rgm Imola (jaguar Ferrari Maserati)",
    "wof:placetype":"venue"
},
  "geometry": {"coordinates":[-1.495834,43.466091],"type":"Point"}
}