{
  "type": "Feature",
  "properties": {
    "addr:full":"2 rue Persil 30300 BEAUCAIRE Languedoc-Roussillon 30300",
    "addr:housenumber":"2",
    "addr:postcode":"30300;30300",
    "addr:street":"Rue Persil",
    "iso:country":"FR",
    "sg:address":"2 rue Persil 30300 BEAUCAIRE",
    "sg:classifiers":[
        {
            "category":"Wholesale",
            "subcategory":"Home Furnishings",
            "type":"Manufacturing & Wholesale Goods"
        }
    ],
    "sg:phone":"+33 4 66 59 12 00",
    "sg:postcode":"30300",
    "sg:province":"Languedoc-Roussillon",
    "sg:tags":[
        "chair"
    ],
    "wof:name":"Sabatier Et Navarro S.a.r.l.",
    "wof:placetype":"venue"
},
  "geometry": {"coordinates":[4.645113,43.804852],"type":"Point"}
}