{
  "type": "Feature",
  "properties": {
    "addr:full":"ZA De La Nouvelle Energie 59560 Comines Nord Pas-de-Calais 59560",
    "addr:postcode":"59560;59560",
    "addr:street":"Za De La Nouvelle Energie",
    "iso:country":"FR",
    "sg:address":"ZA De La Nouvelle Energie 59560 Comines",
    "sg:classifiers":[
        {
            "category":"Wholesale",
            "subcategory":"Machinery & Supplies",
            "type":"Manufacturing & Wholesale Goods"
        }
    ],
    "sg:phone":"+33 3 20 39 03 33",
    "sg:postcode":"59560",
    "sg:province":"Nord Pas-de-Calais",
    "sg:tags":[
        "agricultural",
        "equipment"
    ],
    "wof:name":"Grimme France Sarl",
    "wof:placetype":"venue"
},
  "geometry": {"coordinates":[3.006479,50.764984],"type":"Point"}
}