{
  "type": "Feature",
  "properties": {
    "iso:country":"FR",
    "sg:address":"B.P. 432, 62225 Calais C\u00e9dex^^15, Rue Mal de Lattre de Tassigny, 62100 Calais",
    "sg:orig_category":"Non-Classified Establishments",
    "sg:phone":"+33 3 21 34 61 56",
    "sg:postcode":"62100",
    "sg:province":"Nord Pas-de-Calais",
    "wof:name":"Boitard, Pruvost Et Herbaut S.a.",
    "wof:placetype":"venue"
},
  "geometry": {"coordinates":[1.85305,50.953079],"type":"Point"}
}