{
  "type": "Feature",
  "properties": {
    "addr:full":"Rue Jean-Baptiste Macaux Lumbres Nord Pas-de-Calais 62380",
    "addr:postcode":"62380",
    "addr:street":"Rue Jean-Baptiste Macaux Lumbres Nord",
    "iso:country":"FR",
    "sg:address":"Rue Jean-Baptiste Macaux",
    "sg:city":"Lumbres",
    "sg:orig_category":"Non-Classified Establishments",
    "sg:phone":"+33 3 21 38 11 11",
    "sg:postcode":"62380",
    "sg:province":"Nord Pas-de-Calais",
    "wof:name":"Ciments D'origny S.a.",
    "wof:placetype":"venue"
},
  "geometry": {"coordinates":[2.12301,50.708866],"type":"Point"}
}