{
  "type": "Feature",
  "properties": {
    "addr:full":"19 rue de l'Industrie 67721 HOERDT Hoerdt Alsace 67720",
    "addr:housenumber":"19",
    "addr:postcode":"67721;67720",
    "addr:street":"Rue De L'Industrie",
    "iso:country":"FR",
    "sg:address":"19 rue de l'Industrie 67721 HOERDT",
    "sg:city":"Hoerdt",
    "sg:classifiers":[
        {
            "category":"Food & Beverages",
            "subcategory":"Dairy",
            "type":"Retail Goods"
        }
    ],
    "sg:phone":"+33 3 88 69 22 00",
    "sg:postcode":"67720",
    "sg:province":"Alsace",
    "sg:tags":[
        "product",
        "milk"
    ],
    "wof:name":"Alsace Lait Coop",
    "wof:placetype":"venue"
},
  "geometry": {"coordinates":[7.795894,48.676208],"type":"Point"}
}