{
  "type": "Feature",
  "properties": {
    "iso:country":"FR",
    "sg:address":"B.P. 192, 59444 Wasquehal C\u00e9dex^^3, Av. D\u00e9sir\u00e9 Delsalle, 59444 Wasquehal",
    "sg:orig_category":"Non-Classified Establishments",
    "sg:phone":"+33 3 28 33 07 79",
    "sg:province":"Midi Pyr\u00e9n\u00e9es",
    "wof:name":"Chocodar S.a.",
    "wof:placetype":"venue"
},
  "geometry": {"coordinates":[3.12938,50.669281],"type":"Point"}
}