{
  "type": "Feature",
  "properties": {
    "addr:full":"331, Bd de la R\u00e9publique - Zone Industrielle B, 62232 Annezin Nord Pas-de-Calais",
    "addr:housenumber":"331;b",
    "addr:postcode":"62232",
    "addr:street":"Bd De La Re\u0301Publique;Industrielle",
    "iso:country":"FR",
    "sg:address":"331, Bd de la R\u00e9publique - Zone Industrielle B, 62232 Annezin",
    "sg:orig_category":"Unclassifiable Establishments",
    "sg:phone":"+33 3 21 57 26 57",
    "sg:province":"Nord Pas-de-Calais",
    "wof:name":"Euroben S.a.",
    "wof:placetype":"venue"
},
  "geometry": {"coordinates":[2.618587,50.532475],"type":"Point"}
}