{
  "type": "Feature",
  "properties": {
    "iso:country":"FR",
    "sg:address":"Rte De Dijon 70100 Arc Les Gray",
    "sg:classifiers":[
        {
            "category":"Home & Garden",
            "subcategory":"Furniture",
            "type":"Retail Goods"
        }
    ],
    "sg:phone":"+33 3 84 65 21 04",
    "sg:province":"Franche Comt\u00e9",
    "sg:tags":[
        "wood"
    ],
    "wof:name":"Bois Impregnes Sa",
    "wof:placetype":"venue"
},
  "geometry": {"coordinates":[5.575406,47.453815],"type":"Point"}
}