{
  "type": "Feature",
  "properties": {
    "addr:full":"46, Rte de Thionville, 57140 Woippy Lorraine",
    "addr:housenumber":"46",
    "addr:postcode":"57140",
    "addr:street":"Rte De Thionville",
    "iso:country":"FR",
    "sg:address":"46, Rte de Thionville, 57140 Woippy",
    "sg:orig_category":"Unclassifiable Establishments",
    "sg:phone":"+33 3 87 32 98 98",
    "sg:province":"Lorraine",
    "wof:name":"Lce - Brossette B.t.i. S.a.",
    "wof:placetype":"venue"
},
  "geometry": {"coordinates":[6.160028,49.148685],"type":"Point"}
}