{
  "type": "Feature",
  "properties": {
    "addr:full":"20 B Chem De Pitoys. Zi Maignon 64600 Anglet Anglet Aquitaine 64600",
    "addr:housenumber":"20 b",
    "addr:postcode":"64600;64600",
    "addr:street":"Chem De Pitoys. Zi Maignon",
    "iso:country":"FR",
    "sg:address":"20 B Chem De Pitoys. Zi Maignon 64600 Anglet",
    "sg:city":"Anglet",
    "sg:classifiers":[
        {
            "category":"Manufacturing",
            "subcategory":"Chemicals & Compounds",
            "type":"Manufacturing & Wholesale Goods"
        }
    ],
    "sg:phone":"+33 5 59 31 45 30",
    "sg:postcode":"64600",
    "sg:province":"Aquitaine",
    "sg:tags":[
        "pharmaceutical",
        "chemistry",
        "-",
        "by-product"
    ],
    "wof:name":"Euridep Direct Peintures",
    "wof:placetype":"venue"
},
  "geometry": {"coordinates":[-1.514707,43.481705],"type":"Point"}
}