{
  "type": "Feature",
  "properties": {
    "addr:full":"B.P. 6, 08090 Tournes^^ZI Tournes Cliron, 08090 Tournes Aiglemont Champagne 08090",
    "addr:housenumber":"6",
    "addr:postcode":"08090;08090;08090",
    "addr:street":"B.P.;Champagne",
    "iso:country":"FR",
    "sg:address":"B.P. 6, 08090 Tournes^^ZI Tournes Cliron, 08090 Tournes",
    "sg:city":"Aiglemont",
    "sg:orig_category":"Non-Classified Establishments",
    "sg:phone":"+33 3 24 52 92 43",
    "sg:postcode":"08090",
    "sg:province":"Champagne",
    "wof:name":"Batimetal S.a.r.l.",
    "wof:placetype":"venue"
},
  "geometry": {"coordinates":[4.667313,49.792923],"type":"Point"}
}