{
  "type": "Feature",
  "properties": {
    "addr:full":"13 rue des Fontaines du Temple 75003 Paris Ile de France 75003",
    "addr:housenumber":"13",
    "addr:postcode":"75003;75003",
    "addr:street":"Rue Des Fontaines Du Temple",
    "iso:country":"FR",
    "sg:address":"13 rue des Fontaines du Temple 75003 Paris",
    "sg:orig_category":"Furskins",
    "sg:phone":"+33 1 42 78 67 67",
    "sg:postcode":"75003",
    "sg:province":"Ile de France",
    "wof:name":"Pel Europ S.a.r.l.",
    "wof:placetype":"venue"
},
  "geometry": {"coordinates":[2.358867,48.865582],"type":"Point"}
}