{
  "type": "Feature",
  "properties": {
    "iso:country":"FR",
    "sg:address":"8, Rue Jules Rainu, 31200 Toulouse",
    "sg:orig_category":"Unclassifiable Establishments",
    "sg:phone":"+33 5 61 58 03 00",
    "sg:province":"Midi Pyr\u00e9n\u00e9es",
    "wof:name":"C.e.r.m. Sols S.a.r.l.",
    "wof:placetype":"venue"
},
  "geometry": {"coordinates":[1.47494,43.635006],"type":"Point"}
}