{
  "type": "Feature",
  "properties": {
    "addr:full":"24, Rue Emile Duchaux, 92150 Suresnes Ile de France 92150",
    "addr:housenumber":"24",
    "addr:postcode":"92150;ile;92150",
    "addr:street":"Rue Emile Duchaux;France",
    "iso:country":"FR",
    "sg:address":"24, Rue Emile Duchaux, 92150 Suresnes",
    "sg:orig_category":"Non-Classified Establishments",
    "sg:phone":"+33 1 42 04 53 76",
    "sg:postcode":"92150",
    "sg:province":"Ile de France",
    "wof:name":"Digital Services S.a.s.",
    "wof:placetype":"venue"
},
  "geometry": {"coordinates":[2.23467,48.878571],"type":"Point"}
}