{
  "type": "Feature",
  "properties": {
    "addr:full":"ZI De Thionville Nord Est 57971 YUTZ CEDEX Vill\u00e9 Alsace 67220",
    "addr:postcode":"57971;67220",
    "addr:street":"Zi De Thionville Nord Est",
    "iso:country":"FR",
    "sg:address":"ZI De Thionville Nord Est 57971 YUTZ CEDEX",
    "sg:city":"Vill\u00e9",
    "sg:classifiers":[
        {
            "category":"Autos & Motor Vehicles",
            "subcategory":"Auto Supplies",
            "type":"Retail Goods"
        }
    ],
    "sg:phone":"+33 3 82 55 92 86",
    "sg:postcode":"67220",
    "sg:province":"Alsace",
    "sg:tags":[
        "piston"
    ],
    "wof:name":"S.m.p. Sa",
    "wof:placetype":"venue"
},
  "geometry": {"coordinates":[6.1873,49.35741],"type":"Point"}
}