{
  "type": "Feature",
  "properties": {
    "addr:full":"1, Rue Saint Eloi, 71300 Montceau les Mines Saint-Berain-sous-Sanvignes Bourgogne 71300",
    "addr:housenumber":"1",
    "addr:postcode":"71300;71300",
    "addr:street":"Rue Saint Eloi;Bourgogne",
    "iso:country":"FR",
    "sg:address":"1, Rue Saint Eloi, 71300 Montceau les Mines",
    "sg:city":"Saint-Berain-sous-Sanvignes",
    "sg:orig_category":"Unclassifiable Establishments",
    "sg:phone":"+33 3 85 67 40 00",
    "sg:postcode":"71300",
    "sg:province":"Bourgogne",
    "wof:name":"Gega Electronique S.a.r.l.",
    "wof:placetype":"venue"
},
  "geometry": {"coordinates":[4.358706,46.674213],"type":"Point"}
}