{
  "type": "Feature",
  "properties": {
    "addr:full":"B.P. 10910 Tremblay en France Ile de France 93290",
    "addr:housenumber":"10910",
    "addr:postcode":"93290",
    "iso:country":"FR",
    "sg:address":"B.P. 10910",
    "sg:city":"Tremblay en France",
    "sg:orig_category":"Non-Classified Establishments",
    "sg:phone":"+33 1 49 19 21 09",
    "sg:postcode":"93290",
    "sg:province":"Ile de France",
    "wof:name":"Moog S.a.",
    "wof:placetype":"venue"
},
  "geometry": {"coordinates":[2.56727,48.951214],"type":"Point"}
}