{
  "type": "Feature",
  "properties": {
    "iso:country":"FR",
    "sg:address":"7, Rue des Tilleuls, 51130 Pierre Morains",
    "sg:orig_category":"Non-Classified Establishments",
    "sg:phone":"+33 3 26 52 11 62",
    "sg:province":"Champagne",
    "wof:name":"Mafroco S.a.r.l.",
    "wof:placetype":"venue"
},
  "geometry": {"coordinates":[4.027029,48.837803],"type":"Point"}
}