{
  "type": "Feature",
  "properties": {
    "iso:country":"FR",
    "sg:address":"93",
    "sg:city":"Andr\u00e9 Marie Amp\u00e8re 53000 Laval",
    "sg:classifiers":[
        {
            "category":"Professional",
            "type":"Services"
        }
    ],
    "sg:phone":"+33 2 43 59 28 59",
    "sg:province":"Pays de Loire",
    "sg:tags":[
        "transport",
        "road"
    ],
    "wof:name":"T.r.m. (transports Rapide Du Maine)",
    "wof:placetype":"venue"
},
  "geometry": {"coordinates":[-0.756451,48.036293],"type":"Point"}
}