{
  "type": "Feature",
  "properties": {
    "iso:country":"FR",
    "sg:address":"755, Av. Ambroise Croizat - ZI, 38920 Crolles",
    "sg:city":"Crolles",
    "sg:orig_category":"Unclassifiable Establishments",
    "sg:phone":"+33 4 76 08 18 16",
    "sg:postcode":"38190",
    "sg:province":"Rhone-Alpes",
    "wof:name":"Raisonance S.a.",
    "wof:placetype":"venue"
},
  "geometry": {"coordinates":[5.884878,45.2854],"type":"Point"}
}