{
  "type": "Feature",
  "properties": {
    "addr:full":"39 Rue Moulin 59710 Ennevelin Nord Pas-de-Calais",
    "addr:housenumber":"39",
    "addr:postcode":"59710",
    "addr:street":"Rue Moulin",
    "iso:country":"FR",
    "sg:address":"39 Rue Moulin 59710 Ennevelin",
    "sg:classifiers":[
        {
            "category":"Home & Garden",
            "subcategory":"Furniture",
            "type":"Retail Goods"
        }
    ],
    "sg:phone":"+33 3 20 61 92 92",
    "sg:province":"Nord Pas-de-Calais",
    "sg:tags":[
        "wood"
    ],
    "wof:name":"Sodim Sa",
    "wof:placetype":"venue"
},
  "geometry": {"coordinates":[3.121399,50.541355],"type":"Point"}
}