{
  "type": "Feature",
  "properties": {
    "addr:full":"Av. Sevreau Niort Poitou-Charentes 79000",
    "addr:postcode":"79000",
    "addr:street":"Av. Sevreau Niort",
    "iso:country":"FR",
    "sg:address":"Av. Sevreau",
    "sg:city":"Niort",
    "sg:orig_category":"Unclassifiable Establishments",
    "sg:phone":"+33 5 49 73 47 42",
    "sg:postcode":"79000",
    "sg:province":"Poitou-Charentes",
    "wof:name":"Ang\u00e9lique De Niort Thonnard S.a.r.l.",
    "wof:placetype":"venue"
},
  "geometry": {"coordinates":[-0.509566,46.314461],"type":"Point"}
}