{
  "type": "Feature",
  "properties": {
    "iso:country":"FR",
    "sg:address":"54, Av. de Bonaventure, 84000 Avignon",
    "sg:orig_category":"Unclassifiable Establishments",
    "sg:phone":"+33 4 90 86 64 39",
    "sg:province":"Bourgogne",
    "wof:name":"Sonito",
    "wof:placetype":"venue"
},
  "geometry": {"coordinates":[4.833732,43.955296],"type":"Point"}
}