{
  "type": "Feature",
  "properties": {
    "addr:full":"83, Rue de l'Amp\u00e8re, 63200 Riom Riom Auvergne 63200",
    "addr:housenumber":"83",
    "addr:postcode":"63200;63200",
    "addr:street":"Rue De L'Ampe \u0300Re",
    "iso:country":"FR",
    "sg:address":"83, Rue de l'Amp\u00e8re, 63200 Riom",
    "sg:city":"Riom",
    "sg:orig_category":"Unclassifiable Establishments",
    "sg:phone":"+33 4 73 64 11 00",
    "sg:postcode":"63200",
    "sg:province":"Auvergne",
    "wof:name":"Maison Vacher S.a.",
    "wof:placetype":"venue"
},
  "geometry": {"coordinates":[3.12211,45.912579],"type":"Point"}
}