{
  "type": "Feature",
  "properties": {
    "addr:full":"Rue De La Gatine Pa 49300 Cholet Pays de Loire 49300",
    "addr:postcode":"49300;49300",
    "addr:street":"Rue De La Gatine",
    "iso:country":"FR",
    "sg:address":"Rue De La Gatine Pa 49300 Cholet",
    "sg:classifiers":[
        {
            "category":"Home & Garden",
            "subcategory":"Furniture",
            "type":"Retail Goods"
        }
    ],
    "sg:phone":"+33 2 41 75 24 78",
    "sg:postcode":"49300",
    "sg:province":"Pays de Loire",
    "sg:tags":[
        "household",
        "wood"
    ],
    "wof:name":"Tartrou Sa",
    "wof:placetype":"venue"
},
  "geometry": {"coordinates":[-0.892689,46.99659],"type":"Point"}
}