{
  "type": "Feature",
  "properties": {
    "addr:full":"38 Jeanne d'Arc 59150 Wattrelos Nord Pas-de-Calais 59150",
    "addr:housenumber":"38",
    "addr:postcode":"59150;59150",
    "addr:street":"Jeanne D'Arc",
    "iso:country":"FR",
    "sg:address":"38",
    "sg:city":"Jeanne d'Arc 59150 Wattrelos",
    "sg:classifiers":[
        {
            "category":"Professional",
            "subcategory":"Printing & Photocopies",
            "type":"Services"
        }
    ],
    "sg:phone":"+33 3 20 75 02 97",
    "sg:postcode":"59150",
    "sg:province":"Nord Pas-de-Calais",
    "sg:tags":[
        "machine",
        "engineering",
        "-",
        "mechanical"
    ],
    "wof:name":"Imprimerie Europeenne De Repiquage",
    "wof:placetype":"venue"
},
  "geometry": {"coordinates":[3.209544,50.70303],"type":"Point"}
}