{
  "type": "Feature",
  "properties": {
    "iso:country":"FR",
    "sg:address":"47",
    "sg:city":"Petits Champs 75001 PARIS",
    "sg:classifiers":[
        {
            "category":"Shopping",
            "subcategory":"Crafts & Fabrics",
            "type":"Retail Goods"
        }
    ],
    "sg:phone":"+33 1 44 77 36 00",
    "sg:postcode":"75001",
    "sg:province":"Ile de France",
    "sg:tags":[
        "textile",
        "linen",
        "clothing"
    ],
    "wof:name":"Pierre Frey",
    "wof:placetype":"venue"
},
  "geometry": {"coordinates":[2.335485,48.866928],"type":"Point"}
}