{
  "type": "Feature",
  "properties": {
    "iso:country":"FR",
    "sg:address":"ZI des Mottes Longues",
    "sg:city":"Bonneville",
    "sg:orig_category":"Unclassifiable Establishments",
    "sg:phone":"+33 4 50 25 79 29",
    "sg:postcode":"74130",
    "sg:province":"Picardie",
    "wof:name":"Ateliers De Bonneville",
    "wof:placetype":"venue"
},
  "geometry": {"coordinates":[6.408045,46.077595],"type":"Point"}
}