{
  "type": "Feature",
  "properties": {
    "iso:country":"FR",
    "sg:address":"Za Marcel Dassault 93140 Dondy",
    "sg:classifiers":[
        {
            "category":"Professional",
            "type":"Services"
        }
    ],
    "sg:phone":"+33 1 48 49 87 00",
    "sg:province":"Ile de France",
    "sg:tags":[
        "transport",
        "road"
    ],
    "wof:name":"Fercam France Sarl",
    "wof:placetype":"venue"
},
  "geometry": {"coordinates":[-119.698853,34.419239],"type":"Point"}
}