{
  "type": "Feature",
  "properties": {
    "addr:full":"4, All\u00e9e du Parc - ZA des Brosses, 37270 Lar\u00e7ay Lar\u00e7ay Centre 37270",
    "addr:housenumber":"4;larc\u0327ay",
    "addr:postcode":"37270;37270",
    "addr:street":"Alle\u0301E Du Parc Za Des Brosses",
    "iso:country":"FR",
    "sg:address":"4, All\u00e9e du Parc - ZA des Brosses, 37270 Lar\u00e7ay",
    "sg:city":"Lar\u00e7ay",
    "sg:orig_category":"Unclassifiable Establishments",
    "sg:phone":"+33 2 47 25 20 20",
    "sg:postcode":"37270",
    "sg:province":"Centre",
    "wof:name":"Corvaisier S.a.",
    "wof:placetype":"venue"
},
  "geometry": {"coordinates":[0.918022,47.31168],"type":"Point"}
}