{
  "type": "Feature",
  "properties": {
    "iso:country":"FR",
    "sg:address":"9, Rue des Petites Industries, 44470 Carquefou",
    "sg:orig_category":"Unclassifiable Establishments",
    "sg:phone":"+33 2 40 25 29 90",
    "sg:province":"Pays de Loire",
    "wof:name":"A.e. Marquet S.n.c. - Automatisme Electricit\u00e9 Marquet",
    "wof:placetype":"venue"
},
  "geometry": {"coordinates":[-1.492066,47.265739],"type":"Point"}
}