{
  "type": "Feature",
  "properties": {
    "iso:country":"FR",
    "sg:address":"1153, Av. de l'Epinette - ZA de l'Epinette, 59113 Seclin",
    "sg:orig_category":"Unclassifiable Establishments",
    "sg:phone":"+33 3 28 16 05 25",
    "sg:province":"Nord Pas-de-Calais",
    "wof:name":"Cadillac Plastic S.a.",
    "wof:placetype":"venue"
},
  "geometry": {"coordinates":[3.02694,50.545441],"type":"Point"}
}