{
  "type": "Feature",
  "properties": {
    "addr:full":"1153, Av. de l'Epinette - ZA de l'Epinette, 59113 Seclin Nord Pas-de-Calais",
    "addr:housenumber":"1153",
    "addr:postcode":"59113",
    "addr:street":"Av. De L'Epinette Za De L'Epinette",
    "iso:country":"FR",
    "sg:address":"1153, Av. de l'Epinette - ZA de l'Epinette, 59113 Seclin",
    "sg:orig_category":"Unclassifiable Establishments",
    "sg:phone":"+33 3 28 16 05 25",
    "sg:province":"Nord Pas-de-Calais",
    "wof:name":"Cadillac Plastic S.a.",
    "wof:placetype":"venue"
},
  "geometry": {"coordinates":[3.02694,50.545441],"type":"Point"}
}