{
  "type": "Feature",
  "properties": {
    "addr:full":"Zi De Gourhel 56800 Ploermel Plo\u00ebrmel Bretagne 56800",
    "addr:postcode":"56800;56800",
    "addr:street":"Zi De Gourhel;Ploe\u0308Rmel",
    "iso:country":"FR",
    "sg:address":"Zi De Gourhel 56800 Ploermel",
    "sg:city":"Plo\u00ebrmel",
    "sg:classifiers":[
        {
            "category":"Building & Trades",
            "subcategory":"Construction",
            "type":"Services"
        }
    ],
    "sg:phone":"+33 2 97 74 00 63",
    "sg:postcode":"56800",
    "sg:province":"Bretagne",
    "sg:tags":[
        "work",
        "public"
    ],
    "wof:name":"Screg Ouest",
    "wof:placetype":"venue"
},
  "geometry": {"coordinates":[-2.398204,47.931625],"type":"Point"}
}