{
  "type": "Feature",
  "properties": {
    "iso:country":"FR",
    "sg:address":"21, Av. de l'Agriculture - ZI du Br\u00e9zet, 63100 Clermont Ferrand",
    "sg:city":"Clermont-Ferrand",
    "sg:orig_category":"Unclassifiable Establishments",
    "sg:phone":"+33 4 73 91 93 51",
    "sg:postcode":"63100",
    "sg:province":"Auvergne",
    "wof:name":"Etablissement Yvan B\u00e9al S.a.",
    "wof:placetype":"venue"
},
  "geometry": {"coordinates":[3.10785,45.796341],"type":"Point"}
}