{
  "type": "Feature",
  "properties": {
    "addr:full":"Rue de l'Industrie - Z.I. - Fosse n\u00b014 Carvin Nord Pas-de-Calais 62220",
    "addr:postcode":"62220",
    "addr:street":"Rue De L'Industrie Z.I. Fosse N\u00b014 Carvin Nord",
    "iso:country":"FR",
    "sg:address":"Rue de l'Industrie - Z.I. - Fosse n\u00b014",
    "sg:city":"Carvin",
    "sg:orig_category":"Non-Classified Establishments",
    "sg:phone":"+33 3 21 08 60 00",
    "sg:postcode":"62220",
    "sg:province":"Nord Pas-de-Calais",
    "wof:name":"Maxi Pneu - M\u00e9tisiot S.a.",
    "wof:placetype":"venue"
},
  "geometry": {"coordinates":[2.938055,50.488876],"type":"Point"}
}