{
  "type": "Feature",
  "properties": {
    "iso:country":"FR",
    "sg:address":"1-3, Rue Andr\u00e9 Citro\u00ebn, 72000 Le Mans",
    "sg:orig_category":"Unclassifiable Establishments",
    "sg:phone":"+33 2 43 28 52 20",
    "sg:province":"Pays de Loire",
    "wof:name":"M.r.t. Electronique S.a.r.l.",
    "wof:placetype":"venue"
},
  "geometry": {"coordinates":[0.173522,48.028908],"type":"Point"}
}