{
  "type": "Feature",
  "properties": {
    "iso:country":"FR",
    "sg:address":"9, Rue Louis Grignon, 51000 Ch\u00e2lons en Champagne",
    "sg:orig_category":"Unclassifiable Establishments",
    "sg:phone":"+33 3 26 21 07 54",
    "sg:province":"Champagne",
    "wof:name":"Klinos Est S.a.s.",
    "wof:placetype":"venue"
},
  "geometry": {"coordinates":[4.349485,48.944778],"type":"Point"}
}