{
  "type": "Feature",
  "properties": {
    "addr:full":"2 All Des Tilleuls 59170 Croix Nord Pas-de-Calais",
    "addr:housenumber":"2",
    "addr:postcode":"59170",
    "addr:street":"All Des Tilleuls;Croix Nord",
    "iso:country":"FR",
    "sg:address":"2 All Des Tilleuls 59170 Croix",
    "sg:classifiers":[
        {
            "category":"Manufacturing",
            "subcategory":"Paper Products",
            "type":"Manufacturing & Wholesale Goods"
        }
    ],
    "sg:phone":"+33 3 20 20 74 60",
    "sg:province":"Nord Pas-de-Calais",
    "sg:tags":[
        "finished",
        "cardboard",
        "-"
    ],
    "wof:name":"Gpv Navarre Diffusion",
    "wof:placetype":"venue"
},
  "geometry": {"coordinates":[3.141531,50.676277],"type":"Point"}
}