{
  "type": "Feature",
  "properties": {
    "addr:full":"Chemin du Parc - ZI 11 \u00e8me Avenue Pierrelaye Ile de France 95480",
    "addr:housenumber":"11",
    "addr:postcode":"95480",
    "addr:street":"Chemin Du Parc Zi;E\u0300Me Avenue;Ile De France",
    "iso:country":"FR",
    "sg:address":"Chemin du Parc - ZI 11 \u00e8me Avenue",
    "sg:city":"Pierrelaye",
    "sg:orig_category":"Unclassifiable Establishments",
    "sg:phone":"+33 1 30 40 93 65",
    "sg:postcode":"95480",
    "sg:province":"Ile de France",
    "wof:name":"Paredis S.a.",
    "wof:placetype":"venue"
},
  "geometry": {"coordinates":[2.156565,49.022736],"type":"Point"}
}