{
  "type": "Feature",
  "properties": {
    "iso:country":"FR",
    "sg:address":"1, Rue Jean Gay - Les Bonnins , 16130 Salles d'Angles",
    "sg:orig_category":"Non-Classified Establishments",
    "sg:phone":"+33 5 45 83 64 81",
    "sg:postcode":"16130",
    "sg:province":"Poitou-Charentes",
    "wof:name":"Air Valley S.a.r.l.",
    "wof:placetype":"venue"
},
  "geometry": {"coordinates":[-75.615517,39.757557],"type":"Point"}
}