{
  "type": "Feature",
  "properties": {
    "iso:country":"FR",
    "sg:address":"20, Bd Victor Hugo, 02100 Saint Quentin",
    "sg:orig_category":"Unclassifiable Establishments",
    "sg:phone":"+33 3 23 62 23 26",
    "sg:province":"Picardie",
    "wof:name":"Marchant G\u00e9rard S.a.r.l.",
    "wof:placetype":"venue"
},
  "geometry": {"coordinates":[3.281235,49.842705],"type":"Point"}
}