{
  "type": "Feature",
  "properties": {
    "iso:country":"FR",
    "sg:address":"Le Musset 61110 Cond\u00e9 sur Huisne",
    "sg:city":"Saint-Maurice-sur-Huisne",
    "sg:orig_category":"Non-Classified Establishments",
    "sg:phone":"+33 2 33 73 30 74",
    "sg:postcode":"61110",
    "sg:province":"Basse Normandie",
    "wof:name":"Soparco S.a. - Soci\u00e9t\u00e9 Parisienne De Courtage",
    "wof:placetype":"venue"
},
  "geometry": {"coordinates":[0.85473,48.380863],"type":"Point"}
}