{
  "type": "Feature",
  "properties": {
    "addr:full":"Rte de Lavelanet B\u00e9lesta Midi Pyr\u00e9n\u00e9es 09300",
    "addr:postcode":"09300",
    "addr:street":"Rte De Lavelanet",
    "iso:country":"FR",
    "sg:address":"Rte de Lavelanet",
    "sg:city":"B\u00e9lesta",
    "sg:orig_category":"Non-Classified Establishments",
    "sg:phone":"+33 5 61 01 60 89",
    "sg:postcode":"09300",
    "sg:province":"Midi Pyr\u00e9n\u00e9es",
    "wof:name":"Salvaire S.a.",
    "wof:placetype":"venue"
},
  "geometry": {"coordinates":[1.93193,42.904709],"type":"Point"}
}