{
  "type": "Feature",
  "properties": {
    "iso:country":"FR",
    "sg:address":"4, Rue Georges Guynemer - ZI de Toul Garros, 56400 Auray",
    "sg:city":"Auray",
    "sg:orig_category":"Unclassifiable Establishments",
    "sg:phone":"+33 2 97 56 65 21",
    "sg:postcode":"56400",
    "sg:province":"Bretagne",
    "wof:name":"Kantemir S.a.",
    "wof:placetype":"venue"
},
  "geometry": {"coordinates":[-2.949126,47.63744],"type":"Point"}
}