{
  "type": "Feature",
  "properties": {
    "addr:full":"52-72 Mal Leclerc BP 10 10121 St Andr\u00e9 Les Vergers Cedex Basse Normandie",
    "addr:housenumber":"52-72;10",
    "addr:postcode":"10121;vergers cedex",
    "addr:street":"Mal Leclerc Bp;Les",
    "iso:country":"FR",
    "sg:address":"52-72 Mal Leclerc BP 10 10121 St Andr\u00e9 Les Vergers Cedex",
    "sg:orig_category":"Banking institutions Banking, finance and insurances Electrical and Electronic Equipment Lighting",
    "sg:phone":"+33 3 25 71 32 00",
    "sg:province":"Basse Normandie",
    "wof:name":"Petitjean Industries Sa",
    "wof:placetype":"venue"
},
  "geometry": {"coordinates":[4.050426,48.277775],"type":"Point"}
}