{
  "type": "Feature",
  "properties": {
    "addr:full":"B.P. 326, 01203 Bellegarde sur Valserine C\u00e9dex^^4, Av. Paul Langevin - ZI, 01200 Bellegarde sur Vals Rhone-Alpes 01200",
    "addr:housenumber":"b.p. 326",
    "addr:postcode":"01203;01200;01200",
    "addr:street":"Av. Paul Langevin Zi;Rhone-Alpes",
    "iso:country":"FR",
    "sg:address":"B.P. 326, 01203 Bellegarde sur Valserine C\u00e9dex^^4, Av. Paul Langevin - ZI, 01200 Bellegarde sur Vals",
    "sg:orig_category":"Non-Classified Establishments",
    "sg:phone":"+33 4 50 48 02 10",
    "sg:postcode":"01200",
    "sg:province":"Rhone-Alpes",
    "wof:name":"Anciens Etablissements Marion S.a.r.l.",
    "wof:placetype":"venue"
},
  "geometry": {"coordinates":[5.80849,46.110901],"type":"Point"}
}