{
  "type": "Feature",
  "properties": {
    "iso:country":"FR",
    "sg:address":"27, Av. du Pr\u00e9sident Wilson, 34500 B\u00e9ziers",
    "sg:orig_category":"Unclassifiable Establishments",
    "sg:phone":"+33 4 67 46 54 22",
    "sg:province":"Languedoc-Roussillon",
    "wof:name":"Soci\u00e9t\u00e9 Nouvelle Imprimerie Mathieu S.a.r.l.",
    "wof:placetype":"venue"
},
  "geometry": {"coordinates":[3.220679,43.339336],"type":"Point"}
}