{
  "type": "Feature",
  "properties": {
    "iso:country":"FR",
    "sg:address":"1 Avenue Daumesnil Voute N 7 8 75012 Paris",
    "sg:classifiers":[
        {
            "category":"Shopping",
            "subcategory":"Crafts & Fabrics",
            "type":"Retail Goods"
        }
    ],
    "sg:phone":"+33 5 55 66 55 42",
    "sg:postcode":"75012",
    "sg:province":"Ile de France",
    "sg:tags":[
        "textile",
        "linen",
        "clothing"
    ],
    "wof:name":"Les Fuses Manufacture Pinton",
    "wof:placetype":"venue"
},
  "geometry": {"coordinates":[2.389295,48.841045],"type":"Point"}
}