{
  "type": "Feature",
  "properties": {
    "iso:country":"FR",
    "sg:address":"71, Rue du Moulin Carron - ZAC de Dardilly - B\u00e2t. le Florentin, 69570 Dardilly",
    "sg:orig_category":"Non-Classified Establishments",
    "sg:phone":"+33 4 78 66 88 20",
    "sg:province":"Rhone-Alpes",
    "wof:name":"Hesiem S.a.r.l.",
    "wof:placetype":"venue"
},
  "geometry": {"coordinates":[4.753535,45.805908],"type":"Point"}
}