{
  "type": "Feature",
  "properties": {
    "addr:full":"55 Rue De Paris 91400 Orsay Ile de France 91400",
    "addr:housenumber":"55",
    "addr:postcode":"91400;91400",
    "addr:street":"Rue De Paris;Ile De France",
    "iso:country":"FR",
    "sg:address":"55 Rue De Paris 91400 Orsay",
    "sg:classifiers":[
        {
            "category":"Bakery",
            "type":"Food & Drink"
        }
    ],
    "sg:phone":"+33 1 69 28 42 41",
    "sg:postcode":"91400",
    "sg:province":"Ile de France",
    "sg:tags":[
        "cake",
        "product",
        "related",
        "bread"
    ],
    "wof:name":"La Chocolatine Snc",
    "wof:placetype":"venue"
},
  "geometry": {"coordinates":[2.187581,48.697716],"type":"Point"}
}