{
  "type": "Feature",
  "properties": {
    "addr:full":"Les Quatres Vents 87430 Verneuil sur Vienne Limousin",
    "addr:postcode":"87430",
    "addr:street":"Vents",
    "iso:country":"FR",
    "sg:address":"Les Quatres Vents 87430 Verneuil sur Vienne",
    "sg:orig_category":"Unclassifiable Establishments",
    "sg:phone":"+33 5 55 00 10 04",
    "sg:province":"Limousin",
    "wof:name":"S.a.o.t.m. S.a. - Soci\u00e9t\u00e9 Aixoise D'outils Tranchants M\u00e9caniques",
    "wof:placetype":"venue"
},
  "geometry": {"coordinates":[1.127005,45.848839],"type":"Point"}
}