{
  "type": "Feature",
  "properties": {
    "addr:full":"Rte de Lassigny Elincourt Sainte Marguerite Picardie 60157",
    "addr:postcode":"60157",
    "addr:street":"Rte De Lassigny Elincourt Sainte Marguerite Picardie",
    "iso:country":"FR",
    "sg:address":"Rte de Lassigny",
    "sg:city":"Elincourt Sainte Marguerite",
    "sg:orig_category":"Unclassifiable Establishments",
    "sg:phone":"+33 3 44 96 00 33",
    "sg:postcode":"60157",
    "sg:province":"Picardie",
    "wof:name":"Ch\u00e2teau De Bellinglise S.a.",
    "wof:placetype":"venue"
},
  "geometry": {"coordinates":[2.818301,49.524086],"type":"Point"}
}