{
  "type": "Feature",
  "properties": {
    "addr:full":"18, Place des Reflets - Tour Aurore, 92965 Paris La D\u00e9fence C\u00e9dex 2 Midi Pyr\u00e9n\u00e9es",
    "addr:housenumber":"18;2",
    "addr:postcode":"92965",
    "addr:street":"Place Des Reflets Tour Aurore;Ce\u0301Dex",
    "iso:country":"FR",
    "sg:address":"18, Place des Reflets - Tour Aurore, 92965 Paris La D\u00e9fence C\u00e9dex 2",
    "sg:orig_category":"Non-Classified Establishments",
    "sg:phone":"+33 1 43 78 62 40",
    "sg:province":"Midi Pyr\u00e9n\u00e9es",
    "wof:name":"Ermawa S.a.",
    "wof:placetype":"venue"
},
  "geometry": {"coordinates":[2.34123,48.856911],"type":"Point"}
}