{
  "type": "Feature",
  "properties": {
    "iso:country":"FR",
    "sg:address":"50 AVENUE DE GROSBOIS 94440 Marolles en Brie",
    "sg:classifiers":[
        {
            "category":"Manufacturing",
            "subcategory":"Tools & Machinery",
            "type":"Manufacturing & Wholesale Goods"
        }
    ],
    "sg:phone":"+33 1 45 10 60 00",
    "sg:province":"Ile de France",
    "sg:tags":[
        "packaging",
        "industry",
        "cosmetic"
    ],
    "wof:name":"Raffypack Sa",
    "wof:placetype":"venue"
},
  "geometry": {"coordinates":[2.54375,48.730701],"type":"Point"}
}