{
  "type": "Feature",
  "properties": {
    "iso:country":"FR",
    "sg:address":"121 Rue Lacroix Du Lac 35120 Cherrueix",
    "sg:city":"Cherrueix",
    "sg:classifiers":[
        {
            "category":"Farming",
            "subcategory":"Livestock Farm",
            "type":"Manufacturing & Wholesale Goods"
        }
    ],
    "sg:phone":"+33 2 99 48 91 29",
    "sg:postcode":"35120",
    "sg:province":"Bretagne",
    "sg:tags":[
        "agriculture"
    ],
    "wof:name":"Ame-hasle Sa",
    "wof:placetype":"venue"
},
  "geometry": {"coordinates":[-1.649389,48.473736],"type":"Point"}
}