{
  "type": "Feature",
  "properties": {
    "addr:full":"Chemin du Port aux Bois Joigny Bourgogne 89300",
    "addr:postcode":"89300",
    "addr:street":"Chemin Du Port Aux Bois",
    "iso:country":"FR",
    "sg:address":"Chemin du Port aux Bois",
    "sg:city":"Joigny",
    "sg:orig_category":"Unclassifiable Establishments",
    "sg:phone":"+33 3 86 91 46 66",
    "sg:postcode":"89300",
    "sg:province":"Bourgogne",
    "wof:name":"Le Rive Gauche",
    "wof:placetype":"venue"
},
  "geometry": {"coordinates":[3.390565,47.981281],"type":"Point"}
}