{
  "type": "Feature",
  "properties": {
    "iso:country":"FR",
    "sg:address":"ZAC Puy Saint Martin - Plateforme Douani\u00e8re",
    "sg:city":"Saint Julien en Genevois",
    "sg:orig_category":"Unclassifiable Establishments",
    "sg:phone":"+33 4 50 35 17 27",
    "sg:postcode":"74160",
    "sg:province":"Rhone-Alpes",
    "wof:name":"S.f.t Gondrand Fr\u00e8res - Soci\u00e9t\u00e9 Fran\u00e7aise De Transport Gondrand",
    "wof:placetype":"venue"
},
  "geometry": {"coordinates":[6.083075,46.141129],"type":"Point"}
}