{
  "type": "Feature",
  "properties": {
    "iso:country":"FR",
    "sg:address":"3, Impasse Casse Diable, 34410 Sauvian",
    "sg:orig_category":"Unclassifiable Establishments",
    "sg:phone":"+33 4 67 32 34 88",
    "sg:province":"Languedoc-Roussillon",
    "wof:name":"C.t.s. S.a.r.l. - Chaudronnerie Tuyauterie Du Sud",
    "wof:placetype":"venue"
},
  "geometry": {"coordinates":[3.25097,43.296844],"type":"Point"}
}