{
  "type": "Feature",
  "properties": {
    "addr:full":"43, Chemin de l'Arm\u00e9e d'Afrique, 13005 Marseille Provence-Alpes-C\u00f4te d'Azur",
    "addr:housenumber":"43",
    "addr:postcode":"13005",
    "addr:street":"Chemin De L'Arme \u0301E D'Afrique",
    "iso:country":"FR",
    "sg:address":"43, Chemin de l'Arm\u00e9e d'Afrique, 13005 Marseille",
    "sg:orig_category":"Unclassifiable Establishments",
    "sg:phone":"+33 4 91 24 34 64",
    "sg:province":"Provence-Alpes-C\u00f4te d'Azur",
    "wof:name":"Corania S.a.r.l.",
    "wof:placetype":"venue"
},
  "geometry": {"coordinates":[5.405603,43.290623],"type":"Point"}
}