{
  "type": "Feature",
  "properties": {
    "iso:country":"FR",
    "sg:address":"B.P. 9454, 73094 Chamb\u00e9ry Cedex 9^^60, Av. Ren\u00e9 Cassin, 73290 La Motte Servolex",
    "sg:orig_category":"Non-Classified Establishments",
    "sg:phone":"+33 4 79 68 22 25",
    "sg:province":"Rhone-Alpes",
    "wof:name":"Syl\u00e8ne S.a.",
    "wof:placetype":"venue"
},
  "geometry": {"coordinates":[5.87817,45.596516],"type":"Point"}
}