{
  "type": "Feature",
  "properties": {
    "iso:country":"FR",
    "sg:address":"La Maison Blanche Hameau De Buglise 76930 CAUVILLE",
    "sg:orig_category":"Fittings, Valves",
    "sg:phone":"+33 2 35 20 80 60",
    "sg:postcode":"76930",
    "sg:province":"Haute Normandie",
    "wof:name":"Produits Et Accessoires Industriels Sa",
    "wof:placetype":"venue"
},
  "geometry": {"coordinates":[0.117804,49.55648],"type":"Point"}
}