{
  "type": "Feature",
  "properties": {
    "addr:full":"62 Avenue Docteur Manouvrier 23000 Gueret Limousin 23000",
    "addr:housenumber":"62",
    "addr:postcode":"23000;23000",
    "addr:street":"Avenue Docteur Manouvrier",
    "iso:country":"FR",
    "sg:address":"62 Avenue Docteur Manouvrier 23000 Gueret",
    "sg:classifiers":[
        {
            "category":"Shopping",
            "type":"Retail Goods"
        }
    ],
    "sg:phone":"+33 5 55 52 23 44",
    "sg:postcode":"23000",
    "sg:province":"Limousin",
    "sg:tags":[
        "metallurgy",
        "finished",
        "-",
        "metalworking",
        "metallic"
    ],
    "wof:name":"Cmc",
    "wof:placetype":"venue"
},
  "geometry": {"coordinates":[1.877221,46.170933],"type":"Point"}
}