{
  "type": "Feature",
  "properties": {
    "addr:full":"430 Rte De Gamaches 80210 Aigneville Picardie 80210",
    "addr:housenumber":"430",
    "addr:postcode":"80210;80210",
    "addr:street":"Rte De Gamaches;Picardie",
    "iso:country":"FR",
    "sg:address":"430 Rte De Gamaches 80210 Aigneville",
    "sg:classifiers":[
        {
            "category":"Manufacturing",
            "subcategory":"Tools & Machinery",
            "type":"Manufacturing & Wholesale Goods"
        }
    ],
    "sg:phone":"+33 3 22 26 77 88",
    "sg:postcode":"80210",
    "sg:province":"Picardie",
    "sg:tags":[
        "metallurgy",
        "metalworking",
        "processing",
        "metal"
    ],
    "wof:name":"Delabre Sarl",
    "wof:placetype":"venue"
},
  "geometry": {"coordinates":[1.586434,50.030945],"type":"Point"}
}