{
  "type": "Feature",
  "properties": {
    "addr:full":"110, Av. du Petit Ch\u00e2teau, 94220 Charenton le Pont Ile de France",
    "addr:housenumber":"110",
    "addr:postcode":"94220",
    "addr:street":"Av. Du Petit Cha\u0302Teau",
    "iso:country":"FR",
    "sg:address":"110, Av. du Petit Ch\u00e2teau, 94220 Charenton le Pont",
    "sg:orig_category":"Unclassifiable Establishments",
    "sg:phone":"+33 1 43 68 38 93",
    "sg:province":"Ile de France",
    "wof:name":"Allcasts S.a.s.",
    "wof:placetype":"venue"
},
  "geometry": {"coordinates":[2.40151,48.827942],"type":"Point"}
}