{
  "type": "Feature",
  "properties": {
    "addr:full":"21 Quai De La Citadelle 59383 Dunkerque Midi Pyr\u00e9n\u00e9es",
    "addr:housenumber":"21",
    "addr:postcode":"59383",
    "addr:street":"Quai De La Citadelle",
    "iso:country":"FR",
    "sg:address":"21 Quai De La Citadelle 59383 Dunkerque",
    "sg:classifiers":[
        {
            "category":"Professional",
            "subcategory":"Business Services",
            "type":"Services"
        }
    ],
    "sg:phone":"+33 3 28 23 71 00",
    "sg:province":"Midi Pyr\u00e9n\u00e9es",
    "sg:tags":[
        "training",
        "advice"
    ],
    "wof:name":"Universite Du Littoral Cote D Opale",
    "wof:placetype":"venue"
},
  "geometry": {"coordinates":[2.374385,51.039345],"type":"Point"}
}