{
  "type": "Feature",
  "properties": {
    "addr:full":"Lieu-Dit Veilly 71290 La Genete La Gen\u00eate Bourgogne 71290",
    "addr:postcode":"71290;71290",
    "addr:street":"Lieu-Dit Veilly",
    "iso:country":"FR",
    "sg:address":"Lieu-Dit Veilly 71290 La Genete",
    "sg:city":"La Gen\u00eate",
    "sg:classifiers":[
        {
            "category":"Home & Garden",
            "subcategory":"Household Appliances",
            "type":"Retail Goods"
        }
    ],
    "sg:phone":"+33 3 85 32 27 50",
    "sg:postcode":"71290",
    "sg:province":"Bourgogne",
    "sg:tags":[
        "grate",
        "grill",
        "grids",
        "oven"
    ],
    "wof:name":"Somagic Barbecues S.a.",
    "wof:placetype":"venue"
},
  "geometry": {"coordinates":[5.035485,46.539082],"type":"Point"}
}