{
  "type": "Feature",
  "properties": {
    "addr:full":"4, Rue Edouard Branly - ZA de Pissaloup, 78190 Trappes Ile de France",
    "addr:housenumber":"4",
    "addr:postcode":"78190;ile",
    "addr:street":"Rue Edouard Branly Za De Pissaloup",
    "iso:country":"FR",
    "sg:address":"4, Rue Edouard Branly - ZA de Pissaloup, 78190 Trappes",
    "sg:orig_category":"Unclassifiable Establishments",
    "sg:phone":"+33 1 34 63 70 00",
    "sg:province":"Ile de France",
    "wof:name":"Matra Syst\u00e8me S.a.",
    "wof:placetype":"venue"
},
  "geometry": {"coordinates":[1.999285,48.774651],"type":"Point"}
}