{
  "type": "Feature",
  "properties": {
    "iso:country":"FR",
    "sg:address":"329 Avenue Du Gal De Gaulle 92140 Clamart",
    "sg:classifiers":[
        {
            "category":"Manufacturing",
            "subcategory":"Rubber & Plastics",
            "type":"Manufacturing & Wholesale Goods"
        }
    ],
    "sg:phone":"+33 1 46 31 12 04",
    "sg:province":"Ile de France",
    "wof:name":"Clamart Pneus",
    "wof:placetype":"venue"
},
  "geometry": {"coordinates":[2.248532,48.784081],"type":"Point"}
}