{
  "type": "Feature",
  "properties": {
    "iso:country":"FR",
    "sg:address":"Chemin de Pontoise",
    "sg:city":"Pierrelaye",
    "sg:orig_category":"Unclassifiable Establishments",
    "sg:phone":"+33 1 39 97 80 44",
    "sg:postcode":"95480",
    "sg:province":"Ile de France",
    "wof:name":"M\u00e9cachimique S.a.",
    "wof:placetype":"venue"
},
  "geometry": {"coordinates":[2.134675,49.017185],"type":"Point"}
}