{
  "type": "Feature",
  "properties": {
    "addr:full":"Za La Massane 13210 St. R\u00e9my De Provence Nord Pas-de-Calais",
    "addr:postcode":"13210",
    "addr:street":"Za La Massane;Provence;Pas-De-Calais",
    "iso:country":"FR",
    "sg:address":"Za La Massane 13210 St. R\u00e9my De Provence",
    "sg:classifiers":[
        {
            "category":"Manufacturing",
            "subcategory":"Chemicals & Compounds",
            "type":"Manufacturing & Wholesale Goods"
        }
    ],
    "sg:phone":"+33 4 90 92 74 70",
    "sg:province":"Nord Pas-de-Calais",
    "sg:tags":[
        "pharmaceutical",
        "chemistry"
    ],
    "wof:name":"Tec Industries",
    "wof:placetype":"venue"
},
  "geometry": {"coordinates":[4.829515,43.788704],"type":"Point"}
}