{
  "type": "Feature",
  "properties": {
    "iso:country":"FR",
    "sg:address":"1, Quai de Grenelle, 75015 Paris",
    "sg:orig_category":"Unclassifiable Establishments",
    "sg:phone":"+33 1 44 37 75 80",
    "sg:province":"Ile de France",
    "wof:name":"Agence Conseil 3p S.a.",
    "wof:placetype":"venue"
},
  "geometry": {"coordinates":[2.288623,48.854328],"type":"Point"}
}