{
  "type": "Feature",
  "properties": {
    "iso:country":"FR",
    "sg:address":"99 rue des Grands Pins 40990 Mees",
    "sg:city":"M\u00e9es",
    "sg:orig_category":"Poultry, Slaughtered",
    "sg:phone":"+33 5 58 91 17 00",
    "sg:postcode":"40990",
    "sg:province":"Aquitaine",
    "wof:name":"Euro Food France Sa",
    "wof:placetype":"venue"
},
  "geometry": {"coordinates":[-1.119709,43.710754],"type":"Point"}
}