{
  "type": "Feature",
  "properties": {
    "addr:full":"B.P. 28, 34201 S\u00e8te C\u00e9dex^^52, Quai des Moulins, 34200 S\u00e8te Languedoc-Roussillon 34200",
    "addr:postcode":"34201;34200;34200",
    "addr:street":"B.P. 28;Quai Des Moulins",
    "iso:country":"FR",
    "sg:address":"B.P. 28, 34201 S\u00e8te C\u00e9dex^^52, Quai des Moulins, 34200 S\u00e8te",
    "sg:orig_category":"Non-Classified Establishments",
    "sg:phone":"+33 4 67 80 71 60",
    "sg:postcode":"34200",
    "sg:province":"Languedoc-Roussillon",
    "wof:name":"Cartembal S.a.",
    "wof:placetype":"venue"
},
  "geometry": {"coordinates":[3.69633,43.399052],"type":"Point"}
}