{
  "type": "Feature",
  "properties": {
    "addr:full":"18, Rue Camille Saint Sa\u00ebns, 11000 Carcassonne Languedoc-Roussillon",
    "addr:housenumber":"18",
    "addr:postcode":"11000",
    "addr:street":"Rue Camille Saint Sae\u0308Ns",
    "iso:country":"FR",
    "sg:address":"18, Rue Camille Saint Sa\u00ebns, 11000 Carcassonne",
    "sg:orig_category":"Unclassifiable Establishments",
    "sg:phone":"+33 4 68 11 92 82",
    "sg:province":"Languedoc-Roussillon",
    "wof:name":"Mercure Carcassonne - Porte De La Cit\u00e9",
    "wof:placetype":"venue"
},
  "geometry": {"coordinates":[2.36936,43.207062],"type":"Point"}
}