{
  "type": "Feature",
  "properties": {
    "iso:country":"FR",
    "sg:address":"100, Rue Vaillant Couturier, 93130 Noisy le Sec",
    "sg:orig_category":"Non-Classified Establishments",
    "sg:phone":"+33 1 48 45 95 12",
    "sg:postcode":"93130",
    "sg:province":"Ile de France",
    "wof:name":"Chagnon S.a.r.l.",
    "wof:placetype":"venue"
},
  "geometry": {"coordinates":[2.443052,48.892342],"type":"Point"}
}