{
  "type": "Feature",
  "properties": {
    "iso:country":"FR",
    "sg:address":"200, All\u00e9e des Ormeaux, 69760 Limonest",
    "sg:orig_category":"Unclassifiable Establishments",
    "sg:phone":"+33 4 78 66 34 00",
    "sg:province":"Rhone-Alpes",
    "wof:name":"M\u00e9travib R.d.s. S.a.",
    "wof:placetype":"venue"
},
  "geometry": {"coordinates":[4.772876,45.81007],"type":"Point"}
}