{
  "type": "Feature",
  "properties": {
    "addr:full":"450, Av. Gasseras, 82000 Montauban Midi Pyr\u00e9n\u00e9es",
    "addr:housenumber":"450",
    "addr:postcode":"82000",
    "addr:street":"Av. Gasseras",
    "iso:country":"FR",
    "sg:address":"450, Av. Gasseras, 82000 Montauban",
    "sg:orig_category":"Non-Classified Establishments",
    "sg:phone":"+33 5 63 66 73 92",
    "sg:province":"Midi Pyr\u00e9n\u00e9es",
    "wof:name":"S.e.a.m. S.a. - Soci\u00e9t\u00e9 D'exploitation Des Abattoirs De Montauban",
    "wof:placetype":"venue"
},
  "geometry": {"coordinates":[1.330485,44.019371],"type":"Point"}
}