{
  "type": "Feature",
  "properties": {
    "addr:full":"474, Rue du Bois Lay, 42720 Pouilly sous Charlieu Rhone-Alpes",
    "addr:housenumber":"474",
    "addr:postcode":"42720",
    "addr:street":"Rue Du Bois Lay",
    "iso:country":"FR",
    "sg:address":"474, Rue du Bois Lay, 42720 Pouilly sous Charlieu",
    "sg:orig_category":"Non-Classified Establishments",
    "sg:phone":"+33 4 77 60 85 45",
    "sg:province":"Rhone-Alpes",
    "wof:name":"Tricots Jym S.a.r.l.",
    "wof:placetype":"venue"
},
  "geometry": {"coordinates":[4.113757,46.145985],"type":"Point"}
}