{
  "type": "Feature",
  "properties": {
    "addr:full":"route de Florensac 34630 ST THIBERY Languedoc-Roussillon",
    "addr:postcode":"34630",
    "addr:street":"Route De Florensac",
    "iso:country":"FR",
    "sg:address":"route de Florensac 34630 ST THIBERY",
    "sg:classifiers":[
        {
            "category":"Manufacturing",
            "subcategory":"Building Materials",
            "type":"Manufacturing & Wholesale Goods"
        }
    ],
    "sg:phone":"+33 4 67 77 77 07",
    "sg:province":"Languedoc-Roussillon",
    "sg:tags":[
        "permanent",
        "way"
    ],
    "wof:name":"Ste Nouvelle Basaltine S.a.",
    "wof:placetype":"venue"
},
  "geometry": {"coordinates":[3.415575,43.395592],"type":"Point"}
}