{
  "type": "Feature",
  "properties": {
    "iso:country":"FR",
    "sg:address":"B.P. 79, 95503 Gonesse C\u00e9dex^^12, Rue Gay Lussac, 95500 Gonesse",
    "sg:orig_category":"Non-Classified Establishments",
    "sg:phone":"+33 1 34 45 35 35",
    "sg:province":"Ile de France",
    "wof:name":"Promodentaire S.a.",
    "wof:placetype":"venue"
},
  "geometry": {"coordinates":[2.449633,48.986462],"type":"Point"}
}