{
  "type": "Feature",
  "properties": {
    "addr:full":"2, Rue des Chenevi\u00e8res, 38240 Meylan Rhone-Alpes",
    "addr:housenumber":"2",
    "addr:postcode":"38240",
    "addr:street":"Rue Des Chenevie\u0300Res",
    "iso:country":"FR",
    "sg:address":"2, Rue des Chenevi\u00e8res, 38240 Meylan",
    "sg:orig_category":"Unclassifiable Establishments",
    "sg:phone":"+33 4 76 90 06 37",
    "sg:province":"Rhone-Alpes",
    "wof:name":"Bor\u00e9al Iceberg S.a.",
    "wof:placetype":"venue"
},
  "geometry": {"coordinates":[5.7909,45.211849],"type":"Point"}
}