{
  "type": "Feature",
  "properties": {
    "addr:full":"29, Rue Pernety, 75014 Paris Ile de France",
    "addr:housenumber":"29",
    "addr:postcode":"75014",
    "addr:street":"Rue Pernety",
    "iso:country":"FR",
    "sg:address":"29, Rue Pernety, 75014 Paris",
    "sg:orig_category":"Unclassifiable Establishments",
    "sg:phone":"+33 1 43 95 61 61",
    "sg:province":"Ile de France",
    "wof:name":"A.p.m.p. S.a. - Application Papeti\u00e8re Du Marquage De Prix",
    "wof:placetype":"venue"
},
  "geometry": {"coordinates":[2.319357,48.833027],"type":"Point"}
}