{
  "type": "Feature",
  "properties": {
    "addr:full":"30 Rue Du Docteur Henri Abel 26000 Valence Rhone-Alpes 26000",
    "addr:housenumber":"30",
    "addr:postcode":"26000;26000",
    "addr:street":"Rue Du Docteur Henri Abel",
    "iso:country":"FR",
    "sg:address":"30 Rue Du Docteur Henri Abel 26000 Valence",
    "sg:classifiers":[
        {
            "category":"Wholesale",
            "subcategory":"Medical Equipment & Supplies",
            "type":"Manufacturing & Wholesale Goods"
        }
    ],
    "sg:phone":"+33 4 75 78 69 00",
    "sg:postcode":"26000",
    "sg:province":"Rhone-Alpes",
    "sg:tags":[
        "instrument",
        "health",
        "-",
        "precision"
    ],
    "wof:name":"Lpg Systems",
    "wof:placetype":"venue"
},
  "geometry": {"coordinates":[4.909911,44.912209],"type":"Point"}
}