{
  "type": "Feature",
  "properties": {
    "iso:country":"FR",
    "sg:address":"Rte de Faulquemont - Zone Industrielle",
    "sg:city":"Long\u00e9ville l\u00e8s Saint Avold",
    "sg:orig_category":"Unclassifiable Establishments",
    "sg:phone":"+33 3 87 91 37 20",
    "sg:postcode":"57540",
    "sg:province":"Lorraine",
    "wof:name":"Flash Entretien",
    "wof:placetype":"venue"
},
  "geometry": {"coordinates":[-99.589363,44.525749],"type":"Point"}
}