{
  "type": "Feature",
  "properties": {
    "iso:country":"FR",
    "sg:address":"2 avenue Mar\u00e9chal Foch 51200 Epernay",
    "sg:classifiers":[
        {
            "category":"Food & Beverages",
            "subcategory":"Liquor & Beverages",
            "type":"Retail Goods"
        }
    ],
    "sg:phone":"+33 3 26 55 37 55",
    "sg:postcode":"51200",
    "sg:province":"Champagne",
    "sg:tags":[
        "champagne"
    ],
    "wof:name":"Champagne Trouillard Sarl",
    "wof:placetype":"venue"
},
  "geometry": {"coordinates":[3.949916,49.040714],"type":"Point"}
}