{
  "type": "Feature",
  "properties": {
    "iso:country":"FR",
    "sg:address":"16, Rue de la Noue Guimante - ZI de la Courtilli\u00e8re, 77400 Saint Thibault des Vignes",
    "sg:orig_category":"Non-Classified Establishments",
    "sg:phone":"+33 1 64 30 92 47",
    "sg:postcode":"77400",
    "sg:province":"Ile de France",
    "wof:name":"Eckold France S.a.r.l.",
    "wof:placetype":"venue"
},
  "geometry": {"coordinates":[2.701485,48.87775],"type":"Point"}
}