{
  "type": "Feature",
  "properties": {
    "addr:full":"18, Rue Amp\u00e8re, 67500 Haguenau Haguenau Alsace 67500",
    "addr:housenumber":"18",
    "addr:postcode":"67500;67500",
    "addr:street":"Rue Ampe\u0300Re",
    "iso:country":"FR",
    "sg:address":"18, Rue Amp\u00e8re, 67500 Haguenau",
    "sg:city":"Haguenau",
    "sg:orig_category":"Unclassifiable Establishments",
    "sg:phone":"+33 3 88 93 91 91",
    "sg:postcode":"67500",
    "sg:province":"Alsace",
    "wof:name":"Simec S.a. - Soci\u00e9t\u00e9 Industrielle De Montage Et D'equipement Electrique",
    "wof:placetype":"venue"
},
  "geometry": {"coordinates":[7.803347,48.801323],"type":"Point"}
}