{
  "type": "Feature",
  "properties": {
    "iso:country":"FR",
    "sg:address":"50 Av De L'Europe 78160 Marly Le Roi",
    "sg:classifiers":[
        {
            "category":"Building & Trades",
            "subcategory":"Pest Control",
            "type":"Services"
        }
    ],
    "sg:phone":"+33 1 39 17 20 20",
    "sg:postcode":"78160",
    "sg:province":"Ile de France",
    "sg:tags":[
        "pharmaceutical",
        "-",
        "pharmacy",
        "chemical",
        "engineering",
        "machine",
        "mechanical"
    ],
    "wof:name":"Valois Sas",
    "wof:placetype":"venue"
},
  "geometry": {"coordinates":[2.101976,48.877399],"type":"Point"}
}