{
  "type": "Feature",
  "properties": {
    "addr:full":"7 Rue Albert Camus 38200 Vienne Rhone-Alpes 38200",
    "addr:housenumber":"7",
    "addr:postcode":"38200;38200",
    "addr:street":"Rue Albert Camus",
    "iso:country":"FR",
    "sg:address":"7 Rue Albert Camus 38200 Vienne",
    "sg:classifiers":[
        {
            "category":"Transit Center",
            "subcategory":"Freight",
            "type":"Transportation"
        }
    ],
    "sg:phone":"+33 4 74 85 66 54",
    "sg:postcode":"38200",
    "sg:province":"Rhone-Alpes",
    "sg:tags":[
        "metallurgy",
        "pipe",
        "metalworking",
        "sheet"
    ],
    "wof:name":"Slti Sa",
    "wof:placetype":"venue"
},
  "geometry": {"coordinates":[4.85407,45.502274],"type":"Point"}
}