{
  "type": "Feature",
  "properties": {
    "addr:full":"ZI Ath\u00e9lia 1 La Ciotat C\u00e9dex Provence-Alpes-C\u00f4te d'Azur 13705",
    "addr:housenumber":"1",
    "addr:postcode":"13705",
    "addr:street":"Athe\u0301Lia;Ce\u0301Dex",
    "iso:country":"FR",
    "sg:address":"ZI Ath\u00e9lia 1",
    "sg:city":"La Ciotat C\u00e9dex",
    "sg:orig_category":"Non-Classified Establishments",
    "sg:phone":"+33 4 42 08 46 46",
    "sg:postcode":"13705",
    "sg:province":"Provence-Alpes-C\u00f4te d'Azur",
    "wof:name":"Intervascular S.a.s.",
    "wof:placetype":"venue"
},
  "geometry": {"coordinates":[5.598495,43.181904],"type":"Point"}
}