{
  "type": "Feature",
  "properties": {
    "iso:country":"FR",
    "sg:address":"102",
    "sg:city":"des Champs Elys\u00e9es; Paris; 75008",
    "sg:classifiers":[
        {
            "category":"Shopping",
            "subcategory":"Computers & Home Electronics",
            "type":"Retail Goods"
        }
    ],
    "sg:postcode":"75008",
    "sg:province":"Ile de France",
    "sg:tags":[
        "chamber",
        "commerce"
    ],
    "wof:name":"Chambre De Commerce Franco-russe",
    "wof:placetype":"venue"
},
  "geometry": {"coordinates":[2.301799,48.871761],"type":"Point"}
}