{
  "type": "Feature",
  "properties": {
    "addr:full":"3, Rue Gabriel P\u00e9ri, 31000 Toulouse Midi Pyr\u00e9n\u00e9es",
    "addr:housenumber":"3",
    "addr:postcode":"31000",
    "addr:street":"Rue Gabriel Pe\u0301Ri",
    "iso:country":"FR",
    "sg:address":"3, Rue Gabriel P\u00e9ri, 31000 Toulouse",
    "sg:orig_category":"Unclassifiable Establishments",
    "sg:phone":"+33 5 61 99 44 44",
    "sg:province":"Midi Pyr\u00e9n\u00e9es",
    "wof:name":"La Croix Du Midi S.a.",
    "wof:placetype":"venue"
},
  "geometry": {"coordinates":[1.449997,43.605713],"type":"Point"}
}