{
  "type": "Feature",
  "properties": {
    "iso:country":"FR",
    "sg:address":"Les Stations 45210 Fontenay Sur Loing",
    "sg:city":"La Selle-en-Hermoy",
    "sg:classifiers":[
        {
            "category":"Manufacturing",
            "subcategory":"Metals",
            "type":"Manufacturing & Wholesale Goods"
        }
    ],
    "sg:phone":"+33 2 38 95 81 31",
    "sg:postcode":"45210",
    "sg:province":"Centre",
    "sg:tags":[
        "metallurgy",
        "steel",
        "metalworking"
    ],
    "wof:name":"Loiret Affinage",
    "wof:placetype":"venue"
},
  "geometry": {"coordinates":[2.7651,48.064499],"type":"Point"}
}