{
  "type": "Feature",
  "properties": {
    "addr:full":"11 rue Pasteur 95260 Beaumont sur Oise Ile de France",
    "addr:housenumber":"11",
    "addr:postcode":"95260",
    "addr:street":"Rue Pasteur",
    "iso:country":"FR",
    "sg:address":"11 rue Pasteur 95260 Beaumont sur Oise",
    "sg:classifiers":[
        {
            "category":"Manufacturing",
            "subcategory":"Motor Vehicles & Parts",
            "type":"Manufacturing & Wholesale Goods"
        }
    ],
    "sg:phone":"+33 1 34 70 02 73",
    "sg:province":"Ile de France",
    "sg:tags":[
        "precision",
        "mechanic"
    ],
    "wof:name":"Etablissements Gogry S.a.",
    "wof:placetype":"venue"
},
  "geometry": {"coordinates":[2.292061,49.141846],"type":"Point"}
}