{
  "type": "Feature",
  "properties": {
    "iso:country":"FR",
    "sg:address":"159, Rte de Lorient, 35000 Rennes",
    "sg:city":"Rennes",
    "sg:orig_category":"Unclassifiable Establishments",
    "sg:phone":"+33 2 99 59 17 95",
    "sg:postcode":"35000",
    "sg:province":"Bretagne",
    "wof:name":"Cedeo",
    "wof:placetype":"venue"
},
  "geometry": {"coordinates":[-1.72872,48.10667],"type":"Point"}
}