{
  "type": "Feature",
  "properties": {
    "iso:country":"FR",
    "sg:address":"B.P. 85, 68273 Wittenheim C\u00e9dex^^27, Rue du G\u00e9n\u00e9ral de Gaulle, 68270 Wittenheim",
    "sg:city":"Wittenheim",
    "sg:orig_category":"Non-Classified Establishments",
    "sg:phone":"+33 3 89 62 52 00",
    "sg:postcode":"68270",
    "sg:province":"Alsace",
    "wof:name":"Seremine S.a.",
    "wof:placetype":"venue"
},
  "geometry": {"coordinates":[7.339937,47.810852],"type":"Point"}
}