{
  "type": "Feature",
  "properties": {
    "iso:country":"FR",
    "sg:address":"54 av de Paris; Cavignac; 33620",
    "sg:city":"Cavignac",
    "sg:classifiers":[
        {
            "category":"Banks & Credit Unions",
            "subcategory":"Bank",
            "type":"Services"
        }
    ],
    "sg:phone":"+33 3357686556",
    "sg:postcode":"33620",
    "sg:province":"Aquitaine",
    "wof:name":"Cr\u00e9dit Agricole De La Gironde",
    "wof:placetype":"venue"
},
  "geometry": {"coordinates":[-0.389378,45.099819],"type":"Point"}
}