{
  "type": "Feature",
  "properties": {
    "addr:full":"Z.I. du Bisconte 56680 PLOUHINEC Plouhinec Bretagne 56680",
    "addr:postcode":"56680;56680",
    "addr:street":"Z.I. Du Bisconte",
    "iso:country":"FR",
    "sg:address":"Z.I. du Bisconte 56680 PLOUHINEC",
    "sg:city":"Plouhinec",
    "sg:classifiers":[
        {
            "category":"Manufacturing",
            "subcategory":"Rubber & Plastics",
            "type":"Manufacturing & Wholesale Goods"
        }
    ],
    "sg:phone":"+33 2 97 85 88 00",
    "sg:postcode":"56680",
    "sg:province":"Bretagne",
    "sg:tags":[
        "packaging",
        "mean"
    ],
    "wof:name":"Mt Packages Sa",
    "wof:placetype":"venue"
},
  "geometry": {"coordinates":[-3.25645,47.700256],"type":"Point"}
}