{
  "type": "Feature",
  "properties": {
    "iso:country":"FR",
    "sg:address":"2450, Rte d'Orl\u00e9ans, 45160 Saint Hilaire Saint Mesmin",
    "sg:city":"Ardon",
    "sg:orig_category":"Unclassifiable Establishments",
    "sg:phone":"+33 2 38 76 32 33",
    "sg:postcode":"45160",
    "sg:province":"Centre",
    "wof:name":"Dorleane G.i.e.",
    "wof:placetype":"venue"
},
  "geometry": {"coordinates":[1.817807,47.857243],"type":"Point"}
}