{
  "type": "Feature",
  "properties": {
    "addr:full":"19, Rue Louis Gu\u00e9rin, 69100 Villeurbanne Rhone-Alpes 69100",
    "addr:housenumber":"19",
    "addr:postcode":"69100;69100",
    "addr:street":"Rue Louis Gue\u0301Rin",
    "iso:country":"FR",
    "sg:address":"19, Rue Louis Gu\u00e9rin, 69100 Villeurbanne",
    "sg:orig_category":"Non-Classified Establishments",
    "sg:phone":"+33 4 72 69 09 10",
    "sg:postcode":"69100",
    "sg:province":"Rhone-Alpes",
    "wof:name":"G. C.i.m. Lyon S.a.r.l.",
    "wof:placetype":"venue"
},
  "geometry": {"coordinates":[4.860607,45.77813],"type":"Point"}
}