{
  "type": "Feature",
  "properties": {
    "addr:full":"17 rue Victor Hugo; Avesnes; 59440 Nord Pas-de-Calais 59440",
    "addr:housenumber":"17",
    "addr:postcode":"59440;59440",
    "addr:street":"Rue Victor Hugo",
    "iso:country":"FR",
    "sg:address":"17 rue Victor Hugo; Avesnes; 59440",
    "sg:classifiers":[
        {
            "category":"Banks & Credit Unions",
            "subcategory":"Bank",
            "type":"Services"
        }
    ],
    "sg:phone":"+33 27610587",
    "sg:postcode":"59440",
    "sg:province":"Nord Pas-de-Calais",
    "wof:name":"Banque Nationale De Paris",
    "wof:placetype":"venue"
},
  "geometry": {"coordinates":[3.9395,50.114292],"type":"Point"}
}