{
  "type": "Feature",
  "properties": {
    "iso:country":"FR",
    "sg:address":"40 rue la Bo\u00e9tie 75008 Paris",
    "sg:orig_category":"Train Attendant Wagons",
    "sg:phone":"+33 1 45 61 56 20",
    "sg:province":"Ile de France",
    "wof:name":"Nacco Sa",
    "wof:placetype":"venue"
},
  "geometry": {"coordinates":[2.314021,48.873726],"type":"Point"}
}