{
  "type": "Feature",
  "properties": {
    "addr:full":"Clos de Triguedina 46700 Puy l'Ev\u00eaque Midi Pyr\u00e9n\u00e9es",
    "addr:postcode":"46700",
    "addr:street":"Clos De Triguedina",
    "iso:country":"FR",
    "sg:address":"Clos de Triguedina 46700 Puy l'Ev\u00eaque",
    "sg:orig_category":"Unclassifiable Establishments",
    "sg:phone":"+33 5 65 21 30 81",
    "sg:province":"Midi Pyr\u00e9n\u00e9es",
    "wof:name":"Clos De Triguedina",
    "wof:placetype":"venue"
},
  "geometry": {"coordinates":[-111.964462,46.250797],"type":"Point"}
}