{
  "type": "Feature",
  "properties": {
    "iso:country":"FR",
    "sg:address":"73, Bd Gay Lussac, 13014 Marseille",
    "sg:orig_category":"Unclassifiable Establishments",
    "sg:phone":"+33 4 91 67 32 46",
    "sg:province":"Provence-Alpes-C\u00f4te d'Azur",
    "wof:name":"Prohygi\u00e9na S.a.",
    "wof:placetype":"venue"
},
  "geometry": {"coordinates":[5.374755,43.337364],"type":"Point"}
}