{
  "type": "Feature",
  "properties": {
    "addr:full":"13 Rue De Rouen 49400 Saumur Pays de Loire 49400",
    "addr:housenumber":"13",
    "addr:postcode":"49400;49400",
    "addr:street":"Rue De Rouen",
    "iso:country":"FR",
    "sg:address":"13 Rue De Rouen 49400 Saumur",
    "sg:classifiers":[
        {
            "category":"Bakery",
            "type":"Food & Drink"
        }
    ],
    "sg:phone":"+33 2 41 67 42 97",
    "sg:postcode":"49400",
    "sg:province":"Pays de Loire",
    "sg:tags":[
        "cake",
        "product",
        "related",
        "bread"
    ],
    "wof:name":"Sarl Froger",
    "wof:placetype":"venue"
},
  "geometry": {"coordinates":[-0.068156,47.268944],"type":"Point"}
}