{
  "type": "Feature",
  "properties": {
    "addr:full":"6 Rue Du Marechal Leclerc 60400 Noyon Picardie 60400",
    "addr:housenumber":"6",
    "addr:postcode":"60400;60400",
    "addr:street":"Rue Du Marechal Leclerc",
    "iso:country":"FR",
    "sg:address":"6 Rue Du Marechal Leclerc 60400 Noyon",
    "sg:classifiers":[
        {
            "category":"Bakery",
            "type":"Food & Drink"
        }
    ],
    "sg:phone":"+33 3 44 44 03 17",
    "sg:postcode":"60400",
    "sg:province":"Picardie",
    "sg:tags":[
        "cake",
        "product",
        "related",
        "bread"
    ],
    "wof:name":"Sarl Rousseaux",
    "wof:placetype":"venue"
},
  "geometry": {"coordinates":[3.004758,49.582256],"type":"Point"}
}