{
  "type": "Feature",
  "properties": {
    "addr:full":"8, Av. de la R\u00e9publique, 75011 Paris Ile de France",
    "addr:postcode":"75011",
    "addr:street":"Av. De La Re\u0301Publique",
    "iso:country":"FR",
    "sg:address":"8, Av. de la R\u00e9publique, 75011 Paris",
    "sg:orig_category":"Unclassifiable Establishments",
    "sg:phone":"+33 1 43 55 33 60",
    "sg:province":"Ile de France",
    "wof:name":"Vocatif S.a.",
    "wof:placetype":"venue"
},
  "geometry": {"coordinates":[2.366062,48.866688],"type":"Point"}
}