{
  "type": "Feature",
  "properties": {
    "addr:full":"3, Rue Verlaine, 57280 Sem\u00e9court Lorraine",
    "addr:housenumber":"3",
    "addr:postcode":"57280",
    "addr:street":"Rue Verlaine",
    "iso:country":"FR",
    "sg:address":"3, Rue Verlaine, 57280 Sem\u00e9court",
    "sg:orig_category":"Non-Classified Establishments",
    "sg:phone":"+33 3 87 51 13 95",
    "sg:province":"Lorraine",
    "wof:name":"Lorraine Du Froid S.a.r.l.",
    "wof:placetype":"venue"
},
  "geometry": {"coordinates":[6.130206,49.193668],"type":"Point"}
}