{
  "type": "Feature",
  "properties": {
    "iso:country":"FR",
    "sg:address":"Rue de Bitburg - ZI de Pargny",
    "sg:city":"Rethel",
    "sg:orig_category":"Non-Classified Establishments",
    "sg:phone":"+33 3 24 38 26 65",
    "sg:postcode":"08300",
    "sg:province":"Champagne",
    "wof:name":"Routi\u00e8re Morin S.a.",
    "wof:placetype":"venue"
},
  "geometry": {"coordinates":[6.52291,49.972252],"type":"Point"}
}