{
  "type": "Feature",
  "properties": {
    "iso:country":"FR",
    "sg:address":"ZI B",
    "sg:city":"Annezin",
    "sg:orig_category":"Unclassifiable Establishments",
    "sg:phone":"+33 3 21 01 63 70",
    "sg:postcode":"62232",
    "sg:province":"Nord Pas-de-Calais",
    "wof:name":"Apligom S.a.r.l.",
    "wof:placetype":"venue"
},
  "geometry": {"coordinates":[2.618587,50.532475],"type":"Point"}
}