{
  "type": "Feature",
  "properties": {
    "iso:country":"FR",
    "sg:address":"70 rue Amp\u00e8re 77400 Lagny sur Marne",
    "sg:classifiers":[
        {
            "category":"Manufacturing",
            "subcategory":"Printing",
            "type":"Manufacturing & Wholesale Goods"
        }
    ],
    "sg:phone":"+33 1 60 07 80 00",
    "sg:postcode":"77400",
    "sg:province":"Ile de France",
    "sg:tags":[
        "house",
        "book"
    ],
    "wof:name":"R.e.g. Sa",
    "wof:placetype":"venue"
},
  "geometry": {"coordinates":[2.67999,48.873497],"type":"Point"}
}