{
  "type": "Feature",
  "properties": {
    "iso:country":"FR",
    "sg:address":"Rue Bouvard Dessous",
    "sg:city":"Voglans",
    "sg:orig_category":"Unclassifiable Establishments",
    "sg:phone":"+33 4 79 52 08 00",
    "sg:postcode":"73420",
    "sg:province":"Rhone-Alpes",
    "wof:name":"Gerland Savoie Leman S.n.c.",
    "wof:placetype":"venue"
},
  "geometry": {"coordinates":[5.892894,45.624466],"type":"Point"}
}