{
  "type": "Feature",
  "properties": {
    "iso:country":"FR",
    "sg:address":"Chem Du Genevray 74200 Thonon Les Bains",
    "sg:classifiers":[
        {
            "category":"Food Court",
            "type":"Food & Drink"
        }
    ],
    "sg:phone":"+33 4 50 71 14 31",
    "sg:postcode":"74200",
    "sg:province":"Rhone-Alpes",
    "sg:tags":[
        "product",
        "related"
    ],
    "wof:name":"Ste Eaux Minerales Thonon Sa",
    "wof:placetype":"venue"
},
  "geometry": {"coordinates":[6.464469,46.357834],"type":"Point"}
}