{
  "type": "Feature",
  "properties": {
    "addr:full":"1, Cours de l'Esplanade, 07000 Privas Rhone-Alpes 07000",
    "addr:housenumber":"1",
    "addr:postcode":"07000;07000",
    "addr:street":"Cours De L'Esplanade",
    "iso:country":"FR",
    "sg:address":"1, Cours de l'Esplanade, 07000 Privas",
    "sg:orig_category":"Unclassifiable Establishments",
    "sg:phone":"+33 4 75 64 23 65",
    "sg:postcode":"07000",
    "sg:province":"Rhone-Alpes",
    "wof:name":"Cabinet Guymathevet S.a.",
    "wof:placetype":"venue"
},
  "geometry": {"coordinates":[4.599022,44.734543],"type":"Point"}
}