{
  "type": "Feature",
  "properties": {
    "iso:country":"FR",
    "sg:address":"1, Cours de l'Esplanade, 07000 Privas",
    "sg:orig_category":"Unclassifiable Establishments",
    "sg:phone":"+33 4 75 64 23 65",
    "sg:postcode":"07000",
    "sg:province":"Rhone-Alpes",
    "wof:name":"Cabinet Guymathevet S.a.",
    "wof:placetype":"venue"
},
  "geometry": {"coordinates":[4.599022,44.734543],"type":"Point"}
}