{
  "type": "Feature",
  "properties": {
    "addr:full":"Z.A.C. du Haut Vigneau Gradignan Aquitaine 33170",
    "addr:postcode":"33170",
    "addr:street":"Z.A.C. Du Haut Vigneau",
    "iso:country":"FR",
    "sg:address":"Z.A.C. du Haut Vigneau",
    "sg:city":"Gradignan",
    "sg:orig_category":"Unclassifiable Establishments",
    "sg:phone":"+33 5 57 35 40 00",
    "sg:postcode":"33170",
    "sg:province":"Aquitaine",
    "wof:name":"Davigel S.a.",
    "wof:placetype":"venue"
},
  "geometry": {"coordinates":[-0.614138,44.773132],"type":"Point"}
}