{
  "type": "Feature",
  "properties": {
    "iso:country":"FR",
    "sg:address":"7/9, Rue L\u00e9on Geoffroy, 94400 Vitry sur Seine",
    "sg:orig_category":"Unclassifiable Establishments",
    "sg:phone":"+33 1 47 18 38 38",
    "sg:province":"Ile de France",
    "wof:name":"D8 S.a.",
    "wof:placetype":"venue"
},
  "geometry": {"coordinates":[2.409091,48.775074],"type":"Point"}
}