{
  "type": "Feature",
  "properties": {
    "addr:full":"3, Rue des Chantiers, 71160 Digoin Digoin Bourgogne 71160",
    "addr:housenumber":"3",
    "addr:postcode":"71160;71160",
    "addr:street":"Rue Des Chantiers",
    "iso:country":"FR",
    "sg:address":"3, Rue des Chantiers, 71160 Digoin",
    "sg:city":"Digoin",
    "sg:orig_category":"Non-Classified Establishments",
    "sg:phone":"+33 3 85 53 37 48",
    "sg:postcode":"71160",
    "sg:province":"Bourgogne",
    "wof:name":"C.c.e. S.a.",
    "wof:placetype":"venue"
},
  "geometry": {"coordinates":[3.985418,46.478798],"type":"Point"}
}