{
  "type": "Feature",
  "properties": {
    "addr:full":"4 avenue le Verrier 78190 Trappes Ile de France 78190",
    "addr:housenumber":"4",
    "addr:postcode":"78190;ile;78190",
    "addr:street":"Avenue Le Verrier;France",
    "iso:country":"FR",
    "sg:address":"4 avenue le Verrier 78190 Trappes",
    "sg:orig_category":"Flacons",
    "sg:phone":"+33 1 30 13 93 00",
    "sg:postcode":"78190",
    "sg:province":"Ile de France",
    "wof:name":"Rps Top Emballage S.a.",
    "wof:placetype":"venue"
},
  "geometry": {"coordinates":[1.975414,48.787487],"type":"Point"}
}