{
  "type": "Feature",
  "properties": {
    "addr:full":"27 R De La Vall\u00e9e Maillard 41000 Blois Blois Centre 41000",
    "addr:housenumber":"27",
    "addr:postcode":"41000;41000",
    "addr:street":"R De La Valle\u0301E Maillard",
    "iso:country":"FR",
    "sg:address":"27 R De La Vall\u00e9e Maillard 41000 Blois",
    "sg:city":"Blois",
    "sg:classifiers":[
        {
            "category":"Professional",
            "subcategory":"Advertising",
            "type":"Services"
        }
    ],
    "sg:phone":"+33 2 54 57 35 30",
    "sg:postcode":"41000",
    "sg:province":"Centre",
    "sg:tags":[
        "information",
        "medium",
        "communication"
    ],
    "wof:name":"Saint Gobain Archives Gie",
    "wof:placetype":"venue"
},
  "geometry": {"coordinates":[1.335287,47.611382],"type":"Point"}
}