{
  "type": "Feature",
  "properties": {
    "iso:country":"FR",
    "sg:address":"Rue Galil\u00e9e",
    "sg:city":"Le Haillan",
    "sg:orig_category":"Unclassifiable Establishments",
    "sg:phone":"+33 5 56 13 10 05",
    "sg:postcode":"33185",
    "sg:province":"Aquitaine",
    "wof:name":"P.a.o. System S.a.r.l.",
    "wof:placetype":"venue"
},
  "geometry": {"coordinates":[-0.680535,44.859547],"type":"Point"}
}