{
  "type": "Feature",
  "properties": {
    "iso:country":"FR",
    "sg:address":"3 rue Jacques Bingen; 75017 Paris",
    "sg:classifiers":[
        {
            "category":"Industrial Area",
            "type":"Public Place"
        }
    ],
    "sg:phone":"+33 1 44 15 01 11",
    "sg:province":"Ile de France",
    "sg:tags":[
        "large",
        "private"
    ],
    "wof:name":"Eurazeo",
    "wof:placetype":"venue"
},
  "geometry": {"coordinates":[2.31061,48.88308],"type":"Point"}
}