{
  "type": "Feature",
  "properties": {
    "addr:full":"13, Rue de la S\u00f4ne, 38160 Saint Marcellin Rhone-Alpes 38160",
    "addr:housenumber":"13",
    "addr:postcode":"38160;38160",
    "addr:street":"Rue De La So\u0302Ne;Marcellin Rhone-Alpes",
    "iso:country":"FR",
    "sg:address":"13, Rue de la S\u00f4ne, 38160 Saint Marcellin",
    "sg:orig_category":"Non-Classified Establishments",
    "sg:phone":"+33 4 76 64 90 82",
    "sg:postcode":"38160",
    "sg:province":"Rhone-Alpes",
    "wof:name":"Cintralp S.a.r.l.",
    "wof:placetype":"venue"
},
  "geometry": {"coordinates":[5.310551,45.145313],"type":"Point"}
}