{
  "type": "Feature",
  "properties": {
    "addr:full":"40, Rue du Ponceau, 75002 Paris Ile de France",
    "addr:housenumber":"40",
    "addr:postcode":"75002",
    "addr:street":"Rue Du Ponceau",
    "iso:country":"FR",
    "sg:address":"40, Rue du Ponceau, 75002 Paris",
    "sg:orig_category":"Unclassifiable Establishments",
    "sg:phone":"+33 1 40 41 92 49",
    "sg:province":"Ile de France",
    "wof:name":"Misia S.a.r.l.",
    "wof:placetype":"venue"
},
  "geometry": {"coordinates":[2.352091,48.867817],"type":"Point"}
}