{
  "type": "Feature",
  "properties": {
    "addr:full":"2, Rue Flambourg, 51150 Juvigny Champagne",
    "addr:housenumber":"2",
    "addr:postcode":"51150",
    "addr:street":"Rue Flambourg",
    "iso:country":"FR",
    "sg:address":"2, Rue Flambourg, 51150 Juvigny",
    "sg:orig_category":"Unclassifiable Establishments",
    "sg:phone":"+33 3 26 67 33 47",
    "sg:province":"Champagne",
    "wof:name":"B.c.m. Industrie S.a.r.l.",
    "wof:placetype":"venue"
},
  "geometry": {"coordinates":[4.25437,49.021317],"type":"Point"}
}