{
  "type": "Feature",
  "properties": {
    "addr:full":"83, Rue de Dole, 25000 Besan\u00e7on Franche Comt\u00e9",
    "addr:housenumber":"83",
    "addr:postcode":"25000",
    "addr:street":"Rue De Dole;Franche Comte\u0301",
    "iso:country":"FR",
    "sg:address":"83, Rue de Dole, 25000 Besan\u00e7on",
    "sg:orig_category":"Unclassifiable Establishments",
    "sg:phone":"+33 3 81 41 13 13",
    "sg:province":"Franche Comt\u00e9",
    "wof:name":"Direction R\u00e9gionale Du Commerce Ext\u00e9rieur",
    "wof:placetype":"venue"
},
  "geometry": {"coordinates":[5.99197,47.229664],"type":"Point"}
}