{
  "type": "Feature",
  "properties": {
    "addr:full":"1, Rue Paul Langevin - Parc Saint Jacques II, 54320 Max\u00e9ville Lorraine",
    "addr:housenumber":"1",
    "addr:postcode":"54320",
    "addr:street":"Rue Paul Langevin",
    "iso:country":"FR",
    "sg:address":"1, Rue Paul Langevin - Parc Saint Jacques II, 54320 Max\u00e9ville",
    "sg:orig_category":"Unclassifiable Establishments",
    "sg:phone":"+33 3 83 93 44 00",
    "sg:province":"Lorraine",
    "wof:name":"S.l.i. S.a. - Soci\u00e9t\u00e9 Lorraine D'ing\u00e9nierie",
    "wof:placetype":"venue"
},
  "geometry": {"coordinates":[6.132038,48.704685],"type":"Point"}
}