{
  "type": "Feature",
  "properties": {
    "iso:country":"FR",
    "sg:address":"LD Domaine de Marconnay 49400 Souzay Champigny",
    "sg:classifiers":[
        {
            "category":"Wholesale",
            "subcategory":"Wine & Distilled Alcoholic Beverages",
            "type":"Manufacturing & Wholesale Goods"
        }
    ],
    "sg:phone":"+33 2 41 67 24 14",
    "sg:postcode":"49400",
    "sg:province":"Pays de Loire",
    "sg:tags":[
        "french"
    ],
    "wof:name":"Herv\u00e9 Goumain Sarl",
    "wof:placetype":"venue"
},
  "geometry": {"coordinates":[-0.068679,47.2145],"type":"Point"}
}