{
  "type": "Feature",
  "properties": {
    "addr:full":"46250 Marminiac Midi Pyr\u00e9n\u00e9es",
    "addr:postcode":"46250",
    "iso:country":"FR",
    "sg:address":"46250 Marminiac",
    "sg:classifiers":[
        {
            "category":"Home & Garden",
            "subcategory":"Furniture",
            "type":"Retail Goods"
        }
    ],
    "sg:phone":"+33 5 65 22 82 34",
    "sg:province":"Midi Pyr\u00e9n\u00e9es",
    "sg:tags":[
        "wood"
    ],
    "wof:name":"Galiacy Et Fils",
    "wof:placetype":"venue"
},
  "geometry": {"coordinates":[1.193845,44.666466],"type":"Point"}
}