{
  "type": "Feature",
  "properties": {
    "iso:country":"FR",
    "sg:address":"Zi De Rousset Av Ville Vieille 13106 Rousset Cedex",
    "sg:city":"Vill\u00e9",
    "sg:classifiers":[
        {
            "category":"Manufacturing",
            "subcategory":"Tools & Machinery",
            "type":"Manufacturing & Wholesale Goods"
        }
    ],
    "sg:phone":"+33 4 42 29 10 20",
    "sg:postcode":"67220",
    "sg:province":"Alsace",
    "sg:tags":[
        "equipment",
        "measurement",
        "-",
        "precision",
        "instrument"
    ],
    "wof:name":"Test Innovation Sa",
    "wof:placetype":"venue"
},
  "geometry": {"coordinates":[5.612044,43.473206],"type":"Point"}
}