{
  "type": "Feature",
  "properties": {
    "addr:full":"40, Rue de Bailleul, 62580 Th\u00e9lus Nord Pas-de-Calais",
    "addr:housenumber":"40",
    "addr:postcode":"62580",
    "addr:street":"Rue De Bailleul",
    "iso:country":"FR",
    "sg:address":"40, Rue de Bailleul, 62580 Th\u00e9lus",
    "sg:orig_category":"Unclassifiable Establishments",
    "sg:phone":"+33 3 21 73 72 35",
    "sg:province":"Nord Pas-de-Calais",
    "wof:name":"Poteaux S.a.",
    "wof:placetype":"venue"
},
  "geometry": {"coordinates":[2.806075,50.35257],"type":"Point"}
}