{
  "type": "Feature",
  "properties": {
    "iso:country":"FR",
    "sg:address":"460 Av Quiera 06370 Mouans Sartoux",
    "sg:classifiers":[
        {
            "category":"Manufacturing",
            "subcategory":"Paper Products",
            "type":"Manufacturing & Wholesale Goods"
        }
    ],
    "sg:phone":"+33 4 93 75 55 00",
    "sg:province":"Midi Pyr\u00e9n\u00e9es",
    "sg:tags":[
        "cardb",
        "material",
        "-",
        "miscellaneous",
        "packaging",
        "cardboard"
    ],
    "wof:name":"Papeterie Provencale Sa",
    "wof:placetype":"venue"
},
  "geometry": {"coordinates":[6.956253,43.606804],"type":"Point"}
}