{
  "type": "Feature",
  "properties": {
    "iso:country":"FR",
    "sg:address":"4, Rue Claude Gonin - ZI Montaudran, 31400 Toulouse",
    "sg:orig_category":"Unclassifiable Establishments",
    "sg:phone":"+33 5 61 36 83 00",
    "sg:province":"Midi Pyr\u00e9n\u00e9es",
    "wof:name":"Bernard Pag\u00e8s",
    "wof:placetype":"venue"
},
  "geometry": {"coordinates":[1.4579,43.57795],"type":"Point"}
}