{
  "type": "Feature",
  "properties": {
    "iso:country":"FR",
    "sg:address":"B.P. 1601, 68016 Colmar C\u00e9dex^^20, Rue Andr\u00e9 Kiener - Zone Industrielle Nord, 68000 Colmar",
    "sg:city":"Colmar",
    "sg:orig_category":"Non-Classified Establishments",
    "sg:phone":"+33 3 89 20 12 12",
    "sg:postcode":"68000",
    "sg:province":"Alsace",
    "wof:name":"Vossloh Schwabe France S.a.r.l.",
    "wof:placetype":"venue"
},
  "geometry": {"coordinates":[7.363583,48.081985],"type":"Point"}
}