{
  "type": "Feature",
  "properties": {
    "addr:full":"B.P. 90185, 86962 Futuroscope Chasseneuil C\u00e9dex^^16, Bd des Fr\u00e8res Lumi\u00e8re, 86960 Chasseneuil du Poi Auvergne",
    "addr:housenumber":"86962",
    "addr:postcode":"86960",
    "addr:street":"Futuroscope Chasseneuil;Bd Des Fre\u0300Res Lumie\u0300Re;Poi",
    "iso:country":"FR",
    "sg:address":"B.P. 90185, 86962 Futuroscope Chasseneuil C\u00e9dex^^16, Bd des Fr\u00e8res Lumi\u00e8re, 86960 Chasseneuil du Poi",
    "sg:orig_category":"Non-Classified Establishments",
    "sg:phone":"+33 5 49 49 45 10",
    "sg:province":"Auvergne",
    "wof:name":"Ant\u00e9a",
    "wof:placetype":"venue"
},
  "geometry": {"coordinates":[4.07363,46.86726],"type":"Point"}
}