{
  "type": "Feature",
  "properties": {
    "addr:full":"1 all\u00e9e du Closeau 93160 Noisy le Grand Ile de France 93160",
    "addr:housenumber":"1",
    "addr:postcode":"93160;93160",
    "addr:street":"Alle\u0301E Du Closeau",
    "iso:country":"FR",
    "sg:address":"1 all\u00e9e du Closeau 93160 Noisy le Grand",
    "sg:classifiers":[
        {
            "category":"Professional",
            "subcategory":"Art Services",
            "type":"Services"
        }
    ],
    "sg:phone":"+33 1 48 15 41 80",
    "sg:postcode":"93160",
    "sg:province":"Ile de France",
    "sg:tags":[
        "-d",
        "design",
        "structure",
        "modelling"
    ],
    "wof:name":"Ste Modelage Ile De France S.a.r.l.",
    "wof:placetype":"venue"
},
  "geometry": {"coordinates":[2.575883,48.836182],"type":"Point"}
}