{
  "type": "Feature",
  "properties": {
    "iso:country":"FR",
    "sg:address":"Les Chalards 24310 St Crepin De Richemont",
    "sg:city":"La Gonterie-Boulouneix",
    "sg:classifiers":[
        {
            "category":"Shopping",
            "subcategory":"Clothing, Apparel, & Fashions",
            "type":"Retail Goods"
        }
    ],
    "sg:phone":"+33 5 53 05 38 24",
    "sg:postcode":"24310",
    "sg:province":"Aquitaine",
    "sg:tags":[
        "textile",
        "clothing",
        "clothes"
    ],
    "wof:name":"Confection Des Chalards (cdc)",
    "wof:placetype":"venue"
},
  "geometry": {"coordinates":[0.638531,45.289734],"type":"Point"}
}