{
  "type": "Feature",
  "properties": {
    "addr:full":"250, Rue Victor Baltard - ZI les Milles - Le Phoebus, 13854 Aix en Provence C\u00e9dex 03^^250, Rue Victo Auvergne",
    "addr:housenumber":"250;03 ^ ^ 250",
    "addr:postcode":"13854",
    "addr:street":"Rue Victor Baltard Zi Les Milles Le Phoebus;Ce\u0301Dex;Rue Victo",
    "iso:country":"FR",
    "sg:address":"250, Rue Victor Baltard - ZI les Milles - Le Phoebus, 13854 Aix en Provence C\u00e9dex 03^^250, Rue Victo",
    "sg:orig_category":"Non-Classified Establishments",
    "sg:phone":"+33 4 42 24 41 35",
    "sg:province":"Auvergne",
    "wof:name":"Lignes S.a.r.l.",
    "wof:placetype":"venue"
},
  "geometry": {"coordinates":[3.682456,46.0476],"type":"Point"}
}