{
  "type": "Feature",
  "properties": {
    "iso:country":"FR",
    "sg:address":"3 Chemin De La Cote 69800 St Priest",
    "sg:classifiers":[
        {
            "category":"Utilities",
            "subcategory":"Electric",
            "type":"Services"
        }
    ],
    "sg:phone":"+33 4 72 35 37 37",
    "sg:postcode":"69800",
    "sg:province":"Rhone-Alpes",
    "sg:tags":[
        "electricity",
        "electronic",
        "electrical",
        "equipment"
    ],
    "wof:name":"Alstom T Et D Sa",
    "wof:placetype":"venue"
},
  "geometry": {"coordinates":[4.921485,45.717819],"type":"Point"}
}