{
  "type": "Feature",
  "properties": {
    "iso:country":"FR",
    "sg:address":"Rue De L'Armor 22390 Bourbriac",
    "sg:city":"Bourbriac",
    "sg:classifiers":[
        {
            "category":"Farming",
            "subcategory":"Crops",
            "type":"Manufacturing & Wholesale Goods"
        }
    ],
    "sg:phone":"+33 2 96 43 43 41",
    "sg:postcode":"22390",
    "sg:province":"Bretagne",
    "sg:tags":[
        "horticulture",
        "mech",
        "livestock",
        "-",
        "equipment",
        "grain",
        "machinery",
        "cereal",
        "agriculture"
    ],
    "wof:name":"Coopagri",
    "wof:placetype":"venue"
},
  "geometry": {"coordinates":[-3.186531,48.476494],"type":"Point"}
}