{
  "type": "Feature",
  "properties": {
    "addr:full":"7, Rue Commines, 75003 Paris Ile de France",
    "addr:housenumber":"7",
    "addr:postcode":"75003",
    "addr:street":"Rue Commines",
    "iso:country":"FR",
    "sg:address":"7, Rue Commines, 75003 Paris",
    "sg:orig_category":"Non-Classified Establishments",
    "sg:phone":"+33 1 42 77 12 06",
    "sg:province":"Ile de France",
    "wof:name":"In Folio",
    "wof:placetype":"venue"
},
  "geometry": {"coordinates":[2.365619,48.862083],"type":"Point"}
}