{
  "type": "Feature",
  "properties": {
    "addr:full":"Zone Artisanale Beauchastel Rhone-Alpes 07800",
    "addr:postcode":"07800",
    "addr:street":"Zone Artisanale;Rhone-Alpes",
    "iso:country":"FR",
    "sg:address":"Zone Artisanale",
    "sg:city":"Beauchastel",
    "sg:orig_category":"Non-Classified Establishments",
    "sg:phone":"+33 4 75 85 17 81",
    "sg:postcode":"07800",
    "sg:province":"Rhone-Alpes",
    "wof:name":"Simen S.a.",
    "wof:placetype":"venue"
},
  "geometry": {"coordinates":[4.8004,44.825081],"type":"Point"}
}