{
  "type": "Feature",
  "properties": {
    "iso:country":"FR",
    "sg:address":"145 Rue Dannemarie 68480 Durlinsdorf",
    "sg:city":"Linsdorf",
    "sg:classifiers":[
        {
            "category":"Professional",
            "subcategory":"Engineering",
            "type":"Services"
        }
    ],
    "sg:phone":"+33 3 89 40 80 10",
    "sg:postcode":"68480",
    "sg:province":"Alsace",
    "sg:tags":[
        "machine",
        "-",
        "mechanical"
    ],
    "wof:name":"Lutz Edmond Et Fils Etablissemnents Sa",
    "wof:placetype":"venue"
},
  "geometry": {"coordinates":[7.240066,47.48521],"type":"Point"}
}