{
  "type": "Feature",
  "properties": {
    "addr:full":"Place Ch\u00e2teau; Fos Ch\u00e2teau Bourgogne 71250",
    "addr:postcode":"71250",
    "addr:street":"Place Cha\u0302Teau",
    "iso:country":"FR",
    "sg:address":"Place Ch\u00e2teau; Fos",
    "sg:city":"Ch\u00e2teau",
    "sg:classifiers":[
        {
            "category":"Banks & Credit Unions",
            "subcategory":"Bank",
            "type":"Services"
        }
    ],
    "sg:phone":"+33 3342050268",
    "sg:postcode":"71250",
    "sg:province":"Bourgogne",
    "wof:name":"Caisse R\u00e9gionale De, Cr\u00e9dit Agricole (c.r.c.a.)",
    "wof:placetype":"venue"
},
  "geometry": {"coordinates":[3.246251,43.566906],"type":"Point"}
}