{
  "type": "Feature",
  "properties": {
    "iso:country":"FR",
    "sg:address":"46, Rue du Chemin Vert, 75011 Paris",
    "sg:orig_category":"Unclassifiable Establishments",
    "sg:phone":"+33 1 43 55 78 78",
    "sg:province":"Ile de France",
    "wof:name":"Gacec S.a.r.l.",
    "wof:placetype":"venue"
},
  "geometry": {"coordinates":[2.374603,48.858875],"type":"Point"}
}