{
  "type": "Feature",
  "properties": {
    "addr:full":"3 Rue Albert Gerig 67540 Ostwald Ostwald Alsace 67540",
    "addr:housenumber":"3",
    "addr:postcode":"67540;67540",
    "addr:street":"Rue Albert Gerig",
    "iso:country":"FR",
    "sg:address":"3 Rue Albert Gerig 67540 Ostwald",
    "sg:city":"Ostwald",
    "sg:classifiers":[
        {
            "category":"Manufacturing",
            "subcategory":"Glass & Minerals",
            "type":"Manufacturing & Wholesale Goods"
        }
    ],
    "sg:phone":"+33 3 88 10 04 40",
    "sg:postcode":"67540",
    "sg:province":"Alsace",
    "sg:tags":[
        "building",
        "material"
    ],
    "wof:name":"Beton De France Rhones-alpes",
    "wof:placetype":"venue"
},
  "geometry": {"coordinates":[7.713311,48.552765],"type":"Point"}
}