{
  "type": "Feature",
  "properties": {
    "addr:full":"B.P. 1, 82303 Caussade C\u00e9dex^^55, Bd Edouard Herriot, 82300 Caussade Midi Pyr\u00e9n\u00e9es 82300",
    "addr:housenumber":"1",
    "addr:postcode":"82303;ce\u0301dex^^55;82300;82300",
    "addr:street":"B.P.;Bd Edouard Herriot",
    "iso:country":"FR",
    "sg:address":"B.P. 1, 82303 Caussade C\u00e9dex^^55, Bd Edouard Herriot, 82300 Caussade",
    "sg:orig_category":"Non-Classified Establishments",
    "sg:phone":"+33 5 63 93 14 98",
    "sg:postcode":"82300",
    "sg:province":"Midi Pyr\u00e9n\u00e9es",
    "wof:name":"Apem S.a.",
    "wof:placetype":"venue"
},
  "geometry": {"coordinates":[1.605065,44.145657],"type":"Point"}
}