{
  "type": "Feature",
  "properties": {
    "addr:full":"13 Rue Emile Zola 59730 Solesmes Nord Pas-de-Calais 59730",
    "addr:housenumber":"13",
    "addr:postcode":"59730;59730",
    "addr:street":"Rue Emile Zola",
    "iso:country":"FR",
    "sg:address":"13 Rue Emile Zola 59730 Solesmes",
    "sg:classifiers":[
        {
            "category":"Professional",
            "subcategory":"Business Services",
            "type":"Services"
        }
    ],
    "sg:phone":"+33 3 27 37 33 77",
    "sg:postcode":"59730",
    "sg:province":"Nord Pas-de-Calais",
    "sg:tags":[
        "training",
        "advice"
    ],
    "wof:name":"Institution Saint Michel",
    "wof:placetype":"venue"
},
  "geometry": {"coordinates":[3.503155,50.183994],"type":"Point"}
}