{
  "type": "Feature",
  "properties": {
    "addr:full":"95 Bis Rue De Lille 59300 Valenciennes Nord Pas-de-Calais 59300",
    "addr:housenumber":"95 bis",
    "addr:postcode":"59300;59300",
    "addr:street":"Rue De Lille",
    "iso:country":"FR",
    "sg:address":"95 Bis Rue De Lille 59300 Valenciennes",
    "sg:classifiers":[
        {
            "category":"Food & Beverages",
            "subcategory":"Groceries & Convenience Stores",
            "type":"Retail Goods"
        }
    ],
    "sg:phone":"+33 3 27 46 20 51",
    "sg:postcode":"59300",
    "sg:province":"Nord Pas-de-Calais",
    "sg:tags":[
        "product",
        "related"
    ],
    "wof:name":"Fran\u00c7ois Traiteur",
    "wof:placetype":"venue"
},
  "geometry": {"coordinates":[3.52252,50.36132],"type":"Point"}
}