{
  "type": "Feature",
  "properties": {
    "addr:full":"Domaine de Rouret 07120 Grospierres Rhone-Alpes",
    "addr:postcode":"07120",
    "iso:country":"FR",
    "sg:address":"Domaine de Rouret 07120 Grospierres",
    "sg:orig_category":"Non-Classified Establishments",
    "sg:phone":"+33 4 75 35 77 00",
    "sg:province":"Rhone-Alpes",
    "wof:name":"Ma\u00ebva Sud Ard\u00e8ches Latitudes Le Rouret",
    "wof:placetype":"venue"
},
  "geometry": {"coordinates":[4.27027,44.375458],"type":"Point"}
}