{
  "type": "Feature",
  "properties": {
    "iso:country":"FR",
    "sg:address":"10 avenue F\u00e9lix Louat 60300 Senlis",
    "sg:classifiers":[
        {
            "category":"Sports & Exercise",
            "subcategory":"Ice Rink",
            "type":"Entertainment"
        }
    ],
    "sg:phone":"+33 3 44 62 48 00",
    "sg:postcode":"60300",
    "sg:province":"Picardie",
    "sg:tags":[
        "made",
        "polyvinyl",
        "baseboard",
        "pvc",
        "rigid",
        "chloride"
    ],
    "wof:name":"Planet-wattohm (filiale Legrand) Snc",
    "wof:placetype":"venue"
},
  "geometry": {"coordinates":[2.600344,49.205982],"type":"Point"}
}