{
  "type": "Feature",
  "properties": {
    "iso:country":"FR",
    "sg:address":"B.P. 42, 56302 Pontivy C\u00e9dex^^Z.I. le Sourn, 56300 Pontivy",
    "sg:city":"Pontivy",
    "sg:orig_category":"Non-Classified Establishments",
    "sg:phone":"+33 2 97 25 03 33",
    "sg:postcode":"56300",
    "sg:province":"Bretagne",
    "wof:name":"S.l.p S.n.c. - Soci\u00e9t\u00e9 Laiti\u00e8re De Pontivy",
    "wof:placetype":"venue"
},
  "geometry": {"coordinates":[-2.951319,48.018394],"type":"Point"}
}