{
  "type": "Feature",
  "properties": {
    "addr:full":"Rue des Bruy\u00e8res - ZA Porcelette Lorraine 57890",
    "addr:postcode":"57890",
    "addr:street":"Rue Des Bruye\u0300Res Za Porcelette Lorraine",
    "iso:country":"FR",
    "sg:address":"Rue des Bruy\u00e8res - ZA",
    "sg:city":"Porcelette",
    "sg:orig_category":"Photographie industrielle Photographie publicitaire",
    "sg:phone":"+33 3 87 82 28 00",
    "sg:postcode":"57890",
    "sg:province":"Lorraine",
    "wof:name":"Synchro S.a.r.l.",
    "wof:placetype":"venue"
},
  "geometry": {"coordinates":[6.647132,49.154011],"type":"Point"}
}