{
  "type": "Feature",
  "properties": {
    "addr:full":"12 rue d'Ivry 69004 Lyon Rhone-Alpes",
    "addr:housenumber":"12",
    "addr:postcode":"69004",
    "addr:street":"Rue D'Ivry",
    "iso:country":"FR",
    "sg:address":"12 rue d'Ivry 69004 Lyon",
    "sg:orig_category":"Technical Exhibition Site Equipment For Museums",
    "sg:phone":"+33 4 78 28 62 04",
    "sg:province":"Rhone-Alpes",
    "wof:name":"Maison D'ecanuts Sarl",
    "wof:placetype":"venue"
},
  "geometry": {"coordinates":[4.836801,45.777275],"type":"Point"}
}