{
  "type": "Feature",
  "properties": {
    "iso:country":"FR",
    "sg:address":"16 Rue Du Coll\u00e8ge 37160 Descartes",
    "sg:city":"Descartes",
    "sg:classifiers":[
        {
            "category":"Professional",
            "subcategory":"Business Services",
            "type":"Services"
        }
    ],
    "sg:phone":"+33 2 47 91 26 26",
    "sg:postcode":"37160",
    "sg:province":"Centre",
    "sg:tags":[
        "training",
        "advice"
    ],
    "wof:name":"College Roger Jahan",
    "wof:placetype":"venue"
},
  "geometry": {"coordinates":[0.69636,46.977997],"type":"Point"}
}