{
  "type": "Feature",
  "properties": {
    "iso:country":"FR",
    "sg:address":"12 Rue De L'Epine 67000 Strasbourg",
    "sg:city":"Strasbourg",
    "sg:classifiers":[
        {
            "category":"Manufacturing",
            "subcategory":"Tools & Machinery",
            "type":"Manufacturing & Wholesale Goods"
        }
    ],
    "sg:phone":"+33 3 88 32 41 42",
    "sg:postcode":"67000",
    "sg:province":"Alsace",
    "sg:tags":[
        "metallurgy",
        "finished",
        "-",
        "metalworking",
        "metallic"
    ],
    "wof:name":"Ets Stutz",
    "wof:placetype":"venue"
},
  "geometry": {"coordinates":[7.747921,48.580769],"type":"Point"}
}