{
  "type": "Feature",
  "properties": {
    "iso:country":"FR",
    "sg:address":"185",
    "sg:city":"Aristide Briand 27930 Gravigny",
    "sg:orig_category":"Mechanical Engineering - machines Printing Road transport Transport services",
    "sg:phone":"+33 2 32 38 03 93",
    "sg:postcode":"27930",
    "sg:province":"Haute Normandie",
    "wof:name":"Ams",
    "wof:placetype":"venue"
},
  "geometry": {"coordinates":[1.16725,49.054859],"type":"Point"}
}