{
  "type": "Feature",
  "properties": {
    "addr:full":"64, Rue des P\u00e9cheurs, 03000 Moulins Moulins Auvergne 03000",
    "addr:housenumber":"64",
    "addr:postcode":"03000;03000",
    "addr:street":"Rue Des Pe\u0301Cheurs",
    "iso:country":"FR",
    "sg:address":"64, Rue des P\u00e9cheurs, 03000 Moulins",
    "sg:city":"Moulins",
    "sg:orig_category":"Unclassifiable Establishments",
    "sg:phone":"+33 4 70 20 72 72",
    "sg:postcode":"03000",
    "sg:province":"Auvergne",
    "wof:name":"E.d.f. Et Gaz De France",
    "wof:placetype":"venue"
},
  "geometry": {"coordinates":[3.32655,46.566509],"type":"Point"}
}