{
  "type": "Feature",
  "properties": {
    "addr:full":"B.P. 23, 67037 Strasbourg C\u00e9dex 2^^9, Rue Jacob Mayer, 67000 Strasbourg Strasbourg Alsace 67000",
    "addr:housenumber":"2 ^ ^ 9",
    "addr:postcode":"67037;67000;67000",
    "addr:street":"B.P. 23;Ce\u0301Dex;Rue Jacob Mayer",
    "iso:country":"FR",
    "sg:address":"B.P. 23, 67037 Strasbourg C\u00e9dex 2^^9, Rue Jacob Mayer, 67000 Strasbourg",
    "sg:city":"Strasbourg",
    "sg:orig_category":"Non-Classified Establishments",
    "sg:phone":"+33 3 88 77 79 79",
    "sg:postcode":"67000",
    "sg:province":"Alsace",
    "wof:name":"A.d.p. - G.s.i. France S.a.s.",
    "wof:placetype":"venue"
},
  "geometry": {"coordinates":[7.73643,48.585079],"type":"Point"}
}