{
  "type": "Feature",
  "properties": {
    "iso:country":"FR",
    "sg:address":"Les Vignerons du Tursan 40320 GEAUNE",
    "sg:city":"Geaune",
    "sg:classifiers":[
        {
            "category":"Wholesale",
            "subcategory":"Wine & Distilled Alcoholic Beverages",
            "type":"Manufacturing & Wholesale Goods"
        }
    ],
    "sg:phone":"+33 5 58 44 51 25",
    "sg:postcode":"40320",
    "sg:province":"Aquitaine",
    "sg:tags":[
        "french"
    ],
    "wof:name":"Les Vignerons Du Tursan",
    "wof:placetype":"venue"
},
  "geometry": {"coordinates":[-0.446669,43.564331],"type":"Point"}
}