{
  "type": "Feature",
  "properties": {
    "iso:country":"FR",
    "sg:address":"83, Av. Antoine Peccot, 44700 Orvault",
    "sg:orig_category":"Unclassifiable Establishments",
    "sg:phone":"+33 2 40 63 09 23",
    "sg:province":"Pays de Loire",
    "wof:name":"Ateliers De La Choli\u00e8re",
    "wof:placetype":"venue"
},
  "geometry": {"coordinates":[-1.615084,47.254314],"type":"Point"}
}