{
  "type": "Feature",
  "properties": {
    "addr:full":"Rte de Bouvaincourt Beauchamps Picardie 80770",
    "addr:postcode":"80770",
    "addr:street":"Rte De Bouvaincourt;Picardie",
    "iso:country":"FR",
    "sg:address":"Rte de Bouvaincourt",
    "sg:city":"Beauchamps",
    "sg:orig_category":"Unclassifiable Establishments",
    "sg:phone":"+33 3 22 26 15 55",
    "sg:postcode":"80770",
    "sg:province":"Picardie",
    "wof:name":"A.p.b. S.a. - Aff\u00fbtage De Pr\u00e9cision De La Bresle",
    "wof:placetype":"venue"
},
  "geometry": {"coordinates":[1.500966,50.023937],"type":"Point"}
}