{
  "type": "Feature",
  "properties": {
    "iso:country":"FR",
    "sg:address":"14 Rue De Birague 75004 Paris",
    "sg:classifiers":[
        {
            "category":"Shopping",
            "subcategory":"Clothing, Apparel, & Fashions",
            "type":"Retail Goods"
        }
    ],
    "sg:phone":"+33 1 48 87 58 08",
    "sg:postcode":"75004",
    "sg:province":"Ile de France",
    "sg:tags":[
        "textile",
        "clothing",
        "clothes"
    ],
    "wof:name":"Bernard Zins Pour La Femme Sarl",
    "wof:placetype":"venue"
},
  "geometry": {"coordinates":[2.365404,48.854725],"type":"Point"}
}