{
  "type": "Feature",
  "properties": {
    "iso:country":"FR",
    "sg:address":"11-13 Av Ferdinand de Lesse; Morangis; 91420",
    "sg:classifiers":[
        {
            "category":"Banks & Credit Unions",
            "subcategory":"Bank",
            "type":"Services"
        }
    ],
    "sg:phone":"+33 1 64 48 45 31",
    "sg:postcode":"91420",
    "sg:province":"Ile de France",
    "wof:name":"Bics Banque Populaire",
    "wof:placetype":"venue"
},
  "geometry": {"coordinates":[2.338108,48.698063],"type":"Point"}
}