{
  "type": "Feature",
  "properties": {
    "addr:full":"1, Rue Emile Schwoerer, 68000 Colmar Colmar Alsace 68000",
    "addr:housenumber":"1",
    "addr:postcode":"68000;68000",
    "addr:street":"Rue Emile Schwoerer",
    "iso:country":"FR",
    "sg:address":"1, Rue Emile Schwoerer, 68000 Colmar",
    "sg:city":"Colmar",
    "sg:orig_category":"Unclassifiable Establishments",
    "sg:phone":"+33 3 89 41 48 13",
    "sg:postcode":"68000",
    "sg:province":"Alsace",
    "wof:name":"S.a.m.a.g. S.a. - Soci\u00e9t\u00e9 Des Appareils M\u00e9nagers Application Gaz",
    "wof:placetype":"venue"
},
  "geometry": {"coordinates":[7.370511,48.101166],"type":"Point"}
}