{
  "type": "Feature",
  "properties": {
    "addr:full":"Ld La Garenne 34560 Poussan Languedoc-Roussillon 34560",
    "addr:postcode":"34560;34560",
    "addr:street":"Ld La Garenne",
    "iso:country":"FR",
    "sg:address":"Ld La Garenne 34560 Poussan",
    "sg:classifiers":[
        {
            "category":"Building & Trades",
            "subcategory":"Construction",
            "type":"Services"
        }
    ],
    "sg:phone":"+33 4 67 78 28 08",
    "sg:postcode":"34560",
    "sg:province":"Languedoc-Roussillon",
    "sg:tags":[
        "work",
        "public"
    ],
    "wof:name":"Nebot Daniel",
    "wof:placetype":"venue"
},
  "geometry": {"coordinates":[3.66836,43.482121],"type":"Point"}
}