{
  "type": "Feature",
  "properties": {
    "iso:country":"FR",
    "sg:address":"43, Rue Chenevi\u00e8res - ZI de Chenevi\u00e8res, 54450 B\u00e9nam\u00e9nil",
    "sg:orig_category":"Non-Classified Establishments",
    "sg:phone":"+33 3 83 71 11 40",
    "sg:postcode":"54450",
    "sg:province":"Lorraine",
    "wof:name":"Bornet Daniel S.a.",
    "wof:placetype":"venue"
},
  "geometry": {"coordinates":[6.8423,48.590405],"type":"Point"}
}