{
  "type": "Feature",
  "properties": {
    "addr:full":"Rue Andr\u00e9 Amp\u00e8re De Jarlard 81000 Albi Midi Pyr\u00e9n\u00e9es 81000",
    "addr:postcode":"81000;81000",
    "addr:street":"Rue Andre\u0301 Ampe\u0300Re De Jarlard",
    "iso:country":"FR",
    "sg:address":"Rue Andr\u00e9 Amp\u00e8re",
    "sg:city":"De Jarlard 81000 Albi",
    "sg:classifiers":[
        {
            "category":"Food & Beverages",
            "subcategory":"Groceries & Convenience Stores",
            "type":"Retail Goods"
        }
    ],
    "sg:phone":"+33 5 63 46 02 24",
    "sg:postcode":"81000",
    "sg:province":"Midi Pyr\u00e9n\u00e9es",
    "sg:tags":[
        "processing",
        "-",
        "equipment",
        "machinery",
        "animal",
        "breeding",
        "agriculture"
    ],
    "wof:name":"Tsi",
    "wof:placetype":"venue"
},
  "geometry": {"coordinates":[2.148375,43.926205],"type":"Point"}
}