{
  "type": "Feature",
  "properties": {
    "addr:full":"7 Rue Du Docteur Arnaudet 92190 Meudon Ile de France 92190",
    "addr:housenumber":"7",
    "addr:postcode":"92190;92190",
    "addr:street":"Rue Du Docteur Arnaudet",
    "iso:country":"FR",
    "sg:address":"7 Rue Du Docteur Arnaudet 92190 Meudon",
    "sg:classifiers":[
        {
            "category":"Shopping",
            "subcategory":"Clothing, Apparel, & Fashions",
            "type":"Retail Goods"
        }
    ],
    "sg:phone":"+33 1 45 07 05 08",
    "sg:postcode":"92190",
    "sg:province":"Ile de France",
    "sg:tags":[
        "textile",
        "clothing",
        "clothes"
    ],
    "wof:name":"Repass Clair",
    "wof:placetype":"venue"
},
  "geometry": {"coordinates":[2.248172,48.814655],"type":"Point"}
}