{
  "type": "Feature",
  "properties": {
    "iso:country":"FR",
    "sg:address":"13/15, Rue de Calais, 75320 Paris C\u00e9dex 9",
    "sg:orig_category":"Non-Classified Establishments",
    "sg:phone":"+33 1 48 20 61 65",
    "sg:province":"Nord Pas-de-Calais",
    "wof:name":"Cerp France S.a.",
    "wof:placetype":"venue"
},
  "geometry": {"coordinates":[2.330659,48.882404],"type":"Point"}
}