{
  "type": "Feature",
  "properties": {
    "addr:full":"39 Rue De Paris 93000 Bobigny Ile de France 93000",
    "addr:housenumber":"39",
    "addr:postcode":"93000;ile;93000",
    "addr:street":"Rue De Paris;France",
    "iso:country":"FR",
    "sg:address":"39 Rue De Paris 93000 Bobigny",
    "sg:classifiers":[
        {
            "category":"Manufacturing",
            "subcategory":"Tools & Machinery",
            "type":"Manufacturing & Wholesale Goods"
        }
    ],
    "sg:phone":"+33 1 48 40 32 32",
    "sg:postcode":"93000",
    "sg:province":"Ile de France",
    "sg:tags":[
        "metallurgy",
        "metalworking"
    ],
    "wof:name":"Baktor Sa",
    "wof:placetype":"venue"
},
  "geometry": {"coordinates":[2.44439,48.898991],"type":"Point"}
}