{
  "type": "Feature",
  "properties": {
    "iso:country":"FR",
    "sg:address":"93 Avenue De Montolivet 13004 Marseille",
    "sg:classifiers":[
        {
            "category":"Professional",
            "subcategory":"Business Services",
            "type":"Services"
        }
    ],
    "sg:phone":"+33 4 91 34 95 49",
    "sg:province":"Poitou-Charentes",
    "sg:tags":[
        "body",
        "advice"
    ],
    "wof:name":"Ass Stella Aide Aux Familles",
    "wof:placetype":"venue"
},
  "geometry": {"coordinates":[5.406182,43.309696],"type":"Point"}
}