{
  "type": "Feature",
  "properties": {
    "addr:full":"Rue Pierre et Marie Curie Cholet Pays de Loire 49300",
    "addr:postcode":"49300",
    "addr:street":"Rue Pierre Et Marie Curie",
    "iso:country":"FR",
    "sg:address":"Rue Pierre et Marie Curie",
    "sg:city":"Cholet",
    "sg:orig_category":"Non-Classified Establishments",
    "sg:phone":"+33 2 41 75 91 57",
    "sg:postcode":"49300",
    "sg:province":"Pays de Loire",
    "wof:name":"Erbe Exploitation Produits Erbe S.a.",
    "wof:placetype":"venue"
},
  "geometry": {"coordinates":[-0.863134,47.070953],"type":"Point"}
}