{
  "type": "Feature",
  "properties": {
    "iso:country":"FR",
    "sg:address":"Le Tr\u00e8ve",
    "sg:city":"Le Perr\u00e9on",
    "sg:orig_category":"Non-Classified Establishments",
    "sg:phone":"+33 4 74 02 10 10",
    "sg:postcode":"69460",
    "sg:province":"Rhone-Alpes",
    "wof:name":"Fran\u00e7ois Paquet S.a.",
    "wof:placetype":"venue"
},
  "geometry": {"coordinates":[4.594985,46.062561],"type":"Point"}
}