{
  "type": "Feature",
  "properties": {
    "addr:full":"33, Rue du Mort Ru, 91310 Longpont sur Orge Ile de France 91310",
    "addr:housenumber":"33",
    "addr:postcode":"91310;91310",
    "addr:street":"Rue Du Mort Ru",
    "iso:country":"FR",
    "sg:address":"33, Rue du Mort Ru, 91310 Longpont sur Orge",
    "sg:orig_category":"Non-Classified Establishments",
    "sg:phone":"+33 1 69 01 63 84",
    "sg:postcode":"91310",
    "sg:province":"Ile de France",
    "wof:name":"D.a.c. S.a. - Diffusion Art Et Couleur",
    "wof:placetype":"venue"
},
  "geometry": {"coordinates":[2.27561,48.652451],"type":"Point"}
}