{
  "type": "Feature",
  "properties": {
    "iso:country":"FR",
    "sg:address":"50, Rue du Commerce, 51350 Cormontreuil",
    "sg:orig_category":"CERTIFI\u00c9E QUALIFELEC Installateur: Installations \u00e9lectriques construction de tableaux \u00e9lectriques \u00e9q",
    "sg:phone":"+33 3 26 85 73 20",
    "sg:postcode":"51350",
    "sg:province":"Champagne",
    "wof:name":"S.e.e.i. Roque Industrie S.a. - Soci\u00e9t\u00e9 D'equipement Electrique Industriel",
    "wof:placetype":"venue"
},
  "geometry": {"coordinates":[4.063651,49.215893],"type":"Point"}
}