{
  "type": "Feature",
  "properties": {
    "addr:full":"85, Rue de la Richelandi\u00e8re, 42100 Saint Etienne Rhone-Alpes 42100",
    "addr:housenumber":"85",
    "addr:postcode":"42100;42100",
    "addr:street":"Rue De La Richelandie\u0300Re",
    "iso:country":"FR",
    "sg:address":"85, Rue de la Richelandi\u00e8re, 42100 Saint Etienne",
    "sg:orig_category":"Non-Classified Establishments",
    "sg:phone":"+33 4 77 32 31 98",
    "sg:postcode":"42100",
    "sg:province":"Rhone-Alpes",
    "wof:name":"Comptoir For\u00e9zien Du Roulement S.a.r.l.",
    "wof:placetype":"venue"
},
  "geometry": {"coordinates":[4.4077,45.437111],"type":"Point"}
}