{
  "type": "Feature",
  "properties": {
    "addr:full":"160 Boulevard De Valmy BP 82 92704 Colombes Cedex \u00cele-de-France",
    "addr:housenumber":"160;82",
    "addr:postcode":"92704;cedex",
    "addr:street":"Boulevard De Valmy Bp",
    "iso:country":"FR",
    "sg:address":"160 Boulevard De Valmy BP 82 92704 Colombes Cedex",
    "sg:classifiers":[
        {
            "category":"Marine",
            "type":"Transportation"
        }
    ],
    "sg:phone":"+33 1 41 30 30 00",
    "sg:province":"\u00cele-de-France",
    "sg:tags":[
        "transport",
        "sea"
    ],
    "wof:name":"Thales Communications",
    "wof:placetype":"venue"
},
  "geometry": {"coordinates":[2.25572,48.93388],"type":"Point"}
}