{
  "type": "Feature",
  "properties": {
    "addr:full":"Zone A\u00e9roportuaire de Semoutiers Chaumont Basse Normandie 52903",
    "addr:postcode":"52903",
    "addr:street":"Zone;Basse",
    "iso:country":"FR",
    "sg:address":"Zone A\u00e9roportuaire de Semoutiers",
    "sg:city":"Chaumont",
    "sg:orig_category":"Unclassifiable Establishments",
    "sg:phone":"+33 3 25 30 52 00",
    "sg:postcode":"52903",
    "sg:province":"Basse Normandie",
    "wof:name":"Les Menuiseries Fran\u00e7aises",
    "wof:placetype":"venue"
},
  "geometry": {"coordinates":[5.1435,48.104141],"type":"Point"}
}