{
  "type": "Feature",
  "properties": {
    "iso:country":"FR",
    "sg:address":"Za 50480 Ste M\u00e8re Eglise",
    "sg:city":"Amfreville",
    "sg:classifiers":[
        {
            "category":"Farming",
            "subcategory":"Livestock Farm",
            "type":"Manufacturing & Wholesale Goods"
        }
    ],
    "sg:phone":"+33 2 33 95 40 10",
    "sg:postcode":"50480",
    "sg:province":"Basse Normandie",
    "sg:tags":[
        "horticulture",
        "pharmaceutical",
        "-",
        "chemical",
        "chemistry",
        "agriculture",
        "by-product"
    ],
    "wof:name":"Agreale Point Vert",
    "wof:placetype":"venue"
},
  "geometry": {"coordinates":[-1.254904,49.35006],"type":"Point"}
}