{
  "type": "Feature",
  "properties": {
    "addr:full":"1, Av. Rudoph Diesel - Parc d'Activit\u00e9s Kennedy - B\u00e2t. A, 33700 M\u00e9rignac M\u00e9rignac Aquitaine 33700",
    "addr:housenumber":"ba\u0302t a",
    "addr:postcode":"33700;33700",
    "addr:street":"Av. Rudoph Diesel Parc D'Activite \u0301S Kennedy",
    "iso:country":"FR",
    "sg:address":"1, Av. Rudoph Diesel - Parc d'Activit\u00e9s Kennedy - B\u00e2t. A, 33700 M\u00e9rignac",
    "sg:city":"M\u00e9rignac",
    "sg:orig_category":"Unclassifiable Establishments",
    "sg:phone":"+33 5 57 92 66 00",
    "sg:postcode":"33700",
    "sg:province":"Aquitaine",
    "wof:name":"M.s.c. France S.a. - M\u00e9diterran\u00e9an Shipping Company",
    "wof:placetype":"venue"
},
  "geometry": {"coordinates":[-0.6817,44.831348],"type":"Point"}
}