{
  "type": "Feature",
  "properties": {
    "iso:country":"FR",
    "sg:address":"Parc d'Activit\u00e9s du Moulin",
    "sg:city":"Fesches le Ch\u00e2tel",
    "sg:orig_category":"Unclassifiable Establishments",
    "sg:phone":"+33 3 81 96 16 47",
    "sg:postcode":"25490",
    "sg:province":"Franche Comt\u00e9",
    "wof:name":"Pompes Japy S.a.",
    "wof:placetype":"venue"
},
  "geometry": {"coordinates":[6.90555,47.523762],"type":"Point"}
}