{
  "type": "Feature",
  "properties": {
    "iso:country":"FR",
    "sg:address":"11 route de Neuf Brisach 68000 Colmar",
    "sg:city":"Colmar",
    "sg:classifiers":[
        {
            "category":"Professional",
            "subcategory":"Employment Agencies",
            "type":"Services"
        }
    ],
    "sg:phone":"+33 3 89 41 41 10",
    "sg:postcode":"68000",
    "sg:province":"Alsace",
    "sg:tags":[
        "personnel",
        "temporary"
    ],
    "wof:name":"Via Interim Sa",
    "wof:placetype":"venue"
},
  "geometry": {"coordinates":[7.362794,48.080063],"type":"Point"}
}