{
  "type": "Feature",
  "properties": {
    "iso:country":"FR",
    "sg:address":"Rte de Saint Paul du Bois",
    "sg:city":"La Plaine",
    "sg:orig_category":"Unclassifiable Establishments",
    "sg:phone":"+33 2 41 55 92 30",
    "sg:postcode":"49360",
    "sg:province":"Pays de Loire",
    "wof:name":"Etablissements Marchand Et Fils S.a.r.l.",
    "wof:placetype":"venue"
},
  "geometry": {"coordinates":[-0.641124,46.999599],"type":"Point"}
}