{
  "type": "Feature",
  "properties": {
    "iso:country":"FR",
    "sg:address":"B.P. 64648, 67457 Mundolsheim C\u00e9dex^^48, Rte de Brumath, 67460 Souffelweyersheim",
    "sg:city":"Souffelweyersheim",
    "sg:orig_category":"Non-Classified Establishments",
    "sg:phone":"+33 3 90 22 58 90",
    "sg:postcode":"67460",
    "sg:province":"Alsace",
    "wof:name":"La Gache Electrique S.a.r.l.",
    "wof:placetype":"venue"
},
  "geometry": {"coordinates":[7.74147,48.635509],"type":"Point"}
}