{
  "type": "Feature",
  "properties": {
    "iso:country":"FR",
    "sg:address":"B.P. 43, 33250 Pauillac C\u00e9dex^^32, Rte des Ch\u00e2teaux, 33250 Pauillac",
    "sg:city":"Pauillac",
    "sg:orig_category":"Non-Classified Establishments",
    "sg:phone":"+33 5 56 59 16 51",
    "sg:postcode":"33250",
    "sg:province":"Aquitaine",
    "wof:name":"Rullier M\u00e9doc E.u.r.l.",
    "wof:placetype":"venue"
},
  "geometry": {"coordinates":[-0.748824,45.199036],"type":"Point"}
}