{
  "type": "Feature",
  "properties": {
    "iso:country":"FR",
    "sg:address":"18, Rue Alfred Rondeaux Hollard, 89260 La Chapelle sur Oreuse",
    "sg:city":"Chapelle-sur-Oreuse",
    "sg:orig_category":"Non-Classified Establishments",
    "sg:phone":"+33 3 86 97 69 59",
    "sg:postcode":"89260",
    "sg:province":"Bourgogne",
    "wof:name":"Sidh Et Banshees Images E.u.r.l.",
    "wof:placetype":"venue"
},
  "geometry": {"coordinates":[3.39958,48.293964],"type":"Point"}
}