{
  "type": "Feature",
  "properties": {
    "addr:full":"Ch\u00e2teau Ph\u00e9lan S\u00e9gur 33180 St Est\u00e8phe Saint-Est\u00e8phe Aquitaine 33180",
    "addr:postcode":"33180;33180",
    "addr:street":"Se\u0301Gur",
    "iso:country":"FR",
    "sg:address":"Ch\u00e2teau Ph\u00e9lan S\u00e9gur 33180 St Est\u00e8phe",
    "sg:city":"Saint-Est\u00e8phe",
    "sg:classifiers":[
        {
            "category":"Food Court",
            "type":"Food & Drink"
        }
    ],
    "sg:phone":"+33 5 56 59 74 00",
    "sg:postcode":"33180",
    "sg:province":"Aquitaine",
    "sg:tags":[
        "product",
        "related"
    ],
    "wof:name":"Chateau Phelan Segur",
    "wof:placetype":"venue"
},
  "geometry": {"coordinates":[-0.79017,45.265709],"type":"Point"}
}