{
  "type": "Feature",
  "properties": {
    "iso:country":"FR",
    "sg:address":"Ferme de Gouberville 76690 Sierville",
    "sg:orig_category":"Non-Classified Establishments",
    "sg:phone":"+33 2 35 32 51 84",
    "sg:province":"Haute Normandie",
    "wof:name":"M.j.r. N\u00e9goce S.a.r.l.",
    "wof:placetype":"venue"
},
  "geometry": {"coordinates":[1.229765,49.532104],"type":"Point"}
}