{
  "type": "Feature",
  "properties": {
    "iso:country":"FR",
    "sg:address":"184, Rte de Nantes, 79000 Niort",
    "sg:orig_category":"Unclassifiable Establishments",
    "sg:phone":"+33 5 49 09 09 12",
    "sg:postcode":"79000",
    "sg:province":"Poitou-Charentes",
    "wof:name":"B\u00e9ton Libaud S.a.",
    "wof:placetype":"venue"
},
  "geometry": {"coordinates":[-0.48928,46.34111],"type":"Point"}
}