{
  "type": "Feature",
  "properties": {
    "iso:country":"FR",
    "sg:address":"28, Rue de Coutelier, 44800 Saint Herblain",
    "sg:orig_category":"Non-Classified Establishments",
    "sg:phone":"+33 2 28 03 03 60",
    "sg:postcode":"44800",
    "sg:province":"Pays de Loire",
    "wof:name":"Brake France Service S.a.s.",
    "wof:placetype":"venue"
},
  "geometry": {"coordinates":[-1.650476,47.220783],"type":"Point"}
}