{
  "type": "Feature",
  "properties": {
    "iso:country":"FR",
    "sg:address":"497 R Ren\u00e9 Cassin BP 406 42354 La Talaudi\u00e8re Cedex",
    "sg:classifiers":[
        {
            "category":"Shopping",
            "subcategory":"Computers & Home Electronics",
            "type":"Retail Goods"
        }
    ],
    "sg:phone":"+33 4 77 47 69 47",
    "sg:province":"Rhone-Alpes",
    "sg:tags":[
        "electronic",
        "electrical",
        "equipment"
    ],
    "wof:name":"Sytelval Sarl",
    "wof:placetype":"venue"
},
  "geometry": {"coordinates":[4.427881,45.466797],"type":"Point"}
}