{
  "type": "Feature",
  "properties": {
    "iso:country":"FR",
    "sg:address":"Zi Moulin Cheyrout 87700 Aixe Sur Vienne",
    "sg:classifiers":[
        {
            "category":"Professional",
            "subcategory":"Engineering",
            "type":"Services"
        }
    ],
    "sg:phone":"+33 5 55 70 98 18",
    "sg:postcode":"87700",
    "sg:province":"Limousin",
    "sg:tags":[
        "machine",
        "-",
        "mechanical"
    ],
    "wof:name":"Alma Concept Sa",
    "wof:placetype":"venue"
},
  "geometry": {"coordinates":[1.137907,45.796898],"type":"Point"}
}