{
  "type": "Feature",
  "properties": {
    "iso:country":"FR",
    "sg:address":"67 avenue d'Estienne d'Orves 06000 Nice",
    "sg:classifiers":[
        {
            "category":"Building & Trades",
            "subcategory":"Pest Control",
            "type":"Services"
        }
    ],
    "sg:phone":"+33 4 93 44 58 59",
    "sg:province":"Franche Comt\u00e9",
    "sg:tags":[
        "insecticide"
    ],
    "wof:name":"Sodimark S.a.r.l.",
    "wof:placetype":"venue"
},
  "geometry": {"coordinates":[7.249691,43.700272],"type":"Point"}
}