{
  "type": "Feature",
  "properties": {
    "addr:full":"25, Rue de Bagneaux, 45140 Saint Jean de la Ruelle Ingr\u00e9 Centre 45140",
    "addr:housenumber":"25",
    "addr:postcode":"45140;45140",
    "addr:street":"Rue De Bagneaux;La Ruelle Ingre\u0301",
    "iso:country":"FR",
    "sg:address":"25, Rue de Bagneaux, 45140 Saint Jean de la Ruelle",
    "sg:city":"Ingr\u00e9",
    "sg:orig_category":"Unclassifiable Establishments",
    "sg:phone":"+33 2 38 88 27 09",
    "sg:postcode":"45140",
    "sg:province":"Centre",
    "wof:name":"Bernardi S.a.",
    "wof:placetype":"venue"
},
  "geometry": {"coordinates":[1.880136,47.914993],"type":"Point"}
}