{
  "type": "Feature",
  "properties": {
    "iso:country":"FR",
    "sg:address":"B.P. 145, 68313 Illzach C\u00e9dex^^74, Av de Belgique, 68110 Illzach",
    "sg:city":"Illzach",
    "sg:orig_category":"Non-Classified Establishments",
    "sg:phone":"+33 3 89 61 73 74",
    "sg:postcode":"68110",
    "sg:province":"Alsace",
    "wof:name":"Tresch S.a.",
    "wof:placetype":"venue"
},
  "geometry": {"coordinates":[7.348394,47.782181],"type":"Point"}
}