{
  "type": "Feature",
  "properties": {
    "addr:full":"B.P. 103, 68703 Cernay C\u00e9dex^^3, Fbg de Belfort, 68700 Cernay Cernay Alsace 68700",
    "addr:housenumber":"b.p. 103",
    "addr:postcode":"68703;68700;68700",
    "addr:street":"Belfort",
    "iso:country":"FR",
    "sg:address":"B.P. 103, 68703 Cernay C\u00e9dex^^3, Fbg de Belfort, 68700 Cernay",
    "sg:city":"Cernay",
    "sg:orig_category":"Non-Classified Establishments",
    "sg:phone":"+33 3 89 75 42 50",
    "sg:postcode":"68700",
    "sg:province":"Alsace",
    "wof:name":"M.f.m. S.a.r.l. - M\u00e9canique Fran\u00e7ois Muller",
    "wof:placetype":"venue"
},
  "geometry": {"coordinates":[7.178375,47.809181],"type":"Point"}
}