{
  "type": "Feature",
  "properties": {
    "iso:country":"FR",
    "sg:address":"La Bareliere 86700 Payre",
    "sg:classifiers":[
        {
            "category":"Farming",
            "subcategory":"Livestock Farm",
            "type":"Manufacturing & Wholesale Goods"
        }
    ],
    "sg:phone":"+33 5 49 42 49 93",
    "sg:postcode":"86700",
    "sg:province":"Poitou-Charentes",
    "sg:tags":[
        "breeding",
        "agriculture",
        "animal"
    ],
    "wof:name":"Sarl Du Berlais",
    "wof:placetype":"venue"
},
  "geometry": {"coordinates":[0.179385,46.33371],"type":"Point"}
}