{
  "type": "Feature",
  "properties": {
    "addr:full":"1, Rue L\u00e9o Lagrange, 79000 Niort Poitou-Charentes 79000",
    "addr:housenumber":"1",
    "addr:postcode":"79000;79000",
    "addr:street":"Rue Le\u0301O Lagrange",
    "iso:country":"FR",
    "sg:address":"1, Rue L\u00e9o Lagrange, 79000 Niort",
    "sg:orig_category":"Unclassifiable Establishments",
    "sg:phone":"+33 5 49 09 09 57",
    "sg:postcode":"79000",
    "sg:province":"Poitou-Charentes",
    "wof:name":"Sigma S.a.r.l.",
    "wof:placetype":"venue"
},
  "geometry": {"coordinates":[-0.469032,46.316006],"type":"Point"}
}