{
  "type": "Feature",
  "properties": {
    "iso:country":"FR",
    "sg:address":"Rue Edouard Branly",
    "sg:city":"Saint Georges sur Eure",
    "sg:orig_category":"Unclassifiable Establishments",
    "sg:phone":"+33 2 37 26 82 00",
    "sg:postcode":"28190",
    "sg:province":"Centre",
    "wof:name":"D.m.a. Industries S.a.",
    "wof:placetype":"venue"
},
  "geometry": {"coordinates":[1.36724,48.419895],"type":"Point"}
}