{
  "type": "Feature",
  "properties": {
    "iso:country":"FR",
    "sg:address":"Rue des Genets - ZI",
    "sg:city":"Clisson",
    "sg:orig_category":"Unclassifiable Establishments",
    "sg:phone":"+33 2 40 54 05 98",
    "sg:postcode":"44190",
    "sg:province":"Pays de Loire",
    "wof:name":"Paillat S.a.r.l.",
    "wof:placetype":"venue"
},
  "geometry": {"coordinates":[-1.185822,47.044689],"type":"Point"}
}