{
  "type": "Feature",
  "properties": {
    "iso:country":"FR",
    "sg:address":"51, Rue de Flandre, 80200 March\u00e9lepot",
    "sg:orig_category":"Unclassifiable Establishments",
    "sg:phone":"+33 3 22 83 90 02",
    "sg:province":"Picardie",
    "wof:name":"Delauzanne S.a.",
    "wof:placetype":"venue"
},
  "geometry": {"coordinates":[2.86464,49.83387],"type":"Point"}
}