{
  "type": "Feature",
  "properties": {
    "iso:country":"FR",
    "sg:address":"6, Rue des Brossillons, 41500 Mer",
    "sg:city":"Mer",
    "sg:orig_category":"Non-Classified Establishments",
    "sg:phone":"+33 2 54 81 39 10",
    "sg:postcode":"41500",
    "sg:province":"Centre",
    "wof:name":"Decover France S.a.r.l.",
    "wof:placetype":"venue"
},
  "geometry": {"coordinates":[1.50874,47.71394],"type":"Point"}
}