{
  "type": "Feature",
  "properties": {
    "iso:country":"FR",
    "sg:address":"16 Place Du Chateau 91590 La Ferte Alais",
    "sg:classifiers":[
        {
            "category":"Manufacturing",
            "subcategory":"Printing",
            "type":"Manufacturing & Wholesale Goods"
        }
    ],
    "sg:phone":"+33 1 64 57 61 38",
    "sg:province":"Ile de France",
    "sg:tags":[
        "publishing"
    ],
    "wof:name":"Id 1 Prim Et Marceau",
    "wof:placetype":"venue"
},
  "geometry": {"coordinates":[2.347694,48.48251],"type":"Point"}
}