{
  "type": "Feature",
  "properties": {
    "iso:country":"FR",
    "sg:address":"7, Rue du Fonds Pernant - Z.A.C. de Merci\u00e8res 3, 60200 Compi\u00e8gne",
    "sg:orig_category":"Non-Classified Establishments",
    "sg:phone":"+33 3 44 30 33 00",
    "sg:province":"Picardie",
    "wof:name":"Hayward Industrial Products France S.a.",
    "wof:placetype":"venue"
},
  "geometry": {"coordinates":[2.825,49.417671],"type":"Point"}
}