{
  "type": "Feature",
  "properties": {
    "addr:full":"102, Av. de Villiers, 75017 Paris Ile de France",
    "addr:postcode":"75017",
    "addr:street":"102 Av. De Villiers",
    "iso:country":"FR",
    "sg:address":"102, Av. de Villiers, 75017 Paris",
    "sg:orig_category":"Unclassifiable Establishments",
    "sg:phone":"+33 1 44 29 17 17",
    "sg:province":"Ile de France",
    "wof:name":"H\u00f4tel Amp\u00e8re",
    "wof:placetype":"venue"
},
  "geometry": {"coordinates":[2.299805,48.884727],"type":"Point"}
}