{
  "type": "Feature",
  "properties": {
    "addr:full":"12, Rue Tessier, 03200 Vichy Vichy Auvergne 03200",
    "addr:housenumber":"12",
    "addr:postcode":"03200;03200",
    "addr:street":"Rue Tessier",
    "iso:country":"FR",
    "sg:address":"12, Rue Tessier, 03200 Vichy",
    "sg:city":"Vichy",
    "sg:orig_category":"Unclassifiable Establishments",
    "sg:phone":"+33 4 70 98 96 77",
    "sg:postcode":"03200",
    "sg:province":"Auvergne",
    "wof:name":"03 France Express S.a.",
    "wof:placetype":"venue"
},
  "geometry": {"coordinates":[3.43305,46.131405],"type":"Point"}
}