{
  "type": "Feature",
  "properties": {
    "iso:country":"FR",
    "sg:address":"12, Rue Paul Langevin - ZI de la Croix Cadeau, 49240 Avrill\u00e9",
    "sg:orig_category":"Unclassifiable Establishments",
    "sg:phone":"+33 2 41 21 13 59",
    "sg:province":"Pays de Loire",
    "wof:name":"S.i.m.p.a. J.d.m. S.a. - Soci\u00e9t\u00e9 Industrielle De Mati\u00e8res Plastiques Arm\u00e9es",
    "wof:placetype":"venue"
},
  "geometry": {"coordinates":[-0.587263,47.504822],"type":"Point"}
}