{
  "type": "Feature",
  "properties": {
    "iso:country":"FR",
    "sg:address":"30, Rue Maurice Delabie, 80220 Bouvaincourt sur Bresle",
    "sg:orig_category":"Non-Classified Establishments",
    "sg:phone":"+33 3 22 30 15 10",
    "sg:province":"Picardie",
    "wof:name":"F.a.b.a.l. S.a.r.l. - Fonderie Aluminium Bronze D'alu Laiton",
    "wof:placetype":"venue"
},
  "geometry": {"coordinates":[1.49411,50.02763],"type":"Point"}
}