{
  "type": "Feature",
  "properties": {
    "addr:full":"228 R Paul Et Camille Thomoux 93330 Neuilly Sur Marne Ile de France 93330",
    "addr:housenumber":"228",
    "addr:postcode":"93330;93330",
    "addr:street":"R Paul Et Camille Thomoux",
    "iso:country":"FR",
    "sg:address":"228 R Paul Et Camille Thomoux 93330 Neuilly Sur Marne",
    "sg:classifiers":[
        {
            "category":"Professional",
            "subcategory":"Engineering",
            "type":"Services"
        }
    ],
    "sg:phone":"+33 1 43 08 13 90",
    "sg:postcode":"93330",
    "sg:province":"Ile de France",
    "sg:tags":[
        "machine",
        "-",
        "mechanical"
    ],
    "wof:name":"Airap Sa",
    "wof:placetype":"venue"
},
  "geometry": {"coordinates":[2.529751,48.87241],"type":"Point"}
}