{
  "type": "Feature",
  "properties": {
    "addr:full":"B.P. 5143 Ajaccio C\u00e9dex 5^^Talaveza Sgaretatu 20167 Cuttoli Corticchiato Corse 20501",
    "addr:postcode":"5143;20167;20501",
    "addr:street":"B.P.;Sgaretatu",
    "iso:country":"FR",
    "sg:address":"B.P. 5143",
    "sg:city":"Ajaccio C\u00e9dex 5^^Talaveza Sgaretatu 20167 Cuttoli Corticchiato",
    "sg:orig_category":"Non-Classified Establishments",
    "sg:phone":"+33 4 95 25 24 25",
    "sg:postcode":"20501",
    "sg:province":"Corse",
    "wof:name":"Mannarini S.a.r.l.",
    "wof:placetype":"venue"
},
  "geometry": {"coordinates":[8.668294,41.959526],"type":"Point"}
}