{
  "type": "Feature",
  "properties": {
    "addr:full":"ZAC Jeumont Schneider Champagne sur Seine Ile de France 77430",
    "addr:postcode":"77430",
    "addr:street":"Zac;Champagne;Seine;France",
    "iso:country":"FR",
    "sg:address":"ZAC Jeumont Schneider",
    "sg:city":"Champagne sur Seine",
    "sg:orig_category":"Unclassifiable Establishments",
    "sg:phone":"+33 1 60 39 52 70",
    "sg:postcode":"77430",
    "sg:province":"Ile de France",
    "wof:name":"Amours Preel S.a.r.l.",
    "wof:placetype":"venue"
},
  "geometry": {"coordinates":[2.798565,48.402039],"type":"Point"}
}