{
  "type": "Feature",
  "properties": {
    "iso:country":"FR",
    "sg:address":"1576, Av. du Mont Blanc, 74130 Vougy",
    "sg:orig_category":"Unclassifiable Establishments",
    "sg:phone":"+33 4 50 89 13 20",
    "sg:province":"Rhone-Alpes",
    "wof:name":"S.t. Roulage S.a.s.",
    "wof:placetype":"venue"
},
  "geometry": {"coordinates":[6.388322,45.95652],"type":"Point"}
}