{
  "type": "Feature",
  "properties": {
    "iso:country":"FR",
    "sg:address":"La Bonnetrie 41400 Montrichard",
    "sg:city":"Montrichard",
    "sg:classifiers":[
        {
            "category":"Shopping",
            "type":"Retail Goods"
        }
    ],
    "sg:phone":"+33 2 54 32 10 33",
    "sg:postcode":"41400",
    "sg:province":"Centre",
    "sg:tags":[
        "metallurgy",
        "finished",
        "-",
        "metalworking",
        "metallic"
    ],
    "wof:name":"Comptoir G\u00c9n\u00c9ral Du Ressort (cgr)",
    "wof:placetype":"venue"
},
  "geometry": {"coordinates":[1.17734,47.354786],"type":"Point"}
}