{
  "type": "Feature",
  "properties": {
    "addr:full":"3 R L\u00e9on Jouhaux 75010 Paris Ile de France 75010",
    "addr:housenumber":"3",
    "addr:postcode":"75010;75010",
    "addr:street":"R Le\u0301On Jouhaux",
    "iso:country":"FR",
    "sg:address":"3 R L\u00e9on Jouhaux 75010 Paris",
    "sg:classifiers":[
        {
            "category":"Manufacturing",
            "subcategory":"Jewelry",
            "type":"Manufacturing & Wholesale Goods"
        }
    ],
    "sg:phone":"+33 1 42 02 10 24",
    "sg:postcode":"75010",
    "sg:province":"Ile de France",
    "sg:tags":[
        "product",
        "jewellery",
        "equipement",
        "miscellaneous",
        "timekeeping",
        "equipment",
        "precision"
    ],
    "wof:name":"Lilas Or Sarl",
    "wof:placetype":"venue"
},
  "geometry": {"coordinates":[2.363188,48.868729],"type":"Point"}
}