{
  "type": "Feature",
  "properties": {
    "addr:full":"64, Rue Ernest Lesaffre, 59680 Ferri\u00e8re la Grande Nord Pas-de-Calais",
    "addr:housenumber":"64",
    "addr:postcode":"59680",
    "addr:street":"Rue Ernest Lesaffre;La Grande Nord",
    "iso:country":"FR",
    "sg:address":"64, Rue Ernest Lesaffre, 59680 Ferri\u00e8re la Grande",
    "sg:orig_category":"Unclassifiable Establishments",
    "sg:phone":"+33 3 27 69 88 88",
    "sg:province":"Nord Pas-de-Calais",
    "wof:name":"Spie Ferri\u00e8re Tuyauterie, S.a.",
    "wof:placetype":"venue"
},
  "geometry": {"coordinates":[4.003502,50.252857],"type":"Point"}
}