{
  "type": "Feature",
  "properties": {
    "addr:full":"33 Av Carnot 83300 Draguignan",
    "addr:postcode":"83300",
    "addr:street":"33 Av Carnot",
    "iso:country":"FR",
    "sg:address":"33 Av Carnot 83300 Draguignan",
    "sg:classifiers":[
        {
            "category":"Banks & Credit Unions",
            "subcategory":"Financial Services",
            "type":"Services"
        }
    ],
    "sg:phone":"+33 4 94 60 62 04",
    "sg:tags":[
        "banking",
        "insurance",
        "institution",
        "finance"
    ],
    "wof:name":"Banque De France",
    "wof:placetype":"venue"
},
  "geometry": {"coordinates":[6.467081,43.534939],"type":"Point"}
}