{
  "type": "Feature",
  "properties": {
    "addr:full":"Rue Du Nouveau Siecle 59127 Walincourt Selvigny Nord Pas-de-Calais 59127",
    "addr:postcode":"59127;59127",
    "addr:street":"Rue Du Nouveau Siecle;Selvigny Nord",
    "iso:country":"FR",
    "sg:address":"Rue Du Nouveau Siecle 59127 Walincourt Selvigny",
    "sg:classifiers":[
        {
            "category":"Shopping",
            "subcategory":"Crafts & Fabrics",
            "type":"Retail Goods"
        }
    ],
    "sg:phone":"+33 3 27 70 75 50",
    "sg:postcode":"59127",
    "sg:province":"Nord Pas-de-Calais",
    "sg:tags":[
        "textile",
        "clothing"
    ],
    "wof:name":"Broderies Du Loup Noir",
    "wof:placetype":"venue"
},
  "geometry": {"coordinates":[3.329085,50.065269],"type":"Point"}
}