{
  "type": "Feature",
  "properties": {
    "addr:full":"3 rue des Castaings 33470 Le Teich Le Teich Aquitaine 33470",
    "addr:housenumber":"3;teich;teich",
    "addr:postcode":"33470;33470",
    "addr:street":"Rue Des Castaings",
    "iso:country":"FR",
    "sg:address":"3 rue des Castaings 33470 Le Teich",
    "sg:city":"Le Teich",
    "sg:classifiers":[
        {
            "category":"Home & Garden",
            "subcategory":"Garden Supply",
            "type":"Retail Goods"
        }
    ],
    "sg:phone":"+33 5 56 22 61 95",
    "sg:postcode":"33470",
    "sg:province":"Aquitaine",
    "sg:tags":[
        "fertilizer",
        "organic"
    ],
    "wof:name":"Fertilisation Moderne Et Scientifique Sa",
    "wof:placetype":"venue"
},
  "geometry": {"coordinates":[-1.023335,44.635696],"type":"Point"}
}