{
  "type": "Feature",
  "properties": {
    "iso:country":"FR",
    "sg:address":"B.P. 18, 78730 Saint Arnoult en Yvelines C\u00e9dex^^23, Rue de la Charronnerie, 78730 Saint Arnoult en Y",
    "sg:orig_category":"Non-Classified Establishments",
    "sg:phone":"+33 1 30 88 21 30",
    "sg:province":"Ile de France",
    "wof:name":"Sery S.a.r.l.",
    "wof:placetype":"venue"
},
  "geometry": {"coordinates":[1.93534,48.570969],"type":"Point"}
}