{
  "type": "Feature",
  "properties": {
    "iso:country":"FR",
    "sg:address":"ZI des M\u00e9tairies",
    "sg:city":"Nivillac",
    "sg:orig_category":"Unclassifiable Establishments",
    "sg:phone":"+33 2 99 90 83 14",
    "sg:postcode":"56130",
    "sg:province":"Bretagne",
    "wof:name":"A.m.p. Herblin S.a.r.l.",
    "wof:placetype":"venue"
},
  "geometry": {"coordinates":[-2.283153,47.533764],"type":"Point"}
}