{
  "type": "Feature",
  "properties": {
    "addr:full":"101 avenue Blaise Pascal 33160 ST MEDARD EN JALLES Salaunes Aquitaine 33160",
    "addr:housenumber":"101",
    "addr:postcode":"33160;33160",
    "addr:street":"Avenue Blaise Pascal",
    "iso:country":"FR",
    "sg:address":"101 avenue Blaise Pascal 33160 ST MEDARD EN JALLES",
    "sg:city":"Salaunes",
    "sg:classifiers":[
        {
            "category":"Retail",
            "subcategory":"Car Wash",
            "type":"Services"
        }
    ],
    "sg:phone":"+33 5 56 05 06 03",
    "sg:postcode":"33160",
    "sg:province":"Aquitaine",
    "sg:tags":[
        "transportation",
        "special"
    ],
    "wof:name":"Angeleri S.a.r.l.",
    "wof:placetype":"venue"
},
  "geometry": {"coordinates":[-0.779755,44.896564],"type":"Point"}
}