{
  "type": "Feature",
  "properties": {
    "addr:full":"Les Moironds 38360 Noyarey Rhone-Alpes",
    "addr:postcode":"38360",
    "iso:country":"FR",
    "sg:address":"Les Moironds 38360 Noyarey",
    "sg:classifiers":[
        {
            "category":"Manufacturing",
            "subcategory":"Wood Products",
            "type":"Manufacturing & Wholesale Goods"
        }
    ],
    "sg:phone":"+33 4 76 71 43 18",
    "sg:province":"Rhone-Alpes",
    "sg:tags":[
        "furniture"
    ],
    "wof:name":"Scierie Du Vercors Sa",
    "wof:placetype":"venue"
},
  "geometry": {"coordinates":[5.662875,45.206551],"type":"Point"}
}