{
  "type": "Feature",
  "properties": {
    "addr:full":"4 Avenue De L'Ile Brune Immeuble Le Boreal 38120 St Egreve Rhone-Alpes 38120",
    "addr:housenumber":"4;immeuble",
    "addr:postcode":"38120;38120",
    "addr:street":"Avenue De L'Ile;Le Boreal;Rhone-Alpes",
    "iso:country":"FR",
    "sg:address":"4 Avenue De L'Ile Brune Immeuble Le Boreal 38120 St Egreve",
    "sg:classifiers":[
        {
            "category":"Shopping",
            "subcategory":"Stationery & Office Supplies",
            "type":"Retail Goods"
        }
    ],
    "sg:phone":"+33 4 76 75 91 75",
    "sg:postcode":"38120",
    "sg:province":"Rhone-Alpes",
    "sg:tags":[
        "information",
        "technology",
        "telecommunication",
        "equipment"
    ],
    "wof:name":"Minolta France Sa",
    "wof:placetype":"venue"
},
  "geometry": {"coordinates":[5.66968,45.235554],"type":"Point"}
}