{
  "type": "Feature",
  "properties": {
    "addr:full":"ZAC les 2 B Bressolles Rhone-Alpes 01360",
    "addr:housenumber":"2 b",
    "addr:postcode":"01360",
    "addr:street":"Zac Les;Rhone-Alpes",
    "iso:country":"FR",
    "sg:address":"ZAC les 2 B",
    "sg:city":"Bressolles",
    "sg:orig_category":"Non-Classified Establishments",
    "sg:phone":"+33 4 72 25 19 19",
    "sg:postcode":"01360",
    "sg:province":"Rhone-Alpes",
    "wof:name":"Etablissement Rose S.a.",
    "wof:placetype":"venue"
},
  "geometry": {"coordinates":[5.120386,45.829571],"type":"Point"}
}