{
  "type": "Feature",
  "properties": {
    "addr:full":"16 Rue Ficatier 92400 Courbevoie Ile de France 92400",
    "addr:housenumber":"16",
    "addr:postcode":"92400;92400",
    "addr:street":"Rue Ficatier",
    "iso:country":"FR",
    "sg:address":"16 Rue Ficatier 92400 Courbevoie",
    "sg:classifiers":[
        {
            "category":"Professional",
            "subcategory":"Advertising",
            "type":"Services"
        }
    ],
    "sg:phone":"+33 1 41 88 00 00",
    "sg:postcode":"92400",
    "sg:province":"Ile de France",
    "sg:tags":[
        "communication",
        "medium"
    ],
    "wof:name":"Magnitude",
    "wof:placetype":"venue"
},
  "geometry": {"coordinates":[2.257183,48.893318],"type":"Point"}
}