{
  "type": "Feature",
  "properties": {
    "addr:full":"21, Av. de Rochetaill\u00e9e, 42000 Saint Etienne Rhone-Alpes 42000",
    "addr:postcode":"42000;42000",
    "addr:street":"21 Av. De Rochetaille\u0301E",
    "iso:country":"FR",
    "sg:address":"21, Av. de Rochetaill\u00e9e, 42000 Saint Etienne",
    "sg:orig_category":"Unclassifiable Establishments",
    "sg:phone":"+33 4 77 80 00 49",
    "sg:postcode":"42000",
    "sg:province":"Rhone-Alpes",
    "wof:name":"Ateliers M\u00e9caniques De La Rivi\u00e8re S.a.r.l.",
    "wof:placetype":"venue"
},
  "geometry": {"coordinates":[4.398982,45.41996],"type":"Point"}
}