{
  "type": "Feature",
  "properties": {
    "addr:full":"1 Milly 89190 Foissy Sur Vanne Bagneaux Bourgogne 89190",
    "addr:housenumber":"1",
    "addr:postcode":"89190;89190",
    "addr:street":"Milly",
    "iso:country":"FR",
    "sg:address":"1 Milly 89190 Foissy Sur Vanne",
    "sg:city":"Bagneaux",
    "sg:classifiers":[
        {
            "category":"Farming",
            "subcategory":"Crops",
            "type":"Manufacturing & Wholesale Goods"
        }
    ],
    "sg:phone":"+33 3 86 86 70 23",
    "sg:postcode":"89190",
    "sg:province":"Bourgogne",
    "sg:tags":[
        "vegetable",
        "fruit",
        "agriculture",
        "livestock"
    ],
    "wof:name":"Novaserre Sa",
    "wof:placetype":"venue"
},
  "geometry": {"coordinates":[3.51902,48.222111],"type":"Point"}
}