{
  "type": "Feature",
  "properties": {
    "iso:country":"FR",
    "sg:address":"112 ter, Rue Cardinet, 75017 Paris",
    "sg:orig_category":"Non-Classified Establishments",
    "sg:phone":"+33 1 44 29 70 50",
    "sg:province":"Ile de France",
    "wof:name":"Keymage S.a.",
    "wof:placetype":"venue"
},
  "geometry": {"coordinates":[2.311861,48.885593],"type":"Point"}
}