{
  "type": "Feature",
  "properties": {
    "addr:full":"3155, Rue de la Lys - Bac Saint Maur, 62840 Sailly sur la Lys Nord Pas-de-Calais",
    "addr:housenumber":"3155",
    "addr:postcode":"62840",
    "addr:street":"Rue De La Lys Bac Saint Maur",
    "iso:country":"FR",
    "sg:address":"3155, Rue de la Lys - Bac Saint Maur, 62840 Sailly sur la Lys",
    "sg:orig_category":"Unclassifiable Establishments",
    "sg:phone":"+33 3 21 66 24 77",
    "sg:province":"Nord Pas-de-Calais",
    "wof:name":"Safilin S.a.",
    "wof:placetype":"venue"
},
  "geometry": {"coordinates":[2.772065,50.626614],"type":"Point"}
}