{
  "type": "Feature",
  "properties": {
    "iso:country":"FR",
    "sg:address":"Harania 64240 Macaye",
    "sg:city":"Macaye",
    "sg:orig_category":"Unclassifiable Establishments",
    "sg:phone":"+33 5 59 29 52 43",
    "sg:postcode":"64240",
    "sg:province":"Aquitaine",
    "wof:name":"Onetik S.a.",
    "wof:placetype":"venue"
},
  "geometry": {"coordinates":[-1.327019,43.330639],"type":"Point"}
}