{
  "type": "Feature",
  "properties": {
    "iso:country":"FR",
    "sg:address":"47 Bd Edmond Roussin 35300 Fougeres",
    "sg:city":"Foug\u00e8res",
    "sg:classifiers":[
        {
            "category":"Shopping",
            "subcategory":"Luggage & Leather Goods",
            "type":"Retail Goods"
        }
    ],
    "sg:phone":"+33 2 99 94 60 60",
    "sg:postcode":"35300",
    "sg:province":"Bretagne",
    "sg:tags":[
        "shoe"
    ],
    "wof:name":"J B Martin",
    "wof:placetype":"venue"
},
  "geometry": {"coordinates":[-1.198629,48.346165],"type":"Point"}
}