{
  "type": "Feature",
  "properties": {
    "addr:full":"Route Nationale 7 84420 Piolenc",
    "addr:postcode":"84420",
    "addr:street":"Route Nationale 7",
    "iso:country":"FR",
    "sg:address":"Route Nationale 7 84420 Piolenc",
    "sg:classifiers":[
        {
            "category":"Home & Garden",
            "subcategory":"Furniture",
            "type":"Retail Goods"
        }
    ],
    "sg:phone":"+33 4 90 29 60 12",
    "sg:tags":[
        "wood"
    ],
    "wof:name":"Bonjean Mireille",
    "wof:placetype":"venue"
},
  "geometry": {"coordinates":[4.76149,44.172798],"type":"Point"}
}