{
  "type": "Feature",
  "properties": {
    "addr:full":"2 Rue L\u00e9on Blum 62330 Isbergues Nord Pas-de-Calais 62330",
    "addr:housenumber":"2",
    "addr:postcode":"62330;62330",
    "addr:street":"Rue Le\u0301On Blum",
    "iso:country":"FR",
    "sg:address":"2 Rue L\u00e9on Blum 62330 Isbergues",
    "sg:orig_category":"Chemicals and Pharmaceuticals Energy Energy and Raw Materials",
    "sg:phone":"+33 3 21 02 09 22",
    "sg:postcode":"62330",
    "sg:province":"Nord Pas-de-Calais",
    "wof:name":"Artois Combustibles Et Materiaux Sa",
    "wof:placetype":"venue"
},
  "geometry": {"coordinates":[2.474604,50.614922],"type":"Point"}
}