{
  "type": "Feature",
  "properties": {
    "addr:full":"1, Grande Rue, 89190 Foissy sur Vanne Bagneaux Bourgogne 89190",
    "addr:housenumber":"1",
    "addr:postcode":"89190;89190",
    "addr:street":"Grande Rue",
    "iso:country":"FR",
    "sg:address":"1, Grande Rue, 89190 Foissy sur Vanne",
    "sg:city":"Bagneaux",
    "sg:orig_category":"Non-Classified Establishments",
    "sg:phone":"+33 3 86 96 88 88",
    "sg:postcode":"89190",
    "sg:province":"Bourgogne",
    "wof:name":"Serres Vannoises S.a.s.",
    "wof:placetype":"venue"
},
  "geometry": {"coordinates":[3.50119,48.221931],"type":"Point"}
}