{
  "type": "Feature",
  "properties": {
    "addr:full":"58 Av De L'Ile Brune 38120 St Egr\u00e8ve Tennessee",
    "addr:postcode":"38120",
    "addr:street":"58 Av De L'Ile Brune",
    "iso:country":"FR",
    "sg:address":"58 Av De L'Ile Brune 38120 St Egr\u00e8ve",
    "sg:classifiers":[
        {
            "category":"Professional",
            "type":"Services"
        }
    ],
    "sg:phone":"+33 4 76 75 06 36",
    "sg:province":"Tennessee",
    "sg:tags":[
        "transport",
        "road"
    ],
    "wof:name":"Bc Transport Sarl",
    "wof:placetype":"venue"
},
  "geometry": {"coordinates":[-89.842308,35.12442],"type":"Point"}
}