{
  "type": "Feature",
  "properties": {
    "addr:full":"Le Gite 76490 MAULEVRIER STE GERTRUDE Haute Normandie 76490",
    "addr:postcode":"76490;76490",
    "addr:street":"Haute Normandie",
    "iso:country":"FR",
    "sg:address":"Le Gite 76490 MAULEVRIER STE GERTRUDE",
    "sg:orig_category":"Netting, Industrial",
    "sg:phone":"+33 2 35 95 22 07",
    "sg:postcode":"76490",
    "sg:province":"Haute Normandie",
    "wof:name":"Multimailles Sarl",
    "wof:placetype":"venue"
},
  "geometry": {"coordinates":[0.743811,49.558487],"type":"Point"}
}