{
  "type": "Feature",
  "properties": {
    "addr:full":"5 Rue Chapon 75003 Paris Ile de France 75003",
    "addr:housenumber":"5",
    "addr:postcode":"75003;75003",
    "addr:street":"Rue Chapon",
    "iso:country":"FR",
    "sg:address":"5 Rue Chapon 75003 Paris",
    "sg:classifiers":[
        {
            "category":"Manufacturing",
            "subcategory":"Leather Goods",
            "type":"Manufacturing & Wholesale Goods"
        }
    ],
    "sg:phone":"+33 1 48 87 18 02",
    "sg:postcode":"75003",
    "sg:province":"Ile de France",
    "sg:tags":[
        "shoe"
    ],
    "wof:name":"Fransac",
    "wof:placetype":"venue"
},
  "geometry": {"coordinates":[2.357262,48.862888],"type":"Point"}
}