{
  "type": "Feature",
  "properties": {
    "addr:full":"Av. de Cheval Blanc - ZI Cavaillon Provence-Alpes-C\u00f4te d'Azur 84300",
    "addr:postcode":"84300",
    "addr:street":"Av. De Cheval Blanc Zi Cavaillon",
    "iso:country":"FR",
    "sg:address":"Av. de Cheval Blanc - ZI",
    "sg:city":"Cavaillon",
    "sg:orig_category":"Unclassifiable Establishments",
    "sg:phone":"+33 4 90 71 15 46",
    "sg:postcode":"84300",
    "sg:province":"Provence-Alpes-C\u00f4te d'Azur",
    "wof:name":"Etablissements Gaston Jouval S.a.",
    "wof:placetype":"venue"
},
  "geometry": {"coordinates":[5.039415,43.837685],"type":"Point"}
}