{
  "type": "Feature",
  "properties": {
    "addr:full":"Chemin des Pr\u00e9s - ZI Biot Midi Pyr\u00e9n\u00e9es 06410",
    "addr:postcode":"06410",
    "addr:street":"Chemin Des Pre\u0301S",
    "iso:country":"FR",
    "sg:address":"Chemin des Pr\u00e9s - ZI",
    "sg:city":"Biot",
    "sg:orig_category":"Unclassifiable Establishments",
    "sg:phone":"+33 4 92 91 52 20",
    "sg:postcode":"06410",
    "sg:province":"Midi Pyr\u00e9n\u00e9es",
    "wof:name":"Emcorp S.a.r.l.",
    "wof:placetype":"venue"
},
  "geometry": {"coordinates":[7.104342,43.62265],"type":"Point"}
}