{
  "type": "Feature",
  "properties": {
    "addr:full":"Z.A.C. de la Goulguati\u00e8re Ch\u00e2teaubourg Bretagne 35220",
    "addr:postcode":"35220",
    "addr:street":"Z.A.C. De La Goulguatie\u0300Re Cha\u0302Teaubourg Bretagne",
    "iso:country":"FR",
    "sg:address":"Z.A.C. de la Goulguati\u00e8re",
    "sg:city":"Ch\u00e2teaubourg",
    "sg:orig_category":"Unclassifiable Establishments",
    "sg:phone":"+33 2 99 62 34 62",
    "sg:postcode":"35220",
    "sg:province":"Bretagne",
    "wof:name":"Collet Distribution S.a.r.l.",
    "wof:placetype":"venue"
},
  "geometry": {"coordinates":[-1.392459,48.111],"type":"Point"}
}