{
  "type": "Feature",
  "properties": {
    "iso:country":"FR",
    "sg:address":"2 Rue De La Mare Neuve",
    "sg:city":"Evry Cedex",
    "sg:classifiers":[
        {
            "category":"Banks & Credit Unions",
            "subcategory":"Financial Services",
            "type":"Services"
        }
    ],
    "sg:phone":"+33 1 69 36 87 87",
    "sg:postcode":"91021",
    "sg:province":"Haute Normandie",
    "sg:tags":[
        "banking",
        "finance",
        "insurance"
    ],
    "wof:name":"Mercure France Est",
    "wof:placetype":"venue"
},
  "geometry": {"coordinates":[2.43072,48.626919],"type":"Point"}
}