{
  "type": "Feature",
  "properties": {
    "addr:full":"Zi 2 St Germain 60800 Cr\u00e9py En Valois Picardie 60800",
    "addr:housenumber":"2",
    "addr:postcode":"60800;60800",
    "addr:street":"Zi;En;Picardie",
    "iso:country":"FR",
    "sg:address":"Zi 2",
    "sg:city":"St Germain 60800 Cr\u00e9py En Valois",
    "sg:classifiers":[
        {
            "category":"Train Station",
            "subcategory":"Rail",
            "type":"Transportation"
        }
    ],
    "sg:phone":"+33 3 44 39 60 30",
    "sg:postcode":"60800",
    "sg:province":"Picardie",
    "sg:tags":[
        "steel",
        "pipe",
        "sheet",
        "metal",
        "metallurgy",
        "metalworking"
    ],
    "wof:name":"Distritube Sa",
    "wof:placetype":"venue"
},
  "geometry": {"coordinates":[2.887172,49.235062],"type":"Point"}
}