{
  "type": "Feature",
  "properties": {
    "addr:full":"6, Rue des Vignes, 67370 Stutzheim Offenheim Berstett Alsace 67370",
    "addr:housenumber":"6",
    "addr:postcode":"67370;67370",
    "addr:street":"Rue Des Vignes",
    "iso:country":"FR",
    "sg:address":"6, Rue des Vignes, 67370 Stutzheim Offenheim",
    "sg:city":"Berstett",
    "sg:orig_category":"Non-Classified Establishments",
    "sg:phone":"+33 3 88 69 78 77",
    "sg:postcode":"67370",
    "sg:province":"Alsace",
    "wof:name":"M.t.c. S.a.r.l.",
    "wof:placetype":"venue"
},
  "geometry": {"coordinates":[7.61577,48.632309],"type":"Point"}
}