{
  "type": "Feature",
  "properties": {
    "addr:full":"2, Rue du Docteur Lombard, 92130 Issy les Moulineaux Ile de France",
    "addr:housenumber":"2",
    "addr:postcode":"92130",
    "addr:street":"Rue Du Docteur Lombard",
    "iso:country":"FR",
    "sg:address":"2, Rue du Docteur Lombard, 92130 Issy les Moulineaux",
    "sg:orig_category":"Non-Classified Establishments",
    "sg:phone":"+33 1 55 95 01 01",
    "sg:province":"Ile de France",
    "wof:name":"New Com S.a.",
    "wof:placetype":"venue"
},
  "geometry": {"coordinates":[2.250733,48.819939],"type":"Point"}
}