{
  "type": "Feature",
  "properties": {
    "addr:full":"Lombre 16320 Magnac Lavalette Villars Poitou-Charentes 16320",
    "addr:postcode":"16320;16320",
    "addr:street":"Lombre;Villars",
    "iso:country":"FR",
    "sg:address":"Lombre 16320 Magnac Lavalette Villars",
    "sg:classifiers":[
        {
            "category":"Wholesale",
            "subcategory":"Drugs",
            "type":"Manufacturing & Wholesale Goods"
        }
    ],
    "sg:phone":"+33 5 45 64 74 74",
    "sg:postcode":"16320",
    "sg:province":"Poitou-Charentes",
    "sg:tags":[
        "chemical",
        "pharmaceutical"
    ],
    "wof:name":"Avel",
    "wof:placetype":"venue"
},
  "geometry": {"coordinates":[0.246205,45.493408],"type":"Point"}
}