{
  "type": "Feature",
  "properties": {
    "iso:country":"FR",
    "sg:address":"76 rue Jean Jaur\u00e8s 59410 Anzin",
    "sg:classifiers":[
        {
            "category":"Manufacturing",
            "subcategory":"Motor Vehicles & Parts",
            "type":"Manufacturing & Wholesale Goods"
        }
    ],
    "sg:phone":"+33 3 27 45 35 00",
    "sg:province":"Nord Pas-de-Calais",
    "sg:tags":[
        "precision",
        "mechanic"
    ],
    "wof:name":"Famacom Sa",
    "wof:placetype":"venue"
},
  "geometry": {"coordinates":[3.517684,50.375805],"type":"Point"}
}