{
  "type": "Feature",
  "properties": {
    "addr:full":"B.P. 98, 62102 Calais C\u00e9dex^^54, Rue Neuve, 62100 Calais Nord Pas-de-Calais",
    "addr:postcode":"62102;62100",
    "addr:street":"B.P. 98;Rue Neuve;Calais;Pas-De-Calais",
    "iso:country":"FR",
    "sg:address":"B.P. 98, 62102 Calais C\u00e9dex^^54, Rue Neuve, 62100 Calais",
    "sg:orig_category":"Non-Classified Establishments",
    "sg:phone":"+33 3 21 36 04 35",
    "sg:province":"Nord Pas-de-Calais",
    "wof:name":"Wissocq Pierre Edmond",
    "wof:placetype":"venue"
},
  "geometry": {"coordinates":[1.85305,50.953079],"type":"Point"}
}