{
  "type": "Feature",
  "properties": {
    "addr:full":"2 rue Bartholdi 92100 Boulogne Billancourt Ile de France 92100",
    "addr:housenumber":"2",
    "addr:postcode":"92100;92100",
    "addr:street":"Rue Bartholdi",
    "iso:country":"FR",
    "sg:address":"2 rue Bartholdi 92100 Boulogne Billancourt",
    "sg:classifiers":[
        {
            "category":"Shopping",
            "subcategory":"Gifts & Souvenirs",
            "type":"Retail Goods"
        }
    ],
    "sg:phone":"+33 1 48 25 52 55",
    "sg:postcode":"92100",
    "sg:province":"Ile de France",
    "sg:tags":[
        "item",
        "porcelain",
        "made"
    ],
    "wof:name":"Sophie D'e Sa",
    "wof:placetype":"venue"
},
  "geometry": {"coordinates":[2.242906,48.844261],"type":"Point"}
}