{
  "type": "Feature",
  "properties": {
    "iso:country":"FR",
    "sg:address":"7, Rue du Chat Noir, 62230 Outreau",
    "sg:orig_category":"Non-Classified Establishments",
    "sg:phone":"+33 3 21 99 03 03",
    "sg:postcode":"62230",
    "sg:province":"Nord Pas-de-Calais",
    "wof:name":"C.b.i. S.a. - Comptoir Des Bois Industriels",
    "wof:placetype":"venue"
},
  "geometry": {"coordinates":[1.607527,50.707176],"type":"Point"}
}