{
  "type": "Feature",
  "properties": {
    "iso:country":"FR",
    "sg:address":"143 avenue Charles de Gaulle 92200 Neuilly sur Seine",
    "sg:orig_category":"Cardboard, General",
    "sg:phone":"+33 1 55 61 44 11",
    "sg:postcode":"92200",
    "sg:province":"Ile de France",
    "wof:name":"Hugues Nicollet S.a.",
    "wof:placetype":"venue"
},
  "geometry": {"coordinates":[2.266014,48.882549],"type":"Point"}
}