{
  "type": "Feature",
  "properties": {
    "addr:full":"3 Rue Edmond Poillot 28000 Chartres Chartres Centre 28000",
    "addr:housenumber":"3",
    "addr:postcode":"28000;28000",
    "addr:street":"Rue Edmond Poillot",
    "iso:country":"FR",
    "sg:address":"3 Rue Edmond Poillot 28000 Chartres",
    "sg:city":"Chartres",
    "sg:classifiers":[
        {
            "category":"Professional",
            "subcategory":"Engineering",
            "type":"Services"
        }
    ],
    "sg:phone":"+33 2 37 28 74 80",
    "sg:postcode":"28000",
    "sg:province":"Centre",
    "sg:tags":[
        "machine",
        "-",
        "environment",
        "equipment",
        "machinery",
        "mechanical"
    ],
    "wof:name":"Harden Sa",
    "wof:placetype":"venue"
},
  "geometry": {"coordinates":[1.50935,48.432255],"type":"Point"}
}