{
  "type": "Feature",
  "properties": {
    "addr:full":"B.P. 45, 42190 Charlieu C\u00e9dex^^10, Av Charnay, 42190 Charlieu Rhone-Alpes",
    "addr:postcode":"42190;42190",
    "addr:street":"B.P. 45;Av Charnay",
    "iso:country":"FR",
    "sg:address":"B.P. 45, 42190 Charlieu C\u00e9dex^^10, Av Charnay, 42190 Charlieu",
    "sg:orig_category":"Non-Classified Establishments",
    "sg:phone":"+33 4 77 69 32 60",
    "sg:province":"Rhone-Alpes",
    "wof:name":"Guillaud S.a.",
    "wof:placetype":"venue"
},
  "geometry": {"coordinates":[4.182715,46.122444],"type":"Point"}
}