{
  "type": "Feature",
  "properties": {
    "addr:full":"27 rue Jean Goujon 75008 Paris Ile de France",
    "addr:housenumber":"27",
    "addr:postcode":"75008",
    "addr:street":"Rue Jean Goujon",
    "iso:country":"FR",
    "sg:address":"27 rue Jean Goujon 75008 Paris",
    "sg:classifiers":[
        {
            "category":"Shopping",
            "subcategory":"Beauty & Cosmetics",
            "type":"Retail Goods"
        }
    ],
    "sg:phone":"+33 1 53 77 55 40",
    "sg:province":"Ile de France",
    "sg:tags":[
        "perfume"
    ],
    "wof:name":"Parfums Ted Lapidus S.a.",
    "wof:placetype":"venue"
},
  "geometry": {"coordinates":[2.305453,48.865391],"type":"Point"}
}