{
  "type": "Feature",
  "properties": {
    "iso:country":"FR",
    "sg:address":"Rte de Chamberet",
    "sg:city":"Eyburie",
    "sg:orig_category":"Unclassifiable Establishments",
    "sg:phone":"+33 5 55 73 22 79",
    "sg:postcode":"19140",
    "sg:province":"Limousin",
    "wof:name":"Lachenaud Roger Albert",
    "wof:placetype":"venue"
},
  "geometry": {"coordinates":[1.636785,45.462231],"type":"Point"}
}