{
  "type": "Feature",
  "properties": {
    "iso:country":"FR",
    "sg:address":"ZA de la Papeterie 38140 Renage",
    "sg:orig_category":"Measuring Instruments For The Paper Industry",
    "sg:phone":"+33 4 76 65 35 64",
    "sg:postcode":"38140",
    "sg:province":"Rhone-Alpes",
    "wof:name":"Sire S.a.",
    "wof:placetype":"venue"
},
  "geometry": {"coordinates":[5.484325,45.332794],"type":"Point"}
}