{
  "type": "Feature",
  "properties": {
    "iso:country":"FR",
    "sg:address":"Rue Noue Grenet 85170 Les Lucs Sur Boulogne",
    "sg:classifiers":[
        {
            "category":"Shopping",
            "subcategory":"Clothing, Apparel, & Fashions",
            "type":"Retail Goods"
        }
    ],
    "sg:phone":"+33 2 51 46 50 26",
    "sg:postcode":"85170",
    "sg:province":"Pays de Loire",
    "sg:tags":[
        "textile",
        "clothing",
        "clothes"
    ],
    "wof:name":"Sefa Sas",
    "wof:placetype":"venue"
},
  "geometry": {"coordinates":[-1.399664,46.72414],"type":"Point"}
}