{
  "type": "Feature",
  "properties": {
    "iso:country":"FR",
    "sg:address":"15, Rue de la Marne, 29140 Rosporden",
    "sg:city":"Rosporden",
    "sg:orig_category":"Unclassifiable Establishments",
    "sg:phone":"+33 2 99 00 44 00",
    "sg:postcode":"29140",
    "sg:province":"Bretagne",
    "wof:name":"Qu\u00e9r\u00e9 S.a.",
    "wof:placetype":"venue"
},
  "geometry": {"coordinates":[-3.830384,47.960258],"type":"Point"}
}