{
  "type": "Feature",
  "properties": {
    "addr:full":"74520 Chenex Rhone-Alpes",
    "addr:postcode":"74520",
    "iso:country":"FR",
    "sg:address":"74520 Chenex",
    "sg:orig_category":"Non-Classified Establishments",
    "sg:phone":"+33 4 50 04 32 22",
    "sg:province":"Rhone-Alpes",
    "wof:name":"Super G Etablissement Gondret S.a.",
    "wof:placetype":"venue"
},
  "geometry": {"coordinates":[5.994043,46.104839],"type":"Point"}
}