{
  "type": "Feature",
  "properties": {
    "addr:full":"4 Rue Du 11 Novembre 28114 Luc\u00e9 Midi Pyr\u00e9n\u00e9es",
    "addr:housenumber":"4",
    "addr:postcode":"28114",
    "addr:street":"Rue Du 11 Novembre",
    "iso:country":"FR",
    "sg:address":"4 Rue Du 11 Novembre 28114 Luc\u00e9",
    "sg:classifiers":[
        {
            "category":"Professional",
            "subcategory":"Business Services",
            "type":"Services"
        }
    ],
    "sg:phone":"+33 2 37 35 15 97",
    "sg:province":"Midi Pyr\u00e9n\u00e9es",
    "sg:tags":[
        "training",
        "advice"
    ],
    "wof:name":"College Les Petits Sentiers",
    "wof:placetype":"venue"
},
  "geometry": {"coordinates":[1.467334,48.440228],"type":"Point"}
}