{
  "type": "Feature",
  "properties": {
    "addr:full":"B.P. 50190, 86962 Chasseneuil du Poitou C\u00e9dex^^3, Av. du T\u00e9l\u00e9port, 86960 Chasseneuil du Poitou La Feuillie Basse Normandie 50190",
    "addr:housenumber":"86962",
    "addr:postcode":"86960;50190",
    "addr:street":"Av. Du Te\u0301Le\u0301Port",
    "iso:country":"FR",
    "sg:address":"B.P. 50190, 86962 Chasseneuil du Poitou C\u00e9dex^^3, Av. du T\u00e9l\u00e9port, 86960 Chasseneuil du Poitou",
    "sg:city":"La Feuillie",
    "sg:orig_category":"Non-Classified Establishments",
    "sg:phone":"+33 5 49 49 55 00",
    "sg:postcode":"50190",
    "sg:province":"Basse Normandie",
    "wof:name":"Aquatis Futuroscope",
    "wof:placetype":"venue"
},
  "geometry": {"coordinates":[-0.11335,47.194229],"type":"Point"}
}