{
  "type": "Feature",
  "properties": {
    "addr:full":"131, Rue Bugarel, 34070 Montpellier Languedoc-Roussillon 34070",
    "addr:housenumber":"131",
    "addr:postcode":"34070;34070",
    "addr:street":"Rue Bugarel",
    "iso:country":"FR",
    "sg:address":"131, Rue Bugarel, 34070 Montpellier",
    "sg:orig_category":"Non-Classified Establishments",
    "sg:phone":"+33 4 67 42 70 25",
    "sg:postcode":"34070",
    "sg:province":"Languedoc-Roussillon",
    "wof:name":"Etablissements Mitjavila S.a.",
    "wof:placetype":"venue"
},
  "geometry": {"coordinates":[3.860394,43.594448],"type":"Point"}
}