{
  "type": "Feature",
  "properties": {
    "addr:full":"63 rue Dauphine; Paris; 75006 Ile de France 75006",
    "addr:housenumber":"63",
    "addr:postcode":"75006 ile;france 75006",
    "addr:street":"Rue Dauphine",
    "iso:country":"FR",
    "sg:address":"63 rue Dauphine; Paris; 75006",
    "sg:classifiers":[
        {
            "category":"Banks & Credit Unions",
            "subcategory":"Bank",
            "type":"Services"
        }
    ],
    "sg:phone":"+33 1 43 25 53 28",
    "sg:postcode":"75006",
    "sg:province":"Ile de France",
    "wof:name":"Soci\u00e9t\u00e9 G\u00e9n\u00e9rale",
    "wof:placetype":"venue"
},
  "geometry": {"coordinates":[2.338568,48.853695],"type":"Point"}
}