{
  "type": "Feature",
  "properties": {
    "addr:full":"19, Rue des Saints P\u00e8res, 75006 Paris Ile de France",
    "addr:housenumber":"19",
    "addr:postcode":"75006",
    "addr:street":"Rue Des Saints Pe\u0300Res",
    "iso:country":"FR",
    "sg:address":"19, Rue des Saints P\u00e8res, 75006 Paris",
    "sg:orig_category":"Unclassifiable Establishments",
    "sg:phone":"+33 1 42 44 29 29",
    "sg:province":"Ile de France",
    "wof:name":"Kvadrat S.a.",
    "wof:placetype":"venue"
},
  "geometry": {"coordinates":[2.332257,48.856792],"type":"Point"}
}