{
  "type": "Feature",
  "properties": {
    "addr:full":"96, Av. Pasteur, 33185 Le Haillan Le Haillan Aquitaine 33185",
    "addr:housenumber":"haillan;haillan",
    "addr:postcode":"33185;33185",
    "addr:street":"96 Av. Pasteur",
    "iso:country":"FR",
    "sg:address":"96, Av. Pasteur, 33185 Le Haillan",
    "sg:city":"Le Haillan",
    "sg:orig_category":"Non-Classified Establishments",
    "sg:phone":"+33 5 56 13 61 61",
    "sg:postcode":"33185",
    "sg:province":"Aquitaine",
    "wof:name":"Sogico S.a.",
    "wof:placetype":"venue"
},
  "geometry": {"coordinates":[-0.672937,44.86924],"type":"Point"}
}