{
  "type": "Feature",
  "properties": {
    "iso:country":"FR",
    "sg:address":"Rte de Graye",
    "sg:city":"Gigny",
    "sg:orig_category":"Non-Classified Establishments",
    "sg:phone":"+33 3 84 85 43 12",
    "sg:postcode":"39320",
    "sg:province":"Franche Comt\u00e9",
    "wof:name":"Corsetti Et Compagnie S.a.r.l.",
    "wof:placetype":"venue"
},
  "geometry": {"coordinates":[5.452781,46.393513],"type":"Point"}
}