{
  "type": "Feature",
  "properties": {
    "addr:full":"Z I Rue Nicolas Appert 39800 VAUX SUR POLIGNY Franche Comt\u00e9",
    "addr:housenumber":"z i",
    "addr:postcode":"39800",
    "addr:street":"Rue Nicolas Appert;Franche Comte\u0301",
    "iso:country":"FR",
    "sg:address":"Z I Rue Nicolas Appert 39800 VAUX SUR POLIGNY",
    "sg:classifiers":[
        {
            "category":"Train Station",
            "subcategory":"Light Rail",
            "type":"Transportation"
        }
    ],
    "sg:phone":"+33 3 84 37 35 20",
    "sg:province":"Franche Comt\u00e9",
    "sg:tags":[
        "box",
        "transport"
    ],
    "wof:name":"Sas Alp",
    "wof:placetype":"venue"
},
  "geometry": {"coordinates":[5.708668,46.834393],"type":"Point"}
}