{
  "type": "Feature",
  "properties": {
    "iso:country":"FR",
    "sg:address":"1814, Av. des Landiers, 73000 Chamb\u00e9ry",
    "sg:orig_category":"Unclassifiable Establishments",
    "sg:phone":"+33 4 79 68 63 63",
    "sg:postcode":"73000",
    "sg:province":"Rhone-Alpes",
    "wof:name":"Etablissements Savoicolor S.a.",
    "wof:placetype":"venue"
},
  "geometry": {"coordinates":[5.896102,45.597977],"type":"Point"}
}