{
  "type": "Feature",
  "properties": {
    "iso:country":"FR",
    "sg:address":"108, Faubourg d'Ambrail, 88000 Epinal",
    "sg:orig_category":"Unclassifiable Establishments",
    "sg:phone":"+33 3 29 35 27 21",
    "sg:province":"Lorraine",
    "wof:name":"Ideal Confort",
    "wof:placetype":"venue"
},
  "geometry": {"coordinates":[6.457513,48.174698],"type":"Point"}
}