{
  "type": "Feature",
  "properties": {
    "addr:full":"Quai Georges V - CHCI Le Havre Haute Normandie 76600",
    "addr:postcode":"76600",
    "addr:street":"Quai Georges V Chci",
    "iso:country":"FR",
    "sg:address":"Quai Georges V - CHCI",
    "sg:city":"Le Havre",
    "sg:orig_category":"Unclassifiable Establishments",
    "sg:phone":"+33 2 32 74 68 00",
    "sg:postcode":"76600",
    "sg:province":"Haute Normandie",
    "wof:name":"M.s.c. France S.a. - M\u00e9diterran\u00e9an Shipping Company",
    "wof:placetype":"venue"
},
  "geometry": {"coordinates":[0.101405,49.493511],"type":"Point"}
}