{
  "type": "Feature",
  "properties": {
    "addr:full":"19, Impasse Fourcaran, 31200 Toulouse Midi Pyr\u00e9n\u00e9es",
    "addr:housenumber":"19",
    "addr:postcode":"31200",
    "addr:street":"Impasse Fourcaran",
    "iso:country":"FR",
    "sg:address":"19, Impasse Fourcaran, 31200 Toulouse",
    "sg:orig_category":"Unclassifiable Establishments",
    "sg:phone":"+33 5 61 58 79 00",
    "sg:province":"Midi Pyr\u00e9n\u00e9es",
    "wof:name":"Fournie Grospaud S.a.",
    "wof:placetype":"venue"
},
  "geometry": {"coordinates":[1.452687,43.623032],"type":"Point"}
}