{
  "type": "Feature",
  "properties": {
    "addr:full":"Zone D Activite 22100 St Carne Dinan Bretagne 22100",
    "addr:postcode":"22100;22100",
    "iso:country":"FR",
    "sg:address":"Zone D Activite 22100 St Carne",
    "sg:city":"Dinan",
    "sg:classifiers":[
        {
            "category":"Manufacturing",
            "subcategory":"Wood Products",
            "type":"Manufacturing & Wholesale Goods"
        }
    ],
    "sg:phone":"+33 2 96 83 51 12",
    "sg:postcode":"22100",
    "sg:province":"Bretagne",
    "sg:tags":[
        "furniture"
    ],
    "wof:name":"Daniel Pestel",
    "wof:placetype":"venue"
},
  "geometry": {"coordinates":[-2.064739,48.416714],"type":"Point"}
}