{
  "type": "Feature",
  "properties": {
    "iso:country":"FR",
    "sg:address":"37, Rue de Li\u00e8ge, 75008 Paris",
    "sg:orig_category":"Non-Classified Establishments",
    "sg:phone":"+33 1 55 30 17 00",
    "sg:province":"Ile de France",
    "wof:name":"Navision France S.a.",
    "wof:placetype":"venue"
},
  "geometry": {"coordinates":[2.32526,48.879208],"type":"Point"}
}