{
  "type": "Feature",
  "properties": {
    "addr:full":"Angle rue Canot; Miramas; 13140 Picardie",
    "addr:postcode":"13140",
    "addr:street":"Angle Rue Canot",
    "iso:country":"FR",
    "sg:address":"Angle rue Canot; Miramas; 13140",
    "sg:classifiers":[
        {
            "category":"Banks & Credit Unions",
            "subcategory":"Bank",
            "type":"Services"
        }
    ],
    "sg:phone":"+33 3390582363",
    "sg:province":"Picardie",
    "wof:name":"Soci\u00e9t\u00e9 G\u00e9n\u00e9rale",
    "wof:placetype":"venue"
},
  "geometry": {"coordinates":[5.00306,43.584637],"type":"Point"}
}