{
  "type": "Feature",
  "properties": {
    "addr:full":"11, Rue du Bel Air, 14790 Verson Verson Basse Normandie 14790",
    "addr:housenumber":"11",
    "addr:postcode":"14790;14790",
    "addr:street":"Rue Du Bel Air",
    "iso:country":"FR",
    "sg:address":"11, Rue du Bel Air, 14790 Verson",
    "sg:city":"Verson",
    "sg:orig_category":"Non-Classified Establishments",
    "sg:phone":"+33 2 31 26 58 80",
    "sg:postcode":"14790",
    "sg:province":"Basse Normandie",
    "wof:name":"N.c.i.i. S.n.c. - Nourry Conception Engineering Inject",
    "wof:placetype":"venue"
},
  "geometry": {"coordinates":[-0.46347,49.158974],"type":"Point"}
}