{
  "type": "Feature",
  "properties": {
    "addr:full":"9, Rue Gustave Eiffel - ZI de Gellainville, 28630 Gellainville Gellainville Centre 28630",
    "addr:housenumber":"9;gellainville",
    "addr:postcode":"28630;28630",
    "addr:street":"Rue Gustave Eiffel Zi De Gellainville",
    "iso:country":"FR",
    "sg:address":"9, Rue Gustave Eiffel - ZI de Gellainville, 28630 Gellainville",
    "sg:city":"Gellainville",
    "sg:orig_category":"Non-Classified Establishments",
    "sg:phone":"+33 2 37 33 40 00",
    "sg:postcode":"28630",
    "sg:province":"Centre",
    "wof:name":"Architel S.a.",
    "wof:placetype":"venue"
},
  "geometry": {"coordinates":[1.49045,48.429531],"type":"Point"}
}