{
  "type": "Feature",
  "properties": {
    "iso:country":"FR",
    "sg:address":"28 rue Jean Bertin 26000 Valence",
    "sg:classifiers":[
        {
            "category":"Science Facility",
            "type":"Public Place"
        }
    ],
    "sg:phone":"+33 4 75 56 89 49",
    "sg:postcode":"26000",
    "sg:province":"Rhone-Alpes",
    "sg:tags":[
        "aid",
        "natural",
        "teaching"
    ],
    "wof:name":"A.t.e. S.a.r.l.",
    "wof:placetype":"venue"
},
  "geometry": {"coordinates":[4.915879,44.914078],"type":"Point"}
}