{
  "type": "Feature",
  "properties": {
    "addr:full":"Rue de l'Industrie - ZI M\u00e9lou Castres Midi Pyr\u00e9n\u00e9es 81100",
    "addr:postcode":"81100",
    "addr:street":"Rue De L'Industrie Zi Me\u0301Lou",
    "iso:country":"FR",
    "sg:address":"Rue de l'Industrie - ZI M\u00e9lou",
    "sg:city":"Castres",
    "sg:orig_category":"Unclassifiable Establishments",
    "sg:phone":"+33 5 63 59 15 75",
    "sg:postcode":"81100",
    "sg:province":"Midi Pyr\u00e9n\u00e9es",
    "wof:name":"Etablissements Lucien Albouy Et Compagnie S.a.",
    "wof:placetype":"venue"
},
  "geometry": {"coordinates":[2.233331,43.607273],"type":"Point"}
}