{
  "type": "Feature",
  "properties": {
    "addr:full":"54, Rue Raspail, 69150 D\u00e9cines Charpieu Rhone-Alpes",
    "addr:housenumber":"54",
    "addr:postcode":"69150",
    "addr:street":"Rue Raspail",
    "iso:country":"FR",
    "sg:address":"54, Rue Raspail, 69150 D\u00e9cines Charpieu",
    "sg:orig_category":"Unclassifiable Establishments",
    "sg:phone":"+33 4 37 42 20 50",
    "sg:province":"Rhone-Alpes",
    "wof:name":"Bosch Techniques D'automation S.a.",
    "wof:placetype":"venue"
},
  "geometry": {"coordinates":[4.947026,45.761047],"type":"Point"}
}