{
  "type": "Feature",
  "properties": {
    "addr:full":"6 Cours De L'Argonne 33000 Bordeaux Bordeaux Aquitaine 33000",
    "addr:housenumber":"6",
    "addr:postcode":"33000;33000",
    "addr:street":"Cours De L'Argonne",
    "iso:country":"FR",
    "sg:address":"6 Cours De L'Argonne 33000 Bordeaux",
    "sg:city":"Bordeaux",
    "sg:classifiers":[
        {
            "category":"Home & Garden",
            "subcategory":"Furniture",
            "type":"Retail Goods"
        }
    ],
    "sg:phone":"+33 5 56 33 38 38",
    "sg:postcode":"33000",
    "sg:province":"Aquitaine",
    "sg:tags":[
        "household",
        "wood"
    ],
    "wof:name":"Generale De Literie Sa",
    "wof:placetype":"venue"
},
  "geometry": {"coordinates":[-0.573788,44.829365],"type":"Point"}
}