{
  "type": "Feature",
  "properties": {
    "iso:country":"FR",
    "sg:address":"30-34 ave Jean Lolive; Paris; 93503",
    "sg:classifiers":[
        {
            "category":"Banks & Credit Unions",
            "subcategory":"Bank",
            "type":"Services"
        }
    ],
    "sg:phone":"+33 1 48 10 88 10",
    "sg:province":"Ile de France",
    "wof:name":"Banque De France",
    "wof:placetype":"venue"
},
  "geometry": {"coordinates":[2.40379,48.885441],"type":"Point"}
}