{
  "type": "Feature",
  "properties": {
    "iso:country":"FR",
    "sg:address":"16, Rue de la Petite Sensive, 44300 Nantes",
    "sg:orig_category":"Non-Classified Establishments",
    "sg:phone":"+33 2 51 81 85 85",
    "sg:postcode":"44300",
    "sg:province":"Pays de Loire",
    "wof:name":"D.s.i.a. S.n.c. - Division Des Syst\u00e8mes Informatiques Appliqu\u00e9s",
    "wof:placetype":"venue"
},
  "geometry": {"coordinates":[-1.560539,47.259365],"type":"Point"}
}