{
  "type": "Feature",
  "properties": {
    "addr:full":"10 R Vauvert 37210 Rochecorbon Rochecorbon Centre 37210",
    "addr:housenumber":"10",
    "addr:postcode":"37210;37210",
    "addr:street":"R Vauvert",
    "iso:country":"FR",
    "sg:address":"10 R Vauvert 37210 Rochecorbon",
    "sg:city":"Rochecorbon",
    "sg:classifiers":[
        {
            "category":"Food Court",
            "type":"Food & Drink"
        }
    ],
    "sg:phone":"+33 2 47 52 54 85",
    "sg:postcode":"37210",
    "sg:province":"Centre",
    "sg:tags":[
        "product",
        "related"
    ],
    "wof:name":"Roger Felicien Brou Sa",
    "wof:placetype":"venue"
},
  "geometry": {"coordinates":[0.764926,47.411469],"type":"Point"}
}