{
  "type": "Feature",
  "properties": {
    "addr:full":"Rue du Commerce Vern d'Anjou Pays de Loire 49220",
    "addr:postcode":"49220",
    "addr:street":"Rue Du Commerce;D'Anjou",
    "iso:country":"FR",
    "sg:address":"Rue du Commerce",
    "sg:city":"Vern d'Anjou",
    "sg:orig_category":"Unclassifiable Establishments",
    "sg:phone":"+33 2 41 61 00 97",
    "sg:postcode":"49220",
    "sg:province":"Pays de Loire",
    "wof:name":"Sai Vern D'anjou S.a.",
    "wof:placetype":"venue"
},
  "geometry": {"coordinates":[-0.834513,47.600414],"type":"Point"}
}