{
  "type": "Feature",
  "properties": {
    "iso:country":"FR",
    "sg:address":"Fond de Veau 02210 ROZET ST ALBIN",
    "sg:classifiers":[
        {
            "category":"Conference Center",
            "type":"Public Place"
        }
    ],
    "sg:phone":"+33 3 23 71 11 11",
    "sg:province":"Picardie",
    "sg:tags":[
        "system",
        "trade",
        "call",
        "telephones",
        "telephone",
        "systems"
    ],
    "wof:name":"Decelect Forgos Sa",
    "wof:placetype":"venue"
},
  "geometry": {"coordinates":[3.35096,49.21339],"type":"Point"}
}