{
  "type": "Feature",
  "properties": {
    "addr:full":"Ch\u00e2teau de Rolland 33720 Barsac Barsac Aquitaine 33720",
    "addr:postcode":"33720;33720",
    "iso:country":"FR",
    "sg:address":"Ch\u00e2teau de Rolland 33720 Barsac",
    "sg:city":"Barsac",
    "sg:orig_category":"Non-Classified Establishments",
    "sg:phone":"+33 5 56 27 15 02",
    "sg:postcode":"33720",
    "sg:province":"Aquitaine",
    "wof:name":"Vignobles Guignard S.c.a.",
    "wof:placetype":"venue"
},
  "geometry": {"coordinates":[-0.385279,44.533298],"type":"Point"}
}