{
  "type": "Feature",
  "properties": {
    "addr:full":"29 Cours Georges Clemenceau Bordeaux Aquitaine 33000",
    "addr:housenumber":"29",
    "addr:postcode":"33000",
    "addr:street":"Cours Georges Clemenceau",
    "iso:country":"FR",
    "sg:address":"29 Cours Georges Clemenceau",
    "sg:city":"Bordeaux",
    "sg:classifiers":[
        {
            "category":"Banks & Credit Unions",
            "subcategory":"Financial Services",
            "type":"Services"
        }
    ],
    "sg:phone":"+33 5 56 00 40 60",
    "sg:postcode":"33000",
    "sg:province":"Aquitaine",
    "sg:tags":[
        "banking",
        "finance",
        "insurance"
    ],
    "wof:name":"Paribas",
    "wof:placetype":"venue"
},
  "geometry": {"coordinates":[-0.579414,44.843113],"type":"Point"}
}