{
  "type": "Feature",
  "properties": {
    "addr:full":"Park Touraine - Tauxigny Tauxigny Centre 37310",
    "addr:postcode":"37310",
    "addr:street":"Park",
    "iso:country":"FR",
    "sg:address":"Park Touraine - Tauxigny",
    "sg:city":"Tauxigny",
    "sg:orig_category":"Unclassifiable Establishments",
    "sg:phone":"+33 2 47 34 63 46",
    "sg:postcode":"37310",
    "sg:province":"Centre",
    "wof:name":"M\u00e9tronic S.a.s.",
    "wof:placetype":"venue"
},
  "geometry": {"coordinates":[0.89534,47.164757],"type":"Point"}
}