{
  "type": "Feature",
  "properties": {
    "iso:country":"FR",
    "sg:address":"La Villette Aux Aulnes Zac 77290 Mitry Mory",
    "sg:classifiers":[
        {
            "category":"Autos & Motor Vehicles",
            "subcategory":"Automobile Sales",
            "type":"Retail Goods"
        }
    ],
    "sg:phone":"+33 1 64 67 59 59",
    "sg:province":"Ile de France",
    "sg:tags":[
        "equipment",
        "transport"
    ],
    "wof:name":"Ste Du Poids Lourd Paris Sa",
    "wof:placetype":"venue"
},
  "geometry": {"coordinates":[2.57673,48.967949],"type":"Point"}
}