{
  "type": "Feature",
  "properties": {
    "iso:country":"FR",
    "sg:address":"21, Quai des Mines, 59300 Valenciennes",
    "sg:orig_category":"Unclassifiable Establishments",
    "sg:phone":"+33 3 27 46 34 22",
    "sg:province":"Nord Pas-de-Calais",
    "wof:name":"Dejonghe Et Dervaux S.a.r.l.",
    "wof:placetype":"venue"
},
  "geometry": {"coordinates":[3.51696,50.368519],"type":"Point"}
}