{
  "type": "Feature",
  "properties": {
    "iso:country":"FR",
    "sg:address":"14, Grande Rue, 90160 P\u00e9rouse",
    "sg:orig_category":"Unclassifiable Establishments",
    "sg:phone":"+33 3 84 22 46 86",
    "sg:province":"Franche Comt\u00e9",
    "wof:name":"Rui Plasti Concept S.a.",
    "wof:placetype":"venue"
},
  "geometry": {"coordinates":[6.883182,47.637768],"type":"Point"}
}