{
  "type": "Feature",
  "properties": {
    "addr:full":"127, Av. Aristide Briand, 93190 Livry Gargan Ile de France",
    "addr:postcode":"93190",
    "addr:street":"127 Av. Aristide Briand",
    "iso:country":"FR",
    "sg:address":"127, Av. Aristide Briand, 93190 Livry Gargan",
    "sg:orig_category":"Unclassifiable Establishments",
    "sg:phone":"+33 1 43 02 82 00",
    "sg:province":"Ile de France",
    "wof:name":"C.i.b.c.f. S.a.",
    "wof:placetype":"venue"
},
  "geometry": {"coordinates":[2.52531,48.913944],"type":"Point"}
}