{
  "type": "Feature",
  "properties": {
    "iso:country":"FR",
    "sg:address":"B.P. 53, 69513 Vaulx en Velin C\u00e9dex^^65, Rue Alexandre Dumas, 69120 Vaulx en Velin",
    "sg:orig_category":"Non-Classified Establishments",
    "sg:phone":"+33 4 72 15 11 80",
    "sg:postcode":"69120",
    "sg:province":"Rhone-Alpes",
    "wof:name":"Id\u00e9al S.a.",
    "wof:placetype":"venue"
},
  "geometry": {"coordinates":[4.916895,45.779022],"type":"Point"}
}