{
  "type": "Feature",
  "properties": {
    "addr:full":"94508 Champigny sur Marne C\u00e9dex^^466, Rue du March\u00e9 Rollay, 94500 Champigny sur Marne Ile de France 94500",
    "addr:postcode":"94508;94500;94500",
    "addr:street":"Rue Du Marche\u0301 Rollay",
    "iso:country":"FR",
    "sg:address":"94508 Champigny sur Marne C\u00e9dex^^466, Rue du March\u00e9 Rollay, 94500 Champigny sur Marne",
    "sg:orig_category":"Non-Classified Establishments",
    "sg:phone":"+33 1 48 81 84 59",
    "sg:postcode":"94500",
    "sg:province":"Ile de France",
    "wof:name":"Dynisco Instruments S.a.r.l.",
    "wof:placetype":"venue"
},
  "geometry": {"coordinates":[2.51158,48.813404],"type":"Point"}
}