{
  "type": "Feature",
  "properties": {
    "iso:country":"FR",
    "sg:address":"27 Rue Victor Hugo 59430 St Pol Sur Mer",
    "sg:classifiers":[
        {
            "category":"Utilities",
            "subcategory":"Electric",
            "type":"Services"
        }
    ],
    "sg:phone":"+33 3 28 64 10 30",
    "sg:postcode":"59430",
    "sg:province":"Nord Pas-de-Calais",
    "sg:tags":[
        "electricity",
        "electronic",
        "electrical",
        "equipment"
    ],
    "wof:name":"Tercem",
    "wof:placetype":"venue"
},
  "geometry": {"coordinates":[2.355835,51.032387],"type":"Point"}
}