{
  "type": "Feature",
  "properties": {
    "iso:country":"FR",
    "sg:address":"113, Av du G\u00e9n\u00e9ral de Gaulle, 60550 Verneuil en Halatte",
    "sg:orig_category":"Unclassifiable Establishments",
    "sg:phone":"+33 3 44 29 65 00",
    "sg:province":"Picardie",
    "wof:name":"Bourjois S.a.",
    "wof:placetype":"venue"
},
  "geometry": {"coordinates":[2.52891,49.287071],"type":"Point"}
}