{
  "type": "Feature",
  "properties": {
    "iso:country":"FR",
    "sg:address":"route nationale 143 36501 BUZANCAIS",
    "sg:orig_category":"Carpets, Machine-Tufted",
    "sg:phone":"+33 2 54 02 27 27",
    "sg:province":"Centre",
    "wof:name":"Berry Tapis S.a.",
    "wof:placetype":"venue"
},
  "geometry": {"coordinates":[1.422442,46.889423],"type":"Point"}
}