{
  "type": "Feature",
  "properties": {
    "iso:country":"FR",
    "sg:address":"8 Rue D'Entrecasteaux 13100 Aix En Provence",
    "sg:classifiers":[
        {
            "category":"Travel",
            "subcategory":"Hotels & Motels",
            "type":"Entertainment"
        }
    ],
    "sg:phone":"+33 4 42 26 27 20",
    "sg:province":"Nord Pas-de-Calais",
    "sg:tags":[
        "hotels",
        "business",
        "restaurant"
    ],
    "wof:name":"Hotel Le Manoir Sa",
    "wof:placetype":"venue"
},
  "geometry": {"coordinates":[5.444691,43.528637],"type":"Point"}
}