{
  "type": "Feature",
  "properties": {
    "iso:country":"FR",
    "sg:address":"Chemin De Morcourt 02100 St Quentin",
    "sg:classifiers":[
        {
            "category":"Professional",
            "subcategory":"Advertising",
            "type":"Services"
        }
    ],
    "sg:phone":"+33 3 23 06 04 02",
    "sg:postcode":"02100",
    "sg:province":"Picardie",
    "sg:tags":[
        "information",
        "medium",
        "communication"
    ],
    "wof:name":"Edelcolor France",
    "wof:placetype":"venue"
},
  "geometry": {"coordinates":[3.306302,49.862316],"type":"Point"}
}