{
  "type": "Feature",
  "properties": {
    "iso:country":"FR",
    "sg:address":"69009 Lyon",
    "sg:classifiers":[
        {
            "category":"Shopping",
            "subcategory":"Clothing, Apparel, & Fashions",
            "type":"Retail Goods"
        }
    ],
    "sg:phone":"+33 4 72 53 04 43",
    "sg:postcode":"69009",
    "sg:province":"Rhone-Alpes",
    "sg:tags":[
        "industry",
        "clothing",
        "drawing"
    ],
    "wof:name":"Lyon Lisages Sarl",
    "wof:placetype":"venue"
},
  "geometry": {"coordinates":[4.81266,45.78347],"type":"Point"}
}