{
  "type": "Feature",
  "properties": {
    "iso:country":"FR",
    "sg:address":"293, Rue de la Justice, 77000 Melun",
    "sg:orig_category":"Unclassifiable Establishments",
    "sg:phone":"+33 1 64 39 61 25",
    "sg:province":"Ile de France",
    "wof:name":"Artenis Varisellaz S.a.",
    "wof:placetype":"venue"
},
  "geometry": {"coordinates":[2.664085,48.539577],"type":"Point"}
}