{
  "type": "Feature",
  "properties": {
    "addr:full":"192, Av. boudin, 87000 Limoges Limousin 87000",
    "addr:postcode":"87000;87000",
    "addr:street":"192 Av. Boudin",
    "iso:country":"FR",
    "sg:address":"192, Av. boudin, 87000 Limoges",
    "sg:orig_category":"Non-Classified Establishments",
    "sg:phone":"+33 5 55 11 92 10",
    "sg:postcode":"87000",
    "sg:province":"Limousin",
    "wof:name":"Elis Limousin S.a.s.",
    "wof:placetype":"venue"
},
  "geometry": {"coordinates":[1.26201,45.828785],"type":"Point"}
}