{
  "type": "Feature",
  "properties": {
    "addr:full":"Castilloux 24800 Nanthiat Nanthiat Aquitaine 24800",
    "addr:postcode":"24800;24800",
    "addr:street":"Castilloux",
    "iso:country":"FR",
    "sg:address":"Castilloux 24800 Nanthiat",
    "sg:city":"Nanthiat",
    "sg:orig_category":"Unclassifiable Establishments",
    "sg:phone":"+33 5 53 62 20 00",
    "sg:postcode":"24800",
    "sg:province":"Aquitaine",
    "wof:name":"Guyenne Papier S.a.",
    "wof:placetype":"venue"
},
  "geometry": {"coordinates":[0.81799,45.360855],"type":"Point"}
}