{
  "type": "Feature",
  "properties": {
    "addr:full":"32 Rue De La Republique 71300 Montceau Les Mines Saint-Berain-sous-Sanvignes Bourgogne 71300",
    "addr:housenumber":"32",
    "addr:postcode":"71300;71300",
    "addr:street":"Rue De La Republique;Bourgogne",
    "iso:country":"FR",
    "sg:address":"32 Rue De La Republique 71300 Montceau Les Mines",
    "sg:city":"Saint-Berain-sous-Sanvignes",
    "sg:classifiers":[
        {
            "category":"Professional",
            "subcategory":"Printing & Photocopies",
            "type":"Services"
        }
    ],
    "sg:phone":"+33 3 85 58 71 17",
    "sg:postcode":"71300",
    "sg:province":"Bourgogne",
    "sg:tags":[
        "publishing"
    ],
    "wof:name":"Comareg Sa",
    "wof:placetype":"venue"
},
  "geometry": {"coordinates":[4.365012,46.676266],"type":"Point"}
}