{
  "type": "Feature",
  "properties": {
    "addr:full":"8 Rue Garibaldi; Fos Midi Pyr\u00e9n\u00e9es",
    "addr:housenumber":"8",
    "addr:street":"Rue Garibaldi",
    "iso:country":"FR",
    "sg:address":"8 Rue Garibaldi; Fos",
    "sg:classifiers":[
        {
            "category":"Banks & Credit Unions",
            "subcategory":"Bank",
            "type":"Services"
        }
    ],
    "sg:phone":"+33 3342050905",
    "sg:province":"Midi Pyr\u00e9n\u00e9es",
    "wof:name":"Cr\u00e9dit Mutuel",
    "wof:placetype":"venue"
},
  "geometry": {"coordinates":[3.246629,43.56694],"type":"Point"}
}