{
  "type": "Feature",
  "properties": {
    "addr:full":"All\u00e9e de la Deule - ZI des Ansereuilles Wavrin Nord Pas-de-Calais 59136",
    "addr:postcode":"59136",
    "addr:street":"Alle\u0301E De La Deule Zi Des Ansereuilles Wavrin Nord",
    "iso:country":"FR",
    "sg:address":"All\u00e9e de la Deule - ZI des Ansereuilles",
    "sg:city":"Wavrin",
    "sg:orig_category":"Unclassifiable Establishments",
    "sg:phone":"+33 3 20 58 76 70",
    "sg:postcode":"59136",
    "sg:province":"Nord Pas-de-Calais",
    "wof:name":"J.p.b. S.a.r.l.",
    "wof:placetype":"venue"
},
  "geometry": {"coordinates":[2.93284,50.570339],"type":"Point"}
}