{
  "type": "Feature",
  "properties": {
    "addr:full":"29 R Des Ard\u00e8nes 21000 Dijon Dijon Bourgogne 21000",
    "addr:housenumber":"29",
    "addr:postcode":"21000;21000",
    "addr:street":"R Des Arde\u0300Nes",
    "iso:country":"FR",
    "sg:address":"29 R Des Ard\u00e8nes 21000 Dijon",
    "sg:city":"Dijon",
    "sg:classifiers":[
        {
            "category":"Manufacturing",
            "subcategory":"Rubber & Plastics",
            "type":"Manufacturing & Wholesale Goods"
        }
    ],
    "sg:phone":"+33 3 80 28 09 40",
    "sg:postcode":"21000",
    "sg:province":"Bourgogne",
    "wof:name":"Pum Plastique Sa",
    "wof:placetype":"venue"
},
  "geometry": {"coordinates":[5.064487,47.35561],"type":"Point"}
}