{
  "type": "Feature",
  "properties": {
    "addr:full":"5 Bd Raspail 75007 Paris Ile de France 75007",
    "addr:housenumber":"5",
    "addr:postcode":"75007;75007",
    "addr:street":"Bd Raspail",
    "iso:country":"FR",
    "sg:address":"5 Bd Raspail 75007 Paris",
    "sg:classifiers":[
        {
            "category":"Home & Garden",
            "subcategory":"Furniture",
            "type":"Retail Goods"
        }
    ],
    "sg:phone":"+33 1 42 22 21 25",
    "sg:postcode":"75007",
    "sg:province":"Ile de France",
    "sg:tags":[
        "household",
        "wood"
    ],
    "wof:name":"Notre Dame Decoration Cuisines",
    "wof:placetype":"venue"
},
  "geometry": {"coordinates":[2.326061,48.855309],"type":"Point"}
}