{
  "type": "Feature",
  "properties": {
    "iso:country":"FR",
    "sg:address":"110, Rte des Relles Gouttes, 88400 Xonrupt Longemer",
    "sg:orig_category":"Unclassifiable Establishments",
    "sg:phone":"+33 3 29 63 07 18",
    "sg:province":"Lorraine",
    "wof:name":"Mathieu Jean S.a.",
    "wof:placetype":"venue"
},
  "geometry": {"coordinates":[6.924276,48.08041],"type":"Point"}
}