{
  "type": "Feature",
  "properties": {
    "iso:country":"FR",
    "sg:address":"226 Boulevard Saint-Germain",
    "sg:city":"Paris",
    "sg:classifiers":[
        {
            "category":"Banks & Credit Unions",
            "subcategory":"Financial Services",
            "type":"Services"
        }
    ],
    "sg:phone":"+33 1 45 44 38 70",
    "sg:postcode":"75007",
    "sg:province":"Ile de France",
    "sg:tags":[
        "banking",
        "finance",
        "insurance"
    ],
    "wof:name":"Dominique Ader",
    "wof:placetype":"venue"
},
  "geometry": {"coordinates":[2.327274,48.855614],"type":"Point"}
}