{
  "type": "Feature",
  "properties": {
    "addr:full":"5, Rue de la R\u00e9union, 91940 Les Ulis Ile de France",
    "addr:housenumber":"5",
    "addr:postcode":"91940",
    "addr:street":"Rue De La Re\u0301Union",
    "iso:country":"FR",
    "sg:address":"5, Rue de la R\u00e9union, 91940 Les Ulis",
    "sg:orig_category":"Non-Classified Establishments",
    "sg:phone":"+33 1 69 29 85 35",
    "sg:province":"Ile de France",
    "wof:name":"Groupe Voisin S.a.",
    "wof:placetype":"venue"
},
  "geometry": {"coordinates":[2.201508,48.681435],"type":"Point"}
}