{
  "type": "Feature",
  "properties": {
    "iso:country":"FR",
    "sg:address":"189 Rue D Aubervilliers 75018 Paris",
    "sg:classifiers":[
        {
            "category":"Manufacturing",
            "subcategory":"Printing",
            "type":"Manufacturing & Wholesale Goods"
        }
    ],
    "sg:phone":"+33 1 40 34 99 58",
    "sg:province":"Ile de France",
    "sg:tags":[
        "publishing"
    ],
    "wof:name":"Photogravure D 6",
    "wof:placetype":"venue"
},
  "geometry": {"coordinates":[2.370354,48.896683],"type":"Point"}
}