{
  "type": "Feature",
  "properties": {
    "addr:full":"42 rue de la Gare 68150 Ostheim Ostheim Alsace 68150",
    "addr:housenumber":"42",
    "addr:postcode":"68150;68150",
    "addr:street":"Rue De La Gare",
    "iso:country":"FR",
    "sg:address":"42 rue de la Gare 68150 Ostheim",
    "sg:city":"Ostheim",
    "sg:classifiers":[
        {
            "category":"Manufacturing",
            "subcategory":"Lumber",
            "type":"Manufacturing & Wholesale Goods"
        }
    ],
    "sg:phone":"+33 3 89 47 90 53",
    "sg:postcode":"68150",
    "sg:province":"Alsace",
    "sg:tags":[
        "hardwood",
        "sawmill"
    ],
    "wof:name":"St\u00e9 D'exploitation Des Ets Grauer S.a.",
    "wof:placetype":"venue"
},
  "geometry": {"coordinates":[7.363652,48.159355],"type":"Point"}
}