{
  "type": "Feature",
  "properties": {
    "addr:full":"69, Rue Saint Nicolas, 78600 Maisons Laffitte Ile de France",
    "addr:housenumber":"69",
    "addr:postcode":"78600",
    "addr:street":"Rue Saint Nicolas",
    "iso:country":"FR",
    "sg:address":"69, Rue Saint Nicolas, 78600 Maisons Laffitte",
    "sg:orig_category":"Unclassifiable Establishments",
    "sg:phone":"+33 1 39 62 47 98",
    "sg:province":"Ile de France",
    "wof:name":"Etablissement G. Chambert S.a.",
    "wof:placetype":"venue"
},
  "geometry": {"coordinates":[2.136194,48.946518],"type":"Point"}
}