{
  "type": "Feature",
  "properties": {
    "addr:full":"16 Rue De La Taye 28110 Luc\u00e9 Luc\u00e9 Centre 28110",
    "addr:housenumber":"16",
    "addr:postcode":"28110;28110",
    "addr:street":"Rue De La Taye",
    "iso:country":"FR",
    "sg:address":"16 Rue De La Taye 28110 Luc\u00e9",
    "sg:city":"Luc\u00e9",
    "sg:classifiers":[
        {
            "category":"Utilities",
            "subcategory":"Telephone",
            "type":"Services"
        }
    ],
    "sg:phone":"+33 2 37 28 27 27",
    "sg:postcode":"28110",
    "sg:province":"Centre",
    "sg:tags":[
        "electricity",
        "equipment",
        "electrical",
        "telecommunication",
        "electronic"
    ],
    "wof:name":"Telephonie Francaise Du Centre",
    "wof:placetype":"venue"
},
  "geometry": {"coordinates":[1.446282,48.428207],"type":"Point"}
}