{
  "type": "Feature",
  "properties": {
    "iso:country":"FR",
    "sg:address":"B.P. 40212, 60722 Pont Sainte Maxence^^Zone Industrielle - Les Poiriers , 60700 Pont Sainte Maxence",
    "sg:orig_category":"Non-Classified Establishments",
    "sg:phone":"+33 3 44 72 22 33",
    "sg:postcode":"60700",
    "sg:province":"Picardie",
    "wof:name":"Bordeau S.a.",
    "wof:placetype":"venue"
},
  "geometry": {"coordinates":[2.604419,49.302036],"type":"Point"}
}