{
  "type": "Feature",
  "properties": {
    "iso:country":"FR",
    "sg:address":"15, rue du Quatre Septembre, 75002 Paris",
    "sg:classifiers":[
        {
            "category":"Banks & Credit Unions",
            "subcategory":"Financial Services",
            "type":"Services"
        }
    ],
    "sg:phone":"+33 1 44 86 10 00",
    "sg:postcode":"75002",
    "sg:province":"Ile de France",
    "sg:tags":[
        "banking",
        "finance",
        "insurance"
    ],
    "wof:name":"Odysseyre",
    "wof:placetype":"venue"
},
  "geometry": {"coordinates":[2.336854,48.869431],"type":"Point"}
}