{
  "type": "Feature",
  "properties": {
    "iso:country":"FR",
    "sg:address":"41-43 Paul Peytral; Marseille; 13006",
    "sg:classifiers":[
        {
            "category":"Banks & Credit Unions",
            "subcategory":"Bank",
            "type":"Services"
        }
    ],
    "sg:phone":"+33 4 91 81 65 60",
    "sg:province":"Poitou-Charentes",
    "wof:name":"Banque Chaix",
    "wof:placetype":"venue"
},
  "geometry": {"coordinates":[5.378736,43.289982],"type":"Point"}
}