{
  "type": "Feature",
  "properties": {
    "iso:country":"FR",
    "sg:address":"Le Vivier des Landes 37130 Mazi\u00e8res de Touraine",
    "sg:city":"Br\u00e9h\u00e9mont",
    "sg:orig_category":"Unclassifiable Establishments",
    "sg:phone":"+33 2 47 96 44 22",
    "sg:postcode":"37130",
    "sg:province":"Centre",
    "wof:name":"Cousseau - Elevage Du Vivier Des Landes E.a.r.l.",
    "wof:placetype":"venue"
},
  "geometry": {"coordinates":[0.396924,47.380188],"type":"Point"}
}