{
  "type": "Feature",
  "properties": {
    "addr:full":"23 Av Jean De Lattre De Tassi 06400 Cannes",
    "addr:postcode":"06400",
    "addr:street":"23 Av Jean De Lattre De Tassi",
    "iso:country":"FR",
    "sg:address":"23 Av Jean De Lattre De Tassi 06400 Cannes",
    "sg:classifiers":[
        {
            "category":"Government",
            "subcategory":"Department Of Motor Vehicles",
            "type":"Public Place"
        }
    ],
    "sg:phone":"+33 4 93 39 35 73",
    "sg:tags":[
        "equipment",
        "industrial",
        "transport",
        "motor-cars"
    ],
    "wof:name":"Electricite Nautique Auto (ena)",
    "wof:placetype":"venue"
},
  "geometry": {"coordinates":[7.013327,43.556038],"type":"Point"}
}