{
  "type": "Feature",
  "properties": {
    "iso:country":"FR",
    "sg:address":"12, Quai Magellan, 44000 Nantes",
    "sg:orig_category":"Unclassifiable Establishments",
    "sg:phone":"+33 2 40 47 40 57",
    "sg:province":"Pays de Loire",
    "wof:name":"Chantiers Magellan S.a.",
    "wof:placetype":"venue"
},
  "geometry": {"coordinates":[-1.544259,47.210461],"type":"Point"}
}