{
  "type": "Feature",
  "properties": {
    "iso:country":"FR",
    "sg:address":"69330 Meyzieu",
    "sg:orig_category":"Unclassifiable Establishments",
    "sg:phone":"+33 4 78 04 12 62",
    "sg:postcode":"69330",
    "sg:province":"Rhone-Alpes",
    "wof:name":"Berruet Monnet S.a.",
    "wof:placetype":"venue"
},
  "geometry": {"coordinates":[5.04071,45.773151],"type":"Point"}
}