{
  "type": "Feature",
  "properties": {
    "addr:full":"Lieu Dit La Neuville 27500 Tourville Sur Pont Audemer Haute Normandie 27500",
    "addr:postcode":"27500;27500",
    "addr:street":"Lieu Dit La Neuville;Audemer Haute Normandie",
    "iso:country":"FR",
    "sg:address":"Lieu Dit La Neuville 27500 Tourville Sur Pont Audemer",
    "sg:classifiers":[
        {
            "category":"Utilities",
            "subcategory":"Electric",
            "type":"Services"
        }
    ],
    "sg:phone":"+33 2 32 42 00 93",
    "sg:postcode":"27500",
    "sg:province":"Haute Normandie",
    "sg:tags":[
        "electricity",
        "raw",
        "energy",
        "material"
    ],
    "wof:name":"Enth",
    "wof:placetype":"venue"
},
  "geometry": {"coordinates":[0.5067,49.300587],"type":"Point"}
}