{
  "type": "Feature",
  "properties": {
    "iso:country":"FR",
    "sg:address":"Zi Des Cadesteaux 13744 Vitrolles",
    "sg:classifiers":[
        {
            "category":"Autos & Motor Vehicles",
            "subcategory":"Automobile Sales",
            "type":"Retail Goods"
        }
    ],
    "sg:phone":"+33 4 42 87 15 86",
    "sg:province":"Midi Pyr\u00e9n\u00e9es",
    "sg:tags":[
        "equipment",
        "motor-cars",
        "transport"
    ],
    "wof:name":"Sovicar",
    "wof:placetype":"venue"
},
  "geometry": {"coordinates":[5.24853,43.46043],"type":"Point"}
}