{
  "type": "Feature",
  "properties": {
    "iso:country":"FR",
    "sg:address":"ZI Suzerolles",
    "sg:city":"Seiches sur le Loir",
    "sg:orig_category":"Non-Classified Establishments",
    "sg:phone":"+33 2 41 76 28 40",
    "sg:postcode":"49140",
    "sg:province":"Pays de Loire",
    "wof:name":"Eurodifroid S.a.",
    "wof:placetype":"venue"
},
  "geometry": {"coordinates":[-0.358809,47.574299],"type":"Point"}
}