{
  "type": "Feature",
  "properties": {
    "addr:full":"33, Rue de Miromesnil, 75008 Paris Ile de France 75008",
    "addr:housenumber":"33",
    "addr:postcode":"75008;75008",
    "addr:street":"Rue De Miromesnil",
    "iso:country":"FR",
    "sg:address":"33, Rue de Miromesnil, 75008 Paris",
    "sg:orig_category":"Non-Classified Establishments",
    "sg:phone":"+33 1 42 66 11 11",
    "sg:postcode":"75008",
    "sg:province":"Ile de France",
    "wof:name":"Drouot L'hermine Consultants S.a.",
    "wof:placetype":"venue"
},
  "geometry": {"coordinates":[2.315731,48.873402],"type":"Point"}
}