{
  "type": "Feature",
  "properties": {
    "iso:country":"FR",
    "sg:address":"B.P. 11, 71201 Le Creusot C\u00e9dex^^ZA Harfleur, 71200 Le Creusot",
    "sg:city":"Le Creusot",
    "sg:orig_category":"Non-Classified Establishments",
    "sg:phone":"+33 3 85 77 48 30",
    "sg:postcode":"71200",
    "sg:province":"Bourgogne",
    "wof:name":"Sotarpi S.a.",
    "wof:placetype":"venue"
},
  "geometry": {"coordinates":[4.421295,46.806164],"type":"Point"}
}