{
  "type": "Feature",
  "properties": {
    "addr:full":"B.P. 21, 70800 Saint Loup sur Semouse^^126, Av Albert Thomas, 70800 Saint Loup sur Semouse Franche Comt\u00e9 70800",
    "addr:postcode":"70800;70800;70800",
    "addr:street":"B.P. 21;Av Albert Thomas;Franche Comte\u0301",
    "iso:country":"FR",
    "sg:address":"B.P. 21, 70800 Saint Loup sur Semouse^^126, Av Albert Thomas, 70800 Saint Loup sur Semouse",
    "sg:orig_category":"Non-Classified Establishments",
    "sg:phone":"+33 3 84 93 44 44",
    "sg:postcode":"70800",
    "sg:province":"Franche Comt\u00e9",
    "wof:name":"Antoine S.a.",
    "wof:placetype":"venue"
},
  "geometry": {"coordinates":[6.276124,47.884094],"type":"Point"}
}