{
  "type": "Feature",
  "properties": {
    "iso:country":"FR",
    "sg:address":"9, Rte de Froncles, 52270 Doulaincourt Saucourt",
    "sg:orig_category":"Unclassifiable Establishments",
    "sg:phone":"+33 3 25 94 60 35",
    "sg:province":"Champagne",
    "wof:name":"Geyer Jean Bernard S.a.r.l.",
    "wof:placetype":"venue"
},
  "geometry": {"coordinates":[5.201242,48.319946],"type":"Point"}
}