{
  "type": "Feature",
  "properties": {
    "iso:country":"FR",
    "sg:address":"64, Rue Nieuport, 93700 Drancy",
    "sg:orig_category":"Non-Classified Establishments",
    "sg:phone":"+33 1 48 31 54 18",
    "sg:postcode":"93700",
    "sg:province":"Ile de France",
    "wof:name":"C.a.t.e.p. S.a. - Chaudronnerie A\u00e9ronautique T\u00f4lerie Electronique D",
    "wof:placetype":"venue"
},
  "geometry": {"coordinates":[2.44048,48.916859],"type":"Point"}
}