{
  "type": "Feature",
  "properties": {
    "addr:full":"98, Rue Michel Carr\u00e9, 95100 Argenteuil Ile de France 95100",
    "addr:housenumber":"98",
    "addr:postcode":"95100;ile;95100",
    "addr:street":"Rue Michel Carre\u0301;France",
    "iso:country":"FR",
    "sg:address":"98, Rue Michel Carr\u00e9, 95100 Argenteuil",
    "sg:orig_category":"Non-Classified Establishments",
    "sg:phone":"+33 1 39 61 55 38",
    "sg:postcode":"95100",
    "sg:province":"Ile de France",
    "wof:name":"A.e.g. - S.a.r.l. - Anciens Etablissemnts Gillet",
    "wof:placetype":"venue"
},
  "geometry": {"coordinates":[2.233771,48.932755],"type":"Point"}
}