{
  "type": "Feature",
  "properties": {
    "addr:full":"B.P. 50065, 57972 Yutz C\u00e9dex^^2, Rue Cl\u00e9ment Ader - ZI Actip\u00f4le, 57970 Yutz Midi Pyr\u00e9n\u00e9es",
    "addr:housenumber":"57972",
    "addr:postcode":"57970",
    "addr:street":"Rue Cle\u0301Ment Ader Zi Actipo\u0302Le",
    "iso:country":"FR",
    "sg:address":"B.P. 50065, 57972 Yutz C\u00e9dex^^2, Rue Cl\u00e9ment Ader - ZI Actip\u00f4le, 57970 Yutz",
    "sg:orig_category":"Non-Classified Establishments",
    "sg:phone":"+33 3 82 86 00 16",
    "sg:province":"Midi Pyr\u00e9n\u00e9es",
    "wof:name":"J.l.s. Informatique",
    "wof:placetype":"venue"
},
  "geometry": {"coordinates":[6.1873,49.35741],"type":"Point"}
}