{
  "type": "Feature",
  "properties": {
    "addr:full":"Rue Lavoisier - ZI Sainte Agathe Florange Lorraine 57190",
    "addr:housenumber":"florange",
    "addr:postcode":"57190",
    "addr:street":"Rue Lavoisier Zi;Lorraine",
    "iso:country":"FR",
    "sg:address":"Rue Lavoisier - ZI Sainte Agathe",
    "sg:city":"Florange",
    "sg:orig_category":"Unclassifiable Establishments",
    "sg:phone":"+33 3 82 59 32 00",
    "sg:postcode":"57190",
    "sg:province":"Lorraine",
    "wof:name":"Synergie S.a.",
    "wof:placetype":"venue"
},
  "geometry": {"coordinates":[6.12272,49.327431],"type":"Point"}
}