{
  "type": "Feature",
  "properties": {
    "iso:country":"FR",
    "sg:address":"15, Rue du Sabot, 22440 Ploufragan",
    "sg:city":"Ploufragan",
    "sg:orig_category":"Unclassifiable Establishments",
    "sg:phone":"+33 2 96 01 37 96",
    "sg:postcode":"22440",
    "sg:province":"Bretagne",
    "wof:name":"Ad Tech S.a.r.l.",
    "wof:placetype":"venue"
},
  "geometry": {"coordinates":[-2.796525,48.481796],"type":"Point"}
}