{
  "type": "Feature",
  "properties": {
    "iso:country":"FR",
    "sg:address":"17, Av. Pierre Renaudel, 83400 Hy\u00e8res",
    "sg:orig_category":"Non-Classified Establishments",
    "sg:phone":"+33 4 94 57 71 95",
    "sg:province":"Languedoc-Roussillon",
    "wof:name":"Man Clean",
    "wof:placetype":"venue"
},
  "geometry": {"coordinates":[6.126348,43.109238],"type":"Point"}
}