{
  "type": "Feature",
  "properties": {
    "iso:country":"FR",
    "sg:address":"La Marquisie 19100 Brive La Gaillarde",
    "sg:classifiers":[
        {
            "category":"Manufacturing",
            "subcategory":"Rubber & Plastics",
            "type":"Manufacturing & Wholesale Goods"
        }
    ],
    "sg:phone":"+33 5 55 86 43 86",
    "sg:province":"Limousin",
    "wof:name":"Socap",
    "wof:placetype":"venue"
},
  "geometry": {"coordinates":[1.491006,45.157646],"type":"Point"}
}