{
  "type": "Feature",
  "properties": {
    "addr:full":"7, Rue des Chemineaux, 41130 Ch\u00e2tillon sur Cher Ch\u00e2tillon-sur-Cher Centre 41130",
    "addr:housenumber":"7",
    "addr:postcode":"41130;41130",
    "addr:street":"Rue Des Chemineaux",
    "iso:country":"FR",
    "sg:address":"7, Rue des Chemineaux, 41130 Ch\u00e2tillon sur Cher",
    "sg:city":"Ch\u00e2tillon-sur-Cher",
    "sg:orig_category":"Unclassifiable Establishments",
    "sg:phone":"+33 2 54 71 25 50",
    "sg:postcode":"41130",
    "sg:province":"Centre",
    "wof:name":"Transports Bailly Guemon S.a.",
    "wof:placetype":"venue"
},
  "geometry": {"coordinates":[1.50956,47.29871],"type":"Point"}
}