{
  "type": "Feature",
  "properties": {
    "iso:country":"FR",
    "sg:address":"16",
    "sg:city":"Haute BP 1219 cedex 29102 Quimper",
    "sg:classifiers":[
        {
            "category":"Home & Garden",
            "subcategory":"Building Materials",
            "type":"Retail Goods"
        }
    ],
    "sg:phone":"+33 2 98 90 09 36",
    "sg:province":"Bretagne",
    "sg:tags":[
        "glass",
        "household",
        "ceramic",
        "wood",
        "furniture"
    ],
    "wof:name":"Faienceries De Quimper",
    "wof:placetype":"venue"
},
  "geometry": {"coordinates":[-4.09986,47.99593],"type":"Point"}
}