{
  "type": "Feature",
  "properties": {
    "addr:full":"47bis, Rue de la R\u00e9publique, 76490 Caudebec en Caux Haute Normandie",
    "addr:housenumber":"47bis",
    "addr:postcode":"76490",
    "addr:street":"Rue De La Re\u0301Publique;Haute Normandie",
    "iso:country":"FR",
    "sg:address":"47bis, Rue de la R\u00e9publique, 76490 Caudebec en Caux",
    "sg:orig_category":"Unclassifiable Establishments",
    "sg:phone":"+33 2 35 95 98 20",
    "sg:province":"Haute Normandie",
    "wof:name":"S.f.e.b. S.a. - Soci\u00e9t\u00e9 Fran\u00e7aise D'equipements De Bureau",
    "wof:placetype":"venue"
},
  "geometry": {"coordinates":[0.723742,49.530201],"type":"Point"}
}