{
  "type": "Feature",
  "properties": {
    "iso:country":"FR",
    "sg:address":"100 Grand Rue 68470 Fellering",
    "sg:city":"Fellering",
    "sg:classifiers":[
        {
            "category":"Manufacturing",
            "subcategory":"Rubber & Plastics",
            "type":"Manufacturing & Wholesale Goods"
        }
    ],
    "sg:phone":"+33 3 89 38 27 28",
    "sg:postcode":"68470",
    "sg:province":"Alsace",
    "wof:name":"Striebel & John France Sarl",
    "wof:placetype":"venue"
},
  "geometry": {"coordinates":[6.980466,47.899227],"type":"Point"}
}