{
  "type": "Feature",
  "properties": {
    "addr:full":"28, Rue Thierry Mieg, 90000 Belfort Franche Comt\u00e9",
    "addr:housenumber":"28",
    "addr:postcode":"90000",
    "addr:street":"Rue Thierry Mieg;Franche Comte\u0301",
    "iso:country":"FR",
    "sg:address":"28, Rue Thierry Mieg, 90000 Belfort",
    "sg:orig_category":"Unclassifiable Establishments",
    "sg:phone":"+33 3 84 54 50 00",
    "sg:province":"Franche Comt\u00e9",
    "wof:name":"Nipson S.a.",
    "wof:placetype":"venue"
},
  "geometry": {"coordinates":[6.84456,47.6418],"type":"Point"}
}