{
  "type": "Feature",
  "properties": {
    "iso:country":"FR",
    "sg:address":"81, Rue du Haut du Pin, 88470 Saint Michel sur Meurthe",
    "sg:orig_category":"Unclassifiable Establishments",
    "sg:phone":"+33 3 29 53 55 55",
    "sg:province":"Lorraine",
    "wof:name":"Vins Marchal S.a.",
    "wof:placetype":"venue"
},
  "geometry": {"coordinates":[6.88869,48.316544],"type":"Point"}
}