{
  "type": "Feature",
  "properties": {
    "iso:country":"FR",
    "sg:address":"B.P. 577",
    "sg:city":"V\u00e9nissieux C\u00e9dex",
    "sg:orig_category":"Non-Classified Establishments",
    "sg:phone":"+33 4 72 50 06 78",
    "sg:postcode":"69637",
    "sg:province":"Haute Normandie",
    "wof:name":"S.r.m. S.a. - Soci\u00e9t\u00e9 Rhodanienne De M\u00e9canographie S.a.",
    "wof:placetype":"venue"
},
  "geometry": {"coordinates":[4.88381,45.696381],"type":"Point"}
}