{
  "type": "Feature",
  "properties": {
    "addr:full":"7 All De La Cotonni\u00e8re 76570 Pavilly Haute Normandie",
    "addr:housenumber":"7",
    "addr:postcode":"76570",
    "addr:street":"All De La Cotonnie\u0300Re;Haute Normandie",
    "iso:country":"FR",
    "sg:address":"7 All De La Cotonni\u00e8re 76570 Pavilly",
    "sg:classifiers":[
        {
            "category":"Professional",
            "type":"Services"
        }
    ],
    "sg:phone":"+33 2 35 92 35 75",
    "sg:province":"Haute Normandie",
    "sg:tags":[
        "transport",
        "road"
    ],
    "wof:name":"Boivin Sa",
    "wof:placetype":"venue"
},
  "geometry": {"coordinates":[0.95579,49.562038],"type":"Point"}
}