{
  "type": "Feature",
  "properties": {
    "addr:full":"74, Rue Rivay, 92300 Levallois Perret Ile de France 92300",
    "addr:housenumber":"74",
    "addr:postcode":"92300;ile;92300",
    "addr:street":"Rue Rivay;France",
    "iso:country":"FR",
    "sg:address":"74, Rue Rivay, 92300 Levallois Perret",
    "sg:orig_category":"Non-Classified Establishments",
    "sg:phone":"+33 1 47 37 13 86",
    "sg:postcode":"92300",
    "sg:province":"Ile de France",
    "wof:name":"Dubois Fr\u00e8res S.a.r.l.",
    "wof:placetype":"venue"
},
  "geometry": {"coordinates":[2.287239,48.897293],"type":"Point"}
}