{
  "type": "Feature",
  "properties": {
    "addr:full":"Za Du Grand Chemin 50540 Isigny Le Buat Isigny-le-Buat Basse Normandie 50540",
    "addr:postcode":"50540;50540",
    "addr:street":"Za Du Grand Chemin;Isigny-Le-Buat Basse",
    "iso:country":"FR",
    "sg:address":"Za Du Grand Chemin 50540 Isigny Le Buat",
    "sg:city":"Isigny-le-Buat",
    "sg:classifiers":[
        {
            "category":"Social Services",
            "subcategory":"Job Training",
            "type":"Services"
        }
    ],
    "sg:phone":"+33 2 33 48 09 28",
    "sg:postcode":"50540",
    "sg:province":"Basse Normandie",
    "sg:tags":[
        "metallurgy",
        "metal",
        "processing",
        "-",
        "metalworking",
        "machine",
        "engineering",
        "mechanical"
    ],
    "wof:name":"Mecanique Generale De Precision D Isigny",
    "wof:placetype":"venue"
},
  "geometry": {"coordinates":[-1.172694,48.619751],"type":"Point"}
}