{
  "type": "Feature",
  "properties": {
    "iso:country":"FR",
    "sg:address":"6 rue du Chapelier 95700 Roissy en France",
    "sg:classifiers":[
        {
            "category":"Transit Center",
            "subcategory":"Passenger",
            "type":"Transportation"
        }
    ],
    "sg:phone":"+33 1 48 16 85 00",
    "sg:province":"Ile de France",
    "sg:tags":[
        "route",
        "planning",
        "tour"
    ],
    "wof:name":"Panalpina France Transports",
    "wof:placetype":"venue"
},
  "geometry": {"coordinates":[2.52393,48.996052],"type":"Point"}
}