{
  "type": "Feature",
  "properties": {
    "addr:full":"Mas St Michel 66000 Perpignan Languedoc-Roussillon 66000",
    "addr:postcode":"66000;66000",
    "addr:street":"St Michel",
    "iso:country":"FR",
    "sg:address":"Mas St Michel 66000 Perpignan",
    "sg:classifiers":[
        {
            "category":"Wholesale",
            "subcategory":"Wine & Distilled Alcoholic Beverages",
            "type":"Manufacturing & Wholesale Goods"
        }
    ],
    "sg:phone":"+33 4 68 56 72 38",
    "sg:postcode":"66000",
    "sg:province":"Languedoc-Roussillon",
    "sg:tags":[
        "french"
    ],
    "wof:name":"Scea Du Domaine Sarda Malet",
    "wof:placetype":"venue"
},
  "geometry": {"coordinates":[2.8968,42.700073],"type":"Point"}
}