{
  "type": "Feature",
  "properties": {
    "iso:country":"FR",
    "sg:address":"1 Rue D'Alembert Zi Sud 22000 St Brieuc",
    "sg:city":"Saint-Brieuc",
    "sg:classifiers":[
        {
            "category":"Shopping",
            "type":"Retail Goods"
        }
    ],
    "sg:phone":"+33 2 96 68 05 05",
    "sg:postcode":"22000",
    "sg:province":"Bretagne",
    "sg:tags":[
        "metallurgy",
        "finished",
        "-",
        "metalworking",
        "metallic"
    ],
    "wof:name":"Roulement Service",
    "wof:placetype":"venue"
},
  "geometry": {"coordinates":[-2.741763,48.502827],"type":"Point"}
}