{
  "type": "Feature",
  "properties": {
    "addr:full":"3 Avenue James De Rothschild 77164 Ferrieres En Brie Ile de France",
    "addr:housenumber":"3",
    "addr:postcode":"77164",
    "addr:street":"Avenue James De Rothschild",
    "iso:country":"FR",
    "sg:address":"3 Avenue James De Rothschild 77164 Ferrieres En Brie",
    "sg:classifiers":[
        {
            "category":"Wholesale",
            "subcategory":"Machinery & Supplies",
            "type":"Manufacturing & Wholesale Goods"
        }
    ],
    "sg:phone":"+33 1 64 76 89 90",
    "sg:province":"Ile de France",
    "sg:tags":[
        "equipment",
        "precision"
    ],
    "wof:name":"Pesage Vial Jcl",
    "wof:placetype":"venue"
},
  "geometry": {"coordinates":[2.704828,48.826473],"type":"Point"}
}