{
  "type": "Feature",
  "properties": {
    "iso:country":"FR",
    "sg:address":"20/22 rue Charles Paradinas 92110 Clichy",
    "sg:orig_category":"Finite Element Analyses",
    "sg:phone":"+33 1 41 06 95 95",
    "sg:postcode":"92110",
    "sg:province":"Ile de France",
    "wof:name":"Laboratoires Simon France Sa",
    "wof:placetype":"venue"
},
  "geometry": {"coordinates":[2.306067,48.904903],"type":"Point"}
}