{
  "type": "Feature",
  "properties": {
    "addr:full":"8 pl du March\u00e9; Wissembourg; 67160 Wissembourg Alsace 67160",
    "addr:housenumber":"8",
    "addr:postcode":"67160;67160",
    "addr:street":"Pl Du Marche\u0301",
    "iso:country":"FR",
    "sg:address":"8 pl du March\u00e9; Wissembourg; 67160",
    "sg:city":"Wissembourg",
    "sg:classifiers":[
        {
            "category":"Banks & Credit Unions",
            "subcategory":"Bank",
            "type":"Services"
        }
    ],
    "sg:phone":"+33 3 88 54 89 54",
    "sg:postcode":"67160",
    "sg:province":"Alsace",
    "wof:name":"Cr\u00e9dit Industriel D'alsace, Et De Lorraine Sa",
    "wof:placetype":"venue"
},
  "geometry": {"coordinates":[7.944043,49.034904],"type":"Point"}
}