{
  "type": "Feature",
  "properties": {
    "iso:country":"FR",
    "sg:address":"2 Rue Emile Sehet 95150 Taverny",
    "sg:classifiers":[
        {
            "category":"Wholesale",
            "subcategory":"Chemicals & Plastics",
            "type":"Manufacturing & Wholesale Goods"
        }
    ],
    "sg:phone":"+33 1 39 60 32 82",
    "sg:postcode":"95150",
    "sg:province":"Ile de France",
    "sg:tags":[
        "pharmaceutical",
        "cardboard",
        "-",
        "fini",
        "paper",
        "chemistry",
        "by-product"
    ],
    "wof:name":"Secobat",
    "wof:placetype":"venue"
},
  "geometry": {"coordinates":[2.1915,49.027996],"type":"Point"}
}