{
  "type": "Feature",
  "properties": {
    "addr:full":"18 Rue Coquill\u00e8re 75001 Paris Ile de France 75001",
    "addr:housenumber":"18",
    "addr:postcode":"75001;75001",
    "addr:street":"Rue Coquille\u0300Re",
    "iso:country":"FR",
    "sg:address":"18 Rue Coquill\u00e8re 75001 Paris",
    "sg:classifiers":[
        {
            "category":"Professional",
            "subcategory":"Engineering",
            "type":"Services"
        }
    ],
    "sg:phone":"+33 1 42 36 53 13",
    "sg:postcode":"75001",
    "sg:province":"Ile de France",
    "sg:tags":[
        "machine",
        "-",
        "mechanical"
    ],
    "wof:name":"Dehillerin Sa",
    "wof:placetype":"venue"
},
  "geometry": {"coordinates":[2.342627,48.863697],"type":"Point"}
}