{
  "type": "Feature",
  "properties": {
    "iso:country":"FR",
    "sg:address":"18-22 Av Edouard Herriot 92350 Le Plessis Robinson",
    "sg:classifiers":[
        {
            "category":"Professional",
            "subcategory":"Advertising",
            "type":"Services"
        }
    ],
    "sg:phone":"+33 1 41 28 01 01",
    "sg:postcode":"92350",
    "sg:province":"Ile de France",
    "sg:tags":[
        "communication",
        "medium"
    ],
    "wof:name":"Crystal Plv",
    "wof:placetype":"venue"
},
  "geometry": {"coordinates":[2.25248,48.782349],"type":"Point"}
}