{
  "type": "Feature",
  "properties": {
    "addr:full":"7 Avenue Gen De Gaulle Ales Languedoc-Roussillon 30100",
    "addr:housenumber":"7",
    "addr:postcode":"30100",
    "addr:street":"Avenue Gen De Gaulle",
    "iso:country":"FR",
    "sg:address":"7 Avenue Gen De Gaulle",
    "sg:city":"Ales",
    "sg:classifiers":[
        {
            "category":"Banks & Credit Unions",
            "subcategory":"Financial Services",
            "type":"Services"
        }
    ],
    "sg:phone":"+33 4 66 30 28 28",
    "sg:postcode":"30100",
    "sg:province":"Languedoc-Roussillon",
    "sg:tags":[
        "banking",
        "finance",
        "insurance"
    ],
    "wof:name":"La Mondiale",
    "wof:placetype":"venue"
},
  "geometry": {"coordinates":[4.081122,44.126869],"type":"Point"}
}