{
  "type": "Feature",
  "properties": {
    "addr:full":"80 Impasse Thomas Edison 53100 Mayenne Pays de Loire 53100",
    "addr:housenumber":"80",
    "addr:postcode":"53100 mayenne;53100",
    "addr:street":"Impasse Thomas Edison",
    "iso:country":"FR",
    "sg:address":"80 Impasse Thomas Edison 53100 Mayenne",
    "sg:classifiers":[
        {
            "category":"Shopping",
            "type":"Retail Goods"
        }
    ],
    "sg:phone":"+33 2 43 00 08 78",
    "sg:postcode":"53100",
    "sg:province":"Pays de Loire",
    "sg:tags":[
        "metallurgy",
        "finished",
        "-",
        "metalworking",
        "metallic"
    ],
    "wof:name":"Atelier Des Techniciens Moulistes Sa",
    "wof:placetype":"venue"
},
  "geometry": {"coordinates":[-0.626216,48.283737],"type":"Point"}
}