{
  "type": "Feature",
  "properties": {
    "addr:full":"8, Av. d'Avignon, 84300 Cavaillon Provence-Alpes-C\u00f4te d'Azur",
    "addr:postcode":"84300",
    "addr:street":"Av. D'Avignon",
    "iso:country":"FR",
    "sg:address":"8, Av. d'Avignon, 84300 Cavaillon",
    "sg:orig_category":"Unclassifiable Establishments",
    "sg:phone":"+33 4 90 06 40 00",
    "sg:province":"Provence-Alpes-C\u00f4te d'Azur",
    "wof:name":"Provence Bureau S.a.",
    "wof:placetype":"venue"
},
  "geometry": {"coordinates":[5.04855,43.84869],"type":"Point"}
}