{
  "type": "Feature",
  "properties": {
    "addr:full":"ZI du Pr\u00e9 de l'Orme Crolles Rhone-Alpes 38920",
    "addr:postcode":"38920",
    "addr:street":"Zi Du Pre\u0301 De L'Orme;Rhone-Alpes",
    "iso:country":"FR",
    "sg:address":"ZI du Pr\u00e9 de l'Orme",
    "sg:city":"Crolles",
    "sg:orig_category":"Unclassifiable Establishments",
    "sg:phone":"+33 4 76 08 96 97",
    "sg:postcode":"38920",
    "sg:province":"Rhone-Alpes",
    "wof:name":"S.g.e. S.a.r.l. - Soci\u00e9t\u00e9 Grenobloise D'equipement",
    "wof:placetype":"venue"
},
  "geometry": {"coordinates":[5.888528,45.269714],"type":"Point"}
}