{
  "type": "Feature",
  "properties": {
    "addr:full":"153 Rue Verdun 60170 Carlepont Picardie 60170",
    "addr:housenumber":"153",
    "addr:postcode":"60170;60170",
    "addr:street":"Rue Verdun;Picardie",
    "iso:country":"FR",
    "sg:address":"153 Rue Verdun 60170 Carlepont",
    "sg:classifiers":[
        {
            "category":"Professional",
            "subcategory":"Engineering",
            "type":"Services"
        }
    ],
    "sg:phone":"+33 3 44 75 81 11",
    "sg:postcode":"60170",
    "sg:province":"Picardie",
    "sg:tags":[
        "machine",
        "-",
        "mechanical"
    ],
    "wof:name":"Prodel Automation",
    "wof:placetype":"venue"
},
  "geometry": {"coordinates":[3.034752,49.511551],"type":"Point"}
}