{
  "type": "Feature",
  "properties": {
    "addr:full":"B.P. 106 Villefranche sur Sa\u00f4ne C\u00e9dex Rhone-Alpes 69654",
    "addr:housenumber":"b.p. 106",
    "addr:postcode":"69654",
    "addr:street":"Villefranche;Rhone-Alpes",
    "iso:country":"FR",
    "sg:address":"B.P. 106",
    "sg:city":"Villefranche sur Sa\u00f4ne C\u00e9dex",
    "sg:orig_category":"Non-Classified Establishments",
    "sg:phone":"+33 4 74 09 13 22",
    "sg:postcode":"69654",
    "sg:province":"Rhone-Alpes",
    "wof:name":"Interplastiques Industries S.a.r.l",
    "wof:placetype":"venue"
},
  "geometry": {"coordinates":[4.71875,45.989868],"type":"Point"}
}