{
  "type": "Feature",
  "properties": {
    "addr:full":"All\u00e9e Moulin Pinard - Parc Uzurat Limoges Limousin 87100",
    "addr:postcode":"87100",
    "addr:street":"Alle\u0301E Moulin Pinard Parc Uzurat",
    "iso:country":"FR",
    "sg:address":"All\u00e9e Moulin Pinard - Parc Uzurat",
    "sg:city":"Limoges",
    "sg:orig_category":"Non-Classified Establishments",
    "sg:phone":"+33 5 55 37 00 34",
    "sg:postcode":"87100",
    "sg:province":"Limousin",
    "wof:name":"Ccmx S.a.",
    "wof:placetype":"venue"
},
  "geometry": {"coordinates":[1.27007,45.862888],"type":"Point"}
}