{
  "type": "Feature",
  "properties": {
    "addr:full":"49 Rue Doc Rollet 69100 Villeurbanne Rhone-Alpes 69100",
    "addr:housenumber":"49",
    "addr:postcode":"69100;69100",
    "addr:street":"Rue Doc Rollet",
    "iso:country":"FR",
    "sg:address":"49 Rue Doc Rollet 69100 Villeurbanne",
    "sg:classifiers":[
        {
            "category":"Shopping",
            "subcategory":"Crafts & Fabrics",
            "type":"Retail Goods"
        }
    ],
    "sg:phone":"+33 4 78 84 13 22",
    "sg:postcode":"69100",
    "sg:province":"Rhone-Alpes",
    "sg:tags":[
        "textile",
        "linen",
        "clothing"
    ],
    "wof:name":"Mdc Print",
    "wof:placetype":"venue"
},
  "geometry": {"coordinates":[4.884586,45.76479],"type":"Point"}
}