{
  "type": "Feature",
  "properties": {
    "iso:country":"FR",
    "sg:address":"Quartier Mazorel",
    "sg:city":"Crest",
    "sg:orig_category":"Non-Classified Establishments",
    "sg:phone":"+33 4 75 21 53 68",
    "sg:postcode":"26400",
    "sg:province":"Rhone-Alpes",
    "wof:name":"Murat S.a.",
    "wof:placetype":"venue"
},
  "geometry": {"coordinates":[4.998188,44.725254],"type":"Point"}
}