{
  "type": "Feature",
  "properties": {
    "iso:country":"FR",
    "sg:address":"31 Rue De Courcelles 75008 Paris",
    "sg:classifiers":[
        {
            "category":"Banks & Credit Unions",
            "subcategory":"Financial Services",
            "type":"Services"
        }
    ],
    "sg:phone":"+33 1 44 35 31 00",
    "sg:postcode":"75008",
    "sg:province":"Ile de France",
    "sg:tags":[
        "banking",
        "finance",
        "insurance"
    ],
    "wof:name":"Ccr Caisse Centrale De Reassurance",
    "wof:placetype":"venue"
},
  "geometry": {"coordinates":[2.309104,48.874821],"type":"Point"}
}