{
  "type": "Feature",
  "properties": {
    "addr:full":"274, Chemin Ren\u00e9 Pouchol, 06670 Levens Franche Comt\u00e9",
    "addr:housenumber":"274",
    "addr:postcode":"06670",
    "addr:street":"Chemin Rene\u0301 Pouchol;Franche Comte\u0301",
    "iso:country":"FR",
    "sg:address":"274, Chemin Ren\u00e9 Pouchol, 06670 Levens",
    "sg:orig_category":"Non-Classified Establishments",
    "sg:phone":"+33 4 93 79 82 96",
    "sg:province":"Franche Comt\u00e9",
    "wof:name":"Eric Soulier Photographie",
    "wof:placetype":"venue"
},
  "geometry": {"coordinates":[7.233297,43.855091],"type":"Point"}
}