{
  "type": "Feature",
  "properties": {
    "addr:full":"4 rue des Freres Lumiere 69680 Chassieu Rhone-Alpes 69680",
    "addr:housenumber":"4",
    "addr:postcode":"69680;69680",
    "addr:street":"Rue Des Freres",
    "iso:country":"FR",
    "sg:address":"4 rue des Freres Lumiere 69680 Chassieu",
    "sg:classifiers":[
        {
            "category":"Airport",
            "type":"Transportation"
        }
    ],
    "sg:phone":"+33 4 72 47 42 80",
    "sg:postcode":"69680",
    "sg:province":"Rhone-Alpes",
    "sg:tags":[
        "air-freight",
        "forwarders"
    ],
    "wof:name":"Confreight Air Sa",
    "wof:placetype":"venue"
},
  "geometry": {"coordinates":[4.961712,45.730591],"type":"Point"}
}