{
  "type": "Feature",
  "properties": {
    "addr:full":"4, Rue de la Sabli\u00e8re, 92634 Gennevilliers C\u00e9dex Ile-de-France",
    "addr:housenumber":"4",
    "addr:postcode":"92634",
    "addr:street":"Rue De La Sablie\u0300Re",
    "iso:country":"FR",
    "sg:address":"4, Rue de la Sabli\u00e8re, 92634 Gennevilliers C\u00e9dex",
    "sg:orig_category":"Non-Classified Establishments",
    "sg:phone":"+33 1 41 11 57 40",
    "sg:province":"Ile-de-France",
    "wof:name":"Tranfesa France S.a.r.l.",
    "wof:placetype":"venue"
},
  "geometry": {"coordinates":[2.30617,48.917343],"type":"Point"}
}