{
  "type": "Feature",
  "properties": {
    "addr:full":"6, Bd du 11 Novembre, 42380 Saint Bonnet le Ch\u00e2teau Rhone-Alpes 42380",
    "addr:housenumber":"6",
    "addr:postcode":"42380;42380",
    "addr:street":"Bd Du 11 Novembre",
    "iso:country":"FR",
    "sg:address":"6, Bd du 11 Novembre, 42380 Saint Bonnet le Ch\u00e2teau",
    "sg:orig_category":"Unclassifiable Establishments",
    "sg:phone":"+33 4 77 50 05 78",
    "sg:postcode":"42380",
    "sg:province":"Rhone-Alpes",
    "wof:name":"Tissages Chataignier S.a.r.l.",
    "wof:placetype":"venue"
},
  "geometry": {"coordinates":[4.0632,45.42205],"type":"Point"}
}