{
  "type": "Feature",
  "properties": {
    "iso:country":"FR",
    "sg:address":"Rue Thorez Zi Les Estaches 62730 Les Attaques",
    "sg:classifiers":[
        {
            "category":"Manufacturing",
            "subcategory":"Printing",
            "type":"Manufacturing & Wholesale Goods"
        }
    ],
    "sg:phone":"+33 3 21 82 19 22",
    "sg:province":"Nord Pas-de-Calais",
    "sg:tags":[
        "publishing"
    ],
    "wof:name":"Offset Service Sarl",
    "wof:placetype":"venue"
},
  "geometry": {"coordinates":[1.956175,50.949181],"type":"Point"}
}