{
  "type": "Feature",
  "properties": {
    "addr:full":"45, Rue des Chataigniers, 45770 Saran Saran Centre 45770",
    "addr:housenumber":"45",
    "addr:postcode":"45770;45770",
    "addr:street":"Rue Des Chataigniers",
    "iso:country":"FR",
    "sg:address":"45, Rue des Chataigniers, 45770 Saran",
    "sg:city":"Saran",
    "sg:orig_category":"Non-Classified Establishments",
    "sg:phone":"+33 2 38 74 88 44",
    "sg:postcode":"45770",
    "sg:province":"Centre",
    "wof:name":"C.d.c. Packaging Group S.a.r.l.",
    "wof:placetype":"venue"
},
  "geometry": {"coordinates":[1.843164,47.951702],"type":"Point"}
}