{
  "type": "Feature",
  "properties": {
    "addr:full":"66, Rue Jean Baptiste Colbert, 10600 La Chapelle Saint Luc Champagne 10600",
    "addr:housenumber":"66",
    "addr:postcode":"10600;10600",
    "addr:street":"Rue Jean Baptiste Colbert;Champagne",
    "iso:country":"FR",
    "sg:address":"66, Rue Jean Baptiste Colbert, 10600 La Chapelle Saint Luc",
    "sg:orig_category":"Non-Classified Establishments",
    "sg:phone":"+33 3 25 79 82 82",
    "sg:postcode":"10600",
    "sg:province":"Champagne",
    "wof:name":"Aubnet S.a. - Soci\u00e9t\u00e9 Auboise De Nettoyage",
    "wof:placetype":"venue"
},
  "geometry": {"coordinates":[4.024213,48.32019],"type":"Point"}
}