{
  "type": "Feature",
  "properties": {
    "addr:full":"10 F, Rue de la Productique, 42000 Saint Etienne Rhone-Alpes 42000",
    "addr:housenumber":"10 f",
    "addr:postcode":"42000;42000",
    "addr:street":"Rue De La Productique",
    "iso:country":"FR",
    "sg:address":"10 F, Rue de la Productique, 42000 Saint Etienne",
    "sg:orig_category":"Unclassifiable Establishments",
    "sg:phone":"+33 4 77 93 68 82",
    "sg:postcode":"42000",
    "sg:province":"Rhone-Alpes",
    "wof:name":"Secmhy V\u00e9rins S.a.r.l.",
    "wof:placetype":"venue"
},
  "geometry": {"coordinates":[4.393981,45.456463],"type":"Point"}
}