{
  "type": "Feature",
  "properties": {
    "iso:country":"FR",
    "sg:address":"51 avenue du Mar\u00e9chal Joffre 92000 Nanterre",
    "sg:classifiers":[
        {
            "category":"Manufacturing",
            "subcategory":"Textiles",
            "type":"Manufacturing & Wholesale Goods"
        }
    ],
    "sg:phone":"+33 1 40 97 03 75",
    "sg:province":"Ile de France",
    "sg:tags":[
        "import"
    ],
    "wof:name":"Zoneco France Sa",
    "wof:placetype":"venue"
},
  "geometry": {"coordinates":[2.194679,48.884838],"type":"Point"}
}