{
  "type": "Feature",
  "properties": {
    "addr:full":"4, Rue Jean Lemoine, 94000 Cr\u00e9teil Ile de France",
    "addr:housenumber":"4",
    "addr:postcode":"94000",
    "addr:street":"Rue Jean Lemoine",
    "iso:country":"FR",
    "sg:address":"4, Rue Jean Lemoine, 94000 Cr\u00e9teil",
    "sg:orig_category":"Unclassifiable Establishments",
    "sg:phone":"+33 1 48 98 90 90",
    "sg:province":"Ile de France",
    "wof:name":"Impra S.a.",
    "wof:placetype":"venue"
},
  "geometry": {"coordinates":[2.438582,48.792164],"type":"Point"}
}