{
  "type": "Feature",
  "properties": {
    "addr:full":"3, Grand'Rue, 86000 Poitiers Poitou-Charentes",
    "addr:housenumber":"3",
    "addr:postcode":"86000",
    "addr:street":"Grand'Rue",
    "iso:country":"FR",
    "sg:address":"3, Grand'Rue, 86000 Poitiers",
    "sg:orig_category":"Unclassifiable Establishments",
    "sg:phone":"+33 5 49 50 54 74",
    "sg:province":"Poitou-Charentes",
    "wof:name":"Cabinet Jean-pierre Thomas Communication S.a.r.l.",
    "wof:placetype":"venue"
},
  "geometry": {"coordinates":[0.340998,46.58844],"type":"Point"}
}