{
  "type": "Feature",
  "properties": {
    "iso:country":"FR",
    "sg:address":"La Grage des Bois 01370 Meillonnas",
    "sg:classifiers":[
        {
            "category":"Education",
            "subcategory":"Music School",
            "type":"Public Place"
        }
    ],
    "sg:phone":"+33 4 74 42 10 30",
    "sg:postcode":"01370",
    "sg:province":"Rhone-Alpes",
    "sg:tags":[
        "breeding",
        "cattle"
    ],
    "wof:name":"Bovi Coop",
    "wof:placetype":"venue"
},
  "geometry": {"coordinates":[5.315355,46.248123],"type":"Point"}
}