{
  "type": "Feature",
  "properties": {
    "iso:country":"FR",
    "sg:address":"B.P. 8, 62170 Ecuires^^Rte de Paris - ZI de Montreuil, 62170 Ecuires",
    "sg:orig_category":"Non-Classified Establishments",
    "sg:phone":"+33 3 21 06 10 37",
    "sg:province":"Nord Pas-de-Calais",
    "wof:name":"Lo Bello Jean S.a.",
    "wof:placetype":"venue"
},
  "geometry": {"coordinates":[1.73439,50.384281],"type":"Point"}
}