{
  "type": "Feature",
  "properties": {
    "iso:country":"FR",
    "sg:address":"150 Rue Amp\u00e8re 36000 Chateauroux",
    "sg:city":"Ch\u00e2teauroux",
    "sg:classifiers":[
        {
            "category":"Manufacturing",
            "subcategory":"Glass & Minerals",
            "type":"Manufacturing & Wholesale Goods"
        }
    ],
    "sg:phone":"+33 2 54 61 40 50",
    "sg:postcode":"36000",
    "sg:province":"Centre",
    "sg:tags":[
        "building",
        "material"
    ],
    "wof:name":"Lariviere Sa",
    "wof:placetype":"venue"
},
  "geometry": {"coordinates":[1.721291,46.8134],"type":"Point"}
}