{
  "type": "Feature",
  "properties": {
    "iso:country":"FR",
    "sg:address":"ZI du Haut Cre\u00ef",
    "sg:city":"Menton",
    "sg:orig_category":"Unclassifiable Establishments",
    "sg:phone":"+33 4 93 35 61 15",
    "sg:postcode":"06500",
    "sg:province":"Pays de Loire",
    "wof:name":"Les Mat\u00e9riaux R\u00e9unies S.a.",
    "wof:placetype":"venue"
},
  "geometry": {"coordinates":[7.50444,43.774586],"type":"Point"}
}