{
  "type": "Feature",
  "properties": {
    "addr:full":"69 Grande Rue 69600 Oullins Rhone-Alpes 69600",
    "addr:housenumber":"69",
    "addr:postcode":"69600;69600",
    "addr:street":"Grande Rue",
    "iso:country":"FR",
    "sg:address":"69 Grande Rue 69600 Oullins",
    "sg:classifiers":[
        {
            "category":"Shopping",
            "subcategory":"Clothing, Apparel, & Fashions",
            "type":"Retail Goods"
        }
    ],
    "sg:phone":"+33 4 78 51 30 91",
    "sg:postcode":"69600",
    "sg:province":"Rhone-Alpes",
    "sg:tags":[
        "textile",
        "accessory",
        "clothing",
        "clothes"
    ],
    "wof:name":"Vetements Charles Sa",
    "wof:placetype":"venue"
},
  "geometry": {"coordinates":[4.806695,45.714306],"type":"Point"}
}