{
  "type": "Feature",
  "properties": {
    "addr:full":"RN 19 Grisy Suisnes Ile de France 77166",
    "addr:postcode":"77166",
    "addr:street":"Rn 19 Grisy Suisnes Ile De France",
    "iso:country":"FR",
    "sg:address":"RN 19",
    "sg:city":"Grisy Suisnes",
    "sg:orig_category":"Unclassifiable Establishments",
    "sg:phone":"+33 1 64 05 90 21",
    "sg:postcode":"77166",
    "sg:province":"Ile de France",
    "wof:name":"Feritec S.a.r.l.",
    "wof:placetype":"venue"
},
  "geometry": {"coordinates":[2.634074,48.652786],"type":"Point"}
}