{
  "type": "Feature",
  "properties": {
    "addr:full":"passage Cauvi 06600 Antibes Languedoc-Roussillon",
    "addr:postcode":"06600",
    "addr:street":"Passage Cauvi",
    "iso:country":"FR",
    "sg:address":"passage Cauvi 06600 Antibes",
    "sg:classifiers":[
        {
            "category":"Professional",
            "subcategory":"Advertising",
            "type":"Services"
        }
    ],
    "sg:phone":"+33 4 93 33 03 65",
    "sg:province":"Languedoc-Roussillon",
    "sg:tags":[
        "articles"
    ],
    "wof:name":"Covico Sarl",
    "wof:placetype":"venue"
},
  "geometry": {"coordinates":[7.116471,43.58466],"type":"Point"}
}