{
  "type": "Feature",
  "properties": {
    "iso:country":"FR",
    "sg:address":"102, Quartier Montplaisir - ZA - Port de Camargue , 30240 Le Grau du Roi",
    "sg:orig_category":"Non-Classified Establishments",
    "sg:phone":"+33 4 66 53 15 34",
    "sg:province":"Languedoc-Roussillon",
    "wof:name":"Maison Hours S.a.r.l.",
    "wof:placetype":"venue"
},
  "geometry": {"coordinates":[4.138094,43.534302],"type":"Point"}
}