{
  "type": "Feature",
  "properties": {
    "addr:full":"32, Rte de Roderen, 68800 Thann Thann Alsace 68800",
    "addr:housenumber":"32",
    "addr:postcode":"68800;68800",
    "addr:street":"Rte De Roderen",
    "iso:country":"FR",
    "sg:address":"32, Rte de Roderen, 68800 Thann",
    "sg:city":"Thann",
    "sg:orig_category":"Unclassifiable Establishments",
    "sg:phone":"+33 3 89 37 11 32",
    "sg:postcode":"68800",
    "sg:province":"Alsace",
    "wof:name":"Blanck S.a.",
    "wof:placetype":"venue"
},
  "geometry": {"coordinates":[7.11576,47.79636],"type":"Point"}
}