{
  "type": "Feature",
  "properties": {
    "iso:country":"FR",
    "sg:address":"B.P. 51110",
    "sg:city":"Pont Saint Esprit",
    "sg:orig_category":"Non-Classified Establishments",
    "sg:phone":"+33 4 66 50 56 00",
    "sg:postcode":"30130",
    "sg:province":"Languedoc-Roussillon",
    "wof:name":"A.t.m. S.a. - Assistance Totale En Maintenance",
    "wof:placetype":"venue"
},
  "geometry": {"coordinates":[4.64758,44.256756],"type":"Point"}
}