{
  "type": "Feature",
  "properties": {
    "addr:full":"B.P. 286, 71107 Chalon sur Sa\u00f4ne C\u00e9dex^^31, Rue Julien Leneuveu, 71380 Saint Marcel Ch\u00e2tenoy-en-Bresse Bourgogne 71380",
    "addr:housenumber":"b.p. 286",
    "addr:postcode":"71107;71380;71380",
    "addr:street":"Rue Julien Leneuveu;Marcel",
    "iso:country":"FR",
    "sg:address":"B.P. 286, 71107 Chalon sur Sa\u00f4ne C\u00e9dex^^31, Rue Julien Leneuveu, 71380 Saint Marcel",
    "sg:city":"Ch\u00e2tenoy-en-Bresse",
    "sg:orig_category":"Non-Classified Establishments",
    "sg:phone":"+33 3 85 42 54 32",
    "sg:postcode":"71380",
    "sg:province":"Bourgogne",
    "wof:name":"R.g.a.c. S.a. - Rectification G\u00e9n\u00e9rale Automobile Chalonnaise",
    "wof:placetype":"venue"
},
  "geometry": {"coordinates":[4.890325,46.775509],"type":"Point"}
}