{
  "type": "Feature",
  "properties": {
    "iso:country":"FR",
    "sg:address":"3, Rte de Livilliers, 95300 Ennery",
    "sg:orig_category":"Non-Classified Establishments",
    "sg:phone":"+33 1 30 30 23 61",
    "sg:postcode":"95300",
    "sg:province":"Ile de France",
    "wof:name":"C.e.r.d.p. S.a.r.l. - Cr\u00e9ation Entretien R\u00e9novation Du Paysage",
    "wof:placetype":"venue"
},
  "geometry": {"coordinates":[2.107441,49.080509],"type":"Point"}
}