{
  "type": "Feature",
  "properties": {
    "addr:full":"5, Rue Jean Perrin, 33600 Pessac Pessac Aquitaine 33600",
    "addr:housenumber":"5",
    "addr:postcode":"33600;33600",
    "addr:street":"Rue Jean Perrin",
    "iso:country":"FR",
    "sg:address":"5, Rue Jean Perrin, 33600 Pessac",
    "sg:city":"Pessac",
    "sg:orig_category":"Unclassifiable Establishments",
    "sg:phone":"+33 5 57 26 02 12",
    "sg:postcode":"33600",
    "sg:province":"Aquitaine",
    "wof:name":"Electrification G\u00e9n\u00e9rale S.a.",
    "wof:placetype":"venue"
},
  "geometry": {"coordinates":[-0.653772,44.780716],"type":"Point"}
}