{
  "type": "Feature",
  "properties": {
    "addr:full":"16 pl et 1 rue Saint; Falaise; 14700 Falaise Basse Normandie 14700",
    "addr:housenumber":"16;1",
    "addr:postcode":"14700;basse;14700",
    "addr:street":"Pl Et;Rue Saint Falaise",
    "iso:country":"FR",
    "sg:address":"16 pl et 1 rue Saint; Falaise; 14700",
    "sg:city":"Falaise",
    "sg:classifiers":[
        {
            "category":"Banks & Credit Unions",
            "subcategory":"Bank",
            "type":"Services"
        }
    ],
    "sg:phone":"+33 31901117",
    "sg:postcode":"14700",
    "sg:province":"Basse Normandie",
    "wof:name":"Soci\u00e9t\u00e9 G\u00e9n\u00e9rale",
    "wof:placetype":"venue"
},
  "geometry": {"coordinates":[-0.227884,48.852352],"type":"Point"}
}