{
  "type": "Feature",
  "properties": {
    "addr:full":"All Guimet 69250 Fleurieu Sur Sa\u00f4ne Rhone-Alpes 69250",
    "addr:postcode":"69250;sao\u0302ne rhone-alpes 69250",
    "addr:street":"Fleurieu",
    "iso:country":"FR",
    "sg:address":"All Guimet 69250 Fleurieu Sur Sa\u00f4ne",
    "sg:classifiers":[
        {
            "category":"Manufacturing",
            "subcategory":"Metals",
            "type":"Manufacturing & Wholesale Goods"
        }
    ],
    "sg:phone":"+33 4 78 91 27 91",
    "sg:postcode":"69250",
    "sg:province":"Rhone-Alpes",
    "sg:tags":[
        "metallurgy",
        "metalworking",
        "processing"
    ],
    "wof:name":"Societe Industrielle Fontainoise Sa",
    "wof:placetype":"venue"
},
  "geometry": {"coordinates":[4.840055,45.85471],"type":"Point"}
}