{
  "type": "Feature",
  "properties": {
    "addr:full":"12, Rue Gutenberg, 49000 Angers Pays de Loire",
    "addr:housenumber":"12",
    "addr:postcode":"49000",
    "addr:street":"Rue Gutenberg",
    "iso:country":"FR",
    "sg:address":"12, Rue Gutenberg, 49000 Angers",
    "sg:orig_category":"Unclassifiable Establishments",
    "sg:phone":"+33 2 41 88 93 12",
    "sg:province":"Pays de Loire",
    "wof:name":"Manulettres S.a.",
    "wof:placetype":"venue"
},
  "geometry": {"coordinates":[-0.553137,47.458378],"type":"Point"}
}