{
  "type": "Feature",
  "properties": {
    "addr:full":"30bis, Rue du Bailly, 93210 La Plaine Saint Denis \u00cele-de-France",
    "addr:housenumber":"30bis",
    "addr:postcode":"93210",
    "addr:street":"Rue Du Bailly",
    "iso:country":"FR",
    "sg:address":"30bis, Rue du Bailly, 93210 La Plaine Saint Denis",
    "sg:orig_category":"Unclassifiable Establishments",
    "sg:phone":"+33 1 49 46 58 00",
    "sg:province":"\u00cele-de-France",
    "wof:name":"Visiodent S.a.",
    "wof:placetype":"venue"
},
  "geometry": {"coordinates":[2.35599,48.913548],"type":"Point"}
}