{
  "type": "Feature",
  "properties": {
    "iso:country":"FR",
    "sg:address":"Boulevard Thomson Boulevard Des Sports 59810 Lesquin",
    "sg:classifiers":[
        {
            "category":"Professional",
            "subcategory":"Engineering",
            "type":"Services"
        }
    ],
    "sg:phone":"+33 3 20 16 65 65",
    "sg:postcode":"59810",
    "sg:province":"Nord Pas-de-Calais",
    "sg:tags":[
        "machine",
        "-",
        "mechanical"
    ],
    "wof:name":"Elcobrandt",
    "wof:placetype":"venue"
},
  "geometry": {"coordinates":[3.11003,50.588009],"type":"Point"}
}