{
  "type": "Feature",
  "properties": {
    "addr:full":"B.P. 134, 85203 Fontenay le Comte C\u00e9dex^^Rte de S\u00e9rign\u00e9 - Le Porteau, 85200 Fontenay le Comte Pays de Loire 85200",
    "addr:housenumber":"b.p. 134",
    "addr:postcode":"85203;85200;85200",
    "addr:street":"Le Comte Pays",
    "iso:country":"FR",
    "sg:address":"B.P. 134, 85203 Fontenay le Comte C\u00e9dex^^Rte de S\u00e9rign\u00e9 - Le Porteau, 85200 Fontenay le Comte",
    "sg:orig_category":"Non-Classified Establishments",
    "sg:phone":"+33 2 51 69 40 55",
    "sg:postcode":"85200",
    "sg:province":"Pays de Loire",
    "wof:name":"Etablissement Leduc Et Lubot S.a.s.",
    "wof:placetype":"venue"
},
  "geometry": {"coordinates":[-0.807965,46.392536],"type":"Point"}
}