{
  "type": "Feature",
  "properties": {
    "iso:country":"FR",
    "sg:address":"ZAC des Morands",
    "sg:city":"Montchanin",
    "sg:orig_category":"Non-Classified Establishments",
    "sg:phone":"+33 3 85 78 87 00",
    "sg:postcode":"71210",
    "sg:province":"Bourgogne",
    "wof:name":"Bourgogne Abats Triperies S.a.",
    "wof:placetype":"venue"
},
  "geometry": {"coordinates":[4.46917,46.748814],"type":"Point"}
}