{
  "type": "Feature",
  "properties": {
    "iso:country":"FR",
    "sg:address":"9 Rue De Catalogne Parc Des Pivolles 69150 Decines Charpieu",
    "sg:classifiers":[
        {
            "category":"Professional",
            "subcategory":"Engineering",
            "type":"Services"
        }
    ],
    "sg:phone":"+33 4 72 15 88 70",
    "sg:postcode":"69150",
    "sg:province":"Rhone-Alpes",
    "sg:tags":[
        "machine",
        "-",
        "mechanical"
    ],
    "wof:name":"C 2a I",
    "wof:placetype":"venue"
},
  "geometry": {"coordinates":[4.942962,45.749065],"type":"Point"}
}