{
  "type": "Feature",
  "properties": {
    "iso:country":"FR",
    "sg:address":"74 Boulevard De L'Atlantique Domaine De Cramphore 44510 Le Pouliguen",
    "sg:classifiers":[
        {
            "category":"Travel",
            "subcategory":"Hotels & Motels",
            "type":"Entertainment"
        }
    ],
    "sg:phone":"+33 2 40 11 28 00",
    "sg:postcode":"44510",
    "sg:province":"Pays de Loire",
    "sg:tags":[
        "hotels",
        "business",
        "restaurant"
    ],
    "wof:name":"Pierre Et Vacances Tourisme",
    "wof:placetype":"venue"
},
  "geometry": {"coordinates":[-2.440872,47.269547],"type":"Point"}
}