{
  "type": "Feature",
  "properties": {
    "iso:country":"FR",
    "sg:address":"18 Av De Luzanne 33880 St Caprais De Bordeaux",
    "sg:city":"Baurech",
    "sg:classifiers":[
        {
            "category":"Home & Garden",
            "subcategory":"Furniture",
            "type":"Retail Goods"
        }
    ],
    "sg:phone":"+33 5 57 97 12 50",
    "sg:postcode":"33880",
    "sg:province":"Aquitaine",
    "sg:tags":[
        "wood"
    ],
    "wof:name":"Tonnellerie Demptos",
    "wof:placetype":"venue"
},
  "geometry": {"coordinates":[-0.430189,44.748089],"type":"Point"}
}