{
  "type": "Feature",
  "properties": {
    "addr:full":"Rue Hector Berlioz Tullins Rhone-Alpes 38210",
    "addr:postcode":"38210",
    "addr:street":"Rue Hector Berlioz;Rhone-Alpes",
    "iso:country":"FR",
    "sg:address":"Rue Hector Berlioz",
    "sg:city":"Tullins",
    "sg:orig_category":"Unclassifiable Establishments",
    "sg:phone":"+33 4 76 07 29 20",
    "sg:postcode":"38210",
    "sg:province":"Rhone-Alpes",
    "wof:name":"S.a.c. S.a.r.l. - Soci\u00e9t\u00e9 Alpine De Commerce",
    "wof:placetype":"venue"
},
  "geometry": {"coordinates":[5.4948,45.307678],"type":"Point"}
}