{
  "type": "Feature",
  "properties": {
    "addr:full":"4, Grande Rue, 80500 Courtemanche Picardie",
    "addr:housenumber":"4",
    "addr:postcode":"80500",
    "addr:street":"Grande Rue",
    "iso:country":"FR",
    "sg:address":"4, Grande Rue, 80500 Courtemanche",
    "sg:orig_category":"Unclassifiable Establishments",
    "sg:phone":"+33 3 22 78 65 97",
    "sg:province":"Picardie",
    "wof:name":"Plastech Industries S.a.r.l.",
    "wof:placetype":"venue"
},
  "geometry": {"coordinates":[2.540227,49.663418],"type":"Point"}
}