{
  "type": "Feature",
  "properties": {
    "iso:country":"FR",
    "sg:address":"238, Rue J. Marie Car\u00e8re, 29300 Baye",
    "sg:city":"Baye",
    "sg:orig_category":"Unclassifiable Establishments",
    "sg:phone":"+33 2 98 96 81 87",
    "sg:postcode":"29300",
    "sg:province":"Bretagne",
    "wof:name":"Jean-jacques Cellier",
    "wof:placetype":"venue"
},
  "geometry": {"coordinates":[-3.606619,47.856815],"type":"Point"}
}