{
  "type": "Feature",
  "properties": {
    "iso:country":"FR",
    "sg:address":"12 pl Clemen\u00e7eau; Pau; 64004",
    "sg:classifiers":[
        {
            "category":"Banks & Credit Unions",
            "subcategory":"Bank",
            "type":"Services"
        }
    ],
    "sg:phone":"+33 3359271623",
    "sg:province":"Aquitaine",
    "wof:name":"Cr\u00e9dit Foncier De France",
    "wof:placetype":"venue"
},
  "geometry": {"coordinates":[-0.367966,43.29594],"type":"Point"}
}