{
  "type": "Feature",
  "properties": {
    "iso:country":"FR",
    "sg:address":"ZI",
    "sg:city":"Levroux",
    "sg:orig_category":"Non-Classified Establishments",
    "sg:phone":"+33 2 54 35 18 30",
    "sg:postcode":"36110",
    "sg:province":"Centre",
    "wof:name":"Gabachim D\u00e9co S.a.",
    "wof:placetype":"venue"
},
  "geometry": {"coordinates":[1.636735,46.901894],"type":"Point"}
}