{
  "type": "Feature",
  "properties": {
    "addr:full":"43, Rte Nationale, 62921 Aire sur la Lys C\u00e9dex Champagne",
    "addr:housenumber":"43",
    "addr:postcode":"62921",
    "addr:street":"Rte Nationale;Aire;La",
    "iso:country":"FR",
    "sg:address":"43, Rte Nationale, 62921 Aire sur la Lys C\u00e9dex",
    "sg:orig_category":"Unclassifiable Establishments",
    "sg:phone":"+33 3 21 95 44 44",
    "sg:province":"Champagne",
    "wof:name":"Voyages Inglard S.a.",
    "wof:placetype":"venue"
},
  "geometry": {"coordinates":[2.39416,50.652405],"type":"Point"}
}