{
  "type": "Feature",
  "properties": {
    "addr:full":"Pompierre 44800 Saint Herblain Pays de Loire",
    "addr:postcode":"44800",
    "addr:street":"Herblain",
    "iso:country":"FR",
    "sg:address":"Pompierre 44800 Saint Herblain",
    "sg:orig_category":"Unclassifiable Establishments",
    "sg:phone":"+33 2 40 86 14 31",
    "sg:province":"Pays de Loire",
    "wof:name":"Cl\u00e9ment Et Fils S.a.",
    "wof:placetype":"venue"
},
  "geometry": {"coordinates":[-1.639215,47.208775],"type":"Point"}
}