{
  "type": "Feature",
  "properties": {
    "addr:full":"Parc d'Affaire Silic Cergy Saint Christophe Ile de France 95800",
    "addr:postcode":"95800",
    "addr:street":"Saint",
    "iso:country":"FR",
    "sg:address":"Parc d'Affaire Silic",
    "sg:city":"Cergy Saint Christophe",
    "sg:orig_category":"Unclassifiable Establishments",
    "sg:phone":"+33 1 34 20 13 40",
    "sg:postcode":"95800",
    "sg:province":"Ile de France",
    "wof:name":"Soci\u00e9t\u00e9 Cergydis S.a.r.l.",
    "wof:placetype":"venue"
},
  "geometry": {"coordinates":[5.501143,46.57917],"type":"Point"}
}