{
  "type": "Feature",
  "properties": {
    "addr:full":"22, Rue Morvan Lebesque, 51370 Saint Brice Courcelles Champagne 51370",
    "addr:housenumber":"22",
    "addr:postcode":"51370;51370",
    "addr:street":"Rue Morvan Lebesque",
    "iso:country":"FR",
    "sg:address":"22, Rue Morvan Lebesque, 51370 Saint Brice Courcelles",
    "sg:orig_category":"Non-Classified Establishments",
    "sg:phone":"+33 3 26 87 55 40",
    "sg:postcode":"51370",
    "sg:province":"Champagne",
    "wof:name":"Daniel Val\u00e9ro Design S.a.r.l.",
    "wof:placetype":"venue"
},
  "geometry": {"coordinates":[3.990734,49.260056],"type":"Point"}
}