{
  "type": "Feature",
  "properties": {
    "addr:full":"B.P. 30, 17140 Lagord C\u00e9dex^^Rue Gustave Eiffel, 17140 Lagord Poitou-Charentes",
    "addr:postcode":"17140;17140",
    "addr:street":"B.P. 30;Ce\u0301Dex^^Rue Gustave Eiffel",
    "iso:country":"FR",
    "sg:address":"B.P. 30, 17140 Lagord C\u00e9dex^^Rue Gustave Eiffel, 17140 Lagord",
    "sg:orig_category":"Non-Classified Establishments",
    "sg:phone":"+33 5 46 43 86 62",
    "sg:province":"Poitou-Charentes",
    "wof:name":"Soci\u00e9t\u00e9 D'exploitation Des Etablissements Roth S.a.r.l.",
    "wof:placetype":"venue"
},
  "geometry": {"coordinates":[-1.152969,46.190434],"type":"Point"}
}