{
  "type": "Feature",
  "properties": {
    "addr:full":"8, Rue Person, 67700 Saverne Saverne Alsace 67700",
    "addr:housenumber":"8",
    "addr:postcode":"67700;67700",
    "addr:street":"Rue Person",
    "iso:country":"FR",
    "sg:address":"8, Rue Person, 67700 Saverne",
    "sg:city":"Saverne",
    "sg:orig_category":"Unclassifiable Establishments",
    "sg:phone":"+33 3 88 91 31 66",
    "sg:postcode":"67700",
    "sg:province":"Alsace",
    "wof:name":"Cartonnages Robitzer S.a.r.l.",
    "wof:placetype":"venue"
},
  "geometry": {"coordinates":[7.372072,48.739105],"type":"Point"}
}