{
  "type": "Feature",
  "properties": {
    "iso:country":"FR",
    "sg:address":"2 Place Victor Hugo 38000 Grenoble",
    "sg:classifiers":[
        {
            "category":"Manufacturing",
            "subcategory":"Jewelry",
            "type":"Manufacturing & Wholesale Goods"
        }
    ],
    "sg:phone":"+33 4 76 85 03 33",
    "sg:postcode":"38000",
    "sg:province":"Rhone-Alpes",
    "sg:tags":[
        "product",
        "miscellaneous",
        "jewellery"
    ],
    "wof:name":"Maty",
    "wof:placetype":"venue"
},
  "geometry": {"coordinates":[5.724363,45.189621],"type":"Point"}
}