{
  "type": "Feature",
  "properties": {
    "addr:full":"Chem Raperie 62120 Aire Sur La Lys Nord Pas-de-Calais 62120",
    "addr:postcode":"62120;62120",
    "addr:street":"Raperie;Aire;La Lys Nord",
    "iso:country":"FR",
    "sg:address":"Chem Raperie 62120 Aire Sur La Lys",
    "sg:classifiers":[
        {
            "category":"Manufacturing",
            "subcategory":"Glass & Minerals",
            "type":"Manufacturing & Wholesale Goods"
        }
    ],
    "sg:phone":"+33 3 21 39 15 43",
    "sg:postcode":"62120",
    "sg:province":"Nord Pas-de-Calais",
    "sg:tags":[
        "building",
        "material",
        "-",
        "metalworking",
        "metallic",
        "metallurgy",
        "finished"
    ],
    "wof:name":"Machines Et Materiel De Verrerie",
    "wof:placetype":"venue"
},
  "geometry": {"coordinates":[2.413117,50.639919],"type":"Point"}
}