{
  "type": "Feature",
  "properties": {
    "addr:full":"6, Rue de Berlange - Parc d'Activit\u00e9 de Berlange, 57140 Woippy Lorraine",
    "addr:housenumber":"6",
    "addr:postcode":"57140",
    "addr:street":"Rue De Berlange Parc D'Activite \u0301 De Berlange",
    "iso:country":"FR",
    "sg:address":"6, Rue de Berlange - Parc d'Activit\u00e9 de Berlange, 57140 Woippy",
    "sg:orig_category":"Unclassifiable Establishments",
    "sg:phone":"+33 3 87 16 94 94",
    "sg:province":"Lorraine",
    "wof:name":"Cl\u00e9ment S.a.",
    "wof:placetype":"venue"
},
  "geometry": {"coordinates":[6.157838,49.152752],"type":"Point"}
}