{
  "type": "Feature",
  "properties": {
    "addr:full":"B.P. 40, 93260 Les Lilas^^20, Rue des Villegranges, 93260 Les Lilas Ile de France",
    "addr:postcode":"93260;93260",
    "addr:street":"B.P. 40;Rue Des Villegranges",
    "iso:country":"FR",
    "sg:address":"B.P. 40, 93260 Les Lilas^^20, Rue des Villegranges, 93260 Les Lilas",
    "sg:orig_category":"Non-Classified Establishments",
    "sg:phone":"+33 1 43 62 88 23",
    "sg:province":"Ile de France",
    "wof:name":"Nebo S.a.r.l.",
    "wof:placetype":"venue"
},
  "geometry": {"coordinates":[2.415765,48.879616],"type":"Point"}
}