{
  "type": "Feature",
  "properties": {
    "iso:country":"FR",
    "sg:address":"50520 Bellefontaine",
    "sg:city":"Bellefontaine",
    "sg:orig_category":"Non-Classified Establishments",
    "sg:phone":"+33 2 33 79 34 40",
    "sg:postcode":"50520",
    "sg:province":"Basse Normandie",
    "wof:name":"Lacroix Compagnie S.a.",
    "wof:placetype":"venue"
},
  "geometry": {"coordinates":[-0.973209,48.687759],"type":"Point"}
}