{
  "type": "Feature",
  "properties": {
    "iso:country":"FR",
    "sg:address":"C I Du Porzo 56700 Kervignac",
    "sg:city":"Kervignac",
    "sg:classifiers":[
        {
            "category":"Farming",
            "subcategory":"Fish & Marine Products",
            "type":"Manufacturing & Wholesale Goods"
        }
    ],
    "sg:phone":"+33 2 97 85 19 39",
    "sg:postcode":"56700",
    "sg:province":"Bretagne",
    "sg:tags":[
        "preserve",
        "frozen",
        "food",
        "related"
    ],
    "wof:name":"Societe Marine",
    "wof:placetype":"venue"
},
  "geometry": {"coordinates":[-3.204294,47.719566],"type":"Point"}
}