{
  "type": "Feature",
  "properties": {
    "iso:country":"FR",
    "sg:address":"35, Bd Anatole France, 93200 Saint Denis",
    "sg:orig_category":"Non-Classified Establishments",
    "sg:phone":"+33 1 48 13 78 80",
    "sg:province":"Ile de France",
    "wof:name":"Sorima Industries S.a.",
    "wof:placetype":"venue"
},
  "geometry": {"coordinates":[2.352019,48.926811],"type":"Point"}
}