{
  "type": "Feature",
  "properties": {
    "addr:full":"Rue des Onze Arpents Blois Centre 41000",
    "addr:postcode":"41000",
    "addr:street":"Rue Des Onze Arpents Blois",
    "iso:country":"FR",
    "sg:address":"Rue des Onze Arpents",
    "sg:city":"Blois",
    "sg:orig_category":"Unclassifiable Establishments",
    "sg:phone":"+33 2 54 55 83 00",
    "sg:postcode":"41000",
    "sg:province":"Centre",
    "wof:name":"Team Partners Groupe I.s.m. S.a.",
    "wof:placetype":"venue"
},
  "geometry": {"coordinates":[1.33664,47.613979],"type":"Point"}
}