{
  "type": "Feature",
  "properties": {
    "iso:country":"FR",
    "sg:address":"B.P. 36, 77212 Avon C\u00e9dex^^44, Av. de Valvins, 77210 Avon",
    "sg:orig_category":"Non-Classified Establishments",
    "sg:phone":"+33 1 60 72 61 21",
    "sg:province":"Ile de France",
    "wof:name":"Granit N\u00e9goce S.a.",
    "wof:placetype":"venue"
},
  "geometry": {"coordinates":[2.72196,48.415936],"type":"Point"}
}