{
  "type": "Feature",
  "properties": {
    "addr:full":"11, Rue Louisa Paulin, 19000 Tulle Limousin",
    "addr:housenumber":"11",
    "addr:postcode":"19000",
    "addr:street":"Rue Louisa Paulin",
    "iso:country":"FR",
    "sg:address":"11, Rue Louisa Paulin, 19000 Tulle",
    "sg:orig_category":"Unclassifiable Establishments",
    "sg:phone":"+33 5 55 29 99 23",
    "sg:province":"Limousin",
    "wof:name":"R.i.e.p. - R\u00e9gie Industrielle Des Etablissements P\u00e9nitentiai",
    "wof:placetype":"venue"
},
  "geometry": {"coordinates":[1.753035,45.260414],"type":"Point"}
}