{
  "type": "Feature",
  "properties": {
    "addr:full":"417, Rte de Lyon - RN 6, 69480 Amb\u00e9rieux d'Azergues Rhone-Alpes",
    "addr:housenumber":"417",
    "addr:postcode":"69480",
    "addr:street":"Rte De Lyon Rn 6",
    "iso:country":"FR",
    "sg:address":"417, Rte de Lyon - RN 6, 69480 Amb\u00e9rieux d'Azergues",
    "sg:orig_category":"Unclassifiable Establishments",
    "sg:phone":"+33 4 74 67 11 13",
    "sg:province":"Rhone-Alpes",
    "wof:name":"Ravoux Et Associ\u00e9s S.a.r.l.",
    "wof:placetype":"venue"
},
  "geometry": {"coordinates":[4.725517,45.931343],"type":"Point"}
}