{
  "type": "Feature",
  "properties": {
    "addr:full":"Route de Caromb 84380 MAZAN Aquitaine",
    "addr:postcode":"84380",
    "addr:street":"Route De Caromb",
    "iso:country":"FR",
    "sg:address":"Route de Caromb 84380 MAZAN",
    "sg:classifiers":[
        {
            "category":"Wholesale",
            "subcategory":"Wine & Distilled Alcoholic Beverages",
            "type":"Manufacturing & Wholesale Goods"
        }
    ],
    "sg:phone":"+33 4 90 69 70 31",
    "sg:province":"Aquitaine",
    "sg:tags":[
        "french"
    ],
    "wof:name":"Vignerons De Canteperdrix Coop",
    "wof:placetype":"venue"
},
  "geometry": {"coordinates":[5.128094,44.064831],"type":"Point"}
}