{
  "type": "Feature",
  "properties": {
    "addr:full":"Rte de Portet - ZA les Pousses Villeneuve Tolosane Midi Pyr\u00e9n\u00e9es 31270",
    "addr:postcode":"31270",
    "addr:street":"Rte De Portet Za Les Pousses",
    "iso:country":"FR",
    "sg:address":"Rte de Portet - ZA les Pousses",
    "sg:city":"Villeneuve Tolosane",
    "sg:orig_category":"Unclassifiable Establishments",
    "sg:phone":"+33 5 61 76 99 76",
    "sg:postcode":"31270",
    "sg:province":"Midi Pyr\u00e9n\u00e9es",
    "wof:name":"Andeco Informatique S.a.r.l.",
    "wof:placetype":"venue"
},
  "geometry": {"coordinates":[1.34424,43.536976],"type":"Point"}
}