{
  "type": "Feature",
  "properties": {
    "addr:full":"Petit Lecussan 47310 Moirax Moirax Aquitaine 47310",
    "addr:postcode":"47310;47310",
    "iso:country":"FR",
    "sg:address":"Petit Lecussan 47310 Moirax",
    "sg:city":"Moirax",
    "sg:classifiers":[
        {
            "category":"Manufacturing",
            "subcategory":"Textiles",
            "type":"Manufacturing & Wholesale Goods"
        }
    ],
    "sg:phone":"+33 5 53 67 00 77",
    "sg:postcode":"47310",
    "sg:province":"Aquitaine",
    "sg:tags":[
        "clothing",
        "accessory"
    ],
    "wof:name":"Garonne Confection",
    "wof:placetype":"venue"
},
  "geometry": {"coordinates":[0.518632,44.076218],"type":"Point"}
}