{
  "type": "Feature",
  "properties": {
    "iso:country":"FR",
    "sg:address":"4 rue Galvani 91300 Massy",
    "sg:classifiers":[
        {
            "category":"Shopping",
            "subcategory":"Pharmacy",
            "type":"Retail Goods"
        }
    ],
    "sg:phone":"+33 1 64 53 16 64",
    "sg:province":"Ile de France",
    "sg:tags":[
        "preparation",
        "pharmaceutical"
    ],
    "wof:name":"Vipharco Sa",
    "wof:placetype":"venue"
},
  "geometry": {"coordinates":[2.269316,48.723801],"type":"Point"}
}