{
  "type": "Feature",
  "properties": {
    "addr:full":"Rue St Pierre 63120 Courpi\u00e8re Courpi\u00e8re Auvergne 63120",
    "addr:postcode":"63120;courpie\u0300re;63120",
    "addr:street":"Rue St Pierre",
    "iso:country":"FR",
    "sg:address":"Rue St Pierre 63120 Courpi\u00e8re",
    "sg:city":"Courpi\u00e8re",
    "sg:classifiers":[
        {
            "category":"Professional",
            "subcategory":"Business Services",
            "type":"Services"
        }
    ],
    "sg:phone":"+33 4 73 51 72 00",
    "sg:postcode":"63120",
    "sg:province":"Auvergne",
    "sg:tags":[
        "training",
        "advice"
    ],
    "wof:name":"Groupe Scolaire St Pierre",
    "wof:placetype":"venue"
},
  "geometry": {"coordinates":[3.53429,45.753716],"type":"Point"}
}