{
  "type": "Feature",
  "properties": {
    "addr:full":"Z I Bois Pataud 37150 BLERE Bl\u00e9r\u00e9 Centre 37150",
    "addr:postcode":"37150;37150",
    "addr:street":"Z I Bois Pataud;Ble\u0301Re\u0301",
    "iso:country":"FR",
    "sg:address":"Z I Bois Pataud 37150 BLERE",
    "sg:city":"Bl\u00e9r\u00e9",
    "sg:classifiers":[
        {
            "category":"Transit Center",
            "subcategory":"Freight",
            "type":"Transportation"
        }
    ],
    "sg:phone":"+33 2 47 57 95 39",
    "sg:postcode":"37150",
    "sg:province":"Centre",
    "sg:tags":[
        "necktie"
    ],
    "wof:name":"Etablissements Thiercelin S.a.",
    "wof:placetype":"venue"
},
  "geometry": {"coordinates":[1.049415,47.247349],"type":"Point"}
}