{
  "type": "Feature",
  "properties": {
    "addr:full":"10, Rue de l'Industrie - ZI, 74130 Vougy Rhone-Alpes",
    "addr:housenumber":"10",
    "addr:postcode":"74130",
    "addr:street":"Rue De L'Industrie Zi",
    "iso:country":"FR",
    "sg:address":"10, Rue de l'Industrie - ZI, 74130 Vougy",
    "sg:orig_category":"Unclassifiable Establishments",
    "sg:phone":"+33 4 50 34 69 61",
    "sg:province":"Rhone-Alpes",
    "wof:name":"Microdec S.a.r.l.",
    "wof:placetype":"venue"
},
  "geometry": {"coordinates":[6.410583,46.075848],"type":"Point"}
}