{
  "type": "Feature",
  "properties": {
    "iso:country":"FR",
    "sg:address":"Zi La Folie 85310 La Chaize Le Vicomte",
    "sg:classifiers":[
        {
            "category":"Autos & Motor Vehicles",
            "subcategory":"Automobile Sales",
            "type":"Retail Goods"
        }
    ],
    "sg:phone":"+33 2 51 05 81 75",
    "sg:postcode":"85310",
    "sg:province":"Pays de Loire",
    "sg:tags":[
        "equipment",
        "motor-cars",
        "transport"
    ],
    "wof:name":"Carrosserie Cantin",
    "wof:placetype":"venue"
},
  "geometry": {"coordinates":[-1.291824,46.672306],"type":"Point"}
}