{
  "type": "Feature",
  "properties": {
    "iso:country":"FR",
    "sg:address":"B.P. 30601, 44006 Nantes C\u00e9dex 01^^5, All\u00e9e Baco, 44000 Nantes",
    "sg:orig_category":"Non-Classified Establishments",
    "sg:phone":"+33 2 40 47 63 77",
    "sg:province":"Pays de Loire",
    "wof:name":"Sedim Jaclebert S.a.",
    "wof:placetype":"venue"
},
  "geometry": {"coordinates":[-1.553059,47.218117],"type":"Point"}
}