{
  "type": "Feature",
  "properties": {
    "addr:full":"1 pl Fran\u00e7ois Henry Cliquot 77100 Meaux Ile de France",
    "addr:housenumber":"1",
    "addr:postcode":"77100;ile",
    "addr:street":"Pl Franc\u0327Ois Henry Cliquot",
    "iso:country":"FR",
    "sg:address":"1 pl Fran\u00e7ois Henry Cliquot 77100 Meaux",
    "sg:classifiers":[
        {
            "category":"Manufacturing",
            "subcategory":"Electronics",
            "type":"Manufacturing & Wholesale Goods"
        }
    ],
    "sg:phone":"+33 1 64 36 53 70",
    "sg:province":"Ile de France",
    "sg:tags":[
        "pcb",
        "printed",
        "circuit",
        "board"
    ],
    "wof:name":"Ice-cee Sa",
    "wof:placetype":"venue"
},
  "geometry": {"coordinates":[2.883054,48.959351],"type":"Point"}
}