{
  "type": "Feature",
  "properties": {
    "iso:country":"FR",
    "sg:address":"36, Rue Michelet, 78220 Viroflay",
    "sg:orig_category":"Non-Classified Establishments",
    "sg:phone":"+33 1 30 24 02 44",
    "sg:postcode":"78220",
    "sg:province":"Ile de France",
    "wof:name":"Blanchisserie De La Marquette S.a.r.l.",
    "wof:placetype":"venue"
},
  "geometry": {"coordinates":[2.17125,48.806122],"type":"Point"}
}