{
  "type": "Feature",
  "properties": {
    "addr:full":"Rue Bois Rochefort Za Les Perriers 78500 Sartrouville Ile de France 78500",
    "addr:postcode":"78500;ile;78500",
    "addr:street":"Rue Bois;Za Les Perriers;France",
    "iso:country":"FR",
    "sg:address":"Rue Bois Rochefort Za Les Perriers 78500 Sartrouville",
    "sg:classifiers":[
        {
            "category":"Shopping",
            "subcategory":"Crafts & Fabrics",
            "type":"Retail Goods"
        }
    ],
    "sg:phone":"+33 1 61 04 44 44",
    "sg:postcode":"78500",
    "sg:province":"Ile de France",
    "sg:tags":[
        "household",
        "textile",
        "linen",
        "wood",
        "clothing",
        "furniture"
    ],
    "wof:name":"Galedo",
    "wof:placetype":"venue"
},
  "geometry": {"coordinates":[2.16183,48.941525],"type":"Point"}
}