{
  "type": "Feature",
  "properties": {
    "addr:full":"B.P. 139, 06803 Cagnes sur Mer C\u00e9dex^^45/47, Av. de Grasse, 06800 Cagnes sur Mer Provence-Alpes-C\u00f4te d'Azur",
    "addr:housenumber":"b.p. 139",
    "addr:postcode":"06803;06800",
    "addr:street":"47 Av. De Grasse;Mer",
    "iso:country":"FR",
    "sg:address":"B.P. 139, 06803 Cagnes sur Mer C\u00e9dex^^45/47, Av. de Grasse, 06800 Cagnes sur Mer",
    "sg:orig_category":"Non-Classified Establishments",
    "sg:phone":"+33 4 92 13 51 00",
    "sg:province":"Provence-Alpes-C\u00f4te d'Azur",
    "wof:name":"S.b.g.c.a. S.a. - Soci\u00e9t\u00e9 De Boissons Gazeuses De La C\u00f4te D'azur",
    "wof:placetype":"venue"
},
  "geometry": {"coordinates":[7.1533,43.664429],"type":"Point"}
}