{
  "type": "Feature",
  "properties": {
    "iso:country":"FR",
    "sg:address":"7, Chemin de Monboulin, 18000 Bourges",
    "sg:city":"Bourges",
    "sg:orig_category":"Unclassifiable Establishments",
    "sg:phone":"+33 2 48 24 67 46",
    "sg:postcode":"18000",
    "sg:province":"Centre",
    "wof:name":"Onet Propret\u00e9 S.a.",
    "wof:placetype":"venue"
},
  "geometry": {"coordinates":[2.401398,47.109188],"type":"Point"}
}