{
  "type": "Feature",
  "properties": {
    "addr:full":"29, Av. de Russie, 03700 Bellerive sur Allier Bellerive-sur-Allier Auvergne 03700",
    "addr:postcode":"03700;03700",
    "addr:street":"29 Av. De Russie",
    "iso:country":"FR",
    "sg:address":"29, Av. de Russie, 03700 Bellerive sur Allier",
    "sg:city":"Bellerive-sur-Allier",
    "sg:orig_category":"Unclassifiable Establishments",
    "sg:phone":"+33 4 70 32 50 63",
    "sg:postcode":"03700",
    "sg:province":"Auvergne",
    "wof:name":"Etablissements Andr\u00e9 Pomar\u00e8de S.a.",
    "wof:placetype":"venue"
},
  "geometry": {"coordinates":[3.407224,46.115082],"type":"Point"}
}