{
  "type": "Feature",
  "properties": {
    "iso:country":"FR",
    "sg:address":"16, Rue Vimaine, 38200 Vienne",
    "sg:orig_category":"Non-Classified Establishments",
    "sg:phone":"+33 4 74 53 34 05",
    "sg:postcode":"38200",
    "sg:province":"Rhone-Alpes",
    "wof:name":"Alpac S.a.",
    "wof:placetype":"venue"
},
  "geometry": {"coordinates":[4.865032,45.515739],"type":"Point"}
}