{
  "type": "Feature",
  "properties": {
    "addr:full":"4 rue Edouard Branly 78190 Trappes Ile de France",
    "addr:housenumber":"4",
    "addr:postcode":"78190;ile",
    "addr:street":"Rue Edouard Branly",
    "iso:country":"FR",
    "sg:address":"4 rue Edouard Branly 78190 Trappes",
    "sg:classifiers":[
        {
            "category":"Banks & Credit Unions",
            "subcategory":"Investment Brokerage",
            "type":"Services"
        }
    ],
    "sg:phone":"+33 1 30 68 01 23",
    "sg:province":"Ile de France",
    "sg:tags":[
        "overhead",
        "conductor"
    ],
    "wof:name":"Ctms S.a.",
    "wof:placetype":"venue"
},
  "geometry": {"coordinates":[1.983247,48.793644],"type":"Point"}
}