{
  "type": "Feature",
  "properties": {
    "iso:country":"FR",
    "sg:address":"B.P. 74, 47003 Agen C\u00e9dex^^Rue du Midi - ZAC Agen Sud, 47000 Agen",
    "sg:city":"Agen",
    "sg:orig_category":"Non-Classified Establishments",
    "sg:phone":"+33 5 53 68 08 88",
    "sg:postcode":"47000",
    "sg:province":"Aquitaine",
    "wof:name":"De Latour Midel S.a.",
    "wof:placetype":"venue"
},
  "geometry": {"coordinates":[0.62061,44.205109],"type":"Point"}
}