{
  "type": "Feature",
  "properties": {
    "iso:country":"FR",
    "sg:address":"10, Place Charles B\u00e9raudier - Immeuble l'Orient, 69428 Lyon C\u00e9dex 03",
    "sg:orig_category":"Non-Classified Establishments",
    "sg:phone":"+33 4 72 11 41 80",
    "sg:province":"Rhone-Alpes",
    "wof:name":"Axialog Rh\u00f4ne-alpes S.a.",
    "wof:placetype":"venue"
},
  "geometry": {"coordinates":[4.85879,45.759949],"type":"Point"}
}