{
  "type": "Feature",
  "properties": {
    "addr:full":"26 Rue De L'H\u00f4tel Des Postes 03200 Vichy Vichy Auvergne 03200",
    "addr:housenumber":"26",
    "addr:postcode":"03200;03200",
    "addr:street":"Rue De L'Ho;Des Postes",
    "iso:country":"FR",
    "sg:address":"26 Rue De L'H\u00f4tel Des Postes 03200 Vichy",
    "sg:city":"Vichy",
    "sg:classifiers":[
        {
            "category":"Banks & Credit Unions",
            "subcategory":"Financial Services",
            "type":"Services"
        }
    ],
    "sg:phone":"+33 4 70 30 11 30",
    "sg:postcode":"03200",
    "sg:province":"Auvergne",
    "sg:tags":[
        "banking",
        "insurance",
        "institution",
        "finance"
    ],
    "wof:name":"Credit Lyonnais",
    "wof:placetype":"venue"
},
  "geometry": {"coordinates":[3.435126,46.127289],"type":"Point"}
}