{
  "type": "Feature",
  "properties": {
    "iso:country":"FR",
    "sg:address":"Euro Plaza Tower",
    "sg:city":"avenue Andr\u00e9-Prothin; Paris Cedex; 92927",
    "sg:classifiers":[
        {
            "category":"Industrial Area",
            "type":"Public Place"
        }
    ],
    "sg:phone":"+33 1 71 00 37 00",
    "sg:province":"Haute Normandie",
    "sg:tags":[
        "large",
        "private"
    ],
    "wof:name":"Bail Investissement",
    "wof:placetype":"venue"
},
  "geometry": {"coordinates":[2.208,48.896141],"type":"Point"}
}