{
  "type": "Feature",
  "properties": {
    "addr:full":"La Chapelle Thireuil 79160 Coulonges sur l'Autize Poitou-Charentes",
    "addr:postcode":"79160",
    "addr:street":"La;Thireuil;L'Autize",
    "iso:country":"FR",
    "sg:address":"La Chapelle Thireuil 79160 Coulonges sur l'Autize",
    "sg:orig_category":"Unclassifiable Establishments",
    "sg:phone":"+33 5 49 04 21 18",
    "sg:province":"Poitou-Charentes",
    "wof:name":"Laiterie Coop\u00e9rative De La Vall\u00e9e Du Rivault",
    "wof:placetype":"venue"
},
  "geometry": {"coordinates":[-0.5565,46.557541],"type":"Point"}
}