{
  "type": "Feature",
  "properties": {
    "addr:full":"Rte De Montignac 16230 Mansle Poitou-Charentes",
    "addr:postcode":"16230",
    "addr:street":"Rte De Montignac",
    "iso:country":"FR",
    "sg:address":"Rte De Montignac 16230 Mansle",
    "sg:classifiers":[
        {
            "category":"Manufacturing",
            "subcategory":"Rubber & Plastics",
            "type":"Manufacturing & Wholesale Goods"
        }
    ],
    "sg:phone":"+33 5 45 22 73 82",
    "sg:province":"Poitou-Charentes",
    "wof:name":"Cinq Mc",
    "wof:placetype":"venue"
},
  "geometry": {"coordinates":[0.31836,45.833389],"type":"Point"}
}