{
  "type": "Feature",
  "properties": {
    "iso:country":"FR",
    "sg:address":"Av. Spinoza",
    "sg:city":"Emerainville",
    "sg:orig_category":"Unclassifiable Establishments",
    "sg:phone":"+33 1 60 95 88 88",
    "sg:postcode":"77184",
    "sg:province":"Ile de France",
    "wof:name":"France Gift S.a.",
    "wof:placetype":"venue"
},
  "geometry": {"coordinates":[2.587925,48.832657],"type":"Point"}
}