{
  "type": "Feature",
  "properties": {
    "addr:full":"Rue des Trois Rochers Confort Rhone-Alpes 01200",
    "addr:postcode":"01200",
    "addr:street":"Rue Des Trois Rochers",
    "iso:country":"FR",
    "sg:address":"Rue des Trois Rochers",
    "sg:city":"Confort",
    "sg:orig_category":"Unclassifiable Establishments",
    "sg:phone":"+33 4 50 56 51 17",
    "sg:postcode":"01200",
    "sg:province":"Rhone-Alpes",
    "wof:name":"Entreprise Briffod Pascal S.a.r.l.",
    "wof:placetype":"venue"
},
  "geometry": {"coordinates":[5.821962,46.150009],"type":"Point"}
}