{
  "type": "Feature",
  "properties": {
    "addr:full":"1 Rte Bauge 49630 Maz\u00e9 Champagne",
    "addr:housenumber":"1",
    "addr:postcode":"49630",
    "addr:street":"Rte Bauge",
    "iso:country":"FR",
    "sg:address":"1 Rte Bauge 49630 Maz\u00e9",
    "sg:classifiers":[
        {
            "category":"Farming",
            "subcategory":"Farm",
            "type":"Manufacturing & Wholesale Goods"
        }
    ],
    "sg:phone":"+33 2 41 80 60 38",
    "sg:province":"Champagne",
    "sg:tags":[
        "horticulture",
        "agriculture",
        "livestock"
    ],
    "wof:name":"Graines Brivain Sa",
    "wof:placetype":"venue"
},
  "geometry": {"coordinates":[-0.256462,47.472469],"type":"Point"}
}