{
  "type": "Feature",
  "properties": {
    "iso:country":"FR",
    "sg:address":"30 Rue De Dunkerque 11400 Castelnaudary",
    "sg:classifiers":[
        {
            "category":"Food & Beverages",
            "subcategory":"Groceries & Convenience Stores",
            "type":"Retail Goods"
        }
    ],
    "sg:phone":"+33 4 68 23 16 88",
    "sg:postcode":"11400",
    "sg:province":"Languedoc-Roussillon",
    "sg:tags":[
        "product",
        "related"
    ],
    "wof:name":"Maison Escourrou",
    "wof:placetype":"venue"
},
  "geometry": {"coordinates":[1.955185,43.317493],"type":"Point"}
}