{
  "type": "Feature",
  "properties": {
    "iso:country":"FR",
    "sg:address":"Le Plan 30440 SUMENE",
    "sg:orig_category":"Nylon\u00ae Stockings",
    "sg:phone":"+33 4 67 73 70 19",
    "sg:province":"Languedoc-Roussillon",
    "wof:name":"Sotexmi Sarl",
    "wof:placetype":"venue"
},
  "geometry": {"coordinates":[3.71603,43.980984],"type":"Point"}
}