{
  "type": "Feature",
  "properties": {
    "addr:full":"ZA Lioujas, 12740 La Loubi\u00e8re^^ZA Lioujas, 12740 La Loubi\u00e8re Midi Pyr\u00e9n\u00e9es",
    "addr:housenumber":"12740;12740",
    "addr:street":"Za Lioujas",
    "iso:country":"FR",
    "sg:address":"ZA Lioujas, 12740 La Loubi\u00e8re^^ZA Lioujas, 12740 La Loubi\u00e8re",
    "sg:orig_category":"Non-Classified Establishments",
    "sg:phone":"+33 5 65 46 94 43",
    "sg:province":"Midi Pyr\u00e9n\u00e9es",
    "wof:name":"Soci\u00e9t\u00e9 Grimal Bernard S.a.r.l.",
    "wof:placetype":"venue"
},
  "geometry": {"coordinates":[2.59946,44.403584],"type":"Point"}
}