{
  "type": "Feature",
  "properties": {
    "addr:full":"B.P. 46 Montoir de Bretagne C\u00e9dex^^La Torse 44550 Montoir de Bretagne Pays de Loire 44550",
    "addr:postcode":"44550;44550",
    "addr:street":"B.P. 46;De",
    "iso:country":"FR",
    "sg:address":"B.P. 46",
    "sg:city":"Montoir de Bretagne C\u00e9dex^^La Torse 44550 Montoir de Bretagne",
    "sg:orig_category":"Non-Classified Establishments",
    "sg:phone":"+33 2 51 16 60 60",
    "sg:postcode":"44550",
    "sg:province":"Pays de Loire",
    "wof:name":"S.o.f.o.p. Taliaplast S.a.s. - Soci\u00e9t\u00e9 Fran\u00e7aise D'outils Professionnels",
    "wof:placetype":"venue"
},
  "geometry": {"coordinates":[-2.177519,47.308414],"type":"Point"}
}