{
  "type": "Feature",
  "properties": {
    "addr:full":"Le Crozat 01480 Frans Rhone-Alpes 01480",
    "addr:postcode":"01480;01480",
    "addr:street":"Frans Rhone-Alpes",
    "iso:country":"FR",
    "sg:address":"Le Crozat 01480 Frans",
    "sg:orig_category":"Unclassifiable Establishments",
    "sg:phone":"+33 4 74 67 54 62",
    "sg:postcode":"01480",
    "sg:province":"Rhone-Alpes",
    "wof:name":"Soci\u00e9t\u00e9 Bressane De Pl\u00e2trerie S.a.r.l.",
    "wof:placetype":"venue"
},
  "geometry": {"coordinates":[4.77321,45.996479],"type":"Point"}
}