{
  "type": "Feature",
  "properties": {
    "addr:full":"164, Chemin Madragueville, 13015 Marseille Vill\u00e9 Alsace 67220",
    "addr:housenumber":"164",
    "addr:postcode":"13015;67220",
    "addr:street":"Chemin Madragueville",
    "iso:country":"FR",
    "sg:address":"164, Chemin Madragueville, 13015 Marseille",
    "sg:city":"Vill\u00e9",
    "sg:orig_category":"Non-Classified Establishments",
    "sg:phone":"+33 4 91 11 67 00",
    "sg:postcode":"67220",
    "sg:province":"Alsace",
    "wof:name":"Or\u00e9fi Sud Est Transmisions S.a.",
    "wof:placetype":"venue"
},
  "geometry": {"coordinates":[5.359541,43.328476],"type":"Point"}
}