{
  "type": "Feature",
  "properties": {
    "iso:country":"FR",
    "sg:address":"20, Rue Schnapper, 78100 Saint Germain en Laye",
    "sg:orig_category":"Non-Classified Establishments",
    "sg:phone":"+33 1 34 51 72 27",
    "sg:province":"Ile de France",
    "wof:name":"Formatech S.a.r.l.",
    "wof:placetype":"venue"
},
  "geometry": {"coordinates":[2.089719,48.888618],"type":"Point"}
}