{
  "type": "Feature",
  "properties": {
    "addr:full":"Bellevue Pa De Bellevue 71400 Autun Autun Bourgogne 71400",
    "addr:postcode":"71400;71400",
    "iso:country":"FR",
    "sg:address":"Bellevue Pa De Bellevue 71400 Autun",
    "sg:city":"Autun",
    "sg:classifiers":[
        {
            "category":"Building & Trades",
            "subcategory":"Construction",
            "type":"Services"
        }
    ],
    "sg:phone":"+33 3 85 86 92 00",
    "sg:postcode":"71400",
    "sg:province":"Bourgogne",
    "sg:tags":[
        "work",
        "public"
    ],
    "wof:name":"Tracyl",
    "wof:placetype":"venue"
},
  "geometry": {"coordinates":[4.411325,46.902779],"type":"Point"}
}