{
  "type": "Feature",
  "properties": {
    "iso:country":"FR",
    "sg:address":"161 boulevard Gabriel P\u00e9ri 91170 Viry Chatillon",
    "sg:classifiers":[
        {
            "category":"Home & Garden",
            "subcategory":"Furniture",
            "type":"Retail Goods"
        }
    ],
    "sg:phone":"+33 1 69 96 62 00",
    "sg:postcode":"91170",
    "sg:province":"Ile de France",
    "sg:tags":[
        "kitchen"
    ],
    "wof:name":"Electrofroid S.a.",
    "wof:placetype":"venue"
},
  "geometry": {"coordinates":[2.366682,48.674568],"type":"Point"}
}