{
  "type": "Feature",
  "properties": {
    "addr:full":"4 Rue Mal De Lattre De Tassigny Agence Bourgogne-Franche C 71100 Chalon Sur Saone Chalon-sur-Sa\u00f4ne Bourgogne 71100",
    "addr:housenumber":"4;71100",
    "addr:postcode":"71100",
    "addr:street":"Rue Mal De Lattre De Tassigny;Chalon;Saone;Bourgogne",
    "iso:country":"FR",
    "sg:address":"4 Rue Mal De Lattre De Tassigny Agence Bourgogne-Franche C 71100 Chalon Sur Saone",
    "sg:city":"Chalon-sur-Sa\u00f4ne",
    "sg:classifiers":[
        {
            "category":"Travel",
            "subcategory":"Hotels & Motels",
            "type":"Entertainment"
        }
    ],
    "sg:phone":"+33 3 85 43 68 69",
    "sg:postcode":"71100",
    "sg:province":"Bourgogne",
    "sg:tags":[
        "hotels",
        "business",
        "restaurant"
    ],
    "wof:name":"Alsacienne De Restauration D'entreprise",
    "wof:placetype":"venue"
},
  "geometry": {"coordinates":[4.85501,46.779694],"type":"Point"}
}