{
  "type": "Feature",
  "properties": {
    "addr:full":"Rue Emile Guyard Couchey Bourgogne 21160",
    "addr:postcode":"21160",
    "addr:street":"Rue Emile Guyard",
    "iso:country":"FR",
    "sg:address":"Rue Emile Guyard",
    "sg:city":"Couchey",
    "sg:orig_category":"Non-Classified Establishments",
    "sg:phone":"+33 3 80 52 31 08",
    "sg:postcode":"21160",
    "sg:province":"Bourgogne",
    "wof:name":"Imprimerie Jobard - I.f. 2000 S.a.r.l.",
    "wof:placetype":"venue"
},
  "geometry": {"coordinates":[4.996357,47.256744],"type":"Point"}
}