{
  "type": "Feature",
  "properties": {
    "iso:country":"FR",
    "sg:address":"130, Av. de Versailles, 75016 Paris",
    "sg:orig_category":"Unclassifiable Establishments",
    "sg:phone":"+33 1 46 47 50 98",
    "sg:province":"Ile de France",
    "wof:name":"C\u00e9ramis Azulejos S.a.r.l.",
    "wof:placetype":"venue"
},
  "geometry": {"coordinates":[2.267405,48.842121],"type":"Point"}
}