{
  "type": "Feature",
  "properties": {
    "addr:full":"16, Bd Villebois Mareuil, 35000 Rennes Rennes Bretagne 35000",
    "addr:housenumber":"16",
    "addr:postcode":"35000;35000",
    "addr:street":"Bd Villebois Mareuil",
    "iso:country":"FR",
    "sg:address":"16, Bd Villebois Mareuil, 35000 Rennes",
    "sg:city":"Rennes",
    "sg:orig_category":"Non-Classified Establishments",
    "sg:phone":"+33 2 99 27 55 00",
    "sg:postcode":"35000",
    "sg:province":"Bretagne",
    "wof:name":"Roucaire",
    "wof:placetype":"venue"
},
  "geometry": {"coordinates":[-1.652174,48.107857],"type":"Point"}
}