{
  "type": "Feature",
  "properties": {
    "iso:country":"FR",
    "sg:address":"38, Rte Nationale - Les Fontainettes , 60650 Lachapelle aux Pots",
    "sg:orig_category":"Non-Classified Establishments",
    "sg:phone":"+33 3 44 84 25 98",
    "sg:province":"Picardie",
    "wof:name":"S.i.t. S.a. - Soci\u00e9t\u00e9 Internationale Transaction",
    "wof:placetype":"venue"
},
  "geometry": {"coordinates":[2.011019,49.434746],"type":"Point"}
}