{
  "type": "Feature",
  "properties": {
    "addr:full":"77, Rue de la Bo\u00e9tie, 75008 Paris Ile de France",
    "addr:housenumber":"77",
    "addr:postcode":"75008",
    "addr:street":"Rue De La Boe\u0301Tie",
    "iso:country":"FR",
    "sg:address":"77, Rue de la Bo\u00e9tie, 75008 Paris",
    "sg:orig_category":"Non-Classified Establishments",
    "sg:phone":"+33 1 44 20 66 22",
    "sg:province":"Ile de France",
    "wof:name":"Sabre France S.a.r.l.",
    "wof:placetype":"venue"
},
  "geometry": {"coordinates":[2.309547,48.872208],"type":"Point"}
}