{
  "type": "Feature",
  "properties": {
    "addr:full":"B.P. 51, 51202 Epernay C\u00e9dex^^44, All\u00e9e de Cumi\u00e8res, 51202 Epernay C\u00e9dex Champagne",
    "addr:postcode":"51202;51202",
    "addr:street":"B.P. 51;Alle\u0301E De Cumie\u0300Res",
    "iso:country":"FR",
    "sg:address":"B.P. 51, 51202 Epernay C\u00e9dex^^44, All\u00e9e de Cumi\u00e8res, 51202 Epernay C\u00e9dex",
    "sg:orig_category":"Non-Classified Establishments",
    "sg:phone":"+33 3 26 59 86 00",
    "sg:province":"Champagne",
    "wof:name":"C.s.g.v. - Coop\u00e9rative Du Syndicat G\u00e9n\u00e9ral Des Vignerons",
    "wof:placetype":"venue"
},
  "geometry": {"coordinates":[3.95475,49.045197],"type":"Point"}
}