{
  "type": "Feature",
  "properties": {
    "addr:full":"828, Rue Centrale, 01700 Beynost Rhone-Alpes 01700",
    "addr:housenumber":"828",
    "addr:postcode":"01700;01700",
    "addr:street":"Rue Centrale",
    "iso:country":"FR",
    "sg:address":"828, Rue Centrale, 01700 Beynost",
    "sg:orig_category":"Non-Classified Establishments",
    "sg:phone":"+33 4 78 55 57 24",
    "sg:postcode":"01700",
    "sg:province":"Rhone-Alpes",
    "wof:name":"Astruc Christian Alias",
    "wof:placetype":"venue"
},
  "geometry": {"coordinates":[4.996135,45.83876],"type":"Point"}
}