{
  "type": "Feature",
  "properties": {
    "addr:full":"Z.A 63480 VERTOLAYE Vertolaye Auvergne 63480",
    "addr:postcode":"63480;vertolaye;63480",
    "iso:country":"FR",
    "sg:address":"Z.A 63480 VERTOLAYE",
    "sg:city":"Vertolaye",
    "sg:classifiers":[
        {
            "category":"Transit Center",
            "subcategory":"Freight",
            "type":"Transportation"
        }
    ],
    "sg:phone":"+33 4 73 95 27 37",
    "sg:postcode":"63480",
    "sg:province":"Auvergne",
    "sg:tags":[
        "packaging",
        "special"
    ],
    "wof:name":"Blix Sarl",
    "wof:placetype":"venue"
},
  "geometry": {"coordinates":[3.682702,45.618797],"type":"Point"}
}