{
  "type": "Feature",
  "properties": {
    "addr:full":"All Du Petit Paradis 59044 Lille Cedex Nord Pas-de-Calais",
    "addr:postcode":"59044;cedex nord",
    "iso:country":"FR",
    "sg:address":"All Du Petit Paradis 59044 Lille Cedex",
    "sg:classifiers":[
        {
            "category":"Sports & Exercise",
            "subcategory":"Sports Center",
            "type":"Entertainment"
        }
    ],
    "sg:phone":"+33 3 20 54 50 73",
    "sg:province":"Nord Pas-de-Calais",
    "sg:tags":[
        "game"
    ],
    "wof:name":"Losc Lille Metropole-saems",
    "wof:placetype":"venue"
},
  "geometry": {"coordinates":[3.048709,50.645626],"type":"Point"}
}