{
  "type": "Feature",
  "properties": {
    "addr:full":"110, Av. de Verdun, 91520 Egly Ile de France",
    "addr:housenumber":"110",
    "addr:postcode":"91520",
    "addr:street":"Av. De Verdun;Ile De France",
    "iso:country":"FR",
    "sg:address":"110, Av. de Verdun, 91520 Egly",
    "sg:orig_category":"Non-Classified Establishments",
    "sg:phone":"+33 1 64 90 16 04",
    "sg:province":"Ile de France",
    "wof:name":"V.s.l. France S.a.",
    "wof:placetype":"venue"
},
  "geometry": {"coordinates":[2.239107,48.577831],"type":"Point"}
}