{
  "type": "Feature",
  "properties": {
    "addr:full":"28, Rue du Rendez-Vous, 75012 Paris Ile de France",
    "addr:housenumber":"28",
    "addr:postcode":"75012",
    "addr:street":"Rue Du Rendez-Vous",
    "iso:country":"FR",
    "sg:address":"28, Rue du Rendez-Vous, 75012 Paris",
    "sg:orig_category":"Non-Classified Establishments",
    "sg:phone":"+33 1 43 07 57 68",
    "sg:province":"Ile de France",
    "wof:name":"Nicolas S.a.r.l.",
    "wof:placetype":"venue"
},
  "geometry": {"coordinates":[2.403723,48.845581],"type":"Point"}
}