{
  "type": "Feature",
  "properties": {
    "addr:full":"17\u00e8me Rue - 1\u00e8re Avenue 4889 M - LID Carros Provence-Alpes-C\u00f4te d'Azur 06510",
    "addr:housenumber":"4889 m",
    "addr:postcode":"06510",
    "addr:street":"Rue 1E\u0300Re Avenue;Lid Carros",
    "iso:country":"FR",
    "sg:address":"17\u00e8me Rue - 1\u00e8re Avenue 4889 M - LID",
    "sg:city":"Carros",
    "sg:orig_category":"Unclassifiable Establishments",
    "sg:phone":"+33 4 92 08 02 97",
    "sg:postcode":"06510",
    "sg:province":"Provence-Alpes-C\u00f4te d'Azur",
    "wof:name":"Greyston S.a.",
    "wof:placetype":"venue"
},
  "geometry": {"coordinates":[7.203098,43.766811],"type":"Point"}
}