{
  "type": "Feature",
  "properties": {
    "iso:country":"FR",
    "sg:address":"211, Av. Jean Mermoz, 63100 Clermont Ferrand",
    "sg:city":"Clermont-Ferrand",
    "sg:orig_category":"Non-Classified Establishments",
    "sg:phone":"+33 4 73 90 64 75",
    "sg:postcode":"63100",
    "sg:province":"Auvergne",
    "wof:name":"A.c.i. S.a. - Air Cargo International",
    "wof:placetype":"venue"
},
  "geometry": {"coordinates":[3.133555,45.790478],"type":"Point"}
}