{
  "type": "Feature",
  "properties": {
    "addr:full":"1 Bis Rue Des Ec\u00f4les 89400 Migennes Migennes Bourgogne 89400",
    "addr:housenumber":"1 bis",
    "addr:postcode":"89400;89400",
    "addr:street":"Rue Des Eco\u0302Les",
    "iso:country":"FR",
    "sg:address":"1 Bis Rue Des Ec\u00f4les 89400 Migennes",
    "sg:city":"Migennes",
    "sg:classifiers":[
        {
            "category":"Sports & Exercise",
            "subcategory":"Sports Center",
            "type":"Entertainment"
        }
    ],
    "sg:phone":"+33 3 86 80 44 99",
    "sg:postcode":"89400",
    "sg:province":"Bourgogne",
    "sg:tags":[
        "game"
    ],
    "wof:name":"Ass Centr Loisirs Comunote De Commune Du Migennois",
    "wof:placetype":"venue"
},
  "geometry": {"coordinates":[3.521692,47.964897],"type":"Point"}
}