{
  "type": "Feature",
  "properties": {
    "iso:country":"FR",
    "sg:address":"18 bis, Rue des Louveries, 78310 Coigni\u00e8res",
    "sg:orig_category":"Non-Classified Establishments",
    "sg:phone":"+33 1 34 61 37 82",
    "sg:postcode":"78310",
    "sg:province":"Ile de France",
    "wof:name":"Elcea France S.a.",
    "wof:placetype":"venue"
},
  "geometry": {"coordinates":[1.926077,48.752575],"type":"Point"}
}