{
  "type": "Feature",
  "properties": {
    "addr:full":"B.P. 353, 62406 B\u00e9thune C\u00e9dex^^218, Rue Bernard Palissy, 62400 B\u00e9thune Nord Pas-de-Calais 62400",
    "addr:housenumber":"b.p. 353",
    "addr:postcode":"62406;62400;62400",
    "addr:street":"Rue Bernard Palissy",
    "iso:country":"FR",
    "sg:address":"B.P. 353, 62406 B\u00e9thune C\u00e9dex^^218, Rue Bernard Palissy, 62400 B\u00e9thune",
    "sg:orig_category":"Non-Classified Establishments",
    "sg:phone":"+33 3 21 68 04 30",
    "sg:postcode":"62400",
    "sg:province":"Nord Pas-de-Calais",
    "wof:name":"Ateliers De La Nave, S.a.",
    "wof:placetype":"venue"
},
  "geometry": {"coordinates":[2.63787,50.530472],"type":"Point"}
}