{
  "type": "Feature",
  "properties": {
    "addr:full":"B.P. 147, 93403 Saint Ouen C\u00e9dex^^4/8, Quai de Seine, 93400 Saint Ouen Ile de France 93400",
    "addr:housenumber":"b.p. 147;8",
    "addr:postcode":"93403;93400 saint;ile;93400",
    "addr:street":"Quai De Seine;France",
    "iso:country":"FR",
    "sg:address":"B.P. 147, 93403 Saint Ouen C\u00e9dex^^4/8, Quai de Seine, 93400 Saint Ouen",
    "sg:orig_category":"Non-Classified Establishments",
    "sg:phone":"+33 1 49 18 12 30",
    "sg:postcode":"93400",
    "sg:province":"Ile de France",
    "wof:name":"Decasport S.a.",
    "wof:placetype":"venue"
},
  "geometry": {"coordinates":[2.333555,48.911171],"type":"Point"}
}