{
  "type": "Feature",
  "properties": {
    "addr:full":"29 R Amp\u00e8re 69680 Chassieu Rhone-Alpes 69680",
    "addr:housenumber":"29",
    "addr:postcode":"69680;69680",
    "addr:street":"R Ampe\u0300Re",
    "iso:country":"FR",
    "sg:address":"29 R Amp\u00e8re 69680 Chassieu",
    "sg:classifiers":[
        {
            "category":"Manufacturing",
            "subcategory":"Wood Products",
            "type":"Manufacturing & Wholesale Goods"
        }
    ],
    "sg:phone":"+33 4 72 47 20 10",
    "sg:postcode":"69680",
    "sg:province":"Rhone-Alpes",
    "sg:tags":[
        "furniture"
    ],
    "wof:name":"Crozat S A",
    "wof:placetype":"venue"
},
  "geometry": {"coordinates":[4.975898,45.729904],"type":"Point"}
}