{
  "type": "Feature",
  "properties": {
    "addr:full":"5 rue Parmentier 94140 Alfortville Ile de France",
    "addr:housenumber":"5",
    "addr:postcode":"94140;ile",
    "addr:street":"Rue Parmentier",
    "iso:country":"FR",
    "sg:address":"5 rue Parmentier 94140 Alfortville",
    "sg:classifiers":[
        {
            "category":"Wholesale",
            "subcategory":"Hardware",
            "type":"Manufacturing & Wholesale Goods"
        }
    ],
    "sg:phone":"+33 1 49 77 85 37",
    "sg:province":"Ile de France",
    "sg:tags":[
        "inventories",
        "equipment",
        "used",
        "storage",
        "factory"
    ],
    "wof:name":"Invest Commerce Sarl",
    "wof:placetype":"venue"
},
  "geometry": {"coordinates":[2.411894,48.80706],"type":"Point"}
}