{
  "type": "Feature",
  "properties": {
    "addr:full":"373 Rue Des Pyrenees Paris Ile de France 75020",
    "addr:housenumber":"373",
    "addr:postcode":"75020",
    "addr:street":"Rue Des Pyrenees",
    "iso:country":"FR",
    "sg:address":"373 Rue Des Pyrenees",
    "sg:city":"Paris",
    "sg:classifiers":[
        {
            "category":"Banks & Credit Unions",
            "subcategory":"Financial Services",
            "type":"Services"
        }
    ],
    "sg:phone":"+33 1 44 62 83 83",
    "sg:postcode":"75020",
    "sg:province":"Ile de France",
    "sg:tags":[
        "banking",
        "finance",
        "insurance"
    ],
    "wof:name":"Union De Banques A Paris (ubp)",
    "wof:placetype":"venue"
},
  "geometry": {"coordinates":[2.389808,48.87339],"type":"Point"}
}