{
  "type": "Feature",
  "properties": {
    "addr:full":"13 Rue Chateau D Angleterre 67300 Schiltigheim Schiltigheim Alsace 67300",
    "addr:housenumber":"13",
    "addr:postcode":"67300;67300",
    "addr:street":"Rue Chateau D Angleterre",
    "iso:country":"FR",
    "sg:address":"13 Rue Chateau D Angleterre 67300 Schiltigheim",
    "sg:city":"Schiltigheim",
    "sg:classifiers":[
        {
            "category":"Professional",
            "subcategory":"Business Services",
            "type":"Services"
        }
    ],
    "sg:phone":"+33 3 88 62 80 49",
    "sg:postcode":"67300",
    "sg:province":"Alsace",
    "sg:tags":[
        "information",
        "advice",
        "technology",
        "software"
    ],
    "wof:name":"Bull Sa",
    "wof:placetype":"venue"
},
  "geometry": {"coordinates":[7.774617,48.623932],"type":"Point"}
}