{
  "type": "Feature",
  "properties": {
    "iso:country":"FR",
    "sg:address":"Zi Du Capiscol",
    "sg:city":"Joliot Curie 34500 B\u00e9ziers",
    "sg:classifiers":[
        {
            "category":"Professional",
            "subcategory":"Engineering",
            "type":"Services"
        }
    ],
    "sg:phone":"+33 4 67 76 46 65",
    "sg:postcode":"34500",
    "sg:province":"Languedoc-Roussillon",
    "sg:tags":[
        "machine",
        "-",
        "mechanical"
    ],
    "wof:name":"Societe Des Etablissements Criballet Sarl",
    "wof:placetype":"venue"
},
  "geometry": {"coordinates":[3.216105,43.344234],"type":"Point"}
}