{
  "type": "Feature",
  "properties": {
    "addr:full":"32, Rue Alexandre Dumas, 75543 Paris C\u00e9dex 11 \u00cele-de-France",
    "addr:housenumber":"32",
    "addr:postcode":"75543",
    "addr:street":"Rue Alexandre Dumas",
    "iso:country":"FR",
    "sg:address":"32, Rue Alexandre Dumas, 75543 Paris C\u00e9dex 11",
    "sg:orig_category":"Non-Classified Establishments",
    "sg:phone":"+33 1 43 56 59 59",
    "sg:province":"\u00cele-de-France",
    "wof:name":"Soci\u00e9t\u00e9 Des Editions Et Protection Route S.a.",
    "wof:placetype":"venue"
},
  "geometry": {"coordinates":[2.391895,48.853271],"type":"Point"}
}