{
  "type": "Feature",
  "properties": {
    "addr:full":"L'hermitage Zone Industrielle 44151 ANCENIS CEDEX Aquitaine",
    "addr:postcode":"44151",
    "addr:street":"Zone Industrielle",
    "iso:country":"FR",
    "sg:address":"L'hermitage Zone Industrielle 44151 ANCENIS CEDEX",
    "sg:classifiers":[
        {
            "category":"Fast Food",
            "type":"Food & Drink"
        }
    ],
    "sg:phone":"+33 2 51 14 23 64",
    "sg:province":"Aquitaine",
    "sg:tags":[
        "egg",
        "powder"
    ],
    "wof:name":"Epi Ingredients Sas",
    "wof:placetype":"venue"
},
  "geometry": {"coordinates":[-1.17886,47.370411],"type":"Point"}
}