{
  "type": "Feature",
  "properties": {
    "addr:full":"64, Rue Vergniaud, 75013 Paris Ile de France",
    "addr:housenumber":"64",
    "addr:postcode":"75013",
    "addr:street":"Rue Vergniaud",
    "iso:country":"FR",
    "sg:address":"64, Rue Vergniaud, 75013 Paris",
    "sg:orig_category":"Unclassifiable Establishments",
    "sg:phone":"+33 1 45 80 91 15",
    "sg:province":"Ile de France",
    "wof:name":"Atelier Cler",
    "wof:placetype":"venue"
},
  "geometry": {"coordinates":[2.344479,48.824547],"type":"Point"}
}