{
  "type": "Feature",
  "properties": {
    "addr:full":"Le Ronzy Bourg de Thizy Rhone-Alpes 69240",
    "addr:postcode":"69240",
    "addr:street":"Bourg De Thizy Rhone-Alpes",
    "iso:country":"FR",
    "sg:address":"Le Ronzy",
    "sg:city":"Bourg de Thizy",
    "sg:orig_category":"Unclassifiable Establishments",
    "sg:phone":"+33 4 74 13 85 40",
    "sg:postcode":"69240",
    "sg:province":"Rhone-Alpes",
    "wof:name":"Teinture Du Ronzy S.a.",
    "wof:placetype":"venue"
},
  "geometry": {"coordinates":[4.30456,46.04718],"type":"Point"}
}