{
  "type": "Feature",
  "properties": {
    "addr:full":"Rte De Salbris 18330 Nan\u00e7ay Nan\u00e7ay Centre 18330",
    "addr:housenumber":"nanc\u0327ay",
    "addr:postcode":"18330;18330",
    "addr:street":"Rte De Salbris",
    "iso:country":"FR",
    "sg:address":"Rte De Salbris 18330 Nan\u00e7ay",
    "sg:city":"Nan\u00e7ay",
    "sg:classifiers":[
        {
            "category":"Farming",
            "subcategory":"Livestock Farm",
            "type":"Manufacturing & Wholesale Goods"
        }
    ],
    "sg:phone":"+33 2 48 51 80 71",
    "sg:postcode":"18330",
    "sg:province":"Centre",
    "sg:tags":[
        "breeding",
        "agriculture",
        "animal"
    ],
    "wof:name":"Covi Sologne Perigord",
    "wof:placetype":"venue"
},
  "geometry": {"coordinates":[2.195018,47.349945],"type":"Point"}
}