{
  "type": "Feature",
  "properties": {
    "iso:country":"FR",
    "sg:address":"11 Rue Du Moulin 67270 Wilwisheim",
    "sg:city":"Wilwisheim",
    "sg:classifiers":[
        {
            "category":"Farming",
            "subcategory":"Farm & Veterinary Services",
            "type":"Manufacturing & Wholesale Goods"
        }
    ],
    "sg:phone":"+33 3 88 02 20 92",
    "sg:postcode":"67270",
    "sg:province":"Alsace",
    "sg:tags":[
        "food",
        "product",
        "breeding",
        "animal",
        "related"
    ],
    "wof:name":"Afc Sanders Sa",
    "wof:placetype":"venue"
},
  "geometry": {"coordinates":[7.513251,48.74786],"type":"Point"}
}