{
  "type": "Feature",
  "properties": {
    "iso:country":"FR",
    "sg:address":"14, Rue du Ferraillon, 83570 Montfort sur Argens",
    "sg:orig_category":"Non-Classified Establishments",
    "sg:phone":"+33 4 94 59 59 14",
    "sg:province":"Midi Pyr\u00e9n\u00e9es",
    "wof:name":"Rucher Notre Dame De Gr\u00e2ces",
    "wof:placetype":"venue"
},
  "geometry": {"coordinates":[6.125903,43.472431],"type":"Point"}
}