{
  "type": "Feature",
  "properties": {
    "addr:full":"26, Rte de Nantes, 78240 Chambourcy Ile de France",
    "addr:housenumber":"26",
    "addr:postcode":"78240;ile",
    "addr:street":"Rte De Nantes",
    "iso:country":"FR",
    "sg:address":"26, Rte de Nantes, 78240 Chambourcy",
    "sg:orig_category":"Unclassifiable Establishments",
    "sg:phone":"+33 1 30 06 39 69",
    "sg:province":"Ile de France",
    "wof:name":"Egli Cit\u00e9 Nature S.a.r.l.",
    "wof:placetype":"venue"
},
  "geometry": {"coordinates":[2.038427,48.907097],"type":"Point"}
}