{
  "type": "Feature",
  "properties": {
    "addr:full":"Rue du 18 Juin - ZAC de Beaulieu Puilboreau Poitou-Charentes 17138",
    "addr:postcode":"puilboreau;17138",
    "addr:street":"Rue Du 18 Juin Zac De Beaulieu",
    "iso:country":"FR",
    "sg:address":"Rue du 18 Juin - ZAC de Beaulieu",
    "sg:city":"Puilboreau",
    "sg:orig_category":"Non-Classified Establishments",
    "sg:phone":"+33 5 46 68 15 30",
    "sg:postcode":"17138",
    "sg:province":"Poitou-Charentes",
    "wof:name":"B.m.i.n.i. S.a. - Bureau Moderne Informatique Et N\u00e9goce Interprofessionnel",
    "wof:placetype":"venue"
},
  "geometry": {"coordinates":[-1.107864,46.176586],"type":"Point"}
}