{
  "type": "Feature",
  "properties": {
    "addr:full":"115 Av Du Medoc 33320 Eysines Eysines Aquitaine 33320",
    "addr:postcode":"33320;33320",
    "addr:street":"115 Av Du Medoc",
    "iso:country":"FR",
    "sg:address":"115 Av Du Medoc 33320 Eysines",
    "sg:city":"Eysines",
    "sg:classifiers":[
        {
            "category":"Professional",
            "type":"Services"
        }
    ],
    "sg:phone":"+33 5 56 28 14 83",
    "sg:postcode":"33320",
    "sg:province":"Aquitaine",
    "sg:tags":[
        "transport",
        "road"
    ],
    "wof:name":"Transports Didier Daunis Sarl",
    "wof:placetype":"venue"
},
  "geometry": {"coordinates":[-0.643863,44.888077],"type":"Point"}
}