{
  "type": "Feature",
  "properties": {
    "addr:full":"128 de Lattre de Tassigny 87000 Limoges Limousin 87000",
    "addr:housenumber":"128",
    "addr:postcode":"87000;87000",
    "addr:street":"De Lattre De Tassigny",
    "iso:country":"FR",
    "sg:address":"128",
    "sg:city":"de Lattre de Tassigny 87000 Limoges",
    "sg:classifiers":[
        {
            "category":"Utilities",
            "subcategory":"Electric",
            "type":"Services"
        }
    ],
    "sg:phone":"+33 5 55 06 74 74",
    "sg:postcode":"87000",
    "sg:province":"Limousin",
    "sg:tags":[
        "telecommunication",
        "electricity",
        "component",
        "equipment",
        "electrical",
        "electronic"
    ],
    "wof:name":"Legrand",
    "wof:placetype":"venue"
},
  "geometry": {"coordinates":[1.278331,45.825291],"type":"Point"}
}