{
  "type": "Feature",
  "properties": {
    "addr:full":"15 R De Margnant 75008 Paris Ile de France 75008",
    "addr:housenumber":"15",
    "addr:postcode":"75008;75008",
    "addr:street":"R De Margnant",
    "iso:country":"FR",
    "sg:address":"15 R De Margnant 75008 Paris",
    "sg:orig_category":"Clothes Jewellery Miscellaneous Products Textiles and Clothing",
    "sg:phone":"+33 1 42 56 29 84",
    "sg:postcode":"75008",
    "sg:province":"Ile de France",
    "wof:name":"Daniel Swarovski Sa",
    "wof:placetype":"venue"
},
  "geometry": {"coordinates":[2.306111,48.868626],"type":"Point"}
}