{
  "type": "Feature",
  "properties": {
    "iso:country":"FR",
    "sg:address":"Rte de Valence - Caderousse",
    "sg:city":"Noyarey",
    "sg:orig_category":"Non-Classified Establishments",
    "sg:phone":"+33 4 76 53 99 99",
    "sg:postcode":"38360",
    "sg:province":"Rhone-Alpes",
    "wof:name":"I.s.e.a. France S.a.",
    "wof:placetype":"venue"
},
  "geometry": {"coordinates":[5.662875,45.206551],"type":"Point"}
}