{
  "type": "Feature",
  "properties": {
    "addr:full":"9, Rue du Stade, 70270 M\u00e9lisey Franche Comt\u00e9",
    "addr:housenumber":"9",
    "addr:postcode":"70270",
    "addr:street":"Rue Du Stade;Franche Comte\u0301",
    "iso:country":"FR",
    "sg:address":"9, Rue du Stade, 70270 M\u00e9lisey",
    "sg:orig_category":"Unclassifiable Establishments",
    "sg:phone":"+33 3 84 20 84 12",
    "sg:province":"Franche Comt\u00e9",
    "wof:name":"Transports Pierrat S.a.r.l.",
    "wof:placetype":"venue"
},
  "geometry": {"coordinates":[6.565392,47.750214],"type":"Point"}
}