{
  "type": "Feature",
  "properties": {
    "addr:full":"Rue du 19 Mars 1962 B\u00e9gadan Aquitaine 33340",
    "addr:housenumber":"be\u0301gadan",
    "addr:postcode":"33340",
    "addr:street":"Rue Du 19 Mars 1962",
    "iso:country":"FR",
    "sg:address":"Rue du 19 Mars 1962",
    "sg:city":"B\u00e9gadan",
    "sg:orig_category":"Non-Classified Establishments",
    "sg:phone":"+33 5 56 41 50 18",
    "sg:postcode":"33340",
    "sg:province":"Aquitaine",
    "wof:name":"Ch\u00e2teau Patache D'aux S.a.",
    "wof:placetype":"venue"
},
  "geometry": {"coordinates":[-0.893124,45.357491],"type":"Point"}
}