{
  "type": "Feature",
  "properties": {
    "addr:full":"B.P. 82, 49071 Beaucouz\u00e9 C\u00e9dex^^2, Rue du Pavillon, 49070 Beaucouz\u00e9 Pays de Loire",
    "addr:postcode":"49071;49070",
    "addr:street":"B.P. 82;Rue Du Pavillon",
    "iso:country":"FR",
    "sg:address":"B.P. 82, 49071 Beaucouz\u00e9 C\u00e9dex^^2, Rue du Pavillon, 49070 Beaucouz\u00e9",
    "sg:orig_category":"Non-Classified Establishments",
    "sg:phone":"+33 2 41 36 60 00",
    "sg:province":"Pays de Loire",
    "wof:name":"Spie - Trindel S.a.",
    "wof:placetype":"venue"
},
  "geometry": {"coordinates":[-0.658364,47.45779],"type":"Point"}
}