{
  "type": "Feature",
  "properties": {
    "addr:full":"24, Rue de la Chasse Verte, 50100 Cherbourg Cherbourg-Octeville Basse Normandie 50100",
    "addr:housenumber":"24",
    "addr:postcode":"50100;50100",
    "addr:street":"Rue De La Chasse Verte",
    "iso:country":"FR",
    "sg:address":"24, Rue de la Chasse Verte, 50100 Cherbourg",
    "sg:city":"Cherbourg-Octeville",
    "sg:orig_category":"Non-Classified Establishments",
    "sg:phone":"+33 2 33 44 22 22",
    "sg:postcode":"50100",
    "sg:province":"Basse Normandie",
    "wof:name":"S.m.a.n.c.o. S.a. - Soci\u00e9t\u00e9 Mutuelle D'abattage Du Nord Cotentin",
    "wof:placetype":"venue"
},
  "geometry": {"coordinates":[-1.616124,49.640484],"type":"Point"}
}