{
  "type": "Feature",
  "properties": {
    "addr:full":"29, Rue de la Pannerie, 59840 P\u00e9renchies Nord Pas-de-Calais",
    "addr:housenumber":"29",
    "addr:postcode":"59840",
    "addr:street":"Rue De La Pannerie",
    "iso:country":"FR",
    "sg:address":"29, Rue de la Pannerie, 59840 P\u00e9renchies",
    "sg:orig_category":"Unclassifiable Establishments",
    "sg:phone":"+33 3 20 08 09 80",
    "sg:province":"Nord Pas-de-Calais",
    "wof:name":"Source Saint L\u00e9ger S.a.",
    "wof:placetype":"venue"
},
  "geometry": {"coordinates":[2.96583,50.669693],"type":"Point"}
}