{
  "type": "Feature",
  "properties": {
    "addr:full":"20 Rue De La Plaine Des Isles 89470 Moneteau Mon\u00e9teau Bourgogne 89470",
    "addr:housenumber":"20",
    "addr:postcode":"89470;89470",
    "addr:street":"Rue De La Plaine Des",
    "iso:country":"FR",
    "sg:address":"20 Rue De La Plaine Des Isles 89470 Moneteau",
    "sg:city":"Mon\u00e9teau",
    "sg:classifiers":[
        {
            "category":"Professional",
            "subcategory":"Printing & Photocopies",
            "type":"Services"
        }
    ],
    "sg:phone":"+33 3 86 46 96 76",
    "sg:postcode":"89470",
    "sg:province":"Bourgogne",
    "sg:tags":[
        "machine",
        "engineering",
        "-",
        "mechanical"
    ],
    "wof:name":"Mm Packaging France (mmp France)",
    "wof:placetype":"venue"
},
  "geometry": {"coordinates":[3.578225,47.829414],"type":"Point"}
}