{
  "type": "Feature",
  "properties": {
    "addr:full":"127 Cour Caffarelli 14120 Mondeville Mondeville Basse Normandie 14120",
    "addr:housenumber":"127",
    "addr:postcode":"14120;14120",
    "addr:street":"Cour Caffarelli;Basse",
    "iso:country":"FR",
    "sg:address":"127 Cour Caffarelli 14120 Mondeville",
    "sg:city":"Mondeville",
    "sg:classifiers":[
        {
            "category":"Professional",
            "subcategory":"Engineering",
            "type":"Services"
        }
    ],
    "sg:phone":"+33 2 31 34 86 80",
    "sg:postcode":"14120",
    "sg:province":"Basse Normandie",
    "sg:tags":[
        "machine",
        "-",
        "mechanical"
    ],
    "wof:name":"Someve Sa (someve)",
    "wof:placetype":"venue"
},
  "geometry": {"coordinates":[-0.334069,49.180222],"type":"Point"}
}