{
  "type": "Feature",
  "properties": {
    "addr:full":"La B\u00e9chardi\u00e8re 35250 Saint Germain sur Ille Chasn\u00e9-sur-Illet Bretagne 35250",
    "addr:postcode":"35250;35250",
    "addr:street":"Germain;Chasne\u0301-Sur-Illet Bretagne",
    "iso:country":"FR",
    "sg:address":"La B\u00e9chardi\u00e8re 35250 Saint Germain sur Ille",
    "sg:city":"Chasn\u00e9-sur-Illet",
    "sg:orig_category":"Non-Classified Establishments",
    "sg:phone":"+33 2 99 55 41 41",
    "sg:postcode":"35250",
    "sg:province":"Bretagne",
    "wof:name":"Bicha S.a.r.l. - Bureau D'ing\u00e9nieurs Conseils En Hydraulique Et Am",
    "wof:placetype":"venue"
},
  "geometry": {"coordinates":[-1.652549,48.248516],"type":"Point"}
}