{
  "type": "Feature",
  "properties": {
    "addr:full":"Za Franqueville 24290 Montignac Montignac Aquitaine 24290",
    "addr:postcode":"24290;24290",
    "addr:street":"Za Franqueville",
    "iso:country":"FR",
    "sg:address":"Za Franqueville 24290 Montignac",
    "sg:city":"Montignac",
    "sg:classifiers":[
        {
            "category":"Manufacturing",
            "subcategory":"Printing",
            "type":"Manufacturing & Wholesale Goods"
        }
    ],
    "sg:phone":"+33 5 53 51 97 29",
    "sg:postcode":"24290",
    "sg:province":"Aquitaine",
    "sg:tags":[
        "publishing"
    ],
    "wof:name":"Sfc Ste Fran\u00c7aise De Continu",
    "wof:placetype":"venue"
},
  "geometry": {"coordinates":[1.160975,45.065845],"type":"Point"}
}