{
  "type": "Feature",
  "properties": {
    "addr:full":"Zi Du Puy Nardon 85290 Mortagne Sur S\u00e8vre Pays de Loire 85290",
    "addr:postcode":"85290;85290",
    "addr:street":"Zi Du Puy Nardon;Se\u0300Vre",
    "iso:country":"FR",
    "sg:address":"Zi Du Puy Nardon 85290 Mortagne Sur S\u00e8vre",
    "sg:classifiers":[
        {
            "category":"Professional",
            "subcategory":"Engineering",
            "type":"Services"
        }
    ],
    "sg:phone":"+33 2 51 63 02 72",
    "sg:postcode":"85290",
    "sg:province":"Pays de Loire",
    "sg:tags":[
        "-",
        "household",
        "appliance",
        "machine",
        "equipment",
        "electrical",
        "mechanical",
        "electronic"
    ],
    "wof:name":"Dynamic",
    "wof:placetype":"venue"
},
  "geometry": {"coordinates":[-0.953982,46.994831],"type":"Point"}
}