{
  "type": "Feature",
  "properties": {
    "iso:country":"FR",
    "sg:address":"33330 Vignonet",
    "sg:city":"Vignonet",
    "sg:orig_category":"Unclassifiable Establishments",
    "sg:phone":"+33 5 57 84 53 15",
    "sg:postcode":"33330",
    "sg:province":"Aquitaine",
    "wof:name":"Moulin Des Graves E.a.r.l.",
    "wof:placetype":"venue"
},
  "geometry": {"coordinates":[-0.148079,44.848289],"type":"Point"}
}