{
  "type": "Feature",
  "properties": {
    "addr:full":"40 B Avenue Carnot 42300 Roanne Rhone-Alpes 42300",
    "addr:housenumber":"40",
    "addr:postcode":"42300;42300",
    "addr:street":"B Avenue Carnot;Rhone-Alpes",
    "iso:country":"FR",
    "sg:address":"40 B Avenue Carnot 42300 Roanne",
    "sg:classifiers":[
        {
            "category":"Shopping",
            "subcategory":"Clothing, Apparel, & Fashions",
            "type":"Retail Goods"
        }
    ],
    "sg:phone":"+33 4 77 23 31 82",
    "sg:postcode":"42300",
    "sg:province":"Rhone-Alpes",
    "sg:tags":[
        "textile",
        "clothing",
        "clothes"
    ],
    "wof:name":"Tom Et Julie Confection",
    "wof:placetype":"venue"
},
  "geometry": {"coordinates":[4.070006,46.041721],"type":"Point"}
}