{
  "type": "Feature",
  "properties": {
    "iso:country":"FR",
    "sg:address":"Rue de Buray - ZI de Buray",
    "sg:city":"Mer",
    "sg:orig_category":"Unclassifiable Establishments",
    "sg:phone":"+33 2 54 81 08 32",
    "sg:postcode":"41500",
    "sg:province":"Centre",
    "wof:name":"Sillinger S.a.",
    "wof:placetype":"venue"
},
  "geometry": {"coordinates":[1.431871,47.654369],"type":"Point"}
}