{
  "type": "Feature",
  "properties": {
    "iso:country":"FR",
    "sg:address":"289, Rue Saint Denis, 75002 Paris",
    "sg:orig_category":"Non-Classified Establishments",
    "sg:phone":"+33 1 42 33 10 24",
    "sg:postcode":"75002",
    "sg:province":"Ile de France",
    "wof:name":"Etablissements Albert B\u00e9har S.a.",
    "wof:placetype":"venue"
},
  "geometry": {"coordinates":[2.352136,48.869194],"type":"Point"}
}