{
  "type": "Feature",
  "properties": {
    "iso:country":"FR",
    "sg:address":"9, Rue du Stade, 85130 Les Landes Genusson",
    "sg:orig_category":"Unclassifiable Establishments",
    "sg:phone":"+33 2 51 61 61 60",
    "sg:province":"Pays de Loire",
    "wof:name":"Etablissements Rieker Gaborieau S.a.",
    "wof:placetype":"venue"
},
  "geometry": {"coordinates":[-1.122494,46.967686],"type":"Point"}
}