{
  "type": "Feature",
  "properties": {
    "addr:full":"34 rue Principale 49123 LE FRESNE SUR LOIRE Pays de Loire 49123",
    "addr:housenumber":"34",
    "addr:postcode":"49123;49123",
    "addr:street":"Rue Principale;Fresne;Loire",
    "iso:country":"FR",
    "sg:address":"34 rue Principale 49123 LE FRESNE SUR LOIRE",
    "sg:classifiers":[
        {
            "category":"Recreation",
            "subcategory":"Fishing",
            "type":"Entertainment"
        }
    ],
    "sg:phone":"+33 2 41 39 40 06",
    "sg:postcode":"49123",
    "sg:province":"Pays de Loire",
    "sg:tags":[
        "equipment"
    ],
    "wof:name":"Rg France Si",
    "wof:placetype":"venue"
},
  "geometry": {"coordinates":[-0.926107,47.400471],"type":"Point"}
}