{
  "type": "Feature",
  "properties": {
    "iso:country":"FR",
    "sg:address":"63, Rue Mass\u00e9na, 59200 Tourcoing",
    "sg:orig_category":"Non-Classified Establishments",
    "sg:phone":"+33 3 20 26 65 17",
    "sg:province":"Nord Pas-de-Calais",
    "wof:name":"Fils Mode Haese S.a.r.l.",
    "wof:placetype":"venue"
},
  "geometry": {"coordinates":[3.160825,50.712891],"type":"Point"}
}