{
  "type": "Feature",
  "properties": {
    "iso:country":"FR",
    "sg:address":"4 Rue Saint-Guillaume 22000 St Brieuc",
    "sg:city":"Saint-Brieuc",
    "sg:classifiers":[
        {
            "category":"Shopping",
            "subcategory":"Clothing, Apparel, & Fashions",
            "type":"Retail Goods"
        }
    ],
    "sg:phone":"+33 2 96 33 18 20",
    "sg:postcode":"22000",
    "sg:province":"Bretagne",
    "sg:tags":[
        "textile",
        "clothing",
        "clothes"
    ],
    "wof:name":"Sporlux Sarl",
    "wof:placetype":"venue"
},
  "geometry": {"coordinates":[-2.760775,48.513889],"type":"Point"}
}