{
  "type": "Feature",
  "properties": {
    "iso:country":"FR",
    "sg:address":"47, Rte de Lapoutroie, 68240 Kaysersberg",
    "sg:city":"Kaysersberg",
    "sg:orig_category":"Unclassifiable Establishments",
    "sg:phone":"+33 3 89 47 14 00",
    "sg:postcode":"68240",
    "sg:province":"Alsace",
    "wof:name":"Printek S.a.",
    "wof:placetype":"venue"
},
  "geometry": {"coordinates":[7.250299,48.148167],"type":"Point"}
}