{
  "type": "Feature",
  "properties": {
    "addr:full":"Lieu-Dit La Plaine 42240 ST PAUL EN CORNILLON Rhone-Alpes 42240",
    "addr:postcode":"42240;42240",
    "addr:street":"Lieu-Dit La Plaine;Rhone-Alpes",
    "iso:country":"FR",
    "sg:address":"Lieu-Dit La Plaine 42240 ST PAUL EN CORNILLON",
    "sg:orig_category":"Ladies' Trousers Suits, Suits, Jackets, Skirts, And Trousers",
    "sg:phone":"+33 4 77 35 75 37",
    "sg:postcode":"42240",
    "sg:province":"Rhone-Alpes",
    "wof:name":"Ste Nouv Teint De La Paix Sntp S.a.",
    "wof:placetype":"venue"
},
  "geometry": {"coordinates":[4.261915,45.399975],"type":"Point"}
}