{
  "type": "Feature",
  "properties": {
    "iso:country":"FR",
    "sg:address":"3 rue du Maine 38070 ST QUENTIN FALLAVIER",
    "sg:classifiers":[
        {
            "category":"Food & Beverages",
            "subcategory":"Meat & Fish",
            "type":"Retail Goods"
        }
    ],
    "sg:phone":"+33 4 74 94 23 53",
    "sg:postcode":"38070",
    "sg:province":"Rhone-Alpes",
    "sg:tags":[
        "sausage",
        "cured",
        "product",
        "dried"
    ],
    "wof:name":"Popy Sas",
    "wof:placetype":"venue"
},
  "geometry": {"coordinates":[5.119373,45.642597],"type":"Point"}
}