{
  "type": "Feature",
  "properties": {
    "addr:full":"691, Chemin de la Rose, 13100 Aix en Provence Nord Pas-de-Calais",
    "addr:housenumber":"691",
    "addr:postcode":"13100",
    "addr:street":"Chemin De La Rose;En Provence Nord",
    "iso:country":"FR",
    "sg:address":"691, Chemin de la Rose, 13100 Aix en Provence",
    "sg:orig_category":"Non-Classified Establishments",
    "sg:phone":"+33 4 42 23 13 65",
    "sg:province":"Nord Pas-de-Calais",
    "wof:name":"B.v.a. S.a.r.l. - B\u00e9ton Vibre Aixois",
    "wof:placetype":"venue"
},
  "geometry": {"coordinates":[5.45624,43.559238],"type":"Point"}
}