{
  "type": "Feature",
  "properties": {
    "iso:country":"FR",
    "sg:address":"72 ave Henri Barbusse; Paris; 93700",
    "sg:classifiers":[
        {
            "category":"Banks & Credit Unions",
            "subcategory":"Bank",
            "type":"Services"
        }
    ],
    "sg:phone":"+33 1 48 96 07 70",
    "sg:postcode":"93700",
    "sg:province":"Ile de France",
    "wof:name":"Caisse D'epargne, Ile De France Paris",
    "wof:placetype":"venue"
},
  "geometry": {"coordinates":[2.447048,48.917599],"type":"Point"}
}