{
  "type": "Feature",
  "properties": {
    "addr:full":"21 rue Gaston Monmousseau 95190 Goussainville Ile de France",
    "addr:housenumber":"21",
    "addr:postcode":"95190",
    "addr:street":"Rue Gaston Monmousseau",
    "iso:country":"FR",
    "sg:address":"21 rue Gaston Monmousseau 95190 Goussainville",
    "sg:classifiers":[
        {
            "category":"Shopping",
            "subcategory":"Stationery & Office Supplies",
            "type":"Retail Goods"
        }
    ],
    "sg:phone":"+33 1 39 88 02 04",
    "sg:province":"Ile de France",
    "sg:tags":[
        "packaging"
    ],
    "wof:name":"Sopac M\u00e9dical",
    "wof:placetype":"venue"
},
  "geometry": {"coordinates":[2.443909,49.018734],"type":"Point"}
}