{
  "type": "Feature",
  "properties": {
    "addr:full":"3, Rue Pierre Amys, 35000 Rennes Rennes Bretagne 35000",
    "addr:housenumber":"3",
    "addr:postcode":"35000;35000",
    "addr:street":"Rue Pierre Amys",
    "iso:country":"FR",
    "sg:address":"3, Rue Pierre Amys, 35000 Rennes",
    "sg:city":"Rennes",
    "sg:orig_category":"Non-Classified Establishments",
    "sg:phone":"+33 2 99 27 77 51",
    "sg:postcode":"35000",
    "sg:province":"Bretagne",
    "wof:name":"L'etiquetage Rationnel Bretagne S.a.",
    "wof:placetype":"venue"
},
  "geometry": {"coordinates":[-1.654897,48.107258],"type":"Point"}
}