{
  "type": "Feature",
  "properties": {
    "addr:full":"B.P. 50209, 44202 Nantes C\u00e9dex 02^^17, Bd Gaston Doumergue, 44200 Nantes Pays de Loire 44200",
    "addr:housenumber":"02;^ 17",
    "addr:postcode":"44202;44200;44200",
    "addr:street":"^;Bd Gaston Doumergue",
    "iso:country":"FR",
    "sg:address":"B.P. 50209, 44202 Nantes C\u00e9dex 02^^17, Bd Gaston Doumergue, 44200 Nantes",
    "sg:orig_category":"Non-Classified Establishments",
    "sg:phone":"+33 2 51 88 32 32",
    "sg:postcode":"44200",
    "sg:province":"Pays de Loire",
    "wof:name":"Compagnie Saupiquet S.a.",
    "wof:placetype":"venue"
},
  "geometry": {"coordinates":[-1.55206,47.199429],"type":"Point"}
}