{
  "type": "Feature",
  "properties": {
    "addr:full":"46, Bd Jules Vernes, 44300 Nantes Pays de Loire",
    "addr:housenumber":"46",
    "addr:postcode":"44300",
    "addr:street":"Bd Jules Vernes",
    "iso:country":"FR",
    "sg:address":"46, Bd Jules Vernes, 44300 Nantes",
    "sg:orig_category":"Unclassifiable Establishments",
    "sg:phone":"+33 2 51 89 74 74",
    "sg:province":"Pays de Loire",
    "wof:name":"C.r.i.t. Int\u00e9rim S.a.",
    "wof:placetype":"venue"
},
  "geometry": {"coordinates":[-1.533034,47.236992],"type":"Point"}
}