{
  "type": "Feature",
  "properties": {
    "addr:full":"10, Rue du Bellay, 49410 La Chapelle Saint Florent Pays de Loire",
    "addr:housenumber":"10",
    "addr:postcode":"49410;florent",
    "addr:street":"Rue Du Bellay",
    "iso:country":"FR",
    "sg:address":"10, Rue du Bellay, 49410 La Chapelle Saint Florent",
    "sg:orig_category":"Unclassifiable Establishments",
    "sg:phone":"+33 2 41 22 17 17",
    "sg:province":"Pays de Loire",
    "wof:name":"Les Fils De R. Ch\u00e9n\u00e9 Vincent S.a.",
    "wof:placetype":"venue"
},
  "geometry": {"coordinates":[-1.063829,47.33643],"type":"Point"}
}