{
  "type": "Feature",
  "properties": {
    "iso:country":"FR",
    "sg:address":"chemin du Clos Lapierre 52100 St Dizier",
    "sg:classifiers":[
        {
            "category":"Government",
            "subcategory":"Post Office",
            "type":"Public Place"
        }
    ],
    "sg:phone":"+33 3 25 05 63 38",
    "sg:postcode":"52100",
    "sg:province":"Champagne",
    "sg:tags":[
        "machine",
        "part"
    ],
    "wof:name":"Evinox Sa",
    "wof:placetype":"venue"
},
  "geometry": {"coordinates":[4.95437,48.647224],"type":"Point"}
}