{
  "type": "Feature",
  "properties": {
    "addr:full":"Chevalier St Georges 75001 Paris Ile de France 75001",
    "addr:postcode":"75001;75001",
    "addr:street":"Chevalier St",
    "iso:country":"FR",
    "sg:address":"Chevalier St Georges 75001 Paris",
    "sg:classifiers":[
        {
            "category":"Shopping",
            "subcategory":"Clothing, Apparel, & Fashions",
            "type":"Retail Goods"
        }
    ],
    "sg:phone":"+33 1 42 60 13 49",
    "sg:postcode":"75001",
    "sg:province":"Ile de France",
    "sg:tags":[
        "textile",
        "clothing",
        "clothes"
    ],
    "wof:name":"Claude Patrick",
    "wof:placetype":"venue"
},
  "geometry": {"coordinates":[2.32492,48.868496],"type":"Point"}
}