{
  "type": "Feature",
  "properties": {
    "addr:full":"980 Rue Ampere 13793 Aix En Provence Cedex 3 Nord Pas-de-Calais",
    "addr:housenumber":"980;3",
    "addr:postcode":"13793",
    "addr:street":"Rue Ampere",
    "iso:country":"FR",
    "sg:address":"980 Rue Ampere 13793 Aix En Provence Cedex 3",
    "sg:classifiers":[
        {
            "category":"Building & Trades",
            "subcategory":"Construction",
            "type":"Services"
        }
    ],
    "sg:phone":"+33 4 42 37 26 00",
    "sg:province":"Nord Pas-de-Calais",
    "sg:tags":[
        "work",
        "public"
    ],
    "wof:name":"Dumez Mediterranee",
    "wof:placetype":"venue"
},
  "geometry": {"coordinates":[5.4542,43.52494],"type":"Point"}
}