{
  "type": "Feature",
  "properties": {
    "iso:country":"FR",
    "sg:address":"14, Rue du Panicale - Immeuble le Vauban, 78320 La Verri\u00e8re",
    "sg:orig_category":"Unclassifiable Establishments",
    "sg:phone":"+33 1 30 13 78 40",
    "sg:province":"Ile de France",
    "wof:name":"Baumann Automation S.a.r.l.",
    "wof:placetype":"venue"
},
  "geometry": {"coordinates":[1.945974,48.757053],"type":"Point"}
}