{
  "type": "Feature",
  "properties": {
    "iso:country":"FR",
    "sg:address":"13, Rue Jacquard, 69240 Thizy",
    "sg:orig_category":"Unclassifiable Establishments",
    "sg:phone":"+33 4 74 13 85 85",
    "sg:province":"Rhone-Alpes",
    "wof:name":"Franfitex S.a.",
    "wof:placetype":"venue"
},
  "geometry": {"coordinates":[4.312533,46.024544],"type":"Point"}
}