{
  "type": "Feature",
  "properties": {
    "addr:full":"B.P. 245, 30105 Al\u00e8s C\u00e9dex^^1115, Rte d'Uz\u00e8s, 30100 Al\u00e8s Languedoc-Roussillon",
    "addr:housenumber":"b.p. 245",
    "addr:postcode":"30105;30100",
    "addr:street":"Rte D'Uze \u0300S",
    "iso:country":"FR",
    "sg:address":"B.P. 245, 30105 Al\u00e8s C\u00e9dex^^1115, Rte d'Uz\u00e8s, 30100 Al\u00e8s",
    "sg:orig_category":"Non-Classified Establishments",
    "sg:phone":"+33 4 66 54 29 29",
    "sg:province":"Languedoc-Roussillon",
    "wof:name":"J. Blanc S.a.r.l.",
    "wof:placetype":"venue"
},
  "geometry": {"coordinates":[4.098727,44.115372],"type":"Point"}
}