{
  "type": "Feature",
  "properties": {
    "iso:country":"FR",
    "sg:address":"18",
    "sg:city":"Balard; Paris; 75015",
    "sg:classifiers":[
        {
            "category":"Shopping",
            "subcategory":"Computers & Home Electronics",
            "type":"Retail Goods"
        }
    ],
    "sg:phone":"+33 1 40 58 35 35",
    "sg:postcode":"75015",
    "sg:province":"Ile de France",
    "sg:tags":[
        "chamber",
        "commerce"
    ],
    "wof:name":"Chambre Franco-allemande De Commerce Et D'industrie",
    "wof:placetype":"venue"
},
  "geometry": {"coordinates":[2.277207,48.844051],"type":"Point"}
}