{
  "type": "Feature",
  "properties": {
    "iso:country":"FR",
    "sg:address":"1 rue Amp\u00e8re 26100 ROMANS SUR ISERE",
    "sg:classifiers":[
        {
            "category":"Manufacturing",
            "subcategory":"Paper Products",
            "type":"Manufacturing & Wholesale Goods"
        }
    ],
    "sg:phone":"+33 4 75 72 42 75",
    "sg:postcode":"26100",
    "sg:province":"Rhone-Alpes",
    "sg:tags":[
        "hygiene",
        "animal"
    ],
    "wof:name":"Hc Cosmetique Diffusion S.a.r.l.",
    "wof:placetype":"venue"
},
  "geometry": {"coordinates":[5.059819,45.043316],"type":"Point"}
}