{
  "type": "Feature",
  "properties": {
    "iso:country":"FR",
    "sg:address":"B.P. 15, 14860 Ranville^^19, Rue du Colonel Fabien, 14860 Ranville",
    "sg:city":"Ranville",
    "sg:orig_category":"Non-Classified Establishments",
    "sg:phone":"+33 2 31 78 78 86",
    "sg:postcode":"14860",
    "sg:province":"Basse Normandie",
    "wof:name":"Normandie App\u00e2ts S.a.r.l.",
    "wof:placetype":"venue"
},
  "geometry": {"coordinates":[-0.191696,49.230114],"type":"Point"}
}