{
  "type": "Feature",
  "properties": {
    "iso:country":"FR",
    "sg:address":"16, Bd de la Marne, 89000 Auxerre",
    "sg:city":"Auxerre",
    "sg:orig_category":"Unclassifiable Establishments",
    "sg:phone":"+33 3 86 42 62 62",
    "sg:postcode":"89000",
    "sg:province":"Bourgogne",
    "wof:name":"C.r.c.a.m. - Caisse R\u00e9gionale De Cr\u00e9dit Agricole",
    "wof:placetype":"venue"
},
  "geometry": {"coordinates":[3.561397,47.812],"type":"Point"}
}