{
  "type": "Feature",
  "properties": {
    "addr:full":"13 Rue De La Station 92600 Asni\u00e8res Sur Seine Ile de France 92600",
    "addr:housenumber":"13",
    "addr:postcode":"92600;92600",
    "addr:street":"Rue De La Station",
    "iso:country":"FR",
    "sg:address":"13 Rue De La Station 92600 Asni\u00e8res Sur Seine",
    "sg:classifiers":[
        {
            "category":"Professional",
            "subcategory":"Business Services",
            "type":"Services"
        }
    ],
    "sg:phone":"+33 1 47 93 05 28",
    "sg:postcode":"92600",
    "sg:province":"Ile de France",
    "sg:tags":[
        "training",
        "advice"
    ],
    "wof:name":"Institution Sainte Genevieve",
    "wof:placetype":"venue"
},
  "geometry": {"coordinates":[2.284954,48.906803],"type":"Point"}
}