{
  "type": "Feature",
  "properties": {
    "addr:full":"18 Quai De La Rapee, 75012 Paris, Dept 75 Ile de France 75012",
    "addr:housenumber":"18;75",
    "addr:postcode":"75012;75012",
    "addr:street":"Quai De La Rapee;Ile De France",
    "iso:country":"FR",
    "sg:address":"18 Quai De La Rapee, 75012 Paris, Dept 75",
    "sg:classifiers":[
        {
            "category":"Banks & Credit Unions",
            "subcategory":"Bank",
            "type":"Services"
        }
    ],
    "sg:postcode":"75012",
    "sg:province":"Ile de France",
    "wof:name":"Cofibred",
    "wof:placetype":"venue"
},
  "geometry": {"coordinates":[2.374564,48.840397],"type":"Point"}
}