{
  "type": "Feature",
  "properties": {
    "iso:country":"FR",
    "sg:address":"165 Avenue Des Pyrenees 33140 Villenave D Ornon",
    "sg:city":"Cadaujac",
    "sg:classifiers":[
        {
            "category":"Manufacturing",
            "subcategory":"Wood Products",
            "type":"Manufacturing & Wholesale Goods"
        }
    ],
    "sg:phone":"+33 5 56 87 83 03",
    "sg:postcode":"33140",
    "sg:province":"Aquitaine",
    "sg:tags":[
        "household",
        "-",
        "machine",
        "engineering",
        "mechanical",
        "furniture"
    ],
    "wof:name":"Techni Cuisine Aquitaine",
    "wof:placetype":"venue"
},
  "geometry": {"coordinates":[-0.565019,44.777393],"type":"Point"}
}