{
  "type": "Feature",
  "properties": {
    "addr:full":"18 R De Ronde 39000 Lons Le Saunier Franche Comt\u00e9",
    "addr:housenumber":"18",
    "addr:postcode":"39000",
    "addr:street":"R De Ronde;Franche Comte\u0301",
    "iso:country":"FR",
    "sg:address":"18 R De Ronde 39000 Lons Le Saunier",
    "sg:classifiers":[
        {
            "category":"Professional",
            "subcategory":"Printing & Photocopies",
            "type":"Services"
        }
    ],
    "sg:phone":"+33 3 84 87 16 16",
    "sg:province":"Franche Comt\u00e9",
    "sg:tags":[
        "publishing"
    ],
    "wof:name":"Ste De Presse Et D'edition Du Jura Sa",
    "wof:placetype":"venue"
},
  "geometry": {"coordinates":[5.553692,46.673943],"type":"Point"}
}