{
  "type": "Feature",
  "properties": {
    "iso:country":"FR",
    "sg:address":"Rue du Stade",
    "sg:city":"La Ferri\u00e8re",
    "sg:orig_category":"Unclassifiable Establishments",
    "sg:phone":"+33 2 51 98 41 62",
    "sg:postcode":"85280",
    "sg:province":"Pays de Loire",
    "wof:name":"Etablissement Rouhaud S.a.r.l.",
    "wof:placetype":"venue"
},
  "geometry": {"coordinates":[-1.317581,46.715034],"type":"Point"}
}