{
  "type": "Feature",
  "properties": {
    "iso:country":"FR",
    "sg:address":"B.P. 69, 44260 Malville C\u00e9dex^^ZI de la Croix Rouge, 44260 Malville",
    "sg:orig_category":"Non-Classified Establishments",
    "sg:phone":"+33 2 40 57 00 41",
    "sg:postcode":"44260",
    "sg:province":"Pays de Loire",
    "wof:name":"Bugal S.a.",
    "wof:placetype":"venue"
},
  "geometry": {"coordinates":[-1.965349,47.30954],"type":"Point"}
}