{
  "type": "Feature",
  "properties": {
    "addr:full":"Zi Bidaille 74930 Scientrier Rhone-Alpes 74930",
    "addr:postcode":"74930;74930",
    "addr:street":"Rhone-Alpes",
    "iso:country":"FR",
    "sg:address":"Zi Bidaille 74930 Scientrier",
    "sg:classifiers":[
        {
            "category":"Home & Garden",
            "subcategory":"Furniture",
            "type":"Retail Goods"
        }
    ],
    "sg:phone":"+33 4 50 25 52 29",
    "sg:postcode":"74930",
    "sg:province":"Rhone-Alpes",
    "sg:tags":[
        "wood"
    ],
    "wof:name":"Espace Charpente",
    "wof:placetype":"venue"
},
  "geometry": {"coordinates":[6.331081,46.112339],"type":"Point"}
}