{
  "type": "Feature",
  "properties": {
    "iso:country":"FR",
    "sg:address":"B.P. 25, 39110 Salins les Bains^^Rte de Champagnole, 39110 Salins les Bains",
    "sg:orig_category":"Non-Classified Establishments",
    "sg:phone":"+33 3 84 73 09 08",
    "sg:province":"Franche Comt\u00e9",
    "wof:name":"L.e.g. S.a.",
    "wof:placetype":"venue"
},
  "geometry": {"coordinates":[5.935865,46.852779],"type":"Point"}
}