{
  "type": "Feature",
  "properties": {
    "iso:country":"FR",
    "sg:address":"4 R L\u00e9on Cur\u00e9 80800 Corbie",
    "sg:classifiers":[
        {
            "category":"Shopping",
            "subcategory":"Crafts & Fabrics",
            "type":"Retail Goods"
        }
    ],
    "sg:phone":"+33 3 22 96 45 00",
    "sg:postcode":"80800",
    "sg:province":"Picardie",
    "sg:tags":[
        "textile",
        "clothing"
    ],
    "wof:name":"Bvr Sa",
    "wof:placetype":"venue"
},
  "geometry": {"coordinates":[2.501065,49.912048],"type":"Point"}
}