{
  "type": "Feature",
  "properties": {
    "iso:country":"FR",
    "sg:address":"146, Bd de Chanzy, 93108 Montreuil C\u00e9dex",
    "sg:orig_category":"Non-Classified Establishments",
    "sg:phone":"+33 1 42 87 26 22",
    "sg:province":"Haute Normandie",
    "wof:name":"Thollon S.a.",
    "wof:placetype":"venue"
},
  "geometry": {"coordinates":[2.424817,48.859467],"type":"Point"}
}