{
  "type": "Feature",
  "properties": {
    "addr:full":"4, Rue Ren\u00e9 B\u00e9ranger, 26000 Valence Rhone-Alpes 26000",
    "addr:housenumber":"4",
    "addr:postcode":"26000;26000",
    "addr:street":"Rue Rene\u0301 Be\u0301Ranger",
    "iso:country":"FR",
    "sg:address":"4, Rue Ren\u00e9 B\u00e9ranger, 26000 Valence",
    "sg:orig_category":"Unclassifiable Establishments",
    "sg:phone":"+33 4 75 81 26 15",
    "sg:postcode":"26000",
    "sg:province":"Rhone-Alpes",
    "wof:name":"Graphi Laser S.a.r.l.",
    "wof:placetype":"venue"
},
  "geometry": {"coordinates":[4.891442,44.919479],"type":"Point"}
}