{
  "type": "Feature",
  "properties": {
    "addr:full":"B\u00e2timent D Aulnay sous Bois Champagne 93620",
    "addr:postcode":"93620",
    "addr:street":"Champagne",
    "iso:country":"FR",
    "sg:address":"B\u00e2timent D",
    "sg:city":"Aulnay sous Bois",
    "sg:orig_category":"Unclassifiable Establishments",
    "sg:phone":"+33 1 45 91 28 98",
    "sg:postcode":"93620",
    "sg:province":"Champagne",
    "wof:name":"Wibo France S.a.r.l.",
    "wof:placetype":"venue"
},
  "geometry": {"coordinates":[0.654042,44.715748],"type":"Point"}
}