{
  "type": "Feature",
  "properties": {
    "addr:full":"59 Rue Pierre Semard Nancy Lorraine 54000",
    "addr:housenumber":"59",
    "addr:postcode":"54000",
    "addr:street":"Rue Pierre Semard",
    "iso:country":"FR",
    "sg:address":"59 Rue Pierre Semard",
    "sg:city":"Nancy",
    "sg:classifiers":[
        {
            "category":"Banks & Credit Unions",
            "subcategory":"Financial Services",
            "type":"Services"
        }
    ],
    "sg:phone":"+33 3 83 30 40 48",
    "sg:postcode":"54000",
    "sg:province":"Lorraine",
    "sg:tags":[
        "banking",
        "finance",
        "insurance"
    ],
    "wof:name":"Caisse Regionale De Credit Agricole Mutuel De Lorraine (crcam De Lorraine)",
    "wof:placetype":"venue"
},
  "geometry": {"coordinates":[6.178432,48.689373],"type":"Point"}
}