{
  "type": "Feature",
  "properties": {
    "addr:full":"35 Rue Des Granges Galand 37555 St Avertin Cedex Midi Pyr\u00e9n\u00e9es",
    "addr:housenumber":"35",
    "addr:postcode":"37555;avertin cedex midi",
    "addr:street":"Rue Des Granges Galand",
    "iso:country":"FR",
    "sg:address":"35 Rue Des Granges Galand 37555 St Avertin Cedex",
    "sg:classifiers":[
        {
            "category":"Manufacturing",
            "subcategory":"Tools & Machinery",
            "type":"Manufacturing & Wholesale Goods"
        }
    ],
    "sg:phone":"+33 2 47 71 44 44",
    "sg:province":"Midi Pyr\u00e9n\u00e9es",
    "sg:tags":[
        "equipment",
        "measurement",
        "-",
        "precision",
        "instrument"
    ],
    "wof:name":"Siemens - Landis Et Staefa",
    "wof:placetype":"venue"
},
  "geometry": {"coordinates":[0.718483,47.370216],"type":"Point"}
}