{
  "type": "Feature",
  "properties": {
    "iso:country":"FR",
    "sg:address":"B.P. 3, 16400 La Couronne^^2, Rue de Quiers, 16400 La Couronne",
    "sg:orig_category":"Non-Classified Establishments",
    "sg:phone":"+33 5 45 61 04 83",
    "sg:province":"Poitou-Charentes",
    "wof:name":"Graphicom S.a.r.l.",
    "wof:placetype":"venue"
},
  "geometry": {"coordinates":[0.102157,45.608215],"type":"Point"}
}