{
  "type": "Feature",
  "properties": {
    "iso:country":"FR",
    "sg:address":"1 ave Claude Vigon; S. Jean Pied de Port; 06230",
    "sg:classifiers":[
        {
            "category":"Banks & Credit Unions",
            "subcategory":"Bank",
            "type":"Services"
        }
    ],
    "sg:phone":"+33 4 93 76 10 17",
    "sg:province":"Aquitaine",
    "wof:name":"Banque Populaire, De La C\u00f4te D'azur",
    "wof:placetype":"venue"
},
  "geometry": {"coordinates":[-72.010582,41.861092],"type":"Point"}
}