{
  "type": "Feature",
  "properties": {
    "addr:full":"1335, Av. d'Espagne, 66100 Perpignan Languedoc-Roussillon",
    "addr:housenumber":"1335",
    "addr:postcode":"66100",
    "addr:street":"Av. D'Espagne",
    "iso:country":"FR",
    "sg:address":"1335, Av. d'Espagne, 66100 Perpignan",
    "sg:orig_category":"Non-Classified Establishments",
    "sg:phone":"+33 4 68 54 44 11",
    "sg:province":"Languedoc-Roussillon",
    "wof:name":"Quinta France S.a.",
    "wof:placetype":"venue"
},
  "geometry": {"coordinates":[2.892088,42.678913],"type":"Point"}
}