{
  "type": "Feature",
  "properties": {
    "addr:full":"rue Raymond Sommet 42000 ST ETIENNE Rhone-Alpes",
    "addr:postcode":"42000",
    "addr:street":"Rue Raymond Sommet",
    "iso:country":"FR",
    "sg:address":"rue Raymond Sommet 42000 ST ETIENNE",
    "sg:classifiers":[
        {
            "category":"Utilities",
            "subcategory":"Natural Gas",
            "type":"Services"
        }
    ],
    "sg:phone":"+33 4 77 25 82 49",
    "sg:province":"Rhone-Alpes",
    "sg:tags":[
        "plant"
    ],
    "wof:name":"Chaudronnerie Maintenance Cintrage-cmc S.a.",
    "wof:placetype":"venue"
},
  "geometry": {"coordinates":[4.397704,45.450493],"type":"Point"}
}