{
  "type": "Feature",
  "properties": {
    "iso:country":"FR",
    "sg:address":"2 avenue du bosquet 95560 Baillet en France",
    "sg:classifiers":[
        {
            "category":"Manufacturing",
            "subcategory":"Motor Vehicles & Parts",
            "type":"Manufacturing & Wholesale Goods"
        }
    ],
    "sg:phone":"+33 1 34 08 37 37",
    "sg:postcode":"95560",
    "sg:province":"Ile de France",
    "sg:tags":[
        "industrial",
        "insulating",
        "material"
    ],
    "wof:name":"Les Ateliers De Villetaneuse Sa",
    "wof:placetype":"venue"
},
  "geometry": {"coordinates":[2.323405,49.06361],"type":"Point"}
}