{
  "type": "Feature",
  "properties": {
    "addr:full":"620 Rue Blaise Pascal Zone Industrielle 77550 Moissy Cramayel Ile de France 77550",
    "addr:housenumber":"620",
    "addr:postcode":"77550;77550",
    "addr:street":"Rue Blaise Pascal Zone Industrielle",
    "iso:country":"FR",
    "sg:address":"620 Rue Blaise Pascal Zone Industrielle 77550 Moissy Cramayel",
    "sg:classifiers":[
        {
            "category":"Food Court",
            "type":"Food & Drink"
        }
    ],
    "sg:phone":"+33 1 60 60 59 25",
    "sg:postcode":"77550",
    "sg:province":"Ile de France",
    "sg:tags":[
        "product",
        "related"
    ],
    "wof:name":"Exploitation Adoucisseurs Et Unites De Traitement (eau)",
    "wof:placetype":"venue"
},
  "geometry": {"coordinates":[2.59017,48.627384],"type":"Point"}
}