{
  "type": "Feature",
  "properties": {
    "addr:full":"3 Rue De La Roye 21310 Reneve Ren\u00e8ve Bourgogne 21310",
    "addr:housenumber":"3",
    "addr:postcode":"21310;21310",
    "addr:street":"Rue De La Roye",
    "iso:country":"FR",
    "sg:address":"3 Rue De La Roye 21310 Reneve",
    "sg:city":"Ren\u00e8ve",
    "sg:orig_category":"Miscellaneous Products",
    "sg:phone":"+33 3 80 47 76 57",
    "sg:postcode":"21310",
    "sg:province":"Bourgogne",
    "wof:name":"Grey Michel",
    "wof:placetype":"venue"
},
  "geometry": {"coordinates":[5.3956,47.411346],"type":"Point"}
}