{
  "type": "Feature",
  "properties": {
    "iso:country":"FR",
    "sg:address":"B.P. 36",
    "sg:city":"Anse",
    "sg:orig_category":"Non-Classified Establishments",
    "sg:phone":"+33 4 37 55 56 10",
    "sg:postcode":"69480",
    "sg:province":"Rhone-Alpes",
    "wof:name":"Vanel S.a.s.",
    "wof:placetype":"venue"
},
  "geometry": {"coordinates":[4.718405,45.935356],"type":"Point"}
}