{
  "type": "Feature",
  "properties": {
    "addr:full":"41, Rue Richelieu, 75001 Paris Ile de France",
    "addr:housenumber":"41",
    "addr:postcode":"75001",
    "addr:street":"Rue Richelieu",
    "iso:country":"FR",
    "sg:address":"41, Rue Richelieu, 75001 Paris",
    "sg:orig_category":"Non-Classified Establishments",
    "sg:phone":"+33 1 42 44 18 00",
    "sg:province":"Ile de France",
    "wof:name":"Robert Four S.a.",
    "wof:placetype":"venue"
},
  "geometry": {"coordinates":[2.336754,48.865807],"type":"Point"}
}