{
  "type": "Feature",
  "properties": {
    "addr:full":"4, Rue de la 2\u00e8me DB, 80000 Amiens Picardie",
    "addr:housenumber":"4",
    "addr:postcode":"80000",
    "addr:street":"Rue De La 2E\u0300Me",
    "iso:country":"FR",
    "sg:address":"4, Rue de la 2\u00e8me DB, 80000 Amiens",
    "sg:orig_category":"Non-Classified Establishments",
    "sg:phone":"+33 3 22 80 43 00",
    "sg:province":"Picardie",
    "wof:name":"Socotec S.a. - Soci\u00e9t\u00e9 De Contr\u00f4le Technique De Construction",
    "wof:placetype":"venue"
},
  "geometry": {"coordinates":[2.292542,49.893616],"type":"Point"}
}