{
  "type": "Feature",
  "properties": {
    "addr:full":"21 rue Fondaud\u00e8ge; Bordeaux Bordeaux Aquitaine 33100",
    "addr:housenumber":"21",
    "addr:postcode":"33100",
    "addr:street":"Rue Fondaude\u0300Ge",
    "iso:country":"FR",
    "sg:address":"21 rue Fondaud\u00e8ge; Bordeaux",
    "sg:city":"Bordeaux",
    "sg:classifiers":[
        {
            "category":"Banks & Credit Unions",
            "subcategory":"Bank",
            "type":"Services"
        }
    ],
    "sg:phone":"+33 3356013100",
    "sg:postcode":"33100",
    "sg:province":"Aquitaine",
    "wof:name":"Caisse D'epargne, Aquitaine Nord",
    "wof:placetype":"venue"
},
  "geometry": {"coordinates":[-0.578685,44.845783],"type":"Point"}
}