{
  "type": "Feature",
  "properties": {
    "iso:country":"FR",
    "sg:address":"21 rue Fondaud\u00e8ge; Bordeaux",
    "sg:city":"Bordeaux",
    "sg:classifiers":[
        {
            "category":"Banks & Credit Unions",
            "subcategory":"Bank",
            "type":"Services"
        }
    ],
    "sg:phone":"+33 3356013100",
    "sg:postcode":"33100",
    "sg:province":"Aquitaine",
    "wof:name":"Caisse D'epargne, Aquitaine Nord",
    "wof:placetype":"venue"
},
  "geometry": {"coordinates":[-0.578685,44.845783],"type":"Point"}
}