{
  "type": "Feature",
  "properties": {
    "addr:full":"63380 Saint Avit Combrailles Auvergne 63380",
    "addr:housenumber":"63380",
    "addr:postcode":"63380",
    "addr:street":"Saint Avit",
    "iso:country":"FR",
    "sg:address":"63380 Saint Avit",
    "sg:city":"Combrailles",
    "sg:orig_category":"Non-Classified Establishments",
    "sg:phone":"+33 4 73 79 01 14",
    "sg:postcode":"63380",
    "sg:province":"Auvergne",
    "wof:name":"Scierie Dubot Et Fils S.a.",
    "wof:placetype":"venue"
},
  "geometry": {"coordinates":[2.521566,45.871437],"type":"Point"}
}