{
  "type": "Feature",
  "properties": {
    "iso:country":"FR",
    "sg:address":"B.P. 54, 69564 Saint Genis Laval C\u00e9dex^^40, Av. du Chanoine Cartellier, 69230 Saint Genis Laval",
    "sg:orig_category":"Non-Classified Establishments",
    "sg:phone":"+33 4 78 56 75 52",
    "sg:province":"Rhone-Alpes",
    "wof:name":"Terradis S.a.",
    "wof:placetype":"venue"
},
  "geometry": {"coordinates":[4.780668,45.6759],"type":"Point"}
}