{
  "type": "Feature",
  "properties": {
    "iso:country":"FR",
    "sg:address":"B.P. Silic 597, 94663 Rungis C\u00e9dex^^40/42, Rue du Jura, 94150 Rungis",
    "sg:orig_category":"Non-Classified Establishments",
    "sg:phone":"+33 1 46 87 76 00",
    "sg:province":"Ile de France",
    "wof:name":"Stanford S.a.",
    "wof:placetype":"venue"
},
  "geometry": {"coordinates":[2.35142,48.74918],"type":"Point"}
}