{
  "type": "Feature",
  "properties": {
    "iso:country":"FR",
    "sg:address":"24, Rue du Vieux Ch\u00eane, 38240 Meylan",
    "sg:orig_category":"Non-Classified Establishments",
    "sg:phone":"+33 4 76 39 41 10",
    "sg:postcode":"38240",
    "sg:province":"Rhone-Alpes",
    "wof:name":"Schneider Electric S.a.",
    "wof:placetype":"venue"
},
  "geometry": {"coordinates":[5.791177,45.208782],"type":"Point"}
}