{
  "type": "Feature",
  "properties": {
    "addr:full":"6, Impasse du Ch\u00e2teau, 33640 Beautiran Beautiran Aquitaine 33640",
    "addr:housenumber":"6",
    "addr:postcode":"33640;33640",
    "addr:street":"Impasse Du Cha\u0302Teau",
    "iso:country":"FR",
    "sg:address":"6, Impasse du Ch\u00e2teau, 33640 Beautiran",
    "sg:city":"Beautiran",
    "sg:orig_category":"Unclassifiable Establishments",
    "sg:phone":"+33 5 56 67 39 39",
    "sg:postcode":"33640",
    "sg:province":"Aquitaine",
    "wof:name":"La Landaise Bordeaux Industrie S.a.r.l.",
    "wof:placetype":"venue"
},
  "geometry": {"coordinates":[-0.445789,44.701077],"type":"Point"}
}