{
  "type": "Feature",
  "properties": {
    "addr:full":"201 Rte De Gen\u00e8ve 74130 Vougy Rhone-Alpes 74130",
    "addr:housenumber":"201",
    "addr:postcode":"74130;74130",
    "addr:street":"Rte De Gene\u0300Ve;Rhone-Alpes",
    "iso:country":"FR",
    "sg:address":"201 Rte De Gen\u00e8ve 74130 Vougy",
    "sg:classifiers":[
        {
            "category":"Manufacturing",
            "subcategory":"Metals",
            "type":"Manufacturing & Wholesale Goods"
        }
    ],
    "sg:phone":"+33 4 50 34 59 43",
    "sg:postcode":"74130",
    "sg:province":"Rhone-Alpes",
    "sg:tags":[
        "metallurgy",
        "metalworking",
        "processing"
    ],
    "wof:name":"Sedajec Sarl",
    "wof:placetype":"venue"
},
  "geometry": {"coordinates":[6.464885,46.067585],"type":"Point"}
}