{
  "type": "Feature",
  "properties": {
    "addr:full":"Rte de Spay - La Tunisie Allonnes Pays de Loire 72700",
    "addr:postcode":"72700",
    "addr:street":"Rte De Spay",
    "iso:country":"FR",
    "sg:address":"Rte de Spay - La Tunisie",
    "sg:city":"Allonnes",
    "sg:orig_category":"Unclassifiable Establishments",
    "sg:phone":"+33 2 43 21 79 00",
    "sg:postcode":"72700",
    "sg:province":"Pays de Loire",
    "wof:name":"Sorbial S.a.s.",
    "wof:placetype":"venue"
},
  "geometry": {"coordinates":[0.150345,47.923435],"type":"Point"}
}