{
  "type": "Feature",
  "properties": {
    "addr:full":"1 Place Arago 66000 Perpignan Languedoc-Roussillon",
    "addr:housenumber":"1",
    "addr:postcode":"66000",
    "addr:street":"Place Arago",
    "iso:country":"FR",
    "sg:address":"1 Place Arago 66000 Perpignan",
    "sg:classifiers":[
        {
            "category":"Professional",
            "subcategory":"Printing & Photocopies",
            "type":"Services"
        }
    ],
    "sg:phone":"+33 4 68 34 54 94",
    "sg:province":"Languedoc-Roussillon",
    "sg:tags":[
        "publishing"
    ],
    "wof:name":"Societe Du Journal Midi Libre",
    "wof:placetype":"venue"
},
  "geometry": {"coordinates":[2.891475,42.697166],"type":"Point"}
}