{
  "type": "Feature",
  "properties": {
    "addr:full":"92, Rue Etion, 08000 Charleville M\u00e9zi\u00e8res Charleville-M\u00e9zi\u00e8res Champagne 08000",
    "addr:housenumber":"92",
    "addr:postcode":"08000;08000",
    "addr:street":"Rue Etion",
    "iso:country":"FR",
    "sg:address":"92, Rue Etion, 08000 Charleville M\u00e9zi\u00e8res",
    "sg:city":"Charleville-M\u00e9zi\u00e8res",
    "sg:orig_category":"Unclassifiable Establishments",
    "sg:phone":"+33 3 24 37 80 01",
    "sg:postcode":"08000",
    "sg:province":"Champagne",
    "wof:name":"Foissy Golf S.a.",
    "wof:placetype":"venue"
},
  "geometry": {"coordinates":[4.700824,49.782925],"type":"Point"}
}