{
  "type": "Feature",
  "properties": {
    "addr:full":"33 Ter Rue L\u00e9cuyer 93400 St Ouen Ile de France 93400",
    "addr:housenumber":"33 ter",
    "addr:postcode":"93400;93400",
    "addr:street":"Rue Le\u0301Cuyer;St;Ile De France",
    "iso:country":"FR",
    "sg:address":"33 Ter Rue L\u00e9cuyer 93400 St Ouen",
    "sg:classifiers":[
        {
            "category":"Professional",
            "subcategory":"Business Services",
            "type":"Services"
        }
    ],
    "sg:phone":"+33 1 40 11 20 40",
    "sg:postcode":"93400",
    "sg:province":"Ile de France",
    "sg:tags":[
        "travel",
        "fair"
    ],
    "wof:name":"Entreprise De Gestion Et De Services",
    "wof:placetype":"venue"
},
  "geometry": {"coordinates":[2.337144,48.901501],"type":"Point"}
}