{
  "type": "Feature",
  "properties": {
    "iso:country":"FR",
    "sg:address":"14, Rue Saint Wolfgang, 67750 Scherwiller",
    "sg:city":"Scherwiller",
    "sg:orig_category":"Unclassifiable Establishments",
    "sg:phone":"+33 3 88 58 37 20",
    "sg:postcode":"67750",
    "sg:province":"Alsace",
    "wof:name":"Vogel Robert S.a.",
    "wof:placetype":"venue"
},
  "geometry": {"coordinates":[7.422019,48.284279],"type":"Point"}
}