{
  "type": "Feature",
  "properties": {
    "addr:full":"Zone Industrielle 01370 Treffort Cuisiat Rhone-Alpes 01370",
    "addr:postcode":"01370;01370",
    "addr:street":"Zone Industrielle;Rhone-Alpes",
    "iso:country":"FR",
    "sg:address":"Zone Industrielle 01370 Treffort Cuisiat",
    "sg:classifiers":[
        {
            "category":"Manufacturing",
            "subcategory":"Metals",
            "type":"Manufacturing & Wholesale Goods"
        }
    ],
    "sg:phone":"+33 4 74 42 31 56",
    "sg:postcode":"01370",
    "sg:province":"Rhone-Alpes",
    "sg:tags":[
        "-",
        "machine",
        "equipment",
        "engineering",
        "machinery",
        "mechanical"
    ],
    "wof:name":"Serrurerie Metallerie De L'ain (sma)",
    "wof:placetype":"venue"
},
  "geometry": {"coordinates":[5.367818,46.269913],"type":"Point"}
}