{
  "type": "Feature",
  "properties": {
    "addr:full":"B.P. 61, 34140 M\u00e8ze C\u00e9dex^^Quai Baptiste Guitard, 34140 M\u00e8ze Languedoc-Roussillon",
    "addr:postcode":"34140;34140",
    "addr:street":"B.P. 61;Guitard",
    "iso:country":"FR",
    "sg:address":"B.P. 61, 34140 M\u00e8ze C\u00e9dex^^Quai Baptiste Guitard, 34140 M\u00e8ze",
    "sg:orig_category":"Non-Classified Establishments",
    "sg:phone":"+33 4 67 43 95 61",
    "sg:province":"Languedoc-Roussillon",
    "wof:name":"Gravit S.a.r.l.",
    "wof:placetype":"venue"
},
  "geometry": {"coordinates":[3.605895,43.427921],"type":"Point"}
}