{
  "type": "Feature",
  "properties": {
    "addr:full":"36 Rue Bri\u00e7onnet 37000 Tours Tours Centre 37000",
    "addr:housenumber":"36",
    "addr:postcode":"37000;37000",
    "addr:street":"Rue Bric\u0327Onnet",
    "iso:country":"FR",
    "sg:address":"36 Rue Bri\u00e7onnet 37000 Tours",
    "sg:city":"Tours",
    "sg:classifiers":[
        {
            "category":"Communications",
            "type":"Services"
        }
    ],
    "sg:phone":"+33 2 47 66 01 00",
    "sg:postcode":"37000",
    "sg:province":"Centre",
    "sg:tags":[
        "translation",
        "training",
        "interpretation",
        "advice",
        "business"
    ],
    "wof:name":"Tours Langues",
    "wof:placetype":"venue"
},
  "geometry": {"coordinates":[0.681509,47.394642],"type":"Point"}
}