{
  "type": "Feature",
  "properties": {
    "addr:full":"1, Av. de l'Europe, 31400 Toulouse Midi Pyr\u00e9n\u00e9es 31400",
    "addr:postcode":"31400;31400",
    "addr:street":"Av. De L'Europe",
    "iso:country":"FR",
    "sg:address":"1, Av. de l'Europe, 31400 Toulouse",
    "sg:orig_category":"Non-Classified Establishments",
    "sg:phone":"+33 5 61 00 30 80",
    "sg:postcode":"31400",
    "sg:province":"Midi Pyr\u00e9n\u00e9es",
    "wof:name":"B.2i. S.a.",
    "wof:placetype":"venue"
},
  "geometry": {"coordinates":[1.482193,43.556118],"type":"Point"}
}