{
  "type": "Feature",
  "properties": {
    "iso:country":"FR",
    "sg:address":"31, Rue Fran\u00e7ois 1er, 75008 Paris",
    "sg:orig_category":"Unclassifiable Establishments",
    "sg:phone":"+33 1 47 20 47 47",
    "sg:province":"Ile de France",
    "wof:name":"K.c.a. S.a.",
    "wof:placetype":"venue"
},
  "geometry": {"coordinates":[2.304212,48.868141],"type":"Point"}
}