{
  "type": "Feature",
  "properties": {
    "addr:full":"B.P. 105, 80202 P\u00e9ronne C\u00e9dex^^Rte de Biaches - Zone Industrielle, 80200 P\u00e9ronne Picardie",
    "addr:housenumber":"b.p. 105;biaches",
    "addr:postcode":"80202;80200",
    "addr:street":"Zone Industrielle",
    "iso:country":"FR",
    "sg:address":"B.P. 105, 80202 P\u00e9ronne C\u00e9dex^^Rte de Biaches - Zone Industrielle, 80200 P\u00e9ronne",
    "sg:orig_category":"Non-Classified Establishments",
    "sg:phone":"+33 3 22 84 14 73",
    "sg:province":"Picardie",
    "wof:name":"S.t.l.d. - S.a.s. - Transports Lef\u00e8vre-delavenne",
    "wof:placetype":"venue"
},
  "geometry": {"coordinates":[2.935345,49.929661],"type":"Point"}
}