{
  "type": "Feature",
  "properties": {
    "iso:country":"FR",
    "sg:address":"Rte de Bouglainval",
    "sg:city":"Pierres",
    "sg:orig_category":"Unclassifiable Establishments",
    "sg:phone":"+33 2 37 27 55 55",
    "sg:postcode":"28130",
    "sg:province":"Centre",
    "wof:name":"Coudroy S.a.r.l.",
    "wof:placetype":"venue"
},
  "geometry": {"coordinates":[1.571847,48.582073],"type":"Point"}
}