{
  "type": "Feature",
  "properties": {
    "addr:full":"Av. du Bois - ZA de Pont Royal Lambersart Nord Pas-de-Calais 59130",
    "addr:postcode":"59130",
    "addr:street":"Av. Du Bois Za De Pont",
    "iso:country":"FR",
    "sg:address":"Av. du Bois - ZA de Pont Royal",
    "sg:city":"Lambersart",
    "sg:orig_category":"Unclassifiable Establishments",
    "sg:phone":"+33 3 20 17 10 20",
    "sg:postcode":"59130",
    "sg:province":"Nord Pas-de-Calais",
    "wof:name":"Sylis S.a.",
    "wof:placetype":"venue"
},
  "geometry": {"coordinates":[3.02277,50.647751],"type":"Point"}
}