{
  "type": "Feature",
  "properties": {
    "addr:full":"95, Av. Marcel Leclerc, 11000 Carcassonne Languedoc-Roussillon 11000",
    "addr:postcode":"11000;11000",
    "addr:street":"95 Av. Marcel Leclerc",
    "iso:country":"FR",
    "sg:address":"95, Av. Marcel Leclerc, 11000 Carcassonne",
    "sg:orig_category":"Non-Classified Establishments",
    "sg:phone":"+33 4 68 47 58 08",
    "sg:postcode":"11000",
    "sg:province":"Languedoc-Roussillon",
    "wof:name":"A.s.f.o. Midi Pyr\u00e9n\u00e9es - Association Pour La Formation Et Le Perfectionnem",
    "wof:placetype":"venue"
},
  "geometry": {"coordinates":[2.36862,43.209183],"type":"Point"}
}