{
  "type": "Feature",
  "properties": {
    "addr:full":"Av Pasteur Saint Julien du Sault Bourgogne 89330",
    "addr:postcode":"89330",
    "addr:street":"Av Pasteur Saint;Du Sault Bourgogne",
    "iso:country":"FR",
    "sg:address":"Av Pasteur",
    "sg:city":"Saint Julien du Sault",
    "sg:orig_category":"Unclassifiable Establishments",
    "sg:phone":"+33 3 86 63 23 45",
    "sg:postcode":"89330",
    "sg:province":"Bourgogne",
    "wof:name":"Asca -demico S.a.",
    "wof:placetype":"venue"
},
  "geometry": {"coordinates":[3.304105,48.032291],"type":"Point"}
}