{
  "type": "Feature",
  "properties": {
    "addr:full":"1 Rue Du Dauphine 69120 Vaulx En Velin Rhone-Alpes 69120",
    "addr:housenumber":"1",
    "addr:postcode":"69120;69120",
    "addr:street":"Rue Du Dauphine",
    "iso:country":"FR",
    "sg:address":"1 Rue Du Dauphine 69120 Vaulx En Velin",
    "sg:classifiers":[
        {
            "category":"Professional",
            "subcategory":"Engineering",
            "type":"Services"
        }
    ],
    "sg:phone":"+33 4 72 15 11 20",
    "sg:postcode":"69120",
    "sg:province":"Rhone-Alpes",
    "sg:tags":[
        "machine",
        "-",
        "mechanical"
    ],
    "wof:name":"Diff Sa",
    "wof:placetype":"venue"
},
  "geometry": {"coordinates":[4.925395,45.753712],"type":"Point"}
}