{
  "type": "Feature",
  "properties": {
    "addr:full":"B.P. 57, 84232 Ch\u00e2teauneuf du Pape C\u00e9dex^^Av. Imp\u00e9riale, 84230 Ch\u00e2teauneuf du Pape Ch\u00e2teau Bourgogne 71250",
    "addr:postcode":"84232;84230;71250",
    "addr:street":"B.P. 57",
    "iso:country":"FR",
    "sg:address":"B.P. 57, 84232 Ch\u00e2teauneuf du Pape C\u00e9dex^^Av. Imp\u00e9riale, 84230 Ch\u00e2teauneuf du Pape",
    "sg:city":"Ch\u00e2teau",
    "sg:orig_category":"Non-Classified Establishments",
    "sg:phone":"+33 4 90 83 71 72",
    "sg:postcode":"71250",
    "sg:province":"Bourgogne",
    "wof:name":"Domaine Roger Sabon Et Fils E.a.r.l.",
    "wof:placetype":"venue"
},
  "geometry": {"coordinates":[4.835999,44.049744],"type":"Point"}
}