{
  "type": "Feature",
  "properties": {
    "addr:full":"Le Moulin 05800 St Firmin En Valgodemard Midi Pyr\u00e9n\u00e9es",
    "addr:postcode":"05800",
    "addr:street":"Le Moulin",
    "iso:country":"FR",
    "sg:address":"Le Moulin 05800 St Firmin En Valgodemard",
    "sg:classifiers":[
        {
            "category":"Shopping",
            "subcategory":"Crafts & Fabrics",
            "type":"Retail Goods"
        }
    ],
    "sg:phone":"+33 4 92 55 20 07",
    "sg:province":"Midi Pyr\u00e9n\u00e9es",
    "sg:tags":[
        "textile",
        "clothing"
    ],
    "wof:name":"Filature Du Valgaudemar",
    "wof:placetype":"venue"
},
  "geometry": {"coordinates":[6.05091,44.782082],"type":"Point"}
}