{
  "type": "Feature",
  "properties": {
    "iso:country":"FR",
    "sg:address":"3, Place Grangier, 21000 Dijon",
    "sg:city":"Dijon",
    "sg:orig_category":"Unclassifiable Establishments",
    "sg:phone":"+33 3 80 50 94 65",
    "sg:postcode":"21000",
    "sg:province":"Bourgogne",
    "wof:name":"R.h. Partners S.a.r.l.",
    "wof:placetype":"venue"
},
  "geometry": {"coordinates":[5.037854,47.323009],"type":"Point"}
}