{
  "type": "Feature",
  "properties": {
    "addr:full":"79, Rue de l'Arbre, 59274 Marquillies Nord Pas-de-Calais",
    "addr:housenumber":"79",
    "addr:postcode":"59274",
    "addr:street":"Rue De L'Arbre",
    "iso:country":"FR",
    "sg:address":"79, Rue de l'Arbre, 59274 Marquillies",
    "sg:orig_category":"Unclassifiable Establishments",
    "sg:phone":"+33 3 20 29 05 58",
    "sg:province":"Nord Pas-de-Calais",
    "wof:name":"Ets Wozniak Edmond",
    "wof:placetype":"venue"
},
  "geometry": {"coordinates":[2.86795,50.557011],"type":"Point"}
}