{
  "type": "Feature",
  "properties": {
    "addr:full":"Route de Clere les Pins 37130 MAZIERES DE TOURAINE Br\u00e9h\u00e9mont Centre 37130",
    "addr:postcode":"37130;37130",
    "addr:street":"Route De Clere Les Pins",
    "iso:country":"FR",
    "sg:address":"Route de Clere les Pins 37130 MAZIERES DE TOURAINE",
    "sg:city":"Br\u00e9h\u00e9mont",
    "sg:classifiers":[
        {
            "category":"Military Area",
            "subcategory":"Air Force Base",
            "type":"Public Place"
        }
    ],
    "sg:phone":"+33 2 47 96 23 23",
    "sg:postcode":"37130",
    "sg:province":"Centre",
    "sg:tags":[
        "window",
        "skylight",
        "dormer"
    ],
    "wof:name":"Weser Sa",
    "wof:placetype":"venue"
},
  "geometry": {"coordinates":[0.302169,47.285252],"type":"Point"}
}