{
  "type": "Feature",
  "properties": {
    "iso:country":"FR",
    "sg:address":"8 Rue Des Moulins 30300 Beaucaire",
    "sg:classifiers":[
        {
            "category":"Utilities",
            "subcategory":"Electric",
            "type":"Services"
        }
    ],
    "sg:phone":"+33 4 66 59 25 25",
    "sg:postcode":"30300",
    "sg:province":"Languedoc-Roussillon",
    "sg:tags":[
        "electricity",
        "electronic",
        "electrical",
        "equipment"
    ],
    "wof:name":"Ecaie Electricite Cablage Automatisme Industriel Europeen (ecaie)",
    "wof:placetype":"venue"
},
  "geometry": {"coordinates":[4.644208,43.809013],"type":"Point"}
}