{
  "type": "Feature",
  "properties": {
    "addr:full":"1 rue Ren\u00e9 Alban 89580 VAL DE MERCY Vallan Bourgogne 89580",
    "addr:housenumber":"1",
    "addr:postcode":"89580;89580",
    "addr:street":"Rue Rene\u0301 Alban;Bourgogne",
    "iso:country":"FR",
    "sg:address":"1 rue Ren\u00e9 Alban 89580 VAL DE MERCY",
    "sg:city":"Vallan",
    "sg:classifiers":[
        {
            "category":"Wholesale",
            "subcategory":"Wine & Distilled Alcoholic Beverages",
            "type":"Manufacturing & Wholesale Goods"
        }
    ],
    "sg:phone":"+33 3 86 41 48 00",
    "sg:postcode":"89580",
    "sg:province":"Bourgogne",
    "sg:tags":[
        "french"
    ],
    "wof:name":"Domaine Du Ch\u00e2teau Du Val Eurl",
    "wof:placetype":"venue"
},
  "geometry": {"coordinates":[3.58379,47.675945],"type":"Point"}
}