{
  "type": "Feature",
  "properties": {
    "addr:full":"B.P. 4 Anse Rhone-Alpes 69480",
    "addr:postcode":"69480",
    "addr:street":"B.P. 4 Anse Rhone-Alpes",
    "iso:country":"FR",
    "sg:address":"B.P. 4",
    "sg:city":"Anse",
    "sg:orig_category":"Non-Classified Establishments",
    "sg:phone":"+33 4 74 68 24 09",
    "sg:postcode":"69480",
    "sg:province":"Rhone-Alpes",
    "wof:name":"Jeanne De Laval S.a.r.l.",
    "wof:placetype":"venue"
},
  "geometry": {"coordinates":[4.718405,45.935356],"type":"Point"}
}