{
  "type": "Feature",
  "properties": {
    "addr:full":"54, Bd Michelet, 13008 Marseille Poitou-Charentes",
    "addr:housenumber":"54",
    "addr:postcode":"13008",
    "addr:street":"Bd Michelet",
    "iso:country":"FR",
    "sg:address":"54, Bd Michelet, 13008 Marseille",
    "sg:orig_category":"Unclassifiable Establishments",
    "sg:phone":"+33 4 91 71 31 00",
    "sg:province":"Poitou-Charentes",
    "wof:name":"M.t.t. S.a.r.l. - M\u00e9taero Travail Temporaire",
    "wof:placetype":"venue"
},
  "geometry": {"coordinates":[5.392794,43.269073],"type":"Point"}
}