{
  "type": "Feature",
  "properties": {
    "addr:full":"4, Rue Gustave Fouillaron, 49300 Cholet Pays de Loire",
    "addr:housenumber":"4",
    "addr:postcode":"49300",
    "addr:street":"Rue Gustave Fouillaron",
    "iso:country":"FR",
    "sg:address":"4, Rue Gustave Fouillaron, 49300 Cholet",
    "sg:orig_category":"Unclassifiable Establishments",
    "sg:phone":"+33 2 41 62 21 45",
    "sg:province":"Pays de Loire",
    "wof:name":"Perfecta S.a.",
    "wof:placetype":"venue"
},
  "geometry": {"coordinates":[-0.916322,47.029091],"type":"Point"}
}