{
  "type": "Feature",
  "properties": {
    "addr:full":"Route De Pau Le Mas Aire Sur L Adour Aquitaine 40800",
    "addr:postcode":"40800",
    "addr:street":"Route De Pau Le;Aire;L",
    "iso:country":"FR",
    "sg:address":"Route De Pau Le Mas",
    "sg:city":"Aire Sur L Adour",
    "sg:classifiers":[
        {
            "category":"Banks & Credit Unions",
            "subcategory":"Financial Services",
            "type":"Services"
        }
    ],
    "sg:phone":"+33 5 58 71 43 43",
    "sg:postcode":"40800",
    "sg:province":"Aquitaine",
    "sg:tags":[
        "banking",
        "finance",
        "insurance"
    ],
    "wof:name":"Caisse Regionale De Credit Agricole Du Sud Ouest (crca)",
    "wof:placetype":"venue"
},
  "geometry": {"coordinates":[-0.273659,43.592381],"type":"Point"}
}