{
  "type": "Feature",
  "properties": {
    "addr:full":"16, Rue du Bois de la Rose, 74100 Ville la Grand Rhone-Alpes 74100",
    "addr:housenumber":"16",
    "addr:postcode":"74100;74100",
    "addr:street":"Rue Du Bois De La Rose;La Grand Rhone-Alpes",
    "iso:country":"FR",
    "sg:address":"16, Rue du Bois de la Rose, 74100 Ville la Grand",
    "sg:orig_category":"Non-Classified Establishments",
    "sg:phone":"+33 4 50 38 68 78",
    "sg:postcode":"74100",
    "sg:province":"Rhone-Alpes",
    "wof:name":"I.s.s. Abilis S.a.",
    "wof:placetype":"venue"
},
  "geometry": {"coordinates":[6.27656,46.205814],"type":"Point"}
}