{
  "type": "Feature",
  "properties": {
    "iso:country":"FR",
    "sg:address":"B.P. 19, 38670 Chasse sur Rh\u00f4ne C\u00e9dex^^Rue des Barbi\u00e8res, 38670 Chasse sur Rh\u00f4ne",
    "sg:orig_category":"Non-Classified Establishments",
    "sg:phone":"+33 4 72 49 14 40",
    "sg:province":"Rhone-Alpes",
    "wof:name":"Groupe Stecmi S.a.",
    "wof:placetype":"venue"
},
  "geometry": {"coordinates":[4.79349,45.581604],"type":"Point"}
}