{
  "type": "Feature",
  "properties": {
    "iso:country":"FR",
    "sg:address":"175, Av. Victor Hugo, 93300 Aubervilliers",
    "sg:orig_category":"Unclassifiable Establishments",
    "sg:phone":"+33 1 43 52 07 19",
    "sg:province":"Ile de France",
    "wof:name":"Astier S.a.r.l.",
    "wof:placetype":"venue"
},
  "geometry": {"coordinates":[2.379597,48.912189],"type":"Point"}
}