{
  "type": "Feature",
  "properties": {
    "iso:country":"FR",
    "sg:address":"B.P. 903, 27207 Vernon C\u00e9dex^^Place Barette, 27200 Vernon",
    "sg:orig_category":"Non-Classified Establishments",
    "sg:phone":"+33 2 32 64 38 00",
    "sg:province":"Haute Normandie",
    "wof:name":"Mairie De Vernon",
    "wof:placetype":"venue"
},
  "geometry": {"coordinates":[1.48403,49.093414],"type":"Point"}
}