{
  "type": "Feature",
  "properties": {
    "addr:full":"Zi Prairie 91141 Villebon Sur Yvette Cedex Vill\u00e9 Alsace 67220",
    "addr:postcode":"91141;67220",
    "addr:street":"Prairie",
    "iso:country":"FR",
    "sg:address":"Zi Prairie 91141 Villebon Sur Yvette Cedex",
    "sg:city":"Vill\u00e9",
    "sg:classifiers":[
        {
            "category":"Professional",
            "subcategory":"Advertising",
            "type":"Services"
        }
    ],
    "sg:phone":"+33 1 69 09 34 24",
    "sg:postcode":"67220",
    "sg:province":"Alsace",
    "sg:tags":[
        "medium",
        "communication",
        "-",
        "paper",
        "packa",
        "cardboard"
    ],
    "wof:name":"Seed Cartonnage Sarl",
    "wof:placetype":"venue"
},
  "geometry": {"coordinates":[2.227225,48.700069],"type":"Point"}
}