{
  "type": "Feature",
  "properties": {
    "addr:full":"13 Rue Modigliani 06800 Cagnes Sur Mer Centre",
    "addr:housenumber":"13",
    "addr:postcode":"06800",
    "addr:street":"Rue Modigliani;Mer",
    "iso:country":"FR",
    "sg:address":"13 Rue Modigliani 06800 Cagnes Sur Mer",
    "sg:classifiers":[
        {
            "category":"Professional",
            "type":"Services"
        }
    ],
    "sg:phone":"+33 4 93 73 42 60",
    "sg:province":"Centre",
    "sg:tags":[
        "transport",
        "road"
    ],
    "wof:name":"Transport Dh Manutention Sarl",
    "wof:placetype":"venue"
},
  "geometry": {"coordinates":[7.15195,43.665371],"type":"Point"}
}