{
  "type": "Feature",
  "properties": {
    "addr:full":"329 Avenue Du Pr\u00e9sident Kennedy 62400 B\u00e9thune Nord Pas-de-Calais",
    "addr:housenumber":"329",
    "addr:postcode":"62400",
    "addr:street":"Avenue Du Pre\u0301Sident Kennedy",
    "iso:country":"FR",
    "sg:address":"329 Avenue Du Pr\u00e9sident Kennedy 62400 B\u00e9thune",
    "sg:classifiers":[
        {
            "category":"Autos & Motor Vehicles",
            "subcategory":"Automobile Sales",
            "type":"Retail Goods"
        }
    ],
    "sg:phone":"+33 3 21 61 48 06",
    "sg:province":"Nord Pas-de-Calais",
    "sg:tags":[
        "equipment",
        "transport"
    ],
    "wof:name":"Ste D Exploitation Saba",
    "wof:placetype":"venue"
},
  "geometry": {"coordinates":[2.648759,50.536888],"type":"Point"}
}