{
  "type": "Feature",
  "properties": {
    "iso:country":"FR",
    "sg:address":"77435 Marne la Vall\u00e9e C\u00e9dex 2^^26, Rue L\u00e9on Jouhaux - Croissy Beaubourg , 77183 Croissy Beaubourg",
    "sg:orig_category":"Non-Classified Establishments",
    "sg:phone":"+33 1 64 11 42 50",
    "sg:province":"Ile de France",
    "wof:name":"G\u00e9odis Logistics Europarts S.a.",
    "wof:placetype":"venue"
},
  "geometry": {"coordinates":[2.659334,48.828526],"type":"Point"}
}