{
  "type": "Feature",
  "properties": {
    "addr:full":"ZAC du Cormier Cholet Pays de Loire 49300",
    "addr:postcode":"49300",
    "addr:street":"Zac Du Cormier Cholet",
    "iso:country":"FR",
    "sg:address":"ZAC du Cormier",
    "sg:city":"Cholet",
    "sg:orig_category":"Unclassifiable Establishments",
    "sg:phone":"+33 2 41 62 01 03",
    "sg:postcode":"49300",
    "sg:province":"Pays de Loire",
    "wof:name":"Quincaillerie Conin S.a.r.l.",
    "wof:placetype":"venue"
},
  "geometry": {"coordinates":[-0.880687,47.062592],"type":"Point"}
}