{
  "type": "Feature",
  "properties": {
    "iso:country":"FR",
    "sg:address":"Rue Charles Gounod",
    "sg:city":"Pontivy",
    "sg:orig_category":"Non-Classified Establishments",
    "sg:phone":"+33 2 97 25 37 17",
    "sg:postcode":"56300",
    "sg:province":"Bretagne",
    "wof:name":"Gr\u00e9ta-centre-bretagne",
    "wof:placetype":"venue"
},
  "geometry": {"coordinates":[-2.960274,48.057838],"type":"Point"}
}