{
  "type": "Feature",
  "properties": {
    "addr:full":"295 avenue de la R\u00e9publique 33200 Bordeaux Bordeaux Aquitaine 33200",
    "addr:housenumber":"295",
    "addr:postcode":"33200;33200",
    "addr:street":"Avenue De La Re\u0301Publique",
    "iso:country":"FR",
    "sg:address":"295 avenue de la R\u00e9publique 33200 Bordeaux",
    "sg:city":"Bordeaux",
    "sg:classifiers":[
        {
            "category":"Wholesale",
            "subcategory":"Office Equipment",
            "type":"Manufacturing & Wholesale Goods"
        }
    ],
    "sg:phone":"+33 5 56 08 41 16",
    "sg:postcode":"33200",
    "sg:province":"Aquitaine",
    "sg:tags":[
        "furniture"
    ],
    "wof:name":"Aquitaine Organisation Sarl",
    "wof:placetype":"venue"
},
  "geometry": {"coordinates":[-0.61498,44.838791],"type":"Point"}
}