{
  "type": "Feature",
  "properties": {
    "iso:country":"FR",
    "sg:address":"100 Avenue De Suffren 75015 Paris",
    "sg:classifiers":[
        {
            "category":"Building & Trades",
            "subcategory":"Construction",
            "type":"Services"
        }
    ],
    "sg:phone":"+33 1 40 61 70 00",
    "sg:postcode":"75015",
    "sg:province":"Ile de France",
    "sg:tags":[
        "work",
        "public"
    ],
    "wof:name":"Atmb",
    "wof:placetype":"venue"
},
  "geometry": {"coordinates":[2.302576,48.849972],"type":"Point"}
}