{
  "type": "Feature",
  "properties": {
    "addr:full":"450, Rue Joigny, 73490 La Ravoire Rhone-Alpes",
    "addr:housenumber":"450",
    "addr:postcode":"73490",
    "addr:street":"Rue Joigny",
    "iso:country":"FR",
    "sg:address":"450, Rue Joigny, 73490 La Ravoire",
    "sg:orig_category":"Unclassifiable Establishments",
    "sg:phone":"+33 4 79 71 12 00",
    "sg:province":"Rhone-Alpes",
    "wof:name":"Soframat B.t.p. S.a.r.l.",
    "wof:placetype":"venue"
},
  "geometry": {"coordinates":[5.962353,45.551407],"type":"Point"}
}