{
  "type": "Feature",
  "properties": {
    "addr:full":"Rue du Barry Camar\u00e8s Midi Pyr\u00e9n\u00e9es 12360",
    "addr:postcode":"12360",
    "addr:street":"Rue Du Barry",
    "iso:country":"FR",
    "sg:address":"Rue du Barry",
    "sg:city":"Camar\u00e8s",
    "sg:orig_category":"Unclassifiable Establishments",
    "sg:phone":"+33 5 65 99 53 22",
    "sg:postcode":"12360",
    "sg:province":"Midi Pyr\u00e9n\u00e9es",
    "wof:name":"Soci\u00e9t\u00e9 D'exploitation Des Transports Jeanjean S.a.r.l.",
    "wof:placetype":"venue"
},
  "geometry": {"coordinates":[2.878258,43.825413],"type":"Point"}
}