{
  "type": "Feature",
  "properties": {
    "addr:full":"ZI de la Bodini\u00e8re Ro\u00e8ze sur Sarthe Pays de Loire 72210",
    "addr:postcode":"72210",
    "addr:street":"Zi De La Bodinie\u0300Re Roe\u0300Ze Sur Sarthe Pays;Loire",
    "iso:country":"FR",
    "sg:address":"ZI de la Bodini\u00e8re",
    "sg:city":"Ro\u00e8ze sur Sarthe",
    "sg:orig_category":"Unclassifiable Establishments",
    "sg:phone":"+33 2 43 88 79 83",
    "sg:postcode":"72210",
    "sg:province":"Pays de Loire",
    "wof:name":"Avenplast S.a.r.l.",
    "wof:placetype":"venue"
},
  "geometry": {"coordinates":[0.067595,47.895176],"type":"Point"}
}