{
  "type": "Feature",
  "properties": {
    "addr:full":"route de Pau 65421 BORDERES SUR L ECHEZ CEDEX Bord\u00e8res Aquitaine 64800",
    "addr:postcode":"65421;echez cedex;64800",
    "addr:street":"Route De Pau",
    "iso:country":"FR",
    "sg:address":"route de Pau 65421 BORDERES SUR L ECHEZ CEDEX",
    "sg:city":"Bord\u00e8res",
    "sg:classifiers":[
        {
            "category":"Transit Center",
            "subcategory":"Freight",
            "type":"Transportation"
        }
    ],
    "sg:phone":"+33 5 62 90 06 80",
    "sg:postcode":"64800",
    "sg:province":"Aquitaine",
    "sg:tags":[
        "rail",
        "transport"
    ],
    "wof:name":"D.p Jaffrezic Sa",
    "wof:placetype":"venue"
},
  "geometry": {"coordinates":[0.05132,43.2589],"type":"Point"}
}