{
  "type": "Feature",
  "properties": {
    "addr:full":"221 Rte Du Stade 40400 Tartas Tartas Aquitaine 40400",
    "addr:housenumber":"221",
    "addr:postcode":"40400;40400",
    "addr:street":"Rte Du Stade",
    "iso:country":"FR",
    "sg:address":"221 Rte Du Stade 40400 Tartas",
    "sg:city":"Tartas",
    "sg:classifiers":[
        {
            "category":"Food Court",
            "type":"Food & Drink"
        }
    ],
    "sg:phone":"+33 5 58 73 56 19",
    "sg:postcode":"40400",
    "sg:province":"Aquitaine",
    "sg:tags":[
        "product",
        "related"
    ],
    "wof:name":"Tembec Avebene Sa",
    "wof:placetype":"venue"
},
  "geometry": {"coordinates":[-0.823506,43.83345],"type":"Point"}
}