{
  "type": "Feature",
  "properties": {
    "iso:country":"FR",
    "sg:address":"17184 P\u00e9rigny C\u00e9dex^^1, Av. Louis Lumi\u00e8re, 17180 P\u00e9rigny",
    "sg:orig_category":"Non-Classified Establishments",
    "sg:phone":"+33 5 46 30 17 50",
    "sg:province":"Poitou-Charentes",
    "wof:name":"N.c.i. Abilis",
    "wof:placetype":"venue"
},
  "geometry": {"coordinates":[-1.096665,46.15501],"type":"Point"}
}