{
  "type": "Feature",
  "properties": {
    "iso:country":"FR",
    "sg:address":"21, Rue Balland, 01100 Oyonnax",
    "sg:orig_category":"Unclassifiable Establishments",
    "sg:phone":"+33 4 74 73 83 52",
    "sg:postcode":"01100",
    "sg:province":"Rhone-Alpes",
    "wof:name":"Vittet Joseph & Fils S.a.r.l.",
    "wof:placetype":"venue"
},
  "geometry": {"coordinates":[5.661414,46.261929],"type":"Point"}
}