{
  "type": "Feature",
  "properties": {
    "iso:country":"FR",
    "sg:address":"80 Route De Metz 57100 Thionville",
    "sg:classifiers":[
        {
            "category":"Manufacturing",
            "subcategory":"Chemicals & Compounds",
            "type":"Manufacturing & Wholesale Goods"
        }
    ],
    "sg:phone":"+33 3 82 88 49 41",
    "sg:postcode":"57100",
    "sg:province":"Lorraine",
    "sg:tags":[
        "pharmaceutical",
        "energy",
        "chemistry",
        "-",
        "by-product"
    ],
    "wof:name":"Cpe Thionville",
    "wof:placetype":"venue"
},
  "geometry": {"coordinates":[6.16078,49.342548],"type":"Point"}
}