{
  "type": "Feature",
  "properties": {
    "addr:full":"19, Rue des Granges Galand, 37550 Saint Avertin Saint-Avertin Centre 37550",
    "addr:housenumber":"19;saint-avertin",
    "addr:postcode":"37550;37550",
    "addr:street":"Rue Des Granges Galand",
    "iso:country":"FR",
    "sg:address":"19, Rue des Granges Galand, 37550 Saint Avertin",
    "sg:city":"Saint-Avertin",
    "sg:orig_category":"Unclassifiable Establishments",
    "sg:phone":"+33 2 47 25 27 00",
    "sg:postcode":"37550",
    "sg:province":"Centre",
    "wof:name":"Presse Portage S.a.r.l.",
    "wof:placetype":"venue"
},
  "geometry": {"coordinates":[0.719443,47.36871],"type":"Point"}
}