{
  "type": "Feature",
  "properties": {
    "iso:country":"FR",
    "sg:address":"18 rue de la R\u00e9publique; S. Germain en Laye; 78101",
    "sg:classifiers":[
        {
            "category":"Banks & Credit Unions",
            "subcategory":"Bank",
            "type":"Services"
        }
    ],
    "sg:phone":"+33 5 39 73 05 80",
    "sg:province":"Champagne",
    "wof:name":"Banque De France",
    "wof:placetype":"venue"
},
  "geometry": {"coordinates":[-98.24700199999999,29.357746],"type":"Point"}
}