{
  "type": "Feature",
  "properties": {
    "addr:full":"287, Rte des Creuses, 74600 Seynod Rhone-Alpes 74600",
    "addr:housenumber":"287",
    "addr:postcode":"74600;74600",
    "addr:street":"Rte Des Creuses",
    "iso:country":"FR",
    "sg:address":"287, Rte des Creuses, 74600 Seynod",
    "sg:orig_category":"Unclassifiable Establishments",
    "sg:phone":"+33 4 50 60 54 50",
    "sg:postcode":"74600",
    "sg:province":"Rhone-Alpes",
    "wof:name":"Gen\u00e8ve Service S.a.r.l.",
    "wof:placetype":"venue"
},
  "geometry": {"coordinates":[6.07651,45.88847],"type":"Point"}
}