{
  "type": "Feature",
  "properties": {
    "addr:full":"Rue du G\u00e9n\u00e9ral de Gaulle Valmont Lorraine 57730",
    "addr:postcode":"57730",
    "addr:street":"Rue Du Ge\u0301Ne\u0301Ral De Gaulle",
    "iso:country":"FR",
    "sg:address":"Rue du G\u00e9n\u00e9ral de Gaulle",
    "sg:city":"Valmont",
    "sg:orig_category":"Non-Classified Establishments",
    "sg:phone":"+33 3 87 29 87 41",
    "sg:postcode":"57730",
    "sg:province":"Lorraine",
    "wof:name":"Sotrans S.a.r.l.",
    "wof:placetype":"venue"
},
  "geometry": {"coordinates":[6.717364,49.089806],"type":"Point"}
}