{
  "type": "Feature",
  "properties": {
    "addr:full":"7, Rue de Belle Ile, 72190 Coulaines Pays de Loire",
    "addr:housenumber":"7",
    "addr:postcode":"72190",
    "addr:street":"Rue De Belle Ile",
    "iso:country":"FR",
    "sg:address":"7, Rue de Belle Ile, 72190 Coulaines",
    "sg:orig_category":"Unclassifiable Establishments",
    "sg:phone":"+33 2 43 82 32 00",
    "sg:province":"Pays de Loire",
    "wof:name":"Cabinet Guillerminet S.a.",
    "wof:placetype":"venue"
},
  "geometry": {"coordinates":[0.198858,48.027142],"type":"Point"}
}