{
  "type": "Feature",
  "properties": {
    "addr:full":"ZI Auguste 1 Cestas Aquitaine 33610",
    "addr:housenumber":"1",
    "addr:postcode":"33610",
    "addr:street":"Zi Auguste",
    "iso:country":"FR",
    "sg:address":"ZI Auguste 1",
    "sg:city":"Cestas",
    "sg:orig_category":"Non-Classified Establishments",
    "sg:phone":"+33 5 56 36 46 98",
    "sg:postcode":"33610",
    "sg:province":"Aquitaine",
    "wof:name":"Calmon R. S.a.r.l.",
    "wof:placetype":"venue"
},
  "geometry": {"coordinates":[-0.685714,44.741707],"type":"Point"}
}