{
  "type": "Feature",
  "properties": {
    "addr:full":"141, Av. Marcel Casti\u00e9 - Espace Maurice, 83000 Toulon Aquitaine",
    "addr:postcode":"83000",
    "addr:street":"141 Av. Marcel Castie\u0301 Espace Maurice",
    "iso:country":"FR",
    "sg:address":"141, Av. Marcel Casti\u00e9 - Espace Maurice, 83000 Toulon",
    "sg:orig_category":"Unclassifiable Establishments",
    "sg:phone":"+33 4 94 16 02 25",
    "sg:province":"Aquitaine",
    "wof:name":"Planitec",
    "wof:placetype":"venue"
},
  "geometry": {"coordinates":[5.940554,43.12331],"type":"Point"}
}