{
  "type": "Feature",
  "properties": {
    "addr:full":"Rue De La Chapelle 79140 Combrand Poitou-Charentes 79140",
    "addr:postcode":"79140;79140",
    "addr:street":"Rue De La Chapelle",
    "iso:country":"FR",
    "sg:address":"Rue De La Chapelle 79140 Combrand",
    "sg:classifiers":[
        {
            "category":"Professional",
            "subcategory":"Engineering",
            "type":"Services"
        }
    ],
    "sg:phone":"+33 5 49 81 01 65",
    "sg:postcode":"79140",
    "sg:province":"Poitou-Charentes",
    "sg:tags":[
        "machine",
        "-",
        "mechanical"
    ],
    "wof:name":"Etablissements Fauchereau",
    "wof:placetype":"venue"
},
  "geometry": {"coordinates":[-0.687659,46.868725],"type":"Point"}
}