{
  "type": "Feature",
  "properties": {
    "addr:full":"2 Rue Gare 57320 Anzeling Lorraine 57320",
    "addr:housenumber":"2",
    "addr:postcode":"57320;57320",
    "addr:street":"Rue Gare",
    "iso:country":"FR",
    "sg:address":"2 Rue Gare 57320 Anzeling",
    "sg:classifiers":[
        {
            "category":"Shopping",
            "type":"Retail Goods"
        }
    ],
    "sg:phone":"+33 3 87 35 75 11",
    "sg:postcode":"57320",
    "sg:province":"Lorraine",
    "sg:tags":[
        "metallurgy",
        "finished",
        "-",
        "metalworking",
        "metallic"
    ],
    "wof:name":"Lang Sa",
    "wof:placetype":"venue"
},
  "geometry": {"coordinates":[6.46051,49.261784],"type":"Point"}
}