{
  "type": "Feature",
  "properties": {
    "iso:country":"FR",
    "sg:address":"B.P. 50, 13834 Ch\u00e2teaurenard C\u00e9dex^^ZI des Iscles, 13830 Ch\u00e2teaurenard",
    "sg:orig_category":"Non-Classified Establishments",
    "sg:phone":"+33 4 90 24 21 00",
    "sg:province":"Provence-Alpes-C\u00f4te d'Azur",
    "wof:name":"Rotosud S.a.r.l.",
    "wof:placetype":"venue"
},
  "geometry": {"coordinates":[5.589952,43.247658],"type":"Point"}
}