{
  "type": "Feature",
  "properties": {
    "addr:full":"Au Pont De Cana 19102 Brive Cedex Bourgogne",
    "addr:postcode":"19102 brive cedex bourgogne",
    "iso:country":"FR",
    "sg:address":"Au Pont De Cana 19102 Brive Cedex",
    "sg:classifiers":[
        {
            "category":"Food & Beverages",
            "subcategory":"Groceries & Convenience Stores",
            "type":"Retail Goods"
        }
    ],
    "sg:phone":"+33 5 55 88 21 50",
    "sg:province":"Bourgogne",
    "sg:tags":[
        "product",
        "related"
    ],
    "wof:name":"Ets Coste Et Fils",
    "wof:placetype":"venue"
},
  "geometry": {"coordinates":[1.53263,45.158611],"type":"Point"}
}