{
  "type": "Feature",
  "properties": {
    "iso:country":"FR",
    "sg:address":"6, Rte du Stade, 08150 Renwez",
    "sg:city":"Harcy",
    "sg:orig_category":"Unclassifiable Establishments",
    "sg:phone":"+33 3 24 54 93 58",
    "sg:postcode":"08150",
    "sg:province":"Champagne",
    "wof:name":"Ridremont S.a.",
    "wof:placetype":"venue"
},
  "geometry": {"coordinates":[4.605571,49.835583],"type":"Point"}
}