{
  "type": "Feature",
  "properties": {
    "addr:full":"27 Avenue Du Granier 38240 Meylan Rhone-Alpes",
    "addr:housenumber":"27",
    "addr:postcode":"38240",
    "addr:street":"Avenue Du Granier",
    "iso:country":"FR",
    "sg:address":"27 Avenue Du Granier 38240 Meylan",
    "sg:classifiers":[
        {
            "category":"Manufacturing",
            "subcategory":"Paper Products",
            "type":"Manufacturing & Wholesale Goods"
        }
    ],
    "sg:phone":"+33 4 76 61 42 00",
    "sg:province":"Rhone-Alpes",
    "sg:tags":[
        "finished",
        "cardboard",
        "-"
    ],
    "wof:name":"Papeteries Matussiere Et Forest",
    "wof:placetype":"venue"
},
  "geometry": {"coordinates":[5.784366,45.210224],"type":"Point"}
}