{
  "type": "Feature",
  "properties": {
    "iso:country":"FR",
    "sg:address":"31 Rue Du Landy 93210 La Plaine St Denis",
    "sg:city":"Plaine",
    "sg:classifiers":[
        {
            "category":"Professional",
            "subcategory":"Engineering",
            "type":"Services"
        }
    ],
    "sg:phone":"+33 1 49 17 83 90",
    "sg:postcode":"67420",
    "sg:province":"Alsace",
    "sg:tags":[
        "machine",
        "-",
        "mechanical"
    ],
    "wof:name":"Mazelgaines Sa",
    "wof:placetype":"venue"
},
  "geometry": {"coordinates":[2.362788,48.915279],"type":"Point"}
}