{
  "type": "Feature",
  "properties": {
    "addr:full":"B.P. 28, 25660 Sa\u00f4ne^^Zone Industrielle, 25660 Sa\u00f4ne Franche Comt\u00e9 25660",
    "addr:postcode":"25660;25660;25660",
    "addr:street":"B.P. 28;Industrielle;Franche Comte\u0301",
    "iso:country":"FR",
    "sg:address":"B.P. 28, 25660 Sa\u00f4ne^^Zone Industrielle, 25660 Sa\u00f4ne",
    "sg:orig_category":"Non-Classified Establishments",
    "sg:phone":"+33 3 81 55 93 00",
    "sg:postcode":"25660",
    "sg:province":"Franche Comt\u00e9",
    "wof:name":"Bonnefoy S.a.",
    "wof:placetype":"venue"
},
  "geometry": {"coordinates":[6.11653,47.225906],"type":"Point"}
}