{
  "type": "Feature",
  "properties": {
    "addr:full":"85 Rue Charles Le Coulond 37170 Chambray Les Tours Chambray-l\u00e8s-Tours Centre 37170",
    "addr:housenumber":"85",
    "addr:postcode":"37170;37170",
    "addr:street":"Rue Charles Le Coulond",
    "iso:country":"FR",
    "sg:address":"85 Rue Charles Le Coulond 37170 Chambray Les Tours",
    "sg:city":"Chambray-l\u00e8s-Tours",
    "sg:classifiers":[
        {
            "category":"Autos & Motor Vehicles",
            "subcategory":"Automobile Sales",
            "type":"Retail Goods"
        }
    ],
    "sg:phone":"+33 2 47 71 37 37",
    "sg:postcode":"37170",
    "sg:province":"Centre",
    "sg:tags":[
        "equipment",
        "motor-cars",
        "transport"
    ],
    "wof:name":"Societe Commerciale Citroen",
    "wof:placetype":"venue"
},
  "geometry": {"coordinates":[0.702587,47.331192],"type":"Point"}
}