{
  "type": "Feature",
  "properties": {
    "addr:full":"15 des Vanesses; Villepinte; 93420 Ile de France",
    "addr:housenumber":"15",
    "addr:postcode":"93420 ile",
    "addr:street":"Des Vanesses",
    "iso:country":"FR",
    "sg:address":"15",
    "sg:city":"des Vanesses; Villepinte; 93420",
    "sg:classifiers":[
        {
            "category":"Industrial Area",
            "type":"Public Place"
        }
    ],
    "sg:phone":"+33 1 45 91 50 00",
    "sg:province":"Ile de France",
    "sg:tags":[
        "large",
        "private"
    ],
    "wof:name":"Guerbet Group",
    "wof:placetype":"venue"
},
  "geometry": {"coordinates":[2.505738,48.974586],"type":"Point"}
}