{
  "type": "Feature",
  "properties": {
    "addr:full":"5 bis, Rue Gambetta, 92140 Clamart Ile de France",
    "addr:housenumber":"5 bis",
    "addr:postcode":"92140;ile",
    "addr:street":"Rue Gambetta",
    "iso:country":"FR",
    "sg:address":"5 bis, Rue Gambetta, 92140 Clamart",
    "sg:orig_category":"Unclassifiable Establishments",
    "sg:phone":"+33 1 46 38 71 81",
    "sg:province":"Ile de France",
    "wof:name":"Amt Data S.a.r.l.",
    "wof:placetype":"venue"
},
  "geometry": {"coordinates":[2.268279,48.810608],"type":"Point"}
}