{
  "type": "Feature",
  "properties": {
    "addr:full":"ZI de la Grande Noue Ch\u00e2teauneuf en Thymerais Centre 28170",
    "addr:postcode":"28170",
    "addr:street":"Zi De La Grande Noue Cha\u0302Teauneuf En",
    "iso:country":"FR",
    "sg:address":"ZI de la Grande Noue",
    "sg:city":"Ch\u00e2teauneuf en Thymerais",
    "sg:orig_category":"Non-Classified Establishments",
    "sg:phone":"+33 2 37 51 67 34",
    "sg:postcode":"28170",
    "sg:province":"Centre",
    "wof:name":"C.s.m.t. S.a.r.l. - Chaudronnerie Serrurerie M\u00e9cano Soudure De Thyme",
    "wof:placetype":"venue"
},
  "geometry": {"coordinates":[1.240185,48.582344],"type":"Point"}
}