{
  "type": "Feature",
  "properties": {
    "iso:country":"FR",
    "sg:address":"14, Rue Andr\u00e9 Allar, 13015 Marseille",
    "sg:orig_category":"Unclassifiable Establishments",
    "sg:phone":"+33 4 91 50 56 30",
    "sg:province":"Poitou-Charentes",
    "wof:name":"Les Mat\u00e9riaux Modernes S.a.",
    "wof:placetype":"venue"
},
  "geometry": {"coordinates":[5.366365,43.324944],"type":"Point"}
}