{
  "type": "Feature",
  "properties": {
    "iso:country":"FR",
    "sg:address":"81, Rue du Molinel, 59800 Lille",
    "sg:orig_category":"Unclassifiable Establishments",
    "sg:phone":"+33 3 20 40 21 71",
    "sg:province":"Nord Pas-de-Calais",
    "wof:name":"Samtex",
    "wof:placetype":"venue"
},
  "geometry": {"coordinates":[3.066851,50.633801],"type":"Point"}
}