{
  "type": "Feature",
  "properties": {
    "iso:country":"FR",
    "sg:address":"44, Chemin Haut, 67200 Strasbourg",
    "sg:city":"Strasbourg",
    "sg:orig_category":"Unclassifiable Establishments",
    "sg:phone":"+33 3 88 26 88 88",
    "sg:postcode":"67200",
    "sg:province":"Alsace",
    "wof:name":"Seegmuller S.t.i.s. S.a.",
    "wof:placetype":"venue"
},
  "geometry": {"coordinates":[7.734431,48.594982],"type":"Point"}
}