{
  "type": "Feature",
  "properties": {
    "addr:full":"50 bis, Av. de la Grande Arm\u00e9e, 75848 Paris C\u00e9dex 17 Haute Normandie",
    "addr:housenumber":"50 bis;17",
    "addr:postcode":"75848",
    "addr:street":"Av. De La Grande Arme\u0301E;Haute Normandie",
    "iso:country":"FR",
    "sg:address":"50 bis, Av. de la Grande Arm\u00e9e, 75848 Paris C\u00e9dex 17",
    "sg:orig_category":"Non-Classified Establishments",
    "sg:phone":"+33 1 44 09 24 24",
    "sg:province":"Haute Normandie",
    "wof:name":"E.f.e. S.a. - Edition Formation Entreprise",
    "wof:placetype":"venue"
},
  "geometry": {"coordinates":[2.287692,48.876472],"type":"Point"}
}