{
  "type": "Feature",
  "properties": {
    "iso:country":"FR",
    "sg:address":"71, Rue d'Alsace, 69100 Villeurbanne",
    "sg:orig_category":"Non-Classified Establishments",
    "sg:phone":"+33 4 37 43 31 13",
    "sg:postcode":"69100",
    "sg:province":"Rhone-Alpes",
    "wof:name":"Impressions Tracol S.a.",
    "wof:placetype":"venue"
},
  "geometry": {"coordinates":[4.869863,45.771603],"type":"Point"}
}