{
  "type": "Feature",
  "properties": {
    "addr:full":"Impasse Edouard Branly Graulhet Midi Pyr\u00e9n\u00e9es 81300",
    "addr:postcode":"81300",
    "addr:street":"Impasse Edouard Branly",
    "iso:country":"FR",
    "sg:address":"Impasse Edouard Branly",
    "sg:city":"Graulhet",
    "sg:orig_category":"Unclassifiable Establishments",
    "sg:phone":"+33 5 63 42 11 05",
    "sg:postcode":"81300",
    "sg:province":"Midi Pyr\u00e9n\u00e9es",
    "wof:name":"Marily Cuir S.a.r.l.",
    "wof:placetype":"venue"
},
  "geometry": {"coordinates":[2.028947,43.697151],"type":"Point"}
}