{
  "type": "Feature",
  "properties": {
    "addr:full":"2, All\u00e9e des Arums - B\u00e2t. C1, 94635 Rungis C\u00e9dex \u00cele-de-France",
    "addr:housenumber":"2;ba\u0302t c1",
    "addr:postcode":"94635",
    "addr:street":"Alle\u0301E Des Arums;Ce\u0301Dex",
    "iso:country":"FR",
    "sg:address":"2, All\u00e9e des Arums - B\u00e2t. C1, 94635 Rungis C\u00e9dex",
    "sg:orig_category":"Non-Classified Establishments",
    "sg:phone":"+33 1 46 87 03 46",
    "sg:province":"\u00cele-de-France",
    "wof:name":"Fleuropa S.a.r.l.",
    "wof:placetype":"venue"
},
  "geometry": {"coordinates":[2.35325,48.751419],"type":"Point"}
}