{
  "type": "Feature",
  "properties": {
    "addr:full":"21, Rue Med\u00e9ric, 10120 Saint Andr\u00e9 les Vergers Champagne",
    "addr:housenumber":"21",
    "addr:postcode":"10120",
    "addr:street":"Rue Mede\u0301Ric;Andre\u0301 Les",
    "iso:country":"FR",
    "sg:address":"21, Rue Med\u00e9ric, 10120 Saint Andr\u00e9 les Vergers",
    "sg:orig_category":"Unclassifiable Establishments",
    "sg:phone":"+33 3 25 79 13 36",
    "sg:province":"Champagne",
    "wof:name":"Froid Electro Technique Equipement 10 000 S.a.r.l.",
    "wof:placetype":"venue"
},
  "geometry": {"coordinates":[4.049143,48.280148],"type":"Point"}
}