{
  "type": "Feature",
  "properties": {
    "iso:country":"FR",
    "sg:address":"49 R L\u00e9on Chartier 91160 Saulx Les Chartreux",
    "sg:classifiers":[
        {
            "category":"Professional",
            "subcategory":"Advertising",
            "type":"Services"
        }
    ],
    "sg:phone":"+33 1 64 54 96 60",
    "sg:postcode":"91160",
    "sg:province":"Ile de France",
    "sg:tags":[
        "information",
        "medium",
        "communication"
    ],
    "wof:name":"Languille Bernard Sa",
    "wof:placetype":"venue"
},
  "geometry": {"coordinates":[2.274156,48.688587],"type":"Point"}
}