{
  "type": "Feature",
  "properties": {
    "addr:full":"30 av de la Division Leclerc 91160 Ballainvilliers Ile de France 91160",
    "addr:postcode":"91160;ile;91160",
    "addr:street":"30 Av De La Division Leclerc;France",
    "iso:country":"FR",
    "sg:address":"30 av de la Division Leclerc 91160 Ballainvilliers",
    "sg:classifiers":[
        {
            "category":"Retail",
            "subcategory":"Driving School",
            "type":"Services"
        }
    ],
    "sg:phone":"+33 1 69 01 75 68",
    "sg:postcode":"91160",
    "sg:province":"Ile de France",
    "sg:tags":[
        "drive",
        "lifting"
    ],
    "wof:name":"Gmtp Sarl",
    "wof:placetype":"venue"
},
  "geometry": {"coordinates":[2.277045,48.662319],"type":"Point"}
}