{
  "type": "Feature",
  "properties": {
    "addr:full":"6 Rue Raymond 4 Toulouse Midi Pyr\u00e9n\u00e9es 31000",
    "addr:housenumber":"6;4",
    "addr:postcode":"31000",
    "addr:street":"Rue Raymond",
    "iso:country":"FR",
    "sg:address":"6 Rue Raymond 4",
    "sg:city":"Toulouse",
    "sg:classifiers":[
        {
            "category":"Banks & Credit Unions",
            "subcategory":"Financial Services",
            "type":"Services"
        }
    ],
    "sg:phone":"+33 5 62 73 66 80",
    "sg:postcode":"31000",
    "sg:province":"Midi Pyr\u00e9n\u00e9es",
    "sg:tags":[
        "banking",
        "finance",
        "insurance"
    ],
    "wof:name":"Banque Francaise Du Credit Cooperatif (credit Cooperatif Ou Bfcc)",
    "wof:placetype":"venue"
},
  "geometry": {"coordinates":[1.447215,43.609604],"type":"Point"}
}