{
  "type": "Feature",
  "properties": {
    "addr:full":"Rte de Bordeaux N\u00e9rac Aquitaine 47600",
    "addr:postcode":"47600",
    "addr:street":"Rte De Bordeaux",
    "iso:country":"FR",
    "sg:address":"Rte de Bordeaux",
    "sg:city":"N\u00e9rac",
    "sg:orig_category":"Non-Classified Establishments",
    "sg:phone":"+33 5 53 97 66 50",
    "sg:postcode":"47600",
    "sg:province":"Aquitaine",
    "wof:name":"Cadralbret",
    "wof:placetype":"venue"
},
  "geometry": {"coordinates":[0.33179,44.143036],"type":"Point"}
}