{
  "type": "Feature",
  "properties": {
    "addr:full":"B.P. 176, 21005 Dijon C\u00e9dex^^10, All\u00e9e Andr\u00e9 Bourland - Parc Technologique Toison d'Or, 21000 Dijon Dijon Bourgogne 21000",
    "addr:housenumber":"b.p. 176",
    "addr:postcode":"21005;21000;21000",
    "addr:street":"Alle\u0301E Andre\u0301 Bourland Parc;D'Or",
    "iso:country":"FR",
    "sg:address":"B.P. 176, 21005 Dijon C\u00e9dex^^10, All\u00e9e Andr\u00e9 Bourland - Parc Technologique Toison d'Or, 21000 Dijon",
    "sg:city":"Dijon",
    "sg:orig_category":"Non-Classified Establishments",
    "sg:phone":"+33 3 80 78 75 50",
    "sg:postcode":"21000",
    "sg:province":"Bourgogne",
    "wof:name":"A.i.f.c. - Association Interprofessionnelle Pour La Formation Continue",
    "wof:placetype":"venue"
},
  "geometry": {"coordinates":[5.044497,47.358009],"type":"Point"}
}