{
  "type": "Feature",
  "properties": {
    "addr:full":"2 Rue Bois D'Hur\u00e9 17140 Lagord Poitou-Charentes",
    "addr:housenumber":"2",
    "addr:postcode":"17140",
    "addr:street":"Rue Bois D'Hure \u0301",
    "iso:country":"FR",
    "sg:address":"2 Rue Bois D'Hur\u00e9 17140 Lagord",
    "sg:classifiers":[
        {
            "category":"Professional",
            "subcategory":"Advertising",
            "type":"Services"
        }
    ],
    "sg:phone":"+33 5 46 67 46 44",
    "sg:province":"Poitou-Charentes",
    "sg:tags":[
        "communication",
        "medium"
    ],
    "wof:name":"Avenir Decaux",
    "wof:placetype":"venue"
},
  "geometry": {"coordinates":[-1.15297,46.19043],"type":"Point"}
}