{
  "type": "Feature",
  "properties": {
    "iso:country":"FR",
    "sg:address":"158 Boulevard De Creteil 94100 St Maur Des Fosses",
    "sg:classifiers":[
        {
            "category":"Wholesale",
            "subcategory":"Medical Equipment & Supplies",
            "type":"Manufacturing & Wholesale Goods"
        }
    ],
    "sg:phone":"+33 1 48 83 81 64",
    "sg:postcode":"94100",
    "sg:province":"Ile de France",
    "sg:tags":[
        "instrument",
        "health",
        "-",
        "precision"
    ],
    "wof:name":"Laboratoires Carbonneaux",
    "wof:placetype":"venue"
},
  "geometry": {"coordinates":[2.492508,48.797832],"type":"Point"}
}