{
  "type": "Feature",
  "properties": {
    "addr:full":"19, Rue Sainte Catherine, 24100 Bergerac Bergerac Aquitaine 24100",
    "addr:housenumber":"19",
    "addr:postcode":"24100;24100",
    "addr:street":"Rue Sainte Catherine",
    "iso:country":"FR",
    "sg:address":"19, Rue Sainte Catherine, 24100 Bergerac",
    "sg:city":"Bergerac",
    "sg:orig_category":"Unclassifiable Establishments",
    "sg:phone":"+33 5 53 63 70 00",
    "sg:postcode":"24100",
    "sg:province":"Aquitaine",
    "wof:name":"B.p.c. - Banque Populaire Du Centre",
    "wof:placetype":"venue"
},
  "geometry": {"coordinates":[0.484117,44.854031],"type":"Point"}
}