{
  "type": "Feature",
  "properties": {
    "addr:full":"B.P. 238, 29834 Carhaix Plouguer C\u00e9dex^^2, Place de la Gare, 29270 Carhaix Plouguer Carhaix-Plouguer Bretagne 29270",
    "addr:housenumber":"b.p. 238",
    "addr:postcode":"29834;29270;29270",
    "addr:street":"Ce\u0301Dex^^2 Place De La Gare;Carhaix-Plouguer",
    "iso:country":"FR",
    "sg:address":"B.P. 238, 29834 Carhaix Plouguer C\u00e9dex^^2, Place de la Gare, 29270 Carhaix Plouguer",
    "sg:city":"Carhaix-Plouguer",
    "sg:orig_category":"Non-Classified Establishments",
    "sg:phone":"+33 2 98 93 08 06",
    "sg:postcode":"29270",
    "sg:province":"Bretagne",
    "wof:name":"T.p.r. S.a. - Soci\u00e9t\u00e9 De Travaux Publics Rohou",
    "wof:placetype":"venue"
},
  "geometry": {"coordinates":[-3.555118,48.202301],"type":"Point"}
}