{
  "type": "Feature",
  "properties": {
    "addr:full":"23 rue du G\u00e9n\u00e9ral Leclerc 94270 Le Kremlin Bicetre Ile de France 94270",
    "addr:housenumber":"23",
    "addr:postcode":"94270;94270",
    "addr:street":"Rue Du Ge\u0301Ne\u0301Ral Leclerc",
    "iso:country":"FR",
    "sg:address":"23 rue du G\u00e9n\u00e9ral Leclerc 94270 Le Kremlin Bicetre",
    "sg:classifiers":[
        {
            "category":"Manufacturing",
            "subcategory":"Glass & Minerals",
            "type":"Manufacturing & Wholesale Goods"
        }
    ],
    "sg:phone":"+33 1 46 58 82 32",
    "sg:postcode":"94270",
    "sg:province":"Ile de France",
    "sg:tags":[
        "engraving"
    ],
    "wof:name":"Germain Et Cie Sarl",
    "wof:placetype":"venue"
},
  "geometry": {"coordinates":[2.359547,48.813801],"type":"Point"}
}