{
  "type": "Feature",
  "properties": {
    "addr:full":"19, Av Le Corbusier, 59040 Lille C\u00e9dex Centre",
    "addr:postcode":"59040",
    "addr:street":"19 Av Le Corbusier",
    "iso:country":"FR",
    "sg:address":"19, Av Le Corbusier, 59040 Lille C\u00e9dex",
    "sg:orig_category":"Non-Classified Establishments",
    "sg:phone":"+33 3 20 63 15 58",
    "sg:province":"Centre",
    "wof:name":"Dexia Cr\u00e9dit Local De France",
    "wof:placetype":"venue"
},
  "geometry": {"coordinates":[3.071625,50.637745],"type":"Point"}
}