{
  "type": "Feature",
  "properties": {
    "addr:full":"15 Rue Jeanne D'Arc Rouen Haute Normandie 76000",
    "addr:housenumber":"15",
    "addr:postcode":"76000",
    "addr:street":"Rue Jeanne D'Arc;Haute Normandie",
    "iso:country":"FR",
    "sg:address":"15 Rue Jeanne D'Arc",
    "sg:city":"Rouen",
    "sg:classifiers":[
        {
            "category":"Banks & Credit Unions",
            "subcategory":"Financial Services",
            "type":"Services"
        }
    ],
    "sg:phone":"+33 2 35 71 70 63",
    "sg:postcode":"76000",
    "sg:province":"Haute Normandie",
    "sg:tags":[
        "banking",
        "finance",
        "insurance"
    ],
    "wof:name":"Barclays Bank Plc",
    "wof:placetype":"venue"
},
  "geometry": {"coordinates":[1.090708,49.442806],"type":"Point"}
}