{
  "type": "Feature",
  "properties": {
    "addr:full":"47 Avenue Montaigne 93160 Noisy Le Grand Ile de France",
    "addr:housenumber":"47",
    "addr:postcode":"93160",
    "addr:street":"Avenue Montaigne",
    "iso:country":"FR",
    "sg:address":"47 Avenue Montaigne 93160 Noisy Le Grand",
    "sg:classifiers":[
        {
            "category":"Manufacturing",
            "subcategory":"Printing",
            "type":"Manufacturing & Wholesale Goods"
        }
    ],
    "sg:phone":"+33 1 48 15 16 95",
    "sg:province":"Ile de France",
    "sg:tags":[
        "publishing"
    ],
    "wof:name":"Icone Graphic",
    "wof:placetype":"venue"
},
  "geometry": {"coordinates":[2.538096,48.846004],"type":"Point"}
}