{
  "type": "Feature",
  "properties": {
    "iso:country":"FR",
    "sg:address":"55 Rue Claude Delaroa 42000 St Etienne",
    "sg:orig_category":"Miscellaneous Products",
    "sg:phone":"+33 4 77 33 00 41",
    "sg:postcode":"42000",
    "sg:province":"Rhone-Alpes",
    "wof:name":"Garnier Armurier",
    "wof:placetype":"venue"
},
  "geometry": {"coordinates":[4.385626,45.428036],"type":"Point"}
}