{
  "type": "Feature",
  "properties": {
    "iso:country":"FR",
    "sg:address":"B.P. 6",
    "sg:city":"Tossiat",
    "sg:orig_category":"Non-Classified Establishments",
    "sg:phone":"+33 4 74 51 60 63",
    "sg:postcode":"01250",
    "sg:province":"Rhone-Alpes",
    "wof:name":"M.s.p. S.a.r.l. - M\u00e9tallerie Soudure Pontet",
    "wof:placetype":"venue"
},
  "geometry": {"coordinates":[5.316532,46.13921],"type":"Point"}
}