{
  "type": "Feature",
  "properties": {
    "addr:full":"B.P. 302, 38434 Echirolles C\u00e9dex^^2, Rue du Docteur Pascal - ZA du Rondeau, 38130 Echirolles Rhone-Alpes 38130",
    "addr:housenumber":"b.p. 302",
    "addr:postcode":"38434;38130;38130",
    "addr:street":"Rue Du Docteur Pascal Za Du Rondeau;Rhone-Alpes",
    "iso:country":"FR",
    "sg:address":"B.P. 302, 38434 Echirolles C\u00e9dex^^2, Rue du Docteur Pascal - ZA du Rondeau, 38130 Echirolles",
    "sg:orig_category":"Non-Classified Establishments",
    "sg:phone":"+33 4 76 09 14 51",
    "sg:postcode":"38130",
    "sg:province":"Rhone-Alpes",
    "wof:name":"Entreprises Paul Dervieux S.a.",
    "wof:placetype":"venue"
},
  "geometry": {"coordinates":[5.7194,45.149536],"type":"Point"}
}