{
  "type": "Feature",
  "properties": {
    "iso:country":"FR",
    "sg:address":"Les Farges 24580 Rouffignac St Cernin",
    "sg:city":"Fleurac",
    "sg:classifiers":[
        {
            "category":"Manufacturing",
            "subcategory":"Chemicals & Compounds",
            "type":"Manufacturing & Wholesale Goods"
        }
    ],
    "sg:phone":"+33 5 53 05 47 01",
    "sg:postcode":"24580",
    "sg:province":"Aquitaine",
    "sg:tags":[
        "pharmaceutical",
        "chemistry",
        "-",
        "by-product"
    ],
    "wof:name":"Alcal Chimie Sarl",
    "wof:placetype":"venue"
},
  "geometry": {"coordinates":[1.001274,45.008488],"type":"Point"}
}