{
  "type": "Feature",
  "properties": {
    "iso:country":"FR",
    "sg:address":"Centre d'Affaire Paris Nord - B\u00e2t Amp\u00e8re",
    "sg:city":"Le Blanc Mesnil",
    "sg:orig_category":"Unclassifiable Establishments",
    "sg:phone":"+33 1 48 67 12 38",
    "sg:postcode":"93150",
    "sg:province":"Ile de France",
    "wof:name":"Benecke Kaliko S.a.r.l.",
    "wof:placetype":"venue"
},
  "geometry": {"coordinates":[2.480913,48.935608],"type":"Point"}
}