{
  "type": "Feature",
  "properties": {
    "iso:country":"FR",
    "sg:address":"Rue du Vieux Four",
    "sg:city":"Saint Martin le Beau",
    "sg:orig_category":"Non-Classified Establishments",
    "sg:phone":"+33 2 47 45 72 00",
    "sg:postcode":"37270",
    "sg:province":"Centre",
    "wof:name":"Pullflex S.a.",
    "wof:placetype":"venue"
},
  "geometry": {"coordinates":[0.894445,47.364689],"type":"Point"}
}