{
  "type": "Feature",
  "properties": {
    "addr:full":"Avoriaz Parking De La Falaise 74110 Morzine Rhone-Alpes",
    "addr:postcode":"74110",
    "iso:country":"FR",
    "sg:address":"Avoriaz Parking De La Falaise 74110 Morzine",
    "sg:classifiers":[
        {
            "category":"Home & Garden",
            "subcategory":"Building Materials",
            "type":"Retail Goods"
        }
    ],
    "sg:phone":"+33 4 50 74 01 42",
    "sg:province":"Rhone-Alpes",
    "sg:tags":[
        "equipment",
        "energy",
        "-",
        "environment",
        "raw",
        "machinery"
    ],
    "wof:name":"Suez Lyonnaise Des Eaux",
    "wof:placetype":"venue"
},
  "geometry": {"coordinates":[6.701018,46.181168],"type":"Point"}
}