{
  "type": "Feature",
  "properties": {
    "iso:country":"FR",
    "sg:address":"33650 Cabanac et Villagrains",
    "sg:city":"Cabanac-et-Villagrains",
    "sg:orig_category":"Non-Classified Establishments",
    "sg:phone":"+33 5 57 54 17 90",
    "sg:postcode":"33650",
    "sg:province":"Aquitaine",
    "wof:name":"T.b.5 S.a.r.l. - Transport Bennes 5",
    "wof:placetype":"venue"
},
  "geometry": {"coordinates":[-0.553799,44.60627],"type":"Point"}
}