{
  "type": "Feature",
  "properties": {
    "iso:country":"FR",
    "sg:address":"2 Rue Clos Fours 78930 Guerville",
    "sg:classifiers":[
        {
            "category":"Professional",
            "subcategory":"Engineering",
            "type":"Services"
        }
    ],
    "sg:phone":"+33 1 30 98 49 49",
    "sg:postcode":"78930",
    "sg:province":"Ile de France",
    "sg:tags":[
        "machine",
        "-",
        "mechanical"
    ],
    "wof:name":"Otdi Sarl (otdi Sarl)",
    "wof:placetype":"venue"
},
  "geometry": {"coordinates":[1.732965,48.970383],"type":"Point"}
}