{
  "type": "Feature",
  "properties": {
    "iso:country":"FR",
    "sg:address":"89 Av Louis Coudant 58340 Cercy La Tour",
    "sg:city":"Montigny-sur-Canne",
    "sg:classifiers":[
        {
            "category":"Autos & Motor Vehicles",
            "subcategory":"Automobile Sales",
            "type":"Retail Goods"
        }
    ],
    "sg:phone":"+33 3 86 77 52 52",
    "sg:postcode":"58340",
    "sg:province":"Bourgogne",
    "sg:tags":[
        "equipment",
        "motor-cars",
        "transport"
    ],
    "wof:name":"Saurecia",
    "wof:placetype":"venue"
},
  "geometry": {"coordinates":[3.647461,46.860268],"type":"Point"}
}