{
  "type": "Feature",
  "properties": {
    "iso:country":"FR",
    "sg:address":"Le Gunin 73520 La Bridoire",
    "sg:classifiers":[
        {
            "category":"Manufacturing",
            "subcategory":"Chemicals & Compounds",
            "type":"Manufacturing & Wholesale Goods"
        }
    ],
    "sg:phone":"+33 4 76 31 25 26",
    "sg:postcode":"73520",
    "sg:province":"Rhone-Alpes",
    "sg:tags":[
        "pharmaceutical",
        "chemistry",
        "-",
        "by-product"
    ],
    "wof:name":"Zolpan Savoie Sa",
    "wof:placetype":"venue"
},
  "geometry": {"coordinates":[5.72153,45.533096],"type":"Point"}
}