{
  "type": "Feature",
  "properties": {
    "addr:full":"Quai Beauvais Chez Mlle Renault Aline 14230 La Cambe La Cambe Basse Normandie 14230",
    "addr:housenumber":"mlle;14230",
    "addr:postcode":"14230",
    "addr:street":"Quai Beauvais Chez;Aline;Cambe;Cambe Basse",
    "iso:country":"FR",
    "sg:address":"Quai Beauvais Chez Mlle Renault Aline 14230 La Cambe",
    "sg:city":"La Cambe",
    "sg:classifiers":[
        {
            "category":"Farming",
            "subcategory":"Farm & Veterinary Services",
            "type":"Manufacturing & Wholesale Goods"
        }
    ],
    "sg:phone":"+33 2 31 22 01 20",
    "sg:postcode":"14230",
    "sg:province":"Basse Normandie",
    "sg:tags":[
        "advice",
        "agriculture",
        "livestock",
        "business"
    ],
    "wof:name":"Euro Calisce",
    "wof:placetype":"venue"
},
  "geometry": {"coordinates":[-1.098561,49.271591],"type":"Point"}
}