{
  "type": "Feature",
  "properties": {
    "addr:full":"Le Moulin Neuf 22950 Tregueux Tr\u00e9gueux Bretagne 22950",
    "addr:postcode":"22950;22950",
    "addr:street":"Le Moulin Neuf",
    "iso:country":"FR",
    "sg:address":"Le Moulin Neuf 22950 Tregueux",
    "sg:city":"Tr\u00e9gueux",
    "sg:classifiers":[
        {
            "category":"Farming",
            "subcategory":"Farm & Veterinary Services",
            "type":"Manufacturing & Wholesale Goods"
        }
    ],
    "sg:phone":"+33 2 96 63 82 50",
    "sg:postcode":"22950",
    "sg:province":"Bretagne",
    "sg:tags":[
        "food",
        "product",
        "breeding",
        "animal",
        "related"
    ],
    "wof:name":"Codislait Distrib Prod Neolait",
    "wof:placetype":"venue"
},
  "geometry": {"coordinates":[-2.690908,48.481514],"type":"Point"}
}