{
  "type": "Feature",
  "properties": {
    "addr:full":"Av. Robert Frank La Rochette Ile de France 73110",
    "addr:postcode":"73110",
    "addr:street":"Av. Robert Frank La",
    "iso:country":"FR",
    "sg:address":"Av. Robert Frank",
    "sg:city":"La Rochette",
    "sg:orig_category":"Unclassifiable Establishments",
    "sg:phone":"+33 4 79 75 89 00",
    "sg:postcode":"73110",
    "sg:province":"Ile de France",
    "wof:name":"R.c.o. Savoie",
    "wof:placetype":"venue"
},
  "geometry": {"coordinates":[6.11121,45.452961],"type":"Point"}
}