{
  "type": "Feature",
  "properties": {
    "iso:country":"FR",
    "sg:address":"Quai Emile Paraff",
    "sg:city":"Cou\u00ebron",
    "sg:orig_category":"Unclassifiable Establishments",
    "sg:phone":"+33 2 40 38 67 50",
    "sg:postcode":"44220",
    "sg:province":"Pays de Loire",
    "wof:name":"N.g.k. Berylco France S.a.",
    "wof:placetype":"venue"
},
  "geometry": {"coordinates":[-1.724154,47.208885],"type":"Point"}
}