{
  "type": "Feature",
  "properties": {
    "addr:full":"17 Rue Du Gal De Gaulle 57050 Longeville Les Metz Lorraine 57050",
    "addr:housenumber":"17",
    "addr:postcode":"57050;57050",
    "addr:street":"Rue Du Gal De Gaulle",
    "iso:country":"FR",
    "sg:address":"17 Rue Du Gal De Gaulle 57050 Longeville Les Metz",
    "sg:classifiers":[
        {
            "category":"Utilities",
            "subcategory":"Electric",
            "type":"Services"
        }
    ],
    "sg:phone":"+33 3 87 31 89 00",
    "sg:postcode":"57050",
    "sg:province":"Lorraine",
    "sg:tags":[
        "electricity",
        "electronic",
        "electrical",
        "equipment"
    ],
    "wof:name":"Forclum Lorraine",
    "wof:placetype":"venue"
},
  "geometry": {"coordinates":[6.137297,49.113312],"type":"Point"}
}