{
  "type": "Feature",
  "properties": {
    "iso:country":"FR",
    "sg:address":"53 rue Stanislas; Nancy; 54009",
    "sg:classifiers":[
        {
            "category":"Banks & Credit Unions",
            "subcategory":"Bank",
            "type":"Services"
        }
    ],
    "sg:phone":"+33 3383173131",
    "sg:province":"Rhone-Alpes",
    "wof:name":"Banque Francaise Du Commerce, Exterieur",
    "wof:placetype":"venue"
},
  "geometry": {"coordinates":[6.177004,48.691467],"type":"Point"}
}