{
  "type": "Feature",
  "properties": {
    "addr:full":"1 R De Mesmerien 29200 Brest Brest Bretagne 29200",
    "addr:housenumber":"1",
    "addr:postcode":"29200;29200",
    "addr:street":"R De Mesmerien",
    "iso:country":"FR",
    "sg:address":"1 R De Mesmerien 29200 Brest",
    "sg:city":"Brest",
    "sg:classifiers":[
        {
            "category":"Manufacturing",
            "subcategory":"Chemicals & Compounds",
            "type":"Manufacturing & Wholesale Goods"
        }
    ],
    "sg:phone":"+33 2 98 34 60 00",
    "sg:postcode":"29200",
    "sg:province":"Bretagne",
    "sg:tags":[
        "pharmaceutical",
        "energy",
        "chemistry",
        "-",
        "by-product"
    ],
    "wof:name":"Sofiquem",
    "wof:placetype":"venue"
},
  "geometry": {"coordinates":[-4.46664,48.422329],"type":"Point"}
}