{
  "type": "Feature",
  "properties": {
    "iso:country":"FR",
    "sg:address":"30 Rue Des Saulniers 35370 Argentre Du Plessis",
    "sg:city":"Argentr\u00e9-du-Plessis",
    "sg:classifiers":[
        {
            "category":"Autos & Motor Vehicles",
            "subcategory":"Automobile Sales",
            "type":"Retail Goods"
        }
    ],
    "sg:phone":"+33 2 99 96 56 46",
    "sg:postcode":"35370",
    "sg:province":"Bretagne",
    "sg:tags":[
        "equipment",
        "motor-cars",
        "transport"
    ],
    "wof:name":"Etablissements Safar",
    "wof:placetype":"venue"
},
  "geometry": {"coordinates":[-1.16302,48.056499],"type":"Point"}
}