{
  "type": "Feature",
  "properties": {
    "iso:country":"FR",
    "sg:address":"71, Rue de la Rabaterie, 37700 Saint Pierre des Corps",
    "sg:city":"La Ville-aux-Dames",
    "sg:orig_category":"Non-Classified Establishments",
    "sg:phone":"+33 2 47 44 06 68",
    "sg:postcode":"37700",
    "sg:province":"Centre",
    "wof:name":"T.f.m S.a.r.l.",
    "wof:placetype":"venue"
},
  "geometry": {"coordinates":[0.726164,47.392071],"type":"Point"}
}