{
  "type": "Feature",
  "properties": {
    "addr:full":"Lieu-Dit L'Homey 42160 St Cyprien Rhone-Alpes 42160",
    "addr:postcode":"42160;42160",
    "addr:street":"Lieu-Dit L'Homey;Rhone-Alpes",
    "iso:country":"FR",
    "sg:address":"Lieu-Dit L'Homey 42160 St Cyprien",
    "sg:classifiers":[
        {
            "category":"Government",
            "subcategory":"Department Of Motor Vehicles",
            "type":"Public Place"
        }
    ],
    "sg:phone":"+33 4 77 55 54 53",
    "sg:postcode":"42160",
    "sg:province":"Rhone-Alpes",
    "sg:tags":[
        "town",
        "citymobiles",
        "different",
        "drive",
        "kind"
    ],
    "wof:name":"Forges De La Becque S.a.",
    "wof:placetype":"venue"
},
  "geometry": {"coordinates":[1.04446,44.831539],"type":"Point"}
}