{
  "type": "Feature",
  "properties": {
    "iso:country":"FR",
    "sg:address":"Rue Usine",
    "sg:city":"Brousseval",
    "sg:orig_category":"Non-Classified Establishments",
    "sg:phone":"+33 3 25 56 74 74",
    "sg:postcode":"52130",
    "sg:province":"Champagne",
    "wof:name":"Somborn Lang Ferry Et Compagnie S.a.",
    "wof:placetype":"venue"
},
  "geometry": {"coordinates":[4.9476,48.498482],"type":"Point"}
}