{
  "type": "Feature",
  "properties": {
    "addr:full":"4BIS rue Henri Becquerel 69740 Genas Rhone-Alpes 69740",
    "addr:housenumber":"4bis",
    "addr:postcode":"69740;69740",
    "addr:street":"Rue Henri Becquerel",
    "iso:country":"FR",
    "sg:address":"4BIS rue Henri Becquerel 69740 Genas",
    "sg:classifiers":[
        {
            "category":"Home & Garden",
            "subcategory":"Building Materials",
            "type":"Retail Goods"
        }
    ],
    "sg:phone":"+33 4 72 79 10 30",
    "sg:postcode":"69740",
    "sg:province":"Rhone-Alpes",
    "sg:tags":[
        "operated",
        "gates",
        "electrically"
    ],
    "wof:name":"Afca S.a.",
    "wof:placetype":"venue"
},
  "geometry": {"coordinates":[4.994526,45.711063],"type":"Point"}
}