{
  "type": "Feature",
  "properties": {
    "iso:country":"FR",
    "sg:address":"25650 Gilley",
    "sg:orig_category":"Unclassifiable Establishments",
    "sg:phone":"+33 3 81 43 32 76",
    "sg:province":"Franche Comt\u00e9",
    "wof:name":"Meca - Carbure S.a.",
    "wof:placetype":"venue"
},
  "geometry": {"coordinates":[6.480621,47.046806],"type":"Point"}
}