{
  "type": "Feature",
  "properties": {
    "iso:country":"FR",
    "sg:address":"Le Grand Verdus 33670 SADIRAC",
    "sg:city":"Sadirac",
    "sg:classifiers":[
        {
            "category":"Wholesale",
            "subcategory":"Wine & Distilled Alcoholic Beverages",
            "type":"Manufacturing & Wholesale Goods"
        }
    ],
    "sg:phone":"+33 5 56 30 50 90",
    "sg:postcode":"33670",
    "sg:province":"Aquitaine",
    "sg:tags":[
        "french"
    ],
    "wof:name":"Scea Philippe Et Antoine Le Grix De La Salle",
    "wof:placetype":"venue"
},
  "geometry": {"coordinates":[-0.394619,44.796581],"type":"Point"}
}