{
  "type": "Feature",
  "properties": {
    "addr:full":"B.P. 1139, 03103 Montlu\u00e7on C\u00e9dex^^Rue Eug\u00e8ne Sue - ZI Blanzat, 03100 Montlu\u00e7on Montlu\u00e7on Auvergne 03100",
    "addr:postcode":"03103;03100;03100",
    "addr:street":"B.P. 1139;Euge\u0300Ne Sue Zi",
    "iso:country":"FR",
    "sg:address":"B.P. 1139, 03103 Montlu\u00e7on C\u00e9dex^^Rue Eug\u00e8ne Sue - ZI Blanzat, 03100 Montlu\u00e7on",
    "sg:city":"Montlu\u00e7on",
    "sg:orig_category":"Non-Classified Establishments",
    "sg:phone":"+33 4 70 03 47 47",
    "sg:postcode":"03100",
    "sg:province":"Auvergne",
    "wof:name":"Soci\u00e9t\u00e9 Le R\u00e9servoir S.a.",
    "wof:placetype":"venue"
},
  "geometry": {"coordinates":[2.59568,46.343418],"type":"Point"}
}