{
  "type": "Feature",
  "properties": {
    "addr:full":"22 Rue Denis Epitalon 42000 St Etienne Rhone-Alpes 42000",
    "addr:housenumber":"22",
    "addr:postcode":"42000;42000",
    "addr:street":"Rue Denis Epitalon",
    "iso:country":"FR",
    "sg:address":"22 Rue Denis Epitalon 42000 St Etienne",
    "sg:classifiers":[
        {
            "category":"Shopping",
            "subcategory":"Computers & Home Electronics",
            "type":"Retail Goods"
        }
    ],
    "sg:phone":"+33 4 77 32 00 93",
    "sg:postcode":"42000",
    "sg:province":"Rhone-Alpes",
    "sg:tags":[
        "electronic",
        "electrical",
        "equipment"
    ],
    "wof:name":"Brondelle Joly Sarl",
    "wof:placetype":"venue"
},
  "geometry": {"coordinates":[4.380017,45.43087],"type":"Point"}
}