{
  "type": "Feature",
  "properties": {
    "addr:full":"49, Rue de Toul, 54840 Velaine en Haye Lorraine 54840",
    "addr:housenumber":"49",
    "addr:postcode":"54840;54840",
    "addr:street":"Rue De Toul",
    "iso:country":"FR",
    "sg:address":"49, Rue de Toul, 54840 Velaine en Haye",
    "sg:orig_category":"Non-Classified Establishments",
    "sg:phone":"+33 3 83 28 20 92",
    "sg:postcode":"54840",
    "sg:province":"Lorraine",
    "wof:name":"B.c.s.e. S.a. - Bureau Central S\u00e9curit\u00e9 Electronique",
    "wof:placetype":"venue"
},
  "geometry": {"coordinates":[6.037742,48.691788],"type":"Point"}
}