{
  "type": "Feature",
  "properties": {
    "addr:full":"37 R M\u00e9nantille 88100 Saint Die Lorraine 88100",
    "addr:housenumber":"37",
    "addr:postcode":"88100;88100",
    "addr:street":"R Me\u0301Nantille",
    "iso:country":"FR",
    "sg:address":"37 R M\u00e9nantille 88100 Saint Die",
    "sg:classifiers":[
        {
            "category":"Professional",
            "subcategory":"Engineering",
            "type":"Services"
        }
    ],
    "sg:phone":"+33 3 29 55 06 22",
    "sg:postcode":"88100",
    "sg:province":"Lorraine",
    "sg:tags":[
        "steel",
        "metallurgy",
        "metal",
        "-",
        "machine",
        "metalworking",
        "mechanical"
    ],
    "wof:name":"Deodatienne De Mecanique Appliquee",
    "wof:placetype":"venue"
},
  "geometry": {"coordinates":[6.89995,48.249744],"type":"Point"}
}