{
  "type": "Feature",
  "properties": {
    "addr:full":"1, Rue de la Petite Fin, 21121 Fontaine l\u00e8s Dijon Ahuy Bourgogne 21121",
    "addr:housenumber":"1",
    "addr:postcode":"21121;21121",
    "addr:street":"Rue De La Petite Fin;Bourgogne",
    "iso:country":"FR",
    "sg:address":"1, Rue de la Petite Fin, 21121 Fontaine l\u00e8s Dijon",
    "sg:city":"Ahuy",
    "sg:orig_category":"Non-Classified Establishments",
    "sg:phone":"+33 3 80 56 66 47",
    "sg:postcode":"21121",
    "sg:province":"Bourgogne",
    "wof:name":"La Mouette S.a.r.l.",
    "wof:placetype":"venue"
},
  "geometry": {"coordinates":[5.028811,47.349155],"type":"Point"}
}