{
  "type": "Feature",
  "properties": {
    "iso:country":"FR",
    "sg:address":"Rue Georges Claude 57365 ENNERY",
    "sg:classifiers":[
        {
            "category":"Parking",
            "subcategory":"Garage",
            "type":"Transportation"
        }
    ],
    "sg:phone":"+33 3 87 73 68 59",
    "sg:province":"Lorraine",
    "sg:tags":[
        "bulk",
        "good"
    ],
    "wof:name":"Translo Sa",
    "wof:placetype":"venue"
},
  "geometry": {"coordinates":[6.227205,49.231865],"type":"Point"}
}