{
  "type": "Feature",
  "properties": {
    "iso:country":"FR",
    "sg:address":"1777, Rte de Gen\u00e8ve, 01700 Beynost",
    "sg:orig_category":"Non-Classified Establishments",
    "sg:phone":"+33 4 78 55 67 19",
    "sg:postcode":"01700",
    "sg:province":"Rhone-Alpes",
    "wof:name":"Abd-demeco S.a.",
    "wof:placetype":"venue"
},
  "geometry": {"coordinates":[4.99289,45.833389],"type":"Point"}
}