{
  "type": "Feature",
  "properties": {
    "addr:full":"Ch\u00e2teau B\u00e9lingard 24240 Pomport Pomport Aquitaine 24240",
    "addr:postcode":"24240;24240",
    "iso:country":"FR",
    "sg:address":"Ch\u00e2teau B\u00e9lingard 24240 Pomport",
    "sg:city":"Pomport",
    "sg:orig_category":"Unclassifiable Establishments",
    "sg:phone":"+33 5 53 58 28 03",
    "sg:postcode":"24240",
    "sg:province":"Aquitaine",
    "wof:name":"Comte De Bosredon S.c.e.a.",
    "wof:placetype":"venue"
},
  "geometry": {"coordinates":[0.433954,44.798916],"type":"Point"}
}