{
  "type": "Feature",
  "properties": {
    "addr:full":"336, Rue Alfred Krug, 54000 Nancy Lorraine",
    "addr:housenumber":"336",
    "addr:postcode":"54000",
    "addr:street":"Rue Alfred Krug",
    "iso:country":"FR",
    "sg:address":"336, Rue Alfred Krug, 54000 Nancy",
    "sg:orig_category":"Unclassifiable Establishments",
    "sg:phone":"+33 3 83 32 01 75",
    "sg:province":"Lorraine",
    "wof:name":"Photogravure Mangeolle S.a.r.l.",
    "wof:placetype":"venue"
},
  "geometry": {"coordinates":[6.20658,48.682869],"type":"Point"}
}