{
  "type": "Feature",
  "properties": {
    "addr:full":"1, Rue du Mont Gerbault, 93106 Epinay sur Seine C\u00e9dex Picardie",
    "addr:housenumber":"1",
    "addr:postcode":"93106",
    "addr:street":"Rue Du Mont Gerbault",
    "iso:country":"FR",
    "sg:address":"1, Rue du Mont Gerbault, 93106 Epinay sur Seine C\u00e9dex",
    "sg:orig_category":"Non-Classified Establishments",
    "sg:phone":"+33 1 48 41 30 00",
    "sg:province":"Picardie",
    "wof:name":"Entreprise Fradelizi S.a.",
    "wof:placetype":"venue"
},
  "geometry": {"coordinates":[-119.84139999999999,34.414268],"type":"Point"}
}