{
  "type": "Feature",
  "properties": {
    "addr:full":"6, All\u00e9e Guerl\u00e9dan, 35135 Chantepie Chantepie Bretagne 35135",
    "addr:housenumber":"6",
    "addr:postcode":"35135;35135",
    "addr:street":"Alle\u0301E Guerle\u0301Dan",
    "iso:country":"FR",
    "sg:address":"6, All\u00e9e Guerl\u00e9dan, 35135 Chantepie",
    "sg:city":"Chantepie",
    "sg:orig_category":"Unclassifiable Establishments",
    "sg:phone":"+33 2 99 41 61 61",
    "sg:postcode":"35135",
    "sg:province":"Bretagne",
    "wof:name":"Ardial Fiduciaire S.a.",
    "wof:placetype":"venue"
},
  "geometry": {"coordinates":[-1.630435,48.085506],"type":"Point"}
}