{
  "type": "Feature",
  "properties": {
    "addr:full":"7, All\u00e9e du Combattant Mouchotte, 91781 Wissous C\u00e9dex Ile de France",
    "addr:housenumber":"7",
    "addr:postcode":"91781",
    "addr:street":"Alle\u0301E Du Combattant Mouchotte",
    "iso:country":"FR",
    "sg:address":"7, All\u00e9e du Combattant Mouchotte, 91781 Wissous C\u00e9dex",
    "sg:orig_category":"Unclassifiable Establishments",
    "sg:phone":"+33 1 49 75 33 85",
    "sg:province":"Ile de France",
    "wof:name":"Onet Propret\u00e9 S.a.",
    "wof:placetype":"venue"
},
  "geometry": {"coordinates":[2.32742,48.730991],"type":"Point"}
}