{
  "type": "Feature",
  "properties": {
    "iso:country":"FR",
    "sg:address":"Bd Dambourney - ZI",
    "sg:city":"Oissel",
    "sg:orig_category":"Non-Classified Establishments",
    "sg:phone":"+33 2 35 64 73 24",
    "sg:postcode":"76350",
    "sg:province":"Haute Normandie",
    "wof:name":"Jorge Patrice S.a.",
    "wof:placetype":"venue"
},
  "geometry": {"coordinates":[1.095915,49.341049],"type":"Point"}
}