{
  "type": "Feature",
  "properties": {
    "iso:country":"FR",
    "sg:address":"Rue Alfred Nobel",
    "sg:city":"Feyzin",
    "sg:orig_category":"Unclassifiable Establishments",
    "sg:phone":"+33 4 72 89 07 40",
    "sg:postcode":"69320",
    "sg:province":"Rhone-Alpes",
    "wof:name":"Sika S.a.",
    "wof:placetype":"venue"
},
  "geometry": {"coordinates":[4.853535,45.672749],"type":"Point"}
}