{
  "type": "Feature",
  "properties": {
    "iso:country":"FR",
    "sg:address":"B.P. 174, 81103 Castres C\u00e9dex^^46, Av. Charles de Gaulle, 81100 Castres",
    "sg:orig_category":"Non-Classified Establishments",
    "sg:phone":"+33 5 63 62 53 00",
    "sg:postcode":"81100",
    "sg:province":"Midi Pyr\u00e9n\u00e9es",
    "wof:name":"E.d.f. Et Gaz De France - Electricit\u00e9 De France Et Gaz De France",
    "wof:placetype":"venue"
},
  "geometry": {"coordinates":[2.257356,43.56094],"type":"Point"}
}