{
  "type": "Feature",
  "properties": {
    "addr:full":"322, Cours des Fr\u00e8res Folgauld, 84140 Montfavet Midi Pyr\u00e9n\u00e9es",
    "addr:housenumber":"322",
    "addr:postcode":"84140",
    "addr:street":"Cours Des Fre\u0300Res Folgauld",
    "iso:country":"FR",
    "sg:address":"322, Cours des Fr\u00e8res Folgauld, 84140 Montfavet",
    "sg:orig_category":"Non-Classified Establishments",
    "sg:phone":"+33 4 90 32 01 46",
    "sg:province":"Midi Pyr\u00e9n\u00e9es",
    "wof:name":"Richaud Fran\u00e7ois S.a.",
    "wof:placetype":"venue"
},
  "geometry": {"coordinates":[4.870683,43.938721],"type":"Point"}
}