{
  "type": "Feature",
  "properties": {
    "iso:country":"FR",
    "sg:address":"99, Av. des Aygalades - Parc Lavoisier - B\u00e2t. A, 13015 Marseille",
    "sg:orig_category":"Non-Classified Establishments",
    "sg:phone":"+33 4 91 60 70 70",
    "sg:province":"Midi Pyr\u00e9n\u00e9es",
    "wof:name":"Securyparc S.a.",
    "wof:placetype":"venue"
},
  "geometry": {"coordinates":[5.36684,43.337742],"type":"Point"}
}