{
  "type": "Feature",
  "properties": {
    "addr:full":"14 Rue Marcel Paul 17021 La Rochelle Cedex 1 La Rochelle Poitou-Charentes 17000",
    "addr:housenumber":"14",
    "addr:postcode":"17021;17000",
    "addr:street":"Rue Marcel Paul;Rochelle",
    "iso:country":"FR",
    "sg:address":"14 Rue Marcel Paul 17021 La Rochelle Cedex 1",
    "sg:city":"La Rochelle",
    "sg:classifiers":[
        {
            "category":"Utilities",
            "subcategory":"Electric",
            "type":"Services"
        }
    ],
    "sg:phone":"+33 5 46 68 36 36",
    "sg:postcode":"17000",
    "sg:province":"Poitou-Charentes",
    "sg:tags":[
        "electricity",
        "raw",
        "energy",
        "material"
    ],
    "wof:name":"Electricite De France (edf)",
    "wof:placetype":"venue"
},
  "geometry": {"coordinates":[-1.148598,46.166416],"type":"Point"}
}