{
  "type": "Feature",
  "properties": {
    "iso:country":"FR",
    "sg:address":"Av des Maurettes",
    "sg:city":"Villeneuve Loubet",
    "sg:orig_category":"Unclassifiable Establishments",
    "sg:phone":"+33 4 92 13 36 66",
    "sg:postcode":"06270",
    "sg:province":"Provence-Alpes-C\u00f4te d'Azur",
    "wof:name":"T.c.a. S.a. - Transfert Et Conditionnement De L'air",
    "wof:placetype":"venue"
},
  "geometry": {"coordinates":[7.133352,43.62957],"type":"Point"}
}