{
  "type": "Feature",
  "properties": {
    "addr:full":"19, Rue du Port - ZI du Parc de l'Ile, 92000 Nanterre Ile de France 92000",
    "addr:housenumber":"19",
    "addr:postcode":"92000;92000",
    "addr:street":"Rue Du Port Zi Du Parc De L'Ile",
    "iso:country":"FR",
    "sg:address":"19, Rue du Port - ZI du Parc de l'Ile, 92000 Nanterre",
    "sg:orig_category":"Non-Classified Establishments",
    "sg:phone":"+33 1 47 29 88 88",
    "sg:postcode":"92000",
    "sg:province":"Ile de France",
    "wof:name":"C\u00e9cilor S.a.r.l.",
    "wof:placetype":"venue"
},
  "geometry": {"coordinates":[2.178653,48.893318],"type":"Point"}
}