{
  "type": "Feature",
  "properties": {
    "addr:full":"Rte de Lan\u00e7on - La Cabard\u00e8le Lan\u00e7on Provence Limousin 13680",
    "addr:postcode":"13680",
    "addr:street":"Rte De Lanc\u0327On La Cabarde\u0300Le",
    "iso:country":"FR",
    "sg:address":"Rte de Lan\u00e7on - La Cabard\u00e8le",
    "sg:city":"Lan\u00e7on Provence",
    "sg:orig_category":"Non-Classified Establishments",
    "sg:phone":"+33 4 90 42 71 32",
    "sg:postcode":"13680",
    "sg:province":"Limousin",
    "wof:name":"S.i.t.a. S.a.r.l. - Soci\u00e9t\u00e9 D'irrigation Et Technologie Agricole",
    "wof:placetype":"venue"
},
  "geometry": {"coordinates":[5.12418,43.590092],"type":"Point"}
}