{
  "type": "Feature",
  "properties": {
    "addr:full":"77 Bd Du Cami-Seali\u00e9 64000 Pau Pau Aquitaine 64000",
    "addr:housenumber":"77",
    "addr:postcode":"64000;64000",
    "addr:street":"Bd Du Cami-Sealie\u0301",
    "iso:country":"FR",
    "sg:address":"77 Bd Du Cami-Seali\u00e9 64000 Pau",
    "sg:city":"Pau",
    "sg:classifiers":[
        {
            "category":"Professional",
            "type":"Services"
        }
    ],
    "sg:phone":"+33 5 59 84 81 84",
    "sg:postcode":"64000",
    "sg:province":"Aquitaine",
    "sg:tags":[
        "transport",
        "road"
    ],
    "wof:name":"Ambulances Larreche",
    "wof:placetype":"venue"
},
  "geometry": {"coordinates":[-0.316632,43.323143],"type":"Point"}
}