{
  "type": "Feature",
  "properties": {
    "addr:full":"265 rue Pierre Seghers 84000 Avignon Provence-Alpes-C\u00f4te d'Azur",
    "addr:housenumber":"265",
    "addr:postcode":"84000",
    "addr:street":"Rue Pierre Seghers",
    "iso:country":"FR",
    "sg:address":"265 rue Pierre Seghers 84000 Avignon",
    "sg:classifiers":[
        {
            "category":"Real Estate",
            "subcategory":"Real Estate Agent",
            "type":"Services"
        }
    ],
    "sg:phone":"+33 4 90 87 08 09",
    "sg:province":"Provence-Alpes-C\u00f4te d'Azur",
    "sg:tags":[
        "sealing",
        "material",
        "swimming-pool"
    ],
    "wof:name":"Euro Piscines Service Sarl",
    "wof:placetype":"venue"
},
  "geometry": {"coordinates":[4.838564,43.927731],"type":"Point"}
}