{
  "type": "Feature",
  "properties": {
    "addr:full":"55 Rue Saint-Didier 75116 Paris Rhone-Alpes",
    "addr:housenumber":"55",
    "addr:postcode":"75116",
    "addr:street":"Rue Saint-Didier",
    "iso:country":"FR",
    "sg:address":"55 Rue Saint-Didier 75116 Paris",
    "sg:classifiers":[
        {
            "category":"Health Services",
            "subcategory":"Medical Lab",
            "type":"Services"
        }
    ],
    "sg:phone":"+33 1 53 70 64 80",
    "sg:province":"Rhone-Alpes",
    "sg:tags":[
        "chemical",
        "pharmaceutical",
        "pharmacy"
    ],
    "wof:name":"Laboratoire D Eylau",
    "wof:placetype":"venue"
},
  "geometry": {"coordinates":[2.282195,48.867363],"type":"Point"}
}