{
  "type": "Feature",
  "properties": {
    "iso:country":"FR",
    "sg:address":"3 rue Jean Maire; Arnay le Duc",
    "sg:classifiers":[
        {
            "category":"Banks & Credit Unions",
            "subcategory":"Bank",
            "type":"Services"
        }
    ],
    "sg:phone":"+33 3380901012",
    "sg:province":"Champagne",
    "wof:name":"Banque Populaire De, Bourgogne (b.p.b)",
    "wof:placetype":"venue"
},
  "geometry": {"coordinates":[4.486348,47.130249],"type":"Point"}
}