{
  "type": "Feature",
  "properties": {
    "iso:country":"FR",
    "sg:address":"B.P. 34, 29250 Saint Pol de L\u00e9on C\u00e9dex^^ZI de Kerranou, 29250 Saint Pol de L\u00e9on",
    "sg:city":"Plougoulm",
    "sg:orig_category":"Non-Classified Establishments",
    "sg:phone":"+33 2 98 24 41 00",
    "sg:postcode":"29250",
    "sg:province":"Bretagne",
    "wof:name":"Bdl Tambour Moteur S.a.s.",
    "wof:placetype":"venue"
},
  "geometry": {"coordinates":[-4.000417,48.669865],"type":"Point"}
}