{
  "type": "Feature",
  "properties": {
    "iso:country":"FR",
    "sg:address":"ZF Lyon Sant Exup\u00e9ry A\u00e9roport",
    "sg:city":"Lyon",
    "sg:orig_category":"Unclassifiable Establishments",
    "sg:phone":"+33 4 72 23 75 00",
    "sg:postcode":"69120",
    "sg:province":"Rhone-Alpes",
    "wof:name":"Scac Air Service S.a.",
    "wof:placetype":"venue"
},
  "geometry": {"coordinates":[4.916895,45.779022],"type":"Point"}
}