{
  "type": "Feature",
  "properties": {
    "addr:full":"ZI De Maingournois 28130 MAINTENON Maintenon Centre 28130",
    "addr:postcode":"28130;28130",
    "addr:street":"Zi De Maingournois",
    "iso:country":"FR",
    "sg:address":"ZI De Maingournois 28130 MAINTENON",
    "sg:city":"Maintenon",
    "sg:orig_category":"Nail Polish And Nail Polish Remover",
    "sg:phone":"+33 2 37 18 25 00",
    "sg:postcode":"28130",
    "sg:province":"Centre",
    "wof:name":"Fiabila S.a.",
    "wof:placetype":"venue"
},
  "geometry": {"coordinates":[1.577555,48.586205],"type":"Point"}
}