{
  "type": "Feature",
  "properties": {
    "iso:country":"FR",
    "sg:address":"7 Rue Pascal 93120 La Courneuve",
    "sg:orig_category":"Chemicals and Pharmaceuticals Chemistry - by-products Finished goods - metallic Mechanical Engineeri",
    "sg:phone":"+33 1 48 35 12 18",
    "sg:postcode":"93120",
    "sg:province":"Ile de France",
    "wof:name":"Recca Sarl",
    "wof:placetype":"venue"
},
  "geometry": {"coordinates":[2.401761,48.927368],"type":"Point"}
}