{
  "type": "Feature",
  "properties": {
    "addr:full":"B.P. 7, 25190 Villars sous Dampjoux^^Rue du Stade, 25190 Villars sous Dampjoux Franche Comt\u00e9",
    "addr:housenumber":"7",
    "addr:postcode":"25190;25190",
    "addr:street":"B.P.;Dampjoux^^Rue;Stade;Franche Comte\u0301",
    "iso:country":"FR",
    "sg:address":"B.P. 7, 25190 Villars sous Dampjoux^^Rue du Stade, 25190 Villars sous Dampjoux",
    "sg:orig_category":"Non-Classified Establishments",
    "sg:phone":"+33 3 81 92 29 26",
    "sg:province":"Franche Comt\u00e9",
    "wof:name":"Vautrin S.a.r.l.",
    "wof:placetype":"venue"
},
  "geometry": {"coordinates":[6.691455,47.301331],"type":"Point"}
}