{
  "type": "Feature",
  "properties": {
    "addr:full":"14, Rue du Ballon - ZI les RIchardets, 93165 Noisy le Grand C\u00e9dex Poitou-Charentes",
    "addr:housenumber":"14",
    "addr:postcode":"93165",
    "addr:street":"Rue Du Ballon Zi Les Richardets;Ce\u0301Dex",
    "iso:country":"FR",
    "sg:address":"14, Rue du Ballon - ZI les RIchardets, 93165 Noisy le Grand C\u00e9dex",
    "sg:orig_category":"Non-Classified Establishments",
    "sg:phone":"+33 1 48 15 00 30",
    "sg:province":"Poitou-Charentes",
    "wof:name":"Parfums Balmain S.a.",
    "wof:placetype":"venue"
},
  "geometry": {"coordinates":[2.553644,48.848892],"type":"Point"}
}