{
  "type": "Feature",
  "properties": {
    "iso:country":"FR",
    "sg:address":"49, Rte d'Ennezat, 63200 Riom",
    "sg:city":"Riom",
    "sg:orig_category":"Unclassifiable Establishments",
    "sg:phone":"+33 4 73 64 54 10",
    "sg:postcode":"63200",
    "sg:province":"Auvergne",
    "wof:name":"S.e.i.a. S.a.r.l. - Soci\u00e9t\u00e9 D'equipement Pour L'industrie Et L'agriculture",
    "wof:placetype":"venue"
},
  "geometry": {"coordinates":[3.130659,45.892258],"type":"Point"}
}