{
  "type": "Feature",
  "properties": {
    "addr:full":"535, Rue Pierre et Marie Curie - Zone Industrielle, 54710 Ludres Lorraine",
    "addr:housenumber":"535",
    "addr:postcode":"54710",
    "addr:street":"Rue Pierre Et Marie Curie Zone Industrielle",
    "iso:country":"FR",
    "sg:address":"535, Rue Pierre et Marie Curie - Zone Industrielle, 54710 Ludres",
    "sg:orig_category":"Unclassifiable Establishments",
    "sg:phone":"+33 3 83 59 40 40",
    "sg:province":"Lorraine",
    "wof:name":"Elyo Nord Est S.a.",
    "wof:placetype":"venue"
},
  "geometry": {"coordinates":[6.161059,48.621563],"type":"Point"}
}