{
  "type": "Feature",
  "properties": {
    "iso:country":"FR",
    "sg:address":"47, Rue Principale du Port, 92230 Gennevilliers",
    "sg:orig_category":"Unclassifiable Establishments",
    "sg:phone":"+33 1 47 92 45 45",
    "sg:province":"Ile de France",
    "wof:name":"Transeuro Desbordes Worldvide Relocation S.a.",
    "wof:placetype":"venue"
},
  "geometry": {"coordinates":[2.273237,48.93684],"type":"Point"}
}