{
  "type": "Feature",
  "properties": {
    "addr:full":"305 rte de Schirmeck; Lingolsheim; 67383 Schirmeck Alsace 67130",
    "addr:housenumber":"305",
    "addr:postcode":"67383;67130",
    "addr:street":"Rte De Schirmeck",
    "iso:country":"FR",
    "sg:address":"305 rte de Schirmeck; Lingolsheim; 67383",
    "sg:city":"Schirmeck",
    "sg:classifiers":[
        {
            "category":"Banks & Credit Unions",
            "subcategory":"Bank",
            "type":"Services"
        }
    ],
    "sg:phone":"+33 3 88 78 85 85",
    "sg:postcode":"67130",
    "sg:province":"Alsace",
    "wof:name":"Credit Industriel D'alsace, Et De Lorraine Sa",
    "wof:placetype":"venue"
},
  "geometry": {"coordinates":[7.68126,48.554295],"type":"Point"}
}