{
  "type": "Feature",
  "properties": {
    "addr:full":"Les Beluzes 42720 Pouilly Sous Charlieu Rhone-Alpes 42720",
    "addr:postcode":"42720;42720",
    "iso:country":"FR",
    "sg:address":"Les Beluzes 42720 Pouilly Sous Charlieu",
    "sg:orig_category":"Miscellaneous Products",
    "sg:phone":"+33 4 77 69 30 00",
    "sg:postcode":"42720",
    "sg:province":"Rhone-Alpes",
    "wof:name":"Val De Seille Sa",
    "wof:placetype":"venue"
},
  "geometry": {"coordinates":[4.16401,46.097897],"type":"Point"}
}