{
  "type": "Feature",
  "properties": {
    "addr:full":"4 Rue De Strasbourg 14000 Caen Caen Basse Normandie 14000",
    "addr:housenumber":"4",
    "addr:postcode":"14000;14000",
    "addr:street":"Rue De Strasbourg",
    "iso:country":"FR",
    "sg:address":"4 Rue De Strasbourg 14000 Caen",
    "sg:city":"Caen",
    "sg:classifiers":[
        {
            "category":"Banks & Credit Unions",
            "subcategory":"Financial Services",
            "type":"Services"
        }
    ],
    "sg:phone":"+33 2 31 39 95 70",
    "sg:postcode":"14000",
    "sg:province":"Basse Normandie",
    "sg:tags":[
        "banking",
        "insurance",
        "institution",
        "finance"
    ],
    "wof:name":"Credit Du Nord",
    "wof:placetype":"venue"
},
  "geometry": {"coordinates":[-0.364302,49.182762],"type":"Point"}
}