{
  "type": "Feature",
  "properties": {
    "iso:country":"FR",
    "sg:address":"Fraytet 47150 Montagnac sur L\u00e8de",
    "sg:city":"Gavaudun",
    "sg:orig_category":"Non-Classified Establishments",
    "sg:phone":"+33 5 53 36 52 66",
    "sg:postcode":"47150",
    "sg:province":"Aquitaine",
    "wof:name":"Boulangeot Bernard",
    "wof:placetype":"venue"
},
  "geometry": {"coordinates":[0.853905,44.519661],"type":"Point"}
}