{
  "type": "Feature",
  "properties": {
    "addr:full":"10 Chem De La Ferte Alais 91790 Boissy Sous St Yon Ile de France 91790",
    "addr:housenumber":"10",
    "addr:postcode":"91790;91790",
    "addr:street":"Chem De La Ferte Alais;Sous St",
    "iso:country":"FR",
    "sg:address":"10 Chem De La Ferte Alais 91790 Boissy Sous St Yon",
    "sg:classifiers":[
        {
            "category":"Building & Trades",
            "subcategory":"Construction",
            "type":"Services"
        }
    ],
    "sg:phone":"+33 1 60 82 08 61",
    "sg:postcode":"91790",
    "sg:province":"Ile de France",
    "sg:tags":[
        "work",
        "public"
    ],
    "wof:name":"Etel",
    "wof:placetype":"venue"
},
  "geometry": {"coordinates":[2.21834,48.55201],"type":"Point"}
}