{
  "type": "Feature",
  "properties": {
    "addr:full":"18, Av Gustave Eiffel - ZI Nord, 37100 Tours Tours Centre 37100",
    "addr:postcode":"37100;37100",
    "addr:street":"18 Av Gustave Eiffel Zi Nord",
    "iso:country":"FR",
    "sg:address":"18, Av Gustave Eiffel - ZI Nord, 37100 Tours",
    "sg:city":"Tours",
    "sg:orig_category":"Non-Classified Establishments",
    "sg:phone":"+33 2 47 88 50 50",
    "sg:postcode":"37100",
    "sg:province":"Centre",
    "wof:name":"Bouyer Entreprise S.a.",
    "wof:placetype":"venue"
},
  "geometry": {"coordinates":[0.69944,47.418121],"type":"Point"}
}