{
  "type": "Feature",
  "properties": {
    "iso:country":"FR",
    "sg:address":"414, Rue Faidherbe, 59119 Waziers",
    "sg:orig_category":"Non-Classified Establishments",
    "sg:phone":"+33 3 27 71 50 10",
    "sg:province":"Nord Pas-de-Calais",
    "wof:name":"J.c.b. Impression",
    "wof:placetype":"venue"
},
  "geometry": {"coordinates":[3.11274,50.38459],"type":"Point"}
}