{
  "type": "Feature",
  "properties": {
    "addr:full":"Rte De Sav\u00e8res 31370 Rieumes Midi Pyr\u00e9n\u00e9es 31370",
    "addr:postcode":"31370;31370",
    "addr:street":"Rte De Save\u0300Res",
    "iso:country":"FR",
    "sg:address":"Rte De Sav\u00e8res 31370 Rieumes",
    "sg:classifiers":[
        {
            "category":"Professional",
            "subcategory":"Engineering",
            "type":"Services"
        }
    ],
    "sg:phone":"+33 5 61 91 82 31",
    "sg:postcode":"31370",
    "sg:province":"Midi Pyr\u00e9n\u00e9es",
    "sg:tags":[
        "machine",
        "-",
        "mechanical"
    ],
    "wof:name":"Produits Sous Pression Sarl",
    "wof:placetype":"venue"
},
  "geometry": {"coordinates":[1.107511,43.391129],"type":"Point"}
}