{
  "type": "Feature",
  "properties": {
    "addr:full":"62, Rue de la R\u00e9publique, 29410 Pleyber Christ Le Clo\u00eetre-Saint-Th\u00e9gonnec Bretagne 29410",
    "addr:housenumber":"62",
    "addr:postcode":"29410;29410",
    "addr:street":"Rue De La Re\u0301Publique;Le Cloi\u0302Tre-Saint-The\u0301Gonnec Bretagne",
    "iso:country":"FR",
    "sg:address":"62, Rue de la R\u00e9publique, 29410 Pleyber Christ",
    "sg:city":"Le Clo\u00eetre-Saint-Th\u00e9gonnec",
    "sg:orig_category":"Non-Classified Establishments",
    "sg:phone":"+33 2 98 78 43 00",
    "sg:postcode":"29410",
    "sg:province":"Bretagne",
    "wof:name":"Guevel S.a.",
    "wof:placetype":"venue"
},
  "geometry": {"coordinates":[-3.875707,48.506035],"type":"Point"}
}