{
  "type": "Feature",
  "properties": {
    "addr:full":"B.P. 75, 59435 Roncq C\u00e9dex^^Av de l'Europe - Cit de Roncq, 59960 Roncq Nord Pas-de-Calais",
    "addr:postcode":"59435;59960",
    "addr:street":"B.P. 75;L'Europe",
    "iso:country":"FR",
    "sg:address":"B.P. 75, 59435 Roncq C\u00e9dex^^Av de l'Europe - Cit de Roncq, 59960 Roncq",
    "sg:orig_category":"Non-Classified Establishments",
    "sg:phone":"+33 3 20 11 51 80",
    "sg:province":"Nord Pas-de-Calais",
    "wof:name":"Schenker S.a.",
    "wof:placetype":"venue"
},
  "geometry": {"coordinates":[3.16141,50.75581],"type":"Point"}
}