{
  "type": "Feature",
  "properties": {
    "addr:full":"B.P. 9, 01540 Vonnas C\u00e9dex^^302, Rue Antoine Manigand, 01540 Vonnas Rhone-Alpes 01540",
    "addr:housenumber":"9",
    "addr:postcode":"01540;01540;01540",
    "addr:street":"B.P.;Rue Antoine Manigand",
    "iso:country":"FR",
    "sg:address":"B.P. 9, 01540 Vonnas C\u00e9dex^^302, Rue Antoine Manigand, 01540 Vonnas",
    "sg:orig_category":"Non-Classified Establishments",
    "sg:phone":"+33 4 74 50 17 44",
    "sg:postcode":"01540",
    "sg:province":"Rhone-Alpes",
    "wof:name":"Hatty Vonnas S.a.",
    "wof:placetype":"venue"
},
  "geometry": {"coordinates":[4.97927,46.218891],"type":"Point"}
}