{
  "type": "Feature",
  "properties": {
    "addr:full":"Les L\u00e9zines 01260 Songieu Rhone-Alpes 01260",
    "addr:postcode":"01260;01260",
    "addr:street":"Rhone-Alpes",
    "iso:country":"FR",
    "sg:address":"Les L\u00e9zines 01260 Songieu",
    "sg:orig_category":"Non-Classified Establishments",
    "sg:phone":"+33 4 79 87 73 44",
    "sg:postcode":"01260",
    "sg:province":"Rhone-Alpes",
    "wof:name":"Martinod Fr\u00e8res S.a.r.l.",
    "wof:placetype":"venue"
},
  "geometry": {"coordinates":[5.686542,45.952518],"type":"Point"}
}