{
  "type": "Feature",
  "properties": {
    "iso:country":"FR",
    "sg:address":"11, Quai Cl\u00e9menceau, 69300 Caluire et Cuire",
    "sg:orig_category":"Unclassifiable Establishments",
    "sg:phone":"+33 4 78 29 35 92",
    "sg:province":"Rhone-Alpes",
    "wof:name":"Soubeyrand S.a.",
    "wof:placetype":"venue"
},
  "geometry": {"coordinates":[4.822031,45.790695],"type":"Point"}
}