{
  "type": "Feature",
  "properties": {
    "iso:country":"FR",
    "sg:address":"ZA les Grillonni\u00e8res",
    "sg:city":"Saint Martin le Beau",
    "sg:orig_category":"Unclassifiable Establishments",
    "sg:phone":"+33 2 47 50 68 68",
    "sg:postcode":"37270",
    "sg:province":"Centre",
    "wof:name":"Jamois F S.a.r.l.",
    "wof:placetype":"venue"
},
  "geometry": {"coordinates":[0.908385,47.355659],"type":"Point"}
}