{
  "type": "Feature",
  "properties": {
    "addr:full":"Rue Rivoalon Sainte Anne-Du-Portzic 29200 Brest Brest Bretagne 29200",
    "addr:postcode":"29200;29200",
    "addr:street":"Rue Rivoalon Sainte Anne-Du-Portzic",
    "iso:country":"FR",
    "sg:address":"Rue Rivoalon Sainte Anne-Du-Portzic 29200 Brest",
    "sg:city":"Brest",
    "sg:classifiers":[
        {
            "category":"Utilities",
            "subcategory":"Telephone",
            "type":"Services"
        }
    ],
    "sg:phone":"+33 2 98 05 67 00",
    "sg:postcode":"29200",
    "sg:province":"Bretagne",
    "sg:tags":[
        "telecommunication"
    ],
    "wof:name":"Ixsea Oceano",
    "wof:placetype":"venue"
},
  "geometry": {"coordinates":[-4.552903,48.362408],"type":"Point"}
}