{
  "type": "Feature",
  "properties": {
    "iso:country":"FR",
    "sg:address":"115 rue Montemartre, 75002 Paris, Dept 75",
    "sg:classifiers":[
        {
            "category":"Banks & Credit Unions",
            "subcategory":"Bank",
            "type":"Services"
        }
    ],
    "sg:phone":"+33 1 41 79 51 00",
    "sg:postcode":"75002",
    "sg:province":"Ile de France",
    "wof:name":"Bail Banque Populaire",
    "wof:placetype":"venue"
},
  "geometry": {"coordinates":[2.343228,48.868633],"type":"Point"}
}