{
  "type": "Feature",
  "properties": {
    "addr:full":"46 Rue De La Cure 85630 Barbatre Pays de Loire 85630",
    "addr:housenumber":"46",
    "addr:postcode":"85630;85630",
    "addr:street":"Rue De La Cure;Barbatre",
    "iso:country":"FR",
    "sg:address":"46 Rue De La Cure 85630 Barbatre",
    "sg:orig_category":"Miscellaneous Products",
    "sg:phone":"+33 2 51 39 64 51",
    "sg:postcode":"85630",
    "sg:province":"Pays de Loire",
    "wof:name":"Metier Jeanne",
    "wof:placetype":"venue"
},
  "geometry": {"coordinates":[-2.179394,46.943771],"type":"Point"}
}