{
  "type": "Feature",
  "properties": {
    "addr:full":"Ferme de Milly Foissy sur Vanne Bourgogne 89190",
    "addr:postcode":"89190",
    "addr:street":"Foissy;Bourgogne",
    "iso:country":"FR",
    "sg:address":"Ferme de Milly",
    "sg:city":"Foissy sur Vanne",
    "sg:orig_category":"Non-Classified Establishments",
    "sg:phone":"+33 3 86 86 88 00",
    "sg:postcode":"89190",
    "sg:province":"Bourgogne",
    "wof:name":"C.a.s.a.y. S.c.a. - Coop\u00e9rative Agricole Des Serristes De L'aube Et De L'yonne",
    "wof:placetype":"venue"
},
  "geometry": {"coordinates":[3.55753,48.233505],"type":"Point"}
}