{
  "type": "Feature",
  "properties": {
    "addr:full":"92357 Le Plessis Robinson C\u00e9dex^^Centre d'Affaires la Boursidi\u00e8re Le Plessis Robinson Ile de France 92350",
    "addr:postcode":"92357;92350",
    "addr:street":"D'Affaires;Boursidie\u0300Re",
    "iso:country":"FR",
    "sg:address":"92357 Le Plessis Robinson C\u00e9dex^^Centre d'Affaires la Boursidi\u00e8re",
    "sg:city":"Le Plessis Robinson",
    "sg:orig_category":"Non-Classified Establishments",
    "sg:phone":"+33 1 41 07 73 00",
    "sg:postcode":"92350",
    "sg:province":"Ile de France",
    "wof:name":"Sochibo S.a.",
    "wof:placetype":"venue"
},
  "geometry": {"coordinates":[2.240835,48.773865],"type":"Point"}
}