{
  "type": "Feature",
  "properties": {
    "addr:full":"99, Rue des R\u00e9sistants, 59280 Armenti\u00e8res Nord Pas-de-Calais",
    "addr:housenumber":"99",
    "addr:postcode":"59280",
    "addr:street":"Rue Des Re\u0301Sistants",
    "iso:country":"FR",
    "sg:address":"99, Rue des R\u00e9sistants, 59280 Armenti\u00e8res",
    "sg:orig_category":"Unclassifiable Establishments",
    "sg:phone":"+33 3 20 77 07 04",
    "sg:province":"Nord Pas-de-Calais",
    "wof:name":"S.a.e.m. S.a. - Soci\u00e9t\u00e9 Des Anciens Etablissements Meauxsoone",
    "wof:placetype":"venue"
},
  "geometry": {"coordinates":[2.870342,50.692211],"type":"Point"}
}