{
  "type": "Feature",
  "properties": {
    "addr:full":"Zone Industrielle 59147 Gondecourt Nord Pas-de-Calais",
    "addr:postcode":"59147",
    "addr:street":"Zone Industrielle",
    "iso:country":"FR",
    "sg:address":"Zone Industrielle 59147 Gondecourt",
    "sg:classifiers":[
        {
            "category":"Manufacturing",
            "subcategory":"Rubber & Plastics",
            "type":"Manufacturing & Wholesale Goods"
        }
    ],
    "sg:phone":"+33 3 20 32 72 77",
    "sg:province":"Nord Pas-de-Calais",
    "wof:name":"Joint Lyonnais Techniques Industrielles",
    "wof:placetype":"venue"
},
  "geometry": {"coordinates":[2.986804,50.548714],"type":"Point"}
}