{
  "type": "Feature",
  "properties": {
    "addr:full":"4, Rue de la Croix Bourgot - ZI, 28800 Bonneval Bonneval Centre 28800",
    "addr:housenumber":"4",
    "addr:postcode":"28800;28800",
    "addr:street":"Rue De La Croix Bourgot Zi;Bonneval",
    "iso:country":"FR",
    "sg:address":"4, Rue de la Croix Bourgot - ZI, 28800 Bonneval",
    "sg:city":"Bonneval",
    "sg:orig_category":"Unclassifiable Establishments",
    "sg:phone":"+33 2 37 44 72 00",
    "sg:postcode":"28800",
    "sg:province":"Centre",
    "wof:name":"T.r.a.n.s.m.a. S.a. - Transformation Des Mati\u00e8res Adh\u00e9sives",
    "wof:placetype":"venue"
},
  "geometry": {"coordinates":[1.49009,48.133808],"type":"Point"}
}