{
  "type": "Feature",
  "properties": {
    "addr:full":"25, Av. de Lyon, 01000 Bourg en Bresse Rhone-Alpes 01000",
    "addr:postcode":"01000;01000",
    "addr:street":"25 Av. De Lyon;Rhone-Alpes",
    "iso:country":"FR",
    "sg:address":"25, Av. de Lyon, 01000 Bourg en Bresse",
    "sg:orig_category":"Unclassifiable Establishments",
    "sg:phone":"+33 4 74 32 82 82",
    "sg:postcode":"01000",
    "sg:province":"Rhone-Alpes",
    "wof:name":"Te Pointes S.n.c.",
    "wof:placetype":"venue"
},
  "geometry": {"coordinates":[5.213562,46.193081],"type":"Point"}
}