{
  "type": "Feature",
  "properties": {
    "addr:full":"900 rue des Pr\u00e9s Moulin 74190 Passy Rhone-Alpes",
    "addr:housenumber":"900",
    "addr:postcode":"74190",
    "addr:street":"Rue Des Pre\u0301S",
    "iso:country":"FR",
    "sg:address":"900 rue des Pr\u00e9s Moulin 74190 Passy",
    "sg:classifiers":[
        {
            "category":"Retail",
            "subcategory":"Laundry & Dry Cleaning",
            "type":"Services"
        }
    ],
    "sg:phone":"+33 4 50 78 23 33",
    "sg:province":"Rhone-Alpes",
    "sg:tags":[
        "sprays",
        "refractory",
        "castables"
    ],
    "wof:name":"Ste Equipement Et Damage Des Pistes S.a.",
    "wof:placetype":"venue"
},
  "geometry": {"coordinates":[6.714293,45.91954],"type":"Point"}
}