{
  "type": "Feature",
  "properties": {
    "iso:country":"FR",
    "sg:address":"Quartier Bassaquet - Module 2 - B\u00e2t. B - Parc Burotel",
    "sg:city":"Six Fours les Plages",
    "sg:orig_category":"Unclassifiable Establishments",
    "sg:phone":"+33 4 94 63 03 02",
    "sg:postcode":"83140",
    "sg:province":"Provence-Alpes-C\u00f4te d'Azur",
    "wof:name":"Canon France S.a.",
    "wof:placetype":"venue"
},
  "geometry": {"coordinates":[5.842716,43.093311],"type":"Point"}
}