{
  "type": "Feature",
  "properties": {
    "addr:full":"70 Route De Nimes 30540 Milhaud Languedoc-Roussillon 30540",
    "addr:housenumber":"70",
    "addr:postcode":"30540;30540",
    "addr:street":"Route De Nimes",
    "iso:country":"FR",
    "sg:address":"70 Route De Nimes 30540 Milhaud",
    "sg:classifiers":[
        {
            "category":"Wholesale",
            "subcategory":"Medical Equipment & Supplies",
            "type":"Manufacturing & Wholesale Goods"
        }
    ],
    "sg:phone":"+33 4 66 74 05 14",
    "sg:postcode":"30540",
    "sg:province":"Languedoc-Roussillon",
    "sg:tags":[
        "instrument",
        "health",
        "-",
        "precision"
    ],
    "wof:name":"Prodentec",
    "wof:placetype":"venue"
},
  "geometry": {"coordinates":[4.31217,43.795212],"type":"Point"}
}