{
  "type": "Feature",
  "properties": {
    "iso:country":"FR",
    "sg:address":"Rue Jean Monnet - ZI du Grand Logis",
    "sg:city":"Lompret",
    "sg:orig_category":"Unclassifiable Establishments",
    "sg:phone":"+33 3 20 00 93 93",
    "sg:postcode":"59840",
    "sg:province":"Nord Pas-de-Calais",
    "wof:name":"Importation Distribution Service S.a.",
    "wof:placetype":"venue"
},
  "geometry": {"coordinates":[2.973282,50.668343],"type":"Point"}
}