{
  "type": "Feature",
  "properties": {
    "addr:full":"108 chemin du Cr\u00eat de Montcher 69210 LENTILLY Rhone-Alpes 69210",
    "addr:housenumber":"108",
    "addr:postcode":"69210;69210",
    "addr:street":"Chemin Du Cre\u0302T De Montcher;Rhone-Alpes",
    "iso:country":"FR",
    "sg:address":"108 chemin du Cr\u00eat de Montcher 69210 LENTILLY",
    "sg:classifiers":[
        {
            "category":"Professional",
            "subcategory":"Computer Services",
            "type":"Services"
        }
    ],
    "sg:phone":"+33 4 74 72 19 80",
    "sg:postcode":"69210",
    "sg:province":"Rhone-Alpes",
    "sg:tags":[
        "informatics",
        "consulting"
    ],
    "wof:name":"Adermiis Sa",
    "wof:placetype":"venue"
},
  "geometry": {"coordinates":[4.66749,45.806583],"type":"Point"}
}