{
  "type": "Feature",
  "properties": {
    "iso:country":"FR",
    "sg:address":"85 Rue Moli\u00e8re 94200 Ivry Sur Seine",
    "sg:classifiers":[
        {
            "category":"Shopping",
            "subcategory":"Crafts & Fabrics",
            "type":"Retail Goods"
        }
    ],
    "sg:phone":"+33 1 46 58 90 69",
    "sg:postcode":"94200",
    "sg:province":"Ile de France",
    "sg:tags":[
        "textile",
        "clothing",
        "clothes"
    ],
    "wof:name":"Corner Sa",
    "wof:placetype":"venue"
},
  "geometry": {"coordinates":[2.391445,48.817165],"type":"Point"}
}