{
  "type": "Feature",
  "properties": {
    "addr:full":"Rte De Boisg\u00e9loup 27140 Gisors Haute Normandie 27140",
    "addr:postcode":"27140;27140",
    "addr:street":"Rte De Boisge\u0301Loup;Haute Normandie",
    "iso:country":"FR",
    "sg:address":"Rte De Boisg\u00e9loup 27140 Gisors",
    "sg:classifiers":[
        {
            "category":"Professional",
            "subcategory":"Engineering",
            "type":"Services"
        }
    ],
    "sg:phone":"+33 2 32 27 15 74",
    "sg:postcode":"27140",
    "sg:province":"Haute Normandie",
    "sg:tags":[
        "machine",
        "-",
        "mechanical"
    ],
    "wof:name":"Czewo Sa",
    "wof:placetype":"venue"
},
  "geometry": {"coordinates":[1.781525,49.268078],"type":"Point"}
}