{
  "type": "Feature",
  "properties": {
    "addr:full":"8 Rue Marcel Dassault Zi Du Sanital 86100 Chatellerault Poitou-Charentes 86100",
    "addr:housenumber":"8",
    "addr:postcode":"86100;86100",
    "addr:street":"Rue Marcel Dassault Zi Du Sanital",
    "iso:country":"FR",
    "sg:address":"8 Rue Marcel Dassault Zi Du Sanital 86100 Chatellerault",
    "sg:classifiers":[
        {
            "category":"Home & Garden",
            "subcategory":"Building Materials",
            "type":"Retail Goods"
        }
    ],
    "sg:phone":"+33 5 49 20 02 51",
    "sg:postcode":"86100",
    "sg:province":"Poitou-Charentes",
    "sg:tags":[
        "equipment",
        "energy",
        "-",
        "environment",
        "raw",
        "machinery"
    ],
    "wof:name":"Ceo",
    "wof:placetype":"venue"
},
  "geometry": {"coordinates":[0.614296,46.778336],"type":"Point"}
}