{
  "type": "Feature",
  "properties": {
    "addr:full":"B.P. 14, 76450 Cany Barville^^Zone Industrielle de la Gare, 76450 Cany Barville Haute Normandie",
    "addr:postcode":"76450;76450",
    "addr:street":"B.P. 14;La Gare;Haute Normandie",
    "iso:country":"FR",
    "sg:address":"B.P. 14, 76450 Cany Barville^^Zone Industrielle de la Gare, 76450 Cany Barville",
    "sg:orig_category":"Non-Classified Establishments",
    "sg:phone":"+33 2 35 57 81 81",
    "sg:province":"Haute Normandie",
    "wof:name":"Polytechs S.a.",
    "wof:placetype":"venue"
},
  "geometry": {"coordinates":[0.619919,49.694202],"type":"Point"}
}