{
  "type": "Feature",
  "properties": {
    "addr:full":"40 ave des Ternes; Paris; 75017 Ile de France 75017",
    "addr:postcode":"75017 ile;france 75017",
    "addr:street":"40 Ave Des Ternes",
    "iso:country":"FR",
    "sg:address":"40 ave des Ternes; Paris; 75017",
    "sg:classifiers":[
        {
            "category":"Banks & Credit Unions",
            "subcategory":"Bank",
            "type":"Services"
        }
    ],
    "sg:phone":"+33 1 40 68 37 70",
    "sg:postcode":"75017",
    "sg:province":"Ile de France",
    "wof:name":"Soci\u00e9t\u00e9 G\u00e9n\u00e9rale",
    "wof:placetype":"venue"
},
  "geometry": {"coordinates":[2.29306,48.879036],"type":"Point"}
}