{
  "type": "Feature",
  "properties": {
    "iso:country":"FR",
    "sg:address":"Rte de Pau",
    "sg:city":"Maz\u00e8res",
    "sg:orig_category":"Unclassifiable Establishments",
    "sg:phone":"+33 5 57 98 01 21",
    "sg:postcode":"33210",
    "sg:province":"Aquitaine",
    "wof:name":"Saphore Equipements S.a.",
    "wof:placetype":"venue"
},
  "geometry": {"coordinates":[-0.260022,44.494415],"type":"Point"}
}