{
  "type": "Feature",
  "properties": {
    "addr:full":"13, Rue Alexander Fl\u00e9ming - ZI des Renouill\u00e8res, 93360 Neuilly Plaisance Ile de France",
    "addr:housenumber":"13",
    "addr:postcode":"93360",
    "addr:street":"Rue Alexander Fle\u0301Ming Zi Des Renouille\u0300Res;Ile De France",
    "iso:country":"FR",
    "sg:address":"13, Rue Alexander Fl\u00e9ming - ZI des Renouill\u00e8res, 93360 Neuilly Plaisance",
    "sg:orig_category":"Non-Classified Establishments",
    "sg:phone":"+33 1 41 54 20 00",
    "sg:province":"Ile de France",
    "wof:name":"W.i.v. France S.a.r.l.",
    "wof:placetype":"venue"
},
  "geometry": {"coordinates":[2.502418,48.860184],"type":"Point"}
}