{
  "type": "Feature",
  "properties": {
    "addr:full":"665 Rte De La Sini\u00e8re 38490 Charancieu Rhone-Alpes 38490",
    "addr:housenumber":"665",
    "addr:postcode":"38490;38490",
    "addr:street":"Rte De La Sinie\u0300Re;Rhone-Alpes",
    "iso:country":"FR",
    "sg:address":"665 Rte De La Sini\u00e8re 38490 Charancieu",
    "sg:classifiers":[
        {
            "category":"Transit Center",
            "subcategory":"Freight",
            "type":"Transportation"
        }
    ],
    "sg:phone":"+33 4 76 32 20 25",
    "sg:postcode":"38490",
    "sg:province":"Rhone-Alpes",
    "sg:tags":[
        "metallurgy",
        "pipe",
        "metalworking",
        "sheet"
    ],
    "wof:name":"Sofen (sa)",
    "wof:placetype":"venue"
},
  "geometry": {"coordinates":[5.58323,45.527824],"type":"Point"}
}