{
  "type": "Feature",
  "properties": {
    "iso:country":"FR",
    "sg:address":"122, Rte de Saint Omer, 62610 Autingues",
    "sg:orig_category":"Unclassifiable Establishments",
    "sg:phone":"+33 3 21 46 60 00",
    "sg:province":"Nord Pas-de-Calais",
    "wof:name":"Ledoux Claude Imprimerie S.a.",
    "wof:placetype":"venue"
},
  "geometry": {"coordinates":[1.97956,50.856152],"type":"Point"}
}