{
  "type": "Feature",
  "properties": {
    "iso:country":"FR",
    "sg:address":"Impasse du Petit Gour",
    "sg:city":"Martigues",
    "sg:orig_category":"Unclassifiable Establishments",
    "sg:phone":"+33 4 42 80 35 52",
    "sg:postcode":"13500",
    "sg:province":"Provence-Alpes-C\u00f4te d'Azur",
    "wof:name":"A\u00e9roservice International S.a.r.l.",
    "wof:placetype":"venue"
},
  "geometry": {"coordinates":[5.054239,43.424786],"type":"Point"}
}