{
  "type": "Feature",
  "properties": {
    "addr:full":"163 avenue Pierre Mend\u00e8s-France 02000 Laon Picardie 02000",
    "addr:housenumber":"163",
    "addr:postcode":"02000;02000",
    "addr:street":"Avenue Pierre Mende\u0300S-France",
    "iso:country":"FR",
    "sg:address":"163 avenue Pierre Mend\u00e8s-France 02000 Laon",
    "sg:classifiers":[
        {
            "category":"Bars & Pubs",
            "subcategory":"Sports Bar",
            "type":"Food & Drink"
        }
    ],
    "sg:phone":"+33 3 23 27 14 00",
    "sg:postcode":"02000",
    "sg:province":"Picardie",
    "sg:tags":[
        "packaging",
        "manufacturing",
        "customized"
    ],
    "wof:name":"Norepi Sa",
    "wof:placetype":"venue"
},
  "geometry": {"coordinates":[3.64374,49.581364],"type":"Point"}
}