{
  "type": "Feature",
  "properties": {
    "iso:country":"FR",
    "sg:address":"6 rue Alfred J\u00e9del\u00e9 68130 Altkirch",
    "sg:city":"Altkirch",
    "sg:classifiers":[
        {
            "category":"Professional",
            "subcategory":"Engineering",
            "type":"Services"
        }
    ],
    "sg:phone":"+33 3 89 40 01 30",
    "sg:postcode":"68130",
    "sg:province":"Alsace",
    "sg:tags":[
        "surface"
    ],
    "wof:name":"J\u00e9del\u00e9 S.a.",
    "wof:placetype":"venue"
},
  "geometry": {"coordinates":[7.233303,47.626221],"type":"Point"}
}