{
  "type": "Feature",
  "properties": {
    "addr:full":"Les Plant\u00e9es 42680 Saint Marcellin en Forez Rhone-Alpes",
    "addr:postcode":"42680",
    "addr:street":"Marcellin En Forez Rhone-Alpes",
    "iso:country":"FR",
    "sg:address":"Les Plant\u00e9es 42680 Saint Marcellin en Forez",
    "sg:orig_category":"Non-Classified Establishments",
    "sg:phone":"+33 4 77 52 72 52",
    "sg:province":"Rhone-Alpes",
    "wof:name":"Imerys Structure S.a.s.",
    "wof:placetype":"venue"
},
  "geometry": {"coordinates":[4.183151,45.497353],"type":"Point"}
}