{
  "type": "Feature",
  "properties": {
    "addr:full":"2 Champ Fr\u00e9d\u00e9ric 70400 H\u00e9ricourt Franche Comt\u00e9 70400",
    "addr:housenumber":"2",
    "addr:postcode":"70400;70400",
    "addr:street":"Champ Fre\u0301De\u0301Ric;Franche Comte\u0301",
    "iso:country":"FR",
    "sg:address":"2",
    "sg:city":"Champ Fr\u00e9d\u00e9ric 70400 H\u00e9ricourt",
    "sg:classifiers":[
        {
            "category":"Manufacturing",
            "subcategory":"Metals",
            "type":"Manufacturing & Wholesale Goods"
        }
    ],
    "sg:phone":"+33 3 84 46 43 06",
    "sg:postcode":"70400",
    "sg:province":"Franche Comt\u00e9",
    "sg:tags":[
        "metallurgy",
        "metalworking",
        "processing"
    ],
    "wof:name":"A.p.i. Franche Comte",
    "wof:placetype":"venue"
},
  "geometry": {"coordinates":[6.754775,47.574718],"type":"Point"}
}