{
  "type": "Feature",
  "properties": {
    "addr:full":"198, Cours du Lub\u00e9ron, 84530 Villelaure Provence-Alpes-C\u00f4te d'Azur",
    "addr:housenumber":"198",
    "addr:postcode":"84530",
    "addr:street":"Cours Du Lube\u0301Ron",
    "iso:country":"FR",
    "sg:address":"198, Cours du Lub\u00e9ron, 84530 Villelaure",
    "sg:orig_category":"Unclassifiable Establishments",
    "sg:phone":"+33 4 90 09 11 78",
    "sg:province":"Provence-Alpes-C\u00f4te d'Azur",
    "wof:name":"Sitrasol S.a.r.l.",
    "wof:placetype":"venue"
},
  "geometry": {"coordinates":[5.43119,43.71344],"type":"Point"}
}