{
  "type": "Feature",
  "properties": {
    "addr:full":"ZI du Planty - La Guyonni\u00e8re Montaigu Pays de Loire 85600",
    "addr:postcode":"85600",
    "addr:street":"Zi Du Planty La Guyonnie\u0300Re Montaigu Pays",
    "iso:country":"FR",
    "sg:address":"ZI du Planty - La Guyonni\u00e8re",
    "sg:city":"Montaigu",
    "sg:orig_category":"Unclassifiable Establishments",
    "sg:phone":"+33 2 51 48 86 86",
    "sg:postcode":"85600",
    "sg:province":"Pays de Loire",
    "wof:name":"Landa S.a.r.l.",
    "wof:placetype":"venue"
},
  "geometry": {"coordinates":[-1.190697,46.949257],"type":"Point"}
}