{
  "type": "Feature",
  "properties": {
    "iso:country":"FR",
    "sg:address":"71bis, Av. Sadi Carno, 26000 Valence",
    "sg:orig_category":"Non-Classified Establishments",
    "sg:phone":"+33 4 75 78 17 60",
    "sg:postcode":"26000",
    "sg:province":"Rhone-Alpes",
    "wof:name":"Bureau V\u00e9ritas S.a.",
    "wof:placetype":"venue"
},
  "geometry": {"coordinates":[4.897326,44.934067],"type":"Point"}
}