{
  "type": "Feature",
  "properties": {
    "iso:country":"FR",
    "sg:address":"26, Rue du Pont Cotelle, 45073 Orl\u00e9ans C\u00e9dex",
    "sg:city":"Orl\u00e9ans",
    "sg:orig_category":"Non-Classified Establishments",
    "sg:phone":"+33 2 38 56 90 10",
    "sg:postcode":"45000",
    "sg:province":"Centre",
    "wof:name":"Solnet S.a.",
    "wof:placetype":"venue"
},
  "geometry": {"coordinates":[1.90398,47.90139],"type":"Point"}
}