{
  "type": "Feature",
  "properties": {
    "iso:country":"FR",
    "sg:address":"1 Route Gironcourt 88170 St Menge",
    "sg:classifiers":[
        {
            "category":"Professional",
            "subcategory":"Engineering",
            "type":"Services"
        }
    ],
    "sg:phone":"+33 3 29 94 96 55",
    "sg:postcode":"88170",
    "sg:province":"Lorraine",
    "sg:tags":[
        "machine",
        "-",
        "environment",
        "equipment",
        "machinery",
        "mechanical"
    ],
    "wof:name":"Pat\u00c9 Sas",
    "wof:placetype":"venue"
},
  "geometry": {"coordinates":[5.949205,48.287987],"type":"Point"}
}