{
  "type": "Feature",
  "properties": {
    "addr:full":"63 blvd Lazare; Toulouse; 31000 Midi Pyr\u00e9n\u00e9es 31000",
    "addr:postcode":"31000;31000",
    "addr:street":"63 Blvd Lazare Toulouse",
    "iso:country":"FR",
    "sg:address":"63 blvd Lazare; Toulouse; 31000",
    "sg:classifiers":[
        {
            "category":"Banks & Credit Unions",
            "subcategory":"Bank",
            "type":"Services"
        }
    ],
    "sg:phone":"+33 5 61 12 23 12",
    "sg:postcode":"31000",
    "sg:province":"Midi Pyr\u00e9n\u00e9es",
    "wof:name":"Caixa D'estalvis, De Catalunya",
    "wof:placetype":"venue"
},
  "geometry": {"coordinates":[1.44869,43.60574],"type":"Point"}
}