{
  "type": "Feature",
  "properties": {
    "iso:country":"FR",
    "sg:address":"61 Rue Auguste Rispal 76600 Le Havre",
    "sg:orig_category":"Clothing accessories Engines and parts Mechanical Engineering - machines Textiles and Clothing",
    "sg:phone":"+33 2 35 24 79 00",
    "sg:postcode":"76600",
    "sg:province":"Haute Normandie",
    "wof:name":"Orefi",
    "wof:placetype":"venue"
},
  "geometry": {"coordinates":[0.142177,49.492992],"type":"Point"}
}