{
  "type": "Feature",
  "properties": {
    "addr:full":"85, Chemin des Bruy\u00e8res, 69153 D\u00e9cines Charpieu C\u00e9dex Rhone-Alpes",
    "addr:housenumber":"85",
    "addr:postcode":"69153",
    "addr:street":"Chemin Des Bruye\u0300Res",
    "iso:country":"FR",
    "sg:address":"85, Chemin des Bruy\u00e8res, 69153 D\u00e9cines Charpieu C\u00e9dex",
    "sg:orig_category":"Non-Classified Establishments",
    "sg:phone":"+33 4 72 05 60 10",
    "sg:province":"Rhone-Alpes",
    "wof:name":"S.e.r.f. S.a. - Soci\u00e9t\u00e9 D'etudes Recherches Et Fabrications",
    "wof:placetype":"venue"
},
  "geometry": {"coordinates":[4.943087,45.755753],"type":"Point"}
}