{
  "type": "Feature",
  "properties": {
    "addr:full":"B.P. 101, 63019 Clermont Ferrand C\u00e9dex 2^^20, Bd Etienne Cl\u00e9mentel, 63100 Clermont Ferrand Clermont-Ferrand Auvergne 63100",
    "addr:housenumber":"b.p. 101;2 ^ ^ 20",
    "addr:postcode":"63019;63100;63100",
    "addr:street":"Ce\u0301Dex;Bd Etienne Cle\u0301Mentel",
    "iso:country":"FR",
    "sg:address":"B.P. 101, 63019 Clermont Ferrand C\u00e9dex 2^^20, Bd Etienne Cl\u00e9mentel, 63100 Clermont Ferrand",
    "sg:city":"Clermont-Ferrand",
    "sg:orig_category":"Non-Classified Establishments",
    "sg:phone":"+33 4 73 25 86 00",
    "sg:postcode":"63100",
    "sg:province":"Auvergne",
    "wof:name":"Peintamelec Ing\u00e9nierie S.a.",
    "wof:placetype":"venue"
},
  "geometry": {"coordinates":[2.09017,43.151814],"type":"Point"}
}