{
  "type": "Feature",
  "properties": {
    "addr:full":"RD 911 Saint Germain de Marencennes Poitou-Charentes 17700",
    "addr:postcode":"17700",
    "addr:street":"Rd 911;Germain;Marencennes",
    "iso:country":"FR",
    "sg:address":"RD 911",
    "sg:city":"Saint Germain de Marencennes",
    "sg:orig_category":"Unclassifiable Establishments",
    "sg:phone":"+33 5 46 27 62 90",
    "sg:postcode":"17700",
    "sg:province":"Poitou-Charentes",
    "wof:name":"S.o.f.e.c. S.a. - Soci\u00e9t\u00e9 De Fabrication D'el\u00e9ments De Cuisine",
    "wof:placetype":"venue"
},
  "geometry": {"coordinates":[-0.782312,46.076965],"type":"Point"}
}