{
  "type": "Feature",
  "properties": {
    "addr:full":"B.P. 29, 72120 Saint Calais^^ZI de la Pocherie, 72120 Saint Calais Pays de Loire",
    "addr:postcode":"72120;72120",
    "addr:street":"B.P. 29",
    "iso:country":"FR",
    "sg:address":"B.P. 29, 72120 Saint Calais^^ZI de la Pocherie, 72120 Saint Calais",
    "sg:orig_category":"Non-Classified Establishments",
    "sg:phone":"+33 2 43 63 16 41",
    "sg:province":"Pays de Loire",
    "wof:name":"Soci\u00e9t\u00e9 Nouvelle Atelier 41 S.a.r.l.",
    "wof:placetype":"venue"
},
  "geometry": {"coordinates":[0.741306,47.887047],"type":"Point"}
}