{
  "type": "Feature",
  "properties": {
    "iso:country":"FR",
    "sg:address":"Zone Artisanale 56150 Baud",
    "sg:city":"Baud",
    "sg:classifiers":[
        {
            "category":"Building & Trades",
            "subcategory":"Electrical",
            "type":"Services"
        }
    ],
    "sg:phone":"+33 2 97 51 08 07",
    "sg:postcode":"56150",
    "sg:province":"Bretagne",
    "sg:tags":[
        "electronic",
        "lighting",
        "equipment"
    ],
    "wof:name":"Luminaires Le Louer",
    "wof:placetype":"venue"
},
  "geometry": {"coordinates":[-3.019457,47.87542],"type":"Point"}
}