{
  "type": "Feature",
  "properties": {
    "iso:country":"FR",
    "sg:address":"7 Rue Nicolas Appert 41700 Contres",
    "sg:city":"Contres",
    "sg:classifiers":[
        {
            "category":"Food & Beverages",
            "subcategory":"Fruits & Vegetables",
            "type":"Retail Goods"
        }
    ],
    "sg:phone":"+33 2 54 79 71 00",
    "sg:postcode":"41700",
    "sg:province":"Centre",
    "sg:tags":[
        "preserve",
        "product",
        "related"
    ],
    "wof:name":"Sica",
    "wof:placetype":"venue"
},
  "geometry": {"coordinates":[1.44554,47.428574],"type":"Point"}
}