{
  "type": "Feature",
  "properties": {
    "addr:full":"7 Rue Nicolas Appert 41700 Contres Contres Centre 41700",
    "addr:housenumber":"7",
    "addr:postcode":"41700;41700",
    "addr:street":"Rue Nicolas Appert",
    "iso:country":"FR",
    "sg:address":"7 Rue Nicolas Appert 41700 Contres",
    "sg:city":"Contres",
    "sg:classifiers":[
        {
            "category":"Food & Beverages",
            "subcategory":"Fruits & Vegetables",
            "type":"Retail Goods"
        }
    ],
    "sg:phone":"+33 2 54 79 71 00",
    "sg:postcode":"41700",
    "sg:province":"Centre",
    "sg:tags":[
        "preserve",
        "product",
        "related"
    ],
    "wof:name":"Sica",
    "wof:placetype":"venue"
},
  "geometry": {"coordinates":[1.44554,47.428574],"type":"Point"}
}