{
  "type": "Feature",
  "properties": {
    "addr:full":"Rte de Villefranche Caussade Midi Pyr\u00e9n\u00e9es 82300",
    "addr:postcode":"82300",
    "addr:street":"Rte De Villefranche",
    "iso:country":"FR",
    "sg:address":"Rte de Villefranche",
    "sg:city":"Caussade",
    "sg:orig_category":"Unclassifiable Establishments",
    "sg:phone":"+33 5 63 93 10 78",
    "sg:postcode":"82300",
    "sg:province":"Midi Pyr\u00e9n\u00e9es",
    "wof:name":"Dejean-servi\u00e8res S.a.",
    "wof:placetype":"venue"
},
  "geometry": {"coordinates":[1.605065,44.145657],"type":"Point"}
}