{
  "type": "Feature",
  "properties": {
    "addr:full":"1-3 rue du Pied Sec 93290 Tremblay en France Ile de France",
    "addr:housenumber":"1-3",
    "addr:postcode":"93290",
    "addr:street":"Rue Du Pied Sec",
    "iso:country":"FR",
    "sg:address":"1-3 rue du Pied Sec 93290 Tremblay en France",
    "sg:classifiers":[
        {
            "category":"Professional",
            "type":"Services"
        }
    ],
    "sg:phone":"+33 1 48 62 71 43",
    "sg:province":"Ile de France",
    "sg:tags":[
        "transport"
    ],
    "wof:name":"Debeaux Transit S.a.r.l.",
    "wof:placetype":"venue"
},
  "geometry": {"coordinates":[2.530791,48.999985],"type":"Point"}
}