{
  "type": "Feature",
  "properties": {
    "iso:country":"FR",
    "sg:address":"Rue du Ch\u00eane - ZI la Louvi\u00e8re",
    "sg:city":"Pirey",
    "sg:orig_category":"Unclassifiable Establishments",
    "sg:phone":"+33 3 81 53 32 55",
    "sg:postcode":"25480",
    "sg:province":"Franche Comt\u00e9",
    "wof:name":"Trumel-or\u00e9fi S.a.",
    "wof:placetype":"venue"
},
  "geometry": {"coordinates":[5.982078,47.27187],"type":"Point"}
}