{
  "type": "Feature",
  "properties": {
    "iso:country":"FR",
    "sg:address":"33720 Landiras",
    "sg:city":"Landiras",
    "sg:orig_category":"Unclassifiable Establishments",
    "sg:phone":"+33 5 56 62 50 66",
    "sg:postcode":"33720",
    "sg:province":"Aquitaine",
    "wof:name":"Domaine Du Moulin \u00e0 Vent",
    "wof:placetype":"venue"
},
  "geometry": {"coordinates":[-0.414069,44.56757],"type":"Point"}
}