{
  "type": "Feature",
  "properties": {
    "iso:country":"FR",
    "sg:address":"B.P. 27",
    "sg:city":"Sotta C\u00e9dex^^Paltanaggia 20146 Sotta",
    "sg:orig_category":"Non-Classified Establishments",
    "sg:phone":"+33 4 95 71 24 64",
    "sg:postcode":"20146",
    "sg:province":"Corse",
    "wof:name":"Euro Corse Voyages S.a.r.l.",
    "wof:placetype":"venue"
},
  "geometry": {"coordinates":[9.191675,41.545044],"type":"Point"}
}