{
  "type": "Feature",
  "properties": {
    "addr:full":"28 Rue Victor Hugo 59142 Villers Outr\u00e9aux Nord Pas-de-Calais 59142",
    "addr:housenumber":"28",
    "addr:postcode":"59142;59142",
    "addr:street":"Rue Victor Hugo;Pas-De-Calais",
    "iso:country":"FR",
    "sg:address":"28 Rue Victor Hugo 59142 Villers Outr\u00e9aux",
    "sg:classifiers":[
        {
            "category":"Shopping",
            "subcategory":"Crafts & Fabrics",
            "type":"Retail Goods"
        }
    ],
    "sg:phone":"+33 3 27 82 01 73",
    "sg:postcode":"59142",
    "sg:province":"Nord Pas-de-Calais",
    "sg:tags":[
        "textile",
        "clothing"
    ],
    "wof:name":"Langlet (sarl Broderies Jean Marc)",
    "wof:placetype":"venue"
},
  "geometry": {"coordinates":[3.301892,50.035686],"type":"Point"}
}