{
  "type": "Feature",
  "properties": {
    "addr:full":"route d'Angers 86120 Les Trois Moutiers Poitou-Charentes",
    "addr:postcode":"86120",
    "addr:street":"Route D'Angers;Moutiers",
    "iso:country":"FR",
    "sg:address":"route d'Angers 86120 Les Trois Moutiers",
    "sg:classifiers":[
        {
            "category":"Utilities",
            "subcategory":"Natural Gas",
            "type":"Services"
        }
    ],
    "sg:phone":"+33 5 49 22 58 50",
    "sg:province":"Poitou-Charentes",
    "sg:tags":[
        "processing",
        "metal",
        "cnc"
    ],
    "wof:name":"M.3.m Sa",
    "wof:placetype":"venue"
},
  "geometry": {"coordinates":[0.01808,47.062229],"type":"Point"}
}