{
  "type": "Feature",
  "properties": {
    "addr:full":"49, Rue du G\u00e9n\u00e9ral Leclerc, 67210 Obernai Obernai Alsace 67210",
    "addr:housenumber":"49",
    "addr:postcode":"67210;67210",
    "addr:street":"Rue Du Ge\u0301Ne\u0301Ral Leclerc",
    "iso:country":"FR",
    "sg:address":"49, Rue du G\u00e9n\u00e9ral Leclerc, 67210 Obernai",
    "sg:city":"Obernai",
    "sg:orig_category":"Unclassifiable Establishments",
    "sg:phone":"+33 3 88 49 97 97",
    "sg:postcode":"67210",
    "sg:province":"Alsace",
    "wof:name":"Sobovia S.a.",
    "wof:placetype":"venue"
},
  "geometry": {"coordinates":[7.492913,48.469555],"type":"Point"}
}