{
  "type": "Feature",
  "properties": {
    "addr:full":"7 cours Vitton 69006 Lyon Rhone-Alpes",
    "addr:housenumber":"7",
    "addr:postcode":"69006",
    "addr:street":"Cours Vitton",
    "iso:country":"FR",
    "sg:address":"7 cours Vitton 69006 Lyon",
    "sg:classifiers":[
        {
            "category":"Shopping",
            "subcategory":"Crafts & Fabrics",
            "type":"Retail Goods"
        }
    ],
    "sg:phone":"+33 4 78 89 05 71",
    "sg:province":"Rhone-Alpes",
    "sg:tags":[
        "silk"
    ],
    "wof:name":"Pellet Et Compagnie Sa",
    "wof:placetype":"venue"
},
  "geometry": {"coordinates":[4.850999,45.769485],"type":"Point"}
}