{
  "type": "Feature",
  "properties": {
    "addr:full":"66 Rue Des Courtiaux 63000 Clermont Ferrand Clermont-Ferrand Auvergne 63000",
    "addr:housenumber":"66",
    "addr:postcode":"63000;63000",
    "addr:street":"Rue Des Courtiaux",
    "iso:country":"FR",
    "sg:address":"66 Rue Des Courtiaux 63000 Clermont Ferrand",
    "sg:city":"Clermont-Ferrand",
    "sg:classifiers":[
        {
            "category":"Manufacturing",
            "subcategory":"Jewelry",
            "type":"Manufacturing & Wholesale Goods"
        }
    ],
    "sg:phone":"+33 4 73 27 50 98",
    "sg:postcode":"63000",
    "sg:province":"Auvergne",
    "sg:tags":[
        "product",
        "miscellaneous",
        "jewellery"
    ],
    "wof:name":"Sarl Les Perles De Venus",
    "wof:placetype":"venue"
},
  "geometry": {"coordinates":[3.1302,45.768757],"type":"Point"}
}