{
  "type": "Feature",
  "properties": {
    "iso:country":"FR",
    "sg:address":"Rue De Tohagues 50440 Beaumont Hague",
    "sg:city":"Acqueville",
    "sg:classifiers":[
        {
            "category":"Farming",
            "subcategory":"Farm & Veterinary Services",
            "type":"Manufacturing & Wholesale Goods"
        }
    ],
    "sg:phone":"+33 2 33 52 70 33",
    "sg:postcode":"50440",
    "sg:province":"Basse Normandie",
    "sg:tags":[
        "food",
        "product",
        "breeding",
        "animal",
        "related"
    ],
    "wof:name":"Societe Cooperative Agricole Et Agro Alimentaire Des Provinc (agralco)",
    "wof:placetype":"venue"
},
  "geometry": {"coordinates":[-1.831998,49.661343],"type":"Point"}
}