{
  "type": "Feature",
  "properties": {
    "iso:country":"FR",
    "sg:address":"106, Av. Vaucanson, 93370 Montfermeil",
    "sg:orig_category":"Unclassifiable Establishments",
    "sg:phone":"+33 1 45 09 31 00",
    "sg:province":"Ile de France",
    "wof:name":"Abry Nicolas S.a.r.l.",
    "wof:placetype":"venue"
},
  "geometry": {"coordinates":[2.586293,48.900684],"type":"Point"}
}