{
  "type": "Feature",
  "properties": {
    "addr:full":"174 avenue de France 75013 Paris Ile de France",
    "addr:housenumber":"174",
    "addr:postcode":"75013",
    "addr:street":"Avenue De France",
    "iso:country":"FR",
    "sg:address":"174 avenue de France 75013 Paris",
    "sg:classifiers":[
        {
            "category":"Manufacturing",
            "subcategory":"Chemicals & Compounds",
            "type":"Manufacturing & Wholesale Goods"
        }
    ],
    "sg:phone":"+33 1 53 77 41 33",
    "sg:province":"Ile de France",
    "sg:tags":[
        "pharmaceutical"
    ],
    "wof:name":"Francopia S.a.",
    "wof:placetype":"venue"
},
  "geometry": {"coordinates":[2.37313,48.834461],"type":"Point"}
}