{
  "type": "Feature",
  "properties": {
    "iso:country":"FR",
    "sg:address":"18 Rue Troyon 92316 S\u00e8vres Cedex",
    "sg:classifiers":[
        {
            "category":"Manufacturing",
            "subcategory":"Motor Vehicles & Parts",
            "type":"Manufacturing & Wholesale Goods"
        }
    ],
    "sg:phone":"+33 1 46 23 56 56",
    "sg:province":"Lorraine",
    "sg:tags":[
        "equipment",
        "product",
        "miscellaneous",
        "transport"
    ],
    "wof:name":"Sfce",
    "wof:placetype":"venue"
},
  "geometry": {"coordinates":[2.226787,48.825878],"type":"Point"}
}