{
  "type": "Feature",
  "properties": {
    "iso:country":"FR",
    "sg:address":"7, Rue du Colombier Blanc, 93120 La Courneuve",
    "sg:orig_category":"Unclassifiable Establishments",
    "sg:phone":"+33 1 49 92 93 40",
    "sg:province":"Ile de France",
    "wof:name":"Le Si\u00e8ge Personnalis\u00e9 S.a.r.l.",
    "wof:placetype":"venue"
},
  "geometry": {"coordinates":[2.404931,48.929855],"type":"Point"}
}