{
  "type": "Feature",
  "properties": {
    "iso:country":"FR",
    "sg:address":"120, Av. Raoul Aladenize, 18500 Mehun sur Y\u00e8vre",
    "sg:city":"Marmagne",
    "sg:orig_category":"Unclassifiable Establishments",
    "sg:phone":"+33 2 48 57 31 05",
    "sg:postcode":"18500",
    "sg:province":"Centre",
    "wof:name":"Etablissements R Melin S.a.",
    "wof:placetype":"venue"
},
  "geometry": {"coordinates":[2.23348,47.14296],"type":"Point"}
}