{
  "type": "Feature",
  "properties": {
    "iso:country":"FR",
    "sg:address":"14/18, Rue Bernard D\u00e9licieux, 34000 Montpellier",
    "sg:orig_category":"Unclassifiable Establishments",
    "sg:phone":"+33 4 67 02 00 51",
    "sg:province":"Languedoc-Roussillon",
    "wof:name":"A.c.t.a. S.a.r.l.",
    "wof:placetype":"venue"
},
  "geometry": {"coordinates":[3.881521,43.615902],"type":"Point"}
}