{
  "type": "Feature",
  "properties": {
    "addr:full":"Pl Winston Churchill 19100 Brive La Gaillarde Limousin",
    "addr:postcode":"19100",
    "addr:street":"Pl Winston Churchill",
    "iso:country":"FR",
    "sg:address":"Pl Winston Churchill 19100 Brive La Gaillarde",
    "sg:classifiers":[
        {
            "category":"Banks & Credit Unions",
            "subcategory":"Investment Brokerage",
            "type":"Services"
        }
    ],
    "sg:phone":"+33 5 55 18 33 00",
    "sg:province":"Limousin",
    "sg:tags":[
        "-",
        "transport",
        "related"
    ],
    "wof:name":"La Poste",
    "wof:placetype":"venue"
},
  "geometry": {"coordinates":[1.53574,45.156891],"type":"Point"}
}