{
  "type": "Feature",
  "properties": {
    "addr:full":"3, Rue de Laon, 02240 Sery l\u00e8s M\u00e9zi\u00e8res Picardie 02240",
    "addr:housenumber":"3",
    "addr:postcode":"02240;02240",
    "addr:street":"Rue De Laon",
    "iso:country":"FR",
    "sg:address":"3, Rue de Laon, 02240 Sery l\u00e8s M\u00e9zi\u00e8res",
    "sg:orig_category":"Non-Classified Establishments",
    "sg:phone":"+33 3 23 66 72 07",
    "sg:postcode":"02240",
    "sg:province":"Picardie",
    "wof:name":"Etablissements Degrande S.a.",
    "wof:placetype":"venue"
},
  "geometry": {"coordinates":[3.42425,49.770161],"type":"Point"}
}