{
  "type": "Feature",
  "properties": {
    "iso:country":"FR",
    "sg:address":"9 rue Eug\u00e8ne H\u00e9naff 78190 Trappes",
    "sg:classifiers":[
        {
            "category":"Arena",
            "subcategory":"Sports Club",
            "type":"Entertainment"
        }
    ],
    "sg:phone":"+33 1 30 66 35 35",
    "sg:postcode":"78190",
    "sg:province":"Ile de France",
    "sg:tags":[
        "graphite"
    ],
    "wof:name":"Graphites Technologie Industrie Sa",
    "wof:placetype":"venue"
},
  "geometry": {"coordinates":[2.006728,48.770218],"type":"Point"}
}