{
  "type": "Feature",
  "properties": {
    "addr:full":"4 Rue L\u00e9on Serpollet 89000 Auxerre Auxerre Bourgogne 89000",
    "addr:housenumber":"4",
    "addr:postcode":"89000;89000",
    "addr:street":"Rue Le\u0301On Serpollet",
    "iso:country":"FR",
    "sg:address":"4 Rue L\u00e9on Serpollet 89000 Auxerre",
    "sg:city":"Auxerre",
    "sg:classifiers":[
        {
            "category":"Government",
            "subcategory":"Department Of Motor Vehicles",
            "type":"Public Place"
        }
    ],
    "sg:phone":"+33 3 86 42 90 89",
    "sg:postcode":"89000",
    "sg:province":"Bourgogne",
    "sg:tags":[
        "equipment",
        "industrial",
        "transport",
        "motor-cars"
    ],
    "wof:name":"Bourgogne Batteries",
    "wof:placetype":"venue"
},
  "geometry": {"coordinates":[3.579475,47.807316],"type":"Point"}
}