{
  "type": "Feature",
  "properties": {
    "iso:country":"FR",
    "sg:address":"13, Av. de Margencel, 74300 Cluses",
    "sg:orig_category":"Unclassifiable Establishments",
    "sg:phone":"+33 4 50 98 02 42",
    "sg:province":"Rhone-Alpes",
    "wof:name":"B.p.c S.a. - B\u00e9chet Production Cluses",
    "wof:placetype":"venue"
},
  "geometry": {"coordinates":[6.57765,46.065384],"type":"Point"}
}