{
  "type": "Feature",
  "properties": {
    "addr:full":"Zi Kerboulard 56250 St Nolff Elven Bretagne 56250",
    "addr:postcode":"56250;56250",
    "addr:street":"Elven",
    "iso:country":"FR",
    "sg:address":"Zi Kerboulard 56250 St Nolff",
    "sg:city":"Elven",
    "sg:classifiers":[
        {
            "category":"Food & Beverages",
            "subcategory":"Groceries & Convenience Stores",
            "type":"Retail Goods"
        }
    ],
    "sg:phone":"+33 2 97 45 58 90",
    "sg:postcode":"56250",
    "sg:province":"Bretagne",
    "sg:tags":[
        "product",
        "related"
    ],
    "wof:name":"Regalette",
    "wof:placetype":"venue"
},
  "geometry": {"coordinates":[-2.653569,47.70607],"type":"Point"}
}