{
  "type": "Feature",
  "properties": {
    "iso:country":"FR",
    "sg:address":"RD 518 - Le parc d'activit\u00e9s le Regain",
    "sg:city":"Toussieu",
    "sg:orig_category":"Unclassifiable Establishments",
    "sg:phone":"+33 4 78 40 20 05",
    "sg:postcode":"69780",
    "sg:province":"Rhone-Alpes",
    "wof:name":"Alpal R\u00e9alisations S.a.r.l.",
    "wof:placetype":"venue"
},
  "geometry": {"coordinates":[4.99177,45.65134],"type":"Point"}
}