{
  "type": "Feature",
  "properties": {
    "iso:country":"FR",
    "sg:address":"1, Place de la R\u00e9publique - Tour Atlantique, 92911 Paris la D\u00e9fence C\u00e9dex",
    "sg:orig_category":"Non-Classified Establishments",
    "sg:phone":"+33 1 40 90 43 70",
    "sg:province":"\u00cele-de-France",
    "wof:name":"Global S.a.",
    "wof:placetype":"venue"
},
  "geometry": {"coordinates":[2.208,48.896141],"type":"Point"}
}