{
  "type": "Feature",
  "properties": {
    "addr:full":"1 Pl Saint Luc 28320 Gallardon Gallardon Centre 28320",
    "addr:housenumber":"1",
    "addr:postcode":"28320;28320",
    "addr:street":"Pl Saint Luc",
    "iso:country":"FR",
    "sg:address":"1 Pl Saint Luc 28320 Gallardon",
    "sg:city":"Gallardon",
    "sg:classifiers":[
        {
            "category":"Professional",
            "subcategory":"Business Services",
            "type":"Services"
        }
    ],
    "sg:phone":"+33 2 37 33 38 20",
    "sg:postcode":"28320",
    "sg:province":"Centre",
    "sg:tags":[
        "training",
        "advice"
    ],
    "wof:name":"College Du Val De L'oise",
    "wof:placetype":"venue"
},
  "geometry": {"coordinates":[1.68767,48.52486],"type":"Point"}
}