{
  "type": "Feature",
  "properties": {
    "addr:full":"17, Rue Saint Exup\u00e9ry, 92700 Colombes Ile de France",
    "addr:housenumber":"17",
    "addr:postcode":"92700;ile",
    "addr:street":"Rue Saint Exupe\u0301Ry",
    "iso:country":"FR",
    "sg:address":"17, Rue Saint Exup\u00e9ry, 92700 Colombes",
    "sg:orig_category":"Non-Classified Establishments",
    "sg:phone":"+33 1 42 42 13 13",
    "sg:province":"Ile de France",
    "wof:name":"Imprimerie Bellemoise S.a.",
    "wof:placetype":"venue"
},
  "geometry": {"coordinates":[2.244481,48.914864],"type":"Point"}
}