{
  "type": "Feature",
  "properties": {
    "addr:full":"21, Rue d'Hennemont, 78100 Saint Germain en Laye Ile de France",
    "addr:housenumber":"21",
    "addr:postcode":"78100",
    "addr:street":"Rue D'Hennemont",
    "iso:country":"FR",
    "sg:address":"21, Rue d'Hennemont, 78100 Saint Germain en Laye",
    "sg:orig_category":"Unclassifiable Establishments",
    "sg:phone":"+33 1 39 73 35 05",
    "sg:province":"Ile de France",
    "wof:name":"B. T\u00e9ran Et Associ\u00e9s S.a.",
    "wof:placetype":"venue"
},
  "geometry": {"coordinates":[2.082352,48.901512],"type":"Point"}
}