{
  "type": "Feature",
  "properties": {
    "iso:country":"FR",
    "sg:address":"15, Rue du Vieux Pont, 92000 Nanterre",
    "sg:orig_category":"Non-Classified Establishments",
    "sg:phone":"+33 1 55 17 21 31",
    "sg:postcode":"92000",
    "sg:province":"Ile de France",
    "wof:name":"Apsynet S.a.",
    "wof:placetype":"venue"
},
  "geometry": {"coordinates":[2.188684,48.891293],"type":"Point"}
}