{
  "type": "Feature",
  "properties": {
    "addr:full":"Le Jangot 69380 Chessy Rhone-Alpes 69380",
    "addr:postcode":"69380;69380",
    "iso:country":"FR",
    "sg:address":"Le Jangot 69380 Chessy",
    "sg:orig_category":"Unclassifiable Establishments",
    "sg:phone":"+33 4 78 43 92 80",
    "sg:postcode":"69380",
    "sg:province":"Rhone-Alpes",
    "wof:name":"Avipol S.a.r.l.",
    "wof:placetype":"venue"
},
  "geometry": {"coordinates":[4.6043,45.885399],"type":"Point"}
}