{
  "type": "Feature",
  "properties": {
    "addr:full":"Le Courtois 69390 Millery Rhone-Alpes",
    "addr:postcode":"69390",
    "iso:country":"FR",
    "sg:address":"Le Courtois 69390 Millery",
    "sg:orig_category":"Unclassifiable Establishments",
    "sg:phone":"+33 4 78 46 19 16",
    "sg:province":"Rhone-Alpes",
    "wof:name":"Vill\u00e9na Fr\u00e8res",
    "wof:placetype":"venue"
},
  "geometry": {"coordinates":[4.792787,45.650181],"type":"Point"}
}