{
  "type": "Feature",
  "properties": {
    "iso:country":"FR",
    "sg:address":"16 Av Mal De Lattre De Tassigy 94120 Fontenay Sous Bois",
    "sg:classifiers":[
        {
            "category":"Building & Trades",
            "subcategory":"Construction",
            "type":"Services"
        }
    ],
    "sg:phone":"+33 1 48 77 70 77",
    "sg:postcode":"94120",
    "sg:province":"Ile de France",
    "sg:tags":[
        "work",
        "public"
    ],
    "wof:name":"Societe Nouvelle Vallet",
    "wof:placetype":"venue"
},
  "geometry": {"coordinates":[2.493845,48.853706],"type":"Point"}
}