{
  "type": "Feature",
  "properties": {
    "iso:country":"FR",
    "sg:address":"8/10, Rue des Immeubles Industriels, 75011 Paris",
    "sg:orig_category":"Unclassifiable Establishments",
    "sg:phone":"+33 1 43 73 78 30",
    "sg:province":"Ile de France",
    "wof:name":"Etablissements Josnin Sarl",
    "wof:placetype":"venue"
},
  "geometry": {"coordinates":[2.39293,48.849545],"type":"Point"}
}