{
  "type": "Feature",
  "properties": {
    "iso:country":"FR",
    "sg:address":"575 Rue Galil\u00e9e Zaet Les Haies 60740 St Maximin",
    "sg:classifiers":[
        {
            "category":"Manufacturing",
            "subcategory":"Metals",
            "type":"Manufacturing & Wholesale Goods"
        }
    ],
    "sg:phone":"+33 3 44 64 61 61",
    "sg:postcode":"60740",
    "sg:province":"Picardie",
    "sg:tags":[
        "metallurgy",
        "metalworking",
        "processing"
    ],
    "wof:name":"Thermi Platin",
    "wof:placetype":"venue"
},
  "geometry": {"coordinates":[2.454171,49.220432],"type":"Point"}
}