{
  "type": "Feature",
  "properties": {
    "addr:full":"1, Rue de la Fontaine, 80120 Rue Picardie",
    "addr:housenumber":"1;80120",
    "addr:street":"Rue De La Fontaine;Rue Picardie",
    "iso:country":"FR",
    "sg:address":"1, Rue de la Fontaine, 80120 Rue",
    "sg:orig_category":"Unclassifiable Establishments",
    "sg:phone":"+33 3 22 25 00 01",
    "sg:province":"Picardie",
    "wof:name":"Sucreries Du Marquenterre S.a.",
    "wof:placetype":"venue"
},
  "geometry": {"coordinates":[1.681767,50.227131],"type":"Point"}
}