{
  "type": "Feature",
  "properties": {
    "iso:country":"FR",
    "sg:address":"6, Rue de Chamrousse, 38600 Fontaine",
    "sg:orig_category":"Non-Classified Establishments",
    "sg:phone":"+33 4 76 26 43 72",
    "sg:province":"Rhone-Alpes",
    "wof:name":"Groupe Roland Bailly S.a.",
    "wof:placetype":"venue"
},
  "geometry": {"coordinates":[5.699027,45.187424],"type":"Point"}
}