{
  "type": "Feature",
  "properties": {
    "iso:country":"FR",
    "sg:address":"21 Avenue De La Division Leclerc 94230 Cachan",
    "sg:classifiers":[
        {
            "category":"Professional",
            "subcategory":"Advertising",
            "type":"Services"
        }
    ],
    "sg:phone":"+33 1 45 46 31 90",
    "sg:postcode":"94230",
    "sg:province":"Ile de France",
    "sg:tags":[
        "marketing",
        "medium",
        "communication"
    ],
    "wof:name":"Cie Etude Sarl",
    "wof:placetype":"venue"
},
  "geometry": {"coordinates":[2.328211,48.78476],"type":"Point"}
}