{
  "type": "Feature",
  "properties": {
    "iso:country":"FR",
    "sg:address":"30 Rue Mal Foch 80130 Friville Escarbotin",
    "sg:classifiers":[
        {
            "category":"Shopping",
            "type":"Retail Goods"
        }
    ],
    "sg:phone":"+33 3 22 60 31 00",
    "sg:postcode":"80130",
    "sg:province":"Picardie",
    "sg:tags":[
        "metallurgy",
        "finished",
        "-",
        "metalworking",
        "metallic"
    ],
    "wof:name":"Laperche Sas",
    "wof:placetype":"venue"
},
  "geometry": {"coordinates":[1.542147,50.080269],"type":"Point"}
}