{
  "type": "Feature",
  "properties": {
    "addr:full":"19, Bd des Varennes, 51700 Dormans Champagne",
    "addr:housenumber":"19",
    "addr:postcode":"51700",
    "addr:street":"Bd Des Varennes",
    "iso:country":"FR",
    "sg:address":"19, Bd des Varennes, 51700 Dormans",
    "sg:orig_category":"Unclassifiable Establishments",
    "sg:phone":"+33 3 26 58 89 03",
    "sg:province":"Champagne",
    "wof:name":"S.a.c.e.m. S.a. - Soci\u00e9t\u00e9 Anonyme De Construction Et D'echaffaudage",
    "wof:placetype":"venue"
},
  "geometry": {"coordinates":[3.642336,49.079063],"type":"Point"}
}