{
  "type": "Feature",
  "properties": {
    "iso:country":"FR",
    "sg:address":"Rue Du Port Aux Cerises 91210 Draveil",
    "sg:classifiers":[
        {
            "category":"Sports & Exercise",
            "subcategory":"Sports Center",
            "type":"Entertainment"
        }
    ],
    "sg:phone":"+33 1 69 83 46 00",
    "sg:postcode":"91210",
    "sg:province":"Ile de France",
    "sg:tags":[
        "game"
    ],
    "wof:name":"Base Regional Plein Air Port Aux Cerises",
    "wof:placetype":"venue"
},
  "geometry": {"coordinates":[2.409055,48.690987],"type":"Point"}
}