{
  "type": "Feature",
  "properties": {
    "iso:country":"FR",
    "sg:address":"31 Av De Bosquet 75007 Paris",
    "sg:classifiers":[
        {
            "category":"Professional",
            "subcategory":"Business Services",
            "type":"Services"
        }
    ],
    "sg:phone":"+33 1 40 62 06 00",
    "sg:postcode":"75007",
    "sg:province":"Ile de France",
    "sg:tags":[
        "training",
        "advice"
    ],
    "wof:name":"The American University Of Paris",
    "wof:placetype":"venue"
},
  "geometry": {"coordinates":[2.305447,48.855679],"type":"Point"}
}