{
  "type": "Feature",
  "properties": {
    "iso:country":"FR",
    "sg:address":"B.P. 125, 37701 Saint Pierre des Corps C\u00e9dex^^45, Rue du Colombier - ZI les Yvaudi\u00e8res, 37700 Saint ",
    "sg:city":"La Ville-aux-Dames",
    "sg:orig_category":"Non-Classified Establishments",
    "sg:phone":"+33 2 47 44 23 08",
    "sg:postcode":"37700",
    "sg:province":"Centre",
    "wof:name":"Thaudi\u00e8re S.a.r.l.",
    "wof:placetype":"venue"
},
  "geometry": {"coordinates":[0.737983,47.38158],"type":"Point"}
}