{
  "type": "Feature",
  "properties": {
    "addr:full":"19 R Des Ecluses 37120 Richelieu Richelieu Centre 37120",
    "addr:housenumber":"19",
    "addr:postcode":"37120;37120",
    "addr:street":"R Des Ecluses",
    "iso:country":"FR",
    "sg:address":"19 R Des Ecluses 37120 Richelieu",
    "sg:city":"Richelieu",
    "sg:classifiers":[
        {
            "category":"Home & Garden",
            "subcategory":"Furniture",
            "type":"Retail Goods"
        }
    ],
    "sg:phone":"+33 2 47 95 30 31",
    "sg:postcode":"37120",
    "sg:province":"Centre",
    "sg:tags":[
        "household",
        "wood"
    ],
    "wof:name":"Mme Ducray Marolleau Bernadette St James M.",
    "wof:placetype":"venue"
},
  "geometry": {"coordinates":[0.326625,47.011822],"type":"Point"}
}