{
  "type": "Feature",
  "properties": {
    "addr:full":"B.P. 75, 67590 Schweighouse sur Moder^^Z.I. de Zinsel, 67590 Schweighouse sur Moder Ohlungen Alsace 67590",
    "addr:postcode":"67590;67590;67590",
    "addr:street":"B.P. 75;Moder^^Z I. De Zinsel",
    "iso:country":"FR",
    "sg:address":"B.P. 75, 67590 Schweighouse sur Moder^^Z.I. de Zinsel, 67590 Schweighouse sur Moder",
    "sg:city":"Ohlungen",
    "sg:orig_category":"Non-Classified Establishments",
    "sg:phone":"+33 3 88 06 40 40",
    "sg:postcode":"67590",
    "sg:province":"Alsace",
    "wof:name":"Isobox Technologies S.a.",
    "wof:placetype":"venue"
},
  "geometry": {"coordinates":[7.73517,48.82151],"type":"Point"}
}