{
  "type": "Feature",
  "properties": {
    "addr:full":"52-54 place Jean Jaur\u00e8s; Albi; 81012 Midi Pyr\u00e9n\u00e9es",
    "addr:housenumber":"52-54",
    "addr:postcode":"81012",
    "addr:street":"Place Jean Jaure\u0300S",
    "iso:country":"FR",
    "sg:address":"52-54 place Jean Jaur\u00e8s; Albi; 81012",
    "sg:classifiers":[
        {
            "category":"Banks & Credit Unions",
            "subcategory":"Bank",
            "type":"Services"
        }
    ],
    "sg:phone":"+33 3363496349",
    "sg:province":"Midi Pyr\u00e9n\u00e9es",
    "wof:name":"Banque Populaire, Du Tran Et De L'aveyron",
    "wof:placetype":"venue"
},
  "geometry": {"coordinates":[2.149544,43.925167],"type":"Point"}
}