{
  "type": "Feature",
  "properties": {
    "addr:full":"16, Rue Sainte Marie, 92230 Gennevilliers Ile de France",
    "addr:housenumber":"16",
    "addr:postcode":"92230;ile",
    "addr:street":"Rue Sainte Marie",
    "iso:country":"FR",
    "sg:address":"16, Rue Sainte Marie, 92230 Gennevilliers",
    "sg:orig_category":"Non-Classified Establishments",
    "sg:phone":"+33 1 47 33 18 19",
    "sg:province":"Ile de France",
    "wof:name":"Joint Helios S.a.",
    "wof:placetype":"venue"
},
  "geometry": {"coordinates":[2.301746,48.916153],"type":"Point"}
}