{
  "type": "Feature",
  "properties": {
    "addr:full":"21 Rue Mairie 59131 Rousies Nord Pas-de-Calais 59131",
    "addr:housenumber":"21",
    "addr:postcode":"59131;59131",
    "addr:street":"Rue Mairie",
    "iso:country":"FR",
    "sg:address":"21 Rue Mairie 59131 Rousies",
    "sg:classifiers":[
        {
            "category":"Manufacturing",
            "subcategory":"Metals",
            "type":"Manufacturing & Wholesale Goods"
        }
    ],
    "sg:phone":"+33 3 27 65 10 28",
    "sg:postcode":"59131",
    "sg:province":"Nord Pas-de-Calais",
    "sg:tags":[
        "metallurgy",
        "metalworking"
    ],
    "wof:name":"Its Febry Ateliers",
    "wof:placetype":"venue"
},
  "geometry": {"coordinates":[4.005418,50.273048],"type":"Point"}
}