{
  "type": "Feature",
  "properties": {
    "iso:country":"FR",
    "sg:address":"4 Rue Camille Desmoulins 75011 Paris",
    "sg:classifiers":[
        {
            "category":"Professional",
            "subcategory":"Business Services",
            "type":"Services"
        }
    ],
    "sg:phone":"+33 1 40 24 02 48",
    "sg:postcode":"75011",
    "sg:province":"Ile de France",
    "sg:tags":[
        "travel",
        "fair"
    ],
    "wof:name":"Espace Voltaire Sa",
    "wof:placetype":"venue"
},
  "geometry": {"coordinates":[2.380631,48.85857],"type":"Point"}
}