{
  "type": "Feature",
  "properties": {
    "addr:full":"B.P. 815, 27200 Vernon^^4, Chemin du Virolet, 27200 Vernon Haute Normandie",
    "addr:housenumber":"b.p. 815",
    "addr:postcode":"27200;27200",
    "addr:street":"Chemin Du Virolet;Haute Normandie",
    "iso:country":"FR",
    "sg:address":"B.P. 815, 27200 Vernon^^4, Chemin du Virolet, 27200 Vernon",
    "sg:orig_category":"Non-Classified Establishments",
    "sg:phone":"+33 2 32 64 65 66",
    "sg:province":"Haute Normandie",
    "wof:name":"Rowenta France S.a.",
    "wof:placetype":"venue"
},
  "geometry": {"coordinates":[1.48403,49.093414],"type":"Point"}
}