{
  "type": "Feature",
  "properties": {
    "addr:full":"Coat An Doc H 22170 Lanrodec Lanrodec Bretagne 22170",
    "addr:postcode":"22170;22170",
    "addr:street":"Doc;Lanrodec",
    "iso:country":"FR",
    "sg:address":"Coat An Doc H 22170 Lanrodec",
    "sg:city":"Lanrodec",
    "sg:classifiers":[
        {
            "category":"Building & Trades",
            "subcategory":"Construction",
            "type":"Services"
        }
    ],
    "sg:phone":"+33 2 96 32 68 68",
    "sg:postcode":"22170",
    "sg:province":"Bretagne",
    "sg:tags":[
        "work",
        "public"
    ],
    "wof:name":"Etablissements Rousseau",
    "wof:placetype":"venue"
},
  "geometry": {"coordinates":[-3.045945,48.535904],"type":"Point"}
}