{
  "type": "Feature",
  "properties": {
    "addr:full":"1 Av Du Mal Foch Carrefour Pompadour 94000 Creteil Ile de France 94000",
    "addr:postcode":"94000;ile;94000",
    "addr:street":"Av Du Mal Foch;Pompadour;France",
    "iso:country":"FR",
    "sg:address":"1 Av Du Mal Foch Carrefour Pompadour 94000 Creteil",
    "sg:classifiers":[
        {
            "category":"Home & Garden",
            "subcategory":"Furniture",
            "type":"Retail Goods"
        }
    ],
    "sg:phone":"+33 1 45 13 29 00",
    "sg:postcode":"94000",
    "sg:province":"Ile de France",
    "sg:tags":[
        "household",
        "wood"
    ],
    "wof:name":"Societe D'exploitation Rapp Fly",
    "wof:placetype":"venue"
},
  "geometry": {"coordinates":[2.455115,48.777866],"type":"Point"}
}