{
  "type": "Feature",
  "properties": {
    "addr:full":"18 Bd Foch 93806 Epinay Sur Seine Cedex Champagne",
    "addr:housenumber":"18",
    "addr:postcode":"93806;seine cedex",
    "addr:street":"Bd Foch",
    "iso:country":"FR",
    "sg:address":"18 Bd Foch 93806 Epinay Sur Seine Cedex",
    "sg:classifiers":[
        {
            "category":"Manufacturing",
            "subcategory":"Metals",
            "type":"Manufacturing & Wholesale Goods"
        }
    ],
    "sg:phone":"+33 1 49 40 10 10",
    "sg:province":"Champagne",
    "sg:tags":[
        "metallurgy",
        "steel",
        "metalworking"
    ],
    "wof:name":"Aciers Durand Freres Sa",
    "wof:placetype":"venue"
},
  "geometry": {"coordinates":[2.336242,48.945461],"type":"Point"}
}