{
  "type": "Feature",
  "properties": {
    "addr:full":"Route Vieille De Graulhet Ld Lombardou 81000 Albi Midi Pyr\u00e9n\u00e9es 81000",
    "addr:postcode":"81000;81000",
    "addr:street":"Route Vieille De Graulhet Ld Lombardou",
    "iso:country":"FR",
    "sg:address":"Route Vieille De Graulhet Ld Lombardou 81000 Albi",
    "sg:classifiers":[
        {
            "category":"Building & Trades",
            "subcategory":"Construction",
            "type":"Services"
        }
    ],
    "sg:phone":"+33 5 63 43 24 40",
    "sg:postcode":"81000",
    "sg:province":"Midi Pyr\u00e9n\u00e9es",
    "sg:tags":[
        "work",
        "public"
    ],
    "wof:name":"Midi Pyrenees Snc",
    "wof:placetype":"venue"
},
  "geometry": {"coordinates":[2.12788,43.90625],"type":"Point"}
}