{
  "type": "Feature",
  "properties": {
    "addr:full":"La Grande Bastide Neuve 84400 Rustrel Haute Normandie",
    "addr:postcode":"84400",
    "addr:street":"La Grande;Neuve;Haute Normandie",
    "iso:country":"FR",
    "sg:address":"La Grande Bastide Neuve 84400 Rustrel",
    "sg:orig_category":"Plastering Services",
    "sg:phone":"+33 4 90 04 92 10",
    "sg:province":"Haute Normandie",
    "wof:name":"Arc Ceramique S.a.r.l.",
    "wof:placetype":"venue"
},
  "geometry": {"coordinates":[5.47399,43.917583],"type":"Point"}
}