{
  "type": "Feature",
  "properties": {
    "iso:country":"FR",
    "sg:address":"RN 532",
    "sg:city":"Saint Quentin sur Is\u00e8re",
    "sg:orig_category":"Unclassifiable Establishments",
    "sg:phone":"+33 4 76 53 94 41",
    "sg:postcode":"38210",
    "sg:province":"Rhone-Alpes",
    "wof:name":"Ravanat Chaudronnerie S.a.",
    "wof:placetype":"venue"
},
  "geometry": {"coordinates":[5.507735,45.237461],"type":"Point"}
}