{
  "type": "Feature",
  "properties": {
    "addr:full":"76540 Ypreville Biville Haute Normandie",
    "addr:postcode":"76540",
    "addr:street":"Haute Normandie",
    "iso:country":"FR",
    "sg:address":"76540 Ypreville Biville",
    "sg:orig_category":"Unclassifiable Establishments",
    "sg:phone":"+33 2 35 10 34 50",
    "sg:province":"Haute Normandie",
    "wof:name":"Etablissements Lerebours S.a.",
    "wof:placetype":"venue"
},
  "geometry": {"coordinates":[0.533875,49.693703],"type":"Point"}
}