{
  "type": "Feature",
  "properties": {
    "addr:full":"20, Rue Pastre, 28109 Dreux C\u00e9dex Centre",
    "addr:housenumber":"20",
    "addr:postcode":"28109",
    "addr:street":"Rue Pastre",
    "iso:country":"FR",
    "sg:address":"20, Rue Pastre, 28109 Dreux C\u00e9dex",
    "sg:orig_category":"Non-Classified Establishments",
    "sg:phone":"+33 2 37 63 04 00",
    "sg:province":"Centre",
    "wof:name":"Esmery Caron Structures S.a.",
    "wof:placetype":"venue"
},
  "geometry": {"coordinates":[1.373229,48.734043],"type":"Point"}
}