{
  "type": "Feature",
  "properties": {
    "addr:full":"13, Av. du Rh\u00f4ne, 74000 Annecy Rhone-Alpes 74000",
    "addr:postcode":"74000;74000",
    "addr:street":"13 Av. Du Rho\u0302Ne",
    "iso:country":"FR",
    "sg:address":"13, Av. du Rh\u00f4ne, 74000 Annecy",
    "sg:orig_category":"Unclassifiable Establishments",
    "sg:phone":"+33 4 50 51 38 98",
    "sg:postcode":"74000",
    "sg:province":"Rhone-Alpes",
    "wof:name":"Synergie S.a.",
    "wof:placetype":"venue"
},
  "geometry": {"coordinates":[6.116103,45.900043],"type":"Point"}
}