{
  "type": "Feature",
  "properties": {
    "iso:country":"FR",
    "sg:address":"Zone Industrielle Du Moustoir BP 80216 56402 Auray Cedex",
    "sg:classifiers":[
        {
            "category":"Professional",
            "subcategory":"Engineering",
            "type":"Services"
        }
    ],
    "sg:phone":"+33 2 97 30 26 26",
    "sg:province":"Bretagne",
    "sg:tags":[
        "machine",
        "-",
        "mechanical"
    ],
    "wof:name":"Ouest Composites",
    "wof:placetype":"venue"
},
  "geometry": {"coordinates":[-2.982301,47.665485],"type":"Point"}
}