{
  "type": "Feature",
  "properties": {
    "addr:full":"6 rue Vauban 33000 Bordeaux Bordeaux Aquitaine 33000",
    "addr:housenumber":"6",
    "addr:postcode":"33000;33000",
    "addr:street":"Rue Vauban",
    "iso:country":"FR",
    "sg:address":"6 rue Vauban 33000 Bordeaux",
    "sg:city":"Bordeaux",
    "sg:classifiers":[
        {
            "category":"Wholesale",
            "subcategory":"Tobacco Products",
            "type":"Manufacturing & Wholesale Goods"
        }
    ],
    "sg:phone":"+33 5 56 00 61 61",
    "sg:postcode":"33000",
    "sg:province":"Aquitaine",
    "sg:tags":[
        "raw",
        "waste"
    ],
    "wof:name":"Aquitaine Plastique S.a.",
    "wof:placetype":"venue"
},
  "geometry": {"coordinates":[-0.573796,44.847515],"type":"Point"}
}