{
  "type": "Feature",
  "properties": {
    "addr:full":"Rue de la Croix Bougard - Zone Industrielle Lesquin Nord-Pas-de-Calais 59817",
    "addr:postcode":"59817",
    "addr:street":"Rue De La Croix Bougard Zone Industrielle",
    "iso:country":"FR",
    "sg:address":"Rue de la Croix Bougard - Zone Industrielle",
    "sg:city":"Lesquin",
    "sg:orig_category":"Non-Classified Establishments",
    "sg:phone":"+33 3 20 87 89 50",
    "sg:postcode":"59817",
    "sg:province":"Nord-Pas-de-Calais",
    "wof:name":"Loueurs De France B.t.p. S.a.",
    "wof:placetype":"venue"
},
  "geometry": {"coordinates":[3.11003,50.588009],"type":"Point"}
}