{
  "type": "Feature",
  "properties": {
    "iso:country":"FR",
    "sg:address":"86, Rue de la R\u00e9publique, 71000 M\u00e2con",
    "sg:city":"Sanc\u00e9",
    "sg:orig_category":"Non-Classified Establishments",
    "sg:phone":"+33 3 85 20 92 00",
    "sg:postcode":"71000",
    "sg:province":"Bourgogne",
    "wof:name":"Sofembal - Soflog S.a.s.",
    "wof:placetype":"venue"
},
  "geometry": {"coordinates":[4.825837,46.293659],"type":"Point"}
}