{
  "type": "Feature",
  "properties": {
    "iso:country":"FR",
    "sg:address":"5, Rue d'Amiens, 60200 Compi\u00e8gne",
    "sg:orig_category":"Unclassifiable Establishments",
    "sg:phone":"+33 3 44 36 66 65",
    "sg:province":"Picardie",
    "wof:name":"A.a.a. France Cars S.a.s.",
    "wof:placetype":"venue"
},
  "geometry": {"coordinates":[2.820204,49.423161],"type":"Point"}
}