{
  "type": "Feature",
  "properties": {
    "iso:country":"FR",
    "sg:address":"2 Rue Du Marechal Foch 45370 Clery St Andre",
    "sg:city":"Cl\u00e9ry-Saint-Andr\u00e9",
    "sg:classifiers":[
        {
            "category":"Health Services",
            "subcategory":"Medical Lab",
            "type":"Services"
        }
    ],
    "sg:phone":"+33 2 38 45 71 86",
    "sg:postcode":"45370",
    "sg:province":"Centre",
    "sg:tags":[
        "chemical",
        "pharmaceutical",
        "pharmacy"
    ],
    "wof:name":"Cs",
    "wof:placetype":"venue"
},
  "geometry": {"coordinates":[1.753116,47.818699],"type":"Point"}
}