{
  "type": "Feature",
  "properties": {
    "addr:full":"20, Rue Garibaldi, 69006 Lyon Rhone-Alpes",
    "addr:housenumber":"20",
    "addr:postcode":"69006",
    "addr:street":"Rue Garibaldi",
    "iso:country":"FR",
    "sg:address":"20, Rue Garibaldi, 69006 Lyon",
    "sg:orig_category":"Non-Classified Establishments",
    "sg:phone":"+33 1 78 17 81 00",
    "sg:province":"Rhone-Alpes",
    "wof:name":"Landwell Et Partners S.a.",
    "wof:placetype":"venue"
},
  "geometry": {"coordinates":[4.849689,45.772198],"type":"Point"}
}