{
  "type": "Feature",
  "properties": {
    "addr:full":"165 Rue Jacquard 76330 Notre Dame De Gravenchon Haute Normandie 76330",
    "addr:housenumber":"165",
    "addr:postcode":"76330;76330",
    "addr:street":"Rue Jacquard;Dame",
    "iso:country":"FR",
    "sg:address":"165 Rue Jacquard 76330 Notre Dame De Gravenchon",
    "sg:classifiers":[
        {
            "category":"Shopping",
            "type":"Retail Goods"
        }
    ],
    "sg:phone":"+33 2 35 39 82 38",
    "sg:postcode":"76330",
    "sg:province":"Haute Normandie",
    "sg:tags":[
        "metallurgy",
        "finished",
        "-",
        "metalworking",
        "metallic"
    ],
    "wof:name":"Ste Sgl",
    "wof:placetype":"venue"
},
  "geometry": {"coordinates":[0.579408,49.483528],"type":"Point"}
}