{
  "type": "Feature",
  "properties": {
    "addr:full":"13398 Marseille C\u00e9dex 20^^Traverse de la Montre Marseille Poitou-Charentes 13020",
    "addr:postcode":"13398;13020",
    "addr:street":"Montre",
    "iso:country":"FR",
    "sg:address":"13398 Marseille C\u00e9dex 20^^Traverse de la Montre",
    "sg:city":"Marseille",
    "sg:orig_category":"Non-Classified Establishments",
    "sg:phone":"+33 4 91 45 62 00",
    "sg:postcode":"13020",
    "sg:province":"Poitou-Charentes",
    "wof:name":"Soci\u00e9t\u00e9 Suisse Sant\u00e9",
    "wof:placetype":"venue"
},
  "geometry": {"coordinates":[5.38078,43.311352],"type":"Point"}
}