{
  "type": "Feature",
  "properties": {
    "addr:full":"17 rue Jacob 75006 Paris Ile de France 75006",
    "addr:housenumber":"17",
    "addr:postcode":"75006;75006",
    "addr:street":"Rue Jacob",
    "iso:country":"FR",
    "sg:address":"17 rue Jacob 75006 Paris",
    "sg:classifiers":[
        {
            "category":"Shopping",
            "subcategory":"Books",
            "type":"Retail Goods"
        }
    ],
    "sg:phone":"+33 1 44 41 74 00",
    "sg:postcode":"75006",
    "sg:province":"Ile de France",
    "wof:name":"Editions Jean Claude Lattes Snc",
    "wof:placetype":"venue"
},
  "geometry": {"coordinates":[2.334887,48.855019],"type":"Point"}
}