{
  "type": "Feature",
  "properties": {
    "addr:full":"158, Av. Francis de Pressens\u00e9 - Parc d'Activit\u00e9 de Pressenc\u00e9, 69200 V\u00e9nissieux Rhone-Alpes",
    "addr:postcode":"69200",
    "addr:street":"158 Av. Francis De Pressense\u0301 Parc D'Activite \u0301 De Pressence\u0301",
    "iso:country":"FR",
    "sg:address":"158, Av. Francis de Pressens\u00e9 - Parc d'Activit\u00e9 de Pressenc\u00e9, 69200 V\u00e9nissieux",
    "sg:orig_category":"Unclassifiable Establishments",
    "sg:phone":"+33 4 78 77 97 97",
    "sg:province":"Rhone-Alpes",
    "wof:name":"Solmurex S.a.",
    "wof:placetype":"venue"
},
  "geometry": {"coordinates":[4.867358,45.720612],"type":"Point"}
}