{
  "type": "Feature",
  "properties": {
    "addr:full":"21 Rue De L'Ems 76360 Barentin Haute Normandie 76360",
    "addr:housenumber":"21",
    "addr:postcode":"76360;76360",
    "addr:street":"Rue De L'Ems;Haute Normandie",
    "iso:country":"FR",
    "sg:address":"21 Rue De L'Ems 76360 Barentin",
    "sg:classifiers":[
        {
            "category":"Home & Garden",
            "subcategory":"Furniture",
            "type":"Retail Goods"
        }
    ],
    "sg:phone":"+33 2 32 94 97 97",
    "sg:postcode":"76360",
    "sg:province":"Haute Normandie",
    "sg:tags":[
        "household",
        "wood"
    ],
    "wof:name":"Societe D'exploitation Rapp Fly",
    "wof:placetype":"venue"
},
  "geometry": {"coordinates":[0.95364,49.545399],"type":"Point"}
}