{
  "type": "Feature",
  "properties": {
    "addr:full":"Les Baraques 42640 St Romain La Motte Rhone-Alpes",
    "addr:postcode":"42640",
    "addr:street":"Baraques;Rhone-Alpes",
    "iso:country":"FR",
    "sg:address":"Les Baraques 42640 St Romain La Motte",
    "sg:classifiers":[
        {
            "category":"Professional",
            "subcategory":"Printing & Photocopies",
            "type":"Services"
        }
    ],
    "sg:phone":"+33 4 77 71 62 29",
    "sg:province":"Rhone-Alpes",
    "sg:tags":[
        "publishing"
    ],
    "wof:name":"Imprimerie Des Arts Graphiques Sa",
    "wof:placetype":"venue"
},
  "geometry": {"coordinates":[4.024036,46.084061],"type":"Point"}
}