{
  "type": "Feature",
  "properties": {
    "addr:full":"20, Rue du Pont d'Arrot, 71150 Rully Rully Bourgogne 71150",
    "addr:housenumber":"20",
    "addr:postcode":"71150;71150",
    "addr:street":"Rue Du Pont D'Arrot",
    "iso:country":"FR",
    "sg:address":"20, Rue du Pont d'Arrot, 71150 Rully",
    "sg:city":"Rully",
    "sg:orig_category":"Unclassifiable Establishments",
    "sg:phone":"+33 3 85 87 23 97",
    "sg:postcode":"71150",
    "sg:province":"Bourgogne",
    "wof:name":"Vitteaut Alberti S.a.r.l.",
    "wof:placetype":"venue"
},
  "geometry": {"coordinates":[4.742976,46.875916],"type":"Point"}
}