{
  "type": "Feature",
  "properties": {
    "addr:full":"Chem De Halage De Casa 25000 Besan\u00e7on Franche Comt\u00e9 25000",
    "addr:postcode":"25000;25000",
    "addr:street":"Chem De Halage De Casa;Franche Comte\u0301",
    "iso:country":"FR",
    "sg:address":"Chem De Halage De Casa 25000 Besan\u00e7on",
    "sg:classifiers":[
        {
            "category":"Manufacturing",
            "subcategory":"Building Materials",
            "type":"Manufacturing & Wholesale Goods"
        }
    ],
    "sg:phone":"+33 3 81 51 42 70",
    "sg:postcode":"25000",
    "sg:province":"Franche Comt\u00e9",
    "sg:tags":[
        "glass",
        "ceramic"
    ],
    "wof:name":"Longchamp Carreaux",
    "wof:placetype":"venue"
},
  "geometry": {"coordinates":[6.024041,47.21954],"type":"Point"}
}