{
  "type": "Feature",
  "properties": {
    "addr:full":"ZI des Monts Havards - Espace 2000 Villedieu les Po\u00eales Basse Normandie 50800",
    "addr:postcode":"2000;50800",
    "addr:street":"Des Monts Havards Espace",
    "iso:country":"FR",
    "sg:address":"ZI des Monts Havards - Espace 2000",
    "sg:city":"Villedieu les Po\u00eales",
    "sg:orig_category":"Unclassifiable Establishments",
    "sg:phone":"+33 2 33 91 26 26",
    "sg:postcode":"50800",
    "sg:province":"Basse Normandie",
    "wof:name":"Normatrans S.a.",
    "wof:placetype":"venue"
},
  "geometry": {"coordinates":[-1.178043,48.785904],"type":"Point"}
}