{
  "type": "Feature",
  "properties": {
    "iso:country":"FR",
    "sg:address":"70, Av. des Champs Elys\u00e9es, 75008 Paris",
    "sg:orig_category":"Unclassifiable Establishments",
    "sg:phone":"+33 1 53 93 55 00",
    "sg:province":"Ile de France",
    "wof:name":"H\u00f4tel Paris Marriott Champs Elys\u00e9es",
    "wof:placetype":"venue"
},
  "geometry": {"coordinates":[2.304744,48.870796],"type":"Point"}
}