{
  "type": "Feature",
  "properties": {
    "addr:full":"Lieu Dit La Chapelle Pecha 24250 Castelnaud La Chapelle Bouzic Aquitaine 24250",
    "addr:postcode":"24250;24250",
    "addr:street":"Lieu Dit La Chapelle Pecha",
    "iso:country":"FR",
    "sg:address":"Lieu Dit La Chapelle Pecha 24250 Castelnaud La Chapelle",
    "sg:city":"Bouzic",
    "sg:classifiers":[
        {
            "category":"Home & Garden",
            "subcategory":"Furniture",
            "type":"Retail Goods"
        }
    ],
    "sg:phone":"+33 5 53 29 52 05",
    "sg:postcode":"24250",
    "sg:province":"Aquitaine",
    "sg:tags":[
        "wood"
    ],
    "wof:name":"Etablissements Coste",
    "wof:placetype":"venue"
},
  "geometry": {"coordinates":[1.120474,44.778599],"type":"Point"}
}