{
  "type": "Feature",
  "properties": {
    "addr:full":"La Grange Barbier 37250 Sorigny Sorigny Centre 37250",
    "addr:postcode":"37250;37250",
    "iso:country":"FR",
    "sg:address":"La Grange Barbier 37250 Sorigny",
    "sg:city":"Sorigny",
    "sg:orig_category":"Non-Classified Establishments",
    "sg:phone":"+33 2 47 73 14 00",
    "sg:postcode":"37250",
    "sg:province":"Centre",
    "wof:name":"A.c.s E.u.r.l. - Alu Concept System's",
    "wof:placetype":"venue"
},
  "geometry": {"coordinates":[0.69419,47.241489],"type":"Point"}
}