{
  "type": "Feature",
  "properties": {
    "addr:full":"76 Rue De La Forge 76690 Les Authieux Rati\u00e9ville Haute Normandie 76690",
    "addr:housenumber":"76",
    "addr:postcode":"76690;76690",
    "addr:street":"Rue De La Forge;Authieux;Haute Normandie",
    "iso:country":"FR",
    "sg:address":"76 Rue De La Forge 76690 Les Authieux Rati\u00e9ville",
    "sg:classifiers":[
        {
            "category":"Wholesale",
            "subcategory":"Farm Supplies",
            "type":"Manufacturing & Wholesale Goods"
        }
    ],
    "sg:phone":"+33 2 35 33 23 34",
    "sg:postcode":"76690",
    "sg:province":"Haute Normandie",
    "sg:tags":[
        "-",
        "machine",
        "equipment",
        "engineering",
        "machinery",
        "mechanical",
        "agriculture"
    ],
    "wof:name":"Ets Mouchard Sa",
    "wof:placetype":"venue"
},
  "geometry": {"coordinates":[1.13728,49.590527],"type":"Point"}
}