{
  "type": "Feature",
  "properties": {
    "addr:full":"RN 10 Les Ormes Bourgogne 86220",
    "addr:postcode":"86220",
    "addr:street":"Rn 10 Les;Bourgogne",
    "iso:country":"FR",
    "sg:address":"RN 10",
    "sg:city":"Les Ormes",
    "sg:orig_category":"Unclassifiable Establishments",
    "sg:phone":"+33 5 49 19 12 30",
    "sg:postcode":"86220",
    "sg:province":"Bourgogne",
    "wof:name":"Cartonnage De Touraine S.a.",
    "wof:placetype":"venue"
},
  "geometry": {"coordinates":[0.628151,46.872829],"type":"Point"}
}