{
  "type": "Feature",
  "properties": {
    "addr:full":"41 rue Jean Moulin; Caluire et Cuire Picardie",
    "addr:housenumber":"41",
    "addr:street":"Rue Jean Moulin",
    "iso:country":"FR",
    "sg:address":"41 rue Jean Moulin; Caluire et Cuire",
    "sg:classifiers":[
        {
            "category":"Banks & Credit Unions",
            "subcategory":"Bank",
            "type":"Services"
        }
    ],
    "sg:phone":"+33 3378233829",
    "sg:province":"Picardie",
    "wof:name":"Cr\u00e9dit Agricole Du Sud Est",
    "wof:placetype":"venue"
},
  "geometry": {"coordinates":[4.847242,45.799763],"type":"Point"}
}