{
  "type": "Feature",
  "properties": {
    "addr:full":"1635, Chemin de la Plaine, 06250 Mougins Plaine Alsace 67420",
    "addr:housenumber":"1635",
    "addr:postcode":"06250;67420",
    "addr:street":"Chemin De La Plaine;Plaine",
    "iso:country":"FR",
    "sg:address":"1635, Chemin de la Plaine, 06250 Mougins",
    "sg:city":"Plaine",
    "sg:orig_category":"Non-Classified Establishments",
    "sg:phone":"+33 4 92 92 20 25",
    "sg:postcode":"67420",
    "sg:province":"Alsace",
    "wof:name":"A.p.f. S.a.r.l.",
    "wof:placetype":"venue"
},
  "geometry": {"coordinates":[6.9689,43.598526],"type":"Point"}
}