{
  "type": "Feature",
  "properties": {
    "addr:full":"Rue De Beyne 05000 Gap Bourgogne",
    "addr:postcode":"05000;bourgogne",
    "addr:street":"Rue De Beyne",
    "iso:country":"FR",
    "sg:address":"Rue De Beyne 05000 Gap",
    "sg:classifiers":[
        {
            "category":"Travel",
            "subcategory":"Hotels & Motels",
            "type":"Entertainment"
        }
    ],
    "sg:phone":"+33 4 92 52 02 73",
    "sg:province":"Bourgogne",
    "sg:tags":[
        "hotels",
        "business",
        "restaurant"
    ],
    "wof:name":"Ste Exploit Hotelier Carina Sa",
    "wof:placetype":"venue"
},
  "geometry": {"coordinates":[6.07483,44.554939],"type":"Point"}
}