{
  "type": "Feature",
  "properties": {
    "addr:full":"60 R Francis De Pressens\u00e9 93200 St Denis Ile de France 93200",
    "addr:housenumber":"60 r",
    "addr:postcode":"93200;93200",
    "addr:street":"Francis De Pressense\u0301",
    "iso:country":"FR",
    "sg:address":"60 R Francis De Pressens\u00e9 93200 St Denis",
    "sg:classifiers":[
        {
            "category":"Utilities",
            "subcategory":"Mobile Phone",
            "type":"Services"
        }
    ],
    "sg:phone":"+33 1 48 33 14 14",
    "sg:postcode":"93200",
    "sg:province":"Ile de France",
    "sg:tags":[
        "telecommunication",
        "audio-visual"
    ],
    "wof:name":"Jolu Sa",
    "wof:placetype":"venue"
},
  "geometry": {"coordinates":[2.373059,48.924187],"type":"Point"}
}