{
  "type": "Feature",
  "properties": {
    "addr:full":"122, Rue du Commandant Rolland - Le Montcalm n\u00b01, 13008 Marseille Poitou-Charentes",
    "addr:housenumber":"122",
    "addr:postcode":"n\u00b01 13008",
    "addr:street":"Rue Du Commandant Rolland",
    "iso:country":"FR",
    "sg:address":"122, Rue du Commandant Rolland - Le Montcalm n\u00b01, 13008 Marseille",
    "sg:orig_category":"Non-Classified Establishments",
    "sg:phone":"+33 4 91 77 36 66",
    "sg:province":"Poitou-Charentes",
    "wof:name":"Canyon S.a.r.l.",
    "wof:placetype":"venue"
},
  "geometry": {"coordinates":[5.364135,43.238701],"type":"Point"}
}