{
  "type": "Feature",
  "properties": {
    "addr:full":"B.P. 55, 13908 Marseille C\u00e9dex 20^^33, Bd Ferdinand de Lesseps, 13020 Marseille Poitou-Charentes",
    "addr:housenumber":"20 ^ ^ 33",
    "addr:postcode":"13908;13020",
    "addr:street":"B.P. 55;Ce\u0301Dex;Bd Ferdinand De Lesseps",
    "iso:country":"FR",
    "sg:address":"B.P. 55, 13908 Marseille C\u00e9dex 20^^33, Bd Ferdinand de Lesseps, 13020 Marseille",
    "sg:orig_category":"Non-Classified Establishments",
    "sg:phone":"+33 4 95 05 57 00",
    "sg:province":"Poitou-Charentes",
    "wof:name":"Dole France S.a.",
    "wof:placetype":"venue"
},
  "geometry": {"coordinates":[5.38078,43.311352],"type":"Point"}
}