{
  "type": "Feature",
  "properties": {
    "addr:full":"Centre Urbain; Vitrolles; 13127 Centre",
    "addr:housenumber":"13127",
    "iso:country":"FR",
    "sg:address":"Centre Urbain; Vitrolles; 13127",
    "sg:classifiers":[
        {
            "category":"Banks & Credit Unions",
            "subcategory":"Bank",
            "type":"Services"
        }
    ],
    "sg:phone":"+33 3342105480",
    "sg:province":"Centre",
    "wof:name":"Soci\u00e9t\u00e9 G\u00e9n\u00e9rale",
    "wof:placetype":"venue"
},
  "geometry": {"coordinates":[5.253005,43.449944],"type":"Point"}
}