{
  "type": "Feature",
  "properties": {
    "addr:full":"7 Rue Des Reculettes 75013 Paris Ile de France 75013",
    "addr:housenumber":"7",
    "addr:postcode":"75013;75013",
    "addr:street":"Rue Des Reculettes",
    "iso:country":"FR",
    "sg:address":"7 Rue Des Reculettes 75013 Paris",
    "sg:classifiers":[
        {
            "category":"Professional",
            "subcategory":"Business Services",
            "type":"Services"
        }
    ],
    "sg:phone":"+33 1 43 37 51 45",
    "sg:postcode":"75013",
    "sg:province":"Ile de France",
    "sg:tags":[
        "body",
        "advice"
    ],
    "wof:name":"Ass Soins Et Services A Domicile",
    "wof:placetype":"venue"
},
  "geometry": {"coordinates":[2.350627,48.831787],"type":"Point"}
}