{
  "type": "Feature",
  "properties": {
    "iso:country":"FR",
    "sg:address":"Place de l'Eglise 21630 POMMARD",
    "sg:city":"Pommard",
    "sg:classifiers":[
        {
            "category":"Wholesale",
            "subcategory":"Wine & Distilled Alcoholic Beverages",
            "type":"Manufacturing & Wholesale Goods"
        }
    ],
    "sg:phone":"+33 3 80 22 15 08",
    "sg:postcode":"21630",
    "sg:province":"Bourgogne",
    "sg:tags":[
        "french"
    ],
    "wof:name":"Sa Du Domaine Parent S.a.",
    "wof:placetype":"venue"
},
  "geometry": {"coordinates":[4.794191,47.00919],"type":"Point"}
}