{
  "type": "Feature",
  "properties": {
    "iso:country":"FR",
    "sg:address":"2 Bis Rue Louis Chauvet 50100 Cherbourg",
    "sg:city":"Cherbourg-Octeville",
    "sg:classifiers":[
        {
            "category":"Wholesale",
            "subcategory":"Medical Equipment & Supplies",
            "type":"Manufacturing & Wholesale Goods"
        }
    ],
    "sg:phone":"+33 2 33 53 10 26",
    "sg:postcode":"50100",
    "sg:province":"Basse Normandie",
    "sg:tags":[
        "instrument",
        "health",
        "-",
        "precision"
    ],
    "wof:name":"Laboratoire Eurodenthese Eurl",
    "wof:placetype":"venue"
},
  "geometry": {"coordinates":[-1.633745,49.639565],"type":"Point"}
}