{
  "type": "Feature",
  "properties": {
    "addr:full":"15 Route De Douchy 45220 Chateau Renard Douchy Centre 45220",
    "addr:housenumber":"15",
    "addr:postcode":"45220;45220",
    "addr:street":"Route De Douchy",
    "iso:country":"FR",
    "sg:address":"15 Route De Douchy 45220 Chateau Renard",
    "sg:city":"Douchy",
    "sg:classifiers":[
        {
            "category":"Manufacturing",
            "subcategory":"Printing",
            "type":"Manufacturing & Wholesale Goods"
        }
    ],
    "sg:phone":"+33 2 38 94 06 75",
    "sg:postcode":"45220",
    "sg:province":"Centre",
    "sg:tags":[
        "publishing"
    ],
    "wof:name":"Kairos",
    "wof:placetype":"venue"
},
  "geometry": {"coordinates":[2.952895,47.895451],"type":"Point"}
}