{
  "type": "Feature",
  "properties": {
    "iso:country":"FR",
    "sg:address":"26, Place Madeleine, 21200 Beaune",
    "sg:city":"Beaune",
    "sg:orig_category":"Unclassifiable Establishments",
    "sg:phone":"+33 3 80 26 27 00",
    "sg:postcode":"21200",
    "sg:province":"Bourgogne",
    "wof:name":"Caisse D'epargne De Bourgogne - Agence Beaune Madeleine",
    "wof:placetype":"venue"
},
  "geometry": {"coordinates":[4.842404,47.021809],"type":"Point"}
}