{
  "type": "Feature",
  "properties": {
    "addr:full":"111, Rte de Pezenas, 34500 B\u00e9ziers Languedoc-Roussillon",
    "addr:housenumber":"111",
    "addr:postcode":"34500",
    "addr:street":"Rte De Pezenas",
    "iso:country":"FR",
    "sg:address":"111, Rte de Pezenas, 34500 B\u00e9ziers",
    "sg:orig_category":"Unclassifiable Establishments",
    "sg:phone":"+33 4 67 09 10 00",
    "sg:province":"Languedoc-Roussillon",
    "wof:name":"Gedimat S.a.",
    "wof:placetype":"venue"
},
  "geometry": {"coordinates":[3.216105,43.344234],"type":"Point"}
}