{
  "type": "Feature",
  "properties": {
    "addr:full":"Zone d'activit\u00e9 Champ 7 Laux 38190 LE CHAMP PRES FROGES Rhone-Alpes 38190",
    "addr:housenumber":"7;froges",
    "addr:postcode":"38190;38190",
    "addr:street":"Zone;\u0301 Champ;Laux;Champ Pres",
    "iso:country":"FR",
    "sg:address":"Zone d'activit\u00e9 Champ 7 Laux 38190 LE CHAMP PRES FROGES",
    "sg:orig_category":"Illuminated Balloons",
    "sg:phone":"+33 4 76 13 12 20",
    "sg:postcode":"38190",
    "sg:province":"Rhone-Alpes",
    "wof:name":"Airstar Sa",
    "wof:placetype":"venue"
},
  "geometry": {"coordinates":[5.933131,45.285702],"type":"Point"}
}