{
  "type": "Feature",
  "properties": {
    "iso:country":"FR",
    "sg:address":"Zone d'activit\u00e9 Champ 7 Laux 38190 LE CHAMP PRES FROGES",
    "sg:orig_category":"Illuminated Balloons",
    "sg:phone":"+33 4 76 13 12 20",
    "sg:postcode":"38190",
    "sg:province":"Rhone-Alpes",
    "wof:name":"Airstar Sa",
    "wof:placetype":"venue"
},
  "geometry": {"coordinates":[5.933131,45.285702],"type":"Point"}
}