{
  "type": "Feature",
  "properties": {
    "iso:country":"FR",
    "sg:address":"102, Rue Emile Zola, 76300 Sotteville l\u00e8s Rouen",
    "sg:orig_category":"Unclassifiable Establishments",
    "sg:phone":"+33 2 35 72 15 30",
    "sg:province":"Haute Normandie",
    "wof:name":"S.n.a.t. S.a. - Soci\u00e9t\u00e9 Normande D'assistance Temporaire",
    "wof:placetype":"venue"
},
  "geometry": {"coordinates":[1.08765,49.419617],"type":"Point"}
}