{
  "type": "Feature",
  "properties": {
    "iso:country":"FR",
    "sg:address":"89, Av. de Colmar, 67100 Strasbourg",
    "sg:city":"Strasbourg",
    "sg:orig_category":"Unclassifiable Establishments",
    "sg:phone":"+33 3 88 84 90 60",
    "sg:postcode":"67100",
    "sg:province":"Alsace",
    "wof:name":"Insep Consulting S.a.",
    "wof:placetype":"venue"
},
  "geometry": {"coordinates":[7.752166,48.568356],"type":"Point"}
}