{
  "type": "Feature",
  "properties": {
    "addr:full":"BP 1, 1-3 Place du G\u00e9n\u00e9ral de Gaulle, 88500 Mirecourt, Dept 88 Lorraine 88500",
    "addr:housenumber":"1-3;88",
    "addr:postcode":"88500;88500",
    "addr:street":"1;Place Du Ge\u0301Ne\u0301Ral De Gaulle;Lorraine",
    "iso:country":"FR",
    "sg:address":"BP 1, 1-3 Place du G\u00e9n\u00e9ral de Gaulle, 88500 Mirecourt, Dept 88",
    "sg:classifiers":[
        {
            "category":"Banks & Credit Unions",
            "subcategory":"Bank",
            "type":"Services"
        }
    ],
    "sg:phone":"+33 3 29 37 11 77",
    "sg:postcode":"88500",
    "sg:province":"Lorraine",
    "wof:name":"Banque Kolb Sa",
    "wof:placetype":"venue"
},
  "geometry": {"coordinates":[6.133969,48.301151],"type":"Point"}
}