{
  "type": "Feature",
  "properties": {
    "addr:full":"Bd Pierre Lefaucheux Arnage Pays de Loire 72230",
    "addr:postcode":"72230",
    "addr:street":"Bd Pierre Lefaucheux",
    "iso:country":"FR",
    "sg:address":"Bd Pierre Lefaucheux",
    "sg:city":"Arnage",
    "sg:orig_category":"Unclassifiable Establishments",
    "sg:phone":"+33 2 43 21 13 74",
    "sg:postcode":"72230",
    "sg:province":"Pays de Loire",
    "wof:name":"Rocheron Machines-outils S.a.",
    "wof:placetype":"venue"
},
  "geometry": {"coordinates":[0.186801,47.935577],"type":"Point"}
}