{
  "type": "Feature",
  "properties": {
    "addr:full":"rte des Hauts de Mont 54360 Mont sur Meurthe Lorraine",
    "addr:postcode":"54360",
    "addr:street":"Rte Des Hauts De Mont",
    "iso:country":"FR",
    "sg:address":"rte",
    "sg:city":"des Hauts de Mont 54360 Mont sur Meurthe",
    "sg:classifiers":[
        {
            "category":"Manufacturing",
            "subcategory":"Paper Products",
            "type":"Manufacturing & Wholesale Goods"
        }
    ],
    "sg:phone":"+33 3 83 75 70 17",
    "sg:province":"Lorraine",
    "sg:tags":[
        "packaging",
        "material",
        "-",
        "cardboard"
    ],
    "wof:name":"Emballages Diffusion (sa)",
    "wof:placetype":"venue"
},
  "geometry": {"coordinates":[6.41022,48.555401],"type":"Point"}
}