{
  "type": "Feature",
  "properties": {
    "iso:country":"FR",
    "sg:address":"19, Av. de Grammont, 37000 Tours",
    "sg:city":"Tours",
    "sg:orig_category":"Unclassifiable Establishments",
    "sg:phone":"+33 2 47 21 80 00",
    "sg:postcode":"37000",
    "sg:province":"Centre",
    "wof:name":"M.p.f.a.",
    "wof:placetype":"venue"
},
  "geometry": {"coordinates":[0.689603,47.387295],"type":"Point"}
}