{
  "type": "Feature",
  "properties": {
    "addr:full":"64, Rue de la Gatelli\u00e8re, 45380 La chapelle Saint Mesmin La Chapelle-Saint-Mesmin Centre 45380",
    "addr:housenumber":"64;chapelle-saint-mesmin",
    "addr:postcode":"45380;45380",
    "addr:street":"Rue De La Gatellie\u0300Re;La",
    "iso:country":"FR",
    "sg:address":"64, Rue de la Gatelli\u00e8re, 45380 La chapelle Saint Mesmin",
    "sg:city":"La Chapelle-Saint-Mesmin",
    "sg:orig_category":"Unclassifiable Establishments",
    "sg:phone":"+33 2 38 70 56 00",
    "sg:postcode":"45380",
    "sg:province":"Centre",
    "wof:name":"J.beaudenuit Ressorts E.u.r.l.",
    "wof:placetype":"venue"
},
  "geometry": {"coordinates":[1.83682,47.889439],"type":"Point"}
}