{
  "type": "Feature",
  "properties": {
    "addr:full":"23 Rue Michel Le Comte 75003 Paris Ile de France 75003",
    "addr:housenumber":"23",
    "addr:postcode":"75003;75003",
    "addr:street":"Rue Michel Le Comte",
    "iso:country":"FR",
    "sg:address":"23 Rue Michel Le Comte 75003 Paris",
    "sg:classifiers":[
        {
            "category":"Manufacturing",
            "subcategory":"Jewelry",
            "type":"Manufacturing & Wholesale Goods"
        }
    ],
    "sg:phone":"+33 1 48 04 75 74",
    "sg:postcode":"75003",
    "sg:province":"Ile de France",
    "sg:tags":[
        "product",
        "miscellaneous",
        "jewellery"
    ],
    "wof:name":"Babylone",
    "wof:placetype":"venue"
},
  "geometry": {"coordinates":[2.355224,48.862335],"type":"Point"}
}