{
  "type": "Feature",
  "properties": {
    "addr:full":"Vallon Saint Guenol\u00e9 - Le Varquez Carantec Bretagne 29660",
    "addr:postcode":"29660",
    "addr:street":"Vallon;Carantec Bretagne",
    "iso:country":"FR",
    "sg:address":"Vallon Saint Guenol\u00e9 - Le Varquez",
    "sg:city":"Carantec",
    "sg:orig_category":"Unclassifiable Establishments",
    "sg:phone":"+33 2 98 67 00 46",
    "sg:postcode":"29660",
    "sg:province":"Bretagne",
    "wof:name":"S.d.a.b. S.a. - Soci\u00e9t\u00e9 De Distribution Et D'approvisionnement De Bretagne",
    "wof:placetype":"venue"
},
  "geometry": {"coordinates":[-3.914004,48.667179],"type":"Point"}
}