{
  "type": "Feature",
  "properties": {
    "iso:country":"FR",
    "sg:address":"53, Rue de la Libert\u00e9, 54490 Piennes",
    "sg:orig_category":"Unclassifiable Establishments",
    "sg:phone":"+33 3 82 21 90 93",
    "sg:province":"Lorraine",
    "wof:name":"P.e.b. - Piennes Electro-bobinage S.a.r.l.",
    "wof:placetype":"venue"
},
  "geometry": {"coordinates":[5.78654,49.313309],"type":"Point"}
}