{
  "type": "Feature",
  "properties": {
    "iso:country":"FR",
    "sg:address":"Rue Du Courtois Prolongee Za 41500 Menars",
    "sg:city":"Menars",
    "sg:classifiers":[
        {
            "category":"Wholesale",
            "subcategory":"Medical Equipment & Supplies",
            "type":"Manufacturing & Wholesale Goods"
        }
    ],
    "sg:phone":"+33 2 54 46 54 05",
    "sg:postcode":"41500",
    "sg:province":"Centre",
    "sg:tags":[
        "instrument",
        "health",
        "-",
        "precision"
    ],
    "wof:name":"Ste De Fab Et De Realisation D'implants Chirurgicaux (sferic)",
    "wof:placetype":"venue"
},
  "geometry": {"coordinates":[1.40691,47.63966],"type":"Point"}
}