{
  "type": "Feature",
  "properties": {
    "addr:full":"2 rue Louis Bleriot 57365 Ennery Lorraine 57365",
    "addr:housenumber":"2",
    "addr:postcode":"57365;57365",
    "addr:street":"Rue Louis Bleriot",
    "iso:country":"FR",
    "sg:address":"2 rue Louis Bleriot 57365 Ennery",
    "sg:classifiers":[
        {
            "category":"Manufacturing",
            "subcategory":"Metals",
            "type":"Manufacturing & Wholesale Goods"
        }
    ],
    "sg:phone":"+33 3 87 70 85 50",
    "sg:postcode":"57365",
    "sg:province":"Lorraine",
    "sg:tags":[
        "steel",
        "stainless",
        "aluminium",
        "container",
        "cryogenic"
    ],
    "wof:name":"Cryolor S.a.",
    "wof:placetype":"venue"
},
  "geometry": {"coordinates":[6.221613,49.22702],"type":"Point"}
}