{
  "type": "Feature",
  "properties": {
    "addr:full":"Av. Didier Daurat Blagnac Midi Pyr\u00e9n\u00e9es 31700",
    "addr:postcode":"31700",
    "addr:street":"Av. Didier Daurat",
    "iso:country":"FR",
    "sg:address":"Av. Didier Daurat",
    "sg:city":"Blagnac",
    "sg:orig_category":"Non-Classified Establishments",
    "sg:phone":"+33 5 61 30 00 94",
    "sg:postcode":"31700",
    "sg:province":"Midi Pyr\u00e9n\u00e9es",
    "wof:name":"Ch\u00e8que-d\u00e9jeuner C.c.r. S.a.",
    "wof:placetype":"venue"
},
  "geometry": {"coordinates":[1.37925,43.63031],"type":"Point"}
}