{
  "type": "Feature",
  "properties": {
    "addr:full":"28, Rue des Broucounies, 81000 Albi Midi Pyr\u00e9n\u00e9es 81000",
    "addr:housenumber":"28",
    "addr:postcode":"81000;81000",
    "addr:street":"Rue Des Broucounies",
    "iso:country":"FR",
    "sg:address":"28, Rue des Broucounies, 81000 Albi",
    "sg:orig_category":"Non-Classified Establishments",
    "sg:phone":"+33 5 63 60 74 58",
    "sg:postcode":"81000",
    "sg:province":"Midi Pyr\u00e9n\u00e9es",
    "wof:name":"Entreprise Pierre Chamayou S.a.r.l.",
    "wof:placetype":"venue"
},
  "geometry": {"coordinates":[2.14824,43.952812],"type":"Point"}
}