{
  "type": "Feature",
  "properties": {
    "addr:full":"Rue Gr\u00e9goire Nicolas Finez Valenciennes Nord Pas-de-Calais 59300",
    "addr:postcode":"59300",
    "addr:street":"Rue Gre\u0301Goire Nicolas Finez Valenciennes Nord",
    "iso:country":"FR",
    "sg:address":"Rue Gr\u00e9goire Nicolas Finez",
    "sg:city":"Valenciennes",
    "sg:orig_category":"Unclassifiable Establishments",
    "sg:phone":"+33 3 27 33 31 11",
    "sg:postcode":"59300",
    "sg:province":"Nord Pas-de-Calais",
    "wof:name":"A.f.t. I.f.t.i.m.",
    "wof:placetype":"venue"
},
  "geometry": {"coordinates":[3.480002,50.355553],"type":"Point"}
}