{
  "type": "Feature",
  "properties": {
    "iso:country":"FR",
    "sg:address":"B.P. 69, 69672 Bron C\u00e9dex^^25 bis, Rue du 35\u00e8me R\u00e9giment Aviation, 69500 Bron",
    "sg:orig_category":"Non-Classified Establishments",
    "sg:phone":"+33 4 78 26 47 47",
    "sg:province":"Rhone-Alpes",
    "wof:name":"Rh\u00e9o Mix S.a.",
    "wof:placetype":"venue"
},
  "geometry": {"coordinates":[4.9087,45.733807],"type":"Point"}
}