{
  "type": "Feature",
  "properties": {
    "iso:country":"FR",
    "sg:address":"Bd Winston Churchill",
    "sg:city":"Tours",
    "sg:orig_category":"Unclassifiable Establishments",
    "sg:phone":"+33 2 47 39 81 00",
    "sg:postcode":"37000",
    "sg:province":"Centre",
    "wof:name":"C.r.c.a.m",
    "wof:placetype":"venue"
},
  "geometry": {"coordinates":[0.68373,47.373699],"type":"Point"}
}