{
  "type": "Feature",
  "properties": {
    "iso:country":"FR",
    "sg:address":"2, Place de la Gare, 29870 Lannilis",
    "sg:city":"Lannilis",
    "sg:orig_category":"Unclassifiable Establishments",
    "sg:phone":"+33 2 98 04 01 82",
    "sg:postcode":"29870",
    "sg:province":"Bretagne",
    "wof:name":"Tretcobat S.a.",
    "wof:placetype":"venue"
},
  "geometry": {"coordinates":[-4.543331,48.507816],"type":"Point"}
}