{
  "type": "Feature",
  "properties": {
    "iso:country":"FR",
    "sg:address":"11, Bd de la Grande Thumine - B\u00e2t A - Parc Ariane, 13080 Aix en Provence",
    "sg:orig_category":"Non-Classified Establishments",
    "sg:phone":"+33 4 42 95 19 19",
    "sg:province":"Nord Pas-de-Calais",
    "wof:name":"Sygeste S.a.",
    "wof:placetype":"venue"
},
  "geometry": {"coordinates":[5.41954,43.484966],"type":"Point"}
}