{
  "type": "Feature",
  "properties": {
    "iso:country":"FR",
    "sg:address":"B.P. 96164, 57061 Metz C\u00e9dex 02^^9, Rue Teilhard de Chardin, 57000 Metz",
    "sg:orig_category":"Non-Classified Establishments",
    "sg:phone":"+33 3 87 30 54 75",
    "sg:province":"Lorraine",
    "wof:name":"Mosellane Des Eaux S.a.",
    "wof:placetype":"venue"
},
  "geometry": {"coordinates":[6.183995,49.07645],"type":"Point"}
}