{
  "type": "Feature",
  "properties": {
    "addr:full":"B.P. 24, 71170 Chauffailles^^19, Av. Jean Barraud, 71170 Chauffailles Chauffailles Bourgogne 71170",
    "addr:postcode":"71170;71170;71170",
    "addr:street":"B.P. 24;Av. Jean Barraud",
    "iso:country":"FR",
    "sg:address":"B.P. 24, 71170 Chauffailles^^19, Av. Jean Barraud, 71170 Chauffailles",
    "sg:city":"Chauffailles",
    "sg:orig_category":"Non-Classified Establishments",
    "sg:phone":"+33 3 85 26 00 73",
    "sg:postcode":"71170",
    "sg:province":"Bourgogne",
    "wof:name":"L.b.l. Brenta C.d. S.a.",
    "wof:placetype":"venue"
},
  "geometry": {"coordinates":[4.267355,46.168701],"type":"Point"}
}