{
  "type": "Feature",
  "properties": {
    "iso:country":"FR",
    "sg:address":"ZI de la Praux - Le Noyer",
    "sg:city":"Allinges",
    "sg:orig_category":"Non-Classified Establishments",
    "sg:phone":"+33 4 50 70 53 78",
    "sg:postcode":"74200",
    "sg:province":"Rhone-Alpes",
    "wof:name":"Les Carri\u00e8res D'allinges S.a.",
    "wof:placetype":"venue"
},
  "geometry": {"coordinates":[6.46468,46.335693],"type":"Point"}
}