{
  "type": "Feature",
  "properties": {
    "addr:full":"20 Rue De Frene 10390 Verrieres Champagne 10390",
    "addr:housenumber":"20",
    "addr:postcode":"10390;10390",
    "addr:street":"Rue De Frene;Champagne",
    "iso:country":"FR",
    "sg:address":"20 Rue De Frene 10390 Verrieres",
    "sg:classifiers":[
        {
            "category":"Shopping",
            "subcategory":"Crafts & Fabrics",
            "type":"Retail Goods"
        }
    ],
    "sg:phone":"+33 3 25 41 91 92",
    "sg:postcode":"10390",
    "sg:province":"Champagne",
    "sg:tags":[
        "textile",
        "clothing"
    ],
    "wof:name":"Sarl Gaellique (sarl Gaellique)",
    "wof:placetype":"venue"
},
  "geometry": {"coordinates":[4.14884,48.233826],"type":"Point"}
}