{
  "type": "Feature",
  "properties": {
    "addr:full":"62, Av. Galois, 92340 Bourg la Reine Ile de France",
    "addr:postcode":"92340",
    "addr:street":"62 Av. Galois;Ile De France",
    "iso:country":"FR",
    "sg:address":"62, Av. Galois, 92340 Bourg la Reine",
    "sg:orig_category":"Unclassifiable Establishments",
    "sg:phone":"+33 1 46 61 12 44",
    "sg:province":"Ile de France",
    "wof:name":"Le N\u00e9on Prog\u00e8s S.a.",
    "wof:placetype":"venue"
},
  "geometry": {"coordinates":[2.322575,48.776634],"type":"Point"}
}