{
  "type": "Feature",
  "properties": {
    "addr:full":"Rte du Parc Animalier Bourbonne les Bains Champagne 52400",
    "addr:postcode":"52400",
    "addr:street":"Rte Du Parc Animalier",
    "iso:country":"FR",
    "sg:address":"Rte du Parc Animalier",
    "sg:city":"Bourbonne les Bains",
    "sg:orig_category":"Non-Classified Establishments",
    "sg:phone":"+33 3 25 90 21 30",
    "sg:postcode":"52400",
    "sg:province":"Champagne",
    "wof:name":"S.k. France S.a.",
    "wof:placetype":"venue"
},
  "geometry": {"coordinates":[5.739133,47.947086],"type":"Point"}
}