{
  "type": "Feature",
  "properties": {
    "iso:country":"FR",
    "sg:address":"9 Rue Soufflot 31400 Toulouse",
    "sg:classifiers":[
        {
            "category":"Banks & Credit Unions",
            "subcategory":"Investment Brokerage",
            "type":"Services"
        }
    ],
    "sg:phone":"+33 5 61 25 78 78",
    "sg:province":"Midi Pyr\u00e9n\u00e9es",
    "sg:tags":[
        "-",
        "transport",
        "related"
    ],
    "wof:name":"Toulouse Courses Sarl",
    "wof:placetype":"venue"
},
  "geometry": {"coordinates":[1.440546,43.585522],"type":"Point"}
}