{
  "type": "Feature",
  "properties": {
    "addr:full":"Za Du Borrey 01100 Martignat Rhone-Alpes",
    "addr:postcode":"01100",
    "addr:street":"Za Du Borrey",
    "iso:country":"FR",
    "sg:address":"Za Du Borrey 01100 Martignat",
    "sg:classifiers":[
        {
            "category":"Manufacturing",
            "subcategory":"Rubber & Plastics",
            "type":"Manufacturing & Wholesale Goods"
        }
    ],
    "sg:phone":"+33 4 74 81 13 57",
    "sg:province":"Rhone-Alpes",
    "wof:name":"Tecmaplast Sa",
    "wof:placetype":"venue"
},
  "geometry": {"coordinates":[5.608977,46.208912],"type":"Point"}
}