{
  "type": "Feature",
  "properties": {
    "iso:country":"FR",
    "sg:address":"10 Rue De Grassi 33250 PAUILLAC",
    "sg:city":"Pauillac",
    "sg:classifiers":[
        {
            "category":"Wholesale",
            "subcategory":"Wine & Distilled Alcoholic Beverages",
            "type":"Manufacturing & Wholesale Goods"
        }
    ],
    "sg:phone":"+33 5 56 73 20 20",
    "sg:postcode":"33250",
    "sg:province":"Aquitaine",
    "sg:tags":[
        "french"
    ],
    "wof:name":"Baron Philippe De Rothschild Sa",
    "wof:placetype":"venue"
},
  "geometry": {"coordinates":[-0.749699,45.199478],"type":"Point"}
}