{
  "type": "Feature",
  "properties": {
    "iso:country":"FR",
    "sg:address":"Route De Chateau Chinon Lieu Dit Bellevue 71400 Autun",
    "sg:city":"Autun",
    "sg:classifiers":[
        {
            "category":"Home & Garden",
            "subcategory":"Furniture",
            "type":"Retail Goods"
        }
    ],
    "sg:phone":"+33 3 85 52 17 80",
    "sg:postcode":"71400",
    "sg:province":"Bourgogne",
    "sg:tags":[
        "wood"
    ],
    "wof:name":"Rousselin Fils Et Compagnie",
    "wof:placetype":"venue"
},
  "geometry": {"coordinates":[4.411325,46.902779],"type":"Point"}
}