{
  "type": "Feature",
  "properties": {
    "addr:full":"Rue Lavoisier - Z.I. Verneuil sur Avre Haute Normandie 27130",
    "addr:postcode":"27130",
    "addr:street":"Rue Lavoisier;Avre Haute Normandie",
    "iso:country":"FR",
    "sg:address":"Rue Lavoisier - Z.I.",
    "sg:city":"Verneuil sur Avre",
    "sg:orig_category":"Non-Classified Establishments",
    "sg:phone":"+33 2 32 32 04 38",
    "sg:postcode":"27130",
    "sg:province":"Haute Normandie",
    "wof:name":"T.d.j. S.a.r.l. - Technique De D\u00e9coupage Au Jet D'eau",
    "wof:placetype":"venue"
},
  "geometry": {"coordinates":[0.85463,48.701855],"type":"Point"}
}