{
  "type": "Feature",
  "properties": {
    "addr:full":"R NO 2 MALITORNE 18230 SAINT DOULCHARD Centre 18230",
    "addr:housenumber":"r",
    "addr:postcode":"18230;18230",
    "addr:street":"No 2 Malitorne",
    "iso:country":"FR",
    "sg:address":"R",
    "sg:city":"NO 2 MALITORNE 18230 SAINT DOULCHARD",
    "sg:classifiers":[
        {
            "category":"Manufacturing",
            "subcategory":"Motor Vehicles & Parts",
            "type":"Manufacturing & Wholesale Goods"
        }
    ],
    "sg:phone":"+33 2 48 24 09 70",
    "sg:postcode":"18230",
    "sg:province":"Centre",
    "sg:tags":[
        "engine",
        "machine",
        "engineering",
        "-",
        "mechanical"
    ],
    "wof:name":"Berry Radiateurs",
    "wof:placetype":"venue"
},
  "geometry": {"coordinates":[2.35792,47.104084],"type":"Point"}
}