{
  "type": "Feature",
  "properties": {
    "addr:full":"12 Rue De L'Horloge 30000 N\u00eemes Languedoc-Roussillon 30000",
    "addr:housenumber":"12",
    "addr:postcode":"30000;30000",
    "addr:street":"Rue De L'Horloge",
    "iso:country":"FR",
    "sg:address":"12 Rue De L'Horloge 30000 N\u00eemes",
    "sg:classifiers":[
        {
            "category":"Shopping",
            "subcategory":"Luggage & Leather Goods",
            "type":"Retail Goods"
        }
    ],
    "sg:phone":"+33 4 66 67 01 62",
    "sg:postcode":"30000",
    "sg:province":"Languedoc-Roussillon",
    "sg:tags":[
        "shoe"
    ],
    "wof:name":"Ets Gauffres Claud",
    "wof:placetype":"venue"
},
  "geometry": {"coordinates":[4.356439,43.837845],"type":"Point"}
}