{
  "type": "Feature",
  "properties": {
    "addr:full":"40 Grande Rue 77114 Villiers Sur Seine Ile de France",
    "addr:housenumber":"40",
    "addr:postcode":"77114",
    "addr:street":"Grande Rue",
    "iso:country":"FR",
    "sg:address":"40 Grande Rue 77114 Villiers Sur Seine",
    "sg:classifiers":[
        {
            "category":"Home & Garden",
            "subcategory":"Furniture",
            "type":"Retail Goods"
        }
    ],
    "sg:phone":"+33 1 64 01 86 75",
    "sg:province":"Ile de France",
    "sg:tags":[
        "wood"
    ],
    "wof:name":"Etablissements Garnier Bernard",
    "wof:placetype":"venue"
},
  "geometry": {"coordinates":[3.379531,48.453762],"type":"Point"}
}