{
  "type": "Feature",
  "properties": {
    "addr:full":"12, Bd de Chinon, 37300 Jou\u00e9 l\u00e8s Tours Jou\u00e9-l\u00e8s-Tours Centre 37300",
    "addr:housenumber":"12",
    "addr:postcode":"37300;37300",
    "addr:street":"Bd De Chinon",
    "iso:country":"FR",
    "sg:address":"12, Bd de Chinon, 37300 Jou\u00e9 l\u00e8s Tours",
    "sg:city":"Jou\u00e9-l\u00e8s-Tours",
    "sg:orig_category":"Non-Classified Establishments",
    "sg:phone":"+33 2 47 25 00 42",
    "sg:postcode":"37300",
    "sg:province":"Centre",
    "wof:name":"Amats S.a.",
    "wof:placetype":"venue"
},
  "geometry": {"coordinates":[0.696907,47.354931],"type":"Point"}
}