{
  "type": "Feature",
  "properties": {
    "addr:full":"288bis, Rue de Clermont, 60000 Beauvais Picardie",
    "addr:housenumber":"288bis",
    "addr:postcode":"60000",
    "addr:street":"Rue De Clermont",
    "iso:country":"FR",
    "sg:address":"288bis, Rue de Clermont, 60000 Beauvais",
    "sg:orig_category":"Unclassifiable Establishments",
    "sg:phone":"+33 3 44 05 87 87",
    "sg:province":"Picardie",
    "wof:name":"Sin & Stes S.a.",
    "wof:placetype":"venue"
},
  "geometry": {"coordinates":[2.115958,49.429859],"type":"Point"}
}