{
  "type": "Feature",
  "properties": {
    "iso:country":"FR",
    "sg:address":"29, Rue du Dix Neuf Mars 1962, 81300 Graulhet",
    "sg:orig_category":"Unclassifiable Establishments",
    "sg:phone":"+33 5 63 34 63 74",
    "sg:province":"Midi Pyr\u00e9n\u00e9es",
    "wof:name":"La Sac Co S.a.r.l.",
    "wof:placetype":"venue"
},
  "geometry": {"coordinates":[1.982072,43.761406],"type":"Point"}
}