{
  "type": "Feature",
  "properties": {
    "iso:country":"FR",
    "sg:address":"79 rue des Martyrs; Meru; 60110",
    "sg:classifiers":[
        {
            "category":"Banks & Credit Unions",
            "subcategory":"Bank",
            "type":"Services"
        }
    ],
    "sg:phone":"+33 3344223622",
    "sg:postcode":"60110",
    "sg:province":"Picardie",
    "wof:name":"Soci\u00e9t\u00e9 G\u00e9n\u00e9rale",
    "wof:placetype":"venue"
},
  "geometry": {"coordinates":[2.135155,49.235676],"type":"Point"}
}