{
  "type": "Feature",
  "properties": {
    "addr:full":"B.P. 15, 45130 Baule C\u00e9dex^^ZA les Bredanes, 45130 Baule Baule Centre 45130",
    "addr:housenumber":"baule",
    "addr:postcode":"45130;45130;45130",
    "addr:street":"B.P. 15",
    "iso:country":"FR",
    "sg:address":"B.P. 15, 45130 Baule C\u00e9dex^^ZA les Bredanes, 45130 Baule",
    "sg:city":"Baule",
    "sg:orig_category":"Non-Classified Establishments",
    "sg:phone":"+33 2 38 45 00 70",
    "sg:postcode":"45130",
    "sg:province":"Centre",
    "wof:name":"M.d.e. S.a.",
    "wof:placetype":"venue"
},
  "geometry": {"coordinates":[1.671607,47.811596],"type":"Point"}
}