{
  "type": "Feature",
  "properties": {
    "addr:full":"2 Rue Anne De Bretagne 44360 Vigneux De Bretagne Pays de Loire",
    "addr:housenumber":"2",
    "addr:postcode":"44360;pays",
    "addr:street":"Rue Anne De Bretagne",
    "iso:country":"FR",
    "sg:address":"2 Rue Anne De Bretagne 44360 Vigneux De Bretagne",
    "sg:classifiers":[
        {
            "category":"Manufacturing",
            "subcategory":"Printing",
            "type":"Manufacturing & Wholesale Goods"
        }
    ],
    "sg:phone":"+33 2 40 57 36 69",
    "sg:province":"Pays de Loire",
    "sg:tags":[
        "publishing"
    ],
    "wof:name":"Vanden Sa",
    "wof:placetype":"venue"
},
  "geometry": {"coordinates":[-1.697428,47.334473],"type":"Point"}
}