{
  "type": "Feature",
  "properties": {
    "addr:full":"21 Av De La Coop\u00e9ration 86200 Loudun Poitou-Charentes 86200",
    "addr:postcode":"86200;86200",
    "addr:street":"21 Av De La Coope\u0301Ration",
    "iso:country":"FR",
    "sg:address":"21 Av De La Coop\u00e9ration 86200 Loudun",
    "sg:classifiers":[
        {
            "category":"Farming",
            "subcategory":"Livestock Farm",
            "type":"Manufacturing & Wholesale Goods"
        }
    ],
    "sg:phone":"+33 5 49 98 18 40",
    "sg:postcode":"86200",
    "sg:province":"Poitou-Charentes",
    "sg:tags":[
        "breeding",
        "agriculture",
        "animal"
    ],
    "wof:name":"Howard Sa",
    "wof:placetype":"venue"
},
  "geometry": {"coordinates":[0.084906,47.017509],"type":"Point"}
}