{
  "type": "Feature",
  "properties": {
    "addr:full":"B.P. 4, 62710 Courri\u00e8res^^Rue Raoul Briquet - ZAL du Fond du Val, 62710 Courri\u00e8res Nord Pas-de-Calais",
    "addr:housenumber":"4",
    "addr:postcode":"62710;62710",
    "addr:street":"B.P.;Raoul Briquet Zal Du Fond Du Val",
    "iso:country":"FR",
    "sg:address":"B.P. 4, 62710 Courri\u00e8res^^Rue Raoul Briquet - ZAL du Fond du Val, 62710 Courri\u00e8res",
    "sg:orig_category":"Non-Classified Establishments",
    "sg:phone":"+33 3 21 75 01 09",
    "sg:province":"Nord Pas-de-Calais",
    "wof:name":"V\u00e9ralu France S.a.",
    "wof:placetype":"venue"
},
  "geometry": {"coordinates":[2.947573,50.458054],"type":"Point"}
}