{
  "type": "Feature",
  "properties": {
    "addr:full":"ZA Les Pradeaux 13850 GREASQUE Provence-Alpes-C\u00f4te d'Azur",
    "addr:postcode":"13850",
    "addr:street":"Za Les Pradeaux;Greasque",
    "iso:country":"FR",
    "sg:address":"ZA Les Pradeaux 13850 GREASQUE",
    "sg:classifiers":[
        {
            "category":"Train Station",
            "subcategory":"Light Rail",
            "type":"Transportation"
        }
    ],
    "sg:phone":"+33 4 42 69 86 40",
    "sg:province":"Provence-Alpes-C\u00f4te d'Azur",
    "sg:tags":[
        "sensor"
    ],
    "wof:name":"Chromasys S.a.",
    "wof:placetype":"venue"
},
  "geometry": {"coordinates":[5.541299,43.434277],"type":"Point"}
}