{
  "type": "Feature",
  "properties": {
    "addr:full":"46 bis, Rue des Hauts Pav\u00e9s, 44000 Nantes Pays de Loire",
    "addr:housenumber":"46 bis",
    "addr:postcode":"44000",
    "addr:street":"Rue Des Hauts Pave\u0301S",
    "iso:country":"FR",
    "sg:address":"46 bis, Rue des Hauts Pav\u00e9s, 44000 Nantes",
    "sg:orig_category":"Unclassifiable Establishments",
    "sg:phone":"+33 2 40 20 21 22",
    "sg:province":"Pays de Loire",
    "wof:name":"Exco Atlantique S.a.",
    "wof:placetype":"venue"
},
  "geometry": {"coordinates":[-1.565539,47.224945],"type":"Point"}
}