{
  "type": "Feature",
  "properties": {
    "iso:country":"FR",
    "sg:address":"25, Av. Jean Moulin, 71700 Tournus",
    "sg:city":"Tournus",
    "sg:orig_category":"Unclassifiable Establishments",
    "sg:phone":"+33 3 85 40 47 40",
    "sg:postcode":"71700",
    "sg:province":"Bourgogne",
    "wof:name":"Tournus Equipement S.a.",
    "wof:placetype":"venue"
},
  "geometry": {"coordinates":[4.902198,46.568256],"type":"Point"}
}