{
  "type": "Feature",
  "properties": {
    "addr:full":"6 R De Madagascar Num Voie 6 A 8 75012 Paris Ile de France 75012",
    "addr:housenumber":"6;num;6 a 8",
    "addr:postcode":"75012;75012",
    "addr:street":"R De Madagascar;Voie",
    "iso:country":"FR",
    "sg:address":"6 R De Madagascar Num Voie 6 A 8 75012 Paris",
    "sg:classifiers":[
        {
            "category":"Wholesale",
            "subcategory":"Medical Equipment & Supplies",
            "type":"Manufacturing & Wholesale Goods"
        }
    ],
    "sg:phone":"+33 1 43 44 35 04",
    "sg:postcode":"75012",
    "sg:province":"Ile de France",
    "sg:tags":[
        "instrument",
        "health",
        "-",
        "precision"
    ],
    "wof:name":"M. Fellous Devy",
    "wof:placetype":"venue"
},
  "geometry": {"coordinates":[2.389295,48.841045],"type":"Point"}
}