{
  "type": "Feature",
  "properties": {
    "addr:full":"105, Grande Rue, 89113 Fleury la Vall\u00e9e Branches Bourgogne 89113",
    "addr:housenumber":"105",
    "addr:postcode":"89113;89113",
    "addr:street":"Grande Rue;Valle\u0301E;Bourgogne",
    "iso:country":"FR",
    "sg:address":"105, Grande Rue, 89113 Fleury la Vall\u00e9e",
    "sg:city":"Branches",
    "sg:orig_category":"Unclassifiable Establishments",
    "sg:phone":"+33 3 86 73 71 33",
    "sg:postcode":"89113",
    "sg:province":"Bourgogne",
    "wof:name":"Moissonnier S.a.",
    "wof:placetype":"venue"
},
  "geometry": {"coordinates":[3.448245,47.866413],"type":"Point"}
}