{
  "type": "Feature",
  "properties": {
    "addr:full":"201 Rue Nationale 49300 Cholet Pays de Loire 49300",
    "addr:housenumber":"201",
    "addr:postcode":"49300;49300",
    "addr:street":"Rue Nationale",
    "iso:country":"FR",
    "sg:address":"201 Rue Nationale 49300 Cholet",
    "sg:classifiers":[
        {
            "category":"Professional",
            "subcategory":"Advertising",
            "type":"Services"
        }
    ],
    "sg:phone":"+33 2 41 49 02 00",
    "sg:postcode":"49300",
    "sg:province":"Pays de Loire",
    "sg:tags":[
        "communication",
        "medium"
    ],
    "wof:name":"Lithographic Sarl",
    "wof:placetype":"venue"
},
  "geometry": {"coordinates":[-0.885423,47.061642],"type":"Point"}
}