{
  "type": "Feature",
  "properties": {
    "iso:country":"FR",
    "sg:address":"39, Av. Roger Salengro, 69100 Villeurbanne",
    "sg:orig_category":"Non-Classified Establishments",
    "sg:phone":"+33 4 78 93 78 59",
    "sg:postcode":"69100",
    "sg:province":"Rhone-Alpes",
    "wof:name":"T.s.l. S.a. - Technique Service Loyon",
    "wof:placetype":"venue"
},
  "geometry": {"coordinates":[4.871567,45.776318],"type":"Point"}
}