{
  "type": "Feature",
  "properties": {
    "addr:full":"213, Rue du Bois, 59200 Tourcoing Nord Pas-de-Calais",
    "addr:housenumber":"213",
    "addr:postcode":"59200",
    "addr:street":"Rue Du Bois",
    "iso:country":"FR",
    "sg:address":"213, Rue du Bois, 59200 Tourcoing",
    "sg:orig_category":"Unclassifiable Establishments",
    "sg:phone":"+33 3 20 36 06 47",
    "sg:province":"Nord Pas-de-Calais",
    "wof:name":"Sa D'exploitation Des Etablissements Janssoone S.a.",
    "wof:placetype":"venue"
},
  "geometry": {"coordinates":[3.140699,50.72065],"type":"Point"}
}