{
  "type": "Feature",
  "properties": {
    "addr:full":"La Clairciere Rd 734 St Pierre D Oleron Poitou-Charentes 17310",
    "addr:postcode":"17310",
    "addr:street":"Clairciere Rd 734 St Pierre D Oleron",
    "iso:country":"FR",
    "sg:address":"La Clairciere Rd 734",
    "sg:city":"St Pierre D Oleron",
    "sg:classifiers":[
        {
            "category":"Banks & Credit Unions",
            "subcategory":"Financial Services",
            "type":"Services"
        }
    ],
    "sg:phone":"+33 5 46 76 50 04",
    "sg:postcode":"17310",
    "sg:province":"Poitou-Charentes",
    "sg:tags":[
        "banking",
        "finance",
        "insurance"
    ],
    "wof:name":"Societe Fiduciaire Nationale D'expertise Comptable Fidexpert (fid)",
    "wof:placetype":"venue"
},
  "geometry": {"coordinates":[-1.309064,45.937641],"type":"Point"}
}