{
  "type": "Feature",
  "properties": {
    "iso:country":"FR",
    "sg:address":"41, Rue Saint Martin, 60310 Roye sur Matz",
    "sg:orig_category":"Unclassifiable Establishments",
    "sg:phone":"+33 3 44 43 07 00",
    "sg:province":"Picardie",
    "wof:name":"Sotep S.a.",
    "wof:placetype":"venue"
},
  "geometry": {"coordinates":[2.78429,49.59367],"type":"Point"}
}