{
  "type": "Feature",
  "properties": {
    "iso:country":"FR",
    "sg:address":"14 Av De L' Abattoir 87000 Limoges",
    "sg:classifiers":[
        {
            "category":"Manufacturing",
            "subcategory":"Glass & Minerals",
            "type":"Manufacturing & Wholesale Goods"
        }
    ],
    "sg:phone":"+33 5 55 30 12 15",
    "sg:postcode":"87000",
    "sg:province":"Limousin",
    "sg:tags":[
        "building",
        "ceramic",
        "material",
        "-",
        "machine",
        "engineering",
        "mechanical"
    ],
    "wof:name":"La Bovida",
    "wof:placetype":"venue"
},
  "geometry": {"coordinates":[1.258731,45.811329],"type":"Point"}
}