{
  "type": "Feature",
  "properties": {
    "addr:full":"14 Euler 33700 M\u00e9rignac M\u00e9rignac Aquitaine 33700",
    "addr:housenumber":"14",
    "addr:postcode":"33700;33700",
    "addr:street":"Euler",
    "iso:country":"FR",
    "sg:address":"14 Euler 33700 M\u00e9rignac",
    "sg:city":"M\u00e9rignac",
    "sg:classifiers":[
        {
            "category":"Professional",
            "subcategory":"Engineering",
            "type":"Services"
        }
    ],
    "sg:phone":"+33 5 56 55 93 63",
    "sg:postcode":"33700",
    "sg:province":"Aquitaine",
    "sg:tags":[
        "machine",
        "-",
        "mechanical"
    ],
    "wof:name":"Wesper Sa",
    "wof:placetype":"venue"
},
  "geometry": {"coordinates":[-0.673335,44.832554],"type":"Point"}
}