{
  "type": "Feature",
  "properties": {
    "addr:full":"4 R Sib\u00e9lius 76410 Sotteville Sous Le Val Haute Normandie",
    "addr:housenumber":"4",
    "addr:postcode":"76410",
    "addr:street":"R Sibe\u0301Lius;Sous Le Val Haute Normandie",
    "iso:country":"FR",
    "sg:address":"4 R Sib\u00e9lius 76410 Sotteville Sous Le Val",
    "sg:classifiers":[
        {
            "category":"Manufacturing",
            "subcategory":"Rubber & Plastics",
            "type":"Manufacturing & Wholesale Goods"
        }
    ],
    "sg:phone":"+33 2 32 96 07 47",
    "sg:province":"Haute Normandie",
    "wof:name":"Pvg France Sarl",
    "wof:placetype":"venue"
},
  "geometry": {"coordinates":[1.116975,49.324394],"type":"Point"}
}