{
  "type": "Feature",
  "properties": {
    "addr:full":"142, Av. de Verdun - Le Plein Sud, 06700 Saint Laurent du Var Provence-Alpes-C\u00f4te d'Azur",
    "addr:postcode":"06700",
    "addr:street":"142 Av. De Verdun Le Plein Sud;Var",
    "iso:country":"FR",
    "sg:address":"142, Av. de Verdun - Le Plein Sud, 06700 Saint Laurent du Var",
    "sg:orig_category":"Unclassifiable Establishments",
    "sg:phone":"+33 4 93 31 10 11",
    "sg:province":"Provence-Alpes-C\u00f4te d'Azur",
    "wof:name":"Sud Conseil Audit S.a.r.l.",
    "wof:placetype":"venue"
},
  "geometry": {"coordinates":[7.18804,43.678242],"type":"Point"}
}