{
  "type": "Feature",
  "properties": {
    "addr:full":"Zi Fernand L\u00e9ger 18400 St Florent Sur Cher Centre 18400",
    "addr:housenumber":"18400;cher",
    "addr:postcode":"18400",
    "addr:street":"St Florent Sur",
    "iso:country":"FR",
    "sg:address":"Zi",
    "sg:city":"Fernand L\u00e9ger 18400 St Florent Sur Cher",
    "sg:classifiers":[
        {
            "category":"Building & Trades",
            "subcategory":"Electrical",
            "type":"Services"
        }
    ],
    "sg:phone":"+33 2 48 23 17 37",
    "sg:postcode":"18400",
    "sg:province":"Centre",
    "sg:tags":[
        "electronic",
        "lighting",
        "equipment"
    ],
    "wof:name":"Comatelec Sa",
    "wof:placetype":"venue"
},
  "geometry": {"coordinates":[2.244945,46.992325],"type":"Point"}
}