{
  "type": "Feature",
  "properties": {
    "iso:country":"FR",
    "sg:address":"La Boisni\u00e8re 37110 Villed\u00e9mer",
    "sg:city":"Autr\u00e8che",
    "sg:classifiers":[
        {
            "category":"Professional",
            "subcategory":"Business Services",
            "type":"Services"
        }
    ],
    "sg:phone":"+33 2 47 55 46 55",
    "sg:postcode":"37110",
    "sg:province":"Centre",
    "sg:tags":[
        "body",
        "advice"
    ],
    "wof:name":"Association La Boisniere",
    "wof:placetype":"venue"
},
  "geometry": {"coordinates":[0.99705,47.524975],"type":"Point"}
}