{
  "type": "Feature",
  "properties": {
    "addr:full":"B.P. 137, 59590 Raismes^^Rue du Commerce - ZA du Plouich, 59590 Raismes Nord Pas-de-Calais 59590",
    "addr:housenumber":"b.p. 137",
    "addr:postcode":"59590;59590;59590",
    "addr:street":"Du Commerce Za Du Plouich",
    "iso:country":"FR",
    "sg:address":"B.P. 137, 59590 Raismes^^Rue du Commerce - ZA du Plouich, 59590 Raismes",
    "sg:orig_category":"Non-Classified Establishments",
    "sg:phone":"+33 3 27 45 81 45",
    "sg:postcode":"59590",
    "sg:province":"Nord Pas-de-Calais",
    "wof:name":"C.i.m.e. S.a.",
    "wof:placetype":"venue"
},
  "geometry": {"coordinates":[3.483329,50.392513],"type":"Point"}
}