{
  "type": "Feature",
  "properties": {
    "iso:country":"FR",
    "sg:address":"11, RN, 45380 La Chapelle Saint Mesmin",
    "sg:city":"La Chapelle-Saint-Mesmin",
    "sg:orig_category":"Unclassifiable Establishments",
    "sg:phone":"+33 2 38 72 03 30",
    "sg:postcode":"45380",
    "sg:province":"Centre",
    "wof:name":"Le Rayon Vert S.a.r.l.",
    "wof:placetype":"venue"
},
  "geometry": {"coordinates":[1.83682,47.889439],"type":"Point"}
}