{
  "type": "Feature",
  "properties": {
    "iso:country":"FR",
    "sg:address":"3 Place De La Halle",
    "sg:city":"Valen\u00e7ay",
    "sg:classifiers":[
        {
            "category":"Banks & Credit Unions",
            "subcategory":"Financial Services",
            "type":"Services"
        }
    ],
    "sg:phone":"+33 2 54 00 00 10",
    "sg:postcode":"36600",
    "sg:province":"Centre",
    "sg:tags":[
        "banking",
        "finance",
        "insurance"
    ],
    "wof:name":"Cogep Groupe D'experts Comptables Et De Commissaires Au",
    "wof:placetype":"venue"
},
  "geometry": {"coordinates":[1.567327,47.16048],"type":"Point"}
}