{
  "type": "Feature",
  "properties": {
    "iso:country":"FR",
    "sg:address":"Immeuble Salorges 1 15, quai Ernest Renaud",
    "sg:city":"Nantes",
    "sg:classifiers":[
        {
            "category":"Professional",
            "subcategory":"Computer Services",
            "type":"Services"
        }
    ],
    "sg:postcode":"44100",
    "sg:website":"http://www.linkbynet.com",
    "wof:name":"LINKBYNET",
    "wof:placetype":"venue"
},
  "geometry": {"coordinates":[-1.575263,47.204519],"type":"Point"}
}