{
  "type": "Feature",
  "properties": {
    "iso:country":"FR",
    "sg:address":"24 rue Th\u00e9ophraste Renaudot 17000 La Rochelle",
    "sg:classifiers":[
        {
            "category":"Manufacturing",
            "subcategory":"Motor Vehicles & Parts",
            "type":"Manufacturing & Wholesale Goods"
        }
    ],
    "sg:phone":"+33 5 46 34 10 81",
    "sg:province":"Poitou-Charentes",
    "sg:tags":[
        "industry",
        "metallurgical",
        "spare"
    ],
    "wof:name":"Framex Supply S.a.r.l.",
    "wof:placetype":"venue"
},
  "geometry": {"coordinates":[-1.161688,46.157787],"type":"Point"}
}