{
  "type": "Feature",
  "properties": {
    "addr:full":"Rte de Jallais-Beaullieu Beaupr\u00e9au Pays de Loire 49600",
    "addr:postcode":"49600",
    "addr:street":"Rte De Jallais-Beaullieu",
    "iso:country":"FR",
    "sg:address":"Rte de Jallais-Beaullieu",
    "sg:city":"Beaupr\u00e9au",
    "sg:orig_category":"Non-Classified Establishments",
    "sg:phone":"+33 2 41 63 01 93",
    "sg:postcode":"49600",
    "sg:province":"Pays de Loire",
    "wof:name":"Etablissements Goubaud S.a.r.l.",
    "wof:placetype":"venue"
},
  "geometry": {"coordinates":[-1.017466,47.151772],"type":"Point"}
}