{
  "type": "Feature",
  "properties": {
    "addr:full":"Chaintre 49400 Saumur Pays de Loire 49400",
    "addr:postcode":"49400;49400",
    "addr:street":"Chaintre",
    "iso:country":"FR",
    "sg:address":"Chaintre 49400 Saumur",
    "sg:classifiers":[
        {
            "category":"Food Court",
            "type":"Food & Drink"
        }
    ],
    "sg:phone":"+33 2 41 52 90 84",
    "sg:postcode":"49400",
    "sg:province":"Pays de Loire",
    "sg:tags":[
        "product",
        "related"
    ],
    "wof:name":"Sa Filliatreau",
    "wof:placetype":"venue"
},
  "geometry": {"coordinates":[-0.067394,47.240826],"type":"Point"}
}