{
  "type": "Feature",
  "properties": {
    "addr:full":"55 rue Raspail Levallois Perret Cedex 92300 ",
    "addr:housenumber":"55",
    "addr:postcode":"92300",
    "addr:street":"Rue Raspail",
    "iso:country":"FR",
    "sg:address":"55 rue Raspail",
    "sg:city":"Levallois Perret Cedex",
    "sg:classifiers":[
        {
            "category":"Professional",
            "subcategory":"Computer Services",
            "type":"Services"
        }
    ],
    "sg:postcode":"92300 ",
    "sg:website":"http://www.neocasesoftware.com/",
    "wof:name":"Neocase Software ",
    "wof:placetype":"venue"
},
  "geometry": {"coordinates":[2.29128,48.898648],"type":"Point"}
}