{
  "type": "Feature",
  "properties": {
    "iso:country":"FR",
    "sg:address":"Ch\u00e2teau la Rose Cotes Rol 33330 Saint Emilion",
    "sg:city":"Saint-\u00c9tienne-de-Lisse",
    "sg:orig_category":"Non-Classified Establishments",
    "sg:phone":"+33 5 57 24 71 28",
    "sg:postcode":"33330",
    "sg:province":"Aquitaine",
    "wof:name":"Vignobles Mirande S.c.e.a. - Ch\u00e2teau La Rose Cotes Rol",
    "wof:placetype":"venue"
},
  "geometry": {"coordinates":[-0.148079,44.848289],"type":"Point"}
}