{
  "type": "Feature",
  "properties": {
    "addr:full":"10 Impasse Ruby 38500 Voiron Rhone-Alpes 38500",
    "addr:housenumber":"10",
    "addr:postcode":"38500;38500",
    "addr:street":"Impasse Ruby",
    "iso:country":"FR",
    "sg:address":"10 Impasse Ruby 38500 Voiron",
    "sg:classifiers":[
        {
            "category":"Professional",
            "subcategory":"Engineering",
            "type":"Services"
        }
    ],
    "sg:phone":"+33 4 76 93 04 21",
    "sg:postcode":"38500",
    "sg:province":"Rhone-Alpes",
    "sg:tags":[
        "machine",
        "-",
        "mechanical"
    ],
    "wof:name":"Concepts De Prefab Pour Le Batiment (cpba)",
    "wof:placetype":"venue"
},
  "geometry": {"coordinates":[5.590512,45.351078],"type":"Point"}
}