{
  "type": "Feature",
  "properties": {
    "iso:country":"FR",
    "sg:address":"rue des Terrasses 74961 CRAN GEVRIER CEDEX",
    "sg:classifiers":[
        {
            "category":"Manufacturing",
            "subcategory":"Tools & Machinery",
            "type":"Manufacturing & Wholesale Goods"
        }
    ],
    "sg:phone":"+33 4 50 46 59 00",
    "sg:province":"Rhone-Alpes",
    "sg:tags":[
        "packaging",
        "industry",
        "cosmetic"
    ],
    "wof:name":"Rexam Reboul Sa",
    "wof:placetype":"venue"
},
  "geometry": {"coordinates":[6.10581,45.914009],"type":"Point"}
}