{
  "type": "Feature",
  "properties": {
    "addr:full":"B.P. 43, 28110 Luc\u00e9 C\u00e9dex^^59, Rue du Mar\u00e9chal Leclerc, 28110 Luc\u00e9 Luc\u00e9 Centre 28110",
    "addr:postcode":"28110;28110;28110",
    "addr:street":"B.P. 43;Rue Du Mare\u0301Chal Leclerc",
    "iso:country":"FR",
    "sg:address":"B.P. 43, 28110 Luc\u00e9 C\u00e9dex^^59, Rue du Mar\u00e9chal Leclerc, 28110 Luc\u00e9",
    "sg:city":"Luc\u00e9",
    "sg:orig_category":"Non-Classified Establishments",
    "sg:phone":"+33 2 37 34 44 44",
    "sg:postcode":"28110",
    "sg:province":"Centre",
    "wof:name":"A.g.s. S\u00e9curit\u00e9 S.a.",
    "wof:placetype":"venue"
},
  "geometry": {"coordinates":[1.467334,48.440228],"type":"Point"}
}