{
  "type": "Feature",
  "properties": {
    "iso:country":"FR",
    "sg:address":"ZI la Feuillouse",
    "sg:city":"Varennes sur Allier",
    "sg:orig_category":"Unclassifiable Establishments",
    "sg:phone":"+33 4 70 48 48 48",
    "sg:postcode":"03150",
    "sg:province":"Auvergne",
    "wof:name":"Wavin S.a.",
    "wof:placetype":"venue"
},
  "geometry": {"coordinates":[3.405165,46.312134],"type":"Point"}
}