{
  "type": "Feature",
  "properties": {
    "addr:full":"8 Pl De L'Ancienne Mairie 53600 Evron Pays de Loire 53600",
    "addr:housenumber":"8",
    "addr:postcode":"53600;53600",
    "addr:street":"Pl De L'Ancienne Mairie;Evron",
    "iso:country":"FR",
    "sg:address":"8 Pl De L'Ancienne Mairie 53600 Evron",
    "sg:classifiers":[
        {
            "category":"Banks & Credit Unions",
            "subcategory":"Financial Services",
            "type":"Services"
        }
    ],
    "sg:phone":"+33 2 43 01 96 52",
    "sg:postcode":"53600",
    "sg:province":"Pays de Loire",
    "sg:tags":[
        "banking",
        "finance",
        "insurance"
    ],
    "wof:name":"Cecoma",
    "wof:placetype":"venue"
},
  "geometry": {"coordinates":[-0.37095,48.167809],"type":"Point"}
}