{
  "type": "Feature",
  "properties": {
    "addr:full":"71 Rue De Rennes 75006 Paris Ile de France 75006",
    "addr:housenumber":"71",
    "addr:postcode":"75006;75006",
    "addr:street":"Rue De Rennes",
    "iso:country":"FR",
    "sg:address":"71 Rue De Rennes 75006 Paris",
    "sg:classifiers":[
        {
            "category":"Shopping",
            "subcategory":"Clothing, Apparel, & Fashions",
            "type":"Retail Goods"
        }
    ],
    "sg:phone":"+33 1 42 22 40 27",
    "sg:postcode":"75006",
    "sg:province":"Ile de France",
    "sg:tags":[
        "textile",
        "clothing",
        "clothes"
    ],
    "wof:name":"Biche De Bere",
    "wof:placetype":"venue"
},
  "geometry": {"coordinates":[2.330925,48.851135],"type":"Point"}
}