{
  "type": "Feature",
  "properties": {
    "addr:full":"RN 446 Le Mee sur Seine Ile de France 77350",
    "addr:postcode":"77350",
    "addr:street":"Rn 446 Le Mee;Seine;France",
    "iso:country":"FR",
    "sg:address":"RN 446",
    "sg:city":"Le Mee sur Seine",
    "sg:orig_category":"Unclassifiable Establishments",
    "sg:phone":"+33 1 60 68 71 90",
    "sg:postcode":"77350",
    "sg:province":"Ile de France",
    "wof:name":"Sacar S.a.",
    "wof:placetype":"venue"
},
  "geometry": {"coordinates":[2.63157,48.542267],"type":"Point"}
}