{
  "type": "Feature",
  "properties": {
    "addr:full":"53, Rue Louis Braille, 42230 Roche la Moli\u00e8re Rhone-Alpes",
    "addr:housenumber":"53",
    "addr:postcode":"42230",
    "addr:street":"Rue Louis Braille",
    "iso:country":"FR",
    "sg:address":"53, Rue Louis Braille, 42230 Roche la Moli\u00e8re",
    "sg:orig_category":"Unclassifiable Establishments",
    "sg:phone":"+33 4 77 90 58 28",
    "sg:province":"Rhone-Alpes",
    "wof:name":"Transports Flouret S.a.r.l.",
    "wof:placetype":"venue"
},
  "geometry": {"coordinates":[4.305266,45.414803],"type":"Point"}
}