{
  "type": "Feature",
  "properties": {
    "addr:full":"Tignat 01580 Izernore Rhone-Alpes 01580",
    "addr:postcode":"01580;01580",
    "addr:street":"Tignat;Rhone-Alpes",
    "iso:country":"FR",
    "sg:address":"Tignat 01580 Izernore",
    "sg:orig_category":"Unclassifiable Establishments",
    "sg:phone":"+33 4 74 76 94 24",
    "sg:postcode":"01580",
    "sg:province":"Rhone-Alpes",
    "wof:name":"Entreprise Vincent Raymond",
    "wof:placetype":"venue"
},
  "geometry": {"coordinates":[5.567009,46.218571],"type":"Point"}
}