{
  "type": "Feature",
  "properties": {
    "addr:full":"10, Rte de Miss\u00e9, 79100 Saint Jean de Thouars Poitou-Charentes",
    "addr:housenumber":"10",
    "addr:postcode":"79100",
    "addr:street":"Rte De Misse\u0301",
    "iso:country":"FR",
    "sg:address":"10, Rte de Miss\u00e9, 79100 Saint Jean de Thouars",
    "sg:orig_category":"Non-Classified Establishments",
    "sg:phone":"+33 5 49 67 89 13",
    "sg:province":"Poitou-Charentes",
    "wof:name":"Translucia S.a.r.l.",
    "wof:placetype":"venue"
},
  "geometry": {"coordinates":[-0.200641,47.044006],"type":"Point"}
}