{
  "type": "Feature",
  "properties": {
    "addr:full":"Pont de Couze 24150 Couze et Saint Front Bayac Aquitaine 24150",
    "addr:postcode":"24150;24150",
    "addr:street":"Pont;Saint Front",
    "iso:country":"FR",
    "sg:address":"Pont de Couze 24150 Couze et Saint Front",
    "sg:city":"Bayac",
    "sg:orig_category":"Unclassifiable Establishments",
    "sg:phone":"+33 5 53 63 80 80",
    "sg:postcode":"24150",
    "sg:province":"Aquitaine",
    "wof:name":"Polyrey S.a.s.",
    "wof:placetype":"venue"
},
  "geometry": {"coordinates":[0.728799,44.804478],"type":"Point"}
}