{
  "type": "Feature",
  "properties": {
    "addr:full":"16 Rue Bruyere 51190 Grauves Champagne 51190",
    "addr:housenumber":"16",
    "addr:postcode":"51190;51190",
    "addr:street":"Rue Bruyere;Champagne",
    "iso:country":"FR",
    "sg:address":"16 Rue Bruyere 51190 Grauves",
    "sg:classifiers":[
        {
            "category":"Food Court",
            "type":"Food & Drink"
        }
    ],
    "sg:phone":"+33 3 26 59 71 31",
    "sg:postcode":"51190",
    "sg:province":"Champagne",
    "sg:tags":[
        "product",
        "related"
    ],
    "wof:name":"Champagne Mathieu Princet",
    "wof:placetype":"venue"
},
  "geometry": {"coordinates":[3.96512,48.97324],"type":"Point"}
}