{
  "type": "Feature",
  "properties": {
    "addr:full":"33640 PORTETS Portets Aquitaine 33640",
    "addr:postcode":"33640;33640",
    "iso:country":"FR",
    "sg:address":"33640 PORTETS",
    "sg:city":"Portets",
    "sg:classifiers":[
        {
            "category":"Wholesale",
            "subcategory":"Wine & Distilled Alcoholic Beverages",
            "type":"Manufacturing & Wholesale Goods"
        }
    ],
    "sg:phone":"+33 5 56 67 20 63",
    "sg:postcode":"33640",
    "sg:province":"Aquitaine",
    "sg:tags":[
        "french"
    ],
    "wof:name":"Ch\u00e2teau Du Mirail Ass",
    "wof:placetype":"venue"
},
  "geometry": {"coordinates":[-0.421847,44.696342],"type":"Point"}
}