{
  "type": "Feature",
  "properties": {
    "addr:full":"Le Clocher 23000 Saint Sulpice le Gu\u00e9r\u00e9tois Limousin 23000",
    "addr:housenumber":"23000",
    "addr:postcode":"23000",
    "addr:street":"Saint Sulpice Le Gue\u0301Re\u0301Tois Limousin",
    "iso:country":"FR",
    "sg:address":"Le Clocher 23000 Saint Sulpice le Gu\u00e9r\u00e9tois",
    "sg:orig_category":"Non-Classified Establishments",
    "sg:phone":"+33 5 55 41 20 20",
    "sg:postcode":"23000",
    "sg:province":"Limousin",
    "wof:name":"A.f.p.a.",
    "wof:placetype":"venue"
},
  "geometry": {"coordinates":[1.844092,46.175934],"type":"Point"}
}