{
  "type": "Feature",
  "properties": {
    "addr:full":"Z.I. du Fournalet Sorgues Provence-Alpes-C\u00f4te d'Azur 84700",
    "addr:postcode":"84700",
    "addr:street":"Z.I. Du Fournalet Sorgues",
    "iso:country":"FR",
    "sg:address":"Z.I. du Fournalet",
    "sg:city":"Sorgues",
    "sg:orig_category":"Unclassifiable Establishments",
    "sg:phone":"+33 4 90 39 70 00",
    "sg:postcode":"84700",
    "sg:province":"Provence-Alpes-C\u00f4te d'Azur",
    "wof:name":"B.m. Provence S.c.i.",
    "wof:placetype":"venue"
},
  "geometry": {"coordinates":[4.873481,44.00827],"type":"Point"}
}