{
  "type": "Feature",
  "properties": {
    "iso:country":"FR",
    "sg:address":"23 Avenue Bosquet 75007 Paris",
    "sg:classifiers":[
        {
            "category":"Professional",
            "subcategory":"Business Services",
            "type":"Services"
        }
    ],
    "sg:phone":"+33 1 45 50 45 49",
    "sg:postcode":"75007",
    "sg:province":"Ile de France",
    "sg:tags":[
        "body",
        "advice"
    ],
    "wof:name":"Fiabci",
    "wof:placetype":"venue"
},
  "geometry": {"coordinates":[2.30311,48.860363],"type":"Point"}
}