{
  "type": "Feature",
  "properties": {
    "iso:country":"FR",
    "sg:address":"Faye 24600 Riberac",
    "sg:city":"Rib\u00e9rac",
    "sg:classifiers":[
        {
            "category":"Home & Garden",
            "subcategory":"Furniture",
            "type":"Retail Goods"
        }
    ],
    "sg:phone":"+33 5 53 90 95 95",
    "sg:postcode":"24600",
    "sg:province":"Aquitaine",
    "sg:tags":[
        "household",
        "wood"
    ],
    "wof:name":"Ste D'exploitation Des Etss Chartres Christian (meubles D'art)",
    "wof:placetype":"venue"
},
  "geometry": {"coordinates":[0.36328,45.246857],"type":"Point"}
}