{
  "type": "Feature",
  "properties": {
    "iso:country":"FR",
    "sg:address":"Le Grand Chasse Rn 92 26750 St Paul Les Romans",
    "sg:classifiers":[
        {
            "category":"Professional",
            "subcategory":"Engineering",
            "type":"Services"
        }
    ],
    "sg:phone":"+33 4 75 05 10 31",
    "sg:postcode":"26750",
    "sg:province":"Rhone-Alpes",
    "sg:tags":[
        "leather",
        "material",
        "-",
        "machine",
        "raw",
        "mechanical"
    ],
    "wof:name":"Cuir Decoupe",
    "wof:placetype":"venue"
},
  "geometry": {"coordinates":[5.094173,45.059593],"type":"Point"}
}