{
  "type": "Feature",
  "properties": {
    "addr:full":"Rue Du Moulin Le Blanc 08000 Charleville Mezi\u00e8res Charleville-M\u00e9zi\u00e8res Champagne 08000",
    "addr:postcode":"08000;08000",
    "addr:street":"Rue Du Moulin Le Blanc",
    "iso:country":"FR",
    "sg:address":"Rue Du Moulin Le Blanc 08000 Charleville Mezi\u00e8res",
    "sg:city":"Charleville-M\u00e9zi\u00e8res",
    "sg:classifiers":[
        {
            "category":"Travel",
            "subcategory":"Hotels & Motels",
            "type":"Entertainment"
        }
    ],
    "sg:phone":"+33 3 24 57 47 83",
    "sg:postcode":"08000",
    "sg:province":"Champagne",
    "sg:tags":[
        "hotels",
        "business",
        "restaurant"
    ],
    "wof:name":"Buffalo Grill",
    "wof:placetype":"venue"
},
  "geometry": {"coordinates":[4.723505,49.739269],"type":"Point"}
}