{
  "type": "Feature",
  "properties": {
    "iso:country":"FR",
    "sg:address":"36 Av Verdun 91290 Arpajon",
    "sg:classifiers":[
        {
            "category":"Building & Trades",
            "subcategory":"Construction",
            "type":"Services"
        }
    ],
    "sg:phone":"+33 1 69 26 81 50",
    "sg:postcode":"91290",
    "sg:province":"Ile de France",
    "sg:tags":[
        "work",
        "public"
    ],
    "wof:name":"Appia",
    "wof:placetype":"venue"
},
  "geometry": {"coordinates":[2.241871,48.581444],"type":"Point"}
}