{
  "type": "Feature",
  "properties": {
    "addr:full":"567, Rte des R\u00e9mouleurs - ZI de la Courtine, 84000 Avignon Provence-Alpes-C\u00f4te d'Azur",
    "addr:housenumber":"567",
    "addr:postcode":"84000",
    "addr:street":"Rte Des Re\u0301Mouleurs Zi De La Courtine",
    "iso:country":"FR",
    "sg:address":"567, Rte des R\u00e9mouleurs - ZI de la Courtine, 84000 Avignon",
    "sg:orig_category":"Non-Classified Establishments",
    "sg:phone":"+33 4 90 14 42 00",
    "sg:province":"Provence-Alpes-C\u00f4te d'Azur",
    "wof:name":"G.p.s S.a. - Gardiennage Pr\u00e9vention Et S\u00e9curit\u00e9",
    "wof:placetype":"venue"
},
  "geometry": {"coordinates":[4.806015,43.948753],"type":"Point"}
}