{
  "type": "Feature",
  "properties": {
    "iso:country":"FR",
    "sg:address":"Place De La Gare 59602 Maubeuge",
    "sg:classifiers":[
        {
            "category":"Manufacturing",
            "subcategory":"Wood Products",
            "type":"Manufacturing & Wholesale Goods"
        }
    ],
    "sg:phone":"+33 3 27 65 66 77",
    "sg:province":"Basse Normandie",
    "sg:tags":[
        "furniture"
    ],
    "wof:name":"Publidecor Sarl",
    "wof:placetype":"venue"
},
  "geometry": {"coordinates":[3.967145,50.27298],"type":"Point"}
}