{
  "type": "Feature",
  "properties": {
    "addr:full":"Route Du Contournement Z A 67770 Stattmatten Stattmatten Alsace 67770",
    "addr:postcode":"67770;67770",
    "addr:street":"Route Du Contournement;A;Stattmatten",
    "iso:country":"FR",
    "sg:address":"Route Du Contournement Z A 67770 Stattmatten",
    "sg:city":"Stattmatten",
    "sg:classifiers":[
        {
            "category":"Shopping",
            "type":"Retail Goods"
        }
    ],
    "sg:phone":"+33 3 88 05 75 85",
    "sg:postcode":"67770",
    "sg:province":"Alsace",
    "sg:tags":[
        "metallurgy",
        "finished",
        "-",
        "metalworking",
        "metallic"
    ],
    "wof:name":"Agencement Menuiserie Emde",
    "wof:placetype":"venue"
},
  "geometry": {"coordinates":[8.001505,48.800304],"type":"Point"}
}