{
  "type": "Feature",
  "properties": {
    "addr:full":"12, Rue Charles Nungesser, 33290 Blanquefort Blanquefort Aquitaine 33290",
    "addr:housenumber":"12",
    "addr:postcode":"33290;33290",
    "addr:street":"Rue Charles Nungesser",
    "iso:country":"FR",
    "sg:address":"12, Rue Charles Nungesser, 33290 Blanquefort",
    "sg:city":"Blanquefort",
    "sg:orig_category":"Unclassifiable Establishments",
    "sg:phone":"+33 5 56 57 11 11",
    "sg:postcode":"33290",
    "sg:province":"Aquitaine",
    "wof:name":"Semaq - S.a.r.l. - Soci\u00e9t\u00e9 D'emballage Et Manutention Aquitaine",
    "wof:placetype":"venue"
},
  "geometry": {"coordinates":[-0.618216,44.925179],"type":"Point"}
}