{
  "type": "Feature",
  "properties": {
    "iso:country":"FR",
    "sg:address":"Rue Du Pont Fourneau 13 59360 Le Ch\u00e2teau Cambr\u00e9sis",
    "sg:classifiers":[
        {
            "category":"Shopping",
            "subcategory":"Crafts & Fabrics",
            "type":"Retail Goods"
        }
    ],
    "sg:phone":"+33 3 27 84 08 77",
    "sg:postcode":"59360",
    "sg:province":"Nord Pas-de-Calais",
    "sg:tags":[
        "textile",
        "clothing"
    ],
    "wof:name":"Drubay Et Cie",
    "wof:placetype":"venue"
},
  "geometry": {"coordinates":[-122.13299600000001,48.125565],"type":"Point"}
}