{
  "type": "Feature",
  "properties": {
    "addr:full":"B.P. 53, 59580 Aniche^^6, Impasse Ducret, 59580 Aniche Nord Pas-de-Calais 59580",
    "addr:postcode":"59580;59580;59580",
    "addr:street":"B.P. 53;Impasse Ducret",
    "iso:country":"FR",
    "sg:address":"B.P. 53, 59580 Aniche^^6, Impasse Ducret, 59580 Aniche",
    "sg:orig_category":"Non-Classified Establishments",
    "sg:phone":"+33 3 27 92 53 33",
    "sg:postcode":"59580",
    "sg:province":"Nord Pas-de-Calais",
    "wof:name":"Boivin Miroiterie S.a.",
    "wof:placetype":"venue"
},
  "geometry": {"coordinates":[3.249528,50.331013],"type":"Point"}
}