{
  "type": "Feature",
  "properties": {
    "iso:country":"FR",
    "sg:address":"B.P. 53, 59580 Aniche^^6, Impasse Ducret, 59580 Aniche",
    "sg:orig_category":"Non-Classified Establishments",
    "sg:phone":"+33 3 27 92 53 33",
    "sg:postcode":"59580",
    "sg:province":"Nord Pas-de-Calais",
    "wof:name":"Boivin Miroiterie S.a.",
    "wof:placetype":"venue"
},
  "geometry": {"coordinates":[3.249528,50.331013],"type":"Point"}
}