{
  "type": "Feature",
  "properties": {
    "addr:full":"25 Rue Des Alouettes 49450 St Macaire En Mauges Pays de Loire 49450",
    "addr:housenumber":"25",
    "addr:postcode":"49450;49450",
    "addr:street":"Rue Des Alouettes;Mauges",
    "iso:country":"FR",
    "sg:address":"25 Rue Des Alouettes 49450 St Macaire En Mauges",
    "sg:classifiers":[
        {
            "category":"Manufacturing",
            "subcategory":"Food",
            "type":"Manufacturing & Wholesale Goods"
        }
    ],
    "sg:phone":"+33 2 41 46 32 32",
    "sg:postcode":"49450",
    "sg:province":"Pays de Loire",
    "sg:tags":[
        "preserve",
        "product",
        "related"
    ],
    "wof:name":"Flo Seafoods",
    "wof:placetype":"venue"
},
  "geometry": {"coordinates":[-0.974044,47.118713],"type":"Point"}
}