{
  "type": "Feature",
  "properties": {
    "addr:full":"33, Voie Verdun, 01100 Oyonnax Rhone-Alpes 01100",
    "addr:housenumber":"33",
    "addr:postcode":"01100;01100",
    "addr:street":"Voie Verdun",
    "iso:country":"FR",
    "sg:address":"33, Voie Verdun, 01100 Oyonnax",
    "sg:orig_category":"Unclassifiable Establishments",
    "sg:phone":"+33 4 74 73 42 33",
    "sg:postcode":"01100",
    "sg:province":"Rhone-Alpes",
    "wof:name":"I.d.i.c.e. S.a. - Initiative De D\u00e9veloppement International De Cong",
    "wof:placetype":"venue"
},
  "geometry": {"coordinates":[5.653932,46.266197],"type":"Point"}
}