{
  "type": "Feature",
  "properties": {
    "iso:country":"FR",
    "sg:address":"24 rue Pasteur 59980 Bertry",
    "sg:classifiers":[
        {
            "category":"Parking",
            "subcategory":"Garage",
            "type":"Transportation"
        }
    ],
    "sg:phone":"+33 3 27 76 59 88",
    "sg:province":"Nord Pas-de-Calais",
    "sg:tags":[
        "ornament",
        "graf"
    ],
    "wof:name":"Hyodall Productions Sa",
    "wof:placetype":"venue"
},
  "geometry": {"coordinates":[3.444702,50.090214],"type":"Point"}
}