{
  "type": "Feature",
  "properties": {
    "addr:full":"R MAL DE LATTRE DE TASSIGNY 78990 Elancourt Ile de France 78990",
    "addr:postcode":"78990;78990",
    "addr:street":"Mal De Lattre De Tassigny;Ile De France",
    "iso:country":"FR",
    "sg:address":"R MAL DE LATTRE DE TASSIGNY 78990 Elancourt",
    "sg:classifiers":[
        {
            "category":"Professional",
            "subcategory":"Business Services",
            "type":"Services"
        }
    ],
    "sg:phone":"+33 1 30 68 82 68",
    "sg:postcode":"78990",
    "sg:province":"Ile de France",
    "sg:tags":[
        "agency",
        "export"
    ],
    "wof:name":"Scoa Inter Sarl",
    "wof:placetype":"venue"
},
  "geometry": {"coordinates":[1.97648,48.797676],"type":"Point"}
}