{
  "type": "Feature",
  "properties": {
    "addr:full":"7, Bd Chanoine Kir, 21000 Dijon Dijon Bourgogne 21000",
    "addr:housenumber":"7",
    "addr:postcode":"21000;21000",
    "addr:street":"Bd Chanoine",
    "iso:country":"FR",
    "sg:address":"7, Bd Chanoine Kir, 21000 Dijon",
    "sg:city":"Dijon",
    "sg:orig_category":"Unclassifiable Establishments",
    "sg:phone":"+33 3 80 42 42 42",
    "sg:postcode":"21000",
    "sg:province":"Bourgogne",
    "wof:name":"Le Bien Public - Les D\u00e9p\u00eaches S.a.",
    "wof:placetype":"venue"
},
  "geometry": {"coordinates":[5.00567,47.318497],"type":"Point"}
}