{
  "type": "Feature",
  "properties": {
    "iso:country":"FR",
    "sg:address":"La Gare 71570 Romaneche Thorins",
    "sg:city":"Chaintr\u00e9",
    "sg:classifiers":[
        {
            "category":"Food Court",
            "type":"Food & Drink"
        }
    ],
    "sg:phone":"+33 3 85 35 34 20",
    "sg:postcode":"71570",
    "sg:province":"Bourgogne",
    "sg:tags":[
        "product",
        "related"
    ],
    "wof:name":"Les Vins Georges Duboeuf",
    "wof:placetype":"venue"
},
  "geometry": {"coordinates":[4.740734,46.176765],"type":"Point"}
}