{
  "type": "Feature",
  "properties": {
    "addr:full":"B.P. 15, 59890 Quesnoy sur De\u00fble^^156, Rue de Lille, 59890 Quesnoy sur De\u00fble Nord Pas-de-Calais",
    "addr:postcode":"59890;59890",
    "addr:street":"B.P. 15;Rue De Lille;Deu\u0302Le",
    "iso:country":"FR",
    "sg:address":"B.P. 15, 59890 Quesnoy sur De\u00fble^^156, Rue de Lille, 59890 Quesnoy sur De\u00fble",
    "sg:orig_category":"Non-Classified Establishments",
    "sg:phone":"+33 3 20 21 89 30",
    "sg:province":"Nord Pas-de-Calais",
    "wof:name":"S.t.m.c. Nord S.a.",
    "wof:placetype":"venue"
},
  "geometry": {"coordinates":[3.000988,50.712395],"type":"Point"}
}