{
  "type": "Feature",
  "properties": {
    "iso:country":"FR",
    "sg:address":"14 rue du Platre 69360 ST SYMPHORIEN D OZON",
    "sg:classifiers":[
        {
            "category":"Manufacturing",
            "subcategory":"Textiles",
            "type":"Manufacturing & Wholesale Goods"
        }
    ],
    "sg:phone":"+33 4 78 02 70 54",
    "sg:postcode":"69360",
    "sg:province":"Rhone-Alpes",
    "sg:tags":[
        "natural"
    ],
    "wof:name":"Lalse Sa",
    "wof:placetype":"venue"
},
  "geometry": {"coordinates":[-101.201523,30.710594],"type":"Point"}
}