{
  "type": "Feature",
  "properties": {
    "iso:country":"FR",
    "sg:address":"120, Rue Sainte, 13007 Marseille",
    "sg:orig_category":"Non-Classified Establishments",
    "sg:phone":"+33 4 91 33 33 16",
    "sg:province":"Poitou-Charentes",
    "wof:name":"Imprimerie Nouvelle S.a.r.l.",
    "wof:placetype":"venue"
},
  "geometry": {"coordinates":[5.36068,43.283264],"type":"Point"}
}