{
  "type": "Feature",
  "properties": {
    "iso:country":"FR",
    "sg:address":"4 Rue Aliz\u00e9s 14790 Verson",
    "sg:city":"Verson",
    "sg:classifiers":[
        {
            "category":"Farming",
            "subcategory":"Livestock Farm",
            "type":"Manufacturing & Wholesale Goods"
        }
    ],
    "sg:phone":"+33 2 31 26 47 00",
    "sg:postcode":"14790",
    "sg:province":"Basse Normandie",
    "sg:tags":[
        "breeding",
        "agriculture",
        "animal"
    ],
    "wof:name":"Nutrimer Sa",
    "wof:placetype":"venue"
},
  "geometry": {"coordinates":[-0.460438,49.159313],"type":"Point"}
}