{
  "type": "Feature",
  "properties": {
    "addr:full":"Zi Du Costet Beillard Chem Granges Bas 88400 G\u00e9rardmer Lorraine 88400",
    "addr:postcode":"88400;88400",
    "addr:street":"Zi Du Costet Beillard Chem",
    "iso:country":"FR",
    "sg:address":"Zi Du Costet Beillard",
    "sg:city":"Chem Granges Bas 88400 G\u00e9rardmer",
    "sg:classifiers":[
        {
            "category":"Food Court",
            "type":"Food & Drink"
        }
    ],
    "sg:phone":"+33 3 29 63 63 63",
    "sg:postcode":"88400",
    "sg:province":"Lorraine",
    "sg:tags":[
        "product",
        "related"
    ],
    "wof:name":"Vogdis Sa",
    "wof:placetype":"venue"
},
  "geometry": {"coordinates":[6.816913,48.071114],"type":"Point"}
}