{
  "type": "Feature",
  "properties": {
    "iso:country":"FR",
    "sg:address":"60, Rte de Neuvy sur Seille, 39210 Voiteur",
    "sg:orig_category":"Unclassifiable Establishments",
    "sg:phone":"+33 3 84 85 21 29",
    "sg:province":"Franche Comt\u00e9",
    "wof:name":"Fruiti\u00e8re Vinicole De Voiteur",
    "wof:placetype":"venue"
},
  "geometry": {"coordinates":[5.59976,46.762726],"type":"Point"}
}