{
  "type": "Feature",
  "properties": {
    "addr:full":"44, Av. Maurice et Marius Peyre - ZI la Grand'Colle, 13110 Port de Bouc Aquitaine",
    "addr:housenumber":"13110",
    "addr:street":"44 Av. Maurice Et Marius Peyre Zi La Grand'Colle",
    "iso:country":"FR",
    "sg:address":"44, Av. Maurice et Marius Peyre - ZI la Grand'Colle, 13110 Port de Bouc",
    "sg:orig_category":"Unclassifiable Establishments",
    "sg:phone":"+33 4 42 06 10 31",
    "sg:province":"Aquitaine",
    "wof:name":"Aspimat S.a.r.l.",
    "wof:placetype":"venue"
},
  "geometry": {"coordinates":[4.99928,43.42075],"type":"Point"}
}