{
  "type": "Feature",
  "properties": {
    "iso:country":"FR",
    "sg:address":"12, Rue Clavel, 75019 Paris",
    "sg:orig_category":"Unclassifiable Establishments",
    "sg:phone":"+33 1 42 02 71 69",
    "sg:province":"Ile de France",
    "wof:name":"Imprimerie Dubois S.a.r.l.",
    "wof:placetype":"venue"
},
  "geometry": {"coordinates":[2.384532,48.875149],"type":"Point"}
}