{
  "type": "Feature",
  "properties": {
    "iso:country":"FR",
    "sg:address":"Imm Pre Lacour Bat E 38660 Saint Hilaire du Touvet",
    "sg:classifiers":[
        {
            "category":"Government",
            "subcategory":"Fire Station",
            "type":"Public Place"
        }
    ],
    "sg:phone":"+33 4 76 08 37 06",
    "sg:postcode":"38660",
    "sg:province":"Rhone-Alpes",
    "sg:tags":[
        "development",
        "hardware",
        "soft"
    ],
    "wof:name":"Gentiane Informatique S.a.r.l.",
    "wof:placetype":"venue"
},
  "geometry": {"coordinates":[5.875529,45.301979],"type":"Point"}
}