{
  "type": "Feature",
  "properties": {
    "addr:full":"134 Rue Julian Grimau 94400 Vitry Sur Seine Ile de France 94400",
    "addr:housenumber":"134",
    "addr:postcode":"94400;94400",
    "addr:street":"Rue Julian Grimau;France",
    "iso:country":"FR",
    "sg:address":"134 Rue Julian Grimau 94400 Vitry Sur Seine",
    "sg:classifiers":[
        {
            "category":"Professional",
            "subcategory":"Engineering",
            "type":"Services"
        }
    ],
    "sg:phone":"+33 1 46 80 67 08",
    "sg:postcode":"94400",
    "sg:province":"Ile de France",
    "sg:tags":[
        "machine",
        "-",
        "environment",
        "equipment",
        "machinery",
        "mechanical"
    ],
    "wof:name":"Europeenne D'electricite Automatismes Informatises (2 Eai)",
    "wof:placetype":"venue"
},
  "geometry": {"coordinates":[2.376663,48.77779],"type":"Point"}
}