{
  "type": "Feature",
  "properties": {
    "addr:full":"Zi Les Beno\u00eets 71470 Romenay Romenay Bourgogne 71470",
    "addr:postcode":"71470;71470",
    "addr:street":"Zi Les Benoi\u0302Ts",
    "iso:country":"FR",
    "sg:address":"Zi Les Beno\u00eets 71470 Romenay",
    "sg:city":"Romenay",
    "sg:classifiers":[
        {
            "category":"Manufacturing",
            "subcategory":"Wood Products",
            "type":"Manufacturing & Wholesale Goods"
        }
    ],
    "sg:phone":"+33 3 85 40 35 62",
    "sg:postcode":"71470",
    "sg:province":"Bourgogne",
    "sg:tags":[
        "professional",
        "furniture"
    ],
    "wof:name":"Ste Distribution Aux Collectivites",
    "wof:placetype":"venue"
},
  "geometry": {"coordinates":[5.06668,46.502464],"type":"Point"}
}