{
  "type": "Feature",
  "properties": {
    "iso:country":"FR",
    "sg:address":"Ch\u00e2teau Cissac 33250 Cissac M\u00e9doc",
    "sg:city":"Cissac-M\u00e9doc",
    "sg:orig_category":"Unclassifiable Establishments",
    "sg:phone":"+33 5 56 59 58 13",
    "sg:postcode":"33250",
    "sg:province":"Aquitaine",
    "wof:name":"L. Vialard Ch\u00e2teau Cissac S.a.",
    "wof:placetype":"venue"
},
  "geometry": {"coordinates":[-0.828098,45.227722],"type":"Point"}
}