{
  "type": "Feature",
  "properties": {
    "addr:full":"264 Rue Marcel Sembat 59283 Raimbeaucourt Nord Pas-de-Calais",
    "addr:housenumber":"264",
    "addr:postcode":"59283",
    "addr:street":"Rue Marcel Sembat",
    "iso:country":"FR",
    "sg:address":"264 Rue Marcel Sembat 59283 Raimbeaucourt",
    "sg:classifiers":[
        {
            "category":"Utilities",
            "subcategory":"Telephone",
            "type":"Services"
        }
    ],
    "sg:phone":"+33 3 27 80 35 57",
    "sg:province":"Nord Pas-de-Calais",
    "sg:tags":[
        "telecommunication"
    ],
    "wof:name":"Corfu Radiocommunications",
    "wof:placetype":"venue"
},
  "geometry": {"coordinates":[3.075674,50.429386],"type":"Point"}
}