{
  "type": "Feature",
  "properties": {
    "addr:full":"Min Fleurs 12 box 9 06200 Nice Haute Normandie",
    "addr:housenumber":"12;9",
    "addr:postcode":"06200",
    "addr:street":"Box;Haute Normandie",
    "iso:country":"FR",
    "sg:address":"Min Fleurs 12 box 9 06200 Nice",
    "sg:classifiers":[
        {
            "category":"Utilities",
            "subcategory":"Natural Gas",
            "type":"Services"
        }
    ],
    "sg:phone":"+33 4 93 83 10 73",
    "sg:province":"Haute Normandie",
    "sg:tags":[
        "flower",
        "dried"
    ],
    "wof:name":"Fleurs Des Alpes S.a.r.l.",
    "wof:placetype":"venue"
},
  "geometry": {"coordinates":[7.215093,43.745003],"type":"Point"}
}