{
  "type": "Feature",
  "properties": {
    "iso:country":"FR",
    "sg:address":"48 Bd Marcel Sembat 69200 Venissieux",
    "sg:classifiers":[
        {
            "category":"Building & Trades",
            "subcategory":"Construction",
            "type":"Services"
        }
    ],
    "sg:phone":"+33 4 72 78 37 37",
    "sg:province":"Rhone-Alpes",
    "sg:tags":[
        "work",
        "public"
    ],
    "wof:name":"Screg Sud-est",
    "wof:placetype":"venue"
},
  "geometry": {"coordinates":[4.87888,45.713993],"type":"Point"}
}