{
  "type": "Feature",
  "properties": {
    "addr:full":"160 Rue Tourmaline D'Activit\u00e9s 13510 Eguilles Poitou-Charentes",
    "addr:housenumber":"160",
    "addr:postcode":"13510",
    "addr:street":"Rue Tourmaline D'Activite \u0301S;Eguilles",
    "iso:country":"FR",
    "sg:address":"160 Rue Tourmaline",
    "sg:city":"D'Activit\u00e9s 13510 Eguilles",
    "sg:classifiers":[
        {
            "category":"Building & Trades",
            "subcategory":"Construction",
            "type":"Services"
        }
    ],
    "sg:phone":"+33 4 42 20 00 10",
    "sg:province":"Poitou-Charentes",
    "sg:tags":[
        "work",
        "public"
    ],
    "wof:name":"Etandex",
    "wof:placetype":"venue"
},
  "geometry": {"coordinates":[5.364044,43.546677],"type":"Point"}
}