{
  "type": "Feature",
  "properties": {
    "iso:country":"FR",
    "sg:address":"15, Rue du Docteur Quignard, 21000 Dijon",
    "sg:city":"Dijon",
    "sg:orig_category":"Non-Classified Establishments",
    "sg:phone":"+33 3 80 78 77 80",
    "sg:postcode":"21000",
    "sg:province":"Bourgogne",
    "wof:name":"Sagem S.a.",
    "wof:placetype":"venue"
},
  "geometry": {"coordinates":[5.068607,47.349365],"type":"Point"}
}