{
  "type": "Feature",
  "properties": {
    "iso:country":"FR",
    "sg:address":"21, Av. du Garigliano - ZAC des G\u00e2tines, 91600 Savigny sur Orge",
    "sg:orig_category":"Non-Classified Establishments",
    "sg:phone":"+33 1 69 05 37 70",
    "sg:province":"Ile de France",
    "wof:name":"Les D\u00e9coupages Fran\u00e7ais S.a.r.l.",
    "wof:placetype":"venue"
},
  "geometry": {"coordinates":[2.35317,48.675098],"type":"Point"}
}