{
  "type": "Feature",
  "properties": {
    "iso:country":"FR",
    "sg:address":"Za Gaillagues 12200 St R\u00e9my",
    "sg:classifiers":[
        {
            "category":"Manufacturing",
            "subcategory":"Printing",
            "type":"Manufacturing & Wholesale Goods"
        }
    ],
    "sg:phone":"+33 5 65 65 01 12",
    "sg:province":"Midi Pyr\u00e9n\u00e9es",
    "sg:tags":[
        "publishing"
    ],
    "wof:name":"Grapho 12 Sa",
    "wof:placetype":"venue"
},
  "geometry": {"coordinates":[2.039621,44.39917],"type":"Point"}
}