{
  "type": "Feature",
  "properties": {
    "iso:country":"FR",
    "sg:address":"Rte De Rigny 70100 Arc-L\u00e8s-Gray",
    "sg:classifiers":[
        {
            "category":"Autos & Motor Vehicles",
            "subcategory":"Automobile Sales",
            "type":"Retail Goods"
        }
    ],
    "sg:phone":"+33 3 84 65 07 24",
    "sg:postcode":"70100",
    "sg:province":"Franche Comt\u00e9",
    "sg:tags":[
        "equipment",
        "industrial",
        "transport"
    ],
    "wof:name":"Carrosserie Berthet Barbin Sarl",
    "wof:placetype":"venue"
},
  "geometry": {"coordinates":[5.600876,47.459743],"type":"Point"}
}