{
  "type": "Feature",
  "properties": {
    "addr:full":"1 Rue Raymond Rousseau 18500 Foecy Fo\u00ebcy Centre 18500",
    "addr:housenumber":"1;foe\u0308cy",
    "addr:postcode":"18500;18500",
    "addr:street":"Rue Raymond Rousseau",
    "iso:country":"FR",
    "sg:address":"1 Rue Raymond Rousseau 18500 Foecy",
    "sg:city":"Fo\u00ebcy",
    "sg:classifiers":[
        {
            "category":"Home & Garden",
            "subcategory":"Furniture",
            "type":"Retail Goods"
        }
    ],
    "sg:phone":"+33 2 48 51 14 86",
    "sg:postcode":"18500",
    "sg:province":"Centre",
    "sg:tags":[
        "wood"
    ],
    "wof:name":"Barroso Da Fonte Antonio",
    "wof:placetype":"venue"
},
  "geometry": {"coordinates":[2.16665,47.177029],"type":"Point"}
}