{
  "type": "Feature",
  "properties": {
    "addr:full":"Usine de Renesson Tr\u00e9mont sur Saulx Lorraine 55000",
    "addr:postcode":"55000",
    "addr:street":"Tre\u0301Mont;Saulx Lorraine",
    "iso:country":"FR",
    "sg:address":"Usine de Renesson",
    "sg:city":"Tr\u00e9mont sur Saulx",
    "sg:orig_category":"Non-Classified Establishments",
    "sg:phone":"+33 3 29 76 84 84",
    "sg:postcode":"55000",
    "sg:province":"Lorraine",
    "wof:name":"Hoppecke S.a.r.l.",
    "wof:placetype":"venue"
},
  "geometry": {"coordinates":[5.084741,48.685223],"type":"Point"}
}