{
  "type": "Feature",
  "properties": {
    "addr:full":"93537 Aubervilliers C\u00e9dex^^55, Bd F\u00e9lix Faure, 93300 Aubervilliers Ile de France",
    "addr:postcode":"93537;93300",
    "addr:street":"Bd Fe\u0301Lix Faure",
    "iso:country":"FR",
    "sg:address":"93537 Aubervilliers C\u00e9dex^^55, Bd F\u00e9lix Faure, 93300 Aubervilliers",
    "sg:orig_category":"Non-Classified Establishments",
    "sg:phone":"+33 1 48 34 41 41",
    "sg:province":"Ile de France",
    "wof:name":"Kdi Fertube S.a.",
    "wof:placetype":"venue"
},
  "geometry": {"coordinates":[2.382535,48.913391],"type":"Point"}
}