{
  "type": "Feature",
  "properties": {
    "addr:full":"La Quilla 44690 La Haie Fouassi\u00e8re Pays de Loire 44690",
    "addr:housenumber":"44690",
    "addr:postcode":"44690",
    "addr:street":"Haie Fouassie\u0300Re Pays",
    "iso:country":"FR",
    "sg:address":"La Quilla 44690 La Haie Fouassi\u00e8re",
    "sg:classifiers":[
        {
            "category":"Food Court",
            "type":"Food & Drink"
        }
    ],
    "sg:phone":"+33 2 40 54 88 96",
    "sg:postcode":"44690",
    "sg:province":"Pays de Loire",
    "sg:tags":[
        "product",
        "related"
    ],
    "wof:name":"Daniel Et Gerard Vinet Gaec",
    "wof:placetype":"venue"
},
  "geometry": {"coordinates":[-1.376389,47.1651],"type":"Point"}
}