{
  "type": "Feature",
  "properties": {
    "iso:country":"FR",
    "sg:address":"88, Rue du Caud Soleil, 76340 Villers sous Foucarmont",
    "sg:orig_category":"Unclassifiable Establishments",
    "sg:phone":"+33 2 35 93 71 72",
    "sg:province":"Haute Normandie",
    "wof:name":"Brun S.a.",
    "wof:placetype":"venue"
},
  "geometry": {"coordinates":[1.568325,49.8344],"type":"Point"}
}