{
  "type": "Feature",
  "properties": {
    "iso:country":"FR",
    "sg:address":"12, Rue Mercier - ZI Mitry Compans, 77290 Mitry Mory",
    "sg:orig_category":"Non-Classified Establishments",
    "sg:phone":"+33 1 60 93 71 00",
    "sg:postcode":"77290",
    "sg:province":"Ile de France",
    "wof:name":"B\u00f6hler S.a.",
    "wof:placetype":"venue"
},
  "geometry": {"coordinates":[2.619585,48.984165],"type":"Point"}
}