{
  "type": "Feature",
  "properties": {
    "addr:full":"47, Rue de Neuilly, 92000 Nanterre Ile de France",
    "addr:housenumber":"47",
    "addr:postcode":"92000",
    "addr:street":"Rue De Neuilly",
    "iso:country":"FR",
    "sg:address":"47, Rue de Neuilly, 92000 Nanterre",
    "sg:orig_category":"Unclassifiable Establishments",
    "sg:phone":"+33 1 47 29 29 20",
    "sg:province":"Ile de France",
    "wof:name":"Veng Hour S.a.",
    "wof:placetype":"venue"
},
  "geometry": {"coordinates":[2.21067,48.886292],"type":"Point"}
}