{
  "type": "Feature",
  "properties": {
    "iso:country":"FR",
    "sg:address":"13, Rue du Maine, 68270 Wittenheim",
    "sg:city":"Wittenheim",
    "sg:orig_category":"Unclassifiable Establishments",
    "sg:phone":"+33 3 89 50 76 20",
    "sg:postcode":"68270",
    "sg:province":"Alsace",
    "wof:name":"Knoerr S.a.",
    "wof:placetype":"venue"
},
  "geometry": {"coordinates":[7.307634,47.811054],"type":"Point"}
}