{
  "type": "Feature",
  "properties": {
    "iso:country":"FR",
    "sg:address":"Le Prouzeau 44470 Carquefou",
    "sg:classifiers":[
        {
            "category":"Building & Trades",
            "subcategory":"Construction",
            "type":"Services"
        }
    ],
    "sg:phone":"+33 2 40 52 78 00",
    "sg:postcode":"44470",
    "sg:province":"Pays de Loire",
    "sg:tags":[
        "work",
        "public"
    ],
    "wof:name":"Art Dan",
    "wof:placetype":"venue"
},
  "geometry": {"coordinates":[-1.439776,47.292416],"type":"Point"}
}