{
  "type": "Feature",
  "properties": {
    "addr:full":"B.P. 324, 50203 Coutances C\u00e9dex^^4, Rue Tancr\u00e8de, 50200 Coutances Coutances Basse Normandie 50200",
    "addr:housenumber":"b.p. 324",
    "addr:postcode":"50203;50200;50200",
    "addr:street":"Rue Tancre\u0300De",
    "iso:country":"FR",
    "sg:address":"B.P. 324, 50203 Coutances C\u00e9dex^^4, Rue Tancr\u00e8de, 50200 Coutances",
    "sg:city":"Coutances",
    "sg:orig_category":"Non-Classified Establishments",
    "sg:phone":"+33 2 33 45 15 27",
    "sg:postcode":"50200",
    "sg:province":"Basse Normandie",
    "wof:name":"Pierre S.a.",
    "wof:placetype":"venue"
},
  "geometry": {"coordinates":[-1.433329,49.00985],"type":"Point"}
}