{
  "type": "Feature",
  "properties": {
    "addr:full":"75, Av. Oehmichen, 25460 Etupes Franche Comt\u00e9",
    "addr:postcode":"25460",
    "addr:street":"75 Av. Oehmichen;Franche Comte\u0301",
    "iso:country":"FR",
    "sg:address":"75, Av. Oehmichen, 25460 Etupes",
    "sg:orig_category":"Unclassifiable Establishments",
    "sg:phone":"+33 3 81 94 20 20",
    "sg:province":"Franche Comt\u00e9",
    "wof:name":"Createl S.a.r.l.",
    "wof:placetype":"venue"
},
  "geometry": {"coordinates":[6.872015,47.516636],"type":"Point"}
}