{
  "type": "Feature",
  "properties": {
    "iso:country":"FR",
    "sg:address":"B.P. 81, 33370 Artigues pr\u00e8s Bordeaux C\u00e9dex^^Place Pierre Curie, 33370 Artigues pr\u00e8s Bordeaux",
    "sg:city":"Artigues-pr\u00e8s-Bordeaux",
    "sg:orig_category":"Non-Classified Establishments",
    "sg:phone":"+33 5 57 77 44 40",
    "sg:postcode":"33370",
    "sg:province":"Aquitaine",
    "wof:name":"Sobodec S.a. - Soci\u00e9t\u00e9 Bordelaise De D\u00e9coration",
    "wof:placetype":"venue"
},
  "geometry": {"coordinates":[-0.392679,44.808125],"type":"Point"}
}