{
  "type": "Feature",
  "properties": {
    "addr:full":"2480 Av Julien Panchot Route De Thuir Km 3 66000 Perpignan Languedoc-Roussillon 66000",
    "addr:postcode":"2480;66000;66000",
    "addr:street":"Av Julien Panchot Route De Thuir Km 3",
    "iso:country":"FR",
    "sg:address":"2480 Av Julien Panchot Route De Thuir Km 3 66000 Perpignan",
    "sg:classifiers":[
        {
            "category":"Professional",
            "subcategory":"Engineering",
            "type":"Services"
        }
    ],
    "sg:phone":"+33 4 68 55 50 02",
    "sg:postcode":"66000",
    "sg:province":"Languedoc-Roussillon",
    "sg:tags":[
        "machine",
        "-",
        "mechanical"
    ],
    "wof:name":"Domoservices Maintenance",
    "wof:placetype":"venue"
},
  "geometry": {"coordinates":[2.88743,42.69812],"type":"Point"}
}