{
  "type": "Feature",
  "properties": {
    "iso:country":"FR",
    "sg:address":"39, Cours de Verdun, 01100 Oyonnax",
    "sg:orig_category":"Unclassifiable Establishments",
    "sg:phone":"+33 4 74 77 26 73",
    "sg:postcode":"01100",
    "sg:province":"Rhone-Alpes",
    "wof:name":"A.s.b.i. S.a.",
    "wof:placetype":"venue"
},
  "geometry": {"coordinates":[5.652649,46.264923],"type":"Point"}
}