{
  "type": "Feature",
  "properties": {
    "iso:country":"FR",
    "sg:address":"3, Rue Lucien Menut, 03100 Montlu\u00e7on",
    "sg:city":"Montlu\u00e7on",
    "sg:orig_category":"Unclassifiable Establishments",
    "sg:phone":"+33 4 70 28 31 70",
    "sg:postcode":"03100",
    "sg:province":"Auvergne",
    "wof:name":"Greyf's Int\u00e9rim S.a.",
    "wof:placetype":"venue"
},
  "geometry": {"coordinates":[2.602475,46.34248],"type":"Point"}
}