{
  "type": "Feature",
  "properties": {
    "addr:full":"5, Quai de la Souys, 33100 Bordeaux Bordeaux Aquitaine 33100",
    "addr:housenumber":"5",
    "addr:postcode":"33100;33100",
    "addr:street":"Quai De La Souys",
    "iso:country":"FR",
    "sg:address":"5, Quai de la Souys, 33100 Bordeaux",
    "sg:city":"Bordeaux",
    "sg:orig_category":"Unclassifiable Establishments",
    "sg:phone":"+33 5 57 80 03 27",
    "sg:postcode":"33100",
    "sg:province":"Aquitaine",
    "wof:name":"R.i.p. S.a.",
    "wof:placetype":"venue"
},
  "geometry": {"coordinates":[-0.548823,44.832767],"type":"Point"}
}