{
  "type": "Feature",
  "properties": {
    "addr:full":"672, Av. de la Fleuride - ZI des Paluds, 13780 Aubagne Haute Normandie",
    "addr:postcode":"13780",
    "addr:street":"672 Av. De La Fleuride Zi Des Paluds;Haute Normandie",
    "iso:country":"FR",
    "sg:address":"672, Av. de la Fleuride - ZI des Paluds, 13780 Aubagne",
    "sg:orig_category":"Unclassifiable Establishments",
    "sg:phone":"+33 4 42 82 40 40",
    "sg:province":"Haute Normandie",
    "wof:name":"M\u00e9ridionale Des Plastiques S.a.",
    "wof:placetype":"venue"
},
  "geometry": {"coordinates":[5.699832,43.27586],"type":"Point"}
}