{
  "type": "Feature",
  "properties": {
    "addr:full":"14, Av du 23 Novembre, 67300 Schiltigheim Schiltigheim Alsace 67300",
    "addr:postcode":"67300;67300",
    "addr:street":"14 Av Du 23 Novembre",
    "iso:country":"FR",
    "sg:address":"14, Av du 23 Novembre, 67300 Schiltigheim",
    "sg:city":"Schiltigheim",
    "sg:orig_category":"Unclassifiable Establishments",
    "sg:phone":"+33 3 88 18 60 80",
    "sg:postcode":"67300",
    "sg:province":"Alsace",
    "wof:name":"Ytong S.a.r.l.",
    "wof:placetype":"venue"
},
  "geometry": {"coordinates":[7.732399,48.609428],"type":"Point"}
}