{
  "type": "Feature",
  "properties": {
    "iso:country":"FR",
    "sg:address":"27, Rue Jules Verne - ZI Saint Cosme, 37520 La Riche",
    "sg:city":"La Riche",
    "sg:orig_category":"Unclassifiable Establishments",
    "sg:phone":"+33 2 47 37 20 80",
    "sg:postcode":"37520",
    "sg:province":"Centre",
    "wof:name":"Vignal S.a.",
    "wof:placetype":"venue"
},
  "geometry": {"coordinates":[0.66471,47.390419],"type":"Point"}
}