{
  "type": "Feature",
  "properties": {
    "addr:full":"Zone Industrielle Nord 39400 Morez Franche Comt\u00e9",
    "addr:postcode":"39400",
    "addr:street":"Zone Industrielle Nord;Franche Comte\u0301",
    "iso:country":"FR",
    "sg:address":"Zone Industrielle Nord 39400 Morez",
    "sg:classifiers":[
        {
            "category":"Manufacturing",
            "subcategory":"Printing",
            "type":"Manufacturing & Wholesale Goods"
        }
    ],
    "sg:phone":"+33 3 84 33 09 53",
    "sg:province":"Franche Comt\u00e9",
    "sg:tags":[
        "publishing"
    ],
    "wof:name":"La Biennoise Imprimerie Sarl",
    "wof:placetype":"venue"
},
  "geometry": {"coordinates":[6.023062,46.525715],"type":"Point"}
}