{
  "type": "Feature",
  "properties": {
    "addr:full":"1 Rue Oise 95610 Eragny Sur Oise Ile de France 95610",
    "addr:housenumber":"1",
    "addr:postcode":"95610;95610",
    "addr:street":"Rue Oise",
    "iso:country":"FR",
    "sg:address":"1 Rue Oise 95610 Eragny Sur Oise",
    "sg:classifiers":[
        {
            "category":"Professional",
            "subcategory":"Business Services",
            "type":"Services"
        }
    ],
    "sg:phone":"+33 1 34 64 48 74",
    "sg:postcode":"95610",
    "sg:province":"Ile de France",
    "sg:tags":[
        "travel",
        "fair"
    ],
    "wof:name":"La Fontaine Aux Delices",
    "wof:placetype":"venue"
},
  "geometry": {"coordinates":[2.095003,49.024956],"type":"Point"}
}