{
  "type": "Feature",
  "properties": {
    "addr:full":"18, Rue de Steinbach, 57200 Sarreguemines Lorraine",
    "addr:housenumber":"18",
    "addr:postcode":"57200",
    "addr:street":"Rue De Steinbach",
    "iso:country":"FR",
    "sg:address":"18, Rue de Steinbach, 57200 Sarreguemines",
    "sg:orig_category":"Unclassifiable Establishments",
    "sg:phone":"+33 3 87 98 44 31",
    "sg:province":"Lorraine",
    "wof:name":"Kihl Paul S.a.",
    "wof:placetype":"venue"
},
  "geometry": {"coordinates":[7.078103,49.10062],"type":"Point"}
}