{
  "type": "Feature",
  "properties": {
    "addr:full":"08250 Termes Champagne 08250",
    "addr:postcode":"08250;08250",
    "addr:street":"Champagne",
    "iso:country":"FR",
    "sg:address":"08250 Termes",
    "sg:classifiers":[
        {
            "category":"Food & Beverages",
            "subcategory":"Groceries & Convenience Stores",
            "type":"Retail Goods"
        }
    ],
    "sg:phone":"+33 3 24 30 52 88",
    "sg:postcode":"08250",
    "sg:province":"Champagne",
    "sg:tags":[
        "product",
        "grain",
        "cereal",
        "related"
    ],
    "wof:name":"Sas Maillot Le Coffre",
    "wof:placetype":"venue"
},
  "geometry": {"coordinates":[4.823305,49.322731],"type":"Point"}
}