{
  "type": "Feature",
  "properties": {
    "iso:country":"FR",
    "sg:address":"79, Av. de la Cour de France, 91260 Juvisy sur Orge",
    "sg:orig_category":"Unclassifiable Establishments",
    "sg:phone":"+33 1 69 24 20 20",
    "sg:province":"Ile de France",
    "wof:name":"Hase Po\u00eales Chemin\u00e9es S.a.r.l.",
    "wof:placetype":"venue"
},
  "geometry": {"coordinates":[2.371137,48.695496],"type":"Point"}
}