{
  "type": "Feature",
  "properties": {
    "addr:full":"B.P. 9, 89150 Saint Val\u00e9rien^^3, Rue de l'Agriculture, 89150 Saint Val\u00e9rien Brannay Bourgogne 89150",
    "addr:housenumber":"9",
    "addr:postcode":"89150;89150;vale\u0301rien;89150",
    "addr:street":"B.P.;Rue De L'Agriculture;Bourgogne",
    "iso:country":"FR",
    "sg:address":"B.P. 9, 89150 Saint Val\u00e9rien^^3, Rue de l'Agriculture, 89150 Saint Val\u00e9rien",
    "sg:city":"Brannay",
    "sg:orig_category":"Non-Classified Establishments",
    "sg:phone":"+33 3 86 88 61 63",
    "sg:postcode":"89150",
    "sg:province":"Bourgogne",
    "wof:name":"Ponserval",
    "wof:placetype":"venue"
},
  "geometry": {"coordinates":[3.089947,48.1796],"type":"Point"}
}