{
  "type": "Feature",
  "properties": {
    "addr:full":"B.P. 1532, 87020 Limoges C\u00e9dex 9^^Rue Barth\u00e9l\u00e9my Thimmonier - Z.I. Nord, 87280 Limoges Limousin",
    "addr:postcode":"87020;87280",
    "addr:street":"B.P. 1532;9^^Rue Barthe\u0301Le\u0301My Thimmonier Z.I. Nord",
    "iso:country":"FR",
    "sg:address":"B.P. 1532, 87020 Limoges C\u00e9dex 9^^Rue Barth\u00e9l\u00e9my Thimmonier - Z.I. Nord, 87280 Limoges",
    "sg:orig_category":"Non-Classified Establishments",
    "sg:phone":"+33 5 55 04 38 00",
    "sg:province":"Limousin",
    "wof:name":"Val\u00e9o Mat\u00e9riaux De Friction",
    "wof:placetype":"venue"
},
  "geometry": {"coordinates":[1.299435,45.914837],"type":"Point"}
}