{
  "type": "Feature",
  "properties": {
    "addr:full":"137 Rue Du Docteur Guichard 49000 Angers Pays de Loire 49000",
    "addr:housenumber":"137",
    "addr:postcode":"49000;49000",
    "addr:street":"Rue Du Docteur Guichard",
    "iso:country":"FR",
    "sg:address":"137 Rue Du Docteur Guichard 49000 Angers",
    "sg:classifiers":[
        {
            "category":"Farming",
            "subcategory":"Farm",
            "type":"Manufacturing & Wholesale Goods"
        }
    ],
    "sg:phone":"+33 2 41 66 35 45",
    "sg:postcode":"49000",
    "sg:province":"Pays de Loire",
    "sg:tags":[
        "horticulture",
        "agriculture",
        "livestock"
    ],
    "wof:name":"Froger Fleurs",
    "wof:placetype":"venue"
},
  "geometry": {"coordinates":[-0.548517,47.4534],"type":"Point"}
}