{
  "type": "Feature",
  "properties": {
    "iso:country":"FR",
    "sg:address":"60 Rue Des Queries 33100 Bordeaux",
    "sg:city":"Bordeaux",
    "sg:classifiers":[
        {
            "category":"Food & Beverages",
            "subcategory":"Groceries & Convenience Stores",
            "type":"Retail Goods"
        }
    ],
    "sg:phone":"+33 5 57 77 99 99",
    "sg:postcode":"33100",
    "sg:province":"Aquitaine",
    "sg:tags":[
        "product",
        "related"
    ],
    "wof:name":"Ste Europeenne Des Beurres",
    "wof:placetype":"venue"
},
  "geometry": {"coordinates":[-0.564307,44.847008],"type":"Point"}
}