{
  "type": "Feature",
  "properties": {
    "iso:country":"FR",
    "sg:address":"4 Rue Georges Clemenceau 77170 Brie Comte Robert",
    "sg:classifiers":[
        {
            "category":"Banks & Credit Unions",
            "subcategory":"Investment Brokerage",
            "type":"Services"
        }
    ],
    "sg:phone":"+33 1 64 05 07 75",
    "sg:province":"Ile de France",
    "sg:tags":[
        "-",
        "transport",
        "related"
    ],
    "wof:name":"Doret Messageries",
    "wof:placetype":"venue"
},
  "geometry": {"coordinates":[2.604887,48.697693],"type":"Point"}
}