{
  "type": "Feature",
  "properties": {
    "addr:full":"19-21 rue Baudin 93310 Le Pr\u00e9 Saint Gervais Ile de France",
    "addr:housenumber":"19-21",
    "addr:postcode":"93310",
    "addr:street":"Rue Baudin;Pre\u0301",
    "iso:country":"FR",
    "sg:address":"19-21 rue Baudin 93310 Le Pr\u00e9 Saint Gervais",
    "sg:classifiers":[
        {
            "category":"Manufacturing",
            "subcategory":"Building Materials",
            "type":"Manufacturing & Wholesale Goods"
        }
    ],
    "sg:phone":"+33 1 48 44 01 29",
    "sg:province":"Ile de France",
    "sg:tags":[
        "processing",
        "special"
    ],
    "wof:name":"Laroche Tradition S.a.",
    "wof:placetype":"venue"
},
  "geometry": {"coordinates":[2.405036,48.8866],"type":"Point"}
}