{
  "type": "Feature",
  "properties": {
    "addr:full":"46, Les Vanneaux, 76360 Villers Ecalles Haute Normandie 76360",
    "addr:housenumber":"46",
    "addr:postcode":"76360;76360",
    "addr:street":"Les Vanneaux;Haute Normandie",
    "iso:country":"FR",
    "sg:address":"46, Les Vanneaux, 76360 Villers Ecalles",
    "sg:orig_category":"Non-Classified Establishments",
    "sg:phone":"+33 2 32 94 99 99",
    "sg:postcode":"76360",
    "sg:province":"Haute Normandie",
    "wof:name":"Erhyd S.a.r.l.",
    "wof:placetype":"venue"
},
  "geometry": {"coordinates":[0.916319,49.537617],"type":"Point"}
}