{
  "type": "Feature",
  "properties": {
    "addr:full":"374, Rue Eug\u00e8ne Flachat - ZI Nord, 66000 Perpignan Languedoc-Roussillon",
    "addr:housenumber":"374",
    "addr:postcode":"66000",
    "addr:street":"Rue Euge\u0300Ne Flachat Zi Nord",
    "iso:country":"FR",
    "sg:address":"374, Rue Eug\u00e8ne Flachat - ZI Nord, 66000 Perpignan",
    "sg:orig_category":"Unclassifiable Establishments",
    "sg:phone":"+33 4 68 52 71 22",
    "sg:province":"Languedoc-Roussillon",
    "wof:name":"Tecwell Roussillon S.a.r.l.",
    "wof:placetype":"venue"
},
  "geometry": {"coordinates":[2.88743,42.69812],"type":"Point"}
}