{
  "type": "Feature",
  "properties": {
    "addr:full":"4, Rue Verriers, 57500 Saint Avold Lorraine",
    "addr:housenumber":"4",
    "addr:postcode":"57500",
    "addr:street":"Rue Verriers;Avold",
    "iso:country":"FR",
    "sg:address":"4, Rue Verriers, 57500 Saint Avold",
    "sg:orig_category":"Unclassifiable Establishments",
    "sg:phone":"+33 3 87 29 89 89",
    "sg:province":"Lorraine",
    "wof:name":"Soci\u00e9t\u00e9 Des Eaux De L'est S.a.",
    "wof:placetype":"venue"
},
  "geometry": {"coordinates":[6.715953,49.110302],"type":"Point"}
}