{
  "type": "Feature",
  "properties": {
    "addr:full":"36Bis rue Jules Ferry 10600 La Chapelle St Luc Champagne",
    "addr:housenumber":"36bis",
    "addr:postcode":"10600",
    "addr:street":"Rue Jules Ferry;La Chapelle St Luc",
    "iso:country":"FR",
    "sg:address":"36Bis rue Jules Ferry 10600 La Chapelle St Luc",
    "sg:classifiers":[
        {
            "category":"Manufacturing",
            "subcategory":"Textiles",
            "type":"Manufacturing & Wholesale Goods"
        }
    ],
    "sg:phone":"+33 3 25 80 05 16",
    "sg:province":"Champagne",
    "sg:tags":[
        "used",
        "machines"
    ],
    "wof:name":"Trimatex Sarl",
    "wof:placetype":"venue"
},
  "geometry": {"coordinates":[4.055948,48.320061],"type":"Point"}
}