{
  "type": "Feature",
  "properties": {
    "addr:full":"r Promenade 87310 Saint Laurent sur Gorre Limousin",
    "addr:postcode":"87310",
    "addr:street":"R Promenade",
    "iso:country":"FR",
    "sg:address":"r Promenade 87310 Saint Laurent sur Gorre",
    "sg:classifiers":[
        {
            "category":"Professional",
            "type":"Services"
        }
    ],
    "sg:phone":"+33 5 55 00 00 32",
    "sg:province":"Limousin",
    "sg:tags":[
        "transport",
        "road"
    ],
    "wof:name":"Roulaud Transports (sa)",
    "wof:placetype":"venue"
},
  "geometry": {"coordinates":[0.959736,45.766186],"type":"Point"}
}