{
  "type": "Feature",
  "properties": {
    "addr:full":"431 avenue Ambroise Croizat 38920 Crolles Crolles Rhone-Alpes 38190",
    "addr:housenumber":"431",
    "addr:postcode":"38920;38190",
    "addr:street":"Avenue Ambroise Croizat",
    "iso:country":"FR",
    "sg:address":"431 avenue Ambroise Croizat 38920 Crolles",
    "sg:city":"Crolles",
    "sg:classifiers":[
        {
            "category":"Manufacturing",
            "subcategory":"Chemicals & Compounds",
            "type":"Manufacturing & Wholesale Goods"
        }
    ],
    "sg:phone":"+33 4 76 08 00 11",
    "sg:postcode":"38190",
    "sg:province":"Rhone-Alpes",
    "sg:tags":[
        "industrial"
    ],
    "wof:name":"Nalco Sas",
    "wof:placetype":"venue"
},
  "geometry": {"coordinates":[5.885646,45.273266],"type":"Point"}
}