{
  "type": "Feature",
  "properties": {
    "iso:country":"FR",
    "sg:address":"63 Chem De La Poudrette Centre D'Actvit\u00e9",
    "sg:city":"Poudrette 69120 Vaulx En Velin",
    "sg:classifiers":[
        {
            "category":"Manufacturing",
            "subcategory":"Rubber & Plastics",
            "type":"Manufacturing & Wholesale Goods"
        }
    ],
    "sg:phone":"+33 4 78 26 54 30",
    "sg:postcode":"69120",
    "sg:province":"Rhone-Alpes",
    "wof:name":"Socrep Sa",
    "wof:placetype":"venue"
},
  "geometry": {"coordinates":[4.919235,45.764233],"type":"Point"}
}