{
  "type": "Feature",
  "properties": {
    "iso:country":"FR",
    "sg:address":"56BIS rue G\u00e9n\u00e9ral de Gaulle 42400 ST CHAMOND",
    "sg:classifiers":[
        {
            "category":"Manufacturing",
            "subcategory":"Textiles",
            "type":"Manufacturing & Wholesale Goods"
        }
    ],
    "sg:phone":"+33 4 77 22 25 77",
    "sg:postcode":"42400",
    "sg:province":"Rhone-Alpes",
    "sg:tags":[
        "cloth",
        "industrial",
        "cleaning"
    ],
    "wof:name":"Blanchisserie Industrielle Du Centre Sarl",
    "wof:placetype":"venue"
},
  "geometry": {"coordinates":[4.524378,45.467587],"type":"Point"}
}