{
  "type": "Feature",
  "properties": {
    "iso:country":"FR",
    "sg:address":"11 all\u00e9e du Clos des Charmes 77090 Collegien",
    "sg:orig_category":"Reflector Mirrors",
    "sg:phone":"+33 1 60 05 77 22",
    "sg:province":"Ile de France",
    "wof:name":"Vertal Ile De France Sa",
    "wof:placetype":"venue"
},
  "geometry": {"coordinates":[2.67499,48.828072],"type":"Point"}
}