{
  "type": "Feature",
  "properties": {
    "iso:country":"FR",
    "sg:address":"1 Avenue Foch 54270 Essey L\u00e8s Nancy",
    "sg:classifiers":[
        {
            "category":"Professional",
            "subcategory":"Business Services",
            "type":"Services"
        }
    ],
    "sg:phone":"+33 3 83 18 10 20",
    "sg:postcode":"54270",
    "sg:province":"Lorraine",
    "sg:tags":[
        "training",
        "advice"
    ],
    "wof:name":"Ctre D'education Populaire Et Des Sports De Lorraine",
    "wof:placetype":"venue"
},
  "geometry": {"coordinates":[6.216548,48.703197],"type":"Point"}
}