{
  "type": "Feature",
  "properties": {
    "addr:full":"525 Chem Des N\u00e9gadoux 83140 Six Fours Les Plages Poitou-Charentes",
    "addr:housenumber":"525",
    "addr:postcode":"83140",
    "addr:street":"Chem Des Ne\u0301Gadoux;Fours Les Plages",
    "iso:country":"FR",
    "sg:address":"525 Chem Des N\u00e9gadoux 83140 Six Fours Les Plages",
    "sg:classifiers":[
        {
            "category":"Shopping",
            "type":"Retail Goods"
        }
    ],
    "sg:phone":"+33 4 94 87 09 75",
    "sg:province":"Poitou-Charentes",
    "sg:tags":[
        "metallurgy",
        "finished",
        "-",
        "metalworking",
        "metallic"
    ],
    "wof:name":"Var Industries Sarl",
    "wof:placetype":"venue"
},
  "geometry": {"coordinates":[5.84215,43.111305],"type":"Point"}
}