{
  "type": "Feature",
  "properties": {
    "iso:country":"FR",
    "sg:address":"607 Rue Sommaing 59213 Vendegies Sur Ecaillon",
    "sg:classifiers":[
        {
            "category":"Farming",
            "subcategory":"Livestock Farm",
            "type":"Manufacturing & Wholesale Goods"
        }
    ],
    "sg:phone":"+33 3 27 27 04 49",
    "sg:postcode":"59213",
    "sg:province":"Nord Pas-de-Calais",
    "sg:tags":[
        "grain",
        "agriculture",
        "cereal"
    ],
    "wof:name":"Delfanne Sarl",
    "wof:placetype":"venue"
},
  "geometry": {"coordinates":[3.50631,50.263931],"type":"Point"}
}