{
  "type": "Feature",
  "properties": {
    "addr:full":"77555 Moissy Cramayel Cedex^^450, Av. Blaise Pascal, 77550 Moissy Cramayel Ile de France 77550",
    "addr:postcode":"77555;77550;77550",
    "addr:street":"Av. Blaise Pascal",
    "iso:country":"FR",
    "sg:address":"77555 Moissy Cramayel Cedex^^450, Av. Blaise Pascal, 77550 Moissy Cramayel",
    "sg:orig_category":"Non-Classified Establishments",
    "sg:phone":"+33 1 64 88 61 61",
    "sg:postcode":"77550",
    "sg:province":"Ile de France",
    "wof:name":"2 H Photo S.a.r.l.",
    "wof:placetype":"venue"
},
  "geometry": {"coordinates":[2.59017,48.627384],"type":"Point"}
}