{
  "type": "Feature",
  "properties": {
    "iso:country":"FR",
    "sg:address":"Residence Des Glevians 29750 Loctudy",
    "sg:city":"Loctudy",
    "sg:classifiers":[
        {
            "category":"Farming",
            "subcategory":"Livestock Farm",
            "type":"Manufacturing & Wholesale Goods"
        }
    ],
    "sg:phone":"+33 2 98 87 53 27",
    "sg:postcode":"29750",
    "sg:province":"Bretagne",
    "sg:tags":[
        "breeding",
        "agriculture",
        "animal"
    ],
    "wof:name":"Le Dreau Jacques",
    "wof:placetype":"venue"
},
  "geometry": {"coordinates":[-4.169609,47.826305],"type":"Point"}
}