{
  "type": "Feature",
  "properties": {
    "addr:full":"4, Rue de Lorraine - ZA Jeune Bois, 68270 Wittenheim Wittenheim Alsace 68270",
    "addr:housenumber":"4",
    "addr:postcode":"68270;68270",
    "addr:street":"Rue De Lorraine Za Jeune Bois",
    "iso:country":"FR",
    "sg:address":"4, Rue de Lorraine - ZA Jeune Bois, 68270 Wittenheim",
    "sg:city":"Wittenheim",
    "sg:orig_category":"Unclassifiable Establishments",
    "sg:phone":"+33 3 89 57 33 34",
    "sg:postcode":"68270",
    "sg:province":"Alsace",
    "wof:name":"Ventacid S.a.",
    "wof:placetype":"venue"
},
  "geometry": {"coordinates":[7.339937,47.810852],"type":"Point"}
}