{
  "type": "Feature",
  "properties": {
    "addr:full":"11/23, Av. du Chemin des Reniers, 92390 Villeneuve la Garenne Ile de France",
    "addr:housenumber":"11 / 23",
    "addr:postcode":"92390",
    "addr:street":"Av. Du Chemin Des Reniers;Ile",
    "iso:country":"FR",
    "sg:address":"11/23, Av. du Chemin des Reniers, 92390 Villeneuve la Garenne",
    "sg:orig_category":"Unclassifiable Establishments",
    "sg:phone":"+33 1 41 47 43 00",
    "sg:province":"Ile de France",
    "wof:name":"Affilog S.a.r.l.",
    "wof:placetype":"venue"
},
  "geometry": {"coordinates":[2.321987,48.933273],"type":"Point"}
}