{
  "type": "Feature",
  "properties": {
    "iso:country":"FR",
    "sg:address":"B.P. 164",
    "sg:city":"Pontivy",
    "sg:orig_category":"Non-Classified Establishments",
    "sg:phone":"+33 2 97 28 54 00",
    "sg:postcode":"56300",
    "sg:province":"Bretagne",
    "wof:name":"S.o.f.r.a.l. S.a. - Soci\u00e9t\u00e9 Fran\u00e7aise D'aliments",
    "wof:placetype":"venue"
},
  "geometry": {"coordinates":[-2.951319,48.018394],"type":"Point"}
}