{
  "type": "Feature",
  "properties": {
    "iso:country":"FR",
    "sg:address":"B.P. 13, 01105 Oyonnax C\u00e9dex^^Rue de l'Ange - ZI Sud, 01100 Bellignat",
    "sg:orig_category":"Non-Classified Establishments",
    "sg:phone":"+33 4 74 77 00 12",
    "sg:postcode":"01100",
    "sg:province":"Rhone-Alpes",
    "wof:name":"Rexroth Mecman Pneumatics S.a.r.l.",
    "wof:placetype":"venue"
},
  "geometry": {"coordinates":[5.630209,46.238998],"type":"Point"}
}