{
  "type": "Feature",
  "properties": {
    "addr:full":"35, Rue Greneta, 75002 Paris Ile de France",
    "addr:housenumber":"35",
    "addr:postcode":"75002",
    "addr:street":"Rue Greneta",
    "iso:country":"FR",
    "sg:address":"35, Rue Greneta, 75002 Paris",
    "sg:orig_category":"Non-Classified Establishments",
    "sg:phone":"+33 1 44 88 14 88",
    "sg:province":"Ile de France",
    "wof:name":"Evroforum France S.a.r.l.",
    "wof:placetype":"venue"
},
  "geometry": {"coordinates":[2.350026,48.865055],"type":"Point"}
}