{
  "type": "Feature",
  "properties": {
    "addr:full":"La Lande 50290 Coudeville sur Mer Br\u00e9hal Basse Normandie 50290",
    "addr:postcode":"50290;50290",
    "addr:street":"Lande",
    "iso:country":"FR",
    "sg:address":"La Lande 50290 Coudeville sur Mer",
    "sg:city":"Br\u00e9hal",
    "sg:classifiers":[
        {
            "category":"Food & Beverages",
            "subcategory":"Dairy",
            "type":"Retail Goods"
        }
    ],
    "sg:phone":"+33 2 33 91 16 60",
    "sg:postcode":"50290",
    "sg:province":"Basse Normandie",
    "sg:tags":[
        "product",
        "milk"
    ],
    "wof:name":"Scerma Snc",
    "wof:placetype":"venue"
},
  "geometry": {"coordinates":[-1.520334,48.870129],"type":"Point"}
}