{
  "type": "Feature",
  "properties": {
    "addr:full":"Rte de Fins Combles Picardie 80360",
    "addr:postcode":"80360",
    "addr:street":"Rte De Fins;Picardie",
    "iso:country":"FR",
    "sg:address":"Rte de Fins",
    "sg:city":"Combles",
    "sg:orig_category":"Non-Classified Establishments",
    "sg:phone":"+33 3 22 85 12 55",
    "sg:postcode":"80360",
    "sg:province":"Picardie",
    "wof:name":"Agri Somme S.a.",
    "wof:placetype":"venue"
},
  "geometry": {"coordinates":[2.865175,50.009689],"type":"Point"}
}