{
  "type": "Feature",
  "properties": {
    "addr:full":"21/23, Rue Draye de Meyne, 26110 Nyons Rhone-Alpes",
    "addr:housenumber":"21 / 23",
    "addr:postcode":"26110",
    "addr:street":"Rue Draye De Meyne",
    "iso:country":"FR",
    "sg:address":"21/23, Rue Draye de Meyne, 26110 Nyons",
    "sg:orig_category":"Unclassifiable Establishments",
    "sg:phone":"+33 4 75 26 26 21",
    "sg:province":"Rhone-Alpes",
    "wof:name":"C.c.i. De La Dr\u00f4me - Chambre De Commerce Et D'industrie De La Dr\u00f4me",
    "wof:placetype":"venue"
},
  "geometry": {"coordinates":[5.140112,44.359951],"type":"Point"}
}