{
  "type": "Feature",
  "properties": {
    "iso:country":"FR",
    "sg:address":"155, Rue du Beuvron - ZAC des Aulnaies, 45160 Olivet",
    "sg:city":"Ardon",
    "sg:orig_category":"Unclassifiable Establishments",
    "sg:phone":"+33 2 38 69 62 62",
    "sg:postcode":"45160",
    "sg:province":"Centre",
    "wof:name":"Caumon S.a.",
    "wof:placetype":"venue"
},
  "geometry": {"coordinates":[1.875266,47.778763],"type":"Point"}
}