{
  "type": "Feature",
  "properties": {
    "addr:full":"11, Bd Charles de Gaulle - ZI, 42120 Le Coteau Rhone-Alpes 42120",
    "addr:housenumber":"11",
    "addr:postcode":"42120;42120",
    "addr:street":"Bd Charles De Gaulle Zi;Rhone-Alpes",
    "iso:country":"FR",
    "sg:address":"11, Bd Charles de Gaulle - ZI, 42120 Le Coteau",
    "sg:orig_category":"Unclassifiable Establishments",
    "sg:phone":"+33 4 77 70 52 33",
    "sg:postcode":"42120",
    "sg:province":"Rhone-Alpes",
    "wof:name":"Electro-zinc S.a.r.l.",
    "wof:placetype":"venue"
},
  "geometry": {"coordinates":[4.096496,46.020561],"type":"Point"}
}