{
  "type": "Feature",
  "properties": {
    "iso:country":"FR",
    "sg:address":"19, Rte de Witry, 51100 Reims",
    "sg:orig_category":"Non-Classified Establishments",
    "sg:phone":"+33 3 26 02 05 06",
    "sg:province":"Champagne",
    "wof:name":"Somatem S.a.",
    "wof:placetype":"venue"
},
  "geometry": {"coordinates":[4.054899,49.262104],"type":"Point"}
}