{
  "type": "Feature",
  "properties": {
    "addr:full":"ZAC - Espace de la Motte Vesoul Franche Comt\u00e9 70000",
    "addr:postcode":"70000",
    "addr:street":"Zac Espace De La Motte;Franche Comte\u0301",
    "iso:country":"FR",
    "sg:address":"ZAC - Espace de la Motte",
    "sg:city":"Vesoul",
    "sg:orig_category":"Unclassifiable Establishments",
    "sg:phone":"+33 3 84 75 21 59",
    "sg:postcode":"70000",
    "sg:province":"Franche Comt\u00e9",
    "wof:name":"Emann Fr\u00e8res S.a.r.l.",
    "wof:placetype":"venue"
},
  "geometry": {"coordinates":[6.212135,47.612965],"type":"Point"}
}