{
  "type": "Feature",
  "properties": {
    "addr:full":"20, Esplanade Charles de Gaulle, 92000 Nanterre Ile de France",
    "addr:housenumber":"20",
    "addr:postcode":"92000",
    "addr:street":"Esplanade Charles De Gaulle",
    "iso:country":"FR",
    "sg:address":"20, Esplanade Charles de Gaulle, 92000 Nanterre",
    "sg:orig_category":"Unclassifiable Establishments",
    "sg:phone":"+33 1 42 04 11 33",
    "sg:province":"Ile de France",
    "wof:name":"Godirings S.a.r.l",
    "wof:placetype":"venue"
},
  "geometry": {"coordinates":[2.222522,48.895863],"type":"Point"}
}