{
  "type": "Feature",
  "properties": {
    "addr:full":"64 Cours Carnot Salon De Provence Provence-Alpes-C\u00f4te d'Azur 13300",
    "addr:housenumber":"64",
    "addr:postcode":"13300",
    "addr:street":"Cours Carnot",
    "iso:country":"FR",
    "sg:address":"64 Cours Carnot",
    "sg:city":"Salon De Provence",
    "sg:classifiers":[
        {
            "category":"Banks & Credit Unions",
            "subcategory":"Financial Services",
            "type":"Services"
        }
    ],
    "sg:phone":"+33 4 90 56 21 38",
    "sg:postcode":"13300",
    "sg:province":"Provence-Alpes-C\u00f4te d'Azur",
    "sg:tags":[
        "banking",
        "finance",
        "insurance"
    ],
    "wof:name":"Cabinet Mla Sa",
    "wof:placetype":"venue"
},
  "geometry": {"coordinates":[5.096115,43.641209],"type":"Point"}
}