{
  "type": "Feature",
  "properties": {
    "addr:full":"Rue Du Santerre Zi Nord 80080 Amiens Amiens Picardie 80000",
    "addr:postcode":"80080 amiens;80000",
    "addr:street":"Rue Du Santerre Zi Nord",
    "iso:country":"FR",
    "sg:address":"Rue Du Santerre Zi Nord 80080 Amiens",
    "sg:city":"Amiens",
    "sg:classifiers":[
        {
            "category":"Transit Center",
            "subcategory":"Freight",
            "type":"Transportation"
        }
    ],
    "sg:phone":"+33 3 22 54 63 80",
    "sg:postcode":"80000",
    "sg:province":"Picardie",
    "sg:tags":[
        "metallurgy",
        "pipe",
        "metalworking",
        "sheet"
    ],
    "wof:name":"Friedlander",
    "wof:placetype":"venue"
},
  "geometry": {"coordinates":[2.2913,49.924992],"type":"Point"}
}