{
  "type": "Feature",
  "properties": {
    "addr:full":"B.P. 06, 08370 Margut^^ZI de la Chiers, 08110 Blagny Champagne 08370",
    "addr:postcode":"08370;08110;08370",
    "addr:street":"B.P. 06;Chiers;Champagne",
    "iso:country":"FR",
    "sg:address":"B.P. 06, 08370 Margut^^ZI de la Chiers, 08110 Blagny",
    "sg:orig_category":"Chaudronnerie en acier inoxydable Chaudronnerie, T\u00f4lerie Cisaillage m\u00e9tal Maintenance industrielle M",
    "sg:phone":"+33 3 24 22 61 04",
    "sg:postcode":"08370",
    "sg:province":"Champagne",
    "wof:name":"A.m.c.i. S.a.r.l. - Atelier De M\u00e9canique Et Chaudronnerie Industriell",
    "wof:placetype":"venue"
},
  "geometry": {"coordinates":[5.18032,49.639069],"type":"Point"}
}