{
  "type": "Feature",
  "properties": {
    "iso:country":"FR",
    "sg:address":"Domaine Saint Michel 30129 Manduel",
    "sg:orig_category":"Non-Classified Establishments",
    "sg:phone":"+33 4 66 20 31 25",
    "sg:province":"Languedoc-Roussillon",
    "wof:name":"Hortigard E.a.r.l.",
    "wof:placetype":"venue"
},
  "geometry": {"coordinates":[4.463661,43.819958],"type":"Point"}
}