{
  "type": "Feature",
  "properties": {
    "iso:country":"FR",
    "sg:address":"Rte des Entreprises",
    "sg:city":"Gonfreville l'Orcher",
    "sg:orig_category":"Non-Classified Establishments",
    "sg:phone":"+33 2 35 24 75 30",
    "sg:postcode":"76700",
    "sg:province":"Haute Normandie",
    "wof:name":"Entreprise Philippe Lassarat S.a.",
    "wof:placetype":"venue"
},
  "geometry": {"coordinates":[0.222157,49.482666],"type":"Point"}
}