{
  "type": "Feature",
  "properties": {
    "addr:full":"71 route d'Angers 49124 ST BARTHELEMY D ANJOU Pays de Loire 49124",
    "addr:housenumber":"71",
    "addr:postcode":"49124;49124",
    "addr:street":"Route D'Angers;D",
    "iso:country":"FR",
    "sg:address":"71 route d'Angers 49124 ST BARTHELEMY D ANJOU",
    "sg:orig_category":"Apples, Fresh",
    "sg:phone":"+33 2 41 93 62 30",
    "sg:postcode":"49124",
    "sg:province":"Pays de Loire",
    "wof:name":"Ass Producteurs De Pommes Pour Exportat Sarl",
    "wof:placetype":"venue"
},
  "geometry": {"coordinates":[-0.4666,47.48579],"type":"Point"}
}