{
  "type": "Feature",
  "properties": {
    "iso:country":"FR",
    "sg:address":"10, Rue de Courcelles, 95590 Presles",
    "sg:orig_category":"Unclassifiable Establishments",
    "sg:phone":"+33 1 34 70 09 87",
    "sg:province":"Ile de France",
    "wof:name":"Lohyer",
    "wof:placetype":"venue"
},
  "geometry": {"coordinates":[2.301772,49.105518],"type":"Point"}
}