{
  "type": "Feature",
  "properties": {
    "addr:full":"4 bis, Rue Paul Doumer, 78510 Triel sur Seine Ile de France",
    "addr:housenumber":"4 bis",
    "addr:postcode":"78510",
    "addr:street":"Rue Paul Doumer",
    "iso:country":"FR",
    "sg:address":"4 bis, Rue Paul Doumer, 78510 Triel sur Seine",
    "sg:orig_category":"Unclassifiable Establishments",
    "sg:phone":"+33 1 39 74 72 70",
    "sg:province":"Ile de France",
    "wof:name":"M\u00e9cafondo S.a.r.l.",
    "wof:placetype":"venue"
},
  "geometry": {"coordinates":[2.0097,48.969978],"type":"Point"}
}