{
  "type": "Feature",
  "properties": {
    "addr:full":"2 rue Gustave Nast; Chelles; 77500 Ile de France 77500",
    "addr:housenumber":"2",
    "addr:postcode":"77500 ile;france 77500",
    "addr:street":"Rue Gustave Nast",
    "iso:country":"FR",
    "sg:address":"2 rue Gustave Nast; Chelles; 77500",
    "sg:classifiers":[
        {
            "category":"Banks & Credit Unions",
            "subcategory":"Bank",
            "type":"Services"
        }
    ],
    "sg:phone":"+33 3360209005",
    "sg:postcode":"77500",
    "sg:province":"Ile de France",
    "wof:name":"Sovac",
    "wof:placetype":"venue"
},
  "geometry": {"coordinates":[2.58803,48.879238],"type":"Point"}
}