{
  "type": "Feature",
  "properties": {
    "addr:full":"Rue Aime Et Eugenie Cotton 13200 Arles Rhone-Alpes",
    "addr:postcode":"13200",
    "addr:street":"Rue Aime Et Eugenie Cotton",
    "iso:country":"FR",
    "sg:address":"Rue Aime Et Eugenie Cotton 13200 Arles",
    "sg:classifiers":[
        {
            "category":"Utilities",
            "subcategory":"Electric",
            "type":"Services"
        }
    ],
    "sg:phone":"+33 4 90 93 44 10",
    "sg:province":"Rhone-Alpes",
    "sg:tags":[
        "electricity",
        "electronic",
        "electrical",
        "equipment"
    ],
    "wof:name":"Approvisionnement General Electrique Industriel (agei)",
    "wof:placetype":"venue"
},
  "geometry": {"coordinates":[4.63618,43.704552],"type":"Point"}
}