{
  "type": "Feature",
  "properties": {
    "iso:country":"FR",
    "sg:address":"3 Rue Triolet 60440 P\u00e9roy Les Gombries",
    "sg:classifiers":[
        {
            "category":"Manufacturing",
            "subcategory":"Paper Products",
            "type":"Manufacturing & Wholesale Goods"
        }
    ],
    "sg:phone":"+33 3 44 88 14 64",
    "sg:province":"Picardie",
    "sg:tags":[
        "packaging",
        "material",
        "-",
        "cardboard"
    ],
    "wof:name":"Emballage Industriel De Valognes",
    "wof:placetype":"venue"
},
  "geometry": {"coordinates":[2.847814,49.163147],"type":"Point"}
}