{
  "type": "Feature",
  "properties": {
    "iso:country":"FR",
    "sg:address":"35 rue de Wattignies 59139 Noyelles les Seclin",
    "sg:classifiers":[
        {
            "category":"Food & Beverages",
            "subcategory":"Meat & Fish",
            "type":"Retail Goods"
        }
    ],
    "sg:phone":"+33 3 20 32 47 71",
    "sg:postcode":"59139",
    "sg:province":"Nord Pas-de-Calais",
    "sg:tags":[
        "pie"
    ],
    "wof:name":"Philippe Vancoillie Sarl",
    "wof:placetype":"venue"
},
  "geometry": {"coordinates":[3.026495,50.573868],"type":"Point"}
}