{
  "type": "Feature",
  "properties": {
    "iso:country":"FR",
    "sg:address":"P\u00f4le d'Activit\u00e9 A26",
    "sg:city":"Guignicourt",
    "sg:orig_category":"Non-Classified Establishments",
    "sg:phone":"+33 3 23 79 85 85",
    "sg:postcode":"02190",
    "sg:province":"Picardie",
    "wof:name":"H.d.m. S.a.r.l.",
    "wof:placetype":"venue"
},
  "geometry": {"coordinates":[3.930837,49.431744],"type":"Point"}
}