{
  "type": "Feature",
  "properties": {
    "iso:country":"FR",
    "sg:address":"152, Rue Roger Salengro, 62160 Bully les Mines",
    "sg:orig_category":"Non-Classified Establishments",
    "sg:phone":"+33 3 21 29 12 33",
    "sg:postcode":"62160",
    "sg:province":"Nord Pas-de-Calais",
    "wof:name":"Enfant Du Pays S.a.r.l.",
    "wof:placetype":"venue"
},
  "geometry": {"coordinates":[2.733647,50.447796],"type":"Point"}
}