{
  "type": "Feature",
  "properties": {
    "addr:full":"12, Rue du 8 Mai - ZI du Bord de Mer, 59760 Grande Synthe Nord Pas-de-Calais 59760",
    "addr:housenumber":"12",
    "addr:postcode":"59760;59760",
    "addr:street":"Rue Du 8 Mai Zi Du Bord De Mer;Pas-De-Calais",
    "iso:country":"FR",
    "sg:address":"12, Rue du 8 Mai - ZI du Bord de Mer, 59760 Grande Synthe",
    "sg:orig_category":"Non-Classified Establishments",
    "sg:phone":"+33 3 28 27 27 72",
    "sg:postcode":"59760",
    "sg:province":"Nord Pas-de-Calais",
    "wof:name":"Arc Diffusion S.a.r.l.",
    "wof:placetype":"venue"
},
  "geometry": {"coordinates":[2.30272,51.013069],"type":"Point"}
}