{
  "type": "Feature",
  "properties": {
    "addr:full":"4, Rue du Grand Pr\u00e9 - ZAC Euromoselle Sud, 57140 Norroy le Veneur Lorraine",
    "addr:housenumber":"4;veneur",
    "addr:postcode":"57140 norroy le",
    "addr:street":"Rue Du Grand Pre\u0301 Zac Euromoselle Sud",
    "iso:country":"FR",
    "sg:address":"4, Rue du Grand Pr\u00e9 - ZAC Euromoselle Sud, 57140 Norroy le Veneur",
    "sg:orig_category":"Non-Classified Establishments",
    "sg:phone":"+33 3 87 51 11 93",
    "sg:province":"Lorraine",
    "wof:name":"Net Services Air S.a.r.l.",
    "wof:placetype":"venue"
},
  "geometry": {"coordinates":[6.150305,49.15131],"type":"Point"}
}