{
  "type": "Feature",
  "properties": {
    "addr:full":"6, Rue de la Douane, 54000 Nancy Lorraine 54000",
    "addr:housenumber":"6",
    "addr:postcode":"54000;54000",
    "addr:street":"Rue De La Douane",
    "iso:country":"FR",
    "sg:address":"6, Rue de la Douane, 54000 Nancy",
    "sg:orig_category":"Non-Classified Establishments",
    "sg:phone":"+33 3 83 32 37 94",
    "sg:postcode":"54000",
    "sg:province":"Lorraine",
    "wof:name":"C.p.i.h. S.a.r.l. - Centre De Protection Industrielle De L'habitat",
    "wof:placetype":"venue"
},
  "geometry": {"coordinates":[6.204765,48.683868],"type":"Point"}
}