{
  "type": "Feature",
  "properties": {
    "iso:country":"FR",
    "sg:address":"30 Bd De La Liane 62360 St L\u00e9onard",
    "sg:classifiers":[
        {
            "category":"Wholesale",
            "subcategory":"Machinery & Supplies",
            "type":"Manufacturing & Wholesale Goods"
        }
    ],
    "sg:phone":"+33 3 21 80 50 24",
    "sg:province":"Nord Pas-de-Calais",
    "sg:tags":[
        "equipment",
        "optical",
        "precision",
        "instrument"
    ],
    "wof:name":"Minolta France",
    "wof:placetype":"venue"
},
  "geometry": {"coordinates":[1.61692,50.690121],"type":"Point"}
}