{
  "type": "Feature",
  "properties": {
    "addr:full":"106, Rue Gabriel P\u00e9ri, 78800 Houilles Ile de France",
    "addr:housenumber":"106",
    "addr:postcode":"78800;ile",
    "addr:street":"Rue Gabriel Pe\u0301Ri",
    "iso:country":"FR",
    "sg:address":"106, Rue Gabriel P\u00e9ri, 78800 Houilles",
    "sg:orig_category":"Unclassifiable Establishments",
    "sg:phone":"+33 1 39 68 41 01",
    "sg:province":"Ile de France",
    "wof:name":"E.r.e.p. S.a.r.l. - Etudes R\u00e9alisations Emballages Plastiques",
    "wof:placetype":"venue"
},
  "geometry": {"coordinates":[2.195208,48.924915],"type":"Point"}
}