{
  "type": "Feature",
  "properties": {
    "addr:full":"120, Av. Ledru Rollin, 75011 Paris Ile de France",
    "addr:postcode":"75011",
    "addr:street":"120 Av. Ledru Rollin",
    "iso:country":"FR",
    "sg:address":"120, Av. Ledru Rollin, 75011 Paris",
    "sg:orig_category":"Non-Classified Establishments",
    "sg:phone":"+33 1 48 05 25 80",
    "sg:province":"Ile de France",
    "wof:name":"Fouasse S.a.",
    "wof:placetype":"venue"
},
  "geometry": {"coordinates":[2.377691,48.853519],"type":"Point"}
}