{
  "type": "Feature",
  "properties": {
    "iso:country":"FR",
    "sg:address":"Rte De Dinard 22100 Taden",
    "sg:city":"Taden",
    "sg:classifiers":[
        {
            "category":"Bakery",
            "type":"Food & Drink"
        }
    ],
    "sg:phone":"+33 2 96 87 13 01",
    "sg:postcode":"22100",
    "sg:province":"Bretagne",
    "sg:tags":[
        "cake",
        "product",
        "related",
        "bread"
    ],
    "wof:name":"Les Gavottes",
    "wof:placetype":"venue"
},
  "geometry": {"coordinates":[-2.064859,48.390835],"type":"Point"}
}