{
  "type": "Feature",
  "properties": {
    "addr:full":"B.P. 268, 38433 Echirolles C\u00e9dex^^113, Av. de la R\u00e9publique, 38130 Echirolles Rhone-Alpes 38130",
    "addr:housenumber":"b.p. 268",
    "addr:postcode":"38433;38130;38130",
    "addr:street":"Av. De La Re\u0301Publique;Rhone-Alpes",
    "iso:country":"FR",
    "sg:address":"B.P. 268, 38433 Echirolles C\u00e9dex^^113, Av. de la R\u00e9publique, 38130 Echirolles",
    "sg:orig_category":"Non-Classified Establishments",
    "sg:phone":"+33 4 76 23 01 18",
    "sg:postcode":"38130",
    "sg:province":"Rhone-Alpes",
    "wof:name":"Karting S.a.",
    "wof:placetype":"venue"
},
  "geometry": {"coordinates":[5.7194,45.149536],"type":"Point"}
}