{
  "type": "Feature",
  "properties": {
    "iso:country":"FR",
    "sg:address":"18BIS rue du Rond Buisson 25000 BESANCON",
    "sg:classifiers":[
        {
            "category":"Shopping Center",
            "type":"Public Place"
        }
    ],
    "sg:phone":"+33 3 81 50 40 24",
    "sg:postcode":"25000",
    "sg:province":"Franche Comt\u00e9",
    "sg:tags":[
        "case",
        "clock"
    ],
    "wof:name":"St\u00e9 Nouvelle Union Bisontine De Monteu De Boites S.a.r.l.",
    "wof:placetype":"venue"
},
  "geometry": {"coordinates":[6.055213,47.265781],"type":"Point"}
}