{
  "type": "Feature",
  "properties": {
    "iso:country":"FR",
    "sg:address":"22, Rte de Gallerie, 41700 Cour Cheverny",
    "sg:city":"Cheverny",
    "sg:orig_category":"Non-Classified Establishments",
    "sg:phone":"+33 2 54 79 95 89",
    "sg:postcode":"41700",
    "sg:province":"Centre",
    "wof:name":"Pierre Fribourg S.a.s.",
    "wof:placetype":"venue"
},
  "geometry": {"coordinates":[1.43052,47.520111],"type":"Point"}
}