{
  "type": "Feature",
  "properties": {
    "iso:country":"FR",
    "sg:address":"34 boulevard des Italiens 75009 Paris",
    "sg:classifiers":[
        {
            "category":"Shopping",
            "subcategory":"Pharmacy",
            "type":"Retail Goods"
        }
    ],
    "sg:phone":"+33 1 69 79 95 00",
    "sg:province":"Ile de France",
    "sg:tags":[
        "preparation",
        "pharmaceutical"
    ],
    "wof:name":"Pharmajet Sa",
    "wof:placetype":"venue"
},
  "geometry": {"coordinates":[2.335173,48.871311],"type":"Point"}
}