{
  "type": "Feature",
  "properties": {
    "addr:full":"B.P. 117, 59471 Seclin C\u00e9dex^^Rue du Rouge Bouton - ZI B, 59113 Seclin Nord Pas-de-Calais",
    "addr:housenumber":"b.p. 117;b",
    "addr:postcode":"59471;59113",
    "iso:country":"FR",
    "sg:address":"B.P. 117, 59471 Seclin C\u00e9dex^^Rue du Rouge Bouton - ZI B, 59113 Seclin",
    "sg:orig_category":"Non-Classified Establishments",
    "sg:phone":"+33 3 20 32 37 37",
    "sg:province":"Nord Pas-de-Calais",
    "wof:name":"Vandenostende S.a.",
    "wof:placetype":"venue"
},
  "geometry": {"coordinates":[3.026865,50.54681],"type":"Point"}
}