{
  "type": "Feature",
  "properties": {
    "addr:full":"168 Avenue Henri Falcoz 73300 St Jean De Maurienne Rhone-Alpes 73300",
    "addr:housenumber":"168",
    "addr:postcode":"73300;73300",
    "addr:street":"Avenue Henri Falcoz;Rhone-Alpes",
    "iso:country":"FR",
    "sg:address":"168 Avenue Henri Falcoz 73300 St Jean De Maurienne",
    "sg:classifiers":[
        {
            "category":"Professional",
            "subcategory":"Printing & Photocopies",
            "type":"Services"
        }
    ],
    "sg:phone":"+33 4 79 59 97 63",
    "sg:postcode":"73300",
    "sg:province":"Rhone-Alpes",
    "sg:tags":[
        "publishing"
    ],
    "wof:name":"Societe D'edition Du Journal La Maurienne",
    "wof:placetype":"venue"
},
  "geometry": {"coordinates":[6.348244,45.277149],"type":"Point"}
}