{
  "type": "Feature",
  "properties": {
    "iso:country":"FR",
    "sg:address":"26 chemin de la Croix 74600 Seynod",
    "sg:classifiers":[
        {
            "category":"Government",
            "subcategory":"Fire Station",
            "type":"Public Place"
        }
    ],
    "sg:phone":"+33 4 50 69 17 25",
    "sg:province":"Rhone-Alpes",
    "sg:tags":[
        "leather",
        "watch",
        "strap"
    ],
    "wof:name":"Z.r.c. Sa",
    "wof:placetype":"venue"
},
  "geometry": {"coordinates":[6.077439,45.888168],"type":"Point"}
}