{
  "type": "Feature",
  "properties": {
    "iso:country":"FR",
    "sg:address":"1, Rue du Duc de Guise, 28500 Vernouillet",
    "sg:city":"Vernouillet",
    "sg:orig_category":"Non-Classified Establishments",
    "sg:phone":"+33 2 37 42 81 61",
    "sg:postcode":"28500",
    "sg:province":"Centre",
    "wof:name":"E.m.e.l. S.a.r.l.",
    "wof:placetype":"venue"
},
  "geometry": {"coordinates":[1.379511,48.715248],"type":"Point"}
}