{
  "type": "Feature",
  "properties": {
    "iso:country":"FR",
    "sg:address":"25, Rue des Moulineaux, 59300 Valenciennes",
    "sg:orig_category":"Non-Classified Establishments",
    "sg:phone":"+33 3 27 21 58 58",
    "sg:province":"Nord Pas-de-Calais",
    "wof:name":"Valarep",
    "wof:placetype":"venue"
},
  "geometry": {"coordinates":[3.52126,50.35828],"type":"Point"}
}