{
  "type": "Feature",
  "properties": {
    "addr:full":"Rte de Beire le Fort Genlis Bourgogne 21110",
    "addr:postcode":"21110",
    "addr:street":"Rte De Beire Le;Bourgogne",
    "iso:country":"FR",
    "sg:address":"Rte de Beire le Fort",
    "sg:city":"Genlis",
    "sg:orig_category":"Unclassifiable Establishments",
    "sg:phone":"+33 3 80 47 28 28",
    "sg:postcode":"21110",
    "sg:province":"Bourgogne",
    "wof:name":"Bergerat Monnoyeur S.a.s.",
    "wof:placetype":"venue"
},
  "geometry": {"coordinates":[5.220228,47.241528],"type":"Point"}
}