{
  "type": "Feature",
  "properties": {
    "addr:full":"2, Rte de Tilly, 14400 Bayeux Bayeux Basse Normandie 14400",
    "addr:housenumber":"2",
    "addr:postcode":"14400;14400",
    "addr:street":"Rte De Tilly",
    "iso:country":"FR",
    "sg:address":"2, Rte de Tilly, 14400 Bayeux",
    "sg:city":"Bayeux",
    "sg:orig_category":"Unclassifiable Establishments",
    "sg:phone":"+33 2 31 51 42 00",
    "sg:postcode":"14400",
    "sg:province":"Basse Normandie",
    "wof:name":"Prodis Maison Johanes Boub\u00e9e S.a.s.",
    "wof:placetype":"venue"
},
  "geometry": {"coordinates":[-0.697118,49.269768],"type":"Point"}
}