{
  "type": "Feature",
  "properties": {
    "iso:country":"FR",
    "sg:address":"3, Rue Dampierre, 59100 Roubaix",
    "sg:orig_category":"Unclassifiable Establishments",
    "sg:phone":"+33 3 20 20 70 00",
    "sg:province":"Nord Pas-de-Calais",
    "wof:name":"Eurindus S.a.",
    "wof:placetype":"venue"
},
  "geometry": {"coordinates":[3.196222,50.692558],"type":"Point"}
}