{
  "type": "Feature",
  "properties": {
    "addr:full":"3, Rue Dampierre, 59100 Roubaix Nord Pas-de-Calais",
    "addr:housenumber":"3",
    "addr:postcode":"59100",
    "addr:street":"Rue Dampierre",
    "iso:country":"FR",
    "sg:address":"3, Rue Dampierre, 59100 Roubaix",
    "sg:orig_category":"Unclassifiable Establishments",
    "sg:phone":"+33 3 20 20 70 00",
    "sg:province":"Nord Pas-de-Calais",
    "wof:name":"Eurindus S.a.",
    "wof:placetype":"venue"
},
  "geometry": {"coordinates":[3.196222,50.692558],"type":"Point"}
}