{
  "type": "Feature",
  "properties": {
    "addr:full":"1327 Av De La Houille Blanche 73000 Chamb\u00e9ry Rhone-Alpes 73000",
    "addr:housenumber":"1327",
    "addr:postcode":"73000;73000",
    "addr:street":"Av De La Houille Blanche",
    "iso:country":"FR",
    "sg:address":"1327 Av De La Houille Blanche 73000 Chamb\u00e9ry",
    "sg:classifiers":[
        {
            "category":"Professional",
            "type":"Services"
        }
    ],
    "sg:phone":"+33 4 79 75 80 80",
    "sg:postcode":"73000",
    "sg:province":"Rhone-Alpes",
    "sg:tags":[
        "transport",
        "road"
    ],
    "wof:name":"Societe Auxiliaire De Transport Et De Materiel (satm) Garage Station Service",
    "wof:placetype":"venue"
},
  "geometry": {"coordinates":[5.890109,45.587933],"type":"Point"}
}