{
  "type": "Feature",
  "properties": {
    "addr:full":"3 rue Malakoff; Grenoble; 38001 Grenoble Rhone-Alpes 38100",
    "addr:housenumber":"3",
    "addr:postcode":"38001;38100",
    "addr:street":"Rue Malakoff",
    "iso:country":"FR",
    "sg:address":"3 rue Malakoff; Grenoble; 38001",
    "sg:city":"Grenoble",
    "sg:classifiers":[
        {
            "category":"Banks & Credit Unions",
            "subcategory":"Bank",
            "type":"Services"
        }
    ],
    "sg:phone":"+33 4 76 63 78 00",
    "sg:postcode":"38100",
    "sg:province":"Rhone-Alpes",
    "wof:name":"Natexis Groupe",
    "wof:placetype":"venue"
},
  "geometry": {"coordinates":[5.739324,45.188847],"type":"Point"}
}