{
  "type": "Feature",
  "properties": {
    "addr:full":"198, Chemin des Eucalyptus, 06600 Antibes Provence-Alpes-C\u00f4te d'Azur",
    "addr:housenumber":"198",
    "addr:postcode":"06600",
    "addr:street":"Chemin Des Eucalyptus",
    "iso:country":"FR",
    "sg:address":"198, Chemin des Eucalyptus, 06600 Antibes",
    "sg:orig_category":"Unclassifiable Establishments",
    "sg:phone":"+33 4 93 33 63 09",
    "sg:province":"Provence-Alpes-C\u00f4te d'Azur",
    "wof:name":"Gagneraud Construction S.a.s.",
    "wof:placetype":"venue"
},
  "geometry": {"coordinates":[7.10839,43.590439],"type":"Point"}
}