{
  "type": "Feature",
  "properties": {
    "addr:full":"10 Rue N D De Nazareth 75003 Paris Ile de France 75003",
    "addr:housenumber":"10",
    "addr:postcode":"75003;75003",
    "addr:street":"Rue N D De Nazareth",
    "iso:country":"FR",
    "sg:address":"10 Rue N D De Nazareth 75003 Paris",
    "sg:classifiers":[
        {
            "category":"Shopping",
            "subcategory":"Clothing, Apparel, & Fashions",
            "type":"Retail Goods"
        }
    ],
    "sg:phone":"+33 1 48 87 98 74",
    "sg:postcode":"75003",
    "sg:province":"Ile de France",
    "sg:tags":[
        "textile",
        "clothing",
        "clothes"
    ],
    "wof:name":"Spontini Diffusion",
    "wof:placetype":"venue"
},
  "geometry": {"coordinates":[2.36455,48.864704],"type":"Point"}
}