{
  "type": "Feature",
  "properties": {
    "addr:full":"Quartier Beausseret Mont\u00e9limar Rhone-Alpes 26200",
    "addr:postcode":"26200",
    "iso:country":"FR",
    "sg:address":"Quartier Beausseret",
    "sg:city":"Mont\u00e9limar",
    "sg:orig_category":"Non-Classified Establishments",
    "sg:phone":"+33 4 75 01 62 77",
    "sg:postcode":"26200",
    "sg:province":"Rhone-Alpes",
    "wof:name":"Entreprise Sillac S.a.r.l.",
    "wof:placetype":"venue"
},
  "geometry": {"coordinates":[4.78244,44.574463],"type":"Point"}
}