{
  "type": "Feature",
  "properties": {
    "iso:country":"FR",
    "sg:address":"21, Av. Montaigne, 75008 Paris",
    "sg:orig_category":"Unclassifiable Establishments",
    "sg:phone":"+33 1 47 20 95 05",
    "sg:province":"Ile de France",
    "wof:name":"G.i.p. S.a. - Groupement Immobilier En Placement",
    "wof:placetype":"venue"
},
  "geometry": {"coordinates":[2.303937,48.866096],"type":"Point"}
}