{
  "type": "Feature",
  "properties": {
    "addr:full":"2, All\u00e9e Fran\u00e7ois Cevert, 91310 Linas Ile de France",
    "addr:housenumber":"2",
    "addr:postcode":"91310;ile",
    "addr:street":"Alle\u0301E Franc\u0327Ois Cevert",
    "iso:country":"FR",
    "sg:address":"2, All\u00e9e Fran\u00e7ois Cevert, 91310 Linas",
    "sg:orig_category":"Unclassifiable Establishments",
    "sg:phone":"+33 1 42 97 27 27",
    "sg:province":"Ile de France",
    "wof:name":"Process Consult S.a.r.l.",
    "wof:placetype":"venue"
},
  "geometry": {"coordinates":[2.258532,48.628574],"type":"Point"}
}