{
  "type": "Feature",
  "properties": {
    "iso:country":"FR",
    "sg:address":"89, Av. du Progr\u00e9s, 69680 Chassieu",
    "sg:orig_category":"Unclassifiable Establishments",
    "sg:phone":"+33 4 78 90 02 62",
    "sg:postcode":"69680",
    "sg:province":"Rhone-Alpes",
    "wof:name":"Seltra S.a.",
    "wof:placetype":"venue"
},
  "geometry": {"coordinates":[4.963106,45.725864],"type":"Point"}
}