{
  "type": "Feature",
  "properties": {
    "addr:full":"28 Route De Corbeil Ste Genevi\u00e8ve Des Bois Ile de France 91700",
    "addr:housenumber":"28",
    "addr:postcode":"91700",
    "addr:street":"Route De Corbeil Ste Genevie\u0300Ve Des Bois Ile De France",
    "iso:country":"FR",
    "sg:address":"28 Route De Corbeil",
    "sg:city":"Ste Genevi\u00e8ve Des Bois",
    "sg:classifiers":[
        {
            "category":"Banks & Credit Unions",
            "subcategory":"Financial Services",
            "type":"Services"
        }
    ],
    "sg:phone":"+33 1 69 04 33 90",
    "sg:postcode":"91700",
    "sg:province":"Ile de France",
    "sg:tags":[
        "banking",
        "finance",
        "insurance"
    ],
    "wof:name":"Assouline Elie",
    "wof:placetype":"venue"
},
  "geometry": {"coordinates":[2.336098,48.648918],"type":"Point"}
}