{
  "type": "Feature",
  "properties": {
    "iso:country":"FR",
    "sg:address":"5, Av. Saint Denis - ZI de l'Hippodrome, 29000 Quimper",
    "sg:city":"Quimper",
    "sg:orig_category":"Unclassifiable Establishments",
    "sg:phone":"+33 2 98 64 43 43",
    "sg:postcode":"29000",
    "sg:province":"Bretagne",
    "wof:name":"Le Goff Habitat S.a.",
    "wof:placetype":"venue"
},
  "geometry": {"coordinates":[-4.078345,47.996113],"type":"Point"}
}