{
  "type": "Feature",
  "properties": {
    "addr:full":"ZA Domagne Ceyz\u00e9riat Rhone-Alpes 01250",
    "addr:postcode":"01250",
    "addr:street":"Za Domagne;Rhone-Alpes",
    "iso:country":"FR",
    "sg:address":"ZA Domagne",
    "sg:city":"Ceyz\u00e9riat",
    "sg:orig_category":"Unclassifiable Establishments",
    "sg:phone":"+33 4 74 30 02 14",
    "sg:postcode":"01250",
    "sg:province":"Rhone-Alpes",
    "wof:name":"Pierre Chichoux S.a.r.l.",
    "wof:placetype":"venue"
},
  "geometry": {"coordinates":[5.324115,46.178776],"type":"Point"}
}