{
  "type": "Feature",
  "properties": {
    "iso:country":"FR",
    "sg:address":"3 rue de Fos sur Mer 69007 Lyon",
    "sg:classifiers":[
        {
            "category":"Utilities",
            "subcategory":"Recycling",
            "type":"Services"
        }
    ],
    "sg:phone":"+33 4 78 72 43 96",
    "sg:postcode":"69007",
    "sg:province":"Rhone-Alpes",
    "sg:tags":[
        "metal"
    ],
    "wof:name":"Recyclage Des Metaux Sa",
    "wof:placetype":"venue"
},
  "geometry": {"coordinates":[4.840141,45.724743],"type":"Point"}
}