{
  "type": "Feature",
  "properties": {
    "addr:full":"B.P. 54, 63015 Clermont Ferrand C\u00e9dex^^5, Rue Newton - ZI du Br\u00e9zet Saint Jean, 63000 Clermont Ferra Clermont-Ferrand Auvergne 63000",
    "addr:postcode":"63015;63000;63000",
    "addr:street":"B.P. 54;Rue Newton Zi Du Bre\u0301Zet Saint Jean",
    "iso:country":"FR",
    "sg:address":"B.P. 54, 63015 Clermont Ferrand C\u00e9dex^^5, Rue Newton - ZI du Br\u00e9zet Saint Jean, 63000 Clermont Ferra",
    "sg:city":"Clermont-Ferrand",
    "sg:orig_category":"Non-Classified Establishments",
    "sg:phone":"+33 4 73 98 08 58",
    "sg:postcode":"63000",
    "sg:province":"Auvergne",
    "wof:name":"Varenne Et Fils S.a.",
    "wof:placetype":"venue"
},
  "geometry": {"coordinates":[3.127243,45.786507],"type":"Point"}
}