{
  "type": "Feature",
  "properties": {
    "addr:full":"38730 Panissage Rhone-Alpes 38730",
    "addr:postcode":"38730;38730",
    "addr:street":"Rhone-Alpes",
    "iso:country":"FR",
    "sg:address":"38730 Panissage",
    "sg:classifiers":[
        {
            "category":"Food & Beverages",
            "subcategory":"Dairy",
            "type":"Retail Goods"
        }
    ],
    "sg:phone":"+33 4 74 88 27 66",
    "sg:postcode":"38730",
    "sg:province":"Rhone-Alpes",
    "sg:tags":[
        "product",
        "related"
    ],
    "wof:name":"Fruitiere De Domessin",
    "wof:placetype":"venue"
},
  "geometry": {"coordinates":[5.47112,45.490135],"type":"Point"}
}