{
  "type": "Feature",
  "properties": {
    "iso:country":"FR",
    "sg:address":"B.P. 189, 62304 Lens C\u00e9dex^^Parc d'Activit\u00e9s de Bois Rigault, 62300 Lens",
    "sg:orig_category":"Non-Classified Establishments",
    "sg:phone":"+33 3 21 28 00 48",
    "sg:province":"Nord Pas-de-Calais",
    "wof:name":"Soci\u00e9t\u00e9 Nouvelle S.t.r.a.s. S.a. - Soci\u00e9t\u00e9 De Travaux Routiers Et D'am\u00e9nagements Des Sols",
    "wof:placetype":"venue"
},
  "geometry": {"coordinates":[2.81767,50.436279],"type":"Point"}
}