{
  "type": "Feature",
  "properties": {
    "addr:full":"B.P. 90, 92112 Clichy^^24, Rue Villeneuve, 92110 Clichy Ile de France",
    "addr:postcode":"92112;92110",
    "addr:street":"B.P. 90;Rue Villeneuve;Ile De France",
    "iso:country":"FR",
    "sg:address":"B.P. 90, 92112 Clichy^^24, Rue Villeneuve, 92110 Clichy",
    "sg:orig_category":"Non-Classified Establishments",
    "sg:phone":"+33 1 41 06 40 00",
    "sg:province":"Ile de France",
    "wof:name":"Rest' Agraf S.a.",
    "wof:placetype":"venue"
},
  "geometry": {"coordinates":[2.30511,48.902859],"type":"Point"}
}