{
  "type": "Feature",
  "properties": {
    "iso:country":"FR",
    "sg:address":"39, Bd de la Muette, 95140 Garges l\u00e8s Gonesse",
    "sg:orig_category":"Unclassifiable Establishments",
    "sg:phone":"+33 1 39 86 96 20",
    "sg:province":"Ile de France",
    "wof:name":"Mi\u00e8ge Et Piollet S.a.",
    "wof:placetype":"venue"
},
  "geometry": {"coordinates":[2.414863,48.976509],"type":"Point"}
}