{
  "type": "Feature",
  "properties": {
    "addr:full":"B.P. 66, 67402 Illkirch Graffenstaden C\u00e9dex^^Parc d'Innovation Technologique, 67400 Illkirch Graffen Geispolsheim Alsace 67400",
    "addr:postcode":"67402;technologique 67400;67400",
    "addr:street":"B.P. 66",
    "iso:country":"FR",
    "sg:address":"B.P. 66, 67402 Illkirch Graffenstaden C\u00e9dex^^Parc d'Innovation Technologique, 67400 Illkirch Graffen",
    "sg:city":"Geispolsheim",
    "sg:orig_category":"Non-Classified Establishments",
    "sg:phone":"+33 3 90 40 09 99",
    "sg:postcode":"67400",
    "sg:province":"Alsace",
    "wof:name":"Baeurer S.a.",
    "wof:placetype":"venue"
},
  "geometry": {"coordinates":[7.695823,48.531391],"type":"Point"}
}