{
  "type": "Feature",
  "properties": {
    "addr:full":"B.P. 945, 84092 Avignon C\u00e9dex 9^^730, Rte des Remouleurs, 84000 Avignon Provence-Alpes-C\u00f4te d'Azur",
    "addr:housenumber":"b.p. 945;9 ^ ^ 730",
    "addr:postcode":"84092;84000",
    "addr:street":"Ce\u0301Dex;Rte Des Remouleurs",
    "iso:country":"FR",
    "sg:address":"B.P. 945, 84092 Avignon C\u00e9dex 9^^730, Rte des Remouleurs, 84000 Avignon",
    "sg:orig_category":"Non-Classified Establishments",
    "sg:phone":"+33 4 66 39 00 92",
    "sg:province":"Provence-Alpes-C\u00f4te d'Azur",
    "wof:name":"Ovostar S.a.",
    "wof:placetype":"venue"
},
  "geometry": {"coordinates":[4.806015,43.948753],"type":"Point"}
}