{
  "type": "Feature",
  "properties": {
    "iso:country":"FR",
    "sg:address":"3/5, Rue Marie Curie - ZI Pariwest, 78310 Maurepas",
    "sg:orig_category":"Unclassifiable Establishments",
    "sg:phone":"+33 1 30 66 06 06",
    "sg:province":"Ile de France",
    "wof:name":"Air Products S.a.",
    "wof:placetype":"venue"
},
  "geometry": {"coordinates":[1.944855,48.761749],"type":"Point"}
}