{
  "type": "Feature",
  "properties": {
    "addr:full":"Zi Du Bray Rte De Mayenne 53600 Evron Pays de Loire 53600",
    "addr:postcode":"53600;53600",
    "addr:street":"Zi Du Bray Rte De Mayenne;Evron",
    "iso:country":"FR",
    "sg:address":"Zi Du Bray Rte De Mayenne 53600 Evron",
    "sg:classifiers":[
        {
            "category":"Farming",
            "subcategory":"Livestock Farm",
            "type":"Manufacturing & Wholesale Goods"
        }
    ],
    "sg:phone":"+33 2 43 01 25 70",
    "sg:postcode":"53600",
    "sg:province":"Pays de Loire",
    "sg:tags":[
        "breeding",
        "agriculture",
        "animal"
    ],
    "wof:name":"Cooperative Des Agriculteurs De La Mayenne (cam)",
    "wof:placetype":"venue"
},
  "geometry": {"coordinates":[-0.394527,48.153019],"type":"Point"}
}