{
  "type": "Feature",
  "properties": {
    "addr:full":"20 Avenue Benezits 13720 La Bouilladisse Centre",
    "addr:housenumber":"20;13720;bouilladisse",
    "addr:street":"Avenue Benezits",
    "iso:country":"FR",
    "sg:address":"20 Avenue Benezits 13720 La Bouilladisse",
    "sg:classifiers":[
        {
            "category":"Shopping",
            "subcategory":"Luggage & Leather Goods",
            "type":"Retail Goods"
        }
    ],
    "sg:phone":"+33 4 42 62 97 33",
    "sg:province":"Centre",
    "sg:tags":[
        "shoe"
    ],
    "wof:name":"Meger (societe D'exploitation Des Chaussures) Sarl",
    "wof:placetype":"venue"
},
  "geometry": {"coordinates":[5.586925,43.401974],"type":"Point"}
}