{
  "type": "Feature",
  "properties": {
    "addr:full":"9, Chemin du Vieux Ch\u00eane, 38240 Meylan Rhone-Alpes 38240",
    "addr:housenumber":"9",
    "addr:postcode":"38240;38240",
    "addr:street":"Chemin Du Vieux Che\u0302Ne",
    "iso:country":"FR",
    "sg:address":"9, Chemin du Vieux Ch\u00eane, 38240 Meylan",
    "sg:orig_category":"Non-Classified Establishments",
    "sg:phone":"+33 4 76 61 63 70",
    "sg:postcode":"38240",
    "sg:province":"Rhone-Alpes",
    "wof:name":"S\u00e9curitas S.a.r.l.",
    "wof:placetype":"venue"
},
  "geometry": {"coordinates":[5.784548,45.207184],"type":"Point"}
}