{
  "type": "Feature",
  "properties": {
    "addr:full":"54 Avenue Aristide Briand 80320 Chaulnes Picardie 80320",
    "addr:housenumber":"54",
    "addr:postcode":"80320;80320",
    "addr:street":"Avenue Aristide Briand",
    "iso:country":"FR",
    "sg:address":"54 Avenue Aristide Briand 80320 Chaulnes",
    "sg:classifiers":[
        {
            "category":"Utilities",
            "subcategory":"Electric",
            "type":"Services"
        }
    ],
    "sg:phone":"+33 3 22 85 40 49",
    "sg:postcode":"80320",
    "sg:province":"Picardie",
    "sg:tags":[
        "electricity",
        "electronic",
        "electrical",
        "equipment"
    ],
    "wof:name":"Moret Sa",
    "wof:placetype":"venue"
},
  "geometry": {"coordinates":[2.805051,49.814415],"type":"Point"}
}