{
  "type": "Feature",
  "properties": {
    "iso:country":"FR",
    "sg:address":"157 Av Charles De Gaulle 92200 Neuilly Sur Seine",
    "sg:classifiers":[
        {
            "category":"Travel",
            "subcategory":"Hotels & Motels",
            "type":"Entertainment"
        }
    ],
    "sg:phone":"+33 1 41 92 30 00",
    "sg:postcode":"92200",
    "sg:province":"Ile de France",
    "sg:tags":[
        "hotels",
        "business",
        "restaurant"
    ],
    "wof:name":"Groupe Flo",
    "wof:placetype":"venue"
},
  "geometry": {"coordinates":[2.263762,48.883278],"type":"Point"}
}