{
  "type": "Feature",
  "properties": {
    "iso:country":"FR",
    "sg:address":"5, Chemin Carrosse, 31400 Toulouse",
    "sg:orig_category":"Unclassifiable Establishments",
    "sg:phone":"+33 5 61 20 35 63",
    "sg:province":"Midi Pyr\u00e9n\u00e9es",
    "wof:name":"Etablissements San\u00e8gre S.a.",
    "wof:placetype":"venue"
},
  "geometry": {"coordinates":[1.481349,43.574387],"type":"Point"}
}