{
  "type": "Feature",
  "properties": {
    "addr:full":"117 Bd De S\u00e8bastopol 75002 Paris Ile de France 75002",
    "addr:housenumber":"117",
    "addr:postcode":"75002;75002",
    "addr:street":"Bd De Se\u0300Bastopol",
    "iso:country":"FR",
    "sg:address":"117 Bd De S\u00e8bastopol 75002 Paris",
    "sg:classifiers":[
        {
            "category":"Shopping",
            "subcategory":"Clothing, Apparel, & Fashions",
            "type":"Retail Goods"
        }
    ],
    "sg:phone":"+33 1 40 26 40 40",
    "sg:postcode":"75002",
    "sg:province":"Ile de France",
    "sg:tags":[
        "textile",
        "clothing",
        "clothes"
    ],
    "wof:name":"Ludmilla B Sarl",
    "wof:placetype":"venue"
},
  "geometry": {"coordinates":[2.353017,48.867317],"type":"Point"}
}