{
  "type": "Feature",
  "properties": {
    "addr:full":"Avenue Emile Machet Za La Prairie 73350 Bozel Rhone-Alpes 73350",
    "addr:postcode":"73350;73350",
    "addr:street":"Avenue Emile Machet Za La Prairie;Rhone-Alpes",
    "iso:country":"FR",
    "sg:address":"Avenue Emile Machet Za La Prairie 73350 Bozel",
    "sg:classifiers":[
        {
            "category":"Manufacturing",
            "subcategory":"Metals",
            "type":"Manufacturing & Wholesale Goods"
        }
    ],
    "sg:phone":"+33 4 79 22 15 15",
    "sg:postcode":"73350",
    "sg:province":"Rhone-Alpes",
    "sg:tags":[
        "metallurgy",
        "metalworking"
    ],
    "wof:name":"Atelier De Metallerie De Bozel Amb",
    "wof:placetype":"venue"
},
  "geometry": {"coordinates":[6.695495,45.454071],"type":"Point"}
}