{
  "type": "Feature",
  "properties": {
    "addr:full":"Rte de Valanjou Champ sur Layon Pays de Loire 49380",
    "addr:postcode":"49380",
    "addr:street":"Rte De Valanjou Champ Sur Layon Pays",
    "iso:country":"FR",
    "sg:address":"Rte de Valanjou",
    "sg:city":"Champ sur Layon",
    "sg:orig_category":"Non-Classified Establishments",
    "sg:phone":"+33 2 41 78 64 40",
    "sg:postcode":"49380",
    "sg:province":"Pays de Loire",
    "wof:name":"Herb'atlantic S.a.",
    "wof:placetype":"venue"
},
  "geometry": {"coordinates":[-0.499644,47.238811],"type":"Point"}
}