{
  "type": "Feature",
  "properties": {
    "addr:full":"3 Rue De Chatillon 51700 Binson Et Orquigny Champagne 51700",
    "addr:housenumber":"3",
    "addr:postcode":"51700;51700",
    "addr:street":"Rue De Chatillon;Champagne",
    "iso:country":"FR",
    "sg:address":"3 Rue De Chatillon 51700 Binson Et Orquigny",
    "sg:classifiers":[
        {
            "category":"Food Court",
            "type":"Food & Drink"
        }
    ],
    "sg:phone":"+33 3 26 58 33 23",
    "sg:postcode":"51700",
    "sg:province":"Champagne",
    "sg:tags":[
        "product",
        "related"
    ],
    "wof:name":"Sarl Champagne Godinat Et Fils",
    "wof:placetype":"venue"
},
  "geometry": {"coordinates":[3.786175,49.093182],"type":"Point"}
}