{
  "type": "Feature",
  "properties": {
    "addr:full":"14, Av. de Royat, 63400 Chamali\u00e9re Chamali\u00e8res Auvergne 63400",
    "addr:postcode":"63400;63400",
    "addr:street":"14 Av. De Royat",
    "iso:country":"FR",
    "sg:address":"14, Av. de Royat, 63400 Chamali\u00e9re",
    "sg:city":"Chamali\u00e8res",
    "sg:orig_category":"Non-Classified Establishments",
    "sg:phone":"+33 4 73 37 92 00",
    "sg:postcode":"63400",
    "sg:province":"Auvergne",
    "wof:name":"Hibon S.a.s.",
    "wof:placetype":"venue"
},
  "geometry": {"coordinates":[3.071341,45.776272],"type":"Point"}
}