{
  "type": "Feature",
  "properties": {
    "addr:full":"4, Rue de l'Egalit\u00e9, 59640 Petite Synthe Picardie",
    "addr:housenumber":"4",
    "addr:postcode":"59640",
    "addr:street":"Rue De L'Egalite \u0301",
    "iso:country":"FR",
    "sg:address":"4, Rue de l'Egalit\u00e9, 59640 Petite Synthe",
    "sg:orig_category":"Unclassifiable Establishments",
    "sg:phone":"+33 3 28 64 37 05",
    "sg:province":"Picardie",
    "wof:name":"Peind\u00e9cor S.a.r.l.",
    "wof:placetype":"venue"
},
  "geometry": {"coordinates":[2.383479,51.036842],"type":"Point"}
}