{
  "type": "Feature",
  "properties": {
    "iso:country":"FR",
    "sg:address":"355, Rue Victor Hugo - Parc d'activit\u00e9, 76300 Sotteville les Rouen",
    "sg:orig_category":"Non-Classified Establishments",
    "sg:phone":"+33 2 35 73 19 19",
    "sg:province":"Haute Normandie",
    "wof:name":"Sonormat Location S.a.s.",
    "wof:placetype":"venue"
},
  "geometry": {"coordinates":[1.097363,49.409588],"type":"Point"}
}