{
  "type": "Feature",
  "properties": {
    "addr:full":"37 rue des Morillons 75015 Paris Ile de France 75015",
    "addr:housenumber":"37",
    "addr:postcode":"75015;75015",
    "addr:street":"Rue Des Morillons",
    "iso:country":"FR",
    "sg:address":"37 rue des Morillons 75015 Paris",
    "sg:classifiers":[
        {
            "category":"Utilities",
            "subcategory":"Fuel Oil & Lpg",
            "type":"Services"
        }
    ],
    "sg:phone":"+33 1 48 28 54 72",
    "sg:postcode":"75015",
    "sg:province":"Ile de France",
    "sg:tags":[
        "fluid",
        "mechanic"
    ],
    "wof:name":"Ciex Internationale Sa",
    "wof:placetype":"venue"
},
  "geometry": {"coordinates":[2.299465,48.83329],"type":"Point"}
}