{
  "type": "Feature",
  "properties": {
    "addr:full":"32, Av Foch, 57730 Folschviller Lorraine",
    "addr:postcode":"57730",
    "addr:street":"32 Av Foch",
    "iso:country":"FR",
    "sg:address":"32, Av Foch, 57730 Folschviller",
    "sg:orig_category":"Non-Classified Establishments",
    "sg:phone":"+33 3 87 92 16 88",
    "sg:province":"Lorraine",
    "wof:name":"T.m.c. S.a. - Transports Et Mat\u00e9riaux De Constructions",
    "wof:placetype":"venue"
},
  "geometry": {"coordinates":[6.689914,49.073357],"type":"Point"}
}