{
  "type": "Feature",
  "properties": {
    "iso:country":"FR",
    "sg:address":"13, Rte de Lyon, 84000 Avignon",
    "sg:orig_category":"Unclassifiable Establishments",
    "sg:phone":"+33 4 90 16 76 00",
    "sg:province":"Rhone-Alpes",
    "wof:name":"Axit Informatique Territoriale S.a.",
    "wof:placetype":"venue"
},
  "geometry": {"coordinates":[4.823502,43.950512],"type":"Point"}
}