{
  "type": "Feature",
  "properties": {
    "addr:full":"13, Rte de Lyon, 84000 Avignon Rhone-Alpes",
    "addr:housenumber":"13",
    "addr:postcode":"84000",
    "addr:street":"Rte De Lyon",
    "iso:country":"FR",
    "sg:address":"13, Rte de Lyon, 84000 Avignon",
    "sg:orig_category":"Unclassifiable Establishments",
    "sg:phone":"+33 4 90 16 76 00",
    "sg:province":"Rhone-Alpes",
    "wof:name":"Axit Informatique Territoriale S.a.",
    "wof:placetype":"venue"
},
  "geometry": {"coordinates":[4.823502,43.950512],"type":"Point"}
}