{
  "type": "Feature",
  "properties": {
    "addr:full":"Rue Berthelot 60200 Compiegne Picardie 60200",
    "addr:postcode":"60200;60200",
    "addr:street":"Rue Berthelot;Picardie",
    "iso:country":"FR",
    "sg:address":"Rue Berthelot 60200 Compiegne",
    "sg:classifiers":[
        {
            "category":"Travel",
            "subcategory":"Hotels & Motels",
            "type":"Entertainment"
        }
    ],
    "sg:phone":"+33 3 44 97 02 73",
    "sg:postcode":"60200",
    "sg:province":"Picardie",
    "sg:tags":[
        "hotels",
        "business",
        "restaurant"
    ],
    "wof:name":"Buffalo Grill",
    "wof:placetype":"venue"
},
  "geometry": {"coordinates":[2.788654,49.391014],"type":"Point"}
}