{
  "type": "Feature",
  "properties": {
    "iso:country":"FR",
    "sg:address":"Ponte Nuovo 20235 Castello di Rostino",
    "sg:orig_category":"Unclassifiable Establishments",
    "sg:phone":"+33 4 95 38 60 82",
    "sg:province":"Corse",
    "wof:name":"Corse Protection Industrielle S.a.r.l.",
    "wof:placetype":"venue"
},
  "geometry": {"coordinates":[9.281165,42.486477],"type":"Point"}
}