{
  "type": "Feature",
  "properties": {
    "addr:full":"2 Rue Du Stade La Neuville 60220 Moliens Picardie 60220",
    "addr:housenumber":"2",
    "addr:postcode":"60220;60220",
    "addr:street":"Rue Du Stade La Neuville",
    "iso:country":"FR",
    "sg:address":"2 Rue Du Stade La Neuville 60220 Moliens",
    "sg:classifiers":[
        {
            "category":"Shopping",
            "subcategory":"Crafts & Fabrics",
            "type":"Retail Goods"
        }
    ],
    "sg:phone":"+33 3 44 46 75 32",
    "sg:postcode":"60220",
    "sg:province":"Picardie",
    "sg:tags":[
        "textile",
        "clothing"
    ],
    "wof:name":"Lt Couture",
    "wof:placetype":"venue"
},
  "geometry": {"coordinates":[1.730822,49.650074],"type":"Point"}
}