{
  "type": "Feature",
  "properties": {
    "iso:country":"FR",
    "sg:address":"53 Boulevard Aristide Briand 22700 Perros Guirec",
    "sg:city":"Louannec",
    "sg:classifiers":[
        {
            "category":"Manufacturing",
            "subcategory":"Printing",
            "type":"Manufacturing & Wholesale Goods"
        }
    ],
    "sg:phone":"+33 2 96 23 20 18",
    "sg:postcode":"22700",
    "sg:province":"Bretagne",
    "sg:tags":[
        "publishing"
    ],
    "wof:name":"Imprimerie R Chevalier",
    "wof:placetype":"venue"
},
  "geometry": {"coordinates":[-3.452006,48.812885],"type":"Point"}
}