{
  "type": "Feature",
  "properties": {
    "addr:full":"B.P. 59, 78230 Le Pecq C\u00e9dex^^12, Rue de Paris, 78230 Le Pecq Ile de France 78230",
    "addr:postcode":"78230;78230;78230",
    "addr:street":"B.P. 59;Rue De Paris",
    "iso:country":"FR",
    "sg:address":"B.P. 59, 78230 Le Pecq C\u00e9dex^^12, Rue de Paris, 78230 Le Pecq",
    "sg:orig_category":"Non-Classified Establishments",
    "sg:phone":"+33 1 30 87 62 00",
    "sg:postcode":"78230",
    "sg:province":"Ile de France",
    "wof:name":"Bull S.a.",
    "wof:placetype":"venue"
},
  "geometry": {"coordinates":[2.10699,48.89732],"type":"Point"}
}