{
  "type": "Feature",
  "properties": {
    "addr:full":"9, Rue Amp\u00e8re - Zone Industrielle des Bruy\u00e8res, 71031 M\u00e2con C\u00e9dex Haute Normandie",
    "addr:housenumber":"9",
    "addr:postcode":"71031",
    "addr:street":"Rue Ampe\u0300Re;Industrielle Des Bruye\u0300Res;Haute Normandie",
    "iso:country":"FR",
    "sg:address":"9, Rue Amp\u00e8re - Zone Industrielle des Bruy\u00e8res, 71031 M\u00e2con C\u00e9dex",
    "sg:orig_category":"Non-Classified Establishments",
    "sg:phone":"+33 3 85 29 39 00",
    "sg:province":"Haute Normandie",
    "wof:name":"Schlumberger Industries S.a.",
    "wof:placetype":"venue"
},
  "geometry": {"coordinates":[4.78461,46.310059],"type":"Point"}
}