{
  "type": "Feature",
  "properties": {
    "iso:country":"FR",
    "sg:address":"Mont\u00e9e De Prat 01290 St Jean Sur Veyle",
    "sg:classifiers":[
        {
            "category":"Food & Beverages",
            "subcategory":"Groceries & Convenience Stores",
            "type":"Retail Goods"
        }
    ],
    "sg:phone":"+33 3 85 31 54 58",
    "sg:postcode":"01290",
    "sg:province":"Rhone-Alpes",
    "sg:tags":[
        "product",
        "grain",
        "cereal",
        "related"
    ],
    "wof:name":"Moulin Humbert Sa",
    "wof:placetype":"venue"
},
  "geometry": {"coordinates":[4.91609,46.25779],"type":"Point"}
}