{
  "type": "Feature",
  "properties": {
    "iso:country":"FR",
    "sg:address":"39, Rue de la R\u00e9publique - Immeuble les Portes de Saint Priest, 42270 Saint Priest en Jarez",
    "sg:orig_category":"Unclassifiable Establishments",
    "sg:phone":"+33 4 77 93 72 72",
    "sg:postcode":"42270",
    "sg:province":"Rhone-Alpes",
    "wof:name":"Apicom S.a.",
    "wof:placetype":"venue"
},
  "geometry": {"coordinates":[4.379298,45.46682],"type":"Point"}
}