{
  "type": "Feature",
  "properties": {
    "addr:full":"35 ave Paul Doumer; Paris; 75016 Ile de France 75016",
    "addr:postcode":"75016 ile;france 75016",
    "addr:street":"35 Ave Paul Doumer",
    "iso:country":"FR",
    "sg:address":"35 ave Paul Doumer; Paris; 75016",
    "sg:classifiers":[
        {
            "category":"Banks & Credit Unions",
            "subcategory":"Bank",
            "type":"Services"
        }
    ],
    "sg:phone":"+33 1 45 04 21 01",
    "sg:postcode":"75016",
    "sg:province":"Ile de France",
    "wof:name":"Soci\u00e9t\u00e9 G\u00e9n\u00e9rale",
    "wof:placetype":"venue"
},
  "geometry": {"coordinates":[2.282416,48.860523],"type":"Point"}
}