{
  "type": "Feature",
  "properties": {
    "addr:full":"92, Rue Andr\u00e9 Breton, 46000 Cahors Midi Pyr\u00e9n\u00e9es",
    "addr:housenumber":"92",
    "addr:postcode":"46000",
    "addr:street":"Rue Andre\u0301 Breton",
    "iso:country":"FR",
    "sg:address":"92, Rue Andr\u00e9 Breton, 46000 Cahors",
    "sg:orig_category":"Unclassifiable Establishments",
    "sg:phone":"+33 5 65 22 39 49",
    "sg:province":"Midi Pyr\u00e9n\u00e9es",
    "wof:name":"Campagnac S.a.",
    "wof:placetype":"venue"
},
  "geometry": {"coordinates":[1.432889,44.446041],"type":"Point"}
}