{
  "type": "Feature",
  "properties": {
    "addr:full":"B.P. 19, 60290 Rantigny^^19, Rue Emile Zola, 60290 Rantigny Picardie",
    "addr:postcode":"60290;60290",
    "addr:street":"B.P. 19;Rue Emile Zola",
    "iso:country":"FR",
    "sg:address":"B.P. 19, 60290 Rantigny^^19, Rue Emile Zola, 60290 Rantigny",
    "sg:orig_category":"Non-Classified Establishments",
    "sg:phone":"+33 3 44 27 00 03",
    "sg:province":"Picardie",
    "wof:name":"Isover Saint Gobain",
    "wof:placetype":"venue"
},
  "geometry": {"coordinates":[2.44369,49.293819],"type":"Point"}
}