{
  "type": "Feature",
  "properties": {
    "addr:full":"15 Av Daniel 94420 Le Plessis Tr\u00e9vise Ile de France 94420",
    "addr:postcode":"94420;94420",
    "addr:street":"15 Av Daniel",
    "iso:country":"FR",
    "sg:address":"15 Av Daniel 94420 Le Plessis Tr\u00e9vise",
    "sg:classifiers":[
        {
            "category":"Wholesale",
            "subcategory":"Medical Equipment & Supplies",
            "type":"Manufacturing & Wholesale Goods"
        }
    ],
    "sg:phone":"+33 1 45 76 46 25",
    "sg:postcode":"94420",
    "sg:province":"Ile de France",
    "sg:tags":[
        "instrument",
        "health",
        "-",
        "precision"
    ],
    "wof:name":"Broville Christian Eurl",
    "wof:placetype":"venue"
},
  "geometry": {"coordinates":[2.56166,48.805511],"type":"Point"}
}