{
  "type": "Feature",
  "properties": {
    "addr:full":"1, Rue Wendel, 57700 Hayange Lorraine",
    "addr:housenumber":"1",
    "addr:postcode":"57700",
    "addr:street":"Rue Wendel",
    "iso:country":"FR",
    "sg:address":"1, Rue Wendel, 57700 Hayange",
    "sg:orig_category":"Unclassifiable Establishments",
    "sg:phone":"+33 3 82 85 46 70",
    "sg:province":"Lorraine",
    "wof:name":"Beugin Industrie S.a.r.l.",
    "wof:placetype":"venue"
},
  "geometry": {"coordinates":[6.07484,49.324371],"type":"Point"}
}