{
  "type": "Feature",
  "properties": {
    "iso:country":"FR",
    "sg:address":"25 Rue Jean Jacques Rousseau 36200 Argenton Sur Creuse",
    "sg:city":"Argenton-sur-Creuse",
    "sg:classifiers":[
        {
            "category":"Wholesale",
            "subcategory":"Medical Equipment & Supplies",
            "type":"Manufacturing & Wholesale Goods"
        }
    ],
    "sg:phone":"+33 2 54 24 03 13",
    "sg:postcode":"36200",
    "sg:province":"Centre",
    "sg:tags":[
        "instrument",
        "health",
        "-",
        "precision"
    ],
    "wof:name":"Laboratoire Acolas Sarl",
    "wof:placetype":"venue"
},
  "geometry": {"coordinates":[1.514165,46.593891],"type":"Point"}
}