{
  "type": "Feature",
  "properties": {
    "addr:full":"Z.A.E. du Vernoy Longeau Champagne 52250",
    "addr:postcode":"52250",
    "addr:street":"Champagne",
    "iso:country":"FR",
    "sg:address":"Z.A.E. du Vernoy",
    "sg:city":"Longeau",
    "sg:orig_category":"Non-Classified Establishments",
    "sg:phone":"+33 3 25 88 49 50",
    "sg:postcode":"52250",
    "sg:province":"Champagne",
    "wof:name":"Transports Feint Leboucher S.a.r.l.",
    "wof:placetype":"venue"
},
  "geometry": {"coordinates":[5.222831,47.767933],"type":"Point"}
}