{
  "type": "Feature",
  "properties": {
    "addr:full":"100 bis, Av. Kl\u00e9ber, 75116 Paris Ile de France",
    "addr:housenumber":"100",
    "addr:postcode":"75116",
    "addr:street":"Bis Av. Kle\u0301Ber",
    "iso:country":"FR",
    "sg:address":"100 bis, Av. Kl\u00e9ber, 75116 Paris",
    "sg:orig_category":"Non-Classified Establishments",
    "sg:phone":"+33 1 45 53 37 22",
    "sg:province":"Ile de France",
    "wof:name":"Permanence Europ\u00e9enne",
    "wof:placetype":"venue"
},
  "geometry": {"coordinates":[2.288706,48.865654],"type":"Point"}
}