{
  "type": "Feature",
  "properties": {
    "addr:full":"B.P. 132, 74954 Scionzier C\u00e9dex^^16, Rue du Bargy, 74950 Scionzier Rhone-Alpes 74950",
    "addr:housenumber":"b.p. 132",
    "addr:postcode":"74954;74950;74950",
    "addr:street":"Rue Du Bargy;Rhone-Alpes",
    "iso:country":"FR",
    "sg:address":"B.P. 132, 74954 Scionzier C\u00e9dex^^16, Rue du Bargy, 74950 Scionzier",
    "sg:orig_category":"Non-Classified Establishments",
    "sg:phone":"+33 4 50 98 61 79",
    "sg:postcode":"74950",
    "sg:province":"Rhone-Alpes",
    "wof:name":"Dufour Fran\u00e7ois Et Fils S.a.",
    "wof:placetype":"venue"
},
  "geometry": {"coordinates":[6.549965,46.057178],"type":"Point"}
}