{
  "type": "Feature",
  "properties": {
    "addr:full":"Rte du Chenal Gravelines Nord Pas-de-Calais 59820",
    "addr:postcode":"59820",
    "addr:street":"Rte Du Chenal Gravelines Nord",
    "iso:country":"FR",
    "sg:address":"Rte du Chenal",
    "sg:city":"Gravelines",
    "sg:orig_category":"Non-Classified Establishments",
    "sg:phone":"+33 3 28 23 92 60",
    "sg:postcode":"59820",
    "sg:province":"Nord Pas-de-Calais",
    "wof:name":"Norelec S.n.c.",
    "wof:placetype":"venue"
},
  "geometry": {"coordinates":[2.119574,50.986252],"type":"Point"}
}