{
  "type": "Feature",
  "properties": {
    "addr:full":"8 bis, Rue Traversi\u00e8re, 92100 Boulogne Billancourt Ile de France",
    "addr:housenumber":"8 bis",
    "addr:postcode":"92100",
    "addr:street":"Rue Traversie\u0300Re",
    "iso:country":"FR",
    "sg:address":"8 bis, Rue Traversi\u00e8re, 92100 Boulogne Billancourt",
    "sg:orig_category":"Non-Classified Establishments",
    "sg:phone":"+33 1 46 20 19 42",
    "sg:province":"Ile de France",
    "wof:name":"I.n.g.e. S.a.r.l. - Industrie Normalis\u00e9e Et Gestion D' Environnement",
    "wof:placetype":"venue"
},
  "geometry": {"coordinates":[2.246436,48.825397],"type":"Point"}
}