{
  "type": "Feature",
  "properties": {
    "iso:country":"FR",
    "sg:address":"B.P. 35, 25301 Pontarlier C\u00e9dex^^37, Rue des Salins, 25300 Pontarlier",
    "sg:orig_category":"Non-Classified Establishments",
    "sg:phone":"+33 3 81 46 71 87",
    "sg:postcode":"25300",
    "sg:province":"Franche Comt\u00e9",
    "wof:name":"De Giorgi Constructions S.a.r.l.",
    "wof:placetype":"venue"
},
  "geometry": {"coordinates":[6.40966,46.833256],"type":"Point"}
}