{
  "type": "Feature",
  "properties": {
    "iso:country":"FR",
    "sg:address":"85, Rue des Alli\u00e9s, 42100 Saint Etienne",
    "sg:orig_category":"Non-Classified Establishments",
    "sg:phone":"+33 4 77 32 50 62",
    "sg:postcode":"42100",
    "sg:province":"Rhone-Alpes",
    "wof:name":"C.g.s.t. Save S.a.s. - Compagnie Gazi\u00e8re Service Technique Save",
    "wof:placetype":"venue"
},
  "geometry": {"coordinates":[4.407811,45.440273],"type":"Point"}
}