{
  "type": "Feature",
  "properties": {
    "addr:full":"9, Rue Salvador Allende - ZI, 91124 Palaiseau C\u00e9dex Ile-de-France",
    "addr:housenumber":"9",
    "addr:postcode":"91124",
    "addr:street":"Rue Salvador Allende Zi",
    "iso:country":"FR",
    "sg:address":"9, Rue Salvador Allende - ZI, 91124 Palaiseau C\u00e9dex",
    "sg:orig_category":"Non-Classified Establishments",
    "sg:phone":"+33 1 69 20 57 35",
    "sg:province":"Ile-de-France",
    "wof:name":"Rovatti France S.a.r.l.",
    "wof:placetype":"venue"
},
  "geometry": {"coordinates":[2.246296,48.713036],"type":"Point"}
}