{
  "type": "Feature",
  "properties": {
    "iso:country":"FR",
    "sg:address":"La Berg\u00e8re 07290 Satillieu",
    "sg:classifiers":[
        {
            "category":"Shopping",
            "subcategory":"Crafts & Fabrics",
            "type":"Retail Goods"
        }
    ],
    "sg:phone":"+33 4 75 69 91 34",
    "sg:postcode":"07290",
    "sg:province":"Rhone-Alpes",
    "sg:tags":[
        "textile",
        "clothing"
    ],
    "wof:name":"Tissage De La Bergere",
    "wof:placetype":"venue"
},
  "geometry": {"coordinates":[4.62263,45.154545],"type":"Point"}
}