{
  "type": "Feature",
  "properties": {
    "addr:full":"70, Rue Pierre Duhem - ZI les Milles, 13856 Aix en Provence C\u00e9dex 03 Nord Pas-de-Calais",
    "addr:housenumber":"70;03",
    "addr:postcode":"13856",
    "addr:street":"Rue Pierre Duhem Zi Les Milles;Ce\u0301Dex",
    "iso:country":"FR",
    "sg:address":"70, Rue Pierre Duhem - ZI les Milles, 13856 Aix en Provence C\u00e9dex 03",
    "sg:orig_category":"Non-Classified Establishments",
    "sg:phone":"+33 4 42 16 65 25",
    "sg:province":"Nord Pas-de-Calais",
    "wof:name":"G.r.a.m. S.a. - Guigues Recherche Appliqu\u00e9e En Microbiologie",
    "wof:placetype":"venue"
},
  "geometry": {"coordinates":[5.38935,43.50206],"type":"Point"}
}