{
  "type": "Feature",
  "properties": {
    "iso:country":"FR",
    "sg:address":"Rue Jules Ferry - ZI du Bas Pontet",
    "sg:city":"Saint Symphorien d'Ozon",
    "sg:orig_category":"Non-Classified Establishments",
    "sg:phone":"+33 4 78 02 19 96",
    "sg:postcode":"69360",
    "sg:province":"Rhone-Alpes",
    "wof:name":"S K L Serbat S.a.r.l.",
    "wof:placetype":"venue"
},
  "geometry": {"coordinates":[4.85609,45.634979],"type":"Point"}
}