{
  "type": "Feature",
  "properties": {
    "addr:full":"rue du Meix Martin 21700 Bagnot Bagnot Bourgogne 21700",
    "addr:postcode":"21700;21700",
    "addr:street":"Rue Du Meix Martin",
    "iso:country":"FR",
    "sg:address":"rue du Meix Martin 21700 Bagnot",
    "sg:city":"Bagnot",
    "sg:orig_category":"Two-Way Radios",
    "sg:phone":"+33 3 80 26 91 91",
    "sg:postcode":"21700",
    "sg:province":"Bourgogne",
    "wof:name":"Crt France International Sa",
    "wof:placetype":"venue"
},
  "geometry": {"coordinates":[5.070597,47.056816],"type":"Point"}
}