{
  "type": "Feature",
  "properties": {
    "iso:country":"FR",
    "sg:address":"Route Du Bourrian 83580 Gassin",
    "sg:classifiers":[
        {
            "category":"Home & Garden",
            "subcategory":"Furniture",
            "type":"Retail Goods"
        }
    ],
    "sg:phone":"+33 4 94 55 20 30",
    "sg:province":"Centre",
    "sg:tags":[
        "household",
        "wood"
    ],
    "wof:name":"Saint Tropez Parcs Et Jardins",
    "wof:placetype":"venue"
},
  "geometry": {"coordinates":[6.585806,43.254646],"type":"Point"}
}