{
  "type": "Feature",
  "properties": {
    "iso:country":"FR",
    "sg:address":"B.P. 262, 13269 Marseille C\u00e9dex 08^^64, Av. d'Haifa, 13008 Marseille",
    "sg:orig_category":"Non-Classified Establishments",
    "sg:phone":"+33 4 91 23 85 50",
    "sg:province":"Poitou-Charentes",
    "wof:name":"Dalkia",
    "wof:placetype":"venue"
},
  "geometry": {"coordinates":[5.391953,43.252419],"type":"Point"}
}