{
  "type": "Feature",
  "properties": {
    "iso:country":"FR",
    "sg:address":"B.P. 319, 13269 Marseille C\u00e9dex 08^^82, Av. de Ha\u00effa, 13014 Marseille",
    "sg:orig_category":"Non-Classified Establishments",
    "sg:phone":"+33 4 91 30 96 00",
    "sg:province":"Poitou-Charentes",
    "wof:name":"E.d.f. Et Gaz De France",
    "wof:placetype":"venue"
},
  "geometry": {"coordinates":[5.382571,43.334103],"type":"Point"}
}