{
  "type": "Feature",
  "properties": {
    "addr:full":"7 Grande Rue 33420 Rauzan Rauzan Aquitaine 33420",
    "addr:housenumber":"7",
    "addr:postcode":"33420;33420",
    "addr:street":"Grande Rue",
    "iso:country":"FR",
    "sg:address":"7 Grande Rue 33420 Rauzan",
    "sg:city":"Rauzan",
    "sg:classifiers":[
        {
            "category":"Wholesale",
            "subcategory":"Farm Supplies",
            "type":"Manufacturing & Wholesale Goods"
        }
    ],
    "sg:phone":"+33 5 57 84 04 81",
    "sg:postcode":"33420",
    "sg:province":"Aquitaine",
    "sg:tags":[
        "-",
        "machine",
        "equipment",
        "engineering",
        "machinery",
        "mechanical",
        "agriculture"
    ],
    "wof:name":"Aquitaine Viticole",
    "wof:placetype":"venue"
},
  "geometry": {"coordinates":[-0.124768,44.77951],"type":"Point"}
}