{
  "type": "Feature",
  "properties": {
    "iso:country":"FR",
    "sg:address":"16, Rue Henri Martin, 76100 Rouen",
    "sg:orig_category":"Non-Classified Establishments",
    "sg:phone":"+33 2 35 72 75 06",
    "sg:postcode":"76100",
    "sg:province":"Haute Normandie",
    "wof:name":"Cornu France S.a.",
    "wof:placetype":"venue"
},
  "geometry": {"coordinates":[1.09366,49.430321],"type":"Point"}
}