{
  "type": "Feature",
  "properties": {
    "iso:country":"FR",
    "sg:address":"Rte de Montereau",
    "sg:city":"Darvault",
    "sg:orig_category":"Unclassifiable Establishments",
    "sg:phone":"+33 1 64 45 23 64",
    "sg:postcode":"77140",
    "sg:province":"Ile de France",
    "wof:name":"Friatec D. P. L. S.a. - Friatec Distribution Produits Lemaire",
    "wof:placetype":"venue"
},
  "geometry": {"coordinates":[2.74244,48.273609],"type":"Point"}
}