{
  "type": "Feature",
  "properties": {
    "iso:country":"FR",
    "sg:address":"39 R Du Moulin 39120 Rahon",
    "sg:classifiers":[
        {
            "category":"Professional",
            "subcategory":"Engineering",
            "type":"Services"
        }
    ],
    "sg:phone":"+33 3 84 81 85 39",
    "sg:postcode":"39120",
    "sg:province":"Franche Comt\u00e9",
    "sg:tags":[
        "machine",
        "-",
        "mechanical"
    ],
    "wof:name":"Scierie Mutelet Sa",
    "wof:placetype":"venue"
},
  "geometry": {"coordinates":[5.407075,46.96719],"type":"Point"}
}