{
  "type": "Feature",
  "properties": {
    "addr:full":"Chemin Des Peupliers I De Croupillac 30340 St Privat Des Vieux Languedoc-Roussillon",
    "addr:postcode":"30340",
    "addr:street":"Chemin Des Peupliers I De Croupillac;Des Vieux",
    "iso:country":"FR",
    "sg:address":"Chemin Des Peupliers",
    "sg:city":"I De Croupillac 30340 St Privat Des Vieux",
    "sg:classifiers":[
        {
            "category":"Manufacturing",
            "subcategory":"Paper Products",
            "type":"Manufacturing & Wholesale Goods"
        }
    ],
    "sg:phone":"+33 4 66 30 04 08",
    "sg:province":"Languedoc-Roussillon",
    "sg:tags":[
        "packaging",
        "material",
        "-",
        "cardboard"
    ],
    "wof:name":"Tout Embal",
    "wof:placetype":"venue"
},
  "geometry": {"coordinates":[4.15388,44.100094],"type":"Point"}
}