{
  "type": "Feature",
  "properties": {
    "addr:full":"B.P. 39, 54302 Lun\u00e9ville C\u00e9dex^^9, Av. de la Lib\u00e9ration, 54300 Lun\u00e9ville Lorraine",
    "addr:postcode":"54302;54300",
    "addr:street":"B.P. 39;Av. De La Libe\u0301Ration",
    "iso:country":"FR",
    "sg:address":"B.P. 39, 54302 Lun\u00e9ville C\u00e9dex^^9, Av. de la Lib\u00e9ration, 54300 Lun\u00e9ville",
    "sg:orig_category":"Non-Classified Establishments",
    "sg:phone":"+33 3 83 76 47 00",
    "sg:province":"Lorraine",
    "wof:name":"General Trailers S.a.",
    "wof:placetype":"venue"
},
  "geometry": {"coordinates":[6.49027,48.59306],"type":"Point"}
}