{
  "type": "Feature",
  "properties": {
    "iso:country":"FR",
    "sg:address":"15, Rue Jean Baptiste Berlier, 75013 Paris",
    "sg:orig_category":"Unclassifiable Establishments",
    "sg:phone":"+33 1 45 86 25 25",
    "sg:province":"Ile de France",
    "wof:name":"Prescard S.a.r.l.",
    "wof:placetype":"venue"
},
  "geometry": {"coordinates":[2.355155,48.832119],"type":"Point"}
}