{
  "type": "Feature",
  "properties": {
    "addr:full":"55 rue Georges d'Amboise, 76000 Rouen, Dept 76 Haute Normandie 76000",
    "addr:housenumber":"55;76",
    "addr:postcode":"76000;76000",
    "addr:street":"Rue Georges D'Amboise;Normandie",
    "iso:country":"FR",
    "sg:address":"55 rue Georges d'Amboise, 76000 Rouen, Dept 76",
    "sg:classifiers":[
        {
            "category":"Banks & Credit Unions",
            "subcategory":"Bank",
            "type":"Services"
        }
    ],
    "sg:postcode":"76000",
    "sg:province":"Haute Normandie",
    "wof:name":"Sci Du Mont St Gatien",
    "wof:placetype":"venue"
},
  "geometry": {"coordinates":[1.081137,49.443462],"type":"Point"}
}