{
  "type": "Feature",
  "properties": {
    "iso:country":"FR",
    "sg:address":"48, Rue du Faubourg Raines, 21000 Dijon",
    "sg:city":"Dijon",
    "sg:orig_category":"Non-Classified Establishments",
    "sg:phone":"+33 3 80 42 05 04",
    "sg:postcode":"21000",
    "sg:province":"Bourgogne",
    "wof:name":"B.f.k. Electroniques S.a.r.l. - Bourgogne Fournitures Kit",
    "wof:placetype":"venue"
},
  "geometry": {"coordinates":[5.02749,47.319187],"type":"Point"}
}