{
  "type": "Feature",
  "properties": {
    "addr:full":"5 bis, Rue de Tacoigni\u00e8res, 78550 Richebourg Ile de France",
    "addr:housenumber":"5 bis",
    "addr:postcode":"78550;ile",
    "addr:street":"Rue De Tacoignie\u0300Res",
    "iso:country":"FR",
    "sg:address":"5 bis, Rue de Tacoigni\u00e8res, 78550 Richebourg",
    "sg:orig_category":"Non-Classified Establishments",
    "sg:phone":"+33 1 34 87 61 26",
    "sg:province":"Ile de France",
    "wof:name":"Logic Partners S.a.",
    "wof:placetype":"venue"
},
  "geometry": {"coordinates":[1.641108,48.825474],"type":"Point"}
}