{
  "type": "Feature",
  "properties": {
    "iso:country":"FR",
    "sg:address":"1, Rue du Ch\u00e2teau, 67520 Marlenheim",
    "sg:city":"Marlenheim",
    "sg:orig_category":"Unclassifiable Establishments",
    "sg:phone":"+33 3 88 87 76 00",
    "sg:postcode":"67520",
    "sg:province":"Alsace",
    "wof:name":"A.v.e.p. S.a.r.l. - Action Vers L'entreprise Performante",
    "wof:placetype":"venue"
},
  "geometry": {"coordinates":[7.49054,48.622139],"type":"Point"}
}