{
  "type": "Feature",
  "properties": {
    "iso:country":"FR",
    "sg:address":"42 Rue Du Centre 62127 Maizi\u00e8res",
    "sg:classifiers":[
        {
            "category":"Manufacturing",
            "subcategory":"Building Materials",
            "type":"Manufacturing & Wholesale Goods"
        }
    ],
    "sg:phone":"+33 3 21 47 31 55",
    "sg:postcode":"62127",
    "sg:province":"Nord Pas-de-Calais",
    "sg:tags":[
        "glass",
        "ceramic"
    ],
    "wof:name":"Sarl Laine Et Roger",
    "wof:placetype":"venue"
},
  "geometry": {"coordinates":[2.445531,50.322708],"type":"Point"}
}