{
  "type": "Feature",
  "properties": {
    "iso:country":"FR",
    "sg:address":"25 Cours Fauriel 42100 St Etienne",
    "sg:classifiers":[
        {
            "category":"Professional",
            "subcategory":"Business Services",
            "type":"Services"
        }
    ],
    "sg:phone":"+33 4 77 25 94 21",
    "sg:postcode":"42100",
    "sg:province":"Rhone-Alpes",
    "sg:tags":[
        "body",
        "advice"
    ],
    "wof:name":"Saint Etienne Infirmiers",
    "wof:placetype":"venue"
},
  "geometry": {"coordinates":[4.39861,45.428791],"type":"Point"}
}