{
  "type": "Feature",
  "properties": {
    "addr:full":"Zi Le Bois Joly BP 404 85504 Les Herbiers R\u00e9gion Pays de la Loire",
    "addr:housenumber":"404",
    "addr:postcode":"85504",
    "addr:street":"Zi Le",
    "iso:country":"FR",
    "sg:address":"Zi Le Bois Joly BP 404 85504 Les Herbiers",
    "sg:classifiers":[
        {
            "category":"Professional",
            "type":"Services"
        }
    ],
    "sg:phone":"+33 2 51 91 07 46",
    "sg:province":"R\u00e9gion Pays de la Loire",
    "sg:tags":[
        "transport",
        "road"
    ],
    "wof:name":"Transports Pineau Sa",
    "wof:placetype":"venue"
},
  "geometry": {"coordinates":[-1.015364,46.871265],"type":"Point"}
}