{
  "type": "Feature",
  "properties": {
    "addr:full":"55 Boulevard Frederic Mistral Beziers Languedoc-Roussillon 34500",
    "addr:housenumber":"55",
    "addr:postcode":"34500",
    "addr:street":"Boulevard Frederic Mistral Beziers",
    "iso:country":"FR",
    "sg:address":"55 Boulevard Frederic Mistral",
    "sg:city":"Beziers",
    "sg:classifiers":[
        {
            "category":"Banks & Credit Unions",
            "subcategory":"Financial Services",
            "type":"Services"
        }
    ],
    "sg:phone":"+33 4 67 36 50 15",
    "sg:postcode":"34500",
    "sg:province":"Languedoc-Roussillon",
    "sg:tags":[
        "banking",
        "finance",
        "insurance"
    ],
    "wof:name":"Caisse Regionale De Credit Agricole Mutuel Du Midiagence De Beziers Mistral",
    "wof:placetype":"venue"
},
  "geometry": {"coordinates":[3.219512,43.345943],"type":"Point"}
}