{
  "type": "Feature",
  "properties": {
    "addr:full":"2 rue Du Gros Chene 57960 MEISENTHAL Lorraine",
    "addr:housenumber":"2",
    "addr:postcode":"57960",
    "addr:street":"Rue Du Gros Chene",
    "iso:country":"FR",
    "sg:address":"2 rue Du Gros Chene 57960 MEISENTHAL",
    "sg:classifiers":[
        {
            "category":"Manufacturing",
            "subcategory":"Motor Vehicles & Parts",
            "type":"Manufacturing & Wholesale Goods"
        }
    ],
    "sg:phone":"+33 3 87 96 88 34",
    "sg:province":"Lorraine",
    "sg:tags":[
        "precision",
        "mechanic"
    ],
    "wof:name":"Ste Novotherm",
    "wof:placetype":"venue"
},
  "geometry": {"coordinates":[7.356075,48.974232],"type":"Point"}
}