{
  "type": "Feature",
  "properties": {
    "addr:full":"27 ave Andr\u00e9 Maginot; Tours; 37000 Tours Centre 37000",
    "addr:postcode":"37000;37000",
    "addr:street":"27 Ave Andre\u0301 Maginot",
    "iso:country":"FR",
    "sg:address":"27 ave Andr\u00e9 Maginot; Tours; 37000",
    "sg:city":"Tours",
    "sg:classifiers":[
        {
            "category":"Banks & Credit Unions",
            "subcategory":"Bank",
            "type":"Services"
        }
    ],
    "sg:phone":"+33 3347544221",
    "sg:postcode":"37000",
    "sg:province":"Centre",
    "wof:name":"Cr\u00e9dit Agricole Mutuel",
    "wof:placetype":"venue"
},
  "geometry": {"coordinates":[0.682962,47.410229],"type":"Point"}
}