{
  "type": "Feature",
  "properties": {
    "addr:full":"B.P. 2 Morestel Rhone-Alpes 38510",
    "addr:postcode":"38510",
    "addr:street":"B.P. 2;Rhone-Alpes",
    "iso:country":"FR",
    "sg:address":"B.P. 2",
    "sg:city":"Morestel",
    "sg:orig_category":"Non-Classified Establishments",
    "sg:phone":"+33 4 74 80 26 28",
    "sg:postcode":"38510",
    "sg:province":"Rhone-Alpes",
    "wof:name":"Tirtiss S.a.r.l.",
    "wof:placetype":"venue"
},
  "geometry": {"coordinates":[5.471508,45.674973],"type":"Point"}
}