{
  "type": "Feature",
  "properties": {
    "addr:full":"Chemin des Loges Beuvillers Basse Normandie 14100",
    "addr:postcode":"14100",
    "addr:street":"Chemin Des Loges;Basse",
    "iso:country":"FR",
    "sg:address":"Chemin des Loges",
    "sg:city":"Beuvillers",
    "sg:orig_category":"Unclassifiable Establishments",
    "sg:phone":"+33 2 31 31 43 01",
    "sg:postcode":"14100",
    "sg:province":"Basse Normandie",
    "wof:name":"B.m.g. Investissements S.a.r.l.",
    "wof:placetype":"venue"
},
  "geometry": {"coordinates":[0.246425,49.130661],"type":"Point"}
}