{
  "type": "Feature",
  "properties": {
    "iso:country":"FR",
    "sg:address":"2525 Rte D'Orange 84700 Sorgues",
    "sg:classifiers":[
        {
            "category":"Shopping",
            "type":"Retail Goods"
        }
    ],
    "sg:phone":"+33 4 90 83 43 45",
    "sg:province":"Centre",
    "sg:tags":[
        "metallurgy",
        "finished",
        "-",
        "metalworking",
        "metallic"
    ],
    "wof:name":"Sifco",
    "wof:placetype":"venue"
},
  "geometry": {"coordinates":[4.871694,44.008732],"type":"Point"}
}