{
  "type": "Feature",
  "properties": {
    "iso:country":"FR",
    "sg:address":"191, Av. Charles de Gaulle, 92200 Neuilly sur Seine",
    "sg:orig_category":"Non-Classified Establishments",
    "sg:phone":"+33 1 46 41 46 41",
    "sg:postcode":"92200",
    "sg:province":"Ile de France",
    "wof:name":"China Airlines Limited",
    "wof:placetype":"venue"
},
  "geometry": {"coordinates":[2.261429,48.884056],"type":"Point"}
}