{
  "type": "Feature",
  "properties": {
    "addr:full":"41 Rue Jacquard 71000 Macon Sanc\u00e9 Bourgogne 71000",
    "addr:housenumber":"41",
    "addr:postcode":"71000;71000",
    "addr:street":"Rue Jacquard",
    "iso:country":"FR",
    "sg:address":"41 Rue Jacquard 71000 Macon",
    "sg:city":"Sanc\u00e9",
    "sg:classifiers":[
        {
            "category":"Building & Trades",
            "subcategory":"Construction",
            "type":"Services"
        }
    ],
    "sg:phone":"+33 3 85 20 92 20",
    "sg:postcode":"71000",
    "sg:province":"Bourgogne",
    "sg:tags":[
        "work",
        "public"
    ],
    "wof:name":"Snctp",
    "wof:placetype":"venue"
},
  "geometry": {"coordinates":[4.810201,46.279591],"type":"Point"}
}