{
  "type": "Feature",
  "properties": {
    "iso:country":"FR",
    "sg:address":"37 A Chemin Des Tartugues 13800 Istres",
    "sg:classifiers":[
        {
            "category":"Building & Trades",
            "subcategory":"Construction",
            "type":"Services"
        }
    ],
    "sg:phone":"+33 4 42 56 30 93",
    "sg:province":"Franche Comt\u00e9",
    "sg:tags":[
        "work",
        "public"
    ],
    "wof:name":"Gil Travaux Publics",
    "wof:placetype":"venue"
},
  "geometry": {"coordinates":[4.972719,43.507698],"type":"Point"}
}