{
  "type": "Feature",
  "properties": {
    "iso:country":"FR",
    "sg:address":"Zi 49000 Ecouflant",
    "sg:classifiers":[
        {
            "category":"Professional",
            "type":"Services"
        }
    ],
    "sg:phone":"+33 2 41 43 97 97",
    "sg:province":"Pays de Loire",
    "sg:tags":[
        "transport",
        "road"
    ],
    "wof:name":"Meledo Anjou Sas",
    "wof:placetype":"venue"
},
  "geometry": {"coordinates":[-0.519448,47.500992],"type":"Point"}
}