{
  "type": "Feature",
  "properties": {
    "iso:country":"FR",
    "sg:address":"Rue L\u00e9on Gaumont",
    "sg:city":"Orvault",
    "sg:orig_category":"Unclassifiable Establishments",
    "sg:phone":"+33 2 51 77 86 50",
    "sg:postcode":"44700",
    "sg:province":"Pays de Loire",
    "wof:name":"Fondasol Atlantique S.a.",
    "wof:placetype":"venue"
},
  "geometry": {"coordinates":[-1.642899,47.26067],"type":"Point"}
}