{
  "type": "Feature",
  "properties": {
    "addr:full":"27 Avenue De La Senatorerie Gueret Limousin 23000",
    "addr:housenumber":"27",
    "addr:postcode":"23000",
    "addr:street":"Avenue De La Senatorerie Gueret Limousin",
    "iso:country":"FR",
    "sg:address":"27 Avenue De La Senatorerie",
    "sg:city":"Gueret",
    "sg:classifiers":[
        {
            "category":"Banks & Credit Unions",
            "subcategory":"Financial Services",
            "type":"Services"
        }
    ],
    "sg:phone":"+33 5 55 52 08 55",
    "sg:postcode":"23000",
    "sg:province":"Limousin",
    "sg:tags":[
        "banking",
        "finance",
        "insurance"
    ],
    "wof:name":"Fiduciaire De France Societe D'expertise Comptable Commissai (fidex)",
    "wof:placetype":"venue"
},
  "geometry": {"coordinates":[1.870229,46.166313],"type":"Point"}
}