{
  "type": "Feature",
  "properties": {
    "addr:full":"B.P. 199, 59054 Roubaix C\u00e9dex 1^^22, Rue du Ch\u00e2teau, 59100 Roubaix Nord Pas-de-Calais",
    "addr:housenumber":"b.p. 199;1;^ 22",
    "addr:postcode":"59054;59100",
    "addr:street":"^;Rue Du Cha\u0302Teau",
    "iso:country":"FR",
    "sg:address":"B.P. 199, 59054 Roubaix C\u00e9dex 1^^22, Rue du Ch\u00e2teau, 59100 Roubaix",
    "sg:orig_category":"Non-Classified Establishments",
    "sg:phone":"+33 3 20 81 58 20",
    "sg:province":"Nord Pas-de-Calais",
    "wof:name":"S.a.d.f. S.a. - Soci\u00e9t\u00e9 Analyse D\u00e9veloppement France",
    "wof:placetype":"venue"
},
  "geometry": {"coordinates":[3.1752,50.691704],"type":"Point"}
}