{
  "type": "Feature",
  "properties": {
    "iso:country":"FR",
    "sg:address":"6, Rue Bossuet - ZI de la Vigne aux Loups, 91160 Longjumeau",
    "sg:orig_category":"Unclassifiable Establishments",
    "sg:phone":"+33 1 69 10 15 00",
    "sg:province":"Ile de France",
    "wof:name":"Axis C.c. S.a. - Axis Connecteurs C\u00e2bles",
    "wof:placetype":"venue"
},
  "geometry": {"coordinates":[2.29005,48.691734],"type":"Point"}
}