{
  "type": "Feature",
  "properties": {
    "addr:full":"B.P. 10045, 57502 Saint Avold C\u00e9dex^^Rte du Puits, 57500 Saint Avold Lorraine",
    "addr:housenumber":"10045 57502",
    "addr:postcode":"57500",
    "addr:street":"Saint Avold Ce\u0301Dex^^Rte Du Puits;Avold",
    "iso:country":"FR",
    "sg:address":"B.P. 10045, 57502 Saint Avold C\u00e9dex^^Rte du Puits, 57500 Saint Avold",
    "sg:orig_category":"Non-Classified Establishments",
    "sg:phone":"+33 3 87 91 18 10",
    "sg:province":"Lorraine",
    "wof:name":"Grison S.a.",
    "wof:placetype":"venue"
},
  "geometry": {"coordinates":[6.705505,49.104275],"type":"Point"}
}