{
  "type": "Feature",
  "properties": {
    "iso:country":"FR",
    "sg:address":"48 Av De La Baraudi\u00e8re 44800 St Herblain",
    "sg:classifiers":[
        {
            "category":"Professional",
            "subcategory":"Business Services",
            "type":"Services"
        }
    ],
    "sg:phone":"+33 2 40 16 08 10",
    "sg:postcode":"44800",
    "sg:province":"Pays de Loire",
    "sg:tags":[
        "training",
        "advice"
    ],
    "wof:name":"Uaggep Jeanne Bernard Bel Air",
    "wof:placetype":"venue"
},
  "geometry": {"coordinates":[-1.591214,47.23555],"type":"Point"}
}