{
  "type": "Feature",
  "properties": {
    "iso:country":"FR",
    "sg:address":"60 ave du Raincy; Paris; 93250",
    "sg:classifiers":[
        {
            "category":"Banks & Credit Unions",
            "subcategory":"Bank",
            "type":"Services"
        }
    ],
    "sg:phone":"+33 1 48 94 71 38",
    "sg:postcode":"93250",
    "sg:province":"Ile de France",
    "wof:name":"Soci\u00e9t\u00e9 G\u00e9n\u00e9rale, Marocaine De Banques Sa",
    "wof:placetype":"venue"
},
  "geometry": {"coordinates":[2.510955,48.884956],"type":"Point"}
}