{
  "type": "Feature",
  "properties": {
    "iso:country":"FR",
    "sg:address":"B.P. 33, 59571 Jeumont C\u00e9dex^^Rue Pierre Pelet du Planty, 59460 Jeumont",
    "sg:orig_category":"Non-Classified Establishments",
    "sg:phone":"+33 3 27 39 50 40",
    "sg:province":"Nord Pas-de-Calais",
    "wof:name":"Froment Michel S.a.r.l.",
    "wof:placetype":"venue"
},
  "geometry": {"coordinates":[4.10194,50.296375],"type":"Point"}
}