{
  "type": "Feature",
  "properties": {
    "addr:full":"35, Av de Strasbourg, 57070 Metz Lorraine",
    "addr:postcode":"57070",
    "addr:street":"35 Av De Strasbourg",
    "iso:country":"FR",
    "sg:address":"35, Av de Strasbourg, 57070 Metz",
    "sg:orig_category":"Unclassifiable Establishments",
    "sg:phone":"+33 3 87 74 11 91",
    "sg:province":"Lorraine",
    "wof:name":"Piodi Marbrerie S.a.r.l.",
    "wof:placetype":"venue"
},
  "geometry": {"coordinates":[6.19471,49.112309],"type":"Point"}
}