{
  "type": "Feature",
  "properties": {
    "addr:full":"1 Rue Jean Monet 62117 Brebieres Nord Pas-de-Calais 62117",
    "addr:housenumber":"1",
    "addr:postcode":"62117;62117",
    "addr:street":"Rue Jean Monet;Brebieres Nord",
    "iso:country":"FR",
    "sg:address":"1 Rue Jean Monet 62117 Brebieres",
    "sg:classifiers":[
        {
            "category":"Farming",
            "subcategory":"Crops",
            "type":"Manufacturing & Wholesale Goods"
        }
    ],
    "sg:phone":"+33 3 21 55 52 52",
    "sg:postcode":"62117",
    "sg:province":"Nord Pas-de-Calais",
    "sg:tags":[
        "vegetable",
        "fruit",
        "agriculture",
        "livestock"
    ],
    "wof:name":"Ger Nor",
    "wof:placetype":"venue"
},
  "geometry": {"coordinates":[3.033889,50.344425],"type":"Point"}
}