{
  "type": "Feature",
  "properties": {
    "iso:country":"FR",
    "sg:address":"B.P. 22, 17320 Marennes^^15, Rue du Bois Meynardie, 17320 Marennes",
    "sg:orig_category":"Non-Classified Establishments",
    "sg:phone":"+33 5 46 85 15 42",
    "sg:province":"Poitou-Charentes",
    "wof:name":"I.t.o.m. S.a.s - Imprimerie Typo Offset Marennes",
    "wof:placetype":"venue"
},
  "geometry": {"coordinates":[-1.053868,45.796875],"type":"Point"}
}