{
  "type": "Feature",
  "properties": {
    "addr:full":"15 Place Grangier Dijon Bourgogne 21000",
    "addr:housenumber":"15",
    "addr:postcode":"21000",
    "addr:street":"Place Grangier;Bourgogne",
    "iso:country":"FR",
    "sg:address":"15 Place Grangier",
    "sg:city":"Dijon",
    "sg:classifiers":[
        {
            "category":"Banks & Credit Unions",
            "subcategory":"Financial Services",
            "type":"Services"
        }
    ],
    "sg:phone":"+33 3 80 30 65 87",
    "sg:postcode":"21000",
    "sg:province":"Bourgogne",
    "sg:tags":[
        "banking",
        "finance",
        "insurance"
    ],
    "wof:name":"Coutot Roehrig",
    "wof:placetype":"venue"
},
  "geometry": {"coordinates":[5.036725,47.323246],"type":"Point"}
}