{
  "type": "Feature",
  "properties": {
    "iso:country":"FR",
    "sg:address":"Boulevard Du Cormier 49300 Cholet",
    "sg:classifiers":[
        {
            "category":"Wholesale",
            "subcategory":"Machinery & Supplies",
            "type":"Manufacturing & Wholesale Goods"
        }
    ],
    "sg:phone":"+33 2 41 71 44 00",
    "sg:province":"Pays de Loire",
    "sg:tags":[
        "equipment",
        "equipement",
        "precision",
        "timekeeping"
    ],
    "wof:name":"Bodet Sa",
    "wof:placetype":"venue"
},
  "geometry": {"coordinates":[-0.914964,47.031914],"type":"Point"}
}