{
  "type": "Feature",
  "properties": {
    "addr:full":"Maillard 01400 Ch\u00e2tillon sur Chalaronne Rhone-Alpes",
    "addr:postcode":"01400",
    "addr:street":"Maillard",
    "iso:country":"FR",
    "sg:address":"Maillard 01400 Ch\u00e2tillon sur Chalaronne",
    "sg:orig_category":"Unclassifiable Establishments",
    "sg:phone":"+33 4 74 55 00 53",
    "sg:province":"Rhone-Alpes",
    "wof:name":"Sols Et Paysages S.a.",
    "wof:placetype":"venue"
},
  "geometry": {"coordinates":[4.94928,46.11776],"type":"Point"}
}