{
  "type": "Feature",
  "properties": {
    "iso:country":"FR",
    "sg:address":"36 Av De L'Europe 07100 Annonay",
    "sg:classifiers":[
        {
            "category":"Professional",
            "subcategory":"Business Services",
            "type":"Services"
        }
    ],
    "sg:phone":"+33 4 75 67 63 67",
    "sg:postcode":"07100",
    "sg:province":"Rhone-Alpes",
    "sg:tags":[
        "body",
        "advice"
    ],
    "wof:name":"Semad Ass",
    "wof:placetype":"venue"
},
  "geometry": {"coordinates":[4.669592,45.243019],"type":"Point"}
}