{
  "type": "Feature",
  "properties": {
    "addr:full":"Allee De Kerivarho Zi Du Prat 56000 Vannes Vannes Bretagne 56000",
    "addr:postcode":"56000;56000",
    "addr:street":"Allee;Zi Du Prat",
    "iso:country":"FR",
    "sg:address":"Allee De Kerivarho Zi Du Prat 56000 Vannes",
    "sg:city":"Vannes",
    "sg:classifiers":[
        {
            "category":"Professional",
            "subcategory":"Printing & Photocopies",
            "type":"Services"
        }
    ],
    "sg:phone":"+33 2 97 47 12 07",
    "sg:postcode":"56000",
    "sg:province":"Bretagne",
    "sg:tags":[
        "publishing"
    ],
    "wof:name":"Arka Ouest",
    "wof:placetype":"venue"
},
  "geometry": {"coordinates":[-2.759959,47.658169],"type":"Point"}
}