{
  "type": "Feature",
  "properties": {
    "iso:country":"FR",
    "sg:address":"69 Rue De Paris 59800 Lille",
    "sg:classifiers":[
        {
            "category":"Manufacturing",
            "subcategory":"Printing",
            "type":"Manufacturing & Wholesale Goods"
        }
    ],
    "sg:phone":"+33 3 20 15 83 40",
    "sg:province":"Nord Pas-de-Calais",
    "sg:tags":[
        "publishing"
    ],
    "wof:name":"Print Forum",
    "wof:placetype":"venue"
},
  "geometry": {"coordinates":[3.067483,50.635113],"type":"Point"}
}