{
  "type": "Feature",
  "properties": {
    "iso:country":"FR",
    "sg:address":"Bd Jean Moulin Zi Du Clos Bonnet 49400 Saumur",
    "sg:classifiers":[
        {
            "category":"Manufacturing",
            "subcategory":"Glass & Minerals",
            "type":"Manufacturing & Wholesale Goods"
        }
    ],
    "sg:phone":"+33 2 41 50 20 82",
    "sg:postcode":"49400",
    "sg:province":"Pays de Loire",
    "sg:tags":[
        "building",
        "material"
    ],
    "wof:name":"Lariviere Sa",
    "wof:placetype":"venue"
},
  "geometry": {"coordinates":[-0.068679,47.2145],"type":"Point"}
}