{
  "type": "Feature",
  "properties": {
    "iso:country":"FR",
    "sg:address":"La Fondinais 44750 Campbon",
    "sg:classifiers":[
        {
            "category":"Food & Beverages",
            "subcategory":"Dairy",
            "type":"Retail Goods"
        }
    ],
    "sg:phone":"+33 2 40 57 42 00",
    "sg:postcode":"44750",
    "sg:province":"Pays de Loire",
    "sg:tags":[
        "product",
        "related"
    ],
    "wof:name":"Cedilac Sa",
    "wof:placetype":"venue"
},
  "geometry": {"coordinates":[-1.96815,47.420532],"type":"Point"}
}