{
  "type": "Feature",
  "properties": {
    "addr:full":"3, Bd des Fr\u00e8res Bouliveau, 28200 Ch\u00e2teaudun Ch\u00e2teaudun Centre 28200",
    "addr:housenumber":"3",
    "addr:postcode":"28200;28200",
    "addr:street":"Bd Des Fre\u0300Res Bouliveau",
    "iso:country":"FR",
    "sg:address":"3, Bd des Fr\u00e8res Bouliveau, 28200 Ch\u00e2teaudun",
    "sg:city":"Ch\u00e2teaudun",
    "sg:orig_category":"Unclassifiable Establishments",
    "sg:phone":"+33 2 37 94 05 80",
    "sg:postcode":"28200",
    "sg:province":"Centre",
    "wof:name":"Boutard",
    "wof:placetype":"venue"
},
  "geometry": {"coordinates":[1.342809,48.084328],"type":"Point"}
}