{
  "type": "Feature",
  "properties": {
    "addr:full":"12 rue Louis Bl\u00e9riot 63100 CLERMONT FERRAND CEDEX 2 Clermont-Ferrand Auvergne 63100",
    "addr:housenumber":"12",
    "addr:postcode":"63100;63100",
    "addr:street":"Rue Louis Ble\u0301Riot",
    "iso:country":"FR",
    "sg:address":"12 rue Louis Bl\u00e9riot 63100 CLERMONT FERRAND CEDEX 2",
    "sg:city":"Clermont-Ferrand",
    "sg:classifiers":[
        {
            "category":"Shopping",
            "subcategory":"Pharmacy",
            "type":"Retail Goods"
        }
    ],
    "sg:phone":"+33 4 73 98 14 14",
    "sg:postcode":"63100",
    "sg:province":"Auvergne",
    "sg:tags":[
        "supply"
    ],
    "wof:name":"Transphyto Sa",
    "wof:placetype":"venue"
},
  "geometry": {"coordinates":[3.134498,45.783558],"type":"Point"}
}