{
  "type": "Feature",
  "properties": {
    "addr:full":"8/10, Rue de la Ferme, 92100 Boulogne Billancourt Ile de France",
    "addr:housenumber":"8 / 10",
    "addr:postcode":"92100",
    "addr:street":"Rue De La Ferme",
    "iso:country":"FR",
    "sg:address":"8/10, Rue de la Ferme, 92100 Boulogne Billancourt",
    "sg:orig_category":"Unclassifiable Establishments",
    "sg:phone":"+33 1 46 10 49 49",
    "sg:province":"Ile de France",
    "wof:name":"Ge Access S.a.r.l.",
    "wof:placetype":"venue"
},
  "geometry": {"coordinates":[2.238253,48.831154],"type":"Point"}
}