{
  "type": "Feature",
  "properties": {
    "iso:country":"FR",
    "sg:address":"Zi",
    "sg:city":"81000 Albi",
    "sg:classifiers":[
        {
            "category":"Park",
            "type":"Public Place"
        }
    ],
    "sg:phone":"+33 5 63 77 36 15",
    "sg:postcode":"81000",
    "sg:province":"Midi Pyr\u00e9n\u00e9es",
    "sg:tags":[
        "work",
        "construction",
        "sport"
    ],
    "wof:name":"Colas",
    "wof:placetype":"venue"
},
  "geometry": {"coordinates":[2.148375,43.926205],"type":"Point"}
}