{
  "type": "Feature",
  "properties": {
    "iso:country":"FR",
    "sg:address":"19 Grande Rue 51530 Chouilly",
    "sg:classifiers":[
        {
            "category":"Food Court",
            "type":"Food & Drink"
        }
    ],
    "sg:phone":"+33 3 26 55 40 30",
    "sg:province":"Haute Normandie",
    "sg:tags":[
        "product",
        "related"
    ],
    "wof:name":"Roland Champion Sa",
    "wof:placetype":"venue"
},
  "geometry": {"coordinates":[3.93405,49.05574],"type":"Point"}
}