{
  "type": "Feature",
  "properties": {
    "addr:full":"La Barbi\u00e8re P\u00e9age Macon Nord 71000 Sellece Les Macon Sanc\u00e9 Bourgogne 71000",
    "addr:postcode":"71000;71000",
    "addr:street":"Macon",
    "iso:country":"FR",
    "sg:address":"La Barbi\u00e8re P\u00e9age Macon Nord 71000 Sellece Les Macon",
    "sg:city":"Sanc\u00e9",
    "sg:classifiers":[
        {
            "category":"Professional",
            "type":"Services"
        }
    ],
    "sg:phone":"+33 3 85 20 41 00",
    "sg:postcode":"71000",
    "sg:province":"Bourgogne",
    "sg:tags":[
        "transport",
        "road"
    ],
    "wof:name":"Societe Des Autoroutes Paris Rhin Rhone",
    "wof:placetype":"venue"
},
  "geometry": {"coordinates":[4.833055,46.303043],"type":"Point"}
}