{
  "type": "Feature",
  "properties": {
    "iso:country":"FR",
    "sg:address":"29, Av. Auguste V\u00e9rola - Parc Hibiscus, 06200 Nice",
    "sg:orig_category":"Unclassifiable Establishments",
    "sg:phone":"+33 4 92 29 57 60",
    "sg:province":"Ile de France",
    "wof:name":"Punch S.a.r.l.",
    "wof:placetype":"venue"
},
  "geometry": {"coordinates":[7.188408,43.710228],"type":"Point"}
}