{
  "type": "Feature",
  "properties": {
    "iso:country":"FR",
    "sg:address":"17, Rue des Martyrs de la R\u00e9sistance, 59113 Seclin",
    "sg:orig_category":"Non-Classified Establishments",
    "sg:phone":"+33 3 20 90 60 16",
    "sg:postcode":"59113",
    "sg:province":"Nord Pas-de-Calais",
    "wof:name":"Bocage S.a.r.l.",
    "wof:placetype":"venue"
},
  "geometry": {"coordinates":[3.017911,50.554867],"type":"Point"}
}