{
  "type": "Feature",
  "properties": {
    "iso:country":"FR",
    "sg:address":"2, Bd Joliot Curie, 69694 V\u00e9nissieux C\u00e9dex",
    "sg:orig_category":"Non-Classified Establishments",
    "sg:phone":"+33 4 78 77 14 14",
    "sg:province":"Haute Normandie",
    "wof:name":"Aldes S.a.",
    "wof:placetype":"venue"
},
  "geometry": {"coordinates":[4.871242,45.724262],"type":"Point"}
}