{
  "type": "Feature",
  "properties": {
    "iso:country":"FR",
    "sg:address":"Rue Galil\u00e9e - Technopole Anticipa P\u00e9gase",
    "sg:city":"Lannion",
    "sg:orig_category":"Non-Classified Establishments",
    "sg:phone":"+33 2 96 48 11 86",
    "sg:postcode":"22300",
    "sg:province":"Bretagne",
    "wof:name":"Symbiose Informatique S.a.r.l.",
    "wof:placetype":"venue"
},
  "geometry": {"coordinates":[-3.508297,48.647575],"type":"Point"}
}