{
  "type": "Feature",
  "properties": {
    "addr:full":"17 Bd Gaston Birg\u00e9 49100 Angers Pays de Loire 49100",
    "addr:housenumber":"17",
    "addr:postcode":"49100;49100",
    "addr:street":"Bd Gaston Birge\u0301",
    "iso:country":"FR",
    "sg:address":"17 Bd Gaston Birg\u00e9 49100 Angers",
    "sg:classifiers":[
        {
            "category":"Shopping",
            "subcategory":"Computers & Home Electronics",
            "type":"Retail Goods"
        }
    ],
    "sg:phone":"+33 2 41 37 30 00",
    "sg:postcode":"49100",
    "sg:province":"Pays de Loire",
    "sg:tags":[
        "household",
        "appliance",
        "telecommunication",
        "audio-visual"
    ],
    "wof:name":"Thomson Television Angers Sa",
    "wof:placetype":"venue"
},
  "geometry": {"coordinates":[-0.520251,47.476955],"type":"Point"}
}