{
  "type": "Feature",
  "properties": {
    "addr:full":"Le Port 71110 Artaix Artaix Bourgogne 71110",
    "addr:postcode":"71110;71110",
    "iso:country":"FR",
    "sg:address":"Le Port 71110 Artaix",
    "sg:city":"Artaix",
    "sg:orig_category":"Drop Bollards",
    "sg:phone":"+33 3 85 25 29 27",
    "sg:postcode":"71110",
    "sg:province":"Bourgogne",
    "wof:name":"Holiste Laboratoires Et Developpement Sarl",
    "wof:placetype":"venue"
},
  "geometry": {"coordinates":[4.020965,46.256905],"type":"Point"}
}