{
  "type": "Feature",
  "properties": {
    "iso:country":"FR",
    "sg:address":"13130 Berre l'Etang",
    "sg:orig_category":"Unclassifiable Establishments",
    "sg:phone":"+33 4 42 74 42 74",
    "sg:province":"Provence-Alpes-C\u00f4te d'Azur",
    "wof:name":"Berroise De Raffinage S.a.",
    "wof:placetype":"venue"
},
  "geometry": {"coordinates":[5.15965,43.495338],"type":"Point"}
}