{
  "type": "Feature",
  "properties": {
    "iso:country":"FR",
    "sg:address":"21-23 Rue De Chevilly 94262 Fresnes Cedex",
    "sg:classifiers":[
        {
            "category":"Utilities",
            "subcategory":"Telephone",
            "type":"Services"
        }
    ],
    "sg:phone":"+33 1 46 15 42 50",
    "sg:province":"\u00cele-de-France",
    "sg:tags":[
        "telecommunication"
    ],
    "wof:name":"Globecast Reportage Sa",
    "wof:placetype":"venue"
},
  "geometry": {"coordinates":[2.33426,48.761169],"type":"Point"}
}