{
  "type": "Feature",
  "properties": {
    "addr:full":"La Magdeleine 44590 Saint Vincent des Landes Pays de Loire",
    "addr:postcode":"44590",
    "addr:street":"Magdeleine",
    "iso:country":"FR",
    "sg:address":"La Magdeleine 44590 Saint Vincent des Landes",
    "sg:orig_category":"Unclassifiable Establishments",
    "sg:phone":"+33 2 40 55 38 21",
    "sg:province":"Pays de Loire",
    "wof:name":"Gl\u00e9maud S.a.r.l.",
    "wof:placetype":"venue"
},
  "geometry": {"coordinates":[-1.506584,47.655079],"type":"Point"}
}