{
  "type": "Feature",
  "properties": {
    "addr:full":"192, Av. Charles Floquet, 93150 Le Blanc Mesnil Ile de France",
    "addr:postcode":"93150",
    "addr:street":"192 Av. Charles Floquet",
    "iso:country":"FR",
    "sg:address":"192, Av. Charles Floquet, 93150 Le Blanc Mesnil",
    "sg:orig_category":"Unclassifiable Establishments",
    "sg:phone":"+33 1 48 65 45 45",
    "sg:province":"Ile de France",
    "wof:name":"Bricopal S.a.r.l.",
    "wof:placetype":"venue"
},
  "geometry": {"coordinates":[2.44532,48.940559],"type":"Point"}
}