{
  "type": "Feature",
  "properties": {
    "addr:full":"1955 Chem St-Bernard 06225 Vallauris Cedex Rhone-Alpes",
    "addr:housenumber":"1955",
    "addr:postcode":"06225",
    "addr:street":"Chem St-Bernard",
    "iso:country":"FR",
    "sg:address":"1955 Chem St-Bernard 06225 Vallauris Cedex",
    "sg:classifiers":[
        {
            "category":"Professional",
            "subcategory":"Engineering",
            "type":"Services"
        }
    ],
    "sg:phone":"+33 4 93 64 53 10",
    "sg:province":"Rhone-Alpes",
    "sg:tags":[
        "machine",
        "-",
        "mechanical"
    ],
    "wof:name":"Delta Thermique Sarl",
    "wof:placetype":"venue"
},
  "geometry": {"coordinates":[7.057369,43.594307],"type":"Point"}
}