{
  "type": "Feature",
  "properties": {
    "addr:full":"50, Rue Alfred Mattez, 59158 Thun Saint Amand Nord Pas-de-Calais",
    "addr:housenumber":"50",
    "addr:postcode":"59158",
    "addr:street":"Rue Alfred Mattez;Amand Nord",
    "iso:country":"FR",
    "sg:address":"50, Rue Alfred Mattez, 59158 Thun Saint Amand",
    "sg:orig_category":"Unclassifiable Establishments",
    "sg:phone":"+33 3 27 26 92 16",
    "sg:province":"Nord Pas-de-Calais",
    "wof:name":"Blaszczynski S.a.r.l.",
    "wof:placetype":"venue"
},
  "geometry": {"coordinates":[3.440325,50.486725],"type":"Point"}
}