{
  "type": "Feature",
  "properties": {
    "addr:full":"60, Rue Albert Vanderhagen, 59320 Haubourdin Nord Pas-de-Calais 59320",
    "addr:housenumber":"60",
    "addr:postcode":"59320;59320",
    "addr:street":"Rue Albert Vanderhagen",
    "iso:country":"FR",
    "sg:address":"60, Rue Albert Vanderhagen, 59320 Haubourdin",
    "sg:orig_category":"Non-Classified Establishments",
    "sg:phone":"+33 3 20 50 50 46",
    "sg:postcode":"59320",
    "sg:province":"Nord Pas-de-Calais",
    "wof:name":"Defives S.a.",
    "wof:placetype":"venue"
},
  "geometry": {"coordinates":[2.977171,50.611732],"type":"Point"}
}