{
  "type": "Feature",
  "properties": {
    "addr:full":"57, Av. du Crozet, 74950 Scionzier Rhone-Alpes 74950",
    "addr:postcode":"74950;74950",
    "addr:street":"57 Av. Du Crozet;Rhone-Alpes",
    "iso:country":"FR",
    "sg:address":"57, Av. du Crozet, 74950 Scionzier",
    "sg:orig_category":"Non-Classified Establishments",
    "sg:phone":"+33 4 50 98 12 63",
    "sg:postcode":"74950",
    "sg:province":"Rhone-Alpes",
    "wof:name":"Cm Cmaes S.a.",
    "wof:placetype":"venue"
},
  "geometry": {"coordinates":[6.549194,46.063656],"type":"Point"}
}