{
  "type": "Feature",
  "properties": {
    "iso:country":"FR",
    "sg:address":"44, Rue de la Fa\u00efencerie, 33300 Bordeaux",
    "sg:city":"Bordeaux",
    "sg:orig_category":"Unclassifiable Establishments",
    "sg:phone":"+33 5 56 39 58 23",
    "sg:postcode":"33300",
    "sg:province":"Aquitaine",
    "wof:name":"H. Lawton S.a.",
    "wof:placetype":"venue"
},
  "geometry": {"coordinates":[-0.55659,44.860912],"type":"Point"}
}