{
  "type": "Feature",
  "properties": {
    "iso:country":"FR",
    "sg:address":"27-29 rue Henri Farman 93290 Tremblay en France",
    "sg:orig_category":"Register Punching",
    "sg:phone":"+33 1 48 61 92 00",
    "sg:province":"Ile de France",
    "wof:name":"Hourdain Chaumeil S.a.",
    "wof:placetype":"venue"
},
  "geometry": {"coordinates":[2.566515,48.967213],"type":"Point"}
}