{
  "type": "Feature",
  "properties": {
    "iso:country":"FR",
    "sg:address":"38 Bis Rue Vivienne 75002 Paris",
    "sg:classifiers":[
        {
            "category":"Professional",
            "subcategory":"Business Services",
            "type":"Services"
        }
    ],
    "sg:phone":"+33 1 40 26 56 56",
    "sg:postcode":"75002",
    "sg:province":"Ile de France",
    "sg:tags":[
        "training",
        "advice"
    ],
    "wof:name":"Europe Formation Conseil Sa",
    "wof:placetype":"venue"
},
  "geometry": {"coordinates":[2.341409,48.871037],"type":"Point"}
}