{
  "type": "Feature",
  "properties": {
    "iso:country":"FR",
    "sg:address":"Av. des Souspirous - ZI de Fontcouverte",
    "sg:city":"Avignon",
    "sg:orig_category":"Non-Classified Establishments",
    "sg:phone":"+33 4 90 89 20 20",
    "sg:postcode":"84000",
    "sg:province":"Poitou-Charentes",
    "wof:name":"Fac Simil\u00e9",
    "wof:placetype":"venue"
},
  "geometry": {"coordinates":[4.806015,43.948753],"type":"Point"}
}