{
  "type": "Feature",
  "properties": {
    "addr:full":"RN 5 Boulogne Billancourt Ile de France 92100",
    "addr:postcode":"92100",
    "addr:street":"Rn 5",
    "iso:country":"FR",
    "sg:address":"RN 5",
    "sg:city":"Boulogne Billancourt",
    "sg:orig_category":"Non-Classified Establishments",
    "sg:phone":"+33 1 41 41 96 60",
    "sg:postcode":"92100",
    "sg:province":"Ile de France",
    "wof:name":"P.a.o. Nicoles",
    "wof:placetype":"venue"
},
  "geometry": {"coordinates":[2.24102,48.835155],"type":"Point"}
}