{
  "type": "Feature",
  "properties": {
    "iso:country":"FR",
    "sg:address":"2, Rue Balzac, 75008 Paris",
    "sg:orig_category":"Unclassifiable Establishments",
    "sg:phone":"+33 1 40 74 83 00",
    "sg:province":"Ile de France",
    "wof:name":"Hutchinson S.n.c.",
    "wof:placetype":"venue"
},
  "geometry": {"coordinates":[2.299866,48.872543],"type":"Point"}
}