{
  "type": "Feature",
  "properties": {
    "addr:full":"ZI La B\u00e2thie Rhone-Alpes 73540",
    "addr:postcode":"73540",
    "addr:street":"Zi La;Rhone-Alpes",
    "iso:country":"FR",
    "sg:address":"ZI",
    "sg:city":"La B\u00e2thie",
    "sg:orig_category":"Unclassifiable Establishments",
    "sg:phone":"+33 4 79 89 69 03",
    "sg:postcode":"73540",
    "sg:province":"Rhone-Alpes",
    "wof:name":"Berthier Alpes S.a.s.",
    "wof:placetype":"venue"
},
  "geometry": {"coordinates":[6.43614,45.639965],"type":"Point"}
}