{
  "type": "Feature",
  "properties": {
    "iso:country":"FR",
    "sg:address":"Bellevue 10110 Bar sur Seine",
    "sg:orig_category":"Unclassifiable Establishments",
    "sg:phone":"+33 3 25 38 50 50",
    "sg:province":"Champagne",
    "wof:name":"C.a.v.e. S.a.",
    "wof:placetype":"venue"
},
  "geometry": {"coordinates":[4.38639,48.077702],"type":"Point"}
}