{
  "type": "Feature",
  "properties": {
    "addr:full":"300 Rue Vozerier 74800 Amancy Rhone-Alpes 74800",
    "addr:housenumber":"300",
    "addr:postcode":"74800;74800",
    "addr:street":"Rue Vozerier",
    "iso:country":"FR",
    "sg:address":"300 Rue Vozerier 74800 Amancy",
    "sg:classifiers":[
        {
            "category":"Farming",
            "subcategory":"Livestock Farm",
            "type":"Manufacturing & Wholesale Goods"
        }
    ],
    "sg:phone":"+33 4 50 03 25 66",
    "sg:postcode":"74800",
    "sg:province":"Rhone-Alpes",
    "sg:tags":[
        "breeding",
        "agriculture",
        "animal"
    ],
    "wof:name":"Pelizzari Christian Et Fils Sa - Sa Bopre Sa Porcs De Bourgogne",
    "wof:placetype":"venue"
},
  "geometry": {"coordinates":[6.341644,46.065968],"type":"Point"}
}