{
  "type": "Feature",
  "properties": {
    "iso:country":"FR",
    "sg:address":"ZI La Croix Rouge",
    "sg:city":"Vern sur Seiche",
    "sg:orig_category":"Unclassifiable Establishments",
    "sg:phone":"+33 2 99 04 85 85",
    "sg:postcode":"35770",
    "sg:province":"Bretagne",
    "wof:name":"Cewe Color S.a.",
    "wof:placetype":"venue"
},
  "geometry": {"coordinates":[-1.604871,48.050728],"type":"Point"}
}