{
  "type": "Feature",
  "properties": {
    "addr:full":"5, Rue Pasteur, 34430 Saint Jean de V\u00e9das Languedoc-Roussillon 34430",
    "addr:housenumber":"5",
    "addr:postcode":"34430;34430",
    "addr:street":"Rue Pasteur;Ve\u0301Das",
    "iso:country":"FR",
    "sg:address":"5, Rue Pasteur, 34430 Saint Jean de V\u00e9das",
    "sg:orig_category":"Non-Classified Establishments",
    "sg:phone":"+33 4 67 69 09 49",
    "sg:postcode":"34430",
    "sg:province":"Languedoc-Roussillon",
    "wof:name":"Auxitane Propret\u00e9 S.a.",
    "wof:placetype":"venue"
},
  "geometry": {"coordinates":[3.827355,43.576775],"type":"Point"}
}