{
  "type": "Feature",
  "properties": {
    "addr:full":"1 Rue Jean Pierre Timbaud 78187 Montigny Le Bretonneux Bretagne",
    "addr:housenumber":"1",
    "addr:postcode":"78187",
    "addr:street":"Rue Jean Pierre Timbaud;Bretonneux",
    "iso:country":"FR",
    "sg:address":"1 Rue Jean Pierre Timbaud 78187 Montigny Le Bretonneux",
    "sg:classifiers":[
        {
            "category":"Professional",
            "subcategory":"Engineering",
            "type":"Services"
        }
    ],
    "sg:phone":"+33 1 30 47 30 47",
    "sg:province":"Bretagne",
    "sg:tags":[
        "machine",
        "-",
        "mechanical"
    ],
    "wof:name":"Meto",
    "wof:placetype":"venue"
},
  "geometry": {"coordinates":[2.03644,48.79319],"type":"Point"}
}