{
  "type": "Feature",
  "properties": {
    "addr:full":"Avenue 1\u00e8re 12\u00e8me Rue 06510 Carros Corse",
    "addr:postcode":"06510",
    "addr:street":"Avenue 1E\u0300Re 12E\u0300Me Rue",
    "iso:country":"FR",
    "sg:address":"Avenue 1\u00e8re 12\u00e8me Rue 06510 Carros",
    "sg:classifiers":[
        {
            "category":"Professional",
            "type":"Services"
        }
    ],
    "sg:phone":"+33 4 92 08 50 00",
    "sg:province":"Corse",
    "sg:tags":[
        "transport",
        "road"
    ],
    "wof:name":"Alliance Bailiy Bedel International",
    "wof:placetype":"venue"
},
  "geometry": {"coordinates":[7.194835,43.803421],"type":"Point"}
}