{
  "type": "Feature",
  "properties": {
    "addr:full":"65 Bd C\u00f4te Blatin 63000 Clermont Ferrand Clermont-Ferrand Auvergne 63000",
    "addr:housenumber":"65",
    "addr:postcode":"63000;63000",
    "addr:street":"Bd Co\u0302Te Blatin",
    "iso:country":"FR",
    "sg:address":"65 Bd C\u00f4te Blatin 63000 Clermont Ferrand",
    "sg:city":"Clermont-Ferrand",
    "sg:classifiers":[
        {
            "category":"Manufacturing",
            "subcategory":"Printing",
            "type":"Manufacturing & Wholesale Goods"
        }
    ],
    "sg:phone":"+33 4 73 93 13 96",
    "sg:postcode":"63000",
    "sg:province":"Auvergne",
    "sg:tags":[
        "publishing"
    ],
    "wof:name":"Chaumeil Repro Sa",
    "wof:placetype":"venue"
},
  "geometry": {"coordinates":[3.088152,45.767956],"type":"Point"}
}