{
  "type": "Feature",
  "properties": {
    "addr:full":"2, Av. Rhin et Danube, 34500 B\u00e9ziers Languedoc-Roussillon 34500",
    "addr:postcode":"34500;34500",
    "addr:street":"Av. Rhin Et Danube",
    "iso:country":"FR",
    "sg:address":"2, Av. Rhin et Danube, 34500 B\u00e9ziers",
    "sg:orig_category":"Non-Classified Establishments",
    "sg:phone":"+33 4 67 31 11 34",
    "sg:postcode":"34500",
    "sg:province":"Languedoc-Roussillon",
    "wof:name":"Etablissements Bouzat E.u.r.l.",
    "wof:placetype":"venue"
},
  "geometry": {"coordinates":[3.225809,43.353294],"type":"Point"}
}