{
  "type": "Feature",
  "properties": {
    "iso:country":"FR",
    "sg:address":"1 rue Jean-Jacques Rousseau 94200 Ivry sur Seine",
    "sg:classifiers":[
        {
            "category":"Professional",
            "subcategory":"Printing & Photocopies",
            "type":"Services"
        }
    ],
    "sg:phone":"+33 1 46 72 15 87",
    "sg:province":"Ile de France",
    "sg:tags":[
        "offset"
    ],
    "wof:name":"Etablissement Martinenq Sa",
    "wof:placetype":"venue"
},
  "geometry": {"coordinates":[2.390719,48.821289],"type":"Point"}
}