{
  "type": "Feature",
  "properties": {
    "addr:full":"Rue Soeur Goby 21420 Savigny Les Beaune Aloxe-Corton Bourgogne 21420",
    "addr:postcode":"21420;21420",
    "addr:street":"Rue Soeur Goby",
    "iso:country":"FR",
    "sg:address":"Rue Soeur Goby 21420 Savigny Les Beaune",
    "sg:city":"Aloxe-Corton",
    "sg:classifiers":[
        {
            "category":"Food Court",
            "type":"Food & Drink"
        }
    ],
    "sg:phone":"+33 3 80 21 52 31",
    "sg:postcode":"21420",
    "sg:province":"Bourgogne",
    "sg:tags":[
        "product",
        "related"
    ],
    "wof:name":"Domaine Chandon De Briailles",
    "wof:placetype":"venue"
},
  "geometry": {"coordinates":[4.82173,47.061069],"type":"Point"}
}