{
  "type": "Feature",
  "properties": {
    "addr:full":"11, Rue de l'Industrie, 18600 Sancoins Sancoins Centre 18600",
    "addr:housenumber":"11;sancoins",
    "addr:postcode":"18600;18600",
    "addr:street":"Rue De L'Industrie",
    "iso:country":"FR",
    "sg:address":"11, Rue de l'Industrie, 18600 Sancoins",
    "sg:city":"Sancoins",
    "sg:orig_category":"Non-Classified Establishments",
    "sg:phone":"+33 2 48 74 68 37",
    "sg:postcode":"18600",
    "sg:province":"Centre",
    "wof:name":"Charlet Composites E.u.r.l.",
    "wof:placetype":"venue"
},
  "geometry": {"coordinates":[2.919199,46.828014],"type":"Point"}
}