{
  "type": "Feature",
  "properties": {
    "addr:full":"Ch\u00e2teau d'Issan Cantenac Aquitaine 33460",
    "addr:housenumber":"cantenac",
    "addr:postcode":"33460",
    "iso:country":"FR",
    "sg:address":"Ch\u00e2teau d'Issan",
    "sg:city":"Cantenac",
    "sg:orig_category":"Non-Classified Establishments",
    "sg:phone":"+33 5 57 88 35 91",
    "sg:postcode":"33460",
    "sg:province":"Aquitaine",
    "wof:name":"Soci\u00e9t\u00e9 Fermi\u00e8re Viticole De Cantenac S.c.a.",
    "wof:placetype":"venue"
},
  "geometry": {"coordinates":[-0.639836,45.020943],"type":"Point"}
}