{
  "type": "Feature",
  "properties": {
    "iso:country":"FR",
    "sg:address":"533 route de Toulouse; Bordeaux",
    "sg:city":"Bordeaux",
    "sg:classifiers":[
        {
            "category":"Banks & Credit Unions",
            "subcategory":"Bank",
            "type":"Services"
        }
    ],
    "sg:phone":"+33 3356758530",
    "sg:postcode":"33100",
    "sg:province":"Aquitaine",
    "wof:name":"Cr\u00e9dit Mutuel Sud Ouest",
    "wof:placetype":"venue"
},
  "geometry": {"coordinates":[-0.573549,44.81266],"type":"Point"}
}