{
  "type": "Feature",
  "properties": {
    "addr:full":"25 Bis Av Jules Cantini 13006 Marseille Midi Pyr\u00e9n\u00e9es",
    "addr:housenumber":"25 bis",
    "addr:postcode":"13006",
    "addr:street":"Av Jules Cantini",
    "iso:country":"FR",
    "sg:address":"25 Bis Av Jules Cantini 13006 Marseille",
    "sg:classifiers":[
        {
            "category":"Banks & Credit Unions",
            "subcategory":"Financial Services",
            "type":"Services"
        }
    ],
    "sg:phone":"+33 4 91 32 80 60",
    "sg:province":"Midi Pyr\u00e9n\u00e9es",
    "sg:tags":[
        "banking",
        "insurance",
        "institution",
        "finance"
    ],
    "wof:name":"Union De Credit Pour Le Batiment",
    "wof:placetype":"venue"
},
  "geometry": {"coordinates":[5.385288,43.28511],"type":"Point"}
}