{
  "type": "Feature",
  "properties": {
    "addr:full":"B.P. 90204, 60740 Saint Maximin^^325, Rue Paul Langevin, 60740 Saint Maximin Picardie",
    "addr:housenumber":"60740",
    "addr:postcode":"60740",
    "addr:street":"Saint;Rue Paul Langevin",
    "iso:country":"FR",
    "sg:address":"B.P. 90204, 60740 Saint Maximin^^325, Rue Paul Langevin, 60740 Saint Maximin",
    "sg:orig_category":"Non-Classified Establishments",
    "sg:phone":"+33 3 44 64 10 00",
    "sg:province":"Picardie",
    "wof:name":"R\u00f6hm S.a.r.l.",
    "wof:placetype":"venue"
},
  "geometry": {"coordinates":[2.454171,49.220432],"type":"Point"}
}