{
  "type": "Feature",
  "properties": {
    "addr:full":"B.P. 24, 41600 Nouan le Fuzelier^^ZA les Loati\u00e8res, 41600 Nouan le Fuzelier Chaon Centre 41600",
    "addr:postcode":"41600;41600;41600",
    "addr:street":"B.P. 24;Fuzelier^^Za;Loatie\u0300Res",
    "iso:country":"FR",
    "sg:address":"B.P. 24, 41600 Nouan le Fuzelier^^ZA les Loati\u00e8res, 41600 Nouan le Fuzelier",
    "sg:city":"Chaon",
    "sg:orig_category":"Non-Classified Establishments",
    "sg:phone":"+33 2 54 88 83 83",
    "sg:postcode":"41600",
    "sg:province":"Centre",
    "wof:name":"Dianelec S.a.",
    "wof:placetype":"venue"
},
  "geometry": {"coordinates":[2.035673,47.536289],"type":"Point"}
}