{
  "type": "Feature",
  "properties": {
    "addr:full":"Zone Industrielle Yvetot Haute Normandie 76190",
    "addr:postcode":"76190",
    "addr:street":"Zone Industrielle;Haute Normandie",
    "iso:country":"FR",
    "sg:address":"Zone Industrielle",
    "sg:city":"Yvetot",
    "sg:orig_category":"Unclassifiable Establishments",
    "sg:phone":"+33 2 35 95 45 54",
    "sg:postcode":"76190",
    "sg:province":"Haute Normandie",
    "wof:name":"Blondel S.a.",
    "wof:placetype":"venue"
},
  "geometry": {"coordinates":[0.75448,49.616741],"type":"Point"}
}