{
  "type": "Feature",
  "properties": {
    "addr:full":"Zac Du Port 90850 Essert Franche Comt\u00e9 90850",
    "addr:postcode":"90850;90850",
    "addr:street":"Zac Du Port;Franche Comte\u0301",
    "iso:country":"FR",
    "sg:address":"Zac Du Port 90850 Essert",
    "sg:classifiers":[
        {
            "category":"Manufacturing",
            "subcategory":"Metals",
            "type":"Manufacturing & Wholesale Goods"
        }
    ],
    "sg:phone":"+33 3 84 54 03 78",
    "sg:postcode":"90850",
    "sg:province":"Franche Comt\u00e9",
    "sg:tags":[
        "metallurgy",
        "metalworking",
        "processing"
    ],
    "wof:name":"Sarl Petit Jean Pascal",
    "wof:placetype":"venue"
},
  "geometry": {"coordinates":[6.816372,47.632938],"type":"Point"}
}