{
  "type": "Feature",
  "properties": {
    "iso:country":"FR",
    "sg:address":"Rte Bazoin 85420 Damvix",
    "sg:classifiers":[
        {
            "category":"Manufacturing",
            "subcategory":"Metals",
            "type":"Manufacturing & Wholesale Goods"
        }
    ],
    "sg:phone":"+33 2 51 87 15 45",
    "sg:postcode":"85420",
    "sg:province":"Pays de Loire",
    "sg:tags":[
        "metallurgy",
        "steel",
        "metalworking"
    ],
    "wof:name":"T F C M -s T P G Sa",
    "wof:placetype":"venue"
},
  "geometry": {"coordinates":[-0.774609,46.318165],"type":"Point"}
}