{
  "type": "Feature",
  "properties": {
    "addr:full":"125, Rue Anatole France, 18100 Vierzon Vierzon Centre 18100",
    "addr:housenumber":"125;vierzon",
    "addr:postcode":"18100;18100",
    "addr:street":"Rue Anatole France",
    "iso:country":"FR",
    "sg:address":"125, Rue Anatole France, 18100 Vierzon",
    "sg:city":"Vierzon",
    "sg:orig_category":"Unclassifiable Establishments",
    "sg:phone":"+33 2 48 75 22 15",
    "sg:postcode":"18100",
    "sg:province":"Centre",
    "wof:name":"Voisin Espaces Verts S.a.r.l.",
    "wof:placetype":"venue"
},
  "geometry": {"coordinates":[2.047485,47.222836],"type":"Point"}
}