{
  "type": "Feature",
  "properties": {
    "addr:full":"98, Av. des Roissy Hauts, 91540 Ormoy Ile de France",
    "addr:postcode":"91540;ile",
    "addr:street":"98 Av. Des Roissy Hauts",
    "iso:country":"FR",
    "sg:address":"98, Av. des Roissy Hauts, 91540 Ormoy",
    "sg:orig_category":"Unclassifiable Establishments",
    "sg:phone":"+33 1 69 90 07 07",
    "sg:province":"Ile de France",
    "wof:name":"Coffima S.a. - Comptoir Fran\u00e7ais Fournitures Automobiles",
    "wof:placetype":"venue"
},
  "geometry": {"coordinates":[2.464183,48.570889],"type":"Point"}
}