{
  "type": "Feature",
  "properties": {
    "iso:country":"FR",
    "sg:address":"184 B Bd De Cr\u00e9teil 94100 St Maur Des Foss\u00e9s",
    "sg:classifiers":[
        {
            "category":"Manufacturing",
            "subcategory":"Wood Products",
            "type":"Manufacturing & Wholesale Goods"
        }
    ],
    "sg:phone":"+33 1 55 12 18 18",
    "sg:province":"Ile de France",
    "sg:tags":[
        "professional",
        "furniture"
    ],
    "wof:name":"Schmit Tradition Sarl",
    "wof:placetype":"venue"
},
  "geometry": {"coordinates":[2.496286,48.797817],"type":"Point"}
}