{
  "type": "Feature",
  "properties": {
    "addr:full":"Pa De Broc\u00e9liande 56430 Mauron Mauron Bretagne 56430",
    "addr:postcode":"56430;56430",
    "addr:street":"De Broce\u0301Liande;Mauron",
    "iso:country":"FR",
    "sg:address":"Pa De Broc\u00e9liande 56430 Mauron",
    "sg:city":"Mauron",
    "sg:classifiers":[
        {
            "category":"Wholesale",
            "subcategory":"Vending Machines",
            "type":"Manufacturing & Wholesale Goods"
        }
    ],
    "sg:phone":"+33 2 97 22 62 63",
    "sg:postcode":"56430",
    "sg:province":"Bretagne",
    "sg:tags":[
        "product",
        "food",
        "processing",
        "-",
        "related",
        "equipment",
        "engineering",
        "machinery",
        "mechanical"
    ],
    "wof:name":"Armor Inox Sa",
    "wof:placetype":"venue"
},
  "geometry": {"coordinates":[-2.283715,48.078529],"type":"Point"}
}