{
  "type": "Feature",
  "properties": {
    "addr:full":"4 avenue de Toulouse 31650 St Orens De Gameville Midi Pyr\u00e9n\u00e9es 31650",
    "addr:housenumber":"4",
    "addr:postcode":"31650;31650",
    "addr:street":"Avenue De Toulouse",
    "iso:country":"FR",
    "sg:address":"4 avenue de Toulouse 31650 St Orens De Gameville",
    "sg:orig_category":"Customs Agencies, Declarants",
    "sg:phone":"+33 5 62 24 80 20",
    "sg:postcode":"31650",
    "sg:province":"Midi Pyr\u00e9n\u00e9es",
    "wof:name":"La Catalane De Transit Sarl",
    "wof:placetype":"venue"
},
  "geometry": {"coordinates":[1.514421,43.564499],"type":"Point"}
}