{
  "type": "Feature",
  "properties": {
    "addr:full":"Les Oudilles Decize Bourgogne 58300",
    "addr:postcode":"58300",
    "addr:street":"Bourgogne",
    "iso:country":"FR",
    "sg:address":"Les Oudilles",
    "sg:city":"Decize",
    "sg:orig_category":"Unclassifiable Establishments",
    "sg:phone":"+33 3 86 50 73 32",
    "sg:postcode":"58300",
    "sg:province":"Bourgogne",
    "wof:name":"Bouillet",
    "wof:placetype":"venue"
},
  "geometry": {"coordinates":[3.43775,46.764919],"type":"Point"}
}