{
  "type": "Feature",
  "properties": {
    "iso:country":"FR",
    "sg:address":"41",
    "sg:city":"Halles; S. Nazaire",
    "sg:classifiers":[
        {
            "category":"Banks & Credit Unions",
            "subcategory":"Bank",
            "type":"Services"
        }
    ],
    "sg:phone":"+33 3340220366",
    "sg:province":"Champagne",
    "wof:name":"Cr\u00e9dit Mutuel De Saint Gohard",
    "wof:placetype":"venue"
},
  "geometry": {"coordinates":[-75.605957,37.787762],"type":"Point"}
}