{
  "type": "Feature",
  "properties": {
    "addr:full":"45 Rue Pierre Baour 33083 Bordeaux Cedex Bordeaux Aquitaine 33100",
    "addr:housenumber":"45",
    "addr:postcode":"33083 bordeaux cedex;33100",
    "addr:street":"Rue Pierre Baour",
    "iso:country":"FR",
    "sg:address":"45 Rue Pierre Baour 33083 Bordeaux Cedex",
    "sg:city":"Bordeaux",
    "sg:classifiers":[
        {
            "category":"Professional",
            "subcategory":"Engineering",
            "type":"Services"
        }
    ],
    "sg:phone":"+33 5 57 19 16 30",
    "sg:postcode":"33100",
    "sg:province":"Aquitaine",
    "sg:tags":[
        "machine",
        "-",
        "mechanical"
    ],
    "wof:name":"Etablissements Maleyran Freres Sa",
    "wof:placetype":"venue"
},
  "geometry": {"coordinates":[-0.547909,44.890701],"type":"Point"}
}