{
  "type": "Feature",
  "properties": {
    "iso:country":"FR",
    "sg:address":"12, Cours Ren\u00e9 Teille, 81200 Mazamet",
    "sg:orig_category":"Unclassifiable Establishments",
    "sg:phone":"+33 5 63 97 56 70",
    "sg:province":"Midi Pyr\u00e9n\u00e9es",
    "wof:name":"B.p.t.a. - Banque Populaire Du Tarn Et De L'aveyron",
    "wof:placetype":"venue"
},
  "geometry": {"coordinates":[2.375279,43.489662],"type":"Point"}
}