{
  "type": "Feature",
  "properties": {
    "iso:country":"FR",
    "sg:address":"69 Rue De La Belle Etoile 95701 ROISSY EN FRANCE",
    "sg:classifiers":[
        {
            "category":"Shopping",
            "subcategory":"Computers & Home Electronics",
            "type":"Retail Goods"
        }
    ],
    "sg:phone":"+33 1 49 90 75 75",
    "sg:province":"Aquitaine",
    "sg:tags":[
        "electronic",
        "module"
    ],
    "wof:name":"Stock N Source S.a.",
    "wof:placetype":"venue"
},
  "geometry": {"coordinates":[2.501656,48.980232],"type":"Point"}
}