{
  "type": "Feature",
  "properties": {
    "addr:full":"1 Rue De La Moucheti\u00e8re 45142 St Jean De La Ruelle Cedex La Mouche Basse Normandie 50320",
    "addr:housenumber":"1",
    "addr:postcode":"45142;50320",
    "addr:street":"Rue De La Mouchetie\u0300Re;La Ruelle Cedex",
    "iso:country":"FR",
    "sg:address":"1 Rue De La Moucheti\u00e8re 45142 St Jean De La Ruelle Cedex",
    "sg:city":"La Mouche",
    "sg:classifiers":[
        {
            "category":"Manufacturing",
            "subcategory":"Tools & Machinery",
            "type":"Manufacturing & Wholesale Goods"
        }
    ],
    "sg:phone":"+33 2 38 71 33 33",
    "sg:postcode":"50320",
    "sg:province":"Basse Normandie",
    "sg:tags":[
        "metallurgy",
        "metal",
        "-",
        "metalworking",
        "machine",
        "equipment",
        "engineering",
        "mechanical"
    ],
    "wof:name":"Fimatec Sa",
    "wof:placetype":"venue"
},
  "geometry": {"coordinates":[1.857382,47.911667],"type":"Point"}
}