{
  "type": "Feature",
  "properties": {
    "iso:country":"FR",
    "sg:address":"2",
    "sg:city":"Jacques Daguerre 92500 Rueil Malmaison",
    "sg:classifiers":[
        {
            "category":"Professional",
            "subcategory":"Computer Services",
            "type":"Services"
        }
    ],
    "sg:phone":"+33 1 47 49 36 66",
    "sg:postcode":"92500",
    "sg:province":"Ile de France",
    "sg:tags":[
        "information",
        "technology",
        "software"
    ],
    "wof:name":"Generix",
    "wof:placetype":"venue"
},
  "geometry": {"coordinates":[2.168869,48.888577],"type":"Point"}
}