{
  "type": "Feature",
  "properties": {
    "iso:country":"FR",
    "sg:address":"B.P. 123, 71305 Montceau les Mines C\u00e9dex^^6, Rue de Gueugnon, 71300 Montceau les Mines",
    "sg:city":"Saint-Berain-sous-Sanvignes",
    "sg:orig_category":"Non-Classified Establishments",
    "sg:phone":"+33 3 85 67 75 94",
    "sg:postcode":"71300",
    "sg:province":"Bourgogne",
    "wof:name":"Optima Soci\u00e9t\u00e9 Nouvelle E.u.r.l.",
    "wof:placetype":"venue"
},
  "geometry": {"coordinates":[4.498485,46.618446],"type":"Point"}
}