{
  "type": "Feature",
  "properties": {
    "addr:full":"1 Rue Pont D'Albord 02240 Ribemont Picardie 02240",
    "addr:housenumber":"1",
    "addr:postcode":"02240;02240",
    "addr:street":"Rue Pont D'Albord;Picardie",
    "iso:country":"FR",
    "sg:address":"1 Rue Pont D'Albord 02240 Ribemont",
    "sg:classifiers":[
        {
            "category":"Manufacturing",
            "subcategory":"Tools & Machinery",
            "type":"Manufacturing & Wholesale Goods"
        }
    ],
    "sg:phone":"+33 3 23 63 71 94",
    "sg:postcode":"02240",
    "sg:province":"Picardie",
    "sg:tags":[
        "metallurgy",
        "metalworking"
    ],
    "wof:name":"Tannerie Vallee De L'oise Sa",
    "wof:placetype":"venue"
},
  "geometry": {"coordinates":[2.527896,49.90873],"type":"Point"}
}