{
  "type": "Feature",
  "properties": {
    "iso:country":"FR",
    "sg:address":"227, Rue d'Alembert - ZA Champs Rolland, 38150 Salaise sur Sanne",
    "sg:orig_category":"Unclassifiable Establishments",
    "sg:phone":"+33 4 74 86 28 49",
    "sg:postcode":"38150",
    "sg:province":"Rhone-Alpes",
    "wof:name":"Ariane Protection S.a.r.l.",
    "wof:placetype":"venue"
},
  "geometry": {"coordinates":[4.801457,45.349232],"type":"Point"}
}