{
  "type": "Feature",
  "properties": {
    "addr:full":"Rue Gustave Fouillaron Cholet Pays de Loire 49300",
    "addr:postcode":"49300",
    "addr:street":"Rue Gustave Fouillaron Cholet",
    "iso:country":"FR",
    "sg:address":"Rue Gustave Fouillaron",
    "sg:city":"Cholet",
    "sg:orig_category":"Unclassifiable Establishments",
    "sg:phone":"+33 2 41 64 80 20",
    "sg:postcode":"49300",
    "sg:province":"Pays de Loire",
    "wof:name":"Soci\u00e9t\u00e9 Nouvelle Scavo S.a.",
    "wof:placetype":"venue"
},
  "geometry": {"coordinates":[-0.929364,47.026146],"type":"Point"}
}