{
  "type": "Feature",
  "properties": {
    "iso:country":"FR",
    "sg:address":"18, Bd Charles de Gaulle, 91540 Mennecy",
    "sg:orig_category":"Unclassifiable Establishments",
    "sg:phone":"+33 1 64 57 01 09",
    "sg:province":"Ile de France",
    "wof:name":"Sindex N.c.o. S.a.r.l.",
    "wof:placetype":"venue"
},
  "geometry": {"coordinates":[2.446825,48.566902],"type":"Point"}
}