{
  "type": "Feature",
  "properties": {
    "addr:full":"Zi De Lavialle Le Vigean Auvergne 15200",
    "addr:postcode":"15200",
    "addr:street":"Zi De Lavialle Le Vigean",
    "iso:country":"FR",
    "sg:address":"Zi De Lavialle",
    "sg:city":"Le Vigean",
    "sg:classifiers":[
        {
            "category":"Banks & Credit Unions",
            "subcategory":"Financial Services",
            "type":"Services"
        }
    ],
    "sg:phone":"+33 4 73 35 40 79",
    "sg:postcode":"15200",
    "sg:province":"Auvergne",
    "sg:tags":[
        "banking",
        "finance",
        "insurance"
    ],
    "wof:name":"Societe Cantalienne De Travaux Telephoniques Et Electriques Socattel",
    "wof:placetype":"venue"
},
  "geometry": {"coordinates":[2.353329,45.226444],"type":"Point"}
}