{
  "type": "Feature",
  "properties": {
    "addr:full":"Chemin de Saint Gibrien Ch\u00e2lons en Champagne Champagne 51000",
    "addr:postcode":"51000",
    "addr:street":"Chemin De Saint Gibrien",
    "iso:country":"FR",
    "sg:address":"Chemin de Saint Gibrien",
    "sg:city":"Ch\u00e2lons en Champagne",
    "sg:orig_category":"Non-Classified Establishments",
    "sg:phone":"+33 3 26 68 03 98",
    "sg:postcode":"51000",
    "sg:province":"Champagne",
    "wof:name":"Sotraser S.a.",
    "wof:placetype":"venue"
},
  "geometry": {"coordinates":[4.337578,48.961266],"type":"Point"}
}