{
  "type": "Feature",
  "properties": {
    "addr:full":"B.P. 326, 95617 Cergy Pontoise C\u00e9dex^^Rue Rosa Luxembourg - Parc d'Activit\u00e9s les Bellevues - B\u00e2t. le Centre",
    "addr:housenumber":"b.p. 326;ba\u0302t",
    "addr:postcode":"95617",
    "iso:country":"FR",
    "sg:address":"B.P. 326, 95617 Cergy Pontoise C\u00e9dex^^Rue Rosa Luxembourg - Parc d'Activit\u00e9s les Bellevues - B\u00e2t. le",
    "sg:orig_category":"Non-Classified Establishments",
    "sg:phone":"+33 1 39 09 90 90",
    "sg:province":"Centre",
    "wof:name":"Euchner France",
    "wof:placetype":"venue"
},
  "geometry": {"coordinates":[6.1333,49.815281],"type":"Point"}
}