{
  "type": "Feature",
  "properties": {
    "iso:country":"FR",
    "sg:address":"10 Mail Ouest 45300 Pithiviers",
    "sg:city":"Pithiviers",
    "sg:classifiers":[
        {
            "category":"Travel",
            "subcategory":"Hotels & Motels",
            "type":"Entertainment"
        }
    ],
    "sg:phone":"+33 2 38 30 40 30",
    "sg:postcode":"45300",
    "sg:province":"Centre",
    "sg:tags":[
        "hotels",
        "business",
        "restaurant"
    ],
    "wof:name":"Le Relais De La Poste Sa",
    "wof:placetype":"venue"
},
  "geometry": {"coordinates":[2.253064,48.174068],"type":"Point"}
}