{
  "type": "Feature",
  "properties": {
    "addr:full":"34, Rue Casimir P\u00e9rier, 69002 Lyon Rhone-Alpes 69002",
    "addr:housenumber":"34",
    "addr:postcode":"69002;69002",
    "addr:street":"Rue Casimir Pe\u0301Rier",
    "iso:country":"FR",
    "sg:address":"34, Rue Casimir P\u00e9rier, 69002 Lyon",
    "sg:orig_category":"Unclassifiable Establishments",
    "sg:phone":"+33 4 72 77 82 70",
    "sg:postcode":"69002",
    "sg:province":"Rhone-Alpes",
    "wof:name":"Dumont Et Compagnie S.a.",
    "wof:placetype":"venue"
},
  "geometry": {"coordinates":[4.828975,45.759399],"type":"Point"}
}