{
  "type": "Feature",
  "properties": {
    "iso:country":"FR",
    "sg:address":"B.P. 69, 63016 Clermont Ferrand C\u00e9dex^^22, Jules Verne, 63000 Clermont Ferrand",
    "sg:city":"Clermont-Ferrand",
    "sg:orig_category":"Non-Classified Establishments",
    "sg:phone":"+33 4 73 98 38 00",
    "sg:postcode":"63000",
    "sg:province":"Auvergne",
    "wof:name":"A.c.c. Ing\u00e9nierie Et Maintenance S.a.",
    "wof:placetype":"venue"
},
  "geometry": {"coordinates":[3.08183,45.777618],"type":"Point"}
}