{
  "type": "Feature",
  "properties": {
    "iso:country":"FR",
    "sg:address":"80 Rue Du Bois Girault 45077 Orl\u00e9ans Cedex 2",
    "sg:classifiers":[
        {
            "category":"Utilities",
            "subcategory":"Telephone",
            "type":"Services"
        }
    ],
    "sg:phone":"+33 2 38 51 51 51",
    "sg:province":"Centre",
    "sg:tags":[
        "telecommunication"
    ],
    "wof:name":"Telephonie Fran\u00c7aise Du Centre Sarl",
    "wof:placetype":"venue"
},
  "geometry": {"coordinates":[1.925318,47.874748],"type":"Point"}
}