{
  "type": "Feature",
  "properties": {
    "iso:country":"FR",
    "sg:address":"10/12, Rue Victor Bize, 93700 Drancy",
    "sg:orig_category":"Unclassifiable Establishments",
    "sg:phone":"+33 1 48 96 91 80",
    "sg:province":"Ile de France",
    "wof:name":"S.i.a.t. S.a. - Soci\u00e9t\u00e9 Imprimerie Art Et Technique",
    "wof:placetype":"venue"
},
  "geometry": {"coordinates":[2.430438,48.917828],"type":"Point"}
}