{
  "type": "Feature",
  "properties": {
    "iso:country":"FR",
    "sg:address":"34, Bd de Bois Guilbert, 76000 Rouen",
    "sg:orig_category":"Unclassifiable Establishments",
    "sg:phone":"+33 2 35 52 55 88",
    "sg:province":"Haute Normandie",
    "wof:name":"Port Autonome De Rouen",
    "wof:placetype":"venue"
},
  "geometry": {"coordinates":[1.07207,49.444229],"type":"Point"}
}