{
  "type": "Feature",
  "properties": {
    "iso:country":"FR",
    "sg:address":"Rte de Caromb",
    "sg:city":"Carpentras",
    "sg:orig_category":"Unclassifiable Establishments",
    "sg:phone":"+33 4 90 63 07 16",
    "sg:postcode":"84200",
    "sg:province":"Aquitaine",
    "wof:name":"Kelatron - France S.a.",
    "wof:placetype":"venue"
},
  "geometry": {"coordinates":[5.074096,44.087151],"type":"Point"}
}