{
  "type": "Feature",
  "properties": {
    "addr:full":"B.P. 29, 01330 Villars les Dombes C\u00e9dex^^108, Rue de Bresse, 01330 Villars les Dombes Rhone-Alpes",
    "addr:postcode":"01330;01330",
    "addr:street":"B.P. 29;Rue De Bresse",
    "iso:country":"FR",
    "sg:address":"B.P. 29, 01330 Villars les Dombes C\u00e9dex^^108, Rue de Bresse, 01330 Villars les Dombes",
    "sg:orig_category":"Non-Classified Establishments",
    "sg:phone":"+33 4 74 98 07 96",
    "sg:province":"Rhone-Alpes",
    "wof:name":"Matherm - La Solution Infra-rouge S.a.s.",
    "wof:placetype":"venue"
},
  "geometry": {"coordinates":[5.01121,46.002338],"type":"Point"}
}