{
  "type": "Feature",
  "properties": {
    "addr:full":"16 rue Grande; Argenton; 36200 Argenton-sur-Creuse Centre 36200",
    "addr:housenumber":"16;argenton-sur-creuse",
    "addr:postcode":"36200;36200",
    "addr:street":"Rue Grande Argenton",
    "iso:country":"FR",
    "sg:address":"16 rue Grande; Argenton; 36200",
    "sg:city":"Argenton-sur-Creuse",
    "sg:classifiers":[
        {
            "category":"Banks & Credit Unions",
            "subcategory":"Bank",
            "type":"Services"
        }
    ],
    "sg:phone":"+33 3354240718",
    "sg:postcode":"36200",
    "sg:province":"Centre",
    "wof:name":"Banque Nationale De Paris",
    "wof:placetype":"venue"
},
  "geometry": {"coordinates":[1.561745,46.516987],"type":"Point"}
}