{
  "type": "Feature",
  "properties": {
    "addr:full":"82, Rte de Roquetoire, 62120 Aire sur la Lys Nord Pas-de-Calais",
    "addr:housenumber":"82",
    "addr:postcode":"62120",
    "addr:street":"Rte De Roquetoire;Aire;La Lys Nord",
    "iso:country":"FR",
    "sg:address":"82, Rte de Roquetoire, 62120 Aire sur la Lys",
    "sg:orig_category":"Non-Classified Establishments",
    "sg:phone":"+33 3 21 39 06 55",
    "sg:province":"Nord Pas-de-Calais",
    "wof:name":"Sanitaire Chauffe S.a.r.l.",
    "wof:placetype":"venue"
},
  "geometry": {"coordinates":[2.39073,50.648579],"type":"Point"}
}