{
  "type": "Feature",
  "properties": {
    "iso:country":"FR",
    "sg:address":"B.P. 207, 95106 Argenteuil C\u00e9dex^^18, Rue Jules Vercruysse, 95100 Argenteuil",
    "sg:orig_category":"Non-Classified Establishments",
    "sg:phone":"+33 1 34 10 57 17",
    "sg:province":"Ile de France",
    "wof:name":"Pivicat S.a.",
    "wof:placetype":"venue"
},
  "geometry": {"coordinates":[2.245075,48.942097],"type":"Point"}
}