{
  "type": "Feature",
  "properties": {
    "addr:full":"80, Rue de Metz, 57300 Hagondange Lorraine",
    "addr:housenumber":"80",
    "addr:postcode":"57300",
    "addr:street":"Rue De Metz",
    "iso:country":"FR",
    "sg:address":"80, Rue de Metz, 57300 Hagondange",
    "sg:orig_category":"Unclassifiable Establishments",
    "sg:phone":"+33 3 87 72 02 51",
    "sg:province":"Lorraine",
    "wof:name":"F.f.c. S.a. - Fonderie Fran\u00e7aise Chauffage",
    "wof:placetype":"venue"
},
  "geometry": {"coordinates":[6.170131,49.25053],"type":"Point"}
}