{
  "type": "Feature",
  "properties": {
    "addr:full":"58 Rue De L Oradou 63000 Clermont Ferrand Clermont-Ferrand Auvergne 63000",
    "addr:housenumber":"58",
    "addr:postcode":"63000;63000",
    "addr:street":"Rue De L Oradou",
    "iso:country":"FR",
    "sg:address":"58 Rue De L Oradou 63000 Clermont Ferrand",
    "sg:city":"Clermont-Ferrand",
    "sg:classifiers":[
        {
            "category":"Professional",
            "subcategory":"Printing & Photocopies",
            "type":"Services"
        }
    ],
    "sg:phone":"+33 4 73 92 05 70",
    "sg:postcode":"63000",
    "sg:province":"Auvergne",
    "sg:tags":[
        "publishing"
    ],
    "wof:name":"Editions Du Lys",
    "wof:placetype":"venue"
},
  "geometry": {"coordinates":[3.108605,45.770687],"type":"Point"}
}