{
  "type": "Feature",
  "properties": {
    "addr:full":"B.P. 71, 77543 Savigny le Temple C\u00e9dex^^10, Rue du Laiton, 77176 Savigny le Temple Ile de France 77176",
    "addr:postcode":"77543;77176;france 77176",
    "addr:street":"B.P. 71;Rue Du Laiton;Ile",
    "iso:country":"FR",
    "sg:address":"B.P. 71, 77543 Savigny le Temple C\u00e9dex^^10, Rue du Laiton, 77176 Savigny le Temple",
    "sg:orig_category":"Non-Classified Establishments",
    "sg:phone":"+33 1 64 41 75 04",
    "sg:postcode":"77176",
    "sg:province":"Ile de France",
    "wof:name":"Essinox Industrie S.a.",
    "wof:placetype":"venue"
},
  "geometry": {"coordinates":[2.58025,48.595909],"type":"Point"}
}