{
  "type": "Feature",
  "properties": {
    "iso:country":"FR",
    "sg:address":"B.P. 1, 80440 Dommartin^^Rue Emile Bourgeois, 80440 Dommartin",
    "sg:orig_category":"Non-Classified Establishments",
    "sg:phone":"+33 3 22 09 50 11",
    "sg:postcode":"80440",
    "sg:province":"Picardie",
    "wof:name":"Bourgeois E. S.a.",
    "wof:placetype":"venue"
},
  "geometry": {"coordinates":[2.393359,49.847733],"type":"Point"}
}