{
  "type": "Feature",
  "properties": {
    "iso:country":"FR",
    "sg:address":"8, Rue Florian, 93698 Pantin C\u00e9dex",
    "sg:orig_category":"Non-Classified Establishments",
    "sg:phone":"+33 1 48 10 34 80",
    "sg:province":"\u00cele-de-France",
    "wof:name":"Hemma Diffusion S.a.",
    "wof:placetype":"venue"
},
  "geometry": {"coordinates":[2.402446,48.894604],"type":"Point"}
}