{
  "type": "Feature",
  "properties": {
    "iso:country":"FR",
    "sg:address":"180, Rue Ernest Langlet, 60400 Vauchelles",
    "sg:orig_category":"Unclassifiable Establishments",
    "sg:phone":"+33 3 44 44 28 09",
    "sg:province":"Picardie",
    "wof:name":"R.e.m.i. S.a.r.l. - R\u00e9alisation Entretien Et Montage Industriel",
    "wof:placetype":"venue"
},
  "geometry": {"coordinates":[2.964146,49.587933],"type":"Point"}
}