{
  "type": "Feature",
  "properties": {
    "iso:country":"FR",
    "sg:address":"11 pl Monteil; Pessac",
    "sg:classifiers":[
        {
            "category":"Banks & Credit Unions",
            "subcategory":"Bank",
            "type":"Services"
        }
    ],
    "sg:phone":"+33 3356364366",
    "sg:province":"Aquitaine",
    "wof:name":"Soci\u00e9t\u00e9 G\u00e9n\u00e9rale",
    "wof:placetype":"venue"
},
  "geometry": {"coordinates":[-0.647457,44.80188],"type":"Point"}
}