{
  "type": "Feature",
  "properties": {
    "addr:full":"Moulin de la Giraudi\u00e8re Brussieu Rhone-Alpes 69690",
    "addr:postcode":"69690",
    "addr:street":"Moulin De La;Rhone-Alpes",
    "iso:country":"FR",
    "sg:address":"Moulin de la Giraudi\u00e8re",
    "sg:city":"Brussieu",
    "sg:orig_category":"Non-Classified Establishments",
    "sg:phone":"+33 4 74 70 85 06",
    "sg:postcode":"69690",
    "sg:province":"Rhone-Alpes",
    "wof:name":"Soci\u00e9t\u00e9 Moulin De La Giraudi\u00e8re Lotte S.a.r.l.",
    "wof:placetype":"venue"
},
  "geometry": {"coordinates":[4.543073,45.752724],"type":"Point"}
}