{
  "type": "Feature",
  "properties": {
    "iso:country":"FR",
    "sg:address":"6 rue de l'Industrie 89100 Sens",
    "sg:city":"Sens",
    "sg:classifiers":[
        {
            "category":"Home & Garden",
            "subcategory":"Household Appliances",
            "type":"Retail Goods"
        }
    ],
    "sg:phone":"+33 3 86 83 90 90",
    "sg:postcode":"89100",
    "sg:province":"Bourgogne",
    "sg:tags":[
        "electric"
    ],
    "wof:name":"White And Brown Sa",
    "wof:placetype":"venue"
},
  "geometry": {"coordinates":[3.29621,48.205719],"type":"Point"}
}