{
  "type": "Feature",
  "properties": {
    "iso:country":"FR",
    "sg:address":"2, Rue Louis Pergaud, 94700 Maisons Alfort",
    "sg:orig_category":"Unclassifiable Establishments",
    "sg:phone":"+33 1 43 53 52 51",
    "sg:province":"Ile de France",
    "wof:name":"Mediatel Groupe Seritex S.a.",
    "wof:placetype":"venue"
},
  "geometry": {"coordinates":[2.444793,48.803066],"type":"Point"}
}