{
  "type": "Feature",
  "properties": {
    "addr:full":"7, Rue Principale, 71530 Crissey Crissey Bourgogne 71530",
    "addr:housenumber":"7",
    "addr:postcode":"71530;71530",
    "addr:street":"Rue Principale",
    "iso:country":"FR",
    "sg:address":"7, Rue Principale, 71530 Crissey",
    "sg:city":"Crissey",
    "sg:orig_category":"Unclassifiable Establishments",
    "sg:phone":"+33 3 85 97 28 00",
    "sg:postcode":"71530",
    "sg:province":"Bourgogne",
    "wof:name":"Apco Technologies S.a.",
    "wof:placetype":"venue"
},
  "geometry": {"coordinates":[4.869268,46.812057],"type":"Point"}
}