{
  "type": "Feature",
  "properties": {
    "iso:country":"FR",
    "sg:address":"51 Av Du G\u00e9n\u00e9ral Michel Bizot 75012 Paris",
    "sg:classifiers":[
        {
            "category":"Professional",
            "subcategory":"Engineering",
            "type":"Services"
        }
    ],
    "sg:phone":"+33 1 43 07 51 12",
    "sg:postcode":"75012",
    "sg:province":"Ile de France",
    "sg:tags":[
        "machine",
        "-",
        "mechanical"
    ],
    "wof:name":"Otrad",
    "wof:placetype":"venue"
},
  "geometry": {"coordinates":[2.40125,48.835209],"type":"Point"}
}