{
  "type": "Feature",
  "properties": {
    "addr:full":"32240 Lias D Armagnac Midi Pyr\u00e9n\u00e9es",
    "addr:postcode":"32240",
    "iso:country":"FR",
    "sg:address":"32240 Lias D Armagnac",
    "sg:classifiers":[
        {
            "category":"Home & Garden",
            "subcategory":"Furniture",
            "type":"Retail Goods"
        }
    ],
    "sg:phone":"+33 5 62 09 64 63",
    "sg:province":"Midi Pyr\u00e9n\u00e9es",
    "sg:tags":[
        "wood"
    ],
    "wof:name":"Etablissements R Dalies Et Fils",
    "wof:placetype":"venue"
},
  "geometry": {"coordinates":[-0.073049,43.865196],"type":"Point"}
}