{
  "type": "Feature",
  "properties": {
    "addr:full":"B.P. Case Postale : 80067, 60304 Senlis^^52, Av. F\u00e9lix Louat, 60300 Senlis Picardie 60300",
    "addr:housenumber":"b.p.",
    "addr:postcode":"80067 60304;60300;60300",
    "addr:street":"Case Postale;Av. Fe\u0301Lix Louat",
    "iso:country":"FR",
    "sg:address":"B.P. Case Postale : 80067, 60304 Senlis^^52, Av. F\u00e9lix Louat, 60300 Senlis",
    "sg:orig_category":"Non-Classified Establishments",
    "sg:phone":"+33 3 44 67 30 00",
    "sg:postcode":"60300",
    "sg:province":"Picardie",
    "wof:name":"Cetim",
    "wof:placetype":"venue"
},
  "geometry": {"coordinates":[2.5857,49.206364],"type":"Point"}
}