{
  "type": "Feature",
  "properties": {
    "iso:country":"FR",
    "sg:address":"Moulin de Bidou 47140 Penne d'Agenais",
    "sg:city":"Auradou",
    "sg:orig_category":"Unclassifiable Establishments",
    "sg:phone":"+33 5 53 41 21 01",
    "sg:postcode":"47140",
    "sg:province":"Aquitaine",
    "wof:name":"Minoterie Desp\u00e9ri\u00e8re Et Fils S.a.r.l.",
    "wof:placetype":"venue"
},
  "geometry": {"coordinates":[0.81514,44.388489],"type":"Point"}
}