{
  "type": "Feature",
  "properties": {
    "addr:full":"83 Rue Central La Clayette Bourgogne 71800",
    "addr:housenumber":"83",
    "addr:postcode":"71800",
    "addr:street":"Rue Central La",
    "iso:country":"FR",
    "sg:address":"83 Rue Central",
    "sg:city":"La Clayette",
    "sg:classifiers":[
        {
            "category":"Banks & Credit Unions",
            "subcategory":"Financial Services",
            "type":"Services"
        }
    ],
    "sg:phone":"+33 3 85 28 03 96",
    "sg:postcode":"71800",
    "sg:province":"Bourgogne",
    "sg:tags":[
        "banking",
        "finance",
        "insurance"
    ],
    "wof:name":"Societe Fiduciaire Nationale D'expertise Comptable Fidexpert (fid)",
    "wof:placetype":"venue"
},
  "geometry": {"coordinates":[4.30661,46.291569],"type":"Point"}
}