{
  "type": "Feature",
  "properties": {
    "addr:full":"Luzunin 56500 Naizin Naizin Bretagne 56500",
    "addr:postcode":"56500;56500",
    "addr:street":"Luzunin;Naizin",
    "iso:country":"FR",
    "sg:address":"Luzunin 56500 Naizin",
    "sg:city":"Naizin",
    "sg:orig_category":"Unclassifiable Establishments",
    "sg:phone":"+33 2 97 27 40 96",
    "sg:postcode":"56500",
    "sg:province":"Bretagne",
    "wof:name":"La Fruiti\u00e8re Du Val Evel",
    "wof:placetype":"venue"
},
  "geometry": {"coordinates":[-2.828419,47.977005],"type":"Point"}
}