{
  "type": "Feature",
  "properties": {
    "addr:full":"Rue des Peupliers Rumegies Nord Pas-de-Calais 59226",
    "addr:postcode":"59226",
    "addr:street":"Rue Des Peupliers Rumegies Nord",
    "iso:country":"FR",
    "sg:address":"Rue des Peupliers",
    "sg:city":"Rumegies",
    "sg:orig_category":"Unclassifiable Establishments",
    "sg:phone":"+33 3 27 26 70 02",
    "sg:postcode":"59226",
    "sg:province":"Nord Pas-de-Calais",
    "wof:name":"A.m.i. S.a.r.l. - Avenir Maintenance Industrie",
    "wof:placetype":"venue"
},
  "geometry": {"coordinates":[3.35032,50.482498],"type":"Point"}
}