{
  "type": "Feature",
  "properties": {
    "addr:full":"15, Rue Pr\u00e9 Voisin, 77120 Mauperthuis Ile de France 77120",
    "addr:housenumber":"15",
    "addr:postcode":"77120;77120",
    "addr:street":"Rue Pre\u0301 Voisin;Ile De France",
    "iso:country":"FR",
    "sg:address":"15, Rue Pr\u00e9 Voisin, 77120 Mauperthuis",
    "sg:orig_category":"Non-Classified Establishments",
    "sg:phone":"+33 1 64 03 35 96",
    "sg:postcode":"77120",
    "sg:province":"Ile de France",
    "wof:name":"Cardot Photogravure S.a.r.l.",
    "wof:placetype":"venue"
},
  "geometry": {"coordinates":[3.041295,48.767586],"type":"Point"}
}