{
  "type": "Feature",
  "properties": {
    "iso:country":"FR",
    "sg:address":"Zac Baudini\u00e8re 44470 Thouar\u00e9 Sur Loire",
    "sg:classifiers":[
        {
            "category":"Professional",
            "type":"Services"
        }
    ],
    "sg:phone":"+33 2 40 18 30 30",
    "sg:province":"Pays de Loire",
    "sg:tags":[
        "transport",
        "road"
    ],
    "wof:name":"Bct-rave",
    "wof:placetype":"venue"
},
  "geometry": {"coordinates":[-1.440899,47.266781],"type":"Point"}
}