{
  "type": "Feature",
  "properties": {
    "iso:country":"FR",
    "sg:address":"3, Chemin Fran\u00e7ois Lefeuvre, 92420 Vaucresson",
    "sg:orig_category":"Unclassifiable Establishments",
    "sg:phone":"+33 1 47 95 16 16",
    "sg:province":"Ile de France",
    "wof:name":"P.t.c. S.a. - Product Trade Conseil",
    "wof:placetype":"venue"
},
  "geometry": {"coordinates":[2.169479,48.845093],"type":"Point"}
}