{
  "type": "Feature",
  "properties": {
    "iso:country":"FR",
    "sg:address":"R De L'Italie Zac De Coudoulet 84100 Orange",
    "sg:classifiers":[
        {
            "category":"Shopping",
            "subcategory":"Computers & Home Electronics",
            "type":"Retail Goods"
        }
    ],
    "sg:phone":"+33 4 90 51 00 51",
    "sg:province":"Centre",
    "sg:tags":[
        "electric",
        "electricity",
        "component",
        "equipment",
        "electrical",
        "electronic"
    ],
    "wof:name":"Comptoir Electrique Fran\u00c7ais",
    "wof:placetype":"venue"
},
  "geometry": {"coordinates":[4.80182,44.153831],"type":"Point"}
}