{
  "type": "Feature",
  "properties": {
    "iso:country":"FR",
    "sg:address":"Rue Pierre et Marie Curie - ZI Oiry",
    "sg:city":"Oiry",
    "sg:orig_category":"Non-Classified Establishments",
    "sg:phone":"+33 3 26 51 07 89",
    "sg:postcode":"51530",
    "sg:province":"Champagne",
    "wof:name":"Adresses Industries S.a.r.l.",
    "wof:placetype":"venue"
},
  "geometry": {"coordinates":[3.93405,49.05574],"type":"Point"}
}