{
  "type": "Feature",
  "properties": {
    "iso:country":"FR",
    "sg:address":"1 rue du Cimeti\u00e8re; Soisy-sous-Montmorency; 95230",
    "sg:classifiers":[
        {
            "category":"Industrial Area",
            "type":"Public Place"
        }
    ],
    "sg:phone":"+33 1 39 34 97 97",
    "sg:province":"Ile de France",
    "sg:tags":[
        "large",
        "private"
    ],
    "wof:name":"Systran S.a.",
    "wof:placetype":"venue"
},
  "geometry": {"coordinates":[2.308636,49.000782],"type":"Point"}
}