{
  "type": "Feature",
  "properties": {
    "iso:country":"FR",
    "sg:address":"70, Rue Francoeur, 91170 Viry Ch\u00e2tillon",
    "sg:orig_category":"Non-Classified Establishments",
    "sg:phone":"+33 1 69 05 44 48",
    "sg:postcode":"91170",
    "sg:province":"Ile de France",
    "wof:name":"C.g.s.t. Save S.a.s. - Compagnie Gazi\u00e8re Service Technique Save",
    "wof:placetype":"venue"
},
  "geometry": {"coordinates":[2.377346,48.67112],"type":"Point"}
}