{
  "type": "Feature",
  "properties": {
    "iso:country":"FR",
    "sg:address":"46 Rue Claude Drivon",
    "sg:city":"Rive De Gier",
    "sg:classifiers":[
        {
            "category":"Banks & Credit Unions",
            "subcategory":"Financial Services",
            "type":"Services"
        }
    ],
    "sg:phone":"+33 4 77 75 06 89",
    "sg:postcode":"42800",
    "sg:province":"Rhone-Alpes",
    "sg:tags":[
        "banking",
        "finance",
        "insurance"
    ],
    "wof:name":"Caisse Regionale De Credit Agricole Mutuel Loire Haute Loir (crcam Loire Haute Loire)",
    "wof:placetype":"venue"
},
  "geometry": {"coordinates":[4.611254,45.526684],"type":"Point"}
}