{
  "type": "Feature",
  "properties": {
    "addr:full":"10, Chemin du Balon, 21700 Gerland Gerland Bourgogne 21700",
    "addr:housenumber":"10",
    "addr:postcode":"21700;21700",
    "addr:street":"Chemin Du Balon;Bourgogne",
    "iso:country":"FR",
    "sg:address":"10, Chemin du Balon, 21700 Gerland",
    "sg:city":"Gerland",
    "sg:orig_category":"Non-Classified Establishments",
    "sg:phone":"+33 3 80 61 10 11",
    "sg:postcode":"21700",
    "sg:province":"Bourgogne",
    "wof:name":"Soci\u00e9t\u00e9 Nouvelle Pierdor S.a.",
    "wof:placetype":"venue"
},
  "geometry": {"coordinates":[5.006702,47.090824],"type":"Point"}
}