{
  "type": "Feature",
  "properties": {
    "addr:full":"223 Rue Jean Jaur\u00e8s 79024 Niort Cedex 09 Champagne",
    "addr:housenumber":"223",
    "addr:postcode":"79024",
    "addr:street":"Rue Jean Jaure\u0300S",
    "iso:country":"FR",
    "sg:address":"223 Rue Jean Jaur\u00e8s 79024 Niort Cedex 09",
    "sg:classifiers":[
        {
            "category":"Wholesale",
            "subcategory":"Machinery & Supplies",
            "type":"Manufacturing & Wholesale Goods"
        }
    ],
    "sg:phone":"+33 5 49 79 34 44",
    "sg:province":"Champagne",
    "sg:tags":[
        "food",
        "processing",
        "-",
        "machine",
        "equipment",
        "engineering",
        "mechanical"
    ],
    "wof:name":"Tecnal Industrie Sa",
    "wof:placetype":"venue"
},
  "geometry": {"coordinates":[-0.459354,46.296497],"type":"Point"}
}