{
  "type": "Feature",
  "properties": {
    "addr:full":"16 Rue Emile Combes 33150 Cenon Cenon Aquitaine 33150",
    "addr:housenumber":"16",
    "addr:postcode":"33150;33150",
    "addr:street":"Rue Emile Combes",
    "iso:country":"FR",
    "sg:address":"16 Rue Emile Combes 33150 Cenon",
    "sg:city":"Cenon",
    "sg:classifiers":[
        {
            "category":"Shopping",
            "type":"Retail Goods"
        }
    ],
    "sg:phone":"+33 5 57 54 04 03",
    "sg:postcode":"33150",
    "sg:province":"Aquitaine",
    "sg:tags":[
        "metallurgy",
        "finished",
        "-",
        "metalworking",
        "metallic"
    ],
    "wof:name":"Mellado Armatures",
    "wof:placetype":"venue"
},
  "geometry": {"coordinates":[-0.535585,44.847198],"type":"Point"}
}