{
  "type": "Feature",
  "properties": {
    "addr:full":"3-5, Rue F\u00e9libien, 44034 Nantes Basse Normandie",
    "addr:housenumber":"3-5",
    "addr:postcode":"44034",
    "addr:street":"Rue Fe\u0301Libien",
    "iso:country":"FR",
    "sg:address":"3-5, Rue F\u00e9libien, 44034 Nantes",
    "sg:orig_category":"Unclassifiable Establishments",
    "sg:phone":"+33 2 40 41 37 37",
    "sg:province":"Basse Normandie",
    "wof:name":"Groupama",
    "wof:placetype":"venue"
},
  "geometry": {"coordinates":[-1.563623,47.220654],"type":"Point"}
}