{
  "type": "Feature",
  "properties": {
    "addr:full":"18, Rte de Thann, 68130 Altkirch Altkirch Alsace 68130",
    "addr:housenumber":"18",
    "addr:postcode":"68130;68130",
    "addr:street":"Rte De Thann",
    "iso:country":"FR",
    "sg:address":"18, Rte de Thann, 68130 Altkirch",
    "sg:city":"Altkirch",
    "sg:orig_category":"Unclassifiable Establishments",
    "sg:phone":"+33 3 89 40 90 75",
    "sg:postcode":"68130",
    "sg:province":"Alsace",
    "wof:name":"Litzler Mat\u00e9riaux S.a.",
    "wof:placetype":"venue"
},
  "geometry": {"coordinates":[7.24009,47.625919],"type":"Point"}
}