{
  "type": "Feature",
  "properties": {
    "addr:full":"992, Av. de provence, 83600 Fr\u00e9jus Provence-Alpes-C\u00f4te d'Azur",
    "addr:postcode":"83600",
    "addr:street":"992 Av. De Provence",
    "iso:country":"FR",
    "sg:address":"992, Av. de provence, 83600 Fr\u00e9jus",
    "sg:orig_category":"Unclassifiable Establishments",
    "sg:phone":"+33 4 94 44 54 54",
    "sg:province":"Provence-Alpes-C\u00f4te d'Azur",
    "wof:name":"S.t.c.m. S.a. - Soci\u00e9t\u00e9 Travaux Construction Mat\u00e9riaux",
    "wof:placetype":"venue"
},
  "geometry": {"coordinates":[6.74907,43.427319],"type":"Point"}
}