{
  "type": "Feature",
  "properties": {
    "addr:full":"Montanay 26210 Lapeyrouse Mornay Rhone-Alpes",
    "addr:postcode":"26210",
    "iso:country":"FR",
    "sg:address":"Montanay 26210 Lapeyrouse Mornay",
    "sg:orig_category":"Non-Classified Establishments",
    "sg:phone":"+33 4 75 31 91 88",
    "sg:province":"Rhone-Alpes",
    "wof:name":"Laquet S.a.s.",
    "wof:placetype":"venue"
},
  "geometry": {"coordinates":[5.016129,45.323505],"type":"Point"}
}