{
  "type": "Feature",
  "properties": {
    "iso:country":"FR",
    "sg:address":"Echangeur A 26 - P\u00f4le d'Activit\u00e9",
    "sg:city":"Guignicourt",
    "sg:orig_category":"Unclassifiable Establishments",
    "sg:phone":"+33 3 23 79 70 37",
    "sg:postcode":"02190",
    "sg:province":"Picardie",
    "wof:name":"Brusselles Atelier S.a.",
    "wof:placetype":"venue"
},
  "geometry": {"coordinates":[3.96701,49.434349],"type":"Point"}
}