{
  "type": "Feature",
  "properties": {
    "addr:full":"Rte de Graves Anse Rhone-Alpes 69480",
    "addr:postcode":"69480",
    "addr:street":"Rte De Graves;Rhone-Alpes",
    "iso:country":"FR",
    "sg:address":"Rte de Graves",
    "sg:city":"Anse",
    "sg:orig_category":"Non-Classified Establishments",
    "sg:phone":"+33 4 74 60 24 46",
    "sg:postcode":"69480",
    "sg:province":"Rhone-Alpes",
    "wof:name":"Saint Romain",
    "wof:placetype":"venue"
},
  "geometry": {"coordinates":[4.71586,45.939346],"type":"Point"}
}