{
  "type": "Feature",
  "properties": {
    "iso:country":"FR",
    "sg:address":"5 rue Goethe 67000 Strasbourg",
    "sg:city":"Strasbourg",
    "sg:classifiers":[
        {
            "category":"Professional",
            "subcategory":"Advertising",
            "type":"Services"
        }
    ],
    "sg:phone":"+33 3 88 45 62 62",
    "sg:postcode":"67000",
    "sg:province":"Alsace",
    "sg:tags":[
        "agency"
    ],
    "wof:name":"Carr\u00e9 Blanc Sarl",
    "wof:placetype":"venue"
},
  "geometry": {"coordinates":[7.76339,48.58551],"type":"Point"}
}