{
  "type": "Feature",
  "properties": {
    "iso:country":"FR",
    "sg:address":"16, Place Dom Gu\u00e9renger, 72300 Solesmes",
    "sg:orig_category":"Non-Classified Establishments",
    "sg:phone":"+33 2 43 95 45 10",
    "sg:province":"Pays de Loire",
    "wof:name":"Grand H\u00f4tel De Solesmes",
    "wof:placetype":"venue"
},
  "geometry": {"coordinates":[-0.303614,47.8512],"type":"Point"}
}