{
  "type": "Feature",
  "properties": {
    "addr:full":"5, Rue des Grillettes, 42160 Bonson Rhone-Alpes 42160",
    "addr:housenumber":"5",
    "addr:postcode":"42160;42160",
    "addr:street":"Rue Des Grillettes",
    "iso:country":"FR",
    "sg:address":"5, Rue des Grillettes, 42160 Bonson",
    "sg:orig_category":"Non-Classified Establishments",
    "sg:phone":"+33 4 77 55 01 39",
    "sg:postcode":"42160",
    "sg:province":"Rhone-Alpes",
    "wof:name":"Beaup\u00e8re S.a.r.l.",
    "wof:placetype":"venue"
},
  "geometry": {"coordinates":[4.214362,45.520302],"type":"Point"}
}