{
  "type": "Feature",
  "properties": {
    "addr:full":"2 rue Magenta; Compi\u00e8gne; 60200 Picardie 60200",
    "addr:housenumber":"2",
    "addr:postcode":"60200;60200",
    "addr:street":"Rue Magenta",
    "iso:country":"FR",
    "sg:address":"2 rue Magenta; Compi\u00e8gne; 60200",
    "sg:classifiers":[
        {
            "category":"Banks & Credit Unions",
            "subcategory":"Bank",
            "type":"Services"
        }
    ],
    "sg:phone":"+33 3344202105",
    "sg:postcode":"60200",
    "sg:province":"Picardie",
    "wof:name":"Soci\u00e9t\u00e9 G\u00e9n\u00e9rale",
    "wof:placetype":"venue"
},
  "geometry": {"coordinates":[2.826371,49.416973],"type":"Point"}
}