{
  "type": "Feature",
  "properties": {
    "addr:full":"B.P. 54, 67150 Erstein^^Rue de l'Expansion, 67150 Erstein Erstein Alsace 67150",
    "addr:postcode":"67150;67150;67150",
    "addr:street":"B.P. 54;L'Expansion",
    "iso:country":"FR",
    "sg:address":"B.P. 54, 67150 Erstein^^Rue de l'Expansion, 67150 Erstein",
    "sg:city":"Erstein",
    "sg:orig_category":"Non-Classified Establishments",
    "sg:phone":"+33 3 88 59 88 00",
    "sg:postcode":"67150",
    "sg:province":"Alsace",
    "wof:name":"Or Est S.a.",
    "wof:placetype":"venue"
},
  "geometry": {"coordinates":[7.633605,48.412617],"type":"Point"}
}