{
  "type": "Feature",
  "properties": {
    "iso:country":"FR",
    "sg:address":"B.P. 71, 44150 Ancenis c\u00e9dex^^55, Av. de la Lib\u00e9ration, 44150 Ancenis",
    "sg:orig_category":"Non-Classified Establishments",
    "sg:phone":"+33 2 40 83 00 07",
    "sg:postcode":"44150",
    "sg:province":"Pays de Loire",
    "wof:name":"Angebault Fr\u00e8res S.a.",
    "wof:placetype":"venue"
},
  "geometry": {"coordinates":[-1.202109,47.366123],"type":"Point"}
}