{
  "type": "Feature",
  "properties": {
    "addr:full":"Kerfeunteun 29630 PLOUGASNOU Plougasnou Bretagne 29630",
    "addr:postcode":"29630;29630",
    "addr:street":"Plougasnou",
    "iso:country":"FR",
    "sg:address":"Kerfeunteun 29630 PLOUGASNOU",
    "sg:city":"Plougasnou",
    "sg:classifiers":[
        {
            "category":"Manufacturing",
            "subcategory":"Food",
            "type":"Manufacturing & Wholesale Goods"
        }
    ],
    "sg:phone":"+33 2 98 67 35 40",
    "sg:postcode":"29630",
    "sg:province":"Bretagne",
    "sg:tags":[
        "frozen"
    ],
    "wof:name":"Primel Gastronomie Sas",
    "wof:placetype":"venue"
},
  "geometry": {"coordinates":[-3.796109,48.650761],"type":"Point"}
}