{
  "type": "Feature",
  "properties": {
    "addr:full":"Rte d'Erondelle Pont R\u00e9my Picardie 80580",
    "addr:postcode":"80580",
    "addr:street":"Rte D'Erondelle Pont Re\u0301My Picardie",
    "iso:country":"FR",
    "sg:address":"Rte d'Erondelle",
    "sg:city":"Pont R\u00e9my",
    "sg:orig_category":"Unclassifiable Establishments",
    "sg:phone":"+33 3 22 27 31 51",
    "sg:postcode":"80580",
    "sg:province":"Picardie",
    "wof:name":"S.t.r.a.p. S.a.",
    "wof:placetype":"venue"
},
  "geometry": {"coordinates":[1.9005,50.048809],"type":"Point"}
}