{
  "type": "Feature",
  "properties": {
    "iso:country":"FR",
    "sg:address":"4, Bd Voltaire - Le Clos Bailly B\u00e2t. E, 91290 Arpajon",
    "sg:orig_category":"Non-Classified Establishments",
    "sg:phone":"+33 1 69 26 04 06",
    "sg:postcode":"91290",
    "sg:province":"Ile de France",
    "wof:name":"Dormelles S.a.r.l.",
    "wof:placetype":"venue"
},
  "geometry": {"coordinates":[2.249095,48.590462],"type":"Point"}
}