{
  "type": "Feature",
  "properties": {
    "addr:full":"ZI Aur\u00e9ats Portes l\u00e8s Valence Rhone-Alpes 26800",
    "addr:postcode":"26800",
    "iso:country":"FR",
    "sg:address":"ZI Aur\u00e9ats",
    "sg:city":"Portes l\u00e8s Valence",
    "sg:orig_category":"Unclassifiable Establishments",
    "sg:phone":"+33 4 75 41 83 00",
    "sg:postcode":"26800",
    "sg:province":"Rhone-Alpes",
    "wof:name":"Valtrans S.a.r.l.",
    "wof:placetype":"venue"
},
  "geometry": {"coordinates":[4.87721,44.876316],"type":"Point"}
}