{
  "type": "Feature",
  "properties": {
    "addr:full":"31, Rue Ambroise Par\u00e9, 69740 Genas Rhone-Alpes",
    "addr:housenumber":"31",
    "addr:postcode":"69740",
    "addr:street":"Rue Ambroise Pare\u0301",
    "iso:country":"FR",
    "sg:address":"31, Rue Ambroise Par\u00e9, 69740 Genas",
    "sg:orig_category":"Unclassifiable Establishments",
    "sg:phone":"+33 4 78 90 66 36",
    "sg:province":"Rhone-Alpes",
    "wof:name":"Couty S.a.",
    "wof:placetype":"venue"
},
  "geometry": {"coordinates":[4.975966,45.714848],"type":"Point"}
}