{
  "type": "Feature",
  "properties": {
    "iso:country":"FR",
    "sg:address":"B.P. 33869, 44338 Nantes C\u00e9dex 3^^8, Impasse des Jades - Technoparc de l'Aubini\u00e8re, 44000 Nantes",
    "sg:orig_category":"Non-Classified Establishments",
    "sg:phone":"+33 2 40 52 58 58",
    "sg:province":"Pays de Loire",
    "wof:name":"Garon Bonvalot S.a.",
    "wof:placetype":"venue"
},
  "geometry": {"coordinates":[-1.567257,47.229397],"type":"Point"}
}