{
  "type": "Feature",
  "properties": {
    "addr:full":"7, Rue Marcel Dassault - ZI les Fruchardi\u00e8res, 85340 Olonne sur Mer Pays de Loire",
    "addr:housenumber":"7",
    "addr:postcode":"85340",
    "addr:street":"Rue Marcel Dassault Zi Les Fruchardie\u0300Res",
    "iso:country":"FR",
    "sg:address":"7, Rue Marcel Dassault - ZI les Fruchardi\u00e8res, 85340 Olonne sur Mer",
    "sg:orig_category":"Unclassifiable Establishments",
    "sg:phone":"+33 2 51 32 99 69",
    "sg:province":"Pays de Loire",
    "wof:name":"Fantronic Composants S.a.",
    "wof:placetype":"venue"
},
  "geometry": {"coordinates":[-1.773149,46.536518],"type":"Point"}
}