{
  "type": "Feature",
  "properties": {
    "addr:full":"Rte de Nozay Marcoussis Ile de France 91460",
    "addr:postcode":"91460",
    "addr:street":"Rte De Nozay;Ile De France",
    "iso:country":"FR",
    "sg:address":"Rte de Nozay",
    "sg:city":"Marcoussis",
    "sg:orig_category":"Unclassifiable Establishments",
    "sg:phone":"+33 1 64 54 48 00",
    "sg:postcode":"91460",
    "sg:province":"Ile de France",
    "wof:name":"Cilas Instruments S.a.",
    "wof:placetype":"venue"
},
  "geometry": {"coordinates":[2.233609,48.64484],"type":"Point"}
}