{
  "type": "Feature",
  "properties": {
    "addr:full":"1 Rue Du Parc 92593 Levallois Perret Cedex Languedoc-Roussillon",
    "addr:housenumber":"1",
    "addr:postcode":"92593",
    "addr:street":"Rue Du Parc",
    "iso:country":"FR",
    "sg:address":"1 Rue Du Parc 92593 Levallois Perret Cedex",
    "sg:classifiers":[
        {
            "category":"Professional",
            "subcategory":"Business Services",
            "type":"Services"
        }
    ],
    "sg:phone":"+33 1 49 68 56 40",
    "sg:province":"Languedoc-Roussillon",
    "sg:tags":[
        "travel",
        "fair"
    ],
    "wof:name":"Societe 3 E",
    "wof:placetype":"venue"
},
  "geometry": {"coordinates":[2.28525,48.895981],"type":"Point"}
}