{
  "type": "Feature",
  "properties": {
    "iso:country":"FR",
    "sg:address":"Ctre Com Des Ulis 2 91940 Les Ulis",
    "sg:classifiers":[
        {
            "category":"Professional",
            "subcategory":"Printing & Photocopies",
            "type":"Services"
        }
    ],
    "sg:phone":"+33 1 69 07 35 97",
    "sg:province":"Ile de France",
    "sg:tags":[
        "publishing"
    ],
    "wof:name":"France Loisirs (fl)",
    "wof:placetype":"venue"
},
  "geometry": {"coordinates":[2.169475,48.68161],"type":"Point"}
}