{
  "type": "Feature",
  "properties": {
    "iso:country":"FR",
    "sg:address":"218, Chemin des Cheneviers, 73190 Challes les Eaux",
    "sg:orig_category":"Non-Classified Establishments",
    "sg:phone":"+33 4 79 71 18 08",
    "sg:postcode":"73190",
    "sg:province":"Rhone-Alpes",
    "wof:name":"Banfi France S.a.r.l.",
    "wof:placetype":"venue"
},
  "geometry": {"coordinates":[5.975642,45.543713],"type":"Point"}
}