{
  "type": "Feature",
  "properties": {
    "iso:country":"FR",
    "sg:address":"10, Rue de Verdun, 80000 Amiens",
    "sg:orig_category":"Unclassifiable Establishments",
    "sg:phone":"+33 3 22 71 10 90",
    "sg:province":"Picardie",
    "wof:name":"Supae Picardie S.n.c.",
    "wof:placetype":"venue"
},
  "geometry": {"coordinates":[2.310671,49.894054],"type":"Point"}
}