{
  "type": "Feature",
  "properties": {
    "addr:full":"8 Rue Montespan \u00c9vry Ile de France 91000",
    "addr:housenumber":"8",
    "addr:postcode":"91000",
    "addr:street":"Rue Montespan;Ile De France",
    "iso:country":"FR",
    "sg:address":"8 Rue Montespan",
    "sg:city":"\u00c9vry",
    "sg:classifiers":[
        {
            "category":"Banks & Credit Unions",
            "subcategory":"Financial Services",
            "type":"Services"
        }
    ],
    "sg:phone":"+33 1 69 91 15 77",
    "sg:postcode":"91000",
    "sg:province":"Ile de France",
    "sg:tags":[
        "banking",
        "finance",
        "insurance"
    ],
    "wof:name":"Biofords Consultants Sarl",
    "wof:placetype":"venue"
},
  "geometry": {"coordinates":[2.436802,48.633686],"type":"Point"}
}