{
  "type": "Feature",
  "properties": {
    "addr:full":"33 Cours Guynemer 60200 Compi\u00e8gne Picardie 60200",
    "addr:housenumber":"33",
    "addr:postcode":"60200;60200",
    "addr:street":"Cours Guynemer",
    "iso:country":"FR",
    "sg:address":"33 Cours Guynemer 60200 Compi\u00e8gne",
    "sg:classifiers":[
        {
            "category":"Travel",
            "subcategory":"Hotels & Motels",
            "type":"Entertainment"
        }
    ],
    "sg:phone":"+33 3 44 92 26 26",
    "sg:postcode":"60200",
    "sg:province":"Picardie",
    "sg:tags":[
        "hotels",
        "business",
        "restaurant"
    ],
    "wof:name":"Hotel Les Beaux Arts",
    "wof:placetype":"venue"
},
  "geometry": {"coordinates":[2.824572,49.419956],"type":"Point"}
}