{
  "type": "Feature",
  "properties": {
    "addr:full":"ZI de Pommenauque 50500 Carentan Carentan Basse Normandie 50500",
    "addr:postcode":"50500;50500",
    "addr:street":"Zi De Pommenauque",
    "iso:country":"FR",
    "sg:address":"ZI de Pommenauque 50500 Carentan",
    "sg:city":"Carentan",
    "sg:classifiers":[
        {
            "category":"Sports & Exercise",
            "subcategory":"Playing Field",
            "type":"Entertainment"
        }
    ],
    "sg:phone":"+33 2 33 42 09 52",
    "sg:postcode":"50500",
    "sg:province":"Basse Normandie",
    "sg:tags":[
        "decoration",
        "panel"
    ],
    "wof:name":"Laudescher S.a.",
    "wof:placetype":"venue"
},
  "geometry": {"coordinates":[-1.247078,49.30291],"type":"Point"}
}