{
  "type": "Feature",
  "properties": {
    "addr:full":"22250 S\u00e9vignac S\u00e9vignac Bretagne 22250",
    "addr:housenumber":"22250",
    "addr:postcode":"22250",
    "addr:street":"Se\u0301Vignac Se\u0301Vignac Bretagne",
    "iso:country":"FR",
    "sg:address":"22250 S\u00e9vignac",
    "sg:city":"S\u00e9vignac",
    "sg:orig_category":"Non-Classified Establishments",
    "sg:phone":"+33 2 96 84 92 15",
    "sg:postcode":"22250",
    "sg:province":"Bretagne",
    "wof:name":"Carri\u00e8res De Guitternel S.a.",
    "wof:placetype":"venue"
},
  "geometry": {"coordinates":[-2.339019,48.332706],"type":"Point"}
}