{
  "type": "Feature",
  "properties": {
    "addr:full":"65, Rue du Baron le Ray - Gare Bercy Rap\u00e9e Quai N\u00b016, 75012 Paris Ile de France",
    "addr:housenumber":"65",
    "addr:postcode":"75012",
    "addr:street":"Rue Du Baron Le;Gare;Quai N\u00b016",
    "iso:country":"FR",
    "sg:address":"65, Rue du Baron le Ray - Gare Bercy Rap\u00e9e Quai N\u00b016, 75012 Paris",
    "sg:orig_category":"Unclassifiable Establishments",
    "sg:phone":"+33 1 53 17 18 60",
    "sg:province":"Ile de France",
    "wof:name":"Besson Et Compagnie S.a.",
    "wof:placetype":"venue"
},
  "geometry": {"coordinates":[2.389295,48.841045],"type":"Point"}
}