{
  "type": "Feature",
  "properties": {
    "addr:full":"22 Rue Claude Bernard 35008 Rennes Cedex Brittany",
    "addr:housenumber":"22",
    "addr:postcode":"35008",
    "addr:street":"Rue Claude Bernard",
    "iso:country":"FR",
    "sg:address":"22 Rue Claude Bernard 35008 Rennes Cedex",
    "sg:classifiers":[
        {
            "category":"Marine",
            "type":"Transportation"
        }
    ],
    "sg:phone":"+33 800 87 78 77",
    "sg:province":"Brittany",
    "sg:tags":[
        "transport",
        "sea"
    ],
    "wof:name":"Ups France Snc",
    "wof:placetype":"venue"
},
  "geometry": {"coordinates":[-1.694197,48.103451],"type":"Point"}
}