{
  "type": "Feature",
  "properties": {
    "iso:country":"FR",
    "sg:address":"ZA la Cornella",
    "sg:city":"Hauteville Lompnes",
    "sg:orig_category":"Non-Classified Establishments",
    "sg:phone":"+33 4 74 35 31 45",
    "sg:postcode":"01110",
    "sg:province":"Rhone-Alpes",
    "wof:name":"Pesenti P\u00e8re Et Fils S.a.r.l.",
    "wof:placetype":"venue"
},
  "geometry": {"coordinates":[5.600358,45.97802],"type":"Point"}
}