{
  "type": "Feature",
  "properties": {
    "iso:country":"FR",
    "sg:address":"94/102, Rue des Vignoles, 75020 Paris",
    "sg:orig_category":"Unclassifiable Establishments",
    "sg:phone":"+33 1 43 70 70 52",
    "sg:province":"Ile de France",
    "wof:name":"L'audacieuse Sa",
    "wof:placetype":"venue"
},
  "geometry": {"coordinates":[2.402734,48.856167],"type":"Point"}
}