{
  "type": "Feature",
  "properties": {
    "addr:full":"4 Rue Du Faubourg Saint Honore 75008 Paris Ile de France 75008",
    "addr:housenumber":"4",
    "addr:postcode":"75008;france 75008",
    "addr:street":"Rue Du Faubourg Saint Honore",
    "iso:country":"FR",
    "sg:address":"4 Rue Du Faubourg Saint Honore 75008 Paris",
    "sg:classifiers":[
        {
            "category":"Building & Trades",
            "subcategory":"Electrical",
            "type":"Services"
        }
    ],
    "sg:phone":"+33 1 42 66 66 11",
    "sg:postcode":"75008",
    "sg:province":"Ile de France",
    "sg:tags":[
        "electronic",
        "lighting",
        "equipment"
    ],
    "wof:name":"Charle Luminaire",
    "wof:placetype":"venue"
},
  "geometry": {"coordinates":[2.322967,48.868607],"type":"Point"}
}