{
  "type": "Feature",
  "properties": {
    "addr:full":"ZI de Mestre Marty Estillac Aquitaine 47310",
    "addr:postcode":"47310",
    "addr:street":"Zi De Mestre Marty",
    "iso:country":"FR",
    "sg:address":"ZI de Mestre Marty",
    "sg:city":"Estillac",
    "sg:orig_category":"Non-Classified Establishments",
    "sg:phone":"+33 5 53 87 62 62",
    "sg:postcode":"47310",
    "sg:province":"Aquitaine",
    "wof:name":"Saviel Estillac S.n.c.",
    "wof:placetype":"venue"
},
  "geometry": {"coordinates":[0.563847,44.157024],"type":"Point"}
}