{
  "type": "Feature",
  "properties": {
    "iso:country":"FR",
    "sg:address":"1 Rue Des Platanes 94600 Choisy Le Roi",
    "sg:classifiers":[
        {
            "category":"Professional",
            "subcategory":"Engineering",
            "type":"Services"
        }
    ],
    "sg:phone":"+33 1 45 12 14 00",
    "sg:postcode":"94600",
    "sg:province":"Ile de France",
    "sg:tags":[
        "machine",
        "-",
        "environment",
        "equipment",
        "machinery",
        "mechanical"
    ],
    "wof:name":"Sa De Gestion Des Eaux De Paris (sagep)",
    "wof:placetype":"venue"
},
  "geometry": {"coordinates":[2.419833,48.751259],"type":"Point"}
}