{
  "type": "Feature",
  "properties": {
    "iso:country":"FR",
    "sg:address":"1 Pl des Comtes du Maine; Le Mans; 72000",
    "sg:classifiers":[
        {
            "category":"Banks & Credit Unions",
            "subcategory":"Bank",
            "type":"Services"
        }
    ],
    "sg:phone":"+33 3343770809",
    "sg:postcode":"72000",
    "sg:province":"Pays de Loire",
    "wof:name":"Cr\u00e9dit Mutuel",
    "wof:placetype":"venue"
},
  "geometry": {"coordinates":[0.200138,48.005112],"type":"Point"}
}