{
  "type": "Feature",
  "properties": {
    "addr:full":"2\u00e8me Avenue - 8\u00e8me Rue - Port de Lille Lille Nord Pas-de-Calais 59000",
    "addr:postcode":"59000",
    "addr:street":"2E\u0300Me Avenue 8E\u0300Me Rue Port De Lille Lille Nord",
    "iso:country":"FR",
    "sg:address":"2\u00e8me Avenue - 8\u00e8me Rue - Port de Lille",
    "sg:city":"Lille",
    "sg:orig_category":"Non-Classified Establishments",
    "sg:phone":"+33 3 20 09 22 77",
    "sg:postcode":"59000",
    "sg:province":"Nord Pas-de-Calais",
    "wof:name":"Marandin S.a.",
    "wof:placetype":"venue"
},
  "geometry": {"coordinates":[3.02995,50.627304],"type":"Point"}
}