{
  "type": "Feature",
  "properties": {
    "iso:country":"FR",
    "sg:address":"Rte des Pontots",
    "sg:city":"Anglet",
    "sg:orig_category":"Non-Classified Establishments",
    "sg:phone":"+33 5 59 58 32 59",
    "sg:postcode":"64600",
    "sg:province":"Aquitaine",
    "wof:name":"A.d. Blanchardet Gadso S.a.",
    "wof:placetype":"venue"
},
  "geometry": {"coordinates":[-1.498519,43.493923],"type":"Point"}
}