{
  "type": "Feature",
  "properties": {
    "addr:full":"2, Rue Jean Perrin, 69740 Genas Rhone-Alpes",
    "addr:housenumber":"2",
    "addr:postcode":"69740",
    "addr:street":"Rue Jean Perrin",
    "iso:country":"FR",
    "sg:address":"2, Rue Jean Perrin, 69740 Genas",
    "sg:orig_category":"Unclassifiable Establishments",
    "sg:phone":"+33 4 72 79 09 70",
    "sg:province":"Rhone-Alpes",
    "wof:name":"Embalfour S.a.",
    "wof:placetype":"venue"
},
  "geometry": {"coordinates":[4.994821,45.712139],"type":"Point"}
}