{
  "type": "Feature",
  "properties": {
    "addr:full":"Le Boulay 41170 Cormenon Cormenon Centre 41170",
    "addr:housenumber":"cormenon",
    "addr:postcode":"41170;41170",
    "iso:country":"FR",
    "sg:address":"Le Boulay 41170 Cormenon",
    "sg:city":"Cormenon",
    "sg:classifiers":[
        {
            "category":"Building & Trades",
            "subcategory":"Construction",
            "type":"Services"
        }
    ],
    "sg:phone":"+33 2 54 73 55 30",
    "sg:postcode":"41170",
    "sg:province":"Centre",
    "sg:tags":[
        "work",
        "public"
    ],
    "wof:name":"Trigano Jardin",
    "wof:placetype":"venue"
},
  "geometry": {"coordinates":[0.9126,47.963749],"type":"Point"}
}