{
  "type": "Feature",
  "properties": {
    "addr:full":"20 Rue Nesle 80400 Hombleux Picardie 80400",
    "addr:housenumber":"20",
    "addr:postcode":"80400;80400",
    "addr:street":"Rue Nesle;Picardie",
    "iso:country":"FR",
    "sg:address":"20 Rue Nesle 80400 Hombleux",
    "sg:classifiers":[
        {
            "category":"Manufacturing",
            "subcategory":"Metals",
            "type":"Manufacturing & Wholesale Goods"
        }
    ],
    "sg:phone":"+33 3 23 81 10 44",
    "sg:postcode":"80400",
    "sg:province":"Picardie",
    "sg:tags":[
        "metallurgy",
        "metalworking",
        "processing"
    ],
    "wof:name":"Hanssart (constructions Metalliques) Sa",
    "wof:placetype":"venue"
},
  "geometry": {"coordinates":[2.981755,49.743439],"type":"Point"}
}