{
  "type": "Feature",
  "properties": {
    "iso:country":"FR",
    "sg:address":"4, All\u00e9e Paul Halary - ZI Nord-Est, 51100 Reims",
    "sg:orig_category":"Unclassifiable Establishments",
    "sg:phone":"+33 3 26 07 53 49",
    "sg:province":"Champagne",
    "wof:name":"Contr\u00f4le Et Automatisme S.a.",
    "wof:placetype":"venue"
},
  "geometry": {"coordinates":[4.028445,49.26284],"type":"Point"}
}