{
  "type": "Feature",
  "properties": {
    "iso:country":"FR",
    "sg:address":"51 Fbg Fermorens BP 348 38509 Voiron Cedex",
    "sg:classifiers":[
        {
            "category":"Manufacturing",
            "subcategory":"Metals",
            "type":"Manufacturing & Wholesale Goods"
        }
    ],
    "sg:phone":"+33 4 76 05 20 51",
    "sg:province":"Midi Pyr\u00e9n\u00e9es",
    "sg:tags":[
        "metallurgy",
        "metalworking"
    ],
    "wof:name":"Unv Industrie",
    "wof:placetype":"venue"
},
  "geometry": {"coordinates":[5.591101,45.367214],"type":"Point"}
}