{
  "type": "Feature",
  "properties": {
    "iso:country":"FR",
    "sg:address":"B.P. 3, 25720 Beure^^1, Rue des Romains, 25720 Beure",
    "sg:orig_category":"Non-Classified Establishments",
    "sg:phone":"+33 3 81 41 28 41",
    "sg:province":"Franche Comt\u00e9",
    "wof:name":"Groupe Simonin S.a.",
    "wof:placetype":"venue"
},
  "geometry": {"coordinates":[5.96273,47.201542],"type":"Point"}
}