{
  "type": "Feature",
  "properties": {
    "iso:country":"FR",
    "sg:address":"93 Avenue De La Marne",
    "sg:city":"Asnieres Sur Seine",
    "sg:classifiers":[
        {
            "category":"Banks & Credit Unions",
            "subcategory":"Financial Services",
            "type":"Services"
        }
    ],
    "sg:phone":"+33 1 41 11 41 11",
    "sg:postcode":"92600",
    "sg:province":"Ile de France",
    "sg:tags":[
        "banking",
        "finance",
        "insurance"
    ],
    "wof:name":"Credit Commercial De France (ccf) Agence Asnieres",
    "wof:placetype":"venue"
},
  "geometry": {"coordinates":[2.286608,48.909836],"type":"Point"}
}