{
  "type": "Feature",
  "properties": {
    "addr:full":"Zi Albasud 82000 Montauban Midi Pyr\u00e9n\u00e9es 82000",
    "addr:postcode":"82000;82000",
    "iso:country":"FR",
    "sg:address":"Zi Albasud 82000 Montauban",
    "sg:classifiers":[
        {
            "category":"Travel",
            "subcategory":"Hotels & Motels",
            "type":"Entertainment"
        }
    ],
    "sg:phone":"+33 5 63 02 16 47",
    "sg:postcode":"82000",
    "sg:province":"Midi Pyr\u00e9n\u00e9es",
    "sg:tags":[
        "hotels",
        "business",
        "restaurant"
    ],
    "wof:name":"Casino Cafeteria",
    "wof:placetype":"venue"
},
  "geometry": {"coordinates":[1.352205,44.016762],"type":"Point"}
}