{
  "type": "Feature",
  "properties": {
    "addr:full":"2 Rue Adrien Legay Zac De Geoffroy 63300 Thiers Thiers Auvergne 63300",
    "addr:housenumber":"2",
    "addr:postcode":"63300;63300",
    "addr:street":"Rue Adrien Legay Zac De Geoffroy",
    "iso:country":"FR",
    "sg:address":"2 Rue Adrien Legay Zac De Geoffroy 63300 Thiers",
    "sg:city":"Thiers",
    "sg:classifiers":[
        {
            "category":"Manufacturing",
            "subcategory":"Metals",
            "type":"Manufacturing & Wholesale Goods"
        }
    ],
    "sg:phone":"+33 4 73 80 63 23",
    "sg:postcode":"63300",
    "sg:province":"Auvergne",
    "sg:tags":[
        "metallurgy",
        "metalworking",
        "processing"
    ],
    "wof:name":"Gorce Sa",
    "wof:placetype":"venue"
},
  "geometry": {"coordinates":[3.563396,45.82058],"type":"Point"}
}