{
  "type": "Feature",
  "properties": {
    "addr:full":"109 boulevard Beaumarchais 75003 Paris Ile de France 75003",
    "addr:housenumber":"109",
    "addr:postcode":"75003;75003",
    "addr:street":"Boulevard Beaumarchais",
    "iso:country":"FR",
    "sg:address":"109 boulevard Beaumarchais 75003 Paris",
    "sg:classifiers":[
        {
            "category":"Home & Garden",
            "subcategory":"Carpets & Floor Coverings",
            "type":"Retail Goods"
        }
    ],
    "sg:phone":"+33 1 40 29 95 81",
    "sg:postcode":"75003",
    "sg:province":"Ile de France",
    "sg:tags":[
        "curtain",
        "finishing"
    ],
    "wof:name":"Decoration Contemporaine Bisson Bruneel Sarl",
    "wof:placetype":"venue"
},
  "geometry": {"coordinates":[2.367188,48.860504],"type":"Point"}
}