{
  "type": "Feature",
  "properties": {
    "iso:country":"FR",
    "sg:address":"37 Rue Des Pres 27950 St Marcel",
    "sg:classifiers":[
        {
            "category":"Manufacturing",
            "subcategory":"Rubber & Plastics",
            "type":"Manufacturing & Wholesale Goods"
        }
    ],
    "sg:phone":"+33 2 32 71 25 25",
    "sg:province":"Haute Normandie",
    "wof:name":"Condi Ouest",
    "wof:placetype":"venue"
},
  "geometry": {"coordinates":[1.44734,49.1022],"type":"Point"}
}