{
  "type": "Feature",
  "properties": {
    "addr:full":"28 chemin du Solarium 33170 Gradignan Gradignan Aquitaine 33170",
    "addr:housenumber":"28",
    "addr:postcode":"33170;33170",
    "addr:street":"Chemin Du Solarium",
    "iso:country":"FR",
    "sg:address":"28 chemin du Solarium 33170 Gradignan",
    "sg:city":"Gradignan",
    "sg:classifiers":[
        {
            "category":"Farming",
            "subcategory":"Crops",
            "type":"Manufacturing & Wholesale Goods"
        }
    ],
    "sg:phone":"+33 5 56 75 59 44",
    "sg:postcode":"33170",
    "sg:province":"Aquitaine",
    "sg:tags":[
        "refrigerator",
        "wine"
    ],
    "wof:name":"Bellot S.a.",
    "wof:placetype":"venue"
},
  "geometry": {"coordinates":[-0.631079,44.780109],"type":"Point"}
}