{
  "type": "Feature",
  "properties": {
    "addr:full":"B.P. 37, 44260 Malville^^ZI de la Croix Rouge, 44260 Malville Pays de Loire 44260",
    "addr:postcode":"44260;44260;44260",
    "addr:street":"B.P. 37;La Croix Rouge",
    "iso:country":"FR",
    "sg:address":"B.P. 37, 44260 Malville^^ZI de la Croix Rouge, 44260 Malville",
    "sg:orig_category":"Non-Classified Establishments",
    "sg:phone":"+33 2 40 57 05 02",
    "sg:postcode":"44260",
    "sg:province":"Pays de Loire",
    "wof:name":"Bretagne Composite S.a.",
    "wof:placetype":"venue"
},
  "geometry": {"coordinates":[-1.965349,47.30954],"type":"Point"}
}