{
  "type": "Feature",
  "properties": {
    "addr:full":"1 Rue Jacques Monod Europarc Du Ch\u00eane 69673 Bron Cedex Nord Pas-de-Calais",
    "addr:housenumber":"1",
    "addr:postcode":"69673;cedex nord",
    "addr:street":"Rue Jacques Monod Europarc Du Che\u0302Ne",
    "iso:country":"FR",
    "sg:address":"1 Rue Jacques Monod Europarc Du Ch\u00eane 69673 Bron Cedex",
    "sg:classifiers":[
        {
            "category":"Farming",
            "subcategory":"Livestock Farm",
            "type":"Manufacturing & Wholesale Goods"
        }
    ],
    "sg:phone":"+33 4 72 14 40 40",
    "sg:province":"Nord Pas-de-Calais",
    "sg:tags":[
        "grain",
        "agriculture",
        "cereal"
    ],
    "wof:name":"Monsanto France Sa",
    "wof:placetype":"venue"
},
  "geometry": {"coordinates":[4.90861,45.73357],"type":"Point"}
}