{
  "type": "Feature",
  "properties": {
    "addr:full":"74 Route Nationale 45380 La Chapelle St Mesmin La Chapelle-Saint-Mesmin Centre 45380",
    "addr:housenumber":"74;chapelle-saint-mesmin",
    "addr:postcode":"45380;45380",
    "addr:street":"Route Nationale;La Chapelle St",
    "iso:country":"FR",
    "sg:address":"74 Route Nationale 45380 La Chapelle St Mesmin",
    "sg:city":"La Chapelle-Saint-Mesmin",
    "sg:classifiers":[
        {
            "category":"Professional",
            "subcategory":"Business Services",
            "type":"Services"
        }
    ],
    "sg:phone":"+33 2 38 22 33 10",
    "sg:postcode":"45380",
    "sg:province":"Centre",
    "sg:tags":[
        "training",
        "advice"
    ],
    "wof:name":"Cfai Centre",
    "wof:placetype":"venue"
},
  "geometry": {"coordinates":[1.833757,47.888485],"type":"Point"}
}