{
  "type": "Feature",
  "properties": {
    "iso:country":"FR",
    "sg:address":"B.P. 229, 13131 Berre l'Etang C\u00e9dex^^Quartier Mauran, 13130 Berre l'Etang",
    "sg:orig_category":"Non-Classified Establishments",
    "sg:phone":"+33 4 42 10 21 70",
    "sg:province":"Provence-Alpes-C\u00f4te d'Azur",
    "wof:name":"Four\u00e9 Lagadec S.a.r.l.",
    "wof:placetype":"venue"
},
  "geometry": {"coordinates":[5.167831,43.484978],"type":"Point"}
}