{
  "type": "Feature",
  "properties": {
    "iso:country":"FR",
    "sg:address":"22, Bd Oscar Planat, 16100 Cognac",
    "sg:orig_category":"Unclassifiable Establishments",
    "sg:phone":"+33 5 45 35 04 74",
    "sg:province":"Poitou-Charentes",
    "wof:name":"Etablissement Martin Dominique S.a.r.l.",
    "wof:placetype":"venue"
},
  "geometry": {"coordinates":[-0.338136,45.689068],"type":"Point"}
}