{
  "type": "Feature",
  "properties": {
    "iso:country":"FR",
    "sg:address":"Route Nationale 30 59282 Douchy Les Mines",
    "sg:classifiers":[
        {
            "category":"Building & Trades",
            "subcategory":"Construction",
            "type":"Services"
        }
    ],
    "sg:phone":"+33 3 27 21 95 40",
    "sg:postcode":"59282",
    "sg:province":"Nord Pas-de-Calais",
    "sg:tags":[
        "work",
        "public"
    ],
    "wof:name":"Beugnet Escaut (societe En Nom Collectif)",
    "wof:placetype":"venue"
},
  "geometry": {"coordinates":[3.390598,50.300709],"type":"Point"}
}