{
  "type": "Feature",
  "properties": {
    "iso:country":"FR",
    "sg:address":"B.P. 66, 38340 Voreppe^^305, Rue Emile Romanet, 38340 Voreppe",
    "sg:orig_category":"Non-Classified Establishments",
    "sg:phone":"+33 4 76 50 26 91",
    "sg:province":"Rhone-Alpes",
    "wof:name":"Sog\u00e9a Rh\u00f4ne-alpes S.n.c.",
    "wof:placetype":"venue"
},
  "geometry": {"coordinates":[5.63766,45.298351],"type":"Point"}
}