{
  "type": "Feature",
  "properties": {
    "addr:full":"3, Rue de Mars, 08000 Charleville M\u00e9zi\u00e8res Charleville-M\u00e9zi\u00e8res Champagne 08000",
    "addr:housenumber":"3",
    "addr:postcode":"08000;08000",
    "addr:street":"Rue De Mars",
    "iso:country":"FR",
    "sg:address":"3, Rue de Mars, 08000 Charleville M\u00e9zi\u00e8res",
    "sg:city":"Charleville-M\u00e9zi\u00e8res",
    "sg:orig_category":"Unclassifiable Establishments",
    "sg:phone":"+33 3 24 57 62 74",
    "sg:postcode":"08000",
    "sg:province":"Champagne",
    "wof:name":"Art D\u00e9cor S.a.",
    "wof:placetype":"venue"
},
  "geometry": {"coordinates":[4.718027,49.757664],"type":"Point"}
}