{
  "type": "Feature",
  "properties": {
    "addr:full":"Hameau Fresnoy Le Petit 02100 Gricourt Picardie 02100",
    "addr:postcode":"02100;02100",
    "addr:street":"Hameau Fresnoy Le Petit",
    "iso:country":"FR",
    "sg:address":"Hameau Fresnoy Le Petit 02100 Gricourt",
    "sg:classifiers":[
        {
            "category":"Farming",
            "subcategory":"Livestock Farm",
            "type":"Manufacturing & Wholesale Goods"
        }
    ],
    "sg:phone":"+33 3 23 62 70 56",
    "sg:postcode":"02100",
    "sg:province":"Picardie",
    "sg:tags":[
        "grain",
        "agriculture",
        "cereal"
    ],
    "wof:name":"Carlier Ets Sa",
    "wof:placetype":"venue"
},
  "geometry": {"coordinates":[3.291286,49.850952],"type":"Point"}
}