{
  "type": "Feature",
  "properties": {
    "addr:full":"156, Rue Fin de la Guerre, 59200 Tourcoing Nord Pas-de-Calais",
    "addr:housenumber":"156",
    "addr:postcode":"59200",
    "addr:street":"Rue Fin De La Guerre",
    "iso:country":"FR",
    "sg:address":"156, Rue Fin de la Guerre, 59200 Tourcoing",
    "sg:orig_category":"Unclassifiable Establishments",
    "sg:phone":"+33 3 20 03 60 71",
    "sg:province":"Nord Pas-de-Calais",
    "wof:name":"Sebi S.a.",
    "wof:placetype":"venue"
},
  "geometry": {"coordinates":[3.144414,50.729359],"type":"Point"}
}