{
  "type": "Feature",
  "properties": {
    "iso:country":"FR",
    "sg:address":"Autoroute A 10 Aire De Meillac 33240 Cubzac Les Ponts",
    "sg:city":"Aubie-et-Espessas",
    "sg:classifiers":[
        {
            "category":"Manufacturing",
            "subcategory":"Chemicals & Compounds",
            "type":"Manufacturing & Wholesale Goods"
        }
    ],
    "sg:phone":"+33 5 57 43 58 10",
    "sg:postcode":"33240",
    "sg:province":"Aquitaine",
    "sg:tags":[
        "pharmaceutical",
        "energy",
        "chemistry",
        "-",
        "by-product"
    ],
    "wof:name":"Gesmin -station Bp Cubzac",
    "wof:placetype":"venue"
},
  "geometry": {"coordinates":[-0.333284,44.95092],"type":"Point"}
}