{
  "type": "Feature",
  "properties": {
    "addr:full":"29, Rue de l'Industrie, 67400 Illkirch Graffenstaden Geispolsheim Alsace 67400",
    "addr:housenumber":"29",
    "addr:postcode":"67400;67400",
    "addr:street":"Rue De L'Industrie",
    "iso:country":"FR",
    "sg:address":"29, Rue de l'Industrie, 67400 Illkirch Graffenstaden",
    "sg:city":"Geispolsheim",
    "sg:orig_category":"Non-Classified Establishments",
    "sg:phone":"+33 3 88 66 72 73",
    "sg:postcode":"67400",
    "sg:province":"Alsace",
    "wof:name":"Kirn Fr\u00e8res Charcuterie S.a.",
    "wof:placetype":"venue"
},
  "geometry": {"coordinates":[7.731668,48.530483],"type":"Point"}
}