{
  "type": "Feature",
  "properties": {
    "addr:full":"Rue des Terres Noires Saint Philbert du Peuple Pays de Loire 49160",
    "addr:postcode":"49160",
    "addr:street":"Rue Des Terres Noires Saint Philbert Du Peuple Pays",
    "iso:country":"FR",
    "sg:address":"Rue des Terres Noires",
    "sg:city":"Saint Philbert du Peuple",
    "sg:orig_category":"Unclassifiable Establishments",
    "sg:phone":"+33 2 41 52 15 83",
    "sg:postcode":"49160",
    "sg:province":"Pays de Loire",
    "wof:name":"Polydec Industries S.a.",
    "wof:placetype":"venue"
},
  "geometry": {"coordinates":[-0.148994,47.315624],"type":"Point"}
}