{
  "type": "Feature",
  "properties": {
    "iso:country":"FR",
    "sg:address":"Lieu Dit Les Essarts Z I 85670 St Christophe Du Ligneron",
    "sg:classifiers":[
        {
            "category":"Government",
            "subcategory":"Department Of Motor Vehicles",
            "type":"Public Place"
        }
    ],
    "sg:phone":"+33 2 51 93 23 50",
    "sg:postcode":"85670",
    "sg:province":"Pays de Loire",
    "sg:tags":[
        "equipment",
        "industrial",
        "transport",
        "motor-cars"
    ],
    "wof:name":"Societe De Mecanique Et Decolletage Vendeenne (somedev)",
    "wof:placetype":"venue"
},
  "geometry": {"coordinates":[-1.62195,46.782482],"type":"Point"}
}