{
  "type": "Feature",
  "properties": {
    "addr:full":"B.P. 5002, 01105 Oyonnax C\u00e9dex^^Rue de la Tuilerie, 01100 Oyonnax Rhone-Alpes",
    "addr:postcode":"01105;01100",
    "addr:street":"B.P. 5002;La Tuilerie",
    "iso:country":"FR",
    "sg:address":"B.P. 5002, 01105 Oyonnax C\u00e9dex^^Rue de la Tuilerie, 01100 Oyonnax",
    "sg:orig_category":"Non-Classified Establishments",
    "sg:phone":"+33 4 74 73 77 65",
    "sg:province":"Rhone-Alpes",
    "wof:name":"Optim\u00e9tal S.a.r.l.",
    "wof:placetype":"venue"
},
  "geometry": {"coordinates":[5.64405,46.24968],"type":"Point"}
}