{
  "type": "Feature",
  "properties": {
    "addr:full":"71 Chem Du Bardot 42000 St Etienne Rhone-Alpes 42000",
    "addr:housenumber":"71",
    "addr:postcode":"42000;42000",
    "addr:street":"Chem Du Bardot",
    "iso:country":"FR",
    "sg:address":"71 Chem Du Bardot 42000 St Etienne",
    "sg:classifiers":[
        {
            "category":"Professional",
            "type":"Services"
        }
    ],
    "sg:phone":"+33 4 77 32 80 76",
    "sg:postcode":"42000",
    "sg:province":"Rhone-Alpes",
    "sg:tags":[
        "transport",
        "road"
    ],
    "wof:name":"Transports Driot Sa",
    "wof:placetype":"venue"
},
  "geometry": {"coordinates":[4.40795,45.447948],"type":"Point"}
}