{
  "type": "Feature",
  "properties": {
    "iso:country":"FR",
    "sg:address":"75, Rue L\u00e9on Gambetta, 59041 Lille C\u00e9dex",
    "sg:orig_category":"Non-Classified Establishments",
    "sg:phone":"+33 3 20 63 04 05",
    "sg:province":"Nord-Pas-de-Calais",
    "wof:name":"N.f.x. - Nord France Experts",
    "wof:placetype":"venue"
},
  "geometry": {"coordinates":[3.058167,50.630768],"type":"Point"}
}