{
  "type": "Feature",
  "properties": {
    "addr:full":"10, Rue de la Grange, 53220 Pontmain Pays de Loire 53220",
    "addr:housenumber":"10",
    "addr:postcode":"53220;53220",
    "addr:street":"Rue De La Grange",
    "iso:country":"FR",
    "sg:address":"10, Rue de la Grange, 53220 Pontmain",
    "sg:orig_category":"Non-Classified Establishments",
    "sg:phone":"+33 2 43 30 18 82",
    "sg:postcode":"53220",
    "sg:province":"Pays de Loire",
    "wof:name":"C.a.t.",
    "wof:placetype":"venue"
},
  "geometry": {"coordinates":[-1.056521,48.438713],"type":"Point"}
}