{
  "type": "Feature",
  "properties": {
    "addr:full":"58, Rue Paul Petit, 33920 Saint Savin Civrac-de-Blaye Aquitaine 33920",
    "addr:housenumber":"58",
    "addr:postcode":"33920;33920",
    "addr:street":"Rue Paul Petit",
    "iso:country":"FR",
    "sg:address":"58, Rue Paul Petit, 33920 Saint Savin",
    "sg:city":"Civrac-de-Blaye",
    "sg:orig_category":"Non-Classified Establishments",
    "sg:phone":"+33 5 57 52 96 99",
    "sg:postcode":"33920",
    "sg:province":"Aquitaine",
    "wof:name":"F. Et Y. Petit Bois Et S\u00e9chage S.a.r.l.",
    "wof:placetype":"venue"
},
  "geometry": {"coordinates":[-0.440031,45.145702],"type":"Point"}
}