{
  "type": "Feature",
  "properties": {
    "iso:country":"FR",
    "sg:address":"34-7, Rue de Luyot, 59113 Seclin",
    "sg:orig_category":"Non-Classified Establishments",
    "sg:phone":"+33 3 28 55 90 40",
    "sg:province":"Nord Pas-de-Calais",
    "wof:name":"Label Ing\u00e9nierie S.a.",
    "wof:placetype":"venue"
},
  "geometry": {"coordinates":[3.038045,50.558296],"type":"Point"}
}