{
  "type": "Feature",
  "properties": {
    "iso:country":"FR",
    "sg:address":"45 Rue De Savoie Plaine Manissieux 69800 St Priest",
    "sg:classifiers":[
        {
            "category":"Professional",
            "subcategory":"Advertising",
            "type":"Services"
        }
    ],
    "sg:phone":"+33 4 72 47 63 63",
    "sg:postcode":"69800",
    "sg:province":"Rhone-Alpes",
    "sg:tags":[
        "information",
        "medium",
        "communication"
    ],
    "wof:name":"Eco Arc Eco-arc",
    "wof:placetype":"venue"
},
  "geometry": {"coordinates":[4.935695,45.694202],"type":"Point"}
}