{
  "type": "Feature",
  "properties": {
    "iso:country":"FR",
    "sg:address":"3, Rue Georges Meli\u00e8s, 69680 Chassieu",
    "sg:orig_category":"Unclassifiable Establishments",
    "sg:phone":"+33 4 78 90 23 23",
    "sg:province":"Rhone-Alpes",
    "wof:name":"M\u00e9ca Bonier Garaffa S.a.r.l.",
    "wof:placetype":"venue"
},
  "geometry": {"coordinates":[4.959759,45.73502],"type":"Point"}
}