{
  "type": "Feature",
  "properties": {
    "iso:country":"FR",
    "sg:address":"B.P. 20, 95320 Saint Leu la For\u00eat^^3/6, Rue Louis Armand - ZI Saint Leu, 95130 Le Plessis Bouchard",
    "sg:orig_category":"Non-Classified Establishments",
    "sg:phone":"+33 1 34 44 15 15",
    "sg:province":"Ile de France",
    "wof:name":"Plastimed S.a.",
    "wof:placetype":"venue"
},
  "geometry": {"coordinates":[2.2487,49.00016],"type":"Point"}
}