{
  "type": "Feature",
  "properties": {
    "addr:full":"14, Rue Balzac, 69150 D\u00e9cines Charpieu Rhone-Alpes",
    "addr:housenumber":"14",
    "addr:postcode":"69150",
    "addr:street":"Rue Balzac",
    "iso:country":"FR",
    "sg:address":"14, Rue Balzac, 69150 D\u00e9cines Charpieu",
    "sg:orig_category":"Non-Classified Establishments",
    "sg:phone":"+33 4 78 49 25 11",
    "sg:province":"Rhone-Alpes",
    "wof:name":"Ravy Andr\u00e9 Et Fils",
    "wof:placetype":"venue"
},
  "geometry": {"coordinates":[4.982175,45.771595],"type":"Point"}
}