{
  "type": "Feature",
  "properties": {
    "iso:country":"FR",
    "sg:address":"B.P. 128",
    "sg:city":"Chen\u00f4ve C\u00e9dex",
    "sg:orig_category":"Non-Classified Establishments",
    "sg:phone":"+33 3 80 59 60 00",
    "sg:postcode":"21303",
    "sg:province":"Bourgogne",
    "wof:name":"A.c.e. S.a. - Automatismes Du Centre Est",
    "wof:placetype":"venue"
},
  "geometry": {"coordinates":[5.004665,47.294296],"type":"Point"}
}