{
  "type": "Feature",
  "properties": {
    "addr:full":"46 Rue Chanzy 75011 Paris Ile de France 75011",
    "addr:housenumber":"46",
    "addr:postcode":"75011;75011",
    "addr:street":"Rue Chanzy",
    "iso:country":"FR",
    "sg:address":"46 Rue Chanzy 75011 Paris",
    "sg:classifiers":[
        {
            "category":"Home & Garden",
            "subcategory":"Furniture",
            "type":"Retail Goods"
        }
    ],
    "sg:phone":"+33 1 43 71 50 09",
    "sg:postcode":"75011",
    "sg:province":"Ile de France",
    "sg:tags":[
        "household",
        "wood"
    ],
    "wof:name":"Societe Paris Baches",
    "wof:placetype":"venue"
},
  "geometry": {"coordinates":[2.387171,48.853008],"type":"Point"}
}