{
  "type": "Feature",
  "properties": {
    "addr:full":"Zone D'Activit\u00e9 Rosais 35550 Sixt Sur Aff Bruc-sur-Aff Bretagne 35550",
    "addr:postcode":"35550;35550",
    "addr:street":"Zone;Bruc-Sur-Aff",
    "iso:country":"FR",
    "sg:address":"Zone D'Activit\u00e9 Rosais 35550 Sixt Sur Aff",
    "sg:city":"Bruc-sur-Aff",
    "sg:classifiers":[
        {
            "category":"Manufacturing",
            "subcategory":"Metals",
            "type":"Manufacturing & Wholesale Goods"
        }
    ],
    "sg:phone":"+33 2 99 70 00 91",
    "sg:postcode":"35550",
    "sg:province":"Bretagne",
    "sg:tags":[
        "metallurgy",
        "metalworking",
        "processing"
    ],
    "wof:name":"Chromatlantique Sa",
    "wof:placetype":"venue"
},
  "geometry": {"coordinates":[-2.062183,47.779045],"type":"Point"}
}