{
  "type": "Feature",
  "properties": {
    "addr:full":"20, Rue du Commerce, 31120 Portet sur Garonne Midi Pyr\u00e9n\u00e9es 31120",
    "addr:housenumber":"20",
    "addr:postcode":"31120;31120",
    "addr:street":"Rue Du Commerce",
    "iso:country":"FR",
    "sg:address":"20, Rue du Commerce, 31120 Portet sur Garonne",
    "sg:orig_category":"Non-Classified Establishments",
    "sg:phone":"+33 5 61 72 26 96",
    "sg:postcode":"31120",
    "sg:province":"Midi Pyr\u00e9n\u00e9es",
    "wof:name":"Amiantech S.a.r.l.",
    "wof:placetype":"venue"
},
  "geometry": {"coordinates":[1.406819,43.524021],"type":"Point"}
}