{
  "type": "Feature",
  "properties": {
    "addr:full":"B.P. 16, 59640 Dunkerque^^1, Av de la Garonne - ZI de Petite Synthe, 59640 Dunkerque Nord-Pas-de-Calais",
    "addr:postcode":"59640;59640",
    "addr:street":"B.P. 16;Av De La Garonne Zi De Petite Synthe",
    "iso:country":"FR",
    "sg:address":"B.P. 16, 59640 Dunkerque^^1, Av de la Garonne - ZI de Petite Synthe, 59640 Dunkerque",
    "sg:orig_category":"Non-Classified Establishments",
    "sg:phone":"+33 3 28 26 74 40",
    "sg:province":"Nord-Pas-de-Calais",
    "wof:name":"Izard Et Compagnie S.a.r.l.",
    "wof:placetype":"venue"
},
  "geometry": {"coordinates":[2.35294,51.022812],"type":"Point"}
}