{
  "type": "Feature",
  "properties": {
    "iso:country":"FR",
    "sg:address":"34, Rue de Troyes, 10100 Romilly sur Seine",
    "sg:orig_category":"Non-Classified Establishments",
    "sg:phone":"+33 3 25 24 72 14",
    "sg:province":"Champagne",
    "wof:name":"F.v.",
    "wof:placetype":"venue"
},
  "geometry": {"coordinates":[3.733683,48.51453],"type":"Point"}
}