{
  "type": "Feature",
  "properties": {
    "iso:country":"FR",
    "sg:address":"B.P. 77, 54714 Ludres C\u00e9dex^^211, Rue Lavoisier, 54710 Ludres",
    "sg:orig_category":"Non-Classified Establishments",
    "sg:phone":"+33 3 83 26 30 20",
    "sg:province":"Lorraine",
    "wof:name":"P.c.l. Emballage S.a. - Papeteries Et Cartonneries De Lorraine",
    "wof:placetype":"venue"
},
  "geometry": {"coordinates":[6.161059,48.621563],"type":"Point"}
}