{
  "type": "Feature",
  "properties": {
    "addr:full":"B.P. 412, 84071 Avignon C\u00e9dex^^1, Rue Saint Jean le Vieux, 84000 Avignon Haute Normandie",
    "addr:housenumber":"b.p. 412",
    "addr:postcode":"84071;84000",
    "addr:street":"Rue Saint Jean Le Vieux;Haute Normandie",
    "iso:country":"FR",
    "sg:address":"B.P. 412, 84071 Avignon C\u00e9dex^^1, Rue Saint Jean le Vieux, 84000 Avignon",
    "sg:orig_category":"Non-Classified Establishments",
    "sg:phone":"+33 4 90 27 26 50",
    "sg:province":"Haute Normandie",
    "wof:name":"B.f.c.c. - Banque Fran\u00e7aise De Cr\u00e9dit Coop\u00e9ratif",
    "wof:placetype":"venue"
},
  "geometry": {"coordinates":[4.806015,43.948753],"type":"Point"}
}