{
  "type": "Feature",
  "properties": {
    "iso:country":"FR",
    "sg:address":"5 rue Coq Chante",
    "sg:city":"Puteaux ",
    "sg:classifiers":[
        {
            "category":"Professional",
            "subcategory":"Computer Services",
            "type":"Services"
        }
    ],
    "sg:postcode":"92800",
    "sg:website":"http://www.athic.fr",
    "wof:name":"Athic Solutions",
    "wof:placetype":"venue"
},
  "geometry": {"coordinates":[2.238256,48.883011],"type":"Point"}
}