{
  "type": "Feature",
  "properties": {
    "iso:country":"FR",
    "sg:address":"14, Rue de la R\u00e9publique, 54140 Jarville la Malgrange",
    "sg:orig_category":"Unclassifiable Establishments",
    "sg:phone":"+33 3 83 55 57 50",
    "sg:province":"Lorraine",
    "wof:name":"Pasquereau S.a.",
    "wof:placetype":"venue"
},
  "geometry": {"coordinates":[6.201227,48.674622],"type":"Point"}
}