{
  "type": "Feature",
  "properties": {
    "addr:full":"11, Rue des Arquebusiers, 75003 Paris Ile de France",
    "addr:housenumber":"11",
    "addr:postcode":"75003",
    "addr:street":"Rue Des Arquebusiers",
    "iso:country":"FR",
    "sg:address":"11, Rue des Arquebusiers, 75003 Paris",
    "sg:orig_category":"Non-Classified Establishments",
    "sg:phone":"+33 1 40 29 04 04",
    "sg:province":"Ile de France",
    "wof:name":"Profil S.a.r.l.",
    "wof:placetype":"venue"
},
  "geometry": {"coordinates":[2.366466,48.859604],"type":"Point"}
}