{
  "type": "Feature",
  "properties": {
    "iso:country":"FR",
    "sg:address":"7 Impasse Ste Claire Deville 78200 Mantes La Jolie",
    "sg:classifiers":[
        {
            "category":"Wholesale",
            "subcategory":"Machinery & Supplies",
            "type":"Manufacturing & Wholesale Goods"
        }
    ],
    "sg:phone":"+33 1 30 94 35 62",
    "sg:postcode":"78200",
    "sg:province":"Ile de France",
    "sg:tags":[
        "handling",
        "material",
        "-",
        "machine",
        "equipment",
        "engineering",
        "mechanical"
    ],
    "wof:name":"Mgi Ouest Caoutchouc",
    "wof:placetype":"venue"
},
  "geometry": {"coordinates":[1.6902,48.992661],"type":"Point"}
}