{
  "type": "Feature",
  "properties": {
    "addr:full":"1, Rue du Vallon - ZI n\u00b01, 67490 Dettwiller Dettwiller Alsace 67490",
    "addr:housenumber":"1;n\u00b01",
    "addr:postcode":"67490;67490",
    "addr:street":"Rue Du Vallon Zi",
    "iso:country":"FR",
    "sg:address":"1, Rue du Vallon - ZI n\u00b01, 67490 Dettwiller",
    "sg:city":"Dettwiller",
    "sg:orig_category":"Unclassifiable Establishments",
    "sg:phone":"+33 3 88 71 99 00",
    "sg:postcode":"67490",
    "sg:province":"Alsace",
    "wof:name":"Spenl\u00e9",
    "wof:placetype":"venue"
},
  "geometry": {"coordinates":[7.46685,48.754059],"type":"Point"}
}