{
  "type": "Feature",
  "properties": {
    "addr:full":"B.P. 90513, 35505 Vitr\u00e9 C\u00e9dex^^106, Bd de Laval, 35500 Vitr\u00e9 Vitr\u00e9 Bretagne 35500",
    "addr:postcode":"35505;ce\u0301dex^^106;35500;35500",
    "addr:street":"Bd De Laval;Bretagne",
    "iso:country":"FR",
    "sg:address":"B.P. 90513, 35505 Vitr\u00e9 C\u00e9dex^^106, Bd de Laval, 35500 Vitr\u00e9",
    "sg:city":"Vitr\u00e9",
    "sg:orig_category":"Non-Classified Establishments",
    "sg:phone":"+33 2 99 75 33 75",
    "sg:postcode":"35500",
    "sg:province":"Bretagne",
    "wof:name":"A.f.t.e.c. Formation S.a.",
    "wof:placetype":"venue"
},
  "geometry": {"coordinates":[-1.30752,48.080273],"type":"Point"}
}