{
  "type": "Feature",
  "properties": {
    "iso:country":"FR",
    "sg:address":"7, Bd de Strasbourg - Parc Gustave Eiffel, 77607 Bussy Saint Georges C\u00e9dex",
    "sg:orig_category":"Non-Classified Establishments",
    "sg:phone":"+33 1 64 76 49 77",
    "sg:province":"\u00cele-de-France",
    "wof:name":"Minolta S.a.",
    "wof:placetype":"venue"
},
  "geometry": {"coordinates":[2.73528,48.830963],"type":"Point"}
}