{
  "type": "Feature",
  "properties": {
    "addr:full":"Ch\u00e2teau Fonpl\u00e9gade 33330 Saint Emilion Saint-\u00c9tienne-de-Lisse Aquitaine 33330",
    "addr:postcode":"33330;33330",
    "addr:street":"Fonple\u0301Gade",
    "iso:country":"FR",
    "sg:address":"Ch\u00e2teau Fonpl\u00e9gade 33330 Saint Emilion",
    "sg:city":"Saint-\u00c9tienne-de-Lisse",
    "sg:orig_category":"Non-Classified Establishments",
    "sg:phone":"+33 5 57 74 43 11",
    "sg:postcode":"33330",
    "sg:province":"Aquitaine",
    "wof:name":"Domaines Viticoles Armand Moueix S.c.e.a.",
    "wof:placetype":"venue"
},
  "geometry": {"coordinates":[-0.165489,44.883171],"type":"Point"}
}