{
  "type": "Feature",
  "properties": {
    "iso:country":"FR",
    "sg:address":"B.P. 34",
    "sg:city":"Autechaux^^25110 Autechaux",
    "sg:orig_category":"Non-Classified Establishments",
    "sg:phone":"+33 3 81 84 00 79",
    "sg:postcode":"25110",
    "sg:province":"Franche Comt\u00e9",
    "wof:name":"Laffond S.a.",
    "wof:placetype":"venue"
},
  "geometry": {"coordinates":[6.35857,47.35133],"type":"Point"}
}