{
  "type": "Feature",
  "properties": {
    "addr:full":"46 Rue Lauriston 75116 Paris Rhone-Alpes",
    "addr:housenumber":"46",
    "addr:postcode":"75116",
    "addr:street":"Rue Lauriston",
    "iso:country":"FR",
    "sg:address":"46 Rue Lauriston 75116 Paris",
    "sg:classifiers":[
        {
            "category":"Travel",
            "subcategory":"Hotels & Motels",
            "type":"Entertainment"
        }
    ],
    "sg:phone":"+33 1 47 27 15 15",
    "sg:province":"Rhone-Alpes",
    "sg:tags":[
        "hotels",
        "business",
        "restaurant"
    ],
    "wof:name":"Tradotel Sarl Centrale De Reservations Hotelieres",
    "wof:placetype":"venue"
},
  "geometry": {"coordinates":[2.290757,48.870277],"type":"Point"}
}