{
  "type": "Feature",
  "properties": {
    "addr:full":"Rte de Tarbes - La Croix de Cassagne Saint Gaudens Midi Pyr\u00e9n\u00e9es 31800",
    "addr:postcode":"31800",
    "addr:street":"Rte De Tarbes La Croix De Cassagne Saint Gaudens Midi Pyre\u0301Ne\u0301Es",
    "iso:country":"FR",
    "sg:address":"Rte de Tarbes - La Croix de Cassagne",
    "sg:city":"Saint Gaudens",
    "sg:orig_category":"Unclassifiable Establishments",
    "sg:phone":"+33 5 61 89 20 86",
    "sg:postcode":"31800",
    "sg:province":"Midi Pyr\u00e9n\u00e9es",
    "wof:name":"A.s.c. S.a.r.l.",
    "wof:placetype":"venue"
},
  "geometry": {"coordinates":[0.723251,43.050159],"type":"Point"}
}