{
  "type": "Feature",
  "properties": {
    "addr:full":"34 B Rue De La Division Leclerc 54120 Baccarat Lorraine 54120",
    "addr:housenumber":"34 b",
    "addr:postcode":"54120;54120",
    "addr:street":"Rue De La Division Leclerc",
    "iso:country":"FR",
    "sg:address":"34 B Rue De La Division Leclerc 54120 Baccarat",
    "sg:classifiers":[
        {
            "category":"Shopping",
            "type":"Retail Goods"
        }
    ],
    "sg:phone":"+33 3 83 75 10 38",
    "sg:postcode":"54120",
    "sg:province":"Lorraine",
    "sg:tags":[
        "metallurgy",
        "finished",
        "-",
        "metalworking",
        "metallic"
    ],
    "wof:name":"Manulor",
    "wof:placetype":"venue"
},
  "geometry": {"coordinates":[6.74038,48.453381],"type":"Point"}
}