{
  "type": "Feature",
  "properties": {
    "addr:full":"32 quai des Am\u00e9ricains 59140 Dunkerque Nord Pas-de-Calais 59140",
    "addr:housenumber":"32",
    "addr:postcode":"59140;59140",
    "addr:street":"Quai Des Ame\u0301Ricains",
    "iso:country":"FR",
    "sg:address":"32 quai des Am\u00e9ricains 59140 Dunkerque",
    "sg:classifiers":[
        {
            "category":"Manufacturing",
            "subcategory":"Tools & Machinery",
            "type":"Manufacturing & Wholesale Goods"
        }
    ],
    "sg:phone":"+33 3 28 66 30 80",
    "sg:postcode":"59140",
    "sg:province":"Nord Pas-de-Calais",
    "sg:tags":[
        "device",
        "handling"
    ],
    "wof:name":"Etablissements Le Lann Sa",
    "wof:placetype":"venue"
},
  "geometry": {"coordinates":[2.378471,51.041763],"type":"Point"}
}