{
  "type": "Feature",
  "properties": {
    "iso:country":"FR",
    "sg:address":"11, Rue de la Menove, 32400 Riscle",
    "sg:orig_category":"Unclassifiable Establishments",
    "sg:phone":"+33 5 62 69 71 72",
    "sg:province":"Midi Pyr\u00e9n\u00e9es",
    "wof:name":"S.c.a. Vivadour - Soci\u00e9t\u00e9 Coop\u00e9rative Agricole Vivadour",
    "wof:placetype":"venue"
},
  "geometry": {"coordinates":[-0.13978,43.598343],"type":"Point"}
}