{
  "type": "Feature",
  "properties": {
    "addr:full":"rue de l'Aviation 21121 Darois Darois Bourgogne 21121",
    "addr:postcode":"21121;21121",
    "addr:street":"Rue De L'Aviation",
    "iso:country":"FR",
    "sg:address":"rue de l'Aviation 21121 Darois",
    "sg:city":"Darois",
    "sg:classifiers":[
        {
            "category":"Professional",
            "subcategory":"Advertising",
            "type":"Services"
        }
    ],
    "sg:phone":"+33 3 80 35 63 10",
    "sg:postcode":"21121",
    "sg:province":"Bourgogne",
    "sg:tags":[
        "flight",
        "balloon",
        "aerial"
    ],
    "wof:name":"C.j.b. Sa",
    "wof:placetype":"venue"
},
  "geometry": {"coordinates":[4.942376,47.38929],"type":"Point"}
}