{
  "type": "Feature",
  "properties": {
    "addr:full":"9, Rue Moulin des Bruy\u00e8res, 92400 Courbevoie Ile de France",
    "addr:housenumber":"9",
    "addr:postcode":"92400",
    "addr:street":"Rue Moulin Des Bruye\u0300Res",
    "iso:country":"FR",
    "sg:address":"9, Rue Moulin des Bruy\u00e8res, 92400 Courbevoie",
    "sg:orig_category":"Unclassifiable Establishments",
    "sg:phone":"+33 1 49 04 92 00",
    "sg:province":"Ile de France",
    "wof:name":"Houvenaghel Hennequin S.a.",
    "wof:placetype":"venue"
},
  "geometry": {"coordinates":[2.261178,48.903332],"type":"Point"}
}