{
  "type": "Feature",
  "properties": {
    "iso:country":"FR",
    "sg:address":"B.P. 32, 59392 Wattrelos C\u00e9dex^^108, Rue du Mont \u00e0 Leux, 59150 Wattrelos",
    "sg:orig_category":"Non-Classified Establishments",
    "sg:phone":"+33 3 20 01 07 60",
    "sg:province":"Nord Pas-de-Calais",
    "wof:name":"Sion Paul Et Fils S.a.",
    "wof:placetype":"venue"
},
  "geometry": {"coordinates":[3.215276,50.701122],"type":"Point"}
}