{
  "type": "Feature",
  "properties": {
    "addr:full":"19, Rue de la Ladrie, 59000 Lille Nord Pas-de-Calais",
    "addr:housenumber":"19",
    "addr:postcode":"59000",
    "addr:street":"Rue De La Ladrie",
    "iso:country":"FR",
    "sg:address":"19, Rue de la Ladrie, 59000 Lille",
    "sg:orig_category":"Unclassifiable Establishments",
    "sg:phone":"+33 3 28 33 32 30",
    "sg:province":"Nord Pas-de-Calais",
    "wof:name":"Howden Sirocco S.a.",
    "wof:placetype":"venue"
},
  "geometry": {"coordinates":[3.0319,50.635479],"type":"Point"}
}