{
  "type": "Feature",
  "properties": {
    "iso:country":"FR",
    "sg:address":"19, Rue de la Ladrie, 59000 Lille",
    "sg:orig_category":"Unclassifiable Establishments",
    "sg:phone":"+33 3 28 33 32 30",
    "sg:province":"Nord Pas-de-Calais",
    "wof:name":"Howden Sirocco S.a.",
    "wof:placetype":"venue"
},
  "geometry": {"coordinates":[3.0319,50.635479],"type":"Point"}
}