{
  "type": "Feature",
  "properties": {
    "iso:country":"FR",
    "sg:address":"2, Rue Joseph Monier, 92859 Rueil Malmaison C\u00e9dex",
    "sg:orig_category":"Non-Classified Establishments",
    "sg:phone":"+33 1 55 94 11 00",
    "sg:province":"\u00cele-de-France",
    "wof:name":"V\u00e9ninov S.a.",
    "wof:placetype":"venue"
},
  "geometry": {"coordinates":[2.172337,48.890812],"type":"Point"}
}