{
  "type": "Feature",
  "properties": {
    "addr:full":"11, Rue Victor Bach, 42000 Saint Etienne Rhone-Alpes 42000",
    "addr:housenumber":"11",
    "addr:postcode":"42000;42000",
    "addr:street":"Rue Victor Bach",
    "iso:country":"FR",
    "sg:address":"11, Rue Victor Bach, 42000 Saint Etienne",
    "sg:orig_category":"Non-Classified Establishments",
    "sg:phone":"+33 4 77 74 72 60",
    "sg:postcode":"42000",
    "sg:province":"Rhone-Alpes",
    "wof:name":"Chaudronnerie Fine De La Loire S.a.",
    "wof:placetype":"venue"
},
  "geometry": {"coordinates":[4.379992,45.442329],"type":"Point"}
}