{
  "type": "Feature",
  "properties": {
    "iso:country":"FR",
    "sg:address":"Route De Firminy 43330 St Ferreol D Auroure",
    "sg:city":"Pont-Salomon",
    "sg:classifiers":[
        {
            "category":"Shopping",
            "subcategory":"Crafts & Fabrics",
            "type":"Retail Goods"
        }
    ],
    "sg:phone":"+33 4 77 35 85 74",
    "sg:postcode":"43330",
    "sg:province":"Auvergne",
    "sg:tags":[
        "textile",
        "clothing"
    ],
    "wof:name":"Adf",
    "wof:placetype":"venue"
},
  "geometry": {"coordinates":[-83.41918200000001,40.812832],"type":"Point"}
}