{
  "type": "Feature",
  "properties": {
    "addr:full":"Zone Industrielle Angecourt Champagne 08450",
    "addr:postcode":"08450",
    "addr:street":"Zone Industrielle;Champagne",
    "iso:country":"FR",
    "sg:address":"Zone Industrielle",
    "sg:city":"Angecourt",
    "sg:orig_category":"Unclassifiable Establishments",
    "sg:phone":"+33 3 24 26 77 61",
    "sg:postcode":"08450",
    "sg:province":"Champagne",
    "wof:name":"T.s.c. S.a.r.l. - Textile Synth\u00e9tique Card\u00e9",
    "wof:placetype":"venue"
},
  "geometry": {"coordinates":[4.9793,49.633705],"type":"Point"}
}