{
  "type": "Feature",
  "properties": {
    "addr:full":"15 rue Benjamin Raspail 92240 Malakoff Ile de France",
    "addr:housenumber":"15",
    "addr:postcode":"92240;ile",
    "addr:street":"Rue Benjamin Raspail",
    "iso:country":"FR",
    "sg:address":"15 rue Benjamin Raspail 92240 Malakoff",
    "sg:classifiers":[
        {
            "category":"Communications",
            "subcategory":"Film & Video Production",
            "type":"Services"
        }
    ],
    "sg:phone":"+33 1 46 12 19 19",
    "sg:province":"Ile de France",
    "wof:name":"C.m.c. Sa",
    "wof:placetype":"venue"
},
  "geometry": {"coordinates":[2.304218,48.818306],"type":"Point"}
}