{
  "type": "Feature",
  "properties": {
    "addr:full":"19, Rue d'Eschau, 67112 Illkirch Graffenstaden C\u00e9dex Breuschwickersheim Alsace 67112",
    "addr:housenumber":"19",
    "addr:postcode":"67112;67112",
    "addr:street":"Rue D'Eschau",
    "iso:country":"FR",
    "sg:address":"19, Rue d'Eschau, 67112 Illkirch Graffenstaden C\u00e9dex",
    "sg:city":"Breuschwickersheim",
    "sg:orig_category":"Non-Classified Establishments",
    "sg:phone":"+33 3 88 40 56 38",
    "sg:postcode":"67112",
    "sg:province":"Alsace",
    "wof:name":"Sog\u00e9a Est B.t.p. S.n.c.",
    "wof:placetype":"venue"
},
  "geometry": {"coordinates":[7.71556,48.487961],"type":"Point"}
}