{
  "type": "Feature",
  "properties": {
    "addr:full":"53, Rte de Dortan, 01100 Oyonnax Rhone-Alpes 01100",
    "addr:housenumber":"53",
    "addr:postcode":"01100;01100",
    "addr:street":"Rte De Dortan",
    "iso:country":"FR",
    "sg:address":"53, Rte de Dortan, 01100 Oyonnax",
    "sg:orig_category":"Unclassifiable Establishments",
    "sg:phone":"+33 4 74 77 34 96",
    "sg:postcode":"01100",
    "sg:province":"Rhone-Alpes",
    "wof:name":"Nano D\u00e9cor S.a.r.l.",
    "wof:placetype":"venue"
},
  "geometry": {"coordinates":[5.65959,46.269531],"type":"Point"}
}