{
  "type": "Feature",
  "properties": {
    "addr:full":"15, ZI Bompertuis, 13120 Gardanne",
    "addr:housenumber":"15",
    "addr:postcode":"13120",
    "addr:street":"Zi Bompertuis",
    "iso:country":"FR",
    "sg:address":"15, ZI Bompertuis, 13120 Gardanne",
    "sg:orig_category":"Non-Classified Establishments",
    "sg:phone":"+33 4 42 58 33 99",
    "wof:name":"S.g.d.a. S.a.",
    "wof:placetype":"venue"
},
  "geometry": {"coordinates":[5.47062,43.454971],"type":"Point"}
}