{
  "type": "Feature",
  "properties": {
    "addr:full":"1430, Av. de la Lib\u00e9ration, 74460 Marnaz Rhone-Alpes 74460",
    "addr:housenumber":"1430",
    "addr:postcode":"74460;74460",
    "addr:street":"Av. De La Libe\u0301Ration;Rhone-Alpes",
    "iso:country":"FR",
    "sg:address":"1430, Av. de la Lib\u00e9ration, 74460 Marnaz",
    "sg:orig_category":"Non-Classified Establishments",
    "sg:phone":"+33 4 50 98 31 71",
    "sg:postcode":"74460",
    "sg:province":"Rhone-Alpes",
    "wof:name":"De Franceschi Et Fils S.a.r.l.",
    "wof:placetype":"venue"
},
  "geometry": {"coordinates":[6.514075,46.065655],"type":"Point"}
}