{
  "type": "Feature",
  "properties": {
    "iso:country":"FR",
    "sg:address":"101, Rue Saint Dominique, 75007 Paris",
    "sg:orig_category":"Non-Classified Establishments",
    "sg:phone":"+33 1 47 53 53 53",
    "sg:province":"Ile de France",
    "wof:name":"Florence Dor\u00e9 S.a.r.l.",
    "wof:placetype":"venue"
},
  "geometry": {"coordinates":[2.306154,48.859306],"type":"Point"}
}