{
  "type": "Feature",
  "properties": {
    "iso:country":"FR",
    "sg:address":"bd",
    "sg:city":"Innovation 67400 Illkirch Graffenstaden",
    "sg:classifiers":[
        {
            "category":"Manufacturing",
            "subcategory":"Tools & Machinery",
            "type":"Manufacturing & Wholesale Goods"
        }
    ],
    "sg:phone":"+33 3 88 67 14 14",
    "sg:postcode":"67400",
    "sg:province":"Alsace",
    "sg:tags":[
        "equipment",
        "measurement",
        "-",
        "precision",
        "instrument"
    ],
    "wof:name":"Fisher Bioblock Scientific",
    "wof:placetype":"venue"
},
  "geometry": {"coordinates":[7.711838,48.528809],"type":"Point"}
}