{
  "type": "Feature",
  "properties": {
    "addr:full":"7, Place Dufour, 72170 Beaumont sur Sarthe Pays de Loire 72170",
    "addr:housenumber":"7",
    "addr:postcode":"72170;sarthe;72170",
    "addr:street":"Place Dufour;Loire",
    "iso:country":"FR",
    "sg:address":"7, Place Dufour, 72170 Beaumont sur Sarthe",
    "sg:orig_category":"Non-Classified Establishments",
    "sg:phone":"+33 2 43 97 00 12",
    "sg:postcode":"72170",
    "sg:province":"Pays de Loire",
    "wof:name":"Etablissements Maudet S.a.",
    "wof:placetype":"venue"
},
  "geometry": {"coordinates":[0.129935,48.226665],"type":"Point"}
}