{
  "type": "Feature",
  "properties": {
    "addr:full":"3788 Avenue Kennedy 30900 N\u00eemes Languedoc-Roussillon",
    "addr:housenumber":"3788",
    "addr:postcode":"30900",
    "addr:street":"Avenue Kennedy",
    "iso:country":"FR",
    "sg:address":"3788 Avenue Kennedy 30900 N\u00eemes",
    "sg:classifiers":[
        {
            "category":"Professional",
            "type":"Services"
        }
    ],
    "sg:phone":"+33 4 66 68 92 92",
    "sg:province":"Languedoc-Roussillon",
    "sg:tags":[
        "transport",
        "road"
    ],
    "wof:name":"Mory Team Sa",
    "wof:placetype":"venue"
},
  "geometry": {"coordinates":[4.311468,43.814365],"type":"Point"}
}