{
  "type": "Feature",
  "properties": {
    "addr:full":"1, Rue de l'Industrie, 44520 Iss\u00e9 Pays de Loire 44520",
    "addr:housenumber":"1",
    "addr:postcode":"44520;44520",
    "addr:street":"Rue De L'Industrie",
    "iso:country":"FR",
    "sg:address":"1, Rue de l'Industrie, 44520 Iss\u00e9",
    "sg:orig_category":"Non-Classified Establishments",
    "sg:phone":"+33 2 40 55 10 05",
    "sg:postcode":"44520",
    "sg:province":"Pays de Loire",
    "wof:name":"Atlas S.a.",
    "wof:placetype":"venue"
},
  "geometry": {"coordinates":[-1.452887,47.620457],"type":"Point"}
}