{
  "type": "Feature",
  "properties": {
    "addr:full":"10, All\u00e9e des Erables, 86130 Dissay Poitou-Charentes 86130",
    "addr:housenumber":"10",
    "addr:postcode":"86130;86130",
    "addr:street":"Alle\u0301E Des Erables",
    "iso:country":"FR",
    "sg:address":"10, All\u00e9e des Erables, 86130 Dissay",
    "sg:orig_category":"Unclassifiable Establishments",
    "sg:phone":"+33 5 49 52 44 39",
    "sg:postcode":"86130",
    "sg:province":"Poitou-Charentes",
    "wof:name":"Chaveneau Bernis S.a.",
    "wof:placetype":"venue"
},
  "geometry": {"coordinates":[0.404632,46.703548],"type":"Point"}
}