{
  "type": "Feature",
  "properties": {
    "iso:country":"FR",
    "sg:address":"42, Rue Ernest Renan, 92240 Malakoff",
    "sg:orig_category":"Non-Classified Establishments",
    "sg:phone":"+33 1 40 92 81 29",
    "sg:postcode":"92240",
    "sg:province":"Ile de France",
    "wof:name":"C.e.i. Design S.a.r.l.",
    "wof:placetype":"venue"
},
  "geometry": {"coordinates":[2.30543,48.822292],"type":"Point"}
}