{
  "type": "Feature",
  "properties": {
    "addr:full":"26 Avenue De La Feuillade 26200 Montelimar Rhone-Alpes 26200",
    "addr:housenumber":"26",
    "addr:postcode":"26200;26200",
    "addr:street":"Avenue De La Feuillade;Rhone-Alpes",
    "iso:country":"FR",
    "sg:address":"26 Avenue De La Feuillade 26200 Montelimar",
    "sg:classifiers":[
        {
            "category":"Utilities",
            "subcategory":"Electric",
            "type":"Services"
        }
    ],
    "sg:phone":"+33 4 75 53 02 28",
    "sg:postcode":"26200",
    "sg:province":"Rhone-Alpes",
    "sg:tags":[
        "electricity",
        "electronic",
        "electrical",
        "equipment"
    ],
    "wof:name":"Comptoir Electrique Francais",
    "wof:placetype":"venue"
},
  "geometry": {"coordinates":[4.747993,44.575935],"type":"Point"}
}