{
  "type": "Feature",
  "properties": {
    "iso:country":"FR",
    "sg:address":"2, Passage Flourens, 75017 Paris",
    "sg:orig_category":"Non-Classified Establishments",
    "sg:phone":"+33 1 48 33 19 60",
    "sg:province":"Ile de France",
    "wof:name":"Ps-coffres-forts S.a.r.l.",
    "wof:placetype":"venue"
},
  "geometry": {"coordinates":[2.32649,48.897335],"type":"Point"}
}