{
  "type": "Feature",
  "properties": {
    "addr:full":"51, Rue de la Source, 62149 Givenchy les la Bass\u00e9e Nord Pas-de-Calais",
    "addr:housenumber":"51",
    "addr:postcode":"62149",
    "addr:street":"Rue De La Source",
    "iso:country":"FR",
    "sg:address":"51, Rue de la Source, 62149 Givenchy les la Bass\u00e9e",
    "sg:orig_category":"Non-Classified Establishments",
    "sg:phone":"+33 3 21 02 06 05",
    "sg:province":"Nord Pas-de-Calais",
    "wof:name":"H2o S.a.",
    "wof:placetype":"venue"
},
  "geometry": {"coordinates":[2.749179,50.528324],"type":"Point"}
}