{
  "type": "Feature",
  "properties": {
    "iso:country":"FR",
    "sg:address":"10 Rue Edouard Branly 37550 St Avertin",
    "sg:city":"Saint-Avertin",
    "sg:classifiers":[
        {
            "category":"Professional",
            "subcategory":"Engineering",
            "type":"Services"
        }
    ],
    "sg:phone":"+33 2 47 48 03 91",
    "sg:postcode":"37550",
    "sg:province":"Centre",
    "sg:tags":[
        "machine",
        "-",
        "mechanical"
    ],
    "wof:name":"Societe Lehoux",
    "wof:placetype":"venue"
},
  "geometry": {"coordinates":[0.730319,47.344898],"type":"Point"}
}