{
  "type": "Feature",
  "properties": {
    "addr:full":"34 Rue Du Gal Sarrail 62500 St Omer Nord Pas-de-Calais",
    "addr:housenumber":"34",
    "addr:postcode":"62500",
    "addr:street":"Rue Du Gal Sarrail;Omer Nord",
    "iso:country":"FR",
    "sg:address":"34 Rue Du Gal Sarrail 62500 St Omer",
    "sg:classifiers":[
        {
            "category":"Professional",
            "subcategory":"Printing & Photocopies",
            "type":"Services"
        }
    ],
    "sg:phone":"+33 3 21 98 12 12",
    "sg:province":"Nord Pas-de-Calais",
    "sg:tags":[
        "publishing"
    ],
    "wof:name":"G Et B Affichage",
    "wof:placetype":"venue"
},
  "geometry": {"coordinates":[2.263621,50.748402],"type":"Point"}
}