{
  "type": "Feature",
  "properties": {
    "addr:full":"B.P. 93, 67455 Mundolsheim C\u00e9dex^^1, Rue du Commerce, 67116 Reichstett Reichstett Alsace 67116",
    "addr:postcode":"67455;67116;67116",
    "addr:street":"B.P. 93;Rue Du Commerce",
    "iso:country":"FR",
    "sg:address":"B.P. 93, 67455 Mundolsheim C\u00e9dex^^1, Rue du Commerce, 67116 Reichstett",
    "sg:city":"Reichstett",
    "sg:orig_category":"Portes Portes accord\u00e9ons Portes automatiques Portes coulissantes Portes industrielles Portes pliante",
    "sg:phone":"+33 3 88 81 81 01",
    "sg:postcode":"67116",
    "sg:province":"Alsace",
    "wof:name":"Bator France S.a.",
    "wof:placetype":"venue"
},
  "geometry": {"coordinates":[7.753589,48.648308],"type":"Point"}
}