{
  "type": "Feature",
  "properties": {
    "addr:full":"11 Rue Des Fr\u00e8res Lumi\u00e8re Zi Du Plan D'Acier 39200 St Claude Franche Comt\u00e9 39200",
    "addr:housenumber":"11",
    "addr:postcode":"39200;39200",
    "addr:street":"Rue Des Fre\u0300Res Lumie\u0300Re Zi Du Plan D'Acier;St Claude Franche Comte\u0301",
    "iso:country":"FR",
    "sg:address":"11 Rue Des Fr\u00e8res Lumi\u00e8re Zi Du Plan D'Acier 39200 St Claude",
    "sg:classifiers":[
        {
            "category":"Manufacturing",
            "subcategory":"Metals",
            "type":"Manufacturing & Wholesale Goods"
        }
    ],
    "sg:phone":"+33 3 84 41 50 00",
    "sg:postcode":"39200",
    "sg:province":"Franche Comt\u00e9",
    "sg:tags":[
        "pharmaceutical",
        "processing",
        "-",
        "metallurgy",
        "metalworking",
        "chemical",
        "chemistry",
        "by-product"
    ],
    "wof:name":"Cts Sa",
    "wof:placetype":"venue"
},
  "geometry": {"coordinates":[5.827746,46.38319],"type":"Point"}
}