{
  "type": "Feature",
  "properties": {
    "iso:country":"FR",
    "sg:address":"B.P. 5, 40320 Geaune^^80, Rte de Garlin, 40320 Geaune",
    "sg:city":"Geaune",
    "sg:orig_category":"Non-Classified Establishments",
    "sg:phone":"+33 5 58 44 57 85",
    "sg:postcode":"40320",
    "sg:province":"Aquitaine",
    "wof:name":"Brethes Alain S.a.r.l.",
    "wof:placetype":"venue"
},
  "geometry": {"coordinates":[-0.446669,43.564331],"type":"Point"}
}