{
  "type": "Feature",
  "properties": {
    "iso:country":"FR",
    "sg:address":"128 Rue Lecourbe 75015 Paris",
    "sg:classifiers":[
        {
            "category":"Professional",
            "subcategory":"Business Services",
            "type":"Services"
        }
    ],
    "sg:phone":"+33 1 48 42 22 79",
    "sg:postcode":"75015",
    "sg:province":"Ile de France",
    "sg:tags":[
        "travel",
        "fair"
    ],
    "wof:name":"Centrale Des Seminaires Sarl",
    "wof:placetype":"venue"
},
  "geometry": {"coordinates":[2.301421,48.842392],"type":"Point"}
}