{
  "type": "Feature",
  "properties": {
    "iso:country":"FR",
    "sg:address":"72 avenue de Ferrieres 70170 Port Sur Saone",
    "sg:classifiers":[
        {
            "category":"Parking",
            "subcategory":"Garage",
            "type":"Transportation"
        }
    ],
    "sg:phone":"+33 3 84 91 51 55",
    "sg:postcode":"70170",
    "sg:province":"Franche Comt\u00e9",
    "sg:tags":[
        "agricultural",
        "trailer"
    ],
    "wof:name":"Etablissements Masson S.a.r.l.",
    "wof:placetype":"venue"
},
  "geometry": {"coordinates":[6.02534,47.679409],"type":"Point"}
}