{
  "type": "Feature",
  "properties": {
    "iso:country":"FR",
    "sg:address":"ZI",
    "sg:city":"Gustave Eiffel 28630 Chartres",
    "sg:classifiers":[
        {
            "category":"Manufacturing",
            "subcategory":"Rubber & Plastics",
            "type":"Manufacturing & Wholesale Goods"
        }
    ],
    "sg:phone":"+33 2 37 33 43 63",
    "sg:postcode":"28630",
    "sg:province":"Centre",
    "sg:tags":[
        "packaging",
        "product",
        "material",
        "-",
        "miscellaneous"
    ],
    "wof:name":"Sipack",
    "wof:placetype":"venue"
},
  "geometry": {"coordinates":[1.537205,48.444801],"type":"Point"}
}