{
  "type": "Feature",
  "properties": {
    "iso:country":"FR",
    "sg:address":"Avenue De La Dordogne Zi De Petite Synthe 59640 Dunkerque",
    "sg:classifiers":[
        {
            "category":"Professional",
            "subcategory":"Engineering",
            "type":"Services"
        }
    ],
    "sg:phone":"+33 3 28 58 72 92",
    "sg:province":"Midi Pyr\u00e9n\u00e9es",
    "sg:tags":[
        "machine",
        "-",
        "mechanical"
    ],
    "wof:name":"Ponticelli Martin Mecanique Pmm",
    "wof:placetype":"venue"
},
  "geometry": {"coordinates":[2.335941,51.015495],"type":"Point"}
}