{
  "type": "Feature",
  "properties": {
    "iso:country":"FR",
    "sg:address":"39570 Quintigny",
    "sg:classifiers":[
        {
            "category":"Food Court",
            "type":"Food & Drink"
        }
    ],
    "sg:phone":"+33 3 84 48 12 18",
    "sg:postcode":"39570",
    "sg:province":"Franche Comt\u00e9",
    "sg:tags":[
        "product",
        "related"
    ],
    "wof:name":"M. Jacquier Louis",
    "wof:placetype":"venue"
},
  "geometry": {"coordinates":[5.524993,46.734066],"type":"Point"}
}