{
  "type": "Feature",
  "properties": {
    "addr:full":"16 Av Louison Bobet 06130 Grasse Rhone-Alpes",
    "addr:postcode":"06130",
    "addr:street":"16 Av Louison Bobet",
    "iso:country":"FR",
    "sg:address":"16 Av Louison Bobet 06130 Grasse",
    "sg:classifiers":[
        {
            "category":"Manufacturing",
            "subcategory":"Chemicals & Compounds",
            "type":"Manufacturing & Wholesale Goods"
        }
    ],
    "sg:phone":"+33 4 92 42 42 52",
    "sg:province":"Rhone-Alpes",
    "sg:tags":[
        "pharmaceutical",
        "chemistry",
        "-",
        "by-product"
    ],
    "wof:name":"Parfex Sa",
    "wof:placetype":"venue"
},
  "geometry": {"coordinates":[6.941587,43.626945],"type":"Point"}
}