{
  "type": "Feature",
  "properties": {
    "iso:country":"FR",
    "sg:address":"62, Rte de Bretagne, 14760 Bretteville sur Odon",
    "sg:city":"Bretteville-sur-Odon",
    "sg:orig_category":"Unclassifiable Establishments",
    "sg:phone":"+33 2 31 75 07 80",
    "sg:postcode":"14760",
    "sg:province":"Basse Normandie",
    "wof:name":"I.f.i. S.n.c.",
    "wof:placetype":"venue"
},
  "geometry": {"coordinates":[-0.40996,49.167873],"type":"Point"}
}