{
  "type": "Feature",
  "properties": {
    "addr:full":"51 bd Dames 2e; Marseille Nord Pas-de-Calais",
    "addr:housenumber":"51;2e",
    "addr:street":"Bd Dames",
    "iso:country":"FR",
    "sg:address":"51 bd Dames 2e; Marseille",
    "sg:classifiers":[
        {
            "category":"Banks & Credit Unions",
            "subcategory":"Bank",
            "type":"Services"
        }
    ],
    "sg:phone":"+33 3391397000",
    "sg:province":"Nord Pas-de-Calais",
    "wof:name":"Cr\u00e9dit Universel",
    "wof:placetype":"venue"
},
  "geometry": {"coordinates":[5.37249,43.293686],"type":"Point"}
}