{
  "type": "Feature",
  "properties": {
    "iso:country":"FR",
    "sg:address":"1 Rue Henri Iv 80000 Amiens",
    "sg:classifiers":[
        {
            "category":"Manufacturing",
            "subcategory":"Wood Products",
            "type":"Manufacturing & Wholesale Goods"
        }
    ],
    "sg:phone":"+33 3 22 22 51 70",
    "sg:province":"Picardie",
    "sg:tags":[
        "professional",
        "furniture"
    ],
    "wof:name":"Sansen Sa",
    "wof:placetype":"venue"
},
  "geometry": {"coordinates":[2.299397,49.895035],"type":"Point"}
}