{
  "type": "Feature",
  "properties": {
    "addr:full":"65, Bd Vivier Merle, 69482 Lyon C\u00e9dex 03 Rhone-Alpes",
    "addr:housenumber":"65;03",
    "addr:postcode":"69482",
    "addr:street":"Bd Vivier;Ce\u0301Dex",
    "iso:country":"FR",
    "sg:address":"65, Bd Vivier Merle, 69482 Lyon C\u00e9dex 03",
    "sg:orig_category":"Non-Classified Establishments",
    "sg:phone":"+33 4 72 13 40 40",
    "sg:province":"Rhone-Alpes",
    "wof:name":"Winterthur Assurances",
    "wof:placetype":"venue"
},
  "geometry": {"coordinates":[4.86843,45.751369],"type":"Point"}
}