{
  "type": "Feature",
  "properties": {
    "iso:country":"FR",
    "sg:address":"Les Landes de Beaug\u00e9 35345 Liffr\u00e9 C\u00e9dex",
    "sg:orig_category":"Non-Classified Establishments",
    "sg:phone":"+33 2 99 23 51 11",
    "sg:province":"Haute Normandie",
    "wof:name":"Canon Bretagne S.a.",
    "wof:placetype":"venue"
},
  "geometry": {"coordinates":[-1.507956,48.213875],"type":"Point"}
}