{
  "type": "Feature",
  "properties": {
    "addr:full":"Av Sarraz Bournet 62480 Le Portel Nord Pas-de-Calais 62480",
    "addr:postcode":"62480;62480",
    "addr:street":"Av Sarraz Bournet;Pas-De-Calais",
    "iso:country":"FR",
    "sg:address":"Av Sarraz Bournet 62480 Le Portel",
    "sg:classifiers":[
        {
            "category":"Farming",
            "subcategory":"Livestock Farm",
            "type":"Manufacturing & Wholesale Goods"
        }
    ],
    "sg:phone":"+33 3 21 32 27 28",
    "sg:postcode":"62480",
    "sg:province":"Nord Pas-de-Calais",
    "sg:tags":[
        "breeding",
        "agriculture",
        "animal"
    ],
    "wof:name":"Eurofilets Sa",
    "wof:placetype":"venue"
},
  "geometry": {"coordinates":[1.584358,50.721577],"type":"Point"}
}