{
  "type": "Feature",
  "properties": {
    "iso:country":"FR",
    "sg:address":"Zac de la Sol\u00e8re 54420 SAULXURES LES NANCY",
    "sg:classifiers":[
        {
            "category":"Shopping",
            "subcategory":"Beauty & Cosmetics",
            "type":"Retail Goods"
        }
    ],
    "sg:phone":"+33 3 83 29 46 46",
    "sg:province":"Lorraine",
    "sg:tags":[
        "perfume"
    ],
    "wof:name":"C.e.p. Sa",
    "wof:placetype":"venue"
},
  "geometry": {"coordinates":[6.24509,48.687649],"type":"Point"}
}