{
  "type": "Feature",
  "properties": {
    "iso:country":"FR",
    "sg:address":"B.P. 204, 41200 Romorantin Lanthenay^^Av. de Villefranche - ZI de l'Arche, 41200 Romorantin Lanthena",
    "sg:city":"Villefranche-sur-Cher",
    "sg:orig_category":"Non-Classified Establishments",
    "sg:phone":"+33 2 54 76 22 71",
    "sg:postcode":"41200",
    "sg:province":"Centre",
    "wof:name":"Simon Martin Partner S.a.r.l.",
    "wof:placetype":"venue"
},
  "geometry": {"coordinates":[4.717579,45.991653],"type":"Point"}
}