{
  "type": "Feature",
  "properties": {
    "iso:country":"FR",
    "sg:address":"ZA du Chalet",
    "sg:city":"Vitr\u00e9",
    "sg:orig_category":"Non-Classified Establishments",
    "sg:phone":"+33 2 99 74 75 39",
    "sg:postcode":"35550",
    "sg:province":"Bretagne",
    "wof:name":"Famip S.a.",
    "wof:placetype":"venue"
},
  "geometry": {"coordinates":[-87.153,33.737171],"type":"Point"}
}