{
  "type": "Feature",
  "properties": {
    "iso:country":"FR",
    "sg:address":"215, Rue Samuel Morse, 34000 Montpellier",
    "sg:orig_category":"Unclassifiable Establishments",
    "sg:phone":"+33 4 99 52 47 00",
    "sg:province":"Languedoc-Roussillon",
    "wof:name":"Compagnie Des Salins Du Midi Et Des Salines De L'est S.a.",
    "wof:placetype":"venue"
},
  "geometry": {"coordinates":[3.913959,43.606453],"type":"Point"}
}