{
  "type": "Feature",
  "properties": {
    "addr:full":"All Cl\u00e9ment Ader Zi La Rte De Surgy 58500 Clamecy Surgy Bourgogne 58500",
    "addr:postcode":"58500;58500",
    "addr:street":"Zi La Rte De Surgy",
    "iso:country":"FR",
    "sg:address":"All Cl\u00e9ment Ader Zi La Rte De Surgy 58500 Clamecy",
    "sg:city":"Surgy",
    "sg:classifiers":[
        {
            "category":"Shopping",
            "type":"Retail Goods"
        }
    ],
    "sg:phone":"+33 3 86 27 50 50",
    "sg:postcode":"58500",
    "sg:province":"Bourgogne",
    "sg:tags":[
        "metallurgy",
        "finished",
        "-",
        "metalworking",
        "metallic"
    ],
    "wof:name":"Cico Centre Sa",
    "wof:placetype":"venue"
},
  "geometry": {"coordinates":[3.520745,47.459946],"type":"Point"}
}