{
  "type": "Feature",
  "properties": {
    "addr:full":"1 impasse Champeau 21800 Quetigny Quetigny Bourgogne 21800",
    "addr:housenumber":"1",
    "addr:postcode":"21800;21800",
    "addr:street":"Impasse Champeau",
    "iso:country":"FR",
    "sg:address":"1 impasse Champeau 21800 Quetigny",
    "sg:city":"Quetigny",
    "sg:classifiers":[
        {
            "category":"Professional",
            "subcategory":"Advertising",
            "type":"Services"
        }
    ],
    "sg:phone":"+33 3 80 48 90 90",
    "sg:postcode":"21800",
    "sg:province":"Bourgogne",
    "sg:tags":[
        "film"
    ],
    "wof:name":"B.v.i. S.a.r.l.",
    "wof:placetype":"venue"
},
  "geometry": {"coordinates":[5.093649,47.316307],"type":"Point"}
}