{
  "type": "Feature",
  "properties": {
    "addr:full":"RN 7 - ZI les Plaines 1 Malataverne Rhone-Alpes 26780",
    "addr:housenumber":"1",
    "addr:postcode":"26780",
    "addr:street":"Rn 7 Zi Les Plaines;Rhone-Alpes",
    "iso:country":"FR",
    "sg:address":"RN 7 - ZI les Plaines 1",
    "sg:city":"Malataverne",
    "sg:orig_category":"Unclassifiable Establishments",
    "sg:phone":"+33 4 75 90 70 45",
    "sg:postcode":"26780",
    "sg:province":"Rhone-Alpes",
    "wof:name":"Carr\u00e9 Bleu International G.i.e.",
    "wof:placetype":"venue"
},
  "geometry": {"coordinates":[4.734275,44.459469],"type":"Point"}
}