{
  "type": "Feature",
  "properties": {
    "iso:country":"FR",
    "sg:address":"5 Quai Charles Lallement 57400 Sarrebourg",
    "sg:classifiers":[
        {
            "category":"Professional",
            "subcategory":"Printing & Photocopies",
            "type":"Services"
        }
    ],
    "sg:phone":"+33 3 87 03 05 50",
    "sg:province":"Lorraine",
    "sg:tags":[
        "publishing"
    ],
    "wof:name":"Le Republicain Lorrain (rl)",
    "wof:placetype":"venue"
},
  "geometry": {"coordinates":[7.049696,48.736099],"type":"Point"}
}