{
  "type": "Feature",
  "properties": {
    "addr:full":"B.P. 5, 08000 Warcq^^Chemin de Sury, 08000 Warcq Charleville-M\u00e9zi\u00e8res Champagne 08000",
    "addr:housenumber":"5",
    "addr:postcode":"08000;08000;08000",
    "addr:street":"B.P.;Sury",
    "iso:country":"FR",
    "sg:address":"B.P. 5, 08000 Warcq^^Chemin de Sury, 08000 Warcq",
    "sg:city":"Charleville-M\u00e9zi\u00e8res",
    "sg:orig_category":"Brochage Fraisage CN M\u00e9canique de pr\u00e9cision M\u00e9canique g\u00e9n\u00e9rale Rodage Tournage CN Usinage Usinage de",
    "sg:phone":"+33 3 24 56 04 67",
    "sg:postcode":"08000",
    "sg:province":"Champagne",
    "wof:name":"Socaus S.a.s.",
    "wof:placetype":"venue"
},
  "geometry": {"coordinates":[4.7174,49.758801],"type":"Point"}
}