{
  "type": "Feature",
  "properties": {
    "iso:country":"FR",
    "sg:address":"B.P. 17, 59127 Walincourt Selvigny^^32, Rue de Caullery, 59127 Walincourt Selvigny",
    "sg:orig_category":"Non-Classified Establishments",
    "sg:phone":"+33 3 27 78 82 21",
    "sg:postcode":"59127",
    "sg:province":"Nord Pas-de-Calais",
    "wof:name":"Broderies Du Loup Noir S.a.r.l.",
    "wof:placetype":"venue"
},
  "geometry": {"coordinates":[3.33203,50.071609],"type":"Point"}
}