{
  "type": "Feature",
  "properties": {
    "iso:country":"FR",
    "sg:address":"38, Av. de la Glaci\u00e8re, 95100 Argenteuil",
    "sg:orig_category":"Unclassifiable Establishments",
    "sg:phone":"+33 1 39 80 57 85",
    "sg:province":"Ile de France",
    "wof:name":"Delva S.a.",
    "wof:placetype":"venue"
},
  "geometry": {"coordinates":[2.229197,48.937496],"type":"Point"}
}