{
  "type": "Feature",
  "properties": {
    "addr:full":"33 Rue Saint Mathieu Quimper Bretagne 29000",
    "addr:housenumber":"33",
    "addr:postcode":"29000",
    "addr:street":"Rue Saint Mathieu Quimper",
    "iso:country":"FR",
    "sg:address":"33 Rue Saint Mathieu",
    "sg:city":"Quimper",
    "sg:classifiers":[
        {
            "category":"Banks & Credit Unions",
            "subcategory":"Financial Services",
            "type":"Services"
        }
    ],
    "sg:phone":"+33 2 98 64 69 00",
    "sg:postcode":"29000",
    "sg:province":"Bretagne",
    "sg:tags":[
        "banking",
        "finance",
        "insurance"
    ],
    "wof:name":"Caisse Regionale De Credit Agricole Mutuel Du Finistere (ca)",
    "wof:placetype":"venue"
},
  "geometry": {"coordinates":[-4.108217,47.995361],"type":"Point"}
}