{
  "type": "Feature",
  "properties": {
    "addr:full":"139, Rue Alexis Peronsel, 69100 Villeurbanne Rhone-Alpes 69100",
    "addr:housenumber":"139",
    "addr:postcode":"69100;69100",
    "addr:street":"Rue Alexis Peronsel",
    "iso:country":"FR",
    "sg:address":"139, Rue Alexis Peronsel, 69100 Villeurbanne",
    "sg:orig_category":"Non-Classified Establishments",
    "sg:phone":"+33 4 78 68 07 95",
    "sg:postcode":"69100",
    "sg:province":"Rhone-Alpes",
    "wof:name":"M.e.r.i.c. S.a.r.l. - Ma\u00e7onnerie Entretien Ravalement Isolation Constructions",
    "wof:placetype":"venue"
},
  "geometry": {"coordinates":[4.883813,45.775852],"type":"Point"}
}