{
  "type": "Feature",
  "properties": {
    "iso:country":"FR",
    "sg:address":"Route De Najauge Zi 08320 Vireux Molhain",
    "sg:city":"Aubrives",
    "sg:classifiers":[
        {
            "category":"Autos & Motor Vehicles",
            "subcategory":"Automobile Sales",
            "type":"Retail Goods"
        }
    ],
    "sg:phone":"+33 3 24 41 00 36",
    "sg:postcode":"08320",
    "sg:province":"Champagne",
    "sg:tags":[
        "equipment",
        "motor-cars",
        "transport"
    ],
    "wof:name":"Brichet Courtois Hache Bch",
    "wof:placetype":"venue"
},
  "geometry": {"coordinates":[4.73821,50.105011],"type":"Point"}
}