{
  "type": "Feature",
  "properties": {
    "addr:full":"av Henri Clews Napoule; Mandelieu la Napoule Haute Normandie",
    "addr:street":"Av Henri Clews Napoule;Haute Normandie",
    "iso:country":"FR",
    "sg:address":"av Henri Clews Napoule; Mandelieu la Napoule",
    "sg:classifiers":[
        {
            "category":"Banks & Credit Unions",
            "subcategory":"Bank",
            "type":"Services"
        }
    ],
    "sg:phone":"+33 3393930947",
    "sg:province":"Haute Normandie",
    "wof:name":"Soci\u00e9t\u00e9 G\u00e9n\u00e9rale",
    "wof:placetype":"venue"
},
  "geometry": {"coordinates":[6.93744,43.544094],"type":"Point"}
}