{
  "type": "Feature",
  "properties": {
    "addr:full":"1, Rue Jean Perrin, 93150 Le Blanc Mesnil Ile de France 93150",
    "addr:housenumber":"1",
    "addr:postcode":"93150;93150",
    "addr:street":"Rue Jean Perrin",
    "iso:country":"FR",
    "sg:address":"1, Rue Jean Perrin, 93150 Le Blanc Mesnil",
    "sg:orig_category":"Non-Classified Establishments",
    "sg:phone":"+33 1 55 81 00 71",
    "sg:postcode":"93150",
    "sg:province":"Ile de France",
    "wof:name":"A.m.s. S.a. - Audio Marketing Services",
    "wof:placetype":"venue"
},
  "geometry": {"coordinates":[2.450206,48.953289],"type":"Point"}
}