{
  "type": "Feature",
  "properties": {
    "iso:country":"FR",
    "sg:address":"8, Croix Jacquebot, 95450 Vigny",
    "sg:orig_category":"Unclassifiable Establishments",
    "sg:phone":"+33 1 34 48 61 61",
    "sg:province":"Ile de France",
    "wof:name":"M.d.s. S.a.r.l. - Maintenance De Services",
    "wof:placetype":"venue"
},
  "geometry": {"coordinates":[1.928298,49.082207],"type":"Point"}
}