{
  "type": "Feature",
  "properties": {
    "addr:full":"ZI de Cormage Vizille Rhone-Alpes 38220",
    "addr:postcode":"38220",
    "addr:street":"Zi De Cormage;Rhone-Alpes",
    "iso:country":"FR",
    "sg:address":"ZI de Cormage",
    "sg:city":"Vizille",
    "sg:orig_category":"Unclassifiable Establishments",
    "sg:phone":"+33 4 76 68 19 44",
    "sg:postcode":"38220",
    "sg:province":"Rhone-Alpes",
    "wof:name":"Antico S.a.",
    "wof:placetype":"venue"
},
  "geometry": {"coordinates":[5.77226,45.075569],"type":"Point"}
}