{
  "type": "Feature",
  "properties": {
    "iso:country":"FR",
    "sg:address":"21, Rue de Borolan - ZI des Landiers, 73000 Chamb\u00e9ry",
    "sg:orig_category":"Non-Classified Establishments",
    "sg:phone":"+33 4 79 96 15 30",
    "sg:postcode":"73000",
    "sg:province":"Rhone-Alpes",
    "wof:name":"Bessone S.a.",
    "wof:placetype":"venue"
},
  "geometry": {"coordinates":[5.90839,45.538151],"type":"Point"}
}