{
  "type": "Feature",
  "properties": {
    "addr:full":"22, Av Foch, 54000 Nancy Lorraine",
    "addr:postcode":"54000",
    "addr:street":"22 Av Foch",
    "iso:country":"FR",
    "sg:address":"22, Av Foch, 54000 Nancy",
    "sg:orig_category":"Unclassifiable Establishments",
    "sg:phone":"+33 3 83 28 61 11",
    "sg:province":"Lorraine",
    "wof:name":"Schweitzer S.a.",
    "wof:placetype":"venue"
},
  "geometry": {"coordinates":[6.172795,48.688129],"type":"Point"}
}