{
  "type": "Feature",
  "properties": {
    "addr:full":"Bd de Yougoslavie Rennes Bretagne 35000",
    "addr:postcode":"35000",
    "addr:street":"Bd De Yougoslavie Rennes",
    "iso:country":"FR",
    "sg:address":"Bd de Yougoslavie",
    "sg:city":"Rennes",
    "sg:orig_category":"Unclassifiable Establishments",
    "sg:phone":"+33 2 99 22 27 27",
    "sg:postcode":"35000",
    "sg:province":"Bretagne",
    "wof:name":"Triangle Culture Et Congr\u00e8s - Rennes",
    "wof:placetype":"venue"
},
  "geometry": {"coordinates":[-1.658287,48.088154],"type":"Point"}
}