{
  "type": "Feature",
  "properties": {
    "iso:country":"FR",
    "sg:address":"Rue de la Gare",
    "sg:city":"Saint Pierre l\u00e8s Elbeuf",
    "sg:orig_category":"Non-Classified Establishments",
    "sg:phone":"+33 2 35 77 61 50",
    "sg:postcode":"76320",
    "sg:province":"Haute Normandie",
    "wof:name":"Grem S.a.",
    "wof:placetype":"venue"
},
  "geometry": {"coordinates":[1.036502,49.269714],"type":"Point"}
}