{
  "type": "Feature",
  "properties": {
    "addr:full":"Av. Hector Berlioz - ZI Cournon d'Auvergne C\u00e9dex Champagne 63802",
    "addr:postcode":"ce\u0301dex;63802",
    "addr:street":"Av. Hector Berlioz Zi;D'Auvergne",
    "iso:country":"FR",
    "sg:address":"Av. Hector Berlioz - ZI",
    "sg:city":"Cournon d'Auvergne C\u00e9dex",
    "sg:orig_category":"Non-Classified Establishments",
    "sg:phone":"+33 4 73 64 75 00",
    "sg:postcode":"63802",
    "sg:province":"Champagne",
    "wof:name":"Auvergne Transroute Transbennes",
    "wof:placetype":"venue"
},
  "geometry": {"coordinates":[3.19922,45.741951],"type":"Point"}
}