{
  "type": "Feature",
  "properties": {
    "addr:full":"13, Av de la Fontenelle, 88000 Epinal Lorraine",
    "addr:postcode":"88000",
    "addr:street":"13 Av De La Fontenelle",
    "iso:country":"FR",
    "sg:address":"13, Av de la Fontenelle, 88000 Epinal",
    "sg:orig_category":"Non-Classified Establishments",
    "sg:phone":"+33 3 29 81 50 00",
    "sg:province":"Lorraine",
    "wof:name":"Malnoy Pneu S.a.",
    "wof:placetype":"venue"
},
  "geometry": {"coordinates":[6.44211,48.189739],"type":"Point"}
}