{
  "type": "Feature",
  "properties": {
    "iso:country":"FR",
    "sg:address":"6, Rue du Champ des Cosaques, 60400 Noyon",
    "sg:orig_category":"Non-Classified Establishments",
    "sg:phone":"+33 3 44 44 14 96",
    "sg:province":"Picardie",
    "wof:name":"Seibo S.a.",
    "wof:placetype":"venue"
},
  "geometry": {"coordinates":[3.009088,49.579266],"type":"Point"}
}