{
  "type": "Feature",
  "properties": {
    "addr:full":"78410 Flins sur Seine Ile de France",
    "addr:postcode":"78410",
    "addr:street":"Flins;Seine",
    "iso:country":"FR",
    "sg:address":"78410 Flins sur Seine",
    "sg:orig_category":"Unclassifiable Establishments",
    "sg:phone":"+33 1 30 22 72 72",
    "sg:province":"Ile de France",
    "wof:name":"Renault S.a.",
    "wof:placetype":"venue"
},
  "geometry": {"coordinates":[1.87072,48.96463],"type":"Point"}
}