{
  "type": "Feature",
  "properties": {
    "iso:country":"FR",
    "sg:address":"ZI La Demi Lune",
    "sg:city":"Poitiers C\u00e9dex",
    "sg:orig_category":"Non-Classified Establishments",
    "sg:phone":"+33 5 49 37 60 10",
    "sg:postcode":"86060",
    "sg:province":"Poitou-Charentes",
    "wof:name":"Eurovia Poitou Charentes Limousin S.n.c.",
    "wof:placetype":"venue"
},
  "geometry": {"coordinates":[0.326725,46.597576],"type":"Point"}
}