{
  "type": "Feature",
  "properties": {
    "addr:full":"Rte d'Evron Br\u00e9e Pays de Loire 53150",
    "addr:postcode":"53150",
    "addr:street":"Rte D'Evron",
    "iso:country":"FR",
    "sg:address":"Rte d'Evron",
    "sg:city":"Br\u00e9e",
    "sg:orig_category":"Unclassifiable Establishments",
    "sg:phone":"+33 2 43 01 26 79",
    "sg:postcode":"53150",
    "sg:province":"Pays de Loire",
    "wof:name":"Rossignol S.a.",
    "wof:placetype":"venue"
},
  "geometry": {"coordinates":[-0.473519,48.156357],"type":"Point"}
}