{
  "type": "Feature",
  "properties": {
    "iso:country":"FR",
    "sg:address":"43, Rue des Fr\u00e8res Robespierre, 59300 Aulnoy lez Valenciennes",
    "sg:orig_category":"Unclassifiable Establishments",
    "sg:phone":"+33 3 27 47 35 78",
    "sg:province":"Nord Pas-de-Calais",
    "wof:name":"L.f.m. Electronique S.a.r.l.",
    "wof:placetype":"venue"
},
  "geometry": {"coordinates":[3.520323,50.331192],"type":"Point"}
}