{
  "type": "Feature",
  "properties": {
    "iso:country":"FR",
    "sg:address":"48, Rue de Poissy, 78100 Saint Germain en Laye",
    "sg:orig_category":"Unclassifiable Establishments",
    "sg:phone":"+33 1 39 21 14 50",
    "sg:province":"Ile de France",
    "wof:name":"Barclays Bank P.l.c. S.a.",
    "wof:placetype":"venue"
},
  "geometry": {"coordinates":[2.089777,48.897778],"type":"Point"}
}