{
  "type": "Feature",
  "properties": {
    "iso:country":"FR",
    "sg:address":"25, Rue du Mar\u00e9chal Foch, 78000 Versailles",
    "sg:orig_category":"Unclassifiable Establishments",
    "sg:phone":"+33 1 30 84 98 30",
    "sg:province":"Ile de France",
    "wof:name":"Polyplast M\u00fcller France S.a.r.l.",
    "wof:placetype":"venue"
},
  "geometry": {"coordinates":[2.132255,48.807373],"type":"Point"}
}