{
  "type": "Feature",
  "properties": {
    "addr:full":"Av. Gustave Eiffel - ZI Grande Marine L'Isle sur la Sorgue Haute Normandie 84800",
    "addr:postcode":"84800",
    "addr:street":"Av. Gustave Eiffel Zi Grande Marine;Haute Normandie",
    "iso:country":"FR",
    "sg:address":"Av. Gustave Eiffel - ZI Grande Marine",
    "sg:city":"L'Isle sur la Sorgue",
    "sg:orig_category":"Unclassifiable Establishments",
    "sg:phone":"+33 4 90 38 21 33",
    "sg:postcode":"84800",
    "sg:province":"Haute Normandie",
    "wof:name":"Imprimerie Des Sorgues S.a.r.l.",
    "wof:placetype":"venue"
},
  "geometry": {"coordinates":[5.03345,43.920746],"type":"Point"}
}