{
  "type": "Feature",
  "properties": {
    "iso:country":"FR",
    "sg:address":"19 rue Jean Rey 78220 Viroflay",
    "sg:classifiers":[
        {
            "category":"Home & Garden",
            "subcategory":"Building Materials",
            "type":"Retail Goods"
        }
    ],
    "sg:phone":"+33 1 30 24 47 58",
    "sg:postcode":"78220",
    "sg:province":"Ile de France",
    "sg:tags":[
        "current",
        "meter"
    ],
    "wof:name":"Souchon Sa",
    "wof:placetype":"venue"
},
  "geometry": {"coordinates":[2.170228,48.799152],"type":"Point"}
}