{
  "type": "Feature",
  "properties": {
    "addr:full":"4 Rue Du Courant Parc D'Activit\u00e9s Gardette 33310 Lormont Lormont Aquitaine 33310",
    "addr:housenumber":"4",
    "addr:postcode":"33310;33310",
    "addr:street":"Rue Du Courant Parc D'Activite \u0301S Gardette",
    "iso:country":"FR",
    "sg:address":"4 Rue Du Courant Parc D'Activit\u00e9s Gardette 33310 Lormont",
    "sg:city":"Lormont",
    "sg:classifiers":[
        {
            "category":"Professional",
            "subcategory":"Advertising",
            "type":"Services"
        }
    ],
    "sg:phone":"+33 5 57 77 16 10",
    "sg:postcode":"33310",
    "sg:province":"Aquitaine",
    "sg:tags":[
        "information",
        "medium",
        "communication"
    ],
    "wof:name":"Elyo Midi Ocean Agence Bordeaux Aquitaine",
    "wof:placetype":"venue"
},
  "geometry": {"coordinates":[-0.517545,44.885399],"type":"Point"}
}