{
  "type": "Feature",
  "properties": {
    "addr:full":"Rancy 03400 Yzeure Yzeure Auvergne 03400",
    "addr:postcode":"03400;03400",
    "iso:country":"FR",
    "sg:address":"Rancy 03400 Yzeure",
    "sg:city":"Yzeure",
    "sg:classifiers":[
        {
            "category":"Professional",
            "type":"Services"
        }
    ],
    "sg:phone":"+33 4 70 20 67 89",
    "sg:postcode":"03400",
    "sg:province":"Auvergne",
    "sg:tags":[
        "transport",
        "road"
    ],
    "wof:name":"Transports Yzeuriens Sarl",
    "wof:placetype":"venue"
},
  "geometry": {"coordinates":[3.356535,46.540051],"type":"Point"}
}