{
  "type": "Feature",
  "properties": {
    "addr:full":"116, Rte de Thionville - ZI Tilly - Hall 16, 57140 Woippy Lorraine",
    "addr:housenumber":"116;16",
    "addr:postcode":"57140",
    "addr:street":"Rte De Thionville Zi Tilly",
    "iso:country":"FR",
    "sg:address":"116, Rte de Thionville - ZI Tilly - Hall 16, 57140 Woippy",
    "sg:orig_category":"Unclassifiable Establishments",
    "sg:phone":"+33 3 87 33 24 24",
    "sg:province":"Lorraine",
    "wof:name":"Bacou D\u00e9veloppement - R\u00e9gion-est S.a.",
    "wof:placetype":"venue"
},
  "geometry": {"coordinates":[6.150305,49.15131],"type":"Point"}
}