{
  "type": "Feature",
  "properties": {
    "addr:full":"2 chemin des Vo\u00fbtes 81300 Graulhet Midi Pyr\u00e9n\u00e9es 81300",
    "addr:housenumber":"2",
    "addr:postcode":"81300;81300",
    "addr:street":"Chemin Des Vou\u0302Tes",
    "iso:country":"FR",
    "sg:address":"2 chemin des Vo\u00fbtes 81300 Graulhet",
    "sg:classifiers":[
        {
            "category":"Personal",
            "subcategory":"Shoe Repair & Shine",
            "type":"Services"
        }
    ],
    "sg:phone":"+33 5 63 34 63 86",
    "sg:postcode":"81300",
    "sg:province":"Midi Pyr\u00e9n\u00e9es",
    "sg:tags":[
        "leather",
        "cutting"
    ],
    "wof:name":"T.2.l. Sarl",
    "wof:placetype":"venue"
},
  "geometry": {"coordinates":[1.999625,43.769291],"type":"Point"}
}