{
  "type": "Feature",
  "properties": {
    "addr:full":"27 rue Raymond Poincare; Cernay; 68700 Cernay Alsace 68700",
    "addr:housenumber":"27",
    "addr:postcode":"68700;68700",
    "addr:street":"Rue Raymond Poincare",
    "iso:country":"FR",
    "sg:address":"27 rue Raymond Poincare; Cernay; 68700",
    "sg:city":"Cernay",
    "sg:classifiers":[
        {
            "category":"Banks & Credit Unions",
            "subcategory":"Bank",
            "type":"Services"
        }
    ],
    "sg:phone":"+33 3389754543",
    "sg:postcode":"68700",
    "sg:province":"Alsace",
    "wof:name":"Banque Nationale De Paris",
    "wof:placetype":"venue"
},
  "geometry": {"coordinates":[7.175704,47.80724],"type":"Point"}
}