{
  "type": "Feature",
  "properties": {
    "addr:full":"Rte de Concarneau Tr\u00e9gunc Bretagne 29910",
    "addr:postcode":"29910",
    "addr:street":"Rte De Concarneau Tre\u0301Gunc Bretagne",
    "iso:country":"FR",
    "sg:address":"Rte de Concarneau",
    "sg:city":"Tr\u00e9gunc",
    "sg:orig_category":"Unclassifiable Establishments",
    "sg:phone":"+33 2 98 97 66 79",
    "sg:postcode":"29910",
    "sg:province":"Bretagne",
    "wof:name":"Guy Cotten S.a.",
    "wof:placetype":"venue"
},
  "geometry": {"coordinates":[-3.866129,47.856899],"type":"Point"}
}