{
  "type": "Feature",
  "properties": {
    "addr:full":"21, Rue du Saule Trapu, 91300 Massy Ile de France",
    "addr:housenumber":"21",
    "addr:postcode":"91300",
    "addr:street":"Rue Du Saule Trapu;Ile De France",
    "iso:country":"FR",
    "sg:address":"21, Rue du Saule Trapu, 91300 Massy",
    "sg:orig_category":"Unclassifiable Establishments",
    "sg:phone":"+33 1 60 11 21 20",
    "sg:province":"Ile de France",
    "wof:name":"Brique De Vaugirard S.a.",
    "wof:placetype":"venue"
},
  "geometry": {"coordinates":[2.30347,48.730751],"type":"Point"}
}