{
  "type": "Feature",
  "properties": {
    "addr:full":"B.P. 90154, 35801 Dinard C\u00e9dex^^A\u00e9roport de Dinard, 35800 Dinard Dinard Bretagne 35800",
    "addr:postcode":"35801;35800;35800",
    "iso:country":"FR",
    "sg:address":"B.P. 90154, 35801 Dinard C\u00e9dex^^A\u00e9roport de Dinard, 35800 Dinard",
    "sg:city":"Dinard",
    "sg:orig_category":"Non-Classified Establishments",
    "sg:phone":"+33 2 99 82 72 00",
    "sg:postcode":"35800",
    "sg:province":"Bretagne",
    "wof:name":"A.b.p. S.a. - Aircraft Biostripping And Painting",
    "wof:placetype":"venue"
},
  "geometry": {"coordinates":[-2.136755,48.624207],"type":"Point"}
}