{
  "type": "Feature",
  "properties": {
    "addr:full":"3 Rue De L'Arm\u00e9e Patton 54000 Nancy Lorraine 54000",
    "addr:housenumber":"3",
    "addr:postcode":"54000;54000",
    "addr:street":"Rue De L'Arme \u0301E Patton",
    "iso:country":"FR",
    "sg:address":"3 Rue De L'Arm\u00e9e Patton 54000 Nancy",
    "sg:classifiers":[
        {
            "category":"Travel",
            "subcategory":"Hotels & Motels",
            "type":"Entertainment"
        }
    ],
    "sg:phone":"+33 3 83 40 31 24",
    "sg:postcode":"54000",
    "sg:province":"Lorraine",
    "sg:tags":[
        "hotels",
        "business",
        "restaurant"
    ],
    "wof:name":"Hotel Albert 1er Astoria",
    "wof:placetype":"venue"
},
  "geometry": {"coordinates":[6.16972,48.691696],"type":"Point"}
}