{
  "type": "Feature",
  "properties": {
    "iso:country":"FR",
    "sg:address":"23 Av Guynemer 81600 Gaillac",
    "sg:classifiers":[
        {
            "category":"Food Court",
            "type":"Food & Drink"
        }
    ],
    "sg:phone":"+33 5 63 57 01 40",
    "sg:postcode":"81600",
    "sg:province":"Midi Pyr\u00e9n\u00e9es",
    "sg:tags":[
        "product",
        "related"
    ],
    "wof:name":"Sa Des Alcools Du Tarn",
    "wof:placetype":"venue"
},
  "geometry": {"coordinates":[1.8833,43.894138],"type":"Point"}
}