{
  "type": "Feature",
  "properties": {
    "addr:full":"Zi De La Lombardiere 07100 Annonay Rhone-Alpes 07100",
    "addr:postcode":"07100;07100",
    "addr:street":"Zi De La Lombardiere",
    "iso:country":"FR",
    "sg:address":"Zi De La Lombardiere 07100 Annonay",
    "sg:classifiers":[
        {
            "category":"Building & Trades",
            "subcategory":"Construction",
            "type":"Services"
        }
    ],
    "sg:phone":"+33 4 75 69 29 29",
    "sg:postcode":"07100",
    "sg:province":"Rhone-Alpes",
    "sg:tags":[
        "work",
        "public"
    ],
    "wof:name":"Chabanel Sa",
    "wof:placetype":"venue"
},
  "geometry": {"coordinates":[4.667835,45.239681],"type":"Point"}
}