{
  "type": "Feature",
  "properties": {
    "addr:full":"ZI Gravasses Villefranche de Rouergue Midi Pyr\u00e9n\u00e9es 12200",
    "addr:postcode":"12200",
    "iso:country":"FR",
    "sg:address":"ZI Gravasses",
    "sg:city":"Villefranche de Rouergue",
    "sg:orig_category":"Unclassifiable Establishments",
    "sg:phone":"+33 5 65 65 12 12",
    "sg:postcode":"12200",
    "sg:province":"Midi Pyr\u00e9n\u00e9es",
    "wof:name":"Union Sud Aliment S.a.",
    "wof:placetype":"venue"
},
  "geometry": {"coordinates":[2.03635,44.349468],"type":"Point"}
}