{
  "type": "Feature",
  "properties": {
    "iso:country":"FR",
    "sg:address":"212, Rue de Picardie, 45160 Olivet",
    "sg:city":"Ardon",
    "sg:orig_category":"Unclassifiable Establishments",
    "sg:phone":"+33 2 38 63 53 68",
    "sg:postcode":"45160",
    "sg:province":"Centre",
    "wof:name":"C.v.v.l. S.a.",
    "wof:placetype":"venue"
},
  "geometry": {"coordinates":[1.922233,47.841961],"type":"Point"}
}