{
  "type": "Feature",
  "properties": {
    "addr:full":"La Pazioterie 86600 Coulombiers Poitou-Charentes 86600",
    "addr:postcode":"86600;86600",
    "iso:country":"FR",
    "sg:address":"La Pazioterie 86600 Coulombiers",
    "sg:orig_category":"Non-Classified Establishments",
    "sg:phone":"+33 5 49 60 91 61",
    "sg:postcode":"86600",
    "sg:province":"Poitou-Charentes",
    "wof:name":"A.f.m. - Atlantique Ferraille M\u00e9taux",
    "wof:placetype":"venue"
},
  "geometry": {"coordinates":[0.203585,46.498878],"type":"Point"}
}