{
  "type": "Feature",
  "properties": {
    "iso:country":"FR",
    "sg:address":"49240 Avrill\u00e9",
    "sg:orig_category":"Unclassifiable Establishments",
    "sg:phone":"+33 2 41 21 01 80",
    "sg:province":"Pays de Loire",
    "wof:name":"Chrisola S.a.",
    "wof:placetype":"venue"
},
  "geometry": {"coordinates":[-0.60109,47.502621],"type":"Point"}
}