{
  "type": "Feature",
  "properties": {
    "addr:full":"70 rue Fran\u00e7ois Pochat 74300 Cluses Rhone-Alpes",
    "addr:housenumber":"70",
    "addr:postcode":"74300",
    "addr:street":"Rue Franc\u0327Ois Pochat",
    "iso:country":"FR",
    "sg:address":"70 rue Fran\u00e7ois Pochat 74300 Cluses",
    "sg:classifiers":[
        {
            "category":"Building & Trades",
            "subcategory":"Construction",
            "type":"Services"
        }
    ],
    "sg:phone":"+33 4 50 89 62 18",
    "sg:province":"Rhone-Alpes",
    "sg:tags":[
        "turning",
        "vertical"
    ],
    "wof:name":"Deco-decoup Sa",
    "wof:placetype":"venue"
},
  "geometry": {"coordinates":[6.599595,46.047215],"type":"Point"}
}