{
  "type": "Feature",
  "properties": {
    "iso:country":"FR",
    "sg:address":"A Frimont Ouest Z Commerciale 33190 LOUPIAC DE LA REOLE",
    "sg:city":"La R\u00e9ole",
    "sg:classifiers":[
        {
            "category":"Banks & Credit Unions",
            "subcategory":"Investment Brokerage",
            "type":"Services"
        }
    ],
    "sg:phone":"+33 5 56 61 13 66",
    "sg:postcode":"33190",
    "sg:province":"Aquitaine",
    "sg:tags":[
        "processing",
        "data",
        "system"
    ],
    "wof:name":"Buromat Sarl",
    "wof:placetype":"venue"
},
  "geometry": {"coordinates":[-0.012771,44.516201],"type":"Point"}
}