{
  "type": "Feature",
  "properties": {
    "addr:full":"Sarrazac 24420 Mayac Mayac Aquitaine 24420",
    "addr:postcode":"24420;24420",
    "iso:country":"FR",
    "sg:address":"Sarrazac 24420 Mayac",
    "sg:city":"Mayac",
    "sg:orig_category":"Unclassifiable Establishments",
    "sg:phone":"+33 5 53 05 91 15",
    "sg:postcode":"24420",
    "sg:province":"Aquitaine",
    "wof:name":"Laboratoire Euro Natura S.a.r.l.",
    "wof:placetype":"venue"
},
  "geometry": {"coordinates":[0.95229,45.285133],"type":"Point"}
}