{
  "type": "Feature",
  "properties": {
    "addr:full":"chemin des Loges 14100 Beuvillers Beuvillers Basse Normandie 14100",
    "addr:postcode":"14100;14100",
    "addr:street":"Chemin Des Loges",
    "iso:country":"FR",
    "sg:address":"chemin des Loges 14100 Beuvillers",
    "sg:city":"Beuvillers",
    "sg:classifiers":[
        {
            "category":"Structure",
            "subcategory":"Restrooms",
            "type":"Public Place"
        }
    ],
    "sg:phone":"+33 2 31 31 35 17",
    "sg:postcode":"14100",
    "sg:province":"Basse Normandie",
    "sg:tags":[
        "floor-mounted",
        "system",
        "conveyor"
    ],
    "wof:name":"Itp S.a.r.l.",
    "wof:placetype":"venue"
},
  "geometry": {"coordinates":[0.246425,49.130661],"type":"Point"}
}