{
  "type": "Feature",
  "properties": {
    "addr:full":"R Abb\u00e9 Jerzy Popieluszko Parc D'Activit\u00e9 La Croisette 62300 Lens Nord Pas-de-Calais 62300",
    "addr:postcode":"62300;62300",
    "addr:street":"R Abbe\u0301 Jerzy;Parc;\u0301 La Croisette",
    "iso:country":"FR",
    "sg:address":"R Abb\u00e9 Jerzy Popieluszko Parc D'Activit\u00e9 La Croisette 62300 Lens",
    "sg:classifiers":[
        {
            "category":"Food & Beverages",
            "subcategory":"Fruits & Vegetables",
            "type":"Retail Goods"
        }
    ],
    "sg:phone":"+33 3 21 13 03 80",
    "sg:postcode":"62300",
    "sg:province":"Nord Pas-de-Calais",
    "sg:tags":[
        "preserve",
        "cooked",
        "product",
        "meat",
        "related"
    ],
    "wof:name":"Prodirest",
    "wof:placetype":"venue"
},
  "geometry": {"coordinates":[2.821324,50.451958],"type":"Point"}
}