{
  "type": "Feature",
  "properties": {
    "addr:full":"5, Rue Dreyfus Dupont - ZI des Deux Fontaines, 57000 Metz Lorraine",
    "addr:housenumber":"5",
    "addr:postcode":"57000",
    "addr:street":"Rue Dreyfus;Zi Des Deux Fontaines",
    "iso:country":"FR",
    "sg:address":"5, Rue Dreyfus Dupont - ZI des Deux Fontaines, 57000 Metz",
    "sg:orig_category":"Unclassifiable Establishments",
    "sg:phone":"+33 3 87 31 42 03",
    "sg:province":"Lorraine",
    "wof:name":"Ecritech S.a.r.l.",
    "wof:placetype":"venue"
},
  "geometry": {"coordinates":[6.183995,49.07645],"type":"Point"}
}