{
  "type": "Feature",
  "properties": {
    "addr:full":"Z.I. Houdan Ile de France 78550",
    "addr:housenumber":"z.i.",
    "addr:postcode":"78550",
    "iso:country":"FR",
    "sg:address":"Z.I.",
    "sg:city":"Houdan",
    "sg:orig_category":"Unclassifiable Establishments",
    "sg:phone":"+33 1 30 88 16 50",
    "sg:postcode":"78550",
    "sg:province":"Ile de France",
    "wof:name":"Etablissement Harang Guy S.a.",
    "wof:placetype":"venue"
},
  "geometry": {"coordinates":[1.60191,48.788956],"type":"Point"}
}