{
  "type": "Feature",
  "properties": {
    "iso:country":"FR",
    "sg:address":"ZI Nord",
    "sg:city":"Beynost",
    "sg:orig_category":"Unclassifiable Establishments",
    "sg:phone":"+33 4 78 55 07 63",
    "sg:postcode":"01700",
    "sg:province":"Rhone-Alpes",
    "wof:name":"Sof\u00e9ral Et Compagnie S.a.r.l.",
    "wof:placetype":"venue"
},
  "geometry": {"coordinates":[5.002065,45.840061],"type":"Point"}
}