{
  "type": "Feature",
  "properties": {
    "addr:full":"11, Rue de la Lionne, 45000 Orl\u00e9ans Orl\u00e9ans Centre 45000",
    "addr:housenumber":"11",
    "addr:postcode":"45000;45000",
    "addr:street":"Rue De La Lionne",
    "iso:country":"FR",
    "sg:address":"11, Rue de la Lionne, 45000 Orl\u00e9ans",
    "sg:city":"Orl\u00e9ans",
    "sg:orig_category":"Non-Classified Establishments",
    "sg:phone":"+33 2 38 77 06 02",
    "sg:postcode":"45000",
    "sg:province":"Centre",
    "wof:name":"3 D Plast S.a.",
    "wof:placetype":"venue"
},
  "geometry": {"coordinates":[1.901862,47.903999],"type":"Point"}
}