{
  "type": "Feature",
  "properties": {
    "iso:country":"FR",
    "sg:address":"Za De La Caille 49340 Nuaill\u00e9",
    "sg:classifiers":[
        {
            "category":"Professional",
            "type":"Services"
        }
    ],
    "sg:phone":"+33 2 41 64 10 79",
    "sg:province":"Pays de Loire",
    "sg:tags":[
        "transport",
        "road"
    ],
    "wof:name":"Transports De Mauges Sarl",
    "wof:placetype":"venue"
},
  "geometry": {"coordinates":[-0.795589,47.095066],"type":"Point"}
}