{
  "type": "Feature",
  "properties": {
    "iso:country":"FR",
    "sg:address":"52 Av Du Capitaine Glarner 93400 St Ouen",
    "sg:classifiers":[
        {
            "category":"Shopping",
            "subcategory":"Hobbies, Toys, & Games",
            "type":"Retail Goods"
        }
    ],
    "sg:phone":"+33 1 49 21 13 13",
    "sg:postcode":"93400",
    "sg:province":"Ile de France",
    "sg:tags":[
        "product",
        "miscellaneous",
        "entertainment"
    ],
    "wof:name":"Bally France Sa",
    "wof:placetype":"venue"
},
  "geometry": {"coordinates":[2.329369,48.90337],"type":"Point"}
}