{
  "type": "Feature",
  "properties": {
    "addr:full":"2 Rue De La Perriere 25130 Villers Le Lac Franche Comt\u00e9 25130",
    "addr:housenumber":"2",
    "addr:postcode":"25130;25130",
    "addr:street":"Rue De La Perriere;Villers Le;Franche Comte\u0301",
    "iso:country":"FR",
    "sg:address":"2 Rue De La Perriere 25130 Villers Le Lac",
    "sg:classifiers":[
        {
            "category":"Manufacturing",
            "subcategory":"Metals",
            "type":"Manufacturing & Wholesale Goods"
        }
    ],
    "sg:phone":"+33 3 81 68 13 51",
    "sg:postcode":"25130",
    "sg:province":"Franche Comt\u00e9",
    "sg:tags":[
        "metallurgy",
        "metalworking",
        "processing"
    ],
    "wof:name":"At3 Polissage",
    "wof:placetype":"venue"
},
  "geometry": {"coordinates":[6.670484,47.061543],"type":"Point"}
}