{
  "type": "Feature",
  "properties": {
    "addr:full":"850, Rte de Saint Julien, 69400 Arnas Rhone-Alpes 69400",
    "addr:housenumber":"850",
    "addr:postcode":"69400;69400",
    "addr:street":"Rte De Saint Julien",
    "iso:country":"FR",
    "sg:address":"850, Rte de Saint Julien, 69400 Arnas",
    "sg:orig_category":"Non-Classified Establishments",
    "sg:phone":"+33 4 74 68 37 53",
    "sg:postcode":"69400",
    "sg:province":"Rhone-Alpes",
    "wof:name":"Bibet Et Fils S.a.r.l.",
    "wof:placetype":"venue"
},
  "geometry": {"coordinates":[4.699017,46.013256],"type":"Point"}
}