{
  "type": "Feature",
  "properties": {
    "addr:full":"497 R Amp\u00e8re 69400 Villefranche-Sur-Sa\u00f4ne Rhone-Alpes 69400",
    "addr:housenumber":"497",
    "addr:postcode":"69400;69400",
    "addr:street":"R Ampe\u0300Re",
    "iso:country":"FR",
    "sg:address":"497 R Amp\u00e8re 69400 Villefranche-Sur-Sa\u00f4ne",
    "sg:classifiers":[
        {
            "category":"Manufacturing",
            "subcategory":"Tools & Machinery",
            "type":"Manufacturing & Wholesale Goods"
        }
    ],
    "sg:phone":"+33 4 74 65 06 04",
    "sg:postcode":"69400",
    "sg:province":"Rhone-Alpes",
    "sg:tags":[
        "metallurgy",
        "metalworking"
    ],
    "wof:name":"Mailland (etablissements) Sa",
    "wof:placetype":"venue"
},
  "geometry": {"coordinates":[4.727698,45.987019],"type":"Point"}
}