{
  "type": "Feature",
  "properties": {
    "iso:country":"FR",
    "sg:address":"403 E, Rte de la Gare, 74200 Allinges",
    "sg:orig_category":"Unclassifiable Establishments",
    "sg:phone":"+33 4 50 17 08 00",
    "sg:postcode":"74200",
    "sg:province":"Rhone-Alpes",
    "wof:name":"Bel Et Morand S.a.",
    "wof:placetype":"venue"
},
  "geometry": {"coordinates":[6.61462,46.305523],"type":"Point"}
}