{
  "type": "Feature",
  "properties": {
    "iso:country":"FR",
    "sg:address":"avenue des Repes 70000 Vesoul",
    "sg:classifiers":[
        {
            "category":"Military Area",
            "subcategory":"Air Force Base",
            "type":"Public Place"
        }
    ],
    "sg:phone":"+33 3 84 75 86 66",
    "sg:postcode":"70000",
    "sg:province":"Franche Comt\u00e9",
    "sg:tags":[
        "water",
        "ceiling",
        "cooling"
    ],
    "wof:name":"Durlumen Sa",
    "wof:placetype":"venue"
},
  "geometry": {"coordinates":[6.16721,47.639126],"type":"Point"}
}