{
  "type": "Feature",
  "properties": {
    "addr:full":"Le Vieux Chazal Des Maures 26740 LA COUCOURDE Rhone-Alpes 26740",
    "addr:housenumber":"26740",
    "addr:postcode":"26740",
    "addr:street":"Coucourde Rhone-Alpes",
    "iso:country":"FR",
    "sg:address":"Le Vieux Chazal Des Maures 26740 LA COUCOURDE",
    "sg:classifiers":[
        {
            "category":"Autos & Motor Vehicles",
            "subcategory":"Auto Supplies",
            "type":"Retail Goods"
        }
    ],
    "sg:phone":"+33 4 75 53 07 08",
    "sg:postcode":"26740",
    "sg:province":"Rhone-Alpes",
    "sg:tags":[
        "automobile",
        "accessory"
    ],
    "wof:name":"Recuperation Vente Pieces Occasion Sarl",
    "wof:placetype":"venue"
},
  "geometry": {"coordinates":[4.80878,44.554249],"type":"Point"}
}