{
  "type": "Feature",
  "properties": {
    "addr:full":"96 Ch Sous Le Fort 69552 Feyzin Lorraine",
    "addr:housenumber":"96",
    "addr:postcode":"69552",
    "addr:street":"Ch Sous Le Fort",
    "iso:country":"FR",
    "sg:address":"96 Ch Sous Le Fort 69552 Feyzin",
    "sg:classifiers":[
        {
            "category":"Professional",
            "subcategory":"Business Services",
            "type":"Services"
        }
    ],
    "sg:phone":"+33 4 78 70 32 84",
    "sg:province":"Lorraine",
    "sg:tags":[
        "training",
        "advice"
    ],
    "wof:name":"College Frederic Mistral",
    "wof:placetype":"venue"
},
  "geometry": {"coordinates":[4.85674,45.669941],"type":"Point"}
}