{
  "type": "Feature",
  "properties": {
    "iso:country":"FR",
    "sg:address":"Rue Du Panehem 62830 Tingry",
    "sg:classifiers":[
        {
            "category":"Banks & Credit Unions",
            "subcategory":"Investment Brokerage",
            "type":"Services"
        }
    ],
    "sg:phone":"+33 3 21 33 54 59",
    "sg:province":"Nord Pas-de-Calais",
    "sg:tags":[
        "-",
        "transport",
        "related"
    ],
    "wof:name":"Creteur Rousseau Lucienne",
    "wof:placetype":"venue"
},
  "geometry": {"coordinates":[1.738572,50.623043],"type":"Point"}
}