{
  "type": "Feature",
  "properties": {
    "addr:full":"38 rue de Vannes 35600 Redon Redon Bretagne 35600",
    "addr:housenumber":"38",
    "addr:postcode":"35600;35600",
    "addr:street":"Rue De Vannes;Redon",
    "iso:country":"FR",
    "sg:address":"38 rue de Vannes 35600 Redon",
    "sg:city":"Redon",
    "sg:classifiers":[
        {
            "category":"Banks & Credit Unions",
            "subcategory":"Investment Brokerage",
            "type":"Services"
        }
    ],
    "sg:phone":"+33 2 99 71 73 73",
    "sg:postcode":"35600",
    "sg:province":"Bretagne",
    "sg:tags":[
        "casting"
    ],
    "wof:name":"A.f.c. Redon S.a",
    "wof:placetype":"venue"
},
  "geometry": {"coordinates":[-2.090553,47.646107],"type":"Point"}
}