{
  "type": "Feature",
  "properties": {
    "addr:full":"70 Rue De Rechevres 28000 Chartres Chartres Centre 28000",
    "addr:housenumber":"70",
    "addr:postcode":"28000;28000",
    "addr:street":"Rue De Rechevres",
    "iso:country":"FR",
    "sg:address":"70 Rue De Rechevres 28000 Chartres",
    "sg:city":"Chartres",
    "sg:classifiers":[
        {
            "category":"Professional",
            "subcategory":"Engineering",
            "type":"Services"
        }
    ],
    "sg:phone":"+33 2 37 21 27 07",
    "sg:postcode":"28000",
    "sg:province":"Centre",
    "sg:tags":[
        "machine",
        "-",
        "mechanical"
    ],
    "wof:name":"Elyo Centre Ouest",
    "wof:placetype":"venue"
},
  "geometry": {"coordinates":[1.477894,48.453365],"type":"Point"}
}