{
  "type": "Feature",
  "properties": {
    "addr:full":"Rue Le Tintoret 80000 Amiens Picardie",
    "addr:postcode":"80000",
    "addr:street":"Rue Le Tintoret",
    "iso:country":"FR",
    "sg:address":"Rue Le Tintoret 80000 Amiens",
    "sg:classifiers":[
        {
            "category":"Professional",
            "type":"Services"
        }
    ],
    "sg:phone":"+33 3 22 66 34 80",
    "sg:province":"Picardie",
    "sg:tags":[
        "transport",
        "road"
    ],
    "wof:name":"Picardie Express Sa",
    "wof:placetype":"venue"
},
  "geometry": {"coordinates":[2.299688,49.925205],"type":"Point"}
}