{
  "type": "Feature",
  "properties": {
    "addr:full":"3, Rue David, 19100 Brive la Gaillarde Limousin",
    "addr:housenumber":"3",
    "addr:postcode":"19100",
    "addr:street":"Rue David",
    "iso:country":"FR",
    "sg:address":"3, Rue David, 19100 Brive la Gaillarde",
    "sg:orig_category":"Unclassifiable Establishments",
    "sg:phone":"+33 5 55 17 10 10",
    "sg:province":"Limousin",
    "wof:name":"Imprimerie J.p. Dales S.a.r.l.",
    "wof:placetype":"venue"
},
  "geometry": {"coordinates":[1.531679,45.163925],"type":"Point"}
}