{
  "type": "Feature",
  "properties": {
    "addr:full":"Rue du Moulin Saint Martin sur le Pr\u00e9 Champagne 51000",
    "addr:postcode":"51000",
    "addr:street":"Rue Du Moulin Saint;Sur Le Pre\u0301 Champagne",
    "iso:country":"FR",
    "sg:address":"Rue du Moulin",
    "sg:city":"Saint Martin sur le Pr\u00e9",
    "sg:orig_category":"Unclassifiable Establishments",
    "sg:phone":"+33 3 26 65 88 49",
    "sg:postcode":"51000",
    "sg:province":"Champagne",
    "wof:name":"T.c.c. S.a. - Tuyauterie Chaudronnerie Champenoise",
    "wof:placetype":"venue"
},
  "geometry": {"coordinates":[4.37998,48.965542],"type":"Point"}
}