{
  "type": "Feature",
  "properties": {
    "addr:full":"29, Rue Ledru Rollin, 92150 Suresnes Ile de France",
    "addr:housenumber":"29",
    "addr:postcode":"92150;ile",
    "addr:street":"Rue Ledru Rollin",
    "iso:country":"FR",
    "sg:address":"29, Rue Ledru Rollin, 92150 Suresnes",
    "sg:orig_category":"Unclassifiable Establishments",
    "sg:phone":"+33 1 41 44 33 33",
    "sg:province":"Ile de France",
    "wof:name":"C.d.e. S.a. - Componente Devices Electronics",
    "wof:placetype":"venue"
},
  "geometry": {"coordinates":[2.230605,48.871864],"type":"Point"}
}