{
  "type": "Feature",
  "properties": {
    "addr:full":"33 Boulevard De Strassbourg 75010 Paris Ile de France 75010",
    "addr:housenumber":"33",
    "addr:postcode":"75010;75010",
    "addr:street":"Boulevard De Strassbourg",
    "iso:country":"FR",
    "sg:address":"33 Boulevard De Strassbourg 75010 Paris",
    "sg:classifiers":[
        {
            "category":"Shopping",
            "subcategory":"Clothing, Apparel, & Fashions",
            "type":"Retail Goods"
        }
    ],
    "sg:phone":"+33 1 48 24 46 43",
    "sg:postcode":"75010",
    "sg:province":"Ile de France",
    "sg:tags":[
        "textile",
        "clothing",
        "clothes"
    ],
    "wof:name":"Creation Morgan",
    "wof:placetype":"venue"
},
  "geometry": {"coordinates":[2.35525,48.871429],"type":"Point"}
}