{
  "type": "Feature",
  "properties": {
    "iso:country":"FR",
    "sg:address":"50, Rue Th\u00e9nard, 89100 Sens",
    "sg:city":"Sens",
    "sg:orig_category":"Non-Classified Establishments",
    "sg:phone":"+33 3 86 65 16 54",
    "sg:postcode":"89100",
    "sg:province":"Bourgogne",
    "wof:name":"Technifroid S.a.",
    "wof:placetype":"venue"
},
  "geometry": {"coordinates":[3.286462,48.198593],"type":"Point"}
}