{
  "type": "Feature",
  "properties": {
    "addr:full":"4 Rue Salomon De Caus 75003 Paris Ile de France 75003",
    "addr:housenumber":"4",
    "addr:postcode":"75003;75003",
    "addr:street":"Rue Salomon De Caus",
    "iso:country":"FR",
    "sg:address":"4 Rue Salomon De Caus 75003 Paris",
    "sg:classifiers":[
        {
            "category":"Travel",
            "subcategory":"Hotels & Motels",
            "type":"Entertainment"
        }
    ],
    "sg:phone":"+33 1 42 72 08 15",
    "sg:postcode":"75003",
    "sg:province":"Ile de France",
    "sg:tags":[
        "hotels",
        "business",
        "restaurant"
    ],
    "wof:name":"Little Palace Sa",
    "wof:placetype":"venue"
},
  "geometry": {"coordinates":[2.354345,48.867439],"type":"Point"}
}