{
  "type": "Feature",
  "properties": {
    "addr:full":"8 Rue Du Portail De Ville 38110 La Tour Du Pin Rhone-Alpes 38110",
    "addr:housenumber":"8",
    "addr:postcode":"38110;38110",
    "addr:street":"Rue Du Portail De Ville",
    "iso:country":"FR",
    "sg:address":"8 Rue Du Portail De Ville 38110 La Tour Du Pin",
    "sg:classifiers":[
        {
            "category":"Shopping",
            "subcategory":"Hobbies, Toys, & Games",
            "type":"Retail Goods"
        }
    ],
    "sg:phone":"+33 4 74 83 20 75",
    "sg:postcode":"38110",
    "sg:province":"Rhone-Alpes",
    "sg:tags":[
        "product",
        "miscellaneous",
        "entertainment"
    ],
    "wof:name":"Le Hussard",
    "wof:placetype":"venue"
},
  "geometry": {"coordinates":[5.449592,45.563358],"type":"Point"}
}