{
  "type": "Feature",
  "properties": {
    "addr:full":"36/40, Bd Robert Schuman, 93190 Livry Gargan Ile de France",
    "addr:housenumber":"36 / 40",
    "addr:postcode":"93190",
    "addr:street":"Bd Robert Schuman",
    "iso:country":"FR",
    "sg:address":"36/40, Bd Robert Schuman, 93190 Livry Gargan",
    "sg:orig_category":"Unclassifiable Establishments",
    "sg:phone":"+33 1 49 36 26 70",
    "sg:province":"Ile de France",
    "wof:name":"R.p.n. S.a.s. - Roto Presse Numeris",
    "wof:placetype":"venue"
},
  "geometry": {"coordinates":[2.548465,48.927601],"type":"Point"}
}