{
  "type": "Feature",
  "properties": {
    "iso:country":"FR",
    "sg:address":"40, Rue Abb\u00e9 Bellemer, 33390 Blaye",
    "sg:city":"Blaye",
    "sg:orig_category":"Non-Classified Establishments",
    "sg:phone":"+33 5 57 42 11 61",
    "sg:postcode":"33390",
    "sg:province":"Aquitaine",
    "wof:name":"Transports H\u00e9brard S.a.r.l.",
    "wof:placetype":"venue"
},
  "geometry": {"coordinates":[-0.662969,45.124969],"type":"Point"}
}