{
  "type": "Feature",
  "properties": {
    "addr:full":"667, Rue Aristide Berg\u00e8s, 38330 Montbonnot Saint Martin Rhone-Alpes 38330",
    "addr:housenumber":"667",
    "addr:postcode":"38330;38330",
    "addr:street":"Rue Aristide Berge\u0300S;Rhone-Alpes",
    "iso:country":"FR",
    "sg:address":"667, Rue Aristide Berg\u00e8s, 38330 Montbonnot Saint Martin",
    "sg:orig_category":"Non-Classified Establishments",
    "sg:phone":"+33 4 76 52 55 77",
    "sg:postcode":"38330",
    "sg:province":"Rhone-Alpes",
    "wof:name":"Fugro France S.a.",
    "wof:placetype":"venue"
},
  "geometry": {"coordinates":[5.817105,45.221626],"type":"Point"}
}