{
  "type": "Feature",
  "properties": {
    "addr:full":"1 R Thomas Edison 94028 Creteil Cedex \u00cele-de-France",
    "addr:housenumber":"1",
    "addr:postcode":"94028 creteil cedex",
    "addr:street":"R Thomas Edison",
    "iso:country":"FR",
    "sg:address":"1 R Thomas Edison 94028 Creteil Cedex",
    "sg:classifiers":[
        {
            "category":"Wholesale",
            "subcategory":"Machinery & Supplies",
            "type":"Manufacturing & Wholesale Goods"
        }
    ],
    "sg:phone":"+33 1 48 98 70 00",
    "sg:province":"\u00cele-de-France",
    "sg:tags":[
        "equipment",
        "optical",
        "precision",
        "instrument"
    ],
    "wof:name":"Essilor International Sarl",
    "wof:placetype":"venue"
},
  "geometry": {"coordinates":[2.447722,48.797684],"type":"Point"}
}