{
  "type": "Feature",
  "properties": {
    "iso:country":"FR",
    "sg:address":"54 Rue Du General De Gaulle 94510 La Queue En Brie",
    "sg:classifiers":[
        {
            "category":"Manufacturing",
            "subcategory":"Wood Products",
            "type":"Manufacturing & Wholesale Goods"
        }
    ],
    "sg:phone":"+33 1 45 76 30 01",
    "sg:province":"Ile de France",
    "sg:tags":[
        "furniture"
    ],
    "wof:name":"E Fiel Et Compagnie",
    "wof:placetype":"venue"
},
  "geometry": {"coordinates":[2.579598,48.779701],"type":"Point"}
}