{
  "type": "Feature",
  "properties": {
    "iso:country":"FR",
    "sg:address":"Chemin Mandin",
    "sg:city":"Camblanes et Meynac",
    "sg:orig_category":"Non-Classified Establishments",
    "sg:phone":"+33 5 56 20 60 57",
    "sg:postcode":"33360",
    "sg:province":"Aquitaine",
    "wof:name":"If Expansion S.a.r.l.",
    "wof:placetype":"venue"
},
  "geometry": {"coordinates":[-0.462709,44.770538],"type":"Point"}
}