{
  "type": "Feature",
  "properties": {
    "addr:full":"Rte de Maz\u00e9 - ZI Saint Mathurin sur Loire Pays de Loire 49250",
    "addr:postcode":"49250",
    "addr:street":"Rte De Maze\u0301 Zi Saint Mathurin Sur Loire",
    "iso:country":"FR",
    "sg:address":"Rte de Maz\u00e9 - ZI",
    "sg:city":"Saint Mathurin sur Loire",
    "sg:orig_category":"Unclassifiable Establishments",
    "sg:phone":"+33 2 41 79 79 19",
    "sg:postcode":"49250",
    "sg:province":"Pays de Loire",
    "wof:name":"S.t.p.v.l. S.n.c. - Soci\u00e9t\u00e9 Des Travaux Publics Val De Loire",
    "wof:placetype":"venue"
},
  "geometry": {"coordinates":[-0.341294,47.385021],"type":"Point"}
}