{
  "type": "Feature",
  "properties": {
    "addr:full":"3 cours Vauban; Blaye Champagne",
    "addr:housenumber":"3",
    "addr:street":"Cours Vauban",
    "iso:country":"FR",
    "sg:address":"3 cours Vauban; Blaye",
    "sg:classifiers":[
        {
            "category":"Banks & Credit Unions",
            "subcategory":"Bank",
            "type":"Services"
        }
    ],
    "sg:phone":"+33 3357429000",
    "sg:province":"Champagne",
    "wof:name":"Cr\u00e9dit Agricole",
    "wof:placetype":"venue"
},
  "geometry": {"coordinates":[-0.663159,45.127171],"type":"Point"}
}