{
  "type": "Feature",
  "properties": {
    "iso:country":"FR",
    "sg:address":"Rue Du Nouveau Bele 44470 Carquefou",
    "sg:classifiers":[
        {
            "category":"Professional",
            "type":"Services"
        }
    ],
    "sg:phone":"+33 2 40 30 36 21",
    "sg:province":"Pays de Loire",
    "sg:tags":[
        "transport",
        "road"
    ],
    "wof:name":"Logeais Et Fils Sa",
    "wof:placetype":"venue"
},
  "geometry": {"coordinates":[-1.494459,47.276211],"type":"Point"}
}