{
  "type": "Feature",
  "properties": {
    "addr:full":"108, Av. Louis Roche, 92230 Gennevilliers Ile de France",
    "addr:postcode":"92230;ile",
    "addr:street":"108 Av. Louis Roche",
    "iso:country":"FR",
    "sg:address":"108, Av. Louis Roche, 92230 Gennevilliers",
    "sg:orig_category":"Unclassifiable Establishments",
    "sg:phone":"+33 1 41 47 74 10",
    "sg:province":"Ile de France",
    "wof:name":"Rexair S.a.",
    "wof:placetype":"venue"
},
  "geometry": {"coordinates":[2.315238,48.926701],"type":"Point"}
}