{
  "type": "Feature",
  "properties": {
    "addr:full":"77, Rue du Faubourg Saint Jacques, 75014 Paris Ile de France",
    "addr:housenumber":"77",
    "addr:postcode":"75014",
    "addr:street":"Rue Du Faubourg Saint Jacques",
    "iso:country":"FR",
    "sg:address":"77, Rue du Faubourg Saint Jacques, 75014 Paris",
    "sg:orig_category":"Unclassifiable Establishments",
    "sg:phone":"+33 1 47 07 28 00",
    "sg:province":"Ile de France",
    "wof:name":"Guitar Raymond",
    "wof:placetype":"venue"
},
  "geometry": {"coordinates":[2.336843,48.834198],"type":"Point"}
}