{
  "type": "Feature",
  "properties": {
    "addr:full":"Zi Chem Du Fl\u00e9chet 49240 Avrill\u00e9 Pays de Loire 49240",
    "addr:postcode":"49240;49240",
    "iso:country":"FR",
    "sg:address":"Zi Chem Du Fl\u00e9chet 49240 Avrill\u00e9",
    "sg:classifiers":[
        {
            "category":"Bakery",
            "type":"Food & Drink"
        }
    ],
    "sg:phone":"+33 2 41 42 45 36",
    "sg:postcode":"49240",
    "sg:province":"Pays de Loire",
    "sg:tags":[
        "cake",
        "product",
        "related",
        "bread"
    ],
    "wof:name":"Foucteau Sa",
    "wof:placetype":"venue"
},
  "geometry": {"coordinates":[-0.587263,47.504822],"type":"Point"}
}