{
  "type": "Feature",
  "properties": {
    "iso:country":"FR",
    "sg:address":"Av. Auguste Marius Peyre",
    "sg:city":"Port de Bouc",
    "sg:orig_category":"Unclassifiable Establishments",
    "sg:phone":"+33 4 42 40 72 40",
    "sg:postcode":"13110",
    "sg:province":"Centre",
    "wof:name":"Trackair Airport Systems S.a.r.l.",
    "wof:placetype":"venue"
},
  "geometry": {"coordinates":[4.981783,43.423779],"type":"Point"}
}