{
  "type": "Feature",
  "properties": {
    "iso:country":"FR",
    "sg:address":"11, Rue du G\u00e9n\u00e9ral Patonne, 57330 Hettange Grande",
    "sg:orig_category":"Unclassifiable Establishments",
    "sg:phone":"+33 3 82 53 05 49",
    "sg:province":"Lorraine",
    "wof:name":"Dialsoft S.a.r.l.",
    "wof:placetype":"venue"
},
  "geometry": {"coordinates":[6.155788,49.405334],"type":"Point"}
}