{
  "type": "Feature",
  "properties": {
    "iso:country":"FR",
    "sg:address":"19, Rue du Moulin, 92800 Puteaux",
    "sg:orig_category":"Unclassifiable Establishments",
    "sg:phone":"+33 1 47 75 37 41",
    "sg:province":"Ile de France",
    "wof:name":"A.r.p.e.m. S.a.r.l.",
    "wof:placetype":"venue"
},
  "geometry": {"coordinates":[2.229857,48.885422],"type":"Point"}
}