{
  "type": "Feature",
  "properties": {
    "addr:full":"11 Avenue Louis Renault 44800 St Herblain Pays de Loire",
    "addr:housenumber":"11",
    "addr:postcode":"44800",
    "addr:street":"Avenue Louis Renault;Herblain",
    "iso:country":"FR",
    "sg:address":"11 Avenue Louis Renault 44800 St Herblain",
    "sg:classifiers":[
        {
            "category":"Professional",
            "subcategory":"Printing & Photocopies",
            "type":"Services"
        }
    ],
    "sg:phone":"+33 2 40 63 30 24",
    "sg:province":"Pays de Loire",
    "sg:tags":[
        "publishing"
    ],
    "wof:name":"Serpo",
    "wof:placetype":"venue"
},
  "geometry": {"coordinates":[-1.645614,47.25687],"type":"Point"}
}