{
  "type": "Feature",
  "properties": {
    "iso:country":"FR",
    "sg:address":"Route de Vrignemeuse",
    "sg:city":"Vivier au Court",
    "sg:orig_category":"Non-Classified Establishments",
    "sg:phone":"+33 3 24 52 38 70",
    "sg:postcode":"08440",
    "sg:province":"Champagne",
    "wof:name":"Aub'net S.a.",
    "wof:placetype":"venue"
},
  "geometry": {"coordinates":[4.81287,49.741402],"type":"Point"}
}