{
  "type": "Feature",
  "properties": {
    "addr:full":"41 Avenue Reibaud Antibes Bretagne 06600",
    "addr:housenumber":"41",
    "addr:postcode":"06600",
    "addr:street":"Avenue Reibaud Antibes",
    "iso:country":"FR",
    "sg:address":"41 Avenue Reibaud",
    "sg:city":"Antibes",
    "sg:classifiers":[
        {
            "category":"Banks & Credit Unions",
            "subcategory":"Financial Services",
            "type":"Services"
        }
    ],
    "sg:phone":"+33 4 93 33 01 01",
    "sg:postcode":"06600",
    "sg:province":"Bretagne",
    "sg:tags":[
        "banking",
        "finance",
        "insurance"
    ],
    "wof:name":"Pierrisnard Et Associe Sarl",
    "wof:placetype":"venue"
},
  "geometry": {"coordinates":[7.11504,43.58424],"type":"Point"}
}