{
  "type": "Feature",
  "properties": {
    "addr:full":"Avenue Du Campon Le Cannet 2000 Bretelle Au Le Cannet Provence-Alpes-C\u00f4te d'Azur 06110",
    "addr:postcode":"2000;06110",
    "addr:street":"Avenue Du Campon;Cannet;Au Le Cannet",
    "iso:country":"FR",
    "sg:address":"Avenue Du Campon Le Cannet 2000 Bretelle Au",
    "sg:city":"Le Cannet",
    "sg:classifiers":[
        {
            "category":"Banks & Credit Unions",
            "subcategory":"Financial Services",
            "type":"Services"
        }
    ],
    "sg:phone":"+33 4 93 69 96 25",
    "sg:postcode":"06110",
    "sg:province":"Provence-Alpes-C\u00f4te d'Azur",
    "sg:tags":[
        "banking",
        "finance",
        "insurance"
    ],
    "wof:name":"Societe D'arbitrage Et D'expertise Technique Saretec (saretec) Saretec",
    "wof:placetype":"venue"
},
  "geometry": {"coordinates":[7.00241,43.570782],"type":"Point"}
}