{
  "type": "Feature",
  "properties": {
    "addr:full":"B.P. 9 Percy Basse Normandie 50410",
    "addr:housenumber":"9",
    "addr:postcode":"50410",
    "addr:street":"B.P.",
    "iso:country":"FR",
    "sg:address":"B.P. 9",
    "sg:city":"Percy",
    "sg:orig_category":"Non-Classified Establishments",
    "sg:phone":"+33 2 33 61 24 88",
    "sg:postcode":"50410",
    "sg:province":"Basse Normandie",
    "wof:name":"Katuor Cr\u00e9ation S.a.r.l.",
    "wof:placetype":"venue"
},
  "geometry": {"coordinates":[-1.189879,48.916309],"type":"Point"}
}