{
  "type": "Feature",
  "properties": {
    "iso:country":"FR",
    "sg:address":"Impasse de Lande Bourne",
    "sg:city":"Cou\u00ebron",
    "sg:orig_category":"Unclassifiable Establishments",
    "sg:phone":"+33 2 40 16 73 20",
    "sg:postcode":"44220",
    "sg:province":"Pays de Loire",
    "wof:name":"K.s.b. S.a.",
    "wof:placetype":"venue"
},
  "geometry": {"coordinates":[-1.663914,47.240665],"type":"Point"}
}