{
  "type": "Feature",
  "properties": {
    "addr:full":"Rue Jean Perrin - ZA des Courri\u00e8res Isle Limousin 87170",
    "addr:postcode":"87170",
    "addr:street":"Rue Jean Perrin Za Des Courrie\u0300Res Isle Limousin",
    "iso:country":"FR",
    "sg:address":"Rue Jean Perrin - ZA des Courri\u00e8res",
    "sg:city":"Isle",
    "sg:orig_category":"Unclassifiable Establishments",
    "sg:phone":"+33 5 55 05 20 33",
    "sg:postcode":"87170",
    "sg:province":"Limousin",
    "wof:name":"Etablissements Vromant S.a.",
    "wof:placetype":"venue"
},
  "geometry": {"coordinates":[1.225635,45.804314],"type":"Point"}
}