{
  "type": "Feature",
  "properties": {
    "iso:country":"FR",
    "sg:address":"55 Route Nationale 53 Vannerie Du Boisle 80150 Le Boisle",
    "sg:classifiers":[
        {
            "category":"Shopping",
            "subcategory":"Hobbies, Toys, & Games",
            "type":"Retail Goods"
        }
    ],
    "sg:phone":"+33 3 22 29 65 65",
    "sg:postcode":"80150",
    "sg:province":"Picardie",
    "sg:tags":[
        "product",
        "miscellaneous",
        "entertainment"
    ],
    "wof:name":"Societe Vannerie Candas Freres",
    "wof:placetype":"venue"
},
  "geometry": {"coordinates":[1.880765,50.25227],"type":"Point"}
}