{
  "type": "Feature",
  "properties": {
    "iso:country":"FR",
    "sg:address":"12, Rue de Montr\u00e9al, 74100 Ville la Grand",
    "sg:orig_category":"Unclassifiable Establishments",
    "sg:phone":"+33 4 50 92 08 36",
    "sg:province":"Rhone-Alpes",
    "wof:name":"Baret S.a.",
    "wof:placetype":"venue"
},
  "geometry": {"coordinates":[6.27846,46.203861],"type":"Point"}
}