{
  "type": "Feature",
  "properties": {
    "addr:full":"46160 Cajarc Midi Pyr\u00e9n\u00e9es 46160",
    "addr:postcode":"46160;46160",
    "iso:country":"FR",
    "sg:address":"46160 Cajarc",
    "sg:classifiers":[
        {
            "category":"Utilities",
            "subcategory":"Electric",
            "type":"Services"
        }
    ],
    "sg:phone":"+33 5 65 40 65 21",
    "sg:postcode":"46160",
    "sg:province":"Midi Pyr\u00e9n\u00e9es",
    "sg:tags":[
        "electricity",
        "raw",
        "energy",
        "material"
    ],
    "wof:name":"Electricite De France (edf)",
    "wof:placetype":"venue"
},
  "geometry": {"coordinates":[1.84169,44.485771],"type":"Point"}
}