{
  "type": "Feature",
  "properties": {
    "iso:country":"FR",
    "sg:address":"151, Rte de Turin - Tour 21, 06300 Nice",
    "sg:orig_category":"Unclassifiable Establishments",
    "sg:phone":"+33 4 93 89 37 52",
    "sg:province":"Provence-Alpes-C\u00f4te d'Azur",
    "wof:name":"Sudequip S.a.",
    "wof:placetype":"venue"
},
  "geometry": {"coordinates":[7.28588,43.719692],"type":"Point"}
}