{
  "type": "Feature",
  "properties": {
    "addr:full":"14, Rue du Bus, 59200 Tourcoing Nord Pas-de-Calais",
    "addr:housenumber":"14",
    "addr:postcode":"59200",
    "addr:street":"Rue Du Bus",
    "iso:country":"FR",
    "sg:address":"14, Rue du Bus, 59200 Tourcoing",
    "sg:orig_category":"Unclassifiable Establishments",
    "sg:phone":"+33 3 20 25 01 58",
    "sg:province":"Nord Pas-de-Calais",
    "wof:name":"Soliplast Associ\u00e9s S.a.r.l.",
    "wof:placetype":"venue"
},
  "geometry": {"coordinates":[3.161768,50.726589],"type":"Point"}
}