{
  "type": "Feature",
  "properties": {
    "addr:full":"6/8, All\u00e9e de la Garenne, 91610 Ballancourt sur Essonne Ile de France",
    "addr:housenumber":"6 / 8",
    "addr:postcode":"91610;ile",
    "addr:street":"Alle\u0301E De La Garenne",
    "iso:country":"FR",
    "sg:address":"6/8, All\u00e9e de la Garenne, 91610 Ballancourt sur Essonne",
    "sg:orig_category":"Unclassifiable Establishments",
    "sg:phone":"+33 1 64 93 25 00",
    "sg:province":"Ile de France",
    "wof:name":"Fav\u00e9co S.a.",
    "wof:placetype":"venue"
},
  "geometry": {"coordinates":[2.386565,48.52478],"type":"Point"}
}