{
  "type": "Feature",
  "properties": {
    "iso:country":"FR",
    "sg:address":"82, Rue de la 3\u00e8me D.I. Motoris\u00e9, 02100 Saint Quentin",
    "sg:orig_category":"Non-Classified Establishments",
    "sg:phone":"+33 3 23 62 28 46",
    "sg:province":"Picardie",
    "wof:name":"Lachant Fr\u00e8res S.a.r.l.",
    "wof:placetype":"venue"
},
  "geometry": {"coordinates":[3.275741,49.852001],"type":"Point"}
}