{
  "type": "Feature",
  "properties": {
    "iso:country":"FR",
    "sg:address":"103 Rue Aux Arenes 57000 Metz",
    "sg:classifiers":[
        {
            "category":"Utilities",
            "type":"Services"
        }
    ],
    "sg:phone":"+33 3 87 30 54 75",
    "sg:postcode":"57000",
    "sg:province":"Lorraine",
    "sg:tags":[
        "raw",
        "energy",
        "material"
    ],
    "wof:name":"Societe Mosellane Des Eaux",
    "wof:placetype":"venue"
},
  "geometry": {"coordinates":[6.176489,49.106464],"type":"Point"}
}