{
  "type": "Feature",
  "properties": {
    "addr:full":"4 Bd Des Capucines 75009 Paris Ile de France 75009",
    "addr:housenumber":"4",
    "addr:postcode":"75009;75009",
    "addr:street":"Bd Des Capucines",
    "iso:country":"FR",
    "sg:address":"4 Bd Des Capucines 75009 Paris",
    "sg:classifiers":[
        {
            "category":"Sports & Exercise",
            "subcategory":"Sports Center",
            "type":"Entertainment"
        }
    ],
    "sg:phone":"+33 1 47 42 29 63",
    "sg:postcode":"75009",
    "sg:province":"Ile de France",
    "sg:tags":[
        "game"
    ],
    "wof:name":"Club Anglais Ass",
    "wof:placetype":"venue"
},
  "geometry": {"coordinates":[2.333541,48.87101],"type":"Point"}
}