{
  "type": "Feature",
  "properties": {
    "addr:full":"RN 8 83330 LE BEAUSSET Beausse Pays de Loire 49410",
    "addr:postcode":"83330;49410",
    "addr:street":"Rn 8",
    "iso:country":"FR",
    "sg:address":"RN 8 83330 LE BEAUSSET",
    "sg:city":"Beausse",
    "sg:classifiers":[
        {
            "category":"Building & Trades",
            "subcategory":"Construction",
            "type":"Services"
        }
    ],
    "sg:phone":"+33 4 94 90 54 00",
    "sg:postcode":"49410",
    "sg:province":"Pays de Loire",
    "sg:tags":[
        "small",
        "component",
        "industry",
        "assembly"
    ],
    "wof:name":"Kordial Laboratoire Sa",
    "wof:placetype":"venue"
},
  "geometry": {"coordinates":[5.84586,43.164211],"type":"Point"}
}