{
  "type": "Feature",
  "properties": {
    "iso:country":"FR",
    "sg:address":"Route du Sauze 05160 SAVINES LE LAC",
    "sg:orig_category":"Radio Receivers",
    "sg:phone":"+33 4 92 44 20 35",
    "sg:province":"Midi Pyr\u00e9n\u00e9es",
    "wof:name":"Soci\u00e9t\u00e9 Fabric. Des Produits Optex Sa",
    "wof:placetype":"venue"
},
  "geometry": {"coordinates":[6.367,44.53056],"type":"Point"}
}