{
  "type": "Feature",
  "properties": {
    "addr:full":"24 avenue Joannes Masset 69009 Lyon Rhone-Alpes 69009",
    "addr:housenumber":"24",
    "addr:postcode":"69009;69009",
    "addr:street":"Avenue Joannes",
    "iso:country":"FR",
    "sg:address":"24 avenue Joannes Masset 69009 Lyon",
    "sg:classifiers":[
        {
            "category":"Manufacturing",
            "subcategory":"Printing",
            "type":"Manufacturing & Wholesale Goods"
        }
    ],
    "sg:phone":"+33 4 78 83 08 88",
    "sg:postcode":"69009",
    "sg:province":"Rhone-Alpes",
    "sg:tags":[
        "screen",
        "auxiliary"
    ],
    "wof:name":"Tripette Et Renaud Image Sa",
    "wof:placetype":"venue"
},
  "geometry": {"coordinates":[4.800193,45.770794],"type":"Point"}
}