{
  "type": "Feature",
  "properties": {
    "addr:full":"Billieu 01300 Magnieu Rhone-Alpes 01300",
    "addr:postcode":"01300;01300",
    "addr:street":"Billieu;Rhone-Alpes",
    "iso:country":"FR",
    "sg:address":"Billieu 01300 Magnieu",
    "sg:orig_category":"Non-Classified Establishments",
    "sg:phone":"+33 4 79 81 39 91",
    "sg:postcode":"01300",
    "sg:province":"Rhone-Alpes",
    "wof:name":"Entreprise Berthaud Robert",
    "wof:placetype":"venue"
},
  "geometry": {"coordinates":[5.70607,45.788395],"type":"Point"}
}