{
  "type": "Feature",
  "properties": {
    "iso:country":"FR",
    "sg:address":"32, Rue de la Seigli\u00e8re, 33800 Bordeaux",
    "sg:city":"Bordeaux",
    "sg:orig_category":"Unclassifiable Establishments",
    "sg:phone":"+33 5 57 35 74 74",
    "sg:postcode":"33800",
    "sg:province":"Aquitaine",
    "wof:name":"Euro Wild S.a.",
    "wof:placetype":"venue"
},
  "geometry": {"coordinates":[-0.549401,44.824867],"type":"Point"}
}