{
  "type": "Feature",
  "properties": {
    "iso:country":"FR",
    "sg:address":"B.P. 31, 31190 Auterive^^ZI la Pradelle, 31190 Auterive",
    "sg:orig_category":"Non-Classified Establishments",
    "sg:phone":"+33 5 61 50 96 30",
    "sg:province":"Midi Pyr\u00e9n\u00e9es",
    "wof:name":"Procolor S.a.",
    "wof:placetype":"venue"
},
  "geometry": {"coordinates":[1.40004,43.297123],"type":"Point"}
}