{
  "type": "Feature",
  "properties": {
    "addr:full":"B.P. 157, 06272 Villeneuve Loubet^^679, Av du Docteur Lef\u00e8bvre - Immeuble Twins 1, 06270 Villeneuve  Vill\u00e9 Alsace 67220",
    "addr:housenumber":"b.p. 157;1",
    "addr:postcode":"06272;06270;67220",
    "addr:street":"Av Du Docteur Lefe\u0300Bvre;Twins",
    "iso:country":"FR",
    "sg:address":"B.P. 157, 06272 Villeneuve Loubet^^679, Av du Docteur Lef\u00e8bvre - Immeuble Twins 1, 06270 Villeneuve ",
    "sg:city":"Vill\u00e9",
    "sg:orig_category":"Non-Classified Establishments",
    "sg:phone":"+33 4 92 13 52 30",
    "sg:postcode":"67220",
    "sg:province":"Alsace",
    "wof:name":"Retif S.a.",
    "wof:placetype":"venue"
},
  "geometry": {"coordinates":[7.120123,43.646404],"type":"Point"}
}