{
  "type": "Feature",
  "properties": {
    "iso:country":"FR",
    "sg:address":"21, Rue du Mont, 52360 Neuilly l'Ev\u00eaque",
    "sg:orig_category":"Unclassifiable Establishments",
    "sg:phone":"+33 3 25 84 01 29",
    "sg:province":"Champagne",
    "wof:name":"Gallissot Entreprise S.a.",
    "wof:placetype":"venue"
},
  "geometry": {"coordinates":[5.441745,47.916569],"type":"Point"}
}