{
  "type": "Feature",
  "properties": {
    "addr:full":"Pa 50600 Virey Virey Basse Normandie 50600",
    "addr:postcode":"50600;50600",
    "iso:country":"FR",
    "sg:address":"Pa 50600 Virey",
    "sg:city":"Virey",
    "sg:classifiers":[
        {
            "category":"Professional",
            "subcategory":"Engineering",
            "type":"Services"
        }
    ],
    "sg:phone":"+33 2 33 79 00 60",
    "sg:postcode":"50600",
    "sg:province":"Basse Normandie",
    "sg:tags":[
        "machine",
        "-",
        "mechanical"
    ],
    "wof:name":"Aes",
    "wof:placetype":"venue"
},
  "geometry": {"coordinates":[-1.091154,48.539909],"type":"Point"}
}