{
  "type": "Feature",
  "properties": {
    "iso:country":"FR",
    "sg:address":"5, Bd Brian\u00e7on, 13003 Marseille",
    "sg:orig_category":"Unclassifiable Establishments",
    "sg:phone":"+33 4 91 62 29 31",
    "sg:province":"Poitou-Charentes",
    "wof:name":"Midi M\u00e9taux S.a.r.l.",
    "wof:placetype":"venue"
},
  "geometry": {"coordinates":[5.369402,43.316891],"type":"Point"}
}