{
  "type": "Feature",
  "properties": {
    "iso:country":"FR",
    "sg:address":"325, Rue du Mas de Portaly, 34000 Montpellier",
    "sg:orig_category":"Unclassifiable Establishments",
    "sg:phone":"+33 4 67 92 66 62",
    "sg:province":"Languedoc-Roussillon",
    "wof:name":"F.d.g. Languedoc S.a.",
    "wof:placetype":"venue"
},
  "geometry": {"coordinates":[3.882236,43.582024],"type":"Point"}
}