{
  "type": "Feature",
  "properties": {
    "addr:full":"41 Rue Charles Fourier 94400 Vitry Sur Seine Ile de France 94400",
    "addr:housenumber":"41",
    "addr:postcode":"94400;94400",
    "addr:street":"Rue Charles Fourier;France",
    "iso:country":"FR",
    "sg:address":"41 Rue Charles Fourier 94400 Vitry Sur Seine",
    "sg:classifiers":[
        {
            "category":"Manufacturing",
            "subcategory":"Glass & Minerals",
            "type":"Manufacturing & Wholesale Goods"
        }
    ],
    "sg:phone":"+33 1 46 80 20 00",
    "sg:postcode":"94400",
    "sg:province":"Ile de France",
    "sg:tags":[
        "building",
        "material"
    ],
    "wof:name":"Pmb Couleur (ste)",
    "wof:placetype":"venue"
},
  "geometry": {"coordinates":[2.407344,48.802532],"type":"Point"}
}