{
  "type": "Feature",
  "properties": {
    "iso:country":"FR",
    "sg:address":"rte Etampes 45300 Pithiviers le Vieil",
    "sg:city":"Courcelles",
    "sg:classifiers":[
        {
            "category":"Professional",
            "subcategory":"Engineering",
            "type":"Services"
        }
    ],
    "sg:phone":"+33 2 38 30 90 00",
    "sg:postcode":"45300",
    "sg:province":"Centre",
    "sg:tags":[
        "machine",
        "-",
        "mechanical"
    ],
    "wof:name":"Cornet",
    "wof:placetype":"venue"
},
  "geometry": {"coordinates":[2.21384,48.064007],"type":"Point"}
}