{
  "type": "Feature",
  "properties": {
    "addr:full":"17 rue du Luxembourg 68110 Illzach Illzach Alsace 68110",
    "addr:housenumber":"17",
    "addr:postcode":"68110;68110",
    "addr:street":"Rue Du Luxembourg",
    "iso:country":"FR",
    "sg:address":"17 rue du Luxembourg 68110 Illzach",
    "sg:city":"Illzach",
    "sg:orig_category":"Partition Wall Systems",
    "sg:phone":"+33 3 89 61 84 80",
    "sg:postcode":"68110",
    "sg:province":"Alsace",
    "wof:name":"Perisse Equipement Sa",
    "wof:placetype":"venue"
},
  "geometry": {"coordinates":[7.368505,47.770519],"type":"Point"}
}