{
  "type": "Feature",
  "properties": {
    "addr:full":"31 Rue De Cambrai 75946 Papris Cedex 19 Cambrai Nord Pas-de-Calais 59400",
    "addr:housenumber":"31",
    "addr:postcode":"75946;cedex 19;59400",
    "addr:street":"Rue De Cambrai",
    "iso:country":"FR",
    "sg:address":"31 Rue De Cambrai 75946 Papris Cedex 19",
    "sg:city":"Cambrai",
    "sg:orig_category":"Miscellaneous Products",
    "sg:phone":"+33 1 55 26 54 00",
    "sg:postcode":"59400",
    "sg:province":"Nord Pas-de-Calais",
    "wof:name":"Ogf Pfg",
    "wof:placetype":"venue"
},
  "geometry": {"coordinates":[2.381851,48.89579],"type":"Point"}
}