{
  "type": "Feature",
  "properties": {
    "iso:country":"FR",
    "sg:address":"Bourjaguet 31390 Carbonne",
    "sg:orig_category":"Non-Classified Establishments",
    "sg:phone":"+33 5 61 98 40 80",
    "sg:postcode":"31390",
    "sg:province":"Midi Pyr\u00e9n\u00e9es",
    "wof:name":"Bou\u00e9 Fils Et Compagnie S.a.",
    "wof:placetype":"venue"
},
  "geometry": {"coordinates":[1.246305,43.281654],"type":"Point"}
}