{
  "type": "Feature",
  "properties": {
    "addr:full":"10 rue Antoine de Saint-Exup\u00e9ry 56100 Lorient Lorient Bretagne 56100",
    "addr:housenumber":"10",
    "addr:postcode":"56100;56100",
    "addr:street":"Rue Antoine De Saint-Exupe\u0301Ry",
    "iso:country":"FR",
    "sg:address":"10 rue Antoine de Saint-Exup\u00e9ry 56100 Lorient",
    "sg:city":"Lorient",
    "sg:classifiers":[
        {
            "category":"Retail",
            "subcategory":"Auto Repair",
            "type":"Services"
        }
    ],
    "sg:phone":"+33 2 97 37 25 87",
    "sg:postcode":"56100",
    "sg:province":"Bretagne",
    "sg:tags":[
        "motor"
    ],
    "wof:name":"Rgbb S.a.",
    "wof:placetype":"venue"
},
  "geometry": {"coordinates":[-3.402766,47.762516],"type":"Point"}
}