{
  "type": "Feature",
  "properties": {
    "iso:country":"FR",
    "sg:address":"B.P. 20609",
    "sg:city":"Compi\u00e8gne C\u00e9dex",
    "sg:orig_category":"Non-Classified Establishments",
    "sg:phone":"+33 3 44 90 70 07",
    "sg:postcode":"60206",
    "sg:province":"Picardie",
    "wof:name":"Novance S.a.",
    "wof:placetype":"venue"
},
  "geometry": {"coordinates":[2.825,49.417671],"type":"Point"}
}