{
  "type": "Feature",
  "properties": {
    "addr:full":"3 Av Du Garigliano Zac Les G\u00e2tines 91602 Savigna Sur Orge Basse Normandie",
    "addr:postcode":"91602",
    "addr:street":"Av Du Garigliano Zac Les Ga\u0302Tines",
    "iso:country":"FR",
    "sg:address":"3 Av Du Garigliano Zac Les G\u00e2tines 91602 Savigna Sur Orge",
    "sg:classifiers":[
        {
            "category":"Shopping",
            "type":"Retail Goods"
        }
    ],
    "sg:phone":"+33 1 69 05 72 83",
    "sg:province":"Basse Normandie",
    "sg:tags":[
        "metallurgy",
        "finished",
        "-",
        "metalworking",
        "metallic"
    ],
    "wof:name":"Vraco Sa",
    "wof:placetype":"venue"
},
  "geometry": {"coordinates":[5.57782,46.442612],"type":"Point"}
}