{
  "type": "Feature",
  "properties": {
    "addr:full":"B.P. 1627, 80016 Amiens C\u00e9dex 1^^65, Rue Robert Le Coq, 80000 Amiens Picardie",
    "addr:housenumber":"80016;1 ^ ^ 65",
    "addr:postcode":"80000",
    "addr:street":"B.P. 1627;Ce\u0301Dex;Rue Robert Le",
    "iso:country":"FR",
    "sg:address":"B.P. 1627, 80016 Amiens C\u00e9dex 1^^65, Rue Robert Le Coq, 80000 Amiens",
    "sg:orig_category":"Non-Classified Establishments",
    "sg:phone":"+33 3 22 54 67 67",
    "sg:province":"Picardie",
    "wof:name":"Magneti Marelli France S.a.",
    "wof:placetype":"venue"
},
  "geometry": {"coordinates":[2.293165,49.894733],"type":"Point"}
}