{
  "type": "Feature",
  "properties": {
    "addr:full":"10, Av. du Granier - Immeuble la Chantignole, 38240 Meylan Rhone-Alpes 38240",
    "addr:postcode":"38240;38240",
    "addr:street":"10 Av. Du Granier Immeuble La Chantignole",
    "iso:country":"FR",
    "sg:address":"10, Av. du Granier - Immeuble la Chantignole, 38240 Meylan",
    "sg:orig_category":"Unclassifiable Establishments",
    "sg:phone":"+33 4 76 90 85 23",
    "sg:postcode":"38240",
    "sg:province":"Rhone-Alpes",
    "wof:name":"Trinome S.a.r.l.",
    "wof:placetype":"venue"
},
  "geometry": {"coordinates":[5.788559,45.211658],"type":"Point"}
}