{
  "type": "Feature",
  "properties": {
    "iso:country":"FR",
    "sg:address":"Av De Belgique 46500 Gramat",
    "sg:classifiers":[
        {
            "category":"Food Court",
            "type":"Food & Drink"
        }
    ],
    "sg:phone":"+33 5 65 38 74 95",
    "sg:postcode":"46500",
    "sg:province":"Midi Pyr\u00e9n\u00e9es",
    "sg:tags":[
        "product",
        "related"
    ],
    "wof:name":"Elidis Aquitaine Centre",
    "wof:placetype":"venue"
},
  "geometry": {"coordinates":[1.713637,44.788128],"type":"Point"}
}