{
  "type": "Feature",
  "properties": {
    "addr:full":"1 Rue Alphonse Daudet 34590 Marsillargues Languedoc-Roussillon 34590",
    "addr:housenumber":"1",
    "addr:postcode":"34590;34590",
    "addr:street":"Rue Alphonse Daudet",
    "iso:country":"FR",
    "sg:address":"1 Rue Alphonse Daudet 34590 Marsillargues",
    "sg:classifiers":[
        {
            "category":"Wholesale",
            "subcategory":"Medical Equipment & Supplies",
            "type":"Manufacturing & Wholesale Goods"
        }
    ],
    "sg:phone":"+33 4 67 83 86 73",
    "sg:postcode":"34590",
    "sg:province":"Languedoc-Roussillon",
    "sg:tags":[
        "instrument",
        "health",
        "-",
        "precision"
    ],
    "wof:name":"Sud Embouts",
    "wof:placetype":"venue"
},
  "geometry": {"coordinates":[4.177774,43.661568],"type":"Point"}
}