{
  "type": "Feature",
  "properties": {
    "iso:country":"FR",
    "sg:address":"avenue du Pr\u00e9sident Coty 21400 CHATILLON SUR SEINE",
    "sg:city":"Aisey-sur-Seine",
    "sg:orig_category":"Harness Taping Machines For Longitudinal Covering Of Wire Harnesses",
    "sg:phone":"+33 3 80 91 11 35",
    "sg:postcode":"21400",
    "sg:province":"Bourgogne",
    "wof:name":"Ets Fernand Brug\u00e8re S.a.",
    "wof:placetype":"venue"
},
  "geometry": {"coordinates":[4.574269,47.866104],"type":"Point"}
}