{
  "type": "Feature",
  "properties": {
    "iso:country":"FR",
    "sg:address":"Pac De L'Oc\u00e9anie 53950 Louvern\u00e9",
    "sg:classifiers":[
        {
            "category":"Manufacturing",
            "subcategory":"Printing",
            "type":"Manufacturing & Wholesale Goods"
        }
    ],
    "sg:phone":"+33 2 43 37 82 37",
    "sg:province":"Pays de Loire",
    "sg:tags":[
        "publishing"
    ],
    "wof:name":"Publi Decor",
    "wof:placetype":"venue"
},
  "geometry": {"coordinates":[-0.72001,48.122681],"type":"Point"}
}