{
  "type": "Feature",
  "properties": {
    "iso:country":"FR",
    "sg:address":"B.P. 32, 57520 Grosbliederstroff^^Chemin de l'Ecluse, 57520 Grosbliederstroff",
    "sg:orig_category":"Automatismes Menuiserie PVC Portails",
    "sg:phone":"+33 3 87 27 19 93",
    "sg:postcode":"57520",
    "sg:province":"Lorraine",
    "wof:name":"Emb. Concept S.a.r.l.",
    "wof:placetype":"venue"
},
  "geometry": {"coordinates":[7.043765,49.127541],"type":"Point"}
}