{
  "type": "Feature",
  "properties": {
    "addr:full":"B.P. 32, 57520 Grosbliederstroff^^Chemin de l'Ecluse, 57520 Grosbliederstroff Lorraine 57520",
    "addr:postcode":"57520;57520;57520",
    "addr:street":"B.P. 32;L'Ecluse",
    "iso:country":"FR",
    "sg:address":"B.P. 32, 57520 Grosbliederstroff^^Chemin de l'Ecluse, 57520 Grosbliederstroff",
    "sg:orig_category":"Automatismes Menuiserie PVC Portails",
    "sg:phone":"+33 3 87 27 19 93",
    "sg:postcode":"57520",
    "sg:province":"Lorraine",
    "wof:name":"Emb. Concept S.a.r.l.",
    "wof:placetype":"venue"
},
  "geometry": {"coordinates":[7.043765,49.127541],"type":"Point"}
}