{
  "type": "Feature",
  "properties": {
    "addr:full":"117, Rue M\u00e9lanie, 67000 Strasbourg Strasbourg Alsace 67000",
    "addr:housenumber":"117",
    "addr:postcode":"67000;67000",
    "addr:street":"Rue Me\u0301Lanie",
    "iso:country":"FR",
    "sg:address":"117, Rue M\u00e9lanie, 67000 Strasbourg",
    "sg:city":"Strasbourg",
    "sg:orig_category":"Non-Classified Establishments",
    "sg:phone":"+33 3 88 31 20 30",
    "sg:postcode":"67000",
    "sg:province":"Alsace",
    "wof:name":"A.m.m. S.a.r.l. - Assistance Maintenance Multim\u00e9dia",
    "wof:placetype":"venue"
},
  "geometry": {"coordinates":[7.797447,48.604107],"type":"Point"}
}