{
  "type": "Feature",
  "properties": {
    "iso:country":"FR",
    "sg:address":"5, Villa Malakoff, 75116 Paris",
    "sg:city":"Malakoff",
    "sg:orig_category":"Non-Classified Establishments",
    "sg:phone":"+33 1 44 34 09 00",
    "sg:postcode":"92240",
    "sg:province":"Ile de France",
    "wof:name":"Massa S.a.r.l.",
    "wof:placetype":"venue"
},
  "geometry": {"coordinates":[2.287007,48.865669],"type":"Point"}
}