{
  "type": "Feature",
  "properties": {
    "addr:full":"Chazey 71130 Gueugnon Gueugnon Bourgogne 71130",
    "addr:postcode":"71130;71130",
    "addr:street":"Chazey",
    "iso:country":"FR",
    "sg:address":"Chazey 71130 Gueugnon",
    "sg:city":"Gueugnon",
    "sg:classifiers":[
        {
            "category":"Wholesale",
            "subcategory":"Machinery & Supplies",
            "type":"Manufacturing & Wholesale Goods"
        }
    ],
    "sg:phone":"+33 3 85 85 62 00",
    "sg:postcode":"71130",
    "sg:province":"Bourgogne",
    "sg:tags":[
        "handling",
        "material",
        "-",
        "machine",
        "equipment",
        "engineering",
        "mechanical"
    ],
    "wof:name":"Transports Rave Sa",
    "wof:placetype":"venue"
},
  "geometry": {"coordinates":[4.05878,46.572475],"type":"Point"}
}