{
  "type": "Feature",
  "properties": {
    "addr:full":"A\u00e9roport N\u00eemes Arles Camargue BP 23 30128 Garons Languedoc-Roussillon 30128",
    "addr:housenumber":"bp 23",
    "addr:postcode":"30128;30128",
    "iso:country":"FR",
    "sg:address":"A\u00e9roport N\u00eemes Arles Camargue BP 23 30128 Garons",
    "sg:classifiers":[
        {
            "category":"Manufacturing",
            "subcategory":"Aerospace",
            "type":"Manufacturing & Wholesale Goods"
        }
    ],
    "sg:phone":"+33 4 66 70 72 00",
    "sg:postcode":"30128",
    "sg:province":"Languedoc-Roussillon",
    "sg:tags":[
        "equipment",
        "aeronautic",
        "transport",
        "vehicle"
    ],
    "wof:name":"Tat Industries Aomi",
    "wof:placetype":"venue"
},
  "geometry": {"coordinates":[4.42732,43.770672],"type":"Point"}
}