{
  "type": "Feature",
  "properties": {
    "addr:full":"70 Rue Du Quesnoy 59300 Valenciennes Nord Pas-de-Calais 59300",
    "addr:housenumber":"70",
    "addr:postcode":"59300;59300",
    "addr:street":"Rue Du Quesnoy",
    "iso:country":"FR",
    "sg:address":"70 Rue Du Quesnoy 59300 Valenciennes",
    "sg:classifiers":[
        {
            "category":"Shopping",
            "subcategory":"Luggage & Leather Goods",
            "type":"Retail Goods"
        }
    ],
    "sg:phone":"+33 3 27 45 21 99",
    "sg:postcode":"59300",
    "sg:province":"Nord Pas-de-Calais",
    "sg:tags":[
        "shoe"
    ],
    "wof:name":"Orthopedie Legrand",
    "wof:placetype":"venue"
},
  "geometry": {"coordinates":[3.526828,50.356712],"type":"Point"}
}