{
  "type": "Feature",
  "properties": {
    "addr:full":"Rue des Peupliers - ZI Vimoutiers Basse Normandie 61120",
    "addr:postcode":"61120",
    "addr:street":"Rue Des Peupliers Zi",
    "iso:country":"FR",
    "sg:address":"Rue des Peupliers - ZI",
    "sg:city":"Vimoutiers",
    "sg:orig_category":"Non-Classified Establishments",
    "sg:phone":"+33 2 33 39 16 38",
    "sg:postcode":"61120",
    "sg:province":"Basse Normandie",
    "wof:name":"Sodev Industries S.a. - Soci\u00e9t\u00e9 D'outillage De D\u00e9coupage D'emboutissage D",
    "wof:placetype":"venue"
},
  "geometry": {"coordinates":[0.232705,48.851215],"type":"Point"}
}