{
  "type": "Feature",
  "properties": {
    "iso:country":"FR",
    "sg:address":"Rue du Rhin Napol\u00e9on",
    "sg:city":"Strasbourg",
    "sg:orig_category":"Unclassifiable Establishments",
    "sg:phone":"+33 3 88 40 12 00",
    "sg:postcode":"67100",
    "sg:province":"Alsace",
    "wof:name":"Skako Comessa S.a.",
    "wof:placetype":"venue"
},
  "geometry": {"coordinates":[7.799362,48.553173],"type":"Point"}
}