{
  "type": "Feature",
  "properties": {
    "iso:country":"FR",
    "sg:address":"11, Rue Dulong, 75017 Paris",
    "sg:orig_category":"Non-Classified Establishments",
    "sg:phone":"+33 1 56 33 47 80",
    "sg:province":"Ile de France",
    "wof:name":"Id\u00e9actif S.a.r.l.",
    "wof:placetype":"venue"
},
  "geometry": {"coordinates":[2.317835,48.883541],"type":"Point"}
}