{
  "type": "Feature",
  "properties": {
    "addr:full":"ZI de la Chenois Briey Lorraine 54150",
    "addr:postcode":"54150",
    "addr:street":"Zi De La Chenois Briey Lorraine",
    "iso:country":"FR",
    "sg:address":"ZI de la Chenois",
    "sg:city":"Briey",
    "sg:orig_category":"Non-Classified Establishments",
    "sg:phone":"+33 3 82 20 06 06",
    "sg:postcode":"54150",
    "sg:province":"Lorraine",
    "wof:name":"Straplor",
    "wof:placetype":"venue"
},
  "geometry": {"coordinates":[5.93833,49.24958],"type":"Point"}
}