{
  "type": "Feature",
  "properties": {
    "addr:full":"68 Bd De Courcelles 75017 Paris Ile de France 75017",
    "addr:housenumber":"68",
    "addr:postcode":"75017;75017",
    "addr:street":"Bd De Courcelles",
    "iso:country":"FR",
    "sg:address":"68 Bd De Courcelles 75017 Paris",
    "sg:classifiers":[
        {
            "category":"Banks & Credit Unions",
            "subcategory":"Financial Services",
            "type":"Services"
        }
    ],
    "sg:phone":"+33 1 44 01 44 01",
    "sg:postcode":"75017",
    "sg:province":"Ile de France",
    "sg:tags":[
        "banking",
        "finance",
        "insurance"
    ],
    "wof:name":"Berlioz & Co",
    "wof:placetype":"venue"
},
  "geometry": {"coordinates":[2.307231,48.880245],"type":"Point"}
}