{
  "type": "Feature",
  "properties": {
    "addr:full":"Quai Morin 26220 Dieulefit Rhone-Alpes 26220",
    "addr:postcode":"26220;26220",
    "addr:street":"Quai Morin",
    "iso:country":"FR",
    "sg:address":"Quai Morin 26220 Dieulefit",
    "sg:classifiers":[
        {
            "category":"Home & Garden",
            "subcategory":"Furniture",
            "type":"Retail Goods"
        }
    ],
    "sg:phone":"+33 4 75 46 44 74",
    "sg:postcode":"26220",
    "sg:province":"Rhone-Alpes",
    "sg:tags":[
        "household",
        "wood"
    ],
    "wof:name":"Sarl Diorca",
    "wof:placetype":"venue"
},
  "geometry": {"coordinates":[5.064537,44.523773],"type":"Point"}
}