{
  "type": "Feature",
  "properties": {
    "addr:full":"13/15, Rue Cassette, 75006 Paris Ile de France",
    "addr:housenumber":"13 / 15",
    "addr:postcode":"75006",
    "addr:street":"Rue Cassette",
    "iso:country":"FR",
    "sg:address":"13/15, Rue Cassette, 75006 Paris",
    "sg:orig_category":"Unclassifiable Establishments",
    "sg:phone":"+33 1 53 63 14 14",
    "sg:province":"Ile de France",
    "wof:name":"Jean-charles De Castelbajac S.a.",
    "wof:placetype":"venue"
},
  "geometry": {"coordinates":[2.331033,48.849953],"type":"Point"}
}