{
  "type": "Feature",
  "properties": {
    "addr:full":"56 Rue Principale 67360 Goersdorf Goersdorf Alsace 67360",
    "addr:housenumber":"56",
    "addr:postcode":"67360;67360",
    "addr:street":"Rue Principale;Goersdorf",
    "iso:country":"FR",
    "sg:address":"56 Rue Principale 67360 Goersdorf",
    "sg:city":"Goersdorf",
    "sg:classifiers":[
        {
            "category":"Home & Garden",
            "subcategory":"Furniture",
            "type":"Retail Goods"
        }
    ],
    "sg:phone":"+33 3 88 54 09 22",
    "sg:postcode":"67360",
    "sg:province":"Alsace",
    "sg:tags":[
        "household",
        "wood"
    ],
    "wof:name":"Stephan Marthe",
    "wof:placetype":"venue"
},
  "geometry": {"coordinates":[7.767305,48.950878],"type":"Point"}
}