{
  "type": "Feature",
  "properties": {
    "iso:country":"FR",
    "sg:address":"Zac Des Grands Clos 37420 Avoine",
    "sg:city":"Avoine",
    "sg:classifiers":[
        {
            "category":"Farming",
            "subcategory":"Livestock Farm",
            "type":"Manufacturing & Wholesale Goods"
        }
    ],
    "sg:phone":"+33 2 47 58 90 17",
    "sg:postcode":"37420",
    "sg:province":"Centre",
    "sg:tags":[
        "grain",
        "agriculture",
        "cereal"
    ],
    "wof:name":"Delto",
    "wof:placetype":"venue"
},
  "geometry": {"coordinates":[0.181698,47.206543],"type":"Point"}
}