{
  "type": "Feature",
  "properties": {
    "addr:full":"5 av Gambetta; Lussac Aquitaine",
    "addr:street":"Av Gambetta",
    "iso:country":"FR",
    "sg:address":"5 av Gambetta; Lussac",
    "sg:classifiers":[
        {
            "category":"Banks & Credit Unions",
            "subcategory":"Bank",
            "type":"Services"
        }
    ],
    "sg:phone":"+33 3357554780",
    "sg:province":"Aquitaine",
    "wof:name":"Cr\u00e9dit Agicole Mutuel, Du Libournais",
    "wof:placetype":"venue"
},
  "geometry": {"coordinates":[-0.096593,44.949722],"type":"Point"}
}