{
  "type": "Feature",
  "properties": {
    "iso:country":"FR",
    "sg:address":"B.P. 14",
    "sg:city":"Soullans",
    "sg:orig_category":"Non-Classified Establishments",
    "sg:phone":"+33 2 51 68 05 88",
    "sg:postcode":"85300",
    "sg:province":"Pays de Loire",
    "wof:name":"Marcel Favreau S.a.r.l.",
    "wof:placetype":"venue"
},
  "geometry": {"coordinates":[-1.900733,46.795818],"type":"Point"}
}