{
  "type": "Feature",
  "properties": {
    "addr:full":"rte Kirchheim 67520 Marlenheim Marlenheim Alsace 67520",
    "addr:postcode":"67520;67520",
    "addr:street":"Rte",
    "iso:country":"FR",
    "sg:address":"rte Kirchheim 67520 Marlenheim",
    "sg:city":"Marlenheim",
    "sg:classifiers":[
        {
            "category":"Shopping",
            "subcategory":"Crafts & Fabrics",
            "type":"Retail Goods"
        }
    ],
    "sg:phone":"+33 3 88 59 27 37",
    "sg:postcode":"67520",
    "sg:province":"Alsace",
    "sg:tags":[
        "adhesive"
    ],
    "wof:name":"Chimistra S.a.",
    "wof:placetype":"venue"
},
  "geometry": {"coordinates":[7.498,48.613785],"type":"Point"}
}