{
  "type": "Feature",
  "properties": {
    "addr:full":"Rue Jean Monnet - ZAC du C\u00e9sar Le Subdray Centre 18570",
    "addr:housenumber":"subdray",
    "addr:postcode":"18570",
    "addr:street":"Rue Jean Monnet Zac Du Ce\u0301Sar Le",
    "iso:country":"FR",
    "sg:address":"Rue Jean Monnet - ZAC du C\u00e9sar",
    "sg:city":"Le Subdray",
    "sg:orig_category":"Non-Classified Establishments",
    "sg:phone":"+33 2 48 23 45 65",
    "sg:postcode":"18570",
    "sg:province":"Centre",
    "wof:name":"Labonne Bertrand S.a.",
    "wof:placetype":"venue"
},
  "geometry": {"coordinates":[2.355745,47.008541],"type":"Point"}
}