{
  "type": "Feature",
  "properties": {
    "addr:full":"B.P. 22, 76210 Bolbec^^ZI de Roncherolles, 76210 Bolbec Haute Normandie",
    "addr:postcode":"76210;76210",
    "addr:street":"B.P. 22;Roncherolles;Haute Normandie",
    "iso:country":"FR",
    "sg:address":"B.P. 22, 76210 Bolbec^^ZI de Roncherolles, 76210 Bolbec",
    "sg:orig_category":"Non-Classified Establishments",
    "sg:phone":"+33 2 35 31 07 54",
    "sg:province":"Haute Normandie",
    "wof:name":"Painblanc Menuiserie S.a.r.l.",
    "wof:placetype":"venue"
},
  "geometry": {"coordinates":[0.451852,49.553249],"type":"Point"}
}