{
  "type": "Feature",
  "properties": {
    "iso:country":"FR",
    "sg:address":"13 Rue Perier 92120 Montrouge",
    "sg:classifiers":[
        {
            "category":"Health Services",
            "subcategory":"Medical Lab",
            "type":"Services"
        }
    ],
    "sg:phone":"+33 1 47 35 35 10",
    "sg:postcode":"92120",
    "sg:province":"Ile de France",
    "sg:tags":[
        "chemical",
        "pharmaceutical",
        "pharmacy"
    ],
    "wof:name":"Laboratoires Besins Iscovesco",
    "wof:placetype":"venue"
},
  "geometry": {"coordinates":[2.31861,48.813274],"type":"Point"}
}