{
  "type": "Feature",
  "properties": {
    "iso:country":"FR",
    "sg:address":"63500 Issoire",
    "sg:city":"Issoire",
    "sg:orig_category":"Unclassifiable Establishments",
    "sg:phone":"+43 555400",
    "sg:postcode":"63500",
    "sg:province":"Auvergne",
    "wof:name":"Aubert Et Duval Fortech S.a.",
    "wof:placetype":"venue"
},
  "geometry": {"coordinates":[3.22033,45.554291],"type":"Point"}
}