{
  "type": "Feature",
  "properties": {
    "iso:country":"FR",
    "sg:address":"Rue de la Meurthe",
    "sg:city":"Saulcy sur Meurthe",
    "sg:orig_category":"Unclassifiable Establishments",
    "sg:phone":"+33 3 29 50 00 21",
    "sg:postcode":"88580",
    "sg:province":"Lorraine",
    "wof:name":"Ballasti\u00e8res Cantrelle S.a.",
    "wof:placetype":"venue"
},
  "geometry": {"coordinates":[6.9572,48.24284],"type":"Point"}
}