{
  "type": "Feature",
  "properties": {
    "addr:full":"12 Rue Des Fr\u00e8res Lumi\u00e8re BP 165 69720 St Bonnet De Mure Rhone-Alpes 69720",
    "addr:housenumber":"12;165",
    "addr:postcode":"69720;de;69720",
    "addr:street":"Rue Des Fre\u0300Res Lumie\u0300Re Bp;Rhone-Alpes",
    "iso:country":"FR",
    "sg:address":"12 Rue Des Fr\u00e8res Lumi\u00e8re BP 165 69720 St Bonnet De Mure",
    "sg:classifiers":[
        {
            "category":"Professional",
            "subcategory":"Engineering",
            "type":"Services"
        }
    ],
    "sg:phone":"+33 4 72 48 30 00",
    "sg:postcode":"69720",
    "sg:province":"Rhone-Alpes",
    "sg:tags":[
        "machine",
        "-",
        "mechanical"
    ],
    "wof:name":"G.f.f Sas",
    "wof:placetype":"venue"
},
  "geometry": {"coordinates":[5.014353,45.69902],"type":"Point"}
}