{
  "type": "Feature",
  "properties": {
    "iso:country":"FR",
    "sg:address":"68 Rue Bayard 31000 Toulouse",
    "sg:classifiers":[
        {
            "category":"Travel",
            "subcategory":"Hotels & Motels",
            "type":"Entertainment"
        }
    ],
    "sg:phone":"+33 5 61 62 65 84",
    "sg:postcode":"31000",
    "sg:province":"Midi Pyr\u00e9n\u00e9es",
    "sg:tags":[
        "hotels",
        "business",
        "restaurant"
    ],
    "wof:name":"Hotel Les Ambassadeurs",
    "wof:placetype":"venue"
},
  "geometry": {"coordinates":[1.451557,43.610928],"type":"Point"}
}