{
  "type": "Feature",
  "properties": {
    "addr:full":"60800 S\u00e9ry Magneval^^10, Chemin des Dimes, 60800 S\u00e9ry Magneval Picardie",
    "addr:postcode":"60800;60800",
    "addr:street":"Chemin Des Dimes",
    "iso:country":"FR",
    "sg:address":"60800 S\u00e9ry Magneval^^10, Chemin des Dimes, 60800 S\u00e9ry Magneval",
    "sg:orig_category":"Non-Classified Establishments",
    "sg:phone":"+33 3 44 59 11 01",
    "sg:province":"Picardie",
    "wof:name":"Stan Dec S.a.r.l.",
    "wof:placetype":"venue"
},
  "geometry": {"coordinates":[2.887172,49.235062],"type":"Point"}
}