{
  "type": "Feature",
  "properties": {
    "addr:full":"120, Rue du Marais - ZAC des Landiers Nord, 73000 Chamb\u00e9ry Rhone-Alpes",
    "addr:housenumber":"120",
    "addr:postcode":"73000",
    "addr:street":"Rue Du Marais Zac Des Landiers Nord",
    "iso:country":"FR",
    "sg:address":"120, Rue du Marais - ZAC des Landiers Nord, 73000 Chamb\u00e9ry",
    "sg:orig_category":"Non-Classified Establishments",
    "sg:phone":"+33 4 79 69 00 24",
    "sg:province":"Rhone-Alpes",
    "wof:name":"M.a.",
    "wof:placetype":"venue"
},
  "geometry": {"coordinates":[5.90839,45.538151],"type":"Point"}
}