{
  "type": "Feature",
  "properties": {
    "iso:country":"FR",
    "sg:address":"3056 Avenue Etienne M\u00e9hul 34070 Montpellier",
    "sg:classifiers":[
        {
            "category":"Professional",
            "type":"Services"
        }
    ],
    "sg:phone":"+33 4 67 42 94 80",
    "sg:province":"Languedoc-Roussillon",
    "sg:tags":[
        "transport",
        "road"
    ],
    "wof:name":"Transport Brel",
    "wof:placetype":"venue"
},
  "geometry": {"coordinates":[3.860034,43.575657],"type":"Point"}
}