{
  "type": "Feature",
  "properties": {
    "addr:full":"21 Rue N D De Nazareth 75003 Paris Ile de France 75003",
    "addr:housenumber":"21",
    "addr:postcode":"75003;75003",
    "addr:street":"Rue N D De Nazareth",
    "iso:country":"FR",
    "sg:address":"21 Rue N D De Nazareth 75003 Paris",
    "sg:classifiers":[
        {
            "category":"Shopping",
            "subcategory":"Clothing, Apparel, & Fashions",
            "type":"Retail Goods"
        }
    ],
    "sg:phone":"+33 1 42 78 33 20",
    "sg:postcode":"75003",
    "sg:province":"Ile de France",
    "sg:tags":[
        "textile",
        "clothing",
        "clothes"
    ],
    "wof:name":"Sammy Jo",
    "wof:placetype":"venue"
},
  "geometry": {"coordinates":[2.36455,48.864704],"type":"Point"}
}