{
  "type": "Feature",
  "properties": {
    "addr:full":"42 rue La Bo\u00e9tie, 75008 Paris, Dept 75 Ile de France 75008",
    "addr:housenumber":"42;75",
    "addr:postcode":"75008;75008",
    "addr:street":"Rue La Boe\u0301Tie;Ile De France",
    "iso:country":"FR",
    "sg:address":"42 rue La Bo\u00e9tie, 75008 Paris, Dept 75",
    "sg:classifiers":[
        {
            "category":"Banks & Credit Unions",
            "subcategory":"Bank",
            "type":"Services"
        }
    ],
    "sg:postcode":"75008",
    "sg:province":"Ile de France",
    "wof:name":"Sphera Sarl",
    "wof:placetype":"venue"
},
  "geometry": {"coordinates":[2.314002,48.873722],"type":"Point"}
}