{
  "type": "Feature",
  "properties": {
    "iso:country":"FR",
    "sg:address":"La Tonnelle 16720 Saint M\u00eame les Carri\u00e8res",
    "sg:orig_category":"Unclassifiable Establishments",
    "sg:phone":"+33 5 45 81 91 55",
    "sg:province":"Poitou-Charentes",
    "wof:name":"Menuet S.a.r.l.",
    "wof:placetype":"venue"
},
  "geometry": {"coordinates":[-0.150283,45.646282],"type":"Point"}
}