{
  "type": "Feature",
  "properties": {
    "iso:country":"FR",
    "sg:address":"Route Du Mans 72250 Parign\u00e9 L'Ev\u00eaque",
    "sg:classifiers":[
        {
            "category":"Manufacturing",
            "subcategory":"Metals",
            "type":"Manufacturing & Wholesale Goods"
        }
    ],
    "sg:phone":"+33 2 43 75 82 09",
    "sg:postcode":"72250",
    "sg:province":"Pays de Loire",
    "sg:tags":[
        "metallurgy",
        "metalworking",
        "processing"
    ],
    "wof:name":"Metallerie Williamey Sa",
    "wof:placetype":"venue"
},
  "geometry": {"coordinates":[-1.147012,48.370781],"type":"Point"}
}