{
  "type": "Feature",
  "properties": {
    "iso:country":"FR",
    "sg:address":"Menti\u00e8re 12600 Taussac",
    "sg:orig_category":"Unclassifiable Establishments",
    "sg:phone":"+33 5 65 66 07 84",
    "sg:province":"Midi Pyr\u00e9n\u00e9es",
    "wof:name":"Soreco S.a.",
    "wof:placetype":"venue"
},
  "geometry": {"coordinates":[2.577236,44.755375],"type":"Point"}
}