{
  "type": "Feature",
  "properties": {
    "addr:full":"Rue Thimonnier - ZI Lyon Nord Genay Bourgogne 69730",
    "addr:postcode":"69730",
    "addr:street":"Rue Thimonnier Zi",
    "iso:country":"FR",
    "sg:address":"Rue Thimonnier - ZI Lyon Nord",
    "sg:city":"Genay",
    "sg:orig_category":"Unclassifiable Establishments",
    "sg:phone":"+33 4 78 98 21 19",
    "sg:postcode":"69730",
    "sg:province":"Bourgogne",
    "wof:name":"Tubo Sider S.a.",
    "wof:placetype":"venue"
},
  "geometry": {"coordinates":[4.840655,45.897675],"type":"Point"}
}