{
  "type": "Feature",
  "properties": {
    "iso:country":"FR",
    "sg:address":"3bis, Cours du Roulage, 36000 Ch\u00e2teauroux",
    "sg:city":"Ch\u00e2teauroux",
    "sg:orig_category":"Unclassifiable Establishments",
    "sg:phone":"+33 2 54 22 59 95",
    "sg:postcode":"36000",
    "sg:province":"Centre",
    "wof:name":"Suprafax S.a.r.l.",
    "wof:placetype":"venue"
},
  "geometry": {"coordinates":[1.685164,46.810719],"type":"Point"}
}