{
  "type": "Feature",
  "properties": {
    "addr:full":"3bis, Cours du Roulage, 36000 Ch\u00e2teauroux Ch\u00e2teauroux Centre 36000",
    "addr:housenumber":"3bis",
    "addr:postcode":"36000;36000",
    "addr:street":"Cours Du Roulage;Cha\u0302Teauroux",
    "iso:country":"FR",
    "sg:address":"3bis, Cours du Roulage, 36000 Ch\u00e2teauroux",
    "sg:city":"Ch\u00e2teauroux",
    "sg:orig_category":"Unclassifiable Establishments",
    "sg:phone":"+33 2 54 22 59 95",
    "sg:postcode":"36000",
    "sg:province":"Centre",
    "wof:name":"Suprafax S.a.r.l.",
    "wof:placetype":"venue"
},
  "geometry": {"coordinates":[1.685164,46.810719],"type":"Point"}
}