{
  "type": "Feature",
  "properties": {
    "addr:full":"Les Grandes Bruy\u00e8res 69700 Chassagny Rhone-Alpes 69700",
    "addr:postcode":"69700;69700",
    "addr:street":"Les Grandes Bruye\u0300Res;Rhone-Alpes",
    "iso:country":"FR",
    "sg:address":"Les Grandes Bruy\u00e8res 69700 Chassagny",
    "sg:classifiers":[
        {
            "category":"Home & Garden",
            "subcategory":"Furniture",
            "type":"Retail Goods"
        }
    ],
    "sg:phone":"+33 4 78 48 23 83",
    "sg:postcode":"69700",
    "sg:province":"Rhone-Alpes",
    "sg:tags":[
        "household",
        "wood"
    ],
    "wof:name":"Servos Sarl",
    "wof:placetype":"venue"
},
  "geometry": {"coordinates":[4.715199,45.551682],"type":"Point"}
}