{
  "type": "Feature",
  "properties": {
    "iso:country":"FR",
    "sg:address":"Avenue Du Docteur Lefebvre 1er Cai 06270 Villeneuve Loubet",
    "sg:classifiers":[
        {
            "category":"Manufacturing",
            "subcategory":"Printing",
            "type":"Manufacturing & Wholesale Goods"
        }
    ],
    "sg:phone":"+33 4 93 73 51 01",
    "sg:province":"Provence-Alpes-C\u00f4te d'Azur",
    "sg:tags":[
        "publishing"
    ],
    "wof:name":"Euroimpression",
    "wof:placetype":"venue"
},
  "geometry": {"coordinates":[7.120123,43.646404],"type":"Point"}
}