{
  "type": "Feature",
  "properties": {
    "iso:country":"FR",
    "sg:address":"Rue Jean Monnet Hotel D Entreprises Box 2 02300 Chauny",
    "sg:classifiers":[
        {
            "category":"Manufacturing",
            "subcategory":"Leather Goods",
            "type":"Manufacturing & Wholesale Goods"
        }
    ],
    "sg:phone":"+33 3 23 38 18 94",
    "sg:postcode":"02300",
    "sg:province":"Picardie",
    "sg:tags":[
        "shoe"
    ],
    "wof:name":"Cuirs Equipements",
    "wof:placetype":"venue"
},
  "geometry": {"coordinates":[3.203075,49.601242],"type":"Point"}
}