{
  "type": "Feature",
  "properties": {
    "addr:full":"44, Rue de la Laiterie - Les Plantes , 79330 Saint Varent Poitou-Charentes 79330",
    "addr:housenumber":"44",
    "addr:postcode":"79330 saint varent;79330",
    "addr:street":"Rue De La Laiterie Les Plantes",
    "iso:country":"FR",
    "sg:address":"44, Rue de la Laiterie - Les Plantes , 79330 Saint Varent",
    "sg:orig_category":"Unclassifiable Establishments",
    "sg:phone":"+33 5 49 64 89 04",
    "sg:postcode":"79330",
    "sg:province":"Poitou-Charentes",
    "wof:name":"C.m.i. S.a.r.l. - Chaudronnerie Maintenance Industrielle",
    "wof:placetype":"venue"
},
  "geometry": {"coordinates":[-0.200911,46.857601],"type":"Point"}
}