{
  "type": "Feature",
  "properties": {
    "addr:full":"108 rue de la R\u00e9publique; Villefranche sur Sa\u00f4ne; 69657 Vill\u00e9 Alsace 67220",
    "addr:housenumber":"108",
    "addr:postcode":"69657;67220",
    "addr:street":"Rue De La Re\u0301Publique",
    "iso:country":"FR",
    "sg:address":"108 rue de la R\u00e9publique; Villefranche sur Sa\u00f4ne; 69657",
    "sg:city":"Vill\u00e9",
    "sg:classifiers":[
        {
            "category":"Banks & Credit Unions",
            "subcategory":"Bank",
            "type":"Services"
        }
    ],
    "sg:phone":"+33 4 74 62 85 60",
    "sg:postcode":"67220",
    "sg:province":"Alsace",
    "wof:name":"Banque Rh\u00f4ne-alpes",
    "wof:placetype":"venue"
},
  "geometry": {"coordinates":[4.716459,45.987839],"type":"Point"}
}