{
  "type": "Feature",
  "properties": {
    "iso:country":"FR",
    "sg:address":"B.P. 135, 89002 Auxerre C\u00e9dex^^52, Rue du Moulin du Pr\u00e9sident, 89000 Auxerre",
    "sg:city":"Auxerre",
    "sg:orig_category":"Non-Classified Establishments",
    "sg:phone":"+33 3 86 42 03 80",
    "sg:postcode":"89000",
    "sg:province":"Bourgogne",
    "wof:name":"Yonne M\u00e9canographie S.a.",
    "wof:placetype":"venue"
},
  "geometry": {"coordinates":[3.569305,47.796051],"type":"Point"}
}