{
  "type": "Feature",
  "properties": {
    "addr:full":"9 B Cr Des Petites Ecuries 75010 Paris Ile de France 75010",
    "addr:housenumber":"9 b",
    "addr:postcode":"75010;75010",
    "addr:street":"Cr Des Petites Ecuries",
    "iso:country":"FR",
    "sg:address":"9 B Cr Des Petites Ecuries 75010 Paris",
    "sg:classifiers":[
        {
            "category":"Shopping",
            "subcategory":"Clothing, Apparel, & Fashions",
            "type":"Retail Goods"
        }
    ],
    "sg:phone":"+33 1 42 46 83 66",
    "sg:postcode":"75010",
    "sg:province":"Ile de France",
    "sg:tags":[
        "textile",
        "clothing",
        "clothes"
    ],
    "wof:name":"Infinitif",
    "wof:placetype":"venue"
},
  "geometry": {"coordinates":[2.358515,48.87352],"type":"Point"}
}