{
  "type": "Feature",
  "properties": {
    "addr:full":"Rue Antoine Becquerel Narbonne Languedoc-Roussillon 11100",
    "addr:postcode":"11100",
    "addr:street":"Rue Antoine Becquerel",
    "iso:country":"FR",
    "sg:address":"Rue Antoine Becquerel",
    "sg:city":"Narbonne",
    "sg:orig_category":"Unclassifiable Establishments",
    "sg:phone":"+33 4 68 41 17 17",
    "sg:postcode":"11100",
    "sg:province":"Languedoc-Roussillon",
    "wof:name":"Stan S.a.",
    "wof:placetype":"venue"
},
  "geometry": {"coordinates":[2.975343,43.152763],"type":"Point"}
}