{
  "type": "Feature",
  "properties": {
    "iso:country":"FR",
    "sg:address":"1 ave Garibaldi; Marseille; 13001",
    "sg:classifiers":[
        {
            "category":"Banks & Credit Unions",
            "subcategory":"Bank",
            "type":"Services"
        }
    ],
    "sg:phone":"+33 4 91 92 58 54",
    "sg:province":"Poitou-Charentes",
    "wof:name":"Wafabank",
    "wof:placetype":"venue"
},
  "geometry": {"coordinates":[5.381205,43.297539],"type":"Point"}
}