{
  "type": "Feature",
  "properties": {
    "iso:country":"FR",
    "sg:address":"418, Rue Denis Papin, 54170 Ludres",
    "sg:orig_category":"Unclassifiable Establishments",
    "sg:phone":"+33 3 83 26 32 32",
    "sg:province":"Lorraine",
    "wof:name":"Alstom Drives & Controls",
    "wof:placetype":"venue"
},
  "geometry": {"coordinates":[-88.590332,44.525799],"type":"Point"}
}