{
  "type": "Feature",
  "properties": {
    "iso:country":"FR",
    "sg:address":"Le Bluizard 69460 Saint Etienne la Varenne",
    "sg:orig_category":"Unclassifiable Establishments",
    "sg:phone":"+33 4 74 03 30 90",
    "sg:province":"Rhone-Alpes",
    "wof:name":"So.fra.d.i. S.a.r.l. - Soci\u00e9t\u00e9 Fran\u00e7aise De Distribution Internationale",
    "wof:placetype":"venue"
},
  "geometry": {"coordinates":[4.620258,46.078495],"type":"Point"}
}