{
  "type": "Feature",
  "properties": {
    "iso:country":"FR",
    "sg:address":"B.P. 5, 60400 Pont l'Ev\u00eaque C\u00e9dex^^29, Rue Calvin, 60400 Pont l'Ev\u00eaque",
    "sg:orig_category":"Ajustage Ensembles m\u00e9cano-soud\u00e9s Fraisage Fraisage CN Maintenance industrielle Maintenance m\u00e9canique",
    "sg:phone":"+33 3 44 44 05 33",
    "sg:postcode":"60400",
    "sg:province":"Picardie",
    "wof:name":"Dutilloy S.a.r.l.",
    "wof:placetype":"venue"
},
  "geometry": {"coordinates":[-111.964462,46.250797],"type":"Point"}
}