{
  "type": "Feature",
  "properties": {
    "iso:country":"FR",
    "sg:address":"Varenne Grillemont 37130 Cinq Mars La Pile",
    "sg:city":"Br\u00e9h\u00e9mont",
    "sg:classifiers":[
        {
            "category":"Professional",
            "type":"Services"
        }
    ],
    "sg:phone":"+33 2 47 96 40 81",
    "sg:postcode":"37130",
    "sg:province":"Centre",
    "sg:tags":[
        "transport",
        "road"
    ],
    "wof:name":"Sarl Transport Schneider",
    "wof:placetype":"venue"
},
  "geometry": {"coordinates":[0.46651,47.348137],"type":"Point"}
}