{
  "type": "Feature",
  "properties": {
    "iso:country":"FR",
    "sg:address":"8, Rue Au Bouchet, 21000 Dijon",
    "sg:city":"Dijon",
    "sg:orig_category":"Unclassifiable Establishments",
    "sg:phone":"+33 3 80 71 14 43",
    "sg:postcode":"21000",
    "sg:province":"Bourgogne",
    "wof:name":"Construction S.a.r.l.",
    "wof:placetype":"venue"
},
  "geometry": {"coordinates":[5.079574,47.348232],"type":"Point"}
}