{
  "type": "Feature",
  "properties": {
    "addr:full":"12 Imp Fosse Rouge 77220 Presles En Brie Ile de France 77220",
    "addr:housenumber":"12",
    "addr:postcode":"77220;77220",
    "addr:street":"Imp Fosse Rouge",
    "iso:country":"FR",
    "sg:address":"12 Imp Fosse Rouge",
    "sg:city":"77220 Presles En Brie",
    "sg:classifiers":[
        {
            "category":"Wholesale",
            "subcategory":"Machinery & Supplies",
            "type":"Manufacturing & Wholesale Goods"
        }
    ],
    "sg:phone":"+33 1 64 07 88 93",
    "sg:postcode":"77220",
    "sg:province":"Ile de France",
    "sg:tags":[
        "handling",
        "material",
        "-",
        "machine",
        "equipment",
        "engineering",
        "mechanical"
    ],
    "wof:name":"Atelier De Presles Sarl",
    "wof:placetype":"venue"
},
  "geometry": {"coordinates":[2.736721,48.740906],"type":"Point"}
}