{
  "type": "Feature",
  "properties": {
    "addr:full":"11 Dugommier 75012 Paris Ile de France 75012",
    "addr:housenumber":"11",
    "addr:postcode":"75012;75012",
    "addr:street":"Dugommier",
    "iso:country":"FR",
    "sg:address":"11",
    "sg:city":"Dugommier 75012 Paris",
    "sg:orig_category":"Miscellaneous Products",
    "sg:phone":"+33 1 43 45 62 63",
    "sg:postcode":"75012",
    "sg:province":"Ile de France",
    "wof:name":"C.f.i",
    "wof:placetype":"venue"
},
  "geometry": {"coordinates":[2.390901,48.839821],"type":"Point"}
}