{
  "type": "Feature",
  "properties": {
    "iso:country":"FR",
    "sg:address":"Route Rn 113 33720 PODENSAC",
    "sg:city":"Podensac",
    "sg:classifiers":[
        {
            "category":"Utilities",
            "subcategory":"Electric",
            "type":"Services"
        }
    ],
    "sg:phone":"+33 5 57 98 00 50",
    "sg:postcode":"33720",
    "sg:province":"Aquitaine",
    "sg:tags":[
        "drive"
    ],
    "wof:name":"2h Energie S.a.",
    "wof:placetype":"venue"
},
  "geometry": {"coordinates":[-0.385279,44.533298],"type":"Point"}
}