{
  "type": "Feature",
  "properties": {
    "iso:country":"FR",
    "sg:address":"B.P. 39, 84231 Ch\u00e2teauneuf du Pape C\u00e9dex^^Rte de Courth\u00e9zon, 84230 Ch\u00e2teauneuf du Pape",
    "sg:city":"Ch\u00e2teau",
    "sg:orig_category":"Non-Classified Establishments",
    "sg:phone":"+33 4 90 83 72 52",
    "sg:postcode":"71250",
    "sg:province":"Bourgogne",
    "wof:name":"Domaine De Nalys",
    "wof:placetype":"venue"
},
  "geometry": {"coordinates":[4.835999,44.049744],"type":"Point"}
}