{
  "type": "Feature",
  "properties": {
    "addr:full":"4 Pl Du Village 92632 Geneviliers Pays de Loire",
    "addr:housenumber":"4",
    "addr:postcode":"92632",
    "addr:street":"Pl Du Village;Geneviliers",
    "iso:country":"FR",
    "sg:address":"4 Pl Du Village 92632 Geneviliers",
    "sg:classifiers":[
        {
            "category":"Professional",
            "subcategory":"Printing & Photocopies",
            "type":"Services"
        }
    ],
    "sg:phone":"+33 1 41 47 70 00",
    "sg:province":"Pays de Loire",
    "sg:tags":[
        "machine",
        "engineering",
        "-",
        "mechanical"
    ],
    "wof:name":"Mc Imaging Sa",
    "wof:placetype":"venue"
},
  "geometry": {"coordinates":[2.29927,48.933479],"type":"Point"}
}