{
  "type": "Feature",
  "properties": {
    "addr:full":"RN 140 Boisse Penchot Midi Pyr\u00e9n\u00e9es 12300",
    "addr:postcode":"12300",
    "addr:street":"Rn 140 Boisse Penchot Midi Pyre\u0301Ne\u0301Es",
    "iso:country":"FR",
    "sg:address":"RN 140",
    "sg:city":"Boisse Penchot",
    "sg:orig_category":"Unclassifiable Establishments",
    "sg:phone":"+33 5 65 43 77 00",
    "sg:postcode":"12300",
    "sg:province":"Midi Pyr\u00e9n\u00e9es",
    "wof:name":"S.e.t.c.m. S.a.",
    "wof:placetype":"venue"
},
  "geometry": {"coordinates":[2.307615,44.541191],"type":"Point"}
}