{
  "type": "Feature",
  "properties": {
    "addr:full":"261, Rue Saint Denis, 75002 Paris Ile de France",
    "addr:housenumber":"261",
    "addr:postcode":"75002",
    "addr:street":"Rue Saint Denis",
    "iso:country":"FR",
    "sg:address":"261, Rue Saint Denis, 75002 Paris",
    "sg:orig_category":"Non-Classified Establishments",
    "sg:phone":"+33 1 42 33 56 01",
    "sg:province":"Ile de France",
    "wof:name":"Roseline Cr\u00e9ations S.a.r.l.",
    "wof:placetype":"venue"
},
  "geometry": {"coordinates":[2.351736,48.868286],"type":"Point"}
}