{
  "type": "Feature",
  "properties": {
    "addr:full":"10, Rue Jacques Maritain - ZAC Val de Murigny, 51100 Reims Champagne",
    "addr:housenumber":"10",
    "addr:postcode":"51100",
    "addr:street":"Rue Jacques Maritain Zac Val De Murigny",
    "iso:country":"FR",
    "sg:address":"10, Rue Jacques Maritain - ZAC Val de Murigny, 51100 Reims",
    "sg:orig_category":"Non-Classified Establishments",
    "sg:phone":"+33 3 26 83 88 00",
    "sg:province":"Champagne",
    "wof:name":"L'article Publicitaire S.a.r.l.",
    "wof:placetype":"venue"
},
  "geometry": {"coordinates":[4.024409,49.218361],"type":"Point"}
}