{
  "type": "Feature",
  "properties": {
    "iso:country":"FR",
    "sg:address":"10, Rue Jules Ferry, 92300 Levallois Perret",
    "sg:orig_category":"Unclassifiable Establishments",
    "sg:phone":"+33 1 47 31 69 55",
    "sg:province":"Ile de France",
    "wof:name":"D'arcy International S.a.r.l.",
    "wof:placetype":"venue"
},
  "geometry": {"coordinates":[2.29336,48.894146],"type":"Point"}
}