{
  "type": "Feature",
  "properties": {
    "addr:full":"140, Av. du Mar\u00e9chal Leclerc, 33130 B\u00e8gles B\u00e8gles Aquitaine 33130",
    "addr:postcode":"33130;33130",
    "addr:street":"140 Av. Du Mare\u0301Chal Leclerc",
    "iso:country":"FR",
    "sg:address":"140, Av. du Mar\u00e9chal Leclerc, 33130 B\u00e8gles",
    "sg:city":"B\u00e8gles",
    "sg:orig_category":"Unclassifiable Establishments",
    "sg:phone":"+33 5 56 85 96 32",
    "sg:postcode":"33130",
    "sg:province":"Aquitaine",
    "wof:name":"Cogifer Tf",
    "wof:placetype":"venue"
},
  "geometry": {"coordinates":[-0.541323,44.812031],"type":"Point"}
}