{
  "type": "Feature",
  "properties": {
    "iso:country":"FR",
    "sg:address":"68 boulevard Gallieni 92130 Issy les Moulineaux",
    "sg:orig_category":"Paperboard For Files",
    "sg:phone":"+33 1 46 44 23 00",
    "sg:province":"Ile de France",
    "wof:name":"Organisation Classement Equipement Bureau Sa",
    "wof:placetype":"venue"
},
  "geometry": {"coordinates":[2.267334,48.82756],"type":"Point"}
}