{
  "type": "Feature",
  "properties": {
    "addr:full":"92 boulevard de Port Royal 75005 Paris Ile de France 75005",
    "addr:housenumber":"92",
    "addr:postcode":"75005;75005",
    "addr:street":"Boulevard De Port Royal",
    "iso:country":"FR",
    "sg:address":"92 boulevard de Port Royal 75005 Paris",
    "sg:classifiers":[
        {
            "category":"Banks & Credit Unions",
            "subcategory":"Atm",
            "type":"Services"
        }
    ],
    "sg:phone":"+33 1 43 25 41 37",
    "sg:postcode":"75005",
    "sg:province":"Ile de France",
    "sg:tags":[
        "miscellaneous",
        "devices",
        "microelectronic"
    ],
    "wof:name":"M C T S.a.r.l.",
    "wof:placetype":"venue"
},
  "geometry": {"coordinates":[2.338105,48.839466],"type":"Point"}
}