{
  "type": "Feature",
  "properties": {
    "iso:country":"FR",
    "sg:address":"29, Rue de Marignan, 75008 Paris",
    "sg:orig_category":"Non-Classified Establishments",
    "sg:phone":"+33 1 42 89 25 52",
    "sg:province":"Ile de France",
    "wof:name":"Jacques Albert S.a.r.l.",
    "wof:placetype":"venue"
},
  "geometry": {"coordinates":[2.306423,48.87001],"type":"Point"}
}