{
  "type": "Feature",
  "properties": {
    "iso:country":"FR",
    "sg:address":"10, Rue du Pillier, 93300 Aubervilliers",
    "sg:orig_category":"Unclassifiable Establishments",
    "sg:phone":"+33 1 53 56 13 93",
    "sg:province":"Ile de France",
    "wof:name":"S.a.d. S.a. - Soci\u00e9t\u00e9 Alcools D\u00e9natur\u00e9s",
    "wof:placetype":"venue"
},
  "geometry": {"coordinates":[2.368754,48.908363],"type":"Point"}
}