{
  "type": "Feature",
  "properties": {
    "addr:full":"11 avenue de Friedland 75008 Paris Ile de France 75008",
    "addr:housenumber":"11",
    "addr:postcode":"75008;75008",
    "addr:street":"Avenue De Friedland",
    "iso:country":"FR",
    "sg:address":"11 avenue de Friedland 75008 Paris",
    "sg:classifiers":[
        {
            "category":"Education",
            "subcategory":"Special Training",
            "type":"Public Place"
        }
    ],
    "sg:phone":"+33 1 49 53 90 38",
    "sg:postcode":"75008",
    "sg:province":"Ile de France",
    "sg:tags":[
        "credit",
        "interim",
        "sale"
    ],
    "wof:name":"Olympia Capital Services S.a.r.l.",
    "wof:placetype":"venue"
},
  "geometry": {"coordinates":[2.303522,48.874496],"type":"Point"}
}