{
  "type": "Feature",
  "properties": {
    "iso:country":"FR",
    "sg:address":"ZA",
    "sg:city":"Corbi\u00e8res",
    "sg:orig_category":"Unclassifiable Establishments",
    "sg:phone":"+33 4 92 79 75 76",
    "sg:postcode":"04220",
    "sg:province":"Provence-Alpes-C\u00f4te d'Azur",
    "wof:name":"R.i.p. S.a.r.l. - R\u00e9alisation Industrielle De Provence",
    "wof:placetype":"venue"
},
  "geometry": {"coordinates":[5.76545,43.778259],"type":"Point"}
}