{
  "type": "Feature",
  "properties": {
    "iso:country":"FR",
    "sg:address":"119 Av Gambetta 17100 Saintes",
    "sg:classifiers":[
        {
            "category":"Professional",
            "subcategory":"Computer Services",
            "type":"Services"
        }
    ],
    "sg:phone":"+33 5 46 74 12 25",
    "sg:postcode":"17100",
    "sg:province":"Poitou-Charentes",
    "sg:tags":[
        "information",
        "technology",
        "software"
    ],
    "wof:name":"Centre Ouest Informatique Sarl",
    "wof:placetype":"venue"
},
  "geometry": {"coordinates":[-0.622285,45.746723],"type":"Point"}
}