{
  "type": "Feature",
  "properties": {
    "iso:country":"FR",
    "sg:address":"ZI - La Plage Sud",
    "sg:city":"Quillan",
    "sg:orig_category":"Non-Classified Establishments",
    "sg:phone":"+33 4 68 20 12 27",
    "sg:postcode":"11500",
    "sg:province":"Languedoc-Roussillon",
    "wof:name":"M\u00e9cadeq S.a.r.l.",
    "wof:placetype":"venue"
},
  "geometry": {"coordinates":[2.182374,42.87534],"type":"Point"}
}