{
  "type": "Feature",
  "properties": {
    "addr:full":"B.P. 311 Mont Saint Aignan C\u00e9dex Midi Pyr\u00e9n\u00e9es 76136",
    "addr:housenumber":"b.p. 311",
    "addr:postcode":"76136",
    "iso:country":"FR",
    "sg:address":"B.P. 311",
    "sg:city":"Mont Saint Aignan C\u00e9dex",
    "sg:orig_category":"Non-Classified Establishments",
    "sg:phone":"+33 2 35 59 62 50",
    "sg:postcode":"76136",
    "sg:province":"Midi Pyr\u00e9n\u00e9es",
    "wof:name":"Corame S.a.",
    "wof:placetype":"venue"
},
  "geometry": {"coordinates":[1.070859,49.46204],"type":"Point"}
}