{
  "type": "Feature",
  "properties": {
    "addr:full":"Rue des Bois Torfou Pays de Loire 49660",
    "addr:postcode":"49660",
    "addr:street":"Rue Des Bois",
    "iso:country":"FR",
    "sg:address":"Rue des Bois",
    "sg:city":"Torfou",
    "sg:orig_category":"Unclassifiable Establishments",
    "sg:phone":"+33 2 41 49 18 49",
    "sg:postcode":"49660",
    "sg:province":"Pays de Loire",
    "wof:name":"Etablissements Michel Guinaudeau S.a.",
    "wof:placetype":"venue"
},
  "geometry": {"coordinates":[-1.107959,47.037224],"type":"Point"}
}