{
  "type": "Feature",
  "properties": {
    "addr:full":"Ruols 12450 Luc Midi Pyr\u00e9n\u00e9es",
    "addr:postcode":"12450",
    "addr:street":"Ruols",
    "iso:country":"FR",
    "sg:address":"Ruols 12450 Luc",
    "sg:orig_category":"Unclassifiable Establishments",
    "sg:phone":"+33 5 65 69 52 28",
    "sg:province":"Midi Pyr\u00e9n\u00e9es",
    "wof:name":"S.a.t. S.a.r.l.",
    "wof:placetype":"venue"
},
  "geometry": {"coordinates":[2.50877,44.325588],"type":"Point"}
}