{
  "type": "Feature",
  "properties": {
    "addr:full":"200, Rue Gabriel Voisin, 69400 Villefranche sur Sa\u00f4ne Rhone-Alpes",
    "addr:housenumber":"200",
    "addr:postcode":"69400;sur sao\u0302ne rhone-alpes",
    "addr:street":"Rue Gabriel Voisin",
    "iso:country":"FR",
    "sg:address":"200, Rue Gabriel Voisin, 69400 Villefranche sur Sa\u00f4ne",
    "sg:orig_category":"Unclassifiable Establishments",
    "sg:phone":"+33 4 74 65 95 64",
    "sg:province":"Rhone-Alpes",
    "wof:name":"Cayon Levage S.a.",
    "wof:placetype":"venue"
},
  "geometry": {"coordinates":[4.741743,45.978458],"type":"Point"}
}