{
  "type": "Feature",
  "properties": {
    "addr:full":"25, Rue des Artisans - ZAC, 86200 Loudun Poitou-Charentes",
    "addr:housenumber":"25",
    "addr:postcode":"86200",
    "addr:street":"Rue Des Artisans Zac",
    "iso:country":"FR",
    "sg:address":"25, Rue des Artisans - ZAC, 86200 Loudun",
    "sg:orig_category":"Unclassifiable Establishments",
    "sg:phone":"+33 5 49 98 33 26",
    "sg:province":"Poitou-Charentes",
    "wof:name":"Transports Chauveau",
    "wof:placetype":"venue"
},
  "geometry": {"coordinates":[0.156242,46.958393],"type":"Point"}
}