{
  "type": "Feature",
  "properties": {
    "addr:full":"80, Rue Gallieni, 92773 Boulogne Billancourt C\u00e9dex Ancourt Haute Normandie 76370",
    "addr:housenumber":"80",
    "addr:postcode":"92773;76370",
    "addr:street":"Rue Gallieni;Haute Normandie",
    "iso:country":"FR",
    "sg:address":"80, Rue Gallieni, 92773 Boulogne Billancourt C\u00e9dex",
    "sg:city":"Ancourt",
    "sg:orig_category":"Non-Classified Establishments",
    "sg:phone":"+33 1 47 12 53 00",
    "sg:postcode":"76370",
    "sg:province":"Haute Normandie",
    "wof:name":"C.m. International S.a.",
    "wof:placetype":"venue"
},
  "geometry": {"coordinates":[2.24347,48.83382],"type":"Point"}
}