{
  "type": "Feature",
  "properties": {
    "addr:full":"Parc d'Affaires de la Vall\u00e9e de l'Ozon - Le Chapotin Chaponnay Rhone-Alpes 69970",
    "addr:postcode":"69970",
    "addr:street":"Valle\u0301E",
    "iso:country":"FR",
    "sg:address":"Parc d'Affaires de la Vall\u00e9e de l'Ozon - Le Chapotin",
    "sg:city":"Chaponnay",
    "sg:orig_category":"Non-Classified Establishments",
    "sg:phone":"+33 4 78 96 73 29",
    "sg:postcode":"69970",
    "sg:province":"Rhone-Alpes",
    "wof:name":"Biesse Groupe France S.a.r.l.",
    "wof:placetype":"venue"
},
  "geometry": {"coordinates":[4.932609,45.638103],"type":"Point"}
}