{
  "type": "Feature",
  "properties": {
    "iso:country":"FR",
    "sg:address":"Parc d'Activit\u00e9s la Mongie - ZI",
    "sg:city":"Les Essarts",
    "sg:orig_category":"Unclassifiable Establishments",
    "sg:phone":"+33 2 51 48 42 40",
    "sg:postcode":"85140",
    "sg:province":"Pays de Loire",
    "wof:name":"I.d.e.m. 85 S.a.r.l. - Insertin Et D\u00e9veloppement De L'emploi",
    "wof:placetype":"venue"
},
  "geometry": {"coordinates":[-1.228,46.773129],"type":"Point"}
}