{
  "type": "Feature",
  "properties": {
    "addr:full":"B.P. 13 Le Creusot Bourgogne 71200",
    "addr:housenumber":"13",
    "addr:postcode":"71200",
    "addr:street":"B.P.",
    "iso:country":"FR",
    "sg:address":"B.P. 13",
    "sg:city":"Le Creusot",
    "sg:orig_category":"Non-Classified Establishments",
    "sg:phone":"+33 3 85 80 62 62",
    "sg:postcode":"71200",
    "sg:province":"Bourgogne",
    "wof:name":"N.f.m. Technologies S.a.",
    "wof:placetype":"venue"
},
  "geometry": {"coordinates":[4.421295,46.806164],"type":"Point"}
}