{
  "type": "Feature",
  "properties": {
    "iso:country":"FR",
    "sg:address":"Rue Des Fr\u00e8res Lumi\u00e8re Zi La Mouline 33560 Carbon Blanc",
    "sg:city":"Carbon-Blanc",
    "sg:classifiers":[
        {
            "category":"Manufacturing",
            "subcategory":"Chemicals & Compounds",
            "type":"Manufacturing & Wholesale Goods"
        }
    ],
    "sg:phone":"+33 5 57 77 87 47",
    "sg:postcode":"33560",
    "sg:province":"Aquitaine",
    "sg:tags":[
        "pharmaceutical",
        "chemistry",
        "-",
        "by-product"
    ],
    "wof:name":"Messer France",
    "wof:placetype":"venue"
},
  "geometry": {"coordinates":[-0.473724,44.908085],"type":"Point"}
}