{
  "type": "Feature",
  "properties": {
    "addr:full":"Rue Sainte Blaise - ZA Sabl\u00e9 sur Sarthe Pays de Loire 72300",
    "addr:postcode":"72300",
    "addr:street":"Rue Sainte Blaise Za Sable\u0301;Sarthe Pays;Loire",
    "iso:country":"FR",
    "sg:address":"Rue Sainte Blaise - ZA",
    "sg:city":"Sabl\u00e9 sur Sarthe",
    "sg:orig_category":"Unclassifiable Establishments",
    "sg:phone":"+33 2 43 62 07 07",
    "sg:postcode":"72300",
    "sg:province":"Pays de Loire",
    "wof:name":"Satelec Industrie S.a.",
    "wof:placetype":"venue"
},
  "geometry": {"coordinates":[-0.326529,47.731071],"type":"Point"}
}