{
  "type": "Feature",
  "properties": {
    "addr:full":"4\u00e8me Boulevard - B\u00e2t. E : ABC 3 Archamps Rhone-Alpes 74160",
    "addr:housenumber":"3",
    "addr:postcode":"74160",
    "addr:street":"4E\u0300Me Boulevard Ba\u0302T;Abc;Rhone-Alpes",
    "iso:country":"FR",
    "sg:address":"4\u00e8me Boulevard - B\u00e2t. E : ABC 3",
    "sg:city":"Archamps",
    "sg:orig_category":"Unclassifiable Establishments",
    "sg:phone":"+33 4 50 43 29 80",
    "sg:postcode":"74160",
    "sg:province":"Rhone-Alpes",
    "wof:name":"Sodeco Bureautique S.a.r.l.",
    "wof:placetype":"venue"
},
  "geometry": {"coordinates":[6.031919,46.088573],"type":"Point"}
}