{
  "type": "Feature",
  "properties": {
    "iso:country":"FR",
    "sg:address":"Za Les Tuileries Za Les Tuileries 81140 Cahuzac Sur Vere",
    "sg:classifiers":[
        {
            "category":"Professional",
            "subcategory":"Printing & Photocopies",
            "type":"Services"
        }
    ],
    "sg:phone":"+33 5 63 33 92 02",
    "sg:province":"Midi Pyr\u00e9n\u00e9es",
    "sg:tags":[
        "publishing"
    ],
    "wof:name":"Le Materiel Scolaire Masco Map",
    "wof:placetype":"venue"
},
  "geometry": {"coordinates":[1.91103,43.983067],"type":"Point"}
}