{
  "type": "Feature",
  "properties": {
    "addr:full":"41 Bd De La Prairie Au Duc 44200 Nantes Pays de Loire",
    "addr:housenumber":"41",
    "addr:postcode":"44200",
    "addr:street":"Bd De La Prairie Au Duc",
    "iso:country":"FR",
    "sg:address":"41 Bd De La Prairie Au Duc 44200 Nantes",
    "sg:classifiers":[
        {
            "category":"Professional",
            "type":"Services"
        }
    ],
    "sg:phone":"+33 2 40 35 25 00",
    "sg:province":"Pays de Loire",
    "sg:tags":[
        "transport",
        "road"
    ],
    "wof:name":"Transports Rapides Joyau (trj)",
    "wof:placetype":"venue"
},
  "geometry": {"coordinates":[-1.562134,47.204407],"type":"Point"}
}