{
  "type": "Feature",
  "properties": {
    "addr:full":"Rue Bac 12100 Millau Midi Pyr\u00e9n\u00e9es 12100",
    "addr:postcode":"12100;12100",
    "addr:street":"Rue Bac",
    "iso:country":"FR",
    "sg:address":"Rue Bac 12100 Millau",
    "sg:classifiers":[
        {
            "category":"Real Estate",
            "subcategory":"Surveying",
            "type":"Services"
        }
    ],
    "sg:phone":"+33 5 65 60 50 20",
    "sg:postcode":"12100",
    "sg:province":"Midi Pyr\u00e9n\u00e9es",
    "sg:tags":[
        "leather",
        "raw",
        "material",
        "-",
        "shoe"
    ],
    "wof:name":"Tanneries Nouvelles Pechdo Sa",
    "wof:placetype":"venue"
},
  "geometry": {"coordinates":[2.98414,44.063969],"type":"Point"}
}