{
  "type": "Feature",
  "properties": {
    "addr:full":"1208, Rte des Lucioles - Espace Beethoven - B\u00e2t. 2, 06902 Sophia Antipolis C\u00e9dex Connecticut",
    "addr:housenumber":"1208;ba\u0302t;06902",
    "addr:street":"Rte Des Lucioles Espace Beethoven",
    "iso:country":"FR",
    "sg:address":"1208, Rte des Lucioles - Espace Beethoven - B\u00e2t. 2, 06902 Sophia Antipolis C\u00e9dex",
    "sg:orig_category":"Non-Classified Establishments",
    "sg:phone":"+33 4 93 00 40 30",
    "sg:province":"Connecticut",
    "wof:name":"W.h. & P. S.a.r.l. - Weguitz H\u00f6ser & Partners",
    "wof:placetype":"venue"
},
  "geometry": {"coordinates":[-73.544983,41.060089],"type":"Point"}
}