{
  "type": "Feature",
  "properties": {
    "iso:country":"FR",
    "sg:address":"2 Rue De Chantecouriol 26000 Valence",
    "sg:classifiers":[
        {
            "category":"Food & Beverages",
            "subcategory":"Fruits & Vegetables",
            "type":"Retail Goods"
        }
    ],
    "sg:phone":"+33 4 75 41 87 50",
    "sg:postcode":"26000",
    "sg:province":"Rhone-Alpes",
    "sg:tags":[
        "frozen",
        "product",
        "related"
    ],
    "wof:name":"Les Vergers Boiron Production",
    "wof:placetype":"venue"
},
  "geometry": {"coordinates":[4.879409,44.903221],"type":"Point"}
}