{
  "type": "Feature",
  "properties": {
    "iso:country":"FR",
    "sg:address":"40, Av. de Hambourg - Immeuble Borely B\u00e2t DE 8, 13008 Marseille",
    "sg:orig_category":"Non-Classified Establishments",
    "sg:phone":"+33 4 91 29 15 15",
    "sg:province":"Poitou-Charentes",
    "wof:name":"Phone Marketing S.a.",
    "wof:placetype":"venue"
},
  "geometry": {"coordinates":[9.99244,53.553341],"type":"Point"}
}