{
  "type": "Feature",
  "properties": {
    "addr:full":"26, Rue Serpollet, 75020 Paris Ile de France",
    "addr:housenumber":"26",
    "addr:postcode":"75020",
    "addr:street":"Rue Serpollet",
    "iso:country":"FR",
    "sg:address":"26, Rue Serpollet, 75020 Paris",
    "sg:orig_category":"Non-Classified Establishments",
    "sg:phone":"+33 1 40 31 60 20",
    "sg:province":"Ile de France",
    "wof:name":"Prothia S.a.r.l.",
    "wof:placetype":"venue"
},
  "geometry": {"coordinates":[2.412107,48.860744],"type":"Point"}
}