{
  "type": "Feature",
  "properties": {
    "addr:full":"11119, Rte Vignettaz, 74800 Cornier Rhone-Alpes 74800",
    "addr:housenumber":"11119",
    "addr:postcode":"74800;74800",
    "addr:street":"Rte Vignettaz",
    "iso:country":"FR",
    "sg:address":"11119, Rte Vignettaz, 74800 Cornier",
    "sg:orig_category":"Unclassifiable Establishments",
    "sg:phone":"+33 4 50 03 05 25",
    "sg:postcode":"74800",
    "sg:province":"Rhone-Alpes",
    "wof:name":"D\u00e9co Cornier S.a.r.l.",
    "wof:placetype":"venue"
},
  "geometry": {"coordinates":[6.299795,46.092758],"type":"Point"}
}