{
  "type": "Feature",
  "properties": {
    "addr:full":"5 Rue Cambon 75001 Paris Ile de France 75001",
    "addr:housenumber":"5",
    "addr:postcode":"75001;75001",
    "addr:street":"Rue Cambon",
    "iso:country":"FR",
    "sg:address":"5 Rue Cambon 75001 Paris",
    "sg:classifiers":[
        {
            "category":"Travel",
            "subcategory":"Hotels & Motels",
            "type":"Entertainment"
        }
    ],
    "sg:phone":"+33 1 42 60 38 89",
    "sg:postcode":"75001",
    "sg:province":"Ile de France",
    "sg:tags":[
        "hotels",
        "business",
        "restaurant"
    ],
    "wof:name":"Hotel Residence La Concorde",
    "wof:placetype":"venue"
},
  "geometry": {"coordinates":[2.32523,48.866585],"type":"Point"}
}