{
  "type": "Feature",
  "properties": {
    "addr:full":"2, Rue Louis Aimand - Hall 3, 92600 Asni\u00e8res sur Seine Ile de France",
    "addr:housenumber":"2;3",
    "addr:postcode":"92600",
    "addr:street":"Rue Louis Aimand",
    "iso:country":"FR",
    "sg:address":"2, Rue Louis Aimand - Hall 3, 92600 Asni\u00e8res sur Seine",
    "sg:orig_category":"Unclassifiable Establishments",
    "sg:phone":"+33 1 41 11 88 44",
    "sg:province":"Ile de France",
    "wof:name":"Azur Net",
    "wof:placetype":"venue"
},
  "geometry": {"coordinates":[2.289035,48.910294],"type":"Point"}
}