{
  "type": "Feature",
  "properties": {
    "addr:full":"Parc d'Activit\u00e9s du Puits d'Ordet Challes les Eaux Rhone-Alpes 73190",
    "addr:postcode":"73190",
    "iso:country":"FR",
    "sg:address":"Parc d'Activit\u00e9s du Puits d'Ordet",
    "sg:city":"Challes les Eaux",
    "sg:orig_category":"Non-Classified Establishments",
    "sg:phone":"+33 4 79 72 71 74",
    "sg:postcode":"73190",
    "sg:province":"Rhone-Alpes",
    "wof:name":"H. + M. Eloquence S.a.",
    "wof:placetype":"venue"
},
  "geometry": {"coordinates":[5.974675,45.555035],"type":"Point"}
}