{
  "type": "Feature",
  "properties": {
    "iso:country":"FR",
    "sg:address":"Le Becquet 79800 Pamproux",
    "sg:orig_category":"Unclassifiable Establishments",
    "sg:phone":"+33 5 49 76 30 09",
    "sg:postcode":"79800",
    "sg:province":"Poitou-Charentes",
    "wof:name":"Etablissement Bonargent-goyon",
    "wof:placetype":"venue"
},
  "geometry": {"coordinates":[-0.049243,46.400818],"type":"Point"}
}