{
  "type": "Feature",
  "properties": {
    "iso:country":"FR",
    "sg:address":"rue de Siltzheim 57200 Remelfing",
    "sg:classifiers":[
        {
            "category":"Banks & Credit Unions",
            "subcategory":"Bureau De Change",
            "type":"Services"
        }
    ],
    "sg:phone":"+33 3 87 98 72 00",
    "sg:postcode":"57200",
    "sg:province":"Lorraine",
    "sg:tags":[
        "decoration",
        "accessory"
    ],
    "wof:name":"Ste D'articles De Decoration Sarl",
    "wof:placetype":"venue"
},
  "geometry": {"coordinates":[7.080439,49.096157],"type":"Point"}
}