{
  "type": "Feature",
  "properties": {
    "addr:full":"rue Claude Brosse 42140 CHAZELLES SUR LYON Rhone-Alpes 42140",
    "addr:postcode":"42140;42140",
    "addr:street":"Rue Claude Brosse",
    "iso:country":"FR",
    "sg:address":"rue Claude Brosse 42140 CHAZELLES SUR LYON",
    "sg:classifiers":[
        {
            "category":"Manufacturing",
            "subcategory":"Building Materials",
            "type":"Manufacturing & Wholesale Goods"
        }
    ],
    "sg:phone":"+33 4 77 54 21 91",
    "sg:postcode":"42140",
    "sg:province":"Rhone-Alpes",
    "sg:tags":[
        "insulation",
        "materials",
        "high-temperature",
        "non-fibrous"
    ],
    "wof:name":"Isolation Et Techniques Isotec Sas",
    "wof:placetype":"venue"
},
  "geometry": {"coordinates":[4.378865,45.637524],"type":"Point"}
}