{
  "type": "Feature",
  "properties": {
    "addr:full":"Mairie 03170 Doyet Doyet Auvergne 03170",
    "addr:postcode":"03170;doyet;03170",
    "iso:country":"FR",
    "sg:address":"Mairie 03170 Doyet",
    "sg:city":"Doyet",
    "sg:classifiers":[
        {
            "category":"Utilities",
            "type":"Services"
        }
    ],
    "sg:phone":"+33 4 70 07 70 52",
    "sg:postcode":"03170",
    "sg:province":"Auvergne",
    "sg:tags":[
        "raw",
        "energy",
        "material"
    ],
    "wof:name":"Synd Intercom Alim Eau Potable De La Region Miniere (siaep)",
    "wof:placetype":"venue"
},
  "geometry": {"coordinates":[2.766323,46.347267],"type":"Point"}
}