{
  "type": "Feature",
  "properties": {
    "iso:country":"FR",
    "sg:address":"Les Jonchets 71118 Saint Martin Belle Roche",
    "sg:city":"Saint-Martin-Belle-Roche",
    "sg:orig_category":"Unclassifiable Establishments",
    "sg:phone":"+33 3 85 37 59 79",
    "sg:postcode":"71118",
    "sg:province":"Bourgogne",
    "wof:name":"Bouquerod Alimentaire S.a.",
    "wof:placetype":"venue"
},
  "geometry": {"coordinates":[4.85656,46.384026],"type":"Point"}
}