{
  "type": "Feature",
  "properties": {
    "addr:full":"2040, Saint Bernard - ZAC Sophia Antipolis, 06220 Vallauris Provence-Alpes-C\u00f4te d'Azur",
    "addr:housenumber":"2040",
    "addr:postcode":"06220",
    "addr:street":"Saint;Zac Sophia Antipolis",
    "iso:country":"FR",
    "sg:address":"2040, Saint Bernard - ZAC Sophia Antipolis, 06220 Vallauris",
    "sg:orig_category":"Non-Classified Establishments",
    "sg:phone":"+33 4 93 65 22 65",
    "sg:province":"Provence-Alpes-C\u00f4te d'Azur",
    "wof:name":"Pro-tech S\u00e9curit\u00e9 S.a.r.l.",
    "wof:placetype":"venue"
},
  "geometry": {"coordinates":[7.060788,43.573296],"type":"Point"}
}