{
  "type": "Feature",
  "properties": {
    "iso:country":"FR",
    "sg:address":"7, Rue du Chesnay Beauregard, 35760 Saint Gr\u00e9goire",
    "sg:city":"Montgermont",
    "sg:orig_category":"Unclassifiable Establishments",
    "sg:phone":"+33 2 99 84 51 50",
    "sg:postcode":"35760",
    "sg:province":"Bretagne",
    "wof:name":"Delourmel B.m. Motoculture S.a.s.",
    "wof:placetype":"venue"
},
  "geometry": {"coordinates":[-1.690513,48.137127],"type":"Point"}
}