{
  "type": "Feature",
  "properties": {
    "iso:country":"FR",
    "sg:address":"B.P. 262, 76137 Mont Saint Aignan C\u00e9dex^^16, Rue Pierre Gilles de Gennes, 76130 Mont Saint Aignan",
    "sg:orig_category":"Non-Classified Establishments",
    "sg:phone":"+33 2 35 12 21 80",
    "sg:province":"Haute Normandie",
    "wof:name":"Ugine Savoie France S.a.",
    "wof:placetype":"venue"
},
  "geometry": {"coordinates":[1.089561,49.473732],"type":"Point"}
}