{
  "type": "Feature",
  "properties": {
    "iso:country":"FR",
    "sg:address":"7",
    "sg:city":"Guerin; La Ciotat; 13600",
    "sg:classifiers":[
        {
            "category":"Banks & Credit Unions",
            "subcategory":"Bank",
            "type":"Services"
        }
    ],
    "sg:phone":"+33 3342084040",
    "sg:province":"Nord Pas-de-Calais",
    "wof:name":"Soci\u00e9t\u00e9 Marseillaise De Cr\u00e9dit",
    "wof:placetype":"venue"
},
  "geometry": {"coordinates":[5.605577,43.174072],"type":"Point"}
}