{
  "type": "Feature",
  "properties": {
    "iso:country":"FR",
    "sg:address":"B.P. 135, 90003 Belfort C\u00e9dex^^5, Rue Dauphin, 90000 Belfort",
    "sg:orig_category":"Non-Classified Establishments",
    "sg:phone":"+33 3 84 46 67 00",
    "sg:postcode":"90000",
    "sg:province":"Franche Comt\u00e9",
    "wof:name":"Autodistribution Colard S.a.",
    "wof:placetype":"venue"
},
  "geometry": {"coordinates":[6.863753,47.639225],"type":"Point"}
}