{
  "type": "Feature",
  "properties": {
    "iso:country":"FR",
    "sg:address":"Les Triol\u00e8res Basses 63670 La Roche Blanche",
    "sg:city":"Le Cendre",
    "sg:orig_category":"Non-Classified Establishments",
    "sg:phone":"+33 4 73 79 13 08",
    "sg:postcode":"63670",
    "sg:province":"Auvergne",
    "wof:name":"Vigilec Pauly",
    "wof:placetype":"venue"
},
  "geometry": {"coordinates":[3.129955,45.704155],"type":"Point"}
}