{
  "type": "Feature",
  "properties": {
    "addr:full":"31440 Cierp Gaud Midi Pyr\u00e9n\u00e9es 31440",
    "addr:postcode":"31440;31440",
    "iso:country":"FR",
    "sg:address":"31440 Cierp Gaud",
    "sg:classifiers":[
        {
            "category":"Utilities",
            "subcategory":"Electric",
            "type":"Services"
        }
    ],
    "sg:phone":"+33 5 61 79 12 58",
    "sg:postcode":"31440",
    "sg:province":"Midi Pyr\u00e9n\u00e9es",
    "sg:tags":[
        "electricity",
        "raw",
        "energy",
        "material"
    ],
    "wof:name":"Electricite De France (edf)",
    "wof:placetype":"venue"
},
  "geometry": {"coordinates":[0.639283,42.914906],"type":"Point"}
}