{
  "type": "Feature",
  "properties": {
    "iso:country":"FR",
    "sg:address":"15 rue de Brazza 92800 Puteaux",
    "sg:classifiers":[
        {
            "category":"Utilities",
            "subcategory":"Sewage",
            "type":"Services"
        }
    ],
    "sg:phone":"+33 1 47 78 78 30",
    "sg:province":"Ile de France",
    "sg:tags":[
        "water",
        "conditioning",
        "treatment"
    ],
    "wof:name":"Hydromeca S.a.r.l.",
    "wof:placetype":"venue"
},
  "geometry": {"coordinates":[2.236027,48.885899],"type":"Point"}
}