{
  "type": "Feature",
  "properties": {
    "addr:full":"B.P. 247, 56602 Lanester C\u00e9dex^^148, Rue L\u00e9on Foucault, 56600 Lanester Lanester Bretagne 56600",
    "addr:housenumber":"b.p. 247",
    "addr:postcode":"56602;56600;56600",
    "addr:street":"Rue Le\u0301On Foucault",
    "iso:country":"FR",
    "sg:address":"B.P. 247, 56602 Lanester C\u00e9dex^^148, Rue L\u00e9on Foucault, 56600 Lanester",
    "sg:city":"Lanester",
    "sg:orig_category":"Non-Classified Establishments",
    "sg:phone":"+33 2 97 76 30 90",
    "sg:postcode":"56600",
    "sg:province":"Bretagne",
    "wof:name":"Chantelle S.a.",
    "wof:placetype":"venue"
},
  "geometry": {"coordinates":[-3.345244,47.76532],"type":"Point"}
}