{
  "type": "Feature",
  "properties": {
    "iso:country":"FR",
    "sg:address":"7 Rue Pierre Poizat 69240 Bourg De Thizy",
    "sg:classifiers":[
        {
            "category":"Wholesale",
            "subcategory":"Drugs",
            "type":"Manufacturing & Wholesale Goods"
        }
    ],
    "sg:phone":"+33 4 74 64 67 67",
    "sg:postcode":"69240",
    "sg:province":"Rhone-Alpes",
    "sg:tags":[
        "chemical",
        "pharmaceutical"
    ],
    "wof:name":"Avery Dennison",
    "wof:placetype":"venue"
},
  "geometry": {"coordinates":[4.296737,46.035721],"type":"Point"}
}