{
  "type": "Feature",
  "properties": {
    "addr:full":"30, Rue Maurice Cervaux, 51200 Epernay Champagne 51200",
    "addr:housenumber":"30",
    "addr:postcode":"51200;51200",
    "addr:street":"Rue Maurice Cervaux;Champagne",
    "iso:country":"FR",
    "sg:address":"30, Rue Maurice Cervaux, 51200 Epernay",
    "sg:orig_category":"Non-Classified Establishments",
    "sg:phone":"+33 3 26 54 38 20",
    "sg:postcode":"51200",
    "sg:province":"Champagne",
    "wof:name":"Champagne Alfred Gratien S.a.",
    "wof:placetype":"venue"
},
  "geometry": {"coordinates":[3.961274,49.039104],"type":"Point"}
}