{
  "type": "Feature",
  "properties": {
    "addr:full":"Zi Bracots 74890 Bons En Chablais Rhone-Alpes 74890",
    "addr:postcode":"74890;74890",
    "iso:country":"FR",
    "sg:address":"Zi Bracots 74890 Bons En Chablais",
    "sg:classifiers":[
        {
            "category":"Wholesale",
            "subcategory":"Vending Machines",
            "type":"Manufacturing & Wholesale Goods"
        }
    ],
    "sg:phone":"+33 4 50 36 15 08",
    "sg:postcode":"74890",
    "sg:province":"Rhone-Alpes",
    "sg:tags":[
        "product",
        "food",
        "processing",
        "-",
        "related",
        "equipment",
        "engineering",
        "machinery",
        "mechanical"
    ],
    "wof:name":"France Decor Sas",
    "wof:placetype":"venue"
},
  "geometry": {"coordinates":[6.37106,46.264935],"type":"Point"}
}