{
  "type": "Feature",
  "properties": {
    "addr:full":"B.P. 136, 88205 Remiremont C\u00e9dex^^8Ter, Place Jules M\u00e9line, 88200 Remiremont Lorraine",
    "addr:housenumber":"b.p. 136",
    "addr:postcode":"88205;88200",
    "addr:street":"Ce\u0301Dex^^8Ter Place Jules Me\u0301Line",
    "iso:country":"FR",
    "sg:address":"B.P. 136, 88205 Remiremont C\u00e9dex^^8Ter, Place Jules M\u00e9line, 88200 Remiremont",
    "sg:orig_category":"Non-Classified Establishments",
    "sg:phone":"+33 3 29 62 23 12",
    "sg:province":"Lorraine",
    "wof:name":"Nicole Germain S.a.r.l.",
    "wof:placetype":"venue"
},
  "geometry": {"coordinates":[6.636039,47.980343],"type":"Point"}
}