{
  "type": "Feature",
  "properties": {
    "iso:country":"FR",
    "sg:address":"104, Rue de la Bongarde, 92390 Villeneuve la Garenne",
    "sg:orig_category":"Non-Classified Establishments",
    "sg:phone":"+33 1 41 21 12 12",
    "sg:province":"Ile de France",
    "wof:name":"Loreste France S.a.",
    "wof:placetype":"venue"
},
  "geometry": {"coordinates":[2.320566,48.926857],"type":"Point"}
}