{
  "type": "Feature",
  "properties": {
    "addr:full":"181, Rue des Ch\u00eanes - ZA, 77590 Chartrettes Ile de France",
    "addr:housenumber":"181",
    "addr:postcode":"77590",
    "addr:street":"Rue Des Che\u0302Nes Za;Ile De France",
    "iso:country":"FR",
    "sg:address":"181, Rue des Ch\u00eanes - ZA, 77590 Chartrettes",
    "sg:orig_category":"Unclassifiable Establishments",
    "sg:phone":"+33 1 60 69 10 69",
    "sg:province":"Ile de France",
    "wof:name":"Brassas S.a.",
    "wof:placetype":"venue"
},
  "geometry": {"coordinates":[2.706351,48.469528],"type":"Point"}
}