{
  "type": "Feature",
  "properties": {
    "iso:country":"FR",
    "sg:address":"33, Bd Saint Roch, 06300 Nice",
    "sg:orig_category":"Unclassifiable Establishments",
    "sg:phone":"+33 4 93 26 71 71",
    "sg:province":"Basse Normandie",
    "wof:name":"Sassi S.a.",
    "wof:placetype":"venue"
},
  "geometry": {"coordinates":[7.292312,43.712074],"type":"Point"}
}