{
  "type": "Feature",
  "properties": {
    "addr:full":"72250 Challes Pays de Loire",
    "addr:postcode":"72250;pays",
    "addr:street":"Challes",
    "iso:country":"FR",
    "sg:address":"72250 Challes",
    "sg:orig_category":"Unclassifiable Establishments",
    "sg:phone":"+33 2 43 86 74 10",
    "sg:province":"Pays de Loire",
    "wof:name":"Teleplastics Industries S.a.",
    "wof:placetype":"venue"
},
  "geometry": {"coordinates":[0.413945,47.930744],"type":"Point"}
}