{
  "type": "Feature",
  "properties": {
    "iso:country":"FR",
    "sg:address":"72250 Challes",
    "sg:orig_category":"Unclassifiable Establishments",
    "sg:phone":"+33 2 43 86 74 10",
    "sg:province":"Pays de Loire",
    "wof:name":"Teleplastics Industries S.a.",
    "wof:placetype":"venue"
},
  "geometry": {"coordinates":[0.413945,47.930744],"type":"Point"}
}