{
  "type": "Feature",
  "properties": {
    "addr:full":"B.P. 150, 68331 Huningue C\u00e9dex^^3, Rue du Rhin, 68330 Huningue Huningue Alsace 68330",
    "addr:housenumber":"b.p. 150",
    "addr:postcode":"68331;68330;68330",
    "addr:street":"Rue Du Rhin",
    "iso:country":"FR",
    "sg:address":"B.P. 150, 68331 Huningue C\u00e9dex^^3, Rue du Rhin, 68330 Huningue",
    "sg:city":"Huningue",
    "sg:orig_category":"Non-Classified Establishments",
    "sg:phone":"+33 3 89 69 67 68",
    "sg:postcode":"68330",
    "sg:province":"Alsace",
    "wof:name":"Endress + Hauser S.a.",
    "wof:placetype":"venue"
},
  "geometry": {"coordinates":[7.583745,47.59119],"type":"Point"}
}