{
  "type": "Feature",
  "properties": {
    "addr:full":"Rue de Courcelles Paris Ile de France 75017",
    "addr:postcode":"75017",
    "addr:street":"Rue De Courcelles",
    "iso:country":"FR",
    "sg:address":"Rue de Courcelles",
    "sg:city":"Paris",
    "sg:orig_category":"Non-Classified Establishments",
    "sg:phone":"+33 1 40 53 01 27",
    "sg:postcode":"75017",
    "sg:province":"Ile de France",
    "wof:name":"F.g.i. Etiquettes S.a.r.l.",
    "wof:placetype":"venue"
},
  "geometry": {"coordinates":[2.29506,48.887131],"type":"Point"}
}