{
  "type": "Feature",
  "properties": {
    "addr:full":"Rue de la Gare Loulans Verchamp Franche Comt\u00e9 70230",
    "addr:postcode":"70230",
    "addr:street":"Rue De La Gare;Verchamp Franche Comte\u0301",
    "iso:country":"FR",
    "sg:address":"Rue de la Gare",
    "sg:city":"Loulans Verchamp",
    "sg:orig_category":"Non-Classified Establishments",
    "sg:phone":"+33 3 84 68 31 34",
    "sg:postcode":"70230",
    "sg:province":"Franche Comt\u00e9",
    "wof:name":"Sopreco S.a.r.l.",
    "wof:placetype":"venue"
},
  "geometry": {"coordinates":[6.211304,47.43795],"type":"Point"}
}