{
  "type": "Feature",
  "properties": {
    "iso:country":"FR",
    "sg:address":"B.P. 6",
    "sg:city":"Prigonrieux",
    "sg:orig_category":"Non-Classified Establishments",
    "sg:phone":"+33 5 53 63 28 78",
    "sg:postcode":"24130",
    "sg:province":"Aquitaine",
    "wof:name":"Bernard S.a.r.l.",
    "wof:placetype":"venue"
},
  "geometry": {"coordinates":[0.400585,44.853413],"type":"Point"}
}