{
  "type": "Feature",
  "properties": {
    "addr:full":"70, Bd du Capitaine G\u00e8ze, 13014 Marseille Provence-Alpes-C\u00f4te d'Azur",
    "addr:housenumber":"70",
    "addr:postcode":"13014",
    "addr:street":"Bd Du Capitaine Ge\u0300Ze",
    "iso:country":"FR",
    "sg:address":"70, Bd du Capitaine G\u00e8ze, 13014 Marseille",
    "sg:orig_category":"Non-Classified Establishments",
    "sg:phone":"+33 4 95 05 31 70",
    "sg:province":"Provence-Alpes-C\u00f4te d'Azur",
    "wof:name":"I.t.c. S.a. - International Trading Company",
    "wof:placetype":"venue"
},
  "geometry": {"coordinates":[5.376655,43.331276],"type":"Point"}
}