{
  "type": "Feature",
  "properties": {
    "addr:full":"ZA les Echavagnes Saint Marcellin Rhone-Alpes 38160",
    "addr:postcode":"38160",
    "addr:street":"Za Les Echavagnes Saint Marcellin Rhone-Alpes",
    "iso:country":"FR",
    "sg:address":"ZA les Echavagnes",
    "sg:city":"Saint Marcellin",
    "sg:orig_category":"Unclassifiable Establishments",
    "sg:phone":"+33 4 76 64 60 30",
    "sg:postcode":"38160",
    "sg:province":"Rhone-Alpes",
    "wof:name":"S.o.d.e.d. S.a. - Soci\u00e9t\u00e9 Outillage D\u00e9coupage Emboutissage Du Dauph",
    "wof:placetype":"venue"
},
  "geometry": {"coordinates":[5.32245,45.153374],"type":"Point"}
}