{
  "type": "Feature",
  "properties": {
    "addr:full":"53 Rue Reaumur 75002 Paris Ile de France 75002",
    "addr:housenumber":"53",
    "addr:postcode":"75002;75002",
    "addr:street":"Rue Reaumur",
    "iso:country":"FR",
    "sg:address":"53 Rue Reaumur 75002 Paris",
    "sg:classifiers":[
        {
            "category":"Shopping",
            "subcategory":"Clothing, Apparel, & Fashions",
            "type":"Retail Goods"
        }
    ],
    "sg:phone":"+33 1 45 08 80 81",
    "sg:postcode":"75002",
    "sg:province":"Ile de France",
    "sg:tags":[
        "textile",
        "clothing",
        "clothes"
    ],
    "wof:name":"Creations Mil Mike",
    "wof:placetype":"venue"
},
  "geometry": {"coordinates":[2.351824,48.866261],"type":"Point"}
}