{
  "type": "Feature",
  "properties": {
    "iso:country":"FR",
    "sg:address":"Place du Martray; Treguier; 22220",
    "sg:city":"Tr\u00e9guier",
    "sg:classifiers":[
        {
            "category":"Banks & Credit Unions",
            "subcategory":"Bank",
            "type":"Services"
        }
    ],
    "sg:phone":"+33 2 96 92 32 29",
    "sg:postcode":"22220",
    "sg:province":"Bretagne",
    "wof:name":"Caisse Regionale De Cr\u00e9dit, Maritime Mutuel Du Finist\u00e8re",
    "wof:placetype":"venue"
},
  "geometry": {"coordinates":[-3.231329,48.787224],"type":"Point"}
}