{
  "type": "Feature",
  "properties": {
    "addr:full":"101 Rue Alsace Lorraine 65300 Lannemezan Midi Pyr\u00e9n\u00e9es",
    "addr:housenumber":"101",
    "addr:postcode":"65300",
    "addr:street":"Rue Alsace Lorraine",
    "iso:country":"FR",
    "sg:address":"101 Rue Alsace Lorraine 65300 Lannemezan",
    "sg:classifiers":[
        {
            "category":"Manufacturing",
            "subcategory":"Printing",
            "type":"Manufacturing & Wholesale Goods"
        }
    ],
    "sg:phone":"+33 5 62 98 33 03",
    "sg:province":"Midi Pyr\u00e9n\u00e9es",
    "sg:tags":[
        "publishing"
    ],
    "wof:name":"Imprimerie Ricaud",
    "wof:placetype":"venue"
},
  "geometry": {"coordinates":[0.384589,43.125046],"type":"Point"}
}