{
  "type": "Feature",
  "properties": {
    "addr:full":"51, Rue des Ch\u00eanes - ZI, 65380 Lanne Midi Pyr\u00e9n\u00e9es",
    "addr:housenumber":"51",
    "addr:postcode":"65380",
    "addr:street":"Rue Des Che\u0302Nes Zi",
    "iso:country":"FR",
    "sg:address":"51, Rue des Ch\u00eanes - ZI, 65380 Lanne",
    "sg:orig_category":"Non-Classified Establishments",
    "sg:phone":"+33 5 62 45 42 52",
    "sg:province":"Midi Pyr\u00e9n\u00e9es",
    "wof:name":"Transports Barcos S.a.",
    "wof:placetype":"venue"
},
  "geometry": {"coordinates":[-0.029159,43.18401],"type":"Point"}
}