{
  "type": "Feature",
  "properties": {
    "addr:full":"15 Rue G\u00e9n\u00e9ral Leclerc 71100 Chalon Sur Sa\u00f4ne Chalon-sur-Sa\u00f4ne Bourgogne 71100",
    "addr:housenumber":"15",
    "addr:postcode":"71100;71100",
    "addr:street":"Rue Ge\u0301Ne\u0301Ral Leclerc",
    "iso:country":"FR",
    "sg:address":"15 Rue G\u00e9n\u00e9ral Leclerc 71100 Chalon Sur Sa\u00f4ne",
    "sg:city":"Chalon-sur-Sa\u00f4ne",
    "sg:classifiers":[
        {
            "category":"Shopping",
            "subcategory":"Bicycles & Sporting Goods",
            "type":"Retail Goods"
        }
    ],
    "sg:phone":"+33 3 85 48 11 41",
    "sg:postcode":"71100",
    "sg:province":"Bourgogne",
    "sg:tags":[
        "product",
        "sport",
        "miscellaneous"
    ],
    "wof:name":"Dael Sports",
    "wof:placetype":"venue"
},
  "geometry": {"coordinates":[4.853622,46.782215],"type":"Point"}
}