{
  "type": "Feature",
  "properties": {
    "iso:country":"FR",
    "sg:address":"21 Rue De La Sabliere 75014 Paris",
    "sg:classifiers":[
        {
            "category":"Manufacturing",
            "subcategory":"Tools & Machinery",
            "type":"Manufacturing & Wholesale Goods"
        }
    ],
    "sg:phone":"+33 1 45 43 81 51",
    "sg:postcode":"75014",
    "sg:province":"Ile de France",
    "sg:tags":[
        "metallurgy",
        "metalworking"
    ],
    "wof:name":"Ateliers Lea",
    "wof:placetype":"venue"
},
  "geometry": {"coordinates":[2.322979,48.831799],"type":"Point"}
}