{
  "type": "Feature",
  "properties": {
    "iso:country":"FR",
    "sg:address":"B.P. 8135, 45081 Orl\u00e9ans C\u00e9dex 2^^18, Rue Guignegault, 45000 Orl\u00e9ans",
    "sg:city":"Orl\u00e9ans",
    "sg:orig_category":"Non-Classified Establishments",
    "sg:phone":"+33 2 38 65 09 00",
    "sg:postcode":"45000",
    "sg:province":"Centre",
    "wof:name":"Sema Distribution S.a.",
    "wof:placetype":"venue"
},
  "geometry": {"coordinates":[1.904965,47.901428],"type":"Point"}
}