{
  "type": "Feature",
  "properties": {
    "addr:full":"Le Moulin de Salon 19510 Salon la Tour Limousin",
    "iso:country":"FR",
    "sg:address":"Le Moulin de Salon 19510 Salon la Tour",
    "sg:orig_category":"Unclassifiable Establishments",
    "sg:phone":"+33 5 55 97 97 97",
    "sg:province":"Limousin",
    "wof:name":"Soci\u00e9t\u00e9 Galetou S.a.r.l.",
    "wof:placetype":"venue"
},
  "geometry": {"coordinates":[1.574,45.490189],"type":"Point"}
}