{
  "type": "Feature",
  "properties": {
    "addr:full":"146 rue Sainte 13007 Marseille Poitou-Charentes",
    "addr:housenumber":"146",
    "addr:postcode":"13007",
    "addr:street":"Rue Sainte",
    "iso:country":"FR",
    "sg:address":"146 rue Sainte 13007 Marseille",
    "sg:orig_category":"Underwater And Seabed Cables",
    "sg:phone":"+33 4 91 04 42 00",
    "sg:province":"Poitou-Charentes",
    "wof:name":"Ld Travocean S.a.",
    "wof:placetype":"venue"
},
  "geometry": {"coordinates":[5.364365,43.290558],"type":"Point"}
}