{
  "type": "Feature",
  "properties": {
    "addr:full":"13 Port Moelou 22110 Rostrenen Rostrenen Bretagne 22110",
    "addr:housenumber":"13",
    "addr:postcode":"22110;22110",
    "addr:street":"Port Moelou",
    "iso:country":"FR",
    "sg:address":"13 Port Moelou 22110 Rostrenen",
    "sg:city":"Rostrenen",
    "sg:classifiers":[
        {
            "category":"Professional",
            "subcategory":"Business Services",
            "type":"Services"
        }
    ],
    "sg:phone":"+33 2 96 29 01 19",
    "sg:postcode":"22110",
    "sg:province":"Bretagne",
    "sg:tags":[
        "training",
        "advice"
    ],
    "wof:name":"College Departemental Edouard Herriot",
    "wof:placetype":"venue"
},
  "geometry": {"coordinates":[-3.296701,48.174469],"type":"Point"}
}