{
  "type": "Feature",
  "properties": {
    "addr:full":"45 quai de Bosc 34200 SETE Languedoc-Roussillon 34200",
    "addr:housenumber":"45",
    "addr:postcode":"34200;34200",
    "addr:street":"Quai De Bosc",
    "iso:country":"FR",
    "sg:address":"45 quai de Bosc 34200 SETE",
    "sg:orig_category":"Menswear, Suits, Trousers, Sports Jackets",
    "sg:phone":"+33 4 67 46 66 00",
    "sg:postcode":"34200",
    "sg:province":"Languedoc-Roussillon",
    "wof:name":"Manufacture De Vetements Paul Boye Sa",
    "wof:placetype":"venue"
},
  "geometry": {"coordinates":[3.695204,43.408398],"type":"Point"}
}