{
  "type": "Feature",
  "properties": {
    "iso:country":"FR",
    "sg:address":"B.P. 131, 27501 Pont Audemer C\u00e9dex^^Rue des Papetiers, 27500 Pont Audemer",
    "sg:orig_category":"Non-Classified Establishments",
    "sg:phone":"+33 2 32 41 61 00",
    "sg:postcode":"27500",
    "sg:province":"Haute Normandie",
    "wof:name":"Ahlstrom - Dalle",
    "wof:placetype":"venue"
},
  "geometry": {"coordinates":[0.5067,49.300587],"type":"Point"}
}