{
  "type": "Feature",
  "properties": {
    "iso:country":"FR",
    "sg:address":"64, Av. de Fenots, 28100 Dreux",
    "sg:city":"Dreux",
    "sg:orig_category":"Non-Classified Establishments",
    "sg:phone":"+33 2 37 46 07 72",
    "sg:postcode":"28100",
    "sg:province":"Centre",
    "wof:name":"Tenuta & Gambuto P\u00e8re Et Fils S.a.r.l.",
    "wof:placetype":"venue"
},
  "geometry": {"coordinates":[1.341925,48.741306],"type":"Point"}
}