{
  "type": "Feature",
  "properties": {
    "iso:country":"FR",
    "sg:address":"9 A Boulevard Jourdan 75014 Paris",
    "sg:classifiers":[
        {
            "category":"Professional",
            "subcategory":"Business Services",
            "type":"Services"
        }
    ],
    "sg:phone":"+33 1 40 78 72 00",
    "sg:postcode":"75014",
    "sg:province":"Ile de France",
    "sg:tags":[
        "training",
        "advice"
    ],
    "wof:name":"Cite Internationale Universitaire De Paris",
    "wof:placetype":"venue"
},
  "geometry": {"coordinates":[2.32515,48.832199],"type":"Point"}
}