{
  "type": "Feature",
  "properties": {
    "iso:country":"FR",
    "sg:address":"12 Route Bouxwiller 67340 Ingwiller",
    "sg:city":"Ingwiller",
    "sg:classifiers":[
        {
            "category":"Manufacturing",
            "subcategory":"Metals",
            "type":"Manufacturing & Wholesale Goods"
        }
    ],
    "sg:phone":"+33 3 88 89 64 64",
    "sg:postcode":"67340",
    "sg:province":"Alsace",
    "sg:tags":[
        "metallurgy",
        "metalworking",
        "processing"
    ],
    "wof:name":"Cd Industries",
    "wof:placetype":"venue"
},
  "geometry": {"coordinates":[7.470649,48.863476],"type":"Point"}
}