{
  "type": "Feature",
  "properties": {
    "iso:country":"FR",
    "sg:address":"Pa Du Moulin BP 52 44880 Sautron",
    "sg:classifiers":[
        {
            "category":"Professional",
            "subcategory":"Engineering",
            "type":"Services"
        }
    ],
    "sg:phone":"+33 2 40 63 80 00",
    "sg:postcode":"44880",
    "sg:province":"Pays de Loire",
    "sg:tags":[
        "machine",
        "-",
        "mechanical"
    ],
    "wof:name":"Doregrill",
    "wof:placetype":"venue"
},
  "geometry": {"coordinates":[-1.658084,47.259796],"type":"Point"}
}