{
  "type": "Feature",
  "properties": {
    "iso:country":"FR",
    "sg:address":"17, Bd Poissonni\u00e8re, 75002 Paris",
    "sg:orig_category":"Non-Classified Establishments",
    "sg:phone":"+33 1 40 39 14 39",
    "sg:province":"Ile de France",
    "wof:name":"Safari S.a.r.l.",
    "wof:placetype":"venue"
},
  "geometry": {"coordinates":[2.344786,48.871044],"type":"Point"}
}