{
  "type": "Feature",
  "properties": {
    "addr:full":"114 Rue Jean Jaures 62240 Desvres Nord Pas-de-Calais 62240",
    "addr:housenumber":"114",
    "addr:postcode":"62240;62240",
    "addr:street":"Rue Jean Jaures",
    "iso:country":"FR",
    "sg:address":"114 Rue Jean Jaures 62240 Desvres",
    "sg:classifiers":[
        {
            "category":"Home & Garden",
            "subcategory":"Furniture",
            "type":"Retail Goods"
        }
    ],
    "sg:phone":"+33 3 21 91 57 96",
    "sg:postcode":"62240",
    "sg:province":"Nord Pas-de-Calais",
    "sg:tags":[
        "household",
        "wood"
    ],
    "wof:name":"Herbeau Productions",
    "wof:placetype":"venue"
},
  "geometry": {"coordinates":[1.832495,50.673714],"type":"Point"}
}