{
  "type": "Feature",
  "properties": {
    "addr:full":"28, Bd de Stalingrad, 92240 Malakoff Ile de France",
    "addr:housenumber":"28",
    "addr:postcode":"92240;ile",
    "addr:street":"Bd De Stalingrad",
    "iso:country":"FR",
    "sg:address":"28, Bd de Stalingrad, 92240 Malakoff",
    "sg:orig_category":"Unclassifiable Establishments",
    "sg:phone":"+33 1 42 53 83 11",
    "sg:province":"Ile de France",
    "wof:name":"C.i.e.c. S.a.",
    "wof:placetype":"venue"
},
  "geometry": {"coordinates":[2.29511,48.812294],"type":"Point"}
}