{
  "type": "Feature",
  "properties": {
    "addr:full":"244, Rue Branly, 71000 M\u00e2con Sanc\u00e9 Bourgogne 71000",
    "addr:housenumber":"244",
    "addr:postcode":"71000;71000",
    "addr:street":"Rue Branly",
    "iso:country":"FR",
    "sg:address":"244, Rue Branly, 71000 M\u00e2con",
    "sg:city":"Sanc\u00e9",
    "sg:orig_category":"Non-Classified Establishments",
    "sg:phone":"+33 3 85 29 11 00",
    "sg:postcode":"71000",
    "sg:province":"Bourgogne",
    "wof:name":"M\u00e2con Bus S.a.",
    "wof:placetype":"venue"
},
  "geometry": {"coordinates":[4.81194,46.283661],"type":"Point"}
}