{
  "type": "Feature",
  "properties": {
    "addr:full":"B.P. 301, 16008 Angoul\u00eame C\u00e9dex^^35, Rte de Vars, 16160 Gond Pontouvre Poitou-Charentes 16160",
    "addr:housenumber":"b.p. 301",
    "addr:postcode":"16008;16160;16160",
    "addr:street":"Rte De Vars;Pontouvre",
    "iso:country":"FR",
    "sg:address":"B.P. 301, 16008 Angoul\u00eame C\u00e9dex^^35, Rte de Vars, 16160 Gond Pontouvre",
    "sg:orig_category":"Non-Classified Establishments",
    "sg:phone":"+33 5 45 68 31 51",
    "sg:postcode":"16160",
    "sg:province":"Poitou-Charentes",
    "wof:name":"Cars De Maillard S.a.",
    "wof:placetype":"venue"
},
  "geometry": {"coordinates":[0.166295,45.668095],"type":"Point"}
}