{
  "type": "Feature",
  "properties": {
    "iso:country":"FR",
    "sg:address":"116, Rue de la Gare, 74300 Magland",
    "sg:orig_category":"Non-Classified Establishments",
    "sg:phone":"+33 4 50 34 71 06",
    "sg:postcode":"74300",
    "sg:province":"Rhone-Alpes",
    "wof:name":"Cartonnages Burtin-marquis",
    "wof:placetype":"venue"
},
  "geometry": {"coordinates":[6.622339,46.017033],"type":"Point"}
}