{
  "type": "Feature",
  "properties": {
    "iso:country":"FR",
    "sg:address":"2 Rue Emile Zola 77450 Montry",
    "sg:classifiers":[
        {
            "category":"Manufacturing",
            "subcategory":"Glass & Minerals",
            "type":"Manufacturing & Wholesale Goods"
        }
    ],
    "sg:phone":"+33 1 60 04 55 95",
    "sg:postcode":"77450",
    "sg:province":"Ile de France",
    "sg:tags":[
        "building",
        "material"
    ],
    "wof:name":"Arribas France Sarl",
    "wof:placetype":"venue"
},
  "geometry": {"coordinates":[2.833964,48.889702],"type":"Point"}
}