{
  "type": "Feature",
  "properties": {
    "iso:country":"FR",
    "sg:address":"5 Rue De L'Euron 54320 Max\u00e9ville",
    "sg:classifiers":[
        {
            "category":"Wholesale",
            "subcategory":"Machinery & Supplies",
            "type":"Manufacturing & Wholesale Goods"
        }
    ],
    "sg:phone":"+33 3 83 95 10 30",
    "sg:postcode":"54320",
    "sg:province":"Lorraine",
    "sg:tags":[
        "handling",
        "material",
        "-",
        "machine",
        "equipment",
        "engineering",
        "mechanical"
    ],
    "wof:name":"Thyssen Ascenseurs Agence De Nancy",
    "wof:placetype":"venue"
},
  "geometry": {"coordinates":[6.134354,48.70343],"type":"Point"}
}