{
  "type": "Feature",
  "properties": {
    "addr:full":"B.P. 49, 49140 Seiches sur le Loir^^ZA des Muloti\u00e8res, 49140 Seiches sur le Loir Pays de Loire 49140",
    "addr:postcode":"49140;sur le;49140;49140",
    "addr:street":"B.P. 49;Le Loir",
    "iso:country":"FR",
    "sg:address":"B.P. 49, 49140 Seiches sur le Loir^^ZA des Muloti\u00e8res, 49140 Seiches sur le Loir",
    "sg:orig_category":"Non-Classified Establishments",
    "sg:phone":"+33 2 41 33 73 33",
    "sg:postcode":"49140",
    "sg:province":"Pays de Loire",
    "wof:name":"D\u00e9polabo S.a.",
    "wof:placetype":"venue"
},
  "geometry": {"coordinates":[-0.317761,47.499454],"type":"Point"}
}