{
  "type": "Feature",
  "properties": {
    "addr:full":"126, Av. Pavlov - ZI Saint C\u00e9saire, 30900 N\u00eemes Languedoc-Roussillon",
    "addr:postcode":"30900",
    "addr:street":"126 Av. Pavlov Zi Saint Ce\u0301Saire",
    "iso:country":"FR",
    "sg:address":"126, Av. Pavlov - ZI Saint C\u00e9saire, 30900 N\u00eemes",
    "sg:orig_category":"Unclassifiable Establishments",
    "sg:phone":"+33 4 66 28 82 00",
    "sg:province":"Languedoc-Roussillon",
    "wof:name":"Roger S.a.",
    "wof:placetype":"venue"
},
  "geometry": {"coordinates":[4.356115,43.830025],"type":"Point"}
}