{
  "type": "Feature",
  "properties": {
    "iso:country":"FR",
    "sg:address":"Rue Leclanche",
    "sg:city":"Notre Dame de Gravenchon",
    "sg:orig_category":"Non-Classified Establishments",
    "sg:phone":"+33 2 32 84 47 10",
    "sg:postcode":"76330",
    "sg:province":"Haute Normandie",
    "wof:name":"Sonotraf S.a.",
    "wof:placetype":"venue"
},
  "geometry": {"coordinates":[0.58071,49.484814],"type":"Point"}
}