{
  "type": "Feature",
  "properties": {
    "addr:full":"133, Rue d'Herny, 74130 Vougy Rhone-Alpes",
    "addr:housenumber":"133",
    "addr:postcode":"74130",
    "addr:street":"Rue D'Herny",
    "iso:country":"FR",
    "sg:address":"133, Rue d'Herny, 74130 Vougy",
    "sg:orig_category":"Unclassifiable Establishments",
    "sg:phone":"+33 4 50 89 96 11",
    "sg:province":"Rhone-Alpes",
    "wof:name":"Etablissement Sandrin Jean",
    "wof:placetype":"venue"
},
  "geometry": {"coordinates":[6.49431,46.06749],"type":"Point"}
}