{
  "type": "Feature",
  "properties": {
    "addr:full":"Rue Franche 39360 Viry Franche Comt\u00e9",
    "addr:postcode":"39360",
    "addr:street":"Rue Franche;Franche Comte\u0301",
    "iso:country":"FR",
    "sg:address":"Rue Franche 39360 Viry",
    "sg:classifiers":[
        {
            "category":"Manufacturing",
            "subcategory":"Rubber & Plastics",
            "type":"Manufacturing & Wholesale Goods"
        }
    ],
    "sg:phone":"+33 3 84 41 10 29",
    "sg:province":"Franche Comt\u00e9",
    "wof:name":"Sarl Moyret",
    "wof:placetype":"venue"
},
  "geometry": {"coordinates":[5.737995,46.29892],"type":"Point"}
}