{
  "type": "Feature",
  "properties": {
    "addr:full":"ZI Pontots - Le Forum Bayonne Aquitaine 64100",
    "addr:postcode":"64100",
    "iso:country":"FR",
    "sg:address":"ZI Pontots - Le Forum",
    "sg:city":"Bayonne",
    "sg:orig_category":"Unclassifiable Establishments",
    "sg:phone":"+33 5 59 57 25 00",
    "sg:postcode":"64100",
    "sg:province":"Aquitaine",
    "wof:name":"S\u00e9l\u00e9nium S.a.",
    "wof:placetype":"venue"
},
  "geometry": {"coordinates":[-1.476364,43.492741],"type":"Point"}
}