{
  "type": "Feature",
  "properties": {
    "addr:full":"Av Du Pr\u00e9sident Kennedy 33700 M\u00e9rignac M\u00e9rignac Aquitaine 33700",
    "addr:postcode":"33700;33700",
    "addr:street":"Av Du Pre\u0301Sident Kennedy",
    "iso:country":"FR",
    "sg:address":"Av Du Pr\u00e9sident Kennedy 33700 M\u00e9rignac",
    "sg:city":"M\u00e9rignac",
    "sg:classifiers":[
        {
            "category":"Travel",
            "subcategory":"Hotels & Motels",
            "type":"Entertainment"
        }
    ],
    "sg:phone":"+33 5 56 34 10 19",
    "sg:postcode":"33700",
    "sg:province":"Aquitaine",
    "sg:tags":[
        "hotels",
        "business",
        "restaurant"
    ],
    "wof:name":"Ibis",
    "wof:placetype":"venue"
},
  "geometry": {"coordinates":[-0.653634,44.840691],"type":"Point"}
}