{
  "type": "Feature",
  "properties": {
    "addr:full":"96 Bd Des B\u00e8gles BP 349 85000 La Roche Sur Yon Pays de Loire 85000",
    "addr:housenumber":"96;349",
    "addr:postcode":"85000;85000",
    "addr:street":"Bd Des Be\u0300Gles Bp;Roche;Yon",
    "iso:country":"FR",
    "sg:address":"96 Bd Des B\u00e8gles BP 349 85000 La Roche Sur Yon",
    "sg:classifiers":[
        {
            "category":"Professional",
            "subcategory":"Business Services",
            "type":"Services"
        }
    ],
    "sg:phone":"+33 2 51 47 89 00",
    "sg:postcode":"85000",
    "sg:province":"Pays de Loire",
    "sg:tags":[
        "training",
        "advice"
    ],
    "wof:name":"College Prive Richelieu",
    "wof:placetype":"venue"
},
  "geometry": {"coordinates":[-1.423639,46.675117],"type":"Point"}
}