{
  "type": "Feature",
  "properties": {
    "addr:full":"8, Rue Mercier, 77290 Mitry Mory Ile de France",
    "addr:housenumber":"8",
    "addr:postcode":"77290",
    "addr:street":"Rue Mercier",
    "iso:country":"FR",
    "sg:address":"8, Rue Mercier, 77290 Mitry Mory",
    "sg:orig_category":"Non-Classified Establishments",
    "sg:phone":"+33 1 60 21 67 00",
    "sg:province":"Ile de France",
    "wof:name":"Serimer S.a.s.",
    "wof:placetype":"venue"
},
  "geometry": {"coordinates":[2.64998,48.986092],"type":"Point"}
}