{
  "type": "Feature",
  "properties": {
    "addr:full":"21 bis, Rue du Mar\u00e9chal de Lattre de Tassigny, 50000 Saint L\u00f4 Saint-L\u00f4 Basse Normandie 50000",
    "addr:housenumber":"21 bis",
    "addr:postcode":"50000;50000",
    "addr:street":"Rue Du Mare\u0301Chal De Lattre De Tassigny",
    "iso:country":"FR",
    "sg:address":"21 bis, Rue du Mar\u00e9chal de Lattre de Tassigny, 50000 Saint L\u00f4",
    "sg:city":"Saint-L\u00f4",
    "sg:orig_category":"Unclassifiable Establishments",
    "sg:phone":"+33 2 33 77 31 60",
    "sg:postcode":"50000",
    "sg:province":"Basse Normandie",
    "wof:name":"Cabinet M. Pesce S.a.r.l.",
    "wof:placetype":"venue"
},
  "geometry": {"coordinates":[-1.080704,49.114258],"type":"Point"}
}