{
  "type": "Feature",
  "properties": {
    "iso:country":"FR",
    "sg:address":"500, Rue des Trois Tilleuls, 77000 Vaux le P\u00e9nil",
    "sg:orig_category":"Non-Classified Establishments",
    "sg:phone":"+33 1 64 39 50 80",
    "sg:province":"Ile de France",
    "wof:name":"Plastocean Industrie Mat\u00e9riaux Composites S.a.r.l.",
    "wof:placetype":"venue"
},
  "geometry": {"coordinates":[2.690543,48.534969],"type":"Point"}
}