{
  "type": "Feature",
  "properties": {
    "iso:country":"FR",
    "sg:address":"799, Rue Marcel Paul, 94508 Champigny sur Marne C\u00e9dex",
    "sg:orig_category":"Non-Classified Establishments",
    "sg:phone":"+33 1 47 06 95 70",
    "sg:province":"Midi Pyr\u00e9n\u00e9es",
    "wof:name":"M.m.p. S.a.r.l. - Moulage Mati\u00e8re Plastique",
    "wof:placetype":"venue"
},
  "geometry": {"coordinates":[2.531664,48.80917],"type":"Point"}
}