{
  "type": "Feature",
  "properties": {
    "addr:full":"B.P. 6, 88260 Lerrain^^Rte d'Escl\u00e9s, 88260 Lerrain Lorraine 88260",
    "addr:housenumber":"6",
    "addr:postcode":"88260;88260;88260",
    "addr:street":"B.P.;\u0301S",
    "iso:country":"FR",
    "sg:address":"B.P. 6, 88260 Lerrain^^Rte d'Escl\u00e9s, 88260 Lerrain",
    "sg:orig_category":"Non-Classified Establishments",
    "sg:phone":"+33 3 29 07 50 56",
    "sg:postcode":"88260",
    "sg:province":"Lorraine",
    "wof:name":"Choff\u00e9 Motoculture S.a.r.l.",
    "wof:placetype":"venue"
},
  "geometry": {"coordinates":[6.175108,48.130146],"type":"Point"}
}