{
  "type": "Feature",
  "properties": {
    "iso:country":"FR",
    "sg:address":"5 Rue Bailly 92200 Neuilly Sur Seine",
    "sg:classifiers":[
        {
            "category":"Professional",
            "subcategory":"Advertising",
            "type":"Services"
        }
    ],
    "sg:phone":"+33 1 46 24 75 06",
    "sg:postcode":"92200",
    "sg:province":"Ile de France",
    "sg:tags":[
        "information",
        "medium",
        "communication"
    ],
    "wof:name":"Societe D'editions De Neuilly Journal Independant",
    "wof:placetype":"venue"
},
  "geometry": {"coordinates":[2.260476,48.886086],"type":"Point"}
}