{
  "type": "Feature",
  "properties": {
    "addr:full":"36 Rue Des Veyettes 35000 Rennes Rennes Bretagne 35000",
    "addr:housenumber":"36",
    "addr:postcode":"35000;35000",
    "addr:street":"Rue Des Veyettes",
    "iso:country":"FR",
    "sg:address":"36 Rue Des Veyettes 35000 Rennes",
    "sg:city":"Rennes",
    "sg:classifiers":[
        {
            "category":"Manufacturing",
            "subcategory":"Printing",
            "type":"Manufacturing & Wholesale Goods"
        }
    ],
    "sg:phone":"+33 2 99 26 72 72",
    "sg:postcode":"35000",
    "sg:province":"Bretagne",
    "sg:tags":[
        "publishing"
    ],
    "wof:name":"Calligraphy",
    "wof:placetype":"venue"
},
  "geometry": {"coordinates":[-1.629999,48.09716],"type":"Point"}
}