{
  "type": "Feature",
  "properties": {
    "addr:full":"56, Rue Ferrer, 59210 Coudekerque Branche Nord Pas-de-Calais",
    "addr:housenumber":"56",
    "addr:postcode":"59210",
    "addr:street":"Rue Ferrer;Branche Nord",
    "iso:country":"FR",
    "sg:address":"56, Rue Ferrer, 59210 Coudekerque Branche",
    "sg:orig_category":"Unclassifiable Establishments",
    "sg:phone":"+33 3 28 29 20 80",
    "sg:province":"Nord Pas-de-Calais",
    "wof:name":"S.2e.i. S.a. - Soci\u00e9t\u00e9 Equipements Et Entretiens Industriels",
    "wof:placetype":"venue"
},
  "geometry": {"coordinates":[2.38219,51.018566],"type":"Point"}
}