{
  "type": "Feature",
  "properties": {
    "iso:country":"FR",
    "sg:address":"99, Rue de la R\u00e9publique, 92800 Puteaux",
    "sg:orig_category":"Unclassifiable Establishments",
    "sg:phone":"+33 1 47 73 98 58",
    "sg:province":"Ile de France",
    "wof:name":"France 1 Communication S.a.",
    "wof:placetype":"venue"
},
  "geometry": {"coordinates":[2.241814,48.885323],"type":"Point"}
}