{
  "type": "Feature",
  "properties": {
    "addr:full":"B.P. 231, 18102 Vierzon C\u00e9dex^^Rte de Fo\u00ebcy - ZI des Forges, 18100 Vierzon Vierzon Centre 18100",
    "addr:housenumber":"b.p. 231;vierzon",
    "addr:postcode":"18102;18100;18100",
    "addr:street":"Zi Des Forges",
    "iso:country":"FR",
    "sg:address":"B.P. 231, 18102 Vierzon C\u00e9dex^^Rte de Fo\u00ebcy - ZI des Forges, 18100 Vierzon",
    "sg:city":"Vierzon",
    "sg:orig_category":"Non-Classified Establishments",
    "sg:phone":"+33 2 48 71 31 75",
    "sg:postcode":"18100",
    "sg:province":"Centre",
    "wof:name":"Valric S.a.",
    "wof:placetype":"venue"
},
  "geometry": {"coordinates":[2.020555,47.206581],"type":"Point"}
}