{
  "type": "Feature",
  "properties": {
    "addr:full":"B.P. 28, 67620 Soufflenheim^^3, Rue Louis Armand, 67620 Soufflenheim Soufflenheim Alsace 67620",
    "addr:postcode":"67620;67620;67620",
    "addr:street":"B.P. 28;Rue Louis Armand",
    "iso:country":"FR",
    "sg:address":"B.P. 28, 67620 Soufflenheim^^3, Rue Louis Armand, 67620 Soufflenheim",
    "sg:city":"Soufflenheim",
    "sg:orig_category":"Non-Classified Establishments",
    "sg:phone":"+33 3 88 05 78 45",
    "sg:postcode":"67620",
    "sg:province":"Alsace",
    "wof:name":"Imprimerie Modern Graphic S.a.r.l.",
    "wof:placetype":"venue"
},
  "geometry": {"coordinates":[7.95924,48.8298],"type":"Point"}
}