{
  "type": "Feature",
  "properties": {
    "addr:full":"B.P. 146, 71104 Chalon sur Sa\u00f4ne C\u00e9dex^^228, Av de Paris, 71100 Ch\u00e2lon sur Sa\u00f4ne Chalon-sur-Sa\u00f4ne Bourgogne 71100",
    "addr:housenumber":"b.p. 146",
    "addr:postcode":"71104;71100;71100",
    "addr:street":"Av De Paris",
    "iso:country":"FR",
    "sg:address":"B.P. 146, 71104 Chalon sur Sa\u00f4ne C\u00e9dex^^228, Av de Paris, 71100 Ch\u00e2lon sur Sa\u00f4ne",
    "sg:city":"Chalon-sur-Sa\u00f4ne",
    "sg:orig_category":"Non-Classified Establishments",
    "sg:phone":"+33 3 85 46 05 67",
    "sg:postcode":"71100",
    "sg:province":"Bourgogne",
    "wof:name":"Cardot - M.f.b.i. S.a.",
    "wof:placetype":"venue"
},
  "geometry": {"coordinates":[4.85501,46.779694],"type":"Point"}
}