{
  "type": "Feature",
  "properties": {
    "addr:full":"Lieu Dit Les Quatre Vents 35130 Rannee Rann\u00e9e Bretagne 35130",
    "addr:postcode":"35130;35130",
    "addr:street":"Lieu Dit Les Quatre Vents;Ranne\u0301E",
    "iso:country":"FR",
    "sg:address":"Lieu Dit Les Quatre Vents 35130 Rannee",
    "sg:city":"Rann\u00e9e",
    "sg:classifiers":[
        {
            "category":"Farming",
            "subcategory":"Farm",
            "type":"Manufacturing & Wholesale Goods"
        }
    ],
    "sg:phone":"+33 2 99 96 23 28",
    "sg:postcode":"35130",
    "sg:province":"Bretagne",
    "sg:tags":[
        "horticulture",
        "agriculture",
        "livestock"
    ],
    "wof:name":"Sarl Lardeux Freres Pepiniere Et Paysage",
    "wof:placetype":"venue"
},
  "geometry": {"coordinates":[-1.207897,47.91785],"type":"Point"}
}