{
  "type": "Feature",
  "properties": {
    "iso:country":"FR",
    "sg:address":"B.P. 10180, 35803 Dinard C\u00e9dex^^55, Bd Jules Verger, 35800 Dinard",
    "sg:city":"Dinard",
    "sg:orig_category":"Non-Classified Establishments",
    "sg:phone":"+33 2 99 16 51 50",
    "sg:postcode":"35800",
    "sg:province":"Bretagne",
    "wof:name":"Timab Distribution S.a.r.l.",
    "wof:placetype":"venue"
},
  "geometry": {"coordinates":[-2.136755,48.624207],"type":"Point"}
}