{
  "type": "Feature",
  "properties": {
    "addr:full":"2 Rue De Fontaine Dijon Bourgogne 21000",
    "addr:housenumber":"2",
    "addr:postcode":"21000",
    "addr:street":"Rue De Fontaine;Bourgogne",
    "iso:country":"FR",
    "sg:address":"2 Rue De Fontaine",
    "sg:city":"Dijon",
    "sg:classifiers":[
        {
            "category":"Banks & Credit Unions",
            "subcategory":"Financial Services",
            "type":"Services"
        }
    ],
    "sg:phone":"+33 3 80 53 18 53",
    "sg:postcode":"21000",
    "sg:province":"Bourgogne",
    "sg:tags":[
        "banking",
        "finance",
        "insurance"
    ],
    "wof:name":"Cleon Martin Broichot Et Associes Sarl",
    "wof:placetype":"venue"
},
  "geometry": {"coordinates":[5.053431,47.335003],"type":"Point"}
}