{
  "type": "Feature",
  "properties": {
    "addr:full":"22 rue Childebert; Lyon; 69291 Auvergne",
    "addr:housenumber":"22",
    "addr:postcode":"69291",
    "addr:street":"Rue Childebert",
    "iso:country":"FR",
    "sg:address":"22 rue Childebert; Lyon; 69291",
    "sg:classifiers":[
        {
            "category":"Banks & Credit Unions",
            "subcategory":"Bank",
            "type":"Services"
        }
    ],
    "sg:phone":"+33 4 72 56 23 00",
    "sg:province":"Auvergne",
    "wof:name":"Cr\u00e9dit Foncier, De France Sa",
    "wof:placetype":"venue"
},
  "geometry": {"coordinates":[4.836688,45.76004],"type":"Point"}
}