{
  "type": "Feature",
  "properties": {
    "addr:full":"1 Rue Escaut 21850 St Apollinaire Saint-Apollinaire Bourgogne 21850",
    "addr:housenumber":"1",
    "addr:postcode":"21850;21850",
    "addr:street":"Rue Escaut",
    "iso:country":"FR",
    "sg:address":"1 Rue Escaut 21850 St Apollinaire",
    "sg:city":"Saint-Apollinaire",
    "sg:classifiers":[
        {
            "category":"Manufacturing",
            "subcategory":"Rubber & Plastics",
            "type":"Manufacturing & Wholesale Goods"
        }
    ],
    "sg:phone":"+33 3 80 71 21 40",
    "sg:postcode":"21850",
    "sg:province":"Bourgogne",
    "wof:name":"Metifiot Pneu",
    "wof:placetype":"venue"
},
  "geometry": {"coordinates":[5.075449,47.340687],"type":"Point"}
}