{
  "type": "Feature",
  "properties": {
    "addr:full":"Za Froehn 67310 Scharrachbergheim Balbronn Alsace 67310",
    "addr:postcode":"67310;67310",
    "addr:street":"Za Froehn;Balbronn",
    "iso:country":"FR",
    "sg:address":"Za Froehn 67310 Scharrachbergheim",
    "sg:city":"Balbronn",
    "sg:classifiers":[
        {
            "category":"Food & Beverages",
            "subcategory":"Groceries & Convenience Stores",
            "type":"Retail Goods"
        }
    ],
    "sg:phone":"+33 3 88 50 62 55",
    "sg:postcode":"67310",
    "sg:province":"Alsace",
    "sg:tags":[
        "product",
        "related"
    ],
    "wof:name":"Ste Alsacienne D'ovoproduits",
    "wof:placetype":"venue"
},
  "geometry": {"coordinates":[7.495818,48.59301],"type":"Point"}
}