{
  "type": "Feature",
  "properties": {
    "iso:country":"FR",
    "sg:address":"Av. Benoit Frachon - ZI",
    "sg:city":"Boulazac",
    "sg:orig_category":"Non-Classified Establishments",
    "sg:phone":"+33 5 53 09 00 62",
    "sg:postcode":"24750",
    "sg:province":"Aquitaine",
    "wof:name":"Snad S.a.",
    "wof:placetype":"venue"
},
  "geometry": {"coordinates":[0.789735,45.09977],"type":"Point"}
}