{
  "type": "Feature",
  "properties": {
    "addr:full":"2, Rue Porte Dor\u00e9e, 10140 Vendeuvre sur Barse Champagne",
    "addr:housenumber":"2",
    "addr:postcode":"10140",
    "addr:street":"Rue Porte Dore\u0301E",
    "iso:country":"FR",
    "sg:address":"2, Rue Porte Dor\u00e9e, 10140 Vendeuvre sur Barse",
    "sg:orig_category":"Non-Classified Establishments",
    "sg:phone":"+33 3 25 41 36 55",
    "sg:province":"Champagne",
    "wof:name":"Guerrier P\u00e8re Et Fils S.a.",
    "wof:placetype":"venue"
},
  "geometry": {"coordinates":[4.4729,48.238026],"type":"Point"}
}