{
  "type": "Feature",
  "properties": {
    "addr:full":"30 Rue De Bassano 75116 Paris Languedoc-Roussillon",
    "addr:housenumber":"30",
    "addr:postcode":"75116",
    "addr:street":"Rue De Bassano",
    "iso:country":"FR",
    "sg:address":"30 Rue De Bassano 75116 Paris",
    "sg:classifiers":[
        {
            "category":"Travel",
            "subcategory":"Hotels & Motels",
            "type":"Entertainment"
        }
    ],
    "sg:phone":"+33 1 53 57 75 00",
    "sg:province":"Languedoc-Roussillon",
    "sg:tags":[
        "hotels",
        "business",
        "restaurant"
    ],
    "wof:name":"Hotel Belmont Sa",
    "wof:placetype":"venue"
},
  "geometry": {"coordinates":[2.297835,48.869259],"type":"Point"}
}