{
  "type": "Feature",
  "properties": {
    "iso:country":"FR",
    "sg:address":"247 cours Gambetta; Talence",
    "sg:classifiers":[
        {
            "category":"Banks & Credit Unions",
            "subcategory":"Bank",
            "type":"Services"
        }
    ],
    "sg:phone":"+33 3357350029",
    "sg:province":"Midi Pyr\u00e9n\u00e9es",
    "wof:name":"Cr\u00e9dit Lyonnais",
    "wof:placetype":"venue"
},
  "geometry": {"coordinates":[-0.590526,44.813084],"type":"Point"}
}