{
  "type": "Feature",
  "properties": {
    "iso:country":"FR",
    "sg:address":"78440 Porcheville",
    "sg:orig_category":"Unclassifiable Establishments",
    "sg:phone":"+33 1 34 78 94 00",
    "sg:province":"Ile de France",
    "wof:name":"E.d.f. - Centre De Production Thermique",
    "wof:placetype":"venue"
},
  "geometry": {"coordinates":[1.77809,48.970123],"type":"Point"}
}