{
  "type": "Feature",
  "properties": {
    "iso:country":"FR",
    "sg:address":"Ste Chateau du Breuil 14130 LE BREUIL EN AUGE",
    "sg:city":"Blangy-le-Ch\u00e2teau",
    "sg:classifiers":[
        {
            "category":"Food & Beverages",
            "subcategory":"Fruits & Vegetables",
            "type":"Retail Goods"
        }
    ],
    "sg:phone":"+33 2 31 65 60 00",
    "sg:postcode":"14130",
    "sg:province":"Basse Normandie",
    "sg:tags":[
        "brandy"
    ],
    "wof:name":"St\u00e9 Ch\u00e2teau Du Breuil S.a.",
    "wof:placetype":"venue"
},
  "geometry": {"coordinates":[0.215825,49.230255],"type":"Point"}
}