{
  "type": "Feature",
  "properties": {
    "iso:country":"FR",
    "sg:address":"B.P. 60, 40110 Morcenx C\u00e9dex^^ZI, 40110 Morcenx",
    "sg:city":"Morcenx",
    "sg:orig_category":"Non-Classified Establishments",
    "sg:phone":"+33 5 58 04 43 12",
    "sg:postcode":"40110",
    "sg:province":"Aquitaine",
    "wof:name":"Defi S.a. - Diagnostic Etude Faisabilit\u00e9 Ing\u00e9nierie",
    "wof:placetype":"venue"
},
  "geometry": {"coordinates":[-0.761829,43.957363],"type":"Point"}
}