{
  "type": "Feature",
  "properties": {
    "iso:country":"FR",
    "sg:address":"Z I 10110 Bar Sur Seine",
    "sg:classifiers":[
        {
            "category":"Food Court",
            "type":"Food & Drink"
        }
    ],
    "sg:phone":"+33 3 25 38 39 40",
    "sg:postcode":"10110",
    "sg:province":"Champagne",
    "sg:tags":[
        "product",
        "related"
    ],
    "wof:name":"Societe A Responsabilite Limitee Champagne Noellat",
    "wof:placetype":"venue"
},
  "geometry": {"coordinates":[4.376615,48.114494],"type":"Point"}
}