{
  "type": "Feature",
  "properties": {
    "addr:full":"B.P. 33, 91541 Mennecy C\u00e9dex^^46, Rue de Champoreux, 91540 Mennecy Ile de France 91540",
    "addr:postcode":"91541;91540;91540",
    "addr:street":"B.P. 33;Rue De Champoreux",
    "iso:country":"FR",
    "sg:address":"B.P. 33, 91541 Mennecy C\u00e9dex^^46, Rue de Champoreux, 91540 Mennecy",
    "sg:orig_category":"Non-Classified Establishments",
    "sg:phone":"+33 1 69 90 71 00",
    "sg:postcode":"91540",
    "sg:province":"Ile de France",
    "wof:name":"Bru\u00ebl Et Kjaer S.a.",
    "wof:placetype":"venue"
},
  "geometry": {"coordinates":[2.434665,48.566704],"type":"Point"}
}