{
  "type": "Feature",
  "properties": {
    "addr:full":"All\u00e9e Traversi\u00e8re Seclin Nord Pas-de-Calais 59113",
    "addr:postcode":"59113",
    "addr:street":"Alle\u0301E Traversie\u0300Re",
    "iso:country":"FR",
    "sg:address":"All\u00e9e Traversi\u00e8re",
    "sg:city":"Seclin",
    "sg:orig_category":"Unclassifiable Establishments",
    "sg:phone":"+33 3 28 16 91 50",
    "sg:postcode":"59113",
    "sg:province":"Nord Pas-de-Calais",
    "wof:name":"Universo S.a.s.",
    "wof:placetype":"venue"
},
  "geometry": {"coordinates":[3.026865,50.54681],"type":"Point"}
}