{
  "type": "Feature",
  "properties": {
    "iso:country":"FR",
    "sg:address":"Domaine de Capdessus 40630 Trensacq",
    "sg:city":"Trensacq",
    "sg:classifiers":[
        {
            "category":"Food & Beverages",
            "subcategory":"Fruits & Vegetables",
            "type":"Retail Goods"
        }
    ],
    "sg:phone":"+33 5 58 07 61 04",
    "sg:postcode":"40630",
    "sg:province":"Aquitaine",
    "wof:name":"Naou Sa",
    "wof:placetype":"venue"
},
  "geometry": {"coordinates":[-0.744519,44.215549],"type":"Point"}
}