{
  "type": "Feature",
  "properties": {
    "iso:country":"FR",
    "sg:address":"Chemin de la Plaine - Les Ecarroz",
    "sg:city":"Anjou",
    "sg:orig_category":"Non-Classified Establishments",
    "sg:phone":"+33 4 74 84 13 66",
    "sg:postcode":"38150",
    "sg:province":"Rhone-Alpes",
    "wof:name":"Dumortier E.a.r.l.",
    "wof:placetype":"venue"
},
  "geometry": {"coordinates":[4.823532,45.31955],"type":"Point"}
}