{
  "type": "Feature",
  "properties": {
    "iso:country":"FR",
    "sg:address":"Zi Les Pierrelets 45380 Chaingy",
    "sg:city":"Chaingy",
    "sg:classifiers":[
        {
            "category":"Manufacturing",
            "subcategory":"Rubber & Plastics",
            "type":"Manufacturing & Wholesale Goods"
        }
    ],
    "sg:phone":"+33 2 38 43 31 90",
    "sg:postcode":"45380",
    "sg:province":"Centre",
    "sg:tags":[
        "packaging",
        "material",
        "-"
    ],
    "wof:name":"Soparco",
    "wof:placetype":"venue"
},
  "geometry": {"coordinates":[1.77233,47.88353],"type":"Point"}
}