{
  "type": "Feature",
  "properties": {
    "iso:country":"FR",
    "sg:address":"59, Rte de Badet, 33770 Salles",
    "sg:city":"Salles",
    "sg:orig_category":"Unclassifiable Establishments",
    "sg:phone":"+33 5 56 88 41 48",
    "sg:postcode":"33770",
    "sg:province":"Aquitaine",
    "wof:name":"Etablissements Delobel S.a.",
    "wof:placetype":"venue"
},
  "geometry": {"coordinates":[-0.864481,44.548668],"type":"Point"}
}