{
  "type": "Feature",
  "properties": {
    "iso:country":"FR",
    "sg:address":"109, Bd P\u00e9reire, 75017 Paris",
    "sg:orig_category":"Non-Classified Establishments",
    "sg:phone":"+33 1 56 79 15 15",
    "sg:postcode":"75017",
    "sg:province":"Ile de France",
    "wof:name":"Dialogues Direct S.a.r.l.",
    "wof:placetype":"venue"
},
  "geometry": {"coordinates":[2.299607,48.885712],"type":"Point"}
}