{
  "type": "Feature",
  "properties": {
    "addr:full":"Le Balmay 01430 Vieu D'Izenave Rhone-Alpes 01430",
    "addr:postcode":"01430;01430",
    "addr:street":"Rhone-Alpes",
    "iso:country":"FR",
    "sg:address":"Le Balmay 01430 Vieu D'Izenave",
    "sg:classifiers":[
        {
            "category":"Farming",
            "subcategory":"Livestock Farm",
            "type":"Manufacturing & Wholesale Goods"
        }
    ],
    "sg:phone":"+33 4 74 76 34 27",
    "sg:postcode":"01430",
    "sg:province":"Rhone-Alpes",
    "sg:tags":[
        "breeding",
        "agriculture",
        "animal"
    ],
    "wof:name":"Larcon Freres",
    "wof:placetype":"venue"
},
  "geometry": {"coordinates":[5.544345,46.093575],"type":"Point"}
}