{
  "type": "Feature",
  "properties": {
    "iso:country":"FR",
    "sg:address":"22 Rue Garnier",
    "sg:city":"Neuilly Sur Seine",
    "sg:classifiers":[
        {
            "category":"Banks & Credit Unions",
            "subcategory":"Financial Services",
            "type":"Services"
        }
    ],
    "sg:phone":"+33 1 55 72 60 00",
    "sg:postcode":"92200",
    "sg:province":"Ile de France",
    "sg:tags":[
        "banking",
        "finance",
        "insurance"
    ],
    "wof:name":"Les Laboratoires Servier",
    "wof:placetype":"venue"
},
  "geometry": {"coordinates":[2.258523,48.886909],"type":"Point"}
}