{
  "type": "Feature",
  "properties": {
    "addr:full":"2, Av. Jacques Brel, 31570 Sainte Foy d'Aigrefeuille Midi Pyr\u00e9n\u00e9es",
    "addr:postcode":"31570",
    "addr:street":"Av. Jacques Brel;Foy D'Aigrefeuille Midi",
    "iso:country":"FR",
    "sg:address":"2, Av. Jacques Brel, 31570 Sainte Foy d'Aigrefeuille",
    "sg:orig_category":"Unclassifiable Establishments",
    "sg:phone":"+33 5 61 83 89 38",
    "sg:province":"Midi Pyr\u00e9n\u00e9es",
    "wof:name":"Web Synergy S.a.s.",
    "wof:placetype":"venue"
},
  "geometry": {"coordinates":[1.604218,43.545254],"type":"Point"}
}