{
  "type": "Feature",
  "properties": {
    "addr:full":"Quartier Rougnac 32600 L Isle Jourdain Midi Pyr\u00e9n\u00e9es 32600",
    "addr:postcode":"32600;32600",
    "iso:country":"FR",
    "sg:address":"Quartier Rougnac 32600 L Isle Jourdain",
    "sg:classifiers":[
        {
            "category":"Shopping",
            "subcategory":"Clothing, Apparel, & Fashions",
            "type":"Retail Goods"
        }
    ],
    "sg:phone":"+33 5 62 07 12 11",
    "sg:postcode":"32600",
    "sg:province":"Midi Pyr\u00e9n\u00e9es",
    "sg:tags":[
        "textile",
        "clothing",
        "clothes"
    ],
    "wof:name":"Societe Nouvelle Armagnac Midi",
    "wof:placetype":"venue"
},
  "geometry": {"coordinates":[1.020175,43.552231],"type":"Point"}
}