{
  "type": "Feature",
  "properties": {
    "addr:full":"38, Rue de la Poterie, 50450 Gavray Gavray Basse Normandie 50450",
    "addr:housenumber":"38",
    "addr:postcode":"50450;50450",
    "addr:street":"Rue De La Poterie",
    "iso:country":"FR",
    "sg:address":"38, Rue de la Poterie, 50450 Gavray",
    "sg:city":"Gavray",
    "sg:orig_category":"Unclassifiable Establishments",
    "sg:phone":"+33 2 33 61 41 92",
    "sg:postcode":"50450",
    "sg:province":"Basse Normandie",
    "wof:name":"Sofic S.a.",
    "wof:placetype":"venue"
},
  "geometry": {"coordinates":[-1.347109,48.910709],"type":"Point"}
}