{
  "type": "Feature",
  "properties": {
    "addr:full":"B.P. 597, 62411 B\u00e9thune C\u00e9dex^^Rue Fleming, 62400 B\u00e9thune Nord Pas-de-Calais",
    "addr:housenumber":"b.p. 597",
    "addr:postcode":"62411;62400",
    "addr:street":"Ce\u0301Dex^^Rue Fleming",
    "iso:country":"FR",
    "sg:address":"B.P. 597, 62411 B\u00e9thune C\u00e9dex^^Rue Fleming, 62400 B\u00e9thune",
    "sg:orig_category":"Non-Classified Establishments",
    "sg:phone":"+33 3 21 61 78 36",
    "sg:province":"Nord Pas-de-Calais",
    "wof:name":"H\u00e9co Diffusion S.a.r.l.",
    "wof:placetype":"venue"
},
  "geometry": {"coordinates":[2.63787,50.530472],"type":"Point"}
}