{
  "type": "Feature",
  "properties": {
    "iso:country":"FR",
    "sg:address":"10, Rue de Picardie, 95310 Saint Ouen l'Aum\u00f4ne",
    "sg:orig_category":"Unclassifiable Establishments",
    "sg:phone":"+33 1 34 48 31 00",
    "sg:province":"Ile de France",
    "wof:name":"Haynes International S.a.r.l.",
    "wof:placetype":"venue"
},
  "geometry": {"coordinates":[1.67314,50.271332],"type":"Point"}
}