{
  "type": "Feature",
  "properties": {
    "iso:country":"FR",
    "sg:address":"19, Av. des Indes, 91940 Les Ulis",
    "sg:orig_category":"Non-Classified Establishments",
    "sg:phone":"+33 1 63 18 75 25",
    "sg:province":"Ile de France",
    "wof:name":"P.m.s. S.a.r.l. - Pr\u00e9sence Micro Syst\u00e8me",
    "wof:placetype":"venue"
},
  "geometry": {"coordinates":[2.204172,48.68512],"type":"Point"}
}