{
  "type": "Feature",
  "properties": {
    "addr:full":"107, Av. Henry Fr\u00e9ville, 35200 Rennes Rennes Bretagne 35200",
    "addr:postcode":"35200;35200",
    "addr:street":"107 Av. Henry Fre\u0301Ville",
    "iso:country":"FR",
    "sg:address":"107, Av. Henry Fr\u00e9ville, 35200 Rennes",
    "sg:city":"Rennes",
    "sg:orig_category":"Unclassifiable Establishments",
    "sg:phone":"+33 2 99 22 32 00",
    "sg:postcode":"35200",
    "sg:province":"Bretagne",
    "wof:name":"F\u00e9ridis S.a.r.l.",
    "wof:placetype":"venue"
},
  "geometry": {"coordinates":[-1.674178,48.087139],"type":"Point"}
}