{
  "type": "Feature",
  "properties": {
    "addr:full":"B.P. 7, 38490 Chimilin C\u00e9dex^^ZA de Poulattier, 38490 Chimilin Rhone-Alpes 38490",
    "addr:housenumber":"7",
    "addr:postcode":"38490;38490;38490",
    "addr:street":"B.P.;Rhone-Alpes",
    "iso:country":"FR",
    "sg:address":"B.P. 7, 38490 Chimilin C\u00e9dex^^ZA de Poulattier, 38490 Chimilin",
    "sg:orig_category":"Non-Classified Establishments",
    "sg:phone":"+33 4 76 32 50 15",
    "sg:postcode":"38490",
    "sg:province":"Rhone-Alpes",
    "wof:name":"Aluminium Martigny France S.a.",
    "wof:placetype":"venue"
},
  "geometry": {"coordinates":[5.59776,45.510784],"type":"Point"}
}