{
  "type": "Feature",
  "properties": {
    "iso:country":"FR",
    "sg:address":"Rue de la Sucrerie - ZI du Foirail",
    "sg:city":"Sault les Rethel",
    "sg:orig_category":"Unclassifiable Establishments",
    "sg:phone":"+33 3 24 38 06 76",
    "sg:postcode":"08300",
    "sg:province":"Champagne",
    "wof:name":"Alum\u00e9tal S.a.r.l.",
    "wof:placetype":"venue"
},
  "geometry": {"coordinates":[4.354238,49.498524],"type":"Point"}
}