{
  "type": "Feature",
  "properties": {
    "iso:country":"FR",
    "sg:address":"13 rue Emile Ch\u00e9nel 14500 VIRE",
    "sg:city":"Vire",
    "sg:classifiers":[
        {
            "category":"Train Station",
            "subcategory":"Rail",
            "type":"Transportation"
        }
    ],
    "sg:phone":"+33 2 31 66 44 00",
    "sg:postcode":"14500",
    "sg:province":"Basse Normandie",
    "sg:tags":[
        "steel",
        "cutlery",
        "rust-proof"
    ],
    "wof:name":"Guy Degrenne S.a.",
    "wof:placetype":"venue"
},
  "geometry": {"coordinates":[-0.886623,48.834743],"type":"Point"}
}