{
  "type": "Feature",
  "properties": {
    "addr:full":"52-54 avenue du 8 Mai 1945 95200 Sarcelles Ile de France 95200",
    "addr:housenumber":"52-54",
    "addr:postcode":"95200;ile;95200",
    "addr:street":"Avenue Du 8 Mai 1945;France",
    "iso:country":"FR",
    "sg:address":"52-54 avenue du 8 Mai 1945 95200 Sarcelles",
    "sg:classifiers":[
        {
            "category":"Shopping",
            "subcategory":"Computers & Home Electronics",
            "type":"Retail Goods"
        }
    ],
    "sg:phone":"+33 1 34 19 98 00",
    "sg:postcode":"95200",
    "sg:province":"Ile de France",
    "sg:tags":[
        "electronic",
        "module"
    ],
    "wof:name":"Cart Electronique S.a.r.l.",
    "wof:placetype":"venue"
},
  "geometry": {"coordinates":[2.36812,48.978111],"type":"Point"}
}