{
  "type": "Feature",
  "properties": {
    "iso:country":"FR",
    "sg:address":"335, Chemin du Chaland, 13270 Fos sur Mer",
    "sg:orig_category":"Unclassifiable Establishments",
    "sg:phone":"+33 4 42 05 09 82",
    "sg:province":"Provence-Alpes-C\u00f4te d'Azur",
    "wof:name":"S.d.c.p.t. Aliz\u00e9 S.a. - Saint Didier Construction Prestation Transport",
    "wof:placetype":"venue"
},
  "geometry": {"coordinates":[4.931497,43.455498],"type":"Point"}
}