{
  "type": "Feature",
  "properties": {
    "addr:full":"93, Rue de la Marne, 95220 Herblay Ile de France",
    "addr:housenumber":"93",
    "addr:postcode":"95220;ile",
    "addr:street":"Rue De La Marne",
    "iso:country":"FR",
    "sg:address":"93, Rue de la Marne, 95220 Herblay",
    "sg:orig_category":"Unclassifiable Establishments",
    "sg:phone":"+33 1 39 97 65 10",
    "sg:province":"Ile de France",
    "wof:name":"Motralec S.a.",
    "wof:placetype":"venue"
},
  "geometry": {"coordinates":[2.18209,49.000751],"type":"Point"}
}