{
  "type": "Feature",
  "properties": {
    "addr:full":"16 Bd Du Mond'Est 93192 Noisy Le Grand Cedex Lorraine",
    "addr:housenumber":"16",
    "addr:postcode":"93192",
    "addr:street":"Bd Du Mond'Est",
    "iso:country":"FR",
    "sg:address":"16 Bd Du Mond'Est 93192 Noisy Le Grand Cedex",
    "sg:classifiers":[
        {
            "category":"Professional",
            "subcategory":"Business Services",
            "type":"Services"
        }
    ],
    "sg:phone":"+33 1 48 15 18 90",
    "sg:province":"Lorraine",
    "sg:tags":[
        "body",
        "advice"
    ],
    "wof:name":"Inst Recherches Economique Sociales",
    "wof:placetype":"venue"
},
  "geometry": {"coordinates":[2.394186,48.87101],"type":"Point"}
}