{
  "type": "Feature",
  "properties": {
    "iso:country":"FR",
    "sg:address":"B.P. 9, 62840 Laventie^^91, Rue du G\u00e9n\u00e9ral de Gaulle, 62840 Laventie",
    "sg:orig_category":"Non-Classified Establishments",
    "sg:phone":"+33 3 21 27 63 33",
    "sg:postcode":"62840",
    "sg:province":"Nord Pas-de-Calais",
    "wof:name":"Berthier Production S.a.",
    "wof:placetype":"venue"
},
  "geometry": {"coordinates":[2.772065,50.626614],"type":"Point"}
}