{
  "type": "Feature",
  "properties": {
    "iso:country":"FR",
    "sg:address":"82, Av. du Ch\u00e2teau, 95310 Saint Ouen l'Aum\u00f4ne",
    "sg:orig_category":"Unclassifiable Establishments",
    "sg:phone":"+33 1 34 21 93 22",
    "sg:province":"Ile de France",
    "wof:name":"C.e.i. S.a. - Compagnie Europ\u00e9enne De L'inox",
    "wof:placetype":"venue"
},
  "geometry": {"coordinates":[1.195581,49.690762],"type":"Point"}
}