{
  "type": "Feature",
  "properties": {
    "addr:full":"La Croix Saint Mathieu Za 28320 Gallardon Gallardon Centre 28320",
    "addr:postcode":"28320;28320",
    "addr:street":"La Croix Saint Mathieu Za",
    "iso:country":"FR",
    "sg:address":"La Croix Saint Mathieu Za 28320 Gallardon",
    "sg:city":"Gallardon",
    "sg:orig_category":"Games and entertainment Horticulture Miscellaneous Products",
    "sg:phone":"+33 2 37 31 00 10",
    "sg:postcode":"28320",
    "sg:province":"Centre",
    "wof:name":"Societe De Pulverisateurs Andre Cornu",
    "wof:placetype":"venue"
},
  "geometry": {"coordinates":[1.68767,48.52486],"type":"Point"}
}