{
  "type": "Feature",
  "properties": {
    "iso:country":"FR",
    "sg:address":"Rte de Damville - ZI Les Pistes",
    "sg:city":"Conches en Ouche",
    "sg:orig_category":"Unclassifiable Establishments",
    "sg:phone":"+33 2 32 30 56 62",
    "sg:postcode":"27190",
    "sg:province":"Haute Normandie",
    "wof:name":"Roux S.a.",
    "wof:placetype":"venue"
},
  "geometry": {"coordinates":[0.914948,48.911053],"type":"Point"}
}