{
  "type": "Feature",
  "properties": {
    "addr:full":"92 rue R\u00e9aumur 75002 Paris Ile de France 75002",
    "addr:housenumber":"92",
    "addr:postcode":"75002;75002",
    "addr:street":"Rue Re\u0301Aumur",
    "iso:country":"FR",
    "sg:address":"92 rue R\u00e9aumur 75002 Paris",
    "sg:orig_category":"Analysis For Textiles",
    "sg:phone":"+33 1 44 82 69 66",
    "sg:postcode":"75002",
    "sg:province":"Ile de France",
    "wof:name":"Devanlay S.a.",
    "wof:placetype":"venue"
},
  "geometry": {"coordinates":[2.349833,48.866928],"type":"Point"}
}