{
  "type": "Feature",
  "properties": {
    "addr:full":"Rue de Flandre - ZA Village Nord Lillers Nord Pas-de-Calais 62190",
    "addr:postcode":"62190",
    "addr:street":"Rue De Flandre Za Village Nord Lillers Nord",
    "iso:country":"FR",
    "sg:address":"Rue de Flandre - ZA Village Nord",
    "sg:city":"Lillers",
    "sg:orig_category":"Unclassifiable Establishments",
    "sg:phone":"+33 3 21 54 10 77",
    "sg:postcode":"62190",
    "sg:province":"Nord Pas-de-Calais",
    "wof:name":"Applisurfaces S.a.r.l.",
    "wof:placetype":"venue"
},
  "geometry": {"coordinates":[2.480824,50.563316],"type":"Point"}
}