{
  "type": "Feature",
  "properties": {
    "addr:full":"4 rue de Messy 74300 Cluses Rhone-Alpes 74300",
    "addr:housenumber":"4",
    "addr:postcode":"74300;74300",
    "addr:street":"Rue De Messy",
    "iso:country":"FR",
    "sg:address":"4 rue de Messy 74300 Cluses",
    "sg:classifiers":[
        {
            "category":"Shopping Center",
            "type":"Public Place"
        }
    ],
    "sg:phone":"+33 4 50 98 09 00",
    "sg:postcode":"74300",
    "sg:province":"Rhone-Alpes",
    "sg:tags":[
        "nut",
        "eye",
        "bolt"
    ],
    "wof:name":"Ravinet Industrie Sa",
    "wof:placetype":"venue"
},
  "geometry": {"coordinates":[6.570879,46.062317],"type":"Point"}
}