{
  "type": "Feature",
  "properties": {
    "iso:country":"FR",
    "sg:address":"42 Av De Friedland 75008 Paris",
    "sg:classifiers":[
        {
            "category":"Utilities",
            "subcategory":"Telephone",
            "type":"Services"
        }
    ],
    "sg:phone":"+33 1 71 07 07 07",
    "sg:province":"Ile de France",
    "sg:tags":[
        "telecommunication"
    ],
    "wof:name":"Vivindi",
    "wof:placetype":"venue"
},
  "geometry": {"coordinates":[2.297465,48.87413],"type":"Point"}
}