{
  "type": "Feature",
  "properties": {
    "addr:full":"46, Av. des Fr\u00e8res Lumi\u00e8re, 78190 Trappes Ile de France",
    "addr:postcode":"78190;ile",
    "addr:street":"46 Av. Des Fre\u0300Res Lumie\u0300Re",
    "iso:country":"FR",
    "sg:address":"46, Av. des Fr\u00e8res Lumi\u00e8re, 78190 Trappes",
    "sg:orig_category":"Non-Classified Establishments",
    "sg:phone":"+33 1 30 13 15 78",
    "sg:province":"Ile de France",
    "wof:name":"Lohmann Lah",
    "wof:placetype":"venue"
},
  "geometry": {"coordinates":[1.991246,48.760307],"type":"Point"}
}