{
  "type": "Feature",
  "properties": {
    "iso:country":"FR",
    "sg:address":"37, Rue Denis Epitalon, 42000 Saint Etienne",
    "sg:orig_category":"Unclassifiable Establishments",
    "sg:phone":"+33 4 77 32 89 28",
    "sg:province":"Rhone-Alpes",
    "wof:name":"Soci\u00e9t\u00e9 D'exploitation Des Transports D'charra S.a.r.l.",
    "wof:placetype":"venue"
},
  "geometry": {"coordinates":[4.380574,45.429237],"type":"Point"}
}