{
  "type": "Feature",
  "properties": {
    "addr:full":"Quartier Valmy 31 Ronde; La D\u00e9fense; 92986 Midi Pyr\u00e9n\u00e9es",
    "addr:housenumber":"31",
    "addr:postcode":"92986",
    "addr:street":"Quartier Valmy;Ronde La",
    "iso:country":"FR",
    "sg:address":"Quartier Valmy 31",
    "sg:city":"Ronde; La D\u00e9fense; 92986",
    "sg:classifiers":[
        {
            "category":"Industrial Area",
            "type":"Public Place"
        }
    ],
    "sg:phone":"+33 1 41 02 82 00",
    "sg:province":"Midi Pyr\u00e9n\u00e9es",
    "sg:tags":[
        "large",
        "private"
    ],
    "wof:name":"Assystem",
    "wof:placetype":"venue"
},
  "geometry": {"coordinates":[2.24119,48.888939],"type":"Point"}
}