{
  "type": "Feature",
  "properties": {
    "addr:full":"2, Rue des Romains, 68580 Friesen Friesen Alsace 68580",
    "addr:housenumber":"2",
    "addr:postcode":"68580;68580",
    "addr:street":"Rue Des Romains;Friesen",
    "iso:country":"FR",
    "sg:address":"2, Rue des Romains, 68580 Friesen",
    "sg:city":"Friesen",
    "sg:orig_category":"Unclassifiable Establishments",
    "sg:phone":"+33 3 89 25 62 23",
    "sg:postcode":"68580",
    "sg:province":"Alsace",
    "wof:name":"Osa S.a.r.l.",
    "wof:placetype":"venue"
},
  "geometry": {"coordinates":[7.156415,47.560749],"type":"Point"}
}