{
  "type": "Feature",
  "properties": {
    "iso:country":"FR",
    "sg:address":"2, Rue des Romains, 68580 Friesen",
    "sg:city":"Friesen",
    "sg:orig_category":"Unclassifiable Establishments",
    "sg:phone":"+33 3 89 25 62 23",
    "sg:postcode":"68580",
    "sg:province":"Alsace",
    "wof:name":"Osa S.a.r.l.",
    "wof:placetype":"venue"
},
  "geometry": {"coordinates":[7.156415,47.560749],"type":"Point"}
}