{
  "type": "Feature",
  "properties": {
    "iso:country":"FR",
    "sg:address":"161 Rue D Altorf 67120 Dachstein",
    "sg:city":"Dachstein",
    "sg:classifiers":[
        {
            "category":"Home & Garden",
            "subcategory":"Furniture",
            "type":"Retail Goods"
        }
    ],
    "sg:phone":"+33 3 88 38 18 86",
    "sg:postcode":"67120",
    "sg:province":"Alsace",
    "sg:tags":[
        "household",
        "wood"
    ],
    "wof:name":"Societe D'exploitation Des Etablissements Raugel Richard",
    "wof:placetype":"venue"
},
  "geometry": {"coordinates":[7.533391,48.550468],"type":"Point"}
}