{
  "type": "Feature",
  "properties": {
    "iso:country":"FR",
    "sg:address":"B.P. 55",
    "sg:city":"Espaly Saint Marcel C\u00e9dex^^Le S\u00e9jalat 43000 Espaly Saint Marcel",
    "sg:orig_category":"Non-Classified Establishments",
    "sg:phone":"+33 4 71 09 24 51",
    "sg:postcode":"43002",
    "sg:province":"Auvergne",
    "wof:name":"Soci\u00e9t\u00e9 Nouvelle Elastelle S.a.",
    "wof:placetype":"venue"
},
  "geometry": {"coordinates":[3.866693,45.049038],"type":"Point"}
}