{
  "type": "Feature",
  "properties": {
    "addr:full":"Impasse Gui Rue Saint Etienne 58019 Nevers Cedex Picardie",
    "addr:postcode":"58019",
    "addr:street":"Impasse Gui Rue Saint Etienne",
    "iso:country":"FR",
    "sg:address":"Impasse Gui Rue Saint Etienne 58019 Nevers Cedex",
    "sg:classifiers":[
        {
            "category":"Farming",
            "subcategory":"Farm & Veterinary Services",
            "type":"Manufacturing & Wholesale Goods"
        }
    ],
    "sg:phone":"+33 3 86 71 82 50",
    "sg:province":"Picardie",
    "sg:tags":[
        "advice",
        "agriculture",
        "livestock",
        "business"
    ],
    "wof:name":"Office National Des Forets (onf)",
    "wof:placetype":"venue"
},
  "geometry": {"coordinates":[3.16169,46.98711],"type":"Point"}
}