{
  "type": "Feature",
  "properties": {
    "iso:country":"FR",
    "sg:address":"195 Av Paul Vaillant Couturier",
    "sg:city":"Bobigny",
    "sg:classifiers":[
        {
            "category":"Banks & Credit Unions",
            "subcategory":"Financial Services",
            "type":"Services"
        }
    ],
    "sg:phone":"+33 1 48 96 48 48",
    "sg:postcode":"93014",
    "sg:province":"Ile de France",
    "sg:tags":[
        "banking",
        "finance",
        "insurance"
    ],
    "wof:name":"Cpam Seine Saint Denis",
    "wof:placetype":"venue"
},
  "geometry": {"coordinates":[2.454346,48.907497],"type":"Point"}
}