{
  "type": "Feature",
  "properties": {
    "iso:country":"FR",
    "sg:address":"B.P. 130, 78196 Trappes C\u00e9dex^^2, rue des H\u00eatres - Miniparc du Manet, 78190 Trappes",
    "sg:orig_category":"Non-Classified Establishments",
    "sg:phone":"+33 1 30 13 80 00",
    "sg:province":"Ile de France",
    "wof:name":"Hellermann France S.a.",
    "wof:placetype":"venue"
},
  "geometry": {"coordinates":[1.999285,48.774651],"type":"Point"}
}