{
  "type": "Feature",
  "properties": {
    "addr:full":"Rte De Crulai Zi De La Fremondi\u00e8re 61300 L'Aigle Crulai Basse Normandie 61300",
    "addr:postcode":"61300;61300",
    "addr:street":"Rte De Crulai Zi De La Fremondie\u0300Re",
    "iso:country":"FR",
    "sg:address":"Rte De Crulai Zi De La Fremondi\u00e8re 61300 L'Aigle",
    "sg:city":"Crulai",
    "sg:classifiers":[
        {
            "category":"Manufacturing",
            "subcategory":"Building Materials",
            "type":"Manufacturing & Wholesale Goods"
        }
    ],
    "sg:phone":"+33 2 33 84 50 50",
    "sg:postcode":"61300",
    "sg:province":"Basse Normandie",
    "sg:tags":[
        "-",
        "machine",
        "raw",
        "engineering",
        "paper",
        "mechanical",
        "cardboard"
    ],
    "wof:name":"Pelletier Et Jaminet",
    "wof:placetype":"venue"
},
  "geometry": {"coordinates":[0.738917,48.751774],"type":"Point"}
}