{
  "type": "Feature",
  "properties": {
    "addr:full":"B.P. 16, 67610 La Wantzenau^^5, Rue Gutenberg - ZA, 67610 La Wantzenau La Wantzenau Alsace 67610",
    "addr:housenumber":"67610",
    "addr:postcode":"67610;67610",
    "addr:street":"B.P. 16;Rue Gutenberg Za;Wantzenau",
    "iso:country":"FR",
    "sg:address":"B.P. 16, 67610 La Wantzenau^^5, Rue Gutenberg - ZA, 67610 La Wantzenau",
    "sg:city":"La Wantzenau",
    "sg:orig_category":"Non-Classified Establishments",
    "sg:phone":"+33 3 88 96 29 39",
    "sg:postcode":"67610",
    "sg:province":"Alsace",
    "wof:name":"Mecasal S.a.r.l.",
    "wof:placetype":"venue"
},
  "geometry": {"coordinates":[7.825742,48.65926],"type":"Point"}
}