{
  "type": "Feature",
  "properties": {
    "addr:full":"B.P. 77, 33390 Blaye^^19, Rue des Ma\u00e7ons, 33390 Blaye Blaye Aquitaine 33390",
    "addr:postcode":"33390;33390;33390",
    "addr:street":"B.P. 77;Rue Des Mac\u0327Ons",
    "iso:country":"FR",
    "sg:address":"B.P. 77, 33390 Blaye^^19, Rue des Ma\u00e7ons, 33390 Blaye",
    "sg:city":"Blaye",
    "sg:orig_category":"Non-Classified Establishments",
    "sg:phone":"+33 5 57 42 04 65",
    "sg:postcode":"33390",
    "sg:province":"Aquitaine",
    "wof:name":"Donitian Groupe S.a.r.l.",
    "wof:placetype":"venue"
},
  "geometry": {"coordinates":[-0.642894,45.101875],"type":"Point"}
}