{
  "type": "Feature",
  "properties": {
    "iso:country":"FR",
    "sg:address":"2 Rue De La Scierie 80200 Doingt Flamicourt",
    "sg:classifiers":[
        {
            "category":"Banks & Credit Unions",
            "subcategory":"Bank",
            "type":"Services"
        }
    ],
    "sg:phone":"+33 3 22 84 13 95",
    "sg:postcode":"80200",
    "sg:province":"Picardie",
    "sg:tags":[
        "good",
        "livestock",
        "business",
        "advice",
        "material",
        "-",
        "equipment",
        "handling",
        "agriculture"
    ],
    "wof:name":"Exploitation Forestiere Nobecourt",
    "wof:placetype":"venue"
},
  "geometry": {"coordinates":[2.966186,49.921902],"type":"Point"}
}