{
  "type": "Feature",
  "properties": {
    "addr:full":"645, Av. Mayor de Montricher - B\u00e2t Technidus D1, 13854 Aix en Provence C\u00e9dex 03 Nord Pas-de-Calais",
    "addr:housenumber":"645;ba\u0302t;d1;03",
    "addr:postcode":"13854",
    "addr:street":"Av. Mayor De Montricher;Ce\u0301Dex",
    "iso:country":"FR",
    "sg:address":"645, Av. Mayor de Montricher - B\u00e2t Technidus D1, 13854 Aix en Provence C\u00e9dex 03",
    "sg:orig_category":"Non-Classified Establishments",
    "sg:phone":"+33 4 42 39 32 80",
    "sg:province":"Nord Pas-de-Calais",
    "wof:name":"Franciaflex Industrie S.a.",
    "wof:placetype":"venue"
},
  "geometry": {"coordinates":[5.382159,43.480019],"type":"Point"}
}