{
  "type": "Feature",
  "properties": {
    "iso:country":"FR",
    "sg:address":"Loge Coucou 56320 Lanv\u00e9n\u00e9gen",
    "sg:city":"Lanv\u00e9n\u00e9gen",
    "sg:orig_category":"Animals and breeding Food and Related Products Fruits and vegetables Preserves",
    "sg:phone":"+33 2 97 23 07 15",
    "sg:postcode":"56320",
    "sg:province":"Bretagne",
    "wof:name":"Conserverie Morbihannaise Sa",
    "wof:placetype":"venue"
},
  "geometry": {"coordinates":[-3.4993,47.984997],"type":"Point"}
}