{
  "type": "Feature",
  "properties": {
    "iso:country":"FR",
    "sg:address":"Rue des Quatres Filles",
    "sg:city":"\u00c9pernon",
    "sg:orig_category":"Unclassifiable Establishments",
    "sg:phone":"+33 2 37 20 33 33",
    "sg:postcode":"28230",
    "sg:province":"Centre",
    "wof:name":"Laboratoires Pharmascience S.a.",
    "wof:placetype":"venue"
},
  "geometry": {"coordinates":[1.67713,48.609051],"type":"Point"}
}