{
  "type": "Feature",
  "properties": {
    "iso:country":"FR",
    "sg:address":"Zi De L'Aubr\u00e9e 72300 Sabl\u00e9e Sur Sarthe",
    "sg:classifiers":[
        {
            "category":"Food & Beverages",
            "subcategory":"Groceries & Convenience Stores",
            "type":"Retail Goods"
        }
    ],
    "sg:phone":"+33 2 43 62 12 20",
    "sg:postcode":"72300",
    "sg:province":"Pays de Loire",
    "sg:tags":[
        "product",
        "related"
    ],
    "wof:name":"Generale Traiteur",
    "wof:placetype":"venue"
},
  "geometry": {"coordinates":[-0.327631,47.836143],"type":"Point"}
}