{
  "type": "Feature",
  "properties": {
    "iso:country":"FR",
    "sg:address":"18, Av. Franklin Roosevelt, 78200 Mantes la Jolie",
    "sg:orig_category":"Non-Classified Establishments",
    "sg:phone":"+33 1 30 98 62 15",
    "sg:province":"Ile de France",
    "wof:name":"Maser S.a.r.l. - Manutention Automatismes Servitudes",
    "wof:placetype":"venue"
},
  "geometry": {"coordinates":[1.709066,48.9902],"type":"Point"}
}