{
  "type": "Feature",
  "properties": {
    "iso:country":"FR",
    "sg:address":"540, Rue des Entrepreneurs, 78570 Vernouillet",
    "sg:orig_category":"Unclassifiable Establishments",
    "sg:phone":"+33 1 39 71 04 04",
    "sg:province":"Ile de France",
    "wof:name":"R.s.a. S.a.r.l. - Riv\u00e9lec Surcables Associ\u00e9s",
    "wof:placetype":"venue"
},
  "geometry": {"coordinates":[-97.911423,26.14126],"type":"Point"}
}