{
  "type": "Feature",
  "properties": {
    "addr:full":"Rte du Pin la Garenne Mauves sur Huisne Basse Normandie 61400",
    "addr:postcode":"61400",
    "addr:street":"Rte Du Pin La Garenne;Huisne Basse",
    "iso:country":"FR",
    "sg:address":"Rte du Pin la Garenne",
    "sg:city":"Mauves sur Huisne",
    "sg:orig_category":"Unclassifiable Establishments",
    "sg:phone":"+33 2 33 83 83 44",
    "sg:postcode":"61400",
    "sg:province":"Basse Normandie",
    "wof:name":"Etablissement Baert S.a.",
    "wof:placetype":"venue"
},
  "geometry": {"coordinates":[0.55013,48.423157],"type":"Point"}
}