{
  "type": "Feature",
  "properties": {
    "iso:country":"FR",
    "sg:address":"26/38, Rue du G\u00e9n\u00e9ral Malleret Joinville, 94405 Vitry sur Seine C\u00e9dex",
    "sg:city":"Vill\u00e9",
    "sg:orig_category":"Non-Classified Establishments",
    "sg:phone":"+33 1 47 18 14 80",
    "sg:postcode":"67220",
    "sg:province":"Alsace",
    "wof:name":"T.e.b. S.a.",
    "wof:placetype":"venue"
},
  "geometry": {"coordinates":[2.407166,48.774193],"type":"Point"}
}