{
  "type": "Feature",
  "properties": {
    "addr:full":"Rue Jacquard - Parc d'Activit\u00e9 Lavoisier Petite For\u00eat Nord Pas-de-Calais 59410",
    "addr:postcode":"59410",
    "addr:street":"Rue Jacquard Parc D'Activite \u0301 Lavoisier;Fore\u0302T",
    "iso:country":"FR",
    "sg:address":"Rue Jacquard - Parc d'Activit\u00e9 Lavoisier",
    "sg:city":"Petite For\u00eat",
    "sg:orig_category":"Unclassifiable Establishments",
    "sg:phone":"+33 3 27 14 18 00",
    "sg:postcode":"59410",
    "sg:province":"Nord Pas-de-Calais",
    "wof:name":"Alsthom Transport S.a.",
    "wof:placetype":"venue"
},
  "geometry": {"coordinates":[3.475998,50.382172],"type":"Point"}
}