{
  "type": "Feature",
  "properties": {
    "addr:full":"7, Rue Jules Vernes - ZI de Wins, 62575 Blendecques Nord Pas-de-Calais",
    "addr:housenumber":"7",
    "addr:postcode":"62575",
    "addr:street":"Rue Jules Vernes Zi De Wins",
    "iso:country":"FR",
    "sg:address":"7, Rue Jules Vernes - ZI de Wins, 62575 Blendecques",
    "sg:orig_category":"Non-Classified Establishments",
    "sg:phone":"+33 3 21 39 87 06",
    "sg:province":"Nord Pas-de-Calais",
    "wof:name":"S.a. Caf\u00e9s Boulet Coq Prim\u00e9 S.a.",
    "wof:placetype":"venue"
},
  "geometry": {"coordinates":[2.27307,50.715118],"type":"Point"}
}