{
  "type": "Feature",
  "properties": {
    "addr:full":"Za Du Grand Clos 14320 St Andre Sur Orne Clinchamps-sur-Orne Basse Normandie 14320",
    "addr:postcode":"14320;14320",
    "addr:street":"Za Du Grand Clos",
    "iso:country":"FR",
    "sg:address":"Za Du Grand Clos 14320 St Andre Sur Orne",
    "sg:city":"Clinchamps-sur-Orne",
    "sg:classifiers":[
        {
            "category":"Professional",
            "subcategory":"Engineering",
            "type":"Services"
        }
    ],
    "sg:phone":"+33 2 31 79 63 72",
    "sg:postcode":"14320",
    "sg:province":"Basse Normandie",
    "sg:tags":[
        "machine",
        "-",
        "mechanical"
    ],
    "wof:name":"Matal Sa",
    "wof:placetype":"venue"
},
  "geometry": {"coordinates":[-0.381466,49.116539],"type":"Point"}
}