{
  "type": "Feature",
  "properties": {
    "addr:full":"ZI Arsac Sainte Rad\u00e9gonde Midi Pyr\u00e9n\u00e9es 12850",
    "addr:postcode":"12850",
    "iso:country":"FR",
    "sg:address":"ZI Arsac",
    "sg:city":"Sainte Rad\u00e9gonde",
    "sg:orig_category":"Non-Classified Establishments",
    "sg:phone":"+33 5 65 77 67 00",
    "sg:postcode":"12850",
    "sg:province":"Midi Pyr\u00e9n\u00e9es",
    "wof:name":"A.d.r. S.a.r.l. - Abattoirs De Rodez",
    "wof:placetype":"venue"
},
  "geometry": {"coordinates":[2.62688,44.337284],"type":"Point"}
}