{
  "type": "Feature",
  "properties": {
    "iso:country":"FR",
    "sg:address":"143 Bd Anatole France 93200 St Denis",
    "sg:classifiers":[
        {
            "category":"Health Services",
            "subcategory":"Medical Lab",
            "type":"Services"
        }
    ],
    "sg:phone":"+33 1 55 87 30 00",
    "sg:postcode":"93200",
    "sg:province":"Ile de France",
    "sg:tags":[
        "chemical",
        "pharmaceutical",
        "pharmacy"
    ],
    "wof:name":"Afssaps",
    "wof:placetype":"venue"
},
  "geometry": {"coordinates":[2.345415,48.921249],"type":"Point"}
}