{
  "type": "Feature",
  "properties": {
    "addr:full":"Zac Des Portes De Riom 63200 Riom Riom Auvergne 63200",
    "addr:housenumber":"zac",
    "addr:postcode":"63200;63200",
    "addr:street":"Des Portes De Riom",
    "iso:country":"FR",
    "sg:address":"Zac Des Portes De Riom 63200 Riom",
    "sg:city":"Riom",
    "sg:classifiers":[
        {
            "category":"Autos & Motor Vehicles",
            "subcategory":"Automobile Sales",
            "type":"Retail Goods"
        }
    ],
    "sg:phone":"+33 4 73 67 15 15",
    "sg:postcode":"63200",
    "sg:province":"Auvergne",
    "sg:tags":[
        "equipment",
        "transport"
    ],
    "wof:name":"Csee Transport",
    "wof:placetype":"venue"
},
  "geometry": {"coordinates":[3.115165,45.893814],"type":"Point"}
}