{
  "type": "Feature",
  "properties": {
    "iso:country":"FR",
    "sg:address":"rue de l'Equerre 95310 ST OUEN L AUMONE",
    "sg:classifiers":[
        {
            "category":"Manufacturing",
            "subcategory":"Motor Vehicles & Parts",
            "type":"Manufacturing & Wholesale Goods"
        }
    ],
    "sg:phone":"+33 1 34 40 25 25",
    "sg:postcode":"95310",
    "sg:province":"Ile de France",
    "sg:tags":[
        "packing",
        "handling",
        "robot",
        "unpacking"
    ],
    "wof:name":"Abb Flexible Automation Sas",
    "wof:placetype":"venue"
},
  "geometry": {"coordinates":[-120.396912,38.051048],"type":"Point"}
}