{
  "type": "Feature",
  "properties": {
    "addr:full":"33 Rue Hoche 93500 Pantin Ile de France",
    "addr:housenumber":"33",
    "addr:postcode":"93500;ile",
    "addr:street":"Rue Hoche",
    "iso:country":"FR",
    "sg:address":"33 Rue Hoche 93500 Pantin",
    "sg:classifiers":[
        {
            "category":"Manufacturing",
            "subcategory":"Paper Products",
            "type":"Manufacturing & Wholesale Goods"
        }
    ],
    "sg:phone":"+33 1 48 45 22 42",
    "sg:province":"Ile de France",
    "sg:tags":[
        "publishing",
        "material",
        "-",
        "raw",
        "printing",
        "cardboard"
    ],
    "wof:name":"Le Comptoir De L'image Sa",
    "wof:placetype":"venue"
},
  "geometry": {"coordinates":[2.401451,48.893345],"type":"Point"}
}