{
  "type": "Feature",
  "properties": {
    "addr:full":"B.P. 34, 77860 Saint Germain sur Morin^^4, Rue des Voyeux, 77860 Saint Germain sur Morin Ile de France 77860",
    "addr:postcode":"77860;77860;france 77860",
    "addr:street":"B.P. 34;Germain;Rue Des Voyeux;Germain;Morin",
    "iso:country":"FR",
    "sg:address":"B.P. 34, 77860 Saint Germain sur Morin^^4, Rue des Voyeux, 77860 Saint Germain sur Morin",
    "sg:orig_category":"Non-Classified Establishments",
    "sg:phone":"+33 1 60 04 66 44",
    "sg:postcode":"77860",
    "sg:province":"Ile de France",
    "wof:name":"Etablissements J.p.c. S.a.",
    "wof:placetype":"venue"
},
  "geometry": {"coordinates":[2.851558,48.884678],"type":"Point"}
}