{
  "type": "Feature",
  "properties": {
    "addr:full":"Quartier De Piecourt 30440 St Julien De La Nef Languedoc-Roussillon 30440",
    "addr:housenumber":"30440",
    "addr:postcode":"30440",
    "addr:street":"Quartier;St Julien De La Nef",
    "iso:country":"FR",
    "sg:address":"Quartier De Piecourt 30440 St Julien De La Nef",
    "sg:classifiers":[
        {
            "category":"Building & Trades",
            "subcategory":"Construction",
            "type":"Services"
        }
    ],
    "sg:phone":"+33 4 66 77 22 63",
    "sg:postcode":"30440",
    "sg:province":"Languedoc-Roussillon",
    "sg:tags":[
        "work",
        "public"
    ],
    "wof:name":"Cevenoles De Travaux Routiers",
    "wof:placetype":"venue"
},
  "geometry": {"coordinates":[3.68484,43.966671],"type":"Point"}
}