{
  "type": "Feature",
  "properties": {
    "iso:country":"FR",
    "sg:address":"B.P. 154, 06203 Nice C\u00e9dex 9^^Frigorifique de l'Union Min Saint Augustin, 06000 Nice",
    "sg:orig_category":"Non-Classified Establishments",
    "sg:phone":"+33 4 93 71 05 00",
    "sg:province":"Basse Normandie",
    "wof:name":"Davigel S.a.",
    "wof:placetype":"venue"
},
  "geometry": {"coordinates":[7.27434,43.718231],"type":"Point"}
}