{
  "type": "Feature",
  "properties": {
    "addr:full":"rue Meurgers Sonchamp 78120 Rambouillet Ile de France 78120",
    "addr:postcode":"78120;ile;78120",
    "addr:street":"Rue Meurgers;France",
    "iso:country":"FR",
    "sg:address":"rue Meurgers Sonchamp 78120 Rambouillet",
    "sg:classifiers":[
        {
            "category":"Transit Center",
            "subcategory":"Freight",
            "type":"Transportation"
        }
    ],
    "sg:phone":"+33 1 30 41 23 62",
    "sg:postcode":"78120",
    "sg:province":"Ile de France",
    "sg:tags":[
        "load",
        "cell",
        "dynamometers"
    ],
    "wof:name":"Mesurex Sas",
    "wof:placetype":"venue"
},
  "geometry": {"coordinates":[1.826199,48.643406],"type":"Point"}
}