{
  "type": "Feature",
  "properties": {
    "iso:country":"FR",
    "sg:address":"38, Rue du Clos, 69200 V\u00e9nissieux",
    "sg:orig_category":"Non-Classified Establishments",
    "sg:phone":"+33 4 78 74 02 03",
    "sg:postcode":"69200",
    "sg:province":"Rhone-Alpes",
    "wof:name":"C\u00e9lion S.a.r.l.",
    "wof:placetype":"venue"
},
  "geometry": {"coordinates":[4.89238,45.719009],"type":"Point"}
}