{
  "type": "Feature",
  "properties": {
    "addr:full":"1/3, Rte de Lamotte, 18410 Brinon sur Sauldre Argent-sur-Sauldre Centre 18410",
    "addr:housenumber":"1 / 3",
    "addr:postcode":"18410;18410",
    "addr:street":"Rte De Lamotte",
    "iso:country":"FR",
    "sg:address":"1/3, Rte de Lamotte, 18410 Brinon sur Sauldre",
    "sg:city":"Argent-sur-Sauldre",
    "sg:orig_category":"Non-Classified Establishments",
    "sg:phone":"+33 2 48 57 21 73",
    "sg:postcode":"18410",
    "sg:province":"Centre",
    "wof:name":"Labrunie S.a.r.l.",
    "wof:placetype":"venue"
},
  "geometry": {"coordinates":[2.250615,47.565449],"type":"Point"}
}