{
  "type": "Feature",
  "properties": {
    "iso:country":"FR",
    "sg:address":"10, Rte de Nanfray - PAE du Levray, 74960 Cran Gevrier",
    "sg:orig_category":"Non-Classified Establishments",
    "sg:phone":"+33 801 75 92 71",
    "sg:province":"Rhone-Alpes",
    "wof:name":"P.s. Engineering S.a.",
    "wof:placetype":"venue"
},
  "geometry": {"coordinates":[6.10647,45.907654],"type":"Point"}
}