{
  "type": "Feature",
  "properties": {
    "addr:full":"10, Rte de Nanfray - PAE du Levray, 74960 Cran Gevrier Rhone-Alpes",
    "addr:housenumber":"10",
    "addr:postcode":"74960",
    "addr:street":"Rte De Nanfray Pae Du Levray",
    "iso:country":"FR",
    "sg:address":"10, Rte de Nanfray - PAE du Levray, 74960 Cran Gevrier",
    "sg:orig_category":"Non-Classified Establishments",
    "sg:phone":"+33 801 75 92 71",
    "sg:province":"Rhone-Alpes",
    "wof:name":"P.s. Engineering S.a.",
    "wof:placetype":"venue"
},
  "geometry": {"coordinates":[6.10647,45.907654],"type":"Point"}
}