{
  "type": "Feature",
  "properties": {
    "addr:full":"16, Av. L\u00e9o Lagrange, 79000 Niort Poitou-Charentes",
    "addr:postcode":"79000",
    "addr:street":"16 Av. Le\u0301O Lagrange",
    "iso:country":"FR",
    "sg:address":"16, Av. L\u00e9o Lagrange, 79000 Niort",
    "sg:orig_category":"Unclassifiable Establishments",
    "sg:phone":"+33 5 49 73 55 55",
    "sg:province":"Poitou-Charentes",
    "wof:name":"Kpmg",
    "wof:placetype":"venue"
},
  "geometry": {"coordinates":[-0.470276,46.316364],"type":"Point"}
}