{
  "type": "Feature",
  "properties": {
    "addr:full":"3-5 rue Maurice Ravel 92300 Levallois Perret Ile de France",
    "addr:housenumber":"3-5",
    "addr:postcode":"92300;ile",
    "addr:street":"Rue Maurice Ravel",
    "iso:country":"FR",
    "sg:address":"3-5 rue Maurice Ravel 92300 Levallois Perret",
    "sg:classifiers":[
        {
            "category":"Retail",
            "subcategory":"Event Space",
            "type":"Services"
        }
    ],
    "sg:phone":"+33 1 56 76 29 50",
    "sg:province":"Ile de France",
    "sg:tags":[
        "telecommunication"
    ],
    "wof:name":"Primus Telecommunications France Sa",
    "wof:placetype":"venue"
},
  "geometry": {"coordinates":[2.294145,48.889725],"type":"Point"}
}