{
  "type": "Feature",
  "properties": {
    "addr:full":"B.P. 73445, 67455 Mundolsheim C\u00e9dex^^Rue du Commerce, 67116 Reichstett Reichstett Alsace 67116",
    "addr:postcode":"67455;67116;67116",
    "iso:country":"FR",
    "sg:address":"B.P. 73445, 67455 Mundolsheim C\u00e9dex^^Rue du Commerce, 67116 Reichstett",
    "sg:city":"Reichstett",
    "sg:orig_category":"Non-Classified Establishments",
    "sg:phone":"+33 3 88 18 39 20",
    "sg:postcode":"67116",
    "sg:province":"Alsace",
    "wof:name":"G\u00e9bo Industrie S.a.",
    "wof:placetype":"venue"
},
  "geometry": {"coordinates":[7.753589,48.648308],"type":"Point"}
}