{
  "type": "Feature",
  "properties": {
    "iso:country":"FR",
    "sg:address":"Zae La Folie 80220 Gamaches",
    "sg:classifiers":[
        {
            "category":"Manufacturing",
            "subcategory":"Metals",
            "type":"Manufacturing & Wholesale Goods"
        }
    ],
    "sg:phone":"+33 3 22 60 21 00",
    "sg:postcode":"80220",
    "sg:province":"Picardie",
    "sg:tags":[
        "metallurgy",
        "metalworking",
        "processing"
    ],
    "wof:name":"Parachevement Du Nord",
    "wof:placetype":"venue"
},
  "geometry": {"coordinates":[1.556783,49.986042],"type":"Point"}
}