{
  "type": "Feature",
  "properties": {
    "iso:country":"FR",
    "sg:address":"505, Place des Champs Elys\u00e9es - B\u00e2timent D, 91026 Evry C\u00e9dex",
    "sg:orig_category":"Non-Classified Establishments",
    "sg:phone":"+33 1 60 87 35 90",
    "sg:province":"Auvergne",
    "wof:name":"Soci\u00e9t\u00e9 Nouvelle Gaelic S.a.",
    "wof:placetype":"venue"
},
  "geometry": {"coordinates":[2.43072,48.626919],"type":"Point"}
}