{
  "type": "Feature",
  "properties": {
    "addr:full":"4, Rue Jean Monnet - ZA des C\u00f4tes, 78990 Elancourt Ile de France",
    "addr:housenumber":"4",
    "addr:postcode":"78990",
    "addr:street":"Rue Jean Monnet Za Des Co\u0302Tes;Ile De France",
    "iso:country":"FR",
    "sg:address":"4, Rue Jean Monnet - ZA des C\u00f4tes, 78990 Elancourt",
    "sg:orig_category":"Non-Classified Establishments",
    "sg:phone":"+33 1 30 51 99 33",
    "sg:province":"Ile de France",
    "wof:name":"V.2.s. S.a.r.l. - Soci\u00e9t\u00e9 Versaillaise De Sonorisation",
    "wof:placetype":"venue"
},
  "geometry": {"coordinates":[1.949475,48.768543],"type":"Point"}
}