{
  "type": "Feature",
  "properties": {
    "iso:country":"FR",
    "sg:address":"Promenade Du Leon Perriers 84500 Bollene",
    "sg:classifiers":[
        {
            "category":"Utilities",
            "subcategory":"Electric",
            "type":"Services"
        }
    ],
    "sg:phone":"+33 4 90 30 52 94",
    "sg:province":"Midi Pyr\u00e9n\u00e9es",
    "sg:tags":[
        "electricity",
        "raw",
        "energy",
        "material"
    ],
    "wof:name":"Cnr",
    "wof:placetype":"venue"
},
  "geometry": {"coordinates":[4.749213,44.298573],"type":"Point"}
}