{
  "type": "Feature",
  "properties": {
    "iso:country":"FR",
    "sg:address":"ZA de sailly sur la Lys 62840 Sailly sur la Lys",
    "sg:classifiers":[
        {
            "category":"Utilities",
            "type":"Services"
        }
    ],
    "sg:phone":"+33 3 21 02 96 79",
    "sg:postcode":"62840",
    "sg:province":"Nord Pas-de-Calais",
    "sg:tags":[
        "plant",
        "industrial",
        "maintenance"
    ],
    "wof:name":"Pal Industrie Lubing S.a.r.l.",
    "wof:placetype":"venue"
},
  "geometry": {"coordinates":[2.769795,50.657944],"type":"Point"}
}