{
  "type": "Feature",
  "properties": {
    "addr:full":"78, Av. de Verdun, 41000 Blois Blois Centre 41000",
    "addr:postcode":"41000;41000",
    "addr:street":"78 Av. De Verdun",
    "iso:country":"FR",
    "sg:address":"78, Av. de Verdun, 41000 Blois",
    "sg:city":"Blois",
    "sg:orig_category":"Non-Classified Establishments",
    "sg:phone":"+33 2 54 78 55 34",
    "sg:postcode":"41000",
    "sg:province":"Centre",
    "wof:name":"Delceram S.a.r.l.",
    "wof:placetype":"venue"
},
  "geometry": {"coordinates":[1.348305,47.596519],"type":"Point"}
}