{
  "type": "Feature",
  "properties": {
    "addr:full":"2, En Chaplerue, 57000 Metz Lorraine",
    "addr:postcode":"57000",
    "iso:country":"FR",
    "sg:address":"2, En Chaplerue, 57000 Metz",
    "sg:orig_category":"Unclassifiable Establishments",
    "sg:phone":"+33 3 87 38 58 38",
    "sg:province":"Lorraine",
    "wof:name":"R.l. Voyages S.a.",
    "wof:placetype":"venue"
},
  "geometry": {"coordinates":[6.175414,49.117043],"type":"Point"}
}