{
  "type": "Feature",
  "properties": {
    "addr:full":"Bd Kennedy Tarbes Midi Pyr\u00e9n\u00e9es 65000",
    "addr:postcode":"65000",
    "addr:street":"Bd Kennedy",
    "iso:country":"FR",
    "sg:address":"Bd Kennedy",
    "sg:city":"Tarbes",
    "sg:orig_category":"Non-Classified Establishments",
    "sg:phone":"+33 5 62 44 21 10",
    "sg:postcode":"65000",
    "sg:province":"Midi Pyr\u00e9n\u00e9es",
    "wof:name":"Tarbes Sem Parc Expo",
    "wof:placetype":"venue"
},
  "geometry": {"coordinates":[0.080097,43.218117],"type":"Point"}
}