{
  "type": "Feature",
  "properties": {
    "addr:full":"10, Av. de l'Entreprise - Parc Saint Christophe, 95863 Cergy C\u00e9dex Ile de France",
    "addr:postcode":"95863",
    "addr:street":"10 Av. De L'Entreprise;Christophe",
    "iso:country":"FR",
    "sg:address":"10, Av. de l'Entreprise - Parc Saint Christophe, 95863 Cergy C\u00e9dex",
    "sg:orig_category":"Non-Classified Establishments",
    "sg:phone":"+33 1 34 24 30 00",
    "sg:province":"Ile de France",
    "wof:name":"Spie Capag S.a.",
    "wof:placetype":"venue"
},
  "geometry": {"coordinates":[2.09101,49.035709],"type":"Point"}
}