{
  "type": "Feature",
  "properties": {
    "addr:full":"14 rue Hoen 68980 Beblenheim Beblenheim Alsace 68980",
    "addr:housenumber":"14",
    "addr:postcode":"68980;68980",
    "addr:street":"Rue Hoen",
    "iso:country":"FR",
    "sg:address":"14 rue Hoen 68980 Beblenheim",
    "sg:city":"Beblenheim",
    "sg:classifiers":[
        {
            "category":"Wholesale",
            "subcategory":"Wine & Distilled Alcoholic Beverages",
            "type":"Manufacturing & Wholesale Goods"
        }
    ],
    "sg:phone":"+33 3 89 47 90 02",
    "sg:postcode":"68980",
    "sg:province":"Alsace",
    "sg:tags":[
        "french"
    ],
    "wof:name":"Ste Vinicole De Beblenheim Coop",
    "wof:placetype":"venue"
},
  "geometry": {"coordinates":[7.327654,48.159218],"type":"Point"}
}