{
  "type": "Feature",
  "properties": {
    "addr:full":"Palais Des Pyr\u00e9n\u00e9es Building Pyr\u00e9n\u00e9es 2 K 64000 Pau Pau Aquitaine 64000",
    "addr:housenumber":"2 k",
    "addr:postcode":"64000;64000",
    "iso:country":"FR",
    "sg:address":"Palais Des Pyr\u00e9n\u00e9es Building Pyr\u00e9n\u00e9es 2 K 64000 Pau",
    "sg:city":"Pau",
    "sg:classifiers":[
        {
            "category":"Banks & Credit Unions",
            "subcategory":"Financial Services",
            "type":"Services"
        }
    ],
    "sg:phone":"+33 5 59 27 16 25",
    "sg:postcode":"64000",
    "sg:province":"Aquitaine",
    "sg:tags":[
        "banking",
        "finance",
        "insurance"
    ],
    "wof:name":"Texa",
    "wof:placetype":"venue"
},
  "geometry": {"coordinates":[-0.374294,43.296558],"type":"Point"}
}