{
  "type": "Feature",
  "properties": {
    "addr:full":"Route Aux Pierres 77174 Villeneuve Le Comte Ile de France 77174",
    "addr:postcode":"77174;77174",
    "addr:street":"Route Aux Pierres",
    "iso:country":"FR",
    "sg:address":"Route Aux Pierres 77174 Villeneuve Le Comte",
    "sg:classifiers":[
        {
            "category":"Wholesale",
            "subcategory":"Machinery & Supplies",
            "type":"Manufacturing & Wholesale Goods"
        }
    ],
    "sg:phone":"+33 1 60 43 00 40",
    "sg:postcode":"77174",
    "sg:province":"Ile de France",
    "sg:tags":[
        "handling",
        "material",
        "-",
        "machine",
        "equipment",
        "engineering",
        "mechanical"
    ],
    "wof:name":"Sarl D'exploitation Adment",
    "wof:placetype":"venue"
},
  "geometry": {"coordinates":[2.832665,48.809933],"type":"Point"}
}