{
  "type": "Feature",
  "properties": {
    "iso:country":"FR",
    "sg:address":"41 Rue Des 3 Fontanot 92024 Nanterre Cedex",
    "sg:classifiers":[
        {
            "category":"Manufacturing",
            "subcategory":"Metals",
            "type":"Manufacturing & Wholesale Goods"
        }
    ],
    "sg:phone":"+33 1 55 17 22 44",
    "sg:province":"Languedoc-Roussillon",
    "sg:tags":[
        "-",
        "machine",
        "equipment",
        "engineering",
        "machinery",
        "mechanical"
    ],
    "wof:name":"Ingersoll-france Sarl",
    "wof:placetype":"venue"
},
  "geometry": {"coordinates":[2.221197,48.89603],"type":"Point"}
}