{
  "type": "Feature",
  "properties": {
    "addr:full":"5, Rue des Fr\u00e8res Lumi\u00e8re, 68000 Colmar Colmar Alsace 68000",
    "addr:housenumber":"5",
    "addr:postcode":"68000;68000",
    "addr:street":"Rue Des Fre\u0300Res Lumie\u0300Re",
    "iso:country":"FR",
    "sg:address":"5, Rue des Fr\u00e8res Lumi\u00e8re, 68000 Colmar",
    "sg:city":"Colmar",
    "sg:orig_category":"Unclassifiable Establishments",
    "sg:phone":"+33 3 89 21 13 50",
    "sg:postcode":"68000",
    "sg:province":"Alsace",
    "wof:name":"Auxicad S.a.",
    "wof:placetype":"venue"
},
  "geometry": {"coordinates":[7.367705,48.111526],"type":"Point"}
}