{
  "type": "Feature",
  "properties": {
    "iso:country":"FR",
    "sg:address":"B.P. 4, 85292 Saint Laurent sur S\u00e8vre C\u00e9dex^^Rte de la Gare, 85290 Saint Laurent sur S\u00e8vre",
    "sg:orig_category":"Non-Classified Establishments",
    "sg:phone":"+33 2 51 64 14 00",
    "sg:province":"Pays de Loire",
    "wof:name":"Newtec Palettisation S.a.",
    "wof:placetype":"venue"
},
  "geometry": {"coordinates":[-0.899161,46.961712],"type":"Point"}
}