{
  "type": "Feature",
  "properties": {
    "addr:full":"15, Rue de la Belle Borne - B\u00e2t. 3456, 93290 Tremblay en France Ile de France",
    "addr:housenumber":"15;ba\u0302t 3456",
    "addr:postcode":"93290",
    "addr:street":"Rue De La Belle Borne",
    "iso:country":"FR",
    "sg:address":"15, Rue de la Belle Borne - B\u00e2t. 3456, 93290 Tremblay en France",
    "sg:orig_category":"Non-Classified Establishments",
    "sg:phone":"+33 1 49 19 59 38",
    "sg:province":"Ile de France",
    "wof:name":"Go Fast S.a.",
    "wof:placetype":"venue"
},
  "geometry": {"coordinates":[2.521565,48.989269],"type":"Point"}
}