{
  "type": "Feature",
  "properties": {
    "addr:full":"Rue Blaise Pascal - Campus de Kerlann Bruz Bretagne 35170",
    "addr:postcode":"35170",
    "addr:street":"Rue Blaise Pascal Campus De Kerlann;Bretagne",
    "iso:country":"FR",
    "sg:address":"Rue Blaise Pascal - Campus de Kerlann",
    "sg:city":"Bruz",
    "sg:orig_category":"Non-Classified Establishments",
    "sg:phone":"+33 2 99 05 30 10",
    "sg:postcode":"35170",
    "sg:province":"Bretagne",
    "wof:name":"A3.dis S.a.r.l.",
    "wof:placetype":"venue"
},
  "geometry": {"coordinates":[-1.773184,48.006374],"type":"Point"}
}