{
  "type": "Feature",
  "properties": {
    "iso:country":"FR",
    "sg:address":"11",
    "sg:city":"Friedland 75008 PARIS",
    "sg:classifiers":[
        {
            "category":"Professional",
            "subcategory":"Printing & Photocopies",
            "type":"Services"
        }
    ],
    "sg:phone":"+33 1 40 75 25 00",
    "sg:province":"Ile de France",
    "sg:tags":[
        "publishing"
    ],
    "wof:name":"Mc Graw-hill Companies (the)",
    "wof:placetype":"venue"
},
  "geometry": {"coordinates":[2.303522,48.874496],"type":"Point"}
}