{
  "type": "Feature",
  "properties": {
    "addr:full":"Place Martenot 03600 Commentry Commentry Auvergne 03600",
    "addr:postcode":"03600;commentry;03600",
    "addr:street":"Place Martenot",
    "iso:country":"FR",
    "sg:address":"Place Martenot 03600 Commentry",
    "sg:city":"Commentry",
    "sg:classifiers":[
        {
            "category":"Manufacturing",
            "subcategory":"Metals",
            "type":"Manufacturing & Wholesale Goods"
        }
    ],
    "sg:phone":"+33 4 70 28 78 00",
    "sg:postcode":"03600",
    "sg:province":"Auvergne",
    "sg:tags":[
        "metallurgy",
        "metalworking",
        "processing"
    ],
    "wof:name":"Erasteel Commentry",
    "wof:placetype":"venue"
},
  "geometry": {"coordinates":[2.744275,46.287575],"type":"Point"}
}