{
  "type": "Feature",
  "properties": {
    "iso:country":"FR",
    "sg:address":"829 route des Loubes 83400 Hy\u00e8res",
    "sg:classifiers":[
        {
            "category":"Recreation",
            "subcategory":"Boat Charter",
            "type":"Entertainment"
        }
    ],
    "sg:phone":"+33 4 94 57 59 84",
    "sg:province":"Picardie",
    "sg:tags":[
        "tarp"
    ],
    "wof:name":"Azur Engieneering Company Sa",
    "wof:placetype":"venue"
},
  "geometry": {"coordinates":[6.10533,43.113022],"type":"Point"}
}