{
  "type": "Feature",
  "properties": {
    "addr:full":"20 R St Antoine 26100 Romans Sur Is\u00e8re Rhone-Alpes 26100",
    "addr:housenumber":"20",
    "addr:postcode":"26100;26100",
    "addr:street":"R St",
    "iso:country":"FR",
    "sg:address":"20 R St Antoine 26100 Romans Sur Is\u00e8re",
    "sg:classifiers":[
        {
            "category":"Professional",
            "subcategory":"Business Services",
            "type":"Services"
        }
    ],
    "sg:phone":"+33 4 75 05 04 45",
    "sg:postcode":"26100",
    "sg:province":"Rhone-Alpes",
    "sg:tags":[
        "training",
        "advice"
    ],
    "wof:name":"Acces Ass",
    "wof:placetype":"venue"
},
  "geometry": {"coordinates":[5.032969,45.052006],"type":"Point"}
}