{
  "type": "Feature",
  "properties": {
    "iso:country":"FR",
    "sg:address":"ZA La Tremblaie",
    "sg:city":"Herbault",
    "sg:orig_category":"Non-Classified Establishments",
    "sg:phone":"+33 2 54 46 10 30",
    "sg:postcode":"41190",
    "sg:province":"Centre",
    "wof:name":"Cousin S.a.r.l.",
    "wof:placetype":"venue"
},
  "geometry": {"coordinates":[1.140075,47.604309],"type":"Point"}
}