{
  "type": "Feature",
  "properties": {
    "iso:country":"FR",
    "sg:address":"B.P. 103, 35603 Redon C\u00e9dex^^ZI de Tournebride - Bains sur Oust , 35600 Redon",
    "sg:city":"Redon",
    "sg:orig_category":"Non-Classified Establishments",
    "sg:phone":"+33 2 99 71 04 07",
    "sg:postcode":"35600",
    "sg:province":"Bretagne",
    "wof:name":"A.d.e.o. S.a. - Atelier D\u00e9coupage Emboutissage De L'ouest",
    "wof:placetype":"venue"
},
  "geometry": {"coordinates":[-2.085934,47.651035],"type":"Point"}
}