{
  "type": "Feature",
  "properties": {
    "addr:full":"12 Rue Curie 69150 Decines Charpieu Rhone-Alpes 69150",
    "addr:housenumber":"12",
    "addr:postcode":"69150;69150",
    "addr:street":"Rue Curie;Rhone-Alpes",
    "iso:country":"FR",
    "sg:address":"12 Rue Curie 69150 Decines Charpieu",
    "sg:classifiers":[
        {
            "category":"Professional",
            "subcategory":"Engineering",
            "type":"Services"
        }
    ],
    "sg:phone":"+33 4 78 49 43 80",
    "sg:postcode":"69150",
    "sg:province":"Rhone-Alpes",
    "sg:tags":[
        "machine",
        "-",
        "mechanical"
    ],
    "wof:name":"Mp Services",
    "wof:placetype":"venue"
},
  "geometry": {"coordinates":[4.959747,45.771614],"type":"Point"}
}