{
  "type": "Feature",
  "properties": {
    "iso:country":"FR",
    "sg:address":"Rte Pierre Beno\u00eet - 400 Village d'Entreprises",
    "sg:city":"Saint Paul les Dax",
    "sg:orig_category":"Unclassifiable Establishments",
    "sg:phone":"+33 5 58 91 53 41",
    "sg:postcode":"40990",
    "sg:province":"Aquitaine",
    "wof:name":"S.e.r.i.a.a. S.a. - Soci\u00e9t\u00e9 D'etudes Et De R\u00e9alisation D'armoires Et",
    "wof:placetype":"venue"
},
  "geometry": {"coordinates":[-1.052951,43.739902],"type":"Point"}
}