{
  "type": "Feature",
  "properties": {
    "addr:full":"Zone Industrielle La Sauni\u00e8re Saint Florentin Bourgogne 89600",
    "addr:postcode":"89600",
    "addr:street":"Zone Industrielle La",
    "iso:country":"FR",
    "sg:address":"Zone Industrielle La Sauni\u00e8re",
    "sg:city":"Saint Florentin",
    "sg:orig_category":"Unclassifiable Establishments",
    "sg:phone":"+33 3 86 43 75 30",
    "sg:postcode":"89600",
    "sg:province":"Bourgogne",
    "wof:name":"S.e.v.a. S.a.r.l. - Soci\u00e9t\u00e9 D'etudes Du Val D'armance",
    "wof:placetype":"venue"
},
  "geometry": {"coordinates":[3.72972,48.002575],"type":"Point"}
}