{
  "type": "Feature",
  "properties": {
    "addr:full":"19 Rue Foulon Quincey 10400 Ferreux Quincey Champagne",
    "addr:housenumber":"19",
    "addr:postcode":"10400",
    "addr:street":"Rue Foulon",
    "iso:country":"FR",
    "sg:address":"19 Rue Foulon Quincey 10400 Ferreux Quincey",
    "sg:classifiers":[
        {
            "category":"Professional",
            "type":"Services"
        }
    ],
    "sg:phone":"+33 3 25 24 40 92",
    "sg:province":"Champagne",
    "sg:tags":[
        "transport",
        "road"
    ],
    "wof:name":"Ozanne Pascal Transports Garage Sa",
    "wof:placetype":"venue"
},
  "geometry": {"coordinates":[3.50251,48.492336],"type":"Point"}
}