{
  "type": "Feature",
  "properties": {
    "addr:full":"29, Rte de Lyon, 69960 Corbas Rhone-Alpes",
    "addr:housenumber":"29",
    "addr:postcode":"69960",
    "addr:street":"Rte De Lyon",
    "iso:country":"FR",
    "sg:address":"29, Rte de Lyon, 69960 Corbas",
    "sg:orig_category":"Unclassifiable Establishments",
    "sg:phone":"+33 4 72 50 68 89",
    "sg:province":"Rhone-Alpes",
    "wof:name":"Comptoir National S.a.",
    "wof:placetype":"venue"
},
  "geometry": {"coordinates":[4.89539,45.678291],"type":"Point"}
}