{
  "type": "Feature",
  "properties": {
    "addr:full":"103 rue la Boetie PARIS  75008",
    "addr:housenumber":"103",
    "addr:postcode":"75008",
    "addr:street":"Rue La Boetie Paris",
    "iso:country":"FR",
    "sg:address":"103 rue la Boetie",
    "sg:city":"PARIS ",
    "sg:classifiers":[
        {
            "category":"Professional",
            "subcategory":"Computer Services",
            "type":"Services"
        }
    ],
    "sg:postcode":"75008",
    "sg:website":"http://www.viseo.net",
    "wof:name":"VISEO",
    "wof:placetype":"venue"
},
  "geometry": {"coordinates":[2.307045,48.871279],"type":"Point"}
}