{
  "type": "Feature",
  "properties": {
    "addr:full":"Zi 88510 Eloyes Lorraine",
    "addr:postcode":"88510",
    "addr:street":"Zi",
    "iso:country":"FR",
    "sg:address":"Zi 88510 Eloyes",
    "sg:classifiers":[
        {
            "category":"Manufacturing",
            "subcategory":"Rubber & Plastics",
            "type":"Manufacturing & Wholesale Goods"
        }
    ],
    "sg:phone":"+33 3 29 32 80 70",
    "sg:province":"Lorraine",
    "wof:name":"Plastigray",
    "wof:placetype":"venue"
},
  "geometry": {"coordinates":[6.610609,48.093906],"type":"Point"}
}