{
  "type": "Feature",
  "properties": {
    "addr:full":"01290 Laiz Rhone-Alpes",
    "addr:postcode":"01290",
    "addr:street":"Rhone-Alpes",
    "iso:country":"FR",
    "sg:address":"01290 Laiz",
    "sg:orig_category":"Unclassifiable Establishments",
    "sg:phone":"+33 3 85 31 52 09",
    "sg:province":"Rhone-Alpes",
    "wof:name":"Entreprise Berardan Jean-michel",
    "wof:placetype":"venue"
},
  "geometry": {"coordinates":[4.89194,46.245628],"type":"Point"}
}