{
  "type": "Feature",
  "properties": {
    "addr:full":"66 Rue De La Pompe 75116 Paris Ile de France",
    "addr:housenumber":"66",
    "addr:postcode":"75116",
    "addr:street":"Rue De La Pompe",
    "iso:country":"FR",
    "sg:address":"66 Rue De La Pompe 75116 Paris",
    "sg:classifiers":[
        {
            "category":"Shopping",
            "type":"Retail Goods"
        }
    ],
    "sg:phone":"+33 1 40 72 55 08",
    "sg:province":"Ile de France",
    "sg:tags":[
        "metallurgy",
        "finished",
        "-",
        "metalworking",
        "metallic"
    ],
    "wof:name":"La Maison Du Decolletage Et Du Pivotage",
    "wof:placetype":"venue"
},
  "geometry": {"coordinates":[2.27658,48.862919],"type":"Point"}
}