{
  "type": "Feature",
  "properties": {
    "iso:country":"FR",
    "sg:address":"116, Rue Andr\u00e9 Ternynck, 02300 Chauny",
    "sg:orig_category":"Unclassifiable Establishments",
    "sg:phone":"+33 3 23 06 28 88",
    "sg:province":"Picardie",
    "wof:name":"Espace Formation Afida",
    "wof:placetype":"venue"
},
  "geometry": {"coordinates":[3.210814,49.629581],"type":"Point"}
}