{
  "type": "Feature",
  "properties": {
    "addr:full":"Rte de Provins - ZI Nangis Ile de France 77370",
    "addr:postcode":"77370",
    "addr:street":"Rte De Provins Zi",
    "iso:country":"FR",
    "sg:address":"Rte de Provins - ZI",
    "sg:city":"Nangis",
    "sg:orig_category":"Non-Classified Establishments",
    "sg:phone":"+33 1 64 75 35 35",
    "sg:postcode":"77370",
    "sg:province":"Ile de France",
    "wof:name":"La Brie Cabe Camev",
    "wof:placetype":"venue"
},
  "geometry": {"coordinates":[2.948903,48.507874],"type":"Point"}
}