{
  "type": "Feature",
  "properties": {
    "iso:country":"FR",
    "sg:address":"61, All\u00e9e de Roberstau, 67000 Strasbourg",
    "sg:city":"Strasbourg",
    "sg:orig_category":"Non-Classified Establishments",
    "sg:phone":"+33 3 88 21 23 80",
    "sg:postcode":"67000",
    "sg:province":"Alsace",
    "wof:name":"Voest Alpine Stahl S.a.",
    "wof:placetype":"venue"
},
  "geometry": {"coordinates":[7.767966,48.59071],"type":"Point"}
}