{
  "type": "Feature",
  "properties": {
    "iso:country":"FR",
    "sg:address":"24 bis, Rue du Bargy, 74950 Scionzier",
    "sg:orig_category":"Unclassifiable Establishments",
    "sg:phone":"+33 4 50 96 16 71",
    "sg:postcode":"74950",
    "sg:province":"Rhone-Alpes",
    "wof:name":"Bourgeaux-basthard S.a.",
    "wof:placetype":"venue"
},
  "geometry": {"coordinates":[6.54603,46.05484],"type":"Point"}
}