{
  "type": "Feature",
  "properties": {
    "iso:country":"FR",
    "sg:address":"ZAC des 2 Vall\u00e9es",
    "sg:city":"Abbeville",
    "sg:orig_category":"T\u00d4LERIE DE PR\u00c9CISION",
    "sg:phone":"+33 3 22 20 25 00",
    "sg:postcode":"80100",
    "sg:province":"Picardie",
    "wof:name":"T.f.i. S.a.r.l. - T\u00f4lerie Fine Industrielle",
    "wof:placetype":"venue"
},
  "geometry": {"coordinates":[1.861588,50.109184],"type":"Point"}
}