{
  "type": "Feature",
  "properties": {
    "addr:full":"Rue Andr\u00e9 Durouchez B\u00e2t 6 Zi Nord 80046 Amiens Amiens Picardie 80000",
    "addr:housenumber":"6",
    "addr:postcode":"80046 amiens;80000",
    "addr:street":"Rue Andre\u0301 Durouchez Ba\u0302T",
    "iso:country":"FR",
    "sg:address":"Rue Andr\u00e9 Durouchez B\u00e2t 6 Zi Nord 80046 Amiens",
    "sg:city":"Amiens",
    "sg:classifiers":[
        {
            "category":"Utilities",
            "subcategory":"Electric",
            "type":"Services"
        }
    ],
    "sg:phone":"+33 3 22 54 64 70",
    "sg:postcode":"80000",
    "sg:province":"Picardie",
    "sg:tags":[
        "electricity",
        "electronic",
        "electrical",
        "equipment"
    ],
    "wof:name":"Orefi Martine Picardie Transmission Sa",
    "wof:placetype":"venue"
},
  "geometry": {"coordinates":[2.2654,49.937653],"type":"Point"}
}