{
  "type": "Feature",
  "properties": {
    "addr:full":"89-91 Av Du Mar\u00e9chal Joffre 92027 Nanterre Cedex Languedoc-Roussillon",
    "addr:housenumber":"89-91",
    "addr:postcode":"92027;cedex",
    "addr:street":"Av Du Mare\u0301Chal Joffre",
    "iso:country":"FR",
    "sg:address":"89-91 Av Du Mar\u00e9chal Joffre 92027 Nanterre Cedex",
    "sg:classifiers":[
        {
            "category":"Manufacturing",
            "subcategory":"Chemicals & Compounds",
            "type":"Manufacturing & Wholesale Goods"
        }
    ],
    "sg:phone":"+33 1 55 47 71 00",
    "sg:province":"Languedoc-Roussillon",
    "sg:tags":[
        "pharmaceutical",
        "chemistry",
        "-",
        "by-product"
    ],
    "wof:name":"Coates Lorilleux",
    "wof:placetype":"venue"
},
  "geometry": {"coordinates":[2.192635,48.884037],"type":"Point"}
}