{
  "type": "Feature",
  "properties": {
    "iso:country":"FR",
    "sg:address":"1 Rue Ch St Pierre 49100 Angers",
    "sg:classifiers":[
        {
            "category":"Professional",
            "subcategory":"Printing & Photocopies",
            "type":"Services"
        }
    ],
    "sg:phone":"+33 2 41 25 52 55",
    "sg:province":"Pays de Loire",
    "sg:tags":[
        "publishing"
    ],
    "wof:name":"Publications Du Courrier De L'ouest",
    "wof:placetype":"venue"
},
  "geometry": {"coordinates":[-0.552433,47.471153],"type":"Point"}
}