{
  "type": "Feature",
  "properties": {
    "iso:country":"FR",
    "sg:address":"13 Rue Jean Moulin 45100 Orleans",
    "sg:city":"Orl\u00e9ans",
    "sg:classifiers":[
        {
            "category":"Professional",
            "subcategory":"Advertising",
            "type":"Services"
        }
    ],
    "sg:phone":"+33 2 38 51 36 00",
    "sg:postcode":"45100",
    "sg:province":"Centre",
    "sg:tags":[
        "marketing",
        "medium",
        "communication"
    ],
    "wof:name":"Delta Diffusion Centre Ouest",
    "wof:placetype":"venue"
},
  "geometry": {"coordinates":[1.919526,47.865147],"type":"Point"}
}