{
  "type": "Feature",
  "properties": {
    "iso:country":"FR",
    "sg:address":"Rte De Fougeres Zi 53120 Gorron",
    "sg:classifiers":[
        {
            "category":"Shopping",
            "subcategory":"Computers & Home Electronics",
            "type":"Retail Goods"
        }
    ],
    "sg:phone":"+33 2 43 08 63 43",
    "sg:postcode":"53120",
    "sg:province":"Pays de Loire",
    "sg:tags":[
        "equipment",
        "electrical",
        "component",
        "electric",
        "electronic"
    ],
    "wof:name":"Societe Technique Montage Electronique Tme Tme",
    "wof:placetype":"venue"
},
  "geometry": {"coordinates":[-0.905929,48.385075],"type":"Point"}
}