{
  "type": "Feature",
  "properties": {
    "iso:country":"FR",
    "sg:address":"ZA",
    "sg:city":"Orchamps Vennes",
    "sg:orig_category":"Non-Classified Establishments",
    "sg:phone":"+33 3 81 43 65 65",
    "sg:postcode":"25390",
    "sg:province":"Franche Comt\u00e9",
    "wof:name":"Cr\u00e9ations J.c. Perrin S.a.r.l.",
    "wof:placetype":"venue"
},
  "geometry": {"coordinates":[6.545305,47.095703],"type":"Point"}
}