{
  "type": "Feature",
  "properties": {
    "iso:country":"FR",
    "sg:address":"25 rue Senac 13001 Marseille",
    "sg:classifiers":[
        {
            "category":"Manufacturing",
            "subcategory":"Jewelry",
            "type":"Manufacturing & Wholesale Goods"
        }
    ],
    "sg:phone":"+33 4 91 48 72 13",
    "sg:province":"Poitou-Charentes",
    "sg:tags":[
        "gemstone",
        "gold",
        "jewellery"
    ],
    "wof:name":"Sud Bijoux Sa",
    "wof:placetype":"venue"
},
  "geometry": {"coordinates":[5.37249,43.293686],"type":"Point"}
}