{
  "type": "Feature",
  "properties": {
    "iso:country":"FR",
    "sg:address":"Rue De La Bastide Blanche 13127 Vitrolles",
    "sg:city":"Anch\u00e9",
    "sg:classifiers":[
        {
            "category":"Professional",
            "subcategory":"Engineering",
            "type":"Services"
        }
    ],
    "sg:phone":"+33 4 42 15 94 40",
    "sg:postcode":"37500",
    "sg:province":"Centre",
    "sg:tags":[
        "machine",
        "-",
        "mechanical"
    ],
    "wof:name":"T I M Transitube Sa",
    "wof:placetype":"venue"
},
  "geometry": {"coordinates":[5.265181,43.430847],"type":"Point"}
}