{
  "type": "Feature",
  "properties": {
    "iso:country":"FR",
    "sg:address":"143, Rue Saint Charles, 75015 Paris",
    "sg:orig_category":"Unclassifiable Establishments",
    "sg:phone":"+33 1 45 77 54 81",
    "sg:province":"Ile de France",
    "wof:name":"Ferruvor S.a.r.l.",
    "wof:placetype":"venue"
},
  "geometry": {"coordinates":[2.282767,48.843262],"type":"Point"}
}