{
  "type": "Feature",
  "properties": {
    "addr:full":"ZI Bois de Leuze Saint Martin de Crau Provence-Alpes-C\u00f4te d'Azur 13310",
    "addr:postcode":"13310",
    "addr:street":"Zi Bois De Leuze Saint Martin De Crau",
    "iso:country":"FR",
    "sg:address":"ZI Bois de Leuze",
    "sg:city":"Saint Martin de Crau",
    "sg:orig_category":"Unclassifiable Establishments",
    "sg:phone":"+33 4 90 47 34 07",
    "sg:postcode":"13310",
    "sg:province":"Provence-Alpes-C\u00f4te d'Azur",
    "wof:name":"E.c.c.r. S.a.r.l. - Etudes Calculs Conception Et R\u00e9alisations",
    "wof:placetype":"venue"
},
  "geometry": {"coordinates":[4.809945,43.638184],"type":"Point"}
}