{
  "type": "Feature",
  "properties": {
    "addr:full":"Rue De La Leterie 57670 Benestroff Lorraine",
    "addr:postcode":"57670",
    "addr:street":"Rue De La Leterie",
    "iso:country":"FR",
    "sg:address":"Rue De La Leterie 57670 Benestroff",
    "sg:classifiers":[
        {
            "category":"Professional",
            "type":"Services"
        }
    ],
    "sg:phone":"+33 3 87 01 54 90",
    "sg:province":"Lorraine",
    "sg:tags":[
        "transport",
        "road"
    ],
    "wof:name":"Transports Jung Sarl",
    "wof:placetype":"venue"
},
  "geometry": {"coordinates":[6.759537,48.907146],"type":"Point"}
}