{
  "type": "Feature",
  "properties": {
    "addr:full":"1, Rue des Champs aux F\u00e8ves, 21121 Fontaine les Dijon Ahuy Bourgogne 21121",
    "addr:housenumber":"1",
    "addr:postcode":"21121;21121",
    "addr:street":"Rue Des Champs Aux Fe\u0300Ves",
    "iso:country":"FR",
    "sg:address":"1, Rue des Champs aux F\u00e8ves, 21121 Fontaine les Dijon",
    "sg:city":"Ahuy",
    "sg:orig_category":"Non-Classified Establishments",
    "sg:phone":"+33 3 80 55 27 21",
    "sg:postcode":"21121",
    "sg:province":"Bourgogne",
    "wof:name":"Groupe Scribe S.a.r.l.",
    "wof:placetype":"venue"
},
  "geometry": {"coordinates":[5.031061,47.352444],"type":"Point"}
}