{
  "type": "Feature",
  "properties": {
    "addr:full":"1 rue d'Espagne 67230 Benfeld Benfeld Alsace 67230",
    "addr:housenumber":"1",
    "addr:postcode":"67230;67230",
    "addr:street":"Rue D'Espagne",
    "iso:country":"FR",
    "sg:address":"1 rue d'Espagne 67230 Benfeld",
    "sg:city":"Benfeld",
    "sg:classifiers":[
        {
            "category":"Manufacturing",
            "subcategory":"Tools & Machinery",
            "type":"Manufacturing & Wholesale Goods"
        }
    ],
    "sg:phone":"+33 3 88 74 03 22",
    "sg:postcode":"67230",
    "sg:province":"Alsace",
    "sg:tags":[
        "machine"
    ],
    "wof:name":"M2c Sarl",
    "wof:placetype":"venue"
},
  "geometry": {"coordinates":[7.595641,48.378059],"type":"Point"}
}