{
  "type": "Feature",
  "properties": {
    "iso:country":"FR",
    "sg:address":"16 pl Vend\u00f4me; Paris; 75001",
    "sg:classifiers":[
        {
            "category":"Banks & Credit Unions",
            "subcategory":"Bank",
            "type":"Services"
        }
    ],
    "sg:phone":"+33 1 42 86 90 19",
    "sg:postcode":"75001",
    "sg:province":"Ile de France",
    "wof:name":"Hambros France Sa",
    "wof:placetype":"venue"
},
  "geometry": {"coordinates":[2.330015,48.867035],"type":"Point"}
}