{
  "type": "Feature",
  "properties": {
    "addr:full":"160 Av 69\u00e8me R\u00e9giment D'Infante 54270 Essey Les Nancy Lorraine 54270",
    "addr:housenumber":"160",
    "addr:postcode":"54270;54270",
    "addr:street":"Av 69E\u0300Me Re\u0301Giment D'Infante",
    "iso:country":"FR",
    "sg:address":"160 Av 69\u00e8me R\u00e9giment D'Infante 54270 Essey Les Nancy",
    "sg:classifiers":[
        {
            "category":"Wholesale",
            "subcategory":"Medical Equipment & Supplies",
            "type":"Manufacturing & Wholesale Goods"
        }
    ],
    "sg:phone":"+33 3 83 29 80 00",
    "sg:postcode":"54270",
    "sg:province":"Lorraine",
    "sg:tags":[
        "instrument",
        "health",
        "-",
        "precision"
    ],
    "wof:name":"Technologies Hospitalieres De Lorraine (thl)",
    "wof:placetype":"venue"
},
  "geometry": {"coordinates":[6.244093,48.710915],"type":"Point"}
}