{
  "type": "Feature",
  "properties": {
    "addr:full":"Rue Principale Pisseloup Champagne 52500",
    "addr:postcode":"52500",
    "addr:street":"Rue;Champagne",
    "iso:country":"FR",
    "sg:address":"Rue Principale",
    "sg:city":"Pisseloup",
    "sg:classifiers":[
        {
            "category":"Banks & Credit Unions",
            "subcategory":"Financial Services",
            "type":"Services"
        }
    ],
    "sg:phone":"+33 3 25 84 32 40",
    "sg:postcode":"52500",
    "sg:province":"Champagne",
    "sg:tags":[
        "banking",
        "finance",
        "insurance"
    ],
    "wof:name":"Mercer",
    "wof:placetype":"venue"
},
  "geometry": {"coordinates":[5.733643,47.822842],"type":"Point"}
}