{
  "type": "Feature",
  "properties": {
    "addr:full":"18 Rue Emile Zola 80036 Amiens Cedex 1 Amiens Picardie 80000",
    "addr:housenumber":"18",
    "addr:postcode":"80036 amiens;80000",
    "addr:street":"Rue Emile Zola",
    "iso:country":"FR",
    "sg:address":"18 Rue Emile Zola 80036 Amiens Cedex 1",
    "sg:city":"Amiens",
    "sg:classifiers":[
        {
            "category":"Professional",
            "subcategory":"Business Services",
            "type":"Services"
        }
    ],
    "sg:phone":"+33 3 22 91 33 41",
    "sg:postcode":"80000",
    "sg:province":"Picardie",
    "sg:tags":[
        "training",
        "advice"
    ],
    "wof:name":"Ecole Maternelle Primaire Sainte Clotilde",
    "wof:placetype":"venue"
},
  "geometry": {"coordinates":[2.300105,49.890152],"type":"Point"}
}