{
  "type": "Feature",
  "properties": {
    "iso:country":"FR",
    "sg:address":"4, Rue Chevignerot, 21200 Beaune",
    "sg:city":"Beaune",
    "sg:orig_category":"Non-Classified Establishments",
    "sg:phone":"+33 3 80 22 27 77",
    "sg:postcode":"21200",
    "sg:province":"Bourgogne",
    "wof:name":"Coop\u00e9rative Laiti\u00e8re De Bourgogne",
    "wof:placetype":"venue"
},
  "geometry": {"coordinates":[4.848085,47.021652],"type":"Point"}
}