{
  "type": "Feature",
  "properties": {
    "addr:full":"79, Av. la Bruy\u00e8re, 94400 Vitry sur Seine Ile de France 94400",
    "addr:postcode":"94400;94400",
    "addr:street":"79 Av. La Bruye\u0300Re;France",
    "iso:country":"FR",
    "sg:address":"79, Av. la Bruy\u00e8re, 94400 Vitry sur Seine",
    "sg:orig_category":"Non-Classified Establishments",
    "sg:phone":"+33 1 45 73 22 33",
    "sg:postcode":"94400",
    "sg:province":"Ile de France",
    "wof:name":"Duo Graphic S.a.r.l.",
    "wof:placetype":"venue"
},
  "geometry": {"coordinates":[2.401076,48.787621],"type":"Point"}
}