{
  "type": "Feature",
  "properties": {
    "addr:full":"ZI le Moulin \u00e0 Vent Briare Centre 45250",
    "addr:postcode":"45250",
    "addr:street":"Zi Le Moulin",
    "iso:country":"FR",
    "sg:address":"ZI le Moulin \u00e0 Vent",
    "sg:city":"Briare",
    "sg:orig_category":"Unclassifiable Establishments",
    "sg:phone":"+33 2 38 37 11 46",
    "sg:postcode":"45250",
    "sg:province":"Centre",
    "wof:name":"S.3.c. S.a.r.l.",
    "wof:placetype":"venue"
},
  "geometry": {"coordinates":[2.737985,47.639431],"type":"Point"}
}