{
  "type": "Feature",
  "properties": {
    "addr:full":"R Andr\u00e9 Boulle 86100 Ch\u00e2tellerault Poitou-Charentes 86100",
    "addr:postcode":"86100;86100",
    "iso:country":"FR",
    "sg:address":"R Andr\u00e9 Boulle 86100 Ch\u00e2tellerault",
    "sg:classifiers":[
        {
            "category":"Professional",
            "subcategory":"Engineering",
            "type":"Services"
        }
    ],
    "sg:phone":"+33 5 49 02 43 00",
    "sg:postcode":"86100",
    "sg:province":"Poitou-Charentes",
    "sg:tags":[
        "machine",
        "-",
        "mechanical"
    ],
    "wof:name":"Fabris Groupe Euralcom",
    "wof:placetype":"venue"
},
  "geometry": {"coordinates":[0.542846,46.847744],"type":"Point"}
}