{
  "type": "Feature",
  "properties": {
    "iso:country":"FR",
    "sg:address":"194 Rte De Toulouse 81100 Castres",
    "sg:classifiers":[
        {
            "category":"Autos & Motor Vehicles",
            "subcategory":"Automobile Sales",
            "type":"Retail Goods"
        }
    ],
    "sg:phone":"+33 5 63 71 81 50",
    "sg:province":"Midi Pyr\u00e9n\u00e9es",
    "sg:tags":[
        "equipment",
        "transport"
    ],
    "wof:name":"Sud Auto Sa",
    "wof:placetype":"venue"
},
  "geometry": {"coordinates":[2.200382,43.590488],"type":"Point"}
}