{
  "type": "Feature",
  "properties": {
    "addr:full":"Parc Industriel du Mesnil Lillebonne Haute Normandie 76170",
    "addr:postcode":"76170",
    "addr:street":"Parc Industriel Du Mesnil;Haute Normandie",
    "iso:country":"FR",
    "sg:address":"Parc Industriel du Mesnil",
    "sg:city":"Lillebonne",
    "sg:orig_category":"Unclassifiable Establishments",
    "sg:phone":"+33 2 32 84 11 60",
    "sg:postcode":"76170",
    "sg:province":"Haute Normandie",
    "wof:name":"Lenhardt S.a.",
    "wof:placetype":"venue"
},
  "geometry": {"coordinates":[0.537604,49.506561],"type":"Point"}
}