{
  "type": "Feature",
  "properties": {
    "addr:full":"B.P. 13205, 35532 Noyal sur Vilaine C\u00e9dex^^11, Av. de la Giravoli\u00e8re, 35530 Noyal sur Vilaine Br\u00e9c\u00e9 Bretagne 35530",
    "addr:housenumber":"13205",
    "addr:postcode":"35532;35530;bre\u0301ce\u0301;35530",
    "addr:street":"Av. De La Giravolie\u0300Re",
    "iso:country":"FR",
    "sg:address":"B.P. 13205, 35532 Noyal sur Vilaine C\u00e9dex^^11, Av. de la Giravoli\u00e8re, 35530 Noyal sur Vilaine",
    "sg:city":"Br\u00e9c\u00e9",
    "sg:orig_category":"Non-Classified Establishments",
    "sg:phone":"+33 2 99 00 53 35",
    "sg:postcode":"35530",
    "sg:province":"Bretagne",
    "wof:name":"Ovi Ouest Distribution E.u.r.l.",
    "wof:placetype":"venue"
},
  "geometry": {"coordinates":[-1.521279,48.110287],"type":"Point"}
}