{
  "type": "Feature",
  "properties": {
    "iso:country":"FR",
    "sg:address":"237, Rue de la Martini\u00e8re, 73000 Bassens",
    "sg:orig_category":"Non-Classified Establishments",
    "sg:phone":"+33 4 79 70 41 26",
    "sg:postcode":"73000",
    "sg:province":"Rhone-Alpes",
    "wof:name":"G.p.i. Concept",
    "wof:placetype":"venue"
},
  "geometry": {"coordinates":[5.939918,45.570587],"type":"Point"}
}