{
  "type": "Feature",
  "properties": {
    "iso:country":"FR",
    "sg:address":"B.P. 31, 67451 Mundolsheim C\u00e9dex^^Rue Vauban - Zone Industrielle, 67450 Mundolsheim",
    "sg:city":"Mundolsheim",
    "sg:orig_category":"Non-Classified Establishments",
    "sg:phone":"+33 3 88 20 45 13",
    "sg:postcode":"67450",
    "sg:province":"Alsace",
    "wof:name":"Nesta S.a.",
    "wof:placetype":"venue"
},
  "geometry": {"coordinates":[7.715445,48.641788],"type":"Point"}
}