{
  "type": "Feature",
  "properties": {
    "addr:full":"ZI de Boulay Sainte Gemmes sur Loire Pays de Loire 49130",
    "addr:postcode":"49130",
    "addr:street":"Zi De Boulay Sainte Gemmes Sur Loire",
    "iso:country":"FR",
    "sg:address":"ZI de Boulay",
    "sg:city":"Sainte Gemmes sur Loire",
    "sg:orig_category":"Unclassifiable Establishments",
    "sg:phone":"+33 2 41 68 41 55",
    "sg:postcode":"49130",
    "sg:province":"Pays de Loire",
    "wof:name":"Paxor S.a.",
    "wof:placetype":"venue"
},
  "geometry": {"coordinates":[-0.557269,47.425049],"type":"Point"}
}