{
  "type": "Feature",
  "properties": {
    "addr:full":"67 Rue Charles De Gaulle 78350 Jouy En Josas Ile de France 78350",
    "addr:housenumber":"67",
    "addr:postcode":"78350;78350",
    "addr:street":"Rue Charles De Gaulle",
    "iso:country":"FR",
    "sg:address":"67 Rue Charles De Gaulle 78350 Jouy En Josas",
    "sg:classifiers":[
        {
            "category":"Shopping",
            "subcategory":"Stationery & Office Supplies",
            "type":"Retail Goods"
        }
    ],
    "sg:phone":"+33 1 39 56 72 72",
    "sg:postcode":"78350",
    "sg:province":"Ile de France",
    "sg:tags":[
        "information",
        "technology",
        "telecommunication",
        "equipment"
    ],
    "wof:name":"Thales Computers Sa",
    "wof:placetype":"venue"
},
  "geometry": {"coordinates":[2.152055,48.768814],"type":"Point"}
}