{
  "type": "Feature",
  "properties": {
    "iso:country":"FR",
    "sg:address":"57, Rue Choletaise, 49450 Saint Macaire en Mauges",
    "sg:orig_category":"Non-Classified Establishments",
    "sg:phone":"+33 2 41 55 25 64",
    "sg:province":"Pays de Loire",
    "wof:name":"H\u00e9rault S.a.r.l.",
    "wof:placetype":"venue"
},
  "geometry": {"coordinates":[-0.988629,47.12281],"type":"Point"}
}