{
  "type": "Feature",
  "properties": {
    "addr:full":"4, Rue Marcel Jeantet, 78370 Plaisir Ile de France",
    "addr:housenumber":"4",
    "addr:postcode":"78370",
    "addr:street":"Rue Marcel Jeantet",
    "iso:country":"FR",
    "sg:address":"4, Rue Marcel Jeantet, 78370 Plaisir",
    "sg:orig_category":"Unclassifiable Establishments",
    "sg:phone":"+33 1 30 54 25 66",
    "sg:province":"Ile de France",
    "wof:name":"Soci\u00e9t\u00e9 A.l.v. Electronic S.a.r.l.",
    "wof:placetype":"venue"
},
  "geometry": {"coordinates":[1.942098,48.828098],"type":"Point"}
}