{
  "type": "Feature",
  "properties": {
    "addr:full":"8 bis, Rue des Creuses - PA des Verts Pr\u00e9s, 74960 Cran Gevrier Rhone-Alpes 74960",
    "addr:housenumber":"8 bis",
    "addr:postcode":"74960;74960",
    "addr:street":"Rue Des Creuses;Cran Gevrier Rhone-Alpes",
    "iso:country":"FR",
    "sg:address":"8 bis, Rue des Creuses - PA des Verts Pr\u00e9s, 74960 Cran Gevrier",
    "sg:orig_category":"Non-Classified Establishments",
    "sg:phone":"+33 4 50 52 17 89",
    "sg:postcode":"74960",
    "sg:province":"Rhone-Alpes",
    "wof:name":"Securiton S.a.",
    "wof:placetype":"venue"
},
  "geometry": {"coordinates":[6.10647,45.907654],"type":"Point"}
}