{
  "type": "Feature",
  "properties": {
    "iso:country":"FR",
    "sg:address":"Ch\u00e2teau Moulins \u00e0 Vent - Expert Nord",
    "sg:city":"C\u00e9rons",
    "sg:orig_category":"Non-Classified Establishments",
    "sg:phone":"+33 5 56 27 14 23",
    "sg:postcode":"33720",
    "sg:province":"Aquitaine",
    "wof:name":"Ch\u00e2teau Moulins \u00e0 Vent S.c.i.",
    "wof:placetype":"venue"
},
  "geometry": {"coordinates":[-0.385279,44.533298],"type":"Point"}
}