{
  "type": "Feature",
  "properties": {
    "iso:country":"FR",
    "sg:address":"129, Cours Emile Zola - Entr\u00e9e Rue Hippolyte Khan, 69100 Villeurbanne",
    "sg:orig_category":"Unclassifiable Establishments",
    "sg:phone":"+33 4 78 03 78 20",
    "sg:postcode":"69100",
    "sg:province":"Rhone-Alpes",
    "wof:name":"Setelinf S.a.r.l.",
    "wof:placetype":"venue"
},
  "geometry": {"coordinates":[4.875164,45.770432],"type":"Point"}
}