{
  "type": "Feature",
  "properties": {
    "addr:full":"3, Av Beauregard, 10400 Nogent sur Seine Champagne",
    "addr:postcode":"10400",
    "addr:street":"Av Beauregard",
    "iso:country":"FR",
    "sg:address":"3, Av Beauregard, 10400 Nogent sur Seine",
    "sg:orig_category":"Unclassifiable Establishments",
    "sg:phone":"+33 3 25 39 49 00",
    "sg:province":"Champagne",
    "wof:name":"Bertrand Faure Equipement S.a.",
    "wof:placetype":"venue"
},
  "geometry": {"coordinates":[3.494157,48.499485],"type":"Point"}
}