{
  "type": "Feature",
  "properties": {
    "iso:country":"FR",
    "sg:address":"Rte de F\u00e8re Champenoise",
    "sg:city":"S\u00e9zanne",
    "sg:orig_category":"Non-Classified Establishments",
    "sg:phone":"+33 3 26 80 69 01",
    "sg:postcode":"51120",
    "sg:province":"Champagne",
    "wof:name":"Coop\u00e9rative Agricole De S\u00e9zanne S.c.a.",
    "wof:placetype":"venue"
},
  "geometry": {"coordinates":[3.738545,48.717972],"type":"Point"}
}