{
  "type": "Feature",
  "properties": {
    "addr:full":"1 rue Gambetta; Aire sur l'Adour Champagne",
    "addr:housenumber":"1",
    "addr:street":"Rue Gambetta Aire Sur L'Adour",
    "iso:country":"FR",
    "sg:address":"1 rue Gambetta; Aire sur l'Adour",
    "sg:classifiers":[
        {
            "category":"Banks & Credit Unions",
            "subcategory":"Bank",
            "type":"Services"
        }
    ],
    "sg:phone":"+33 3358718585",
    "sg:province":"Champagne",
    "wof:name":"Banque Populaire, Du Sud-ouest",
    "wof:placetype":"venue"
},
  "geometry": {"coordinates":[-0.262797,43.699978],"type":"Point"}
}