{
  "type": "Feature",
  "properties": {
    "iso:country":"FR",
    "sg:address":"2 Carrefour de Od\u00e9on; Paris; 75006",
    "sg:classifiers":[
        {
            "category":"Banks & Credit Unions",
            "subcategory":"Bank",
            "type":"Services"
        }
    ],
    "sg:phone":"+33 1 43 25 38 17",
    "sg:postcode":"75006",
    "sg:province":"Ile de France",
    "wof:name":"Cr\u00e9dit Commercial De France",
    "wof:placetype":"venue"
},
  "geometry": {"coordinates":[2.33851,48.852139],"type":"Point"}
}