{
  "type": "Feature",
  "properties": {
    "iso:country":"FR",
    "sg:address":"B.P. 165, 41005 Blois C\u00e9dex^^36, Rue du Mar\u00e9chal de Lattre de Tassigny, 41000 Blois",
    "sg:city":"Blois",
    "sg:orig_category":"Non-Classified Establishments",
    "sg:phone":"+33 2 54 78 58 95",
    "sg:postcode":"41000",
    "sg:province":"Centre",
    "wof:name":"Forpis S.a.",
    "wof:placetype":"venue"
},
  "geometry": {"coordinates":[1.331433,47.586849],"type":"Point"}
}