{
  "type": "Feature",
  "properties": {
    "iso:country":"FR",
    "sg:address":"Route De Nouan 41300 Pierrefitte Sur Sauldre",
    "sg:city":"La Fert\u00e9-Imbault",
    "sg:classifiers":[
        {
            "category":"Manufacturing",
            "subcategory":"Rubber & Plastics",
            "type":"Manufacturing & Wholesale Goods"
        }
    ],
    "sg:phone":"+33 2 54 88 77 45",
    "sg:postcode":"41300",
    "sg:province":"Centre",
    "wof:name":"Orcaplast",
    "wof:placetype":"venue"
},
  "geometry": {"coordinates":[2.150805,47.51339],"type":"Point"}
}