{
  "type": "Feature",
  "properties": {
    "addr:full":"29 rue Gutenberg 93000 Bobigny Ile de France 93000",
    "addr:housenumber":"29",
    "addr:postcode":"93000;ile;93000",
    "addr:street":"Rue Gutenberg;France",
    "iso:country":"FR",
    "sg:address":"29 rue Gutenberg 93000 Bobigny",
    "sg:classifiers":[
        {
            "category":"Government",
            "subcategory":"Post Office",
            "type":"Public Place"
        }
    ],
    "sg:phone":"+33 1 48 44 37 27",
    "sg:postcode":"93000",
    "sg:province":"Ile de France",
    "sg:tags":[
        "mailbox"
    ],
    "wof:name":"Sirandr\u00e9 S.a.",
    "wof:placetype":"venue"
},
  "geometry": {"coordinates":[2.426609,48.903366],"type":"Point"}
}