{
  "type": "Feature",
  "properties": {
    "iso:country":"FR",
    "sg:address":"77320 Montolivet",
    "sg:orig_category":"Non-Classified Establishments",
    "sg:phone":"+33 1 64 03 75 03",
    "sg:province":"Ile de France",
    "wof:name":"S.l.c. S.a.r.l. - Soci\u00e9t\u00e9 Locatercienne De Cr\u00e9ation",
    "wof:placetype":"venue"
},
  "geometry": {"coordinates":[3.440787,48.829605],"type":"Point"}
}