{
  "type": "Feature",
  "properties": {
    "iso:country":"FR",
    "sg:address":"17, Rue du Faubourg Saint Honor\u00e9, 75008 Paris",
    "sg:orig_category":"Non-Classified Establishments",
    "sg:phone":"+33 1 40 06 89 00",
    "sg:postcode":"75008",
    "sg:province":"Ile de France",
    "wof:name":"Est\u00e9e Lauder S.n.c.",
    "wof:placetype":"venue"
},
  "geometry": {"coordinates":[2.321673,48.868755],"type":"Point"}
}