{
  "type": "Feature",
  "properties": {
    "addr:full":"26 Boulevard Mar\u00e9chal Joffre Lorient Bretagne 56100",
    "addr:housenumber":"26",
    "addr:postcode":"56100",
    "addr:street":"Boulevard Mare\u0301Chal Joffre;Bretagne",
    "iso:country":"FR",
    "sg:address":"26 Boulevard Mar\u00e9chal Joffre",
    "sg:city":"Lorient",
    "sg:classifiers":[
        {
            "category":"Banks & Credit Unions",
            "subcategory":"Financial Services",
            "type":"Services"
        }
    ],
    "sg:phone":"+33 2 97 64 72 73",
    "sg:postcode":"56100",
    "sg:province":"Bretagne",
    "sg:tags":[
        "banking",
        "finance",
        "insurance"
    ],
    "wof:name":"Dcn Log Sa",
    "wof:placetype":"venue"
},
  "geometry": {"coordinates":[-3.362343,47.752811],"type":"Point"}
}