{
  "type": "Feature",
  "properties": {
    "iso:country":"FR",
    "sg:address":"48150 Meyrueis",
    "sg:orig_category":"Unclassifiable Establishments",
    "sg:phone":"+33 4 66 45 60 42",
    "sg:province":"Languedoc-Roussillon",
    "wof:name":"Aigoual Provence S.a.r.l.",
    "wof:placetype":"venue"
},
  "geometry": {"coordinates":[3.431028,44.180534],"type":"Point"}
}