{
  "type": "Feature",
  "properties": {
    "iso:country":"FR",
    "sg:address":"4 All De La Garenne Zi Nord 28109 Dreux Cedex",
    "sg:classifiers":[
        {
            "category":"Professional",
            "subcategory":"Engineering",
            "type":"Services"
        }
    ],
    "sg:phone":"+33 2 37 62 57 01",
    "sg:province":"Aquitaine",
    "sg:tags":[
        "machine",
        "-",
        "mechanical"
    ],
    "wof:name":"Stork Systemes Alimentaires",
    "wof:placetype":"venue"
},
  "geometry": {"coordinates":[1.362293,48.736141],"type":"Point"}
}