{
  "type": "Feature",
  "properties": {
    "addr:full":"12, Place du Grand Jardin, 06140 Vence Provence-Alpes-C\u00f4te d'Azur",
    "addr:housenumber":"12",
    "addr:postcode":"06140",
    "addr:street":"Place Du Grand Jardin",
    "iso:country":"FR",
    "sg:address":"12, Place du Grand Jardin, 06140 Vence",
    "sg:orig_category":"Unclassifiable Establishments",
    "sg:phone":"+33 4 93 58 37 60",
    "sg:province":"Provence-Alpes-C\u00f4te d'Azur",
    "wof:name":"S.a.p. S.a. - Soci\u00e9t\u00e9 Automobiles De Provence",
    "wof:placetype":"venue"
},
  "geometry": {"coordinates":[7.111655,43.722939],"type":"Point"}
}