{
  "type": "Feature",
  "properties": {
    "iso:country":"FR",
    "sg:address":"57, Rte du Fort Rouge, 59173 Renescure",
    "sg:orig_category":"Unclassifiable Establishments",
    "sg:phone":"+33 3 28 49 81 36",
    "sg:province":"Nord Pas-de-Calais",
    "wof:name":"Broussart Transport S.a.",
    "wof:placetype":"venue"
},
  "geometry": {"coordinates":[2.350212,50.737045],"type":"Point"}
}