{
  "type": "Feature",
  "properties": {
    "iso:country":"FR",
    "sg:address":"56, Rue Ferdinand Buisson - Centre Directionnel, 62200 Boulogne sur Mer",
    "sg:orig_category":"Non-Classified Establishments",
    "sg:phone":"+33 3 21 10 48 88",
    "sg:postcode":"62200",
    "sg:province":"Nord Pas-de-Calais",
    "wof:name":"Distrifish S.a.r.l.",
    "wof:placetype":"venue"
},
  "geometry": {"coordinates":[1.615514,50.727444],"type":"Point"}
}