{
  "type": "Feature",
  "properties": {
    "addr:full":"B.P. 109, 29411 Landerneau^^ZI de K\u00e9riel, 29800 Plou\u00e9dern Plou\u00e9dern Bretagne 29800",
    "addr:housenumber":"b.p. 109",
    "addr:postcode":"29411;29800;29800",
    "iso:country":"FR",
    "sg:address":"B.P. 109, 29411 Landerneau^^ZI de K\u00e9riel, 29800 Plou\u00e9dern",
    "sg:city":"Plou\u00e9dern",
    "sg:orig_category":"Non-Classified Establishments",
    "sg:phone":"+33 2 98 85 46 00",
    "sg:postcode":"29800",
    "sg:province":"Bretagne",
    "wof:name":"V\u00e9tarvor S.a.",
    "wof:placetype":"venue"
},
  "geometry": {"coordinates":[-4.228497,48.400295],"type":"Point"}
}