{
  "type": "Feature",
  "properties": {
    "addr:full":"10, Bd Victor Hugo, 02100 Saint Quentin Picardie",
    "addr:housenumber":"10",
    "addr:postcode":"02100",
    "addr:street":"Bd Victor Hugo",
    "iso:country":"FR",
    "sg:address":"10, Bd Victor Hugo, 02100 Saint Quentin",
    "sg:orig_category":"Non-Classified Establishments",
    "sg:phone":"+33 3 23 06 53 80",
    "sg:province":"Picardie",
    "wof:name":"Grand Moulin De Saint Quentin S.a.",
    "wof:placetype":"venue"
},
  "geometry": {"coordinates":[3.279875,49.84301],"type":"Point"}
}