{
  "type": "Feature",
  "properties": {
    "addr:full":"65 Rue De Turbigo 75003 Paris Ile de France 75003",
    "addr:housenumber":"65",
    "addr:postcode":"75003;75003",
    "addr:street":"Rue De Turbigo",
    "iso:country":"FR",
    "sg:address":"65 Rue De Turbigo 75003 Paris",
    "sg:classifiers":[
        {
            "category":"Manufacturing",
            "subcategory":"Textiles",
            "type":"Manufacturing & Wholesale Goods"
        }
    ],
    "sg:phone":"+33 1 42 71 93 34",
    "sg:postcode":"75003",
    "sg:province":"Ile de France",
    "sg:tags":[
        "clothing",
        "accessory"
    ],
    "wof:name":"Societe De Faconnage D'ille Et Vilaine (sofail)",
    "wof:placetype":"venue"
},
  "geometry": {"coordinates":[2.358403,48.866112],"type":"Point"}
}