{
  "type": "Feature",
  "properties": {
    "iso:country":"FR",
    "sg:address":"ZI de la Fondani\u00e8re",
    "sg:city":"La Tardi\u00e8re",
    "sg:orig_category":"Non-Classified Establishments",
    "sg:phone":"+33 2 51 52 60 88",
    "sg:postcode":"85120",
    "sg:province":"Pays de Loire",
    "wof:name":"C\u00e9leste S.a.r.l.",
    "wof:placetype":"venue"
},
  "geometry": {"coordinates":[-0.732236,46.661289],"type":"Point"}
}