{
  "type": "Feature",
  "properties": {
    "addr:full":"Rue De La Burliere 04300 MANE Centre",
    "addr:postcode":"04300",
    "addr:street":"Rue De La Burliere",
    "iso:country":"FR",
    "sg:address":"Rue De La Burliere 04300 MANE",
    "sg:classifiers":[
        {
            "category":"Food & Beverages",
            "subcategory":"Specialty",
            "type":"Retail Goods"
        }
    ],
    "sg:phone":"+33 4 92 70 48 20",
    "sg:province":"Centre",
    "sg:tags":[
        "olive-oil"
    ],
    "wof:name":"Oliviers Et Co Sa",
    "wof:placetype":"venue"
},
  "geometry": {"coordinates":[5.765732,43.936478],"type":"Point"}
}