{
  "type": "Feature",
  "properties": {
    "iso:country":"FR",
    "sg:address":"Av. Paul Sabatier - ZI de la Pomme",
    "sg:city":"Revel",
    "sg:orig_category":"Non-Classified Establishments",
    "sg:phone":"+33 5 62 18 71 88",
    "sg:postcode":"31250",
    "sg:province":"Midi Pyr\u00e9n\u00e9es",
    "wof:name":"M\u00e9calaser S.a.r.l.",
    "wof:placetype":"venue"
},
  "geometry": {"coordinates":[1.981125,43.426174],"type":"Point"}
}