{
  "type": "Feature",
  "properties": {
    "addr:full":"B.P. 2 Uz\u00e8s C\u00e9dex^^Saint Geni\u00e8s 30700 Uz\u00e8s Languedoc-Roussillon 30702",
    "addr:postcode":"30700;30702",
    "addr:street":"B.P. 2;Ce\u0301Dex^^Saint Genie\u0300S",
    "iso:country":"FR",
    "sg:address":"B.P. 2",
    "sg:city":"Uz\u00e8s C\u00e9dex^^Saint Geni\u00e8s 30700 Uz\u00e8s",
    "sg:orig_category":"Non-Classified Establishments",
    "sg:phone":"+33 4 66 03 21 21",
    "sg:postcode":"30702",
    "sg:province":"Languedoc-Roussillon",
    "wof:name":"Sedi S.a.",
    "wof:placetype":"venue"
},
  "geometry": {"coordinates":[4.4258,43.953457],"type":"Point"}
}