{
  "type": "Feature",
  "properties": {
    "addr:full":"35 Pl Pey-Bernand 33000 Bordeaux Bordeaux Aquitaine 33000",
    "addr:housenumber":"35",
    "addr:postcode":"33000;33000",
    "addr:street":"Pl Pey-Bernand",
    "iso:country":"FR",
    "sg:address":"35 Pl Pey-Bernand 33000 Bordeaux",
    "sg:city":"Bordeaux",
    "sg:classifiers":[
        {
            "category":"Professional",
            "subcategory":"Business Services",
            "type":"Services"
        }
    ],
    "sg:phone":"+33 5 56 00 45 67",
    "sg:postcode":"33000",
    "sg:province":"Aquitaine",
    "sg:tags":[
        "training",
        "advice"
    ],
    "wof:name":"Institut D'administration Des Entreprises",
    "wof:placetype":"venue"
},
  "geometry": {"coordinates":[-0.577927,44.837082],"type":"Point"}
}