{
  "type": "Feature",
  "properties": {
    "addr:full":"1 rue du port de Valvins Avon 77210",
    "addr:housenumber":"1",
    "addr:postcode":"77210",
    "addr:street":"Rue Du Port De Valvins",
    "iso:country":"FR",
    "sg:address":"1 rue du port de Valvins",
    "sg:city":"Avon",
    "sg:classifiers":[
        {
            "category":"Professional",
            "subcategory":"Computer Services",
            "type":"Services"
        }
    ],
    "sg:postcode":"77210",
    "sg:tags":[
        "environment",
        "industry",
        "security",
        "machine-listening",
        "sound-source-recognition",
        "audio"
    ],
    "sg:website":"http://www.orelia.fr",
    "wof:name":"ORELIA",
    "wof:placetype":"venue"
},
  "geometry": {"coordinates":[2.74495,48.423737],"type":"Point"}
}