{
  "type": "Feature",
  "properties": {
    "iso:country":"FR",
    "sg:address":"2, Rue de la Gare, 67650 Dambach la Ville",
    "sg:city":"Blienschwiller",
    "sg:orig_category":"Unclassifiable Establishments",
    "sg:phone":"+33 3 88 92 41 14",
    "sg:postcode":"67650",
    "sg:province":"Alsace",
    "wof:name":"Freyermuth S.a.r.l.",
    "wof:placetype":"venue"
},
  "geometry": {"coordinates":[7.430722,48.323517],"type":"Point"}
}