{
  "type": "Feature",
  "properties": {
    "addr:full":"85/93, Bd Alsace Lorraine, 93115 Rosny sous Bois C\u00e9dex Poitou-Charentes",
    "addr:housenumber":"85 / 93",
    "addr:postcode":"93115",
    "addr:street":"Bd Alsace Lorraine;Ce\u0301Dex",
    "iso:country":"FR",
    "sg:address":"85/93, Bd Alsace Lorraine, 93115 Rosny sous Bois C\u00e9dex",
    "sg:orig_category":"Non-Classified Establishments",
    "sg:phone":"+33 1 48 54 48 00",
    "sg:province":"Poitou-Charentes",
    "wof:name":"Bonin Atecma S.a.",
    "wof:placetype":"venue"
},
  "geometry": {"coordinates":[2.481961,48.885078],"type":"Point"}
}