{
  "type": "Feature",
  "properties": {
    "addr:full":"5, Rte des Vall\u00e9es, 74100 Annemasse Rhone-Alpes",
    "addr:housenumber":"5",
    "addr:postcode":"74100",
    "addr:street":"Rte Des Valle\u0301Es",
    "iso:country":"FR",
    "sg:address":"5, Rte des Vall\u00e9es, 74100 Annemasse",
    "sg:orig_category":"Non-Classified Establishments",
    "sg:phone":"+33 4 50 37 71 81",
    "sg:province":"Rhone-Alpes",
    "wof:name":"Richardson S.a.",
    "wof:placetype":"venue"
},
  "geometry": {"coordinates":[6.241167,46.194069],"type":"Point"}
}