{
  "type": "Feature",
  "properties": {
    "addr:full":"lieu dit la Pelissi\u00e8re 01300 Belley Rhone-Alpes 01300",
    "addr:postcode":"01300;01300",
    "addr:street":"Lieu Dit La Pelissie\u0300Re",
    "iso:country":"FR",
    "sg:address":"lieu dit la Pelissi\u00e8re 01300 Belley",
    "sg:classifiers":[
        {
            "category":"Shopping",
            "subcategory":"Luggage & Leather Goods",
            "type":"Retail Goods"
        }
    ],
    "sg:phone":"+33 4 79 81 29 15",
    "sg:postcode":"01300",
    "sg:province":"Rhone-Alpes",
    "sg:tags":[
        "fine"
    ],
    "wof:name":"Tranchand Sa",
    "wof:placetype":"venue"
},
  "geometry": {"coordinates":[5.680552,45.744801],"type":"Point"}
}