{
  "type": "Feature",
  "properties": {
    "addr:full":"Au Moulin De Culausse 32160 Beaumarch\u00e9s Midi Pyr\u00e9n\u00e9es 32160",
    "addr:postcode":"32160;32160",
    "iso:country":"FR",
    "sg:address":"Au Moulin De Culausse 32160 Beaumarch\u00e9s",
    "sg:classifiers":[
        {
            "category":"Manufacturing",
            "subcategory":"Chemicals & Compounds",
            "type":"Manufacturing & Wholesale Goods"
        }
    ],
    "sg:phone":"+33 5 62 69 35 01",
    "sg:postcode":"32160",
    "sg:province":"Midi Pyr\u00e9n\u00e9es",
    "sg:tags":[
        "pharmaceutical",
        "chemistry"
    ],
    "wof:name":"Hjp Cazaban Sa",
    "wof:placetype":"venue"
},
  "geometry": {"coordinates":[0.081769,43.578201],"type":"Point"}
}