{
  "type": "Feature",
  "properties": {
    "addr:full":"279 Chem Cantecor BP 66 82100 Castelsarrasin Midi Pyr\u00e9n\u00e9es 82100",
    "addr:housenumber":"279;66",
    "addr:postcode":"82100;82100",
    "addr:street":"Chem Cantecor Bp",
    "iso:country":"FR",
    "sg:address":"279 Chem Cantecor BP 66 82100 Castelsarrasin",
    "sg:classifiers":[
        {
            "category":"Manufacturing",
            "subcategory":"Textiles",
            "type":"Manufacturing & Wholesale Goods"
        }
    ],
    "sg:phone":"+33 5 63 32 30 41",
    "sg:postcode":"82100",
    "sg:province":"Midi Pyr\u00e9n\u00e9es",
    "sg:tags":[
        "linen",
        "clothing",
        "fabric"
    ],
    "wof:name":"Fourment Christian Et Fils Sa",
    "wof:placetype":"venue"
},
  "geometry": {"coordinates":[1.115304,44.041035],"type":"Point"}
}