{
  "type": "Feature",
  "properties": {
    "addr:full":"167, Impasse des Deux Poteaux, 33127 Saint Jean d'Illac Martignas-sur-Jalle Aquitaine 33127",
    "addr:housenumber":"167",
    "addr:postcode":"33127;33127",
    "addr:street":"Impasse Des Deux Poteaux",
    "iso:country":"FR",
    "sg:address":"167, Impasse des Deux Poteaux, 33127 Saint Jean d'Illac",
    "sg:city":"Martignas-sur-Jalle",
    "sg:orig_category":"Unclassifiable Establishments",
    "sg:phone":"+33 5 56 13 19 65",
    "sg:postcode":"33127",
    "sg:province":"Aquitaine",
    "wof:name":"D\u00e9cap' Services S.a.r.l.",
    "wof:placetype":"venue"
},
  "geometry": {"coordinates":[-0.728629,44.812458],"type":"Point"}
}