{
  "type": "Feature",
  "properties": {
    "addr:full":"182 Rue Delespaul 59100 Roubaix Nord Pas-de-Calais 59100",
    "addr:housenumber":"182",
    "addr:postcode":"59100;59100",
    "addr:street":"Rue Delespaul",
    "iso:country":"FR",
    "sg:address":"182 Rue Delespaul 59100 Roubaix",
    "sg:classifiers":[
        {
            "category":"Manufacturing",
            "subcategory":"Textiles",
            "type":"Manufacturing & Wholesale Goods"
        }
    ],
    "sg:phone":"+33 3 20 24 88 35",
    "sg:postcode":"59100",
    "sg:province":"Nord Pas-de-Calais",
    "sg:tags":[
        "clothing",
        "accessory"
    ],
    "wof:name":"Sarl Cartigny",
    "wof:placetype":"venue"
},
  "geometry": {"coordinates":[3.184671,50.705067],"type":"Point"}
}