{
  "type": "Feature",
  "properties": {
    "iso:country":"FR",
    "sg:address":"70 avenue de l'Europe 13127 Vitrolles",
    "sg:classifiers":[
        {
            "category":"Organizations",
            "subcategory":"Non-profit Organization",
            "type":"Services"
        }
    ],
    "sg:phone":"+33 4 42 34 42 34",
    "sg:province":"Haute Normandie",
    "sg:tags":[
        "industrial",
        "system",
        "hydraulic"
    ],
    "wof:name":"Le Vulcain Sa",
    "wof:placetype":"venue"
},
  "geometry": {"coordinates":[5.25141,43.42292],"type":"Point"}
}