{
  "type": "Feature",
  "properties": {
    "addr:full":"206, Rue de la Benauge, 33100 Bordeaux Bordeaux Aquitaine 33100",
    "addr:housenumber":"206",
    "addr:postcode":"33100;33100",
    "addr:street":"Rue De La Benauge",
    "iso:country":"FR",
    "sg:address":"206, Rue de la Benauge, 33100 Bordeaux",
    "sg:city":"Bordeaux",
    "sg:orig_category":"Unclassifiable Establishments",
    "sg:phone":"+33 5 56 32 56 59",
    "sg:postcode":"33100",
    "sg:province":"Aquitaine",
    "wof:name":"White Production Music",
    "wof:placetype":"venue"
},
  "geometry": {"coordinates":[-0.546966,44.841469],"type":"Point"}
}