{
  "type": "Feature",
  "properties": {
    "addr:full":"33, Rue de la Mainguais, 44470 Carquefou Pays de Loire",
    "addr:housenumber":"33",
    "addr:postcode":"44470",
    "addr:street":"Rue De La Mainguais",
    "iso:country":"FR",
    "sg:address":"33, Rue de la Mainguais, 44470 Carquefou",
    "sg:orig_category":"Unclassifiable Establishments",
    "sg:phone":"+33 2 40 68 68 68",
    "sg:province":"Pays de Loire",
    "wof:name":"S.e.i.t.a. S.a. - Soci\u00e9t\u00e9 D'exploitation Industrielle Des Tabacs Et Allumettes, Groupe Altadis",
    "wof:placetype":"venue"
},
  "geometry": {"coordinates":[-1.502016,47.268116],"type":"Point"}
}