{
  "type": "Feature",
  "properties": {
    "iso:country":"FR",
    "sg:address":"3-5 R De La Haute Borne 95610 Eragny Sur Oise",
    "sg:classifiers":[
        {
            "category":"Manufacturing",
            "subcategory":"Tools & Machinery",
            "type":"Manufacturing & Wholesale Goods"
        }
    ],
    "sg:phone":"+33 1 34 48 53 53",
    "sg:postcode":"95610",
    "sg:province":"Ile de France",
    "sg:tags":[
        "metallurgy",
        "metalworking"
    ],
    "wof:name":"Snor",
    "wof:placetype":"venue"
},
  "geometry": {"coordinates":[2.110934,49.010746],"type":"Point"}
}