{
  "type": "Feature",
  "properties": {
    "iso:country":"FR",
    "sg:address":"Chemin de Castre - Les Mouli\u00e8res",
    "sg:city":"P\u00e9zenas",
    "sg:orig_category":"Non-Classified Establishments",
    "sg:phone":"+33 4 67 98 26 65",
    "sg:postcode":"34120",
    "sg:province":"Languedoc-Roussillon",
    "wof:name":"Guitard Philippe S.a.r.l.",
    "wof:placetype":"venue"
},
  "geometry": {"coordinates":[3.424247,43.461823],"type":"Point"}
}