{
  "type": "Feature",
  "properties": {
    "iso:country":"FR",
    "sg:address":"1, Rue de l'Epinette, 59000 Lille",
    "sg:orig_category":"Unclassifiable Establishments",
    "sg:phone":"+33 3 20 10 32 40",
    "sg:province":"Nord Pas-de-Calais",
    "wof:name":"Comptoir Lillois De L'automobile S.a.",
    "wof:placetype":"venue"
},
  "geometry": {"coordinates":[3.062628,50.67411],"type":"Point"}
}