{
  "type": "Feature",
  "properties": {
    "addr:full":"B.P. 524, 50105 Cherbourg C\u00e9dex^^Quai Batavia, 50100 Cherbourg Cherbourg-Octeville Basse Normandie 50100",
    "addr:housenumber":"b.p. 524",
    "addr:postcode":"50105;50100;50100",
    "iso:country":"FR",
    "sg:address":"B.P. 524, 50105 Cherbourg C\u00e9dex^^Quai Batavia, 50100 Cherbourg",
    "sg:city":"Cherbourg-Octeville",
    "sg:orig_category":"Non-Classified Establishments",
    "sg:phone":"+33 2 33 88 50 00",
    "sg:postcode":"50100",
    "sg:province":"Basse Normandie",
    "wof:name":"Socoval S.a.",
    "wof:placetype":"venue"
},
  "geometry": {"coordinates":[-1.616124,49.640484],"type":"Point"}
}