{
  "type": "Feature",
  "properties": {
    "addr:full":"Uffel 01590 DORTAN Rhone-Alpes 01590",
    "addr:postcode":"01590;01590",
    "addr:street":"Uffel",
    "iso:country":"FR",
    "sg:address":"Uffel 01590 DORTAN",
    "sg:classifiers":[
        {
            "category":"Wholesale",
            "subcategory":"Vending Machines",
            "type":"Manufacturing & Wholesale Goods"
        }
    ],
    "sg:phone":"+33 4 74 75 83 02",
    "sg:postcode":"01590",
    "sg:province":"Rhone-Alpes",
    "sg:tags":[
        "plastics",
        "used",
        "welding"
    ],
    "wof:name":"Srmo S.a.r.l.",
    "wof:placetype":"venue"
},
  "geometry": {"coordinates":[5.647441,46.333443],"type":"Point"}
}