{
  "type": "Feature",
  "properties": {
    "iso:country":"FR",
    "sg:address":"B.P. 16, 59420 Mouvaux^^91, Rue de l'Epinette, 59420 Mouvaux",
    "sg:orig_category":"Non-Classified Establishments",
    "sg:phone":"+33 3 20 11 63 63",
    "sg:province":"Nord Pas-de-Calais",
    "wof:name":"Subrenat Expansion S.a.",
    "wof:placetype":"venue"
},
  "geometry": {"coordinates":[3.131775,50.691559],"type":"Point"}
}