{
  "type": "Feature",
  "properties": {
    "addr:full":"lieu dit Saint-Denis 27130 Verneuil sur Avre Haute Normandie 27130",
    "addr:postcode":"27130;27130",
    "addr:street":"Lieu Dit Saint-Denis;Haute Normandie",
    "iso:country":"FR",
    "sg:address":"lieu dit Saint-Denis 27130 Verneuil sur Avre",
    "sg:orig_category":"Multi-Modal Transportation Services Rail, Road, Water, Air",
    "sg:phone":"+33 2 32 32 01 60",
    "sg:postcode":"27130",
    "sg:province":"Haute Normandie",
    "wof:name":"Gunst Sa",
    "wof:placetype":"venue"
},
  "geometry": {"coordinates":[0.935007,48.750996],"type":"Point"}
}