{
  "type": "Feature",
  "properties": {
    "iso:country":"FR",
    "sg:address":"32, Rue de l'Est, 68110 Illzach",
    "sg:city":"Illzach",
    "sg:orig_category":"Unclassifiable Establishments",
    "sg:phone":"+33 3 89 53 54 71",
    "sg:postcode":"68110",
    "sg:province":"Alsace",
    "wof:name":"Enviro Consult S.a.r.l.",
    "wof:placetype":"venue"
},
  "geometry": {"coordinates":[7.354897,47.78017],"type":"Point"}
}