{
  "type": "Feature",
  "properties": {
    "iso:country":"FR",
    "sg:address":"3, Rue du Noyer, 35000 Rennes",
    "sg:city":"Rennes",
    "sg:orig_category":"Non-Classified Establishments",
    "sg:phone":"+33 2 99 53 08 43",
    "sg:postcode":"35000",
    "sg:province":"Bretagne",
    "wof:name":"Armel S.a.r.l.",
    "wof:placetype":"venue"
},
  "geometry": {"coordinates":[-1.635644,48.098202],"type":"Point"}
}