{
  "type": "Feature",
  "properties": {
    "addr:full":"Route Port St Pierre 70140 Broye Aubigney Montseugny Franche Comt\u00e9 70140",
    "addr:postcode":"70140;70140",
    "addr:street":"Route Port St Pierre;Aubigney Montseugny Franche Comte\u0301",
    "iso:country":"FR",
    "sg:address":"Route Port St Pierre 70140 Broye Aubigney Montseugny",
    "sg:classifiers":[
        {
            "category":"Professional",
            "subcategory":"Engineering",
            "type":"Services"
        }
    ],
    "sg:phone":"+33 3 84 31 60 90",
    "sg:postcode":"70140",
    "sg:province":"Franche Comt\u00e9",
    "sg:tags":[
        "machine",
        "-",
        "mechanical"
    ],
    "wof:name":"Sodramec Sarl",
    "wof:placetype":"venue"
},
  "geometry": {"coordinates":[5.509005,47.318272],"type":"Point"}
}