{
  "type": "Feature",
  "properties": {
    "addr:full":"9 Rue D Amboise 37530 Nazelles Negron Cangey Centre 37530",
    "addr:housenumber":"9;cangey",
    "addr:postcode":"37530;37530",
    "addr:street":"Rue D Amboise",
    "iso:country":"FR",
    "sg:address":"9 Rue D Amboise 37530 Nazelles Negron",
    "sg:city":"Cangey",
    "sg:classifiers":[
        {
            "category":"Wholesale",
            "subcategory":"Machinery & Supplies",
            "type":"Manufacturing & Wholesale Goods"
        }
    ],
    "sg:phone":"+33 2 47 57 10 40",
    "sg:postcode":"37530",
    "sg:province":"Centre",
    "sg:tags":[
        "handling",
        "material",
        "-",
        "machine",
        "equipment",
        "engineering",
        "mechanical"
    ],
    "wof:name":"Costen",
    "wof:placetype":"venue"
},
  "geometry": {"coordinates":[0.977416,47.419239],"type":"Point"}
}