{
  "type": "Feature",
  "properties": {
    "addr:full":"18, Rue des Potiers d'Etain - Actip\u00f4le Metz-Borny, 57070 Metz Lorraine",
    "addr:housenumber":"18",
    "addr:postcode":"57070",
    "addr:street":"Rue Des Potiers D'Etain Actipo\u0302Le Metz-Borny",
    "iso:country":"FR",
    "sg:address":"18, Rue des Potiers d'Etain - Actip\u00f4le Metz-Borny, 57070 Metz",
    "sg:orig_category":"Unclassifiable Establishments",
    "sg:phone":"+33 3 87 21 12 21",
    "sg:province":"Lorraine",
    "wof:name":"B.e.s. S.a. - Bealas Energie Services - Agence De Metz",
    "wof:placetype":"venue"
},
  "geometry": {"coordinates":[6.243937,49.111488],"type":"Point"}
}