{
  "type": "Feature",
  "properties": {
    "addr:full":"rte C\u00e9pet 31150 Brugui\u00e8res Midi Pyr\u00e9n\u00e9es 31150",
    "addr:postcode":"31150;31150",
    "addr:street":"Rte Ce\u0301Pet",
    "iso:country":"FR",
    "sg:address":"rte C\u00e9pet 31150 Brugui\u00e8res",
    "sg:classifiers":[
        {
            "category":"Food & Beverages",
            "subcategory":"Meat & Fish",
            "type":"Retail Goods"
        }
    ],
    "sg:phone":"+33 5 62 22 08 22",
    "sg:postcode":"31150",
    "sg:province":"Midi Pyr\u00e9n\u00e9es",
    "sg:tags":[
        "preserve",
        "cooked",
        "product",
        "related"
    ],
    "wof:name":"Marquisat Foie Gras",
    "wof:placetype":"venue"
},
  "geometry": {"coordinates":[1.420539,43.751408],"type":"Point"}
}