{
  "type": "Feature",
  "properties": {
    "addr:full":"18, Rue du Poitou, 94150 Rungis Ile de France",
    "addr:housenumber":"18",
    "addr:postcode":"94150",
    "addr:street":"Rue Du Poitou",
    "iso:country":"FR",
    "sg:address":"18, Rue du Poitou, 94150 Rungis",
    "sg:orig_category":"Unclassifiable Establishments",
    "sg:phone":"+33 1 45 12 82 00",
    "sg:province":"Ile de France",
    "wof:name":"Banexo S.a.",
    "wof:placetype":"venue"
},
  "geometry": {"coordinates":[2.361155,48.757225],"type":"Point"}
}