{
  "type": "Feature",
  "properties": {
    "iso:country":"FR",
    "sg:address":"30, Rue Tronchet, 69006 Lyon",
    "sg:orig_category":"Non-Classified Establishments",
    "sg:phone":"+33 4 78 89 57 66",
    "sg:postcode":"69006",
    "sg:province":"Rhone-Alpes",
    "wof:name":"D\u00e9m\u00e9nagement Fontaine S.a.",
    "wof:placetype":"venue"
},
  "geometry": {"coordinates":[4.847403,45.769676],"type":"Point"}
}