{
  "type": "Feature",
  "properties": {
    "addr:full":"10, Rue de l'Eglise, 59292 Saint Hilaire lez Cambrai Nord Pas-de-Calais",
    "addr:housenumber":"10",
    "addr:postcode":"59292",
    "addr:street":"Rue De L'Eglise",
    "iso:country":"FR",
    "sg:address":"10, Rue de l'Eglise, 59292 Saint Hilaire lez Cambrai",
    "sg:orig_category":"Unclassifiable Establishments",
    "sg:phone":"+33 3 27 37 07 33",
    "sg:province":"Nord Pas-de-Calais",
    "wof:name":"Jacquemin Et Fils S.a.r.l.",
    "wof:placetype":"venue"
},
  "geometry": {"coordinates":[3.413598,50.183067],"type":"Point"}
}