{
  "type": "Feature",
  "properties": {
    "addr:full":"22, Rue Paulin M\u00e9ry, 75013 Paris Ile de France",
    "addr:housenumber":"22",
    "addr:postcode":"75013",
    "addr:street":"Rue Paulin",
    "iso:country":"FR",
    "sg:address":"22, Rue Paulin M\u00e9ry, 75013 Paris",
    "sg:orig_category":"Non-Classified Establishments",
    "sg:phone":"+33 1 45 81 59 20",
    "sg:province":"Ile de France",
    "wof:name":"Gaymard Consultants",
    "wof:placetype":"venue"
},
  "geometry": {"coordinates":[2.353099,48.829914],"type":"Point"}
}