{
  "type": "Feature",
  "properties": {
    "addr:full":"B.P. 94, 67038 Strasbourg C\u00e9dex 2^^1, Rue Alfred Kasler, 67200 Eckbolsheim Strasbourg Alsace 67200",
    "addr:housenumber":"2 ^ ^ 1",
    "addr:postcode":"67038;67200;67200",
    "addr:street":"B.P. 94;Ce\u0301Dex;Rue Alfred Kasler",
    "iso:country":"FR",
    "sg:address":"B.P. 94, 67038 Strasbourg C\u00e9dex 2^^1, Rue Alfred Kasler, 67200 Eckbolsheim",
    "sg:city":"Strasbourg",
    "sg:orig_category":"Non-Classified Establishments",
    "sg:phone":"+33 3 88 78 91 91",
    "sg:postcode":"67200",
    "sg:province":"Alsace",
    "wof:name":"Editions Du Signe S.a.",
    "wof:placetype":"venue"
},
  "geometry": {"coordinates":[7.687253,48.579323],"type":"Point"}
}