{
  "type": "Feature",
  "properties": {
    "iso:country":"FR",
    "sg:address":"Rue de l'Abattoir",
    "sg:city":"Brumath",
    "sg:orig_category":"Unclassifiable Establishments",
    "sg:phone":"+33 3 88 64 67 00",
    "sg:postcode":"67170",
    "sg:province":"Alsace",
    "wof:name":"Copvial - Coop\u00e9rative Des Producteurs De Viande D'alsace",
    "wof:placetype":"venue"
},
  "geometry": {"coordinates":[7.688706,48.735622],"type":"Point"}
}