{
  "type": "Feature",
  "properties": {
    "addr:full":"Saint Lazare 37500 Chinon Cedex Chinon Centre 37500",
    "addr:postcode":"37500;37500",
    "addr:street":"Saint Lazare",
    "iso:country":"FR",
    "sg:address":"Saint Lazare 37500 Chinon Cedex",
    "sg:city":"Chinon",
    "sg:classifiers":[
        {
            "category":"Building & Trades",
            "subcategory":"Construction",
            "type":"Services"
        }
    ],
    "sg:phone":"+33 2 47 93 16 56",
    "sg:postcode":"37500",
    "sg:province":"Centre",
    "sg:tags":[
        "work",
        "public"
    ],
    "wof:name":"Eurovia Centre Loire",
    "wof:placetype":"venue"
},
  "geometry": {"coordinates":[0.237335,47.160206],"type":"Point"}
}