{
  "type": "Feature",
  "properties": {
    "addr:full":"19, Rue Albert Einstein - Centre Entreprise 32, 93591 Le Blanc Mesnil C\u00e9dex Alb\u00e9 Alsace 67220",
    "addr:housenumber":"19;32",
    "addr:postcode":"93591;67220",
    "addr:street":"Rue Albert Einstein;Entreprise",
    "iso:country":"FR",
    "sg:address":"19, Rue Albert Einstein - Centre Entreprise 32, 93591 Le Blanc Mesnil C\u00e9dex",
    "sg:city":"Alb\u00e9",
    "sg:orig_category":"Non-Classified Establishments",
    "sg:phone":"+33 1 48 67 07 65",
    "sg:postcode":"67220",
    "sg:province":"Alsace",
    "wof:name":"Ile De France S.a.r.l.",
    "wof:placetype":"venue"
},
  "geometry": {"coordinates":[2.46049,48.93832],"type":"Point"}
}