{
  "type": "Feature",
  "properties": {
    "addr:full":"67, Rue Jacquard - ZI, 77400 Lagny sur Marne Ile de France",
    "addr:housenumber":"67",
    "addr:postcode":"77400",
    "addr:street":"Rue Jacquard Zi",
    "iso:country":"FR",
    "sg:address":"67, Rue Jacquard - ZI, 77400 Lagny sur Marne",
    "sg:orig_category":"Unclassifiable Establishments",
    "sg:phone":"+33 1 64 30 09 10",
    "sg:province":"Ile de France",
    "wof:name":"E.m.a. S.a. - Europ\u00e9enne De Manutention Et D'automatismes",
    "wof:placetype":"venue"
},
  "geometry": {"coordinates":[2.701485,48.87775],"type":"Point"}
}