{
  "type": "Feature",
  "properties": {
    "iso:country":"FR",
    "sg:address":"3 pl du Grand Martroy; Pontoise; 95303",
    "sg:classifiers":[
        {
            "category":"Banks & Credit Unions",
            "subcategory":"Bank",
            "type":"Services"
        }
    ],
    "sg:phone":"+33 30323500",
    "sg:province":"Lorraine",
    "wof:name":"Cr\u00e9dit Industrie Et, Commercial De Paris",
    "wof:placetype":"venue"
},
  "geometry": {"coordinates":[2.100678,49.050671],"type":"Point"}
}