{
  "type": "Feature",
  "properties": {
    "addr:full":"37 Avenue Carnot 77140 St Pierre Les Nemours Ile de France 77140",
    "addr:housenumber":"37",
    "addr:postcode":"77140;77140",
    "addr:street":"Avenue Carnot;St Pierre Les Nemours Ile De France",
    "iso:country":"FR",
    "sg:address":"37 Avenue Carnot 77140 St Pierre Les Nemours",
    "sg:classifiers":[
        {
            "category":"Home & Garden",
            "subcategory":"Furniture",
            "type":"Retail Goods"
        }
    ],
    "sg:phone":"+33 1 64 29 11 84",
    "sg:postcode":"77140",
    "sg:province":"Ile de France",
    "sg:tags":[
        "household",
        "wood"
    ],
    "wof:name":"Hbm Mobilier Rotin Sarl",
    "wof:placetype":"venue"
},
  "geometry": {"coordinates":[2.684743,48.273285],"type":"Point"}
}