{
  "type": "Feature",
  "properties": {
    "addr:full":"Za de l'Aigue 69780 St Pierre De Chandieu Rhone-Alpes 69780",
    "addr:postcode":"69780;69780",
    "addr:street":"Za De L'Aigue;Rhone-Alpes",
    "iso:country":"FR",
    "sg:address":"Za de l'Aigue 69780 St Pierre De Chandieu",
    "sg:classifiers":[
        {
            "category":"Utilities",
            "subcategory":"Sewage",
            "type":"Services"
        }
    ],
    "sg:phone":"+33 4 78 40 20 82",
    "sg:postcode":"69780",
    "sg:province":"Rhone-Alpes",
    "sg:tags":[
        "water",
        "conditioning",
        "treatment"
    ],
    "wof:name":"Ste Fr D'etudes & De Commercialisation S.a.r.l.",
    "wof:placetype":"venue"
},
  "geometry": {"coordinates":[5.0234,45.646759],"type":"Point"}
}