{
  "type": "Feature",
  "properties": {
    "addr:full":"56, Av. Lamartine, 94170 Le Perreux sur Marne Ile de France",
    "addr:postcode":"94170",
    "addr:street":"56 Av. Lamartine",
    "iso:country":"FR",
    "sg:address":"56, Av. Lamartine, 94170 Le Perreux sur Marne",
    "sg:orig_category":"Unclassifiable Establishments",
    "sg:phone":"+33 1 43 24 42 07",
    "sg:province":"Ile de France",
    "wof:name":"Formfil S.a.r.l.",
    "wof:placetype":"venue"
},
  "geometry": {"coordinates":[2.499827,48.852776],"type":"Point"}
}