{
  "type": "Feature",
  "properties": {
    "addr:full":"75, Rue Rateau - B\u00e2t. C, 93120 La Courneuve Ile de France",
    "addr:housenumber":"75;ba\u0302t c",
    "addr:postcode":"93120",
    "addr:street":"Rue Rateau",
    "iso:country":"FR",
    "sg:address":"75, Rue Rateau - B\u00e2t. C, 93120 La Courneuve",
    "sg:orig_category":"Unclassifiable Establishments",
    "sg:phone":"+33 1 43 11 10 10",
    "sg:province":"Ile de France",
    "wof:name":"Aldes A\u00e9raulique S.a.",
    "wof:placetype":"venue"
},
  "geometry": {"coordinates":[2.406904,48.924931],"type":"Point"}
}