{
  "type": "Feature",
  "properties": {
    "addr:full":"route des Mesniers 16600 MORNAC Poitou-Charentes",
    "addr:postcode":"16600",
    "addr:street":"Route Des Mesniers",
    "iso:country":"FR",
    "sg:address":"route des Mesniers 16600 MORNAC",
    "sg:classifiers":[
        {
            "category":"Manufacturing",
            "subcategory":"Motor Vehicles & Parts",
            "type":"Manufacturing & Wholesale Goods"
        }
    ],
    "sg:phone":"+33 5 45 65 92 18",
    "sg:province":"Poitou-Charentes",
    "sg:tags":[
        "precision",
        "mechanic"
    ],
    "wof:name":"Hydraulique Et Mecanique D'aquitaine S.a.",
    "wof:placetype":"venue"
},
  "geometry": {"coordinates":[0.27298,45.678509],"type":"Point"}
}