{
  "type": "Feature",
  "properties": {
    "addr:full":"Rue des Sources - ZI Crolles Rhone-Alpes 38920",
    "addr:postcode":"38920",
    "addr:street":"Rue Des Sources;Rhone-Alpes",
    "iso:country":"FR",
    "sg:address":"Rue des Sources - ZI",
    "sg:city":"Crolles",
    "sg:orig_category":"Unclassifiable Establishments",
    "sg:phone":"+33 4 76 08 05 42",
    "sg:postcode":"38920",
    "sg:province":"Rhone-Alpes",
    "wof:name":"Caratelli S.a.",
    "wof:placetype":"venue"
},
  "geometry": {"coordinates":[5.884878,45.2854],"type":"Point"}
}