{
  "type": "Feature",
  "properties": {
    "iso:country":"FR",
    "sg:address":"8 Rue Jean De Guerlins 31104 Toulouse Cedex 1",
    "sg:classifiers":[
        {
            "category":"Shopping",
            "type":"Retail Goods"
        }
    ],
    "sg:phone":"+33 5 61 41 25 05",
    "sg:province":"Bretagne",
    "sg:tags":[
        "metallurgy",
        "finished",
        "-",
        "metalworking",
        "metallic"
    ],
    "wof:name":"Ets Romain Chelle Sarl",
    "wof:placetype":"venue"
},
  "geometry": {"coordinates":[1.393943,43.54192],"type":"Point"}
}