{
  "type": "Feature",
  "properties": {
    "iso:country":"FR",
    "sg:address":"176 rue Gustave Eiffel 30000 Nimes",
    "sg:classifiers":[
        {
            "category":"Health Services",
            "subcategory":"Medical Lab",
            "type":"Services"
        }
    ],
    "sg:phone":"+33 4 66 28 06 85",
    "sg:postcode":"30000",
    "sg:province":"Languedoc-Roussillon",
    "sg:tags":[
        "implant"
    ],
    "wof:name":"Transyst\u00e8me S.a.",
    "wof:placetype":"venue"
},
  "geometry": {"coordinates":[4.418386,43.834515],"type":"Point"}
}