{
  "type": "Feature",
  "properties": {
    "iso:country":"FR",
    "sg:address":"Les Beaubutaines 58200 Cosne Cours Sur Loire",
    "sg:city":"Cosne-Cours-sur-Loire",
    "sg:classifiers":[
        {
            "category":"Home & Garden",
            "subcategory":"Furniture",
            "type":"Retail Goods"
        }
    ],
    "sg:phone":"+33 3 86 28 14 05",
    "sg:postcode":"58200",
    "sg:province":"Bourgogne",
    "sg:tags":[
        "wood"
    ],
    "wof:name":"Etablissements Bonnet",
    "wof:placetype":"venue"
},
  "geometry": {"coordinates":[2.92471,47.385506],"type":"Point"}
}