{
  "type": "Feature",
  "properties": {
    "iso:country":"FR",
    "sg:address":"56 route du Moulin 76840 St Martin de Boscherville",
    "sg:classifiers":[
        {
            "category":"Utilities",
            "subcategory":"Cable",
            "type":"Services"
        }
    ],
    "sg:phone":"+33 2 35 32 01 54",
    "sg:postcode":"76840",
    "sg:province":"Haute Normandie",
    "sg:tags":[
        "trailer"
    ],
    "wof:name":"Sofemi",
    "wof:placetype":"venue"
},
  "geometry": {"coordinates":[0.959663,49.417702],"type":"Point"}
}