{
  "type": "Feature",
  "properties": {
    "iso:country":"FR",
    "sg:address":"18/20 Place G\u00e9n\u00e9ral De Gaulle",
    "sg:city":"R\u00e9malard",
    "sg:classifiers":[
        {
            "category":"Banks & Credit Unions",
            "subcategory":"Financial Services",
            "type":"Services"
        }
    ],
    "sg:phone":"+33 2 33 73 71 33",
    "sg:postcode":"61110",
    "sg:province":"Basse Normandie",
    "sg:tags":[
        "banking",
        "finance",
        "insurance"
    ],
    "wof:name":"Scp Gerondeau Bouvier Louchard",
    "wof:placetype":"venue"
},
  "geometry": {"coordinates":[0.773082,48.428989],"type":"Point"}
}