{
  "type": "Feature",
  "properties": {
    "addr:full":"16 Avenue De Saint Antoine 13015 Marseille Poitou-Charentes",
    "addr:housenumber":"16",
    "addr:postcode":"13015",
    "addr:street":"Avenue De Saint Antoine",
    "iso:country":"FR",
    "sg:address":"16 Avenue De Saint Antoine 13015 Marseille",
    "sg:classifiers":[
        {
            "category":"Shopping",
            "subcategory":"Hobbies, Toys, & Games",
            "type":"Retail Goods"
        }
    ],
    "sg:phone":"+33 4 91 03 97 00",
    "sg:province":"Poitou-Charentes",
    "sg:tags":[
        "product",
        "miscellaneous",
        "entertainment"
    ],
    "wof:name":"Lecourtier Drapeaux",
    "wof:placetype":"venue"
},
  "geometry": {"coordinates":[5.356884,43.366447],"type":"Point"}
}