{
  "type": "Feature",
  "properties": {
    "iso:country":"FR",
    "sg:address":"Chem Jaure Guiborda 64200 Arcangues",
    "sg:city":"Arcangues",
    "sg:classifiers":[
        {
            "category":"Shopping",
            "subcategory":"Luggage & Leather Goods",
            "type":"Retail Goods"
        }
    ],
    "sg:phone":"+33 5 59 43 01 90",
    "sg:postcode":"64200",
    "sg:province":"Aquitaine",
    "sg:tags":[
        "shoe"
    ],
    "wof:name":"Viva Sa",
    "wof:placetype":"venue"
},
  "geometry": {"coordinates":[-1.52229,43.436646],"type":"Point"}
}