{
  "type": "Feature",
  "properties": {
    "iso:country":"FR",
    "sg:address":"68 Rue Reaumur 75003 Paris",
    "sg:classifiers":[
        {
            "category":"Shopping",
            "subcategory":"Clothing, Apparel, & Fashions",
            "type":"Retail Goods"
        }
    ],
    "sg:phone":"+33 1 44 54 89 00",
    "sg:postcode":"75003",
    "sg:province":"Ile de France",
    "sg:tags":[
        "textile",
        "clothing",
        "clothes"
    ],
    "wof:name":"Almach",
    "wof:placetype":"venue"
},
  "geometry": {"coordinates":[2.353123,48.866234],"type":"Point"}
}