{
  "type": "Feature",
  "properties": {
    "addr:full":"Domaine du Petit Arbois Aix en Provence Provence-Alpes-C\u00f4te d'Azur 13100",
    "addr:postcode":"13100",
    "addr:street":"Domaine Du Petit Arbois Aix;Provence",
    "iso:country":"FR",
    "sg:address":"Domaine du Petit Arbois",
    "sg:city":"Aix en Provence",
    "sg:orig_category":"Unclassifiable Establishments",
    "sg:phone":"+33 4 42 97 14 80",
    "sg:postcode":"13100",
    "sg:province":"Provence-Alpes-C\u00f4te d'Azur",
    "wof:name":"Ineris Sud Est E.p.i.c.",
    "wof:placetype":"venue"
},
  "geometry": {"coordinates":[5.45948,43.528172],"type":"Point"}
}