{
  "type": "Feature",
  "properties": {
    "iso:country":"FR",
    "sg:address":"Rue Albert Einstein Zi 02200 Villeneuve St Germain",
    "sg:classifiers":[
        {
            "category":"Shopping",
            "type":"Retail Goods"
        }
    ],
    "sg:phone":"+33 3 23 75 34 34",
    "sg:postcode":"02200",
    "sg:province":"Picardie",
    "sg:tags":[
        "metallurgy",
        "finished",
        "-",
        "metalworking",
        "metallic"
    ],
    "wof:name":"Axinox",
    "wof:placetype":"venue"
},
  "geometry": {"coordinates":[3.370755,49.368877],"type":"Point"}
}