{
  "type": "Feature",
  "properties": {
    "iso:country":"FR",
    "sg:address":"54 bis, Rue d'Alsace Lorraine, 31000 Toulouse",
    "sg:orig_category":"Unclassifiable Establishments",
    "sg:phone":"+33 5 61 21 15 72",
    "sg:province":"Midi Pyr\u00e9n\u00e9es",
    "wof:name":"Editions Bucerep S.a.r.l.",
    "wof:placetype":"venue"
},
  "geometry": {"coordinates":[1.43483,43.604069],"type":"Point"}
}