{
  "type": "Feature",
  "properties": {
    "iso:country":"FR",
    "sg:address":"16, Rue du Moulin des Bruy\u00e8res, 92400 Courbevoie",
    "sg:orig_category":"Unclassifiable Establishments",
    "sg:phone":"+33 1 46 67 51 00",
    "sg:province":"Ile de France",
    "wof:name":"Dotcom S.a.",
    "wof:placetype":"venue"
},
  "geometry": {"coordinates":[2.261282,48.903824],"type":"Point"}
}