{
  "type": "Feature",
  "properties": {
    "iso:country":"FR",
    "sg:address":"10 avenue Descartes 92350 Le Plessis Robinson",
    "sg:classifiers":[
        {
            "category":"Organizations",
            "subcategory":"Professional Association",
            "type":"Services"
        }
    ],
    "sg:phone":"+33 1 46 01 05 06",
    "sg:postcode":"92350",
    "sg:province":"Ile de France",
    "sg:tags":[
        "system",
        "bar-code"
    ],
    "wof:name":"Tx Com S.a.",
    "wof:placetype":"venue"
},
  "geometry": {"coordinates":[2.244808,48.777134],"type":"Point"}
}