{
  "type": "Feature",
  "properties": {
    "addr:full":"3 B Rue Des Cuirassiers 69003 Lyon Rhone-Alpes 69003",
    "addr:housenumber":"3 b",
    "addr:postcode":"69003;69003",
    "addr:street":"Rue Des Cuirassiers",
    "iso:country":"FR",
    "sg:address":"3 B Rue Des Cuirassiers 69003 Lyon",
    "sg:classifiers":[
        {
            "category":"Utilities",
            "subcategory":"Electric",
            "type":"Services"
        }
    ],
    "sg:phone":"+33 4 78 71 33 33",
    "sg:postcode":"69003",
    "sg:province":"Rhone-Alpes",
    "sg:tags":[
        "electricity",
        "raw",
        "energy",
        "material"
    ],
    "wof:name":"Electricite De France (edf)",
    "wof:placetype":"venue"
},
  "geometry": {"coordinates":[4.856158,45.757275],"type":"Point"}
}