{
  "type": "Feature",
  "properties": {
    "iso:country":"FR",
    "sg:address":"430, Rue Emile Zola, 73490 La Ravoire",
    "sg:orig_category":"Non-Classified Establishments",
    "sg:phone":"+33 4 79 72 65 62",
    "sg:province":"Rhone-Alpes",
    "wof:name":"Spi Energie S.a.",
    "wof:placetype":"venue"
},
  "geometry": {"coordinates":[5.970999,45.558243],"type":"Point"}
}