{
  "type": "Feature",
  "properties": {
    "iso:country":"FR",
    "sg:address":"15, Place du Bel Ebat, 78280 Guyancourt",
    "sg:orig_category":"Unclassifiable Establishments",
    "sg:phone":"+33 1 39 44 99 47",
    "sg:province":"Ile de France",
    "wof:name":"Cedefi",
    "wof:placetype":"venue"
},
  "geometry": {"coordinates":[2.06953,48.770302],"type":"Point"}
}