{
  "type": "Feature",
  "properties": {
    "addr:full":"148, Rue de Boisdenier, 37000 Tours Tours Centre 37000",
    "addr:housenumber":"148",
    "addr:postcode":"37000;37000",
    "addr:street":"Rue De Boisdenier",
    "iso:country":"FR",
    "sg:address":"148, Rue de Boisdenier, 37000 Tours",
    "sg:city":"Tours",
    "sg:orig_category":"Non-Classified Establishments",
    "sg:phone":"+33 2 47 05 34 96",
    "sg:postcode":"37000",
    "sg:province":"Centre",
    "wof:name":"L.t.d S.a.r.l. - Logiciel Et Technologie Diffusion",
    "wof:placetype":"venue"
},
  "geometry": {"coordinates":[0.680973,47.384296],"type":"Point"}
}