{
  "type": "Feature",
  "properties": {
    "iso:country":"FR",
    "sg:address":"2474 Rn7 Le Logis Bonneau 06270 Villeneuve Loubet",
    "sg:city":"Vill\u00e9",
    "sg:classifiers":[
        {
            "category":"Manufacturing",
            "subcategory":"Tools & Machinery",
            "type":"Manufacturing & Wholesale Goods"
        }
    ],
    "sg:phone":"+33 4 92 02 47 70",
    "sg:postcode":"67220",
    "sg:province":"Alsace",
    "sg:tags":[
        "equipment",
        "measurement",
        "-",
        "precision",
        "instrument"
    ],
    "wof:name":"Siemens",
    "wof:placetype":"venue"
},
  "geometry": {"coordinates":[7.120035,43.646286],"type":"Point"}
}