{
  "type": "Feature",
  "properties": {
    "addr:full":"8 Charloun Rieu; Aix en Provence Nord Pas-de-Calais",
    "addr:housenumber":"8",
    "addr:street":"Charloun Rieu Aix",
    "iso:country":"FR",
    "sg:address":"8",
    "sg:city":"Charloun Rieu; Aix en Provence",
    "sg:classifiers":[
        {
            "category":"Banks & Credit Unions",
            "subcategory":"Bank",
            "type":"Services"
        }
    ],
    "sg:phone":"+33 3342591100",
    "sg:province":"Nord Pas-de-Calais",
    "wof:name":"Cr\u00e9dit Lyonnais, Valcros",
    "wof:placetype":"venue"
},
  "geometry": {"coordinates":[5.414914,43.528996],"type":"Point"}
}