{
  "type": "Feature",
  "properties": {
    "iso:country":"FR",
    "sg:address":"100, Rte de la Loire - Le Guineau , 44450 La Chapelle Basse Mer",
    "sg:orig_category":"Unclassifiable Establishments",
    "sg:phone":"+33 2 40 06 33 66",
    "sg:province":"Pays de Loire",
    "wof:name":"P\u00e9pini\u00e8res Ripoche S.c.a",
    "wof:placetype":"venue"
},
  "geometry": {"coordinates":[-1.432701,47.220284],"type":"Point"}
}