{
  "type": "Feature",
  "properties": {
    "iso:country":"FR",
    "sg:address":"RN 10 - Immeuble Seine B\u00e2t. A5",
    "sg:city":"Trappes",
    "sg:orig_category":"Unclassifiable Establishments",
    "sg:phone":"+33 1 30 16 20 60",
    "sg:postcode":"78190",
    "sg:province":"Ile de France",
    "wof:name":"Orbisph\u00e8re Laboratories France S.a.r.l.",
    "wof:placetype":"venue"
},
  "geometry": {"coordinates":[1.999285,48.774651],"type":"Point"}
}