{
  "type": "Feature",
  "properties": {
    "iso:country":"FR",
    "sg:address":"21 Avenue De L'Agriculture 63100 Clermont Ferrand",
    "sg:city":"Clermont-Ferrand",
    "sg:classifiers":[
        {
            "category":"Wholesale",
            "subcategory":"Farm Supplies",
            "type":"Manufacturing & Wholesale Goods"
        }
    ],
    "sg:phone":"+33 4 73 91 93 51",
    "sg:postcode":"63100",
    "sg:province":"Auvergne",
    "sg:tags":[
        "-",
        "machine",
        "equipment",
        "engineering",
        "machinery",
        "mechanical",
        "agriculture"
    ],
    "wof:name":"Beal Yvan Et Cie",
    "wof:placetype":"venue"
},
  "geometry": {"coordinates":[3.117388,45.779789],"type":"Point"}
}