{
  "type": "Feature",
  "properties": {
    "iso:country":"FR",
    "sg:address":"20 Av Verdun 88160 Le Thillot",
    "sg:classifiers":[
        {
            "category":"Autos & Motor Vehicles",
            "subcategory":"Automobile Sales",
            "type":"Retail Goods"
        }
    ],
    "sg:phone":"+33 3 29 25 01 17",
    "sg:postcode":"88160",
    "sg:province":"Lorraine",
    "sg:tags":[
        "equipment",
        "motor-cars",
        "transport"
    ],
    "wof:name":"Garage Du Centre Sa",
    "wof:placetype":"venue"
},
  "geometry": {"coordinates":[6.76085,47.881863],"type":"Point"}
}