{
  "type": "Feature",
  "properties": {
    "iso:country":"FR",
    "sg:address":"Le Bois Bodin 79390 Th\u00e9nezay",
    "sg:classifiers":[
        {
            "category":"Professional",
            "subcategory":"Engineering",
            "type":"Services"
        }
    ],
    "sg:phone":"+33 5 49 63 06 46",
    "sg:postcode":"79390",
    "sg:province":"Poitou-Charentes",
    "sg:tags":[
        "machine",
        "-",
        "mechanical"
    ],
    "wof:name":"Socobois Sarl",
    "wof:placetype":"venue"
},
  "geometry": {"coordinates":[-0.032529,46.714069],"type":"Point"}
}