{
  "type": "Feature",
  "properties": {
    "iso:country":"FR",
    "sg:address":"5-16 Av L\u00e9on Blum 59370 Mons En Baroeul",
    "sg:classifiers":[
        {
            "category":"Manufacturing",
            "subcategory":"Printing",
            "type":"Manufacturing & Wholesale Goods"
        }
    ],
    "sg:phone":"+33 3 20 61 98 44",
    "sg:province":"Nord Pas-de-Calais",
    "sg:tags":[
        "publishing"
    ],
    "wof:name":"Imprimerie Monsoise Sa",
    "wof:placetype":"venue"
},
  "geometry": {"coordinates":[3.10574,50.650059],"type":"Point"}
}