{
  "type": "Feature",
  "properties": {
    "addr:full":"chemin de la Cartairade 34830 Jacou Languedoc-Roussillon 34830",
    "addr:postcode":"34830;34830",
    "addr:street":"Chemin De La Cartairade",
    "iso:country":"FR",
    "sg:address":"chemin de la Cartairade 34830 Jacou",
    "sg:classifiers":[
        {
            "category":"Banks & Credit Unions",
            "subcategory":"Investment Brokerage",
            "type":"Services"
        }
    ],
    "sg:phone":"+33 4 67 55 90 60",
    "sg:postcode":"34830",
    "sg:province":"Languedoc-Roussillon",
    "sg:tags":[
        "curtain",
        "rod",
        "accessory"
    ],
    "wof:name":"Ste Rene Villeminot S.a.",
    "wof:placetype":"venue"
},
  "geometry": {"coordinates":[3.906521,43.659168],"type":"Point"}
}