{
  "type": "Feature",
  "properties": {
    "addr:full":"R Des Erables Zi 61130 Belleme Bell\u00eame Basse Normandie 61130",
    "addr:postcode":"61130;61130",
    "addr:street":"Zi",
    "iso:country":"FR",
    "sg:address":"R Des Erables Zi 61130 Belleme",
    "sg:city":"Bell\u00eame",
    "sg:classifiers":[
        {
            "category":"Manufacturing",
            "subcategory":"Printing",
            "type":"Manufacturing & Wholesale Goods"
        }
    ],
    "sg:phone":"+33 2 33 83 57 73",
    "sg:postcode":"61130",
    "sg:province":"Basse Normandie",
    "sg:tags":[
        "publishing"
    ],
    "wof:name":"At\u00c9lier De Fa\u00c7onnage Du Centre Ouest (afco Fa\u00c7onnage)",
    "wof:placetype":"venue"
},
  "geometry": {"coordinates":[0.544102,48.268017],"type":"Point"}
}