{
  "type": "Feature",
  "properties": {
    "iso:country":"FR",
    "sg:address":"Quai Du Rhone 01700 Miribel",
    "sg:classifiers":[
        {
            "category":"Manufacturing",
            "subcategory":"Metals",
            "type":"Manufacturing & Wholesale Goods"
        }
    ],
    "sg:phone":"+33 4 78 55 09 93",
    "sg:postcode":"01700",
    "sg:province":"Rhone-Alpes",
    "sg:tags":[
        "metallurgy",
        "metalworking",
        "processing"
    ],
    "wof:name":"Cmp Sarl",
    "wof:placetype":"venue"
},
  "geometry": {"coordinates":[4.96326,45.822224],"type":"Point"}
}