{
  "type": "Feature",
  "properties": {
    "addr:full":"40, Bd de la Beaujoire, 44300 Nantes Pays de Loire",
    "addr:housenumber":"40",
    "addr:postcode":"44300",
    "addr:street":"Bd De La Beaujoire",
    "iso:country":"FR",
    "sg:address":"40, Bd de la Beaujoire, 44300 Nantes",
    "sg:orig_category":"Non-Classified Establishments",
    "sg:phone":"+33 2 40 30 31 01",
    "sg:province":"Pays de Loire",
    "wof:name":"Sofi S.a.r.l.",
    "wof:placetype":"venue"
},
  "geometry": {"coordinates":[-1.520751,47.258907],"type":"Point"}
}