{
  "type": "Feature",
  "properties": {
    "addr:full":"12 R Marie Curie 78310 Maurepas Ile de France 78310",
    "addr:housenumber":"12",
    "addr:postcode":"78310;ile;78310",
    "addr:street":"R Marie Curie;France",
    "iso:country":"FR",
    "sg:address":"12 R Marie Curie 78310 Maurepas",
    "sg:classifiers":[
        {
            "category":"Professional",
            "subcategory":"Engineering",
            "type":"Services"
        }
    ],
    "sg:phone":"+33 1 34 82 18 00",
    "sg:postcode":"78310",
    "sg:province":"Ile de France",
    "sg:tags":[
        "machine",
        "-",
        "mechanical"
    ],
    "wof:name":"Milacron France Sas Division Ferromatik Milacron",
    "wof:placetype":"venue"
},
  "geometry": {"coordinates":[1.93184,48.759624],"type":"Point"}
}