{
  "type": "Feature",
  "properties": {
    "addr:full":"Rue Des Mongazons Zac Des Brosses 78200 Magnanville Ile de France 78200",
    "addr:postcode":"78200;ile;78200",
    "addr:street":"Rue Des Mongazons Zac Des Brosses;France",
    "iso:country":"FR",
    "sg:address":"Rue Des Mongazons Zac Des Brosses 78200 Magnanville",
    "sg:classifiers":[
        {
            "category":"Government",
            "subcategory":"Fire Station",
            "type":"Public Place"
        }
    ],
    "sg:phone":"+33 1 30 92 61 77",
    "sg:postcode":"78200",
    "sg:province":"Ile de France",
    "sg:tags":[
        "electric",
        "electricity",
        "component",
        "equipment",
        "lighting",
        "electrical",
        "electronic"
    ],
    "wof:name":"Cefb",
    "wof:placetype":"venue"
},
  "geometry": {"coordinates":[1.714715,48.989491],"type":"Point"}
}