{
  "type": "Feature",
  "properties": {
    "iso:country":"FR",
    "sg:address":"Vigouse 82100 Castelsarrasin",
    "sg:orig_category":"Fruit, Preserved",
    "sg:phone":"+33 5 63 32 31 26",
    "sg:postcode":"82100",
    "sg:province":"Midi Pyr\u00e9n\u00e9es",
    "wof:name":"Prestifruit S.a.r.l.",
    "wof:placetype":"venue"
},
  "geometry": {"coordinates":[1.109529,43.941746],"type":"Point"}
}