{
  "type": "Feature",
  "properties": {
    "iso:country":"FR",
    "sg:address":"4, Rue du Pr\u00e9 Chapelon - ZA la Bargette, 42270 Saint Priest en Jarez",
    "sg:orig_category":"Unclassifiable Establishments",
    "sg:phone":"+33 4 77 91 12 00",
    "sg:postcode":"42270",
    "sg:province":"Rhone-Alpes",
    "wof:name":"Codep S.a.",
    "wof:placetype":"venue"
},
  "geometry": {"coordinates":[4.379601,45.473232],"type":"Point"}
}