{
  "type": "Feature",
  "properties": {
    "addr:full":"12, Bd John Kennedy, 25000 Besan\u00e7on Franche Comt\u00e9",
    "addr:housenumber":"12",
    "addr:postcode":"25000",
    "addr:street":"Bd John Kennedy;Franche Comte\u0301",
    "iso:country":"FR",
    "sg:address":"12, Bd John Kennedy, 25000 Besan\u00e7on",
    "sg:orig_category":"Unclassifiable Establishments",
    "sg:phone":"+33 3 81 40 22 00",
    "sg:province":"Franche Comt\u00e9",
    "wof:name":"Aug\u00e9 D\u00e9coupage S.a.",
    "wof:placetype":"venue"
},
  "geometry": {"coordinates":[5.988332,47.238552],"type":"Point"}
}