{
  "type": "Feature",
  "properties": {
    "iso:country":"FR",
    "sg:address":"3, Rue de Fionie, 44240 La Chapelle sur Erdre",
    "sg:orig_category":"Non-Classified Establishments",
    "sg:phone":"+33 2 40 72 92 00",
    "sg:province":"Pays de Loire",
    "wof:name":"Jet Ouest S.a.r.l.",
    "wof:placetype":"venue"
},
  "geometry": {"coordinates":[-1.547399,47.282082],"type":"Point"}
}