{
  "type": "Feature",
  "properties": {
    "iso:country":"FR",
    "sg:address":"Zi Mezau Bert 35133 Javon\u00e9",
    "sg:city":"Beauc\u00e9",
    "sg:classifiers":[
        {
            "category":"Professional",
            "subcategory":"Engineering",
            "type":"Services"
        }
    ],
    "sg:phone":"+33 2 99 99 80 03",
    "sg:postcode":"35133",
    "sg:province":"Bretagne",
    "sg:tags":[
        "machine",
        "-",
        "mechanical"
    ],
    "wof:name":"H2m Technologies Sarl",
    "wof:placetype":"venue"
},
  "geometry": {"coordinates":[-1.117809,48.283527],"type":"Point"}
}