{
  "type": "Feature",
  "properties": {
    "addr:full":"Deyrier 74350 Cruseilles Rhone-Alpes",
    "addr:postcode":"74350",
    "addr:street":"Deyrier",
    "iso:country":"FR",
    "sg:address":"Deyrier 74350 Cruseilles",
    "sg:orig_category":"Unclassifiable Establishments",
    "sg:phone":"+33 4 50 44 26 27",
    "sg:province":"Rhone-Alpes",
    "wof:name":"Eusebio S.a.r.l.",
    "wof:placetype":"venue"
},
  "geometry": {"coordinates":[6.112903,46.024216],"type":"Point"}
}