{
  "type": "Feature",
  "properties": {
    "iso:country":"FR",
    "sg:address":"59 Rte Vers Le Nant Les Bossons 74400 Chamonix Mont Blanc",
    "sg:classifiers":[
        {
            "category":"Travel",
            "subcategory":"Hotels & Motels",
            "type":"Entertainment"
        }
    ],
    "sg:phone":"+33 4 50 53 26 22",
    "sg:postcode":"74400",
    "sg:province":"Rhone-Alpes",
    "sg:tags":[
        "hotels",
        "business",
        "restaurant"
    ],
    "wof:name":"Novotel Sa",
    "wof:placetype":"venue"
},
  "geometry": {"coordinates":[6.871972,45.92485],"type":"Point"}
}