{
  "type": "Feature",
  "properties": {
    "addr:full":"Centre d'Affaires Alis\u00e9 Cesson S\u00e9vign\u00e9 Champagne 35070",
    "addr:postcode":"35070",
    "addr:street":"Champagne",
    "iso:country":"FR",
    "sg:address":"Centre d'Affaires Alis\u00e9",
    "sg:city":"Cesson S\u00e9vign\u00e9",
    "sg:orig_category":"Non-Classified Establishments",
    "sg:phone":"+33 2 99 83 05 64",
    "sg:postcode":"35070",
    "sg:province":"Champagne",
    "wof:name":"S.g.i.",
    "wof:placetype":"venue"
},
  "geometry": {"coordinates":[-87.38722199999999,44.726311],"type":"Point"}
}