{
  "type": "Feature",
  "properties": {
    "addr:full":"B.P. 13 Yenne^^Chambuet 73170 Yenne Rhone-Alpes 73170",
    "addr:postcode":"73170;73170",
    "addr:street":"B.P. 13 Yenne^^Chambuet",
    "iso:country":"FR",
    "sg:address":"B.P. 13",
    "sg:city":"Yenne^^Chambuet 73170 Yenne",
    "sg:orig_category":"Non-Classified Establishments",
    "sg:phone":"+33 4 79 36 71 57",
    "sg:postcode":"73170",
    "sg:province":"Rhone-Alpes",
    "wof:name":"Coop\u00e9rative Laiti\u00e8re De Yenne",
    "wof:placetype":"venue"
},
  "geometry": {"coordinates":[5.74203,45.62989],"type":"Point"}
}