{
  "type": "Feature",
  "properties": {
    "iso:country":"FR",
    "sg:address":"17, Rue de l'Industrie, 42390 Villars",
    "sg:orig_category":"Non-Classified Establishments",
    "sg:phone":"+33 4 77 74 36 23",
    "sg:province":"Rhone-Alpes",
    "wof:name":"Segm S.a.r.l.",
    "wof:placetype":"venue"
},
  "geometry": {"coordinates":[4.357319,45.471073],"type":"Point"}
}