{
  "type": "Feature",
  "properties": {
    "addr:full":"10, Rue de Rome, 75008 Paris Ile de France",
    "addr:housenumber":"10",
    "addr:postcode":"75008",
    "addr:street":"Rue De Rome",
    "iso:country":"FR",
    "sg:address":"10, Rue de Rome, 75008 Paris",
    "sg:orig_category":"Non-Classified Establishments",
    "sg:phone":"+33 1 44 70 61 61",
    "sg:province":"Ile de France",
    "wof:name":"Prodest S.a.",
    "wof:placetype":"venue"
},
  "geometry": {"coordinates":[2.325197,48.874706],"type":"Point"}
}