{
  "type": "Feature",
  "properties": {
    "addr:full":"8 Rue Du Bois Cerdon Zi 94460 Valenton Ile de France 94460",
    "addr:housenumber":"8",
    "addr:postcode":"94460;ile;94460",
    "addr:street":"Rue Du Bois;Zi;France",
    "iso:country":"FR",
    "sg:address":"8 Rue Du Bois Cerdon Zi 94460 Valenton",
    "sg:classifiers":[
        {
            "category":"Food & Beverages",
            "subcategory":"Groceries & Convenience Stores",
            "type":"Retail Goods"
        }
    ],
    "sg:phone":"+33 1 43 82 80 80",
    "sg:postcode":"94460",
    "sg:province":"Ile de France",
    "sg:tags":[
        "product",
        "related"
    ],
    "wof:name":"Multipond",
    "wof:placetype":"venue"
},
  "geometry": {"coordinates":[2.47036,48.744244],"type":"Point"}
}