{
  "type": "Feature",
  "properties": {
    "iso:country":"FR",
    "sg:address":"173 rue L\u00e9on Blum 69100 Villeurbanne",
    "sg:classifiers":[
        {
            "category":"Wholesale",
            "subcategory":"Painting Supplies",
            "type":"Manufacturing & Wholesale Goods"
        }
    ],
    "sg:phone":"+33 4 72 35 13 35",
    "sg:postcode":"69100",
    "sg:province":"Rhone-Alpes",
    "sg:tags":[
        "interior",
        "decoration"
    ],
    "wof:name":"Inov S.a.",
    "wof:placetype":"venue"
},
  "geometry": {"coordinates":[4.906659,45.760925],"type":"Point"}
}