{
  "type": "Feature",
  "properties": {
    "addr:full":"1 Ld Langevin 19100 Brive La Gaillarde Limousin 19100",
    "addr:housenumber":"1",
    "addr:postcode":"19100;19100",
    "addr:street":"Ld Langevin",
    "iso:country":"FR",
    "sg:address":"1 Ld Langevin 19100 Brive La Gaillarde",
    "sg:classifiers":[
        {
            "category":"Professional",
            "subcategory":"Engineering",
            "type":"Services"
        }
    ],
    "sg:phone":"+33 5 55 92 75 00",
    "sg:postcode":"19100",
    "sg:province":"Limousin",
    "sg:tags":[
        "machine",
        "-",
        "mechanical"
    ],
    "wof:name":"Mecabrive",
    "wof:placetype":"venue"
},
  "geometry": {"coordinates":[1.558088,45.154659],"type":"Point"}
}