{
  "type": "Feature",
  "properties": {
    "iso:country":"FR",
    "sg:address":"11 impasse du Chemin-de-Fer 88400 GERARDMER",
    "sg:orig_category":"Flexible Wooden Slats For Slatted Frames",
    "sg:phone":"+33 3 29 60 00 04",
    "sg:postcode":"88400",
    "sg:province":"Lorraine",
    "wof:name":"Franslatte S.a.r.l.",
    "wof:placetype":"venue"
},
  "geometry": {"coordinates":[6.882905,48.077801],"type":"Point"}
}