{
  "type": "Feature",
  "properties": {
    "addr:full":"42, Ruelle des Plantes, 95280 Jouy le Moutier Ile de France",
    "addr:housenumber":"42",
    "addr:postcode":"95280",
    "addr:street":"Ruelle Des Plantes;Moutier Ile De France",
    "iso:country":"FR",
    "sg:address":"42, Ruelle des Plantes, 95280 Jouy le Moutier",
    "sg:orig_category":"Unclassifiable Establishments",
    "sg:phone":"+33 1 30 17 31 90",
    "sg:province":"Ile de France",
    "wof:name":"Sogezy-zivy Contr\u00f4le S.a.r.l.",
    "wof:placetype":"venue"
},
  "geometry": {"coordinates":[2.057601,49.00946],"type":"Point"}
}