{
  "type": "Feature",
  "properties": {
    "iso:country":"FR",
    "sg:address":"Rue Arthur Enaud 22601 LOUDEAC CEDEX",
    "sg:city":"Loud\u00e9ac",
    "sg:classifiers":[
        {
            "category":"Food & Beverages",
            "subcategory":"Bakery",
            "type":"Retail Goods"
        }
    ],
    "sg:phone":"+33 2 96 66 17 17",
    "sg:postcode":"22600",
    "sg:province":"Bretagne",
    "sg:tags":[
        "biscuit"
    ],
    "wof:name":"Patisseries Gourmandes Sa",
    "wof:placetype":"venue"
},
  "geometry": {"coordinates":[-2.755631,48.158802],"type":"Point"}
}