{
  "type": "Feature",
  "properties": {
    "addr:full":"r Henri Moissam 39800 Poligny Franche Comt\u00e9 39800",
    "addr:postcode":"39800;39800",
    "addr:street":"R;Franche Comte\u0301",
    "iso:country":"FR",
    "sg:address":"r Henri Moissam 39800 Poligny",
    "sg:classifiers":[
        {
            "category":"Manufacturing",
            "subcategory":"Metals",
            "type":"Manufacturing & Wholesale Goods"
        }
    ],
    "sg:phone":"+33 3 84 73 74 75",
    "sg:postcode":"39800",
    "sg:province":"Franche Comt\u00e9",
    "sg:tags":[
        "-",
        "machine",
        "equipment",
        "engineering",
        "machinery",
        "mechanical"
    ],
    "wof:name":"Diager (sa)",
    "wof:placetype":"venue"
},
  "geometry": {"coordinates":[5.690433,46.846115],"type":"Point"}
}