{
  "type": "Feature",
  "properties": {
    "addr:full":"38 Pa Du Gard BP 179 62303 Lens Midi Pyr\u00e9n\u00e9es",
    "addr:housenumber":"38;179",
    "addr:postcode":"62303",
    "addr:street":"Pa Du Gard Bp",
    "iso:country":"FR",
    "sg:address":"38 Pa Du Gard BP 179 62303 Lens",
    "sg:classifiers":[
        {
            "category":"Professional",
            "subcategory":"Advertising",
            "type":"Services"
        }
    ],
    "sg:phone":"+33 3 21 70 50 50",
    "sg:province":"Midi Pyr\u00e9n\u00e9es",
    "sg:tags":[
        "communication",
        "medium"
    ],
    "wof:name":"Interstice Sarl",
    "wof:placetype":"venue"
},
  "geometry": {"coordinates":[2.83296,50.42934],"type":"Point"}
}