{
  "type": "Feature",
  "properties": {
    "iso:country":"FR",
    "sg:address":"264, Av. Pierre Mend\u00e8s France, 83500 La Seyne sur Mer",
    "sg:orig_category":"Non-Classified Establishments",
    "sg:phone":"+33 4 94 10 21 02",
    "sg:province":"Aquitaine",
    "wof:name":"C.i.t. S.a.r.l. - Centre Informatique De Traitement",
    "wof:placetype":"venue"
},
  "geometry": {"coordinates":[5.874446,43.109447],"type":"Point"}
}