{
  "type": "Feature",
  "properties": {
    "iso:country":"FR",
    "sg:address":"Zi St Arnoult 28170 Ch\u00e2teauneuf En Thymerais",
    "sg:city":"Ardelles",
    "sg:classifiers":[
        {
            "category":"Health Services",
            "subcategory":"Medical Lab",
            "type":"Services"
        }
    ],
    "sg:phone":"+33 2 37 65 88 00",
    "sg:postcode":"28170",
    "sg:province":"Centre",
    "sg:tags":[
        "chemical",
        "pharmaceutical",
        "pharmacy"
    ],
    "wof:name":"Ethypharm",
    "wof:placetype":"venue"
},
  "geometry": {"coordinates":[1.240185,48.582344],"type":"Point"}
}