{
  "type": "Feature",
  "properties": {
    "iso:country":"FR",
    "sg:address":"32, Chemin de Thalor, 26000 Valence",
    "sg:orig_category":"Non-Classified Establishments",
    "sg:phone":"+33 4 75 78 51 51",
    "sg:postcode":"26000",
    "sg:province":"Rhone-Alpes",
    "wof:name":"Lecl\u00e8re S.a.",
    "wof:placetype":"venue"
},
  "geometry": {"coordinates":[4.889246,44.930458],"type":"Point"}
}