{
  "type": "Feature",
  "properties": {
    "iso:country":"FR",
    "sg:address":"B.P. 119, 22000 Saint Brieuc^^69, Rue Chaptal, 22000 Saint Brieuc",
    "sg:city":"Saint-Brieuc",
    "sg:orig_category":"Non-Classified Establishments",
    "sg:phone":"+33 2 96 68 11 60",
    "sg:postcode":"22000",
    "sg:province":"Bretagne",
    "wof:name":"S.n.c.m.a. S.a.",
    "wof:placetype":"venue"
},
  "geometry": {"coordinates":[-2.763814,48.515701],"type":"Point"}
}