{
  "type": "Feature",
  "properties": {
    "addr:full":"3, Quai Kleber, 67000 Strasbourg Strasbourg Alsace 67000",
    "addr:housenumber":"3",
    "addr:postcode":"67000;67000",
    "addr:street":"Quai Kleber",
    "iso:country":"FR",
    "sg:address":"3, Quai Kleber, 67000 Strasbourg",
    "sg:city":"Strasbourg",
    "sg:orig_category":"Unclassifiable Establishments",
    "sg:phone":"+33 3 88 75 65 55",
    "sg:postcode":"67000",
    "sg:province":"Alsace",
    "wof:name":"Mercuri Urval S.a.",
    "wof:placetype":"venue"
},
  "geometry": {"coordinates":[7.746268,48.582951],"type":"Point"}
}