{
  "type": "Feature",
  "properties": {
    "addr:full":"47 Avenue Georges Mandel Paris Ile de France 75116",
    "addr:housenumber":"47",
    "addr:postcode":"75116",
    "addr:street":"Avenue Georges Mandel",
    "iso:country":"FR",
    "sg:address":"47 Avenue Georges Mandel",
    "sg:city":"Paris",
    "sg:classifiers":[
        {
            "category":"Banks & Credit Unions",
            "subcategory":"Financial Services",
            "type":"Services"
        }
    ],
    "sg:phone":"+33 1 44 05 80 00",
    "sg:postcode":"75116",
    "sg:province":"Ile de France",
    "sg:tags":[
        "banking",
        "finance",
        "insurance"
    ],
    "wof:name":"Hughes Hubbard & Reed Llp",
    "wof:placetype":"venue"
},
  "geometry": {"coordinates":[2.280794,48.863438],"type":"Point"}
}