{
  "type": "Feature",
  "properties": {
    "addr:full":"36, Rue Georges d'Amboise, 76000 Rouen Haute Normandie",
    "addr:housenumber":"36",
    "addr:postcode":"76000",
    "addr:street":"Rue Georges D'Amboise;Haute Normandie",
    "iso:country":"FR",
    "sg:address":"36, Rue Georges d'Amboise, 76000 Rouen",
    "sg:orig_category":"Non-Classified Establishments",
    "sg:phone":"+33 2 35 98 35 55",
    "sg:province":"Haute Normandie",
    "wof:name":"Filipson 100 000 Volts S.a.",
    "wof:placetype":"venue"
},
  "geometry": {"coordinates":[1.081137,49.443462],"type":"Point"}
}