{
  "type": "Feature",
  "properties": {
    "iso:country":"FR",
    "sg:address":"7 Pl De La Poste 36100 Issoudun",
    "sg:city":"Issoudun",
    "sg:classifiers":[
        {
            "category":"Professional",
            "subcategory":"Printing & Photocopies",
            "type":"Services"
        }
    ],
    "sg:phone":"+33 2 54 03 17 71",
    "sg:postcode":"36100",
    "sg:province":"Centre",
    "sg:tags":[
        "publishing"
    ],
    "wof:name":"Eppc Sarl",
    "wof:placetype":"venue"
},
  "geometry": {"coordinates":[1.989608,46.948288],"type":"Point"}
}