{
  "type": "Feature",
  "properties": {
    "addr:full":"ZI Saint Vincent de Tyrosse Aquitaine 40230",
    "addr:postcode":"40230",
    "iso:country":"FR",
    "sg:address":"ZI",
    "sg:city":"Saint Vincent de Tyrosse",
    "sg:orig_category":"Unclassifiable Establishments",
    "sg:phone":"+33 5 58 77 49 88",
    "sg:postcode":"40230",
    "sg:province":"Aquitaine",
    "wof:name":"Maisadour Semences S.a.",
    "wof:placetype":"venue"
},
  "geometry": {"coordinates":[-1.368627,43.60276],"type":"Point"}
}