{
  "type": "Feature",
  "properties": {
    "iso:country":"FR",
    "sg:address":"72, Bd Saint Jean, 13010 Marseille",
    "sg:orig_category":"Non-Classified Establishments",
    "sg:phone":"+33 4 91 79 69 69",
    "sg:province":"Poitou-Charentes",
    "wof:name":"P.b.f. S.a.r.l. - Production De Bois Fa\u00e7onn\u00e9",
    "wof:placetype":"venue"
},
  "geometry": {"coordinates":[5.408904,43.279099],"type":"Point"}
}