{
  "type": "Feature",
  "properties": {
    "addr:full":"1, Rue Nationale, 62118 Monchy le Preux Nord Pas-de-Calais",
    "addr:housenumber":"1",
    "addr:postcode":"62118",
    "addr:street":"Rue Nationale;Preux Nord",
    "iso:country":"FR",
    "sg:address":"1, Rue Nationale, 62118 Monchy le Preux",
    "sg:orig_category":"Unclassifiable Establishments",
    "sg:phone":"+33 3 21 07 12 12",
    "sg:province":"Nord Pas-de-Calais",
    "wof:name":"M.d.n. Isolation M\u00e9dina S.a.r.l.",
    "wof:placetype":"venue"
},
  "geometry": {"coordinates":[2.895601,50.259666],"type":"Point"}
}