{
  "type": "Feature",
  "properties": {
    "addr:full":"64, Bd Industriel, 62230 Outreau Nord Pas-de-Calais",
    "addr:housenumber":"64",
    "addr:postcode":"62230",
    "addr:street":"Bd Industriel",
    "iso:country":"FR",
    "sg:address":"64, Bd Industriel, 62230 Outreau",
    "sg:orig_category":"Unclassifiable Establishments",
    "sg:phone":"+33 3 21 92 26 90",
    "sg:province":"Nord Pas-de-Calais",
    "wof:name":"Les Rouleurs S.a.",
    "wof:placetype":"venue"
},
  "geometry": {"coordinates":[1.608452,50.706245],"type":"Point"}
}