{
  "type": "Feature",
  "properties": {
    "iso:country":"FR",
    "sg:address":"quartier Notre Dame Cellier 84240 La Tour d'Aigues",
    "sg:city":"La Tour",
    "sg:classifiers":[
        {
            "category":"Wholesale",
            "subcategory":"Wine & Distilled Alcoholic Beverages",
            "type":"Manufacturing & Wholesale Goods"
        }
    ],
    "sg:phone":"+33 4 90 07 40 65",
    "sg:postcode":"74250",
    "sg:province":"Rhone-Alpes",
    "sg:tags":[
        "french"
    ],
    "wof:name":"Union Des Vignerons Des C\u00f4tes Du Luberon Sa",
    "wof:placetype":"venue"
},
  "geometry": {"coordinates":[5.437254,43.773575],"type":"Point"}
}