{
  "type": "Feature",
  "properties": {
    "addr:full":"17, Rue du Bois de la Champelle, 54500 Vandoeuvre l\u00e8s Nancy Lorraine 54500",
    "addr:housenumber":"17",
    "addr:postcode":"54500;54500",
    "addr:street":"Rue Du Bois De La Champelle",
    "iso:country":"FR",
    "sg:address":"17, Rue du Bois de la Champelle, 54500 Vandoeuvre l\u00e8s Nancy",
    "sg:orig_category":"Non-Classified Establishments",
    "sg:phone":"+33 3 83 90 72 06",
    "sg:postcode":"54500",
    "sg:province":"Lorraine",
    "wof:name":"Bull S.a.",
    "wof:placetype":"venue"
},
  "geometry": {"coordinates":[6.135295,48.650818],"type":"Point"}
}