{
  "type": "Feature",
  "properties": {
    "addr:full":"14, Rue Raymond Poincar\u00e9, 54570 Foug Lorraine",
    "addr:housenumber":"14",
    "addr:postcode":"54570",
    "addr:street":"Rue Raymond Poincare\u0301",
    "iso:country":"FR",
    "sg:address":"14, Rue Raymond Poincar\u00e9, 54570 Foug",
    "sg:orig_category":"Unclassifiable Establishments",
    "sg:phone":"+33 3 83 62 70 40",
    "sg:province":"Lorraine",
    "wof:name":"Cl\u00e9ment Entreprise S.a.",
    "wof:placetype":"venue"
},
  "geometry": {"coordinates":[5.787686,48.683098],"type":"Point"}
}