{
  "type": "Feature",
  "properties": {
    "addr:full":"1, All\u00e9e des Bastilliers, 92230 G\u00e9nnevilliers Ile de France",
    "addr:housenumber":"1",
    "addr:postcode":"92230",
    "addr:street":"Alle\u0301E Des Bastilliers;Ile De France",
    "iso:country":"FR",
    "sg:address":"1, All\u00e9e des Bastilliers, 92230 G\u00e9nnevilliers",
    "sg:orig_category":"Non-Classified Establishments",
    "sg:phone":"+33 1 41 85 10 20",
    "sg:province":"Ile de France",
    "wof:name":"Risc Technology Europe S.n.c.",
    "wof:placetype":"venue"
},
  "geometry": {"coordinates":[2.303204,48.934155],"type":"Point"}
}