{
  "type": "Feature",
  "properties": {
    "iso:country":"FR",
    "sg:address":"77244 Cesson C\u00e9dex^^15, Rue Lavoisier - ZA de Bel Air, 77240 Cesson",
    "sg:orig_category":"Non-Classified Establishments",
    "sg:phone":"+33 1 64 10 75 75",
    "sg:postcode":"77240",
    "sg:province":"Ile de France",
    "wof:name":"Cr\u00e9a Bois",
    "wof:placetype":"venue"
},
  "geometry": {"coordinates":[2.600472,48.563885],"type":"Point"}
}