{
  "type": "Feature",
  "properties": {
    "addr:full":"710 Rue Jean Perrin Douai Nord Pas-de-Calais 59500",
    "addr:housenumber":"710",
    "addr:postcode":"59500",
    "addr:street":"Rue Jean Perrin",
    "iso:country":"FR",
    "sg:address":"710 Rue Jean Perrin",
    "sg:city":"Douai",
    "sg:classifiers":[
        {
            "category":"Banks & Credit Unions",
            "subcategory":"Financial Services",
            "type":"Services"
        }
    ],
    "sg:phone":"+33 3 27 95 88 44",
    "sg:postcode":"59500",
    "sg:province":"Nord Pas-de-Calais",
    "sg:tags":[
        "banking",
        "finance",
        "insurance"
    ],
    "wof:name":"Courtray Consulting Centre Tertia",
    "wof:placetype":"venue"
},
  "geometry": {"coordinates":[3.101233,50.397339],"type":"Point"}
}