{
  "type": "Feature",
  "properties": {
    "addr:full":"B.P. 53, 01115 Bellignat C\u00e9dex^^501, Rue des Pr\u00e8s - Parc Industriel Sud, 01100 Bellignat Rhone-Alpes",
    "addr:postcode":"01115;01100",
    "addr:street":"B.P. 53;Rue Des Pre\u0300S Parc Industriel Sud",
    "iso:country":"FR",
    "sg:address":"B.P. 53, 01115 Bellignat C\u00e9dex^^501, Rue des Pr\u00e8s - Parc Industriel Sud, 01100 Bellignat",
    "sg:orig_category":"Non-Classified Establishments",
    "sg:phone":"+33 4 74 77 07 76",
    "sg:province":"Rhone-Alpes",
    "wof:name":"Les Cartonnages Bertrand S.a.",
    "wof:placetype":"venue"
},
  "geometry": {"coordinates":[5.64405,46.24968],"type":"Point"}
}