{
  "type": "Feature",
  "properties": {
    "addr:full":"Rue De L'Universite Technoparc Futura Bp 77 62400 Bethune Nord Pas-de-Calais 62400",
    "addr:housenumber":"77",
    "addr:postcode":"62400;62400",
    "addr:street":"Rue De L'Universite Technoparc Futura Bp;Bethune Nord",
    "iso:country":"FR",
    "sg:address":"Rue De L'Universite Technoparc Futura Bp 77 62400 Bethune",
    "sg:classifiers":[
        {
            "category":"Building & Trades",
            "subcategory":"Construction",
            "type":"Services"
        }
    ],
    "sg:phone":"+33 3 21 68 71 71",
    "sg:postcode":"62400",
    "sg:province":"Nord Pas-de-Calais",
    "sg:tags":[
        "work",
        "public"
    ],
    "wof:name":"Colas Nord Picardie",
    "wof:placetype":"venue"
},
  "geometry": {"coordinates":[2.653541,50.521114],"type":"Point"}
}