{
  "type": "Feature",
  "properties": {
    "addr:full":"Z I Saint Joseph 04101 MANOSQUE Aquitaine",
    "addr:postcode":"04101",
    "addr:street":"Z I",
    "iso:country":"FR",
    "sg:address":"Z I Saint Joseph 04101 MANOSQUE",
    "sg:classifiers":[
        {
            "category":"Wholesale",
            "subcategory":"Fruits & Vegetables",
            "type":"Manufacturing & Wholesale Goods"
        }
    ],
    "sg:phone":"+33 4 92 70 13 30",
    "sg:province":"Aquitaine",
    "sg:tags":[
        "product",
        "cereal"
    ],
    "wof:name":"Groupe Provence Services Coop.",
    "wof:placetype":"venue"
},
  "geometry": {"coordinates":[5.784205,43.831474],"type":"Point"}
}