{
  "type": "Feature",
  "properties": {
    "iso:country":"FR",
    "sg:address":"138 Route De Lyon 01600 Trevoux",
    "sg:classifiers":[
        {
            "category":"Manufacturing",
            "subcategory":"Wood Products",
            "type":"Manufacturing & Wholesale Goods"
        }
    ],
    "sg:phone":"+33 4 74 00 05 27",
    "sg:province":"Rhone-Alpes",
    "sg:tags":[
        "professional",
        "furniture"
    ],
    "wof:name":"Mobagem",
    "wof:placetype":"venue"
},
  "geometry": {"coordinates":[4.788052,45.936069],"type":"Point"}
}