{
  "type": "Feature",
  "properties": {
    "iso:country":"FR",
    "sg:address":"137, Rue Louis Rochemond, 33130 B\u00e8gles",
    "sg:city":"B\u00e8gles",
    "sg:orig_category":"Unclassifiable Establishments",
    "sg:phone":"+33 5 56 85 90 54",
    "sg:postcode":"33130",
    "sg:province":"Aquitaine",
    "wof:name":"Claverie Yves-jacques",
    "wof:placetype":"venue"
},
  "geometry": {"coordinates":[-0.551718,44.800194],"type":"Point"}
}