{
  "type": "Feature",
  "properties": {
    "addr:full":"4/6 rue Georges Cuvier 37550 ST AVERTIN Saint-Avertin Centre 37550",
    "addr:housenumber":"4 / 6;saint-avertin",
    "addr:postcode":"37550;37550",
    "addr:street":"Rue Georges Cuvier",
    "iso:country":"FR",
    "sg:address":"4/6 rue Georges Cuvier 37550 ST AVERTIN",
    "sg:city":"Saint-Avertin",
    "sg:classifiers":[
        {
            "category":"Retail",
            "subcategory":"Car Wash",
            "type":"Services"
        }
    ],
    "sg:phone":"+33 2 47 28 65 19",
    "sg:postcode":"37550",
    "sg:province":"Centre",
    "sg:tags":[
        "transportation",
        "special"
    ],
    "wof:name":"Camexim-cominser Sa",
    "wof:placetype":"venue"
},
  "geometry": {"coordinates":[0.733355,47.343666],"type":"Point"}
}