{
  "type": "Feature",
  "properties": {
    "iso:country":"FR",
    "sg:address":"Eyguebelle Le Couvent Montjoyer 26230 GRIGNAN",
    "sg:classifiers":[
        {
            "category":"Food & Beverages",
            "subcategory":"Fruits & Vegetables",
            "type":"Retail Goods"
        }
    ],
    "sg:phone":"+33 4 75 98 64 64",
    "sg:postcode":"26230",
    "sg:province":"Rhone-Alpes",
    "sg:tags":[
        "syrup"
    ],
    "wof:name":"Eyguebelle S.a.",
    "wof:placetype":"venue"
},
  "geometry": {"coordinates":[4.900287,44.392792],"type":"Point"}
}