{
  "type": "Feature",
  "properties": {
    "iso:country":"FR",
    "sg:address":"B.P. 11, 69290 Craponne^^6, Rue Aqueducs, 69290 Craponne",
    "sg:orig_category":"Non-Classified Establishments",
    "sg:phone":"+33 4 78 57 81 81",
    "sg:postcode":"69290",
    "sg:province":"Rhone-Alpes",
    "wof:name":"Elit S.a. - Entreprise Lyonnaise D'isolations Thermiques",
    "wof:placetype":"venue"
},
  "geometry": {"coordinates":[4.72283,45.747356],"type":"Point"}
}