{
  "type": "Feature",
  "properties": {
    "iso:country":"FR",
    "sg:address":"B.P. 138, 69823 Belleville C\u00e9dex^^272/316, Av. de l'Europe, 69220 Saint Jean d'Ardi\u00e8res",
    "sg:orig_category":"Non-Classified Establishments",
    "sg:phone":"+33 4 74 66 13 20",
    "sg:province":"Rhone-Alpes",
    "wof:name":"Transport Jean Fran\u00e7ois Lefert S.a.",
    "wof:placetype":"venue"
},
  "geometry": {"coordinates":[4.734701,46.112019],"type":"Point"}
}