{
  "type": "Feature",
  "properties": {
    "addr:full":"25 pl Francois Caire; Velaux Champagne",
    "addr:housenumber":"25",
    "addr:street":"Pl Francois Caire",
    "iso:country":"FR",
    "sg:address":"25 pl Francois Caire; Velaux",
    "sg:classifiers":[
        {
            "category":"Banks & Credit Unions",
            "subcategory":"Bank",
            "type":"Services"
        }
    ],
    "sg:phone":"+33 3342879245",
    "sg:province":"Champagne",
    "wof:name":"Caisse R\u00e9gionale Cr\u00e9dit Agricole",
    "wof:placetype":"venue"
},
  "geometry": {"coordinates":[5.254007,43.522686],"type":"Point"}
}