{
  "type": "Feature",
  "properties": {
    "iso:country":"FR",
    "sg:address":"782, Rue du Coin, 74970 Marignier",
    "sg:orig_category":"Non-Classified Establishments",
    "sg:phone":"+33 4 50 34 59 45",
    "sg:postcode":"74970",
    "sg:province":"Rhone-Alpes",
    "wof:name":"Marchand Roger Et Fils S.a.",
    "wof:placetype":"venue"
},
  "geometry": {"coordinates":[6.505664,46.081711],"type":"Point"}
}