{
  "type": "Feature",
  "properties": {
    "iso:country":"FR",
    "sg:address":"B.P. 124, 36003 Ch\u00e2teauroux C\u00e9dex^^154, Rue Amp\u00e8re, 36000 Ch\u00e2teauroux",
    "sg:city":"Ch\u00e2teauroux",
    "sg:orig_category":"Non-Classified Establishments",
    "sg:phone":"+33 2 54 34 38 28",
    "sg:postcode":"36000",
    "sg:province":"Centre",
    "wof:name":"Imprimerie Badel S.a.",
    "wof:placetype":"venue"
},
  "geometry": {"coordinates":[1.696558,46.812469],"type":"Point"}
}