{
  "type": "Feature",
  "properties": {
    "addr:full":"B.P. 24, 72540 Lou\u00e9 C\u00e9dex^^10, Rue du 8 Mai 1945, 72540 Lou\u00e9 Pays de Loire 72540",
    "addr:postcode":"72540;72540;72540",
    "addr:street":"B.P. 24;Rue Du 8 Mai 1945",
    "iso:country":"FR",
    "sg:address":"B.P. 24, 72540 Lou\u00e9 C\u00e9dex^^10, Rue du 8 Mai 1945, 72540 Lou\u00e9",
    "sg:orig_category":"Non-Classified Establishments",
    "sg:phone":"+33 2 43 88 40 62",
    "sg:postcode":"72540",
    "sg:province":"Pays de Loire",
    "wof:name":"Etablissement Gautier S.a.r.l.",
    "wof:placetype":"venue"
},
  "geometry": {"coordinates":[-0.068649,47.962605],"type":"Point"}
}