{
  "type": "Feature",
  "properties": {
    "addr:full":"20 Rue Garibaldi Lyon Rhone-Alpes 69006",
    "addr:housenumber":"20",
    "addr:postcode":"69006",
    "addr:street":"Rue Garibaldi;Rhone-Alpes",
    "iso:country":"FR",
    "sg:address":"20 Rue Garibaldi",
    "sg:city":"Lyon",
    "sg:classifiers":[
        {
            "category":"Banks & Credit Unions",
            "subcategory":"Financial Services",
            "type":"Services"
        }
    ],
    "sg:phone":"+33 4 78 17 81 00",
    "sg:postcode":"69006",
    "sg:province":"Rhone-Alpes",
    "sg:tags":[
        "banking",
        "finance",
        "insurance"
    ],
    "wof:name":"Landwell Et Associes",
    "wof:placetype":"venue"
},
  "geometry": {"coordinates":[4.849689,45.772198],"type":"Point"}
}