{
  "type": "Feature",
  "properties": {
    "iso:country":"FR",
    "sg:address":"Rue De Chamrousse Voies Collines 38800 Le Pont De Claix",
    "sg:classifiers":[
        {
            "category":"Government",
            "subcategory":"Department Of Motor Vehicles",
            "type":"Public Place"
        }
    ],
    "sg:phone":"+33 4 76 99 04 40",
    "sg:postcode":"38800",
    "sg:province":"Rhone-Alpes",
    "sg:tags":[
        "equipment",
        "industrial",
        "transport",
        "motor-cars"
    ],
    "wof:name":"Federal Mogul Operations France Sas",
    "wof:placetype":"venue"
},
  "geometry": {"coordinates":[5.697638,45.124317],"type":"Point"}
}