{
  "type": "Feature",
  "properties": {
    "addr:full":"Ld Le Fief Du Parc Zi 44190 G\u00e9tign\u00e9 Pays de Loire",
    "addr:postcode":"44190",
    "addr:street":"Ld;Zi",
    "iso:country":"FR",
    "sg:address":"Ld Le Fief Du Parc Zi 44190 G\u00e9tign\u00e9",
    "sg:classifiers":[
        {
            "category":"Manufacturing",
            "subcategory":"Paper Products",
            "type":"Manufacturing & Wholesale Goods"
        }
    ],
    "sg:phone":"+33 2 40 54 05 21",
    "sg:province":"Pays de Loire",
    "sg:tags":[
        "raw",
        "material",
        "-",
        "cardboard"
    ],
    "wof:name":"Kappa Scao",
    "wof:placetype":"venue"
},
  "geometry": {"coordinates":[-1.259067,47.083702],"type":"Point"}
}