{
  "type": "Feature",
  "properties": {
    "addr:full":"52, Rue du Mar\u00e9chal Foch, 56100 Lorient Lorient Bretagne 56100",
    "addr:housenumber":"52",
    "addr:postcode":"56100;56100",
    "addr:street":"Rue Du Mare\u0301Chal Foch",
    "iso:country":"FR",
    "sg:address":"52, Rue du Mar\u00e9chal Foch, 56100 Lorient",
    "sg:city":"Lorient",
    "sg:orig_category":"Unclassifiable Establishments",
    "sg:phone":"+33 2 97 21 87 77",
    "sg:postcode":"56100",
    "sg:province":"Bretagne",
    "wof:name":"Creyf's Interim",
    "wof:placetype":"venue"
},
  "geometry": {"coordinates":[-3.359247,47.749386],"type":"Point"}
}