{
  "type": "Feature",
  "properties": {
    "iso:country":"FR",
    "sg:address":"8 Avenue De L Osier 49125 Tierce",
    "sg:classifiers":[
        {
            "category":"Professional",
            "subcategory":"Engineering",
            "type":"Services"
        }
    ],
    "sg:phone":"+33 2 41 42 10 00",
    "sg:postcode":"49125",
    "sg:province":"Pays de Loire",
    "sg:tags":[
        "machine",
        "-",
        "mechanical"
    ],
    "wof:name":"Sofal",
    "wof:placetype":"venue"
},
  "geometry": {"coordinates":[-0.46084,47.613251],"type":"Point"}
}