{
  "type": "Feature",
  "properties": {
    "addr:full":"21, Rte d'Alex, 01100 Bellignat Rhone-Alpes 01100",
    "addr:housenumber":"21",
    "addr:postcode":"01100;01100",
    "addr:street":"Rte D'Alex;Rhone-Alpes",
    "iso:country":"FR",
    "sg:address":"21, Rte d'Alex, 01100 Bellignat",
    "sg:orig_category":"Unclassifiable Establishments",
    "sg:phone":"+33 4 74 73 58 33",
    "sg:postcode":"01100",
    "sg:province":"Rhone-Alpes",
    "wof:name":"S.m.p. S.a. - Soci\u00e9t\u00e9 Moules Pr\u00e9cision",
    "wof:placetype":"venue"
},
  "geometry": {"coordinates":[5.62355,46.226421],"type":"Point"}
}