{
  "type": "Feature",
  "properties": {
    "iso:country":"FR",
    "sg:address":"61100 Flers",
    "sg:city":"Flers",
    "sg:orig_category":"Unclassifiable Establishments",
    "sg:phone":"+33 2 33 64 00 32",
    "sg:postcode":"61100",
    "sg:province":"Basse Normandie",
    "wof:name":"Napoly Transports S.a.",
    "wof:placetype":"venue"
},
  "geometry": {"coordinates":[-0.53315,48.76524],"type":"Point"}
}