{
  "type": "Feature",
  "properties": {
    "addr:full":"Rue Bonor - ZI des Trois Fontaines Saint Dizier Champagne 52100",
    "addr:postcode":"52100",
    "addr:street":"Rue Bonor Zi Des Trois Fontaines Saint;Champagne",
    "iso:country":"FR",
    "sg:address":"Rue Bonor - ZI des Trois Fontaines",
    "sg:city":"Saint Dizier",
    "sg:orig_category":"Unclassifiable Establishments",
    "sg:phone":"+33 3 25 56 57 00",
    "sg:postcode":"52100",
    "sg:province":"Champagne",
    "wof:name":"Lenoir A.t.i.e. S.a. - Transports Internationaux",
    "wof:placetype":"venue"
},
  "geometry": {"coordinates":[4.934152,48.647793],"type":"Point"}
}