{
  "type": "Feature",
  "properties": {
    "addr:full":"B.P. 5, 56650 Inzinzac Lochrist C\u00e9dex^^ZI des Forges, 56650 Inzinzac Lochrist Inzinzac-Lochrist Bretagne 56650",
    "addr:housenumber":"5",
    "addr:postcode":"56650;56650;inzinzac-lochrist;56650",
    "addr:street":"B.P.;Des Forges",
    "iso:country":"FR",
    "sg:address":"B.P. 5, 56650 Inzinzac Lochrist C\u00e9dex^^ZI des Forges, 56650 Inzinzac Lochrist",
    "sg:city":"Inzinzac-Lochrist",
    "sg:orig_category":"Non-Classified Establishments",
    "sg:phone":"+33 2 97 36 83 84",
    "sg:postcode":"56650",
    "sg:province":"Bretagne",
    "wof:name":"Bretagne Rev\u00eatements Industriels S.a.r.l.",
    "wof:placetype":"venue"
},
  "geometry": {"coordinates":[-3.250278,47.826729],"type":"Point"}
}