{
  "type": "Feature",
  "properties": {
    "iso:country":"FR",
    "sg:address":"77, Rue de Montreuil, 75011 Paris",
    "sg:orig_category":"Unclassifiable Establishments",
    "sg:phone":"+33 1 43 73 46 62",
    "sg:province":"Ile de France",
    "wof:name":"Etablissement Bertin S.a.r.l.",
    "wof:placetype":"venue"
},
  "geometry": {"coordinates":[2.391341,48.850578],"type":"Point"}
}