{
  "type": "Feature",
  "properties": {
    "iso:country":"FR",
    "sg:address":"Route De Bitche Zone Artisanale 57620 Goetzenbruck",
    "sg:classifiers":[
        {
            "category":"Manufacturing",
            "subcategory":"Rubber & Plastics",
            "type":"Manufacturing & Wholesale Goods"
        }
    ],
    "sg:phone":"+33 3 87 96 98 84",
    "sg:province":"Lorraine",
    "sg:tags":[
        "packaging",
        "material",
        "-"
    ],
    "wof:name":"Slip Societe Lorraine D'injection Plastique (slip)",
    "wof:placetype":"venue"
},
  "geometry": {"coordinates":[7.379061,49.002766],"type":"Point"}
}