{
  "type": "Feature",
  "properties": {
    "iso:country":"FR",
    "sg:address":"Zi Des Marais 78310 Coigni\u00e8res",
    "sg:classifiers":[
        {
            "category":"Manufacturing",
            "subcategory":"Glass & Minerals",
            "type":"Manufacturing & Wholesale Goods"
        }
    ],
    "sg:phone":"+33 1 34 61 13 67",
    "sg:postcode":"78310",
    "sg:province":"Ile de France",
    "sg:tags":[
        "building",
        "material"
    ],
    "wof:name":"Bds France",
    "wof:placetype":"venue"
},
  "geometry": {"coordinates":[1.918093,48.74704],"type":"Point"}
}