{
  "type": "Feature",
  "properties": {
    "addr:full":"6, Rue du Tanay - ZAC du Levray, 74960 Cran Gevrier Rhone-Alpes 74960",
    "addr:housenumber":"6",
    "addr:postcode":"74960;74960",
    "addr:street":"Rue Du Tanay Zac Du Levray;Rhone-Alpes",
    "iso:country":"FR",
    "sg:address":"6, Rue du Tanay - ZAC du Levray, 74960 Cran Gevrier",
    "sg:orig_category":"Unclassifiable Establishments",
    "sg:phone":"+33 4 50 69 36 36",
    "sg:postcode":"74960",
    "sg:province":"Rhone-Alpes",
    "wof:name":"Lecot S.a.",
    "wof:placetype":"venue"
},
  "geometry": {"coordinates":[6.10647,45.907654],"type":"Point"}
}