{
  "type": "Feature",
  "properties": {
    "addr:full":"B.P. 99 Harfleur Haute Normandie 76700",
    "addr:postcode":"76700",
    "addr:street":"B.P. 99;Haute Normandie",
    "iso:country":"FR",
    "sg:address":"B.P. 99",
    "sg:city":"Harfleur",
    "sg:orig_category":"Non-Classified Establishments",
    "sg:phone":"+33 2 35 13 04 80",
    "sg:postcode":"76700",
    "sg:province":"Haute Normandie",
    "wof:name":"Entreprise Nouvelle Isotherma S.a.",
    "wof:placetype":"venue"
},
  "geometry": {"coordinates":[0.198909,49.504921],"type":"Point"}
}