{
  "type": "Feature",
  "properties": {
    "iso:country":"FR",
    "sg:address":"Rn 7",
    "sg:city":"Barestes 83480 Puget Sur Argens",
    "sg:classifiers":[
        {
            "category":"Utilities",
            "type":"Services"
        }
    ],
    "sg:phone":"+33 4 94 19 92 25",
    "sg:province":"Aquitaine",
    "sg:tags":[
        "raw",
        "energy",
        "material"
    ],
    "wof:name":"Energie Plus",
    "wof:placetype":"venue"
},
  "geometry": {"coordinates":[6.68748,43.454556],"type":"Point"}
}