{
  "type": "Feature",
  "properties": {
    "iso:country":"FR",
    "sg:address":"3, Rue de l'Escure, 45000 Orl\u00e9ans",
    "sg:city":"Orl\u00e9ans",
    "sg:orig_category":"Unclassifiable Establishments",
    "sg:phone":"+33 2 38 78 81 78",
    "sg:postcode":"45000",
    "sg:province":"Centre",
    "wof:name":"Caisse D'epargne Du Val De France Orl\u00e9anais S.a.",
    "wof:placetype":"venue"
},
  "geometry": {"coordinates":[1.90846,47.903194],"type":"Point"}
}