{
  "type": "Feature",
  "properties": {
    "addr:full":"5, Rue du Moulin, 51300 Vitry en Perthois Champagne",
    "addr:housenumber":"5",
    "addr:postcode":"51300",
    "addr:street":"Rue Du Moulin",
    "iso:country":"FR",
    "sg:address":"5, Rue du Moulin, 51300 Vitry en Perthois",
    "sg:orig_category":"Unclassifiable Establishments",
    "sg:phone":"+33 3 26 74 17 31",
    "sg:province":"Champagne",
    "wof:name":"Gaz Comprim\u00e9s De L'est S.a.r.l.",
    "wof:placetype":"venue"
},
  "geometry": {"coordinates":[4.62686,48.747299],"type":"Point"}
}