{
  "type": "Feature",
  "properties": {
    "iso:country":"FR",
    "sg:address":"13 Rue Jacques Monod Zi Chassieu 69680 Chassieu",
    "sg:orig_category":"Agriculture - machinery and equipment Chemicals and Pharmaceuticals Chemistry - by-products Mechanic",
    "sg:phone":"+33 4 72 47 03 30",
    "sg:postcode":"69680",
    "sg:province":"Rhone-Alpes",
    "wof:name":"Labor Hako Sa",
    "wof:placetype":"venue"
},
  "geometry": {"coordinates":[4.972185,45.743477],"type":"Point"}
}