{
  "type": "Feature",
  "properties": {
    "iso:country":"FR",
    "sg:address":"131, RN 7, 38150 Salaise sur Sanne",
    "sg:orig_category":"Unclassifiable Establishments",
    "sg:phone":"+33 4 74 86 26 03",
    "sg:province":"Rhone-Alpes",
    "wof:name":"B\u00e9natru Mat\u00e9riaux S.a.",
    "wof:placetype":"venue"
},
  "geometry": {"coordinates":[4.823532,45.31955],"type":"Point"}
}