{
  "type": "Feature",
  "properties": {
    "addr:full":"Za Du Grand Chemin 33370 Yvrac Yvrac Aquitaine 33370",
    "addr:postcode":"33370;33370",
    "addr:street":"Za Du Grand Chemin",
    "iso:country":"FR",
    "sg:address":"Za Du Grand Chemin 33370 Yvrac",
    "sg:city":"Yvrac",
    "sg:classifiers":[
        {
            "category":"Manufacturing",
            "subcategory":"Printing",
            "type":"Manufacturing & Wholesale Goods"
        }
    ],
    "sg:phone":"+33 5 57 34 06 01",
    "sg:postcode":"33370",
    "sg:province":"Aquitaine",
    "sg:tags":[
        "publishing"
    ],
    "wof:name":"Imprimerie Nolasque",
    "wof:placetype":"venue"
},
  "geometry": {"coordinates":[-0.461917,44.880695],"type":"Point"}
}