{
  "type": "Feature",
  "properties": {
    "addr:full":"B.P. 55, 21120 Is sur Tille^^Rte de Chatillon, 21120 Is sur Tille Avelanges Bourgogne 21120",
    "addr:postcode":"21120;21120;21120",
    "addr:street":"B.P. 55;Tille^^Rte;Chatillon",
    "iso:country":"FR",
    "sg:address":"B.P. 55, 21120 Is sur Tille^^Rte de Chatillon, 21120 Is sur Tille",
    "sg:city":"Avelanges",
    "sg:orig_category":"Non-Classified Establishments",
    "sg:phone":"+33 3 80 95 08 77",
    "sg:postcode":"21120",
    "sg:province":"Bourgogne",
    "wof:name":"Sedam S.a.",
    "wof:placetype":"venue"
},
  "geometry": {"coordinates":[5.11037,47.525398],"type":"Point"}
}