{
  "type": "Feature",
  "properties": {
    "iso:country":"FR",
    "sg:address":"7, Bd Bassins de Radous, 13002 Marseille",
    "sg:orig_category":"Non-Classified Establishments",
    "sg:phone":"+33 4 91 02 02 59",
    "sg:province":"Poitou-Charentes",
    "wof:name":"L'electricit\u00e9 Navale S.a.r.l.",
    "wof:placetype":"venue"
},
  "geometry": {"coordinates":[5.36197,43.320309],"type":"Point"}
}