{
  "type": "Feature",
  "properties": {
    "addr:full":"76, Rue Emile Bot, 59870 Tilloy lez Marchiennes Nord Pas-de-Calais",
    "addr:housenumber":"76",
    "addr:postcode":"59870",
    "addr:street":"Rue Emile Bot",
    "iso:country":"FR",
    "sg:address":"76, Rue Emile Bot, 59870 Tilloy lez Marchiennes",
    "sg:orig_category":"Unclassifiable Establishments",
    "sg:phone":"+33 3 27 27 99 80",
    "sg:province":"Nord Pas-de-Calais",
    "wof:name":"Entreprise Brasseur",
    "wof:placetype":"venue"
},
  "geometry": {"coordinates":[3.317885,50.431458],"type":"Point"}
}