{
  "type": "Feature",
  "properties": {
    "addr:full":"Rue de la Croix Blaise Feves Lorraine 57280",
    "addr:postcode":"57280",
    "addr:street":"Rue De La Croix Blaise Feves Lorraine",
    "iso:country":"FR",
    "sg:address":"Rue de la Croix Blaise",
    "sg:city":"Feves",
    "sg:orig_category":"Unclassifiable Establishments",
    "sg:phone":"+33 3 87 31 84 31",
    "sg:postcode":"57280",
    "sg:province":"Lorraine",
    "wof:name":"M\u00e9tareg S.a.",
    "wof:placetype":"venue"
},
  "geometry": {"coordinates":[6.14754,49.18639],"type":"Point"}
}