{
  "type": "Feature",
  "properties": {
    "iso:country":"FR",
    "sg:address":"Rte de Fourges",
    "sg:city":"Gasny",
    "sg:orig_category":"Unclassifiable Establishments",
    "sg:phone":"+33 2 32 52 81 40",
    "sg:postcode":"27620",
    "sg:province":"Haute Normandie",
    "wof:name":"S.e.e. S.a. - Soci\u00e9t\u00e9 Europ\u00e9enne D'etanch\u00e9it\u00e9",
    "wof:placetype":"venue"
},
  "geometry": {"coordinates":[1.610624,49.098358],"type":"Point"}
}