{
  "type": "Feature",
  "properties": {
    "iso:country":"FR",
    "sg:address":"Palais Rihour - Place Rihour; BP 205; Lille; 59002",
    "sg:classifiers":[
        {
            "category":"Travel",
            "subcategory":"Travel Agent",
            "type":"Entertainment"
        }
    ],
    "sg:phone":"+33 3335957942",
    "sg:province":"Nord Pas-de-Calais",
    "wof:name":"Lille Tourist Office",
    "wof:placetype":"venue"
},
  "geometry": {"coordinates":[3.06281,50.637184],"type":"Point"}
}