{
  "type": "Feature",
  "properties": {
    "addr:full":"5, Rue Robert Schuman, 29480 Le Relecq Kerhuon Le Relecq-Kerhuon Bretagne 29480",
    "addr:housenumber":"5",
    "addr:postcode":"29480;relecq-kerhuon;29480",
    "addr:street":"Rue Robert Schuman",
    "iso:country":"FR",
    "sg:address":"5, Rue Robert Schuman, 29480 Le Relecq Kerhuon",
    "sg:city":"Le Relecq-Kerhuon",
    "sg:orig_category":"Non-Classified Establishments",
    "sg:phone":"+33 2 98 30 45 00",
    "sg:postcode":"29480",
    "sg:province":"Bretagne",
    "wof:name":"Seitha Techniques Et R\u00e9alisations S.a.",
    "wof:placetype":"venue"
},
  "geometry": {"coordinates":[-4.407381,48.398788],"type":"Point"}
}