{
  "type": "Feature",
  "properties": {
    "addr:full":"Rte d'Alet - ZI Limoux Languedoc-Roussillon 11300",
    "addr:postcode":"11300",
    "addr:street":"Rte D'Alet Zi",
    "iso:country":"FR",
    "sg:address":"Rte d'Alet - ZI",
    "sg:city":"Limoux",
    "sg:orig_category":"Non-Classified Establishments",
    "sg:phone":"+33 4 68 31 02 59",
    "sg:postcode":"11300",
    "sg:province":"Languedoc-Roussillon",
    "wof:name":"Del Bano S.a.r.l.",
    "wof:placetype":"venue"
},
  "geometry": {"coordinates":[2.19377,43.05294],"type":"Point"}
}