{
  "type": "Feature",
  "properties": {
    "addr:full":"3, Rte Eaulne, 76270 Sainte Beuve en Rivi\u00e8re Haute Normandie 76270",
    "addr:housenumber":"3",
    "addr:postcode":"76270;76270",
    "addr:street":"Rte Eaulne",
    "iso:country":"FR",
    "sg:address":"3, Rte Eaulne, 76270 Sainte Beuve en Rivi\u00e8re",
    "sg:orig_category":"Non-Classified Establishments",
    "sg:phone":"+33 2 35 93 69 08",
    "sg:postcode":"76270",
    "sg:province":"Haute Normandie",
    "wof:name":"Dalencourt S.a.r.l.",
    "wof:placetype":"venue"
},
  "geometry": {"coordinates":[1.524081,49.760868],"type":"Point"}
}