{
  "type": "Feature",
  "properties": {
    "addr:full":"Ronquerolles 60600 Agnetz Picardie",
    "addr:postcode":"60600",
    "iso:country":"FR",
    "sg:address":"Ronquerolles 60600 Agnetz",
    "sg:orig_category":"Unclassifiable Establishments",
    "sg:phone":"+33 3 44 68 20 40",
    "sg:province":"Picardie",
    "wof:name":"Soci\u00e9t\u00e9 Du Pont Roy S.a.r.l.",
    "wof:placetype":"venue"
},
  "geometry": {"coordinates":[2.384607,49.39912],"type":"Point"}
}