{
  "type": "Feature",
  "properties": {
    "iso:country":"FR",
    "sg:address":"Zone Des Marais",
    "sg:city":"407 Zone Des Marais 94124 Fontenay Sous Bois Cedex",
    "sg:classifiers":[
        {
            "category":"Shopping",
            "subcategory":"Computers & Home Electronics",
            "type":"Retail Goods"
        }
    ],
    "sg:phone":"+33 1 45 14 67 00",
    "sg:province":"Champagne",
    "sg:tags":[
        "information",
        "peripheral",
        "-",
        "technology"
    ],
    "wof:name":"Paxar Monarch France Sa",
    "wof:placetype":"venue"
},
  "geometry": {"coordinates":[2.474705,48.850994],"type":"Point"}
}