{
  "type": "Feature",
  "properties": {
    "addr:full":"ZI Branges Bourgogne 71500",
    "addr:postcode":"71500",
    "addr:street":"Bourgogne",
    "iso:country":"FR",
    "sg:address":"ZI",
    "sg:city":"Branges",
    "sg:orig_category":"Unclassifiable Establishments",
    "sg:phone":"+33 3 85 74 06 14",
    "sg:postcode":"71500",
    "sg:province":"Bourgogne",
    "wof:name":"Jardin Diffusion Crozil\u00e8ne S.a.",
    "wof:placetype":"venue"
},
  "geometry": {"coordinates":[5.189319,46.654655],"type":"Point"}
}