{
  "type": "Feature",
  "properties": {
    "addr:full":"29-31 R Du Bois Galon 94120 Fontenay Sous Bois Ile de France 94120",
    "addr:housenumber":"29-31",
    "addr:postcode":"94120;94120",
    "addr:street":"R Du Bois Galon;Bois Ile De France",
    "iso:country":"FR",
    "sg:address":"29-31 R Du Bois Galon 94120 Fontenay Sous Bois",
    "sg:orig_category":"Business advice and other services Plastics Rubber Rubber and Plastics",
    "sg:phone":"+33 1 48 77 60 75",
    "sg:postcode":"94120",
    "sg:province":"Ile de France",
    "wof:name":"R B Matieres Plastiques",
    "wof:placetype":"venue"
},
  "geometry": {"coordinates":[2.492981,48.859306],"type":"Point"}
}