{
  "type": "Feature",
  "properties": {
    "iso:country":"FR",
    "sg:address":"1329, Rue Louise Michel - ZI de la Villette, 42153 Riorges",
    "sg:orig_category":"Non-Classified Establishments",
    "sg:phone":"+33 4 77 70 46 49",
    "sg:province":"Rhone-Alpes",
    "wof:name":"Jantine S.a.r.l.",
    "wof:placetype":"venue"
},
  "geometry": {"coordinates":[4.04235,46.039371],"type":"Point"}
}