{
  "type": "Feature",
  "properties": {
    "iso:country":"FR",
    "sg:address":"17 Route D'Eschau 67400 Illkirch Graffenstaden",
    "sg:city":"Geispolsheim",
    "sg:classifiers":[
        {
            "category":"Building & Trades",
            "subcategory":"Construction",
            "type":"Services"
        }
    ],
    "sg:phone":"+33 3 88 40 48 37",
    "sg:postcode":"67400",
    "sg:province":"Alsace",
    "sg:tags":[
        "work",
        "public"
    ],
    "wof:name":"Etm",
    "wof:placetype":"venue"
},
  "geometry": {"coordinates":[7.714686,48.512234],"type":"Point"}
}