{
  "type": "Feature",
  "properties": {
    "iso:country":"FR",
    "sg:address":"3 Rue De Lombardie Zac Des Pivolles 69150 Decines Charpieu",
    "sg:classifiers":[
        {
            "category":"Professional",
            "subcategory":"Engineering",
            "type":"Services"
        }
    ],
    "sg:phone":"+33 4 72 81 65 65",
    "sg:postcode":"69150",
    "sg:province":"Rhone-Alpes",
    "sg:tags":[
        "machine",
        "-",
        "mechanical"
    ],
    "wof:name":"Pago Sa",
    "wof:placetype":"venue"
},
  "geometry": {"coordinates":[4.95911,45.770794],"type":"Point"}
}