{
  "type": "Feature",
  "properties": {
    "addr:full":"29690 Brennilis Brennilis Bretagne 29690",
    "addr:postcode":"29690;29690",
    "addr:street":"Brennilis",
    "iso:country":"FR",
    "sg:address":"29690 Brennilis",
    "sg:city":"Brennilis",
    "sg:orig_category":"Unclassifiable Establishments",
    "sg:phone":"+33 2 98 99 60 03",
    "sg:postcode":"29690",
    "sg:province":"Bretagne",
    "wof:name":"Les Salaisons De L'arr\u00e9e S.a.",
    "wof:placetype":"venue"
},
  "geometry": {"coordinates":[-3.850704,48.360104],"type":"Point"}
}