{
  "type": "Feature",
  "properties": {
    "addr:full":"77 Rue Broca 75013 Paris Ile de France",
    "addr:housenumber":"77",
    "addr:postcode":"75013",
    "addr:street":"Rue Broca",
    "iso:country":"FR",
    "sg:address":"77 Rue Broca 75013 Paris",
    "sg:classifiers":[
        {
            "category":"Manufacturing",
            "subcategory":"Printing",
            "type":"Manufacturing & Wholesale Goods"
        }
    ],
    "sg:phone":"+33 1 43 31 40 36",
    "sg:province":"Ile de France",
    "sg:tags":[
        "publishing"
    ],
    "wof:name":"Claude Houdart Reliures",
    "wof:placetype":"venue"
},
  "geometry": {"coordinates":[2.347039,48.83662],"type":"Point"}
}