{
  "type": "Feature",
  "properties": {
    "addr:full":"26, Rue B\u00e9n\u00e9dit, 13004 Marseille Poitou-Charentes",
    "addr:housenumber":"26",
    "addr:postcode":"13004",
    "addr:street":"Rue Be\u0301Ne\u0301Dit",
    "iso:country":"FR",
    "sg:address":"26, Rue B\u00e9n\u00e9dit, 13004 Marseille",
    "sg:orig_category":"Non-Classified Establishments",
    "sg:phone":"+33 4 91 62 21 64",
    "sg:province":"Poitou-Charentes",
    "wof:name":"Auxiliaire De La Ferblanterie S.a.",
    "wof:placetype":"venue"
},
  "geometry": {"coordinates":[5.391701,43.308907],"type":"Point"}
}