{
  "type": "Feature",
  "properties": {
    "iso:country":"FR",
    "sg:address":"1842 avenue des Templiers 06140 Vence",
    "sg:classifiers":[
        {
            "category":"Professional",
            "subcategory":"Management & Consulting",
            "type":"Services"
        }
    ],
    "sg:phone":"+33 4 93 58 25 00",
    "sg:province":"Provence-Alpes-C\u00f4te d'Azur",
    "sg:tags":[
        "project"
    ],
    "wof:name":"Scenarios + Vision Sarl",
    "wof:placetype":"venue"
},
  "geometry": {"coordinates":[7.111072,43.730309],"type":"Point"}
}