{
  "type": "Feature",
  "properties": {
    "iso:country":"FR",
    "sg:address":"228 Avenue Alfred Motte 59100 Roubaix",
    "sg:classifiers":[
        {
            "category":"Shopping",
            "subcategory":"Clothing, Apparel, & Fashions",
            "type":"Retail Goods"
        }
    ],
    "sg:phone":"+33 3 20 83 08 58",
    "sg:postcode":"59100",
    "sg:province":"Nord Pas-de-Calais",
    "sg:tags":[
        "textile",
        "clothing",
        "clothes"
    ],
    "wof:name":"Promod",
    "wof:placetype":"venue"
},
  "geometry": {"coordinates":[3.196502,50.675602],"type":"Point"}
}