{
  "type": "Feature",
  "properties": {
    "iso:country":"FR",
    "sg:address":"B.P. 211, 29804 Brest C\u00e9dex 09^^60, Av. du Baron Lacrosse, 29850 Gouesnou",
    "sg:city":"Gouesnou",
    "sg:orig_category":"Non-Classified Establishments",
    "sg:phone":"+33 2 98 41 44 78",
    "sg:postcode":"29850",
    "sg:province":"Bretagne",
    "wof:name":"Axe M\u00e9dia E.u.r.l.",
    "wof:placetype":"venue"
},
  "geometry": {"coordinates":[-4.465689,48.44989],"type":"Point"}
}