{
  "type": "Feature",
  "properties": {
    "iso:country":"FR",
    "sg:address":"227, Corniche de Kerallic, 22310 Plestin les Gr\u00e8ves",
    "sg:city":"Plestin-les-Gr\u00e8ves",
    "sg:orig_category":"Unclassifiable Establishments",
    "sg:phone":"+33 2 96 35 63 51",
    "sg:postcode":"22310",
    "sg:province":"Bretagne",
    "wof:name":"Serres De Kerallic E.a.r.l.",
    "wof:placetype":"venue"
},
  "geometry": {"coordinates":[-3.619574,48.679848],"type":"Point"}
}