{
  "type": "Feature",
  "properties": {
    "addr:full":"22 bis Flamen 59000 Lille Nord Pas-de-Calais 59000",
    "addr:housenumber":"22 bis",
    "addr:postcode":"59000;59000",
    "addr:street":"Flamen",
    "iso:country":"FR",
    "sg:address":"22 bis",
    "sg:city":"Flamen 59000 Lille",
    "sg:classifiers":[
        {
            "category":"Shopping",
            "subcategory":"Gifts & Souvenirs",
            "type":"Retail Goods"
        }
    ],
    "sg:phone":"+33 3 20 22 82 43",
    "sg:postcode":"59000",
    "sg:province":"Nord Pas-de-Calais",
    "sg:tags":[
        "product",
        "miscellaneous"
    ],
    "wof:name":"Leschevin Christophe",
    "wof:placetype":"venue"
},
  "geometry": {"coordinates":[3.041546,50.624809],"type":"Point"}
}