{
  "type": "Feature",
  "properties": {
    "addr:full":"2, Rte de Balaruc, 34200 S\u00e8te Languedoc-Roussillon",
    "addr:housenumber":"2",
    "addr:postcode":"34200",
    "addr:street":"Rte De Balaruc",
    "iso:country":"FR",
    "sg:address":"2, Rte de Balaruc, 34200 S\u00e8te",
    "sg:orig_category":"Unclassifiable Establishments",
    "sg:phone":"+33 4 67 48 63 66",
    "sg:province":"Languedoc-Roussillon",
    "wof:name":"Mandagot Vitale Fr\u00e9d\u00e9rique",
    "wof:placetype":"venue"
},
  "geometry": {"coordinates":[3.708855,43.422352],"type":"Point"}
}