{
  "type": "Feature",
  "properties": {
    "addr:full":"Le Bourg; Quincie Centre",
    "addr:street":"Le Bourg Quincie",
    "iso:country":"FR",
    "sg:address":"Le Bourg; Quincie",
    "sg:classifiers":[
        {
            "category":"Banks & Credit Unions",
            "subcategory":"Bank",
            "type":"Services"
        }
    ],
    "sg:phone":"+33 3374043374",
    "sg:province":"Centre",
    "wof:name":"Cr\u00e9dit Agricole Mutuel Du Sud Est",
    "wof:placetype":"venue"
},
  "geometry": {"coordinates":[5.385653,45.275349],"type":"Point"}
}