{
  "type": "Feature",
  "properties": {
    "iso:country":"FR",
    "sg:address":"30300 Beaucaire",
    "sg:orig_category":"Unclassifiable Establishments",
    "sg:phone":"+33 4 66 59 81 30",
    "sg:province":"Languedoc-Roussillon",
    "wof:name":"Ciments Calcia",
    "wof:placetype":"venue"
},
  "geometry": {"coordinates":[4.5657,43.7882],"type":"Point"}
}