{
  "type": "Feature",
  "properties": {
    "addr:full":"B.P. 14, 32201 Gimont C\u00e9dex^^Chemin d'Enrobert, 32200 Gimont Midi Pyr\u00e9n\u00e9es",
    "addr:postcode":"32201;32200",
    "addr:street":"B.P. 14;D'Enrobert",
    "iso:country":"FR",
    "sg:address":"B.P. 14, 32201 Gimont C\u00e9dex^^Chemin d'Enrobert, 32200 Gimont",
    "sg:orig_category":"Non-Classified Establishments",
    "sg:phone":"+33 5 62 67 92 30",
    "sg:province":"Midi Pyr\u00e9n\u00e9es",
    "wof:name":"Par\u00e9ra S.a.",
    "wof:placetype":"venue"
},
  "geometry": {"coordinates":[0.878801,43.631039],"type":"Point"}
}