{
  "type": "Feature",
  "properties": {
    "iso:country":"FR",
    "sg:address":"B.P. 15, 16200 Jarnac^^29, Quai de l'Ile Madame, 16200 Jarnac",
    "sg:orig_category":"Non-Classified Establishments",
    "sg:phone":"+33 5 45 36 87 00",
    "sg:postcode":"16200",
    "sg:province":"Poitou-Charentes",
    "wof:name":"Etablissement Tiffon S.a.",
    "wof:placetype":"venue"
},
  "geometry": {"coordinates":[-0.175883,45.677105],"type":"Point"}
}