{
  "type": "Feature",
  "properties": {
    "addr:full":"12 Rue Winston Churchill 57000 Metz Lorraine",
    "addr:housenumber":"12",
    "addr:postcode":"57000",
    "addr:street":"Rue Winston Churchill",
    "iso:country":"FR",
    "sg:address":"12 Rue Winston Churchill 57000 Metz",
    "sg:classifiers":[
        {
            "category":"Professional",
            "subcategory":"Printing & Photocopies",
            "type":"Services"
        }
    ],
    "sg:phone":"+33 3 87 36 20 21",
    "sg:province":"Lorraine",
    "sg:tags":[
        "publishing"
    ],
    "wof:name":"Comareg Sa",
    "wof:placetype":"venue"
},
  "geometry": {"coordinates":[6.173419,49.116028],"type":"Point"}
}