{
  "type": "Feature",
  "properties": {
    "addr:full":"all\u00e9e Ren\u00e9 Cassagne 33310 Lormont Lormont Aquitaine 33310",
    "addr:postcode":"33310;33310",
    "addr:street":"Alle\u0301E Rene\u0301 Cassagne",
    "iso:country":"FR",
    "sg:address":"all\u00e9e Ren\u00e9 Cassagne 33310 Lormont",
    "sg:city":"Lormont",
    "sg:orig_category":"Ferrites",
    "sg:phone":"+33 5 56 33 82 82",
    "sg:postcode":"33310",
    "sg:province":"Aquitaine",
    "wof:name":"Epcos S.a.",
    "wof:placetype":"venue"
},
  "geometry": {"coordinates":[-0.511999,44.870094],"type":"Point"}
}