{
  "type": "Feature",
  "properties": {
    "addr:full":"31 Rue Henri Rochefort 75017 Paris Ile de France 75017",
    "addr:housenumber":"31",
    "addr:postcode":"75017;75017",
    "addr:street":"Rue Henri Rochefort",
    "iso:country":"FR",
    "sg:address":"31 Rue Henri Rochefort 75017 Paris",
    "sg:classifiers":[
        {
            "category":"Manufacturing",
            "subcategory":"Glass & Minerals",
            "type":"Manufacturing & Wholesale Goods"
        }
    ],
    "sg:phone":"+33 1 56 79 63 00",
    "sg:postcode":"75017",
    "sg:province":"Ile de France",
    "sg:tags":[
        "building",
        "material"
    ],
    "wof:name":"Bsn Glasspack",
    "wof:placetype":"venue"
},
  "geometry": {"coordinates":[2.308359,48.882633],"type":"Point"}
}