{
  "type": "Feature",
  "properties": {
    "addr:full":"ZI Beausoleil La Vespi\u00e8re Basse Normandie 14290",
    "addr:postcode":"14290",
    "iso:country":"FR",
    "sg:address":"ZI Beausoleil",
    "sg:city":"La Vespi\u00e8re",
    "sg:orig_category":"Unclassifiable Establishments",
    "sg:phone":"+33 2 31 63 48 48",
    "sg:postcode":"14290",
    "sg:province":"Basse Normandie",
    "wof:name":"Imprimerie Du Baillage S.a.r.l.",
    "wof:placetype":"venue"
},
  "geometry": {"coordinates":[0.411531,49.017822],"type":"Point"}
}