{
  "type": "Feature",
  "properties": {
    "iso:country":"FR",
    "sg:address":"1 rue de Stockholm 75008 Paris",
    "sg:classifiers":[
        {
            "category":"Wholesale",
            "subcategory":"Machinery & Supplies",
            "type":"Manufacturing & Wholesale Goods"
        }
    ],
    "sg:phone":"+33 1 69 48 79 78",
    "sg:province":"Ile de France",
    "sg:tags":[
        "industry",
        "workshop"
    ],
    "wof:name":"Eticartocc S.a.r.l.",
    "wof:placetype":"venue"
},
  "geometry": {"coordinates":[2.322802,48.877026],"type":"Point"}
}