{
  "type": "Feature",
  "properties": {
    "iso:country":"FR",
    "sg:address":"Route Nationale 191 91540 Fontenay Le Vicomte",
    "sg:classifiers":[
        {
            "category":"Farming",
            "subcategory":"Farm",
            "type":"Manufacturing & Wholesale Goods"
        }
    ],
    "sg:phone":"+33 1 64 57 04 19",
    "sg:postcode":"91540",
    "sg:province":"Ile de France",
    "sg:tags":[
        "horticulture",
        "agriculture",
        "livestock"
    ],
    "wof:name":"Les Jardiniers De Paris",
    "wof:placetype":"venue"
},
  "geometry": {"coordinates":[2.434665,48.566704],"type":"Point"}
}