{
  "type": "Feature",
  "properties": {
    "addr:full":"67, Rue Carnot, 89100 Sens Sens Bourgogne 89100",
    "addr:housenumber":"67",
    "addr:postcode":"89100;89100",
    "addr:street":"Rue Carnot",
    "iso:country":"FR",
    "sg:address":"67, Rue Carnot, 89100 Sens",
    "sg:city":"Sens",
    "sg:orig_category":"Unclassifiable Establishments",
    "sg:phone":"+33 3 86 83 79 60",
    "sg:postcode":"89100",
    "sg:province":"Bourgogne",
    "wof:name":"C.a.t. -centre D'aide Par Le Travail",
    "wof:placetype":"venue"
},
  "geometry": {"coordinates":[3.27842,48.203529],"type":"Point"}
}