{
  "type": "Feature",
  "properties": {
    "iso:country":"FR",
    "sg:address":"Chemin Aum\u00f4ne Vieille - Parc d'Angevini\u00e8re - B\u00e2t. 3B",
    "sg:city":"Aubagne",
    "sg:orig_category":"Non-Classified Establishments",
    "sg:phone":"+33 4 91 27 12 25",
    "sg:postcode":"13400",
    "sg:province":"Centre",
    "wof:name":"Fischer Bioblock Scientific S.a.s.",
    "wof:placetype":"venue"
},
  "geometry": {"coordinates":[5.521601,43.285622],"type":"Point"}
}