{
  "type": "Feature",
  "properties": {
    "iso:country":"FR",
    "sg:address":"70, Av. du Point du Jour, 69005 Lyon",
    "sg:orig_category":"Non-Classified Establishments",
    "sg:phone":"+33 4 78 36 28 74",
    "sg:province":"Rhone-Alpes",
    "wof:name":"Boucherie Vessi\u00e8re S.a.",
    "wof:placetype":"venue"
},
  "geometry": {"coordinates":[4.797213,45.756481],"type":"Point"}
}