{
  "type": "Feature",
  "properties": {
    "addr:full":"2, Rue de la Garenne, 94360 Bry sur Marne Ile de France",
    "addr:housenumber":"2",
    "addr:postcode":"94360",
    "addr:street":"Rue De La Garenne",
    "iso:country":"FR",
    "sg:address":"2, Rue de la Garenne, 94360 Bry sur Marne",
    "sg:orig_category":"Unclassifiable Establishments",
    "sg:phone":"+33 1 48 81 43 10",
    "sg:province":"Ile de France",
    "wof:name":"A.l.g. Fabae S.a.",
    "wof:placetype":"venue"
},
  "geometry": {"coordinates":[2.529661,48.843281],"type":"Point"}
}