{
  "type": "Feature",
  "properties": {
    "addr:full":"74-76 rue du Pr\u00e9 Catelan 59110 La Madeleine Nord Pas-de-Calais 59110",
    "addr:housenumber":"74-76",
    "addr:postcode":"59110;59110",
    "addr:street":"Rue Du Pre\u0301 Catelan",
    "iso:country":"FR",
    "sg:address":"74-76 rue du Pr\u00e9 Catelan 59110 La Madeleine",
    "sg:orig_category":"Fans, Blowers",
    "sg:phone":"+33 3 20 14 50 95",
    "sg:postcode":"59110",
    "sg:province":"Nord Pas-de-Calais",
    "wof:name":"Etablissements Descamps S.a.",
    "wof:placetype":"venue"
},
  "geometry": {"coordinates":[3.06097,50.656612],"type":"Point"}
}