{
  "type": "Feature",
  "properties": {
    "iso:country":"FR",
    "sg:address":"11, Rue Barrade, 74960 Meythet",
    "sg:orig_category":"Unclassifiable Establishments",
    "sg:phone":"+33 4 50 57 18 98",
    "sg:province":"Rhone-Alpes",
    "wof:name":"Plasti Savoies Industries S.a.",
    "wof:placetype":"venue"
},
  "geometry": {"coordinates":[6.104407,45.919758],"type":"Point"}
}