{
  "type": "Feature",
  "properties": {
    "addr:full":"30, Rue Johannot, 42000 Saint Etienne Rhone-Alpes",
    "addr:housenumber":"30",
    "addr:postcode":"42000",
    "addr:street":"Rue Johannot",
    "iso:country":"FR",
    "sg:address":"30, Rue Johannot, 42000 Saint Etienne",
    "sg:orig_category":"Unclassifiable Establishments",
    "sg:phone":"+33 4 77 43 08 58",
    "sg:province":"Rhone-Alpes",
    "wof:name":"Moteurs Leroy Somer S.a.",
    "wof:placetype":"venue"
},
  "geometry": {"coordinates":[4.402373,45.45491],"type":"Point"}
}