{
  "type": "Feature",
  "properties": {
    "iso:country":"FR",
    "sg:address":"Route De Limoges 19140 UZERCHE",
    "sg:classifiers":[
        {
            "category":"Train Station",
            "subcategory":"Rail",
            "type":"Transportation"
        }
    ],
    "sg:phone":"+33 5 55 73 18 84",
    "sg:province":"Limousin",
    "sg:tags":[
        "railway",
        "sleeper"
    ],
    "wof:name":"Valette Scierie Parquetterie Sarl",
    "wof:placetype":"venue"
},
  "geometry": {"coordinates":[1.561477,45.438789],"type":"Point"}
}