{
  "type": "Feature",
  "properties": {
    "addr:full":"Rte Falaises - Parc d'Activit\u00e9 Val de Reuil Haute Normandie 27100",
    "addr:postcode":"27100",
    "addr:street":"Rte Falaises Parc D'Activite \u0301 Val De Reuil Haute Normandie",
    "iso:country":"FR",
    "sg:address":"Rte Falaises - Parc d'Activit\u00e9",
    "sg:city":"Val de Reuil",
    "sg:orig_category":"Unclassifiable Establishments",
    "sg:phone":"+33 2 32 61 04 73",
    "sg:postcode":"27100",
    "sg:province":"Haute Normandie",
    "wof:name":"C.e.r.a. S.a. - Conception Etude R\u00e9alisation D'automatismes Electroniques",
    "wof:placetype":"venue"
},
  "geometry": {"coordinates":[1.198377,49.260983],"type":"Point"}
}