{
  "type": "Feature",
  "properties": {
    "addr:full":"11 Rue Du Canal 67400 Illkirch Graffenstaden Geispolsheim Alsace 67400",
    "addr:housenumber":"11",
    "addr:postcode":"67400;67400",
    "addr:street":"Rue Du Canal",
    "iso:country":"FR",
    "sg:address":"11 Rue Du Canal 67400 Illkirch Graffenstaden",
    "sg:city":"Geispolsheim",
    "sg:classifiers":[
        {
            "category":"Transit Center",
            "subcategory":"Freight",
            "type":"Transportation"
        }
    ],
    "sg:phone":"+33 3 88 39 43 91",
    "sg:postcode":"67400",
    "sg:province":"Alsace",
    "sg:tags":[
        "metallurgy",
        "pipe",
        "metalworking",
        "sheet"
    ],
    "wof:name":"Corderie Weiss Sa",
    "wof:placetype":"venue"
},
  "geometry": {"coordinates":[7.734166,48.548901],"type":"Point"}
}