{
  "type": "Feature",
  "properties": {
    "iso:country":"FR",
    "sg:address":"813, Av L\u00e9on Blum, 01500 Amb\u00e9rieu en Bugey",
    "sg:orig_category":"Unclassifiable Establishments",
    "sg:phone":"+33 4 74 46 13 46",
    "sg:province":"Rhone-Alpes",
    "wof:name":"Brunet Travaux Publics S.a.",
    "wof:placetype":"venue"
},
  "geometry": {"coordinates":[5.340296,45.964081],"type":"Point"}
}