{
  "type": "Feature",
  "properties": {
    "iso:country":"FR",
    "sg:address":"9 Av Du Paradis 65100 Lourdes",
    "sg:classifiers":[
        {
            "category":"Travel",
            "subcategory":"Hotels & Motels",
            "type":"Entertainment"
        }
    ],
    "sg:phone":"+33 5 62 94 50 02",
    "sg:postcode":"65100",
    "sg:province":"Midi Pyr\u00e9n\u00e9es",
    "sg:tags":[
        "hotels",
        "business",
        "restaurant"
    ],
    "wof:name":"Hotel D'espagne Et Saboureau",
    "wof:placetype":"venue"
},
  "geometry": {"coordinates":[-0.052713,43.094063],"type":"Point"}
}