{
  "type": "Feature",
  "properties": {
    "addr:full":"Le Barbut 33750 Beychac et Caillau Beychac-et-Caillau Aquitaine 33750",
    "addr:housenumber":"beychac-et-caillau",
    "addr:postcode":"33750;33750",
    "iso:country":"FR",
    "sg:address":"Le Barbut 33750 Beychac et Caillau",
    "sg:city":"Beychac-et-Caillau",
    "sg:orig_category":"Non-Classified Establishments",
    "sg:phone":"+33 5 56 72 97 07",
    "sg:postcode":"33750",
    "sg:province":"Aquitaine",
    "wof:name":"Aquitaine Ressorts S.a.r.l.",
    "wof:placetype":"venue"
},
  "geometry": {"coordinates":[-0.397144,44.871407],"type":"Point"}
}