{
  "type": "Feature",
  "properties": {
    "addr:full":"35 avenue Victor Hugo 13100 AIX EN PROVENCE Nord Pas-de-Calais",
    "addr:housenumber":"35",
    "addr:postcode":"13100",
    "addr:street":"Avenue Victor Hugo;En Provence Nord",
    "iso:country":"FR",
    "sg:address":"35 avenue Victor Hugo 13100 AIX EN PROVENCE",
    "sg:classifiers":[
        {
            "category":"Food & Beverages",
            "subcategory":"Chocolate",
            "type":"Retail Goods"
        }
    ],
    "sg:phone":"+33 4 42 26 05 71",
    "sg:province":"Nord Pas-de-Calais",
    "wof:name":"L\u00e9onard Parli S.a.r.l",
    "wof:placetype":"venue"
},
  "geometry": {"coordinates":[5.44603,43.523441],"type":"Point"}
}