{
  "type": "Feature",
  "properties": {
    "addr:full":"Allee De Bretagne Zi Nord 26300 Bourg De Peage Rhone-Alpes 26300",
    "addr:postcode":"26300;26300",
    "addr:street":"Allee De Bretagne Zi Nord;Rhone-Alpes",
    "iso:country":"FR",
    "sg:address":"Allee De Bretagne Zi Nord 26300 Bourg De Peage",
    "sg:classifiers":[
        {
            "category":"Manufacturing",
            "subcategory":"Paper Products",
            "type":"Manufacturing & Wholesale Goods"
        }
    ],
    "sg:phone":"+33 4 75 72 60 47",
    "sg:postcode":"26300",
    "sg:province":"Rhone-Alpes",
    "sg:tags":[
        "packaging",
        "material",
        "-",
        "cardboard"
    ],
    "wof:name":"Emballage Services",
    "wof:placetype":"venue"
},
  "geometry": {"coordinates":[5.09157,44.938511],"type":"Point"}
}