{
  "type": "Feature",
  "properties": {
    "iso:country":"FR",
    "sg:address":"48 bis, Rue Bretonneau, 37540 Saint Cyr sur Loire",
    "sg:city":"Saint-Cyr-sur-Loire",
    "sg:orig_category":"Unclassifiable Establishments",
    "sg:phone":"+33 2 47 54 00 08",
    "sg:postcode":"37540",
    "sg:province":"Centre",
    "wof:name":"Le Jardinier S.a.r.l.",
    "wof:placetype":"venue"
},
  "geometry": {"coordinates":[0.655981,47.39859],"type":"Point"}
}