{
  "type": "Feature",
  "properties": {
    "addr:full":"Plasti\u00e8res 71290 Cuisery Cuisery Bourgogne 71290",
    "addr:postcode":"71290;71290",
    "addr:street":"Plastie\u0300Res",
    "iso:country":"FR",
    "sg:address":"Plasti\u00e8res 71290 Cuisery",
    "sg:city":"Cuisery",
    "sg:classifiers":[
        {
            "category":"Farming",
            "subcategory":"Livestock Farm",
            "type":"Manufacturing & Wholesale Goods"
        }
    ],
    "sg:phone":"+33 3 85 40 09 30",
    "sg:postcode":"71290",
    "sg:province":"Bourgogne",
    "sg:tags":[
        "breeding",
        "agriculture",
        "animal"
    ],
    "wof:name":"Agro France Sa",
    "wof:placetype":"venue"
},
  "geometry": {"coordinates":[4.951675,46.516216],"type":"Point"}
}