{
  "type": "Feature",
  "properties": {
    "addr:full":"6, Rue Jacquart, 33700 M\u00e9rignac M\u00e9rignac Aquitaine 33700",
    "addr:housenumber":"6",
    "addr:postcode":"33700;33700",
    "addr:street":"Rue Jacquart",
    "iso:country":"FR",
    "sg:address":"6, Rue Jacquart, 33700 M\u00e9rignac",
    "sg:city":"M\u00e9rignac",
    "sg:orig_category":"Unclassifiable Establishments",
    "sg:phone":"+33 5 57 92 50 80",
    "sg:postcode":"33700",
    "sg:province":"Aquitaine",
    "wof:name":"Comi Service S.a.r.l.",
    "wof:placetype":"venue"
},
  "geometry": {"coordinates":[-0.672179,44.851704],"type":"Point"}
}