{
  "type": "Feature",
  "properties": {
    "addr:full":"19, Av. de F\u00e9tilly, 17000 La Rochelle Poitou-Charentes",
    "addr:postcode":"17000",
    "addr:street":"19 Av. De Fe\u0301Tilly",
    "iso:country":"FR",
    "sg:address":"19, Av. de F\u00e9tilly, 17000 La Rochelle",
    "sg:orig_category":"Unclassifiable Establishments",
    "sg:phone":"+33 5 46 34 77 88",
    "sg:province":"Poitou-Charentes",
    "wof:name":"Editions Rupella S.a.r.l.",
    "wof:placetype":"venue"
},
  "geometry": {"coordinates":[-1.152589,46.170395],"type":"Point"}
}