{
  "type": "Feature",
  "properties": {
    "iso:country":"FR",
    "sg:address":"chem Peine 84820 Visan",
    "sg:classifiers":[
        {
            "category":"Food Court",
            "type":"Food & Drink"
        }
    ],
    "sg:phone":"+33 4 90 28 50 80",
    "sg:province":"Nord Pas-de-Calais",
    "sg:tags":[
        "product",
        "related"
    ],
    "wof:name":"Cave Les Coteaux De Visan",
    "wof:placetype":"venue"
},
  "geometry": {"coordinates":[4.95022,44.313202],"type":"Point"}
}