{
  "type": "Feature",
  "properties": {
    "addr:full":"185 Rue De Bercy Vaugirard 75012 Paris Ile de France 75012",
    "addr:housenumber":"185",
    "addr:postcode":"75012;75012",
    "addr:street":"Rue De Bercy",
    "iso:country":"FR",
    "sg:address":"185 Rue De Bercy Vaugirard 75012 Paris",
    "sg:classifiers":[
        {
            "category":"Professional",
            "subcategory":"Engineering",
            "type":"Services"
        }
    ],
    "sg:phone":"+33 1 44 68 68 68",
    "sg:postcode":"75012",
    "sg:province":"Ile de France",
    "sg:tags":[
        "machine",
        "-",
        "mechanical"
    ],
    "wof:name":"Cpcu",
    "wof:placetype":"venue"
},
  "geometry": {"coordinates":[2.389295,48.841045],"type":"Point"}
}