{
  "type": "Feature",
  "properties": {
    "iso:country":"FR",
    "sg:address":"62 Rue De Richelieu 75002 Paris",
    "sg:classifiers":[
        {
            "category":"Professional",
            "subcategory":"Printing & Photocopies",
            "type":"Services"
        }
    ],
    "sg:phone":"+33 1 55 35 56 00",
    "sg:province":"Ile de France",
    "sg:tags":[
        "publishing"
    ],
    "wof:name":"Sciences Et Avenir",
    "wof:placetype":"venue"
},
  "geometry": {"coordinates":[2.33851,48.868443],"type":"Point"}
}