{
  "type": "Feature",
  "properties": {
    "addr:full":"B.P. 6 Meymac^^La Gouale 19250 Meymac Limousin 19250",
    "addr:postcode":"19250;19250",
    "addr:street":"B.P. 6 Meymac^^La Gouale",
    "iso:country":"FR",
    "sg:address":"B.P. 6",
    "sg:city":"Meymac^^La Gouale 19250 Meymac",
    "sg:orig_category":"Non-Classified Establishments",
    "sg:phone":"+33 5 55 46 70 00",
    "sg:postcode":"19250",
    "sg:province":"Limousin",
    "wof:name":"B.m.s. S.a. - Bristol Myers Squibb",
    "wof:placetype":"venue"
},
  "geometry": {"coordinates":[2.14335,45.47224],"type":"Point"}
}