{
  "type": "Feature",
  "properties": {
    "addr:full":"Rue Saint Eloi Cr\u00e9py en Valois Picardie 60800",
    "addr:postcode":"60800",
    "addr:street":"Rue Saint Eloi;En;Picardie",
    "iso:country":"FR",
    "sg:address":"Rue Saint Eloi",
    "sg:city":"Cr\u00e9py en Valois",
    "sg:orig_category":"Non-Classified Establishments",
    "sg:phone":"+33 3 44 87 63 38",
    "sg:postcode":"60800",
    "sg:province":"Picardie",
    "wof:name":"Texidel S.a.",
    "wof:placetype":"venue"
},
  "geometry": {"coordinates":[2.90574,49.230347],"type":"Point"}
}