{
  "type": "Feature",
  "properties": {
    "iso:country":"FR",
    "sg:address":"7 Rue Des Claires 50460 Querqueville",
    "sg:city":"Querqueville",
    "sg:classifiers":[
        {
            "category":"Manufacturing",
            "subcategory":"Metals",
            "type":"Manufacturing & Wholesale Goods"
        }
    ],
    "sg:phone":"+33 2 33 08 81 00",
    "sg:postcode":"50460",
    "sg:province":"Basse Normandie",
    "sg:tags":[
        "pipe",
        "sheet",
        "-",
        "metalworking",
        "metallic",
        "metallurgy",
        "finished"
    ],
    "wof:name":"Gie Ace",
    "wof:placetype":"venue"
},
  "geometry": {"coordinates":[-1.692272,49.659676],"type":"Point"}
}