{
  "type": "Feature",
  "properties": {
    "addr:full":"Quartier de la Rivesaltes Cases de Pene Languedoc-Roussillon 66600",
    "addr:postcode":"66600",
    "addr:street":"Quartier De La Rivesaltes Cases De Pene",
    "iso:country":"FR",
    "sg:address":"Quartier de la Rivesaltes",
    "sg:city":"Cases de Pene",
    "sg:orig_category":"Unclassifiable Establishments",
    "sg:phone":"+33 4 68 38 98 00",
    "sg:postcode":"66600",
    "sg:province":"Languedoc-Roussillon",
    "wof:name":"Proven\u00e7ale S.a.",
    "wof:placetype":"venue"
},
  "geometry": {"coordinates":[2.874005,42.770721],"type":"Point"}
}