{
  "type": "Feature",
  "properties": {
    "addr:full":"Rte De Nevy BP 1 58310 St Amand En Puisaye Arquian Bourgogne 58310",
    "addr:housenumber":"1",
    "addr:postcode":"58310;58310",
    "addr:street":"Rte De Nevy Bp;Bourgogne",
    "iso:country":"FR",
    "sg:address":"Rte De Nevy BP 1 58310 St Amand En Puisaye",
    "sg:city":"Arquian",
    "sg:classifiers":[
        {
            "category":"Home & Garden",
            "subcategory":"Furniture",
            "type":"Retail Goods"
        }
    ],
    "sg:phone":"+33 3 86 39 56 00",
    "sg:postcode":"58310",
    "sg:province":"Bourgogne",
    "sg:tags":[
        "wood"
    ],
    "wof:name":"Parqueterie Du Beau Soleil Sa",
    "wof:placetype":"venue"
},
  "geometry": {"coordinates":[3.05575,47.480518],"type":"Point"}
}