{
  "type": "Feature",
  "properties": {
    "addr:full":"Mont\u00e9gut 87140 Compreignac Limousin 87140",
    "addr:postcode":"87140;87140",
    "iso:country":"FR",
    "sg:address":"Mont\u00e9gut 87140 Compreignac",
    "sg:classifiers":[
        {
            "category":"Wholesale",
            "subcategory":"Farm Supplies",
            "type":"Manufacturing & Wholesale Goods"
        }
    ],
    "sg:phone":"+33 5 55 71 00 93",
    "sg:postcode":"87140",
    "sg:province":"Limousin",
    "sg:tags":[
        "-",
        "machine",
        "equipment",
        "engineering",
        "machinery",
        "mechanical",
        "agriculture"
    ],
    "wof:name":"Clavaud Constructeur",
    "wof:placetype":"venue"
},
  "geometry": {"coordinates":[1.277645,45.964512],"type":"Point"}
}