{
  "type": "Feature",
  "properties": {
    "iso:country":"FR",
    "sg:address":"12 Rue Des Arbres 57360 Amn\u00e9ville Les Thermes",
    "sg:classifiers":[
        {
            "category":"Manufacturing",
            "subcategory":"Metals",
            "type":"Manufacturing & Wholesale Goods"
        }
    ],
    "sg:phone":"+33 3 87 71 00 03",
    "sg:postcode":"57360",
    "sg:province":"Lorraine",
    "sg:tags":[
        "metallurgy",
        "metalworking"
    ],
    "wof:name":"Haas Sarl",
    "wof:placetype":"venue"
},
  "geometry": {"coordinates":[6.1423,49.26086],"type":"Point"}
}