{
  "type": "Feature",
  "properties": {
    "iso:country":"FR",
    "sg:address":"8 Rue Carnot 54300 Luneville",
    "sg:classifiers":[
        {
            "category":"Professional",
            "subcategory":"Printing & Photocopies",
            "type":"Services"
        }
    ],
    "sg:phone":"+33 3 83 73 07 56",
    "sg:province":"Lorraine",
    "sg:tags":[
        "publishing"
    ],
    "wof:name":"Societe Du Journal L'est Republicain",
    "wof:placetype":"venue"
},
  "geometry": {"coordinates":[6.495817,48.589684],"type":"Point"}
}