{
  "type": "Feature",
  "properties": {
    "addr:full":"Rte R\u00e9almont 81300 Graulhet Midi Pyr\u00e9n\u00e9es 81300",
    "addr:postcode":"81300;81300",
    "addr:street":"Rte Re\u0301Almont",
    "iso:country":"FR",
    "sg:address":"Rte R\u00e9almont 81300 Graulhet",
    "sg:classifiers":[
        {
            "category":"Food Court",
            "type":"Food & Drink"
        }
    ],
    "sg:phone":"+33 5 63 42 14 41",
    "sg:postcode":"81300",
    "sg:province":"Midi Pyr\u00e9n\u00e9es",
    "sg:tags":[
        "product",
        "related"
    ],
    "wof:name":"Weishardt International Sarl",
    "wof:placetype":"venue"
},
  "geometry": {"coordinates":[2.00546,43.764225],"type":"Point"}
}