{
  "type": "Feature",
  "properties": {
    "addr:full":"Carri\u00e8re De Londaitzia 64240 Ayherre Ayherre Aquitaine 64240",
    "addr:postcode":"64240;64240",
    "iso:country":"FR",
    "sg:address":"Carri\u00e8re De Londaitzia 64240 Ayherre",
    "sg:city":"Ayherre",
    "sg:classifiers":[
        {
            "category":"Building & Trades",
            "subcategory":"Construction",
            "type":"Services"
        }
    ],
    "sg:phone":"+33 5 59 29 64 06",
    "sg:postcode":"64240",
    "sg:province":"Aquitaine",
    "sg:tags":[
        "work",
        "public"
    ],
    "wof:name":"Societe Des Travaux D'hasparren Sth",
    "wof:placetype":"venue"
},
  "geometry": {"coordinates":[-1.262661,43.387348],"type":"Point"}
}