{
  "type": "Feature",
  "properties": {
    "addr:full":"B.P. 9, 45490 Corbeilles^^Rte de Bordeaux, 45490 Corbeilles Corbeilles Centre 45490",
    "addr:housenumber":"9;corbeilles",
    "addr:postcode":"45490;45490;45490",
    "addr:street":"B.P.",
    "iso:country":"FR",
    "sg:address":"B.P. 9, 45490 Corbeilles^^Rte de Bordeaux, 45490 Corbeilles",
    "sg:city":"Corbeilles",
    "sg:orig_category":"Non-Classified Establishments",
    "sg:phone":"+33 2 38 92 20 73",
    "sg:postcode":"45490",
    "sg:province":"Centre",
    "wof:name":"Etablissements Deffaugt Et Fils S.a.",
    "wof:placetype":"venue"
},
  "geometry": {"coordinates":[2.623006,48.048569],"type":"Point"}
}