{
  "type": "Feature",
  "properties": {
    "addr:full":"4 Rue Jean Elys\u00e9e Dupuy 69410 Champagne Au Mont D'Or Rhone-Alpes 69410",
    "addr:housenumber":"4",
    "addr:postcode":"69410;69410",
    "addr:street":"Rue Jean Elyse\u0301E Dupuy;D'Or Rhone-Alpes",
    "iso:country":"FR",
    "sg:address":"4 Rue Jean Elys\u00e9e Dupuy 69410 Champagne Au Mont D'Or",
    "sg:orig_category":"Information Technology Office equipment Telecommunications Wood and Furniture",
    "sg:phone":"+33 4 78 66 24 50",
    "sg:postcode":"69410",
    "sg:province":"Rhone-Alpes",
    "wof:name":"Orgaco Sa",
    "wof:placetype":"venue"
},
  "geometry": {"coordinates":[-0.100754,47.869232],"type":"Point"}
}