{
  "type": "Feature",
  "properties": {
    "addr:full":"92517 Boulogne Billancourt^^12, Rue d'Anjou, Ancourt Haute Normandie 76370",
    "addr:postcode":"92517;76370",
    "addr:street":"Rue D'Anjou;Haute Normandie",
    "iso:country":"FR",
    "sg:address":"92517 Boulogne Billancourt^^12, Rue d'Anjou,",
    "sg:city":"Ancourt",
    "sg:orig_category":"Non-Classified Establishments",
    "sg:phone":"+33 1 46 10 90 90",
    "sg:postcode":"76370",
    "sg:province":"Haute Normandie",
    "wof:name":"Business Document S.a.",
    "wof:placetype":"venue"
},
  "geometry": {"coordinates":[2.351662,48.892944],"type":"Point"}
}