{
  "type": "Feature",
  "properties": {
    "iso:country":"FR",
    "sg:address":"25 R Desmazi\u00e8res 49000 Angers",
    "sg:classifiers":[
        {
            "category":"Professional",
            "subcategory":"Business Services",
            "type":"Services"
        }
    ],
    "sg:phone":"+33 2 41 66 95 31",
    "sg:postcode":"49000",
    "sg:province":"Pays de Loire",
    "sg:tags":[
        "body",
        "advice"
    ],
    "wof:name":"Ass Residence Noisetiers Oree Du Parc",
    "wof:placetype":"venue"
},
  "geometry": {"coordinates":[-0.536413,47.460625],"type":"Point"}
}