{
  "type": "Feature",
  "properties": {
    "addr:full":"9 place du Capitole 31000 Toulouse Midi Pyr\u00e9n\u00e9es",
    "addr:housenumber":"9",
    "addr:postcode":"31000",
    "addr:street":"Place Du Capitole",
    "iso:country":"FR",
    "sg:address":"9 place du Capitole 31000 Toulouse",
    "sg:classifiers":[
        {
            "category":"Shopping",
            "subcategory":"Jewelry",
            "type":"Retail Goods"
        }
    ],
    "sg:phone":"+33 5 62 68 93 33",
    "sg:province":"Midi Pyr\u00e9n\u00e9es",
    "sg:tags":[
        "watch"
    ],
    "wof:name":"Lip France Sarl",
    "wof:placetype":"venue"
},
  "geometry": {"coordinates":[1.442809,43.604019],"type":"Point"}
}