{
  "type": "Feature",
  "properties": {
    "addr:full":"93 Place Drouet D'Erlon 51100 Reims Champagne 51100",
    "addr:housenumber":"93",
    "addr:postcode":"51100;51100",
    "addr:street":"Place Drouet D'Erlon",
    "iso:country":"FR",
    "sg:address":"93 Place Drouet D'Erlon 51100 Reims",
    "sg:classifiers":[
        {
            "category":"Travel",
            "subcategory":"Hotels & Motels",
            "type":"Entertainment"
        }
    ],
    "sg:phone":"+33 3 26 40 39 35",
    "sg:postcode":"51100",
    "sg:province":"Champagne",
    "sg:tags":[
        "hotels",
        "business",
        "restaurant"
    ],
    "wof:name":"Grand Hotel Continental Sarl",
    "wof:placetype":"venue"
},
  "geometry": {"coordinates":[4.027317,49.255451],"type":"Point"}
}