{
  "type": "Feature",
  "properties": {
    "addr:full":"26 rue du Dominant 16100 ST LAURENT DE COGNAC Poitou-Charentes",
    "addr:housenumber":"26",
    "addr:postcode":"16100;cognac",
    "addr:street":"Rue Du Dominant",
    "iso:country":"FR",
    "sg:address":"26 rue du Dominant 16100 ST LAURENT DE COGNAC",
    "sg:classifiers":[
        {
            "category":"Home & Garden",
            "subcategory":"Hardware",
            "type":"Retail Goods"
        }
    ],
    "sg:phone":"+33 5 45 32 07 00",
    "sg:province":"Poitou-Charentes",
    "sg:tags":[
        "produced",
        "spirit",
        "specialities"
    ],
    "wof:name":"Sncpeva S.a.",
    "wof:placetype":"venue"
},
  "geometry": {"coordinates":[-0.317519,45.687084],"type":"Point"}
}