{
  "type": "Feature",
  "properties": {
    "iso:country":"FR",
    "sg:address":"1, Place Jacques Balmat, 74400 Chamonix Mont Blanc",
    "sg:orig_category":"Non-Classified Establishments",
    "sg:phone":"+33 4 50 53 30 25",
    "sg:postcode":"74400",
    "sg:province":"Rhone-Alpes",
    "wof:name":"Banque De Savoie",
    "wof:placetype":"venue"
},
  "geometry": {"coordinates":[6.869838,45.923328],"type":"Point"}
}