{
  "type": "Feature",
  "properties": {
    "iso:country":"FR",
    "sg:address":"26 Rte De Canta Gallet 06200 Nice",
    "sg:classifiers":[
        {
            "category":"Professional",
            "subcategory":"Business Services",
            "type":"Services"
        }
    ],
    "sg:phone":"+33 4 93 86 81 60",
    "sg:tags":[
        "pharmaceutical",
        "advice",
        "-",
        "chemical",
        "chemistry",
        "energy",
        "by-product"
    ],
    "wof:name":"Bollore Energie",
    "wof:placetype":"venue"
},
  "geometry": {"coordinates":[7.23076,43.69775],"type":"Point"}
}