{
  "type": "Feature",
  "properties": {
    "iso:country":"FR",
    "sg:address":"Zone d'activit\u00e9 de Migelane 33650 SAUCATS",
    "sg:city":"Saucats",
    "sg:orig_category":"Dial Indicators",
    "sg:phone":"+33 5 57 97 17 97",
    "sg:postcode":"33650",
    "sg:province":"Aquitaine",
    "wof:name":"A Puissance 3",
    "wof:placetype":"venue"
},
  "geometry": {"coordinates":[-0.59647,44.651451],"type":"Point"}
}