{
  "type": "Feature",
  "properties": {
    "iso:country":"FR",
    "sg:address":"82, Av. de Paris, 91790 Boissy Sous Saint Yon",
    "sg:orig_category":"Unclassifiable Establishments",
    "sg:phone":"+33 1 60 82 01 75",
    "sg:province":"Ile de France",
    "wof:name":"Cars Fleury S.a.r.l.",
    "wof:placetype":"venue"
},
  "geometry": {"coordinates":[2.21425,48.545319],"type":"Point"}
}