{
  "type": "Feature",
  "properties": {
    "addr:full":"78, Rue des Forges, 67110 Reichshoffen Reichshoffen Alsace 67110",
    "addr:housenumber":"78",
    "addr:postcode":"67110;67110",
    "addr:street":"Rue Des Forges",
    "iso:country":"FR",
    "sg:address":"78, Rue des Forges, 67110 Reichshoffen",
    "sg:city":"Reichshoffen",
    "sg:orig_category":"Chanfreiner, Machines \u00e0 Etudes et fabrications de machines sp\u00e9ciales Machines d'usinage sp\u00e9ciales Ma",
    "sg:phone":"+33 3 88 80 32 66",
    "sg:postcode":"67110",
    "sg:province":"Alsace",
    "wof:name":"Suhner France S.a.",
    "wof:placetype":"venue"
},
  "geometry": {"coordinates":[7.648134,48.914799],"type":"Point"}
}