{
  "type": "Feature",
  "properties": {
    "addr:full":"ZI Sarre Union Alsace 67260",
    "addr:postcode":"67260",
    "addr:street":"Zi Sarre Union",
    "iso:country":"FR",
    "sg:address":"ZI",
    "sg:city":"Sarre Union",
    "sg:orig_category":"Unclassifiable Establishments",
    "sg:phone":"+33 3 88 01 14 19",
    "sg:postcode":"67260",
    "sg:province":"Alsace",
    "wof:name":"Bruder - Keller S.a.",
    "wof:placetype":"venue"
},
  "geometry": {"coordinates":[7.0869,48.939201],"type":"Point"}
}