{
  "type": "Feature",
  "properties": {
    "iso:country":"FR",
    "sg:address":"10, Rue des Cl\u00e9rimois - ZI des Vauguillettes, 89100 Sens",
    "sg:city":"Sens",
    "sg:orig_category":"Non-Classified Establishments",
    "sg:phone":"+33 3 86 83 15 50",
    "sg:postcode":"89100",
    "sg:province":"Bourgogne",
    "wof:name":"Lef\u00e8vre Jacques S.a.",
    "wof:placetype":"venue"
},
  "geometry": {"coordinates":[3.3115,48.150352],"type":"Point"}
}