{
  "type": "Feature",
  "properties": {
    "iso:country":"FR",
    "sg:address":"65 Rue Baron Leroy 75012 Paris",
    "sg:classifiers":[
        {
            "category":"Professional",
            "type":"Services"
        }
    ],
    "sg:phone":"+33 1 53 17 18 60",
    "sg:province":"Ile de France",
    "sg:tags":[
        "transport",
        "road"
    ],
    "wof:name":"Transports Rapides J Besson Et Compagnie",
    "wof:placetype":"venue"
},
  "geometry": {"coordinates":[2.38789,48.834728],"type":"Point"}
}