{
  "type": "Feature",
  "properties": {
    "addr:full":"Dumont St Pierre Rte Champigny 15430 Tinqueux Cussac Auvergne 15430",
    "addr:postcode":"15430;cussac;15430",
    "addr:street":"Dumont;Rte Champigny",
    "iso:country":"FR",
    "sg:address":"Dumont St Pierre Rte Champigny 15430 Tinqueux",
    "sg:city":"Cussac",
    "sg:classifiers":[
        {
            "category":"Manufacturing",
            "subcategory":"Printing",
            "type":"Manufacturing & Wholesale Goods"
        }
    ],
    "sg:phone":"+33 3 26 08 00 46",
    "sg:postcode":"15430",
    "sg:province":"Auvergne",
    "sg:tags":[
        "publishing"
    ],
    "wof:name":"Hebdoprint",
    "wof:placetype":"venue"
},
  "geometry": {"coordinates":[2.904586,45.006706],"type":"Point"}
}