{
  "type": "Feature",
  "properties": {
    "addr:full":"B.P. 581, 69637 V\u00e9nissieux C\u00e9dex^^22, Rue Eug\u00e8ne H\u00e9naff, 69200 V\u00e9nissieux Rhone-Alpes 69200",
    "addr:housenumber":"b.p. 581",
    "addr:postcode":"69637;69200;69200",
    "addr:street":"Rue Euge\u0300Ne He\u0301Naff",
    "iso:country":"FR",
    "sg:address":"B.P. 581, 69637 V\u00e9nissieux C\u00e9dex^^22, Rue Eug\u00e8ne H\u00e9naff, 69200 V\u00e9nissieux",
    "sg:orig_category":"Non-Classified Establishments",
    "sg:phone":"+33 4 72 21 24 50",
    "sg:postcode":"69200",
    "sg:province":"Rhone-Alpes",
    "wof:name":"Antia S.a.",
    "wof:placetype":"venue"
},
  "geometry": {"coordinates":[4.885109,45.696575],"type":"Point"}
}