{
  "type": "Feature",
  "properties": {
    "addr:full":"Rue de la Lib\u00e9ration Eloyes Lorraine 88510",
    "addr:postcode":"88510",
    "addr:street":"Rue De La Libe\u0301Ration Eloyes Lorraine",
    "iso:country":"FR",
    "sg:address":"Rue de la Lib\u00e9ration",
    "sg:city":"Eloyes",
    "sg:orig_category":"Non-Classified Establishments",
    "sg:phone":"+33 3 29 32 40 28",
    "sg:postcode":"88510",
    "sg:province":"Lorraine",
    "wof:name":"Humbert P\u00e8re Et Fils S.a.",
    "wof:placetype":"venue"
},
  "geometry": {"coordinates":[6.611425,48.095509],"type":"Point"}
}