{
  "type": "Feature",
  "properties": {
    "addr:full":"B.P. 143, 12101 Millau C\u00e9dex 01^^Z.I. Plaine des Ondes, 12100 Millau Midi Pyr\u00e9n\u00e9es 12100",
    "addr:housenumber":"b.p. 143",
    "addr:postcode":"12101;12100;12100",
    "addr:street":"Plaine Des Ondes",
    "iso:country":"FR",
    "sg:address":"B.P. 143, 12101 Millau C\u00e9dex 01^^Z.I. Plaine des Ondes, 12100 Millau",
    "sg:orig_category":"Non-Classified Establishments",
    "sg:phone":"+33 5 65 59 23 00",
    "sg:postcode":"12100",
    "sg:province":"Midi Pyr\u00e9n\u00e9es",
    "wof:name":"Canat S.a.",
    "wof:placetype":"venue"
},
  "geometry": {"coordinates":[2.98414,44.063969],"type":"Point"}
}