{
  "type": "Feature",
  "properties": {
    "iso:country":"FR",
    "sg:address":"38 Rue Des Jardins 57940 Volstroff",
    "sg:classifiers":[
        {
            "category":"Manufacturing",
            "subcategory":"Rubber & Plastics",
            "type":"Manufacturing & Wholesale Goods"
        }
    ],
    "sg:phone":"+33 3 82 56 93 75",
    "sg:province":"Lorraine",
    "wof:name":"Sovulor",
    "wof:placetype":"venue"
},
  "geometry": {"coordinates":[6.258866,49.311611],"type":"Point"}
}