{
  "type": "Feature",
  "properties": {
    "iso:country":"FR",
    "sg:address":"5, Rue de la T\u00e9l\u00e9matique, 42000 Saint Etienne",
    "sg:orig_category":"Non-Classified Establishments",
    "sg:phone":"+33 4 77 91 49 49",
    "sg:postcode":"42000",
    "sg:province":"Rhone-Alpes",
    "wof:name":"Bricauto S.a.",
    "wof:placetype":"venue"
},
  "geometry": {"coordinates":[4.392561,45.455826],"type":"Point"}
}