{
  "type": "Feature",
  "properties": {
    "addr:full":"21 Igny 92140 Clamart Ile de France 92140",
    "addr:housenumber":"21",
    "addr:postcode":"92140;ile;92140",
    "addr:street":"Igny;France",
    "iso:country":"FR",
    "sg:address":"21",
    "sg:city":"Igny 92140 Clamart",
    "sg:classifiers":[
        {
            "category":"Shopping",
            "subcategory":"Clothing, Apparel, & Fashions",
            "type":"Retail Goods"
        }
    ],
    "sg:phone":"+33 1 46 31 52 23",
    "sg:postcode":"92140",
    "sg:province":"Ile de France",
    "sg:tags":[
        "textile",
        "clothing",
        "clothes"
    ],
    "wof:name":"Ovalice (sarl)",
    "wof:placetype":"venue"
},
  "geometry": {"coordinates":[2.249971,48.784279],"type":"Point"}
}