{
  "type": "Feature",
  "properties": {
    "iso:country":"FR",
    "sg:address":"RN 6",
    "sg:city":"Saint Laurent de M\u00fbre",
    "sg:orig_category":"Unclassifiable Establishments",
    "sg:phone":"+33 4 37 25 82 82",
    "sg:postcode":"69720",
    "sg:province":"Rhone-Alpes",
    "wof:name":"G\u00e9odis Logistics Euromatic S.a.",
    "wof:placetype":"venue"
},
  "geometry": {"coordinates":[5.037474,45.690609],"type":"Point"}
}