{
  "type": "Feature",
  "properties": {
    "addr:full":"avenue de Belle Fontaine 64200 Biarritz Biarritz Aquitaine 64200",
    "addr:postcode":"64200;64200",
    "addr:street":"Avenue De Belle Fontaine",
    "iso:country":"FR",
    "sg:address":"avenue de Belle Fontaine 64200 Biarritz",
    "sg:city":"Biarritz",
    "sg:classifiers":[
        {
            "category":"Professional",
            "type":"Services"
        }
    ],
    "sg:phone":"+33 5 59 23 16 16",
    "sg:postcode":"64200",
    "sg:province":"Aquitaine",
    "sg:tags":[
        "transport"
    ],
    "wof:name":"Transports Destandau Sa",
    "wof:placetype":"venue"
},
  "geometry": {"coordinates":[-1.558758,43.4753],"type":"Point"}
}