{
  "type": "Feature",
  "properties": {
    "addr:full":"Za Les Dineux Rn 12 Bp30 22250 Tremeur Tr\u00e9meur Bretagne 22250",
    "addr:postcode":"22250;22250",
    "addr:street":"Za Les;Rn 12 Bp30;Tre\u0301Meur",
    "iso:country":"FR",
    "sg:address":"Za Les Dineux Rn 12 Bp30 22250 Tremeur",
    "sg:city":"Tr\u00e9meur",
    "sg:classifiers":[
        {
            "category":"Autos & Motor Vehicles",
            "subcategory":"Automobile Sales",
            "type":"Retail Goods"
        }
    ],
    "sg:phone":"+33 2 96 84 65 63",
    "sg:postcode":"22250",
    "sg:province":"Bretagne",
    "sg:tags":[
        "equipment",
        "motor-cars",
        "transport"
    ],
    "wof:name":"Carrosserie Guitton",
    "wof:placetype":"venue"
},
  "geometry": {"coordinates":[-2.263419,48.347321],"type":"Point"}
}