{
  "type": "Feature",
  "properties": {
    "addr:full":"8, Square Newton, 78180 Montigny le Bretonneux Ile de France",
    "addr:housenumber":"8",
    "addr:postcode":"78180",
    "addr:street":"Square Newton",
    "iso:country":"FR",
    "sg:address":"8, Square Newton, 78180 Montigny le Bretonneux",
    "sg:orig_category":"Unclassifiable Establishments",
    "sg:phone":"+33 1 30 85 87 00",
    "sg:province":"Ile de France",
    "wof:name":"Connecteurs C.i.n.c.h. S.a.",
    "wof:placetype":"venue"
},
  "geometry": {"coordinates":[2.04465,48.791821],"type":"Point"}
}