{
  "type": "Feature",
  "properties": {
    "addr:full":"45, Rue de Vauquois, 45000 Orl\u00e9ans Orl\u00e9ans Centre 45000",
    "addr:housenumber":"45",
    "addr:postcode":"45000;45000",
    "addr:street":"Rue De Vauquois",
    "iso:country":"FR",
    "sg:address":"45, Rue de Vauquois, 45000 Orl\u00e9ans",
    "sg:city":"Orl\u00e9ans",
    "sg:orig_category":"Unclassifiable Establishments",
    "sg:phone":"+33 2 38 77 42 42",
    "sg:postcode":"45000",
    "sg:province":"Centre",
    "wof:name":"M.d. S.a. - Molfox Depigny",
    "wof:placetype":"venue"
},
  "geometry": {"coordinates":[1.890258,47.903667],"type":"Point"}
}