{
  "type": "Feature",
  "properties": {
    "addr:full":"19 rue L\u00e9onard Masse 60510 Therdonne Picardie",
    "addr:housenumber":"19",
    "addr:postcode":"60510",
    "addr:street":"Rue Le\u0301Onard Masse",
    "iso:country":"FR",
    "sg:address":"19 rue L\u00e9onard Masse 60510 Therdonne",
    "sg:classifiers":[
        {
            "category":"Education",
            "subcategory":"Dance Studio",
            "type":"Public Place"
        }
    ],
    "sg:phone":"+33 3 44 07 34 34",
    "sg:province":"Picardie",
    "sg:tags":[
        "spring",
        "special-purpose"
    ],
    "wof:name":"Les Ressorts De L'oise Sa",
    "wof:placetype":"venue"
},
  "geometry": {"coordinates":[2.159135,49.417122],"type":"Point"}
}