{
  "type": "Feature",
  "properties": {
    "addr:full":"10 Cudos Aquitaine 33430",
    "addr:housenumber":"10",
    "addr:postcode":"33430",
    "iso:country":"FR",
    "sg:address":"10",
    "sg:city":"Cudos",
    "sg:classifiers":[
        {
            "category":"Home & Garden",
            "subcategory":"Furniture",
            "type":"Retail Goods"
        }
    ],
    "sg:phone":"+33 5 56 25 24 44",
    "sg:postcode":"33430",
    "sg:province":"Aquitaine",
    "sg:tags":[
        "wood"
    ],
    "wof:name":"Caisserie Du Bazadais",
    "wof:placetype":"venue"
},
  "geometry": {"coordinates":[-0.254911,44.376896],"type":"Point"}
}