{
  "type": "Feature",
  "properties": {
    "iso:country":"FR",
    "sg:address":"B.P. 194, 62254 H\u00e9nin Beaumont C\u00e9dex^^Rue Jules Verne, 62110 H\u00e9nin Beaumont",
    "sg:orig_category":"Non-Classified Establishments",
    "sg:phone":"+33 3 21 20 14 20",
    "sg:postcode":"62110",
    "sg:province":"Nord Pas-de-Calais",
    "wof:name":"E.c.i. S.a. - Europ\u00e9enne De Composites Industriels",
    "wof:placetype":"venue"
},
  "geometry": {"coordinates":[2.947094,50.41885],"type":"Point"}
}