{
  "type": "Feature",
  "properties": {
    "iso:country":"FR",
    "sg:address":"B.P. 12",
    "sg:city":"Marssac sur Tarn^^81150 Marssac sur Tarn",
    "sg:orig_category":"Non-Classified Establishments",
    "sg:phone":"+33 5 63 53 73 73",
    "sg:postcode":"81150",
    "sg:province":"Midi Pyr\u00e9n\u00e9es",
    "wof:name":"C.c.l. S.c.a. - Cave De Labastide De Levis",
    "wof:placetype":"venue"
},
  "geometry": {"coordinates":[2.066139,43.883747],"type":"Point"}
}