{
  "type": "Feature",
  "properties": {
    "addr:full":"3 Et 5 Av De Fondeyre 31200 Toulouse Midi Pyr\u00e9n\u00e9es 31200",
    "addr:housenumber":"3 et",
    "addr:postcode":"31200;31200",
    "addr:street":"Av De Fondeyre",
    "iso:country":"FR",
    "sg:address":"3 Et 5 Av De Fondeyre 31200 Toulouse",
    "sg:classifiers":[
        {
            "category":"Shopping",
            "subcategory":"Clothing, Apparel, & Fashions",
            "type":"Retail Goods"
        }
    ],
    "sg:phone":"+33 5 34 40 71 71",
    "sg:postcode":"31200",
    "sg:province":"Midi Pyr\u00e9n\u00e9es",
    "sg:tags":[
        "textile",
        "clothing",
        "clothes"
    ],
    "wof:name":"Texenergie",
    "wof:placetype":"venue"
},
  "geometry": {"coordinates":[1.44954,43.639011],"type":"Point"}
}