{
  "type": "Feature",
  "properties": {
    "iso:country":"FR",
    "sg:address":"B.P. 2, 81120 R\u00e9almont^^Le Rivet, 81120 R\u00e9almont",
    "sg:orig_category":"Non-Classified Establishments",
    "sg:phone":"+33 5 63 55 51 29",
    "sg:postcode":"81120",
    "sg:province":"Midi Pyr\u00e9n\u00e9es",
    "wof:name":"Bessac T.p.c. S.a.",
    "wof:placetype":"venue"
},
  "geometry": {"coordinates":[2.288703,43.764061],"type":"Point"}
}