{
  "type": "Feature",
  "properties": {
    "addr:full":"Zac Du Nouveau Monde Romaine 57300 Hagondange Lorraine 57300",
    "addr:postcode":"57300;57300",
    "addr:street":"Zac Du Nouveau Monde Romaine",
    "iso:country":"FR",
    "sg:address":"Zac Du Nouveau Monde",
    "sg:city":"Romaine 57300 Hagondange",
    "sg:classifiers":[
        {
            "category":"Building & Trades",
            "subcategory":"Construction",
            "type":"Services"
        }
    ],
    "sg:phone":"+33 3 87 51 48 30",
    "sg:postcode":"57300",
    "sg:province":"Lorraine",
    "sg:tags":[
        "work",
        "public"
    ],
    "wof:name":"Trabet Lorraine",
    "wof:placetype":"venue"
},
  "geometry": {"coordinates":[6.16994,49.254086],"type":"Point"}
}