{
  "type": "Feature",
  "properties": {
    "iso:country":"FR",
    "sg:address":"7, Rue Vinatier, 69500 Bron",
    "sg:orig_category":"Non-Classified Establishments",
    "sg:phone":"+33 4 72 68 69 00",
    "sg:postcode":"69500",
    "sg:province":"Rhone-Alpes",
    "wof:name":"Groupe Lepine S.a.",
    "wof:placetype":"venue"
},
  "geometry": {"coordinates":[4.897945,45.751705],"type":"Point"}
}