{
  "type": "Feature",
  "properties": {
    "iso:country":"FR",
    "sg:address":"13 Rue Epinette 77165 St Soupplets",
    "sg:classifiers":[
        {
            "category":"Wholesale",
            "subcategory":"Medical Equipment & Supplies",
            "type":"Manufacturing & Wholesale Goods"
        }
    ],
    "sg:phone":"+33 1 60 01 35 36",
    "sg:postcode":"77165",
    "sg:province":"Ile de France",
    "sg:tags":[
        "instrument",
        "health",
        "-",
        "precision"
    ],
    "wof:name":"Societe Francaise Des Produits D'hygiene Sarl (sfph)",
    "wof:placetype":"venue"
},
  "geometry": {"coordinates":[2.798238,49.037739],"type":"Point"}
}