{
  "type": "Feature",
  "properties": {
    "addr:full":"7, Square Paul Doumer, 02400 Ch\u00e2teau Thierry Picardie",
    "addr:housenumber":"7",
    "addr:postcode":"02400",
    "addr:street":"Square Paul Doumer",
    "iso:country":"FR",
    "sg:address":"7, Square Paul Doumer, 02400 Ch\u00e2teau Thierry",
    "sg:orig_category":"Unclassifiable Establishments",
    "sg:phone":"+33 3 23 83 16 00",
    "sg:province":"Picardie",
    "wof:name":"Gl Bureau Tout Pour Le Bureau",
    "wof:placetype":"venue"
},
  "geometry": {"coordinates":[3.404057,49.040039],"type":"Point"}
}