{
  "type": "Feature",
  "properties": {
    "iso:country":"FR",
    "sg:address":"Chemin Eve 60950 Ermenonville",
    "sg:classifiers":[
        {
            "category":"Building & Trades",
            "subcategory":"Construction",
            "type":"Services"
        }
    ],
    "sg:phone":"+33 3 44 54 00 33",
    "sg:postcode":"60950",
    "sg:province":"Picardie",
    "sg:tags":[
        "work",
        "public"
    ],
    "wof:name":"Supersol",
    "wof:placetype":"venue"
},
  "geometry": {"coordinates":[2.701749,49.11805],"type":"Point"}
}