{
  "type": "Feature",
  "properties": {
    "iso:country":"FR",
    "sg:address":"12, Rue du S\u00e9minaire, 94550 Rungis",
    "sg:orig_category":"Non-Classified Establishments",
    "sg:phone":"+33 1 45 60 43 75",
    "sg:postcode":"94550",
    "sg:province":"Ile de France",
    "wof:name":"Creyf's Int\u00e9rim S.a.",
    "wof:placetype":"venue"
},
  "geometry": {"coordinates":[-121.659882,37.546101],"type":"Point"}
}