{
  "type": "Feature",
  "properties": {
    "addr:full":"11, Cit\u00e9 Malesherbes, 75009 Paris Ile de France",
    "addr:housenumber":"11",
    "addr:postcode":"75009",
    "addr:street":"Cite\u0301 Malesherbes",
    "iso:country":"FR",
    "sg:address":"11, Cit\u00e9 Malesherbes, 75009 Paris",
    "sg:orig_category":"Unclassifiable Establishments",
    "sg:phone":"+33 1 53 20 19 00",
    "sg:province":"Ile de France",
    "wof:name":"Soner\u00e8me S.a.s.",
    "wof:placetype":"venue"
},
  "geometry": {"coordinates":[2.338836,48.880955],"type":"Point"}
}