{
  "type": "Feature",
  "properties": {
    "addr:full":"B.P. 24, 50700 Valognes^^Rue Burnouf, 50700 Valognes Valognes Basse Normandie 50700",
    "addr:postcode":"50700;50700;50700",
    "addr:street":"B.P. 24;Burnouf",
    "iso:country":"FR",
    "sg:address":"B.P. 24, 50700 Valognes^^Rue Burnouf, 50700 Valognes",
    "sg:city":"Valognes",
    "sg:orig_category":"Non-Classified Establishments",
    "sg:phone":"+33 2 33 40 13 86",
    "sg:postcode":"50700",
    "sg:province":"Basse Normandie",
    "wof:name":"Brunot-tant\u00f4t Guy S.a.",
    "wof:placetype":"venue"
},
  "geometry": {"coordinates":[-1.43503,49.451469],"type":"Point"}
}