{
  "type": "Feature",
  "properties": {
    "addr:full":"87 Rue Du Marais 62157 ALLOUAGNE Nord Pas-de-Calais",
    "addr:housenumber":"87",
    "addr:postcode":"62157",
    "addr:street":"Rue Du Marais",
    "iso:country":"FR",
    "sg:address":"87 Rue Du Marais 62157 ALLOUAGNE",
    "sg:classifiers":[
        {
            "category":"Farming",
            "subcategory":"Livestock Farm",
            "type":"Manufacturing & Wholesale Goods"
        }
    ],
    "sg:phone":"+33 3 21 64 33 71",
    "sg:province":"Nord Pas-de-Calais",
    "sg:tags":[
        "breeding",
        "pig"
    ],
    "wof:name":"Albert & Paul Dehosse Sarl",
    "wof:placetype":"venue"
},
  "geometry": {"coordinates":[2.52959,50.541523],"type":"Point"}
}