{
  "type": "Feature",
  "properties": {
    "addr:full":"36 boulevard Charles de Gaulle 49800 Trelaze Pays de Loire 49800",
    "addr:housenumber":"36",
    "addr:postcode":"49800;49800",
    "addr:street":"Boulevard Charles De Gaulle;Trelaze",
    "iso:country":"FR",
    "sg:address":"36 boulevard Charles de Gaulle 49800 Trelaze",
    "sg:classifiers":[
        {
            "category":"Shopping",
            "subcategory":"Florist",
            "type":"Retail Goods"
        }
    ],
    "sg:phone":"+33 2 41 34 00 52",
    "sg:postcode":"49800",
    "sg:province":"Pays de Loire",
    "sg:tags":[
        "decoration",
        "article"
    ],
    "wof:name":"Embafleur Et Cie Sarl",
    "wof:placetype":"venue"
},
  "geometry": {"coordinates":[-0.481011,47.453835],"type":"Point"}
}