{
  "type": "Feature",
  "properties": {
    "addr:full":"3, Rue Micha\u00ebl Faraday, 78180 Montigny le Bretonneux Ile de France",
    "addr:housenumber":"3",
    "addr:postcode":"78180",
    "addr:street":"Rue Michae\u0308L",
    "iso:country":"FR",
    "sg:address":"3, Rue Micha\u00ebl Faraday, 78180 Montigny le Bretonneux",
    "sg:orig_category":"Non-Classified Establishments",
    "sg:phone":"+33 1 30 85 55 66",
    "sg:province":"Ile de France",
    "wof:name":"Soci\u00e9t\u00e9 D'exploitation Sectrad S.a.",
    "wof:placetype":"venue"
},
  "geometry": {"coordinates":[2.04977,48.7952],"type":"Point"}
}