{
  "type": "Feature",
  "properties": {
    "addr:full":"11-13 place Nationale; Dieppe; 76200 Haute Normandie 76200",
    "addr:housenumber":"11-13",
    "addr:postcode":"76200;76200",
    "addr:street":"Place Nationale Dieppe;Normandie",
    "iso:country":"FR",
    "sg:address":"11-13 place Nationale; Dieppe; 76200",
    "sg:classifiers":[
        {
            "category":"Banks & Credit Unions",
            "subcategory":"Bank",
            "type":"Services"
        }
    ],
    "sg:phone":"+33 2 35 82 88 33",
    "sg:postcode":"76200",
    "sg:province":"Haute Normandie",
    "wof:name":"Bred Banque Populaire",
    "wof:placetype":"venue"
},
  "geometry": {"coordinates":[1.077846,49.926628],"type":"Point"}
}