{
  "type": "Feature",
  "properties": {
    "iso:country":"FR",
    "sg:address":"23 R Stanislas 68000 Colmar",
    "sg:city":"Colmar",
    "sg:classifiers":[
        {
            "category":"Autos & Motor Vehicles",
            "subcategory":"Automobile Sales",
            "type":"Retail Goods"
        }
    ],
    "sg:phone":"+33 3 89 24 42 67",
    "sg:postcode":"68000",
    "sg:province":"Alsace",
    "sg:tags":[
        "equipment",
        "transport"
    ],
    "wof:name":"Zimmermann Motorcycles Eurl",
    "wof:placetype":"venue"
},
  "geometry": {"coordinates":[7.352668,48.08078],"type":"Point"}
}