{
  "type": "Feature",
  "properties": {
    "iso:country":"FR",
    "sg:address":"33 rue des Chardonnerets 95950 ROISSY CH DE GAULLE CEDEX",
    "sg:orig_category":"Gaskets, Washers, Seals",
    "sg:phone":"+33 1 48 63 20 80",
    "sg:province":"Franche Comt\u00e9",
    "wof:name":"Angst + Pfister Sa",
    "wof:placetype":"venue"
},
  "geometry": {"coordinates":[-121.894348,39.074108],"type":"Point"}
}