{
  "type": "Feature",
  "properties": {
    "addr:full":"Rte Du Marais Zi 76340 Blangy Sur Bresle Haute Normandie",
    "addr:postcode":"76340",
    "addr:street":"Rte Du Marais Zi;Haute Normandie",
    "iso:country":"FR",
    "sg:address":"Rte Du Marais Zi 76340 Blangy Sur Bresle",
    "sg:classifiers":[
        {
            "category":"Manufacturing",
            "subcategory":"Printing",
            "type":"Manufacturing & Wholesale Goods"
        }
    ],
    "sg:phone":"+33 2 32 97 41 11",
    "sg:province":"Haute Normandie",
    "sg:tags":[
        "publishing"
    ],
    "wof:name":"Euro Decor 93",
    "wof:placetype":"venue"
},
  "geometry": {"coordinates":[1.593718,49.821468],"type":"Point"}
}