{
  "type": "Feature",
  "properties": {
    "iso:country":"FR",
    "sg:address":"1, Rue Jean Monnet, 60000 Beauvais",
    "sg:orig_category":"Non-Classified Establishments",
    "sg:phone":"+33 3 44 10 00 35",
    "sg:postcode":"60000",
    "sg:province":"Picardie",
    "wof:name":"Becip S.a.r.l.",
    "wof:placetype":"venue"
},
  "geometry": {"coordinates":[2.10163,49.445412],"type":"Point"}
}