{
  "type": "Feature",
  "properties": {
    "addr:full":"1, Rue Jean Monnet, 60000 Beauvais Picardie 60000",
    "addr:housenumber":"1",
    "addr:postcode":"60000;60000",
    "addr:street":"Rue Jean Monnet",
    "iso:country":"FR",
    "sg:address":"1, Rue Jean Monnet, 60000 Beauvais",
    "sg:orig_category":"Non-Classified Establishments",
    "sg:phone":"+33 3 44 10 00 35",
    "sg:postcode":"60000",
    "sg:province":"Picardie",
    "wof:name":"Becip S.a.r.l.",
    "wof:placetype":"venue"
},
  "geometry": {"coordinates":[2.10163,49.445412],"type":"Point"}
}