{
  "type": "Feature",
  "properties": {
    "iso:country":"FR",
    "sg:address":"Rue Emile Zola",
    "sg:city":"Romilly sur Seine",
    "sg:orig_category":"Unclassifiable Establishments",
    "sg:phone":"+33 3 25 24 72 88",
    "sg:postcode":"10100",
    "sg:province":"Champagne",
    "wof:name":"Textiles Essor S.a.r.l.",
    "wof:placetype":"venue"
},
  "geometry": {"coordinates":[3.72886,48.500889],"type":"Point"}
}