{
  "type": "Feature",
  "properties": {
    "iso:country":"FR",
    "sg:address":"B.P. 7164",
    "sg:city":"Tours C\u00e9dex 2^^Les Grands Champs 37390 Chanceaux sur Choisille",
    "sg:orig_category":"Non-Classified Establishments",
    "sg:phone":"+33 2 47 88 42 42",
    "sg:postcode":"37071",
    "sg:province":"Centre",
    "wof:name":"Pl\u00e9e Construction S.a.",
    "wof:placetype":"venue"
},
  "geometry": {"coordinates":[0.578275,47.445446],"type":"Point"}
}