{
  "type": "Feature",
  "properties": {
    "addr:full":"83790 Pignans Franche Comt\u00e9",
    "addr:postcode":"83790",
    "addr:street":"Franche Comte\u0301",
    "iso:country":"FR",
    "sg:address":"83790 Pignans",
    "sg:orig_category":"Unclassifiable Establishments",
    "sg:phone":"+33 4 94 48 80 45",
    "sg:province":"Franche Comt\u00e9",
    "wof:name":"Domaine De Rimauresq S.a.",
    "wof:placetype":"venue"
},
  "geometry": {"coordinates":[6.22559,43.300514],"type":"Point"}
}