{
  "type": "Feature",
  "properties": {
    "addr:full":"34, Rue R\u00e9aumur, 75003 Paris Ile de France",
    "addr:housenumber":"34",
    "addr:postcode":"75003",
    "addr:street":"Rue Re\u0301Aumur",
    "iso:country":"FR",
    "sg:address":"34, Rue R\u00e9aumur, 75003 Paris",
    "sg:orig_category":"Unclassifiable Establishments",
    "sg:phone":"+33 1 42 72 28 23",
    "sg:province":"Ile de France",
    "wof:name":"Lapidaire France S.a.",
    "wof:placetype":"venue"
},
  "geometry": {"coordinates":[2.357692,48.865341],"type":"Point"}
}