{
  "type": "Feature",
  "properties": {
    "addr:full":"Les Muronnes 01240 Lent Rhone-Alpes",
    "addr:postcode":"01240",
    "iso:country":"FR",
    "sg:address":"Les Muronnes 01240 Lent",
    "sg:orig_category":"Unclassifiable Establishments",
    "sg:phone":"+33 4 74 52 74 30",
    "sg:province":"Rhone-Alpes",
    "wof:name":"Entreprise Fremion Michel Peinture",
    "wof:placetype":"venue"
},
  "geometry": {"coordinates":[5.16483,46.100128],"type":"Point"}
}