{
  "type": "Feature",
  "properties": {
    "addr:full":"La Rouvi\u00e8re 48100 Le Buisson Languedoc-Roussillon",
    "addr:postcode":"48100",
    "iso:country":"FR",
    "sg:address":"La Rouvi\u00e8re 48100 Le Buisson",
    "sg:orig_category":"Unclassifiable Establishments",
    "sg:phone":"+33 4 66 32 17 37",
    "sg:province":"Languedoc-Roussillon",
    "wof:name":"Etablissements Salles G\u00e9rard S.a.r.l.",
    "wof:placetype":"venue"
},
  "geometry": {"coordinates":[3.264506,44.623394],"type":"Point"}
}