{
  "type": "Feature",
  "properties": {
    "addr:full":"Rte de Fleury Perrigny Perrigny Bourgogne 89000",
    "addr:postcode":"89000",
    "addr:street":"Rte De Fleury",
    "iso:country":"FR",
    "sg:address":"Rte de Fleury Perrigny",
    "sg:city":"Perrigny",
    "sg:orig_category":"Unclassifiable Establishments",
    "sg:phone":"+33 3 86 46 89 32",
    "sg:postcode":"89000",
    "sg:province":"Bourgogne",
    "wof:name":"Bergerat Monnoyeur Travaux Publics S.a.",
    "wof:placetype":"venue"
},
  "geometry": {"coordinates":[3.558752,47.814449],"type":"Point"}
}