{
  "type": "Feature",
  "properties": {
    "iso:country":"FR",
    "sg:address":"Av Du Gal De Gaulle 35580 Guichen",
    "sg:city":"Guichen",
    "sg:classifiers":[
        {
            "category":"Professional",
            "subcategory":"Business Services",
            "type":"Services"
        }
    ],
    "sg:phone":"+33 2 99 57 02 61",
    "sg:postcode":"35580",
    "sg:province":"Bretagne",
    "sg:tags":[
        "training",
        "advice"
    ],
    "wof:name":"College Noel Du Fail",
    "wof:placetype":"venue"
},
  "geometry": {"coordinates":[-1.788483,47.905689],"type":"Point"}
}