{
  "type": "Feature",
  "properties": {
    "addr:full":"13 Avenue Aristide Briand Loches Centre 37600",
    "addr:housenumber":"13",
    "addr:postcode":"37600",
    "addr:street":"Avenue Aristide Briand",
    "iso:country":"FR",
    "sg:address":"13 Avenue Aristide Briand",
    "sg:city":"Loches",
    "sg:classifiers":[
        {
            "category":"Banks & Credit Unions",
            "subcategory":"Financial Services",
            "type":"Services"
        }
    ],
    "sg:phone":"+33 2 47 59 00 31",
    "sg:postcode":"37600",
    "sg:province":"Centre",
    "sg:tags":[
        "banking",
        "finance",
        "insurance"
    ],
    "wof:name":"Societe Fiduciaire Nationale D'expertise Comptable Fidexpert (fid)",
    "wof:placetype":"venue"
},
  "geometry": {"coordinates":[1.001818,47.120354],"type":"Point"}
}