{
  "type": "Feature",
  "properties": {
    "addr:full":"Chemin de la Thillay - ZA de Glatigny Lisieux Basse Normandie 14100",
    "addr:postcode":"14100",
    "addr:street":"Chemin De La Thillay Za De Glatigny;Basse",
    "iso:country":"FR",
    "sg:address":"Chemin de la Thillay - ZA de Glatigny",
    "sg:city":"Lisieux",
    "sg:orig_category":"Non-Classified Establishments",
    "sg:phone":"+33 2 31 31 82 35",
    "sg:postcode":"14100",
    "sg:province":"Basse Normandie",
    "wof:name":"Quantaflow S.a.",
    "wof:placetype":"venue"
},
  "geometry": {"coordinates":[0.189525,49.074329],"type":"Point"}
}