{
  "type": "Feature",
  "properties": {
    "addr:full":"4 Av Jean Mermoz 63100 Clermont Ferrand Clermont-Ferrand Auvergne 63100",
    "addr:postcode":"63100;63100",
    "addr:street":"Av Jean Mermoz",
    "iso:country":"FR",
    "sg:address":"4 Av Jean Mermoz 63100 Clermont Ferrand",
    "sg:city":"Clermont-Ferrand",
    "sg:classifiers":[
        {
            "category":"Building & Trades",
            "subcategory":"Construction",
            "type":"Services"
        }
    ],
    "sg:phone":"+33 4 73 92 10 12",
    "sg:postcode":"63100",
    "sg:province":"Auvergne",
    "sg:tags":[
        "work",
        "public"
    ],
    "wof:name":"Appia Auvergne",
    "wof:placetype":"venue"
},
  "geometry": {"coordinates":[3.124184,45.788074],"type":"Point"}
}