{
  "type": "Feature",
  "properties": {
    "iso:country":"FR",
    "sg:address":"5 rue Jacob Mayer 67200 Strasbourg",
    "sg:city":"Strasbourg",
    "sg:classifiers":[
        {
            "category":"Wholesale",
            "subcategory":"Books, Periodicals, & Newspapers",
            "type":"Manufacturing & Wholesale Goods"
        }
    ],
    "sg:phone":"+33 3 90 20 65 00",
    "sg:postcode":"67200",
    "sg:province":"Alsace",
    "sg:tags":[
        "publisher",
        "journal"
    ],
    "wof:name":"Documentation Organique Sa",
    "wof:placetype":"venue"
},
  "geometry": {"coordinates":[7.719309,48.590813],"type":"Point"}
}