{
  "type": "Feature",
  "properties": {
    "iso:country":"FR",
    "sg:address":"RN 15 Le Mesnil Roux",
    "sg:city":"Barentin",
    "sg:orig_category":"Unclassifiable Establishments",
    "sg:phone":"+33 2 32 94 50 80",
    "sg:postcode":"76360",
    "sg:province":"Haute Normandie",
    "wof:name":"T.g.i. S.a. - T\u00f4lerie Ganaye Industrielle",
    "wof:placetype":"venue"
},
  "geometry": {"coordinates":[0.953649,49.545403],"type":"Point"}
}