{
  "type": "Feature",
  "properties": {
    "addr:full":"12 Rue Ste Genevi\u00e8ve 29600 Morlaix Morlaix Bretagne 29600",
    "addr:housenumber":"12",
    "addr:postcode":"29600;29600",
    "addr:street":"Rue Ste Genevie\u0300Ve",
    "iso:country":"FR",
    "sg:address":"12 Rue Ste Genevi\u00e8ve 29600 Morlaix",
    "sg:city":"Morlaix",
    "sg:classifiers":[
        {
            "category":"Manufacturing",
            "subcategory":"Wood Products",
            "type":"Manufacturing & Wholesale Goods"
        }
    ],
    "sg:phone":"+33 2 98 88 65 77",
    "sg:postcode":"29600",
    "sg:province":"Bretagne",
    "sg:tags":[
        "professional",
        "furniture"
    ],
    "wof:name":"Atout Bois Industrie Sarl",
    "wof:placetype":"venue"
},
  "geometry": {"coordinates":[-3.809203,48.597645],"type":"Point"}
}