{
  "type": "Feature",
  "properties": {
    "iso:country":"FR",
    "sg:address":"11, Rue Jean Rodier, 31400 Toulouse",
    "sg:orig_category":"Unclassifiable Establishments",
    "sg:phone":"+33 5 61 17 42 38",
    "sg:province":"Midi Pyr\u00e9n\u00e9es",
    "wof:name":"Cabinet Coudenc Delon Et Associ\u00e9s",
    "wof:placetype":"venue"
},
  "geometry": {"coordinates":[1.486098,43.569443],"type":"Point"}
}