{
  "type": "Feature",
  "properties": {
    "iso:country":"FR",
    "sg:address":"rue du Consier 71530 Crissey",
    "sg:city":"Crissey",
    "sg:classifiers":[
        {
            "category":"Sports & Exercise",
            "subcategory":"Sports Center",
            "type":"Entertainment"
        }
    ],
    "sg:phone":"+33 3 85 46 55 45",
    "sg:postcode":"71530",
    "sg:province":"Bourgogne",
    "sg:tags":[
        "billiards",
        "accessory"
    ],
    "wof:name":"Ren\u00e9 Pierre-jeux Automatiques S.a.",
    "wof:placetype":"venue"
},
  "geometry": {"coordinates":[4.866043,46.814289],"type":"Point"}
}