{
  "type": "Feature",
  "properties": {
    "addr:full":"B.P. 78, 67020 Strasbourg C\u00e9dex^^16, Rue de Rheinfeld, 67100 Strasbourg Strasbourg Alsace 67100",
    "addr:postcode":"67020;67100;67100",
    "addr:street":"B.P. 78;Rue De Rheinfeld",
    "iso:country":"FR",
    "sg:address":"B.P. 78, 67020 Strasbourg C\u00e9dex^^16, Rue de Rheinfeld, 67100 Strasbourg",
    "sg:city":"Strasbourg",
    "sg:orig_category":"Non-Classified Establishments",
    "sg:phone":"+33 3 88 79 88 50",
    "sg:postcode":"67100",
    "sg:province":"Alsace",
    "wof:name":"K\u00fchne & Nagel S.a.",
    "wof:placetype":"venue"
},
  "geometry": {"coordinates":[7.76865,48.534969],"type":"Point"}
}