{
  "type": "Feature",
  "properties": {
    "iso:country":"FR",
    "sg:address":"24, Rue de Li\u00e8ge, 75008 Paris",
    "sg:orig_category":"Non-Classified Establishments",
    "sg:phone":"+33 1 39 82 26 38",
    "sg:province":"Ile de France",
    "wof:name":"M.m.t. S.a.r.l. - Multi-machines-trade",
    "wof:placetype":"venue"
},
  "geometry": {"coordinates":[2.326379,48.879673],"type":"Point"}
}