{
  "type": "Feature",
  "properties": {
    "addr:full":"40, Rue de Ch\u00e2teaudun, 75009 Paris Ile de France",
    "addr:housenumber":"40",
    "addr:postcode":"75009",
    "addr:street":"Rue De Cha\u0302Teaudun",
    "iso:country":"FR",
    "sg:address":"40, Rue de Ch\u00e2teaudun, 75009 Paris",
    "sg:orig_category":"Unclassifiable Establishments",
    "sg:phone":"+33 1 45 26 60 16",
    "sg:province":"Ile de France",
    "wof:name":"Atria Capital Partenaires S.a.",
    "wof:placetype":"venue"
},
  "geometry": {"coordinates":[2.334994,48.876339],"type":"Point"}
}