{
  "type": "Feature",
  "properties": {
    "addr:full":"Za De Kergazuel 29930 Pont Aven Pont-Aven Bretagne 29930",
    "addr:postcode":"29930;29930",
    "addr:street":"Za De Kergazuel;Aven",
    "iso:country":"FR",
    "sg:address":"Za De Kergazuel 29930 Pont Aven",
    "sg:city":"Pont-Aven",
    "sg:classifiers":[
        {
            "category":"Government",
            "subcategory":"Department Of Motor Vehicles",
            "type":"Public Place"
        }
    ],
    "sg:phone":"+33 2 98 06 12 06",
    "sg:postcode":"29930",
    "sg:province":"Bretagne",
    "sg:tags":[
        "equipment",
        "industrial",
        "transport",
        "motor-cars"
    ],
    "wof:name":"Aven Casse",
    "wof:placetype":"venue"
},
  "geometry": {"coordinates":[-3.747139,47.855446],"type":"Point"}
}