{
  "type": "Feature",
  "properties": {
    "iso:country":"FR",
    "sg:address":"10, Rue Sadi Carnot, 14000 Caen",
    "sg:city":"Caen",
    "sg:orig_category":"Non-Classified Establishments",
    "sg:phone":"+33 2 31 15 20 00",
    "sg:postcode":"14000",
    "sg:province":"Basse Normandie",
    "wof:name":"Robinson Europe S.a.",
    "wof:placetype":"venue"
},
  "geometry": {"coordinates":[-0.362099,49.17894],"type":"Point"}
}