{
  "type": "Feature",
  "properties": {
    "addr:full":"B.P. 94, 34800 Clermont l'H\u00e9rault C\u00e9dex^^18, Av. de Montpellier - ZI, 34800 Clermont l'H\u00e9rault Languedoc-Roussillon",
    "addr:postcode":"34800;34800",
    "addr:street":"B.P. 94;Av. De Montpellier Zi;\u0301Rault",
    "iso:country":"FR",
    "sg:address":"B.P. 94, 34800 Clermont l'H\u00e9rault C\u00e9dex^^18, Av. de Montpellier - ZI, 34800 Clermont l'H\u00e9rault",
    "sg:orig_category":"Non-Classified Establishments",
    "sg:phone":"+33 4 67 88 46 46",
    "sg:province":"Languedoc-Roussillon",
    "wof:name":"Im\u00e9ca S.a.",
    "wof:placetype":"venue"
},
  "geometry": {"coordinates":[3.843697,43.629562],"type":"Point"}
}