{
  "type": "Feature",
  "properties": {
    "iso:country":"FR",
    "sg:address":"5 Rte De Besan\u00e7on 25290 Ornans",
    "sg:classifiers":[
        {
            "category":"Professional",
            "subcategory":"Engineering",
            "type":"Services"
        }
    ],
    "sg:phone":"+33 3 81 62 25 87",
    "sg:postcode":"25290",
    "sg:province":"Franche Comt\u00e9",
    "sg:tags":[
        "machine",
        "-",
        "mechanical"
    ],
    "wof:name":"Sosolic Sarl",
    "wof:placetype":"venue"
},
  "geometry": {"coordinates":[6.127001,47.108166],"type":"Point"}
}