{
  "type": "Feature",
  "properties": {
    "addr:full":"12 Rue De L Arquebuse 71400 Autun Autun Bourgogne 71400",
    "addr:housenumber":"12",
    "addr:postcode":"71400;71400",
    "addr:street":"Rue De L Arquebuse",
    "iso:country":"FR",
    "sg:address":"12 Rue De L Arquebuse 71400 Autun",
    "sg:city":"Autun",
    "sg:classifiers":[
        {
            "category":"Professional",
            "subcategory":"Printing & Photocopies",
            "type":"Services"
        }
    ],
    "sg:phone":"+33 3 85 86 34 34",
    "sg:postcode":"71400",
    "sg:province":"Bourgogne",
    "sg:tags":[
        "publishing"
    ],
    "wof:name":"La Gazette Independante De Saone Et Loire",
    "wof:placetype":"venue"
},
  "geometry": {"coordinates":[4.301695,46.949989],"type":"Point"}
}