{
  "type": "Feature",
  "properties": {
    "iso:country":"FR",
    "sg:address":"Zi De La Pelaterie 34 Rue De Ch\u00e2teau Z A Du Buisson 59443 Wasquehal Cedex",
    "sg:classifiers":[
        {
            "category":"Professional",
            "subcategory":"Advertising",
            "type":"Services"
        }
    ],
    "sg:phone":"+33 3 20 20 62 40",
    "sg:province":"Midi Pyr\u00e9n\u00e9es",
    "sg:tags":[
        "information",
        "medium",
        "communication"
    ],
    "wof:name":"Giraudy",
    "wof:placetype":"venue"
},
  "geometry": {"coordinates":[3.12938,50.669281],"type":"Point"}
}