{
  "type": "Feature",
  "properties": {
    "addr:full":"5 rue C\u00f4te Legendes; Kerlouan Kerlouan Bretagne 29890",
    "addr:housenumber":"5",
    "addr:postcode":"29890",
    "addr:street":"Rue Co\u0302Te Legendes;Kerlouan",
    "iso:country":"FR",
    "sg:address":"5 rue C\u00f4te Legendes; Kerlouan",
    "sg:city":"Kerlouan",
    "sg:classifiers":[
        {
            "category":"Banks & Credit Unions",
            "subcategory":"Bank",
            "type":"Services"
        }
    ],
    "sg:phone":"+33 3398839349",
    "sg:postcode":"29890",
    "sg:province":"Bretagne",
    "wof:name":"Cr\u00e9dit Mutuel De Bretagne",
    "wof:placetype":"venue"
},
  "geometry": {"coordinates":[-4.366035,48.644642],"type":"Point"}
}