{
  "type": "Feature",
  "properties": {
    "iso:country":"FR",
    "sg:address":"5 rue C\u00f4te Legendes; Kerlouan",
    "sg:city":"Kerlouan",
    "sg:classifiers":[
        {
            "category":"Banks & Credit Unions",
            "subcategory":"Bank",
            "type":"Services"
        }
    ],
    "sg:phone":"+33 3398839349",
    "sg:postcode":"29890",
    "sg:province":"Bretagne",
    "wof:name":"Cr\u00e9dit Mutuel De Bretagne",
    "wof:placetype":"venue"
},
  "geometry": {"coordinates":[-4.366035,48.644642],"type":"Point"}
}