{
  "type": "Feature",
  "properties": {
    "addr:full":"12 bis, Bd de Groslay, 35300 Foug\u00e8res Foug\u00e8res Bretagne 35300",
    "addr:housenumber":"12 bis",
    "addr:postcode":"35300;35300",
    "addr:street":"Bd De Groslay",
    "iso:country":"FR",
    "sg:address":"12 bis, Bd de Groslay, 35300 Foug\u00e8res",
    "sg:city":"Foug\u00e8res",
    "sg:orig_category":"Unclassifiable Establishments",
    "sg:phone":"+33 2 99 99 40 90",
    "sg:postcode":"35300",
    "sg:province":"Bretagne",
    "wof:name":"C.p.v.b. - Coop\u00e9rative Production Vente Bovine",
    "wof:placetype":"venue"
},
  "geometry": {"coordinates":[-1.187369,48.358612],"type":"Point"}
}