{
  "type": "Feature",
  "properties": {
    "addr:full":"Rue Armand Peugeot Zi Nord 72000 Le Mans Pays de Loire 72000",
    "addr:postcode":"72000;72000",
    "addr:street":"Rue Armand Peugeot Zi Nord",
    "iso:country":"FR",
    "sg:address":"Rue Armand Peugeot Zi Nord 72000 Le Mans",
    "sg:classifiers":[
        {
            "category":"Manufacturing",
            "subcategory":"Glass & Minerals",
            "type":"Manufacturing & Wholesale Goods"
        }
    ],
    "sg:phone":"+33 2 43 39 32 43",
    "sg:postcode":"72000",
    "sg:province":"Pays de Loire",
    "sg:tags":[
        "building",
        "material"
    ],
    "wof:name":"Beton De France Centre Et Bretagne Sas",
    "wof:placetype":"venue"
},
  "geometry": {"coordinates":[0.197813,48.008095],"type":"Point"}
}