{
  "type": "Feature",
  "properties": {
    "iso:country":"FR",
    "sg:address":"7 bis, Rue des Aulnes, 69410 Champagne au Mont d'Or",
    "sg:orig_category":"Non-Classified Establishments",
    "sg:phone":"+33 4 78 66 25 44",
    "sg:province":"BE.07",
    "wof:name":"Munters France",
    "wof:placetype":"venue"
},
  "geometry": {"coordinates":[5.002347,50.322292],"type":"Point"}
}