{
  "type": "Feature",
  "properties": {
    "iso:country":"FR",
    "sg:address":"Nouveau Port De Golfe Juan Port De Golfe Juan 06220 Vallauris",
    "sg:classifiers":[
        {
            "category":"Autos & Motor Vehicles",
            "subcategory":"Boat Sales",
            "type":"Retail Goods"
        }
    ],
    "sg:phone":"+33 4 97 21 85 00",
    "sg:province":"Rhone-Alpes",
    "sg:tags":[
        "equipment",
        "transport"
    ],
    "wof:name":"G Rodriguez S A Golfe Juan",
    "wof:placetype":"venue"
},
  "geometry": {"coordinates":[7.06074,43.573238],"type":"Point"}
}