{
  "type": "Feature",
  "properties": {
    "iso:country":"FR",
    "sg:address":"B.P. 181, 91161 Longjumeau C\u00e9dex^^23, Rue Bossuet, 91160 Longjumeau",
    "sg:orig_category":"Non-Classified Establishments",
    "sg:phone":"+33 1 69 09 77 85",
    "sg:province":"Ile de France",
    "wof:name":"P.c.a.s. S.a. - Produits Chimiques Auxiliaires Synth\u00e8se",
    "wof:placetype":"venue"
},
  "geometry": {"coordinates":[2.29005,48.691734],"type":"Point"}
}