{
  "type": "Feature",
  "properties": {
    "addr:full":"20 Rue Des Foss\u00e9s St Jacques 75005 Paris Ile de France",
    "addr:housenumber":"20",
    "addr:postcode":"75005",
    "addr:street":"Rue Des Fosse\u0301S St",
    "iso:country":"FR",
    "sg:address":"20 Rue Des Foss\u00e9s St Jacques 75005 Paris",
    "sg:classifiers":[
        {
            "category":"Professional",
            "subcategory":"Printing & Photocopies",
            "type":"Services"
        }
    ],
    "sg:phone":"+33 1 44 41 93 93",
    "sg:province":"Ile de France",
    "sg:tags":[
        "publishing"
    ],
    "wof:name":"Universal Music",
    "wof:placetype":"venue"
},
  "geometry": {"coordinates":[2.344365,48.845318],"type":"Point"}
}