{
  "type": "Feature",
  "properties": {
    "addr:full":"5 R Des M\u00e9rites 95000 Cergy Ile de France 95000",
    "addr:housenumber":"5",
    "addr:postcode":"95000;ile;95000",
    "addr:street":"R Des Me\u0301Rites;France",
    "iso:country":"FR",
    "sg:address":"5 R Des M\u00e9rites 95000 Cergy",
    "sg:classifiers":[
        {
            "category":"Shopping",
            "type":"Retail Goods"
        }
    ],
    "sg:phone":"+33 1 30 30 11 89",
    "sg:postcode":"95000",
    "sg:province":"Ile de France",
    "sg:tags":[
        "metallurgy",
        "finished",
        "-",
        "metalworking",
        "metallic"
    ],
    "wof:name":"Paul Marqu\u00c8s Sa",
    "wof:placetype":"venue"
},
  "geometry": {"coordinates":[2.071417,49.045979],"type":"Point"}
}