{
  "type": "Feature",
  "properties": {
    "addr:full":"B.P. B95, 90101 Delle C\u00e9dex^^3 bis, Grande Rue, 90100 Delle Franche Comt\u00e9 90100",
    "addr:housenumber":"bis",
    "addr:postcode":"90101;90100;90100",
    "addr:street":"Delle Ce\u0301Dex^^3;Grande Rue;Franche Comte\u0301",
    "iso:country":"FR",
    "sg:address":"B.P. B95, 90101 Delle C\u00e9dex^^3 bis, Grande Rue, 90100 Delle",
    "sg:orig_category":"Non-Classified Establishments",
    "sg:phone":"+33 820 09 82 33",
    "sg:postcode":"90100",
    "sg:province":"Franche Comt\u00e9",
    "wof:name":"Cr\u00e9dit Mutuel Sud Territoire",
    "wof:placetype":"venue"
},
  "geometry": {"coordinates":[7.00309,47.508034],"type":"Point"}
}