{
  "type": "Feature",
  "properties": {
    "iso:country":"FR",
    "sg:address":"2 Rue Fontenottes 25690 Avoudrey",
    "sg:orig_category":"Agriculture and Livestock Animals and breeding Food and Related Products Games and entertainment Hor",
    "sg:phone":"+33 3 81 43 20 77",
    "sg:postcode":"25690",
    "sg:province":"Franche Comt\u00e9",
    "wof:name":"Coopadou",
    "wof:placetype":"venue"
},
  "geometry": {"coordinates":[6.434357,47.128845],"type":"Point"}
}