{
  "type": "Feature",
  "properties": {
    "iso:country":"FR",
    "sg:address":"Ponchardon 61120 Vimoutiers",
    "sg:city":"Vimoutiers",
    "sg:orig_category":"Non-Classified Establishments",
    "sg:phone":"+33 2 33 39 05 42",
    "sg:postcode":"61120",
    "sg:province":"Basse Normandie",
    "wof:name":"Pamco Industries S.a.",
    "wof:placetype":"venue"
},
  "geometry": {"coordinates":[0.232705,48.851215],"type":"Point"}
}