{
  "type": "Feature",
  "properties": {
    "addr:full":"6 Rue De La Chalotais 35135 Chantepie Chantepie Bretagne 35135",
    "addr:housenumber":"6",
    "addr:postcode":"35135;35135",
    "addr:street":"Rue De La Chalotais",
    "iso:country":"FR",
    "sg:address":"6 Rue De La Chalotais 35135 Chantepie",
    "sg:city":"Chantepie",
    "sg:classifiers":[
        {
            "category":"Health Services",
            "subcategory":"Medical Lab",
            "type":"Services"
        }
    ],
    "sg:phone":"+33 2 99 41 06 43",
    "sg:postcode":"35135",
    "sg:province":"Bretagne",
    "sg:tags":[
        "chemical",
        "pharmaceutical",
        "pharmacy"
    ],
    "wof:name":"Ocp Repartition Sas",
    "wof:placetype":"venue"
},
  "geometry": {"coordinates":[-1.622957,48.085491],"type":"Point"}
}