{
  "type": "Feature",
  "properties": {
    "addr:full":"ZI la Valampe Ch\u00e2teauneuf les Martigues Provence-Alpes-C\u00f4te d'Azur 13220",
    "addr:postcode":"13220",
    "addr:street":"Zi La Valampe Cha\u0302Teauneuf Les Martigues",
    "iso:country":"FR",
    "sg:address":"ZI la Valampe",
    "sg:city":"Ch\u00e2teauneuf les Martigues",
    "sg:orig_category":"Unclassifiable Establishments",
    "sg:phone":"+33 4 42 79 99 99",
    "sg:postcode":"13220",
    "sg:province":"Provence-Alpes-C\u00f4te d'Azur",
    "wof:name":"Ouest Isol",
    "wof:placetype":"venue"
},
  "geometry": {"coordinates":[5.166426,43.383366],"type":"Point"}
}