{
  "type": "Feature",
  "properties": {
    "iso:country":"FR",
    "sg:address":"Rte d'Orgueil",
    "sg:city":"Fronton",
    "sg:orig_category":"Non-Classified Establishments",
    "sg:phone":"+33 5 61 82 45 43",
    "sg:postcode":"31620",
    "sg:province":"Midi Pyr\u00e9n\u00e9es",
    "wof:name":"Les Dauban E.a.r.l.",
    "wof:placetype":"venue"
},
  "geometry": {"coordinates":[1.396416,43.854126],"type":"Point"}
}