{
  "type": "Feature",
  "properties": {
    "iso:country":"FR",
    "sg:address":"12, av. des Co\u00efdes - Z.I., 51370 Saint Brice Courcelles",
    "sg:orig_category":"Non-Classified Establishments",
    "sg:phone":"+33 3 26 77 42 30",
    "sg:province":"Champagne",
    "wof:name":"J.m.d.p. S.a.r.l. - Jeu Maquette Diffusion Presse",
    "wof:placetype":"venue"
},
  "geometry": {"coordinates":[3.985995,49.261791],"type":"Point"}
}