{
  "type": "Feature",
  "properties": {
    "iso:country":"FR",
    "sg:address":"3, Parc Bradfer, 55000 Bar le Duc",
    "sg:orig_category":"Unclassifiable Establishments",
    "sg:phone":"+33 3 29 79 22 09",
    "sg:province":"Lorraine",
    "wof:name":"Serre Publicit\u00e9",
    "wof:placetype":"venue"
},
  "geometry": {"coordinates":[5.167513,48.770523],"type":"Point"}
}