{
  "type": "Feature",
  "properties": {
    "addr:full":"Rte de Chatillon Is sur Tille Bourgogne 21120",
    "addr:postcode":"21120",
    "addr:street":"Rte De Chatillon Is Sur Tille Bourgogne",
    "iso:country":"FR",
    "sg:address":"Rte de Chatillon",
    "sg:city":"Is sur Tille",
    "sg:orig_category":"Unclassifiable Establishments",
    "sg:phone":"+33 3 80 95 08 77",
    "sg:postcode":"21120",
    "sg:province":"Bourgogne",
    "wof:name":"Sedam S.a.",
    "wof:placetype":"venue"
},
  "geometry": {"coordinates":[5.116855,47.531132],"type":"Point"}
}