{
  "type": "Feature",
  "properties": {
    "iso:country":"FR",
    "sg:address":"1 Rue Du Coll\u00e8ge 67320 Drulingen",
    "sg:city":"Drulingen",
    "sg:classifiers":[
        {
            "category":"Professional",
            "subcategory":"Business Services",
            "type":"Services"
        }
    ],
    "sg:phone":"+33 3 88 00 62 92",
    "sg:postcode":"67320",
    "sg:province":"Alsace",
    "sg:tags":[
        "training",
        "advice"
    ],
    "wof:name":"College Nationalise",
    "wof:placetype":"venue"
},
  "geometry": {"coordinates":[7.195349,48.867283],"type":"Point"}
}