{
  "type": "Feature",
  "properties": {
    "addr:full":"2, Rue de Besan\u00e7on, 25610 Arc et Senans Franche Comt\u00e9",
    "addr:housenumber":"2",
    "addr:postcode":"25610",
    "addr:street":"Rue De Besanc\u0327On;Franche Comte\u0301",
    "iso:country":"FR",
    "sg:address":"2, Rue de Besan\u00e7on, 25610 Arc et Senans",
    "sg:orig_category":"Non-Classified Establishments",
    "sg:phone":"+33 3 81 57 56 10",
    "sg:province":"Franche Comt\u00e9",
    "wof:name":"Scop Lombard S.a.",
    "wof:placetype":"venue"
},
  "geometry": {"coordinates":[5.789411,47.037758],"type":"Point"}
}