{
  "type": "Feature",
  "properties": {
    "addr:full":"ZI n\u00b03 Clos Barral Frontenex Rhone-Alpes 73460",
    "addr:postcode":"73460",
    "addr:street":"Clos Barral;Rhone-Alpes",
    "iso:country":"FR",
    "sg:address":"ZI n\u00b03 Clos Barral",
    "sg:city":"Frontenex",
    "sg:orig_category":"Non-Classified Establishments",
    "sg:phone":"+33 4 79 38 58 88",
    "sg:postcode":"73460",
    "sg:province":"Rhone-Alpes",
    "wof:name":"Bucari Et Fils S.a.",
    "wof:placetype":"venue"
},
  "geometry": {"coordinates":[6.306249,45.587067],"type":"Point"}
}