{
  "type": "Feature",
  "properties": {
    "iso:country":"FR",
    "sg:address":"Zone Industrielle Bel Air 56130 P\u00e9aule",
    "sg:city":"P\u00e9aule",
    "sg:classifiers":[
        {
            "category":"Manufacturing",
            "subcategory":"Rubber & Plastics",
            "type":"Manufacturing & Wholesale Goods"
        }
    ],
    "sg:phone":"+33 2 97 42 82 90",
    "sg:postcode":"56130",
    "sg:province":"Bretagne",
    "wof:name":"Precis Moule",
    "wof:placetype":"venue"
},
  "geometry": {"coordinates":[-2.360289,47.578594],"type":"Point"}
}