{
  "type": "Feature",
  "properties": {
    "addr:full":"35 bd L\u00e9opold Maissin; Le Relecq Kerhuon",
    "addr:housenumber":"35",
    "addr:street":"Bd Le\u0301Opold Maissin Le;Kerhuon",
    "iso:country":"FR",
    "sg:address":"35 bd L\u00e9opold Maissin; Le Relecq Kerhuon",
    "sg:classifiers":[
        {
            "category":"Banks & Credit Unions",
            "subcategory":"Bank",
            "type":"Services"
        }
    ],
    "sg:phone":"+33 3398282604",
    "wof:name":"Cr\u00e9dit Mutuel De Bretagne",
    "wof:placetype":"venue"
},
  "geometry": {"coordinates":[-4.413815,48.395355],"type":"Point"}
}