{
  "type": "Feature",
  "properties": {
    "addr:full":"Av de Hauts Grigneux - Horizon 2000 Mach 4 Bihorel Haute Normandie 76420",
    "addr:postcode":"2000;76420",
    "addr:street":"Av De Hauts Grigneux Horizon;Mach;Haute Normandie",
    "iso:country":"FR",
    "sg:address":"Av de Hauts Grigneux - Horizon 2000 Mach 4",
    "sg:city":"Bihorel",
    "sg:orig_category":"Unclassifiable Establishments",
    "sg:phone":"+33 2 35 60 05 04",
    "sg:postcode":"76420",
    "sg:province":"Haute Normandie",
    "wof:name":"Onet Propret\u00e9 S.a.",
    "wof:placetype":"venue"
},
  "geometry": {"coordinates":[1.143002,49.46619],"type":"Point"}
}