{
  "type": "Feature",
  "properties": {
    "addr:full":"76740 Fontaine Le Dun Haute Normandie 76740",
    "addr:housenumber":"76740",
    "addr:postcode":"76740",
    "addr:street":"Fontaine Le Dun Haute Normandie",
    "iso:country":"FR",
    "sg:address":"76740 Fontaine Le Dun",
    "sg:classifiers":[
        {
            "category":"Banks & Credit Unions",
            "subcategory":"Financial Services",
            "type":"Services"
        }
    ],
    "sg:phone":"+33 2 35 97 41 77",
    "sg:postcode":"76740",
    "sg:province":"Haute Normandie",
    "sg:tags":[
        "banking",
        "insurance",
        "institution",
        "finance"
    ],
    "wof:name":"Ste D'interet Collectif Agri De Deshydratation De Fontaine Le (sidefo)",
    "wof:placetype":"venue"
},
  "geometry": {"coordinates":[0.849081,49.814468],"type":"Point"}
}