{
  "type": "Feature",
  "properties": {
    "addr:full":"Place De La Gare 69380 Lozanne Rhone-Alpes 69380",
    "addr:postcode":"69380;69380",
    "addr:street":"Place De La Gare",
    "iso:country":"FR",
    "sg:address":"Place De La Gare 69380 Lozanne",
    "sg:classifiers":[
        {
            "category":"Wholesale",
            "subcategory":"Medical Equipment & Supplies",
            "type":"Manufacturing & Wholesale Goods"
        }
    ],
    "sg:phone":"+33 4 78 43 72 39",
    "sg:postcode":"69380",
    "sg:province":"Rhone-Alpes",
    "sg:tags":[
        "instrument",
        "health",
        "-",
        "precision"
    ],
    "wof:name":"Biser",
    "wof:placetype":"venue"
},
  "geometry": {"coordinates":[4.681305,45.854416],"type":"Point"}
}