{
  "type": "Feature",
  "properties": {
    "addr:full":"44, Rue Laurent Helmuth, 08120 Bogny sur Meuse Bogny-sur-Meuse Champagne 08120",
    "addr:housenumber":"44",
    "addr:postcode":"08120;08120",
    "addr:street":"Rue Laurent Helmuth;Bogny;Meuse;Champagne",
    "iso:country":"FR",
    "sg:address":"44, Rue Laurent Helmuth, 08120 Bogny sur Meuse",
    "sg:city":"Bogny-sur-Meuse",
    "sg:orig_category":"BOULONNERIE SP\u00c9CIALE EN ACIER, INOX, R\u00c9FRACTAIRE, MONEL, INCONEL, ALLOY, HASTELLOY TIRANTS D'ANCRAGE",
    "sg:phone":"+33 3 24 52 45 45",
    "sg:postcode":"08120",
    "sg:province":"Champagne",
    "wof:name":"Lenoir Et Mernier S.a.",
    "wof:placetype":"venue"
},
  "geometry": {"coordinates":[4.76945,49.851891],"type":"Point"}
}