{
  "type": "Feature",
  "properties": {
    "iso:country":"FR",
    "sg:address":"B.P. 106, 39302 Champagnole C\u00e9dex^^545, Av de Lattre de Tassigny, 39300 Champagnole",
    "sg:orig_category":"Non-Classified Establishments",
    "sg:phone":"+33 3 84 53 07 77",
    "sg:province":"Franche Comt\u00e9",
    "wof:name":"Jouef S.a.r.l.",
    "wof:placetype":"venue"
},
  "geometry": {"coordinates":[5.907597,46.747177],"type":"Point"}
}