{
  "type": "Feature",
  "properties": {
    "addr:full":"B.P. 171, 75770 Paris C\u00e9dex 16^^3, Rue de Chaillot, 75016 Paris Ile de France",
    "addr:housenumber":"b.p. 171;16;^ 3",
    "addr:postcode":"75770;75016",
    "addr:street":"^;Rue De Chaillot",
    "iso:country":"FR",
    "sg:address":"B.P. 171, 75770 Paris C\u00e9dex 16^^3, Rue de Chaillot, 75016 Paris",
    "sg:orig_category":"Non-Classified Establishments",
    "sg:phone":"+33 1 53 23 15 15",
    "sg:province":"Ile de France",
    "wof:name":"Potel Et Chabot S.a.",
    "wof:placetype":"venue"
},
  "geometry": {"coordinates":[2.25657,48.857079],"type":"Point"}
}