{
  "type": "Feature",
  "properties": {
    "addr:full":"45, Bd de Graville, 76600 Le Havre Haute Normandie",
    "addr:housenumber":"45",
    "addr:postcode":"76600",
    "addr:street":"Bd De Graville",
    "iso:country":"FR",
    "sg:address":"45, Bd de Graville, 76600 Le Havre",
    "sg:orig_category":"Unclassifiable Establishments",
    "sg:phone":"+33 2 35 25 84 40",
    "sg:province":"Haute Normandie",
    "wof:name":"Auxitec Industrie D\u00e9partement R\u00e9alisation S.a.",
    "wof:placetype":"venue"
},
  "geometry": {"coordinates":[0.153806,49.480057],"type":"Point"}
}