{
  "type": "Feature",
  "properties": {
    "addr:full":"7, All\u00e9e des Peupliers - ZI, 54180 Heillecourt Lorraine",
    "addr:housenumber":"7",
    "addr:postcode":"54180",
    "addr:street":"Alle\u0301E Des Peupliers Zi",
    "iso:country":"FR",
    "sg:address":"7, All\u00e9e des Peupliers - ZI, 54180 Heillecourt",
    "sg:orig_category":"Unclassifiable Establishments",
    "sg:phone":"+33 3 83 55 05 35",
    "sg:province":"Lorraine",
    "wof:name":"M\u00e9tallerie Mathieu S.a.",
    "wof:placetype":"venue"
},
  "geometry": {"coordinates":[6.194192,48.653137],"type":"Point"}
}