{
  "type": "Feature",
  "properties": {
    "iso:country":"FR",
    "sg:address":"11, Place de Breteuil, 75007 Paris",
    "sg:orig_category":"Non-Classified Establishments",
    "sg:phone":"+33 1 43 06 30 93",
    "sg:postcode":"75007",
    "sg:province":"Ile de France",
    "wof:name":"Action Assistance S.a.r.l.",
    "wof:placetype":"venue"
},
  "geometry": {"coordinates":[2.312355,48.847065],"type":"Point"}
}