{
  "type": "Feature",
  "properties": {
    "addr:full":"Gardut 33390 Cars Cars Aquitaine 33390",
    "addr:postcode":"33390;33390",
    "addr:street":"Gardut",
    "iso:country":"FR",
    "sg:address":"Gardut 33390 Cars",
    "sg:city":"Cars",
    "sg:orig_category":"Unclassifiable Establishments",
    "sg:phone":"+33 5 57 42 20 35",
    "sg:postcode":"33390",
    "sg:province":"Aquitaine",
    "wof:name":"Revaire Patrick",
    "wof:placetype":"venue"
},
  "geometry": {"coordinates":[-0.627929,45.119686],"type":"Point"}
}