{
  "type": "Feature",
  "properties": {
    "addr:full":"241 rue des Bouvards 73420 VOGLANS Rhone-Alpes 73420",
    "addr:housenumber":"241",
    "addr:postcode":"73420;73420",
    "addr:street":"Rue Des Bouvards;Rhone-Alpes",
    "iso:country":"FR",
    "sg:address":"241 rue des Bouvards 73420 VOGLANS",
    "sg:classifiers":[
        {
            "category":"Professional",
            "type":"Services"
        }
    ],
    "sg:phone":"+33 4 79 54 49 90",
    "sg:postcode":"73420",
    "sg:province":"Rhone-Alpes",
    "sg:tags":[
        "transport"
    ],
    "wof:name":"T.b.d. Sarl",
    "wof:placetype":"venue"
},
  "geometry": {"coordinates":[5.893245,45.625511],"type":"Point"}
}