{
  "type": "Feature",
  "properties": {
    "iso:country":"FR",
    "sg:address":"Le Causse Comtal 12630 Montrozier",
    "sg:orig_category":"Unclassifiable Establishments",
    "sg:phone":"+33 5 65 74 90 98",
    "sg:province":"Midi Pyr\u00e9n\u00e9es",
    "wof:name":"H\u00f4tel Causse Comtal",
    "wof:placetype":"venue"
},
  "geometry": {"coordinates":[2.681258,44.358204],"type":"Point"}
}