{
  "type": "Feature",
  "properties": {
    "iso:country":"FR",
    "sg:address":"118, Rue des Tiphoines, 91240 Saint Michel sur Orge",
    "sg:orig_category":"Non-Classified Establishments",
    "sg:phone":"+33 1 64 49 58 85",
    "sg:postcode":"91240",
    "sg:province":"Ile de France",
    "wof:name":"C\u00f4t\u00e9 Nature S.a.",
    "wof:placetype":"venue"
},
  "geometry": {"coordinates":[2.29813,48.626209],"type":"Point"}
}