{
  "type": "Feature",
  "properties": {
    "iso:country":"FR",
    "sg:address":"14, Rue Victor Hugo, 95500 Gonesse",
    "sg:orig_category":"Unclassifiable Establishments",
    "sg:phone":"+33 1 39 85 57 01",
    "sg:province":"Ile de France",
    "wof:name":"K.n.b. M\u00e9dia",
    "wof:placetype":"venue"
},
  "geometry": {"coordinates":[2.435593,48.985226],"type":"Point"}
}