{
  "type": "Feature",
  "properties": {
    "iso:country":"FR",
    "sg:address":"Zone Industrielle",
    "sg:city":"Simandre",
    "sg:orig_category":"Non-Classified Establishments",
    "sg:phone":"+33 3 85 32 49 00",
    "sg:postcode":"71290",
    "sg:province":"Bourgogne",
    "wof:name":"Rexam Cosm\u00e9tiques Closures S.a.r.l.",
    "wof:placetype":"venue"
},
  "geometry": {"coordinates":[4.987365,46.620171],"type":"Point"}
}