{
  "type": "Feature",
  "properties": {
    "addr:full":"B.P. 3, 87800 Nexon^^ZI des Gannes, 87800 Nexon Limousin",
    "addr:housenumber":"3",
    "addr:postcode":"87800;87800",
    "addr:street":"B.P.;Des Gannes",
    "iso:country":"FR",
    "sg:address":"B.P. 3, 87800 Nexon^^ZI des Gannes, 87800 Nexon",
    "sg:orig_category":"Non-Classified Establishments",
    "sg:phone":"+33 5 55 58 50 00",
    "sg:province":"Limousin",
    "wof:name":"Sofrance S.a.",
    "wof:placetype":"venue"
},
  "geometry": {"coordinates":[1.18759,45.576721],"type":"Point"}
}