{
  "type": "Feature",
  "properties": {
    "iso:country":"FR",
    "sg:address":"26 Chem Du Cass\u00e9 33500 Libourne",
    "sg:city":"Libourne",
    "sg:classifiers":[
        {
            "category":"Food Court",
            "type":"Food & Drink"
        }
    ],
    "sg:phone":"+33 5 57 51 52 58",
    "sg:postcode":"33500",
    "sg:province":"Aquitaine",
    "sg:tags":[
        "product",
        "related"
    ],
    "wof:name":"Scea",
    "wof:placetype":"venue"
},
  "geometry": {"coordinates":[-0.223203,44.918083],"type":"Point"}
}