{
  "type": "Feature",
  "properties": {
    "iso:country":"FR",
    "sg:address":"B.P. 1219, 68012 Colmar C\u00e9dex^^21, Rue Andr\u00e9 Kiener, 68000 Colmar",
    "sg:city":"Colmar",
    "sg:orig_category":"Non-Classified Establishments",
    "sg:phone":"+33 3 89 20 50 50",
    "sg:postcode":"68000",
    "sg:province":"Alsace",
    "wof:name":"Weishaupt S.a.",
    "wof:placetype":"venue"
},
  "geometry": {"coordinates":[7.363583,48.081985],"type":"Point"}
}