{
  "type": "Feature",
  "properties": {
    "addr:full":"Lagout\u00e8re 47400 Fauguerolles Fauguerolles Aquitaine 47400",
    "addr:postcode":"47400;47400",
    "addr:street":"Lagoute\u0300Re",
    "iso:country":"FR",
    "sg:address":"Lagout\u00e8re 47400 Fauguerolles",
    "sg:city":"Fauguerolles",
    "sg:orig_category":"Non-Classified Establishments",
    "sg:phone":"+33 5 53 83 31 72",
    "sg:postcode":"47400",
    "sg:province":"Aquitaine",
    "wof:name":"Baland Plastin'agri S.a.",
    "wof:placetype":"venue"
},
  "geometry": {"coordinates":[0.254605,44.436626],"type":"Point"}
}