{
  "type": "Feature",
  "properties": {
    "addr:full":"Rue du Transformateur Bennwihr Alsace 68126",
    "addr:postcode":"68126",
    "addr:street":"Rue Du Transformateur",
    "iso:country":"FR",
    "sg:address":"Rue du Transformateur",
    "sg:city":"Bennwihr",
    "sg:orig_category":"Unclassifiable Establishments",
    "sg:phone":"+33 3 89 41 27 36",
    "sg:postcode":"68126",
    "sg:province":"Alsace",
    "wof:name":"K.r.s. S.a.",
    "wof:placetype":"venue"
},
  "geometry": {"coordinates":[7.351342,48.127449],"type":"Point"}
}