{
  "type": "Feature",
  "properties": {
    "addr:full":"B.P. 5, 84350 Courth\u00e9zon^^Quartier de la Roquette, 84350 Courth\u00e9zon La Roquette Haute Normandie 27700",
    "addr:housenumber":"5",
    "addr:postcode":"84350;84350;27700",
    "addr:street":"B.P.;Normandie",
    "iso:country":"FR",
    "sg:address":"B.P. 5, 84350 Courth\u00e9zon^^Quartier de la Roquette, 84350 Courth\u00e9zon",
    "sg:city":"La Roquette",
    "sg:orig_category":"Non-Classified Establishments",
    "sg:phone":"+33 4 90 70 21 11",
    "sg:postcode":"27700",
    "sg:province":"Haute Normandie",
    "wof:name":"De Paoli S.a.r.l.",
    "wof:placetype":"venue"
},
  "geometry": {"coordinates":[4.882788,44.085251],"type":"Point"}
}