{
  "type": "Feature",
  "properties": {
    "iso:country":"FR",
    "sg:address":"B.P. CP 207, 69336 Lyon C\u00e9dex 09^^12, Quai du Commerce, 69009 Lyon",
    "sg:orig_category":"Non-Classified Establishments",
    "sg:phone":"+33 4 78 64 85 86",
    "sg:province":"Rhone-Alpes",
    "wof:name":"L\u00e9gi Consultants S.a.r.l.",
    "wof:placetype":"venue"
},
  "geometry": {"coordinates":[4.805335,45.774105],"type":"Point"}
}