{
  "type": "Feature",
  "properties": {
    "addr:full":"37, Rue Champfleuri, 63000 Clermont Ferrand Clermont-Ferrand Auvergne 63000",
    "addr:housenumber":"37",
    "addr:postcode":"63000;63000",
    "addr:street":"Rue Champfleuri",
    "iso:country":"FR",
    "sg:address":"37, Rue Champfleuri, 63000 Clermont Ferrand",
    "sg:city":"Clermont-Ferrand",
    "sg:orig_category":"Non-Classified Establishments",
    "sg:phone":"+33 4 73 42 69 69",
    "sg:postcode":"63000",
    "sg:province":"Auvergne",
    "wof:name":"Fichet S\u00e9curit\u00e9 Electronique S.a.s.",
    "wof:placetype":"venue"
},
  "geometry": {"coordinates":[3.087912,45.788433],"type":"Point"}
}