{
  "type": "Feature",
  "properties": {
    "addr:full":"2 all\u00e9e des Tilleuls 59170 Croix Nord Pas-de-Calais",
    "addr:housenumber":"2",
    "addr:postcode":"59170",
    "addr:street":"Alle\u0301E Des Tilleuls;Croix Nord",
    "iso:country":"FR",
    "sg:address":"2 all\u00e9e des Tilleuls 59170 Croix",
    "sg:classifiers":[
        {
            "category":"Shopping",
            "subcategory":"Crafts & Fabrics",
            "type":"Retail Goods"
        }
    ],
    "sg:phone":"+33 3 20 98 98 13",
    "sg:province":"Nord Pas-de-Calais",
    "sg:tags":[
        "marketing",
        "trade"
    ],
    "wof:name":"100% Vpc S.a.r.l.",
    "wof:placetype":"venue"
},
  "geometry": {"coordinates":[3.141531,50.676277],"type":"Point"}
}