{
  "type": "Feature",
  "properties": {
    "addr:full":"Leur Ar Bars 29000 Quimper Quimper Bretagne 29000",
    "addr:postcode":"29000;29000",
    "addr:street":"Leur",
    "iso:country":"FR",
    "sg:address":"Leur Ar Bars 29000 Quimper",
    "sg:city":"Quimper",
    "sg:classifiers":[
        {
            "category":"Food & Beverages",
            "subcategory":"Meat & Fish",
            "type":"Retail Goods"
        }
    ],
    "sg:phone":"+33 2 98 94 63 76",
    "sg:postcode":"29000",
    "sg:province":"Bretagne",
    "sg:tags":[
        "preserve",
        "cooked",
        "product",
        "related"
    ],
    "wof:name":"Sa Le Pape",
    "wof:placetype":"venue"
},
  "geometry": {"coordinates":[-4.030814,47.975559],"type":"Point"}
}