{
  "type": "Feature",
  "properties": {
    "addr:full":"Rue de Nantes Coss\u00e9 le Vivien Pays de Loire 53230",
    "addr:housenumber":"cosse\u0301",
    "addr:postcode":"53230",
    "addr:street":"Rue De Nantes;Le Vivien",
    "iso:country":"FR",
    "sg:address":"Rue de Nantes",
    "sg:city":"Coss\u00e9 le Vivien",
    "sg:orig_category":"Unclassifiable Establishments",
    "sg:phone":"+33 2 43 98 99 29",
    "sg:postcode":"53230",
    "sg:province":"Pays de Loire",
    "wof:name":"Rubycon Coorporation French Office",
    "wof:placetype":"venue"
},
  "geometry": {"coordinates":[-0.9147,47.939175],"type":"Point"}
}