{
  "type": "Feature",
  "properties": {
    "iso:country":"FR",
    "sg:address":"117, Chemin des Vertes Rives, 84320 Entraigues sur la Sorgue",
    "sg:orig_category":"Non-Classified Establishments",
    "sg:phone":"+33 4 90 83 17 95",
    "sg:province":"Provence-Alpes-C\u00f4te d'Azur",
    "wof:name":"Ned Inter Pulv\u00e9 S.a.s. - Norbert Dentressangle Inter Pulv\u00e9",
    "wof:placetype":"venue"
},
  "geometry": {"coordinates":[4.92909,44.007401],"type":"Point"}
}