{
  "type": "Feature",
  "properties": {
    "iso:country":"FR",
    "sg:address":"33, Rue Alphonse Daudet, 80230 Vaudricourt",
    "sg:orig_category":"Unclassifiable Establishments",
    "sg:phone":"+33 3 22 60 20 00",
    "sg:province":"Picardie",
    "wof:name":"Noyon Et Thi\u00e9bault S.a.",
    "wof:placetype":"venue"
},
  "geometry": {"coordinates":[1.547056,50.117538],"type":"Point"}
}