{
  "type": "Feature",
  "properties": {
    "iso:country":"FR",
    "sg:address":"9, Rue Polin Talabot - Parc Basso Cambo, 31100 Toulouse",
    "sg:orig_category":"Non-Classified Establishments",
    "sg:phone":"+33 5 61 44 23 23",
    "sg:province":"Midi Pyr\u00e9n\u00e9es",
    "wof:name":"Laboratoire Wolff Environnement S.a.",
    "wof:placetype":"venue"
},
  "geometry": {"coordinates":[1.386699,43.564182],"type":"Point"}
}