{
  "type": "Feature",
  "properties": {
    "iso:country":"FR",
    "sg:address":"8 R Du Dauphin\u00e9 69960 Corbas",
    "sg:classifiers":[
        {
            "category":"Building & Trades",
            "subcategory":"Construction",
            "type":"Services"
        }
    ],
    "sg:phone":"+33 4 72 21 25 25",
    "sg:postcode":"69960",
    "sg:province":"Rhone-Alpes",
    "sg:tags":[
        "work",
        "public"
    ],
    "wof:name":"Gerland Lyon Snc",
    "wof:placetype":"venue"
},
  "geometry": {"coordinates":[4.91093,45.685265],"type":"Point"}
}