{
  "type": "Feature",
  "properties": {
    "addr:full":"2, Rue de Castres, 02690 Essigny le Grand Picardie 02690",
    "addr:housenumber":"2",
    "addr:postcode":"02690;02690",
    "addr:street":"Rue De Castres",
    "iso:country":"FR",
    "sg:address":"2, Rue de Castres, 02690 Essigny le Grand",
    "sg:orig_category":"Climatisation Froid commercial Froid industriel Froid professionnel",
    "sg:phone":"+33 3 23 63 94 12",
    "sg:postcode":"02690",
    "sg:province":"Picardie",
    "wof:name":"Jm Froid Climatisation S.a.r.l.",
    "wof:placetype":"venue"
},
  "geometry": {"coordinates":[3.274735,49.780762],"type":"Point"}
}