{
  "type": "Feature",
  "properties": {
    "addr:full":"357, Av. G\u00e9n\u00e9ral Pruneau, 83100 Toulon Pays de Loire",
    "addr:postcode":"83100",
    "addr:street":"357 Av. Ge\u0301Ne\u0301Ral Pruneau",
    "iso:country":"FR",
    "sg:address":"357, Av. G\u00e9n\u00e9ral Pruneau, 83100 Toulon",
    "sg:orig_category":"Unclassifiable Establishments",
    "sg:phone":"+33 4 94 16 60 60",
    "sg:province":"Pays de Loire",
    "wof:name":"Agora S.a.",
    "wof:placetype":"venue"
},
  "geometry": {"coordinates":[5.95579,43.121052],"type":"Point"}
}