{
  "type": "Feature",
  "properties": {
    "addr:full":"Z.I. les Consacs Brignoles Poitou-Charentes 83170",
    "addr:postcode":"83170",
    "addr:street":"Z.I. Les Consacs Brignoles",
    "iso:country":"FR",
    "sg:address":"Z.I. les Consacs",
    "sg:city":"Brignoles",
    "sg:orig_category":"Non-Classified Establishments",
    "sg:phone":"+33 4 94 37 21 00",
    "sg:postcode":"83170",
    "sg:province":"Poitou-Charentes",
    "wof:name":"Cellier De Saint Louis",
    "wof:placetype":"venue"
},
  "geometry": {"coordinates":[5.853343,43.393883],"type":"Point"}
}