{
  "type": "Feature",
  "properties": {
    "iso:country":"FR",
    "sg:address":"9, Rue Micka\u00ebl Faraday - ZI des Gailletrous, 41260 La Chauss\u00e9e Saint Victor",
    "sg:city":"La Chauss\u00e9e-Saint-Victor",
    "sg:orig_category":"Non-Classified Establishments",
    "sg:phone":"+33 2 54 55 10 40",
    "sg:postcode":"41260",
    "sg:province":"Centre",
    "wof:name":"Top Assistance 41 S.a.r.l.",
    "wof:placetype":"venue"
},
  "geometry": {"coordinates":[1.354592,47.615322],"type":"Point"}
}