{
  "type": "Feature",
  "properties": {
    "addr:full":"2 Av De F\u00e9tilly 17074 La Rochelle Cedex 9 Champagne",
    "addr:postcode":"17074",
    "addr:street":"Av De Fe\u0301Tilly",
    "iso:country":"FR",
    "sg:address":"2 Av De F\u00e9tilly 17074 La Rochelle Cedex 9",
    "sg:classifiers":[
        {
            "category":"Banks & Credit Unions",
            "subcategory":"Financial Services",
            "type":"Services"
        }
    ],
    "sg:phone":"+33 5 46 34 46 02",
    "sg:province":"Champagne",
    "sg:tags":[
        "banking",
        "finance",
        "insurance"
    ],
    "wof:name":"Centre Departemental Des Jeunes Agriculteurs",
    "wof:placetype":"venue"
},
  "geometry": {"coordinates":[-1.15742,46.173851],"type":"Point"}
}