{
  "type": "Feature",
  "properties": {
    "addr:full":"Rue Jacquard 77400 Lagny Sur Marne Ile de France 77400",
    "addr:postcode":"77400;77400",
    "addr:street":"Rue Jacquard",
    "iso:country":"FR",
    "sg:address":"Rue Jacquard 77400 Lagny Sur Marne",
    "sg:classifiers":[
        {
            "category":"Manufacturing",
            "subcategory":"Metals",
            "type":"Manufacturing & Wholesale Goods"
        }
    ],
    "sg:phone":"+33 1 64 12 71 00",
    "sg:postcode":"77400",
    "sg:province":"Ile de France",
    "sg:tags":[
        "metallurgy",
        "metalworking",
        "processing"
    ],
    "wof:name":"Bodycote Hit",
    "wof:placetype":"venue"
},
  "geometry": {"coordinates":[2.687358,48.874439],"type":"Point"}
}