{
  "type": "Feature",
  "properties": {
    "addr:full":"7, Av. du Clos Rouge, 74200 Thonon les Bains Rhone-Alpes",
    "addr:postcode":"74200",
    "addr:street":"Av. Du Clos Rouge",
    "iso:country":"FR",
    "sg:address":"7, Av. du Clos Rouge, 74200 Thonon les Bains",
    "sg:orig_category":"Unclassifiable Establishments",
    "sg:phone":"+33 4 50 71 35 61",
    "sg:province":"Rhone-Alpes",
    "wof:name":"Meyrier S.a.",
    "wof:placetype":"venue"
},
  "geometry": {"coordinates":[6.496257,46.370495],"type":"Point"}
}