{
  "type": "Feature",
  "properties": {
    "addr:full":"9, Rue Alfred Kastler - ZI le Ried, 67850 Herrlisheim Herrlisheim Alsace 67850",
    "addr:housenumber":"9",
    "addr:postcode":"67850;67850",
    "addr:street":"Rue Alfred Kastler Zi Le Ried",
    "iso:country":"FR",
    "sg:address":"9, Rue Alfred Kastler - ZI le Ried, 67850 Herrlisheim",
    "sg:city":"Herrlisheim",
    "sg:orig_category":"Non-Classified Establishments",
    "sg:phone":"+33 3 88 59 75 15",
    "sg:postcode":"67850",
    "sg:province":"Alsace",
    "wof:name":"Microjet S.a.r.l.",
    "wof:placetype":"venue"
},
  "geometry": {"coordinates":[7.90651,48.729767],"type":"Point"}
}