{
  "type": "Feature",
  "properties": {
    "iso:country":"FR",
    "sg:address":"934 Rue De Bouillargues 30000 Nimes",
    "sg:classifiers":[
        {
            "category":"Utilities",
            "subcategory":"Telephone",
            "type":"Services"
        }
    ],
    "sg:phone":"+33 4 66 84 71 95",
    "sg:province":"Languedoc-Roussillon",
    "sg:tags":[
        "telecommunication"
    ],
    "wof:name":"Societe Nouvelle Lumiere Et Decor",
    "wof:placetype":"venue"
},
  "geometry": {"coordinates":[4.376545,43.829006],"type":"Point"}
}