{
  "type": "Feature",
  "properties": {
    "iso:country":"FR",
    "sg:address":"B.P. 26, 61438 Flers C\u00e9dex^^Usine de Planquivon, 61430 Athis de l'Orne",
    "sg:city":"Berjou",
    "sg:orig_category":"Non-Classified Establishments",
    "sg:phone":"+33 2 33 62 81 00",
    "sg:postcode":"61430",
    "sg:province":"Basse Normandie",
    "wof:name":"Thermocoax S.a.s.",
    "wof:placetype":"venue"
},
  "geometry": {"coordinates":[-0.541717,48.81673],"type":"Point"}
}