{
  "type": "Feature",
  "properties": {
    "addr:full":"151 Rue De Billancourt 92100 Boulogne Billancourt Ile de France 92100",
    "addr:housenumber":"151",
    "addr:postcode":"92100;92100",
    "addr:street":"Rue De Billancourt",
    "iso:country":"FR",
    "sg:address":"151 Rue De Billancourt 92100 Boulogne Billancourt",
    "sg:classifiers":[
        {
            "category":"Professional",
            "subcategory":"Advertising",
            "type":"Services"
        }
    ],
    "sg:phone":"+33 1 46 04 03 03",
    "sg:postcode":"92100",
    "sg:province":"Ile de France",
    "sg:tags":[
        "communication",
        "medium"
    ],
    "wof:name":"Calypso Sa",
    "wof:placetype":"venue"
},
  "geometry": {"coordinates":[2.237511,48.834274],"type":"Point"}
}