{
  "type": "Feature",
  "properties": {
    "addr:full":"Rue De La Guerlande Zone Verte 71880 Chatenoy Le Royal Ch\u00e2tenoy-le-Royal Bourgogne 71880",
    "addr:postcode":"71880;71880",
    "addr:street":"Rue De La Guerlande Zone Verte",
    "iso:country":"FR",
    "sg:address":"Rue De La Guerlande Zone Verte 71880 Chatenoy Le Royal",
    "sg:city":"Ch\u00e2tenoy-le-Royal",
    "sg:orig_category":"Clothing accessories Household goods Textiles and Clothing Wood and Furniture",
    "sg:phone":"+33 3 85 47 87 20",
    "sg:postcode":"71880",
    "sg:province":"Bourgogne",
    "wof:name":"Neyrat Peyronie Parasols",
    "wof:placetype":"venue"
},
  "geometry": {"coordinates":[4.814135,46.795506],"type":"Point"}
}