{
  "type": "Feature",
  "properties": {
    "addr:full":"11, Rue Henri IV, 49510 Jallais Pays de Loire",
    "addr:housenumber":"11",
    "addr:postcode":"49510",
    "addr:street":"Rue Henri Iv",
    "iso:country":"FR",
    "sg:address":"11, Rue Henri IV, 49510 Jallais",
    "sg:orig_category":"Non-Classified Establishments",
    "sg:phone":"+33 2 41 55 65 12",
    "sg:province":"Pays de Loire",
    "wof:name":"S.n.p. S.a.",
    "wof:placetype":"venue"
},
  "geometry": {"coordinates":[-0.862651,47.19606],"type":"Point"}
}