{
  "type": "Feature",
  "properties": {
    "addr:full":"Rue de Borgy - Le Bourg Dezize l\u00e8s Maranges Bourgogne 71150",
    "addr:postcode":"71150",
    "addr:street":"Rue De Borgy Le Bourg",
    "iso:country":"FR",
    "sg:address":"Rue de Borgy - Le Bourg",
    "sg:city":"Dezize l\u00e8s Maranges",
    "sg:orig_category":"Unclassifiable Establishments",
    "sg:phone":"+33 3 85 91 17 19",
    "sg:postcode":"71150",
    "sg:province":"Bourgogne",
    "wof:name":"C.m.m.r. S.a.r.l.",
    "wof:placetype":"venue"
},
  "geometry": {"coordinates":[4.75459,46.910526],"type":"Point"}
}