{
  "type": "Feature",
  "properties": {
    "addr:full":"Route De Coudres 27220 St. Andr\u00e9 De L'Eure Haute Normandie",
    "addr:postcode":"27220",
    "addr:street":"Route De Coudres;Haute Normandie",
    "iso:country":"FR",
    "sg:address":"Route De Coudres 27220 St. Andr\u00e9 De L'Eure",
    "sg:classifiers":[
        {
            "category":"Banks & Credit Unions",
            "subcategory":"Investment Brokerage",
            "type":"Services"
        }
    ],
    "sg:phone":"+33 2 32 23 48 00",
    "sg:province":"Haute Normandie",
    "sg:tags":[
        "-",
        "transport",
        "related"
    ],
    "wof:name":"Ste De Magasinage Et De Gestion Des Stocks",
    "wof:placetype":"venue"
},
  "geometry": {"coordinates":[1.238229,48.898487],"type":"Point"}
}