{
  "type": "Feature",
  "properties": {
    "addr:full":"1 Rue Du Vallon Zi Marolles Nationale 19 94440 Marolles En Brie Ile de France 94440",
    "addr:housenumber":"1",
    "addr:postcode":"94440;94440",
    "addr:street":"Rue Du Vallon Zi;Nationale 19",
    "iso:country":"FR",
    "sg:address":"1 Rue Du Vallon Zi Marolles Nationale 19 94440 Marolles En Brie",
    "sg:classifiers":[
        {
            "category":"Autos & Motor Vehicles",
            "subcategory":"Automobile Sales",
            "type":"Retail Goods"
        }
    ],
    "sg:phone":"+33 1 45 69 60 00",
    "sg:postcode":"94440",
    "sg:province":"Ile de France",
    "sg:tags":[
        "equipment",
        "motor-cars",
        "transport"
    ],
    "wof:name":"Lamberet Constructions Isothermes",
    "wof:placetype":"venue"
},
  "geometry": {"coordinates":[2.53346,48.721809],"type":"Point"}
}