{
  "type": "Feature",
  "properties": {
    "addr:full":"Rte de Carnon Lattes Languedoc-Roussillon 34970",
    "addr:postcode":"34970",
    "addr:street":"Rte De Carnon",
    "iso:country":"FR",
    "sg:address":"Rte de Carnon",
    "sg:city":"Lattes",
    "sg:orig_category":"Non-Classified Establishments",
    "sg:phone":"+33 4 67 65 87 00",
    "sg:postcode":"34970",
    "sg:province":"Languedoc-Roussillon",
    "wof:name":"B.d.i. S.a.s. - B\u00e9daricienne Doras Industries",
    "wof:placetype":"venue"
},
  "geometry": {"coordinates":[3.93241,43.579208],"type":"Point"}
}