{
  "type": "Feature",
  "properties": {
    "iso:country":"FR",
    "sg:address":"Rue de la Station",
    "sg:city":"Aspach le Bas",
    "sg:orig_category":"Non-Classified Establishments",
    "sg:phone":"+33 3 89 48 91 67",
    "sg:postcode":"68700",
    "sg:province":"Alsace",
    "wof:name":"S.a.d.e.f. S.a.r.l. - Soci\u00e9t\u00e9 Alsacienne Pour Le D\u00e9veloppement Et L'etude De La Fertilit\u00e9",
    "wof:placetype":"venue"
},
  "geometry": {"coordinates":[7.14863,47.760044],"type":"Point"}
}