{
  "type": "Feature",
  "properties": {
    "addr:full":"B.P. 115, 02404 Ch\u00e2teau Thierry C\u00e9dex^^Rte Nationale 3, 02400 Blesmes Picardie",
    "addr:housenumber":"b.p. 115;3",
    "addr:postcode":"02404;02400",
    "iso:country":"FR",
    "sg:address":"B.P. 115, 02404 Ch\u00e2teau Thierry C\u00e9dex^^Rte Nationale 3, 02400 Blesmes",
    "sg:orig_category":"Non-Classified Establishments",
    "sg:phone":"+33 3 23 83 21 85",
    "sg:province":"Picardie",
    "wof:name":"Prat Henri Et Ses Fils Parcs Et Jardins Du Val De Marne S.a.r.l.",
    "wof:placetype":"venue"
},
  "geometry": {"coordinates":[3.39314,49.05019],"type":"Point"}
}