{
  "type": "Feature",
  "properties": {
    "addr:full":"1068, Rue de la Gare, 88220 Xertigny Lorraine",
    "addr:housenumber":"1068",
    "addr:postcode":"88220",
    "addr:street":"Rue De La Gare",
    "iso:country":"FR",
    "sg:address":"1068, Rue de la Gare, 88220 Xertigny",
    "sg:orig_category":"Unclassifiable Establishments",
    "sg:phone":"+33 3 29 30 10 12",
    "sg:province":"Lorraine",
    "wof:name":"Mengel S.a.",
    "wof:placetype":"venue"
},
  "geometry": {"coordinates":[6.378985,48.050484],"type":"Point"}
}