{
  "type": "Feature",
  "properties": {
    "addr:full":"B.P. 8, 02201 Soissons C\u00e9dex^^4, Av de Ch\u00e2teau Thierry, 02260 Soissons Picardie 02260",
    "addr:housenumber":"8",
    "addr:postcode":"02201;02260;02260",
    "addr:street":"B.P.;Av De Cha\u0302Teau Thierry",
    "iso:country":"FR",
    "sg:address":"B.P. 8, 02201 Soissons C\u00e9dex^^4, Av de Ch\u00e2teau Thierry, 02260 Soissons",
    "sg:orig_category":"Non-Classified Establishments",
    "sg:phone":"+33 3 23 53 88 30",
    "sg:postcode":"02260",
    "sg:province":"Picardie",
    "wof:name":"Coop\u00e9rative Ax'ion",
    "wof:placetype":"venue"
},
  "geometry": {"coordinates":[3.911019,49.967461],"type":"Point"}
}