{
  "type": "Feature",
  "properties": {
    "iso:country":"FR",
    "sg:address":"199 Rue De Cagny 80000 Amiens",
    "sg:orig_category":"Miscellaneous Products",
    "sg:phone":"+33 3 22 47 21 60",
    "sg:postcode":"80000",
    "sg:province":"Picardie",
    "wof:name":"Devooght Ozenne Rodolphe",
    "wof:placetype":"venue"
},
  "geometry": {"coordinates":[2.319906,49.88166],"type":"Point"}
}