{
  "type": "Feature",
  "properties": {
    "iso:country":"FR",
    "sg:address":"13, Place de l'Eglise, 28150 Voves",
    "sg:city":"Voves",
    "sg:orig_category":"Unclassifiable Establishments",
    "sg:phone":"+33 2 37 18 07 77",
    "sg:postcode":"28150",
    "sg:province":"Centre",
    "wof:name":"Etablissements Dreux S.a.r.l.",
    "wof:placetype":"venue"
},
  "geometry": {"coordinates":[1.626986,48.271683],"type":"Point"}
}