{
  "type": "Feature",
  "properties": {
    "addr:full":"8, Impasse des Jades - Technoparc de l'Aubini\u00e8re, 44000 Nantes Pays de Loire",
    "addr:housenumber":"8",
    "addr:postcode":"44000",
    "addr:street":"Impasse Des Jades Technoparc De L'Aubinie \u0300Re",
    "iso:country":"FR",
    "sg:address":"8, Impasse des Jades - Technoparc de l'Aubini\u00e8re, 44000 Nantes",
    "sg:orig_category":"Unclassifiable Establishments",
    "sg:phone":"+33 2 40 50 56 56",
    "sg:province":"Pays de Loire",
    "wof:name":"Sage France S.a.",
    "wof:placetype":"venue"
},
  "geometry": {"coordinates":[-1.567257,47.229397],"type":"Point"}
}