{
  "type": "Feature",
  "properties": {
    "iso:country":"FR",
    "sg:address":"3, Rue Graham Bell, 57000 Metz",
    "sg:orig_category":"Unclassifiable Establishments",
    "sg:phone":"+33 3 87 37 04 71",
    "sg:province":"Lorraine",
    "wof:name":"Gutenberg Imprimeur Conseil S.a.r.l.",
    "wof:placetype":"venue"
},
  "geometry": {"coordinates":[6.221757,49.10569],"type":"Point"}
}