{
  "type": "Feature",
  "properties": {
    "addr:full":"24-26; Rue do la Pepiniere; Paris; 75008 Ile de France",
    "addr:housenumber":"24-26",
    "addr:postcode":"75008 ile",
    "addr:street":"Rue Do La Pepiniere",
    "iso:country":"FR",
    "sg:address":"24-26; Rue do la Pepiniere; Paris; 75008",
    "sg:classifiers":[
        {
            "category":"Travel",
            "subcategory":"Travel Agent",
            "type":"Entertainment"
        }
    ],
    "sg:province":"Ile de France",
    "wof:name":"Japan Railways Group",
    "wof:placetype":"venue"
},
  "geometry": {"coordinates":[2.321002,48.875065],"type":"Point"}
}