{
  "type": "Feature",
  "properties": {
    "addr:full":"Rue Des Freres Lumiere Arlod 01200 Bellegarde Sur Valserine Rhone-Alpes 01200",
    "addr:postcode":"01200;01200",
    "addr:street":"Rue Des Freres;Arlod;Rhone-Alpes",
    "iso:country":"FR",
    "sg:address":"Rue Des Freres Lumiere Arlod 01200 Bellegarde Sur Valserine",
    "sg:classifiers":[
        {
            "category":"Professional",
            "subcategory":"Engineering",
            "type":"Services"
        }
    ],
    "sg:phone":"+33 4 50 56 67 00",
    "sg:postcode":"01200",
    "sg:province":"Rhone-Alpes",
    "sg:tags":[
        "machine",
        "-",
        "mechanical"
    ],
    "wof:name":"Elastotech",
    "wof:placetype":"venue"
},
  "geometry": {"coordinates":[5.817305,46.089676],"type":"Point"}
}