{
  "type": "Feature",
  "properties": {
    "addr:full":"B.P. 59, 18230 Saint Doulchard C\u00e9dex^^275, Rte de Malitorne, 18230 Saint Doulchard Saint-Doulchard Centre 18230",
    "addr:postcode":"18230;18230;18230",
    "addr:street":"B.P. 59;Rte De Malitorne",
    "iso:country":"FR",
    "sg:address":"B.P. 59, 18230 Saint Doulchard C\u00e9dex^^275, Rte de Malitorne, 18230 Saint Doulchard",
    "sg:city":"Saint-Doulchard",
    "sg:orig_category":"Non-Classified Establishments",
    "sg:phone":"+33 2 48 24 22 14",
    "sg:postcode":"18230",
    "sg:province":"Centre",
    "wof:name":"Euro Nickelroc S.a.r.l.",
    "wof:placetype":"venue"
},
  "geometry": {"coordinates":[2.35792,47.104084],"type":"Point"}
}