{
  "type": "Feature",
  "properties": {
    "addr:full":"Promenade Roger Denouette 76111 Yport Haute Normandie 76111",
    "addr:postcode":"76111;76111",
    "addr:street":"Promenade Roger Denouette;Haute Normandie",
    "iso:country":"FR",
    "sg:address":"Promenade Roger Denouette 76111 Yport",
    "sg:classifiers":[
        {
            "category":"Sports & Exercise",
            "subcategory":"Sports Center",
            "type":"Entertainment"
        }
    ],
    "sg:phone":"+33 2 35 28 77 36",
    "sg:postcode":"76111",
    "sg:province":"Haute Normandie",
    "sg:tags":[
        "game"
    ],
    "wof:name":"Yport Loisirs Sa",
    "wof:placetype":"venue"
},
  "geometry": {"coordinates":[0.308616,49.73941],"type":"Point"}
}