{
  "type": "Feature",
  "properties": {
    "addr:full":"25360 Bouclans Franche Comt\u00e9 25360",
    "addr:postcode":"25360;25360",
    "addr:street":"Franche Comte\u0301",
    "iso:country":"FR",
    "sg:address":"25360 Bouclans",
    "sg:classifiers":[
        {
            "category":"Wholesale",
            "subcategory":"Machinery & Supplies",
            "type":"Manufacturing & Wholesale Goods"
        }
    ],
    "sg:phone":"+33 3 81 55 28 52",
    "sg:postcode":"25360",
    "sg:province":"Franche Comt\u00e9",
    "sg:tags":[
        "-",
        "machine",
        "equipment",
        "engineering",
        "animal",
        "mechanical",
        "breeding",
        "agriculture"
    ],
    "wof:name":"Dimag France",
    "wof:placetype":"venue"
},
  "geometry": {"coordinates":[6.238805,47.245998],"type":"Point"}
}