{
  "type": "Feature",
  "properties": {
    "addr:full":"Rte Marsangis Allemanche Launay et Soyer Champagne 51260",
    "addr:postcode":"51260",
    "addr:street":"Rte Marsangis Allemanche Launay Et Soyer Champagne",
    "iso:country":"FR",
    "sg:address":"Rte Marsangis",
    "sg:city":"Allemanche Launay et Soyer",
    "sg:orig_category":"Unclassifiable Establishments",
    "sg:phone":"+33 3 26 42 72 10",
    "sg:postcode":"51260",
    "sg:province":"Champagne",
    "wof:name":"A.p.m. D\u00e9shy - Union Coop\u00e9rative De D\u00e9shydratation",
    "wof:placetype":"venue"
},
  "geometry": {"coordinates":[3.78155,48.554821],"type":"Point"}
}