{
  "type": "Feature",
  "properties": {
    "addr:full":"22, Rue du Docteur Ageorge, 94290 Villeneuve le Roi Ile de France",
    "addr:housenumber":"22",
    "addr:postcode":"94290",
    "addr:street":"Rue Du Docteur Ageorge",
    "iso:country":"FR",
    "sg:address":"22, Rue du Docteur Ageorge, 94290 Villeneuve le Roi",
    "sg:orig_category":"Non-Classified Establishments",
    "sg:phone":"+33 1 49 61 12 12",
    "sg:province":"Ile de France",
    "wof:name":"F.a.i.c. S.a. -fournitures Et Adh\u00e9sifs Pour Industries Et Commerces",
    "wof:placetype":"venue"
},
  "geometry": {"coordinates":[2.422432,48.732929],"type":"Point"}
}