{
  "type": "Feature",
  "properties": {
    "iso:country":"FR",
    "sg:address":"27, Rue Stratman, 90000 Belfort",
    "sg:orig_category":"Unclassifiable Establishments",
    "sg:phone":"+33 3 84 22 80 21",
    "sg:province":"Franche Comt\u00e9",
    "wof:name":"Parte-co S.a.r.l.",
    "wof:placetype":"venue"
},
  "geometry": {"coordinates":[6.863753,47.639225],"type":"Point"}
}