{
  "type": "Feature",
  "properties": {
    "iso:country":"FR",
    "sg:address":"Les Froidures 01140 Saint Etienne sur Chalaronne",
    "sg:orig_category":"Unclassifiable Establishments",
    "sg:phone":"+33 4 74 24 04 65",
    "sg:postcode":"01140",
    "sg:province":"Rhone-Alpes",
    "wof:name":"Entreprise Pitron Patrick",
    "wof:placetype":"venue"
},
  "geometry": {"coordinates":[4.863384,46.139706],"type":"Point"}
}