{
  "type": "Feature",
  "properties": {
    "iso:country":"FR",
    "sg:address":"Zi 76450 Cany Barville",
    "sg:classifiers":[
        {
            "category":"Manufacturing",
            "subcategory":"Rubber & Plastics",
            "type":"Manufacturing & Wholesale Goods"
        }
    ],
    "sg:phone":"+33 2 35 57 81 82",
    "sg:province":"Haute Normandie",
    "wof:name":"Ste Des Polymeres Techniques Sa",
    "wof:placetype":"venue"
},
  "geometry": {"coordinates":[0.619919,49.694202],"type":"Point"}
}