{
  "type": "Feature",
  "properties": {
    "addr:full":"171, Rue Roger Salengro, 69100 Villeurbanne Rhone-Alpes",
    "addr:housenumber":"171",
    "addr:postcode":"69100",
    "addr:street":"Rue Roger Salengro",
    "iso:country":"FR",
    "sg:address":"171, Rue Roger Salengro, 69100 Villeurbanne",
    "sg:orig_category":"Unclassifiable Establishments",
    "sg:phone":"+33 4 72 69 12 69",
    "sg:province":"Rhone-Alpes",
    "wof:name":"Informatique Appliqu\u00e9e S.a.r.l.",
    "wof:placetype":"venue"
},
  "geometry": {"coordinates":[4.885921,45.781593],"type":"Point"}
}