{
  "type": "Feature",
  "properties": {
    "iso:country":"FR",
    "sg:address":"La Salamandri\u00e9 81150 Sainte Croix",
    "sg:orig_category":"Non-Classified Establishments",
    "sg:phone":"+33 5 63 56 80 52",
    "sg:postcode":"81150",
    "sg:province":"Midi Pyr\u00e9n\u00e9es",
    "wof:name":"Denis Balaran E.a.r.l.",
    "wof:placetype":"venue"
},
  "geometry": {"coordinates":[2.060839,43.97266],"type":"Point"}
}