{
  "type": "Feature",
  "properties": {
    "addr:full":"Rte du Circuit de Magny-cours Saint Parize le Ch\u00e2tel Bourgogne 58490",
    "addr:postcode":"58490",
    "addr:street":"Rte Du Circuit De Magny-Cours Saint Parize",
    "iso:country":"FR",
    "sg:address":"Rte du Circuit de Magny-cours",
    "sg:city":"Saint Parize le Ch\u00e2tel",
    "sg:orig_category":"Unclassifiable Establishments",
    "sg:phone":"+33 3 86 21 22 22",
    "sg:postcode":"58490",
    "sg:province":"Bourgogne",
    "wof:name":"Martinat S.a.",
    "wof:placetype":"venue"
},
  "geometry": {"coordinates":[3.18207,46.85421],"type":"Point"}
}