{
  "type": "Feature",
  "properties": {
    "addr:full":"Rue Ir\u00e9ne Joliot Curie - Parc d'Activit\u00e9s de Ruires Saint Martin d'H\u00e8res Rhone-Alpes 38400",
    "addr:postcode":"38400",
    "addr:street":"Rue Ire\u0301Ne Joliot Curie Parc D'Activite \u0301S De Ruires;Rhone-Alpes",
    "iso:country":"FR",
    "sg:address":"Rue Ir\u00e9ne Joliot Curie - Parc d'Activit\u00e9s de Ruires",
    "sg:city":"Saint Martin d'H\u00e8res",
    "sg:orig_category":"Unclassifiable Establishments",
    "sg:phone":"+33 4 76 24 02 36",
    "sg:postcode":"38400",
    "sg:province":"Rhone-Alpes",
    "wof:name":"G.m.p. A.t.i.m. S.a.",
    "wof:placetype":"venue"
},
  "geometry": {"coordinates":[5.768643,45.179626],"type":"Point"}
}