{
  "type": "Feature",
  "properties": {
    "addr:full":"52 R Du Commandant Duval 92140 Clamart Ile de France 92140",
    "addr:housenumber":"52",
    "addr:postcode":"92140;ile;92140",
    "addr:street":"R Du Commandant Duval;France",
    "iso:country":"FR",
    "sg:address":"52 R Du Commandant Duval 92140 Clamart",
    "sg:classifiers":[
        {
            "category":"Shopping",
            "subcategory":"Clothing, Apparel, & Fashions",
            "type":"Retail Goods"
        }
    ],
    "sg:phone":"+33 1 46 32 52 22",
    "sg:postcode":"92140",
    "sg:province":"Ile de France",
    "sg:tags":[
        "textile",
        "clothing",
        "clothes"
    ],
    "wof:name":"Mme Piric Armen Linda",
    "wof:placetype":"venue"
},
  "geometry": {"coordinates":[2.23393,48.782139],"type":"Point"}
}