{
  "type": "Feature",
  "properties": {
    "iso:country":"FR",
    "sg:address":"9, Rue des Charrons, 60480 Saint Andr\u00e9 Farivillers",
    "sg:orig_category":"Unclassifiable Establishments",
    "sg:phone":"+33 3 44 80 60 20",
    "sg:province":"Picardie",
    "wof:name":"Caulle S.a. - Constructions M\u00e9talliques M\u00e9cano-soudure",
    "wof:placetype":"venue"
},
  "geometry": {"coordinates":[2.324675,49.582798],"type":"Point"}
}