{
  "type": "Feature",
  "properties": {
    "addr:full":"111/113, Rue de Longchamp, 75116 Paris Picardie",
    "addr:housenumber":"111 / 113",
    "addr:postcode":"75116",
    "addr:street":"Rue De Longchamp",
    "iso:country":"FR",
    "sg:address":"111/113, Rue de Longchamp, 75116 Paris",
    "sg:orig_category":"Non-Classified Establishments",
    "sg:phone":"+33 1 44 05 56 00",
    "sg:province":"Picardie",
    "wof:name":"Gerling France",
    "wof:placetype":"venue"
},
  "geometry": {"coordinates":[2.279361,48.866653],"type":"Point"}
}