{
  "type": "Feature",
  "properties": {
    "addr:full":"B.P. 46 Thann C\u00e9dex Alsace 68801",
    "addr:postcode":"68801",
    "addr:street":"B.P. 46;Ce\u0301Dex",
    "iso:country":"FR",
    "sg:address":"B.P. 46",
    "sg:city":"Thann C\u00e9dex",
    "sg:orig_category":"Non-Classified Establishments",
    "sg:phone":"+33 3 89 38 53 53",
    "sg:postcode":"68801",
    "sg:province":"Alsace",
    "wof:name":"Riby S.a.",
    "wof:placetype":"venue"
},
  "geometry": {"coordinates":[7.10335,47.810196],"type":"Point"}
}