{
  "type": "Feature",
  "properties": {
    "iso:country":"FR",
    "sg:address":"B.P. 92, 02004 Laon C\u00e9dex^^32, Rue Linotte, 02000 Laon",
    "sg:orig_category":"Non-Classified Establishments",
    "sg:phone":"+33 3 23 79 16 15",
    "sg:province":"Picardie",
    "wof:name":"S.a.b. S.a.r.l. - Soci\u00e9t\u00e9 Agglom\u00e8r\u00e9 B\u00e9ton - Boucard Et Compagnie",
    "wof:placetype":"venue"
},
  "geometry": {"coordinates":[3.6064,49.556999],"type":"Point"}
}