{
  "type": "Feature",
  "properties": {
    "iso:country":"FR",
    "sg:address":"11 Rte De Nanfray 74960 Cran Gevrier",
    "sg:classifiers":[
        {
            "category":"Shopping",
            "subcategory":"Computers & Home Electronics",
            "type":"Retail Goods"
        }
    ],
    "sg:phone":"+33 4 50 69 34 31",
    "sg:postcode":"74960",
    "sg:province":"Rhone-Alpes",
    "sg:tags":[
        "equipment",
        "electrical",
        "component",
        "electric",
        "electronic"
    ],
    "wof:name":"Tam\u00c9 (technologies Appliquees A La Micro-electronique)",
    "wof:placetype":"venue"
},
  "geometry": {"coordinates":[6.087343,45.892162],"type":"Point"}
}