{
  "type": "Feature",
  "properties": {
    "iso:country":"FR",
    "sg:address":"170 Rue General Andrea 01100 Arbent",
    "sg:classifiers":[
        {
            "category":"Health Services",
            "subcategory":"Optometrist",
            "type":"Services"
        }
    ],
    "sg:phone":"+33 4 74 77 61 47",
    "sg:postcode":"01100",
    "sg:province":"Rhone-Alpes",
    "sg:tags":[
        "instrument",
        "optical",
        "-",
        "precision",
        "equipment"
    ],
    "wof:name":"Artplast",
    "wof:placetype":"venue"
},
  "geometry": {"coordinates":[5.67727,46.292881],"type":"Point"}
}