{
  "type": "Feature",
  "properties": {
    "addr:full":"B.P. 31507, 44315 Nantes C\u00e9dex 3^^1, Rue du Ch\u00e2teau de l'Eraudi\u00e8re, 44300 Nantes Pays de Loire 44300",
    "addr:housenumber":"3;^ 1",
    "addr:postcode":"44315;44300;44300",
    "addr:street":"^;Rue Du Cha\u0302Teau De L'Eraudie \u0300Re",
    "iso:country":"FR",
    "sg:address":"B.P. 31507, 44315 Nantes C\u00e9dex 3^^1, Rue du Ch\u00e2teau de l'Eraudi\u00e8re, 44300 Nantes",
    "sg:orig_category":"Non-Classified Establishments",
    "sg:phone":"+33 2 40 18 77 77",
    "sg:postcode":"44300",
    "sg:province":"Pays de Loire",
    "wof:name":"Capfor Atlantique S.a.r.l.",
    "wof:placetype":"venue"
},
  "geometry": {"coordinates":[-1.540981,47.238392],"type":"Point"}
}