{
  "type": "Feature",
  "properties": {
    "iso:country":"FR",
    "sg:address":"B.P. 26,^^Chemin du Teppe, 73460 Frontenex",
    "sg:orig_category":"Non-Classified Establishments",
    "sg:phone":"+33 4 79 38 51 79",
    "sg:postcode":"73460",
    "sg:province":"Rhone-Alpes",
    "wof:name":"Martin-belaysoud S.a.",
    "wof:placetype":"venue"
},
  "geometry": {"coordinates":[6.306249,45.587067],"type":"Point"}
}