{
  "type": "Feature",
  "properties": {
    "addr:full":"76, Bd Piot - B\u00e2t. E, 13008 Marseille Poitou-Charentes",
    "addr:housenumber":"76;ba\u0302t e",
    "addr:postcode":"13008",
    "addr:street":"Bd Piot",
    "iso:country":"FR",
    "sg:address":"76, Bd Piot - B\u00e2t. E, 13008 Marseille",
    "sg:orig_category":"Non-Classified Establishments",
    "sg:phone":"+33 4 91 72 43 62",
    "sg:province":"Poitou-Charentes",
    "wof:name":"Cabart Michel",
    "wof:placetype":"venue"
},
  "geometry": {"coordinates":[5.373782,43.240643],"type":"Point"}
}