{
  "type": "Feature",
  "properties": {
    "iso:country":"FR",
    "sg:address":"15 Avenue Du 24 Aout 1944 Zi 69960 Corbas",
    "sg:classifiers":[
        {
            "category":"Manufacturing",
            "subcategory":"Glass & Minerals",
            "type":"Manufacturing & Wholesale Goods"
        }
    ],
    "sg:phone":"+33 4 72 90 00 83",
    "sg:postcode":"69960",
    "sg:province":"Rhone-Alpes",
    "sg:tags":[
        "building",
        "material"
    ],
    "wof:name":"Solyver",
    "wof:placetype":"venue"
},
  "geometry": {"coordinates":[4.91598,45.678814],"type":"Point"}
}