{
  "type": "Feature",
  "properties": {
    "addr:full":"Za Du Saosnois 72600 Mamers Pays de Loire 72600",
    "addr:postcode":"72600;72600",
    "addr:street":"Za Du Saosnois",
    "iso:country":"FR",
    "sg:address":"Za Du Saosnois 72600 Mamers",
    "sg:classifiers":[
        {
            "category":"Shopping",
            "subcategory":"Computers & Home Electronics",
            "type":"Retail Goods"
        }
    ],
    "sg:phone":"+33 2 43 31 15 40",
    "sg:postcode":"72600",
    "sg:province":"Pays de Loire",
    "sg:tags":[
        "electric",
        "appliance",
        "household",
        "component",
        "equipment",
        "electrical",
        "electronic"
    ],
    "wof:name":"Mamers Injection",
    "wof:placetype":"venue"
},
  "geometry": {"coordinates":[0.368685,48.350681],"type":"Point"}
}