{
  "type": "Feature",
  "properties": {
    "addr:full":"B.P. 185, 59018 Lille C\u00e9dex^^2, Rue Balzac, 59000 Lille Nord Pas-de-Calais",
    "addr:housenumber":"b.p. 185",
    "addr:postcode":"59018;59000",
    "addr:street":"Rue Balzac",
    "iso:country":"FR",
    "sg:address":"B.P. 185, 59018 Lille C\u00e9dex^^2, Rue Balzac, 59000 Lille",
    "sg:orig_category":"Non-Classified Establishments",
    "sg:phone":"+33 3 20 18 30 60",
    "sg:province":"Nord Pas-de-Calais",
    "wof:name":"Facen S.a.",
    "wof:placetype":"venue"
},
  "geometry": {"coordinates":[3.06281,50.637184],"type":"Point"}
}