{
  "type": "Feature",
  "properties": {
    "iso:country":"FR",
    "sg:address":"B.P. 745, 03007 Moulins C\u00e9dex^^Rue du Champ Fromager, 03400 Yzeure",
    "sg:city":"Yzeure",
    "sg:orig_category":"Non-Classified Establishments",
    "sg:phone":"+33 4 70 44 41 20",
    "sg:postcode":"03400",
    "sg:province":"Auvergne",
    "wof:name":"Flag\u00e9lectric S.a.",
    "wof:placetype":"venue"
},
  "geometry": {"coordinates":[3.37215,46.573559],"type":"Point"}
}