{
  "type": "Feature",
  "properties": {
    "addr:full":"93, Bd de la Valbarelle, 13011 Marseille Provence-Alpes-C\u00f4te d'Azur",
    "addr:housenumber":"93",
    "addr:postcode":"13011",
    "addr:street":"Bd De La Valbarelle",
    "iso:country":"FR",
    "sg:address":"93, Bd de la Valbarelle, 13011 Marseille",
    "sg:orig_category":"Unclassifiable Establishments",
    "sg:phone":"+33 4 91 45 56 48",
    "sg:province":"Provence-Alpes-C\u00f4te d'Azur",
    "wof:name":"Sericom S.a.r.l.",
    "wof:placetype":"venue"
},
  "geometry": {"coordinates":[5.447798,43.287876],"type":"Point"}
}