{
  "type": "Feature",
  "properties": {
    "addr:full":"17380 Tonnay Boutonne Poitou-Charentes",
    "addr:housenumber":"17380",
    "addr:street":"Tonnay Boutonne",
    "iso:country":"FR",
    "sg:address":"17380 Tonnay Boutonne",
    "sg:orig_category":"Unclassifiable Establishments",
    "sg:phone":"+33 5 46 07 06 14",
    "sg:province":"Poitou-Charentes",
    "wof:name":"Soci\u00e9t\u00e9 Coop\u00e9ratives Agricoles Charentes",
    "wof:placetype":"venue"
},
  "geometry": {"coordinates":[-0.709779,45.96669],"type":"Point"}
}