{
  "type": "Feature",
  "properties": {
    "addr:full":"30-32 Av Des Fond\u00e8re 31200 Toulouse Midi Pyr\u00e9n\u00e9es 31200",
    "addr:housenumber":"30-32",
    "addr:postcode":"31200;31200",
    "addr:street":"Av Des Fonde\u0300Re",
    "iso:country":"FR",
    "sg:address":"30-32 Av Des Fond\u00e8re 31200 Toulouse",
    "sg:classifiers":[
        {
            "category":"Manufacturing",
            "subcategory":"Metals",
            "type":"Manufacturing & Wholesale Goods"
        }
    ],
    "sg:phone":"+33 5 61 13 57 17",
    "sg:postcode":"31200",
    "sg:province":"Midi Pyr\u00e9n\u00e9es",
    "sg:tags":[
        "metallurgy",
        "steel",
        "metalworking"
    ],
    "wof:name":"Ste Traitements Chimiques Des Metaux",
    "wof:placetype":"venue"
},
  "geometry": {"coordinates":[1.426416,43.63752],"type":"Point"}
}