{
  "type": "Feature",
  "properties": {
    "addr:full":"Route Du Champ De Courses 50350 Donville Les Bains Donville-les-Bains Basse Normandie 50350",
    "addr:postcode":"50350;50350",
    "addr:street":"Route Du Champ De Courses",
    "iso:country":"FR",
    "sg:address":"Route Du Champ De Courses 50350 Donville Les Bains",
    "sg:city":"Donville-les-Bains",
    "sg:classifiers":[
        {
            "category":"Manufacturing",
            "subcategory":"Glass & Minerals",
            "type":"Manufacturing & Wholesale Goods"
        }
    ],
    "sg:phone":"+33 2 33 50 64 34",
    "sg:postcode":"50350",
    "sg:province":"Basse Normandie",
    "sg:tags":[
        "building",
        "material"
    ],
    "wof:name":"Beton De France Normandie",
    "wof:placetype":"venue"
},
  "geometry": {"coordinates":[-1.579353,48.852161],"type":"Point"}
}