{
  "type": "Feature",
  "properties": {
    "addr:full":"avenue Leon Jouhaux 33210 Langon Langon Aquitaine 33210",
    "addr:postcode":"33210;33210",
    "addr:street":"Avenue Leon Jouhaux",
    "iso:country":"FR",
    "sg:address":"avenue Leon Jouhaux 33210 Langon",
    "sg:city":"Langon",
    "sg:classifiers":[
        {
            "category":"Building & Trades",
            "subcategory":"Equipment Rental",
            "type":"Services"
        }
    ],
    "sg:phone":"+33 5 56 34 02 14",
    "sg:postcode":"33210",
    "sg:province":"Aquitaine",
    "sg:tags":[
        "aircraft",
        "charter"
    ],
    "wof:name":"Airlec Air Espace S.a.r.l.",
    "wof:placetype":"venue"
},
  "geometry": {"coordinates":[-0.264703,44.547054],"type":"Point"}
}