{
  "type": "Feature",
  "properties": {
    "addr:full":"1 Rue Des Pyr\u00e9n\u00e9es 94150 Rungis Ile de France 94150",
    "addr:housenumber":"1",
    "addr:postcode":"94150;94150",
    "addr:street":"Rue Des Pyre\u0301Ne\u0301Es",
    "iso:country":"FR",
    "sg:address":"1 Rue Des Pyr\u00e9n\u00e9es 94150 Rungis",
    "sg:classifiers":[
        {
            "category":"Professional",
            "subcategory":"Engineering",
            "type":"Services"
        }
    ],
    "sg:phone":"+33 1 41 80 25 50",
    "sg:postcode":"94150",
    "sg:province":"Ile de France",
    "sg:tags":[
        "machine",
        "-",
        "mechanical"
    ],
    "wof:name":"Branson Ultrasons",
    "wof:placetype":"venue"
},
  "geometry": {"coordinates":[2.34848,48.741215],"type":"Point"}
}