{
  "type": "Feature",
  "properties": {
    "iso:country":"FR",
    "sg:address":"79 avenue Louis Roche 92230 Gennevilliers",
    "sg:classifiers":[
        {
            "category":"Shopping",
            "subcategory":"Discount & Variety Stores",
            "type":"Retail Goods"
        }
    ],
    "sg:phone":"+33 1 41 32 21 21",
    "sg:postcode":"92230",
    "sg:province":"Ile de France",
    "sg:tags":[
        "storage",
        "medium",
        "data"
    ],
    "wof:name":"Datamedia Snc",
    "wof:placetype":"venue"
},
  "geometry": {"coordinates":[2.317608,48.925133],"type":"Point"}
}