{
  "type": "Feature",
  "properties": {
    "iso:country":"FR",
    "sg:address":"Za De La Lande 49170 St-Georges-Sur-Loire",
    "sg:classifiers":[
        {
            "category":"Shopping",
            "type":"Retail Goods"
        }
    ],
    "sg:phone":"+33 2 41 72 16 82",
    "sg:postcode":"49170",
    "sg:province":"Pays de Loire",
    "sg:tags":[
        "metallurgy",
        "finished",
        "-",
        "metalworking",
        "metallic"
    ],
    "wof:name":"Stif",
    "wof:placetype":"venue"
},
  "geometry": {"coordinates":[-0.760769,47.40876],"type":"Point"}
}