{
  "type": "Feature",
  "properties": {
    "addr:full":"15 Rue Soufflot 75005 Paris Ile de France",
    "addr:housenumber":"15",
    "addr:postcode":"75005",
    "addr:street":"Rue Soufflot",
    "iso:country":"FR",
    "sg:address":"15 Rue Soufflot 75005 Paris",
    "sg:classifiers":[
        {
            "category":"Professional",
            "subcategory":"Printing & Photocopies",
            "type":"Services"
        }
    ],
    "sg:phone":"+33 1 44 41 64 84",
    "sg:province":"Ile de France",
    "sg:tags":[
        "publishing"
    ],
    "wof:name":"Editions Odile Jacob Sa",
    "wof:placetype":"venue"
},
  "geometry": {"coordinates":[2.342082,48.84692],"type":"Point"}
}