{
  "type": "Feature",
  "properties": {
    "addr:full":"70, Rue Jean Bart, 59110 La Madeleine Nord Pas-de-Calais",
    "addr:housenumber":"70",
    "addr:postcode":"59110",
    "addr:street":"Rue Jean Bart",
    "iso:country":"FR",
    "sg:address":"70, Rue Jean Bart, 59110 La Madeleine",
    "sg:orig_category":"Unclassifiable Establishments",
    "sg:phone":"+33 3 20 55 04 97",
    "sg:province":"Nord Pas-de-Calais",
    "wof:name":"Billiet Etablissements S.a.",
    "wof:placetype":"venue"
},
  "geometry": {"coordinates":[3.079376,50.652641],"type":"Point"}
}