{
  "type": "Feature",
  "properties": {
    "iso:country":"FR",
    "sg:address":"Zi 71210 Torcy",
    "sg:city":"Torcy",
    "sg:classifiers":[
        {
            "category":"Shopping",
            "type":"Retail Goods"
        }
    ],
    "sg:phone":"+33 3 85 55 17 00",
    "sg:postcode":"71210",
    "sg:province":"Bourgogne",
    "sg:tags":[
        "metallurgy",
        "finished",
        "-",
        "metalworking",
        "metallic"
    ],
    "wof:name":"Carlier Sa",
    "wof:placetype":"venue"
},
  "geometry": {"coordinates":[4.463261,46.713284],"type":"Point"}
}