{
  "type": "Feature",
  "properties": {
    "iso:country":"FR",
    "sg:address":"Ctre De Mar\u00e9e Le Port 85800 St Gilles Croix De Vie",
    "sg:classifiers":[
        {
            "category":"Farming",
            "subcategory":"Livestock Farm",
            "type":"Manufacturing & Wholesale Goods"
        }
    ],
    "sg:phone":"+33 2 51 60 00 70",
    "sg:postcode":"85800",
    "sg:province":"Pays de Loire",
    "sg:tags":[
        "breeding",
        "agriculture",
        "animal"
    ],
    "wof:name":"La Maree Vendeenne Sa",
    "wof:placetype":"venue"
},
  "geometry": {"coordinates":[-1.884384,46.671253],"type":"Point"}
}