{
  "type": "Feature",
  "properties": {
    "addr:full":"10 Rue De Beauregard Pincon 45330 Malesherbes Malesherbes Centre 45330",
    "addr:housenumber":"10",
    "addr:postcode":"45330;45330",
    "addr:street":"Rue De Beauregard Pincon;Malesherbes",
    "iso:country":"FR",
    "sg:address":"10 Rue De Beauregard Pincon 45330 Malesherbes",
    "sg:city":"Malesherbes",
    "sg:classifiers":[
        {
            "category":"Shopping",
            "subcategory":"Computers & Home Electronics",
            "type":"Retail Goods"
        }
    ],
    "sg:phone":"+33 2 38 34 77 29",
    "sg:postcode":"45330",
    "sg:province":"Centre",
    "sg:tags":[
        "electronic",
        "electrical",
        "equipment"
    ],
    "wof:name":"Sarl Cbs Distribution",
    "wof:placetype":"venue"
},
  "geometry": {"coordinates":[2.41541,48.296745],"type":"Point"}
}