{
  "type": "Feature",
  "properties": {
    "addr:full":"Rue Henry Le Chatelier Za La Chartreuse 81100 Castres Midi Pyr\u00e9n\u00e9es 81100",
    "addr:postcode":"81100;81100",
    "addr:street":"Rue Henry Le Chatelier Za La",
    "iso:country":"FR",
    "sg:address":"Rue Henry Le Chatelier Za La Chartreuse 81100 Castres",
    "sg:classifiers":[
        {
            "category":"Shopping",
            "subcategory":"Hobbies, Toys, & Games",
            "type":"Retail Goods"
        }
    ],
    "sg:phone":"+33 5 63 35 08 02",
    "sg:postcode":"81100",
    "sg:province":"Midi Pyr\u00e9n\u00e9es",
    "sg:tags":[
        "product",
        "miscellaneous",
        "entertainment"
    ],
    "wof:name":"Papeteries Des Salvages",
    "wof:placetype":"venue"
},
  "geometry": {"coordinates":[2.257356,43.56094],"type":"Point"}
}