{
  "type": "Feature",
  "properties": {
    "addr:full":"4, Av. des Marguerites, 94380 Bonneuil sur Marne Ile de France",
    "addr:postcode":"94380",
    "addr:street":"Av. Des Marguerites",
    "iso:country":"FR",
    "sg:address":"4, Av. des Marguerites, 94380 Bonneuil sur Marne",
    "sg:orig_category":"Non-Classified Establishments",
    "sg:phone":"+33 1 45 13 92 00",
    "sg:province":"Ile de France",
    "wof:name":"Tagg Informatique S.a.",
    "wof:placetype":"venue"
},
  "geometry": {"coordinates":[2.493985,48.768517],"type":"Point"}
}