{
  "type": "Feature",
  "properties": {
    "iso:country":"FR",
    "sg:address":"43, Rte de Thionville, 57185 Vitry sur Orne",
    "sg:orig_category":"Unclassifiable Establishments",
    "sg:phone":"+33 3 87 58 22 32",
    "sg:province":"Lorraine",
    "wof:name":"Barri\u00e8re Et Compagnie S.a.r.l.",
    "wof:placetype":"venue"
},
  "geometry": {"coordinates":[6.111953,49.266747],"type":"Point"}
}