{
  "type": "Feature",
  "properties": {
    "addr:full":"1, Av. du Pr\u00e9sident Pompidou, 92508 Rueil Malmaison C\u00e9dex Picardie",
    "addr:postcode":"92508",
    "addr:street":"Av. Du Pre\u0301Sident Pompidou",
    "iso:country":"FR",
    "sg:address":"1, Av. du Pr\u00e9sident Pompidou, 92508 Rueil Malmaison C\u00e9dex",
    "sg:orig_category":"Non-Classified Establishments",
    "sg:phone":"+33 1 41 39 09 90",
    "sg:province":"Picardie",
    "wof:name":"Sonex S.n.c.",
    "wof:placetype":"venue"
},
  "geometry": {"coordinates":[2.190607,48.873276],"type":"Point"}
}