{
  "type": "Feature",
  "properties": {
    "addr:full":"Rte de Saint Alv\u00e8re Bergerac Aquitaine 24100",
    "addr:postcode":"24100",
    "addr:street":"Rte De Saint Alve\u0300Re",
    "iso:country":"FR",
    "sg:address":"Rte de Saint Alv\u00e8re",
    "sg:city":"Bergerac",
    "sg:orig_category":"Unclassifiable Establishments",
    "sg:phone":"+33 5 53 57 07 25",
    "sg:postcode":"24100",
    "sg:province":"Aquitaine",
    "wof:name":"Arcadie Distribution Sud Ouest",
    "wof:placetype":"venue"
},
  "geometry": {"coordinates":[0.460435,44.851452],"type":"Point"}
}