{
  "type": "Feature",
  "properties": {
    "iso:country":"FR",
    "sg:address":"Rte de Levet",
    "sg:city":"Dun sur Auron",
    "sg:orig_category":"Non-Classified Establishments",
    "sg:phone":"+33 2 48 59 55 97",
    "sg:postcode":"18130",
    "sg:province":"Centre",
    "wof:name":"R. Melin Mat\u00e9riaux S.a.r.l.",
    "wof:placetype":"venue"
},
  "geometry": {"coordinates":[2.555215,46.884563],"type":"Point"}
}