{
  "type": "Feature",
  "properties": {
    "addr:full":"47 Rue Dupont Des Loges BP 10271 57006 Metz Lorraine",
    "addr:housenumber":"47",
    "addr:postcode":"57006",
    "addr:street":"Rue Dupont Des Loges Bp 10271",
    "iso:country":"FR",
    "sg:address":"47 Rue Dupont Des Loges BP 10271 57006 Metz",
    "sg:classifiers":[
        {
            "category":"Professional",
            "subcategory":"Business Services",
            "type":"Services"
        }
    ],
    "sg:phone":"+33 3 87 75 40 28",
    "sg:province":"Lorraine",
    "sg:tags":[
        "body",
        "advice"
    ],
    "wof:name":"Comite Mosellan De Sauvegarde De L'enfant Et Adultes",
    "wof:placetype":"venue"
},
  "geometry": {"coordinates":[6.173751,49.114262],"type":"Point"}
}