{
  "type": "Feature",
  "properties": {
    "addr:full":"Av Du Dr. J. Torreilles 66011 Perpignan Cedex Midi Pyr\u00e9n\u00e9es",
    "addr:postcode":"66011",
    "addr:street":"Av Du Dr. J.",
    "iso:country":"FR",
    "sg:address":"Av Du Dr. J. Torreilles 66011 Perpignan Cedex",
    "sg:classifiers":[
        {
            "category":"Food & Beverages",
            "subcategory":"Meat & Fish",
            "type":"Retail Goods"
        }
    ],
    "sg:phone":"+33 4 68 54 36 86",
    "sg:province":"Midi Pyr\u00e9n\u00e9es",
    "sg:tags":[
        "preserve",
        "cooked",
        "product",
        "related"
    ],
    "wof:name":"Guasch & Fils",
    "wof:placetype":"venue"
},
  "geometry": {"coordinates":[2.8966,42.700611],"type":"Point"}
}