{
  "type": "Feature",
  "properties": {
    "iso:country":"FR",
    "sg:address":"12, Rue des Alouettes, 95600 Eaubonne",
    "sg:orig_category":"Unclassifiable Establishments",
    "sg:phone":"+33 1 34 16 41 44",
    "sg:province":"Ile de France",
    "wof:name":"Ravel Et Robiteau Industrie S.a.r.l.",
    "wof:placetype":"venue"
},
  "geometry": {"coordinates":[2.280078,48.980171],"type":"Point"}
}