{
  "type": "Feature",
  "properties": {
    "iso:country":"FR",
    "sg:address":"125 Bureaux De La Colline 92210 St Cloud",
    "sg:classifiers":[
        {
            "category":"Health Services",
            "subcategory":"Medical Lab",
            "type":"Services"
        }
    ],
    "sg:phone":"+33 1 41 12 03 70",
    "sg:postcode":"92210",
    "sg:province":"Ile de France",
    "sg:tags":[
        "chemical",
        "pharmaceutical",
        "pharmacy"
    ],
    "wof:name":"Laboratoire Renaudin",
    "wof:placetype":"venue"
},
  "geometry": {"coordinates":[2.22036,48.84441],"type":"Point"}
}