{
  "type": "Feature",
  "properties": {
    "addr:full":"B.P. 221, 61104 Flers C\u00e9dex^^184, Rue Henri V\u00e9niard, 61100 Saint Georges des Groseillers Flers Basse Normandie 61100",
    "addr:housenumber":"b.p. 221",
    "addr:postcode":"61104;61100;61100",
    "addr:street":"Rue Henri Ve\u0301Niard;Georges Des Groseillers;Basse",
    "iso:country":"FR",
    "sg:address":"B.P. 221, 61104 Flers C\u00e9dex^^184, Rue Henri V\u00e9niard, 61100 Saint Georges des Groseillers",
    "sg:city":"Flers",
    "sg:orig_category":"Non-Classified Establishments",
    "sg:phone":"+33 2 33 65 22 78",
    "sg:postcode":"61100",
    "sg:province":"Basse Normandie",
    "wof:name":"Vicq Emballages S.a.r.l.",
    "wof:placetype":"venue"
},
  "geometry": {"coordinates":[-0.566716,48.753838],"type":"Point"}
}