{
  "type": "Feature",
  "properties": {
    "iso:country":"FR",
    "sg:address":"6 Rue Jules Michelet",
    "sg:city":"Oyonnax",
    "sg:classifiers":[
        {
            "category":"Banks & Credit Unions",
            "subcategory":"Financial Services",
            "type":"Services"
        }
    ],
    "sg:phone":"+33 4 74 73 22 90",
    "sg:postcode":"01100",
    "sg:province":"Rhone-Alpes",
    "sg:tags":[
        "banking",
        "finance",
        "insurance"
    ],
    "wof:name":"Caisse Regionale Credit Agricole Mutuel Centre Est (crcamce) Bureau 0410",
    "wof:placetype":"venue"
},
  "geometry": {"coordinates":[5.65585,46.259369],"type":"Point"}
}