{
  "type": "Feature",
  "properties": {
    "addr:full":"B.P. 10, 76530 Grand Couronne^^Bd Rouvray, 76530 Grand Couronne Haute Normandie",
    "addr:housenumber":"76530;76530",
    "addr:street":"B.P. 10;Grand Couronne^^Bd Rouvray;Grand Couronne Haute Normandie",
    "iso:country":"FR",
    "sg:address":"B.P. 10, 76530 Grand Couronne^^Bd Rouvray, 76530 Grand Couronne",
    "sg:orig_category":"Non-Classified Establishments",
    "sg:phone":"+33 2 35 18 38 60",
    "sg:province":"Haute Normandie",
    "wof:name":"S.d.e.l. Val De Seine S.a.",
    "wof:placetype":"venue"
},
  "geometry": {"coordinates":[1.00869,49.357891],"type":"Point"}
}