{
  "type": "Feature",
  "properties": {
    "iso:country":"FR",
    "sg:address":"8 Quai Maximin Licciardi 34200 S\u00e9te",
    "sg:classifiers":[
        {
            "category":"Farming",
            "subcategory":"Livestock Farm",
            "type":"Manufacturing & Wholesale Goods"
        }
    ],
    "sg:phone":"+33 4 67 51 88 51",
    "sg:postcode":"34200",
    "sg:province":"Languedoc-Roussillon",
    "sg:tags":[
        "breeding",
        "agriculture",
        "animal"
    ],
    "wof:name":"Cotes De France Sarl",
    "wof:placetype":"venue"
},
  "geometry": {"coordinates":[-75.927422,40.3978],"type":"Point"}
}