{
  "type": "Feature",
  "properties": {
    "addr:full":"60, Cours Lafayette, 69003 Lyon Rhone-Alpes 69003",
    "addr:housenumber":"60",
    "addr:postcode":"69003;69003",
    "addr:street":"Cours Lafayette",
    "iso:country":"FR",
    "sg:address":"60, Cours Lafayette, 69003 Lyon",
    "sg:orig_category":"Unclassifiable Establishments",
    "sg:phone":"+33 4 78 37 51 47",
    "sg:postcode":"69003",
    "sg:province":"Rhone-Alpes",
    "wof:name":"N.g.l. S.a.r.l. - Nettoyage G\u00e9n\u00e9ral Lyonnais",
    "wof:placetype":"venue"
},
  "geometry": {"coordinates":[4.84829,45.76363],"type":"Point"}
}