{
  "type": "Feature",
  "properties": {
    "iso:country":"FR",
    "sg:address":"122 ave Jean Jaur\u00e8s; Paris; 92140",
    "sg:classifiers":[
        {
            "category":"Banks & Credit Unions",
            "subcategory":"Bank",
            "type":"Services"
        }
    ],
    "sg:phone":"+33 1 46 42 11 81",
    "sg:postcode":"92140",
    "sg:province":"Ile de France",
    "wof:name":"Caisse D'epargne, Ile De France Paris",
    "wof:placetype":"venue"
},
  "geometry": {"coordinates":[2.262025,48.80027],"type":"Point"}
}