{
  "type": "Feature",
  "properties": {
    "iso:country":"FR",
    "sg:address":"Le Champ Fleuri 44840 Les Sorini\u00e8res",
    "sg:classifiers":[
        {
            "category":"Professional",
            "type":"Services"
        }
    ],
    "sg:phone":"+33 2 40 84 53 33",
    "sg:province":"Pays de Loire",
    "sg:tags":[
        "transport",
        "road"
    ],
    "wof:name":"Societe Rezeenne De Transport",
    "wof:placetype":"venue"
},
  "geometry": {"coordinates":[-1.522829,47.141735],"type":"Point"}
}