{
  "type": "Feature",
  "properties": {
    "iso:country":"FR",
    "sg:address":"Rue De Charlieu 42300 Roanne",
    "sg:classifiers":[
        {
            "category":"Shopping",
            "subcategory":"Hobbies, Toys, & Games",
            "type":"Retail Goods"
        }
    ],
    "sg:phone":"+33 4 77 44 79 00",
    "sg:postcode":"42300",
    "sg:province":"Rhone-Alpes",
    "sg:tags":[
        "product",
        "miscellaneous",
        "entertainment"
    ],
    "wof:name":"Giat Industries",
    "wof:placetype":"venue"
},
  "geometry": {"coordinates":[4.087821,46.059666],"type":"Point"}
}