{
  "type": "Feature",
  "properties": {
    "addr:full":"7 Rue Niepce 60200 Compi\u00e8gne Picardie 60200",
    "addr:housenumber":"7",
    "addr:postcode":"60200;60200",
    "addr:street":"Rue Niepce",
    "iso:country":"FR",
    "sg:address":"7 Rue Niepce 60200 Compi\u00e8gne",
    "sg:classifiers":[
        {
            "category":"Shopping",
            "subcategory":"Computers & Home Electronics",
            "type":"Retail Goods"
        }
    ],
    "sg:phone":"+33 3 44 30 60 00",
    "sg:postcode":"60200",
    "sg:province":"Picardie",
    "sg:tags":[
        "electronic",
        "electrical",
        "equipment"
    ],
    "wof:name":"Sanelec",
    "wof:placetype":"venue"
},
  "geometry": {"coordinates":[2.793413,49.391636],"type":"Point"}
}