{
  "type": "Feature",
  "properties": {
    "iso:country":"FR",
    "sg:address":"B.P. 1436",
    "sg:city":"Aubagne C\u00e9dex",
    "sg:orig_category":"Non-Classified Establishments",
    "sg:phone":"+33 4 42 18 01 70",
    "sg:postcode":"13785",
    "sg:province":"Provence-Alpes-C\u00f4te d'Azur",
    "wof:name":"Exposium S.a.",
    "wof:placetype":"venue"
},
  "geometry": {"coordinates":[5.57028,43.293251],"type":"Point"}
}