{
  "type": "Feature",
  "properties": {
    "iso:country":"FR",
    "sg:address":"Zi De Fontanille 82710 Bressols",
    "sg:classifiers":[
        {
            "category":"Professional",
            "type":"Services"
        }
    ],
    "sg:phone":"+33 5 63 02 11 40",
    "sg:province":"Midi Pyr\u00e9n\u00e9es",
    "sg:tags":[
        "transport",
        "road"
    ],
    "wof:name":"Bergo-fruits Sarl",
    "wof:placetype":"venue"
},
  "geometry": {"coordinates":[1.339165,43.968559],"type":"Point"}
}