{
  "type": "Feature",
  "properties": {
    "addr:full":"Route Borgneres 85300 Soullans Pays de Loire",
    "addr:postcode":"85300",
    "addr:street":"Route Borgneres",
    "iso:country":"FR",
    "sg:address":"Route Borgneres 85300 Soullans",
    "sg:classifiers":[
        {
            "category":"Manufacturing",
            "subcategory":"Paper Products",
            "type":"Manufacturing & Wholesale Goods"
        }
    ],
    "sg:phone":"+33 2 51 49 17 27",
    "sg:province":"Pays de Loire",
    "sg:tags":[
        "finished",
        "cardboard",
        "-"
    ],
    "wof:name":"Etik Ouest Sarl",
    "wof:placetype":"venue"
},
  "geometry": {"coordinates":[-1.874249,46.791962],"type":"Point"}
}