{
  "type": "Feature",
  "properties": {
    "iso:country":"FR",
    "sg:address":"5, Av. Joffre, 57000 Metz",
    "sg:orig_category":"Unclassifiable Establishments",
    "sg:phone":"+33 3 87 65 53 68",
    "sg:province":"Lorraine",
    "wof:name":"B.g.l. Bail S.a.",
    "wof:placetype":"venue"
},
  "geometry": {"coordinates":[6.171593,49.111553],"type":"Point"}
}