{
  "type": "Feature",
  "properties": {
    "addr:full":"12bis blvd Lelasseur; Nantes; 44300 Pays de Loire 44300",
    "addr:housenumber":"12bis",
    "addr:postcode":"44300;44300",
    "addr:street":"Blvd Lelasseur",
    "iso:country":"FR",
    "sg:address":"12bis blvd Lelasseur; Nantes; 44300",
    "sg:classifiers":[
        {
            "category":"Banks & Credit Unions",
            "subcategory":"Bank",
            "type":"Services"
        }
    ],
    "sg:phone":"+33 3340400934",
    "sg:postcode":"44300",
    "sg:province":"Pays de Loire",
    "wof:name":"Caisse Regionale, De Cr\u00e9dit Agricole",
    "wof:placetype":"venue"
},
  "geometry": {"coordinates":[-1.5359,47.25631],"type":"Point"}
}