{
  "type": "Feature",
  "properties": {
    "addr:full":"19, Rue des Fr\u00e8res Lumi\u00e8re - ZI Nord, 68000 Colmar Colmar Alsace 68000",
    "addr:housenumber":"19",
    "addr:postcode":"68000;68000",
    "addr:street":"Rue Des Fre\u0300Res Lumie\u0300Re Zi Nord",
    "iso:country":"FR",
    "sg:address":"19, Rue des Fr\u00e8res Lumi\u00e8re - ZI Nord, 68000 Colmar",
    "sg:city":"Colmar",
    "sg:orig_category":"Unclassifiable Establishments",
    "sg:phone":"+33 3 89 23 45 51",
    "sg:postcode":"68000",
    "sg:province":"Alsace",
    "wof:name":"S.a.m.g. S.a. - Soci\u00e9t\u00e9 Alsacienne De M\u00e9canique G\u00e9n\u00e9rale",
    "wof:placetype":"venue"
},
  "geometry": {"coordinates":[7.363583,48.081985],"type":"Point"}
}