{
  "type": "Feature",
  "properties": {
    "addr:full":"7, Rte de la For\u00eat, 25660 Fontain Franche Comt\u00e9",
    "addr:housenumber":"7",
    "addr:postcode":"25660",
    "addr:street":"Rte De La Fore\u0302T;Franche Comte\u0301",
    "iso:country":"FR",
    "sg:address":"7, Rte de la For\u00eat, 25660 Fontain",
    "sg:orig_category":"Unclassifiable Establishments",
    "sg:phone":"+33 3 81 57 27 73",
    "sg:province":"Franche Comt\u00e9",
    "wof:name":"B\u00e2ti Confort S.a.r.l.",
    "wof:placetype":"venue"
},
  "geometry": {"coordinates":[6.024115,47.199928],"type":"Point"}
}