{
  "type": "Feature",
  "properties": {
    "addr:full":"Grange Figat Pomeys Rhone-Alpes 69590",
    "addr:postcode":"69590",
    "addr:street":"Rhone-Alpes",
    "iso:country":"FR",
    "sg:address":"Grange Figat",
    "sg:city":"Pomeys",
    "sg:orig_category":"Unclassifiable Establishments",
    "sg:phone":"+33 4 78 44 45 97",
    "sg:postcode":"69590",
    "sg:province":"Rhone-Alpes",
    "wof:name":"Delorme S.a.r.l.",
    "wof:placetype":"venue"
},
  "geometry": {"coordinates":[4.47565,45.639935],"type":"Point"}
}