{
  "type": "Feature",
  "properties": {
    "addr:full":"Rue Nicolas Appert - ZI Nord Limoges Limousin 87260",
    "addr:postcode":"87260",
    "addr:street":"Rue Nicolas Appert Zi Nord",
    "iso:country":"FR",
    "sg:address":"Rue Nicolas Appert - ZI Nord",
    "sg:city":"Limoges",
    "sg:orig_category":"Unclassifiable Establishments",
    "sg:phone":"+33 5 55 38 81 55",
    "sg:postcode":"87260",
    "sg:province":"Limousin",
    "wof:name":"Kr\u00e9on Industrie S.a.",
    "wof:placetype":"venue"
},
  "geometry": {"coordinates":[1.382435,45.646881],"type":"Point"}
}