{
  "type": "Feature",
  "properties": {
    "addr:full":"Quartier Escarelle 83170 La Celle Centre",
    "addr:housenumber":"83170",
    "iso:country":"FR",
    "sg:address":"Quartier Escarelle 83170 La Celle",
    "sg:classifiers":[
        {
            "category":"Food Court",
            "type":"Food & Drink"
        }
    ],
    "sg:phone":"+33 4 94 69 09 98",
    "sg:province":"Centre",
    "sg:tags":[
        "product",
        "related"
    ],
    "wof:name":"Escarelle Sa",
    "wof:placetype":"venue"
},
  "geometry": {"coordinates":[5.980929,43.391132],"type":"Point"}
}