{
  "type": "Feature",
  "properties": {
    "addr:full":"23, Av Foch, 54270 Essey l\u00e8s Nancy Lorraine",
    "addr:postcode":"54270",
    "addr:street":"23 Av Foch",
    "iso:country":"FR",
    "sg:address":"23, Av Foch, 54270 Essey l\u00e8s Nancy",
    "sg:orig_category":"Non-Classified Establishments",
    "sg:phone":"+33 3 83 21 47 11",
    "sg:province":"Lorraine",
    "wof:name":"Lettreshop",
    "wof:placetype":"venue"
},
  "geometry": {"coordinates":[6.219573,48.704487],"type":"Point"}
}