{
  "type": "Feature",
  "properties": {
    "addr:full":"Rue Pr\u00e9 Favi\u00e8res Pougny Rhone-Alpes 01550",
    "addr:postcode":"01550",
    "addr:street":"Rue Pre\u0301 Favie\u0300Res;Rhone-Alpes",
    "iso:country":"FR",
    "sg:address":"Rue Pr\u00e9 Favi\u00e8res",
    "sg:city":"Pougny",
    "sg:orig_category":"Non-Classified Establishments",
    "sg:phone":"+33 4 50 56 77 55",
    "sg:postcode":"01550",
    "sg:province":"Rhone-Alpes",
    "wof:name":"Entreprise Cart Jean-claude",
    "wof:placetype":"venue"
},
  "geometry": {"coordinates":[5.959331,46.145172],"type":"Point"}
}