{
  "type": "Feature",
  "properties": {
    "iso:country":"FR",
    "sg:address":"pl John Kennedy; Evreux",
    "sg:classifiers":[
        {
            "category":"Banks & Credit Unions",
            "subcategory":"Bank",
            "type":"Services"
        }
    ],
    "sg:phone":"+33 32287480",
    "sg:province":"Haute Normandie",
    "wof:name":"Soci\u00e9t\u00e9 G\u00e9n\u00e9rale",
    "wof:placetype":"venue"
},
  "geometry": {"coordinates":[1.160645,49.009457],"type":"Point"}
}