{
  "type": "Feature",
  "properties": {
    "addr:full":"99, Rue Pierre Curie, 52000 Chaumont Champagne",
    "addr:housenumber":"99",
    "addr:postcode":"52000",
    "addr:street":"Rue Pierre Curie",
    "iso:country":"FR",
    "sg:address":"99, Rue Pierre Curie, 52000 Chaumont",
    "sg:orig_category":"Unclassifiable Establishments",
    "sg:phone":"+33 3 25 32 19 89",
    "sg:province":"Champagne",
    "wof:name":"Renard Jacques",
    "wof:placetype":"venue"
},
  "geometry": {"coordinates":[5.126653,48.112152],"type":"Point"}
}