{
  "type": "Feature",
  "properties": {
    "iso:country":"FR",
    "sg:address":"140, Rte de Bonsecours, 59163 Cond\u00e9 sur l'Escaut",
    "sg:orig_category":"Unclassifiable Establishments",
    "sg:phone":"+33 3 27 40 10 30",
    "sg:province":"Nord Pas-de-Calais",
    "wof:name":"A.i.t. S.a.r.l. - Active International Trade",
    "wof:placetype":"venue"
},
  "geometry": {"coordinates":[3.59666,50.468964],"type":"Point"}
}