{
  "type": "Feature",
  "properties": {
    "iso:country":"FR",
    "sg:address":"19 all\u00e9e Gl\u00fcck 68200 Mulhouse",
    "sg:city":"Mulhouse",
    "sg:classifiers":[
        {
            "category":"Social Services",
            "subcategory":"Child Care",
            "type":"Services"
        }
    ],
    "sg:phone":"+33 3 89 33 15 50",
    "sg:postcode":"68200",
    "sg:province":"Alsace",
    "sg:tags":[
        "consulting",
        "management"
    ],
    "wof:name":"Orea Consultants Eurl",
    "wof:placetype":"venue"
},
  "geometry": {"coordinates":[7.319726,47.75494],"type":"Point"}
}