{
  "type": "Feature",
  "properties": {
    "addr:full":"Rieux le Cornet 76340 Blangy sur Bresle Haute Normandie",
    "addr:postcode":"76340",
    "addr:street":"Rieux;Cornet;Haute Normandie",
    "iso:country":"FR",
    "sg:address":"Rieux le Cornet 76340 Blangy sur Bresle",
    "sg:orig_category":"Unclassifiable Establishments",
    "sg:phone":"+33 2 35 93 39 62",
    "sg:province":"Haute Normandie",
    "wof:name":"Polyver S.a.r.l.",
    "wof:placetype":"venue"
},
  "geometry": {"coordinates":[1.57493,49.922489],"type":"Point"}
}