{
  "type": "Feature",
  "properties": {
    "addr:full":"3, Bd Georges Bidault - Croissy Beaubourg , 77437 Marne la Vall\u00e9e C\u00e9dex 2 Midi Pyr\u00e9n\u00e9es",
    "addr:housenumber":"3;2",
    "addr:postcode":"77437",
    "addr:street":"Bd Georges Bidault;Beaubourg;Ce\u0301Dex",
    "iso:country":"FR",
    "sg:address":"3, Bd Georges Bidault - Croissy Beaubourg , 77437 Marne la Vall\u00e9e C\u00e9dex 2",
    "sg:orig_category":"Non-Classified Establishments",
    "sg:phone":"+33 1 64 62 55 00",
    "sg:province":"Midi Pyr\u00e9n\u00e9es",
    "wof:name":"Merloni Electrom\u00e9nager S.a.",
    "wof:placetype":"venue"
},
  "geometry": {"coordinates":[2.655696,48.830811],"type":"Point"}
}