{
  "type": "Feature",
  "properties": {
    "addr:full":"8 Rue L\u00e9onel Terray 92500 Rueil-Malmaison Cedex Ile de France 92500",
    "addr:housenumber":"8",
    "addr:postcode":"92500;ile;92500",
    "addr:street":"Rue Le\u0301Onel Terray;France",
    "iso:country":"FR",
    "sg:address":"8 Rue L\u00e9onel Terray 92500 Rueil-Malmaison Cedex",
    "sg:classifiers":[
        {
            "category":"Health Services",
            "subcategory":"Medical Lab",
            "type":"Services"
        }
    ],
    "sg:phone":"+33 1 55 70 46 00",
    "sg:postcode":"92500",
    "sg:province":"Ile de France",
    "sg:tags":[
        "chemical",
        "pharmaceutical",
        "pharmacy"
    ],
    "wof:name":"Ciba Specialites Chimiques S.a.",
    "wof:placetype":"venue"
},
  "geometry": {"coordinates":[2.179703,48.861259],"type":"Point"}
}