{
  "type": "Feature",
  "properties": {
    "addr:full":"129 Cours Berriat 38000 Grenoble Rhone-Alpes 38000",
    "addr:housenumber":"129",
    "addr:postcode":"38000;38000",
    "addr:street":"Cours Berriat",
    "iso:country":"FR",
    "sg:address":"129 Cours Berriat 38000 Grenoble",
    "sg:classifiers":[
        {
            "category":"Professional",
            "subcategory":"Business Services",
            "type":"Services"
        }
    ],
    "sg:phone":"+33 4 76 49 73 54",
    "sg:postcode":"38000",
    "sg:province":"Rhone-Alpes",
    "sg:tags":[
        "body",
        "advice"
    ],
    "wof:name":"Assoc Dep Sauvegarde Enfance",
    "wof:placetype":"venue"
},
  "geometry": {"coordinates":[5.708062,45.188622],"type":"Point"}
}