{
  "type": "Feature",
  "properties": {
    "addr:full":"B.P. 22, 49427 Saumur C\u00e9dex^^Rte de Dou\u00e9, 49400 Distr\u00e9 Pays de Loire",
    "addr:postcode":"49427;49400",
    "addr:street":"B.P. 22;Doue\u0301",
    "iso:country":"FR",
    "sg:address":"B.P. 22, 49427 Saumur C\u00e9dex^^Rte de Dou\u00e9, 49400 Distr\u00e9",
    "sg:orig_category":"Non-Classified Establishments",
    "sg:phone":"+33 2 41 50 19 94",
    "sg:province":"Pays de Loire",
    "wof:name":"Savas S.a.",
    "wof:placetype":"venue"
},
  "geometry": {"coordinates":[-0.068679,47.2145],"type":"Point"}
}