{
  "type": "Feature",
  "properties": {
    "iso:country":"FR",
    "sg:address":"ZI Parc Lavoisier - Espace Linquette",
    "sg:city":"Petite For\u00eat",
    "sg:orig_category":"Non-Classified Establishments",
    "sg:phone":"+33 3 27 25 52 33",
    "sg:postcode":"59494",
    "sg:province":"Nord Pas-de-Calais",
    "wof:name":"Pruftechnik S.a.r.l.",
    "wof:placetype":"venue"
},
  "geometry": {"coordinates":[3.472586,50.370441],"type":"Point"}
}