{
  "type": "Feature",
  "properties": {
    "addr:full":"49 Rue Du Tamarin 85270 St Hilaire De Riez Pays de Loire 85270",
    "addr:housenumber":"49",
    "addr:postcode":"85270;85270",
    "addr:street":"Rue Du Tamarin;Riez",
    "iso:country":"FR",
    "sg:address":"49 Rue Du Tamarin 85270 St Hilaire De Riez",
    "sg:classifiers":[
        {
            "category":"Manufacturing",
            "subcategory":"Tools & Machinery",
            "type":"Manufacturing & Wholesale Goods"
        }
    ],
    "sg:phone":"+33 2 51 54 70 25",
    "sg:postcode":"85270",
    "sg:province":"Pays de Loire",
    "sg:tags":[
        "environment",
        "equipment",
        "-"
    ],
    "wof:name":"Thomazeau Caroline",
    "wof:placetype":"venue"
},
  "geometry": {"coordinates":[-1.961059,46.717575],"type":"Point"}
}