{
  "type": "Feature",
  "properties": {
    "iso:country":"FR",
    "sg:address":"14bis, Rue des Pellissiers, 76150 Maromme",
    "sg:orig_category":"Unclassifiable Establishments",
    "sg:phone":"+33 2 32 82 38 70",
    "sg:province":"Haute Normandie",
    "wof:name":"E.r.e.e.l. S.a. - Etudes Et R\u00e9alisations D'equipements Electriques",
    "wof:placetype":"venue"
},
  "geometry": {"coordinates":[-97.32923099999999,32.748508],"type":"Point"}
}