{
  "type": "Feature",
  "properties": {
    "iso:country":"FR",
    "sg:address":"691, Rte d'Albertville, 74320 Sevrier",
    "sg:orig_category":"Non-Classified Establishments",
    "sg:phone":"+33 4 50 52 40 59",
    "sg:postcode":"74320",
    "sg:province":"Rhone-Alpes",
    "wof:name":"H\u00f4tel Beauregard",
    "wof:placetype":"venue"
},
  "geometry": {"coordinates":[6.142122,45.882881],"type":"Point"}
}