{
  "type": "Feature",
  "properties": {
    "addr:full":"3, Av. Louis Armand, 95228 Herblay C\u00e9dex Champagne",
    "addr:postcode":"95228",
    "addr:street":"Av. Louis Armand",
    "iso:country":"FR",
    "sg:address":"3, Av. Louis Armand, 95228 Herblay C\u00e9dex",
    "sg:orig_category":"Non-Classified Establishments",
    "sg:phone":"+33 1 39 97 51 80",
    "sg:province":"Champagne",
    "wof:name":"Soudalinox S.a.r.l.",
    "wof:placetype":"venue"
},
  "geometry": {"coordinates":[2.176516,49.002754],"type":"Point"}
}