{
  "type": "Feature",
  "properties": {
    "addr:full":"Rte de Niafles Craon Pays de Loire 53400",
    "addr:postcode":"53400",
    "addr:street":"Rte De Niafles",
    "iso:country":"FR",
    "sg:address":"Rte de Niafles",
    "sg:city":"Craon",
    "sg:orig_category":"Unclassifiable Establishments",
    "sg:phone":"+33 2 43 09 13 77",
    "sg:postcode":"53400",
    "sg:province":"Pays de Loire",
    "wof:name":"Transports Gaudin S.a.",
    "wof:placetype":"venue"
},
  "geometry": {"coordinates":[-0.962529,47.846416],"type":"Point"}
}