{
  "type": "Feature",
  "properties": {
    "addr:full":"B.P. 6307, 35063 Rennes C\u00e9dex^^36, Rue des Veyettes, 35000 Rennes Rennes Bretagne 35000",
    "addr:postcode":"35063;35000;35000",
    "addr:street":"B.P. 6307;Rue Des Veyettes",
    "iso:country":"FR",
    "sg:address":"B.P. 6307, 35063 Rennes C\u00e9dex^^36, Rue des Veyettes, 35000 Rennes",
    "sg:city":"Rennes",
    "sg:orig_category":"Non-Classified Establishments",
    "sg:phone":"+33 2 23 30 40 30",
    "sg:postcode":"35000",
    "sg:province":"Bretagne",
    "wof:name":"Fabrication Pour L'edition S.a.r.l.",
    "wof:placetype":"venue"
},
  "geometry": {"coordinates":[-1.684477,48.107521],"type":"Point"}
}