{
  "type": "Feature",
  "properties": {
    "iso:country":"FR",
    "sg:address":"16 Rue Hoche 92906 Paris La D\u00e9fense Cedex",
    "sg:classifiers":[
        {
            "category":"Professional",
            "subcategory":"Advertising",
            "type":"Services"
        }
    ],
    "sg:phone":"+33 1 46 53 71 71",
    "sg:province":"Midi Pyr\u00e9n\u00e9es",
    "sg:tags":[
        "marketing",
        "medium",
        "communication"
    ],
    "wof:name":"Hay Management Consultants Sa",
    "wof:placetype":"venue"
},
  "geometry": {"coordinates":[2.24119,48.888939],"type":"Point"}
}