{
  "type": "Feature",
  "properties": {
    "iso:country":"FR",
    "sg:address":"1",
    "sg:city":"Fr\u00e9deric Mistral; Aix en Provence; 13100",
    "sg:classifiers":[
        {
            "category":"Banks & Credit Unions",
            "subcategory":"Bank",
            "type":"Services"
        }
    ],
    "sg:phone":"+33 3342288660",
    "sg:province":"Nord Pas-de-Calais",
    "wof:name":"Banque Finindus, Agence",
    "wof:placetype":"venue"
},
  "geometry": {"coordinates":[5.450879,43.52673],"type":"Point"}
}