{
  "type": "Feature",
  "properties": {
    "addr:full":"1 Fr\u00e9deric Mistral; Aix en Provence; 13100 Nord Pas-de-Calais",
    "addr:housenumber":"1",
    "addr:postcode":"13100",
    "addr:street":"Fre\u0301Deric Mistral;En",
    "iso:country":"FR",
    "sg:address":"1",
    "sg:city":"Fr\u00e9deric Mistral; Aix en Provence; 13100",
    "sg:classifiers":[
        {
            "category":"Banks & Credit Unions",
            "subcategory":"Bank",
            "type":"Services"
        }
    ],
    "sg:phone":"+33 3342288660",
    "sg:province":"Nord Pas-de-Calais",
    "wof:name":"Banque Finindus, Agence",
    "wof:placetype":"venue"
},
  "geometry": {"coordinates":[5.450879,43.52673],"type":"Point"}
}