{
  "type": "Feature",
  "properties": {
    "addr:full":"Z.I les Quatres Routes Jugon les Lacs Bretagne 22270",
    "addr:postcode":"22270",
    "addr:street":"Z.I;Jugon Les Lacs",
    "iso:country":"FR",
    "sg:address":"Z.I les Quatres Routes",
    "sg:city":"Jugon les Lacs",
    "sg:orig_category":"Non-Classified Establishments",
    "sg:phone":"+33 2 96 50 65 50",
    "sg:postcode":"22270",
    "sg:province":"Bretagne",
    "wof:name":"Tournafol S.a.",
    "wof:placetype":"venue"
},
  "geometry": {"coordinates":[-2.249209,48.374851],"type":"Point"}
}