{
  "type": "Feature",
  "properties": {
    "addr:full":"Rte De Nantes 44580 Bourgneuf En Retz Pays de Loire 44580",
    "addr:postcode":"44580;44580",
    "addr:street":"Rte De Nantes;Retz",
    "iso:country":"FR",
    "sg:address":"Rte De Nantes 44580 Bourgneuf En Retz",
    "sg:classifiers":[
        {
            "category":"Wholesale",
            "subcategory":"Machinery & Supplies",
            "type":"Manufacturing & Wholesale Goods"
        }
    ],
    "sg:phone":"+33 2 40 21 42 42",
    "sg:postcode":"44580",
    "sg:province":"Pays de Loire",
    "sg:tags":[
        "handling",
        "material",
        "-",
        "machine",
        "equipment",
        "engineering",
        "mechanical"
    ],
    "wof:name":"Faber System Sa",
    "wof:placetype":"venue"
},
  "geometry": {"coordinates":[-1.948274,47.04454],"type":"Point"}
}