{
  "type": "Feature",
  "properties": {
    "iso:country":"FR",
    "sg:address":"Rue Andr\u00e9 Boule - ZI Nord",
    "sg:city":"Chatellerault",
    "sg:orig_category":"Unclassifiable Establishments",
    "sg:phone":"+33 5 49 02 43 00",
    "sg:postcode":"86100",
    "sg:province":"Poitou-Charentes",
    "wof:name":"Fabris S.a.",
    "wof:placetype":"venue"
},
  "geometry": {"coordinates":[0.614296,46.778336],"type":"Point"}
}