{
  "type": "Feature",
  "properties": {
    "iso:country":"FR",
    "sg:address":"10, Av. du Mail, 35000 Rennes",
    "sg:city":"Rennes",
    "sg:orig_category":"Non-Classified Establishments",
    "sg:phone":"+33 2 99 33 25 40",
    "sg:postcode":"35000",
    "sg:province":"Bretagne",
    "wof:name":"Hertz France",
    "wof:placetype":"venue"
},
  "geometry": {"coordinates":[-1.687234,48.110264],"type":"Point"}
}