{
  "type": "Feature",
  "properties": {
    "iso:country":"FR",
    "sg:address":"12 R Andrei Sakharov 76137 Mont St Aignan",
    "sg:city":"Aignan",
    "sg:classifiers":[
        {
            "category":"Wholesale",
            "subcategory":"Machinery & Supplies",
            "type":"Manufacturing & Wholesale Goods"
        }
    ],
    "sg:phone":"+33 2 35 12 20 30",
    "sg:postcode":"32290",
    "sg:province":"Midi Pyr\u00e9n\u00e9es",
    "sg:tags":[
        "handling",
        "material",
        "-",
        "machine",
        "equipment",
        "engineering",
        "mechanical"
    ],
    "wof:name":"Otis Sa",
    "wof:placetype":"venue"
},
  "geometry": {"coordinates":[0.086285,43.698807],"type":"Point"}
}