{
  "type": "Feature",
  "properties": {
    "iso:country":"FR",
    "sg:address":"986 Rte Megevants 74330 Choisy",
    "sg:classifiers":[
        {
            "category":"Wholesale",
            "subcategory":"Machinery & Supplies",
            "type":"Manufacturing & Wholesale Goods"
        }
    ],
    "sg:phone":"+33 4 50 77 47 76",
    "sg:postcode":"74330",
    "sg:province":"Rhone-Alpes",
    "sg:tags":[
        "equipment",
        "-",
        "precision",
        "glass",
        "optical",
        "health",
        "instrument"
    ],
    "wof:name":"Jhb Etablissements Julien Buffard Sarl",
    "wof:placetype":"venue"
},
  "geometry": {"coordinates":[6.047837,46.006046],"type":"Point"}
}