{
  "type": "Feature",
  "properties": {
    "iso:country":"FR",
    "sg:address":"B.P. 3, 42420 Lorette C\u00e9dex^^Rue Pierre Timbaud, 42420 Lorette",
    "sg:orig_category":"Non-Classified Establishments",
    "sg:phone":"+33 4 77 73 20 56",
    "sg:postcode":"42420",
    "sg:province":"Rhone-Alpes",
    "wof:name":"Di Bartolom\u00e9o S.a.",
    "wof:placetype":"venue"
},
  "geometry": {"coordinates":[4.58077,45.512573],"type":"Point"}
}