{
  "type": "Feature",
  "properties": {
    "addr:full":"R Henri Becquerel Zac De Ther 60000 Beauvais Picardie 60000",
    "addr:postcode":"60000;60000",
    "addr:street":"R Henri Becquerel Zac De Ther",
    "iso:country":"FR",
    "sg:address":"R Henri Becquerel Zac De Ther 60000 Beauvais",
    "sg:classifiers":[
        {
            "category":"Autos & Motor Vehicles",
            "subcategory":"Automobile Sales",
            "type":"Retail Goods"
        }
    ],
    "sg:phone":"+33 3 44 02 84 00",
    "sg:postcode":"60000",
    "sg:province":"Picardie",
    "sg:tags":[
        "equipment",
        "motor-cars",
        "transport"
    ],
    "wof:name":"Garage De La Piscine Sa",
    "wof:placetype":"venue"
},
  "geometry": {"coordinates":[2.116344,49.411545],"type":"Point"}
}