{
  "type": "Feature",
  "properties": {
    "addr:full":"pl Eglise; Lacanau Lacanau Aquitaine 33680",
    "addr:housenumber":"lacanau",
    "addr:postcode":"33680",
    "addr:street":"Pl",
    "iso:country":"FR",
    "sg:address":"pl Eglise; Lacanau",
    "sg:city":"Lacanau",
    "sg:classifiers":[
        {
            "category":"Banks & Credit Unions",
            "subcategory":"Bank",
            "type":"Services"
        }
    ],
    "sg:phone":"+33 3356035576",
    "sg:postcode":"33680",
    "sg:province":"Aquitaine",
    "wof:name":"Soci\u00e9t\u00e9 G\u00e9n\u00e9rale",
    "wof:placetype":"venue"
},
  "geometry": {"coordinates":[-1.077938,44.978214],"type":"Point"}
}