{
  "type": "Feature",
  "properties": {
    "addr:full":"23 Rue Br\u00e9zin Paris Ile de France 75014",
    "addr:housenumber":"23",
    "addr:postcode":"75014",
    "addr:street":"Rue Bre\u0301Zin",
    "iso:country":"FR",
    "sg:address":"23 Rue Br\u00e9zin",
    "sg:city":"Paris",
    "sg:classifiers":[
        {
            "category":"Banks & Credit Unions",
            "subcategory":"Financial Services",
            "type":"Services"
        }
    ],
    "sg:phone":"+33 1 45 40 65 38",
    "sg:postcode":"75014",
    "sg:province":"Ile de France",
    "sg:tags":[
        "banking",
        "finance",
        "insurance"
    ],
    "wof:name":"Mairie Jose Asselin Et Francois Samain Sct",
    "wof:placetype":"venue"
},
  "geometry": {"coordinates":[2.326682,48.831436],"type":"Point"}
}