{
  "type": "Feature",
  "properties": {
    "addr:full":"820, Av. Amp\u00e8re - ZI les Milles, 13760 Aix en Provence Provence-Alpes-C\u00f4te d'Azur",
    "addr:housenumber":"820",
    "addr:postcode":"13760",
    "addr:street":"Av. Ampe\u0300Re Zi Les Milles;En Provence",
    "iso:country":"FR",
    "sg:address":"820, Av. Amp\u00e8re - ZI les Milles, 13760 Aix en Provence",
    "sg:orig_category":"Unclassifiable Establishments",
    "sg:phone":"+33 4 42 39 60 30",
    "sg:province":"Provence-Alpes-C\u00f4te d'Azur",
    "wof:name":"Codip S.a.",
    "wof:placetype":"venue"
},
  "geometry": {"coordinates":[5.298045,43.621151],"type":"Point"}
}