{
  "type": "Feature",
  "properties": {
    "iso:country":"FR",
    "sg:address":"ZA de Cromel",
    "sg:city":"Saint Quentin sur le Homme",
    "sg:orig_category":"Unclassifiable Establishments",
    "sg:phone":"+33 2 33 89 61 62",
    "sg:postcode":"50220",
    "sg:province":"Basse Normandie",
    "wof:name":"Avranches Automatic S.a.s.",
    "wof:placetype":"venue"
},
  "geometry": {"coordinates":[-1.317229,48.646919],"type":"Point"}
}