{
  "type": "Feature",
  "properties": {
    "addr:full":"21, Rue Edouard Belin, 92566 Rueil Malmaison C\u00e9dex Picardie",
    "addr:housenumber":"21",
    "addr:postcode":"92566",
    "addr:street":"Rue Edouard Belin",
    "iso:country":"FR",
    "sg:address":"21, Rue Edouard Belin, 92566 Rueil Malmaison C\u00e9dex",
    "sg:orig_category":"Non-Classified Establishments",
    "sg:phone":"+33 1 41 96 80 80",
    "sg:province":"Picardie",
    "wof:name":"Fair Isaac International",
    "wof:placetype":"venue"
},
  "geometry": {"coordinates":[2.168257,48.888279],"type":"Point"}
}