{
  "type": "Feature",
  "properties": {
    "addr:full":"ZA La Grande Terre Aubord Languedoc-Roussillon 30620",
    "addr:postcode":"30620",
    "addr:street":"Za La Grande Terre",
    "iso:country":"FR",
    "sg:address":"ZA La Grande Terre",
    "sg:city":"Aubord",
    "sg:orig_category":"Non-Classified Establishments",
    "sg:phone":"+33 4 66 71 31 31",
    "sg:postcode":"30620",
    "sg:province":"Languedoc-Roussillon",
    "wof:name":"Soci\u00e9t\u00e9 Fages Et Aiglon S.a.",
    "wof:placetype":"venue"
},
  "geometry": {"coordinates":[4.312505,43.757687],"type":"Point"}
}