{
  "type": "Feature",
  "properties": {
    "iso:country":"FR",
    "sg:address":"1931 Route Quarante Sous 78630 Orgeval",
    "sg:classifiers":[
        {
            "category":"Wholesale",
            "subcategory":"Farm Supplies",
            "type":"Manufacturing & Wholesale Goods"
        }
    ],
    "sg:phone":"+33 1 39 75 86 00",
    "sg:postcode":"78630",
    "sg:province":"Ile de France",
    "sg:tags":[
        "-",
        "machine",
        "equipment",
        "engineering",
        "machinery",
        "mechanical",
        "agriculture"
    ],
    "wof:name":"Ets Chartier Sa",
    "wof:placetype":"venue"
},
  "geometry": {"coordinates":[1.974838,48.930267],"type":"Point"}
}