{
  "type": "Feature",
  "properties": {
    "iso:country":"FR",
    "sg:address":"5 boulevard Montmartre; Paris; 75002",
    "sg:classifiers":[
        {
            "category":"Industrial Area",
            "type":"Public Place"
        }
    ],
    "sg:phone":"+33 1 53 00 01 00",
    "sg:province":"Ile de France",
    "sg:tags":[
        "large",
        "private"
    ],
    "wof:name":"Fininfo Sa",
    "wof:placetype":"venue"
},
  "geometry": {"coordinates":[2.342532,48.871437],"type":"Point"}
}