{
  "type": "Feature",
  "properties": {
    "addr:full":"3, Rue de Bic\u00eatre, 94240 L'Hay des Roses Ile de France",
    "addr:housenumber":"3",
    "addr:postcode":"94240",
    "addr:street":"Rue De Bice\u0302Tre;Des Roses Ile De France",
    "iso:country":"FR",
    "sg:address":"3, Rue de Bic\u00eatre, 94240 L'Hay des Roses",
    "sg:orig_category":"Unclassifiable Establishments",
    "sg:phone":"+33 1 41 80 67 10",
    "sg:province":"Ile de France",
    "wof:name":"J.p.c. Expositions S.a.",
    "wof:placetype":"venue"
},
  "geometry": {"coordinates":[-79.14250199999999,41.455242],"type":"Point"}
}