{
  "type": "Feature",
  "properties": {
    "addr:full":"82, Rue Cl\u00e9menceau, 57360 Amn\u00e9ville les Thermes Lorraine",
    "addr:housenumber":"82",
    "addr:postcode":"57360",
    "addr:street":"Rue Cle\u0301Menceau",
    "iso:country":"FR",
    "sg:address":"82, Rue Cl\u00e9menceau, 57360 Amn\u00e9ville les Thermes",
    "sg:orig_category":"Non-Classified Establishments",
    "sg:phone":"+33 3 87 71 76 49",
    "sg:province":"Lorraine",
    "wof:name":"Lesserteur S.a.r.l.",
    "wof:placetype":"venue"
},
  "geometry": {"coordinates":[6.135446,49.258133],"type":"Point"}
}