{
  "type": "Feature",
  "properties": {
    "addr:full":"26, Grand Rue, 67430 Diemeringen Diemeringen Alsace 67430",
    "addr:housenumber":"26",
    "addr:postcode":"67430;67430",
    "addr:street":"Grand Rue",
    "iso:country":"FR",
    "sg:address":"26, Grand Rue, 67430 Diemeringen",
    "sg:city":"Diemeringen",
    "sg:orig_category":"Non-Classified Establishments",
    "sg:phone":"+33 3 88 00 42 20",
    "sg:postcode":"67430",
    "sg:province":"Alsace",
    "wof:name":"Etablissements Ernest Schmidt Et Compagnie S.a.",
    "wof:placetype":"venue"
},
  "geometry": {"coordinates":[7.185944,48.947227],"type":"Point"}
}