{
  "type": "Feature",
  "properties": {
    "addr:full":"115, Place du March\u00e9, 76230 Isneauville Haute Normandie",
    "addr:housenumber":"115",
    "addr:postcode":"76230",
    "addr:street":"Place Du Marche\u0301;Haute Normandie",
    "iso:country":"FR",
    "sg:address":"115, Place du March\u00e9, 76230 Isneauville",
    "sg:orig_category":"Unclassifiable Establishments",
    "sg:phone":"+33 2 35 60 12 74",
    "sg:province":"Haute Normandie",
    "wof:name":"E.n.a.f. S.a.r.l. - Entreprise Normande D'application Frigorifique",
    "wof:placetype":"venue"
},
  "geometry": {"coordinates":[1.11769,49.469929],"type":"Point"}
}