{
  "type": "Feature",
  "properties": {
    "addr:full":"8, Rue Eug\u00e8ne et Armand Peugeot, 92567 Rueil Malmaison C\u00e9dex Haute Normandie",
    "addr:housenumber":"8",
    "addr:postcode":"92567",
    "addr:street":"Rue Euge\u0300Ne Et Armand Peugeot;Haute Normandie",
    "iso:country":"FR",
    "sg:address":"8, Rue Eug\u00e8ne et Armand Peugeot, 92567 Rueil Malmaison C\u00e9dex",
    "sg:orig_category":"Non-Classified Establishments",
    "sg:phone":"+33 1 47 14 65 00",
    "sg:province":"Haute Normandie",
    "wof:name":"U.d.p. S.a. - Urbaine Des P\u00e9troles",
    "wof:placetype":"venue"
},
  "geometry": {"coordinates":[2.173221,48.8899],"type":"Point"}
}