{
  "type": "Feature",
  "properties": {
    "addr:full":"rue de la Pierre Blanche 49120 Chemille Pays de Loire 49120",
    "addr:postcode":"49120;49120",
    "addr:street":"Rue De La Pierre Blanche;Chemille",
    "iso:country":"FR",
    "sg:address":"rue de la Pierre Blanche 49120 Chemille",
    "sg:classifiers":[
        {
            "category":"Manufacturing",
            "subcategory":"Building Materials",
            "type":"Manufacturing & Wholesale Goods"
        }
    ],
    "sg:phone":"+33 2 41 71 55 55",
    "sg:postcode":"49120",
    "sg:province":"Pays de Loire",
    "sg:tags":[
        "fleece",
        "fabric"
    ],
    "wof:name":"Tharreau Sa",
    "wof:placetype":"venue"
},
  "geometry": {"coordinates":[-0.716889,47.216354],"type":"Point"}
}