{
  "type": "Feature",
  "properties": {
    "iso:country":"FR",
    "sg:address":"10 Rue De Belfort 25600 Vieux Charmont",
    "sg:classifiers":[
        {
            "category":"Manufacturing",
            "subcategory":"Motor Vehicles & Parts",
            "type":"Manufacturing & Wholesale Goods"
        }
    ],
    "sg:phone":"+33 3 81 31 24 30",
    "sg:postcode":"25600",
    "sg:province":"Franche Comt\u00e9",
    "sg:tags":[
        "engine",
        "machine",
        "engineering",
        "-",
        "mechanical"
    ],
    "wof:name":"Burgress Norton Europe",
    "wof:placetype":"venue"
},
  "geometry": {"coordinates":[6.837478,47.521046],"type":"Point"}
}