{
  "type": "Feature",
  "properties": {
    "addr:full":"26, Rue de Reims, 51500 Rilly la Montagne Champagne",
    "addr:housenumber":"26",
    "addr:postcode":"51500",
    "addr:street":"Rue De Reims",
    "iso:country":"FR",
    "sg:address":"26, Rue de Reims, 51500 Rilly la Montagne",
    "sg:orig_category":"Unclassifiable Establishments",
    "sg:phone":"+33 3 26 03 40 27",
    "sg:province":"Champagne",
    "wof:name":"Champagne Veuve Maurice Lepitre E.a.r.l.",
    "wof:placetype":"venue"
},
  "geometry": {"coordinates":[4.046911,49.165798],"type":"Point"}
}