{
  "type": "Feature",
  "properties": {
    "addr:full":"ZI Les Plantes Jacques 89210 Brienon Sur Arman\u00e7on Bellechaume Bourgogne 89210",
    "addr:postcode":"89210;89210",
    "addr:street":"Zi Les Plantes Jacques",
    "iso:country":"FR",
    "sg:address":"ZI Les Plantes Jacques 89210 Brienon Sur Arman\u00e7on",
    "sg:city":"Bellechaume",
    "sg:classifiers":[
        {
            "category":"Building & Trades",
            "subcategory":"Electrical",
            "type":"Services"
        }
    ],
    "sg:phone":"+33 3 86 56 09 09",
    "sg:postcode":"89210",
    "sg:province":"Bourgogne",
    "sg:tags":[
        "tool",
        "high-quality"
    ],
    "wof:name":"Milbox Sa",
    "wof:placetype":"venue"
},
  "geometry": {"coordinates":[3.617082,47.992756],"type":"Point"}
}