{
  "type": "Feature",
  "properties": {
    "addr:full":"Hameau chez Jacquier 74890 Lully Rhone-Alpes 74890",
    "addr:postcode":"74890;74890",
    "addr:street":"Hameau Chez Jacquier",
    "iso:country":"FR",
    "sg:address":"Hameau chez Jacquier 74890 Lully",
    "sg:orig_category":"Non-Classified Establishments",
    "sg:phone":"+33 4 50 36 38 44",
    "sg:postcode":"74890",
    "sg:province":"Rhone-Alpes",
    "wof:name":"Royal Viandes S.a.r.l.",
    "wof:placetype":"venue"
},
  "geometry": {"coordinates":[6.408535,46.291931],"type":"Point"}
}