{
  "type": "Feature",
  "properties": {
    "addr:full":"Av. Poincar\u00e9 Anould Lorraine 88650",
    "addr:postcode":"88650",
    "addr:street":"Av. Poincare\u0301",
    "iso:country":"FR",
    "sg:address":"Av. Poincar\u00e9",
    "sg:city":"Anould",
    "sg:orig_category":"Unclassifiable Establishments",
    "sg:phone":"+33 3 29 57 00 50",
    "sg:postcode":"88650",
    "sg:province":"Lorraine",
    "wof:name":"Le Roy Logistique S.a.",
    "wof:placetype":"venue"
},
  "geometry": {"coordinates":[6.944818,48.206818],"type":"Point"}
}