{
  "type": "Feature",
  "properties": {
    "iso:country":"FR",
    "sg:address":"10 Avenue D'Aquitaine 24000 P\u00e9rigueux",
    "sg:city":"P\u00e9rigueux",
    "sg:classifiers":[
        {
            "category":"Professional",
            "subcategory":"Printing & Photocopies",
            "type":"Services"
        }
    ],
    "sg:phone":"+33 5 53 08 37 11",
    "sg:postcode":"24000",
    "sg:province":"Aquitaine",
    "sg:tags":[
        "publishing"
    ],
    "wof:name":"Ste Des Gratuits De Guyenne Et Gascogne S3g",
    "wof:placetype":"venue"
},
  "geometry": {"coordinates":[0.70664,45.194248],"type":"Point"}
}