{
  "type": "Feature",
  "properties": {
    "addr:full":"68 rue Jean Jaur\u00e8s 92800 Puteaux Ile de France 92800",
    "addr:housenumber":"68",
    "addr:postcode":"92800;92800",
    "addr:street":"Rue Jean Jaure\u0300S",
    "iso:country":"FR",
    "sg:address":"68 rue Jean Jaur\u00e8s 92800 Puteaux",
    "sg:classifiers":[
        {
            "category":"Shopping",
            "subcategory":"Books",
            "type":"Retail Goods"
        }
    ],
    "sg:phone":"+33 1 47 73 01 23",
    "sg:postcode":"92800",
    "sg:province":"Ile de France",
    "wof:name":"Erec S.a.r.l.",
    "wof:placetype":"venue"
},
  "geometry": {"coordinates":[2.243822,48.883781],"type":"Point"}
}