{
  "type": "Feature",
  "properties": {
    "addr:full":"118, Chemin du Pas de la Paille, 66000 Perpignan Languedoc-Roussillon",
    "addr:housenumber":"118",
    "addr:postcode":"66000",
    "addr:street":"Chemin Du Pas De La Paille",
    "iso:country":"FR",
    "sg:address":"118, Chemin du Pas de la Paille, 66000 Perpignan",
    "sg:orig_category":"Unclassifiable Establishments",
    "sg:phone":"+33 4 68 85 04 81",
    "sg:province":"Languedoc-Roussillon",
    "wof:name":"Sotranasa T\u00e9l\u00e9vid\u00e9ocom S.a.r.l.",
    "wof:placetype":"venue"
},
  "geometry": {"coordinates":[2.865576,42.686436],"type":"Point"}
}