{
  "type": "Feature",
  "properties": {
    "iso:country":"FR",
    "sg:address":"118, Chemin du Pas de la Paille, 66000 Perpignan",
    "sg:orig_category":"Unclassifiable Establishments",
    "sg:phone":"+33 4 68 85 04 81",
    "sg:province":"Languedoc-Roussillon",
    "wof:name":"Sotranasa T\u00e9l\u00e9vid\u00e9ocom S.a.r.l.",
    "wof:placetype":"venue"
},
  "geometry": {"coordinates":[2.865576,42.686436],"type":"Point"}
}