{
  "type": "Feature",
  "properties": {
    "iso:country":"FR",
    "sg:address":"rue d'Arb\u00e8re 01220 Divonne les Bains",
    "sg:classifiers":[
        {
            "category":"Food & Beverages",
            "subcategory":"Fruits & Vegetables",
            "type":"Retail Goods"
        }
    ],
    "sg:phone":"+33 4 50 20 01 04",
    "sg:postcode":"01220",
    "sg:province":"Rhone-Alpes",
    "wof:name":"Alimentation Generale Divonnaise Sa",
    "wof:placetype":"venue"
},
  "geometry": {"coordinates":[6.130655,46.346458],"type":"Point"}
}