{
  "type": "Feature",
  "properties": {
    "addr:full":"6, Av. du Docteur Schweitzer, 69330 Meyzieu Rhone-Alpes 69330",
    "addr:postcode":"69330;69330",
    "addr:street":"Av. Du Docteur Schweitzer",
    "iso:country":"FR",
    "sg:address":"6, Av. du Docteur Schweitzer, 69330 Meyzieu",
    "sg:orig_category":"Non-Classified Establishments",
    "sg:phone":"+33 4 78 04 37 78",
    "sg:postcode":"69330",
    "sg:province":"Rhone-Alpes",
    "wof:name":"G.s.p. Son\u00e9mi S.a.r.l.",
    "wof:placetype":"venue"
},
  "geometry": {"coordinates":[5.027511,45.763699],"type":"Point"}
}