{
  "type": "Feature",
  "properties": {
    "addr:full":"12, Rue Jules Guesde, 26800 Portes les Valence Rhone-Alpes 26800",
    "addr:housenumber":"12",
    "addr:postcode":"26800;26800",
    "addr:street":"Rue Jules Guesde",
    "iso:country":"FR",
    "sg:address":"12, Rue Jules Guesde, 26800 Portes les Valence",
    "sg:orig_category":"Non-Classified Establishments",
    "sg:phone":"+33 4 75 57 21 21",
    "sg:postcode":"26800",
    "sg:province":"Rhone-Alpes",
    "wof:name":"Locamion",
    "wof:placetype":"venue"
},
  "geometry": {"coordinates":[4.873756,44.886204],"type":"Point"}
}