{
  "type": "Feature",
  "properties": {
    "addr:full":"Chemin De Barandeguy Quai Aguerressaria 64990 Mouguerre Mouguerre Aquitaine 64990",
    "addr:postcode":"64990;64990",
    "addr:street":"Chemin De Barandeguy Quai Aguerressaria",
    "iso:country":"FR",
    "sg:address":"Chemin De Barandeguy Quai Aguerressaria 64990 Mouguerre",
    "sg:city":"Mouguerre",
    "sg:classifiers":[
        {
            "category":"Farming",
            "subcategory":"Livestock Farm",
            "type":"Manufacturing & Wholesale Goods"
        }
    ],
    "sg:phone":"+33 5 59 31 80 42",
    "sg:postcode":"64990",
    "sg:province":"Aquitaine",
    "sg:tags":[
        "agriculture"
    ],
    "wof:name":"Mendiburu Freres",
    "wof:placetype":"venue"
},
  "geometry": {"coordinates":[-1.452823,43.437317],"type":"Point"}
}