{
  "type": "Feature",
  "properties": {
    "addr:full":"22, Av. Jean Jaur\u00e8s, 82200 Moissac Midi Pyr\u00e9n\u00e9es",
    "addr:postcode":"82200",
    "addr:street":"22 Av. Jean Jaure\u0300S",
    "iso:country":"FR",
    "sg:address":"22, Av. Jean Jaur\u00e8s, 82200 Moissac",
    "sg:orig_category":"Unclassifiable Establishments",
    "sg:phone":"+33 5 63 05 11 11",
    "sg:province":"Midi Pyr\u00e9n\u00e9es",
    "wof:name":"Soci\u00e9t\u00e9 M.e.r.i.s. S.a.r.l. - Soci\u00e9t\u00e9 Maintenance Etudes R\u00e9alisation Industrielle S\u00e9chage",
    "wof:placetype":"venue"
},
  "geometry": {"coordinates":[1.094329,44.105057],"type":"Point"}
}