{
  "type": "Feature",
  "properties": {
    "iso:country":"FR",
    "sg:address":"B.P. 4, 29540 Sp\u00e9zet^^ZA de Kerangwenn, 29540 Sp\u00e9zet",
    "sg:city":"Sp\u00e9zet",
    "sg:orig_category":"Non-Classified Establishments",
    "sg:phone":"+33 2 98 93 89 25",
    "sg:postcode":"29540",
    "sg:province":"Bretagne",
    "wof:name":"Keltia Graphic S.a.r.l.",
    "wof:placetype":"venue"
},
  "geometry": {"coordinates":[-3.712032,48.192722],"type":"Point"}
}