{
  "type": "Feature",
  "properties": {
    "iso:country":"FR",
    "sg:address":"chemin des Artisans 44470 Carquefou",
    "sg:classifiers":[
        {
            "category":"Home & Garden",
            "subcategory":"Home Furnishings",
            "type":"Retail Goods"
        }
    ],
    "sg:phone":"+33 2 51 13 17 13",
    "sg:postcode":"44470",
    "sg:province":"Pays de Loire",
    "sg:tags":[
        "candle"
    ],
    "wof:name":"Devineau Sas",
    "wof:placetype":"venue"
},
  "geometry": {"coordinates":[-1.47981,47.293701],"type":"Point"}
}