{
  "type": "Feature",
  "properties": {
    "iso:country":"FR",
    "sg:address":"17, Av. de la Lib\u00e9ration, 33320 Eysines",
    "sg:city":"Eysines",
    "sg:orig_category":"Non-Classified Establishments",
    "sg:phone":"+33 5 56 28 72 19",
    "sg:postcode":"33320",
    "sg:province":"Aquitaine",
    "wof:name":"Bredelec S.a.r.l.",
    "wof:placetype":"venue"
},
  "geometry": {"coordinates":[-0.648473,44.888378],"type":"Point"}
}