{
  "type": "Feature",
  "properties": {
    "addr:full":"Mln Pont Estrade 63500 Perrier Perrier Auvergne 63500",
    "addr:postcode":"63500;63500",
    "addr:street":"Estrade;Perrier",
    "iso:country":"FR",
    "sg:address":"Mln Pont Estrade 63500 Perrier",
    "sg:city":"Perrier",
    "sg:classifiers":[
        {
            "category":"Building & Trades",
            "subcategory":"Electrical",
            "type":"Services"
        }
    ],
    "sg:phone":"+33 4 73 89 14 92",
    "sg:postcode":"63500",
    "sg:province":"Auvergne",
    "sg:tags":[
        "electronic",
        "lighting",
        "equipment"
    ],
    "wof:name":"Sarl Abat Jour Du Moulin",
    "wof:placetype":"venue"
},
  "geometry": {"coordinates":[3.243349,45.499271],"type":"Point"}
}