{
  "type": "Feature",
  "properties": {
    "iso:country":"FR",
    "sg:address":"Rue Marcel Paul 01500 Amberieu En Bugey",
    "sg:classifiers":[
        {
            "category":"Wholesale",
            "subcategory":"Medical Equipment & Supplies",
            "type":"Manufacturing & Wholesale Goods"
        }
    ],
    "sg:phone":"+33 4 74 34 67 66",
    "sg:postcode":"01500",
    "sg:province":"Rhone-Alpes",
    "sg:tags":[
        "instrument",
        "health",
        "-",
        "precision"
    ],
    "wof:name":"Laboratoire C G P De Protheses Dentaires Sarl",
    "wof:placetype":"venue"
},
  "geometry": {"coordinates":[5.348315,45.964931],"type":"Point"}
}