{
  "type": "Feature",
  "properties": {
    "addr:full":"26 rue Marbeuf 75008 Paris Ile de France 75008",
    "addr:housenumber":"26",
    "addr:postcode":"75008;75008",
    "addr:street":"Rue Marbeuf",
    "iso:country":"FR",
    "sg:address":"26 rue Marbeuf 75008 Paris",
    "sg:classifiers":[
        {
            "category":"Shopping",
            "subcategory":"Clothing, Apparel, & Fashions",
            "type":"Retail Goods"
        }
    ],
    "sg:phone":"+33 1 58 36 17 00",
    "sg:postcode":"75008",
    "sg:province":"Ile de France",
    "sg:tags":[
        "children's",
        "clothing"
    ],
    "wof:name":"Solka Sa",
    "wof:placetype":"venue"
},
  "geometry": {"coordinates":[2.304437,48.868931],"type":"Point"}
}