{
  "type": "Feature",
  "properties": {
    "addr:full":"32 Rue Alfred Pechin 90500 Beaucourt Franche Comt\u00e9 90500",
    "addr:housenumber":"32",
    "addr:postcode":"90500;90500",
    "addr:street":"Rue Alfred Pechin;Franche Comte\u0301",
    "iso:country":"FR",
    "sg:address":"32 Rue Alfred Pechin 90500 Beaucourt",
    "sg:classifiers":[
        {
            "category":"Manufacturing",
            "subcategory":"Metals",
            "type":"Manufacturing & Wholesale Goods"
        }
    ],
    "sg:phone":"+33 3 84 56 91 13",
    "sg:postcode":"90500",
    "sg:province":"Franche Comt\u00e9",
    "sg:tags":[
        "metallurgy",
        "metalworking",
        "processing"
    ],
    "wof:name":"Humbert Ets",
    "wof:placetype":"venue"
},
  "geometry": {"coordinates":[6.915412,47.493259],"type":"Point"}
}