{
  "type": "Feature",
  "properties": {
    "addr:full":"1 place Firmin Gautier 38000 Grenoble Rhone-Alpes 38000",
    "addr:housenumber":"1",
    "addr:postcode":"38000;38000",
    "addr:street":"Place Firmin Gautier",
    "iso:country":"FR",
    "sg:address":"1 place Firmin Gautier 38000 Grenoble",
    "sg:orig_category":"Petroleum Sulphonates",
    "sg:phone":"+33 4 76 70 95 00",
    "sg:postcode":"38000",
    "sg:province":"Rhone-Alpes",
    "wof:name":"Enichem France Sa",
    "wof:placetype":"venue"
},
  "geometry": {"coordinates":[5.711251,45.190716],"type":"Point"}
}