{
  "type": "Feature",
  "properties": {
    "iso:country":"FR",
    "sg:address":"Av. Joliot Curie - ZI de P\u00e9rigny",
    "sg:city":"P\u00e9rigny C\u00e9dex",
    "sg:orig_category":"Non-Classified Establishments",
    "sg:phone":"+33 1 46 38 88 72",
    "sg:postcode":"17185",
    "sg:province":"Poitou-Charentes",
    "wof:name":"Miltron Ross Composants S.a.",
    "wof:placetype":"venue"
},
  "geometry": {"coordinates":[-1.096665,46.15501],"type":"Point"}
}