{
  "type": "Feature",
  "properties": {
    "addr:full":"B.P. 1878, 13222 Marseille C\u00e9dex 01^^14, Rue Fortia, 13001 Marseille Poitou-Charentes",
    "addr:housenumber":"01 ^ ^ 14",
    "addr:postcode":"13222;13001",
    "addr:street":"B.P. 1878;Ce\u0301Dex;Rue Fortia",
    "iso:country":"FR",
    "sg:address":"B.P. 1878, 13222 Marseille C\u00e9dex 01^^14, Rue Fortia, 13001 Marseille",
    "sg:orig_category":"Non-Classified Establishments",
    "sg:phone":"+33 4 91 04 88 00",
    "sg:province":"Poitou-Charentes",
    "wof:name":"Daras Georges S.a.",
    "wof:placetype":"venue"
},
  "geometry": {"coordinates":[5.37249,43.293686],"type":"Point"}
}