{
  "type": "Feature",
  "properties": {
    "addr:full":"Rue Louis Gu\u00e9rin Villeurbanne Rhone-Alpes 69100",
    "addr:postcode":"69100",
    "addr:street":"Rue Louis Gue\u0301Rin;Rhone-Alpes",
    "iso:country":"FR",
    "sg:address":"Rue Louis Gu\u00e9rin",
    "sg:city":"Villeurbanne",
    "sg:orig_category":"Non-Classified Establishments",
    "sg:phone":"+33 4 78 93 72 69",
    "sg:postcode":"69100",
    "sg:province":"Rhone-Alpes",
    "wof:name":"Cholley-minangoy S.a.",
    "wof:placetype":"venue"
},
  "geometry": {"coordinates":[4.86005,45.77602],"type":"Point"}
}