{
  "type": "Feature",
  "properties": {
    "iso:country":"FR",
    "sg:address":"B.P. 89, 68002 Colmar C\u00e9dex^^2, Rue Tinken, 68000 Colmar",
    "sg:city":"Colmar",
    "sg:orig_category":"Non-Classified Establishments",
    "sg:phone":"+33 3 89 21 44 44",
    "sg:postcode":"68000",
    "sg:province":"Alsace",
    "wof:name":"Timken France",
    "wof:placetype":"venue"
},
  "geometry": {"coordinates":[7.363583,48.081985],"type":"Point"}
}