{
  "type": "Feature",
  "properties": {
    "addr:full":"Ld La Fraidi\u00e8re 38380 St Christophe Sur Guiers Rhone-Alpes 38380",
    "addr:postcode":"38380;38380",
    "addr:street":"Ld;Rhone-Alpes",
    "iso:country":"FR",
    "sg:address":"Ld La Fraidi\u00e8re 38380 St Christophe Sur Guiers",
    "sg:classifiers":[
        {
            "category":"Food & Beverages",
            "subcategory":"Dairy",
            "type":"Retail Goods"
        }
    ],
    "sg:phone":"+33 4 76 66 06 08",
    "sg:postcode":"38380",
    "sg:province":"Rhone-Alpes",
    "sg:tags":[
        "product",
        "related"
    ],
    "wof:name":"Le Chartrousin Fromagerie Berruyer",
    "wof:placetype":"venue"
},
  "geometry": {"coordinates":[5.790159,45.314697],"type":"Point"}
}