{
  "type": "Feature",
  "properties": {
    "iso:country":"FR",
    "sg:address":"chemin De Rampaud 38290 FRONTONAS",
    "sg:classifiers":[
        {
            "category":"Tea Room",
            "subcategory":"None",
            "type":"Food & Drink"
        }
    ],
    "sg:phone":"+33 4 74 94 15 41",
    "sg:province":"Rhone-Alpes",
    "sg:tags":[
        "cart"
    ],
    "wof:name":"Neoservice S.a.r.l.",
    "wof:placetype":"venue"
},
  "geometry": {"coordinates":[5.184698,45.649551],"type":"Point"}
}