{
  "type": "Feature",
  "properties": {
    "iso:country":"FR",
    "sg:address":"14 Rue Du Aurant",
    "sg:city":"Sud 35400 St Malo",
    "sg:classifiers":[
        {
            "category":"Utilities",
            "subcategory":"Electric",
            "type":"Services"
        }
    ],
    "sg:phone":"+33 2 99 19 98 19",
    "sg:postcode":"35400",
    "sg:province":"Bretagne",
    "sg:tags":[
        "electricity",
        "electronic",
        "electrical",
        "equipment"
    ],
    "wof:name":"Cef Sa",
    "wof:placetype":"venue"
},
  "geometry": {"coordinates":[-2.003669,48.604897],"type":"Point"}
}