{
  "type": "Feature",
  "properties": {
    "iso:country":"FR",
    "sg:address":"347, Rue Aristide Berg\u00e8s, 38340 Voreppe",
    "sg:orig_category":"Unclassifiable Establishments",
    "sg:phone":"+33 4 76 50 00 02",
    "sg:postcode":"38340",
    "sg:province":"Rhone-Alpes",
    "wof:name":"Office Plus S.a.r.l.",
    "wof:placetype":"venue"
},
  "geometry": {"coordinates":[5.613878,45.309895],"type":"Point"}
}