{
  "type": "Feature",
  "properties": {
    "addr:full":"21, Rue Carion, 71400 Autun Autun Bourgogne 71400",
    "addr:housenumber":"21",
    "addr:postcode":"71400;71400",
    "addr:street":"Rue Carion",
    "iso:country":"FR",
    "sg:address":"21, Rue Carion, 71400 Autun",
    "sg:city":"Autun",
    "sg:orig_category":"Montage d'ensembles m\u00e9caniques M\u00e9canique de pr\u00e9cision Usinage de pr\u00e9cision",
    "sg:phone":"+33 3 85 52 21 21",
    "sg:postcode":"71400",
    "sg:province":"Bourgogne",
    "wof:name":"A.c.me. S.a.r.l. - Atelier De Construction M\u00e9canique",
    "wof:placetype":"venue"
},
  "geometry": {"coordinates":[4.293393,46.956493],"type":"Point"}
}