{
  "type": "Feature",
  "properties": {
    "iso:country":"FR",
    "sg:address":"La Framboise 71420 G\u00e9nelard",
    "sg:city":"G\u00e9nelard",
    "sg:orig_category":"Unclassifiable Establishments",
    "sg:phone":"+33 3 85 79 27 55",
    "sg:postcode":"71420",
    "sg:province":"Bourgogne",
    "wof:name":"Fonderie Charollaise S.a.",
    "wof:placetype":"venue"
},
  "geometry": {"coordinates":[4.156883,46.575153],"type":"Point"}
}