{
  "type": "Feature",
  "properties": {
    "addr:full":"8, Rue Blanche, 75009 Paris Ile de France 75009",
    "addr:housenumber":"8",
    "addr:postcode":"75009;75009",
    "addr:street":"Rue Blanche",
    "iso:country":"FR",
    "sg:address":"8, Rue Blanche, 75009 Paris",
    "sg:orig_category":"Non-Classified Establishments",
    "sg:phone":"+33 1 45 26 64 39",
    "sg:postcode":"75009",
    "sg:province":"Ile de France",
    "wof:name":"Arcane Sout\u00e8nements Acier S.a.",
    "wof:placetype":"venue"
},
  "geometry": {"coordinates":[2.332302,48.877419],"type":"Point"}
}