{
  "type": "Feature",
  "properties": {
    "addr:full":"38, Rte de Woerth, 67510 Lembach Lembach Alsace 67510",
    "addr:housenumber":"38",
    "addr:postcode":"67510;67510",
    "addr:street":"Rte De Woerth",
    "iso:country":"FR",
    "sg:address":"38, Rte de Woerth, 67510 Lembach",
    "sg:city":"Lembach",
    "sg:orig_category":"Non-Classified Establishments",
    "sg:phone":"+33 3 88 94 42 66",
    "sg:postcode":"67510",
    "sg:province":"Alsace",
    "wof:name":"Jost Joseph S.a.r.l.",
    "wof:placetype":"venue"
},
  "geometry": {"coordinates":[7.784456,48.994793],"type":"Point"}
}