{
  "type": "Feature",
  "properties": {
    "iso:country":"FR",
    "sg:address":"5, Rue du 1er Mai, 80460 Friaucourt",
    "sg:orig_category":"Non-Classified Establishments",
    "sg:phone":"+33 3 22 30 47 03",
    "sg:province":"Picardie",
    "wof:name":"Polistyl S.a.r.l.",
    "wof:placetype":"venue"
},
  "geometry": {"coordinates":[1.449713,50.100746],"type":"Point"}
}