{
  "type": "Feature",
  "properties": {
    "addr:full":"B.P. 35, 28400 Nogent le Rotrou^^4, Rue de la Herse, 28400 Nogent le Rotrou Brunelles Centre 28400",
    "addr:postcode":"28400;28400;28400",
    "addr:street":"B.P. 35;Rue De La Herse",
    "iso:country":"FR",
    "sg:address":"B.P. 35, 28400 Nogent le Rotrou^^4, Rue de la Herse, 28400 Nogent le Rotrou",
    "sg:city":"Brunelles",
    "sg:orig_category":"Non-Classified Establishments",
    "sg:phone":"+33 2 37 53 48 20",
    "sg:postcode":"28400",
    "sg:province":"Centre",
    "wof:name":"La R\u00e9publique Du Centre",
    "wof:placetype":"venue"
},
  "geometry": {"coordinates":[0.855275,48.267063],"type":"Point"}
}