{
  "type": "Feature",
  "properties": {
    "addr:full":"R Andr\u00e9 Thevet 47400 Tonneins Tonneins Aquitaine 47400",
    "addr:postcode":"47400;47400",
    "iso:country":"FR",
    "sg:address":"R Andr\u00e9 Thevet 47400 Tonneins",
    "sg:city":"Tonneins",
    "sg:classifiers":[
        {
            "category":"Shopping",
            "subcategory":"Gifts & Souvenirs",
            "type":"Retail Goods"
        }
    ],
    "sg:phone":"+33 5 53 88 33 20",
    "sg:postcode":"47400",
    "sg:province":"Aquitaine",
    "sg:tags":[
        "product",
        "miscellaneous"
    ],
    "wof:name":"Altadis",
    "wof:placetype":"venue"
},
  "geometry": {"coordinates":[0.30072,44.408653],"type":"Point"}
}