{
  "type": "Feature",
  "properties": {
    "addr:full":"82402 Valence d'Agen Aquitaine",
    "addr:postcode":"82402",
    "iso:country":"FR",
    "sg:address":"82402 Valence d'Agen",
    "sg:orig_category":"Unclassifiable Establishments",
    "sg:phone":"+33 5 63 29 60 00",
    "sg:province":"Aquitaine",
    "wof:name":"Agribrandf Europe France S.a.",
    "wof:placetype":"venue"
},
  "geometry": {"coordinates":[0.612557,44.196617],"type":"Point"}
}