{
  "type": "Feature",
  "properties": {
    "iso:country":"FR",
    "sg:address":"r Croix 60420 Ferri\u00e8res",
    "sg:classifiers":[
        {
            "category":"Wholesale",
            "subcategory":"Machinery & Supplies",
            "type":"Manufacturing & Wholesale Goods"
        }
    ],
    "sg:phone":"+33 3 44 51 11 22",
    "sg:province":"Picardie",
    "sg:tags":[
        "equipment",
        "equipement",
        "precision",
        "timekeeping"
    ],
    "wof:name":"Horloges Huchez",
    "wof:placetype":"venue"
},
  "geometry": {"coordinates":[2.51647,49.588856],"type":"Point"}
}