{
  "type": "Feature",
  "properties": {
    "addr:full":"Quartier Sainte Anne V\u00e9d\u00e8ne Provence-Alpes-C\u00f4te d'Azur 84270",
    "addr:postcode":"84270",
    "addr:street":"Quartier",
    "iso:country":"FR",
    "sg:address":"Quartier Sainte Anne",
    "sg:city":"V\u00e9d\u00e8ne",
    "sg:orig_category":"Non-Classified Establishments",
    "sg:phone":"+33 4 90 32 41 00",
    "sg:postcode":"84270",
    "sg:province":"Provence-Alpes-C\u00f4te d'Azur",
    "wof:name":"R\u00e9so",
    "wof:placetype":"venue"
},
  "geometry": {"coordinates":[4.897022,43.987694],"type":"Point"}
}