{
  "type": "Feature",
  "properties": {
    "addr:full":"centre cial; Pusignan Pusignan Rhone-Alpes 69330",
    "addr:housenumber":"pusignan pusignan",
    "addr:postcode":"69330",
    "addr:street":"Cial;Rhone-Alpes",
    "iso:country":"FR",
    "sg:address":"centre cial; Pusignan",
    "sg:city":"Pusignan",
    "sg:classifiers":[
        {
            "category":"Banks & Credit Unions",
            "subcategory":"Bank",
            "type":"Services"
        }
    ],
    "sg:phone":"+33 3378313131",
    "sg:postcode":"69330",
    "sg:province":"Rhone-Alpes",
    "wof:name":"Cr\u00e9dit Agricole Mutuel Sud Est",
    "wof:placetype":"venue"
},
  "geometry": {"coordinates":[5.069754,45.757637],"type":"Point"}
}