{
  "type": "Feature",
  "properties": {
    "addr:full":"Chemin de la Nasque - ZI en Jacca Colomiers Midi Pyr\u00e9n\u00e9es 31770",
    "addr:postcode":"31770",
    "addr:street":"Chemin De La Nasque Zi En Jacca",
    "iso:country":"FR",
    "sg:address":"Chemin de la Nasque - ZI en Jacca",
    "sg:city":"Colomiers",
    "sg:orig_category":"Unclassifiable Establishments",
    "sg:phone":"+33 5 61 15 59 14",
    "sg:postcode":"31770",
    "sg:province":"Midi Pyr\u00e9n\u00e9es",
    "wof:name":"Kdi M\u00e9tal Barbier Besson S.a.s.",
    "wof:placetype":"venue"
},
  "geometry": {"coordinates":[1.33337,43.612431],"type":"Point"}
}