{
  "type": "Feature",
  "properties": {
    "addr:full":"21 avenue du Quebec 91940 Les Ulis Ile de France",
    "addr:housenumber":"21",
    "addr:postcode":"91940",
    "addr:street":"Avenue Du Quebec",
    "iso:country":"FR",
    "sg:address":"21 avenue du Quebec 91940 Les Ulis",
    "sg:classifiers":[
        {
            "category":"Professional",
            "subcategory":"Printing & Photocopies",
            "type":"Services"
        }
    ],
    "sg:phone":"+33 1 69 59 19 20",
    "sg:province":"Ile de France",
    "sg:tags":[
        "publishing",
        "software"
    ],
    "wof:name":"Backweb Technologies S.a.r.l.",
    "wof:placetype":"venue"
},
  "geometry": {"coordinates":[2.169475,48.68161],"type":"Point"}
}