{
  "type": "Feature",
  "properties": {
    "iso:country":"FR",
    "sg:address":"110, Chemin des Combes Noirs, 34400 Villetelle",
    "sg:orig_category":"Non-Classified Establishments",
    "sg:phone":"+33 4 67 86 03 05",
    "sg:postcode":"34400",
    "sg:province":"Languedoc-Roussillon",
    "wof:name":"C\u00f4t\u00e9 Cigale S.a.r.l.",
    "wof:placetype":"venue"
},
  "geometry": {"coordinates":[4.134722,43.722527],"type":"Point"}
}