{
  "type": "Feature",
  "properties": {
    "addr:full":"1 Rue Henry Dunant 45140 Ingr\u00e9 Ingr\u00e9 Centre 45140",
    "addr:housenumber":"1",
    "addr:postcode":"45140;45140",
    "addr:street":"Rue Henry Dunant",
    "iso:country":"FR",
    "sg:address":"1 Rue Henry Dunant 45140 Ingr\u00e9",
    "sg:city":"Ingr\u00e9",
    "sg:classifiers":[
        {
            "category":"Wholesale",
            "subcategory":"Machinery & Supplies",
            "type":"Manufacturing & Wholesale Goods"
        }
    ],
    "sg:phone":"+33 2 38 43 16 16",
    "sg:postcode":"45140",
    "sg:province":"Centre",
    "sg:tags":[
        "handling",
        "material",
        "-",
        "machine",
        "equipment",
        "engineering",
        "mechanical"
    ],
    "wof:name":"Sefi Sa",
    "wof:placetype":"venue"
},
  "geometry": {"coordinates":[1.851304,47.905296],"type":"Point"}
}