{
  "type": "Feature",
  "properties": {
    "addr:full":"COLOMBIERS 34440 COLOMBIERS Languedoc-Roussillon",
    "addr:postcode":"34440",
    "iso:country":"FR",
    "sg:address":"COLOMBIERS 34440 COLOMBIERS",
    "sg:classifiers":[
        {
            "category":"Retail",
            "subcategory":"Auto Repair",
            "type":"Services"
        }
    ],
    "sg:phone":"+33 4 67 37 01 11",
    "sg:province":"Languedoc-Roussillon",
    "sg:tags":[
        "railway",
        "carriage"
    ],
    "wof:name":"Etab Claude S.a.",
    "wof:placetype":"venue"
},
  "geometry": {"coordinates":[3.13962,43.313999],"type":"Point"}
}