{
  "type": "Feature",
  "properties": {
    "addr:full":"25 rue Andr\u00e9 Vasseur 31200 Toulouse Midi Pyr\u00e9n\u00e9es 31200",
    "addr:housenumber":"25",
    "addr:postcode":"31200;31200",
    "addr:street":"Rue Andre\u0301 Vasseur",
    "iso:country":"FR",
    "sg:address":"25 rue Andr\u00e9 Vasseur 31200 Toulouse",
    "sg:classifiers":[
        {
            "category":"Wholesale",
            "subcategory":"Medical Equipment & Supplies",
            "type":"Manufacturing & Wholesale Goods"
        }
    ],
    "sg:phone":"+33 5 34 25 07 70",
    "sg:postcode":"31200",
    "sg:province":"Midi Pyr\u00e9n\u00e9es",
    "wof:name":"Medic Systems S.a.r.l.",
    "wof:placetype":"venue"
},
  "geometry": {"coordinates":[1.4723,43.635475],"type":"Point"}
}