{
  "type": "Feature",
  "properties": {
    "iso:country":"FR",
    "sg:address":"Cour de la Gare Marchandises",
    "sg:city":"Saint Dizier",
    "sg:orig_category":"Unclassifiable Establishments",
    "sg:phone":"+33 3 25 56 19 96",
    "sg:postcode":"52100",
    "sg:province":"Champagne",
    "wof:name":"52 Express Nord S.a.r.l.",
    "wof:placetype":"venue"
},
  "geometry": {"coordinates":[4.946965,48.636589],"type":"Point"}
}