{
  "type": "Feature",
  "properties": {
    "addr:full":"ZI n\u00b0470 des Fournels Lunel Languedoc-Roussillon 34400",
    "addr:postcode":"34400",
    "iso:country":"FR",
    "sg:address":"ZI n\u00b0470 des Fournels",
    "sg:city":"Lunel",
    "sg:orig_category":"Non-Classified Establishments",
    "sg:phone":"+33 4 67 71 78 00",
    "sg:postcode":"34400",
    "sg:province":"Languedoc-Roussillon",
    "wof:name":"Espace Composite S.a.r.l.",
    "wof:placetype":"venue"
},
  "geometry": {"coordinates":[4.108795,43.679749],"type":"Point"}
}