{
  "type": "Feature",
  "properties": {
    "addr:full":"Av. Santos Dumont Saint Aignan Grandlieu Pays de Loire 44860",
    "addr:postcode":"grandlieu;44860",
    "addr:street":"Av. Santos Dumont",
    "iso:country":"FR",
    "sg:address":"Av. Santos Dumont",
    "sg:city":"Saint Aignan Grandlieu",
    "sg:orig_category":"Unclassifiable Establishments",
    "sg:phone":"+33 2 40 13 56 00",
    "sg:postcode":"44860",
    "sg:province":"Pays de Loire",
    "wof:name":"Transports Graveleau S.a.",
    "wof:placetype":"venue"
},
  "geometry": {"coordinates":[-1.59491,47.152016],"type":"Point"}
}