{
  "type": "Feature",
  "properties": {
    "iso:country":"FR",
    "sg:address":"B.P. 2",
    "sg:city":"La Bresse^^88250 La Bresse",
    "sg:orig_category":"Non-Classified Establishments",
    "sg:phone":"+33 3 29 25 41 04",
    "sg:postcode":"88250",
    "sg:province":"Lorraine",
    "wof:name":"Demange Andr\u00e9 Graniterie S.a.r.l.",
    "wof:placetype":"venue"
},
  "geometry": {"coordinates":[6.87512,48.003704],"type":"Point"}
}