{
  "type": "Feature",
  "properties": {
    "addr:full":"130 Av De Mayenne 53000 Laval Pays de Loire 53000",
    "addr:postcode":"53000;53000",
    "addr:street":"130 Av De Mayenne",
    "iso:country":"FR",
    "sg:address":"130 Av De Mayenne 53000 Laval",
    "sg:classifiers":[
        {
            "category":"Manufacturing",
            "subcategory":"Motor Vehicles & Parts",
            "type":"Manufacturing & Wholesale Goods"
        }
    ],
    "sg:phone":"+33 2 43 49 42 00",
    "sg:postcode":"53000",
    "sg:province":"Pays de Loire",
    "sg:tags":[
        "engine",
        "machine",
        "engineering",
        "-",
        "mechanical"
    ],
    "wof:name":"Valeo Thermique Moteur Sa",
    "wof:placetype":"venue"
},
  "geometry": {"coordinates":[-0.752307,48.081768],"type":"Point"}
}