{
  "type": "Feature",
  "properties": {
    "addr:full":"Zi Maltete 56140 Pleucadeuc Pleucadeuc Bretagne 56140",
    "addr:postcode":"56140;56140",
    "addr:street":"Pleucadeuc",
    "iso:country":"FR",
    "sg:address":"Zi Maltete 56140 Pleucadeuc",
    "sg:city":"Pleucadeuc",
    "sg:classifiers":[
        {
            "category":"Professional",
            "subcategory":"Engineering",
            "type":"Services"
        }
    ],
    "sg:phone":"+33 2 97 26 91 43",
    "sg:postcode":"56140",
    "sg:province":"Bretagne",
    "sg:tags":[
        "machine",
        "-",
        "mechanical"
    ],
    "wof:name":"Saric Sa",
    "wof:placetype":"venue"
},
  "geometry": {"coordinates":[-2.375769,47.758858],"type":"Point"}
}