{
  "type": "Feature",
  "properties": {
    "addr:full":"103, Rue Kuntzig, 57970 Yutz Kuntzig Lorraine 57110",
    "addr:housenumber":"103",
    "addr:postcode":"57970;57110",
    "addr:street":"Rue Kuntzig",
    "iso:country":"FR",
    "sg:address":"103, Rue Kuntzig, 57970 Yutz",
    "sg:city":"Kuntzig",
    "sg:orig_category":"Non-Classified Establishments",
    "sg:phone":"+33 3 82 56 74 00",
    "sg:postcode":"57110",
    "sg:province":"Lorraine",
    "wof:name":"S.e.r.e.i. S.a.r.l. - Soci\u00e9t\u00e9 Etude R\u00e9alisation D'equipement Industriel",
    "wof:placetype":"venue"
},
  "geometry": {"coordinates":[6.209669,49.352364],"type":"Point"}
}