{
  "type": "Feature",
  "properties": {
    "addr:full":"Quartier De La Chaberte Chem De Toulon Qut De La Chaberte 83210 La Farlede Auvergne",
    "addr:postcode":"83210",
    "addr:street":"Quartier;La Chaberte Chem De Toulon",
    "iso:country":"FR",
    "sg:address":"Quartier De La Chaberte",
    "sg:city":"Chem De Toulon Qut De La Chaberte 83210 La Farlede",
    "sg:classifiers":[
        {
            "category":"Banks & Credit Unions",
            "subcategory":"Investment Brokerage",
            "type":"Services"
        }
    ],
    "sg:phone":"+33 4 94 14 37 20",
    "sg:province":"Auvergne",
    "sg:tags":[
        "-",
        "transport",
        "related"
    ],
    "wof:name":"Extand",
    "wof:placetype":"venue"
},
  "geometry": {"coordinates":[6.042811,43.166992],"type":"Point"}
}