{
  "type": "Feature",
  "properties": {
    "addr:full":"4, Rue Emile Noirot, 42000 saint Etienne Rhone-Alpes 42000",
    "addr:housenumber":"4",
    "addr:postcode":"42000;42000",
    "addr:street":"Rue Emile Noirot",
    "iso:country":"FR",
    "sg:address":"4, Rue Emile Noirot, 42000 saint Etienne",
    "sg:orig_category":"Non-Classified Establishments",
    "sg:phone":"+33 4 77 41 82 22",
    "sg:postcode":"42000",
    "sg:province":"Rhone-Alpes",
    "wof:name":"A.v.t.s. S.a.r.l. - Air Et Voiles Techniques St\u00e9phanoises",
    "wof:placetype":"venue"
},
  "geometry": {"coordinates":[4.382893,45.427265],"type":"Point"}
}