{
  "type": "Feature",
  "properties": {
    "addr:full":"4 cours Alsace-Lorraine 24100 Bergerac Bergerac Aquitaine 24100",
    "addr:housenumber":"4",
    "addr:postcode":"24100;24100",
    "addr:street":"Cours Alsace-Lorraine",
    "iso:country":"FR",
    "sg:address":"4 cours Alsace-Lorraine 24100 Bergerac",
    "sg:city":"Bergerac",
    "sg:classifiers":[
        {
            "category":"Food & Beverages",
            "subcategory":"Specialty",
            "type":"Retail Goods"
        }
    ],
    "sg:phone":"+33 5 53 61 25 25",
    "sg:postcode":"24100",
    "sg:province":"Aquitaine",
    "sg:tags":[
        "olive-oil"
    ],
    "wof:name":"Import Produits Aliment Collectivites Sa",
    "wof:placetype":"venue"
},
  "geometry": {"coordinates":[0.485949,44.855816],"type":"Point"}
}