{
  "type": "Feature",
  "properties": {
    "iso:country":"FR",
    "sg:address":"Z I des Jonquieres 57365 Ennery",
    "sg:classifiers":[
        {
            "category":"Manufacturing",
            "subcategory":"Electronics",
            "type":"Manufacturing & Wholesale Goods"
        }
    ],
    "sg:phone":"+33 3 87 73 86 73",
    "sg:province":"Lorraine",
    "sg:tags":[
        "pcb",
        "printed",
        "circuit",
        "board"
    ],
    "wof:name":"Cimulec S A",
    "wof:placetype":"venue"
},
  "geometry": {"coordinates":[6.221613,49.22702],"type":"Point"}
}