{
  "type": "Feature",
  "properties": {
    "addr:full":"132, Rue Dominique Clos, 31300 Toulouse Midi Pyr\u00e9n\u00e9es",
    "addr:housenumber":"132",
    "addr:postcode":"31300",
    "addr:street":"Rue Dominique Clos",
    "iso:country":"FR",
    "sg:address":"132, Rue Dominique Clos, 31300 Toulouse",
    "sg:orig_category":"Non-Classified Establishments",
    "sg:phone":"+33 5 61 49 17 61",
    "sg:province":"Midi Pyr\u00e9n\u00e9es",
    "wof:name":"Vidal S.a.",
    "wof:placetype":"venue"
},
  "geometry": {"coordinates":[1.366964,43.605934],"type":"Point"}
}