{
  "type": "Feature",
  "properties": {
    "addr:full":"29, Rue de Tr\u00e9vise, 75009 Paris Ile de France",
    "addr:housenumber":"29",
    "addr:postcode":"75009",
    "addr:street":"Rue De Tre\u0301Vise",
    "iso:country":"FR",
    "sg:address":"29, Rue de Tr\u00e9vise, 75009 Paris",
    "sg:orig_category":"Unclassifiable Establishments",
    "sg:phone":"+33 1 53 24 20 20",
    "sg:province":"Ile de France",
    "wof:name":"Assistante Marketing Direct S.a.r.l.",
    "wof:placetype":"venue"
},
  "geometry": {"coordinates":[2.345165,48.87468],"type":"Point"}
}