{
  "type": "Feature",
  "properties": {
    "iso:country":"FR",
    "sg:address":"11, Av. du G\u00e9n\u00e9ral Lyautey, 78170 La Celle Saint Cloud",
    "sg:orig_category":"Non-Classified Establishments",
    "sg:phone":"+33 1 30 82 63 13",
    "sg:province":"Ile de France",
    "wof:name":"Grain D'eau S.a.r.l.",
    "wof:placetype":"venue"
},
  "geometry": {"coordinates":[2.131767,48.851406],"type":"Point"}
}