{
  "type": "Feature",
  "properties": {
    "addr:full":"36 Rue Des Otages 80037 Amiens Cedex 1 Amiens Picardie 80000",
    "addr:housenumber":"36",
    "addr:postcode":"80037 amiens;80000",
    "addr:street":"Rue Des Otages",
    "iso:country":"FR",
    "sg:address":"36 Rue Des Otages 80037 Amiens Cedex 1",
    "sg:city":"Amiens",
    "sg:classifiers":[
        {
            "category":"Professional",
            "subcategory":"Business Services",
            "type":"Services"
        }
    ],
    "sg:phone":"+33 3 22 82 80 93",
    "sg:postcode":"80000",
    "sg:province":"Picardie",
    "sg:tags":[
        "body",
        "advice"
    ],
    "wof:name":"Chambre Regionale Commerce Industrie Picardie",
    "wof:placetype":"venue"
},
  "geometry": {"coordinates":[2.30253,49.893959],"type":"Point"}
}