{
  "type": "Feature",
  "properties": {
    "addr:full":"Zi De La Gravoux 42380 La Tourette Rhone-Alpes 42380",
    "addr:postcode":"42380;42380",
    "addr:street":"Zi De La Gravoux;Tourette Rhone-Alpes",
    "iso:country":"FR",
    "sg:address":"Zi De La Gravoux 42380 La Tourette",
    "sg:classifiers":[
        {
            "category":"Shopping",
            "subcategory":"Crafts & Fabrics",
            "type":"Retail Goods"
        }
    ],
    "sg:phone":"+33 4 77 50 13 52",
    "sg:postcode":"42380",
    "sg:province":"Rhone-Alpes",
    "sg:tags":[
        "textile",
        "linen",
        "clothing"
    ],
    "wof:name":"Stof",
    "wof:placetype":"venue"
},
  "geometry": {"coordinates":[4.083075,45.415443],"type":"Point"}
}