{
  "type": "Feature",
  "properties": {
    "addr:full":"Le Bosc Adam 76560 Yvecrique Haute Normandie",
    "addr:housenumber":"le bosc",
    "addr:postcode":"76560",
    "addr:street":"Adam;Haute Normandie",
    "iso:country":"FR",
    "sg:address":"Le Bosc Adam 76560 Yvecrique",
    "sg:orig_category":"Unclassifiable Establishments",
    "sg:phone":"+33 2 35 56 40 39",
    "sg:province":"Haute Normandie",
    "wof:name":"C.t.p. S.a.r.l. - Cr\u00e9ation Et Travaux Du Paysage",
    "wof:placetype":"venue"
},
  "geometry": {"coordinates":[0.81018,49.689823],"type":"Point"}
}