{
  "type": "Feature",
  "properties": {
    "addr:full":"Rue de Coudekerque Teteghem Nord Pas-de-Calais 59229",
    "addr:postcode":"59229",
    "addr:street":"Rue De Coudekerque Teteghem Nord",
    "iso:country":"FR",
    "sg:address":"Rue de Coudekerque",
    "sg:city":"Teteghem",
    "sg:orig_category":"Unclassifiable Establishments",
    "sg:phone":"+33 3 28 26 15 50",
    "sg:postcode":"59229",
    "sg:province":"Nord Pas-de-Calais",
    "wof:name":"Destock S.a.",
    "wof:placetype":"venue"
},
  "geometry": {"coordinates":[2.445056,51.010948],"type":"Point"}
}