{
  "type": "Feature",
  "properties": {
    "addr:full":"ZA de Troyalac'h Saint Evarzec Bretagne 29170",
    "addr:postcode":"29170",
    "addr:street":"Za De Troyalac'H Saint Evarzec Bretagne",
    "iso:country":"FR",
    "sg:address":"ZA de Troyalac'h",
    "sg:city":"Saint Evarzec",
    "sg:orig_category":"Non-Classified Establishments",
    "sg:phone":"+33 2 98 94 65 11",
    "sg:postcode":"29170",
    "sg:province":"Bretagne",
    "wof:name":"A.t.b. S.a.r.l. - Andouilles Et Tripes De Bretagne",
    "wof:placetype":"venue"
},
  "geometry": {"coordinates":[-4.02197,47.936451],"type":"Point"}
}