{
  "type": "Feature",
  "properties": {
    "iso:country":"FR",
    "sg:address":"37C, Rue des Vignes, 67205 Oberhausbergen",
    "sg:city":"Oberhausbergen",
    "sg:orig_category":"Non-Classified Establishments",
    "sg:phone":"+33 3 90 20 58 18",
    "sg:postcode":"67205",
    "sg:province":"Alsace",
    "wof:name":"G\u00e9tronik France S.a.",
    "wof:placetype":"venue"
},
  "geometry": {"coordinates":[7.679697,48.608353],"type":"Point"}
}