{
  "type": "Feature",
  "properties": {
    "iso:country":"FR",
    "sg:address":"35, Av. Paul Vaillant Couturier, 93120 La Courneuve",
    "sg:orig_category":"Non-Classified Establishments",
    "sg:phone":"+33 1 48 28 22 23",
    "sg:province":"Ile de France",
    "wof:name":"Synergie S.a.",
    "wof:placetype":"venue"
},
  "geometry": {"coordinates":[2.409497,48.920101],"type":"Point"}
}