{
  "type": "Feature",
  "properties": {
    "addr:full":"39 Rue Des Fossettes 95650 Genicourt Ile de France 95650",
    "addr:housenumber":"39",
    "addr:postcode":"95650;95650",
    "addr:street":"Rue Des Fossettes;Ile De France",
    "iso:country":"FR",
    "sg:address":"39 Rue Des Fossettes 95650 Genicourt",
    "sg:classifiers":[
        {
            "category":"Professional",
            "subcategory":"Engineering",
            "type":"Services"
        }
    ],
    "sg:phone":"+33 1 34 42 61 10",
    "sg:postcode":"95650",
    "sg:province":"Ile de France",
    "sg:tags":[
        "machine",
        "-",
        "mechanical"
    ],
    "wof:name":"Lafon Sa",
    "wof:placetype":"venue"
},
  "geometry": {"coordinates":[2.06936,49.086472],"type":"Point"}
}