{
  "type": "Feature",
  "properties": {
    "addr:full":"Zone Industrielle Les Noyes Froideconche Franche Comt\u00e9 70300",
    "addr:postcode":"70300",
    "addr:street":"Zone Industrielle Les;Franche Comte\u0301",
    "iso:country":"FR",
    "sg:address":"Zone Industrielle Les Noyes",
    "sg:city":"Froideconche",
    "sg:orig_category":"Unclassifiable Establishments",
    "sg:phone":"+33 3 84 93 93 00",
    "sg:postcode":"70300",
    "sg:province":"Franche Comt\u00e9",
    "wof:name":"Transports Luxoviens S.a.",
    "wof:placetype":"venue"
},
  "geometry": {"coordinates":[6.41594,47.819145],"type":"Point"}
}