{
  "type": "Feature",
  "properties": {
    "iso:country":"FR",
    "sg:address":"21, Rue Louis Blanc, 69006 Lyon",
    "sg:orig_category":"Non-Classified Establishments",
    "sg:phone":"+33 4 78 52 29 49",
    "sg:province":"Rhone-Alpes",
    "wof:name":"Fast Maintenance Informatique S.a.",
    "wof:placetype":"venue"
},
  "geometry": {"coordinates":[4.848551,45.764839],"type":"Point"}
}