{
  "type": "Feature",
  "properties": {
    "iso:country":"FR",
    "sg:address":"Rte de Bedarrides",
    "sg:city":"Entraigues sur la Sorgue",
    "sg:orig_category":"Unclassifiable Establishments",
    "sg:phone":"+33 4 90 83 10 50",
    "sg:postcode":"84320",
    "sg:province":"Auvergne",
    "wof:name":"Sifraco",
    "wof:placetype":"venue"
},
  "geometry": {"coordinates":[4.922002,44.020458],"type":"Point"}
}