{
  "type": "Feature",
  "properties": {
    "addr:full":"Queue de l'Ile Les Rosiers sur Loire Pays de Loire 49350",
    "addr:postcode":"49350",
    "iso:country":"FR",
    "sg:address":"Queue de l'Ile",
    "sg:city":"Les Rosiers sur Loire",
    "sg:orig_category":"Unclassifiable Establishments",
    "sg:phone":"+33 2 41 38 06 06",
    "sg:postcode":"49350",
    "sg:province":"Pays de Loire",
    "wof:name":"M\u00e9gnien Distribution S.n.c.",
    "wof:placetype":"venue"
},
  "geometry": {"coordinates":[-0.216993,47.346592],"type":"Point"}
}