{
  "type": "Feature",
  "properties": {
    "addr:full":"22 Boulevard de Strasbourg, 31007 Toulouse, Dept 31 Strasbourg Alsace 67000",
    "addr:housenumber":"22;31",
    "addr:postcode":"31007;67000",
    "addr:street":"Boulevard De Strasbourg;Strasbourg",
    "iso:country":"FR",
    "sg:address":"22 Boulevard de Strasbourg, 31007 Toulouse, Dept 31",
    "sg:city":"Strasbourg",
    "sg:classifiers":[
        {
            "category":"Banks & Credit Unions",
            "subcategory":"Bank",
            "type":"Services"
        }
    ],
    "sg:postcode":"67000",
    "sg:province":"Alsace",
    "wof:name":"Soci\u00e9t\u00e9 De Banque Midi-pyr\u00e9n\u00e9es Sa",
    "wof:placetype":"venue"
},
  "geometry": {"coordinates":[1.447433,43.607319],"type":"Point"}
}