{
  "type": "Feature",
  "properties": {
    "iso:country":"FR",
    "sg:address":"Rue Climont Zi 67220 Neuve-Eglise",
    "sg:city":"Neuve-\u00c9glise",
    "sg:classifiers":[
        {
            "category":"Shopping",
            "subcategory":"Computers & Home Electronics",
            "type":"Retail Goods"
        }
    ],
    "sg:phone":"+33 3 88 58 90 50",
    "sg:postcode":"67220",
    "sg:province":"Alsace",
    "sg:tags":[
        "equipment",
        "electrical",
        "component",
        "electric",
        "electronic"
    ],
    "wof:name":"Signal Lux Electronics",
    "wof:placetype":"venue"
},
  "geometry": {"coordinates":[7.302732,48.342537],"type":"Point"}
}