{
  "type": "Feature",
  "properties": {
    "addr:full":"route De Nogent Le Roi 28230 Epernon \u00c9pernon Centre 28230",
    "addr:housenumber":"e\u0301pernon",
    "addr:postcode":"28230;28230",
    "addr:street":"Route De Nogent Le Roi",
    "iso:country":"FR",
    "sg:address":"route De Nogent Le Roi 28230 Epernon",
    "sg:city":"\u00c9pernon",
    "sg:classifiers":[
        {
            "category":"Manufacturing",
            "subcategory":"Glass & Minerals",
            "type":"Manufacturing & Wholesale Goods"
        }
    ],
    "sg:phone":"+33 2 37 83 79 53",
    "sg:postcode":"28230",
    "sg:province":"Centre",
    "sg:tags":[
        "polystyrene"
    ],
    "wof:name":"Euro Polydecor S.a.",
    "wof:placetype":"venue"
},
  "geometry": {"coordinates":[1.671139,48.61087],"type":"Point"}
}