{
  "type": "Feature",
  "properties": {
    "addr:full":"Rue Notre Dame Z I Batiment A 02360 Rozoy Sur Serre Picardie",
    "addr:postcode":"02360",
    "addr:street":"Rue Notre Dame;Rozoy",
    "iso:country":"FR",
    "sg:address":"Rue Notre Dame Z I Batiment A 02360 Rozoy Sur Serre",
    "sg:classifiers":[
        {
            "category":"Autos & Motor Vehicles",
            "subcategory":"Automobile Sales",
            "type":"Retail Goods"
        }
    ],
    "sg:phone":"+33 3 23 91 33 00",
    "sg:province":"Picardie",
    "sg:tags":[
        "equipment",
        "transport"
    ],
    "wof:name":"Trigano Service",
    "wof:placetype":"venue"
},
  "geometry": {"coordinates":[4.14562,49.747921],"type":"Point"}
}