{
  "type": "Feature",
  "properties": {
    "addr:full":"A\u00e9roport B\u00e2le Mulhouse Saint Louis Alsace 68300",
    "addr:postcode":"68300",
    "iso:country":"FR",
    "sg:address":"A\u00e9roport B\u00e2le Mulhouse",
    "sg:city":"Saint Louis",
    "sg:orig_category":"Non-Classified Establishments",
    "sg:phone":"+33 3 89 90 21 21",
    "sg:postcode":"68300",
    "sg:province":"Alsace",
    "wof:name":"Sog\u00e9tra Air Service S.a.",
    "wof:placetype":"venue"
},
  "geometry": {"coordinates":[7.53134,47.599789],"type":"Point"}
}