{
  "type": "Feature",
  "properties": {
    "iso:country":"FR",
    "sg:address":"87, Rue des Jardins, 59182 Montigny en Ostrevent",
    "sg:orig_category":"Non-Classified Establishments",
    "sg:phone":"+33 3 27 91 45 36",
    "sg:province":"Nord Pas-de-Calais",
    "wof:name":"France Coq S.a.",
    "wof:placetype":"venue"
},
  "geometry": {"coordinates":[3.183445,50.364494],"type":"Point"}
}