{
  "type": "Feature",
  "properties": {
    "addr:full":"1, Impasse Blaise Pascal, 15000 Aurillac Aurillac Auvergne 15000",
    "addr:housenumber":"1",
    "addr:postcode":"15000;15000",
    "addr:street":"Impasse Blaise Pascal",
    "iso:country":"FR",
    "sg:address":"1, Impasse Blaise Pascal, 15000 Aurillac",
    "sg:city":"Aurillac",
    "sg:orig_category":"Unclassifiable Establishments",
    "sg:phone":"+33 4 71 64 97 90",
    "sg:postcode":"15000",
    "sg:province":"Auvergne",
    "wof:name":"L'escargot Courbeyre S.a.r.l.",
    "wof:placetype":"venue"
},
  "geometry": {"coordinates":[2.429235,44.90163],"type":"Point"}
}