{
  "type": "Feature",
  "properties": {
    "addr:full":"12 - 1, Rue Chauvart, 95500 Gonesse Ile de France",
    "addr:housenumber":"1",
    "addr:postcode":"95500;ile",
    "addr:street":"12;Rue Chauvart",
    "iso:country":"FR",
    "sg:address":"12 - 1, Rue Chauvart, 95500 Gonesse",
    "sg:orig_category":"Unclassifiable Establishments",
    "sg:phone":"+33 1 39 87 00 96",
    "sg:province":"Ile de France",
    "wof:name":"Guyon S.a.",
    "wof:placetype":"venue"
},
  "geometry": {"coordinates":[2.456221,48.984955],"type":"Point"}
}