{
  "type": "Feature",
  "properties": {
    "addr:full":"3, Rue du Pont Madame, 78440 Brueil en Vexin Ile de France",
    "addr:housenumber":"3",
    "addr:postcode":"78440",
    "addr:street":"Rue Du Pont Madame",
    "iso:country":"FR",
    "sg:address":"3, Rue du Pont Madame, 78440 Brueil en Vexin",
    "sg:orig_category":"Unclassifiable Establishments",
    "sg:phone":"+33 1 34 75 10 52",
    "sg:province":"Ile de France",
    "wof:name":"Chance Partenaires S.a.r.l.",
    "wof:placetype":"venue"
},
  "geometry": {"coordinates":[1.817347,49.031685],"type":"Point"}
}