{
  "type": "Feature",
  "properties": {
    "iso:country":"FR",
    "sg:address":"Roz Even 29620 Lanmeur",
    "sg:city":"Lanmeur",
    "sg:classifiers":[
        {
            "category":"Building & Trades",
            "subcategory":"Construction",
            "type":"Services"
        }
    ],
    "sg:phone":"+33 2 98 79 90 14",
    "sg:postcode":"29620",
    "sg:province":"Bretagne",
    "sg:tags":[
        "livestock",
        "business",
        "advice",
        "animal",
        "breeding",
        "agriculture"
    ],
    "wof:name":"Sarl De Roz Even",
    "wof:placetype":"venue"
},
  "geometry": {"coordinates":[-3.700159,48.62635],"type":"Point"}
}