{
  "type": "Feature",
  "properties": {
    "addr:full":"9 R Des Mar\u00e9chaux 68100 Mulhouse Mulhouse Alsace 68100",
    "addr:housenumber":"9 r",
    "addr:postcode":"68100;68100",
    "addr:street":"Des Mare\u0301Chaux",
    "iso:country":"FR",
    "sg:address":"9 R Des Mar\u00e9chaux 68100 Mulhouse",
    "sg:city":"Mulhouse",
    "sg:classifiers":[
        {
            "category":"Shopping",
            "subcategory":"Bicycles & Sporting Goods",
            "type":"Retail Goods"
        }
    ],
    "sg:phone":"+33 3 89 45 67 18",
    "sg:postcode":"68100",
    "sg:province":"Alsace",
    "sg:tags":[
        "product",
        "sport",
        "miscellaneous"
    ],
    "wof:name":"Weigel Sports Sa",
    "wof:placetype":"venue"
},
  "geometry": {"coordinates":[7.337169,47.748386],"type":"Point"}
}