{
  "type": "Feature",
  "properties": {
    "addr:full":"B.P. 605, 03317 Montlu\u00e7on C\u00e9dex^^Rue Benoist d'Azy, 03100 Montlu\u00e7on Montlu\u00e7on Auvergne 03100",
    "addr:housenumber":"b.p. 605",
    "addr:postcode":"03317;03100;03100",
    "addr:street":"D'Azy",
    "iso:country":"FR",
    "sg:address":"B.P. 605, 03317 Montlu\u00e7on C\u00e9dex^^Rue Benoist d'Azy, 03100 Montlu\u00e7on",
    "sg:city":"Montlu\u00e7on",
    "sg:orig_category":"Non-Classified Establishments",
    "sg:phone":"+33 4 70 29 52 02",
    "sg:postcode":"03100",
    "sg:province":"Auvergne",
    "wof:name":"Montlu\u00e7on Viandes S.a.",
    "wof:placetype":"venue"
},
  "geometry": {"coordinates":[2.606608,46.356499],"type":"Point"}
}