{
  "type": "Feature",
  "properties": {
    "addr:full":"Route Paris 89700 Tonnerre Tonnerre Bourgogne 89700",
    "addr:postcode":"89700;89700",
    "addr:street":"Route Paris",
    "iso:country":"FR",
    "sg:address":"Route Paris 89700 Tonnerre",
    "sg:city":"Tonnerre",
    "sg:classifiers":[
        {
            "category":"Autos & Motor Vehicles",
            "subcategory":"Automobile Sales",
            "type":"Retail Goods"
        }
    ],
    "sg:phone":"+33 3 86 55 05 88",
    "sg:postcode":"89700",
    "sg:province":"Bourgogne",
    "sg:tags":[
        "equipment",
        "industrial",
        "transport"
    ],
    "wof:name":"Materiel Agricole Du Tonnerrois Sa",
    "wof:placetype":"venue"
},
  "geometry": {"coordinates":[3.964393,47.877403],"type":"Point"}
}