{
  "type": "Feature",
  "properties": {
    "iso:country":"FR",
    "sg:address":"B.P. 31",
    "sg:city":"Richelieu",
    "sg:orig_category":"Non-Classified Establishments",
    "sg:phone":"+33 2 47 95 30 01",
    "sg:postcode":"37120",
    "sg:province":"Centre",
    "wof:name":"Etablissements Catin S.a.",
    "wof:placetype":"venue"
},
  "geometry": {"coordinates":[0.324045,47.01247],"type":"Point"}
}