{
  "type": "Feature",
  "properties": {
    "addr:full":"8 Place Gambetta 66000 Perpignan Languedoc-Roussillon 66000",
    "addr:housenumber":"8",
    "addr:postcode":"66000;66000",
    "addr:street":"Place Gambetta",
    "iso:country":"FR",
    "sg:address":"8 Place Gambetta 66000 Perpignan",
    "sg:orig_category":"Miscellaneous Products",
    "sg:phone":"+33 4 68 51 30 20",
    "sg:postcode":"66000",
    "sg:province":"Languedoc-Roussillon",
    "wof:name":"Pompes Funebres Du Roussillon",
    "wof:placetype":"venue"
},
  "geometry": {"coordinates":[2.896524,42.700432],"type":"Point"}
}