{
  "type": "Feature",
  "properties": {
    "addr:full":"B.P. 129, 60251 Mouy C\u00e9dex^^Rte de Balagny - ZI les Petits Pr\u00e9s, 60250 Mouy Picardie",
    "addr:housenumber":"b.p. 129",
    "addr:postcode":"60251;60250",
    "addr:street":"Zi Les Petits Pre\u0301S",
    "iso:country":"FR",
    "sg:address":"B.P. 129, 60251 Mouy C\u00e9dex^^Rte de Balagny - ZI les Petits Pr\u00e9s, 60250 Mouy",
    "sg:orig_category":"Non-Classified Establishments",
    "sg:phone":"+33 3 44 31 15 15",
    "sg:province":"Picardie",
    "wof:name":"Tec Automatismes S.a.s.",
    "wof:placetype":"venue"
},
  "geometry": {"coordinates":[2.322815,49.320976],"type":"Point"}
}