{
  "type": "Feature",
  "properties": {
    "iso:country":"FR",
    "sg:address":"7, Av du 8 Mai 1945, 76610 Le Havre",
    "sg:orig_category":"Non-Classified Establishments",
    "sg:phone":"+33 2 32 79 54 80",
    "sg:province":"Haute-Normandie",
    "wof:name":"S.e.r.o. S.a. - Soci\u00e9t\u00e9 D'etudes Et De Recherche Op\u00e9rationnelle",
    "wof:placetype":"venue"
},
  "geometry": {"coordinates":[0.16879,49.516579],"type":"Point"}
}