{
  "type": "Feature",
  "properties": {
    "iso:country":"FR",
    "sg:address":"7 Bd Omer Sarrault 11000 Carcassonne",
    "sg:classifiers":[
        {
            "category":"Building & Trades",
            "subcategory":"Construction",
            "type":"Services"
        }
    ],
    "sg:phone":"+33 4 68 47 36 16",
    "sg:postcode":"11000",
    "sg:province":"Languedoc-Roussillon",
    "sg:tags":[
        "work",
        "public"
    ],
    "wof:name":"Entreprise Llasera",
    "wof:placetype":"venue"
},
  "geometry": {"coordinates":[2.353167,43.216286],"type":"Point"}
}