{
  "type": "Feature",
  "properties": {
    "iso:country":"FR",
    "sg:address":"52, Rue des Entrepreneurs, 91560 Crosne",
    "sg:orig_category":"Non-Classified Establishments",
    "sg:phone":"+33 1 69 48 49 99",
    "sg:province":"Ile de France",
    "wof:name":"R.c.s.i. S.a.r.l. - Recherche Composants Service Industrie",
    "wof:placetype":"venue"
},
  "geometry": {"coordinates":[2.473045,48.726982],"type":"Point"}
}