{
  "type": "Feature",
  "properties": {
    "iso:country":"FR",
    "sg:address":"Rue D Orleans Zi 51120 Sezanne",
    "sg:classifiers":[
        {
            "category":"Professional",
            "subcategory":"Engineering",
            "type":"Services"
        }
    ],
    "sg:phone":"+33 3 26 80 64 62",
    "sg:postcode":"51120",
    "sg:province":"Champagne",
    "sg:tags":[
        "machine",
        "-",
        "mechanical"
    ],
    "wof:name":"Etablissements Henriot",
    "wof:placetype":"venue"
},
  "geometry": {"coordinates":[3.718915,48.72324],"type":"Point"}
}