{
  "type": "Feature",
  "properties": {
    "iso:country":"FR",
    "sg:address":"B.P. 73, 77483 Provins C\u00e9dex^^12, Rue aux Aulx, 77160 Provins",
    "sg:orig_category":"Non-Classified Establishments",
    "sg:phone":"+33 1 60 67 60 80",
    "sg:province":"Ile de France",
    "wof:name":"Sbec S.a.",
    "wof:placetype":"venue"
},
  "geometry": {"coordinates":[3.312839,48.527699],"type":"Point"}
}