{
  "type": "Feature",
  "properties": {
    "addr:full":"B.P. 56, 81210 Lacrouzette^^65, Rte de Vabre, 81210 Lacrouzette Midi Pyr\u00e9n\u00e9es",
    "addr:postcode":"81210;81210",
    "addr:street":"B.P. 56;Rte De Vabre",
    "iso:country":"FR",
    "sg:address":"B.P. 56, 81210 Lacrouzette^^65, Rte de Vabre, 81210 Lacrouzette",
    "sg:orig_category":"Non-Classified Establishments",
    "sg:phone":"+33 5 63 50 60 37",
    "sg:province":"Midi Pyr\u00e9n\u00e9es",
    "wof:name":"Etablissements Sablayrolles Et Fils S.a.r.l.",
    "wof:placetype":"venue"
},
  "geometry": {"coordinates":[2.293234,43.666641],"type":"Point"}
}