{
  "type": "Feature",
  "properties": {
    "addr:full":"ZI Saint Joseph Manosque Aquitaine 04100",
    "addr:postcode":"04100",
    "addr:street":"Joseph",
    "iso:country":"FR",
    "sg:address":"ZI Saint Joseph",
    "sg:city":"Manosque",
    "sg:orig_category":"Unclassifiable Establishments",
    "sg:phone":"+33 4 92 87 32 33",
    "sg:postcode":"04100",
    "sg:province":"Aquitaine",
    "wof:name":"Eral Irrigation S.a.",
    "wof:placetype":"venue"
},
  "geometry": {"coordinates":[5.784205,43.831474],"type":"Point"}
}