{
  "type": "Feature",
  "properties": {
    "addr:full":"885 Av Du Dr Julien Lefebvre 06270 Villeneuve Loubet Vill\u00e9 Alsace 67220",
    "addr:postcode":"06270;67220",
    "addr:street":"885 Av Du Dr Julien Lefebvre",
    "iso:country":"FR",
    "sg:address":"885 Av Du Dr Julien Lefebvre 06270 Villeneuve Loubet",
    "sg:city":"Vill\u00e9",
    "sg:classifiers":[
        {
            "category":"Shopping",
            "subcategory":"Computers & Home Electronics",
            "type":"Retail Goods"
        }
    ],
    "sg:phone":"+33 4 92 02 82 00",
    "sg:postcode":"67220",
    "sg:province":"Alsace",
    "sg:tags":[
        "equipment",
        "electrical",
        "component",
        "electric",
        "electronic"
    ],
    "wof:name":"Stel France",
    "wof:placetype":"venue"
},
  "geometry": {"coordinates":[7.129025,43.62978],"type":"Point"}
}