{
  "type": "Feature",
  "properties": {
    "iso:country":"FR",
    "sg:address":"19 Avenue Aristide Briand 91550 Paray Vieille Poste",
    "sg:classifiers":[
        {
            "category":"Wholesale",
            "subcategory":"Machinery & Supplies",
            "type":"Manufacturing & Wholesale Goods"
        }
    ],
    "sg:phone":"+33 1 60 48 33 22",
    "sg:province":"Ile de France",
    "sg:tags":[
        "equipment",
        "optical",
        "precision",
        "instrument"
    ],
    "wof:name":"Orly Graphic",
    "wof:placetype":"venue"
},
  "geometry": {"coordinates":[2.367672,48.709167],"type":"Point"}
}