{
  "type": "Feature",
  "properties": {
    "addr:full":"20, Bd du G\u00e9n\u00e9ral Leclerc, 59100 Roubaix Nord Pas-de-Calais",
    "addr:housenumber":"20",
    "addr:postcode":"59100",
    "addr:street":"Bd Du Ge\u0301Ne\u0301Ral Leclerc",
    "iso:country":"FR",
    "sg:address":"20, Bd du G\u00e9n\u00e9ral Leclerc, 59100 Roubaix",
    "sg:orig_category":"Non-Classified Establishments",
    "sg:phone":"+33 3 20 80 48 49",
    "sg:province":"Nord Pas-de-Calais",
    "wof:name":"Mass\u00e9 Bernard",
    "wof:placetype":"venue"
},
  "geometry": {"coordinates":[3.176385,50.688072],"type":"Point"}
}