{
  "type": "Feature",
  "properties": {
    "iso:country":"FR",
    "sg:address":"71 Bis R Du Cardinal Lemoine 75005 Paris",
    "sg:classifiers":[
        {
            "category":"Professional",
            "subcategory":"Advertising",
            "type":"Services"
        }
    ],
    "sg:phone":"+33 1 56 81 15 00",
    "sg:postcode":"75005",
    "sg:province":"Ile de France",
    "sg:tags":[
        "marketing",
        "medium",
        "communication"
    ],
    "wof:name":"Ruder Finn France Sarl",
    "wof:placetype":"venue"
},
  "geometry": {"coordinates":[2.350421,48.845482],"type":"Point"}
}