{
  "type": "Feature",
  "properties": {
    "addr:full":"ZA Soorts Soorts Hossegor Aquitaine 40150",
    "addr:postcode":"40150",
    "addr:street":"Za Soorts Soorts Hossegor",
    "iso:country":"FR",
    "sg:address":"ZA Soorts",
    "sg:city":"Soorts Hossegor",
    "sg:orig_category":"Unclassifiable Establishments",
    "sg:phone":"+33 5 58 41 98 98",
    "sg:postcode":"40150",
    "sg:province":"Aquitaine",
    "wof:name":"Arnette Europe S.a.r.l.",
    "wof:placetype":"venue"
},
  "geometry": {"coordinates":[-1.428519,43.658497],"type":"Point"}
}