{
  "type": "Feature",
  "properties": {
    "iso:country":"FR",
    "sg:address":"32 Rue Florion 51800 Ste Menehould",
    "sg:classifiers":[
        {
            "category":"Wholesale",
            "subcategory":"Farm Supplies",
            "type":"Manufacturing & Wholesale Goods"
        }
    ],
    "sg:phone":"+33 3 26 60 50 50",
    "sg:postcode":"51800",
    "sg:province":"Champagne",
    "sg:tags":[
        "-",
        "machine",
        "equipment",
        "engineering",
        "machinery",
        "mechanical",
        "agriculture"
    ],
    "wof:name":"Ets Rochas",
    "wof:placetype":"venue"
},
  "geometry": {"coordinates":[4.890755,49.089867],"type":"Point"}
}