{
  "type": "Feature",
  "properties": {
    "iso:country":"FR",
    "sg:address":"2, Rue de Queyzans, 33340 Saint Yzans de M\u00e9doc",
    "sg:city":"B\u00e9gadan",
    "sg:orig_category":"Non-Classified Establishments",
    "sg:phone":"+33 5 56 09 05 07",
    "sg:postcode":"33340",
    "sg:province":"Aquitaine",
    "wof:name":"Souslikoff Et Compagnie S.a.r.l.",
    "wof:placetype":"venue"
},
  "geometry": {"coordinates":[-0.818369,45.335064],"type":"Point"}
}