{
  "type": "Feature",
  "properties": {
    "iso:country":"FR",
    "sg:address":"Pa De Laurade 13103 St Etienne Du Gres",
    "sg:classifiers":[
        {
            "category":"Professional",
            "type":"Services"
        }
    ],
    "sg:phone":"+33 4 90 18 70 00",
    "sg:province":"Midi Pyr\u00e9n\u00e9es",
    "sg:tags":[
        "transport",
        "road"
    ],
    "wof:name":"Appia Equipements De La Route Snc",
    "wof:placetype":"venue"
},
  "geometry": {"coordinates":[4.715759,43.789791],"type":"Point"}
}