{
  "type": "Feature",
  "properties": {
    "addr:full":"60 B, Rue du Mar\u00e9chal Leclerc, 28110 Luc\u00e9 Luc\u00e9 Centre 28110",
    "addr:housenumber":"60 b",
    "addr:postcode":"28110;28110",
    "addr:street":"Rue Du Mare\u0301Chal Leclerc",
    "iso:country":"FR",
    "sg:address":"60 B, Rue du Mar\u00e9chal Leclerc, 28110 Luc\u00e9",
    "sg:city":"Luc\u00e9",
    "sg:orig_category":"Unclassifiable Establishments",
    "sg:phone":"+33 2 37 30 97 72",
    "sg:postcode":"28110",
    "sg:province":"Centre",
    "wof:name":"Manuli Sonatra S.a.",
    "wof:placetype":"venue"
},
  "geometry": {"coordinates":[1.457688,48.426762],"type":"Point"}
}