{
  "type": "Feature",
  "properties": {
    "addr:full":"Av Ernest Cristal 63000 Clermont Ferrand Clermont-Ferrand Auvergne 63000",
    "addr:postcode":"63000;63000",
    "addr:street":"Av Ernest Cristal",
    "iso:country":"FR",
    "sg:address":"Av Ernest Cristal 63000 Clermont Ferrand",
    "sg:city":"Clermont-Ferrand",
    "sg:classifiers":[
        {
            "category":"Building & Trades",
            "subcategory":"Construction",
            "type":"Services"
        }
    ],
    "sg:phone":"+33 4 73 26 45 28",
    "sg:postcode":"63000",
    "sg:province":"Auvergne",
    "sg:tags":[
        "work",
        "public"
    ],
    "wof:name":"Les Liants D'auvergne",
    "wof:placetype":"venue"
},
  "geometry": {"coordinates":[3.13692,45.760204],"type":"Point"}
}