{
  "type": "Feature",
  "properties": {
    "addr:full":"3, Rue de la Hille - ZA, 31830 Plaisance du Touch Midi Pyr\u00e9n\u00e9es 31830",
    "addr:housenumber":"3",
    "addr:postcode":"31830;31830",
    "addr:street":"Rue De La Hille Za",
    "iso:country":"FR",
    "sg:address":"3, Rue de la Hille - ZA, 31830 Plaisance du Touch",
    "sg:orig_category":"Non-Classified Establishments",
    "sg:phone":"+33 5 61 86 42 67",
    "sg:postcode":"31830",
    "sg:province":"Midi Pyr\u00e9n\u00e9es",
    "wof:name":"Astec Sud Ouest S.a.r.l.",
    "wof:placetype":"venue"
},
  "geometry": {"coordinates":[1.293855,43.564415],"type":"Point"}
}