{
  "type": "Feature",
  "properties": {
    "addr:full":"21 place Massenet 42000 ST ETIENNE Rhone-Alpes",
    "addr:housenumber":"21",
    "addr:postcode":"42000",
    "addr:street":"Place Massenet",
    "iso:country":"FR",
    "sg:address":"21 place Massenet 42000 ST ETIENNE",
    "sg:classifiers":[
        {
            "category":"Shopping",
            "subcategory":"Stationery & Office Supplies",
            "type":"Retail Goods"
        }
    ],
    "sg:phone":"+33 4 77 92 05 95",
    "sg:province":"Rhone-Alpes",
    "sg:tags":[
        "packaging"
    ],
    "wof:name":"Forez Emballage Sa",
    "wof:placetype":"venue"
},
  "geometry": {"coordinates":[4.378319,45.465965],"type":"Point"}
}