{
  "type": "Feature",
  "properties": {
    "iso:country":"FR",
    "sg:address":"B.P. 14, 47130 Port Sainte Marie C\u00e9dex^^RN 113, 47130 Port Sainte Marie",
    "sg:city":"Bazens",
    "sg:orig_category":"Non-Classified Establishments",
    "sg:phone":"+33 5 53 67 47 96",
    "sg:postcode":"47130",
    "sg:province":"Aquitaine",
    "wof:name":"Etablissements Faget Et Fils S.a.r.l.",
    "wof:placetype":"venue"
},
  "geometry": {"coordinates":[0.438146,44.203495],"type":"Point"}
}