{
  "type": "Feature",
  "properties": {
    "addr:full":"28, Rue Mal de Lattre de Tassigny, 67300 Schiltigheim Schiltigheim Alsace 67300",
    "addr:housenumber":"28",
    "addr:postcode":"67300;67300",
    "addr:street":"Rue Mal De Lattre De Tassigny",
    "iso:country":"FR",
    "sg:address":"28, Rue Mal de Lattre de Tassigny, 67300 Schiltigheim",
    "sg:city":"Schiltigheim",
    "sg:orig_category":"Unclassifiable Establishments",
    "sg:phone":"+33 3 88 81 14 16",
    "sg:postcode":"67300",
    "sg:province":"Alsace",
    "wof:name":"Neutre S.a.r.l.",
    "wof:placetype":"venue"
},
  "geometry": {"coordinates":[7.748565,48.605949],"type":"Point"}
}