{
  "type": "Feature",
  "properties": {
    "addr:full":"route de la Muyre 39210 DOMBLANS Franche Comt\u00e9 39210",
    "addr:postcode":"39210;39210",
    "addr:street":"Route De La Muyre;Franche Comte\u0301",
    "iso:country":"FR",
    "sg:address":"route de la Muyre 39210 DOMBLANS",
    "sg:orig_category":"Aluminium Packings",
    "sg:phone":"+33 3 84 44 61 04",
    "sg:postcode":"39210",
    "sg:province":"Franche Comt\u00e9",
    "wof:name":"St\u00e9 Baudry S.a.r.l.",
    "wof:placetype":"venue"
},
  "geometry": {"coordinates":[5.587205,46.762295],"type":"Point"}
}