{
  "type": "Feature",
  "properties": {
    "addr:full":"Av De L'Europe Zi De Cambrai 59400 Cambrai Nord Pas-de-Calais 59400",
    "addr:postcode":"59400;59400",
    "addr:street":"Av De L'Europe Zi De Cambrai",
    "iso:country":"FR",
    "sg:address":"Av De L'Europe Zi De Cambrai 59400 Cambrai",
    "sg:classifiers":[
        {
            "category":"Manufacturing",
            "subcategory":"Textiles",
            "type":"Manufacturing & Wholesale Goods"
        }
    ],
    "sg:phone":"+33 3 27 81 38 00",
    "sg:postcode":"59400",
    "sg:province":"Nord Pas-de-Calais",
    "sg:tags":[
        "linen",
        "clothing",
        "fabric"
    ],
    "wof:name":"Teinturerie Blanchisserie Nouvelles Sa",
    "wof:placetype":"venue"
},
  "geometry": {"coordinates":[3.22325,50.1576],"type":"Point"}
}