{
  "type": "Feature",
  "properties": {
    "iso:country":"FR",
    "sg:address":"19, Rue des Tourelles, 27640 Villiers en D\u00e9soeuvre",
    "sg:orig_category":"Unclassifiable Establishments",
    "sg:phone":"+33 2 32 26 16 83",
    "sg:province":"Haute Normandie",
    "wof:name":"Routex S.a.r.l.",
    "wof:placetype":"venue"
},
  "geometry": {"coordinates":[1.48753,48.951591],"type":"Point"}
}