{
  "type": "Feature",
  "properties": {
    "iso:country":"FR",
    "sg:address":"714 rue Georges Sand 42351 LA TALAUDIERE",
    "sg:classifiers":[
        {
            "category":"Building & Trades",
            "subcategory":"Construction",
            "type":"Services"
        }
    ],
    "sg:phone":"+33 4 77 34 30 20",
    "sg:province":"Rhone-Alpes",
    "sg:tags":[
        "profile"
    ],
    "wof:name":"Profimo Sa",
    "wof:placetype":"venue"
},
  "geometry": {"coordinates":[4.43358,45.471558],"type":"Point"}
}