{
  "type": "Feature",
  "properties": {
    "addr:full":"37, Bd Henri Martin, 02100 Saint Quentin Picardie",
    "addr:housenumber":"37",
    "addr:postcode":"02100",
    "addr:street":"Bd Henri Martin",
    "iso:country":"FR",
    "sg:address":"37, Bd Henri Martin, 02100 Saint Quentin",
    "sg:orig_category":"Unclassifiable Establishments",
    "sg:phone":"+33 3 23 62 95 30",
    "sg:province":"Picardie",
    "wof:name":"Jean Lef\u00e8vre - Picardie S.n.c.",
    "wof:placetype":"venue"
},
  "geometry": {"coordinates":[3.279085,49.845135],"type":"Point"}
}