{
  "type": "Feature",
  "properties": {
    "addr:full":"ZA les Alleux Dinan Bretagne 22100",
    "addr:postcode":"22100",
    "addr:street":"Za Les Alleux Dinan Bretagne",
    "iso:country":"FR",
    "sg:address":"ZA les Alleux",
    "sg:city":"Dinan",
    "sg:orig_category":"Unclassifiable Establishments",
    "sg:phone":"+33 2 96 85 82 20",
    "sg:postcode":"22100",
    "sg:province":"Bretagne",
    "wof:name":"Cordon Electronique S.a.r.l.",
    "wof:placetype":"venue"
},
  "geometry": {"coordinates":[-2.047959,48.454266],"type":"Point"}
}