{
  "type": "Feature",
  "properties": {
    "iso:country":"FR",
    "sg:address":"2, Rue Jean Lender, 56100 Lorient",
    "sg:city":"Lorient",
    "sg:orig_category":"Non-Classified Establishments",
    "sg:phone":"+33 2 97 37 77 77",
    "sg:postcode":"56100",
    "sg:province":"Bretagne",
    "wof:name":"Courtes Et Associ\u00e9s S.a.r.l.",
    "wof:placetype":"venue"
},
  "geometry": {"coordinates":[-3.367469,47.736694],"type":"Point"}
}