{
  "type": "Feature",
  "properties": {
    "iso:country":"FR",
    "sg:address":"28/30, Av. Galli\u00e9ni, 94100 Saint Maur des Fosses",
    "sg:orig_category":"Unclassifiable Establishments",
    "sg:phone":"+33 1 55 12 35 50",
    "sg:province":"Ile de France",
    "wof:name":"Jostra France S.a.r.l.",
    "wof:placetype":"venue"
},
  "geometry": {"coordinates":[2.475193,48.808369],"type":"Point"}
}