{
  "type": "Feature",
  "properties": {
    "addr:full":"23 Rue Claude Veyron 69361 Lyon Rhone-Alpes",
    "addr:housenumber":"23",
    "addr:postcode":"69361",
    "addr:street":"Rue Claude Veyron",
    "iso:country":"FR",
    "sg:address":"23 Rue Claude Veyron 69361 Lyon",
    "sg:classifiers":[
        {
            "category":"Professional",
            "subcategory":"Business Services",
            "type":"Services"
        }
    ],
    "sg:phone":"+33 4 72 71 50 00",
    "sg:province":"Rhone-Alpes",
    "sg:tags":[
        "training",
        "advice"
    ],
    "wof:name":"Lycee Polyvalent Hector Guimard",
    "wof:placetype":"venue"
},
  "geometry": {"coordinates":[4.83936,45.732059],"type":"Point"}
}