{
  "type": "Feature",
  "properties": {
    "iso:country":"FR",
    "sg:address":"B.P. 23, 67401 Illkirch C\u00e9dex^^156, Rte de Lyon, 67400 Illkirch Graffenstaden",
    "sg:city":"Geispolsheim",
    "sg:orig_category":"Non-Classified Establishments",
    "sg:phone":"+33 3 88 66 97 60",
    "sg:postcode":"67400",
    "sg:province":"Alsace",
    "wof:name":"Meto Graffenstaden S.a.",
    "wof:placetype":"venue"
},
  "geometry": {"coordinates":[7.711838,48.528809],"type":"Point"}
}