{
  "type": "Feature",
  "properties": {
    "addr:full":"1112 Bl Fernand Darchicourt 62253 Henin Beaumont Auvergne",
    "addr:housenumber":"1112 bl fernand",
    "addr:postcode":"62253",
    "addr:street":"Darchicourt",
    "iso:country":"FR",
    "sg:address":"1112 Bl Fernand Darchicourt 62253 Henin Beaumont",
    "sg:classifiers":[
        {
            "category":"Shopping",
            "subcategory":"Department Store",
            "type":"Retail Goods"
        }
    ],
    "sg:phone":"+33 3 21 08 74 74",
    "sg:province":"Auvergne",
    "sg:tags":[
        "shop",
        "equipment",
        "bakery"
    ],
    "wof:name":"Electrolux Baking Sa",
    "wof:placetype":"venue"
},
  "geometry": {"coordinates":[3.341874,45.313515],"type":"Point"}
}