{
  "type": "Feature",
  "properties": {
    "addr:full":"Rue Des Eglantines 74150 Rumilly Rhone-Alpes",
    "addr:postcode":"74150",
    "addr:street":"Rue Des Eglantines",
    "iso:country":"FR",
    "sg:address":"Rue Des Eglantines 74150 Rumilly",
    "sg:classifiers":[
        {
            "category":"Wholesale",
            "subcategory":"Machinery & Supplies",
            "type":"Manufacturing & Wholesale Goods"
        }
    ],
    "sg:phone":"+33 4 50 01 30 70",
    "sg:province":"Rhone-Alpes",
    "sg:tags":[
        "food",
        "processing",
        "-",
        "machine",
        "equipment",
        "engineering",
        "mechanical"
    ],
    "wof:name":"Fromagerie Mugnier",
    "wof:placetype":"venue"
},
  "geometry": {"coordinates":[5.942465,45.856396],"type":"Point"}
}