{
  "type": "Feature",
  "properties": {
    "iso:country":"FR",
    "sg:address":"B.P. 02, 59531 Neuville en Ferrain C\u00e9dex^^Rue de Reckem - ZI, 59960 Neuville en Ferrain",
    "sg:orig_category":"Non-Classified Establishments",
    "sg:phone":"+33 3 20 46 57 19",
    "sg:postcode":"59960",
    "sg:province":"Nord Pas-de-Calais",
    "wof:name":"Brustlein S.a.",
    "wof:placetype":"venue"
},
  "geometry": {"coordinates":[3.15239,50.750355],"type":"Point"}
}