{
  "type": "Feature",
  "properties": {
    "addr:full":"20 bis, Rue Gubernatis, 06000 Nice Provence-Alpes-C\u00f4te d'Azur",
    "addr:housenumber":"20 bis",
    "addr:postcode":"06000",
    "addr:street":"Rue Gubernatis",
    "iso:country":"FR",
    "sg:address":"20 bis, Rue Gubernatis, 06000 Nice",
    "sg:orig_category":"Unclassifiable Establishments",
    "sg:phone":"+33 4 93 62 28 28",
    "sg:province":"Provence-Alpes-C\u00f4te d'Azur",
    "wof:name":"Ollivier S.a.",
    "wof:placetype":"venue"
},
  "geometry": {"coordinates":[7.272481,43.700912],"type":"Point"}
}