{
  "type": "Feature",
  "properties": {
    "iso:country":"FR",
    "sg:address":"avenue de Magudas 33185 Le Haillan",
    "sg:city":"Le Haillan",
    "sg:orig_category":"Film Shrinking Devices And Equipment",
    "sg:phone":"+33 5 56 34 35 18",
    "sg:postcode":"33185",
    "sg:province":"Aquitaine",
    "wof:name":"Ripack Sefmat Sa",
    "wof:placetype":"venue"
},
  "geometry": {"coordinates":[-0.695369,44.861324],"type":"Point"}
}