{
  "type": "Feature",
  "properties": {
    "iso:country":"FR",
    "sg:address":"82, Rue Mandron, 33000 Bordeaux",
    "sg:city":"Bordeaux",
    "sg:orig_category":"Unclassifiable Establishments",
    "sg:phone":"+33 5 57 87 02 56",
    "sg:postcode":"33000",
    "sg:province":"Aquitaine",
    "wof:name":"Seignouret Fr\u00e8res S.a.",
    "wof:placetype":"venue"
},
  "geometry": {"coordinates":[-0.580823,44.85342],"type":"Point"}
}