{
  "type": "Feature",
  "properties": {
    "addr:full":"B.P. 27, 29280 Locmaria Plouzan\u00e9^^31, Rte de Plouzan\u00e9, 29280 Locmaria Plouzan\u00e9 Plouzan\u00e9 Bretagne 29280",
    "addr:postcode":"29280;29280;29280",
    "addr:street":"B.P. 27;Rte De Plouzane\u0301",
    "iso:country":"FR",
    "sg:address":"B.P. 27, 29280 Locmaria Plouzan\u00e9^^31, Rte de Plouzan\u00e9, 29280 Locmaria Plouzan\u00e9",
    "sg:city":"Plouzan\u00e9",
    "sg:orig_category":"Non-Classified Establishments",
    "sg:phone":"+33 2 98 48 40 90",
    "sg:postcode":"29280",
    "sg:province":"Bretagne",
    "wof:name":"Sobrefer S.a.",
    "wof:placetype":"venue"
},
  "geometry": {"coordinates":[-4.662229,48.354164],"type":"Point"}
}