{
  "type": "Feature",
  "properties": {
    "iso:country":"FR",
    "sg:address":"18 avenue du Quebec 91140 Villebon sur Yvette",
    "sg:classifiers":[
        {
            "category":"Wholesale",
            "subcategory":"Medical Equipment & Supplies",
            "type":"Manufacturing & Wholesale Goods"
        }
    ],
    "sg:phone":"+33 1 64 46 14 84",
    "sg:province":"Ile de France",
    "sg:tags":[
        "machine",
        "technology",
        "special"
    ],
    "wof:name":"Corryl Sa",
    "wof:placetype":"venue"
},
  "geometry": {"coordinates":[2.215381,48.689766],"type":"Point"}
}