{
  "type": "Feature",
  "properties": {
    "iso:country":"FR",
    "sg:address":"B.P. 54, 57365 Ennery^^Rue Andr\u00e9 Citro\u00ebn, 57365 Ennery",
    "sg:orig_category":"Non-Classified Establishments",
    "sg:phone":"+33 3 87 73 60 50",
    "sg:postcode":"57365",
    "sg:province":"Lorraine",
    "wof:name":"C.f.c. S.a.s. - Centrale Fran\u00e7aise De Commercialisation",
    "wof:placetype":"venue"
},
  "geometry": {"coordinates":[6.221613,49.22702],"type":"Point"}
}