{
  "type": "Feature",
  "properties": {
    "iso:country":"FR",
    "sg:address":"157, Av Ferber, 62250 Marquise",
    "sg:orig_category":"Unclassifiable Establishments",
    "sg:phone":"+33 3 21 87 32 33",
    "sg:province":"Nord Pas-de-Calais",
    "wof:name":"Speed Transport",
    "wof:placetype":"venue"
},
  "geometry": {"coordinates":[1.704122,50.819298],"type":"Point"}
}