{
  "type": "Feature",
  "properties": {
    "addr:full":"Route de Schopperten 67260 Keskastel Schopperten Alsace 67260",
    "addr:postcode":"67260;67260",
    "addr:street":"Route De Schopperten;Schopperten",
    "iso:country":"FR",
    "sg:address":"Route de Schopperten 67260 Keskastel",
    "sg:city":"Schopperten",
    "sg:classifiers":[
        {
            "category":"Home & Garden",
            "subcategory":"Building Materials",
            "type":"Retail Goods"
        }
    ],
    "sg:phone":"+33 3 88 00 13 02",
    "sg:postcode":"67260",
    "sg:province":"Alsace",
    "sg:tags":[
        "steel",
        "shelf",
        "plate"
    ],
    "wof:name":"Wilhelm Sa",
    "wof:placetype":"venue"
},
  "geometry": {"coordinates":[7.048,48.96172],"type":"Point"}
}