{
  "type": "Feature",
  "properties": {
    "iso:country":"FR",
    "sg:address":"Rte de Courcemont - ZI",
    "sg:city":"Bonn\u00e9table",
    "sg:orig_category":"Non-Classified Establishments",
    "sg:phone":"+33 2 43 29 33 40",
    "sg:postcode":"72110",
    "sg:province":"Pays de Loire",
    "wof:name":"Freix S.a.r.l.",
    "wof:placetype":"venue"
},
  "geometry": {"coordinates":[0.432377,48.123772],"type":"Point"}
}