{
  "type": "Feature",
  "properties": {
    "iso:country":"FR",
    "sg:address":"13 Rue De Nesles 75006 Paris",
    "sg:classifiers":[
        {
            "category":"Professional",
            "subcategory":"Printing & Photocopies",
            "type":"Services"
        }
    ],
    "sg:phone":"+33 1 44 41 97 20",
    "sg:province":"Ile de France",
    "sg:tags":[
        "publishing"
    ],
    "wof:name":"Agence Pour Le Developpement De La Librairie Sarl (adl)",
    "wof:placetype":"venue"
},
  "geometry": {"coordinates":[2.338744,48.855225],"type":"Point"}
}