{
  "type": "Feature",
  "properties": {
    "iso:country":"FR",
    "sg:address":"B.P. 11, 72380 Sainte Jamme sur Sarthe C\u00e9dex^^ZI Antoign\u00e9, 72380 Sainte Jamme sur Sarthe",
    "sg:orig_category":"Non-Classified Establishments",
    "sg:phone":"+33 2 43 27 48 20",
    "sg:postcode":"72380",
    "sg:province":"Pays de Loire",
    "wof:name":"Etablissement Le Fratique S.a.r.l.",
    "wof:placetype":"venue"
},
  "geometry": {"coordinates":[0.216875,48.110428],"type":"Point"}
}