{
  "type": "Feature",
  "properties": {
    "addr:full":"5, Rue Gay Lussac - ZI, 94430 Chennevi\u00e8res sur Marne Ile de France",
    "addr:housenumber":"5",
    "addr:postcode":"94430",
    "addr:street":"Rue Gay Lussac Zi",
    "iso:country":"FR",
    "sg:address":"5, Rue Gay Lussac - ZI, 94430 Chennevi\u00e8res sur Marne",
    "sg:orig_category":"Unclassifiable Establishments",
    "sg:phone":"+33 1 49 62 24 24",
    "sg:province":"Ile de France",
    "wof:name":"La Corpo S.a.",
    "wof:placetype":"venue"
},
  "geometry": {"coordinates":[2.53196,48.796413],"type":"Point"}
}