{
  "type": "Feature",
  "properties": {
    "iso:country":"FR",
    "sg:address":"9, Av. Michelet, 93400 Saint Ouen",
    "sg:orig_category":"Unclassifiable Establishments",
    "sg:phone":"+33 1 49 48 87 40",
    "sg:province":"Ile de France",
    "wof:name":"La Garde De Nuit S.a.",
    "wof:placetype":"venue"
},
  "geometry": {"coordinates":[2.344437,48.913071],"type":"Point"}
}