{
  "type": "Feature",
  "properties": {
    "addr:full":"147, Bd Hosmann - Tour Franklin, 75379 Paris C\u00e9dex 08 \u00cele-de-France",
    "addr:housenumber":"147",
    "addr:postcode":"75379",
    "addr:street":"Bd Hosmann Tour",
    "iso:country":"FR",
    "sg:address":"147, Bd Hosmann - Tour Franklin, 75379 Paris C\u00e9dex 08",
    "sg:orig_category":"Non-Classified Establishments",
    "sg:phone":"+33 1 58 56 58 56",
    "sg:province":"\u00cele-de-France",
    "wof:name":"Key Men S.a.r.l.",
    "wof:placetype":"venue"
},
  "geometry": {"coordinates":[2.286585,48.862133],"type":"Point"}
}