{
  "type": "Feature",
  "properties": {
    "addr:full":"19, Rue Albert Einstein, 93591 Le Blanc Mesnil C\u00e9dex \u00cele-de-France",
    "addr:housenumber":"19",
    "addr:postcode":"93591",
    "addr:street":"Rue Albert Einstein;Ce\u0301Dex",
    "iso:country":"FR",
    "sg:address":"19, Rue Albert Einstein, 93591 Le Blanc Mesnil C\u00e9dex",
    "sg:orig_category":"Non-Classified Establishments",
    "sg:phone":"+33 1 48 65 15 69",
    "sg:province":"\u00cele-de-France",
    "wof:name":"Ogl Agence Sob S.a.",
    "wof:placetype":"venue"
},
  "geometry": {"coordinates":[2.47481,48.942562],"type":"Point"}
}