{
  "type": "Feature",
  "properties": {
    "addr:full":"49/51 av Vladimir Ilitch L\u00e9nine 94110 Arcueil Ile de France",
    "addr:housenumber":"49 / 51",
    "addr:postcode":"94110;ile",
    "addr:street":"Av Vladimir Ilitch Le\u0301Nine",
    "iso:country":"FR",
    "sg:address":"49/51 av Vladimir Ilitch L\u00e9nine 94110 Arcueil",
    "sg:classifiers":[
        {
            "category":"Building & Trades",
            "subcategory":"Construction",
            "type":"Services"
        }
    ],
    "sg:phone":"+33 1 46 55 20 20",
    "sg:province":"Ile de France",
    "sg:tags":[
        "steel"
    ],
    "wof:name":"Ets Aubart S.a",
    "wof:placetype":"venue"
},
  "geometry": {"coordinates":[2.33076,48.811638],"type":"Point"}
}