{
  "type": "Feature",
  "properties": {
    "addr:full":"105 route d'Orl\u00e9ans 45600 Sully sur Loire Guilly Centre 45600",
    "addr:housenumber":"105;guilly",
    "addr:postcode":"45600;45600",
    "addr:street":"Route D'Orle \u0301Ans",
    "iso:country":"FR",
    "sg:address":"105 route d'Orl\u00e9ans 45600 Sully sur Loire",
    "sg:city":"Guilly",
    "sg:classifiers":[
        {
            "category":"Autos & Motor Vehicles",
            "subcategory":"Recreational Vehicle Sales",
            "type":"Retail Goods"
        }
    ],
    "sg:phone":"+33 2 38 29 87 22",
    "sg:postcode":"45600",
    "sg:province":"Centre",
    "sg:tags":[
        "special-purpose"
    ],
    "wof:name":"Meritor Light Vehicle Systems France Sarl",
    "wof:placetype":"venue"
},
  "geometry": {"coordinates":[2.370771,47.772335],"type":"Point"}
}