{
  "type": "Feature",
  "properties": {
    "iso:country":"FR",
    "sg:address":"route de Munchhausen 67470 SELTZ",
    "sg:city":"Seltz",
    "sg:classifiers":[
        {
            "category":"Home & Garden",
            "subcategory":"Carpets & Floor Coverings",
            "type":"Retail Goods"
        }
    ],
    "sg:phone":"+33 3 88 86 13 21",
    "sg:postcode":"67470",
    "sg:province":"Alsace",
    "sg:tags":[
        "industrial",
        "flooring"
    ],
    "wof:name":"Geholit S.a.r.l.",
    "wof:placetype":"venue"
},
  "geometry": {"coordinates":[8.11165,48.903198],"type":"Point"}
}