{
  "type": "Feature",
  "properties": {
    "addr:full":"20 ter, Rue Schnapper, 78100 Saint Germain en Laye Ile de France 78100",
    "addr:housenumber":"20 ter",
    "addr:postcode":"78100;78100",
    "addr:street":"Rue Schnapper",
    "iso:country":"FR",
    "sg:address":"20 ter, Rue Schnapper, 78100 Saint Germain en Laye",
    "sg:orig_category":"Non-Classified Establishments",
    "sg:phone":"+33 1 30 61 59 04",
    "sg:postcode":"78100",
    "sg:province":"Ile de France",
    "wof:name":"Auxipap S.a.",
    "wof:placetype":"venue"
},
  "geometry": {"coordinates":[2.089719,48.888618],"type":"Point"}
}