{
  "type": "Feature",
  "properties": {
    "addr:full":"84 Rte Viran 74371 Pringy Franche Comt\u00e9",
    "addr:housenumber":"84",
    "addr:postcode":"74371",
    "addr:street":"Rte Viran;Franche Comte\u0301",
    "iso:country":"FR",
    "sg:address":"84 Rte Viran 74371 Pringy",
    "sg:classifiers":[
        {
            "category":"Professional",
            "subcategory":"Computer Services",
            "type":"Services"
        }
    ],
    "sg:phone":"+33 4 50 27 21 52",
    "sg:province":"Franche Comt\u00e9",
    "sg:tags":[
        "information",
        "technology",
        "software"
    ],
    "wof:name":"Rsai",
    "wof:placetype":"venue"
},
  "geometry": {"coordinates":[6.114249,45.95237],"type":"Point"}
}