{
  "type": "Feature",
  "properties": {
    "addr:full":"B.P. 99, 84203 Carpentras C\u00e9dex^^121, Bd des Boettes, 84200 Carpentras Aquitaine",
    "addr:postcode":"84203;ce\u0301dex^^121;84200",
    "addr:street":"B.P. 99;Bd Des Boettes",
    "iso:country":"FR",
    "sg:address":"B.P. 99, 84203 Carpentras C\u00e9dex^^121, Bd des Boettes, 84200 Carpentras",
    "sg:orig_category":"Non-Classified Establishments",
    "sg:phone":"+33 4 90 63 14 21",
    "sg:province":"Aquitaine",
    "wof:name":"Equi'd S.a.",
    "wof:placetype":"venue"
},
  "geometry": {"coordinates":[5.052614,44.055759],"type":"Point"}
}