{
  "type": "Feature",
  "properties": {
    "iso:country":"FR",
    "sg:address":"28 Rue Port 59380 Bergues",
    "sg:classifiers":[
        {
            "category":"Food Court",
            "type":"Food & Drink"
        }
    ],
    "sg:phone":"+33 3 28 65 99 25",
    "sg:postcode":"59380",
    "sg:province":"Nord Pas-de-Calais",
    "sg:tags":[
        "product",
        "related"
    ],
    "wof:name":"Meesemaecker Sarl",
    "wof:placetype":"venue"
},
  "geometry": {"coordinates":[2.429011,50.970989],"type":"Point"}
}