{
  "type": "Feature",
  "properties": {
    "addr:full":"B.P. 33, 91941 Courtaboeuf C\u00e9dex^^114, Av. de la Baltique, 91140 Villebon sur Yvette Ile de France 91140",
    "addr:postcode":"91941;91140;91140",
    "addr:street":"B.P. 33;Av. De La Baltique",
    "iso:country":"FR",
    "sg:address":"B.P. 33, 91941 Courtaboeuf C\u00e9dex^^114, Av. de la Baltique, 91140 Villebon sur Yvette",
    "sg:orig_category":"Non-Classified Establishments",
    "sg:phone":"+33 1 69 86 50 00",
    "sg:postcode":"91140",
    "sg:province":"Ile de France",
    "wof:name":"Christian Bernard Diffusion",
    "wof:placetype":"venue"
},
  "geometry": {"coordinates":[2.227225,48.700069],"type":"Point"}
}