{
  "type": "Feature",
  "properties": {
    "addr:full":"33710 Saint Ciers de Canesse Bayon-sur-Gironde Aquitaine 33710",
    "addr:postcode":"33710;33710",
    "addr:street":"Saint",
    "iso:country":"FR",
    "sg:address":"33710 Saint Ciers de Canesse",
    "sg:city":"Bayon-sur-Gironde",
    "sg:orig_category":"Non-Classified Establishments",
    "sg:phone":"+33 5 57 42 68 80",
    "sg:postcode":"33710",
    "sg:province":"Aquitaine",
    "wof:name":"Vignobles A. Faure S.c.e.a.",
    "wof:placetype":"venue"
},
  "geometry": {"coordinates":[-0.611621,45.086803],"type":"Point"}
}