{
  "type": "Feature",
  "properties": {
    "iso:country":"FR",
    "sg:address":"32 Rue Loire 44430 Le Loroux Bottereau",
    "sg:classifiers":[
        {
            "category":"Food Court",
            "type":"Food & Drink"
        }
    ],
    "sg:phone":"+33 2 40 03 76 00",
    "sg:postcode":"44430",
    "sg:province":"Pays de Loire",
    "sg:tags":[
        "product",
        "related"
    ],
    "wof:name":"Etablissements J Mace",
    "wof:placetype":"venue"
},
  "geometry": {"coordinates":[-1.351119,47.238586],"type":"Point"}
}