{
  "type": "Feature",
  "properties": {
    "addr:full":"47 G\u00e9n de Gaulle 76000 Rouen Haute Normandie 76000",
    "addr:housenumber":"47",
    "addr:postcode":"76000;76000",
    "addr:street":"Ge\u0301N De Gaulle;Haute Normandie",
    "iso:country":"FR",
    "sg:address":"47",
    "sg:city":"G\u00e9n de Gaulle 76000 Rouen",
    "sg:classifiers":[
        {
            "category":"Professional",
            "subcategory":"Advertising",
            "type":"Services"
        }
    ],
    "sg:phone":"+33 2 32 76 07 54",
    "sg:postcode":"76000",
    "sg:province":"Haute Normandie",
    "sg:tags":[
        "communication",
        "medium"
    ],
    "wof:name":"Norphi Pictures",
    "wof:placetype":"venue"
},
  "geometry": {"coordinates":[1.098584,49.444012],"type":"Point"}
}