{
  "type": "Feature",
  "properties": {
    "addr:full":"Rue Du Moulin De La Carolle 08460 SIGNY L ABBAYE Dommery Champagne 08460",
    "addr:postcode":"08460;08460",
    "addr:street":"Rue Du Moulin De La Carolle",
    "iso:country":"FR",
    "sg:address":"Rue Du Moulin De La Carolle 08460 SIGNY L ABBAYE",
    "sg:city":"Dommery",
    "sg:classifiers":[
        {
            "category":"Banks & Credit Unions",
            "subcategory":"Investment Brokerage",
            "type":"Services"
        }
    ],
    "sg:phone":"+33 3 24 52 81 03",
    "sg:postcode":"08460",
    "sg:province":"Champagne",
    "sg:tags":[
        "wooden",
        "packaging"
    ],
    "wof:name":"Etablissements Collet Fr\u00e8res Sa",
    "wof:placetype":"venue"
},
  "geometry": {"coordinates":[4.46708,49.718552],"type":"Point"}
}