{
  "type": "Feature",
  "properties": {
    "addr:full":"19, Rue des Liouds, 38150 Roussillon Rhone-Alpes 38150",
    "addr:housenumber":"19",
    "addr:postcode":"38150;38150",
    "addr:street":"Rue Des Liouds",
    "iso:country":"FR",
    "sg:address":"19, Rue des Liouds, 38150 Roussillon",
    "sg:orig_category":"Non-Classified Establishments",
    "sg:phone":"+33 4 78 70 38 05",
    "sg:postcode":"38150",
    "sg:province":"Rhone-Alpes",
    "wof:name":"Agrain S.a.",
    "wof:placetype":"venue"
},
  "geometry": {"coordinates":[4.820473,45.366348],"type":"Point"}
}