{
  "type": "Feature",
  "properties": {
    "addr:full":"Chemin du Pont Lozanne Rhone-Alpes 69380",
    "addr:postcode":"69380",
    "addr:street":"Chemin Du Pont;Rhone-Alpes",
    "iso:country":"FR",
    "sg:address":"Chemin du Pont",
    "sg:city":"Lozanne",
    "sg:orig_category":"Non-Classified Establishments",
    "sg:phone":"+33 4 72 54 12 72",
    "sg:postcode":"69380",
    "sg:province":"Rhone-Alpes",
    "wof:name":"Moulins Soufflet S.a.",
    "wof:placetype":"venue"
},
  "geometry": {"coordinates":[4.679609,45.855309],"type":"Point"}
}