{
  "type": "Feature",
  "properties": {
    "addr:full":"ZI Montgivray Centre 36400",
    "addr:postcode":"36400",
    "iso:country":"FR",
    "sg:address":"ZI",
    "sg:city":"Montgivray",
    "sg:orig_category":"Unclassifiable Establishments",
    "sg:phone":"+33 2 54 48 22 23",
    "sg:postcode":"36400",
    "sg:province":"Centre",
    "wof:name":"Performances Constructions M\u00e9talliques S.a.",
    "wof:placetype":"venue"
},
  "geometry": {"coordinates":[1.938385,46.541531],"type":"Point"}
}