{
  "type": "Feature",
  "properties": {
    "iso:country":"FR",
    "sg:address":"B.P. 74, 54021 Nancy C\u00e9dex^^20, Rue Isabey, 54000 Nancy",
    "sg:orig_category":"Non-Classified Establishments",
    "sg:phone":"+33 3 83 90 40 20",
    "sg:province":"Lorraine",
    "wof:name":"Viva S.a.",
    "wof:placetype":"venue"
},
  "geometry": {"coordinates":[6.183405,48.689548],"type":"Point"}
}