{
  "type": "Feature",
  "properties": {
    "iso:country":"FR",
    "sg:address":"4, All\u00e9e Aub\u00e9pines - Parc de Haye, 54840 Velaine en Haye",
    "sg:orig_category":"Unclassifiable Establishments",
    "sg:phone":"+33 3 83 23 32 40",
    "sg:province":"Lorraine",
    "wof:name":"Publi Cadeaux S.a.",
    "wof:placetype":"venue"
},
  "geometry": {"coordinates":[6.055453,48.696339],"type":"Point"}
}