{
  "type": "Feature",
  "properties": {
    "addr:full":"130 rue Fondaudege 33000 Bordeaux Bordeaux Aquitaine 33000",
    "addr:housenumber":"130",
    "addr:postcode":"33000;33000",
    "addr:street":"Rue Fondaudege",
    "iso:country":"FR",
    "sg:address":"130 rue Fondaudege 33000 Bordeaux",
    "sg:city":"Bordeaux",
    "sg:classifiers":[
        {
            "category":"Home & Garden",
            "subcategory":"Hardware",
            "type":"Retail Goods"
        }
    ],
    "sg:phone":"+33 5 56 01 85 85",
    "sg:postcode":"33000",
    "sg:province":"Aquitaine",
    "sg:tags":[
        "produced",
        "spirit",
        "specialities"
    ],
    "wof:name":"Marie Brizard Et Roger S.a.",
    "wof:placetype":"venue"
},
  "geometry": {"coordinates":[-0.583717,44.848946],"type":"Point"}
}