{
  "type": "Feature",
  "properties": {
    "iso:country":"FR",
    "sg:address":"Zi",
    "sg:city":"De La Mode 01580 Izernore",
    "sg:classifiers":[
        {
            "category":"Autos & Motor Vehicles",
            "subcategory":"Automobile Sales",
            "type":"Retail Goods"
        }
    ],
    "sg:phone":"+33 4 74 76 57 00",
    "sg:postcode":"01580",
    "sg:province":"Rhone-Alpes",
    "sg:tags":[
        "equipment",
        "motor-cars",
        "transport"
    ],
    "wof:name":"Neyr Plastiques Holding Sa",
    "wof:placetype":"venue"
},
  "geometry": {"coordinates":[5.55378,46.218575],"type":"Point"}
}