{
  "type": "Feature",
  "properties": {
    "addr:full":"2 Chemin Des Cloiseaux Montbard Bourgogne 21500",
    "addr:housenumber":"2",
    "addr:postcode":"21500",
    "addr:street":"Chemin Des Cloiseaux;Bourgogne",
    "iso:country":"FR",
    "sg:address":"2 Chemin Des Cloiseaux",
    "sg:city":"Montbard",
    "sg:classifiers":[
        {
            "category":"Professional",
            "subcategory":"Engineering",
            "type":"Services"
        }
    ],
    "sg:phone":"+33 3 80 92 19 75",
    "sg:postcode":"21500",
    "sg:province":"Bourgogne",
    "sg:tags":[
        "machine",
        "-",
        "mechanical"
    ],
    "wof:name":"Mecanique Generale De Montbard",
    "wof:placetype":"venue"
},
  "geometry": {"coordinates":[4.33617,47.621639],"type":"Point"}
}