{
  "type": "Feature",
  "properties": {
    "iso:country":"FR",
    "sg:address":"B.P. 1473, 25000 Besan\u00e7on^^3, Rue Berthelot - Zone Industrielle, 25000 Besan\u00e7on",
    "sg:orig_category":"Non-Classified Establishments",
    "sg:phone":"+33 3 81 50 17 42",
    "sg:province":"Franche Comt\u00e9",
    "wof:name":"Soci\u00e9t\u00e9 Nouvelle Miroiterie Comtoise S.a.r.l.",
    "wof:placetype":"venue"
},
  "geometry": {"coordinates":[6.025686,47.242317],"type":"Point"}
}